{
  "type": "Feature",
  "properties": {
    "iso:country":"IN",
    "ks:ks_name":"Bharahuan",
    "ks:ks_pop":1287,
    "ks:ks_type":"HABITATION",
    "name:eng_x_preferred":[
        "Bharahuan"
    ],
    "wof:name":"Bharahuan",
    "wof:placetype":"locality",
    "wof:population":1287
},
  "geometry": {"coordinates":[82.79371999999999,25.371324],"type":"Point"}
}