{
  "type": "Feature",
  "properties": {
    "gn:admin1_code":"13.0",
    "gn:admin2_code":"588.0",
    "gn:asciiname":"Peringana",
    "gn:country_code":"IN",
    "gn:dem":219,
    "gn:feature_class":"P",
    "gn:feature_code":"PPL",
    "gn:name":"Peringana",
    "gn:population":0,
    "gn:timezone":"Asia/Kolkata",
    "iso:country":"IN",
    "ks:ks_name":"Peringanam",
    "ks:ks_pop":1158,
    "ks:ks_type":"HABITATION",
    "name:eng_x_preferred":[
        "Peringanam"
    ],
    "name:eng_x_variant":[
        "Peringana"
    ],
    "wof:name":"Peringanam",
    "wof:placetype":"locality",
    "wof:population":1158
},
  "geometry": {"coordinates":[75.203565,12.454709],"type":"Point"}
}