{
  "type": "Feature",
  "properties": {
    "iso:country":"IN",
    "ks:ks_name":"Sanpurunapani",
    "ks:ks_pop":345,
    "ks:ks_type":"VILLAGE",
    "name:eng_x_preferred":[
        "Sanpurunapani"
    ],
    "wof:name":"Sanpurunapani",
    "wof:placetype":"locality",
    "wof:population":345
},
  "geometry": {"coordinates":[84.95196199999999,21.952259],"type":"Point"}
}