{
  "type": "Feature",
  "properties": {
    "iso:country":"IN",
    "ks:ks_name":"Navalagudi",
    "ks:ks_pop":62,
    "ks:ks_type":"HABITATION",
    "name:eng_x_preferred":[
        "Navalagudi"
    ],
    "wof:name":"Navalagudi",
    "wof:placetype":"locality",
    "wof:population":62
},
  "geometry": {"coordinates":[74.865943,15.016786],"type":"Point"}
}