{
  "type": "Feature",
  "properties": {
    "iso:country":"IN",
    "ks:ks_name":"Aardak Estate",
    "ks:ks_pop":59,
    "ks:ks_type":"HABITATION",
    "name:eng_x_preferred":[
        "Aardak Estate"
    ],
    "wof:name":"Aardak Estate",
    "wof:placetype":"locality",
    "wof:population":59
},
  "geometry": {"coordinates":[75.425721,13.551247],"type":"Point"}
}