{
  "type": "Feature",
  "properties": {
    "iso:country":"IN",
    "ks:ks_alt_nam":"MC Quarters",
    "ks:ks_name":"Mc Quarters",
    "ks:ks_pop":1814,
    "ks:ks_type":"HABITATION",
    "ks:ks_uagg_main":0,
    "name:eng_x_preferred":[
        "Mc Quarters"
    ],
    "wof:name":"Mc Quarters",
    "wof:placetype":"neighbourhood",
    "wof:population":1814
},
  "geometry": {"coordinates":[80.79687699999999,17.910874],"type":"Point"}
}