{
  "type": "Feature",
  "properties": {
    "iso:country":"IN",
    "ks:ks_name":"Oothupatti",
    "ks:ks_pop":137,
    "ks:ks_type":"HABITATION",
    "ks:ks_uagg_main":0,
    "name:eng_x_preferred":[
        "Oothupatti"
    ],
    "wof:name":"Oothupatti",
    "wof:placetype":"neighbourhood",
    "wof:population":137
},
  "geometry": {"coordinates":[78.12823899999999,10.486886],"type":"Point"}
}