{
  "type": "Feature",
  "properties": {
    "gn:admin1_code":"36",
    "gn:admin2_code":"173.0",
    "gn:asciiname":"Ganai Dih",
    "gn:country_code":"IN",
    "gn:dem":98,
    "gn:feature_class":"P",
    "gn:feature_code":"PPL",
    "gn:name":"Ganai D\u012bh",
    "gn:population":0,
    "gn:timezone":"Asia/Kolkata",
    "iso:country":"IN",
    "ks:ks_alt_nam":"Ganai D\u012bh",
    "ks:ks_name":"Ganai Dih",
    "ks:ks_type":"VILLAGE",
    "ks:ks_uagg_main":0,
    "name:eng_x_preferred":[
        "Ganai Dih"
    ],
    "name:eng_x_variant":[
        "Ganai D\u012bh"
    ],
    "wof:name":"Ganai Dih",
    "wof:placetype":"neighbourhood"
},
  "geometry": {"coordinates":[82.059223,25.920544],"type":"Point"}
}