{
  "type": "Feature",
  "properties": {
    "iso:country":"IN",
    "ks:ks_name":"Suliya",
    "ks:ks_pop":1509,
    "ks:ks_type":"VILLAGE",
    "name:eng_x_preferred":[
        "Suliya"
    ],
    "wof:name":"Suliya",
    "wof:placetype":"locality",
    "wof:population":1509
},
  "geometry": {"coordinates":[73.26608899999999,20.151934],"type":"Point"}
}