{
  "type": "Feature",
  "properties": {
    "iso:country":"IN",
    "ks:ks_name":"Khadarwa",
    "ks:ks_pop":618,
    "ks:ks_type":"HABITATION",
    "name:eng_x_preferred":[
        "Khadarwa"
    ],
    "wof:name":"Khadarwa",
    "wof:placetype":"locality",
    "wof:population":618
},
  "geometry": {"coordinates":[83.56683200000001,24.35082],"type":"Point"}
}