{
  "type": "Feature",
  "properties": {
    "gn:admin1_code":"36",
    "gn:admin2_code":"186.0",
    "gn:asciiname":"Bhikharipur",
    "gn:country_code":"IN",
    "gn:dem":81,
    "gn:feature_class":"P",
    "gn:feature_code":"PPL",
    "gn:name":"Bhikh\u0101ripur",
    "gn:population":0,
    "gn:timezone":"Asia/Kolkata",
    "iso:country":"IN",
    "ks:ks_alt_nam":"Bhikh\u0101ripur",
    "ks:ks_name":"Bhikharipur",
    "ks:ks_pop":653,
    "ks:ks_type":"VILLAGE",
    "name:eng_x_preferred":[
        "Bhikharipur"
    ],
    "name:eng_x_variant":[
        "Bhikh\u0101ripur"
    ],
    "wof:name":"Bhikharipur",
    "wof:placetype":"locality",
    "wof:population":653
},
  "geometry": {"coordinates":[83.022446,26.48772],"type":"Point"}
}