{
  "type": "Feature",
  "properties": {
    "iso:country":"IN",
    "ks:ks_name":"Babusajbahar",
    "ks:ks_pop":1179,
    "ks:ks_type":"VILLAGE",
    "name:eng_x_preferred":[
        "Babusajbahar"
    ],
    "wof:name":"Babusajbahar",
    "wof:placetype":"locality",
    "wof:population":1179
},
  "geometry": {"coordinates":[83.940245,22.402635],"type":"Point"}
}