{
  "type": "Feature",
  "properties": {
    "iso:country":"IN",
    "ks:ks_name":"Govari",
    "ks:ks_pop":154,
    "ks:ks_type":"VILLAGE",
    "name:eng_x_preferred":[
        "Govari"
    ],
    "wof:name":"Govari",
    "wof:placetype":"locality",
    "wof:population":154
},
  "geometry": {"coordinates":[82.105087,24.696619],"type":"Point"}
}