{
  "type": "Feature",
  "properties": {
    "gn:admin1_code":"34.0",
    "gn:admin2_code":"239.0",
    "gn:asciiname":"Haji Sarai",
    "gn:country_code":"IN",
    "gn:dem":74,
    "gn:feature_class":"P",
    "gn:feature_code":"PPL",
    "gn:name":"H\u0101ji Sarai",
    "gn:population":0,
    "gn:timezone":"Asia/Kolkata",
    "iso:country":"IN",
    "ks:ks_alt_nam":"H\u0101ji Sarai",
    "ks:ks_name":"Haji Sarai",
    "ks:ks_pop":849,
    "ks:ks_type":"VILLAGE",
    "ks:ks_uagg_main":0,
    "name:eng_x_preferred":[
        "Haji Sarai"
    ],
    "name:eng_x_variant":[
        "H\u0101ji Sarai"
    ],
    "wof:name":"Haji Sarai",
    "wof:placetype":"neighbourhood",
    "wof:population":849
},
  "geometry": {"coordinates":[85.07681700000001,25.154372],"type":"Point"}
}