{
  "type": "Feature",
  "properties": {
    "iso:country":"IN",
    "ks:ks_name":"Aminarchar",
    "ks:ks_pop":1755,
    "ks:ks_type":"HABITATION",
    "name:eng_x_preferred":[
        "Aminarchar"
    ],
    "wof:name":"Aminarchar",
    "wof:placetype":"locality",
    "wof:population":1755
},
  "geometry": {"coordinates":[89.946888,25.99658],"type":"Point"}
}