{
  "type": "Feature",
  "properties": {
    "gn:admin1_code":"2.0",
    "gn:admin2_code":"551.0",
    "gn:asciiname":"Chintalapalle",
    "gn:country_code":"IN",
    "gn:dem":186,
    "gn:feature_class":"P",
    "gn:feature_code":"PPL",
    "gn:name":"Chintalapalle",
    "gn:population":0,
    "gn:timezone":"Asia/Kolkata",
    "iso:country":"IN",
    "wof:name":"Chintalapalle",
    "wof:placetype":"locality"
},
  "geometry": {"coordinates":[78.99936,15.05038],"type":"Point"}
}