{
  "type": "Feature",
  "properties": {
    "gn:admin1_code":"36.0",
    "gn:admin2_code":"158.0",
    "gn:asciiname":"Raghunathpur Paterwa",
    "gn:country_code":"IN",
    "gn:dem":116,
    "gn:feature_class":"P",
    "gn:feature_code":"PPL",
    "gn:name":"Raghun\u0101thpur Paterwa",
    "gn:population":0,
    "gn:timezone":"Asia/Kolkata",
    "iso:country":"IN",
    "wof:name":"Raghunathpur Paterwa",
    "wof:placetype":"locality"
},
  "geometry": {"coordinates":[81.34109000000002,25.94808],"type":"Point"}
}