{
  "type": "Feature",
  "properties": {
    "iso:country":"IN",
    "ks:ks_name":"Sijna",
    "ks:ks_pop":2060,
    "ks:ks_type":"VILLAGE",
    "ks:ks_uagg_main":0,
    "name:eng_x_preferred":[
        "Sijna"
    ],
    "wof:name":"Sijna",
    "wof:placetype":"neighbourhood",
    "wof:population":2060
},
  "geometry": {"coordinates":[88.098584,23.368289],"type":"Point"}
}