{
  "type": "Feature",
  "properties": {
    "iso:country":"IN",
    "ks:ks_name":"Uchanuagan",
    "ks:ks_pop":956,
    "ks:ks_type":"VILLAGE",
    "name:eng_x_preferred":[
        "Uchanuagan"
    ],
    "wof:name":"Uchanuagan",
    "wof:placetype":"locality",
    "wof:population":956
},
  "geometry": {"coordinates":[86.478431,20.215891],"type":"Point"}
}