{
  "type": "Feature",
  "properties": {
    "iso:country":"IN",
    "ks:ks_name":"Kotagaruvu",
    "ks:ks_pop":57,
    "ks:ks_type":"HABITATION",
    "name:eng_x_preferred":[
        "Kotagaruvu"
    ],
    "wof:name":"Kotagaruvu",
    "wof:placetype":"locality",
    "wof:population":57
},
  "geometry": {"coordinates":[82.818291,18.0819],"type":"Point"}
}