{
  "type": "Feature",
  "properties": {
    "gn:admin1_code":"39",
    "gn:admin2_code":"61.0",
    "gn:asciiname":"Bangarh",
    "gn:country_code":"IN",
    "gn:dem":1717,
    "gn:feature_class":"P",
    "gn:feature_code":"PPL",
    "gn:name":"Bangarh",
    "gn:population":0,
    "gn:timezone":"Asia/Kolkata",
    "iso:country":"IN",
    "ks:ks_name":"Bangarh",
    "ks:ks_pop":226,
    "ks:ks_type":"VILLAGE",
    "name:ben_x_preferred":[
        "\u09a6\u09c7\u09ac\u0995\u09cb\u099f"
    ],
    "name:eng_x_preferred":[
        "Bangarh"
    ],
    "wof:name":"Bangarh",
    "wof:placetype":"locality",
    "wof:population":226
},
  "geometry": {"coordinates":[78.947783,29.782443],"type":"Point"}
}