{
  "type": "Feature",
  "properties": {
    "iso:country":"IN",
    "ks:ks_name":"Cheruveedhi",
    "ks:ks_pop":132,
    "ks:ks_type":"HABITATION",
    "name:eng_x_preferred":[
        "Cheruveedhi"
    ],
    "wof:name":"Cheruveedhi",
    "wof:placetype":"locality",
    "wof:population":132
},
  "geometry": {"coordinates":[82.587941,18.241601],"type":"Point"}
}