{
  "type": "Feature",
  "properties": {
    "gn:admin1_code":"35",
    "gn:admin2_code":"419.0",
    "gn:asciiname":"Dandoli",
    "gn:country_code":"IN",
    "gn:dem":155,
    "gn:feature_class":"P",
    "gn:feature_code":"PPL",
    "gn:name":"Dandoli",
    "gn:population":0,
    "gn:timezone":"Asia/Kolkata",
    "iso:country":"IN",
    "name:fin_x_preferred":[
        "Dandoli"
    ],
    "name:fra_x_preferred":[
        "Dandoli"
    ],
    "name:ita_x_preferred":[
        "Dandoli"
    ],
    "name:nld_x_preferred":[
        "Dandoli"
    ],
    "name:spa_x_preferred":[
        "Dandoli"
    ],
    "name:zho_x_preferred":[
        "\u4e39\u591a\u5229"
    ],
    "wof:name":"Dandoli",
    "wof:placetype":"locality"
},
  "geometry": {"coordinates":[78.15191999999998,26.71494],"type":"Point"}
}