{
  "type": "Feature",
  "properties": {
    "iso:country":"IN",
    "ks:ks_name":"Goni",
    "ks:ks_pop":1461,
    "ks:ks_type":"VILLAGE",
    "name:eng_x_preferred":[
        "Goni"
    ],
    "wof:name":"Goni",
    "wof:placetype":"locality",
    "wof:population":1461
},
  "geometry": {"coordinates":[79.01725999999999,21.827112],"type":"Point"}
}