{
  "type": "Feature",
  "properties": {
    "iso:country":"IN",
    "ks:ks_name":"Ghusukpur",
    "ks:ks_pop":1205,
    "ks:ks_type":"HABITATION",
    "name:eng_x_preferred":[
        "Ghusukpur"
    ],
    "wof:name":"Ghusukpur",
    "wof:placetype":"locality",
    "wof:population":1205
},
  "geometry": {"coordinates":[84.70784999999999,26.76068],"type":"Point"}
}