{
  "type": "Feature",
  "properties": {
    "iso:country":"IN",
    "ks:ks_name":"Baleguli",
    "ks:ks_pop":292,
    "ks:ks_type":"HABITATION",
    "name:eng_x_preferred":[
        "Baleguli"
    ],
    "wof:name":"Baleguli",
    "wof:placetype":"locality",
    "wof:population":292
},
  "geometry": {"coordinates":[74.32628,14.679179],"type":"Point"}
}