{
  "type": "Feature",
  "properties": {
    "iso:country":"IN",
    "ks:ks_name":"Koothakkollai",
    "ks:ks_pop":160,
    "ks:ks_type":"HABITATION",
    "name:eng_x_preferred":[
        "Koothakkollai"
    ],
    "wof:name":"Koothakkollai",
    "wof:placetype":"locality",
    "wof:population":160
},
  "geometry": {"coordinates":[79.198911,10.518438],"type":"Point"}
}