{
  "type": "Feature",
  "properties": {
    "gn:admin1_code":"10.0",
    "gn:admin2_code":"83.0",
    "gn:asciiname":"Gangtian",
    "gn:country_code":"IN",
    "gn:dem":219,
    "gn:feature_class":"P",
    "gn:feature_code":"PPL",
    "gn:name":"G\u0101ngti\u0101n",
    "gn:population":0,
    "gn:timezone":"Asia/Kolkata",
    "iso:country":"IN",
    "ks:ks_alt_nam":"G\u0101ngti\u0101n",
    "ks:ks_name":"Gangtian",
    "ks:ks_pop":1517,
    "ks:ks_type":"VILLAGE",
    "ks:ks_uagg_main":0,
    "name:eng_x_preferred":[
        "Gangtian"
    ],
    "name:eng_x_variant":[
        "G\u0101ngti\u0101n"
    ],
    "wof:name":"Gangtian",
    "wof:placetype":"neighbourhood",
    "wof:population":1517
},
  "geometry": {"coordinates":[76.63968300000001,28.764841],"type":"Point"}
}