{
  "type": "Feature",
  "properties": {
    "iso:country":"IN",
    "ks:ks_name":"Mestriwadi",
    "ks:ks_pop":73,
    "ks:ks_type":"HABITATION",
    "name:eng_x_preferred":[
        "Mestriwadi"
    ],
    "wof:name":"Mestriwadi",
    "wof:placetype":"locality",
    "wof:population":73
},
  "geometry": {"coordinates":[73.68895999999999,15.954876],"type":"Point"}
}