{
  "type": "Feature",
  "properties": {
    "iso:country":"IN",
    "ks:ks_name":"Gazipur",
    "ks:ks_pop":327,
    "ks:ks_type":"VILLAGE",
    "name:eng_x_preferred":[
        "Gazipur"
    ],
    "wof:name":"Gazipur",
    "wof:placetype":"locality",
    "wof:population":327
},
  "geometry": {"coordinates":[88.110952,25.254215],"type":"Point"}
}