{
  "type": "Feature",
  "properties": {
    "iso:country":"IN",
    "ks:ks_name":"Chhawani",
    "ks:ks_pop":255,
    "ks:ks_type":"HABITATION",
    "ks:ks_uagg_main":0,
    "name:eng_x_preferred":[
        "Chhawani"
    ],
    "wof:name":"Chhawani",
    "wof:placetype":"neighbourhood",
    "wof:population":255
},
  "geometry": {"coordinates":[83.746999,26.581288],"type":"Point"}
}