{
  "type": "Feature",
  "properties": {
    "iso:country":"IN",
    "ks:ks_name":"Kanhupur",
    "ks:ks_pop":1151,
    "ks:ks_type":"VILLAGE",
    "name:eng_x_preferred":[
        "Kanhupur"
    ],
    "wof:name":"Kanhupur",
    "wof:placetype":"locality",
    "wof:population":1151
},
  "geometry": {"coordinates":[86.35268600000001,21.210886],"type":"Point"}
}