{
  "type": "Feature",
  "properties": {
    "iso:country":"IN",
    "ks:ks_name":"Madhya Haidubi",
    "ks:ks_pop":2528,
    "ks:ks_type":"HABITATION",
    "ks:ks_uagg_main":0,
    "name:eng_x_preferred":[
        "Madhya Haidubi"
    ],
    "wof:name":"Madhya Haidubi",
    "wof:placetype":"neighbourhood",
    "wof:population":2528
},
  "geometry": {"coordinates":[92.556625,26.425987],"type":"Point"}
}