{
  "type": "Feature",
  "properties": {
    "iso:country":"IN",
    "ks:ks_name":"Bhimiriguda",
    "ks:ks_pop":253,
    "ks:ks_type":"VILLAGE",
    "name:eng_x_preferred":[
        "Bhimiriguda"
    ],
    "wof:name":"Bhimiriguda",
    "wof:placetype":"locality",
    "wof:population":253
},
  "geometry": {"coordinates":[83.973145,19.658911],"type":"Point"}
}