{
  "type": "Feature",
  "properties": {
    "gn:admin1_code":"35.0",
    "gn:admin2_code":"427.0",
    "gn:asciiname":"Kherpani",
    "gn:country_code":"IN",
    "gn:dem":451,
    "gn:feature_class":"P",
    "gn:feature_code":"PPL",
    "gn:name":"Kherp\u0101ni",
    "gn:population":0,
    "gn:timezone":"Asia/Kolkata",
    "iso:country":"IN",
    "ks:ks_name":"Kerpani",
    "ks:ks_pop":578,
    "ks:ks_type":"VILLAGE",
    "name:eng_x_preferred":[
        "Kerpani"
    ],
    "name:eng_x_variant":[
        "Kherpani"
    ],
    "wof:name":"Kerpani",
    "wof:placetype":"locality",
    "wof:population":578
},
  "geometry": {"coordinates":[78.863201,23.234802],"type":"Point"}
}