{
  "type": "Feature",
  "properties": {
    "iso:country":"IN",
    "ks:ks_name":"Dugdugi",
    "ks:ks_pop":41,
    "ks:ks_type":"HABITATION",
    "name:eng_x_preferred":[
        "Dugdugi"
    ],
    "wof:name":"Dugdugi",
    "wof:placetype":"locality",
    "wof:population":41
},
  "geometry": {"coordinates":[87.963886,26.363009],"type":"Point"}
}