{
  "type": "Feature",
  "properties": {
    "iso:country":"IN",
    "ks:ks_alt_nam":"DUSADH TOL",
    "ks:ks_name":"Dusadh Tol",
    "ks:ks_pop":1133,
    "ks:ks_type":"HABITATION",
    "name:eng_x_preferred":[
        "Dusadh Tol"
    ],
    "wof:name":"Dusadh Tol",
    "wof:placetype":"locality",
    "wof:population":1133
},
  "geometry": {"coordinates":[86.04133299999999,26.057734],"type":"Point"}
}