{
  "type": "Feature",
  "properties": {
    "iso:country":"IN",
    "ks:ks_name":"Virupatchipuram",
    "ks:ks_pop":582,
    "ks:ks_type":"HABITATION",
    "name:eng_x_preferred":[
        "Virupatchipuram"
    ],
    "wof:name":"Virupatchipuram",
    "wof:placetype":"locality",
    "wof:population":582
},
  "geometry": {"coordinates":[79.102968,12.756757],"type":"Point"}
}