{
  "type": "Feature",
  "properties": {
    "gn:admin1_code":"2.0",
    "gn:asciiname":"Tabaru",
    "gn:country_code":"IN",
    "gn:dem":511,
    "gn:feature_class":"P",
    "gn:feature_code":"PPL",
    "gn:name":"Tabaru",
    "gn:population":0,
    "gn:timezone":"Asia/Kolkata",
    "iso:country":"IN",
    "wof:name":"Tabaru",
    "wof:placetype":"locality"
},
  "geometry": {"coordinates":[82.38133000000001,18.38009],"type":"Point"}
}