{
  "type": "Feature",
  "properties": {
    "iso:country":"IN",
    "ks:ks_name":"Bakal Chhoti",
    "ks:ks_pop":401,
    "ks:ks_type":"HABITATION",
    "name:eng_x_preferred":[
        "Bakal Chhoti"
    ],
    "wof:name":"Bakal Chhoti",
    "wof:placetype":"locality",
    "wof:population":401
},
  "geometry": {"coordinates":[74.61695,22.473506],"type":"Point"}
}