{
  "type": "Feature",
  "properties": {
    "iso:country":"IN",
    "ks:ks_name":"Pasin Purwa",
    "ks:ks_pop":55,
    "ks:ks_type":"HABITATION",
    "name:eng_x_preferred":[
        "Pasin Purwa"
    ],
    "wof:name":"Pasin Purwa",
    "wof:placetype":"locality",
    "wof:population":55
},
  "geometry": {"coordinates":[81.589207,27.238513],"type":"Point"}
}