{
  "type": "Feature",
  "properties": {
    "iso:country":"IN",
    "ks:ks_name":"Guddeangadi",
    "ks:ks_pop":990,
    "ks:ks_type":"HABITATION",
    "name:eng_x_preferred":[
        "Guddeangadi"
    ],
    "wof:name":"Guddeangadi",
    "wof:placetype":"locality",
    "wof:population":990
},
  "geometry": {"coordinates":[74.672518,13.723861],"type":"Point"}
}