{
  "type": "Feature",
  "properties": {
    "iso:country":"IN",
    "ks:ks_name":"Waghlud Kh.",
    "ks:ks_pop":776,
    "ks:ks_type":"VILLAGE",
    "name:eng_x_preferred":[
        "Waghlud Kh."
    ],
    "wof:name":"Waghlud Kh.",
    "wof:placetype":"locality",
    "wof:population":776
},
  "geometry": {"coordinates":[75.342645,21.038728],"type":"Point"}
}