{
  "type": "Feature",
  "properties": {
    "iso:country":"IN",
    "ks:ks_name":"West Kamrangabari",
    "ks:ks_pop":749,
    "ks:ks_type":"HABITATION",
    "name:eng_x_preferred":[
        "West Kamrangabari"
    ],
    "wof:name":"West Kamrangabari",
    "wof:placetype":"locality",
    "wof:population":749
},
  "geometry": {"coordinates":[92.018389,24.288565],"type":"Point"}
}