{
  "type": "Feature",
  "properties": {
    "iso:country":"IN",
    "ks:ks_name":"Rusni",
    "ks:ks_pop":0,
    "ks:ks_type":"VILLAGE",
    "name:eng_x_preferred":[
        "Rusni"
    ],
    "wof:name":"Rusni",
    "wof:placetype":"locality",
    "wof:population":0
},
  "geometry": {"coordinates":[82.13070999999999,23.650867],"type":"Point"}
}