{
  "type": "Feature",
  "properties": {
    "iso:country":"IN",
    "ks:ks_name":"Kunnathodi",
    "ks:ks_pop":1318,
    "ks:ks_type":"HABITATION",
    "name:eng_x_preferred":[
        "Kunnathodi"
    ],
    "wof:name":"Kunnathodi",
    "wof:placetype":"locality",
    "wof:population":1318
},
  "geometry": {"coordinates":[76.358366,10.900387],"type":"Point"}
}