{
  "type": "Feature",
  "properties": {
    "iso:country":"IN",
    "ks:ks_name":"Lodpa",
    "ks:ks_pop":428,
    "ks:ks_type":"VILLAGE",
    "ks:ks_uagg_main":0,
    "name:eng_x_preferred":[
        "Lodpa"
    ],
    "wof:name":"Lodpa",
    "wof:placetype":"neighbourhood",
    "wof:population":428
},
  "geometry": {"coordinates":[72.33488699999999,24.311692],"type":"Point"}
}