{
  "type": "Feature",
  "properties": {
    "iso:country":"IN",
    "ks:ks_name":"Basapanga",
    "ks:ks_pop":10,
    "ks:ks_type":"VILLAGE",
    "name:eng_x_preferred":[
        "Basapanga"
    ],
    "wof:name":"Basapanga",
    "wof:placetype":"locality",
    "wof:population":10
},
  "geometry": {"coordinates":[84.194328,20.352496],"type":"Point"}
}