{
  "type": "Feature",
  "properties": {
    "gn:admin1_code":"12.0",
    "gn:admin2_code":"16.0",
    "gn:asciiname":"Lungri",
    "gn:country_code":"IN",
    "gn:dem":2246,
    "gn:feature_class":"P",
    "gn:feature_code":"PPL",
    "gn:name":"Lungri",
    "gn:population":0,
    "gn:timezone":"Asia/Kolkata",
    "iso:country":"IN",
    "wof:name":"Lungri",
    "wof:placetype":"locality"
},
  "geometry": {"coordinates":[75.58053000000002,33.02006],"type":"Point"}
}