{
  "type": "Feature",
  "properties": {
    "gn:admin1_code":"35.0",
    "gn:admin2_code":"463",
    "gn:asciiname":"Kachani",
    "gn:country_code":"IN",
    "gn:dem":290,
    "gn:feature_class":"P",
    "gn:feature_code":"PPL",
    "gn:name":"Kachani",
    "gn:population":0,
    "gn:timezone":"Asia/Kolkata",
    "iso:country":"IN",
    "name:und_x_variant":[
        "Kaohni"
    ],
    "wof:name":"Kachani",
    "wof:placetype":"neighbourhood"
},
  "geometry": {"coordinates":[82.58958,24.08676],"type":"Point"}
}