{
  "type": "Feature",
  "properties": {
    "iso:country":"IN",
    "ks:ks_name":"Taraiguda",
    "ks:ks_pop":240,
    "ks:ks_type":"HABITATION",
    "ks:ks_uagg_main":0,
    "name:eng_x_preferred":[
        "Taraiguda"
    ],
    "wof:name":"Taraiguda",
    "wof:placetype":"neighbourhood",
    "wof:population":240
},
  "geometry": {"coordinates":[81.977463,19.126004],"type":"Point"}
}