{
  "type": "Feature",
  "properties": {
    "iso:country":"IN",
    "ks:ks_name":"Bamoli",
    "ks:ks_pop":40,
    "ks:ks_type":"VILLAGE",
    "name:eng_x_preferred":[
        "Bamoli"
    ],
    "wof:name":"Bamoli",
    "wof:placetype":"locality",
    "wof:population":40
},
  "geometry": {"coordinates":[79.00007100000001,30.346481],"type":"Point"}
}