{
  "type": "Feature",
  "properties": {
    "iso:country":"IN",
    "ks:ks_name":"Ghoradih",
    "ks:ks_type":"VILLAGE",
    "name:eng_x_preferred":[
        "Ghoradih"
    ],
    "wof:name":"Ghoradih",
    "wof:placetype":"locality"
},
  "geometry": {"coordinates":[80.27048000000001,22.655884],"type":"Point"}
}