{
  "type": "Feature",
  "properties": {
    "iso:country":"IN",
    "ks:ks_name":"Karaimedu-south",
    "ks:ks_pop":1860,
    "ks:ks_type":"HABITATION",
    "name:eng_x_preferred":[
        "Karaimedu-south"
    ],
    "wof:name":"Karaimedu-south",
    "wof:placetype":"locality",
    "wof:population":1860
},
  "geometry": {"coordinates":[79.340875,11.233843],"type":"Point"}
}