{
  "type": "Feature",
  "properties": {
    "gn:admin1_code":"19.0",
    "gn:admin2_code":"579",
    "gn:asciiname":"Bandarwad",
    "gn:country_code":"IN",
    "gn:dem":407,
    "gn:feature_class":"P",
    "gn:feature_code":"PPL",
    "gn:name":"Bandarw\u0101d",
    "gn:population":0,
    "gn:timezone":"Asia/Kolkata",
    "iso:country":"IN",
    "name:und_x_variant":[
        "Bandarw\u0101d",
        "Bandanw\u0101da"
    ],
    "wof:name":"Bandarwad",
    "wof:placetype":"locality"
},
  "geometry": {"coordinates":[76.58183000000002,17.17824],"type":"Point"}
}