{
  "type": "Feature",
  "properties": {
    "iso:country":"IN",
    "ks:ks_name":"Paja Para",
    "ks:ks_pop":1266,
    "ks:ks_type":"HABITATION",
    "ks:ks_uagg_main":0,
    "name:eng_x_preferred":[
        "Paja Para"
    ],
    "wof:name":"Paja Para",
    "wof:placetype":"locality",
    "wof:population":1266
},
  "geometry": {"coordinates":[88.34948,22.413321],"type":"Point"}
}