{
  "type": "Feature",
  "properties": {
    "iso:country":"IN",
    "ks:ks_name":"Khas",
    "ks:ks_pop":1133,
    "ks:ks_type":"HABITATION",
    "name:eng_x_preferred":[
        "Khas"
    ],
    "wof:name":"Khas",
    "wof:placetype":"locality",
    "wof:population":1133
},
  "geometry": {"coordinates":[83.833474,27.16032],"type":"Point"}
}