{
  "type": "Feature",
  "properties": {
    "iso:country":"IN",
    "ks:ks_name":"Gumapadara",
    "ks:ks_pop":226,
    "ks:ks_type":"VILLAGE",
    "name:eng_x_preferred":[
        "Gumapadara"
    ],
    "wof:name":"Gumapadara",
    "wof:placetype":"locality",
    "wof:population":226
},
  "geometry": {"coordinates":[83.74097399999999,19.767352],"type":"Point"}
}