{
  "type": "Feature",
  "properties": {
    "gn:admin1_code":"36",
    "gn:admin2_code":"185.0",
    "gn:asciiname":"Akari",
    "gn:country_code":"IN",
    "gn:dem":86,
    "gn:feature_class":"P",
    "gn:feature_code":"PPL",
    "gn:name":"Ak\u0101ri",
    "gn:population":0,
    "gn:timezone":"Asia/Kolkata",
    "iso:country":"IN",
    "name:fra_x_preferred":[
        "Akari"
    ],
    "name:jpn_x_preferred":[
        "\u30a2\u30ab\u30ea"
    ],
    "name:kor_x_preferred":[
        "\uc544\uce74\ub9ac"
    ],
    "name:rus_x_preferred":[
        "\u0410\u043a\u0430\u0440\u0438"
    ],
    "wof:name":"Akari",
    "wof:placetype":"locality"
},
  "geometry": {"coordinates":[82.79080999999999,26.68685],"type":"Point"}
}