{
  "type": "Feature",
  "properties": {
    "iso:country":"IN",
    "ks:ks_name":"Deoghar",
    "ks:ks_pop":557,
    "ks:ks_type":"VILLAGE",
    "name:eng_x_preferred":[
        "Deoghar"
    ],
    "wof:name":"Deoghar",
    "wof:placetype":"locality",
    "wof:population":557
},
  "geometry": {"coordinates":[72.954367,18.588916],"type":"Point"}
}