{
  "type": "Feature",
  "properties": {
    "iso:country":"IN",
    "ks:ks_name":"Analemane",
    "ks:ks_pop":11,
    "ks:ks_type":"HABITATION",
    "name:eng_x_preferred":[
        "Analemane"
    ],
    "wof:name":"Analemane",
    "wof:placetype":"locality",
    "wof:population":11
},
  "geometry": {"coordinates":[74.984859,14.08277],"type":"Point"}
}