{
  "type": "Feature",
  "properties": {
    "iso:country":"IN",
    "ks:ks_name":"Babhandiha",
    "ks:ks_pop":534,
    "ks:ks_type":"VILLAGE",
    "ks:ks_uagg_main":0,
    "name:eng_x_preferred":[
        "Babhandiha"
    ],
    "wof:name":"Babhandiha",
    "wof:placetype":"neighbourhood",
    "wof:population":534
},
  "geometry": {"coordinates":[85.771683,24.36162],"type":"Point"}
}