{
  "type": "Feature",
  "properties": {
    "iso:country":"IN",
    "ks:ks_name":"Dharuwa Halehaura",
    "ks:ks_pop":1807,
    "ks:ks_type":"HABITATION",
    "ks:ks_uagg_main":0,
    "name:eng_x_preferred":[
        "Dharuwa Halehaura"
    ],
    "wof:name":"Dharuwa Halehaura",
    "wof:placetype":"neighbourhood",
    "wof:population":1807
},
  "geometry": {"coordinates":[84.963003,26.75191],"type":"Point"}
}