{
  "type": "Feature",
  "properties": {
    "gn:admin1_code":"36",
    "gn:admin2_code":"197.0",
    "gn:asciiname":"Jeorampur",
    "gn:country_code":"IN",
    "gn:dem":86,
    "gn:feature_class":"P",
    "gn:feature_code":"PPL",
    "gn:name":"Jeor\u0101mpur",
    "gn:population":0,
    "gn:timezone":"Asia/Kolkata",
    "iso:country":"IN",
    "ks:ks_name":"Jewarampur",
    "ks:ks_pop":171,
    "ks:ks_type":"HABITATION",
    "ks:ks_uagg_main":0,
    "name:eng_x_preferred":[
        "Jewarampur"
    ],
    "wof:name":"Jewarampur",
    "wof:placetype":"neighbourhood",
    "wof:population":171
},
  "geometry": {"coordinates":[82.77426,25.344866],"type":"Point"}
}