{
  "type": "Feature",
  "properties": {
    "iso:country":"IN",
    "ks:ks_name":"Krishnapuram",
    "ks:ks_pop":315,
    "ks:ks_type":"HABITATION",
    "name:eng_x_preferred":[
        "Krishnapuram"
    ],
    "wof:name":"Krishnapuram",
    "wof:placetype":"locality",
    "wof:population":315
},
  "geometry": {"coordinates":[78.932316,9.309956],"type":"Point"}
}