{
  "type": "Feature",
  "properties": {
    "iso:country":"IN",
    "ks:ks_name":"Sila",
    "ks:ks_pop":1163,
    "ks:ks_type":"HABITATION",
    "name:eng_x_preferred":[
        "Sila"
    ],
    "wof:name":"Sila",
    "wof:placetype":"locality",
    "wof:population":1163
},
  "geometry": {"coordinates":[85.167557,24.66711],"type":"Point"}
}