{
  "type": "Feature",
  "properties": {
    "iso:country":"IN",
    "ks:ks_name":"Jallaram",
    "ks:ks_pop":11010,
    "ks:ks_type":"VILLAGE",
    "name:eng_x_preferred":[
        "Jallaram"
    ],
    "wof:name":"Jallaram",
    "wof:placetype":"neighbourhood",
    "wof:population":11010
},
  "geometry": {"coordinates":[79.514673,18.742674],"type":"Point"}
}