{
  "type": "Feature",
  "properties": {
    "gn:admin1_code":"28.0",
    "gn:admin2_code":"337",
    "gn:asciiname":"Dattapara",
    "gn:country_code":"IN",
    "gn:dem":10,
    "gn:feature_class":"P",
    "gn:feature_code":"PPL",
    "gn:name":"Dattap\u0101ra",
    "gn:population":0,
    "gn:timezone":"Asia/Kolkata",
    "iso:country":"IN",
    "ks:ks_alt_nam":"Dattap\u0101ra",
    "ks:ks_name":"Dattapara",
    "ks:ks_pop":7438,
    "ks:ks_type":"VILLAGE",
    "ks:ks_uagg_main":0,
    "name:eng_x_preferred":[
        "Dattapara"
    ],
    "name:eng_x_variant":[
        "Dattap\u0101ra"
    ],
    "wof:name":"Dattapara",
    "wof:placetype":"neighbourhood",
    "wof:population":7438
},
  "geometry": {"coordinates":[88.900779,22.850463],"type":"Point"}
}