{
  "type": "Feature",
  "properties": {
    "iso:country":"IN",
    "ks:ks_name":"Bhait Garh",
    "ks:ks_pop":1787,
    "ks:ks_type":"HABITATION",
    "name:eng_x_preferred":[
        "Bhait Garh"
    ],
    "wof:name":"Bhait Garh",
    "wof:placetype":"locality",
    "wof:population":1787
},
  "geometry": {"coordinates":[87.773793,21.902826],"type":"Point"}
}