{
  "type": "Feature",
  "properties": {
    "iso:country":"IN",
    "ks:ks_name":"Rengampatti",
    "ks:ks_pop":251,
    "ks:ks_type":"VILLAGE",
    "name:eng_x_preferred":[
        "Rengampatti"
    ],
    "wof:name":"Rengampatti",
    "wof:placetype":"locality",
    "wof:population":251
},
  "geometry": {"coordinates":[78.03280599999999,12.356346],"type":"Point"}
}