{
  "type": "Feature",
  "properties": {
    "gn:admin1_code":"34.0",
    "gn:admin2_code":"219.0",
    "gn:asciiname":"Tola Badai Raut",
    "gn:country_code":"IN",
    "gn:dem":62,
    "gn:feature_class":"P",
    "gn:feature_code":"PPL",
    "gn:name":"Tola B\u0101dai R\u0101ut",
    "gn:population":0,
    "gn:timezone":"Asia/Kolkata",
    "iso:country":"IN",
    "wof:name":"Tola Badai Raut",
    "wof:placetype":"locality"
},
  "geometry": {"coordinates":[84.87631999999998,26.05742],"type":"Point"}
}