{
  "type": "Feature",
  "properties": {
    "gn:admin1_code":"35",
    "gn:admin2_code":"421.0",
    "gn:asciiname":"Sohan",
    "gn:country_code":"IN",
    "gn:dem":173,
    "gn:feature_class":"P",
    "gn:feature_code":"PPL",
    "gn:name":"Sohan",
    "gn:population":0,
    "gn:timezone":"Asia/Kolkata",
    "iso:country":"IN",
    "name:fas_x_preferred":[
        "\u0633\u0648\u0647\u0646"
    ],
    "name:urd_x_preferred":[
        "\u0633\u0648\u06c1\u0646"
    ],
    "wof:name":"Sohan",
    "wof:placetype":"locality"
},
  "geometry": {"coordinates":[78.791,25.94781],"type":"Point"}
}