{
  "type": "Feature",
  "properties": {
    "gn:admin1_code":"36.0",
    "gn:asciiname":"Mahdew",
    "gn:country_code":"IN",
    "gn:dem":453,
    "gn:feature_class":"P",
    "gn:feature_code":"PPL",
    "gn:name":"Mahdew",
    "gn:population":0,
    "gn:timezone":"Asia/Kolkata",
    "iso:country":"IN",
    "wof:name":"Mahdew",
    "wof:placetype":"neighbourhood"
},
  "geometry": {"coordinates":[77.43895999999999,25.46219],"type":"Point"}
}