{
  "type": "Feature",
  "properties": {
    "iso:country":"IN",
    "ks:ks_name":"Mahulapada",
    "ks:ks_pop":286,
    "ks:ks_type":"VILLAGE",
    "name:eng_x_preferred":[
        "Mahulapada"
    ],
    "wof:name":"Mahulapada",
    "wof:placetype":"locality",
    "wof:population":286
},
  "geometry": {"coordinates":[84.326866,19.565003],"type":"Point"}
}