{
  "type": "Feature",
  "properties": {
    "iso:country":"IN",
    "ks:ks_name":"Kinchaiput",
    "ks:ks_pop":0,
    "ks:ks_type":"VILLAGE",
    "name:eng_x_preferred":[
        "Kinchaiput"
    ],
    "wof:name":"Kinchaiput",
    "wof:placetype":"locality",
    "wof:population":0
},
  "geometry": {"coordinates":[82.606312,18.70629],"type":"Point"}
}