{
  "type": "Feature",
  "properties": {
    "iso:country":"IN",
    "ks:ks_name":"Kumalsingi",
    "ks:ks_pop":371,
    "ks:ks_type":"VILLAGE",
    "name:eng_x_preferred":[
        "Kumalsingi"
    ],
    "wof:name":"Kumalsingi",
    "wof:placetype":"locality",
    "wof:population":371
},
  "geometry": {"coordinates":[83.875925,20.547129],"type":"Point"}
}