{
  "type": "Feature",
  "properties": {
    "iso:country":"IN",
    "ks:ks_name":"Kizhikunnu",
    "ks:ks_pop":523,
    "ks:ks_type":"HABITATION",
    "name:eng_x_preferred":[
        "Kizhikunnu"
    ],
    "wof:name":"Kizhikunnu",
    "wof:placetype":"locality",
    "wof:population":523
},
  "geometry": {"coordinates":[76.187067,11.834834],"type":"Point"}
}