{
  "type": "Feature",
  "properties": {
    "iso:country":"IN",
    "ks:ks_name":"Belu Faliyu",
    "ks:ks_pop":725,
    "ks:ks_type":"HABITATION",
    "name:eng_x_preferred":[
        "Belu Faliyu"
    ],
    "wof:name":"Belu Faliyu",
    "wof:placetype":"locality",
    "wof:population":725
},
  "geometry": {"coordinates":[72.792056,20.299556],"type":"Point"}
}