{
  "type": "Feature",
  "properties": {
    "iso:country":"IN",
    "ks:ks_name":"Teghari",
    "ks:ks_pop":215,
    "ks:ks_type":"VILLAGE",
    "name:eng_x_preferred":[
        "Teghari"
    ],
    "wof:name":"Teghari",
    "wof:placetype":"locality",
    "wof:population":215
},
  "geometry": {"coordinates":[87.342321,21.684281],"type":"Point"}
}