{
  "type": "Feature",
  "properties": {
    "iso:country":"IN",
    "ks:ks_name":"Indra Nagar Rael Ki Dhani",
    "ks:ks_pop":176,
    "ks:ks_type":"HABITATION",
    "name:eng_x_preferred":[
        "Indra Nagar Rael Ki Dhani"
    ],
    "wof:name":"Indra Nagar Rael Ki Dhani",
    "wof:placetype":"locality",
    "wof:population":176
},
  "geometry": {"coordinates":[71.77498300000001,25.668792],"type":"Point"}
}