{
  "type": "Feature",
  "properties": {
    "iso:country":"IN",
    "ks:ks_name":"Ishwarpura",
    "ks:ks_pop":928,
    "ks:ks_type":"HABITATION",
    "name:eng_x_preferred":[
        "Ishwarpura"
    ],
    "wof:name":"Ishwarpura",
    "wof:placetype":"locality",
    "wof:population":928
},
  "geometry": {"coordinates":[72.988,22.501333],"type":"Point"}
}