{
  "type": "Feature",
  "properties": {
    "gn:admin1_code":"40",
    "gn:admin2_code":"535.0",
    "gn:asciiname":"Jukal",
    "gn:country_code":"IN",
    "gn:dem":508,
    "gn:feature_class":"P",
    "gn:feature_code":"PPL",
    "gn:name":"Jukal",
    "gn:population":0,
    "gn:timezone":"Asia/Kolkata",
    "iso:country":"IN",
    "wof:name":"Jukal",
    "wof:placetype":"locality"
},
  "geometry": {"coordinates":[77.79590999999998,18.02771],"type":"Point"}
}