{
  "type": "Feature",
  "properties": {
    "iso:country":"IN",
    "ks:ks_name":"Kadomali",
    "ks:ks_pop":2,
    "ks:ks_type":"VILLAGE",
    "name:eng_x_preferred":[
        "Kadomali"
    ],
    "wof:name":"Kadomali",
    "wof:placetype":"locality",
    "wof:population":2
},
  "geometry": {"coordinates":[83.301635,19.664363],"type":"Point"}
}