{
  "type": "Feature",
  "properties": {
    "gn:admin1_code":"35",
    "gn:admin2_code":"425.0",
    "gn:asciiname":"Intwa",
    "gn:country_code":"IN",
    "gn:dem":197,
    "gn:feature_class":"P",
    "gn:feature_code":"PPL",
    "gn:name":"Intwa",
    "gn:population":0,
    "gn:timezone":"Asia/Kolkata",
    "iso:country":"IN",
    "wof:name":"Intwa",
    "wof:placetype":"neighbourhood"
},
  "geometry": {"coordinates":[79.94408,25.22276],"type":"Point"}
}