{
  "type": "Feature",
  "properties": {
    "iso:country":"IN",
    "ks:ks_name":"Vishawas",
    "ks:ks_pop":30,
    "ks:ks_type":"VILLAGE",
    "name:eng_x_preferred":[
        "Vishawas"
    ],
    "wof:name":"Vishawas",
    "wof:placetype":"locality",
    "wof:population":30
},
  "geometry": {"coordinates":[72.984432,25.967646],"type":"Point"}
}