{
  "type": "Feature",
  "properties": {
    "gn:admin1_code":"34",
    "gn:admin2_code":"203.0",
    "gn:asciiname":"Lauriya Nandangarh",
    "gn:country_code":"IN",
    "gn:dem":86,
    "gn:feature_class":"P",
    "gn:feature_code":"PPL",
    "gn:name":"Lauriy\u0101 Nandangarh",
    "gn:population":0,
    "gn:timezone":"Asia/Kolkata",
    "iso:country":"IN",
    "name:tam_x_preferred":[
        "\u0bb2\u0bb5\u0bc1\u0bb0\u0bbf\u0baf\u0bbe \u0b9a\u0b9f\u0bcd\u0b9f\u0bae\u0ba9\u0bcd\u0bb1\u0ba4\u0bcd \u0ba4\u0bca\u0b95\u0bc1\u0ba4\u0bbf"
    ],
    "name:und_x_variant":[
        "Lauriya",
        "Lauriya Nandangarh",
        "Lauriy\u0101 Nandangarh"
    ],
    "wof:name":"Lauriya Nandangarh",
    "wof:placetype":"locality"
},
  "geometry": {"coordinates":[84.40432,26.99362],"type":"Point"}
}