{
  "type": "Feature",
  "properties": {
    "iso:country":"IN",
    "ks:ks_name":"Kalyaniya",
    "ks:ks_pop":1326,
    "ks:ks_type":"VILLAGE",
    "name:eng_x_preferred":[
        "Kalyaniya"
    ],
    "wof:name":"Kalyaniya",
    "wof:placetype":"locality",
    "wof:population":1326
},
  "geometry": {"coordinates":[82.689362,27.268895],"type":"Point"}
}