{
  "type": "Feature",
  "properties": {
    "iso:country":"IN",
    "ks:ks_alt_nam":"PUKRIPI",
    "ks:ks_name":"Pukripi",
    "ks:ks_pop":272,
    "ks:ks_type":"HABITATION",
    "name:eng_x_preferred":[
        "Pukripi"
    ],
    "wof:name":"Pukripi",
    "wof:placetype":"locality",
    "wof:population":272
},
  "geometry": {"coordinates":[85.80395300000001,22.367279],"type":"Point"}
}