{
  "type": "Feature",
  "properties": {
    "iso:country":"IN",
    "ks:ks_name":"Bangargi",
    "ks:ks_pop":996,
    "ks:ks_type":"VILLAGE",
    "name:eng_x_preferred":[
        "Bangargi"
    ],
    "wof:name":"Bangargi",
    "wof:placetype":"locality",
    "wof:population":996
},
  "geometry": {"coordinates":[85.95087599999999,24.402496],"type":"Point"}
}