{
  "type": "Feature",
  "properties": {
    "iso:country":"IN",
    "ks:ks_name":"Kaishali",
    "ks:ks_pop":369,
    "ks:ks_type":"HABITATION",
    "name:eng_x_preferred":[
        "Kaishali"
    ],
    "wof:name":"Kaishali",
    "wof:placetype":"locality",
    "wof:population":369
},
  "geometry": {"coordinates":[78.206547,23.167054],"type":"Point"}
}