{
  "type": "Feature",
  "properties": {
    "iso:country":"IN",
    "ks:ks_name":"Edakkattuvayal",
    "ks:ks_pop":10977,
    "ks:ks_type":"VILLAGE",
    "name:eng_x_preferred":[
        "Edakkattuvayal"
    ],
    "wof:name":"Edakkattuvayal",
    "wof:placetype":"locality",
    "wof:population":10977
},
  "geometry": {"coordinates":[76.432669,9.874546],"type":"Point"}
}