{
  "type": "Feature",
  "properties": {
    "iso:country":"IN",
    "ks:ks_name":"Kumaranahalli",
    "ks:ks_pop":31,
    "ks:ks_type":"HABITATION",
    "name:eng_x_preferred":[
        "Kumaranahalli"
    ],
    "wof:name":"Kumaranahalli",
    "wof:placetype":"locality",
    "wof:population":31
},
  "geometry": {"coordinates":[75.746122,13.096538],"type":"Point"}
}