{
  "type": "Feature",
  "properties": {
    "iso:country":"IN",
    "ks:ks_name":"Kanthipadar",
    "ks:ks_pop":211,
    "ks:ks_type":"VILLAGE",
    "name:eng_x_preferred":[
        "Kanthipadar"
    ],
    "wof:name":"Kanthipadar",
    "wof:placetype":"locality",
    "wof:population":211
},
  "geometry": {"coordinates":[84.675236,20.316361],"type":"Point"}
}