{
  "type": "Feature",
  "properties": {
    "gn:admin1_code":"24.0",
    "gn:admin2_code":"129.0",
    "gn:asciiname":"Bagod",
    "gn:country_code":"IN",
    "gn:dem":283,
    "gn:feature_class":"P",
    "gn:feature_code":"PPL",
    "gn:name":"B\u0101god",
    "gn:population":0,
    "gn:timezone":"Asia/Kolkata",
    "iso:country":"IN",
    "name:ces_x_preferred":[
        "Bagod"
    ],
    "name:epo_x_preferred":[
        "Bagod"
    ],
    "name:fas_x_preferred":[
        "\u0628\u0627\u06af\u0648\u062f"
    ],
    "name:fra_x_preferred":[
        "Bagod"
    ],
    "name:hun_x_preferred":[
        "Bagod"
    ],
    "name:ita_x_preferred":[
        "Bagod"
    ],
    "name:msa_x_preferred":[
        "Bagod"
    ],
    "name:nld_x_preferred":[
        "Bagod"
    ],
    "name:ron_x_preferred":[
        "Bagod"
    ],
    "name:slk_x_preferred":[
        "Bagod"
    ],
    "name:slv_x_preferred":[
        "Bagod"
    ],
    "name:vie_x_preferred":[
        "Bagod"
    ],
    "name:zho_x_preferred":[
        "\u9c8d\u6208\u5fb7"
    ],
    "wof:name":"Bagod",
    "wof:placetype":"locality"
},
  "geometry": {"coordinates":[76.25341,24.73097000000001],"type":"Point"}
}