{
  "type": "Feature",
  "properties": {
    "iso:country":"IN",
    "ks:ks_alt_nam":"Chakkinkal palla",
    "ks:ks_name":"Chakkinkal Palla",
    "ks:ks_pop":260,
    "ks:ks_type":"HABITATION",
    "name:eng_x_preferred":[
        "Chakkinkal Palla"
    ],
    "wof:name":"Chakkinkal Palla",
    "wof:placetype":"locality",
    "wof:population":260
},
  "geometry": {"coordinates":[76.71068,10.732453],"type":"Point"}
}