{
  "type": "Feature",
  "properties": {
    "iso:country":"IN",
    "ks:ks_name":"Doblya",
    "ks:ks_pop":77,
    "ks:ks_type":"HABITATION",
    "name:eng_x_preferred":[
        "Doblya"
    ],
    "wof:name":"Doblya",
    "wof:placetype":"locality",
    "wof:population":77
},
  "geometry": {"coordinates":[78.69302999999999,30.296081],"type":"Point"}
}