{
  "type": "Feature",
  "properties": {
    "iso:country":"IN",
    "ks:ks_name":"Kisiri",
    "ks:ks_pop":236,
    "ks:ks_type":"VILLAGE",
    "name:eng_x_preferred":[
        "Kisiri"
    ],
    "wof:name":"Kisiri",
    "wof:placetype":"locality",
    "wof:population":236
},
  "geometry": {"coordinates":[83.611722,19.241811],"type":"Point"}
}