{
  "type": "Feature",
  "properties": {
    "gn:admin1_code":"11",
    "gn:admin2_code":"23.0",
    "gn:asciiname":"Chara",
    "gn:country_code":"IN",
    "gn:dem":1894,
    "gn:feature_class":"P",
    "gn:feature_code":"PPL",
    "gn:name":"Chara",
    "gn:population":0,
    "gn:timezone":"Asia/Kolkata",
    "iso:country":"IN",
    "name:ara_x_preferred":[
        "\u062a\u0634\u0627\u0631\u0627"
    ],
    "name:ben_x_preferred":[
        "\u099a\u09be\u09b0\u09be"
    ],
    "name:ceb_x_preferred":[
        "Chara"
    ],
    "name:deu_x_preferred":[
        "Chara"
    ],
    "name:ell_x_preferred":[
        "\u03a7\u03b1\u03c1\u03ac"
    ],
    "name:fas_x_preferred":[
        "\u0686\u0627\u0631\u0627"
    ],
    "name:fin_x_preferred":[
        "Chara"
    ],
    "name:fra_x_preferred":[
        "Chara"
    ],
    "name:heb_x_preferred":[
        "\u05e6'\u05d0\u05e8\u05d4"
    ],
    "name:hin_x_preferred":[
        "\u091a\u093e\u0930\u093e"
    ],
    "name:hrv_x_preferred":[
        "Chara"
    ],
    "name:ind_x_preferred":[
        "Chara"
    ],
    "name:ita_x_preferred":[
        "Chara"
    ],
    "name:jpn_x_preferred":[
        "Chara"
    ],
    "name:por_x_preferred":[
        "Tchara"
    ],
    "name:rus_x_preferred":[
        "\u0427\u0430\u0440\u0430"
    ],
    "name:slk_x_preferred":[
        "Chara"
    ],
    "name:spa_x_preferred":[
        "Chara"
    ],
    "name:swe_x_preferred":[
        "Chara"
    ],
    "name:tur_x_preferred":[
        "Chara"
    ],
    "name:ukr_x_preferred":[
        "\u0427\u0430\u0440\u0430"
    ],
    "name:urd_x_preferred":[
        "\u0686\u0627\u0631\u0627"
    ],
    "name:vie_x_preferred":[
        "S\u00f4ng Chara"
    ],
    "wof:name":"Chara",
    "wof:placetype":"locality"
},
  "geometry": {"coordinates":[76.17138,32.7964],"type":"Point"}
}