{
  "type": "Feature",
  "properties": {
    "iso:country":"IN",
    "ks:ks_name":"Parbatipur",
    "ks:ks_pop":203,
    "ks:ks_type":"VILLAGE",
    "ks:ks_uagg_main":0,
    "name:eng_x_preferred":[
        "Parbatipur"
    ],
    "wof:name":"Parbatipur",
    "wof:placetype":"neighbourhood",
    "wof:population":203
},
  "geometry": {"coordinates":[88.01533000000001,22.011896],"type":"Point"}
}