{
  "type": "Feature",
  "properties": {
    "iso:country":"IN",
    "ks:ks_name":"Tenkabylu",
    "ks:ks_pop":543,
    "ks:ks_type":"VILLAGE",
    "name:eng_x_preferred":[
        "Tenkabylu"
    ],
    "wof:name":"Tenkabylu",
    "wof:placetype":"locality",
    "wof:population":543
},
  "geometry": {"coordinates":[75.108296,13.752408],"type":"Point"}
}