{
  "type": "Feature",
  "properties": {
    "iso:country":"IN",
    "ks:ks_alt_nam":"Kut\u012bb\u0101ri",
    "ks:ks_name":"Kutibari",
    "ks:ks_pop":51,
    "ks:ks_type":"VILLAGE",
    "name:eng_x_preferred":[
        "Kutibari"
    ],
    "name:eng_x_variant":[
        "Kut\u012bb\u0101ri"
    ],
    "wof:name":"Kutibari",
    "wof:placetype":"locality",
    "wof:population":51
},
  "geometry": {"coordinates":[84.28128100000001,20.650117],"type":"Point"}
}