{
  "type": "Feature",
  "properties": {
    "iso:country":"IN",
    "ks:ks_name":"Majari",
    "ks:ks_pop":12,
    "ks:ks_type":"VILLAGE",
    "ks:ks_uagg_main":0,
    "name:eng_x_preferred":[
        "Majari"
    ],
    "wof:name":"Majari",
    "wof:placetype":"neighbourhood",
    "wof:population":12
},
  "geometry": {"coordinates":[76.244556,31.081335],"type":"Point"}
}