{
  "type": "Feature",
  "properties": {
    "gn:admin1_code":"36",
    "gn:admin2_code":"199.0",
    "gn:asciiname":"Misrauli",
    "gn:country_code":"IN",
    "gn:dem":106,
    "gn:feature_class":"P",
    "gn:feature_code":"PPL",
    "gn:name":"Misrauli",
    "gn:population":0,
    "gn:timezone":"Asia/Kolkata",
    "iso:country":"IN",
    "ks:ks_name":"Mishrauli",
    "ks:ks_pop":177,
    "ks:ks_type":"HABITATION",
    "name:eng_x_preferred":[
        "Mishrauli"
    ],
    "name:eng_x_variant":[
        "Misrauli"
    ],
    "wof:name":"Mishrauli",
    "wof:placetype":"locality",
    "wof:population":177
},
  "geometry": {"coordinates":[82.67831700000001,25.060938],"type":"Point"}
}