{
  "type": "Feature",
  "properties": {
    "gn:admin1_code":"12.0",
    "gn:admin2_code":"17.0",
    "gn:asciiname":"Agmandi",
    "gn:country_code":"IN",
    "gn:dem":2795,
    "gn:feature_class":"P",
    "gn:feature_code":"PPL",
    "gn:name":"Agmandi",
    "gn:population":0,
    "gn:timezone":"Asia/Kolkata",
    "iso:country":"IN",
    "wof:name":"Agmandi",
    "wof:placetype":"locality"
},
  "geometry": {"coordinates":[75.29433,33.39909],"type":"Point"}
}