{
  "type": "Feature",
  "properties": {
    "gn:admin1_code":"24.0",
    "gn:admin2_code":"104.0",
    "gn:asciiname":"Jaitpur",
    "gn:country_code":"IN",
    "gn:dem":286,
    "gn:feature_class":"P",
    "gn:feature_code":"PPL",
    "gn:name":"Jaitpur",
    "gn:population":0,
    "gn:timezone":"Asia/Kolkata",
    "iso:country":"IN",
    "name:ara_x_preferred":[
        "\u062c\u0627\u064a\u0628\u0648\u0631"
    ],
    "name:ben_bn_x_preferred":[
        "\u099c\u09be\u0987\u09a4\u09aa\u09c1\u09b0"
    ],
    "name:ben_in_x_preferred":[
        "\u099c\u09be\u0987\u09a4\u09aa\u09c1\u09b0"
    ],
    "name:fra_x_preferred":[
        "Jaitpur"
    ],
    "name:guj_x_preferred":[
        "\u0a9c\u0ac8\u0aa4\u0aaa\u0ac1\u0ab0"
    ],
    "name:hin_x_preferred":[
        "\u091c\u0948\u0924\u092a\u0941\u0930"
    ],
    "name:kan_x_preferred":[
        "\u0c9c\u0cc8\u0ca4\u0ccd\u0caa\u0cc1\u0cb0"
    ],
    "name:mal_x_preferred":[
        "\u0d1c\u0d2f\u0d4d\u0d24\u0d4d\u0d2a\u0d42\u0d7c"
    ],
    "name:mar_x_preferred":[
        "\u091c\u0948\u0924\u092a\u0942\u0930"
    ],
    "name:pan_x_preferred":[
        "\u0a1c\u0a48\u0a24\u0a2a\u0a41\u0a30"
    ],
    "name:tam_x_preferred":[
        "\u0b9c\u0bc8\u0b9f\u0bcd\u0baa\u0bc2\u0bb0\u0bcd"
    ],
    "name:tel_x_preferred":[
        "\u0c1c\u0c48\u0c24\u0c4d"
    ],
    "name:urd_x_preferred":[
        "\u062c\u06cc\u062a \u067e\u0648\u0631"
    ],
    "name:urd_x_variant":[
        "\u062c\u06cc\u062a\u067e\u0648\u0631"
    ],
    "wof:name":"Jaitpur",
    "wof:placetype":"locality"
},
  "geometry": {"coordinates":[76.32800999999998,28.15633],"type":"Point"}
}