{
  "type": "Feature",
  "properties": {
    "iso:country":"IN",
    "ks:ks_alt_nam":"TAKALEKAR VASTI",
    "ks:ks_name":"Takalekar Vasti",
    "ks:ks_pop":304,
    "ks:ks_type":"HABITATION",
    "name:eng_x_preferred":[
        "Takalekar Vasti"
    ],
    "wof:name":"Takalekar Vasti",
    "wof:placetype":"locality",
    "wof:population":304
},
  "geometry": {"coordinates":[74.755634,16.744927],"type":"Point"}
}