{
  "type": "Feature",
  "properties": {
    "iso:country":"IN",
    "ks:ks_alt_nam":"Sr\u012bpar\u0101nkusanall\u016br",
    "ks:ks_name":"Sriparankusanallur",
    "ks:ks_pop":1663,
    "ks:ks_type":"VILLAGE",
    "ks:ks_uagg_main":0,
    "name:eng_x_preferred":[
        "Sriparankusanallur"
    ],
    "name:eng_x_variant":[
        "Sr\u012bpar\u0101nkusanall\u016br"
    ],
    "wof:name":"Sriparankusanallur",
    "wof:placetype":"neighbourhood",
    "wof:population":1663
},
  "geometry": {"coordinates":[77.918279,8.624714],"type":"Point"}
}