{
  "type": "Feature",
  "properties": {
    "iso:country":"IN",
    "ks:ks_alt_nam":"Al-Ameen",
    "ks:ks_name":"Al-ameen",
    "ks:ks_pop":1978,
    "ks:ks_type":"HABITATION",
    "name:eng_x_preferred":[
        "Al-ameen"
    ],
    "wof:name":"Al-ameen",
    "wof:placetype":"locality",
    "wof:population":1978
},
  "geometry": {"coordinates":[76.36862499999999,10.070418],"type":"Point"}
}