{
  "type": "Feature",
  "properties": {
    "iso:country":"IN",
    "ks:ks_name":"Bhalgora",
    "ks:ks_pop":362,
    "ks:ks_type":"VILLAGE",
    "name:eng_x_preferred":[
        "Bhalgora"
    ],
    "wof:name":"Bhalgora",
    "wof:placetype":"locality",
    "wof:population":362
},
  "geometry": {"coordinates":[87.40715299999999,24.958108],"type":"Point"}
}