{
  "type": "Feature",
  "properties": {
    "gn:admin1_code":"34.0",
    "gn:admin2_code":"220.0",
    "gn:asciiname":"Paharpur Bishunpur",
    "gn:country_code":"IN",
    "gn:dem":51,
    "gn:feature_class":"P",
    "gn:feature_code":"PPL",
    "gn:name":"Pah\u0101rpur Bishunpur",
    "gn:population":0,
    "gn:timezone":"Asia/Kolkata",
    "iso:country":"IN",
    "ks:ks_name":"Baharpur Bishunpur",
    "ks:ks_pop":4824,
    "ks:ks_type":"VILLAGE",
    "name:eng_x_preferred":[
        "Baharpur Bishunpur"
    ],
    "name:eng_x_variant":[
        "Paharpur Bishunpur"
    ],
    "wof:name":"Baharpur Bishunpur",
    "wof:placetype":"locality",
    "wof:population":4824
},
  "geometry": {"coordinates":[85.493358,25.647367],"type":"Point"}
}