{
  "type": "Feature",
  "properties": {
    "gn:admin1_code":"13.0",
    "gn:admin2_code":"600.0",
    "gn:asciiname":"Kaitodu",
    "gn:country_code":"IN",
    "gn:dem":72,
    "gn:feature_class":"P",
    "gn:feature_code":"PPL",
    "gn:name":"Kaitodu",
    "gn:population":0,
    "gn:timezone":"Asia/Kolkata",
    "iso:country":"IN",
    "ks:ks_name":"Kaithodu",
    "ks:ks_pop":365,
    "ks:ks_type":"HABITATION",
    "ks:ks_uagg_main":0,
    "name:eng_x_preferred":[
        "Kaithodu"
    ],
    "wof:name":"Kaithodu",
    "wof:placetype":"neighbourhood",
    "wof:population":365
},
  "geometry": {"coordinates":[76.858941,8.831254],"type":"Point"}
}