{
  "type": "Feature",
  "properties": {
    "gn:admin1_code":"38.0",
    "gn:admin2_code":"347.0",
    "gn:asciiname":"Dagdiria",
    "gn:country_code":"IN",
    "gn:dem":416,
    "gn:feature_class":"P",
    "gn:feature_code":"PPL",
    "gn:name":"Dagdiri\u0101",
    "gn:population":0,
    "gn:timezone":"Asia/Kolkata",
    "iso:country":"IN",
    "name:und_x_variant":[
        "Dagdiri\u0101",
        "Burh\u012b"
    ],
    "wof:name":"Dagdiria",
    "wof:placetype":"locality"
},
  "geometry": {"coordinates":[84.66121,24.06957],"type":"Point"}
}