{
  "type": "Feature",
  "properties": {
    "iso:country":"IN",
    "ks:ks_name":"Nukyadi",
    "ks:ks_pop":78,
    "ks:ks_type":"HABITATION",
    "name:eng_x_preferred":[
        "Nukyadi"
    ],
    "wof:name":"Nukyadi",
    "wof:placetype":"locality",
    "wof:population":78
},
  "geometry": {"coordinates":[74.830017,13.650262],"type":"Point"}
}