{
  "type": "Feature",
  "properties": {
    "iso:country":"IN",
    "ks:ks_name":"Salaiya Ryt",
    "ks:ks_pop":244,
    "ks:ks_type":"HABITATION",
    "name:eng_x_preferred":[
        "Salaiya Ryt"
    ],
    "wof:name":"Salaiya Ryt",
    "wof:placetype":"locality",
    "wof:population":244
},
  "geometry": {"coordinates":[80.946073,22.903165],"type":"Point"}
}