{
  "type": "Feature",
  "properties": {
    "iso:country":"IN",
    "ks:ks_name":"Bhogdabri Kesharibari",
    "ks:ks_pop":2789,
    "ks:ks_type":"VILLAGE",
    "name:eng_x_preferred":[
        "Bhogdabri Kesharibari"
    ],
    "wof:name":"Bhogdabri Kesharibari",
    "wof:placetype":"locality",
    "wof:population":2789
},
  "geometry": {"coordinates":[89.361485,26.285264],"type":"Point"}
}