{
  "type": "Feature",
  "properties": {
    "iso:country":"IN",
    "ks:ks_alt_nam":"Sag pada",
    "ks:ks_name":"Sag Pada",
    "ks:ks_pop":185,
    "ks:ks_type":"HABITATION",
    "name:eng_x_preferred":[
        "Sag Pada"
    ],
    "wof:name":"Sag Pada",
    "wof:placetype":"locality",
    "wof:population":185
},
  "geometry": {"coordinates":[73.050172,19.914161],"type":"Point"}
}