{
  "type": "Feature",
  "properties": {
    "iso:country":"IN",
    "ks:ks_name":"Sunnapu Kota",
    "ks:ks_pop":37,
    "ks:ks_type":"HABITATION",
    "name:eng_x_preferred":[
        "Sunnapu Kota"
    ],
    "wof:name":"Sunnapu Kota",
    "wof:placetype":"locality",
    "wof:population":37
},
  "geometry": {"coordinates":[82.502369,18.340921],"type":"Point"}
}