{
  "type": "Feature",
  "properties": {
    "iso:country":"IN",
    "ks:ks_name":"Jarang",
    "ks:ks_pop":136,
    "ks:ks_type":"VILLAGE",
    "name:eng_x_preferred":[
        "Jarang"
    ],
    "wof:name":"Jarang",
    "wof:placetype":"locality",
    "wof:population":136
},
  "geometry": {"coordinates":[83.960267,20.201235],"type":"Point"}
}