{
  "type": "Feature",
  "properties": {
    "iso:country":"IN",
    "ks:ks_alt_nam":"Pu Mambakkam ADC",
    "ks:ks_name":"Pu Mambakkam Adc",
    "ks:ks_pop":474,
    "ks:ks_type":"HABITATION",
    "name:eng_x_preferred":[
        "Pu Mambakkam Adc"
    ],
    "wof:name":"Pu Mambakkam Adc",
    "wof:placetype":"locality",
    "wof:population":474
},
  "geometry": {"coordinates":[79.31535700000001,11.664496],"type":"Point"}
}