{
  "type": "Feature",
  "properties": {
    "iso:country":"IN",
    "ks:ks_name":"Radhanagar Purba",
    "ks:ks_pop":3771,
    "ks:ks_type":"VILLAGE",
    "name:eng_x_preferred":[
        "Radhanagar Purba"
    ],
    "wof:name":"Radhanagar Purba",
    "wof:placetype":"locality",
    "wof:population":3771
},
  "geometry": {"coordinates":[88.876518,22.261518],"type":"Point"}
}