{
  "type": "Feature",
  "properties": {
    "iso:country":"IN",
    "ks:ks_name":"Dibbagangulapalem",
    "ks:ks_pop":64,
    "ks:ks_type":"HABITATION",
    "name:eng_x_preferred":[
        "Dibbagangulapalem"
    ],
    "wof:name":"Dibbagangulapalem",
    "wof:placetype":"locality",
    "wof:population":64
},
  "geometry": {"coordinates":[82.706519,17.398197],"type":"Point"}
}