{
  "type": "Feature",
  "properties": {
    "gn:admin1_code":"36.0",
    "gn:admin2_code":"195.0",
    "gn:asciiname":"Hardia",
    "gn:country_code":"IN",
    "gn:dem":76,
    "gn:feature_class":"P",
    "gn:feature_code":"PPL",
    "gn:name":"Hardi\u0101",
    "gn:population":0,
    "gn:timezone":"Asia/Kolkata",
    "iso:country":"IN",
    "wof:name":"Hardia",
    "wof:placetype":"locality"
},
  "geometry": {"coordinates":[83.6566,25.67786],"type":"Point"}
}