{
  "type": "Feature",
  "properties": {
    "iso:country":"IN",
    "ks:ks_name":"Bhadrapur",
    "ks:ks_pop":25,
    "ks:ks_type":"HABITATION",
    "name:eng_x_preferred":[
        "Bhadrapur"
    ],
    "wof:name":"Bhadrapur",
    "wof:placetype":"locality",
    "wof:population":25
},
  "geometry": {"coordinates":[74.820364,14.947355],"type":"Point"}
}