{
  "type": "Feature",
  "properties": {
    "gn:admin1_code":"16.0",
    "gn:admin2_code":"509.0",
    "gn:asciiname":"Agarjnari",
    "gn:country_code":"IN",
    "gn:dem":229,
    "gn:feature_class":"P",
    "gn:feature_code":"PPL",
    "gn:name":"\u0100garjnari",
    "gn:population":0,
    "gn:timezone":"Asia/Kolkata",
    "iso:country":"IN",
    "name:und_x_variant":[
        "\u0100garjnari",
        "Agarihari"
    ],
    "wof:name":"Agarjnari",
    "wof:placetype":"locality"
},
  "geometry": {"coordinates":[79.32769999999999,20.10889],"type":"Point"}
}