{
  "type": "Feature",
  "properties": {
    "iso:country":"IN",
    "ks:ks_name":"3 AM-A",
    "ks:ks_pop":135,
    "ks:ks_type":"VILLAGE",
    "name:eng_x_preferred":[
        "3 AM-A"
    ],
    "wof:name":"3 AM-A",
    "wof:placetype":"locality",
    "wof:population":135
},
  "geometry": {"coordinates":[72.98780499999999,29.067333],"type":"Point"}
}