{
  "type": "Feature",
  "properties": {
    "iso:country":"IN",
    "ks:ks_name":"Uttar Simulia",
    "ks:ks_pop":943,
    "ks:ks_type":"HABITATION",
    "name:eng_x_preferred":[
        "Uttar Simulia"
    ],
    "wof:name":"Uttar Simulia",
    "wof:placetype":"locality",
    "wof:population":943
},
  "geometry": {"coordinates":[87.535245,21.679072],"type":"Point"}
}