{
  "type": "Feature",
  "properties": {
    "gn:admin1_code":"35.0",
    "gn:admin2_code":"446.0",
    "gn:asciiname":"Simaria",
    "gn:country_code":"IN",
    "gn:dem":327,
    "gn:feature_class":"P",
    "gn:feature_code":"PPL",
    "gn:name":"Simaria",
    "gn:population":0,
    "gn:timezone":"Asia/Kolkata",
    "iso:country":"IN",
    "wof:name":"Simaria",
    "wof:placetype":"locality"
},
  "geometry": {"coordinates":[78.35916,23.06574],"type":"Point"}
}