{
  "type": "Feature",
  "properties": {
    "iso:country":"IN",
    "ks:ks_name":"Amadau",
    "ks:ks_pop":168,
    "ks:ks_type":"VILLAGE",
    "name:eng_x_preferred":[
        "Amadau"
    ],
    "wof:name":"Amadau",
    "wof:placetype":"locality",
    "wof:population":168
},
  "geometry": {"coordinates":[79.659295,29.304327],"type":"Point"}
}