{
  "type": "Feature",
  "properties": {
    "gn:admin1_code":"24.0",
    "gn:admin2_code":"107.0",
    "gn:asciiname":"Anandgarh",
    "gn:country_code":"IN",
    "gn:dem":273,
    "gn:feature_class":"P",
    "gn:feature_code":"PPL",
    "gn:name":"\u0100nandgarh",
    "gn:population":0,
    "gn:timezone":"Asia/Kolkata",
    "iso:country":"IN",
    "wof:name":"Anandgarh",
    "wof:placetype":"locality"
},
  "geometry": {"coordinates":[76.96011,26.51074],"type":"Point"}
}