{
  "type": "Feature",
  "properties": {
    "iso:country":"IN",
    "ks:ks_name":"Jokhu Chak",
    "ks:ks_pop":49,
    "ks:ks_type":"VILLAGE",
    "ks:ks_uagg_main":0,
    "name:eng_x_preferred":[
        "Jokhu Chak"
    ],
    "wof:name":"Jokhu Chak",
    "wof:placetype":"neighbourhood",
    "wof:population":49
},
  "geometry": {"coordinates":[82.359993,25.204334],"type":"Point"}
}