{
  "type": "Feature",
  "properties": {
    "iso:country":"IN",
    "ks:ks_name":"Tadpada Falia",
    "ks:ks_pop":135,
    "ks:ks_type":"HABITATION",
    "name:eng_x_preferred":[
        "Tadpada Falia"
    ],
    "wof:name":"Tadpada Falia",
    "wof:placetype":"locality",
    "wof:population":135
},
  "geometry": {"coordinates":[73.15738899999999,20.251361],"type":"Point"}
}