{
  "type": "Feature",
  "properties": {
    "iso:country":"IN",
    "ks:ks_name":"Thar Nai Abadi",
    "ks:ks_pop":90,
    "ks:ks_type":"HABITATION",
    "name:eng_x_preferred":[
        "Thar Nai Abadi"
    ],
    "wof:name":"Thar Nai Abadi",
    "wof:placetype":"locality",
    "wof:population":90
},
  "geometry": {"coordinates":[78.402613,27.191323],"type":"Point"}
}