{
  "type": "Feature",
  "properties": {
    "gn:admin1_code":"24.0",
    "gn:admin2_code":"123.0",
    "gn:asciiname":"Akhaigarh",
    "gn:country_code":"IN",
    "gn:dem":523,
    "gn:feature_class":"P",
    "gn:feature_code":"PPL",
    "gn:name":"Akhaigarh",
    "gn:population":0,
    "gn:timezone":"Asia/Kolkata",
    "iso:country":"IN",
    "ks:ks_name":"Akhegarh",
    "ks:ks_pop":308,
    "ks:ks_type":"VILLAGE",
    "name:eng_x_preferred":[
        "Akhegarh"
    ],
    "name:eng_x_variant":[
        "Akhaigarh"
    ],
    "wof:name":"Akhegarh",
    "wof:placetype":"locality",
    "wof:population":308
},
  "geometry": {"coordinates":[74.29652,25.949642],"type":"Point"}
}