{
  "type": "Feature",
  "properties": {
    "iso:country":"IN",
    "ks:ks_name":"Sarik Teron",
    "ks:ks_pop":87,
    "ks:ks_type":"HABITATION",
    "ks:ks_uagg_main":0,
    "name:eng_x_preferred":[
        "Sarik Teron"
    ],
    "wof:name":"Sarik Teron",
    "wof:placetype":"neighbourhood",
    "wof:population":87
},
  "geometry": {"coordinates":[93.090896,26.255362],"type":"Point"}
}