{
  "type": "Feature",
  "properties": {
    "gn:admin1_code":"39.0",
    "gn:admin2_code":"63.0",
    "gn:asciiname":"Lakhni",
    "gn:country_code":"IN",
    "gn:dem":1380,
    "gn:feature_class":"P",
    "gn:feature_code":"PPL",
    "gn:name":"Lakhni",
    "gn:population":0,
    "gn:timezone":"Asia/Kolkata",
    "iso:country":"IN",
    "ks:ks_name":"Lakhani",
    "ks:ks_pop":1313,
    "ks:ks_type":"VILLAGE",
    "name:eng_x_preferred":[
        "Lakhani"
    ],
    "name:eng_x_variant":[
        "Lakhni"
    ],
    "name:urd_x_preferred":[
        "\u0644\u06a9\u06be\u0646\u06cc"
    ],
    "wof:name":"Lakhani",
    "wof:placetype":"locality",
    "wof:population":1313
},
  "geometry": {"coordinates":[79.649582,29.863205],"type":"Point"}
}