{
  "type": "Feature",
  "properties": {
    "iso:country":"IN",
    "ks:ks_name":"Sashpara",
    "ks:ks_pop":4051,
    "ks:ks_type":"VILLAGE",
    "ks:ks_uagg_main":0,
    "name:eng_x_preferred":[
        "Sashpara"
    ],
    "wof:name":"Sashpara",
    "wof:placetype":"locality",
    "wof:population":4051
},
  "geometry": {"coordinates":[88.067866,23.953839],"type":"Point"}
}