{
  "type": "Feature",
  "properties": {
    "iso:country":"IN",
    "ks:ks_name":"Alkuni",
    "ks:ks_pop":14,
    "ks:ks_type":"HABITATION",
    "name:eng_x_preferred":[
        "Alkuni"
    ],
    "wof:name":"Alkuni",
    "wof:placetype":"locality",
    "wof:population":14
},
  "geometry": {"coordinates":[74.66919900000001,14.380971],"type":"Point"}
}