{
  "type": "Feature",
  "properties": {
    "gn:admin1_code":"29.0",
    "gn:admin2_code":"244.0",
    "gn:asciiname":"Dikling",
    "gn:country_code":"IN",
    "gn:dem":1615,
    "gn:feature_class":"P",
    "gn:feature_code":"PPL",
    "gn:name":"Dikling",
    "gn:population":0,
    "gn:timezone":"Asia/Kolkata",
    "iso:country":"IN",
    "wof:name":"Dikling",
    "wof:placetype":"locality"
},
  "geometry": {"coordinates":[88.58065999999999,27.23304000000001],"type":"Point"}
}