{
  "type": "Feature",
  "properties": {
    "gn:admin1_code":"12.0",
    "gn:asciiname":"Domel",
    "gn:country_code":"IN",
    "gn:dem":2585,
    "gn:feature_class":"P",
    "gn:feature_code":"PPL",
    "gn:name":"Domel",
    "gn:population":0,
    "gn:timezone":"Asia/Kolkata",
    "iso:country":"IN",
    "name:fas_x_preferred":[
        "\u062f\u0648\u0645\u06cc\u0644"
    ],
    "name:mar_x_preferred":[
        "\u0921\u094b\u092e\u0947\u0932"
    ],
    "name:urd_x_preferred":[
        "\u062f\u0648\u0645\u06cc\u0644"
    ],
    "wof:name":"Domel",
    "wof:placetype":"locality"
},
  "geometry": {"coordinates":[74.04058000000001,34.58644],"type":"Point"}
}