{
  "type": "Feature",
  "properties": {
    "iso:country":"IN",
    "ks:ks_alt_nam":"LACHHTMINPUR",
    "ks:ks_name":"Lachhtminpur",
    "ks:ks_pop":176,
    "ks:ks_type":"HABITATION",
    "name:eng_x_preferred":[
        "Lachhtminpur"
    ],
    "wof:name":"Lachhtminpur",
    "wof:placetype":"locality",
    "wof:population":176
},
  "geometry": {"coordinates":[83.243762,24.737963],"type":"Point"}
}