{
  "type": "Feature",
  "properties": {
    "iso:country":"IN",
    "ks:ks_name":"Bazar Para",
    "ks:ks_pop":372,
    "ks:ks_type":"HABITATION",
    "ks:ks_uagg_main":0,
    "name:eng_x_preferred":[
        "Bazar Para"
    ],
    "wof:name":"Bazar Para",
    "wof:placetype":"neighbourhood",
    "wof:population":372
},
  "geometry": {"coordinates":[91.459416,23.577475],"type":"Point"}
}