{
  "type": "Feature",
  "properties": {
    "iso:country":"IN",
    "ks:ks_name":"Timmaipalli",
    "ks:ks_type":"VILLAGE",
    "ks:ks_uagg_main":0,
    "name:eng_x_preferred":[
        "Timmaipalli"
    ],
    "wof:name":"Timmaipalli",
    "wof:placetype":"neighbourhood"
},
  "geometry": {"coordinates":[78.478821,17.978275],"type":"Point"}
}