{
  "type": "Feature",
  "properties": {
    "iso:country":"IN",
    "ks:ks_name":"Roha Goulwadi",
    "ks:ks_pop":270,
    "ks:ks_type":"HABITATION",
    "name:eng_x_preferred":[
        "Roha Goulwadi"
    ],
    "wof:name":"Roha Goulwadi",
    "wof:placetype":"locality",
    "wof:population":270
},
  "geometry": {"coordinates":[73.103875,18.437004],"type":"Point"}
}