{
  "type": "Feature",
  "properties": {
    "iso:country":"IN",
    "ks:ks_name":"Gopachari",
    "ks:ks_pop":0,
    "ks:ks_type":"VILLAGE",
    "name:eng_x_preferred":[
        "Gopachari"
    ],
    "wof:name":"Gopachari",
    "wof:placetype":"locality",
    "wof:population":0
},
  "geometry": {"coordinates":[72.969774,18.716686],"type":"Point"}
}