{
  "type": "Feature",
  "properties": {
    "iso:country":"IN",
    "ks:ks_name":"Gollavani Vanka",
    "ks:ks_pop":18,
    "ks:ks_type":"HABITATION",
    "name:eng_x_preferred":[
        "Gollavani Vanka"
    ],
    "wof:name":"Gollavani Vanka",
    "wof:placetype":"locality",
    "wof:population":18
},
  "geometry": {"coordinates":[79.09725,13.479406],"type":"Point"}
}