{
  "type": "Feature",
  "properties": {
    "iso:country":"IN",
    "ks:ks_name":"3 ASM",
    "ks:ks_pop":78,
    "ks:ks_type":"VILLAGE",
    "name:eng_x_preferred":[
        "3 ASM"
    ],
    "wof:name":"3 ASM",
    "wof:placetype":"locality",
    "wof:population":78
},
  "geometry": {"coordinates":[74.422149,29.30035],"type":"Point"}
}