{
  "type": "Feature",
  "properties": {
    "gn:admin1_code":"9.0",
    "gn:admin2_code":"492.0",
    "gn:asciiname":"Sosak",
    "gn:country_code":"IN",
    "gn:dem":10,
    "gn:feature_class":"P",
    "gn:feature_code":"PPL",
    "gn:name":"Sosak",
    "gn:population":0,
    "gn:timezone":"Asia/Kolkata",
    "iso:country":"IN",
    "wof:name":"Sosak",
    "wof:placetype":"locality"
},
  "geometry": {"coordinates":[72.75789,21.27366],"type":"Point"}
}