{
  "type": "Feature",
  "properties": {
    "gn:admin1_code":"23.0",
    "gn:admin2_code":"040",
    "gn:asciiname":"Bhadalthua",
    "gn:country_code":"IN",
    "gn:dem":264,
    "gn:feature_class":"P",
    "gn:feature_code":"PPL",
    "gn:name":"Bhadalthua",
    "gn:population":0,
    "gn:timezone":"Asia/Kolkata",
    "iso:country":"IN",
    "ks:ks_name":"Bhadalthua",
    "ks:ks_pop":2961,
    "ks:ks_type":"VILLAGE",
    "ks:ks_uagg_main":0,
    "name:eng_x_preferred":[
        "Bhadalthua"
    ],
    "wof:name":"Bhadalthua",
    "wof:placetype":"locality",
    "wof:population":2961
},
  "geometry": {"coordinates":[76.238052,30.589703],"type":"Point"}
}