{
  "type": "Feature",
  "properties": {
    "iso:country":"IN",
    "ks:ks_name":"Dethli",
    "ks:ks_pop":267,
    "ks:ks_type":"VILLAGE",
    "name:eng_x_preferred":[
        "Dethli"
    ],
    "wof:name":"Dethli",
    "wof:placetype":"locality",
    "wof:population":267
},
  "geometry": {"coordinates":[73.123943,21.237362],"type":"Point"}
}