{
  "type": "Feature",
  "properties": {
    "iso:country":"IN",
    "ks:ks_name":"Ugavatwadi",
    "ks:ks_pop":30,
    "ks:ks_type":"HABITATION",
    "name:eng_x_preferred":[
        "Ugavatwadi"
    ],
    "wof:name":"Ugavatwadi",
    "wof:placetype":"locality",
    "wof:population":30
},
  "geometry": {"coordinates":[73.58,17.06],"type":"Point"}
}