{
  "type": "Feature",
  "properties": {
    "iso:country":"IN",
    "ks:ks_name":"Chincholi",
    "ks:ks_type":"VILLAGE",
    "name:eng_x_preferred":[
        "Chincholi"
    ],
    "wof:name":"Chincholi",
    "wof:placetype":"locality"
},
  "geometry": {"coordinates":[78.08066100000001,20.05026],"type":"Point"}
}