{
  "type": "Feature",
  "properties": {
    "iso:country":"IN",
    "ks:ks_name":"Vank Falia",
    "ks:ks_pop":775,
    "ks:ks_type":"HABITATION",
    "name:eng_x_preferred":[
        "Vank Falia"
    ],
    "wof:name":"Vank Falia",
    "wof:placetype":"locality",
    "wof:population":775
},
  "geometry": {"coordinates":[74.12050000000001,23.023889],"type":"Point"}
}