{
  "type": "Feature",
  "properties": {
    "iso:country":"IN",
    "ks:ks_name":"Jambhulpada",
    "ks:ks_pop":78,
    "ks:ks_type":"HABITATION",
    "ks:ks_uagg_main":0,
    "name:eng_x_preferred":[
        "Jambhulpada"
    ],
    "wof:name":"Jambhulpada",
    "wof:placetype":"neighbourhood",
    "wof:population":78
},
  "geometry": {"coordinates":[72.89518700000001,19.327917],"type":"Point"}
}