{
  "type": "Feature",
  "properties": {
    "iso:country":"IN",
    "ks:ks_name":"Rinchha Falia",
    "ks:ks_pop":654,
    "ks:ks_type":"HABITATION",
    "name:eng_x_preferred":[
        "Rinchha Falia"
    ],
    "wof:name":"Rinchha Falia",
    "wof:placetype":"locality",
    "wof:population":654
},
  "geometry": {"coordinates":[73.607483,22.630983],"type":"Point"}
}