{
  "type": "Feature",
  "properties": {
    "iso:country":"IN",
    "ks:ks_name":"Harijana Nuasahi",
    "ks:ks_pop":20,
    "ks:ks_type":"HABITATION",
    "name:eng_x_preferred":[
        "Harijana Nuasahi"
    ],
    "wof:name":"Harijana Nuasahi",
    "wof:placetype":"locality",
    "wof:population":20
},
  "geometry": {"coordinates":[84.844752,20.275364],"type":"Point"}
}