{
  "type": "Feature",
  "properties": {
    "iso:country":"IN",
    "ks:ks_name":"Jagadishpur",
    "ks:ks_pop":329,
    "ks:ks_type":"VILLAGE",
    "name:eng_x_preferred":[
        "Jagadishpur"
    ],
    "wof:name":"Jagadishpur",
    "wof:placetype":"locality",
    "wof:population":329
},
  "geometry": {"coordinates":[88.251721,25.276474],"type":"Point"}
}