{
  "type": "Feature",
  "properties": {
    "iso:country":"IN",
    "ks:ks_alt_nam":"BADHAN CH. PARA",
    "ks:ks_name":"Badhan Ch. Para",
    "ks:ks_pop":115,
    "ks:ks_type":"HABITATION",
    "name:eng_x_preferred":[
        "Badhan Ch. Para"
    ],
    "wof:name":"Badhan Ch. Para",
    "wof:placetype":"locality",
    "wof:population":115
},
  "geometry": {"coordinates":[91.720777,23.884353],"type":"Point"}
}