{
  "type": "Feature",
  "properties": {
    "iso:country":"IN",
    "ks:ks_name":"Araji Isopur",
    "ks:ks_pop":431,
    "ks:ks_type":"HABITATION",
    "name:eng_x_preferred":[
        "Araji Isopur"
    ],
    "wof:name":"Araji Isopur",
    "wof:placetype":"locality",
    "wof:population":431
},
  "geometry": {"coordinates":[83.13669400000001,25.533557],"type":"Point"}
}