{
  "type": "Feature",
  "properties": {
    "gn:admin1_code":"2.0",
    "gn:admin2_code":"551.0",
    "gn:asciiname":"Repalle",
    "gn:country_code":"IN",
    "gn:dem":206,
    "gn:feature_class":"P",
    "gn:feature_code":"PPL",
    "gn:name":"Repalle",
    "gn:population":0,
    "gn:timezone":"Asia/Kolkata",
    "iso:country":"IN",
    "ks:ks_name":"Repalli",
    "ks:ks_pop":173,
    "ks:ks_type":"HABITATION",
    "name:bpy_x_preferred":[
        "\u09b0\u09bf\u09aa\u09be\u09b2\u09cd\u09b2\u09c7"
    ],
    "name:ceb_x_preferred":[
        "Repalle"
    ],
    "name:eng_x_preferred":[
        "Repalli"
    ],
    "name:eng_x_variant":[
        "Repalle"
    ],
    "name:hif_x_preferred":[
        "Repalle"
    ],
    "name:ita_x_preferred":[
        "Repalle"
    ],
    "name:mar_x_preferred":[
        "\u0930\u0947\u092a\u0932\u094d\u0932\u0947"
    ],
    "name:msa_x_preferred":[
        "Repalle"
    ],
    "name:new_x_preferred":[
        "\u0930\u0947\u092a\u0932\u094d\u0932\u0947 \u092e\u0923\u094d\u0921\u0932"
    ],
    "name:ori_x_preferred":[
        "\u0b30\u0b47\u0b2a\u0b3e\u0b32\u0b4d\u0b32\u0b47"
    ],
    "name:pam_x_preferred":[
        "Repalle"
    ],
    "name:por_x_preferred":[
        "Repalle"
    ],
    "name:swe_x_preferred":[
        "Repalle"
    ],
    "name:tel_x_preferred":[
        "\u0c30\u0c47\u0c2a\u0c32\u0c4d\u0c32\u0c46"
    ],
    "name:vie_x_preferred":[
        "Repalle"
    ],
    "name:zho_x_preferred":[
        "\u96f7\u5e15\u5c14\u83b1"
    ],
    "wof:name":"Repalli",
    "wof:placetype":"locality",
    "wof:population":173
},
  "geometry": {"coordinates":[78.19841599999999,14.803814],"type":"Point"}
}