{
  "type": "Feature",
  "properties": {
    "iso:country":"IN",
    "ks:ks_name":"Gulariha",
    "ks:ks_pop":270,
    "ks:ks_type":"HABITATION",
    "name:eng_x_preferred":[
        "Gulariha"
    ],
    "wof:name":"Gulariha",
    "wof:placetype":"locality",
    "wof:population":270
},
  "geometry": {"coordinates":[83.159942,27.227139],"type":"Point"}
}