{
  "type": "Feature",
  "properties": {
    "gn:admin1_code":"36.0",
    "gn:admin2_code":"179.0",
    "gn:asciiname":"Sundarpur",
    "gn:country_code":"IN",
    "gn:dem":110,
    "gn:feature_class":"P",
    "gn:feature_code":"PPL",
    "gn:name":"Sundarpur",
    "gn:population":0,
    "gn:timezone":"Asia/Kolkata",
    "iso:country":"IN",
    "name:ceb_x_preferred":[
        "Sundarpur"
    ],
    "name:fra_x_preferred":[
        "Sundarpur"
    ],
    "name:ita_x_preferred":[
        "Sundarpur"
    ],
    "name:mai_x_preferred":[
        "\u0938\u0941\u0928\u094d\u0926\u0930\u092a\u0941\u0930"
    ],
    "name:new_x_preferred":[
        "\u0938\u0941\u0928\u094d\u0926\u0930\u092a\u0941\u0930"
    ],
    "name:pol_x_preferred":[
        "Sundarpur"
    ],
    "wof:name":"Sundarpur",
    "wof:placetype":"locality"
},
  "geometry": {"coordinates":[81.75079000000002,26.14465],"type":"Point"}
}