{
  "type": "Feature",
  "properties": {
    "iso:country":"IN",
    "ks:ks_name":"Shyampur",
    "ks:ks_pop":723,
    "ks:ks_type":"HABITATION",
    "name:eng_x_preferred":[
        "Shyampur"
    ],
    "wof:name":"Shyampur",
    "wof:placetype":"locality",
    "wof:population":723
},
  "geometry": {"coordinates":[86.150746,25.843687],"type":"Point"}
}