{
  "type": "Feature",
  "properties": {
    "iso:country":"IN",
    "ks:ks_name":"Shivnagar",
    "ks:ks_pop":763,
    "ks:ks_type":"VILLAGE",
    "name:eng_x_preferred":[
        "Shivnagar"
    ],
    "wof:name":"Shivnagar",
    "wof:placetype":"locality",
    "wof:population":763
},
  "geometry": {"coordinates":[82.78124800000001,22.877904],"type":"Point"}
}