{
  "type": "Feature",
  "properties": {
    "iso:country":"IN",
    "ks:ks_name":"Mainol",
    "ks:ks_pop":494,
    "ks:ks_type":"VILLAGE",
    "name:eng_x_preferred":[
        "Mainol"
    ],
    "wof:name":"Mainol",
    "wof:placetype":"locality",
    "wof:population":494
},
  "geometry": {"coordinates":[78.27811,30.673636],"type":"Point"}
}