{
  "type": "Feature",
  "properties": {
    "gn:admin1_code":"21",
    "gn:admin2_code":"396.0",
    "gn:asciiname":"Khaliaguda",
    "gn:country_code":"IN",
    "gn:dem":377,
    "gn:feature_class":"P",
    "gn:feature_code":"PPL",
    "gn:name":"Khaliaguda",
    "gn:population":0,
    "gn:timezone":"Asia/Kolkata",
    "iso:country":"IN",
    "ks:ks_name":"Khaliaguda",
    "ks:ks_pop":638,
    "ks:ks_type":"VILLAGE",
    "name:eng_x_preferred":[
        "Khaliaguda"
    ],
    "wof:name":"Khaliaguda",
    "wof:placetype":"locality",
    "wof:population":638
},
  "geometry": {"coordinates":[83.474749,19.944732],"type":"Point"}
}