{
  "type": "Feature",
  "properties": {
    "iso:country":"IN",
    "ks:ks_name":"Kutwa Talab",
    "ks:ks_pop":254,
    "ks:ks_type":"HABITATION",
    "name:eng_x_preferred":[
        "Kutwa Talab"
    ],
    "wof:name":"Kutwa Talab",
    "wof:placetype":"locality",
    "wof:population":254
},
  "geometry": {"coordinates":[82.446399,27.082702],"type":"Point"}
}