{
  "type": "Feature",
  "properties": {
    "iso:country":"IN",
    "ks:ks_name":"Dhalgaon",
    "ks:ks_pop":751,
    "ks:ks_type":"VILLAGE",
    "ks:ks_uagg_main":0,
    "name:eng_x_preferred":[
        "Dhalgaon"
    ],
    "wof:name":"Dhalgaon",
    "wof:placetype":"neighbourhood",
    "wof:population":751
},
  "geometry": {"coordinates":[88.119423,25.789237],"type":"Point"}
}