{
  "type": "Feature",
  "properties": {
    "gn:admin1_code":"37",
    "gn:admin2_code":"410.0",
    "gn:asciiname":"Tarajhar",
    "gn:country_code":"IN",
    "gn:dem":779,
    "gn:feature_class":"P",
    "gn:feature_code":"PPL",
    "gn:name":"T\u0101rajhar",
    "gn:population":0,
    "gn:timezone":"Asia/Kolkata",
    "iso:country":"IN",
    "wof:name":"Tarajhar",
    "wof:placetype":"locality"
},
  "geometry": {"coordinates":[82.40524000000001,20.28867],"type":"Point"}
}