{
  "type": "Feature",
  "properties": {
    "iso:country":"IN",
    "ks:ks_alt_nam":"KHON TOLA",
    "ks:ks_name":"Khon Tola",
    "ks:ks_pop":194,
    "ks:ks_type":"HABITATION",
    "ks:ks_uagg_main":0,
    "name:eng_x_preferred":[
        "Khon Tola"
    ],
    "wof:name":"Khon Tola",
    "wof:placetype":"neighbourhood",
    "wof:population":194
},
  "geometry": {"coordinates":[86.52193,26.09091],"type":"Point"}
}