{
  "type": "Feature",
  "properties": {
    "iso:country":"IN",
    "ks:ks_name":"Ludubandha",
    "ks:ks_pop":394,
    "ks:ks_type":"VILLAGE",
    "name:eng_x_preferred":[
        "Ludubandha"
    ],
    "wof:name":"Ludubandha",
    "wof:placetype":"locality",
    "wof:population":394
},
  "geometry": {"coordinates":[84.055643,20.033791],"type":"Point"}
}