{
  "type": "Feature",
  "properties": {
    "iso:country":"IN",
    "ks:ks_name":"Umedpura",
    "ks:ks_pop":140,
    "ks:ks_type":"VILLAGE",
    "name:eng_x_preferred":[
        "Umedpura"
    ],
    "wof:name":"Umedpura",
    "wof:placetype":"locality",
    "wof:population":140
},
  "geometry": {"coordinates":[72.86903599999999,24.030036],"type":"Point"}
}