{
  "type": "Feature",
  "properties": {
    "gn:admin1_code":"34.0",
    "gn:admin2_code":"213.0",
    "gn:asciiname":"Piprahi",
    "gn:country_code":"IN",
    "gn:dem":54,
    "gn:feature_class":"P",
    "gn:feature_code":"PPL",
    "gn:name":"Pipr\u0101hi",
    "gn:population":0,
    "gn:timezone":"Asia/Kolkata",
    "iso:country":"IN",
    "ks:ks_name":"Piprahi",
    "ks:ks_pop":526,
    "ks:ks_type":"VILLAGE",
    "ks:ks_uagg_main":0,
    "name:eng_x_preferred":[
        "Piprahi"
    ],
    "wof:name":"Piprahi",
    "wof:placetype":"neighbourhood",
    "wof:population":526
},
  "geometry": {"coordinates":[86.7863,26.064188],"type":"Point"}
}