{
  "type": "Feature",
  "properties": {
    "iso:country":"IN",
    "ks:ks_name":"Dhangarwada",
    "ks:ks_pop":143,
    "ks:ks_type":"HABITATION",
    "name:eng_x_preferred":[
        "Dhangarwada"
    ],
    "wof:name":"Dhangarwada",
    "wof:placetype":"locality",
    "wof:population":143
},
  "geometry": {"coordinates":[74.083856,16.372297],"type":"Point"}
}