{
  "type": "Feature",
  "properties": {
    "gn:admin1_code":"16.0",
    "gn:admin2_code":"528",
    "gn:asciiname":"Gothna",
    "gn:country_code":"IN",
    "gn:dem":905,
    "gn:feature_class":"P",
    "gn:feature_code":"PPL",
    "gn:name":"Gothna",
    "gn:population":0,
    "gn:timezone":"Asia/Kolkata",
    "iso:country":"IN",
    "wof:name":"Gothna",
    "wof:placetype":"locality"
},
  "geometry": {"coordinates":[73.76911,17.09752000000001],"type":"Point"}
}