{
  "type": "Feature",
  "properties": {
    "iso:country":"IN",
    "ks:ks_name":"Baghaura",
    "ks:ks_pop":951,
    "ks:ks_type":"HABITATION",
    "name:eng_x_preferred":[
        "Baghaura"
    ],
    "wof:name":"Baghaura",
    "wof:placetype":"locality",
    "wof:population":951
},
  "geometry": {"coordinates":[78.616428,24.972098],"type":"Point"}
}