{
  "type": "Feature",
  "properties": {
    "iso:country":"IN",
    "ks:ks_name":"Karekal",
    "ks:ks_pop":263,
    "ks:ks_type":"HABITATION",
    "name:eng_x_preferred":[
        "Karekal"
    ],
    "wof:name":"Karekal",
    "wof:placetype":"locality",
    "wof:population":263
},
  "geometry": {"coordinates":[77.04781,13.393401],"type":"Point"}
}