{
  "type": "Feature",
  "properties": {
    "iso:country":"IN",
    "ks:ks_name":"Panasaputtu",
    "ks:ks_pop":53,
    "ks:ks_type":"HABITATION",
    "name:eng_x_preferred":[
        "Panasaputtu"
    ],
    "wof:name":"Panasaputtu",
    "wof:placetype":"locality",
    "wof:population":53
},
  "geometry": {"coordinates":[82.59103399999999,18.213518],"type":"Point"}
}