{
  "type": "Feature",
  "properties": {
    "gn:admin1_code":"2.0",
    "gn:admin2_code":"554.0",
    "gn:asciiname":"Yenumulutimmapalli",
    "gn:country_code":"IN",
    "gn:dem":778,
    "gn:feature_class":"P",
    "gn:feature_code":"PPL",
    "gn:name":"Yenumulutimmapalli",
    "gn:population":0,
    "gn:timezone":"Asia/Kolkata",
    "iso:country":"IN",
    "wof:name":"Yenumulutimmapalli",
    "wof:placetype":"neighbourhood"
},
  "geometry": {"coordinates":[78.46048999999999,12.96072],"type":"Point"}
}