{
  "type": "Feature",
  "properties": {
    "iso:country":"IN",
    "ks:ks_name":"Bengdoba",
    "ks:ks_pop":380,
    "ks:ks_type":"VILLAGE",
    "name:eng_x_preferred":[
        "Bengdoba"
    ],
    "wof:name":"Bengdoba",
    "wof:placetype":"locality",
    "wof:population":380
},
  "geometry": {"coordinates":[87.561294,24.40466],"type":"Point"}
}