{
  "type": "Feature",
  "properties": {
    "iso:country":"IN",
    "ks:ks_name":"Tadpada",
    "ks:ks_pop":593,
    "ks:ks_type":"VILLAGE",
    "name:eng_x_preferred":[
        "Tadpada"
    ],
    "wof:name":"Tadpada",
    "wof:placetype":"locality",
    "wof:population":593
},
  "geometry": {"coordinates":[73.45399,20.758892],"type":"Point"}
}