{
  "type": "Feature",
  "properties": {
    "iso:country":"IN",
    "ks:ks_name":"Chilla Dera",
    "ks:ks_pop":326,
    "ks:ks_type":"HABITATION",
    "name:eng_x_preferred":[
        "Chilla Dera"
    ],
    "wof:name":"Chilla Dera",
    "wof:placetype":"locality",
    "wof:population":326
},
  "geometry": {"coordinates":[80.228188,25.711074],"type":"Point"}
}