{
  "type": "Feature",
  "properties": {
    "gn:admin1_code":"37",
    "gn:admin2_code":"403.0",
    "gn:asciiname":"Daukijor",
    "gn:country_code":"IN",
    "gn:dem":222,
    "gn:feature_class":"P",
    "gn:feature_code":"PPL",
    "gn:name":"Daukijor",
    "gn:population":0,
    "gn:timezone":"Asia/Kolkata",
    "iso:country":"IN",
    "wof:name":"Daukijor",
    "wof:placetype":"locality"
},
  "geometry": {"coordinates":[83.04443000000001,21.62279],"type":"Point"}
}