{
  "type": "Feature",
  "properties": {
    "iso:country":"IN",
    "ks:ks_name":"Chanian",
    "ks:ks_pop":0,
    "ks:ks_type":"VILLAGE",
    "name:eng_x_preferred":[
        "Chanian"
    ],
    "wof:name":"Chanian",
    "wof:placetype":"locality",
    "wof:population":0
},
  "geometry": {"coordinates":[75.67672899999999,31.004507],"type":"Point"}
}