{
  "type": "Feature",
  "properties": {
    "iso:country":"IN",
    "ks:ks_name":"Sahabad Pt II",
    "ks:ks_pop":1870,
    "ks:ks_type":"VILLAGE",
    "ks:ks_uagg_main":0,
    "name:eng_x_preferred":[
        "Sahabad Pt II"
    ],
    "wof:name":"Sahabad Pt II",
    "wof:placetype":"neighbourhood",
    "wof:population":1870
},
  "geometry": {"coordinates":[92.591714,24.485276],"type":"Point"}
}