{
  "type": "Feature",
  "properties": {
    "iso:country":"IN",
    "ks:ks_name":"Achampet",
    "ks:ks_pop":440,
    "ks:ks_type":"VILLAGE",
    "name:eng_x_preferred":[
        "Achampet"
    ],
    "wof:name":"Achampet",
    "wof:placetype":"locality",
    "wof:population":440
},
  "geometry": {"coordinates":[78.87222800000001,16.552368],"type":"Point"}
}