{
  "type": "Feature",
  "properties": {
    "iso:country":"IN",
    "ks:ks_name":"Nuagan",
    "ks:ks_pop":538,
    "ks:ks_type":"VILLAGE",
    "ks:ks_uagg_main":0,
    "name:eng_x_preferred":[
        "Nuagan"
    ],
    "wof:name":"Nuagan",
    "wof:placetype":"neighbourhood",
    "wof:population":538
},
  "geometry": {"coordinates":[86.125416,20.630871],"type":"Point"}
}