{
  "type": "Feature",
  "properties": {
    "gn:admin1_code":"19.0",
    "gn:admin2_code":"555.0",
    "gn:asciiname":"Chandgad",
    "gn:country_code":"IN",
    "gn:dem":753,
    "gn:feature_class":"P",
    "gn:feature_code":"PPL",
    "gn:name":"Chandgad",
    "gn:population":0,
    "gn:timezone":"Asia/Kolkata",
    "iso:country":"IN",
    "name:mar_x_preferred":[
        "\u091a\u0902\u0926\u0917\u0921"
    ],
    "name:vie_x_preferred":[
        "Chandgad"
    ],
    "wof:name":"Chandgad",
    "wof:placetype":"locality"
},
  "geometry": {"coordinates":[74.60973,15.90804],"type":"Point"}
}