{
  "type": "Feature",
  "properties": {
    "iso:country":"IN",
    "ks:ks_name":"Harvegudem",
    "ks:ks_pop":136,
    "ks:ks_type":"VILLAGE",
    "name:eng_x_preferred":[
        "Harvegudem"
    ],
    "wof:name":"Harvegudem",
    "wof:placetype":"locality",
    "wof:population":136
},
  "geometry": {"coordinates":[81.341606,17.737718],"type":"Point"}
}