{
  "type": "Feature",
  "properties": {
    "gn:admin1_code":"33",
    "gn:admin2_code":"585.0",
    "gn:asciiname":"Nadora",
    "gn:country_code":"IN",
    "gn:dem":95,
    "gn:feature_class":"P",
    "gn:feature_code":"PPL",
    "gn:name":"Nadora",
    "gn:population":0,
    "gn:timezone":"Asia/Kolkata",
    "iso:country":"IN",
    "ks:ks_name":"Nadora",
    "ks:ks_pop":1372,
    "ks:ks_type":"VILLAGE",
    "name:eng_x_preferred":[
        "Nadora"
    ],
    "wof:name":"Nadora",
    "wof:placetype":"locality",
    "wof:population":1372
},
  "geometry": {"coordinates":[73.874526,15.675375],"type":"Point"}
}