{
  "type": "Feature",
  "properties": {
    "iso:country":"IN",
    "ks:ks_name":"Mahammad Pur",
    "ks:ks_pop":776,
    "ks:ks_type":"VILLAGE",
    "name:eng_x_preferred":[
        "Mahammad Pur"
    ],
    "wof:name":"Mahammad Pur",
    "wof:placetype":"locality",
    "wof:population":776
},
  "geometry": {"coordinates":[86.326967,20.721887],"type":"Point"}
}