{
  "type": "Feature",
  "properties": {
    "iso:country":"IN",
    "ks:ks_name":"Bantolawa",
    "ks:ks_pop":174,
    "ks:ks_type":"HABITATION",
    "name:eng_x_preferred":[
        "Bantolawa"
    ],
    "wof:name":"Bantolawa",
    "wof:placetype":"locality",
    "wof:population":174
},
  "geometry": {"coordinates":[85.64099299999999,23.681688],"type":"Point"}
}