{
  "type": "Feature",
  "properties": {
    "iso:country":"IN",
    "ks:ks_name":"Mahkhowa",
    "ks:ks_pop":926,
    "ks:ks_type":"HABITATION",
    "name:eng_x_preferred":[
        "Mahkhowa"
    ],
    "wof:name":"Mahkhowa",
    "wof:placetype":"locality",
    "wof:population":926
},
  "geometry": {"coordinates":[95.069034,27.185936],"type":"Point"}
}