{
  "type": "Feature",
  "properties": {
    "gn:admin1_code":"36.0",
    "gn:admin2_code":"134.0",
    "gn:asciiname":"Khairullahpur",
    "gn:country_code":"IN",
    "gn:dem":239,
    "gn:feature_class":"P",
    "gn:feature_code":"PPL",
    "gn:name":"Khair\u016bllahpur",
    "gn:population":0,
    "gn:timezone":"Asia/Kolkata",
    "iso:country":"IN",
    "name:und_x_variant":[
        "Khair\u016bllahpur",
        "Mom\u012bnnagar"
    ],
    "wof:name":"Khairullahpur",
    "wof:placetype":"locality"
},
  "geometry": {"coordinates":[78.70044,29.44344],"type":"Point"}
}