{
  "type": "Feature",
  "properties": {
    "iso:country":"IN",
    "ks:ks_name":"Ethankadu",
    "ks:ks_pop":271,
    "ks:ks_type":"HABITATION",
    "ks:ks_uagg_main":0,
    "name:eng_x_preferred":[
        "Ethankadu"
    ],
    "wof:name":"Ethankadu",
    "wof:placetype":"neighbourhood",
    "wof:population":271
},
  "geometry": {"coordinates":[77.59397300000001,8.145645],"type":"Point"}
}