{
  "type": "Feature",
  "properties": {
    "iso:country":"IN",
    "ks:ks_name":"Parsau",
    "ks:ks_pop":1182,
    "ks:ks_type":"VILLAGE",
    "ks:ks_uagg_main":0,
    "name:eng_x_preferred":[
        "Parsau"
    ],
    "wof:name":"Parsau",
    "wof:placetype":"neighbourhood",
    "wof:population":1182
},
  "geometry": {"coordinates":[81.740751,26.850541],"type":"Point"}
}