{
  "type": "Feature",
  "properties": {
    "iso:country":"IN",
    "ks:ks_name":"Bagha",
    "ks:ks_pop":1272,
    "ks:ks_type":"VILLAGE",
    "ks:ks_uagg_main":0,
    "name:eng_x_preferred":[
        "Bagha"
    ],
    "wof:name":"Bagha",
    "wof:placetype":"neighbourhood",
    "wof:population":1272
},
  "geometry": {"coordinates":[87.909291,23.82741],"type":"Point"}
}