{
  "type": "Feature",
  "properties": {
    "gn:admin1_code":"24",
    "gn:admin2_code":"101.0",
    "gn:asciiname":"Udasar",
    "gn:country_code":"IN",
    "gn:dem":227,
    "gn:feature_class":"P",
    "gn:feature_code":"PPL",
    "gn:name":"\u016ad\u0101sar",
    "gn:population":0,
    "gn:timezone":"Asia/Kolkata",
    "iso:country":"IN",
    "ks:ks_alt_nam":"\u016ad\u0101sar",
    "ks:ks_name":"Udasar",
    "ks:ks_pop":7588,
    "ks:ks_type":"VILLAGE",
    "ks:ks_uagg_main":0,
    "name:und_x_variant":[
        "\u016ad\u0101sar",
        "Ud\u0101sar"
    ],
    "wof:name":"Udasar",
    "wof:placetype":"neighbourhood"
},
  "geometry": {"coordinates":[73.38162,28.04041],"type":"Point"}
}