{
  "type": "Feature",
  "properties": {
    "iso:country":"IN",
    "ks:ks_name":"Ethikkal Medu Attumali Street",
    "ks:ks_pop":520,
    "ks:ks_type":"HABITATION",
    "name:eng_x_preferred":[
        "Ethikkal Medu Attumali Street"
    ],
    "wof:name":"Ethikkal Medu Attumali Street",
    "wof:placetype":"locality",
    "wof:population":520
},
  "geometry": {"coordinates":[77.22125800000001,10.462675],"type":"Point"}
}