{
  "type": "Feature",
  "properties": {
    "iso:country":"IN",
    "ks:ks_name":"Padariya Heerachand",
    "ks:ks_pop":8,
    "ks:ks_type":"HABITATION",
    "name:eng_x_preferred":[
        "Padariya Heerachand"
    ],
    "wof:name":"Padariya Heerachand",
    "wof:placetype":"locality",
    "wof:population":8
},
  "geometry": {"coordinates":[78.376625,24.069184],"type":"Point"}
}