{
  "type": "Feature",
  "properties": {
    "iso:country":"IN",
    "ks:ks_name":"Lohargara",
    "ks:ks_pop":8,
    "ks:ks_type":"VILLAGE",
    "name:eng_x_preferred":[
        "Lohargara"
    ],
    "wof:name":"Lohargara",
    "wof:placetype":"locality",
    "wof:population":8
},
  "geometry": {"coordinates":[85.216211,24.228589],"type":"Point"}
}