{
  "type": "Feature",
  "properties": {
    "iso:country":"IN",
    "ks:ks_name":"Labanipada",
    "ks:ks_pop":433,
    "ks:ks_type":"VILLAGE",
    "name:eng_x_preferred":[
        "Labanipada"
    ],
    "wof:name":"Labanipada",
    "wof:placetype":"locality",
    "wof:population":433
},
  "geometry": {"coordinates":[74.864847,23.233651],"type":"Point"}
}