{
  "type": "Feature",
  "properties": {
    "iso:country":"IN",
    "ks:ks_name":"Niranjanbar",
    "ks:ks_pop":792,
    "ks:ks_type":"VILLAGE",
    "name:eng_x_preferred":[
        "Niranjanbar"
    ],
    "wof:name":"Niranjanbar",
    "wof:placetype":"locality",
    "wof:population":792
},
  "geometry": {"coordinates":[87.279606,22.352423],"type":"Point"}
}