{
  "type": "Feature",
  "properties": {
    "gn:admin1_code":"3.0",
    "gn:admin2_code":"324.0",
    "gn:asciiname":"Santipur",
    "gn:country_code":"IN",
    "gn:dem":68,
    "gn:feature_class":"P",
    "gn:feature_code":"PPL",
    "gn:name":"Santipur",
    "gn:population":0,
    "gn:timezone":"Asia/Kolkata",
    "iso:country":"IN",
    "ks:ks_name":"Santipur",
    "ks:ks_pop":1258,
    "ks:ks_type":"VILLAGE",
    "name:eng_x_preferred":[
        "Santipur"
    ],
    "wof:name":"Santipur",
    "wof:placetype":"locality",
    "wof:population":1258
},
  "geometry": {"coordinates":[91.465664,26.582749],"type":"Point"}
}