{
  "type": "Feature",
  "properties": {
    "iso:country":"IN",
    "ks:ks_name":"Sabalooru",
    "ks:ks_pop":325,
    "ks:ks_type":"HABITATION",
    "name:eng_x_preferred":[
        "Sabalooru"
    ],
    "wof:name":"Sabalooru",
    "wof:placetype":"locality",
    "wof:population":325
},
  "geometry": {"coordinates":[75.32235300000001,12.765988],"type":"Point"}
}