{
  "type": "Feature",
  "properties": {
    "iso:country":"IN",
    "qs:name":"Jagat Ganj",
    "qs:name_adm0":"India",
    "qs:name_adm1":"Uttar Pradesh",
    "qs:photos":10,
    "qs:photos_1k":2,
    "qs:photos_9k":1,
    "qs:photos_9r":1,
    "qs:photos_all":10,
    "qs:photos_sr":1,
    "qs:placetype":"Suburb",
    "qs:pop_sr":"0",
    "wof:name":"Jagat Ganj",
    "wof:placetype":"neighbourhood"
},
  "geometry": {"coordinates":[82.9972775,25.328658],"type":"Point"}
}