{
  "type": "Feature",
  "properties": {
    "iso:country":"IN",
    "name:ara_x_preferred":[
        "\u062c\u0627\u063a\u0627\u062a \u063a\u0627\u0646\u062c"
    ],
    "name:ben_bn_x_preferred":[
        "\u099c\u0997\u09a4 \u0997\u099e\u09cd\u099c"
    ],
    "name:ben_in_x_preferred":[
        "\u099c\u0997\u09a4 \u0997\u099e\u09cd\u099c"
    ],
    "name:guj_x_preferred":[
        "\u0a9c\u0a97\u0aa4 \u0a97\u0a82\u0a9c"
    ],
    "name:hin_x_preferred":[
        "\u091c\u0917\u0924 \u0917\u0902\u091c"
    ],
    "name:kan_x_preferred":[
        "\u0c9c\u0c97\u0ca4\u0ccd"
    ],
    "name:mal_x_preferred":[
        "\u0d1c\u0d17\u0d24\u0d4d \u0d17\u0d1e\u0d4d\u0d1a\u0d4d"
    ],
    "name:mar_x_preferred":[
        "\u091c\u0917\u0924 \u0917\u0902\u091c"
    ],
    "name:pan_x_preferred":[
        "\u0a1c\u0a17\u0a24 \u0a17\u0a70\u0a1c"
    ],
    "name:tam_x_preferred":[
        "\u0b9c\u0b95\u0ba4\u0bcd \u0b95\u0b9e\u0bcd\u0b9a\u0bcd"
    ],
    "name:tel_x_preferred":[
        "\u0c1c\u0c17\u0c24\u0c4d \u0c17\u0c02\u0c1c\u0c4d"
    ],
    "name:urd_x_preferred":[
        "\u062c\u06af\u062a \u06af\u0646\u062c"
    ],
    "qs:name":"Jagat Ganj",
    "qs:name_adm0":"India",
    "qs:name_adm1":"Uttar Pradesh",
    "qs:photos":10,
    "qs:photos_1k":2,
    "qs:photos_9k":1,
    "qs:photos_9r":1,
    "qs:photos_all":10,
    "qs:photos_sr":1,
    "qs:placetype":"Suburb",
    "qs:pop_sr":"0",
    "wof:name":"Jagat Ganj",
    "wof:placetype":"neighbourhood"
},
  "geometry": {"coordinates":[82.9972775,25.328658],"type":"Point"}
}