{
  "type": "Feature",
  "properties": {
    "gn:admin1_code":"35",
    "gn:admin2_code":"446.0",
    "gn:asciiname":"Baroda",
    "gn:country_code":"IN",
    "gn:dem":473,
    "gn:feature_class":"P",
    "gn:feature_code":"PPL",
    "gn:name":"Baroda",
    "gn:population":0,
    "gn:timezone":"Asia/Kolkata",
    "iso:country":"IN",
    "ks:ks_name":"Badoda",
    "ks:ks_pop":1507,
    "ks:ks_type":"VILLAGE",
    "name:eng_x_preferred":[
        "Badoda"
    ],
    "name:eng_x_variant":[
        "Baroda"
    ],
    "wof:name":"Badoda",
    "wof:placetype":"locality",
    "wof:population":1507
},
  "geometry": {"coordinates":[77.900413,23.349177],"type":"Point"}
}