{
  "type": "Feature",
  "properties": {
    "iso:country":"IN",
    "ks:ks_name":"Nagaon",
    "ks:ks_pop":113,
    "ks:ks_type":"VILLAGE",
    "name:eng_x_preferred":[
        "Nagaon"
    ],
    "wof:name":"Nagaon",
    "wof:placetype":"locality",
    "wof:population":113
},
  "geometry": {"coordinates":[73.33038000000001,18.482134],"type":"Point"}
}