{
  "type": "Feature",
  "properties": {
    "iso:country":"IN",
    "ks:ks_name":"Nathura Purwa",
    "ks:ks_pop":183,
    "ks:ks_type":"HABITATION",
    "ks:ks_uagg_main":0,
    "name:eng_x_preferred":[
        "Nathura Purwa"
    ],
    "wof:name":"Nathura Purwa",
    "wof:placetype":"neighbourhood",
    "wof:population":183
},
  "geometry": {"coordinates":[80.33677299999999,27.232644],"type":"Point"}
}