{
  "type": "Feature",
  "properties": {
    "iso:country":"IN",
    "ks:ks_name":"Barapania",
    "ks:ks_pop":0,
    "ks:ks_type":"VILLAGE",
    "name:eng_x_preferred":[
        "Barapania"
    ],
    "wof:name":"Barapania",
    "wof:placetype":"locality",
    "wof:population":0
},
  "geometry": {"coordinates":[86.07996900000001,20.623113],"type":"Point"}
}