{
  "type": "Feature",
  "properties": {
    "gn:admin1_code":"36",
    "gn:admin2_code":"135.0",
    "gn:asciiname":"Jagatpur Ramrai",
    "gn:country_code":"IN",
    "gn:dem":189,
    "gn:feature_class":"P",
    "gn:feature_code":"PPL",
    "gn:name":"Jagatpur R\u0101mrai",
    "gn:population":0,
    "gn:timezone":"Asia/Kolkata",
    "iso:country":"IN",
    "ks:ks_alt_nam":"Jagatpur R\u0101mrai",
    "ks:ks_name":"Jagatpur Ramrai",
    "ks:ks_type":"VILLAGE",
    "name:eng_x_preferred":[
        "Jagatpur Ramrai"
    ],
    "name:eng_x_variant":[
        "Jagatpur R\u0101mrai"
    ],
    "wof:name":"Jagatpur Ramrai",
    "wof:placetype":"locality"
},
  "geometry": {"coordinates":[78.840615,28.821088],"type":"Point"}
}