{
  "type": "Feature",
  "properties": {
    "gn:admin1_code":"19.0",
    "gn:admin2_code":"574.0",
    "gn:asciiname":"Dasirakoppal",
    "gn:country_code":"IN",
    "gn:dem":983,
    "gn:feature_class":"P",
    "gn:feature_code":"PPL",
    "gn:name":"D\u0101sirakoppal",
    "gn:population":0,
    "gn:timezone":"Asia/Kolkata",
    "iso:country":"IN",
    "wof:name":"Dasirakoppal",
    "wof:placetype":"locality"
},
  "geometry": {"coordinates":[76.10231999999998,13.03391],"type":"Point"}
}