{
  "type": "Feature",
  "properties": {
    "gn:admin1_code":"39.0",
    "gn:admin2_code":"68.0",
    "gn:asciiname":"Ibrahimpur",
    "gn:country_code":"IN",
    "gn:dem":284,
    "gn:feature_class":"P",
    "gn:feature_code":"PPL",
    "gn:name":"Ibr\u0101himpur",
    "gn:population":0,
    "gn:timezone":"Asia/Kolkata",
    "iso:country":"IN",
    "wof:name":"Ibrahimpur",
    "wof:placetype":"locality"
},
  "geometry": {"coordinates":[77.89291,29.97352],"type":"Point"}
}