{
  "type": "Feature",
  "properties": {
    "iso:country":"IN",
    "ks:ks_name":"Chumoni",
    "ks:ks_pop":530,
    "ks:ks_type":"HABITATION",
    "name:eng_x_preferred":[
        "Chumoni"
    ],
    "wof:name":"Chumoni",
    "wof:placetype":"locality",
    "wof:population":530
},
  "geometry": {"coordinates":[94.86646500000001,27.055858],"type":"Point"}
}