{
  "type": "Feature",
  "properties": {
    "iso:country":"IN",
    "ks:ks_name":"Mohalla",
    "ks:ks_pop":39,
    "ks:ks_type":"HABITATION",
    "name:eng_x_preferred":[
        "Mohalla"
    ],
    "wof:name":"Mohalla",
    "wof:placetype":"locality",
    "wof:population":39
},
  "geometry": {"coordinates":[73.428344,17.831739],"type":"Point"}
}