{
  "type": "Feature",
  "properties": {
    "gn:admin1_code":"23.0",
    "gn:admin2_code":"54.0",
    "gn:asciiname":"Badechha",
    "gn:country_code":"IN",
    "gn:dem":229,
    "gn:feature_class":"P",
    "gn:feature_code":"PPL",
    "gn:name":"Badechha",
    "gn:population":0,
    "gn:timezone":"Asia/Kolkata",
    "iso:country":"IN",
    "name:und_x_variant":[
        "Patti Sekh\u0101ma"
    ],
    "wof:name":"Badechha",
    "wof:placetype":"neighbourhood"
},
  "geometry": {"coordinates":[75.49978,30.40667],"type":"Point"}
}