{
  "type": "Feature",
  "properties": {
    "iso:country":"IN",
    "ks:ks_name":"Sasna",
    "ks:ks_pop":238,
    "ks:ks_type":"HABITATION",
    "name:eng_x_preferred":[
        "Sasna"
    ],
    "wof:name":"Sasna",
    "wof:placetype":"locality",
    "wof:population":238
},
  "geometry": {"coordinates":[78.970455,23.375601],"type":"Point"}
}