{
  "type": "Feature",
  "properties": {
    "iso:country":"IN",
    "ks:ks_name":"Yedthe",
    "ks:ks_pop":94,
    "ks:ks_type":"HABITATION",
    "name:eng_x_preferred":[
        "Yedthe"
    ],
    "wof:name":"Yedthe",
    "wof:placetype":"locality",
    "wof:population":94
},
  "geometry": {"coordinates":[74.97682399999999,13.409395],"type":"Point"}
}