{
  "type": "Feature",
  "properties": {
    "gn:admin1_code":"38.0",
    "gn:admin2_code":"347.0",
    "gn:asciiname":"Leoriatoli",
    "gn:country_code":"IN",
    "gn:dem":421,
    "gn:feature_class":"P",
    "gn:feature_code":"PPL",
    "gn:name":"Leori\u0101tol\u012b",
    "gn:population":0,
    "gn:timezone":"Asia/Kolkata",
    "iso:country":"IN",
    "wof:name":"Leoriatoli",
    "wof:placetype":"locality"
},
  "geometry": {"coordinates":[84.74781,24.14179],"type":"Point"}
}