{
  "type": "Feature",
  "properties": {
    "iso:country":"IN",
    "ks:ks_name":"Dasmariya",
    "ks:ks_pop":222,
    "ks:ks_type":"VILLAGE",
    "ks:ks_uagg_main":0,
    "name:eng_x_preferred":[
        "Dasmariya"
    ],
    "wof:name":"Dasmariya",
    "wof:placetype":"neighbourhood",
    "wof:population":222
},
  "geometry": {"coordinates":[86.895476,24.351438],"type":"Point"}
}