{
  "type": "Feature",
  "properties": {
    "iso:country":"IN",
    "ks:ks_name":"Rabanbasa",
    "ks:ks_pop":140,
    "ks:ks_type":"HABITATION",
    "name:eng_x_preferred":[
        "Rabanbasa"
    ],
    "wof:name":"Rabanbasa",
    "wof:placetype":"locality",
    "wof:population":140
},
  "geometry": {"coordinates":[84.792125,21.657964],"type":"Point"}
}