{
  "type": "Feature",
  "properties": {
    "gn:admin1_code":"10.0",
    "gn:admin2_code":"75.0",
    "gn:asciiname":"Dhandar",
    "gn:country_code":"IN",
    "gn:dem":231,
    "gn:feature_class":"P",
    "gn:feature_code":"PPL",
    "gn:name":"Dhand\u0101r",
    "gn:population":0,
    "gn:timezone":"Asia/Kolkata",
    "iso:country":"IN",
    "wof:name":"Dhandar",
    "wof:placetype":"neighbourhood"
},
  "geometry": {"coordinates":[76.93926,29.21315],"type":"Point"}
}