{
  "type": "Feature",
  "properties": {
    "iso:country":"IN",
    "ks:ks_name":"Shivechapada",
    "ks:ks_pop":40,
    "ks:ks_type":"HABITATION",
    "name:eng_x_preferred":[
        "Shivechapada"
    ],
    "wof:name":"Shivechapada",
    "wof:placetype":"locality",
    "wof:population":40
},
  "geometry": {"coordinates":[72.991941,19.643631],"type":"Point"}
}