{
  "type": "Feature",
  "properties": {
    "iso:country":"IN",
    "ks:ks_name":"Sillapur",
    "ks:ks_pop":0,
    "ks:ks_type":"VILLAGE",
    "name:eng_x_preferred":[
        "Sillapur"
    ],
    "wof:name":"Sillapur",
    "wof:placetype":"locality",
    "wof:population":0
},
  "geometry": {"coordinates":[79.339247,26.202264],"type":"Point"}
}