{
  "type": "Feature",
  "properties": {
    "iso:country":"IN",
    "ks:ks_name":"Rasul Pur",
    "ks:ks_pop":46,
    "ks:ks_type":"HABITATION",
    "ks:ks_uagg_main":0,
    "name:eng_x_preferred":[
        "Rasul Pur"
    ],
    "wof:name":"Rasul Pur",
    "wof:placetype":"neighbourhood",
    "wof:population":46
},
  "geometry": {"coordinates":[82.058646,26.346927],"type":"Point"}
}