{
  "type": "Feature",
  "properties": {
    "iso:country":"IN",
    "ks:ks_name":"Thattarumunda Jn.",
    "ks:ks_pop":782,
    "ks:ks_type":"HABITATION",
    "name:eng_x_preferred":[
        "Thattarumunda Jn."
    ],
    "wof:name":"Thattarumunda Jn.",
    "wof:placetype":"locality",
    "wof:population":782
},
  "geometry": {"coordinates":[76.30116599999999,11.202143],"type":"Point"}
}