{
  "type": "Feature",
  "properties": {
    "iso:country":"IN",
    "ks:ks_name":"Iloliyo Ki Basti",
    "ks:ks_pop":372,
    "ks:ks_type":"HABITATION",
    "name:eng_x_preferred":[
        "Iloliyo Ki Basti"
    ],
    "wof:name":"Iloliyo Ki Basti",
    "wof:placetype":"locality",
    "wof:population":372
},
  "geometry": {"coordinates":[71.124408,25.750911],"type":"Point"}
}