{
  "type": "Feature",
  "properties": {
    "gn:admin1_code":"16.0",
    "gn:admin2_code":"522.0",
    "gn:asciiname":"Kambi",
    "gn:country_code":"IN",
    "gn:dem":446,
    "gn:feature_class":"P",
    "gn:feature_code":"PPL",
    "gn:name":"Kambi",
    "gn:population":0,
    "gn:timezone":"Asia/Kolkata",
    "iso:country":"IN",
    "name:ceb_x_preferred":[
        "Kambi"
    ],
    "name:est_x_preferred":[
        "Kambi"
    ],
    "name:swe_x_preferred":[
        "Kambi"
    ],
    "wof:name":"Kambi",
    "wof:placetype":"locality"
},
  "geometry": {"coordinates":[75.51411999999998,19.35919],"type":"Point"}
}