{
  "type": "Feature",
  "properties": {
    "iso:country":"IN",
    "ks:ks_name":"Mathalwadi",
    "ks:ks_pop":268,
    "ks:ks_type":"HABITATION",
    "name:eng_x_preferred":[
        "Mathalwadi"
    ],
    "wof:name":"Mathalwadi",
    "wof:placetype":"locality",
    "wof:population":268
},
  "geometry": {"coordinates":[73.90261599999999,19.564951],"type":"Point"}
}