{
  "type": "Feature",
  "properties": {
    "gn:admin1_code":"19.0",
    "gn:admin2_code":"575.0",
    "gn:asciiname":"Kariyandur",
    "gn:country_code":"IN",
    "gn:dem":338,
    "gn:feature_class":"P",
    "gn:feature_code":"PPL",
    "gn:name":"Kariyandur",
    "gn:population":0,
    "gn:timezone":"Asia/Kolkata",
    "iso:country":"IN",
    "ks:ks_name":"Kariyandoor",
    "ks:ks_pop":100,
    "ks:ks_type":"HABITATION",
    "name:eng_x_preferred":[
        "Kariyandoor"
    ],
    "name:eng_x_variant":[
        "Kariyandur"
    ],
    "wof:name":"Kariyandoor",
    "wof:placetype":"locality",
    "wof:population":100
},
  "geometry": {"coordinates":[75.387873,13.139023],"type":"Point"}
}