{
  "type": "Feature",
  "properties": {
    "iso:country":"IN",
    "ks:ks_name":"Kommuputtuga",
    "ks:ks_pop":185,
    "ks:ks_type":"HABITATION",
    "name:eng_x_preferred":[
        "Kommuputtuga"
    ],
    "wof:name":"Kommuputtuga",
    "wof:placetype":"locality",
    "wof:population":185
},
  "geometry": {"coordinates":[84.72065600000001,19.037332],"type":"Point"}
}