{
  "type": "Feature",
  "properties": {
    "iso:country":"IN",
    "ks:ks_name":"Eachampetty",
    "ks:ks_pop":1088,
    "ks:ks_type":"HABITATION",
    "name:eng_x_preferred":[
        "Eachampetty"
    ],
    "wof:name":"Eachampetty",
    "wof:placetype":"locality",
    "wof:population":1088
},
  "geometry": {"coordinates":[77.16820199999999,10.302674],"type":"Point"}
}