{
  "type": "Feature",
  "properties": {
    "gn:admin1_code":"36",
    "gn:admin2_code":"180.0",
    "gn:asciiname":"Ahata",
    "gn:country_code":"IN",
    "gn:dem":109,
    "gn:feature_class":"P",
    "gn:feature_code":"PPL",
    "gn:name":"Ah\u0101ta",
    "gn:population":0,
    "gn:timezone":"Asia/Kolkata",
    "iso:country":"IN",
    "ks:ks_alt_nam":"Ah\u0101ta",
    "ks:ks_name":"Ahata",
    "ks:ks_pop":3531,
    "ks:ks_type":"VILLAGE",
    "name:eng_x_preferred":[
        "Ahata"
    ],
    "name:eng_x_variant":[
        "Ah\u0101ta"
    ],
    "wof:name":"Ahata",
    "wof:placetype":"locality",
    "wof:population":3531
},
  "geometry": {"coordinates":[81.455738,27.147008],"type":"Point"}
}