{
  "type": "Feature",
  "properties": {
    "iso:country":"IN",
    "ks:ks_alt_nam":"JABDI",
    "ks:ks_name":"Jabdi",
    "ks:ks_pop":17,
    "ks:ks_type":"HABITATION",
    "name:eng_x_preferred":[
        "Jabdi"
    ],
    "wof:name":"Jabdi",
    "wof:placetype":"locality",
    "wof:population":17
},
  "geometry": {"coordinates":[81.509135,27.591887],"type":"Point"}
}