{
  "type": "Feature",
  "properties": {
    "gn:admin1_code":"25.0",
    "gn:admin2_code":"604",
    "gn:asciiname":"Keranaipudchcheri",
    "gn:country_code":"IN",
    "gn:dem":37,
    "gn:feature_class":"P",
    "gn:feature_code":"PPL",
    "gn:name":"Keranaipudchcheri",
    "gn:population":0,
    "gn:timezone":"Asia/Kolkata",
    "iso:country":"IN",
    "ks:ks_name":"Karanaipuducheri",
    "ks:ks_pop":784,
    "ks:ks_type":"VILLAGE",
    "ks:ks_uagg_main":0,
    "name:eng_x_preferred":[
        "Karanaipuducheri"
    ],
    "wof:name":"Karanaipuducheri",
    "wof:placetype":"locality",
    "wof:population":784
},
  "geometry": {"coordinates":[80.08439199999999,12.844865],"type":"Point"}
}