{
  "type": "Feature",
  "properties": {
    "gn:admin1_code":"19.0",
    "gn:admin2_code":"563.0",
    "gn:asciiname":"Kuppalki",
    "gn:country_code":"IN",
    "gn:dem":362,
    "gn:feature_class":"P",
    "gn:feature_code":"PPL",
    "gn:name":"Kupp\u0101lki",
    "gn:population":0,
    "gn:timezone":"Asia/Kolkata",
    "iso:country":"IN",
    "ks:ks_alt_nam":"kuppali",
    "ks:ks_name":"Kuppali",
    "ks:ks_pop":214,
    "ks:ks_type":"HABITATION",
    "name:eng_x_preferred":[
        "Kuppali"
    ],
    "name:eng_x_variant":[
        "Kuppalki"
    ],
    "wof:name":"Kuppali",
    "wof:placetype":"locality",
    "wof:population":214
},
  "geometry": {"coordinates":[74.58537699999999,14.650363],"type":"Point"}
}