{
  "type": "Feature",
  "properties": {
    "iso:country":"IN",
    "ks:ks_name":"Ganadamane",
    "ks:ks_pop":33,
    "ks:ks_type":"HABITATION",
    "name:eng_x_preferred":[
        "Ganadamane"
    ],
    "wof:name":"Ganadamane",
    "wof:placetype":"locality",
    "wof:population":33
},
  "geometry": {"coordinates":[74.85647899999999,14.511846],"type":"Point"}
}