{
  "type": "Feature",
  "properties": {
    "iso:country":"IN",
    "ks:ks_alt_nam":"YADAV TOLA",
    "ks:ks_name":"Yadav Tola",
    "ks:ks_pop":295,
    "ks:ks_type":"HABITATION",
    "name:eng_x_preferred":[
        "Yadav Tola"
    ],
    "wof:name":"Yadav Tola",
    "wof:placetype":"locality",
    "wof:population":295
},
  "geometry": {"coordinates":[87.83177999999999,25.95002],"type":"Point"}
}