{
  "type": "Feature",
  "properties": {
    "iso:country":"IN",
    "ks:ks_name":"Kanjipara",
    "ks:ks_pop":750,
    "ks:ks_type":"HABITATION",
    "ks:ks_uagg_main":0,
    "name:eng_x_preferred":[
        "Kanjipara"
    ],
    "wof:name":"Kanjipara",
    "wof:placetype":"neighbourhood",
    "wof:population":750
},
  "geometry": {"coordinates":[88.03369499999999,22.51254],"type":"Point"}
}