{
  "type": "Feature",
  "properties": {
    "iso:country":"IN",
    "ks:ks_name":"Bhatudi",
    "ks:ks_pop":565,
    "ks:ks_type":"VILLAGE",
    "name:eng_x_preferred":[
        "Bhatudi"
    ],
    "wof:name":"Bhatudi",
    "wof:placetype":"locality",
    "wof:population":565
},
  "geometry": {"coordinates":[87.087474,24.066518],"type":"Point"}
}