{
  "type": "Feature",
  "properties": {
    "iso:country":"IN",
    "ks:ks_name":"Rampuragarhi",
    "ks:ks_pop":14,
    "ks:ks_type":"HABITATION",
    "name:eng_x_preferred":[
        "Rampuragarhi"
    ],
    "wof:name":"Rampuragarhi",
    "wof:placetype":"locality",
    "wof:population":14
},
  "geometry": {"coordinates":[78.16877599999999,23.39991],"type":"Point"}
}