{
  "type": "Feature",
  "properties": {
    "gn:admin1_code":"2.0",
    "gn:admin2_code":"544.0",
    "gn:asciiname":"Buradamamidi",
    "gn:country_code":"IN",
    "gn:dem":671,
    "gn:feature_class":"P",
    "gn:feature_code":"PPL",
    "gn:name":"Buradam\u0101midi",
    "gn:population":0,
    "gn:timezone":"Asia/Kolkata",
    "iso:country":"IN",
    "ks:ks_alt_nam":"Buradam\u0101midi",
    "ks:ks_name":"Buradamamidi",
    "ks:ks_pop":46,
    "ks:ks_type":"VILLAGE",
    "name:eng_x_preferred":[
        "Buradamamidi"
    ],
    "name:eng_x_variant":[
        "Buradam\u0101midi"
    ],
    "wof:name":"Buradamamidi",
    "wof:placetype":"locality",
    "wof:population":46
},
  "geometry": {"coordinates":[82.317784,18.033745],"type":"Point"}
}