{
  "type": "Feature",
  "properties": {
    "gn:admin1_code":"2.0",
    "gn:admin2_code":"544.0",
    "gn:asciiname":"Buradamamidi",
    "gn:country_code":"IN",
    "gn:dem":671,
    "gn:feature_class":"P",
    "gn:feature_code":"PPL",
    "gn:name":"Buradam\u0101midi",
    "gn:population":0,
    "gn:timezone":"Asia/Kolkata",
    "iso:country":"IN",
    "wof:name":"Buradamamidi",
    "wof:placetype":"locality"
},
  "geometry": {"coordinates":[82.31918,18.0305],"type":"Point"}
}