{
  "type": "Feature",
  "properties": {
    "iso:country":"IN",
    "ks:ks_name":"Kanbhai",
    "ks:ks_pop":2722,
    "ks:ks_type":"VILLAGE",
    "name:eng_x_preferred":[
        "Kanbhai"
    ],
    "wof:name":"Kanbhai",
    "wof:placetype":"locality",
    "wof:population":2722
},
  "geometry": {"coordinates":[73.19013200000001,20.706905],"type":"Point"}
}