{
  "type": "Feature",
  "properties": {
    "gn:admin1_code":"36.0",
    "gn:admin2_code":"161",
    "gn:asciiname":"Sheopuri Tamarwa",
    "gn:country_code":"IN",
    "gn:dem":156,
    "gn:feature_class":"P",
    "gn:feature_code":"PPL",
    "gn:name":"Sheopuri Tamarwa",
    "gn:population":0,
    "gn:timezone":"Asia/Kolkata",
    "iso:country":"IN",
    "name:und_x_variant":[
        "Timar\u016ba"
    ],
    "wof:name":"Sheopuri Tamarwa",
    "wof:placetype":"locality"
},
  "geometry": {"coordinates":[79.07831999999998,26.95802],"type":"Point"}
}