{
  "type": "Feature",
  "properties": {
    "iso:country":"IN",
    "ks:ks_name":"Panchayat Well",
    "ks:ks_pop":636,
    "ks:ks_type":"HABITATION",
    "name:eng_x_preferred":[
        "Panchayat Well"
    ],
    "wof:name":"Panchayat Well",
    "wof:placetype":"locality",
    "wof:population":636
},
  "geometry": {"coordinates":[76.22855199999999,10.728167],"type":"Point"}
}