{
  "type": "Feature",
  "properties": {
    "iso:country":"IN",
    "ks:ks_name":"Sundaria",
    "ks:ks_pop":0,
    "ks:ks_type":"VILLAGE",
    "name:eng_x_preferred":[
        "Sundaria"
    ],
    "wof:name":"Sundaria",
    "wof:placetype":"locality",
    "wof:population":0
},
  "geometry": {"coordinates":[85.07526900000001,19.805028],"type":"Point"}
}