{
  "type": "Feature",
  "properties": {
    "gn:admin1_code":"34.0",
    "gn:admin2_code":"217.0",
    "gn:asciiname":"Pathra Tola",
    "gn:country_code":"IN",
    "gn:dem":71,
    "gn:feature_class":"P",
    "gn:feature_code":"PPL",
    "gn:name":"Pathra Tola",
    "gn:population":0,
    "gn:timezone":"Asia/Kolkata",
    "iso:country":"IN",
    "ks:ks_name":"Pathra Tola",
    "ks:ks_pop":772,
    "ks:ks_type":"VILLAGE",
    "ks:ks_uagg_main":0,
    "name:eng_x_preferred":[
        "Pathra Tola"
    ],
    "wof:name":"Pathra Tola",
    "wof:placetype":"locality",
    "wof:population":772
},
  "geometry": {"coordinates":[84.54571900000001,26.417348],"type":"Point"}
}