{
  "type": "Feature",
  "properties": {
    "iso:country":"IN",
    "ks:ks_name":"Purnapani",
    "ks:ks_pop":103,
    "ks:ks_type":"HABITATION",
    "name:eng_x_preferred":[
        "Purnapani"
    ],
    "wof:name":"Purnapani",
    "wof:placetype":"locality",
    "wof:population":103
},
  "geometry": {"coordinates":[82.26820600000001,18.656173],"type":"Point"}
}