{
  "type": "Feature",
  "properties": {
    "iso:country":"IN",
    "ks:ks_alt_nam":"BASEN",
    "ks:ks_name":"Basen",
    "ks:ks_pop":617,
    "ks:ks_type":"HABITATION",
    "name:eng_x_preferred":[
        "Basen"
    ],
    "wof:name":"Basen",
    "wof:placetype":"locality",
    "wof:population":617
},
  "geometry": {"coordinates":[83.66365500000001,22.754562],"type":"Point"}
}