{
  "type": "Feature",
  "properties": {
    "iso:country":"IN",
    "ks:ks_name":"Barsia",
    "ks:ks_pop":526,
    "ks:ks_type":"VILLAGE",
    "name:eng_x_preferred":[
        "Barsia"
    ],
    "wof:name":"Barsia",
    "wof:placetype":"locality",
    "wof:population":526
},
  "geometry": {"coordinates":[86.32852200000001,21.943552],"type":"Point"}
}