{
  "type": "Feature",
  "properties": {
    "gn:admin1_code":"11.0",
    "gn:admin2_code":"33.0",
    "gn:asciiname":"Maran",
    "gn:country_code":"IN",
    "gn:dem":2187,
    "gn:feature_class":"P",
    "gn:feature_code":"PPL",
    "gn:name":"Mar\u0101n",
    "gn:population":0,
    "gn:timezone":"Asia/Kolkata",
    "iso:country":"IN",
    "name:fra_x_preferred":[
        "Maran"
    ],
    "name:heb_x_preferred":[
        "\u05de\u05e8\u05df"
    ],
    "name:lad_x_preferred":[
        "Maran"
    ],
    "name:spa_x_preferred":[
        "Maran"
    ],
    "name:vie_x_preferred":[
        "Maran"
    ],
    "wof:name":"Maran",
    "wof:placetype":"locality"
},
  "geometry": {"coordinates":[77.65018000000001,31.11485],"type":"Point"}
}