{
  "type": "Feature",
  "properties": {
    "iso:country":"IN",
    "ks:ks_name":"Badkudar",
    "ks:ks_pop":135,
    "ks:ks_type":"VILLAGE",
    "name:eng_x_preferred":[
        "Badkudar"
    ],
    "wof:name":"Badkudar",
    "wof:placetype":"locality",
    "wof:population":135
},
  "geometry": {"coordinates":[84.60775599999999,21.997795],"type":"Point"}
}