{
  "type": "Feature",
  "properties": {
    "iso:country":"IN",
    "ks:ks_name":"Dakshin Srikrishnapur",
    "ks:ks_pop":1553,
    "ks:ks_type":"VILLAGE",
    "name:eng_x_preferred":[
        "Dakshin Srikrishnapur"
    ],
    "wof:name":"Dakshin Srikrishnapur",
    "wof:placetype":"locality",
    "wof:population":1553
},
  "geometry": {"coordinates":[87.92478699999999,22.223986],"type":"Point"}
}