{
  "type": "Feature",
  "properties": {
    "iso:country":"IN",
    "ks:ks_name":"Outabgarh",
    "ks:ks_type":"URBAN",
    "name:eng_x_preferred":[
        "Outabgarh"
    ],
    "wof:name":"Outabgarh",
    "wof:placetype":"neighbourhood"
},
  "geometry": {"coordinates":[76.95926,28.800782],"type":"Point"}
}