{
  "type": "Feature",
  "properties": {
    "gn:admin1_code":"19.0",
    "gn:admin2_code":"566.0",
    "gn:asciiname":"Kudiahalli",
    "gn:country_code":"IN",
    "gn:dem":583,
    "gn:feature_class":"P",
    "gn:feature_code":"PPL",
    "gn:name":"K\u016bdiahalli",
    "gn:population":0,
    "gn:timezone":"Asia/Kolkata",
    "iso:country":"IN",
    "wof:name":"Kudiahalli",
    "wof:placetype":"neighbourhood"
},
  "geometry": {"coordinates":[76.71841000000001,13.98751],"type":"Point"}
}