{
  "type": "Feature",
  "properties": {
    "iso:country":"IN",
    "ks:ks_name":"Barred",
    "ks:ks_pop":1216,
    "ks:ks_type":"HABITATION",
    "name:eng_x_preferred":[
        "Barred"
    ],
    "wof:name":"Barred",
    "wof:placetype":"locality",
    "wof:population":1216
},
  "geometry": {"coordinates":[76.76536900000001,26.293049],"type":"Point"}
}