{
  "type": "Feature",
  "properties": {
    "iso:country":"IN",
    "ks:ks_name":"Mohanpur",
    "ks:ks_pop":0,
    "ks:ks_type":"VILLAGE",
    "name:eng_x_preferred":[
        "Mohanpur"
    ],
    "wof:name":"Mohanpur",
    "wof:placetype":"locality",
    "wof:population":0
},
  "geometry": {"coordinates":[75.619058,31.133316],"type":"Point"}
}