{
  "type": "Feature",
  "properties": {
    "iso:country":"IN",
    "ks:ks_name":"Halder Para",
    "ks:ks_pop":144,
    "ks:ks_type":"HABITATION",
    "name:eng_x_preferred":[
        "Halder Para"
    ],
    "wof:name":"Halder Para",
    "wof:placetype":"locality",
    "wof:population":144
},
  "geometry": {"coordinates":[88.389588,22.183406],"type":"Point"}
}