{
  "type": "Feature",
  "properties": {
    "iso:country":"IN",
    "ks:ks_name":"Anchu Eitty",
    "ks:ks_pop":1110,
    "ks:ks_type":"HABITATION",
    "ks:ks_uagg_main":0,
    "name:eng_x_preferred":[
        "Anchu Eitty"
    ],
    "wof:name":"Anchu Eitty",
    "wof:placetype":"neighbourhood",
    "wof:population":1110
},
  "geometry": {"coordinates":[76.24763400000001,10.613754],"type":"Point"}
}