{
  "type": "Feature",
  "properties": {
    "gn:admin1_code":"36",
    "gn:admin2_code":"189.0",
    "gn:asciiname":"Lehani",
    "gn:country_code":"IN",
    "gn:dem":90,
    "gn:feature_class":"P",
    "gn:feature_code":"PPL",
    "gn:name":"Lehani",
    "gn:population":0,
    "gn:timezone":"Asia/Kolkata",
    "iso:country":"IN",
    "wof:name":"Lehani",
    "wof:placetype":"locality"
},
  "geometry": {"coordinates":[83.67690999999998,26.77295],"type":"Point"}
}