{
  "type": "Feature",
  "properties": {
    "gn:country":"IN",
    "gn:fcode":"PPL",
    "gn:pop":16557,
    "iso:country":"IN",
    "name:ben_x_preferred":[
        "\u09b8\u09be\u09b2\u09c1\u09ae\u09cd\u09ac\u09be\u09b0"
    ],
    "name:bpy_x_preferred":[
        "\u09b8\u09be\u09b2\u09c1\u09ae\u09cd\u09ac\u09be\u09b0"
    ],
    "name:cat_x_preferred":[
        "Salumbar"
    ],
    "name:deu_x_preferred":[
        "Salumbar"
    ],
    "name:eng_x_preferred":[
        "Salumbar"
    ],
    "name:fra_x_preferred":[
        "Salumbar"
    ],
    "name:guj_x_preferred":[
        "\u0ab8\u0ab2\u0ac1\u0a82\u0aae\u0acd\u0aac\u0ab0"
    ],
    "name:ita_x_preferred":[
        "Salumbar"
    ],
    "name:jpn_x_preferred":[
        "\u30b5\u30eb\u30e0\u30d0\u30fc\u30eb"
    ],
    "name:kan_x_preferred":[
        "\u0cb8\u0cb2\u0ccd\u0cac\u0cbe\u0cb0\u0ccd"
    ],
    "name:kor_x_preferred":[
        "\uc0b4\ub8f8\ubc14"
    ],
    "name:msa_x_preferred":[
        "Salumbar"
    ],
    "name:nld_x_preferred":[
        "Salumbar"
    ],
    "name:por_x_preferred":[
        "Salumbar"
    ],
    "name:rus_x_preferred":[
        "\u0421\u0430\u043b\u0443\u043c\u0431\u0430\u0440"
    ],
    "name:spa_x_preferred":[
        "Salumbar"
    ],
    "name:swe_x_preferred":[
        "S\u0101l\u016bmbar"
    ],
    "name:tam_x_preferred":[
        "\u0b9a\u0bb2\u0bc1\u0bae\u0bcd\u0baa\u0bbe\u0bb0\u0bcd"
    ],
    "name:tel_x_preferred":[
        "\u0c38\u0c32\u0c41\u0c02\u0c2c\u0c30\u0c4d"
    ],
    "name:unk_x_variant":[
        "S\u0101l\u016bmbar"
    ],
    "name:urd_x_preferred":[
        "\u0633\u0627\u0644\u0648\u0645\u0628\u0631"
    ],
    "name:vie_x_preferred":[
        "Salumbar"
    ],
    "name:zho_x_preferred":[
        "\u8428\u5362\u59c6\u5df4\u5c14"
    ],
    "qs:name":"Salumbar",
    "qs:name_adm0":"India",
    "qs:name_adm1":"Rajasthan",
    "qs:photos_9r":0,
    "qs:photos_sr":0,
    "qs:placetype":"Town",
    "qs:pop_sr":"6",
    "wd:wordcount":300,
    "wof:name":"Salumbar",
    "wof:placetype":"locality",
    "wof:population":16557
},
  "geometry": {"coordinates":[74.04442,24.13524],"type":"Point"}
}