{
  "type": "Feature",
  "properties": {
    "iso:country":"IN",
    "ks:ks_name":"Gharewadi",
    "ks:ks_pop":570,
    "ks:ks_type":"HABITATION",
    "name:eng_x_preferred":[
        "Gharewadi"
    ],
    "wof:name":"Gharewadi",
    "wof:placetype":"locality",
    "wof:population":570
},
  "geometry": {"coordinates":[73.504167,17.23],"type":"Point"}
}