{
  "type": "Feature",
  "properties": {
    "iso:country":"IN",
    "ks:ks_name":"Bhuri Tekri",
    "ks:ks_pop":39,
    "ks:ks_type":"HABITATION",
    "name:eng_x_preferred":[
        "Bhuri Tekri"
    ],
    "wof:name":"Bhuri Tekri",
    "wof:placetype":"locality",
    "wof:population":39
},
  "geometry": {"coordinates":[77.763019,23.138984],"type":"Point"}
}