{
  "type": "Feature",
  "properties": {
    "iso:country":"IN",
    "ks:ks_name":"Pullarikkodu",
    "ks:ks_pop":342,
    "ks:ks_type":"HABITATION",
    "ks:ks_uagg_main":0,
    "name:eng_x_preferred":[
        "Pullarikkodu"
    ],
    "wof:name":"Pullarikkodu",
    "wof:placetype":"neighbourhood",
    "wof:population":342
},
  "geometry": {"coordinates":[76.365025,10.98288],"type":"Point"}
}