{
  "type": "Feature",
  "properties": {
    "iso:country":"IN",
    "ks:ks_name":"Pirghatpura",
    "ks:ks_pop":381,
    "ks:ks_type":"HABITATION",
    "name:eng_x_preferred":[
        "Pirghatpura"
    ],
    "wof:name":"Pirghatpura",
    "wof:placetype":"locality",
    "wof:population":381
},
  "geometry": {"coordinates":[75.56093300000001,22.443899],"type":"Point"}
}