{
  "type": "Feature",
  "properties": {
    "iso:country":"IN",
    "ks:ks_name":"Barawe",
    "ks:ks_pop":956,
    "ks:ks_type":"HABITATION",
    "name:eng_x_preferred":[
        "Barawe"
    ],
    "wof:name":"Barawe",
    "wof:placetype":"locality",
    "wof:population":956
},
  "geometry": {"coordinates":[83.127364,23.995775],"type":"Point"}
}