{
  "type": "Feature",
  "properties": {
    "gn:admin1_code":"39",
    "gn:admin2_code":"61.0",
    "gn:asciiname":"Mandau",
    "gn:country_code":"IN",
    "gn:dem":989,
    "gn:feature_class":"P",
    "gn:feature_code":"PPL",
    "gn:name":"Mand\u0101u",
    "gn:population":0,
    "gn:timezone":"Asia/Kolkata",
    "iso:country":"IN",
    "name:bar_x_preferred":[
        "Mandau"
    ],
    "name:ceb_x_preferred":[
        "Mandau"
    ],
    "name:ces_x_preferred":[
        "Mandava"
    ],
    "name:dan_x_preferred":[
        "Mandau"
    ],
    "name:deu_x_preferred":[
        "Mandau"
    ],
    "name:hsb_x_preferred":[
        "Mandawa"
    ],
    "name:mkd_x_preferred":[
        "\u041c\u0430\u043d\u0434\u0430\u0443"
    ],
    "name:pol_x_preferred":[
        "Mandau"
    ],
    "wof:name":"Mandau",
    "wof:placetype":"locality"
},
  "geometry": {"coordinates":[78.98220999999999,29.65103],"type":"Point"}
}