{
  "type": "Feature",
  "properties": {
    "gn:admin1_code":"11.0",
    "gn:admin2_code":"31.0",
    "gn:asciiname":"Korun",
    "gn:country_code":"IN",
    "gn:dem":1850,
    "gn:feature_class":"P",
    "gn:feature_code":"PPL",
    "gn:name":"Kor\u016bn",
    "gn:population":0,
    "gn:timezone":"Asia/Kolkata",
    "iso:country":"IN",
    "name:slv_x_preferred":[
        "Korun"
    ],
    "wof:name":"Korun",
    "wof:placetype":"locality"
},
  "geometry": {"coordinates":[77.05543,30.91339],"type":"Point"}
}