{
  "type": "Feature",
  "properties": {
    "gn:admin1_code":"34.0",
    "gn:admin2_code":"221.0",
    "gn:asciiname":"Kankar",
    "gn:country_code":"IN",
    "gn:dem":50,
    "gn:feature_class":"P",
    "gn:feature_code":"PPL",
    "gn:name":"K\u0101nkar",
    "gn:population":0,
    "gn:timezone":"Asia/Kolkata",
    "iso:country":"IN",
    "name:deu_x_preferred":[
        "Kankar"
    ],
    "name:kan_x_preferred":[
        "\u0c95\u0c82\u0c95\u0cb0\u0ccd"
    ],
    "wof:name":"Kankar",
    "wof:placetype":"locality"
},
  "geometry": {"coordinates":[86.08677,25.84842],"type":"Point"}
}