{
  "type": "Feature",
  "properties": {
    "iso:country":"IN",
    "ks:ks_name":"Pahadfalia",
    "ks:ks_pop":440,
    "ks:ks_type":"HABITATION",
    "name:eng_x_preferred":[
        "Pahadfalia"
    ],
    "wof:name":"Pahadfalia",
    "wof:placetype":"locality",
    "wof:population":440
},
  "geometry": {"coordinates":[72.979417,20.648667],"type":"Point"}
}