{
  "type": "Feature",
  "properties": {
    "iso:country":"IN",
    "ks:ks_name":"Kanta Khali",
    "ks:ks_pop":570,
    "ks:ks_type":"HABITATION",
    "ks:ks_uagg_main":0,
    "name:eng_x_preferred":[
        "Kanta Khali"
    ],
    "wof:name":"Kanta Khali",
    "wof:placetype":"neighbourhood",
    "wof:population":570
},
  "geometry": {"coordinates":[88.190416,22.336967],"type":"Point"}
}