{
  "type": "Feature",
  "properties": {
    "iso:country":"IN",
    "ks:ks_name":"Dakhin Jangalpara",
    "ks:ks_pop":584,
    "ks:ks_type":"VILLAGE",
    "ks:ks_uagg_main":0,
    "name:eng_x_preferred":[
        "Dakhin Jangalpara"
    ],
    "wof:name":"Dakhin Jangalpara",
    "wof:placetype":"neighbourhood",
    "wof:population":584
},
  "geometry": {"coordinates":[91.930053,26.651979],"type":"Point"}
}