{
  "type": "Feature",
  "properties": {
    "iso:country":"IN",
    "ks:ks_name":"Khiroli",
    "ks:ks_pop":80,
    "ks:ks_type":"HABITATION",
    "name:eng_x_preferred":[
        "Khiroli"
    ],
    "wof:name":"Khiroli",
    "wof:placetype":"locality",
    "wof:population":80
},
  "geometry": {"coordinates":[79.863001,29.717673],"type":"Point"}
}