{
  "type": "Feature",
  "properties": {
    "iso:country":"IN",
    "ks:ks_name":"Kishanpur",
    "ks:ks_pop":0,
    "ks:ks_type":"VILLAGE",
    "name:eng_x_preferred":[
        "Kishanpur"
    ],
    "wof:name":"Kishanpur",
    "wof:placetype":"locality",
    "wof:population":0
},
  "geometry": {"coordinates":[85.231268,24.896529],"type":"Point"}
}