{
  "type": "Feature",
  "properties": {
    "gn:admin1_code":"30",
    "gn:admin2_code":"254.0",
    "gn:asciiname":"Laju",
    "gn:country_code":"IN",
    "gn:dem":1422,
    "gn:feature_class":"P",
    "gn:feature_code":"PPL",
    "gn:name":"L\u0101ju",
    "gn:population":0,
    "gn:timezone":"Asia/Kolkata",
    "iso:country":"IN",
    "wof:name":"Laju",
    "wof:placetype":"locality"
},
  "geometry": {"coordinates":[95.5752,26.90348],"type":"Point"}
}