{
  "type": "Feature",
  "properties": {
    "gn:admin1_code":"2.0",
    "gn:admin2_code":"543.0",
    "gn:asciiname":"Ippavalasa",
    "gn:country_code":"IN",
    "gn:dem":720,
    "gn:feature_class":"P",
    "gn:feature_code":"PPL",
    "gn:name":"Ippavalasa",
    "gn:population":0,
    "gn:timezone":"Asia/Kolkata",
    "iso:country":"IN",
    "wof:name":"Ippavalasa",
    "wof:placetype":"locality"
},
  "geometry": {"coordinates":[83.18089000000001,18.39779],"type":"Point"}
}