{
  "type": "Feature",
  "properties": {
    "gn:admin1_code":"36.0",
    "gn:admin2_code":"155.0",
    "gn:asciiname":"Kanchan Bagh",
    "gn:country_code":"IN",
    "gn:dem":149,
    "gn:feature_class":"P",
    "gn:feature_code":"PPL",
    "gn:name":"Kanchan B\u0101gh",
    "gn:population":0,
    "gn:timezone":"Asia/Kolkata",
    "iso:country":"IN",
    "name:ara_x_preferred":[
        "\u0643\u0627\u0646\u0634\u0627\u0646 \u0628\u0627\u063a"
    ],
    "name:ben_bn_x_preferred":[
        "\u0995\u09be\u099e\u09cd\u099a\u09a8 \u09ac\u09be\u0997"
    ],
    "name:ben_in_x_preferred":[
        "\u0995\u09be\u099e\u09cd\u099a\u09a8 \u09ac\u09be\u0997"
    ],
    "name:guj_x_preferred":[
        "\u0a95\u0a82\u0a9a\u0aa8 \u0aac\u0abe\u0a97"
    ],
    "name:hin_x_preferred":[
        "\u0915\u0902\u091a\u0928 \u092c\u093e\u0917"
    ],
    "name:kan_x_preferred":[
        "\u0c95\u0c82\u0c9a\u0ca8\u0ccd"
    ],
    "name:mal_x_preferred":[
        "\u0d15\u0d3e\u0d1e\u0d4d\u0d1a\u0d7b \u0d2c\u0d3e\u0d17\u0d4d"
    ],
    "name:mar_x_preferred":[
        "\u0915\u093e\u0902\u091a\u0928 \u092c\u093e\u0917"
    ],
    "name:pan_x_preferred":[
        "\u0a15\u0a70\u0a1a\u0a28 \u0a2c\u0a3e\u0a17"
    ],
    "name:tam_x_preferred":[
        "\u0b95\u0b9e\u0bcd\u0b9a\u0ba9\u0bcd \u0baa\u0bbe\u0b95\u0bcd"
    ],
    "name:tel_x_preferred":[
        "\u0c15\u0c02\u0c1a\u0c02\u0c28\u0c4d \u0c2c\u0c3e\u0c17\u0c4d"
    ],
    "name:urd_x_preferred":[
        "\u06a9\u0646\u0686\u0646 \u0628\u0627\u063a"
    ],
    "wof:name":"Kanchan Bagh",
    "wof:placetype":"neighbourhood"
},
  "geometry": {"coordinates":[80.20086000000001,27.62744],"type":"Point"}
}