{
  "type": "Feature",
  "properties": {
    "gn:admin1_code":"24.0",
    "gn:admin2_code":"123.0",
    "gn:asciiname":"Dara",
    "gn:country_code":"IN",
    "gn:dem":597,
    "gn:feature_class":"P",
    "gn:feature_code":"PPL",
    "gn:name":"Dara",
    "gn:population":0,
    "gn:timezone":"Asia/Kolkata",
    "iso:country":"IN",
    "name:ces_x_preferred":[
        "Dara"
    ],
    "name:isl_x_preferred":[
        "Dara"
    ],
    "name:slv_x_preferred":[
        "Dara"
    ],
    "name:srp_x_preferred":[
        "\u0414\u0430\u0440\u0430"
    ],
    "wof:name":"Dara",
    "wof:placetype":"locality"
},
  "geometry": {"coordinates":[74.17406,25.80738],"type":"Point"}
}