{
  "type": "Feature",
  "properties": {
    "iso:country":"IN",
    "ks:ks_name":"Pure Ganga Ram",
    "ks:ks_pop":153,
    "ks:ks_type":"HABITATION",
    "ks:ks_uagg_main":0,
    "name:eng_x_preferred":[
        "Pure Ganga Ram"
    ],
    "wof:name":"Pure Ganga Ram",
    "wof:placetype":"neighbourhood",
    "wof:population":153
},
  "geometry": {"coordinates":[81.721417,26.25621],"type":"Point"}
}