{
  "type": "Feature",
  "properties": {
    "iso:country":"IN",
    "ks:ks_alt_nam":"Nishal Faliya ITI",
    "ks:ks_name":"Nishal Faliya Iti",
    "ks:ks_pop":388,
    "ks:ks_type":"HABITATION",
    "ks:ks_uagg_main":0,
    "name:eng_x_preferred":[
        "Nishal Faliya Iti"
    ],
    "wof:name":"Nishal Faliya Iti",
    "wof:placetype":"neighbourhood",
    "wof:population":388
},
  "geometry": {"coordinates":[73.670017,22.798583],"type":"Point"}
}