{
  "type": "Feature",
  "properties": {
    "iso:country":"IN",
    "ks:ks_name":"Pandarapuliyakudi",
    "ks:ks_pop":600,
    "ks:ks_type":"HABITATION",
    "name:eng_x_preferred":[
        "Pandarapuliyakudi"
    ],
    "wof:name":"Pandarapuliyakudi",
    "wof:placetype":"locality",
    "wof:population":600
},
  "geometry": {"coordinates":[79.701649,10.872196],"type":"Point"}
}