{
  "type": "Feature",
  "properties": {
    "iso:country":"IN",
    "ks:ks_name":"Hosangady",
    "ks:ks_pop":239,
    "ks:ks_type":"HABITATION",
    "name:eng_x_preferred":[
        "Hosangady"
    ],
    "wof:name":"Hosangady",
    "wof:placetype":"locality",
    "wof:population":239
},
  "geometry": {"coordinates":[74.876114,13.372916],"type":"Point"}
}