{
  "type": "Feature",
  "properties": {
    "gn:admin1_code":"34.0",
    "gn:admin2_code":"215.0",
    "gn:asciiname":"Balia",
    "gn:country_code":"IN",
    "gn:dem":49,
    "gn:feature_class":"P",
    "gn:feature_code":"PPL",
    "gn:name":"Balia",
    "gn:population":0,
    "gn:timezone":"Asia/Kolkata",
    "iso:country":"IN",
    "ks:ks_name":"Balia",
    "ks:ks_pop":4818,
    "ks:ks_type":"VILLAGE",
    "ks:ks_uagg_main":0,
    "name:eng_x_preferred":[
        "Balia"
    ],
    "name:hin_x_preferred":[
        "\u092c\u0932\u093f\u092f\u093e"
    ],
    "wof:name":"Balia",
    "wof:placetype":"neighbourhood",
    "wof:population":4818
},
  "geometry": {"coordinates":[86.226743,25.932126],"type":"Point"}
}