{
  "type": "Feature",
  "properties": {
    "iso:country":"IN",
    "ks:ks_name":"Kushrani Malli",
    "ks:ks_pop":347,
    "ks:ks_type":"VILLAGE",
    "name:eng_x_preferred":[
        "Kushrani Malli"
    ],
    "wof:name":"Kushrani Malli",
    "wof:placetype":"locality",
    "wof:population":347
},
  "geometry": {"coordinates":[79.41538199999999,29.952428],"type":"Point"}
}