{
  "type": "Feature",
  "properties": {
    "gn:admin1_code":"3.0",
    "gn:admin2_code":"315.0",
    "gn:asciiname":"Gopikot",
    "gn:country_code":"IN",
    "gn:dem":1121,
    "gn:feature_class":"P",
    "gn:feature_code":"PPL",
    "gn:name":"Gopikot",
    "gn:population":0,
    "gn:timezone":"Asia/Kolkata",
    "iso:country":"IN",
    "wof:name":"Gopikot",
    "wof:placetype":"locality"
},
  "geometry": {"coordinates":[93.15575,25.08096],"type":"Point"}
}