{
  "type": "Feature",
  "properties": {
    "gn:admin1_code":"36",
    "gn:admin2_code":"180.0",
    "gn:asciiname":"Barwa",
    "gn:country_code":"IN",
    "gn:dem":128,
    "gn:feature_class":"P",
    "gn:feature_code":"PPL",
    "gn:name":"Barwa",
    "gn:population":0,
    "gn:timezone":"Asia/Kolkata",
    "iso:country":"IN",
    "name:deu_x_preferred":[
        "Barwa"
    ],
    "name:slv_x_preferred":[
        "Barwa"
    ],
    "wof:name":"Barwa",
    "wof:placetype":"neighbourhood"
},
  "geometry": {"coordinates":[81.41455999999999,27.86264],"type":"Point"}
}