{
  "type": "Feature",
  "properties": {
    "gn:admin1_code":"36",
    "gn:admin2_code":"195.0",
    "gn:asciiname":"Sabalpur Kalan",
    "gn:country_code":"IN",
    "gn:dem":71,
    "gn:feature_class":"P",
    "gn:feature_code":"PPL",
    "gn:name":"Sabalpur Kal\u0101n",
    "gn:population":0,
    "gn:timezone":"Asia/Kolkata",
    "iso:country":"IN",
    "ks:ks_name":"Sabbalpur Kalan",
    "ks:ks_pop":3352,
    "ks:ks_type":"VILLAGE",
    "ks:ks_uagg_main":0,
    "name:eng_x_preferred":[
        "Sabbalpur Kalan"
    ],
    "wof:name":"Sabbalpur Kalan",
    "wof:placetype":"neighbourhood",
    "wof:population":3352
},
  "geometry": {"coordinates":[83.56735999999999,25.491291],"type":"Point"}
}