{
  "type": "Feature",
  "properties": {
    "gn:admin1_code":"11",
    "gn:admin2_code":"33.0",
    "gn:asciiname":"Gastari",
    "gn:country_code":"IN",
    "gn:dem":2293,
    "gn:feature_class":"P",
    "gn:feature_code":"PPL",
    "gn:name":"Gast\u0101ri",
    "gn:population":0,
    "gn:timezone":"Asia/Kolkata",
    "iso:country":"IN",
    "wof:name":"Gastari",
    "wof:placetype":"locality"
},
  "geometry": {"coordinates":[77.6469,30.99284],"type":"Point"}
}