{
  "type": "Feature",
  "properties": {
    "iso:country":"IN",
    "ks:ks_alt_nam":"Ippagudem UV",
    "ks:ks_name":"Ippagudem Uv",
    "ks:ks_pop":82,
    "ks:ks_type":"HABITATION",
    "ks:ks_uagg_main":0,
    "name:eng_x_preferred":[
        "Ippagudem Uv"
    ],
    "wof:name":"Ippagudem Uv",
    "wof:placetype":"neighbourhood",
    "wof:population":82
},
  "geometry": {"coordinates":[80.565073,18.301972],"type":"Point"}
}