{
  "type": "Feature",
  "properties": {
    "gn:admin1_code":"38.0",
    "gn:admin2_code":"362.0",
    "gn:asciiname":"Jhilidabar",
    "gn:country_code":"IN",
    "gn:dem":152,
    "gn:feature_class":"P",
    "gn:feature_code":"PPL",
    "gn:name":"Jhilidabar",
    "gn:population":0,
    "gn:timezone":"Asia/Kolkata",
    "iso:country":"IN",
    "ks:ks_name":"Jhilidabar",
    "ks:ks_pop":91,
    "ks:ks_type":"VILLAGE",
    "name:eng_x_preferred":[
        "Jhilidabar"
    ],
    "wof:name":"Jhilidabar",
    "wof:placetype":"locality",
    "wof:population":91
},
  "geometry": {"coordinates":[87.50820400000001,24.233248],"type":"Point"}
}