{
  "type": "Feature",
  "properties": {
    "iso:country":"IN",
    "ks:ks_name":"Kopparagundi",
    "ks:ks_pop":26,
    "ks:ks_type":"HABITATION",
    "name:eng_x_preferred":[
        "Kopparagundi"
    ],
    "wof:name":"Kopparagundi",
    "wof:placetype":"locality",
    "wof:population":26
},
  "geometry": {"coordinates":[74.95899900000001,13.509519],"type":"Point"}
}