{
  "type": "Feature",
  "properties": {
    "iso:country":"IN",
    "ks:ks_name":"Baishnabsol",
    "ks:ks_pop":26,
    "ks:ks_type":"VILLAGE",
    "name:eng_x_preferred":[
        "Baishnabsol"
    ],
    "wof:name":"Baishnabsol",
    "wof:placetype":"locality",
    "wof:population":26
},
  "geometry": {"coordinates":[87.12634799999999,22.836761],"type":"Point"}
}