{
  "type": "Feature",
  "properties": {
    "iso:country":"IN",
    "ks:ks_name":"T Karisalkulam",
    "ks:ks_pop":372,
    "ks:ks_type":"HABITATION",
    "name:eng_x_preferred":[
        "T Karisalkulam"
    ],
    "wof:name":"T Karisalkulam",
    "wof:placetype":"locality",
    "wof:population":372
},
  "geometry": {"coordinates":[78.34419800000001,9.19395],"type":"Point"}
}