{
  "type": "Feature",
  "properties": {
    "iso:country":"IN",
    "ks:ks_name":"Lakrapada",
    "ks:ks_pop":62,
    "ks:ks_type":"HABITATION",
    "name:eng_x_preferred":[
        "Lakrapada"
    ],
    "wof:name":"Lakrapada",
    "wof:placetype":"locality",
    "wof:population":62
},
  "geometry": {"coordinates":[84.677778,22.039867],"type":"Point"}
}