{
  "type": "Feature",
  "properties": {
    "iso:country":"IN",
    "ks:ks_name":"Chung Hati",
    "ks:ks_pop":537,
    "ks:ks_type":"HABITATION",
    "name:eng_x_preferred":[
        "Chung Hati"
    ],
    "wof:name":"Chung Hati",
    "wof:placetype":"locality",
    "wof:population":537
},
  "geometry": {"coordinates":[86.849073,22.164976],"type":"Point"}
}