{
  "type": "Feature",
  "properties": {
    "iso:country":"IN",
    "ks:ks_name":"Baiga Tola",
    "ks:ks_pop":210,
    "ks:ks_type":"HABITATION",
    "name:eng_x_preferred":[
        "Baiga Tola"
    ],
    "wof:name":"Baiga Tola",
    "wof:placetype":"locality",
    "wof:population":210
},
  "geometry": {"coordinates":[83.31394400000001,24.424837],"type":"Point"}
}