{
  "type": "Feature",
  "properties": {
    "iso:country":"IN",
    "ks:ks_name":"Kasotiya",
    "ks:ks_pop":200,
    "ks:ks_type":"VILLAGE",
    "name:eng_x_preferred":[
        "Kasotiya"
    ],
    "wof:name":"Kasotiya",
    "wof:placetype":"locality",
    "wof:population":200
},
  "geometry": {"coordinates":[74.18896100000001,24.379025],"type":"Point"}
}