{
  "type": "Feature",
  "properties": {
    "iso:country":"IN",
    "ks:ks_name":"Sathagala",
    "ks:ks_pop":50,
    "ks:ks_type":"HABITATION",
    "name:eng_x_preferred":[
        "Sathagala"
    ],
    "wof:name":"Sathagala",
    "wof:placetype":"locality",
    "wof:population":50
},
  "geometry": {"coordinates":[76.024215,12.944488],"type":"Point"}
}