{
  "type": "Feature",
  "properties": {
    "iso:country":"IN",
    "ks:ks_name":"Gopalpurthanda",
    "ks:ks_pop":106,
    "ks:ks_type":"HABITATION",
    "name:eng_x_preferred":[
        "Gopalpurthanda"
    ],
    "wof:name":"Gopalpurthanda",
    "wof:placetype":"locality",
    "wof:population":106
},
  "geometry": {"coordinates":[79.049451,19.237345],"type":"Point"}
}