{
  "type": "Feature",
  "properties": {
    "iso:country":"IN",
    "ks:ks_name":"Patapanga",
    "ks:ks_pop":97,
    "ks:ks_type":"HABITATION",
    "name:eng_x_preferred":[
        "Patapanga"
    ],
    "wof:name":"Patapanga",
    "wof:placetype":"locality",
    "wof:population":97
},
  "geometry": {"coordinates":[83.941264,19.840312],"type":"Point"}
}