{
  "type": "Feature",
  "properties": {
    "gn:admin1_code":"36.0",
    "gn:admin2_code":"134.0",
    "gn:asciiname":"Kutewala",
    "gn:country_code":"IN",
    "gn:dem":244,
    "gn:feature_class":"P",
    "gn:feature_code":"PPL",
    "gn:name":"K\u016btew\u0101la",
    "gn:population":0,
    "gn:timezone":"Asia/Kolkata",
    "iso:country":"IN",
    "name:und_x_variant":[
        "K\u016btew\u0101la",
        "Isl\u0101mpur"
    ],
    "wof:name":"Kutewala",
    "wof:placetype":"locality"
},
  "geometry": {"coordinates":[78.56241999999997,29.3982],"type":"Point"}
}