{
  "type": "Feature",
  "properties": {
    "iso:country":"IN",
    "ks:ks_name":"Barianai",
    "ks:ks_pop":25,
    "ks:ks_type":"HABITATION",
    "name:eng_x_preferred":[
        "Barianai"
    ],
    "wof:name":"Barianai",
    "wof:placetype":"locality",
    "wof:population":25
},
  "geometry": {"coordinates":[77.856084,12.294474],"type":"Point"}
}