{
  "type": "Feature",
  "properties": {
    "iso:country":"IN",
    "ks:ks_alt_nam":"Mans\u0101pur",
    "ks:ks_name":"Mansapur",
    "ks:ks_pop":589,
    "ks:ks_type":"VILLAGE",
    "name:eng_x_preferred":[
        "Mansapur"
    ],
    "name:eng_x_variant":[
        "Mans\u0101pur"
    ],
    "wof:name":"Mansapur",
    "wof:placetype":"locality",
    "wof:population":589
},
  "geometry": {"coordinates":[83.985214,25.262039],"type":"Point"}
}