{
  "type": "Feature",
  "properties": {
    "gn:admin1_code":"19.0",
    "gn:admin2_code":"569.0",
    "gn:asciiname":"Kenji",
    "gn:country_code":"IN",
    "gn:dem":34,
    "gn:feature_class":"P",
    "gn:feature_code":"PPL",
    "gn:name":"Kenji",
    "gn:population":0,
    "gn:timezone":"Asia/Kolkata",
    "iso:country":"IN",
    "ks:ks_name":"Kenji",
    "ks:ks_pop":90,
    "ks:ks_type":"HABITATION",
    "name:deu_x_preferred":[
        "Kenji"
    ],
    "name:eng_x_preferred":[
        "Kenji"
    ],
    "wof:name":"Kenji",
    "wof:placetype":"locality",
    "wof:population":90
},
  "geometry": {"coordinates":[74.714996,13.772243],"type":"Point"}
}