{
  "type": "Feature",
  "properties": {
    "iso:country":"IN",
    "ks:ks_name":"Punapar Baluwa Par",
    "ks:ks_pop":169,
    "ks:ks_type":"HABITATION",
    "ks:ks_uagg_main":0,
    "name:eng_x_preferred":[
        "Punapar Baluwa Par"
    ],
    "wof:name":"Punapar Baluwa Par",
    "wof:placetype":"neighbourhood",
    "wof:population":169
},
  "geometry": {"coordinates":[83.441075,26.106281],"type":"Point"}
}