{
  "type": "Feature",
  "properties": {
    "gn:admin1_code":"25.0",
    "gn:admin2_code":"619.0",
    "gn:asciiname":"Kamalapuram",
    "gn:country_code":"IN",
    "gn:dem":17,
    "gn:feature_class":"P",
    "gn:feature_code":"PPL",
    "gn:name":"Kamal\u0101puram",
    "gn:population":0,
    "gn:timezone":"Asia/Kolkata",
    "iso:country":"IN",
    "name:ceb_x_preferred":[
        "Kamalapuram"
    ],
    "name:swe_x_preferred":[
        "Kamalapuram"
    ],
    "name:vie_x_preferred":[
        "Kamalapuram"
    ],
    "wof:name":"Kamalapuram",
    "wof:placetype":"locality"
},
  "geometry": {"coordinates":[79.57417,10.73799],"type":"Point"}
}