{
  "type": "Feature",
  "properties": {
    "gn:admin1_code":"19.0",
    "gn:admin2_code":"577.0",
    "gn:asciiname":"Husgur",
    "gn:country_code":"IN",
    "gn:dem":726,
    "gn:feature_class":"P",
    "gn:feature_code":"PPL",
    "gn:name":"Husgur",
    "gn:population":0,
    "gn:timezone":"Asia/Kolkata",
    "iso:country":"IN",
    "ks:ks_name":"Husgur",
    "ks:ks_type":"VILLAGE",
    "name:eng_x_preferred":[
        "Husgur"
    ],
    "wof:name":"Husgur",
    "wof:placetype":"locality"
},
  "geometry": {"coordinates":[76.43869100000001,11.934706],"type":"Point"}
}