{
  "type": "Feature",
  "properties": {
    "iso:country":"IN",
    "ks:ks_name":"Bhawanipur Jagir",
    "ks:ks_pop":1449,
    "ks:ks_type":"VILLAGE",
    "name:eng_x_preferred":[
        "Bhawanipur Jagir"
    ],
    "wof:name":"Bhawanipur Jagir",
    "wof:placetype":"locality",
    "wof:population":1449
},
  "geometry": {"coordinates":[86.983828,25.928967],"type":"Point"}
}