{
  "type": "Feature",
  "properties": {
    "iso:country":"IN",
    "ks:ks_name":"Nagla Sharqi",
    "ks:ks_pop":5425,
    "ks:ks_type":"VILLAGE",
    "ks:ks_uagg_main":0,
    "name:eng_x_preferred":[
        "Nagla Sharqi"
    ],
    "wof:name":"Nagla Sharqi",
    "wof:placetype":"neighbourhood",
    "wof:population":5425
},
  "geometry": {"coordinates":[79.14205200000001,28.033221],"type":"Point"}
}