{
  "type": "Feature",
  "properties": {
    "gn:admin1_code":"24.0",
    "gn:admin2_code":"120.0",
    "gn:asciiname":"Bharthala",
    "gn:country_code":"IN",
    "gn:dem":294,
    "gn:feature_class":"P",
    "gn:feature_code":"PPL",
    "gn:name":"Bharthala",
    "gn:population":0,
    "gn:timezone":"Asia/Kolkata",
    "iso:country":"IN",
    "wof:name":"Bharthala",
    "wof:placetype":"locality"
},
  "geometry": {"coordinates":[76.07760999999998,26.36737],"type":"Point"}
}