{
  "type": "Feature",
  "properties": {
    "iso:country":"IN",
    "ks:ks_name":"Bohat Kheri",
    "ks:ks_pop":581,
    "ks:ks_type":"VILLAGE",
    "name:eng_x_preferred":[
        "Bohat Kheri"
    ],
    "wof:name":"Bohat Kheri",
    "wof:placetype":"locality",
    "wof:population":581
},
  "geometry": {"coordinates":[77.36134800000001,29.739002],"type":"Point"}
}