{
  "type": "Feature",
  "properties": {
    "iso:country":"IN",
    "ks:ks_name":"Rongmandu",
    "ks:ks_pop":500,
    "ks:ks_type":"HABITATION",
    "ks:ks_uagg_main":0,
    "name:eng_x_preferred":[
        "Rongmandu"
    ],
    "wof:name":"Rongmandu",
    "wof:placetype":"neighbourhood",
    "wof:population":500
},
  "geometry": {"coordinates":[92.794596,25.874492],"type":"Point"}
}