{
  "type": "Feature",
  "properties": {
    "gn:admin1_code":"35",
    "gn:admin2_code":"430.0",
    "gn:asciiname":"Beohara",
    "gn:country_code":"IN",
    "gn:dem":327,
    "gn:feature_class":"P",
    "gn:feature_code":"PPL",
    "gn:name":"Beohara",
    "gn:population":0,
    "gn:timezone":"Asia/Kolkata",
    "iso:country":"IN",
    "wof:name":"Beohara",
    "wof:placetype":"locality"
},
  "geometry": {"coordinates":[81.50830999999999,24.57486],"type":"Point"}
}