{
  "type": "Feature",
  "properties": {
    "gn:admin1_code":"2.0",
    "gn:admin2_code":"554.0",
    "gn:asciiname":"Guntipalle",
    "gn:country_code":"IN",
    "gn:dem":322,
    "gn:feature_class":"P",
    "gn:feature_code":"PPL",
    "gn:name":"Guntipalle",
    "gn:population":0,
    "gn:timezone":"Asia/Kolkata",
    "iso:country":"IN",
    "wof:name":"Guntipalle",
    "wof:placetype":"locality"
},
  "geometry": {"coordinates":[79.29751999999998,13.43534],"type":"Point"}
}