{
  "type": "Feature",
  "properties": {
    "iso:country":"IN",
    "ks:ks_name":"Kemraj Kallali Thanda",
    "ks:ks_pop":35,
    "ks:ks_type":"HABITATION",
    "ks:ks_uagg_main":0,
    "name:eng_x_preferred":[
        "Kemraj Kallali Thanda"
    ],
    "wof:name":"Kemraj Kallali Thanda",
    "wof:placetype":"neighbourhood",
    "wof:population":35
},
  "geometry": {"coordinates":[77.680717,18.361032],"type":"Point"}
}