{
  "type": "Feature",
  "properties": {
    "iso:country":"IN",
    "ks:ks_name":"Tedhawa Tola",
    "ks:ks_pop":303,
    "ks:ks_type":"HABITATION",
    "name:eng_x_preferred":[
        "Tedhawa Tola"
    ],
    "wof:name":"Tedhawa Tola",
    "wof:placetype":"locality",
    "wof:population":303
},
  "geometry": {"coordinates":[81.96228499999999,24.420625],"type":"Point"}
}