{
  "type": "Feature",
  "properties": {
    "gn:admin1_code":"40.0",
    "gn:admin2_code":"533.0",
    "gn:asciiname":"Walgoad Kalan",
    "gn:country_code":"IN",
    "gn:dem":378,
    "gn:feature_class":"P",
    "gn:feature_code":"PPL",
    "gn:name":"Walgoad Kal\u0101n",
    "gn:population":0,
    "gn:timezone":"Asia/Kolkata",
    "iso:country":"IN",
    "wof:name":"Walgoad Kalan",
    "wof:placetype":"neighbourhood"
},
  "geometry": {"coordinates":[78.42746,18.60511],"type":"Point"}
}