{
  "type": "Feature",
  "properties": {
    "gn:admin1_code":"25.0",
    "gn:admin2_code":"606.0",
    "gn:asciiname":"Kammambattu",
    "gn:country_code":"IN",
    "gn:dem":660,
    "gn:feature_class":"P",
    "gn:feature_code":"PPL",
    "gn:name":"Kammambattu",
    "gn:population":0,
    "gn:timezone":"Asia/Kolkata",
    "iso:country":"IN",
    "wof:name":"Kammambattu",
    "wof:placetype":"locality"
},
  "geometry": {"coordinates":[79.00561,12.63567],"type":"Point"}
}