{
  "type": "Feature",
  "properties": {
    "gn:admin1_code":"12",
    "gn:admin2_code":"13.0",
    "gn:asciiname":"Malikgund",
    "gn:country_code":"IN",
    "gn:dem":1915,
    "gn:feature_class":"P",
    "gn:feature_code":"PPL",
    "gn:name":"Malikgund",
    "gn:population":0,
    "gn:timezone":"Asia/Kolkata",
    "iso:country":"IN",
    "wof:name":"Malikgund",
    "wof:placetype":"locality"
},
  "geometry": {"coordinates":[74.88469000000001,33.73865],"type":"Point"}
}