{
  "type": "Feature",
  "properties": {
    "iso:country":"IN",
    "ks:ks_name":"Pathuri",
    "ks:ks_pop":419,
    "ks:ks_type":"VILLAGE",
    "ks:ks_uagg_main":0,
    "name:eng_x_preferred":[
        "Pathuri"
    ],
    "wof:name":"Pathuri",
    "wof:placetype":"neighbourhood",
    "wof:population":419
},
  "geometry": {"coordinates":[86.676351,22.187956],"type":"Point"}
}