{
  "type": "Feature",
  "properties": {
    "iso:country":"IN",
    "ks:ks_name":"Khedkarwasti",
    "ks:ks_pop":100,
    "ks:ks_type":"HABITATION",
    "name:eng_x_preferred":[
        "Khedkarwasti"
    ],
    "wof:name":"Khedkarwasti",
    "wof:placetype":"locality",
    "wof:population":100
},
  "geometry": {"coordinates":[75.256299,19.114095],"type":"Point"}
}