{
  "type": "Feature",
  "properties": {
    "iso:country":"IN",
    "ks:ks_alt_nam":"SHEMADE WASTI",
    "ks:ks_name":"Shemade Wasti",
    "ks:ks_pop":259,
    "ks:ks_type":"HABITATION",
    "name:eng_x_preferred":[
        "Shemade Wasti"
    ],
    "wof:name":"Shemade Wasti",
    "wof:placetype":"locality",
    "wof:population":259
},
  "geometry": {"coordinates":[75.17215,19.04373],"type":"Point"}
}