{
  "type": "Feature",
  "properties": {
    "gn:admin1_code":"38.0",
    "gn:admin2_code":"351.0",
    "gn:asciiname":"Majhkola",
    "gn:country_code":"IN",
    "gn:dem":60,
    "gn:feature_class":"P",
    "gn:feature_code":"PPL",
    "gn:name":"Majhkola",
    "gn:population":0,
    "gn:timezone":"Asia/Kolkata",
    "iso:country":"IN",
    "ks:ks_name":"Majh Kola",
    "ks:ks_pop":138,
    "ks:ks_type":"VILLAGE",
    "ks:ks_uagg_main":0,
    "name:eng_x_preferred":[
        "Majh Kola"
    ],
    "wof:name":"Majh Kola",
    "wof:placetype":"neighbourhood",
    "wof:population":138
},
  "geometry": {"coordinates":[87.45771499999999,25.131587],"type":"Point"}
}