{
  "type": "Feature",
  "properties": {
    "iso:country":"IN",
    "ks:ks_alt_nam":"KHATGARH RAYYAT",
    "ks:ks_name":"Khatgarh Rayyat",
    "ks:ks_pop":119,
    "ks:ks_type":"HABITATION",
    "name:eng_x_preferred":[
        "Khatgarh Rayyat"
    ],
    "wof:name":"Khatgarh Rayyat",
    "wof:placetype":"locality",
    "wof:population":119
},
  "geometry": {"coordinates":[77.694975,21.422444],"type":"Point"}
}