{
  "type": "Feature",
  "properties": {
    "iso:country":"IN",
    "ks:ks_name":"Sans",
    "ks:ks_pop":435,
    "ks:ks_type":"VILLAGE",
    "name:eng_x_preferred":[
        "Sans"
    ],
    "wof:name":"Sans",
    "wof:placetype":"locality",
    "wof:population":435
},
  "geometry": {"coordinates":[81.183848,23.456561],"type":"Point"}
}