{
  "type": "Feature",
  "properties": {
    "iso:country":"IN",
    "ks:ks_alt_nam":"JUGNIPARA manikpur",
    "ks:ks_name":"Jugnipara Manikpur",
    "ks:ks_pop":520,
    "ks:ks_type":"HABITATION",
    "name:eng_x_preferred":[
        "Jugnipara Manikpur"
    ],
    "wof:name":"Jugnipara Manikpur",
    "wof:placetype":"locality",
    "wof:population":520
},
  "geometry": {"coordinates":[83.521704,23.667301],"type":"Point"}
}