{
  "type": "Feature",
  "properties": {
    "gn:admin1_code":"21",
    "gn:admin2_code":"394.0",
    "gn:asciiname":"Anurupgarh",
    "gn:country_code":"IN",
    "gn:dem":389,
    "gn:feature_class":"P",
    "gn:feature_code":"PPL",
    "gn:name":"Anur\u016bpgarh",
    "gn:population":0,
    "gn:timezone":"Asia/Kolkata",
    "iso:country":"IN",
    "ks:ks_name":"Anupgarh",
    "ks:ks_pop":168,
    "ks:ks_type":"VILLAGE",
    "name:eng_x_preferred":[
        "Anupgarh"
    ],
    "name:eng_x_variant":[
        "Anurupgarh"
    ],
    "wof:name":"Anupgarh",
    "wof:placetype":"locality",
    "wof:population":168
},
  "geometry": {"coordinates":[82.70167499999999,20.543508],"type":"Point"}
}