{
  "type": "Feature",
  "properties": {
    "iso:country":"IN",
    "ks:ks_name":"Chettikuttimedu",
    "ks:ks_pop":150,
    "ks:ks_type":"HABITATION",
    "name:eng_x_preferred":[
        "Chettikuttimedu"
    ],
    "wof:name":"Chettikuttimedu",
    "wof:placetype":"locality",
    "wof:population":150
},
  "geometry": {"coordinates":[77.986645,11.392766],"type":"Point"}
}