{
  "type": "Feature",
  "properties": {
    "iso:country":"IN",
    "ks:ks_name":"Karaikudi",
    "ks:ks_pop":309,
    "ks:ks_type":"HABITATION",
    "name:eng_x_preferred":[
        "Karaikudi"
    ],
    "wof:name":"Karaikudi",
    "wof:placetype":"locality",
    "wof:population":309
},
  "geometry": {"coordinates":[78.60427199999999,9.613659],"type":"Point"}
}