{
  "type": "Feature",
  "properties": {
    "iso:country":"IN",
    "ks:ks_name":"Ammayanpuram",
    "ks:ks_pop":900,
    "ks:ks_type":"HABITATION",
    "name:eng_x_preferred":[
        "Ammayanpuram"
    ],
    "wof:name":"Ammayanpuram",
    "wof:placetype":"locality",
    "wof:population":900
},
  "geometry": {"coordinates":[78.921935,10.349766],"type":"Point"}
}