{
  "type": "Feature",
  "properties": {
    "gn:admin1_code":"19.0",
    "gn:admin2_code":"569.0",
    "gn:asciiname":"Inna",
    "gn:country_code":"IN",
    "gn:dem":20,
    "gn:feature_class":"P",
    "gn:feature_code":"PPLL",
    "gn:name":"Inna",
    "gn:population":0,
    "gn:timezone":"Asia/Kolkata",
    "iso:country":"IN",
    "name:ara_x_preferred":[
        "\u0625\u064a\u0646\u0627"
    ],
    "name:arz_x_preferred":[
        "\u0625\u064a\u0646\u0627"
    ],
    "name:azb_x_preferred":[
        "\u0627\u06cc\u0646\u0627"
    ],
    "name:aze_x_preferred":[
        "\u0130nna"
    ],
    "name:bul_x_preferred":[
        "\u0418\u043d\u0430"
    ],
    "name:cat_x_preferred":[
        "Inna"
    ],
    "name:ces_x_preferred":[
        "Inna"
    ],
    "name:ckb_x_preferred":[
        "\u0626\u06cc\u0646\u0627"
    ],
    "name:dan_x_preferred":[
        "Inna"
    ],
    "name:deu_x_preferred":[
        "Inna"
    ],
    "name:diq_x_preferred":[
        "Inna"
    ],
    "name:est_x_preferred":[
        "Inna"
    ],
    "name:eus_x_preferred":[
        "Inna"
    ],
    "name:fas_x_preferred":[
        "\u0627\u06cc\u0646\u0627"
    ],
    "name:fin_x_preferred":[
        "Inna"
    ],
    "name:fra_x_preferred":[
        "Inna"
    ],
    "name:glg_x_preferred":[
        "Inna"
    ],
    "name:heb_x_preferred":[
        "\u05d0\u05d9\u05e0\u05d4"
    ],
    "name:hin_x_preferred":[
        "\u0907\u0928\u094d\u0928\u093e"
    ],
    "name:hrv_x_preferred":[
        "Inna"
    ],
    "name:hun_x_preferred":[
        "Inna"
    ],
    "name:hye_x_preferred":[
        "\u053b\u0576\u0576\u0561"
    ],
    "name:ido_x_preferred":[
        "Inna"
    ],
    "name:ita_x_preferred":[
        "Inna"
    ],
    "name:jpn_x_preferred":[
        "\u30a4\u30f3\u30ca"
    ],
    "name:kat_x_preferred":[
        "Inna"
    ],
    "name:kor_x_preferred":[
        "\uc774\ub098"
    ],
    "name:mkd_x_preferred":[
        "\u0418\u043d\u0430"
    ],
    "name:mlt_x_preferred":[
        "Inna"
    ],
    "name:nld_x_preferred":[
        "Inna"
    ],
    "name:nor_x_preferred":[
        "Inna"
    ],
    "name:oci_x_preferred":[
        "Inna"
    ],
    "name:pol_x_preferred":[
        "Inna"
    ],
    "name:por_x_preferred":[
        "Inna"
    ],
    "name:ron_x_preferred":[
        "Inna"
    ],
    "name:rus_x_preferred":[
        "\u0418\u043d\u043d\u0430"
    ],
    "name:slk_x_preferred":[
        "Inna"
    ],
    "name:spa_x_preferred":[
        "Inna"
    ],
    "name:sqi_x_preferred":[
        "Inna"
    ],
    "name:srp_x_preferred":[
        "\u0418\u043d\u0430"
    ],
    "name:swe_x_preferred":[
        "Inna"
    ],
    "name:tur_x_preferred":[
        "Inna"
    ],
    "name:ukr_x_preferred":[
        "Inna"
    ],
    "name:uzb_x_preferred":[
        "Inna"
    ],
    "name:vep_x_preferred":[
        "Inna"
    ],
    "name:vie_x_preferred":[
        "Inna"
    ],
    "wof:name":"Inna",
    "wof:placetype":"locality"
},
  "geometry": {"coordinates":[74.84201999999998,13.13964],"type":"Point"}
}