{
  "type": "Feature",
  "properties": {
    "gn:admin1_code":"36",
    "gn:admin2_code":"167.0",
    "gn:asciiname":"Bharatpur",
    "gn:country_code":"IN",
    "gn:dem":319,
    "gn:feature_class":"P",
    "gn:feature_code":"PPL",
    "gn:name":"Bharatpur",
    "gn:population":0,
    "gn:timezone":"Asia/Kolkata",
    "iso:country":"IN",
    "name:bar_x_preferred":[
        "Bharatpur"
    ],
    "name:ceb_x_preferred":[
        "Bharatpur"
    ],
    "name:deu_x_preferred":[
        "Bharatpur"
    ],
    "name:epo_x_preferred":[
        "Bharatpur"
    ],
    "name:fra_x_preferred":[
        "Bharatpur"
    ],
    "name:ita_x_preferred":[
        "Bharatpur"
    ],
    "name:kor_x_preferred":[
        "\ubc14\ub78f\ud478\ub974"
    ],
    "name:mal_x_preferred":[
        "\u0d2d\u0d30\u0d24\u0d4d\u0d2a\u0d42\u0d7c"
    ],
    "name:msa_x_preferred":[
        "Bharatpur"
    ],
    "name:new_x_preferred":[
        "\u092d\u0930\u0924\u092a\u0941\u0930 \u0968"
    ],
    "name:nld_x_preferred":[
        "Bharatpur"
    ],
    "name:pnb_x_preferred":[
        "\u0628\u06c1\u0631\u062a \u067e\u0648\u0631"
    ],
    "name:swe_x_preferred":[
        "Bharatpur"
    ],
    "name:tam_x_preferred":[
        "\u0baa\u0bb0\u0ba4\u0bcd\u0baa\u0bc2\u0bb0\u0bcd"
    ],
    "name:urd_x_preferred":[
        "\u0628\u06be\u0631\u062a \u067e\u0648\u0631"
    ],
    "wof:name":"Bharatpur",
    "wof:placetype":"locality"
},
  "geometry": {"coordinates":[78.38814000000001,25.04204],"type":"Point"}
}