{
  "type": "Feature",
  "properties": {
    "gn:admin1_code":"36",
    "gn:admin2_code":"167.0",
    "gn:asciiname":"Bharatpur",
    "gn:country_code":"IN",
    "gn:dem":319,
    "gn:feature_class":"P",
    "gn:feature_code":"PPL",
    "gn:name":"Bharatpur",
    "gn:population":0,
    "gn:timezone":"Asia/Kolkata",
    "iso:country":"IN",
    "wof:name":"Bharatpur",
    "wof:placetype":"locality"
},
  "geometry": {"coordinates":[78.38814000000001,25.04204],"type":"Point"}
}