{
  "type": "Feature",
  "properties": {
    "iso:country":"IN",
    "ks:ks_name":"Dakhal Colony West",
    "ks:ks_pop":910,
    "ks:ks_type":"HABITATION",
    "name:eng_x_preferred":[
        "Dakhal Colony West"
    ],
    "wof:name":"Dakhal Colony West",
    "wof:placetype":"locality",
    "wof:population":910
},
  "geometry": {"coordinates":[89.790879,26.458884],"type":"Point"}
}