{
  "type": "Feature",
  "properties": {
    "gn:country":"IN",
    "gn:fcode":"PPL",
    "gn:pop":12871,
    "iso:country":"IN",
    "name:asm_x_preferred":[
        "\u09b2\u0995\u09cd\u09b7\u09c0\u09aa\u09c1\u09f0"
    ],
    "name:ben_x_preferred":[
        "\u09b2\u0995\u09cd\u09b7\u09c0\u09aa\u09c1\u09b0"
    ],
    "name:bpy_x_preferred":[
        "\u09b2\u0995\u09cd\u09b7\u09bf\u09aa\u09c1\u09b0"
    ],
    "name:chi_x_preferred":[
        "\u62c9\u57fa\u666e\u5c14"
    ],
    "name:dut_x_preferred":[
        "Lakhipur"
    ],
    "name:eng_x_preferred":[
        "Lakhipur"
    ],
    "name:hin_x_preferred":[
        "\u0932\u0916\u093f\u092a\u0941\u0930"
    ],
    "name:ita_x_preferred":[
        "Lakhipur"
    ],
    "name:may_x_preferred":[
        "Lakhipur"
    ],
    "name:new_x_preferred":[
        "\u0932\u0916\u093f\u092a\u0941\u0930"
    ],
    "name:swe_x_preferred":[
        "Lakhipur"
    ],
    "name:urd_x_preferred":[
        "\u0644\u06a9\u06be\u06cc\u067e\u0648\u0631"
    ],
    "name:vie_x_preferred":[
        "Lakhipur"
    ],
    "qs:name":"Lakhipur",
    "qs:photos_9r":0,
    "qs:photos_sr":0,
    "qs:pop_sr":"6",
    "wd:elevation":22.0,
    "wd:wordcount":1004,
    "wof:name":"Lakhipur",
    "wof:placetype":"locality",
    "wof:population":12871
},
  "geometry": {"coordinates":[93.0091,24.79281],"type":"Point"}
}