{
  "type": "Feature",
  "properties": {
    "iso:country":"IN",
    "ks:ks_name":"Dalka Berpani F.V.",
    "ks:ks_pop":203,
    "ks:ks_type":"VILLAGE",
    "name:eng_x_preferred":[
        "Dalka Berpani F.V."
    ],
    "wof:name":"Dalka Berpani F.V.",
    "wof:placetype":"locality",
    "wof:population":203
},
  "geometry": {"coordinates":[80.407718,22.73656],"type":"Point"}
}