{
  "type": "Feature",
  "properties": {
    "iso:country":"IN",
    "ks:ks_name":"Kutunisira",
    "ks:ks_pop":28,
    "ks:ks_type":"VILLAGE",
    "name:eng_x_preferred":[
        "Kutunisira"
    ],
    "wof:name":"Kutunisira",
    "wof:placetype":"locality",
    "wof:population":28
},
  "geometry": {"coordinates":[85.103977,20.280362],"type":"Point"}
}