{
  "type": "Feature",
  "properties": {
    "iso:country":"IN",
    "ks:ks_name":"Pattayamkudy",
    "ks:ks_pop":400,
    "ks:ks_type":"HABITATION",
    "name:eng_x_preferred":[
        "Pattayamkudy"
    ],
    "wof:name":"Pattayamkudy",
    "wof:placetype":"locality",
    "wof:population":400
},
  "geometry": {"coordinates":[76.850624,9.98915],"type":"Point"}
}