{
  "type": "Feature",
  "properties": {
    "iso:country":"IN",
    "ks:ks_name":"Nagshet",
    "ks:ks_pop":795,
    "ks:ks_type":"VILLAGE",
    "name:eng_x_preferred":[
        "Nagshet"
    ],
    "wof:name":"Nagshet",
    "wof:placetype":"locality",
    "wof:population":795
},
  "geometry": {"coordinates":[73.346056,18.484769],"type":"Point"}
}