{
  "type": "Feature",
  "properties": {
    "gn:admin1_code":"35",
    "gn:admin2_code":"426.0",
    "gn:asciiname":"Aima Khera",
    "gn:country_code":"IN",
    "gn:dem":163,
    "gn:feature_class":"P",
    "gn:feature_code":"PPL",
    "gn:name":"Aima Khera",
    "gn:population":0,
    "gn:timezone":"Asia/Kolkata",
    "iso:country":"IN",
    "wof:name":"Aima Khera",
    "wof:placetype":"locality"
},
  "geometry": {"coordinates":[80.49268000000002,25.03915],"type":"Point"}
}