{
  "type": "Feature",
  "properties": {
    "iso:country":"IN",
    "name:ara_x_preferred":[
        "\u0634\u0627\u0631\u062f\u0648\u0643\u0627\u0646"
    ],
    "name:ben_bn_x_preferred":[
        "\u099a\u09be\u09b0\u09a6\u09c1\u0995\u09be\u09a8"
    ],
    "name:ben_in_x_preferred":[
        "\u099a\u09be\u09b0\u09a6\u09c1\u0995\u09be\u09a8"
    ],
    "name:guj_x_preferred":[
        "\u0a9a\u0abe\u0ab0\u0aa6\u0ac1\u0a95\u0abe\u0aa8"
    ],
    "name:hin_x_preferred":[
        "\u091a\u093e\u0930\u0926\u0941\u0915\u093e\u0928"
    ],
    "name:kan_x_preferred":[
        "\u0c9a\u0cbe\u0cb0\u0ccd"
    ],
    "name:mal_x_preferred":[
        "\u0d1a\u0d3e\u0d7c\u0d21\u0d41\u0d15\u0d7b"
    ],
    "name:mar_x_preferred":[
        "\u091a\u093e\u0930\u0926\u0941\u0915\u093e\u0928"
    ],
    "name:pan_x_preferred":[
        "\u0a1a\u0a5c\u0a26\u0a42\u0a15\u0a28"
    ],
    "name:tam_x_preferred":[
        "\u0b9a\u0bbe\u0bb0\u0bcd\u0ba4\u0bc2\u0b95\u0bbe\u0ba9\u0bcd"
    ],
    "name:tel_x_preferred":[
        "\u0c1b\u0c3e\u0c30\u0c4d"
    ],
    "name:urd_x_preferred":[
        "\u0686\u0627\u0631\u062f\u06a9\u0627\u0646"
    ],
    "qs:name":"Chardukan",
    "qs:name_adm0":"India",
    "qs:name_adm1":"Uttarakhand",
    "qs:photos":141,
    "qs:photos_1k":29,
    "qs:photos_9k":1,
    "qs:photos_9r":3,
    "qs:photos_all":141,
    "qs:photos_sr":3,
    "qs:placetype":"Suburb",
    "qs:pop_sr":"0",
    "wof:name":"Chardukan",
    "wof:placetype":"neighbourhood"
},
  "geometry": {"coordinates":[78.097171,30.459309],"type":"Point"}
}