{
  "type": "Feature",
  "properties": {
    "iso:country":"IN",
    "qs:name":"Chardukan",
    "qs:name_adm0":"India",
    "qs:name_adm1":"Uttarakhand",
    "qs:photos":141,
    "qs:photos_1k":29,
    "qs:photos_9k":1,
    "qs:photos_9r":3,
    "qs:photos_all":141,
    "qs:photos_sr":3,
    "qs:placetype":"Suburb",
    "qs:pop_sr":"0",
    "wof:name":"Chardukan",
    "wof:placetype":"neighbourhood"
},
  "geometry": {"coordinates":[78.097171,30.459309],"type":"Point"}
}