{
  "type": "Feature",
  "properties": {
    "iso:country":"IN",
    "ks:ks_name":"Ellappakottalu",
    "ks:ks_pop":76,
    "ks:ks_type":"HABITATION",
    "name:eng_x_preferred":[
        "Ellappakottalu"
    ],
    "wof:name":"Ellappakottalu",
    "wof:placetype":"locality",
    "wof:population":76
},
  "geometry": {"coordinates":[78.342339,12.783947],"type":"Point"}
}