{
  "type": "Feature",
  "properties": {
    "iso:country":"IN",
    "ks:ks_name":"Andhari",
    "ks:ks_pop":66,
    "ks:ks_type":"VILLAGE",
    "name:eng_x_preferred":[
        "Andhari"
    ],
    "wof:name":"Andhari",
    "wof:placetype":"locality",
    "wof:population":66
},
  "geometry": {"coordinates":[76.342827,21.23289],"type":"Point"}
}