{
  "type": "Feature",
  "properties": {
    "iso:country":"IN",
    "ks:ks_alt_nam":"MOLBICHAK",
    "ks:ks_name":"Molbichak",
    "ks:ks_pop":405,
    "ks:ks_type":"HABITATION",
    "name:eng_x_preferred":[
        "Molbichak"
    ],
    "wof:name":"Molbichak",
    "wof:placetype":"locality",
    "wof:population":405
},
  "geometry": {"coordinates":[84.987674,24.893731],"type":"Point"}
}