{
  "type": "Feature",
  "properties": {
    "iso:country":"IN",
    "ks:ks_alt_nam":"chourewadi",
    "ks:ks_name":"Chourewadi",
    "ks:ks_pop":86,
    "ks:ks_type":"HABITATION",
    "name:eng_x_preferred":[
        "Chourewadi"
    ],
    "wof:name":"Chourewadi",
    "wof:placetype":"locality",
    "wof:population":86
},
  "geometry": {"coordinates":[73.506111,16.640556],"type":"Point"}
}