{
  "type": "Feature",
  "properties": {
    "gn:admin1_code":"2.0",
    "gn:admin2_code":"550.0",
    "gn:asciiname":"Dayyaladibba",
    "gn:country_code":"IN",
    "gn:dem":12,
    "gn:feature_class":"P",
    "gn:feature_code":"PPL",
    "gn:name":"Dayyaladibba",
    "gn:population":0,
    "gn:timezone":"Asia/Kolkata",
    "iso:country":"IN",
    "ks:ks_name":"Dayyaladibba",
    "ks:ks_pop":233,
    "ks:ks_type":"HABITATION",
    "name:eng_x_preferred":[
        "Dayyaladibba"
    ],
    "wof:name":"Dayyaladibba",
    "wof:placetype":"locality",
    "wof:population":233
},
  "geometry": {"coordinates":[80.10016299999999,14.057975],"type":"Point"}
}