{
  "type": "Feature",
  "properties": {
    "iso:country":"IN",
    "ks:ks_name":"Siddhi Nandi",
    "ks:ks_pop":1132,
    "ks:ks_type":"VILLAGE",
    "ks:ks_uagg_main":0,
    "name:eng_x_preferred":[
        "Siddhi Nandi"
    ],
    "wof:name":"Siddhi Nandi",
    "wof:placetype":"neighbourhood",
    "wof:population":1132
},
  "geometry": {"coordinates":[88.481522,24.073054],"type":"Point"}
}