{
  "type": "Feature",
  "properties": {
    "iso:country":"IN",
    "ks:ks_name":"Kundpani",
    "ks:ks_pop":529,
    "ks:ks_type":"VILLAGE",
    "name:eng_x_preferred":[
        "Kundpani"
    ],
    "wof:name":"Kundpani",
    "wof:placetype":"locality",
    "wof:population":529
},
  "geometry": {"coordinates":[83.28747300000001,20.644796],"type":"Point"}
}