{
  "type": "Feature",
  "properties": {
    "gn:admin1_code":"24",
    "gn:admin2_code":"103.0",
    "gn:asciiname":"Dhani Triloka",
    "gn:country_code":"IN",
    "gn:dem":283,
    "gn:feature_class":"P",
    "gn:feature_code":"PPL",
    "gn:name":"Dh\u0101ni Triloka",
    "gn:population":0,
    "gn:timezone":"Asia/Kolkata",
    "iso:country":"IN",
    "wof:name":"Dhani Triloka",
    "wof:placetype":"locality"
},
  "geometry": {"coordinates":[75.86735,28.32078],"type":"Point"}
}