{
  "type": "Feature",
  "properties": {
    "gn:admin1_code":"24",
    "gn:admin2_code":"112.0",
    "gn:asciiname":"Rir",
    "gn:country_code":"IN",
    "gn:dem":436,
    "gn:feature_class":"P",
    "gn:feature_code":"PPL",
    "gn:name":"Rir",
    "gn:population":0,
    "gn:timezone":"Asia/Kolkata",
    "iso:country":"IN",
    "wof:name":"Rir",
    "wof:placetype":"neighbourhood"
},
  "geometry": {"coordinates":[74.53856,26.70117],"type":"Point"}
}