{
  "type": "Feature",
  "properties": {
    "gn:admin1_code":"34.0",
    "gn:admin2_code":"210.0",
    "gn:asciiname":"Abalugachh",
    "gn:country_code":"IN",
    "gn:dem":58,
    "gn:feature_class":"P",
    "gn:feature_code":"PPL",
    "gn:name":"Ab\u0101lug\u0101chh",
    "gn:population":0,
    "gn:timezone":"Asia/Kolkata",
    "iso:country":"IN",
    "wof:name":"Abalugachh",
    "wof:placetype":"locality"
},
  "geometry": {"coordinates":[87.86044,26.2808],"type":"Point"}
}