{
  "type": "Feature",
  "properties": {
    "iso:country":"IN",
    "ks:ks_name":"Paripatti",
    "ks:ks_pop":1355,
    "ks:ks_type":"VILLAGE",
    "ks:ks_uagg_main":0,
    "name:eng_x_preferred":[
        "Paripatti"
    ],
    "wof:name":"Paripatti",
    "wof:placetype":"neighbourhood",
    "wof:population":1355
},
  "geometry": {"coordinates":[83.277984,26.159862],"type":"Point"}
}