{
  "type": "Feature",
  "properties": {
    "iso:country":"IN",
    "ks:ks_name":"Koradpada",
    "ks:ks_pop":189,
    "ks:ks_type":"HABITATION",
    "name:eng_x_preferred":[
        "Koradpada"
    ],
    "wof:name":"Koradpada",
    "wof:placetype":"locality",
    "wof:population":189
},
  "geometry": {"coordinates":[72.813554,19.863093],"type":"Point"}
}