{
  "type": "Feature",
  "properties": {
    "iso:country":"IN",
    "ks:ks_name":"Nandukaran Valavu",
    "ks:ks_pop":140,
    "ks:ks_type":"HABITATION",
    "name:eng_x_preferred":[
        "Nandukaran Valavu"
    ],
    "wof:name":"Nandukaran Valavu",
    "wof:placetype":"locality",
    "wof:population":140
},
  "geometry": {"coordinates":[77.813942,11.561272],"type":"Point"}
}