{
  "type": "Feature",
  "properties": {
    "gn:admin1_code":"21.0",
    "gn:admin2_code":"396.0",
    "gn:asciiname":"Tikrapada",
    "gn:country_code":"IN",
    "gn:dem":790,
    "gn:feature_class":"P",
    "gn:feature_code":"PPL",
    "gn:name":"Tikr\u0101pada",
    "gn:population":0,
    "gn:timezone":"Asia/Kolkata",
    "iso:country":"IN",
    "wof:name":"Tikrapada",
    "wof:placetype":"locality"
},
  "geometry": {"coordinates":[83.01390000000001,19.21682],"type":"Point"}
}