{
  "type": "Feature",
  "properties": {
    "iso:country":"IN",
    "ks:ks_name":"Gularia",
    "ks:ks_pop":8376,
    "ks:ks_type":"HABITATION",
    "name:eng_x_preferred":[
        "Gularia"
    ],
    "wof:name":"Gularia",
    "wof:placetype":"locality",
    "wof:population":8376
},
  "geometry": {"coordinates":[79.59226700000001,27.831814],"type":"Point"}
}