{
  "type": "Feature",
  "properties": {
    "iso:country":"IN",
    "ks:ks_name":"Lumsum Pathar",
    "ks:ks_pop":233,
    "ks:ks_type":"HABITATION",
    "name:eng_x_preferred":[
        "Lumsum Pathar"
    ],
    "wof:name":"Lumsum Pathar",
    "wof:placetype":"locality",
    "wof:population":233
},
  "geometry": {"coordinates":[92.04440700000001,26.113009],"type":"Point"}
}