{
  "type": "Feature",
  "properties": {
    "gn:admin1_code":"34.0",
    "gn:admin2_code":"219.0",
    "gn:asciiname":"Bahuara",
    "gn:country_code":"IN",
    "gn:dem":62,
    "gn:feature_class":"P",
    "gn:feature_code":"PPL",
    "gn:name":"Bahuara",
    "gn:population":0,
    "gn:timezone":"Asia/Kolkata",
    "iso:country":"IN",
    "ks:ks_name":"Bahuara",
    "ks:ks_pop":1312,
    "ks:ks_type":"VILLAGE",
    "ks:ks_uagg_main":0,
    "name:eng_x_preferred":[
        "Bahuara"
    ],
    "wof:name":"Bahuara",
    "wof:placetype":"neighbourhood",
    "wof:population":1312
},
  "geometry": {"coordinates":[84.73696700000001,26.116566],"type":"Point"}
}