{
  "type": "Feature",
  "properties": {
    "iso:country":"IN",
    "ks:ks_name":"Kakun Talla",
    "ks:ks_pop":10,
    "ks:ks_type":"VILLAGE",
    "name:eng_x_preferred":[
        "Kakun Talla"
    ],
    "wof:name":"Kakun Talla",
    "wof:placetype":"locality",
    "wof:population":10
},
  "geometry": {"coordinates":[79.106098,29.714796],"type":"Point"}
}