{
  "type": "Feature",
  "properties": {
    "iso:country":"IN",
    "ks:ks_alt_nam":"Subal para",
    "ks:ks_name":"Subal Para",
    "ks:ks_pop":201,
    "ks:ks_type":"HABITATION",
    "name:eng_x_preferred":[
        "Subal Para"
    ],
    "wof:name":"Subal Para",
    "wof:placetype":"locality",
    "wof:population":201
},
  "geometry": {"coordinates":[91.75261399999999,23.09275],"type":"Point"}
}