{
  "type": "Feature",
  "properties": {
    "gn:admin1_code":"34.0",
    "gn:admin2_code":"221.0",
    "gn:asciiname":"Akauna",
    "gn:country_code":"IN",
    "gn:dem":46,
    "gn:feature_class":"P",
    "gn:feature_code":"PPL",
    "gn:name":"Akauna",
    "gn:population":0,
    "gn:timezone":"Asia/Kolkata",
    "iso:country":"IN",
    "ks:ks_name":"Akauna",
    "ks:ks_pop":817,
    "ks:ks_type":"HABITATION",
    "name:eng_x_preferred":[
        "Akauna"
    ],
    "wof:name":"Akauna",
    "wof:placetype":"locality",
    "wof:population":817
},
  "geometry": {"coordinates":[86.21746400000001,25.789396],"type":"Point"}
}