{
  "type": "Feature",
  "properties": {
    "gn:admin1_code":"36.0",
    "gn:admin2_code":"149.0",
    "gn:asciiname":"Badshahbad",
    "gn:country_code":"IN",
    "gn:dem":169,
    "gn:feature_class":"P",
    "gn:feature_code":"PPL",
    "gn:name":"B\u0101dsh\u0101hb\u0101d",
    "gn:population":0,
    "gn:timezone":"Asia/Kolkata",
    "iso:country":"IN",
    "wof:name":"Badshahbad",
    "wof:placetype":"locality"
},
  "geometry": {"coordinates":[78.73365,28.0656],"type":"Point"}
}