{
  "type": "Feature",
  "properties": {
    "gn:admin1_code":"36",
    "gn:admin2_code":"146.0",
    "gn:asciiname":"Ataiyapura",
    "gn:country_code":"IN",
    "gn:dem":165,
    "gn:feature_class":"P",
    "gn:feature_code":"PPL",
    "gn:name":"Ataiy\u0101pura",
    "gn:population":0,
    "gn:timezone":"Asia/Kolkata",
    "iso:country":"IN",
    "ks:ks_name":"Atai Pura",
    "ks:ks_pop":270,
    "ks:ks_type":"HABITATION",
    "name:eng_x_preferred":[
        "Atai Pura"
    ],
    "name:eng_x_variant":[
        "Ataiyapura"
    ],
    "wof:name":"Atai Pura",
    "wof:placetype":"locality",
    "wof:population":270
},
  "geometry": {"coordinates":[78.384219,26.908673],"type":"Point"}
}