{
  "type": "Feature",
  "properties": {
    "iso:country":"IN",
    "ks:ks_alt_nam":"Gh\u0101ta",
    "ks:ks_name":"Ghata",
    "ks:ks_pop":713,
    "ks:ks_type":"VILLAGE",
    "name:eng_x_preferred":[
        "Ghata"
    ],
    "name:eng_x_variant":[
        "Gh\u0101ta"
    ],
    "wof:name":"Ghata",
    "wof:placetype":"locality",
    "wof:population":713
},
  "geometry": {"coordinates":[73.30601900000001,24.695475],"type":"Point"}
}