{
  "type": "Feature",
  "properties": {
    "gn:admin1_code":"2.0",
    "gn:admin2_code":"542.0",
    "gn:asciiname":"Ravichendri",
    "gn:country_code":"IN",
    "gn:dem":42,
    "gn:feature_class":"P",
    "gn:feature_code":"PPL",
    "gn:name":"R\u0101vichendri",
    "gn:population":0,
    "gn:timezone":"Asia/Kolkata",
    "iso:country":"IN",
    "wof:name":"Ravichendri",
    "wof:placetype":"locality"
},
  "geometry": {"coordinates":[83.92354,18.60488],"type":"Point"}
}