{
  "type": "Feature",
  "properties": {
    "iso:country":"IN",
    "ks:ks_alt_nam":"Bakna pandripani",
    "ks:ks_name":"Bakna Pandripani",
    "ks:ks_pop":587,
    "ks:ks_type":"HABITATION",
    "name:eng_x_preferred":[
        "Bakna Pandripani"
    ],
    "wof:name":"Bakna Pandripani",
    "wof:placetype":"locality",
    "wof:population":587
},
  "geometry": {"coordinates":[82.69356500000001,23.179382],"type":"Point"}
}