{
  "type": "Feature",
  "properties": {
    "iso:country":"IN",
    "ks:ks_name":"Mediya",
    "ks:ks_pop":1030,
    "ks:ks_type":"VILLAGE",
    "name:eng_x_preferred":[
        "Mediya"
    ],
    "wof:name":"Mediya",
    "wof:placetype":"locality",
    "wof:population":1030
},
  "geometry": {"coordinates":[74.32246000000001,26.127669],"type":"Point"}
}