{
  "type": "Feature",
  "properties": {
    "iso:country":"IN",
    "ks:ks_name":"Samathuvapuram",
    "ks:ks_pop":57,
    "ks:ks_type":"HABITATION",
    "name:eng_x_preferred":[
        "Samathuvapuram"
    ],
    "wof:name":"Samathuvapuram",
    "wof:placetype":"locality",
    "wof:population":57
},
  "geometry": {"coordinates":[78.90598199999999,10.729575],"type":"Point"}
}