{
  "type": "Feature",
  "properties": {
    "gn:country":"IN",
    "gn:fcode":"PPL",
    "gn:population":40662,
    "iso:country":"IN",
    "name:ara_x_preferred":[
        "\u0645\u0646\u0637\u0642\u0629 \u062c\u0627\u0631\u0647\u0648\u0627"
    ],
    "name:ben_x_preferred":[
        "\u0997\u09b0\u09cd\u09ac"
    ],
    "name:bho_x_preferred":[
        "\u0917\u0922\u093c\u0935\u093e"
    ],
    "name:bpy_x_preferred":[
        "\u0997\u09b0\u09b9\u09f1\u09be"
    ],
    "name:ceb_x_preferred":[
        "Garwa"
    ],
    "name:deu_x_preferred":[
        "Garhwa"
    ],
    "name:eng_x_preferred":[
        "Garhwa"
    ],
    "name:fra_x_preferred":[
        "Garhwa"
    ],
    "name:guj_x_preferred":[
        "\u0a97\u0aa2\u0ab5\u0abe"
    ],
    "name:hin_x_preferred":[
        "\u0917\u0922\u0935\u093e"
    ],
    "name:ita_x_preferred":[
        "Garhwa"
    ],
    "name:jpn_x_preferred":[
        "\u30ac\u30fc\u30ef"
    ],
    "name:kan_x_preferred":[
        "\u0c97\u0cb0\u0ccd\u0cb9\u0ccd\u0cb5\u0cbe"
    ],
    "name:kor_x_preferred":[
        "\uac00\ub974\uc640"
    ],
    "name:mai_x_preferred":[
        "\u0917\u0922\u0935\u093e"
    ],
    "name:mar_x_preferred":[
        "\u0917\u0922\u0935\u093e"
    ],
    "name:mlg_x_preferred":[
        "Garhwa"
    ],
    "name:msa_x_preferred":[
        "Garhwa"
    ],
    "name:nep_x_preferred":[
        "\u0917\u0922\u0935\u093e"
    ],
    "name:new_x_preferred":[
        "\u0917\u0930\u094d\u0935\u093e"
    ],
    "name:nld_x_preferred":[
        "Garhwa"
    ],
    "name:por_x_preferred":[
        "Garhwa"
    ],
    "name:rus_x_preferred":[
        "\u0413\u0430\u0440\u0445\u0432\u0430"
    ],
    "name:san_x_preferred":[
        "\u0917\u0922\u0935\u093e"
    ],
    "name:spa_x_preferred":[
        "Garhwa"
    ],
    "name:swe_x_preferred":[
        "Garhwa"
    ],
    "name:tam_x_preferred":[
        "\u0b95\u0bbe\u0bb0\u0bcd\u0bb9\u0bb5\u0bbe"
    ],
    "name:tel_x_preferred":[
        "\u0c17\u0c3e\u0c30\u0c4d\u0c35\u0c3e"
    ],
    "name:urd_x_preferred":[
        "\u06af\u0691\u06be\u0648\u0627"
    ],
    "name:vie_x_preferred":[
        "Garhwa"
    ],
    "name:zho_x_preferred":[
        "\u52a0\u5c14\u8d6b\u74e6"
    ],
    "qs:name":"Garwa",
    "qs:photos_9r":0,
    "qs:photos_sr":0,
    "qs:pop_sr":"7",
    "wof:name":"Garwa",
    "wof:placetype":"locality",
    "wof:population":40662
},
  "geometry": {"coordinates":[83.81037000000001,24.16291],"type":"Point"}
}