{
  "type": "Feature",
  "properties": {
    "gn:admin1_code":"37.0",
    "gn:admin2_code":"408.0",
    "gn:asciiname":"Khajri",
    "gn:country_code":"IN",
    "gn:dem":312,
    "gn:feature_class":"P",
    "gn:feature_code":"PPL",
    "gn:name":"Khajri",
    "gn:population":0,
    "gn:timezone":"Asia/Kolkata",
    "iso:country":"IN",
    "wof:name":"Khajri",
    "wof:placetype":"locality"
},
  "geometry": {"coordinates":[81.07937,21.32122],"type":"Point"}
}