{
  "type": "Feature",
  "properties": {
    "iso:country":"IN",
    "ks:ks_name":"Sabeya Musai",
    "ks:ks_pop":421,
    "ks:ks_type":"HABITATION",
    "name:eng_x_preferred":[
        "Sabeya Musai"
    ],
    "wof:name":"Sabeya Musai",
    "wof:placetype":"locality",
    "wof:population":421
},
  "geometry": {"coordinates":[84.07046,27.1862],"type":"Point"}
}