{
  "type": "Feature",
  "properties": {
    "iso:country":"IN",
    "ks:ks_alt_nam":"WARD NO -II",
    "ks:ks_name":"Ward No -ii",
    "ks:ks_pop":552,
    "ks:ks_type":"HABITATION",
    "name:eng_x_preferred":[
        "Ward No -ii"
    ],
    "wof:name":"Ward No -ii",
    "wof:placetype":"locality",
    "wof:population":552
},
  "geometry": {"coordinates":[91.285802,23.538734],"type":"Point"}
}