{
  "type": "Feature",
  "properties": {
    "gn:admin1_code":"24.0",
    "gn:admin2_code":"110",
    "gn:asciiname":"Keslahala",
    "gn:country_code":"IN",
    "gn:dem":407,
    "gn:feature_class":"P",
    "gn:feature_code":"PPL",
    "gn:name":"Kesl\u0101h\u0101la",
    "gn:population":0,
    "gn:timezone":"Asia/Kolkata",
    "iso:country":"IN",
    "name:und_x_variant":[
        "Kesl\u0101h\u0101la",
        "Kes\u0101la"
    ],
    "wof:name":"Keslahala",
    "wof:placetype":"locality"
},
  "geometry": {"coordinates":[75.56293000000002,26.90911],"type":"Point"}
}