{
  "type": "Feature",
  "properties": {
    "iso:country":"IN",
    "ks:ks_name":"Chabhi",
    "ks:ks_pop":78,
    "ks:ks_type":"VILLAGE",
    "name:eng_x_preferred":[
        "Chabhi"
    ],
    "wof:name":"Chabhi",
    "wof:placetype":"locality",
    "wof:population":78
},
  "geometry": {"coordinates":[87.483615,24.631247],"type":"Point"}
}