{
  "type": "Feature",
  "properties": {
    "iso:country":"IN",
    "ks:ks_name":"Dubbathanda",
    "ks:ks_pop":558,
    "ks:ks_type":"HABITATION",
    "ks:ks_uagg_main":0,
    "name:eng_x_preferred":[
        "Dubbathanda"
    ],
    "wof:name":"Dubbathanda",
    "wof:placetype":"neighbourhood",
    "wof:population":558
},
  "geometry": {"coordinates":[79.518918,16.842352],"type":"Point"}
}