{
  "type": "Feature",
  "properties": {
    "gn:admin1_code":"24.0",
    "gn:admin2_code":"109.0",
    "gn:asciiname":"Banjipad",
    "gn:country_code":"IN",
    "gn:dem":516,
    "gn:feature_class":"P",
    "gn:feature_code":"PPL",
    "gn:name":"B\u0101nj\u012bp\u0101d",
    "gn:population":0,
    "gn:timezone":"Asia/Kolkata",
    "iso:country":"IN",
    "wof:name":"Banjipad",
    "wof:placetype":"locality"
},
  "geometry": {"coordinates":[76.47634000000002,26.70884],"type":"Point"}
}