{
  "type": "Feature",
  "properties": {
    "gn:country":"IN",
    "gn:fcode":"PPL",
    "gn:pop":0,
    "iso:country":"IN",
    "name:eng_x_preferred":[
        "Dharmasthala"
    ],
    "name:hin_x_preferred":[
        "\u0927\u0930\u094d\u092e\u0938\u094d\u0925\u0932"
    ],
    "name:kan_x_preferred":[
        "\u0ca7\u0cb0\u0ccd\u0cae\u0cb8\u0ccd\u0ca5\u0cb3"
    ],
    "name:mal_x_preferred":[
        "\u0d27\u0d7c\u0d2e\u0d4d\u0d2e\u0d38\u0d4d\u0d25\u0d32"
    ],
    "name:nld_x_preferred":[
        "Dharmasthala"
    ],
    "name:rus_x_preferred":[
        "\u0414\u0445\u0430\u0440\u043c\u0430\u0441\u0442\u0430\u043b\u0430"
    ],
    "name:san_x_preferred":[
        "\u0927\u0930\u094d\u092e\u0938\u094d\u0925\u0932\u092e\u094d"
    ],
    "name:tam_x_preferred":[
        "\u0ba4\u0bb0\u0bcd\u0bae\u0bb8\u0bcd\u0ba4\u0bb2\u0bbe"
    ],
    "name:tcy_x_preferred":[
        "\u0ca7\u0cb0\u0ccd\u0cae\u0cb8\u0ccd\u0ca5\u0cb3"
    ],
    "name:tel_x_preferred":[
        "\u0c27\u0c30\u0c4d\u0c2e\u0c38\u0c4d\u0c25\u0c32"
    ],
    "name:unk_x_variant":[
        "Dharmastala"
    ],
    "name:urd_x_preferred":[
        "\u062f\u06be\u0631\u0645 \u0627\u0633\u062a\u06be\u0627\u0644\u0627"
    ],
    "name:vie_x_preferred":[
        "Dharmasthala"
    ],
    "name:xmf_x_preferred":[
        "\u10d3\u10f0\u10d0\u10e0\u10db\u10d0\u10e1\u10e2\u10d0\u10da\u10d0"
    ],
    "qs:name":"Dharmasthala",
    "qs:name_adm0":"India",
    "qs:name_adm1":"Karnataka",
    "qs:photos":77,
    "qs:photos_1k":16,
    "qs:photos_9k":1,
    "qs:photos_9r":3,
    "qs:photos_all":77,
    "qs:photos_sr":3,
    "qs:placetype":"Town",
    "qs:pop_sr":"3",
    "wd:wordcount":1578,
    "wof:name":"Dharmasthala",
    "wof:placetype":"locality",
    "wof:population":0
},
  "geometry": {"coordinates":[75.38070999999999,12.94792],"type":"Point"}
}