{
  "type": "Feature",
  "properties": {
    "iso:country":"IN",
    "ks:ks_name":"Kudimittipatti",
    "ks:ks_pop":540,
    "ks:ks_type":"HABITATION",
    "name:eng_x_preferred":[
        "Kudimittipatti"
    ],
    "wof:name":"Kudimittipatti",
    "wof:placetype":"locality",
    "wof:population":540
},
  "geometry": {"coordinates":[78.867653,13.053162],"type":"Point"}
}