{
  "type": "Feature",
  "properties": {
    "iso:country":"IN",
    "ks:ks_name":"Dhodhiawad",
    "ks:ks_pop":505,
    "ks:ks_type":"HABITATION",
    "name:eng_x_preferred":[
        "Dhodhiawad"
    ],
    "wof:name":"Dhodhiawad",
    "wof:placetype":"locality",
    "wof:population":505
},
  "geometry": {"coordinates":[73.081639,20.544972],"type":"Point"}
}