{
  "type": "Feature",
  "properties": {
    "iso:country":"IN",
    "ks:ks_name":"Haripurpaitari",
    "ks:ks_pop":34,
    "ks:ks_type":"VILLAGE",
    "name:eng_x_preferred":[
        "Haripurpaitari"
    ],
    "wof:name":"Haripurpaitari",
    "wof:placetype":"locality",
    "wof:population":34
},
  "geometry": {"coordinates":[84.71671600000001,19.516527],"type":"Point"}
}