{
  "type": "Feature",
  "properties": {
    "iso:country":"IN",
    "ks:ks_name":"Barudi",
    "ks:ks_pop":735,
    "ks:ks_type":"HABITATION",
    "name:eng_x_preferred":[
        "Barudi"
    ],
    "wof:name":"Barudi",
    "wof:placetype":"locality",
    "wof:population":735
},
  "geometry": {"coordinates":[85.963381,23.27037],"type":"Point"}
}