{
  "type": "Feature",
  "properties": {
    "gn:admin1_code":"2",
    "gn:admin2_code":"545.0",
    "gn:asciiname":"Gundrali",
    "gn:country_code":"IN",
    "gn:dem":706,
    "gn:feature_class":"P",
    "gn:feature_code":"PPL",
    "gn:name":"Gundr\u0101li",
    "gn:population":0,
    "gn:timezone":"Asia/Kolkata",
    "iso:country":"IN",
    "ks:ks_name":"Gundrathi",
    "ks:ks_pop":64,
    "ks:ks_type":"HABITATION",
    "name:eng_x_preferred":[
        "Gundrathi"
    ],
    "name:eng_x_variant":[
        "Gundrali"
    ],
    "wof:name":"Gundrathi",
    "wof:placetype":"locality",
    "wof:population":64
},
  "geometry": {"coordinates":[81.78228799999999,17.791593],"type":"Point"}
}