{
  "type": "Feature",
  "properties": {
    "iso:country":"IN",
    "ks:ks_name":"Kelaginagomala",
    "ks:ks_pop":132,
    "ks:ks_type":"HABITATION",
    "name:eng_x_preferred":[
        "Kelaginagomala"
    ],
    "wof:name":"Kelaginagomala",
    "wof:placetype":"locality",
    "wof:population":132
},
  "geometry": {"coordinates":[75.027839,14.603727],"type":"Point"}
}