{
  "type": "Feature",
  "properties": {
    "gn:admin1_code":"10",
    "gn:admin2_code":"86.0",
    "gn:asciiname":"Dhani Sunderpur",
    "gn:country_code":"IN",
    "gn:dem":218,
    "gn:feature_class":"P",
    "gn:feature_code":"PPL",
    "gn:name":"Dh\u0101ni Sunderpur",
    "gn:population":0,
    "gn:timezone":"Asia/Kolkata",
    "iso:country":"IN",
    "wof:name":"Dhani Sunderpur",
    "wof:placetype":"locality"
},
  "geometry": {"coordinates":[76.73354999999999,28.46011],"type":"Point"}
}