{
  "type": "Feature",
  "properties": {
    "iso:country":"IN",
    "name:amh_x_preferred":[
        "\u1293\u130b\u122d\u1301\u1290\u12ae\u122d\u1295\u12f0"
    ],
    "name:ben_x_preferred":[
        "\u09a8\u09be\u0997\u09be\u09b0\u09cd\u099c\u09c1\u09a8\u09be\u0995\u09cb\u09a8\u09cd\u09a1\u09be"
    ],
    "name:deu_x_preferred":[
        "Nagarjunakonda"
    ],
    "name:eng_x_preferred":[
        "Nagarjunakonda"
    ],
    "name:fas_x_preferred":[
        "\u0646\u0627\u06af\u0627\u0631\u062c\u0648\u0646\u0627\u06a9\u0648\u0646\u062f\u0627"
    ],
    "name:fra_x_preferred":[
        "Nagarjunakonda"
    ],
    "name:heb_x_preferred":[
        "\u05e0\u05d2\u05d0\u05e8\u05d2'\u05d5\u05e0\u05e7\u05d5\u05e0\u05d3\u05d4"
    ],
    "name:hin_x_preferred":[
        "\u0928\u093e\u0917\u093e\u0930\u094d\u091c\u0941\u0928\u0915\u094b\u0902\u0921\u093e"
    ],
    "name:jpn_x_preferred":[
        "\u30ca\u30fc\u30ac\u30eb\u30b8\u30e5\u30ca\u30b3\u30f3\u30c0"
    ],
    "name:kor_x_preferred":[
        "\ub098\uac00\ub974\uc8fc\ub098\ucf58\ub2e4"
    ],
    "name:mal_x_preferred":[
        "\u0d28\u0d3e\u0d17\u0d3e\u0d7c\u0d1c\u0d41\u0d28\u0d15\u0d4a\u0d23\u0d4d\u0d1f"
    ],
    "name:mar_x_preferred":[
        "\u0928\u093e\u0917\u093e\u0930\u094d\u091c\u0941\u0928\u0915\u094b\u0902\u0921\u093e"
    ],
    "name:nld_x_preferred":[
        "Nagarjunakonda"
    ],
    "name:ori_x_preferred":[
        "\u0b28\u0b3e\u0b17\u0b3e\u0b30\u0b4d\u0b1c\u0b41\u0b28\u0b15\u0b4b\u0b23\u0b4d\u0b21\u0b3e"
    ],
    "name:san_x_preferred":[
        "\u0928\u093e\u0917\u093e\u0930\u094d\u091c\u0941\u0928\u0915\u094b\u0923\u094d\u0921"
    ],
    "name:tam_x_preferred":[
        "\u0ba8\u0bbe\u0b95\u0bbe\u0bb0\u0bcd\u0b9c\u0bc1\u0ba9\u0b95\u0bca\u0ba3\u0bcd\u0b9f\u0bbe"
    ],
    "name:tel_x_preferred":[
        "\u0c28\u0c3e\u0c17\u0c3e\u0c30\u0c4d\u0c1c\u0c41\u0c28\u0c15\u0c4a\u0c02\u0c21 \u0c2e\u0c4d\u0c2f\u0c42\u0c1c\u0c3f\u0c2f\u0c02"
    ],
    "name:urd_x_preferred":[
        "\u0646\u0627\u06af\u0627\u0631\u062c\u0646 \u06a9\u0648\u0646\u0688\u0627"
    ],
    "qs:name":"Nagarjuna Konda",
    "qs:name_adm0":"India",
    "qs:name_adm1":"Andhra Pradesh",
    "qs:photos":92,
    "qs:photos_1k":19,
    "qs:photos_9k":1,
    "qs:photos_9r":3,
    "qs:photos_all":92,
    "qs:photos_sr":3,
    "qs:placetype":"Town",
    "qs:pop_sr":"0",
    "wd:wordcount":1019,
    "wof:name":"Nagarjuna Konda",
    "wof:placetype":"locality"
},
  "geometry": {"coordinates":[79.22721799999999,16.545544],"type":"Point"}
}