{
  "type": "Feature",
  "properties": {
    "iso:country":"IN",
    "name:amh_x_preferred":[
        "\u1293\u130b\u122d\u1301\u1290\u12ae\u122d\u1295\u12f0"
    ],
    "name:ben_x_preferred":[
        "\u09a8\u09be\u0997\u09be\u09b0\u09cd\u099c\u09c1\u09a8\u09be\u0995\u09cb\u09a8\u09cd\u09a1\u09be"
    ],
    "name:deu_x_preferred":[
        "Nagarjunakonda"
    ],
    "name:eng_x_preferred":[
        "Nagarjunakonda"
    ],
    "name:fra_x_preferred":[
        "Nagarjunakonda"
    ],
    "name:hin_x_preferred":[
        "\u0928\u093e\u0917\u093e\u0930\u094d\u091c\u0941\u0928\u0915\u094b\u0902\u0921\u093e"
    ],
    "name:jpn_x_preferred":[
        "\u30ca\u30fc\u30ac\u30eb\u30b8\u30e5\u30ca\u30b3\u30f3\u30c0"
    ],
    "name:kor_x_preferred":[
        "\ub098\uac00\ub974\uc8fc\ub098\ucf58\ub2e4"
    ],
    "name:nld_x_preferred":[
        "Nagarjunakonda"
    ],
    "name:san_x_preferred":[
        "\u0928\u093e\u0917\u093e\u0930\u094d\u091c\u0941\u0928\u0915\u094b\u0923\u094d\u0921"
    ],
    "name:tam_x_preferred":[
        "\u0ba8\u0bbe\u0b95\u0bbe\u0bb0\u0bcd\u0b9c\u0bc1\u0ba9\u0b95\u0bca\u0ba3\u0bcd\u0b9f\u0bbe"
    ],
    "name:tel_x_preferred":[
        "\u0c28\u0c3e\u0c17\u0c3e\u0c30\u0c4d\u0c1c\u0c41\u0c28\u0c15\u0c4a\u0c02\u0c21 \u0c2e\u0c4d\u0c2f\u0c42\u0c1c\u0c3f\u0c2f\u0c02"
    ],
    "qs:name":"Nagarjuna Konda",
    "qs:name_adm0":"India",
    "qs:name_adm1":"Andhra Pradesh",
    "qs:photos":92,
    "qs:photos_1k":19,
    "qs:photos_9k":1,
    "qs:photos_9r":3,
    "qs:photos_all":92,
    "qs:photos_sr":3,
    "qs:placetype":"Town",
    "qs:pop_sr":"0",
    "wd:wordcount":1019,
    "wof:name":"Nagarjuna Konda",
    "wof:placetype":"locality"
},
  "geometry": {"coordinates":[79.22721799999999,16.545544],"type":"Point"}
}