{
  "type": "Feature",
  "properties": {
    "iso:country":"IN",
    "ks:ks_name":"Koranpalle",
    "ks:ks_pop":104,
    "ks:ks_type":"VILLAGE",
    "name:eng_x_preferred":[
        "Koranpalle"
    ],
    "wof:name":"Koranpalle",
    "wof:placetype":"locality",
    "wof:population":104
},
  "geometry": {"coordinates":[77.812915,18.32065],"type":"Point"}
}