{
  "type": "Feature",
  "properties": {
    "gn:admin1_code":"36",
    "gn:admin2_code":"154.0",
    "gn:asciiname":"Yaqubpur",
    "gn:country_code":"IN",
    "gn:dem":127,
    "gn:feature_class":"P",
    "gn:feature_code":"PPL",
    "gn:name":"Yaq\u016bbpur",
    "gn:population":0,
    "gn:timezone":"Asia/Kolkata",
    "iso:country":"IN",
    "name:ara_x_preferred":[
        "\u064a\u0627\u0642\u0648 \u0628\u0648\u0631"
    ],
    "name:ben_bn_x_preferred":[
        "\u0987\u09df\u09be\u0995\u09c1\u09ac\u09aa\u09c1\u09b0"
    ],
    "name:ben_in_x_preferred":[
        "\u0987\u09df\u09be\u0995\u09c1\u09ac\u09aa\u09c1\u09b0"
    ],
    "name:guj_x_preferred":[
        "\u0aaf\u0abe\u0a95\u0aac\u0aaa\u0ac1\u0ab0"
    ],
    "name:hin_x_preferred":[
        "\u092f\u093e\u0958\u0942\u092c\u092a\u0941\u0930"
    ],
    "name:kan_x_preferred":[
        "\u0caf\u0cbe\u0c96\u0cc2\u0cac\u0ccd"
    ],
    "name:mal_x_preferred":[
        "\u0d2f\u0d3e\u0d15\u0d4d\u0d15\u0d42\u0d2a\u0d42\u0d7c"
    ],
    "name:mar_x_preferred":[
        "\u092f\u093e\u0915\u0942\u092c\u092a\u0942\u0930"
    ],
    "name:pan_x_preferred":[
        "\u0a2f\u0a3e\u0a15\u0a42\u0a2c\u0a2a\u0a41\u0a30"
    ],
    "name:tam_x_preferred":[
        "\u0baf\u0b95\u0bbe\u0baa\u0bcd\u0baa\u0bc2\u0bb0\u0bcd"
    ],
    "name:tel_x_preferred":[
        "\u0c2f\u0c3e\u0c15\u0c41\u0c2c\u0c4d"
    ],
    "name:urd_x_preferred":[
        "\u06cc\u0639\u0642\u0648\u0628 \u067e\u0648\u0631"
    ],
    "wof:name":"Yaqubpur",
    "wof:placetype":"locality"
},
  "geometry": {"coordinates":[81.18581999999998,27.28265],"type":"Point"}
}