{
  "type": "Feature",
  "properties": {
    "iso:country":"IN",
    "ks:ks_name":"Bhadakamba",
    "ks:ks_pop":197,
    "ks:ks_type":"HABITATION",
    "name:eng_x_preferred":[
        "Bhadakamba"
    ],
    "wof:name":"Bhadakamba",
    "wof:placetype":"locality",
    "wof:population":197
},
  "geometry": {"coordinates":[73.295278,17.535833],"type":"Point"}
}