{
  "type": "Feature",
  "properties": {
    "iso:country":"IN",
    "ks:ks_name":"Purihasa",
    "ks:ks_pop":7175,
    "ks:ks_type":"VILLAGE",
    "name:eng_x_preferred":[
        "Purihasa"
    ],
    "wof:name":"Purihasa",
    "wof:placetype":"neighbourhood",
    "wof:population":7175
},
  "geometry": {"coordinates":[86.185531,22.730664],"type":"Point"}
}