{
  "type": "Feature",
  "properties": {
    "iso:country":"IN",
    "ks:ks_name":"Chennamkari",
    "ks:ks_pop":1401,
    "ks:ks_type":"HABITATION",
    "name:eng_x_preferred":[
        "Chennamkari"
    ],
    "wof:name":"Chennamkari",
    "wof:placetype":"locality",
    "wof:population":1401
},
  "geometry": {"coordinates":[76.365939,9.458023],"type":"Point"}
}