{
  "type": "Feature",
  "properties": {
    "gn:admin1_code":"12",
    "gn:admin2_code":"15.0",
    "gn:asciiname":"Kilabal",
    "gn:country_code":"IN",
    "gn:dem":1897,
    "gn:feature_class":"P",
    "gn:feature_code":"PPL",
    "gn:name":"Kilabal",
    "gn:population":0,
    "gn:timezone":"Asia/Kolkata",
    "iso:country":"IN",
    "wof:name":"Kilabal",
    "wof:placetype":"locality"
},
  "geometry": {"coordinates":[74.92469,33.67589],"type":"Point"}
}