{
  "type": "Feature",
  "properties": {
    "iso:country":"IN",
    "ks:ks_alt_nam":"thillaicheetiyapatti",
    "ks:ks_name":"Thillaicheetiyapatti",
    "ks:ks_pop":35,
    "ks:ks_type":"HABITATION",
    "name:eng_x_preferred":[
        "Thillaicheetiyapatti"
    ],
    "wof:name":"Thillaicheetiyapatti",
    "wof:placetype":"locality",
    "wof:population":35
},
  "geometry": {"coordinates":[78.482467,10.535607],"type":"Point"}
}