{
  "type": "Feature",
  "properties": {
    "iso:country":"IN",
    "ks:ks_name":"Atchiahpalem",
    "ks:ks_pop":1191,
    "ks:ks_type":"VILLAGE",
    "ks:ks_uagg_main":0,
    "name:eng_x_preferred":[
        "Atchiahpalem"
    ],
    "wof:name":"Atchiahpalem",
    "wof:placetype":"neighbourhood",
    "wof:population":1191
},
  "geometry": {"coordinates":[81.382761,17.21158],"type":"Point"}
}