{
  "type": "Feature",
  "properties": {
    "iso:country":"IN",
    "ks:ks_name":"Mandrooponiyon Ki Dhani",
    "ks:ks_pop":703,
    "ks:ks_type":"HABITATION",
    "name:eng_x_preferred":[
        "Mandrooponiyon Ki Dhani"
    ],
    "wof:name":"Mandrooponiyon Ki Dhani",
    "wof:placetype":"locality",
    "wof:population":703
},
  "geometry": {"coordinates":[71.752286,26.030928],"type":"Point"}
}