{
  "type": "Feature",
  "properties": {
    "gn:admin1_code":"35",
    "gn:admin2_code":"426.0",
    "gn:asciiname":"Rohania",
    "gn:country_code":"IN",
    "gn:dem":544,
    "gn:feature_class":"P",
    "gn:feature_code":"PPL",
    "gn:name":"Rohania",
    "gn:population":0,
    "gn:timezone":"Asia/Kolkata",
    "iso:country":"IN",
    "ks:ks_name":"Rohania",
    "ks:ks_pop":363,
    "ks:ks_type":"HABITATION",
    "name:eng_x_preferred":[
        "Rohania"
    ],
    "wof:name":"Rohania",
    "wof:placetype":"locality",
    "wof:population":363
},
  "geometry": {"coordinates":[80.524165,24.194909],"type":"Point"}
}