{
  "type": "Feature",
  "properties": {
    "iso:country":"IN",
    "ks:ks_name":"P .burhien",
    "ks:ks_pop":126,
    "ks:ks_type":"HABITATION",
    "ks:ks_uagg_main":0,
    "name:eng_x_preferred":[
        "P .burhien"
    ],
    "wof:name":"P .burhien",
    "wof:placetype":"neighbourhood",
    "wof:population":126
},
  "geometry": {"coordinates":[81.350101,26.142345],"type":"Point"}
}