{
  "type": "Feature",
  "properties": {
    "iso:country":"IN",
    "ks:ks_name":"Shrivana",
    "ks:ks_pop":29,
    "ks:ks_type":"HABITATION",
    "name:eng_x_preferred":[
        "Shrivana"
    ],
    "wof:name":"Shrivana",
    "wof:placetype":"locality",
    "wof:population":29
},
  "geometry": {"coordinates":[74.843864,14.395431],"type":"Point"}
}