{
  "type": "Feature",
  "properties": {
    "iso:country":"IN",
    "ks:ks_name":"Athanga",
    "ks:ks_pop":813,
    "ks:ks_type":"VILLAGE",
    "ks:ks_uagg_main":0,
    "name:eng_x_preferred":[
        "Athanga"
    ],
    "wof:name":"Athanga",
    "wof:placetype":"neighbourhood",
    "wof:population":813
},
  "geometry": {"coordinates":[86.065303,20.18322],"type":"Point"}
}