{
  "type": "Feature",
  "properties": {
    "iso:country":"IN",
    "ks:ks_name":"Jamuguda",
    "ks:ks_pop":29,
    "ks:ks_type":"HABITATION",
    "name:eng_x_preferred":[
        "Jamuguda"
    ],
    "wof:name":"Jamuguda",
    "wof:placetype":"locality",
    "wof:population":29
},
  "geometry": {"coordinates":[83.04826,18.262696],"type":"Point"}
}