{
  "type": "Feature",
  "properties": {
    "gn:admin1_code":"35",
    "gn:admin2_code":"467.0",
    "gn:asciiname":"Gambhirpura",
    "gn:country_code":"IN",
    "gn:dem":460,
    "gn:feature_class":"P",
    "gn:feature_code":"PPL",
    "gn:name":"Gambh\u012brpura",
    "gn:population":0,
    "gn:timezone":"Asia/Kolkata",
    "iso:country":"IN",
    "wof:name":"Gambhirpura",
    "wof:placetype":"locality"
},
  "geometry": {"coordinates":[76.13549,21.55194],"type":"Point"}
}