{
  "type": "Feature",
  "properties": {
    "gn:admin1_code":"40.0",
    "gn:admin2_code":"537",
    "gn:asciiname":"Tangatur",
    "gn:country_code":"IN",
    "gn:dem":572,
    "gn:feature_class":"P",
    "gn:feature_code":"PPL",
    "gn:name":"Tangat\u016br",
    "gn:population":0,
    "gn:timezone":"Asia/Kolkata",
    "iso:country":"IN",
    "name:tel_x_preferred":[
        "\u0c1f\u0c02\u0c17\u0c41\u0c1f\u0c42\u0c30\u0c41"
    ],
    "name:urd_x_preferred":[
        "\u0679\u0646\u06af\u0627\u0679\u0648\u0631"
    ],
    "wof:name":"Tangatur",
    "wof:placetype":"neighbourhood"
},
  "geometry": {"coordinates":[78.17915000000001,17.41285],"type":"Point"}
}