{
  "type": "Feature",
  "properties": {
    "iso:country":"IN",
    "ks:ks_name":"Kanchanbari",
    "ks:ks_pop":339,
    "ks:ks_type":"HABITATION",
    "name:eng_x_preferred":[
        "Kanchanbari"
    ],
    "wof:name":"Kanchanbari",
    "wof:placetype":"locality",
    "wof:population":339
},
  "geometry": {"coordinates":[87.74599000000001,26.348479],"type":"Point"}
}