{
  "type": "Feature",
  "properties": {
    "iso:country":"IN",
    "ks:ks_name":"Navaneet Pur",
    "ks:ks_pop":625,
    "ks:ks_type":"HABITATION",
    "ks:ks_uagg_main":0,
    "name:eng_x_preferred":[
        "Navaneet Pur"
    ],
    "wof:name":"Navaneet Pur",
    "wof:placetype":"neighbourhood",
    "wof:population":625
},
  "geometry": {"coordinates":[81.536749,26.340435],"type":"Point"}
}