{
  "type": "Feature",
  "properties": {
    "gn:admin1_code":"16",
    "gn:admin2_code":"509.0",
    "gn:asciiname":"Tirur",
    "gn:country_code":"IN",
    "gn:dem":195,
    "gn:feature_class":"P",
    "gn:feature_code":"PPL",
    "gn:name":"Tirur",
    "gn:population":0,
    "gn:timezone":"Asia/Kolkata",
    "iso:country":"IN",
    "ks:ks_name":"Tirur",
    "ks:ks_pop":0,
    "ks:ks_type":"VILLAGE",
    "name:ben_x_preferred":[
        "\u09a4\u09bf\u09b0\u09c1\u09b0"
    ],
    "name:bpy_x_preferred":[
        "\u09a4\u09bf\u09b0\u09c1\u09b0"
    ],
    "name:ceb_x_preferred":[
        "Tir\u016br"
    ],
    "name:eng_x_preferred":[
        "Tirur"
    ],
    "name:ita_x_preferred":[
        "Tirur"
    ],
    "name:mal_x_preferred":[
        "\u0d24\u0d3f\u0d30\u0d42\u0d7c"
    ],
    "name:mlg_x_preferred":[
        "Tirur"
    ],
    "name:msa_x_preferred":[
        "Tirur"
    ],
    "name:swe_x_preferred":[
        "Tir\u016br"
    ],
    "name:tam_x_preferred":[
        "\u0ba4\u0bbf\u0bb0\u0bc2\u0bb0\u0bcd"
    ],
    "name:urd_x_preferred":[
        "\u062a\u06cc\u0631\u0648\u0631"
    ],
    "name:vie_x_preferred":[
        "Tirur"
    ],
    "name:zho_x_preferred":[
        "\u8482\u9c81\u5c14"
    ],
    "wof:name":"Tirur",
    "wof:placetype":"locality",
    "wof:population":0
},
  "geometry": {"coordinates":[79.22107200000001,20.050617],"type":"Point"}
}