{
  "type": "Feature",
  "properties": {
    "iso:country":"IN",
    "ks:ks_name":"Kalaria",
    "ks:ks_pop":5930,
    "ks:ks_type":"VILLAGE",
    "ks:ks_uagg_main":0,
    "name:eng_x_preferred":[
        "Kalaria"
    ],
    "wof:name":"Kalaria",
    "wof:placetype":"locality",
    "wof:population":5930
},
  "geometry": {"coordinates":[88.523601,22.385326],"type":"Point"}
}