{
  "type": "Feature",
  "properties": {
    "iso:country":"IN",
    "ks:ks_name":"Adasu",
    "ks:ks_type":"VILLAGE",
    "name:eng_x_preferred":[
        "Adasu"
    ],
    "wof:name":"Adasu",
    "wof:placetype":"locality"
},
  "geometry": {"coordinates":[77.913752,31.082288],"type":"Point"}
}