{
  "type": "Feature",
  "properties": {
    "iso:country":"IN",
    "ks:ks_name":"Kadakulam",
    "ks:ks_pop":5150,
    "ks:ks_type":"HABITATION",
    "name:eng_x_preferred":[
        "Kadakulam"
    ],
    "wof:name":"Kadakulam",
    "wof:placetype":"locality",
    "wof:population":5150
},
  "geometry": {"coordinates":[76.717741,8.79351],"type":"Point"}
}