{
  "type": "Feature",
  "properties": {
    "iso:country":"IN",
    "ks:ks_alt_nam":"MAHTO TOLA",
    "ks:ks_name":"Mahto Tola",
    "ks:ks_pop":74,
    "ks:ks_type":"HABITATION",
    "name:eng_x_preferred":[
        "Mahto Tola"
    ],
    "wof:name":"Mahto Tola",
    "wof:placetype":"locality",
    "wof:population":74
},
  "geometry": {"coordinates":[86.665083,26.307679],"type":"Point"}
}