{
  "type": "Feature",
  "properties": {
    "iso:country":"IN",
    "ks:ks_name":"Soetba",
    "ks:ks_pop":864,
    "ks:ks_type":"VILLAGE",
    "name:eng_x_preferred":[
        "Soetba"
    ],
    "wof:name":"Soetba",
    "wof:placetype":"locality",
    "wof:population":864
},
  "geometry": {"coordinates":[85.601535,22.546933],"type":"Point"}
}