{
  "type": "Feature",
  "properties": {
    "iso:country":"IN",
    "ks:ks_name":"Keli",
    "ks:ks_pop":139,
    "ks:ks_type":"VILLAGE",
    "name:eng_x_preferred":[
        "Keli"
    ],
    "wof:name":"Keli",
    "wof:placetype":"locality",
    "wof:population":139
},
  "geometry": {"coordinates":[74.27870299999999,24.149688],"type":"Point"}
}