{
  "type": "Feature",
  "properties": {
    "iso:country":"IN",
    "ks:ks_name":"Shri Kheda",
    "ks:ks_pop":132,
    "ks:ks_type":"VILLAGE",
    "name:eng_x_preferred":[
        "Shri Kheda"
    ],
    "wof:name":"Shri Kheda",
    "wof:placetype":"locality",
    "wof:population":132
},
  "geometry": {"coordinates":[74.778486,23.543952],"type":"Point"}
}