{
  "type": "Feature",
  "properties": {
    "iso:country":"IN",
    "ks:ks_name":"Gangapura",
    "ks:ks_pop":198,
    "ks:ks_type":"VILLAGE",
    "name:eng_x_preferred":[
        "Gangapura"
    ],
    "wof:name":"Gangapura",
    "wof:placetype":"locality",
    "wof:population":198
},
  "geometry": {"coordinates":[72.260678,26.198614],"type":"Point"}
}