{
  "type": "Feature",
  "properties": {
    "gn:admin1_code":"36",
    "gn:admin2_code":"175.0",
    "gn:asciiname":"Dhobaha",
    "gn:country_code":"IN",
    "gn:dem":100,
    "gn:feature_class":"P",
    "gn:feature_code":"PPL",
    "gn:name":"Dhobaha",
    "gn:population":0,
    "gn:timezone":"Asia/Kolkata",
    "iso:country":"IN",
    "wof:name":"Dhobaha",
    "wof:placetype":"locality"
},
  "geometry": {"coordinates":[82.02459,25.59648],"type":"Point"}
}