{
  "type": "Feature",
  "properties": {
    "iso:country":"IN",
    "ks:ks_name":"Khoja",
    "ks:ks_pop":135,
    "ks:ks_type":"VILLAGE",
    "name:eng_x_preferred":[
        "Khoja"
    ],
    "wof:name":"Khoja",
    "wof:placetype":"locality",
    "wof:population":135
},
  "geometry": {"coordinates":[80.275453,29.813334],"type":"Point"}
}