{
  "type": "Feature",
  "properties": {
    "gn:admin1_code":"36.0",
    "gn:admin2_code":"175.0",
    "gn:asciiname":"Bhupatpur",
    "gn:country_code":"IN",
    "gn:dem":98,
    "gn:feature_class":"P",
    "gn:feature_code":"PPL",
    "gn:name":"Bhupatpur",
    "gn:population":0,
    "gn:timezone":"Asia/Kolkata",
    "iso:country":"IN",
    "ks:ks_name":"Bhopat Pur",
    "ks:ks_pop":2047,
    "ks:ks_type":"VILLAGE",
    "ks:ks_uagg_main":0,
    "name:eng_x_preferred":[
        "Bhopat Pur"
    ],
    "wof:name":"Bhopat Pur",
    "wof:placetype":"neighbourhood",
    "wof:population":2047
},
  "geometry": {"coordinates":[81.98812599999999,25.492772],"type":"Point"}
}