{
  "type": "Feature",
  "properties": {
    "iso:country":"IN",
    "ks:ks_name":"Gunangabali",
    "ks:ks_pop":14,
    "ks:ks_type":"HABITATION",
    "name:eng_x_preferred":[
        "Gunangabali"
    ],
    "wof:name":"Gunangabali",
    "wof:placetype":"locality",
    "wof:population":14
},
  "geometry": {"coordinates":[83.756441,19.467433],"type":"Point"}
}