{
  "type": "Feature",
  "properties": {
    "iso:country":"IN",
    "ks:ks_alt_nam":"panangatoor",
    "ks:ks_name":"Panangatoor",
    "ks:ks_pop":1454,
    "ks:ks_type":"HABITATION",
    "name:eng_x_preferred":[
        "Panangatoor"
    ],
    "wof:name":"Panangatoor",
    "wof:placetype":"locality",
    "wof:population":1454
},
  "geometry": {"coordinates":[75.361617,12.080869],"type":"Point"}
}