{
  "type": "Feature",
  "properties": {
    "iso:country":"IN",
    "ks:ks_name":"Jipti",
    "ks:ks_pop":357,
    "ks:ks_type":"VILLAGE",
    "name:eng_x_preferred":[
        "Jipti"
    ],
    "wof:name":"Jipti",
    "wof:placetype":"locality",
    "wof:population":357
},
  "geometry": {"coordinates":[80.72897500000001,30.009446],"type":"Point"}
}