{
  "type": "Feature",
  "properties": {
    "iso:country":"IN",
    "ks:ks_name":"Kurichinankarai",
    "ks:ks_pop":65,
    "ks:ks_type":"HABITATION",
    "name:eng_x_preferred":[
        "Kurichinankarai"
    ],
    "wof:name":"Kurichinankarai",
    "wof:placetype":"locality",
    "wof:population":65
},
  "geometry": {"coordinates":[78.814802,9.768091],"type":"Point"}
}