{
  "type": "Feature",
  "properties": {
    "iso:country":"IN",
    "ks:ks_name":"Karenjaguda",
    "ks:ks_pop":31,
    "ks:ks_type":"VILLAGE",
    "name:eng_x_preferred":[
        "Karenjaguda"
    ],
    "wof:name":"Karenjaguda",
    "wof:placetype":"locality",
    "wof:population":31
},
  "geometry": {"coordinates":[82.258152,18.253541],"type":"Point"}
}