{
  "type": "Feature",
  "properties": {
    "gn:admin1_code":"35",
    "gn:admin2_code":"445.0",
    "gn:asciiname":"Itawa Kalan",
    "gn:country_code":"IN",
    "gn:dem":293,
    "gn:feature_class":"P",
    "gn:feature_code":"PPL",
    "gn:name":"It\u0101wa Kal\u0101n",
    "gn:population":0,
    "gn:timezone":"Asia/Kolkata",
    "iso:country":"IN",
    "ks:ks_alt_nam":"It\u0101wa Kal\u0101n",
    "ks:ks_name":"Itawa Kalan",
    "ks:ks_pop":1374,
    "ks:ks_type":"VILLAGE",
    "ks:ks_uagg_main":0,
    "name:eng_x_preferred":[
        "Itawa Kalan"
    ],
    "name:eng_x_variant":[
        "It\u0101wa Kal\u0101n"
    ],
    "wof:name":"Itawa Kalan",
    "wof:placetype":"neighbourhood",
    "wof:population":1374
},
  "geometry": {"coordinates":[77.136774,22.642827],"type":"Point"}
}