{
  "type": "Feature",
  "properties": {
    "iso:country":"IN",
    "ks:ks_name":"Inarabaran",
    "ks:ks_pop":205,
    "ks:ks_type":"HABITATION",
    "name:eng_x_preferred":[
        "Inarabaran"
    ],
    "wof:name":"Inarabaran",
    "wof:placetype":"locality",
    "wof:population":205
},
  "geometry": {"coordinates":[86.836764,24.653337],"type":"Point"}
}