{
  "type": "Feature",
  "properties": {
    "iso:country":"IN",
    "ks:ks_name":"Karbi Lalung",
    "ks:ks_pop":176,
    "ks:ks_type":"HABITATION",
    "name:eng_x_preferred":[
        "Karbi Lalung"
    ],
    "wof:name":"Karbi Lalung",
    "wof:placetype":"locality",
    "wof:population":176
},
  "geometry": {"coordinates":[92.36291199999999,25.941886],"type":"Point"}
}