{
  "type": "Feature",
  "properties": {
    "iso:country":"IN",
    "ks:ks_name":"Mandavkarwadi",
    "ks:ks_pop":108,
    "ks:ks_type":"HABITATION",
    "name:eng_x_preferred":[
        "Mandavkarwadi"
    ],
    "wof:name":"Mandavkarwadi",
    "wof:placetype":"locality",
    "wof:population":108
},
  "geometry": {"coordinates":[73.359092,16.959627],"type":"Point"}
}