{
  "type": "Feature",
  "properties": {
    "iso:country":"IN",
    "ks:ks_alt_nam":"Gulal tekadi",
    "ks:ks_name":"Gulal Tekadi",
    "ks:ks_pop":221,
    "ks:ks_type":"HABITATION",
    "name:eng_x_preferred":[
        "Gulal Tekadi"
    ],
    "wof:name":"Gulal Tekadi",
    "wof:placetype":"locality",
    "wof:population":221
},
  "geometry": {"coordinates":[74.565558,16.741406],"type":"Point"}
}