{
  "type": "Feature",
  "properties": {
    "iso:country":"IN",
    "ks:ks_name":"Kapur Dhuwa",
    "ks:ks_pop":154,
    "ks:ks_type":"HABITATION",
    "name:eng_x_preferred":[
        "Kapur Dhuwa"
    ],
    "wof:name":"Kapur Dhuwa",
    "wof:placetype":"locality",
    "wof:population":154
},
  "geometry": {"coordinates":[94.608324,27.443266],"type":"Point"}
}