{
  "type": "Feature",
  "properties": {
    "gn:admin1_code":"39",
    "gn:admin2_code":"60.0",
    "gn:asciiname":"Jabrani",
    "gn:country_code":"IN",
    "gn:dem":742,
    "gn:feature_class":"P",
    "gn:feature_code":"PPL",
    "gn:name":"Jabr\u0101ni",
    "gn:population":0,
    "gn:timezone":"Asia/Kolkata",
    "iso:country":"IN",
    "name:ara_x_preferred":[
        "\u062c\u0628\u0631\u0627\u0646\u064a"
    ],
    "name:ceb_x_preferred":[
        "Jabr\u0101n\u012b"
    ],
    "name:fas_x_preferred":[
        "\u062c\u0628\u0631\u0627\u0646\u06cc"
    ],
    "name:msa_x_preferred":[
        "Jabrani"
    ],
    "name:swe_x_preferred":[
        "Jabr\u0101n\u012b"
    ],
    "name:urd_x_preferred":[
        "\u062c\u0628\u0631\u0627\u0646\u06cc"
    ],
    "wof:name":"Jabrani",
    "wof:placetype":"locality"
},
  "geometry": {"coordinates":[78.19856999999998,30.24509],"type":"Point"}
}