{
  "type": "Feature",
  "properties": {
    "gn:admin1_code":"19.0",
    "gn:admin2_code":"583.0",
    "gn:asciiname":"Ajgondanhalli",
    "gn:country_code":"IN",
    "gn:dem":864,
    "gn:feature_class":"P",
    "gn:feature_code":"PPL",
    "gn:name":"Ajgondanhalli",
    "gn:population":0,
    "gn:timezone":"Asia/Kolkata",
    "iso:country":"IN",
    "wof:name":"Ajgondanhalli",
    "wof:placetype":"locality"
},
  "geometry": {"coordinates":[77.77083,12.96082],"type":"Point"}
}