{
  "type": "Feature",
  "properties": {
    "gn:admin1_code":"35.0",
    "gn:admin2_code":"437.0",
    "gn:asciiname":"Piplia Khurd",
    "gn:country_code":"IN",
    "gn:dem":489,
    "gn:feature_class":"P",
    "gn:feature_code":"PPL",
    "gn:name":"P\u012bplia Khurd",
    "gn:population":0,
    "gn:timezone":"Asia/Kolkata",
    "iso:country":"IN",
    "name:und_x_variant":[
        "P\u012bplia Khurd",
        "Koria"
    ],
    "wof:name":"Piplia Khurd",
    "wof:placetype":"locality"
},
  "geometry": {"coordinates":[76.21647,22.93877],"type":"Point"}
}