{
  "type": "Feature",
  "properties": {
    "gn:admin1_code":"34.0",
    "gn:admin2_code":"231.0",
    "gn:asciiname":"Bujh Raidera",
    "gn:country_code":"IN",
    "gn:dem":60,
    "gn:feature_class":"P",
    "gn:feature_code":"PPL",
    "gn:name":"Bujh R\u0101idera",
    "gn:population":0,
    "gn:timezone":"Asia/Kolkata",
    "iso:country":"IN",
    "wof:name":"Bujh Raidera",
    "wof:placetype":"locality"
},
  "geometry": {"coordinates":[84.41410999999999,25.6456],"type":"Point"}
}