{
  "type": "Feature",
  "properties": {
    "gn:admin1_code":"29.0",
    "gn:admin2_code":"242.0",
    "gn:asciiname":"Martam",
    "gn:country_code":"IN",
    "gn:dem":1773,
    "gn:feature_class":"P",
    "gn:feature_code":"PPL",
    "gn:name":"M\u0101rtam",
    "gn:population":0,
    "gn:timezone":"Asia/Kolkata",
    "iso:country":"IN",
    "wof:name":"Martam",
    "wof:placetype":"locality"
},
  "geometry": {"coordinates":[88.22314,27.24512],"type":"Point"}
}