{
  "type": "Feature",
  "properties": {
    "iso:country":"IN",
    "ks:ks_name":"Kachlaram",
    "ks:ks_pop":75,
    "ks:ks_type":"HABITATION",
    "name:eng_x_preferred":[
        "Kachlaram"
    ],
    "wof:name":"Kachlaram",
    "wof:placetype":"locality",
    "wof:population":75
},
  "geometry": {"coordinates":[80.558261,18.8746],"type":"Point"}
}