{
  "type": "Feature",
  "properties": {
    "iso:country":"IN",
    "ks:ks_name":"Abbihole",
    "ks:ks_pop":174,
    "ks:ks_type":"HABITATION",
    "name:eng_x_preferred":[
        "Abbihole"
    ],
    "wof:name":"Abbihole",
    "wof:placetype":"locality",
    "wof:population":174
},
  "geometry": {"coordinates":[74.67534499999999,13.802107],"type":"Point"}
}