{
  "type": "Feature",
  "properties": {
    "iso:country":"IN",
    "ks:ks_name":"Kotri",
    "ks:ks_pop":271,
    "ks:ks_type":"VILLAGE",
    "name:eng_x_preferred":[
        "Kotri"
    ],
    "wof:name":"Kotri",
    "wof:placetype":"locality",
    "wof:population":271
},
  "geometry": {"coordinates":[81.71486299999999,23.454501],"type":"Point"}
}