{
  "type": "Feature",
  "properties": {
    "iso:country":"IN",
    "ks:ks_name":"Naydalu",
    "ks:ks_pop":44,
    "ks:ks_type":"HABITATION",
    "name:eng_x_preferred":[
        "Naydalu"
    ],
    "wof:name":"Naydalu",
    "wof:placetype":"locality",
    "wof:population":44
},
  "geometry": {"coordinates":[75.33726299999999,13.399228],"type":"Point"}
}