{
  "type": "Feature",
  "properties": {
    "gn:admin1_code":"02",
    "gn:admin2_code":"551.0",
    "gn:asciiname":"Peddamudiyam",
    "gn:country_code":"IN",
    "gn:dem":173,
    "gn:feature_class":"P",
    "gn:feature_code":"PPL",
    "gn:name":"Peddamudiyam",
    "gn:population":0,
    "gn:timezone":"Asia/Kolkata",
    "iso:country":"IN",
    "wof:name":"Peddamudiyam",
    "wof:placetype":"locality"
},
  "geometry": {"coordinates":[78.45144000000001,15.01154],"type":"Point"}
}