{
  "type": "Feature",
  "properties": {
    "iso:country":"IN",
    "ks:ks_name":"Sorasapodaru",
    "ks:ks_pop":65,
    "ks:ks_type":"HABITATION",
    "name:eng_x_preferred":[
        "Sorasapodaru"
    ],
    "wof:name":"Sorasapodaru",
    "wof:placetype":"locality",
    "wof:population":65
},
  "geometry": {"coordinates":[82.996724,18.262237],"type":"Point"}
}