{
  "type": "Feature",
  "properties": {
    "iso:country":"IN",
    "ks:ks_name":"Irkampeta",
    "ks:ks_pop":221,
    "ks:ks_type":"VILLAGE",
    "name:eng_x_preferred":[
        "Irkampeta"
    ],
    "wof:name":"Irkampeta",
    "wof:placetype":"locality",
    "wof:population":221
},
  "geometry": {"coordinates":[81.174528,17.779068],"type":"Point"}
}