{
  "type": "Feature",
  "properties": {
    "gn:admin1_code":"36.0",
    "gn:admin2_code":"193.0",
    "gn:asciiname":"Kirpalpur",
    "gn:country_code":"IN",
    "gn:dem":65,
    "gn:feature_class":"P",
    "gn:feature_code":"PPL",
    "gn:name":"Kirp\u0101lpur",
    "gn:population":0,
    "gn:timezone":"Asia/Kolkata",
    "iso:country":"IN",
    "ks:ks_name":"Kripalpur",
    "ks:ks_pop":1393,
    "ks:ks_type":"VILLAGE",
    "name:eng_x_preferred":[
        "Kripalpur"
    ],
    "name:eng_x_variant":[
        "Kirpalpur"
    ],
    "name:mal_x_preferred":[
        "\u0d15\u0d3f\u0d7c\u0d2a\u0d3e\u0d7d\u0d2a\u0d42\u0d7c"
    ],
    "wof:name":"Kripalpur",
    "wof:placetype":"locality",
    "wof:population":1393
},
  "geometry": {"coordinates":[84.291791,25.766479],"type":"Point"}
}