{
  "type": "Feature",
  "properties": {
    "iso:country":"IN",
    "ks:ks_name":"Baksha",
    "ks:ks_pop":2571,
    "ks:ks_type":"VILLAGE",
    "ks:ks_uagg_main":0,
    "name:eng_x_preferred":[
        "Baksha"
    ],
    "wof:name":"Baksha",
    "wof:placetype":"locality",
    "wof:population":2571
},
  "geometry": {"coordinates":[88.55716099999999,23.016068],"type":"Point"}
}