{
  "type": "Feature",
  "properties": {
    "iso:country":"IN",
    "ks:ks_alt_nam":"Santhal tola",
    "ks:ks_name":"Santhal Tola",
    "ks:ks_pop":70,
    "ks:ks_type":"HABITATION",
    "name:eng_x_preferred":[
        "Santhal Tola"
    ],
    "wof:name":"Santhal Tola",
    "wof:placetype":"locality",
    "wof:population":70
},
  "geometry": {"coordinates":[86.37885199999999,24.618027],"type":"Point"}
}