{
  "type": "Feature",
  "properties": {
    "iso:country":"IN",
    "ks:ks_alt_nam":"Bhattu peekla  thanda",
    "ks:ks_name":"Bhattu Peekla Thanda",
    "ks:ks_pop":146,
    "ks:ks_type":"HABITATION",
    "name:eng_x_preferred":[
        "Bhattu Peekla Thanda"
    ],
    "name:eng_x_variant":[
        "Bhattu peekla  thanda"
    ],
    "wof:name":"Bhattu Peekla Thanda",
    "wof:placetype":"locality",
    "wof:population":146
},
  "geometry": {"coordinates":[79.770354,17.754712],"type":"Point"}
}