{
  "type": "Feature",
  "properties": {
    "iso:country":"IN",
    "ks:ks_alt_nam":"KADAM ADDA",
    "ks:ks_name":"Kadam Adda",
    "ks:ks_pop":414,
    "ks:ks_type":"HABITATION",
    "name:eng_x_preferred":[
        "Kadam Adda"
    ],
    "wof:name":"Kadam Adda",
    "wof:placetype":"locality",
    "wof:population":414
},
  "geometry": {"coordinates":[74.315292,16.41963],"type":"Point"}
}