{
  "type": "Feature",
  "properties": {
    "iso:country":"IN",
    "ks:ks_name":"Thar Sarvan",
    "ks:ks_pop":34,
    "ks:ks_type":"HABITATION",
    "name:eng_x_preferred":[
        "Thar Sarvan"
    ],
    "wof:name":"Thar Sarvan",
    "wof:placetype":"locality",
    "wof:population":34
},
  "geometry": {"coordinates":[78.28290200000001,27.060976],"type":"Point"}
}