{
  "type": "Feature",
  "properties": {
    "iso:country":"IN",
    "ks:ks_name":"Chackram Badi",
    "ks:ks_pop":1041,
    "ks:ks_type":"VILLAGE",
    "ks:ks_uagg_main":0,
    "name:eng_x_preferred":[
        "Chackram Badi"
    ],
    "wof:name":"Chackram Badi",
    "wof:placetype":"neighbourhood",
    "wof:population":1041
},
  "geometry": {"coordinates":[77.65217,29.695607],"type":"Point"}
}