{
  "type": "Feature",
  "properties": {
    "iso:country":"IN",
    "ks:ks_name":"Mawad",
    "ks:ks_pop":351,
    "ks:ks_type":"HABITATION",
    "name:eng_x_preferred":[
        "Mawad"
    ],
    "wof:name":"Mawad",
    "wof:placetype":"locality",
    "wof:population":351
},
  "geometry": {"coordinates":[75.14071800000001,22.550323],"type":"Point"}
}