{
  "type": "Feature",
  "properties": {
    "iso:country":"IN",
    "ks:ks_name":"Hulmekhwadi",
    "ks:ks_pop":46,
    "ks:ks_type":"HABITATION",
    "name:eng_x_preferred":[
        "Hulmekhwadi"
    ],
    "wof:name":"Hulmekhwadi",
    "wof:placetype":"locality",
    "wof:population":46
},
  "geometry": {"coordinates":[73.60607899999999,15.879342],"type":"Point"}
}