{
  "type": "Feature",
  "properties": {
    "iso:country":"IN",
    "ks:ks_name":"Kesura",
    "ks:ks_pop":1621,
    "ks:ks_type":"VILLAGE",
    "ks:ks_uagg_main":0,
    "name:eng_x_preferred":[
        "Kesura"
    ],
    "wof:name":"Kesura",
    "wof:placetype":"locality",
    "wof:population":1621
},
  "geometry": {"coordinates":[85.873831,20.267429],"type":"Point"}
}