{
  "type": "Feature",
  "properties": {
    "gn:admin1_code":"12.0",
    "gn:admin2_code":"008",
    "gn:asciiname":"Wussanknui",
    "gn:country_code":"IN",
    "gn:dem":1588,
    "gn:feature_class":"P",
    "gn:feature_code":"PPL",
    "gn:name":"Wussankn\u016bi",
    "gn:population":0,
    "gn:timezone":"Asia/Kolkata",
    "iso:country":"IN",
    "wof:name":"Wussanknui",
    "wof:placetype":"locality"
},
  "geometry": {"coordinates":[74.55329999999999,34.20381],"type":"Point"}
}