{
  "type": "Feature",
  "properties": {
    "iso:country":"IN",
    "ks:ks_name":"Lohariasal Talla",
    "ks:ks_pop":4043,
    "ks:ks_type":"VILLAGE",
    "ks:ks_uagg_main":0,
    "name:eng_x_preferred":[
        "Lohariasal Talla"
    ],
    "wof:name":"Lohariasal Talla",
    "wof:placetype":"neighbourhood",
    "wof:population":4043
},
  "geometry": {"coordinates":[79.487201,29.229524],"type":"Point"}
}