{
  "type": "Feature",
  "properties": {
    "iso:country":"IN",
    "ks:ks_name":"Kabulpur",
    "ks:ks_pop":1065,
    "ks:ks_type":"VILLAGE",
    "name:eng_x_preferred":[
        "Kabulpur"
    ],
    "wof:name":"Kabulpur",
    "wof:placetype":"neighbourhood",
    "wof:population":1065
},
  "geometry": {"coordinates":[75.62245799999999,31.378668],"type":"Point"}
}