{
  "type": "Feature",
  "properties": {
    "gn:admin1_code":"16",
    "gn:admin2_code":"509.0",
    "gn:asciiname":"Piranji",
    "gn:country_code":"IN",
    "gn:dem":213,
    "gn:feature_class":"P",
    "gn:feature_code":"PPL",
    "gn:name":"P\u012branji",
    "gn:population":0,
    "gn:timezone":"Asia/Kolkata",
    "iso:country":"IN",
    "name:und_x_variant":[
        "P\u012branji",
        "Kota"
    ],
    "wof:name":"Piranji",
    "wof:placetype":"locality"
},
  "geometry": {"coordinates":[79.81430999999998,20.09165],"type":"Point"}
}