{
  "type": "Feature",
  "properties": {
    "iso:country":"IN",
    "ks:ks_name":"Santpur",
    "ks:ks_pop":436,
    "ks:ks_type":"HABITATION",
    "name:eng_x_preferred":[
        "Santpur"
    ],
    "wof:name":"Santpur",
    "wof:placetype":"locality",
    "wof:population":436
},
  "geometry": {"coordinates":[86.59846899999999,25.948702],"type":"Point"}
}