{
  "type": "Feature",
  "properties": {
    "iso:country":"IN",
    "ks:ks_name":"Keelthukli",
    "ks:ks_pop":300,
    "ks:ks_type":"HABITATION",
    "name:eng_x_preferred":[
        "Keelthukli"
    ],
    "wof:name":"Keelthukli",
    "wof:placetype":"locality",
    "wof:population":300
},
  "geometry": {"coordinates":[78.669752,11.879167],"type":"Point"}
}