{
  "type": "Feature",
  "properties": {
    "iso:country":"IN",
    "ks:ks_name":"Sharadapur",
    "ks:ks_pop":379,
    "ks:ks_type":"HABITATION",
    "name:eng_x_preferred":[
        "Sharadapur"
    ],
    "wof:name":"Sharadapur",
    "wof:placetype":"locality",
    "wof:population":379
},
  "geometry": {"coordinates":[82.61930099999999,19.908294],"type":"Point"}
}