{
  "type": "Feature",
  "properties": {
    "iso:country":"IN",
    "ks:ks_alt_nam":"Ch\u0101tam",
    "ks:ks_name":"Chatam",
    "ks:ks_pop":166,
    "ks:ks_type":"VILLAGE",
    "name:eng_x_preferred":[
        "Chatam"
    ],
    "name:eng_x_variant":[
        "Ch\u0101tam"
    ],
    "wof:name":"Chatam",
    "wof:placetype":"locality",
    "wof:population":166
},
  "geometry": {"coordinates":[84.313785,23.698154],"type":"Point"}
}