{
  "type": "Feature",
  "properties": {
    "gn:admin1_code":"12.0",
    "gn:admin2_code":"010",
    "gn:asciiname":"Takye Nunar",
    "gn:country_code":"IN",
    "gn:dem":1615,
    "gn:feature_class":"P",
    "gn:feature_code":"PPL",
    "gn:name":"Takye Nunar",
    "gn:population":0,
    "gn:timezone":"Asia/Kolkata",
    "iso:country":"IN",
    "wof:name":"Takye Nunar",
    "wof:placetype":"locality"
},
  "geometry": {"coordinates":[74.7641,34.25925],"type":"Point"}
}