{
  "type": "Feature",
  "properties": {
    "iso:country":"IN",
    "ks:ks_name":"Bovicolony",
    "ks:ks_pop":533,
    "ks:ks_type":"HABITATION",
    "name:eng_x_preferred":[
        "Bovicolony"
    ],
    "wof:name":"Bovicolony",
    "wof:placetype":"locality",
    "wof:population":533
},
  "geometry": {"coordinates":[75.974633,13.236959],"type":"Point"}
}