{
  "type": "Feature",
  "properties": {
    "iso:country":"IN",
    "ks:ks_name":"Gulariha Hisanpur",
    "ks:ks_pop":3325,
    "ks:ks_type":"VILLAGE",
    "name:eng_x_preferred":[
        "Gulariha Hisanpur"
    ],
    "wof:name":"Gulariha Hisanpur",
    "wof:placetype":"locality",
    "wof:population":3325
},
  "geometry": {"coordinates":[82.275425,27.591495],"type":"Point"}
}