{
  "type": "Feature",
  "properties": {
    "iso:country":"IN",
    "ks:ks_name":"Birahimpur",
    "ks:ks_pop":3192,
    "ks:ks_type":"VILLAGE",
    "name:eng_x_preferred":[
        "Birahimpur"
    ],
    "wof:name":"Birahimpur",
    "wof:placetype":"locality",
    "wof:population":3192
},
  "geometry": {"coordinates":[88.08004200000001,24.950107],"type":"Point"}
}