{
  "type": "Feature",
  "properties": {
    "iso:country":"IN",
    "ks:ks_name":"Garada",
    "ks:ks_pop":262,
    "ks:ks_type":"VILLAGE",
    "ks:ks_uagg_main":0,
    "name:eng_x_preferred":[
        "Garada"
    ],
    "wof:name":"Garada",
    "wof:placetype":"neighbourhood",
    "wof:population":262
},
  "geometry": {"coordinates":[86.92350500000001,21.43322],"type":"Point"}
}