{
  "type": "Feature",
  "properties": {
    "gn:admin1_code":"39.0",
    "gn:admin2_code":"62.0",
    "gn:asciiname":"Dwari",
    "gn:country_code":"IN",
    "gn:dem":1192,
    "gn:feature_class":"P",
    "gn:feature_code":"PPL",
    "gn:name":"Dw\u0101ri",
    "gn:population":0,
    "gn:timezone":"Asia/Kolkata",
    "iso:country":"IN",
    "ks:ks_alt_nam":"Dw\u0101ri",
    "ks:ks_name":"Dwari",
    "ks:ks_type":"VILLAGE",
    "name:ceb_x_preferred":[
        "Dwari"
    ],
    "name:eng_x_preferred":[
        "Dwari"
    ],
    "name:eng_x_variant":[
        "Dw\u0101ri"
    ],
    "name:mai_x_preferred":[
        "\u0926\u094d\u0935\u093e\u0930\u0940"
    ],
    "name:nep_x_preferred":[
        "\u0926\u094d\u0935\u093e\u0930\u0940"
    ],
    "name:new_x_preferred":[
        "\u0926\u094d\u0935\u093e\u0930\u0940"
    ],
    "wof:name":"Dwari",
    "wof:placetype":"locality"
},
  "geometry": {"coordinates":[79.851192,29.750938],"type":"Point"}
}