{
  "type": "Feature",
  "properties": {
    "iso:country":"IN",
    "ks:ks_name":"Harche",
    "ks:ks_pop":1377,
    "ks:ks_type":"VILLAGE",
    "name:eng_x_preferred":[
        "Harche"
    ],
    "wof:name":"Harche",
    "wof:placetype":"locality",
    "wof:population":1377
},
  "geometry": {"coordinates":[73.38847199999999,16.748791],"type":"Point"}
}