{
  "type": "Feature",
  "properties": {
    "iso:country":"IN",
    "ks:ks_alt_nam":"LIDHAN PURWA",
    "ks:ks_name":"Lidhan Purwa",
    "ks:ks_pop":224,
    "ks:ks_type":"HABITATION",
    "name:eng_x_preferred":[
        "Lidhan Purwa"
    ],
    "wof:name":"Lidhan Purwa",
    "wof:placetype":"locality",
    "wof:population":224
},
  "geometry": {"coordinates":[81.48934300000001,27.546093],"type":"Point"}
}