{
  "type": "Feature",
  "properties": {
    "iso:country":"IN",
    "ks:ks_alt_nam":"KURMIAN GARHARAN",
    "ks:ks_name":"Kurmian Garharan",
    "ks:ks_pop":146,
    "ks:ks_type":"HABITATION",
    "name:eng_x_preferred":[
        "Kurmian Garharan"
    ],
    "wof:name":"Kurmian Garharan",
    "wof:placetype":"locality",
    "wof:population":146
},
  "geometry": {"coordinates":[81.801939,25.585237],"type":"Point"}
}