{
  "type": "Feature",
  "properties": {
    "gn:admin1_code":"9.0",
    "gn:admin2_code":"493.0",
    "gn:asciiname":"Gangta",
    "gn:country_code":"IN",
    "gn:dem":103,
    "gn:feature_class":"P",
    "gn:feature_code":"PPL",
    "gn:name":"Gangta",
    "gn:population":0,
    "gn:timezone":"Asia/Kolkata",
    "iso:country":"IN",
    "wof:name":"Gangta",
    "wof:placetype":"locality"
},
  "geometry": {"coordinates":[74.00999,21.50844],"type":"Point"}
}