{
  "type": "Feature",
  "properties": {
    "gn:admin1_code":"9.0",
    "gn:admin2_code":"493.0",
    "gn:asciiname":"Gangta",
    "gn:country_code":"IN",
    "gn:dem":103,
    "gn:feature_class":"P",
    "gn:feature_code":"PPL",
    "gn:name":"Gangta",
    "gn:population":0,
    "gn:timezone":"Asia/Kolkata",
    "iso:country":"IN",
    "ks:ks_name":"Gangtha",
    "ks:ks_pop":0,
    "ks:ks_type":"VILLAGE",
    "name:eng_x_preferred":[
        "Gangtha"
    ],
    "name:eng_x_variant":[
        "Gangta"
    ],
    "wof:name":"Gangtha",
    "wof:placetype":"locality",
    "wof:population":0
},
  "geometry": {"coordinates":[74.01124900000001,21.507776],"type":"Point"}
}