{
  "type": "Feature",
  "properties": {
    "gn:admin1_code":"39.0",
    "gn:admin2_code":"65.0",
    "gn:asciiname":"Sakdena",
    "gn:country_code":"IN",
    "gn:dem":1673,
    "gn:feature_class":"P",
    "gn:feature_code":"PPL",
    "gn:name":"Sakdena",
    "gn:population":0,
    "gn:timezone":"Asia/Kolkata",
    "iso:country":"IN",
    "wof:name":"Sakdena",
    "wof:placetype":"locality"
},
  "geometry": {"coordinates":[79.94759000000001,29.34712],"type":"Point"}
}