{
  "type": "Feature",
  "properties": {
    "gn:admin1_code":"39.0",
    "gn:admin2_code":"65.0",
    "gn:asciiname":"Sakdena",
    "gn:country_code":"IN",
    "gn:dem":1673,
    "gn:feature_class":"P",
    "gn:feature_code":"PPL",
    "gn:name":"Sakdena",
    "gn:population":0,
    "gn:timezone":"Asia/Kolkata",
    "iso:country":"IN",
    "ks:ks_alt_nam":"Sakdena Reserved Forest",
    "ks:ks_name":"Sakdena",
    "ks:ks_type":"VILLAGE",
    "name:eng_x_preferred":[
        "Sakdena"
    ],
    "name:eng_x_variant":[
        "Sakdena Reserved Forest"
    ],
    "wof:name":"Sakdena",
    "wof:placetype":"locality"
},
  "geometry": {"coordinates":[79.938621,29.340984],"type":"Point"}
}