{
  "type": "Feature",
  "properties": {
    "gn:admin1_code":"25.0",
    "gn:admin2_code":"632.0",
    "gn:asciiname":"Puchimarathur",
    "gn:country_code":"IN",
    "gn:dem":456,
    "gn:feature_class":"P",
    "gn:feature_code":"PPL",
    "gn:name":"Puchimarath\u016br",
    "gn:population":0,
    "gn:timezone":"Asia/Kolkata",
    "iso:country":"IN",
    "wof:name":"Puchimarathur",
    "wof:placetype":"locality"
},
  "geometry": {"coordinates":[76.79513,11.24255],"type":"Point"}
}