{
  "type": "Feature",
  "properties": {
    "iso:country":"IN",
    "ks:ks_alt_nam":"AmbalamkunnuST colony",
    "ks:ks_name":"Ambalamkunnust Colony",
    "ks:ks_pop":635,
    "ks:ks_type":"HABITATION",
    "name:eng_x_preferred":[
        "Ambalamkunnust Colony"
    ],
    "wof:name":"Ambalamkunnust Colony",
    "wof:placetype":"locality",
    "wof:population":635
},
  "geometry": {"coordinates":[75.88062600000001,11.548748],"type":"Point"}
}