{
  "type": "Feature",
  "properties": {
    "gn:admin1_code":"35.0",
    "gn:admin2_code":"441.0",
    "gn:asciiname":"Dongliapani",
    "gn:country_code":"IN",
    "gn:dem":260,
    "gn:feature_class":"P",
    "gn:feature_code":"PPL",
    "gn:name":"Dongliap\u0101ni",
    "gn:population":0,
    "gn:timezone":"Asia/Kolkata",
    "iso:country":"IN",
    "ks:ks_name":"Dongalya Pani",
    "ks:ks_pop":482,
    "ks:ks_type":"VILLAGE",
    "name:eng_x_preferred":[
        "Dongalya Pani"
    ],
    "name:eng_x_variant":[
        "Dongliapani"
    ],
    "wof:name":"Dongalya Pani",
    "wof:placetype":"locality",
    "wof:population":482
},
  "geometry": {"coordinates":[74.847734,21.920171],"type":"Point"}
}