{
  "type": "Feature",
  "properties": {
    "gn:admin1_code":"13.0",
    "gn:admin2_code":"595.0",
    "gn:asciiname":"Panayali",
    "gn:country_code":"IN",
    "gn:dem":13,
    "gn:feature_class":"P",
    "gn:feature_code":"PPL",
    "gn:name":"Panay\u0101li",
    "gn:population":0,
    "gn:timezone":"Asia/Kolkata",
    "iso:country":"IN",
    "wof:name":"Panayali",
    "wof:placetype":"locality"
},
  "geometry": {"coordinates":[76.45008,10.17819],"type":"Point"}
}