{
  "type": "Feature",
  "properties": {
    "iso:country":"IN",
    "ks:ks_name":"Pothanpalle",
    "ks:ks_pop":285,
    "ks:ks_type":"VILLAGE",
    "name:eng_x_preferred":[
        "Pothanpalle"
    ],
    "wof:name":"Pothanpalle",
    "wof:placetype":"locality",
    "wof:population":285
},
  "geometry": {"coordinates":[79.66924,18.885248],"type":"Point"}
}