{
  "type": "Feature",
  "properties": {
    "gn:admin1_code":"23",
    "gn:admin2_code":"39.0",
    "gn:asciiname":"Jalwaha",
    "gn:country_code":"IN",
    "gn:dem":259,
    "gn:feature_class":"P",
    "gn:feature_code":"PPL",
    "gn:name":"Jalw\u0101ha",
    "gn:population":0,
    "gn:timezone":"Asia/Kolkata",
    "iso:country":"IN",
    "name:por_x_preferred":[
        "Jalwaha"
    ],
    "wof:name":"Jalwaha",
    "wof:placetype":"locality"
},
  "geometry": {"coordinates":[76.18956999999997,31.03548],"type":"Point"}
}