{
  "type": "Feature",
  "properties": {
    "gn:admin1_code":"37.0",
    "gn:admin2_code":"417",
    "gn:asciiname":"Kottur",
    "gn:country_code":"IN",
    "gn:dem":100,
    "gn:feature_class":"P",
    "gn:feature_code":"PPL",
    "gn:name":"Kott\u016br",
    "gn:population":0,
    "gn:timezone":"Asia/Kolkata",
    "iso:country":"IN",
    "name:und_x_variant":[
        "Kott\u016br",
        "Kott\u016bru"
    ],
    "wof:name":"Kottur",
    "wof:placetype":"locality"
},
  "geometry": {"coordinates":[80.373,18.61923],"type":"Point"}
}