{
  "type": "Feature",
  "properties": {
    "gn:admin1_code":"37",
    "gn:admin2_code":"408.0",
    "gn:asciiname":"Amatola",
    "gn:country_code":"IN",
    "gn:dem":342,
    "gn:feature_class":"P",
    "gn:feature_code":"PPL",
    "gn:name":"\u0100m\u0101tola",
    "gn:population":0,
    "gn:timezone":"Asia/Kolkata",
    "iso:country":"IN",
    "ks:ks_alt_nam":"\u0100m\u0101tola",
    "ks:ks_name":"Amatola",
    "ks:ks_pop":523,
    "ks:ks_type":"VILLAGE",
    "name:eng_x_preferred":[
        "Amatola"
    ],
    "name:eng_x_variant":[
        "\u0100m\u0101tola"
    ],
    "wof:name":"Amatola",
    "wof:placetype":"locality",
    "wof:population":523
},
  "geometry": {"coordinates":[80.783998,20.35668],"type":"Point"}
}