{
  "type": "Feature",
  "properties": {
    "gn:admin1_code":"28",
    "gn:admin2_code":"337.0",
    "gn:asciiname":"Nagarbazar",
    "gn:cc2":"IN",
    "gn:country_code":"IN",
    "gn:dem":7,
    "gn:feature_class":"P",
    "gn:feature_code":"PPL",
    "gn:name":"Nagarbazar",
    "gn:population":0,
    "gn:timezone":"Asia/Kolkata",
    "iso:country":"IN",
    "name:und_x_variant":[
        "Nager Bazaar",
        "Nagarbazar"
    ],
    "wof:name":"Nagarbazar",
    "wof:placetype":"locality"
},
  "geometry": {"coordinates":[88.41667,22.61667000000001],"type":"Point"}
}