{
  "type": "Feature",
  "properties": {
    "iso:country":"IN",
    "ks:ks_name":"Dharampur",
    "ks:ks_pop":2386,
    "ks:ks_type":"HABITATION",
    "name:eng_x_preferred":[
        "Dharampur"
    ],
    "wof:name":"Dharampur",
    "wof:placetype":"locality",
    "wof:population":2386
},
  "geometry": {"coordinates":[81.412831,25.300687],"type":"Point"}
}