{
  "type": "Feature",
  "properties": {
    "gn:admin1_code":"16.0",
    "gn:admin2_code":"499.0",
    "gn:asciiname":"Lonvadi Khurd",
    "gn:country_code":"IN",
    "gn:dem":243,
    "gn:feature_class":"P",
    "gn:feature_code":"PPL",
    "gn:name":"Lonv\u0101di Khurd",
    "gn:population":0,
    "gn:timezone":"Asia/Kolkata",
    "iso:country":"IN",
    "wof:name":"Lonvadi Khurd",
    "wof:placetype":"neighbourhood"
},
  "geometry": {"coordinates":[75.50794999999999,20.80614],"type":"Point"}
}