{
  "type": "Feature",
  "properties": {
    "gn:admin1_code":"37",
    "gn:admin2_code":"407.0",
    "gn:asciiname":"Bano",
    "gn:country_code":"IN",
    "gn:dem":292,
    "gn:feature_class":"P",
    "gn:feature_code":"PPL",
    "gn:name":"B\u0101no",
    "gn:population":0,
    "gn:timezone":"Asia/Kolkata",
    "iso:country":"IN",
    "name:ceb_x_preferred":[
        "Bano"
    ],
    "name:fra_x_preferred":[
        "Bano"
    ],
    "name:slk_x_preferred":[
        "Bano"
    ],
    "name:swe_x_preferred":[
        "Bano"
    ],
    "wof:name":"Bano",
    "wof:placetype":"locality"
},
  "geometry": {"coordinates":[81.44976,21.94885],"type":"Point"}
}