{
  "type": "Feature",
  "properties": {
    "gn:admin1_code":"21.0",
    "gn:admin2_code":"389.0",
    "gn:asciiname":"Manderabaju",
    "gn:country_code":"IN",
    "gn:dem":608,
    "gn:feature_class":"P",
    "gn:feature_code":"PPL",
    "gn:name":"Manderab\u0101ju",
    "gn:population":0,
    "gn:timezone":"Asia/Kolkata",
    "iso:country":"IN",
    "ks:ks_name":"Mandrabaju",
    "ks:ks_pop":33,
    "ks:ks_type":"VILLAGE",
    "name:eng_x_preferred":[
        "Mandrabaju"
    ],
    "name:eng_x_variant":[
        "Manderabaju"
    ],
    "wof:name":"Mandrabaju",
    "wof:placetype":"locality",
    "wof:population":33
},
  "geometry": {"coordinates":[83.97305,19.41959],"type":"Point"}
}