{
  "type": "Feature",
  "properties": {
    "iso:country":"IN",
    "ks:ks_alt_nam":"CHHINGATOLI",
    "ks:ks_name":"Chhingatoli",
    "ks:ks_pop":185,
    "ks:ks_type":"HABITATION",
    "name:eng_x_preferred":[
        "Chhingatoli"
    ],
    "wof:name":"Chhingatoli",
    "wof:placetype":"locality",
    "wof:population":185
},
  "geometry": {"coordinates":[83.855048,23.118545],"type":"Point"}
}