{
  "type": "Feature",
  "properties": {
    "iso:country":"IN",
    "ks:ks_name":"Khadkipada",
    "ks:ks_pop":100,
    "ks:ks_type":"HABITATION",
    "name:eng_x_preferred":[
        "Khadkipada"
    ],
    "wof:name":"Khadkipada",
    "wof:placetype":"locality",
    "wof:population":100
},
  "geometry": {"coordinates":[73.078176,20.090217],"type":"Point"}
}