{
  "type": "Feature",
  "properties": {
    "gn:admin1_code":"10.0",
    "gn:admin2_code":"87.0",
    "gn:asciiname":"Kankarka",
    "gn:country_code":"IN",
    "gn:dem":273,
    "gn:feature_class":"P",
    "gn:feature_code":"PPL",
    "gn:name":"K\u0101nkarka",
    "gn:population":0,
    "gn:timezone":"Asia/Kolkata",
    "iso:country":"IN",
    "wof:name":"Kankarka",
    "wof:placetype":"locality"
},
  "geometry": {"coordinates":[76.92744999999999,28.18086],"type":"Point"}
}