{
  "type": "Feature",
  "properties": {
    "gn:admin1_code":"16",
    "gn:admin2_code":"505.0",
    "gn:asciiname":"Sirpur",
    "gn:country_code":"IN",
    "gn:dem":301,
    "gn:feature_class":"P",
    "gn:feature_code":"PPL",
    "gn:name":"S\u012brpur",
    "gn:population":0,
    "gn:timezone":"Asia/Kolkata",
    "iso:country":"IN",
    "name:tel_x_preferred":[
        "\u0c38\u0c3f\u0c30\u0c4d\u0c2a\u0c42\u0c30\u0c4d"
    ],
    "wof:name":"Sirpur",
    "wof:placetype":"locality"
},
  "geometry": {"coordinates":[79.24691,20.85554],"type":"Point"}
}