{
  "type": "Feature",
  "properties": {
    "iso:country":"IN",
    "ks:ks_alt_nam":"TURI TOLA",
    "ks:ks_name":"Turi Tola",
    "ks:ks_pop":137,
    "ks:ks_type":"HABITATION",
    "name:eng_x_preferred":[
        "Turi Tola"
    ],
    "wof:name":"Turi Tola",
    "wof:placetype":"locality",
    "wof:population":137
},
  "geometry": {"coordinates":[85.51180100000001,24.200393],"type":"Point"}
}