{
  "type": "Feature",
  "properties": {
    "gn:admin1_code":"13.0",
    "gn:admin2_code":"591.0",
    "gn:asciiname":"Kappumala",
    "gn:country_code":"IN",
    "gn:dem":53,
    "gn:feature_class":"P",
    "gn:feature_code":"PPL",
    "gn:name":"Kappumala",
    "gn:population":0,
    "gn:timezone":"Asia/Kolkata",
    "iso:country":"IN",
    "ks:ks_name":"Kappummal",
    "ks:ks_pop":452,
    "ks:ks_type":"HABITATION",
    "name:eng_x_preferred":[
        "Kappummal"
    ],
    "name:eng_x_variant":[
        "Kappumala"
    ],
    "wof:name":"Kappummal",
    "wof:placetype":"locality",
    "wof:population":452
},
  "geometry": {"coordinates":[75.717474,11.650179],"type":"Point"}
}