{
  "type": "Feature",
  "properties": {
    "iso:country":"IN",
    "ks:ks_name":"Perapally",
    "ks:ks_pop":1039,
    "ks:ks_type":"HABITATION",
    "name:eng_x_preferred":[
        "Perapally"
    ],
    "wof:name":"Perapally",
    "wof:placetype":"locality",
    "wof:population":1039
},
  "geometry": {"coordinates":[79.516623,18.657798],"type":"Point"}
}