{
  "type": "Feature",
  "properties": {
    "iso:country":"IN",
    "ks:ks_name":"Maj Bahbari",
    "ks:ks_pop":288,
    "ks:ks_type":"HABITATION",
    "ks:ks_uagg_main":0,
    "name:eng_x_preferred":[
        "Maj Bahbari"
    ],
    "wof:name":"Maj Bahbari",
    "wof:placetype":"neighbourhood",
    "wof:population":288
},
  "geometry": {"coordinates":[95.10450899999999,27.020141],"type":"Point"}
}