{
  "type": "Feature",
  "properties": {
    "gn:admin1_code":"19.0",
    "gn:admin2_code":"582.0",
    "gn:asciiname":"Pulaganahalli",
    "gn:country_code":"IN",
    "gn:dem":729,
    "gn:feature_class":"P",
    "gn:feature_code":"PPL",
    "gn:name":"Pulaganahalli",
    "gn:population":0,
    "gn:timezone":"Asia/Kolkata",
    "iso:country":"IN",
    "ks:ks_name":"Pulaganahalli",
    "ks:ks_pop":1358,
    "ks:ks_type":"VILLAGE",
    "ks:ks_uagg_main":0,
    "name:eng_x_preferred":[
        "Pulaganahalli"
    ],
    "wof:name":"Pulaganahalli",
    "wof:placetype":"neighbourhood",
    "wof:population":1358
},
  "geometry": {"coordinates":[77.454431,13.492833],"type":"Point"}
}