{
  "type": "Feature",
  "properties": {
    "gn:admin1_code":"36.0",
    "gn:admin2_code":"151.0",
    "gn:asciiname":"Jagat",
    "gn:country_code":"IN",
    "gn:dem":191,
    "gn:feature_class":"P",
    "gn:feature_code":"PPL",
    "gn:name":"Jagat",
    "gn:population":0,
    "gn:timezone":"Asia/Kolkata",
    "iso:country":"IN",
    "ks:ks_name":"Jagat",
    "ks:ks_type":"VILLAGE",
    "name:eng_x_preferred":[
        "Jagat"
    ],
    "wof:name":"Jagat",
    "wof:placetype":"locality"
},
  "geometry": {"coordinates":[79.774973,28.756058],"type":"Point"}
}