{
  "type": "Feature",
  "properties": {
    "iso:country":"IN",
    "ks:ks_name":"Pokshipada",
    "ks:ks_pop":100,
    "ks:ks_type":"HABITATION",
    "name:eng_x_preferred":[
        "Pokshipada"
    ],
    "wof:name":"Pokshipada",
    "wof:placetype":"locality",
    "wof:population":100
},
  "geometry": {"coordinates":[82.980887,19.549726],"type":"Point"}
}