{
  "type": "Feature",
  "properties": {
    "gn:admin1_code":"12.0",
    "gn:asciiname":"Kanarikhan",
    "gn:country_code":"IN",
    "gn:dem":3019,
    "gn:feature_class":"P",
    "gn:feature_code":"PPL",
    "gn:name":"Kan\u0101r\u012bkhan",
    "gn:population":0,
    "gn:timezone":"Asia/Kolkata",
    "iso:country":"IN",
    "wof:name":"Kanarikhan",
    "wof:placetype":"locality"
},
  "geometry": {"coordinates":[74.20064000000001,34.62728],"type":"Point"}
}