{
  "type": "Feature",
  "properties": {
    "iso:country":"IN",
    "ks:ks_name":"Shaipur",
    "ks:ks_pop":1193,
    "ks:ks_type":"VILLAGE",
    "ks:ks_uagg_main":0,
    "name:eng_x_preferred":[
        "Shaipur"
    ],
    "wof:name":"Shaipur",
    "wof:placetype":"neighbourhood",
    "wof:population":1193
},
  "geometry": {"coordinates":[82.736553,25.404575],"type":"Point"}
}