{
  "type": "Feature",
  "properties": {
    "iso:country":"IN",
    "ks:ks_name":"Tulushibhita",
    "ks:ks_pop":652,
    "ks:ks_type":"VILLAGE",
    "name:eng_x_preferred":[
        "Tulushibhita"
    ],
    "wof:name":"Tulushibhita",
    "wof:placetype":"locality",
    "wof:population":652
},
  "geometry": {"coordinates":[86.724255,23.830355],"type":"Point"}
}