{
  "type": "Feature",
  "properties": {
    "iso:country":"IN",
    "ks:ks_name":"Kottakamuduvalasa",
    "ks:ks_pop":75,
    "ks:ks_type":"HABITATION",
    "name:eng_x_preferred":[
        "Kottakamuduvalasa"
    ],
    "wof:name":"Kottakamuduvalasa",
    "wof:placetype":"locality",
    "wof:population":75
},
  "geometry": {"coordinates":[83.188017,18.678703],"type":"Point"}
}