{
  "type": "Feature",
  "properties": {
    "iso:country":"IN",
    "ks:ks_name":"Dolowjan",
    "ks:ks_pop":799,
    "ks:ks_type":"HABITATION",
    "name:eng_x_preferred":[
        "Dolowjan"
    ],
    "wof:name":"Dolowjan",
    "wof:placetype":"locality",
    "wof:population":799
},
  "geometry": {"coordinates":[93.967842,26.418537],"type":"Point"}
}