{
  "type": "Feature",
  "properties": {
    "iso:country":"IN",
    "ks:ks_name":"Munderi Chembali Jn",
    "ks:ks_pop":2015,
    "ks:ks_type":"HABITATION",
    "name:eng_x_preferred":[
        "Munderi Chembali Jn"
    ],
    "wof:name":"Munderi Chembali Jn",
    "wof:placetype":"locality",
    "wof:population":2015
},
  "geometry": {"coordinates":[76.274839,11.448066],"type":"Point"}
}