{
  "type": "Feature",
  "properties": {
    "iso:country":"IN",
    "ks:ks_name":"10 DKD A",
    "ks:ks_pop":393,
    "ks:ks_type":"VILLAGE",
    "name:eng_x_preferred":[
        "10 DKD A"
    ],
    "wof:name":"10 DKD A",
    "wof:placetype":"locality",
    "wof:population":393
},
  "geometry": {"coordinates":[72.850908,28.680681],"type":"Point"}
}