{
  "type": "Feature",
  "properties": {
    "gn:admin1_code":"25.0",
    "gn:admin2_code":"631.0",
    "gn:asciiname":"Virupasandiram",
    "gn:country_code":"IN",
    "gn:dem":866,
    "gn:feature_class":"P",
    "gn:feature_code":"PPL",
    "gn:name":"Virupasandiram",
    "gn:population":0,
    "gn:timezone":"Asia/Kolkata",
    "iso:country":"IN",
    "wof:name":"Virupasandiram",
    "wof:placetype":"neighbourhood"
},
  "geometry": {"coordinates":[77.84746,12.78529],"type":"Point"}
}