{
  "type": "Feature",
  "properties": {
    "iso:country":"IN",
    "ks:ks_name":"Kotapur",
    "ks:ks_pop":591,
    "ks:ks_type":"VILLAGE",
    "ks:ks_uagg_main":0,
    "name:eng_x_preferred":[
        "Kotapur"
    ],
    "wof:name":"Kotapur",
    "wof:placetype":"neighbourhood",
    "wof:population":591
},
  "geometry": {"coordinates":[86.567577,20.827262],"type":"Point"}
}