{
  "type": "Feature",
  "properties": {
    "iso:country":"IN",
    "ks:ks_name":"Pallam",
    "ks:ks_pop":712,
    "ks:ks_type":"HABITATION",
    "ks:ks_uagg_main":0,
    "name:eng_x_preferred":[
        "Pallam"
    ],
    "wof:name":"Pallam",
    "wof:placetype":"neighbourhood",
    "wof:population":712
},
  "geometry": {"coordinates":[76.24468899999999,10.744014],"type":"Point"}
}