{
  "type": "Feature",
  "properties": {
    "iso:country":"IN",
    "ks:ks_name":"Kanjiravilai",
    "ks:ks_pop":484,
    "ks:ks_type":"HABITATION",
    "name:eng_x_preferred":[
        "Kanjiravilai"
    ],
    "wof:name":"Kanjiravilai",
    "wof:placetype":"locality",
    "wof:population":484
},
  "geometry": {"coordinates":[77.362583,8.13587],"type":"Point"}
}