{
  "type": "Feature",
  "properties": {
    "gn:admin1_code":"36.0",
    "gn:admin2_code":"153.0",
    "gn:asciiname":"Neola",
    "gn:country_code":"IN",
    "gn:dem":157,
    "gn:feature_class":"P",
    "gn:feature_code":"PPL",
    "gn:name":"Neola",
    "gn:population":0,
    "gn:timezone":"Asia/Kolkata",
    "iso:country":"IN",
    "name:ceb_x_preferred":[
        "Neola"
    ],
    "name:deu_x_preferred":[
        "Neola"
    ],
    "name:fra_x_preferred":[
        "Neola"
    ],
    "name:ita_x_preferred":[
        "Neola"
    ],
    "name:nld_x_preferred":[
        "Neola"
    ],
    "name:pol_x_preferred":[
        "Neola"
    ],
    "name:por_x_preferred":[
        "Neola"
    ],
    "name:ukr_x_preferred":[
        "\u041d\u0456\u043e\u043b\u0430"
    ],
    "name:vol_x_preferred":[
        "Neola"
    ],
    "wof:name":"Neola",
    "wof:placetype":"locality"
},
  "geometry": {"coordinates":[80.13351,27.887],"type":"Point"}
}