{
  "type": "Feature",
  "properties": {
    "iso:country":"IN",
    "ks:ks_name":"Lakkarajupindi",
    "ks:ks_pop":67,
    "ks:ks_type":"HABITATION",
    "name:eng_x_preferred":[
        "Lakkarajupindi"
    ],
    "wof:name":"Lakkarajupindi",
    "wof:placetype":"locality",
    "wof:population":67
},
  "geometry": {"coordinates":[81.726125,16.818621],"type":"Point"}
}