{
  "type": "Feature",
  "properties": {
    "gn:admin1_code":"2.0",
    "gn:admin2_code":"551.0",
    "gn:asciiname":"Vayilipativandlapalle",
    "gn:country_code":"IN",
    "gn:dem":317,
    "gn:feature_class":"P",
    "gn:feature_code":"PPL",
    "gn:name":"V\u0101yilip\u0101tiv\u0101ndlapalle",
    "gn:population":0,
    "gn:timezone":"Asia/Kolkata",
    "iso:country":"IN",
    "ks:ks_name":"Vayalapativandlapalli",
    "ks:ks_pop":149,
    "ks:ks_type":"HABITATION",
    "ks:ks_uagg_main":0,
    "name:eng_x_preferred":[
        "Vayalapativandlapalli"
    ],
    "wof:name":"Vayalapativandlapalli",
    "wof:placetype":"neighbourhood",
    "wof:population":149
},
  "geometry": {"coordinates":[78.93694600000001,13.985067],"type":"Point"}
}