{
  "type": "Feature",
  "properties": {
    "gn:admin1_code":"36",
    "gn:admin2_code":"192.0",
    "gn:asciiname":"Nasopur",
    "gn:country_code":"IN",
    "gn:dem":74,
    "gn:feature_class":"P",
    "gn:feature_code":"PPL",
    "gn:name":"Nasopur",
    "gn:population":0,
    "gn:timezone":"Asia/Kolkata",
    "iso:country":"IN",
    "wof:name":"Nasopur",
    "wof:placetype":"locality"
},
  "geometry": {"coordinates":[83.59999000000001,25.94255],"type":"Point"}
}