{
  "type": "Feature",
  "properties": {
    "gn:admin1_code":"19.0",
    "gn:admin2_code":"566.0",
    "gn:asciiname":"Nagarakatte",
    "gn:country_code":"IN",
    "gn:dem":749,
    "gn:feature_class":"P",
    "gn:feature_code":"PPL",
    "gn:name":"Nagarakatte",
    "gn:population":0,
    "gn:timezone":"Asia/Kolkata",
    "iso:country":"IN",
    "wof:name":"Nagarakatte",
    "wof:placetype":"locality"
},
  "geometry": {"coordinates":[76.19745,13.89766],"type":"Point"}
}