{
  "type": "Feature",
  "properties": {
    "iso:country":"IN",
    "ks:ks_name":"Jagdalewasti",
    "ks:ks_pop":112,
    "ks:ks_type":"HABITATION",
    "name:eng_x_preferred":[
        "Jagdalewasti"
    ],
    "wof:name":"Jagdalewasti",
    "wof:placetype":"locality",
    "wof:population":112
},
  "geometry": {"coordinates":[75.645335,18.320081],"type":"Point"}
}