{
  "type": "Feature",
  "properties": {
    "iso:country":"IN",
    "ks:ks_name":"Chak Asraf",
    "ks:ks_pop":1022,
    "ks:ks_type":"VILLAGE",
    "ks:ks_uagg_main":0,
    "name:eng_x_preferred":[
        "Chak Asraf"
    ],
    "wof:name":"Chak Asraf",
    "wof:placetype":"neighbourhood",
    "wof:population":1022
},
  "geometry": {"coordinates":[84.793809,25.877444],"type":"Point"}
}