{
  "type": "Feature",
  "properties": {
    "gn:admin1_code":"34.0",
    "gn:admin2_code":"219.0",
    "gn:asciiname":"Mani Chhapra",
    "gn:country_code":"IN",
    "gn:dem":63,
    "gn:feature_class":"P",
    "gn:feature_code":"PPL",
    "gn:name":"Mani Chh\u0101pra",
    "gn:population":0,
    "gn:timezone":"Asia/Kolkata",
    "iso:country":"IN",
    "ks:ks_alt_nam":"Mani Chh\u0101pra",
    "ks:ks_name":"Mani Chhapra",
    "ks:ks_type":"VILLAGE",
    "ks:ks_uagg_main":0,
    "name:eng_x_preferred":[
        "Mani Chhapra"
    ],
    "name:eng_x_variant":[
        "Mani Chh\u0101pra"
    ],
    "wof:name":"Mani Chhapra",
    "wof:placetype":"neighbourhood"
},
  "geometry": {"coordinates":[84.525656,26.018747],"type":"Point"}
}