{
  "type": "Feature",
  "properties": {
    "iso:country":"IN",
    "ks:ks_name":"Badapepde",
    "ks:ks_pop":240,
    "ks:ks_type":"HABITATION",
    "name:eng_x_preferred":[
        "Badapepde"
    ],
    "wof:name":"Badapepde",
    "wof:placetype":"locality",
    "wof:population":240
},
  "geometry": {"coordinates":[74.998485,13.536762],"type":"Point"}
}