{
  "type": "Feature",
  "properties": {
    "iso:country":"IN",
    "ks:ks_name":"Chhota Bardadih",
    "ks:ks_pop":254,
    "ks:ks_type":"VILLAGE",
    "name:eng_x_preferred":[
        "Chhota Bardadih"
    ],
    "wof:name":"Chhota Bardadih",
    "wof:placetype":"locality",
    "wof:population":254
},
  "geometry": {"coordinates":[85.89934,22.414967],"type":"Point"}
}