{
  "type": "Feature",
  "properties": {
    "iso:country":"IN",
    "ks:ks_name":"Gorla Bodu",
    "ks:ks_type":"VILLAGE",
    "name:eng_x_preferred":[
        "Gorla Bodu"
    ],
    "wof:name":"Gorla Bodu",
    "wof:placetype":"locality"
},
  "geometry": {"coordinates":[79.076261,15.103658],"type":"Point"}
}