{
  "type": "Feature",
  "properties": {
    "iso:country":"IN",
    "ks:ks_alt_nam":"Bakuli\u0101",
    "ks:ks_name":"Bakulia",
    "ks:ks_type":"VILLAGE",
    "name:eng_x_preferred":[
        "Bakulia"
    ],
    "name:eng_x_variant":[
        "Bakuli\u0101"
    ],
    "wof:name":"Bakulia",
    "wof:placetype":"locality"
},
  "geometry": {"coordinates":[84.46274,27.090017],"type":"Point"}
}