{
  "type": "Feature",
  "properties": {
    "iso:country":"IN",
    "ks:ks_name":"Malemathadivalavu",
    "ks:ks_pop":69,
    "ks:ks_type":"HABITATION",
    "name:eng_x_preferred":[
        "Malemathadivalavu"
    ],
    "wof:name":"Malemathadivalavu",
    "wof:placetype":"locality",
    "wof:population":69
},
  "geometry": {"coordinates":[78.390727,11.350893],"type":"Point"}
}