{
  "type": "Feature",
  "properties": {
    "gn:admin1_code":"23.0",
    "gn:admin2_code":"35.0",
    "gn:asciiname":"Azizpur Kalan",
    "gn:country_code":"IN",
    "gn:dem":330,
    "gn:feature_class":"P",
    "gn:feature_code":"PPL",
    "gn:name":"Az\u012bzpur Kal\u0101n",
    "gn:population":0,
    "gn:timezone":"Asia/Kolkata",
    "iso:country":"IN",
    "ks:ks_name":"Azizpur Kalan",
    "ks:ks_pop":1745,
    "ks:ks_type":"VILLAGE",
    "ks:ks_uagg_main":0,
    "name:eng_x_preferred":[
        "Azizpur Kalan"
    ],
    "wof:name":"Azizpur Kalan",
    "wof:placetype":"locality",
    "wof:population":1745
},
  "geometry": {"coordinates":[75.586749,32.321885],"type":"Point"}
}