{
  "type": "Feature",
  "properties": {
    "iso:country":"IN",
    "ks:ks_name":"Bootha Kattu Valavu",
    "ks:ks_pop":281,
    "ks:ks_type":"HABITATION",
    "name:eng_x_preferred":[
        "Bootha Kattu Valavu"
    ],
    "wof:name":"Bootha Kattu Valavu",
    "wof:placetype":"locality",
    "wof:population":281
},
  "geometry": {"coordinates":[78.01058500000001,11.82532],"type":"Point"}
}