{
  "type": "Feature",
  "properties": {
    "iso:country":"IN",
    "ks:ks_name":"Ghodasalia",
    "ks:ks_pop":30,
    "ks:ks_type":"VILLAGE",
    "name:eng_x_preferred":[
        "Ghodasalia"
    ],
    "wof:name":"Ghodasalia",
    "wof:placetype":"locality",
    "wof:population":30
},
  "geometry": {"coordinates":[85.116069,19.762034],"type":"Point"}
}