{
  "type": "Feature",
  "properties": {
    "iso:country":"IN",
    "ks:ks_name":"Ghunimari Pt-I",
    "ks:ks_pop":33,
    "ks:ks_type":"VILLAGE",
    "name:eng_x_preferred":[
        "Ghunimari Pt-I"
    ],
    "wof:name":"Ghunimari Pt-I",
    "wof:placetype":"locality",
    "wof:population":33
},
  "geometry": {"coordinates":[90.19187100000001,26.093884],"type":"Point"}
}