{
  "type": "Feature",
  "properties": {
    "gn:admin1_code":"16",
    "gn:admin2_code":"511.0",
    "gn:asciiname":"Khadki",
    "gn:country_code":"IN",
    "gn:dem":386,
    "gn:feature_class":"P",
    "gn:feature_code":"PPL",
    "gn:name":"Khadki",
    "gn:population":0,
    "gn:timezone":"Asia/Kolkata",
    "iso:country":"IN",
    "name:ben_x_preferred":[
        "\u0995\u09bf\u09b0\u0995\u09c0"
    ],
    "name:bpy_x_preferred":[
        "\u0995\u09bf\u09b0\u0995\u09c0"
    ],
    "name:cat_x_preferred":[
        "Khadki"
    ],
    "name:ceb_x_preferred":[
        "Khadki"
    ],
    "name:ita_x_preferred":[
        "Kirkee"
    ],
    "name:mal_x_preferred":[
        "\u0d16\u0d21\u0d4d\u0d15\u0d3f"
    ],
    "name:mar_x_preferred":[
        "\u0916\u0921\u0915\u0940"
    ],
    "name:msa_x_preferred":[
        "Kirkee"
    ],
    "name:new_x_preferred":[
        "\u0915\u093f\u0930\u094d\u0915\u0940"
    ],
    "name:nld_x_preferred":[
        "Kirkee"
    ],
    "name:swe_x_preferred":[
        "Khadki"
    ],
    "name:tam_x_preferred":[
        "\u0b95\u0b9f\u0bcd\u0b95\u0bbf"
    ],
    "name:ukr_x_preferred":[
        "\u0425\u0430\u0434\u043a\u0456"
    ],
    "name:urd_x_preferred":[
        "\u06a9\u06be\u0691\u06a9\u06cc"
    ],
    "name:vie_x_preferred":[
        "Kirkee"
    ],
    "name:zho_x_preferred":[
        "\u57fa\u5c14\u51ef\u57c3"
    ],
    "wof:name":"Khadki",
    "wof:placetype":"locality"
},
  "geometry": {"coordinates":[77.22247,19.21263],"type":"Point"}
}