{
  "type": "Feature",
  "properties": {
    "iso:country":"IN",
    "ks:ks_name":"Sabarpara",
    "ks:ks_pop":214,
    "ks:ks_type":"HABITATION",
    "name:eng_x_preferred":[
        "Sabarpara"
    ],
    "wof:name":"Sabarpara",
    "wof:placetype":"locality",
    "wof:population":214
},
  "geometry": {"coordinates":[82.40266200000001,19.690526],"type":"Point"}
}