{
  "type": "Feature",
  "properties": {
    "iso:country":"IN",
    "ks:ks_name":"Yaduvanahalli",
    "ks:ks_pop":22,
    "ks:ks_type":"VILLAGE",
    "name:eng_x_preferred":[
        "Yaduvanahalli"
    ],
    "wof:name":"Yaduvanahalli",
    "wof:placetype":"locality",
    "wof:population":22
},
  "geometry": {"coordinates":[76.409092,12.868369],"type":"Point"}
}