{
  "type": "Feature",
  "properties": {
    "gn:admin1_code":"21.0",
    "gn:admin2_code":"396.0",
    "gn:asciiname":"Kyapadu",
    "gn:country_code":"IN",
    "gn:dem":460,
    "gn:feature_class":"P",
    "gn:feature_code":"PPL",
    "gn:name":"Ky\u0101p\u0101du",
    "gn:population":0,
    "gn:timezone":"Asia/Kolkata",
    "iso:country":"IN",
    "ks:ks_name":"Kiyapadu",
    "ks:ks_pop":280,
    "ks:ks_type":"VILLAGE",
    "name:eng_x_preferred":[
        "Kiyapadu"
    ],
    "name:eng_x_variant":[
        "Kyapadu"
    ],
    "wof:name":"Kiyapadu",
    "wof:placetype":"locality",
    "wof:population":280
},
  "geometry": {"coordinates":[83.27229699999999,19.245105],"type":"Point"}
}