{
  "type": "Feature",
  "properties": {
    "gn:admin1_code":"16.0",
    "gn:admin2_code":"515.0",
    "gn:asciiname":"Mahora",
    "gn:country_code":"IN",
    "gn:dem":649,
    "gn:feature_class":"P",
    "gn:feature_code":"PPL",
    "gn:name":"M\u0101hora",
    "gn:population":0,
    "gn:timezone":"Asia/Kolkata",
    "iso:country":"IN",
    "name:ceb_x_preferred":[
        "Mahora"
    ],
    "name:swe_x_preferred":[
        "Mahora"
    ],
    "wof:name":"Mahora",
    "wof:placetype":"locality"
},
  "geometry": {"coordinates":[75.44915,20.27961],"type":"Point"}
}