{
  "type": "Feature",
  "properties": {
    "iso:country":"IN",
    "ks:ks_name":"Harizan Basti",
    "ks:ks_pop":82,
    "ks:ks_type":"HABITATION",
    "name:eng_x_preferred":[
        "Harizan Basti"
    ],
    "wof:name":"Harizan Basti",
    "wof:placetype":"locality",
    "wof:population":82
},
  "geometry": {"coordinates":[83.361924,26.368509],"type":"Point"}
}