{
  "type": "Feature",
  "properties": {
    "iso:country":"IN",
    "ks:ks_alt_nam":"KHUNTITOLI",
    "ks:ks_name":"Khuntitoli",
    "ks:ks_pop":412,
    "ks:ks_type":"HABITATION",
    "name:eng_x_preferred":[
        "Khuntitoli"
    ],
    "wof:name":"Khuntitoli",
    "wof:placetype":"locality",
    "wof:population":412
},
  "geometry": {"coordinates":[83.86108,22.600768],"type":"Point"}
}