{
  "type": "Feature",
  "properties": {
    "iso:country":"IN",
    "ks:ks_name":"Uderiya",
    "ks:ks_pop":41,
    "ks:ks_type":"HABITATION",
    "name:eng_x_preferred":[
        "Uderiya"
    ],
    "wof:name":"Uderiya",
    "wof:placetype":"locality",
    "wof:population":41
},
  "geometry": {"coordinates":[79.97691,29.774676],"type":"Point"}
}