{
  "type": "Feature",
  "properties": {
    "gn:admin1_code":"39",
    "gn:admin2_code":"61.0",
    "gn:asciiname":"Dikoli",
    "gn:country_code":"IN",
    "gn:dem":1133,
    "gn:feature_class":"P",
    "gn:feature_code":"PPL",
    "gn:name":"Dikoli",
    "gn:population":0,
    "gn:timezone":"Asia/Kolkata",
    "iso:country":"IN",
    "wof:name":"Dikoli",
    "wof:placetype":"locality"
},
  "geometry": {"coordinates":[78.89301999999998,30.10353],"type":"Point"}
}