{
  "type": "Feature",
  "properties": {
    "gn:admin1_code":"36",
    "gn:admin2_code":"199.0",
    "gn:asciiname":"Semri",
    "gn:country_code":"IN",
    "gn:dem":90,
    "gn:feature_class":"P",
    "gn:feature_code":"PPL",
    "gn:name":"Semri",
    "gn:population":0,
    "gn:timezone":"Asia/Kolkata",
    "iso:country":"IN",
    "ks:ks_name":"Semri",
    "ks:ks_type":"VILLAGE",
    "name:eng_x_preferred":[
        "Semri"
    ],
    "wof:name":"Semri",
    "wof:placetype":"locality"
},
  "geometry": {"coordinates":[82.351359,25.151898],"type":"Point"}
}