{
  "type": "Feature",
  "properties": {
    "iso:country":"IN",
    "ks:ks_name":"Todma",
    "ks:ks_pop":136,
    "ks:ks_type":"HABITATION",
    "name:eng_x_preferred":[
        "Todma"
    ],
    "wof:name":"Todma",
    "wof:placetype":"locality",
    "wof:population":136
},
  "geometry": {"coordinates":[81.306494,19.195782],"type":"Point"}
}