{
  "type": "Feature",
  "properties": {
    "gn:admin1_code":"39.0",
    "gn:admin2_code":"66.0",
    "gn:asciiname":"Bhagwanpur Jai Singh",
    "gn:country_code":"IN",
    "gn:dem":417,
    "gn:feature_class":"P",
    "gn:feature_code":"PPL",
    "gn:name":"Bhagw\u0101npur Jai Singh",
    "gn:population":0,
    "gn:timezone":"Asia/Kolkata",
    "iso:country":"IN",
    "ks:ks_name":"Bhagwanpur Jaisingh",
    "ks:ks_pop":1371,
    "ks:ks_type":"VILLAGE",
    "ks:ks_uagg_main":0,
    "name:eng_x_preferred":[
        "Bhagwanpur Jaisingh"
    ],
    "wof:name":"Bhagwanpur Jaisingh",
    "wof:placetype":"neighbourhood",
    "wof:population":1371
},
  "geometry": {"coordinates":[79.479823,29.226163],"type":"Point"}
}