{
  "type": "Feature",
  "properties": {
    "gn:admin1_code":"24.0",
    "gn:admin2_code":"128.0",
    "gn:asciiname":"Ratanpura",
    "gn:country_code":"IN",
    "gn:dem":283,
    "gn:feature_class":"P",
    "gn:feature_code":"PPL",
    "gn:name":"Ratanpura",
    "gn:population":0,
    "gn:timezone":"Asia/Kolkata",
    "iso:country":"IN",
    "ks:ks_name":"Ratanpura",
    "ks:ks_pop":2710,
    "ks:ks_type":"VILLAGE",
    "ks:ks_uagg_main":0,
    "name:eng_x_preferred":[
        "Ratanpura"
    ],
    "name:hin_x_preferred":[
        "\u0930\u0924\u0928\u092a\u0941\u0930\u093e"
    ],
    "wof:name":"Ratanpura",
    "wof:placetype":"neighbourhood",
    "wof:population":2710
},
  "geometry": {"coordinates":[76.67482099999999,24.884845],"type":"Point"}
}