{
  "type": "Feature",
  "properties": {
    "iso:country":"IN",
    "ks:ks_name":"Khudoli",
    "ks:ks_pop":138,
    "ks:ks_type":"HABITATION",
    "name:eng_x_preferred":[
        "Khudoli"
    ],
    "wof:name":"Khudoli",
    "wof:placetype":"locality",
    "wof:population":138
},
  "geometry": {"coordinates":[79.487312,29.522417],"type":"Point"}
}