{
  "type": "Feature",
  "properties": {
    "iso:country":"IN",
    "ks:ks_name":"Jasauli",
    "ks:ks_pop":3628,
    "ks:ks_type":"VILLAGE",
    "ks:ks_uagg_main":0,
    "name:eng_x_preferred":[
        "Jasauli"
    ],
    "wof:name":"Jasauli",
    "wof:placetype":"neighbourhood",
    "wof:population":3628
},
  "geometry": {"coordinates":[85.09929700000001,26.227415],"type":"Point"}
}