{
  "type": "Feature",
  "properties": {
    "iso:country":"IN",
    "ks:ks_name":"Gurangi-I",
    "ks:ks_pop":155,
    "ks:ks_type":"VILLAGE",
    "name:eng_x_preferred":[
        "Gurangi-I"
    ],
    "wof:name":"Gurangi-I",
    "wof:placetype":"locality",
    "wof:population":155
},
  "geometry": {"coordinates":[84.441372,19.14597],"type":"Point"}
}