{
  "type": "Feature",
  "properties": {
    "iso:country":"IN",
    "ks:ks_name":"Gangti Kita",
    "ks:ks_pop":23,
    "ks:ks_type":"HABITATION",
    "name:eng_x_preferred":[
        "Gangti Kita"
    ],
    "wof:name":"Gangti Kita",
    "wof:placetype":"locality",
    "wof:population":23
},
  "geometry": {"coordinates":[87.20223300000001,24.929674],"type":"Point"}
}