{
  "type": "Feature",
  "properties": {
    "iso:country":"IN",
    "ks:ks_name":"Manikpur Thegu Urf Akhtiarpur",
    "ks:ks_pop":1111,
    "ks:ks_type":"VILLAGE",
    "name:eng_x_preferred":[
        "Manikpur Thegu Urf Akhtiarpur"
    ],
    "wof:name":"Manikpur Thegu Urf Akhtiarpur",
    "wof:placetype":"locality",
    "wof:population":1111
},
  "geometry": {"coordinates":[85.434355,25.771084],"type":"Point"}
}