{
  "type": "Feature",
  "properties": {
    "gn:admin1_code":"35.0",
    "gn:admin2_code":"454.0",
    "gn:asciiname":"Kumharra",
    "gn:country_code":"IN",
    "gn:dem":476,
    "gn:feature_class":"P",
    "gn:feature_code":"PPL",
    "gn:name":"Kumharr\u0101",
    "gn:population":0,
    "gn:timezone":"Asia/Kolkata",
    "iso:country":"IN",
    "name:und_x_variant":[
        "Kumharr\u0101",
        "Kurw\u0101h\u012b"
    ],
    "wof:name":"Kumharra",
    "wof:placetype":"locality"
},
  "geometry": {"coordinates":[80.49259000000001,22.45954],"type":"Point"}
}