{
  "type": "Feature",
  "properties": {
    "iso:country":"IN",
    "ks:ks_name":"Raghunathpur",
    "ks:ks_pop":258,
    "ks:ks_type":"HABITATION",
    "name:eng_x_preferred":[
        "Raghunathpur"
    ],
    "wof:name":"Raghunathpur",
    "wof:placetype":"locality",
    "wof:population":258
},
  "geometry": {"coordinates":[84.845938,19.999974],"type":"Point"}
}