{
  "type": "Feature",
  "properties": {
    "gn:admin1_code":"21.0",
    "gn:admin2_code":"398.0",
    "gn:asciiname":"Podiriputtu",
    "gn:country_code":"IN",
    "gn:dem":857,
    "gn:feature_class":"P",
    "gn:feature_code":"PPL",
    "gn:name":"Podiriputtu",
    "gn:population":0,
    "gn:timezone":"Asia/Kolkata",
    "iso:country":"IN",
    "wof:name":"Podiriputtu",
    "wof:placetype":"neighbourhood"
},
  "geometry": {"coordinates":[82.88106999999999,18.89187],"type":"Point"}
}