{
  "type": "Feature",
  "properties": {
    "iso:country":"IN",
    "ks:ks_name":"Chirakkepara",
    "ks:ks_pop":101,
    "ks:ks_type":"HABITATION",
    "name:eng_x_preferred":[
        "Chirakkepara"
    ],
    "wof:name":"Chirakkepara",
    "wof:placetype":"locality",
    "wof:population":101
},
  "geometry": {"coordinates":[76.71946699999999,9.461519],"type":"Point"}
}