{
  "type": "Feature",
  "properties": {
    "iso:country":"IN",
    "ks:ks_name":"Kot",
    "ks:ks_pop":224,
    "ks:ks_type":"HABITATION",
    "name:eng_x_preferred":[
        "Kot"
    ],
    "wof:name":"Kot",
    "wof:placetype":"locality",
    "wof:population":224
},
  "geometry": {"coordinates":[85.668336,21.161692],"type":"Point"}
}