{
  "type": "Feature",
  "properties": {
    "iso:country":"IN",
    "ks:ks_name":"Gopatnagar",
    "ks:ks_pop":80,
    "ks:ks_type":"HABITATION",
    "name:eng_x_preferred":[
        "Gopatnagar"
    ],
    "wof:name":"Gopatnagar",
    "wof:placetype":"locality",
    "wof:population":80
},
  "geometry": {"coordinates":[82.29994600000001,23.740584],"type":"Point"}
}