{
  "type": "Feature",
  "properties": {
    "iso:country":"IN",
    "ks:ks_name":"Maijori",
    "ks:ks_pop":396,
    "ks:ks_type":"VILLAGE",
    "ks:ks_uagg_main":0,
    "name:eng_x_preferred":[
        "Maijori"
    ],
    "wof:name":"Maijori",
    "wof:placetype":"neighbourhood",
    "wof:population":396
},
  "geometry": {"coordinates":[85.45757,20.348773],"type":"Point"}
}