{
  "type": "Feature",
  "properties": {
    "iso:country":"IN",
    "ks:ks_name":"Nadhri",
    "ks:ks_pop":711,
    "ks:ks_type":"VILLAGE",
    "name:eng_x_preferred":[
        "Nadhri"
    ],
    "wof:name":"Nadhri",
    "wof:placetype":"locality",
    "wof:population":711
},
  "geometry": {"coordinates":[82.78686399999999,24.366515],"type":"Point"}
}