{
  "type": "Feature",
  "properties": {
    "gn:admin1_code":"11",
    "gn:admin2_code":"23.0",
    "gn:asciiname":"Khola",
    "gn:country_code":"IN",
    "gn:dem":1239,
    "gn:feature_class":"P",
    "gn:feature_code":"PPL",
    "gn:name":"Khola",
    "gn:population":0,
    "gn:timezone":"Asia/Kolkata",
    "iso:country":"IN",
    "name:deu_x_preferred":[
        "Khola"
    ],
    "wof:name":"Khola",
    "wof:placetype":"locality"
},
  "geometry": {"coordinates":[76.03366,32.33881],"type":"Point"}
}