{
  "type": "Feature",
  "properties": {
    "gn:admin1_code":"19.0",
    "gn:admin2_code":"567.0",
    "gn:asciiname":"Halavagalu",
    "gn:country_code":"IN",
    "gn:dem":534,
    "gn:feature_class":"P",
    "gn:feature_code":"PPL",
    "gn:name":"Halav\u0101galu",
    "gn:population":0,
    "gn:timezone":"Asia/Kolkata",
    "iso:country":"IN",
    "wof:name":"Halavagalu",
    "wof:placetype":"locality"
},
  "geometry": {"coordinates":[75.7753,14.70828],"type":"Point"}
}