{
  "type": "Feature",
  "properties": {
    "iso:country":"IN",
    "ks:ks_name":"Chinnathenampatti",
    "ks:ks_pop":167,
    "ks:ks_type":"HABITATION",
    "ks:ks_uagg_main":0,
    "name:eng_x_preferred":[
        "Chinnathenampatti"
    ],
    "wof:name":"Chinnathenampatti",
    "wof:placetype":"neighbourhood",
    "wof:population":167
},
  "geometry": {"coordinates":[78.42939699999999,10.359398],"type":"Point"}
}