{
  "type": "Feature",
  "properties": {
    "gn:admin1_code":"19.0",
    "gn:admin2_code":"584.0",
    "gn:asciiname":"Bhadregowdanpalya",
    "gn:country_code":"IN",
    "gn:dem":882,
    "gn:feature_class":"P",
    "gn:feature_code":"PPL",
    "gn:name":"Bhadregowdanp\u0101lya",
    "gn:population":0,
    "gn:timezone":"Asia/Kolkata",
    "iso:country":"IN",
    "wof:name":"Bhadregowdanpalya",
    "wof:placetype":"locality"
},
  "geometry": {"coordinates":[77.17641999999999,12.9963],"type":"Point"}
}