{
  "type": "Feature",
  "properties": {
    "iso:country":"IN",
    "ks:ks_alt_nam":"Sahr\u0101mau",
    "ks:ks_name":"Sahramau",
    "ks:ks_type":"VILLAGE",
    "name:eng_x_preferred":[
        "Sahramau"
    ],
    "name:eng_x_variant":[
        "Sahr\u0101mau"
    ],
    "wof:name":"Sahramau",
    "wof:placetype":"locality"
},
  "geometry": {"coordinates":[82.851964,26.424343],"type":"Point"}
}