{
  "type": "Feature",
  "properties": {
    "iso:country":"IN",
    "ks:ks_alt_nam":"HARIJANWASTI",
    "ks:ks_name":"Harijanwasti",
    "ks:ks_pop":125,
    "ks:ks_type":"HABITATION",
    "name:eng_x_preferred":[
        "Harijanwasti"
    ],
    "wof:name":"Harijanwasti",
    "wof:placetype":"locality",
    "wof:population":125
},
  "geometry": {"coordinates":[75.003291,17.102503],"type":"Point"}
}