{
  "type": "Feature",
  "properties": {
    "iso:country":"IN",
    "ks:ks_name":"Yadahalli",
    "ks:ks_pop":2502,
    "ks:ks_type":"VILLAGE",
    "ks:ks_uagg_main":0,
    "name:eng_x_preferred":[
        "Yadahalli"
    ],
    "wof:name":"Yadahalli",
    "wof:placetype":"neighbourhood",
    "wof:population":2502
},
  "geometry": {"coordinates":[75.343766,16.299993],"type":"Point"}
}