{
  "type": "Feature",
  "properties": {
    "gn:admin1_code":"38.0",
    "gn:admin2_code":"348.0",
    "gn:asciiname":"Bandha Chak",
    "gn:country_code":"IN",
    "gn:dem":385,
    "gn:feature_class":"P",
    "gn:feature_code":"PPL",
    "gn:name":"Bandha Chak",
    "gn:population":0,
    "gn:timezone":"Asia/Kolkata",
    "iso:country":"IN",
    "ks:ks_name":"Bandha Chak",
    "ks:ks_pop":619,
    "ks:ks_type":"VILLAGE",
    "ks:ks_uagg_main":0,
    "name:eng_x_preferred":[
        "Bandha Chak"
    ],
    "wof:name":"Bandha Chak",
    "wof:placetype":"neighbourhood",
    "wof:population":619
},
  "geometry": {"coordinates":[85.501251,24.394605],"type":"Point"}
}