{
  "type": "Feature",
  "properties": {
    "iso:country":"IN",
    "ks:ks_name":"Harizon Tola",
    "ks:ks_pop":241,
    "ks:ks_type":"HABITATION",
    "name:eng_x_preferred":[
        "Harizon Tola"
    ],
    "wof:name":"Harizon Tola",
    "wof:placetype":"locality",
    "wof:population":241
},
  "geometry": {"coordinates":[85.826437,25.547899],"type":"Point"}
}