{
  "type": "Feature",
  "properties": {
    "gn:country":"IN",
    "gn:fcode":"PPL",
    "gn:pop":23520,
    "iso:country":"IN",
    "name:ben_x_preferred":[
        "\u09a8\u09be\u09a6\u09ac\u09be\u0987"
    ],
    "name:bpy_x_preferred":[
        "\u09a8\u09be\u09a6\u09ac\u09be\u0987"
    ],
    "name:deu_x_preferred":[
        "Nadbai"
    ],
    "name:eng_x_preferred":[
        "Nadbai"
    ],
    "name:fra_x_preferred":[
        "Nadbai"
    ],
    "name:guj_x_preferred":[
        "\u0aa8\u0abe\u0aa6\u0aac\u0abe\u0a87"
    ],
    "name:ita_x_preferred":[
        "Nadbai"
    ],
    "name:jpn_x_preferred":[
        "\u30ca\u30c3\u30c9\u30d0\u30a4"
    ],
    "name:kan_x_preferred":[
        "\u0ca8\u0cbe\u0ca1\u0ccd\u0cac\u0cbe\u0caf\u0cbf"
    ],
    "name:kor_x_preferred":[
        "\ub098\ub4dc\ubc14\uc774"
    ],
    "name:msa_x_preferred":[
        "Nadbai"
    ],
    "name:new_x_preferred":[
        "\u0928\u0926\u094d\u092c\u0948"
    ],
    "name:nld_x_preferred":[
        "Nadbai"
    ],
    "name:ori_x_preferred":[
        "\u0b28\u0b3e\u0b21\u0b3c\u0b2c\u0b3e\u0b07"
    ],
    "name:por_x_preferred":[
        "Nadbai"
    ],
    "name:rus_x_preferred":[
        "\u041d\u0430\u0434\u0431\u0430\u0438"
    ],
    "name:spa_x_preferred":[
        "Nadbai"
    ],
    "name:swe_x_preferred":[
        "N\u0101dbai"
    ],
    "name:tam_x_preferred":[
        "\u0ba8\u0b9f\u0baa\u0bbe\u0baf\u0bcd"
    ],
    "name:tel_x_preferred":[
        "\u0c28\u0c3e\u0c26\u0c4d\u0c2c\u0c2f\u0c40"
    ],
    "name:unk_x_variant":[
        "N\u0101dbai"
    ],
    "name:urd_x_preferred":[
        "\u0646\u062f\u0628\u0627\u0626\u06cc"
    ],
    "name:vie_x_preferred":[
        "Nadbai"
    ],
    "name:zho_x_preferred":[
        "\u7eb3\u5fb7\u62dc"
    ],
    "qs:name":"Nadbai",
    "qs:name_adm0":"India",
    "qs:name_adm1":"Rajasthan",
    "qs:photos_9r":0,
    "qs:photos_sr":0,
    "qs:placetype":"Town",
    "qs:pop_sr":"7",
    "wd:wordcount":583,
    "wof:name":"Nadbai",
    "wof:placetype":"locality",
    "wof:population":23520
},
  "geometry": {"coordinates":[77.19569,27.22288],"type":"Point"}
}