{
  "type": "Feature",
  "properties": {
    "iso:country":"IN",
    "ks:ks_name":"Rajapura",
    "ks:ks_pop":250,
    "ks:ks_type":"HABITATION",
    "name:eng_x_preferred":[
        "Rajapura"
    ],
    "wof:name":"Rajapura",
    "wof:placetype":"locality",
    "wof:population":250
},
  "geometry": {"coordinates":[76.07009100000001,12.166446],"type":"Point"}
}