{
  "type": "Feature",
  "properties": {
    "iso:country":"IN",
    "ks:ks_name":"Anjan",
    "ks:ks_pop":202,
    "ks:ks_type":"HABITATION",
    "name:eng_x_preferred":[
        "Anjan"
    ],
    "wof:name":"Anjan",
    "wof:placetype":"locality",
    "wof:population":202
},
  "geometry": {"coordinates":[83.994215,26.286938],"type":"Point"}
}