{
  "type": "Feature",
  "properties": {
    "gn:admin1_code":"12.0",
    "gn:admin2_code":"12.0",
    "gn:asciiname":"Tsaigund",
    "gn:country_code":"IN",
    "gn:dem":1840,
    "gn:feature_class":"P",
    "gn:feature_code":"PPL",
    "gn:name":"Tsaigund",
    "gn:population":0,
    "gn:timezone":"Asia/Kolkata",
    "iso:country":"IN",
    "wof:name":"Tsaigund",
    "wof:placetype":"locality"
},
  "geometry": {"coordinates":[74.84451,33.79544],"type":"Point"}
}