{
  "type": "Feature",
  "properties": {
    "gn:admin1_code":"24",
    "gn:admin2_code":"119.0",
    "gn:asciiname":"Ramankhera",
    "gn:country_code":"IN",
    "gn:dem":429,
    "gn:feature_class":"P",
    "gn:feature_code":"PPL",
    "gn:name":"R\u0101mankhera",
    "gn:population":0,
    "gn:timezone":"Asia/Kolkata",
    "iso:country":"IN",
    "ks:ks_name":"Rahman Khera",
    "ks:ks_pop":262,
    "ks:ks_type":"VILLAGE",
    "name:eng_x_preferred":[
        "Rahman Khera"
    ],
    "name:eng_x_variant":[
        "Ramankhera"
    ],
    "wof:name":"Rahman Khera",
    "wof:placetype":"locality",
    "wof:population":262
},
  "geometry": {"coordinates":[74.33854700000001,26.172789],"type":"Point"}
}