{
  "type": "Feature",
  "properties": {
    "iso:country":"IN",
    "ks:ks_name":"Chattu Musar Tola",
    "ks:ks_pop":311,
    "ks:ks_type":"HABITATION",
    "name:eng_x_preferred":[
        "Chattu Musar Tola"
    ],
    "wof:name":"Chattu Musar Tola",
    "wof:placetype":"locality",
    "wof:population":311
},
  "geometry": {"coordinates":[83.957519,26.699546],"type":"Point"}
}