{
  "type": "Feature",
  "properties": {
    "iso:country":"IN",
    "ks:ks_alt_nam":"DasariHarijinapeta",
    "ks:ks_name":"Dasariharijinapeta",
    "ks:ks_pop":286,
    "ks:ks_type":"HABITATION",
    "name:eng_x_preferred":[
        "Dasariharijinapeta"
    ],
    "wof:name":"Dasariharijinapeta",
    "wof:placetype":"locality",
    "wof:population":286
},
  "geometry": {"coordinates":[81.919608,16.627653],"type":"Point"}
}