{
  "type": "Feature",
  "properties": {
    "iso:country":"IN",
    "ks:ks_name":"Gadabangiri",
    "ks:ks_pop":294,
    "ks:ks_type":"VILLAGE",
    "name:eng_x_preferred":[
        "Gadabangiri"
    ],
    "wof:name":"Gadabangiri",
    "wof:placetype":"locality",
    "wof:population":294
},
  "geometry": {"coordinates":[83.601281,19.533516],"type":"Point"}
}