{
  "type": "Feature",
  "properties": {
    "iso:country":"IN",
    "ks:ks_name":"Badinu",
    "ks:ks_pop":72,
    "ks:ks_type":"HABITATION",
    "name:eng_x_preferred":[
        "Badinu"
    ],
    "wof:name":"Badinu",
    "wof:placetype":"locality",
    "wof:population":72
},
  "geometry": {"coordinates":[79.00837199999999,29.726866],"type":"Point"}
}