{
  "type": "Feature",
  "properties": {
    "gn:admin1_code":"19.0",
    "gn:admin2_code":"566.0",
    "gn:asciiname":"Aralihalli",
    "gn:country_code":"IN",
    "gn:dem":707,
    "gn:feature_class":"P",
    "gn:feature_code":"PPL",
    "gn:name":"Aralihalli",
    "gn:population":0,
    "gn:timezone":"Asia/Kolkata",
    "iso:country":"IN",
    "wof:name":"Aralihalli",
    "wof:placetype":"locality"
},
  "geometry": {"coordinates":[76.22744,13.78575],"type":"Point"}
}