{
  "type": "Feature",
  "properties": {
    "gn:admin1_code":"39.0",
    "gn:admin2_code":"60.0",
    "gn:asciiname":"Bajhet",
    "gn:country_code":"IN",
    "gn:dem":742,
    "gn:feature_class":"P",
    "gn:feature_code":"PPL",
    "gn:name":"Bajhet",
    "gn:population":0,
    "gn:timezone":"Asia/Kolkata",
    "iso:country":"IN",
    "wof:name":"Bajhet",
    "wof:placetype":"locality"
},
  "geometry": {"coordinates":[78.10965,30.3387],"type":"Point"}
}