{
  "type": "Feature",
  "properties": {
    "gn:admin1_code":"39.0",
    "gn:admin2_code":"60.0",
    "gn:asciiname":"Bajhet",
    "gn:country_code":"IN",
    "gn:dem":742,
    "gn:feature_class":"P",
    "gn:feature_code":"PPL",
    "gn:name":"Bajhet",
    "gn:population":0,
    "gn:timezone":"Asia/Kolkata",
    "iso:country":"IN",
    "ks:ks_name":"Bajhet",
    "ks:ks_type":"VILLAGE",
    "name:eng_x_preferred":[
        "Bajhet"
    ],
    "wof:name":"Bajhet",
    "wof:placetype":"locality"
},
  "geometry": {"coordinates":[78.10964800000001,30.338701],"type":"Point"}
}