{
  "type": "Feature",
  "properties": {
    "iso:country":"IN",
    "ks:ks_name":"Varli F",
    "ks:ks_pop":752,
    "ks:ks_type":"HABITATION",
    "ks:ks_uagg_main":0,
    "name:eng_x_preferred":[
        "Varli F"
    ],
    "wof:name":"Varli F",
    "wof:placetype":"neighbourhood",
    "wof:population":752
},
  "geometry": {"coordinates":[73.28530600000001,20.803528],"type":"Point"}
}