{
  "type": "Feature",
  "properties": {
    "iso:country":"IN",
    "ks:ks_name":"Battnail",
    "ks:ks_pop":15,
    "ks:ks_type":"HABITATION",
    "name:eng_x_preferred":[
        "Battnail"
    ],
    "wof:name":"Battnail",
    "wof:placetype":"locality",
    "wof:population":15
},
  "geometry": {"coordinates":[75.489723,12.766832],"type":"Point"}
}