{
  "type": "Feature",
  "properties": {
    "iso:country":"IN",
    "ks:ks_name":"Uttar Madhabdanga",
    "ks:ks_pop":5413,
    "ks:ks_type":"VILLAGE",
    "ks:ks_uagg_main":0,
    "name:eng_x_preferred":[
        "Uttar Madhabdanga"
    ],
    "wof:name":"Uttar Madhabdanga",
    "wof:placetype":"neighbourhood",
    "wof:population":5413
},
  "geometry": {"coordinates":[88.818151,26.548604],"type":"Point"}
}