{
  "type": "Feature",
  "properties": {
    "gn:admin1_code":"19.0",
    "gn:admin2_code":"578.0",
    "gn:asciiname":"Hosur",
    "gn:country_code":"IN",
    "gn:dem":784,
    "gn:feature_class":"P",
    "gn:feature_code":"PPL",
    "gn:name":"H\u014ds\u016br",
    "gn:population":0,
    "gn:timezone":"Asia/Kolkata",
    "iso:country":"IN",
    "ks:ks_alt_nam":"H\u014ds\u016br",
    "ks:ks_name":"Hosur",
    "ks:ks_type":"VILLAGE",
    "ks:ks_uagg_main":0,
    "name:ara_x_preferred":[
        "\u0647\u0648\u0633\u0648\u0631"
    ],
    "name:ben_bn_x_preferred":[
        "\u09b9\u09cb\u09b8\u09c1\u09b0"
    ],
    "name:ben_in_x_preferred":[
        "\u09b9\u09cb\u09b8\u09c1\u09b0"
    ],
    "name:bih_x_preferred":[
        "\u0939\u094b\u0938\u0941\u0930"
    ],
    "name:bpy_x_preferred":[
        "\u09b9\u09cb\u09b8\u09c1\u09b0"
    ],
    "name:cat_x_preferred":[
        "Hosur"
    ],
    "name:ceb_x_preferred":[
        "Hos\u016br"
    ],
    "name:deu_x_preferred":[
        "Hosur"
    ],
    "name:eng_x_preferred":[
        "Hosur"
    ],
    "name:eng_x_variant":[
        "H\u014ds\u016br"
    ],
    "name:guj_x_preferred":[
        "\u0ab9\u0acb\u0ab8\u0ac1\u0ab0"
    ],
    "name:hin_x_preferred":[
        "\u0939\u094b\u0938\u0941\u0930"
    ],
    "name:hin_x_variant":[
        "\u0939\u094b\u0938\u0942\u0930"
    ],
    "name:ita_x_preferred":[
        "Hosur"
    ],
    "name:kan_x_preferred":[
        "\u0cb9\u0cca\u0cb8\u0cc2\u0cb0\u0cc1"
    ],
    "name:mal_x_preferred":[
        "\u0d39\u0d4a\u0d38\u0d42\u0d7c"
    ],
    "name:mar_x_preferred":[
        "\u0939\u094b\u0938\u0942\u0930"
    ],
    "name:mlg_x_preferred":[
        "Hosur"
    ],
    "name:msa_x_preferred":[
        "Hosur"
    ],
    "name:new_x_preferred":[
        "\u0939\u094b\u0938\u0941\u0930"
    ],
    "name:pan_x_preferred":[
        "\u0a39\u0a4b\u0a1c\u0a41\u0a30"
    ],
    "name:spa_x_preferred":[
        "Hosur"
    ],
    "name:swe_x_preferred":[
        "Hosur"
    ],
    "name:tam_x_preferred":[
        "\u0b93\u0b9a\u0bc2\u0bb0\u0bcd"
    ],
    "name:tel_x_preferred":[
        "\u0c39\u0c4b\u0c38\u0c42\u0c30\u0c4d"
    ],
    "name:urd_x_preferred":[
        "\u06c1\u0648\u0633\u0648\u0631"
    ],
    "name:vie_x_preferred":[
        "Hosur"
    ],
    "name:zho_x_preferred":[
        "\u970d\u82cf\u5c14"
    ],
    "wof:name":"Hosur",
    "wof:placetype":"locality"
},
  "geometry": {"coordinates":[76.693772,11.821421],"type":"Point"}
}