{
  "type": "Feature",
  "properties": {
    "gn:admin1_code":"36.0",
    "gn:admin2_code":"139.0",
    "gn:asciiname":"Begamabadgarhi",
    "gn:country_code":"IN",
    "gn:dem":234,
    "gn:feature_class":"P",
    "gn:feature_code":"PPL",
    "gn:name":"Begam\u0101b\u0101dgarhi",
    "gn:population":0,
    "gn:timezone":"Asia/Kolkata",
    "iso:country":"IN",
    "wof:name":"Begamabadgarhi",
    "wof:placetype":"locality"
},
  "geometry": {"coordinates":[77.40529000000002,29.14632000000001],"type":"Point"}
}