{
  "type": "Feature",
  "properties": {
    "iso:country":"IN",
    "ks:ks_alt_nam":"Sardar para",
    "ks:ks_name":"Sardar Para",
    "ks:ks_pop":754,
    "ks:ks_type":"HABITATION",
    "name:eng_x_preferred":[
        "Sardar Para"
    ],
    "wof:name":"Sardar Para",
    "wof:placetype":"locality",
    "wof:population":754
},
  "geometry": {"coordinates":[88.88561199999999,22.254131],"type":"Point"}
}