{
  "type": "Feature",
  "properties": {
    "gn:admin1_code":"35",
    "gn:admin2_code":"443.0",
    "gn:asciiname":"Kuja",
    "gn:country_code":"IN",
    "gn:dem":421,
    "gn:feature_class":"P",
    "gn:feature_code":"PPL",
    "gn:name":"K\u016bja",
    "gn:population":0,
    "gn:timezone":"Asia/Kolkata",
    "iso:country":"IN",
    "name:ceb_x_preferred":[
        "Kuja"
    ],
    "name:swe_x_preferred":[
        "Kuja"
    ],
    "name:war_x_preferred":[
        "Kuja"
    ],
    "wof:name":"Kuja",
    "wof:placetype":"locality"
},
  "geometry": {"coordinates":[77.90533000000001,24.13367],"type":"Point"}
}