{
  "type": "Feature",
  "properties": {
    "gn:admin1_code":"36",
    "gn:admin2_code":"147.0",
    "gn:asciiname":"Nagla Mahajit",
    "gn:country_code":"IN",
    "gn:dem":163,
    "gn:feature_class":"P",
    "gn:feature_code":"PPL",
    "gn:name":"Nagla Mah\u0101j\u012bt",
    "gn:population":0,
    "gn:timezone":"Asia/Kolkata",
    "iso:country":"IN",
    "name:und_x_variant":[
        "Nagla Mah\u0101j\u012bt",
        "Jaw\u0101hirpur"
    ],
    "wof:name":"Nagla Mahajit",
    "wof:placetype":"neighbourhood"
},
  "geometry": {"coordinates":[78.53585,27.00889],"type":"Point"}
}