{
  "type": "Feature",
  "properties": {
    "iso:country":"IN",
    "ks:ks_name":"Buwa Purwa",
    "ks:ks_pop":486,
    "ks:ks_type":"HABITATION",
    "name:eng_x_preferred":[
        "Buwa Purwa"
    ],
    "wof:name":"Buwa Purwa",
    "wof:placetype":"locality",
    "wof:population":486
},
  "geometry": {"coordinates":[80.84316,25.198828],"type":"Point"}
}