{
  "type": "Feature",
  "properties": {
    "iso:country":"IN",
    "ks:ks_name":"Dhan Garhiya",
    "ks:ks_pop":564,
    "ks:ks_type":"VILLAGE",
    "name:eng_x_preferred":[
        "Dhan Garhiya"
    ],
    "wof:name":"Dhan Garhiya",
    "wof:placetype":"locality",
    "wof:population":564
},
  "geometry": {"coordinates":[82.92406099999999,27.3668],"type":"Point"}
}