{
  "type": "Feature",
  "properties": {
    "iso:country":"IN",
    "ks:ks_name":"Manjha",
    "ks:ks_pop":328,
    "ks:ks_type":"HABITATION",
    "name:eng_x_preferred":[
        "Manjha"
    ],
    "wof:name":"Manjha",
    "wof:placetype":"locality",
    "wof:population":328
},
  "geometry": {"coordinates":[81.612803,27.024776],"type":"Point"}
}