{
  "type": "Feature",
  "properties": {
    "gn:admin1_code":"2",
    "gn:admin2_code":"544.0",
    "gn:asciiname":"Timmapuram",
    "gn:country_code":"IN",
    "gn:dem":93,
    "gn:feature_class":"P",
    "gn:feature_code":"PPL",
    "gn:name":"Timm\u0101puram",
    "gn:population":0,
    "gn:timezone":"Asia/Kolkata",
    "iso:country":"IN",
    "ks:ks_name":"Thimmapuram",
    "ks:ks_pop":204,
    "ks:ks_type":"HABITATION",
    "name:eng_x_preferred":[
        "Thimmapuram"
    ],
    "name:eng_x_variant":[
        "Timmapuram"
    ],
    "wof:name":"Thimmapuram",
    "wof:placetype":"locality",
    "wof:population":204
},
  "geometry": {"coordinates":[82.650347,17.531761],"type":"Point"}
}