{
  "type": "Feature",
  "properties": {
    "iso:country":"IN",
    "ks:ks_name":"Garadibettu",
    "ks:ks_pop":160,
    "ks:ks_type":"HABITATION",
    "name:eng_x_preferred":[
        "Garadibettu"
    ],
    "wof:name":"Garadibettu",
    "wof:placetype":"locality",
    "wof:population":160
},
  "geometry": {"coordinates":[74.79081100000001,13.389751],"type":"Point"}
}