{
  "type": "Feature",
  "properties": {
    "iso:country":"IN",
    "ks:ks_name":"Naldoba",
    "ks:ks_pop":1214,
    "ks:ks_type":"VILLAGE",
    "name:eng_x_preferred":[
        "Naldoba"
    ],
    "wof:name":"Naldoba",
    "wof:placetype":"locality",
    "wof:population":1214
},
  "geometry": {"coordinates":[90.446876,26.391996],"type":"Point"}
}