{
  "type": "Feature",
  "properties": {
    "gn:admin1_code":"21",
    "gn:admin2_code":"396.0",
    "gn:asciiname":"Pottasingi",
    "gn:country_code":"IN",
    "gn:dem":419,
    "gn:feature_class":"P",
    "gn:feature_code":"PPL",
    "gn:name":"Pott\u0101singi",
    "gn:population":0,
    "gn:timezone":"Asia/Kolkata",
    "iso:country":"IN",
    "name:und_x_variant":[
        "Pott\u0101singi",
        "Pott\u0101sing"
    ],
    "wof:name":"Pottasingi",
    "wof:placetype":"neighbourhood"
},
  "geometry": {"coordinates":[83.96075999999999,19.09083],"type":"Point"}
}