{
  "type": "Feature",
  "properties": {
    "gn:admin1_code":"19",
    "gn:admin2_code":"579.0",
    "gn:asciiname":"Ingalgi",
    "gn:country_code":"IN",
    "gn:dem":409,
    "gn:feature_class":"P",
    "gn:feature_code":"PPL",
    "gn:name":"Ingalgi",
    "gn:population":0,
    "gn:timezone":"Asia/Kolkata",
    "iso:country":"IN",
    "ks:ks_name":"Ingalgi",
    "ks:ks_type":"VILLAGE",
    "name:ceb_x_preferred":[
        "Ingalgi"
    ],
    "name:eng_x_preferred":[
        "Ingalgi"
    ],
    "name:swe_x_preferred":[
        "Ingalgi"
    ],
    "wof:name":"Ingalgi",
    "wof:placetype":"locality"
},
  "geometry": {"coordinates":[76.393198,17.130296],"type":"Point"}
}