{
  "type": "Feature",
  "properties": {
    "iso:country":"IN",
    "ks:ks_name":"Sibuttar",
    "ks:ks_pop":1761,
    "ks:ks_type":"VILLAGE",
    "name:eng_x_preferred":[
        "Sibuttar"
    ],
    "wof:name":"Sibuttar",
    "wof:placetype":"locality",
    "wof:population":1761
},
  "geometry": {"coordinates":[92.536768,24.726136],"type":"Point"}
}