{
  "type": "Feature",
  "properties": {
    "gn:admin1_code":"19.0",
    "gn:admin2_code":"558",
    "gn:asciiname":"Dongupura",
    "gn:country_code":"IN",
    "gn:dem":565,
    "gn:feature_class":"P",
    "gn:feature_code":"PPL",
    "gn:name":"Dongupura",
    "gn:population":0,
    "gn:timezone":"Asia/Kolkata",
    "iso:country":"IN",
    "wof:name":"Dongupura",
    "wof:placetype":"locality"
},
  "geometry": {"coordinates":[77.21849,18.12553],"type":"Point"}
}