{
  "type": "Feature",
  "properties": {
    "gn:admin1_code":"19.0",
    "gn:admin2_code":"584.0",
    "gn:asciiname":"Averhalli",
    "gn:country_code":"IN",
    "gn:dem":677,
    "gn:feature_class":"P",
    "gn:feature_code":"PPL",
    "gn:name":"Averhalli",
    "gn:population":0,
    "gn:timezone":"Asia/Kolkata",
    "iso:country":"IN",
    "wof:name":"Averhalli",
    "wof:placetype":"locality"
},
  "geometry": {"coordinates":[77.33714999999999,12.64813],"type":"Point"}
}