{
  "type": "Feature",
  "properties": {
    "gn:admin1_code":"19.0",
    "gn:admin2_code":"570.0",
    "gn:asciiname":"Nagarahalu",
    "gn:country_code":"IN",
    "gn:dem":771,
    "gn:feature_class":"P",
    "gn:feature_code":"PPL",
    "gn:name":"N\u0101gar\u0101halu",
    "gn:population":0,
    "gn:timezone":"Asia/Kolkata",
    "iso:country":"IN",
    "wof:name":"Nagarahalu",
    "wof:placetype":"locality"
},
  "geometry": {"coordinates":[76.05665999999999,13.41935],"type":"Point"}
}