{
  "type": "Feature",
  "properties": {
    "gn:admin1_code":"35.0",
    "gn:admin2_code":"420",
    "gn:asciiname":"Goli ka Pura",
    "gn:country_code":"IN",
    "gn:dem":131,
    "gn:feature_class":"P",
    "gn:feature_code":"PPL",
    "gn:name":"Goli ka Pura",
    "gn:population":0,
    "gn:timezone":"Asia/Kolkata",
    "iso:country":"IN",
    "wof:name":"Goli ka Pura",
    "wof:placetype":"locality"
},
  "geometry": {"coordinates":[79.10500999999999,26.41449],"type":"Point"}
}