{
  "type": "Feature",
  "properties": {
    "iso:country":"IN",
    "ks:ks_name":"Nov Tolia",
    "ks:ks_pop":300,
    "ks:ks_type":"HABITATION",
    "name:eng_x_preferred":[
        "Nov Tolia"
    ],
    "wof:name":"Nov Tolia",
    "wof:placetype":"locality",
    "wof:population":300
},
  "geometry": {"coordinates":[86.507272,25.726867],"type":"Point"}
}