{
  "type": "Feature",
  "properties": {
    "gn:admin1_code":"11.0",
    "gn:admin2_code":"26.0",
    "gn:asciiname":"Mahwi",
    "gn:country_code":"IN",
    "gn:dem":1499,
    "gn:feature_class":"P",
    "gn:feature_code":"PPL",
    "gn:name":"M\u0101hwi",
    "gn:population":0,
    "gn:timezone":"Asia/Kolkata",
    "iso:country":"IN",
    "name:ara_x_preferred":[
        "\u0645\u062d\u0648\u064a"
    ],
    "name:azb_x_preferred":[
        "\u0645\u062d\u0648\u06cc"
    ],
    "name:ckb_x_preferred":[
        "\u0645\u06d5\u062d\u0648\u06cc"
    ],
    "name:fas_x_preferred":[
        "\u0645\u062d\u0648\u06cc"
    ],
    "name:kur_x_preferred":[
        "Mehw\u00ee"
    ],
    "name:tur_x_preferred":[
        "Mahvi"
    ],
    "wof:name":"Mahwi",
    "wof:placetype":"locality"
},
  "geometry": {"coordinates":[77.67551999999998,31.48355],"type":"Point"}
}