{
  "type": "Feature",
  "properties": {
    "iso:country":"IN",
    "ks:ks_name":"Jojotoli",
    "ks:ks_pop":141,
    "ks:ks_type":"HABITATION",
    "name:eng_x_preferred":[
        "Jojotoli"
    ],
    "wof:name":"Jojotoli",
    "wof:placetype":"locality",
    "wof:population":141
},
  "geometry": {"coordinates":[84.60092400000001,22.552719],"type":"Point"}
}