{
  "type": "Feature",
  "properties": {
    "gn:admin1_code":"23.0",
    "gn:admin2_code":"45.0",
    "gn:asciiname":"Channian",
    "gn:country_code":"IN",
    "gn:dem":195,
    "gn:feature_class":"P",
    "gn:feature_code":"PPL",
    "gn:name":"Channi\u0101n",
    "gn:population":0,
    "gn:timezone":"Asia/Kolkata",
    "iso:country":"IN",
    "wof:name":"Channian",
    "wof:placetype":"locality"
},
  "geometry": {"coordinates":[74.58754999999999,30.77662],"type":"Point"}
}