{
  "type": "Feature",
  "properties": {
    "iso:country":"IN",
    "ks:ks_name":"Chigarekunte",
    "ks:ks_pop":87,
    "ks:ks_type":"HABITATION",
    "name:eng_x_preferred":[
        "Chigarekunte"
    ],
    "wof:name":"Chigarekunte",
    "wof:placetype":"locality",
    "wof:population":87
},
  "geometry": {"coordinates":[78.36362200000001,13.428342],"type":"Point"}
}