{
  "type": "Feature",
  "properties": {
    "iso:country":"IN",
    "ks:ks_name":"B. Meenakshipuram",
    "ks:ks_pop":7227,
    "ks:ks_type":"URBAN",
    "name:eng_x_preferred":[
        "B. Meenakshipuram"
    ],
    "wof:name":"B. Meenakshipuram",
    "wof:placetype":"locality",
    "wof:population":7227
},
  "geometry": {"coordinates":[77.407185,9.959556],"type":"Point"}
}