{
  "type": "Feature",
  "properties": {
    "iso:country":"IN",
    "ks:ks_name":"Muchiara",
    "ks:ks_pop":528,
    "ks:ks_type":"VILLAGE",
    "ks:ks_uagg_main":0,
    "name:eng_x_preferred":[
        "Muchiara"
    ],
    "wof:name":"Muchiara",
    "wof:placetype":"neighbourhood",
    "wof:population":528
},
  "geometry": {"coordinates":[87.61017099999999,23.777144],"type":"Point"}
}