{
  "type": "Feature",
  "properties": {
    "iso:country":"IN",
    "ks:ks_name":"Dangapara",
    "ks:ks_pop":1042,
    "ks:ks_type":"HABITATION",
    "name:eng_x_preferred":[
        "Dangapara"
    ],
    "wof:name":"Dangapara",
    "wof:placetype":"locality",
    "wof:population":1042
},
  "geometry": {"coordinates":[87.855582,23.553399],"type":"Point"}
}