{
  "type": "Feature",
  "properties": {
    "iso:country":"IN",
    "ks:ks_name":"Saliwadi",
    "ks:ks_pop":37,
    "ks:ks_type":"HABITATION",
    "name:eng_x_preferred":[
        "Saliwadi"
    ],
    "wof:name":"Saliwadi",
    "wof:placetype":"locality",
    "wof:population":37
},
  "geometry": {"coordinates":[73.35821900000001,17.514483],"type":"Point"}
}