{
  "type": "Feature",
  "properties": {
    "iso:country":"IN",
    "ks:ks_name":"Sutharanada",
    "ks:ks_pop":610,
    "ks:ks_type":"HABITATION",
    "name:eng_x_preferred":[
        "Sutharanada"
    ],
    "wof:name":"Sutharanada",
    "wof:placetype":"locality",
    "wof:population":610
},
  "geometry": {"coordinates":[72.94909199999999,27.320306],"type":"Point"}
}