{
  "type": "Feature",
  "properties": {
    "gn:country":"IN",
    "gn:fcode":"PPL",
    "gn:population":12008,
    "iso:country":"IN",
    "name:ben_x_preferred":[
        "\u09ac\u09be\u09b2\u09bf\u09ae\u09c7\u09b2\u09be"
    ],
    "name:bpy_x_preferred":[
        "\u09ac\u09be\u09b2\u09bf\u09ae\u09c7\u09b2\u09be"
    ],
    "name:ceb_x_preferred":[
        "B\u0101limela"
    ],
    "name:eng_x_preferred":[
        "Balimela"
    ],
    "name:fra_x_preferred":[
        "Balimela"
    ],
    "name:hin_x_preferred":[
        "\u092c\u093e\u0932\u093f\u092e\u0947\u0932\u093e"
    ],
    "name:ita_x_preferred":[
        "Balimela"
    ],
    "name:msa_x_preferred":[
        "Balimela"
    ],
    "name:nan_x_preferred":[
        "Balimela"
    ],
    "name:new_x_preferred":[
        "\u092c\u0932\u093f\u092e\u0947\u0932"
    ],
    "name:nld_x_preferred":[
        "Balimela"
    ],
    "name:ori_x_preferred":[
        "\u0b2c\u0b3e\u0b32\u0b3f\u0b2e\u0b47\u0b33\u0b3e"
    ],
    "name:por_x_preferred":[
        "Balimela"
    ],
    "name:swe_x_preferred":[
        "B\u0101limela"
    ],
    "name:und_x_variant":[
        "Balimila"
    ],
    "name:vie_x_preferred":[
        "Balimela"
    ],
    "name:zho_x_preferred":[
        "\u5df4\u5229\u6885\u62c9"
    ],
    "qs:name":"B\u0101limela",
    "qs:photos_9r":0,
    "qs:photos_sr":0,
    "qs:pop_sr":"6",
    "wd:wordcount":154,
    "wof:name":"B\u0101limela",
    "wof:placetype":"locality",
    "wof:population":12008
},
  "geometry": {"coordinates":[82.11091,18.2517],"type":"Point"}
}