{
  "type": "Feature",
  "properties": {
    "iso:country":"IN",
    "ks:ks_name":"Chingudiguda",
    "ks:ks_pop":147,
    "ks:ks_type":"HABITATION",
    "name:eng_x_preferred":[
        "Chingudiguda"
    ],
    "wof:name":"Chingudiguda",
    "wof:placetype":"locality",
    "wof:population":147
},
  "geometry": {"coordinates":[82.60618700000001,19.175847],"type":"Point"}
}