{
  "type": "Feature",
  "properties": {
    "gn:admin1_code":"9.0",
    "gn:admin2_code":"469.0",
    "gn:asciiname":"Magvas",
    "gn:country_code":"IN",
    "gn:dem":208,
    "gn:feature_class":"P",
    "gn:feature_code":"PPL",
    "gn:name":"Magv\u0101s",
    "gn:population":0,
    "gn:timezone":"Asia/Kolkata",
    "iso:country":"IN",
    "ks:ks_alt_nam":"Magv\u0101s",
    "ks:ks_name":"Magvas",
    "ks:ks_pop":1656,
    "ks:ks_type":"VILLAGE",
    "name:eng_x_preferred":[
        "Magvas"
    ],
    "name:eng_x_variant":[
        "Magv\u0101s"
    ],
    "wof:name":"Magvas",
    "wof:placetype":"locality",
    "wof:population":1656
},
  "geometry": {"coordinates":[72.959441,24.17362],"type":"Point"}
}