{
  "type": "Feature",
  "properties": {
    "iso:country":"IN",
    "ks:ks_name":"Subhashguda",
    "ks:ks_pop":24,
    "ks:ks_type":"HABITATION",
    "name:eng_x_preferred":[
        "Subhashguda"
    ],
    "wof:name":"Subhashguda",
    "wof:placetype":"locality",
    "wof:population":24
},
  "geometry": {"coordinates":[78.852914,19.429829],"type":"Point"}
}