{
  "type": "Feature",
  "properties": {
    "iso:country":"IN",
    "ks:ks_name":"Chikchika",
    "ks:ks_pop":64,
    "ks:ks_type":"VILLAGE",
    "name:eng_x_preferred":[
        "Chikchika"
    ],
    "wof:name":"Chikchika",
    "wof:placetype":"locality",
    "wof:population":64
},
  "geometry": {"coordinates":[86.965766,23.177284],"type":"Point"}
}