{
  "type": "Feature",
  "properties": {
    "iso:country":"IN",
    "ks:ks_name":"Krishnanagara",
    "ks:ks_pop":112,
    "ks:ks_type":"HABITATION",
    "name:eng_x_preferred":[
        "Krishnanagara"
    ],
    "wof:name":"Krishnanagara",
    "wof:placetype":"locality",
    "wof:population":112
},
  "geometry": {"coordinates":[77.357398,13.067383],"type":"Point"}
}