{
  "type": "Feature",
  "properties": {
    "gn:admin1_code":"2.0",
    "gn:admin2_code":"552.0",
    "gn:asciiname":"Bandi Metta",
    "gn:country_code":"IN",
    "gn:dem":399,
    "gn:feature_class":"P",
    "gn:feature_code":"PPL",
    "gn:name":"Bandi Metta",
    "gn:population":0,
    "gn:timezone":"Asia/Kolkata",
    "iso:country":"IN",
    "wof:name":"Bandi Metta",
    "wof:placetype":"locality"
},
  "geometry": {"coordinates":[78.18519999999999,15.55578],"type":"Point"}
}