{
  "type": "Feature",
  "properties": {
    "iso:country":"IN",
    "ks:ks_name":"Somaibasan",
    "ks:ks_pop":157,
    "ks:ks_type":"VILLAGE",
    "name:eng_x_preferred":[
        "Somaibasan"
    ],
    "wof:name":"Somaibasan",
    "wof:placetype":"locality",
    "wof:population":157
},
  "geometry": {"coordinates":[87.536445,21.631452],"type":"Point"}
}