{
  "type": "Feature",
  "properties": {
    "iso:country":"IN",
    "ks:ks_alt_nam":"R\u0101jdhar",
    "ks:ks_name":"Rajdhar",
    "ks:ks_pop":590,
    "ks:ks_type":"VILLAGE",
    "name:eng_x_preferred":[
        "Rajdhar"
    ],
    "name:eng_x_variant":[
        "R\u0101jdhar"
    ],
    "wof:name":"Rajdhar",
    "wof:placetype":"locality",
    "wof:population":590
},
  "geometry": {"coordinates":[85.033711,23.742272],"type":"Point"}
}