{
  "type": "Feature",
  "properties": {
    "iso:country":"IN",
    "ks:ks_name":"Mudariya Mu. Dubgawan",
    "ks:ks_pop":62,
    "ks:ks_type":"HABITATION",
    "name:eng_x_preferred":[
        "Mudariya Mu. Dubgawan"
    ],
    "wof:name":"Mudariya Mu. Dubgawan",
    "wof:placetype":"locality",
    "wof:population":62
},
  "geometry": {"coordinates":[81.841753,24.679817],"type":"Point"}
}