{
  "type": "Feature",
  "properties": {
    "iso:country":"IN",
    "ks:ks_name":"Boriche Tek",
    "ks:ks_pop":110,
    "ks:ks_type":"HABITATION",
    "name:eng_x_preferred":[
        "Boriche Tek"
    ],
    "wof:name":"Boriche Tek",
    "wof:placetype":"locality",
    "wof:population":110
},
  "geometry": {"coordinates":[74.448841,17.127916],"type":"Point"}
}