{
  "type": "Feature",
  "properties": {
    "iso:country":"IN",
    "ks:ks_alt_nam":"Abuk\u0101tu",
    "ks:ks_name":"Abukatu",
    "ks:ks_pop":253,
    "ks:ks_type":"VILLAGE",
    "name:eng_x_preferred":[
        "Abukatu"
    ],
    "name:eng_x_variant":[
        "Abuk\u0101tu"
    ],
    "wof:name":"Abukatu",
    "wof:placetype":"locality",
    "wof:population":253
},
  "geometry": {"coordinates":[84.931932,24.280756],"type":"Point"}
}