{
  "type": "Feature",
  "properties": {
    "iso:country":"IN",
    "ks:ks_name":"Chak Sadar",
    "ks:ks_pop":28,
    "ks:ks_type":"VILLAGE",
    "ks:ks_uagg_main":0,
    "name:eng_x_preferred":[
        "Chak Sadar"
    ],
    "wof:name":"Chak Sadar",
    "wof:placetype":"locality",
    "wof:population":28
},
  "geometry": {"coordinates":[83.603658,25.597478],"type":"Point"}
}