{
  "type": "Feature",
  "properties": {
    "iso:country":"IN",
    "ks:ks_name":"Jhikri",
    "ks:ks_pop":873,
    "ks:ks_type":"VILLAGE",
    "name:eng_x_preferred":[
        "Jhikri"
    ],
    "wof:name":"Jhikri",
    "wof:placetype":"locality",
    "wof:population":873
},
  "geometry": {"coordinates":[87.045433,22.929361],"type":"Point"}
}