{
  "type": "Feature",
  "properties": {
    "gn:admin1_code":"34.0",
    "gn:admin2_code":"217.0",
    "gn:asciiname":"Mura",
    "gn:country_code":"IN",
    "gn:dem":75,
    "gn:feature_class":"P",
    "gn:feature_code":"PPL",
    "gn:name":"M\u016bra",
    "gn:population":0,
    "gn:timezone":"Asia/Kolkata",
    "iso:country":"IN",
    "ks:ks_alt_nam":"M\u016bra",
    "ks:ks_name":"Mura",
    "ks:ks_pop":603,
    "ks:ks_type":"VILLAGE",
    "ks:ks_uagg_main":0,
    "name:bel_x_preferred":[
        "\u041c\u0443\u0440\u0430"
    ],
    "name:bul_x_preferred":[
        "\u041c\u0443\u0440\u0430"
    ],
    "name:ceb_x_preferred":[
        "Mura"
    ],
    "name:ces_x_preferred":[
        "Mura"
    ],
    "name:deu_x_preferred":[
        "Mura"
    ],
    "name:eng_x_preferred":[
        "Mura"
    ],
    "name:eng_x_variant":[
        "M\u016bra"
    ],
    "name:est_x_preferred":[
        "Mura"
    ],
    "name:eus_x_preferred":[
        "Mura"
    ],
    "name:fra_x_preferred":[
        "Mura"
    ],
    "name:hun_x_preferred":[
        "Mura"
    ],
    "name:ita_x_preferred":[
        "Mura"
    ],
    "name:msa_x_preferred":[
        "Mura"
    ],
    "name:nld_x_preferred":[
        "Mura"
    ],
    "name:pol_x_preferred":[
        "Mura"
    ],
    "name:por_x_preferred":[
        "Mura"
    ],
    "name:rus_x_preferred":[
        "\u041c\u0443\u0440\u0430"
    ],
    "name:sco_x_preferred":[
        "Mura"
    ],
    "name:slk_x_preferred":[
        "Mura"
    ],
    "name:slv_x_preferred":[
        "Mura"
    ],
    "name:spa_x_preferred":[
        "Mura"
    ],
    "name:srp_x_preferred":[
        "Mura"
    ],
    "name:swe_x_preferred":[
        "Mura"
    ],
    "name:tgl_x_preferred":[
        "Mura"
    ],
    "name:ukr_x_preferred":[
        "\u041c\u0443\u0440\u0430"
    ],
    "name:vie_x_preferred":[
        "Mura"
    ],
    "name:war_x_preferred":[
        "Mura"
    ],
    "wof:name":"Mura",
    "wof:placetype":"neighbourhood",
    "wof:population":603
},
  "geometry": {"coordinates":[84.244406,26.373084],"type":"Point"}
}