{
  "type": "Feature",
  "properties": {
    "iso:country":"IN",
    "ks:ks_alt_nam":"PURE MEHARBAAN",
    "ks:ks_name":"Pure Meharbaan",
    "ks:ks_pop":260,
    "ks:ks_type":"HABITATION",
    "name:eng_x_preferred":[
        "Pure Meharbaan"
    ],
    "wof:name":"Pure Meharbaan",
    "wof:placetype":"locality",
    "wof:population":260
},
  "geometry": {"coordinates":[81.376977,26.233898],"type":"Point"}
}