{
  "type": "Feature",
  "properties": {
    "iso:country":"IN",
    "ks:ks_name":"Shree Surpura",
    "ks:ks_pop":878,
    "ks:ks_type":"HABITATION",
    "name:eng_x_preferred":[
        "Shree Surpura"
    ],
    "wof:name":"Shree Surpura",
    "wof:placetype":"locality",
    "wof:population":878
},
  "geometry": {"coordinates":[72.524022,27.402286],"type":"Point"}
}