{
  "type": "Feature",
  "properties": {
    "iso:country":"IN",
    "ks:ks_alt_nam":"jagiriya",
    "ks:ks_name":"Jagiriya",
    "ks:ks_pop":247,
    "ks:ks_type":"HABITATION",
    "ks:ks_uagg_main":0,
    "name:eng_x_preferred":[
        "Jagiriya"
    ],
    "wof:name":"Jagiriya",
    "wof:placetype":"neighbourhood",
    "wof:population":247
},
  "geometry": {"coordinates":[82.97964399999999,25.437661],"type":"Point"}
}