{
  "type": "Feature",
  "properties": {
    "gn:admin1_code":"36",
    "gn:admin2_code":"180.0",
    "gn:asciiname":"Pura Matbar",
    "gn:country_code":"IN",
    "gn:dem":111,
    "gn:feature_class":"P",
    "gn:feature_code":"PPL",
    "gn:name":"Pura M\u0101tbar",
    "gn:population":0,
    "gn:timezone":"Asia/Kolkata",
    "iso:country":"IN",
    "wof:name":"Pura Matbar",
    "wof:placetype":"neighbourhood"
},
  "geometry": {"coordinates":[81.60853,27.29294],"type":"Point"}
}