{
  "type": "Feature",
  "properties": {
    "gn:admin1_code":"35.0",
    "gn:admin2_code":"465.0",
    "gn:asciiname":"Bhopalia",
    "gn:country_code":"IN",
    "gn:dem":308,
    "gn:feature_class":"P",
    "gn:feature_code":"PPL",
    "gn:name":"Bhop\u0101lia",
    "gn:population":0,
    "gn:timezone":"Asia/Kolkata",
    "iso:country":"IN",
    "wof:name":"Bhopalia",
    "wof:placetype":"locality"
},
  "geometry": {"coordinates":[74.19499,22.10146],"type":"Point"}
}