{
  "type": "Feature",
  "properties": {
    "iso:country":"IN",
    "ks:ks_name":"Chittivalasa",
    "ks:ks_pop":22,
    "ks:ks_type":"HABITATION",
    "name:eng_x_preferred":[
        "Chittivalasa"
    ],
    "wof:name":"Chittivalasa",
    "wof:placetype":"locality",
    "wof:population":22
},
  "geometry": {"coordinates":[82.842816,18.230846],"type":"Point"}
}