{
  "type": "Feature",
  "properties": {
    "gn:admin1_code":"35.0",
    "gn:admin2_code":"457.0",
    "gn:asciiname":"Pujaritola",
    "gn:country_code":"IN",
    "gn:dem":604,
    "gn:feature_class":"P",
    "gn:feature_code":"PPL",
    "gn:name":"Puj\u0101r\u012btol\u0101",
    "gn:population":0,
    "gn:timezone":"Asia/Kolkata",
    "iso:country":"IN",
    "wof:name":"Pujaritola",
    "wof:placetype":"locality"
},
  "geometry": {"coordinates":[80.48569999999999,21.8963],"type":"Point"}
}