{
  "type": "Feature",
  "properties": {
    "iso:country":"IN",
    "ks:ks_name":"Kangarusola",
    "ks:ks_pop":54,
    "ks:ks_type":"HABITATION",
    "name:eng_x_preferred":[
        "Kangarusola"
    ],
    "wof:name":"Kangarusola",
    "wof:placetype":"locality",
    "wof:population":54
},
  "geometry": {"coordinates":[82.80112699999999,18.371204],"type":"Point"}
}