{
  "type": "Feature",
  "properties": {
    "iso:country":"IN",
    "ks:ks_name":"Hattala",
    "ks:ks_pop":1356,
    "ks:ks_type":"HABITATION",
    "ks:ks_uagg_main":0,
    "name:eng_x_preferred":[
        "Hattala"
    ],
    "wof:name":"Hattala",
    "wof:placetype":"locality",
    "wof:population":1356
},
  "geometry": {"coordinates":[88.209766,22.792042],"type":"Point"}
}