{
  "type": "Feature",
  "properties": {
    "iso:country":"IN",
    "ks:ks_name":"Gurraonipally",
    "ks:ks_pop":207,
    "ks:ks_type":"HABITATION",
    "name:eng_x_preferred":[
        "Gurraonipally"
    ],
    "wof:name":"Gurraonipally",
    "wof:placetype":"locality",
    "wof:population":207
},
  "geometry": {"coordinates":[77.66864,16.262871],"type":"Point"}
}