{
  "type": "Feature",
  "properties": {
    "iso:country":"IN",
    "ks:ks_alt_nam":"KOLHE WASTI",
    "ks:ks_name":"Kolhe Wasti",
    "ks:ks_pop":110,
    "ks:ks_type":"HABITATION",
    "name:eng_x_preferred":[
        "Kolhe Wasti"
    ],
    "wof:name":"Kolhe Wasti",
    "wof:placetype":"locality",
    "wof:population":110
},
  "geometry": {"coordinates":[74.34704499999999,19.724643],"type":"Point"}
}