{
  "type": "Feature",
  "properties": {
    "iso:country":"IN",
    "ks:ks_name":"Pakhariya Sag",
    "ks:ks_pop":328,
    "ks:ks_type":"HABITATION",
    "name:eng_x_preferred":[
        "Pakhariya Sag"
    ],
    "wof:name":"Pakhariya Sag",
    "wof:placetype":"locality",
    "wof:population":328
},
  "geometry": {"coordinates":[74.307344,24.113992],"type":"Point"}
}