{
  "type": "Feature",
  "properties": {
    "iso:country":"IN",
    "ks:ks_name":"Srikrishnapur",
    "ks:ks_pop":932,
    "ks:ks_type":"HABITATION",
    "ks:ks_uagg_main":0,
    "name:eng_x_preferred":[
        "Srikrishnapur"
    ],
    "wof:name":"Srikrishnapur",
    "wof:placetype":"neighbourhood",
    "wof:population":932
},
  "geometry": {"coordinates":[88.230135,26.287678],"type":"Point"}
}