{
  "type": "Feature",
  "properties": {
    "iso:country":"IN",
    "ks:ks_name":"Sirampur",
    "ks:ks_pop":185,
    "ks:ks_type":"VILLAGE",
    "name:eng_x_preferred":[
        "Sirampur"
    ],
    "wof:name":"Sirampur",
    "wof:placetype":"locality",
    "wof:population":185
},
  "geometry": {"coordinates":[86.91466,24.500257],"type":"Point"}
}