{
  "type": "Feature",
  "properties": {
    "gn:admin1_code":"02",
    "gn:admin2_code":"553.0",
    "gn:asciiname":"Tanakallu",
    "gn:country_code":"IN",
    "gn:dem":611,
    "gn:feature_class":"P",
    "gn:feature_code":"PPL",
    "gn:name":"Tanakallu",
    "gn:population":0,
    "gn:timezone":"Asia/Kolkata",
    "iso:country":"IN",
    "wof:name":"Tanakallu",
    "wof:placetype":"locality"
},
  "geometry": {"coordinates":[78.19493,13.92002],"type":"Point"}
}