{
  "type": "Feature",
  "properties": {
    "iso:country":"IN",
    "ks:ks_alt_nam":"Sunabeda AC",
    "ks:ks_name":"Sunabeda Ac",
    "ks:ks_pop":422,
    "ks:ks_type":"HABITATION",
    "ks:ks_uagg_main":0,
    "name:eng_x_preferred":[
        "Sunabeda Ac"
    ],
    "wof:name":"Sunabeda Ac",
    "wof:placetype":"neighbourhood",
    "wof:population":422
},
  "geometry": {"coordinates":[82.25060999999999,19.718382],"type":"Point"}
}