{
  "type": "Feature",
  "properties": {
    "iso:country":"IN",
    "ks:ks_name":"Khokhri Khurd",
    "ks:ks_pop":145,
    "ks:ks_type":"VILLAGE",
    "name:eng_x_preferred":[
        "Khokhri Khurd"
    ],
    "wof:name":"Khokhri Khurd",
    "wof:placetype":"locality",
    "wof:population":145
},
  "geometry": {"coordinates":[74.28940299999999,24.118288],"type":"Point"}
}