{
  "type": "Feature",
  "properties": {
    "gn:admin1_code":"39.0",
    "gn:admin2_code":"061",
    "gn:asciiname":"Khalpari",
    "gn:country_code":"IN",
    "gn:dem":1178,
    "gn:feature_class":"P",
    "gn:feature_code":"PPL",
    "gn:name":"Khalp\u0101ri",
    "gn:population":0,
    "gn:timezone":"Asia/Kolkata",
    "iso:country":"IN",
    "ks:ks_alt_nam":"Khalp\u0101ri",
    "ks:ks_name":"Khalpari",
    "ks:ks_type":"VILLAGE",
    "name:eng_x_preferred":[
        "Khalpari"
    ],
    "name:eng_x_variant":[
        "Khalp\u0101ri"
    ],
    "wof:name":"Khalpari",
    "wof:placetype":"locality"
},
  "geometry": {"coordinates":[78.53337000000001,29.867824],"type":"Point"}
}