{
  "type": "Feature",
  "properties": {
    "iso:country":"IN",
    "ks:ks_name":"Grama Nandi Pur",
    "ks:ks_pop":1233,
    "ks:ks_type":"VILLAGE",
    "name:eng_x_preferred":[
        "Grama Nandi Pur"
    ],
    "wof:name":"Grama Nandi Pur",
    "wof:placetype":"locality",
    "wof:population":1233
},
  "geometry": {"coordinates":[86.436781,20.802725],"type":"Point"}
}