{
  "type": "Feature",
  "properties": {
    "iso:country":"IN",
    "ks:ks_name":"P Murain",
    "ks:ks_pop":125,
    "ks:ks_type":"HABITATION",
    "name:eng_x_preferred":[
        "P Murain"
    ],
    "wof:name":"P Murain",
    "wof:placetype":"locality",
    "wof:population":125
},
  "geometry": {"coordinates":[81.29647300000001,26.043545],"type":"Point"}
}