{
  "type": "Feature",
  "properties": {
    "iso:country":"IN",
    "ks:ks_name":"Paschim Mallikpur",
    "ks:ks_pop":944,
    "ks:ks_type":"VILLAGE",
    "name:eng_x_preferred":[
        "Paschim Mallikpur"
    ],
    "wof:name":"Paschim Mallikpur",
    "wof:placetype":"locality",
    "wof:population":944
},
  "geometry": {"coordinates":[88.07590500000001,22.821689],"type":"Point"}
}