{
  "type": "Feature",
  "properties": {
    "gn:admin1_code":"19.0",
    "gn:admin2_code":"582.0",
    "gn:asciiname":"Eguvabandlacheruvu",
    "gn:country_code":"IN",
    "gn:dem":719,
    "gn:feature_class":"P",
    "gn:feature_code":"PPL",
    "gn:name":"Eguvabandlacheruvu",
    "gn:population":0,
    "gn:timezone":"Asia/Kolkata",
    "iso:country":"IN",
    "wof:name":"Eguvabandlacheruvu",
    "wof:placetype":"locality"
},
  "geometry": {"coordinates":[77.7925,13.80834],"type":"Point"}
}