{
  "type": "Feature",
  "properties": {
    "iso:country":"IN",
    "ks:ks_name":"Bhuraguri",
    "ks:ks_pop":17,
    "ks:ks_type":"VILLAGE",
    "name:eng_x_preferred":[
        "Bhuraguri"
    ],
    "wof:name":"Bhuraguri",
    "wof:placetype":"locality",
    "wof:population":17
},
  "geometry": {"coordinates":[83.595169,19.753163],"type":"Point"}
}