{
  "type": "Feature",
  "properties": {
    "iso:country":"IN",
    "ks:ks_name":"Mudapada",
    "ks:ks_pop":41,
    "ks:ks_type":"HABITATION",
    "name:eng_x_preferred":[
        "Mudapada"
    ],
    "wof:name":"Mudapada",
    "wof:placetype":"locality",
    "wof:population":41
},
  "geometry": {"coordinates":[84.431687,22.251262],"type":"Point"}
}