{
  "type": "Feature",
  "properties": {
    "gn:admin1_code":"36",
    "gn:admin2_code":"159.0",
    "gn:asciiname":"Barti",
    "gn:country_code":"IN",
    "gn:dem":139,
    "gn:feature_class":"P",
    "gn:feature_code":"PPL",
    "gn:name":"Barti",
    "gn:population":0,
    "gn:timezone":"Asia/Kolkata",
    "iso:country":"IN",
    "ks:ks_name":"Barti",
    "ks:ks_type":"VILLAGE",
    "name:eng_x_preferred":[
        "Barti"
    ],
    "wof:name":"Barti",
    "wof:placetype":"locality"
},
  "geometry": {"coordinates":[79.68767800000001,27.314259],"type":"Point"}
}