{
  "type": "Feature",
  "properties": {
    "iso:country":"IN",
    "ks:ks_name":"Pratappura",
    "ks:ks_pop":1871,
    "ks:ks_type":"VILLAGE",
    "name:eng_x_preferred":[
        "Pratappura"
    ],
    "wof:name":"Pratappura",
    "wof:placetype":"locality",
    "wof:population":1871
},
  "geometry": {"coordinates":[71.784458,24.705561],"type":"Point"}
}