{
  "type": "Feature",
  "properties": {
    "iso:country":"IN",
    "ks:ks_name":"Kalkalwa",
    "ks:ks_pop":593,
    "ks:ks_type":"VILLAGE",
    "name:eng_x_preferred":[
        "Kalkalwa"
    ],
    "wof:name":"Kalkalwa",
    "wof:placetype":"locality",
    "wof:population":593
},
  "geometry": {"coordinates":[81.74923200000001,27.907995],"type":"Point"}
}