{
  "type": "Feature",
  "properties": {
    "gn:admin1_code":"25.0",
    "gn:admin2_code":"610.0",
    "gn:asciiname":"Minnuttipalaiyam",
    "gn:country_code":"IN",
    "gn:dem":203,
    "gn:feature_class":"P",
    "gn:feature_code":"PPL",
    "gn:name":"Minnuttip\u0101laiyam",
    "gn:population":0,
    "gn:timezone":"Asia/Kolkata",
    "iso:country":"IN",
    "wof:name":"Minnuttipalaiyam",
    "wof:placetype":"neighbourhood"
},
  "geometry": {"coordinates":[77.57232,11.41301],"type":"Point"}
}