{
  "type": "Feature",
  "properties": {
    "gn:admin1_code":"36",
    "gn:admin2_code":"156.0",
    "gn:asciiname":"Thar",
    "gn:country_code":"IN",
    "gn:dem":121,
    "gn:feature_class":"P",
    "gn:feature_code":"PPL",
    "gn:name":"Thar",
    "gn:population":0,
    "gn:timezone":"Asia/Kolkata",
    "iso:country":"IN",
    "name:ceb_x_preferred":[
        "Thar"
    ],
    "name:deu_x_preferred":[
        "Thar"
    ],
    "name:fra_x_preferred":[
        "Thar"
    ],
    "name:nld_x_preferred":[
        "Thar"
    ],
    "name:swe_x_preferred":[
        "Thar"
    ],
    "wof:name":"Thar",
    "wof:placetype":"locality"
},
  "geometry": {"coordinates":[80.77851,26.27756],"type":"Point"}
}