{
  "type": "Feature",
  "properties": {
    "gn:admin1_code":"11.0",
    "gn:admin2_code":"26.0",
    "gn:asciiname":"Charmatan",
    "gn:country_code":"IN",
    "gn:dem":2385,
    "gn:feature_class":"P",
    "gn:feature_code":"PPL",
    "gn:name":"Charm\u0101tan",
    "gn:population":0,
    "gn:timezone":"Asia/Kolkata",
    "iso:country":"IN",
    "wof:name":"Charmatan",
    "wof:placetype":"locality"
},
  "geometry": {"coordinates":[77.4308,31.49388],"type":"Point"}
}