{
  "type": "Feature",
  "properties": {
    "gn:admin1_code":"37.0",
    "gn:admin2_code":"407.0",
    "gn:asciiname":"Khamaria",
    "gn:country_code":"IN",
    "gn:dem":313,
    "gn:feature_class":"P",
    "gn:feature_code":"PPL",
    "gn:name":"Khamaria",
    "gn:population":0,
    "gn:timezone":"Asia/Kolkata",
    "iso:country":"IN",
    "name:eng_x_preferred":[
        "Khamaria"
    ],
    "wof:name":"Khamaria",
    "wof:placetype":"locality"
},
  "geometry": {"coordinates":[81.22305,21.72096],"type":"Point"}
}