{
  "type": "Feature",
  "properties": {
    "gn:admin1_code":"36",
    "gn:admin2_code":"164.0",
    "gn:asciiname":"Sachendi",
    "gn:country_code":"IN",
    "gn:dem":133,
    "gn:feature_class":"P",
    "gn:feature_code":"PPL",
    "gn:name":"Sachendi",
    "gn:population":0,
    "gn:timezone":"Asia/Kolkata",
    "iso:country":"IN",
    "name:ceb_x_preferred":[
        "Sachendi"
    ],
    "name:swe_x_preferred":[
        "Sachendi"
    ],
    "name:urd_x_preferred":[
        "\u0633\u0686\u0646\u062f\u06cc"
    ],
    "wof:name":"Sachendi",
    "wof:placetype":"locality"
},
  "geometry": {"coordinates":[80.16913000000002,26.42538],"type":"Point"}
}