{
  "type": "Feature",
  "properties": {
    "gn:admin1_code":"36.0",
    "gn:admin2_code":"150.0",
    "gn:asciiname":"Bhawanpur",
    "gn:country_code":"IN",
    "gn:dem":171,
    "gn:feature_class":"P",
    "gn:feature_code":"PPL",
    "gn:name":"Bhawanpur",
    "gn:population":0,
    "gn:timezone":"Asia/Kolkata",
    "iso:country":"IN",
    "name:und_x_variant":[
        "Niamatull\u0101hpur"
    ],
    "wof:name":"Bhawanpur",
    "wof:placetype":"neighbourhood"
},
  "geometry": {"coordinates":[79.57825,28.3163],"type":"Point"}
}