{
  "type": "Feature",
  "properties": {
    "iso:country":"IN",
    "ks:ks_name":"Dhindepada",
    "ks:ks_pop":56,
    "ks:ks_type":"HABITATION",
    "name:eng_x_preferred":[
        "Dhindepada"
    ],
    "wof:name":"Dhindepada",
    "wof:placetype":"locality",
    "wof:population":56
},
  "geometry": {"coordinates":[73.209523,19.840503],"type":"Point"}
}