{
  "type": "Feature",
  "properties": {
    "gn:admin1_code":"11.0",
    "gn:admin2_code":"32.0",
    "gn:asciiname":"Lohgarh",
    "gn:country_code":"IN",
    "gn:dem":447,
    "gn:feature_class":"P",
    "gn:feature_code":"PPL",
    "gn:name":"Lohgarh",
    "gn:population":0,
    "gn:timezone":"Asia/Kolkata",
    "iso:country":"IN",
    "name:fra_x_preferred":[
        "Lohgarh"
    ],
    "wof:name":"Lohgarh",
    "wof:placetype":"locality"
},
  "geometry": {"coordinates":[77.43316,30.45288],"type":"Point"}
}