{
  "type": "Feature",
  "properties": {
    "gn:admin1_code":"11.0",
    "gn:admin2_code":"32.0",
    "gn:asciiname":"Lohgarh",
    "gn:country_code":"IN",
    "gn:dem":447,
    "gn:feature_class":"P",
    "gn:feature_code":"PPL",
    "gn:name":"Lohgarh",
    "gn:population":0,
    "gn:timezone":"Asia/Kolkata",
    "iso:country":"IN",
    "name:ara_x_preferred":[
        "\u0644\u0648\u0647\u062c\u0627\u0631\u0647"
    ],
    "name:ben_bn_x_preferred":[
        "\u09b2\u09cb\u09b9\u0997\u09dc"
    ],
    "name:ben_in_x_preferred":[
        "\u09b2\u09cb\u09b9\u0997\u09dc"
    ],
    "name:fra_x_preferred":[
        "Lohgarh"
    ],
    "name:guj_x_preferred":[
        "\u0ab2\u0acb\u0ab9\u0a97\u0aa2"
    ],
    "name:hin_x_preferred":[
        "\u0932\u094b\u0939\u0917\u095d"
    ],
    "name:kan_x_preferred":[
        "\u0cb2\u0ccb\u0cb9\u0c97\u0ca2"
    ],
    "name:mal_x_preferred":[
        "\u0d32\u0d4b\u0d39\u0d4d\u0d17\u0d21\u0d4d"
    ],
    "name:mar_x_preferred":[
        "\u0932\u094b\u0939\u0917\u0921"
    ],
    "name:pan_x_preferred":[
        "\u0a32\u0a4b\u0a39\u0a17\u0a5c\u0a4d\u0a39"
    ],
    "name:tam_x_preferred":[
        "\u0bb2\u0bcb\u0bb9\u0bcd\u0b95\u0bb0\u0bcd"
    ],
    "name:tel_x_preferred":[
        "\u0c32\u0c4b\u0c17\u0c30\u0c4d"
    ],
    "name:urd_x_preferred":[
        "\u0644\u0648\u06c1 \u06af\u0691\u06be"
    ],
    "wof:name":"Lohgarh",
    "wof:placetype":"locality"
},
  "geometry": {"coordinates":[77.43316,30.45288],"type":"Point"}
}