{
  "type": "Feature",
  "properties": {
    "gn:admin1_code":"2.0",
    "gn:admin2_code":"554",
    "gn:asciiname":"Kalluru",
    "gn:country_code":"IN",
    "gn:dem":560,
    "gn:feature_class":"P",
    "gn:feature_code":"PPL",
    "gn:name":"Kall\u016bru",
    "gn:population":0,
    "gn:timezone":"Asia/Kolkata",
    "iso:country":"IN",
    "name:pam_x_preferred":[
        "Kalluru"
    ],
    "name:und_x_variant":[
        "Kallur",
        "Kall\u016bru"
    ],
    "wof:name":"Kalluru",
    "wof:placetype":"locality"
},
  "geometry": {"coordinates":[78.99923000000003,13.55819],"type":"Point"}
}