{
  "type": "Feature",
  "properties": {
    "iso:country":"IN",
    "ks:ks_name":"Lingayatwadi",
    "ks:ks_pop":156,
    "ks:ks_type":"HABITATION",
    "name:eng_x_preferred":[
        "Lingayatwadi"
    ],
    "wof:name":"Lingayatwadi",
    "wof:placetype":"locality",
    "wof:population":156
},
  "geometry": {"coordinates":[73.307829,16.852561],"type":"Point"}
}