{
  "type": "Feature",
  "properties": {
    "gn:admin1_code":"2.0",
    "gn:admin2_code":"549.0",
    "gn:asciiname":"Kambhaladinne",
    "gn:country_code":"IN",
    "gn:dem":69,
    "gn:feature_class":"P",
    "gn:feature_code":"PPL",
    "gn:name":"Kambh\u0101ladinne",
    "gn:population":0,
    "gn:timezone":"Asia/Kolkata",
    "iso:country":"IN",
    "wof:name":"Kambhaladinne",
    "wof:placetype":"locality"
},
  "geometry": {"coordinates":[79.544,15.04503],"type":"Point"}
}