{
  "type": "Feature",
  "properties": {
    "gn:admin1_code":"35.0",
    "gn:admin2_code":"421.0",
    "gn:asciiname":"Baupura Kalan",
    "gn:country_code":"IN",
    "gn:dem":228,
    "gn:feature_class":"P",
    "gn:feature_code":"PPL",
    "gn:name":"B\u0101\u016bpura Kal\u0101n",
    "gn:population":0,
    "gn:timezone":"Asia/Kolkata",
    "iso:country":"IN",
    "wof:name":"Baupura Kalan",
    "wof:placetype":"locality"
},
  "geometry": {"coordinates":[78.17551999999998,25.92284],"type":"Point"}
}