{
  "type": "Feature",
  "properties": {
    "iso:country":"IN",
    "ks:ks_name":"Machhondi",
    "ks:ks_pop":464,
    "ks:ks_type":"VILLAGE",
    "ks:ks_uagg_main":0,
    "name:eng_x_preferred":[
        "Machhondi"
    ],
    "wof:name":"Machhondi",
    "wof:placetype":"locality",
    "wof:population":464
},
  "geometry": {"coordinates":[76.832229,30.304145],"type":"Point"}
}