{
  "type": "Feature",
  "properties": {
    "iso:country":"IN",
    "ks:ks_name":"Jirat",
    "ks:ks_pop":3187,
    "ks:ks_type":"VILLAGE",
    "ks:ks_uagg_main":0,
    "name:eng_x_preferred":[
        "Jirat"
    ],
    "wof:name":"Jirat",
    "wof:placetype":"locality",
    "wof:population":3187
},
  "geometry": {"coordinates":[88.536019,22.756632],"type":"Point"}
}