{
  "type": "Feature",
  "properties": {
    "iso:country":"IN",
    "ks:ks_name":"Kumbharwadi",
    "ks:ks_pop":329,
    "ks:ks_type":"HABITATION",
    "name:eng_x_preferred":[
        "Kumbharwadi"
    ],
    "wof:name":"Kumbharwadi",
    "wof:placetype":"locality",
    "wof:population":329
},
  "geometry": {"coordinates":[73.76232,16.305181],"type":"Point"}
}