{
  "type": "Feature",
  "properties": {
    "iso:country":"IN",
    "ks:ks_name":"Karanjtoli",
    "ks:ks_pop":269,
    "ks:ks_type":"HABITATION",
    "name:eng_x_preferred":[
        "Karanjtoli"
    ],
    "wof:name":"Karanjtoli",
    "wof:placetype":"locality",
    "wof:population":269
},
  "geometry": {"coordinates":[85.105341,22.859044],"type":"Point"}
}