{
  "type": "Feature",
  "properties": {
    "iso:country":"IN",
    "ks:ks_name":"S I Honnalagere",
    "ks:ks_pop":3298,
    "ks:ks_type":"HABITATION",
    "name:eng_x_preferred":[
        "S I Honnalagere"
    ],
    "wof:name":"S I Honnalagere",
    "wof:placetype":"locality",
    "wof:population":3298
},
  "geometry": {"coordinates":[77.11453899999999,12.444084],"type":"Point"}
}