{
  "type": "Feature",
  "properties": {
    "iso:country":"IN",
    "ks:ks_name":"Diguva Harijanawada",
    "ks:ks_pop":87,
    "ks:ks_type":"HABITATION",
    "ks:ks_uagg_main":0,
    "name:eng_x_preferred":[
        "Diguva Harijanawada"
    ],
    "wof:name":"Diguva Harijanawada",
    "wof:placetype":"neighbourhood",
    "wof:population":87
},
  "geometry": {"coordinates":[78.61798,13.706573],"type":"Point"}
}