{
  "type": "Feature",
  "properties": {
    "iso:country":"IN",
    "ks:ks_name":"Zakhadeshvar",
    "ks:ks_pop":278,
    "ks:ks_type":"HABITATION",
    "name:eng_x_preferred":[
        "Zakhadeshvar"
    ],
    "wof:name":"Zakhadeshvar",
    "wof:placetype":"locality",
    "wof:population":278
},
  "geometry": {"coordinates":[72.313879,24.327975],"type":"Point"}
}