{
  "type": "Feature",
  "properties": {
    "iso:country":"IN",
    "ks:ks_name":"Jaminiwar",
    "ks:ks_pop":200,
    "ks:ks_type":"HABITATION",
    "name:eng_x_preferred":[
        "Jaminiwar"
    ],
    "wof:name":"Jaminiwar",
    "wof:placetype":"locality",
    "wof:population":200
},
  "geometry": {"coordinates":[79.349315,29.716946],"type":"Point"}
}