{
  "type": "Feature",
  "properties": {
    "iso:country":"IN",
    "ks:ks_name":"Turumamidi",
    "ks:ks_pop":39,
    "ks:ks_type":"VILLAGE",
    "name:eng_x_preferred":[
        "Turumamidi"
    ],
    "wof:name":"Turumamidi",
    "wof:placetype":"locality",
    "wof:population":39
},
  "geometry": {"coordinates":[82.31495099999999,18.024908],"type":"Point"}
}