{
  "type": "Feature",
  "properties": {
    "iso:country":"IN",
    "ks:ks_name":"Digipadi",
    "ks:ks_pop":81,
    "ks:ks_type":"VILLAGE",
    "name:eng_x_preferred":[
        "Digipadi"
    ],
    "wof:name":"Digipadi",
    "wof:placetype":"locality",
    "wof:population":81
},
  "geometry": {"coordinates":[83.858116,20.225913],"type":"Point"}
}