{
  "type": "Feature",
  "properties": {
    "iso:country":"IN",
    "ks:ks_name":"Barmaniya",
    "ks:ks_pop":674,
    "ks:ks_type":"VILLAGE",
    "name:eng_x_preferred":[
        "Barmaniya"
    ],
    "wof:name":"Barmaniya",
    "wof:placetype":"locality",
    "wof:population":674
},
  "geometry": {"coordinates":[87.017117,24.493368],"type":"Point"}
}