{
  "type": "Feature",
  "properties": {
    "iso:country":"IN",
    "ks:ks_name":"Despur",
    "ks:ks_pop":550,
    "ks:ks_type":"VILLAGE",
    "ks:ks_uagg_main":0,
    "name:eng_x_preferred":[
        "Despur"
    ],
    "wof:name":"Despur",
    "wof:placetype":"neighbourhood",
    "wof:population":550
},
  "geometry": {"coordinates":[86.291264,20.531528],"type":"Point"}
}