{
  "type": "Feature",
  "properties": {
    "iso:country":"IN",
    "ks:ks_name":"Darmoli",
    "ks:ks_pop":136,
    "ks:ks_type":"VILLAGE",
    "name:eng_x_preferred":[
        "Darmoli"
    ],
    "wof:name":"Darmoli",
    "wof:placetype":"locality",
    "wof:population":136
},
  "geometry": {"coordinates":[80.13928799999999,29.84263],"type":"Point"}
}