{
  "type": "Feature",
  "properties": {
    "iso:country":"IN",
    "ks:ks_name":"Paraspada",
    "ks:ks_pop":416,
    "ks:ks_type":"HABITATION",
    "name:eng_x_preferred":[
        "Paraspada"
    ],
    "wof:name":"Paraspada",
    "wof:placetype":"locality",
    "wof:population":416
},
  "geometry": {"coordinates":[72.82635000000001,20.151928],"type":"Point"}
}