{
  "type": "Feature",
  "properties": {
    "gn:admin1_code":"19.0",
    "gn:admin2_code":"581.0",
    "gn:asciiname":"Marrasandra",
    "gn:country_code":"IN",
    "gn:dem":795,
    "gn:feature_class":"P",
    "gn:feature_code":"PPL",
    "gn:name":"Marrasandra",
    "gn:population":0,
    "gn:timezone":"Asia/Kolkata",
    "iso:country":"IN",
    "wof:name":"Marrasandra",
    "wof:placetype":"locality"
},
  "geometry": {"coordinates":[78.336,13.05019],"type":"Point"}
}