{
  "type": "Feature",
  "properties": {
    "iso:country":"IN",
    "ks:ks_alt_nam":"RAJPUT TOLA",
    "ks:ks_name":"Rajput Tola",
    "ks:ks_pop":273,
    "ks:ks_type":"HABITATION",
    "name:eng_x_preferred":[
        "Rajput Tola"
    ],
    "wof:name":"Rajput Tola",
    "wof:placetype":"locality",
    "wof:population":273
},
  "geometry": {"coordinates":[86.09444000000001,25.03395],"type":"Point"}
}