{
  "type": "Feature",
  "properties": {
    "iso:country":"IN",
    "ks:ks_name":"Alubera",
    "ks:ks_pop":161,
    "ks:ks_type":"VILLAGE",
    "name:eng_x_preferred":[
        "Alubera"
    ],
    "wof:name":"Alubera",
    "wof:placetype":"locality",
    "wof:population":161
},
  "geometry": {"coordinates":[87.42578399999999,24.179941],"type":"Point"}
}