{
  "type": "Feature",
  "properties": {
    "gn:admin1_code":"12.0",
    "gn:admin2_code":"16.0",
    "gn:asciiname":"Sewa",
    "gn:country_code":"IN",
    "gn:dem":1024,
    "gn:feature_class":"P",
    "gn:feature_code":"PPL",
    "gn:name":"Sew\u0101",
    "gn:population":0,
    "gn:timezone":"Asia/Kolkata",
    "iso:country":"IN",
    "name:ceb_x_preferred":[
        "Sewa"
    ],
    "name:fra_x_preferred":[
        "Sewa"
    ],
    "name:swe_x_preferred":[
        "Sewa"
    ],
    "wof:name":"Sewa",
    "wof:placetype":"locality"
},
  "geometry": {"coordinates":[75.71146,33.1573],"type":"Point"}
}