{
  "type": "Feature",
  "properties": {
    "gn:admin1_code":"24.0",
    "gn:admin2_code":"127",
    "gn:asciiname":"Khatoli",
    "gn:country_code":"IN",
    "gn:dem":211,
    "gn:feature_class":"P",
    "gn:feature_code":"PPL",
    "gn:name":"Kh\u0101toli",
    "gn:population":0,
    "gn:timezone":"Asia/Kolkata",
    "iso:country":"IN",
    "wof:name":"Khatoli",
    "wof:placetype":"neighbourhood"
},
  "geometry": {"coordinates":[76.47562000000001,25.68098],"type":"Point"}
}