{
  "type": "Feature",
  "properties": {
    "gn:admin1_code":"13.0",
    "gn:admin2_code":"588.0",
    "gn:asciiname":"Kodibail",
    "gn:country_code":"IN",
    "gn:dem":29,
    "gn:feature_class":"P",
    "gn:feature_code":"PPLL",
    "gn:name":"K\u014ddibail",
    "gn:population":0,
    "gn:timezone":"Asia/Kolkata",
    "iso:country":"IN",
    "name:mal_x_preferred":[
        "\u0d15\u0d4b\u0d1f\u0d3f\u0d2c\u0d2f\u0d7d"
    ],
    "wof:name":"Kodibail",
    "wof:placetype":"locality"
},
  "geometry": {"coordinates":[74.91755000000001,12.67129],"type":"Point"}
}