{
  "type": "Feature",
  "properties": {
    "gn:admin1_code":"35",
    "gn:admin2_code":"460.0",
    "gn:asciiname":"Jurmani",
    "gn:country_code":"IN",
    "gn:dem":325,
    "gn:feature_class":"P",
    "gn:feature_code":"PPL",
    "gn:name":"Jurm\u0101ni",
    "gn:population":0,
    "gn:timezone":"Asia/Kolkata",
    "iso:country":"IN",
    "ks:ks_name":"Judmani",
    "ks:ks_pop":363,
    "ks:ks_type":"HABITATION",
    "name:eng_x_preferred":[
        "Judmani"
    ],
    "name:eng_x_variant":[
        "Jurmani"
    ],
    "wof:name":"Judmani",
    "wof:placetype":"locality",
    "wof:population":363
},
  "geometry": {"coordinates":[81.36821999999999,24.177966],"type":"Point"}
}