{
  "type": "Feature",
  "properties": {
    "iso:country":"IN",
    "ks:ks_name":"Hanumannagar",
    "ks:ks_pop":632,
    "ks:ks_type":"HABITATION",
    "name:eng_x_preferred":[
        "Hanumannagar"
    ],
    "wof:name":"Hanumannagar",
    "wof:placetype":"locality",
    "wof:population":632
},
  "geometry": {"coordinates":[72.08433100000001,27.488364],"type":"Point"}
}