{
  "type": "Feature",
  "properties": {
    "iso:country":"IN",
    "ks:ks_name":"Damor Faliya",
    "ks:ks_pop":205,
    "ks:ks_type":"HABITATION",
    "name:eng_x_preferred":[
        "Damor Faliya"
    ],
    "wof:name":"Damor Faliya",
    "wof:placetype":"locality",
    "wof:population":205
},
  "geometry": {"coordinates":[73.631,23.017889],"type":"Point"}
}