{
  "type": "Feature",
  "properties": {
    "iso:country":"IN",
    "ks:ks_alt_nam":"Line thanda",
    "ks:ks_name":"Line Thanda",
    "ks:ks_pop":38,
    "ks:ks_type":"HABITATION",
    "name:eng_x_preferred":[
        "Line Thanda"
    ],
    "wof:name":"Line Thanda",
    "wof:placetype":"locality",
    "wof:population":38
},
  "geometry": {"coordinates":[79.97996999999999,17.877003],"type":"Point"}
}