{
  "type": "Feature",
  "properties": {
    "iso:country":"IN",
    "ks:ks_name":"Lakshimigudi",
    "ks:ks_pop":400,
    "ks:ks_type":"VILLAGE",
    "ks:ks_uagg_main":0,
    "name:eng_x_preferred":[
        "Lakshimigudi"
    ],
    "wof:name":"Lakshimigudi",
    "wof:placetype":"neighbourhood",
    "wof:population":400
},
  "geometry": {"coordinates":[79.587824,11.336745],"type":"Point"}
}