{
  "type": "Feature",
  "properties": {
    "gn:admin1_code":"36",
    "gn:admin2_code":"188.0",
    "gn:asciiname":"Harpur",
    "gn:country_code":"IN",
    "gn:dem":84,
    "gn:feature_class":"P",
    "gn:feature_code":"PPL",
    "gn:name":"Harpur",
    "gn:population":0,
    "gn:timezone":"Asia/Kolkata",
    "iso:country":"IN",
    "name:new_x_preferred":[
        "\u0939\u0930\u094d\u092a\u0941\u0930"
    ],
    "wof:name":"Harpur",
    "wof:placetype":"locality"
},
  "geometry": {"coordinates":[83.14126,26.70026],"type":"Point"}
}