{
  "type": "Feature",
  "properties": {
    "iso:country":"IN",
    "ks:ks_name":"Parreda",
    "ks:ks_pop":237,
    "ks:ks_type":"HABITATION",
    "name:eng_x_preferred":[
        "Parreda"
    ],
    "wof:name":"Parreda",
    "wof:placetype":"locality",
    "wof:population":237
},
  "geometry": {"coordinates":[82.50004300000001,18.280985],"type":"Point"}
}