{
  "type": "Feature",
  "properties": {
    "gn:admin1_code":"34.0",
    "gn:admin2_code":"220.0",
    "gn:asciiname":"Gorgawan",
    "gn:country_code":"IN",
    "gn:dem":51,
    "gn:feature_class":"P",
    "gn:feature_code":"PPL",
    "gn:name":"Gorg\u0101w\u0101n",
    "gn:population":0,
    "gn:timezone":"Asia/Kolkata",
    "iso:country":"IN",
    "name:eng_x_preferred":[
        "Gorg\u0101w\u0101n"
    ],
    "wof:name":"Gorgawan",
    "wof:placetype":"locality"
},
  "geometry": {"coordinates":[85.52141999999998,25.64467],"type":"Point"}
}