{
  "type": "Feature",
  "properties": {
    "iso:country":"IN",
    "ks:ks_name":"Jaykrishnapur",
    "ks:ks_pop":615,
    "ks:ks_type":"VILLAGE",
    "ks:ks_uagg_main":0,
    "name:eng_x_preferred":[
        "Jaykrishnapur"
    ],
    "wof:name":"Jaykrishnapur",
    "wof:placetype":"neighbourhood",
    "wof:population":615
},
  "geometry": {"coordinates":[87.18646,22.642996],"type":"Point"}
}