{
  "type": "Feature",
  "properties": {
    "gn:admin1_code":"16.0",
    "gn:admin2_code":"505.0",
    "gn:asciiname":"Pohi",
    "gn:country_code":"IN",
    "gn:dem":369,
    "gn:feature_class":"P",
    "gn:feature_code":"PPL",
    "gn:name":"Pohi",
    "gn:population":0,
    "gn:timezone":"Asia/Kolkata",
    "iso:country":"IN",
    "wof:name":"Pohi",
    "wof:placetype":"neighbourhood"
},
  "geometry": {"coordinates":[78.81350999999999,21.23647],"type":"Point"}
}