{
  "type": "Feature",
  "properties": {
    "gn:admin1_code":"19.0",
    "gn:admin2_code":"575.0",
    "gn:asciiname":"Badakodi",
    "gn:country_code":"IN",
    "gn:dem":81,
    "gn:feature_class":"P",
    "gn:feature_code":"PPL",
    "gn:name":"Badakodi",
    "gn:population":0,
    "gn:timezone":"Asia/Kolkata",
    "iso:country":"IN",
    "ks:ks_name":"Badakodi",
    "ks:ks_pop":1270,
    "ks:ks_type":"VILLAGE",
    "name:eng_x_preferred":[
        "Badakodi"
    ],
    "wof:name":"Badakodi",
    "wof:placetype":"locality",
    "wof:population":1270
},
  "geometry": {"coordinates":[75.08883,13.049562],"type":"Point"}
}