{
  "type": "Feature",
  "properties": {
    "iso:country":"IN",
    "ks:ks_alt_nam":"Haduru thanda",
    "ks:ks_name":"Haduru Thanda",
    "ks:ks_pop":49,
    "ks:ks_type":"HABITATION",
    "name:eng_x_preferred":[
        "Haduru Thanda"
    ],
    "wof:name":"Haduru Thanda",
    "wof:placetype":"locality",
    "wof:population":49
},
  "geometry": {"coordinates":[79.578014,17.55014],"type":"Point"}
}