{
  "type": "Feature",
  "properties": {
    "iso:country":"IN",
    "ks:ks_name":"Singhani",
    "ks:ks_pop":12,
    "ks:ks_type":"HABITATION",
    "name:eng_x_preferred":[
        "Singhani"
    ],
    "wof:name":"Singhani",
    "wof:placetype":"locality",
    "wof:population":12
},
  "geometry": {"coordinates":[87.626897,25.179404],"type":"Point"}
}