{
  "type": "Feature",
  "properties": {
    "gn:admin1_code":"34.0",
    "gn:admin2_code":"235.0",
    "gn:asciiname":"Murarkhar",
    "gn:country_code":"IN",
    "gn:dem":159,
    "gn:feature_class":"P",
    "gn:feature_code":"PPL",
    "gn:name":"Mur\u0101rkh\u0101r",
    "gn:population":0,
    "gn:timezone":"Asia/Kolkata",
    "iso:country":"IN",
    "ks:ks_alt_nam":"Mur\u0101rkh\u0101r",
    "ks:ks_name":"Murarkhar",
    "ks:ks_type":"VILLAGE",
    "name:eng_x_preferred":[
        "Murarkhar"
    ],
    "name:eng_x_variant":[
        "Mur\u0101rkh\u0101r"
    ],
    "wof:name":"Murarkhar",
    "wof:placetype":"locality"
},
  "geometry": {"coordinates":[84.371961,24.562177],"type":"Point"}
}