{
  "type": "Feature",
  "properties": {
    "iso:country":"IN",
    "ks:ks_alt_nam":"Sing\u0101ra Reserve",
    "ks:ks_alt_nam_2":"Singara Reserve",
    "ks:ks_name":"Singara",
    "ks:ks_type":"VILLAGE",
    "name:eng_x_preferred":[
        "Singara"
    ],
    "name:eng_x_variant":[
        "Sing\u0101ra Reserve",
        "Singara Reserve"
    ],
    "wof:name":"Singara",
    "wof:placetype":"locality"
},
  "geometry": {"coordinates":[76.62503100000001,11.533166],"type":"Point"}
}