{
  "type": "Feature",
  "properties": {
    "iso:country":"IN",
    "ks:ks_name":"Ghanki",
    "ks:ks_pop":548,
    "ks:ks_type":"HABITATION",
    "name:eng_x_preferred":[
        "Ghanki"
    ],
    "wof:name":"Ghanki",
    "wof:placetype":"locality",
    "wof:population":548
},
  "geometry": {"coordinates":[85.837568,25.296877],"type":"Point"}
}