{
  "type": "Feature",
  "properties": {
    "gn:admin1_code":"35.0",
    "gn:admin2_code":"418",
    "gn:asciiname":"Goras",
    "gn:country_code":"IN",
    "gn:dem":390,
    "gn:feature_class":"P",
    "gn:feature_code":"PPL",
    "gn:name":"Goras",
    "gn:population":0,
    "gn:timezone":"Asia/Kolkata",
    "iso:country":"IN",
    "wof:name":"Goras",
    "wof:placetype":"locality"
},
  "geometry": {"coordinates":[76.94670000000001,25.53291],"type":"Point"}
}