{
  "type": "Feature",
  "properties": {
    "iso:country":"IN",
    "ks:ks_name":"Junapani",
    "ks:ks_pop":630,
    "ks:ks_type":"HABITATION",
    "name:eng_x_preferred":[
        "Junapani"
    ],
    "wof:name":"Junapani",
    "wof:placetype":"locality",
    "wof:population":630
},
  "geometry": {"coordinates":[74.694231,23.240192],"type":"Point"}
}