{
  "type": "Feature",
  "properties": {
    "iso:country":"IN",
    "ks:ks_name":"Hemmannu",
    "ks:ks_pop":180,
    "ks:ks_type":"HABITATION",
    "name:eng_x_preferred":[
        "Hemmannu"
    ],
    "wof:name":"Hemmannu",
    "wof:placetype":"locality",
    "wof:population":180
},
  "geometry": {"coordinates":[74.921024,13.606923],"type":"Point"}
}