{
  "type": "Feature",
  "properties": {
    "iso:country":"IN",
    "ks:ks_name":"Yeguvaballeru",
    "ks:ks_pop":80,
    "ks:ks_type":"HABITATION",
    "name:eng_x_preferred":[
        "Yeguvaballeru"
    ],
    "wof:name":"Yeguvaballeru",
    "wof:placetype":"locality",
    "wof:population":80
},
  "geometry": {"coordinates":[83.76834100000001,18.860152],"type":"Point"}
}