{
  "type": "Feature",
  "properties": {
    "iso:country":"IN",
    "ks:ks_name":"Bommalata Dinne",
    "ks:ks_pop":100,
    "ks:ks_type":"HABITATION",
    "name:eng_x_preferred":[
        "Bommalata Dinne"
    ],
    "wof:name":"Bommalata Dinne",
    "wof:placetype":"locality",
    "wof:population":100
},
  "geometry": {"coordinates":[77.606095,13.544824],"type":"Point"}
}