{
  "type": "Feature",
  "properties": {
    "iso:country":"IN",
    "ks:ks_name":"Voddarahatty",
    "ks:ks_pop":244,
    "ks:ks_type":"HABITATION",
    "name:eng_x_preferred":[
        "Voddarahatty"
    ],
    "wof:name":"Voddarahatty",
    "wof:placetype":"locality",
    "wof:population":244
},
  "geometry": {"coordinates":[77.00167500000001,13.567098],"type":"Point"}
}