{
  "type": "Feature",
  "properties": {
    "gn:admin1_code":"34.0",
    "gn:admin2_code":"237.0",
    "gn:asciiname":"Rampur Dhorhan",
    "gn:country_code":"IN",
    "gn:dem":109,
    "gn:feature_class":"P",
    "gn:feature_code":"PPL",
    "gn:name":"R\u0101mpur Dhorhan",
    "gn:population":0,
    "gn:timezone":"Asia/Kolkata",
    "iso:country":"IN",
    "ks:ks_name":"Rampur Dhorhan",
    "ks:ks_pop":1031,
    "ks:ks_type":"VILLAGE",
    "name:eng_x_preferred":[
        "Rampur Dhorhan"
    ],
    "wof:name":"Rampur Dhorhan",
    "wof:placetype":"locality",
    "wof:population":1031
},
  "geometry": {"coordinates":[85.446234,24.791508],"type":"Point"}
}