{
  "type": "Feature",
  "properties": {
    "iso:country":"IN",
    "ks:ks_alt_nam":"kherbari",
    "ks:ks_name":"Kherbari",
    "ks:ks_pop":29,
    "ks:ks_type":"HABITATION",
    "name:eng_x_preferred":[
        "Kherbari"
    ],
    "wof:name":"Kherbari",
    "wof:placetype":"locality",
    "wof:population":29
},
  "geometry": {"coordinates":[93.17958,25.255001],"type":"Point"}
}