{
  "type": "Feature",
  "properties": {
    "gn:admin1_code":"19.0",
    "gn:admin2_code":"582.0",
    "gn:asciiname":"Dodda Gummanahalli",
    "gn:country_code":"IN",
    "gn:dem":855,
    "gn:feature_class":"P",
    "gn:feature_code":"PPL",
    "gn:name":"Dodda Gummanahalli",
    "gn:population":0,
    "gn:timezone":"Asia/Kolkata",
    "iso:country":"IN",
    "ks:ks_name":"Doddagummanahalli",
    "ks:ks_pop":432,
    "ks:ks_type":"VILLAGE",
    "name:eng_x_preferred":[
        "Doddagummanahalli"
    ],
    "name:eng_x_variant":[
        "Dodda Gummanahalli"
    ],
    "wof:name":"Doddagummanahalli",
    "wof:placetype":"locality",
    "wof:population":432
},
  "geometry": {"coordinates":[77.84139500000001,13.528216],"type":"Point"}
}