{
  "type": "Feature",
  "properties": {
    "iso:country":"IN",
    "ks:ks_name":"Abua",
    "ks:ks_pop":1440,
    "ks:ks_type":"VILLAGE",
    "ks:ks_uagg_main":0,
    "name:eng_x_preferred":[
        "Abua"
    ],
    "wof:name":"Abua",
    "wof:placetype":"neighbourhood",
    "wof:population":1440
},
  "geometry": {"coordinates":[88.54666,22.560381],"type":"Point"}
}