{
  "type": "Feature",
  "properties": {
    "iso:country":"IN",
    "ks:ks_alt_nam":"Anand nagar",
    "ks:ks_name":"Anand Nagar",
    "ks:ks_pop":230,
    "ks:ks_type":"HABITATION",
    "name:eng_x_preferred":[
        "Anand Nagar"
    ],
    "wof:name":"Anand Nagar",
    "wof:placetype":"locality",
    "wof:population":230
},
  "geometry": {"coordinates":[73.074055,18.651907],"type":"Point"}
}