{
  "type": "Feature",
  "properties": {
    "gn:admin1_code":"35",
    "gn:admin2_code":"462.0",
    "gn:asciiname":"Dadar",
    "gn:country_code":"IN",
    "gn:dem":384,
    "gn:feature_class":"P",
    "gn:feature_code":"PPL",
    "gn:name":"D\u0101dar",
    "gn:population":0,
    "gn:timezone":"Asia/Kolkata",
    "iso:country":"IN",
    "name:hin_x_preferred":[
        "\u0926\u093e\u0926\u0930"
    ],
    "name:mar_x_preferred":[
        "\u0926\u093e\u0926\u0930"
    ],
    "name:pan_x_preferred":[
        "\u0a26\u0a3e\u0a26\u0a30"
    ],
    "name:urd_x_preferred":[
        "\u062f\u0627\u062f\u0631"
    ],
    "wof:name":"Dadar",
    "wof:placetype":"locality"
},
  "geometry": {"coordinates":[81.85394000000002,24.07259],"type":"Point"}
}