{
  "type": "Feature",
  "properties": {
    "gn:admin1_code":"19.0",
    "gn:admin2_code":"571.0",
    "gn:asciiname":"Miselimmanahalli",
    "gn:country_code":"IN",
    "gn:dem":826,
    "gn:feature_class":"P",
    "gn:feature_code":"PPL",
    "gn:name":"M\u012bselimmanahalli",
    "gn:population":0,
    "gn:timezone":"Asia/Kolkata",
    "iso:country":"IN",
    "wof:name":"Miselimmanahalli",
    "wof:placetype":"locality"
},
  "geometry": {"coordinates":[76.48163000000002,13.30617],"type":"Point"}
}