{
  "type": "Feature",
  "properties": {
    "iso:country":"IN",
    "ks:ks_name":"Purusankulam",
    "ks:ks_pop":275,
    "ks:ks_type":"HABITATION",
    "name:eng_x_preferred":[
        "Purusankulam"
    ],
    "wof:name":"Purusankulam",
    "wof:placetype":"locality",
    "wof:population":275
},
  "geometry": {"coordinates":[78.499577,9.23175],"type":"Point"}
}