{
  "type": "Feature",
  "properties": {
    "iso:country":"IN",
    "ks:ks_name":"Khamhariya Mal.",
    "ks:ks_pop":657,
    "ks:ks_type":"VILLAGE",
    "name:eng_x_preferred":[
        "Khamhariya Mal."
    ],
    "wof:name":"Khamhariya Mal.",
    "wof:placetype":"locality",
    "wof:population":657
},
  "geometry": {"coordinates":[80.842974,23.023227],"type":"Point"}
}