{
  "type": "Feature",
  "properties": {
    "iso:country":"IN",
    "ks:ks_name":"Madhnagar",
    "ks:ks_pop":477,
    "ks:ks_type":"HABITATION",
    "name:eng_x_preferred":[
        "Madhnagar"
    ],
    "wof:name":"Madhnagar",
    "wof:placetype":"locality",
    "wof:population":477
},
  "geometry": {"coordinates":[81.707245,27.747353],"type":"Point"}
}