{
  "type": "Feature",
  "properties": {
    "gn:admin1_code":"24.0",
    "gn:admin2_code":"127.0",
    "gn:asciiname":"Bhattipura",
    "gn:country_code":"IN",
    "gn:dem":251,
    "gn:feature_class":"P",
    "gn:feature_code":"PPL",
    "gn:name":"Bhatt\u012bpura",
    "gn:population":0,
    "gn:timezone":"Asia/Kolkata",
    "iso:country":"IN",
    "wof:name":"Bhattipura",
    "wof:placetype":"locality"
},
  "geometry": {"coordinates":[76.18451999999998,25.12925],"type":"Point"}
}