{
  "type": "Feature",
  "properties": {
    "gn:admin1_code":"36.0",
    "gn:admin2_code":"192.0",
    "gn:asciiname":"Hankaripur",
    "gn:country_code":"IN",
    "gn:dem":74,
    "gn:feature_class":"P",
    "gn:feature_code":"PPL",
    "gn:name":"Hankaripur",
    "gn:population":0,
    "gn:timezone":"Asia/Kolkata",
    "iso:country":"IN",
    "wof:name":"Hankaripur",
    "wof:placetype":"locality"
},
  "geometry": {"coordinates":[83.66656999999999,26.10928],"type":"Point"}
}