{
  "type": "Feature",
  "properties": {
    "gn:admin1_code":"36",
    "gn:admin2_code":"175.0",
    "gn:asciiname":"Lokapur",
    "gn:country_code":"IN",
    "gn:dem":99,
    "gn:feature_class":"P",
    "gn:feature_code":"PPL",
    "gn:name":"Lok\u0101pur",
    "gn:population":0,
    "gn:timezone":"Asia/Kolkata",
    "iso:country":"IN",
    "name:ceb_x_preferred":[
        "Lok\u0101pur"
    ],
    "name:swe_x_preferred":[
        "Lok\u0101pur"
    ],
    "wof:name":"Lokapur",
    "wof:placetype":"locality"
},
  "geometry": {"coordinates":[82.02558000000001,25.67126],"type":"Point"}
}