{
  "type": "Feature",
  "properties": {
    "gn:admin1_code":"39.0",
    "gn:admin2_code":"64.0",
    "gn:asciiname":"Milgaon",
    "gn:country_code":"IN",
    "gn:dem":1358,
    "gn:feature_class":"P",
    "gn:feature_code":"PPL",
    "gn:name":"Milgaon",
    "gn:population":0,
    "gn:timezone":"Asia/Kolkata",
    "iso:country":"IN",
    "ks:ks_name":"Mel Gaon",
    "ks:ks_pop":192,
    "ks:ks_type":"VILLAGE",
    "name:eng_x_preferred":[
        "Mel Gaon"
    ],
    "name:eng_x_variant":[
        "Milgaon"
    ],
    "wof:name":"Mel Gaon",
    "wof:placetype":"locality",
    "wof:population":192
},
  "geometry": {"coordinates":[79.953543,29.58035],"type":"Point"}
}