{
  "type": "Feature",
  "properties": {
    "iso:country":"IN",
    "ks:ks_alt_nam":"Enn\u0101kuracheri",
    "ks:ks_name":"Ennakuracheri",
    "ks:ks_type":"VILLAGE",
    "name:eng_x_preferred":[
        "Ennakuracheri"
    ],
    "name:eng_x_variant":[
        "Enn\u0101kuracheri"
    ],
    "wof:name":"Ennakuracheri",
    "wof:placetype":"locality"
},
  "geometry": {"coordinates":[80.26462100000001,13.378317],"type":"Point"}
}