{
  "type": "Feature",
  "properties": {
    "gn:admin1_code":"10.0",
    "gn:admin2_code":"69.0",
    "gn:asciiname":"Ambawa",
    "gn:country_code":"IN",
    "gn:dem":587,
    "gn:feature_class":"P",
    "gn:feature_code":"PPL",
    "gn:name":"Ambawa",
    "gn:population":0,
    "gn:timezone":"Asia/Kolkata",
    "iso:country":"IN",
    "name:ceb_x_preferred":[
        "Ambawa"
    ],
    "name:fas_x_preferred":[
        "\u0627\u0645\u0628\u0627\u0648\u0627"
    ],
    "name:swe_x_preferred":[
        "Ambawa"
    ],
    "wof:name":"Ambawa",
    "wof:placetype":"locality"
},
  "geometry": {"coordinates":[77.03094,30.70123],"type":"Point"}
}