{
  "type": "Feature",
  "properties": {
    "iso:country":"IN",
    "ks:ks_name":"Bhumitala",
    "ks:ks_pop":778,
    "ks:ks_type":"VILLAGE",
    "ks:ks_uagg_main":0,
    "name:eng_x_preferred":[
        "Bhumitala"
    ],
    "wof:name":"Bhumitala",
    "wof:placetype":"neighbourhood",
    "wof:population":778
},
  "geometry": {"coordinates":[88.817408,22.848422],"type":"Point"}
}