{
  "type": "Feature",
  "properties": {
    "iso:country":"IN",
    "ks:ks_name":"Pallinada",
    "ks:ks_pop":392,
    "ks:ks_type":"HABITATION",
    "name:eng_x_preferred":[
        "Pallinada"
    ],
    "wof:name":"Pallinada",
    "wof:placetype":"locality",
    "wof:population":392
},
  "geometry": {"coordinates":[76.218036,10.32433],"type":"Point"}
}