{
  "type": "Feature",
  "properties": {
    "iso:country":"IN",
    "ks:ks_name":"Bedobedkot",
    "ks:ks_pop":10,
    "ks:ks_type":"HABITATION",
    "name:eng_x_preferred":[
        "Bedobedkot"
    ],
    "wof:name":"Bedobedkot",
    "wof:placetype":"locality",
    "wof:population":10
},
  "geometry": {"coordinates":[80.949943,19.710358],"type":"Point"}
}