{
  "type": "Feature",
  "properties": {
    "gn:admin1_code":"36.0",
    "gn:admin2_code":"189.0",
    "gn:asciiname":"Parsauna",
    "gn:country_code":"IN",
    "gn:dem":85,
    "gn:feature_class":"P",
    "gn:feature_code":"PPL",
    "gn:name":"Parsauna",
    "gn:population":0,
    "gn:timezone":"Asia/Kolkata",
    "iso:country":"IN",
    "wof:name":"Parsauna",
    "wof:placetype":"locality"
},
  "geometry": {"coordinates":[83.8265,26.84074],"type":"Point"}
}