{
  "type": "Feature",
  "properties": {
    "gn:admin1_code":"23",
    "gn:admin2_code":"36.0",
    "gn:asciiname":"Sarai Jattan",
    "gn:country_code":"IN",
    "gn:dem":242,
    "gn:feature_class":"P",
    "gn:feature_code":"PPL",
    "gn:name":"Sarai Jatt\u0101n",
    "gn:population":0,
    "gn:timezone":"Asia/Kolkata",
    "iso:country":"IN",
    "wof:name":"Sarai Jattan",
    "wof:placetype":"neighbourhood"
},
  "geometry": {"coordinates":[75.72198,31.17667],"type":"Point"}
}