{
  "type": "Feature",
  "properties": {
    "iso:country":"IN",
    "ks:ks_alt_nam":"SHIKARPUR",
    "ks:ks_name":"Shikarpur",
    "ks:ks_pop":513,
    "ks:ks_type":"HABITATION",
    "ks:ks_uagg_main":0,
    "name:eng_x_preferred":[
        "Shikarpur"
    ],
    "wof:name":"Shikarpur",
    "wof:placetype":"neighbourhood",
    "wof:population":513
},
  "geometry": {"coordinates":[88.58973899999999,26.599851],"type":"Point"}
}