{
  "type": "Feature",
  "properties": {
    "iso:country":"IN",
    "ks:ks_name":"Adavaisamypuram",
    "ks:ks_pop":441,
    "ks:ks_type":"HABITATION",
    "ks:ks_uagg_main":0,
    "name:eng_x_preferred":[
        "Adavaisamypuram"
    ],
    "wof:name":"Adavaisamypuram",
    "wof:placetype":"neighbourhood",
    "wof:population":441
},
  "geometry": {"coordinates":[77.801711,12.578754],"type":"Point"}
}