{
  "type": "Feature",
  "properties": {
    "gn:admin1_code":"21.0",
    "gn:admin2_code":"396.0",
    "gn:asciiname":"Duruguda",
    "gn:country_code":"IN",
    "gn:dem":326,
    "gn:feature_class":"P",
    "gn:feature_code":"PPL",
    "gn:name":"Duruguda",
    "gn:population":0,
    "gn:timezone":"Asia/Kolkata",
    "iso:country":"IN",
    "ks:ks_name":"Duriguda",
    "ks:ks_pop":132,
    "ks:ks_type":"VILLAGE",
    "name:eng_x_preferred":[
        "Duriguda"
    ],
    "name:eng_x_variant":[
        "Duruguda"
    ],
    "wof:name":"Duriguda",
    "wof:placetype":"locality",
    "wof:population":132
},
  "geometry": {"coordinates":[83.914011,19.236906],"type":"Point"}
}