{
  "type": "Feature",
  "properties": {
    "iso:country":"IN",
    "ks:ks_name":"Warud",
    "ks:ks_pop":265,
    "ks:ks_type":"VILLAGE",
    "name:eng_x_preferred":[
        "Warud"
    ],
    "wof:name":"Warud",
    "wof:placetype":"locality",
    "wof:population":265
},
  "geometry": {"coordinates":[78.246557,20.68297],"type":"Point"}
}