{
  "type": "Feature",
  "properties": {
    "iso:country":"IN",
    "ks:ks_alt_nam":"Dakhin Kekerikuchi supa",
    "ks:ks_name":"Dakhin Kekerikuchi Supa",
    "ks:ks_pop":231,
    "ks:ks_type":"HABITATION",
    "name:eng_x_preferred":[
        "Dakhin Kekerikuchi Supa"
    ],
    "wof:name":"Dakhin Kekerikuchi Supa",
    "wof:placetype":"locality",
    "wof:population":231
},
  "geometry": {"coordinates":[91.593659,26.58024],"type":"Point"}
}