{
  "type": "Feature",
  "properties": {
    "gn:admin1_code":"37.0",
    "gn:admin2_code":"404.0",
    "gn:asciiname":"Ajgarbahar",
    "gn:country_code":"IN",
    "gn:dem":335,
    "gn:feature_class":"P",
    "gn:feature_code":"PPL",
    "gn:name":"Ajgarbahar",
    "gn:population":0,
    "gn:timezone":"Asia/Kolkata",
    "iso:country":"IN",
    "wof:name":"Ajgarbahar",
    "wof:placetype":"locality"
},
  "geometry": {"coordinates":[82.70909,22.52186],"type":"Point"}
}