{
  "type": "Feature",
  "properties": {
    "gn:admin1_code":"37.0",
    "gn:admin2_code":"404.0",
    "gn:asciiname":"Ajgarbahar",
    "gn:country_code":"IN",
    "gn:dem":335,
    "gn:feature_class":"P",
    "gn:feature_code":"PPL",
    "gn:name":"Ajgarbahar",
    "gn:population":0,
    "gn:timezone":"Asia/Kolkata",
    "iso:country":"IN",
    "ks:ks_alt_nam":"Ajgarbah\u0101r",
    "ks:ks_name":"Ajgarbahar",
    "ks:ks_type":"VILLAGE",
    "name:eng_x_preferred":[
        "Ajgarbahar"
    ],
    "name:eng_x_variant":[
        "Ajgarbah\u0101r"
    ],
    "wof:name":"Ajgarbahar",
    "wof:placetype":"locality"
},
  "geometry": {"coordinates":[82.71159400000001,22.520065],"type":"Point"}
}