{
  "type": "Feature",
  "properties": {
    "iso:country":"IN",
    "ks:ks_name":"Chilkapand",
    "ks:ks_pop":6662,
    "ks:ks_type":"HABITATION",
    "name:eng_x_preferred":[
        "Chilkapand"
    ],
    "wof:name":"Chilkapand",
    "wof:placetype":"locality",
    "wof:population":6662
},
  "geometry": {"coordinates":[82.799278,24.135018],"type":"Point"}
}