{
  "type": "Feature",
  "properties": {
    "iso:country":"IN",
    "ks:ks_name":"Myasarahatty Talavarahally",
    "ks:ks_pop":469,
    "ks:ks_type":"HABITATION",
    "name:eng_x_preferred":[
        "Myasarahatty Talavarahally"
    ],
    "wof:name":"Myasarahatty Talavarahally",
    "wof:placetype":"locality",
    "wof:population":469
},
  "geometry": {"coordinates":[76.675119,14.786941],"type":"Point"}
}