{
  "type": "Feature",
  "properties": {
    "iso:country":"IN",
    "ks:ks_name":"Khaprail Chak",
    "ks:ks_type":"VILLAGE",
    "ks:ks_uagg_main":0,
    "name:eng_x_preferred":[
        "Khaprail Chak"
    ],
    "wof:name":"Khaprail Chak",
    "wof:placetype":"neighbourhood"
},
  "geometry": {"coordinates":[85.116978,25.54766],"type":"Point"}
}