{
  "type": "Feature",
  "properties": {
    "iso:country":"IN",
    "ks:ks_name":"Pala Bagar",
    "ks:ks_pop":16,
    "ks:ks_type":"HABITATION",
    "name:eng_x_preferred":[
        "Pala Bagar"
    ],
    "wof:name":"Pala Bagar",
    "wof:placetype":"locality",
    "wof:population":16
},
  "geometry": {"coordinates":[79.398397,29.95683],"type":"Point"}
}