{
  "type": "Feature",
  "properties": {
    "gn:admin1_code":"19.0",
    "gn:admin2_code":"555.0",
    "gn:asciiname":"Sangal",
    "gn:country_code":"IN",
    "gn:dem":556,
    "gn:feature_class":"P",
    "gn:feature_code":"PPL",
    "gn:name":"Sangal",
    "gn:population":0,
    "gn:timezone":"Asia/Kolkata",
    "iso:country":"IN",
    "wof:name":"Sangal",
    "wof:placetype":"locality"
},
  "geometry": {"coordinates":[75.43557,15.88847],"type":"Point"}
}