{
  "type": "Feature",
  "properties": {
    "gn:admin1_code":"24.0",
    "gn:admin2_code":"109.0",
    "gn:asciiname":"Jagner",
    "gn:country_code":"IN",
    "gn:dem":335,
    "gn:feature_class":"P",
    "gn:feature_code":"PPL",
    "gn:name":"Jagner",
    "gn:population":0,
    "gn:timezone":"Asia/Kolkata",
    "iso:country":"IN",
    "name:bpy_x_preferred":[
        "\u099c\u09be\u0997\u09cd\u09a8\u09c7\u09b0"
    ],
    "name:ita_x_preferred":[
        "Jagner"
    ],
    "name:mlg_x_preferred":[
        "Jagner"
    ],
    "name:msa_x_preferred":[
        "Jagner"
    ],
    "name:new_x_preferred":[
        "\u091c\u0917\u094d\u0928\u0947\u0930"
    ],
    "name:nld_x_preferred":[
        "Jagner"
    ],
    "name:pol_x_preferred":[
        "Jagner"
    ],
    "name:por_x_preferred":[
        "Jagner"
    ],
    "name:urd_x_preferred":[
        "\u062c\u06af\u0646\u06cc\u0631"
    ],
    "name:vie_x_preferred":[
        "Jagner"
    ],
    "name:zho_x_preferred":[
        "\u8d3e\u683c\u5185\u5c14"
    ],
    "wof:name":"Jagner",
    "wof:placetype":"locality"
},
  "geometry": {"coordinates":[76.30228000000002,26.66776],"type":"Point"}
}