{
  "type": "Feature",
  "properties": {
    "gn:admin1_code":"36",
    "gn:admin2_code":"135.0",
    "gn:asciiname":"Jahangirpur Jakhpheri",
    "gn:country_code":"IN",
    "gn:dem":204,
    "gn:feature_class":"P",
    "gn:feature_code":"PPL",
    "gn:name":"Jah\u0101ng\u012brpur Jakhpheri",
    "gn:population":0,
    "gn:timezone":"Asia/Kolkata",
    "iso:country":"IN",
    "name:und_x_variant":[
        "Jah\u0101ng\u012brpur Jakhpheri",
        "Kanjarpura"
    ],
    "wof:name":"Jahangirpur Jakhpheri",
    "wof:placetype":"neighbourhood"
},
  "geometry": {"coordinates":[78.69656000000001,29.01629],"type":"Point"}
}