{
  "type": "Feature",
  "properties": {
    "gn:admin1_code":"35",
    "gn:admin2_code":"458.0",
    "gn:asciiname":"Jharpal",
    "gn:country_code":"IN",
    "gn:dem":442,
    "gn:feature_class":"P",
    "gn:feature_code":"PPL",
    "gn:name":"Jharpal",
    "gn:population":0,
    "gn:timezone":"Asia/Kolkata",
    "iso:country":"IN",
    "ks:ks_name":"Jharpai",
    "ks:ks_pop":1128,
    "ks:ks_type":"VILLAGE",
    "name:eng_x_preferred":[
        "Jharpai"
    ],
    "name:eng_x_variant":[
        "Jharpal"
    ],
    "wof:name":"Jharpai",
    "wof:placetype":"locality",
    "wof:population":1128
},
  "geometry": {"coordinates":[77.272899,24.177968],"type":"Point"}
}