{
  "type": "Feature",
  "properties": {
    "iso:country":"IN",
    "ks:ks_name":"Jheel Tola",
    "ks:ks_pop":270,
    "ks:ks_type":"HABITATION",
    "ks:ks_uagg_main":0,
    "name:eng_x_preferred":[
        "Jheel Tola"
    ],
    "wof:name":"Jheel Tola",
    "wof:placetype":"neighbourhood",
    "wof:population":270
},
  "geometry": {"coordinates":[83.71773399999999,26.555873],"type":"Point"}
}