{
  "type": "Feature",
  "properties": {
    "iso:country":"IN",
    "ks:ks_name":"Harijan Basti m",
    "ks:ks_pop":191,
    "ks:ks_type":"HABITATION",
    "name:eng_x_preferred":[
        "Harijan Basti m"
    ],
    "wof:name":"Harijan Basti m",
    "wof:placetype":"locality",
    "wof:population":191
},
  "geometry": {"coordinates":[82.887565,26.584297],"type":"Point"}
}