{
  "type": "Feature",
  "properties": {
    "gn:admin1_code":"36.0",
    "gn:admin2_code":"161",
    "gn:asciiname":"Nagla Jhinduwa",
    "gn:country_code":"IN",
    "gn:dem":148,
    "gn:feature_class":"P",
    "gn:feature_code":"PPL",
    "gn:name":"Nagla Jhinduwa",
    "gn:population":0,
    "gn:timezone":"Asia/Kolkata",
    "iso:country":"IN",
    "name:und_x_variant":[
        "Jhinduwa"
    ],
    "wof:name":"Nagla Jhinduwa",
    "wof:placetype":"neighbourhood"
},
  "geometry": {"coordinates":[79.13947,26.79759],"type":"Point"}
}