{
  "type": "Feature",
  "properties": {
    "gn:admin1_code":"34.0",
    "gn:admin2_code":"237.0",
    "gn:asciiname":"Partauniyan",
    "gn:country_code":"IN",
    "gn:dem":188,
    "gn:feature_class":"P",
    "gn:feature_code":"PPL",
    "gn:name":"Partauniy\u0101n",
    "gn:population":0,
    "gn:timezone":"Asia/Kolkata",
    "iso:country":"IN",
    "ks:ks_alt_nam":"Partauniy\u0101n",
    "ks:ks_name":"Partauniyan",
    "ks:ks_pop":228,
    "ks:ks_type":"VILLAGE",
    "name:eng_x_preferred":[
        "Partauniyan"
    ],
    "name:eng_x_variant":[
        "Partauniy\u0101n"
    ],
    "wof:name":"Partauniyan",
    "wof:placetype":"locality",
    "wof:population":228
},
  "geometry": {"coordinates":[85.467579,24.575227],"type":"Point"}
}