{
  "type": "Feature",
  "properties": {
    "iso:country":"IN",
    "ks:ks_alt_nam":"CHARIA RAHIKA",
    "ks:ks_name":"Charia Rahika",
    "ks:ks_pop":175,
    "ks:ks_type":"HABITATION",
    "ks:ks_uagg_main":0,
    "name:eng_x_preferred":[
        "Charia Rahika"
    ],
    "wof:name":"Charia Rahika",
    "wof:placetype":"neighbourhood",
    "wof:population":175
},
  "geometry": {"coordinates":[87.353229,25.916318],"type":"Point"}
}