{
  "type": "Feature",
  "properties": {
    "gn:admin1_code":"25.0",
    "gn:admin2_code":"610.0",
    "gn:asciiname":"Sadamugai",
    "gn:country_code":"IN",
    "gn:dem":229,
    "gn:feature_class":"P",
    "gn:feature_code":"PPL",
    "gn:name":"Sadamugai",
    "gn:population":0,
    "gn:timezone":"Asia/Kolkata",
    "iso:country":"IN",
    "wof:name":"Sadamugai",
    "wof:placetype":"locality"
},
  "geometry": {"coordinates":[77.28842,11.46716],"type":"Point"}
}