{
  "type": "Feature",
  "properties": {
    "gn:admin1_code":"37",
    "gn:admin2_code":"408.0",
    "gn:asciiname":"Mangatola",
    "gn:country_code":"IN",
    "gn:dem":360,
    "gn:feature_class":"P",
    "gn:feature_code":"PPL",
    "gn:name":"M\u0101ng\u0101tola",
    "gn:population":0,
    "gn:timezone":"Asia/Kolkata",
    "iso:country":"IN",
    "ks:ks_name":"Mangatola",
    "ks:ks_pop":508,
    "ks:ks_type":"VILLAGE",
    "name:eng_x_preferred":[
        "Mangatola"
    ],
    "wof:name":"Mangatola",
    "wof:placetype":"locality",
    "wof:population":508
},
  "geometry": {"coordinates":[80.679317,20.814904],"type":"Point"}
}