{
  "type": "Feature",
  "properties": {
    "iso:country":"IN",
    "ks:ks_name":"Artaka",
    "ks:ks_pop":278,
    "ks:ks_type":"VILLAGE",
    "name:eng_x_preferred":[
        "Artaka"
    ],
    "wof:name":"Artaka",
    "wof:placetype":"locality",
    "wof:population":278
},
  "geometry": {"coordinates":[86.15139499999999,20.406413],"type":"Point"}
}