{
  "type": "Feature",
  "properties": {
    "gn:admin1_code":"21",
    "gn:admin2_code":"388.0",
    "gn:asciiname":"Merikot",
    "gn:country_code":"IN",
    "gn:dem":212,
    "gn:feature_class":"P",
    "gn:feature_code":"PPL",
    "gn:name":"Merikot",
    "gn:population":0,
    "gn:timezone":"Asia/Kolkata",
    "iso:country":"IN",
    "name:und_x_variant":[
        "Mirikote",
        "Merikot"
    ],
    "wof:name":"Merikot",
    "wof:placetype":"locality"
},
  "geometry": {"coordinates":[84.28474,19.71437],"type":"Point"}
}