{
  "type": "Feature",
  "properties": {
    "iso:country":"IN",
    "ks:ks_alt_nam":"dadi ahiran",
    "ks:ks_name":"Dadi Ahiran",
    "ks:ks_pop":2386,
    "ks:ks_type":"HABITATION",
    "name:eng_x_preferred":[
        "Dadi Ahiran"
    ],
    "wof:name":"Dadi Ahiran",
    "wof:placetype":"locality",
    "wof:population":2386
},
  "geometry": {"coordinates":[82.13189,25.27804],"type":"Point"}
}