{
  "type": "Feature",
  "properties": {
    "gn:admin1_code":"31",
    "gn:admin2_code":"286.0",
    "gn:asciiname":"Thingsai",
    "gn:country_code":"IN",
    "gn:dem":1315,
    "gn:feature_class":"P",
    "gn:feature_code":"PPL",
    "gn:name":"Thingsai",
    "gn:population":0,
    "gn:timezone":"Asia/Kolkata",
    "iso:country":"IN",
    "wof:name":"Thingsai",
    "wof:placetype":"locality"
},
  "geometry": {"coordinates":[93.09868,22.92838],"type":"Point"}
}