{
  "type": "Feature",
  "properties": {
    "gn:admin1_code":"2.0",
    "gn:admin2_code":"543.0",
    "gn:asciiname":"Ramaswamivalasa",
    "gn:country_code":"IN",
    "gn:dem":171,
    "gn:feature_class":"P",
    "gn:feature_code":"PPL",
    "gn:name":"R\u0101maswamivalasa",
    "gn:population":0,
    "gn:timezone":"Asia/Kolkata",
    "iso:country":"IN",
    "ks:ks_name":"Ramaswamyvalasa",
    "ks:ks_pop":98,
    "ks:ks_type":"HABITATION",
    "name:eng_x_preferred":[
        "Ramaswamyvalasa"
    ],
    "name:eng_x_variant":[
        "Ramaswamivalasa"
    ],
    "wof:name":"Ramaswamyvalasa",
    "wof:placetype":"locality",
    "wof:population":98
},
  "geometry": {"coordinates":[83.223856,18.570726],"type":"Point"}
}