{
  "type": "Feature",
  "properties": {
    "iso:country":"IN",
    "ks:ks_name":"Jurukupuda",
    "ks:ks_pop":204,
    "ks:ks_type":"VILLAGE",
    "name:eng_x_preferred":[
        "Jurukupuda"
    ],
    "wof:name":"Jurukupuda",
    "wof:placetype":"locality",
    "wof:population":204
},
  "geometry": {"coordinates":[83.972947,20.118231],"type":"Point"}
}