{
  "type": "Feature",
  "properties": {
    "gn:admin1_code":"19.0",
    "gn:admin2_code":"573",
    "gn:asciiname":"Basaralu",
    "gn:country_code":"IN",
    "gn:dem":761,
    "gn:feature_class":"P",
    "gn:feature_code":"PPL",
    "gn:name":"Basar\u0101lu",
    "gn:population":0,
    "gn:timezone":"Asia/Kolkata",
    "iso:country":"IN",
    "name:bar_x_preferred":[
        "Basaralu"
    ],
    "name:deu_x_preferred":[
        "Basaralu"
    ],
    "name:und_x_variant":[
        "Basar\u0101lu"
    ],
    "name:vie_x_preferred":[
        "Basaralu"
    ],
    "wof:name":"Basaralu",
    "wof:placetype":"locality"
},
  "geometry": {"coordinates":[76.81764,12.70848],"type":"Point"}
}