{
  "type": "Feature",
  "properties": {
    "iso:country":"IN",
    "ks:ks_name":"Kamaldinni D",
    "ks:ks_pop":109,
    "ks:ks_type":"HABITATION",
    "name:eng_x_preferred":[
        "Kamaldinni D"
    ],
    "wof:name":"Kamaldinni D",
    "wof:placetype":"locality",
    "wof:population":109
},
  "geometry": {"coordinates":[76.55614199999999,15.888412],"type":"Point"}
}