{
  "type": "Feature",
  "properties": {
    "iso:country":"IN",
    "ks:ks_name":"Jeevappasamuthiram",
    "ks:ks_pop":120,
    "ks:ks_type":"HABITATION",
    "ks:ks_uagg_main":0,
    "name:eng_x_preferred":[
        "Jeevappasamuthiram"
    ],
    "wof:name":"Jeevappasamuthiram",
    "wof:placetype":"neighbourhood",
    "wof:population":120
},
  "geometry": {"coordinates":[79.35516200000001,10.893647],"type":"Point"}
}