{
  "type": "Feature",
  "properties": {
    "iso:country":"IN",
    "ks:ks_name":"Padave Dhangarwadi",
    "ks:ks_pop":122,
    "ks:ks_type":"HABITATION",
    "name:eng_x_preferred":[
        "Padave Dhangarwadi"
    ],
    "wof:name":"Padave Dhangarwadi",
    "wof:placetype":"locality",
    "wof:population":122
},
  "geometry": {"coordinates":[73.91913599999999,15.812999],"type":"Point"}
}