{
  "type": "Feature",
  "properties": {
    "iso:country":"IN",
    "ks:ks_name":"Harijan Basti North",
    "ks:ks_pop":143,
    "ks:ks_type":"HABITATION",
    "name:eng_x_preferred":[
        "Harijan Basti North"
    ],
    "wof:name":"Harijan Basti North",
    "wof:placetype":"locality",
    "wof:population":143
},
  "geometry": {"coordinates":[83.97060500000001,25.613873],"type":"Point"}
}