{
  "type": "Feature",
  "properties": {
    "gn:admin1_code":"2",
    "gn:admin2_code":"546.0",
    "gn:asciiname":"Singarajupalem",
    "gn:country_code":"IN",
    "gn:dem":10,
    "gn:feature_class":"P",
    "gn:feature_code":"PPL",
    "gn:name":"Singar\u0101jup\u0101lem",
    "gn:population":0,
    "gn:timezone":"Asia/Kolkata",
    "iso:country":"IN",
    "name:tel_x_preferred":[
        "\u0c38\u0c3f\u0c02\u0c17\u0c30\u0c3e\u0c1c\u0c41\u0c2a\u0c3e\u0c32\u0c46\u0c2e\u0c41"
    ],
    "wof:name":"Singarajupalem",
    "wof:placetype":"locality"
},
  "geometry": {"coordinates":[81.51680999999998,16.47415],"type":"Point"}
}