{
  "type": "Feature",
  "properties": {
    "gn:admin1_code":"11",
    "gn:admin2_code":"23.0",
    "gn:asciiname":"Ghor Sumb",
    "gn:country_code":"IN",
    "gn:dem":1575,
    "gn:feature_class":"P",
    "gn:feature_code":"PPL",
    "gn:name":"Ghor Sumb",
    "gn:population":0,
    "gn:timezone":"Asia/Kolkata",
    "iso:country":"IN",
    "wof:name":"Ghor Sumb",
    "wof:placetype":"locality"
},
  "geometry": {"coordinates":[76.09061,32.36154000000001],"type":"Point"}
}