{
  "type": "Feature",
  "properties": {
    "iso:country":"IN",
    "ks:ks_name":"Mahadev Nagar",
    "ks:ks_pop":1472,
    "ks:ks_type":"HABITATION",
    "name:eng_x_preferred":[
        "Mahadev Nagar"
    ],
    "wof:name":"Mahadev Nagar",
    "wof:placetype":"locality",
    "wof:population":1472
},
  "geometry": {"coordinates":[72.686564,26.636067],"type":"Point"}
}