{
  "type": "Feature",
  "properties": {
    "iso:country":"IN",
    "ks:ks_name":"Lakshmandihi",
    "ks:ks_pop":630,
    "ks:ks_type":"VILLAGE",
    "name:eng_x_preferred":[
        "Lakshmandihi"
    ],
    "wof:name":"Lakshmandihi",
    "wof:placetype":"locality",
    "wof:population":630
},
  "geometry": {"coordinates":[87.488573,23.810508],"type":"Point"}
}