{
  "type": "Feature",
  "properties": {
    "gn:admin1_code":"34.0",
    "gn:admin2_code":"236.0",
    "gn:asciiname":"Chamardih",
    "gn:country_code":"IN",
    "gn:dem":106,
    "gn:feature_class":"P",
    "gn:feature_code":"PPL",
    "gn:name":"Cham\u0101rdih",
    "gn:population":0,
    "gn:timezone":"Asia/Kolkata",
    "iso:country":"IN",
    "ks:ks_alt_nam":"Cham\u0101rdih",
    "ks:ks_name":"Chamardih",
    "ks:ks_pop":2230,
    "ks:ks_type":"VILLAGE",
    "ks:ks_uagg_main":0,
    "name:eng_x_preferred":[
        "Chamardih"
    ],
    "name:eng_x_variant":[
        "Cham\u0101rdih"
    ],
    "wof:name":"Chamardih",
    "wof:placetype":"neighbourhood",
    "wof:population":2230
},
  "geometry": {"coordinates":[84.994665,24.885982],"type":"Point"}
}