{
  "type": "Feature",
  "properties": {
    "gn:admin1_code":"36.0",
    "gn:admin2_code":"161.0",
    "gn:asciiname":"Pali Kalan",
    "gn:country_code":"IN",
    "gn:dem":149,
    "gn:feature_class":"P",
    "gn:feature_code":"PPL",
    "gn:name":"P\u0101li Kal\u0101n",
    "gn:population":0,
    "gn:timezone":"Asia/Kolkata",
    "iso:country":"IN",
    "ks:ks_alt_nam":"P\u0101li Kal\u0101n",
    "ks:ks_name":"Pali Kalan",
    "ks:ks_pop":3265,
    "ks:ks_type":"VILLAGE",
    "ks:ks_uagg_main":0,
    "name:eng_x_preferred":[
        "Pali Kalan"
    ],
    "name:eng_x_variant":[
        "P\u0101li Kal\u0101n"
    ],
    "wof:name":"Pali Kalan",
    "wof:placetype":"neighbourhood",
    "wof:population":3265
},
  "geometry": {"coordinates":[79.25893499999999,26.734449],"type":"Point"}
}