{
  "type": "Feature",
  "properties": {
    "iso:country":"IN",
    "ks:ks_name":"Kothe Hariau",
    "ks:ks_pop":330,
    "ks:ks_type":"HABITATION",
    "name:eng_x_preferred":[
        "Kothe Hariau"
    ],
    "wof:name":"Kothe Hariau",
    "wof:placetype":"locality",
    "wof:population":330
},
  "geometry": {"coordinates":[75.706198,29.980904],"type":"Point"}
}