{
  "type": "Feature",
  "properties": {
    "gn:admin1_code":"36.0",
    "gn:admin2_code":"182.0",
    "gn:asciiname":"Aunrahwa",
    "gn:country_code":"IN",
    "gn:dem":107,
    "gn:feature_class":"P",
    "gn:feature_code":"PPL",
    "gn:name":"Aunr\u0101hwa",
    "gn:population":0,
    "gn:timezone":"Asia/Kolkata",
    "iso:country":"IN",
    "ks:ks_name":"Aurahwa",
    "ks:ks_pop":3000,
    "ks:ks_type":"VILLAGE",
    "name:eng_x_preferred":[
        "Aurahwa"
    ],
    "name:eng_x_variant":[
        "Aunrahwa"
    ],
    "wof:name":"Aurahwa",
    "wof:placetype":"locality",
    "wof:population":3000
},
  "geometry": {"coordinates":[82.60713800000001,27.482745],"type":"Point"}
}