{
  "type": "Feature",
  "properties": {
    "iso:country":"IN",
    "ks:ks_alt_nam":"\u0100shikpur",
    "ks:ks_name":"Ashikpur",
    "ks:ks_type":"VILLAGE",
    "name:eng_x_preferred":[
        "Ashikpur"
    ],
    "name:eng_x_variant":[
        "\u0100shikpur"
    ],
    "wof:name":"Ashikpur",
    "wof:placetype":"locality"
},
  "geometry": {"coordinates":[82.98464199999999,26.00341],"type":"Point"}
}