{
  "type": "Feature",
  "properties": {
    "iso:country":"IN",
    "ks:ks_alt_nam":"P\u0101langarh",
    "ks:ks_name":"Palangarh",
    "ks:ks_pop":0,
    "ks:ks_type":"VILLAGE",
    "name:eng_x_preferred":[
        "Palangarh"
    ],
    "name:eng_x_variant":[
        "P\u0101langarh"
    ],
    "wof:name":"Palangarh",
    "wof:placetype":"locality",
    "wof:population":0
},
  "geometry": {"coordinates":[83.989188,24.863863],"type":"Point"}
}