{
  "type": "Feature",
  "properties": {
    "gn:admin1_code":"16.0",
    "gn:admin2_code":"508.0",
    "gn:asciiname":"Bandukpalli",
    "gn:country_code":"IN",
    "gn:dem":160,
    "gn:feature_class":"P",
    "gn:feature_code":"PPL",
    "gn:name":"Band\u016bkpalli",
    "gn:population":0,
    "gn:timezone":"Asia/Kolkata",
    "iso:country":"IN",
    "ks:ks_name":"Bandukpalli",
    "ks:ks_pop":333,
    "ks:ks_type":"VILLAGE",
    "name:eng_x_preferred":[
        "Bandukpalli"
    ],
    "wof:name":"Bandukpalli",
    "wof:placetype":"locality",
    "wof:population":333
},
  "geometry": {"coordinates":[80.029923,19.649577],"type":"Point"}
}