{
  "type": "Feature",
  "properties": {
    "iso:country":"IN",
    "ks:ks_name":"Durbbabere",
    "ks:ks_pop":2106,
    "ks:ks_type":"VILLAGE",
    "name:eng_x_preferred":[
        "Durbbabere"
    ],
    "wof:name":"Durbbabere",
    "wof:placetype":"locality",
    "wof:population":2106
},
  "geometry": {"coordinates":[88.137001,22.126347],"type":"Point"}
}