{
  "type": "Feature",
  "properties": {
    "iso:country":"IN",
    "ks:ks_name":"Thelkogudi",
    "ks:ks_pop":313,
    "ks:ks_type":"HABITATION",
    "name:eng_x_preferred":[
        "Thelkogudi"
    ],
    "wof:name":"Thelkogudi",
    "wof:placetype":"locality",
    "wof:population":313
},
  "geometry": {"coordinates":[84.528203,21.489629],"type":"Point"}
}