{
  "type": "Feature",
  "properties": {
    "iso:country":"IN",
    "ks:ks_name":"Banadurga",
    "ks:ks_pop":126,
    "ks:ks_type":"VILLAGE",
    "ks:ks_uagg_main":0,
    "name:eng_x_preferred":[
        "Banadurga"
    ],
    "wof:name":"Banadurga",
    "wof:placetype":"neighbourhood",
    "wof:population":126
},
  "geometry": {"coordinates":[86.31622299999999,20.237404],"type":"Point"}
}