{
  "type": "Feature",
  "properties": {
    "iso:country":"IN",
    "ks:ks_name":"Sonpur",
    "ks:ks_pop":341,
    "ks:ks_type":"VILLAGE",
    "name:eng_x_preferred":[
        "Sonpur"
    ],
    "wof:name":"Sonpur",
    "wof:placetype":"locality",
    "wof:population":341
},
  "geometry": {"coordinates":[83.60363,22.951727],"type":"Point"}
}