{
  "type": "Feature",
  "properties": {
    "gn:admin1_code":"36",
    "gn:admin2_code":"173.0",
    "gn:asciiname":"Chak Ramchand Patti",
    "gn:country_code":"IN",
    "gn:dem":99,
    "gn:feature_class":"P",
    "gn:feature_code":"PPL",
    "gn:name":"Chak R\u0101mchand Patti",
    "gn:population":0,
    "gn:timezone":"Asia/Kolkata",
    "iso:country":"IN",
    "wof:name":"Chak Ramchand Patti",
    "wof:placetype":"locality"
},
  "geometry": {"coordinates":[82.09385999999998,26.01003],"type":"Point"}
}