{
  "type": "Feature",
  "properties": {
    "iso:country":"IN",
    "ks:ks_name":"Bazar Mahammadpur",
    "ks:ks_pop":654,
    "ks:ks_type":"VILLAGE",
    "name:eng_x_preferred":[
        "Bazar Mahammadpur"
    ],
    "wof:name":"Bazar Mahammadpur",
    "wof:placetype":"locality",
    "wof:population":654
},
  "geometry": {"coordinates":[87.885203,23.388262],"type":"Point"}
}