{
  "type": "Feature",
  "properties": {
    "iso:country":"IN",
    "ks:ks_name":"Mohamadabad",
    "ks:ks_pop":165,
    "ks:ks_type":"VILLAGE",
    "name:eng_x_preferred":[
        "Mohamadabad"
    ],
    "wof:name":"Mohamadabad",
    "wof:placetype":"locality",
    "wof:population":165
},
  "geometry": {"coordinates":[83.007059,25.121018],"type":"Point"}
}