{
  "type": "Feature",
  "properties": {
    "gn:admin1_code":"34.0",
    "gn:admin2_code":"229.0",
    "gn:asciiname":"Beldari",
    "gn:country_code":"IN",
    "gn:dem":57,
    "gn:feature_class":"P",
    "gn:feature_code":"PPL",
    "gn:name":"Beld\u0101ri",
    "gn:population":0,
    "gn:timezone":"Asia/Kolkata",
    "iso:country":"IN",
    "name:ceb_x_preferred":[
        "Beldari"
    ],
    "name:fra_x_preferred":[
        "Beldari"
    ],
    "name:mai_x_preferred":[
        "\u092c\u0947\u0932\u094d\u0926\u093e\u0930\u0940"
    ],
    "name:msa_x_preferred":[
        "Beldari"
    ],
    "name:nep_x_preferred":[
        "\u092c\u0947\u0932\u094d\u0926\u093e\u0930\u0940"
    ],
    "name:pol_x_preferred":[
        "Beldari"
    ],
    "wof:name":"Beldari",
    "wof:placetype":"locality"
},
  "geometry": {"coordinates":[85.59201,25.20678],"type":"Point"}
}