{
  "type": "Feature",
  "properties": {
    "iso:country":"IN",
    "ks:ks_name":"Peddaguda",
    "ks:ks_pop":131,
    "ks:ks_type":"HABITATION",
    "name:eng_x_preferred":[
        "Peddaguda"
    ],
    "wof:name":"Peddaguda",
    "wof:placetype":"locality",
    "wof:population":131
},
  "geometry": {"coordinates":[83.801361,18.799043],"type":"Point"}
}