{
  "type": "Feature",
  "properties": {
    "iso:country":"IN",
    "ks:ks_name":"Kopakatel",
    "ks:ks_pop":243,
    "ks:ks_type":"VILLAGE",
    "name:eng_x_preferred":[
        "Kopakatel"
    ],
    "wof:name":"Kopakatel",
    "wof:placetype":"locality",
    "wof:population":243
},
  "geometry": {"coordinates":[80.934901,20.119039],"type":"Point"}
}