{
  "type": "Feature",
  "properties": {
    "iso:country":"IN",
    "ks:ks_name":"Appajaina",
    "ks:ks_pop":1209,
    "ks:ks_type":"HABITATION",
    "name:eng_x_preferred":[
        "Appajaina"
    ],
    "wof:name":"Appajaina",
    "wof:placetype":"locality",
    "wof:population":1209
},
  "geometry": {"coordinates":[77.130572,12.455248],"type":"Point"}
}