{
  "type": "Feature",
  "properties": {
    "iso:country":"IN",
    "ks:ks_name":"Thekahi",
    "ks:ks_pop":0,
    "ks:ks_type":"VILLAGE",
    "name:eng_x_preferred":[
        "Thekahi"
    ],
    "wof:name":"Thekahi",
    "wof:placetype":"locality",
    "wof:population":0
},
  "geometry": {"coordinates":[84.195211,24.817728],"type":"Point"}
}