{
  "type": "Feature",
  "properties": {
    "iso:country":"IN",
    "ks:ks_name":"Hosalli",
    "ks:ks_pop":20,
    "ks:ks_type":"HABITATION",
    "name:eng_x_preferred":[
        "Hosalli"
    ],
    "wof:name":"Hosalli",
    "wof:placetype":"locality",
    "wof:population":20
},
  "geometry": {"coordinates":[74.672932,14.384357],"type":"Point"}
}