{
  "type": "Feature",
  "properties": {
    "iso:country":"IN",
    "ks:ks_name":"Jotsadar",
    "ks:ks_pop":0,
    "ks:ks_type":"VILLAGE",
    "name:eng_x_preferred":[
        "Jotsadar"
    ],
    "wof:name":"Jotsadar",
    "wof:placetype":"locality",
    "wof:population":0
},
  "geometry": {"coordinates":[88.020343,22.63303],"type":"Point"}
}