{
  "type": "Feature",
  "properties": {
    "iso:country":"IN",
    "ks:ks_name":"Sukridobha",
    "ks:ks_pop":73,
    "ks:ks_type":"VILLAGE",
    "name:eng_x_preferred":[
        "Sukridobha"
    ],
    "wof:name":"Sukridobha",
    "wof:placetype":"locality",
    "wof:population":73
},
  "geometry": {"coordinates":[86.097736,23.157847],"type":"Point"}
}