{
  "type": "Feature",
  "properties": {
    "gn:admin1_code":"16.0",
    "gn:admin2_code":"526",
    "gn:asciiname":"Burli",
    "gn:country_code":"IN",
    "gn:dem":523,
    "gn:feature_class":"P",
    "gn:feature_code":"PPL",
    "gn:name":"Burli",
    "gn:population":0,
    "gn:timezone":"Asia/Kolkata",
    "iso:country":"IN",
    "name:deu_x_preferred":[
        "Burli"
    ],
    "name:und_x_variant":[
        "Burti"
    ],
    "wof:name":"Burli",
    "wof:placetype":"locality"
},
  "geometry": {"coordinates":[75.29035999999998,17.41681],"type":"Point"}
}