{
  "type": "Feature",
  "properties": {
    "iso:country":"IN",
    "ks:ks_name":"Jarthankollai",
    "ks:ks_pop":451,
    "ks:ks_type":"VILLAGE",
    "name:eng_x_preferred":[
        "Jarthankollai"
    ],
    "wof:name":"Jarthankollai",
    "wof:placetype":"locality",
    "wof:population":451
},
  "geometry": {"coordinates":[79.02643500000001,12.766718],"type":"Point"}
}