{
  "type": "Feature",
  "properties": {
    "gn:admin1_code":"36.0",
    "gn:admin2_code":"170.0",
    "gn:asciiname":"Godariyan ka Purwa",
    "gn:country_code":"IN",
    "gn:dem":136,
    "gn:feature_class":"P",
    "gn:feature_code":"PPL",
    "gn:name":"Godariyan ka Purwa",
    "gn:population":0,
    "gn:timezone":"Asia/Kolkata",
    "iso:country":"IN",
    "ks:ks_name":"Gadariyan Purwa",
    "ks:ks_pop":209,
    "ks:ks_type":"HABITATION",
    "name:eng_x_preferred":[
        "Gadariyan Purwa"
    ],
    "name:eng_x_variant":[
        "Godariyan ka Purwa"
    ],
    "wof:name":"Gadariyan Purwa",
    "wof:placetype":"locality",
    "wof:population":209
},
  "geometry": {"coordinates":[80.535945,25.146719],"type":"Point"}
}