{
  "type": "Feature",
  "properties": {
    "iso:country":"IN",
    "ks:ks_name":"Raipur",
    "ks:ks_pop":574,
    "ks:ks_type":"HABITATION",
    "name:eng_x_preferred":[
        "Raipur"
    ],
    "wof:name":"Raipur",
    "wof:placetype":"locality",
    "wof:population":574
},
  "geometry": {"coordinates":[79.94890100000001,27.807931],"type":"Point"}
}