{
  "type": "Feature",
  "properties": {
    "gn:admin1_code":"19.0",
    "gn:admin2_code":"578.0",
    "gn:asciiname":"Ravahayandoddi",
    "gn:country_code":"IN",
    "gn:dem":764,
    "gn:feature_class":"P",
    "gn:feature_code":"PPL",
    "gn:name":"R\u0101vahayandoddi",
    "gn:population":0,
    "gn:timezone":"Asia/Kolkata",
    "iso:country":"IN",
    "wof:name":"Ravahayandoddi",
    "wof:placetype":"locality"
},
  "geometry": {"coordinates":[77.25424,11.97382],"type":"Point"}
}