{
  "type": "Feature",
  "properties": {
    "gn:admin1_code":"21.0",
    "gn:admin2_code":"397.0",
    "gn:asciiname":"Nandahandi",
    "gn:country_code":"IN",
    "gn:dem":568,
    "gn:feature_class":"P",
    "gn:feature_code":"PPL",
    "gn:name":"Nandahandi",
    "gn:population":0,
    "gn:timezone":"Asia/Kolkata",
    "iso:country":"IN",
    "wof:name":"Nandahandi",
    "wof:placetype":"locality"
},
  "geometry": {"coordinates":[82.64588000000001,19.21746],"type":"Point"}
}