{
  "type": "Feature",
  "properties": {
    "iso:country":"IN",
    "ks:ks_name":"Pipar Patti",
    "ks:ks_pop":2064,
    "ks:ks_type":"VILLAGE",
    "ks:ks_uagg_main":0,
    "name:eng_x_preferred":[
        "Pipar Patti"
    ],
    "wof:name":"Pipar Patti",
    "wof:placetype":"locality",
    "wof:population":2064
},
  "geometry": {"coordinates":[83.801429,26.497275],"type":"Point"}
}