{
  "type": "Feature",
  "properties": {
    "iso:country":"IN",
    "ks:ks_name":"Narasipur",
    "ks:ks_pop":25,
    "ks:ks_type":"VILLAGE",
    "name:eng_x_preferred":[
        "Narasipur"
    ],
    "wof:name":"Narasipur",
    "wof:placetype":"locality",
    "wof:population":25
},
  "geometry": {"coordinates":[83.905213,18.917603],"type":"Point"}
}