{
  "type": "Feature",
  "properties": {
    "iso:country":"IN",
    "ks:ks_name":"P. Balheswar",
    "ks:ks_pop":808,
    "ks:ks_type":"HABITATION",
    "ks:ks_uagg_main":0,
    "name:eng_x_preferred":[
        "P. Balheswar"
    ],
    "wof:name":"P. Balheswar",
    "wof:placetype":"neighbourhood",
    "wof:population":808
},
  "geometry": {"coordinates":[81.022295,26.180919],"type":"Point"}
}