{
  "type": "Feature",
  "properties": {
    "gn:admin1_code":"21.0",
    "gn:admin2_code":"398.0",
    "gn:asciiname":"Jumaka",
    "gn:country_code":"IN",
    "gn:dem":411,
    "gn:feature_class":"P",
    "gn:feature_code":"PPL",
    "gn:name":"Jumaka",
    "gn:population":0,
    "gn:timezone":"Asia/Kolkata",
    "iso:country":"IN",
    "wof:name":"Jumaka",
    "wof:placetype":"locality"
},
  "geometry": {"coordinates":[83.21415,18.92813],"type":"Point"}
}