{
  "type": "Feature",
  "properties": {
    "gn:admin1_code":"39.0",
    "gn:admin2_code":"64.0",
    "gn:asciiname":"Selipatli",
    "gn:country_code":"IN",
    "gn:dem":1106,
    "gn:feature_class":"P",
    "gn:feature_code":"PPL",
    "gn:name":"Sel\u012bp\u0101tli",
    "gn:population":0,
    "gn:timezone":"Asia/Kolkata",
    "iso:country":"IN",
    "ks:ks_alt_nam":"Sel\u012bp\u0101tli",
    "ks:ks_name":"Selipatli",
    "ks:ks_type":"VILLAGE",
    "name:eng_x_preferred":[
        "Selipatli"
    ],
    "name:eng_x_variant":[
        "Sel\u012bp\u0101tli"
    ],
    "wof:name":"Selipatli",
    "wof:placetype":"locality"
},
  "geometry": {"coordinates":[79.23348900000001,29.862977],"type":"Point"}
}