{
  "type": "Feature",
  "properties": {
    "iso:country":"IN",
    "ks:ks_name":"Madhabpur",
    "ks:ks_pop":1120,
    "ks:ks_type":"VILLAGE",
    "name:eng_x_preferred":[
        "Madhabpur"
    ],
    "wof:name":"Madhabpur",
    "wof:placetype":"locality",
    "wof:population":1120
},
  "geometry": {"coordinates":[87.10396,22.909502],"type":"Point"}
}