{
  "type": "Feature",
  "properties": {
    "gn:admin1_code":"37",
    "gn:admin2_code":"404.0",
    "gn:asciiname":"Kargamar",
    "gn:country_code":"IN",
    "gn:dem":350,
    "gn:feature_class":"P",
    "gn:feature_code":"PPL",
    "gn:name":"Karg\u0101m\u0101r",
    "gn:population":0,
    "gn:timezone":"Asia/Kolkata",
    "iso:country":"IN",
    "ks:ks_alt_nam":"Karg\u0101m\u0101r",
    "ks:ks_name":"Kargamar",
    "ks:ks_pop":263,
    "ks:ks_type":"VILLAGE",
    "name:eng_x_preferred":[
        "Kargamar"
    ],
    "name:eng_x_variant":[
        "Karg\u0101m\u0101r"
    ],
    "wof:name":"Kargamar",
    "wof:placetype":"locality",
    "wof:population":263
},
  "geometry": {"coordinates":[82.429363,22.69619],"type":"Point"}
}