{
  "type": "Feature",
  "properties": {
    "iso:country":"IN",
    "ks:ks_name":"Chilam",
    "ks:ks_pop":75,
    "ks:ks_type":"VILLAGE",
    "name:eng_x_preferred":[
        "Chilam"
    ],
    "wof:name":"Chilam",
    "wof:placetype":"locality",
    "wof:population":75
},
  "geometry": {"coordinates":[82.675861,18.437933],"type":"Point"}
}