{
  "type": "Feature",
  "properties": {
    "iso:country":"IN",
    "ks:ks_alt_nam":"Sundarpur chuk",
    "ks:ks_name":"Sundarpur Chuk",
    "ks:ks_pop":450,
    "ks:ks_type":"HABITATION",
    "name:eng_x_preferred":[
        "Sundarpur Chuk"
    ],
    "wof:name":"Sundarpur Chuk",
    "wof:placetype":"locality",
    "wof:population":450
},
  "geometry": {"coordinates":[95.23194700000001,27.119801],"type":"Point"}
}