{
  "type": "Feature",
  "properties": {
    "iso:country":"IN",
    "ks:ks_name":"Aramala",
    "ks:ks_pop":1018,
    "ks:ks_type":"HABITATION",
    "name:eng_x_preferred":[
        "Aramala"
    ],
    "wof:name":"Aramala",
    "wof:placetype":"locality",
    "wof:population":1018
},
  "geometry": {"coordinates":[76.03017199999999,11.529752],"type":"Point"}
}