{
  "type": "Feature",
  "properties": {
    "iso:country":"IN",
    "ks:ks_name":"Manjakkarai North",
    "ks:ks_pop":44,
    "ks:ks_type":"HABITATION",
    "name:eng_x_preferred":[
        "Manjakkarai North"
    ],
    "wof:name":"Manjakkarai North",
    "wof:placetype":"locality",
    "wof:population":44
},
  "geometry": {"coordinates":[79.054249,10.191965],"type":"Point"}
}