{
  "type": "Feature",
  "properties": {
    "iso:country":"IN",
    "ks:ks_alt_nam":"Kumbhardara songalwadi",
    "ks:ks_name":"Kumbhardara Songalwadi",
    "ks:ks_pop":181,
    "ks:ks_type":"HABITATION",
    "name:eng_x_preferred":[
        "Kumbhardara Songalwadi"
    ],
    "wof:name":"Kumbhardara Songalwadi",
    "wof:placetype":"locality",
    "wof:population":181
},
  "geometry": {"coordinates":[73.90958000000001,19.594861],"type":"Point"}
}