{
  "type": "Feature",
  "properties": {
    "gn:admin1_code":"24",
    "gn:admin2_code":"111.0",
    "gn:asciiname":"Rewasa",
    "gn:country_code":"IN",
    "gn:dem":443,
    "gn:feature_class":"P",
    "gn:feature_code":"PPL",
    "gn:name":"Rew\u0101sa",
    "gn:population":0,
    "gn:timezone":"Asia/Kolkata",
    "iso:country":"IN",
    "name:und_x_variant":[
        "Rew\u0101sa",
        "Rewassa"
    ],
    "wof:name":"Rewasa",
    "wof:placetype":"neighbourhood"
},
  "geometry": {"coordinates":[75.22595,27.53308],"type":"Point"}
}