{
  "type": "Feature",
  "properties": {
    "iso:country":"IN",
    "ks:ks_name":"Kuwabil",
    "ks:ks_pop":150,
    "ks:ks_type":"HABITATION",
    "name:eng_x_preferred":[
        "Kuwabil"
    ],
    "wof:name":"Kuwabil",
    "wof:placetype":"locality",
    "wof:population":150
},
  "geometry": {"coordinates":[90.241339,26.427527],"type":"Point"}
}