{
  "type": "Feature",
  "properties": {
    "iso:country":"IN",
    "ks:ks_name":"Barabari",
    "ks:ks_pop":5051,
    "ks:ks_type":"VILLAGE",
    "name:eng_x_preferred":[
        "Barabari"
    ],
    "wof:name":"Barabari",
    "wof:placetype":"locality",
    "wof:population":5051
},
  "geometry": {"coordinates":[88.080944,22.100208],"type":"Point"}
}