{
  "type": "Feature",
  "properties": {
    "iso:country":"IN",
    "ks:ks_name":"Chengalavoryapuram",
    "ks:ks_pop":289,
    "ks:ks_type":"HABITATION",
    "ks:ks_uagg_main":0,
    "name:eng_x_preferred":[
        "Chengalavoryapuram"
    ],
    "wof:name":"Chengalavoryapuram",
    "wof:placetype":"neighbourhood",
    "wof:population":289
},
  "geometry": {"coordinates":[79.147896,12.750419],"type":"Point"}
}