{
  "type": "Feature",
  "properties": {
    "gn:admin1_code":"36",
    "gn:admin2_code":"154.0",
    "gn:asciiname":"Chaparwa Purwa",
    "gn:country_code":"IN",
    "gn:dem":139,
    "gn:feature_class":"P",
    "gn:feature_code":"PPL",
    "gn:name":"Chaparwa Purwa",
    "gn:population":0,
    "gn:timezone":"Asia/Kolkata",
    "iso:country":"IN",
    "wof:name":"Chaparwa Purwa",
    "wof:placetype":"neighbourhood"
},
  "geometry": {"coordinates":[80.86408,27.42356],"type":"Point"}
}