{
  "type": "Feature",
  "properties": {
    "gn:admin1_code":"36",
    "gn:admin2_code":"134.0",
    "gn:asciiname":"Islampur Thambuchau",
    "gn:country_code":"IN",
    "gn:dem":245,
    "gn:feature_class":"P",
    "gn:feature_code":"PPL",
    "gn:name":"Isl\u0101mpur Thambuch\u0101u",
    "gn:population":0,
    "gn:timezone":"Asia/Kolkata",
    "iso:country":"IN",
    "wof:name":"Islampur Thambuchau",
    "wof:placetype":"locality"
},
  "geometry": {"coordinates":[78.26758000000002,29.39089],"type":"Point"}
}