{
  "type": "Feature",
  "properties": {
    "iso:country":"IN",
    "ks:ks_alt_nam":"Gunde bailu",
    "ks:ks_name":"Gunde Bailu",
    "ks:ks_pop":300,
    "ks:ks_type":"HABITATION",
    "name:eng_x_preferred":[
        "Gunde Bailu"
    ],
    "wof:name":"Gunde Bailu",
    "wof:placetype":"locality",
    "wof:population":300
},
  "geometry": {"coordinates":[75.195071,12.658148],"type":"Point"}
}