{
  "type": "Feature",
  "properties": {
    "iso:country":"IN",
    "ks:ks_name":"Devar Walla",
    "ks:ks_pop":490,
    "ks:ks_type":"VILLAGE",
    "name:eng_x_preferred":[
        "Devar Walla"
    ],
    "wof:name":"Devar Walla",
    "wof:placetype":"locality",
    "wof:population":490
},
  "geometry": {"coordinates":[79.201852,30.330103],"type":"Point"}
}