{
  "type": "Feature",
  "properties": {
    "gn:admin1_code":"38.0",
    "gn:admin2_code":"352.0",
    "gn:asciiname":"Mangtanr",
    "gn:country_code":"IN",
    "gn:dem":114,
    "gn:feature_class":"P",
    "gn:feature_code":"PPL",
    "gn:name":"Mangt\u0101nr",
    "gn:population":0,
    "gn:timezone":"Asia/Kolkata",
    "iso:country":"IN",
    "ks:ks_alt_nam":"Mangt\u0101nr",
    "ks:ks_name":"Mangtanr",
    "ks:ks_pop":280,
    "ks:ks_type":"VILLAGE",
    "name:eng_x_preferred":[
        "Mangtanr"
    ],
    "name:eng_x_variant":[
        "Mangt\u0101nr"
    ],
    "wof:name":"Mangtanr",
    "wof:placetype":"locality",
    "wof:population":280
},
  "geometry": {"coordinates":[87.616894,25.134088],"type":"Point"}
}