{
  "type": "Feature",
  "properties": {
    "gn:admin1_code":"36.0",
    "gn:admin2_code":"160",
    "gn:asciiname":"Kakraiya",
    "gn:country_code":"IN",
    "gn:dem":151,
    "gn:feature_class":"P",
    "gn:feature_code":"PPL",
    "gn:name":"Kakraiya",
    "gn:population":0,
    "gn:timezone":"Asia/Kolkata",
    "iso:country":"IN",
    "name:und_x_variant":[
        "Sar\u0101i G\u016bjarmal",
        "Kakraiya"
    ],
    "wof:name":"Kakraiya",
    "wof:placetype":"locality"
},
  "geometry": {"coordinates":[79.48436,27.15398],"type":"Point"}
}