{
  "type": "Feature",
  "properties": {
    "iso:country":"IN",
    "ks:ks_name":"Garbere",
    "ks:ks_pop":690,
    "ks:ks_type":"VILLAGE",
    "name:eng_x_preferred":[
        "Garbere"
    ],
    "wof:name":"Garbere",
    "wof:placetype":"locality",
    "wof:population":690
},
  "geometry": {"coordinates":[87.937703,22.726158],"type":"Point"}
}