{
  "type": "Feature",
  "properties": {
    "iso:country":"IN",
    "ks:ks_name":"Jarah",
    "ks:ks_pop":4683,
    "ks:ks_type":"VILLAGE",
    "name:eng_x_preferred":[
        "Jarah"
    ],
    "wof:name":"Jarah",
    "wof:placetype":"locality",
    "wof:population":4683
},
  "geometry": {"coordinates":[77.98374,26.636408],"type":"Point"}
}