{
  "type": "Feature",
  "properties": {
    "gn:admin1_code":"35",
    "gn:admin2_code":"457.0",
    "gn:asciiname":"Dulhapur",
    "gn:country_code":"IN",
    "gn:dem":362,
    "gn:feature_class":"P",
    "gn:feature_code":"PPL",
    "gn:name":"Dulh\u0101pur",
    "gn:population":0,
    "gn:timezone":"Asia/Kolkata",
    "iso:country":"IN",
    "ks:ks_name":"Dulhapur",
    "ks:ks_pop":434,
    "ks:ks_type":"VILLAGE",
    "name:eng_x_preferred":[
        "Dulhapur"
    ],
    "wof:name":"Dulhapur",
    "wof:placetype":"locality",
    "wof:population":434
},
  "geometry": {"coordinates":[79.612047,21.700876],"type":"Point"}
}