{
  "type": "Feature",
  "properties": {
    "iso:country":"IN",
    "ks:ks_name":"Sasithota",
    "ks:ks_pop":46,
    "ks:ks_type":"HABITATION",
    "name:eng_x_preferred":[
        "Sasithota"
    ],
    "wof:name":"Sasithota",
    "wof:placetype":"locality",
    "wof:population":46
},
  "geometry": {"coordinates":[74.86374600000001,14.026412],"type":"Point"}
}