{
  "type": "Feature",
  "properties": {
    "iso:country":"IN",
    "ks:ks_name":"Halebaragal",
    "ks:ks_pop":26,
    "ks:ks_type":"HABITATION",
    "name:eng_x_preferred":[
        "Halebaragal"
    ],
    "wof:name":"Halebaragal",
    "wof:placetype":"locality",
    "wof:population":26
},
  "geometry": {"coordinates":[74.725847,14.317404],"type":"Point"}
}