{
  "type": "Feature",
  "properties": {
    "iso:country":"IN",
    "ks:ks_name":"Ambolwadi",
    "ks:ks_pop":95,
    "ks:ks_type":"HABITATION",
    "name:eng_x_preferred":[
        "Ambolwadi"
    ],
    "wof:name":"Ambolwadi",
    "wof:placetype":"locality",
    "wof:population":95
},
  "geometry": {"coordinates":[73.537081,16.350156],"type":"Point"}
}