{
  "type": "Feature",
  "properties": {
    "iso:country":"IN",
    "ks:ks_name":"Nuagaon",
    "ks:ks_pop":1684,
    "ks:ks_type":"VILLAGE",
    "name:eng_x_preferred":[
        "Nuagaon"
    ],
    "wof:name":"Nuagaon",
    "wof:placetype":"locality",
    "wof:population":1684
},
  "geometry": {"coordinates":[86.510347,21.670304],"type":"Point"}
}