{
  "type": "Feature",
  "properties": {
    "gn:admin1_code":"34.0",
    "gn:admin2_code":"212.0",
    "gn:asciiname":"Jian",
    "gn:country_code":"IN",
    "gn:dem":37,
    "gn:feature_class":"P",
    "gn:feature_code":"PPL",
    "gn:name":"Jian",
    "gn:population":0,
    "gn:timezone":"Asia/Kolkata",
    "iso:country":"IN",
    "name:cat_x_preferred":[
        "Jian"
    ],
    "name:ces_x_preferred":[
        "\u0164ien"
    ],
    "name:deu_x_preferred":[
        "Jian"
    ],
    "name:epo_x_preferred":[
        "\u011cjan"
    ],
    "name:fin_x_preferred":[
        "Jian"
    ],
    "name:fra_x_preferred":[
        "Jian"
    ],
    "name:heb_x_preferred":[
        "\u05d2'\u05d9\u05d0\u05df"
    ],
    "name:hun_x_preferred":[
        "Jian"
    ],
    "name:ind_x_preferred":[
        "Jian"
    ],
    "name:ita_x_preferred":[
        "Jian"
    ],
    "name:jpn_x_preferred":[
        "\u4e2d\u56fd\u5263"
    ],
    "name:kor_x_preferred":[
        "\uac80"
    ],
    "name:pol_x_preferred":[
        "Jian"
    ],
    "name:rus_x_preferred":[
        "\u0426\u0437\u044f\u043d\u044c"
    ],
    "name:spa_x_preferred":[
        "Jian"
    ],
    "name:zho_x_preferred":[
        "\u528d"
    ],
    "wof:name":"Jian",
    "wof:placetype":"locality"
},
  "geometry": {"coordinates":[87.88674,25.64612],"type":"Point"}
}