{
  "type": "Feature",
  "properties": {
    "iso:country":"IN",
    "ks:ks_name":"Narukot",
    "ks:ks_pop":1571,
    "ks:ks_type":"VILLAGE",
    "name:eng_x_preferred":[
        "Narukot"
    ],
    "wof:name":"Narukot",
    "wof:placetype":"locality",
    "wof:population":1571
},
  "geometry": {"coordinates":[73.68928200000001,22.385309],"type":"Point"}
}