{
  "type": "Feature",
  "properties": {
    "iso:country":"IN",
    "ks:ks_alt_nam":"tithin",
    "ks:ks_name":"Tithin",
    "ks:ks_pop":610,
    "ks:ks_type":"HABITATION",
    "name:eng_x_preferred":[
        "Tithin"
    ],
    "wof:name":"Tithin",
    "wof:placetype":"locality",
    "wof:population":610
},
  "geometry": {"coordinates":[85.384236,24.422355],"type":"Point"}
}