{
  "type": "Feature",
  "properties": {
    "gn:admin1_code":"2.0",
    "gn:asciiname":"Kottguddalayalasa",
    "gn:country_code":"IN",
    "gn:dem":196,
    "gn:feature_class":"P",
    "gn:feature_code":"PPL",
    "gn:name":"Kottguddalayalasa",
    "gn:population":0,
    "gn:timezone":"Asia/Kolkata",
    "iso:country":"IN",
    "wof:name":"Kottguddalayalasa",
    "wof:placetype":"locality"
},
  "geometry": {"coordinates":[83.27370999999999,18.76631],"type":"Point"}
}