{
  "type": "Feature",
  "properties": {
    "iso:country":"IN",
    "ks:ks_alt_nam":"REBAI MALA",
    "ks:ks_name":"Rebai Mala",
    "ks:ks_pop":242,
    "ks:ks_type":"HABITATION",
    "name:eng_x_preferred":[
        "Rebai Mala"
    ],
    "wof:name":"Rebai Mala",
    "wof:placetype":"locality",
    "wof:population":242
},
  "geometry": {"coordinates":[74.939626,17.286202],"type":"Point"}
}