{
  "type": "Feature",
  "properties": {
    "iso:country":"IN",
    "ks:ks_name":"Kalat",
    "ks:ks_pop":2139,
    "ks:ks_type":"HABITATION",
    "name:eng_x_preferred":[
        "Kalat"
    ],
    "wof:name":"Kalat",
    "wof:placetype":"locality",
    "wof:population":2139
},
  "geometry": {"coordinates":[73.743639,24.263944],"type":"Point"}
}