{
  "type": "Feature",
  "properties": {
    "iso:country":"IN",
    "ks:ks_name":"Padavettikunnu",
    "ks:ks_pop":412,
    "ks:ks_type":"HABITATION",
    "name:eng_x_preferred":[
        "Padavettikunnu"
    ],
    "wof:name":"Padavettikunnu",
    "wof:placetype":"locality",
    "wof:population":412
},
  "geometry": {"coordinates":[76.146182,11.494018],"type":"Point"}
}