{
  "type": "Feature",
  "properties": {
    "gn:admin1_code":"2.0",
    "gn:admin2_code":"554.0",
    "gn:asciiname":"Mitturu",
    "gn:country_code":"IN",
    "gn:dem":677,
    "gn:feature_class":"P",
    "gn:feature_code":"PPL",
    "gn:name":"Mitt\u016bru",
    "gn:population":0,
    "gn:timezone":"Asia/Kolkata",
    "iso:country":"IN",
    "wof:name":"Mitturu",
    "wof:placetype":"locality"
},
  "geometry": {"coordinates":[78.71755999999998,13.25316],"type":"Point"}
}