{
  "type": "Feature",
  "properties": {
    "iso:country":"IN",
    "ks:ks_name":"Bhokasevasti",
    "ks:ks_pop":293,
    "ks:ks_type":"HABITATION",
    "name:eng_x_preferred":[
        "Bhokasevasti"
    ],
    "wof:name":"Bhokasevasti",
    "wof:placetype":"locality",
    "wof:population":293
},
  "geometry": {"coordinates":[73.782222,18.839167],"type":"Point"}
}