{
  "type": "Feature",
  "properties": {
    "gn:admin1_code":"7.0",
    "gn:admin2_code":"90.0",
    "gn:asciiname":"Palla",
    "gn:country_code":"IN",
    "gn:dem":214,
    "gn:feature_class":"P",
    "gn:feature_code":"PPL",
    "gn:name":"Palla",
    "gn:population":0,
    "gn:timezone":"Asia/Kolkata",
    "iso:country":"IN",
    "name:deu_x_preferred":[
        "Palla eh!"
    ],
    "name:ita_x_preferred":[
        "Palla eh!"
    ],
    "wof:name":"Palla",
    "wof:placetype":"locality"
},
  "geometry": {"coordinates":[77.18698000000001,28.84199000000001],"type":"Point"}
}