{
  "type": "Feature",
  "properties": {
    "iso:country":"IN",
    "ks:ks_name":"Gawadi",
    "ks:ks_pop":228,
    "ks:ks_type":"VILLAGE",
    "name:eng_x_preferred":[
        "Gawadi"
    ],
    "wof:name":"Gawadi",
    "wof:placetype":"locality",
    "wof:population":228
},
  "geometry": {"coordinates":[81.305415,19.844305],"type":"Point"}
}