{
  "type": "Feature",
  "properties": {
    "iso:country":"IN",
    "ks:ks_name":"Haigunda",
    "ks:ks_pop":499,
    "ks:ks_type":"HABITATION",
    "name:eng_x_preferred":[
        "Haigunda"
    ],
    "wof:name":"Haigunda",
    "wof:placetype":"locality",
    "wof:population":499
},
  "geometry": {"coordinates":[74.565606,14.241738],"type":"Point"}
}