{
  "type": "Feature",
  "properties": {
    "gn:admin1_code":"16",
    "gn:admin2_code":"515.0",
    "gn:asciiname":"Ambala",
    "gn:country_code":"IN",
    "gn:dem":715,
    "gn:feature_class":"P",
    "gn:feature_code":"PPL",
    "gn:name":"Amb\u0101la",
    "gn:population":0,
    "gn:timezone":"Asia/Kolkata",
    "iso:country":"IN",
    "wof:name":"Ambala",
    "wof:placetype":"locality"
},
  "geometry": {"coordinates":[75.01599,20.30056],"type":"Point"}
}