{
  "type": "Feature",
  "properties": {
    "iso:country":"IN",
    "ks:ks_name":"Kumbiguda",
    "ks:ks_pop":24,
    "ks:ks_type":"HABITATION",
    "name:eng_x_preferred":[
        "Kumbiguda"
    ],
    "wof:name":"Kumbiguda",
    "wof:placetype":"locality",
    "wof:population":24
},
  "geometry": {"coordinates":[82.53415,18.359991],"type":"Point"}
}