{
  "type": "Feature",
  "properties": {
    "iso:country":"IN",
    "ks:ks_name":"Jalal Patti",
    "ks:ks_pop":5063,
    "ks:ks_type":"VILLAGE",
    "ks:ks_uagg_main":0,
    "name:eng_x_preferred":[
        "Jalal Patti"
    ],
    "wof:name":"Jalal Patti",
    "wof:placetype":"neighbourhood",
    "wof:population":5063
},
  "geometry": {"coordinates":[82.958645,25.285574],"type":"Point"}
}