{
  "type": "Feature",
  "properties": {
    "iso:country":"IN",
    "ks:ks_name":"Moongapattanpatti",
    "ks:ks_pop":104,
    "ks:ks_type":"HABITATION",
    "ks:ks_uagg_main":0,
    "name:eng_x_preferred":[
        "Moongapattanpatti"
    ],
    "wof:name":"Moongapattanpatti",
    "wof:placetype":"neighbourhood",
    "wof:population":104
},
  "geometry": {"coordinates":[78.835505,12.9473],"type":"Point"}
}