{
  "type": "Feature",
  "properties": {
    "iso:country":"IN",
    "ks:ks_name":"Nagangudi",
    "ks:ks_pop":555,
    "ks:ks_type":"HABITATION",
    "name:eng_x_preferred":[
        "Nagangudi"
    ],
    "wof:name":"Nagangudi",
    "wof:placetype":"locality",
    "wof:population":555
},
  "geometry": {"coordinates":[79.55800499999999,10.697635],"type":"Point"}
}