{
  "type": "Feature",
  "properties": {
    "gn:admin1_code":"39.0",
    "gn:admin2_code":"60.0",
    "gn:asciiname":"Kharyan Karanpur",
    "gn:country_code":"IN",
    "gn:dem":1195,
    "gn:feature_class":"P",
    "gn:feature_code":"PPL",
    "gn:name":"Kharyan Karanpur",
    "gn:population":0,
    "gn:timezone":"Asia/Kolkata",
    "iso:country":"IN",
    "wof:name":"Kharyan Karanpur",
    "wof:placetype":"locality"
},
  "geometry": {"coordinates":[78.12085,30.39145],"type":"Point"}
}