{
  "type": "Feature",
  "properties": {
    "iso:country":"IN",
    "ks:ks_name":"Saragdi",
    "ks:ks_pop":82,
    "ks:ks_type":"HABITATION",
    "name:eng_x_preferred":[
        "Saragdi"
    ],
    "wof:name":"Saragdi",
    "wof:placetype":"locality",
    "wof:population":82
},
  "geometry": {"coordinates":[86.305938,22.580922],"type":"Point"}
}