{
  "type": "Feature",
  "properties": {
    "iso:country":"IN",
    "ks:ks_alt_nam":"5 MSM",
    "ks:ks_name":"5 Msm",
    "ks:ks_pop":261,
    "ks:ks_type":"HABITATION",
    "name:eng_x_preferred":[
        "5 Msm"
    ],
    "wof:name":"5 Msm",
    "wof:placetype":"locality",
    "wof:population":261
},
  "geometry": {"coordinates":[72.56856999999999,28.575555],"type":"Point"}
}