{
  "type": "Feature",
  "properties": {
    "gn:admin1_code":"35",
    "gn:admin2_code":"456.0",
    "gn:asciiname":"Turiya",
    "gn:country_code":"IN",
    "gn:dem":430,
    "gn:feature_class":"P",
    "gn:feature_code":"PPL",
    "gn:name":"Turiya",
    "gn:population":0,
    "gn:timezone":"Asia/Kolkata",
    "iso:country":"IN",
    "name:bul_x_preferred":[
        "\u0422\u0443\u0440\u0438\u044f"
    ],
    "name:deu_x_preferred":[
        "Turiya"
    ],
    "name:fra_x_preferred":[
        "Turiya"
    ],
    "name:hin_x_preferred":[
        "\u0924\u0941\u0930\u0940\u092f"
    ],
    "name:ita_x_preferred":[
        "Tur\u012bya"
    ],
    "name:kor_x_preferred":[
        "\ud22c\ub9ac\uc57c"
    ],
    "name:nld_x_preferred":[
        "Turiya"
    ],
    "name:pol_x_preferred":[
        "Turija"
    ],
    "name:por_x_preferred":[
        "Turiya"
    ],
    "name:rus_x_preferred":[
        "\u0422\u0443\u0440\u044c\u044f"
    ],
    "wof:name":"Turiya",
    "wof:placetype":"locality"
},
  "geometry": {"coordinates":[79.36750000000001,21.7358],"type":"Point"}
}