{
  "type": "Feature",
  "properties": {
    "iso:country":"IN",
    "ks:ks_name":"Borichapada",
    "ks:ks_pop":105,
    "ks:ks_type":"HABITATION",
    "name:eng_x_preferred":[
        "Borichapada"
    ],
    "wof:name":"Borichapada",
    "wof:placetype":"locality",
    "wof:population":105
},
  "geometry": {"coordinates":[73.284414,20.007332],"type":"Point"}
}