{
  "type": "Feature",
  "properties": {
    "gn:admin1_code":"10.0",
    "gn:admin2_code":"72.0",
    "gn:asciiname":"Sura",
    "gn:country_code":"IN",
    "gn:dem":266,
    "gn:feature_class":"P",
    "gn:feature_code":"PPL",
    "gn:name":"S\u016bra",
    "gn:population":0,
    "gn:timezone":"Asia/Kolkata",
    "iso:country":"IN",
    "name:ben_x_preferred":[
        "\u09b8\u09c1\u09b0\u09be"
    ],
    "name:heb_x_preferred":[
        "\u05e1\u05d5\u05e8\u05d4"
    ],
    "name:hin_x_preferred":[
        "\u0938\u0942\u0930\u093e"
    ],
    "name:ind_x_preferred":[
        "Sura"
    ],
    "name:swe_x_preferred":[
        "Sura"
    ],
    "name:urd_x_preferred":[
        "\u0633\u0648\u0631\u0627"
    ],
    "name:vie_x_preferred":[
        "S\u00f4ng Sura"
    ],
    "wof:name":"Sura",
    "wof:placetype":"locality"
},
  "geometry": {"coordinates":[77.09935,30.02834],"type":"Point"}
}