{
  "type": "Feature",
  "properties": {
    "iso:country":"IN",
    "ks:ks_name":"Sirkatta",
    "ks:ks_pop":393,
    "ks:ks_type":"HABITATION",
    "name:eng_x_preferred":[
        "Sirkatta"
    ],
    "wof:name":"Sirkatta",
    "wof:placetype":"locality",
    "wof:population":393
},
  "geometry": {"coordinates":[81.869891,20.543873],"type":"Point"}
}