{
  "type": "Feature",
  "properties": {
    "gn:admin1_code":"36.0",
    "gn:admin2_code":"149.0",
    "gn:asciiname":"Azizpur",
    "gn:country_code":"IN",
    "gn:dem":177,
    "gn:feature_class":"P",
    "gn:feature_code":"PPL",
    "gn:name":"Az\u012bzpur",
    "gn:population":0,
    "gn:timezone":"Asia/Kolkata",
    "iso:country":"IN",
    "wof:name":"Azizpur",
    "wof:placetype":"locality"
},
  "geometry": {"coordinates":[78.50159000000002,28.17372],"type":"Point"}
}