{
  "type": "Feature",
  "properties": {
    "iso:country":"IN",
    "ks:ks_alt_nam":"MV 76",
    "ks:ks_name":"Mv 76",
    "ks:ks_pop":336,
    "ks:ks_type":"HABITATION",
    "ks:ks_uagg_main":0,
    "name:eng_x_preferred":[
        "Mv 76"
    ],
    "wof:name":"Mv 76",
    "wof:placetype":"neighbourhood",
    "wof:population":336
},
  "geometry": {"coordinates":[81.585869,17.988791],"type":"Point"}
}