{
  "type": "Feature",
  "properties": {
    "gn:admin1_code":"37.0",
    "gn:admin2_code":"416.0",
    "gn:asciiname":"Kotwalpara",
    "gn:country_code":"IN",
    "gn:dem":550,
    "gn:feature_class":"P",
    "gn:feature_code":"PPL",
    "gn:name":"Kotw\u0101lp\u0101ra",
    "gn:population":0,
    "gn:timezone":"Asia/Kolkata",
    "iso:country":"IN",
    "wof:name":"Kotwalpara",
    "wof:placetype":"locality"
},
  "geometry": {"coordinates":[81.54290999999998,18.90762],"type":"Point"}
}