{
  "type": "Feature",
  "properties": {
    "iso:country":"IN",
    "ks:ks_name":"Pansarewasti",
    "ks:ks_pop":141,
    "ks:ks_type":"HABITATION",
    "ks:ks_uagg_main":0,
    "name:eng_x_preferred":[
        "Pansarewasti"
    ],
    "wof:name":"Pansarewasti",
    "wof:placetype":"neighbourhood",
    "wof:population":141
},
  "geometry": {"coordinates":[74.33889000000001,19.012402],"type":"Point"}
}