{
  "type": "Feature",
  "properties": {
    "iso:country":"IN",
    "ks:ks_name":"Bhandarmala",
    "ks:ks_pop":117,
    "ks:ks_type":"HABITATION",
    "name:eng_x_preferred":[
        "Bhandarmala"
    ],
    "wof:name":"Bhandarmala",
    "wof:placetype":"locality",
    "wof:population":117
},
  "geometry": {"coordinates":[74.943027,17.722421],"type":"Point"}
}