{
  "type": "Feature",
  "properties": {
    "gn:admin1_code":"09",
    "gn:admin2_code":"481.0",
    "gn:asciiname":"Rajpur",
    "gn:country_code":"IN",
    "gn:dem":25,
    "gn:feature_class":"P",
    "gn:feature_code":"PPL",
    "gn:name":"R\u0101jpur",
    "gn:population":0,
    "gn:timezone":"Asia/Kolkata",
    "iso:country":"IN",
    "wof:name":"Rajpur",
    "wof:placetype":"locality"
},
  "geometry": {"coordinates":[72.08373,21.20357000000001],"type":"Point"}
}