{
  "type": "Feature",
  "properties": {
    "iso:country":"IN",
    "ks:ks_name":"Khirman",
    "ks:ks_pop":361,
    "ks:ks_type":"VILLAGE",
    "name:eng_x_preferred":[
        "Khirman"
    ],
    "wof:name":"Khirman",
    "wof:placetype":"locality",
    "wof:population":361
},
  "geometry": {"coordinates":[73.509353,20.409745],"type":"Point"}
}