{
  "type": "Feature",
  "properties": {
    "iso:country":"IN",
    "ks:ks_name":"Manni",
    "ks:ks_pop":22,
    "ks:ks_type":"VILLAGE",
    "name:eng_x_preferred":[
        "Manni"
    ],
    "wof:name":"Manni",
    "wof:placetype":"locality",
    "wof:population":22
},
  "geometry": {"coordinates":[80.95726000000001,24.145052],"type":"Point"}
}