{
  "type": "Feature",
  "properties": {
    "iso:country":"IN",
    "ks:ks_name":"Garatola",
    "ks:ks_pop":98,
    "ks:ks_type":"HABITATION",
    "name:eng_x_preferred":[
        "Garatola"
    ],
    "wof:name":"Garatola",
    "wof:placetype":"locality",
    "wof:population":98
},
  "geometry": {"coordinates":[85.673975,22.897265],"type":"Point"}
}