{
  "type": "Feature",
  "properties": {
    "iso:country":"IN",
    "ks:ks_name":"Kadalipali",
    "ks:ks_pop":107,
    "ks:ks_type":"VILLAGE",
    "name:eng_x_preferred":[
        "Kadalipali"
    ],
    "wof:name":"Kadalipali",
    "wof:placetype":"locality",
    "wof:population":107
},
  "geometry": {"coordinates":[83.53585200000001,20.757766],"type":"Point"}
}