{
  "type": "Feature",
  "properties": {
    "gn:admin1_code":"34",
    "gn:admin2_code":"233.0",
    "gn:asciiname":"Bekas",
    "gn:country_code":"IN",
    "gn:dem":85,
    "gn:feature_class":"P",
    "gn:feature_code":"PPL",
    "gn:name":"Bek\u0101s",
    "gn:population":0,
    "gn:timezone":"Asia/Kolkata",
    "iso:country":"IN",
    "name:ckb_x_preferred":[
        "\u0628\u06ce\u06a9\u06d5\u0633"
    ],
    "name:deu_x_preferred":[
        "Bekas"
    ],
    "name:rus_x_preferred":[
        "\u0411\u0435\u043a\u0430\u0441"
    ],
    "wof:name":"Bekas",
    "wof:placetype":"locality"
},
  "geometry": {"coordinates":[83.59629,25.06857],"type":"Point"}
}