{
  "type": "Feature",
  "properties": {
    "iso:country":"IN",
    "ks:ks_name":"Bishnu Misri Chak",
    "ks:ks_pop":1388,
    "ks:ks_type":"VILLAGE",
    "ks:ks_uagg_main":0,
    "name:eng_x_preferred":[
        "Bishnu Misri Chak"
    ],
    "wof:name":"Bishnu Misri Chak",
    "wof:placetype":"neighbourhood",
    "wof:population":1388
},
  "geometry": {"coordinates":[87.731425,22.309923],"type":"Point"}
}