{
  "type": "Feature",
  "properties": {
    "iso:country":"IN",
    "ks:ks_name":"Jodhpur",
    "ks:ks_pop":515,
    "ks:ks_type":"VILLAGE",
    "ks:ks_uagg_main":0,
    "name:eng_x_preferred":[
        "Jodhpur"
    ],
    "wof:name":"Jodhpur",
    "wof:placetype":"neighbourhood",
    "wof:population":515
},
  "geometry": {"coordinates":[83.83402599999999,23.533903],"type":"Point"}
}