{
  "type": "Feature",
  "properties": {
    "iso:country":"IN",
    "ks:ks_name":"Jamdara",
    "ks:ks_pop":570,
    "ks:ks_type":"HABITATION",
    "name:eng_x_preferred":[
        "Jamdara"
    ],
    "wof:name":"Jamdara",
    "wof:placetype":"locality",
    "wof:population":570
},
  "geometry": {"coordinates":[83.01410199999999,22.841494],"type":"Point"}
}