{
  "type": "Feature",
  "properties": {
    "gn:admin1_code":"16.0",
    "gn:admin2_code":"507.0",
    "gn:asciiname":"Ghatbodi",
    "gn:country_code":"IN",
    "gn:dem":274,
    "gn:feature_class":"P",
    "gn:feature_code":"PPL",
    "gn:name":"Gh\u0101tbod\u012b",
    "gn:population":0,
    "gn:timezone":"Asia/Kolkata",
    "iso:country":"IN",
    "wof:name":"Ghatbodi",
    "wof:placetype":"locality"
},
  "geometry": {"coordinates":[80.12716999999998,21.12917],"type":"Point"}
}