{
  "type": "Feature",
  "properties": {
    "iso:country":"IN",
    "ks:ks_name":"Roziya",
    "ks:ks_pop":1103,
    "ks:ks_type":"VILLAGE",
    "name:eng_x_preferred":[
        "Roziya"
    ],
    "wof:name":"Roziya",
    "wof:placetype":"locality",
    "wof:population":1103
},
  "geometry": {"coordinates":[74.43177300000001,23.081058],"type":"Point"}
}