{
  "type": "Feature",
  "properties": {
    "iso:country":"IN",
    "ks:ks_name":"Eragudipalle",
    "ks:ks_pop":165,
    "ks:ks_type":"HABITATION",
    "name:eng_x_preferred":[
        "Eragudipalle"
    ],
    "wof:name":"Eragudipalle",
    "wof:placetype":"locality",
    "wof:population":165
},
  "geometry": {"coordinates":[78.656184,13.825272],"type":"Point"}
}