{
  "type": "Feature",
  "properties": {
    "gn:admin1_code":"25.0",
    "gn:admin2_code":"606.0",
    "gn:asciiname":"Puliyarambakkam",
    "gn:country_code":"IN",
    "gn:dem":98,
    "gn:feature_class":"P",
    "gn:feature_code":"PPL",
    "gn:name":"Puliyaramb\u0101kkam",
    "gn:population":0,
    "gn:timezone":"Asia/Kolkata",
    "iso:country":"IN",
    "ks:ks_name":"Puliyarampakkam",
    "ks:ks_pop":395,
    "ks:ks_type":"VILLAGE",
    "ks:ks_uagg_main":0,
    "name:eng_x_preferred":[
        "Puliyarampakkam"
    ],
    "wof:name":"Puliyarampakkam",
    "wof:placetype":"neighbourhood",
    "wof:population":395
},
  "geometry": {"coordinates":[79.55756,12.666426],"type":"Point"}
}