{
  "type": "Feature",
  "properties": {
    "iso:country":"IN",
    "ks:ks_alt_nam":"sherichamala",
    "ks:ks_name":"Sherichamala",
    "ks:ks_pop":132,
    "ks:ks_type":"HABITATION",
    "ks:ks_uagg_main":0,
    "name:eng_x_preferred":[
        "Sherichamala"
    ],
    "wof:name":"Sherichamala",
    "wof:placetype":"neighbourhood",
    "wof:population":132
},
  "geometry": {"coordinates":[73.93411999999999,18.404828],"type":"Point"}
}