{
  "type": "Feature",
  "properties": {
    "gn:admin1_code":"19.0",
    "gn:admin2_code":"573.0",
    "gn:asciiname":"Hullukere",
    "gn:country_code":"IN",
    "gn:dem":709,
    "gn:feature_class":"P",
    "gn:feature_code":"PPL",
    "gn:name":"Hullukere",
    "gn:population":0,
    "gn:timezone":"Asia/Kolkata",
    "iso:country":"IN",
    "wof:name":"Hullukere",
    "wof:placetype":"locality"
},
  "geometry": {"coordinates":[76.84569,12.47832],"type":"Point"}
}