{
  "type": "Feature",
  "properties": {
    "iso:country":"IN",
    "ks:ks_name":"Mithupura",
    "ks:ks_pop":8,
    "ks:ks_type":"VILLAGE",
    "name:eng_x_preferred":[
        "Mithupura"
    ],
    "wof:name":"Mithupura",
    "wof:placetype":"locality",
    "wof:population":8
},
  "geometry": {"coordinates":[76.270064,22.499013],"type":"Point"}
}