{
  "type": "Feature",
  "properties": {
    "iso:country":"IN",
    "ks:ks_name":"Barh Awaniya",
    "ks:ks_pop":152,
    "ks:ks_type":"VILLAGE",
    "ks:ks_uagg_main":0,
    "name:eng_x_preferred":[
        "Barh Awaniya"
    ],
    "wof:name":"Barh Awaniya",
    "wof:placetype":"neighbourhood",
    "wof:population":152
},
  "geometry": {"coordinates":[75.531964,26.825247],"type":"Point"}
}