{
  "type": "Feature",
  "properties": {
    "gn:admin1_code":"21.0",
    "gn:admin2_code":"396.0",
    "gn:asciiname":"Dumukupadu",
    "gn:country_code":"IN",
    "gn:dem":642,
    "gn:feature_class":"P",
    "gn:feature_code":"PPL",
    "gn:name":"Dumukup\u0101du",
    "gn:population":0,
    "gn:timezone":"Asia/Kolkata",
    "iso:country":"IN",
    "ks:ks_alt_nam":"Dumukup\u0101du",
    "ks:ks_name":"Dumukupadu",
    "ks:ks_pop":129,
    "ks:ks_type":"VILLAGE",
    "name:eng_x_preferred":[
        "Dumukupadu"
    ],
    "name:eng_x_variant":[
        "Dumukup\u0101du"
    ],
    "wof:name":"Dumukupadu",
    "wof:placetype":"locality",
    "wof:population":129
},
  "geometry": {"coordinates":[83.499962,19.211735],"type":"Point"}
}