{
  "type": "Feature",
  "properties": {
    "iso:country":"IN",
    "ks:ks_name":"Patharia",
    "ks:ks_pop":558,
    "ks:ks_type":"VILLAGE",
    "name:eng_x_preferred":[
        "Patharia"
    ],
    "wof:name":"Patharia",
    "wof:placetype":"locality",
    "wof:population":558
},
  "geometry": {"coordinates":[87.188016,24.557303],"type":"Point"}
}