{
  "type": "Feature",
  "properties": {
    "iso:country":"IN",
    "ks:ks_name":"Umariya",
    "ks:ks_pop":1070,
    "ks:ks_type":"VILLAGE",
    "name:eng_x_preferred":[
        "Umariya"
    ],
    "wof:name":"Umariya",
    "wof:placetype":"locality",
    "wof:population":1070
},
  "geometry": {"coordinates":[81.58244500000001,23.5022],"type":"Point"}
}