{
  "type": "Feature",
  "properties": {
    "gn:admin1_code":"35.0",
    "gn:admin2_code":"419.0",
    "gn:asciiname":"Birampura",
    "gn:country_code":"IN",
    "gn:dem":185,
    "gn:feature_class":"P",
    "gn:feature_code":"PPL",
    "gn:name":"B\u012brampura",
    "gn:population":0,
    "gn:timezone":"Asia/Kolkata",
    "iso:country":"IN",
    "wof:name":"Birampura",
    "wof:placetype":"locality"
},
  "geometry": {"coordinates":[77.89426,26.45511],"type":"Point"}
}