{
  "type": "Feature",
  "properties": {
    "iso:country":"IN",
    "ks:ks_name":"Swargachhira",
    "ks:ks_pop":445,
    "ks:ks_type":"VILLAGE",
    "ks:ks_uagg_main":0,
    "name:eng_x_preferred":[
        "Swargachhira"
    ],
    "wof:name":"Swargachhira",
    "wof:placetype":"neighbourhood",
    "wof:population":445
},
  "geometry": {"coordinates":[86.88038,22.310402],"type":"Point"}
}