{
  "type": "Feature",
  "properties": {
    "iso:country":"IN",
    "ks:ks_name":"Ramireddigaripalle",
    "ks:ks_pop":280,
    "ks:ks_type":"HABITATION",
    "name:eng_x_preferred":[
        "Ramireddigaripalle"
    ],
    "wof:name":"Ramireddigaripalle",
    "wof:placetype":"locality",
    "wof:population":280
},
  "geometry": {"coordinates":[78.374653,13.757079],"type":"Point"}
}