{
  "type": "Feature",
  "properties": {
    "iso:country":"IN",
    "ks:ks_name":"Sunakhandi",
    "ks:ks_pop":650,
    "ks:ks_type":"VILLAGE",
    "name:eng_x_preferred":[
        "Sunakhandi"
    ],
    "wof:name":"Sunakhandi",
    "wof:placetype":"locality",
    "wof:population":650
},
  "geometry": {"coordinates":[84.506573,22.133029],"type":"Point"}
}