{
  "type": "Feature",
  "properties": {
    "iso:country":"IN",
    "ks:ks_name":"Jaiti Chak I",
    "ks:ks_pop":98,
    "ks:ks_type":"VILLAGE",
    "name:eng_x_preferred":[
        "Jaiti Chak I"
    ],
    "wof:name":"Jaiti Chak I",
    "wof:placetype":"locality",
    "wof:population":98
},
  "geometry": {"coordinates":[79.17326199999999,29.995611],"type":"Point"}
}