{
  "type": "Feature",
  "properties": {
    "gn:admin1_code":"36.0",
    "gn:admin2_code":"148.0",
    "gn:asciiname":"Nagla Barepur",
    "gn:country_code":"IN",
    "gn:dem":150,
    "gn:feature_class":"P",
    "gn:feature_code":"PPL",
    "gn:name":"Nagla Barepur",
    "gn:population":0,
    "gn:timezone":"Asia/Kolkata",
    "iso:country":"IN",
    "wof:name":"Nagla Barepur",
    "wof:placetype":"locality"
},
  "geometry": {"coordinates":[79.36948000000002,26.989],"type":"Point"}
}