{
  "type": "Feature",
  "properties": {
    "iso:country":"IN",
    "ks:ks_name":"Rendal",
    "ks:ks_pop":10721,
    "ks:ks_type":"VILLAGE",
    "ks:ks_uagg_main":0,
    "name:eng_x_preferred":[
        "Rendal"
    ],
    "wof:name":"Rendal",
    "wof:placetype":"neighbourhood",
    "wof:population":10721
},
  "geometry": {"coordinates":[74.41742600000001,16.621557],"type":"Point"}
}