{
  "type": "Feature",
  "properties": {
    "gn:admin1_code":"34.0",
    "gn:admin2_code":"236.0",
    "gn:asciiname":"Tahbal Bigha",
    "gn:country_code":"IN",
    "gn:dem":103,
    "gn:feature_class":"P",
    "gn:feature_code":"PPL",
    "gn:name":"Tahbal Bigha",
    "gn:population":0,
    "gn:timezone":"Asia/Kolkata",
    "iso:country":"IN",
    "ks:ks_name":"Tahbal Bigha",
    "ks:ks_pop":127,
    "ks:ks_type":"HABITATION",
    "name:eng_x_preferred":[
        "Tahbal Bigha"
    ],
    "wof:name":"Tahbal Bigha",
    "wof:placetype":"locality",
    "wof:population":127
},
  "geometry": {"coordinates":[85.312349,24.836231],"type":"Point"}
}