{
  "type": "Feature",
  "properties": {
    "iso:country":"IN",
    "ks:ks_name":"Uplawas",
    "ks:ks_pop":736,
    "ks:ks_type":"VILLAGE",
    "name:eng_x_preferred":[
        "Uplawas"
    ],
    "wof:name":"Uplawas",
    "wof:placetype":"locality",
    "wof:population":736
},
  "geometry": {"coordinates":[73.324851,24.766486],"type":"Point"}
}