{
  "type": "Feature",
  "properties": {
    "iso:country":"IN",
    "ks:ks_name":"Andua",
    "ks:ks_pop":765,
    "ks:ks_type":"VILLAGE",
    "ks:ks_uagg_main":0,
    "name:eng_x_preferred":[
        "Andua"
    ],
    "wof:name":"Andua",
    "wof:placetype":"neighbourhood",
    "wof:population":765
},
  "geometry": {"coordinates":[87.57055,22.887973],"type":"Point"}
}