{
  "type": "Feature",
  "properties": {
    "gn:admin1_code":"36.0",
    "gn:admin2_code":"165.0",
    "gn:asciiname":"Kunwarpura Than Singh",
    "gn:country_code":"IN",
    "gn:dem":155,
    "gn:feature_class":"P",
    "gn:feature_code":"PPL",
    "gn:name":"Kunwarpura Th\u0101n Singh",
    "gn:population":0,
    "gn:timezone":"Asia/Kolkata",
    "iso:country":"IN",
    "wof:name":"Kunwarpura Than Singh",
    "wof:placetype":"locality"
},
  "geometry": {"coordinates":[79.09220999999999,26.14213],"type":"Point"}
}