{
  "type": "Feature",
  "properties": {
    "iso:country":"IN",
    "ks:ks_name":"Lorika",
    "ks:ks_pop":710,
    "ks:ks_type":"VILLAGE",
    "name:eng_x_preferred":[
        "Lorika"
    ],
    "wof:name":"Lorika",
    "wof:placetype":"locality",
    "wof:population":710
},
  "geometry": {"coordinates":[85.770139,26.205177],"type":"Point"}
}