{
  "type": "Feature",
  "properties": {
    "gn:admin1_code":"38.0",
    "gn:admin2_code":"347.0",
    "gn:asciiname":"Kanjia",
    "gn:country_code":"IN",
    "gn:dem":402,
    "gn:feature_class":"P",
    "gn:feature_code":"PPL",
    "gn:name":"Kanji\u0101",
    "gn:population":0,
    "gn:timezone":"Asia/Kolkata",
    "iso:country":"IN",
    "wof:name":"Kanjia",
    "wof:placetype":"locality"
},
  "geometry": {"coordinates":[85.20326999999997,24.33117],"type":"Point"}
}