{
  "type": "Feature",
  "properties": {
    "gn:admin1_code":"34.0",
    "gn:admin2_code":"218.0",
    "gn:asciiname":"Hariharpur Lalgarh",
    "gn:country_code":"IN",
    "gn:dem":68,
    "gn:feature_class":"P",
    "gn:feature_code":"PPL",
    "gn:name":"Hariharpur L\u0101lgarh",
    "gn:population":0,
    "gn:timezone":"Asia/Kolkata",
    "iso:country":"IN",
    "ks:ks_alt_nam":"Hariharpur L\u0101lgarh",
    "ks:ks_name":"Hariharpur Lalgarh",
    "ks:ks_pop":2282,
    "ks:ks_type":"VILLAGE",
    "ks:ks_uagg_main":0,
    "name:eng_x_preferred":[
        "Hariharpur Lalgarh"
    ],
    "name:eng_x_variant":[
        "Hariharpur L\u0101lgarh"
    ],
    "wof:name":"Hariharpur Lalgarh",
    "wof:placetype":"neighbourhood",
    "wof:population":2282
},
  "geometry": {"coordinates":[84.53803499999999,26.262399],"type":"Point"}
}