{
  "type": "Feature",
  "properties": {
    "iso:country":"IN",
    "ks:ks_name":"Yusufpur",
    "ks:ks_pop":1308,
    "ks:ks_type":"VILLAGE",
    "ks:ks_uagg_main":0,
    "name:eng_x_preferred":[
        "Yusufpur"
    ],
    "wof:name":"Yusufpur",
    "wof:placetype":"neighbourhood",
    "wof:population":1308
},
  "geometry": {"coordinates":[81.886957,25.587071],"type":"Point"}
}