{
  "type": "Feature",
  "properties": {
    "iso:country":"IN",
    "ks:ks_name":"Bhagat Falia",
    "ks:ks_pop":358,
    "ks:ks_type":"HABITATION",
    "ks:ks_uagg_main":0,
    "name:eng_x_preferred":[
        "Bhagat Falia"
    ],
    "wof:name":"Bhagat Falia",
    "wof:placetype":"neighbourhood",
    "wof:population":358
},
  "geometry": {"coordinates":[73.34916699999999,20.785139],"type":"Point"}
}