{
  "type": "Feature",
  "properties": {
    "iso:country":"IN",
    "ks:ks_name":"East Taichama",
    "ks:ks_pop":347,
    "ks:ks_type":"HABITATION",
    "name:eng_x_preferred":[
        "East Taichama"
    ],
    "wof:name":"East Taichama",
    "wof:placetype":"locality",
    "wof:population":347
},
  "geometry": {"coordinates":[91.501689,23.324411],"type":"Point"}
}