{
  "type": "Feature",
  "properties": {
    "iso:country":"IN",
    "ks:ks_name":"Doddahasala",
    "ks:ks_pop":1070,
    "ks:ks_type":"VILLAGE",
    "name:eng_x_preferred":[
        "Doddahasala"
    ],
    "wof:name":"Doddahasala",
    "wof:placetype":"locality",
    "wof:population":1070
},
  "geometry": {"coordinates":[78.165457,13.090354],"type":"Point"}
}