{
  "type": "Feature",
  "properties": {
    "iso:country":"IN",
    "ks:ks_name":"Walni",
    "ks:ks_pop":92,
    "ks:ks_type":"HABITATION",
    "name:eng_x_preferred":[
        "Walni"
    ],
    "wof:name":"Walni",
    "wof:placetype":"locality",
    "wof:population":92
},
  "geometry": {"coordinates":[79.52046900000001,29.527381],"type":"Point"}
}