{
  "type": "Feature",
  "properties": {
    "gn:admin1_code":"21.0",
    "gn:admin2_code":"398.0",
    "gn:asciiname":"Chapsili",
    "gn:country_code":"IN",
    "gn:dem":895,
    "gn:feature_class":"P",
    "gn:feature_code":"PPL",
    "gn:name":"Chapsili",
    "gn:population":0,
    "gn:timezone":"Asia/Kolkata",
    "iso:country":"IN",
    "wof:name":"Chapsili",
    "wof:placetype":"locality"
},
  "geometry": {"coordinates":[82.79191999999998,18.79495],"type":"Point"}
}