{
  "type": "Feature",
  "properties": {
    "iso:country":"IN",
    "ks:ks_name":"Babuan Tola",
    "ks:ks_pop":154,
    "ks:ks_type":"HABITATION",
    "name:eng_x_preferred":[
        "Babuan Tola"
    ],
    "wof:name":"Babuan Tola",
    "wof:placetype":"locality",
    "wof:population":154
},
  "geometry": {"coordinates":[86.236965,24.500166],"type":"Point"}
}