{
  "type": "Feature",
  "properties": {
    "gn:admin1_code":"36.0",
    "gn:admin2_code":"193.0",
    "gn:asciiname":"Pura Bandhu Ahir",
    "gn:country_code":"IN",
    "gn:dem":75,
    "gn:feature_class":"P",
    "gn:feature_code":"PPL",
    "gn:name":"Pura Bandhu Ahir",
    "gn:population":0,
    "gn:timezone":"Asia/Kolkata",
    "iso:country":"IN",
    "wof:name":"Pura Bandhu Ahir",
    "wof:placetype":"locality"
},
  "geometry": {"coordinates":[83.77061999999999,26.0393],"type":"Point"}
}