{
  "type": "Feature",
  "properties": {
    "iso:country":"IN",
    "ks:ks_name":"Domegadde",
    "ks:ks_pop":89,
    "ks:ks_type":"HABITATION",
    "name:eng_x_preferred":[
        "Domegadde"
    ],
    "wof:name":"Domegadde",
    "wof:placetype":"locality",
    "wof:population":89
},
  "geometry": {"coordinates":[74.818494,14.561731],"type":"Point"}
}