{
  "type": "Feature",
  "properties": {
    "iso:country":"IN",
    "ks:ks_alt_nam":"Thamburan jn",
    "ks:ks_name":"Thamburan Jn",
    "ks:ks_pop":567,
    "ks:ks_type":"HABITATION",
    "name:eng_x_preferred":[
        "Thamburan Jn"
    ],
    "wof:name":"Thamburan Jn",
    "wof:placetype":"locality",
    "wof:population":567
},
  "geometry": {"coordinates":[76.29534700000001,11.364211],"type":"Point"}
}