{
  "type": "Feature",
  "properties": {
    "iso:country":"IN",
    "ks:ks_name":"Sudranuapali",
    "ks:ks_pop":136,
    "ks:ks_type":"VILLAGE",
    "name:eng_x_preferred":[
        "Sudranuapali"
    ],
    "wof:name":"Sudranuapali",
    "wof:placetype":"locality",
    "wof:population":136
},
  "geometry": {"coordinates":[85.01745699999999,19.987665],"type":"Point"}
}