{
  "type": "Feature",
  "properties": {
    "iso:country":"IN",
    "ks:ks_name":"Kunjalimukku",
    "ks:ks_pop":300,
    "ks:ks_type":"HABITATION",
    "name:eng_x_preferred":[
        "Kunjalimukku"
    ],
    "wof:name":"Kunjalimukku",
    "wof:placetype":"locality",
    "wof:population":300
},
  "geometry": {"coordinates":[75.7316,11.51465],"type":"Point"}
}