{
  "type": "Feature",
  "properties": {
    "iso:country":"IN",
    "ks:ks_name":"Modassilpur",
    "ks:ks_type":"VILLAGE",
    "ks:ks_uagg_main":0,
    "name:eng_x_preferred":[
        "Modassilpur"
    ],
    "wof:name":"Modassilpur",
    "wof:placetype":"neighbourhood"
},
  "geometry": {"coordinates":[84.297569,26.108277],"type":"Point"}
}