{
  "type": "Feature",
  "properties": {
    "gn:admin1_code":"19.0",
    "gn:admin2_code":"567.0",
    "gn:asciiname":"Keriyaginadadapuram",
    "gn:country_code":"IN",
    "gn:dem":618,
    "gn:feature_class":"P",
    "gn:feature_code":"PPL",
    "gn:name":"Keriy\u0101ginad\u0101d\u0101puram",
    "gn:population":0,
    "gn:timezone":"Asia/Kolkata",
    "iso:country":"IN",
    "wof:name":"Keriyaginadadapuram",
    "wof:placetype":"locality"
},
  "geometry": {"coordinates":[75.98161,14.77293],"type":"Point"}
}