{
  "type": "Feature",
  "properties": {
    "iso:country":"IN",
    "ks:ks_name":"Chebalaboda",
    "ks:ks_pop":223,
    "ks:ks_type":"HABITATION",
    "name:eng_x_preferred":[
        "Chebalaboda"
    ],
    "wof:name":"Chebalaboda",
    "wof:placetype":"locality",
    "wof:population":223
},
  "geometry": {"coordinates":[72.58806300000001,24.170923],"type":"Point"}
}