{
  "type": "Feature",
  "properties": {
    "iso:country":"IN",
    "ks:ks_name":"Purva Faliya",
    "ks:ks_pop":562,
    "ks:ks_type":"HABITATION",
    "name:eng_x_preferred":[
        "Purva Faliya"
    ],
    "wof:name":"Purva Faliya",
    "wof:placetype":"locality",
    "wof:population":562
},
  "geometry": {"coordinates":[73.901278,23.269222],"type":"Point"}
}