{
  "type": "Feature",
  "properties": {
    "iso:country":"IN",
    "ks:ks_name":"Udakee Mafee",
    "ks:ks_pop":290,
    "ks:ks_type":"VILLAGE",
    "name:eng_x_preferred":[
        "Udakee Mafee"
    ],
    "wof:name":"Udakee Mafee",
    "wof:placetype":"locality",
    "wof:population":290
},
  "geometry": {"coordinates":[80.842067,25.444416],"type":"Point"}
}