{
  "type": "Feature",
  "properties": {
    "gn:admin1_code":"39",
    "gn:admin2_code":"60.0",
    "gn:asciiname":"Udhiar",
    "gn:country_code":"IN",
    "gn:dem":1250,
    "gn:feature_class":"P",
    "gn:feature_code":"PPL",
    "gn:name":"Udhi\u0101r",
    "gn:population":0,
    "gn:timezone":"Asia/Kolkata",
    "iso:country":"IN",
    "wof:name":"Udhiar",
    "wof:placetype":"locality"
},
  "geometry": {"coordinates":[77.85859000000001,30.94148],"type":"Point"}
}