{
  "type": "Feature",
  "properties": {
    "iso:country":"IN",
    "ks:ks_alt_nam":"MALKANIPARA NAYAHAT",
    "ks:ks_name":"Malkanipara Nayahat",
    "ks:ks_pop":625,
    "ks:ks_type":"HABITATION",
    "name:eng_x_preferred":[
        "Malkanipara Nayahat"
    ],
    "wof:name":"Malkanipara Nayahat",
    "wof:placetype":"locality",
    "wof:population":625
},
  "geometry": {"coordinates":[88.713696,26.369318],"type":"Point"}
}