{
  "type": "Feature",
  "properties": {
    "gn:admin1_code":"36.0",
    "gn:admin2_code":"134.0",
    "gn:asciiname":"Salmabad",
    "gn:country_code":"IN",
    "gn:dem":236,
    "gn:feature_class":"P",
    "gn:feature_code":"PPL",
    "gn:name":"S\u0101lm\u0101b\u0101d",
    "gn:population":0,
    "gn:timezone":"Asia/Kolkata",
    "iso:country":"IN",
    "name:nld_x_preferred":[
        "Salmbad"
    ],
    "name:nno_x_preferred":[
        "Salmabad"
    ],
    "wof:name":"Salmabad",
    "wof:placetype":"locality"
},
  "geometry": {"coordinates":[78.16853,29.3793],"type":"Point"}
}