{
  "type": "Feature",
  "properties": {
    "gn:admin1_code":"2.0",
    "gn:admin2_code":"550.0",
    "gn:asciiname":"Kanuru",
    "gn:country_code":"IN",
    "gn:dem":47,
    "gn:feature_class":"P",
    "gn:feature_code":"PPL",
    "gn:name":"K\u0101n\u016bru",
    "gn:population":0,
    "gn:timezone":"Asia/Kolkata",
    "iso:country":"IN",
    "name:ben_x_preferred":[
        "\u0995\u09a8\u09c1\u09b0\u09c1"
    ],
    "name:bpy_x_preferred":[
        "\u0995\u09a8\u09c1\u09b0\u09c1"
    ],
    "name:ceb_x_preferred":[
        "Kanuru"
    ],
    "name:ita_x_preferred":[
        "Kanuru"
    ],
    "name:msa_x_preferred":[
        "Kanuru"
    ],
    "name:new_x_preferred":[
        "\u0915\u0928\u0941\u0930\u0941"
    ],
    "name:nld_x_preferred":[
        "Kanuru"
    ],
    "name:por_x_preferred":[
        "Kanuru"
    ],
    "name:swe_x_preferred":[
        "Kanuru"
    ],
    "name:vie_x_preferred":[
        "Kanuru"
    ],
    "name:zho_x_preferred":[
        "\u5361\u52aa\u9c81"
    ],
    "wof:name":"Kanuru",
    "wof:placetype":"locality"
},
  "geometry": {"coordinates":[79.8942,13.86374],"type":"Point"}
}