{
  "type": "Feature",
  "properties": {
    "iso:country":"IN",
    "name:ara_x_preferred":[
        "\u0633\u0627\u0631\u0627\u0633 \u0628\u0627\u063a"
    ],
    "name:ben_bn_x_preferred":[
        "\u09b8\u09b0\u09b8 \u09ac\u09be\u0997"
    ],
    "name:ben_in_x_preferred":[
        "\u09b8\u09b0\u09b8 \u09ac\u09be\u0997"
    ],
    "name:eng_x_preferred":[
        "Saras Bagh"
    ],
    "name:guj_x_preferred":[
        "\u0ab8\u0ab0\u0ab8 \u0aac\u0abe\u0a97"
    ],
    "name:hin_x_preferred":[
        "\u0938\u0930\u0938 \u092c\u093e\u0917"
    ],
    "name:kan_x_preferred":[
        "\u0cb8\u0cb0\u0cb8\u0ccd"
    ],
    "name:mal_x_preferred":[
        "\u0d38\u0d30\u0d38\u0d4d \u0d2c\u0d3e\u0d17\u0d4d"
    ],
    "name:mar_x_preferred":[
        "\u0938\u093e\u0930\u0938 \u092c\u093e\u0917"
    ],
    "name:pan_x_preferred":[
        "\u0a38\u0a30\u0a38 \u0a2c\u0a3e\u0a17"
    ],
    "name:tam_x_preferred":[
        "\u0b9a\u0bb0\u0bb8\u0bcd \u0baa\u0bbe\u0b95\u0bcd"
    ],
    "name:tel_x_preferred":[
        "\u0c38\u0c30\u0c38\u0c4d"
    ],
    "name:urd_x_preferred":[
        "\u0633\u0627\u0631\u0633 \u0628\u0627\u063a"
    ],
    "qs:gn_adm0_cc":"IN",
    "qs:gn_local":1259229,
    "qs:gn_nam_loc":"Pune, Pune, Maharashtra, IN",
    "qs:gn_namadm1":"16",
    "qs:local_max":2969,
    "qs:local_sum":13446,
    "qs:localhoods":37,
    "qs:name":"Saras Bagh",
    "qs:name_adm0":"India",
    "qs:name_adm1":"Maharashtra",
    "qs:name_adm2":"Pune",
    "qs:name_local":"Pune",
    "qs:photo_max":58,
    "qs:photo_sum":76,
    "qs:placetype":"Suburb",
    "qs:quad_count":5,
    "qs:woe_adm0":23424848,
    "qs:woe_adm1":2345750,
    "qs:woe_adm2":12586544,
    "qs:woe_lau":0,
    "qs:woe_local":2295412,
    "qs:woe_ver":"7.10.0",
    "wof:lang":[
        "eng"
    ],
    "wof:name":"Saras Bagh",
    "wof:placetype":"neighbourhood"
},
  "geometry": {"coordinates":[73.85588,18.501113],"type":"Point"}
}