{
  "type": "Feature",
  "properties": {
    "iso:country":"IN",
    "ks:ks_alt_nam":"BISANPUR",
    "ks:ks_name":"Bisanpur",
    "ks:ks_pop":484,
    "ks:ks_type":"HABITATION",
    "name:eng_x_preferred":[
        "Bisanpur"
    ],
    "wof:name":"Bisanpur",
    "wof:placetype":"locality",
    "wof:population":484
},
  "geometry": {"coordinates":[87.584998,24.456267],"type":"Point"}
}