{
  "type": "Feature",
  "properties": {
    "iso:country":"IN",
    "ks:ks_name":"Kapildharwadi",
    "ks:ks_pop":761,
    "ks:ks_type":"HABITATION",
    "name:eng_x_preferred":[
        "Kapildharwadi"
    ],
    "wof:name":"Kapildharwadi",
    "wof:placetype":"locality",
    "wof:population":761
},
  "geometry": {"coordinates":[75.74473999999999,18.858355],"type":"Point"}
}