{
  "type": "Feature",
  "properties": {
    "iso:country":"IN",
    "ks:ks_name":"Janathagruha",
    "ks:ks_pop":58,
    "ks:ks_type":"HABITATION",
    "ks:ks_uagg_main":0,
    "name:eng_x_preferred":[
        "Janathagruha"
    ],
    "wof:name":"Janathagruha",
    "wof:placetype":"neighbourhood",
    "wof:population":58
},
  "geometry": {"coordinates":[74.845552,14.510804],"type":"Point"}
}