{
  "type": "Feature",
  "properties": {
    "iso:country":"IN",
    "ks:ks_name":"Neyyalabanda",
    "ks:ks_pop":100,
    "ks:ks_type":"HABITATION",
    "name:eng_x_preferred":[
        "Neyyalabanda"
    ],
    "wof:name":"Neyyalabanda",
    "wof:placetype":"locality",
    "wof:population":100
},
  "geometry": {"coordinates":[82.647167,17.960702],"type":"Point"}
}