{
  "type": "Feature",
  "properties": {
    "gn:admin1_code":"36.0",
    "gn:admin2_code":"151.0",
    "gn:asciiname":"Mundia Taluka Pasgawan",
    "gn:country_code":"IN",
    "gn:dem":172,
    "gn:feature_class":"P",
    "gn:feature_code":"PPL",
    "gn:name":"Mundia T\u0101luka Pasgaw\u0101n",
    "gn:population":0,
    "gn:timezone":"Asia/Kolkata",
    "iso:country":"IN",
    "wof:name":"Mundia Taluka Pasgawan",
    "wof:placetype":"locality"
},
  "geometry": {"coordinates":[79.92291999999998,28.31387],"type":"Point"}
}