{
  "type": "Feature",
  "properties": {
    "gn:admin1_code":"40",
    "gn:admin2_code":"533.0",
    "gn:asciiname":"Malkapur",
    "gn:country_code":"IN",
    "gn:dem":404,
    "gn:feature_class":"P",
    "gn:feature_code":"PPL",
    "gn:name":"Malk\u0101pur",
    "gn:population":0,
    "gn:timezone":"Asia/Kolkata",
    "iso:country":"IN",
    "name:hin_x_preferred":[
        "\u092e\u0932\u094d\u0915\u093e\u092a\u0941\u0930"
    ],
    "name:ita_x_preferred":[
        "Malkapur"
    ],
    "name:mar_x_preferred":[
        "\u092e\u0932\u0915\u093e\u092a\u0942\u0930"
    ],
    "name:nld_x_preferred":[
        "Malkapur"
    ],
    "wof:name":"Malkapur",
    "wof:placetype":"locality"
},
  "geometry": {"coordinates":[77.99796000000001,18.59801],"type":"Point"}
}