{
  "type": "Feature",
  "properties": {
    "iso:country":"IN",
    "ks:ks_name":"Arundhatipalem",
    "ks:ks_pop":239,
    "ks:ks_type":"HABITATION",
    "name:eng_x_preferred":[
        "Arundhatipalem"
    ],
    "wof:name":"Arundhatipalem",
    "wof:placetype":"locality",
    "wof:population":239
},
  "geometry": {"coordinates":[82.16531500000001,16.651597],"type":"Point"}
}