{
  "type": "Feature",
  "properties": {
    "iso:country":"IN",
    "ks:ks_name":"Hatuabera",
    "ks:ks_pop":214,
    "ks:ks_type":"VILLAGE",
    "name:eng_x_preferred":[
        "Hatuabera"
    ],
    "wof:name":"Hatuabera",
    "wof:placetype":"locality",
    "wof:population":214
},
  "geometry": {"coordinates":[85.76147,22.916791],"type":"Point"}
}