{
  "type": "Feature",
  "properties": {
    "iso:country":"IN",
    "ks:ks_name":"Deveshpur",
    "ks:ks_pop":189,
    "ks:ks_type":"HABITATION",
    "name:eng_x_preferred":[
        "Deveshpur"
    ],
    "wof:name":"Deveshpur",
    "wof:placetype":"locality",
    "wof:population":189
},
  "geometry": {"coordinates":[82.618692,26.541387],"type":"Point"}
}