{
  "type": "Feature",
  "properties": {
    "iso:country":"IN",
    "ks:ks_name":"Hazarat Nagar",
    "ks:ks_pop":222,
    "ks:ks_type":"VILLAGE",
    "name:eng_x_preferred":[
        "Hazarat Nagar"
    ],
    "wof:name":"Hazarat Nagar",
    "wof:placetype":"locality",
    "wof:population":222
},
  "geometry": {"coordinates":[88.09713000000001,24.981319],"type":"Point"}
}