{
  "type": "Feature",
  "properties": {
    "iso:country":"IN",
    "ks:ks_name":"Survewadi",
    "ks:ks_pop":142,
    "ks:ks_type":"HABITATION",
    "name:eng_x_preferred":[
        "Survewadi"
    ],
    "wof:name":"Survewadi",
    "wof:placetype":"locality",
    "wof:population":142
},
  "geometry": {"coordinates":[73.59222200000001,17.154167],"type":"Point"}
}