{
  "type": "Feature",
  "properties": {
    "gn:admin1_code":"35.0",
    "gn:admin2_code":"427",
    "gn:asciiname":"Nibodiya",
    "gn:country_code":"IN",
    "gn:dem":410,
    "gn:feature_class":"P",
    "gn:feature_code":"PPL",
    "gn:name":"Nibodiya",
    "gn:population":0,
    "gn:timezone":"Asia/Kolkata",
    "iso:country":"IN",
    "ks:ks_name":"Nibodiya",
    "ks:ks_type":"VILLAGE",
    "name:eng_x_preferred":[
        "Nibodiya"
    ],
    "wof:name":"Nibodiya",
    "wof:placetype":"locality"
},
  "geometry": {"coordinates":[78.173573,24.071764],"type":"Point"}
}