{
  "type": "Feature",
  "properties": {
    "gn:admin1_code":"21.0",
    "gn:admin2_code":"396",
    "gn:asciiname":"Dangusurada",
    "gn:country_code":"IN",
    "gn:dem":229,
    "gn:feature_class":"P",
    "gn:feature_code":"PPL",
    "gn:name":"Dangusurada",
    "gn:population":0,
    "gn:timezone":"Asia/Kolkata",
    "iso:country":"IN",
    "wof:name":"Dangusurada",
    "wof:placetype":"locality"
},
  "geometry": {"coordinates":[83.65074,19.60453],"type":"Point"}
}