{
  "type": "Feature",
  "properties": {
    "gn:admin1_code":"36.0",
    "gn:admin2_code":"148",
    "gn:asciiname":"Alampur",
    "gn:country_code":"IN",
    "gn:dem":153,
    "gn:feature_class":"P",
    "gn:feature_code":"PPL",
    "gn:name":"\u0100lampur",
    "gn:population":0,
    "gn:timezone":"Asia/Kolkata",
    "iso:country":"IN",
    "name:ceb_x_preferred":[
        "Alampur"
    ],
    "name:hin_x_preferred":[
        "\u0906\u0932\u092e\u092a\u0941\u0930"
    ],
    "name:swe_x_preferred":[
        "Alampur"
    ],
    "wof:name":"Alampur",
    "wof:placetype":"locality"
},
  "geometry": {"coordinates":[79.36284000000001,27.12805],"type":"Point"}
}