{
  "type": "Feature",
  "properties": {
    "gn:admin1_code":"40.0",
    "gn:admin2_code":"532.0",
    "gn:asciiname":"Guda",
    "gn:country_code":"IN",
    "gn:dem":251,
    "gn:feature_class":"P",
    "gn:feature_code":"PPL",
    "gn:name":"Guda",
    "gn:population":0,
    "gn:timezone":"Asia/Kolkata",
    "iso:country":"IN",
    "name:cat_x_preferred":[
        "Guda"
    ],
    "name:fra_x_preferred":[
        "Guda"
    ],
    "name:ltz_x_preferred":[
        "Guda"
    ],
    "name:nld_x_preferred":[
        "Guda"
    ],
    "name:rus_x_preferred":[
        "\u0413\u0443\u0434\u0430"
    ],
    "wof:name":"Guda",
    "wof:placetype":"locality"
},
  "geometry": {"coordinates":[79.18495,19.4547],"type":"Point"}
}