{
  "type": "Feature",
  "properties": {
    "gn:admin1_code":"36",
    "gn:admin2_code":"176.0",
    "gn:asciiname":"Saidabad",
    "gn:country_code":"IN",
    "gn:dem":120,
    "gn:feature_class":"P",
    "gn:feature_code":"PPL",
    "gn:name":"Said\u0101b\u0101d",
    "gn:population":0,
    "gn:timezone":"Asia/Kolkata",
    "iso:country":"IN",
    "name:ara_x_preferred":[
        "\u0633\u064a\u062f \u0622\u0628\u0627\u062f"
    ],
    "name:ben_bn_x_preferred":[
        "\u09b8\u09be\u09df\u09a6\u09be\u09ac\u09be\u09a6"
    ],
    "name:ben_in_x_preferred":[
        "\u09b8\u09c8\u09a6\u09be\u09ac\u09be\u09a6"
    ],
    "name:fas_x_preferred":[
        "\u0633\u0639\u06cc\u062f\u0622\u0628\u0627\u062f"
    ],
    "name:guj_x_preferred":[
        "\u0ab8\u0ac8\u0aa6\u0abe\u0aac\u0abe\u0aa6"
    ],
    "name:hin_x_preferred":[
        "\u0938\u0948\u0926\u093e\u092c\u093e\u0926"
    ],
    "name:kan_x_preferred":[
        "\u0cb8\u0cc8\u0ca6\u0cbe\u0cac\u0cbe\u0ca6\u0ccd\u200c"
    ],
    "name:mal_x_preferred":[
        "\u0d38\u0d48\u0d26\u0d3e\u0d2c\u0d3e\u0d26\u0d4d"
    ],
    "name:mar_x_preferred":[
        "\u0938\u0948\u0926\u093e\u092c\u093e\u0926"
    ],
    "name:pan_x_preferred":[
        "\u0a38\u0a48\u0a26\u0a3e\u0a2c\u0a3e\u0a26"
    ],
    "name:tam_x_preferred":[
        "\u0b9a\u0bc8\u0ba4\u0bbe\u0baa\u0bcd\u0baa\u0bc7\u0b9f\u0bcd\u0b9f\u0bc8"
    ],
    "name:tel_x_preferred":[
        "\u0c38\u0c48\u0c26\u0c3e\u0c2c\u0c3e\u0c26\u0c4d"
    ],
    "name:urd_x_preferred":[
        "\u0633\u0639\u06cc\u062f \u0622\u0628\u0627\u062f"
    ],
    "wof:name":"Saidabad",
    "wof:placetype":"neighbourhood"
},
  "geometry": {"coordinates":[81.33347000000001,26.92091],"type":"Point"}
}