{
  "type": "Feature",
  "properties": {
    "iso:country":"IN",
    "ks:ks_name":"Keithampatti",
    "ks:ks_pop":112,
    "ks:ks_type":"HABITATION",
    "ks:ks_uagg_main":0,
    "name:eng_x_preferred":[
        "Keithampatti"
    ],
    "wof:name":"Keithampatti",
    "wof:placetype":"locality",
    "wof:population":112
},
  "geometry": {"coordinates":[78.03901399999999,10.916215],"type":"Point"}
}