{
  "type": "Feature",
  "properties": {
    "iso:country":"IN",
    "ks:ks_name":"Chandra",
    "ks:ks_pop":695,
    "ks:ks_type":"VILLAGE",
    "name:eng_x_preferred":[
        "Chandra"
    ],
    "wof:name":"Chandra",
    "wof:placetype":"locality",
    "wof:population":695
},
  "geometry": {"coordinates":[86.818744,22.262734],"type":"Point"}
}