{
  "type": "Feature",
  "properties": {
    "iso:country":"IN",
    "ks:ks_name":"Bhawanipur Bochaha",
    "ks:ks_pop":278,
    "ks:ks_type":"VILLAGE",
    "name:eng_x_preferred":[
        "Bhawanipur Bochaha"
    ],
    "wof:name":"Bhawanipur Bochaha",
    "wof:placetype":"locality",
    "wof:population":278
},
  "geometry": {"coordinates":[87.300656,25.147229],"type":"Point"}
}