{
  "type": "Feature",
  "properties": {
    "iso:country":"IN",
    "ks:ks_name":"Helansar",
    "ks:ks_pop":35,
    "ks:ks_type":"HABITATION",
    "name:eng_x_preferred":[
        "Helansar"
    ],
    "wof:name":"Helansar",
    "wof:placetype":"locality",
    "wof:population":35
},
  "geometry": {"coordinates":[74.826179,14.727222],"type":"Point"}
}