{
  "type": "Feature",
  "properties": {
    "gn:admin1_code":"38.0",
    "gn:admin2_code":"347.0",
    "gn:asciiname":"Gurturi",
    "gn:country_code":"IN",
    "gn:dem":265,
    "gn:feature_class":"P",
    "gn:feature_code":"PPL",
    "gn:name":"Gurtur\u012b",
    "gn:population":0,
    "gn:timezone":"Asia/Kolkata",
    "iso:country":"IN",
    "ks:ks_alt_nam":"Gurtur\u012b",
    "ks:ks_name":"Gurturi",
    "ks:ks_pop":442,
    "ks:ks_type":"VILLAGE",
    "name:eng_x_preferred":[
        "Gurturi"
    ],
    "name:eng_x_variant":[
        "Gurtur\u012b"
    ],
    "wof:name":"Gurturi",
    "wof:placetype":"locality",
    "wof:population":442
},
  "geometry": {"coordinates":[84.461703,24.258255],"type":"Point"}
}