{
  "type": "Feature",
  "properties": {
    "gn:admin1_code":"35",
    "gn:admin2_code":"419.0",
    "gn:asciiname":"Palana",
    "gn:country_code":"IN",
    "gn:dem":166,
    "gn:feature_class":"P",
    "gn:feature_code":"PPL",
    "gn:name":"Palana",
    "gn:population":0,
    "gn:timezone":"Asia/Kolkata",
    "iso:country":"IN",
    "name:ara_x_preferred":[
        "\u0628\u0627\u0644\u0627\u0646\u0627"
    ],
    "name:bel_x_preferred":[
        "\u041f\u0430\u043b\u0430\u043d\u0430"
    ],
    "name:ben_x_preferred":[
        "\u09aa\u09be\u09b2\u09be\u09a8\u09be"
    ],
    "name:bul_x_preferred":[
        "\u041f\u0430\u043b\u0430\u043d\u0430"
    ],
    "name:cat_x_preferred":[
        "Palana"
    ],
    "name:ceb_x_preferred":[
        "Palana"
    ],
    "name:ces_x_preferred":[
        "Palana"
    ],
    "name:deu_x_preferred":[
        "Palana"
    ],
    "name:ell_x_preferred":[
        "\u03a0\u03b1\u03bb\u03ac\u03bd\u03b1"
    ],
    "name:est_x_preferred":[
        "Palana"
    ],
    "name:fas_x_preferred":[
        "\u067e\u0627\u0644\u0627\u0646\u0627"
    ],
    "name:fin_x_preferred":[
        "Palana"
    ],
    "name:fra_x_preferred":[
        "Palana"
    ],
    "name:heb_x_preferred":[
        "\u05e4\u05dc\u05e0\u05d4"
    ],
    "name:hin_x_preferred":[
        "\u092a\u0932\u093e\u0928\u093e"
    ],
    "name:hrv_x_preferred":[
        "Palana"
    ],
    "name:hsb_x_preferred":[
        "Palana"
    ],
    "name:hun_x_preferred":[
        "Palana"
    ],
    "name:ind_x_preferred":[
        "Palana"
    ],
    "name:ita_x_preferred":[
        "Palana"
    ],
    "name:jpn_x_preferred":[
        "\u30d1\u30e9\u30ca"
    ],
    "name:kir_x_preferred":[
        "\u041f\u0430\u043b\u0430\u043d\u0430"
    ],
    "name:kor_x_preferred":[
        "\ud314\ub77c\ub098"
    ],
    "name:lit_x_preferred":[
        "Palana"
    ],
    "name:nld_x_preferred":[
        "Palana"
    ],
    "name:nno_x_preferred":[
        "Palana"
    ],
    "name:oss_x_preferred":[
        "\u041f\u0430\u043b\u0430\u043d\u00e6"
    ],
    "name:pol_x_preferred":[
        "Pa\u0142ana"
    ],
    "name:rus_x_preferred":[
        "\u041f\u0430\u043b\u0430\u043d\u0430"
    ],
    "name:slk_x_preferred":[
        "Palana"
    ],
    "name:spa_x_preferred":[
        "Palana"
    ],
    "name:swe_x_preferred":[
        "Palana"
    ],
    "name:tur_x_preferred":[
        "Palana"
    ],
    "name:twi_x_preferred":[
        "Palana"
    ],
    "name:ukr_x_preferred":[
        "\u041f\u0430\u043b\u0430\u043d\u0430"
    ],
    "name:urd_x_preferred":[
        "\u067e\u0627\u0644\u0627\u0646\u0627"
    ],
    "name:uzb_x_preferred":[
        "Palana"
    ],
    "name:vep_x_preferred":[
        "Palan"
    ],
    "name:vie_x_preferred":[
        "Palana"
    ],
    "name:zho_x_preferred":[
        "\u5e15\u62c9\u7eb3"
    ],
    "wof:name":"Palana",
    "wof:placetype":"locality"
},
  "geometry": {"coordinates":[78.30352000000001,26.68779],"type":"Point"}
}