{
  "type": "Feature",
  "properties": {
    "iso:country":"IN",
    "ks:ks_name":"Sahaebpara",
    "ks:ks_pop":1640,
    "ks:ks_type":"HABITATION",
    "ks:ks_uagg_main":0,
    "name:eng_x_preferred":[
        "Sahaebpara"
    ],
    "wof:name":"Sahaebpara",
    "wof:placetype":"neighbourhood",
    "wof:population":1640
},
  "geometry": {"coordinates":[88.317801,24.057152],"type":"Point"}
}