{
  "type": "Feature",
  "properties": {
    "iso:country":"IN",
    "ks:ks_name":"Bhondada",
    "ks:ks_pop":804,
    "ks:ks_type":"VILLAGE",
    "name:eng_x_preferred":[
        "Bhondada"
    ],
    "wof:name":"Bhondada",
    "wof:placetype":"locality",
    "wof:population":804
},
  "geometry": {"coordinates":[79.102464,29.656237],"type":"Point"}
}