{
  "type": "Feature",
  "properties": {
    "iso:country":"IN",
    "ks:ks_alt_nam":"Tangla PT S",
    "ks:ks_name":"Tangla Pt S",
    "ks:ks_pop":278,
    "ks:ks_type":"HABITATION",
    "name:eng_x_preferred":[
        "Tangla Pt S"
    ],
    "wof:name":"Tangla Pt S",
    "wof:placetype":"locality",
    "wof:population":278
},
  "geometry": {"coordinates":[91.105496,26.477468],"type":"Point"}
}