{
  "type": "Feature",
  "properties": {
    "iso:country":"IN",
    "ks:ks_name":"Dhemagarh No.2",
    "ks:ks_pop":668,
    "ks:ks_type":"VILLAGE",
    "ks:ks_uagg_main":0,
    "name:eng_x_preferred":[
        "Dhemagarh No.2"
    ],
    "wof:name":"Dhemagarh No.2",
    "wof:placetype":"neighbourhood",
    "wof:population":668
},
  "geometry": {"coordinates":[93.94042399999999,27.213019],"type":"Point"}
}