{
  "type": "Feature",
  "properties": {
    "iso:country":"IN",
    "ks:ks_name":"Kandhuli Mari No.2",
    "ks:ks_pop":2761,
    "ks:ks_type":"VILLAGE",
    "ks:ks_uagg_main":0,
    "name:eng_x_preferred":[
        "Kandhuli Mari No.2"
    ],
    "wof:name":"Kandhuli Mari No.2",
    "wof:placetype":"neighbourhood",
    "wof:population":2761
},
  "geometry": {"coordinates":[92.508369,26.499612],"type":"Point"}
}