{
  "type": "Feature",
  "properties": {
    "iso:country":"IN",
    "ks:ks_name":"Kunthahadlu",
    "ks:ks_pop":88,
    "ks:ks_type":"HABITATION",
    "name:eng_x_preferred":[
        "Kunthahadlu"
    ],
    "wof:name":"Kunthahadlu",
    "wof:placetype":"locality",
    "wof:population":88
},
  "geometry": {"coordinates":[75.42214300000001,13.576828],"type":"Point"}
}