{
  "type": "Feature",
  "properties": {
    "gn:admin1_code":"40",
    "gn:admin2_code":"535.0",
    "gn:asciiname":"Loni Kala",
    "gn:country_code":"IN",
    "gn:dem":557,
    "gn:feature_class":"P",
    "gn:feature_code":"PPL",
    "gn:name":"Loni Kala",
    "gn:population":0,
    "gn:timezone":"Asia/Kolkata",
    "iso:country":"IN",
    "wof:name":"Loni Kala",
    "wof:placetype":"neighbourhood"
},
  "geometry": {"coordinates":[77.8263,17.76713],"type":"Point"}
}