{
  "type": "Feature",
  "properties": {
    "iso:country":"IN",
    "ks:ks_name":"Mandunpada",
    "ks:ks_pop":440,
    "ks:ks_type":"HABITATION",
    "name:eng_x_preferred":[
        "Mandunpada"
    ],
    "wof:name":"Mandunpada",
    "wof:placetype":"locality",
    "wof:population":440
},
  "geometry": {"coordinates":[72.97197300000001,19.869212],"type":"Point"}
}