{
  "type": "Feature",
  "properties": {
    "iso:country":"IN",
    "ks:ks_name":"Ambarbhui",
    "ks:ks_pop":425,
    "ks:ks_type":"VILLAGE",
    "name:eng_x_preferred":[
        "Ambarbhui"
    ],
    "wof:name":"Ambarbhui",
    "wof:placetype":"locality",
    "wof:population":425
},
  "geometry": {"coordinates":[72.985769,19.545239],"type":"Point"}
}