{
  "type": "Feature",
  "properties": {
    "iso:country":"IN",
    "ks:ks_name":"Khas",
    "ks:ks_pop":596,
    "ks:ks_type":"HABITATION",
    "ks:ks_uagg_main":0,
    "name:eng_x_preferred":[
        "Khas"
    ],
    "wof:name":"Khas",
    "wof:placetype":"neighbourhood",
    "wof:population":596
},
  "geometry": {"coordinates":[83.921542,26.754703],"type":"Point"}
}