{
  "type": "Feature",
  "properties": {
    "gn:admin1_code":"35",
    "gn:admin2_code":"443.0",
    "gn:asciiname":"Grant Chak",
    "gn:country_code":"IN",
    "gn:dem":417,
    "gn:feature_class":"P",
    "gn:feature_code":"PPL",
    "gn:name":"Gr\u0101nt Chak",
    "gn:population":0,
    "gn:timezone":"Asia/Kolkata",
    "iso:country":"IN",
    "wof:name":"Grant Chak",
    "wof:placetype":"locality"
},
  "geometry": {"coordinates":[77.82189,23.66163],"type":"Point"}
}