{
  "type": "Feature",
  "properties": {
    "gn:admin1_code":"36",
    "gn:admin2_code":"145.0",
    "gn:asciiname":"Nagla Bukta",
    "gn:country_code":"IN",
    "gn:dem":178,
    "gn:feature_class":"P",
    "gn:feature_code":"PPL",
    "gn:name":"Nagla Bukta",
    "gn:population":0,
    "gn:timezone":"Asia/Kolkata",
    "iso:country":"IN",
    "wof:name":"Nagla Bukta",
    "wof:placetype":"locality"
},
  "geometry": {"coordinates":[77.52115999999999,27.41383],"type":"Point"}
}