{
  "type": "Feature",
  "properties": {
    "gn:admin1_code":"36",
    "gn:admin2_code":"188.0",
    "gn:asciiname":"Ratasahi",
    "gn:country_code":"IN",
    "gn:dem":79,
    "gn:feature_class":"P",
    "gn:feature_code":"PPL",
    "gn:name":"Rat\u0101s\u0101hi",
    "gn:population":0,
    "gn:timezone":"Asia/Kolkata",
    "iso:country":"IN",
    "ks:ks_name":"Ratsahi",
    "ks:ks_pop":386,
    "ks:ks_type":"VILLAGE",
    "ks:ks_uagg_main":0,
    "name:eng_x_preferred":[
        "Ratsahi"
    ],
    "wof:name":"Ratsahi",
    "wof:placetype":"neighbourhood",
    "wof:population":386
},
  "geometry": {"coordinates":[83.289545,26.64257],"type":"Point"}
}