{
  "type": "Feature",
  "properties": {
    "iso:country":"IN",
    "ks:ks_name":"Burra Vemula",
    "ks:ks_pop":83,
    "ks:ks_type":"VILLAGE",
    "name:eng_x_preferred":[
        "Burra Vemula"
    ],
    "wof:name":"Burra Vemula",
    "wof:placetype":"locality",
    "wof:population":83
},
  "geometry": {"coordinates":[80.894105,17.836644],"type":"Point"}
}