{
  "type": "Feature",
  "properties": {
    "iso:country":"IN",
    "ks:ks_name":"Leguidhara",
    "ks:ks_pop":0,
    "ks:ks_type":"VILLAGE",
    "name:eng_x_preferred":[
        "Leguidhara"
    ],
    "wof:name":"Leguidhara",
    "wof:placetype":"locality",
    "wof:population":0
},
  "geometry": {"coordinates":[87.215396,22.763505],"type":"Point"}
}