{
  "type": "Feature",
  "properties": {
    "iso:country":"IN",
    "ks:ks_name":"Baiju Bigha",
    "ks:ks_pop":150,
    "ks:ks_type":"HABITATION",
    "name:eng_x_preferred":[
        "Baiju Bigha"
    ],
    "wof:name":"Baiju Bigha",
    "wof:placetype":"locality",
    "wof:population":150
},
  "geometry": {"coordinates":[84.691301,24.935694],"type":"Point"}
}