{
  "type": "Feature",
  "properties": {
    "gn:admin1_code":"38.0",
    "gn:admin2_code":"353.0",
    "gn:asciiname":"Dopahari",
    "gn:country_code":"IN",
    "gn:dem":83,
    "gn:feature_class":"P",
    "gn:feature_code":"PPL",
    "gn:name":"Dopah\u0101ri",
    "gn:population":0,
    "gn:timezone":"Asia/Kolkata",
    "iso:country":"IN",
    "ks:ks_alt_nam":"Dopah\u0101ri",
    "ks:ks_name":"Dopahari",
    "ks:ks_pop":57,
    "ks:ks_type":"VILLAGE",
    "name:eng_x_preferred":[
        "Dopahari"
    ],
    "name:eng_x_variant":[
        "Dopah\u0101ri"
    ],
    "wof:name":"Dopahari",
    "wof:placetype":"locality",
    "wof:population":57
},
  "geometry": {"coordinates":[87.608209,24.731344],"type":"Point"}
}