{
  "type": "Feature",
  "properties": {
    "iso:country":"IN",
    "ks:ks_name":"Charan Ki Garli",
    "ks:ks_pop":731,
    "ks:ks_type":"HABITATION",
    "name:eng_x_preferred":[
        "Charan Ki Garli"
    ],
    "wof:name":"Charan Ki Garli",
    "wof:placetype":"locality",
    "wof:population":731
},
  "geometry": {"coordinates":[74.390033,23.301719],"type":"Point"}
}