{
  "type": "Feature",
  "properties": {
    "iso:country":"IN",
    "ks:ks_name":"Sristipara",
    "ks:ks_pop":541,
    "ks:ks_type":"HABITATION",
    "name:eng_x_preferred":[
        "Sristipara"
    ],
    "wof:name":"Sristipara",
    "wof:placetype":"locality",
    "wof:population":541
},
  "geometry": {"coordinates":[90.55344700000001,26.290435],"type":"Point"}
}