{
  "type": "Feature",
  "properties": {
    "iso:country":"IN",
    "ks:ks_name":"Harijana Colony Padu",
    "ks:ks_pop":240,
    "ks:ks_type":"HABITATION",
    "ks:ks_uagg_main":0,
    "name:eng_x_preferred":[
        "Harijana Colony Padu"
    ],
    "wof:name":"Harijana Colony Padu",
    "wof:placetype":"neighbourhood",
    "wof:population":240
},
  "geometry": {"coordinates":[74.74059,13.223857],"type":"Point"}
}