{
  "type": "Feature",
  "properties": {
    "gn:admin1_code":"36.0",
    "gn:admin2_code":"136.0",
    "gn:asciiname":"Nabiganj",
    "gn:country_code":"IN",
    "gn:dem":194,
    "gn:feature_class":"P",
    "gn:feature_code":"PPL",
    "gn:name":"Nab\u012bg\u0101nj",
    "gn:population":0,
    "gn:timezone":"Asia/Kolkata",
    "iso:country":"IN",
    "ks:ks_alt_nam":"Nab\u012bg\u0101nj",
    "ks:ks_name":"Nabiganj",
    "ks:ks_type":"VILLAGE",
    "name:eng_x_preferred":[
        "Nabiganj"
    ],
    "name:eng_x_variant":[
        "Nab\u012bg\u0101nj"
    ],
    "wof:name":"Nabiganj",
    "wof:placetype":"locality"
},
  "geometry": {"coordinates":[79.008645,28.876475],"type":"Point"}
}