{
  "type": "Feature",
  "properties": {
    "iso:country":"IN",
    "ks:ks_name":"Solaimalaianpatti",
    "ks:ks_pop":245,
    "ks:ks_type":"HABITATION",
    "name:eng_x_preferred":[
        "Solaimalaianpatti"
    ],
    "wof:name":"Solaimalaianpatti",
    "wof:placetype":"locality",
    "wof:population":245
},
  "geometry": {"coordinates":[78.218694,9.146878],"type":"Point"}
}