{
  "type": "Feature",
  "properties": {
    "gn:admin1_code":"28.0",
    "gn:admin2_code":"337.0",
    "gn:asciiname":"Khasdelpur",
    "gn:country_code":"IN",
    "gn:dem":15,
    "gn:feature_class":"P",
    "gn:feature_code":"PPL",
    "gn:name":"Khasdelpur",
    "gn:population":0,
    "gn:timezone":"Asia/Kolkata",
    "iso:country":"IN",
    "ks:ks_name":"Khasdelpur",
    "ks:ks_pop":1992,
    "ks:ks_type":"VILLAGE",
    "ks:ks_uagg_main":0,
    "name:eng_x_preferred":[
        "Khasdelpur"
    ],
    "wof:name":"Khasdelpur",
    "wof:placetype":"locality",
    "wof:population":1992
},
  "geometry": {"coordinates":[88.62160900000001,22.820573],"type":"Point"}
}