{
  "type": "Feature",
  "properties": {
    "iso:country":"IN",
    "ks:ks_name":"Haat Tola",
    "ks:ks_pop":472,
    "ks:ks_type":"HABITATION",
    "name:eng_x_preferred":[
        "Haat Tola"
    ],
    "wof:name":"Haat Tola",
    "wof:placetype":"locality",
    "wof:population":472
},
  "geometry": {"coordinates":[87.985243,26.303666],"type":"Point"}
}