{
  "type": "Feature",
  "properties": {
    "iso:country":"IN",
    "ks:ks_name":"Rampur",
    "ks:ks_pop":0,
    "ks:ks_type":"VILLAGE",
    "name:eng_x_preferred":[
        "Rampur"
    ],
    "wof:name":"Rampur",
    "wof:placetype":"locality",
    "wof:population":0
},
  "geometry": {"coordinates":[92.40104100000001,24.455647],"type":"Point"}
}