{
  "type": "Feature",
  "properties": {
    "gn:admin1_code":"9.0",
    "gn:admin2_code":"472",
    "gn:asciiname":"Akrund",
    "gn:country_code":"IN",
    "gn:dem":113,
    "gn:feature_class":"P",
    "gn:feature_code":"PPL",
    "gn:name":"Akrund",
    "gn:population":0,
    "gn:timezone":"Asia/Kolkata",
    "iso:country":"IN",
    "name:fas_x_preferred":[
        "\u0627\u06a9\u0631\u0627\u0646\u062f"
    ],
    "name:guj_x_preferred":[
        "\u0a85\u0a95\u0abe\u0ab0\u0ac1\u0a82\u0aa6"
    ],
    "wof:name":"Akrund",
    "wof:placetype":"locality"
},
  "geometry": {"coordinates":[73.1297,23.28565],"type":"Point"}
}