{
  "type": "Feature",
  "properties": {
    "gn:admin1_code":"9.0",
    "gn:admin2_code":"472",
    "gn:asciiname":"Akrund",
    "gn:country_code":"IN",
    "gn:dem":113,
    "gn:feature_class":"P",
    "gn:feature_code":"PPL",
    "gn:name":"Akrund",
    "gn:population":0,
    "gn:timezone":"Asia/Kolkata",
    "iso:country":"IN",
    "wof:name":"Akrund",
    "wof:placetype":"locality"
},
  "geometry": {"coordinates":[73.1297,23.28565],"type":"Point"}
}