{
  "type": "Feature",
  "properties": {
    "gn:admin1_code":"36",
    "gn:admin2_code":"158.0",
    "gn:asciiname":"Purwa Lalu",
    "gn:country_code":"IN",
    "gn:dem":119,
    "gn:feature_class":"P",
    "gn:feature_code":"PPL",
    "gn:name":"Purwa L\u0101lu",
    "gn:population":0,
    "gn:timezone":"Asia/Kolkata",
    "iso:country":"IN",
    "wof:name":"Purwa Lalu",
    "wof:placetype":"neighbourhood"
},
  "geometry": {"coordinates":[80.86947000000001,26.08504],"type":"Point"}
}