{
  "type": "Feature",
  "properties": {
    "iso:country":"IN",
    "ks:ks_name":"Suliamari",
    "ks:ks_pop":215,
    "ks:ks_type":"VILLAGE",
    "name:eng_x_preferred":[
        "Suliamari"
    ],
    "wof:name":"Suliamari",
    "wof:placetype":"locality",
    "wof:population":215
},
  "geometry": {"coordinates":[83.04773900000001,18.684465],"type":"Point"}
}