{
  "type": "Feature",
  "properties": {
    "gn:admin1_code":"23.0",
    "gn:admin2_code":"43.0",
    "gn:asciiname":"Banwala Sadhu",
    "gn:country_code":"IN",
    "gn:dem":182,
    "gn:feature_class":"P",
    "gn:feature_code":"PPL",
    "gn:name":"Banw\u0101la S\u0101dhu",
    "gn:population":0,
    "gn:timezone":"Asia/Kolkata",
    "iso:country":"IN",
    "name:und_x_variant":[
        "Banw\u0101la S\u0101dhu",
        "Dew\u0101n Khera"
    ],
    "wof:name":"Banwala Sadhu",
    "wof:placetype":"locality"
},
  "geometry": {"coordinates":[74.00464000000002,30.1156],"type":"Point"}
}