{
  "type": "Feature",
  "properties": {
    "gn:admin1_code":"3.0",
    "gn:admin2_code":"320.0",
    "gn:asciiname":"Madhyam Dakumgaon",
    "gn:country_code":"IN",
    "gn:dem":89,
    "gn:feature_class":"P",
    "gn:feature_code":"PPL",
    "gn:name":"Madhyam Dakumgaon",
    "gn:population":0,
    "gn:timezone":"Asia/Kolkata",
    "iso:country":"IN",
    "wof:name":"Madhyam Dakumgaon",
    "wof:placetype":"locality"
},
  "geometry": {"coordinates":[90.41016,26.64001],"type":"Point"}
}