{
  "type": "Feature",
  "properties": {
    "iso:country":"IN",
    "ks:ks_name":"Adobai",
    "ks:ks_pop":48,
    "ks:ks_type":"VILLAGE",
    "name:eng_x_preferred":[
        "Adobai"
    ],
    "wof:name":"Adobai",
    "wof:placetype":"locality",
    "wof:population":48
},
  "geometry": {"coordinates":[83.690748,19.085342],"type":"Point"}
}