{
  "type": "Feature",
  "properties": {
    "iso:country":"IN",
    "ks:ks_name":"Brahmanpara",
    "ks:ks_pop":267,
    "ks:ks_type":"HABITATION",
    "name:eng_x_preferred":[
        "Brahmanpara"
    ],
    "wof:name":"Brahmanpara",
    "wof:placetype":"locality",
    "wof:population":267
},
  "geometry": {"coordinates":[81.95513699999999,19.417282],"type":"Point"}
}