{
  "type": "Feature",
  "properties": {
    "iso:country":"IN",
    "ks:ks_name":"Bidhpura",
    "ks:ks_pop":1175,
    "ks:ks_type":"VILLAGE",
    "ks:ks_uagg_main":0,
    "name:eng_x_preferred":[
        "Bidhpura"
    ],
    "wof:name":"Bidhpura",
    "wof:placetype":"neighbourhood",
    "wof:population":1175
},
  "geometry": {"coordinates":[79.202067,28.809456],"type":"Point"}
}