{
  "type": "Feature",
  "properties": {
    "iso:country":"IN",
    "ks:ks_alt_nam":"Darbar faliya",
    "ks:ks_name":"Darbar Faliya",
    "ks:ks_pop":440,
    "ks:ks_type":"HABITATION",
    "name:eng_x_preferred":[
        "Darbar Faliya"
    ],
    "wof:name":"Darbar Faliya",
    "wof:placetype":"locality",
    "wof:population":440
},
  "geometry": {"coordinates":[73.340889,20.48375],"type":"Point"}
}