{
  "type": "Feature",
  "properties": {
    "iso:country":"IN",
    "ks:ks_name":"Padarbhari",
    "ks:ks_pop":382,
    "ks:ks_type":"HABITATION",
    "ks:ks_uagg_main":0,
    "name:eng_x_preferred":[
        "Padarbhari"
    ],
    "wof:name":"Padarbhari",
    "wof:placetype":"neighbourhood",
    "wof:population":382
},
  "geometry": {"coordinates":[87.898118,21.79941],"type":"Point"}
}