{
  "type": "Feature",
  "properties": {
    "iso:country":"IN",
    "ks:ks_name":"Adivaram",
    "ks:ks_pop":1910,
    "ks:ks_type":"HABITATION",
    "name:eng_x_preferred":[
        "Adivaram"
    ],
    "wof:name":"Adivaram",
    "wof:placetype":"locality",
    "wof:population":1910
},
  "geometry": {"coordinates":[76.36332,10.066346],"type":"Point"}
}