{
  "type": "Feature",
  "properties": {
    "iso:country":"IN",
    "ks:ks_name":"Alamangalam",
    "ks:ks_pop":128,
    "ks:ks_type":"HABITATION",
    "name:eng_x_preferred":[
        "Alamangalam"
    ],
    "wof:name":"Alamangalam",
    "wof:placetype":"locality",
    "wof:population":128
},
  "geometry": {"coordinates":[79.073578,9.935179],"type":"Point"}
}