{
  "type": "Feature",
  "properties": {
    "iso:country":"IN",
    "ks:ks_name":"Dhudhawan",
    "ks:ks_pop":176,
    "ks:ks_type":"HABITATION",
    "name:eng_x_preferred":[
        "Dhudhawan"
    ],
    "wof:name":"Dhudhawan",
    "wof:placetype":"locality",
    "wof:population":176
},
  "geometry": {"coordinates":[73.488694,18.358387],"type":"Point"}
}