{
  "type": "Feature",
  "properties": {
    "gn:admin1_code":"12.0",
    "gn:admin2_code":"6.0",
    "gn:asciiname":"Gura Sarkari",
    "gn:country_code":"IN",
    "gn:dem":1953,
    "gn:feature_class":"P",
    "gn:feature_code":"PPL",
    "gn:name":"Gura Sark\u0101ri",
    "gn:population":0,
    "gn:timezone":"Asia/Kolkata",
    "iso:country":"IN",
    "wof:name":"Gura Sarkari",
    "wof:placetype":"locality"
},
  "geometry": {"coordinates":[74.45659000000001,33.45017],"type":"Point"}
}