{
  "type": "Feature",
  "properties": {
    "iso:country":"IN",
    "ks:ks_name":"Bornoloni No1",
    "ks:ks_pop":905,
    "ks:ks_type":"HABITATION",
    "name:eng_x_preferred":[
        "Bornoloni No1"
    ],
    "wof:name":"Bornoloni No1",
    "wof:placetype":"locality",
    "wof:population":905
},
  "geometry": {"coordinates":[94.28767999999999,26.990493],"type":"Point"}
}