{
  "type": "Feature",
  "properties": {
    "iso:country":"IN",
    "ks:ks_name":"Bikladih",
    "ks:ks_pop":133,
    "ks:ks_type":"HABITATION",
    "name:eng_x_preferred":[
        "Bikladih"
    ],
    "wof:name":"Bikladih",
    "wof:placetype":"locality",
    "wof:population":133
},
  "geometry": {"coordinates":[87.020658,24.329743],"type":"Point"}
}