{
  "type": "Feature",
  "properties": {
    "gn:admin1_code":"7.0",
    "gn:admin2_code":"097",
    "gn:asciiname":"Mitraon",
    "gn:country_code":"IN",
    "gn:dem":218,
    "gn:feature_class":"P",
    "gn:feature_code":"PPL",
    "gn:name":"Mitr\u0101on",
    "gn:population":0,
    "gn:timezone":"Asia/Kolkata",
    "iso:country":"IN",
    "wof:name":"Mitraon",
    "wof:placetype":"neighbourhood"
},
  "geometry": {"coordinates":[76.94598000000001,28.60623],"type":"Point"}
}