{
  "type": "Feature",
  "properties": {
    "gn:admin1_code":"7.0",
    "gn:admin2_code":"097",
    "gn:asciiname":"Mitraon",
    "gn:country_code":"IN",
    "gn:dem":218,
    "gn:feature_class":"P",
    "gn:feature_code":"PPL",
    "gn:name":"Mitr\u0101on",
    "gn:population":0,
    "gn:timezone":"Asia/Kolkata",
    "iso:country":"IN",
    "name:ara_x_preferred":[
        "\u0645\u064a\u062a\u0631\u0627\u0648\u0646"
    ],
    "name:ben_bn_x_preferred":[
        "\u09ae\u09bf\u09a4\u09cd\u09b0\u09be\u0993\u09a8"
    ],
    "name:ben_in_x_preferred":[
        "\u09ae\u09bf\u09a4\u09cd\u09b0\u09be\u0993\u09a8"
    ],
    "name:guj_x_preferred":[
        "\u0aae\u0abf\u0aa4\u0acd\u0ab0\u0acb"
    ],
    "name:hin_x_preferred":[
        "\u092e\u093f\u0924\u094d\u0930\u093e\u0913\u0902"
    ],
    "name:kan_x_preferred":[
        "\u0cae\u0cbf\u0ca4\u0ccd\u0cb0\u0ccb"
    ],
    "name:mal_x_preferred":[
        "\u0d2e\u0d3f\u0d24\u0d4d\u0d30\u0d4b\u0d7a"
    ],
    "name:mar_x_preferred":[
        "\u092e\u093f\u0924\u094d\u0930\u093e\u0913\u0928"
    ],
    "name:pan_x_preferred":[
        "\u0a2e\u0a3f\u0a24\u0a30\u0a3e\u0a13\u0a02"
    ],
    "name:tam_x_preferred":[
        "\u0bae\u0bbf\u0ba4\u0bcd\u0bb0\u0bcc\u0ba9\u0bcd"
    ],
    "name:tel_x_preferred":[
        "\u0c2e\u0c3f\u0c24\u0c4d\u0c30\u0c3e\u0c13\u0c02"
    ],
    "name:urd_x_preferred":[
        "\u0645\u062a\u0631\u0627\u0624\u06ba"
    ],
    "wof:name":"Mitraon",
    "wof:placetype":"neighbourhood"
},
  "geometry": {"coordinates":[76.94598000000001,28.60623],"type":"Point"}
}