{
  "type": "Feature",
  "properties": {
    "iso:country":"IN",
    "ks:ks_name":"Banjarpally Thurka",
    "ks:ks_pop":532,
    "ks:ks_type":"HABITATION",
    "name:eng_x_preferred":[
        "Banjarpally Thurka"
    ],
    "wof:name":"Banjarpally Thurka",
    "wof:placetype":"locality",
    "wof:population":532
},
  "geometry": {"coordinates":[78.737938,17.963369],"type":"Point"}
}