{
  "type": "Feature",
  "properties": {
    "iso:country":"IN",
    "ks:ks_name":"Kamkar Tola",
    "ks:ks_pop":73,
    "ks:ks_type":"HABITATION",
    "name:eng_x_preferred":[
        "Kamkar Tola"
    ],
    "wof:name":"Kamkar Tola",
    "wof:placetype":"locality",
    "wof:population":73
},
  "geometry": {"coordinates":[84.25563,26.107061],"type":"Point"}
}