{
  "type": "Feature",
  "properties": {
    "iso:country":"IN",
    "ks:ks_name":"Champadighi",
    "ks:ks_pop":375,
    "ks:ks_type":"VILLAGE",
    "name:eng_x_preferred":[
        "Champadighi"
    ],
    "wof:name":"Champadighi",
    "wof:placetype":"locality",
    "wof:population":375
},
  "geometry": {"coordinates":[88.34651700000001,25.107349],"type":"Point"}
}