{
  "type": "Feature",
  "properties": {
    "iso:country":"IN",
    "ks:ks_name":"Bara Muhuldiha",
    "ks:ks_pop":1171,
    "ks:ks_type":"VILLAGE",
    "name:eng_x_preferred":[
        "Bara Muhuldiha"
    ],
    "wof:name":"Bara Muhuldiha",
    "wof:placetype":"locality",
    "wof:population":1171
},
  "geometry": {"coordinates":[85.693153,22.233203],"type":"Point"}
}