{
  "type": "Feature",
  "properties": {
    "iso:country":"IN",
    "ks:ks_name":"Satheamanahally",
    "ks:ks_pop":368,
    "ks:ks_type":"HABITATION",
    "name:eng_x_preferred":[
        "Satheamanahally"
    ],
    "wof:name":"Satheamanahally",
    "wof:placetype":"locality",
    "wof:population":368
},
  "geometry": {"coordinates":[76.446108,13.355373],"type":"Point"}
}