{
  "type": "Feature",
  "properties": {
    "iso:country":"IN",
    "ks:ks_name":"Sarpanch Tola",
    "ks:ks_pop":311,
    "ks:ks_type":"HABITATION",
    "ks:ks_uagg_main":0,
    "name:eng_x_preferred":[
        "Sarpanch Tola"
    ],
    "wof:name":"Sarpanch Tola",
    "wof:placetype":"neighbourhood",
    "wof:population":311
},
  "geometry": {"coordinates":[87.72238900000001,26.137276],"type":"Point"}
}