{
  "type": "Feature",
  "properties": {
    "iso:country":"IN",
    "ks:ks_name":"Vanchira Family Group",
    "ks:ks_pop":91,
    "ks:ks_type":"HABITATION",
    "name:eng_x_preferred":[
        "Vanchira Family Group"
    ],
    "wof:name":"Vanchira Family Group",
    "wof:placetype":"locality",
    "wof:population":91
},
  "geometry": {"coordinates":[75.711944,12.314167],"type":"Point"}
}