{
  "type": "Feature",
  "properties": {
    "gn:admin1_code":"34.0",
    "gn:admin2_code":"207.0",
    "gn:asciiname":"Dhata",
    "gn:country_code":"IN",
    "gn:dem":81,
    "gn:feature_class":"P",
    "gn:feature_code":"PPL",
    "gn:name":"Dh\u0101ta",
    "gn:population":0,
    "gn:timezone":"Asia/Kolkata",
    "iso:country":"IN",
    "wof:name":"Dhata",
    "wof:placetype":"neighbourhood"
},
  "geometry": {"coordinates":[86.32885,26.56018],"type":"Point"}
}