{
  "type": "Feature",
  "properties": {
    "iso:country":"IN",
    "ks:ks_name":"Ambaghanta",
    "ks:ks_pop":255,
    "ks:ks_type":"VILLAGE",
    "name:eng_x_preferred":[
        "Ambaghanta"
    ],
    "wof:name":"Ambaghanta",
    "wof:placetype":"locality",
    "wof:population":255
},
  "geometry": {"coordinates":[72.749469,24.084627],"type":"Point"}
}