{
  "type": "Feature",
  "properties": {
    "iso:country":"IN",
    "ks:ks_name":"Pachra Bansi Arazi",
    "ks:ks_pop":0,
    "ks:ks_type":"VILLAGE",
    "name:eng_x_preferred":[
        "Pachra Bansi Arazi"
    ],
    "wof:name":"Pachra Bansi Arazi",
    "wof:placetype":"locality",
    "wof:population":0
},
  "geometry": {"coordinates":[85.302367,26.382181],"type":"Point"}
}