{
  "type": "Feature",
  "properties": {
    "gn:admin1_code":"24",
    "gn:admin2_code":"118.0",
    "gn:asciiname":"Mala ka Gudha",
    "gn:country_code":"IN",
    "gn:dem":401,
    "gn:feature_class":"P",
    "gn:feature_code":"PPL",
    "gn:name":"M\u0101la ka G\u016bdha",
    "gn:population":0,
    "gn:timezone":"Asia/Kolkata",
    "iso:country":"IN",
    "wof:name":"Mala ka Gudha",
    "wof:placetype":"locality"
},
  "geometry": {"coordinates":[73.88070999999999,25.70035],"type":"Point"}
}