{
  "type": "Feature",
  "properties": {
    "iso:country":"IN",
    "ks:ks_name":"Tanechaparu",
    "ks:ks_pop":4987,
    "ks:ks_type":"HABITATION",
    "name:eng_x_preferred":[
        "Tanechaparu"
    ],
    "wof:name":"Tanechaparu",
    "wof:placetype":"locality",
    "wof:population":4987
},
  "geometry": {"coordinates":[72.075183,23.980598],"type":"Point"}
}