{
  "type": "Feature",
  "properties": {
    "gn:admin1_code":"37",
    "gn:admin2_code":"414.0",
    "gn:asciiname":"Amgaon",
    "gn:country_code":"IN",
    "gn:dem":629,
    "gn:feature_class":"P",
    "gn:feature_code":"PPL",
    "gn:name":"\u0100mgaon",
    "gn:population":0,
    "gn:timezone":"Asia/Kolkata",
    "iso:country":"IN",
    "name:cat_x_preferred":[
        "Amgaon"
    ],
    "name:fas_x_preferred":[
        "\u0627\u0645\u06af\u0627\u0626\u0648\u0646"
    ],
    "name:urd_x_preferred":[
        "\u0622\u0645 \u06af\u0627\u0624\u06ba"
    ],
    "wof:name":"Amgaon",
    "wof:placetype":"locality"
},
  "geometry": {"coordinates":[81.76848000000003,20.00189],"type":"Point"}
}