{
  "type": "Feature",
  "properties": {
    "iso:country":"IN",
    "ks:ks_name":"Jhajhor",
    "ks:ks_pop":1210,
    "ks:ks_type":"VILLAGE",
    "name:eng_x_preferred":[
        "Jhajhor"
    ],
    "wof:name":"Jhajhor",
    "wof:placetype":"locality",
    "wof:population":1210
},
  "geometry": {"coordinates":[74.428454,23.821962],"type":"Point"}
}