{
  "type": "Feature",
  "properties": {
    "gn:admin1_code":"16.0",
    "gn:admin2_code":"508.0",
    "gn:asciiname":"Laskar",
    "gn:country_code":"IN",
    "gn:dem":247,
    "gn:feature_class":"P",
    "gn:feature_code":"PPL",
    "gn:name":"Laskar",
    "gn:population":0,
    "gn:timezone":"Asia/Kolkata",
    "iso:country":"IN",
    "ks:ks_name":"Lashkar",
    "ks:ks_pop":181,
    "ks:ks_type":"VILLAGE",
    "name:eng_x_preferred":[
        "Lashkar"
    ],
    "name:eng_x_variant":[
        "Laskar"
    ],
    "wof:name":"Lashkar",
    "wof:placetype":"locality",
    "wof:population":181
},
  "geometry": {"coordinates":[80.69105,19.46872],"type":"Point"}
}