{
  "type": "Feature",
  "properties": {
    "gn:admin1_code":"13.0",
    "gn:admin2_code":"588.0",
    "gn:asciiname":"Belluru",
    "gn:country_code":"IN",
    "gn:dem":87,
    "gn:feature_class":"P",
    "gn:feature_code":"PPL",
    "gn:name":"Bell\u016bru",
    "gn:population":0,
    "gn:timezone":"Asia/Kolkata",
    "iso:country":"IN",
    "wof:name":"Belluru",
    "wof:placetype":"locality"
},
  "geometry": {"coordinates":[75.17544000000002,12.58503],"type":"Point"}
}