{
  "type": "Feature",
  "properties": {
    "gn:admin1_code":"23.0",
    "gn:admin2_code":"048",
    "gn:asciiname":"Ghagga",
    "gn:country_code":"IN",
    "gn:dem":236,
    "gn:feature_class":"P",
    "gn:feature_code":"PPL",
    "gn:name":"Ghagga",
    "gn:population":0,
    "gn:timezone":"Asia/Kolkata",
    "iso:country":"IN",
    "name:ben_x_preferred":[
        "\u0998\u09be\u0997\u09cd\u0997\u09be"
    ],
    "name:bpy_x_preferred":[
        "\u0998\u09be\u0997\u09cd\u0997\u09be"
    ],
    "name:ita_x_preferred":[
        "Ghagga"
    ],
    "name:msa_x_preferred":[
        "Ghagga"
    ],
    "name:new_x_preferred":[
        "\u0918\u0917\u094d\u0917\u093e"
    ],
    "name:nld_x_preferred":[
        "Ghagga"
    ],
    "name:pan_x_preferred":[
        "\u0a18\u0a71\u0a17\u0a3e"
    ],
    "name:por_x_preferred":[
        "Ghagga"
    ],
    "name:spa_x_preferred":[
        "Ghagga"
    ],
    "name:und_x_variant":[
        "Ghaggar",
        "Chagga",
        "Chagghar"
    ],
    "name:vie_x_preferred":[
        "Ghagga"
    ],
    "wof:name":"Ghagga",
    "wof:placetype":"locality"
},
  "geometry": {"coordinates":[76.10408000000002,30.01975],"type":"Point"}
}