{
  "type": "Feature",
  "properties": {
    "gn:admin1_code":"23.0",
    "gn:admin2_code":"048",
    "gn:asciiname":"Ghagga",
    "gn:country_code":"IN",
    "gn:dem":236,
    "gn:feature_class":"P",
    "gn:feature_code":"PPL",
    "gn:name":"Ghagga",
    "gn:population":0,
    "gn:timezone":"Asia/Kolkata",
    "iso:country":"IN",
    "name:und_x_variant":[
        "Ghaggar",
        "Chagga",
        "Chagghar",
        "Ghagga"
    ],
    "wof:name":"Ghagga",
    "wof:placetype":"locality"
},
  "geometry": {"coordinates":[76.10408000000002,30.01975],"type":"Point"}
}