{
  "type": "Feature",
  "properties": {
    "gn:admin1_code":"38.0",
    "gn:admin2_code":"358.0",
    "gn:asciiname":"Chenrabar",
    "gn:country_code":"IN",
    "gn:dem":213,
    "gn:feature_class":"P",
    "gn:feature_code":"PPL",
    "gn:name":"Chenr\u0101b\u0101r",
    "gn:population":0,
    "gn:timezone":"Asia/Kolkata",
    "iso:country":"IN",
    "wof:name":"Chenrabar",
    "wof:placetype":"locality"
},
  "geometry": {"coordinates":[84.05346999999998,24.07819],"type":"Point"}
}