{
  "type": "Feature",
  "properties": {
    "iso:country":"IN",
    "ks:ks_name":"Kammaragoyyi",
    "ks:ks_pop":71,
    "ks:ks_type":"HABITATION",
    "name:eng_x_preferred":[
        "Kammaragoyyi"
    ],
    "wof:name":"Kammaragoyyi",
    "wof:placetype":"locality",
    "wof:population":71
},
  "geometry": {"coordinates":[82.39733200000001,18.056809],"type":"Point"}
}