{
  "type": "Feature",
  "properties": {
    "iso:country":"IN",
    "ks:ks_name":"1 KWD",
    "ks:ks_pop":142,
    "ks:ks_type":"VILLAGE",
    "name:eng_x_preferred":[
        "1 KWD"
    ],
    "wof:name":"1 KWD",
    "wof:placetype":"locality",
    "wof:population":142
},
  "geometry": {"coordinates":[74.352397,29.31944],"type":"Point"}
}