{
  "type": "Feature",
  "properties": {
    "iso:country":"IN",
    "ks:ks_name":"Karubaru",
    "ks:ks_pop":97,
    "ks:ks_type":"HABITATION",
    "name:eng_x_preferred":[
        "Karubaru"
    ],
    "wof:name":"Karubaru",
    "wof:placetype":"locality",
    "wof:population":97
},
  "geometry": {"coordinates":[83.49094599999999,19.928014],"type":"Point"}
}