{
  "type": "Feature",
  "properties": {
    "gn:admin1_code":"13",
    "gn:admin2_code":"594.0",
    "gn:asciiname":"Ollur",
    "gn:country_code":"IN",
    "gn:dem":20,
    "gn:feature_class":"P",
    "gn:feature_code":"PPL",
    "gn:name":"Oll\u016br",
    "gn:population":0,
    "gn:timezone":"Asia/Kolkata",
    "iso:country":"IN",
    "name:mal_x_preferred":[
        "\u0d12\u0d32\u0d4d\u0d32\u0d42\u0d7c"
    ],
    "name:tam_x_preferred":[
        "\u0b92\u0bb2\u0bcd\u0bb2\u0bc2\u0bb0\u0bcd"
    ],
    "name:und_x_variant":[
        "Oll\u016br"
    ],
    "wof:name":"Ollur",
    "wof:placetype":"neighbourhood"
},
  "geometry": {"coordinates":[76.23333,10.46667],"type":"Point"}
}