{
  "type": "Feature",
  "properties": {
    "gn:admin1_code":"16.0",
    "gn:admin2_code":"509.0",
    "gn:asciiname":"Arwi",
    "gn:country_code":"IN",
    "gn:dem":180,
    "gn:feature_class":"P",
    "gn:feature_code":"PPL",
    "gn:name":"Arwi",
    "gn:population":0,
    "gn:timezone":"Asia/Kolkata",
    "iso:country":"IN",
    "name:ara_x_preferred":[
        "\u062a\u0627\u0645\u064a\u0644\u064a\u0629 \u0639\u0631\u0628\u064a\u0629"
    ],
    "name:est_x_preferred":[
        "Arwi"
    ],
    "name:ind_x_preferred":[
        "Arwi"
    ],
    "name:ita_x_preferred":[
        "Lingua arwi"
    ],
    "name:nor_x_preferred":[
        "Arwi"
    ],
    "name:rus_x_preferred":[
        "\u0410\u0440\u0432\u0438"
    ],
    "name:sin_x_preferred":[
        "\u0d85\u0dbb\u0dca\u0dc0\u0dd2"
    ],
    "name:swe_x_preferred":[
        "Arwi"
    ],
    "name:tha_x_preferred":[
        "\u0e2d\u0e31\u0e01\u0e29\u0e23\u0e2d\u0e32\u0e23\u0e4c\u0e27\u0e35"
    ],
    "name:ukr_x_preferred":[
        "\u0410\u0440\u0432\u0456"
    ],
    "wof:name":"Arwi",
    "wof:placetype":"locality"
},
  "geometry": {"coordinates":[79.49664,19.63686],"type":"Point"}
}