{
  "type": "Feature",
  "properties": {
    "gn:admin1_code":"21",
    "gn:admin2_code":"395.0",
    "gn:asciiname":"Ampara",
    "gn:country_code":"IN",
    "gn:dem":261,
    "gn:feature_class":"P",
    "gn:feature_code":"PPL",
    "gn:name":"\u0100mp\u0101ra",
    "gn:population":0,
    "gn:timezone":"Asia/Kolkata",
    "iso:country":"IN",
    "name:ceb_x_preferred":[
        "Ampara"
    ],
    "name:fas_x_preferred":[
        "\u0627\u0645\u067e\u0631\u0627"
    ],
    "name:fra_x_preferred":[
        "Ampara"
    ],
    "name:guj_x_preferred":[
        "\u0a85\u0aae\u0acd\u0aaa\u0abe\u0ab0\u0abe"
    ],
    "name:hin_x_preferred":[
        "\u0905\u092e\u094d\u092a\u093e\u0930\u093e"
    ],
    "name:hun_x_preferred":[
        "Ampara"
    ],
    "name:ind_x_preferred":[
        "Ampara"
    ],
    "name:ita_x_preferred":[
        "Ampara"
    ],
    "name:jpn_x_preferred":[
        "\u30a2\u30f3\u30d1\u30fc\u30e9"
    ],
    "name:nld_x_preferred":[
        "Ampara"
    ],
    "name:pol_x_preferred":[
        "Ampara"
    ],
    "name:sin_x_preferred":[
        "\u0d85\u0db8\u0dca\u0db4\u0dcf\u0dbb"
    ],
    "name:spa_x_preferred":[
        "Ampara"
    ],
    "name:swe_x_preferred":[
        "Ampara"
    ],
    "name:tam_x_preferred":[
        "\u0b85\u0bae\u0bcd\u0baa\u0bbe\u0bb1\u0bc8"
    ],
    "name:ukr_x_preferred":[
        "\u0410\u043c\u043f\u0430\u0440\u0430"
    ],
    "name:urd_x_preferred":[
        "\u0627\u0645\u067e\u0627\u0631\u0627"
    ],
    "wof:name":"Ampara",
    "wof:placetype":"locality"
},
  "geometry": {"coordinates":[83.11189,19.87671],"type":"Point"}
}