{
  "type": "Feature",
  "properties": {
    "iso:country":"IN",
    "ks:ks_name":"Addigera",
    "ks:ks_pop":236,
    "ks:ks_type":"VILLAGE",
    "name:eng_x_preferred":[
        "Addigera"
    ],
    "wof:name":"Addigera",
    "wof:placetype":"locality",
    "wof:population":236
},
  "geometry": {"coordinates":[74.723168,15.148196],"type":"Point"}
}