{
  "type": "Feature",
  "properties": {
    "iso:country":"IN",
    "ks:ks_name":"Noojadi",
    "ks:ks_pop":694,
    "ks:ks_type":"HABITATION",
    "name:eng_x_preferred":[
        "Noojadi"
    ],
    "wof:name":"Noojadi",
    "wof:placetype":"locality",
    "wof:population":694
},
  "geometry": {"coordinates":[74.663112,13.78829],"type":"Point"}
}