{
  "type": "Feature",
  "properties": {
    "iso:country":"IN",
    "ks:ks_name":"Shaulan",
    "ks:ks_pop":782,
    "ks:ks_type":"VILLAGE",
    "ks:ks_uagg_main":0,
    "name:eng_x_preferred":[
        "Shaulan"
    ],
    "wof:name":"Shaulan",
    "wof:placetype":"neighbourhood",
    "wof:population":782
},
  "geometry": {"coordinates":[87.699116,22.540058],"type":"Point"}
}