{
  "type": "Feature",
  "properties": {
    "iso:country":"IN",
    "ks:ks_name":"Pure Mitai",
    "ks:ks_pop":200,
    "ks:ks_type":"HABITATION",
    "name:eng_x_preferred":[
        "Pure Mitai"
    ],
    "wof:name":"Pure Mitai",
    "wof:placetype":"locality",
    "wof:population":200
},
  "geometry": {"coordinates":[81.998633,26.0938],"type":"Point"}
}