{
  "type": "Feature",
  "properties": {
    "gn:admin1_code":"19.0",
    "gn:admin2_code":"568.0",
    "gn:asciiname":"Kadokal",
    "gn:country_code":"IN",
    "gn:dem":601,
    "gn:feature_class":"P",
    "gn:feature_code":"PPL",
    "gn:name":"Kadokal",
    "gn:population":0,
    "gn:timezone":"Asia/Kolkata",
    "iso:country":"IN",
    "wof:name":"Kadokal",
    "wof:placetype":"locality"
},
  "geometry": {"coordinates":[75.56276,13.84192],"type":"Point"}
}