{
  "type": "Feature",
  "properties": {
    "iso:country":"IN",
    "ks:ks_name":"32 PTP",
    "ks:ks_pop":64,
    "ks:ks_type":"VILLAGE",
    "name:eng_x_preferred":[
        "32 PTP"
    ],
    "wof:name":"32 PTP",
    "wof:placetype":"locality",
    "wof:population":64
},
  "geometry": {"coordinates":[74.179778,29.797575],"type":"Point"}
}