{
  "type": "Feature",
  "properties": {
    "iso:country":"IN",
    "ks:ks_name":"Hasanabad",
    "ks:ks_pop":512,
    "ks:ks_type":"VILLAGE",
    "name:eng_x_preferred":[
        "Hasanabad"
    ],
    "wof:name":"Hasanabad",
    "wof:placetype":"locality",
    "wof:population":512
},
  "geometry": {"coordinates":[75.121593,20.404869],"type":"Point"}
}