{
  "type": "Feature",
  "properties": {
    "iso:country":"IN",
    "ks:ks_name":"Barod",
    "ks:ks_pop":2030,
    "ks:ks_type":"HABITATION",
    "name:eng_x_preferred":[
        "Barod"
    ],
    "wof:name":"Barod",
    "wof:placetype":"locality",
    "wof:population":2030
},
  "geometry": {"coordinates":[73.75514200000001,23.90735],"type":"Point"}
}