{
  "type": "Feature",
  "properties": {
    "iso:country":"IN",
    "ks:ks_name":"Yeguva Madigapalli",
    "ks:ks_pop":144,
    "ks:ks_type":"HABITATION",
    "ks:ks_uagg_main":0,
    "name:eng_x_preferred":[
        "Yeguva Madigapalli"
    ],
    "wof:name":"Yeguva Madigapalli",
    "wof:placetype":"neighbourhood",
    "wof:population":144
},
  "geometry": {"coordinates":[78.262249,14.211261],"type":"Point"}
}