{
  "type": "Feature",
  "properties": {
    "iso:country":"IN",
    "ks:ks_name":"Kundrampatty",
    "ks:ks_pop":117,
    "ks:ks_type":"HABITATION",
    "name:eng_x_preferred":[
        "Kundrampatty"
    ],
    "wof:name":"Kundrampatty",
    "wof:placetype":"locality",
    "wof:population":117
},
  "geometry": {"coordinates":[77.40357400000001,10.324646],"type":"Point"}
}