{
  "type": "Feature",
  "properties": {
    "gn:admin1_code":"40.0",
    "gn:admin2_code":"534.0",
    "gn:asciiname":"Nizamabad",
    "gn:country_code":"IN",
    "gn:dem":390,
    "gn:feature_class":"P",
    "gn:feature_code":"PPL",
    "gn:name":"Niz\u0101m\u0101b\u0101d",
    "gn:population":0,
    "gn:timezone":"Asia/Kolkata",
    "iso:country":"IN",
    "name:ara_x_preferred":[
        "\u0646\u0638\u0627\u0645 \u0623\u0628\u0627\u062f"
    ],
    "name:azb_x_preferred":[
        "\u0646\u0638\u0627\u0645\u200c\u0622\u0628\u0627\u062f"
    ],
    "name:aze_x_preferred":[
        "Nizamabad"
    ],
    "name:bih_x_preferred":[
        "\u0928\u093f\u091c\u093e\u092e\u093e\u092c\u093e\u0926"
    ],
    "name:ceb_x_preferred":[
        "Nizamabad"
    ],
    "name:fas_x_preferred":[
        "\u0646\u0638\u0627\u0645\u200c\u0622\u0628\u0627\u062f"
    ],
    "name:ita_x_preferred":[
        "Nizamabad"
    ],
    "name:new_x_preferred":[
        "\u0928\u093f\u091c\u093e\u092e\u093e\u0935\u093e\u0926"
    ],
    "name:nld_x_preferred":[
        "Nizamabad"
    ],
    "name:pam_x_preferred":[
        "Nizamabad"
    ],
    "name:pol_x_preferred":[
        "Nizamabad"
    ],
    "name:rus_x_preferred":[
        "\u041d\u0438\u0437\u0430\u043c\u0430\u0431\u0430\u0434"
    ],
    "name:san_x_preferred":[
        "\u0928\u093f\u091c\u093e\u092e\u093e\u092c\u093e\u0926-\u0928\u0917\u0930\u092e\u094d"
    ],
    "name:swe_x_preferred":[
        "Nizamabad"
    ],
    "wof:name":"Nizamabad",
    "wof:placetype":"locality"
},
  "geometry": {"coordinates":[78.73277,18.4818],"type":"Point"}
}