{
  "type": "Feature",
  "properties": {
    "iso:country":"IN",
    "ks:ks_alt_nam":"KASHI RAM KI DHANI",
    "ks:ks_name":"Kashi Ram Ki Dhani",
    "ks:ks_pop":30,
    "ks:ks_type":"HABITATION",
    "name:eng_x_preferred":[
        "Kashi Ram Ki Dhani"
    ],
    "wof:name":"Kashi Ram Ki Dhani",
    "wof:placetype":"locality",
    "wof:population":30
},
  "geometry": {"coordinates":[74.295723,29.075508],"type":"Point"}
}