{
  "type": "Feature",
  "properties": {
    "iso:country":"IN",
    "ks:ks_alt_nam":"B\u0101lidiha",
    "ks:ks_name":"Balidiha",
    "ks:ks_type":"VILLAGE",
    "name:eng_x_preferred":[
        "Balidiha"
    ],
    "name:eng_x_variant":[
        "B\u0101lidiha"
    ],
    "wof:name":"Balidiha",
    "wof:placetype":"locality"
},
  "geometry": {"coordinates":[85.599749,21.578338],"type":"Point"}
}