{
  "type": "Feature",
  "properties": {
    "iso:country":"IN",
    "ks:ks_name":"Aralimaradaapalya",
    "ks:ks_pop":26,
    "ks:ks_type":"HABITATION",
    "name:eng_x_preferred":[
        "Aralimaradaapalya"
    ],
    "wof:name":"Aralimaradaapalya",
    "wof:placetype":"locality",
    "wof:population":26
},
  "geometry": {"coordinates":[77.117458,12.924233],"type":"Point"}
}