{
  "type": "Feature",
  "properties": {
    "gn:admin1_code":"39",
    "gn:asciiname":"Kandal",
    "gn:country_code":"IN",
    "gn:dem":1649,
    "gn:feature_class":"P",
    "gn:feature_code":"PPL",
    "gn:name":"Kandal",
    "gn:population":0,
    "gn:timezone":"Asia/Kolkata",
    "iso:country":"IN",
    "wof:name":"Kandal",
    "wof:placetype":"locality"
},
  "geometry": {"coordinates":[77.7462,30.86972],"type":"Point"}
}