{
  "type": "Feature",
  "properties": {
    "iso:country":"IN",
    "ks:ks_name":"Sahabazpur",
    "ks:ks_pop":2476,
    "ks:ks_type":"VILLAGE",
    "ks:ks_uagg_main":0,
    "name:eng_x_preferred":[
        "Sahabazpur"
    ],
    "wof:name":"Sahabazpur",
    "wof:placetype":"neighbourhood",
    "wof:population":2476
},
  "geometry": {"coordinates":[88.239625,24.429305],"type":"Point"}
}