{
  "type": "Feature",
  "properties": {
    "gn:admin1_code":"34",
    "gn:admin2_code":"208.0",
    "gn:asciiname":"Narhi",
    "gn:country_code":"IN",
    "gn:dem":59,
    "gn:feature_class":"P",
    "gn:feature_code":"PPL",
    "gn:name":"Narhi",
    "gn:population":0,
    "gn:timezone":"Asia/Kolkata",
    "iso:country":"IN",
    "ks:ks_alt_nam":"NARHI",
    "ks:ks_name":"Narhi",
    "ks:ks_pop":650,
    "ks:ks_type":"HABITATION",
    "name:eng_x_preferred":[
        "Narhi"
    ],
    "wof:name":"Narhi",
    "wof:placetype":"locality",
    "wof:population":650
},
  "geometry": {"coordinates":[86.651843,26.224706],"type":"Point"}
}