{
  "type": "Feature",
  "properties": {
    "iso:country":"IN",
    "ks:ks_name":"Kakardahi",
    "ks:ks_pop":2302,
    "ks:ks_type":"VILLAGE",
    "ks:ks_uagg_main":0,
    "name:eng_x_preferred":[
        "Kakardahi"
    ],
    "wof:name":"Kakardahi",
    "wof:placetype":"neighbourhood",
    "wof:population":2302
},
  "geometry": {"coordinates":[80.124195,26.532458],"type":"Point"}
}