{
  "type": "Feature",
  "properties": {
    "iso:country":"IN",
    "ks:ks_name":"Mousadha",
    "ks:ks_pop":1195,
    "ks:ks_type":"HABITATION",
    "name:eng_x_preferred":[
        "Mousadha"
    ],
    "wof:name":"Mousadha",
    "wof:placetype":"locality",
    "wof:population":1195
},
  "geometry": {"coordinates":[86.792343,20.851839],"type":"Point"}
}