{
  "type": "Feature",
  "properties": {
    "iso:country":"IN",
    "ks:ks_name":"Lachankunda",
    "ks:ks_pop":33,
    "ks:ks_type":"VILLAGE",
    "name:eng_x_preferred":[
        "Lachankunda"
    ],
    "wof:name":"Lachankunda",
    "wof:placetype":"locality",
    "wof:population":33
},
  "geometry": {"coordinates":[86.899276,22.904776],"type":"Point"}
}