{
  "type": "Feature",
  "properties": {
    "iso:country":"IN",
    "ks:ks_alt_nam":"Ghat tola",
    "ks:ks_name":"Ghat Tola",
    "ks:ks_pop":2454,
    "ks:ks_type":"HABITATION",
    "name:eng_x_preferred":[
        "Ghat Tola"
    ],
    "wof:name":"Ghat Tola",
    "wof:placetype":"locality",
    "wof:population":2454
},
  "geometry": {"coordinates":[87.495369,26.101467],"type":"Point"}
}