{
  "type": "Feature",
  "properties": {
    "iso:country":"IN",
    "ks:ks_name":"Pindari",
    "ks:ks_pop":174,
    "ks:ks_type":"VILLAGE",
    "name:eng_x_preferred":[
        "Pindari"
    ],
    "wof:name":"Pindari",
    "wof:placetype":"locality",
    "wof:population":174
},
  "geometry": {"coordinates":[87.36794,24.437292],"type":"Point"}
}