{
  "type": "Feature",
  "properties": {
    "iso:country":"IN",
    "ks:ks_name":"Garopara",
    "ks:ks_pop":319,
    "ks:ks_type":"HABITATION",
    "name:eng_x_preferred":[
        "Garopara"
    ],
    "wof:name":"Garopara",
    "wof:placetype":"locality",
    "wof:population":319
},
  "geometry": {"coordinates":[90.613362,26.050642],"type":"Point"}
}