{
  "type": "Feature",
  "properties": {
    "gn:admin1_code":"2.0",
    "gn:admin2_code":"553.0",
    "gn:asciiname":"Chigicherla",
    "gn:country_code":"IN",
    "gn:dem":378,
    "gn:feature_class":"P",
    "gn:feature_code":"PPL",
    "gn:name":"Chigicherla",
    "gn:population":0,
    "gn:timezone":"Asia/Kolkata",
    "iso:country":"IN",
    "wof:name":"Chigicherla",
    "wof:placetype":"locality"
},
  "geometry": {"coordinates":[77.68040000000001,14.51908],"type":"Point"}
}