{
  "type": "Feature",
  "properties": {
    "iso:country":"IN",
    "ks:ks_alt_nam":"MALME WASTI",
    "ks:ks_name":"Malme Wasti",
    "ks:ks_pop":78,
    "ks:ks_type":"HABITATION",
    "name:eng_x_preferred":[
        "Malme Wasti"
    ],
    "wof:name":"Malme Wasti",
    "wof:placetype":"locality",
    "wof:population":78
},
  "geometry": {"coordinates":[74.921009,17.131672],"type":"Point"}
}