{
  "type": "Feature",
  "properties": {
    "iso:country":"IN",
    "ks:ks_name":"Rohidaswdi",
    "ks:ks_pop":29,
    "ks:ks_type":"HABITATION",
    "name:eng_x_preferred":[
        "Rohidaswdi"
    ],
    "wof:name":"Rohidaswdi",
    "wof:placetype":"locality",
    "wof:population":29
},
  "geometry": {"coordinates":[73.544747,17.691433],"type":"Point"}
}