{
  "type": "Feature",
  "properties": {
    "gn:admin1_code":"36",
    "gn:admin2_code":"163.0",
    "gn:asciiname":"Madaripur",
    "gn:country_code":"IN",
    "gn:dem":139,
    "gn:feature_class":"P",
    "gn:feature_code":"PPL",
    "gn:name":"Mad\u0101r\u012bpur",
    "gn:population":0,
    "gn:timezone":"Asia/Kolkata",
    "iso:country":"IN",
    "wof:name":"Madaripur",
    "wof:placetype":"locality"
},
  "geometry": {"coordinates":[79.74731,26.31648],"type":"Point"}
}