{
  "type": "Feature",
  "properties": {
    "iso:country":"IN",
    "ks:ks_name":"Dharampur",
    "ks:ks_pop":0,
    "ks:ks_type":"VILLAGE",
    "name:eng_x_preferred":[
        "Dharampur"
    ],
    "wof:name":"Dharampur",
    "wof:placetype":"locality",
    "wof:population":0
},
  "geometry": {"coordinates":[81.27546700000001,27.857157],"type":"Point"}
}