{
  "type": "Feature",
  "properties": {
    "iso:country":"IN",
    "ks:ks_name":"Kudda",
    "ks:ks_pop":1031,
    "ks:ks_type":"HABITATION",
    "name:eng_x_preferred":[
        "Kudda"
    ],
    "wof:name":"Kudda",
    "wof:placetype":"locality",
    "wof:population":1031
},
  "geometry": {"coordinates":[85.394567,22.995688],"type":"Point"}
}