{
  "type": "Feature",
  "properties": {
    "gn:admin1_code":"39.0",
    "gn:admin2_code":"66.0",
    "gn:asciiname":"Sinmoria Jaibasa",
    "gn:country_code":"IN",
    "gn:dem":1213,
    "gn:feature_class":"P",
    "gn:feature_code":"PPL",
    "gn:name":"Sinmoria Jaib\u0101sa",
    "gn:population":0,
    "gn:timezone":"Asia/Kolkata",
    "iso:country":"IN",
    "wof:name":"Sinmoria Jaibasa",
    "wof:placetype":"locality"
},
  "geometry": {"coordinates":[79.43689999999999,29.3574],"type":"Point"}
}