{
  "type": "Feature",
  "properties": {
    "iso:country":"IN",
    "ks:ks_name":"Chak Ladhana",
    "ks:ks_pop":28,
    "ks:ks_type":"HABITATION",
    "name:eng_x_preferred":[
        "Chak Ladhana"
    ],
    "wof:name":"Chak Ladhana",
    "wof:placetype":"locality",
    "wof:population":28
},
  "geometry": {"coordinates":[75.327039,27.455353],"type":"Point"}
}