{
  "type": "Feature",
  "properties": {
    "iso:country":"IN",
    "ks:ks_name":"Gollagudem",
    "ks:ks_pop":873,
    "ks:ks_type":"HABITATION",
    "name:eng_x_preferred":[
        "Gollagudem"
    ],
    "wof:name":"Gollagudem",
    "wof:placetype":"locality",
    "wof:population":873
},
  "geometry": {"coordinates":[81.95908,16.419099],"type":"Point"}
}