{
  "type": "Feature",
  "properties": {
    "iso:country":"IN",
    "ks:ks_name":"Ansi",
    "ks:ks_pop":0,
    "ks:ks_type":"VILLAGE",
    "name:eng_x_preferred":[
        "Ansi"
    ],
    "wof:name":"Ansi",
    "wof:placetype":"locality",
    "wof:population":0
},
  "geometry": {"coordinates":[83.649862,25.270065],"type":"Point"}
}