{
  "type": "Feature",
  "properties": {
    "gn:admin1_code":"21.0",
    "gn:admin2_code":"399",
    "gn:asciiname":"Koiraputtu",
    "gn:country_code":"IN",
    "gn:dem":274,
    "gn:feature_class":"P",
    "gn:feature_code":"PPL",
    "gn:name":"Koir\u0101puttu",
    "gn:population":0,
    "gn:timezone":"Asia/Kolkata",
    "iso:country":"IN",
    "name:und_x_variant":[
        "Koir\u0101puttu",
        "Khairaput"
    ],
    "wof:name":"Koiraputtu",
    "wof:placetype":"locality"
},
  "geometry": {"coordinates":[82.23200000000001,18.48152],"type":"Point"}
}