{
  "type": "Feature",
  "properties": {
    "gn:country":"IN",
    "gn:fcode":"PPL",
    "gn:population":14398,
    "iso:country":"IN",
    "name:bpy_x_preferred":[
        "\u0995\u09be\u09b0\u09bf\u09af\u09bc\u09be\u09aa\u09be\u09a4\u09cd\u09a4\u09bf"
    ],
    "name:bul_x_preferred":[
        "\u041a\u0430\u0440\u0438\u0430\u043f\u0430\u0442\u0438"
    ],
    "name:ceb_x_preferred":[
        "Kariapatti"
    ],
    "name:eng_x_preferred":[
        "Kariapatti"
    ],
    "name:fra_x_preferred":[
        "Kariapatti"
    ],
    "name:hin_x_preferred":[
        "\u0915\u093e\u0930\u093f\u092f\u093e\u092a\u091f\u094d\u091f\u0940"
    ],
    "name:ita_x_preferred":[
        "Kariapatti"
    ],
    "name:msa_x_preferred":[
        "Kariapatti"
    ],
    "name:nan_x_preferred":[
        "Kariapatti"
    ],
    "name:new_x_preferred":[
        "\u0915\u0930\u093f\u092f\u093e\u092a\u091f\u094d\u091f\u0940"
    ],
    "name:nld_x_preferred":[
        "Kariapatti"
    ],
    "name:por_x_preferred":[
        "Kariapatti"
    ],
    "name:swe_x_preferred":[
        "Kariapatti"
    ],
    "name:tam_x_preferred":[
        "\u0b95\u0bbe\u0bb0\u0bbf\u0baf\u0bbe\u0baa\u0bcd\u0baa\u0b9f\u0bcd\u0b9f\u0bbf"
    ],
    "name:vie_x_preferred":[
        "Kariapatti"
    ],
    "name:zho_x_preferred":[
        "\u5361\u91cc\u4e9a\u5e15\u8482"
    ],
    "qs:name":"Kumarapatti",
    "qs:name_adm0":"India",
    "qs:name_adm1":"Tamil Nadu",
    "qs:photos_9r":0,
    "qs:photos_sr":0,
    "qs:placetype":"Town",
    "qs:pop_sr":"6",
    "wof:name":"Kumarapatti",
    "wof:placetype":"locality",
    "wof:population":14398
},
  "geometry": {"coordinates":[78.09992,9.67505],"type":"Point"}
}