{
  "type": "Feature",
  "properties": {
    "gn:admin1_code":"21.0",
    "gn:admin2_code":"370.0",
    "gn:asciiname":"Dumerpali",
    "gn:country_code":"IN",
    "gn:dem":236,
    "gn:feature_class":"P",
    "gn:feature_code":"PPL",
    "gn:name":"Dumerpali",
    "gn:population":0,
    "gn:timezone":"Asia/Kolkata",
    "iso:country":"IN",
    "wof:name":"Dumerpali",
    "wof:placetype":"locality"
},
  "geometry": {"coordinates":[83.36358,21.30804],"type":"Point"}
}