{
  "type": "Feature",
  "properties": {
    "gn:admin1_code":"09",
    "gn:admin2_code":"469.0",
    "gn:asciiname":"Mahmadpur",
    "gn:country_code":"IN",
    "gn:dem":209,
    "gn:feature_class":"P",
    "gn:feature_code":"PPL",
    "gn:name":"Mahmadpur",
    "gn:population":0,
    "gn:timezone":"Asia/Kolkata",
    "iso:country":"IN",
    "wof:name":"Mahmadpur",
    "wof:placetype":"locality"
},
  "geometry": {"coordinates":[72.51989,24.05485],"type":"Point"}
}