{
  "type": "Feature",
  "properties": {
    "iso:country":"IN",
    "ks:ks_name":"Bivaram Para",
    "ks:ks_pop":311,
    "ks:ks_type":"HABITATION",
    "name:eng_x_preferred":[
        "Bivaram Para"
    ],
    "wof:name":"Bivaram Para",
    "wof:placetype":"locality",
    "wof:population":311
},
  "geometry": {"coordinates":[91.72233799999999,23.536914],"type":"Point"}
}