{
  "type": "Feature",
  "properties": {
    "gn:admin1_code":"36",
    "gn:admin2_code":"144.0",
    "gn:asciiname":"Tikri Khurd",
    "gn:country_code":"IN",
    "gn:dem":181,
    "gn:feature_class":"P",
    "gn:feature_code":"PPL",
    "gn:name":"T\u012bkri Khurd",
    "gn:population":0,
    "gn:timezone":"Asia/Kolkata",
    "iso:country":"IN",
    "name:ara_x_preferred":[
        "\u062a\u0643\u0631\u064a \u062e\u0648\u0631\u062f"
    ],
    "name:ben_bn_x_preferred":[
        "\u099f\u09bf\u0995\u09b0\u09bf \u0996\u09c1\u09b0\u09cd\u09a6"
    ],
    "name:ben_in_x_preferred":[
        "\u099f\u09bf\u0995\u09b0\u09bf \u0996\u09c1\u09b0\u09cd\u09a6"
    ],
    "name:guj_x_preferred":[
        "\u0a9f\u0ac0\u0a95\u0ab0\u0ac0 \u0a96\u0ac1\u0ab0\u0acd\u0aa6"
    ],
    "name:hin_x_preferred":[
        "\u0924\u093f\u0915\u0930\u0940 \u0916\u0941\u0930\u094d\u0926"
    ],
    "name:kan_x_preferred":[
        "\u0c9f\u0cbf\u0c95\u0ccd\u0cb0\u0cbf \u0c96\u0cc1\u0cb0\u0ccd\u0ca6\u0ccd"
    ],
    "name:mal_x_preferred":[
        "\u0d24\u0d3f\u0d15\u0d4d\u0d30\u0d3f \u0d16\u0d41\u0d7c\u0d26\u0d4d"
    ],
    "name:mar_x_preferred":[
        "\u0924\u093f\u0915\u094d\u0930\u0940 \u0916\u0941\u0930\u094d\u0926"
    ],
    "name:pan_x_preferred":[
        "\u0a1f\u0a3f\u0a15\u0a30\u0a40 \u0a16\u0a41\u0a30\u0a26"
    ],
    "name:tam_x_preferred":[
        "\u0ba4\u0bbf\u0b95\u0bcd\u0bb0\u0bbf \u0b95\u0bc1\u0bb0\u0bcd\u0ba4\u0bcd"
    ],
    "name:tel_x_preferred":[
        "\u0c1f\u0c3f\u0c15\u0c4d\u0c30\u0c3f \u0c16\u0c41\u0c30\u0c4d\u0c26\u0c4d"
    ],
    "name:urd_x_preferred":[
        "\u062a\u06a9\u0691\u06cc \u062e\u0631\u062f"
    ],
    "wof:name":"Tikri Khurd",
    "wof:placetype":"locality"
},
  "geometry": {"coordinates":[78.39078000000001,27.73201],"type":"Point"}
}