{
  "type": "Feature",
  "properties": {
    "iso:country":"IN",
    "ks:ks_name":"Teliabandi",
    "ks:ks_pop":187,
    "ks:ks_type":"VILLAGE",
    "name:eng_x_preferred":[
        "Teliabandi"
    ],
    "wof:name":"Teliabandi",
    "wof:placetype":"locality",
    "wof:population":187
},
  "geometry": {"coordinates":[87.044141,24.090482],"type":"Point"}
}