{
  "type": "Feature",
  "properties": {
    "gn:admin1_code":"23.0",
    "gn:admin2_code":"50.0",
    "gn:asciiname":"Chan Chak",
    "gn:country_code":"IN",
    "gn:dem":213,
    "gn:feature_class":"P",
    "gn:feature_code":"PPL",
    "gn:name":"Ch\u0101n Chak",
    "gn:population":0,
    "gn:timezone":"Asia/Kolkata",
    "iso:country":"IN",
    "name:cat_x_preferred":[
        "Chan Chak"
    ],
    "name:zho_x_preferred":[
        "\u9673\u7b56"
    ],
    "wof:name":"Chan Chak",
    "wof:placetype":"locality"
},
  "geometry": {"coordinates":[74.73378000000002,31.19018],"type":"Point"}
}