{
  "type": "Feature",
  "properties": {
    "iso:country":"IN",
    "ks:ks_name":"Darwechak",
    "ks:ks_pop":171,
    "ks:ks_type":"VILLAGE",
    "name:eng_x_preferred":[
        "Darwechak"
    ],
    "wof:name":"Darwechak",
    "wof:placetype":"locality",
    "wof:population":171
},
  "geometry": {"coordinates":[87.186449,24.353764],"type":"Point"}
}