{
  "type": "Feature",
  "properties": {
    "iso:country":"IN",
    "ks:ks_name":"Mehraj Ki Beri",
    "ks:ks_pop":896,
    "ks:ks_type":"VILLAGE",
    "name:eng_x_preferred":[
        "Mehraj Ki Beri"
    ],
    "wof:name":"Mehraj Ki Beri",
    "wof:placetype":"locality",
    "wof:population":896
},
  "geometry": {"coordinates":[72.150756,26.107044],"type":"Point"}
}