{
  "type": "Feature",
  "properties": {
    "gn:admin1_code":"12",
    "gn:admin2_code":"14.0",
    "gn:asciiname":"Mamwaingund",
    "gn:country_code":"IN",
    "gn:dem":1630,
    "gn:feature_class":"P",
    "gn:feature_code":"PPL",
    "gn:name":"Mamwaingund",
    "gn:population":0,
    "gn:timezone":"Asia/Kolkata",
    "iso:country":"IN",
    "wof:name":"Mamwaingund",
    "wof:placetype":"locality"
},
  "geometry": {"coordinates":[75.10899999999999,33.64807],"type":"Point"}
}