{
  "type": "Feature",
  "properties": {
    "gn:admin1_code":"2.0",
    "gn:admin2_code":"554.0",
    "gn:asciiname":"Kalavagunta",
    "gn:country_code":"IN",
    "gn:dem":295,
    "gn:feature_class":"P",
    "gn:feature_code":"PPL",
    "gn:name":"Kalavagunta",
    "gn:population":0,
    "gn:timezone":"Asia/Kolkata",
    "iso:country":"IN",
    "wof:name":"Kalavagunta",
    "wof:placetype":"locality"
},
  "geometry": {"coordinates":[79.13323000000003,13.28304],"type":"Point"}
}