{
  "type": "Feature",
  "properties": {
    "iso:country":"IN",
    "ks:ks_name":"Shriganeshpura",
    "ks:ks_pop":263,
    "ks:ks_type":"VILLAGE",
    "name:eng_x_preferred":[
        "Shriganeshpura"
    ],
    "wof:name":"Shriganeshpura",
    "wof:placetype":"locality",
    "wof:population":263
},
  "geometry": {"coordinates":[76.274525,26.625714],"type":"Point"}
}