{
  "type": "Feature",
  "properties": {
    "iso:country":"IN",
    "ks:ks_alt_nam":"Dok\u0101t\u0101",
    "ks:ks_name":"Dokata",
    "ks:ks_pop":1689,
    "ks:ks_type":"VILLAGE",
    "name:eng_x_preferred":[
        "Dokata"
    ],
    "name:eng_x_variant":[
        "Dok\u0101t\u0101"
    ],
    "wof:name":"Dokata",
    "wof:placetype":"locality",
    "wof:population":1689
},
  "geometry": {"coordinates":[85.72453299999999,22.401082],"type":"Point"}
}