{
  "type": "Feature",
  "properties": {
    "iso:country":"IN",
    "ks:ks_name":"Chak Parameshwari",
    "ks:ks_pop":268,
    "ks:ks_type":"VILLAGE",
    "ks:ks_uagg_main":0,
    "name:eng_x_preferred":[
        "Chak Parameshwari"
    ],
    "wof:name":"Chak Parameshwari",
    "wof:placetype":"neighbourhood",
    "wof:population":268
},
  "geometry": {"coordinates":[88.252045,22.092554],"type":"Point"}
}