{
  "type": "Feature",
  "properties": {
    "iso:country":"IN",
    "ks:ks_alt_nam":"amlawa",
    "ks:ks_name":"Amlawa",
    "ks:ks_pop":225,
    "ks:ks_type":"HABITATION",
    "name:eng_x_preferred":[
        "Amlawa"
    ],
    "wof:name":"Amlawa",
    "wof:placetype":"locality",
    "wof:population":225
},
  "geometry": {"coordinates":[86.752854,24.46145],"type":"Point"}
}