{
  "type": "Feature",
  "properties": {
    "iso:country":"IN",
    "ks:ks_name":"Rajpur",
    "ks:ks_pop":345,
    "ks:ks_type":"VILLAGE",
    "ks:ks_uagg_main":0,
    "name:eng_x_preferred":[
        "Rajpur"
    ],
    "wof:name":"Rajpur",
    "wof:placetype":"neighbourhood",
    "wof:population":345
},
  "geometry": {"coordinates":[76.264523,31.077647],"type":"Point"}
}