{
  "type": "Feature",
  "properties": {
    "iso:country":"IN",
    "ks:ks_name":"Angadibail",
    "ks:ks_pop":34,
    "ks:ks_type":"HABITATION",
    "name:eng_x_preferred":[
        "Angadibail"
    ],
    "wof:name":"Angadibail",
    "wof:placetype":"locality",
    "wof:population":34
},
  "geometry": {"coordinates":[74.398025,14.67026],"type":"Point"}
}