{
  "type": "Feature",
  "properties": {
    "iso:country":"IN",
    "ks:ks_name":"Kharigerya",
    "ks:ks_pop":1503,
    "ks:ks_type":"VILLAGE",
    "name:eng_x_preferred":[
        "Kharigerya"
    ],
    "wof:name":"Kharigerya",
    "wof:placetype":"locality",
    "wof:population":1503
},
  "geometry": {"coordinates":[86.887835,22.755731],"type":"Point"}
}