{
  "type": "Feature",
  "properties": {
    "iso:country":"IN",
    "ks:ks_alt_nam":"Tendr\u0101uli",
    "ks:ks_name":"Tendrauli",
    "ks:ks_pop":625,
    "ks:ks_type":"VILLAGE",
    "name:eng_x_preferred":[
        "Tendrauli"
    ],
    "name:eng_x_variant":[
        "Tendr\u0101uli"
    ],
    "wof:name":"Tendrauli",
    "wof:placetype":"locality",
    "wof:population":625
},
  "geometry": {"coordinates":[85.125108,22.434099],"type":"Point"}
}