{
  "type": "Feature",
  "properties": {
    "gn:admin1_code":"16.0",
    "gn:admin2_code":"513.0",
    "gn:asciiname":"Mangrul",
    "gn:country_code":"IN",
    "gn:dem":420,
    "gn:feature_class":"P",
    "gn:feature_code":"PPL",
    "gn:name":"Mangr\u016bl",
    "gn:population":0,
    "gn:timezone":"Asia/Kolkata",
    "iso:country":"IN",
    "wof:name":"Mangrul",
    "wof:placetype":"locality"
},
  "geometry": {"coordinates":[76.58509000000002,19.16689],"type":"Point"}
}