{
  "type": "Feature",
  "properties": {
    "iso:country":"IN",
    "ks:ks_alt_nam":"HARIJAN  TOLA",
    "ks:ks_name":"Harijan Tola",
    "ks:ks_pop":137,
    "ks:ks_type":"HABITATION",
    "name:eng_x_preferred":[
        "Harijan Tola"
    ],
    "name:eng_x_variant":[
        "HARIJAN  TOLA"
    ],
    "wof:name":"Harijan Tola",
    "wof:placetype":"locality",
    "wof:population":137
},
  "geometry": {"coordinates":[83.72030700000001,24.888421],"type":"Point"}
}