{
  "type": "Feature",
  "properties": {
    "iso:country":"IN",
    "ks:ks_alt_nam":"dewan ka pur",
    "ks:ks_name":"Dewan Ka Pur",
    "ks:ks_pop":627,
    "ks:ks_type":"HABITATION",
    "name:eng_x_preferred":[
        "Dewan Ka Pur"
    ],
    "wof:name":"Dewan Ka Pur",
    "wof:placetype":"locality",
    "wof:population":627
},
  "geometry": {"coordinates":[82.77656,25.368856],"type":"Point"}
}