{
  "type": "Feature",
  "properties": {
    "gn:admin1_code":"10",
    "gn:admin2_code":"87.0",
    "gn:asciiname":"Saral",
    "gn:country_code":"IN",
    "gn:dem":195,
    "gn:feature_class":"P",
    "gn:feature_code":"PPL",
    "gn:name":"Saral",
    "gn:population":0,
    "gn:timezone":"Asia/Kolkata",
    "iso:country":"IN",
    "name:aze_x_preferred":[
        "Saral"
    ],
    "name:fas_x_preferred":[
        "\u0633\u0627\u0631\u0627\u0644"
    ],
    "name:fra_x_preferred":[
        "Saral"
    ],
    "wof:name":"Saral",
    "wof:placetype":"locality"
},
  "geometry": {"coordinates":[77.03439,27.93295],"type":"Point"}
}