{
  "type": "Feature",
  "properties": {
    "iso:country":"IN",
    "ks:ks_name":"Rakhaditola",
    "ks:ks_pop":197,
    "ks:ks_type":"HABITATION",
    "name:eng_x_preferred":[
        "Rakhaditola"
    ],
    "wof:name":"Rakhaditola",
    "wof:placetype":"locality",
    "wof:population":197
},
  "geometry": {"coordinates":[80.522201,21.313577],"type":"Point"}
}