{
  "type": "Feature",
  "properties": {
    "gn:admin1_code":"24",
    "gn:admin2_code":"120.0",
    "gn:asciiname":"Kushalpura",
    "gn:country_code":"IN",
    "gn:dem":310,
    "gn:feature_class":"P",
    "gn:feature_code":"PPL",
    "gn:name":"Kush\u0101lpura",
    "gn:population":0,
    "gn:timezone":"Asia/Kolkata",
    "iso:country":"IN",
    "wof:name":"Kushalpura",
    "wof:placetype":"locality"
},
  "geometry": {"coordinates":[75.47123000000001,25.84649],"type":"Point"}
}