{
  "type": "Feature",
  "properties": {
    "gn:admin1_code":"39.0",
    "gn:admin2_code":"68.0",
    "gn:asciiname":"Malakpur",
    "gn:country_code":"IN",
    "gn:dem":258,
    "gn:feature_class":"P",
    "gn:feature_code":"PPL",
    "gn:name":"Malakpur",
    "gn:population":0,
    "gn:timezone":"Asia/Kolkata",
    "iso:country":"IN",
    "name:pan_x_preferred":[
        "\u0a2e\u0a3e\u0a32\u0a15\u0a2a\u0a41\u0a30"
    ],
    "wof:name":"Malakpur",
    "wof:placetype":"locality"
},
  "geometry": {"coordinates":[77.90831999999997,29.8676],"type":"Point"}
}