{
  "type": "Feature",
  "properties": {
    "iso:country":"IN",
    "ks:ks_name":"Talpahari",
    "ks:ks_pop":127,
    "ks:ks_type":"VILLAGE",
    "name:eng_x_preferred":[
        "Talpahari"
    ],
    "wof:name":"Talpahari",
    "wof:placetype":"locality",
    "wof:population":127
},
  "geometry": {"coordinates":[87.70760799999999,24.540258],"type":"Point"}
}