{
  "type": "Feature",
  "properties": {
    "iso:country":"IN",
    "ks:ks_name":"Halgumane",
    "ks:ks_pop":24,
    "ks:ks_type":"HABITATION",
    "name:eng_x_preferred":[
        "Halgumane"
    ],
    "wof:name":"Halgumane",
    "wof:placetype":"locality",
    "wof:population":24
},
  "geometry": {"coordinates":[74.638289,14.736868],"type":"Point"}
}