{
  "type": "Feature",
  "properties": {
    "iso:country":"IN",
    "ks:ks_name":"Dusi Nathakollai",
    "ks:ks_pop":916,
    "ks:ks_type":"HABITATION",
    "name:eng_x_preferred":[
        "Dusi Nathakollai"
    ],
    "wof:name":"Dusi Nathakollai",
    "wof:placetype":"locality",
    "wof:population":916
},
  "geometry": {"coordinates":[79.67229,12.768083],"type":"Point"}
}