{
  "type": "Feature",
  "properties": {
    "iso:country":"IN",
    "ks:ks_name":"Magurkhali",
    "ks:ks_pop":1102,
    "ks:ks_type":"VILLAGE",
    "name:eng_x_preferred":[
        "Magurkhali"
    ],
    "wof:name":"Magurkhali",
    "wof:placetype":"locality",
    "wof:population":1102
},
  "geometry": {"coordinates":[88.34150699999999,22.436219],"type":"Point"}
}