{
  "type": "Feature",
  "properties": {
    "iso:country":"IN",
    "ks:ks_alt_nam":"KANDAGOGHAR",
    "ks:ks_name":"Kandagoghar",
    "ks:ks_pop":114,
    "ks:ks_type":"HABITATION",
    "name:eng_x_preferred":[
        "Kandagoghar"
    ],
    "wof:name":"Kandagoghar",
    "wof:placetype":"locality",
    "wof:population":114
},
  "geometry": {"coordinates":[85.51806500000001,24.217336],"type":"Point"}
}