{
  "type": "Feature",
  "properties": {
    "iso:country":"IN",
    "ks:ks_name":"Baobari",
    "ks:ks_pop":909,
    "ks:ks_type":"VILLAGE",
    "ks:ks_uagg_main":0,
    "name:eng_x_preferred":[
        "Baobari"
    ],
    "wof:name":"Baobari",
    "wof:placetype":"neighbourhood",
    "wof:population":909
},
  "geometry": {"coordinates":[90.786839,26.501217],"type":"Point"}
}