{
  "type": "Feature",
  "properties": {
    "gn:admin1_code":"19.0",
    "gn:admin2_code":"567.0",
    "gn:asciiname":"Tumbigeri",
    "gn:country_code":"IN",
    "gn:dem":546,
    "gn:feature_class":"P",
    "gn:feature_code":"PPL",
    "gn:name":"Tumbigeri",
    "gn:population":0,
    "gn:timezone":"Asia/Kolkata",
    "iso:country":"IN",
    "wof:name":"Tumbigeri",
    "wof:placetype":"locality"
},
  "geometry": {"coordinates":[75.8723,14.60803],"type":"Point"}
}