{
  "type": "Feature",
  "properties": {
    "iso:country":"IN",
    "ks:ks_name":"Sanwal",
    "ks:ks_pop":640,
    "ks:ks_type":"VILLAGE",
    "name:eng_x_preferred":[
        "Sanwal"
    ],
    "wof:name":"Sanwal",
    "wof:placetype":"locality",
    "wof:population":640
},
  "geometry": {"coordinates":[75.51885299999999,26.72949],"type":"Point"}
}