{
  "type": "Feature",
  "properties": {
    "gn:admin1_code":"36",
    "gn:admin2_code":"146.0",
    "gn:asciiname":"Bajehra",
    "gn:country_code":"IN",
    "gn:dem":172,
    "gn:feature_class":"P",
    "gn:feature_code":"PPL",
    "gn:name":"Bajehra",
    "gn:population":0,
    "gn:timezone":"Asia/Kolkata",
    "iso:country":"IN",
    "ks:ks_name":"Bajehra",
    "ks:ks_type":"VILLAGE",
    "wof:name":"Bajehra",
    "wof:placetype":"neighbourhood"
},
  "geometry": {"coordinates":[78.05998,27.08366],"type":"Point"}
}