{
  "type": "Feature",
  "properties": {
    "gn:admin1_code":"36.0",
    "gn:admin2_code":"180.0",
    "gn:asciiname":"Safipur",
    "gn:country_code":"IN",
    "gn:dem":112,
    "gn:feature_class":"P",
    "gn:feature_code":"PPL",
    "gn:name":"Safipur",
    "gn:population":0,
    "gn:timezone":"Asia/Kolkata",
    "iso:country":"IN",
    "name:bpy_x_preferred":[
        "\u09b8\u09ab\u09bf\u09aa\u09c1\u09b0"
    ],
    "name:ceb_x_preferred":[
        "Saf\u012bpur"
    ],
    "name:fas_x_preferred":[
        "\u0635\u0641\u06cc\u200c\u067e\u0648\u0631"
    ],
    "name:hin_x_preferred":[
        "\u0938\u092b\u0940\u092a\u0941\u0930"
    ],
    "name:ita_x_preferred":[
        "Safipur"
    ],
    "name:mlg_x_preferred":[
        "Safipur"
    ],
    "name:msa_x_preferred":[
        "Safipur"
    ],
    "name:new_x_preferred":[
        "\u0938\u092b\u0940\u092a\u0941\u0930 \u0924\u0939\u0938\u0940\u0932"
    ],
    "name:nld_x_preferred":[
        "Safipur"
    ],
    "name:ori_x_preferred":[
        "\u0b38\u0b3e\u0b2b\u0b3f\u0b2a\u0b41\u0b30"
    ],
    "name:pnb_x_preferred":[
        "\u0633\u0641\u067e\u0648\u0631"
    ],
    "name:pol_x_preferred":[
        "Safipur"
    ],
    "name:por_x_preferred":[
        "Safipur"
    ],
    "name:swe_x_preferred":[
        "Saf\u012bpur"
    ],
    "name:urd_x_preferred":[
        "\u0633\u0641\u067e\u0648\u0631"
    ],
    "name:vie_x_preferred":[
        "Safipur"
    ],
    "name:zho_x_preferred":[
        "\u8428\u83f2\u666e\u5c14"
    ],
    "wof:name":"Safipur",
    "wof:placetype":"neighbourhood"
},
  "geometry": {"coordinates":[81.51872,27.20775],"type":"Point"}
}