{
  "type": "Feature",
  "properties": {
    "iso:country":"IN",
    "ks:ks_name":"Gujhwan",
    "ks:ks_pop":262,
    "ks:ks_type":"HABITATION",
    "name:eng_x_preferred":[
        "Gujhwan"
    ],
    "wof:name":"Gujhwan",
    "wof:placetype":"locality",
    "wof:population":262
},
  "geometry": {"coordinates":[81.422524,25.105631],"type":"Point"}
}