{
  "type": "Feature",
  "properties": {
    "gn:admin1_code":"11",
    "gn:admin2_code":"23.0",
    "gn:asciiname":"Bari Suari",
    "gn:country_code":"IN",
    "gn:dem":2882,
    "gn:feature_class":"P",
    "gn:feature_code":"PPL",
    "gn:name":"B\u0101ri Su\u0101ri",
    "gn:population":0,
    "gn:timezone":"Asia/Kolkata",
    "iso:country":"IN",
    "wof:name":"Bari Suari",
    "wof:placetype":"locality"
},
  "geometry": {"coordinates":[76.14578,32.42168],"type":"Point"}
}