{
  "type": "Feature",
  "properties": {
    "gn:admin1_code":"35.0",
    "gn:admin2_code":"447.0",
    "gn:asciiname":"Kanojiya",
    "gn:country_code":"IN",
    "gn:dem":738,
    "gn:feature_class":"P",
    "gn:feature_code":"PPL",
    "gn:name":"Kanojiya",
    "gn:population":0,
    "gn:timezone":"Asia/Kolkata",
    "iso:country":"IN",
    "wof:name":"Kanojiya",
    "wof:placetype":"locality"
},
  "geometry": {"coordinates":[78.16311999999998,21.93076],"type":"Point"}
}