{
  "type": "Feature",
  "properties": {
    "iso:country":"IN",
    "ks:ks_name":"Malon Ka Oda",
    "ks:ks_pop":391,
    "ks:ks_type":"VILLAGE",
    "name:eng_x_preferred":[
        "Malon Ka Oda"
    ],
    "wof:name":"Malon Ka Oda",
    "wof:placetype":"locality",
    "wof:population":391
},
  "geometry": {"coordinates":[74.33690300000001,24.339453],"type":"Point"}
}