{
  "type": "Feature",
  "properties": {
    "iso:country":"IN",
    "ks:ks_name":"Someswarapuram",
    "ks:ks_pop":226,
    "ks:ks_type":"HABITATION",
    "ks:ks_uagg_main":0,
    "name:eng_x_preferred":[
        "Someswarapuram"
    ],
    "wof:name":"Someswarapuram",
    "wof:placetype":"neighbourhood",
    "wof:population":226
},
  "geometry": {"coordinates":[79.046498,14.617845],"type":"Point"}
}