{
  "type": "Feature",
  "properties": {
    "gn:admin1_code":"36.0",
    "gn:admin2_code":"133",
    "gn:asciiname":"Latifgarh",
    "gn:country_code":"IN",
    "gn:dem":248,
    "gn:feature_class":"P",
    "gn:feature_code":"PPL",
    "gn:name":"Latifgarh",
    "gn:population":0,
    "gn:timezone":"Asia/Kolkata",
    "iso:country":"IN",
    "wof:name":"Latifgarh",
    "wof:placetype":"neighbourhood"
},
  "geometry": {"coordinates":[77.41703,29.57296],"type":"Point"}
}