{
  "type": "Feature",
  "properties": {
    "iso:country":"IN",
    "ks:ks_name":"Sennimalaigoundenpudur",
    "ks:ks_pop":425,
    "ks:ks_type":"HABITATION",
    "ks:ks_uagg_main":0,
    "name:eng_x_preferred":[
        "Sennimalaigoundenpudur"
    ],
    "wof:name":"Sennimalaigoundenpudur",
    "wof:placetype":"locality",
    "wof:population":425
},
  "geometry": {"coordinates":[77.252301,11.189243],"type":"Point"}
}