{
  "type": "Feature",
  "properties": {
    "iso:country":"IN",
    "ks:ks_name":"Ai Than",
    "ks:ks_pop":11,
    "ks:ks_type":"HABITATION",
    "name:eng_x_preferred":[
        "Ai Than"
    ],
    "wof:name":"Ai Than",
    "wof:placetype":"locality",
    "wof:population":11
},
  "geometry": {"coordinates":[91.881156,26.226217],"type":"Point"}
}