{
  "type": "Feature",
  "properties": {
    "iso:country":"IN",
    "ks:ks_alt_nam":"Kam\u0101lpur",
    "ks:ks_name":"Kamalpur",
    "ks:ks_type":"VILLAGE",
    "name:eng_x_preferred":[
        "Kamalpur"
    ],
    "name:eng_x_variant":[
        "Kam\u0101lpur"
    ],
    "wof:name":"Kamalpur",
    "wof:placetype":"locality"
},
  "geometry": {"coordinates":[83.696743,25.705259],"type":"Point"}
}