{
  "type": "Feature",
  "properties": {
    "gn:admin1_code":"38",
    "gn:admin2_code":"346.0",
    "gn:asciiname":"Baghokudar",
    "gn:country_code":"IN",
    "gn:dem":415,
    "gn:feature_class":"P",
    "gn:feature_code":"PPL",
    "gn:name":"B\u0101ghokudar",
    "gn:population":0,
    "gn:timezone":"Asia/Kolkata",
    "iso:country":"IN",
    "ks:ks_alt_nam":"B\u0101ghokudar",
    "ks:ks_name":"Baghokudar",
    "ks:ks_pop":530,
    "ks:ks_type":"VILLAGE",
    "name:eng_x_preferred":[
        "Baghokudar"
    ],
    "name:eng_x_variant":[
        "B\u0101ghokudar"
    ],
    "wof:name":"Baghokudar",
    "wof:placetype":"locality",
    "wof:population":530
},
  "geometry": {"coordinates":[83.62114800000001,23.8785],"type":"Point"}
}