{
  "type": "Feature",
  "properties": {
    "gn:admin1_code":"34.0",
    "gn:admin2_code":"227.0",
    "gn:asciiname":"Surji Chak",
    "gn:country_code":"IN",
    "gn:dem":43,
    "gn:feature_class":"P",
    "gn:feature_code":"PPL",
    "gn:name":"Surji Chak",
    "gn:population":0,
    "gn:timezone":"Asia/Kolkata",
    "iso:country":"IN",
    "ks:ks_name":"Surji Chak",
    "ks:ks_pop":589,
    "ks:ks_type":"VILLAGE",
    "name:eng_x_preferred":[
        "Surji Chak"
    ],
    "wof:name":"Surji Chak",
    "wof:placetype":"locality",
    "wof:population":589
},
  "geometry": {"coordinates":[86.149867,25.214658],"type":"Point"}
}