{
  "type": "Feature",
  "properties": {
    "gn:admin1_code":"40.0",
    "gn:admin2_code":"534.0",
    "gn:asciiname":"Korlakunta",
    "gn:country_code":"IN",
    "gn:dem":128,
    "gn:feature_class":"P",
    "gn:feature_code":"PPL",
    "gn:name":"Korlakunta",
    "gn:population":0,
    "gn:timezone":"Asia/Kolkata",
    "iso:country":"IN",
    "ks:ks_name":"Korlakunta",
    "ks:ks_type":"VILLAGE",
    "name:eng_x_preferred":[
        "Korlakunta"
    ],
    "wof:name":"Korlakunta",
    "wof:placetype":"locality"
},
  "geometry": {"coordinates":[80.00116800000001,18.572553],"type":"Point"}
}