{
  "type": "Feature",
  "properties": {
    "iso:country":"IN",
    "ks:ks_name":"Marate",
    "ks:ks_pop":20,
    "ks:ks_type":"HABITATION",
    "name:eng_x_preferred":[
        "Marate"
    ],
    "wof:name":"Marate",
    "wof:placetype":"locality",
    "wof:population":20
},
  "geometry": {"coordinates":[75.282335,13.422805],"type":"Point"}
}