{
  "type": "Feature",
  "properties": {
    "iso:country":"IN",
    "ks:ks_name":"Panbari 3",
    "ks:ks_pop":102,
    "ks:ks_type":"HABITATION",
    "ks:ks_uagg_main":0,
    "name:eng_x_preferred":[
        "Panbari 3"
    ],
    "wof:name":"Panbari 3",
    "wof:placetype":"neighbourhood",
    "wof:population":102
},
  "geometry": {"coordinates":[94.035409,26.24231],"type":"Point"}
}