{
  "type": "Feature",
  "properties": {
    "iso:country":"IN",
    "ks:ks_name":"Kutudupa",
    "ks:ks_pop":177,
    "ks:ks_type":"VILLAGE",
    "name:eng_x_preferred":[
        "Kutudupa"
    ],
    "wof:name":"Kutudupa",
    "wof:placetype":"locality",
    "wof:population":177
},
  "geometry": {"coordinates":[83.930846,20.112141],"type":"Point"}
}