{
  "type": "Feature",
  "properties": {
    "gn:admin1_code":"10.0",
    "gn:admin2_code":"78.0",
    "gn:asciiname":"Karnauli",
    "gn:country_code":"IN",
    "gn:dem":214,
    "gn:feature_class":"P",
    "gn:feature_code":"PPL",
    "gn:name":"Karnauli",
    "gn:population":0,
    "gn:timezone":"Asia/Kolkata",
    "iso:country":"IN",
    "wof:name":"Karnauli",
    "wof:placetype":"locality"
},
  "geometry": {"coordinates":[75.31461,29.54052],"type":"Point"}
}