{
  "type": "Feature",
  "properties": {
    "iso:country":"IN",
    "ks:ks_name":"Kaijhar",
    "ks:ks_pop":1810,
    "ks:ks_type":"HABITATION",
    "name:eng_x_preferred":[
        "Kaijhar"
    ],
    "wof:name":"Kaijhar",
    "wof:placetype":"locality",
    "wof:population":1810
},
  "geometry": {"coordinates":[85.95479,21.102738],"type":"Point"}
}