{
  "type": "Feature",
  "properties": {
    "iso:country":"IN",
    "ks:ks_alt_nam":"Cheyyeru Extension Reserved Forest",
    "ks:ks_name":"Cheyyeru Extension Reserved Fo",
    "ks:ks_type":"VILLAGE",
    "name:eng_x_preferred":[
        "Cheyyeru Extension Reserved Fo"
    ],
    "name:eng_x_variant":[
        "Cheyyeru Extension Reserved Forest"
    ],
    "wof:name":"Cheyyeru Extension Reserved Fo",
    "wof:placetype":"locality"
},
  "geometry": {"coordinates":[78.984661,14.232925],"type":"Point"}
}