{
  "type": "Feature",
  "properties": {
    "iso:country":"IN",
    "ks:ks_name":"Chanakyamoola",
    "ks:ks_pop":535,
    "ks:ks_type":"HABITATION",
    "name:eng_x_preferred":[
        "Chanakyamoola"
    ],
    "wof:name":"Chanakyamoola",
    "wof:placetype":"locality",
    "wof:population":535
},
  "geometry": {"coordinates":[76.204829,11.627102],"type":"Point"}
}