{
  "type": "Feature",
  "properties": {
    "iso:country":"IN",
    "ks:ks_name":"Dongarwadi",
    "ks:ks_pop":233,
    "ks:ks_type":"HABITATION",
    "name:eng_x_preferred":[
        "Dongarwadi"
    ],
    "wof:name":"Dongarwadi",
    "wof:placetype":"locality",
    "wof:population":233
},
  "geometry": {"coordinates":[73.579987,19.39915],"type":"Point"}
}