{
  "type": "Feature",
  "properties": {
    "iso:country":"IN",
    "ks:ks_alt_nam":"Garlabanda tanda",
    "ks:ks_name":"Garlabanda Tanda",
    "ks:ks_pop":250,
    "ks:ks_type":"HABITATION",
    "name:eng_x_preferred":[
        "Garlabanda Tanda"
    ],
    "wof:name":"Garlabanda Tanda",
    "wof:placetype":"locality",
    "wof:population":250
},
  "geometry": {"coordinates":[78.0814,16.527471],"type":"Point"}
}