{
  "type": "Feature",
  "properties": {
    "iso:country":"IN",
    "ks:ks_name":"Kotharamapuram",
    "ks:ks_pop":30,
    "ks:ks_type":"HABITATION",
    "name:eng_x_preferred":[
        "Kotharamapuram"
    ],
    "wof:name":"Kotharamapuram",
    "wof:placetype":"locality",
    "wof:population":30
},
  "geometry": {"coordinates":[79.039655,13.296724],"type":"Point"}
}