{
  "type": "Feature",
  "properties": {
    "iso:country":"IN",
    "ks:ks_alt_nam":"Sonauri baghedi",
    "ks:ks_name":"Sonauri Baghedi",
    "ks:ks_pop":31,
    "ks:ks_type":"HABITATION",
    "name:eng_x_preferred":[
        "Sonauri Baghedi"
    ],
    "wof:name":"Sonauri Baghedi",
    "wof:placetype":"locality",
    "wof:population":31
},
  "geometry": {"coordinates":[81.910301,24.92104],"type":"Point"}
}