{
  "type": "Feature",
  "properties": {
    "gn:admin1_code":"36.0",
    "gn:admin2_code":"140.0",
    "gn:asciiname":"Lock",
    "gn:country_code":"IN",
    "gn:dem":217,
    "gn:feature_class":"P",
    "gn:feature_code":"PPL",
    "gn:name":"Lock",
    "gn:population":0,
    "gn:timezone":"Asia/Kolkata",
    "iso:country":"IN",
    "name:ceb_x_preferred":[
        "Lock"
    ],
    "name:deu_x_preferred":[
        "Lock"
    ],
    "name:fas_x_preferred":[
        "\u0642\u0641\u0644"
    ],
    "name:fin_x_preferred":[
        "Lukko"
    ],
    "name:fra_x_preferred":[
        "Lock"
    ],
    "name:heb_x_preferred":[
        "\u05dc\u05d5\u05e7"
    ],
    "name:ita_x_preferred":[
        "Lock"
    ],
    "name:kaz_x_preferred":[
        "\u049a\u04b1\u043b\u044b\u043f"
    ],
    "name:msa_x_preferred":[
        "Kunci"
    ],
    "name:nds_x_preferred":[
        "Lock"
    ],
    "name:swe_x_preferred":[
        "Lock"
    ],
    "wof:name":"Lock",
    "wof:placetype":"locality"
},
  "geometry": {"coordinates":[77.55016999999999,28.70717],"type":"Point"}
}