{
  "type": "Feature",
  "properties": {
    "iso:country":"IN",
    "ks:ks_name":"Nanawarewasti",
    "ks:ks_pop":547,
    "ks:ks_type":"HABITATION",
    "name:eng_x_preferred":[
        "Nanawarewasti"
    ],
    "wof:name":"Nanawarewasti",
    "wof:placetype":"locality",
    "wof:population":547
},
  "geometry": {"coordinates":[75.0749,17.576897],"type":"Point"}
}