{
  "type": "Feature",
  "properties": {
    "gn:admin1_code":"35.0",
    "gn:admin2_code":"438.0",
    "gn:asciiname":"Isur",
    "gn:country_code":"IN",
    "gn:dem":529,
    "gn:feature_class":"P",
    "gn:feature_code":"PPL",
    "gn:name":"Isur",
    "gn:population":0,
    "gn:timezone":"Asia/Kolkata",
    "iso:country":"IN",
    "wof:name":"Isur",
    "wof:placetype":"locality"
},
  "geometry": {"coordinates":[74.80244999999999,22.66983],"type":"Point"}
}