{
  "type": "Feature",
  "properties": {
    "gn:admin1_code":"25.0",
    "gn:admin2_code":"605.0",
    "gn:asciiname":"Kilmurungi",
    "gn:country_code":"IN",
    "gn:dem":300,
    "gn:feature_class":"P",
    "gn:feature_code":"PPL",
    "gn:name":"K\u012blmurungi",
    "gn:population":0,
    "gn:timezone":"Asia/Kolkata",
    "iso:country":"IN",
    "ks:ks_name":"Kilmurungai",
    "ks:ks_pop":3612,
    "ks:ks_type":"VILLAGE",
    "ks:ks_uagg_main":0,
    "name:eng_x_preferred":[
        "Kilmurungai"
    ],
    "wof:name":"Kilmurungai",
    "wof:placetype":"neighbourhood",
    "wof:population":3612
},
  "geometry": {"coordinates":[78.78277300000001,12.833816],"type":"Point"}
}