{
  "type": "Feature",
  "properties": {
    "gn:admin1_code":"29.0",
    "gn:admin2_code":"242.0",
    "gn:asciiname":"Baijak",
    "gn:country_code":"IN",
    "gn:dem":865,
    "gn:feature_class":"P",
    "gn:feature_code":"PPL",
    "gn:name":"Baijak",
    "gn:population":0,
    "gn:timezone":"Asia/Kolkata",
    "iso:country":"IN",
    "wof:name":"Baijak",
    "wof:placetype":"locality"
},
  "geometry": {"coordinates":[88.17752,27.14301],"type":"Point"}
}