{
  "type": "Feature",
  "properties": {
    "iso:country":"IN",
    "ks:ks_name":"Karuchandi",
    "ks:ks_pop":3124,
    "ks:ks_type":"HABITATION",
    "name:eng_x_preferred":[
        "Karuchandi"
    ],
    "wof:name":"Karuchandi",
    "wof:placetype":"locality",
    "wof:population":3124
},
  "geometry": {"coordinates":[87.843632,22.461274],"type":"Point"}
}