{
  "type": "Feature",
  "properties": {
    "iso:country":"IN",
    "ks:ks_alt_nam":"KEWTAHI",
    "ks:ks_name":"Kewtahi",
    "ks:ks_pop":526,
    "ks:ks_type":"HABITATION",
    "ks:ks_uagg_main":0,
    "name:eng_x_preferred":[
        "Kewtahi"
    ],
    "wof:name":"Kewtahi",
    "wof:placetype":"neighbourhood",
    "wof:population":526
},
  "geometry": {"coordinates":[82.40391700000001,26.150287],"type":"Point"}
}