{
  "type": "Feature",
  "properties": {
    "iso:country":"IN",
    "ks:ks_name":"Maelbailam",
    "ks:ks_pop":45,
    "ks:ks_type":"HABITATION",
    "name:eng_x_preferred":[
        "Maelbailam"
    ],
    "wof:name":"Maelbailam",
    "wof:placetype":"locality",
    "wof:population":45
},
  "geometry": {"coordinates":[78.332437,11.378355],"type":"Point"}
}