{
  "type": "Feature",
  "properties": {
    "gn:admin1_code":"37",
    "gn:admin2_code":"406.0",
    "gn:asciiname":"Bendarchua",
    "gn:country_code":"IN",
    "gn:dem":607,
    "gn:feature_class":"P",
    "gn:feature_code":"PPL",
    "gn:name":"Bendarchua",
    "gn:population":0,
    "gn:timezone":"Asia/Kolkata",
    "iso:country":"IN",
    "ks:ks_name":"Benderchuwa",
    "ks:ks_pop":616,
    "ks:ks_type":"VILLAGE",
    "name:eng_x_preferred":[
        "Benderchuwa"
    ],
    "name:eng_x_variant":[
        "Bendarchua"
    ],
    "wof:name":"Benderchuwa",
    "wof:placetype":"locality",
    "wof:population":616
},
  "geometry": {"coordinates":[82.097385,22.711183],"type":"Point"}
}