{
  "type": "Feature",
  "properties": {
    "iso:country":"IN",
    "ks:ks_alt_nam":"Mah\u0101kud\u0101p\u0101li",
    "ks:ks_name":"Mahakudapali",
    "ks:ks_type":"VILLAGE",
    "name:eng_x_preferred":[
        "Mahakudapali"
    ],
    "name:eng_x_variant":[
        "Mah\u0101kud\u0101p\u0101li"
    ],
    "wof:name":"Mahakudapali",
    "wof:placetype":"locality"
},
  "geometry": {"coordinates":[84.36965600000001,20.811185],"type":"Point"}
}