{
  "type": "Feature",
  "properties": {
    "iso:country":"IN",
    "ks:ks_alt_nam":"G\u016bd\u016bru",
    "ks:ks_name":"Guduru",
    "ks:ks_type":"VILLAGE",
    "ks:ks_uagg_main":0,
    "name:eng_x_preferred":[
        "Guduru"
    ],
    "name:eng_x_variant":[
        "G\u016bd\u016bru"
    ],
    "wof:name":"Guduru",
    "wof:placetype":"neighbourhood"
},
  "geometry": {"coordinates":[78.815597,14.490392],"type":"Point"}
}