{
  "type": "Feature",
  "properties": {
    "iso:country":"IN",
    "ks:ks_name":"Goalpara",
    "ks:ks_pop":755,
    "ks:ks_type":"VILLAGE",
    "ks:ks_uagg_main":0,
    "name:eng_x_preferred":[
        "Goalpara"
    ],
    "name:hin_x_preferred":[
        "\u0917\u094b\u0935\u093e\u0932\u092a\u093e\u0930\u093e"
    ],
    "wof:name":"Goalpara",
    "wof:placetype":"neighbourhood",
    "wof:population":755
},
  "geometry": {"coordinates":[88.231075,25.455376],"type":"Point"}
}