{
  "type": "Feature",
  "properties": {
    "iso:country":"IN",
    "ks:ks_alt_nam":"UPERSAPAHA",
    "ks:ks_name":"Upersapaha",
    "ks:ks_pop":105,
    "ks:ks_type":"HABITATION",
    "name:eng_x_preferred":[
        "Upersapaha"
    ],
    "wof:name":"Upersapaha",
    "wof:placetype":"locality",
    "wof:population":105
},
  "geometry": {"coordinates":[86.439745,24.646384],"type":"Point"}
}