{
  "type": "Feature",
  "properties": {
    "iso:country":"IN",
    "ks:ks_name":"Sijgot",
    "ks:ks_pop":0,
    "ks:ks_type":"VILLAGE",
    "name:eng_x_preferred":[
        "Sijgot"
    ],
    "wof:name":"Sijgot",
    "wof:placetype":"locality",
    "wof:population":0
},
  "geometry": {"coordinates":[87.21944499999999,22.498771],"type":"Point"}
}