{
  "type": "Feature",
  "properties": {
    "iso:country":"IN",
    "ks:ks_name":"13 GD",
    "ks:ks_pop":41,
    "ks:ks_type":"VILLAGE",
    "name:eng_x_preferred":[
        "13 GD"
    ],
    "wof:name":"13 GD",
    "wof:placetype":"locality",
    "wof:population":41
},
  "geometry": {"coordinates":[72.94784799999999,29.001279],"type":"Point"}
}