{
  "type": "Feature",
  "properties": {
    "iso:country":"IN",
    "ks:ks_name":"Karipahari",
    "ks:ks_pop":268,
    "ks:ks_type":"VILLAGE",
    "name:eng_x_preferred":[
        "Karipahari"
    ],
    "wof:name":"Karipahari",
    "wof:placetype":"locality",
    "wof:population":268
},
  "geometry": {"coordinates":[85.863623,24.539248],"type":"Point"}
}