{
  "type": "Feature",
  "properties": {
    "iso:country":"IN",
    "ks:ks_alt_nam":"hombayyanahitlu",
    "ks:ks_name":"Hombayyanahitlu",
    "ks:ks_pop":59,
    "ks:ks_type":"HABITATION",
    "name:eng_x_preferred":[
        "Hombayyanahitlu"
    ],
    "wof:name":"Hombayyanahitlu",
    "wof:placetype":"locality",
    "wof:population":59
},
  "geometry": {"coordinates":[74.492785,14.168663],"type":"Point"}
}