{
  "type": "Feature",
  "properties": {
    "gn:admin1_code":"36",
    "gn:admin2_code":"200.0",
    "gn:asciiname":"Japla",
    "gn:country_code":"IN",
    "gn:dem":248,
    "gn:feature_class":"P",
    "gn:feature_code":"PPL",
    "gn:name":"Japla",
    "gn:population":0,
    "gn:timezone":"Asia/Kolkata",
    "iso:country":"IN",
    "ks:ks_name":"Japala",
    "ks:ks_pop":526,
    "ks:ks_type":"VILLAGE",
    "name:eng_x_preferred":[
        "Japala"
    ],
    "name:eng_x_variant":[
        "Japla"
    ],
    "wof:name":"Japala",
    "wof:placetype":"locality",
    "wof:population":526
},
  "geometry": {"coordinates":[83.239227,24.175636],"type":"Point"}
}