{
  "type": "Feature",
  "properties": {
    "iso:country":"IN",
    "ks:ks_name":"10 P",
    "ks:ks_pop":284,
    "ks:ks_type":"VILLAGE",
    "name:eng_x_preferred":[
        "10 P"
    ],
    "wof:name":"10 P",
    "wof:placetype":"locality",
    "wof:population":284
},
  "geometry": {"coordinates":[73.15419900000001,29.12302],"type":"Point"}
}