{
  "type": "Feature",
  "properties": {
    "iso:country":"IN",
    "ks:ks_name":"Mahewa",
    "ks:ks_pop":111,
    "ks:ks_type":"VILLAGE",
    "name:eng_x_preferred":[
        "Mahewa"
    ],
    "wof:name":"Mahewa",
    "wof:placetype":"locality",
    "wof:population":111
},
  "geometry": {"coordinates":[80.222211,28.406766],"type":"Point"}
}