{
  "type": "Feature",
  "properties": {
    "iso:country":"IN",
    "ks:ks_name":"Rakhal Namasudra Para",
    "ks:ks_pop":229,
    "ks:ks_type":"HABITATION",
    "name:eng_x_preferred":[
        "Rakhal Namasudra Para"
    ],
    "wof:name":"Rakhal Namasudra Para",
    "wof:placetype":"locality",
    "wof:population":229
},
  "geometry": {"coordinates":[91.801243,23.986851],"type":"Point"}
}