{
  "type": "Feature",
  "properties": {
    "iso:country":"IN",
    "ks:ks_name":"Kareniyanendal",
    "ks:ks_pop":574,
    "ks:ks_type":"HABITATION",
    "name:eng_x_preferred":[
        "Kareniyanendal"
    ],
    "wof:name":"Kareniyanendal",
    "wof:placetype":"locality",
    "wof:population":574
},
  "geometry": {"coordinates":[79.08595699999999,10.1382],"type":"Point"}
}