{
  "type": "Feature",
  "properties": {
    "gn:admin1_code":"28.0",
    "gn:admin2_code":"334.0",
    "gn:asciiname":"Kalipur",
    "gn:country_code":"IN",
    "gn:dem":59,
    "gn:feature_class":"P",
    "gn:feature_code":"PPL",
    "gn:name":"K\u0101lipur",
    "gn:population":0,
    "gn:timezone":"Asia/Kolkata",
    "iso:country":"IN",
    "wof:name":"Kalipur",
    "wof:placetype":"locality"
},
  "geometry": {"coordinates":[87.69200000000002,24.12092],"type":"Point"}
}