{
  "type": "Feature",
  "properties": {
    "iso:country":"IN",
    "ks:ks_name":"Nuapada 2",
    "ks:ks_pop":16,
    "ks:ks_type":"HABITATION",
    "name:eng_x_preferred":[
        "Nuapada 2"
    ],
    "wof:name":"Nuapada 2",
    "wof:placetype":"locality",
    "wof:population":16
},
  "geometry": {"coordinates":[84.24593400000001,20.694298],"type":"Point"}
}