{
  "type": "Feature",
  "properties": {
    "iso:country":"IN",
    "ks:ks_name":"Jurirpar",
    "ks:ks_pop":1890,
    "ks:ks_type":"HABITATION",
    "name:eng_x_preferred":[
        "Jurirpar"
    ],
    "wof:name":"Jurirpar",
    "wof:placetype":"locality",
    "wof:population":1890
},
  "geometry": {"coordinates":[92.644166,26.035636],"type":"Point"}
}