{
  "type": "Feature",
  "properties": {
    "iso:country":"IN",
    "ks:ks_name":"Ful Chari",
    "ks:ks_pop":392,
    "ks:ks_type":"HABITATION",
    "name:eng_x_preferred":[
        "Ful Chari"
    ],
    "wof:name":"Ful Chari",
    "wof:placetype":"locality",
    "wof:population":392
},
  "geometry": {"coordinates":[91.82441300000001,24.184801],"type":"Point"}
}