{
  "type": "Feature",
  "properties": {
    "iso:country":"IN",
    "ks:ks_name":"Medarametlavaripalle",
    "ks:ks_pop":11,
    "ks:ks_type":"HABITATION",
    "name:eng_x_preferred":[
        "Medarametlavaripalle"
    ],
    "wof:name":"Medarametlavaripalle",
    "wof:placetype":"locality",
    "wof:population":11
},
  "geometry": {"coordinates":[79.014746,13.693938],"type":"Point"}
}