{
  "type": "Feature",
  "properties": {
    "gn:admin1_code":"12.0",
    "gn:admin2_code":"18.0",
    "gn:asciiname":"Warzakhain",
    "gn:country_code":"IN",
    "gn:dem":3209,
    "gn:feature_class":"P",
    "gn:feature_code":"PPL",
    "gn:name":"Warzakhain",
    "gn:population":0,
    "gn:timezone":"Asia/Kolkata",
    "iso:country":"IN",
    "wof:name":"Warzakhain",
    "wof:placetype":"locality"
},
  "geometry": {"coordinates":[75.78223,33.42285],"type":"Point"}
}