{
  "type": "Feature",
  "properties": {
    "iso:country":"IN",
    "ks:ks_name":"Basantpur",
    "ks:ks_pop":1043,
    "ks:ks_type":"VILLAGE",
    "name:eng_x_preferred":[
        "Basantpur"
    ],
    "wof:name":"Basantpur",
    "wof:placetype":"locality",
    "wof:population":1043
},
  "geometry": {"coordinates":[82.185587,27.56609],"type":"Point"}
}