{
  "type": "Feature",
  "properties": {
    "iso:country":"IN",
    "ks:ks_name":"Ozarpada",
    "ks:ks_pop":696,
    "ks:ks_type":"HABITATION",
    "name:eng_x_preferred":[
        "Ozarpada"
    ],
    "wof:name":"Ozarpada",
    "wof:placetype":"locality",
    "wof:population":696
},
  "geometry": {"coordinates":[72.908029,20.096088],"type":"Point"}
}