{
  "type": "Feature",
  "properties": {
    "iso:country":"IN",
    "ks:ks_name":"Adhari Gadai",
    "ks:ks_pop":673,
    "ks:ks_type":"VILLAGE",
    "name:eng_x_preferred":[
        "Adhari Gadai"
    ],
    "wof:name":"Adhari Gadai",
    "wof:placetype":"locality",
    "wof:population":673
},
  "geometry": {"coordinates":[81.835791,24.232619],"type":"Point"}
}