{
  "type": "Feature",
  "properties": {
    "gn:admin1_code":"25",
    "gn:admin2_code":"630.0",
    "gn:asciiname":"Wodapatti",
    "gn:country_code":"IN",
    "gn:dem":265,
    "gn:feature_class":"P",
    "gn:feature_code":"PPL",
    "gn:name":"Wodapatti",
    "gn:population":0,
    "gn:timezone":"Asia/Kolkata",
    "iso:country":"IN",
    "wof:name":"Wodapatti",
    "wof:placetype":"locality"
},
  "geometry": {"coordinates":[77.78768000000002,12.12311],"type":"Point"}
}