{
  "type": "Feature",
  "properties": {
    "iso:country":"IN",
    "ks:ks_name":"Daruvu Peta",
    "ks:ks_pop":175,
    "ks:ks_type":"HABITATION",
    "name:eng_x_preferred":[
        "Daruvu Peta"
    ],
    "wof:name":"Daruvu Peta",
    "wof:placetype":"locality",
    "wof:population":175
},
  "geometry": {"coordinates":[82.10261199999999,16.735433],"type":"Point"}
}