{
  "type": "Feature",
  "properties": {
    "gn:admin1_code":"25.0",
    "gn:admin2_code":"633.0",
    "gn:asciiname":"Morattuppalaiyam",
    "gn:country_code":"IN",
    "gn:dem":302,
    "gn:feature_class":"P",
    "gn:feature_code":"PPL",
    "gn:name":"Morattupp\u0101laiyam",
    "gn:population":0,
    "gn:timezone":"Asia/Kolkata",
    "iso:country":"IN",
    "ks:ks_name":"Morattupalayam",
    "ks:ks_pop":4661,
    "ks:ks_type":"URBAN",
    "ks:ks_uagg_main":0,
    "name:eng_x_preferred":[
        "Morattupalayam"
    ],
    "wof:name":"Morattupalayam",
    "wof:placetype":"locality",
    "wof:population":4661
},
  "geometry": {"coordinates":[77.41865900000001,11.148497],"type":"Point"}
}