{
  "type": "Feature",
  "properties": {
    "iso:country":"IN",
    "ks:ks_alt_nam":"Duaghat Adivasi sahi",
    "ks:ks_name":"Duaghat Adivasi Sahi",
    "ks:ks_pop":84,
    "ks:ks_type":"HABITATION",
    "name:eng_x_preferred":[
        "Duaghat Adivasi Sahi"
    ],
    "wof:name":"Duaghat Adivasi Sahi",
    "wof:placetype":"locality",
    "wof:population":84
},
  "geometry": {"coordinates":[85.83372300000001,21.769038],"type":"Point"}
}