{
  "type": "Feature",
  "properties": {
    "iso:country":"IN",
    "ks:ks_name":"Tamilia",
    "ks:ks_pop":3577,
    "ks:ks_type":"VILLAGE",
    "ks:ks_uagg_main":0,
    "name:eng_x_preferred":[
        "Tamilia"
    ],
    "wof:name":"Tamilia",
    "wof:placetype":"neighbourhood",
    "wof:population":3577
},
  "geometry": {"coordinates":[86.198915,22.852257],"type":"Point"}
}