{
  "type": "Feature",
  "properties": {
    "iso:country":"IN",
    "ks:ks_name":"Khairguda",
    "ks:ks_pop":61,
    "ks:ks_type":"HABITATION",
    "name:eng_x_preferred":[
        "Khairguda"
    ],
    "wof:name":"Khairguda",
    "wof:placetype":"locality",
    "wof:population":61
},
  "geometry": {"coordinates":[78.662496,19.388354],"type":"Point"}
}