{
  "type": "Feature",
  "properties": {
    "iso:country":"IN",
    "ks:ks_name":"Khalihamari",
    "ks:ks_pop":77,
    "ks:ks_type":"HABITATION",
    "name:eng_x_preferred":[
        "Khalihamari"
    ],
    "wof:name":"Khalihamari",
    "wof:placetype":"locality",
    "wof:population":77
},
  "geometry": {"coordinates":[91.166043,26.659494],"type":"Point"}
}