{
  "type": "Feature",
  "properties": {
    "gn:admin1_code":"38.0",
    "gn:admin2_code":"351.0",
    "gn:asciiname":"Kusmara",
    "gn:country_code":"IN",
    "gn:dem":53,
    "gn:feature_class":"P",
    "gn:feature_code":"PPL",
    "gn:name":"Kusm\u0101ra",
    "gn:population":0,
    "gn:timezone":"Asia/Kolkata",
    "iso:country":"IN",
    "name:bpy_x_preferred":[
        "\u0995\u09c1\u09b8\u09cd\u09ae\u09be\u09b0\u09be"
    ],
    "name:ceb_x_preferred":[
        "Kusmara"
    ],
    "name:ita_x_preferred":[
        "Kusmara"
    ],
    "name:msa_x_preferred":[
        "Kusmara"
    ],
    "name:new_x_preferred":[
        "\u0915\u0941\u0938\u094d\u092e\u093e\u0930\u093e"
    ],
    "name:nld_x_preferred":[
        "Kusmara"
    ],
    "name:pol_x_preferred":[
        "Kusmara"
    ],
    "name:por_x_preferred":[
        "Kusmara"
    ],
    "name:swe_x_preferred":[
        "Kusmara"
    ],
    "name:urd_x_preferred":[
        "\u06a9\u0633\u0645\u0627\u0631\u0627"
    ],
    "name:vie_x_preferred":[
        "Kusmara"
    ],
    "name:zho_x_preferred":[
        "\u5e93\u65af\u9a6c\u62c9"
    ],
    "wof:name":"Kusmara",
    "wof:placetype":"locality"
},
  "geometry": {"coordinates":[87.24694000000002,25.04854],"type":"Point"}
}