{
  "type": "Feature",
  "properties": {
    "gn:admin1_code":"40",
    "gn:admin2_code":"539.0",
    "gn:asciiname":"Tungapati Gauraram",
    "gn:country_code":"IN",
    "gn:dem":338,
    "gn:feature_class":"P",
    "gn:feature_code":"PPL",
    "gn:name":"Tungap\u0101ti Gaur\u0101ram",
    "gn:population":0,
    "gn:timezone":"Asia/Kolkata",
    "iso:country":"IN",
    "wof:name":"Tungapati Gauraram",
    "wof:placetype":"locality"
},
  "geometry": {"coordinates":[78.88930000000001,16.88055],"type":"Point"}
}