{
  "type": "Feature",
  "properties": {
    "gn:admin1_code":"36",
    "gn:admin2_code":"186.0",
    "gn:asciiname":"Firoz Patti",
    "gn:country_code":"IN",
    "gn:dem":84,
    "gn:feature_class":"P",
    "gn:feature_code":"PPL",
    "gn:name":"Firoz Patti",
    "gn:population":0,
    "gn:timezone":"Asia/Kolkata",
    "iso:country":"IN",
    "wof:name":"Firoz Patti",
    "wof:placetype":"neighbourhood"
},
  "geometry": {"coordinates":[83.10482,26.58334],"type":"Point"}
}