{
  "type": "Feature",
  "properties": {
    "gn:admin1_code":"10",
    "gn:admin2_code":"87.0",
    "gn:asciiname":"Pithaurpuri",
    "gn:country_code":"IN",
    "gn:dem":199,
    "gn:feature_class":"P",
    "gn:feature_code":"PPL",
    "gn:name":"Pithaurpuri",
    "gn:population":0,
    "gn:timezone":"Asia/Kolkata",
    "iso:country":"IN",
    "ks:ks_name":"Pithorpuri",
    "ks:ks_pop":181,
    "ks:ks_type":"VILLAGE",
    "name:eng_x_preferred":[
        "Pithorpuri"
    ],
    "name:eng_x_variant":[
        "Pithaurpuri"
    ],
    "wof:name":"Pithorpuri",
    "wof:placetype":"locality",
    "wof:population":181
},
  "geometry": {"coordinates":[77.001795,27.9095],"type":"Point"}
}