{
  "type": "Feature",
  "properties": {
    "gn:admin1_code":"2.0",
    "gn:admin2_code":"554.0",
    "gn:asciiname":"Besavagaripalle",
    "gn:country_code":"IN",
    "gn:dem":614,
    "gn:feature_class":"P",
    "gn:feature_code":"PPL",
    "gn:name":"Besavag\u0101ripalle",
    "gn:population":0,
    "gn:timezone":"Asia/Kolkata",
    "iso:country":"IN",
    "wof:name":"Besavagaripalle",
    "wof:placetype":"locality"
},
  "geometry": {"coordinates":[78.29852,13.71389],"type":"Point"}
}