{
  "type": "Feature",
  "properties": {
    "gn:admin1_code":"39.0",
    "gn:admin2_code":"64.0",
    "gn:asciiname":"Dialekh",
    "gn:country_code":"IN",
    "gn:dem":1563,
    "gn:feature_class":"P",
    "gn:feature_code":"PPL",
    "gn:name":"Dialekh",
    "gn:population":0,
    "gn:timezone":"Asia/Kolkata",
    "iso:country":"IN",
    "ks:ks_name":"Dyalekh",
    "ks:ks_pop":175,
    "ks:ks_type":"VILLAGE",
    "name:eng_x_preferred":[
        "Dyalekh"
    ],
    "name:eng_x_variant":[
        "Dialekh"
    ],
    "wof:name":"Dyalekh",
    "wof:placetype":"locality",
    "wof:population":175
},
  "geometry": {"coordinates":[79.41873200000001,29.57489],"type":"Point"}
}