{
  "type": "Feature",
  "properties": {
    "gn:admin1_code":"35",
    "gn:admin2_code":"423.0",
    "gn:asciiname":"Parichha",
    "gn:country_code":"IN",
    "gn:dem":447,
    "gn:feature_class":"P",
    "gn:feature_code":"PPL",
    "gn:name":"Parichha",
    "gn:population":0,
    "gn:timezone":"Asia/Kolkata",
    "iso:country":"IN",
    "name:bpy_x_preferred":[
        "\u09aa\u09be\u09b0\u09bf\u099b\u09be"
    ],
    "name:ceb_x_preferred":[
        "Par\u012bchh\u0101"
    ],
    "name:hin_x_preferred":[
        "\u092a\u093e\u0930\u0940\u091b\u093e"
    ],
    "name:ita_x_preferred":[
        "Parichha"
    ],
    "name:mlg_x_preferred":[
        "Parichha"
    ],
    "name:msa_x_preferred":[
        "Parichha"
    ],
    "name:nld_x_preferred":[
        "Parichha"
    ],
    "name:pol_x_preferred":[
        "Parichha"
    ],
    "name:por_x_preferred":[
        "Parichha"
    ],
    "name:swe_x_preferred":[
        "Par\u012bchh\u0101"
    ],
    "name:urd_x_preferred":[
        "\u067e\u0631\u06cc\u0686\u06be\u0627"
    ],
    "name:vie_x_preferred":[
        "Parichha"
    ],
    "name:zho_x_preferred":[
        "\u5e15\u91cc\u6070"
    ],
    "wof:name":"Parichha",
    "wof:placetype":"neighbourhood"
},
  "geometry": {"coordinates":[77.45397,25.51376],"type":"Point"}
}