{
  "type": "Feature",
  "properties": {
    "gn:admin1_code":"24.0",
    "gn:admin2_code":"113",
    "gn:asciiname":"Gopalsar",
    "gn:country_code":"IN",
    "gn:dem":260,
    "gn:feature_class":"P",
    "gn:feature_code":"PPL",
    "gn:name":"Gop\u0101lsar",
    "gn:population":0,
    "gn:timezone":"Asia/Kolkata",
    "iso:country":"IN",
    "wof:name":"Gopalsar",
    "wof:placetype":"locality"
},
  "geometry": {"coordinates":[72.58851999999997,26.48937],"type":"Point"}
}