{
  "type": "Feature",
  "properties": {
    "iso:country":"IN",
    "ks:ks_name":"Patniya",
    "ks:ks_pop":450,
    "ks:ks_type":"VILLAGE",
    "name:eng_x_preferred":[
        "Patniya"
    ],
    "wof:name":"Patniya",
    "wof:placetype":"locality",
    "wof:population":450
},
  "geometry": {"coordinates":[78.748631,21.996761],"type":"Point"}
}