{
  "type": "Feature",
  "properties": {
    "iso:country":"IN",
    "qs:name":"Labing",
    "qs:name_adm0":"India",
    "qs:name_adm1":"Sikkim",
    "qs:photos":89,
    "qs:photos_1k":18,
    "qs:photos_9k":1,
    "qs:photos_9r":3,
    "qs:photos_all":89,
    "qs:photos_sr":3,
    "qs:placetype":"Town",
    "qs:pop_sr":"0",
    "wof:name":"Labing",
    "wof:placetype":"locality"
},
  "geometry": {"coordinates":[88.232705,27.36141],"type":"Point"}
}