{
  "type": "Feature",
  "properties": {
    "gn:admin1_code":"19.0",
    "gn:admin2_code":"555.0",
    "gn:asciiname":"Sigihalli",
    "gn:country_code":"IN",
    "gn:dem":714,
    "gn:feature_class":"P",
    "gn:feature_code":"PPL",
    "gn:name":"Sigihalli",
    "gn:population":0,
    "gn:timezone":"Asia/Kolkata",
    "iso:country":"IN",
    "wof:name":"Sigihalli",
    "wof:placetype":"neighbourhood"
},
  "geometry": {"coordinates":[74.8595,15.62931],"type":"Point"}
}