{
  "type": "Feature",
  "properties": {
    "iso:country":"IN",
    "ks:ks_alt_nam":"GHUTUGADEWASTI",
    "ks:ks_name":"Ghutugadewasti",
    "ks:ks_pop":76,
    "ks:ks_type":"HABITATION",
    "name:eng_x_preferred":[
        "Ghutugadewasti"
    ],
    "wof:name":"Ghutugadewasti",
    "wof:placetype":"locality",
    "wof:population":76
},
  "geometry": {"coordinates":[74.66417300000001,17.081272],"type":"Point"}
}