{
  "type": "Feature",
  "properties": {
    "gn:admin1_code":"39.0",
    "gn:admin2_code":"061",
    "gn:asciiname":"Purangarhi",
    "gn:country_code":"IN",
    "gn:dem":1858,
    "gn:feature_class":"P",
    "gn:feature_code":"PPL",
    "gn:name":"Purangarhi",
    "gn:population":0,
    "gn:timezone":"Asia/Kolkata",
    "iso:country":"IN",
    "wof:name":"Purangarhi",
    "wof:placetype":"locality"
},
  "geometry": {"coordinates":[78.64373000000001,29.92122],"type":"Point"}
}