{
  "type": "Feature",
  "properties": {
    "gn:admin1_code":"39.0",
    "gn:admin2_code":"64.0",
    "gn:asciiname":"Semalkhet",
    "gn:country_code":"IN",
    "gn:dem":1366,
    "gn:feature_class":"P",
    "gn:feature_code":"PPL",
    "gn:name":"Semalkhet",
    "gn:population":0,
    "gn:timezone":"Asia/Kolkata",
    "iso:country":"IN",
    "ks:ks_name":"Simal Khet",
    "ks:ks_pop":1032,
    "ks:ks_type":"VILLAGE",
    "name:eng_x_preferred":[
        "Simal Khet"
    ],
    "name:eng_x_variant":[
        "Semalkhet"
    ],
    "wof:name":"Simal Khet",
    "wof:placetype":"locality",
    "wof:population":1032
},
  "geometry": {"coordinates":[79.334425,29.960441],"type":"Point"}
}