{
  "type": "Feature",
  "properties": {
    "iso:country":"IN",
    "ks:ks_name":"Kurhua",
    "ks:ks_pop":1374,
    "ks:ks_type":"VILLAGE",
    "name:eng_x_preferred":[
        "Kurhua"
    ],
    "wof:name":"Kurhua",
    "wof:placetype":"neighbourhood",
    "wof:population":1374
},
  "geometry": {"coordinates":[82.962656,25.226137],"type":"Point"}
}