{
  "type": "Feature",
  "properties": {
    "gn:admin1_code":"36.0",
    "gn:admin2_code":"161.0",
    "gn:asciiname":"Nagla Khenchpura",
    "gn:country_code":"IN",
    "gn:dem":150,
    "gn:feature_class":"P",
    "gn:feature_code":"PPL",
    "gn:name":"Nagla Khenchpura",
    "gn:population":0,
    "gn:timezone":"Asia/Kolkata",
    "iso:country":"IN",
    "wof:name":"Nagla Khenchpura",
    "wof:placetype":"locality"
},
  "geometry": {"coordinates":[79.07108000000002,26.83066],"type":"Point"}
}