{
  "type": "Feature",
  "properties": {
    "gn:admin1_code":"25.0",
    "gn:admin2_code":"619.0",
    "gn:asciiname":"Kaduvangudi",
    "gn:country_code":"IN",
    "gn:dem":13,
    "gn:feature_class":"P",
    "gn:feature_code":"PPL",
    "gn:name":"Kaduvangudi",
    "gn:population":0,
    "gn:timezone":"Asia/Kolkata",
    "iso:country":"IN",
    "ks:ks_name":"Kaduvangudi",
    "ks:ks_pop":667,
    "ks:ks_type":"VILLAGE",
    "ks:ks_uagg_main":0,
    "name:eng_x_preferred":[
        "Kaduvangudi"
    ],
    "wof:name":"Kaduvangudi",
    "wof:placetype":"neighbourhood",
    "wof:population":667
},
  "geometry": {"coordinates":[79.636757,10.697961],"type":"Point"}
}