{
  "type": "Feature",
  "properties": {
    "gn:admin1_code":"37",
    "gn:admin2_code":"407.0",
    "gn:asciiname":"Murwahi",
    "gn:country_code":"IN",
    "gn:dem":768,
    "gn:feature_class":"P",
    "gn:feature_code":"PPL",
    "gn:name":"Murw\u0101hi",
    "gn:population":0,
    "gn:timezone":"Asia/Kolkata",
    "iso:country":"IN",
    "ks:ks_name":"Mudwahi",
    "ks:ks_pop":1078,
    "ks:ks_type":"VILLAGE",
    "name:eng_x_preferred":[
        "Mudwahi"
    ],
    "name:eng_x_variant":[
        "Murwahi"
    ],
    "wof:name":"Mudwahi",
    "wof:placetype":"locality",
    "wof:population":1078
},
  "geometry": {"coordinates":[81.027072,22.040948],"type":"Point"}
}