{
  "type": "Feature",
  "properties": {
    "gn:admin1_code":"38",
    "gn:admin2_code":"346.0",
    "gn:asciiname":"Kadwa",
    "gn:country_code":"IN",
    "gn:dem":367,
    "gn:feature_class":"P",
    "gn:feature_code":"PPL",
    "gn:name":"Kadwa",
    "gn:population":0,
    "gn:timezone":"Asia/Kolkata",
    "iso:country":"IN",
    "name:und_x_variant":[
        "Likhanidhaura"
    ],
    "wof:name":"Kadwa",
    "wof:placetype":"locality"
},
  "geometry": {"coordinates":[83.51212,24.06842],"type":"Point"}
}