{
  "type": "Feature",
  "properties": {
    "gn:admin1_code":"36",
    "gn:admin2_code":"133.0",
    "gn:asciiname":"Kailauda Kalan",
    "gn:country_code":"IN",
    "gn:dem":238,
    "gn:feature_class":"P",
    "gn:feature_code":"PPL",
    "gn:name":"Kailauda Kal\u0101n",
    "gn:population":0,
    "gn:timezone":"Asia/Kolkata",
    "iso:country":"IN",
    "wof:name":"Kailauda Kalan",
    "wof:placetype":"locality"
},
  "geometry": {"coordinates":[77.82682,29.21225],"type":"Point"}
}