{
  "type": "Feature",
  "properties": {
    "iso:country":"IN",
    "ks:ks_name":"Mudenagadde",
    "ks:ks_pop":9,
    "ks:ks_type":"HABITATION",
    "name:eng_x_preferred":[
        "Mudenagadde"
    ],
    "wof:name":"Mudenagadde",
    "wof:placetype":"locality",
    "wof:population":9
},
  "geometry": {"coordinates":[74.641299,14.586692],"type":"Point"}
}