{
  "type": "Feature",
  "properties": {
    "gn:admin1_code":"24.0",
    "gn:admin2_code":"114.0",
    "gn:asciiname":"Bhon",
    "gn:country_code":"IN",
    "gn:dem":70,
    "gn:feature_class":"P",
    "gn:feature_code":"PPL",
    "gn:name":"Bhon",
    "gn:population":0,
    "gn:timezone":"Asia/Kolkata",
    "iso:country":"IN",
    "wof:name":"Bhon",
    "wof:placetype":"locality"
},
  "geometry": {"coordinates":[69.79885999999999,26.6018],"type":"Point"}
}