{
  "type": "Feature",
  "properties": {
    "iso:country":"IN",
    "ks:ks_name":"Melina Besige",
    "ks:ks_pop":244,
    "ks:ks_type":"VILLAGE",
    "name:eng_x_preferred":[
        "Melina Besige"
    ],
    "wof:name":"Melina Besige",
    "wof:placetype":"locality",
    "wof:population":244
},
  "geometry": {"coordinates":[75.070303,13.889424],"type":"Point"}
}