{
  "type": "Feature",
  "properties": {
    "iso:country":"IN",
    "ks:ks_alt_nam":"K\u0101lew\u0101l",
    "ks:ks_name":"Kalewal",
    "ks:ks_type":"VILLAGE",
    "name:eng_x_preferred":[
        "Kalewal"
    ],
    "name:eng_x_variant":[
        "K\u0101lew\u0101l"
    ],
    "wof:name":"Kalewal",
    "wof:placetype":"locality"
},
  "geometry": {"coordinates":[75.61650899999999,31.819517],"type":"Point"}
}