{
  "type": "Feature",
  "properties": {
    "iso:country":"IN",
    "ks:ks_name":"Ng. Bhammi",
    "ks:ks_pop":435,
    "ks:ks_type":"HABITATION",
    "ks:ks_uagg_main":0,
    "name:eng_x_preferred":[
        "Ng. Bhammi"
    ],
    "wof:name":"Ng. Bhammi",
    "wof:placetype":"neighbourhood",
    "wof:population":435
},
  "geometry": {"coordinates":[78.73153000000001,27.90497],"type":"Point"}
}