{
  "type": "Feature",
  "properties": {
    "gn:admin1_code":"34.0",
    "gn:admin2_code":"215.0",
    "gn:asciiname":"Basuham",
    "gn:country_code":"IN",
    "gn:dem":54,
    "gn:feature_class":"P",
    "gn:feature_code":"PPL",
    "gn:name":"Basuh\u0101m",
    "gn:population":0,
    "gn:timezone":"Asia/Kolkata",
    "iso:country":"IN",
    "ks:ks_name":"Basuham",
    "ks:ks_pop":1304,
    "ks:ks_type":"VILLAGE",
    "name:eng_x_preferred":[
        "Basuham"
    ],
    "wof:name":"Basuham",
    "wof:placetype":"locality",
    "wof:population":1304
},
  "geometry": {"coordinates":[86.121762,26.060547],"type":"Point"}
}