{
  "type": "Feature",
  "properties": {
    "iso:country":"IN",
    "ks:ks_name":"Nepalerkuti",
    "ks:ks_pop":243,
    "ks:ks_type":"HABITATION",
    "name:eng_x_preferred":[
        "Nepalerkuti"
    ],
    "wof:name":"Nepalerkuti",
    "wof:placetype":"locality",
    "wof:population":243
},
  "geometry": {"coordinates":[90.02699200000001,26.300255],"type":"Point"}
}