{
  "type": "Feature",
  "properties": {
    "gn:admin1_code":"39",
    "gn:admin2_code":"67.0",
    "gn:asciiname":"Bharatpur",
    "gn:country_code":"IN",
    "gn:dem":239,
    "gn:feature_class":"P",
    "gn:feature_code":"PPL",
    "gn:name":"Bharatpur",
    "gn:population":0,
    "gn:timezone":"Asia/Kolkata",
    "iso:country":"IN",
    "wof:name":"Bharatpur",
    "wof:placetype":"locality"
},
  "geometry": {"coordinates":[78.93056999999997,29.26271],"type":"Point"}
}