{
  "type": "Feature",
  "properties": {
    "iso:country":"IN",
    "ks:ks_name":"Mundri Para",
    "ks:ks_pop":87,
    "ks:ks_type":"VILLAGE",
    "name:eng_x_preferred":[
        "Mundri Para"
    ],
    "wof:name":"Mundri Para",
    "wof:placetype":"locality",
    "wof:population":87
},
  "geometry": {"coordinates":[74.56143400000001,23.530627],"type":"Point"}
}