{
  "type": "Feature",
  "properties": {
    "iso:country":"IN",
    "ks:ks_name":"Metal",
    "ks:ks_pop":107,
    "ks:ks_type":"HABITATION",
    "ks:ks_uagg_main":0,
    "name:eng_x_preferred":[
        "Metal"
    ],
    "wof:name":"Metal",
    "wof:placetype":"neighbourhood",
    "wof:population":107
},
  "geometry": {"coordinates":[87.021081,22.547255],"type":"Point"}
}