{
  "type": "Feature",
  "properties": {
    "gn:admin1_code":"24",
    "gn:admin2_code":"129.0",
    "gn:asciiname":"Mohanpur",
    "gn:country_code":"IN",
    "gn:dem":273,
    "gn:feature_class":"P",
    "gn:feature_code":"PPL",
    "gn:name":"Mohanpur",
    "gn:population":0,
    "gn:timezone":"Asia/Kolkata",
    "iso:country":"IN",
    "wof:name":"Mohanpur",
    "wof:placetype":"locality"
},
  "geometry": {"coordinates":[76.30761,24.79245],"type":"Point"}
}