{
  "type": "Feature",
  "properties": {
    "iso:country":"IN",
    "ks:ks_name":"Ladladi",
    "ks:ks_pop":116,
    "ks:ks_type":"VILLAGE",
    "name:eng_x_preferred":[
        "Ladladi"
    ],
    "wof:name":"Ladladi",
    "wof:placetype":"locality",
    "wof:population":116
},
  "geometry": {"coordinates":[84.206276,21.375086],"type":"Point"}
}