{
  "type": "Feature",
  "properties": {
    "gn:admin1_code":"23.0",
    "gn:admin2_code":"35.0",
    "gn:asciiname":"Maddepur",
    "gn:country_code":"IN",
    "gn:dem":253,
    "gn:feature_class":"P",
    "gn:feature_code":"PPL",
    "gn:name":"Maddepur",
    "gn:population":0,
    "gn:timezone":"Asia/Kolkata",
    "iso:country":"IN",
    "ks:ks_name":"Maddepur",
    "ks:ks_pop":554,
    "ks:ks_type":"VILLAGE",
    "ks:ks_uagg_main":0,
    "name:eng_x_preferred":[
        "Maddepur"
    ],
    "wof:name":"Maddepur",
    "wof:placetype":"neighbourhood",
    "wof:population":554
},
  "geometry": {"coordinates":[75.31218699999999,32.107721],"type":"Point"}
}