{
  "type": "Feature",
  "properties": {
    "iso:country":"IN",
    "ks:ks_alt_nam":"UMARIYA",
    "ks:ks_name":"Umariya",
    "ks:ks_pop":911,
    "ks:ks_type":"HABITATION",
    "name:eng_x_preferred":[
        "Umariya"
    ],
    "wof:name":"Umariya",
    "wof:placetype":"locality",
    "wof:population":911
},
  "geometry": {"coordinates":[73.646792,24.416972],"type":"Point"}
}