{
  "type": "Feature",
  "properties": {
    "gn:admin1_code":"19",
    "gn:admin2_code":"557.0",
    "gn:asciiname":"Lotgeri",
    "gn:country_code":"IN",
    "gn:dem":504,
    "gn:feature_class":"P",
    "gn:feature_code":"PPL",
    "gn:name":"Lotgeri",
    "gn:population":0,
    "gn:timezone":"Asia/Kolkata",
    "iso:country":"IN",
    "ks:ks_name":"Lotageri",
    "ks:ks_pop":1216,
    "ks:ks_type":"VILLAGE",
    "name:eng_x_preferred":[
        "Lotageri"
    ],
    "name:eng_x_variant":[
        "Lotgeri"
    ],
    "wof:name":"Lotageri",
    "wof:placetype":"locality",
    "wof:population":1216
},
  "geometry": {"coordinates":[76.27569200000001,16.209827],"type":"Point"}
}