{
  "type": "Feature",
  "properties": {
    "iso:country":"IN",
    "ks:ks_alt_nam":"Tril piri",
    "ks:ks_name":"Tril Piri",
    "ks:ks_pop":316,
    "ks:ks_type":"HABITATION",
    "name:eng_x_preferred":[
        "Tril Piri"
    ],
    "wof:name":"Tril Piri",
    "wof:placetype":"locality",
    "wof:population":316
},
  "geometry": {"coordinates":[85.480491,22.816229],"type":"Point"}
}