{
  "type": "Feature",
  "properties": {
    "iso:country":"IN",
    "ks:ks_name":"Murlidum",
    "ks:ks_pop":142,
    "ks:ks_type":"VILLAGE",
    "name:eng_x_preferred":[
        "Murlidum"
    ],
    "wof:name":"Murlidum",
    "wof:placetype":"locality",
    "wof:population":142
},
  "geometry": {"coordinates":[87.34281799999999,24.403453],"type":"Point"}
}