{
  "type": "Feature",
  "properties": {
    "gn:admin1_code":"39",
    "gn:admin2_code":"61.0",
    "gn:asciiname":"Kamera",
    "gn:country_code":"IN",
    "gn:dem":1021,
    "gn:feature_class":"P",
    "gn:feature_code":"PPL",
    "gn:name":"Kamera",
    "gn:population":0,
    "gn:timezone":"Asia/Kolkata",
    "iso:country":"IN",
    "ks:ks_name":"Kamera",
    "ks:ks_pop":98,
    "ks:ks_type":"HABITATION",
    "ks:ks_uagg_main":0,
    "name:bul_x_preferred":[
        "\u041a\u0430\u043c\u0435\u0440\u0430"
    ],
    "name:ces_x_preferred":[
        "Kamera"
    ],
    "name:eng_x_preferred":[
        "Kamera"
    ],
    "name:hrv_x_preferred":[
        "Kamera"
    ],
    "name:jpn_x_preferred":[
        "\u30ab\u30e1\u30e9"
    ],
    "name:lav_x_preferred":[
        "Kamera"
    ],
    "name:pol_x_preferred":[
        "Kamera"
    ],
    "name:rus_x_preferred":[
        "\u041a\u0430\u043c\u0435\u0440\u0430"
    ],
    "name:slk_x_preferred":[
        "Kamera"
    ],
    "name:ukr_x_preferred":[
        "\u041a\u0430\u043c\u0435\u0440\u0430"
    ],
    "wof:name":"Kamera",
    "wof:placetype":"neighbourhood",
    "wof:population":98
},
  "geometry": {"coordinates":[78.805767,30.166197],"type":"Point"}
}