{
  "type": "Feature",
  "properties": {
    "iso:country":"IN",
    "ks:ks_name":"Chettitharakadu",
    "ks:ks_pop":900,
    "ks:ks_type":"HABITATION",
    "name:eng_x_preferred":[
        "Chettitharakadu"
    ],
    "wof:name":"Chettitharakadu",
    "wof:placetype":"locality",
    "wof:population":900
},
  "geometry": {"coordinates":[76.497163,10.563789],"type":"Point"}
}