{
  "type": "Feature",
  "properties": {
    "iso:country":"IN",
    "ks:ks_name":"Harijan Tola",
    "ks:ks_pop":590,
    "ks:ks_type":"HABITATION",
    "ks:ks_uagg_main":0,
    "name:eng_x_preferred":[
        "Harijan Tola"
    ],
    "wof:name":"Harijan Tola",
    "wof:placetype":"neighbourhood",
    "wof:population":590
},
  "geometry": {"coordinates":[86.599627,25.189423],"type":"Point"}
}