{
  "type": "Feature",
  "properties": {
    "iso:country":"IN",
    "ks:ks_name":"Harizan Tola",
    "ks:ks_pop":1021,
    "ks:ks_type":"HABITATION",
    "ks:ks_uagg_main":0,
    "name:eng_x_preferred":[
        "Harizan Tola"
    ],
    "wof:name":"Harizan Tola",
    "wof:placetype":"neighbourhood",
    "wof:population":1021
},
  "geometry": {"coordinates":[86.661196,25.121349],"type":"Point"}
}