{
  "type": "Feature",
  "properties": {
    "iso:country":"IN",
    "ks:ks_alt_nam":"CHAMAR  TOLA",
    "ks:ks_name":"Chamar Tola",
    "ks:ks_pop":92,
    "ks:ks_type":"HABITATION",
    "ks:ks_uagg_main":0,
    "name:eng_x_preferred":[
        "Chamar Tola"
    ],
    "name:eng_x_variant":[
        "CHAMAR  TOLA"
    ],
    "wof:name":"Chamar Tola",
    "wof:placetype":"neighbourhood",
    "wof:population":92
},
  "geometry": {"coordinates":[86.72759600000001,26.418102],"type":"Point"}
}