{
  "type": "Feature",
  "properties": {
    "iso:country":"IN",
    "ks:ks_name":"Pathirichal",
    "ks:ks_pop":472,
    "ks:ks_type":"HABITATION",
    "name:eng_x_preferred":[
        "Pathirichal"
    ],
    "wof:name":"Pathirichal",
    "wof:placetype":"locality",
    "wof:population":472
},
  "geometry": {"coordinates":[75.96865,11.752532],"type":"Point"}
}