{
  "type": "Feature",
  "properties": {
    "iso:country":"IN",
    "ks:ks_alt_nam":"Seng\u0101ttuppatti Extension Reserved Forest",
    "ks:ks_alt_nam_2":"Sengattuppatti Extension Reserved Forest",
    "ks:ks_name":"Sengattuppatti",
    "ks:ks_pop":0,
    "ks:ks_type":"VILLAGE",
    "name:eng_x_preferred":[
        "Sengattuppatti"
    ],
    "name:eng_x_variant":[
        "Seng\u0101ttuppatti Extension Reserved Forest",
        "Sengattuppatti Extension Reserved Forest"
    ],
    "wof:name":"Sengattuppatti",
    "wof:placetype":"locality",
    "wof:population":0
},
  "geometry": {"coordinates":[78.55635100000001,11.273502],"type":"Point"}
}