{
  "type": "Feature",
  "properties": {
    "gn:admin1_code":"35",
    "gn:admin2_code":"463.0",
    "gn:asciiname":"Darbari",
    "gn:country_code":"IN",
    "gn:dem":383,
    "gn:feature_class":"P",
    "gn:feature_code":"PPL",
    "gn:name":"Darb\u0101ri",
    "gn:population":0,
    "gn:timezone":"Asia/Kolkata",
    "iso:country":"IN",
    "ks:ks_alt_nam":"Darb\u0101ri",
    "ks:ks_name":"Darbari",
    "ks:ks_pop":1301,
    "ks:ks_type":"VILLAGE",
    "name:eng_x_preferred":[
        "Darbari"
    ],
    "name:eng_x_variant":[
        "Darb\u0101ri"
    ],
    "wof:name":"Darbari",
    "wof:placetype":"locality",
    "wof:population":1301
},
  "geometry": {"coordinates":[82.49352399999999,24.421937],"type":"Point"}
}