{
  "type": "Feature",
  "properties": {
    "gn:admin1_code":"36",
    "gn:admin2_code":"175.0",
    "gn:asciiname":"Qazipur",
    "gn:country_code":"IN",
    "gn:dem":98,
    "gn:feature_class":"P",
    "gn:feature_code":"PPL",
    "gn:name":"Q\u0101z\u012bpur",
    "gn:population":0,
    "gn:timezone":"Asia/Kolkata",
    "iso:country":"IN",
    "ks:ks_alt_nam":"Q\u0101z\u012bpur",
    "ks:ks_name":"Qazipur",
    "ks:ks_type":"VILLAGE",
    "ks:ks_uagg_main":0,
    "name:eng_x_preferred":[
        "Qazipur"
    ],
    "name:eng_x_variant":[
        "Q\u0101z\u012bpur"
    ],
    "wof:name":"Qazipur",
    "wof:placetype":"neighbourhood"
},
  "geometry": {"coordinates":[82.04387699999999,25.424038],"type":"Point"}
}