{
  "type": "Feature",
  "properties": {
    "iso:country":"IN",
    "ks:ks_alt_nam":"BajjappanaHatti",
    "ks:ks_name":"Bajjappanahatti",
    "ks:ks_pop":171,
    "ks:ks_type":"HABITATION",
    "name:eng_x_preferred":[
        "Bajjappanahatti"
    ],
    "wof:name":"Bajjappanahatti",
    "wof:placetype":"locality",
    "wof:population":171
},
  "geometry": {"coordinates":[76.295621,13.804003],"type":"Point"}
}