{
  "type": "Feature",
  "properties": {
    "gn:admin1_code":"16",
    "gn:admin2_code":"514.0",
    "gn:asciiname":"Waghrul",
    "gn:country_code":"IN",
    "gn:dem":597,
    "gn:feature_class":"P",
    "gn:feature_code":"PPL",
    "gn:name":"W\u0101ghrul",
    "gn:population":0,
    "gn:timezone":"Asia/Kolkata",
    "iso:country":"IN",
    "wof:name":"Waghrul",
    "wof:placetype":"locality"
},
  "geometry": {"coordinates":[75.97951999999999,19.96154],"type":"Point"}
}