{
  "type": "Feature",
  "properties": {
    "iso:country":"IN",
    "ks:ks_alt_nam":"M\u0101nakdiha",
    "ks:ks_name":"Manakdiha",
    "ks:ks_pop":192,
    "ks:ks_type":"VILLAGE",
    "name:eng_x_preferred":[
        "Manakdiha"
    ],
    "name:eng_x_variant":[
        "M\u0101nakdiha"
    ],
    "wof:name":"Manakdiha",
    "wof:placetype":"locality",
    "wof:population":192
},
  "geometry": {"coordinates":[86.197067,24.242792],"type":"Point"}
}