{
  "type": "Feature",
  "properties": {
    "gn:admin1_code":"24",
    "gn:admin2_code":"116.0",
    "gn:asciiname":"Mokhatra",
    "gn:country_code":"IN",
    "gn:dem":147,
    "gn:feature_class":"P",
    "gn:feature_code":"PPL",
    "gn:name":"Mokh\u0101tra",
    "gn:population":0,
    "gn:timezone":"Asia/Kolkata",
    "iso:country":"IN",
    "ks:ks_name":"Mokhatara",
    "ks:ks_pop":3643,
    "ks:ks_type":"VILLAGE",
    "name:eng_x_preferred":[
        "Mokhatara"
    ],
    "name:eng_x_variant":[
        "Mokhatra"
    ],
    "name:und_x_variant":[
        "Mukhatra",
        "Mokh\u0101tra"
    ],
    "wof:name":"Mokhatara",
    "wof:placetype":"locality",
    "wof:population":3643
},
  "geometry": {"coordinates":[72.035217,24.803175],"type":"Point"}
}