{
  "type": "Feature",
  "properties": {
    "gn:admin1_code":"24",
    "gn:admin2_code":"116.0",
    "gn:asciiname":"Mokhatra",
    "gn:country_code":"IN",
    "gn:dem":147,
    "gn:feature_class":"P",
    "gn:feature_code":"PPL",
    "gn:name":"Mokh\u0101tra",
    "gn:population":0,
    "gn:timezone":"Asia/Kolkata",
    "iso:country":"IN",
    "name:und_x_variant":[
        "Mukhatra",
        "Mokh\u0101tra"
    ],
    "wof:name":"Mokhatra",
    "wof:placetype":"locality"
},
  "geometry": {"coordinates":[72.04014000000002,24.80053],"type":"Point"}
}