{
  "type": "Feature",
  "properties": {
    "iso:country":"IN",
    "ks:ks_name":"Jahangirpur",
    "ks:ks_pop":695,
    "ks:ks_type":"VILLAGE",
    "name:ben_x_preferred":[
        "\u099c\u09be\u09b9\u09be\u0999\u09cd\u0997\u09c0\u09b0\u09aa\u09c1\u09b0"
    ],
    "name:eng_x_preferred":[
        "Jahangirpur"
    ],
    "name:hin_x_preferred":[
        "\u091c\u0939\u093e\u0902\u0917\u0940\u0930\u092a\u0941\u0930"
    ],
    "wof:name":"Jahangirpur",
    "wof:placetype":"locality",
    "wof:population":695
},
  "geometry": {"coordinates":[87.909344,25.637646],"type":"Point"}
}