{
  "type": "Feature",
  "properties": {
    "iso:country":"IN",
    "ks:ks_name":"Jahangirpur",
    "ks:ks_pop":695,
    "ks:ks_type":"VILLAGE",
    "name:eng_x_preferred":[
        "Jahangirpur"
    ],
    "wof:name":"Jahangirpur",
    "wof:placetype":"locality",
    "wof:population":695
},
  "geometry": {"coordinates":[87.909344,25.637646],"type":"Point"}
}