{
  "type": "Feature",
  "properties": {
    "iso:country":"IN",
    "ks:ks_name":"D.Pinjirakonda",
    "ks:ks_pop":241,
    "ks:ks_type":"VILLAGE",
    "name:eng_x_preferred":[
        "D.Pinjirakonda"
    ],
    "wof:name":"D.Pinjirakonda",
    "wof:placetype":"locality",
    "wof:population":241
},
  "geometry": {"coordinates":[82.00773100000001,17.444636],"type":"Point"}
}