{
  "type": "Feature",
  "properties": {
    "iso:country":"IN",
    "ks:ks_name":"Palasihema",
    "ks:ks_pop":29,
    "ks:ks_type":"HABITATION",
    "name:eng_x_preferred":[
        "Palasihema"
    ],
    "wof:name":"Palasihema",
    "wof:placetype":"locality",
    "wof:population":29
},
  "geometry": {"coordinates":[76.388887,22.734904],"type":"Point"}
}