{
  "type": "Feature",
  "properties": {
    "iso:country":"IN",
    "ks:ks_name":"Kukurtopa",
    "ks:ks_pop":348,
    "ks:ks_type":"VILLAGE",
    "name:eng_x_preferred":[
        "Kukurtopa"
    ],
    "wof:name":"Kukurtopa",
    "wof:placetype":"locality",
    "wof:population":348
},
  "geometry": {"coordinates":[87.225494,24.182186],"type":"Point"}
}