{
  "type": "Feature",
  "properties": {
    "iso:country":"IN",
    "ks:ks_name":"Eduvangi",
    "ks:ks_pop":65,
    "ks:ks_type":"HABITATION",
    "name:eng_x_preferred":[
        "Eduvangi"
    ],
    "wof:name":"Eduvangi",
    "wof:placetype":"locality",
    "wof:population":65
},
  "geometry": {"coordinates":[74.72506,13.804833],"type":"Point"}
}