{
  "type": "Feature",
  "properties": {
    "iso:country":"IN",
    "ks:ks_name":"Madadda",
    "ks:ks_pop":624,
    "ks:ks_type":"HABITATION",
    "name:eng_x_preferred":[
        "Madadda"
    ],
    "wof:name":"Madadda",
    "wof:placetype":"locality",
    "wof:population":624
},
  "geometry": {"coordinates":[75.107715,12.953256],"type":"Point"}
}