{
  "type": "Feature",
  "properties": {
    "iso:country":"IN",
    "ks:ks_name":"Bhangidia Gaon",
    "ks:ks_pop":565,
    "ks:ks_type":"VILLAGE",
    "name:eng_x_preferred":[
        "Bhangidia Gaon"
    ],
    "wof:name":"Bhangidia Gaon",
    "wof:placetype":"locality",
    "wof:population":565
},
  "geometry": {"coordinates":[94.634182,27.382854],"type":"Point"}
}