{
  "type": "Feature",
  "properties": {
    "iso:country":"IN",
    "ks:ks_name":"Narayanpur",
    "ks:ks_pop":199,
    "ks:ks_type":"VILLAGE",
    "name:eng_x_preferred":[
        "Narayanpur"
    ],
    "wof:name":"Narayanpur",
    "wof:placetype":"locality",
    "wof:population":199
},
  "geometry": {"coordinates":[87.379841,24.838986],"type":"Point"}
}