{
  "type": "Feature",
  "properties": {
    "iso:country":"IN",
    "ks:ks_name":"Laripara",
    "ks:ks_pop":69,
    "ks:ks_type":"HABITATION",
    "name:eng_x_preferred":[
        "Laripara"
    ],
    "wof:name":"Laripara",
    "wof:placetype":"locality",
    "wof:population":69
},
  "geometry": {"coordinates":[82.60961500000001,22.593185],"type":"Point"}
}