{
  "type": "Feature",
  "properties": {
    "iso:country":"IN",
    "ks:ks_name":"Didauli",
    "ks:ks_pop":217,
    "ks:ks_type":"VILLAGE",
    "name:eng_x_preferred":[
        "Didauli"
    ],
    "wof:name":"Didauli",
    "wof:placetype":"locality",
    "wof:population":217
},
  "geometry": {"coordinates":[78.909978,24.486952],"type":"Point"}
}