{
  "type": "Feature",
  "properties": {
    "iso:country":"IN",
    "ks:ks_alt_nam":"BAIGAPARA",
    "ks:ks_name":"Baigapara",
    "ks:ks_pop":153,
    "ks:ks_type":"HABITATION",
    "name:eng_x_preferred":[
        "Baigapara"
    ],
    "wof:name":"Baigapara",
    "wof:placetype":"locality",
    "wof:population":153
},
  "geometry": {"coordinates":[81.399787,22.387608],"type":"Point"}
}