{
  "type": "Feature",
  "properties": {
    "gn:admin1_code":"10.0",
    "gn:admin2_code":"69.0",
    "gn:asciiname":"Dhaman",
    "gn:country_code":"IN",
    "gn:dem":1105,
    "gn:feature_class":"P",
    "gn:feature_code":"PPL",
    "gn:name":"Dh\u0101man",
    "gn:population":0,
    "gn:timezone":"Asia/Kolkata",
    "iso:country":"IN",
    "wof:name":"Dhaman",
    "wof:placetype":"locality"
},
  "geometry": {"coordinates":[77.05703000000003,30.73075],"type":"Point"}
}