{
  "type": "Feature",
  "properties": {
    "iso:country":"IN",
    "ks:ks_name":"Jaibigha",
    "ks:ks_pop":76,
    "ks:ks_type":"HABITATION",
    "name:eng_x_preferred":[
        "Jaibigha"
    ],
    "wof:name":"Jaibigha",
    "wof:placetype":"locality",
    "wof:population":76
},
  "geometry": {"coordinates":[84.90505400000001,25.090653],"type":"Point"}
}