{
  "type": "Feature",
  "properties": {
    "iso:country":"IN",
    "ks:ks_name":"Silatvel",
    "ks:ks_pop":0,
    "ks:ks_type":"VILLAGE",
    "name:eng_x_preferred":[
        "Silatvel"
    ],
    "wof:name":"Silatvel",
    "wof:placetype":"locality",
    "wof:population":0
},
  "geometry": {"coordinates":[73.57242100000001,21.23239],"type":"Point"}
}