{
  "type": "Feature",
  "properties": {
    "iso:country":"IN",
    "ks:ks_name":"Thimmareddigari Indlu",
    "ks:ks_pop":23,
    "ks:ks_type":"HABITATION",
    "name:eng_x_preferred":[
        "Thimmareddigari Indlu"
    ],
    "wof:name":"Thimmareddigari Indlu",
    "wof:placetype":"locality",
    "wof:population":23
},
  "geometry": {"coordinates":[78.97118500000001,13.675674],"type":"Point"}
}