{
  "type": "Feature",
  "properties": {
    "gn:admin1_code":"35.0",
    "gn:admin2_code":"458.0",
    "gn:asciiname":"Holiyakheri",
    "gn:country_code":"IN",
    "gn:dem":419,
    "gn:feature_class":"P",
    "gn:feature_code":"PPL",
    "gn:name":"Holiy\u0101kheri",
    "gn:population":0,
    "gn:timezone":"Asia/Kolkata",
    "iso:country":"IN",
    "wof:name":"Holiyakheri",
    "wof:placetype":"neighbourhood"
},
  "geometry": {"coordinates":[76.99721,24.43718],"type":"Point"}
}