{
  "type": "Feature",
  "properties": {
    "iso:country":"IN",
    "ks:ks_name":"Bhuitoli",
    "ks:ks_pop":296,
    "ks:ks_type":"HABITATION",
    "name:eng_x_preferred":[
        "Bhuitoli"
    ],
    "wof:name":"Bhuitoli",
    "wof:placetype":"locality",
    "wof:population":296
},
  "geometry": {"coordinates":[85.190107,24.940512],"type":"Point"}
}