{
  "type": "Feature",
  "properties": {
    "iso:country":"IN",
    "ks:ks_name":"P Mangli Mishir",
    "ks:ks_pop":131,
    "ks:ks_type":"HABITATION",
    "ks:ks_uagg_main":0,
    "name:eng_x_preferred":[
        "P Mangli Mishir"
    ],
    "wof:name":"P Mangli Mishir",
    "wof:placetype":"neighbourhood",
    "wof:population":131
},
  "geometry": {"coordinates":[81.36799499999999,26.297487],"type":"Point"}
}