{
  "type": "Feature",
  "properties": {
    "gn:admin1_code":"25",
    "gn:admin2_code":"606.0",
    "gn:asciiname":"Pushpagiri",
    "gn:country_code":"IN",
    "gn:dem":189,
    "gn:feature_class":"P",
    "gn:feature_code":"PPL",
    "gn:name":"Pushpagiri",
    "gn:population":0,
    "gn:timezone":"Asia/Kolkata",
    "iso:country":"IN",
    "ks:ks_name":"Pushpagiri",
    "ks:ks_pop":860,
    "ks:ks_type":"VILLAGE",
    "ks:ks_uagg_main":0,
    "name:eng_x_preferred":[
        "Pushpagiri"
    ],
    "name:hin_x_preferred":[
        "\u092a\u0941\u0937\u094d\u092a\u0917\u093f\u0930\u093f"
    ],
    "wof:name":"Pushpagiri",
    "wof:placetype":"neighbourhood",
    "wof:population":860
},
  "geometry": {"coordinates":[79.161726,12.646263],"type":"Point"}
}