{
  "type": "Feature",
  "properties": {
    "iso:country":"IN",
    "ks:ks_name":"Thajmahal Street",
    "ks:ks_pop":788,
    "ks:ks_type":"HABITATION",
    "ks:ks_uagg_main":0,
    "name:eng_x_preferred":[
        "Thajmahal Street"
    ],
    "wof:name":"Thajmahal Street",
    "wof:placetype":"neighbourhood",
    "wof:population":788
},
  "geometry": {"coordinates":[79.197598,9.973375],"type":"Point"}
}