{
  "type": "Feature",
  "properties": {
    "gn:admin1_code":"24",
    "gn:admin2_code":"120.0",
    "gn:asciiname":"Rajmahal",
    "gn:country_code":"IN",
    "gn:dem":309,
    "gn:feature_class":"P",
    "gn:feature_code":"PPL",
    "gn:name":"R\u0101jmahal",
    "gn:population":0,
    "gn:timezone":"Asia/Kolkata",
    "iso:country":"IN",
    "name:und_x_variant":[
        "R\u0101jmahal",
        "R\u0101jmah\u0101l"
    ],
    "wof:name":"Rajmahal",
    "wof:placetype":"locality"
},
  "geometry": {"coordinates":[75.46581,25.89217],"type":"Point"}
}