{
  "type": "Feature",
  "properties": {
    "gn:admin1_code":"24",
    "gn:admin2_code":"120.0",
    "gn:asciiname":"Rajmahal",
    "gn:country_code":"IN",
    "gn:dem":309,
    "gn:feature_class":"P",
    "gn:feature_code":"PPL",
    "gn:name":"R\u0101jmahal",
    "gn:population":0,
    "gn:timezone":"Asia/Kolkata",
    "iso:country":"IN",
    "name:ben_x_preferred":[
        "\u09b0\u09be\u099c\u09ae\u09b9\u09b2"
    ],
    "name:bih_x_preferred":[
        "\u0930\u093e\u091c\u092e\u0939\u0932"
    ],
    "name:bpy_x_preferred":[
        "\u09b0\u09be\u099c\u09ae\u09b9\u09b2"
    ],
    "name:cat_x_preferred":[
        "Rajmahal"
    ],
    "name:ceb_x_preferred":[
        "R\u0101jmahal"
    ],
    "name:fra_x_preferred":[
        "Rajmahal"
    ],
    "name:hin_x_preferred":[
        "\u0930\u093e\u091c\u092e\u0939\u0932"
    ],
    "name:ita_x_preferred":[
        "Rajmahal"
    ],
    "name:jpn_x_preferred":[
        "\u30e9\u30fc\u30b8\u30de\u30cf\u30eb"
    ],
    "name:mlg_x_preferred":[
        "Rajmahal"
    ],
    "name:msa_x_preferred":[
        "Rajmahal"
    ],
    "name:nep_x_preferred":[
        "\u0930\u093e\u091c\u092e\u0939\u0932"
    ],
    "name:nld_x_preferred":[
        "Rajmahal"
    ],
    "name:rus_x_preferred":[
        "\u0420\u0430\u0434\u0436\u043c\u0430\u0445\u0430\u043b"
    ],
    "name:swe_x_preferred":[
        "Rajmahal"
    ],
    "name:ukr_x_preferred":[
        "\u0420\u0430\u0434\u0436\u043c\u0430\u0445\u0430\u043b"
    ],
    "name:und_x_variant":[
        "R\u0101jmahal",
        "R\u0101jmah\u0101l"
    ],
    "name:urd_x_preferred":[
        "\u0631\u0627\u062c \u0645\u062d\u0644"
    ],
    "name:vie_x_preferred":[
        "Rajmahal"
    ],
    "name:zho_x_preferred":[
        "\u62c9\u6770\u9a6c\u54c8\u5c14"
    ],
    "wof:name":"Rajmahal",
    "wof:placetype":"locality"
},
  "geometry": {"coordinates":[75.46581,25.89217],"type":"Point"}
}