{
  "type": "Feature",
  "properties": {
    "gn:admin1_code":"2.0",
    "gn:admin2_code":"551.0",
    "gn:asciiname":"Tsapalavandlapalli",
    "gn:country_code":"IN",
    "gn:dem":135,
    "gn:feature_class":"P",
    "gn:feature_code":"PPL",
    "gn:name":"Tsapalav\u0101ndlapalli",
    "gn:population":0,
    "gn:timezone":"Asia/Kolkata",
    "iso:country":"IN",
    "wof:name":"Tsapalavandlapalli",
    "wof:placetype":"locality"
},
  "geometry": {"coordinates":[79.34205,14.15426],"type":"Point"}
}