{
  "type": "Feature",
  "properties": {
    "iso:country":"IN",
    "ks:ks_name":"Kalaminaput",
    "ks:ks_pop":415,
    "ks:ks_type":"VILLAGE",
    "ks:ks_uagg_main":0,
    "name:eng_x_preferred":[
        "Kalaminaput"
    ],
    "wof:name":"Kalaminaput",
    "wof:placetype":"locality",
    "wof:population":415
},
  "geometry": {"coordinates":[87.78898100000001,21.744939],"type":"Point"}
}