{
  "type": "Feature",
  "properties": {
    "iso:country":"IN",
    "ks:ks_name":"Ikarchala",
    "ks:ks_pop":2308,
    "ks:ks_type":"VILLAGE",
    "name:eng_x_preferred":[
        "Ikarchala"
    ],
    "wof:name":"Ikarchala",
    "wof:placetype":"locality",
    "wof:population":2308
},
  "geometry": {"coordinates":[89.459771,26.388418],"type":"Point"}
}