{
  "type": "Feature",
  "properties": {
    "iso:country":"IN",
    "ks:ks_name":"Nizampur",
    "ks:ks_pop":364,
    "ks:ks_type":"HABITATION",
    "name:eng_x_preferred":[
        "Nizampur"
    ],
    "wof:name":"Nizampur",
    "wof:placetype":"locality",
    "wof:population":364
},
  "geometry": {"coordinates":[82.60504400000001,26.524903],"type":"Point"}
}