{
  "type": "Feature",
  "properties": {
    "gn:admin1_code":"2.0",
    "gn:admin2_code":"554.0",
    "gn:asciiname":"Kongavaripalle",
    "gn:country_code":"IN",
    "gn:dem":668,
    "gn:feature_class":"P",
    "gn:feature_code":"PPL",
    "gn:name":"Kongav\u0101ripalle",
    "gn:population":0,
    "gn:timezone":"Asia/Kolkata",
    "iso:country":"IN",
    "wof:name":"Kongavaripalle",
    "wof:placetype":"locality"
},
  "geometry": {"coordinates":[78.70926999999998,13.20759],"type":"Point"}
}