{
  "type": "Feature",
  "properties": {
    "iso:country":"IN",
    "ks:ks_name":"Kavalanahalli",
    "ks:ks_pop":608,
    "ks:ks_type":"VILLAGE",
    "name:eng_x_preferred":[
        "Kavalanahalli"
    ],
    "wof:name":"Kavalanahalli",
    "wof:placetype":"locality",
    "wof:population":608
},
  "geometry": {"coordinates":[76.520922,14.511367],"type":"Point"}
}