{
  "type": "Feature",
  "properties": {
    "iso:country":"IN",
    "ks:ks_name":"Darji Deeh",
    "ks:ks_pop":100,
    "ks:ks_type":"HABITATION",
    "name:eng_x_preferred":[
        "Darji Deeh"
    ],
    "wof:name":"Darji Deeh",
    "wof:placetype":"locality",
    "wof:population":100
},
  "geometry": {"coordinates":[82.29321400000001,27.143658],"type":"Point"}
}