{
  "type": "Feature",
  "properties": {
    "iso:country":"IN",
    "ks:ks_name":"Ramanathapuram",
    "ks:ks_pop":3478,
    "ks:ks_type":"VILLAGE",
    "ks:ks_uagg_main":0,
    "name:eng_x_preferred":[
        "Ramanathapuram"
    ],
    "wof:name":"Ramanathapuram",
    "wof:placetype":"neighbourhood",
    "wof:population":3478
},
  "geometry": {"coordinates":[77.431332,9.281807],"type":"Point"}
}