{
  "type": "Feature",
  "properties": {
    "iso:country":"IN",
    "ks:ks_name":"Madanpur",
    "ks:ks_pop":164,
    "ks:ks_type":"VILLAGE",
    "ks:ks_uagg_main":0,
    "name:eng_x_preferred":[
        "Madanpur"
    ],
    "wof:name":"Madanpur",
    "wof:placetype":"neighbourhood",
    "wof:population":164
},
  "geometry": {"coordinates":[84.4417,20.806258],"type":"Point"}
}