{
  "type": "Feature",
  "properties": {
    "iso:country":"IN",
    "ks:ks_name":"Gheradategad",
    "ks:ks_pop":173,
    "ks:ks_type":"HABITATION",
    "name:eng_x_preferred":[
        "Gheradategad"
    ],
    "wof:name":"Gheradategad",
    "wof:placetype":"locality",
    "wof:population":173
},
  "geometry": {"coordinates":[73.83489899999999,17.402641],"type":"Point"}
}