{
  "type": "Feature",
  "properties": {
    "iso:country":"IN",
    "ks:ks_name":"Bibipur",
    "ks:ks_pop":1750,
    "ks:ks_type":"VILLAGE",
    "ks:ks_uagg_main":0,
    "name:eng_x_preferred":[
        "Bibipur"
    ],
    "wof:name":"Bibipur",
    "wof:placetype":"neighbourhood",
    "wof:population":1750
},
  "geometry": {"coordinates":[80.068653,26.828317],"type":"Point"}
}