{
  "type": "Feature",
  "properties": {
    "iso:country":"IN",
    "ks:ks_name":"Pirpani",
    "ks:ks_pop":225,
    "ks:ks_type":"HABITATION",
    "name:eng_x_preferred":[
        "Pirpani"
    ],
    "wof:name":"Pirpani",
    "wof:placetype":"locality",
    "wof:population":225
},
  "geometry": {"coordinates":[74.99878099999999,21.371588],"type":"Point"}
}