{
  "type": "Feature",
  "properties": {
    "gn:admin1_code":"3.0",
    "gn:admin2_code":"312.0",
    "gn:asciiname":"Koliagaon",
    "gn:country_code":"IN",
    "gn:dem":86,
    "gn:feature_class":"P",
    "gn:feature_code":"PPL",
    "gn:name":"Koli\u0101g\u0101on",
    "gn:population":0,
    "gn:timezone":"Asia/Kolkata",
    "iso:country":"IN",
    "wof:name":"Koliagaon",
    "wof:placetype":"locality"
},
  "geometry": {"coordinates":[94.23614000000001,27.03594],"type":"Point"}
}