{
  "type": "Feature",
  "properties": {
    "iso:country":"IN",
    "ks:ks_name":"Haragodu",
    "ks:ks_pop":220,
    "ks:ks_type":"HABITATION",
    "name:eng_x_preferred":[
        "Haragodu"
    ],
    "wof:name":"Haragodu",
    "wof:placetype":"locality",
    "wof:population":220
},
  "geometry": {"coordinates":[75.574161,13.161048],"type":"Point"}
}