{
  "type": "Feature",
  "properties": {
    "gn:admin1_code":"10",
    "gn:admin2_code":"70.0",
    "gn:asciiname":"Mohra",
    "gn:country_code":"IN",
    "gn:dem":271,
    "gn:feature_class":"P",
    "gn:feature_code":"PPL",
    "gn:name":"Mohra",
    "gn:population":0,
    "gn:timezone":"Asia/Kolkata",
    "iso:country":"IN",
    "name:ara_x_preferred":[
        "\u0631\u0647\u0627\u0646"
    ],
    "name:fas_x_preferred":[
        "\u0645\u0647\u0631\u0647"
    ],
    "name:hin_x_preferred":[
        "\u092e\u094b\u0939\u0930\u093e"
    ],
    "name:ita_x_preferred":[
        "Mohra"
    ],
    "name:new_x_preferred":[
        "\u092e\u094b\u0939\u0930\u093e"
    ],
    "name:pol_x_preferred":[
        "Mohra"
    ],
    "wof:name":"Mohra",
    "wof:placetype":"locality"
},
  "geometry": {"coordinates":[76.85098000000001,30.26786],"type":"Point"}
}