{
  "type": "Feature",
  "properties": {
    "gn:admin1_code":"19.0",
    "gn:admin2_code":"582.0",
    "gn:asciiname":"Nidugurki",
    "gn:country_code":"IN",
    "gn:dem":877,
    "gn:feature_class":"P",
    "gn:feature_code":"PPL",
    "gn:name":"Nidugurki",
    "gn:population":0,
    "gn:timezone":"Asia/Kolkata",
    "iso:country":"IN",
    "wof:name":"Nidugurki",
    "wof:placetype":"locality"
},
  "geometry": {"coordinates":[78.04890999999998,13.3175],"type":"Point"}
}