{
  "type": "Feature",
  "properties": {
    "iso:country":"IN",
    "ks:ks_name":"Gopalhat",
    "ks:ks_pop":592,
    "ks:ks_type":"VILLAGE",
    "name:eng_x_preferred":[
        "Gopalhat"
    ],
    "wof:name":"Gopalhat",
    "wof:placetype":"locality",
    "wof:population":592
},
  "geometry": {"coordinates":[88.20341999999999,24.309626],"type":"Point"}
}