{
  "type": "Feature",
  "properties": {
    "gn:admin1_code":"11.0",
    "gn:admin2_code":"33.0",
    "gn:asciiname":"Satenjlu",
    "gn:country_code":"IN",
    "gn:dem":1603,
    "gn:feature_class":"P",
    "gn:feature_code":"PPL",
    "gn:name":"Satenjlu",
    "gn:population":0,
    "gn:timezone":"Asia/Kolkata",
    "iso:country":"IN",
    "wof:name":"Satenjlu",
    "wof:placetype":"locality"
},
  "geometry": {"coordinates":[77.73456,31.13512],"type":"Point"}
}