{
  "type": "Feature",
  "properties": {
    "gn:admin1_code":"24.0",
    "gn:admin2_code":"117.0",
    "gn:asciiname":"Marri",
    "gn:country_code":"IN",
    "gn:dem":266,
    "gn:feature_class":"P",
    "gn:feature_code":"PPL",
    "gn:name":"Marri",
    "gn:population":0,
    "gn:timezone":"Asia/Kolkata",
    "iso:country":"IN",
    "name:ceb_x_preferred":[
        "Marri"
    ],
    "name:deu_x_preferred":[
        "Marri"
    ],
    "name:swe_x_preferred":[
        "Marri"
    ],
    "wof:name":"Marri",
    "wof:placetype":"locality"
},
  "geometry": {"coordinates":[72.54371,24.87328],"type":"Point"}
}