{
  "type": "Feature",
  "properties": {
    "iso:country":"IN",
    "ks:ks_name":"Kesarpur",
    "ks:ks_pop":1616,
    "ks:ks_type":"VILLAGE",
    "name:eng_x_preferred":[
        "Kesarpur"
    ],
    "wof:name":"Kesarpur",
    "wof:placetype":"locality",
    "wof:population":1616
},
  "geometry": {"coordinates":[86.299161,20.482226],"type":"Point"}
}