{
  "type": "Feature",
  "properties": {
    "iso:country":"IN",
    "ks:ks_name":"A.Ma. Mohabbatpur",
    "ks:ks_pop":57,
    "ks:ks_type":"VILLAGE",
    "name:eng_x_preferred":[
        "A.Ma. Mohabbatpur"
    ],
    "wof:name":"A.Ma. Mohabbatpur",
    "wof:placetype":"locality",
    "wof:population":57
},
  "geometry": {"coordinates":[83.42822,25.65476],"type":"Point"}
}