{
  "type": "Feature",
  "properties": {
    "iso:country":"IN",
    "ks:ks_name":"Mujawar Purwee Ryt.",
    "ks:ks_pop":137,
    "ks:ks_type":"VILLAGE",
    "name:eng_x_preferred":[
        "Mujawar Purwee Ryt."
    ],
    "wof:name":"Mujawar Purwee Ryt.",
    "wof:placetype":"locality",
    "wof:population":137
},
  "geometry": {"coordinates":[78.71943400000001,22.034641],"type":"Point"}
}