{
  "type": "Feature",
  "properties": {
    "iso:country":"IN",
    "ks:ks_name":"Madyottu",
    "ks:ks_pop":188,
    "ks:ks_type":"HABITATION",
    "name:eng_x_preferred":[
        "Madyottu"
    ],
    "wof:name":"Madyottu",
    "wof:placetype":"locality",
    "wof:population":188
},
  "geometry": {"coordinates":[75.347251,12.769337],"type":"Point"}
}