{
  "type": "Feature",
  "properties": {
    "gn:admin1_code":"36",
    "gn:admin2_code":"199.0",
    "gn:asciiname":"Udhwar",
    "gn:country_code":"IN",
    "gn:dem":83,
    "gn:feature_class":"P",
    "gn:feature_code":"PPL",
    "gn:name":"Udhw\u0101r",
    "gn:population":0,
    "gn:timezone":"Asia/Kolkata",
    "iso:country":"IN",
    "ks:ks_alt_nam":"Udhw\u0101r",
    "ks:ks_name":"Udhwar",
    "ks:ks_type":"VILLAGE",
    "ks:ks_uagg_main":0,
    "name:eng_x_preferred":[
        "Udhwar"
    ],
    "name:eng_x_variant":[
        "Udhw\u0101r"
    ],
    "wof:name":"Udhwar",
    "wof:placetype":"neighbourhood"
},
  "geometry": {"coordinates":[82.432711,25.231489],"type":"Point"}
}