{
  "type": "Feature",
  "properties": {
    "gn:admin1_code":"12.0",
    "gn:admin2_code":"001",
    "gn:asciiname":"Kinyal",
    "gn:country_code":"IN",
    "gn:dem":1834,
    "gn:feature_class":"P",
    "gn:feature_code":"PPL",
    "gn:name":"Kinyal",
    "gn:population":0,
    "gn:timezone":"Asia/Kolkata",
    "iso:country":"IN",
    "wof:name":"Kinyal",
    "wof:placetype":"locality"
},
  "geometry": {"coordinates":[74.13110999999998,34.45917],"type":"Point"}
}