{
  "type": "Feature",
  "properties": {
    "iso:country":"IN",
    "ks:ks_name":"Dumurdahadham",
    "ks:ks_pop":4485,
    "ks:ks_type":"VILLAGE",
    "ks:ks_uagg_main":0,
    "name:eng_x_preferred":[
        "Dumurdahadham"
    ],
    "wof:name":"Dumurdahadham",
    "wof:placetype":"locality",
    "wof:population":4485
},
  "geometry": {"coordinates":[88.43259399999999,23.036395],"type":"Point"}
}