{
  "type": "Feature",
  "properties": {
    "iso:country":"IN",
    "ks:ks_name":"Simko",
    "ks:ks_pop":374,
    "ks:ks_type":"VILLAGE",
    "name:eng_x_preferred":[
        "Simko"
    ],
    "wof:name":"Simko",
    "wof:placetype":"locality",
    "wof:population":374
},
  "geometry": {"coordinates":[85.116714,22.636893],"type":"Point"}
}