{
  "type": "Feature",
  "properties": {
    "gn:admin1_code":"10.0",
    "gn:admin2_code":"79.0",
    "gn:asciiname":"Kutyana",
    "gn:country_code":"IN",
    "gn:dem":199,
    "gn:feature_class":"P",
    "gn:feature_code":"PPL",
    "gn:name":"Kutyana",
    "gn:population":0,
    "gn:timezone":"Asia/Kolkata",
    "iso:country":"IN",
    "wof:name":"Kutyana",
    "wof:placetype":"locality"
},
  "geometry": {"coordinates":[74.99927,29.31923],"type":"Point"}
}