{
  "type": "Feature",
  "properties": {
    "iso:country":"IN",
    "ks:ks_name":"15 STG-A",
    "ks:ks_pop":36,
    "ks:ks_type":"VILLAGE",
    "name:eng_x_preferred":[
        "15 STG-A"
    ],
    "wof:name":"15 STG-A",
    "wof:placetype":"locality",
    "wof:population":36
},
  "geometry": {"coordinates":[74.2034,29.5156],"type":"Point"}
}