{
  "type": "Feature",
  "properties": {
    "iso:country":"IN",
    "ks:ks_name":"Poranki",
    "ks:ks_pop":22436,
    "ks:ks_type":"VILLAGE",
    "ks:ks_uagg_main":0,
    "name:eng_x_preferred":[
        "Poranki"
    ],
    "wof:name":"Poranki",
    "wof:placetype":"neighbourhood",
    "wof:population":22436
},
  "geometry": {"coordinates":[80.70703,16.476098],"type":"Point"}
}