{
  "type": "Feature",
  "properties": {
    "iso:country":"IN",
    "ks:ks_name":"Sitekasa Kamakasur",
    "ks:ks_pop":211,
    "ks:ks_type":"HABITATION",
    "name:eng_x_preferred":[
        "Sitekasa Kamakasur"
    ],
    "wof:name":"Sitekasa Kamakasur",
    "wof:placetype":"locality",
    "wof:population":211
},
  "geometry": {"coordinates":[79.64564,21.443332],"type":"Point"}
}