{
  "type": "Feature",
  "properties": {
    "iso:country":"IN",
    "ks:ks_name":"Kurwade",
    "ks:ks_pop":377,
    "ks:ks_type":"VILLAGE",
    "name:eng_x_preferred":[
        "Kurwade"
    ],
    "wof:name":"Kurwade",
    "wof:placetype":"locality",
    "wof:population":377
},
  "geometry": {"coordinates":[73.308029,18.183624],"type":"Point"}
}