{
  "type": "Feature",
  "properties": {
    "iso:country":"IN",
    "ks:ks_name":"Rasoolpur Mubarakpur",
    "ks:ks_pop":1749,
    "ks:ks_type":"VILLAGE",
    "ks:ks_uagg_main":0,
    "name:eng_x_preferred":[
        "Rasoolpur Mubarakpur"
    ],
    "wof:name":"Rasoolpur Mubarakpur",
    "wof:placetype":"locality",
    "wof:population":1749
},
  "geometry": {"coordinates":[82.687483,26.537258],"type":"Point"}
}