{
  "type": "Feature",
  "properties": {
    "gn:admin1_code":"36",
    "gn:admin2_code":"154.0",
    "gn:asciiname":"Bhulbhulaiyapur",
    "gn:country_code":"IN",
    "gn:dem":124,
    "gn:feature_class":"P",
    "gn:feature_code":"PPL",
    "gn:name":"Bhulbhulaiy\u0101pur",
    "gn:population":0,
    "gn:timezone":"Asia/Kolkata",
    "iso:country":"IN",
    "wof:name":"Bhulbhulaiyapur",
    "wof:placetype":"neighbourhood"
},
  "geometry": {"coordinates":[81.15935,27.40743],"type":"Point"}
}