{
  "type": "Feature",
  "properties": {
    "iso:country":"IN",
    "ks:ks_name":"Karanpura",
    "ks:ks_pop":134,
    "ks:ks_type":"VILLAGE",
    "name:eng_x_preferred":[
        "Karanpura"
    ],
    "wof:name":"Karanpura",
    "wof:placetype":"locality",
    "wof:population":134
},
  "geometry": {"coordinates":[73.53908699999999,22.73186],"type":"Point"}
}