{
  "type": "Feature",
  "properties": {
    "iso:country":"IN",
    "ks:ks_name":"Kesharpura",
    "ks:ks_pop":210,
    "ks:ks_type":"VILLAGE",
    "name:eng_x_preferred":[
        "Kesharpura"
    ],
    "wof:name":"Kesharpura",
    "wof:placetype":"locality",
    "wof:population":210
},
  "geometry": {"coordinates":[74.645741,23.280668],"type":"Point"}
}