{
  "type": "Feature",
  "properties": {
    "iso:country":"IN",
    "ks:ks_name":"Kholpura",
    "ks:ks_pop":22,
    "ks:ks_type":"HABITATION",
    "name:eng_x_preferred":[
        "Kholpura"
    ],
    "wof:name":"Kholpura",
    "wof:placetype":"locality",
    "wof:population":22
},
  "geometry": {"coordinates":[75.22969500000001,24.992452],"type":"Point"}
}