{
  "type": "Feature",
  "properties": {
    "iso:country":"IN",
    "ks:ks_name":"Chandratikara",
    "ks:ks_pop":34,
    "ks:ks_type":"VILLAGE",
    "name:eng_x_preferred":[
        "Chandratikara"
    ],
    "wof:name":"Chandratikara",
    "wof:placetype":"locality",
    "wof:population":34
},
  "geometry": {"coordinates":[86.477924,21.323033],"type":"Point"}
}