{
  "type": "Feature",
  "properties": {
    "iso:country":"IN",
    "ks:ks_name":"Thachamalai",
    "ks:ks_pop":247,
    "ks:ks_type":"HABITATION",
    "name:eng_x_preferred":[
        "Thachamalai"
    ],
    "wof:name":"Thachamalai",
    "wof:placetype":"locality",
    "wof:population":247
},
  "geometry": {"coordinates":[77.331287,8.454263],"type":"Point"}
}