{
  "type": "Feature",
  "properties": {
    "iso:country":"IN",
    "ks:ks_alt_nam":"Farasgaon Dudhwara nayabasti",
    "ks:ks_name":"Farasgaon Dudhwara Nayabasti",
    "ks:ks_pop":256,
    "ks:ks_type":"HABITATION",
    "name:eng_x_preferred":[
        "Farasgaon Dudhwara Nayabasti"
    ],
    "wof:name":"Farasgaon Dudhwara Nayabasti",
    "wof:placetype":"locality",
    "wof:population":256
},
  "geometry": {"coordinates":[81.972348,20.196317],"type":"Point"}
}