{
  "type": "Feature",
  "properties": {
    "iso:country":"IN",
    "ks:ks_name":"Rajpur",
    "ks:ks_pop":251,
    "ks:ks_type":"HABITATION",
    "name:eng_x_preferred":[
        "Rajpur"
    ],
    "wof:name":"Rajpur",
    "wof:placetype":"locality",
    "wof:population":251
},
  "geometry": {"coordinates":[79.53216,23.772514],"type":"Point"}
}