{
  "type": "Feature",
  "properties": {
    "gn:admin1_code":"12",
    "gn:admin2_code":"14.0",
    "gn:asciiname":"Salar",
    "gn:country_code":"IN",
    "gn:dem":1816,
    "gn:feature_class":"P",
    "gn:feature_code":"PPL",
    "gn:name":"Salar",
    "gn:population":0,
    "gn:timezone":"Asia/Kolkata",
    "iso:country":"IN",
    "wof:name":"Salar",
    "wof:placetype":"locality"
},
  "geometry": {"coordinates":[75.24847,33.87888],"type":"Point"}
}