{
  "type": "Feature",
  "properties": {
    "iso:country":"IN",
    "ks:ks_name":"Thana Muvada Faliya",
    "ks:ks_pop":1328,
    "ks:ks_type":"HABITATION",
    "name:eng_x_preferred":[
        "Thana Muvada Faliya"
    ],
    "wof:name":"Thana Muvada Faliya",
    "wof:placetype":"locality",
    "wof:population":1328
},
  "geometry": {"coordinates":[73.893111,23.074167],"type":"Point"}
}