{
  "type": "Feature",
  "properties": {
    "iso:country":"IN",
    "ks:ks_name":"Ganeshpur",
    "ks:ks_pop":590,
    "ks:ks_type":"VILLAGE",
    "name:eng_x_preferred":[
        "Ganeshpur"
    ],
    "wof:name":"Ganeshpur",
    "wof:placetype":"locality",
    "wof:population":590
},
  "geometry": {"coordinates":[86.22023,23.782838],"type":"Point"}
}