{
  "type": "Feature",
  "properties": {
    "gn:admin1_code":"12.0",
    "gn:admin2_code":"2.0",
    "gn:asciiname":"Naman",
    "gn:country_code":"IN",
    "gn:dem":1594,
    "gn:feature_class":"P",
    "gn:feature_code":"PPL",
    "gn:name":"N\u0101man",
    "gn:population":0,
    "gn:timezone":"Asia/Kolkata",
    "iso:country":"IN",
    "name:ceb_x_preferred":[
        "Naman"
    ],
    "name:fas_x_preferred":[
        "\u0646\u0627\u0645\u0646"
    ],
    "name:swe_x_preferred":[
        "Naman"
    ],
    "wof:name":"Naman",
    "wof:placetype":"locality"
},
  "geometry": {"coordinates":[74.91545000000001,33.94125],"type":"Point"}
}