{
  "type": "Feature",
  "properties": {
    "gn:admin1_code":"36",
    "gn:admin2_code":"200.0",
    "gn:asciiname":"Ghoraghar",
    "gn:country_code":"IN",
    "gn:dem":540,
    "gn:feature_class":"P",
    "gn:feature_code":"PPL",
    "gn:name":"Ghor\u0101ghar",
    "gn:population":0,
    "gn:timezone":"Asia/Kolkata",
    "iso:country":"IN",
    "ks:ks_name":"Ghoraghar",
    "ks:ks_pop":400,
    "ks:ks_type":"HABITATION",
    "name:eng_x_preferred":[
        "Ghoraghar"
    ],
    "wof:name":"Ghoraghar",
    "wof:placetype":"locality",
    "wof:population":400
},
  "geometry": {"coordinates":[83.107721,24.527966],"type":"Point"}
}