{
  "type": "Feature",
  "properties": {
    "iso:country":"IN",
    "ks:ks_name":"Semar Tori",
    "ks:ks_pop":53,
    "ks:ks_type":"VILLAGE",
    "name:eng_x_preferred":[
        "Semar Tori"
    ],
    "wof:name":"Semar Tori",
    "wof:placetype":"locality",
    "wof:population":53
},
  "geometry": {"coordinates":[77.337075,25.074928],"type":"Point"}
}