{
  "type": "Feature",
  "properties": {
    "iso:country":"IN",
    "ks:ks_name":"Puttaiahnaalya",
    "ks:ks_pop":33,
    "ks:ks_type":"HABITATION",
    "name:eng_x_preferred":[
        "Puttaiahnaalya"
    ],
    "wof:name":"Puttaiahnaalya",
    "wof:placetype":"locality",
    "wof:population":33
},
  "geometry": {"coordinates":[77.154596,12.950211],"type":"Point"}
}