{
  "type": "Feature",
  "properties": {
    "iso:country":"IN",
    "ks:ks_name":"Soni",
    "ks:ks_pop":164,
    "ks:ks_type":"VILLAGE",
    "name:eng_x_preferred":[
        "Soni"
    ],
    "wof:name":"Soni",
    "wof:placetype":"locality",
    "wof:population":164
},
  "geometry": {"coordinates":[78.308634,30.186654],"type":"Point"}
}