{
  "type": "Feature",
  "properties": {
    "gn:admin1_code":"13.0",
    "gn:admin2_code":"593",
    "gn:asciiname":"Cherupulassheri",
    "gn:country_code":"IN",
    "gn:dem":46,
    "gn:feature_class":"P",
    "gn:feature_code":"PPL",
    "gn:name":"Cherupulassh\u0113ri",
    "gn:population":0,
    "gn:timezone":"Asia/Kolkata",
    "iso:country":"IN",
    "name:und_x_variant":[
        "Cherupulassh\u0113ri",
        "Cheruppulasseri"
    ],
    "wof:name":"Cherupulassheri",
    "wof:placetype":"neighbourhood"
},
  "geometry": {"coordinates":[76.31877,10.87462],"type":"Point"}
}