{
  "type": "Feature",
  "properties": {
    "iso:country":"IN",
    "ks:ks_name":"Usari",
    "ks:ks_pop":537,
    "ks:ks_type":"VILLAGE",
    "name:eng_x_preferred":[
        "Usari"
    ],
    "wof:name":"Usari",
    "wof:placetype":"locality",
    "wof:population":537
},
  "geometry": {"coordinates":[81.766949,19.422473],"type":"Point"}
}