{
  "type": "Feature",
  "properties": {
    "iso:country":"IN",
    "ks:ks_name":"Kalsima",
    "ks:ks_pop":220,
    "ks:ks_type":"HABITATION",
    "name:eng_x_preferred":[
        "Kalsima"
    ],
    "wof:name":"Kalsima",
    "wof:placetype":"locality",
    "wof:population":220
},
  "geometry": {"coordinates":[79.645995,29.551913],"type":"Point"}
}