{
  "type": "Feature",
  "properties": {
    "iso:country":"IN",
    "ks:ks_name":"Sindhiputtu",
    "ks:ks_pop":257,
    "ks:ks_type":"HABITATION",
    "name:eng_x_preferred":[
        "Sindhiputtu"
    ],
    "wof:name":"Sindhiputtu",
    "wof:placetype":"locality",
    "wof:population":257
},
  "geometry": {"coordinates":[82.52034500000001,18.302184],"type":"Point"}
}