{
  "type": "Feature",
  "properties": {
    "gn:country":"IN",
    "gn:fcode":"PPL",
    "gn:population":30627,
    "iso:country":"IN",
    "name:ben_x_preferred":[
        "\u09b0\u09be\u099c\u0996\u09c7\u09b0\u09be"
    ],
    "name:bpy_x_preferred":[
        "\u09b0\u09be\u099c\u0996\u09c7\u09b0\u09be"
    ],
    "name:ceb_x_preferred":[
        "R\u0101j\u0101khera"
    ],
    "name:eng_x_preferred":[
        "Rajakhera"
    ],
    "name:fra_x_preferred":[
        "Rajakhera"
    ],
    "name:hin_x_preferred":[
        "\u0930\u093e\u091c\u093e\u0916\u0947\u0921\u093c\u093e"
    ],
    "name:ita_x_preferred":[
        "Rajakhera"
    ],
    "name:mlg_x_preferred":[
        "Rajakhera"
    ],
    "name:msa_x_preferred":[
        "Rajakhera"
    ],
    "name:nld_x_preferred":[
        "Rajakhera"
    ],
    "name:ori_x_preferred":[
        "\u0b30\u0b3e\u0b1c\u0b3e\u0b16\u0b47\u0b30\u0b3e"
    ],
    "name:por_x_preferred":[
        "Rajakhera"
    ],
    "name:swe_x_preferred":[
        "R\u0101j\u0101khera"
    ],
    "name:vie_x_preferred":[
        "Rajakhera"
    ],
    "name:zho_x_preferred":[
        "\u62c9\u8d3e\u51ef\u62c9"
    ],
    "qs:name":"Rajakhera",
    "qs:name_adm0":"India",
    "qs:name_adm1":"Rajasthan",
    "qs:photos_9k":1,
    "qs:photos_9r":1,
    "qs:photos_all":1,
    "qs:photos_sr":0,
    "qs:placetype":"Town",
    "qs:pop_sr":"7",
    "wd:wordcount":628,
    "wof:name":"Rajakhera",
    "wof:placetype":"locality",
    "wof:population":30627
},
  "geometry": {"coordinates":[78.17139,26.89611],"type":"Point"}
}