{
  "type": "Feature",
  "properties": {
    "iso:country":"IN",
    "ks:ks_name":"Bachai Bari",
    "ks:ks_pop":156,
    "ks:ks_type":"HABITATION",
    "name:eng_x_preferred":[
        "Bachai Bari"
    ],
    "wof:name":"Bachai Bari",
    "wof:placetype":"locality",
    "wof:population":156
},
  "geometry": {"coordinates":[91.464732,24.019067],"type":"Point"}
}