{
  "type": "Feature",
  "properties": {
    "iso:country":"IN",
    "ks:ks_name":"Madavalasa",
    "ks:ks_pop":128,
    "ks:ks_type":"HABITATION",
    "name:eng_x_preferred":[
        "Madavalasa"
    ],
    "wof:name":"Madavalasa",
    "wof:placetype":"locality",
    "wof:population":128
},
  "geometry": {"coordinates":[83.248262,18.724704],"type":"Point"}
}