{
  "type": "Feature",
  "properties": {
    "iso:country":"IN",
    "ks:ks_name":"Moulpur",
    "ks:ks_pop":739,
    "ks:ks_type":"VILLAGE",
    "ks:ks_uagg_main":0,
    "name:eng_x_preferred":[
        "Moulpur"
    ],
    "wof:name":"Moulpur",
    "wof:placetype":"neighbourhood",
    "wof:population":739
},
  "geometry": {"coordinates":[88.14116799999999,25.028374],"type":"Point"}
}