{
  "type": "Feature",
  "properties": {
    "gn:admin1_code":"35.0",
    "gn:admin2_code":"440.0",
    "gn:asciiname":"Umatti",
    "gn:country_code":"IN",
    "gn:dem":176,
    "gn:feature_class":"P",
    "gn:feature_code":"PPL",
    "gn:name":"Umatt\u012b",
    "gn:population":0,
    "gn:timezone":"Asia/Kolkata",
    "iso:country":"IN",
    "ks:ks_name":"Ummatti",
    "ks:ks_pop":2,
    "ks:ks_type":"VILLAGE",
    "name:eng_x_preferred":[
        "Ummatti"
    ],
    "name:eng_x_variant":[
        "Umatti"
    ],
    "wof:name":"Ummatti",
    "wof:placetype":"locality",
    "wof:population":2
},
  "geometry": {"coordinates":[75.90247100000001,22.18429],"type":"Point"}
}