{
  "type": "Feature",
  "properties": {
    "iso:country":"IN",
    "name:ara_x_preferred":[
        "\u062c\u0627\u064a\u0627 \u0646\u0627\u062c\u0627\u0631"
    ],
    "name:ben_bn_x_preferred":[
        "\u099c\u09df\u09be \u09a8\u0997\u09b0"
    ],
    "name:ben_in_x_preferred":[
        "\u099c\u09df\u09be \u09a8\u0997\u09b0"
    ],
    "name:eng_x_preferred":[
        "Jaya Nagar"
    ],
    "name:guj_x_preferred":[
        "\u0a9c\u0aaf\u0abe \u0aa8\u0a97\u0ab0"
    ],
    "name:hin_x_preferred":[
        "\u091c\u092f \u0928\u0917\u0930"
    ],
    "name:kan_x_preferred":[
        "\u0c9c\u0caf \u0ca8\u0c97\u0cb0"
    ],
    "name:mal_x_preferred":[
        "\u0d1c\u0d2f \u0d28\u0d17\u0d7c"
    ],
    "name:mar_x_preferred":[
        "\u091c\u092f\u093e \u0928\u0917\u0930"
    ],
    "name:pan_x_preferred":[
        "\u0a1c\u0a3f\u0a06 \u0a28\u0a17\u0a30"
    ],
    "name:tam_x_preferred":[
        "\u0b9c\u0baf \u0ba8\u0b95\u0bb0\u0bcd"
    ],
    "name:tel_x_preferred":[
        "\u0c1c\u0c2f \u0c28\u0c17\u0c30\u0c4d"
    ],
    "name:urd_x_preferred":[
        "\u062c\u06cc\u0627 \u0646\u06af\u0631"
    ],
    "qs:gn_adm0_cc":"IN",
    "qs:gn_local":1272018,
    "qs:gn_nam_loc":"Ernakulam, Ernakulam, Kerala, IN",
    "qs:gn_namadm1":"13",
    "qs:local_max":369,
    "qs:local_sum":1453,
    "qs:localhoods":14,
    "qs:name":"Jaya Nagar",
    "qs:name_adm0":"India",
    "qs:name_adm1":"Kerala",
    "qs:name_adm2":"Ernakulam",
    "qs:name_local":"Ernakulam",
    "qs:photo_max":20,
    "qs:photo_sum":35,
    "qs:placetype":"Suburb",
    "qs:quad_count":4,
    "qs:woe_adm0":23424848,
    "qs:woe_adm1":2345747,
    "qs:woe_adm2":12586468,
    "qs:woe_lau":0,
    "qs:woe_local":2295342,
    "qs:woe_ver":"7.10.0",
    "wof:lang":[
        "eng"
    ],
    "wof:name":"Jaya Nagar",
    "wof:placetype":"neighbourhood"
},
  "geometry": {"coordinates":[76.31849200000001,9.951615],"type":"Point"}
}