{
  "type": "Feature",
  "properties": {
    "iso:country":"IN",
    "ks:ks_name":"Dharhanian",
    "ks:ks_pop":611,
    "ks:ks_type":"VILLAGE",
    "name:eng_x_preferred":[
        "Dharhanian"
    ],
    "wof:name":"Dharhanian",
    "wof:placetype":"locality",
    "wof:population":611
},
  "geometry": {"coordinates":[83.580454,25.037215],"type":"Point"}
}