{
  "type": "Feature",
  "properties": {
    "gn:admin1_code":"36.0",
    "gn:admin2_code":"192.0",
    "gn:asciiname":"Chak Saiyad Ashraf",
    "gn:country_code":"IN",
    "gn:dem":75,
    "gn:feature_class":"P",
    "gn:feature_code":"PPL",
    "gn:name":"Chak Saiyad Ashraf",
    "gn:population":0,
    "gn:timezone":"Asia/Kolkata",
    "iso:country":"IN",
    "wof:name":"Chak Saiyad Ashraf",
    "wof:placetype":"neighbourhood"
},
  "geometry": {"coordinates":[83.54161000000001,26.073],"type":"Point"}
}