{
  "type": "Feature",
  "properties": {
    "gn:gn_country":"IN",
    "gn:gn_fcode":"PPL",
    "gn:gn_pop":9554,
    "gn:population":9554,
    "iso:country":"IN",
    "name:asm_x_preferred":[
        "\u09ac\u09cb\u0995\u09be\u0996\u09be\u09a4"
    ],
    "name:ben_x_preferred":[
        "\u09ac\u09cb\u0995\u09be\u0996\u09be\u09a4"
    ],
    "name:bpy_x_preferred":[
        "\u09ac\u0995\u09be\u0996\u099f"
    ],
    "name:chi_x_preferred":[
        "\u535a\u5361\u5361\u7279"
    ],
    "name:dut_x_preferred":[
        "Bokakhat"
    ],
    "name:eng_x_preferred":[
        "Bokakhat"
    ],
    "name:fre_x_preferred":[
        "Bokakhat"
    ],
    "name:ita_x_preferred":[
        "Bokakhat"
    ],
    "name:mar_x_preferred":[
        "\u092c\u094b\u0915\u093e\u0916\u093e\u091f"
    ],
    "name:may_x_preferred":[
        "Bokakhat"
    ],
    "name:nan_x_preferred":[
        "Bokakhat"
    ],
    "name:new_x_preferred":[
        "\u092c\u094b\u0915\u093e\u0916\u093e\u091f"
    ],
    "name:por_x_preferred":[
        "Bokakhat"
    ],
    "name:swe_x_preferred":[
        "Bok\u0101kh\u0101t"
    ],
    "name:unk_x_variant":[
        "Bok\u0101kh\u0101t"
    ],
    "name:vie_x_preferred":[
        "Bokakhat"
    ],
    "qs_pg:aaroncc":"IN",
    "qs_pg:gn_country":"IN",
    "qs_pg:gn_fcode":"PPL",
    "qs_pg:gn_pop":9554,
    "qs_pg:name":"Bokakhat",
    "qs_pg:name_adm0":"India",
    "qs_pg:name_adm1":"Assam",
    "qs_pg:photos_9k":1,
    "qs_pg:photos_9r":1,
    "qs_pg:photos_all":9,
    "qs_pg:photos_sr":0,
    "qs_pg:pop_sr":5,
    "qs_pg:qs_pg_placetype":"locality",
    "qs_pg:qs_pg_placetype_gp":"Town",
    "qs_pg:woe_adm0":23424848,
    "woe:adm0_id":23424848,
    "woe:name_adm0":"India",
    "woe:name_adm1":"Assam",
    "woe:placetype":"Town",
    "wof:name":"Bokakhat",
    "wof:placetype":"locality",
    "wof:population":9554
},
  "geometry": {"coordinates":[93.60052,26.64018],"type":"Point"}
}