{
  "type": "Feature",
  "properties": {
    "iso:country":"IN",
    "ks:ks_name":"Muradpur",
    "ks:ks_pop":301,
    "ks:ks_type":"VILLAGE",
    "name:eng_x_preferred":[
        "Muradpur"
    ],
    "wof:name":"Muradpur",
    "wof:placetype":"locality",
    "wof:population":301
},
  "geometry": {"coordinates":[75.65068599999999,31.441747],"type":"Point"}
}