{
  "type": "Feature",
  "properties": {
    "iso:country":"IN",
    "ks:ks_name":"Semalpada",
    "ks:ks_pop":166,
    "ks:ks_type":"VILLAGE",
    "name:eng_x_preferred":[
        "Semalpada"
    ],
    "wof:name":"Semalpada",
    "wof:placetype":"locality",
    "wof:population":166
},
  "geometry": {"coordinates":[74.867502,23.126566],"type":"Point"}
}