{
  "type": "Feature",
  "properties": {
    "gn:admin1_code":"38.0",
    "gn:admin2_code":"362.0",
    "gn:asciiname":"Dundia",
    "gn:country_code":"IN",
    "gn:dem":132,
    "gn:feature_class":"P",
    "gn:feature_code":"PPL",
    "gn:name":"Dundia",
    "gn:population":0,
    "gn:timezone":"Asia/Kolkata",
    "iso:country":"IN",
    "ks:ks_name":"Dundua",
    "ks:ks_pop":758,
    "ks:ks_type":"VILLAGE",
    "name:eng_x_preferred":[
        "Dundua"
    ],
    "name:eng_x_variant":[
        "Dundia"
    ],
    "wof:name":"Dundua",
    "wof:placetype":"locality",
    "wof:population":758
},
  "geometry": {"coordinates":[87.544827,24.332359],"type":"Point"}
}