{
  "type": "Feature",
  "properties": {
    "gn:admin1_code":"12.0",
    "gn:admin2_code":"7.0",
    "gn:asciiname":"Seri",
    "gn:country_code":"IN",
    "gn:dem":1675,
    "gn:feature_class":"P",
    "gn:feature_code":"PPL",
    "gn:name":"Seri",
    "gn:population":0,
    "gn:timezone":"Asia/Kolkata",
    "iso:country":"IN",
    "name:ceb_x_preferred":[
        "Seri"
    ],
    "name:chv_x_preferred":[
        "\u0421\u0435\u0440\u0438"
    ],
    "name:deu_x_preferred":[
        "Seri"
    ],
    "name:fra_x_preferred":[
        "Seri"
    ],
    "name:heb_x_preferred":[
        "\u05e1\u05e8\u05d9"
    ],
    "name:ita_x_preferred":[
        "Seri"
    ],
    "name:nld_x_preferred":[
        "Seri"
    ],
    "name:pol_x_preferred":[
        "Seri"
    ],
    "name:rus_x_preferred":[
        "\u0421\u0435\u0440\u0438"
    ],
    "name:spa_x_preferred":[
        "Seri"
    ],
    "name:swe_x_preferred":[
        "Seri"
    ],
    "wof:name":"Seri",
    "wof:placetype":"locality"
},
  "geometry": {"coordinates":[75.62066999999998,32.6654],"type":"Point"}
}