{
  "type": "Feature",
  "properties": {
    "iso:country":"IN",
    "ks:ks_name":"Dolongdia",
    "ks:ks_pop":565,
    "ks:ks_type":"VILLAGE",
    "name:eng_x_preferred":[
        "Dolongdia"
    ],
    "wof:name":"Dolongdia",
    "wof:placetype":"locality",
    "wof:population":565
},
  "geometry": {"coordinates":[91.74789800000001,26.51725],"type":"Point"}
}