{
  "type": "Feature",
  "properties": {
    "iso:country":"IN",
    "ks:ks_name":"Kondagalale",
    "ks:ks_pop":43,
    "ks:ks_type":"VILLAGE",
    "name:eng_x_preferred":[
        "Kondagalale"
    ],
    "wof:name":"Kondagalale",
    "wof:placetype":"locality",
    "wof:population":43
},
  "geometry": {"coordinates":[75.12890899999999,14.321316],"type":"Point"}
}