{
  "type": "Feature",
  "properties": {
    "iso:country":"IN",
    "ks:ks_name":"Velar Theru",
    "ks:ks_pop":190,
    "ks:ks_type":"HABITATION",
    "name:eng_x_preferred":[
        "Velar Theru"
    ],
    "wof:name":"Velar Theru",
    "wof:placetype":"locality",
    "wof:population":190
},
  "geometry": {"coordinates":[79.12785700000001,10.370995],"type":"Point"}
}