{
  "type": "Feature",
  "properties": {
    "gn:admin1_code":"24.0",
    "gn:admin2_code":"110",
    "gn:asciiname":"Nayawas",
    "gn:country_code":"IN",
    "gn:dem":386,
    "gn:feature_class":"P",
    "gn:feature_code":"PPL",
    "gn:name":"Nay\u0101w\u0101s",
    "gn:population":0,
    "gn:timezone":"Asia/Kolkata",
    "iso:country":"IN",
    "name:und_x_variant":[
        "Nay\u0101w\u0101s",
        "R\u0101msinghpura"
    ],
    "wof:name":"Nayawas",
    "wof:placetype":"neighbourhood"
},
  "geometry": {"coordinates":[75.54678,26.86605],"type":"Point"}
}