{
  "type": "Feature",
  "properties": {
    "iso:country":"IN",
    "ks:ks_name":"Baithwasiya",
    "ks:ks_pop":3694,
    "ks:ks_type":"VILLAGE",
    "name:eng_x_preferred":[
        "Baithwasiya"
    ],
    "wof:name":"Baithwasiya",
    "wof:placetype":"locality",
    "wof:population":3694
},
  "geometry": {"coordinates":[72.964356,26.782858],"type":"Point"}
}