{
  "type": "Feature",
  "properties": {
    "iso:country":"IN",
    "ks:ks_name":"Dolibati",
    "ks:ks_pop":110,
    "ks:ks_type":"VILLAGE",
    "name:eng_x_preferred":[
        "Dolibati"
    ],
    "wof:name":"Dolibati",
    "wof:placetype":"locality",
    "wof:population":110
},
  "geometry": {"coordinates":[85.11548999999999,19.583131],"type":"Point"}
}