{
  "type": "Feature",
  "properties": {
    "iso:country":"IN",
    "ks:ks_name":"Jamuniya J. Jagatpur",
    "ks:ks_pop":450,
    "ks:ks_type":"VILLAGE",
    "ks:ks_uagg_main":0,
    "name:eng_x_preferred":[
        "Jamuniya J. Jagatpur"
    ],
    "wof:name":"Jamuniya J. Jagatpur",
    "wof:placetype":"neighbourhood",
    "wof:population":450
},
  "geometry": {"coordinates":[80.049409,28.452233],"type":"Point"}
}