{
  "type": "Feature",
  "properties": {
    "iso:country":"IN",
    "ks:ks_name":"Bihari",
    "ks:ks_pop":0,
    "ks:ks_type":"VILLAGE",
    "name:eng_x_preferred":[
        "Bihari"
    ],
    "wof:name":"Bihari",
    "wof:placetype":"locality",
    "wof:population":0
},
  "geometry": {"coordinates":[85.213148,24.315181],"type":"Point"}
}