{
  "type": "Feature",
  "properties": {
    "iso:country":"IN",
    "ks:ks_name":"Hutgar",
    "ks:ks_pop":83,
    "ks:ks_type":"HABITATION",
    "name:eng_x_preferred":[
        "Hutgar"
    ],
    "wof:name":"Hutgar",
    "wof:placetype":"locality",
    "wof:population":83
},
  "geometry": {"coordinates":[74.748183,14.443582],"type":"Point"}
}