{
  "type": "Feature",
  "properties": {
    "iso:country":"IN",
    "ks:ks_name":"Pathrapada",
    "ks:ks_pop":596,
    "ks:ks_type":"VILLAGE",
    "ks:ks_uagg_main":0,
    "name:eng_x_preferred":[
        "Pathrapada"
    ],
    "wof:name":"Pathrapada",
    "wof:placetype":"neighbourhood",
    "wof:population":596
},
  "geometry": {"coordinates":[84.58779199999999,18.967667],"type":"Point"}
}