{
  "type": "Feature",
  "properties": {
    "gn:admin1_code":"37",
    "gn:admin2_code":"406.0",
    "gn:asciiname":"Thenga",
    "gn:country_code":"IN",
    "gn:dem":296,
    "gn:feature_class":"P",
    "gn:feature_code":"PPL",
    "gn:name":"Thenga",
    "gn:population":0,
    "gn:timezone":"Asia/Kolkata",
    "iso:country":"IN",
    "ks:ks_alt_nam":"THENGA",
    "ks:ks_name":"Thenga",
    "ks:ks_pop":109,
    "ks:ks_type":"HABITATION",
    "name:eng_x_preferred":[
        "Thenga"
    ],
    "wof:name":"Thenga",
    "wof:placetype":"locality",
    "wof:population":109
},
  "geometry": {"coordinates":[81.536123,22.015285],"type":"Point"}
}