{
  "type": "Feature",
  "properties": {
    "gn:admin1_code":"35",
    "gn:admin2_code":"447.0",
    "gn:asciiname":"Baspani",
    "gn:country_code":"IN",
    "gn:dem":666,
    "gn:feature_class":"P",
    "gn:feature_code":"PPL",
    "gn:name":"B\u0101sp\u0101ni",
    "gn:population":0,
    "gn:timezone":"Asia/Kolkata",
    "iso:country":"IN",
    "name:ceb_x_preferred":[
        "Baspani"
    ],
    "name:mai_x_preferred":[
        "\u092c\u093e\u0938\u092a\u093e\u0928\u0940"
    ],
    "name:msa_x_preferred":[
        "Baspani"
    ],
    "name:pol_x_preferred":[
        "Baspani"
    ],
    "wof:name":"Baspani",
    "wof:placetype":"locality"
},
  "geometry": {"coordinates":[77.87900999999999,22.00429],"type":"Point"}
}