{
  "type": "Feature",
  "properties": {
    "gn:admin1_code":"21",
    "gn:admin2_code":"398.0",
    "gn:asciiname":"Kottavalasa",
    "gn:country_code":"IN",
    "gn:dem":774,
    "gn:feature_class":"P",
    "gn:feature_code":"PPL",
    "gn:name":"Kottavalasa",
    "gn:population":0,
    "gn:timezone":"Asia/Kolkata",
    "iso:country":"IN",
    "wof:name":"Kottavalasa",
    "wof:placetype":"locality"
},
  "geometry": {"coordinates":[82.91875999999998,18.38162],"type":"Point"}
}