{
  "type": "Feature",
  "properties": {
    "iso:country":"IN",
    "ks:ks_name":"Mankadchuan",
    "ks:ks_pop":243,
    "ks:ks_type":"VILLAGE",
    "name:eng_x_preferred":[
        "Mankadchuan"
    ],
    "wof:name":"Mankadchuan",
    "wof:placetype":"locality",
    "wof:population":243
},
  "geometry": {"coordinates":[84.829249,21.868702],"type":"Point"}
}