{
  "type": "Feature",
  "properties": {
    "gn:admin1_code":"39.0",
    "gn:admin2_code":"061",
    "gn:asciiname":"Saili",
    "gn:country_code":"IN",
    "gn:dem":949,
    "gn:feature_class":"P",
    "gn:feature_code":"PPL",
    "gn:name":"Saili",
    "gn:population":0,
    "gn:timezone":"Asia/Kolkata",
    "iso:country":"IN",
    "ks:ks_name":"Saili",
    "ks:ks_type":"VILLAGE",
    "name:eng_x_preferred":[
        "Saili"
    ],
    "wof:name":"Saili",
    "wof:placetype":"locality"
},
  "geometry": {"coordinates":[78.672147,29.985156],"type":"Point"}
}