{
  "type": "Feature",
  "properties": {
    "gn:admin1_code":"35.0",
    "gn:admin2_code":"444.0",
    "gn:asciiname":"Patalpani",
    "gn:country_code":"IN",
    "gn:dem":473,
    "gn:feature_class":"P",
    "gn:feature_code":"PPL",
    "gn:name":"Patalpani",
    "gn:population":547,
    "gn:timezone":"Asia/Kolkata",
    "iso:country":"IN",
    "wof:name":"Patalpani",
    "wof:placetype":"locality",
    "wof:population":547
},
  "geometry": {"coordinates":[77.35396,23.84141],"type":"Point"}
}