{
  "type": "Feature",
  "properties": {
    "iso:country":"IN",
    "ks:ks_alt_nam":"Basavanagudi koppalu",
    "ks:ks_name":"Basavanagudi Koppalu",
    "ks:ks_pop":102,
    "ks:ks_type":"HABITATION",
    "name:eng_x_preferred":[
        "Basavanagudi Koppalu"
    ],
    "wof:name":"Basavanagudi Koppalu",
    "wof:placetype":"locality",
    "wof:population":102
},
  "geometry": {"coordinates":[76.71793599999999,12.839952],"type":"Point"}
}