{
  "type": "Feature",
  "properties": {
    "iso:country":"IN",
    "ks:ks_name":"Dagwan",
    "ks:ks_pop":440,
    "ks:ks_type":"HABITATION",
    "name:eng_x_preferred":[
        "Dagwan"
    ],
    "wof:name":"Dagwan",
    "wof:placetype":"locality",
    "wof:population":440
},
  "geometry": {"coordinates":[81.77226,25.2804],"type":"Point"}
}