{
  "type": "Feature",
  "properties": {
    "iso:country":"IN",
    "ks:ks_name":"Amodiya",
    "ks:ks_pop":268,
    "ks:ks_type":"HABITATION",
    "name:eng_x_preferred":[
        "Amodiya"
    ],
    "wof:name":"Amodiya",
    "wof:placetype":"locality",
    "wof:population":268
},
  "geometry": {"coordinates":[76.35527,22.62272],"type":"Point"}
}