{
  "type": "Feature",
  "properties": {
    "iso:country":"IN",
    "ks:ks_name":"Ichanda Hambal",
    "ks:ks_pop":100,
    "ks:ks_type":"HABITATION",
    "name:eng_x_preferred":[
        "Ichanda Hambal"
    ],
    "wof:name":"Ichanda Hambal",
    "wof:placetype":"locality",
    "wof:population":100
},
  "geometry": {"coordinates":[75.804722,12.263056],"type":"Point"}
}