{
  "type": "Feature",
  "properties": {
    "iso:country":"IN",
    "ks:ks_name":"Neelathotti",
    "ks:ks_pop":185,
    "ks:ks_type":"HABITATION",
    "name:eng_x_preferred":[
        "Neelathotti"
    ],
    "wof:name":"Neelathotti",
    "wof:placetype":"locality",
    "wof:population":185
},
  "geometry": {"coordinates":[79.55936800000001,12.149993],"type":"Point"}
}