{
  "type": "Feature",
  "properties": {
    "iso:country":"IN",
    "ks:ks_name":"Salrapara",
    "ks:ks_pop":110,
    "ks:ks_type":"HABITATION",
    "name:eng_x_preferred":[
        "Salrapara"
    ],
    "wof:name":"Salrapara",
    "wof:placetype":"locality",
    "wof:population":110
},
  "geometry": {"coordinates":[74.514961,23.468044],"type":"Point"}
}