{
  "type": "Feature",
  "properties": {
    "iso:country":"IN",
    "ks:ks_name":"Purwa Kishore",
    "ks:ks_pop":75,
    "ks:ks_type":"HABITATION",
    "name:eng_x_preferred":[
        "Purwa Kishore"
    ],
    "wof:name":"Purwa Kishore",
    "wof:placetype":"locality",
    "wof:population":75
},
  "geometry": {"coordinates":[79.59677600000001,26.710856],"type":"Point"}
}