{
  "type": "Feature",
  "properties": {
    "gn:admin1_code":"40",
    "gn:admin2_code":"538.0",
    "gn:asciiname":"Magutaguda",
    "gn:country_code":"IN",
    "gn:dem":572,
    "gn:feature_class":"P",
    "gn:feature_code":"PPL",
    "gn:name":"Magut\u0101guda",
    "gn:population":0,
    "gn:timezone":"Asia/Kolkata",
    "iso:country":"IN",
    "wof:name":"Magutaguda",
    "wof:placetype":"locality"
},
  "geometry": {"coordinates":[78.28116,17.21438],"type":"Point"}
}