{
  "type": "Feature",
  "properties": {
    "iso:country":"IN",
    "ks:ks_name":"Junbani",
    "ks:ks_pop":1471,
    "ks:ks_type":"VILLAGE",
    "name:eng_x_preferred":[
        "Junbani"
    ],
    "wof:name":"Junbani",
    "wof:placetype":"locality",
    "wof:population":1471
},
  "geometry": {"coordinates":[87.64493,21.784851],"type":"Point"}
}