{
  "type": "Feature",
  "properties": {
    "gn:admin1_code":"21.0",
    "gn:admin2_code":"396.0",
    "gn:asciiname":"Kahunguda",
    "gn:country_code":"IN",
    "gn:dem":821,
    "gn:feature_class":"P",
    "gn:feature_code":"PPL",
    "gn:name":"K\u0101hunguda",
    "gn:population":0,
    "gn:timezone":"Asia/Kolkata",
    "iso:country":"IN",
    "ks:ks_name":"Kanhuguda",
    "ks:ks_pop":587,
    "ks:ks_type":"VILLAGE",
    "name:eng_x_preferred":[
        "Kanhuguda"
    ],
    "name:eng_x_variant":[
        "Kahunguda"
    ],
    "wof:name":"Kanhuguda",
    "wof:placetype":"locality",
    "wof:population":587
},
  "geometry": {"coordinates":[83.06494499999999,19.252373],"type":"Point"}
}