{
  "type": "Feature",
  "properties": {
    "gn:admin1_code":"19.0",
    "gn:admin2_code":"570.0",
    "gn:asciiname":"Buradahalli",
    "gn:country_code":"IN",
    "gn:dem":1022,
    "gn:feature_class":"P",
    "gn:feature_code":"PPL",
    "gn:name":"B\u016bradahalli",
    "gn:population":0,
    "gn:timezone":"Asia/Kolkata",
    "iso:country":"IN",
    "ks:ks_name":"Beeradahalli",
    "ks:ks_pop":50,
    "ks:ks_type":"HABITATION",
    "name:eng_x_preferred":[
        "Beeradahalli"
    ],
    "name:eng_x_variant":[
        "Buradahalli"
    ],
    "wof:name":"Beeradahalli",
    "wof:placetype":"locality",
    "wof:population":50
},
  "geometry": {"coordinates":[75.583174,13.369933],"type":"Point"}
}