{
  "type": "Feature",
  "properties": {
    "gn:admin1_code":"16",
    "gn:admin2_code":"507.0",
    "gn:asciiname":"Ballitola",
    "gn:country_code":"IN",
    "gn:dem":272,
    "gn:feature_class":"P",
    "gn:feature_code":"PPL",
    "gn:name":"Ball\u012btola",
    "gn:population":0,
    "gn:timezone":"Asia/Kolkata",
    "iso:country":"IN",
    "ks:ks_name":"Balitola",
    "ks:ks_pop":101,
    "ks:ks_type":"HABITATION",
    "name:eng_x_preferred":[
        "Balitola"
    ],
    "name:eng_x_variant":[
        "Ballitola"
    ],
    "wof:name":"Balitola",
    "wof:placetype":"locality",
    "wof:population":101
},
  "geometry": {"coordinates":[80.259795,20.694172],"type":"Point"}
}