{
  "type": "Feature",
  "properties": {
    "iso:country":"IN",
    "ks:ks_alt_nam":"SURALI",
    "ks:ks_name":"Surali",
    "ks:ks_pop":631,
    "ks:ks_type":"HABITATION",
    "name:eng_x_preferred":[
        "Surali"
    ],
    "wof:name":"Surali",
    "wof:placetype":"locality",
    "wof:population":631
},
  "geometry": {"coordinates":[84.637828,23.756513],"type":"Point"}
}