{
  "type": "Feature",
  "properties": {
    "iso:country":"IN",
    "ks:ks_name":"Ameerpur Kheri",
    "ks:ks_pop":1,
    "ks:ks_type":"VILLAGE",
    "name:eng_x_preferred":[
        "Ameerpur Kheri"
    ],
    "wof:name":"Ameerpur Kheri",
    "wof:placetype":"locality",
    "wof:population":1
},
  "geometry": {"coordinates":[76.92488,24.688813],"type":"Point"}
}