{
  "type": "Feature",
  "properties": {
    "iso:country":"IN",
    "ks:ks_alt_nam":"kalu basa",
    "ks:ks_name":"Kalu Basa",
    "ks:ks_pop":169,
    "ks:ks_type":"HABITATION",
    "ks:ks_uagg_main":0,
    "name:eng_x_preferred":[
        "Kalu Basa"
    ],
    "wof:name":"Kalu Basa",
    "wof:placetype":"neighbourhood",
    "wof:population":169
},
  "geometry": {"coordinates":[86.94997100000001,25.559454],"type":"Point"}
}