{
  "type": "Feature",
  "properties": {
    "iso:country":"IN",
    "ks:ks_name":"Mor Dungara",
    "ks:ks_pop":2423,
    "ks:ks_type":"VILLAGE",
    "name:eng_x_preferred":[
        "Mor Dungara"
    ],
    "wof:name":"Mor Dungara",
    "wof:placetype":"locality",
    "wof:population":2423
},
  "geometry": {"coordinates":[73.6632,22.851065],"type":"Point"}
}