{
  "type": "Feature",
  "properties": {
    "iso:country":"IN",
    "ks:ks_name":"Kutunipadar",
    "ks:ks_pop":110,
    "ks:ks_type":"VILLAGE",
    "name:eng_x_preferred":[
        "Kutunipadar"
    ],
    "wof:name":"Kutunipadar",
    "wof:placetype":"locality",
    "wof:population":110
},
  "geometry": {"coordinates":[82.233749,18.273928],"type":"Point"}
}