{
  "type": "Feature",
  "properties": {
    "gn:admin1_code":"39.0",
    "gn:admin2_code":"60.0",
    "gn:asciiname":"Khurbura",
    "gn:country":"IN",
    "gn:country_code":"IN",
    "gn:dem":658,
    "gn:fcode":"LCTY",
    "gn:feature_class":"P",
    "gn:feature_code":"PPL",
    "gn:name":"Khurbura",
    "gn:population":5000,
    "gn:timezone":"Asia/Kolkata",
    "iso:country":"IN",
    "qs:name":"Khurbura",
    "qs:photos_9r":0,
    "qs:photos_sr":0,
    "qs:pop_sr":"4",
    "wof:name":"Khurbura",
    "wof:placetype":"neighbourhood",
    "wof:population":5000
},
  "geometry": {"coordinates":[78.02912999999999,30.32375],"type":"Point"}
}