{
  "type": "Feature",
  "properties": {
    "iso:country":"IN",
    "ks:ks_name":"Pisoli",
    "ks:ks_pop":230,
    "ks:ks_type":"VILLAGE",
    "ks:ks_uagg_main":0,
    "name:eng_x_preferred":[
        "Pisoli"
    ],
    "wof:name":"Pisoli",
    "wof:placetype":"locality",
    "wof:population":230
},
  "geometry": {"coordinates":[73.91053100000001,18.449734],"type":"Point"}
}