{
  "type": "Feature",
  "properties": {
    "iso:country":"IN",
    "ks:ks_name":"Munda Tola",
    "ks:ks_pop":779,
    "ks:ks_type":"HABITATION",
    "name:eng_x_preferred":[
        "Munda Tola"
    ],
    "wof:name":"Munda Tola",
    "wof:placetype":"locality",
    "wof:population":779
},
  "geometry": {"coordinates":[86.295348,23.996045],"type":"Point"}
}