{
  "type": "Feature",
  "properties": {
    "iso:country":"IN",
    "ks:ks_name":"Vadvara",
    "ks:ks_pop":237,
    "ks:ks_type":"VILLAGE",
    "name:eng_x_preferred":[
        "Vadvara"
    ],
    "wof:name":"Vadvara",
    "wof:placetype":"locality",
    "wof:population":237
},
  "geometry": {"coordinates":[69.89102200000001,23.243989],"type":"Point"}
}