{
  "type": "Feature",
  "properties": {
    "iso:country":"IN",
    "ks:ks_name":"Ahir Toli",
    "ks:ks_pop":298,
    "ks:ks_type":"HABITATION",
    "name:eng_x_preferred":[
        "Ahir Toli"
    ],
    "wof:name":"Ahir Toli",
    "wof:placetype":"locality",
    "wof:population":298
},
  "geometry": {"coordinates":[84.04656199999999,25.49994],"type":"Point"}
}