{
  "type": "Feature",
  "properties": {
    "iso:country":"IN",
    "ks:ks_name":"Bankhedi",
    "ks:ks_pop":5,
    "ks:ks_type":"HABITATION",
    "name:eng_x_preferred":[
        "Bankhedi"
    ],
    "wof:name":"Bankhedi",
    "wof:placetype":"locality",
    "wof:population":5
},
  "geometry": {"coordinates":[77.579803,23.227079],"type":"Point"}
}