{
  "type": "Feature",
  "properties": {
    "iso:country":"IN",
    "ks:ks_name":"Jambuda Faliya",
    "ks:ks_pop":559,
    "ks:ks_type":"HABITATION",
    "name:eng_x_preferred":[
        "Jambuda Faliya"
    ],
    "wof:name":"Jambuda Faliya",
    "wof:placetype":"locality",
    "wof:population":559
},
  "geometry": {"coordinates":[73.87738899999999,23.302528],"type":"Point"}
}