{
  "type": "Feature",
  "properties": {
    "gn:admin1_code":"19.0",
    "gn:admin2_code":"563.0",
    "gn:asciiname":"Heggarni",
    "gn:country_code":"IN",
    "gn:dem":523,
    "gn:feature_class":"P",
    "gn:feature_code":"PPL",
    "gn:name":"Heggarni",
    "gn:population":0,
    "gn:timezone":"Asia/Kolkata",
    "iso:country":"IN",
    "ks:ks_name":"Heggarani",
    "ks:ks_pop":267,
    "ks:ks_type":"VILLAGE",
    "name:eng_x_preferred":[
        "Heggarani"
    ],
    "name:eng_x_variant":[
        "Heggarni"
    ],
    "wof:name":"Heggarani",
    "wof:placetype":"locality",
    "wof:population":267
},
  "geometry": {"coordinates":[74.74079999999999,14.443664],"type":"Point"}
}