{
  "type": "Feature",
  "properties": {
    "gn:admin1_code":"39.0",
    "gn:admin2_code":"68.0",
    "gn:asciiname":"Fatehpur Chamar",
    "gn:country_code":"IN",
    "gn:dem":234,
    "gn:feature_class":"P",
    "gn:feature_code":"PPL",
    "gn:name":"Fatehpur Cham\u0101r",
    "gn:population":0,
    "gn:timezone":"Asia/Kolkata",
    "iso:country":"IN",
    "ks:ks_alt_nam":"Fatehpur Cham\u0101r",
    "ks:ks_name":"Fatehpur Chamar",
    "ks:ks_type":"VILLAGE",
    "name:eng_x_preferred":[
        "Fatehpur Chamar"
    ],
    "name:eng_x_variant":[
        "Fatehpur Cham\u0101r"
    ],
    "wof:name":"Fatehpur Chamar",
    "wof:placetype":"locality"
},
  "geometry": {"coordinates":[78.06407,29.739194],"type":"Point"}
}