{
  "type": "Feature",
  "properties": {
    "gn:admin1_code":"11.0",
    "gn:admin2_code":"27.0",
    "gn:asciiname":"Tanakwarh",
    "gn:country_code":"IN",
    "gn:dem":2213,
    "gn:feature_class":"P",
    "gn:feature_code":"PPL",
    "gn:name":"Tanakw\u0101rh",
    "gn:population":0,
    "gn:timezone":"Asia/Kolkata",
    "iso:country":"IN",
    "wof:name":"Tanakwarh",
    "wof:placetype":"locality"
},
  "geometry": {"coordinates":[77.14813000000002,31.53085],"type":"Point"}
}