{
  "type": "Feature",
  "properties": {
    "iso:country":"IN",
    "ks:ks_name":"Dudhwi",
    "ks:ks_pop":861,
    "ks:ks_type":"VILLAGE",
    "name:eng_x_preferred":[
        "Dudhwi"
    ],
    "wof:name":"Dudhwi",
    "wof:placetype":"locality",
    "wof:population":861
},
  "geometry": {"coordinates":[74.210808,22.021929],"type":"Point"}
}