{
  "type": "Feature",
  "properties": {
    "iso:country":"IN",
    "ks:ks_name":"Dhamanpe",
    "ks:ks_pop":294,
    "ks:ks_type":"VILLAGE",
    "name:eng_x_preferred":[
        "Dhamanpe"
    ],
    "wof:name":"Dhamanpe",
    "wof:placetype":"locality",
    "wof:population":294
},
  "geometry": {"coordinates":[73.690455,16.727744],"type":"Point"}
}