{
  "type": "Feature",
  "properties": {
    "iso:country":"IN",
    "ks:ks_name":"Athase",
    "ks:ks_pop":27,
    "ks:ks_type":"HABITATION",
    "name:eng_x_preferred":[
        "Athase"
    ],
    "wof:name":"Athase",
    "wof:placetype":"locality",
    "wof:population":27
},
  "geometry": {"coordinates":[75.339718,12.731005],"type":"Point"}
}