{
  "type": "Feature",
  "properties": {
    "iso:country":"IN",
    "ks:ks_alt_nam":"Tand\u0101p\u0101ra",
    "ks:ks_name":"Tandapara",
    "ks:ks_type":"VILLAGE",
    "name:eng_x_preferred":[
        "Tandapara"
    ],
    "name:eng_x_variant":[
        "Tand\u0101p\u0101ra"
    ],
    "wof:name":"Tandapara",
    "wof:placetype":"locality"
},
  "geometry": {"coordinates":[84.16165700000001,20.706332],"type":"Point"}
}