{
  "type": "Feature",
  "properties": {
    "iso:country":"IN",
    "ks:ks_name":"Miri Pathar 2",
    "ks:ks_pop":828,
    "ks:ks_type":"VILLAGE",
    "ks:ks_uagg_main":0,
    "name:eng_x_preferred":[
        "Miri Pathar 2"
    ],
    "wof:name":"Miri Pathar 2",
    "wof:placetype":"neighbourhood",
    "wof:population":828
},
  "geometry": {"coordinates":[92.85437899999999,26.786063],"type":"Point"}
}