{
  "type": "Feature",
  "properties": {
    "gn:admin1_code":"2",
    "gn:admin2_code":"545.0",
    "gn:asciiname":"Potamdorapalem",
    "gn:country_code":"IN",
    "gn:dem":235,
    "gn:feature_class":"P",
    "gn:feature_code":"PPL",
    "gn:name":"Potamdorap\u0101lem",
    "gn:population":0,
    "gn:timezone":"Asia/Kolkata",
    "iso:country":"IN",
    "ks:ks_name":"Potammadarapalem",
    "ks:ks_pop":150,
    "ks:ks_type":"HABITATION",
    "name:eng_x_preferred":[
        "Potammadarapalem"
    ],
    "name:eng_x_variant":[
        "Potamdorapalem"
    ],
    "wof:name":"Potammadarapalem",
    "wof:placetype":"locality",
    "wof:population":150
},
  "geometry": {"coordinates":[81.92649400000001,17.516479],"type":"Point"}
}