{
  "type": "Feature",
  "properties": {
    "iso:country":"IN",
    "ks:ks_name":"Shanpur Nagla",
    "ks:ks_pop":199,
    "ks:ks_type":"HABITATION",
    "ks:ks_uagg_main":0,
    "name:eng_x_preferred":[
        "Shanpur Nagla"
    ],
    "wof:name":"Shanpur Nagla",
    "wof:placetype":"neighbourhood",
    "wof:population":199
},
  "geometry": {"coordinates":[79.39685,27.578755],"type":"Point"}
}