{
  "type": "Feature",
  "properties": {
    "gn:admin1_code":"35.0",
    "gn:admin2_code":"419.0",
    "gn:asciiname":"Narhela",
    "gn:country_code":"IN",
    "gn:dem":202,
    "gn:feature_class":"P",
    "gn:feature_code":"PPL",
    "gn:name":"Narhela",
    "gn:population":0,
    "gn:timezone":"Asia/Kolkata",
    "iso:country":"IN",
    "wof:name":"Narhela",
    "wof:placetype":"locality"
},
  "geometry": {"coordinates":[77.82686,26.31054],"type":"Point"}
}