{
  "type": "Feature",
  "properties": {
    "iso:country":"IN",
    "ks:ks_alt_nam":"Khejariya ka Bala",
    "ks:ks_name":"Khejariya Ka Bala",
    "ks:ks_pop":332,
    "ks:ks_type":"HABITATION",
    "name:eng_x_preferred":[
        "Khejariya Ka Bala"
    ],
    "wof:name":"Khejariya Ka Bala",
    "wof:placetype":"locality",
    "wof:population":332
},
  "geometry": {"coordinates":[74.018049,25.883815],"type":"Point"}
}