{
  "type": "Feature",
  "properties": {
    "gn:admin1_code":"10.0",
    "gn:admin2_code":"74.0",
    "gn:asciiname":"Abdullahpur",
    "gn:country_code":"IN",
    "gn:dem":254,
    "gn:feature_class":"P",
    "gn:feature_code":"PPL",
    "gn:name":"Abdull\u0101hpur",
    "gn:population":0,
    "gn:timezone":"Asia/Kolkata",
    "iso:country":"IN",
    "wof:name":"Abdullahpur",
    "wof:placetype":"locality"
},
  "geometry": {"coordinates":[76.98472,29.75045],"type":"Point"}
}