{
  "type": "Feature",
  "properties": {
    "gn:admin1_code":"36",
    "gn:admin2_code":"178.0",
    "gn:asciiname":"Taunkla",
    "gn:country_code":"IN",
    "gn:dem":96,
    "gn:feature_class":"P",
    "gn:feature_code":"PPL",
    "gn:name":"Taunkla",
    "gn:population":0,
    "gn:timezone":"Asia/Kolkata",
    "iso:country":"IN",
    "wof:name":"Taunkla",
    "wof:placetype":"locality"
},
  "geometry": {"coordinates":[82.34681999999999,26.39509],"type":"Point"}
}