{
  "type": "Feature",
  "properties": {
    "gn:admin1_code":"36.0",
    "gn:admin2_code":"149.0",
    "gn:asciiname":"Achalpur",
    "gn:country_code":"IN",
    "gn:dem":186,
    "gn:feature_class":"P",
    "gn:feature_code":"PPL",
    "gn:name":"Achalpur",
    "gn:population":0,
    "gn:timezone":"Asia/Kolkata",
    "iso:country":"IN",
    "name:ben_x_preferred":[
        "\u0985\u099a\u09b2\u09aa\u09c1\u09b0"
    ],
    "name:bih_x_preferred":[
        "\u0905\u091a\u0932\u092a\u0941\u0930"
    ],
    "name:bpy_x_preferred":[
        "\u0986\u099a\u09b2\u09aa\u09c1\u09b0"
    ],
    "name:cat_x_preferred":[
        "Achalpur"
    ],
    "name:ceb_x_preferred":[
        "Achalpur"
    ],
    "name:fas_x_preferred":[
        "\u0627\u06a9\u0627\u0644\u067e\u0648\u0631"
    ],
    "name:hif_x_preferred":[
        "Achalpur"
    ],
    "name:ind_x_preferred":[
        "Achalpur"
    ],
    "name:ita_x_preferred":[
        "Achalpur"
    ],
    "name:jpn_x_preferred":[
        "\u30a2\u30c1\u30e3\u30eb\u30d7\u30eb"
    ],
    "name:mar_x_preferred":[
        "\u0905\u091a\u0932\u092a\u0942\u0930"
    ],
    "name:min_x_preferred":[
        "Achalpur"
    ],
    "name:msa_x_preferred":[
        "Achalpur"
    ],
    "name:new_x_preferred":[
        "\u0905\u0932\u091a\u092a\u0941\u0930"
    ],
    "name:nld_x_preferred":[
        "Achalpur"
    ],
    "name:ori_x_preferred":[
        "\u0b05\u0b1a\u0b33\u0b2a\u0b41\u0b30"
    ],
    "name:pnb_x_preferred":[
        "\u0627\u0686\u0644\u067e\u0648\u0631"
    ],
    "name:por_x_preferred":[
        "Achalpur"
    ],
    "name:swe_x_preferred":[
        "Achalpur"
    ],
    "name:tam_x_preferred":[
        "\u0b85\u0b9a\u0bcd\u0b9a\u0bb2\u0bcd\u0baa\u0bc2\u0bb0\u0bcd"
    ],
    "name:urd_x_preferred":[
        "\u0627\u0686\u0644\u067e\u0648\u0631"
    ],
    "name:vie_x_preferred":[
        "Achalpur"
    ],
    "name:zho_x_preferred":[
        "\u963f\u6070\u5c14\u666e\u5c14"
    ],
    "wof:name":"Achalpur",
    "wof:placetype":"locality"
},
  "geometry": {"coordinates":[78.69879,28.30778],"type":"Point"}
}