{
  "type": "Feature",
  "properties": {
    "gn:admin1_code":"24",
    "gn:admin2_code":"119.0",
    "gn:asciiname":"Jaitpura",
    "gn:country_code":"IN",
    "gn:dem":468,
    "gn:feature_class":"P",
    "gn:feature_code":"PPL",
    "gn:name":"Jaitpura",
    "gn:population":0,
    "gn:timezone":"Asia/Kolkata",
    "iso:country":"IN",
    "name:ara_x_preferred":[
        "\u062c\u064a\u062a\u0628\u0648\u0631\u0627"
    ],
    "name:ben_bn_x_preferred":[
        "\u099c\u09be\u0987\u09a4\u09aa\u09c1\u09b0\u09be"
    ],
    "name:ben_in_x_preferred":[
        "\u099c\u09be\u0987\u09a4\u09aa\u09c1\u09b0\u09be"
    ],
    "name:guj_x_preferred":[
        "\u0a9c\u0abe\u0ab2\u0abf\u0a9f\u0aaa\u0ac1\u0ab0\u0abe"
    ],
    "name:hin_x_preferred":[
        "\u091c\u0948\u0924\u092a\u0941\u0930\u093e"
    ],
    "name:kan_x_preferred":[
        "\u0c9c\u0cc8\u0ca4\u0ccd"
    ],
    "name:mal_x_preferred":[
        "\u0d1c\u0d2f\u0d4d\u0d24\u0d4d\u0d2a\u0d41\u0d30"
    ],
    "name:mar_x_preferred":[
        "\u091c\u0948\u0924\u092a\u0941\u0930\u093e"
    ],
    "name:pan_x_preferred":[
        "\u0a1c\u0a48\u0a24\u0a2a\u0a41\u0a30\u0a3e"
    ],
    "name:tam_x_preferred":[
        "\u0b9c\u0bc8\u0ba4\u0bcd\u0baa\u0bc1\u0bb0\u0bbe"
    ],
    "name:tel_x_preferred":[
        "\u0c1c\u0c48\u0c24\u0c4d"
    ],
    "name:urd_x_preferred":[
        "\u062c\u06cc\u062a \u067e\u0648\u0631"
    ],
    "wof:name":"Jaitpura",
    "wof:placetype":"locality"
},
  "geometry": {"coordinates":[74.32878000000002,26.04109],"type":"Point"}
}