{
  "type": "Feature",
  "properties": {
    "iso:country":"IN",
    "ks:ks_name":"Manjharpara",
    "ks:ks_pop":210,
    "ks:ks_type":"HABITATION",
    "name:eng_x_preferred":[
        "Manjharpara"
    ],
    "wof:name":"Manjharpara",
    "wof:placetype":"locality",
    "wof:population":210
},
  "geometry": {"coordinates":[81.25036799999999,19.109386],"type":"Point"}
}