{
  "type": "Feature",
  "properties": {
    "iso:country":"IN",
    "ks:ks_alt_nam":"TEMRA MAL",
    "ks:ks_name":"Temra Mal",
    "ks:ks_pop":383,
    "ks:ks_type":"HABITATION",
    "name:eng_x_preferred":[
        "Temra Mal"
    ],
    "wof:name":"Temra Mal",
    "wof:placetype":"locality",
    "wof:population":383
},
  "geometry": {"coordinates":[77.777359,22.101888],"type":"Point"}
}