{
  "type": "Feature",
  "properties": {
    "iso:country":"IN",
    "ks:ks_name":"Arikkal",
    "ks:ks_pop":1065,
    "ks:ks_type":"HABITATION",
    "name:eng_x_preferred":[
        "Arikkal"
    ],
    "wof:name":"Arikkal",
    "wof:placetype":"locality",
    "wof:population":1065
},
  "geometry": {"coordinates":[75.980993,11.51674],"type":"Point"}
}