{
  "type": "Feature",
  "properties": {
    "iso:country":"IN",
    "ks:ks_name":"Poyyathanallur",
    "ks:ks_pop":387,
    "ks:ks_type":"HABITATION",
    "name:eng_x_preferred":[
        "Poyyathanallur"
    ],
    "wof:name":"Poyyathanallur",
    "wof:placetype":"locality",
    "wof:population":387
},
  "geometry": {"coordinates":[79.086172,9.871834],"type":"Point"}
}