{
  "type": "Feature",
  "properties": {
    "iso:country":"IN",
    "ks:ks_alt_nam":"Aurang Sh\u0101hpur",
    "ks:ks_name":"Aurang Shahpur",
    "ks:ks_type":"VILLAGE",
    "ks:ks_uagg_main":0,
    "name:eng_x_preferred":[
        "Aurang Shahpur"
    ],
    "name:eng_x_variant":[
        "Aurang Sh\u0101hpur"
    ],
    "wof:name":"Aurang Shahpur",
    "wof:placetype":"neighbourhood"
},
  "geometry": {"coordinates":[77.667822,28.982301],"type":"Point"}
}