{
  "type": "Feature",
  "properties": {
    "iso:country":"IN",
    "ks:ks_name":"Bhatatara",
    "ks:ks_pop":0,
    "ks:ks_type":"VILLAGE",
    "name:eng_x_preferred":[
        "Bhatatara"
    ],
    "wof:name":"Bhatatara",
    "wof:placetype":"locality",
    "wof:population":0
},
  "geometry": {"coordinates":[87.214468,25.481651],"type":"Point"}
}