{
  "type": "Feature",
  "properties": {
    "iso:country":"IN",
    "ks:ks_name":"Sakri",
    "ks:ks_type":"VILLAGE",
    "name:eng_x_preferred":[
        "Sakri"
    ],
    "name:hin_x_preferred":[
        "\u0938\u0915\u0930\u0940"
    ],
    "name:mar_x_preferred":[
        "\u0938\u093e\u0915\u094d\u0930\u0940"
    ],
    "wof:name":"Sakri",
    "wof:placetype":"locality"
},
  "geometry": {"coordinates":[81.86497300000001,21.717873],"type":"Point"}
}