{
  "type": "Feature",
  "properties": {
    "iso:country":"IN",
    "ks:ks_name":"Sakri",
    "ks:ks_type":"VILLAGE",
    "name:eng_x_preferred":[
        "Sakri"
    ],
    "wof:name":"Sakri",
    "wof:placetype":"locality"
},
  "geometry": {"coordinates":[81.86497300000001,21.717873],"type":"Point"}
}