{
  "type": "Feature",
  "properties": {
    "iso:country":"IN",
    "ks:ks_name":"Dera Sheeder",
    "ks:ks_pop":100,
    "ks:ks_type":"HABITATION",
    "name:eng_x_preferred":[
        "Dera Sheeder"
    ],
    "wof:name":"Dera Sheeder",
    "wof:placetype":"locality",
    "wof:population":100
},
  "geometry": {"coordinates":[78.460605,27.972167],"type":"Point"}
}