{
  "type": "Feature",
  "properties": {
    "iso:country":"IN",
    "ks:ks_name":"Keel Vatrampalayam",
    "ks:ks_pop":600,
    "ks:ks_type":"HABITATION",
    "name:eng_x_preferred":[
        "Keel Vatrampalayam"
    ],
    "wof:name":"Keel Vatrampalayam",
    "wof:placetype":"locality",
    "wof:population":600
},
  "geometry": {"coordinates":[77.75688100000001,11.557242],"type":"Point"}
}