{
  "type": "Feature",
  "properties": {
    "iso:country":"IN",
    "ks:ks_name":"Shindewasti",
    "ks:ks_pop":161,
    "ks:ks_type":"HABITATION",
    "name:eng_x_preferred":[
        "Shindewasti"
    ],
    "wof:name":"Shindewasti",
    "wof:placetype":"locality",
    "wof:population":161
},
  "geometry": {"coordinates":[74.843827,17.751024],"type":"Point"}
}