{
  "type": "Feature",
  "properties": {
    "iso:country":"IN",
    "ks:ks_name":"Basra",
    "ks:ks_pop":0,
    "ks:ks_type":"VILLAGE",
    "name:eng_x_preferred":[
        "Basra"
    ],
    "wof:name":"Basra",
    "wof:placetype":"locality",
    "wof:population":0
},
  "geometry": {"coordinates":[83.556387,25.008433],"type":"Point"}
}