{
  "type": "Feature",
  "properties": {
    "gn:admin1_code":"39",
    "gn:admin2_code":"61.0",
    "gn:asciiname":"Dedhar",
    "gn:country_code":"IN",
    "gn:dem":1260,
    "gn:feature_class":"P",
    "gn:feature_code":"PPL",
    "gn:name":"Dedh\u0101r",
    "gn:population":0,
    "gn:timezone":"Asia/Kolkata",
    "iso:country":"IN",
    "ks:ks_name":"Devdhar",
    "ks:ks_pop":25,
    "ks:ks_type":"HABITATION",
    "name:eng_x_preferred":[
        "Devdhar"
    ],
    "name:eng_x_variant":[
        "Dedhar"
    ],
    "wof:name":"Devdhar",
    "wof:placetype":"locality",
    "wof:population":25
},
  "geometry": {"coordinates":[78.80251699999999,29.960448],"type":"Point"}
}