{
  "type": "Feature",
  "properties": {
    "gn:admin1_code":"39",
    "gn:admin2_code":"61.0",
    "gn:asciiname":"Dedhar",
    "gn:country_code":"IN",
    "gn:dem":1260,
    "gn:feature_class":"P",
    "gn:feature_code":"PPL",
    "gn:name":"Dedh\u0101r",
    "gn:population":0,
    "gn:timezone":"Asia/Kolkata",
    "iso:country":"IN",
    "wof:name":"Dedhar",
    "wof:placetype":"locality"
},
  "geometry": {"coordinates":[78.80410999999999,29.95985],"type":"Point"}
}