{
  "type": "Feature",
  "properties": {
    "gn:admin1_code":"34.0",
    "gn:admin2_code":"212.0",
    "gn:asciiname":"Jalkhundar",
    "gn:country_code":"IN",
    "gn:dem":36,
    "gn:feature_class":"P",
    "gn:feature_code":"PPL",
    "gn:name":"Jalkhund\u0101r",
    "gn:population":0,
    "gn:timezone":"Asia/Kolkata",
    "iso:country":"IN",
    "ks:ks_name":"Jalkhundar",
    "ks:ks_pop":1287,
    "ks:ks_type":"VILLAGE",
    "name:eng_x_preferred":[
        "Jalkhundar"
    ],
    "wof:name":"Jalkhundar",
    "wof:placetype":"locality",
    "wof:population":1287
},
  "geometry": {"coordinates":[87.93132,25.612672],"type":"Point"}
}