{
  "type": "Feature",
  "properties": {
    "iso:country":"IN",
    "ks:ks_name":"Purnapani",
    "ks:ks_pop":334,
    "ks:ks_type":"HABITATION",
    "name:eng_x_preferred":[
        "Purnapani"
    ],
    "wof:name":"Purnapani",
    "wof:placetype":"locality",
    "wof:population":334
},
  "geometry": {"coordinates":[84.822253,22.731037],"type":"Point"}
}