{
  "type": "Feature",
  "properties": {
    "gn:admin1_code":"36",
    "gn:admin2_code":"202.0",
    "gn:asciiname":"Bikrampur",
    "gn:country_code":"IN",
    "gn:dem":170,
    "gn:feature_class":"P",
    "gn:feature_code":"PPL",
    "gn:name":"Bikrampur",
    "gn:population":0,
    "gn:timezone":"Asia/Kolkata",
    "iso:country":"IN",
    "name:ben_x_preferred":[
        "\u09ac\u09bf\u0995\u09cd\u09b0\u09ae\u09aa\u09c1\u09b0"
    ],
    "name:cat_x_preferred":[
        "Bikrampur"
    ],
    "name:epo_x_preferred":[
        "Bikrampur"
    ],
    "wof:name":"Bikrampur",
    "wof:placetype":"locality"
},
  "geometry": {"coordinates":[78.86114999999999,27.74049],"type":"Point"}
}