{
  "type": "Feature",
  "properties": {
    "iso:country":"IN",
    "ks:ks_alt_nam":"PUrgaon",
    "ks:ks_name":"Purgaon",
    "ks:ks_pop":233,
    "ks:ks_type":"HABITATION",
    "name:eng_x_preferred":[
        "Purgaon"
    ],
    "wof:name":"Purgaon",
    "wof:placetype":"locality",
    "wof:population":233
},
  "geometry": {"coordinates":[73.550017,16.825316],"type":"Point"}
}