{
  "type": "Feature",
  "properties": {
    "gn:admin1_code":"12.0",
    "gn:admin2_code":"004",
    "gn:asciiname":"Mantha",
    "gn:country_code":"IN",
    "gn:dem":3215,
    "gn:feature_class":"P",
    "gn:feature_code":"PPL",
    "gn:name":"Mantha",
    "gn:population":0,
    "gn:timezone":"Asia/Kolkata",
    "iso:country":"IN",
    "wof:name":"Mantha",
    "wof:placetype":"locality"
},
  "geometry": {"coordinates":[76.38864000000002,34.60683],"type":"Point"}
}