{
  "type": "Feature",
  "properties": {
    "gn:admin1_code":"36",
    "gn:admin2_code":"197.0",
    "gn:asciiname":"Katesar Khurd",
    "gn:country_code":"IN",
    "gn:dem":79,
    "gn:feature_class":"P",
    "gn:feature_code":"PPL",
    "gn:name":"Katesar Khurd",
    "gn:population":0,
    "gn:timezone":"Asia/Kolkata",
    "iso:country":"IN",
    "wof:name":"Katesar Khurd",
    "wof:placetype":"locality"
},
  "geometry": {"coordinates":[83.10833000000002,25.42683],"type":"Point"}
}