{
  "type": "Feature",
  "properties": {
    "iso:country":"IN",
    "ks:ks_name":"Betbeda",
    "ks:ks_pop":204,
    "ks:ks_type":"HABITATION",
    "name:eng_x_preferred":[
        "Betbeda"
    ],
    "wof:name":"Betbeda",
    "wof:placetype":"locality",
    "wof:population":204
},
  "geometry": {"coordinates":[81.59636,19.428576],"type":"Point"}
}