{
  "type": "Feature",
  "properties": {
    "iso:country":"IN",
    "ks:ks_name":"Savaroli Tarf Rahur",
    "ks:ks_pop":238,
    "ks:ks_type":"VILLAGE",
    "name:eng_x_preferred":[
        "Savaroli Tarf Rahur"
    ],
    "wof:name":"Savaroli Tarf Rahur",
    "wof:placetype":"locality",
    "wof:population":238
},
  "geometry": {"coordinates":[73.170255,19.400248],"type":"Point"}
}