{
  "type": "Feature",
  "properties": {
    "gn:admin1_code":"25.0",
    "gn:admin2_code":"630.0",
    "gn:asciiname":"Jakkupati",
    "gn:country_code":"IN",
    "gn:dem":443,
    "gn:feature_class":"P",
    "gn:feature_code":"PPL",
    "gn:name":"Jakkupati",
    "gn:population":0,
    "gn:timezone":"Asia/Kolkata",
    "iso:country":"IN",
    "ks:ks_name":"Jakkupatti",
    "ks:ks_pop":1030,
    "ks:ks_type":"VILLAGE",
    "name:eng_x_preferred":[
        "Jakkupatti"
    ],
    "name:eng_x_variant":[
        "Jakkupati"
    ],
    "wof:name":"Jakkupatti",
    "wof:placetype":"locality",
    "wof:population":1030
},
  "geometry": {"coordinates":[78.2852,12.179482],"type":"Point"}
}