{
  "type": "Feature",
  "properties": {
    "gn:admin1_code":"23.0",
    "gn:admin2_code":"43.0",
    "gn:asciiname":"Kankarwala",
    "gn:country_code":"IN",
    "gn:dem":180,
    "gn:feature_class":"P",
    "gn:feature_code":"PPL",
    "gn:name":"Kankarw\u0101la",
    "gn:population":0,
    "gn:timezone":"Asia/Kolkata",
    "iso:country":"IN",
    "name:und_x_variant":[
        "Kankarw\u0101la",
        "Jaurki"
    ],
    "wof:name":"Kankarwala",
    "wof:placetype":"locality"
},
  "geometry": {"coordinates":[74.08555,30.42243],"type":"Point"}
}