{
  "type": "Feature",
  "properties": {
    "gn:admin1_code":"25.0",
    "gn:admin2_code":"602.0",
    "gn:asciiname":"Matsayilasapuram",
    "gn:country_code":"IN",
    "gn:dem":57,
    "gn:feature_class":"P",
    "gn:feature_code":"PPL",
    "gn:name":"Matsay\u012bl\u0101sapuram",
    "gn:population":0,
    "gn:timezone":"Asia/Kolkata",
    "iso:country":"IN",
    "wof:name":"Matsayilasapuram",
    "wof:placetype":"locality"
},
  "geometry": {"coordinates":[79.73994999999999,13.19395],"type":"Point"}
}