{
  "type": "Feature",
  "properties": {
    "iso:country":"IN",
    "ks:ks_alt_nam":"BANSODE MALA",
    "ks:ks_name":"Bansode Mala",
    "ks:ks_pop":80,
    "ks:ks_type":"HABITATION",
    "name:eng_x_preferred":[
        "Bansode Mala"
    ],
    "wof:name":"Bansode Mala",
    "wof:placetype":"neighbourhood",
    "wof:population":80
},
  "geometry": {"coordinates":[74.600538,16.82911],"type":"Point"}
}