{
  "type": "Feature",
  "properties": {
    "iso:country":"IN",
    "ks:ks_name":"Ahiran Purwa",
    "ks:ks_pop":20,
    "ks:ks_type":"HABITATION",
    "ks:ks_uagg_main":0,
    "name:eng_x_preferred":[
        "Ahiran Purwa"
    ],
    "wof:name":"Ahiran Purwa",
    "wof:placetype":"neighbourhood",
    "wof:population":20
},
  "geometry": {"coordinates":[80.760508,25.211671],"type":"Point"}
}