{
  "type": "Feature",
  "properties": {
    "iso:country":"IN",
    "ks:ks_name":"Vokhadiyapura",
    "ks:ks_pop":585,
    "ks:ks_type":"HABITATION",
    "name:eng_x_preferred":[
        "Vokhadiyapura"
    ],
    "wof:name":"Vokhadiyapura",
    "wof:placetype":"locality",
    "wof:population":585
},
  "geometry": {"coordinates":[72.74763900000001,22.420222],"type":"Point"}
}