{
  "type": "Feature",
  "properties": {
    "gn:admin1_code":"38",
    "gn:admin2_code":"358.0",
    "gn:asciiname":"Jharna Khurd",
    "gn:country_code":"IN",
    "gn:dem":200,
    "gn:feature_class":"P",
    "gn:feature_code":"PPL",
    "gn:name":"Jharna Khurd",
    "gn:population":0,
    "gn:timezone":"Asia/Kolkata",
    "iso:country":"IN",
    "ks:ks_name":"Jharna Khurd",
    "ks:ks_pop":404,
    "ks:ks_type":"VILLAGE",
    "ks:ks_uagg_main":0,
    "name:eng_x_preferred":[
        "Jharna Khurd"
    ],
    "wof:name":"Jharna Khurd",
    "wof:placetype":"neighbourhood",
    "wof:population":404
},
  "geometry": {"coordinates":[83.92374700000001,24.336318],"type":"Point"}
}