{
  "type": "Feature",
  "properties": {
    "iso:country":"IN",
    "ks:ks_name":"Kotekala",
    "ks:ks_pop":580,
    "ks:ks_type":"HABITATION",
    "name:eng_x_preferred":[
        "Kotekala"
    ],
    "wof:name":"Kotekala",
    "wof:placetype":"locality",
    "wof:population":580
},
  "geometry": {"coordinates":[75.375576,12.516446],"type":"Point"}
}