{
  "type": "Feature",
  "properties": {
    "iso:country":"IN",
    "ks:ks_name":"Parma Chak",
    "ks:ks_pop":398,
    "ks:ks_type":"VILLAGE",
    "name:eng_x_preferred":[
        "Parma Chak"
    ],
    "wof:name":"Parma Chak",
    "wof:placetype":"locality",
    "wof:population":398
},
  "geometry": {"coordinates":[84.849943,24.345852],"type":"Point"}
}