{
  "type": "Feature",
  "properties": {
    "gn:admin1_code":"19.0",
    "gn:admin2_code":"574.0",
    "gn:asciiname":"Javanahalli",
    "gn:country_code":"IN",
    "gn:dem":861,
    "gn:feature_class":"P",
    "gn:feature_code":"PPL",
    "gn:name":"Javanahalli",
    "gn:population":0,
    "gn:timezone":"Asia/Kolkata",
    "iso:country":"IN",
    "ks:ks_name":"Javaranahalli",
    "ks:ks_pop":80,
    "ks:ks_type":"HABITATION",
    "name:eng_x_preferred":[
        "Javaranahalli"
    ],
    "name:eng_x_variant":[
        "Javanahalli"
    ],
    "wof:name":"Javaranahalli",
    "wof:placetype":"locality",
    "wof:population":80
},
  "geometry": {"coordinates":[76.210459,13.286971],"type":"Point"}
}