{
  "type": "Feature",
  "properties": {
    "gn:admin1_code":"19.0",
    "gn:admin2_code":"574.0",
    "gn:asciiname":"Javanahalli",
    "gn:country_code":"IN",
    "gn:dem":861,
    "gn:feature_class":"P",
    "gn:feature_code":"PPL",
    "gn:name":"Javanahalli",
    "gn:population":0,
    "gn:timezone":"Asia/Kolkata",
    "iso:country":"IN",
    "wof:name":"Javanahalli",
    "wof:placetype":"locality"
},
  "geometry": {"coordinates":[76.20873,13.29747],"type":"Point"}
}