{
  "type": "Feature",
  "properties": {
    "gn:admin1_code":"23.0",
    "gn:admin2_code":"043",
    "gn:asciiname":"Khui Khera",
    "gn:country_code":"IN",
    "gn:dem":180,
    "gn:feature_class":"P",
    "gn:feature_code":"PPL",
    "gn:name":"Khui Khera",
    "gn:population":0,
    "gn:timezone":"Asia/Kolkata",
    "iso:country":"IN",
    "wof:name":"Khui Khera",
    "wof:placetype":"locality"
},
  "geometry": {"coordinates":[74.09685999999998,30.30164000000001],"type":"Point"}
}