{
  "type": "Feature",
  "properties": {
    "gn:admin1_code":"11",
    "gn:admin2_code":"31.0",
    "gn:asciiname":"Bare di Bhuin",
    "gn:country_code":"IN",
    "gn:dem":1189,
    "gn:feature_class":"P",
    "gn:feature_code":"PPL",
    "gn:name":"B\u0101re di Bhu\u012bn",
    "gn:population":0,
    "gn:timezone":"Asia/Kolkata",
    "iso:country":"IN",
    "wof:name":"Bare di Bhuin",
    "wof:placetype":"locality"
},
  "geometry": {"coordinates":[76.73968000000001,31.21028],"type":"Point"}
}