{
  "type": "Feature",
  "properties": {
    "gn:admin1_code":"19.0",
    "gn:admin2_code":"576.0",
    "gn:asciiname":"Chennayyanakote",
    "gn:country_code":"IN",
    "gn:dem":971,
    "gn:feature_class":"P",
    "gn:feature_code":"PPLL",
    "gn:name":"Chennayyanakote",
    "gn:population":0,
    "gn:timezone":"Asia/Kolkata",
    "iso:country":"IN",
    "wof:name":"Chennayyanakote",
    "wof:placetype":"locality"
},
  "geometry": {"coordinates":[75.93695,12.24214],"type":"Point"}
}