{
  "type": "Feature",
  "properties": {
    "gn:admin1_code":"19.0",
    "gn:admin2_code":"576.0",
    "gn:asciiname":"Chennayyanakote",
    "gn:country_code":"IN",
    "gn:dem":971,
    "gn:feature_class":"P",
    "gn:feature_code":"PPLL",
    "gn:name":"Chennayyanakote",
    "gn:population":0,
    "gn:timezone":"Asia/Kolkata",
    "iso:country":"IN",
    "ks:ks_name":"Channayanakote",
    "ks:ks_pop":6796,
    "ks:ks_type":"HABITATION",
    "name:eng_x_preferred":[
        "Channayanakote"
    ],
    "name:eng_x_variant":[
        "Chennayyanakote"
    ],
    "wof:name":"Channayanakote",
    "wof:placetype":"locality",
    "wof:population":6796
},
  "geometry": {"coordinates":[75.933391,12.241546],"type":"Point"}
}