{
  "type": "Feature",
  "properties": {
    "iso:country":"IN",
    "ks:ks_name":"Shivsharanwasti",
    "ks:ks_pop":58,
    "ks:ks_type":"HABITATION",
    "name:eng_x_preferred":[
        "Shivsharanwasti"
    ],
    "wof:name":"Shivsharanwasti",
    "wof:placetype":"locality",
    "wof:population":58
},
  "geometry": {"coordinates":[74.935091,18.349732],"type":"Point"}
}