{
  "type": "Feature",
  "properties": {
    "gn:admin1_code":"16.0",
    "gn:admin2_code":"526.0",
    "gn:asciiname":"Mahalung",
    "gn:country_code":"IN",
    "gn:dem":482,
    "gn:feature_class":"P",
    "gn:feature_code":"PPL",
    "gn:name":"Mahalung",
    "gn:population":0,
    "gn:timezone":"Asia/Kolkata",
    "iso:country":"IN",
    "wof:name":"Mahalung",
    "wof:placetype":"locality"
},
  "geometry": {"coordinates":[75.0993,17.86617],"type":"Point"}
}