{
  "type": "Feature",
  "properties": {
    "iso:country":"IN",
    "ks:ks_name":"Puttammanapalya",
    "ks:ks_pop":320,
    "ks:ks_type":"HABITATION",
    "name:eng_x_preferred":[
        "Puttammanapalya"
    ],
    "wof:name":"Puttammanapalya",
    "wof:placetype":"locality",
    "wof:population":320
},
  "geometry": {"coordinates":[77.2461,13.593861],"type":"Point"}
}