{
  "type": "Feature",
  "properties": {
    "gn:admin1_code":"39.0",
    "gn:admin2_code":"57.0",
    "gn:asciiname":"Bilagarh",
    "gn:country_code":"IN",
    "gn:dem":1901,
    "gn:feature_class":"P",
    "gn:feature_code":"PPL",
    "gn:name":"Bilagarh",
    "gn:population":0,
    "gn:timezone":"Asia/Kolkata",
    "iso:country":"IN",
    "ks:ks_name":"Bilagar",
    "ks:ks_pop":97,
    "ks:ks_type":"VILLAGE",
    "name:eng_x_preferred":[
        "Bilagar"
    ],
    "name:eng_x_variant":[
        "Bilagarh"
    ],
    "wof:name":"Bilagar",
    "wof:placetype":"locality",
    "wof:population":97
},
  "geometry": {"coordinates":[79.61982999999999,30.495604],"type":"Point"}
}