{
  "type": "Feature",
  "properties": {
    "gn:admin1_code":"39.0",
    "gn:admin2_code":"57.0",
    "gn:asciiname":"Bilagarh",
    "gn:country_code":"IN",
    "gn:dem":1901,
    "gn:feature_class":"P",
    "gn:feature_code":"PPL",
    "gn:name":"Bilagarh",
    "gn:population":0,
    "gn:timezone":"Asia/Kolkata",
    "iso:country":"IN",
    "wof:name":"Bilagarh",
    "wof:placetype":"locality"
},
  "geometry": {"coordinates":[79.61835000000001,30.50044],"type":"Point"}
}