{
  "type": "Feature",
  "properties": {
    "iso:country":"IN",
    "ks:ks_alt_nam":"RONGKUT  No 1 BLOCK - 1 2",
    "ks:ks_name":"Rongkut No 1 Block - 1 2",
    "ks:ks_pop":1204,
    "ks:ks_type":"HABITATION",
    "ks:ks_uagg_main":0,
    "name:eng_x_preferred":[
        "Rongkut No 1 Block - 1 2"
    ],
    "name:eng_x_variant":[
        "RONGKUT  No 1 BLOCK - 1 2"
    ],
    "wof:name":"Rongkut No 1 Block - 1 2",
    "wof:placetype":"neighbourhood",
    "wof:population":1204
},
  "geometry": {"coordinates":[93.118751,26.134072],"type":"Point"}
}