{
  "type": "Feature",
  "properties": {
    "iso:country":"IN",
    "ks:ks_name":"Alka",
    "ks:ks_type":"VILLAGE",
    "name:eng_x_preferred":[
        "Alka"
    ],
    "wof:name":"Alka",
    "wof:placetype":"locality"
},
  "geometry": {"coordinates":[83.353539,23.710695],"type":"Point"}
}