{
  "type": "Feature",
  "properties": {
    "gn:admin1_code":"36.0",
    "gn:admin2_code":"188.0",
    "gn:asciiname":"Marwat",
    "gn:country_code":"IN",
    "gn:dem":75,
    "gn:feature_class":"P",
    "gn:feature_code":"PPL",
    "gn:name":"Marwat",
    "gn:population":0,
    "gn:timezone":"Asia/Kolkata",
    "iso:country":"IN",
    "name:pus_x_preferred":[
        "\u0645\u0631\u0648\u062a"
    ],
    "name:urd_x_preferred":[
        "\u0645\u0631\u0648\u062a"
    ],
    "wof:name":"Marwat",
    "wof:placetype":"locality"
},
  "geometry": {"coordinates":[83.51624,26.30189],"type":"Point"}
}