{
  "type": "Feature",
  "properties": {
    "gn:admin1_code":"39.0",
    "gn:admin2_code":"66.0",
    "gn:asciiname":"Thari Ijar",
    "gn:country_code":"IN",
    "gn:dem":1695,
    "gn:feature_class":"P",
    "gn:feature_code":"PPL",
    "gn:name":"Th\u0101ri Ijar",
    "gn:population":0,
    "gn:timezone":"Asia/Kolkata",
    "iso:country":"IN",
    "wof:name":"Thari Ijar",
    "wof:placetype":"locality"
},
  "geometry": {"coordinates":[79.65857,29.34959000000001],"type":"Point"}
}