{
  "type": "Feature",
  "properties": {
    "gn:admin1_code":"39.0",
    "gn:admin2_code":"061",
    "gn:asciiname":"Gauntiali",
    "gn:country_code":"IN",
    "gn:dem":1040,
    "gn:feature_class":"P",
    "gn:feature_code":"PPL",
    "gn:name":"Gaunti\u0101li",
    "gn:population":0,
    "gn:timezone":"Asia/Kolkata",
    "iso:country":"IN",
    "wof:name":"Gauntiali",
    "wof:placetype":"locality"
},
  "geometry": {"coordinates":[78.60495999999998,29.83555],"type":"Point"}
}