{
  "type": "Feature",
  "properties": {
    "iso:country":"IN",
    "ks:ks_name":"Murwai",
    "ks:ks_pop":870,
    "ks:ks_type":"VILLAGE",
    "name:eng_x_preferred":[
        "Murwai"
    ],
    "wof:name":"Murwai",
    "wof:placetype":"locality",
    "wof:population":870
},
  "geometry": {"coordinates":[77.481819,26.277396],"type":"Point"}
}