{
  "type": "Feature",
  "properties": {
    "gn:country":"IN",
    "gn:fcode":"PPL",
    "gn:population":4967,
    "iso:country":"IN",
    "ks:ks_alt_nam":"Balar\u0101mpur",
    "ks:ks_name":"Balarampur",
    "ks:ks_pop":796,
    "ks:ks_type":"VILLAGE",
    "ks:ks_uagg_main":0,
    "name:ben_x_preferred":[
        "\u09ac\u09b2\u09b0\u09be\u09ae\u09aa\u09c1\u09b0"
    ],
    "name:bpy_x_preferred":[
        "\u09ac\u09b2\u09b0\u09be\u09ae\u09aa\u09c1\u09b0"
    ],
    "name:eng_x_preferred":[
        "Balarampur"
    ],
    "name:eng_x_variant":[
        "Balar\u0101mpur"
    ],
    "name:fra_x_preferred":[
        "Balarampur"
    ],
    "name:hin_x_preferred":[
        "\u092c\u0932\u0930\u093e\u092e\u092a\u0941\u0930"
    ],
    "name:ita_x_preferred":[
        "Balarampur"
    ],
    "name:lld_x_preferred":[
        "Balarampur"
    ],
    "name:msa_x_preferred":[
        "Balarampur"
    ],
    "name:nld_x_preferred":[
        "Balarampur"
    ],
    "name:zho_x_preferred":[
        "\u5df4\u62c9\u62c9\u59c6\u666e\u5c14"
    ],
    "qs:name":"Balarampur",
    "qs:name_adm0":"India",
    "qs:name_adm1":"West Bengal",
    "qs:photos_9r":0,
    "qs:photos_sr":0,
    "qs:placetype":"Town",
    "qs:pop_sr":"4",
    "wof:name":"Balarampur",
    "wof:placetype":"neighbourhood",
    "wof:population":796
},
  "geometry": {"coordinates":[88.29777799999999,22.334167],"type":"Point"}
}