{
  "type": "Feature",
  "properties": {
    "iso:country":"IN",
    "ks:ks_name":"Harkanta",
    "ks:ks_pop":162,
    "ks:ks_type":"HABITATION",
    "name:eng_x_preferred":[
        "Harkanta"
    ],
    "wof:name":"Harkanta",
    "wof:placetype":"locality",
    "wof:population":162
},
  "geometry": {"coordinates":[86.299969,24.017339],"type":"Point"}
}