{
  "type": "Feature",
  "properties": {
    "iso:country":"IN",
    "ks:ks_name":"Madnapur",
    "ks:ks_pop":761,
    "ks:ks_type":"VILLAGE",
    "ks:ks_uagg_main":0,
    "name:eng_x_preferred":[
        "Madnapur"
    ],
    "wof:name":"Madnapur",
    "wof:placetype":"neighbourhood",
    "wof:population":761
},
  "geometry": {"coordinates":[87.25731,22.858051],"type":"Point"}
}