{
  "type": "Feature",
  "properties": {
    "iso:country":"IN",
    "ks:ks_alt_nam":"Care colony",
    "ks:ks_name":"Care Colony",
    "ks:ks_pop":155,
    "ks:ks_type":"HABITATION",
    "name:eng_x_preferred":[
        "Care Colony"
    ],
    "wof:name":"Care Colony",
    "wof:placetype":"locality",
    "wof:population":155
},
  "geometry": {"coordinates":[79.105824,10.488391],"type":"Point"}
}