{
  "type": "Feature",
  "properties": {
    "iso:country":"IN",
    "ks:ks_name":"Tambalgothan",
    "ks:ks_pop":415,
    "ks:ks_type":"HABITATION",
    "name:eng_x_preferred":[
        "Tambalgothan"
    ],
    "wof:name":"Tambalgothan",
    "wof:placetype":"locality",
    "wof:population":415
},
  "geometry": {"coordinates":[73.834838,15.879853],"type":"Point"}
}