{
  "type": "Feature",
  "properties": {
    "iso:country":"IN",
    "ks:ks_name":"Pura Karehan",
    "ks:ks_pop":358,
    "ks:ks_type":"HABITATION",
    "name:eng_x_preferred":[
        "Pura Karehan"
    ],
    "wof:name":"Pura Karehan",
    "wof:placetype":"locality",
    "wof:population":358
},
  "geometry": {"coordinates":[81.589696,26.545471],"type":"Point"}
}