{
  "type": "Feature",
  "properties": {
    "gn:admin1_code":"36",
    "gn:admin2_code":"142.0",
    "gn:asciiname":"Hoshdarpur",
    "gn:country_code":"IN",
    "gn:dem":198,
    "gn:feature_class":"P",
    "gn:feature_code":"PPL",
    "gn:name":"Hoshd\u0101rp\u016br",
    "gn:population":0,
    "gn:timezone":"Asia/Kolkata",
    "iso:country":"IN",
    "name:und_x_variant":[
        "Hoshd\u0101rp\u016br",
        "Andhiar"
    ],
    "wof:name":"Hoshdarpur",
    "wof:placetype":"locality"
},
  "geometry": {"coordinates":[78.13212,28.37069],"type":"Point"}
}