{
  "type": "Feature",
  "properties": {
    "iso:country":"IN",
    "ks:ks_name":"Shedikuli",
    "ks:ks_pop":86,
    "ks:ks_type":"HABITATION",
    "name:eng_x_preferred":[
        "Shedikuli"
    ],
    "wof:name":"Shedikuli",
    "wof:placetype":"locality",
    "wof:population":86
},
  "geometry": {"coordinates":[74.533005,14.413335],"type":"Point"}
}