{
  "type": "Feature",
  "properties": {
    "iso:country":"IN",
    "ks:ks_alt_nam":"Ram taliya",
    "ks:ks_name":"Ram Taliya",
    "ks:ks_pop":77,
    "ks:ks_type":"HABITATION",
    "name:eng_x_preferred":[
        "Ram Taliya"
    ],
    "wof:name":"Ram Taliya",
    "wof:placetype":"locality",
    "wof:population":77
},
  "geometry": {"coordinates":[80.713639,27.622963],"type":"Point"}
}