{
  "type": "Feature",
  "properties": {
    "iso:country":"IN",
    "ks:ks_name":"Rupahi Bhakat Gaon",
    "ks:ks_pop":2402,
    "ks:ks_type":"VILLAGE",
    "name:eng_x_preferred":[
        "Rupahi Bhakat Gaon"
    ],
    "wof:name":"Rupahi Bhakat Gaon",
    "wof:placetype":"locality",
    "wof:population":2402
},
  "geometry": {"coordinates":[92.74418799999999,26.407319],"type":"Point"}
}