{
  "type": "Feature",
  "properties": {
    "iso:country":"IN",
    "qs:name":"N.belathur",
    "qs:name_adm0":"India",
    "qs:name_adm1":"Karnataka",
    "qs:photos":271,
    "qs:photos_1k":55,
    "qs:photos_9k":1,
    "qs:photos_9r":4,
    "qs:photos_all":271,
    "qs:photos_sr":5,
    "qs:placetype":"Town",
    "qs:pop_sr":"0",
    "wof:name":"N.belathur",
    "wof:placetype":"locality"
},
  "geometry": {"coordinates":[76.26863400000001,11.961746],"type":"Point"}
}