{
  "type": "Feature",
  "properties": {
    "gn:admin1_code":"12.0",
    "gn:admin2_code":"16.0",
    "gn:asciiname":"Bash",
    "gn:country_code":"IN",
    "gn:dem":2950,
    "gn:feature_class":"P",
    "gn:feature_code":"PPL",
    "gn:name":"B\u0101sh",
    "gn:population":0,
    "gn:timezone":"Asia/Kolkata",
    "iso:country":"IN",
    "name:ceb_x_preferred":[
        "Bash"
    ],
    "name:deu_x_preferred":[
        "Bash"
    ],
    "name:fra_x_preferred":[
        "Bash"
    ],
    "name:jpn_x_preferred":[
        "\u30d0\u30c3\u30b7\u30e5"
    ],
    "name:nds_x_preferred":[
        "Bash"
    ],
    "name:nld_x_preferred":[
        "The Bash"
    ],
    "name:por_x_preferred":[
        "Bash"
    ],
    "name:rus_x_preferred":[
        "Bash"
    ],
    "name:ukr_x_preferred":[
        "Bash"
    ],
    "wof:name":"Bash",
    "wof:placetype":"locality"
},
  "geometry": {"coordinates":[75.80255,33.0062],"type":"Point"}
}