{
  "type": "Feature",
  "properties": {
    "gn:admin1_code":"3.0",
    "gn:admin2_code":"302.0",
    "gn:asciiname":"Rakhapara",
    "gn:country_code":"IN",
    "gn:dem":43,
    "gn:feature_class":"P",
    "gn:feature_code":"PPL",
    "gn:name":"Rakhapara",
    "gn:population":0,
    "gn:timezone":"Asia/Kolkata",
    "iso:country":"IN",
    "wof:name":"Rakhapara",
    "wof:placetype":"locality"
},
  "geometry": {"coordinates":[90.52342,26.09068],"type":"Point"}
}