{
  "type": "Feature",
  "properties": {
    "iso:country":"IN",
    "ks:ks_alt_nam":"CHITTA KHALA",
    "ks:ks_name":"Chitta Khala",
    "ks:ks_pop":349,
    "ks:ks_type":"HABITATION",
    "name:eng_x_preferred":[
        "Chitta Khala"
    ],
    "wof:name":"Chitta Khala",
    "wof:placetype":"locality",
    "wof:population":349
},
  "geometry": {"coordinates":[91.187319,23.701873],"type":"Point"}
}