{
  "type": "Feature",
  "properties": {
    "iso:country":"IN",
    "ks:ks_name":"Mauzampur Dharma",
    "ks:ks_pop":2,
    "ks:ks_type":"HABITATION",
    "name:eng_x_preferred":[
        "Mauzampur Dharma"
    ],
    "wof:name":"Mauzampur Dharma",
    "wof:placetype":"locality",
    "wof:population":2
},
  "geometry": {"coordinates":[78.29706400000001,29.441361],"type":"Point"}
}