{
  "type": "Feature",
  "properties": {
    "iso:country":"IN",
    "ks:ks_name":"Manjholi",
    "ks:ks_pop":53,
    "ks:ks_type":"VILLAGE",
    "name:eng_x_preferred":[
        "Manjholi"
    ],
    "wof:name":"Manjholi",
    "wof:placetype":"locality",
    "wof:population":53
},
  "geometry": {"coordinates":[70.911361,25.818309],"type":"Point"}
}