{
  "type": "Feature",
  "properties": {
    "iso:country":"IN",
    "ks:ks_name":"Tekra Fa",
    "ks:ks_pop":208,
    "ks:ks_type":"HABITATION",
    "name:eng_x_preferred":[
        "Tekra Fa"
    ],
    "wof:name":"Tekra Fa",
    "wof:placetype":"locality",
    "wof:population":208
},
  "geometry": {"coordinates":[73.049111,20.452694],"type":"Point"}
}