{
  "type": "Feature",
  "properties": {
    "iso:country":"IN",
    "ks:ks_name":"Moolamangalam",
    "ks:ks_pop":560,
    "ks:ks_type":"VILLAGE",
    "ks:ks_uagg_main":0,
    "name:eng_x_preferred":[
        "Moolamangalam"
    ],
    "wof:name":"Moolamangalam",
    "wof:placetype":"neighbourhood",
    "wof:population":560
},
  "geometry": {"coordinates":[79.61952599999999,10.863247],"type":"Point"}
}