{
  "type": "Feature",
  "properties": {
    "iso:country":"IN",
    "ks:ks_name":"Kali Tala",
    "ks:ks_pop":394,
    "ks:ks_type":"HABITATION",
    "name:eng_x_preferred":[
        "Kali Tala"
    ],
    "wof:name":"Kali Tala",
    "wof:placetype":"locality",
    "wof:population":394
},
  "geometry": {"coordinates":[86.908901,22.188524],"type":"Point"}
}