{
  "type": "Feature",
  "properties": {
    "iso:country":"IN",
    "ks:ks_name":"Ganwan Tola",
    "ks:ks_pop":430,
    "ks:ks_type":"HABITATION",
    "name:eng_x_preferred":[
        "Ganwan Tola"
    ],
    "wof:name":"Ganwan Tola",
    "wof:placetype":"locality",
    "wof:population":430
},
  "geometry": {"coordinates":[83.039922,24.113066],"type":"Point"}
}