{
  "type": "Feature",
  "properties": {
    "gn:admin1_code":"28.0",
    "gn:admin2_code":"344.0",
    "gn:asciiname":"Jot Ghanashyam",
    "gn:country_code":"IN",
    "gn:dem":5,
    "gn:feature_class":"P",
    "gn:feature_code":"PPL",
    "gn:name":"Jot Ghanashyam",
    "gn:population":0,
    "gn:timezone":"Asia/Kolkata",
    "iso:country":"IN",
    "wof:name":"Jot Ghanashyam",
    "wof:placetype":"locality"
},
  "geometry": {"coordinates":[87.84024000000002,22.51606],"type":"Point"}
}