{
  "type": "Feature",
  "properties": {
    "iso:country":"IN",
    "ks:ks_name":"Kalppakulam",
    "ks:ks_pop":9770,
    "ks:ks_type":"VILLAGE",
    "ks:ks_uagg_main":0,
    "name:eng_x_preferred":[
        "Kalppakulam"
    ],
    "wof:name":"Kalppakulam",
    "wof:placetype":"neighbourhood",
    "wof:population":9770
},
  "geometry": {"coordinates":[77.532917,9.18828],"type":"Point"}
}