{
  "type": "Feature",
  "properties": {
    "iso:country":"IN",
    "ks:ks_name":"Mahugadi Pawai",
    "ks:ks_pop":237,
    "ks:ks_type":"HABITATION",
    "name:eng_x_preferred":[
        "Mahugadi Pawai"
    ],
    "wof:name":"Mahugadi Pawai",
    "wof:placetype":"locality",
    "wof:population":237
},
  "geometry": {"coordinates":[82.675326,24.450995],"type":"Point"}
}