{
  "type": "Feature",
  "properties": {
    "gn:admin1_code":"39",
    "gn:admin2_code":"60.0",
    "gn:asciiname":"Binson Khera",
    "gn:country_code":"IN",
    "gn:dem":1980,
    "gn:feature_class":"P",
    "gn:feature_code":"PPL",
    "gn:name":"Binson Khera",
    "gn:population":0,
    "gn:timezone":"Asia/Kolkata",
    "iso:country":"IN",
    "wof:name":"Binson Khera",
    "wof:placetype":"locality"
},
  "geometry": {"coordinates":[77.80574,30.78534],"type":"Point"}
}