{
  "type": "Feature",
  "properties": {
    "iso:country":"IN",
    "ks:ks_name":"Rangagora",
    "ks:ks_pop":10,
    "ks:ks_type":"VILLAGE",
    "name:eng_x_preferred":[
        "Rangagora"
    ],
    "wof:name":"Rangagora",
    "wof:placetype":"locality",
    "wof:population":10
},
  "geometry": {"coordinates":[86.305257,23.134268],"type":"Point"}
}