{
  "type": "Feature",
  "properties": {
    "gn:admin1_code":"16",
    "gn:admin2_code":"503.0",
    "gn:asciiname":"Phattepur",
    "gn:country_code":"IN",
    "gn:dem":309,
    "gn:feature_class":"P",
    "gn:feature_code":"PPL",
    "gn:name":"Phattepur",
    "gn:population":0,
    "gn:timezone":"Asia/Kolkata",
    "iso:country":"IN",
    "name:msa_x_preferred":[
        "Fattepur"
    ],
    "name:nep_x_preferred":[
        "\u092b\u0924\u094d\u0924\u0947\u092a\u0941\u0930"
    ],
    "name:new_x_preferred":[
        "\u092b\u0924\u094d\u0924\u0947\u092a\u0941\u0930"
    ],
    "name:pol_x_preferred":[
        "Fattepur"
    ],
    "name:vie_x_preferred":[
        "Fattepur"
    ],
    "wof:name":"Phattepur",
    "wof:placetype":"locality"
},
  "geometry": {"coordinates":[77.73194000000002,20.66072],"type":"Point"}
}