{
  "type": "Feature",
  "properties": {
    "gn:admin1_code":"12.0",
    "gn:admin2_code":"9.0",
    "gn:asciiname":"Nawan",
    "gn:country_code":"IN",
    "gn:dem":3004,
    "gn:feature_class":"P",
    "gn:feature_code":"PPL",
    "gn:name":"N\u0101wan",
    "gn:population":0,
    "gn:timezone":"Asia/Kolkata",
    "iso:country":"IN",
    "name:eng_x_preferred":[
        "N\u0101wan"
    ],
    "name:fas_x_preferred":[
        "\u0646\u0648\u0627\u0646"
    ],
    "name:hin_x_preferred":[
        "\u0928\u094c\u0935\u093e\u0901"
    ],
    "name:urd_x_preferred":[
        "\u0646\u0648\u0627\u06ba"
    ],
    "wof:name":"Nawan",
    "wof:placetype":"locality"
},
  "geometry": {"coordinates":[74.58838,34.47107],"type":"Point"}
}