{
  "type": "Feature",
  "properties": {
    "iso:country":"IN",
    "ks:ks_name":"Dhanuk Tola",
    "ks:ks_pop":470,
    "ks:ks_type":"HABITATION",
    "name:eng_x_preferred":[
        "Dhanuk Tola"
    ],
    "wof:name":"Dhanuk Tola",
    "wof:placetype":"locality",
    "wof:population":470
},
  "geometry": {"coordinates":[84.41219599999999,25.971429],"type":"Point"}
}