{
  "type": "Feature",
  "properties": {
    "iso:country":"IN",
    "ks:ks_alt_nam":"Bah\u0101durpur",
    "ks:ks_name":"Bahadurpur",
    "ks:ks_pop":681,
    "ks:ks_type":"VILLAGE",
    "name:eng_x_preferred":[
        "Bahadurpur"
    ],
    "name:eng_x_variant":[
        "Bah\u0101durpur"
    ],
    "wof:name":"Bahadurpur",
    "wof:placetype":"locality",
    "wof:population":681
},
  "geometry": {"coordinates":[78.216846,25.472329],"type":"Point"}
}