{
  "type": "Feature",
  "properties": {
    "iso:country":"IN",
    "ks:ks_name":"Kagooha",
    "ks:ks_pop":560,
    "ks:ks_type":"HABITATION",
    "ks:ks_uagg_main":0,
    "name:eng_x_preferred":[
        "Kagooha"
    ],
    "wof:name":"Kagooha",
    "wof:placetype":"neighbourhood",
    "wof:population":560
},
  "geometry": {"coordinates":[82.78559799999999,26.837725],"type":"Point"}
}