{
  "type": "Feature",
  "properties": {
    "iso:country":"IN",
    "ks:ks_name":"Garhpehra",
    "ks:ks_pop":230,
    "ks:ks_type":"HABITATION",
    "name:eng_x_preferred":[
        "Garhpehra"
    ],
    "wof:name":"Garhpehra",
    "wof:placetype":"locality",
    "wof:population":230
},
  "geometry": {"coordinates":[79.18354100000001,22.81409],"type":"Point"}
}