{
  "type": "Feature",
  "properties": {
    "gn:admin1_code":"2.0",
    "gn:admin2_code":"544.0",
    "gn:asciiname":"Dhamuku",
    "gn:country_code":"IN",
    "gn:dem":702,
    "gn:feature_class":"P",
    "gn:feature_code":"PPL",
    "gn:name":"Dhamuku",
    "gn:population":0,
    "gn:timezone":"Asia/Kolkata",
    "iso:country":"IN",
    "wof:name":"Dhamuku",
    "wof:placetype":"locality"
},
  "geometry": {"coordinates":[83.03554,18.22228],"type":"Point"}
}