{
  "type": "Feature",
  "properties": {
    "gn:admin1_code":"7.0",
    "gn:admin2_code":"97.0",
    "gn:asciiname":"Indrapuri",
    "gn:country_code":"IN",
    "gn:dem":229,
    "gn:feature_class":"P",
    "gn:feature_code":"PPL",
    "gn:name":"Indrapuri",
    "gn:population":0,
    "gn:timezone":"Asia/Kolkata",
    "iso:country":"IN",
    "wof:name":"Indrapuri",
    "wof:placetype":"neighbourhood"
},
  "geometry": {"coordinates":[77.14962,28.62909],"type":"Point"}
}