{
  "type": "Feature",
  "properties": {
    "gn:admin1_code":"35",
    "gn:admin2_code":"462.0",
    "gn:asciiname":"Danga",
    "gn:country_code":"IN",
    "gn:dem":377,
    "gn:feature_class":"P",
    "gn:feature_code":"PPL",
    "gn:name":"D\u0101nga",
    "gn:population":0,
    "gn:timezone":"Asia/Kolkata",
    "iso:country":"IN",
    "name:ben_x_preferred":[
        "\u09a6\u09be\u0999\u09cd\u0997\u09be"
    ],
    "wof:name":"Danga",
    "wof:placetype":"locality"
},
  "geometry": {"coordinates":[81.68042,24.12102],"type":"Point"}
}