{
  "type": "Feature",
  "properties": {
    "gn:admin1_code":"35",
    "gn:admin2_code":"429.0",
    "gn:asciiname":"Udka",
    "gn:country_code":"IN",
    "gn:dem":300,
    "gn:feature_class":"P",
    "gn:feature_code":"PPL",
    "gn:name":"Udka",
    "gn:population":0,
    "gn:timezone":"Asia/Kolkata",
    "iso:country":"IN",
    "ks:ks_name":"Udaka",
    "ks:ks_pop":49,
    "ks:ks_type":"VILLAGE",
    "name:eng_x_preferred":[
        "Udaka"
    ],
    "name:eng_x_variant":[
        "Udka"
    ],
    "wof:name":"Udaka",
    "wof:placetype":"locality",
    "wof:population":49
},
  "geometry": {"coordinates":[81.029203,24.752992],"type":"Point"}
}