{
  "type": "Feature",
  "properties": {
    "iso:country":"IN",
    "ks:ks_name":"Bilatela Sara",
    "ks:ks_pop":0,
    "ks:ks_type":"VILLAGE",
    "name:eng_x_preferred":[
        "Bilatela Sara"
    ],
    "wof:name":"Bilatela Sara",
    "wof:placetype":"locality",
    "wof:population":0
},
  "geometry": {"coordinates":[86.26627000000001,20.058709],"type":"Point"}
}