{
  "type": "Feature",
  "properties": {
    "gn:admin1_code":"40.0",
    "gn:admin2_code":"535",
    "gn:asciiname":"Kalivanul",
    "gn:country_code":"IN",
    "gn:dem":548,
    "gn:feature_class":"P",
    "gn:feature_code":"PPL",
    "gn:name":"Kalivanul",
    "gn:population":0,
    "gn:timezone":"Asia/Kolkata",
    "iso:country":"IN",
    "name:und_x_variant":[
        "Kalivemul",
        "Kalivanul"
    ],
    "wof:name":"Kalivanul",
    "wof:placetype":"neighbourhood"
},
  "geometry": {"coordinates":[78.09883000000001,17.54608],"type":"Point"}
}