{
  "type": "Feature",
  "properties": {
    "gn:admin1_code":"11",
    "gn:admin2_code":"24.0",
    "gn:asciiname":"Chumarra",
    "gn:country_code":"IN",
    "gn:dem":879,
    "gn:feature_class":"P",
    "gn:feature_code":"PPL",
    "gn:name":"Chum\u0101rra",
    "gn:population":0,
    "gn:timezone":"Asia/Kolkata",
    "iso:country":"IN",
    "wof:name":"Chumarra",
    "wof:placetype":"locality"
},
  "geometry": {"coordinates":[76.11391999999999,31.81732],"type":"Point"}
}