{
  "type": "Feature",
  "properties": {
    "iso:country":"IN",
    "ks:ks_name":"West Vellivadi",
    "ks:ks_pop":100,
    "ks:ks_type":"HABITATION",
    "name:eng_x_preferred":[
        "West Vellivadi"
    ],
    "wof:name":"West Vellivadi",
    "wof:placetype":"locality",
    "wof:population":100
},
  "geometry": {"coordinates":[78.356667,10.64091],"type":"Point"}
}