{
  "type": "Feature",
  "properties": {
    "iso:country":"IN",
    "ks:ks_alt_nam":"Dhirechar II",
    "ks:ks_name":"Dhirechar Ii",
    "ks:ks_pop":1940,
    "ks:ks_type":"HABITATION",
    "name:eng_x_preferred":[
        "Dhirechar Ii"
    ],
    "wof:name":"Dhirechar Ii",
    "wof:placetype":"locality",
    "wof:population":1940
},
  "geometry": {"coordinates":[90.402827,26.228534],"type":"Point"}
}