{
  "type": "Feature",
  "properties": {
    "iso:country":"IN",
    "ks:ks_name":"Keelapandy",
    "ks:ks_pop":586,
    "ks:ks_type":"HABITATION",
    "name:eng_x_preferred":[
        "Keelapandy"
    ],
    "wof:name":"Keelapandy",
    "wof:placetype":"locality",
    "wof:population":586
},
  "geometry": {"coordinates":[79.636832,10.479086],"type":"Point"}
}