{
  "type": "Feature",
  "properties": {
    "iso:country":"IN",
    "ks:ks_name":"Wadder Gudem",
    "ks:ks_pop":150,
    "ks:ks_type":"HABITATION",
    "name:eng_x_preferred":[
        "Wadder Gudem"
    ],
    "wof:name":"Wadder Gudem",
    "wof:placetype":"locality",
    "wof:population":150
},
  "geometry": {"coordinates":[78.5099,18.396915],"type":"Point"}
}