{
  "type": "Feature",
  "properties": {
    "iso:country":"IN",
    "ks:ks_name":"Pirakatagaon",
    "ks:ks_pop":844,
    "ks:ks_type":"VILLAGE",
    "name:eng_x_preferred":[
        "Pirakatagaon"
    ],
    "wof:name":"Pirakatagaon",
    "wof:placetype":"locality",
    "wof:population":844
},
  "geometry": {"coordinates":[92.50479,26.660777],"type":"Point"}
}