{
  "type": "Feature",
  "properties": {
    "iso:country":"IN",
    "ks:ks_name":"Balkapai",
    "ks:ks_pop":133,
    "ks:ks_type":"HABITATION",
    "name:eng_x_preferred":[
        "Balkapai"
    ],
    "wof:name":"Balkapai",
    "wof:placetype":"locality",
    "wof:population":133
},
  "geometry": {"coordinates":[83.18317999999999,19.261704],"type":"Point"}
}