{
  "type": "Feature",
  "properties": {
    "iso:country":"IN",
    "ks:ks_name":"Jaharwadi",
    "ks:ks_pop":587,
    "ks:ks_type":"HABITATION",
    "name:eng_x_preferred":[
        "Jaharwadi"
    ],
    "wof:name":"Jaharwadi",
    "wof:placetype":"locality",
    "wof:population":587
},
  "geometry": {"coordinates":[73.90910599999999,16.932517],"type":"Point"}
}