{
  "type": "Feature",
  "properties": {
    "iso:country":"IN",
    "ks:ks_name":"Deodon Ki Dhani",
    "ks:ks_pop":577,
    "ks:ks_type":"VILLAGE",
    "name:eng_x_preferred":[
        "Deodon Ki Dhani"
    ],
    "wof:name":"Deodon Ki Dhani",
    "wof:placetype":"locality",
    "wof:population":577
},
  "geometry": {"coordinates":[71.739147,25.339486],"type":"Point"}
}