{
  "type": "Feature",
  "properties": {
    "iso:country":"IN",
    "ks:ks_name":"Timanejaddu",
    "ks:ks_pop":23,
    "ks:ks_type":"HABITATION",
    "name:eng_x_preferred":[
        "Timanejaddu"
    ],
    "wof:name":"Timanejaddu",
    "wof:placetype":"locality",
    "wof:population":23
},
  "geometry": {"coordinates":[75.29601599999999,13.416327],"type":"Point"}
}