{
  "type": "Feature",
  "properties": {
    "iso:country":"IN",
    "ks:ks_name":"Jhulaguda",
    "ks:ks_pop":103,
    "ks:ks_type":"HABITATION",
    "name:eng_x_preferred":[
        "Jhulaguda"
    ],
    "wof:name":"Jhulaguda",
    "wof:placetype":"locality",
    "wof:population":103
},
  "geometry": {"coordinates":[82.89259199999999,18.990315],"type":"Point"}
}