{
  "type": "Feature",
  "properties": {
    "iso:country":"IN",
    "name:ara_x_preferred":[
        "\u062e\u064a\u0631\u0643\u064a \u062f\u0648\u0644\u0627"
    ],
    "name:ast_x_preferred":[
        "Kherki Daula"
    ],
    "name:ben_bn_x_preferred":[
        "\u0996\u09c7\u09b0\u0995\u09bf \u09a6\u0989\u09b2\u09be"
    ],
    "name:ben_in_x_preferred":[
        "\u0996\u09c7\u09b0\u0995\u09bf \u09a6\u0989\u09b2\u09be"
    ],
    "name:eng_x_preferred":[
        "Kherki Daula"
    ],
    "name:guj_x_preferred":[
        "\u0a96\u0ac7\u0ab0\u0a95\u0ac0 \u0aa6\u0acc\u0ab2\u0abe"
    ],
    "name:hin_x_preferred":[
        "\u0916\u0947\u0930\u0915\u0940 \u0926\u094c\u0932\u093e"
    ],
    "name:kan_x_preferred":[
        "\u0c96\u0cc7\u0cb0\u0ccd\u0c95\u0cbf \u0ca6\u0ccc\u0cb2\u0cbe"
    ],
    "name:mal_x_preferred":[
        "\u0d16\u0d47\u0d7c\u0d15\u0d3f \u0d26\u0d57 \u0d33"
    ],
    "name:mar_x_preferred":[
        "\u0916\u0947\u0930\u0915\u0940 \u0926\u094c\u0932\u093e"
    ],
    "name:nld_x_preferred":[
        "Kherki Daula"
    ],
    "name:pan_x_preferred":[
        "\u0a16\u0a48\u0a30\u0a15\u0a40 \u0a21\u0a4c\u0a32\u0a3e"
    ],
    "name:tam_x_preferred":[
        "\u0b95\u0bc6\u0bb0\u0bcd\u0b95\u0bbf \u0ba4\u0bcc\u0bb2\u0bbe"
    ],
    "name:tel_x_preferred":[
        "\u0c16\u0c46\u0c30\u0c4d\u0c15\u0c3f \u0c21\u0c35\u0c41\u0c32\u0c3e"
    ],
    "name:urd_x_preferred":[
        "\u06a9\u06be\u0691\u06a9\u06cc \u062f\u0648\u0644\u0627"
    ],
    "qs:gn_adm0_cc":"IN",
    "qs:gn_local":1270642,
    "qs:gn_nam_loc":"Gurgaon, Gurgaon, Haryana, IN",
    "qs:gn_namadm1":"10",
    "qs:local_max":764,
    "qs:local_sum":4037,
    "qs:localhoods":24,
    "qs:name":"Kherki Daula",
    "qs:name_adm0":"India",
    "qs:name_adm1":"Haryana",
    "qs:name_adm2":"Gurgaon",
    "qs:name_local":"Gurgaon",
    "qs:photo_max":12,
    "qs:photo_sum":18,
    "qs:placetype":"Suburb",
    "qs:quad_count":5,
    "qs:woe_adm0":23424848,
    "qs:woe_adm1":2345744,
    "qs:woe_adm2":12586441,
    "qs:woe_lau":0,
    "qs:woe_local":2295020,
    "qs:woe_ver":"7.10.0",
    "wd:wordcount":165,
    "wof:lang":[
        "eng"
    ],
    "wof:name":"Kherki Daula",
    "wof:placetype":"neighbourhood"
},
  "geometry": {"coordinates":[76.98402400000001,28.402675],"type":"Point"}
}