{
  "type": "Feature",
  "properties": {
    "iso:country":"IN",
    "name:eng_x_preferred":[
        "Kherki Daula"
    ],
    "name:unk_x_variant":[
        "Kherki Daula"
    ],
    "qs:gn_adm0_cc":"IN",
    "qs:gn_local":1270642,
    "qs:gn_nam_loc":"Gurgaon, Gurgaon, Haryana, IN",
    "qs:gn_namadm1":"10",
    "qs:local_max":764,
    "qs:local_sum":4037,
    "qs:localhoods":24,
    "qs:name":"Kherki Daula",
    "qs:name_adm0":"India",
    "qs:name_adm1":"Haryana",
    "qs:name_adm2":"Gurgaon",
    "qs:name_local":"Gurgaon",
    "qs:photo_max":12,
    "qs:photo_sum":18,
    "qs:placetype":"Suburb",
    "qs:quad_count":5,
    "qs:woe_adm0":23424848,
    "qs:woe_adm1":2345744,
    "qs:woe_adm2":12586441,
    "qs:woe_lau":0,
    "qs:woe_local":2295020,
    "qs:woe_ver":"7.10.0",
    "wd:wordcount":165,
    "wof:lang":[
        "eng"
    ],
    "wof:name":"Kherki Daula",
    "wof:placetype":"neighbourhood"
},
  "geometry": {"coordinates":[76.98402400000001,28.402675],"type":"Point"}
}