{
  "type": "Feature",
  "properties": {
    "iso:country":"IN",
    "ks:ks_alt_nam":"10 SD-A",
    "ks:ks_name":"10 Sd-a",
    "ks:ks_pop":30,
    "ks:ks_type":"HABITATION",
    "name:eng_x_preferred":[
        "10 Sd-a"
    ],
    "wof:name":"10 Sd-a",
    "wof:placetype":"locality",
    "wof:population":30
},
  "geometry": {"coordinates":[73.721306,29.266894],"type":"Point"}
}