{
  "type": "Feature",
  "properties": {
    "gn:admin1_code":"01",
    "gn:admin2_code":"640.0",
    "gn:asciiname":"Wrightmyo",
    "gn:country_code":"IN",
    "gn:dem":112,
    "gn:feature_class":"P",
    "gn:feature_code":"PPL",
    "gn:name":"Wrightmyo",
    "gn:population":0,
    "gn:timezone":"Asia/Kolkata",
    "iso:country":"IN",
    "ks:ks_name":"Wrightmyo",
    "ks:ks_type":"VILLAGE",
    "ks:ks_uagg_main":0,
    "name:eng_x_preferred":[
        "Wrightmyo"
    ],
    "wof:name":"Wrightmyo",
    "wof:placetype":"neighbourhood"
},
  "geometry": {"coordinates":[92.709594,11.78292],"type":"Point"}
}