{
  "type": "Feature",
  "properties": {
    "gn:admin1_code":"35",
    "gn:admin2_code":"429.0",
    "gn:asciiname":"Nimi",
    "gn:country_code":"IN",
    "gn:dem":311,
    "gn:feature_class":"P",
    "gn:feature_code":"PPL",
    "gn:name":"Nimi",
    "gn:population":0,
    "gn:timezone":"Asia/Kolkata",
    "iso:country":"IN",
    "ks:ks_name":"Nimi",
    "ks:ks_pop":1108,
    "ks:ks_type":"VILLAGE",
    "name:ceb_x_preferred":[
        "Nimi"
    ],
    "name:eng_x_preferred":[
        "Nimi"
    ],
    "name:swe_x_preferred":[
        "Nimi"
    ],
    "wof:name":"Nimi",
    "wof:placetype":"locality",
    "wof:population":1108
},
  "geometry": {"coordinates":[80.91194299999999,24.644244],"type":"Point"}
}