{
  "type": "Feature",
  "properties": {
    "gn:admin1_code":"16",
    "gn:admin2_code":"503.0",
    "gn:asciiname":"Baglinga",
    "gn:country_code":"IN",
    "gn:dem":582,
    "gn:feature_class":"P",
    "gn:feature_code":"PPL",
    "gn:name":"B\u0101glinga",
    "gn:population":0,
    "gn:timezone":"Asia/Kolkata",
    "iso:country":"IN",
    "wof:name":"Baglinga",
    "wof:placetype":"locality"
},
  "geometry": {"coordinates":[77.34964000000002,21.35888],"type":"Point"}
}