{
  "type": "Feature",
  "properties": {
    "gn:admin1_code":"11",
    "gn:admin2_code":"27.0",
    "gn:asciiname":"Thara",
    "gn:country_code":"IN",
    "gn:dem":872,
    "gn:feature_class":"P",
    "gn:feature_code":"PPL",
    "gn:name":"Th\u0101ra",
    "gn:population":0,
    "gn:timezone":"Asia/Kolkata",
    "iso:country":"IN",
    "name:ceb_x_preferred":[
        "Thara"
    ],
    "name:swe_x_preferred":[
        "Thara"
    ],
    "wof:name":"Thara",
    "wof:placetype":"locality"
},
  "geometry": {"coordinates":[76.87597,31.48834],"type":"Point"}
}