{
  "type": "Feature",
  "properties": {
    "gn:admin1_code":"21",
    "gn:admin2_code":"395.0",
    "gn:asciiname":"Podakhunti",
    "gn:country_code":"IN",
    "gn:dem":600,
    "gn:feature_class":"P",
    "gn:feature_code":"PPL",
    "gn:name":"Podakhunti",
    "gn:population":0,
    "gn:timezone":"Asia/Kolkata",
    "iso:country":"IN",
    "ks:ks_name":"Podeikhunti",
    "ks:ks_pop":53,
    "ks:ks_type":"VILLAGE",
    "name:eng_x_preferred":[
        "Podeikhunti"
    ],
    "name:eng_x_variant":[
        "Podakhunti"
    ],
    "wof:name":"Podeikhunti",
    "wof:placetype":"locality",
    "wof:population":53
},
  "geometry": {"coordinates":[83.30825299999999,19.723786],"type":"Point"}
}