{
  "type": "Feature",
  "properties": {
    "iso:country":"IN",
    "ks:ks_name":"Hosahundi",
    "ks:ks_pop":1537,
    "ks:ks_type":"VILLAGE",
    "ks:ks_uagg_main":0,
    "name:eng_x_preferred":[
        "Hosahundi"
    ],
    "wof:name":"Hosahundi",
    "wof:placetype":"neighbourhood",
    "wof:population":1537
},
  "geometry": {"coordinates":[76.67049,12.254289],"type":"Point"}
}