{
  "type": "Feature",
  "properties": {
    "gn:admin1_code":"21",
    "gn:admin2_code":"395.0",
    "gn:asciiname":"Garudaguda",
    "gn:country_code":"IN",
    "gn:dem":512,
    "gn:feature_class":"P",
    "gn:feature_code":"PPL",
    "gn:name":"Garudaguda",
    "gn:population":0,
    "gn:timezone":"Asia/Kolkata",
    "iso:country":"IN",
    "wof:name":"Garudaguda",
    "wof:placetype":"locality"
},
  "geometry": {"coordinates":[83.23119,19.75118],"type":"Point"}
}