{
  "type": "Feature",
  "properties": {
    "iso:country":"IN",
    "ks:ks_alt_nam":"Karm\u0101t\u0101nr",
    "ks:ks_name":"Karmatanr",
    "ks:ks_pop":431,
    "ks:ks_type":"VILLAGE",
    "name:eng_x_preferred":[
        "Karmatanr"
    ],
    "name:eng_x_variant":[
        "Karm\u0101t\u0101nr"
    ],
    "wof:name":"Karmatanr",
    "wof:placetype":"locality",
    "wof:population":431
},
  "geometry": {"coordinates":[86.305909,24.013219],"type":"Point"}
}