{
  "type": "Feature",
  "properties": {
    "gn:admin1_code":"16.0",
    "gn:admin2_code":"497.0",
    "gn:asciiname":"Bhadgaon",
    "gn:country_code":"IN",
    "gn:dem":134,
    "gn:feature_class":"P",
    "gn:feature_code":"PPL",
    "gn:name":"Bhadgaon",
    "gn:population":0,
    "gn:timezone":"Asia/Kolkata",
    "iso:country":"IN",
    "ks:ks_name":"Bhadgaon",
    "ks:ks_pop":194,
    "ks:ks_type":"VILLAGE",
    "ks:ks_uagg_main":0,
    "name:eng_x_preferred":[
        "Bhadgaon"
    ],
    "wof:name":"Bhadgaon",
    "wof:placetype":"neighbourhood",
    "wof:population":194
},
  "geometry": {"coordinates":[74.603482,21.418653],"type":"Point"}
}