{
  "type": "Feature",
  "properties": {
    "gn:admin1_code":"19.0",
    "gn:admin2_code":"575.0",
    "gn:asciiname":"Kodiyala",
    "gn:country_code":"IN",
    "gn:dem":109,
    "gn:feature_class":"P",
    "gn:feature_code":"PPLL",
    "gn:name":"Kodiyala",
    "gn:population":0,
    "gn:timezone":"Asia/Kolkata",
    "iso:country":"IN",
    "ks:ks_name":"Kodiyala",
    "ks:ks_pop":2299,
    "ks:ks_type":"VILLAGE",
    "name:eng_x_preferred":[
        "Kodiyala"
    ],
    "wof:name":"Kodiyala",
    "wof:placetype":"locality",
    "wof:population":2299
},
  "geometry": {"coordinates":[75.37085500000001,12.686846],"type":"Point"}
}