{
  "type": "Feature",
  "properties": {
    "iso:country":"IN",
    "ks:ks_name":"Paharpur Yadau",
    "ks:ks_pop":80,
    "ks:ks_type":"HABITATION",
    "name:eng_x_preferred":[
        "Paharpur Yadau"
    ],
    "wof:name":"Paharpur Yadau",
    "wof:placetype":"locality",
    "wof:population":80
},
  "geometry": {"coordinates":[82.263615,27.292363],"type":"Point"}
}