{
  "type": "Feature",
  "properties": {
    "gn:admin1_code":"36.0",
    "gn:admin2_code":"185.0",
    "gn:asciiname":"Dandwa Shukul",
    "gn:country_code":"IN",
    "gn:dem":91,
    "gn:feature_class":"P",
    "gn:feature_code":"PPL",
    "gn:name":"Dandwa Shukul",
    "gn:population":0,
    "gn:timezone":"Asia/Kolkata",
    "iso:country":"IN",
    "ks:ks_name":"Dandwa Shukul",
    "ks:ks_type":"VILLAGE",
    "name:eng_x_preferred":[
        "Dandwa Shukul"
    ],
    "wof:name":"Dandwa Shukul",
    "wof:placetype":"locality"
},
  "geometry": {"coordinates":[82.80655400000001,27.063518],"type":"Point"}
}