{
  "type": "Feature",
  "properties": {
    "gn:admin1_code":"10",
    "gn:admin2_code":"89.0",
    "gn:asciiname":"Khanbi",
    "gn:country_code":"IN",
    "gn:dem":196,
    "gn:feature_class":"P",
    "gn:feature_code":"PPL",
    "gn:name":"Kh\u0101nbi",
    "gn:population":0,
    "gn:timezone":"Asia/Kolkata",
    "iso:country":"IN",
    "wof:name":"Khanbi",
    "wof:placetype":"locality"
},
  "geometry": {"coordinates":[77.41486,27.96783],"type":"Point"}
}