{
  "type": "Feature",
  "properties": {
    "iso:country":"IN",
    "ks:ks_name":"Koiri Tola",
    "ks:ks_pop":88,
    "ks:ks_type":"HABITATION",
    "name:eng_x_preferred":[
        "Koiri Tola"
    ],
    "wof:name":"Koiri Tola",
    "wof:placetype":"locality",
    "wof:population":88
},
  "geometry": {"coordinates":[84.28104,26.108828],"type":"Point"}
}