{
  "type": "Feature",
  "properties": {
    "iso:country":"IN",
    "ks:ks_name":"Sonapokhari",
    "ks:ks_pop":266,
    "ks:ks_type":"VILLAGE",
    "name:eng_x_preferred":[
        "Sonapokhari"
    ],
    "wof:name":"Sonapokhari",
    "wof:placetype":"locality",
    "wof:population":266
},
  "geometry": {"coordinates":[86.537181,21.628149],"type":"Point"}
}