{
  "type": "Feature",
  "properties": {
    "iso:country":"IN",
    "ks:ks_name":"Gunagummi",
    "ks:ks_pop":38,
    "ks:ks_type":"HABITATION",
    "name:eng_x_preferred":[
        "Gunagummi"
    ],
    "wof:name":"Gunagummi",
    "wof:placetype":"locality",
    "wof:population":38
},
  "geometry": {"coordinates":[82.792866,18.187491],"type":"Point"}
}