{
  "type": "Feature",
  "properties": {
    "iso:country":"IN",
    "ks:ks_name":"Hirbahal",
    "ks:ks_pop":346,
    "ks:ks_type":"VILLAGE",
    "name:eng_x_preferred":[
        "Hirbahal"
    ],
    "wof:name":"Hirbahal",
    "wof:placetype":"locality",
    "wof:population":346
},
  "geometry": {"coordinates":[86.46621399999999,23.42239],"type":"Point"}
}