{
  "type": "Feature",
  "properties": {
    "iso:country":"IN",
    "ks:ks_alt_nam":"Bahati Char Pt II",
    "ks:ks_name":"Bahati Char Pt Ii",
    "ks:ks_pop":1173,
    "ks:ks_type":"HABITATION",
    "name:eng_x_preferred":[
        "Bahati Char Pt Ii"
    ],
    "wof:name":"Bahati Char Pt Ii",
    "wof:placetype":"locality",
    "wof:population":1173
},
  "geometry": {"coordinates":[90.836602,26.1018],"type":"Point"}
}