{
  "type": "Feature",
  "properties": {
    "iso:country":"IN",
    "qs:name":"Padhar Buzurg",
    "qs:name_adm0":"India",
    "qs:name_adm1":"Madhya Pradesh",
    "qs:photos":34,
    "qs:photos_1k":7,
    "qs:photos_9k":1,
    "qs:photos_9r":2,
    "qs:photos_all":34,
    "qs:photos_sr":2,
    "qs:placetype":"Town",
    "qs:pop_sr":"0",
    "wof:name":"Padhar Buzurg",
    "wof:placetype":"locality"
},
  "geometry": {"coordinates":[77.86371200000001,22.050959],"type":"Point"}
}