{
  "type": "Feature",
  "properties": {
    "iso:country":"IN",
    "ks:ks_name":"Roppadapalya",
    "ks:ks_pop":10,
    "ks:ks_type":"HABITATION",
    "ks:ks_uagg_main":0,
    "name:eng_x_preferred":[
        "Roppadapalya"
    ],
    "wof:name":"Roppadapalya",
    "wof:placetype":"neighbourhood",
    "wof:population":10
},
  "geometry": {"coordinates":[76.965228,13.387721],"type":"Point"}
}