{
  "type": "Feature",
  "properties": {
    "iso:country":"IN",
    "ks:ks_name":"Bisadihi",
    "ks:ks_pop":498,
    "ks:ks_type":"HABITATION",
    "name:eng_x_preferred":[
        "Bisadihi"
    ],
    "wof:name":"Bisadihi",
    "wof:placetype":"locality",
    "wof:population":498
},
  "geometry": {"coordinates":[84.04722599999999,21.760695],"type":"Point"}
}