{
  "type": "Feature",
  "properties": {
    "iso:country":"IN",
    "ks:ks_name":"Barmasia",
    "ks:ks_pop":336,
    "ks:ks_type":"HABITATION",
    "name:eng_x_preferred":[
        "Barmasia"
    ],
    "wof:name":"Barmasia",
    "wof:placetype":"locality",
    "wof:population":336
},
  "geometry": {"coordinates":[86.784229,24.076252],"type":"Point"}
}