{
  "type": "Feature",
  "properties": {
    "gn:admin1_code":"35",
    "gn:admin2_code":"421.0",
    "gn:asciiname":"Tilawali",
    "gn:country_code":"IN",
    "gn:dem":302,
    "gn:feature_class":"P",
    "gn:feature_code":"PPL",
    "gn:name":"Til\u0101wali",
    "gn:population":0,
    "gn:timezone":"Asia/Kolkata",
    "iso:country":"IN",
    "wof:name":"Tilawali",
    "wof:placetype":"locality"
},
  "geometry": {"coordinates":[77.86114000000001,26.1196],"type":"Point"}
}