{
  "type": "Feature",
  "properties": {
    "gn:admin1_code":"35",
    "gn:admin2_code":"421.0",
    "gn:asciiname":"Tilawali",
    "gn:country_code":"IN",
    "gn:dem":302,
    "gn:feature_class":"P",
    "gn:feature_code":"PPL",
    "gn:name":"Til\u0101wali",
    "gn:population":0,
    "gn:timezone":"Asia/Kolkata",
    "iso:country":"IN",
    "ks:ks_name":"Tilawali",
    "ks:ks_pop":180,
    "ks:ks_type":"HABITATION",
    "name:eng_x_preferred":[
        "Tilawali"
    ],
    "wof:name":"Tilawali",
    "wof:placetype":"locality",
    "wof:population":180
},
  "geometry": {"coordinates":[77.862405,26.119814],"type":"Point"}
}