{
  "type": "Feature",
  "properties": {
    "iso:country":"IN",
    "ks:ks_name":"Rajadiya",
    "ks:ks_pop":734,
    "ks:ks_type":"VILLAGE",
    "name:eng_x_preferred":[
        "Rajadiya"
    ],
    "wof:name":"Rajadiya",
    "wof:placetype":"locality",
    "wof:population":734
},
  "geometry": {"coordinates":[74.20798000000001,23.181814],"type":"Point"}
}