{
  "type": "Feature",
  "properties": {
    "iso:country":"IN",
    "ks:ks_name":"Khairabada",
    "ks:ks_pop":630,
    "ks:ks_type":"VILLAGE",
    "name:eng_x_preferred":[
        "Khairabada"
    ],
    "wof:name":"Khairabada",
    "wof:placetype":"locality",
    "wof:population":630
},
  "geometry": {"coordinates":[82.357966,24.322741],"type":"Point"}
}