{
  "type": "Feature",
  "properties": {
    "iso:country":"IN",
    "ks:ks_name":"Patelpara",
    "ks:ks_pop":369,
    "ks:ks_type":"HABITATION",
    "name:eng_x_preferred":[
        "Patelpara"
    ],
    "wof:name":"Patelpara",
    "wof:placetype":"locality",
    "wof:population":369
},
  "geometry": {"coordinates":[81.56195200000001,19.849338],"type":"Point"}
}