{
  "type": "Feature",
  "properties": {
    "gn:admin1_code":"40",
    "gn:admin2_code":"532.0",
    "gn:asciiname":"Umri Khurd",
    "gn:country_code":"IN",
    "gn:dem":390,
    "gn:feature_class":"P",
    "gn:feature_code":"PPL",
    "gn:name":"Umri Khurd",
    "gn:population":0,
    "gn:timezone":"Asia/Kolkata",
    "iso:country":"IN",
    "wof:name":"Umri Khurd",
    "wof:placetype":"neighbourhood"
},
  "geometry": {"coordinates":[77.86951999999999,19.05779],"type":"Point"}
}