{
  "type": "Feature",
  "properties": {
    "gn:admin1_code":"35.0",
    "gn:admin2_code":"454.0",
    "gn:asciiname":"Deori Tola",
    "gn:country_code":"IN",
    "gn:dem":477,
    "gn:feature_class":"P",
    "gn:feature_code":"PPL",
    "gn:name":"Deor\u012b Tol\u0101",
    "gn:population":0,
    "gn:timezone":"Asia/Kolkata",
    "iso:country":"IN",
    "wof:name":"Deori Tola",
    "wof:placetype":"locality"
},
  "geometry": {"coordinates":[80.27356999999998,22.83154],"type":"Point"}
}