{
  "type": "Feature",
  "properties": {
    "gn:admin1_code":"39",
    "gn:admin2_code":"59.0",
    "gn:asciiname":"Barkot",
    "gn:country_code":"IN",
    "gn:dem":671,
    "gn:feature_class":"P",
    "gn:feature_code":"PPL",
    "gn:name":"Barkot",
    "gn:population":0,
    "gn:timezone":"Asia/Kolkata",
    "iso:country":"IN",
    "wof:name":"Barkot",
    "wof:placetype":"locality"
},
  "geometry": {"coordinates":[78.80539,30.23606],"type":"Point"}
}