{
  "type": "Feature",
  "properties": {
    "iso:country":"IN",
    "ks:ks_name":"Bardadka",
    "ks:ks_pop":100,
    "ks:ks_type":"HABITATION",
    "name:eng_x_preferred":[
        "Bardadka"
    ],
    "wof:name":"Bardadka",
    "wof:placetype":"locality",
    "wof:population":100
},
  "geometry": {"coordinates":[75.197714,12.99736],"type":"Point"}
}