{
  "type": "Feature",
  "properties": {
    "gn:admin1_code":"12.0",
    "gn:admin2_code":"2.0",
    "gn:asciiname":"Datsan",
    "gn:country_code":"IN",
    "gn:dem":1940,
    "gn:feature_class":"P",
    "gn:feature_code":"PPL",
    "gn:name":"D\u0101tsan",
    "gn:population":0,
    "gn:timezone":"Asia/Kolkata",
    "iso:country":"IN",
    "name:bxr_x_preferred":[
        "\u0414\u0430\u0441\u0430\u043d"
    ],
    "name:deu_x_preferred":[
        "Dazan"
    ],
    "name:est_x_preferred":[
        "Datsan"
    ],
    "name:fra_x_preferred":[
        "Dratsang"
    ],
    "name:jpn_x_preferred":[
        "\u30c0\u30c4\u30a1\u30f3"
    ],
    "name:nld_x_preferred":[
        "Datsan"
    ],
    "name:pol_x_preferred":[
        "Dacan"
    ],
    "name:rus_x_preferred":[
        "\u0414\u0430\u0446\u0430\u043d"
    ],
    "name:tam_x_preferred":[
        "\u0baa\u0bc1\u0ba4\u0bcd\u0ba4 \u0b95\u0bcb\u0bb5\u0bbf\u0bb2\u0bcd"
    ],
    "name:tyv_x_preferred":[
        "\u0414\u0430\u0441\u0441\u044b\u04a3"
    ],
    "name:ukr_x_preferred":[
        "\u0414\u0430\u0446\u0430\u043d"
    ],
    "wof:name":"Datsan",
    "wof:placetype":"locality"
},
  "geometry": {"coordinates":[74.59678000000002,33.97598],"type":"Point"}
}