{
  "type": "Feature",
  "properties": {
    "iso:country":"IN",
    "ks:ks_name":"Napali Pam",
    "ks:ks_pop":305,
    "ks:ks_type":"HABITATION",
    "ks:ks_uagg_main":0,
    "name:eng_x_preferred":[
        "Napali Pam"
    ],
    "wof:name":"Napali Pam",
    "wof:placetype":"neighbourhood",
    "wof:population":305
},
  "geometry": {"coordinates":[92.666189,26.772005],"type":"Point"}
}