{
  "type": "Feature",
  "properties": {
    "iso:country":"IN",
    "ks:ks_name":"Madhan Chara",
    "ks:ks_pop":140,
    "ks:ks_type":"HABITATION",
    "name:eng_x_preferred":[
        "Madhan Chara"
    ],
    "wof:name":"Madhan Chara",
    "wof:placetype":"locality",
    "wof:population":140
},
  "geometry": {"coordinates":[91.44247300000001,24.04723],"type":"Point"}
}