{
  "type": "Feature",
  "properties": {
    "gn:country":"IN",
    "gn:fcode":"PPL",
    "gn:pop":0,
    "iso:country":"IN",
    "name:dut_x_preferred":[
        "Velim"
    ],
    "name:eng_x_preferred":[
        "Velim"
    ],
    "name:per_x_preferred":[
        "\u0648\u0644\u06cc\u0645\u060c \u06af\u0648\u0627"
    ],
    "name:unk_x_variant":[
        "Velim"
    ],
    "qs:name":"Vanelim",
    "qs:name_adm0":"India",
    "qs:name_adm1":"Goa",
    "qs:photos":3,
    "qs:photos_1k":1,
    "qs:photos_9k":1,
    "qs:photos_9r":1,
    "qs:photos_all":3,
    "qs:photos_sr":1,
    "qs:placetype":"Town",
    "qs:pop_sr":"0",
    "wof:name":"Vanelim",
    "wof:placetype":"locality",
    "wof:population":0
},
  "geometry": {"coordinates":[73.97592,15.16441],"type":"Point"}
}