{
  "type": "Feature",
  "properties": {
    "gn:country":"IN",
    "gn:fcode":"PPL",
    "gn:population":0,
    "iso:country":"IN",
    "name:ara_x_preferred":[
        "\u0641\u064a\u0644\u064a\u0645"
    ],
    "name:ben_x_preferred":[
        "\u09ad\u09c7\u09b2\u09bf\u09ae"
    ],
    "name:deu_x_preferred":[
        "Velim"
    ],
    "name:eng_x_preferred":[
        "Velim"
    ],
    "name:fas_x_preferred":[
        "\u0648\u0644\u06cc\u0645\u060c \u06af\u0648\u0627"
    ],
    "name:fas_x_variant":[
        "\u0648\u0644\u06cc\u0645"
    ],
    "name:fra_x_preferred":[
        "V\u00e9lim"
    ],
    "name:gom_x_preferred":[
        "Velim"
    ],
    "name:heb_x_preferred":[
        "\u05d5\u05dc\u05d9\u05dd"
    ],
    "name:hin_x_preferred":[
        "\u0935\u0947\u0932\u093f\u092e"
    ],
    "name:nld_x_preferred":[
        "Velim"
    ],
    "name:por_x_preferred":[
        "Velim"
    ],
    "name:tam_x_preferred":[
        "\u0bb5\u0bc6\u0bb2\u0bbf\u0bae\u0bcd"
    ],
    "qs:name":"Vanelim",
    "qs:name_adm0":"India",
    "qs:name_adm1":"Goa",
    "qs:photos":3,
    "qs:photos_1k":1,
    "qs:photos_9k":1,
    "qs:photos_9r":1,
    "qs:photos_all":3,
    "qs:photos_sr":1,
    "qs:placetype":"Town",
    "qs:pop_sr":"0",
    "wof:name":"Vanelim",
    "wof:placetype":"locality",
    "wof:population":0
},
  "geometry": {"coordinates":[73.97592,15.16441],"type":"Point"}
}