{
  "type": "Feature",
  "properties": {
    "iso:country":"IN",
    "ks:ks_name":"Marhia",
    "ks:ks_pop":120,
    "ks:ks_type":"HABITATION",
    "name:eng_x_preferred":[
        "Marhia"
    ],
    "wof:name":"Marhia",
    "wof:placetype":"locality",
    "wof:population":120
},
  "geometry": {"coordinates":[79.766082,27.025963],"type":"Point"}
}