{
  "type": "Feature",
  "properties": {
    "iso:country":"IN",
    "ks:ks_name":"Samjoida",
    "ks:ks_pop":63,
    "ks:ks_type":"VILLAGE",
    "name:eng_x_preferred":[
        "Samjoida"
    ],
    "wof:name":"Samjoida",
    "wof:placetype":"locality",
    "wof:population":63
},
  "geometry": {"coordinates":[74.485848,15.191795],"type":"Point"}
}