{
  "type": "Feature",
  "properties": {
    "iso:country":"IN",
    "name:ara_x_preferred":[
        "\u0641\u064a\u0631\u0627\u0628\u0627\u0646\u062f\u0627\u0646\u0628\u0627\u062a\u064a\u0646\u0627\u0645"
    ],
    "name:ben_bn_x_preferred":[
        "\u09ac\u09c0\u09b0\u09be\u09aa\u09cd\u09aa\u09be\u09a8\u09be\u09a6\u09bf\u09df\u09be\u09aa\u09be\u099f\u09cd\u099f\u09bf\u09a8\u09be\u09ae"
    ],
    "name:ben_in_x_preferred":[
        "\u09ac\u09c0\u09b0\u09be\u09aa\u09cd\u09aa\u09be\u09a8\u09be\u09a6\u09bf\u09df\u09be\u09aa\u09be\u099f\u09cd\u099f\u09bf\u09a8\u09be\u09ae"
    ],
    "name:eng_x_preferred":[
        "Veerapandianpattinam"
    ],
    "name:guj_x_preferred":[
        "\u0ab5\u0ac0\u0ab0\u0abe\u0aaa\u0aa8\u0acd\u0aa6\u0acd\u0aaf\u0abe\u0aa8\u0aaa\u0a9f\u0abf\u0aa8\u0abe\u0aae\u0acd"
    ],
    "name:hin_x_preferred":[
        "\u0935\u0940\u0930\u092a\u0902\u0921\u093f\u092f\u0928\u092a\u0924\u094d\u0924\u093f\u0928\u092e"
    ],
    "name:kan_x_preferred":[
        "\u0cb5\u0cc0\u0cb0\u0caa\u0cbe\u0c82\u0ca1\u0ccd\u0caf\u0ca8\u0ccd"
    ],
    "name:mal_x_preferred":[
        "\u0d35\u0d40\u0d30\u0d2a\u0d3e\u0d23\u0d4d\u0d21\u0d4d\u0d2f\u0d2a\u0d1f\u0d4d\u0d1f\u0d23\u0d02"
    ],
    "name:mar_x_preferred":[
        "\u0935\u0940\u0930\u092a\u093e\u0902\u0921\u093f\u092f\u093e\u0928\u092a\u091f\u094d\u091f\u093f\u0928\u092e\u094d"
    ],
    "name:pan_x_preferred":[
        "\u0a35\u0a40\u0a30\u0a3e\u0a2a\u0a3e\u0a02\u0a21\u0a40\u0a05\u0a28\u0a2a\u0a1f\u0a3f\u0a28\u0a2e"
    ],
    "name:tam_x_preferred":[
        "\u0bb5\u0bc0\u0bb0\u0baa\u0bbe\u0ba3\u0bcd\u0b9f\u0bbf\u0baf\u0ba9\u0bcd\u0baa\u0b9f\u0bcd\u0b9f\u0bbf\u0ba9\u0bae\u0bcd"
    ],
    "name:tel_x_preferred":[
        "\u0c35\u0c40\u0c30\u0c2a\u0c3e\u0c02\u0c21\u0c3f\u0c2f\u0c28\u0c4d"
    ],
    "name:urd_x_preferred":[
        "\u0648\u06cc\u0631\u067e\u0646 \u0688\u06cc\u0627\u0646 \u067e\u0679\u0651\u06cc\u0646\u0645"
    ],
    "qs:gn_adm0_cc":"IN",
    "qs:gn_local":1254390,
    "qs:gn_nam_loc":"puliyangudi",
    "qs:gn_namadm1":"25",
    "qs:local_max":18,
    "qs:local_sum":18,
    "qs:localhoods":1,
    "qs:name":"Veerapandianpattinam",
    "qs:name_adm0":"India",
    "qs:name_adm1":"Tamil Nadu",
    "qs:name_adm2":"Thoothukkudi",
    "qs:name_local":"Tiruchendur",
    "qs:photo_max":12,
    "qs:photo_sum":18,
    "qs:placetype":"Suburb",
    "qs:quad_count":4,
    "qs:woe_adm0":23424848,
    "qs:woe_adm1":2345758,
    "qs:woe_adm2":12586705,
    "qs:woe_lau":0,
    "qs:woe_local":2295373,
    "qs:woe_ver":"7.10.0",
    "wof:lang":[
        "eng"
    ],
    "wof:name":"Veerapandianpattinam",
    "wof:placetype":"neighbourhood"
},
  "geometry": {"coordinates":[78.119812,8.491388],"type":"Point"}
}