{
  "type": "Feature",
  "properties": {
    "iso:country":"IN",
    "name:eng_x_preferred":[
        "Veerapandianpattinam"
    ],
    "name:unk_x_variant":[
        "Veerapandianpattinam"
    ],
    "qs:gn_adm0_cc":"IN",
    "qs:gn_local":1254390,
    "qs:gn_nam_loc":"puliyangudi",
    "qs:gn_namadm1":"25",
    "qs:local_max":18,
    "qs:local_sum":18,
    "qs:localhoods":1,
    "qs:name":"Veerapandianpattinam",
    "qs:name_adm0":"India",
    "qs:name_adm1":"Tamil Nadu",
    "qs:name_adm2":"Thoothukkudi",
    "qs:name_local":"Tiruchendur",
    "qs:photo_max":12,
    "qs:photo_sum":18,
    "qs:placetype":"Suburb",
    "qs:quad_count":4,
    "qs:woe_adm0":23424848,
    "qs:woe_adm1":2345758,
    "qs:woe_adm2":12586705,
    "qs:woe_lau":0,
    "qs:woe_local":2295373,
    "qs:woe_ver":"7.10.0",
    "wof:lang":[
        "eng"
    ],
    "wof:name":"Veerapandianpattinam",
    "wof:placetype":"neighbourhood"
},
  "geometry": {"coordinates":[78.119812,8.491388],"type":"Point"}
}