{
  "type": "Feature",
  "properties": {
    "iso:country":"IN",
    "ks:ks_name":"Baniagan",
    "ks:ks_pop":373,
    "ks:ks_type":"VILLAGE",
    "name:eng_x_preferred":[
        "Baniagan"
    ],
    "wof:name":"Baniagan",
    "wof:placetype":"locality",
    "wof:population":373
},
  "geometry": {"coordinates":[86.524429,21.531074],"type":"Point"}
}