{
  "type": "Feature",
  "properties": {
    "gn:admin1_code":"12.0",
    "gn:admin2_code":"1.0",
    "gn:asciiname":"Alchazab",
    "gn:country_code":"IN",
    "gn:dem":1742,
    "gn:feature_class":"P",
    "gn:feature_code":"PPL",
    "gn:name":"Alchazab",
    "gn:population":0,
    "gn:timezone":"Asia/Kolkata",
    "iso:country":"IN",
    "wof:name":"Alchazab",
    "wof:placetype":"locality"
},
  "geometry": {"coordinates":[74.18875,34.54461],"type":"Point"}
}