{
  "type": "Feature",
  "properties": {
    "gn:admin1_code":"37.0",
    "gn:admin2_code":"409.0",
    "gn:asciiname":"Agesara",
    "gn:country_code":"IN",
    "gn:dem":310,
    "gn:feature_class":"P",
    "gn:feature_code":"PPL",
    "gn:name":"\u0100gesara",
    "gn:population":0,
    "gn:timezone":"Asia/Kolkata",
    "iso:country":"IN",
    "wof:name":"Agesara",
    "wof:placetype":"locality"
},
  "geometry": {"coordinates":[81.44922,20.85797],"type":"Point"}
}