{
  "type": "Feature",
  "properties": {
    "gn:admin1_code":"19.0",
    "gn:admin2_code":"563.0",
    "gn:asciiname":"Jaglemane",
    "gn:country_code":"IN",
    "gn:dem":553,
    "gn:feature_class":"P",
    "gn:feature_code":"PPL",
    "gn:name":"Jaglemane",
    "gn:population":0,
    "gn:timezone":"Asia/Kolkata",
    "iso:country":"IN",
    "ks:ks_name":"Jagalemane",
    "ks:ks_pop":29,
    "ks:ks_type":"HABITATION",
    "name:eng_x_preferred":[
        "Jagalemane"
    ],
    "name:eng_x_variant":[
        "Jaglemane"
    ],
    "wof:name":"Jagalemane",
    "wof:placetype":"locality",
    "wof:population":29
},
  "geometry": {"coordinates":[74.73069599999999,14.624103],"type":"Point"}
}