{
  "type": "Feature",
  "properties": {
    "gn:admin1_code":"23.0",
    "gn:admin2_code":"51.0",
    "gn:asciiname":"Chhoti Relon",
    "gn:country_code":"IN",
    "gn:dem":275,
    "gn:feature_class":"P",
    "gn:feature_code":"PPL",
    "gn:name":"Chhoti Relon",
    "gn:population":0,
    "gn:timezone":"Asia/Kolkata",
    "iso:country":"IN",
    "ks:ks_name":"Chhoti Relon",
    "ks:ks_type":"VILLAGE",
    "name:eng_x_preferred":[
        "Chhoti Relon"
    ],
    "wof:name":"Chhoti Relon",
    "wof:placetype":"locality"
},
  "geometry": {"coordinates":[76.528026,30.935014],"type":"Point"}
}