{
  "type": "Feature",
  "properties": {
    "iso:country":"IN",
    "ks:ks_alt_nam":"Kotalp\u0101r",
    "ks:ks_name":"Kotalpar",
    "ks:ks_type":"VILLAGE",
    "name:eng_x_preferred":[
        "Kotalpar"
    ],
    "name:eng_x_variant":[
        "Kotalp\u0101r"
    ],
    "wof:name":"Kotalpar",
    "wof:placetype":"locality"
},
  "geometry": {"coordinates":[79.77055799999999,20.436394],"type":"Point"}
}