{
  "type": "Feature",
  "properties": {
    "iso:country":"IN",
    "ks:ks_name":"Chetia Gaon",
    "ks:ks_pop":310,
    "ks:ks_type":"VILLAGE",
    "ks:ks_uagg_main":0,
    "name:eng_x_preferred":[
        "Chetia Gaon"
    ],
    "wof:name":"Chetia Gaon",
    "wof:placetype":"neighbourhood",
    "wof:population":310
},
  "geometry": {"coordinates":[94.809997,27.25712],"type":"Point"}
}