{
  "type": "Feature",
  "properties": {
    "gn:admin1_code":"34",
    "gn:admin2_code":"210.0",
    "gn:asciiname":"Sontha",
    "gn:country_code":"IN",
    "gn:dem":53,
    "gn:feature_class":"P",
    "gn:feature_code":"PPL",
    "gn:name":"Sontha",
    "gn:population":0,
    "gn:timezone":"Asia/Kolkata",
    "iso:country":"IN",
    "wof:name":"Sontha",
    "wof:placetype":"locality"
},
  "geometry": {"coordinates":[87.77663000000003,26.18611],"type":"Point"}
}