{
  "type": "Feature",
  "properties": {
    "gn:admin1_code":"36",
    "gn:admin2_code":"188.0",
    "gn:asciiname":"Gathuakhor",
    "gn:country_code":"IN",
    "gn:dem":84,
    "gn:feature_class":"P",
    "gn:feature_code":"PPL",
    "gn:name":"Gathu\u0101khor",
    "gn:population":0,
    "gn:timezone":"Asia/Kolkata",
    "iso:country":"IN",
    "ks:ks_alt_nam":"Gathu\u0101khor",
    "ks:ks_name":"Gathuakhor",
    "ks:ks_type":"VILLAGE",
    "ks:ks_uagg_main":0,
    "name:eng_x_preferred":[
        "Gathuakhor"
    ],
    "name:eng_x_variant":[
        "Gathu\u0101khor"
    ],
    "wof:name":"Gathuakhor",
    "wof:placetype":"neighbourhood"
},
  "geometry": {"coordinates":[83.192527,26.695075],"type":"Point"}
}