{
  "type": "Feature",
  "properties": {
    "iso:country":"IN",
    "ks:ks_name":"Jhaankarbadhali",
    "ks:ks_pop":299,
    "ks:ks_type":"HABITATION",
    "name:eng_x_preferred":[
        "Jhaankarbadhali"
    ],
    "wof:name":"Jhaankarbadhali",
    "wof:placetype":"locality",
    "wof:population":299
},
  "geometry": {"coordinates":[83.988373,21.347443],"type":"Point"}
}