{
  "type": "Feature",
  "properties": {
    "iso:country":"IN",
    "ks:ks_name":"Gaul Thakral",
    "ks:ks_pop":128,
    "ks:ks_type":"HABITATION",
    "name:eng_x_preferred":[
        "Gaul Thakral"
    ],
    "wof:name":"Gaul Thakral",
    "wof:placetype":"locality",
    "wof:population":128
},
  "geometry": {"coordinates":[78.265412,30.851046],"type":"Point"}
}