{
  "type": "Feature",
  "properties": {
    "gn:admin1_code":"40",
    "gn:admin2_code":"541.0",
    "gn:asciiname":"Chinampeta",
    "gn:country_code":"IN",
    "gn:dem":55,
    "gn:feature_class":"P",
    "gn:feature_code":"PPL",
    "gn:name":"Chinampeta",
    "gn:population":0,
    "gn:timezone":"Asia/Kolkata",
    "iso:country":"IN",
    "ks:ks_name":"Chennampeta",
    "ks:ks_pop":257,
    "ks:ks_type":"HABITATION",
    "name:eng_x_preferred":[
        "Chennampeta"
    ],
    "name:eng_x_variant":[
        "Chinampeta"
    ],
    "wof:name":"Chennampeta",
    "wof:placetype":"locality",
    "wof:population":257
},
  "geometry": {"coordinates":[80.90960800000001,17.709327],"type":"Point"}
}