{
  "type": "Feature",
  "properties": {
    "iso:country":"IN",
    "ks:ks_name":"Atraila",
    "ks:ks_pop":82,
    "ks:ks_type":"HABITATION",
    "name:eng_x_preferred":[
        "Atraila"
    ],
    "wof:name":"Atraila",
    "wof:placetype":"locality",
    "wof:population":82
},
  "geometry": {"coordinates":[81.840469,24.650413],"type":"Point"}
}