{
  "type": "Feature",
  "properties": {
    "iso:country":"IN",
    "ks:ks_name":"Noniya",
    "ks:ks_pop":298,
    "ks:ks_type":"VILLAGE",
    "ks:ks_uagg_main":0,
    "name:eng_x_preferred":[
        "Noniya"
    ],
    "wof:name":"Noniya",
    "wof:placetype":"neighbourhood",
    "wof:population":298
},
  "geometry": {"coordinates":[87.021717,24.525719],"type":"Point"}
}