{
  "type": "Feature",
  "properties": {
    "iso:country":"IN",
    "ks:ks_name":"Bankata",
    "ks:ks_pop":258,
    "ks:ks_type":"VILLAGE",
    "name:eng_x_preferred":[
        "Bankata"
    ],
    "wof:name":"Bankata",
    "wof:placetype":"locality",
    "wof:population":258
},
  "geometry": {"coordinates":[87.139281,23.874444],"type":"Point"}
}