{
  "type": "Feature",
  "properties": {
    "iso:country":"IN",
    "ks:ks_name":"Aathupatti",
    "ks:ks_pop":100,
    "ks:ks_type":"HABITATION",
    "name:eng_x_preferred":[
        "Aathupatti"
    ],
    "wof:name":"Aathupatti",
    "wof:placetype":"locality",
    "wof:population":100
},
  "geometry": {"coordinates":[78.586398,10.581543],"type":"Point"}
}