{
  "type": "Feature",
  "properties": {
    "iso:country":"IN",
    "ks:ks_alt_nam":"DUDHAL WASTI",
    "ks:ks_name":"Dudhal Wasti",
    "ks:ks_pop":76,
    "ks:ks_type":"HABITATION",
    "name:eng_x_preferred":[
        "Dudhal Wasti"
    ],
    "wof:name":"Dudhal Wasti",
    "wof:placetype":"locality",
    "wof:population":76
},
  "geometry": {"coordinates":[75.025826,17.07713],"type":"Point"}
}