{
  "type": "Feature",
  "properties": {
    "gn:admin1_code":"2.0",
    "gn:admin2_code":"543.0",
    "gn:asciiname":"Smartula Chintalavalasa",
    "gn:country_code":"IN",
    "gn:dem":152,
    "gn:feature_class":"P",
    "gn:feature_code":"PPL",
    "gn:name":"Sm\u0101rtula Chintalavalasa",
    "gn:population":0,
    "gn:timezone":"Asia/Kolkata",
    "iso:country":"IN",
    "wof:name":"Smartula Chintalavalasa",
    "wof:placetype":"locality"
},
  "geometry": {"coordinates":[83.29523,18.4938],"type":"Point"}
}