{
  "type": "Feature",
  "properties": {
    "gn:admin1_code":"19.0",
    "gn:admin2_code":"581.0",
    "gn:asciiname":"Dinnur",
    "gn:country_code":"IN",
    "gn:dem":833,
    "gn:feature_class":"P",
    "gn:feature_code":"PPL",
    "gn:name":"Dinn\u016br",
    "gn:population":0,
    "gn:timezone":"Asia/Kolkata",
    "iso:country":"IN",
    "wof:name":"Dinnur",
    "wof:placetype":"locality"
},
  "geometry": {"coordinates":[78.06192,12.92973],"type":"Point"}
}