{
  "type": "Feature",
  "properties": {
    "gn:admin1_code":"39",
    "gn:admin2_code":"59.0",
    "gn:asciiname":"Thati Kathur",
    "gn:country_code":"IN",
    "gn:dem":1345,
    "gn:feature_class":"P",
    "gn:feature_code":"PPL",
    "gn:name":"Th\u0101ti Kath\u016br",
    "gn:population":0,
    "gn:timezone":"Asia/Kolkata",
    "iso:country":"IN",
    "name:und_x_variant":[
        "Kathur",
        "Th\u0101ti Kath\u016br"
    ],
    "wof:name":"Thati Kathur",
    "wof:placetype":"neighbourhood"
},
  "geometry": {"coordinates":[78.64812000000001,30.57893],"type":"Point"}
}