{
  "type": "Feature",
  "properties": {
    "gn:admin1_code":"36",
    "gn:admin2_code":"161.0",
    "gn:asciiname":"Saramau",
    "gn:country_code":"IN",
    "gn:dem":142,
    "gn:feature_class":"P",
    "gn:feature_code":"PPL",
    "gn:name":"Saramau",
    "gn:population":0,
    "gn:timezone":"Asia/Kolkata",
    "iso:country":"IN",
    "ks:ks_name":"Saramai",
    "ks:ks_pop":630,
    "ks:ks_type":"VILLAGE",
    "name:eng_x_preferred":[
        "Saramai"
    ],
    "name:eng_x_variant":[
        "Saramau"
    ],
    "wof:name":"Saramai",
    "wof:placetype":"locality",
    "wof:population":630
},
  "geometry": {"coordinates":[78.790881,26.888068],"type":"Point"}
}