{
  "type": "Feature",
  "properties": {
    "iso:country":"IN",
    "ks:ks_alt_nam":"BIBISHET",
    "ks:ks_name":"Bibishet",
    "ks:ks_pop":50,
    "ks:ks_type":"HABITATION",
    "name:eng_x_preferred":[
        "Bibishet"
    ],
    "wof:name":"Bibishet",
    "wof:placetype":"locality",
    "wof:population":50
},
  "geometry": {"coordinates":[74.66424499999999,17.200597],"type":"Point"}
}