{
  "type": "Feature",
  "properties": {
    "gn:admin1_code":"39",
    "gn:admin2_code":"60.0",
    "gn:asciiname":"Purtar",
    "gn:country_code":"IN",
    "gn:dem":1543,
    "gn:feature_class":"P",
    "gn:feature_code":"PPL",
    "gn:name":"Purtar",
    "gn:population":0,
    "gn:timezone":"Asia/Kolkata",
    "iso:country":"IN",
    "ks:ks_name":"Purtad",
    "ks:ks_pop":373,
    "ks:ks_type":"VILLAGE",
    "name:eng_x_preferred":[
        "Purtad"
    ],
    "name:eng_x_variant":[
        "Purtar"
    ],
    "wof:name":"Purtad",
    "wof:placetype":"locality",
    "wof:population":373
},
  "geometry": {"coordinates":[77.92809800000001,30.914505],"type":"Point"}
}