{
  "type": "Feature",
  "properties": {
    "iso:country":"IN",
    "ks:ks_name":"Deogaon",
    "ks:ks_pop":181,
    "ks:ks_type":"VILLAGE",
    "ks:ks_uagg_main":0,
    "name:eng_x_preferred":[
        "Deogaon"
    ],
    "wof:name":"Deogaon",
    "wof:placetype":"neighbourhood",
    "wof:population":181
},
  "geometry": {"coordinates":[85.81393799999999,21.767755],"type":"Point"}
}