{
  "type": "Feature",
  "properties": {
    "iso:country":"IN",
    "ks:ks_alt_nam":"dongi",
    "ks:ks_name":"Dongi",
    "ks:ks_pop":679,
    "ks:ks_type":"HABITATION",
    "name:eng_x_preferred":[
        "Dongi"
    ],
    "wof:name":"Dongi",
    "wof:placetype":"locality",
    "wof:population":679
},
  "geometry": {"coordinates":[86.637908,24.363134],"type":"Point"}
}