{
  "type": "Feature",
  "properties": {
    "iso:country":"IN",
    "ks:ks_name":"Kelannagar",
    "ks:ks_pop":991,
    "ks:ks_type":"HABITATION",
    "name:eng_x_preferred":[
        "Kelannagar"
    ],
    "wof:name":"Kelannagar",
    "wof:placetype":"locality",
    "wof:population":991
},
  "geometry": {"coordinates":[72.092389,26.959797],"type":"Point"}
}