{
  "type": "Feature",
  "properties": {
    "iso:country":"IN",
    "ks:ks_name":"Varandewadi",
    "ks:ks_pop":17,
    "ks:ks_type":"HABITATION",
    "name:eng_x_preferred":[
        "Varandewadi"
    ],
    "wof:name":"Varandewadi",
    "wof:placetype":"locality",
    "wof:population":17
},
  "geometry": {"coordinates":[74.04237500000001,15.912959],"type":"Point"}
}