{
  "type": "Feature",
  "properties": {
    "gn:admin1_code":"36",
    "gn:admin2_code":"201.0",
    "gn:asciiname":"Babarpur",
    "gn:country_code":"IN",
    "gn:dem":172,
    "gn:feature_class":"P",
    "gn:feature_code":"PPL",
    "gn:name":"B\u0101barpur",
    "gn:population":0,
    "gn:timezone":"Asia/Kolkata",
    "iso:country":"IN",
    "name:urd_x_preferred":[
        "\u0628\u0627\u0628\u0631 \u067e\u0648\u0631"
    ],
    "wof:name":"Babarpur",
    "wof:placetype":"locality"
},
  "geometry": {"coordinates":[78.72414999999999,27.57028],"type":"Point"}
}