{
  "type": "Feature",
  "properties": {
    "gn:admin1_code":"10.0",
    "gn:admin2_code":"074",
    "gn:asciiname":"Bhadson",
    "gn:country_code":"IN",
    "gn:dem":262,
    "gn:feature_class":"P",
    "gn:feature_code":"PPL",
    "gn:name":"Bh\u0101dson",
    "gn:population":0,
    "gn:timezone":"Asia/Kolkata",
    "iso:country":"IN",
    "name:pan_x_preferred":[
        "\u0a2d\u0a3e\u0a26\u0a38\u0a4b\u0a02"
    ],
    "wof:name":"Bhadson",
    "wof:placetype":"locality"
},
  "geometry": {"coordinates":[76.96977,29.91885],"type":"Point"}
}