{
  "type": "Feature",
  "properties": {
    "iso:country":"IN",
    "ks:ks_name":"Tatakpara",
    "ks:ks_pop":113,
    "ks:ks_type":"VILLAGE",
    "name:eng_x_preferred":[
        "Tatakpara"
    ],
    "wof:name":"Tatakpara",
    "wof:placetype":"locality",
    "wof:population":113
},
  "geometry": {"coordinates":[87.401527,24.666864],"type":"Point"}
}