{
  "type": "Feature",
  "properties": {
    "gn:admin1_code":"18",
    "gn:admin2_code":"299.0",
    "gn:asciiname":"Pdengshakap",
    "gn:country_code":"IN",
    "gn:dem":808,
    "gn:feature_class":"P",
    "gn:feature_code":"PPL",
    "gn:name":"Pdengshakap",
    "gn:population":0,
    "gn:timezone":"Asia/Kolkata",
    "iso:country":"IN",
    "wof:name":"Pdengshakap",
    "wof:placetype":"locality"
},
  "geometry": {"coordinates":[92.14764,25.23288],"type":"Point"}
}