{
  "type": "Feature",
  "properties": {
    "iso:country":"IN",
    "ks:ks_name":"Husmu",
    "ks:ks_pop":230,
    "ks:ks_type":"VILLAGE",
    "name:eng_x_preferred":[
        "Husmu"
    ],
    "wof:name":"Husmu",
    "wof:placetype":"locality",
    "wof:population":230
},
  "geometry": {"coordinates":[84.22227100000001,23.403159],"type":"Point"}
}