{
  "type": "Feature",
  "properties": {
    "iso:country":"IN",
    "ks:ks_name":"Andalupara",
    "ks:ks_pop":322,
    "ks:ks_type":"HABITATION",
    "ks:ks_uagg_main":0,
    "name:eng_x_preferred":[
        "Andalupara"
    ],
    "wof:name":"Andalupara",
    "wof:placetype":"locality",
    "wof:population":322
},
  "geometry": {"coordinates":[91.475937,26.102257],"type":"Point"}
}