{
  "type": "Feature",
  "properties": {
    "gn:admin1_code":"36.0",
    "gn:admin2_code":"189.0",
    "gn:asciiname":"Sapahi",
    "gn:country_code":"IN",
    "gn:dem":82,
    "gn:feature_class":"P",
    "gn:feature_code":"PPL",
    "gn:name":"Sap\u0101hi",
    "gn:population":0,
    "gn:timezone":"Asia/Kolkata",
    "iso:country":"IN",
    "name:fra_x_preferred":[
        "Sapahi"
    ],
    "name:new_x_preferred":[
        "\u0938\u092a\u0939\u0940"
    ],
    "name:pol_x_preferred":[
        "Sapahi"
    ],
    "wof:name":"Sapahi",
    "wof:placetype":"locality"
},
  "geometry": {"coordinates":[84.1113,26.72901],"type":"Point"}
}