{
  "type": "Feature",
  "properties": {
    "gn:admin1_code":"36",
    "gn:admin2_code":"191.0",
    "gn:asciiname":"Tayabpur",
    "gn:country_code":"IN",
    "gn:dem":78,
    "gn:feature_class":"P",
    "gn:feature_code":"PPL",
    "gn:name":"Tay\u0101bpur",
    "gn:population":0,
    "gn:timezone":"Asia/Kolkata",
    "iso:country":"IN",
    "ks:ks_alt_nam":"Tay\u0101bpur",
    "ks:ks_name":"Tayabpur",
    "ks:ks_type":"VILLAGE",
    "ks:ks_uagg_main":0,
    "name:eng_x_preferred":[
        "Tayabpur"
    ],
    "name:eng_x_variant":[
        "Tay\u0101bpur"
    ],
    "wof:name":"Tayabpur",
    "wof:placetype":"neighbourhood"
},
  "geometry": {"coordinates":[83.244187,25.913327],"type":"Point"}
}