{
  "type": "Feature",
  "properties": {
    "gn:admin1_code":"13.0",
    "gn:admin2_code":"599.0",
    "gn:asciiname":"Peringanad",
    "gn:country_code":"IN",
    "gn:dem":49,
    "gn:feature_class":"P",
    "gn:feature_code":"PPL",
    "gn:name":"Peringan\u0101d",
    "gn:population":0,
    "gn:timezone":"Asia/Kolkata",
    "iso:country":"IN",
    "ks:ks_alt_nam":"Peringan\u0101d",
    "ks:ks_name":"Peringanad",
    "ks:ks_pop":20785,
    "ks:ks_type":"VILLAGE",
    "name:eng_x_preferred":[
        "Peringanad"
    ],
    "name:eng_x_variant":[
        "Peringan\u0101d"
    ],
    "wof:name":"Peringanad",
    "wof:placetype":"locality",
    "wof:population":20785
},
  "geometry": {"coordinates":[76.70941500000001,9.14962],"type":"Point"}
}