{
  "type": "Feature",
  "properties": {
    "iso:country":"IN",
    "ks:ks_name":"Sahba Chak",
    "ks:ks_pop":891,
    "ks:ks_type":"VILLAGE",
    "ks:ks_uagg_main":0,
    "name:eng_x_preferred":[
        "Sahba Chak"
    ],
    "wof:name":"Sahba Chak",
    "wof:placetype":"locality",
    "wof:population":891
},
  "geometry": {"coordinates":[84.42379200000001,26.293806],"type":"Point"}
}