{
  "type": "Feature",
  "properties": {
    "iso:country":"IN",
    "ks:ks_name":"Brahmalang",
    "ks:ks_pop":227,
    "ks:ks_type":"VILLAGE",
    "ks:ks_uagg_main":0,
    "name:eng_x_preferred":[
        "Brahmalang"
    ],
    "wof:name":"Brahmalang",
    "wof:placetype":"neighbourhood",
    "wof:population":227
},
  "geometry": {"coordinates":[85.797945,20.086944],"type":"Point"}
}