{
  "type": "Feature",
  "properties": {
    "gn:admin1_code":"36.0",
    "gn:admin2_code":"146.0",
    "gn:asciiname":"Tantpur",
    "gn:country_code":"IN",
    "gn:dem":220,
    "gn:feature_class":"P",
    "gn:feature_code":"PPL",
    "gn:name":"T\u0101ntpur",
    "gn:population":0,
    "gn:timezone":"Asia/Kolkata",
    "iso:country":"IN",
    "name:msa_x_preferred":[
        "Tantpur"
    ],
    "wof:name":"Tantpur",
    "wof:placetype":"locality"
},
  "geometry": {"coordinates":[77.46529,26.83371],"type":"Point"}
}