{
  "type": "Feature",
  "properties": {
    "gn:admin1_code":"23.0",
    "gn:admin2_code":"43.0",
    "gn:asciiname":"Mammun Khera Jadid",
    "gn:country_code":"IN",
    "gn:dem":187,
    "gn:feature_class":"P",
    "gn:feature_code":"PPL",
    "gn:name":"Mammun Khera Jad\u012bd",
    "gn:population":0,
    "gn:timezone":"Asia/Kolkata",
    "iso:country":"IN",
    "name:und_x_variant":[
        "Mammun Khera Jad\u012bd",
        "Khatw\u0101n"
    ],
    "wof:name":"Mammun Khera Jadid",
    "wof:placetype":"locality"
},
  "geometry": {"coordinates":[74.18434000000001,30.28337],"type":"Point"}
}