{
  "type": "Feature",
  "properties": {
    "gn:admin1_code":"35",
    "gn:admin2_code":"463.0",
    "gn:asciiname":"Rampurwan",
    "gn:country_code":"IN",
    "gn:dem":395,
    "gn:feature_class":"P",
    "gn:feature_code":"PPL",
    "gn:name":"Rampurw\u0101n",
    "gn:population":0,
    "gn:timezone":"Asia/Kolkata",
    "iso:country":"IN",
    "wof:name":"Rampurwan",
    "wof:placetype":"locality"
},
  "geometry": {"coordinates":[82.53352,24.20256],"type":"Point"}
}