{
  "type": "Feature",
  "properties": {
    "iso:country":"IN",
    "ks:ks_name":"Naraharipur",
    "ks:ks_pop":1668,
    "ks:ks_type":"VILLAGE",
    "ks:ks_uagg_main":0,
    "name:eng_x_preferred":[
        "Naraharipur"
    ],
    "wof:name":"Naraharipur",
    "wof:placetype":"locality",
    "wof:population":1668
},
  "geometry": {"coordinates":[88.857083,23.045026],"type":"Point"}
}