{
  "type": "Feature",
  "properties": {
    "iso:country":"IN",
    "ks:ks_name":"Sonai Nepali",
    "ks:ks_pop":1514,
    "ks:ks_type":"VILLAGE",
    "ks:ks_uagg_main":0,
    "name:eng_x_preferred":[
        "Sonai Nepali"
    ],
    "wof:name":"Sonai Nepali",
    "wof:placetype":"neighbourhood",
    "wof:population":1514
},
  "geometry": {"coordinates":[92.82032,26.886126],"type":"Point"}
}