{
  "type": "Feature",
  "properties": {
    "iso:country":"IN",
    "ks:ks_name":"Kemmanna Hore",
    "ks:ks_pop":64,
    "ks:ks_type":"HABITATION",
    "name:eng_x_preferred":[
        "Kemmanna Hore"
    ],
    "wof:name":"Kemmanna Hore",
    "wof:placetype":"locality",
    "wof:population":64
},
  "geometry": {"coordinates":[74.43889900000001,14.417956],"type":"Point"}
}