{
  "type": "Feature",
  "properties": {
    "iso:country":"IN",
    "ks:ks_name":"Mandagadde",
    "ks:ks_pop":6,
    "ks:ks_type":"HABITATION",
    "name:eng_x_preferred":[
        "Mandagadde"
    ],
    "wof:name":"Mandagadde",
    "wof:placetype":"locality",
    "wof:population":6
},
  "geometry": {"coordinates":[74.76940999999999,13.970272],"type":"Point"}
}