{
  "type": "Feature",
  "properties": {
    "gn:admin1_code":"21",
    "gn:admin2_code":"398.0",
    "gn:asciiname":"Raniguda",
    "gn:country_code":"IN",
    "gn:dem":621,
    "gn:feature_class":"P",
    "gn:feature_code":"PPL",
    "gn:name":"R\u0101niguda",
    "gn:population":0,
    "gn:timezone":"Asia/Kolkata",
    "iso:country":"IN",
    "ks:ks_name":"Ranigada",
    "ks:ks_pop":580,
    "ks:ks_type":"VILLAGE",
    "name:eng_x_preferred":[
        "Ranigada"
    ],
    "name:eng_x_variant":[
        "Raniguda"
    ],
    "name:und_x_variant":[
        "R\u0101nig\u016bda",
        "R\u0101n\u012bgurha",
        "R\u0101niguda"
    ],
    "wof:name":"Ranigada",
    "wof:placetype":"locality",
    "wof:population":580
},
  "geometry": {"coordinates":[82.67428,18.945717],"type":"Point"}
}