{
  "type": "Feature",
  "properties": {
    "gn:admin1_code":"21",
    "gn:admin2_code":"398.0",
    "gn:asciiname":"Raniguda",
    "gn:country_code":"IN",
    "gn:dem":621,
    "gn:feature_class":"P",
    "gn:feature_code":"PPL",
    "gn:name":"R\u0101niguda",
    "gn:population":0,
    "gn:timezone":"Asia/Kolkata",
    "iso:country":"IN",
    "name:und_x_variant":[
        "R\u0101nig\u016bda",
        "R\u0101n\u012bgurha",
        "R\u0101niguda"
    ],
    "wof:name":"Raniguda",
    "wof:placetype":"locality"
},
  "geometry": {"coordinates":[82.67447,18.94524],"type":"Point"}
}