{
  "type": "Feature",
  "properties": {
    "iso:country":"IN",
    "ks:ks_alt_nam":"darauna",
    "ks:ks_name":"Darauna",
    "ks:ks_pop":606,
    "ks:ks_type":"HABITATION",
    "name:eng_x_preferred":[
        "Darauna"
    ],
    "wof:name":"Darauna",
    "wof:placetype":"locality",
    "wof:population":606
},
  "geometry": {"coordinates":[81.445898,27.366082],"type":"Point"}
}