{
  "type": "Feature",
  "properties": {
    "gn:country":"IN",
    "gn:fcode":"PPL",
    "gn:population":18498,
    "iso:country":"IN",
    "name:ben_x_preferred":[
        "\u0996\u09bf\u09a1\u09bc\u0995\u09bf\u09af\u09bc\u09be"
    ],
    "name:bpy_x_preferred":[
        "\u0996\u09bf\u09a1\u09bc\u0995\u09bf\u09af\u09bc\u09be"
    ],
    "name:ceb_x_preferred":[
        "Khirki\u0101n"
    ],
    "name:eng_x_preferred":[
        "Khirkiya"
    ],
    "name:fra_x_preferred":[
        "Khirkiya"
    ],
    "name:ita_x_preferred":[
        "Khirkiya"
    ],
    "name:mlg_x_preferred":[
        "Khirkiya"
    ],
    "name:msa_x_preferred":[
        "Khirkiya"
    ],
    "name:nan_x_preferred":[
        "Khirkiya"
    ],
    "name:new_x_preferred":[
        "\u0916\u093f\u0930\u094d\u0915\u093f\u092f\u093e"
    ],
    "name:nld_x_preferred":[
        "Khirkiya"
    ],
    "name:por_x_preferred":[
        "Khirkiya"
    ],
    "name:swe_x_preferred":[
        "Khirki\u0101n"
    ],
    "name:vie_x_preferred":[
        "Khirkiya"
    ],
    "name:zho_x_preferred":[
        "\u57fa\u5c14\u57fa\u8036"
    ],
    "qs:name":"Khirki\u0101n",
    "qs:photos_9r":0,
    "qs:photos_sr":0,
    "qs:pop_sr":"6",
    "wof:name":"Khirki\u0101n",
    "wof:placetype":"locality",
    "wof:population":18498
},
  "geometry": {"coordinates":[76.8601,22.16749],"type":"Point"}
}