{
  "type": "Feature",
  "properties": {
    "iso:country":"IN",
    "ks:ks_name":"Chechrakuri",
    "ks:ks_pop":161,
    "ks:ks_type":"VILLAGE",
    "ks:ks_uagg_main":0,
    "name:eng_x_preferred":[
        "Chechrakuri"
    ],
    "wof:name":"Chechrakuri",
    "wof:placetype":"neighbourhood",
    "wof:population":161
},
  "geometry": {"coordinates":[88.648437,25.225919],"type":"Point"}
}