{
  "type": "Feature",
  "properties": {
    "iso:country":"IN",
    "ks:ks_name":"Hatpalewadi",
    "ks:ks_pop":115,
    "ks:ks_type":"HABITATION",
    "name:eng_x_preferred":[
        "Hatpalewadi"
    ],
    "wof:name":"Hatpalewadi",
    "wof:placetype":"locality",
    "wof:population":115
},
  "geometry": {"coordinates":[73.534252,16.98249],"type":"Point"}
}