{
  "type": "Feature",
  "properties": {
    "iso:country":"IN",
    "ks:ks_name":"Thathankuppam",
    "ks:ks_pop":275,
    "ks:ks_type":"HABITATION",
    "ks:ks_uagg_main":0,
    "name:eng_x_preferred":[
        "Thathankuppam"
    ],
    "wof:name":"Thathankuppam",
    "wof:placetype":"neighbourhood",
    "wof:population":275
},
  "geometry": {"coordinates":[79.69575399999999,11.624851],"type":"Point"}
}