{
  "type": "Feature",
  "properties": {
    "iso:country":"IN",
    "ks:ks_name":"Khati Bor",
    "ks:ks_pop":300,
    "ks:ks_type":"HABITATION",
    "name:eng_x_preferred":[
        "Khati Bor"
    ],
    "wof:name":"Khati Bor",
    "wof:placetype":"locality",
    "wof:population":300
},
  "geometry": {"coordinates":[73.740067,24.202569],"type":"Point"}
}