{
  "type": "Feature",
  "properties": {
    "iso:country":"IN",
    "ks:ks_name":"Bara",
    "ks:ks_pop":1135,
    "ks:ks_type":"VILLAGE",
    "ks:ks_uagg_main":0,
    "name:eng_x_preferred":[
        "Bara"
    ],
    "wof:name":"Bara",
    "wof:placetype":"neighbourhood",
    "wof:population":1135
},
  "geometry": {"coordinates":[86.775316,24.247582],"type":"Point"}
}