{
  "type": "Feature",
  "properties": {
    "gn:admin1_code":"12.0",
    "gn:admin2_code":"7.0",
    "gn:asciiname":"Tarkhane de Ghar",
    "gn:country_code":"IN",
    "gn:dem":396,
    "gn:feature_class":"P",
    "gn:feature_code":"PPL",
    "gn:name":"Tarkhane de Ghar",
    "gn:population":0,
    "gn:timezone":"Asia/Kolkata",
    "iso:country":"IN",
    "wof:name":"Tarkhane de Ghar",
    "wof:placetype":"locality"
},
  "geometry": {"coordinates":[75.55041999999997,32.39999],"type":"Point"}
}