{
  "type": "Feature",
  "properties": {
    "iso:country":"IN",
    "ks:ks_alt_nam":"EAST TOLA",
    "ks:ks_name":"East Tola",
    "ks:ks_pop":449,
    "ks:ks_type":"HABITATION",
    "name:eng_x_preferred":[
        "East Tola"
    ],
    "wof:name":"East Tola",
    "wof:placetype":"locality",
    "wof:population":449
},
  "geometry": {"coordinates":[84.93326999999999,25.899611],"type":"Point"}
}