{
  "type": "Feature",
  "properties": {
    "iso:country":"IN",
    "ks:ks_name":"Kharkatwa",
    "ks:ks_type":"VILLAGE",
    "name:eng_x_preferred":[
        "Kharkatwa"
    ],
    "wof:name":"Kharkatwa",
    "wof:placetype":"locality"
},
  "geometry": {"coordinates":[84.374197,27.105661],"type":"Point"}
}