{
  "type": "Feature",
  "properties": {
    "gn:country":"IN",
    "gn:fcode":"PPL",
    "gn:pop":11874,
    "iso:country":"IN",
    "qs:name":"Umrala",
    "qs:name_adm0":"India",
    "qs:name_adm1":"Gujarat",
    "qs:photos_9r":0,
    "qs:photos_sr":0,
    "qs:placetype":"Town",
    "qs:pop_sr":"6",
    "wof:name":"Umrala",
    "wof:placetype":"locality",
    "wof:population":11874
},
  "geometry": {"coordinates":[71.80305,21.84353],"type":"Point"}
}