{
  "type": "Feature",
  "properties": {
    "iso:country":"IN",
    "ks:ks_alt_nam":"Kasarua muslim suba",
    "ks:ks_name":"Kasarua Muslim Suba",
    "ks:ks_pop":412,
    "ks:ks_type":"HABITATION",
    "ks:ks_uagg_main":0,
    "name:eng_x_preferred":[
        "Kasarua Muslim Suba"
    ],
    "wof:name":"Kasarua Muslim Suba",
    "wof:placetype":"neighbourhood",
    "wof:population":412
},
  "geometry": {"coordinates":[91.63598399999999,26.362764],"type":"Point"}
}