{
  "type": "Feature",
  "properties": {
    "iso:country":"IN",
    "ks:ks_name":"Kuniya Kalan",
    "ks:ks_pop":804,
    "ks:ks_type":"VILLAGE",
    "name:eng_x_preferred":[
        "Kuniya Kalan"
    ],
    "wof:name":"Kuniya Kalan",
    "wof:placetype":"locality",
    "wof:population":804
},
  "geometry": {"coordinates":[83.301627,22.954173],"type":"Point"}
}