{
  "type": "Feature",
  "properties": {
    "iso:country":"IN",
    "ks:ks_name":"Belpara",
    "ks:ks_pop":198,
    "ks:ks_type":"HABITATION",
    "name:eng_x_preferred":[
        "Belpara"
    ],
    "wof:name":"Belpara",
    "wof:placetype":"locality",
    "wof:population":198
},
  "geometry": {"coordinates":[84.694129,22.249959],"type":"Point"}
}