{
  "type": "Feature",
  "properties": {
    "iso:country":"IN",
    "ks:ks_alt_nam":"Mudikkal road",
    "ks:ks_name":"Mudikkal Road",
    "ks:ks_pop":344,
    "ks:ks_type":"HABITATION",
    "name:eng_x_preferred":[
        "Mudikkal Road"
    ],
    "wof:name":"Mudikkal Road",
    "wof:placetype":"locality",
    "wof:population":344
},
  "geometry": {"coordinates":[75.719814,11.735364],"type":"Point"}
}