{
  "type": "Feature",
  "properties": {
    "gn:admin1_code":"40",
    "gn:admin2_code":"538.0",
    "gn:asciiname":"Penchikalpadu",
    "gn:country_code":"IN",
    "gn:dem":273,
    "gn:feature_class":"P",
    "gn:feature_code":"PPL",
    "gn:name":"Penchikalp\u0101du",
    "gn:population":0,
    "gn:timezone":"Asia/Kolkata",
    "iso:country":"IN",
    "ks:ks_alt_nam":"Penchikalp\u0101du",
    "ks:ks_name":"Penchikalpadu",
    "ks:ks_pop":1185,
    "ks:ks_type":"VILLAGE",
    "name:eng_x_preferred":[
        "Penchikalpadu"
    ],
    "name:eng_x_variant":[
        "Penchikalp\u0101du"
    ],
    "wof:name":"Penchikalpadu",
    "wof:placetype":"locality",
    "wof:population":1185
},
  "geometry": {"coordinates":[77.95996599999999,16.120587],"type":"Point"}
}