{
  "type": "Feature",
  "properties": {
    "iso:country":"IN",
    "ks:ks_name":"Ganga Dharampur",
    "ks:ks_pop":1420,
    "ks:ks_type":"VILLAGE",
    "ks:ks_uagg_main":0,
    "name:eng_x_preferred":[
        "Ganga Dharampur"
    ],
    "wof:name":"Ganga Dharampur",
    "wof:placetype":"neighbourhood",
    "wof:population":1420
},
  "geometry": {"coordinates":[85.35306799999999,26.346773],"type":"Point"}
}