{
  "type": "Feature",
  "properties": {
    "iso:country":"IN",
    "ks:ks_name":"6 DD",
    "ks:ks_pop":364,
    "ks:ks_type":"VILLAGE",
    "ks:ks_uagg_main":0,
    "name:eng_x_preferred":[
        "6 DD"
    ],
    "wof:name":"6 DD",
    "wof:placetype":"neighbourhood",
    "wof:population":364
},
  "geometry": {"coordinates":[73.12452,29.01913],"type":"Point"}
}