{
  "type": "Feature",
  "properties": {
    "iso:country":"IN",
    "ks:ks_name":"Chiktidand",
    "ks:ks_pop":102,
    "ks:ks_type":"HABITATION",
    "name:eng_x_preferred":[
        "Chiktidand"
    ],
    "wof:name":"Chiktidand",
    "wof:placetype":"locality",
    "wof:population":102
},
  "geometry": {"coordinates":[83.375854,22.646254],"type":"Point"}
}