{
  "type": "Feature",
  "properties": {
    "iso:country":"IN",
    "ks:ks_alt_nam":"HARIGAN BASTI 2",
    "ks:ks_name":"Harigan Basti 2",
    "ks:ks_pop":270,
    "ks:ks_type":"HABITATION",
    "name:eng_x_preferred":[
        "Harigan Basti 2"
    ],
    "wof:name":"Harigan Basti 2",
    "wof:placetype":"locality",
    "wof:population":270
},
  "geometry": {"coordinates":[83.97485399999999,25.687255],"type":"Point"}
}