{
  "type": "Feature",
  "properties": {
    "iso:country":"IN",
    "ks:ks_name":"Indkalo",
    "ks:ks_pop":395,
    "ks:ks_type":"VILLAGE",
    "ks:ks_uagg_main":0,
    "name:eng_x_preferred":[
        "Indkalo"
    ],
    "wof:name":"Indkalo",
    "wof:placetype":"neighbourhood",
    "wof:population":395
},
  "geometry": {"coordinates":[83.354339,22.684057],"type":"Point"}
}