{
  "type": "Feature",
  "properties": {
    "gn:admin1_code":"11.0",
    "gn:admin2_code":"34.0",
    "gn:asciiname":"Bering",
    "gn:country_code":"IN",
    "gn:dem":3150,
    "gn:feature_class":"P",
    "gn:feature_code":"PPL",
    "gn:name":"Bering",
    "gn:population":0,
    "gn:timezone":"Asia/Kolkata",
    "iso:country":"IN",
    "name:bak_x_preferred":[
        "\u0411\u0435\u0440\u0438\u043d\u0433"
    ],
    "name:bel_x_preferred":[
        "\u0411\u0435\u0440\u044b\u043d\u0433"
    ],
    "name:bul_x_preferred":[
        "\u0411\u0435\u0440\u0438\u043d\u0433"
    ],
    "name:cat_x_preferred":[
        "Bering"
    ],
    "name:deu_x_preferred":[
        "Bering"
    ],
    "name:eus_x_preferred":[
        "Bering"
    ],
    "name:fra_x_preferred":[
        "B\u00e9ring"
    ],
    "name:heb_x_preferred":[
        "\u05d1\u05e8\u05d9\u05e0\u05d2"
    ],
    "name:ita_x_preferred":[
        "Bering"
    ],
    "name:jpn_x_preferred":[
        "\u30d9\u30fc\u30ea\u30f3\u30b0"
    ],
    "name:nds_x_preferred":[
        "Bering"
    ],
    "name:nld_x_preferred":[
        "Bering"
    ],
    "name:ron_x_preferred":[
        "Bering"
    ],
    "name:rus_x_preferred":[
        "\u0411\u0435\u0440\u0438\u043d\u0433"
    ],
    "name:spa_x_preferred":[
        "Bering"
    ],
    "name:srp_x_preferred":[
        "\u0411\u0435\u0440\u0438\u043d\u0433"
    ],
    "name:tur_x_preferred":[
        "Bering"
    ],
    "name:ukr_x_preferred":[
        "\u0411\u0435\u0440\u0438\u043d\u0433"
    ],
    "wof:name":"Bering",
    "wof:placetype":"locality"
},
  "geometry": {"coordinates":[78.37354000000001,31.37299],"type":"Point"}
}