{
  "type": "Feature",
  "properties": {
    "gn:admin1_code":"11.0",
    "gn:admin2_code":"34.0",
    "gn:asciiname":"Bering",
    "gn:country_code":"IN",
    "gn:dem":3150,
    "gn:feature_class":"P",
    "gn:feature_code":"PPL",
    "gn:name":"Bering",
    "gn:population":0,
    "gn:timezone":"Asia/Kolkata",
    "iso:country":"IN",
    "wof:name":"Bering",
    "wof:placetype":"locality"
},
  "geometry": {"coordinates":[78.37354000000001,31.37299],"type":"Point"}
}