{
  "type": "Feature",
  "properties": {
    "gn:admin1_code":"36.0",
    "gn:admin2_code":"166.0",
    "gn:asciiname":"Garhi Kargawan",
    "gn:country_code":"IN",
    "gn:dem":197,
    "gn:feature_class":"P",
    "gn:feature_code":"PPL",
    "gn:name":"Garhi Kargaw\u0101n",
    "gn:population":0,
    "gn:timezone":"Asia/Kolkata",
    "iso:country":"IN",
    "wof:name":"Garhi Kargawan",
    "wof:placetype":"locality"
},
  "geometry": {"coordinates":[79.03792,25.55487],"type":"Point"}
}