{
  "type": "Feature",
  "properties": {
    "iso:country":"IN",
    "ks:ks_name":"Cheekumaddula",
    "ks:ks_pop":216,
    "ks:ks_type":"VILLAGE",
    "name:eng_x_preferred":[
        "Cheekumaddula"
    ],
    "wof:name":"Cheekumaddula",
    "wof:placetype":"locality",
    "wof:population":216
},
  "geometry": {"coordinates":[82.770826,18.078551],"type":"Point"}
}