{
  "type": "Feature",
  "properties": {
    "gn:admin1_code":"2.0",
    "gn:admin2_code":"544.0",
    "gn:asciiname":"Gindeli",
    "gn:country_code":"IN",
    "gn:dem":943,
    "gn:feature_class":"P",
    "gn:feature_code":"PPL",
    "gn:name":"Gindeli",
    "gn:population":0,
    "gn:timezone":"Asia/Kolkata",
    "iso:country":"IN",
    "ks:ks_name":"Gindali",
    "ks:ks_pop":52,
    "ks:ks_type":"HABITATION",
    "name:eng_x_preferred":[
        "Gindali"
    ],
    "name:eng_x_variant":[
        "Gindeli"
    ],
    "wof:name":"Gindali",
    "wof:placetype":"locality",
    "wof:population":52
},
  "geometry": {"coordinates":[82.39690400000001,18.1848],"type":"Point"}
}