{
  "type": "Feature",
  "properties": {
    "iso:country":"IN",
    "ks:ks_name":"Sahurpura",
    "ks:ks_pop":268,
    "ks:ks_type":"VILLAGE",
    "ks:ks_uagg_main":0,
    "name:eng_x_preferred":[
        "Sahurpura"
    ],
    "wof:name":"Sahurpura",
    "wof:placetype":"locality",
    "wof:population":268
},
  "geometry": {"coordinates":[86.529995,23.861738],"type":"Point"}
}