{
  "type": "Feature",
  "properties": {
    "iso:country":"IN",
    "ks:ks_name":"Banakata",
    "ks:ks_pop":391,
    "ks:ks_type":"HABITATION",
    "name:eng_x_preferred":[
        "Banakata"
    ],
    "wof:name":"Banakata",
    "wof:placetype":"locality",
    "wof:population":391
},
  "geometry": {"coordinates":[86.329474,22.641788],"type":"Point"}
}