{
  "type": "Feature",
  "properties": {
    "iso:country":"IN",
    "ks:ks_name":"Uttar Barbari",
    "ks:ks_pop":257,
    "ks:ks_type":"HABITATION",
    "name:eng_x_preferred":[
        "Uttar Barbari"
    ],
    "wof:name":"Uttar Barbari",
    "wof:placetype":"locality",
    "wof:population":257
},
  "geometry": {"coordinates":[91.397971,26.654621],"type":"Point"}
}