{
  "type": "Feature",
  "properties": {
    "gn:admin1_code":"12",
    "gn:admin2_code":"3.0",
    "gn:asciiname":"Zingral",
    "gn:country_code":"IN",
    "gn:dem":5286,
    "gn:feature_class":"P",
    "gn:feature_code":"PPL",
    "gn:name":"Zingral",
    "gn:population":0,
    "gn:timezone":"Asia/Kolkata",
    "iso:country":"IN",
    "wof:name":"Zingral",
    "wof:placetype":"locality"
},
  "geometry": {"coordinates":[77.91830999999998,34.02643],"type":"Point"}
}