{
  "type": "Feature",
  "properties": {
    "iso:country":"IN",
    "ks:ks_name":"Raipur",
    "ks:ks_pop":5106,
    "ks:ks_type":"VILLAGE",
    "ks:ks_uagg_main":0,
    "name:eng_x_preferred":[
        "Raipur"
    ],
    "name:hin_x_preferred":[
        "\u0930\u093e\u092f\u092a\u0941\u0930"
    ],
    "wof:name":"Raipur",
    "wof:placetype":"neighbourhood",
    "wof:population":5106
},
  "geometry": {"coordinates":[87.550479,23.424843],"type":"Point"}
}