{
  "type": "Feature",
  "properties": {
    "iso:country":"IN",
    "ks:ks_name":"Beermana",
    "ks:ks_pop":429,
    "ks:ks_type":"HABITATION",
    "name:eng_x_preferred":[
        "Beermana"
    ],
    "wof:name":"Beermana",
    "wof:placetype":"locality",
    "wof:population":429
},
  "geometry": {"coordinates":[73.518086,28.591753],"type":"Point"}
}