{
  "type": "Feature",
  "properties": {
    "iso:country":"IN",
    "ks:ks_name":"Satabatia",
    "ks:ks_pop":243,
    "ks:ks_type":"HABITATION",
    "name:eng_x_preferred":[
        "Satabatia"
    ],
    "wof:name":"Satabatia",
    "wof:placetype":"locality",
    "wof:population":243
},
  "geometry": {"coordinates":[86.035864,21.030865],"type":"Point"}
}