{
  "type": "Feature",
  "properties": {
    "gn:admin1_code":"35.0",
    "gn:admin2_code":"441.0",
    "gn:asciiname":"Solavan",
    "gn:country_code":"IN",
    "gn:dem":346,
    "gn:feature_class":"P",
    "gn:feature_code":"PPL",
    "gn:name":"Solav\u0101n",
    "gn:population":0,
    "gn:timezone":"Asia/Kolkata",
    "iso:country":"IN",
    "wof:name":"Solavan",
    "wof:placetype":"locality"
},
  "geometry": {"coordinates":[75.11700999999999,21.54209],"type":"Point"}
}