{
  "type": "Feature",
  "properties": {
    "gn:admin1_code":"35.0",
    "gn:admin2_code":"441.0",
    "gn:asciiname":"Solavan",
    "gn:country_code":"IN",
    "gn:dem":346,
    "gn:feature_class":"P",
    "gn:feature_code":"PPL",
    "gn:name":"Solav\u0101n",
    "gn:population":0,
    "gn:timezone":"Asia/Kolkata",
    "iso:country":"IN",
    "ks:ks_name":"Solwan",
    "ks:ks_pop":3466,
    "ks:ks_type":"VILLAGE",
    "name:eng_x_preferred":[
        "Solwan"
    ],
    "name:eng_x_variant":[
        "Solavan"
    ],
    "wof:name":"Solwan",
    "wof:placetype":"locality",
    "wof:population":3466
},
  "geometry": {"coordinates":[75.135204,21.546847],"type":"Point"}
}