{
  "type": "Feature",
  "properties": {
    "iso:country":"IN",
    "ks:ks_name":"Bhatipara",
    "ks:ks_pop":470,
    "ks:ks_type":"HABITATION",
    "name:eng_x_preferred":[
        "Bhatipara"
    ],
    "wof:name":"Bhatipara",
    "wof:placetype":"locality",
    "wof:population":470
},
  "geometry": {"coordinates":[81.707606,19.353023],"type":"Point"}
}