{
  "type": "Feature",
  "properties": {
    "iso:country":"IN",
    "ks:ks_name":"Jangipur",
    "ks:ks_pop":155,
    "ks:ks_type":"VILLAGE",
    "name:eng_x_preferred":[
        "Jangipur"
    ],
    "wof:name":"Jangipur",
    "wof:placetype":"locality",
    "wof:population":155
},
  "geometry": {"coordinates":[87.629102,21.796392],"type":"Point"}
}