{
  "type": "Feature",
  "properties": {
    "gn:admin1_code":"16",
    "gn:admin2_code":"511.0",
    "gn:asciiname":"Hangirga",
    "gn:country_code":"IN",
    "gn:dem":385,
    "gn:feature_class":"P",
    "gn:feature_code":"PPL",
    "gn:name":"Hangirga",
    "gn:population":0,
    "gn:timezone":"Asia/Kolkata",
    "iso:country":"IN",
    "wof:name":"Hangirga",
    "wof:placetype":"locality"
},
  "geometry": {"coordinates":[77.59314999999999,18.87494],"type":"Point"}
}