{
  "type": "Feature",
  "properties": {
    "iso:country":"IN",
    "ks:ks_name":"Pattoli",
    "ks:ks_pop":24,
    "ks:ks_type":"HABITATION",
    "name:eng_x_preferred":[
        "Pattoli"
    ],
    "wof:name":"Pattoli",
    "wof:placetype":"locality",
    "wof:population":24
},
  "geometry": {"coordinates":[75.53228900000001,12.693035],"type":"Point"}
}