{
  "type": "Feature",
  "properties": {
    "iso:country":"IN",
    "ks:ks_name":"Ceylon Colony",
    "ks:ks_pop":121,
    "ks:ks_type":"HABITATION",
    "name:eng_x_preferred":[
        "Ceylon Colony"
    ],
    "wof:name":"Ceylon Colony",
    "wof:placetype":"locality",
    "wof:population":121
},
  "geometry": {"coordinates":[77.779394,9.618255],"type":"Point"}
}