{
  "type": "Feature",
  "properties": {
    "iso:country":"IN",
    "ks:ks_name":"Muthalsethi",
    "ks:ks_pop":360,
    "ks:ks_type":"HABITATION",
    "name:eng_x_preferred":[
        "Muthalsethi"
    ],
    "wof:name":"Muthalsethi",
    "wof:placetype":"locality",
    "wof:population":360
},
  "geometry": {"coordinates":[79.47408,10.651529],"type":"Point"}
}