{
  "type": "Feature",
  "properties": {
    "gn:admin1_code":"36",
    "gn:admin2_code":"172.0",
    "gn:asciiname":"Lahurajkhera",
    "gn:country_code":"IN",
    "gn:dem":119,
    "gn:feature_class":"P",
    "gn:feature_code":"PPL",
    "gn:name":"Lahur\u0101jkhera",
    "gn:population":0,
    "gn:timezone":"Asia/Kolkata",
    "iso:country":"IN",
    "ks:ks_name":"Lahuraj Khera",
    "ks:ks_pop":199,
    "ks:ks_type":"VILLAGE",
    "name:eng_x_preferred":[
        "Lahuraj Khera"
    ],
    "name:eng_x_variant":[
        "Lahurajkhera"
    ],
    "wof:name":"Lahuraj Khera",
    "wof:placetype":"locality",
    "wof:population":199
},
  "geometry": {"coordinates":[80.59450699999999,25.902586],"type":"Point"}
}