{
  "type": "Feature",
  "properties": {
    "iso:country":"IN",
    "ks:ks_name":"Rakh Cheeta",
    "ks:ks_pop":1122,
    "ks:ks_type":"HABITATION",
    "name:eng_x_preferred":[
        "Rakh Cheeta"
    ],
    "wof:name":"Rakh Cheeta",
    "wof:placetype":"locality",
    "wof:population":1122
},
  "geometry": {"coordinates":[74.98384299999999,31.576589],"type":"Point"}
}