{
  "type": "Feature",
  "properties": {
    "iso:country":"IN",
    "ks:ks_name":"Chamilpada",
    "ks:ks_pop":225,
    "ks:ks_type":"HABITATION",
    "name:eng_x_preferred":[
        "Chamilpada"
    ],
    "wof:name":"Chamilpada",
    "wof:placetype":"locality",
    "wof:population":225
},
  "geometry": {"coordinates":[73.291629,19.953456],"type":"Point"}
}