{
  "type": "Feature",
  "properties": {
    "gn:admin1_code":"36",
    "gn:admin2_code":"154.0",
    "gn:asciiname":"Agaia",
    "gn:country_code":"IN",
    "gn:dem":124,
    "gn:feature_class":"P",
    "gn:feature_code":"PPL",
    "gn:name":"Agaia",
    "gn:population":0,
    "gn:timezone":"Asia/Kolkata",
    "iso:country":"IN",
    "ks:ks_name":"Agaiya",
    "ks:ks_pop":606,
    "ks:ks_type":"VILLAGE",
    "ks:ks_uagg_main":0,
    "name:eng_x_preferred":[
        "Agaiya"
    ],
    "wof:name":"Agaiya",
    "wof:placetype":"neighbourhood",
    "wof:population":606
},
  "geometry": {"coordinates":[81.17731499999999,27.319783],"type":"Point"}
}