{
  "type": "Feature",
  "properties": {
    "iso:country":"IN",
    "ks:ks_name":"Sulagodu",
    "ks:ks_pop":221,
    "ks:ks_type":"HABITATION",
    "name:eng_x_preferred":[
        "Sulagodu"
    ],
    "wof:name":"Sulagodu",
    "wof:placetype":"locality",
    "wof:population":221
},
  "geometry": {"coordinates":[75.212322,14.088078],"type":"Point"}
}