{
  "type": "Feature",
  "properties": {
    "iso:country":"IN",
    "ks:ks_name":"Hadfodi",
    "ks:ks_pop":1697,
    "ks:ks_type":"VILLAGE",
    "name:eng_x_preferred":[
        "Hadfodi"
    ],
    "wof:name":"Hadfodi",
    "wof:placetype":"locality",
    "wof:population":1697
},
  "geometry": {"coordinates":[70.28675,21.701528],"type":"Point"}
}