{
  "type": "Feature",
  "properties": {
    "iso:country":"IN",
    "ks:ks_name":"Kelakoppa",
    "ks:ks_pop":135,
    "ks:ks_type":"VILLAGE",
    "name:eng_x_preferred":[
        "Kelakoppa"
    ],
    "wof:name":"Kelakoppa",
    "wof:placetype":"locality",
    "wof:population":135
},
  "geometry": {"coordinates":[75.275465,13.477898],"type":"Point"}
}