{
  "type": "Feature",
  "properties": {
    "gn:admin1_code":"19.0",
    "gn:admin2_code":"555.0",
    "gn:asciiname":"Hanamsagar",
    "gn:country_code":"IN",
    "gn:dem":612,
    "gn:feature_class":"P",
    "gn:feature_code":"PPL",
    "gn:name":"Hanams\u0101gar",
    "gn:population":0,
    "gn:timezone":"Asia/Kolkata",
    "iso:country":"IN",
    "wof:name":"Hanamsagar",
    "wof:placetype":"locality"
},
  "geometry": {"coordinates":[75.1598,15.94017],"type":"Point"}
}