{
  "type": "Feature",
  "properties": {
    "iso:country":"IN",
    "ks:ks_name":"Malaka",
    "ks:ks_pop":338,
    "ks:ks_type":"HABITATION",
    "name:eng_x_preferred":[
        "Malaka"
    ],
    "wof:name":"Malaka",
    "wof:placetype":"locality",
    "wof:population":338
},
  "geometry": {"coordinates":[81.56259,25.561425],"type":"Point"}
}