{
  "type": "Feature",
  "properties": {
    "iso:country":"IN",
    "ks:ks_name":"Krishchanwadi",
    "ks:ks_pop":37,
    "ks:ks_type":"HABITATION",
    "name:eng_x_preferred":[
        "Krishchanwadi"
    ],
    "wof:name":"Krishchanwadi",
    "wof:placetype":"locality",
    "wof:population":37
},
  "geometry": {"coordinates":[73.772094,15.763818],"type":"Point"}
}