{
  "type": "Feature",
  "properties": {
    "gn:admin1_code":"25.0",
    "gn:admin2_code":"633.0",
    "gn:asciiname":"Rakkiyapalaiyam",
    "gn:country_code":"IN",
    "gn:dem":321,
    "gn:feature_class":"P",
    "gn:feature_code":"PPL",
    "gn:name":"R\u0101kkiy\u0101p\u0101laiyam",
    "gn:population":0,
    "gn:timezone":"Asia/Kolkata",
    "iso:country":"IN",
    "wof:name":"Rakkiyapalaiyam",
    "wof:placetype":"neighbourhood"
},
  "geometry": {"coordinates":[77.28834999999999,11.15959],"type":"Point"}
}