{
  "type": "Feature",
  "properties": {
    "gn:admin1_code":"25.0",
    "gn:admin2_code":"631.0",
    "gn:asciiname":"Kurubarhola",
    "gn:country_code":"IN",
    "gn:dem":1158,
    "gn:feature_class":"P",
    "gn:feature_code":"PPL",
    "gn:name":"Kurubarhola",
    "gn:population":0,
    "gn:timezone":"Asia/Kolkata",
    "iso:country":"IN",
    "wof:name":"Kurubarhola",
    "wof:placetype":"locality"
},
  "geometry": {"coordinates":[77.88438000000002,12.36482],"type":"Point"}
}