{
  "type": "Feature",
  "properties": {
    "iso:country":"IN",
    "ks:ks_alt_nam":"D PAMBALAPALLE",
    "ks:ks_name":"D Pambalapalle",
    "ks:ks_pop":115,
    "ks:ks_type":"HABITATION",
    "name:eng_x_preferred":[
        "D Pambalapalle"
    ],
    "wof:name":"D Pambalapalle",
    "wof:placetype":"locality",
    "wof:population":115
},
  "geometry": {"coordinates":[79.113412,13.399478],"type":"Point"}
}