{
  "type": "Feature",
  "properties": {
    "gn:admin1_code":"40.0",
    "gn:admin2_code":"538.0",
    "gn:asciiname":"Valluru",
    "gn:country_code":"IN",
    "gn:dem":316,
    "gn:feature_class":"P",
    "gn:feature_code":"PPL",
    "gn:name":"Vall\u016bru",
    "gn:population":0,
    "gn:timezone":"Asia/Kolkata",
    "iso:country":"IN",
    "name:und_x_variant":[
        "Vall\u016bru",
        "Vallur"
    ],
    "wof:name":"Valluru",
    "wof:placetype":"locality"
},
  "geometry": {"coordinates":[77.89989,16.01327],"type":"Point"}
}