{
  "type": "Feature",
  "properties": {
    "iso:country":"IN",
    "ks:ks_name":"Muthalabailu",
    "ks:ks_pop":284,
    "ks:ks_type":"HABITATION",
    "name:eng_x_preferred":[
        "Muthalabailu"
    ],
    "wof:name":"Muthalabailu",
    "wof:placetype":"locality",
    "wof:population":284
},
  "geometry": {"coordinates":[75.22166300000001,14.253697],"type":"Point"}
}