{
  "type": "Feature",
  "properties": {
    "iso:country":"IN",
    "ks:ks_alt_nam":"YADAV TOLA",
    "ks:ks_name":"Yadav Tola",
    "ks:ks_pop":321,
    "ks:ks_type":"HABITATION",
    "name:eng_x_preferred":[
        "Yadav Tola"
    ],
    "wof:name":"Yadav Tola",
    "wof:placetype":"locality",
    "wof:population":321
},
  "geometry": {"coordinates":[86.737877,25.231403],"type":"Point"}
}