{
  "type": "Feature",
  "properties": {
    "gn:admin1_code":"35.0",
    "gn:admin2_code":"447.0",
    "gn:asciiname":"Harnakheri",
    "gn:country_code":"IN",
    "gn:dem":753,
    "gn:feature_class":"P",
    "gn:feature_code":"PPL",
    "gn:name":"Harn\u0101kheri",
    "gn:population":0,
    "gn:timezone":"Asia/Kolkata",
    "iso:country":"IN",
    "wof:name":"Harnakheri",
    "wof:placetype":"locality"
},
  "geometry": {"coordinates":[78.27060999999998,21.84662],"type":"Point"}
}