{
  "type": "Feature",
  "properties": {
    "iso:country":"IN",
    "ks:ks_name":"Molesh Gaur Gaon 2",
    "ks:ks_pop":75,
    "ks:ks_type":"HABITATION",
    "name:eng_x_preferred":[
        "Molesh Gaur Gaon 2"
    ],
    "wof:name":"Molesh Gaur Gaon 2",
    "wof:placetype":"locality",
    "wof:population":75
},
  "geometry": {"coordinates":[93.131274,26.03655],"type":"Point"}
}