{
  "type": "Feature",
  "properties": {
    "gn:admin1_code":"19.0",
    "gn:admin2_code":"559",
    "gn:asciiname":"Chikhesrur",
    "gn:country_code":"IN",
    "gn:dem":530,
    "gn:feature_class":"P",
    "gn:feature_code":"PPL",
    "gn:name":"Chikhesr\u016br",
    "gn:population":0,
    "gn:timezone":"Asia/Kolkata",
    "iso:country":"IN",
    "name:und_x_variant":[
        "Chikhesr\u016br",
        "Hesr\u016br"
    ],
    "wof:name":"Chikhesrur",
    "wof:placetype":"neighbourhood"
},
  "geometry": {"coordinates":[76.63773999999999,16.11113],"type":"Point"}
}