{
  "type": "Feature",
  "properties": {
    "iso:country":"IN",
    "ks:ks_name":"Halligadde",
    "ks:ks_pop":108,
    "ks:ks_type":"HABITATION",
    "name:eng_x_preferred":[
        "Halligadde"
    ],
    "wof:name":"Halligadde",
    "wof:placetype":"locality",
    "wof:population":108
},
  "geometry": {"coordinates":[74.835824,14.885213],"type":"Point"}
}