{
  "type": "Feature",
  "properties": {
    "gn:admin1_code":"40",
    "gn:admin2_code":"539.0",
    "gn:asciiname":"Girijanagar",
    "gn:country_code":"IN",
    "gn:dem":315,
    "gn:feature_class":"P",
    "gn:feature_code":"PPL",
    "gn:name":"Girij\u0101nagar",
    "gn:population":0,
    "gn:timezone":"Asia/Kolkata",
    "iso:country":"IN",
    "wof:name":"Girijanagar",
    "wof:placetype":"locality"
},
  "geometry": {"coordinates":[78.86849000000002,16.69422],"type":"Point"}
}