{
  "type": "Feature",
  "properties": {
    "iso:country":"IN",
    "ks:ks_name":"Guravwadi",
    "ks:ks_pop":40,
    "ks:ks_type":"HABITATION",
    "name:eng_x_preferred":[
        "Guravwadi"
    ],
    "wof:name":"Guravwadi",
    "wof:placetype":"locality",
    "wof:population":40
},
  "geometry": {"coordinates":[73.48916699999999,17.145556],"type":"Point"}
}