{
  "type": "Feature",
  "properties": {
    "iso:country":"IN",
    "ks:ks_name":"Sarsa",
    "ks:ks_pop":89,
    "ks:ks_type":"VILLAGE",
    "name:eng_x_preferred":[
        "Sarsa"
    ],
    "wof:name":"Sarsa",
    "wof:placetype":"locality",
    "wof:population":89
},
  "geometry": {"coordinates":[87.701472,25.181577],"type":"Point"}
}