{
  "type": "Feature",
  "properties": {
    "gn:admin1_code":"34.0",
    "gn:admin2_code":"235.0",
    "gn:asciiname":"Azimabad",
    "gn:country_code":"IN",
    "gn:dem":101,
    "gn:feature_class":"P",
    "gn:feature_code":"PPL",
    "gn:name":"Azim\u0101b\u0101d",
    "gn:population":0,
    "gn:timezone":"Asia/Kolkata",
    "iso:country":"IN",
    "name:urd_x_preferred":[
        "\u0639\u0638\u06cc\u0645 \u0622\u0628\u0627\u062f"
    ],
    "wof:name":"Azimabad",
    "wof:placetype":"neighbourhood"
},
  "geometry": {"coordinates":[84.43801000000001,24.86318],"type":"Point"}
}