{
  "type": "Feature",
  "properties": {
    "iso:country":"IN",
    "ks:ks_alt_nam":"Devlaniak tanda",
    "ks:ks_name":"Devlaniak Tanda",
    "ks:ks_pop":115,
    "ks:ks_type":"HABITATION",
    "name:eng_x_preferred":[
        "Devlaniak Tanda"
    ],
    "wof:name":"Devlaniak Tanda",
    "wof:placetype":"locality",
    "wof:population":115
},
  "geometry": {"coordinates":[77.924172,17.029953],"type":"Point"}
}