{
  "type": "Feature",
  "properties": {
    "gn:admin1_code":"11",
    "gn:admin2_code":"33.0",
    "gn:asciiname":"Lingzar",
    "gn:country_code":"IN",
    "gn:dem":2281,
    "gn:feature_class":"P",
    "gn:feature_code":"PPL",
    "gn:name":"Lingz\u0101r",
    "gn:population":0,
    "gn:timezone":"Asia/Kolkata",
    "iso:country":"IN",
    "wof:name":"Lingzar",
    "wof:placetype":"locality"
},
  "geometry": {"coordinates":[77.54363000000002,30.89845],"type":"Point"}
}