{
  "type": "Feature",
  "properties": {
    "gn:admin1_code":"24.0",
    "gn:admin2_code":"124.0",
    "gn:asciiname":"Khajuria",
    "gn:country_code":"IN",
    "gn:dem":264,
    "gn:feature_class":"P",
    "gn:feature_code":"PPL",
    "gn:name":"Khajuria",
    "gn:population":0,
    "gn:timezone":"Asia/Kolkata",
    "iso:country":"IN",
    "ks:ks_name":"Khajuria",
    "ks:ks_type":"VILLAGE",
    "name:eng_x_preferred":[
        "Khajuria"
    ],
    "wof:name":"Khajuria",
    "wof:placetype":"locality"
},
  "geometry": {"coordinates":[73.88561199999999,23.902862],"type":"Point"}
}