{
  "type": "Feature",
  "properties": {
    "iso:country":"IN",
    "ks:ks_alt_nam":"WATEGAON TAL B",
    "ks:ks_name":"Wategaon Tal B",
    "ks:ks_pop":75,
    "ks:ks_type":"HABITATION",
    "name:eng_x_preferred":[
        "Wategaon Tal B"
    ],
    "wof:name":"Wategaon Tal B",
    "wof:placetype":"locality",
    "wof:population":75
},
  "geometry": {"coordinates":[74.142517,17.072932],"type":"Point"}
}