{
  "type": "Feature",
  "properties": {
    "iso:country":"IN",
    "ks:ks_name":"Barigoba",
    "ks:ks_pop":238,
    "ks:ks_type":"VILLAGE",
    "name:eng_x_preferred":[
        "Barigoba"
    ],
    "wof:name":"Barigoba",
    "wof:placetype":"locality",
    "wof:population":238
},
  "geometry": {"coordinates":[83.77853399999999,20.552044],"type":"Point"}
}