{
  "type": "Feature",
  "properties": {
    "gn:admin1_code":"11",
    "gn:admin2_code":"27.0",
    "gn:asciiname":"Basehr",
    "gn:country_code":"IN",
    "gn:dem":868,
    "gn:feature_class":"P",
    "gn:feature_code":"PPL",
    "gn:name":"Basehr",
    "gn:population":0,
    "gn:timezone":"Asia/Kolkata",
    "iso:country":"IN",
    "wof:name":"Basehr",
    "wof:placetype":"locality"
},
  "geometry": {"coordinates":[76.88693000000001,31.60879000000001],"type":"Point"}
}