{
  "type": "Feature",
  "properties": {
    "gn:admin1_code":"36",
    "gn:admin2_code":"180.0",
    "gn:asciiname":"Pura Dhobaha Ahiran",
    "gn:country_code":"IN",
    "gn:dem":115,
    "gn:feature_class":"P",
    "gn:feature_code":"PPL",
    "gn:name":"Pura Dhob\u0101ha Ahiran",
    "gn:population":0,
    "gn:timezone":"Asia/Kolkata",
    "iso:country":"IN",
    "wof:name":"Pura Dhobaha Ahiran",
    "wof:placetype":"neighbourhood"
},
  "geometry": {"coordinates":[81.53348,27.47472],"type":"Point"}
}