{
  "type": "Feature",
  "properties": {
    "iso:country":"IN",
    "ks:ks_name":"Bachanaput",
    "ks:ks_pop":669,
    "ks:ks_type":"VILLAGE",
    "name:eng_x_preferred":[
        "Bachanaput"
    ],
    "wof:name":"Bachanaput",
    "wof:placetype":"locality",
    "wof:population":669
},
  "geometry": {"coordinates":[83.148653,18.851501],"type":"Point"}
}