{
  "type": "Feature",
  "properties": {
    "gn:admin1_code":"23.0",
    "gn:admin2_code":"49.0",
    "gn:asciiname":"Nijjar",
    "gn:country_code":"IN",
    "gn:dem":235,
    "gn:feature_class":"P",
    "gn:feature_code":"PPL",
    "gn:name":"Nijjar",
    "gn:population":0,
    "gn:timezone":"Asia/Kolkata",
    "iso:country":"IN",
    "name:hin_x_preferred":[
        "\u0928\u093f\u091c\u094d\u091c\u0930"
    ],
    "wof:name":"Nijjar",
    "wof:placetype":"locality"
},
  "geometry": {"coordinates":[75.21335000000001,31.52526],"type":"Point"}
}