{
  "type": "Feature",
  "properties": {
    "iso:country":"IN",
    "ks:ks_name":"Rohila Kachhar",
    "ks:ks_pop":179,
    "ks:ks_type":"VILLAGE",
    "name:eng_x_preferred":[
        "Rohila Kachhar"
    ],
    "wof:name":"Rohila Kachhar",
    "wof:placetype":"locality",
    "wof:population":179
},
  "geometry": {"coordinates":[81.855954,23.100458],"type":"Point"}
}