{
  "type": "Feature",
  "properties": {
    "iso:country":"IN",
    "ks:ks_name":"Nariyeli",
    "ks:ks_pop":1006,
    "ks:ks_type":"HABITATION",
    "name:eng_x_preferred":[
        "Nariyeli"
    ],
    "wof:name":"Nariyeli",
    "wof:placetype":"locality",
    "wof:population":1006
},
  "geometry": {"coordinates":[71.163509,22.461432],"type":"Point"}
}