{
  "type": "Feature",
  "properties": {
    "iso:country":"IN",
    "ks:ks_name":"Mhaskewadi",
    "ks:ks_pop":86,
    "ks:ks_type":"HABITATION",
    "name:eng_x_preferred":[
        "Mhaskewadi"
    ],
    "wof:name":"Mhaskewadi",
    "wof:placetype":"locality",
    "wof:population":86
},
  "geometry": {"coordinates":[73.584543,18.103706],"type":"Point"}
}