{
  "type": "Feature",
  "properties": {
    "iso:country":"IN",
    "ks:ks_name":"Kolathur Colony",
    "ks:ks_pop":500,
    "ks:ks_type":"HABITATION",
    "name:eng_x_preferred":[
        "Kolathur Colony"
    ],
    "wof:name":"Kolathur Colony",
    "wof:placetype":"locality",
    "wof:population":500
},
  "geometry": {"coordinates":[79.91517,12.413974],"type":"Point"}
}