{
  "type": "Feature",
  "properties": {
    "gn:admin1_code":"25.0",
    "gn:admin2_code":"611.0",
    "gn:asciiname":"Molaipalaiyam",
    "gn:country_code":"IN",
    "gn:dem":1823,
    "gn:feature_class":"P",
    "gn:feature_code":"PPL",
    "gn:name":"Molaipalaiyam",
    "gn:population":0,
    "gn:timezone":"Asia/Kolkata",
    "iso:country":"IN",
    "wof:name":"Molaipalaiyam",
    "wof:placetype":"locality"
},
  "geometry": {"coordinates":[76.92901999999999,11.48365],"type":"Point"}
}