{
  "type": "Feature",
  "properties": {
    "gn:admin1_code":"36",
    "gn:admin2_code":"189.0",
    "gn:asciiname":"Jamli",
    "gn:country_code":"IN",
    "gn:dem":91,
    "gn:feature_class":"P",
    "gn:feature_code":"PPL",
    "gn:name":"Jamli",
    "gn:population":0,
    "gn:timezone":"Asia/Kolkata",
    "iso:country":"IN",
    "wof:name":"Jamli",
    "wof:placetype":"locality"
},
  "geometry": {"coordinates":[83.61903000000002,26.92781],"type":"Point"}
}