{
  "type": "Feature",
  "properties": {
    "iso:country":"IN",
    "ks:ks_name":"Yenuguwanigudem",
    "ks:ks_pop":73,
    "ks:ks_type":"HABITATION",
    "name:eng_x_preferred":[
        "Yenuguwanigudem"
    ],
    "wof:name":"Yenuguwanigudem",
    "wof:placetype":"locality",
    "wof:population":73
},
  "geometry": {"coordinates":[78.818186,17.355746],"type":"Point"}
}