{
  "type": "Feature",
  "properties": {
    "gn:admin1_code":"21.0",
    "gn:admin2_code":"398.0",
    "gn:asciiname":"Matanguda",
    "gn:country_code":"IN",
    "gn:dem":802,
    "gn:feature_class":"P",
    "gn:feature_code":"PPL",
    "gn:name":"Matanguda",
    "gn:population":0,
    "gn:timezone":"Asia/Kolkata",
    "iso:country":"IN",
    "wof:name":"Matanguda",
    "wof:placetype":"locality"
},
  "geometry": {"coordinates":[82.98409000000002,18.99947],"type":"Point"}
}