{
  "type": "Feature",
  "properties": {
    "gn:admin1_code":"24",
    "gn:admin2_code":"123.0",
    "gn:asciiname":"Bojela",
    "gn:country_code":"IN",
    "gn:dem":635,
    "gn:feature_class":"P",
    "gn:feature_code":"PPL",
    "gn:name":"Bojela",
    "gn:population":0,
    "gn:timezone":"Asia/Kolkata",
    "iso:country":"IN",
    "ks:ks_name":"Bojela",
    "ks:ks_pop":1244,
    "ks:ks_type":"VILLAGE",
    "name:eng_x_preferred":[
        "Bojela"
    ],
    "wof:name":"Bojela",
    "wof:placetype":"locality",
    "wof:population":1244
},
  "geometry": {"coordinates":[73.82697899999999,25.167607],"type":"Point"}
}