{
  "type": "Feature",
  "properties": {
    "iso:country":"IN",
    "ks:ks_name":"5 HDP-A",
    "ks:ks_pop":86,
    "ks:ks_type":"VILLAGE",
    "name:eng_x_preferred":[
        "5 HDP-A"
    ],
    "wof:name":"5 HDP-A",
    "wof:placetype":"locality",
    "wof:population":86
},
  "geometry": {"coordinates":[73.969583,29.632867],"type":"Point"}
}