{
  "type": "Feature",
  "properties": {
    "iso:country":"IN",
    "ks:ks_name":"Karjan Dih",
    "ks:ks_pop":5317,
    "ks:ks_type":"VILLAGE",
    "name:eng_x_preferred":[
        "Karjan Dih"
    ],
    "wof:name":"Karjan Dih",
    "wof:placetype":"locality",
    "wof:population":5317
},
  "geometry": {"coordinates":[85.25546,26.096238],"type":"Point"}
}