{
  "type": "Feature",
  "properties": {
    "iso:country":"IN",
    "ks:ks_name":"Ettani",
    "ks:ks_pop":896,
    "ks:ks_type":"HABITATION",
    "name:eng_x_preferred":[
        "Ettani"
    ],
    "wof:name":"Ettani",
    "wof:placetype":"locality",
    "wof:population":896
},
  "geometry": {"coordinates":[77.24044499999999,8.258089],"type":"Point"}
}