{
  "type": "Feature",
  "properties": {
    "gn:admin1_code":"11.0",
    "gn:admin2_code":"26.0",
    "gn:asciiname":"Marhog",
    "gn:country_code":"IN",
    "gn:dem":2327,
    "gn:feature_class":"P",
    "gn:feature_code":"PPL",
    "gn:name":"Marhog",
    "gn:population":0,
    "gn:timezone":"Asia/Kolkata",
    "iso:country":"IN",
    "wof:name":"Marhog",
    "wof:placetype":"locality"
},
  "geometry": {"coordinates":[77.33849000000002,31.4772],"type":"Point"}
}