{
  "type": "Feature",
  "properties": {
    "iso:country":"IN",
    "ks:ks_name":"Kothanakiripeta",
    "ks:ks_pop":38,
    "ks:ks_type":"HABITATION",
    "name:eng_x_preferred":[
        "Kothanakiripeta"
    ],
    "wof:name":"Kothanakiripeta",
    "wof:placetype":"locality",
    "wof:population":38
},
  "geometry": {"coordinates":[80.813993,17.673062],"type":"Point"}
}