{
  "type": "Feature",
  "properties": {
    "iso:country":"IN",
    "ks:ks_name":"Nohadia",
    "ks:ks_pop":57,
    "ks:ks_type":"HABITATION",
    "name:eng_x_preferred":[
        "Nohadia"
    ],
    "wof:name":"Nohadia",
    "wof:placetype":"locality",
    "wof:population":57
},
  "geometry": {"coordinates":[81.48350000000001,26.381],"type":"Point"}
}