{
  "type": "Feature",
  "properties": {
    "gn:admin1_code":"19",
    "gn:admin2_code":"557.0",
    "gn:asciiname":"Khanikeri",
    "gn:country_code":"IN",
    "gn:dem":492,
    "gn:feature_class":"P",
    "gn:feature_code":"PPL",
    "gn:name":"Kh\u0101nikeri",
    "gn:population":0,
    "gn:timezone":"Asia/Kolkata",
    "iso:country":"IN",
    "ks:ks_name":"Khanikeri",
    "ks:ks_type":"VILLAGE",
    "name:eng_x_preferred":[
        "Khanikeri"
    ],
    "wof:name":"Khanikeri",
    "wof:placetype":"locality"
},
  "geometry": {"coordinates":[76.327445,16.217959],"type":"Point"}
}