{
  "type": "Feature",
  "properties": {
    "iso:country":"IN",
    "ks:ks_name":"Jetpor",
    "ks:ks_pop":137,
    "ks:ks_type":"VILLAGE",
    "name:eng_x_preferred":[
        "Jetpor"
    ],
    "wof:name":"Jetpor",
    "wof:placetype":"locality",
    "wof:population":137
},
  "geometry": {"coordinates":[73.490629,21.84366],"type":"Point"}
}