{
  "type": "Feature",
  "properties": {
    "gn:admin1_code":"10.0",
    "gn:admin2_code":"73.0",
    "gn:asciiname":"Dubal",
    "gn:country_code":"IN",
    "gn:dem":232,
    "gn:feature_class":"P",
    "gn:feature_code":"PPL",
    "gn:name":"D\u016bbal",
    "gn:population":0,
    "gn:timezone":"Asia/Kolkata",
    "iso:country":"IN",
    "name:ara_x_preferred":[
        "\u062f\u0648\u0628\u0627\u0644"
    ],
    "name:fas_x_preferred":[
        "\u062f\u0628\u0627\u0644"
    ],
    "name:fra_x_preferred":[
        "Dubal"
    ],
    "name:ind_x_preferred":[
        "Dubal"
    ],
    "wof:name":"Dubal",
    "wof:placetype":"locality"
},
  "geometry": {"coordinates":[76.22311999999999,29.74465],"type":"Point"}
}