{
  "type": "Feature",
  "properties": {
    "gn:admin1_code":"2.0",
    "gn:admin2_code":"543.0",
    "gn:asciiname":"Subhadrammavalasa",
    "gn:country_code":"IN",
    "gn:dem":168,
    "gn:feature_class":"P",
    "gn:feature_code":"PPL",
    "gn:name":"Subhadrammavalasa",
    "gn:population":0,
    "gn:timezone":"Asia/Kolkata",
    "iso:country":"IN",
    "wof:name":"Subhadrammavalasa",
    "wof:placetype":"locality"
},
  "geometry": {"coordinates":[83.56355000000001,18.8721],"type":"Point"}
}