{
  "type": "Feature",
  "properties": {
    "gn:admin1_code":"24.0",
    "gn:admin2_code":"102",
    "gn:asciiname":"Mehrasar",
    "gn:country_code":"IN",
    "gn:dem":273,
    "gn:feature_class":"P",
    "gn:feature_code":"PPL",
    "gn:name":"Mehr\u0101sar",
    "gn:population":0,
    "gn:timezone":"Asia/Kolkata",
    "iso:country":"IN",
    "name:und_x_variant":[
        "Merasar",
        "Mehr\u0101sar"
    ],
    "wof:name":"Mehrasar",
    "wof:placetype":"neighbourhood"
},
  "geometry": {"coordinates":[74.54094000000001,28.36946],"type":"Point"}
}