{
  "type": "Feature",
  "properties": {
    "iso:country":"IN",
    "ks:ks_alt_nam":"Bordubi T E  WLA  No 6",
    "ks:ks_name":"Bordubi T E Wla No 6",
    "ks:ks_pop":1225,
    "ks:ks_type":"HABITATION",
    "name:eng_x_preferred":[
        "Bordubi T E Wla No 6"
    ],
    "name:eng_x_variant":[
        "Bordubi T E  WLA  No 6"
    ],
    "wof:name":"Bordubi T E Wla No 6",
    "wof:placetype":"locality",
    "wof:population":1225
},
  "geometry": {"coordinates":[95.598979,27.599865],"type":"Point"}
}