{
  "type": "Feature",
  "properties": {
    "gn:admin1_code":"36",
    "gn:admin2_code":"180.0",
    "gn:asciiname":"Laluhi",
    "gn:country_code":"IN",
    "gn:dem":125,
    "gn:feature_class":"P",
    "gn:feature_code":"PPL",
    "gn:name":"Laluhi",
    "gn:population":0,
    "gn:timezone":"Asia/Kolkata",
    "iso:country":"IN",
    "ks:ks_name":"Laluhi",
    "ks:ks_pop":3039,
    "ks:ks_type":"VILLAGE",
    "ks:ks_uagg_main":0,
    "name:eng_x_preferred":[
        "Laluhi"
    ],
    "wof:name":"Laluhi",
    "wof:placetype":"neighbourhood",
    "wof:population":3039
},
  "geometry": {"coordinates":[81.42931799999999,27.783145],"type":"Point"}
}