{
  "type": "Feature",
  "properties": {
    "iso:country":"IN",
    "ks:ks_name":"Uttar Baharat",
    "ks:ks_pop":210,
    "ks:ks_type":"VILLAGE",
    "ks:ks_uagg_main":0,
    "name:eng_x_preferred":[
        "Uttar Baharat"
    ],
    "wof:name":"Uttar Baharat",
    "wof:placetype":"neighbourhood",
    "wof:population":210
},
  "geometry": {"coordinates":[87.452759,22.679139],"type":"Point"}
}