{
  "type": "Feature",
  "properties": {
    "iso:country":"IN",
    "ks:ks_name":"Bheeminenivaripalle",
    "ks:ks_pop":228,
    "ks:ks_type":"HABITATION",
    "name:eng_x_preferred":[
        "Bheeminenivaripalle"
    ],
    "wof:name":"Bheeminenivaripalle",
    "wof:placetype":"locality",
    "wof:population":228
},
  "geometry": {"coordinates":[78.99172299999999,13.420634],"type":"Point"}
}