{
  "type": "Feature",
  "properties": {
    "iso:country":"IN",
    "ks:ks_name":"Putudumaha",
    "ks:ks_pop":377,
    "ks:ks_type":"VILLAGE",
    "name:eng_x_preferred":[
        "Putudumaha"
    ],
    "wof:name":"Putudumaha",
    "wof:placetype":"locality",
    "wof:population":377
},
  "geometry": {"coordinates":[84.027951,19.659721],"type":"Point"}
}