{
  "type": "Feature",
  "properties": {
    "gn:admin1_code":"9",
    "gn:admin2_code":"485.0",
    "gn:asciiname":"Waruna Rawalwala",
    "gn:country_code":"IN",
    "gn:dem":194,
    "gn:feature_class":"P",
    "gn:feature_code":"PPL",
    "gn:name":"War\u016bna R\u0101walw\u0101la",
    "gn:population":0,
    "gn:timezone":"Asia/Kolkata",
    "iso:country":"IN",
    "wof:name":"Waruna Rawalwala",
    "wof:placetype":"locality"
},
  "geometry": {"coordinates":[74.03426999999998,23.15455],"type":"Point"}
}