{
  "type": "Feature",
  "properties": {
    "gn:admin1_code":"35",
    "gn:admin2_code":"459.0",
    "gn:asciiname":"Sonal",
    "gn:country_code":"IN",
    "gn:dem":412,
    "gn:feature_class":"P",
    "gn:feature_code":"PPL",
    "gn:name":"Son\u0101l",
    "gn:population":0,
    "gn:timezone":"Asia/Kolkata",
    "iso:country":"IN",
    "wof:name":"Sonal",
    "wof:placetype":"locality"
},
  "geometry": {"coordinates":[78.12754,24.47606],"type":"Point"}
}