{
  "type": "Feature",
  "properties": {
    "iso:country":"IN",
    "ks:ks_alt_nam":"harni east vtola",
    "ks:ks_name":"Harni East Vtola",
    "ks:ks_pop":47,
    "ks:ks_type":"HABITATION",
    "name:eng_x_preferred":[
        "Harni East Vtola"
    ],
    "wof:name":"Harni East Vtola",
    "wof:placetype":"locality",
    "wof:population":47
},
  "geometry": {"coordinates":[86.59352699999999,24.628394],"type":"Point"}
}