{
  "type": "Feature",
  "properties": {
    "iso:country":"IN",
    "ks:ks_name":"Khalchi Guravwadi",
    "ks:ks_pop":142,
    "ks:ks_type":"HABITATION",
    "name:eng_x_preferred":[
        "Khalchi Guravwadi"
    ],
    "wof:name":"Khalchi Guravwadi",
    "wof:placetype":"locality",
    "wof:population":142
},
  "geometry": {"coordinates":[73.880336,16.164084],"type":"Point"}
}