{
  "type": "Feature",
  "properties": {
    "iso:country":"IN",
    "ks:ks_name":"Hempura",
    "ks:ks_pop":1275,
    "ks:ks_type":"HABITATION",
    "name:eng_x_preferred":[
        "Hempura"
    ],
    "wof:name":"Hempura",
    "wof:placetype":"locality",
    "wof:population":1275
},
  "geometry": {"coordinates":[74.99452100000001,27.039888],"type":"Point"}
}