{
  "type": "Feature",
  "properties": {
    "gn:admin1_code":"36.0",
    "gn:admin2_code":"179.0",
    "gn:asciiname":"Dargah Narayan Das",
    "gn:country_code":"IN",
    "gn:dem":106,
    "gn:feature_class":"P",
    "gn:feature_code":"PPL",
    "gn:name":"Darg\u0101h Nar\u0101yan D\u0101s",
    "gn:population":0,
    "gn:timezone":"Asia/Kolkata",
    "iso:country":"IN",
    "wof:name":"Dargah Narayan Das",
    "wof:placetype":"locality"
},
  "geometry": {"coordinates":[81.64421,26.57951],"type":"Point"}
}