{
  "type": "Feature",
  "properties": {
    "iso:country":"IN",
    "ks:ks_alt_nam":"BarlaMallaiahgumpu",
    "ks:ks_name":"Barlamallaiahgumpu",
    "ks:ks_pop":250,
    "ks:ks_type":"HABITATION",
    "name:eng_x_preferred":[
        "Barlamallaiahgumpu"
    ],
    "wof:name":"Barlamallaiahgumpu",
    "wof:placetype":"locality",
    "wof:population":250
},
  "geometry": {"coordinates":[80.20055499999999,17.971759],"type":"Point"}
}