{
  "type": "Feature",
  "properties": {
    "iso:country":"IN",
    "ks:ks_name":"Harizen Basti",
    "ks:ks_pop":962,
    "ks:ks_type":"HABITATION",
    "name:eng_x_preferred":[
        "Harizen Basti"
    ],
    "wof:name":"Harizen Basti",
    "wof:placetype":"locality",
    "wof:population":962
},
  "geometry": {"coordinates":[82.274811,24.830465],"type":"Point"}
}