{
  "type": "Feature",
  "properties": {
    "iso:country":"IN",
    "ks:ks_alt_nam":"Kasat pada",
    "ks:ks_name":"Kasat Pada",
    "ks:ks_pop":561,
    "ks:ks_type":"HABITATION",
    "name:eng_x_preferred":[
        "Kasat Pada"
    ],
    "wof:name":"Kasat Pada",
    "wof:placetype":"locality",
    "wof:population":561
},
  "geometry": {"coordinates":[73.306556,20.654694],"type":"Point"}
}