{
  "type": "Feature",
  "properties": {
    "gn:admin1_code":"36.0",
    "gn:admin2_code":"163.0",
    "gn:asciiname":"Sariyan",
    "gn:country_code":"IN",
    "gn:dem":138,
    "gn:feature_class":"P",
    "gn:feature_code":"PPL",
    "gn:name":"Sariy\u0101n",
    "gn:population":0,
    "gn:timezone":"Asia/Kolkata",
    "iso:country":"IN",
    "ks:ks_name":"Sariya",
    "ks:ks_pop":839,
    "ks:ks_type":"HABITATION",
    "name:eng_x_preferred":[
        "Sariya"
    ],
    "name:eng_x_variant":[
        "Sariyan"
    ],
    "wof:name":"Sariya",
    "wof:placetype":"locality",
    "wof:population":839
},
  "geometry": {"coordinates":[79.933764,26.729293],"type":"Point"}
}