{
  "type": "Feature",
  "properties": {
    "gn:admin1_code":"39.0",
    "gn:admin2_code":"63.0",
    "gn:asciiname":"Gokhuri",
    "gn:country_code":"IN",
    "gn:dem":1585,
    "gn:feature_class":"P",
    "gn:feature_code":"PPL",
    "gn:name":"Gokhuri",
    "gn:population":0,
    "gn:timezone":"Asia/Kolkata",
    "iso:country":"IN",
    "wof:name":"Gokhuri",
    "wof:placetype":"locality"
},
  "geometry": {"coordinates":[79.9902,29.87877000000001],"type":"Point"}
}