{
  "type": "Feature",
  "properties": {
    "iso:country":"IN",
    "ks:ks_alt_nam":"33Shiroor",
    "ks:ks_name":"33shiroor",
    "ks:ks_pop":489,
    "ks:ks_type":"HABITATION",
    "name:eng_x_preferred":[
        "33shiroor"
    ],
    "wof:name":"33shiroor",
    "wof:placetype":"locality",
    "wof:population":489
},
  "geometry": {"coordinates":[74.930004,13.342801],"type":"Point"}
}