{
  "type": "Feature",
  "properties": {
    "gn:admin1_code":"12.0",
    "gn:admin2_code":"17.0",
    "gn:asciiname":"Jantrog",
    "gn:country_code":"IN",
    "gn:dem":2268,
    "gn:feature_class":"P",
    "gn:feature_code":"PPL",
    "gn:name":"Jantrog",
    "gn:population":0,
    "gn:timezone":"Asia/Kolkata",
    "iso:country":"IN",
    "wof:name":"Jantrog",
    "wof:placetype":"locality"
},
  "geometry": {"coordinates":[75.17464,33.4002],"type":"Point"}
}