{
  "type": "Feature",
  "properties": {
    "gn:admin1_code":"37",
    "gn:admin2_code":"403.0",
    "gn:asciiname":"Jampali Rameshwar",
    "gn:country_code":"IN",
    "gn:dem":228,
    "gn:feature_class":"P",
    "gn:feature_code":"PPL",
    "gn:name":"J\u0101mp\u0101li R\u0101meshwar",
    "gn:population":0,
    "gn:timezone":"Asia/Kolkata",
    "iso:country":"IN",
    "wof:name":"Jampali Rameshwar",
    "wof:placetype":"neighbourhood"
},
  "geometry": {"coordinates":[83.30200000000001,21.84781],"type":"Point"}
}