{
  "type": "Feature",
  "properties": {
    "gn:admin1_code":"16.0",
    "gn:admin2_code":"510.0",
    "gn:asciiname":"Jambhrun",
    "gn:country_code":"IN",
    "gn:dem":340,
    "gn:feature_class":"P",
    "gn:feature_code":"PPL",
    "gn:name":"J\u0101mbhrun",
    "gn:population":0,
    "gn:timezone":"Asia/Kolkata",
    "iso:country":"IN",
    "wof:name":"Jambhrun",
    "wof:placetype":"locality"
},
  "geometry": {"coordinates":[77.78792,19.99208],"type":"Point"}
}