{
  "type": "Feature",
  "properties": {
    "gn:admin1_code":"40",
    "gn:admin2_code":"532.0",
    "gn:asciiname":"Tamsi",
    "gn:country_code":"IN",
    "gn:dem":284,
    "gn:feature_class":"P",
    "gn:feature_code":"PPL",
    "gn:name":"T\u0101msi",
    "gn:population":0,
    "gn:timezone":"Asia/Kolkata",
    "iso:country":"IN",
    "name:new_x_preferred":[
        "\u0924\u093e\u0902\u0938\u0940 \u092e\u0923\u094d\u0921\u0932"
    ],
    "name:pam_x_preferred":[
        "Tamsi"
    ],
    "name:tel_x_preferred":[
        "\u0c24\u0c3e\u0c02\u0c38\u0c40 \u0c2e\u0c02\u0c21\u0c32\u0c02"
    ],
    "name:und_x_variant":[
        "T\u0101msi"
    ],
    "name:vie_x_preferred":[
        "Tamsi"
    ],
    "wof:name":"Tamsi",
    "wof:placetype":"locality"
},
  "geometry": {"coordinates":[78.42384,19.6874],"type":"Point"}
}