{
  "type": "Feature",
  "properties": {
    "iso:country":"IN",
    "ks:ks_name":"Piranwadi",
    "ks:ks_pop":49,
    "ks:ks_type":"HABITATION",
    "name:eng_x_preferred":[
        "Piranwadi"
    ],
    "wof:name":"Piranwadi",
    "wof:placetype":"locality",
    "wof:population":49
},
  "geometry": {"coordinates":[74.521221,15.176056],"type":"Point"}
}