{
  "type": "Feature",
  "properties": {
    "gn:admin1_code":"37",
    "gn:admin2_code":"406.0",
    "gn:asciiname":"Mahamai",
    "gn:country_code":"IN",
    "gn:dem":380,
    "gn:feature_class":"P",
    "gn:feature_code":"PPL",
    "gn:name":"Mah\u0101m\u0101i",
    "gn:population":0,
    "gn:timezone":"Asia/Kolkata",
    "iso:country":"IN",
    "ks:ks_alt_nam":"Mah\u0101m\u0101i",
    "ks:ks_name":"Mahamai",
    "ks:ks_type":"VILLAGE",
    "name:bih_x_preferred":[
        "\u092e\u0939\u092e\u093e\u0907"
    ],
    "name:ceb_x_preferred":[
        "Mahamai"
    ],
    "name:eng_x_preferred":[
        "Mahamai"
    ],
    "name:eng_x_variant":[
        "Mah\u0101m\u0101i"
    ],
    "name:hin_x_preferred":[
        "\u092e\u0939\u092e\u093e\u0907"
    ],
    "name:mai_x_preferred":[
        "\u092e\u0939\u092e\u093e\u0907"
    ],
    "name:msa_x_preferred":[
        "Mahamai"
    ],
    "name:nep_x_preferred":[
        "\u092e\u0939\u092e\u093e\u0907"
    ],
    "name:new_x_preferred":[
        "\u092e\u0939\u092e\u093e\u0908"
    ],
    "name:nld_x_preferred":[
        "Mahamai"
    ],
    "name:pol_x_preferred":[
        "Mahamai"
    ],
    "wof:name":"Mahamai",
    "wof:placetype":"locality"
},
  "geometry": {"coordinates":[81.655024,22.427672],"type":"Point"}
}