{
  "type": "Feature",
  "properties": {
    "iso:country":"IN",
    "ks:ks_name":"Haodabhita",
    "ks:ks_pop":931,
    "ks:ks_type":"VILLAGE",
    "name:eng_x_preferred":[
        "Haodabhita"
    ],
    "wof:name":"Haodabhita",
    "wof:placetype":"locality",
    "wof:population":931
},
  "geometry": {"coordinates":[88.295756,26.606939],"type":"Point"}
}