{
  "type": "Feature",
  "properties": {
    "iso:country":"IN",
    "ks:ks_alt_nam":"PAYANI",
    "ks:ks_name":"Payani",
    "ks:ks_pop":65,
    "ks:ks_type":"HABITATION",
    "name:eng_x_preferred":[
        "Payani"
    ],
    "wof:name":"Payani",
    "wof:placetype":"locality",
    "wof:population":65
},
  "geometry": {"coordinates":[74.691766,17.252293],"type":"Point"}
}