{
  "type": "Feature",
  "properties": {
    "iso:country":"IN",
    "ks:ks_name":"Kasikhera",
    "ks:ks_pop":475,
    "ks:ks_type":"HABITATION",
    "ks:ks_uagg_main":0,
    "name:eng_x_preferred":[
        "Kasikhera"
    ],
    "wof:name":"Kasikhera",
    "wof:placetype":"neighbourhood",
    "wof:population":475
},
  "geometry": {"coordinates":[80.43889900000001,27.105133],"type":"Point"}
}