{
  "type": "Feature",
  "properties": {
    "iso:country":"IN",
    "ks:ks_name":"Nedunkulam North",
    "ks:ks_pop":233,
    "ks:ks_type":"HABITATION",
    "ks:ks_uagg_main":0,
    "name:eng_x_preferred":[
        "Nedunkulam North"
    ],
    "wof:name":"Nedunkulam North",
    "wof:placetype":"neighbourhood",
    "wof:population":233
},
  "geometry": {"coordinates":[78.71048399999999,10.968306],"type":"Point"}
}