{
  "type": "Feature",
  "properties": {
    "iso:country":"IN",
    "ks:ks_name":"Ganganagara",
    "ks:ks_pop":55,
    "ks:ks_type":"HABITATION",
    "name:eng_x_preferred":[
        "Ganganagara"
    ],
    "wof:name":"Ganganagara",
    "wof:placetype":"locality",
    "wof:population":55
},
  "geometry": {"coordinates":[77.287222,13.173889],"type":"Point"}
}