{
  "type": "Feature",
  "properties": {
    "iso:country":"IN",
    "ks:ks_name":"Viratwadi",
    "ks:ks_pop":178,
    "ks:ks_type":"HABITATION",
    "name:eng_x_preferred":[
        "Viratwadi"
    ],
    "wof:name":"Viratwadi",
    "wof:placetype":"locality",
    "wof:population":178
},
  "geometry": {"coordinates":[73.605278,17.162778],"type":"Point"}
}