{
  "type": "Feature",
  "properties": {
    "iso:country":"IN",
    "ks:ks_name":"Guhirpada",
    "ks:ks_pop":51,
    "ks:ks_type":"HABITATION",
    "name:eng_x_preferred":[
        "Guhirpada"
    ],
    "wof:name":"Guhirpada",
    "wof:placetype":"locality",
    "wof:population":51
},
  "geometry": {"coordinates":[73.057255,19.670422],"type":"Point"}
}