{
  "type": "Feature",
  "properties": {
    "gn:admin1_code":"35.0",
    "gn:admin2_code":"457.0",
    "gn:asciiname":"Sundarwahi",
    "gn:country_code":"IN",
    "gn:dem":620,
    "gn:feature_class":"P",
    "gn:feature_code":"PPL",
    "gn:name":"Sundarw\u0101h\u012b",
    "gn:population":0,
    "gn:timezone":"Asia/Kolkata",
    "iso:country":"IN",
    "ks:ks_alt_nam":"Sundarw\u0101h\u012b",
    "ks:ks_name":"Sundarwahi",
    "ks:ks_type":"VILLAGE",
    "name:eng_x_preferred":[
        "Sundarwahi"
    ],
    "name:eng_x_variant":[
        "Sundarw\u0101h\u012b"
    ],
    "wof:name":"Sundarwahi",
    "wof:placetype":"locality"
},
  "geometry": {"coordinates":[80.43394600000001,21.999304],"type":"Point"}
}