{
  "type": "Feature",
  "properties": {
    "iso:country":"IN",
    "ks:ks_name":"Korraiput",
    "ks:ks_pop":51,
    "ks:ks_type":"HABITATION",
    "name:eng_x_preferred":[
        "Korraiput"
    ],
    "wof:name":"Korraiput",
    "wof:placetype":"locality",
    "wof:population":51
},
  "geometry": {"coordinates":[82.495773,18.410667],"type":"Point"}
}