{
  "type": "Feature",
  "properties": {
    "iso:country":"IN",
    "ks:ks_name":"Mirzapur/gaura Narottam",
    "ks:ks_pop":16,
    "ks:ks_type":"HABITATION",
    "name:eng_x_preferred":[
        "Mirzapur/gaura Narottam"
    ],
    "wof:name":"Mirzapur/gaura Narottam",
    "wof:placetype":"locality",
    "wof:population":16
},
  "geometry": {"coordinates":[82.757667,27.219247],"type":"Point"}
}