{
  "type": "Feature",
  "properties": {
    "iso:country":"IN",
    "ks:ks_name":"Gulhutu",
    "ks:ks_pop":105,
    "ks:ks_type":"VILLAGE",
    "name:eng_x_preferred":[
        "Gulhutu"
    ],
    "wof:name":"Gulhutu",
    "wof:placetype":"locality",
    "wof:population":105
},
  "geometry": {"coordinates":[84.855328,24.152146],"type":"Point"}
}