{
  "type": "Feature",
  "properties": {
    "iso:country":"IN",
    "ks:ks_name":"Dewoolwadi",
    "ks:ks_pop":74,
    "ks:ks_type":"HABITATION",
    "name:eng_x_preferred":[
        "Dewoolwadi"
    ],
    "wof:name":"Dewoolwadi",
    "wof:placetype":"locality",
    "wof:population":74
},
  "geometry": {"coordinates":[73.928028,15.812389],"type":"Point"}
}