{
  "type": "Feature",
  "properties": {
    "iso:country":"IN",
    "ks:ks_name":"Bilagam",
    "ks:ks_pop":135,
    "ks:ks_type":"VILLAGE",
    "name:eng_x_preferred":[
        "Bilagam"
    ],
    "wof:name":"Bilagam",
    "wof:placetype":"locality",
    "wof:population":135
},
  "geometry": {"coordinates":[84.393199,18.980436],"type":"Point"}
}