{
  "type": "Feature",
  "properties": {
    "iso:country":"IN",
    "ks:ks_alt_nam":"3rd Mukku PCM",
    "ks:ks_name":"3rd Mukku Pcm",
    "ks:ks_pop":400,
    "ks:ks_type":"HABITATION",
    "name:eng_x_preferred":[
        "3rd Mukku Pcm"
    ],
    "wof:name":"3rd Mukku Pcm",
    "wof:placetype":"locality",
    "wof:population":400
},
  "geometry": {"coordinates":[76.472455,10.501258],"type":"Point"}
}