{
  "type": "Feature",
  "properties": {
    "gn:admin1_code":"13.0",
    "gn:admin2_code":"590.0",
    "gn:asciiname":"Annakunnu",
    "gn:country_code":"IN",
    "gn:dem":900,
    "gn:feature_class":"P",
    "gn:feature_code":"PPL",
    "gn:name":"Annakunnu",
    "gn:population":0,
    "gn:timezone":"Asia/Kolkata",
    "iso:country":"IN",
    "wof:name":"Annakunnu",
    "wof:placetype":"locality"
},
  "geometry": {"coordinates":[76.28594,11.60164],"type":"Point"}
}