{
  "type": "Feature",
  "properties": {
    "iso:country":"IN",
    "ks:ks_name":"Durga",
    "ks:ks_pop":1145,
    "ks:ks_type":"VILLAGE",
    "ks:ks_uagg_main":0,
    "name:eng_x_preferred":[
        "Durga"
    ],
    "wof:name":"Durga",
    "wof:placetype":"neighbourhood",
    "wof:population":1145
},
  "geometry": {"coordinates":[88.449583,22.290349],"type":"Point"}
}