{
  "type": "Feature",
  "properties": {
    "iso:country":"IN",
    "ks:ks_name":"Sarwangpur",
    "ks:ks_pop":0,
    "ks:ks_type":"VILLAGE",
    "name:eng_x_preferred":[
        "Sarwangpur"
    ],
    "wof:name":"Sarwangpur",
    "wof:placetype":"locality",
    "wof:population":0
},
  "geometry": {"coordinates":[79.903767,27.763969],"type":"Point"}
}