{
  "type": "Feature",
  "properties": {
    "gn:admin1_code":"2.0",
    "gn:admin2_code":"542.0",
    "gn:asciiname":"Garnayudupeta",
    "gn:country_code":"IN",
    "gn:dem":29,
    "gn:feature_class":"P",
    "gn:feature_code":"PPL",
    "gn:name":"Garn\u0101yudupeta",
    "gn:population":0,
    "gn:timezone":"Asia/Kolkata",
    "iso:country":"IN",
    "wof:name":"Garnayudupeta",
    "wof:placetype":"locality"
},
  "geometry": {"coordinates":[83.82224000000002,18.41597],"type":"Point"}
}