{
  "type": "Feature",
  "properties": {
    "gn:admin1_code":"36",
    "gn:admin2_code":"132.0",
    "gn:asciiname":"Hathauli",
    "gn:country_code":"IN",
    "gn:dem":300,
    "gn:feature_class":"P",
    "gn:feature_code":"PPL",
    "gn:name":"Hathauli",
    "gn:population":0,
    "gn:timezone":"Asia/Kolkata",
    "iso:country":"IN",
    "wof:name":"Hathauli",
    "wof:placetype":"locality"
},
  "geometry": {"coordinates":[77.575,30.19935],"type":"Point"}
}