{
  "type": "Feature",
  "properties": {
    "iso:country":"IN",
    "ks:ks_name":"Thatha Sodhan",
    "ks:ks_pop":179,
    "ks:ks_type":"VILLAGE",
    "ks:ks_uagg_main":0,
    "name:eng_x_preferred":[
        "Thatha Sodhan"
    ],
    "wof:name":"Thatha Sodhan",
    "wof:placetype":"neighbourhood",
    "wof:population":179
},
  "geometry": {"coordinates":[83.260829,25.781981],"type":"Point"}
}