{
  "type": "Feature",
  "properties": {
    "iso:country":"IN",
    "ks:ks_alt_nam":"K\u0101lankudiyiruppu",
    "ks:ks_name":"Kalankudiyiruppu",
    "ks:ks_type":"VILLAGE",
    "ks:ks_uagg_main":0,
    "name:eng_x_preferred":[
        "Kalankudiyiruppu"
    ],
    "name:eng_x_variant":[
        "K\u0101lankudiyiruppu"
    ],
    "wof:name":"Kalankudiyiruppu",
    "wof:placetype":"neighbourhood"
},
  "geometry": {"coordinates":[78.02897900000001,8.435585],"type":"Point"}
}