{
  "type": "Feature",
  "properties": {
    "gn:admin1_code":"35.0",
    "gn:admin2_code":"439.0",
    "gn:asciiname":"Kishanpura",
    "gn:country_code":"IN",
    "gn:dem":589,
    "gn:feature_class":"P",
    "gn:feature_code":"PPL",
    "gn:name":"Kishanpura",
    "gn:population":0,
    "gn:timezone":"Asia/Kolkata",
    "iso:country":"IN",
    "wof:name":"Kishanpura",
    "wof:placetype":"locality"
},
  "geometry": {"coordinates":[75.65716999999999,22.65728],"type":"Point"}
}