{
  "type": "Feature",
  "properties": {
    "gn:admin1_code":"37.0",
    "gn:admin2_code":"400.0",
    "gn:asciiname":"Jaiti",
    "gn:country_code":"IN",
    "gn:dem":519,
    "gn:feature_class":"P",
    "gn:feature_code":"PPL",
    "gn:name":"Jaiti",
    "gn:population":0,
    "gn:timezone":"Asia/Kolkata",
    "iso:country":"IN",
    "ks:ks_name":"Jaiti",
    "ks:ks_pop":583,
    "ks:ks_type":"VILLAGE",
    "name:eng_x_preferred":[
        "Jaiti"
    ],
    "wof:name":"Jaiti",
    "wof:placetype":"locality",
    "wof:population":583
},
  "geometry": {"coordinates":[81.760558,23.559305],"type":"Point"}
}