{
  "type": "Feature",
  "properties": {
    "gn:admin1_code":"37.0",
    "gn:admin2_code":"400.0",
    "gn:asciiname":"Jaiti",
    "gn:country_code":"IN",
    "gn:dem":519,
    "gn:feature_class":"P",
    "gn:feature_code":"PPL",
    "gn:name":"Jaiti",
    "gn:population":0,
    "gn:timezone":"Asia/Kolkata",
    "iso:country":"IN",
    "wof:name":"Jaiti",
    "wof:placetype":"locality"
},
  "geometry": {"coordinates":[81.76093,23.56698],"type":"Point"}
}