{
  "type": "Feature",
  "properties": {
    "iso:country":"IN",
    "ks:ks_name":"Madpharas",
    "ks:ks_pop":67,
    "ks:ks_type":"HABITATION",
    "name:eng_x_preferred":[
        "Madpharas"
    ],
    "wof:name":"Madpharas",
    "wof:placetype":"locality",
    "wof:population":67
},
  "geometry": {"coordinates":[73.70365099999999,27.264192],"type":"Point"}
}