{
  "type": "Feature",
  "properties": {
    "iso:country":"IN",
    "ks:ks_name":"Gad Ichamal Falia",
    "ks:ks_pop":380,
    "ks:ks_type":"HABITATION",
    "name:eng_x_preferred":[
        "Gad Ichamal Falia"
    ],
    "wof:name":"Gad Ichamal Falia",
    "wof:placetype":"locality",
    "wof:population":380
},
  "geometry": {"coordinates":[73.2465,20.173167],"type":"Point"}
}