{
  "type": "Feature",
  "properties": {
    "gn:admin1_code":"35",
    "gn:admin2_code":"427.0",
    "gn:asciiname":"Sandai",
    "gn:country_code":"IN",
    "gn:dem":390,
    "gn:feature_class":"P",
    "gn:feature_code":"PPL",
    "gn:name":"Sandai",
    "gn:population":0,
    "gn:timezone":"Asia/Kolkata",
    "iso:country":"IN",
    "ks:ks_name":"Sandai",
    "ks:ks_pop":552,
    "ks:ks_type":"VILLAGE",
    "ks:ks_uagg_main":0,
    "name:eng_x_preferred":[
        "Sandai"
    ],
    "name:tam_x_preferred":[
        "\u0b9a\u0ba3\u0bcd\u0b9f\u0bc8"
    ],
    "wof:name":"Sandai",
    "wof:placetype":"neighbourhood",
    "wof:population":552
},
  "geometry": {"coordinates":[79.15328700000001,23.653695],"type":"Point"}
}