{
  "type": "Feature",
  "properties": {
    "iso:country":"IN",
    "ks:ks_name":"Kismatshimla",
    "ks:ks_pop":796,
    "ks:ks_type":"VILLAGE",
    "ks:ks_uagg_main":0,
    "name:eng_x_preferred":[
        "Kismatshimla"
    ],
    "wof:name":"Kismatshimla",
    "wof:placetype":"neighbourhood",
    "wof:population":796
},
  "geometry": {"coordinates":[88.265945,25.689548],"type":"Point"}
}