{
  "type": "Feature",
  "properties": {
    "gn:admin1_code":"23",
    "gn:admin2_code":"39.0",
    "gn:asciiname":"Firozpur",
    "gn:country_code":"IN",
    "gn:dem":250,
    "gn:feature_class":"P",
    "gn:feature_code":"PPL",
    "gn:name":"F\u012brozpur",
    "gn:population":0,
    "gn:timezone":"Asia/Kolkata",
    "iso:country":"IN",
    "wof:name":"Firozpur",
    "wof:placetype":"locality"
},
  "geometry": {"coordinates":[75.95999999999999,31.14426],"type":"Point"}
}