{
  "type": "Feature",
  "properties": {
    "gn:admin1_code":"35",
    "gn:admin2_code":"426.0",
    "gn:asciiname":"Kamalpura",
    "gn:country_code":"IN",
    "gn:dem":342,
    "gn:feature_class":"P",
    "gn:feature_code":"PPL",
    "gn:name":"Kamalpura",
    "gn:population":0,
    "gn:timezone":"Asia/Kolkata",
    "iso:country":"IN",
    "wof:name":"Kamalpura",
    "wof:placetype":"locality"
},
  "geometry": {"coordinates":[80.30259000000002,24.43995],"type":"Point"}
}