{
  "type": "Feature",
  "properties": {
    "iso:country":"IN",
    "ks:ks_alt_nam":"DodkaEnhoor",
    "ks:ks_name":"Dodkaenhoor",
    "ks:ks_pop":210,
    "ks:ks_type":"HABITATION",
    "name:eng_x_preferred":[
        "Dodkaenhoor"
    ],
    "wof:name":"Dodkaenhoor",
    "wof:placetype":"locality",
    "wof:population":210
},
  "geometry": {"coordinates":[80.913343,20.141938],"type":"Point"}
}