{
  "type": "Feature",
  "properties": {
    "gn:admin1_code":"35.0",
    "gn:admin2_code":"438.0",
    "gn:asciiname":"Kalipura",
    "gn:country_code":"IN",
    "gn:dem":536,
    "gn:feature_class":"P",
    "gn:feature_code":"PPL",
    "gn:name":"K\u0101l\u012bpura",
    "gn:population":0,
    "gn:timezone":"Asia/Kolkata",
    "iso:country":"IN",
    "wof:name":"Kalipura",
    "wof:placetype":"locality"
},
  "geometry": {"coordinates":[75.54618000000001,22.45335],"type":"Point"}
}