{
  "type": "Feature",
  "properties": {
    "iso:country":"IN",
    "ks:ks_name":"Matijapur",
    "ks:ks_pop":757,
    "ks:ks_type":"VILLAGE",
    "ks:ks_uagg_main":0,
    "name:eng_x_preferred":[
        "Matijapur"
    ],
    "wof:name":"Matijapur",
    "wof:placetype":"neighbourhood",
    "wof:population":757
},
  "geometry": {"coordinates":[87.381322,23.861191],"type":"Point"}
}