{
  "type": "Feature",
  "properties": {
    "iso:country":"IN",
    "ks:ks_name":"Gharkul",
    "ks:ks_pop":354,
    "ks:ks_type":"HABITATION",
    "name:eng_x_preferred":[
        "Gharkul"
    ],
    "wof:name":"Gharkul",
    "wof:placetype":"locality",
    "wof:population":354
},
  "geometry": {"coordinates":[73.319734,17.154301],"type":"Point"}
}