{
  "type": "Feature",
  "properties": {
    "iso:country":"IN",
    "ks:ks_name":"Mathurapada",
    "ks:ks_pop":331,
    "ks:ks_type":"HABITATION",
    "name:eng_x_preferred":[
        "Mathurapada"
    ],
    "wof:name":"Mathurapada",
    "wof:placetype":"locality",
    "wof:population":331
},
  "geometry": {"coordinates":[82.558539,19.775408],"type":"Point"}
}