{
  "type": "Feature",
  "properties": {
    "gn:admin1_code":"35",
    "gn:admin2_code":"425.0",
    "gn:asciiname":"Shivpuri",
    "gn:country_code":"IN",
    "gn:dem":142,
    "gn:feature_class":"P",
    "gn:feature_code":"PPL",
    "gn:name":"Shivpuri",
    "gn:population":0,
    "gn:timezone":"Asia/Kolkata",
    "iso:country":"IN",
    "name:ben_x_preferred":[
        "\u09b6\u09bf\u09ac\u09aa\u09c1\u09b0\u09bf"
    ],
    "name:bih_x_preferred":[
        "\u0936\u093f\u0935\u092a\u0941\u0930\u0940"
    ],
    "name:bpy_x_preferred":[
        "\u09b6\u09bf\u09ac\u09aa\u09c1\u09b0\u09bf"
    ],
    "name:ceb_x_preferred":[
        "Shivpur\u012b"
    ],
    "name:deu_x_preferred":[
        "Shivpuri"
    ],
    "name:fra_x_preferred":[
        "Shivpuri"
    ],
    "name:guj_x_preferred":[
        "\u0ab6\u0abf\u0ab5\u0aaa\u0ac1\u0ab0\u0ac0"
    ],
    "name:hif_x_preferred":[
        "Shivpuri"
    ],
    "name:hin_x_preferred":[
        "\u0936\u093f\u0935\u092a\u0941\u0930\u0940"
    ],
    "name:ita_x_preferred":[
        "Shivpuri"
    ],
    "name:mar_x_preferred":[
        "\u0936\u093f\u0935\u092a\u0941\u0930\u0940"
    ],
    "name:mlg_x_preferred":[
        "Shivpuri"
    ],
    "name:msa_x_preferred":[
        "Shivpuri"
    ],
    "name:ori_x_preferred":[
        "\u0b36\u0b3f\u0b2c\u0b2a\u0b41\u0b30\u0b3f"
    ],
    "name:pol_x_preferred":[
        "\u015aiwapuri"
    ],
    "name:por_x_preferred":[
        "Shivpuri"
    ],
    "name:rus_x_preferred":[
        "\u0428\u0438\u0432\u043f\u0443\u0440\u0438"
    ],
    "name:san_x_preferred":[
        "\u0936\u093f\u0935\u092a\u0941\u0930\u0940"
    ],
    "name:spa_x_preferred":[
        "Shivpuri"
    ],
    "name:swe_x_preferred":[
        "Shivpuri"
    ],
    "name:urd_x_preferred":[
        "\u0634\u0648\u067e\u0648\u0631\u06cc"
    ],
    "name:vie_x_preferred":[
        "Shivpuri"
    ],
    "name:war_x_preferred":[
        "Shivpuri"
    ],
    "name:zho_x_preferred":[
        "\u65af\u5e0c\u6c83\u666e\u91cc"
    ],
    "wof:name":"Shivpuri",
    "wof:placetype":"locality"
},
  "geometry": {"coordinates":[80.37895999999998,25.22626],"type":"Point"}
}