{
  "type": "Feature",
  "properties": {
    "gn:admin1_code":"35",
    "gn:admin2_code":"425.0",
    "gn:asciiname":"Shivpuri",
    "gn:country_code":"IN",
    "gn:dem":142,
    "gn:feature_class":"P",
    "gn:feature_code":"PPL",
    "gn:name":"Shivpuri",
    "gn:population":0,
    "gn:timezone":"Asia/Kolkata",
    "iso:country":"IN",
    "wof:name":"Shivpuri",
    "wof:placetype":"locality"
},
  "geometry": {"coordinates":[80.37895999999998,25.22626],"type":"Point"}
}