{
  "type": "Feature",
  "properties": {
    "iso:country":"IN",
    "ks:ks_name":"Hadimbh",
    "ks:ks_pop":53,
    "ks:ks_type":"VILLAGE",
    "name:eng_x_preferred":[
        "Hadimbh"
    ],
    "wof:name":"Hadimbh",
    "wof:placetype":"locality",
    "wof:population":53
},
  "geometry": {"coordinates":[78.67688200000001,30.279929],"type":"Point"}
}