{
  "type": "Feature",
  "properties": {
    "iso:country":"IN",
    "ks:ks_alt_nam":"BHANAWATON KA KHERA",
    "ks:ks_name":"Bhanawaton Ka Khera",
    "ks:ks_pop":204,
    "ks:ks_type":"HABITATION",
    "name:eng_x_preferred":[
        "Bhanawaton Ka Khera"
    ],
    "wof:name":"Bhanawaton Ka Khera",
    "wof:placetype":"locality",
    "wof:population":204
},
  "geometry": {"coordinates":[74.62909500000001,23.926263],"type":"Point"}
}