{
  "type": "Feature",
  "properties": {
    "iso:country":"IN",
    "ks:ks_name":"Dabhad Bhatiyan",
    "ks:ks_pop":498,
    "ks:ks_type":"VILLAGE",
    "name:eng_x_preferred":[
        "Dabhad Bhatiyan"
    ],
    "wof:name":"Dabhad Bhatiyan",
    "wof:placetype":"locality",
    "wof:population":498
},
  "geometry": {"coordinates":[71.836647,25.533439],"type":"Point"}
}