{
  "type": "Feature",
  "properties": {
    "iso:country":"IN",
    "ks:ks_name":"Mamdabad",
    "ks:ks_pop":0,
    "ks:ks_type":"VILLAGE",
    "name:eng_x_preferred":[
        "Mamdabad"
    ],
    "wof:name":"Mamdabad",
    "wof:placetype":"locality",
    "wof:population":0
},
  "geometry": {"coordinates":[77.546007,20.443825],"type":"Point"}
}