{
  "type": "Feature",
  "properties": {
    "iso:country":"IN",
    "ks:ks_name":"Khadengapada",
    "ks:ks_pop":13,
    "ks:ks_type":"VILLAGE",
    "name:eng_x_preferred":[
        "Khadengapada"
    ],
    "wof:name":"Khadengapada",
    "wof:placetype":"locality",
    "wof:population":13
},
  "geometry": {"coordinates":[85.59591500000001,21.765466],"type":"Point"}
}