{
  "type": "Feature",
  "properties": {
    "gn:admin1_code":"19.0",
    "gn:admin2_code":"574.0",
    "gn:asciiname":"Vuduve Mane",
    "gn:country_code":"IN",
    "gn:dem":939,
    "gn:feature_class":"P",
    "gn:feature_code":"PPL",
    "gn:name":"Vuduve Mane",
    "gn:population":0,
    "gn:timezone":"Asia/Kolkata",
    "iso:country":"IN",
    "wof:name":"Vuduve Mane",
    "wof:placetype":"locality"
},
  "geometry": {"coordinates":[75.84626999999998,12.79566],"type":"Point"}
}