{
  "type": "Feature",
  "properties": {
    "gn:admin1_code":"03",
    "gn:admin2_code":"305.0",
    "gn:asciiname":"Nam Dabaka",
    "gn:country_code":"IN",
    "gn:dem":75,
    "gn:feature_class":"P",
    "gn:feature_code":"PPL",
    "gn:name":"N\u0101m Dabak\u0101",
    "gn:population":0,
    "gn:timezone":"Asia/Kolkata",
    "iso:country":"IN",
    "name:asm_x_preferred":[
        "\u09a1\u09ac\u0995\u09be"
    ],
    "name:ben_x_preferred":[
        "\u09a6\u09ac\u0995\u09be"
    ],
    "name:bpy_x_preferred":[
        "\u09a6\u09cb\u09ac\u09cb\u0995\u09be"
    ],
    "name:ceb_x_preferred":[
        "N\u0101m Dabak\u0101"
    ],
    "name:ita_x_preferred":[
        "Doboka"
    ],
    "name:msa_x_preferred":[
        "Doboka"
    ],
    "name:new_x_preferred":[
        "\u0926\u094b\u092c\u094b\u0915\u093e"
    ],
    "name:nld_x_preferred":[
        "Doboka"
    ],
    "name:por_x_preferred":[
        "Doboka"
    ],
    "name:swe_x_preferred":[
        "N\u0101m Dabak\u0101"
    ],
    "name:und_x_variant":[
        "Dabaka",
        "N\u0101m Dabak\u0101"
    ],
    "name:vie_x_preferred":[
        "Doboka"
    ],
    "name:zho_x_preferred":[
        "\u591a\u535a\u5361"
    ],
    "wof:name":"Nam Dabaka",
    "wof:placetype":"locality"
},
  "geometry": {"coordinates":[92.85198,26.09875],"type":"Point"}
}