{
  "type": "Feature",
  "properties": {
    "gn:admin1_code":"03",
    "gn:admin2_code":"305.0",
    "gn:asciiname":"Nam Dabaka",
    "gn:country_code":"IN",
    "gn:dem":75,
    "gn:feature_class":"P",
    "gn:feature_code":"PPL",
    "gn:name":"N\u0101m Dabak\u0101",
    "gn:population":0,
    "gn:timezone":"Asia/Kolkata",
    "iso:country":"IN",
    "name:und_x_variant":[
        "Dabaka",
        "N\u0101m Dabak\u0101"
    ],
    "wof:name":"Nam Dabaka",
    "wof:placetype":"locality"
},
  "geometry": {"coordinates":[92.85198,26.09875],"type":"Point"}
}