{
  "type": "Feature",
  "properties": {
    "iso:country":"IN",
    "ks:ks_name":"Agatha Varappadu",
    "ks:ks_pop":1406,
    "ks:ks_type":"VILLAGE",
    "ks:ks_uagg_main":0,
    "name:eng_x_preferred":[
        "Agatha Varappadu"
    ],
    "wof:name":"Agatha Varappadu",
    "wof:placetype":"neighbourhood",
    "wof:population":1406
},
  "geometry": {"coordinates":[80.463532,16.327812],"type":"Point"}
}