{
  "type": "Feature",
  "properties": {
    "iso:country":"IN",
    "ks:ks_name":"Beersapara",
    "ks:ks_pop":120,
    "ks:ks_type":"HABITATION",
    "name:eng_x_preferred":[
        "Beersapara"
    ],
    "wof:name":"Beersapara",
    "wof:placetype":"locality",
    "wof:population":120
},
  "geometry": {"coordinates":[82.705403,23.402567],"type":"Point"}
}