{
  "type": "Feature",
  "properties": {
    "iso:country":"IN",
    "ks:ks_name":"Jevanathopu",
    "ks:ks_pop":18,
    "ks:ks_type":"HABITATION",
    "name:eng_x_preferred":[
        "Jevanathopu"
    ],
    "wof:name":"Jevanathopu",
    "wof:placetype":"locality",
    "wof:population":18
},
  "geometry": {"coordinates":[78.62331500000001,13.775214],"type":"Point"}
}