{
  "type": "Feature",
  "properties": {
    "iso:country":"IN",
    "ks:ks_name":"Sibpur",
    "ks:ks_pop":4764,
    "ks:ks_type":"VILLAGE",
    "ks:ks_uagg_main":0,
    "name:eng_x_preferred":[
        "Sibpur"
    ],
    "wof:name":"Sibpur",
    "wof:placetype":"neighbourhood",
    "wof:population":4764
},
  "geometry": {"coordinates":[88.507349,23.645986],"type":"Point"}
}