{
  "type": "Feature",
  "properties": {
    "iso:country":"IN",
    "ks:ks_name":"Kadamwadi",
    "ks:ks_pop":275,
    "ks:ks_type":"HABITATION",
    "name:eng_x_preferred":[
        "Kadamwadi"
    ],
    "wof:name":"Kadamwadi",
    "wof:placetype":"locality",
    "wof:population":275
},
  "geometry": {"coordinates":[73.749634,16.06232],"type":"Point"}
}