{
  "type": "Feature",
  "properties": {
    "iso:country":"IN",
    "ks:ks_alt_nam":"moolakudi",
    "ks:ks_name":"Moolakudi",
    "ks:ks_pop":265,
    "ks:ks_type":"HABITATION",
    "name:eng_x_preferred":[
        "Moolakudi"
    ],
    "wof:name":"Moolakudi",
    "wof:placetype":"locality",
    "wof:population":265
},
  "geometry": {"coordinates":[78.956138,10.781958],"type":"Point"}
}