{
  "type": "Feature",
  "properties": {
    "gn:admin1_code":"35",
    "gn:admin2_code":"449.0",
    "gn:asciiname":"Sadhpura",
    "gn:country_code":"IN",
    "gn:dem":411,
    "gn:feature_class":"P",
    "gn:feature_code":"PPL",
    "gn:name":"S\u0101dhpura",
    "gn:population":0,
    "gn:timezone":"Asia/Kolkata",
    "iso:country":"IN",
    "ks:ks_alt_nam":"S\u0101dhpura",
    "ks:ks_name":"Sadhpura",
    "ks:ks_pop":612,
    "ks:ks_type":"VILLAGE",
    "name:eng_x_preferred":[
        "Sadhpura"
    ],
    "name:eng_x_variant":[
        "S\u0101dhpura"
    ],
    "wof:name":"Sadhpura",
    "wof:placetype":"locality",
    "wof:population":612
},
  "geometry": {"coordinates":[77.743437,22.353616],"type":"Point"}
}