{
  "type": "Feature",
  "properties": {
    "iso:country":"IN",
    "ks:ks_name":"Gundepalle",
    "ks:ks_pop":387,
    "ks:ks_type":"HABITATION",
    "name:eng_x_preferred":[
        "Gundepalle"
    ],
    "wof:name":"Gundepalle",
    "wof:placetype":"locality",
    "wof:population":387
},
  "geometry": {"coordinates":[79.551813,13.345363],"type":"Point"}
}