{
  "type": "Feature",
  "properties": {
    "gn:admin1_code":"12",
    "gn:admin2_code":"3.0",
    "gn:asciiname":"Markha",
    "gn:country_code":"IN",
    "gn:dem":3786,
    "gn:feature_class":"P",
    "gn:feature_code":"PPL",
    "gn:name":"Markha",
    "gn:population":0,
    "gn:timezone":"Asia/Kolkata",
    "iso:country":"IN",
    "wof:name":"Markha",
    "wof:placetype":"locality"
},
  "geometry": {"coordinates":[77.42384,33.88633],"type":"Point"}
}