{
  "type": "Feature",
  "properties": {
    "gn:admin1_code":"12",
    "gn:admin2_code":"3.0",
    "gn:asciiname":"Markha",
    "gn:country_code":"IN",
    "gn:dem":3786,
    "gn:feature_class":"P",
    "gn:feature_code":"PPL",
    "gn:name":"Markha",
    "gn:population":0,
    "gn:timezone":"Asia/Kolkata",
    "iso:country":"IN",
    "name:ara_x_preferred":[
        "\u0646\u0647\u0631 \u0645\u0627\u0631\u062e\u0627"
    ],
    "name:ben_x_preferred":[
        "\u09ae\u09be\u09b0\u0996\u09be"
    ],
    "name:che_x_preferred":[
        "\u041c\u0430\u0440\u0445\u0430"
    ],
    "name:ell_x_preferred":[
        "\u039c\u03ac\u03c1\u03c7\u03b1"
    ],
    "name:fas_x_preferred":[
        "\u0645\u0627\u0631\u06a9\u0647\u0627"
    ],
    "name:heb_x_preferred":[
        "\u05de\u05e8\u05e7\u05d5\u05d1\u05e6'\u05d9"
    ],
    "name:hin_x_preferred":[
        "\u092e\u0930\u0916\u093e"
    ],
    "name:ind_x_preferred":[
        "Markha"
    ],
    "name:kor_x_preferred":[
        "\ub9c8\uce74"
    ],
    "name:por_x_preferred":[
        "Markha"
    ],
    "name:swe_x_preferred":[
        "Markha"
    ],
    "name:urd_x_preferred":[
        "\u0645\u0627\u0631\u06a9\u06be\u0627"
    ],
    "name:vie_x_preferred":[
        "S\u00f4ng Markha"
    ],
    "wof:name":"Markha",
    "wof:placetype":"locality"
},
  "geometry": {"coordinates":[77.42384,33.88633],"type":"Point"}
}