{
  "type": "Feature",
  "properties": {
    "gn:admin1_code":"16.0",
    "gn:admin2_code":"497.0",
    "gn:asciiname":"Bhogvada Khurd",
    "gn:country_code":"IN",
    "gn:dem":304,
    "gn:feature_class":"P",
    "gn:feature_code":"PPL",
    "gn:name":"Bhogv\u0101da Khurd",
    "gn:population":0,
    "gn:timezone":"Asia/Kolkata",
    "iso:country":"IN",
    "wof:name":"Bhogvada Khurd",
    "wof:placetype":"locality"
},
  "geometry": {"coordinates":[74.25944,21.84502],"type":"Point"}
}