{
  "type": "Feature",
  "properties": {
    "iso:country":"IN",
    "ks:ks_name":"Bidyanagar TE pt I",
    "ks:ks_pop":1502,
    "ks:ks_type":"VILLAGE",
    "name:eng_x_preferred":[
        "Bidyanagar TE pt I"
    ],
    "wof:name":"Bidyanagar TE pt I",
    "wof:placetype":"locality",
    "wof:population":1502
},
  "geometry": {"coordinates":[92.465378,24.522303],"type":"Point"}
}