{
  "type": "Feature",
  "properties": {
    "iso:country":"IN",
    "ks:ks_name":"Ant",
    "ks:ks_pop":257,
    "ks:ks_type":"VILLAGE",
    "name:eng_x_preferred":[
        "Ant"
    ],
    "wof:name":"Ant",
    "wof:placetype":"locality",
    "wof:population":257
},
  "geometry": {"coordinates":[74.441508,23.92487],"type":"Point"}
}