{
  "type": "Feature",
  "properties": {
    "iso:country":"IN",
    "ks:ks_name":"Bankawas",
    "ks:ks_pop":2016,
    "ks:ks_type":"VILLAGE",
    "name:eng_x_preferred":[
        "Bankawas"
    ],
    "wof:name":"Bankawas",
    "wof:placetype":"locality",
    "wof:population":2016
},
  "geometry": {"coordinates":[73.233889,24.730285],"type":"Point"}
}