{
  "type": "Feature",
  "properties": {
    "gn:admin1_code":"16",
    "gn:admin2_code":"529.0",
    "gn:asciiname":"Shirala",
    "gn:country_code":"IN",
    "gn:dem":269,
    "gn:feature_class":"P",
    "gn:feature_code":"PPL",
    "gn:name":"Shir\u0101la",
    "gn:population":0,
    "gn:timezone":"Asia/Kolkata",
    "iso:country":"IN",
    "wof:name":"Shirala",
    "wof:placetype":"locality"
},
  "geometry": {"coordinates":[73.86199000000001,16.46418],"type":"Point"}
}