{
  "type": "Feature",
  "properties": {
    "iso:country":"IN",
    "ks:ks_name":"Arayaluanakalthadam",
    "ks:ks_pop":953,
    "ks:ks_type":"HABITATION",
    "name:eng_x_preferred":[
        "Arayaluanakalthadam"
    ],
    "wof:name":"Arayaluanakalthadam",
    "wof:placetype":"locality",
    "wof:population":953
},
  "geometry": {"coordinates":[76.73236900000001,9.421069],"type":"Point"}
}