{
  "type": "Feature",
  "properties": {
    "iso:country":"IN",
    "ks:ks_name":"Godaron Ka Bas",
    "ks:ks_pop":73,
    "ks:ks_type":"HABITATION",
    "name:eng_x_preferred":[
        "Godaron Ka Bas"
    ],
    "wof:name":"Godaron Ka Bas",
    "wof:placetype":"locality",
    "wof:population":73
},
  "geometry": {"coordinates":[74.698865,27.642182],"type":"Point"}
}