{
  "type": "Feature",
  "properties": {
    "iso:country":"IN",
    "ks:ks_alt_nam":"JOLAHAN PURWA",
    "ks:ks_name":"Jolahan Purwa",
    "ks:ks_pop":44,
    "ks:ks_type":"HABITATION",
    "ks:ks_uagg_main":0,
    "name:eng_x_preferred":[
        "Jolahan Purwa"
    ],
    "wof:name":"Jolahan Purwa",
    "wof:placetype":"neighbourhood",
    "wof:population":44
},
  "geometry": {"coordinates":[81.51066,27.579033],"type":"Point"}
}