{
  "type": "Feature",
  "properties": {
    "iso:country":"IN",
    "ks:ks_name":"Dakshin Odlabari",
    "ks:ks_pop":4280,
    "ks:ks_type":"URBAN",
    "name:eng_x_preferred":[
        "Dakshin Odlabari"
    ],
    "wof:name":"Dakshin Odlabari",
    "wof:placetype":"locality",
    "wof:population":4280
},
  "geometry": {"coordinates":[88.615407,26.837707],"type":"Point"}
}