{
  "type": "Feature",
  "properties": {
    "iso:country":"IN",
    "ks:ks_name":"Mahakalpura",
    "ks:ks_pop":607,
    "ks:ks_type":"VILLAGE",
    "name:eng_x_preferred":[
        "Mahakalpura"
    ],
    "wof:name":"Mahakalpura",
    "wof:placetype":"locality",
    "wof:population":607
},
  "geometry": {"coordinates":[74.80221400000001,22.354795],"type":"Point"}
}