{
  "type": "Feature",
  "properties": {
    "iso:country":"IN",
    "ks:ks_name":"Tetar Guda Para",
    "ks:ks_pop":559,
    "ks:ks_type":"HABITATION",
    "name:eng_x_preferred":[
        "Tetar Guda Para"
    ],
    "wof:name":"Tetar Guda Para",
    "wof:placetype":"locality",
    "wof:population":559
},
  "geometry": {"coordinates":[82.042266,19.341552],"type":"Point"}
}