{
  "type": "Feature",
  "properties": {
    "iso:country":"IN",
    "ks:ks_name":"Dhepaguda",
    "ks:ks_pop":57,
    "ks:ks_type":"HABITATION",
    "name:eng_x_preferred":[
        "Dhepaguda"
    ],
    "wof:name":"Dhepaguda",
    "wof:placetype":"locality",
    "wof:population":57
},
  "geometry": {"coordinates":[83.45891899999999,19.723895],"type":"Point"}
}