{
  "type": "Feature",
  "properties": {
    "iso:country":"IN",
    "ks:ks_name":"Nangalpalli",
    "ks:ks_pop":258,
    "ks:ks_type":"VILLAGE",
    "name:eng_x_preferred":[
        "Nangalpalli"
    ],
    "wof:name":"Nangalpalli",
    "wof:placetype":"locality",
    "wof:population":258
},
  "geometry": {"coordinates":[83.55580399999999,19.275359],"type":"Point"}
}