{
  "type": "Feature",
  "properties": {
    "iso:country":"IN",
    "ks:ks_name":"Srinathpur",
    "ks:ks_pop":206,
    "ks:ks_type":"VILLAGE",
    "name:eng_x_preferred":[
        "Srinathpur"
    ],
    "wof:name":"Srinathpur",
    "wof:placetype":"locality",
    "wof:population":206
},
  "geometry": {"coordinates":[87.012299,21.70389],"type":"Point"}
}