{
  "type": "Feature",
  "properties": {
    "iso:country":"IN",
    "ks:ks_name":"Sanka",
    "ks:ks_pop":1299,
    "ks:ks_type":"VILLAGE",
    "ks:ks_uagg_main":0,
    "name:eng_x_preferred":[
        "Sanka"
    ],
    "wof:name":"Sanka",
    "wof:placetype":"locality",
    "wof:population":1299
},
  "geometry": {"coordinates":[88.241444,22.755397],"type":"Point"}
}