{
  "type": "Feature",
  "properties": {
    "gn:admin1_code":"39.0",
    "gn:admin2_code":"64.0",
    "gn:asciiname":"Sinaura Dangwal",
    "gn:country_code":"IN",
    "gn:dem":1298,
    "gn:feature_class":"P",
    "gn:feature_code":"PPL",
    "gn:name":"Sinaura Dangw\u0101l",
    "gn:population":0,
    "gn:timezone":"Asia/Kolkata",
    "iso:country":"IN",
    "wof:name":"Sinaura Dangwal",
    "wof:placetype":"locality"
},
  "geometry": {"coordinates":[79.29675,29.6473],"type":"Point"}
}