{
  "type": "Feature",
  "properties": {
    "gn:admin1_code":"11.0",
    "gn:admin2_code":"27.0",
    "gn:asciiname":"Stana",
    "gn:country_code":"IN",
    "gn:dem":2607,
    "gn:feature_class":"P",
    "gn:feature_code":"PPL",
    "gn:name":"St\u0101na",
    "gn:population":0,
    "gn:timezone":"Asia/Kolkata",
    "iso:country":"IN",
    "wof:name":"Stana",
    "wof:placetype":"locality"
},
  "geometry": {"coordinates":[77.23680999999998,31.6451],"type":"Point"}
}