{
  "type": "Feature",
  "properties": {
    "gn:admin1_code":"16",
    "gn:admin2_code":"506.0",
    "gn:asciiname":"Govindpur",
    "gn:country_code":"IN",
    "gn:dem":323,
    "gn:feature_class":"P",
    "gn:feature_code":"PPL",
    "gn:name":"Govindpur",
    "gn:population":0,
    "gn:timezone":"Asia/Kolkata",
    "iso:country":"IN",
    "wof:name":"Govindpur",
    "wof:placetype":"locality"
},
  "geometry": {"coordinates":[79.69571999999999,21.57374],"type":"Point"}
}