{
  "type": "Feature",
  "properties": {
    "gn:admin1_code":"36",
    "gn:admin2_code":"175.0",
    "gn:asciiname":"Bansipatti",
    "gn:country_code":"IN",
    "gn:dem":92,
    "gn:feature_class":"P",
    "gn:feature_code":"PPL",
    "gn:name":"Bans\u012bpatt\u012b",
    "gn:population":0,
    "gn:timezone":"Asia/Kolkata",
    "iso:country":"IN",
    "wof:name":"Bansipatti",
    "wof:placetype":"locality"
},
  "geometry": {"coordinates":[82.30824,25.41292],"type":"Point"}
}