{
  "type": "Feature",
  "properties": {
    "gn:admin1_code":"10.0",
    "gn:admin2_code":"072",
    "gn:asciiname":"Model Town",
    "gn:country_code":"IN",
    "gn:dem":255,
    "gn:feature_class":"P",
    "gn:feature_code":"PPL",
    "gn:name":"Model Town",
    "gn:population":0,
    "gn:timezone":"Asia/Kolkata",
    "iso:country":"IN",
    "name:ara_x_preferred":[
        "\u0645\u0648\u062f\u064a\u0644 \u062a\u0627\u0648\u0646"
    ],
    "name:ben_bn_x_preferred":[
        "\u09ae\u09a1\u09c7\u09b2 \u099f\u09be\u0989\u09a8"
    ],
    "name:ben_in_x_preferred":[
        "\u09ae\u09a1\u09c7\u09b2 \u099f\u09be\u0989\u09a8"
    ],
    "name:guj_x_preferred":[
        "\u0aae\u0acb\u0aa1\u0ac7\u0ab2 \u0a9f\u0abe\u0a89\u0aa8"
    ],
    "name:hin_x_preferred":[
        "\u092e\u0949\u0921\u0932 \u091f\u093e\u0909\u0928"
    ],
    "name:kan_x_preferred":[
        "\u0cae\u0cbe\u0ca1\u0cc6\u0cb2\u0ccd"
    ],
    "name:mal_x_preferred":[
        "\u0d2e\u0d4b\u0d21\u0d7d \u0d1f\u0d57\u0d7a"
    ],
    "name:mar_x_preferred":[
        "\u092e\u0949\u0921\u0947\u0932 \u091f\u093e\u090a\u0928"
    ],
    "name:pan_x_preferred":[
        "\u0a2e\u0a3e\u0a21\u0a32 \u0a1f\u0a3e\u0a0a\u0a28"
    ],
    "name:tam_x_preferred":[
        "\u0bae\u0bbe\u0ba4\u0bbf\u0bb0\u0bbf \u0ba8\u0b95\u0bb0\u0bae\u0bcd"
    ],
    "name:tel_x_preferred":[
        "\u0c2e\u0c4b\u0c21\u0c46\u0c32\u0c4d \u0c1f\u0c4c\u0c28\u0c4d"
    ],
    "name:urd_x_preferred":[
        "\u0645\u0627\u0688\u0644 \u0679\u0627\u0624\u0646"
    ],
    "wof:name":"Model Town",
    "wof:placetype":"neighbourhood"
},
  "geometry": {"coordinates":[76.68565,30.14865],"type":"Point"}
}