{
  "type": "Feature",
  "properties": {
    "gn:admin1_code":"2",
    "gn:admin2_code":"544.0",
    "gn:asciiname":"Virabhupalapatnam",
    "gn:country_code":"IN",
    "gn:dem":97,
    "gn:feature_class":"P",
    "gn:feature_code":"PPL",
    "gn:name":"V\u012brabh\u016bp\u0101lapatnam",
    "gn:population":0,
    "gn:timezone":"Asia/Kolkata",
    "iso:country":"IN",
    "wof:name":"Virabhupalapatnam",
    "wof:placetype":"locality"
},
  "geometry": {"coordinates":[82.58396999999999,17.69386],"type":"Point"}
}