{
  "type": "Feature",
  "properties": {
    "iso:country":"IN",
    "ks:ks_name":"Gursagra",
    "ks:ks_pop":235,
    "ks:ks_type":"VILLAGE",
    "name:eng_x_preferred":[
        "Gursagra"
    ],
    "wof:name":"Gursagra",
    "wof:placetype":"locality",
    "wof:population":235
},
  "geometry": {"coordinates":[86.851698,23.377474],"type":"Point"}
}