{
  "type": "Feature",
  "properties": {
    "iso:country":"IN",
    "ks:ks_name":"Tikimalan",
    "ks:ks_pop":72,
    "ks:ks_type":"VILLAGE",
    "name:eng_x_preferred":[
        "Tikimalan"
    ],
    "wof:name":"Tikimalan",
    "wof:placetype":"locality",
    "wof:population":72
},
  "geometry": {"coordinates":[85.111383,22.55915],"type":"Point"}
}