{
  "type": "Feature",
  "properties": {
    "gn:admin1_code":"36.0",
    "gn:admin2_code":"151.0",
    "gn:asciiname":"Karmanpur Mafi",
    "gn:country_code":"IN",
    "gn:dem":170,
    "gn:feature_class":"P",
    "gn:feature_code":"PPL",
    "gn:name":"Karm\u0101npur M\u0101fi",
    "gn:population":0,
    "gn:timezone":"Asia/Kolkata",
    "iso:country":"IN",
    "wof:name":"Karmanpur Mafi",
    "wof:placetype":"locality"
},
  "geometry": {"coordinates":[79.81317,28.21467],"type":"Point"}
}