{
  "type": "Feature",
  "properties": {
    "iso:country":"IN",
    "ks:ks_name":"Mankadakhola",
    "ks:ks_pop":425,
    "ks:ks_type":"VILLAGE",
    "name:eng_x_preferred":[
        "Mankadakhola"
    ],
    "wof:name":"Mankadakhola",
    "wof:placetype":"locality",
    "wof:population":425
},
  "geometry": {"coordinates":[83.51220499999999,20.259111],"type":"Point"}
}