{
  "type": "Feature",
  "properties": {
    "iso:country":"IN",
    "ks:ks_name":"Buj Mahadev",
    "ks:ks_pop":187,
    "ks:ks_type":"HABITATION",
    "name:eng_x_preferred":[
        "Buj Mahadev"
    ],
    "wof:name":"Buj Mahadev",
    "wof:placetype":"locality",
    "wof:population":187
},
  "geometry": {"coordinates":[75.466723,24.58726],"type":"Point"}
}