{
  "type": "Feature",
  "properties": {
    "iso:country":"IN",
    "ks:ks_name":"Basera",
    "ks:ks_pop":805,
    "ks:ks_type":"VILLAGE",
    "name:eng_x_preferred":[
        "Basera"
    ],
    "wof:name":"Basera",
    "wof:placetype":"locality",
    "wof:population":805
},
  "geometry": {"coordinates":[78.27229,29.516991],"type":"Point"}
}