{
  "type": "Feature",
  "properties": {
    "iso:country":"IN",
    "ks:ks_name":"Mallah Tola",
    "ks:ks_pop":221,
    "ks:ks_type":"HABITATION",
    "name:eng_x_preferred":[
        "Mallah Tola"
    ],
    "wof:name":"Mallah Tola",
    "wof:placetype":"locality",
    "wof:population":221
},
  "geometry": {"coordinates":[85.730692,25.703281],"type":"Point"}
}