{
  "type": "Feature",
  "properties": {
    "iso:country":"IN",
    "ks:ks_name":"Kanthi",
    "ks:ks_pop":760,
    "ks:ks_type":"VILLAGE",
    "ks:ks_uagg_main":0,
    "name:eng_x_preferred":[
        "Kanthi"
    ],
    "wof:name":"Kanthi",
    "wof:placetype":"neighbourhood",
    "wof:population":760
},
  "geometry": {"coordinates":[80.688464,26.182991],"type":"Point"}
}