{
  "type": "Feature",
  "properties": {
    "gn:admin1_code":"12.0",
    "gn:admin2_code":"010",
    "gn:asciiname":"Batawara",
    "gn:country_code":"IN",
    "gn:dem":1587,
    "gn:feature_class":"P",
    "gn:feature_code":"PPL",
    "gn:name":"Bataw\u0101ra",
    "gn:population":0,
    "gn:timezone":"Asia/Kolkata",
    "iso:country":"IN",
    "wof:name":"Batawara",
    "wof:placetype":"locality"
},
  "geometry": {"coordinates":[74.84990000000001,34.05778],"type":"Point"}
}