{
  "type": "Feature",
  "properties": {
    "iso:country":"IN",
    "ks:ks_name":"Nadimimadigapalem",
    "ks:ks_pop":167,
    "ks:ks_type":"HABITATION",
    "ks:ks_uagg_main":0,
    "name:eng_x_preferred":[
        "Nadimimadigapalem"
    ],
    "wof:name":"Nadimimadigapalem",
    "wof:placetype":"neighbourhood",
    "wof:population":167
},
  "geometry": {"coordinates":[79.659088,14.882271],"type":"Point"}
}