{
  "type": "Feature",
  "properties": {
    "iso:country":"IN",
    "ks:ks_name":"Gulangapadar",
    "ks:ks_pop":37,
    "ks:ks_type":"HABITATION",
    "name:eng_x_preferred":[
        "Gulangapadar"
    ],
    "wof:name":"Gulangapadar",
    "wof:placetype":"locality",
    "wof:population":37
},
  "geometry": {"coordinates":[82.325862,18.446508],"type":"Point"}
}