{
  "type": "Feature",
  "properties": {
    "gn:admin1_code":"18.0",
    "gn:admin2_code":"297",
    "gn:asciiname":"Bhoilymbong",
    "gn:country_code":"IN",
    "gn:dem":889,
    "gn:feature_class":"P",
    "gn:feature_code":"PPL",
    "gn:name":"Bhoilymbong",
    "gn:population":0,
    "gn:timezone":"Asia/Kolkata",
    "iso:country":"IN",
    "wof:name":"Bhoilymbong",
    "wof:placetype":"locality"
},
  "geometry": {"coordinates":[92.02118,25.70966],"type":"Point"}
}