{
  "type": "Feature",
  "properties": {
    "iso:country":"IN",
    "ks:ks_alt_nam":"L\u0101lpur",
    "ks:ks_name":"Lalpur",
    "ks:ks_type":"VILLAGE",
    "name:eng_x_preferred":[
        "Lalpur"
    ],
    "name:eng_x_variant":[
        "L\u0101lpur"
    ],
    "wof:name":"Lalpur",
    "wof:placetype":"locality"
},
  "geometry": {"coordinates":[81.38140300000001,22.379267],"type":"Point"}
}