{
  "type": "Feature",
  "properties": {
    "gn:admin1_code":"11.0",
    "gn:admin2_code":"32.0",
    "gn:asciiname":"Roranwali",
    "gn:country_code":"IN",
    "gn:dem":744,
    "gn:feature_class":"P",
    "gn:feature_code":"PPL",
    "gn:name":"Ror\u0101nw\u0101li",
    "gn:population":0,
    "gn:timezone":"Asia/Kolkata",
    "iso:country":"IN",
    "name:und_x_variant":[
        "Ror\u0101nw\u0101li"
    ],
    "wof:name":"Roranwali",
    "wof:placetype":"locality"
},
  "geometry": {"coordinates":[77.26938,30.56078],"type":"Point"}
}