{
  "type": "Feature",
  "properties": {
    "iso:country":"IN",
    "ks:ks_name":"Bagaram Ronghang",
    "ks:ks_pop":95,
    "ks:ks_type":"HABITATION",
    "name:eng_x_preferred":[
        "Bagaram Ronghang"
    ],
    "wof:name":"Bagaram Ronghang",
    "wof:placetype":"locality",
    "wof:population":95
},
  "geometry": {"coordinates":[93.146855,26.034862],"type":"Point"}
}