{
  "type": "Feature",
  "properties": {
    "gn:admin1_code":"12.0",
    "gn:asciiname":"Treboni",
    "gn:country_code":"IN",
    "gn:dem":1599,
    "gn:feature_class":"P",
    "gn:feature_code":"PPL",
    "gn:name":"Treboni",
    "gn:population":0,
    "gn:timezone":"Asia/Kolkata",
    "iso:country":"IN",
    "wof:name":"Treboni",
    "wof:placetype":"locality"
},
  "geometry": {"coordinates":[73.82729,34.38417],"type":"Point"}
}