{
  "type": "Feature",
  "properties": {
    "gn:admin1_code":"11.0",
    "gn:admin2_code":"27.0",
    "gn:asciiname":"Saral",
    "gn:country_code":"IN",
    "gn:dem":1331,
    "gn:feature_class":"P",
    "gn:feature_code":"PPL",
    "gn:name":"Sar\u0101l",
    "gn:population":0,
    "gn:timezone":"Asia/Kolkata",
    "iso:country":"IN",
    "name:aze_x_preferred":[
        "Saral"
    ],
    "name:fas_x_preferred":[
        "\u0633\u0627\u0631\u0627\u0644"
    ],
    "name:fra_x_preferred":[
        "Saral"
    ],
    "wof:name":"Saral",
    "wof:placetype":"locality"
},
  "geometry": {"coordinates":[77.36428000000002,31.36648],"type":"Point"}
}