{
  "type": "Feature",
  "properties": {
    "iso:country":"IN",
    "ks:ks_name":"Kasia",
    "ks:ks_pop":479,
    "ks:ks_type":"VILLAGE",
    "name:eng_x_preferred":[
        "Kasia"
    ],
    "wof:name":"Kasia",
    "wof:placetype":"locality",
    "wof:population":479
},
  "geometry": {"coordinates":[86.00282799999999,22.476289],"type":"Point"}
}