{
  "type": "Feature",
  "properties": {
    "gn:admin1_code":"16",
    "gn:admin2_code":"502.0",
    "gn:asciiname":"Jamb",
    "gn:country_code":"IN",
    "gn:dem":439,
    "gn:feature_class":"P",
    "gn:feature_code":"PPL",
    "gn:name":"J\u0101mb",
    "gn:population":0,
    "gn:timezone":"Asia/Kolkata",
    "iso:country":"IN",
    "name:cat_x_preferred":[
        "Brancal"
    ],
    "name:ces_x_preferred":[
        "Z\u00e1rube\u0148"
    ],
    "name:deu_x_preferred":[
        "Laibung"
    ],
    "name:epo_x_preferred":[
        "Gambo"
    ],
    "name:eus_x_preferred":[
        "Janba"
    ],
    "name:fra_x_preferred":[
        "Jambage"
    ],
    "name:gla_x_preferred":[
        "Ursainn"
    ],
    "name:gle_x_preferred":[
        "Ursain"
    ],
    "name:glg_x_preferred":[
        "Xamba"
    ],
    "name:pol_x_preferred":[
        "W\u0119gar"
    ],
    "name:por_x_preferred":[
        "Jamba"
    ],
    "name:rus_x_preferred":[
        "\u0414\u0432\u0435\u0440\u043d\u0430\u044f \u043a\u043e\u0440\u043e\u0431\u043a\u0430"
    ],
    "name:spa_x_preferred":[
        "Jamba"
    ],
    "name:ukr_x_preferred":[
        "\u041e\u0434\u0432\u0456\u0440\u043e\u043a"
    ],
    "wof:name":"Jamb",
    "wof:placetype":"locality"
},
  "geometry": {"coordinates":[77.29388,20.32195],"type":"Point"}
}