{
  "type": "Feature",
  "properties": {
    "iso:country":"IN",
    "ks:ks_name":"Gena Ka Goliya",
    "ks:ks_pop":784,
    "ks:ks_type":"HABITATION",
    "name:eng_x_preferred":[
        "Gena Ka Goliya"
    ],
    "wof:name":"Gena Ka Goliya",
    "wof:placetype":"locality",
    "wof:population":784
},
  "geometry": {"coordinates":[71.778819,24.856054],"type":"Point"}
}