{
  "type": "Feature",
  "properties": {
    "iso:country":"IN",
    "ks:ks_name":"Bankasia",
    "ks:ks_pop":335,
    "ks:ks_type":"HABITATION",
    "name:eng_x_preferred":[
        "Bankasia"
    ],
    "wof:name":"Bankasia",
    "wof:placetype":"locality",
    "wof:population":335
},
  "geometry": {"coordinates":[83.165708,27.446379],"type":"Point"}
}