{
  "type": "Feature",
  "properties": {
    "gn:admin1_code":"2.0",
    "gn:admin2_code":"552.0",
    "gn:asciiname":"Dayyalamadugu",
    "gn:country_code":"IN",
    "gn:dem":331,
    "gn:feature_class":"P",
    "gn:feature_code":"PPL",
    "gn:name":"Dayy\u0101lamadugu",
    "gn:population":0,
    "gn:timezone":"Asia/Kolkata",
    "iso:country":"IN",
    "wof:name":"Dayyalamadugu",
    "wof:placetype":"locality"
},
  "geometry": {"coordinates":[77.79076999999999,15.10481],"type":"Point"}
}