{
  "type": "Feature",
  "properties": {
    "gn:admin1_code":"35.0",
    "gn:admin2_code":"433.0",
    "gn:asciiname":"Jorma",
    "gn:country_code":"IN",
    "gn:dem":423,
    "gn:feature_class":"P",
    "gn:feature_code":"PPL",
    "gn:name":"Jorma",
    "gn:population":0,
    "gn:timezone":"Asia/Kolkata",
    "iso:country":"IN",
    "wof:name":"Jorma",
    "wof:placetype":"locality"
},
  "geometry": {"coordinates":[75.68156999999999,24.37343],"type":"Point"}
}