{
  "type": "Feature",
  "properties": {
    "gn:admin1_code":"12",
    "gn:admin2_code":"12.0",
    "gn:asciiname":"Shar",
    "gn:country_code":"IN",
    "gn:dem":1640,
    "gn:feature_class":"P",
    "gn:feature_code":"PPL",
    "gn:name":"Sh\u0101r",
    "gn:population":0,
    "gn:timezone":"Asia/Kolkata",
    "iso:country":"IN",
    "wof:name":"Shar",
    "wof:placetype":"locality"
},
  "geometry": {"coordinates":[75.00756,34.01219],"type":"Point"}
}