{
  "type": "Feature",
  "properties": {
    "gn:admin1_code":"12",
    "gn:admin2_code":"12.0",
    "gn:asciiname":"Shar",
    "gn:country_code":"IN",
    "gn:dem":1640,
    "gn:feature_class":"P",
    "gn:feature_code":"PPL",
    "gn:name":"Sh\u0101r",
    "gn:population":0,
    "gn:timezone":"Asia/Kolkata",
    "iso:country":"IN",
    "name:ara_x_preferred":[
        "\u0634\u0627\u0631"
    ],
    "name:ben_x_preferred":[
        "\u09b6\u09be\u09b0"
    ],
    "name:ell_x_preferred":[
        "\u03a3\u03b1\u03c1"
    ],
    "name:fas_x_preferred":[
        "\u0634\u0627\u0631"
    ],
    "name:fra_x_preferred":[
        "Charsk"
    ],
    "name:heb_x_preferred":[
        "\u05e9\u05d0\u05e8"
    ],
    "name:hin_x_preferred":[
        "\u0936\u093e\u0930"
    ],
    "name:hun_x_preferred":[
        "Shar"
    ],
    "name:ind_x_preferred":[
        "Shar"
    ],
    "name:ita_x_preferred":[
        "Shar"
    ],
    "name:jpn_x_preferred":[
        "\u30b7\u30e3\u30fc"
    ],
    "name:kor_x_preferred":[
        "\uc0e4\ub974"
    ],
    "name:por_x_preferred":[
        "Charsk"
    ],
    "name:spa_x_preferred":[
        "Shar"
    ],
    "name:tur_x_preferred":[
        "Shar"
    ],
    "name:ukr_x_preferred":[
        "Shar"
    ],
    "name:urd_x_preferred":[
        "\u0634\u0627\u0631"
    ],
    "name:vie_x_preferred":[
        "Shar"
    ],
    "wof:name":"Shar",
    "wof:placetype":"locality"
},
  "geometry": {"coordinates":[75.00756,34.01219],"type":"Point"}
}