{
  "type": "Feature",
  "properties": {
    "iso:country":"IN",
    "ks:ks_alt_nam":"MohammedHausanpur",
    "ks:ks_name":"Mohammedhausanpur",
    "ks:ks_pop":518,
    "ks:ks_type":"HABITATION",
    "name:eng_x_preferred":[
        "Mohammedhausanpur"
    ],
    "wof:name":"Mohammedhausanpur",
    "wof:placetype":"locality",
    "wof:population":518
},
  "geometry": {"coordinates":[86.15943900000001,20.992243],"type":"Point"}
}