{
  "type": "Feature",
  "properties": {
    "iso:country":"IN",
    "ks:ks_name":"Gopalasamuthram",
    "ks:ks_pop":524,
    "ks:ks_type":"HABITATION",
    "name:eng_x_preferred":[
        "Gopalasamuthram"
    ],
    "wof:name":"Gopalasamuthram",
    "wof:placetype":"locality",
    "wof:population":524
},
  "geometry": {"coordinates":[79.55015400000001,10.431538],"type":"Point"}
}