{
  "type": "Feature",
  "properties": {
    "iso:country":"IN",
    "ks:ks_name":"Bhaktauli",
    "ks:ks_pop":120,
    "ks:ks_type":"VILLAGE",
    "name:eng_x_preferred":[
        "Bhaktauli"
    ],
    "wof:name":"Bhaktauli",
    "wof:placetype":"locality",
    "wof:population":120
},
  "geometry": {"coordinates":[85.251237,22.548833],"type":"Point"}
}