{
  "type": "Feature",
  "properties": {
    "iso:country":"IN",
    "ks:ks_name":"Masanki Khaspara",
    "ks:ks_pop":364,
    "ks:ks_type":"HABITATION",
    "name:eng_x_preferred":[
        "Masanki Khaspara"
    ],
    "wof:name":"Masanki Khaspara",
    "wof:placetype":"locality",
    "wof:population":364
},
  "geometry": {"coordinates":[82.84170399999999,23.564735],"type":"Point"}
}