{
  "type": "Feature",
  "properties": {
    "iso:country":"IN",
    "ks:ks_name":"Titheitangar",
    "ks:ks_pop":498,
    "ks:ks_type":"VILLAGE",
    "name:eng_x_preferred":[
        "Titheitangar"
    ],
    "wof:name":"Titheitangar",
    "wof:placetype":"locality",
    "wof:population":498
},
  "geometry": {"coordinates":[84.13588300000001,22.385419],"type":"Point"}
}