{
  "type": "Feature",
  "properties": {
    "gn:admin1_code":"40",
    "gn:admin2_code":"538.0",
    "gn:asciiname":"Pucharlakunta Tanda",
    "gn:country_code":"IN",
    "gn:dem":677,
    "gn:feature_class":"P",
    "gn:feature_code":"PPL",
    "gn:name":"Pucharlakunta T\u0101nda",
    "gn:population":0,
    "gn:timezone":"Asia/Kolkata",
    "iso:country":"IN",
    "wof:name":"Pucharlakunta Tanda",
    "wof:placetype":"locality"
},
  "geometry": {"coordinates":[78.32170000000001,17.05298],"type":"Point"}
}