{
  "type": "Feature",
  "properties": {
    "iso:country":"IN",
    "ks:ks_alt_nam":"dimirkonda",
    "ks:ks_name":"Dimirkonda",
    "ks:ks_pop":94,
    "ks:ks_type":"HABITATION",
    "name:eng_x_preferred":[
        "Dimirkonda"
    ],
    "wof:name":"Dimirkonda",
    "wof:placetype":"locality",
    "wof:population":94
},
  "geometry": {"coordinates":[83.655591,19.184318],"type":"Point"}
}