{
  "type": "Feature",
  "properties": {
    "gn:admin1_code":"36",
    "gn:admin2_code":"134.0",
    "gn:asciiname":"Hasan Alipur Khandu Baghala",
    "gn:country_code":"IN",
    "gn:dem":242,
    "gn:feature_class":"P",
    "gn:feature_code":"PPL",
    "gn:name":"Hasan Al\u012bpur Khandu Bagh\u0101la",
    "gn:population":0,
    "gn:timezone":"Asia/Kolkata",
    "iso:country":"IN",
    "name:und_x_variant":[
        "Hasan Al\u012bpur Khandu Bagh\u0101la",
        "M\u0101mr\u0101jpur"
    ],
    "wof:name":"Hasan Alipur Khandu Baghala",
    "wof:placetype":"locality"
},
  "geometry": {"coordinates":[78.40114,29.3805],"type":"Point"}
}