{
  "type": "Feature",
  "properties": {
    "iso:country":"IN",
    "ks:ks_name":"Gundali Dera",
    "ks:ks_pop":145,
    "ks:ks_type":"HABITATION",
    "name:eng_x_preferred":[
        "Gundali Dera"
    ],
    "wof:name":"Gundali Dera",
    "wof:placetype":"locality",
    "wof:population":145
},
  "geometry": {"coordinates":[80.88292,25.708035],"type":"Point"}
}