{
  "type": "Feature",
  "properties": {
    "iso:country":"IN",
    "ks:ks_name":"Ababakapul",
    "ks:ks_pop":516,
    "ks:ks_type":"VILLAGE",
    "ks:ks_uagg_main":0,
    "name:eng_x_preferred":[
        "Ababakapul"
    ],
    "wof:name":"Ababakapul",
    "wof:placetype":"neighbourhood",
    "wof:population":516
},
  "geometry": {"coordinates":[78.583671,26.985141],"type":"Point"}
}