{
  "type": "Feature",
  "properties": {
    "iso:country":"IN",
    "ks:ks_alt_nam":"KENDUA",
    "ks:ks_name":"Kendua",
    "ks:ks_pop":83,
    "ks:ks_type":"HABITATION",
    "name:eng_x_preferred":[
        "Kendua"
    ],
    "wof:name":"Kendua",
    "wof:placetype":"locality",
    "wof:population":83
},
  "geometry": {"coordinates":[85.66596,24.011091],"type":"Point"}
}