{
  "type": "Feature",
  "properties": {
    "iso:country":"IN",
    "ks:ks_name":"Alinagar Dharmnagar",
    "ks:ks_pop":418,
    "ks:ks_type":"HABITATION",
    "name:eng_x_preferred":[
        "Alinagar Dharmnagar"
    ],
    "wof:name":"Alinagar Dharmnagar",
    "wof:placetype":"locality",
    "wof:population":418
},
  "geometry": {"coordinates":[81.81156300000001,27.809565],"type":"Point"}
}