{
  "type": "Feature",
  "properties": {
    "gn:admin1_code":"36",
    "gn:admin2_code":"149.0",
    "gn:asciiname":"Biohpuri",
    "gn:country_code":"IN",
    "gn:dem":181,
    "gn:feature_class":"P",
    "gn:feature_code":"PPL",
    "gn:name":"Biohp\u016br\u012b",
    "gn:population":0,
    "gn:timezone":"Asia/Kolkata",
    "iso:country":"IN",
    "name:und_x_variant":[
        "Biohp\u016br\u012b",
        "Sail\u0101b"
    ],
    "wof:name":"Biohpuri",
    "wof:placetype":"locality"
},
  "geometry": {"coordinates":[78.42286,28.21571],"type":"Point"}
}