{
  "type": "Feature",
  "properties": {
    "iso:country":"IN",
    "ks:ks_name":"Nilichiwadi",
    "ks:ks_pop":223,
    "ks:ks_type":"HABITATION",
    "name:eng_x_preferred":[
        "Nilichiwadi"
    ],
    "wof:name":"Nilichiwadi",
    "wof:placetype":"locality",
    "wof:population":223
},
  "geometry": {"coordinates":[73.34032500000001,17.250846],"type":"Point"}
}