{
  "type": "Feature",
  "properties": {
    "gn:admin1_code":"2.0",
    "gn:admin2_code":"554.0",
    "gn:asciiname":"Katlatapalle",
    "gn:country_code":"IN",
    "gn:dem":729,
    "gn:feature_class":"P",
    "gn:feature_code":"PPL",
    "gn:name":"K\u0101tl\u0101tapalle",
    "gn:population":0,
    "gn:timezone":"Asia/Kolkata",
    "iso:country":"IN",
    "wof:name":"Katlatapalle",
    "wof:placetype":"locality"
},
  "geometry": {"coordinates":[78.48014999999999,13.58988],"type":"Point"}
}