{
  "type": "Feature",
  "properties": {
    "iso:country":"IN",
    "ks:ks_name":"Mantripalem",
    "ks:ks_pop":522,
    "ks:ks_type":"HABITATION",
    "name:eng_x_preferred":[
        "Mantripalem"
    ],
    "wof:name":"Mantripalem",
    "wof:placetype":"locality",
    "wof:population":522
},
  "geometry": {"coordinates":[82.81962799999999,17.525071],"type":"Point"}
}