{
  "type": "Feature",
  "properties": {
    "iso:country":"IN",
    "ks:ks_name":"Hallusalu",
    "ks:ks_pop":47,
    "ks:ks_type":"HABITATION",
    "name:eng_x_preferred":[
        "Hallusalu"
    ],
    "wof:name":"Hallusalu",
    "wof:placetype":"locality",
    "wof:population":47
},
  "geometry": {"coordinates":[75.20138900000001,13.844167],"type":"Point"}
}