{
  "type": "Feature",
  "properties": {
    "gn:admin1_code":"2.0",
    "gn:admin2_code":"543.0",
    "gn:asciiname":"Butadivalasa",
    "gn:country_code":"IN",
    "gn:dem":236,
    "gn:feature_class":"P",
    "gn:feature_code":"PPL",
    "gn:name":"B\u016bt\u0101divalasa",
    "gn:population":0,
    "gn:timezone":"Asia/Kolkata",
    "iso:country":"IN",
    "ks:ks_name":"Bhutadavalasa",
    "ks:ks_pop":78,
    "ks:ks_type":"HABITATION",
    "name:eng_x_preferred":[
        "Bhutadavalasa"
    ],
    "name:eng_x_variant":[
        "Butadivalasa"
    ],
    "wof:name":"Bhutadavalasa",
    "wof:placetype":"locality",
    "wof:population":78
},
  "geometry": {"coordinates":[83.176044,18.429957],"type":"Point"}
}