{
  "type": "Feature",
  "properties": {
    "iso:country":"IN",
    "ks:ks_name":"Arjun Bigha",
    "ks:ks_pop":255,
    "ks:ks_type":"HABITATION",
    "name:eng_x_preferred":[
        "Arjun Bigha"
    ],
    "wof:name":"Arjun Bigha",
    "wof:placetype":"locality",
    "wof:population":255
},
  "geometry": {"coordinates":[84.529444,24.742101],"type":"Point"}
}