{
  "type": "Feature",
  "properties": {
    "gn:admin1_code":"39.0",
    "gn:admin2_code":"66.0",
    "gn:asciiname":"Chaukhutta",
    "gn:country_code":"IN",
    "gn:dem":2012,
    "gn:feature_class":"P",
    "gn:feature_code":"PPL",
    "gn:name":"Chaukhutta",
    "gn:population":0,
    "gn:timezone":"Asia/Kolkata",
    "iso:country":"IN",
    "ks:ks_name":"Chaukhuta",
    "ks:ks_pop":1080,
    "ks:ks_type":"VILLAGE",
    "ks:ks_uagg_main":0,
    "name:eng_x_preferred":[
        "Chaukhuta"
    ],
    "wof:name":"Chaukhuta",
    "wof:placetype":"neighbourhood",
    "wof:population":1080
},
  "geometry": {"coordinates":[79.638445,29.42322],"type":"Point"}
}