{
  "type": "Feature",
  "properties": {
    "iso:country":"IN",
    "ks:ks_name":"Singlacherra Grant Pt II",
    "ks:ks_pop":1931,
    "ks:ks_type":"VILLAGE",
    "name:eng_x_preferred":[
        "Singlacherra Grant Pt II"
    ],
    "wof:name":"Singlacherra Grant Pt II",
    "wof:placetype":"locality",
    "wof:population":1931
},
  "geometry": {"coordinates":[92.411396,24.459094],"type":"Point"}
}