{
  "type": "Feature",
  "properties": {
    "gn:admin1_code":"11.0",
    "gn:admin2_code":"31.0",
    "gn:asciiname":"Dadheri",
    "gn:country_code":"IN",
    "gn:dem":968,
    "gn:feature_class":"P",
    "gn:feature_code":"PPL",
    "gn:name":"Dadheri",
    "gn:population":0,
    "gn:timezone":"Asia/Kolkata",
    "iso:country":"IN",
    "wof:name":"Dadheri",
    "wof:placetype":"locality"
},
  "geometry": {"coordinates":[77.23565000000001,30.9063],"type":"Point"}
}