{
  "type": "Feature",
  "properties": {
    "gn:admin1_code":"36.0",
    "gn:admin2_code":"134.0",
    "gn:asciiname":"Nurullahpur Hafiz",
    "gn:country_code":"IN",
    "gn:dem":229,
    "gn:feature_class":"P",
    "gn:feature_code":"PPL",
    "gn:name":"N\u016brull\u0101hpur H\u0101fiz",
    "gn:population":0,
    "gn:timezone":"Asia/Kolkata",
    "iso:country":"IN",
    "wof:name":"Nurullahpur Hafiz",
    "wof:placetype":"locality"
},
  "geometry": {"coordinates":[78.11433000000002,29.43032],"type":"Point"}
}