{
  "type": "Feature",
  "properties": {
    "iso:country":"IN",
    "ks:ks_name":"Ramarajapuram",
    "ks:ks_pop":120,
    "ks:ks_type":"HABITATION",
    "ks:ks_uagg_main":0,
    "name:eng_x_preferred":[
        "Ramarajapuram"
    ],
    "wof:name":"Ramarajapuram",
    "wof:placetype":"neighbourhood",
    "wof:population":120
},
  "geometry": {"coordinates":[78.097278,10.507093],"type":"Point"}
}