{
  "type": "Feature",
  "properties": {
    "iso:country":"IN",
    "ks:ks_name":"Potaldiha",
    "ks:ks_pop":647,
    "ks:ks_type":"VILLAGE",
    "name:eng_x_preferred":[
        "Potaldiha"
    ],
    "wof:name":"Potaldiha",
    "wof:placetype":"locality",
    "wof:population":647
},
  "geometry": {"coordinates":[86.50506799999999,21.57219],"type":"Point"}
}