{
  "type": "Feature",
  "properties": {
    "iso:country":"IN",
    "ks:ks_alt_nam":"EKCHATBA",
    "ks:ks_name":"Ekchatba",
    "ks:ks_pop":160,
    "ks:ks_type":"HABITATION",
    "name:eng_x_preferred":[
        "Ekchatba"
    ],
    "wof:name":"Ekchatba",
    "wof:placetype":"locality",
    "wof:population":160
},
  "geometry": {"coordinates":[85.503593,24.632341],"type":"Point"}
}