{
  "type": "Feature",
  "properties": {
    "gn:country":"IN",
    "gn:fcode":"PPL",
    "gn:population":0,
    "iso:country":"IN",
    "name:azb_x_preferred":[
        "\u0645\u0627\u0648"
    ],
    "name:cat_x_preferred":[
        "Mau"
    ],
    "name:ceb_x_preferred":[
        "Mau"
    ],
    "name:deu_x_preferred":[
        "Mau"
    ],
    "name:fas_x_preferred":[
        "\u0645\u0627\u0648"
    ],
    "name:fra_x_preferred":[
        "Mau"
    ],
    "name:hin_x_preferred":[
        "\u092e\u090a"
    ],
    "name:ita_x_preferred":[
        "Mau"
    ],
    "name:msa_x_preferred":[
        "Mau"
    ],
    "name:nld_x_preferred":[
        "Mau"
    ],
    "name:pnb_x_preferred":[
        "\u0645\u0626\u0648"
    ],
    "name:pol_x_preferred":[
        "Mau"
    ],
    "name:por_x_preferred":[
        "Maunath Bhanjan"
    ],
    "name:rus_x_preferred":[
        "\u041c\u0430\u0443"
    ],
    "name:san_x_preferred":[
        "\u092e\u0935\u0941"
    ],
    "name:srp_x_preferred":[
        "\u041c\u0430\u0443"
    ],
    "name:swe_x_preferred":[
        "Maunath Bhanjan"
    ],
    "name:urd_x_preferred":[
        "\u0645\u0626\u0648"
    ],
    "name:vie_x_preferred":[
        "Maunath Bhanjan"
    ],
    "name:war_x_preferred":[
        "Mau"
    ],
    "name:zho_x_preferred":[
        "\u6bdb\u7eb3\u7279\u73ed\u8a79"
    ],
    "qs:name":"Mau",
    "qs:name_adm0":"India",
    "qs:name_adm1":"Madhya Pradesh",
    "qs:photos":133,
    "qs:photos_1k":27,
    "qs:photos_9k":1,
    "qs:photos_9r":3,
    "qs:photos_all":133,
    "qs:photos_sr":3,
    "qs:placetype":"Suburb",
    "qs:pop_sr":"0",
    "wd:wordcount":800,
    "wof:name":"Mau",
    "wof:placetype":"neighbourhood",
    "wof:population":0
},
  "geometry": {"coordinates":[78.18333,26.26667],"type":"Point"}
}