{
  "type": "Feature",
  "properties": {
    "iso:country":"IN",
    "ks:ks_name":"Jaganpur",
    "ks:ks_pop":181,
    "ks:ks_type":"VILLAGE",
    "name:eng_x_preferred":[
        "Jaganpur"
    ],
    "wof:name":"Jaganpur",
    "wof:placetype":"locality",
    "wof:population":181
},
  "geometry": {"coordinates":[75.68628,31.450228],"type":"Point"}
}