{
  "type": "Feature",
  "properties": {
    "iso:country":"IN",
    "ks:ks_name":"Thasankottai",
    "ks:ks_pop":208,
    "ks:ks_type":"HABITATION",
    "ks:ks_uagg_main":0,
    "name:eng_x_preferred":[
        "Thasankottai"
    ],
    "wof:name":"Thasankottai",
    "wof:placetype":"neighbourhood",
    "wof:population":208
},
  "geometry": {"coordinates":[78.213885,12.487586],"type":"Point"}
}