{
  "type": "Feature",
  "properties": {
    "iso:country":"IN",
    "ks:ks_name":"Mirkajoka",
    "ks:ks_pop":29,
    "ks:ks_type":"VILLAGE",
    "name:eng_x_preferred":[
        "Mirkajoka"
    ],
    "wof:name":"Mirkajoka",
    "wof:placetype":"locality",
    "wof:population":29
},
  "geometry": {"coordinates":[87.48207600000001,24.880967],"type":"Point"}
}