{
  "type": "Feature",
  "properties": {
    "iso:country":"IN",
    "ks:ks_name":"Mornoi Namusudra Para",
    "ks:ks_pop":559,
    "ks:ks_type":"HABITATION",
    "name:eng_x_preferred":[
        "Mornoi Namusudra Para"
    ],
    "wof:name":"Mornoi Namusudra Para",
    "wof:placetype":"locality",
    "wof:population":559
},
  "geometry": {"coordinates":[93.93541,27.039576],"type":"Point"}
}