{
  "type": "Feature",
  "properties": {
    "iso:country":"IN",
    "ks:ks_name":"Kusumdih",
    "ks:ks_pop":75,
    "ks:ks_type":"HABITATION",
    "name:eng_x_preferred":[
        "Kusumdih"
    ],
    "wof:name":"Kusumdih",
    "wof:placetype":"locality",
    "wof:population":75
},
  "geometry": {"coordinates":[85.111949,22.275948],"type":"Point"}
}