{
  "type": "Feature",
  "properties": {
    "iso:country":"IN",
    "ks:ks_name":"Hanumanthapura",
    "ks:ks_pop":96,
    "ks:ks_type":"HABITATION",
    "name:eng_x_preferred":[
        "Hanumanthapura"
    ],
    "wof:name":"Hanumanthapura",
    "wof:placetype":"locality",
    "wof:population":96
},
  "geometry": {"coordinates":[77.740596,13.668845],"type":"Point"}
}