{
  "type": "Feature",
  "properties": {
    "gn:admin1_code":"36.0",
    "gn:admin2_code":"141.0",
    "gn:asciiname":"Kheri",
    "gn:country_code":"IN",
    "gn:dem":211,
    "gn:feature_class":"P",
    "gn:feature_code":"PPL",
    "gn:name":"Kheri",
    "gn:population":0,
    "gn:timezone":"Asia/Kolkata",
    "iso:country":"IN",
    "wof:name":"Kheri",
    "wof:placetype":"locality"
},
  "geometry": {"coordinates":[77.50799000000001,28.5559],"type":"Point"}
}