{
  "type": "Feature",
  "properties": {
    "gn:admin1_code":"23.0",
    "gn:admin2_code":"43.0",
    "gn:asciiname":"Naju Shah Misri",
    "gn:country_code":"IN",
    "gn:dem":201,
    "gn:feature_class":"P",
    "gn:feature_code":"PPL",
    "gn:name":"N\u0101ju Sh\u0101h Misri",
    "gn:population":0,
    "gn:timezone":"Asia/Kolkata",
    "iso:country":"IN",
    "name:und_x_variant":[
        "N\u0101ju Sh\u0101h Misri",
        "Misr\u012bw\u0101la"
    ],
    "wof:name":"Naju Shah Misri",
    "wof:placetype":"locality"
},
  "geometry": {"coordinates":[74.75189,30.95447],"type":"Point"}
}