{
  "type": "Feature",
  "properties": {
    "gn:admin1_code":"36",
    "gn:admin2_code":"179.0",
    "gn:asciiname":"Sarsawa",
    "gn:country_code":"IN",
    "gn:dem":94,
    "gn:feature_class":"P",
    "gn:feature_code":"PPL",
    "gn:name":"Sarsawa",
    "gn:population":0,
    "gn:timezone":"Asia/Kolkata",
    "iso:country":"IN",
    "name:bpy_x_preferred":[
        "\u09b8\u09be\u09b0\u09b8\u09be\u09f1\u09be\u09a8"
    ],
    "name:hin_x_preferred":[
        "\u0938\u0930\u0938\u093e\u0935\u093e"
    ],
    "name:ita_x_preferred":[
        "Sarsawan"
    ],
    "name:mlg_x_preferred":[
        "Sarsawan"
    ],
    "name:msa_x_preferred":[
        "Sarsawan"
    ],
    "name:nld_x_preferred":[
        "Sarsawan"
    ],
    "name:pol_x_preferred":[
        "Sarsawan"
    ],
    "name:por_x_preferred":[
        "Sarsawan"
    ],
    "name:urd_x_preferred":[
        "\u0633\u0631\u0633\u0627\u0648\u0627"
    ],
    "name:vie_x_preferred":[
        "Sarsawan"
    ],
    "name:zho_x_preferred":[
        "\u8428\u5c14\u8428\u4e07"
    ],
    "wof:name":"Sarsawa",
    "wof:placetype":"locality"
},
  "geometry": {"coordinates":[82.48945000000001,26.25281],"type":"Point"}
}