{
  "type": "Feature",
  "properties": {
    "iso:country":"IN",
    "ks:ks_name":"Kunissery",
    "ks:ks_pop":510,
    "ks:ks_type":"HABITATION",
    "name:eng_x_preferred":[
        "Kunissery"
    ],
    "wof:name":"Kunissery",
    "wof:placetype":"locality",
    "wof:population":510
},
  "geometry": {"coordinates":[76.60518999999999,10.634709],"type":"Point"}
}