{
  "type": "Feature",
  "properties": {
    "iso:country":"IN",
    "ks:ks_name":"Salemakki",
    "ks:ks_pop":132,
    "ks:ks_type":"HABITATION",
    "name:eng_x_preferred":[
        "Salemakki"
    ],
    "wof:name":"Salemakki",
    "wof:placetype":"locality",
    "wof:population":132
},
  "geometry": {"coordinates":[74.575594,14.251901],"type":"Point"}
}