{
  "type": "Feature",
  "properties": {
    "gn:admin1_code":"13",
    "gn:admin2_code":"599.0",
    "gn:asciiname":"Rani",
    "gn:country_code":"IN",
    "gn:dem":143,
    "gn:feature_class":"P",
    "gn:feature_code":"PPL",
    "gn:name":"R\u0101n\u012b",
    "gn:population":0,
    "gn:timezone":"Asia/Kolkata",
    "iso:country":"IN",
    "name:ben_x_preferred":[
        "\u09b0\u09be\u09a8\u09c0"
    ],
    "name:nld_x_preferred":[
        "Rani"
    ],
    "name:urd_x_preferred":[
        "\u0631\u0627\u0646\u06cc"
    ],
    "wof:name":"Rani",
    "wof:placetype":"locality"
},
  "geometry": {"coordinates":[76.81667,9.38333],"type":"Point"}
}