{
  "type": "Feature",
  "properties": {
    "iso:country":"IN",
    "ks:ks_name":"Dobiya Tal",
    "ks:ks_pop":7,
    "ks:ks_type":"HABITATION",
    "name:eng_x_preferred":[
        "Dobiya Tal"
    ],
    "wof:name":"Dobiya Tal",
    "wof:placetype":"locality",
    "wof:population":7
},
  "geometry": {"coordinates":[79.35252,29.954315],"type":"Point"}
}