{
  "type": "Feature",
  "properties": {
    "gn:admin1_code":"34.0",
    "gn:admin2_code":"236.0",
    "gn:asciiname":"Hichhapur",
    "gn:country_code":"IN",
    "gn:dem":102,
    "gn:feature_class":"P",
    "gn:feature_code":"PPL",
    "gn:name":"Hichh\u0101pur",
    "gn:population":0,
    "gn:timezone":"Asia/Kolkata",
    "iso:country":"IN",
    "wof:name":"Hichhapur",
    "wof:placetype":"locality"
},
  "geometry": {"coordinates":[84.83903000000002,24.90231],"type":"Point"}
}