{
  "type": "Feature",
  "properties": {
    "iso:country":"IN",
    "ks:ks_name":"Khandatada",
    "ks:ks_pop":2368,
    "ks:ks_type":"HABITATION",
    "name:eng_x_preferred":[
        "Khandatada"
    ],
    "wof:name":"Khandatada",
    "wof:placetype":"locality",
    "wof:population":2368
},
  "geometry": {"coordinates":[86.523475,21.002684],"type":"Point"}
}