{
  "type": "Feature",
  "properties": {
    "iso:country":"IN",
    "ks:ks_name":"Vishunpur Banwa Basti",
    "ks:ks_pop":641,
    "ks:ks_type":"HABITATION",
    "name:eng_x_preferred":[
        "Vishunpur Banwa Basti"
    ],
    "wof:name":"Vishunpur Banwa Basti",
    "wof:placetype":"locality",
    "wof:population":641
},
  "geometry": {"coordinates":[83.467462,25.384637],"type":"Point"}
}