{
  "type": "Feature",
  "properties": {
    "gn:admin1_code":"16",
    "gn:admin2_code":"510.0",
    "gn:asciiname":"Aloda",
    "gn:country_code":"IN",
    "gn:dem":249,
    "gn:feature_class":"P",
    "gn:feature_code":"PPL",
    "gn:name":"\u0100loda",
    "gn:population":0,
    "gn:timezone":"Asia/Kolkata",
    "iso:country":"IN",
    "name:bul_x_preferred":[
        "\u0410\u043b\u043e\u0434\u0430"
    ],
    "name:ell_x_preferred":[
        "\u0391\u03c4\u03bb\u03b9\u03bb\u03ac\u03c1"
    ],
    "name:fas_x_preferred":[
        "\u0627\u0644\u0648\u062f\u0627"
    ],
    "name:hye_x_preferred":[
        "\u0531\u056c\u0578\u0564\u0561"
    ],
    "name:msa_x_preferred":[
        "Aloda"
    ],
    "name:pol_x_preferred":[
        "Aloda"
    ],
    "name:urd_x_preferred":[
        "\u0622\u0644\u0648\u062f\u0627"
    ],
    "wof:name":"Aloda",
    "wof:placetype":"locality"
},
  "geometry": {"coordinates":[78.33672,20.51936],"type":"Point"}
}