{
  "type": "Feature",
  "properties": {
    "iso:country":"IN",
    "ks:ks_alt_nam":"MOGEWASTI",
    "ks:ks_name":"Mogewasti",
    "ks:ks_pop":84,
    "ks:ks_type":"HABITATION",
    "name:eng_x_preferred":[
        "Mogewasti"
    ],
    "wof:name":"Mogewasti",
    "wof:placetype":"locality",
    "wof:population":84
},
  "geometry": {"coordinates":[74.317046,17.347288],"type":"Point"}
}