{
  "type": "Feature",
  "properties": {
    "iso:country":"IN",
    "ks:ks_name":"Bangara",
    "ks:ks_pop":327,
    "ks:ks_type":"VILLAGE",
    "name:eng_x_preferred":[
        "Bangara"
    ],
    "wof:name":"Bangara",
    "wof:placetype":"locality",
    "wof:population":327
},
  "geometry": {"coordinates":[86.742869,22.225889],"type":"Point"}
}