{
  "type": "Feature",
  "properties": {
    "gn:admin1_code":"40",
    "gn:admin2_code":"538.0",
    "gn:asciiname":"Parusapur",
    "gn:country_code":"IN",
    "gn:dem":552,
    "gn:feature_class":"P",
    "gn:feature_code":"PPL",
    "gn:name":"Parusapur",
    "gn:population":0,
    "gn:timezone":"Asia/Kolkata",
    "iso:country":"IN",
    "wof:name":"Parusapur",
    "wof:placetype":"neighbourhood"
},
  "geometry": {"coordinates":[77.58750000000001,16.91229],"type":"Point"}
}