{
  "type": "Feature",
  "properties": {
    "iso:country":"IN",
    "ks:ks_name":"Matiyal",
    "ks:ks_pop":14,
    "ks:ks_type":"HABITATION",
    "name:eng_x_preferred":[
        "Matiyal"
    ],
    "wof:name":"Matiyal",
    "wof:placetype":"locality",
    "wof:population":14
},
  "geometry": {"coordinates":[79.980508,29.658238],"type":"Point"}
}