{
  "type": "Feature",
  "properties": {
    "gn:admin1_code":"36",
    "gn:admin2_code":"146.0",
    "gn:asciiname":"Garhi Kharagjit",
    "gn:country_code":"IN",
    "gn:dem":166,
    "gn:feature_class":"P",
    "gn:feature_code":"PPL",
    "gn:name":"Garhi Kharagj\u012bt",
    "gn:population":0,
    "gn:timezone":"Asia/Kolkata",
    "iso:country":"IN",
    "wof:name":"Garhi Kharagjit",
    "wof:placetype":"locality"
},
  "geometry": {"coordinates":[78.23220000000001,27.00379],"type":"Point"}
}