{
  "type": "Feature",
  "properties": {
    "gn:admin1_code":"36",
    "gn:admin2_code":"146.0",
    "gn:asciiname":"Garhi Kharagjit",
    "gn:country_code":"IN",
    "gn:dem":166,
    "gn:feature_class":"P",
    "gn:feature_code":"PPL",
    "gn:name":"Garhi Kharagj\u012bt",
    "gn:population":0,
    "gn:timezone":"Asia/Kolkata",
    "iso:country":"IN",
    "ks:ks_name":"Garhi Kharagjit",
    "ks:ks_pop":72,
    "ks:ks_type":"HABITATION",
    "name:eng_x_preferred":[
        "Garhi Kharagjit"
    ],
    "wof:name":"Garhi Kharagjit",
    "wof:placetype":"locality",
    "wof:population":72
},
  "geometry": {"coordinates":[78.233921,27.005154],"type":"Point"}
}