{
  "type": "Feature",
  "properties": {
    "iso:country":"IN",
    "ks:ks_name":"Krishan Nagar",
    "ks:ks_pop":522,
    "ks:ks_type":"HABITATION",
    "name:eng_x_preferred":[
        "Krishan Nagar"
    ],
    "wof:name":"Krishan Nagar",
    "wof:placetype":"locality",
    "wof:population":522
},
  "geometry": {"coordinates":[71.107669,27.287469],"type":"Point"}
}