{
  "type": "Feature",
  "properties": {
    "gn:admin1_code":"2.0",
    "gn:admin2_code":"553.0",
    "gn:asciiname":"Udegolam",
    "gn:country_code":"IN",
    "gn:dem":451,
    "gn:feature_class":"P",
    "gn:feature_code":"PPL",
    "gn:name":"Udegolam",
    "gn:population":0,
    "gn:timezone":"Asia/Kolkata",
    "iso:country":"IN",
    "name:fas_x_preferred":[
        "\u06cc\u0648\u062f\u06af\u0648\u0644\u0645"
    ],
    "name:urd_x_preferred":[
        "\u0627\u062f\u06d2 \u06af\u0648\u0644\u0645"
    ],
    "wof:name":"Udegolam",
    "wof:placetype":"locality"
},
  "geometry": {"coordinates":[77.0775,14.85201],"type":"Point"}
}