{
  "type": "Feature",
  "properties": {
    "iso:country":"IN",
    "ks:ks_name":"Nalpathu Cent Jn",
    "ks:ks_pop":752,
    "ks:ks_type":"HABITATION",
    "name:eng_x_preferred":[
        "Nalpathu Cent Jn"
    ],
    "wof:name":"Nalpathu Cent Jn",
    "wof:placetype":"locality",
    "wof:population":752
},
  "geometry": {"coordinates":[76.35246600000001,11.23494],"type":"Point"}
}