{
  "type": "Feature",
  "properties": {
    "iso:country":"IN",
    "ks:ks_name":"Madoi",
    "ks:ks_pop":369,
    "ks:ks_type":"VILLAGE",
    "ks:ks_uagg_main":0,
    "name:eng_x_preferred":[
        "Madoi"
    ],
    "wof:name":"Madoi",
    "wof:placetype":"neighbourhood",
    "wof:population":369
},
  "geometry": {"coordinates":[82.27042,26.83306],"type":"Point"}
}