{
  "type": "Feature",
  "properties": {
    "iso:country":"IN",
    "ks:ks_name":"Shekhpur",
    "ks:ks_pop":3998,
    "ks:ks_type":"VILLAGE",
    "name:eng_x_preferred":[
        "Shekhpur"
    ],
    "wof:name":"Shekhpur",
    "wof:placetype":"locality",
    "wof:population":3998
},
  "geometry": {"coordinates":[73.165239,21.010008],"type":"Point"}
}