{
  "type": "Feature",
  "properties": {
    "iso:country":"IN",
    "ks:ks_name":"Kedarwadi",
    "ks:ks_pop":53,
    "ks:ks_type":"HABITATION",
    "name:eng_x_preferred":[
        "Kedarwadi"
    ],
    "wof:name":"Kedarwadi",
    "wof:placetype":"locality",
    "wof:population":53
},
  "geometry": {"coordinates":[73.72122,15.768655],"type":"Point"}
}