{
  "type": "Feature",
  "properties": {
    "iso:country":"IN",
    "ks:ks_name":"Chhota Dhanua",
    "ks:ks_pop":170,
    "ks:ks_type":"HABITATION",
    "name:eng_x_preferred":[
        "Chhota Dhanua"
    ],
    "wof:name":"Chhota Dhanua",
    "wof:placetype":"locality",
    "wof:population":170
},
  "geometry": {"coordinates":[81.4187,26.3698],"type":"Point"}
}