{
  "type": "Feature",
  "properties": {
    "iso:country":"IN",
    "ks:ks_alt_nam":"Pardhe wasti",
    "ks:ks_name":"Pardhe Wasti",
    "ks:ks_pop":310,
    "ks:ks_type":"HABITATION",
    "name:eng_x_preferred":[
        "Pardhe Wasti"
    ],
    "wof:name":"Pardhe Wasti",
    "wof:placetype":"locality",
    "wof:population":310
},
  "geometry": {"coordinates":[75.340356,19.348179],"type":"Point"}
}