{
  "type": "Feature",
  "properties": {
    "iso:country":"IN",
    "ks:ks_name":"Hannpasigaon",
    "ks:ks_pop":1511,
    "ks:ks_type":"HABITATION",
    "name:eng_x_preferred":[
        "Hannpasigaon"
    ],
    "wof:name":"Hannpasigaon",
    "wof:placetype":"locality",
    "wof:population":1511
},
  "geometry": {"coordinates":[80.24093999999999,27.746619],"type":"Point"}
}