{
  "type": "Feature",
  "properties": {
    "iso:country":"IN",
    "ks:ks_name":"Nov Tolia",
    "ks:ks_pop":281,
    "ks:ks_type":"HABITATION",
    "name:eng_x_preferred":[
        "Nov Tolia"
    ],
    "wof:name":"Nov Tolia",
    "wof:placetype":"locality",
    "wof:population":281
},
  "geometry": {"coordinates":[86.993863,25.909997],"type":"Point"}
}