{
  "type": "Feature",
  "properties": {
    "gn:admin1_code":"2",
    "gn:admin2_code":"546.0",
    "gn:asciiname":"Kotturu",
    "gn:country_code":"IN",
    "gn:dem":19,
    "gn:feature_class":"P",
    "gn:feature_code":"PPL",
    "gn:name":"Kott\u016bru",
    "gn:population":0,
    "gn:timezone":"Asia/Kolkata",
    "iso:country":"IN",
    "wof:name":"Kotturu",
    "wof:placetype":"locality"
},
  "geometry": {"coordinates":[81.58835999999999,16.83131],"type":"Point"}
}