{
  "type": "Feature",
  "properties": {
    "iso:country":"IN",
    "ks:ks_name":"Bishanpur",
    "ks:ks_pop":742,
    "ks:ks_type":"VILLAGE",
    "ks:ks_uagg_main":0,
    "name:eng_x_preferred":[
        "Bishanpur"
    ],
    "wof:name":"Bishanpur",
    "wof:placetype":"neighbourhood",
    "wof:population":742
},
  "geometry": {"coordinates":[78.52297299999999,29.729275],"type":"Point"}
}