{
  "type": "Feature",
  "properties": {
    "iso:country":"IN",
    "ks:ks_name":"Dasili",
    "ks:ks_pop":539,
    "ks:ks_type":"VILLAGE",
    "name:eng_x_preferred":[
        "Dasili"
    ],
    "wof:name":"Dasili",
    "wof:placetype":"locality",
    "wof:population":539
},
  "geometry": {"coordinates":[79.91794,29.55081],"type":"Point"}
}