{
  "type": "Feature",
  "properties": {
    "iso:country":"IN",
    "ks:ks_name":"Dhangharwadi",
    "ks:ks_pop":22,
    "ks:ks_type":"HABITATION",
    "name:eng_x_preferred":[
        "Dhangharwadi"
    ],
    "wof:name":"Dhangharwadi",
    "wof:placetype":"locality",
    "wof:population":22
},
  "geometry": {"coordinates":[73.355377,18.213728],"type":"Point"}
}