{
  "type": "Feature",
  "properties": {
    "gn:admin1_code":"36.0",
    "gn:admin2_code":"193.0",
    "gn:asciiname":"Partabpur",
    "gn:country_code":"IN",
    "gn:dem":60,
    "gn:feature_class":"P",
    "gn:feature_code":"PPL",
    "gn:name":"Part\u0101bpur",
    "gn:population":0,
    "gn:timezone":"Asia/Kolkata",
    "iso:country":"IN",
    "wof:name":"Partabpur",
    "wof:placetype":"locality"
},
  "geometry": {"coordinates":[84.2167,25.79731],"type":"Point"}
}