{
  "type": "Feature",
  "properties": {
    "iso:country":"IN",
    "ks:ks_name":"Kukuti",
    "ks:ks_pop":314,
    "ks:ks_type":"VILLAGE",
    "name:eng_x_preferred":[
        "Kukuti"
    ],
    "wof:name":"Kukuti",
    "wof:placetype":"locality",
    "wof:population":314
},
  "geometry": {"coordinates":[84.628677,20.531285],"type":"Point"}
}