{
  "type": "Feature",
  "properties": {
    "gn:admin1_code":"36.0",
    "gn:admin2_code":"179.0",
    "gn:asciiname":"Haidna Kalan",
    "gn:country_code":"IN",
    "gn:dem":108,
    "gn:feature_class":"P",
    "gn:feature_code":"PPL",
    "gn:name":"Haidna Kal\u0101n",
    "gn:population":0,
    "gn:timezone":"Asia/Kolkata",
    "iso:country":"IN",
    "ks:ks_name":"Haidhana Kalan",
    "ks:ks_pop":532,
    "ks:ks_type":"VILLAGE",
    "ks:ks_uagg_main":0,
    "name:eng_x_preferred":[
        "Haidhana Kalan"
    ],
    "wof:name":"Haidhana Kalan",
    "wof:placetype":"neighbourhood",
    "wof:population":532
},
  "geometry": {"coordinates":[81.895849,26.457526],"type":"Point"}
}