{
  "type": "Feature",
  "properties": {
    "iso:country":"IN",
    "ks:ks_name":"Lakhangaon",
    "ks:ks_pop":16,
    "ks:ks_type":"VILLAGE",
    "name:eng_x_preferred":[
        "Lakhangaon"
    ],
    "wof:name":"Lakhangaon",
    "wof:placetype":"locality",
    "wof:population":16
},
  "geometry": {"coordinates":[75.606954,22.153523],"type":"Point"}
}