{
  "type": "Feature",
  "properties": {
    "iso:country":"IN",
    "ks:ks_alt_nam":"B\u0101mulda",
    "ks:ks_name":"Bamulda",
    "ks:ks_pop":840,
    "ks:ks_type":"VILLAGE",
    "name:eng_x_preferred":[
        "Bamulda"
    ],
    "name:eng_x_variant":[
        "B\u0101mulda"
    ],
    "wof:name":"Bamulda",
    "wof:placetype":"locality",
    "wof:population":840
},
  "geometry": {"coordinates":[84.918645,22.608565],"type":"Point"}
}