{
  "type": "Feature",
  "properties": {
    "iso:country":"IN",
    "ks:ks_name":"Pachna",
    "ks:ks_pop":0,
    "ks:ks_type":"VILLAGE",
    "name:eng_x_preferred":[
        "Pachna"
    ],
    "wof:name":"Pachna",
    "wof:placetype":"locality",
    "wof:population":0
},
  "geometry": {"coordinates":[87.29032599999999,25.56357],"type":"Point"}
}