{
  "type": "Feature",
  "properties": {
    "iso:country":"IN",
    "ks:ks_name":"Khas Jangal",
    "ks:ks_pop":117,
    "ks:ks_type":"VILLAGE",
    "ks:ks_uagg_main":0,
    "name:eng_x_preferred":[
        "Khas Jangal"
    ],
    "wof:name":"Khas Jangal",
    "wof:placetype":"neighbourhood",
    "wof:population":117
},
  "geometry": {"coordinates":[86.891774,22.396118],"type":"Point"}
}