{
  "type": "Feature",
  "properties": {
    "iso:country":"IN",
    "ks:ks_name":"Kandapadar",
    "ks:ks_pop":68,
    "ks:ks_type":"HABITATION",
    "name:eng_x_preferred":[
        "Kandapadar"
    ],
    "wof:name":"Kandapadar",
    "wof:placetype":"locality",
    "wof:population":68
},
  "geometry": {"coordinates":[82.988105,19.378367],"type":"Point"}
}