{
  "type": "Feature",
  "properties": {
    "gn:admin1_code":"34.0",
    "gn:admin2_code":"220.0",
    "gn:asciiname":"Chak Said",
    "gn:country_code":"IN",
    "gn:dem":55,
    "gn:feature_class":"P",
    "gn:feature_code":"PPL",
    "gn:name":"Chak Said",
    "gn:population":0,
    "gn:timezone":"Asia/Kolkata",
    "iso:country":"IN",
    "ks:ks_name":"Chak Said",
    "ks:ks_pop":865,
    "ks:ks_type":"VILLAGE",
    "name:eng_x_preferred":[
        "Chak Said"
    ],
    "wof:name":"Chak Said",
    "wof:placetype":"locality",
    "wof:population":865
},
  "geometry": {"coordinates":[85.48533,25.876724],"type":"Point"}
}