{
  "type": "Feature",
  "properties": {
    "gn:admin1_code":"02",
    "gn:admin2_code":"554.0",
    "gn:asciiname":"Vayalpad",
    "gn:country_code":"IN",
    "gn:dem":597,
    "gn:feature_class":"P",
    "gn:feature_code":"PPL",
    "gn:name":"V\u0101yalp\u0101d",
    "gn:population":0,
    "gn:timezone":"Asia/Kolkata",
    "iso:country":"IN",
    "wof:name":"Vayalpad",
    "wof:placetype":"neighbourhood"
},
  "geometry": {"coordinates":[78.62991,13.63732],"type":"Point"}
}