{
  "type": "Feature",
  "properties": {
    "gn:admin1_code":"35",
    "gn:admin2_code":"463.0",
    "gn:asciiname":"Bakhul",
    "gn:country_code":"IN",
    "gn:dem":421,
    "gn:feature_class":"P",
    "gn:feature_code":"PPL",
    "gn:name":"Bakhul",
    "gn:population":0,
    "gn:timezone":"Asia/Kolkata",
    "iso:country":"IN",
    "name:und_x_variant":[
        "Chund\u0101na"
    ],
    "wof:name":"Bakhul",
    "wof:placetype":"locality"
},
  "geometry": {"coordinates":[82.30077,24.09367],"type":"Point"}
}