{
  "type": "Feature",
  "properties": {
    "gn:admin1_code":"25",
    "gn:admin2_code":"604.0",
    "gn:asciiname":"Santhakuppam",
    "gn:country_code":"IN",
    "gn:dem":49,
    "gn:feature_class":"P",
    "gn:feature_code":"PPL",
    "gn:name":"Santhakuppam",
    "gn:population":0,
    "gn:timezone":"Asia/Kolkata",
    "iso:country":"IN",
    "ks:ks_name":"Santhakuppam",
    "ks:ks_pop":150,
    "ks:ks_type":"HABITATION",
    "ks:ks_uagg_main":0,
    "name:eng_x_preferred":[
        "Santhakuppam"
    ],
    "wof:name":"Santhakuppam",
    "wof:placetype":"neighbourhood",
    "wof:population":150
},
  "geometry": {"coordinates":[80.065668,12.719602],"type":"Point"}
}