{
  "type": "Feature",
  "properties": {
    "gn:admin1_code":"12.0",
    "gn:admin2_code":"18.0",
    "gn:asciiname":"Dunwar",
    "gn:country_code":"IN",
    "gn:dem":2509,
    "gn:feature_class":"P",
    "gn:feature_code":"PPL",
    "gn:name":"D\u016bnw\u0101r",
    "gn:population":0,
    "gn:timezone":"Asia/Kolkata",
    "iso:country":"IN",
    "wof:name":"Dunwar",
    "wof:placetype":"locality"
},
  "geometry": {"coordinates":[75.68037,33.47095],"type":"Point"}
}