{
  "type": "Feature",
  "properties": {
    "iso:country":"IN",
    "ks:ks_name":"Ghongadipada",
    "ks:ks_pop":260,
    "ks:ks_type":"HABITATION",
    "name:eng_x_preferred":[
        "Ghongadipada"
    ],
    "wof:name":"Ghongadipada",
    "wof:placetype":"locality",
    "wof:population":260
},
  "geometry": {"coordinates":[73.36027799999999,20.044444],"type":"Point"}
}