{
  "type": "Feature",
  "properties": {
    "iso:country":"IN",
    "ks:ks_name":"Khasia",
    "ks:ks_pop":695,
    "ks:ks_type":"VILLAGE",
    "name:eng_x_preferred":[
        "Khasia"
    ],
    "wof:name":"Khasia",
    "wof:placetype":"locality",
    "wof:population":695
},
  "geometry": {"coordinates":[87.123178,24.510655],"type":"Point"}
}