{
  "type": "Feature",
  "properties": {
    "gn:admin1_code":"36.0",
    "gn:admin2_code":"149.0",
    "gn:asciiname":"Bijauri",
    "gn:country_code":"IN",
    "gn:dem":185,
    "gn:feature_class":"P",
    "gn:feature_code":"PPL",
    "gn:name":"Bijauri",
    "gn:population":0,
    "gn:timezone":"Asia/Kolkata",
    "iso:country":"IN",
    "name:ceb_x_preferred":[
        "Bijauri"
    ],
    "name:hin_x_preferred":[
        "\u092c\u093f\u091c\u094c\u0930\u0940"
    ],
    "name:mai_x_preferred":[
        "\u092c\u093f\u091c\u094c\u0930\u0940"
    ],
    "name:msa_x_preferred":[
        "Bijauri"
    ],
    "name:nep_x_preferred":[
        "\u092c\u093f\u091c\u094c\u0930\u0940"
    ],
    "name:new_x_preferred":[
        "\u092c\u093f\u091c\u094c\u0930\u0940"
    ],
    "name:pol_x_preferred":[
        "Bijauri"
    ],
    "wof:name":"Bijauri",
    "wof:placetype":"locality"
},
  "geometry": {"coordinates":[78.98078000000002,28.40329],"type":"Point"}
}