{
  "type": "Feature",
  "properties": {
    "gn:admin1_code":"34.0",
    "gn:admin2_code":"222.0",
    "gn:asciiname":"Muhammadpur Fatah",
    "gn:country_code":"IN",
    "gn:dem":46,
    "gn:feature_class":"P",
    "gn:feature_code":"PPL",
    "gn:name":"Muhammadpur Fatah",
    "gn:population":0,
    "gn:timezone":"Asia/Kolkata",
    "iso:country":"IN",
    "ks:ks_name":"Mahammadpur Fata",
    "ks:ks_pop":0,
    "ks:ks_type":"VILLAGE",
    "name:eng_x_preferred":[
        "Mahammadpur Fata"
    ],
    "name:eng_x_variant":[
        "Muhammadpur Fatah"
    ],
    "wof:name":"Mahammadpur Fata",
    "wof:placetype":"locality",
    "wof:population":0
},
  "geometry": {"coordinates":[85.882974,25.536618],"type":"Point"}
}