{
  "type": "Feature",
  "properties": {
    "iso:country":"IN",
    "ks:ks_name":"Dakua",
    "ks:ks_pop":0,
    "ks:ks_type":"VILLAGE",
    "name:eng_x_preferred":[
        "Dakua"
    ],
    "wof:name":"Dakua",
    "wof:placetype":"locality",
    "wof:population":0
},
  "geometry": {"coordinates":[93.87369,26.803704],"type":"Point"}
}