{
  "type": "Feature",
  "properties": {
    "gn:admin1_code":"2.0",
    "gn:admin2_code":"547.0",
    "gn:asciiname":"Velpuru",
    "gn:country_code":"IN",
    "gn:dem":12,
    "gn:feature_class":"P",
    "gn:feature_code":"PPL",
    "gn:name":"Velp\u016bru",
    "gn:population":0,
    "gn:timezone":"Asia/Kolkata",
    "iso:country":"IN",
    "name:tel_x_preferred":[
        "\u0c35\u0c47\u0c32\u0c4d\u0c2a\u0c42\u0c30\u0c41"
    ],
    "wof:name":"Velpuru",
    "wof:placetype":"locality"
},
  "geometry": {"coordinates":[80.8965,16.31828],"type":"Point"}
}