{
  "type": "Feature",
  "properties": {
    "iso:country":"IN",
    "ks:ks_name":"Durai Eri",
    "ks:ks_pop":616,
    "ks:ks_type":"HABITATION",
    "name:eng_x_preferred":[
        "Durai Eri"
    ],
    "wof:name":"Durai Eri",
    "wof:placetype":"locality",
    "wof:population":616
},
  "geometry": {"coordinates":[78.32316899999999,12.640005],"type":"Point"}
}