{
  "type": "Feature",
  "properties": {
    "iso:country":"IN",
    "ks:ks_name":"Chauphal",
    "ks:ks_pop":97,
    "ks:ks_type":"VILLAGE",
    "name:eng_x_preferred":[
        "Chauphal"
    ],
    "wof:name":"Chauphal",
    "wof:placetype":"locality",
    "wof:population":97
},
  "geometry": {"coordinates":[86.71247,24.547964],"type":"Point"}
}