{
  "type": "Feature",
  "properties": {
    "iso:country":"IN",
    "ks:ks_name":"Dadhkia",
    "ks:ks_pop":1236,
    "ks:ks_type":"VILLAGE",
    "name:eng_x_preferred":[
        "Dadhkia"
    ],
    "wof:name":"Dadhkia",
    "wof:placetype":"locality",
    "wof:population":1236
},
  "geometry": {"coordinates":[85.928969,23.625613],"type":"Point"}
}