{
  "type": "Feature",
  "properties": {
    "iso:country":"IN",
    "ks:ks_name":"Macharipady",
    "ks:ks_pop":700,
    "ks:ks_type":"HABITATION",
    "name:eng_x_preferred":[
        "Macharipady"
    ],
    "wof:name":"Macharipady",
    "wof:placetype":"locality",
    "wof:population":700
},
  "geometry": {"coordinates":[77.03017199999999,9.973375],"type":"Point"}
}