{
  "type": "Feature",
  "properties": {
    "iso:country":"IN",
    "name:bpy_x_preferred":[
        "\u09a5\u09bf\u09b0\u09c1\u09a8\u0997\u09b0"
    ],
    "name:ceb_x_preferred":[
        "Thirunagar Park"
    ],
    "name:eng_x_preferred":[
        "Thirunagar"
    ],
    "name:fra_x_preferred":[
        "Thirunagar"
    ],
    "name:ita_x_preferred":[
        "Thirunagar"
    ],
    "name:msa_x_preferred":[
        "Thirunagar"
    ],
    "name:nan_x_preferred":[
        "Thirunagar"
    ],
    "name:nld_x_preferred":[
        "Thirunagar"
    ],
    "name:por_x_preferred":[
        "Thirunagar"
    ],
    "name:swe_x_preferred":[
        "Thirunagar Park"
    ],
    "name:tam_x_preferred":[
        "\u0ba4\u0bbf\u0bb0\u0bc1\u0ba8\u0b95\u0bb0\u0bcd"
    ],
    "name:vie_x_preferred":[
        "Thirunagar"
    ],
    "name:zho_x_preferred":[
        "\u8482\u9c81\u7eb3\u52a0\u5c14"
    ],
    "qs:name":"Thirunagar",
    "qs:name_adm0":"India",
    "qs:name_adm1":"Tamil Nadu",
    "qs:photos":66,
    "qs:photos_1k":13,
    "qs:photos_9k":1,
    "qs:photos_9r":2,
    "qs:photos_all":66,
    "qs:photos_sr":2,
    "qs:placetype":"Town",
    "qs:pop_sr":"0",
    "wd:wordcount":594,
    "wof:name":"Thirunagar",
    "wof:placetype":"neighbourhood"
},
  "geometry": {"coordinates":[78.065757,9.880119],"type":"Point"}
}