{
  "type": "Feature",
  "properties": {
    "iso:country":"IN",
    "ks:ks_name":"Seeranagoundenpalayam",
    "ks:ks_pop":370,
    "ks:ks_type":"HABITATION",
    "ks:ks_uagg_main":0,
    "name:eng_x_preferred":[
        "Seeranagoundenpalayam"
    ],
    "wof:name":"Seeranagoundenpalayam",
    "wof:placetype":"locality",
    "wof:population":370
},
  "geometry": {"coordinates":[77.54724899999999,11.314326],"type":"Point"}
}