{
  "type": "Feature",
  "properties": {
    "iso:country":"IN",
    "ks:ks_name":"Dhraha (m)",
    "ks:ks_pop":443,
    "ks:ks_type":"HABITATION",
    "name:eng_x_preferred":[
        "Dhraha (m)"
    ],
    "wof:name":"Dhraha (m)",
    "wof:placetype":"locality",
    "wof:population":443
},
  "geometry": {"coordinates":[82.912429,26.55117],"type":"Point"}
}