{
  "type": "Feature",
  "properties": {
    "gn:admin1_code":"34.0",
    "gn:admin2_code":"230.0",
    "gn:asciiname":"Arari",
    "gn:country_code":"IN",
    "gn:dem":64,
    "gn:feature_class":"P",
    "gn:feature_code":"PPL",
    "gn:name":"Ar\u0101ri",
    "gn:population":0,
    "gn:timezone":"Asia/Kolkata",
    "iso:country":"IN",
    "name:bpy_x_preferred":[
        "\u09f1\u09be\u09b0\u09be\u09b0\u09bf"
    ],
    "name:eus_x_preferred":[
        "Arari"
    ],
    "name:fra_x_preferred":[
        "Arari"
    ],
    "name:hye_x_preferred":[
        "\u0531\u0580\u0561\u0580\u056b"
    ],
    "name:ita_x_preferred":[
        "Arari"
    ],
    "name:kat_x_preferred":[
        "\u10d0\u10e0\u10d0\u10e0\u10d8"
    ],
    "name:kaz_x_preferred":[
        "\u0410\u0440\u0430\u0440\u0438"
    ],
    "name:nld_x_preferred":[
        "Arari"
    ],
    "name:nor_x_preferred":[
        "Arari"
    ],
    "name:pol_x_preferred":[
        "Arari"
    ],
    "name:por_x_preferred":[
        "Arari"
    ],
    "name:ron_x_preferred":[
        "Arari"
    ],
    "name:rus_x_preferred":[
        "\u0410\u0440\u0430\u0440\u0438"
    ],
    "name:spa_x_preferred":[
        "Arari"
    ],
    "name:tet_x_preferred":[
        "Arari"
    ],
    "name:vie_x_preferred":[
        "Arari"
    ],
    "name:vol_x_preferred":[
        "Arari"
    ],
    "name:war_x_preferred":[
        "Arari"
    ],
    "name:zho_x_preferred":[
        "\u963f\u62c9\u91cc"
    ],
    "wof:name":"Arari",
    "wof:placetype":"locality"
},
  "geometry": {"coordinates":[84.90420999999998,25.33289],"type":"Point"}
}