{
  "type": "Feature",
  "properties": {
    "iso:country":"IN",
    "ks:ks_name":"Santa Singh Dhani",
    "ks:ks_pop":835,
    "ks:ks_type":"HABITATION",
    "name:eng_x_preferred":[
        "Santa Singh Dhani"
    ],
    "wof:name":"Santa Singh Dhani",
    "wof:placetype":"locality",
    "wof:population":835
},
  "geometry": {"coordinates":[74.22775799999999,30.307779],"type":"Point"}
}