{
  "type": "Feature",
  "properties": {
    "gn:admin1_code":"2.0",
    "gn:admin2_code":"554.0",
    "gn:asciiname":"Ranginayanipalle",
    "gn:country_code":"IN",
    "gn:dem":675,
    "gn:feature_class":"P",
    "gn:feature_code":"PPL",
    "gn:name":"Rangin\u0101yanipalle",
    "gn:population":0,
    "gn:timezone":"Asia/Kolkata",
    "iso:country":"IN",
    "wof:name":"Ranginayanipalle",
    "wof:placetype":"locality"
},
  "geometry": {"coordinates":[78.70685,13.18994],"type":"Point"}
}