{
  "type": "Feature",
  "properties": {
    "iso:country":"IN",
    "ks:ks_name":"Baradangapadar",
    "ks:ks_pop":120,
    "ks:ks_type":"VILLAGE",
    "name:eng_x_preferred":[
        "Baradangapadar"
    ],
    "wof:name":"Baradangapadar",
    "wof:placetype":"locality",
    "wof:population":120
},
  "geometry": {"coordinates":[83.578012,19.478609],"type":"Point"}
}