{
  "type": "Feature",
  "properties": {
    "iso:country":"IN",
    "ks:ks_alt_nam":"BABHAN GAMA",
    "ks:ks_name":"Babhan Gama",
    "ks:ks_pop":6783,
    "ks:ks_type":"HABITATION",
    "name:eng_x_preferred":[
        "Babhan Gama"
    ],
    "wof:name":"Babhan Gama",
    "wof:placetype":"locality",
    "wof:population":6783
},
  "geometry": {"coordinates":[86.632453,26.073608],"type":"Point"}
}