{
  "type": "Feature",
  "properties": {
    "iso:country":"IN",
    "ks:ks_name":"Bhatora",
    "ks:ks_pop":858,
    "ks:ks_type":"HABITATION",
    "name:eng_x_preferred":[
        "Bhatora"
    ],
    "wof:name":"Bhatora",
    "wof:placetype":"locality",
    "wof:population":858
},
  "geometry": {"coordinates":[82.603939,22.325027],"type":"Point"}
}