{
  "type": "Feature",
  "properties": {
    "iso:country":"IN",
    "ks:ks_name":"Thar Hari Ram",
    "ks:ks_pop":251,
    "ks:ks_type":"HABITATION",
    "name:eng_x_preferred":[
        "Thar Hari Ram"
    ],
    "wof:name":"Thar Hari Ram",
    "wof:placetype":"locality",
    "wof:population":251
},
  "geometry": {"coordinates":[78.26141200000001,27.133463],"type":"Point"}
}