{
  "type": "Feature",
  "properties": {
    "iso:country":"IN",
    "ks:ks_alt_nam":"TALAB FALI",
    "ks:ks_name":"Talab Fali",
    "ks:ks_pop":200,
    "ks:ks_type":"HABITATION",
    "name:eng_x_preferred":[
        "Talab Fali"
    ],
    "wof:name":"Talab Fali",
    "wof:placetype":"locality",
    "wof:population":200
},
  "geometry": {"coordinates":[72.72882799999999,24.407369],"type":"Point"}
}