{
  "type": "Feature",
  "properties": {
    "iso:country":"IN",
    "ks:ks_name":"Pabu Nagar",
    "ks:ks_pop":374,
    "ks:ks_type":"HABITATION",
    "name:eng_x_preferred":[
        "Pabu Nagar"
    ],
    "wof:name":"Pabu Nagar",
    "wof:placetype":"locality",
    "wof:population":374
},
  "geometry": {"coordinates":[72.526197,26.750273],"type":"Point"}
}