{
  "type": "Feature",
  "properties": {
    "gn:admin1_code":"39.0",
    "gn:admin2_code":"64.0",
    "gn:asciiname":"Bakh",
    "gn:country_code":"IN",
    "gn:dem":1363,
    "gn:feature_class":"P",
    "gn:feature_code":"PPL",
    "gn:name":"Bakh",
    "gn:population":0,
    "gn:timezone":"Asia/Kolkata",
    "iso:country":"IN",
    "ks:ks_name":"Bakh",
    "ks:ks_type":"VILLAGE",
    "ks:ks_uagg_main":0,
    "name:eng_x_preferred":[
        "Bakh"
    ],
    "wof:name":"Bakh",
    "wof:placetype":"locality"
},
  "geometry": {"coordinates":[79.67316599999999,29.597102],"type":"Point"}
}