{
  "type": "Feature",
  "properties": {
    "gn:admin1_code":"29",
    "gn:admin2_code":"244.0",
    "gn:asciiname":"Tadong",
    "gn:country_code":"IN",
    "gn:dem":1165,
    "gn:feature_class":"P",
    "gn:feature_code":"PPL",
    "gn:name":"T\u0101dong",
    "gn:population":0,
    "gn:timezone":"Asia/Kolkata",
    "iso:country":"IN",
    "wof:name":"Tadong",
    "wof:placetype":"locality"
},
  "geometry": {"coordinates":[88.60216,27.30246],"type":"Point"}
}