{
  "type": "Feature",
  "properties": {
    "gn:admin1_code":"16",
    "gn:admin2_code":"507.0",
    "gn:asciiname":"Kharki",
    "gn:country_code":"IN",
    "gn:dem":264,
    "gn:feature_class":"P",
    "gn:feature_code":"PPL",
    "gn:name":"Kharki",
    "gn:population":0,
    "gn:timezone":"Asia/Kolkata",
    "iso:country":"IN",
    "ks:ks_name":"Khadki",
    "ks:ks_pop":165,
    "ks:ks_type":"VILLAGE",
    "name:eng_x_preferred":[
        "Khadki"
    ],
    "name:eng_x_variant":[
        "Kharki"
    ],
    "wof:name":"Khadki",
    "wof:placetype":"locality",
    "wof:population":165
},
  "geometry": {"coordinates":[80.24185300000001,20.669828],"type":"Point"}
}