{
  "type": "Feature",
  "properties": {
    "gn:admin1_code":"19.0",
    "gn:admin2_code":"573.0",
    "gn:asciiname":"Gangenahalli",
    "gn:country_code":"IN",
    "gn:dem":835,
    "gn:feature_class":"P",
    "gn:feature_code":"PPL",
    "gn:name":"Gangenahalli",
    "gn:population":0,
    "gn:timezone":"Asia/Kolkata",
    "iso:country":"IN",
    "name:ara_x_preferred":[
        "\u062c\u064a\u0646\u062c\u0627\u0646\u0627\u0647\u0644\u064a"
    ],
    "name:ben_bn_x_preferred":[
        "\u0997\u09be\u0999\u09cd\u0997\u09c7\u09a8\u09be\u09b9\u09be\u09b2\u09cd\u09b2\u09bf"
    ],
    "name:ben_in_x_preferred":[
        "\u0997\u09be\u0999\u09cd\u0997\u09c7\u09a8\u09be\u09b9\u09be\u09b2\u09cd\u09b2\u09bf"
    ],
    "name:guj_x_preferred":[
        "\u0a97\u0a82\u0a97\u0ac7\u0aa8\u0ab9\u0ab2\u0acd\u0ab2\u0ac0"
    ],
    "name:hin_x_preferred":[
        "\u0917\u0902\u0917\u0928\u0939\u0932\u094d\u0932\u0940"
    ],
    "name:kan_x_preferred":[
        "\u0c97\u0c82\u0c97\u0cc7\u0ca8\u0cb9\u0cb3\u0ccd\u0cb3\u0cbf"
    ],
    "name:mal_x_preferred":[
        "\u0d17\u0d02\u0d17\u0d28\u0d39\u0d33\u0d4d\u0d33\u0d3f"
    ],
    "name:mar_x_preferred":[
        "\u0917\u0902\u0917\u0947\u0928\u093e\u0939\u0932\u094d\u0932\u0940"
    ],
    "name:pan_x_preferred":[
        "\u0a17\u0a70\u0a17\u0a47\u0a28\u0a39\u0a48\u0a32\u0a40"
    ],
    "name:tam_x_preferred":[
        "\u0b95\u0b99\u0bcd\u0b95\u0bc6\u0ba9\u0bb9\u0bb3\u0bcd\u0bb3\u0bbf"
    ],
    "name:tel_x_preferred":[
        "\u0c17\u0c02\u0c17\u0c46\u0c28\u0c39\u0c33\u0c4d\u0c33\u0c3f"
    ],
    "name:urd_x_preferred":[
        "\u06af\u0646\u06af\u06cc\u0646\u0627 \u06c1\u0644\u0651\u06cc"
    ],
    "wof:name":"Gangenahalli",
    "wof:placetype":"locality"
},
  "geometry": {"coordinates":[76.41546,12.7631],"type":"Point"}
}