{
  "type": "Feature",
  "properties": {
    "iso:country":"IN",
    "ks:ks_alt_nam":"kajaraai",
    "ks:ks_name":"Kajaraai",
    "ks:ks_pop":550,
    "ks:ks_type":"HABITATION",
    "name:eng_x_preferred":[
        "Kajaraai"
    ],
    "wof:name":"Kajaraai",
    "wof:placetype":"locality",
    "wof:population":550
},
  "geometry": {"coordinates":[84.493202,24.367929],"type":"Point"}
}