{
  "type": "Feature",
  "properties": {
    "iso:country":"IN",
    "ks:ks_name":"Dekakund",
    "ks:ks_pop":1417,
    "ks:ks_type":"VILLAGE",
    "name:eng_x_preferred":[
        "Dekakund"
    ],
    "wof:name":"Dekakund",
    "wof:placetype":"locality",
    "wof:population":1417
},
  "geometry": {"coordinates":[74.65235699999999,22.472553],"type":"Point"}
}