{
  "type": "Feature",
  "properties": {
    "iso:country":"IN",
    "ks:ks_name":"Gangapur",
    "ks:ks_pop":1147,
    "ks:ks_type":"VILLAGE",
    "name:eng_x_preferred":[
        "Gangapur"
    ],
    "wof:name":"Gangapur",
    "wof:placetype":"locality",
    "wof:population":1147
},
  "geometry": {"coordinates":[74.566362,19.531733],"type":"Point"}
}