{
  "type": "Feature",
  "properties": {
    "iso:country":"IN",
    "ks:ks_name":"Maradi",
    "ks:ks_type":"VILLAGE",
    "name:eng_x_preferred":[
        "Maradi"
    ],
    "wof:name":"Maradi",
    "wof:placetype":"locality"
},
  "geometry": {"coordinates":[75.133488,13.645776],"type":"Point"}
}