{
  "type": "Feature",
  "properties": {
    "gn:admin1_code":"36",
    "gn:admin2_code":"166.0",
    "gn:asciiname":"Bhagwantpur",
    "gn:country_code":"IN",
    "gn:dem":235,
    "gn:feature_class":"P",
    "gn:feature_code":"PPL",
    "gn:name":"Bhagwantpur",
    "gn:population":0,
    "gn:timezone":"Asia/Kolkata",
    "iso:country":"IN",
    "ks:ks_name":"Bhagwantpur",
    "ks:ks_pop":2478,
    "ks:ks_type":"VILLAGE",
    "name:eng_x_preferred":[
        "Bhagwantpur"
    ],
    "wof:name":"Bhagwantpur",
    "wof:placetype":"locality",
    "wof:population":2478
},
  "geometry": {"coordinates":[78.62734399999999,25.43406],"type":"Point"}
}