{
  "type": "Feature",
  "properties": {
    "gn:admin1_code":"28.0",
    "gn:admin2_code":"337",
    "gn:asciiname":"Chaital",
    "gn:country_code":"IN",
    "gn:dem":8,
    "gn:feature_class":"P",
    "gn:feature_code":"PPL",
    "gn:name":"Chaital",
    "gn:population":0,
    "gn:timezone":"Asia/Kolkata",
    "iso:country":"IN",
    "wof:name":"Chaital",
    "wof:placetype":"neighbourhood"
},
  "geometry": {"coordinates":[88.77576000000001,22.51519],"type":"Point"}
}