{
  "type": "Feature",
  "properties": {
    "iso:country":"IN",
    "ks:ks_name":"Raul",
    "ks:ks_pop":4,
    "ks:ks_type":"HABITATION",
    "name:eng_x_preferred":[
        "Raul"
    ],
    "wof:name":"Raul",
    "wof:placetype":"locality",
    "wof:population":4
},
  "geometry": {"coordinates":[84.191547,19.61511],"type":"Point"}
}