{
  "type": "Feature",
  "properties": {
    "gn:admin1_code":"19.0",
    "gn:admin2_code":"571.0",
    "gn:asciiname":"Nallekamanahalli",
    "gn:country_code":"IN",
    "gn:dem":697,
    "gn:feature_class":"P",
    "gn:feature_code":"PPL",
    "gn:name":"Nallek\u0101manahalli",
    "gn:population":0,
    "gn:timezone":"Asia/Kolkata",
    "iso:country":"IN",
    "wof:name":"Nallekamanahalli",
    "wof:placetype":"locality"
},
  "geometry": {"coordinates":[77.21713000000003,13.85043],"type":"Point"}
}