{
  "type": "Feature",
  "properties": {
    "iso:country":"IN",
    "ks:ks_name":"Alagurimajalu",
    "ks:ks_pop":190,
    "ks:ks_type":"HABITATION",
    "name:eng_x_preferred":[
        "Alagurimajalu"
    ],
    "wof:name":"Alagurimajalu",
    "wof:placetype":"locality",
    "wof:population":190
},
  "geometry": {"coordinates":[75.244252,12.830048],"type":"Point"}
}