{
  "type": "Feature",
  "properties": {
    "gn:admin1_code":"39.0",
    "gn:admin2_code":"65.0",
    "gn:asciiname":"Tapnipal",
    "gn:country_code":"IN",
    "gn:dem":1799,
    "gn:feature_class":"P",
    "gn:feature_code":"PPL",
    "gn:name":"Tapnipal",
    "gn:population":0,
    "gn:timezone":"Asia/Kolkata",
    "iso:country":"IN",
    "wof:name":"Tapnipal",
    "wof:placetype":"locality"
},
  "geometry": {"coordinates":[79.98583000000001,29.3647],"type":"Point"}
}