{
  "type": "Feature",
  "properties": {
    "iso:country":"IN",
    "ks:ks_name":"Malak",
    "ks:ks_pop":10,
    "ks:ks_type":"VILLAGE",
    "name:eng_x_preferred":[
        "Malak"
    ],
    "wof:name":"Malak",
    "wof:placetype":"locality",
    "wof:population":10
},
  "geometry": {"coordinates":[83.618448,19.976002],"type":"Point"}
}