{
  "type": "Feature",
  "properties": {
    "gn:admin1_code":"21",
    "gn:admin2_code":"399.0",
    "gn:asciiname":"Singaluvencha",
    "gn:country_code":"IN",
    "gn:dem":249,
    "gn:feature_class":"P",
    "gn:feature_code":"PPL",
    "gn:name":"Sing\u0101luvencha",
    "gn:population":0,
    "gn:timezone":"Asia/Kolkata",
    "iso:country":"IN",
    "wof:name":"Singaluvencha",
    "wof:placetype":"locality"
},
  "geometry": {"coordinates":[82.17349,18.52864],"type":"Point"}
}