{
  "type": "Feature",
  "properties": {
    "gn:admin1_code":"13.0",
    "gn:admin2_code":"590.0",
    "gn:asciiname":"Panniyamgat",
    "gn:country_code":"IN",
    "gn:dem":906,
    "gn:feature_class":"P",
    "gn:feature_code":"PPL",
    "gn:name":"Panniyamg\u0101t",
    "gn:population":0,
    "gn:timezone":"Asia/Kolkata",
    "iso:country":"IN",
    "wof:name":"Panniyamgat",
    "wof:placetype":"locality"
},
  "geometry": {"coordinates":[76.26733,11.68174],"type":"Point"}
}