{
  "type": "Feature",
  "properties": {
    "iso:country":"IN",
    "ks:ks_name":"Bitra",
    "ks:ks_pop":445,
    "ks:ks_type":"VILLAGE",
    "name:eng_x_preferred":[
        "Bitra"
    ],
    "wof:name":"Bitra",
    "wof:placetype":"locality",
    "wof:population":445
},
  "geometry": {"coordinates":[83.028544,18.561602],"type":"Point"}
}