{
  "type": "Feature",
  "properties": {
    "gn:admin1_code":"11.0",
    "gn:admin2_code":"26.0",
    "gn:asciiname":"Golingcha",
    "gn:country_code":"IN",
    "gn:dem":2517,
    "gn:feature_class":"P",
    "gn:feature_code":"PPL",
    "gn:name":"Golingcha",
    "gn:population":0,
    "gn:timezone":"Asia/Kolkata",
    "iso:country":"IN",
    "wof:name":"Golingcha",
    "wof:placetype":"locality"
},
  "geometry": {"coordinates":[77.51782,31.60905],"type":"Point"}
}