{
  "type": "Feature",
  "properties": {
    "iso:country":"IN",
    "ks:ks_name":"Gavaliwadi",
    "ks:ks_pop":278,
    "ks:ks_type":"HABITATION",
    "name:eng_x_preferred":[
        "Gavaliwadi"
    ],
    "wof:name":"Gavaliwadi",
    "wof:placetype":"locality",
    "wof:population":278
},
  "geometry": {"coordinates":[73.59040299999999,17.159144],"type":"Point"}
}