{
  "type": "Feature",
  "properties": {
    "iso:country":"IN",
    "ks:ks_name":"Aidoba",
    "ks:ks_pop":327,
    "ks:ks_type":"VILLAGE",
    "name:eng_x_preferred":[
        "Aidoba"
    ],
    "wof:name":"Aidoba",
    "wof:placetype":"locality",
    "wof:population":327
},
  "geometry": {"coordinates":[89.92728700000001,25.567794],"type":"Point"}
}