{
  "type": "Feature",
  "properties": {
    "gn:admin1_code":"35.0",
    "gn:admin2_code":"464.0",
    "gn:asciiname":"Sagwa",
    "gn:country_code":"IN",
    "gn:dem":419,
    "gn:feature_class":"P",
    "gn:feature_code":"PPL",
    "gn:name":"Sagwa",
    "gn:population":0,
    "gn:timezone":"Asia/Kolkata",
    "iso:country":"IN",
    "ks:ks_name":"Sagwa",
    "ks:ks_pop":893,
    "ks:ks_type":"VILLAGE",
    "name:eng_x_preferred":[
        "Sagwa"
    ],
    "name:und_x_variant":[
        "S\u0101gwa"
    ],
    "wof:name":"Sagwa",
    "wof:placetype":"locality",
    "wof:population":893
},
  "geometry": {"coordinates":[74.697684,23.083007],"type":"Point"}
}