{
  "type": "Feature",
  "properties": {
    "gn:admin1_code":"36.0",
    "gn:admin2_code":"145.0",
    "gn:asciiname":"Pati Ka Nagla",
    "gn:country_code":"IN",
    "gn:dem":187,
    "gn:feature_class":"P",
    "gn:feature_code":"PPL",
    "gn:name":"Pati Ka Nagla",
    "gn:population":0,
    "gn:timezone":"Asia/Kolkata",
    "iso:country":"IN",
    "wof:name":"Pati Ka Nagla",
    "wof:placetype":"locality"
},
  "geometry": {"coordinates":[77.76494,27.79013],"type":"Point"}
}