{
  "type": "Feature",
  "properties": {
    "iso:country":"IN",
    "ks:ks_alt_nam":"Pujari tota",
    "ks:ks_name":"Pujari Tota",
    "ks:ks_pop":293,
    "ks:ks_type":"HABITATION",
    "name:eng_x_preferred":[
        "Pujari Tota"
    ],
    "wof:name":"Pujari Tota",
    "wof:placetype":"locality",
    "wof:population":293
},
  "geometry": {"coordinates":[74.849296,16.413841],"type":"Point"}
}