{
  "type": "Feature",
  "properties": {
    "iso:country":"IN",
    "ks:ks_alt_nam":"M\u0101legaon Camp",
    "ks:ks_name":"Malegaon Camp",
    "ks:ks_type":"VILLAGE",
    "ks:ks_uagg_main":0,
    "name:eng_x_preferred":[
        "Malegaon Camp"
    ],
    "name:eng_x_variant":[
        "M\u0101legaon Camp"
    ],
    "wof:name":"Malegaon Camp",
    "wof:placetype":"neighbourhood"
},
  "geometry": {"coordinates":[74.515415,20.569974],"type":"Point"}
}