{
  "type": "Feature",
  "properties": {
    "iso:country":"IN",
    "ks:ks_name":"Gohainchowkham Chenimari Block",
    "ks:ks_pop":43,
    "ks:ks_type":"VILLAGE",
    "name:eng_x_preferred":[
        "Gohainchowkham Chenimari Block"
    ],
    "wof:name":"Gohainchowkham Chenimari Block",
    "wof:placetype":"locality",
    "wof:population":43
},
  "geometry": {"coordinates":[94.641058,27.525597],"type":"Point"}
}