{
  "type": "Feature",
  "properties": {
    "iso:country":"IN",
    "ks:ks_alt_nam":"DUMARTOLA",
    "ks:ks_name":"Dumartola",
    "ks:ks_pop":259,
    "ks:ks_type":"HABITATION",
    "name:eng_x_preferred":[
        "Dumartola"
    ],
    "wof:name":"Dumartola",
    "wof:placetype":"locality",
    "wof:population":259
},
  "geometry": {"coordinates":[83.57860100000001,23.176106],"type":"Point"}
}