{
  "type": "Feature",
  "properties": {
    "gn:admin1_code":"35.0",
    "gn:asciiname":"Narayan Purwa",
    "gn:country_code":"IN",
    "gn:dem":114,
    "gn:feature_class":"P",
    "gn:feature_code":"PPL",
    "gn:name":"Nar\u0101yan Purwa",
    "gn:population":0,
    "gn:timezone":"Asia/Kolkata",
    "iso:country":"IN",
    "name:und_x_variant":[
        "Nar\u0101yan Purwa",
        "Narayan Purwa"
    ],
    "wof:name":"Narayan Purwa",
    "wof:placetype":"locality"
},
  "geometry": {"coordinates":[81.32309000000002,27.40303],"type":"Point"}
}