{
  "type": "Feature",
  "properties": {
    "iso:country":"IN",
    "ks:ks_name":"5 AP",
    "ks:ks_pop":303,
    "ks:ks_type":"VILLAGE",
    "name:eng_x_preferred":[
        "5 AP"
    ],
    "wof:name":"5 AP",
    "wof:placetype":"locality",
    "wof:population":303
},
  "geometry": {"coordinates":[73.74279799999999,29.207807],"type":"Point"}
}