{
  "type": "Feature",
  "properties": {
    "gn:admin1_code":"36",
    "gn:admin2_code":"176.0",
    "gn:asciiname":"Behta Chak Jairam Das",
    "gn:country_code":"IN",
    "gn:dem":128,
    "gn:feature_class":"P",
    "gn:feature_code":"PPL",
    "gn:name":"Behta Chak Jair\u0101m D\u0101s",
    "gn:population":0,
    "gn:timezone":"Asia/Kolkata",
    "iso:country":"IN",
    "wof:name":"Behta Chak Jairam Das",
    "wof:placetype":"locality"
},
  "geometry": {"coordinates":[81.0976,27.08267],"type":"Point"}
}