{
  "type": "Feature",
  "properties": {
    "iso:country":"IN",
    "ks:ks_name":"Alasi",
    "ks:ks_pop":15,
    "ks:ks_type":"VILLAGE",
    "name:eng_x_preferred":[
        "Alasi"
    ],
    "wof:name":"Alasi",
    "wof:placetype":"locality",
    "wof:population":15
},
  "geometry": {"coordinates":[83.03136600000001,18.473181],"type":"Point"}
}