{
  "type": "Feature",
  "properties": {
    "iso:country":"IN",
    "ks:ks_name":"Kankdaha",
    "ks:ks_pop":236,
    "ks:ks_type":"VILLAGE",
    "ks:ks_uagg_main":0,
    "name:eng_x_preferred":[
        "Kankdaha"
    ],
    "wof:name":"Kankdaha",
    "wof:placetype":"neighbourhood",
    "wof:population":236
},
  "geometry": {"coordinates":[87.20325200000001,22.872996],"type":"Point"}
}