{
  "type": "Feature",
  "properties": {
    "iso:country":"IN",
    "ks:ks_name":"Nadipara",
    "ks:ks_pop":89,
    "ks:ks_type":"HABITATION",
    "name:eng_x_preferred":[
        "Nadipara"
    ],
    "wof:name":"Nadipara",
    "wof:placetype":"locality",
    "wof:population":89
},
  "geometry": {"coordinates":[81.19506199999999,20.096482],"type":"Point"}
}