{
  "type": "Feature",
  "properties": {
    "iso:country":"IN",
    "ks:ks_alt_nam":"MADIYAPATTI",
    "ks:ks_name":"Madiyapatti",
    "ks:ks_pop":168,
    "ks:ks_type":"HABITATION",
    "name:eng_x_preferred":[
        "Madiyapatti"
    ],
    "wof:name":"Madiyapatti",
    "wof:placetype":"locality",
    "wof:population":168
},
  "geometry": {"coordinates":[82.072092,23.004457],"type":"Point"}
}