{
  "type": "Feature",
  "properties": {
    "iso:country":"IN",
    "ks:ks_name":"Pure Tale",
    "ks:ks_pop":100,
    "ks:ks_type":"HABITATION",
    "name:eng_x_preferred":[
        "Pure Tale"
    ],
    "wof:name":"Pure Tale",
    "wof:placetype":"locality",
    "wof:population":100
},
  "geometry": {"coordinates":[81.51909999999999,26.466455],"type":"Point"}
}