{
  "type": "Feature",
  "properties": {
    "iso:country":"IN",
    "ks:ks_name":"Panrsaga",
    "ks:ks_pop":15,
    "ks:ks_type":"VILLAGE",
    "name:eng_x_preferred":[
        "Panrsaga"
    ],
    "wof:name":"Panrsaga",
    "wof:placetype":"locality",
    "wof:population":15
},
  "geometry": {"coordinates":[87.710162,24.934304],"type":"Point"}
}