{
  "type": "Feature",
  "properties": {
    "gn:admin1_code":"40.0",
    "gn:admin2_code":"535",
    "gn:asciiname":"Kanukunta",
    "gn:country_code":"IN",
    "gn:dem":639,
    "gn:feature_class":"P",
    "gn:feature_code":"PPL",
    "gn:name":"K\u0101nukunta",
    "gn:population":0,
    "gn:timezone":"Asia/Kolkata",
    "iso:country":"IN",
    "name:und_x_variant":[
        "K\u0101nkunta",
        "K\u0101nukunta"
    ],
    "wof:name":"Kanukunta",
    "wof:placetype":"locality"
},
  "geometry": {"coordinates":[78.41840000000001,17.69858],"type":"Point"}
}