{
  "type": "Feature",
  "properties": {
    "gn:admin1_code":"19.0",
    "gn:admin2_code":"575.0",
    "gn:asciiname":"Panekal",
    "gn:country_code":"IN",
    "gn:dem":148,
    "gn:feature_class":"P",
    "gn:feature_code":"PPL",
    "gn:name":"Pan\u0113kal",
    "gn:population":0,
    "gn:timezone":"Asia/Kolkata",
    "iso:country":"IN",
    "ks:ks_name":"Panekala",
    "ks:ks_pop":128,
    "ks:ks_type":"HABITATION",
    "name:eng_x_preferred":[
        "Panekala"
    ],
    "name:eng_x_variant":[
        "Panekal"
    ],
    "wof:name":"Panekala",
    "wof:placetype":"locality",
    "wof:population":128
},
  "geometry": {"coordinates":[75.36832200000001,13.152818],"type":"Point"}
}