{
  "type": "Feature",
  "properties": {
    "gn:admin1_code":"19",
    "gn:asciiname":"Mundkatte Deven",
    "gn:country_code":"IN",
    "gn:dem":12,
    "gn:feature_class":"P",
    "gn:feature_code":"PPL",
    "gn:name":"Mundkatte Deven",
    "gn:population":0,
    "gn:timezone":"Asia/Kolkata",
    "iso:country":"IN",
    "wof:name":"Mundkatte Deven",
    "wof:placetype":"locality"
},
  "geometry": {"coordinates":[74.69138000000002,13.69109],"type":"Point"}
}