{
  "type": "Feature",
  "properties": {
    "gn:admin1_code":"12.0",
    "gn:admin2_code":"22.0",
    "gn:asciiname":"Loakhi",
    "gn:country_code":"IN",
    "gn:dem":485,
    "gn:feature_class":"P",
    "gn:feature_code":"PPLL",
    "gn:name":"Lo\u0101khi",
    "gn:population":0,
    "gn:timezone":"Asia/Kolkata",
    "iso:country":"IN",
    "wof:name":"Loakhi",
    "wof:placetype":"locality"
},
  "geometry": {"coordinates":[75.17184,32.5503],"type":"Point"}
}