{
  "type": "Feature",
  "properties": {
    "iso:country":"IN",
    "ks:ks_name":"Pakhirbada",
    "ks:ks_pop":545,
    "ks:ks_type":"VILLAGE",
    "name:eng_x_preferred":[
        "Pakhirbada"
    ],
    "wof:name":"Pakhirbada",
    "wof:placetype":"locality",
    "wof:population":545
},
  "geometry": {"coordinates":[92.035692,24.320746],"type":"Point"}
}