{
  "type": "Feature",
  "properties": {
    "iso:country":"IN",
    "ks:ks_alt_nam":"KAPUTOLI",
    "ks:ks_name":"Kaputoli",
    "ks:ks_pop":216,
    "ks:ks_type":"HABITATION",
    "name:eng_x_preferred":[
        "Kaputoli"
    ],
    "wof:name":"Kaputoli",
    "wof:placetype":"locality",
    "wof:population":216
},
  "geometry": {"coordinates":[83.77570799999999,23.041832],"type":"Point"}
}