{
  "type": "Feature",
  "properties": {
    "iso:country":"IN",
    "ks:ks_name":"Dorli",
    "ks:ks_pop":0,
    "ks:ks_type":"VILLAGE",
    "name:eng_x_preferred":[
        "Dorli"
    ],
    "wof:name":"Dorli",
    "wof:placetype":"locality",
    "wof:population":0
},
  "geometry": {"coordinates":[79.736011,20.424638],"type":"Point"}
}