{
  "type": "Feature",
  "properties": {
    "iso:country":"IN",
    "ks:ks_name":"Kui",
    "ks:ks_pop":655,
    "ks:ks_type":"VILLAGE",
    "name:eng_x_preferred":[
        "Kui"
    ],
    "wof:name":"Kui",
    "wof:placetype":"locality",
    "wof:population":655
},
  "geometry": {"coordinates":[81.17922299999999,23.230601],"type":"Point"}
}