{
  "type": "Feature",
  "properties": {
    "iso:country":"IN",
    "ks:ks_name":"Manivilai",
    "ks:ks_pop":305,
    "ks:ks_type":"HABITATION",
    "name:eng_x_preferred":[
        "Manivilai"
    ],
    "wof:name":"Manivilai",
    "wof:placetype":"locality",
    "wof:population":305
},
  "geometry": {"coordinates":[78.455932,9.201843],"type":"Point"}
}