{
  "type": "Feature",
  "properties": {
    "iso:country":"IN",
    "ks:ks_name":"Ambigarkeri",
    "ks:ks_pop":116,
    "ks:ks_type":"HABITATION",
    "name:eng_x_preferred":[
        "Ambigarkeri"
    ],
    "wof:name":"Ambigarkeri",
    "wof:placetype":"locality",
    "wof:population":116
},
  "geometry": {"coordinates":[74.640854,14.234708],"type":"Point"}
}