{
  "type": "Feature",
  "properties": {
    "iso:country":"IN",
    "ks:ks_name":"Digrasi",
    "ks:ks_pop":691,
    "ks:ks_type":"VILLAGE",
    "ks:ks_uagg_main":0,
    "name:eng_x_preferred":[
        "Digrasi"
    ],
    "wof:name":"Digrasi",
    "wof:placetype":"locality",
    "wof:population":691
},
  "geometry": {"coordinates":[87.42071300000001,21.657479],"type":"Point"}
}