{
  "type": "Feature",
  "properties": {
    "iso:country":"IN",
    "ks:ks_name":"Nibarpada",
    "ks:ks_pop":648,
    "ks:ks_type":"HABITATION",
    "name:eng_x_preferred":[
        "Nibarpada"
    ],
    "wof:name":"Nibarpada",
    "wof:placetype":"locality",
    "wof:population":648
},
  "geometry": {"coordinates":[72.799824,19.969253],"type":"Point"}
}