{
  "type": "Feature",
  "properties": {
    "iso:country":"IN",
    "ks:ks_name":"Mahima Rasulpur",
    "ks:ks_pop":1628,
    "ks:ks_type":"VILLAGE",
    "ks:ks_uagg_main":0,
    "name:eng_x_preferred":[
        "Mahima Rasulpur"
    ],
    "wof:name":"Mahima Rasulpur",
    "wof:placetype":"neighbourhood",
    "wof:population":1628
},
  "geometry": {"coordinates":[85.714696,26.453543],"type":"Point"}
}