{
  "type": "Feature",
  "properties": {
    "iso:country":"IN",
    "ks:ks_name":"Gaulpura",
    "ks:ks_pop":121,
    "ks:ks_type":"VILLAGE",
    "name:eng_x_preferred":[
        "Gaulpura"
    ],
    "wof:name":"Gaulpura",
    "wof:placetype":"locality",
    "wof:population":121
},
  "geometry": {"coordinates":[75.740296,22.060377],"type":"Point"}
}