{
  "type": "Feature",
  "properties": {
    "gn:admin1_code":"38.0",
    "gn:admin2_code":"360.0",
    "gn:asciiname":"Mungarmu",
    "gn:country_code":"IN",
    "gn:dem":441,
    "gn:feature_class":"P",
    "gn:feature_code":"PPL",
    "gn:name":"Mungarmu",
    "gn:population":0,
    "gn:timezone":"Asia/Kolkata",
    "iso:country":"IN",
    "ks:ks_name":"Mungarmao",
    "ks:ks_pop":536,
    "ks:ks_type":"VILLAGE",
    "ks:ks_uagg_main":0,
    "name:eng_x_preferred":[
        "Mungarmao"
    ],
    "wof:name":"Mungarmao",
    "wof:placetype":"neighbourhood",
    "wof:population":536
},
  "geometry": {"coordinates":[85.337487,24.18786],"type":"Point"}
}