{
  "type": "Feature",
  "properties": {
    "iso:country":"IN",
    "ks:ks_name":"Chavan Metkariwasti",
    "ks:ks_pop":440,
    "ks:ks_type":"HABITATION",
    "name:eng_x_preferred":[
        "Chavan Metkariwasti"
    ],
    "wof:name":"Chavan Metkariwasti",
    "wof:placetype":"locality",
    "wof:population":440
},
  "geometry": {"coordinates":[75.08832099999999,17.619094],"type":"Point"}
}