{
  "type": "Feature",
  "properties": {
    "gn:admin1_code":"19",
    "gn:admin2_code":"579.0",
    "gn:asciiname":"Kasarbhosgi",
    "gn:country_code":"IN",
    "gn:dem":448,
    "gn:feature_class":"P",
    "gn:feature_code":"PPL",
    "gn:name":"K\u0101sarbhosgi",
    "gn:population":0,
    "gn:timezone":"Asia/Kolkata",
    "iso:country":"IN",
    "wof:name":"Kasarbhosgi",
    "wof:placetype":"neighbourhood"
},
  "geometry": {"coordinates":[76.62209,16.94878],"type":"Point"}
}