{
  "type": "Feature",
  "properties": {
    "gn:admin1_code":"25.0",
    "gn:admin2_code":"606.0",
    "gn:asciiname":"Agilandapuram",
    "gn:country_code":"IN",
    "gn:dem":144,
    "gn:feature_class":"P",
    "gn:feature_code":"PPL",
    "gn:name":"Agil\u0101ndapuram",
    "gn:population":0,
    "gn:timezone":"Asia/Kolkata",
    "iso:country":"IN",
    "ks:ks_name":"Agilandpuram",
    "ks:ks_pop":225,
    "ks:ks_type":"HABITATION",
    "name:eng_x_preferred":[
        "Agilandpuram"
    ],
    "name:eng_x_variant":[
        "Agilandapuram"
    ],
    "wof:name":"Agilandpuram",
    "wof:placetype":"locality",
    "wof:population":225
},
  "geometry": {"coordinates":[79.273145,12.566688],"type":"Point"}
}