{
  "type": "Feature",
  "properties": {
    "iso:country":"IN",
    "ks:ks_name":"Vadabai",
    "ks:ks_pop":231,
    "ks:ks_type":"HABITATION",
    "name:eng_x_preferred":[
        "Vadabai"
    ],
    "wof:name":"Vadabai",
    "wof:placetype":"locality",
    "wof:population":231
},
  "geometry": {"coordinates":[83.59151799999999,19.044206],"type":"Point"}
}