{
  "type": "Feature",
  "properties": {
    "iso:country":"IN",
    "ks:ks_name":"Deva Samuthiram",
    "ks:ks_pop":109,
    "ks:ks_type":"HABITATION",
    "name:eng_x_preferred":[
        "Deva Samuthiram"
    ],
    "wof:name":"Deva Samuthiram",
    "wof:placetype":"locality",
    "wof:population":109
},
  "geometry": {"coordinates":[78.733757,9.625983],"type":"Point"}
}