{
  "type": "Feature",
  "properties": {
    "iso:country":"IN",
    "ks:ks_name":"Niskatepada",
    "ks:ks_pop":68,
    "ks:ks_type":"HABITATION",
    "name:eng_x_preferred":[
        "Niskatepada"
    ],
    "wof:name":"Niskatepada",
    "wof:placetype":"locality",
    "wof:population":68
},
  "geometry": {"coordinates":[72.87901100000001,19.842896],"type":"Point"}
}