{
  "type": "Feature",
  "properties": {
    "iso:country":"IN",
    "ks:ks_name":"Ghaksapara",
    "ks:ks_pop":2419,
    "ks:ks_type":"VILLAGE",
    "name:eng_x_preferred":[
        "Ghaksapara"
    ],
    "wof:name":"Ghaksapara",
    "wof:placetype":"locality",
    "wof:population":2419
},
  "geometry": {"coordinates":[89.811498,26.530863],"type":"Point"}
}