{
  "type": "Feature",
  "properties": {
    "gn:admin1_code":"40.0",
    "gn:admin2_code":"533.0",
    "gn:asciiname":"Yellareddipet",
    "gn:country_code":"IN",
    "gn:dem":535,
    "gn:feature_class":"P",
    "gn:feature_code":"PPL",
    "gn:name":"Yell\u0101reddipet",
    "gn:population":0,
    "gn:timezone":"Asia/Kolkata",
    "iso:country":"IN",
    "name:tel_x_preferred":[
        "\u0c2f\u0c32\u0c4d\u0c32\u0c3e\u0c30\u0c46\u0c21\u0c4d\u0c21\u0c3f\u0c2a\u0c47\u0c1f\u0c4d"
    ],
    "name:urd_x_preferred":[
        "\u06cc\u0644\u0631\u062f\u062f\u067e\u06cc\u0679"
    ],
    "wof:name":"Yellareddipet",
    "wof:placetype":"neighbourhood"
},
  "geometry": {"coordinates":[78.31001999999999,18.37052],"type":"Point"}
}