{
  "type": "Feature",
  "properties": {
    "iso:country":"IN",
    "ks:ks_name":"Sanapachedia",
    "ks:ks_pop":21,
    "ks:ks_type":"VILLAGE",
    "name:eng_x_preferred":[
        "Sanapachedia"
    ],
    "wof:name":"Sanapachedia",
    "wof:placetype":"locality",
    "wof:population":21
},
  "geometry": {"coordinates":[84.392844,18.931798],"type":"Point"}
}