{
  "type": "Feature",
  "properties": {
    "gn:admin1_code":"23",
    "gn:admin2_code":"47.0",
    "gn:asciiname":"Raipur",
    "gn:country_code":"IN",
    "gn:dem":216,
    "gn:feature_class":"P",
    "gn:feature_code":"PPL",
    "gn:name":"R\u0101ipur",
    "gn:population":0,
    "gn:timezone":"Asia/Kolkata",
    "iso:country":"IN",
    "wof:name":"Raipur",
    "wof:placetype":"locality"
},
  "geometry": {"coordinates":[75.25548000000001,29.90491],"type":"Point"}
}