{
  "type": "Feature",
  "properties": {
    "iso:country":"IN",
    "ks:ks_name":"Bir Ghugiana",
    "ks:ks_pop":260,
    "ks:ks_type":"VILLAGE",
    "name:eng_x_preferred":[
        "Bir Ghugiana"
    ],
    "wof:name":"Bir Ghugiana",
    "wof:placetype":"locality",
    "wof:population":260
},
  "geometry": {"coordinates":[74.62900399999999,30.788561],"type":"Point"}
}