{
  "type": "Feature",
  "properties": {
    "iso:country":"IN",
    "ks:ks_name":"Navakulam",
    "ks:ks_pop":250,
    "ks:ks_type":"HABITATION",
    "name:eng_x_preferred":[
        "Navakulam"
    ],
    "wof:name":"Navakulam",
    "wof:placetype":"locality",
    "wof:population":250
},
  "geometry": {"coordinates":[78.19991,9.998861],"type":"Point"}
}