{
  "type": "Feature",
  "properties": {
    "gn:admin1_code":"39.0",
    "gn:admin2_code":"61.0",
    "gn:asciiname":"Kundliya",
    "gn:country_code":"IN",
    "gn:dem":1992,
    "gn:feature_class":"P",
    "gn:feature_code":"PPL",
    "gn:name":"Kundliya",
    "gn:population":0,
    "gn:timezone":"Asia/Kolkata",
    "iso:country":"IN",
    "wof:name":"Kundliya",
    "wof:placetype":"locality"
},
  "geometry": {"coordinates":[79.01040999999999,29.77741],"type":"Point"}
}