{
  "type": "Feature",
  "properties": {
    "iso:country":"IN",
    "ks:ks_alt_nam":"Eedulakunta tanda",
    "ks:ks_name":"Eedulakunta Tanda",
    "ks:ks_pop":50,
    "ks:ks_type":"HABITATION",
    "name:eng_x_preferred":[
        "Eedulakunta Tanda"
    ],
    "wof:name":"Eedulakunta Tanda",
    "wof:placetype":"locality",
    "wof:population":50
},
  "geometry": {"coordinates":[77.724716,17.063092],"type":"Point"}
}