{
  "type": "Feature",
  "properties": {
    "iso:country":"IN",
    "ks:ks_name":"Nallanayagipuram",
    "ks:ks_pop":230,
    "ks:ks_type":"HABITATION",
    "name:eng_x_preferred":[
        "Nallanayagipuram"
    ],
    "wof:name":"Nallanayagipuram",
    "wof:placetype":"locality",
    "wof:population":230
},
  "geometry": {"coordinates":[79.569619,10.535035],"type":"Point"}
}