{
  "type": "Feature",
  "properties": {
    "iso:country":"IN",
    "ks:ks_name":"Yadav Ka Pura",
    "ks:ks_pop":116,
    "ks:ks_type":"HABITATION",
    "name:eng_x_preferred":[
        "Yadav Ka Pura"
    ],
    "wof:name":"Yadav Ka Pura",
    "wof:placetype":"locality",
    "wof:population":116
},
  "geometry": {"coordinates":[82.575267,26.566637],"type":"Point"}
}