{
  "type": "Feature",
  "properties": {
    "iso:country":"IN",
    "ks:ks_name":"Seerapuvanipeta",
    "ks:ks_pop":305,
    "ks:ks_type":"HABITATION",
    "name:eng_x_preferred":[
        "Seerapuvanipeta"
    ],
    "wof:name":"Seerapuvanipeta",
    "wof:placetype":"locality",
    "wof:population":305
},
  "geometry": {"coordinates":[84.266775,18.534434],"type":"Point"}
}