{
  "type": "Feature",
  "properties": {
    "iso:country":"IN",
    "ks:ks_name":"Mithottu",
    "ks:ks_pop":321,
    "ks:ks_type":"HABITATION",
    "name:eng_x_preferred":[
        "Mithottu"
    ],
    "wof:name":"Mithottu",
    "wof:placetype":"locality",
    "wof:population":321
},
  "geometry": {"coordinates":[75.14169699999999,12.967781],"type":"Point"}
}