{
  "type": "Feature",
  "properties": {
    "iso:country":"IN",
    "ks:ks_name":"Ahmad Sujawal",
    "ks:ks_pop":1282,
    "ks:ks_type":"VILLAGE",
    "ks:ks_uagg_main":0,
    "name:eng_x_preferred":[
        "Ahmad Sujawal"
    ],
    "wof:name":"Ahmad Sujawal",
    "wof:placetype":"neighbourhood",
    "wof:population":1282
},
  "geometry": {"coordinates":[85.943804,26.111773],"type":"Point"}
}