{
  "type": "Feature",
  "properties": {
    "iso:country":"IN",
    "ks:ks_name":"Nagjhir",
    "ks:ks_pop":283,
    "ks:ks_type":"VILLAGE",
    "name:eng_x_preferred":[
        "Nagjhir"
    ],
    "wof:name":"Nagjhir",
    "wof:placetype":"locality",
    "wof:population":283
},
  "geometry": {"coordinates":[80.478373,24.395838],"type":"Point"}
}