{
  "type": "Feature",
  "properties": {
    "iso:country":"IN",
    "ks:ks_name":"Heerapura",
    "ks:ks_pop":16,
    "ks:ks_type":"VILLAGE",
    "name:eng_x_preferred":[
        "Heerapura"
    ],
    "wof:name":"Heerapura",
    "wof:placetype":"locality",
    "wof:population":16
},
  "geometry": {"coordinates":[77.269261,26.453414],"type":"Point"}
}