{
  "type": "Feature",
  "properties": {
    "iso:country":"IN",
    "ks:ks_name":"Baraipurwa",
    "ks:ks_pop":283,
    "ks:ks_type":"HABITATION",
    "ks:ks_uagg_main":0,
    "name:eng_x_preferred":[
        "Baraipurwa"
    ],
    "wof:name":"Baraipurwa",
    "wof:placetype":"neighbourhood",
    "wof:population":283
},
  "geometry": {"coordinates":[82.28440000000001,27.651232],"type":"Point"}
}