{
  "type": "Feature",
  "properties": {
    "iso:country":"IN",
    "ks:ks_name":"Niche Tola",
    "ks:ks_pop":234,
    "ks:ks_type":"HABITATION",
    "name:eng_x_preferred":[
        "Niche Tola"
    ],
    "wof:name":"Niche Tola",
    "wof:placetype":"locality",
    "wof:population":234
},
  "geometry": {"coordinates":[86.04290399999999,24.305806],"type":"Point"}
}