{
  "type": "Feature",
  "properties": {
    "gn:admin1_code":"21.0",
    "gn:admin2_code":"375",
    "gn:asciiname":"Govindpur",
    "gn:country_code":"IN",
    "gn:dem":212,
    "gn:feature_class":"P",
    "gn:feature_code":"PPL",
    "gn:name":"Govindpur",
    "gn:population":0,
    "gn:timezone":"Asia/Kolkata",
    "iso:country":"IN",
    "wof:name":"Govindpur",
    "wof:placetype":"locality"
},
  "geometry": {"coordinates":[85.33389,21.48492],"type":"Point"}
}