{
  "type": "Feature",
  "properties": {
    "iso:country":"IN",
    "ks:ks_name":"Karjanpur",
    "ks:ks_pop":548,
    "ks:ks_type":"HABITATION",
    "name:eng_x_preferred":[
        "Karjanpur"
    ],
    "wof:name":"Karjanpur",
    "wof:placetype":"locality",
    "wof:population":548
},
  "geometry": {"coordinates":[78.743758,28.45732],"type":"Point"}
}