{
  "type": "Feature",
  "properties": {
    "gn:admin1_code":"37",
    "gn:admin2_code":"414.0",
    "gn:asciiname":"Bamanaras",
    "gn:country_code":"IN",
    "gn:dem":533,
    "gn:feature_class":"P",
    "gn:feature_code":"PPL",
    "gn:name":"B\u0101manar\u0101s",
    "gn:population":0,
    "gn:timezone":"Asia/Kolkata",
    "iso:country":"IN",
    "ks:ks_name":"Bamnaras",
    "ks:ks_pop":290,
    "ks:ks_type":"HABITATION",
    "name:eng_x_preferred":[
        "Bamnaras"
    ],
    "name:eng_x_variant":[
        "Bamanaras"
    ],
    "wof:name":"Bamnaras",
    "wof:placetype":"locality",
    "wof:population":290
},
  "geometry": {"coordinates":[82.066333,18.865143],"type":"Point"}
}