{
  "type": "Feature",
  "properties": {
    "gn:admin1_code":"21",
    "gn:admin2_code":"394.0",
    "gn:asciiname":"Baijalpur",
    "gn:country_code":"IN",
    "gn:dem":290,
    "gn:feature_class":"P",
    "gn:feature_code":"PPL",
    "gn:name":"Baijalpur",
    "gn:population":0,
    "gn:timezone":"Asia/Kolkata",
    "iso:country":"IN",
    "ks:ks_name":"Baijalpur",
    "ks:ks_pop":308,
    "ks:ks_type":"VILLAGE",
    "name:eng_x_preferred":[
        "Baijalpur"
    ],
    "wof:name":"Baijalpur",
    "wof:placetype":"locality",
    "wof:population":308
},
  "geometry": {"coordinates":[82.515321,20.121809],"type":"Point"}
}