{
  "type": "Feature",
  "properties": {
    "iso:country":"IN",
    "ks:ks_name":"Nathar Basti",
    "ks:ks_pop":252,
    "ks:ks_type":"HABITATION",
    "name:eng_x_preferred":[
        "Nathar Basti"
    ],
    "wof:name":"Nathar Basti",
    "wof:placetype":"locality",
    "wof:population":252
},
  "geometry": {"coordinates":[88.2518,26.352215],"type":"Point"}
}