{
  "type": "Feature",
  "properties": {
    "gn:admin1_code":"35",
    "gn:admin2_code":"466.0",
    "gn:asciiname":"Kekriya",
    "gn:country_code":"IN",
    "gn:dem":453,
    "gn:feature_class":"P",
    "gn:feature_code":"PPL",
    "gn:name":"Kekriya",
    "gn:population":0,
    "gn:timezone":"Asia/Kolkata",
    "iso:country":"IN",
    "wof:name":"Kekriya",
    "wof:placetype":"locality"
},
  "geometry": {"coordinates":[77.19609,21.9011],"type":"Point"}
}