{
  "type": "Feature",
  "properties": {
    "iso:country":"IN",
    "ks:ks_name":"Hinekuttibaina",
    "ks:ks_pop":88,
    "ks:ks_type":"HABITATION",
    "name:eng_x_preferred":[
        "Hinekuttibaina"
    ],
    "wof:name":"Hinekuttibaina",
    "wof:placetype":"locality",
    "wof:population":88
},
  "geometry": {"coordinates":[74.41168399999999,14.618778],"type":"Point"}
}