{
  "type": "Feature",
  "properties": {
    "iso:country":"IN",
    "ks:ks_name":"Kisanpur New",
    "ks:ks_pop":635,
    "ks:ks_type":"HABITATION",
    "name:eng_x_preferred":[
        "Kisanpur New"
    ],
    "wof:name":"Kisanpur New",
    "wof:placetype":"locality",
    "wof:population":635
},
  "geometry": {"coordinates":[92.266231,26.841889],"type":"Point"}
}