{
  "type": "Feature",
  "properties": {
    "gn:admin1_code":"16.0",
    "gn:admin2_code":"510.0",
    "gn:asciiname":"Kotha",
    "gn:country_code":"IN",
    "gn:dem":270,
    "gn:feature_class":"P",
    "gn:feature_code":"PPL",
    "gn:name":"Kotha",
    "gn:population":0,
    "gn:timezone":"Asia/Kolkata",
    "iso:country":"IN",
    "wof:name":"Kotha",
    "wof:placetype":"locality"
},
  "geometry": {"coordinates":[78.07135,20.64649],"type":"Point"}
}