{
  "type": "Feature",
  "properties": {
    "gn:admin1_code":"16.0",
    "gn:admin2_code":"505.0",
    "gn:asciiname":"Chawre Pathar",
    "gn:country_code":"IN",
    "gn:dem":513,
    "gn:feature_class":"P",
    "gn:feature_code":"PPL",
    "gn:name":"Chawre Pathar",
    "gn:population":0,
    "gn:timezone":"Asia/Kolkata",
    "iso:country":"IN",
    "wof:name":"Chawre Pathar",
    "wof:placetype":"locality"
},
  "geometry": {"coordinates":[78.48775000000001,21.26218],"type":"Point"}
}