{
  "type": "Feature",
  "properties": {
    "iso:country":"IN",
    "ks:ks_name":"Kadopani",
    "ks:ks_pop":131,
    "ks:ks_type":"VILLAGE",
    "name:eng_x_preferred":[
        "Kadopani"
    ],
    "wof:name":"Kadopani",
    "wof:placetype":"locality",
    "wof:population":131
},
  "geometry": {"coordinates":[84.19345,22.699079],"type":"Point"}
}