{
  "type": "Feature",
  "properties": {
    "iso:country":"IN",
    "ks:ks_name":"Khodiyar",
    "ks:ks_pop":129,
    "ks:ks_type":"HABITATION",
    "name:eng_x_preferred":[
        "Khodiyar"
    ],
    "wof:name":"Khodiyar",
    "wof:placetype":"locality",
    "wof:population":129
},
  "geometry": {"coordinates":[71.606343,22.360789],"type":"Point"}
}