{
  "type": "Feature",
  "properties": {
    "gn:admin1_code":"19.0",
    "gn:admin2_code":"577.0",
    "gn:asciiname":"Hagaranahalli",
    "gn:country_code":"IN",
    "gn:dem":774,
    "gn:feature_class":"P",
    "gn:feature_code":"PPL",
    "gn:name":"Hagaranahalli",
    "gn:population":0,
    "gn:timezone":"Asia/Kolkata",
    "iso:country":"IN",
    "wof:name":"Hagaranahalli",
    "wof:placetype":"locality"
},
  "geometry": {"coordinates":[76.36675,12.35726],"type":"Point"}
}