{
  "type": "Feature",
  "properties": {
    "gn:admin1_code":"34.0",
    "gn:admin2_code":"204.0",
    "gn:asciiname":"Panre",
    "gn:country_code":"IN",
    "gn:dem":70,
    "gn:feature_class":"P",
    "gn:feature_code":"PPL",
    "gn:name":"P\u0101nre",
    "gn:population":0,
    "gn:timezone":"Asia/Kolkata",
    "iso:country":"IN",
    "wof:name":"Panre",
    "wof:placetype":"locality"
},
  "geometry": {"coordinates":[84.77905,26.53701],"type":"Point"}
}