{
  "type": "Feature",
  "properties": {
    "gn:admin1_code":"35",
    "gn:admin2_code":"452.0",
    "gn:asciiname":"Durajpur",
    "gn:country_code":"IN",
    "gn:dem":363,
    "gn:feature_class":"P",
    "gn:feature_code":"PPL",
    "gn:name":"Dur\u0101jpur",
    "gn:population":0,
    "gn:timezone":"Asia/Kolkata",
    "iso:country":"IN",
    "wof:name":"Durajpur",
    "wof:placetype":"locality"
},
  "geometry": {"coordinates":[79.18349000000001,22.88017],"type":"Point"}
}