{
  "type": "Feature",
  "properties": {
    "gn:admin1_code":"13.0",
    "gn:admin2_code":"595.0",
    "gn:asciiname":"Vadakke Ezhipram",
    "gn:country_code":"IN",
    "gn:dem":22,
    "gn:feature_class":"P",
    "gn:feature_code":"PPL",
    "gn:name":"Vadakke Ezhipram",
    "gn:population":0,
    "gn:timezone":"Asia/Kolkata",
    "iso:country":"IN",
    "wof:name":"Vadakke Ezhipram",
    "wof:placetype":"locality"
},
  "geometry": {"coordinates":[76.43115,10.10278],"type":"Point"}
}