{
  "type": "Feature",
  "properties": {
    "gn:admin1_code":"34.0",
    "gn:admin2_code":"235.0",
    "gn:asciiname":"Sikaria Ratan",
    "gn:country_code":"IN",
    "gn:dem":151,
    "gn:feature_class":"P",
    "gn:feature_code":"PPL",
    "gn:name":"Sikari\u0101 Ratan",
    "gn:population":0,
    "gn:timezone":"Asia/Kolkata",
    "iso:country":"IN",
    "wof:name":"Sikaria Ratan",
    "wof:placetype":"locality"
},
  "geometry": {"coordinates":[84.19549000000001,24.58791],"type":"Point"}
}