{
  "type": "Feature",
  "properties": {
    "gn:admin1_code":"34.0",
    "gn:admin2_code":"236.0",
    "gn:asciiname":"Jhurang",
    "gn:country_code":"IN",
    "gn:dem":185,
    "gn:feature_class":"P",
    "gn:feature_code":"PPL",
    "gn:name":"Jhur\u0101ng",
    "gn:population":0,
    "gn:timezone":"Asia/Kolkata",
    "iso:country":"IN",
    "ks:ks_name":"Jhurang",
    "ks:ks_pop":1098,
    "ks:ks_type":"VILLAGE",
    "ks:ks_uagg_main":0,
    "name:eng_x_preferred":[
        "Jhurang"
    ],
    "wof:name":"Jhurang",
    "wof:placetype":"neighbourhood",
    "wof:population":1098
},
  "geometry": {"coordinates":[85.23345500000001,24.537062],"type":"Point"}
}