{
  "type": "Feature",
  "properties": {
    "gn:admin1_code":"35",
    "gn:admin2_code":"443.0",
    "gn:asciiname":"Marhiya",
    "gn:country_code":"IN",
    "gn:dem":475,
    "gn:feature_class":"P",
    "gn:feature_code":"PPL",
    "gn:name":"Marhiya",
    "gn:population":0,
    "gn:timezone":"Asia/Kolkata",
    "iso:country":"IN",
    "wof:name":"Marhiya",
    "wof:placetype":"locality"
},
  "geometry": {"coordinates":[78.20296999999999,23.54998],"type":"Point"}
}