{
  "type": "Feature",
  "properties": {
    "iso:country":"IN",
    "ks:ks_alt_nam":"BAHELJORE",
    "ks:ks_name":"Baheljore",
    "ks:ks_pop":217,
    "ks:ks_type":"HABITATION",
    "name:eng_x_preferred":[
        "Baheljore"
    ],
    "wof:name":"Baheljore",
    "wof:placetype":"locality",
    "wof:population":217
},
  "geometry": {"coordinates":[83.872738,22.616178],"type":"Point"}
}