{
  "type": "Feature",
  "properties": {
    "iso:country":"IN",
    "ks:ks_name":"Umari Izara",
    "ks:ks_pop":1058,
    "ks:ks_type":"HABITATION",
    "name:eng_x_preferred":[
        "Umari Izara"
    ],
    "wof:name":"Umari Izara",
    "wof:placetype":"locality",
    "wof:population":1058
},
  "geometry": {"coordinates":[77.828141,20.236387],"type":"Point"}
}