{
  "type": "Feature",
  "properties": {
    "iso:country":"IN",
    "ks:ks_name":"Akoriya",
    "ks:ks_pop":302,
    "ks:ks_type":"VILLAGE",
    "name:eng_x_preferred":[
        "Akoriya"
    ],
    "wof:name":"Akoriya",
    "wof:placetype":"locality",
    "wof:population":302
},
  "geometry": {"coordinates":[76.88412599999999,26.010149],"type":"Point"}
}