{
  "type": "Feature",
  "properties": {
    "iso:country":"IN",
    "ks:ks_name":"Rajkhara",
    "ks:ks_pop":633,
    "ks:ks_type":"VILLAGE",
    "name:eng_x_preferred":[
        "Rajkhara"
    ],
    "wof:name":"Rajkhara",
    "wof:placetype":"locality",
    "wof:population":633
},
  "geometry": {"coordinates":[88.23045999999999,23.289961],"type":"Point"}
}