{
  "type": "Feature",
  "properties": {
    "iso:country":"IN",
    "ks:ks_alt_nam":"muniyanatanda",
    "ks:ks_name":"Muniyanatanda",
    "ks:ks_pop":256,
    "ks:ks_type":"HABITATION",
    "name:eng_x_preferred":[
        "Muniyanatanda"
    ],
    "wof:name":"Muniyanatanda",
    "wof:placetype":"locality",
    "wof:population":256
},
  "geometry": {"coordinates":[75.511117,15.089068],"type":"Point"}
}