{
  "type": "Feature",
  "properties": {
    "iso:country":"IN",
    "ks:ks_name":"Tanda Bhagana",
    "ks:ks_pop":180,
    "ks:ks_type":"VILLAGE",
    "name:eng_x_preferred":[
        "Tanda Bhagana"
    ],
    "wof:name":"Tanda Bhagana",
    "wof:placetype":"locality",
    "wof:population":180
},
  "geometry": {"coordinates":[75.83345300000001,31.333142],"type":"Point"}
}