{
  "type": "Feature",
  "properties": {
    "iso:country":"IN",
    "ks:ks_alt_nam":"kutkutervita",
    "ks:ks_name":"Kutkutervita",
    "ks:ks_pop":620,
    "ks:ks_type":"HABITATION",
    "name:eng_x_preferred":[
        "Kutkutervita"
    ],
    "wof:name":"Kutkutervita",
    "wof:placetype":"locality",
    "wof:population":620
},
  "geometry": {"coordinates":[90.119865,26.259454],"type":"Point"}
}