{
  "type": "Feature",
  "properties": {
    "gn:admin1_code":"36.0",
    "gn:admin2_code":"171.0",
    "gn:asciiname":"Madna",
    "gn:country_code":"IN",
    "gn:dem":141,
    "gn:feature_class":"P",
    "gn:feature_code":"PPL",
    "gn:name":"Madna",
    "gn:population":0,
    "gn:timezone":"Asia/Kolkata",
    "iso:country":"IN",
    "ks:ks_name":"Matna",
    "ks:ks_pop":1455,
    "ks:ks_type":"VILLAGE",
    "name:ara_x_preferred":[
        "\u0645\u0627\u062f\u0646\u0629"
    ],
    "name:azb_x_preferred":[
        "\u0645\u0627\u062f\u0646\u0647"
    ],
    "name:eng_x_preferred":[
        "Matna"
    ],
    "name:eng_x_variant":[
        "Madna"
    ],
    "name:fas_x_preferred":[
        "\u0645\u0627\u062f\u0646\u0647"
    ],
    "name:fra_x_preferred":[
        "Madna"
    ],
    "name:ita_x_preferred":[
        "Madna"
    ],
    "name:kab_x_preferred":[
        "Madna"
    ],
    "name:msa_x_preferred":[
        "Madna"
    ],
    "name:por_x_preferred":[
        "Madna"
    ],
    "name:ron_x_preferred":[
        "Madna"
    ],
    "name:spa_x_preferred":[
        "Madna"
    ],
    "name:urd_x_preferred":[
        "\u0645\u06cc\u0688\u0646\u0627"
    ],
    "name:vie_x_preferred":[
        "Madna"
    ],
    "name:zho_x_preferred":[
        "\u99ac\u5fb7\u7d0d"
    ],
    "wof:name":"Matna",
    "wof:placetype":"locality",
    "wof:population":1455
},
  "geometry": {"coordinates":[81.063305,25.192644],"type":"Point"}
}