{
  "type": "Feature",
  "properties": {
    "iso:country":"IN",
    "ks:ks_name":"Kapariya",
    "ks:ks_pop":367,
    "ks:ks_type":"VILLAGE",
    "name:eng_x_preferred":[
        "Kapariya"
    ],
    "wof:name":"Kapariya",
    "wof:placetype":"locality",
    "wof:population":367
},
  "geometry": {"coordinates":[82.162284,23.389108],"type":"Point"}
}