{
  "type": "Feature",
  "properties": {
    "gn:admin1_code":"35",
    "gn:admin2_code":"455.0",
    "gn:asciiname":"Simariya",
    "gn:country_code":"IN",
    "gn:dem":698,
    "gn:feature_class":"P",
    "gn:feature_code":"PPL",
    "gn:name":"Simariya",
    "gn:population":0,
    "gn:timezone":"Asia/Kolkata",
    "iso:country":"IN",
    "name:bih_x_preferred":[
        "\u0938\u093f\u092e\u0930\u093f\u092f\u093e"
    ],
    "name:ceb_x_preferred":[
        "Simariya"
    ],
    "name:fra_x_preferred":[
        "Simariya"
    ],
    "name:hin_x_preferred":[
        "\u0938\u093f\u092e\u0930\u093f\u092f\u093e"
    ],
    "name:mai_x_preferred":[
        "\u0938\u093f\u092e\u0930\u093f\u092f\u093e"
    ],
    "name:msa_x_preferred":[
        "Simariya"
    ],
    "name:nep_x_preferred":[
        "\u0938\u093f\u092e\u0930\u093f\u092f\u093e"
    ],
    "name:new_x_preferred":[
        "\u0938\u093f\u092e\u0930\u093f\u092f\u093e"
    ],
    "name:pol_x_preferred":[
        "Simariya"
    ],
    "wof:name":"Simariya",
    "wof:placetype":"locality"
},
  "geometry": {"coordinates":[79.02736,22.49862000000001],"type":"Point"}
}