{
  "type": "Feature",
  "properties": {
    "iso:country":"IN",
    "ks:ks_alt_nam":"CHAVARE WASTI",
    "ks:ks_name":"Chavare Wasti",
    "ks:ks_pop":117,
    "ks:ks_type":"HABITATION",
    "name:eng_x_preferred":[
        "Chavare Wasti"
    ],
    "wof:name":"Chavare Wasti",
    "wof:placetype":"locality",
    "wof:population":117
},
  "geometry": {"coordinates":[75.287706,17.202408],"type":"Point"}
}