{
  "type": "Feature",
  "properties": {
    "gn:admin1_code":"36.0",
    "gn:admin2_code":"132.0",
    "gn:asciiname":"Gujar",
    "gn:country_code":"IN",
    "gn:dem":279,
    "gn:feature_class":"P",
    "gn:feature_code":"PPL",
    "gn:name":"Gujar",
    "gn:population":0,
    "gn:timezone":"Asia/Kolkata",
    "iso:country":"IN",
    "name:ceb_x_preferred":[
        "Gujar"
    ],
    "name:fas_x_preferred":[
        "\u06af\u0648\u062c\u0631"
    ],
    "wof:name":"Gujar",
    "wof:placetype":"locality"
},
  "geometry": {"coordinates":[77.48690000000001,30.01038],"type":"Point"}
}