{
  "type": "Feature",
  "properties": {
    "gn:admin1_code":"39.0",
    "gn:admin2_code":"66.0",
    "gn:asciiname":"Kahal Kuira",
    "gn:country_code":"IN",
    "gn:dem":1731,
    "gn:feature_class":"P",
    "gn:feature_code":"PPL",
    "gn:name":"Kahal Kuira",
    "gn:population":0,
    "gn:timezone":"Asia/Kolkata",
    "iso:country":"IN",
    "wof:name":"Kahal Kuira",
    "wof:placetype":"neighbourhood"
},
  "geometry": {"coordinates":[79.52884,29.3865],"type":"Point"}
}