{
  "type": "Feature",
  "properties": {
    "iso:country":"IN",
    "ks:ks_name":"Thummedalaneredu",
    "ks:ks_pop":76,
    "ks:ks_type":"HABITATION",
    "name:eng_x_preferred":[
        "Thummedalaneredu"
    ],
    "wof:name":"Thummedalaneredu",
    "wof:placetype":"locality",
    "wof:population":76
},
  "geometry": {"coordinates":[82.532573,18.059968],"type":"Point"}
}