{
  "type": "Feature",
  "properties": {
    "iso:country":"IN",
    "ks:ks_name":"Awasarewadi",
    "ks:ks_pop":208,
    "ks:ks_type":"HABITATION",
    "name:eng_x_preferred":[
        "Awasarewadi"
    ],
    "wof:name":"Awasarewadi",
    "wof:placetype":"locality",
    "wof:population":208
},
  "geometry": {"coordinates":[73.410556,16.953611],"type":"Point"}
}