{
  "type": "Feature",
  "properties": {
    "gn:admin1_code":"35.0",
    "gn:admin2_code":"455.0",
    "gn:asciiname":"Ghatiya",
    "gn:country_code":"IN",
    "gn:dem":642,
    "gn:feature_class":"P",
    "gn:feature_code":"PPL",
    "gn:name":"Gh\u0101tiya",
    "gn:population":0,
    "gn:timezone":"Asia/Kolkata",
    "iso:country":"IN",
    "ks:ks_alt_nam":"Gh\u0101tiya",
    "ks:ks_name":"Ghatiya",
    "ks:ks_pop":1156,
    "ks:ks_type":"VILLAGE",
    "name:eng_x_preferred":[
        "Ghatiya"
    ],
    "name:eng_x_variant":[
        "Gh\u0101tiya"
    ],
    "wof:name":"Ghatiya",
    "wof:placetype":"locality",
    "wof:population":1156
},
  "geometry": {"coordinates":[78.49507,22.317038],"type":"Point"}
}