{
  "type": "Feature",
  "properties": {
    "iso:country":"IN",
    "ks:ks_name":"Varachi Thombarewadi",
    "ks:ks_pop":29,
    "ks:ks_type":"HABITATION",
    "name:eng_x_preferred":[
        "Varachi Thombarewadi"
    ],
    "wof:name":"Varachi Thombarewadi",
    "wof:placetype":"locality",
    "wof:population":29
},
  "geometry": {"coordinates":[73.660836,17.005761],"type":"Point"}
}