{
  "type": "Feature",
  "properties": {
    "iso:country":"IN",
    "ks:ks_name":"Ramsing Tisso",
    "ks:ks_pop":408,
    "ks:ks_type":"HABITATION",
    "name:eng_x_preferred":[
        "Ramsing Tisso"
    ],
    "wof:name":"Ramsing Tisso",
    "wof:placetype":"locality",
    "wof:population":408
},
  "geometry": {"coordinates":[93.100289,26.253372],"type":"Point"}
}