{
  "type": "Feature",
  "properties": {
    "gn:admin1_code":"39",
    "gn:admin2_code":"61.0",
    "gn:asciiname":"Merwarhi",
    "gn:country_code":"IN",
    "gn:dem":1320,
    "gn:feature_class":"P",
    "gn:feature_code":"PPL",
    "gn:name":"Merw\u0101rhi",
    "gn:population":0,
    "gn:timezone":"Asia/Kolkata",
    "iso:country":"IN",
    "ks:ks_name":"Merwari",
    "ks:ks_pop":99,
    "ks:ks_type":"VILLAGE",
    "name:eng_x_preferred":[
        "Merwari"
    ],
    "name:eng_x_variant":[
        "Merwarhi"
    ],
    "wof:name":"Merwari",
    "wof:placetype":"locality",
    "wof:population":99
},
  "geometry": {"coordinates":[78.993595,29.658347],"type":"Point"}
}