{
  "type": "Feature",
  "properties": {
    "iso:country":"IN",
    "ks:ks_name":"Tabinipadar",
    "ks:ks_pop":79,
    "ks:ks_type":"VILLAGE",
    "name:eng_x_preferred":[
        "Tabinipadar"
    ],
    "wof:name":"Tabinipadar",
    "wof:placetype":"locality",
    "wof:population":79
},
  "geometry": {"coordinates":[84.200407,20.306106],"type":"Point"}
}