{
  "type": "Feature",
  "properties": {
    "iso:country":"IN",
    "ks:ks_name":"Kutayyapalem",
    "ks:ks_pop":262,
    "ks:ks_type":"HABITATION",
    "name:eng_x_preferred":[
        "Kutayyapalem"
    ],
    "wof:name":"Kutayyapalem",
    "wof:placetype":"locality",
    "wof:population":262
},
  "geometry": {"coordinates":[82.49385599999999,17.436508],"type":"Point"}
}