{
  "type": "Feature",
  "properties": {
    "iso:country":"IN",
    "ks:ks_name":"Gaura Buzurg",
    "ks:ks_pop":0,
    "ks:ks_type":"VILLAGE",
    "name:eng_x_preferred":[
        "Gaura Buzurg"
    ],
    "wof:name":"Gaura Buzurg",
    "wof:placetype":"locality",
    "wof:population":0
},
  "geometry": {"coordinates":[85.80343000000001,26.196424],"type":"Point"}
}