{
  "type": "Feature",
  "properties": {
    "iso:country":"IN",
    "ks:ks_name":"Barouli",
    "ks:ks_pop":2260,
    "ks:ks_type":"VILLAGE",
    "ks:ks_uagg_main":0,
    "name:eng_x_preferred":[
        "Barouli"
    ],
    "wof:name":"Barouli",
    "wof:placetype":"neighbourhood",
    "wof:population":2260
},
  "geometry": {"coordinates":[78.40825700000001,27.929277],"type":"Point"}
}