{
  "type": "Feature",
  "properties": {
    "gn:admin1_code":"19",
    "gn:admin2_code":"559.0",
    "gn:asciiname":"Saidapur",
    "gn:country_code":"IN",
    "gn:dem":476,
    "gn:feature_class":"P",
    "gn:feature_code":"PPL",
    "gn:name":"Said\u0101pur",
    "gn:population":0,
    "gn:timezone":"Asia/Kolkata",
    "iso:country":"IN",
    "name:pam_x_preferred":[
        "Saidapur"
    ],
    "name:tel_x_preferred":[
        "\u0c38\u0c48\u0c26\u0c3e\u0c2a\u0c42\u0c30\u0c4d"
    ],
    "name:urd_x_preferred":[
        "\u0633\u06cc\u062f\u067e\u0648\u0631"
    ],
    "wof:name":"Saidapur",
    "wof:placetype":"locality"
},
  "geometry": {"coordinates":[76.82840999999998,16.14589],"type":"Point"}
}