{
  "type": "Feature",
  "properties": {
    "gn:admin1_code":"38.0",
    "gn:admin2_code":"358.0",
    "gn:asciiname":"Sundarganj",
    "gn:country_code":"IN",
    "gn:dem":300,
    "gn:feature_class":"P",
    "gn:feature_code":"PPL",
    "gn:name":"Sundarganj",
    "gn:population":0,
    "gn:timezone":"Asia/Kolkata",
    "iso:country":"IN",
    "wof:name":"Sundarganj",
    "wof:placetype":"locality"
},
  "geometry": {"coordinates":[84.32143000000001,24.19635],"type":"Point"}
}