{
  "type": "Feature",
  "properties": {
    "iso:country":"IN",
    "ks:ks_name":"Naraharipur",
    "ks:ks_pop":759,
    "ks:ks_type":"VILLAGE",
    "ks:ks_uagg_main":0,
    "name:eng_x_preferred":[
        "Naraharipur"
    ],
    "wof:name":"Naraharipur",
    "wof:placetype":"neighbourhood",
    "wof:population":759
},
  "geometry": {"coordinates":[87.513628,21.865913],"type":"Point"}
}