{
  "type": "Feature",
  "properties": {
    "iso:country":"IN",
    "ks:ks_name":"Semmangudi",
    "ks:ks_pop":260,
    "ks:ks_type":"HABITATION",
    "name:eng_x_preferred":[
        "Semmangudi"
    ],
    "wof:name":"Semmangudi",
    "wof:placetype":"locality",
    "wof:population":260
},
  "geometry": {"coordinates":[79.647486,10.946687],"type":"Point"}
}