{
  "type": "Feature",
  "properties": {
    "gn:admin1_code":"2.0",
    "gn:admin2_code":"547.0",
    "gn:asciiname":"Reddigudem",
    "gn:country_code":"IN",
    "gn:dem":101,
    "gn:feature_class":"P",
    "gn:feature_code":"PPL",
    "gn:name":"Reddig\u016bdem",
    "gn:population":0,
    "gn:timezone":"Asia/Kolkata",
    "iso:country":"IN",
    "name:new_x_preferred":[
        "\u0930\u0947\u0921\u094d\u0921\u093f\u0917\u0942\u0921\u0947\u0902 \u092e\u0923\u094d\u0921\u0932"
    ],
    "name:tel_x_preferred":[
        "\u0c30\u0c46\u0c21\u0c4d\u0c21\u0c3f\u0c17\u0c42\u0c21\u0c46\u0c02"
    ],
    "wof:name":"Reddigudem",
    "wof:placetype":"locality"
},
  "geometry": {"coordinates":[80.73673000000002,16.86835],"type":"Point"}
}