{
  "type": "Feature",
  "properties": {
    "iso:country":"IN",
    "ks:ks_name":"Gijagini",
    "ks:ks_pop":303,
    "ks:ks_type":"VILLAGE",
    "name:eng_x_preferred":[
        "Gijagini"
    ],
    "wof:name":"Gijagini",
    "wof:placetype":"locality",
    "wof:population":303
},
  "geometry": {"coordinates":[74.686548,14.391837],"type":"Point"}
}