{
  "type": "Feature",
  "properties": {
    "iso:country":"IN",
    "ks:ks_name":"Kuthungara",
    "ks:ks_pop":520,
    "ks:ks_type":"HABITATION",
    "name:eng_x_preferred":[
        "Kuthungara"
    ],
    "wof:name":"Kuthungara",
    "wof:placetype":"locality",
    "wof:population":520
},
  "geometry": {"coordinates":[76.750136,9.897542],"type":"Point"}
}