{
  "type": "Feature",
  "properties": {
    "iso:country":"IN",
    "ks:ks_alt_nam":"PANDARABATIA",
    "ks:ks_name":"Pandarabatia",
    "ks:ks_pop":315,
    "ks:ks_type":"HABITATION",
    "name:eng_x_preferred":[
        "Pandarabatia"
    ],
    "wof:name":"Pandarabatia",
    "wof:placetype":"locality",
    "wof:population":315
},
  "geometry": {"coordinates":[86.55965500000001,20.881281],"type":"Point"}
}