{
  "type": "Feature",
  "properties": {
    "gn:admin1_code":"12.0",
    "gn:admin2_code":"7.0",
    "gn:asciiname":"Duar",
    "gn:country_code":"IN",
    "gn:dem":1742,
    "gn:feature_class":"P",
    "gn:feature_code":"PPL",
    "gn:name":"Du\u0101r",
    "gn:population":0,
    "gn:timezone":"Asia/Kolkata",
    "iso:country":"IN",
    "name:ara_x_preferred":[
        "\u062f\u0648\u0627\u0631"
    ],
    "name:fra_x_preferred":[
        "Duar"
    ],
    "wof:name":"Duar",
    "wof:placetype":"locality"
},
  "geometry": {"coordinates":[75.61751,32.66784000000001],"type":"Point"}
}