{
  "type": "Feature",
  "properties": {
    "iso:country":"IN",
    "ks:ks_name":"Sabak Dhanurjaypur",
    "ks:ks_pop":400,
    "ks:ks_type":"VILLAGE",
    "name:eng_x_preferred":[
        "Sabak Dhanurjaypur"
    ],
    "wof:name":"Sabak Dhanurjaypur",
    "wof:placetype":"locality",
    "wof:population":400
},
  "geometry": {"coordinates":[85.73620099999999,21.771651],"type":"Point"}
}