{
  "type": "Feature",
  "properties": {
    "iso:country":"IN",
    "ks:ks_name":"Sukadwadi",
    "ks:ks_pop":113,
    "ks:ks_type":"HABITATION",
    "name:eng_x_preferred":[
        "Sukadwadi"
    ],
    "wof:name":"Sukadwadi",
    "wof:placetype":"locality",
    "wof:population":113
},
  "geometry": {"coordinates":[73.312364,17.460772],"type":"Point"}
}