{
  "type": "Feature",
  "properties": {
    "gn:admin1_code":"35.0",
    "gn:admin2_code":"446.0",
    "gn:asciiname":"Ramgarh",
    "gn:country_code":"IN",
    "gn:dem":376,
    "gn:feature_class":"P",
    "gn:feature_code":"PPL",
    "gn:name":"R\u0101mgarh",
    "gn:population":0,
    "gn:timezone":"Asia/Kolkata",
    "iso:country":"IN",
    "wof:name":"Ramgarh",
    "wof:placetype":"locality"
},
  "geometry": {"coordinates":[78.28185999999999,23.238],"type":"Point"}
}