{
  "type": "Feature",
  "properties": {
    "iso:country":"IN",
    "ks:ks_name":"Biligeri",
    "ks:ks_pop":1456,
    "ks:ks_type":"VILLAGE",
    "name:eng_x_preferred":[
        "Biligeri"
    ],
    "wof:name":"Biligeri",
    "wof:placetype":"locality",
    "wof:population":1456
},
  "geometry": {"coordinates":[75.73921199999999,12.363761],"type":"Point"}
}