{
  "type": "Feature",
  "properties": {
    "gn:admin1_code":"35",
    "gn:admin2_code":"435.0",
    "gn:asciiname":"Hatiakheri",
    "gn:country_code":"IN",
    "gn:dem":500,
    "gn:feature_class":"P",
    "gn:feature_code":"PPL",
    "gn:name":"Hatiakheri",
    "gn:population":0,
    "gn:timezone":"Asia/Kolkata",
    "iso:country":"IN",
    "wof:name":"Hatiakheri",
    "wof:placetype":"locality"
},
  "geometry": {"coordinates":[75.46634,23.08671],"type":"Point"}
}