{
  "type": "Feature",
  "properties": {
    "iso:country":"IN",
    "ks:ks_name":"Parmanandpur",
    "ks:ks_pop":1421,
    "ks:ks_type":"VILLAGE",
    "ks:ks_uagg_main":0,
    "name:eng_x_preferred":[
        "Parmanandpur"
    ],
    "wof:name":"Parmanandpur",
    "wof:placetype":"locality",
    "wof:population":1421
},
  "geometry": {"coordinates":[85.939756,26.035689],"type":"Point"}
}