{
  "type": "Feature",
  "properties": {
    "iso:country":"IN",
    "ks:ks_name":"Choudhary Tola",
    "ks:ks_pop":1152,
    "ks:ks_type":"HABITATION",
    "name:eng_x_preferred":[
        "Choudhary Tola"
    ],
    "wof:name":"Choudhary Tola",
    "wof:placetype":"locality",
    "wof:population":1152
},
  "geometry": {"coordinates":[86.234561,25.368858],"type":"Point"}
}