{
  "type": "Feature",
  "properties": {
    "iso:country":"IN",
    "ks:ks_name":"Shri Ram Talawali",
    "ks:ks_pop":855,
    "ks:ks_type":"VILLAGE",
    "name:eng_x_preferred":[
        "Shri Ram Talawali"
    ],
    "wof:name":"Shri Ram Talawali",
    "wof:placetype":"neighbourhood",
    "wof:population":855
},
  "geometry": {"coordinates":[75.758439,22.68044],"type":"Point"}
}