{
  "type": "Feature",
  "properties": {
    "iso:country":"IN",
    "ks:ks_name":"Bichkani",
    "ks:ks_pop":113,
    "ks:ks_type":"HABITATION",
    "name:eng_x_preferred":[
        "Bichkani"
    ],
    "wof:name":"Bichkani",
    "wof:placetype":"locality",
    "wof:population":113
},
  "geometry": {"coordinates":[87.509246,25.249817],"type":"Point"}
}