{
  "type": "Feature",
  "properties": {
    "gn:admin1_code":"34.0",
    "gn:admin2_code":"216.0",
    "gn:asciiname":"Rampur Mani",
    "gn:country_code":"IN",
    "gn:dem":54,
    "gn:feature_class":"P",
    "gn:feature_code":"PPL",
    "gn:name":"R\u0101mpur Mani",
    "gn:population":0,
    "gn:timezone":"Asia/Kolkata",
    "iso:country":"IN",
    "ks:ks_alt_nam":"R\u0101mpur Mani",
    "ks:ks_name":"Rampur Mani",
    "ks:ks_pop":2173,
    "ks:ks_type":"VILLAGE",
    "name:eng_x_preferred":[
        "Rampur Mani"
    ],
    "name:eng_x_variant":[
        "R\u0101mpur Mani"
    ],
    "wof:name":"Rampur Mani",
    "wof:placetype":"locality",
    "wof:population":2173
},
  "geometry": {"coordinates":[85.46526,25.992743],"type":"Point"}
}