{
  "type": "Feature",
  "properties": {
    "iso:country":"IN",
    "ks:ks_name":"Sankaralingapuram",
    "ks:ks_pop":181,
    "ks:ks_type":"HABITATION",
    "name:eng_x_preferred":[
        "Sankaralingapuram"
    ],
    "wof:name":"Sankaralingapuram",
    "wof:placetype":"locality",
    "wof:population":181
},
  "geometry": {"coordinates":[78.183699,10.133095],"type":"Point"}
}