{
  "type": "Feature",
  "properties": {
    "iso:country":"IN",
    "ks:ks_name":"Shilottar Raichur",
    "ks:ks_pop":5796,
    "ks:ks_type":"VILLAGE",
    "name:eng_x_preferred":[
        "Shilottar Raichur"
    ],
    "wof:name":"Shilottar Raichur",
    "wof:placetype":"locality",
    "wof:population":5796
},
  "geometry": {"coordinates":[73.138971,18.99933],"type":"Point"}
}