{
  "type": "Feature",
  "properties": {
    "iso:country":"IN",
    "ks:ks_name":"Baruna",
    "ks:ks_pop":716,
    "ks:ks_type":"VILLAGE",
    "ks:ks_uagg_main":0,
    "name:eng_x_preferred":[
        "Baruna"
    ],
    "wof:name":"Baruna",
    "wof:placetype":"neighbourhood",
    "wof:population":716
},
  "geometry": {"coordinates":[88.19456,23.392365],"type":"Point"}
}