{
  "type": "Feature",
  "properties": {
    "gn:admin1_code":"16.0",
    "gn:admin2_code":"510.0",
    "gn:asciiname":"Kharda",
    "gn:country_code":"IN",
    "gn:dem":265,
    "gn:feature_class":"P",
    "gn:feature_code":"PPL",
    "gn:name":"Kharda",
    "gn:population":0,
    "gn:timezone":"Asia/Kolkata",
    "iso:country":"IN",
    "name:jpn_x_preferred":[
        "\u30ab\u30eb\u30c0\u30fc"
    ],
    "name:mar_x_preferred":[
        "\u0916\u0930\u094d\u0921\u093e"
    ],
    "wof:name":"Kharda",
    "wof:placetype":"locality"
},
  "geometry": {"coordinates":[78.17142,20.62014],"type":"Point"}
}