{
  "type": "Feature",
  "properties": {
    "gn:admin1_code":"39.0",
    "gn:admin2_code":"62.0",
    "gn:asciiname":"Kharchaura",
    "gn:country_code":"IN",
    "gn:dem":975,
    "gn:feature_class":"P",
    "gn:feature_code":"PPL",
    "gn:name":"Kharchaura",
    "gn:population":0,
    "gn:timezone":"Asia/Kolkata",
    "iso:country":"IN",
    "ks:ks_name":"Khar Chaura",
    "ks:ks_pop":54,
    "ks:ks_type":"VILLAGE",
    "name:eng_x_preferred":[
        "Khar Chaura"
    ],
    "name:eng_x_variant":[
        "Kharchaura"
    ],
    "wof:name":"Khar Chaura",
    "wof:placetype":"locality",
    "wof:population":54
},
  "geometry": {"coordinates":[79.953231,29.719571],"type":"Point"}
}