{
  "type": "Feature",
  "properties": {
    "iso:country":"IN",
    "ks:ks_name":"Saravu",
    "ks:ks_pop":255,
    "ks:ks_type":"HABITATION",
    "name:eng_x_preferred":[
        "Saravu"
    ],
    "wof:name":"Saravu",
    "wof:placetype":"locality",
    "wof:population":255
},
  "geometry": {"coordinates":[75.09039799999999,12.946924],"type":"Point"}
}