{
  "type": "Feature",
  "properties": {
    "iso:country":"IN",
    "ks:ks_name":"Purba Bhagabanpur",
    "ks:ks_pop":2141,
    "ks:ks_type":"HABITATION",
    "name:eng_x_preferred":[
        "Purba Bhagabanpur"
    ],
    "wof:name":"Purba Bhagabanpur",
    "wof:placetype":"locality",
    "wof:population":2141
},
  "geometry": {"coordinates":[88.063779,25.457529],"type":"Point"}
}