{
  "type": "Feature",
  "properties": {
    "iso:country":"IN",
    "ks:ks_name":"Kuia",
    "ks:ks_pop":1558,
    "ks:ks_type":"VILLAGE",
    "ks:ks_uagg_main":0,
    "name:eng_x_preferred":[
        "Kuia"
    ],
    "wof:name":"Kuia",
    "wof:placetype":"neighbourhood",
    "wof:population":1558
},
  "geometry": {"coordinates":[86.447745,23.753858],"type":"Point"}
}