{
  "type": "Feature",
  "properties": {
    "iso:country":"IN",
    "ks:ks_name":"Mallikpara",
    "ks:ks_pop":666,
    "ks:ks_type":"VILLAGE",
    "ks:ks_uagg_main":0,
    "name:eng_x_preferred":[
        "Mallikpara"
    ],
    "wof:name":"Mallikpara",
    "wof:placetype":"neighbourhood",
    "wof:population":666
},
  "geometry": {"coordinates":[87.56595,23.427335],"type":"Point"}
}