{
  "type": "Feature",
  "properties": {
    "gn:admin1_code":"39.0",
    "gn:admin2_code":"62.0",
    "gn:asciiname":"Biroli",
    "gn:country_code":"IN",
    "gn:dem":1493,
    "gn:feature_class":"P",
    "gn:feature_code":"PPL",
    "gn:name":"Biroli",
    "gn:population":0,
    "gn:timezone":"Asia/Kolkata",
    "iso:country":"IN",
    "wof:name":"Biroli",
    "wof:placetype":"locality"
},
  "geometry": {"coordinates":[79.98899999999998,29.72075],"type":"Point"}
}