{
  "type": "Feature",
  "properties": {
    "iso:country":"IN",
    "ks:ks_name":"Kavalapurwada",
    "ks:ks_pop":180,
    "ks:ks_type":"HABITATION",
    "name:eng_x_preferred":[
        "Kavalapurwada"
    ],
    "wof:name":"Kavalapurwada",
    "wof:placetype":"locality",
    "wof:population":180
},
  "geometry": {"coordinates":[74.437309,15.628915],"type":"Point"}
}