{
  "type": "Feature",
  "properties": {
    "iso:country":"IN",
    "ks:ks_name":"Jogilabailu",
    "ks:ks_pop":180,
    "ks:ks_type":"HABITATION",
    "name:eng_x_preferred":[
        "Jogilabailu"
    ],
    "wof:name":"Jogilabailu",
    "wof:placetype":"locality",
    "wof:population":180
},
  "geometry": {"coordinates":[75.004313,12.82885],"type":"Point"}
}