{
  "type": "Feature",
  "properties": {
    "iso:country":"IN",
    "ks:ks_name":"Bijauli",
    "ks:ks_type":"VILLAGE",
    "name:eng_x_preferred":[
        "Bijauli"
    ],
    "wof:name":"Bijauli",
    "wof:placetype":"locality"
},
  "geometry": {"coordinates":[83.303954,26.791152],"type":"Point"}
}