{
  "type": "Feature",
  "properties": {
    "gn:admin1_code":"11.0",
    "gn:admin2_code":"32.0",
    "gn:asciiname":"Charawala",
    "gn:country_code":"IN",
    "gn:dem":515,
    "gn:feature_class":"P",
    "gn:feature_code":"PPL",
    "gn:name":"Charaw\u0101la",
    "gn:population":0,
    "gn:timezone":"Asia/Kolkata",
    "iso:country":"IN",
    "wof:name":"Charawala",
    "wof:placetype":"locality"
},
  "geometry": {"coordinates":[77.24913000000002,30.55884],"type":"Point"}
}