{
  "type": "Feature",
  "properties": {
    "iso:country":"IN",
    "ks:ks_name":"11 JSN",
    "ks:ks_pop":30,
    "ks:ks_type":"VILLAGE",
    "name:eng_x_preferred":[
        "11 JSN"
    ],
    "wof:name":"11 JSN",
    "wof:placetype":"locality",
    "wof:population":30
},
  "geometry": {"coordinates":[74.936116,29.294533],"type":"Point"}
}