{
  "type": "Feature",
  "properties": {
    "gn:admin1_code":"35.0",
    "gn:admin2_code":"429.0",
    "gn:asciiname":"Khaira",
    "gn:country_code":"IN",
    "gn:dem":349,
    "gn:feature_class":"P",
    "gn:feature_code":"PPL",
    "gn:name":"Khaira",
    "gn:population":0,
    "gn:timezone":"Asia/Kolkata",
    "iso:country":"IN",
    "name:hin_x_preferred":[
        "\u0916\u0948\u0930\u093e"
    ],
    "name:new_x_preferred":[
        "\u0916\u0948\u0930\u093e"
    ],
    "wof:name":"Khaira",
    "wof:placetype":"locality"
},
  "geometry": {"coordinates":[80.75672,24.19153],"type":"Point"}
}