{
  "type": "Feature",
  "properties": {
    "iso:country":"IN",
    "ks:ks_alt_nam":"TARAIYA",
    "ks:ks_name":"Taraiya",
    "ks:ks_pop":1950,
    "ks:ks_type":"HABITATION",
    "name:eng_x_preferred":[
        "Taraiya"
    ],
    "wof:name":"Taraiya",
    "wof:placetype":"locality",
    "wof:population":1950
},
  "geometry": {"coordinates":[84.887027,26.068031],"type":"Point"}
}