{
  "type": "Feature",
  "properties": {
    "iso:country":"IN",
    "ks:ks_name":"Sirsian East",
    "ks:ks_pop":885,
    "ks:ks_type":"HABITATION",
    "ks:ks_uagg_main":0,
    "name:eng_x_preferred":[
        "Sirsian East"
    ],
    "wof:name":"Sirsian East",
    "wof:placetype":"neighbourhood",
    "wof:population":885
},
  "geometry": {"coordinates":[83.861868,26.749641],"type":"Point"}
}