{
  "type": "Feature",
  "properties": {
    "gn:admin1_code":"36",
    "gn:admin2_code":"155.0",
    "gn:asciiname":"Gajhathana",
    "gn:country_code":"IN",
    "gn:dem":141,
    "gn:feature_class":"P",
    "gn:feature_code":"PPL",
    "gn:name":"Gajhathana",
    "gn:population":0,
    "gn:timezone":"Asia/Kolkata",
    "iso:country":"IN",
    "wof:name":"Gajhathana",
    "wof:placetype":"locality"
},
  "geometry": {"coordinates":[79.95911,27.41707],"type":"Point"}
}