{
  "type": "Feature",
  "properties": {
    "iso:country":"IN",
    "ks:ks_name":"Sukhpar Bara",
    "ks:ks_pop":153,
    "ks:ks_type":"VILLAGE",
    "name:eng_x_preferred":[
        "Sukhpar Bara"
    ],
    "wof:name":"Sukhpar Bara",
    "wof:placetype":"locality",
    "wof:population":153
},
  "geometry": {"coordinates":[68.88119,23.308588],"type":"Point"}
}