{
  "type": "Feature",
  "properties": {
    "iso:country":"IN",
    "ks:ks_name":"Chamarajodi",
    "ks:ks_pop":375,
    "ks:ks_type":"VILLAGE",
    "name:eng_x_preferred":[
        "Chamarajodi"
    ],
    "wof:name":"Chamarajodi",
    "wof:placetype":"locality",
    "wof:population":375
},
  "geometry": {"coordinates":[83.091883,19.240708],"type":"Point"}
}