{
  "type": "Feature",
  "properties": {
    "iso:country":"IN",
    "ks:ks_name":"Dhanadahi",
    "ks:ks_pop":155,
    "ks:ks_type":"VILLAGE",
    "name:eng_x_preferred":[
        "Dhanadahi"
    ],
    "wof:name":"Dhanadahi",
    "wof:placetype":"locality",
    "wof:population":155
},
  "geometry": {"coordinates":[86.779718,22.246267],"type":"Point"}
}