{
  "type": "Feature",
  "properties": {
    "gn:admin1_code":"34.0",
    "gn:admin2_code":"204.0",
    "gn:asciiname":"Nayagaon",
    "gn:country_code":"IN",
    "gn:dem":76,
    "gn:feature_class":"P",
    "gn:feature_code":"PPL",
    "gn:name":"Nay\u0101gaon",
    "gn:population":0,
    "gn:timezone":"Asia/Kolkata",
    "iso:country":"IN",
    "ks:ks_name":"Naya Ganw",
    "ks:ks_pop":2059,
    "ks:ks_type":"VILLAGE",
    "ks:ks_uagg_main":0,
    "name:eng_x_preferred":[
        "Naya Ganw"
    ],
    "wof:name":"Naya Ganw",
    "wof:placetype":"neighbourhood",
    "wof:population":2059
},
  "geometry": {"coordinates":[84.668041,26.631234],"type":"Point"}
}