{
  "type": "Feature",
  "properties": {
    "iso:country":"IN",
    "ks:ks_alt_nam":"M\u016bs\u0101pet",
    "ks:ks_name":"Musapet",
    "ks:ks_type":"VILLAGE",
    "ks:ks_uagg_main":0,
    "name:eng_x_preferred":[
        "Musapet"
    ],
    "name:eng_x_variant":[
        "M\u016bs\u0101pet"
    ],
    "wof:name":"Musapet",
    "wof:placetype":"neighbourhood"
},
  "geometry": {"coordinates":[78.424792,17.468819],"type":"Point"}
}