{
  "type": "Feature",
  "properties": {
    "iso:country":"IN",
    "ks:ks_name":"Kampadalisalpara",
    "ks:ks_pop":67,
    "ks:ks_type":"HABITATION",
    "name:eng_x_preferred":[
        "Kampadalisalpara"
    ],
    "wof:name":"Kampadalisalpara",
    "wof:placetype":"locality",
    "wof:population":67
},
  "geometry": {"coordinates":[91.208538,25.759299],"type":"Point"}
}