{
  "type": "Feature",
  "properties": {
    "iso:country":"IN",
    "ks:ks_name":"Manikkala",
    "ks:ks_pop":140,
    "ks:ks_type":"HABITATION",
    "name:eng_x_preferred":[
        "Manikkala"
    ],
    "wof:name":"Manikkala",
    "wof:placetype":"locality",
    "wof:population":140
},
  "geometry": {"coordinates":[75.36217600000001,12.938233],"type":"Point"}
}