{
  "type": "Feature",
  "properties": {
    "iso:country":"IN",
    "ks:ks_name":"Bichhiyari",
    "ks:ks_pop":1027,
    "ks:ks_type":"VILLAGE",
    "name:eng_x_preferred":[
        "Bichhiyari"
    ],
    "wof:name":"Bichhiyari",
    "wof:placetype":"locality",
    "wof:population":1027
},
  "geometry": {"coordinates":[82.971926,23.928784],"type":"Point"}
}