{
  "type": "Feature",
  "properties": {
    "gn:admin1_code":"16.0",
    "gn:admin2_code":"497.0",
    "gn:asciiname":"Valheri",
    "gn:country_code":"IN",
    "gn:dem":192,
    "gn:feature_class":"P",
    "gn:feature_code":"PPL",
    "gn:name":"V\u0101lheri",
    "gn:population":0,
    "gn:timezone":"Asia/Kolkata",
    "iso:country":"IN",
    "ks:ks_alt_nam":"V\u0101lheri",
    "ks:ks_name":"Valheri",
    "ks:ks_type":"VILLAGE",
    "name:eng_x_preferred":[
        "Valheri"
    ],
    "name:eng_x_variant":[
        "V\u0101lheri"
    ],
    "wof:name":"Valheri",
    "wof:placetype":"locality"
},
  "geometry": {"coordinates":[74.125557,21.615498],"type":"Point"}
}