{
  "type": "Feature",
  "properties": {
    "iso:country":"IN",
    "ks:ks_alt_nam":"PANDEY TOLA YADAVI",
    "ks:ks_name":"Pandey Tola Yadavi",
    "ks:ks_pop":295,
    "ks:ks_type":"HABITATION",
    "name:eng_x_preferred":[
        "Pandey Tola Yadavi"
    ],
    "wof:name":"Pandey Tola Yadavi",
    "wof:placetype":"locality",
    "wof:population":295
},
  "geometry": {"coordinates":[84.75590699999999,26.317204],"type":"Point"}
}