{
  "type": "Feature",
  "properties": {
    "iso:country":"IN",
    "ks:ks_name":"Rotodo",
    "ks:ks_pop":288,
    "ks:ks_type":"VILLAGE",
    "name:eng_x_preferred":[
        "Rotodo"
    ],
    "wof:name":"Rotodo",
    "wof:placetype":"locality",
    "wof:population":288
},
  "geometry": {"coordinates":[83.501254,19.772646],"type":"Point"}
}