{
  "type": "Feature",
  "properties": {
    "gn:admin1_code":"24",
    "gn:admin2_code":"104.0",
    "gn:asciiname":"Sherpur",
    "gn:country_code":"IN",
    "gn:dem":324,
    "gn:feature_class":"P",
    "gn:feature_code":"PPL",
    "gn:name":"Sherpur",
    "gn:population":0,
    "gn:timezone":"Asia/Kolkata",
    "iso:country":"IN",
    "name:ceb_x_preferred":[
        "Sherpur"
    ],
    "name:nld_x_preferred":[
        "Sherpur"
    ],
    "name:rus_x_preferred":[
        "\u0428\u0435\u0440\u043f\u0443\u0440"
    ],
    "name:swe_x_preferred":[
        "Sherpur"
    ],
    "name:und_x_variant":[
        "Samarwas"
    ],
    "wof:name":"Sherpur",
    "wof:placetype":"locality"
},
  "geometry": {"coordinates":[76.2761,27.87],"type":"Point"}
}