{
  "type": "Feature",
  "properties": {
    "iso:country":"IN",
    "ks:ks_name":"Chittaparai",
    "ks:ks_pop":150,
    "ks:ks_type":"HABITATION",
    "name:eng_x_preferred":[
        "Chittaparai"
    ],
    "wof:name":"Chittaparai",
    "wof:placetype":"locality",
    "wof:population":150
},
  "geometry": {"coordinates":[79.109554,13.037077],"type":"Point"}
}