{
  "type": "Feature",
  "properties": {
    "gn:admin1_code":"35.0",
    "gn:asciiname":"Sindhan Kalan",
    "gn:country_code":"IN",
    "gn:dem":115,
    "gn:feature_class":"P",
    "gn:feature_code":"PPL",
    "gn:name":"Sindhan Kal\u0101n",
    "gn:population":0,
    "gn:timezone":"Asia/Kolkata",
    "iso:country":"IN",
    "name:und_x_variant":[
        "Sindhan Kal\u0101n",
        "Sindhan Katan"
    ],
    "wof:name":"Sindhan Kalan",
    "wof:placetype":"locality"
},
  "geometry": {"coordinates":[80.44094,25.77252],"type":"Point"}
}