{
  "type": "Feature",
  "properties": {
    "gn:admin1_code":"35.0",
    "gn:admin2_code":"418",
    "gn:asciiname":"Ajapura",
    "gn:country_code":"IN",
    "gn:dem":243,
    "gn:feature_class":"P",
    "gn:feature_code":"PPL",
    "gn:name":"Aj\u0101pura",
    "gn:population":0,
    "gn:timezone":"Asia/Kolkata",
    "iso:country":"IN",
    "wof:name":"Ajapura",
    "wof:placetype":"locality"
},
  "geometry": {"coordinates":[76.67345999999998,25.61785],"type":"Point"}
}