{
  "type": "Feature",
  "properties": {
    "iso:country":"IN",
    "ks:ks_name":"Kanchikai",
    "ks:ks_pop":51,
    "ks:ks_type":"HABITATION",
    "name:eng_x_preferred":[
        "Kanchikai"
    ],
    "wof:name":"Kanchikai",
    "wof:placetype":"locality",
    "wof:population":51
},
  "geometry": {"coordinates":[74.849779,14.142717],"type":"Point"}
}