{
  "type": "Feature",
  "properties": {
    "iso:country":"IN",
    "ks:ks_name":"Kakadpada",
    "ks:ks_pop":167,
    "ks:ks_type":"HABITATION",
    "name:eng_x_preferred":[
        "Kakadpada"
    ],
    "wof:name":"Kakadpada",
    "wof:placetype":"locality",
    "wof:population":167
},
  "geometry": {"coordinates":[72.940428,19.764303],"type":"Point"}
}