{
  "type": "Feature",
  "properties": {
    "iso:country":"IN",
    "ks:ks_name":"Thiruvasal",
    "ks:ks_pop":265,
    "ks:ks_type":"HABITATION",
    "name:eng_x_preferred":[
        "Thiruvasal"
    ],
    "wof:name":"Thiruvasal",
    "wof:placetype":"locality",
    "wof:population":265
},
  "geometry": {"coordinates":[79.736925,10.60179],"type":"Point"}
}