{
  "type": "Feature",
  "properties": {
    "iso:country":"IN",
    "ks:ks_name":"Dhanuduveedhi",
    "ks:ks_pop":70,
    "ks:ks_type":"HABITATION",
    "name:eng_x_preferred":[
        "Dhanuduveedhi"
    ],
    "wof:name":"Dhanuduveedhi",
    "wof:placetype":"locality",
    "wof:population":70
},
  "geometry": {"coordinates":[82.478151,17.778286],"type":"Point"}
}