{
  "type": "Feature",
  "properties": {
    "iso:country":"IN",
    "ks:ks_name":"Sankali Anta Simada",
    "ks:ks_pop":671,
    "ks:ks_type":"HABITATION",
    "name:eng_x_preferred":[
        "Sankali Anta Simada"
    ],
    "wof:name":"Sankali Anta Simada",
    "wof:placetype":"locality",
    "wof:population":671
},
  "geometry": {"coordinates":[73.71901699999999,22.76485],"type":"Point"}
}