{
  "type": "Feature",
  "properties": {
    "gn:admin1_code":"2.0",
    "gn:admin2_code":"544.0",
    "gn:asciiname":"Kumiputtu",
    "gn:country_code":"IN",
    "gn:dem":807,
    "gn:feature_class":"P",
    "gn:feature_code":"PPL",
    "gn:name":"K\u016bmiputtu",
    "gn:population":0,
    "gn:timezone":"Asia/Kolkata",
    "iso:country":"IN",
    "ks:ks_name":"Kumbiputtu",
    "ks:ks_pop":20,
    "ks:ks_type":"HABITATION",
    "name:eng_x_preferred":[
        "Kumbiputtu"
    ],
    "name:eng_x_variant":[
        "Kumiputtu"
    ],
    "wof:name":"Kumbiputtu",
    "wof:placetype":"locality",
    "wof:population":20
},
  "geometry": {"coordinates":[82.497378,18.474135],"type":"Point"}
}