{
  "type": "Feature",
  "properties": {
    "iso:country":"IN",
    "ks:ks_name":"Balaheda",
    "ks:ks_pop":832,
    "ks:ks_type":"VILLAGE",
    "name:eng_x_preferred":[
        "Balaheda"
    ],
    "wof:name":"Balaheda",
    "wof:placetype":"locality",
    "wof:population":832
},
  "geometry": {"coordinates":[75.327499,24.217674],"type":"Point"}
}