{
  "type": "Feature",
  "properties": {
    "gn:admin1_code":"11",
    "gn:admin2_code":"23.0",
    "gn:asciiname":"Sararka",
    "gn:country_code":"IN",
    "gn:dem":1219,
    "gn:feature_class":"P",
    "gn:feature_code":"PPL",
    "gn:name":"Sar\u0101rka",
    "gn:population":0,
    "gn:timezone":"Asia/Kolkata",
    "iso:country":"IN",
    "wof:name":"Sararka",
    "wof:placetype":"locality"
},
  "geometry": {"coordinates":[76.10179000000002,32.5644],"type":"Point"}
}