{
  "type": "Feature",
  "properties": {
    "iso:country":"IN",
    "ks:ks_name":"Chhota Chitolia",
    "ks:ks_pop":2552,
    "ks:ks_type":"VILLAGE",
    "ks:ks_uagg_main":0,
    "name:eng_x_preferred":[
        "Chhota Chitolia"
    ],
    "wof:name":"Chhota Chitolia",
    "wof:placetype":"neighbourhood",
    "wof:population":2552
},
  "geometry": {"coordinates":[87.73428800000001,24.994536],"type":"Point"}
}