{
  "type": "Feature",
  "properties": {
    "iso:country":"IN",
    "ks:ks_name":"Kalaketti",
    "ks:ks_pop":1151,
    "ks:ks_type":"HABITATION",
    "name:eng_x_preferred":[
        "Kalaketti"
    ],
    "wof:name":"Kalaketti",
    "wof:placetype":"locality",
    "wof:population":1151
},
  "geometry": {"coordinates":[76.754963,9.724837],"type":"Point"}
}