{
  "type": "Feature",
  "properties": {
    "iso:country":"IN",
    "ks:ks_name":"Mahua Kheda",
    "ks:ks_pop":34,
    "ks:ks_type":"HABITATION",
    "name:eng_x_preferred":[
        "Mahua Kheda"
    ],
    "wof:name":"Mahua Kheda",
    "wof:placetype":"locality",
    "wof:population":34
},
  "geometry": {"coordinates":[77.37626899999999,23.139154],"type":"Point"}
}