{
  "type": "Feature",
  "properties": {
    "gn:admin1_code":"36.0",
    "gn:admin2_code":"175.0",
    "gn:asciiname":"Chak Lalmuhammad Befikar",
    "gn:country_code":"IN",
    "gn:dem":91,
    "gn:feature_class":"P",
    "gn:feature_code":"PPL",
    "gn:name":"Chak L\u0101lmuhammad Befikar",
    "gn:population":0,
    "gn:timezone":"Asia/Kolkata",
    "iso:country":"IN",
    "wof:name":"Chak Lalmuhammad Befikar",
    "wof:placetype":"neighbourhood"
},
  "geometry": {"coordinates":[81.88370999999999,25.39182],"type":"Point"}
}