{
  "type": "Feature",
  "properties": {
    "iso:country":"IN",
    "ks:ks_name":"Mangraj",
    "ks:ks_pop":972,
    "ks:ks_type":"VILLAGE",
    "ks:ks_uagg_main":0,
    "name:eng_x_preferred":[
        "Mangraj"
    ],
    "wof:name":"Mangraj",
    "wof:placetype":"neighbourhood",
    "wof:population":972
},
  "geometry": {"coordinates":[87.62325199999999,21.978439],"type":"Point"}
}