{
  "type": "Feature",
  "properties": {
    "gn:admin1_code":"11",
    "gn:admin2_code":"33.0",
    "gn:asciiname":"Dhauni Dogri",
    "gn:country_code":"IN",
    "gn:dem":1945,
    "gn:feature_class":"P",
    "gn:feature_code":"PPL",
    "gn:name":"Dhauni Dogri",
    "gn:population":0,
    "gn:timezone":"Asia/Kolkata",
    "iso:country":"IN",
    "wof:name":"Dhauni Dogri",
    "wof:placetype":"locality"
},
  "geometry": {"coordinates":[77.87175000000001,31.21228],"type":"Point"}
}