{
  "type": "Feature",
  "properties": {
    "iso:country":"IN",
    "ks:ks_name":"Gurikanivaripalli",
    "ks:ks_pop":125,
    "ks:ks_type":"HABITATION",
    "name:eng_x_preferred":[
        "Gurikanivaripalli"
    ],
    "wof:name":"Gurikanivaripalli",
    "wof:placetype":"locality",
    "wof:population":125
},
  "geometry": {"coordinates":[78.27785299999999,14.051649],"type":"Point"}
}