{
  "type": "Feature",
  "properties": {
    "gn:admin1_code":"02",
    "gn:admin2_code":"545.0",
    "gn:asciiname":"Medapadu",
    "gn:country_code":"IN",
    "gn:dem":20,
    "gn:feature_class":"P",
    "gn:feature_code":"PPL",
    "gn:name":"Medap\u0101du",
    "gn:population":0,
    "gn:timezone":"Asia/Kolkata",
    "iso:country":"IN",
    "wof:name":"Medapadu",
    "wof:placetype":"neighbourhood"
},
  "geometry": {"coordinates":[82.10011,17.00445],"type":"Point"}
}