{
  "type": "Feature",
  "properties": {
    "iso:country":"IN",
    "ks:ks_name":"Jhariya",
    "ks:ks_pop":1727,
    "ks:ks_type":"HABITATION",
    "name:eng_x_preferred":[
        "Jhariya"
    ],
    "wof:name":"Jhariya",
    "wof:placetype":"locality",
    "wof:population":1727
},
  "geometry": {"coordinates":[72.616589,26.720747],"type":"Point"}
}