{
  "type": "Feature",
  "properties": {
    "iso:country":"IN",
    "ks:ks_name":"9 P",
    "ks:ks_pop":149,
    "ks:ks_type":"HABITATION",
    "name:eng_x_preferred":[
        "9 P"
    ],
    "wof:name":"9 P",
    "wof:placetype":"locality",
    "wof:population":149
},
  "geometry": {"coordinates":[73.179276,29.074186],"type":"Point"}
}