{
  "type": "Feature",
  "properties": {
    "gn:admin1_code":"21",
    "gn:admin2_code":"395.0",
    "gn:asciiname":"Dengparsi",
    "gn:country_code":"IN",
    "gn:dem":805,
    "gn:feature_class":"P",
    "gn:feature_code":"PPL",
    "gn:name":"Dengparsi",
    "gn:population":0,
    "gn:timezone":"Asia/Kolkata",
    "iso:country":"IN",
    "wof:name":"Dengparsi",
    "wof:placetype":"locality"
},
  "geometry": {"coordinates":[83.02455999999999,19.61394],"type":"Point"}
}