{
  "type": "Feature",
  "properties": {
    "gn:admin1_code":"21",
    "gn:admin2_code":"395.0",
    "gn:asciiname":"Dengparsi",
    "gn:country_code":"IN",
    "gn:dem":805,
    "gn:feature_class":"P",
    "gn:feature_code":"PPL",
    "gn:name":"Dengparsi",
    "gn:population":0,
    "gn:timezone":"Asia/Kolkata",
    "iso:country":"IN",
    "ks:ks_name":"Dengpharsi",
    "ks:ks_pop":186,
    "ks:ks_type":"VILLAGE",
    "name:eng_x_preferred":[
        "Dengpharsi"
    ],
    "name:eng_x_variant":[
        "Dengparsi"
    ],
    "wof:name":"Dengpharsi",
    "wof:placetype":"locality",
    "wof:population":186
},
  "geometry": {"coordinates":[83.023842,19.613603],"type":"Point"}
}