{
  "type": "Feature",
  "properties": {
    "iso:country":"IN",
    "ks:ks_name":"Patkoi",
    "ks:ks_pop":462,
    "ks:ks_type":"VILLAGE",
    "name:eng_x_preferred":[
        "Patkoi"
    ],
    "wof:name":"Patkoi",
    "wof:placetype":"locality",
    "wof:population":462
},
  "geometry": {"coordinates":[85.066665,23.552307],"type":"Point"}
}