{
  "type": "Feature",
  "properties": {
    "iso:country":"IN",
    "ks:ks_name":"Pahad Falia",
    "ks:ks_pop":279,
    "ks:ks_type":"HABITATION",
    "name:eng_x_preferred":[
        "Pahad Falia"
    ],
    "wof:name":"Pahad Falia",
    "wof:placetype":"locality",
    "wof:population":279
},
  "geometry": {"coordinates":[73.30166699999999,20.953],"type":"Point"}
}