{
  "type": "Feature",
  "properties": {
    "iso:country":"IN",
    "ks:ks_name":"Juma Jn",
    "ks:ks_pop":547,
    "ks:ks_type":"HABITATION",
    "ks:ks_uagg_main":0,
    "name:eng_x_preferred":[
        "Juma Jn"
    ],
    "wof:name":"Juma Jn",
    "wof:placetype":"neighbourhood",
    "wof:population":547
},
  "geometry": {"coordinates":[76.273043,11.260889],"type":"Point"}
}