{
  "type": "Feature",
  "properties": {
    "iso:country":"IN",
    "ks:ks_name":"Adhivashiwadi",
    "ks:ks_pop":46,
    "ks:ks_type":"HABITATION",
    "name:eng_x_preferred":[
        "Adhivashiwadi"
    ],
    "wof:name":"Adhivashiwadi",
    "wof:placetype":"locality",
    "wof:population":46
},
  "geometry": {"coordinates":[73.473743,17.928913],"type":"Point"}
}