{
  "type": "Feature",
  "properties": {
    "iso:country":"IN",
    "ks:ks_name":"Shaspur",
    "ks:ks_pop":557,
    "ks:ks_type":"VILLAGE",
    "name:eng_x_preferred":[
        "Shaspur"
    ],
    "wof:name":"Shaspur",
    "wof:placetype":"locality",
    "wof:population":557
},
  "geometry": {"coordinates":[87.90101300000001,23.758509],"type":"Point"}
}