{
  "type": "Feature",
  "properties": {
    "iso:country":"IN",
    "ks:ks_alt_nam":"Jagarn\u0101thpur",
    "ks:ks_name":"Jagarnathpur",
    "ks:ks_pop":0,
    "ks:ks_type":"VILLAGE",
    "name:eng_x_preferred":[
        "Jagarnathpur"
    ],
    "name:eng_x_variant":[
        "Jagarn\u0101thpur"
    ],
    "wof:name":"Jagarnathpur",
    "wof:placetype":"locality",
    "wof:population":0
},
  "geometry": {"coordinates":[83.59144999999999,25.21498],"type":"Point"}
}