{
  "type": "Feature",
  "properties": {
    "iso:country":"IN",
    "ks:ks_name":"Dhikarwa",
    "ks:ks_pop":915,
    "ks:ks_type":"HABITATION",
    "name:eng_x_preferred":[
        "Dhikarwa"
    ],
    "wof:name":"Dhikarwa",
    "wof:placetype":"locality",
    "wof:population":915
},
  "geometry": {"coordinates":[81.05731299999999,28.155242],"type":"Point"}
}