{
  "type": "Feature",
  "properties": {
    "iso:country":"IN",
    "ks:ks_name":"Dakshin Gahabi",
    "ks:ks_pop":0,
    "ks:ks_type":"VILLAGE",
    "name:eng_x_preferred":[
        "Dakshin Gahabi"
    ],
    "wof:name":"Dakshin Gahabi",
    "wof:placetype":"locality",
    "wof:population":0
},
  "geometry": {"coordinates":[87.469471,21.753961],"type":"Point"}
}