{
  "type": "Feature",
  "properties": {
    "iso:country":"IN",
    "ks:ks_alt_nam":"JEDIGUNI",
    "ks:ks_name":"Jediguni",
    "ks:ks_pop":295,
    "ks:ks_type":"HABITATION",
    "name:eng_x_preferred":[
        "Jediguni"
    ],
    "wof:name":"Jediguni",
    "wof:placetype":"locality",
    "wof:population":295
},
  "geometry": {"coordinates":[75.283569,13.652871],"type":"Point"}
}