{
  "type": "Feature",
  "properties": {
    "gn:admin1_code":"23.0",
    "gn:admin2_code":"46.0",
    "gn:asciiname":"Lahra Dhulkot",
    "gn:country_code":"IN",
    "gn:dem":218,
    "gn:feature_class":"P",
    "gn:feature_code":"PPL",
    "gn:name":"Lahra Dh\u016blkot",
    "gn:population":0,
    "gn:timezone":"Asia/Kolkata",
    "iso:country":"IN",
    "wof:name":"Lahra Dhulkot",
    "wof:placetype":"locality"
},
  "geometry": {"coordinates":[75.20331999999998,30.25922000000001],"type":"Point"}
}