{
  "type": "Feature",
  "properties": {
    "iso:country":"IN",
    "ks:ks_name":"Purania",
    "ks:ks_pop":67,
    "ks:ks_type":"VILLAGE",
    "name:eng_x_preferred":[
        "Purania"
    ],
    "wof:name":"Purania",
    "wof:placetype":"locality",
    "wof:population":67
},
  "geometry": {"coordinates":[87.241857,24.378117],"type":"Point"}
}