{
  "type": "Feature",
  "properties": {
    "iso:country":"IN",
    "ks:ks_name":"1 STP",
    "ks:ks_pop":54,
    "ks:ks_type":"VILLAGE",
    "name:eng_x_preferred":[
        "1 STP"
    ],
    "wof:name":"1 STP",
    "wof:placetype":"locality",
    "wof:population":54
},
  "geometry": {"coordinates":[74.487521,29.918066],"type":"Point"}
}