{
  "type": "Feature",
  "properties": {
    "gn:admin1_code":"36.0",
    "gn:admin2_code":"184.0",
    "gn:asciiname":"Maldah",
    "gn:country_code":"IN",
    "gn:dem":100,
    "gn:feature_class":"P",
    "gn:feature_code":"PPL",
    "gn:name":"Maldah",
    "gn:population":0,
    "gn:timezone":"Asia/Kolkata",
    "iso:country":"IN",
    "name:ara_x_preferred":[
        "\u0645\u0627\u0644\u062f\u0647"
    ],
    "name:ben_bn_x_preferred":[
        "\u09ae\u09be\u09b2\u09a6\u09b9"
    ],
    "name:ben_in_x_preferred":[
        "\u09ae\u09be\u09b2\u09a6\u09b9"
    ],
    "name:guj_x_preferred":[
        "\u0aae\u0abe\u0ab2\u0aa6\u0abe\u0ab9"
    ],
    "name:hin_x_preferred":[
        "\u092e\u093e\u0932\u094d\u0926\u093e\u0939"
    ],
    "name:kan_x_preferred":[
        "\u0cae\u0cbe\u0cb2\u0ccd\u0ca6\u0cbe"
    ],
    "name:mal_x_preferred":[
        "\u0d2e\u0d3e\u0d7d\u0d26"
    ],
    "name:mar_x_preferred":[
        "\u092e\u093e\u0932\u0926\u093e"
    ],
    "name:pan_x_preferred":[
        "\u0a2e\u0a3e\u0a32\u0a26\u0a3e"
    ],
    "name:tam_x_preferred":[
        "\u0bae\u0bb2\u0bcd\u0b9f\u0bbe"
    ],
    "name:tel_x_preferred":[
        "\u0c2e\u0c32\u0c4d\u0c21\u0c3e"
    ],
    "name:urd_x_preferred":[
        "\u0645\u0627\u0644\u062f\u06c1"
    ],
    "wof:name":"Maldah",
    "wof:placetype":"locality"
},
  "geometry": {"coordinates":[82.57212,27.24308],"type":"Point"}
}