{
  "type": "Feature",
  "properties": {
    "iso:country":"IN",
    "ks:ks_name":"Bihate Kh",
    "ks:ks_pop":336,
    "ks:ks_type":"VILLAGE",
    "name:eng_x_preferred":[
        "Bihate Kh"
    ],
    "wof:name":"Bihate Kh",
    "wof:placetype":"locality",
    "wof:population":336
},
  "geometry": {"coordinates":[80.519075,20.76633],"type":"Point"}
}