{
  "type": "Feature",
  "properties": {
    "gn:admin1_code":"25.0",
    "gn:admin2_code":"631.0",
    "gn:asciiname":"Vadamalaippatti",
    "gn:country_code":"IN",
    "gn:dem":415,
    "gn:feature_class":"P",
    "gn:feature_code":"PPL",
    "gn:name":"Vadamalaippatti",
    "gn:population":0,
    "gn:timezone":"Asia/Kolkata",
    "iso:country":"IN",
    "wof:name":"Vadamalaippatti",
    "wof:placetype":"locality"
},
  "geometry": {"coordinates":[78.36981999999998,12.33515],"type":"Point"}
}