{
  "type": "Feature",
  "properties": {
    "iso:country":"IN",
    "ks:ks_name":"Ingalewasti",
    "ks:ks_pop":249,
    "ks:ks_type":"HABITATION",
    "name:eng_x_preferred":[
        "Ingalewasti"
    ],
    "wof:name":"Ingalewasti",
    "wof:placetype":"locality",
    "wof:population":249
},
  "geometry": {"coordinates":[74.77452599999999,18.730541],"type":"Point"}
}