{
  "type": "Feature",
  "properties": {
    "iso:country":"IN",
    "ks:ks_name":"Salupura",
    "ks:ks_pop":914,
    "ks:ks_type":"VILLAGE",
    "name:eng_x_preferred":[
        "Salupura"
    ],
    "wof:name":"Salupura",
    "wof:placetype":"locality",
    "wof:population":914
},
  "geometry": {"coordinates":[78.154016,26.138331],"type":"Point"}
}