{
  "type": "Feature",
  "properties": {
    "iso:country":"IN",
    "ks:ks_name":"Khumanpura",
    "ks:ks_pop":185,
    "ks:ks_type":"HABITATION",
    "name:eng_x_preferred":[
        "Khumanpura"
    ],
    "wof:name":"Khumanpura",
    "wof:placetype":"locality",
    "wof:population":185
},
  "geometry": {"coordinates":[72.776606,22.293148],"type":"Point"}
}