{
  "type": "Feature",
  "properties": {
    "gn:admin1_code":"39.0",
    "gn:admin2_code":"67.0",
    "gn:asciiname":"Mandaiyan Badripur",
    "gn:country_code":"IN",
    "gn:dem":235,
    "gn:feature_class":"P",
    "gn:feature_code":"PPL",
    "gn:name":"Mandaiy\u0101n Badr\u012bpur",
    "gn:population":0,
    "gn:timezone":"Asia/Kolkata",
    "iso:country":"IN",
    "wof:name":"Mandaiyan Badripur",
    "wof:placetype":"locality"
},
  "geometry": {"coordinates":[79.18713000000002,29.14533],"type":"Point"}
}