{
  "type": "Feature",
  "properties": {
    "iso:country":"IN",
    "ks:ks_name":"Jiribasa Karbi Gaon",
    "ks:ks_pop":301,
    "ks:ks_type":"HABITATION",
    "ks:ks_uagg_main":0,
    "name:eng_x_preferred":[
        "Jiribasa Karbi Gaon"
    ],
    "wof:name":"Jiribasa Karbi Gaon",
    "wof:placetype":"neighbourhood",
    "wof:population":301
},
  "geometry": {"coordinates":[92.977797,25.859462],"type":"Point"}
}