{
  "type": "Feature",
  "properties": {
    "iso:country":"IN",
    "ks:ks_name":"Bandra",
    "ks:ks_pop":18,
    "ks:ks_type":"HABITATION",
    "name:eng_x_preferred":[
        "Bandra"
    ],
    "wof:name":"Bandra",
    "wof:placetype":"locality",
    "wof:population":18
},
  "geometry": {"coordinates":[86.84199099999999,24.459595],"type":"Point"}
}