{
  "type": "Feature",
  "properties": {
    "iso:country":"IN",
    "ks:ks_name":"Meklanur",
    "ks:ks_pop":224,
    "ks:ks_type":"HABITATION",
    "name:eng_x_preferred":[
        "Meklanur"
    ],
    "wof:name":"Meklanur",
    "wof:placetype":"locality",
    "wof:population":224
},
  "geometry": {"coordinates":[77.993056,11.841339],"type":"Point"}
}