{
  "type": "Feature",
  "properties": {
    "gn:admin1_code":"34.0",
    "gn:admin2_code":"235.0",
    "gn:asciiname":"Bhatanri",
    "gn:country_code":"IN",
    "gn:dem":94,
    "gn:feature_class":"P",
    "gn:feature_code":"PPL",
    "gn:name":"Bhat\u0101nri",
    "gn:population":0,
    "gn:timezone":"Asia/Kolkata",
    "iso:country":"IN",
    "ks:ks_alt_nam":"Bhat\u0101nri",
    "ks:ks_name":"Bhatanri",
    "ks:ks_pop":467,
    "ks:ks_type":"VILLAGE",
    "name:eng_x_preferred":[
        "Bhatanri"
    ],
    "name:eng_x_variant":[
        "Bhat\u0101nri"
    ],
    "wof:name":"Bhatanri",
    "wof:placetype":"locality",
    "wof:population":467
},
  "geometry": {"coordinates":[84.50075,24.87609],"type":"Point"}
}