{
  "type": "Feature",
  "properties": {
    "iso:country":"IN",
    "ks:ks_name":"Dangsiapara 2",
    "ks:ks_pop":974,
    "ks:ks_type":"HABITATION",
    "name:eng_x_preferred":[
        "Dangsiapara 2"
    ],
    "wof:name":"Dangsiapara 2",
    "wof:placetype":"locality",
    "wof:population":974
},
  "geometry": {"coordinates":[90.66905,26.627571],"type":"Point"}
}