{
  "type": "Feature",
  "properties": {
    "iso:country":"IN",
    "ks:ks_name":"Hanseliapura",
    "ks:ks_pop":232,
    "ks:ks_type":"VILLAGE",
    "name:eng_x_preferred":[
        "Hanseliapura"
    ],
    "wof:name":"Hanseliapura",
    "wof:placetype":"locality",
    "wof:population":232
},
  "geometry": {"coordinates":[78.551987,26.423604],"type":"Point"}
}