{
  "type": "Feature",
  "properties": {
    "iso:country":"IN",
    "ks:ks_name":"Bhagwanpura",
    "ks:ks_pop":766,
    "ks:ks_type":"HABITATION",
    "name:eng_x_preferred":[
        "Bhagwanpura"
    ],
    "wof:name":"Bhagwanpura",
    "wof:placetype":"locality",
    "wof:population":766
},
  "geometry": {"coordinates":[74.270298,26.545713],"type":"Point"}
}