{
  "type": "Feature",
  "properties": {
    "iso:country":"IN",
    "ks:ks_name":"Tilaipiri",
    "ks:ks_pop":27,
    "ks:ks_type":"HABITATION",
    "name:eng_x_preferred":[
        "Tilaipiri"
    ],
    "wof:name":"Tilaipiri",
    "wof:placetype":"locality",
    "wof:population":27
},
  "geometry": {"coordinates":[85.562854,23.051713],"type":"Point"}
}