{
  "type": "Feature",
  "properties": {
    "gn:admin1_code":"34.0",
    "gn:admin2_code":"204.0",
    "gn:asciiname":"Kalyanpur Khas",
    "gn:country_code":"IN",
    "gn:dem":70,
    "gn:feature_class":"P",
    "gn:feature_code":"PPL",
    "gn:name":"Kaly\u0101npur Kh\u0101s",
    "gn:population":0,
    "gn:timezone":"Asia/Kolkata",
    "iso:country":"IN",
    "ks:ks_alt_nam":"Kaly\u0101npur Kh\u0101s",
    "ks:ks_name":"Kalyanpur Khas",
    "ks:ks_pop":1850,
    "ks:ks_type":"VILLAGE",
    "ks:ks_uagg_main":0,
    "name:eng_x_preferred":[
        "Kalyanpur Khas"
    ],
    "name:eng_x_variant":[
        "Kaly\u0101npur Kh\u0101s"
    ],
    "wof:name":"Kalyanpur Khas",
    "wof:placetype":"neighbourhood",
    "wof:population":1850
},
  "geometry": {"coordinates":[84.817069,26.526232],"type":"Point"}
}