{
  "type": "Feature",
  "properties": {
    "iso:country":"IN",
    "ks:ks_name":"Achhrapur",
    "ks:ks_pop":363,
    "ks:ks_type":"HABITATION",
    "name:eng_x_preferred":[
        "Achhrapur"
    ],
    "wof:name":"Achhrapur",
    "wof:placetype":"locality",
    "wof:population":363
},
  "geometry": {"coordinates":[79.747967,26.616331],"type":"Point"}
}