{
  "type": "Feature",
  "properties": {
    "gn:admin1_code":"30",
    "gn:admin2_code":"245.0",
    "gn:asciiname":"Pangchen",
    "gn:country_code":"IN",
    "gn:dem":3018,
    "gn:feature_class":"P",
    "gn:feature_code":"PPL",
    "gn:name":"Pangchen",
    "gn:population":0,
    "gn:timezone":"Asia/Kolkata",
    "iso:country":"IN",
    "wof:name":"Pangchen",
    "wof:placetype":"locality"
},
  "geometry": {"coordinates":[91.76667,27.68333],"type":"Point"}
}