{
  "type": "Feature",
  "properties": {
    "gn:admin1_code":"12.0",
    "gn:admin2_code":"7.0",
    "gn:asciiname":"Rapur",
    "gn:country_code":"IN",
    "gn:dem":515,
    "gn:feature_class":"P",
    "gn:feature_code":"PPL",
    "gn:name":"R\u0101pur",
    "gn:population":0,
    "gn:timezone":"Asia/Kolkata",
    "iso:country":"IN",
    "name:ceb_x_preferred":[
        "R\u0101p\u016br"
    ],
    "name:new_x_preferred":[
        "\u0930\u093e\u092a\u0942\u0930\u0941 \u092e\u0923\u094d\u0921\u0932"
    ],
    "name:swe_x_preferred":[
        "R\u0101p\u016br"
    ],
    "name:tel_x_preferred":[
        "\u0c30\u0c3e\u0c2a\u0c42\u0c30\u0c41"
    ],
    "name:urd_x_preferred":[
        "\u0631\u0627\u067e\u0648\u0631"
    ],
    "wof:name":"Rapur",
    "wof:placetype":"locality"
},
  "geometry": {"coordinates":[75.60574,32.43295999999999],"type":"Point"}
}