{
  "type": "Feature",
  "properties": {
    "iso:country":"IN",
    "ks:ks_name":"Arkhauli",
    "ks:ks_pop":8,
    "ks:ks_type":"VILLAGE",
    "name:eng_x_preferred":[
        "Arkhauli"
    ],
    "wof:name":"Arkhauli",
    "wof:placetype":"locality",
    "wof:population":8
},
  "geometry": {"coordinates":[82.980479,27.134871],"type":"Point"}
}