{
  "type": "Feature",
  "properties": {
    "gn:admin1_code":"19.0",
    "gn:admin2_code":"568.0",
    "gn:asciiname":"Asimane",
    "gn:country_code":"IN",
    "gn:dem":642,
    "gn:feature_class":"P",
    "gn:feature_code":"PPL",
    "gn:name":"Asiman\u0113",
    "gn:population":0,
    "gn:timezone":"Asia/Kolkata",
    "iso:country":"IN",
    "ks:ks_alt_nam":"ASIMANE",
    "ks:ks_name":"Asimane",
    "ks:ks_pop":65,
    "ks:ks_type":"HABITATION",
    "name:eng_x_preferred":[
        "Asimane"
    ],
    "wof:name":"Asimane",
    "wof:placetype":"locality",
    "wof:population":65
},
  "geometry": {"coordinates":[75.106307,13.554168],"type":"Point"}
}