{
  "type": "Feature",
  "properties": {
    "iso:country":"IN",
    "ks:ks_name":"Kattinamane",
    "ks:ks_pop":19,
    "ks:ks_type":"HABITATION",
    "name:eng_x_preferred":[
        "Kattinamane"
    ],
    "wof:name":"Kattinamane",
    "wof:placetype":"locality",
    "wof:population":19
},
  "geometry": {"coordinates":[75.12914499999999,13.315625],"type":"Point"}
}