{
  "type": "Feature",
  "properties": {
    "iso:country":"IN",
    "ks:ks_name":"Aralikoppa",
    "ks:ks_pop":173,
    "ks:ks_type":"HABITATION",
    "name:eng_x_preferred":[
        "Aralikoppa"
    ],
    "wof:name":"Aralikoppa",
    "wof:placetype":"locality",
    "wof:population":173
},
  "geometry": {"coordinates":[75.007651,14.128551],"type":"Point"}
}