{
  "type": "Feature",
  "properties": {
    "gn:admin1_code":"19.0",
    "gn:admin2_code":"583.0",
    "gn:asciiname":"Aravanhalli",
    "gn:country_code":"IN",
    "gn:dem":948,
    "gn:feature_class":"P",
    "gn:feature_code":"PPL",
    "gn:name":"Aravanhalli",
    "gn:population":0,
    "gn:timezone":"Asia/Kolkata",
    "iso:country":"IN",
    "ks:ks_name":"Aruvanahalli",
    "ks:ks_pop":704,
    "ks:ks_type":"VILLAGE",
    "ks:ks_uagg_main":0,
    "name:eng_x_preferred":[
        "Aruvanahalli"
    ],
    "wof:name":"Aruvanahalli",
    "wof:placetype":"neighbourhood",
    "wof:population":704
},
  "geometry": {"coordinates":[77.634452,13.302722],"type":"Point"}
}