{
  "type": "Feature",
  "properties": {
    "iso:country":"IN",
    "ks:ks_name":"Baloriya",
    "ks:ks_pop":168,
    "ks:ks_type":"VILLAGE",
    "name:eng_x_preferred":[
        "Baloriya"
    ],
    "wof:name":"Baloriya",
    "wof:placetype":"locality",
    "wof:population":168
},
  "geometry": {"coordinates":[74.690766,23.939641],"type":"Point"}
}