{
  "type": "Feature",
  "properties": {
    "iso:country":"IN",
    "ks:ks_name":"Belghati",
    "ks:ks_pop":73,
    "ks:ks_type":"VILLAGE",
    "name:eng_x_preferred":[
        "Belghati"
    ],
    "wof:name":"Belghati",
    "wof:placetype":"locality",
    "wof:population":73
},
  "geometry": {"coordinates":[83.157461,20.566875],"type":"Point"}
}