{
  "type": "Feature",
  "properties": {
    "iso:country":"IN",
    "ks:ks_name":"Jahanabad",
    "ks:ks_pop":2100,
    "ks:ks_type":"VILLAGE",
    "ks:ks_uagg_main":0,
    "name:eng_x_preferred":[
        "Jahanabad"
    ],
    "wof:name":"Jahanabad",
    "wof:placetype":"neighbourhood",
    "wof:population":2100
},
  "geometry": {"coordinates":[87.89755,21.964917],"type":"Point"}
}