{
  "type": "Feature",
  "properties": {
    "iso:country":"IN",
    "ks:ks_alt_nam":"chenchu colony",
    "ks:ks_name":"Chenchu Colony",
    "ks:ks_pop":73,
    "ks:ks_type":"HABITATION",
    "name:eng_x_preferred":[
        "Chenchu Colony"
    ],
    "wof:name":"Chenchu Colony",
    "wof:placetype":"locality",
    "wof:population":73
},
  "geometry": {"coordinates":[78.956243,15.887212],"type":"Point"}
}