{
  "type": "Feature",
  "properties": {
    "iso:country":"IN",
    "ks:ks_name":"Manjari Koppa",
    "ks:ks_pop":335,
    "ks:ks_type":"VILLAGE",
    "name:eng_x_preferred":[
        "Manjari Koppa"
    ],
    "wof:name":"Manjari Koppa",
    "wof:placetype":"locality",
    "wof:population":335
},
  "geometry": {"coordinates":[75.44522000000001,13.937317],"type":"Point"}
}