{
  "type": "Feature",
  "properties": {
    "iso:country":"IN",
    "ks:ks_alt_nam":"Hemr\u0101jpur",
    "ks:ks_name":"Hemrajpur",
    "ks:ks_pop":0,
    "ks:ks_type":"VILLAGE",
    "name:eng_x_preferred":[
        "Hemrajpur"
    ],
    "name:eng_x_variant":[
        "Hemr\u0101jpur"
    ],
    "wof:name":"Hemrajpur",
    "wof:placetype":"locality",
    "wof:population":0
},
  "geometry": {"coordinates":[83.700245,25.326353],"type":"Point"}
}