{
  "type": "Feature",
  "properties": {
    "iso:country":"IN",
    "ks:ks_alt_nam":"Ceilingjhora Pt II",
    "ks:ks_name":"Ceilingjhora Pt Ii",
    "ks:ks_pop":221,
    "ks:ks_type":"HABITATION",
    "name:eng_x_preferred":[
        "Ceilingjhora Pt Ii"
    ],
    "wof:name":"Ceilingjhora Pt Ii",
    "wof:placetype":"locality",
    "wof:population":221
},
  "geometry": {"coordinates":[90.079582,26.225499],"type":"Point"}
}