{
  "type": "Feature",
  "properties": {
    "gn:admin1_code":"37",
    "gn:admin2_code":"401.0",
    "gn:asciiname":"Lodhi",
    "gn:country_code":"IN",
    "gn:dem":453,
    "gn:feature_class":"P",
    "gn:feature_code":"PPL",
    "gn:name":"Lodhi",
    "gn:population":0,
    "gn:timezone":"Asia/Kolkata",
    "iso:country":"IN",
    "ks:ks_name":"Lodhi",
    "ks:ks_pop":1501,
    "ks:ks_type":"VILLAGE",
    "name:eng_x_preferred":[
        "Lodhi"
    ],
    "wof:name":"Lodhi",
    "wof:placetype":"locality",
    "wof:population":1501
},
  "geometry": {"coordinates":[83.061453,23.813632],"type":"Point"}
}