{
  "type": "Feature",
  "properties": {
    "iso:country":"IN",
    "ks:ks_name":"Sadrasar",
    "ks:ks_pop":720,
    "ks:ks_type":"HABITATION",
    "name:eng_x_preferred":[
        "Sadrasar"
    ],
    "wof:name":"Sadrasar",
    "wof:placetype":"locality",
    "wof:population":720
},
  "geometry": {"coordinates":[71.516756,26.692258],"type":"Point"}
}