{
  "type": "Feature",
  "properties": {
    "iso:country":"IN",
    "ks:ks_name":"Pandra Pani",
    "ks:ks_pop":140,
    "ks:ks_type":"HABITATION",
    "name:eng_x_preferred":[
        "Pandra Pani"
    ],
    "wof:name":"Pandra Pani",
    "wof:placetype":"locality",
    "wof:population":140
},
  "geometry": {"coordinates":[83.686485,23.831053],"type":"Point"}
}