{
  "type": "Feature",
  "properties": {
    "iso:country":"IN",
    "ks:ks_name":"Dandekarpada",
    "ks:ks_pop":778,
    "ks:ks_type":"HABITATION",
    "name:eng_x_preferred":[
        "Dandekarpada"
    ],
    "wof:name":"Dandekarpada",
    "wof:placetype":"locality",
    "wof:population":778
},
  "geometry": {"coordinates":[72.851935,20.054748],"type":"Point"}
}