{
  "type": "Feature",
  "properties": {
    "gn:admin1_code":"34.0",
    "gn:admin2_code":"224.0",
    "gn:asciiname":"Masdi",
    "gn:country_code":"IN",
    "gn:dem":45,
    "gn:feature_class":"P",
    "gn:feature_code":"PPL",
    "gn:name":"Masdi",
    "gn:population":0,
    "gn:timezone":"Asia/Kolkata",
    "iso:country":"IN",
    "wof:name":"Masdi",
    "wof:placetype":"locality"
},
  "geometry": {"coordinates":[86.72333,25.24411],"type":"Point"}
}