{
  "type": "Feature",
  "properties": {
    "iso:country":"IN",
    "ks:ks_alt_nam":"Ganyabogat tanda",
    "ks:ks_name":"Ganyabogat Tanda",
    "ks:ks_pop":93,
    "ks:ks_type":"HABITATION",
    "name:eng_x_preferred":[
        "Ganyabogat Tanda"
    ],
    "wof:name":"Ganyabogat Tanda",
    "wof:placetype":"locality",
    "wof:population":93
},
  "geometry": {"coordinates":[78.57213400000001,16.80612],"type":"Point"}
}