{
  "type": "Feature",
  "properties": {
    "iso:country":"IN",
    "ks:ks_alt_nam":"ugvatwadi",
    "ks:ks_name":"Ugvatwadi",
    "ks:ks_pop":92,
    "ks:ks_type":"HABITATION",
    "name:eng_x_preferred":[
        "Ugvatwadi"
    ],
    "wof:name":"Ugvatwadi",
    "wof:placetype":"locality",
    "wof:population":92
},
  "geometry": {"coordinates":[73.757222,17.043889],"type":"Point"}
}