{
  "type": "Feature",
  "properties": {
    "gn:admin1_code":"25.0",
    "gn:admin2_code":"611.0",
    "gn:asciiname":"Kaguchi",
    "gn:country_code":"IN",
    "gn:dem":1868,
    "gn:feature_class":"P",
    "gn:feature_code":"PPL",
    "gn:name":"Kaguchi",
    "gn:population":0,
    "gn:timezone":"Asia/Kolkata",
    "iso:country":"IN",
    "wof:name":"Kaguchi",
    "wof:placetype":"locality"
},
  "geometry": {"coordinates":[76.80611999999998,11.45193],"type":"Point"}
}