{
  "type": "Feature",
  "properties": {
    "iso:country":"IN",
    "ks:ks_name":"Muthiyankuli",
    "ks:ks_pop":139,
    "ks:ks_type":"HABITATION",
    "name:eng_x_preferred":[
        "Muthiyankuli"
    ],
    "wof:name":"Muthiyankuli",
    "wof:placetype":"locality",
    "wof:population":139
},
  "geometry": {"coordinates":[78.405602,11.332395],"type":"Point"}
}