{
  "type": "Feature",
  "properties": {
    "iso:country":"IN",
    "ks:ks_name":"Kallumottepaisory",
    "ks:ks_pop":63,
    "ks:ks_type":"HABITATION",
    "name:eng_x_preferred":[
        "Kallumottepaisory"
    ],
    "wof:name":"Kallumottepaisory",
    "wof:placetype":"locality",
    "wof:population":63
},
  "geometry": {"coordinates":[75.972222,12.053889],"type":"Point"}
}