{
  "type": "Feature",
  "properties": {
    "iso:country":"IN",
    "ks:ks_name":"Gavthan",
    "ks:ks_pop":275,
    "ks:ks_type":"HABITATION",
    "name:eng_x_preferred":[
        "Gavthan"
    ],
    "wof:name":"Gavthan",
    "wof:placetype":"locality",
    "wof:population":275
},
  "geometry": {"coordinates":[73.235394,18.049975],"type":"Point"}
}