{
  "type": "Feature",
  "properties": {
    "gn:admin1_code":"35.0",
    "gn:admin2_code":"429.0",
    "gn:asciiname":"Tikar Khurd",
    "gn:country_code":"IN",
    "gn:dem":379,
    "gn:feature_class":"P",
    "gn:feature_code":"PPL",
    "gn:name":"T\u012bkar Khurd",
    "gn:population":0,
    "gn:timezone":"Asia/Kolkata",
    "iso:country":"IN",
    "ks:ks_name":"Tikar Khurd",
    "ks:ks_pop":387,
    "ks:ks_type":"VILLAGE",
    "name:eng_x_preferred":[
        "Tikar Khurd"
    ],
    "wof:name":"Tikar Khurd",
    "wof:placetype":"locality",
    "wof:population":387
},
  "geometry": {"coordinates":[80.935979,24.156564],"type":"Point"}
}