{
  "type": "Feature",
  "properties": {
    "gn:admin1_code":"35",
    "gn:admin2_code":"461.0",
    "gn:asciiname":"Piparha",
    "gn:country_code":"IN",
    "gn:dem":892,
    "gn:feature_class":"P",
    "gn:feature_code":"PPL",
    "gn:name":"Piparha",
    "gn:population":0,
    "gn:timezone":"Asia/Kolkata",
    "iso:country":"IN",
    "ks:ks_name":"Piparha",
    "ks:ks_pop":359,
    "ks:ks_type":"HABITATION",
    "name:eng_x_preferred":[
        "Piparha"
    ],
    "wof:name":"Piparha",
    "wof:placetype":"locality",
    "wof:population":359
},
  "geometry": {"coordinates":[81.63896800000001,22.856826],"type":"Point"}
}