{
  "type": "Feature",
  "properties": {
    "iso:country":"IN",
    "ks:ks_name":"Chaita",
    "ks:ks_pop":3109,
    "ks:ks_type":"VILLAGE",
    "ks:ks_uagg_main":0,
    "name:eng_x_preferred":[
        "Chaita"
    ],
    "wof:name":"Chaita",
    "wof:placetype":"neighbourhood",
    "wof:population":3109
},
  "geometry": {"coordinates":[86.15746,23.846966],"type":"Point"}
}