{
  "type": "Feature",
  "properties": {
    "iso:country":"IN",
    "ks:ks_name":"Dawarikhota",
    "ks:ks_pop":90,
    "ks:ks_type":"VILLAGE",
    "name:eng_x_preferred":[
        "Dawarikhota"
    ],
    "wof:name":"Dawarikhota",
    "wof:placetype":"locality",
    "wof:population":90
},
  "geometry": {"coordinates":[89.96544,25.93989],"type":"Point"}
}