{
  "type": "Feature",
  "properties": {
    "gn:admin1_code":"38.0",
    "gn:admin2_code":"353",
    "gn:asciiname":"Amrapara",
    "gn:country_code":"IN",
    "gn:dem":82,
    "gn:feature_class":"P",
    "gn:feature_code":"PPL",
    "gn:name":"\u0100mr\u0101p\u0101ra",
    "gn:population":0,
    "gn:timezone":"Asia/Kolkata",
    "iso:country":"IN",
    "name:und_x_variant":[
        "\u0100mr\u0101p\u0101ra",
        "Amr\u0101p\u0101ra"
    ],
    "wof:name":"Amrapara",
    "wof:placetype":"neighbourhood"
},
  "geometry": {"coordinates":[87.57039,24.51891],"type":"Point"}
}