{
  "type": "Feature",
  "properties": {
    "iso:country":"IN",
    "ks:ks_name":"Murkumchhotong",
    "ks:ks_pop":362,
    "ks:ks_type":"HABITATION",
    "name:eng_x_preferred":[
        "Murkumchhotong"
    ],
    "wof:name":"Murkumchhotong",
    "wof:placetype":"locality",
    "wof:population":362
},
  "geometry": {"coordinates":[86.758539,22.743406],"type":"Point"}
}