{
  "type": "Feature",
  "properties": {
    "gn:admin1_code":"36",
    "gn:admin2_code":"144.0",
    "gn:asciiname":"Mahamai",
    "gn:country_code":"IN",
    "gn:dem":184,
    "gn:feature_class":"P",
    "gn:feature_code":"PPL",
    "gn:name":"Mah\u0101mai",
    "gn:population":0,
    "gn:timezone":"Asia/Kolkata",
    "iso:country":"IN",
    "name:bih_x_preferred":[
        "\u092e\u0939\u092e\u093e\u0907"
    ],
    "name:ceb_x_preferred":[
        "Mahamai"
    ],
    "name:hin_x_preferred":[
        "\u092e\u0939\u092e\u093e\u0907"
    ],
    "name:mai_x_preferred":[
        "\u092e\u0939\u092e\u093e\u0907"
    ],
    "name:msa_x_preferred":[
        "Mahamai"
    ],
    "name:nep_x_preferred":[
        "\u092e\u0939\u092e\u093e\u0907"
    ],
    "name:new_x_preferred":[
        "\u092e\u0939\u092e\u093e\u0908"
    ],
    "name:nld_x_preferred":[
        "Mahamai"
    ],
    "name:pol_x_preferred":[
        "Mahamai"
    ],
    "wof:name":"Mahamai",
    "wof:placetype":"neighbourhood"
},
  "geometry": {"coordinates":[78.36671,27.70735],"type":"Point"}
}