{
  "type": "Feature",
  "properties": {
    "iso:country":"IN",
    "ks:ks_name":"Memangalam",
    "ks:ks_pop":620,
    "ks:ks_type":"HABITATION",
    "name:eng_x_preferred":[
        "Memangalam"
    ],
    "wof:name":"Memangalam",
    "wof:placetype":"locality",
    "wof:population":620
},
  "geometry": {"coordinates":[76.78489399999999,8.90628],"type":"Point"}
}