{
  "type": "Feature",
  "properties": {
    "gn:admin1_code":"39",
    "gn:admin2_code":"68.0",
    "gn:asciiname":"Bungalow",
    "gn:country_code":"IN",
    "gn:dem":344,
    "gn:feature_class":"P",
    "gn:feature_code":"PPL",
    "gn:name":"Bungalow",
    "gn:population":0,
    "gn:timezone":"Asia/Kolkata",
    "iso:country":"IN",
    "wof:name":"Bungalow",
    "wof:placetype":"locality"
},
  "geometry": {"coordinates":[78.28643000000002,29.84255],"type":"Point"}
}