{
  "type": "Feature",
  "properties": {
    "gn:admin1_code":"35",
    "gn:admin2_code":"446.0",
    "gn:asciiname":"Mangrol",
    "gn:country_code":"IN",
    "gn:dem":322,
    "gn:feature_class":"P",
    "gn:feature_code":"PPL",
    "gn:name":"M\u0101ngrol",
    "gn:population":0,
    "gn:timezone":"Asia/Kolkata",
    "iso:country":"IN",
    "wof:name":"Mangrol",
    "wof:placetype":"locality"
},
  "geometry": {"coordinates":[77.97766999999997,22.92351],"type":"Point"}
}