{
  "type": "Feature",
  "properties": {
    "gn:admin1_code":"37",
    "gn:admin2_code":"406.0",
    "gn:asciiname":"Nawapara",
    "gn:country_code":"IN",
    "gn:dem":291,
    "gn:feature_class":"P",
    "gn:feature_code":"PPL",
    "gn:name":"Naw\u0101p\u0101ra",
    "gn:population":0,
    "gn:timezone":"Asia/Kolkata",
    "iso:country":"IN",
    "ks:ks_alt_nam":"NAWAPARA",
    "ks:ks_name":"Nawapara",
    "ks:ks_pop":653,
    "ks:ks_type":"HABITATION",
    "name:eng_x_preferred":[
        "Nawapara"
    ],
    "wof:name":"Nawapara",
    "wof:placetype":"locality",
    "wof:population":653
},
  "geometry": {"coordinates":[82.055611,22.170328],"type":"Point"}
}