{
  "type": "Feature",
  "properties": {
    "iso:country":"IN",
    "ks:ks_name":"28 LNP I",
    "ks:ks_pop":41,
    "ks:ks_type":"VILLAGE",
    "name:eng_x_preferred":[
        "28 LNP I"
    ],
    "wof:name":"28 LNP I",
    "wof:placetype":"locality",
    "wof:population":41
},
  "geometry": {"coordinates":[73.89041899999999,29.749214],"type":"Point"}
}