{
  "type": "Feature",
  "properties": {
    "iso:country":"IN",
    "ks:ks_name":"Harijankeri",
    "ks:ks_pop":41,
    "ks:ks_type":"HABITATION",
    "name:eng_x_preferred":[
        "Harijankeri"
    ],
    "wof:name":"Harijankeri",
    "wof:placetype":"locality",
    "wof:population":41
},
  "geometry": {"coordinates":[74.72413899999999,14.649131],"type":"Point"}
}