{
  "type": "Feature",
  "properties": {
    "iso:country":"IN",
    "ks:ks_alt_nam":"Nalisar plot",
    "ks:ks_name":"Nalisar Plot",
    "ks:ks_pop":59,
    "ks:ks_type":"HABITATION",
    "name:eng_x_preferred":[
        "Nalisar Plot"
    ],
    "wof:name":"Nalisar Plot",
    "wof:placetype":"locality",
    "wof:population":59
},
  "geometry": {"coordinates":[74.819835,14.794728],"type":"Point"}
}