{
  "type": "Feature",
  "properties": {
    "gn:admin1_code":"24.0",
    "gn:admin2_code":"124.0",
    "gn:asciiname":"Gara Morai",
    "gn:country_code":"IN",
    "gn:dem":268,
    "gn:feature_class":"P",
    "gn:feature_code":"PPL",
    "gn:name":"G\u0101ra Mor\u0101i",
    "gn:population":0,
    "gn:timezone":"Asia/Kolkata",
    "iso:country":"IN",
    "ks:ks_name":"Garamoraiya",
    "ks:ks_pop":652,
    "ks:ks_type":"VILLAGE",
    "ks:ks_uagg_main":0,
    "name:eng_x_preferred":[
        "Garamoraiya"
    ],
    "wof:name":"Garamoraiya",
    "wof:placetype":"neighbourhood",
    "wof:population":652
},
  "geometry": {"coordinates":[73.774035,23.917498],"type":"Point"}
}