{
  "type": "Feature",
  "properties": {
    "iso:country":"IN",
    "ks:ks_name":"Nayakwada",
    "ks:ks_pop":36,
    "ks:ks_type":"HABITATION",
    "name:eng_x_preferred":[
        "Nayakwada"
    ],
    "wof:name":"Nayakwada",
    "wof:placetype":"locality",
    "wof:population":36
},
  "geometry": {"coordinates":[74.27443599999999,14.820689],"type":"Point"}
}