{
  "type": "Feature",
  "properties": {
    "gn:admin1_code":"19.0",
    "gn:admin2_code":"567.0",
    "gn:asciiname":"Hanumanahalli",
    "gn:country_code":"IN",
    "gn:dem":634,
    "gn:feature_class":"P",
    "gn:feature_code":"PPL",
    "gn:name":"Hanumanahalli",
    "gn:population":0,
    "gn:timezone":"Asia/Kolkata",
    "iso:country":"IN",
    "ks:ks_name":"S Hanumanahalli",
    "ks:ks_pop":618,
    "ks:ks_type":"HABITATION",
    "name:eng_x_preferred":[
        "S Hanumanahalli"
    ],
    "name:eng_x_variant":[
        "Hanumanahalli"
    ],
    "wof:name":"S Hanumanahalli",
    "wof:placetype":"locality",
    "wof:population":618
},
  "geometry": {"coordinates":[75.75,14.27],"type":"Point"}
}