{
  "type": "Feature",
  "properties": {
    "iso:country":"IN",
    "ks:ks_name":"Mal Falia",
    "ks:ks_pop":1135,
    "ks:ks_type":"HABITATION",
    "name:eng_x_preferred":[
        "Mal Falia"
    ],
    "wof:name":"Mal Falia",
    "wof:placetype":"locality",
    "wof:population":1135
},
  "geometry": {"coordinates":[73.747017,22.7495],"type":"Point"}
}