{
  "type": "Feature",
  "properties": {
    "iso:country":"IN",
    "ks:ks_name":"Shiwpur",
    "ks:ks_pop":470,
    "ks:ks_type":"VILLAGE",
    "ks:ks_uagg_main":0,
    "name:eng_x_preferred":[
        "Shiwpur"
    ],
    "wof:name":"Shiwpur",
    "wof:placetype":"neighbourhood",
    "wof:population":470
},
  "geometry": {"coordinates":[84.235039,24.99242],"type":"Point"}
}