{
  "type": "Feature",
  "properties": {
    "gn:admin1_code":"16.0",
    "gn:admin2_code":"497",
    "gn:asciiname":"Bhanoli",
    "gn:country_code":"IN",
    "gn:dem":280,
    "gn:feature_class":"P",
    "gn:feature_code":"PPL",
    "gn:name":"Bh\u0101noli",
    "gn:population":0,
    "gn:timezone":"Asia/Kolkata",
    "iso:country":"IN",
    "ks:ks_alt_nam":"Bh\u0101noli",
    "ks:ks_name":"Bhanoli",
    "ks:ks_pop":238,
    "ks:ks_type":"VILLAGE",
    "name:eng_x_preferred":[
        "Bhanoli"
    ],
    "name:eng_x_variant":[
        "Bh\u0101noli"
    ],
    "wof:name":"Bhanoli",
    "wof:placetype":"locality",
    "wof:population":238
},
  "geometry": {"coordinates":[74.134694,21.856883],"type":"Point"}
}