{
  "type": "Feature",
  "properties": {
    "iso:country":"IN",
    "ks:ks_name":"Jamalpur",
    "ks:ks_pop":3450,
    "ks:ks_type":"VILLAGE",
    "ks:ks_uagg_main":0,
    "name:eng_x_preferred":[
        "Jamalpur"
    ],
    "wof:name":"Jamalpur",
    "wof:placetype":"neighbourhood",
    "wof:population":3450
},
  "geometry": {"coordinates":[86.927128,25.393299],"type":"Point"}
}