{
  "type": "Feature",
  "properties": {
    "iso:country":"IN",
    "ks:ks_name":"Purbi Tola (maurya Tola)",
    "ks:ks_pop":197,
    "ks:ks_type":"HABITATION",
    "name:eng_x_preferred":[
        "Purbi Tola (maurya Tola)"
    ],
    "wof:name":"Purbi Tola (maurya Tola)",
    "wof:placetype":"locality",
    "wof:population":197
},
  "geometry": {"coordinates":[83.570364,26.714588],"type":"Point"}
}