{
  "type": "Feature",
  "properties": {
    "gn:admin1_code":"23",
    "gn:admin2_code":"45.0",
    "gn:asciiname":"Panjgirain Kalan",
    "gn:country_code":"IN",
    "gn:dem":212,
    "gn:feature_class":"P",
    "gn:feature_code":"PPL",
    "gn:name":"Panjgir\u0101in Kal\u0101n",
    "gn:population":0,
    "gn:timezone":"Asia/Kolkata",
    "iso:country":"IN",
    "name:und_x_variant":[
        "Panjgrain Kalan",
        "Panjgir\u0101in",
        "Panjgir\u0101in Kal\u0101n"
    ],
    "wof:name":"Panjgirain Kalan",
    "wof:placetype":"locality"
},
  "geometry": {"coordinates":[74.91434,30.60959],"type":"Point"}
}