{
  "type": "Feature",
  "properties": {
    "gn:admin1_code":"13.0",
    "gn:admin2_code":"598.0",
    "gn:asciiname":"Vadakkumbhagara",
    "gn:country_code":"IN",
    "gn:dem":6,
    "gn:feature_class":"P",
    "gn:feature_code":"PPL",
    "gn:name":"Vadakkumbh\u0101gara",
    "gn:population":0,
    "gn:timezone":"Asia/Kolkata",
    "iso:country":"IN",
    "wof:name":"Vadakkumbhagara",
    "wof:placetype":"neighbourhood"
},
  "geometry": {"coordinates":[76.45438,9.48774],"type":"Point"}
}