{
  "type": "Feature",
  "properties": {
    "iso:country":"IN",
    "ks:ks_name":"Bhokar",
    "ks:ks_pop":55,
    "ks:ks_type":"HABITATION",
    "name:eng_x_preferred":[
        "Bhokar"
    ],
    "wof:name":"Bhokar",
    "wof:placetype":"locality",
    "wof:population":55
},
  "geometry": {"coordinates":[76.08874299999999,22.146603],"type":"Point"}
}