{
  "type": "Feature",
  "properties": {
    "iso:country":"IN",
    "ks:ks_name":"Gumanpura",
    "ks:ks_pop":759,
    "ks:ks_type":"VILLAGE",
    "ks:ks_uagg_main":0,
    "name:eng_x_preferred":[
        "Gumanpura"
    ],
    "wof:name":"Gumanpura",
    "wof:placetype":"neighbourhood",
    "wof:population":759
},
  "geometry": {"coordinates":[76.161874,26.755113],"type":"Point"}
}