{
  "type": "Feature",
  "properties": {
    "iso:country":"IN",
    "ks:ks_name":"Kattinakai",
    "ks:ks_pop":99,
    "ks:ks_type":"HABITATION",
    "name:eng_x_preferred":[
        "Kattinakai"
    ],
    "wof:name":"Kattinakai",
    "wof:placetype":"locality",
    "wof:population":99
},
  "geometry": {"coordinates":[75.024773,13.770423],"type":"Point"}
}