{
  "type": "Feature",
  "properties": {
    "iso:country":"IN",
    "ks:ks_name":"Bintola Malla",
    "ks:ks_pop":268,
    "ks:ks_type":"VILLAGE",
    "name:eng_x_preferred":[
        "Bintola Malla"
    ],
    "wof:name":"Bintola Malla",
    "wof:placetype":"locality",
    "wof:population":268
},
  "geometry": {"coordinates":[79.697693,29.6344],"type":"Point"}
}