{
  "type": "Feature",
  "properties": {
    "gn:admin1_code":"16.0",
    "gn:admin2_code":"499.0",
    "gn:asciiname":"Sarva Budrukh",
    "gn:country_code":"IN",
    "gn:dem":308,
    "gn:feature_class":"P",
    "gn:feature_code":"PPL",
    "gn:name":"S\u0101rva Budrukh",
    "gn:population":0,
    "gn:timezone":"Asia/Kolkata",
    "iso:country":"IN",
    "wof:name":"Sarva Budrukh",
    "wof:placetype":"neighbourhood"
},
  "geometry": {"coordinates":[75.14008,20.52335],"type":"Point"}
}