{
  "type": "Feature",
  "properties": {
    "gn:admin1_code":"2.0",
    "gn:admin2_code":"553.0",
    "gn:asciiname":"Erlampalle",
    "gn:country_code":"IN",
    "gn:dem":481,
    "gn:feature_class":"P",
    "gn:feature_code":"PPL",
    "gn:name":"Erlampalle",
    "gn:population":0,
    "gn:timezone":"Asia/Kolkata",
    "iso:country":"IN",
    "wof:name":"Erlampalle",
    "wof:placetype":"locality"
},
  "geometry": {"coordinates":[77.92862,14.22045],"type":"Point"}
}