{
  "type": "Feature",
  "properties": {
    "iso:country":"IN",
    "ks:ks_name":"Building Madigapalle",
    "ks:ks_pop":50,
    "ks:ks_type":"HABITATION",
    "name:eng_x_preferred":[
        "Building Madigapalle"
    ],
    "wof:name":"Building Madigapalle",
    "wof:placetype":"locality",
    "wof:population":50
},
  "geometry": {"coordinates":[78.703996,14.148935],"type":"Point"}
}