{
  "type": "Feature",
  "properties": {
    "gn:admin1_code":"35",
    "gn:admin2_code":"453.0",
    "gn:asciiname":"Baigatola",
    "gn:country_code":"IN",
    "gn:dem":767,
    "gn:feature_class":"P",
    "gn:feature_code":"PPL",
    "gn:name":"Baig\u0101tola",
    "gn:population":0,
    "gn:timezone":"Asia/Kolkata",
    "iso:country":"IN",
    "wof:name":"Baigatola",
    "wof:placetype":"locality"
},
  "geometry": {"coordinates":[81.10984999999999,22.71116],"type":"Point"}
}