{
  "type": "Feature",
  "properties": {
    "gn:admin1_code":"12.0",
    "gn:asciiname":"Handwal",
    "gn:country_code":"IN",
    "gn:dem":2063,
    "gn:feature_class":"P",
    "gn:feature_code":"PPL",
    "gn:name":"Handw\u0101l",
    "gn:population":0,
    "gn:timezone":"Asia/Kolkata",
    "iso:country":"IN",
    "wof:name":"Handwal",
    "wof:placetype":"locality"
},
  "geometry": {"coordinates":[73.88764999999999,34.40005],"type":"Point"}
}