{
  "type": "Feature",
  "properties": {
    "iso:country":"IN",
    "ks:ks_name":"Dhodiya Falia",
    "ks:ks_pop":213,
    "ks:ks_type":"HABITATION",
    "ks:ks_uagg_main":0,
    "name:eng_x_preferred":[
        "Dhodiya Falia"
    ],
    "wof:name":"Dhodiya Falia",
    "wof:placetype":"neighbourhood",
    "wof:population":213
},
  "geometry": {"coordinates":[73.21127799999999,20.808694],"type":"Point"}
}