{
  "type": "Feature",
  "properties": {
    "iso:country":"IN",
    "ks:ks_name":"Boitalupada",
    "ks:ks_pop":290,
    "ks:ks_type":"VILLAGE",
    "ks:ks_uagg_main":0,
    "name:eng_x_preferred":[
        "Boitalupada"
    ],
    "wof:name":"Boitalupada",
    "wof:placetype":"neighbourhood",
    "wof:population":290
},
  "geometry": {"coordinates":[87.17690399999999,21.963713],"type":"Point"}
}