{
  "type": "Feature",
  "properties": {
    "gn:admin1_code":"39",
    "gn:admin2_code":"57.0",
    "gn:asciiname":"Bandawadyar",
    "gn:country_code":"IN",
    "gn:dem":2889,
    "gn:feature_class":"P",
    "gn:feature_code":"PPL",
    "gn:name":"Band\u0101wady\u0101r",
    "gn:population":0,
    "gn:timezone":"Asia/Kolkata",
    "iso:country":"IN",
    "wof:name":"Bandawadyar",
    "wof:placetype":"locality"
},
  "geometry": {"coordinates":[79.2343,30.51836],"type":"Point"}
}