{
  "type": "Feature",
  "properties": {
    "iso:country":"IN",
    "ks:ks_name":"Bhursatola",
    "ks:ks_pop":4,
    "ks:ks_type":"VILLAGE",
    "name:eng_x_preferred":[
        "Bhursatola"
    ],
    "wof:name":"Bhursatola",
    "wof:placetype":"locality",
    "wof:population":4
},
  "geometry": {"coordinates":[81.0565,21.703093],"type":"Point"}
}