{
  "type": "Feature",
  "properties": {
    "iso:country":"IN",
    "ks:ks_name":"Routpara",
    "ks:ks_pop":104,
    "ks:ks_type":"HABITATION",
    "name:eng_x_preferred":[
        "Routpara"
    ],
    "wof:name":"Routpara",
    "wof:placetype":"locality",
    "wof:population":104
},
  "geometry": {"coordinates":[81.557346,19.002749],"type":"Point"}
}