{
  "type": "Feature",
  "properties": {
    "iso:country":"IN",
    "ks:ks_name":"Mora Saran",
    "ks:ks_pop":323,
    "ks:ks_type":"HABITATION",
    "name:eng_x_preferred":[
        "Mora Saran"
    ],
    "wof:name":"Mora Saran",
    "wof:placetype":"locality",
    "wof:population":323
},
  "geometry": {"coordinates":[73.641014,23.546742],"type":"Point"}
}