{
  "type": "Feature",
  "properties": {
    "gn:admin1_code":"21",
    "gn:admin2_code":"370.0",
    "gn:asciiname":"Loharanbeli",
    "gn:country_code":"IN",
    "gn:dem":326,
    "gn:feature_class":"P",
    "gn:feature_code":"PPL",
    "gn:name":"Loharanbeli",
    "gn:population":0,
    "gn:timezone":"Asia/Kolkata",
    "iso:country":"IN",
    "ks:ks_name":"Luharanbali",
    "ks:ks_pop":96,
    "ks:ks_type":"HABITATION",
    "name:eng_x_preferred":[
        "Luharanbali"
    ],
    "name:eng_x_variant":[
        "Loharanbeli"
    ],
    "wof:name":"Luharanbali",
    "wof:placetype":"locality",
    "wof:population":96
},
  "geometry": {"coordinates":[82.735462,20.736224],"type":"Point"}
}