{
  "type": "Feature",
  "properties": {
    "iso:country":"IN",
    "ks:ks_alt_nam":"MV 131",
    "ks:ks_name":"Mv 131",
    "ks:ks_pop":192,
    "ks:ks_type":"HABITATION",
    "name:eng_x_preferred":[
        "Mv 131"
    ],
    "wof:name":"Mv 131",
    "wof:placetype":"locality",
    "wof:population":192
},
  "geometry": {"coordinates":[81.53200699999999,17.861741],"type":"Point"}
}