{
  "type": "Feature",
  "properties": {
    "iso:country":"IN",
    "ks:ks_name":"Rukhmanipada",
    "ks:ks_pop":283,
    "ks:ks_type":"VILLAGE",
    "name:eng_x_preferred":[
        "Rukhmanipada"
    ],
    "wof:name":"Rukhmanipada",
    "wof:placetype":"locality",
    "wof:population":283
},
  "geometry": {"coordinates":[74.76952900000001,23.152362],"type":"Point"}
}