{
  "type": "Feature",
  "properties": {
    "iso:country":"IN",
    "ks:ks_name":"Odiyur",
    "ks:ks_pop":521,
    "ks:ks_type":"HABITATION",
    "name:eng_x_preferred":[
        "Odiyur"
    ],
    "wof:name":"Odiyur",
    "wof:placetype":"locality",
    "wof:population":521
},
  "geometry": {"coordinates":[75.02852,12.737452],"type":"Point"}
}