{
  "type": "Feature",
  "properties": {
    "iso:country":"IN",
    "ks:ks_name":"Ragimakalapalli",
    "ks:ks_type":"VILLAGE",
    "name:eng_x_preferred":[
        "Ragimakalapalli"
    ],
    "wof:name":"Ragimakalapalli",
    "wof:placetype":"locality"
},
  "geometry": {"coordinates":[78.373836,13.431844],"type":"Point"}
}