{
  "type": "Feature",
  "properties": {
    "iso:country":"IN",
    "ks:ks_name":"Bishanpur",
    "ks:ks_pop":823,
    "ks:ks_type":"HABITATION",
    "ks:ks_uagg_main":0,
    "name:eng_x_preferred":[
        "Bishanpur"
    ],
    "wof:name":"Bishanpur",
    "wof:placetype":"neighbourhood",
    "wof:population":823
},
  "geometry": {"coordinates":[84.486249,26.859328],"type":"Point"}
}