{
  "type": "Feature",
  "properties": {
    "gn:admin1_code":"36",
    "gn:admin2_code":"183.0",
    "gn:asciiname":"Pandri Kirpal",
    "gn:country_code":"IN",
    "gn:dem":115,
    "gn:feature_class":"P",
    "gn:feature_code":"PPL",
    "gn:name":"Pandri Kirp\u0101l",
    "gn:population":0,
    "gn:timezone":"Asia/Kolkata",
    "iso:country":"IN",
    "ks:ks_alt_nam":"Pandri Kirp\u0101l",
    "ks:ks_name":"Pandri Kirpal",
    "ks:ks_type":"VILLAGE",
    "ks:ks_uagg_main":0,
    "name:eng_x_preferred":[
        "Pandri Kirpal"
    ],
    "name:eng_x_variant":[
        "Pandri Kirp\u0101l"
    ],
    "wof:name":"Pandri Kirpal",
    "wof:placetype":"locality"
},
  "geometry": {"coordinates":[81.982641,27.184177],"type":"Point"}
}