{
  "type": "Feature",
  "properties": {
    "iso:country":"IN",
    "ks:ks_name":"Baralagra",
    "ks:ks_pop":1717,
    "ks:ks_type":"VILLAGE",
    "name:eng_x_preferred":[
        "Baralagra"
    ],
    "wof:name":"Baralagra",
    "wof:placetype":"locality",
    "wof:population":1717
},
  "geometry": {"coordinates":[86.016199,22.303409],"type":"Point"}
}