{
  "type": "Feature",
  "properties": {
    "iso:country":"IN",
    "ks:ks_name":"Naria Cheda",
    "ks:ks_pop":468,
    "ks:ks_type":"HABITATION",
    "ks:ks_uagg_main":0,
    "name:eng_x_preferred":[
        "Naria Cheda"
    ],
    "wof:name":"Naria Cheda",
    "wof:placetype":"neighbourhood",
    "wof:population":468
},
  "geometry": {"coordinates":[72.902472,20.579306],"type":"Point"}
}