{
  "type": "Feature",
  "properties": {
    "iso:country":"IN",
    "ks:ks_name":"Jagarnathi",
    "ks:ks_pop":190,
    "ks:ks_type":"VILLAGE",
    "name:eng_x_preferred":[
        "Jagarnathi"
    ],
    "wof:name":"Jagarnathi",
    "wof:placetype":"locality",
    "wof:population":190
},
  "geometry": {"coordinates":[86.819642,24.535727],"type":"Point"}
}