{
  "type": "Feature",
  "properties": {
    "iso:country":"IN",
    "ks:ks_name":"Mungra",
    "ks:ks_pop":81,
    "ks:ks_type":"HABITATION",
    "name:eng_x_preferred":[
        "Mungra"
    ],
    "wof:name":"Mungra",
    "wof:placetype":"locality",
    "wof:population":81
},
  "geometry": {"coordinates":[87.347336,24.923508],"type":"Point"}
}