{
  "type": "Feature",
  "properties": {
    "iso:country":"IN",
    "ks:ks_name":"Jilauni",
    "ks:ks_pop":205,
    "ks:ks_type":"VILLAGE",
    "ks:ks_uagg_main":0,
    "name:eng_x_preferred":[
        "Jilauni"
    ],
    "wof:name":"Jilauni",
    "wof:placetype":"neighbourhood",
    "wof:population":205
},
  "geometry": {"coordinates":[78.541438,24.460614],"type":"Point"}
}