{
  "type": "Feature",
  "properties": {
    "gn:admin1_code":"37.0",
    "gn:admin2_code":"417.0",
    "gn:asciiname":"Murakinar",
    "gn:country_code":"IN",
    "gn:dem":292,
    "gn:feature_class":"P",
    "gn:feature_code":"PPL",
    "gn:name":"Murak\u012bn\u0101r",
    "gn:population":0,
    "gn:timezone":"Asia/Kolkata",
    "iso:country":"IN",
    "ks:ks_name":"Murkinar",
    "ks:ks_pop":274,
    "ks:ks_type":"VILLAGE",
    "name:eng_x_preferred":[
        "Murkinar"
    ],
    "name:eng_x_variant":[
        "Murakinar"
    ],
    "wof:name":"Murkinar",
    "wof:placetype":"locality",
    "wof:population":274
},
  "geometry": {"coordinates":[80.691965,19.140557],"type":"Point"}
}