{
  "type": "Feature",
  "properties": {
    "gn:admin1_code":"36",
    "gn:admin2_code":"196.0",
    "gn:asciiname":"Khetaipur",
    "gn:country_code":"IN",
    "gn:dem":81,
    "gn:feature_class":"P",
    "gn:feature_code":"PPLL",
    "gn:name":"Khetaipur",
    "gn:population":0,
    "gn:timezone":"Asia/Kolkata",
    "iso:country":"IN",
    "ks:ks_name":"Khetaipur",
    "ks:ks_type":"VILLAGE",
    "name:eng_x_preferred":[
        "Khetaipur"
    ],
    "wof:name":"Khetaipur",
    "wof:placetype":"locality"
},
  "geometry": {"coordinates":[83.340891,25.113518],"type":"Point"}
}