{
  "type": "Feature",
  "properties": {
    "gn:admin1_code":"34.0",
    "gn:admin2_code":"224.0",
    "gn:asciiname":"Raghopur",
    "gn:country_code":"IN",
    "gn:dem":40,
    "gn:feature_class":"P",
    "gn:feature_code":"PPL",
    "gn:name":"R\u0101ghopur",
    "gn:population":0,
    "gn:timezone":"Asia/Kolkata",
    "iso:country":"IN",
    "ks:ks_alt_nam":"R\u0101ghopur",
    "ks:ks_name":"Raghopur",
    "ks:ks_pop":1420,
    "ks:ks_type":"VILLAGE",
    "ks:ks_uagg_main":0,
    "name:eng_x_preferred":[
        "Raghopur"
    ],
    "name:eng_x_variant":[
        "R\u0101ghopur"
    ],
    "wof:name":"Raghopur",
    "wof:placetype":"neighbourhood",
    "wof:population":1420
},
  "geometry": {"coordinates":[86.895095,25.256904],"type":"Point"}
}