{
  "type": "Feature",
  "properties": {
    "iso:country":"IN",
    "ks:ks_name":"Kaganoor",
    "ks:ks_pop":512,
    "ks:ks_type":"VILLAGE",
    "name:eng_x_preferred":[
        "Kaganoor"
    ],
    "wof:name":"Kaganoor",
    "wof:placetype":"locality",
    "wof:population":512
},
  "geometry": {"coordinates":[75.884655,12.846473],"type":"Point"}
}