{
  "type": "Feature",
  "properties": {
    "iso:country":"IN",
    "ks:ks_name":"Kattakana",
    "ks:ks_pop":350,
    "ks:ks_type":"HABITATION",
    "name:eng_x_preferred":[
        "Kattakana"
    ],
    "wof:name":"Kattakana",
    "wof:placetype":"locality",
    "wof:population":350
},
  "geometry": {"coordinates":[75.21999700000001,12.629108],"type":"Point"}
}