{
  "type": "Feature",
  "properties": {
    "iso:country":"IN",
    "ks:ks_name":"Salakodu",
    "ks:ks_pop":72,
    "ks:ks_type":"HABITATION",
    "name:eng_x_preferred":[
        "Salakodu"
    ],
    "wof:name":"Salakodu",
    "wof:placetype":"locality",
    "wof:population":72
},
  "geometry": {"coordinates":[74.824988,13.686925],"type":"Point"}
}