{
  "type": "Feature",
  "properties": {
    "iso:country":"IN",
    "ks:ks_alt_nam":"Moti kolivad",
    "ks:ks_name":"Moti Kolivad",
    "ks:ks_pop":869,
    "ks:ks_type":"HABITATION",
    "name:eng_x_preferred":[
        "Moti Kolivad"
    ],
    "wof:name":"Moti Kolivad",
    "wof:placetype":"locality",
    "wof:population":869
},
  "geometry": {"coordinates":[73.222611,20.815917],"type":"Point"}
}