{
  "type": "Feature",
  "properties": {
    "iso:country":"IN",
    "ks:ks_name":"Kachpura",
    "ks:ks_pop":216,
    "ks:ks_type":"HABITATION",
    "name:eng_x_preferred":[
        "Kachpura"
    ],
    "wof:name":"Kachpura",
    "wof:placetype":"locality",
    "wof:population":216
},
  "geometry": {"coordinates":[78.549819,26.963065],"type":"Point"}
}