{
  "type": "Feature",
  "properties": {
    "iso:country":"IN",
    "ks:ks_name":"Brahm Sari Bhaga Chak",
    "ks:ks_pop":240,
    "ks:ks_type":"HABITATION",
    "name:eng_x_preferred":[
        "Brahm Sari Bhaga Chak"
    ],
    "wof:name":"Brahm Sari Bhaga Chak",
    "wof:placetype":"locality",
    "wof:population":240
},
  "geometry": {"coordinates":[78.165622,30.492253],"type":"Point"}
}