{
  "type": "Feature",
  "properties": {
    "gn:admin1_code":"36.0",
    "gn:admin2_code":"183.0",
    "gn:asciiname":"Bellar Purwa",
    "gn:country_code":"IN",
    "gn:dem":100,
    "gn:feature_class":"P",
    "gn:feature_code":"PPL",
    "gn:name":"Bell\u0101r Purwa",
    "gn:population":0,
    "gn:timezone":"Asia/Kolkata",
    "iso:country":"IN",
    "wof:name":"Bellar Purwa",
    "wof:placetype":"locality"
},
  "geometry": {"coordinates":[82.46649000000002,27.02159],"type":"Point"}
}