{
  "type": "Feature",
  "properties": {
    "gn:admin1_code":"24",
    "gn:admin2_code":"106.0",
    "gn:asciiname":"Hingota",
    "gn:country_code":"IN",
    "gn:dem":200,
    "gn:feature_class":"P",
    "gn:feature_code":"PPL",
    "gn:name":"Hingota",
    "gn:population":0,
    "gn:timezone":"Asia/Kolkata",
    "iso:country":"IN",
    "wof:name":"Hingota",
    "wof:placetype":"locality"
},
  "geometry": {"coordinates":[77.5684,26.7838],"type":"Point"}
}