{
  "type": "Feature",
  "properties": {
    "iso:country":"IN",
    "ks:ks_alt_nam":"Gulist\u0101npur",
    "ks:ks_name":"Gulistanpur",
    "ks:ks_type":"VILLAGE",
    "ks:ks_uagg_main":0,
    "name:eng_x_preferred":[
        "Gulistanpur"
    ],
    "name:eng_x_variant":[
        "Gulist\u0101npur"
    ],
    "wof:name":"Gulistanpur",
    "wof:placetype":"neighbourhood"
},
  "geometry": {"coordinates":[77.51446199999999,28.510752],"type":"Point"}
}