{
  "type": "Feature",
  "properties": {
    "gn:admin1_code":"23.0",
    "gn:admin2_code":"51.0",
    "gn:asciiname":"Shampur",
    "gn:country_code":"IN",
    "gn:dem":268,
    "gn:feature_class":"P",
    "gn:feature_code":"PPL",
    "gn:name":"Sh\u0101mpur",
    "gn:population":0,
    "gn:timezone":"Asia/Kolkata",
    "iso:country":"IN",
    "ks:ks_alt_nam":"Sh\u0101mpur",
    "ks:ks_name":"Shampur",
    "ks:ks_pop":2777,
    "ks:ks_type":"VILLAGE",
    "ks:ks_uagg_main":0,
    "name:eng_x_preferred":[
        "Shampur"
    ],
    "name:eng_x_variant":[
        "Sh\u0101mpur"
    ],
    "wof:name":"Shampur",
    "wof:placetype":"locality",
    "wof:population":2777
},
  "geometry": {"coordinates":[76.51201399999999,30.961293],"type":"Point"}
}