{
  "type": "Feature",
  "properties": {
    "gn:admin1_code":"11.0",
    "gn:admin2_code":"33.0",
    "gn:asciiname":"Jalat",
    "gn:country_code":"IN",
    "gn:dem":2159,
    "gn:feature_class":"P",
    "gn:feature_code":"PPL",
    "gn:name":"J\u0101lat",
    "gn:population":0,
    "gn:timezone":"Asia/Kolkata",
    "iso:country":"IN",
    "wof:name":"Jalat",
    "wof:placetype":"locality"
},
  "geometry": {"coordinates":[77.55691,31.10469],"type":"Point"}
}