{
  "type": "Feature",
  "properties": {
    "iso:country":"IN",
    "ks:ks_alt_nam":"Baratagi LT4A",
    "ks:ks_name":"Baratagi Lt4a",
    "ks:ks_pop":150,
    "ks:ks_type":"HABITATION",
    "name:eng_x_preferred":[
        "Baratagi Lt4a"
    ],
    "wof:name":"Baratagi Lt4a",
    "wof:placetype":"locality",
    "wof:population":150
},
  "geometry": {"coordinates":[75.775452,16.893338],"type":"Point"}
}