{
  "type": "Feature",
  "properties": {
    "iso:country":"IN",
    "ks:ks_name":"Gountiapara",
    "ks:ks_pop":40,
    "ks:ks_type":"HABITATION",
    "name:eng_x_preferred":[
        "Gountiapara"
    ],
    "wof:name":"Gountiapara",
    "wof:placetype":"locality",
    "wof:population":40
},
  "geometry": {"coordinates":[83.832435,22.282355],"type":"Point"}
}