{
  "type": "Feature",
  "properties": {
    "iso:country":"IN",
    "ks:ks_name":"Dhamailgachh",
    "ks:ks_pop":0,
    "ks:ks_type":"VILLAGE",
    "name:eng_x_preferred":[
        "Dhamailgachh"
    ],
    "wof:name":"Dhamailgachh",
    "wof:placetype":"locality",
    "wof:population":0
},
  "geometry": {"coordinates":[89.43125000000001,26.049995],"type":"Point"}
}