{
  "type": "Feature",
  "properties": {
    "iso:country":"IN",
    "ks:ks_name":"Khar Kopar",
    "ks:ks_pop":775,
    "ks:ks_type":"VILLAGE",
    "ks:ks_uagg_main":0,
    "name:eng_x_preferred":[
        "Khar Kopar"
    ],
    "wof:name":"Khar Kopar",
    "wof:placetype":"neighbourhood",
    "wof:population":775
},
  "geometry": {"coordinates":[73.013383,18.962081],"type":"Point"}
}