{
  "type": "Feature",
  "properties": {
    "iso:country":"IN",
    "ks:ks_name":"Pratappur",
    "ks:ks_pop":93,
    "ks:ks_type":"HABITATION",
    "name:eng_x_preferred":[
        "Pratappur"
    ],
    "wof:name":"Pratappur",
    "wof:placetype":"locality",
    "wof:population":93
},
  "geometry": {"coordinates":[86.77659300000001,22.372619],"type":"Point"}
}