{
  "type": "Feature",
  "properties": {
    "gn:admin1_code":"25.0",
    "gn:admin2_code":"631.0",
    "gn:asciiname":"Chilpilmangalam",
    "gn:country_code":"IN",
    "gn:dem":906,
    "gn:feature_class":"P",
    "gn:feature_code":"PPL",
    "gn:name":"Chilpilmangalam",
    "gn:population":0,
    "gn:timezone":"Asia/Kolkata",
    "iso:country":"IN",
    "wof:name":"Chilpilmangalam",
    "wof:placetype":"neighbourhood"
},
  "geometry": {"coordinates":[77.7077,12.57664],"type":"Point"}
}