{
  "type": "Feature",
  "properties": {
    "iso:country":"IN",
    "ks:ks_name":"Barbheti",
    "ks:ks_pop":2833,
    "ks:ks_type":"VILLAGE",
    "name:eng_x_preferred":[
        "Barbheti"
    ],
    "wof:name":"Barbheti",
    "wof:placetype":"locality",
    "wof:population":2833
},
  "geometry": {"coordinates":[92.656103,26.342423],"type":"Point"}
}