{
  "type": "Feature",
  "properties": {
    "iso:country":"IN",
    "ks:ks_name":"Katakarwadi",
    "ks:ks_pop":51,
    "ks:ks_type":"HABITATION",
    "name:eng_x_preferred":[
        "Katakarwadi"
    ],
    "wof:name":"Katakarwadi",
    "wof:placetype":"locality",
    "wof:population":51
},
  "geometry": {"coordinates":[73.316767,17.847339],"type":"Point"}
}