{
  "type": "Feature",
  "properties": {
    "iso:country":"IN",
    "ks:ks_name":"Patrapada",
    "ks:ks_pop":55,
    "ks:ks_type":"HABITATION",
    "name:eng_x_preferred":[
        "Patrapada"
    ],
    "wof:name":"Patrapada",
    "wof:placetype":"locality",
    "wof:population":55
},
  "geometry": {"coordinates":[83.480233,19.979601],"type":"Point"}
}