{
  "type": "Feature",
  "properties": {
    "iso:country":"IN",
    "ks:ks_name":"Nuagaon",
    "ks:ks_pop":274,
    "ks:ks_type":"HABITATION",
    "name:eng_x_preferred":[
        "Nuagaon"
    ],
    "wof:name":"Nuagaon",
    "wof:placetype":"locality",
    "wof:population":274
},
  "geometry": {"coordinates":[83.842207,19.531649],"type":"Point"}
}