{
  "type": "Feature",
  "properties": {
    "gn:admin1_code":"16.0",
    "gn:admin2_code":"530.0",
    "gn:asciiname":"Mangaon",
    "gn:country_code":"IN",
    "gn:dem":562,
    "gn:feature_class":"P",
    "gn:feature_code":"PPL",
    "gn:name":"M\u0101ngaon",
    "gn:population":0,
    "gn:timezone":"Asia/Kolkata",
    "iso:country":"IN",
    "name:ceb_x_preferred":[
        "M\u0101ngaon"
    ],
    "name:jpn_x_preferred":[
        "\u30de\u30fc\u30f3\u30ac\u30fc\u30aa\u30f3"
    ],
    "name:mar_x_preferred":[
        "\u092e\u093e\u0923\u0917\u093e\u0935"
    ],
    "name:swe_x_preferred":[
        "M\u0101ngaon"
    ],
    "wof:name":"Mangaon",
    "wof:placetype":"locality"
},
  "geometry": {"coordinates":[74.3693,16.70482],"type":"Point"}
}