{
  "type": "Feature",
  "properties": {
    "iso:country":"IN",
    "ks:ks_name":"Bhatkhera Naya",
    "ks:ks_pop":213,
    "ks:ks_type":"HABITATION",
    "name:eng_x_preferred":[
        "Bhatkhera Naya"
    ],
    "wof:name":"Bhatkhera Naya",
    "wof:placetype":"locality",
    "wof:population":213
},
  "geometry": {"coordinates":[75.064678,24.909797],"type":"Point"}
}