{
  "type": "Feature",
  "properties": {
    "iso:country":"IN",
    "ks:ks_name":"Belortal",
    "ks:ks_pop":26,
    "ks:ks_type":"HABITATION",
    "name:eng_x_preferred":[
        "Belortal"
    ],
    "wof:name":"Belortal",
    "wof:placetype":"locality",
    "wof:population":26
},
  "geometry": {"coordinates":[91.482981,26.177669],"type":"Point"}
}