{
  "type": "Feature",
  "properties": {
    "gn:admin1_code":"11",
    "gn:admin2_code":"23.0",
    "gn:asciiname":"Pindru",
    "gn:country_code":"IN",
    "gn:dem":2349,
    "gn:feature_class":"P",
    "gn:feature_code":"PPL",
    "gn:name":"Pindru",
    "gn:population":0,
    "gn:timezone":"Asia/Kolkata",
    "iso:country":"IN",
    "wof:name":"Pindru",
    "wof:placetype":"locality"
},
  "geometry": {"coordinates":[76.43541999999999,33.02506],"type":"Point"}
}