{
  "type": "Feature",
  "properties": {
    "iso:country":"IN",
    "ks:ks_name":"Anarivadakkekkara",
    "ks:ks_pop":1267,
    "ks:ks_type":"HABITATION",
    "name:eng_x_preferred":[
        "Anarivadakkekkara"
    ],
    "wof:name":"Anarivadakkekkara",
    "wof:placetype":"locality",
    "wof:population":1267
},
  "geometry": {"coordinates":[76.45483,9.333552],"type":"Point"}
}