{
  "type": "Feature",
  "properties": {
    "iso:country":"IN",
    "ks:ks_name":"Melenauplekoppa",
    "ks:ks_pop":240,
    "ks:ks_type":"HABITATION",
    "name:eng_x_preferred":[
        "Melenauplekoppa"
    ],
    "wof:name":"Melenauplekoppa",
    "wof:placetype":"locality",
    "wof:population":240
},
  "geometry": {"coordinates":[74.900477,14.566246],"type":"Point"}
}