{
  "type": "Feature",
  "properties": {
    "iso:country":"IN",
    "ks:ks_name":"Mugudewadi",
    "ks:ks_pop":320,
    "ks:ks_type":"HABITATION",
    "name:eng_x_preferred":[
        "Mugudewadi"
    ],
    "wof:name":"Mugudewadi",
    "wof:placetype":"locality",
    "wof:population":320
},
  "geometry": {"coordinates":[73.95755800000001,16.738811],"type":"Point"}
}