{
  "type": "Feature",
  "properties": {
    "iso:country":"IN",
    "ks:ks_name":"Mudalapalya",
    "ks:ks_pop":42,
    "ks:ks_type":"HABITATION",
    "name:eng_x_preferred":[
        "Mudalapalya"
    ],
    "wof:name":"Mudalapalya",
    "wof:placetype":"locality",
    "wof:population":42
},
  "geometry": {"coordinates":[77.068292,13.082689],"type":"Point"}
}