{
  "type": "Feature",
  "properties": {
    "gn:admin1_code":"39.0",
    "gn:admin2_code":"64.0",
    "gn:asciiname":"Jamni",
    "gn:country_code":"IN",
    "gn:dem":989,
    "gn:feature_class":"P",
    "gn:feature_code":"PPL",
    "gn:name":"J\u0101mni",
    "gn:population":0,
    "gn:timezone":"Asia/Kolkata",
    "iso:country":"IN",
    "ks:ks_alt_nam":"J\u0101mni",
    "ks:ks_name":"Jamni",
    "ks:ks_type":"VILLAGE",
    "name:eng_x_preferred":[
        "Jamni"
    ],
    "name:eng_x_variant":[
        "J\u0101mni"
    ],
    "wof:name":"Jamni",
    "wof:placetype":"locality"
},
  "geometry": {"coordinates":[79.113843,29.669152],"type":"Point"}
}