{
  "type": "Feature",
  "properties": {
    "iso:country":"IN",
    "ks:ks_name":"Waghadewadi",
    "ks:ks_pop":100,
    "ks:ks_type":"HABITATION",
    "name:eng_x_preferred":[
        "Waghadewadi"
    ],
    "wof:name":"Waghadewadi",
    "wof:placetype":"locality",
    "wof:population":100
},
  "geometry": {"coordinates":[73.359352,17.196132],"type":"Point"}
}