{
  "type": "Feature",
  "properties": {
    "iso:country":"IN",
    "ks:ks_alt_nam":"KARALMALA",
    "ks:ks_name":"Karalmala",
    "ks:ks_pop":121,
    "ks:ks_type":"HABITATION",
    "name:eng_x_preferred":[
        "Karalmala"
    ],
    "wof:name":"Karalmala",
    "wof:placetype":"locality",
    "wof:population":121
},
  "geometry": {"coordinates":[74.957509,17.422051],"type":"Point"}
}