{
  "type": "Feature",
  "properties": {
    "iso:country":"IN",
    "ks:ks_name":"Barkheda Moji",
    "ks:ks_pop":325,
    "ks:ks_type":"HABITATION",
    "name:eng_x_preferred":[
        "Barkheda Moji"
    ],
    "wof:name":"Barkheda Moji",
    "wof:placetype":"locality",
    "wof:population":325
},
  "geometry": {"coordinates":[77.453045,23.638264],"type":"Point"}
}