{
  "type": "Feature",
  "properties": {
    "iso:country":"IN",
    "ks:ks_name":"Amalguda",
    "ks:ks_pop":95,
    "ks:ks_type":"HABITATION",
    "name:eng_x_preferred":[
        "Amalguda"
    ],
    "wof:name":"Amalguda",
    "wof:placetype":"locality",
    "wof:population":95
},
  "geometry": {"coordinates":[82.778138,18.244073],"type":"Point"}
}