{
  "type": "Feature",
  "properties": {
    "iso:country":"IN",
    "ks:ks_alt_nam":"kote kanora",
    "ks:ks_name":"Kote Kanora",
    "ks:ks_pop":156,
    "ks:ks_type":"HABITATION",
    "name:eng_x_preferred":[
        "Kote Kanora"
    ],
    "wof:name":"Kote Kanora",
    "wof:placetype":"locality",
    "wof:population":156
},
  "geometry": {"coordinates":[79.902665,29.738204],"type":"Point"}
}