{
  "type": "Feature",
  "properties": {
    "iso:country":"IN",
    "ks:ks_name":"Satral",
    "ks:ks_pop":527,
    "ks:ks_type":"VILLAGE",
    "name:eng_x_preferred":[
        "Satral"
    ],
    "wof:name":"Satral",
    "wof:placetype":"locality",
    "wof:population":527
},
  "geometry": {"coordinates":[73.69384100000001,16.243242],"type":"Point"}
}