{
  "type": "Feature",
  "properties": {
    "gn:admin1_code":"36",
    "gn:admin2_code":"201.0",
    "gn:asciiname":"Jisukhpur Sani",
    "gn:country_code":"IN",
    "gn:dem":169,
    "gn:feature_class":"P",
    "gn:feature_code":"PPL",
    "gn:name":"J\u012bsukhpur S\u0101ni",
    "gn:population":0,
    "gn:timezone":"Asia/Kolkata",
    "iso:country":"IN",
    "name:und_x_variant":[
        "J\u012bsukhpur S\u0101ni",
        "Nagla Bari"
    ],
    "wof:name":"Jisukhpur Sani",
    "wof:placetype":"locality"
},
  "geometry": {"coordinates":[78.68571,27.40207],"type":"Point"}
}