{
  "type": "Feature",
  "properties": {
    "iso:country":"IN",
    "ks:ks_alt_nam":"MURAWAN PURWA",
    "ks:ks_name":"Murawan Purwa",
    "ks:ks_pop":233,
    "ks:ks_type":"HABITATION",
    "ks:ks_uagg_main":0,
    "name:eng_x_preferred":[
        "Murawan Purwa"
    ],
    "wof:name":"Murawan Purwa",
    "wof:placetype":"neighbourhood",
    "wof:population":233
},
  "geometry": {"coordinates":[81.58207,27.479415],"type":"Point"}
}