{
  "type": "Feature",
  "properties": {
    "gn:admin1_code":"16",
    "gn:admin2_code":"501.0",
    "gn:asciiname":"Ramgaon",
    "gn:country_code":"IN",
    "gn:dem":272,
    "gn:feature_class":"P",
    "gn:feature_code":"PPL",
    "gn:name":"R\u0101mgaon",
    "gn:population":0,
    "gn:timezone":"Asia/Kolkata",
    "iso:country":"IN",
    "wof:name":"Ramgaon",
    "wof:placetype":"locality"
},
  "geometry": {"coordinates":[77.20771999999999,20.81096],"type":"Point"}
}