{
  "type": "Feature",
  "properties": {
    "gn:admin1_code":"39.0",
    "gn:admin2_code":"061",
    "gn:asciiname":"Ukhriyalgaon",
    "gn:country_code":"IN",
    "gn:dem":1362,
    "gn:feature_class":"P",
    "gn:feature_code":"PPL",
    "gn:name":"Ukhriy\u0101lgaon",
    "gn:population":0,
    "gn:timezone":"Asia/Kolkata",
    "iso:country":"IN",
    "wof:name":"Ukhriyalgaon",
    "wof:placetype":"locality"
},
  "geometry": {"coordinates":[78.58032,29.86245],"type":"Point"}
}