{
  "type": "Feature",
  "properties": {
    "iso:country":"IN",
    "ks:ks_name":"Sukuduputtu",
    "ks:ks_pop":85,
    "ks:ks_type":"HABITATION",
    "name:eng_x_preferred":[
        "Sukuduputtu"
    ],
    "wof:name":"Sukuduputtu",
    "wof:placetype":"locality",
    "wof:population":85
},
  "geometry": {"coordinates":[82.915702,18.048772],"type":"Point"}
}