{
  "type": "Feature",
  "properties": {
    "gn:admin1_code":"24.0",
    "gn:admin2_code":"102",
    "gn:asciiname":"Khariya",
    "gn:country_code":"IN",
    "gn:dem":310,
    "gn:feature_class":"P",
    "gn:feature_code":"PPL",
    "gn:name":"Kh\u0101riya",
    "gn:population":0,
    "gn:timezone":"Asia/Kolkata",
    "iso:country":"IN",
    "name:bpy_x_preferred":[
        "\u0996\u09be\u09b0\u09bf\u09af\u09bc\u09be"
    ],
    "name:ita_x_preferred":[
        "Khariya"
    ],
    "name:msa_x_preferred":[
        "Khariya"
    ],
    "name:new_x_preferred":[
        "\u0916\u0930\u093f\u092f\u093e"
    ],
    "name:nld_x_preferred":[
        "Khariya"
    ],
    "name:pol_x_preferred":[
        "Khariya"
    ],
    "name:por_x_preferred":[
        "Khariya"
    ],
    "name:und_x_variant":[
        "Kh\u0101riya",
        "Khario"
    ],
    "name:urd_x_preferred":[
        "\u06a9\u06be\u06cc\u0631\u06cc\u0627"
    ],
    "name:vie_x_preferred":[
        "Khariya"
    ],
    "name:zho_x_preferred":[
        "\u5361\u91cc\u8036"
    ],
    "wof:name":"Khariya",
    "wof:placetype":"locality"
},
  "geometry": {"coordinates":[74.72704,28.13064],"type":"Point"}
}