{
  "type": "Feature",
  "properties": {
    "iso:country":"IN",
    "ks:ks_name":"Hasanpur",
    "ks:ks_type":"VILLAGE",
    "name:eng_x_preferred":[
        "Hasanpur"
    ],
    "wof:name":"Hasanpur",
    "wof:placetype":"locality"
},
  "geometry": {"coordinates":[82.96157700000001,25.666599],"type":"Point"}
}