{
  "type": "Feature",
  "properties": {
    "iso:country":"IN",
    "ks:ks_name":"Punchappadam Rd End",
    "ks:ks_pop":534,
    "ks:ks_type":"HABITATION",
    "name:eng_x_preferred":[
        "Punchappadam Rd End"
    ],
    "wof:name":"Punchappadam Rd End",
    "wof:placetype":"locality",
    "wof:population":534
},
  "geometry": {"coordinates":[76.184113,10.371089],"type":"Point"}
}