{
  "type": "Feature",
  "properties": {
    "gn:admin1_code":"2.0",
    "gn:admin2_code":"546.0",
    "gn:asciiname":"Ammapalem",
    "gn:country_code":"IN",
    "gn:dem":76,
    "gn:feature_class":"P",
    "gn:feature_code":"PPL",
    "gn:name":"Ammap\u0101lem",
    "gn:population":0,
    "gn:timezone":"Asia/Kolkata",
    "iso:country":"IN",
    "name:fas_x_preferred":[
        "\u0627\u0645\u0627\u067e\u0627\u0644\u0645"
    ],
    "wof:name":"Ammapalem",
    "wof:placetype":"locality"
},
  "geometry": {"coordinates":[81.26801,17.05101],"type":"Point"}
}