{
  "type": "Feature",
  "properties": {
    "iso:country":"IN",
    "ks:ks_alt_nam":"Bazar Chuk pt 2",
    "ks:ks_name":"Bazar Chuk Pt 2",
    "ks:ks_pop":140,
    "ks:ks_type":"HABITATION",
    "name:eng_x_preferred":[
        "Bazar Chuk Pt 2"
    ],
    "wof:name":"Bazar Chuk Pt 2",
    "wof:placetype":"locality",
    "wof:population":140
},
  "geometry": {"coordinates":[95.21740699999999,27.152628],"type":"Point"}
}