{
  "type": "Feature",
  "properties": {
    "iso:country":"IN",
    "ks:ks_name":"Borwadi",
    "ks:ks_pop":306,
    "ks:ks_type":"HABITATION",
    "name:eng_x_preferred":[
        "Borwadi"
    ],
    "wof:name":"Borwadi",
    "wof:placetype":"locality",
    "wof:population":306
},
  "geometry": {"coordinates":[73.443403,19.020589],"type":"Point"}
}