{
  "type": "Feature",
  "properties": {
    "iso:country":"IN",
    "ks:ks_name":"Ghata Fali",
    "ks:ks_pop":70,
    "ks:ks_type":"HABITATION",
    "name:eng_x_preferred":[
        "Ghata Fali"
    ],
    "wof:name":"Ghata Fali",
    "wof:placetype":"locality",
    "wof:population":70
},
  "geometry": {"coordinates":[72.95265000000001,24.497444],"type":"Point"}
}