{
  "type": "Feature",
  "properties": {
    "iso:country":"IN",
    "ks:ks_name":"Premaguda",
    "ks:ks_pop":162,
    "ks:ks_type":"HABITATION",
    "name:eng_x_preferred":[
        "Premaguda"
    ],
    "wof:name":"Premaguda",
    "wof:placetype":"locality",
    "wof:population":162
},
  "geometry": {"coordinates":[81.93244,18.627406],"type":"Point"}
}