{
  "type": "Feature",
  "properties": {
    "iso:country":"IN",
    "ks:ks_name":"Lakhanpura",
    "ks:ks_pop":0,
    "ks:ks_type":"VILLAGE",
    "name:eng_x_preferred":[
        "Lakhanpura"
    ],
    "wof:name":"Lakhanpura",
    "wof:placetype":"locality",
    "wof:population":0
},
  "geometry": {"coordinates":[81.04720500000001,23.276509],"type":"Point"}
}