{
  "type": "Feature",
  "properties": {
    "iso:country":"IN",
    "ks:ks_name":"Tazpur Handi",
    "ks:ks_pop":705,
    "ks:ks_type":"VILLAGE",
    "name:eng_x_preferred":[
        "Tazpur Handi"
    ],
    "wof:name":"Tazpur Handi",
    "wof:placetype":"locality",
    "wof:population":705
},
  "geometry": {"coordinates":[85.63003399999999,25.677964],"type":"Point"}
}