{
  "type": "Feature",
  "properties": {
    "iso:country":"IN",
    "ks:ks_name":"Naliapur",
    "ks:ks_pop":1425,
    "ks:ks_type":"VILLAGE",
    "ks:ks_uagg_main":0,
    "name:eng_x_preferred":[
        "Naliapur"
    ],
    "wof:name":"Naliapur",
    "wof:placetype":"neighbourhood",
    "wof:population":1425
},
  "geometry": {"coordinates":[88.153156,23.706411],"type":"Point"}
}