{
  "type": "Feature",
  "properties": {
    "iso:country":"IN",
    "ks:ks_name":"Paikapada",
    "ks:ks_pop":903,
    "ks:ks_type":"VILLAGE",
    "name:eng_x_preferred":[
        "Paikapada"
    ],
    "wof:name":"Paikapada",
    "wof:placetype":"locality",
    "wof:population":903
},
  "geometry": {"coordinates":[84.920368,19.317547],"type":"Point"}
}