{
  "type": "Feature",
  "properties": {
    "iso:country":"IN",
    "ks:ks_name":"Mangrahiya",
    "ks:ks_pop":415,
    "ks:ks_type":"HABITATION",
    "ks:ks_uagg_main":0,
    "name:eng_x_preferred":[
        "Mangrahiya"
    ],
    "wof:name":"Mangrahiya",
    "wof:placetype":"neighbourhood",
    "wof:population":415
},
  "geometry": {"coordinates":[84.2953,24.95356],"type":"Point"}
}