{
  "type": "Feature",
  "properties": {
    "gn:admin1_code":"34.0",
    "gn:admin2_code":"237.0",
    "gn:asciiname":"Muhiudinpur",
    "gn:country_code":"IN",
    "gn:dem":94,
    "gn:feature_class":"P",
    "gn:feature_code":"PPL",
    "gn:name":"Muh\u012bud\u012bnpur",
    "gn:population":0,
    "gn:timezone":"Asia/Kolkata",
    "iso:country":"IN",
    "ks:ks_name":"Mohiuddinpur",
    "ks:ks_pop":1085,
    "ks:ks_type":"VILLAGE",
    "name:eng_x_preferred":[
        "Mohiuddinpur"
    ],
    "name:eng_x_variant":[
        "Muhiudinpur"
    ],
    "wof:name":"Mohiuddinpur",
    "wof:placetype":"locality",
    "wof:population":1085
},
  "geometry": {"coordinates":[85.567244,24.859217],"type":"Point"}
}