{
  "type": "Feature",
  "properties": {
    "iso:country":"IN",
    "ks:ks_name":"Karar",
    "ks:ks_pop":572,
    "ks:ks_type":"VILLAGE",
    "name:eng_x_preferred":[
        "Karar"
    ],
    "wof:name":"Karar",
    "wof:placetype":"locality",
    "wof:population":572
},
  "geometry": {"coordinates":[86.94526999999999,24.815277],"type":"Point"}
}