{
  "type": "Feature",
  "properties": {
    "iso:country":"IN",
    "ks:ks_name":"Kanthaldanga",
    "ks:ks_pop":800,
    "ks:ks_type":"HABITATION",
    "name:eng_x_preferred":[
        "Kanthaldanga"
    ],
    "wof:name":"Kanthaldanga",
    "wof:placetype":"locality",
    "wof:population":800
},
  "geometry": {"coordinates":[87.757819,23.463894],"type":"Point"}
}