{
  "type": "Feature",
  "properties": {
    "iso:country":"IN",
    "ks:ks_alt_nam":"S\u0101ke",
    "ks:ks_name":"Sake",
    "ks:ks_pop":556,
    "ks:ks_type":"VILLAGE",
    "name:eng_x_preferred":[
        "Sake"
    ],
    "name:eng_x_variant":[
        "S\u0101ke"
    ],
    "wof:name":"Sake",
    "wof:placetype":"locality",
    "wof:population":556
},
  "geometry": {"coordinates":[85.48869999999999,22.818076],"type":"Point"}
}