{
  "type": "Feature",
  "properties": {
    "iso:country":"IN",
    "ks:ks_name":"Raghunhathpur",
    "ks:ks_pop":518,
    "ks:ks_type":"HABITATION",
    "name:eng_x_preferred":[
        "Raghunhathpur"
    ],
    "wof:name":"Raghunhathpur",
    "wof:placetype":"locality",
    "wof:population":518
},
  "geometry": {"coordinates":[80.047635,26.298352],"type":"Point"}
}