{
  "type": "Feature",
  "properties": {
    "gn:admin1_code":"36",
    "gn:admin2_code":"200.0",
    "gn:asciiname":"Parrahwa",
    "gn:country_code":"IN",
    "gn:dem":310,
    "gn:feature_class":"P",
    "gn:feature_code":"PPL",
    "gn:name":"Parrahwa",
    "gn:population":0,
    "gn:timezone":"Asia/Kolkata",
    "iso:country":"IN",
    "wof:name":"Parrahwa",
    "wof:placetype":"locality"
},
  "geometry": {"coordinates":[82.97543,24.21511],"type":"Point"}
}