{
  "type": "Feature",
  "properties": {
    "iso:country":"IN",
    "ks:ks_name":"Badra",
    "ks:ks_pop":753,
    "ks:ks_type":"VILLAGE",
    "name:eng_x_preferred":[
        "Badra"
    ],
    "wof:name":"Badra",
    "wof:placetype":"locality",
    "wof:population":753
},
  "geometry": {"coordinates":[81.684128,19.700346],"type":"Point"}
}