{
  "type": "Feature",
  "properties": {
    "iso:country":"IN",
    "ks:ks_name":"Marakur",
    "ks:ks_pop":164,
    "ks:ks_type":"HABITATION",
    "name:eng_x_preferred":[
        "Marakur"
    ],
    "wof:name":"Marakur",
    "wof:placetype":"locality",
    "wof:population":164
},
  "geometry": {"coordinates":[75.238236,12.772921],"type":"Point"}
}