{
  "type": "Feature",
  "properties": {
    "gn:admin1_code":"11.0",
    "gn:admin2_code":"33.0",
    "gn:asciiname":"Tarponu",
    "gn:country_code":"IN",
    "gn:dem":2048,
    "gn:feature_class":"P",
    "gn:feature_code":"PPL",
    "gn:name":"Tarponu",
    "gn:population":0,
    "gn:timezone":"Asia/Kolkata",
    "iso:country":"IN",
    "wof:name":"Tarponu",
    "wof:placetype":"locality"
},
  "geometry": {"coordinates":[77.47649,31.05689000000001],"type":"Point"}
}