{
  "type": "Feature",
  "properties": {
    "iso:country":"IN",
    "ks:ks_name":"Ramachandrapuram",
    "ks:ks_pop":597,
    "ks:ks_type":"HABITATION",
    "ks:ks_uagg_main":0,
    "name:eng_x_preferred":[
        "Ramachandrapuram"
    ],
    "wof:name":"Ramachandrapuram",
    "wof:placetype":"neighbourhood",
    "wof:population":597
},
  "geometry": {"coordinates":[81.625187,16.931951],"type":"Point"}
}