{
  "type": "Feature",
  "properties": {
    "iso:country":"IN",
    "ks:ks_alt_nam":"Diphu Tokbi gaon",
    "ks:ks_name":"Diphu Tokbi Gaon",
    "ks:ks_pop":135,
    "ks:ks_type":"HABITATION",
    "ks:ks_uagg_main":0,
    "name:eng_x_preferred":[
        "Diphu Tokbi Gaon"
    ],
    "wof:name":"Diphu Tokbi Gaon",
    "wof:placetype":"neighbourhood",
    "wof:population":135
},
  "geometry": {"coordinates":[93.13246100000001,26.122095],"type":"Point"}
}