{
  "type": "Feature",
  "properties": {
    "iso:country":"IN",
    "ks:ks_alt_nam":"paloramukku",
    "ks:ks_name":"Paloramukku",
    "ks:ks_pop":600,
    "ks:ks_type":"HABITATION",
    "name:eng_x_preferred":[
        "Paloramukku"
    ],
    "wof:name":"Paloramukku",
    "wof:placetype":"locality",
    "wof:population":600
},
  "geometry": {"coordinates":[75.643152,11.566612],"type":"Point"}
}