{
  "type": "Feature",
  "properties": {
    "gn:admin1_code":"36",
    "gn:admin2_code":"198.0",
    "gn:asciiname":"Umri",
    "gn:country_code":"IN",
    "gn:dem":91,
    "gn:feature_class":"P",
    "gn:feature_code":"PPL",
    "gn:name":"Umri",
    "gn:population":0,
    "gn:timezone":"Asia/Kolkata",
    "iso:country":"IN",
    "name:ceb_x_preferred":[
        "Umri"
    ],
    "name:pol_x_preferred":[
        "Umri"
    ],
    "name:swe_x_preferred":[
        "Umri"
    ],
    "wof:name":"Umri",
    "wof:placetype":"neighbourhood"
},
  "geometry": {"coordinates":[82.55410999999999,25.45454],"type":"Point"}
}