{
  "type": "Feature",
  "properties": {
    "iso:country":"IN",
    "ks:ks_alt_nam":"H\u012br\u0101pur",
    "ks:ks_name":"Hirapur",
    "ks:ks_type":"VILLAGE",
    "name:eng_x_preferred":[
        "Hirapur"
    ],
    "name:eng_x_variant":[
        "H\u012br\u0101pur"
    ],
    "wof:name":"Hirapur",
    "wof:placetype":"locality"
},
  "geometry": {"coordinates":[78.53313900000001,20.690152],"type":"Point"}
}