{
  "type": "Feature",
  "properties": {
    "iso:country":"IN",
    "ks:ks_name":"Pabitrapur",
    "ks:ks_pop":168,
    "ks:ks_type":"VILLAGE",
    "ks:ks_uagg_main":0,
    "name:eng_x_preferred":[
        "Pabitrapur"
    ],
    "wof:name":"Pabitrapur",
    "wof:placetype":"neighbourhood",
    "wof:population":168
},
  "geometry": {"coordinates":[86.909256,21.45513],"type":"Point"}
}