{
  "type": "Feature",
  "properties": {
    "iso:country":"IN",
    "ks:ks_name":"Kashdih",
    "ks:ks_pop":576,
    "ks:ks_type":"HABITATION",
    "name:eng_x_preferred":[
        "Kashdih"
    ],
    "wof:name":"Kashdih",
    "wof:placetype":"locality",
    "wof:population":576
},
  "geometry": {"coordinates":[82.935362,27.089053],"type":"Point"}
}