{
  "type": "Feature",
  "properties": {
    "iso:country":"IN",
    "ks:ks_alt_nam":"boudhawadi",
    "ks:ks_name":"Boudhawadi",
    "ks:ks_pop":65,
    "ks:ks_type":"HABITATION",
    "name:eng_x_preferred":[
        "Boudhawadi"
    ],
    "wof:name":"Boudhawadi",
    "wof:placetype":"locality",
    "wof:population":65
},
  "geometry": {"coordinates":[73.56305,16.630967],"type":"Point"}
}