{
  "type": "Feature",
  "properties": {
    "iso:country":"IN",
    "ks:ks_name":"Kotlagaruvu",
    "ks:ks_pop":98,
    "ks:ks_type":"HABITATION",
    "name:eng_x_preferred":[
        "Kotlagaruvu"
    ],
    "wof:name":"Kotlagaruvu",
    "wof:placetype":"locality",
    "wof:population":98
},
  "geometry": {"coordinates":[82.69601900000001,18.054739],"type":"Point"}
}