{
  "type": "Feature",
  "properties": {
    "iso:country":"IN",
    "ks:ks_name":"Prajapatipur",
    "ks:ks_pop":531,
    "ks:ks_type":"VILLAGE",
    "ks:ks_uagg_main":0,
    "name:eng_x_preferred":[
        "Prajapatipur"
    ],
    "wof:name":"Prajapatipur",
    "wof:placetype":"locality",
    "wof:population":531
},
  "geometry": {"coordinates":[82.53505699999999,25.194025],"type":"Point"}
}