{
  "type": "Feature",
  "properties": {
    "gn:admin1_code":"36.0",
    "gn:admin2_code":"133.0",
    "gn:asciiname":"Yahiyapur",
    "gn:country_code":"IN",
    "gn:dem":241,
    "gn:feature_class":"P",
    "gn:feature_code":"PPL",
    "gn:name":"Y\u0101hiy\u0101pur",
    "gn:population":0,
    "gn:timezone":"Asia/Kolkata",
    "iso:country":"IN",
    "name:hin_x_preferred":[
        "\u092f\u093e\u0939\u093f\u092f\u093e\u092a\u0941\u0930"
    ],
    "name:und_x_variant":[
        "Y\u0101hiy\u0101pur"
    ],
    "name:urd_x_preferred":[
        "\u06cc\u06c1\u06cc\u067e\u0631"
    ],
    "wof:name":"Yahiyapur",
    "wof:placetype":"locality"
},
  "geometry": {"coordinates":[77.77506,29.28259000000001],"type":"Point"}
}