{
  "type": "Feature",
  "properties": {
    "iso:country":"IN",
    "ks:ks_alt_nam":"hude",
    "ks:ks_name":"Hude",
    "ks:ks_pop":100,
    "ks:ks_type":"HABITATION",
    "name:eng_x_preferred":[
        "Hude"
    ],
    "wof:name":"Hude",
    "wof:placetype":"locality",
    "wof:population":100
},
  "geometry": {"coordinates":[74.23824399999999,16.068639],"type":"Point"}
}