{
  "type": "Feature",
  "properties": {
    "gn:admin1_code":"16",
    "gn:admin2_code":"510.0",
    "gn:asciiname":"Malkhed Buzurg",
    "gn:country_code":"IN",
    "gn:dem":358,
    "gn:feature_class":"P",
    "gn:feature_code":"PPL",
    "gn:name":"M\u0101lkhed Buzurg",
    "gn:population":0,
    "gn:timezone":"Asia/Kolkata",
    "iso:country":"IN",
    "name:und_x_variant":[
        "M\u0101lkhed Buzurg",
        "M\u0101lkhed"
    ],
    "wof:name":"Malkhed Buzurg",
    "wof:placetype":"locality"
},
  "geometry": {"coordinates":[77.90335999999998,20.42344],"type":"Point"}
}