{
  "type": "Feature",
  "properties": {
    "gn:admin1_code":"37",
    "gn:admin2_code":"406.0",
    "gn:asciiname":"Pudu",
    "gn:country_code":"IN",
    "gn:dem":364,
    "gn:feature_class":"P",
    "gn:feature_code":"PPL",
    "gn:name":"Pud\u016b",
    "gn:population":0,
    "gn:timezone":"Asia/Kolkata",
    "iso:country":"IN",
    "name:msa_x_preferred":[
        "Pudu"
    ],
    "name:nld_x_preferred":[
        "Pudu"
    ],
    "name:vie_x_preferred":[
        "Pudu"
    ],
    "wof:name":"Pudu",
    "wof:placetype":"locality"
},
  "geometry": {"coordinates":[82.13336,22.44215],"type":"Point"}
}