{
  "type": "Feature",
  "properties": {
    "iso:country":"IN",
    "ks:ks_name":"Malwasi",
    "ks:ks_pop":1120,
    "ks:ks_type":"VILLAGE",
    "name:eng_x_preferred":[
        "Malwasi"
    ],
    "wof:name":"Malwasi",
    "wof:placetype":"locality",
    "wof:population":1120
},
  "geometry": {"coordinates":[74.873701,23.186262],"type":"Point"}
}