{
  "type": "Feature",
  "properties": {
    "iso:country":"IN",
    "ks:ks_name":"Huda Gopirampur",
    "ks:ks_pop":364,
    "ks:ks_type":"VILLAGE",
    "ks:ks_uagg_main":0,
    "name:eng_x_preferred":[
        "Huda Gopirampur"
    ],
    "wof:name":"Huda Gopirampur",
    "wof:placetype":"neighbourhood",
    "wof:population":364
},
  "geometry": {"coordinates":[88.621985,23.93179],"type":"Point"}
}