{
  "type": "Feature",
  "properties": {
    "gn:country":"IN",
    "gn:fcode":"PPL",
    "gn:pop":33770,
    "iso:country":"IN",
    "name:ben_x_preferred":[
        "\u09b8\u09bf\u09a8\u09cd\u09a6\u0997\u09bf"
    ],
    "name:bpy_x_preferred":[
        "\u09b8\u09bf\u09a8\u09cd\u09a6\u0997\u09bf"
    ],
    "name:bul_x_preferred":[
        "\u0421\u0438\u043d\u0434\u0433\u0438"
    ],
    "name:ceb_x_preferred":[
        "Sindgi"
    ],
    "name:deu_x_preferred":[
        "Sindgi"
    ],
    "name:eng_x_preferred":[
        "Sindhagi"
    ],
    "name:fra_x_preferred":[
        "Sindhagi"
    ],
    "name:guj_x_preferred":[
        "\u0ab8\u0abf\u0a82\u0aa7\u0abe\u0a97\u0ac0"
    ],
    "name:hif_x_preferred":[
        "Sindhagi"
    ],
    "name:ita_x_preferred":[
        "Sindgi"
    ],
    "name:jpn_x_preferred":[
        "\u30b7\u30f3\u30c0\u30ae"
    ],
    "name:kan_x_preferred":[
        "\u0cb8\u0cbf\u0c82\u0ca6\u0c97\u0cbf"
    ],
    "name:kor_x_preferred":[
        "\uc2e0\ub2e4\uae30"
    ],
    "name:mar_x_preferred":[
        "\u0938\u093f\u0902\u0926\u0917\u0940"
    ],
    "name:msa_x_preferred":[
        "Sindgi"
    ],
    "name:nan_x_preferred":[
        "Sindgi"
    ],
    "name:nld_x_preferred":[
        "Sindgi"
    ],
    "name:ori_x_preferred":[
        "\u0b38\u0b3f\u0b28\u0b4d\u0b26\u0b3e\u0b17\u0b3f"
    ],
    "name:por_x_preferred":[
        "Sindgi"
    ],
    "name:rus_x_preferred":[
        "\u0421\u0438\u043d\u0434\u0445\u0430\u0433\u0438"
    ],
    "name:spa_x_preferred":[
        "Sindgi"
    ],
    "name:swe_x_preferred":[
        "Sindgi"
    ],
    "name:tam_x_preferred":[
        "\u0b9a\u0bbf\u0ba4\u0bcd\u0ba4\u0bbe\u0b95\u0bbf"
    ],
    "name:tel_x_preferred":[
        "\u0c38\u0c3f\u0c02\u0c26\u0c17\u0c3f"
    ],
    "name:unk_x_variant":[
        "Sindgi"
    ],
    "name:urd_x_preferred":[
        "\u0633\u06cc\u0646\u062f\u062d\u0627\u062c\u06cc"
    ],
    "name:vie_x_preferred":[
        "Sindgi"
    ],
    "name:zho_x_preferred":[
        "\u897f\u6069\u5fb7\u5409"
    ],
    "qs:name":"Sindagi",
    "qs:name_adm0":"India",
    "qs:name_adm1":"Karnataka",
    "qs:photos_9r":0,
    "qs:photos_sr":0,
    "qs:placetype":"Town",
    "qs:pop_sr":"7",
    "wd:wordcount":143,
    "wof:name":"Sindagi",
    "wof:placetype":"locality",
    "wof:population":33770
},
  "geometry": {"coordinates":[76.23336,16.91845],"type":"Point"}
}