{
  "type": "Feature",
  "properties": {
    "gn:admin1_code":"25.0",
    "gn:admin2_code":"618.0",
    "gn:asciiname":"Anaikkudi",
    "gn:country_code":"IN",
    "gn:dem":6,
    "gn:feature_class":"P",
    "gn:feature_code":"PPL",
    "gn:name":"Anaikkudi",
    "gn:population":0,
    "gn:timezone":"Asia/Kolkata",
    "iso:country":"IN",
    "wof:name":"Anaikkudi",
    "wof:placetype":"locality"
},
  "geometry": {"coordinates":[79.73563,10.69702],"type":"Point"}
}