{
  "type": "Feature",
  "properties": {
    "iso:country":"IN",
    "ks:ks_name":"Shindichiwadi",
    "ks:ks_pop":98,
    "ks:ks_type":"HABITATION",
    "name:eng_x_preferred":[
        "Shindichiwadi"
    ],
    "wof:name":"Shindichiwadi",
    "wof:placetype":"locality",
    "wof:population":98
},
  "geometry": {"coordinates":[73.486068,19.935484],"type":"Point"}
}