{
  "type": "Feature",
  "properties": {
    "iso:country":"IN",
    "ks:ks_name":"Jhariaguda",
    "ks:ks_pop":100,
    "ks:ks_type":"HABITATION",
    "name:eng_x_preferred":[
        "Jhariaguda"
    ],
    "wof:name":"Jhariaguda",
    "wof:placetype":"locality",
    "wof:population":100
},
  "geometry": {"coordinates":[82.24933299999999,18.480749],"type":"Point"}
}