{
  "type": "Feature",
  "properties": {
    "iso:country":"IN",
    "ks:ks_alt_nam":"KALWANI",
    "ks:ks_name":"Kalwani",
    "ks:ks_pop":1608,
    "ks:ks_type":"HABITATION",
    "name:eng_x_preferred":[
        "Kalwani"
    ],
    "wof:name":"Kalwani",
    "wof:placetype":"locality",
    "wof:population":1608
},
  "geometry": {"coordinates":[74.67600299999999,23.71391],"type":"Point"}
}