{
  "type": "Feature",
  "properties": {
    "iso:country":"IN",
    "ks:ks_name":"Gawai",
    "ks:ks_pop":253,
    "ks:ks_type":"VILLAGE",
    "name:eng_x_preferred":[
        "Gawai"
    ],
    "wof:name":"Gawai",
    "wof:placetype":"locality",
    "wof:population":253
},
  "geometry": {"coordinates":[79.87745,29.44294],"type":"Point"}
}