{
  "type": "Feature",
  "properties": {
    "iso:country":"IN",
    "ks:ks_name":"Pithavur",
    "ks:ks_pop":162,
    "ks:ks_type":"HABITATION",
    "name:eng_x_preferred":[
        "Pithavur"
    ],
    "wof:name":"Pithavur",
    "wof:placetype":"locality",
    "wof:population":162
},
  "geometry": {"coordinates":[78.59252600000001,10.313911],"type":"Point"}
}