{
  "type": "Feature",
  "properties": {
    "iso:country":"IN",
    "ks:ks_name":"Karibayalu",
    "ks:ks_pop":63,
    "ks:ks_type":"HABITATION",
    "name:eng_x_preferred":[
        "Karibayalu"
    ],
    "wof:name":"Karibayalu",
    "wof:placetype":"locality",
    "wof:population":63
},
  "geometry": {"coordinates":[74.41571399999999,14.324388],"type":"Point"}
}