{
  "type": "Feature",
  "properties": {
    "gn:admin1_code":"37",
    "gn:admin2_code":"408.0",
    "gn:asciiname":"Banbod",
    "gn:country_code":"IN",
    "gn:dem":372,
    "gn:feature_class":"P",
    "gn:feature_code":"PPL",
    "gn:name":"Banbod",
    "gn:population":0,
    "gn:timezone":"Asia/Kolkata",
    "iso:country":"IN",
    "ks:ks_name":"Banbod",
    "ks:ks_pop":605,
    "ks:ks_type":"VILLAGE",
    "name:eng_x_preferred":[
        "Banbod"
    ],
    "wof:name":"Banbod",
    "wof:placetype":"locality",
    "wof:population":605
},
  "geometry": {"coordinates":[80.86525899999999,21.297739],"type":"Point"}
}