{
  "type": "Feature",
  "properties": {
    "iso:country":"IN",
    "ks:ks_name":"Rangapalle",
    "ks:ks_pop":272,
    "ks:ks_type":"HABITATION",
    "name:eng_x_preferred":[
        "Rangapalle"
    ],
    "wof:name":"Rangapalle",
    "wof:placetype":"locality",
    "wof:population":272
},
  "geometry": {"coordinates":[78.378927,12.852558],"type":"Point"}
}