{
  "type": "Feature",
  "properties": {
    "iso:country":"IN",
    "ks:ks_alt_nam":"yadav basti",
    "ks:ks_name":"Yadav Basti",
    "ks:ks_pop":371,
    "ks:ks_type":"HABITATION",
    "name:eng_x_preferred":[
        "Yadav Basti"
    ],
    "wof:name":"Yadav Basti",
    "wof:placetype":"locality",
    "wof:population":371
},
  "geometry": {"coordinates":[82.941475,25.441167],"type":"Point"}
}