{
  "type": "Feature",
  "properties": {
    "iso:country":"IN",
    "ks:ks_name":"Hirar Kuthi",
    "ks:ks_pop":393,
    "ks:ks_type":"VILLAGE",
    "name:eng_x_preferred":[
        "Hirar Kuthi"
    ],
    "wof:name":"Hirar Kuthi",
    "wof:placetype":"locality",
    "wof:population":393
},
  "geometry": {"coordinates":[89.440749,26.263242],"type":"Point"}
}