{
  "type": "Feature",
  "properties": {
    "gn:admin1_code":"34.0",
    "gn:admin2_code":"204.0",
    "gn:asciiname":"Tinkoni",
    "gn:country_code":"IN",
    "gn:dem":81,
    "gn:feature_class":"P",
    "gn:feature_code":"PPL",
    "gn:name":"Tinkoni",
    "gn:population":0,
    "gn:timezone":"Asia/Kolkata",
    "iso:country":"IN",
    "wof:name":"Tinkoni",
    "wof:placetype":"locality"
},
  "geometry": {"coordinates":[84.96465000000001,26.86129],"type":"Point"}
}