{
  "type": "Feature",
  "properties": {
    "gn:admin1_code":"39.0",
    "gn:admin2_code":"64.0",
    "gn:asciiname":"Tamadhaun",
    "gn:country_code":"IN",
    "gn:dem":1162,
    "gn:feature_class":"P",
    "gn:feature_code":"PPL",
    "gn:name":"T\u0101m\u0101dhaun",
    "gn:population":0,
    "gn:timezone":"Asia/Kolkata",
    "iso:country":"IN",
    "ks:ks_name":"Tamadhaun",
    "ks:ks_pop":258,
    "ks:ks_type":"VILLAGE",
    "name:eng_x_preferred":[
        "Tamadhaun"
    ],
    "name:und_x_variant":[
        "T\u0101m\u0101dhaun",
        "Say\u0101lde"
    ],
    "wof:name":"Tamadhaun",
    "wof:placetype":"locality",
    "wof:population":258
},
  "geometry": {"coordinates":[79.205213,29.851633],"type":"Point"}
}