{
  "type": "Feature",
  "properties": {
    "iso:country":"IN",
    "ks:ks_name":"Brahman",
    "ks:ks_pop":426,
    "ks:ks_type":"HABITATION",
    "name:eng_x_preferred":[
        "Brahman"
    ],
    "wof:name":"Brahman",
    "wof:placetype":"locality",
    "wof:population":426
},
  "geometry": {"coordinates":[82.406469,25.768535],"type":"Point"}
}