{
  "type": "Feature",
  "properties": {
    "iso:country":"IN",
    "ks:ks_alt_nam":"Jangir\u0101mpur",
    "ks:ks_name":"Jangirampur",
    "ks:ks_type":"VILLAGE",
    "name:eng_x_preferred":[
        "Jangirampur"
    ],
    "name:eng_x_variant":[
        "Jangir\u0101mpur"
    ],
    "wof:name":"Jangirampur",
    "wof:placetype":"locality"
},
  "geometry": {"coordinates":[76.379183,16.205276],"type":"Point"}
}