{
  "type": "Feature",
  "properties": {
    "iso:country":"IN",
    "ks:ks_name":"Raghunath Chak",
    "ks:ks_pop":5500,
    "ks:ks_type":"VILLAGE",
    "ks:ks_uagg_main":0,
    "name:eng_x_preferred":[
        "Raghunath Chak"
    ],
    "wof:name":"Raghunath Chak",
    "wof:placetype":"neighbourhood",
    "wof:population":5500
},
  "geometry": {"coordinates":[87.118996,23.58276],"type":"Point"}
}