{
  "type": "Feature",
  "properties": {
    "gn:admin1_code":"24",
    "gn:admin2_code":"124.0",
    "gn:asciiname":"Natau",
    "gn:country_code":"IN",
    "gn:dem":193,
    "gn:feature_class":"P",
    "gn:feature_code":"PPL",
    "gn:name":"Nat\u0101u",
    "gn:population":0,
    "gn:timezone":"Asia/Kolkata",
    "iso:country":"IN",
    "wof:name":"Natau",
    "wof:placetype":"locality"
},
  "geometry": {"coordinates":[74.28333000000001,23.91667],"type":"Point"}
}