{
  "type": "Feature",
  "properties": {
    "iso:country":"IN",
    "ks:ks_name":"Kolki",
    "ks:ks_pop":5446,
    "ks:ks_type":"VILLAGE",
    "ks:ks_uagg_main":0,
    "name:eng_x_preferred":[
        "Kolki"
    ],
    "wof:name":"Kolki",
    "wof:placetype":"neighbourhood",
    "wof:population":5446
},
  "geometry": {"coordinates":[74.45184999999999,17.977642],"type":"Point"}
}