{
  "type": "Feature",
  "properties": {
    "iso:country":"IN",
    "ks:ks_name":"Tikulia",
    "ks:ks_pop":411,
    "ks:ks_type":"VILLAGE",
    "name:eng_x_preferred":[
        "Tikulia"
    ],
    "wof:name":"Tikulia",
    "wof:placetype":"locality",
    "wof:population":411
},
  "geometry": {"coordinates":[86.069964,24.685748],"type":"Point"}
}