{
  "type": "Feature",
  "properties": {
    "gn:admin1_code":"36.0",
    "gn:admin2_code":"160",
    "gn:asciiname":"Muhammadpur Kirat",
    "gn:country_code":"IN",
    "gn:dem":150,
    "gn:feature_class":"P",
    "gn:feature_code":"PPL",
    "gn:name":"Muhammadpur K\u012brat",
    "gn:population":0,
    "gn:timezone":"Asia/Kolkata",
    "iso:country":"IN",
    "wof:name":"Muhammadpur Kirat",
    "wof:placetype":"neighbourhood"
},
  "geometry": {"coordinates":[79.44183,27.16989],"type":"Point"}
}