{
  "type": "Feature",
  "properties": {
    "iso:country":"IN",
    "ks:ks_name":"Dhawada",
    "ks:ks_pop":2651,
    "ks:ks_type":"HABITATION",
    "name:eng_x_preferred":[
        "Dhawada"
    ],
    "wof:name":"Dhawada",
    "wof:placetype":"locality",
    "wof:population":2651
},
  "geometry": {"coordinates":[75.388355,21.651706],"type":"Point"}
}