{
  "type": "Feature",
  "properties": {
    "gn:admin1_code":"11",
    "gn:admin2_code":"23.0",
    "gn:asciiname":"Nagni",
    "gn:country_code":"IN",
    "gn:dem":2658,
    "gn:feature_class":"P",
    "gn:feature_code":"PPL",
    "gn:name":"N\u0101gni",
    "gn:population":0,
    "gn:timezone":"Asia/Kolkata",
    "iso:country":"IN",
    "wof:name":"Nagni",
    "wof:placetype":"locality"
},
  "geometry": {"coordinates":[76.19506,32.81541],"type":"Point"}
}