{
  "type": "Feature",
  "properties": {
    "gn:admin1_code":"11.0",
    "gn:admin2_code":"32.0",
    "gn:asciiname":"Cheuna",
    "gn:country_code":"IN",
    "gn:dem":1290,
    "gn:feature_class":"P",
    "gn:feature_code":"PPL",
    "gn:name":"Cheuna",
    "gn:population":0,
    "gn:timezone":"Asia/Kolkata",
    "iso:country":"IN",
    "wof:name":"Cheuna",
    "wof:placetype":"locality"
},
  "geometry": {"coordinates":[77.54630999999998,30.62251],"type":"Point"}
}