{
  "type": "Feature",
  "properties": {
    "iso:country":"IN",
    "ks:ks_name":"Talav Falia",
    "ks:ks_pop":170,
    "ks:ks_type":"HABITATION",
    "name:eng_x_preferred":[
        "Talav Falia"
    ],
    "wof:name":"Talav Falia",
    "wof:placetype":"locality",
    "wof:population":170
},
  "geometry": {"coordinates":[73.5085,20.825611],"type":"Point"}
}