{
  "type": "Feature",
  "properties": {
    "iso:country":"IN",
    "ks:ks_name":"Amada",
    "ks:ks_pop":230,
    "ks:ks_type":"HABITATION",
    "name:eng_x_preferred":[
        "Amada"
    ],
    "wof:name":"Amada",
    "wof:placetype":"locality",
    "wof:population":230
},
  "geometry": {"coordinates":[80.82415899999999,24.268984],"type":"Point"}
}