{
  "type": "Feature",
  "properties": {
    "gn:admin1_code":"39.0",
    "gn:admin2_code":"64.0",
    "gn:asciiname":"Kyathaur",
    "gn:country_code":"IN",
    "gn:dem":1622,
    "gn:feature_class":"P",
    "gn:feature_code":"PPL",
    "gn:name":"Ky\u0101thaur",
    "gn:population":0,
    "gn:timezone":"Asia/Kolkata",
    "iso:country":"IN",
    "wof:name":"Kyathaur",
    "wof:placetype":"locality"
},
  "geometry": {"coordinates":[79.14064,29.76054],"type":"Point"}
}