{
  "type": "Feature",
  "properties": {
    "gn:admin1_code":"39.0",
    "gn:admin2_code":"061",
    "gn:asciiname":"Bangla",
    "gn:country_code":"IN",
    "gn:dem":1541,
    "gn:feature_class":"P",
    "gn:feature_code":"PPL",
    "gn:name":"Bangla",
    "gn:population":0,
    "gn:timezone":"Asia/Kolkata",
    "iso:country":"IN",
    "ks:ks_name":"Bangla",
    "ks:ks_type":"VILLAGE",
    "name:asm_x_preferred":[
        "\u09ac\u09be\u0982\u09b2\u09be"
    ],
    "name:ben_x_preferred":[
        "\u09ac\u09be\u0982\u09b2\u09be"
    ],
    "name:ceb_x_preferred":[
        "Bangla"
    ],
    "name:eng_x_preferred":[
        "Bangla"
    ],
    "name:ita_x_preferred":[
        "Bangla"
    ],
    "name:swe_x_preferred":[
        "Bangla"
    ],
    "wof:name":"Bangla",
    "wof:placetype":"locality"
},
  "geometry": {"coordinates":[78.56802399999999,29.825953],"type":"Point"}
}