{
  "type": "Feature",
  "properties": {
    "iso:country":"IN",
    "ks:ks_name":"Dangi Para",
    "ks:ks_pop":170,
    "ks:ks_type":"HABITATION",
    "ks:ks_uagg_main":0,
    "name:eng_x_preferred":[
        "Dangi Para"
    ],
    "wof:name":"Dangi Para",
    "wof:placetype":"neighbourhood",
    "wof:population":170
},
  "geometry": {"coordinates":[87.91131799999999,26.305677],"type":"Point"}
}