{
  "type": "Feature",
  "properties": {
    "iso:country":"IN",
    "ks:ks_name":"Narasingpur",
    "ks:ks_pop":718,
    "ks:ks_type":"VILLAGE",
    "ks:ks_uagg_main":0,
    "name:eng_x_preferred":[
        "Narasingpur"
    ],
    "wof:name":"Narasingpur",
    "wof:placetype":"neighbourhood",
    "wof:population":718
},
  "geometry": {"coordinates":[86.428095,20.401021],"type":"Point"}
}