{
  "type": "Feature",
  "properties": {
    "iso:country":"IN",
    "ks:ks_name":"Dakchin Tola",
    "ks:ks_pop":18,
    "ks:ks_type":"HABITATION",
    "ks:ks_uagg_main":0,
    "name:eng_x_preferred":[
        "Dakchin Tola"
    ],
    "wof:name":"Dakchin Tola",
    "wof:placetype":"neighbourhood",
    "wof:population":18
},
  "geometry": {"coordinates":[88.210668,26.425465],"type":"Point"}
}