{
  "type": "Feature",
  "properties": {
    "iso:country":"IN",
    "ks:ks_name":"Mohanai Falia",
    "ks:ks_pop":811,
    "ks:ks_type":"HABITATION",
    "name:eng_x_preferred":[
        "Mohanai Falia"
    ],
    "wof:name":"Mohanai Falia",
    "wof:placetype":"locality",
    "wof:population":811
},
  "geometry": {"coordinates":[74.062056,23.279694],"type":"Point"}
}