{
  "type": "Feature",
  "properties": {
    "iso:country":"IN",
    "ks:ks_name":"Bhawanisinghpur",
    "ks:ks_pop":235,
    "ks:ks_type":"HABITATION",
    "name:eng_x_preferred":[
        "Bhawanisinghpur"
    ],
    "wof:name":"Bhawanisinghpur",
    "wof:placetype":"locality",
    "wof:population":235
},
  "geometry": {"coordinates":[80.970337,27.10552],"type":"Point"}
}