{
  "type": "Feature",
  "properties": {
    "gn:admin1_code":"36.0",
    "gn:admin2_code":"135.0",
    "gn:asciiname":"Sahriya Abdalnagar",
    "gn:country_code":"IN",
    "gn:dem":196,
    "gn:feature_class":"P",
    "gn:feature_code":"PPL",
    "gn:name":"Sahriya Abd\u0101lnagar",
    "gn:population":0,
    "gn:timezone":"Asia/Kolkata",
    "iso:country":"IN",
    "wof:name":"Sahriya Abdalnagar",
    "wof:placetype":"locality"
},
  "geometry": {"coordinates":[78.63978,28.58927000000001],"type":"Point"}
}