{
  "type": "Feature",
  "properties": {
    "iso:country":"IN",
    "ks:ks_name":"Kuttiyaloor",
    "ks:ks_pop":122,
    "ks:ks_type":"HABITATION",
    "ks:ks_uagg_main":0,
    "name:eng_x_preferred":[
        "Kuttiyaloor"
    ],
    "wof:name":"Kuttiyaloor",
    "wof:placetype":"neighbourhood",
    "wof:population":122
},
  "geometry": {"coordinates":[78.259647,10.626971],"type":"Point"}
}