{
  "type": "Feature",
  "properties": {
    "iso:country":"IN",
    "ks:ks_alt_nam":"Khadkali tanda",
    "ks:ks_name":"Khadkali Tanda",
    "ks:ks_pop":90,
    "ks:ks_type":"HABITATION",
    "name:eng_x_preferred":[
        "Khadkali Tanda"
    ],
    "wof:name":"Khadkali Tanda",
    "wof:placetype":"locality",
    "wof:population":90
},
  "geometry": {"coordinates":[76.879943,18.803261],"type":"Point"}
}