{
  "type": "Feature",
  "properties": {
    "iso:country":"IN",
    "ks:ks_name":"Vilar",
    "ks:ks_pop":5628,
    "ks:ks_type":"VILLAGE",
    "ks:ks_uagg_main":0,
    "name:eng_x_preferred":[
        "Vilar"
    ],
    "wof:name":"Vilar",
    "wof:placetype":"neighbourhood",
    "wof:population":5628
},
  "geometry": {"coordinates":[79.148793,10.759732],"type":"Point"}
}