{
  "type": "Feature",
  "properties": {
    "iso:country":"IN",
    "ks:ks_name":"Nauwa Purwa Garahi",
    "ks:ks_pop":72,
    "ks:ks_type":"HABITATION",
    "name:eng_x_preferred":[
        "Nauwa Purwa Garahi"
    ],
    "wof:name":"Nauwa Purwa Garahi",
    "wof:placetype":"locality",
    "wof:population":72
},
  "geometry": {"coordinates":[80.894649,27.030905],"type":"Point"}
}