{
  "type": "Feature",
  "properties": {
    "gn:admin1_code":"36",
    "gn:admin2_code":"179.0",
    "gn:asciiname":"Daulatpur",
    "gn:country_code":"IN",
    "gn:dem":97,
    "gn:feature_class":"P",
    "gn:feature_code":"PPL",
    "gn:name":"Daulatpur",
    "gn:population":0,
    "gn:timezone":"Asia/Kolkata",
    "iso:country":"IN",
    "ks:ks_name":"Daulatpur",
    "ks:ks_type":"VILLAGE",
    "ks:ks_uagg_main":0,
    "name:ara_x_preferred":[
        "\u062f\u0648\u0644\u062a \u0628\u0648\u0631"
    ],
    "name:ben_bn_x_preferred":[
        "\u09a6\u09cc\u09b2\u09a4\u09aa\u09c1\u09b0"
    ],
    "name:ben_in_x_preferred":[
        "\u09a6\u09cc\u09b2\u09a4\u09aa\u09c1\u09b0"
    ],
    "name:ben_x_preferred":[
        "\u09a6\u09cc\u09b2\u09a4\u09aa\u09c1\u09b0"
    ],
    "name:bpy_x_preferred":[
        "\u09a6\u09cc\u09b2\u09a4\u09aa\u09c1\u09b0"
    ],
    "name:ceb_x_preferred":[
        "Daulatpur"
    ],
    "name:eng_x_preferred":[
        "Daulatpur"
    ],
    "name:fra_x_preferred":[
        "Daulatpur"
    ],
    "name:guj_x_preferred":[
        "\u0aa6\u0acc\u0ab2\u0aa4\u0aaa\u0ac1\u0ab0"
    ],
    "name:hin_x_preferred":[
        "\u0926\u094c\u0932\u0924\u092a\u0941\u0930"
    ],
    "name:ita_x_preferred":[
        "Daulatpur"
    ],
    "name:kan_x_preferred":[
        "\u0ca6\u0ccc\u0cb2\u0ca4\u0ccd"
    ],
    "name:mal_x_preferred":[
        "\u0d26\u0d57\u0d32\u0d24\u0d4d\u0d2a\u0d42\u0d7c"
    ],
    "name:mar_x_preferred":[
        "\u0926\u094c\u0932\u0924\u092a\u0942\u0930"
    ],
    "name:nld_x_preferred":[
        "Daulatpur"
    ],
    "name:pan_x_preferred":[
        "\u0a26\u0a4c\u0a32\u0a24\u0a2a\u0a41\u0a30"
    ],
    "name:pol_x_preferred":[
        "Daulatpur"
    ],
    "name:swe_x_preferred":[
        "Daulatpur"
    ],
    "name:tam_x_preferred":[
        "\u0ba4\u0bcc\u0bb2\u0ba4\u0bcd\u0baa\u0bc2\u0bb0\u0bcd"
    ],
    "name:tel_x_preferred":[
        "\u0c26\u0c4c\u0c32\u0c24\u0c4d"
    ],
    "name:urd_x_preferred":[
        "\u062f\u0648\u0644\u062a \u067e\u0648\u0631"
    ],
    "name:zho_x_preferred":[
        "\u8fbe\u4e4c\u62c9\u7279\u666e\u5c14"
    ],
    "wof:name":"Daulatpur",
    "wof:placetype":"neighbourhood"
},
  "geometry": {"coordinates":[82.385622,26.153554],"type":"Point"}
}