{
  "type": "Feature",
  "properties": {
    "iso:country":"IN",
    "ks:ks_name":"Pursotampur",
    "ks:ks_pop":1411,
    "ks:ks_type":"VILLAGE",
    "name:eng_x_preferred":[
        "Pursotampur"
    ],
    "wof:name":"Pursotampur",
    "wof:placetype":"locality",
    "wof:population":1411
},
  "geometry": {"coordinates":[85.18883,20.151523],"type":"Point"}
}