{
  "type": "Feature",
  "properties": {
    "gn:admin1_code":"23.0",
    "gn:admin2_code":"40.0",
    "gn:asciiname":"Sarana",
    "gn:country_code":"IN",
    "gn:dem":261,
    "gn:feature_class":"P",
    "gn:feature_code":"PPL",
    "gn:name":"Sar\u0101na",
    "gn:population":0,
    "gn:timezone":"Asia/Kolkata",
    "iso:country":"IN",
    "name:ceb_x_preferred":[
        "Sarana"
    ],
    "name:deu_x_preferred":[
        "Sarana"
    ],
    "name:fas_x_preferred":[
        "\u0633\u0627\u0631\u0627\u0646\u0627"
    ],
    "name:fra_x_preferred":[
        "Sarana"
    ],
    "name:swe_x_preferred":[
        "Sarana"
    ],
    "wof:name":"Sarana",
    "wof:placetype":"locality"
},
  "geometry": {"coordinates":[76.39591,30.48106],"type":"Point"}
}