{
  "type": "Feature",
  "properties": {
    "gn:country":"IN",
    "gn:fcode":"PPL",
    "gn:pop":105909,
    "iso:country":"IN",
    "name:bpy_x_preferred":[
        "\u0996\u09c1\u09b0\u09cd\u099c\u09be"
    ],
    "name:cat_x_preferred":[
        "Khurja"
    ],
    "name:chi_x_preferred":[
        "\u5e93\u5c14\u8d3e"
    ],
    "name:dut_x_preferred":[
        "Khurja"
    ],
    "name:eng_x_preferred":[
        "Khurja"
    ],
    "name:ger_x_preferred":[
        "Khurja"
    ],
    "name:hin_x_preferred":[
        "\u0916\u0941\u0930\u094d\u091c\u093e"
    ],
    "name:ita_x_preferred":[
        "Khurja"
    ],
    "name:may_x_preferred":[
        "Khurja"
    ],
    "name:nan_x_preferred":[
        "Khurja"
    ],
    "name:nep_x_preferred":[
        "\u0916\u0941\u0930\u094d\u091c\u093e"
    ],
    "name:new_x_preferred":[
        "\u0916\u0941\u0930\u094d\u091c\u093e"
    ],
    "name:pan_x_preferred":[
        "\u0a16\u0a41\u0a30\u0a1c\u0a3e"
    ],
    "name:pol_x_preferred":[
        "Khurja"
    ],
    "name:swe_x_preferred":[
        "Khurja"
    ],
    "name:urd_x_preferred":[
        "\u062e\u0648\u0631\u062c\u06c1"
    ],
    "name:vie_x_preferred":[
        "Khurja"
    ],
    "qs:name":"Khurja",
    "qs:name_adm0":"India",
    "qs:name_adm1":"Uttar Pradesh",
    "qs:photos_9k":1,
    "qs:photos_9r":1,
    "qs:photos_all":18,
    "qs:photos_sr":0,
    "qs:placetype":"Town",
    "qs:pop_sr":"9",
    "wd:wordcount":2139,
    "wof:name":"Khurja",
    "wof:placetype":"locality",
    "wof:population":105909
},
  "geometry": {"coordinates":[77.85436,28.25436],"type":"Point"}
}