{
  "type": "Feature",
  "properties": {
    "gn:admin1_code":"36",
    "gn:admin2_code":"191.0",
    "gn:asciiname":"Kharagpur",
    "gn:country_code":"IN",
    "gn:dem":82,
    "gn:feature_class":"P",
    "gn:feature_code":"PPL",
    "gn:name":"Kharagpur",
    "gn:population":0,
    "gn:timezone":"Asia/Kolkata",
    "iso:country":"IN",
    "wof:name":"Kharagpur",
    "wof:placetype":"locality"
},
  "geometry": {"coordinates":[83.22865999999998,25.83712],"type":"Point"}
}