{
  "type": "Feature",
  "properties": {
    "iso:country":"IN",
    "ks:ks_name":"Basavanahalli",
    "ks:ks_type":"VILLAGE",
    "name:eng_x_preferred":[
        "Basavanahalli"
    ],
    "wof:name":"Basavanahalli",
    "wof:placetype":"locality"
},
  "geometry": {"coordinates":[76.024005,12.801004],"type":"Point"}
}