{
  "type": "Feature",
  "properties": {
    "gn:admin1_code":"36",
    "gn:admin2_code":"134.0",
    "gn:asciiname":"Kamala",
    "gn:country_code":"IN",
    "gn:dem":220,
    "gn:feature_class":"P",
    "gn:feature_code":"PPL",
    "gn:name":"Kam\u0101la",
    "gn:population":0,
    "gn:timezone":"Asia/Kolkata",
    "iso:country":"IN",
    "name:ceb_x_preferred":[
        "Kamala"
    ],
    "name:deu_x_preferred":[
        "Kamala"
    ],
    "name:fra_x_preferred":[
        "Kamala"
    ],
    "name:kor_x_preferred":[
        "\uce74\ub9d0\ub77c"
    ],
    "name:nld_x_preferred":[
        "Kamala"
    ],
    "name:por_x_preferred":[
        "Kamala"
    ],
    "name:swe_x_preferred":[
        "Kamala"
    ],
    "name:tel_x_preferred":[
        "\u0c15\u0c2e\u0c32"
    ],
    "wof:name":"Kamala",
    "wof:placetype":"locality"
},
  "geometry": {"coordinates":[78.52464000000001,29.10209],"type":"Point"}
}