{
  "type": "Feature",
  "properties": {
    "iso:country":"IN",
    "ks:ks_name":"Oddipalle",
    "ks:ks_pop":97,
    "ks:ks_type":"HABITATION",
    "name:eng_x_preferred":[
        "Oddipalle"
    ],
    "wof:name":"Oddipalle",
    "wof:placetype":"locality",
    "wof:population":97
},
  "geometry": {"coordinates":[78.445637,13.78764],"type":"Point"}
}