{
  "type": "Feature",
  "properties": {
    "gn:admin1_code":"9.0",
    "gn:admin2_code":"492",
    "gn:asciiname":"Ghodbar",
    "gn:country_code":"IN",
    "gn:dem":113,
    "gn:feature_class":"P",
    "gn:feature_code":"PPL",
    "gn:name":"Ghodb\u0101r",
    "gn:population":0,
    "gn:timezone":"Asia/Kolkata",
    "iso:country":"IN",
    "wof:name":"Ghodbar",
    "wof:placetype":"locality"
},
  "geometry": {"coordinates":[73.30533,21.42023],"type":"Point"}
}