{
  "type": "Feature",
  "properties": {
    "gn:admin1_code":"19.0",
    "gn:admin2_code":"581.0",
    "gn:asciiname":"Tirumalhatti",
    "gn:country_code":"IN",
    "gn:dem":858,
    "gn:feature_class":"P",
    "gn:feature_code":"PPL",
    "gn:name":"Tirumalhatti",
    "gn:population":0,
    "gn:timezone":"Asia/Kolkata",
    "iso:country":"IN",
    "wof:name":"Tirumalhatti",
    "wof:placetype":"locality"
},
  "geometry": {"coordinates":[78.00556999999998,12.95878],"type":"Point"}
}