{
  "type": "Feature",
  "properties": {
    "gn:admin1_code":"35",
    "gn:admin2_code":"442.0",
    "gn:asciiname":"Patan Kalan",
    "gn:country_code":"IN",
    "gn:dem":391,
    "gn:feature_class":"P",
    "gn:feature_code":"PPL",
    "gn:name":"P\u0101tan Kal\u0101n",
    "gn:population":0,
    "gn:timezone":"Asia/Kolkata",
    "iso:country":"IN",
    "name:und_x_variant":[
        "P\u0101tan",
        "P\u0101tan Kal\u0101n"
    ],
    "wof:name":"Patan Kalan",
    "wof:placetype":"locality"
},
  "geometry": {"coordinates":[76.74039999999999,23.97391],"type":"Point"}
}