{
  "type": "Feature",
  "properties": {
    "iso:country":"IN",
    "ks:ks_name":"Mahendrapura",
    "ks:ks_pop":56,
    "ks:ks_type":"HABITATION",
    "name:eng_x_preferred":[
        "Mahendrapura"
    ],
    "wof:name":"Mahendrapura",
    "wof:placetype":"locality",
    "wof:population":56
},
  "geometry": {"coordinates":[71.18507200000001,25.613478],"type":"Point"}
}