{
  "type": "Feature",
  "properties": {
    "gn:admin1_code":"36",
    "gn:admin2_code":"145.0",
    "gn:asciiname":"Nagla Garhiasipa",
    "gn:country_code":"IN",
    "gn:dem":182,
    "gn:feature_class":"P",
    "gn:feature_code":"PPL",
    "gn:name":"Nagla Garhi\u0101sipa",
    "gn:population":0,
    "gn:timezone":"Asia/Kolkata",
    "iso:country":"IN",
    "wof:name":"Nagla Garhiasipa",
    "wof:placetype":"locality"
},
  "geometry": {"coordinates":[77.50351999999999,27.44353],"type":"Point"}
}