{
  "type": "Feature",
  "properties": {
    "gn:admin1_code":"34.0",
    "gn:admin2_code":"238.0",
    "gn:asciiname":"Ganesh Nawada",
    "gn:country_code":"IN",
    "gn:dem":70,
    "gn:feature_class":"P",
    "gn:feature_code":"PPL",
    "gn:name":"Ganesh Naw\u0101da",
    "gn:population":0,
    "gn:timezone":"Asia/Kolkata",
    "iso:country":"IN",
    "wof:name":"Ganesh Nawada",
    "wof:placetype":"locality"
},
  "geometry": {"coordinates":[86.12495,24.96138],"type":"Point"}
}