{
  "type": "Feature",
  "properties": {
    "iso:country":"IN",
    "ks:ks_name":"Beede",
    "ks:ks_pop":78,
    "ks:ks_type":"HABITATION",
    "name:eng_x_preferred":[
        "Beede"
    ],
    "wof:name":"Beede",
    "wof:placetype":"locality",
    "wof:population":78
},
  "geometry": {"coordinates":[75.22013699999999,13.829694],"type":"Point"}
}