{
  "type": "Feature",
  "properties": {
    "gn:admin1_code":"36",
    "gn:admin2_code":"200.0",
    "gn:asciiname":"Basuhari",
    "gn:country_code":"IN",
    "gn:dem":154,
    "gn:feature_class":"P",
    "gn:feature_code":"PPL",
    "gn:name":"Basuh\u0101ri",
    "gn:population":0,
    "gn:timezone":"Asia/Kolkata",
    "iso:country":"IN",
    "ks:ks_name":"Bashuhari",
    "ks:ks_pop":300,
    "ks:ks_type":"HABITATION",
    "name:eng_x_preferred":[
        "Bashuhari"
    ],
    "name:eng_x_variant":[
        "Basuhari"
    ],
    "wof:name":"Bashuhari",
    "wof:placetype":"locality",
    "wof:population":300
},
  "geometry": {"coordinates":[83.464719,24.523206],"type":"Point"}
}