{
  "type": "Feature",
  "properties": {
    "gn:admin1_code":"35",
    "gn:admin2_code":"461.0",
    "gn:asciiname":"Venkatnagar",
    "gn:country_code":"IN",
    "gn:dem":552,
    "gn:feature_class":"P",
    "gn:feature_code":"PPL",
    "gn:name":"Venkatnagar",
    "gn:population":0,
    "gn:timezone":"Asia/Kolkata",
    "iso:country":"IN",
    "wof:name":"Venkatnagar",
    "wof:placetype":"locality"
},
  "geometry": {"coordinates":[81.87468,22.92507],"type":"Point"}
}