{
  "type": "Feature",
  "properties": {
    "gn:admin1_code":"16.0",
    "gn:admin2_code":"509.0",
    "gn:asciiname":"Dudholi",
    "gn:country_code":"IN",
    "gn:dem":172,
    "gn:feature_class":"P",
    "gn:feature_code":"PPL",
    "gn:name":"Dudhol\u012b",
    "gn:population":0,
    "gn:timezone":"Asia/Kolkata",
    "iso:country":"IN",
    "name:und_x_variant":[
        "Dudhol\u012b",
        "Dudholi"
    ],
    "wof:name":"Dudholi",
    "wof:placetype":"locality"
},
  "geometry": {"coordinates":[79.37348,19.8159],"type":"Point"}
}