{
  "type": "Feature",
  "properties": {
    "iso:country":"IN",
    "ks:ks_name":"Nischintapur",
    "ks:ks_pop":289,
    "ks:ks_type":"VILLAGE",
    "name:eng_x_preferred":[
        "Nischintapur"
    ],
    "wof:name":"Nischintapur",
    "wof:placetype":"locality",
    "wof:population":289
},
  "geometry": {"coordinates":[87.57683900000001,22.651878],"type":"Point"}
}