{
  "type": "Feature",
  "properties": {
    "iso:country":"IN",
    "ks:ks_name":"Kuppanagoundenvalasu",
    "ks:ks_pop":115,
    "ks:ks_type":"HABITATION",
    "name:eng_x_preferred":[
        "Kuppanagoundenvalasu"
    ],
    "wof:name":"Kuppanagoundenvalasu",
    "wof:placetype":"locality",
    "wof:population":115
},
  "geometry": {"coordinates":[77.629724,10.666915],"type":"Point"}
}