{
  "type": "Feature",
  "properties": {
    "iso:country":"IN",
    "ks:ks_name":"Madvarpur Khas",
    "ks:ks_pop":180,
    "ks:ks_type":"HABITATION",
    "ks:ks_uagg_main":0,
    "name:eng_x_preferred":[
        "Madvarpur Khas"
    ],
    "wof:name":"Madvarpur Khas",
    "wof:placetype":"neighbourhood",
    "wof:population":180
},
  "geometry": {"coordinates":[82.85498699999999,26.173383],"type":"Point"}
}