{
  "type": "Feature",
  "properties": {
    "iso:country":"IN",
    "ks:ks_name":"Ethadaka",
    "ks:ks_pop":135,
    "ks:ks_type":"HABITATION",
    "name:eng_x_preferred":[
        "Ethadaka"
    ],
    "wof:name":"Ethadaka",
    "wof:placetype":"locality",
    "wof:population":135
},
  "geometry": {"coordinates":[75.84916699999999,12.434444],"type":"Point"}
}