{
  "type": "Feature",
  "properties": {
    "iso:country":"IN",
    "ks:ks_name":"Niraballa",
    "ks:ks_pop":35,
    "ks:ks_type":"HABITATION",
    "name:eng_x_preferred":[
        "Niraballa"
    ],
    "wof:name":"Niraballa",
    "wof:placetype":"locality",
    "wof:population":35
},
  "geometry": {"coordinates":[75.31737200000001,12.556459],"type":"Point"}
}