{
  "type": "Feature",
  "properties": {
    "gn:admin1_code":"28.0",
    "gn:admin2_code":"329.0",
    "gn:asciiname":"Sajerpar Ghoramara",
    "gn:country_code":"IN",
    "gn:dem":55,
    "gn:feature_class":"P",
    "gn:feature_code":"PPL",
    "gn:name":"Sajerpar Ghoramara",
    "gn:population":0,
    "gn:timezone":"Asia/Kolkata",
    "iso:country":"IN",
    "ks:ks_name":"Sajherpar Ghoramara",
    "ks:ks_pop":5171,
    "ks:ks_type":"VILLAGE",
    "ks:ks_uagg_main":0,
    "name:eng_x_preferred":[
        "Sajherpar Ghoramara"
    ],
    "wof:name":"Sajherpar Ghoramara",
    "wof:placetype":"locality",
    "wof:population":5171
},
  "geometry": {"coordinates":[89.34302700000001,26.419198],"type":"Point"}
}