{
  "type": "Feature",
  "properties": {
    "iso:country":"IN",
    "ks:ks_alt_nam":"LATIDIH",
    "ks:ks_name":"Latidih",
    "ks:ks_pop":204,
    "ks:ks_type":"HABITATION",
    "name:eng_x_preferred":[
        "Latidih"
    ],
    "wof:name":"Latidih",
    "wof:placetype":"locality",
    "wof:population":204
},
  "geometry": {"coordinates":[83.315709,22.862458],"type":"Point"}
}