{
  "type": "Feature",
  "properties": {
    "iso:country":"IN",
    "ks:ks_alt_nam":"St Marys School jn",
    "ks:ks_name":"St Marys School Jn",
    "ks:ks_pop":5404,
    "ks:ks_type":"HABITATION",
    "name:eng_x_preferred":[
        "St Marys School Jn"
    ],
    "wof:name":"St Marys School Jn",
    "wof:placetype":"locality",
    "wof:population":5404
},
  "geometry": {"coordinates":[76.416684,9.765947],"type":"Point"}
}