{
  "type": "Feature",
  "properties": {
    "iso:country":"IN",
    "ks:ks_name":"Baghpada",
    "ks:ks_pop":147,
    "ks:ks_type":"HABITATION",
    "name:eng_x_preferred":[
        "Baghpada"
    ],
    "wof:name":"Baghpada",
    "wof:placetype":"locality",
    "wof:population":147
},
  "geometry": {"coordinates":[82.41219599999999,19.862829],"type":"Point"}
}