{
  "type": "Feature",
  "properties": {
    "iso:country":"IN",
    "ks:ks_name":"Banjari",
    "ks:ks_pop":28,
    "ks:ks_type":"HABITATION",
    "name:eng_x_preferred":[
        "Banjari"
    ],
    "wof:name":"Banjari",
    "wof:placetype":"locality",
    "wof:population":28
},
  "geometry": {"coordinates":[81.10662000000001,22.151563],"type":"Point"}
}