{
  "type": "Feature",
  "properties": {
    "iso:country":"IN",
    "ks:ks_name":"Tulasipur",
    "ks:ks_pop":521,
    "ks:ks_type":"VILLAGE",
    "ks:ks_uagg_main":0,
    "name:eng_x_preferred":[
        "Tulasipur"
    ],
    "wof:name":"Tulasipur",
    "wof:placetype":"neighbourhood",
    "wof:population":521
},
  "geometry": {"coordinates":[86.14608200000001,20.857129],"type":"Point"}
}