{
  "type": "Feature",
  "properties": {
    "iso:country":"IN",
    "ks:ks_alt_nam":"NANI DAS PARA",
    "ks:ks_name":"Nani Das Para",
    "ks:ks_pop":166,
    "ks:ks_type":"HABITATION",
    "name:eng_x_preferred":[
        "Nani Das Para"
    ],
    "wof:name":"Nani Das Para",
    "wof:placetype":"locality",
    "wof:population":166
},
  "geometry": {"coordinates":[91.206586,23.691712],"type":"Point"}
}