{
  "type": "Feature",
  "properties": {
    "gn:admin1_code":"37",
    "gn:admin2_code":"403.0",
    "gn:asciiname":"Sondika",
    "gn:country_code":"IN",
    "gn:dem":259,
    "gn:feature_class":"P",
    "gn:feature_code":"PPL",
    "gn:name":"Sondika",
    "gn:population":0,
    "gn:timezone":"Asia/Kolkata",
    "iso:country":"IN",
    "ks:ks_name":"Sondika",
    "ks:ks_type":"VILLAGE",
    "name:ara_x_preferred":[
        "\u0633\u0648\u0646\u062f\u0627\u064a\u0643\u0627"
    ],
    "name:arg_x_preferred":[
        "Sondika"
    ],
    "name:ast_x_preferred":[
        "Sondika"
    ],
    "name:cat_x_preferred":[
        "Sondika"
    ],
    "name:ceb_x_preferred":[
        "Sondika"
    ],
    "name:eng_x_preferred":[
        "Sondika"
    ],
    "name:eus_x_preferred":[
        "Sondika"
    ],
    "name:fra_x_preferred":[
        "Sondika"
    ],
    "name:glg_x_preferred":[
        "Sondika"
    ],
    "name:hun_x_preferred":[
        "Sondika"
    ],
    "name:ita_x_preferred":[
        "Sondika"
    ],
    "name:lat_x_preferred":[
        "Sondica"
    ],
    "name:msa_x_preferred":[
        "Sondika"
    ],
    "name:nld_x_preferred":[
        "Sondika"
    ],
    "name:oci_x_preferred":[
        "Sondika"
    ],
    "name:pol_x_preferred":[
        "Sondika"
    ],
    "name:por_x_preferred":[
        "Sondica"
    ],
    "name:rus_x_preferred":[
        "\u0421\u043e\u043d\u0434\u0438\u043a\u0430"
    ],
    "name:sco_x_preferred":[
        "Sondika"
    ],
    "name:spa_x_preferred":[
        "Sondica"
    ],
    "name:swe_x_preferred":[
        "Sondika"
    ],
    "name:ukr_x_preferred":[
        "\u0421\u043e\u043d\u0434\u0456\u043a\u0430"
    ],
    "name:uzb_x_preferred":[
        "Sondica"
    ],
    "name:war_x_preferred":[
        "Sondika"
    ],
    "name:zho_x_preferred":[
        "\u677e\u8fea\u5361"
    ],
    "wof:name":"Sondika",
    "wof:placetype":"locality"
},
  "geometry": {"coordinates":[83.02952399999999,21.547753],"type":"Point"}
}