{
  "type": "Feature",
  "properties": {
    "gn:admin1_code":"37",
    "gn:admin2_code":"403.0",
    "gn:asciiname":"Sondika",
    "gn:country_code":"IN",
    "gn:dem":259,
    "gn:feature_class":"P",
    "gn:feature_code":"PPL",
    "gn:name":"Sondika",
    "gn:population":0,
    "gn:timezone":"Asia/Kolkata",
    "iso:country":"IN",
    "wof:name":"Sondika",
    "wof:placetype":"locality"
},
  "geometry": {"coordinates":[83.02951999999998,21.54775],"type":"Point"}
}