{
  "type": "Feature",
  "properties": {
    "iso:country":"IN",
    "ks:ks_name":"Nagla Tonta",
    "ks:ks_pop":338,
    "ks:ks_type":"HABITATION",
    "ks:ks_uagg_main":0,
    "name:eng_x_preferred":[
        "Nagla Tonta"
    ],
    "wof:name":"Nagla Tonta",
    "wof:placetype":"neighbourhood",
    "wof:population":338
},
  "geometry": {"coordinates":[78.357563,27.693898],"type":"Point"}
}