{
  "type": "Feature",
  "properties": {
    "gn:admin1_code":"09",
    "gn:admin2_code":"479.0",
    "gn:asciiname":"Lungiya",
    "gn:country_code":"IN",
    "gn:dem":196,
    "gn:feature_class":"P",
    "gn:feature_code":"PPL",
    "gn:name":"Lungiya",
    "gn:population":0,
    "gn:timezone":"Asia/Kolkata",
    "iso:country":"IN",
    "wof:name":"Lungiya",
    "wof:placetype":"locality"
},
  "geometry": {"coordinates":[70.92604,21.40643],"type":"Point"}
}