{
  "type": "Feature",
  "properties": {
    "iso:country":"IN",
    "ks:ks_name":"Gurujubaviguda",
    "ks:ks_pop":36,
    "ks:ks_type":"HABITATION",
    "name:eng_x_preferred":[
        "Gurujubaviguda"
    ],
    "wof:name":"Gurujubaviguda",
    "wof:placetype":"locality",
    "wof:population":36
},
  "geometry": {"coordinates":[79.2362,17.326843],"type":"Point"}
}