{
  "type": "Feature",
  "properties": {
    "iso:country":"IN",
    "ks:ks_name":"Chinna Muhilthagam",
    "ks:ks_pop":170,
    "ks:ks_type":"HABITATION",
    "name:eng_x_preferred":[
        "Chinna Muhilthagam"
    ],
    "wof:name":"Chinna Muhilthagam",
    "wof:placetype":"locality",
    "wof:population":170
},
  "geometry": {"coordinates":[78.988652,9.738101],"type":"Point"}
}