{
  "type": "Feature",
  "properties": {
    "gn:admin1_code":"34.0",
    "gn:admin2_code":"210.0",
    "gn:asciiname":"Anarkali",
    "gn:country_code":"IN",
    "gn:dem":52,
    "gn:feature_class":"P",
    "gn:feature_code":"PPL",
    "gn:name":"An\u0101rkali",
    "gn:population":0,
    "gn:timezone":"Asia/Kolkata",
    "iso:country":"IN",
    "name:ara_x_preferred":[
        "\u0623\u0646\u0627\u0631\u0643\u0644\u064a"
    ],
    "name:ben_x_preferred":[
        "\u0986\u09a8\u09be\u09b0\u0995\u09b2\u09bf"
    ],
    "name:fas_x_preferred":[
        "\u0627\u0646\u0627\u0631\u06a9\u0644\u06cc"
    ],
    "name:hin_x_preferred":[
        "\u0905\u0928\u093e\u0930\u0915\u0932\u0940"
    ],
    "name:mal_x_preferred":[
        "\u0d05\u0d28\u0d3e\u0d7c\u0d15\u0d4d\u0d15\u0d32\u0d3f"
    ],
    "name:mar_x_preferred":[
        "\u0905\u0928\u093e\u0930\u0915\u0932\u0940"
    ],
    "name:nep_x_preferred":[
        "\u0905\u0928\u093e\u0930\u0915\u0932\u0940"
    ],
    "name:pan_x_preferred":[
        "\u0a05\u0a28\u0a3e\u0a30\u0a15\u0a32\u0a40"
    ],
    "name:pnb_x_preferred":[
        "\u0627\u0646\u0627\u0631\u06a9\u0644\u06cc"
    ],
    "name:sin_x_preferred":[
        "\u0d85\u0db1\u0dcf\u0dbb\u0dca\u0d9a\u0dbd\u0dd3"
    ],
    "name:snd_x_preferred":[
        "\u0627\u0646\u0627\u0631\u06aa\u0644\u064a"
    ],
    "name:spa_x_preferred":[
        "Anarkali"
    ],
    "name:tam_x_preferred":[
        "\u0b85\u0ba9\u0bbe\u0bb0\u0bcd\u0b95\u0bcd\u0b95\u0bb2\u0bbf"
    ],
    "name:urd_x_preferred":[
        "\u0627\u0646\u0627\u0631\u06a9\u0644\u06cc"
    ],
    "wof:name":"Anarkali",
    "wof:placetype":"locality"
},
  "geometry": {"coordinates":[87.82225,26.16473],"type":"Point"}
}