{
  "type": "Feature",
  "properties": {
    "iso:country":"IN",
    "ks:ks_name":"Kamar Gram",
    "ks:ks_pop":1642,
    "ks:ks_type":"VILLAGE",
    "ks:ks_uagg_main":0,
    "name:eng_x_preferred":[
        "Kamar Gram"
    ],
    "wof:name":"Kamar Gram",
    "wof:placetype":"neighbourhood",
    "wof:population":1642
},
  "geometry": {"coordinates":[92.42586300000001,24.765435],"type":"Point"}
}