{
  "type": "Feature",
  "properties": {
    "iso:country":"IN",
    "ks:ks_name":"Juritand",
    "ks:ks_pop":104,
    "ks:ks_type":"VILLAGE",
    "name:eng_x_preferred":[
        "Juritand"
    ],
    "wof:name":"Juritand",
    "wof:placetype":"locality",
    "wof:population":104
},
  "geometry": {"coordinates":[85.996602,22.810796],"type":"Point"}
}