{
  "type": "Feature",
  "properties": {
    "iso:country":"IN",
    "ks:ks_name":"Dodum",
    "ks:ks_pop":113,
    "ks:ks_type":"VILLAGE",
    "name:eng_x_preferred":[
        "Dodum"
    ],
    "wof:name":"Dodum",
    "wof:placetype":"locality",
    "wof:population":113
},
  "geometry": {"coordinates":[80.906672,19.107111],"type":"Point"}
}