{
  "type": "Feature",
  "properties": {
    "iso:country":"IN",
    "name:eng_x_preferred":[
        "Vidyanagar Colony"
    ],
    "qs:gn_adm0_cc":"IN",
    "qs:gn_local":1253367,
    "qs:gn_nam_loc":"vasco da gama",
    "qs:gn_namadm1":"33",
    "qs:local_max":318,
    "qs:local_sum":767,
    "qs:localhoods":5,
    "qs:name":"Vidyanagar Colony",
    "qs:name_adm0":"India",
    "qs:name_adm1":"Goa",
    "qs:name_adm2":"South Goa",
    "qs:name_local":"Vasco Da Gama",
    "qs:photo_max":175,
    "qs:photo_sum":282,
    "qs:placetype":"Suburb",
    "qs:quad_count":10,
    "qs:woe_adm0":23424848,
    "qs:woe_adm1":2345764,
    "qs:woe_adm2":12586828,
    "qs:woe_lau":0,
    "qs:woe_local":2288122,
    "qs:woe_ver":"7.10.0",
    "wof:lang":[
        "eng"
    ],
    "wof:name":"Vidyanagar Colony",
    "wof:placetype":"neighbourhood"
},
  "geometry": {"coordinates":[73.877228,15.391396],"type":"Point"}
}