{
  "type": "Feature",
  "properties": {
    "iso:country":"IN",
    "name:ara_x_preferred":[
        "\u0645\u0633\u062a\u0639\u0645\u0631\u0629 \u0641\u064a\u062c\u0627\u064a\u0627 \u0646\u0627\u062c\u0627\u0631"
    ],
    "name:ben_bn_x_preferred":[
        "\u09ac\u09bf\u09a6\u09cd\u09af\u09be\u09a8\u0997\u09b0 \u0995\u09b2\u09cb\u09a8\u09c0"
    ],
    "name:ben_in_x_preferred":[
        "\u09ac\u09bf\u09a6\u09cd\u09af\u09be\u09a8\u0997\u09b0 \u0995\u09b2\u09cb\u09a8\u09c0"
    ],
    "name:eng_x_preferred":[
        "Vidyanagar Colony"
    ],
    "name:guj_x_preferred":[
        "\u0ab5\u0abf\u0a9c\u0aaf\u0aa8\u0a97\u0ab0 \u0a95\u0acb\u0ab2\u0acb\u0aa8\u0ac0"
    ],
    "name:hin_x_preferred":[
        "\u0935\u093f\u0926\u094d\u092f\u093e\u0928\u0917\u0930 \u0915\u0949\u0932\u094b\u0928\u0940"
    ],
    "name:kan_x_preferred":[
        "\u0cb5\u0cbf\u0ca6\u0ccd\u0caf\u0cbe\u0ca8\u0c97\u0cb0 \u0c95\u0cbe\u0cb2\u0cca\u0ca8\u0cbf"
    ],
    "name:mal_x_preferred":[
        "\u0d35\u0d3f\u0d1c\u0d2f\u0d28\u0d17\u0d30\u0d4d"
    ],
    "name:mar_x_preferred":[
        "\u0935\u093f\u0926\u094d\u092f\u093e\u0928\u0917\u0930 \u0915\u0949\u0932\u0928\u0940"
    ],
    "name:pan_x_preferred":[
        "\u0a35\u0a3f\u0a26\u0a3f\u0a06\u0a28\u0a17\u0a30 \u0a15\u0a32\u0a4c\u0a28\u0a40"
    ],
    "name:tam_x_preferred":[
        "\u0bb5\u0bbf\u0ba4\u0bcd\u0baf\u0bbe\u0ba8\u0b95\u0bb0\u0bcd \u0b95\u0bc1\u0b9f\u0bbf\u0baf\u0bbf\u0bb0\u0bc1\u0baa\u0bcd\u0baa\u0bc1"
    ],
    "name:tel_x_preferred":[
        "\u0c35\u0c3f\u0c1c\u0c2f\u0c28\u0c17\u0c30\u0c4d \u0c15\u0c3e\u0c32\u0c28\u0c40"
    ],
    "name:urd_x_preferred":[
        "\u0648\u062f\u06cc\u0627 \u0646\u06af\u0631 \u06a9\u0627\u0644\u0648\u0646\u06cc"
    ],
    "qs:gn_adm0_cc":"IN",
    "qs:gn_local":1253367,
    "qs:gn_nam_loc":"vasco da gama",
    "qs:gn_namadm1":"33",
    "qs:local_max":318,
    "qs:local_sum":767,
    "qs:localhoods":5,
    "qs:name":"Vidyanagar Colony",
    "qs:name_adm0":"India",
    "qs:name_adm1":"Goa",
    "qs:name_adm2":"South Goa",
    "qs:name_local":"Vasco Da Gama",
    "qs:photo_max":175,
    "qs:photo_sum":282,
    "qs:placetype":"Suburb",
    "qs:quad_count":10,
    "qs:woe_adm0":23424848,
    "qs:woe_adm1":2345764,
    "qs:woe_adm2":12586828,
    "qs:woe_lau":0,
    "qs:woe_local":2288122,
    "qs:woe_ver":"7.10.0",
    "wof:lang":[
        "eng"
    ],
    "wof:name":"Vidyanagar Colony",
    "wof:placetype":"neighbourhood"
},
  "geometry": {"coordinates":[73.877228,15.391396],"type":"Point"}
}