{
  "type": "Feature",
  "properties": {
    "iso:country":"IN",
    "ks:ks_name":"Bagh Purwa",
    "ks:ks_pop":61,
    "ks:ks_type":"HABITATION",
    "name:eng_x_preferred":[
        "Bagh Purwa"
    ],
    "wof:name":"Bagh Purwa",
    "wof:placetype":"locality",
    "wof:population":61
},
  "geometry": {"coordinates":[79.714277,27.027977],"type":"Point"}
}