{
  "type": "Feature",
  "properties": {
    "iso:country":"IN",
    "ks:ks_name":"Nalemaradu",
    "ks:ks_pop":35,
    "ks:ks_type":"HABITATION",
    "name:eng_x_preferred":[
        "Nalemaradu"
    ],
    "wof:name":"Nalemaradu",
    "wof:placetype":"locality",
    "wof:population":35
},
  "geometry": {"coordinates":[75.171671,13.773356],"type":"Point"}
}