{
  "type": "Feature",
  "properties": {
    "gn:admin1_code":"36.0",
    "gn:admin2_code":"164.0",
    "gn:asciiname":"Bagha",
    "gn:country_code":"IN",
    "gn:dem":130,
    "gn:feature_class":"P",
    "gn:feature_code":"PPL",
    "gn:name":"Bagha",
    "gn:population":0,
    "gn:timezone":"Asia/Kolkata",
    "iso:country":"IN",
    "wof:name":"Bagha",
    "wof:placetype":"locality"
},
  "geometry": {"coordinates":[80.25948000000002,26.35916],"type":"Point"}
}