{
  "type": "Feature",
  "properties": {
    "iso:country":"IN",
    "ks:ks_name":"Bijiliguda",
    "ks:ks_pop":24,
    "ks:ks_type":"HABITATION",
    "name:eng_x_preferred":[
        "Bijiliguda"
    ],
    "wof:name":"Bijiliguda",
    "wof:placetype":"locality",
    "wof:population":24
},
  "geometry": {"coordinates":[78.93693,19.269939],"type":"Point"}
}