{
  "type": "Feature",
  "properties": {
    "gn:admin1_code":"19.0",
    "gn:admin2_code":"567.0",
    "gn:asciiname":"Ayyanahalli",
    "gn:country_code":"IN",
    "gn:dem":706,
    "gn:feature_class":"P",
    "gn:feature_code":"PPL",
    "gn:name":"Ayyanahalli",
    "gn:population":0,
    "gn:timezone":"Asia/Kolkata",
    "iso:country":"IN",
    "wof:name":"Ayyanahalli",
    "wof:placetype":"locality"
},
  "geometry": {"coordinates":[76.26479999999999,14.53489],"type":"Point"}
}