{
  "type": "Feature",
  "properties": {
    "iso:country":"IN",
    "ks:ks_name":"Tadakapalle",
    "ks:ks_pop":159,
    "ks:ks_type":"VILLAGE",
    "name:eng_x_preferred":[
        "Tadakapalle"
    ],
    "wof:name":"Tadakapalle",
    "wof:placetype":"locality",
    "wof:population":159
},
  "geometry": {"coordinates":[82.226704,17.955392],"type":"Point"}
}