{
  "type": "Feature",
  "properties": {
    "iso:country":"IN",
    "ks:ks_name":"Mudikheda",
    "ks:ks_pop":117,
    "ks:ks_type":"VILLAGE",
    "name:eng_x_preferred":[
        "Mudikheda"
    ],
    "wof:name":"Mudikheda",
    "wof:placetype":"locality",
    "wof:population":117
},
  "geometry": {"coordinates":[80.42687100000001,23.423247],"type":"Point"}
}