{
  "type": "Feature",
  "properties": {
    "gn:admin1_code":"38.0",
    "gn:admin2_code":"352.0",
    "gn:asciiname":"Partutola",
    "gn:country_code":"IN",
    "gn:dem":151,
    "gn:feature_class":"P",
    "gn:feature_code":"PPL",
    "gn:name":"Partutola",
    "gn:population":0,
    "gn:timezone":"Asia/Kolkata",
    "iso:country":"IN",
    "ks:ks_name":"Partu Tola",
    "ks:ks_pop":121,
    "ks:ks_type":"VILLAGE",
    "name:eng_x_preferred":[
        "Partu Tola"
    ],
    "name:eng_x_variant":[
        "Partutola"
    ],
    "wof:name":"Partu Tola",
    "wof:placetype":"locality",
    "wof:population":121
},
  "geometry": {"coordinates":[87.59742799999999,25.143501],"type":"Point"}
}