{
  "type": "Feature",
  "properties": {
    "gn:admin1_code":"11",
    "gn:admin2_code":"34.0",
    "gn:asciiname":"Yangpa",
    "gn:country_code":"IN",
    "gn:dem":2679,
    "gn:feature_class":"P",
    "gn:feature_code":"PPL",
    "gn:name":"Y\u0101ngpa",
    "gn:population":0,
    "gn:timezone":"Asia/Kolkata",
    "iso:country":"IN",
    "name:dan_x_preferred":[
        "Yangpa"
    ],
    "name:fra_x_preferred":[
        "Yangpa"
    ],
    "name:kor_x_preferred":[
        "\uc591\ud30c"
    ],
    "name:spa_x_preferred":[
        "Yangpa"
    ],
    "name:tgl_x_preferred":[
        "Yangpa"
    ],
    "name:und_x_variant":[
        "Y\u0101ngpa"
    ],
    "name:zho_x_preferred":[
        "Yangpa"
    ],
    "wof:name":"Yangpa",
    "wof:placetype":"locality"
},
  "geometry": {"coordinates":[78.03386999999999,31.61486],"type":"Point"}
}