{
  "type": "Feature",
  "properties": {
    "iso:country":"IN",
    "ks:ks_alt_nam":"ANDAROO KA PURA",
    "ks:ks_name":"Andaroo Ka Pura",
    "ks:ks_pop":27,
    "ks:ks_type":"HABITATION",
    "ks:ks_uagg_main":0,
    "name:eng_x_preferred":[
        "Andaroo Ka Pura"
    ],
    "wof:name":"Andaroo Ka Pura",
    "wof:placetype":"neighbourhood",
    "wof:population":27
},
  "geometry": {"coordinates":[81.671527,26.344796],"type":"Point"}
}