{
  "type": "Feature",
  "properties": {
    "gn:admin1_code":"23.0",
    "gn:admin2_code":"35.0",
    "gn:asciiname":"Jagatpur",
    "gn:country_code":"IN",
    "gn:dem":274,
    "gn:feature_class":"P",
    "gn:feature_code":"PPL",
    "gn:name":"Jagatpur",
    "gn:population":0,
    "gn:timezone":"Asia/Kolkata",
    "iso:country":"IN",
    "name:ara_x_preferred":[
        "\u062c\u0627\u062c\u062a\u0628\u0648\u0631"
    ],
    "name:ben_bn_x_preferred":[
        "\u099c\u0997\u09ce\u09aa\u09c1\u09b0"
    ],
    "name:ben_in_x_preferred":[
        "\u099c\u0997\u09ce\u09aa\u09c1\u09b0"
    ],
    "name:ceb_x_preferred":[
        "Jagatpur"
    ],
    "name:guj_x_preferred":[
        "\u0a9c\u0a97\u0aa4\u0aaa\u0ac1\u0ab0"
    ],
    "name:hin_x_preferred":[
        "\u091c\u0917\u0924\u092a\u0941\u0930"
    ],
    "name:kan_x_preferred":[
        "\u0c9c\u0c97\u0ca4\u0ccd"
    ],
    "name:mal_x_preferred":[
        "\u0d1c\u0d17\u0d24\u0d4d\u0d2a\u0d42\u0d7c"
    ],
    "name:mar_x_preferred":[
        "\u091c\u0917\u0924\u092a\u0942\u0930"
    ],
    "name:pan_x_preferred":[
        "\u0a1c\u0a17\u0a24\u0a2a\u0a41\u0a30"
    ],
    "name:pol_x_preferred":[
        "Jagatpur"
    ],
    "name:swe_x_preferred":[
        "Jagatpur"
    ],
    "name:tam_x_preferred":[
        "\u0b9c\u0b95\u0ba4\u0bcd\u0baa\u0bc2\u0bb0\u0bcd"
    ],
    "name:tel_x_preferred":[
        "\u0c1c\u0c17\u0c24\u0c4d"
    ],
    "name:urd_x_preferred":[
        "\u062c\u06af\u062a \u067e\u0648\u0631"
    ],
    "wof:name":"Jagatpur",
    "wof:placetype":"locality"
},
  "geometry": {"coordinates":[75.52648000000001,32.19485],"type":"Point"}
}