{
  "type": "Feature",
  "properties": {
    "iso:country":"IN",
    "ks:ks_alt_nam":"Eram jn",
    "ks:ks_name":"Eram Jn",
    "ks:ks_pop":860,
    "ks:ks_type":"HABITATION",
    "name:eng_x_preferred":[
        "Eram Jn"
    ],
    "wof:name":"Eram Jn",
    "wof:placetype":"locality",
    "wof:population":860
},
  "geometry": {"coordinates":[76.892326,8.948442],"type":"Point"}
}