{
  "type": "Feature",
  "properties": {
    "iso:country":"IN",
    "ks:ks_name":"Dhulapwadi",
    "ks:ks_pop":91,
    "ks:ks_type":"HABITATION",
    "name:eng_x_preferred":[
        "Dhulapwadi"
    ],
    "wof:name":"Dhulapwadi",
    "wof:placetype":"locality",
    "wof:population":91
},
  "geometry": {"coordinates":[73.43616400000001,17.686036],"type":"Point"}
}