{
  "type": "Feature",
  "properties": {
    "iso:country":"IN",
    "ks:ks_name":"Rasyun",
    "ks:ks_pop":196,
    "ks:ks_type":"VILLAGE",
    "name:eng_x_preferred":[
        "Rasyun"
    ],
    "wof:name":"Rasyun",
    "wof:placetype":"locality",
    "wof:population":196
},
  "geometry": {"coordinates":[80.042393,29.545004],"type":"Point"}
}