{
  "type": "Feature",
  "properties": {
    "iso:country":"IN",
    "ks:ks_name":"Angariya",
    "ks:ks_pop":273,
    "ks:ks_type":"VILLAGE",
    "name:eng_x_preferred":[
        "Angariya"
    ],
    "wof:name":"Angariya",
    "wof:placetype":"locality",
    "wof:population":273
},
  "geometry": {"coordinates":[85.37664700000001,22.812563],"type":"Point"}
}