{
  "type": "Feature",
  "properties": {
    "gn:admin1_code":"36",
    "gn:admin2_code":"154.0",
    "gn:asciiname":"Hatia Upri",
    "gn:country_code":"IN",
    "gn:dem":139,
    "gn:feature_class":"P",
    "gn:feature_code":"PPL",
    "gn:name":"Hatia Upri",
    "gn:population":0,
    "gn:timezone":"Asia/Kolkata",
    "iso:country":"IN",
    "ks:ks_name":"Hatia Upri",
    "ks:ks_type":"VILLAGE",
    "name:eng_x_preferred":[
        "Hatia Upri"
    ],
    "wof:name":"Hatia Upri",
    "wof:placetype":"locality"
},
  "geometry": {"coordinates":[80.912699,27.723706],"type":"Point"}
}