{
  "type": "Feature",
  "properties": {
    "gn:admin1_code":"38.0",
    "gn:admin2_code":"353.0",
    "gn:asciiname":"Ledhapara",
    "gn:country_code":"IN",
    "gn:dem":110,
    "gn:feature_class":"P",
    "gn:feature_code":"PPL",
    "gn:name":"Ledhap\u0101ra",
    "gn:population":0,
    "gn:timezone":"Asia/Kolkata",
    "iso:country":"IN",
    "ks:ks_alt_nam":"Ledhap\u0101ra",
    "ks:ks_name":"Ledhapara",
    "ks:ks_pop":198,
    "ks:ks_type":"VILLAGE",
    "name:eng_x_preferred":[
        "Ledhapara"
    ],
    "name:eng_x_variant":[
        "Ledhap\u0101ra"
    ],
    "wof:name":"Ledhapara",
    "wof:placetype":"locality",
    "wof:population":198
},
  "geometry": {"coordinates":[87.576487,24.400424],"type":"Point"}
}