{
  "type": "Feature",
  "properties": {
    "gn:admin1_code":"25.0",
    "gn:admin2_code":"611.0",
    "gn:asciiname":"Kutukati",
    "gn:country_code":"IN",
    "gn:dem":1826,
    "gn:feature_class":"P",
    "gn:feature_code":"PPL",
    "gn:name":"Kutukati",
    "gn:population":0,
    "gn:timezone":"Asia/Kolkata",
    "iso:country":"IN",
    "wof:name":"Kutukati",
    "wof:placetype":"neighbourhood"
},
  "geometry": {"coordinates":[76.89333999999999,11.47274],"type":"Point"}
}