{
  "type": "Feature",
  "properties": {
    "gn:admin1_code":"19",
    "gn:admin2_code":"557.0",
    "gn:asciiname":"Bamanjogi",
    "gn:country_code":"IN",
    "gn:dem":507,
    "gn:feature_class":"P",
    "gn:feature_code":"PPL",
    "gn:name":"Bamanjogi",
    "gn:population":0,
    "gn:timezone":"Asia/Kolkata",
    "iso:country":"IN",
    "ks:ks_name":"Bommanjogi",
    "ks:ks_pop":2549,
    "ks:ks_type":"VILLAGE",
    "name:eng_x_preferred":[
        "Bommanjogi"
    ],
    "name:eng_x_variant":[
        "Bamanjogi"
    ],
    "wof:name":"Bommanjogi",
    "wof:placetype":"locality",
    "wof:population":2549
},
  "geometry": {"coordinates":[76.14400000000001,16.82],"type":"Point"}
}