{
  "type": "Feature",
  "properties": {
    "iso:country":"IN",
    "ks:ks_name":"Bariyahi",
    "ks:ks_pop":1327,
    "ks:ks_type":"HABITATION",
    "ks:ks_uagg_main":0,
    "name:eng_x_preferred":[
        "Bariyahi"
    ],
    "wof:name":"Bariyahi",
    "wof:placetype":"neighbourhood",
    "wof:population":1327
},
  "geometry": {"coordinates":[85.994893,25.416549],"type":"Point"}
}