{
  "type": "Feature",
  "properties": {
    "iso:country":"IN",
    "ks:ks_name":"Dongaripada",
    "ks:ks_pop":298,
    "ks:ks_type":"HABITATION",
    "name:eng_x_preferred":[
        "Dongaripada"
    ],
    "wof:name":"Dongaripada",
    "wof:placetype":"locality",
    "wof:population":298
},
  "geometry": {"coordinates":[72.709543,19.899734],"type":"Point"}
}