{
  "type": "Feature",
  "properties": {
    "gn:admin1_code":"19.0",
    "gn:admin2_code":"555.0",
    "gn:asciiname":"Madlur",
    "gn:country_code":"IN",
    "gn:dem":653,
    "gn:feature_class":"P",
    "gn:feature_code":"PPL",
    "gn:name":"Madl\u016br",
    "gn:population":0,
    "gn:timezone":"Asia/Kolkata",
    "iso:country":"IN",
    "name:urd_x_preferred":[
        "\u0645\u06cc\u0688\u0644\u0648\u0631"
    ],
    "wof:name":"Madlur",
    "wof:placetype":"neighbourhood"
},
  "geometry": {"coordinates":[75.05356999999999,15.88316],"type":"Point"}
}