{
  "type": "Feature",
  "properties": {
    "gn:admin1_code":"38.0",
    "gn:admin2_code":"347.0",
    "gn:asciiname":"Dulha",
    "gn:country_code":"IN",
    "gn:dem":434,
    "gn:feature_class":"P",
    "gn:feature_code":"PPL",
    "gn:name":"Dulha",
    "gn:population":0,
    "gn:timezone":"Asia/Kolkata",
    "iso:country":"IN",
    "ks:ks_name":"Dulha",
    "ks:ks_pop":258,
    "ks:ks_type":"VILLAGE",
    "ks:ks_uagg_main":0,
    "name:eng_x_preferred":[
        "Dulha"
    ],
    "wof:name":"Dulha",
    "wof:placetype":"neighbourhood",
    "wof:population":258
},
  "geometry": {"coordinates":[85.01276300000001,24.257886],"type":"Point"}
}