{
  "type": "Feature",
  "properties": {
    "iso:country":"IN",
    "ks:ks_name":"Boro",
    "ks:ks_pop":3456,
    "ks:ks_type":"VILLAGE",
    "ks:ks_uagg_main":0,
    "name:eng_x_preferred":[
        "Boro"
    ],
    "wof:name":"Boro",
    "wof:placetype":"locality",
    "wof:population":3456
},
  "geometry": {"coordinates":[86.281155,24.199838],"type":"Point"}
}