{
  "type": "Feature",
  "properties": {
    "gn:admin1_code":"35",
    "gn:admin2_code":"458.0",
    "gn:asciiname":"Paruwa",
    "gn:country_code":"IN",
    "gn:dem":485,
    "gn:feature_class":"P",
    "gn:feature_code":"PPL",
    "gn:name":"Paruwa",
    "gn:population":0,
    "gn:timezone":"Asia/Kolkata",
    "iso:country":"IN",
    "name:und_x_variant":[
        "Nay\u0101khera"
    ],
    "wof:name":"Paruwa",
    "wof:placetype":"locality"
},
  "geometry": {"coordinates":[77.18189,25.08178],"type":"Point"}
}