{
  "type": "Feature",
  "properties": {
    "gn:admin1_code":"39.0",
    "gn:admin2_code":"64.0",
    "gn:asciiname":"Khudauil",
    "gn:country_code":"IN",
    "gn:dem":1431,
    "gn:feature_class":"P",
    "gn:feature_code":"PPL",
    "gn:name":"Khudauil",
    "gn:population":0,
    "gn:timezone":"Asia/Kolkata",
    "iso:country":"IN",
    "wof:name":"Khudauil",
    "wof:placetype":"locality"
},
  "geometry": {"coordinates":[79.49254000000001,29.55308],"type":"Point"}
}