{
  "type": "Feature",
  "properties": {
    "gn:admin1_code":"11",
    "gn:admin2_code":"23.0",
    "gn:asciiname":"Bera",
    "gn:country_code":"IN",
    "gn:dem":2323,
    "gn:feature_class":"P",
    "gn:feature_code":"PPL",
    "gn:name":"Bera",
    "gn:population":0,
    "gn:timezone":"Asia/Kolkata",
    "iso:country":"IN",
    "name:cat_x_preferred":[
        "Bera"
    ],
    "name:ceb_x_preferred":[
        "Bera"
    ],
    "name:deu_x_preferred":[
        "Bera"
    ],
    "name:fra_x_preferred":[
        "Bera"
    ],
    "name:isl_x_preferred":[
        "Bera"
    ],
    "name:ita_x_preferred":[
        "Bera"
    ],
    "name:nld_x_preferred":[
        "Bera"
    ],
    "name:por_x_preferred":[
        "Bera"
    ],
    "name:rus_x_preferred":[
        "\u0411\u0435\u0440\u0430"
    ],
    "name:srp_x_preferred":[
        "\u0411\u0435\u0440\u0430"
    ],
    "name:swe_x_preferred":[
        "Bera"
    ],
    "wof:name":"Bera",
    "wof:placetype":"locality"
},
  "geometry": {"coordinates":[76.51835,32.38159],"type":"Point"}
}