{
  "type": "Feature",
  "properties": {
    "gn:admin1_code":"11",
    "gn:admin2_code":"23.0",
    "gn:asciiname":"Bera",
    "gn:country_code":"IN",
    "gn:dem":2323,
    "gn:feature_class":"P",
    "gn:feature_code":"PPL",
    "gn:name":"Bera",
    "gn:population":0,
    "gn:timezone":"Asia/Kolkata",
    "iso:country":"IN",
    "wof:name":"Bera",
    "wof:placetype":"locality"
},
  "geometry": {"coordinates":[76.51835,32.38159],"type":"Point"}
}