{
  "type": "Feature",
  "properties": {
    "iso:country":"IN",
    "ks:ks_name":"Gumukudi",
    "ks:ks_pop":109,
    "ks:ks_type":"HABITATION",
    "name:eng_x_preferred":[
        "Gumukudi"
    ],
    "wof:name":"Gumukudi",
    "wof:placetype":"locality",
    "wof:population":109
},
  "geometry": {"coordinates":[83.684308,19.579338],"type":"Point"}
}