{
  "type": "Feature",
  "properties": {
    "gn:admin1_code":"36",
    "gn:admin2_code":"134.0",
    "gn:asciiname":"Husainpur",
    "gn:country_code":"IN",
    "gn:dem":254,
    "gn:feature_class":"P",
    "gn:feature_code":"PPL",
    "gn:name":"Husainpur",
    "gn:population":0,
    "gn:timezone":"Asia/Kolkata",
    "iso:country":"IN",
    "name:und_x_variant":[
        "T\u0101jpur",
        "Asdull\u0101hpur",
        "Aurang\u0101bad"
    ],
    "wof:name":"Husainpur",
    "wof:placetype":"locality"
},
  "geometry": {"coordinates":[78.26554,29.56827],"type":"Point"}
}