{
  "type": "Feature",
  "properties": {
    "iso:country":"IN",
    "ks:ks_alt_nam":"Lokare wasti",
    "ks:ks_name":"Lokare Wasti",
    "ks:ks_pop":120,
    "ks:ks_type":"HABITATION",
    "name:eng_x_preferred":[
        "Lokare Wasti"
    ],
    "wof:name":"Lokare Wasti",
    "wof:placetype":"locality",
    "wof:population":120
},
  "geometry": {"coordinates":[76.032966,18.489945],"type":"Point"}
}