{
  "type": "Feature",
  "properties": {
    "gn:admin1_code":"36",
    "gn:admin2_code":"186.0",
    "gn:asciiname":"Shaikhapur",
    "gn:country_code":"IN",
    "gn:dem":85,
    "gn:feature_class":"P",
    "gn:feature_code":"PPL",
    "gn:name":"Shaikh\u0101pur",
    "gn:population":0,
    "gn:timezone":"Asia/Kolkata",
    "iso:country":"IN",
    "ks:ks_alt_nam":"Shaikh\u0101pur",
    "ks:ks_name":"Shaikhapur",
    "ks:ks_type":"VILLAGE",
    "ks:ks_uagg_main":0,
    "name:eng_x_preferred":[
        "Shaikhapur"
    ],
    "name:eng_x_variant":[
        "Shaikh\u0101pur"
    ],
    "wof:name":"Shaikhapur",
    "wof:placetype":"neighbourhood"
},
  "geometry": {"coordinates":[83.07820100000001,26.992572],"type":"Point"}
}