{
  "type": "Feature",
  "properties": {
    "gn:admin1_code":"11",
    "gn:admin2_code":"32.0",
    "gn:asciiname":"Tarna",
    "gn:country_code":"IN",
    "gn:dem":1969,
    "gn:feature_class":"P",
    "gn:feature_code":"PPL",
    "gn:name":"T\u0101rna",
    "gn:population":0,
    "gn:timezone":"Asia/Kolkata",
    "iso:country":"IN",
    "name:ast_x_preferred":[
        "Tarna"
    ],
    "name:spa_x_preferred":[
        "Tarna"
    ],
    "wof:name":"Tarna",
    "wof:placetype":"locality"
},
  "geometry": {"coordinates":[77.45,30.81667],"type":"Point"}
}