{
  "type": "Feature",
  "properties": {
    "gn:admin1_code":"39.0",
    "gn:admin2_code":"61.0",
    "gn:asciiname":"Ira",
    "gn:country_code":"IN",
    "gn:dem":1493,
    "gn:feature_class":"P",
    "gn:feature_code":"PPL",
    "gn:name":"\u012ara",
    "gn:population":0,
    "gn:timezone":"Asia/Kolkata",
    "iso:country":"IN",
    "wof:name":"Ira",
    "wof:placetype":"locality"
},
  "geometry": {"coordinates":[79.03928000000001,29.93497],"type":"Point"}
}