{
  "type": "Feature",
  "properties": {
    "gn:admin1_code":"39.0",
    "gn:admin2_code":"61.0",
    "gn:asciiname":"Ira",
    "gn:country_code":"IN",
    "gn:dem":1493,
    "gn:feature_class":"P",
    "gn:feature_code":"PPL",
    "gn:name":"\u012ara",
    "gn:population":0,
    "gn:timezone":"Asia/Kolkata",
    "iso:country":"IN",
    "name:cat_x_preferred":[
        "Ira"
    ],
    "name:ceb_x_preferred":[
        "Ira"
    ],
    "name:dan_x_preferred":[
        "IRA"
    ],
    "name:deu_x_preferred":[
        "Ira"
    ],
    "name:fas_x_preferred":[
        "\u0627\u06cc\u0631\u0627"
    ],
    "name:fra_x_preferred":[
        "Ira"
    ],
    "name:fry_x_preferred":[
        "Ira"
    ],
    "name:hun_x_preferred":[
        "IRA"
    ],
    "name:pol_x_preferred":[
        "Ira"
    ],
    "name:por_x_preferred":[
        "Ira"
    ],
    "name:rus_x_preferred":[
        "\u0418\u0440\u0430"
    ],
    "name:slv_x_preferred":[
        "Ira"
    ],
    "name:spa_x_preferred":[
        "Ira"
    ],
    "name:swe_x_preferred":[
        "Ira"
    ],
    "name:vol_x_preferred":[
        "Ira"
    ],
    "wof:name":"Ira",
    "wof:placetype":"locality"
},
  "geometry": {"coordinates":[79.03928000000001,29.93497],"type":"Point"}
}