{
  "type": "Feature",
  "properties": {
    "iso:country":"IN",
    "ks:ks_name":"Raigandha",
    "ks:ks_pop":54,
    "ks:ks_type":"VILLAGE",
    "name:eng_x_preferred":[
        "Raigandha"
    ],
    "wof:name":"Raigandha",
    "wof:placetype":"locality",
    "wof:population":54
},
  "geometry": {"coordinates":[83.33972199999999,18.923098],"type":"Point"}
}