{
  "type": "Feature",
  "properties": {
    "iso:country":"IN",
    "ks:ks_name":"Rekhabhatal",
    "ks:ks_pop":116,
    "ks:ks_type":"HABITATION",
    "name:eng_x_preferred":[
        "Rekhabhatal"
    ],
    "wof:name":"Rekhabhatal",
    "wof:placetype":"locality",
    "wof:population":116
},
  "geometry": {"coordinates":[80.512231,19.755019],"type":"Point"}
}