{
  "type": "Feature",
  "properties": {
    "gn:admin1_code":"35.0",
    "gn:admin2_code":"463",
    "gn:asciiname":"Chachar",
    "gn:country_code":"IN",
    "gn:dem":293,
    "gn:feature_class":"P",
    "gn:feature_code":"PPL",
    "gn:name":"Chachar",
    "gn:population":0,
    "gn:timezone":"Asia/Kolkata",
    "iso:country":"IN",
    "name:snd_x_preferred":[
        "\u0686\u0627\u0686\u0699"
    ],
    "wof:name":"Chachar",
    "wof:placetype":"locality"
},
  "geometry": {"coordinates":[82.54165,23.99583],"type":"Point"}
}