{
  "type": "Feature",
  "properties": {
    "gn:admin1_code":"12.0",
    "gn:admin2_code":"17.0",
    "gn:asciiname":"Dubdalau",
    "gn:country_code":"IN",
    "gn:dem":2903,
    "gn:feature_class":"P",
    "gn:feature_code":"PPL",
    "gn:name":"D\u016bbdalau",
    "gn:population":0,
    "gn:timezone":"Asia/Kolkata",
    "iso:country":"IN",
    "wof:name":"Dubdalau",
    "wof:placetype":"locality"
},
  "geometry": {"coordinates":[75.0646,33.4498],"type":"Point"}
}