{
  "type": "Feature",
  "properties": {
    "iso:country":"IN",
    "ks:ks_name":"Manikara",
    "ks:ks_pop":683,
    "ks:ks_type":"VILLAGE",
    "name:eng_x_preferred":[
        "Manikara"
    ],
    "wof:name":"Manikara",
    "wof:placetype":"locality",
    "wof:population":683
},
  "geometry": {"coordinates":[87.500033,22.135682],"type":"Point"}
}