{
  "type": "Feature",
  "properties": {
    "iso:country":"IN",
    "ks:ks_name":"Karunapuram",
    "ks:ks_pop":245,
    "ks:ks_type":"HABITATION",
    "name:eng_x_preferred":[
        "Karunapuram"
    ],
    "wof:name":"Karunapuram",
    "wof:placetype":"locality",
    "wof:population":245
},
  "geometry": {"coordinates":[77.4849,9.664375],"type":"Point"}
}