{
  "type": "Feature",
  "properties": {
    "iso:country":"IN",
    "ks:ks_name":"Thar",
    "ks:ks_pop":109,
    "ks:ks_type":"HABITATION",
    "name:eng_x_preferred":[
        "Thar"
    ],
    "wof:name":"Thar",
    "wof:placetype":"locality",
    "wof:population":109
},
  "geometry": {"coordinates":[78.663348,26.980263],"type":"Point"}
}