{
  "type": "Feature",
  "properties": {
    "gn:admin1_code":"34.0",
    "gn:admin2_code":"221.0",
    "gn:asciiname":"Bingawan",
    "gn:country_code":"IN",
    "gn:dem":54,
    "gn:feature_class":"P",
    "gn:feature_code":"PPL",
    "gn:name":"Bing\u0101w\u0101n",
    "gn:population":0,
    "gn:timezone":"Asia/Kolkata",
    "iso:country":"IN",
    "ks:ks_alt_nam":"Bing\u0101w\u0101n",
    "ks:ks_name":"Bingawan",
    "ks:ks_pop":1833,
    "ks:ks_type":"VILLAGE",
    "name:eng_x_preferred":[
        "Bingawan"
    ],
    "name:eng_x_variant":[
        "Bing\u0101w\u0101n"
    ],
    "wof:name":"Bingawan",
    "wof:placetype":"locality",
    "wof:population":1833
},
  "geometry": {"coordinates":[85.61700999999999,25.565907],"type":"Point"}
}