{
  "type": "Feature",
  "properties": {
    "iso:country":"IN",
    "ks:ks_alt_nam":"Elladagi vasti",
    "ks:ks_name":"Elladagi Vasti",
    "ks:ks_pop":200,
    "ks:ks_type":"HABITATION",
    "name:eng_x_preferred":[
        "Elladagi Vasti"
    ],
    "wof:name":"Elladagi Vasti",
    "wof:placetype":"locality",
    "wof:population":200
},
  "geometry": {"coordinates":[75.340926,16.937203],"type":"Point"}
}