{
  "type": "Feature",
  "properties": {
    "iso:country":"IN",
    "ks:ks_alt_nam":"Kar\u0101la",
    "ks:ks_name":"Karala",
    "ks:ks_type":"VILLAGE",
    "ks:ks_uagg_main":0,
    "name:eng_x_preferred":[
        "Karala"
    ],
    "name:eng_x_variant":[
        "Kar\u0101la"
    ],
    "wof:name":"Karala",
    "wof:placetype":"neighbourhood"
},
  "geometry": {"coordinates":[77.035224,28.735484],"type":"Point"}
}