{
  "type": "Feature",
  "properties": {
    "gn:admin1_code":"11.0",
    "gn:admin2_code":"26.0",
    "gn:asciiname":"Chhachpal",
    "gn:country_code":"IN",
    "gn:dem":1506,
    "gn:feature_class":"P",
    "gn:feature_code":"PPL",
    "gn:name":"Chhachpal",
    "gn:population":0,
    "gn:timezone":"Asia/Kolkata",
    "iso:country":"IN",
    "wof:name":"Chhachpal",
    "wof:placetype":"locality"
},
  "geometry": {"coordinates":[77.50261,31.36409],"type":"Point"}
}