{
  "type": "Feature",
  "properties": {
    "gn:admin1_code":"39.0",
    "gn:admin2_code":"032",
    "gn:asciiname":"Adan",
    "gn:country_code":"IN",
    "gn:dem":441,
    "gn:feature_class":"P",
    "gn:feature_code":"PPL",
    "gn:name":"Ad\u0101n",
    "gn:population":0,
    "gn:timezone":"Asia/Kolkata",
    "iso:country":"IN",
    "name:cat_x_preferred":[
        "Adan"
    ],
    "name:ceb_x_preferred":[
        "Adan"
    ],
    "name:deu_x_preferred":[
        "Adan"
    ],
    "name:heb_x_preferred":[
        "\u05d0\u05d3\u05df"
    ],
    "name:nld_x_preferred":[
        "Adan"
    ],
    "name:rus_x_preferred":[
        "\u0410\u0434\u0435\u043d"
    ],
    "name:swe_x_preferred":[
        "Adan"
    ],
    "name:tur_x_preferred":[
        "Adan"
    ],
    "name:uzb_x_preferred":[
        "Adan"
    ],
    "wof:name":"Adan",
    "wof:placetype":"locality"
},
  "geometry": {"coordinates":[77.75641,30.49563],"type":"Point"}
}