{
  "type": "Feature",
  "properties": {
    "iso:country":"IN",
    "ks:ks_name":"Musan Tarn",
    "ks:ks_pop":253,
    "ks:ks_type":"HABITATION",
    "name:eng_x_preferred":[
        "Musan Tarn"
    ],
    "wof:name":"Musan Tarn",
    "wof:placetype":"locality",
    "wof:population":253
},
  "geometry": {"coordinates":[84.517503,24.43028],"type":"Point"}
}