{
  "type": "Feature",
  "properties": {
    "gn:admin1_code":"39.0",
    "gn:admin2_code":"061",
    "gn:asciiname":"Sandaniyan",
    "gn:country_code":"IN",
    "gn:dem":1400,
    "gn:feature_class":"P",
    "gn:feature_code":"PPL",
    "gn:name":"Sand\u0101niy\u0101n",
    "gn:population":0,
    "gn:timezone":"Asia/Kolkata",
    "iso:country":"IN",
    "ks:ks_alt_nam":"Sand\u0101niy\u0101n",
    "ks:ks_name":"Sandaniyan",
    "ks:ks_type":"VILLAGE",
    "name:eng_x_preferred":[
        "Sandaniyan"
    ],
    "name:eng_x_variant":[
        "Sand\u0101niy\u0101n"
    ],
    "wof:name":"Sandaniyan",
    "wof:placetype":"locality"
},
  "geometry": {"coordinates":[78.658742,29.950057],"type":"Point"}
}