{
  "type": "Feature",
  "properties": {
    "gn:admin1_code":"39.0",
    "gn:admin2_code":"061",
    "gn:asciiname":"Sandaniyan",
    "gn:country_code":"IN",
    "gn:dem":1400,
    "gn:feature_class":"P",
    "gn:feature_code":"PPL",
    "gn:name":"Sand\u0101niy\u0101n",
    "gn:population":0,
    "gn:timezone":"Asia/Kolkata",
    "iso:country":"IN",
    "wof:name":"Sandaniyan",
    "wof:placetype":"locality"
},
  "geometry": {"coordinates":[78.65874000000002,29.95006],"type":"Point"}
}