{
  "type": "Feature",
  "properties": {
    "iso:country":"IN",
    "ks:ks_name":"Nagana",
    "ks:ks_pop":281,
    "ks:ks_type":"HABITATION",
    "name:eng_x_preferred":[
        "Nagana"
    ],
    "wof:name":"Nagana",
    "wof:placetype":"locality",
    "wof:population":281
},
  "geometry": {"coordinates":[71.36188900000001,26.473372],"type":"Point"}
}