{
  "type": "Feature",
  "properties": {
    "gn:admin1_code":"19.0",
    "gn:admin2_code":"562",
    "gn:asciiname":"Aminbhavi",
    "gn:country_code":"IN",
    "gn:dem":663,
    "gn:feature_class":"P",
    "gn:feature_code":"PPL",
    "gn:name":"Am\u012bnbh\u0101vi",
    "gn:population":0,
    "gn:timezone":"Asia/Kolkata",
    "iso:country":"IN",
    "wof:name":"Aminbhavi",
    "wof:placetype":"locality"
},
  "geometry": {"coordinates":[75.0565,15.5405],"type":"Point"}
}