{
  "type": "Feature",
  "properties": {
    "iso:country":"IN",
    "ks:ks_name":"N. Danee",
    "ks:ks_pop":460,
    "ks:ks_type":"HABITATION",
    "ks:ks_uagg_main":0,
    "name:eng_x_preferred":[
        "N. Danee"
    ],
    "wof:name":"N. Danee",
    "wof:placetype":"neighbourhood",
    "wof:population":460
},
  "geometry": {"coordinates":[78.75295300000001,26.945416],"type":"Point"}
}