{
  "type": "Feature",
  "properties": {
    "iso:country":"IN",
    "ks:ks_alt_nam":"Pesarp\u0101ni",
    "ks:ks_name":"Pesarpani",
    "ks:ks_type":"VILLAGE",
    "name:eng_x_preferred":[
        "Pesarpani"
    ],
    "name:eng_x_variant":[
        "Pesarp\u0101ni"
    ],
    "wof:name":"Pesarpani",
    "wof:placetype":"locality"
},
  "geometry": {"coordinates":[86.176523,24.612183],"type":"Point"}
}