{
  "type": "Feature",
  "properties": {
    "iso:country":"IN",
    "ks:ks_name":"Mensinkeri",
    "ks:ks_pop":60,
    "ks:ks_type":"HABITATION",
    "name:eng_x_preferred":[
        "Mensinkeri"
    ],
    "wof:name":"Mensinkeri",
    "wof:placetype":"locality",
    "wof:population":60
},
  "geometry": {"coordinates":[74.856146,14.591813],"type":"Point"}
}