{
  "type": "Feature",
  "properties": {
    "iso:country":"IN",
    "ks:ks_name":"Malebettu Colony",
    "ks:ks_pop":168,
    "ks:ks_type":"HABITATION",
    "name:eng_x_preferred":[
        "Malebettu Colony"
    ],
    "wof:name":"Malebettu Colony",
    "wof:placetype":"locality",
    "wof:population":168
},
  "geometry": {"coordinates":[75.051091,13.241806],"type":"Point"}
}