{
  "type": "Feature",
  "properties": {
    "iso:country":"IN",
    "ks:ks_name":"Navi Vasahat Falia",
    "ks:ks_pop":246,
    "ks:ks_type":"HABITATION",
    "name:eng_x_preferred":[
        "Navi Vasahat Falia"
    ],
    "wof:name":"Navi Vasahat Falia",
    "wof:placetype":"locality",
    "wof:population":246
},
  "geometry": {"coordinates":[73.74325,23.287111],"type":"Point"}
}