{
  "type": "Feature",
  "properties": {
    "iso:country":"IN",
    "ks:ks_name":"Bijadihi B",
    "ks:ks_pop":50,
    "ks:ks_type":"VILLAGE",
    "name:eng_x_preferred":[
        "Bijadihi B"
    ],
    "wof:name":"Bijadihi B",
    "wof:placetype":"locality",
    "wof:population":50
},
  "geometry": {"coordinates":[84.465761,21.663558],"type":"Point"}
}