{
  "type": "Feature",
  "properties": {
    "iso:country":"IN",
    "ks:ks_name":"Jeliakhali Purba Khanda",
    "ks:ks_pop":4252,
    "ks:ks_type":"VILLAGE",
    "name:eng_x_preferred":[
        "Jeliakhali Purba Khanda"
    ],
    "wof:name":"Jeliakhali Purba Khanda",
    "wof:placetype":"locality",
    "wof:population":4252
},
  "geometry": {"coordinates":[88.842358,22.351162],"type":"Point"}
}