{
  "type": "Feature",
  "properties": {
    "iso:country":"IN",
    "ks:ks_name":"Kumharan Purwa",
    "ks:ks_pop":42,
    "ks:ks_type":"HABITATION",
    "name:eng_x_preferred":[
        "Kumharan Purwa"
    ],
    "wof:name":"Kumharan Purwa",
    "wof:placetype":"locality",
    "wof:population":42
},
  "geometry": {"coordinates":[81.706777,27.473683],"type":"Point"}
}