{
  "type": "Feature",
  "properties": {
    "iso:country":"IN",
    "ks:ks_name":"Bodagollabavi",
    "ks:ks_pop":50,
    "ks:ks_type":"HABITATION",
    "name:eng_x_preferred":[
        "Bodagollabavi"
    ],
    "wof:name":"Bodagollabavi",
    "wof:placetype":"locality",
    "wof:population":50
},
  "geometry": {"coordinates":[77.57073099999999,17.011081],"type":"Point"}
}