{
  "type": "Feature",
  "properties": {
    "iso:country":"IN",
    "ks:ks_name":"Boglamari Pub Supa",
    "ks:ks_pop":299,
    "ks:ks_type":"HABITATION",
    "name:eng_x_preferred":[
        "Boglamari Pub Supa"
    ],
    "wof:name":"Boglamari Pub Supa",
    "wof:placetype":"locality",
    "wof:population":299
},
  "geometry": {"coordinates":[91.43505999999999,26.647937],"type":"Point"}
}