{
  "type": "Feature",
  "properties": {
    "gn:admin1_code":"36",
    "gn:admin2_code":"186.0",
    "gn:asciiname":"Tikui Kol Babu",
    "gn:country_code":"IN",
    "gn:dem":87,
    "gn:feature_class":"P",
    "gn:feature_code":"PPL",
    "gn:name":"Tikui Kol B\u0101bu",
    "gn:population":0,
    "gn:timezone":"Asia/Kolkata",
    "iso:country":"IN",
    "wof:name":"Tikui Kol Babu",
    "wof:placetype":"neighbourhood"
},
  "geometry": {"coordinates":[83.00039,26.64572],"type":"Point"}
}