{
  "type": "Feature",
  "properties": {
    "iso:country":"IN",
    "ks:ks_name":"Agar Chimni",
    "ks:ks_pop":127,
    "ks:ks_type":"VILLAGE",
    "name:eng_x_preferred":[
        "Agar Chimni"
    ],
    "wof:name":"Agar Chimni",
    "wof:placetype":"locality",
    "wof:population":127
},
  "geometry": {"coordinates":[79.411433,30.095283],"type":"Point"}
}