{
  "type": "Feature",
  "properties": {
    "iso:country":"IN",
    "ks:ks_name":"Malapalli",
    "ks:ks_pop":87,
    "ks:ks_type":"HABITATION",
    "ks:ks_uagg_main":0,
    "name:eng_x_preferred":[
        "Malapalli"
    ],
    "wof:name":"Malapalli",
    "wof:placetype":"neighbourhood",
    "wof:population":87
},
  "geometry": {"coordinates":[78.30817399999999,14.201985],"type":"Point"}
}