{
  "type": "Feature",
  "properties": {
    "iso:country":"IN",
    "ks:ks_name":"East Bahargram",
    "ks:ks_pop":2578,
    "ks:ks_type":"HABITATION",
    "name:eng_x_preferred":[
        "East Bahargram"
    ],
    "wof:name":"East Bahargram",
    "wof:placetype":"locality",
    "wof:population":2578
},
  "geometry": {"coordinates":[87.723505,22.40986],"type":"Point"}
}