{
  "type": "Feature",
  "properties": {
    "iso:country":"IN",
    "ks:ks_name":"Ganta Market",
    "ks:ks_pop":248,
    "ks:ks_type":"HABITATION",
    "name:eng_x_preferred":[
        "Ganta Market"
    ],
    "wof:name":"Ganta Market",
    "wof:placetype":"locality",
    "wof:population":248
},
  "geometry": {"coordinates":[84.16276999999999,26.491613],"type":"Point"}
}