{
  "type": "Feature",
  "properties": {
    "gn:admin1_code":"19.0",
    "gn:admin2_code":"570.0",
    "gn:asciiname":"Kanchinkere",
    "gn:country_code":"IN",
    "gn:dem":648,
    "gn:feature_class":"P",
    "gn:feature_code":"PPL",
    "gn:name":"Kanchinkere",
    "gn:population":0,
    "gn:timezone":"Asia/Kolkata",
    "iso:country":"IN",
    "ks:ks_name":"Kachinakere",
    "ks:ks_pop":90,
    "ks:ks_type":"HABITATION",
    "name:eng_x_preferred":[
        "Kachinakere"
    ],
    "name:eng_x_variant":[
        "Kanchinkere"
    ],
    "wof:name":"Kachinakere",
    "wof:placetype":"locality",
    "wof:population":90
},
  "geometry": {"coordinates":[75.222228,13.537106],"type":"Point"}
}