{
  "type": "Feature",
  "properties": {
    "iso:country":"IN",
    "ks:ks_name":"Komari",
    "ks:ks_pop":100,
    "ks:ks_type":"HABITATION",
    "name:eng_x_preferred":[
        "Komari"
    ],
    "wof:name":"Komari",
    "wof:placetype":"locality",
    "wof:population":100
},
  "geometry": {"coordinates":[82.89715700000001,27.370428],"type":"Point"}
}