{
  "type": "Feature",
  "properties": {
    "gn:admin1_code":"16.0",
    "gn:admin2_code":"516.0",
    "gn:asciiname":"Sheri",
    "gn:country_code":"IN",
    "gn:dem":701,
    "gn:feature_class":"P",
    "gn:feature_code":"PPL",
    "gn:name":"Sheri",
    "gn:population":0,
    "gn:timezone":"Asia/Kolkata",
    "iso:country":"IN",
    "name:rus_x_preferred":[
        "\u0428\u0435\u0440\u0438"
    ],
    "wof:name":"Sheri",
    "wof:placetype":"locality"
},
  "geometry": {"coordinates":[74.08861,20.40143],"type":"Point"}
}