{
  "type": "Feature",
  "properties": {
    "gn:admin1_code":"24.0",
    "gn:admin2_code":"110.0",
    "gn:asciiname":"Gondpura",
    "gn:country_code":"IN",
    "gn:dem":456,
    "gn:feature_class":"P",
    "gn:feature_code":"PPL",
    "gn:name":"Gondpura",
    "gn:population":0,
    "gn:timezone":"Asia/Kolkata",
    "iso:country":"IN",
    "wof:name":"Gondpura",
    "wof:placetype":"locality"
},
  "geometry": {"coordinates":[75.71108000000002,27.05368],"type":"Point"}
}