{
  "type": "Feature",
  "properties": {
    "iso:country":"IN",
    "ks:ks_name":"Velif Kumbeli",
    "ks:ks_pop":61,
    "ks:ks_type":"VILLAGE",
    "name:eng_x_preferred":[
        "Velif Kumbeli"
    ],
    "wof:name":"Velif Kumbeli",
    "wof:placetype":"locality",
    "wof:population":61
},
  "geometry": {"coordinates":[74.501076,15.390856],"type":"Point"}
}