{
  "type": "Feature",
  "properties": {
    "iso:country":"IN",
    "ks:ks_name":"Amargarh",
    "ks:ks_pop":304,
    "ks:ks_type":"VILLAGE",
    "name:eng_x_preferred":[
        "Amargarh"
    ],
    "wof:name":"Amargarh",
    "wof:placetype":"locality",
    "wof:population":304
},
  "geometry": {"coordinates":[74.722611,23.403342],"type":"Point"}
}