{
  "type": "Feature",
  "properties": {
    "iso:country":"IN",
    "ks:ks_name":"9 Barani",
    "ks:ks_pop":57,
    "ks:ks_type":"VILLAGE",
    "name:eng_x_preferred":[
        "9 Barani"
    ],
    "wof:name":"9 Barani",
    "wof:placetype":"locality",
    "wof:population":57
},
  "geometry": {"coordinates":[75.206864,29.117714],"type":"Point"}
}