{
  "type": "Feature",
  "properties": {
    "iso:country":"IN",
    "ks:ks_name":"Nariyanendal",
    "ks:ks_pop":186,
    "ks:ks_type":"HABITATION",
    "ks:ks_uagg_main":0,
    "name:eng_x_preferred":[
        "Nariyanendal"
    ],
    "wof:name":"Nariyanendal",
    "wof:placetype":"neighbourhood",
    "wof:population":186
},
  "geometry": {"coordinates":[78.695958,9.41322],"type":"Point"}
}