{
  "type": "Feature",
  "properties": {
    "iso:country":"IN",
    "ks:ks_alt_nam":"Mundr\u016bm\u0101ska",
    "ks:ks_name":"Mundrumaska",
    "ks:ks_type":"VILLAGE",
    "name:eng_x_preferred":[
        "Mundrumaska"
    ],
    "name:eng_x_variant":[
        "Mundr\u016bm\u0101ska"
    ],
    "wof:name":"Mundrumaska",
    "wof:placetype":"locality"
},
  "geometry": {"coordinates":[84.13299600000001,20.433141],"type":"Point"}
}