{
  "type": "Feature",
  "properties": {
    "iso:country":"IN",
    "ks:ks_name":"Kondhari",
    "ks:ks_pop":1575,
    "ks:ks_type":"HABITATION",
    "ks:ks_uagg_main":0,
    "name:eng_x_preferred":[
        "Kondhari"
    ],
    "wof:name":"Kondhari",
    "wof:placetype":"neighbourhood",
    "wof:population":1575
},
  "geometry": {"coordinates":[72.95408,18.851494],"type":"Point"}
}