{
  "type": "Feature",
  "properties": {
    "iso:country":"IN",
    "ks:ks_name":"Basinkhar",
    "ks:ks_pop":255,
    "ks:ks_type":"HABITATION",
    "name:eng_x_preferred":[
        "Basinkhar"
    ],
    "wof:name":"Basinkhar",
    "wof:placetype":"locality",
    "wof:population":255
},
  "geometry": {"coordinates":[82.78320600000001,22.391924],"type":"Point"}
}