{
  "type": "Feature",
  "properties": {
    "gn:admin1_code":"36",
    "gn:admin2_code":"145.0",
    "gn:asciiname":"Karnawal",
    "gn:country_code":"IN",
    "gn:dem":175,
    "gn:feature_class":"P",
    "gn:feature_code":"PPL",
    "gn:name":"Karn\u0101wal",
    "gn:population":0,
    "gn:timezone":"Asia/Kolkata",
    "iso:country":"IN",
    "name:bpy_x_preferred":[
        "\u0995\u09b0\u09cd\u09a8\u09f1\u09be\u09b2"
    ],
    "name:hin_x_preferred":[
        "\u0915\u0930\u0928\u093e\u0935\u0932"
    ],
    "name:ita_x_preferred":[
        "Karnawal"
    ],
    "name:msa_x_preferred":[
        "Karnawal"
    ],
    "name:new_x_preferred":[
        "\u0915\u0930\u094d\u0923\u0935\u093e\u0932"
    ],
    "name:nld_x_preferred":[
        "Karnawal"
    ],
    "name:pol_x_preferred":[
        "Karnawal"
    ],
    "name:por_x_preferred":[
        "Karnawal"
    ],
    "name:urd_x_preferred":[
        "\u06a9\u0631\u0646\u0627\u0648\u0644"
    ],
    "name:vie_x_preferred":[
        "Karnawal"
    ],
    "name:zho_x_preferred":[
        "\u5361\u5c14\u7eb3\u74e6\u5c14"
    ],
    "wof:name":"Karnawal",
    "wof:placetype":"locality"
},
  "geometry": {"coordinates":[77.74251,27.40099],"type":"Point"}
}