{
  "type": "Feature",
  "properties": {
    "iso:country":"IN",
    "ks:ks_name":"Maulitembwadi",
    "ks:ks_pop":216,
    "ks:ks_type":"HABITATION",
    "name:eng_x_preferred":[
        "Maulitembwadi"
    ],
    "wof:name":"Maulitembwadi",
    "wof:placetype":"locality",
    "wof:population":216
},
  "geometry": {"coordinates":[73.74661500000001,15.75571],"type":"Point"}
}