{
  "type": "Feature",
  "properties": {
    "iso:country":"IN",
    "ks:ks_name":"Talewadi",
    "ks:ks_pop":90,
    "ks:ks_type":"HABITATION",
    "name:eng_x_preferred":[
        "Talewadi"
    ],
    "wof:name":"Talewadi",
    "wof:placetype":"locality",
    "wof:population":90
},
  "geometry": {"coordinates":[73.759467,16.168839],"type":"Point"}
}