{
  "type": "Feature",
  "properties": {
    "iso:country":"IN",
    "ks:ks_name":"Madiput",
    "ks:ks_pop":86,
    "ks:ks_type":"VILLAGE",
    "name:eng_x_preferred":[
        "Madiput"
    ],
    "wof:name":"Madiput",
    "wof:placetype":"locality",
    "wof:population":86
},
  "geometry": {"coordinates":[82.60933300000001,18.367868],"type":"Point"}
}