{
  "type": "Feature",
  "properties": {
    "iso:country":"IN",
    "ks:ks_name":"Tumbadpada",
    "ks:ks_pop":100,
    "ks:ks_type":"HABITATION",
    "name:eng_x_preferred":[
        "Tumbadpada"
    ],
    "wof:name":"Tumbadpada",
    "wof:placetype":"locality",
    "wof:population":100
},
  "geometry": {"coordinates":[73.038692,19.919426],"type":"Point"}
}