{
  "type": "Feature",
  "properties": {
    "iso:country":"IN",
    "ks:ks_name":"Thenmadurai",
    "ks:ks_pop":168,
    "ks:ks_type":"HABITATION",
    "name:eng_x_preferred":[
        "Thenmadurai"
    ],
    "wof:name":"Thenmadurai",
    "wof:placetype":"locality",
    "wof:population":168
},
  "geometry": {"coordinates":[78.623746,12.169808],"type":"Point"}
}