{
  "type": "Feature",
  "properties": {
    "gn:admin1_code":"39.0",
    "gn:admin2_code":"61.0",
    "gn:asciiname":"Bakhroti",
    "gn:country_code":"IN",
    "gn:dem":848,
    "gn:feature_class":"P",
    "gn:feature_code":"PPL",
    "gn:name":"Bakhroti",
    "gn:population":0,
    "gn:timezone":"Asia/Kolkata",
    "iso:country":"IN",
    "ks:ks_name":"Bakroti",
    "ks:ks_pop":151,
    "ks:ks_type":"VILLAGE",
    "name:eng_x_preferred":[
        "Bakroti"
    ],
    "name:eng_x_variant":[
        "Bakhroti"
    ],
    "wof:name":"Bakroti",
    "wof:placetype":"locality",
    "wof:population":151
},
  "geometry": {"coordinates":[79.053567,29.611312],"type":"Point"}
}