{
  "type": "Feature",
  "properties": {
    "iso:country":"IN",
    "ks:ks_alt_nam":"rabangda",
    "ks:ks_name":"Rabangda",
    "ks:ks_pop":645,
    "ks:ks_type":"HABITATION",
    "name:eng_x_preferred":[
        "Rabangda"
    ],
    "wof:name":"Rabangda",
    "wof:placetype":"locality",
    "wof:population":645
},
  "geometry": {"coordinates":[85.170252,22.340083],"type":"Point"}
}