{
  "type": "Feature",
  "properties": {
    "iso:country":"IN",
    "ks:ks_name":"Arazi Tofeer",
    "ks:ks_pop":0,
    "ks:ks_type":"VILLAGE",
    "name:eng_x_preferred":[
        "Arazi Tofeer"
    ],
    "wof:name":"Arazi Tofeer",
    "wof:placetype":"locality",
    "wof:population":0
},
  "geometry": {"coordinates":[77.45737699999999,30.084287],"type":"Point"}
}