{
  "type": "Feature",
  "properties": {
    "gn:admin1_code":"36.0",
    "gn:admin2_code":"167",
    "gn:asciiname":"Agora",
    "gn:country_code":"IN",
    "gn:dem":364,
    "gn:feature_class":"P",
    "gn:feature_code":"PPL",
    "gn:name":"Agora",
    "gn:population":0,
    "gn:timezone":"Asia/Kolkata",
    "iso:country":"IN",
    "name:als_x_preferred":[
        "Agora"
    ],
    "name:ara_x_preferred":[
        "\u0623\u063a\u0648\u0631\u0627"
    ],
    "name:aze_x_preferred":[
        "Aqora"
    ],
    "name:ben_x_preferred":[
        "\u0986\u0997\u09cb\u09b0\u09be"
    ],
    "name:bre_x_preferred":[
        "Agora"
    ],
    "name:bul_x_preferred":[
        "\u0410\u0433\u043e\u0440\u0430"
    ],
    "name:cat_x_preferred":[
        "\u00c0gora"
    ],
    "name:ces_x_preferred":[
        "Agora"
    ],
    "name:cym_x_preferred":[
        "Agora"
    ],
    "name:deu_x_preferred":[
        "Agora"
    ],
    "name:ell_x_preferred":[
        "\u0391\u03c1\u03c7\u03b1\u03af\u03b1 \u0391\u03b3\u03bf\u03c1\u03ac"
    ],
    "name:epo_x_preferred":[
        "Agoro"
    ],
    "name:est_x_preferred":[
        "Agoraa"
    ],
    "name:eus_x_preferred":[
        "Agora"
    ],
    "name:fas_x_preferred":[
        "\u0622\u06af\u0648\u0631\u0627"
    ],
    "name:fin_x_preferred":[
        "Agora"
    ],
    "name:fra_x_preferred":[
        "Agora"
    ],
    "name:glg_x_preferred":[
        "\u00c1gora"
    ],
    "name:heb_x_preferred":[
        "\u05d0\u05d2\u05d5\u05e8\u05d4"
    ],
    "name:hrv_x_preferred":[
        "Agora"
    ],
    "name:hun_x_preferred":[
        "Agora"
    ],
    "name:hye_x_preferred":[
        "\u0531\u0563\u0578\u0580\u0561"
    ],
    "name:ina_x_preferred":[
        "Agora"
    ],
    "name:ind_x_preferred":[
        "Agora"
    ],
    "name:ita_x_preferred":[
        "Agor\u00e0"
    ],
    "name:jpn_x_preferred":[
        "\u30a2\u30b4\u30e9"
    ],
    "name:kat_x_preferred":[
        "\u10d0\u10d2\u10dd\u10e0\u10d0"
    ],
    "name:kaz_x_preferred":[
        "\u0410\u0433\u043e\u0440\u0430"
    ],
    "name:kor_x_preferred":[
        "\uc544\uace0\ub77c"
    ],
    "name:lat_x_preferred":[
        "Agora"
    ],
    "name:ltz_x_preferred":[
        "Agora"
    ],
    "name:mkd_x_preferred":[
        "\u0410\u0433\u043e\u0440\u0430"
    ],
    "name:nld_x_preferred":[
        "Agora"
    ],
    "name:nno_x_preferred":[
        "Agora"
    ],
    "name:nor_x_preferred":[
        "Agora"
    ],
    "name:oci_x_preferred":[
        "Agora"
    ],
    "name:pol_x_preferred":[
        "Agora"
    ],
    "name:por_x_preferred":[
        "\u00c1gora"
    ],
    "name:ron_x_preferred":[
        "Agora"
    ],
    "name:rus_x_preferred":[
        "\u0410\u0433\u043e\u0440\u0430"
    ],
    "name:sco_x_preferred":[
        "Agora"
    ],
    "name:slk_x_preferred":[
        "Agora"
    ],
    "name:slv_x_preferred":[
        "Agora"
    ],
    "name:spa_x_preferred":[
        "\u00c1gora"
    ],
    "name:sqi_x_preferred":[
        "Agora"
    ],
    "name:srp_x_preferred":[
        "\u0410\u0433\u043e\u0440\u0430"
    ],
    "name:swe_x_preferred":[
        "Agora"
    ],
    "name:tam_x_preferred":[
        "\u0b85\u0b95\u0bcb\u0bb0\u0bbe"
    ],
    "name:tur_x_preferred":[
        "Agora"
    ],
    "name:ukr_x_preferred":[
        "\u0410\u0433\u043e\u0440\u0430"
    ],
    "name:urd_x_preferred":[
        "\u0622\u06af\u0648\u0631\u06c1"
    ],
    "name:vie_x_preferred":[
        "Agora"
    ],
    "name:zho_x_preferred":[
        "\u963f\u54e5\u62c9"
    ],
    "wof:name":"Agora",
    "wof:placetype":"locality"
},
  "geometry": {"coordinates":[78.79881999999998,24.5813],"type":"Point"}
}