{
  "type": "Feature",
  "properties": {
    "iso:country":"IN",
    "ks:ks_name":"Mondijanguda",
    "ks:ks_pop":73,
    "ks:ks_type":"VILLAGE",
    "name:eng_x_preferred":[
        "Mondijanguda"
    ],
    "wof:name":"Mondijanguda",
    "wof:placetype":"locality",
    "wof:population":73
},
  "geometry": {"coordinates":[83.014819,18.235073],"type":"Point"}
}