{
  "type": "Feature",
  "properties": {
    "iso:country":"IN",
    "ks:ks_name":"Bhada",
    "ks:ks_pop":1254,
    "ks:ks_type":"VILLAGE",
    "name:eng_x_preferred":[
        "Bhada"
    ],
    "wof:name":"Bhada",
    "wof:placetype":"locality",
    "wof:population":1254
},
  "geometry": {"coordinates":[72.91763899999999,21.271028],"type":"Point"}
}