{
  "type": "Feature",
  "properties": {
    "gn:admin1_code":"38.0",
    "gn:admin2_code":"353.0",
    "gn:asciiname":"Sarsa",
    "gn:country_code":"IN",
    "gn:dem":61,
    "gn:feature_class":"P",
    "gn:feature_code":"PPL",
    "gn:name":"Sarsa",
    "gn:population":0,
    "gn:timezone":"Asia/Kolkata",
    "iso:country":"IN",
    "wof:name":"Sarsa",
    "wof:placetype":"neighbourhood"
},
  "geometry": {"coordinates":[87.65038,24.66941],"type":"Point"}
}