{
  "type": "Feature",
  "properties": {
    "gn:admin1_code":"35.0",
    "gn:admin2_code":"430.0",
    "gn:asciiname":"Nidura",
    "gn:country_code":"IN",
    "gn:dem":106,
    "gn:feature_class":"P",
    "gn:feature_code":"PPL",
    "gn:name":"Nidura",
    "gn:population":0,
    "gn:timezone":"Asia/Kolkata",
    "iso:country":"IN",
    "ks:ks_name":"Nedura",
    "ks:ks_pop":508,
    "ks:ks_type":"VILLAGE",
    "name:eng_x_preferred":[
        "Nedura"
    ],
    "name:eng_x_variant":[
        "Nidura"
    ],
    "wof:name":"Nedura",
    "wof:placetype":"locality",
    "wof:population":508
},
  "geometry": {"coordinates":[81.5432,25.001311],"type":"Point"}
}