{
  "type": "Feature",
  "properties": {
    "iso:country":"IN",
    "ks:ks_name":"Harijanwasti",
    "ks:ks_pop":92,
    "ks:ks_type":"HABITATION",
    "name:eng_x_preferred":[
        "Harijanwasti"
    ],
    "wof:name":"Harijanwasti",
    "wof:placetype":"locality",
    "wof:population":92
},
  "geometry": {"coordinates":[74.089989,17.124208],"type":"Point"}
}