{
  "type": "Feature",
  "properties": {
    "gn:admin1_code":"35",
    "gn:admin2_code":"428.0",
    "gn:asciiname":"Hathni",
    "gn:country_code":"IN",
    "gn:dem":377,
    "gn:feature_class":"P",
    "gn:feature_code":"PPL",
    "gn:name":"Hathni",
    "gn:population":0,
    "gn:timezone":"Asia/Kolkata",
    "iso:country":"IN",
    "wof:name":"Hathni",
    "wof:placetype":"locality"
},
  "geometry": {"coordinates":[79.4756,23.75309],"type":"Point"}
}