{
  "type": "Feature",
  "properties": {
    "iso:country":"IN",
    "ks:ks_name":"Korukonda",
    "ks:ks_pop":379,
    "ks:ks_type":"HABITATION",
    "name:eng_x_preferred":[
        "Korukonda"
    ],
    "wof:name":"Korukonda",
    "wof:placetype":"locality",
    "wof:population":379
},
  "geometry": {"coordinates":[82.442922,17.816015],"type":"Point"}
}