{
  "type": "Feature",
  "properties": {
    "gn:admin1_code":"24.0",
    "gn:admin2_code":"104",
    "gn:asciiname":"Kotkasim",
    "gn:country_code":"IN",
    "gn:dem":258,
    "gn:feature_class":"P",
    "gn:feature_code":"PPL",
    "gn:name":"Kotkasim",
    "gn:population":0,
    "gn:timezone":"Asia/Kolkata",
    "iso:country":"IN",
    "name:hin_x_preferred":[
        "\u0915\u094b\u091f \u0915\u093e\u0938\u093f\u092e"
    ],
    "wof:name":"Kotkasim",
    "wof:placetype":"locality"
},
  "geometry": {"coordinates":[76.72045,28.02994],"type":"Point"}
}