{
  "type": "Feature",
  "properties": {
    "gn:admin1_code":"24",
    "gn:admin2_code":"118.0",
    "gn:asciiname":"Dhal",
    "gn:country_code":"IN",
    "gn:dem":362,
    "gn:feature_class":"P",
    "gn:feature_code":"PPL",
    "gn:name":"Dh\u0101l",
    "gn:population":0,
    "gn:timezone":"Asia/Kolkata",
    "iso:country":"IN",
    "wof:name":"Dhal",
    "wof:placetype":"locality"
},
  "geometry": {"coordinates":[73.81560999999998,25.60943],"type":"Point"}
}