{
  "type": "Feature",
  "properties": {
    "iso:country":"IN",
    "ks:ks_name":"Rehari Par",
    "ks:ks_pop":187,
    "ks:ks_type":"HABITATION",
    "name:eng_x_preferred":[
        "Rehari Par"
    ],
    "wof:name":"Rehari Par",
    "wof:placetype":"locality",
    "wof:population":187
},
  "geometry": {"coordinates":[81.595236,25.364682],"type":"Point"}
}