{
  "type": "Feature",
  "properties": {
    "gn:admin1_code":"34.0",
    "gn:admin2_code":"222.0",
    "gn:asciiname":"Aho",
    "gn:country_code":"IN",
    "gn:dem":43,
    "gn:feature_class":"P",
    "gn:feature_code":"PPL",
    "gn:name":"\u0100ho",
    "gn:population":0,
    "gn:timezone":"Asia/Kolkata",
    "iso:country":"IN",
    "name:ceb_x_preferred":[
        "Aho"
    ],
    "name:ces_x_preferred":[
        "Aho"
    ],
    "name:deu_x_preferred":[
        "Aho"
    ],
    "name:fin_x_preferred":[
        "Aho"
    ],
    "name:kaz_x_preferred":[
        "\u0410\u0445\u043e"
    ],
    "name:rus_x_preferred":[
        "\u0410\u0445\u043e"
    ],
    "name:slv_x_preferred":[
        "Aho"
    ],
    "name:swe_x_preferred":[
        "Aho"
    ],
    "name:ukr_x_preferred":[
        "\u0410\u0445\u043e"
    ],
    "wof:name":"Aho",
    "wof:placetype":"locality"
},
  "geometry": {"coordinates":[86.41328,25.48573],"type":"Point"}
}