{
  "type": "Feature",
  "properties": {
    "iso:country":"IN",
    "ks:ks_name":"Lokhariyanpurwa",
    "ks:ks_pop":125,
    "ks:ks_type":"HABITATION",
    "ks:ks_uagg_main":0,
    "name:eng_x_preferred":[
        "Lokhariyanpurwa"
    ],
    "wof:name":"Lokhariyanpurwa",
    "wof:placetype":"neighbourhood",
    "wof:population":125
},
  "geometry": {"coordinates":[81.625609,27.764198],"type":"Point"}
}