{
  "type": "Feature",
  "properties": {
    "iso:country":"IN",
    "ks:ks_name":"Pipalpada",
    "ks:ks_pop":0,
    "ks:ks_type":"VILLAGE",
    "name:eng_x_preferred":[
        "Pipalpada"
    ],
    "wof:name":"Pipalpada",
    "wof:placetype":"locality",
    "wof:population":0
},
  "geometry": {"coordinates":[83.642017,20.296214],"type":"Point"}
}