{
  "type": "Feature",
  "properties": {
    "gn:admin1_code":"16",
    "gn:admin2_code":"505.0",
    "gn:asciiname":"Nirwah",
    "gn:country_code":"IN",
    "gn:dem":287,
    "gn:feature_class":"P",
    "gn:feature_code":"PPL",
    "gn:name":"Nirw\u0101h",
    "gn:population":0,
    "gn:timezone":"Asia/Kolkata",
    "iso:country":"IN",
    "wof:name":"Nirwah",
    "wof:placetype":"locality"
},
  "geometry": {"coordinates":[79.32318000000002,20.95761],"type":"Point"}
}