{
  "type": "Feature",
  "properties": {
    "iso:country":"IN",
    "ks:ks_name":"Vanjur",
    "ks:ks_pop":1560,
    "ks:ks_type":"VILLAGE",
    "ks:ks_uagg_main":0,
    "name:eng_x_preferred":[
        "Vanjur"
    ],
    "wof:name":"Vanjur",
    "wof:placetype":"neighbourhood",
    "wof:population":1560
},
  "geometry": {"coordinates":[79.12538499999999,12.949254],"type":"Point"}
}