{
  "type": "Feature",
  "properties": {
    "gn:admin1_code":"19",
    "gn:admin2_code":"563.0",
    "gn:asciiname":"Kabgar",
    "gn:country_code":"IN",
    "gn:dem":546,
    "gn:feature_class":"P",
    "gn:feature_code":"PPL",
    "gn:name":"Kabg\u0101r",
    "gn:population":0,
    "gn:timezone":"Asia/Kolkata",
    "iso:country":"IN",
    "ks:ks_name":"Kabgar",
    "ks:ks_pop":55,
    "ks:ks_type":"HABITATION",
    "name:eng_x_preferred":[
        "Kabgar"
    ],
    "wof:name":"Kabgar",
    "wof:placetype":"locality",
    "wof:population":55
},
  "geometry": {"coordinates":[74.85430100000001,14.547487],"type":"Point"}
}