{
  "type": "Feature",
  "properties": {
    "iso:country":"IN",
    "ks:ks_name":"Veppankulam",
    "ks:ks_pop":142,
    "ks:ks_type":"VILLAGE",
    "name:eng_x_preferred":[
        "Veppankulam"
    ],
    "wof:name":"Veppankulam",
    "wof:placetype":"locality",
    "wof:population":142
},
  "geometry": {"coordinates":[77.616294,8.475706],"type":"Point"}
}