{
  "type": "Feature",
  "properties": {
    "gn:admin1_code":"37",
    "gn:admin2_code":"412.0",
    "gn:asciiname":"Kormura",
    "gn:country_code":"IN",
    "gn:dem":465,
    "gn:feature_class":"P",
    "gn:feature_code":"PPL",
    "gn:name":"Kormura",
    "gn:population":0,
    "gn:timezone":"Asia/Kolkata",
    "iso:country":"IN",
    "wof:name":"Kormura",
    "wof:placetype":"neighbourhood"
},
  "geometry": {"coordinates":[81.99432,20.28956],"type":"Point"}
}