{
  "type": "Feature",
  "properties": {
    "iso:country":"IN",
    "ks:ks_alt_nam":"RANMALA",
    "ks:ks_name":"Ranmala",
    "ks:ks_pop":25,
    "ks:ks_type":"HABITATION",
    "name:eng_x_preferred":[
        "Ranmala"
    ],
    "wof:name":"Ranmala",
    "wof:placetype":"locality",
    "wof:population":25
},
  "geometry": {"coordinates":[74.936347,17.092706],"type":"Point"}
}