{
  "type": "Feature",
  "properties": {
    "iso:country":"IN",
    "ks:ks_name":"Kuturapara",
    "ks:ks_pop":208,
    "ks:ks_type":"HABITATION",
    "name:eng_x_preferred":[
        "Kuturapara"
    ],
    "wof:name":"Kuturapara",
    "wof:placetype":"locality",
    "wof:population":208
},
  "geometry": {"coordinates":[84.222236,22.280832],"type":"Point"}
}