{
  "type": "Feature",
  "properties": {
    "iso:country":"IN",
    "ks:ks_name":"Durbajoy Para",
    "ks:ks_pop":317,
    "ks:ks_type":"HABITATION",
    "name:eng_x_preferred":[
        "Durbajoy Para"
    ],
    "wof:name":"Durbajoy Para",
    "wof:placetype":"locality",
    "wof:population":317
},
  "geometry": {"coordinates":[92.068478,23.927634],"type":"Point"}
}