{
  "type": "Feature",
  "properties": {
    "iso:country":"IN",
    "ks:ks_name":"Daudpur M. Khetabpur",
    "ks:ks_pop":304,
    "ks:ks_type":"VILLAGE",
    "name:eng_x_preferred":[
        "Daudpur M. Khetabpur"
    ],
    "wof:name":"Daudpur M. Khetabpur",
    "wof:placetype":"locality",
    "wof:population":304
},
  "geometry": {"coordinates":[83.71097,25.760504],"type":"Point"}
}