{
  "type": "Feature",
  "properties": {
    "iso:country":"IN",
    "ks:ks_alt_nam":"SITAGACHHA",
    "ks:ks_name":"Sitagachha",
    "ks:ks_pop":167,
    "ks:ks_type":"HABITATION",
    "name:eng_x_preferred":[
        "Sitagachha"
    ],
    "wof:name":"Sitagachha",
    "wof:placetype":"locality",
    "wof:population":167
},
  "geometry": {"coordinates":[87.824743,26.313594],"type":"Point"}
}