{
  "type": "Feature",
  "properties": {
    "iso:country":"IN",
    "ks:ks_name":"Sijhara",
    "ks:ks_pop":1627,
    "ks:ks_type":"VILLAGE",
    "name:eng_x_preferred":[
        "Sijhara"
    ],
    "wof:name":"Sijhara",
    "wof:placetype":"locality",
    "wof:population":1627
},
  "geometry": {"coordinates":[80.758504,23.90972],"type":"Point"}
}