{
  "type": "Feature",
  "properties": {
    "gn:country":"IN",
    "gn:fcode":"PPL",
    "gn:population":16712,
    "iso:country":"IN",
    "name:bho_x_preferred":[
        "\u0915\u093e\u0902\u0915\u0947"
    ],
    "name:bpy_x_preferred":[
        "\u0995\u09be\u09a8\u0995\u09c7"
    ],
    "name:ceb_x_preferred":[
        "K\u0101nke"
    ],
    "name:dan_x_preferred":[
        "Kanke"
    ],
    "name:eng_x_preferred":[
        "Kanke"
    ],
    "name:heb_x_preferred":[
        "\u05e7\u05d0\u05e0\u05e7"
    ],
    "name:hin_x_preferred":[
        "\u0915\u093e\u0901\u0915\u0947"
    ],
    "name:ita_x_preferred":[
        "Kanke"
    ],
    "name:mlg_x_preferred":[
        "Kanke"
    ],
    "name:msa_x_preferred":[
        "Kanke"
    ],
    "name:nan_x_preferred":[
        "Kanke"
    ],
    "name:new_x_preferred":[
        "\u0915\u093e\u0902\u0915\u0947"
    ],
    "name:nld_x_preferred":[
        "Kanke"
    ],
    "name:ori_x_preferred":[
        "\u0b15\u0b19\u0b4d\u0b15\u0b47"
    ],
    "name:sat_x_preferred":[
        "\u1c60\u1c5f\u1c78\u1c60\u1c6e"
    ],
    "name:swe_x_preferred":[
        "K\u0101nke"
    ],
    "name:vie_x_preferred":[
        "Kanke"
    ],
    "name:zho_x_preferred":[
        "\u5361\u6069\u51ef"
    ],
    "qs:name":"Kenke",
    "qs:name_adm0":"India",
    "qs:name_adm1":"Jharkhand",
    "qs:photos_9r":0,
    "qs:photos_sr":0,
    "qs:placetype":"Town",
    "qs:pop_sr":"6",
    "wof:name":"Kenke",
    "wof:placetype":"neighbourhood",
    "wof:population":16712
},
  "geometry": {"coordinates":[85.3211,23.43362],"type":"Point"}
}