{
  "type": "Feature",
  "properties": {
    "iso:country":"IN",
    "ks:ks_alt_nam":"Bharda pada",
    "ks:ks_name":"Bharda Pada",
    "ks:ks_pop":380,
    "ks:ks_type":"HABITATION",
    "name:eng_x_preferred":[
        "Bharda Pada"
    ],
    "wof:name":"Bharda Pada",
    "wof:placetype":"locality",
    "wof:population":380
},
  "geometry": {"coordinates":[73.410938,20.305855],"type":"Point"}
}