{
  "type": "Feature",
  "properties": {
    "gn:admin1_code":"39.0",
    "gn:admin2_code":"061",
    "gn:asciiname":"Ranakot",
    "gn:country_code":"IN",
    "gn:dem":1138,
    "gn:feature_class":"P",
    "gn:feature_code":"PPL",
    "gn:name":"Ran\u0101kot",
    "gn:population":0,
    "gn:timezone":"Asia/Kolkata",
    "iso:country":"IN",
    "ks:ks_alt_nam":"Ran\u0101kot",
    "ks:ks_name":"Ranakot",
    "ks:ks_pop":60,
    "ks:ks_type":"VILLAGE",
    "name:eng_x_preferred":[
        "Ranakot"
    ],
    "name:eng_x_variant":[
        "Ran\u0101kot"
    ],
    "wof:name":"Ranakot",
    "wof:placetype":"locality",
    "wof:population":60
},
  "geometry": {"coordinates":[78.741135,29.796994],"type":"Point"}
}