{
  "type": "Feature",
  "properties": {
    "iso:country":"IN",
    "ks:ks_name":"Loddiguda",
    "ks:ks_pop":254,
    "ks:ks_type":"VILLAGE",
    "name:eng_x_preferred":[
        "Loddiguda"
    ],
    "wof:name":"Loddiguda",
    "wof:placetype":"locality",
    "wof:population":254
},
  "geometry": {"coordinates":[79.06500800000001,19.231901],"type":"Point"}
}