{
  "type": "Feature",
  "properties": {
    "gn:admin1_code":"10",
    "gn:admin2_code":"83.0",
    "gn:asciiname":"Bhadana",
    "gn:country_code":"IN",
    "gn:dem":221,
    "gn:feature_class":"P",
    "gn:feature_code":"PPL",
    "gn:name":"Bhad\u0101na",
    "gn:population":0,
    "gn:timezone":"Asia/Kolkata",
    "iso:country":"IN",
    "name:pnb_x_preferred":[
        "\u0628\u06be\u0688\u0627\u0646\u0647"
    ],
    "name:urd_x_preferred":[
        "\u0628\u06be\u0688\u0627\u0646\u06c1"
    ],
    "wof:name":"Bhadana",
    "wof:placetype":"locality"
},
  "geometry": {"coordinates":[76.72414000000001,28.62854],"type":"Point"}
}