{
  "type": "Feature",
  "properties": {
    "gn:admin1_code":"23.0",
    "gn:admin2_code":"49.0",
    "gn:asciiname":"Chak Misri Khan",
    "gn:country_code":"IN",
    "gn:dem":226,
    "gn:feature_class":"P",
    "gn:feature_code":"PPL",
    "gn:name":"Chak Misri Kh\u0101n",
    "gn:population":0,
    "gn:timezone":"Asia/Kolkata",
    "iso:country":"IN",
    "wof:name":"Chak Misri Khan",
    "wof:placetype":"locality"
},
  "geometry": {"coordinates":[74.64721999999998,31.74602],"type":"Point"}
}