{
  "type": "Feature",
  "properties": {
    "iso:country":"IN",
    "ks:ks_name":"Chhapra Mohan",
    "ks:ks_pop":485,
    "ks:ks_type":"VILLAGE",
    "ks:ks_uagg_main":0,
    "name:eng_x_preferred":[
        "Chhapra Mohan"
    ],
    "wof:name":"Chhapra Mohan",
    "wof:placetype":"neighbourhood",
    "wof:population":485
},
  "geometry": {"coordinates":[85.124983,26.210673],"type":"Point"}
}