{
  "type": "Feature",
  "properties": {
    "iso:country":"IN",
    "ks:ks_name":"Saharsa",
    "ks:ks_pop":732,
    "ks:ks_type":"HABITATION",
    "ks:ks_uagg_main":0,
    "name:eng_x_preferred":[
        "Saharsa"
    ],
    "name:hin_x_preferred":[
        "\u0938\u0939\u0930\u0938\u093e"
    ],
    "wof:name":"Saharsa",
    "wof:placetype":"neighbourhood",
    "wof:population":732
},
  "geometry": {"coordinates":[84.340194,25.89699],"type":"Point"}
}