{
  "type": "Feature",
  "properties": {
    "iso:country":"IN",
    "ks:ks_name":"Jagda",
    "ks:ks_pop":30,
    "ks:ks_type":"HABITATION",
    "name:eng_x_preferred":[
        "Jagda"
    ],
    "wof:name":"Jagda",
    "wof:placetype":"locality",
    "wof:population":30
},
  "geometry": {"coordinates":[83.368979,22.432712],"type":"Point"}
}