{
  "type": "Feature",
  "properties": {
    "iso:country":"IN",
    "ks:ks_name":"Ghisuan",
    "ks:ks_pop":257,
    "ks:ks_type":"VILLAGE",
    "name:eng_x_preferred":[
        "Ghisuan"
    ],
    "wof:name":"Ghisuan",
    "wof:placetype":"locality",
    "wof:population":257
},
  "geometry": {"coordinates":[86.97611999999999,21.471867],"type":"Point"}
}