{
  "type": "Feature",
  "properties": {
    "gn:admin1_code":"23.0",
    "gn:admin2_code":"50.0",
    "gn:asciiname":"Manawan",
    "gn:country_code":"IN",
    "gn:dem":211,
    "gn:feature_class":"P",
    "gn:feature_code":"PPL",
    "gn:name":"Man\u0101w\u0101n",
    "gn:population":0,
    "gn:timezone":"Asia/Kolkata",
    "iso:country":"IN",
    "name:ara_x_preferred":[
        "\u0645\u0627\u0646\u0627\u0648\u0627\u0646"
    ],
    "name:atj_x_preferred":[
        "Manawan"
    ],
    "name:ceb_x_preferred":[
        "Manawan"
    ],
    "name:deu_x_preferred":[
        "Manawan"
    ],
    "name:eus_x_preferred":[
        "Manawan"
    ],
    "name:fra_x_preferred":[
        "Manawan"
    ],
    "wof:name":"Manawan",
    "wof:placetype":"locality"
},
  "geometry": {"coordinates":[74.56820999999999,31.20681],"type":"Point"}
}