{
  "type": "Feature",
  "properties": {
    "gn:admin1_code":"19.0",
    "gn:admin2_code":"581.0",
    "gn:asciiname":"Buvanhalli",
    "gn:country_code":"IN",
    "gn:dem":875,
    "gn:feature_class":"P",
    "gn:feature_code":"PPL",
    "gn:name":"Buvanhalli",
    "gn:population":0,
    "gn:timezone":"Asia/Kolkata",
    "iso:country":"IN",
    "wof:name":"Buvanhalli",
    "wof:placetype":"locality"
},
  "geometry": {"coordinates":[77.96964,13.17888],"type":"Point"}
}