{
  "type": "Feature",
  "properties": {
    "iso:country":"IN",
    "ks:ks_name":"Uparkonki",
    "ks:ks_pop":1438,
    "ks:ks_type":"VILLAGE",
    "ks:ks_uagg_main":0,
    "name:eng_x_preferred":[
        "Uparkonki"
    ],
    "wof:name":"Uparkonki",
    "wof:placetype":"neighbourhood",
    "wof:population":1438
},
  "geometry": {"coordinates":[85.269488,23.519229],"type":"Point"}
}