{
  "type": "Feature",
  "properties": {
    "iso:country":"IN",
    "ks:ks_name":"Babu Colony",
    "ks:ks_pop":1682,
    "ks:ks_type":"HABITATION",
    "name:eng_x_preferred":[
        "Babu Colony"
    ],
    "wof:name":"Babu Colony",
    "wof:placetype":"locality",
    "wof:population":1682
},
  "geometry": {"coordinates":[78.437804,13.600244],"type":"Point"}
}