{
  "type": "Feature",
  "properties": {
    "gn:admin1_code":"19.0",
    "gn:admin2_code":"562.0",
    "gn:asciiname":"Mugali",
    "gn:country_code":"IN",
    "gn:dem":695,
    "gn:feature_class":"P",
    "gn:feature_code":"PPL",
    "gn:name":"Mugali",
    "gn:population":0,
    "gn:timezone":"Asia/Kolkata",
    "iso:country":"IN",
    "name:new_x_preferred":[
        "\u092e\u0941\u0917\u093e\u0932\u0940"
    ],
    "wof:name":"Mugali",
    "wof:placetype":"locality"
},
  "geometry": {"coordinates":[74.86763000000001,15.57534],"type":"Point"}
}