{
  "type": "Feature",
  "properties": {
    "iso:country":"IN",
    "ks:ks_name":"Kothaindlu",
    "ks:ks_pop":44,
    "ks:ks_type":"HABITATION",
    "name:eng_x_preferred":[
        "Kothaindlu"
    ],
    "wof:name":"Kothaindlu",
    "wof:placetype":"locality",
    "wof:population":44
},
  "geometry": {"coordinates":[79.18010200000001,13.319322],"type":"Point"}
}