{
  "type": "Feature",
  "properties": {
    "iso:country":"IN",
    "ks:ks_name":"Harizan Basti",
    "ks:ks_pop":190,
    "ks:ks_type":"HABITATION",
    "name:eng_x_preferred":[
        "Harizan Basti"
    ],
    "wof:name":"Harizan Basti",
    "wof:placetype":"locality",
    "wof:population":190
},
  "geometry": {"coordinates":[83.329758,25.049728],"type":"Point"}
}