{
  "type": "Feature",
  "properties": {
    "iso:country":"IN",
    "ks:ks_name":"Dalai Molla",
    "ks:ks_pop":1599,
    "ks:ks_type":"VILLAGE",
    "ks:ks_uagg_main":0,
    "name:eng_x_preferred":[
        "Dalai Molla"
    ],
    "wof:name":"Dalai Molla",
    "wof:placetype":"neighbourhood",
    "wof:population":1599
},
  "geometry": {"coordinates":[88.472514,23.468744],"type":"Point"}
}