{
  "type": "Feature",
  "properties": {
    "iso:country":"IN",
    "ks:ks_name":"Herta",
    "ks:ks_pop":753,
    "ks:ks_type":"VILLAGE",
    "name:eng_x_preferred":[
        "Herta"
    ],
    "wof:name":"Herta",
    "wof:placetype":"locality",
    "wof:population":753
},
  "geometry": {"coordinates":[85.173641,22.548232],"type":"Point"}
}