{
  "type": "Feature",
  "properties": {
    "iso:country":"IN",
    "ks:ks_name":"Doddasale Keri",
    "ks:ks_pop":138,
    "ks:ks_type":"HABITATION",
    "name:eng_x_preferred":[
        "Doddasale Keri"
    ],
    "wof:name":"Doddasale Keri",
    "wof:placetype":"locality",
    "wof:population":138
},
  "geometry": {"coordinates":[74.489092,14.245282],"type":"Point"}
}