{
  "type": "Feature",
  "properties": {
    "iso:country":"IN",
    "ks:ks_name":"Hanu Bhunya",
    "ks:ks_pop":4156,
    "ks:ks_type":"VILLAGE",
    "name:eng_x_preferred":[
        "Hanu Bhunya"
    ],
    "wof:name":"Hanu Bhunya",
    "wof:placetype":"locality",
    "wof:population":4156
},
  "geometry": {"coordinates":[87.861743,22.032864],"type":"Point"}
}