{
  "type": "Feature",
  "properties": {
    "iso:country":"IN",
    "ks:ks_alt_nam":"PASWAN TOLA",
    "ks:ks_name":"Paswan Tola",
    "ks:ks_pop":99,
    "ks:ks_type":"HABITATION",
    "ks:ks_uagg_main":0,
    "name:eng_x_preferred":[
        "Paswan Tola"
    ],
    "wof:name":"Paswan Tola",
    "wof:placetype":"neighbourhood",
    "wof:population":99
},
  "geometry": {"coordinates":[85.040666,24.587462],"type":"Point"}
}