{
  "type": "Feature",
  "properties": {
    "iso:country":"IN",
    "ks:ks_name":"Muralsahi",
    "ks:ks_pop":9,
    "ks:ks_type":"VILLAGE",
    "name:eng_x_preferred":[
        "Muralsahi"
    ],
    "wof:name":"Muralsahi",
    "wof:placetype":"locality",
    "wof:population":9
},
  "geometry": {"coordinates":[84.20919000000001,19.017996],"type":"Point"}
}