{
  "type": "Feature",
  "properties": {
    "iso:country":"IN",
    "ks:ks_name":"Kapatkhalipara",
    "ks:ks_pop":222,
    "ks:ks_type":"HABITATION",
    "ks:ks_uagg_main":0,
    "name:eng_x_preferred":[
        "Kapatkhalipara"
    ],
    "wof:name":"Kapatkhalipara",
    "wof:placetype":"neighbourhood",
    "wof:population":222
},
  "geometry": {"coordinates":[88.619322,22.400216],"type":"Point"}
}