{
  "type": "Feature",
  "properties": {
    "iso:country":"IN",
    "ks:ks_name":"Vishnu Nagar",
    "ks:ks_pop":591,
    "ks:ks_type":"HABITATION",
    "name:eng_x_preferred":[
        "Vishnu Nagar"
    ],
    "wof:name":"Vishnu Nagar",
    "wof:placetype":"locality",
    "wof:population":591
},
  "geometry": {"coordinates":[72.580456,26.909375],"type":"Point"}
}