{
  "type": "Feature",
  "properties": {
    "iso:country":"IN",
    "ks:ks_name":"Barora",
    "ks:ks_pop":4663,
    "ks:ks_type":"URBAN",
    "ks:ks_uagg_main":0,
    "name:eng_x_preferred":[
        "Barora"
    ],
    "wof:name":"Barora",
    "wof:placetype":"neighbourhood",
    "wof:population":4663
},
  "geometry": {"coordinates":[86.228945,23.79079],"type":"Point"}
}