{
  "type": "Feature",
  "properties": {
    "iso:country":"IN",
    "ks:ks_name":"Balamath",
    "ks:ks_pop":39,
    "ks:ks_type":"HABITATION",
    "name:eng_x_preferred":[
        "Balamath"
    ],
    "wof:name":"Balamath",
    "wof:placetype":"locality",
    "wof:population":39
},
  "geometry": {"coordinates":[74.73908900000001,14.765398],"type":"Point"}
}