{
  "type": "Feature",
  "properties": {
    "iso:country":"IN",
    "ks:ks_name":"Vaniya Fa",
    "ks:ks_pop":135,
    "ks:ks_type":"HABITATION",
    "name:eng_x_preferred":[
        "Vaniya Fa"
    ],
    "wof:name":"Vaniya Fa",
    "wof:placetype":"locality",
    "wof:population":135
},
  "geometry": {"coordinates":[72.993667,20.465861],"type":"Point"}
}