{
  "type": "Feature",
  "properties": {
    "gn:admin1_code":"36",
    "gn:admin2_code":"191.0",
    "gn:asciiname":"Kadipur Harkesh",
    "gn:country_code":"IN",
    "gn:dem":85,
    "gn:feature_class":"P",
    "gn:feature_code":"PPL",
    "gn:name":"K\u0101dipur Harkesh",
    "gn:population":0,
    "gn:timezone":"Asia/Kolkata",
    "iso:country":"IN",
    "ks:ks_alt_nam":"K\u0101dipur Harkesh",
    "ks:ks_name":"Kadipur Harkesh",
    "ks:ks_type":"VILLAGE",
    "ks:ks_uagg_main":0,
    "name:eng_x_preferred":[
        "Kadipur Harkesh"
    ],
    "name:eng_x_variant":[
        "K\u0101dipur Harkesh"
    ],
    "wof:name":"Kadipur Harkesh",
    "wof:placetype":"neighbourhood"
},
  "geometry": {"coordinates":[83.092506,26.181122],"type":"Point"}
}