{
  "type": "Feature",
  "properties": {
    "iso:country":"IN",
    "ks:ks_name":"Naya Basan Urf Dhaipukhuria",
    "ks:ks_pop":2800,
    "ks:ks_type":"HABITATION",
    "name:eng_x_preferred":[
        "Naya Basan Urf Dhaipukhuria"
    ],
    "wof:name":"Naya Basan Urf Dhaipukhuria",
    "wof:placetype":"locality",
    "wof:population":2800
},
  "geometry": {"coordinates":[87.684293,21.982799],"type":"Point"}
}