{
  "type": "Feature",
  "properties": {
    "iso:country":"IN",
    "ks:ks_name":"Manipur",
    "ks:ks_pop":165,
    "ks:ks_type":"HABITATION",
    "name:eng_x_preferred":[
        "Manipur"
    ],
    "wof:name":"Manipur",
    "wof:placetype":"locality",
    "wof:population":165
},
  "geometry": {"coordinates":[81.06169,27.234527],"type":"Point"}
}