{
  "type": "Feature",
  "properties": {
    "iso:country":"IN",
    "ks:ks_alt_nam":"CHOL DUNGARI",
    "ks:ks_name":"Chol Dungari",
    "ks:ks_pop":730,
    "ks:ks_type":"HABITATION",
    "name:eng_x_preferred":[
        "Chol Dungari"
    ],
    "wof:name":"Chol Dungari",
    "wof:placetype":"locality",
    "wof:population":730
},
  "geometry": {"coordinates":[71.04454200000001,25.521053],"type":"Point"}
}