{
  "type": "Feature",
  "properties": {
    "gn:admin1_code":"11",
    "gn:asciiname":"Ratyor Munammad Bakhsh",
    "gn:country_code":"IN",
    "gn:dem":307,
    "gn:feature_class":"P",
    "gn:feature_code":"PPL",
    "gn:name":"Ratyor Munammad Bakhsh",
    "gn:population":0,
    "gn:timezone":"Asia/Kolkata",
    "iso:country":"IN",
    "wof:name":"Ratyor Munammad Bakhsh",
    "wof:placetype":"locality"
},
  "geometry": {"coordinates":[76.6309,31.10188],"type":"Point"}
}