{
  "type": "Feature",
  "properties": {
    "gn:admin1_code":"36.0",
    "gn:admin2_code":"188.0",
    "gn:asciiname":"Konrar Pande",
    "gn:country_code":"IN",
    "gn:dem":75,
    "gn:feature_class":"P",
    "gn:feature_code":"PPL",
    "gn:name":"Konr\u0101r P\u0101nde",
    "gn:population":0,
    "gn:timezone":"Asia/Kolkata",
    "iso:country":"IN",
    "wof:name":"Konrar Pande",
    "wof:placetype":"locality"
},
  "geometry": {"coordinates":[83.56676999999998,26.33541],"type":"Point"}
}