{
  "type": "Feature",
  "properties": {
    "gn:admin1_code":"3.0",
    "gn:admin2_code":"302.0",
    "gn:asciiname":"Duaapara",
    "gn:country_code":"IN",
    "gn:dem":50,
    "gn:feature_class":"P",
    "gn:feature_code":"PPL",
    "gn:name":"Duaap\u0101ra",
    "gn:population":0,
    "gn:timezone":"Asia/Kolkata",
    "iso:country":"IN",
    "wof:name":"Duaapara",
    "wof:placetype":"locality"
},
  "geometry": {"coordinates":[90.65324,26.1217],"type":"Point"}
}