{
  "type": "Feature",
  "properties": {
    "gn:admin1_code":"2.0",
    "gn:admin2_code":"544.0",
    "gn:asciiname":"Neredupalle",
    "gn:country_code":"IN",
    "gn:dem":480,
    "gn:feature_class":"P",
    "gn:feature_code":"PPL",
    "gn:name":"Neredupalle",
    "gn:population":0,
    "gn:timezone":"Asia/Kolkata",
    "iso:country":"IN",
    "ks:ks_name":"Neredupalle",
    "ks:ks_pop":429,
    "ks:ks_type":"VILLAGE",
    "name:eng_x_preferred":[
        "Neredupalle"
    ],
    "wof:name":"Neredupalle",
    "wof:placetype":"locality",
    "wof:population":429
},
  "geometry": {"coordinates":[82.105693,18.038797],"type":"Point"}
}