{
  "type": "Feature",
  "properties": {
    "gn:admin1_code":"35",
    "gn:admin2_code":"430.0",
    "gn:asciiname":"Marhi Khurd",
    "gn:country_code":"IN",
    "gn:dem":318,
    "gn:feature_class":"P",
    "gn:feature_code":"PPL",
    "gn:name":"Marhi Khurd",
    "gn:population":0,
    "gn:timezone":"Asia/Kolkata",
    "iso:country":"IN",
    "ks:ks_name":"Madhi Khurd",
    "ks:ks_pop":1511,
    "ks:ks_type":"VILLAGE",
    "name:eng_x_preferred":[
        "Madhi Khurd"
    ],
    "name:eng_x_variant":[
        "Marhi Khurd"
    ],
    "wof:name":"Madhi Khurd",
    "wof:placetype":"locality",
    "wof:population":1511
},
  "geometry": {"coordinates":[81.592191,24.711412],"type":"Point"}
}