{
  "type": "Feature",
  "properties": {
    "iso:country":"IN",
    "ks:ks_name":"Hanaikhurd",
    "ks:ks_pop":90,
    "ks:ks_type":"HABITATION",
    "name:eng_x_preferred":[
        "Hanaikhurd"
    ],
    "wof:name":"Hanaikhurd",
    "wof:placetype":"locality",
    "wof:population":90
},
  "geometry": {"coordinates":[80.701667,20.338039],"type":"Point"}
}