{
  "type": "Feature",
  "properties": {
    "gn:admin1_code":"19.0",
    "gn:admin2_code":"582.0",
    "gn:asciiname":"Kachikadit",
    "gn:country_code":"IN",
    "gn:dem":915,
    "gn:feature_class":"P",
    "gn:feature_code":"PPL",
    "gn:name":"K\u0101chikadit",
    "gn:population":0,
    "gn:timezone":"Asia/Kolkata",
    "iso:country":"IN",
    "wof:name":"Kachikadit",
    "wof:placetype":"locality"
},
  "geometry": {"coordinates":[77.72619,13.56987],"type":"Point"}
}