{
  "type": "Feature",
  "properties": {
    "iso:country":"IN",
    "ks:ks_alt_nam":"\u0100mb\u0101ra Reserved Forest",
    "ks:ks_name":"Ambara Reserved Forest",
    "ks:ks_type":"VILLAGE",
    "name:eng_x_preferred":[
        "Ambara Reserved Forest"
    ],
    "name:eng_x_variant":[
        "\u0100mb\u0101ra Reserved Forest"
    ],
    "wof:name":"Ambara Reserved Forest",
    "wof:placetype":"locality"
},
  "geometry": {"coordinates":[78.57242100000001,21.712207],"type":"Point"}
}