{
  "type": "Feature",
  "properties": {
    "iso:country":"IN",
    "ks:ks_name":"Vhavatwadi",
    "ks:ks_pop":90,
    "ks:ks_type":"HABITATION",
    "name:eng_x_preferred":[
        "Vhavatwadi"
    ],
    "wof:name":"Vhavatwadi",
    "wof:placetype":"locality",
    "wof:population":90
},
  "geometry": {"coordinates":[73.79229100000001,16.339295],"type":"Point"}
}