{
  "type": "Feature",
  "properties": {
    "iso:country":"IN",
    "ks:ks_name":"Kankoppa",
    "ks:ks_pop":185,
    "ks:ks_type":"HABITATION",
    "name:eng_x_preferred":[
        "Kankoppa"
    ],
    "wof:name":"Kankoppa",
    "wof:placetype":"locality",
    "wof:population":185
},
  "geometry": {"coordinates":[74.814876,14.42492],"type":"Point"}
}