{
  "type": "Feature",
  "properties": {
    "iso:country":"IN",
    "ks:ks_name":"Dharmaguda",
    "ks:ks_pop":238,
    "ks:ks_type":"HABITATION",
    "name:eng_x_preferred":[
        "Dharmaguda"
    ],
    "wof:name":"Dharmaguda",
    "wof:placetype":"locality",
    "wof:population":238
},
  "geometry": {"coordinates":[78.798619,19.582563],"type":"Point"}
}