{
  "type": "Feature",
  "properties": {
    "iso:country":"IN",
    "ks:ks_alt_nam":"Simlabari Deka supa",
    "ks:ks_name":"Simlabari Deka Supa",
    "ks:ks_pop":223,
    "ks:ks_type":"HABITATION",
    "name:eng_x_preferred":[
        "Simlabari Deka Supa"
    ],
    "wof:name":"Simlabari Deka Supa",
    "wof:placetype":"locality",
    "wof:population":223
},
  "geometry": {"coordinates":[91.446252,26.698899],"type":"Point"}
}