{
  "type": "Feature",
  "properties": {
    "iso:country":"IN",
    "ks:ks_alt_nam":"Bargyan tanda",
    "ks:ks_name":"Bargyan Tanda",
    "ks:ks_pop":172,
    "ks:ks_type":"HABITATION",
    "name:eng_x_preferred":[
        "Bargyan Tanda"
    ],
    "wof:name":"Bargyan Tanda",
    "wof:placetype":"locality",
    "wof:population":172
},
  "geometry": {"coordinates":[77.365278,18.395993],"type":"Point"}
}