{
  "type": "Feature",
  "properties": {
    "iso:country":"IN",
    "ks:ks_alt_nam":"CHAMAR TOLA",
    "ks:ks_name":"Chamar Tola",
    "ks:ks_pop":271,
    "ks:ks_type":"HABITATION",
    "name:eng_x_preferred":[
        "Chamar Tola"
    ],
    "wof:name":"Chamar Tola",
    "wof:placetype":"locality",
    "wof:population":271
},
  "geometry": {"coordinates":[83.941911,26.456511],"type":"Point"}
}