{
  "type": "Feature",
  "properties": {
    "gn:admin1_code":"2.0",
    "gn:admin2_code":"553.0",
    "gn:asciiname":"Ramsagaram",
    "gn:country_code":"IN",
    "gn:dem":479,
    "gn:feature_class":"P",
    "gn:feature_code":"PPL",
    "gn:name":"R\u0101ms\u0101garam",
    "gn:population":0,
    "gn:timezone":"Asia/Kolkata",
    "iso:country":"IN",
    "wof:name":"Ramsagaram",
    "wof:placetype":"locality"
},
  "geometry": {"coordinates":[77.25190000000001,14.72227],"type":"Point"}
}