{
  "type": "Feature",
  "properties": {
    "iso:country":"IN",
    "ks:ks_name":"Medanadu",
    "ks:ks_pop":43,
    "ks:ks_type":"HABITATION",
    "name:eng_x_preferred":[
        "Medanadu"
    ],
    "wof:name":"Medanadu",
    "wof:placetype":"locality",
    "wof:population":43
},
  "geometry": {"coordinates":[76.93667000000001,11.52054],"type":"Point"}
}