{
  "type": "Feature",
  "properties": {
    "iso:country":"IN",
    "ks:ks_name":"H Colony",
    "ks:ks_pop":30,
    "ks:ks_type":"HABITATION",
    "name:eng_x_preferred":[
        "H Colony"
    ],
    "wof:name":"H Colony",
    "wof:placetype":"locality",
    "wof:population":30
},
  "geometry": {"coordinates":[76.36213100000001,13.265272],"type":"Point"}
}