{
  "type": "Feature",
  "properties": {
    "gn:admin1_code":"23.0",
    "gn:admin2_code":"52.0",
    "gn:asciiname":"Mandho Mastana Taprian",
    "gn:country_code":"IN",
    "gn:dem":310,
    "gn:feature_class":"P",
    "gn:feature_code":"PPL",
    "gn:name":"Mandho Mast\u0101na Tapri\u0101n",
    "gn:population":0,
    "gn:timezone":"Asia/Kolkata",
    "iso:country":"IN",
    "wof:name":"Mandho Mastana Taprian",
    "wof:placetype":"neighbourhood"
},
  "geometry": {"coordinates":[76.61329000000001,30.847],"type":"Point"}
}