{
  "type": "Feature",
  "properties": {
    "iso:country":"IN",
    "ks:ks_name":"Nabagram",
    "ks:ks_pop":480,
    "ks:ks_type":"VILLAGE",
    "ks:ks_uagg_main":0,
    "name:eng_x_preferred":[
        "Nabagram"
    ],
    "wof:name":"Nabagram",
    "wof:placetype":"neighbourhood",
    "wof:population":480
},
  "geometry": {"coordinates":[87.418949,23.636317],"type":"Point"}
}