{
  "type": "Feature",
  "properties": {
    "iso:country":"IN",
    "ks:ks_name":"Arilo",
    "ks:ks_pop":78,
    "ks:ks_type":"VILLAGE",
    "name:eng_x_preferred":[
        "Arilo"
    ],
    "wof:name":"Arilo",
    "wof:placetype":"locality",
    "wof:population":78
},
  "geometry": {"coordinates":[85.86321599999999,20.896046],"type":"Point"}
}