{
  "type": "Feature",
  "properties": {
    "iso:country":"IN",
    "ks:ks_name":"Halemane",
    "ks:ks_pop":22,
    "ks:ks_type":"HABITATION",
    "name:eng_x_preferred":[
        "Halemane"
    ],
    "wof:name":"Halemane",
    "wof:placetype":"locality",
    "wof:population":22
},
  "geometry": {"coordinates":[74.78924600000001,14.531705],"type":"Point"}
}