{
  "type": "Feature",
  "properties": {
    "gn:admin1_code":"10.0",
    "gn:admin2_code":"072",
    "gn:asciiname":"Dhurali",
    "gn:country_code":"IN",
    "gn:dem":257,
    "gn:feature_class":"P",
    "gn:feature_code":"PPL",
    "gn:name":"Dh\u016br\u0101li",
    "gn:population":0,
    "gn:timezone":"Asia/Kolkata",
    "iso:country":"IN",
    "wof:name":"Dhurali",
    "wof:placetype":"locality"
},
  "geometry": {"coordinates":[76.81026999999997,30.04768],"type":"Point"}
}