{
  "type": "Feature",
  "properties": {
    "gn:admin1_code":"24",
    "gn:admin2_code":"119.0",
    "gn:asciiname":"Kanakhera",
    "gn:country_code":"IN",
    "gn:dem":492,
    "gn:feature_class":"P",
    "gn:feature_code":"PPL",
    "gn:name":"K\u0101n\u0101khera",
    "gn:population":0,
    "gn:timezone":"Asia/Kolkata",
    "iso:country":"IN",
    "ks:ks_name":"Kana Khera",
    "ks:ks_pop":1879,
    "ks:ks_type":"VILLAGE",
    "name:eng_x_preferred":[
        "Kana Khera"
    ],
    "name:eng_x_variant":[
        "Kanakhera"
    ],
    "wof:name":"Kana Khera",
    "wof:placetype":"locality",
    "wof:population":1879
},
  "geometry": {"coordinates":[74.439181,26.147304],"type":"Point"}
}