{
  "type": "Feature",
  "properties": {
    "iso:country":"IN",
    "ks:ks_alt_nam":"dikewadi",
    "ks:ks_name":"Dikewadi",
    "ks:ks_pop":87,
    "ks:ks_type":"HABITATION",
    "name:eng_x_preferred":[
        "Dikewadi"
    ],
    "wof:name":"Dikewadi",
    "wof:placetype":"locality",
    "wof:population":87
},
  "geometry": {"coordinates":[73.501831,17.380939],"type":"Point"}
}