{
  "type": "Feature",
  "properties": {
    "iso:country":"IN",
    "ks:ks_name":"Minir Tola",
    "ks:ks_pop":332,
    "ks:ks_type":"HABITATION",
    "name:eng_x_preferred":[
        "Minir Tola"
    ],
    "wof:name":"Minir Tola",
    "wof:placetype":"locality",
    "wof:population":332
},
  "geometry": {"coordinates":[87.74561,26.267666],"type":"Point"}
}