{
  "type": "Feature",
  "properties": {
    "iso:country":"IN",
    "ks:ks_alt_nam":"Amdih\u0101",
    "ks:ks_name":"Amdiha",
    "ks:ks_pop":1147,
    "ks:ks_type":"VILLAGE",
    "name:eng_x_preferred":[
        "Amdiha"
    ],
    "name:eng_x_variant":[
        "Amdih\u0101"
    ],
    "wof:name":"Amdiha",
    "wof:placetype":"locality",
    "wof:population":1147
},
  "geometry": {"coordinates":[84.130369,23.893441],"type":"Point"}
}