{
  "type": "Feature",
  "properties": {
    "iso:country":"IN",
    "ks:ks_name":"Lakhipur Bajotola",
    "ks:ks_pop":299,
    "ks:ks_type":"VILLAGE",
    "ks:ks_uagg_main":0,
    "name:eng_x_preferred":[
        "Lakhipur Bajotola"
    ],
    "wof:name":"Lakhipur Bajotola",
    "wof:placetype":"neighbourhood",
    "wof:population":299
},
  "geometry": {"coordinates":[87.78256399999999,24.476517],"type":"Point"}
}