{
  "type": "Feature",
  "properties": {
    "iso:country":"IN",
    "ks:ks_name":"Medu",
    "ks:ks_pop":60,
    "ks:ks_type":"HABITATION",
    "name:eng_x_preferred":[
        "Medu"
    ],
    "wof:name":"Medu",
    "wof:placetype":"locality",
    "wof:population":60
},
  "geometry": {"coordinates":[78.779405,12.86154],"type":"Point"}
}