{
  "type": "Feature",
  "properties": {
    "iso:country":"IN",
    "ks:ks_name":"J H C",
    "ks:ks_pop":240,
    "ks:ks_type":"HABITATION",
    "name:eng_x_preferred":[
        "J H C"
    ],
    "wof:name":"J H C",
    "wof:placetype":"locality",
    "wof:population":240
},
  "geometry": {"coordinates":[74.772762,13.641319],"type":"Point"}
}