{
  "type": "Feature",
  "properties": {
    "iso:country":"IN",
    "ks:ks_name":"Kalhajpur",
    "ks:ks_pop":313,
    "ks:ks_type":"VILLAGE",
    "name:eng_x_preferred":[
        "Kalhajpur"
    ],
    "wof:name":"Kalhajpur",
    "wof:placetype":"locality",
    "wof:population":313
},
  "geometry": {"coordinates":[86.585705,23.677872],"type":"Point"}
}