{
  "type": "Feature",
  "properties": {
    "gn:admin1_code":"36",
    "gn:admin2_code":"143.0",
    "gn:asciiname":"Kheria Bahadurgarhi",
    "gn:country_code":"IN",
    "gn:dem":190,
    "gn:feature_class":"P",
    "gn:feature_code":"PPL",
    "gn:name":"Kheria Bah\u0101durgarh\u012b",
    "gn:population":0,
    "gn:timezone":"Asia/Kolkata",
    "iso:country":"IN",
    "wof:name":"Kheria Bahadurgarhi",
    "wof:placetype":"locality"
},
  "geometry": {"coordinates":[78.33036,28.09525],"type":"Point"}
}