{
  "type": "Feature",
  "properties": {
    "gn:admin1_code":"2.0",
    "gn:admin2_code":"542.0",
    "gn:asciiname":"Addakulaguda",
    "gn:country_code":"IN",
    "gn:dem":87,
    "gn:feature_class":"P",
    "gn:feature_code":"PPL",
    "gn:name":"Add\u0101kulag\u016bda",
    "gn:population":0,
    "gn:timezone":"Asia/Kolkata",
    "iso:country":"IN",
    "ks:ks_alt_nam":"Add\u0101kulag\u016bda",
    "ks:ks_name":"Addakulaguda",
    "ks:ks_pop":15,
    "ks:ks_type":"VILLAGE",
    "name:eng_x_preferred":[
        "Addakulaguda"
    ],
    "name:eng_x_variant":[
        "Add\u0101kulag\u016bda"
    ],
    "wof:name":"Addakulaguda",
    "wof:placetype":"locality",
    "wof:population":15
},
  "geometry": {"coordinates":[83.80373899999999,18.641152],"type":"Point"}
}