{
  "type": "Feature",
  "properties": {
    "iso:country":"IN",
    "ks:ks_name":"Islampur",
    "ks:ks_pop":0,
    "ks:ks_type":"VILLAGE",
    "name:eng_x_preferred":[
        "Islampur"
    ],
    "wof:name":"Islampur",
    "wof:placetype":"locality",
    "wof:population":0
},
  "geometry": {"coordinates":[88.793862,25.353919],"type":"Point"}
}