{
  "type": "Feature",
  "properties": {
    "gn:country":"IN",
    "gn:fcode":"PPL",
    "gn:population":95890,
    "iso:country":"IN",
    "name:ara_x_preferred":[
        "\u0635\u0627\u062d\u0628 \u063a\u0646\u062c"
    ],
    "name:ben_x_preferred":[
        "\u09b8\u09be\u09b9\u09c7\u09ac\u0997\u099e\u09cd\u099c"
    ],
    "name:bho_x_preferred":[
        "\u0938\u093e\u0939\u0947\u092c\u0917\u0902\u091c"
    ],
    "name:bpy_x_preferred":[
        "\u09b8\u09be\u09b9\u09bf\u09ac\u0997\u099e\u09cd\u099c"
    ],
    "name:ceb_x_preferred":[
        "S\u0101hibganj"
    ],
    "name:deu_x_preferred":[
        "Sahebganj"
    ],
    "name:eng_x_preferred":[
        "Sahebganj"
    ],
    "name:fas_x_preferred":[
        "\u0635\u0627\u062d\u0628\u200c\u06af\u0646\u062c"
    ],
    "name:fra_x_preferred":[
        "Sahebganj"
    ],
    "name:guj_x_preferred":[
        "\u0ab8\u0abe\u0ab9\u0abf\u0aac\u0a97\u0a82\u0a9c"
    ],
    "name:hif_x_preferred":[
        "Sahibganj"
    ],
    "name:hin_x_preferred":[
        "\u0938\u093e\u0939\u093f\u092c\u0917\u0902\u091c"
    ],
    "name:ita_x_preferred":[
        "Sahibganj"
    ],
    "name:jpn_x_preferred":[
        "\u30b5\u30d8\u30d6\u30ac\u30f3\u30b8"
    ],
    "name:kan_x_preferred":[
        "\u0cb8\u0cbe\u0cb9\u0cc7\u0cac\u0c82\u0c9c\u0ccd"
    ],
    "name:kor_x_preferred":[
        "\uc0ac\ud5e4\ube0c\uac04\uc988"
    ],
    "name:mar_x_preferred":[
        "\u0938\u093e\u0939\u093f\u092c\u0917\u0902\u091c"
    ],
    "name:msa_x_preferred":[
        "Sahibganj"
    ],
    "name:nep_x_preferred":[
        "\u0938\u093e\u0939\u093f\u092c\u0917\u0902\u091c"
    ],
    "name:new_x_preferred":[
        "\u0938\u093e\u0939\u0947\u092c\u0917\u091e\u094d\u091c"
    ],
    "name:nld_x_preferred":[
        "Sahebganj"
    ],
    "name:ori_x_preferred":[
        "\u0b38\u0b3e\u0b39\u0b3f\u0b2c\u0b17\u0b1e\u0b4d\u0b1c"
    ],
    "name:pnb_x_preferred":[
        "\u0635\u0627\u062d\u0628 \u06af\u0646\u062c"
    ],
    "name:por_x_preferred":[
        "Sahebganj"
    ],
    "name:rus_x_preferred":[
        "\u0421\u0430\u0445\u0438\u0431\u0433\u0430\u043d\u0434\u0436"
    ],
    "name:san_x_preferred":[
        "\u0938\u093e\u0939\u093f\u092c\u0917\u0902\u091c"
    ],
    "name:spa_x_preferred":[
        "Sahibganj"
    ],
    "name:swe_x_preferred":[
        "Sahebganj"
    ],
    "name:tam_x_preferred":[
        "\u0b9a\u0bbe\u0bb9\u0bc6\u0baa\u0bcd\u0b95\u0b9e\u0bcd"
    ],
    "name:tel_x_preferred":[
        "\u0c38\u0c3e\u0c39\u0c46\u0c2c\u0c4d \u0c17\u0c02\u0c1c\u0c4d"
    ],
    "name:ukr_x_preferred":[
        "\u0421\u0430\u0445\u0435\u0431\u0491\u0430\u043d\u0434\u0436"
    ],
    "name:urd_x_preferred":[
        "\u0633\u06c1\u06cc\u0628\u06af\u0646\u062c"
    ],
    "name:urd_x_variant":[
        "\u0635\u0627\u062d\u0628 \u06af\u0646\u062c"
    ],
    "name:vie_x_preferred":[
        "Sahibganj"
    ],
    "name:zho_x_preferred":[
        "\u8428\u5e0c\u5e03\u52a0\u6069\u6770"
    ],
    "qs:name":"Sahibganj",
    "qs:name_adm0":"India",
    "qs:name_adm1":"Jharkhand",
    "qs:photos_9k":1,
    "qs:photos_9r":1,
    "qs:photos_all":1,
    "qs:photos_sr":0,
    "qs:placetype":"Town",
    "qs:pop_sr":"8",
    "wd:wordcount":1362,
    "wof:name":"Sahibganj",
    "wof:placetype":"locality",
    "wof:population":95890
},
  "geometry": {"coordinates":[87.64908,25.24237],"type":"Point"}
}