{
  "type": "Feature",
  "properties": {
    "gn:admin1_code":"36.0",
    "gn:admin2_code":"176.0",
    "gn:asciiname":"Khujhi",
    "gn:country_code":"IN",
    "gn:dem":132,
    "gn:feature_class":"P",
    "gn:feature_code":"PPL",
    "gn:name":"Khujhi",
    "gn:population":0,
    "gn:timezone":"Asia/Kolkata",
    "iso:country":"IN",
    "ks:ks_name":"Khujjhi",
    "ks:ks_pop":537,
    "ks:ks_type":"VILLAGE",
    "name:eng_x_preferred":[
        "Khujjhi"
    ],
    "name:eng_x_variant":[
        "Khujhi"
    ],
    "wof:name":"Khujjhi",
    "wof:placetype":"locality",
    "wof:population":537
},
  "geometry": {"coordinates":[80.969993,27.207068],"type":"Point"}
}