{
  "type": "Feature",
  "properties": {
    "iso:country":"IN",
    "ks:ks_name":"Gingrai",
    "ks:ks_pop":107,
    "ks:ks_type":"VILLAGE",
    "name:eng_x_preferred":[
        "Gingrai"
    ],
    "wof:name":"Gingrai",
    "wof:placetype":"locality",
    "wof:population":107
},
  "geometry": {"coordinates":[79.141648,29.638981],"type":"Point"}
}