{
  "type": "Feature",
  "properties": {
    "iso:country":"IN",
    "ks:ks_name":"Bhugarh",
    "ks:ks_pop":24,
    "ks:ks_type":"VILLAGE",
    "name:eng_x_preferred":[
        "Bhugarh"
    ],
    "wof:name":"Bhugarh",
    "wof:placetype":"locality",
    "wof:population":24
},
  "geometry": {"coordinates":[84.62804800000001,24.277745],"type":"Point"}
}