{
  "type": "Feature",
  "properties": {
    "iso:country":"IN",
    "ks:ks_name":"Jamboota",
    "ks:ks_pop":48,
    "ks:ks_type":"HABITATION",
    "name:eng_x_preferred":[
        "Jamboota"
    ],
    "wof:name":"Jamboota",
    "wof:placetype":"locality",
    "wof:population":48
},
  "geometry": {"coordinates":[74.76052300000001,14.752347],"type":"Point"}
}