{
  "type": "Feature",
  "properties": {
    "iso:country":"IN",
    "ks:ks_name":"Kolyali",
    "ks:ks_pop":1570,
    "ks:ks_type":"HABITATION",
    "name:eng_x_preferred":[
        "Kolyali"
    ],
    "wof:name":"Kolyali",
    "wof:placetype":"locality",
    "wof:population":1570
},
  "geometry": {"coordinates":[75.719325,27.912749],"type":"Point"}
}