{
  "type": "Feature",
  "properties": {
    "iso:country":"IN",
    "ks:ks_name":"Kadamvasti",
    "ks:ks_pop":88,
    "ks:ks_type":"HABITATION",
    "name:eng_x_preferred":[
        "Kadamvasti"
    ],
    "wof:name":"Kadamvasti",
    "wof:placetype":"locality",
    "wof:population":88
},
  "geometry": {"coordinates":[73.749095,19.024275],"type":"Point"}
}