{
  "type": "Feature",
  "properties": {
    "iso:country":"IN",
    "ks:ks_name":"Summer",
    "ks:ks_pop":682,
    "ks:ks_type":"HABITATION",
    "name:eng_x_preferred":[
        "Summer"
    ],
    "wof:name":"Summer",
    "wof:placetype":"locality",
    "wof:population":682
},
  "geometry": {"coordinates":[79.030012,27.375988],"type":"Point"}
}