{
  "type": "Feature",
  "properties": {
    "iso:country":"IN",
    "ks:ks_name":"Butka",
    "ks:ks_pop":791,
    "ks:ks_type":"VILLAGE",
    "name:eng_x_preferred":[
        "Butka"
    ],
    "wof:name":"Butka",
    "wof:placetype":"locality",
    "wof:population":791
},
  "geometry": {"coordinates":[85.990752,22.297],"type":"Point"}
}