{
  "type": "Feature",
  "properties": {
    "iso:country":"IN",
    "ks:ks_name":"Nayapurosottampur",
    "ks:ks_pop":1272,
    "ks:ks_type":"HABITATION",
    "name:eng_x_preferred":[
        "Nayapurosottampur"
    ],
    "wof:name":"Nayapurosottampur",
    "wof:placetype":"locality",
    "wof:population":1272
},
  "geometry": {"coordinates":[86.771643,21.88884],"type":"Point"}
}