{
  "type": "Feature",
  "properties": {
    "iso:country":"IN",
    "ks:ks_alt_nam":"ALAKHDIHA",
    "ks:ks_name":"Alakhdiha",
    "ks:ks_pop":126,
    "ks:ks_type":"HABITATION",
    "name:eng_x_preferred":[
        "Alakhdiha"
    ],
    "wof:name":"Alakhdiha",
    "wof:placetype":"locality",
    "wof:population":126
},
  "geometry": {"coordinates":[84.98415199999999,24.264853],"type":"Point"}
}