{
  "type": "Feature",
  "properties": {
    "iso:country":"IN",
    "ks:ks_name":"C Nandihalli",
    "ks:ks_pop":1123,
    "ks:ks_type":"VILLAGE",
    "name:eng_x_preferred":[
        "C Nandihalli"
    ],
    "wof:name":"C Nandihalli",
    "wof:placetype":"locality",
    "wof:population":1123
},
  "geometry": {"coordinates":[76.96477400000001,13.439038],"type":"Point"}
}