{
  "type": "Feature",
  "properties": {
    "iso:country":"IN",
    "ks:ks_name":"Kannalakattu",
    "ks:ks_pop":84,
    "ks:ks_type":"HABITATION",
    "name:eng_x_preferred":[
        "Kannalakattu"
    ],
    "wof:name":"Kannalakattu",
    "wof:placetype":"locality",
    "wof:population":84
},
  "geometry": {"coordinates":[82.54250999999999,18.138431],"type":"Point"}
}