{
  "type": "Feature",
  "properties": {
    "gn:admin1_code":"9.0",
    "gn:admin2_code":"476",
    "gn:asciiname":"Gavridad",
    "gn:country_code":"IN",
    "gn:dem":115,
    "gn:feature_class":"P",
    "gn:feature_code":"PPL",
    "gn:name":"Gavridad",
    "gn:population":0,
    "gn:timezone":"Asia/Kolkata",
    "iso:country":"IN",
    "wof:name":"Gavridad",
    "wof:placetype":"locality"
},
  "geometry": {"coordinates":[70.79297,22.39629],"type":"Point"}
}