{
  "type": "Feature",
  "properties": {
    "iso:country":"IN",
    "ks:ks_name":"Samarghat",
    "ks:ks_pop":126,
    "ks:ks_type":"VILLAGE",
    "name:eng_x_preferred":[
        "Samarghat"
    ],
    "wof:name":"Samarghat",
    "wof:placetype":"locality",
    "wof:population":126
},
  "geometry": {"coordinates":[73.72931699999999,21.6211],"type":"Point"}
}