{
  "type": "Feature",
  "properties": {
    "iso:country":"IN",
    "ks:ks_alt_nam":"Harn\u0101d",
    "ks:ks_name":"Harnad",
    "ks:ks_pop":791,
    "ks:ks_type":"VILLAGE",
    "ks:ks_uagg_main":0,
    "name:eng_x_preferred":[
        "Harnad"
    ],
    "name:eng_x_variant":[
        "Harn\u0101d"
    ],
    "wof:name":"Harnad",
    "wof:placetype":"neighbourhood",
    "wof:population":791
},
  "geometry": {"coordinates":[85.92444399999999,23.528889],"type":"Point"}
}