{
  "type": "Feature",
  "properties": {
    "iso:country":"IN",
    "ks:ks_alt_nam":"Juna vasiya",
    "ks:ks_name":"Juna Vasiya",
    "ks:ks_pop":785,
    "ks:ks_type":"HABITATION",
    "name:eng_x_preferred":[
        "Juna Vasiya"
    ],
    "wof:name":"Juna Vasiya",
    "wof:placetype":"locality",
    "wof:population":785
},
  "geometry": {"coordinates":[72.968417,23.08875],"type":"Point"}
}