{
  "type": "Feature",
  "properties": {
    "gn:country":"IN",
    "gn:fcode":"PPL",
    "gn:population":18739,
    "iso:country":"IN",
    "name:asm_x_preferred":[
        "\u09f0\u0999\u09be\u09aa\u09be\u09f0\u09be"
    ],
    "name:ben_x_preferred":[
        "\u09b0\u09be\u0999\u09cd\u0997\u09be\u09aa\u09be\u09a1\u09bc\u09be"
    ],
    "name:bpy_x_preferred":[
        "\u09b0\u0999\u09cd\u0997\u09aa\u09be\u09a1\u09bc\u09be"
    ],
    "name:ceb_x_preferred":[
        "Rang\u0101p\u0101ra"
    ],
    "name:eng_x_preferred":[
        "Rangapara"
    ],
    "name:fra_x_preferred":[
        "Rangapara"
    ],
    "name:ita_x_preferred":[
        "Rangapara"
    ],
    "name:msa_x_preferred":[
        "Rangapara"
    ],
    "name:nan_x_preferred":[
        "Rangapara"
    ],
    "name:nld_x_preferred":[
        "Rangapara"
    ],
    "name:por_x_preferred":[
        "Rangapara"
    ],
    "name:spa_x_preferred":[
        "Rangapara"
    ],
    "name:swe_x_preferred":[
        "Rang\u0101p\u0101ra"
    ],
    "name:vie_x_preferred":[
        "Rangapara"
    ],
    "name:zho_x_preferred":[
        "\u6717\u683c\u963f\u5e15\u62c9"
    ],
    "qs:name":"Rang\u0101p\u0101ra",
    "qs:photos_9r":0,
    "qs:photos_sr":0,
    "qs:pop_sr":"6",
    "wd:wordcount":185,
    "wof:name":"Rang\u0101p\u0101ra",
    "wof:placetype":"locality",
    "wof:population":18739
},
  "geometry": {"coordinates":[92.66876000000001,26.83772],"type":"Point"}
}