{
  "type": "Feature",
  "properties": {
    "gn:admin1_code":"21.0",
    "gn:admin2_code":"395.0",
    "gn:asciiname":"Sirliguda",
    "gn:country_code":"IN",
    "gn:dem":291,
    "gn:feature_class":"P",
    "gn:feature_code":"PPL",
    "gn:name":"Sirliguda",
    "gn:population":0,
    "gn:timezone":"Asia/Kolkata",
    "iso:country":"IN",
    "wof:name":"Sirliguda",
    "wof:placetype":"locality"
},
  "geometry": {"coordinates":[82.6551,19.68191],"type":"Point"}
}