{
  "type": "Feature",
  "properties": {
    "gn:admin1_code":"35.0",
    "gn:admin2_code":"445.0",
    "gn:asciiname":"Mundikheri",
    "gn:country_code":"IN",
    "gn:dem":525,
    "gn:feature_class":"P",
    "gn:feature_code":"PPL",
    "gn:name":"Mund\u012bkheri",
    "gn:population":0,
    "gn:timezone":"Asia/Kolkata",
    "iso:country":"IN",
    "wof:name":"Mundikheri",
    "wof:placetype":"locality"
},
  "geometry": {"coordinates":[76.5973,22.98233],"type":"Point"}
}