{
  "type": "Feature",
  "properties": {
    "iso:country":"IN",
    "ks:ks_name":"Sankyura",
    "ks:ks_pop":241,
    "ks:ks_type":"VILLAGE",
    "name:eng_x_preferred":[
        "Sankyura"
    ],
    "wof:name":"Sankyura",
    "wof:placetype":"locality",
    "wof:population":241
},
  "geometry": {"coordinates":[79.98166999999999,29.827852],"type":"Point"}
}