{
  "type": "Feature",
  "properties": {
    "gn:admin1_code":"21.0",
    "gn:admin2_code":"398.0",
    "gn:asciiname":"Gothiguda",
    "gn:country_code":"IN",
    "gn:dem":363,
    "gn:feature_class":"P",
    "gn:feature_code":"PPL",
    "gn:name":"Gothig\u016bda",
    "gn:population":0,
    "gn:timezone":"Asia/Kolkata",
    "iso:country":"IN",
    "ks:ks_name":"Gatiguda",
    "ks:ks_pop":515,
    "ks:ks_type":"VILLAGE",
    "name:eng_x_preferred":[
        "Gatiguda"
    ],
    "name:eng_x_variant":[
        "Gothiguda"
    ],
    "wof:name":"Gatiguda",
    "wof:placetype":"locality",
    "wof:population":515
},
  "geometry": {"coordinates":[83.134169,18.881952],"type":"Point"}
}