{
  "type": "Feature",
  "properties": {
    "iso:country":"IN",
    "ks:ks_name":"Khajepur",
    "ks:ks_pop":730,
    "ks:ks_type":"VILLAGE",
    "ks:ks_uagg_main":0,
    "name:eng_x_preferred":[
        "Khajepur"
    ],
    "wof:name":"Khajepur",
    "wof:placetype":"neighbourhood",
    "wof:population":730
},
  "geometry": {"coordinates":[85.328551,26.407028],"type":"Point"}
}