{
  "type": "Feature",
  "properties": {
    "iso:country":"IN",
    "ks:ks_name":"Ulkottai",
    "ks:ks_pop":5285,
    "ks:ks_type":"VILLAGE",
    "ks:ks_uagg_main":0,
    "name:eng_x_preferred":[
        "Ulkottai"
    ],
    "wof:name":"Ulkottai",
    "wof:placetype":"neighbourhood",
    "wof:population":5285
},
  "geometry": {"coordinates":[79.434927,11.192442],"type":"Point"}
}