{
  "type": "Feature",
  "properties": {
    "iso:country":"IN",
    "ks:ks_name":"Panchayat Bhawn",
    "ks:ks_pop":158,
    "ks:ks_type":"HABITATION",
    "ks:ks_uagg_main":0,
    "name:eng_x_preferred":[
        "Panchayat Bhawn"
    ],
    "wof:name":"Panchayat Bhawn",
    "wof:placetype":"neighbourhood",
    "wof:population":158
},
  "geometry": {"coordinates":[84.01111,26.640143],"type":"Point"}
}