{
  "type": "Feature",
  "properties": {
    "gn:admin1_code":"19.0",
    "gn:admin2_code":"582.0",
    "gn:asciiname":"Guttenahalli",
    "gn:country_code":"IN",
    "gn:dem":759,
    "gn:feature_class":"P",
    "gn:feature_code":"PPL",
    "gn:name":"Guttenahalli",
    "gn:population":0,
    "gn:timezone":"Asia/Kolkata",
    "iso:country":"IN",
    "wof:name":"Guttenahalli",
    "wof:placetype":"locality"
},
  "geometry": {"coordinates":[77.6135,13.56873],"type":"Point"}
}