{
  "type": "Feature",
  "properties": {
    "iso:country":"IN",
    "ks:ks_name":"Sendrayanur S",
    "ks:ks_pop":500,
    "ks:ks_type":"HABITATION",
    "name:eng_x_preferred":[
        "Sendrayanur S"
    ],
    "wof:name":"Sendrayanur S",
    "wof:placetype":"locality",
    "wof:population":500
},
  "geometry": {"coordinates":[77.758796,11.545507],"type":"Point"}
}