{
  "type": "Feature",
  "properties": {
    "gn:admin1_code":"9.0",
    "gn:admin2_code":"469.0",
    "gn:asciiname":"Kabirpur",
    "gn:country_code":"IN",
    "gn:dem":198,
    "gn:feature_class":"P",
    "gn:feature_code":"PPL",
    "gn:name":"Kabirpur",
    "gn:population":0,
    "gn:timezone":"Asia/Kolkata",
    "iso:country":"IN",
    "wof:name":"Kabirpur",
    "wof:placetype":"locality"
},
  "geometry": {"coordinates":[72.61113,24.05755],"type":"Point"}
}