{
  "type": "Feature",
  "properties": {
    "iso:country":"IN",
    "ks:ks_name":"Khairoli",
    "ks:ks_pop":54,
    "ks:ks_type":"HABITATION",
    "name:eng_x_preferred":[
        "Khairoli"
    ],
    "wof:name":"Khairoli",
    "wof:placetype":"locality",
    "wof:population":54
},
  "geometry": {"coordinates":[80.00980199999999,29.608806],"type":"Point"}
}