{
  "type": "Feature",
  "properties": {
    "iso:country":"IN",
    "ks:ks_name":"Jamruddeen Pur",
    "ks:ks_pop":997,
    "ks:ks_type":"VILLAGE",
    "name:eng_x_preferred":[
        "Jamruddeen Pur"
    ],
    "wof:name":"Jamruddeen Pur",
    "wof:placetype":"locality",
    "wof:population":997
},
  "geometry": {"coordinates":[80.25488199999999,26.771921],"type":"Point"}
}