{
  "type": "Feature",
  "properties": {
    "iso:country":"IN",
    "ks:ks_alt_nam":"Stadium kunnu",
    "ks:ks_name":"Stadium Kunnu",
    "ks:ks_pop":320,
    "ks:ks_type":"HABITATION",
    "name:eng_x_preferred":[
        "Stadium Kunnu"
    ],
    "wof:name":"Stadium Kunnu",
    "wof:placetype":"locality",
    "wof:population":320
},
  "geometry": {"coordinates":[75.98953299999999,11.63665],"type":"Point"}
}