{
  "type": "Feature",
  "properties": {
    "iso:country":"IN",
    "ks:ks_name":"Noapara",
    "ks:ks_pop":333,
    "ks:ks_type":"HABITATION",
    "name:eng_x_preferred":[
        "Noapara"
    ],
    "wof:name":"Noapara",
    "wof:placetype":"locality",
    "wof:population":333
},
  "geometry": {"coordinates":[91.227214,25.818509],"type":"Point"}
}