{
  "type": "Feature",
  "properties": {
    "iso:country":"IN",
    "ks:ks_name":"Bena Gerya",
    "ks:ks_pop":742,
    "ks:ks_type":"VILLAGE",
    "name:eng_x_preferred":[
        "Bena Gerya"
    ],
    "wof:name":"Bena Gerya",
    "wof:placetype":"locality",
    "wof:population":742
},
  "geometry": {"coordinates":[87.222649,22.162381],"type":"Point"}
}