{
  "type": "Feature",
  "properties": {
    "iso:country":"IN",
    "name:ben_x_preferred":[
        "\u09b6\u09be\u09a8\u09cd\u09a4\u09bf \u09a8\u0997\u09b0"
    ],
    "name:eng_x_preferred":[
        "Shanti Nagar"
    ],
    "name:unk_x_variant":[
        "Shanti Nagar"
    ],
    "qs:gn_adm0_cc":"IN",
    "qs:gn_fcode":"PPL",
    "qs:gn_local":1277333,
    "qs:gn_nam_loc":"Bangalore, Bangalore, Karnataka, IN",
    "qs:gn_namadm1":"19",
    "qs:gn_name":"ShantiNagar",
    "qs:local_max":7342,
    "qs:local_sum":38996,
    "qs:localhoods":89,
    "qs:name":"Shanti Nagar",
    "qs:name_adm0":"India",
    "qs:name_adm1":"Karnataka",
    "qs:name_adm2":"Bangalore",
    "qs:name_local":"Bangalore",
    "qs:photo_max":2443,
    "qs:photo_sum":3945,
    "qs:placetype":"Suburb",
    "qs:quad_count":31,
    "qs:woe_adm0":23424848,
    "qs:woe_adm1":2345753,
    "qs:woe_adm2":12586572,
    "qs:woe_lau":0,
    "qs:woe_local":2295420,
    "qs:woe_ver":"7.10.0",
    "wd:wordcount":91,
    "wof:lang":[
        "eng"
    ],
    "wof:name":"Shanti Nagar",
    "wof:placetype":"neighbourhood"
},
  "geometry": {"coordinates":[77.59774,12.957442],"type":"Point"}
}