{
  "type": "Feature",
  "properties": {
    "gn:admin1_code":"36",
    "gn:admin2_code":"178.0",
    "gn:asciiname":"Samaisa Pokhta",
    "gn:country_code":"IN",
    "gn:dem":93,
    "gn:feature_class":"P",
    "gn:feature_code":"PPL",
    "gn:name":"Samaisa Pokhta",
    "gn:population":0,
    "gn:timezone":"Asia/Kolkata",
    "iso:country":"IN",
    "ks:ks_name":"Samaisa Pokhta",
    "ks:ks_type":"VILLAGE",
    "ks:ks_uagg_main":0,
    "name:eng_x_preferred":[
        "Samaisa Pokhta"
    ],
    "wof:name":"Samaisa Pokhta",
    "wof:placetype":"neighbourhood"
},
  "geometry": {"coordinates":[82.593929,26.304066],"type":"Point"}
}