{
  "type": "Feature",
  "properties": {
    "iso:country":"IN",
    "ks:ks_name":"Tambewadi",
    "ks:ks_pop":93,
    "ks:ks_type":"HABITATION",
    "name:eng_x_preferred":[
        "Tambewadi"
    ],
    "wof:name":"Tambewadi",
    "wof:placetype":"locality",
    "wof:population":93
},
  "geometry": {"coordinates":[73.473744,17.672822],"type":"Point"}
}