{
  "type": "Feature",
  "properties": {
    "iso:country":"IN",
    "ks:ks_alt_nam":"GANJUTOLI",
    "ks:ks_name":"Ganjutoli",
    "ks:ks_pop":208,
    "ks:ks_type":"HABITATION",
    "name:eng_x_preferred":[
        "Ganjutoli"
    ],
    "wof:name":"Ganjutoli",
    "wof:placetype":"locality",
    "wof:population":208
},
  "geometry": {"coordinates":[83.979157,22.557283],"type":"Point"}
}