{
  "type": "Feature",
  "properties": {
    "iso:country":"IN",
    "ks:ks_name":"Durgamandap",
    "ks:ks_pop":7299,
    "ks:ks_type":"VILLAGE",
    "name:eng_x_preferred":[
        "Durgamandap"
    ],
    "wof:name":"Durgamandap",
    "wof:placetype":"locality",
    "wof:population":7299
},
  "geometry": {"coordinates":[88.85887099999999,22.310587],"type":"Point"}
}