{
  "type": "Feature",
  "properties": {
    "iso:country":"IN",
    "ks:ks_name":"Badakumanekoppa",
    "ks:ks_pop":79,
    "ks:ks_type":"HABITATION",
    "name:eng_x_preferred":[
        "Badakumanekoppa"
    ],
    "wof:name":"Badakumanekoppa",
    "wof:placetype":"locality",
    "wof:population":79
},
  "geometry": {"coordinates":[74.322568,14.657187],"type":"Point"}
}