{
  "type": "Feature",
  "properties": {
    "gn:admin1_code":"34.0",
    "gn:admin2_code":"217.0",
    "gn:asciiname":"Ratanpura",
    "gn:country_code":"IN",
    "gn:dem":76,
    "gn:feature_class":"P",
    "gn:feature_code":"PPL",
    "gn:name":"Ratanpur\u0101",
    "gn:population":0,
    "gn:timezone":"Asia/Kolkata",
    "iso:country":"IN",
    "name:hin_x_preferred":[
        "\u0930\u0924\u0928\u092a\u0941\u0930\u093e"
    ],
    "wof:name":"Ratanpura",
    "wof:placetype":"locality"
},
  "geometry": {"coordinates":[84.24264000000002,26.50424000000001],"type":"Point"}
}