{
  "type": "Feature",
  "properties": {
    "gn:admin1_code":"24",
    "gn:admin2_code":"100.0",
    "gn:asciiname":"Nokera",
    "gn:country_code":"IN",
    "gn:dem":189,
    "gn:feature_class":"P",
    "gn:feature_code":"PPL",
    "gn:name":"Nokera",
    "gn:population":0,
    "gn:timezone":"Asia/Kolkata",
    "iso:country":"IN",
    "wof:name":"Nokera",
    "wof:placetype":"neighbourhood"
},
  "geometry": {"coordinates":[74.37217,29.88913],"type":"Point"}
}