{
  "type": "Feature",
  "properties": {
    "iso:country":"IN",
    "ks:ks_alt_nam":"Ghagmari Pt.I",
    "ks:ks_name":"Ghagmari Pt.i",
    "ks:ks_pop":73,
    "ks:ks_type":"HABITATION",
    "name:eng_x_preferred":[
        "Ghagmari Pt.i"
    ],
    "wof:name":"Ghagmari Pt.i",
    "wof:placetype":"locality",
    "wof:population":73
},
  "geometry": {"coordinates":[90.05173000000001,25.983492],"type":"Point"}
}