{
  "type": "Feature",
  "properties": {
    "iso:country":"IN",
    "ks:ks_name":"Pichladala",
    "ks:ks_pop":6,
    "ks:ks_type":"VILLAGE",
    "ks:ks_uagg_main":0,
    "name:eng_x_preferred":[
        "Pichladala"
    ],
    "wof:name":"Pichladala",
    "wof:placetype":"neighbourhood",
    "wof:population":6
},
  "geometry": {"coordinates":[78.84696099999999,30.177079],"type":"Point"}
}