{
  "type": "Feature",
  "properties": {
    "gn:admin1_code":"12",
    "gn:asciiname":"Tuandikassi",
    "gn:country_code":"IN",
    "gn:dem":1771,
    "gn:feature_class":"P",
    "gn:feature_code":"PPL",
    "gn:name":"Tuandikassi",
    "gn:population":0,
    "gn:timezone":"Asia/Kolkata",
    "iso:country":"IN",
    "wof:name":"Tuandikassi",
    "wof:placetype":"locality"
},
  "geometry": {"coordinates":[74.08196,34.04561],"type":"Point"}
}