{
  "type": "Feature",
  "properties": {
    "iso:country":"IN",
    "ks:ks_name":"Chhat Singimari Torsa",
    "ks:ks_pop":828,
    "ks:ks_type":"HABITATION",
    "name:eng_x_preferred":[
        "Chhat Singimari Torsa"
    ],
    "wof:name":"Chhat Singimari Torsa",
    "wof:placetype":"locality",
    "wof:population":828
},
  "geometry": {"coordinates":[89.325818,26.492238],"type":"Point"}
}