{
  "type": "Feature",
  "properties": {
    "iso:country":"IN",
    "ks:ks_name":"Mane Bhosale Wasti",
    "ks:ks_pop":341,
    "ks:ks_type":"HABITATION",
    "name:eng_x_preferred":[
        "Mane Bhosale Wasti"
    ],
    "wof:name":"Mane Bhosale Wasti",
    "wof:placetype":"locality",
    "wof:population":341
},
  "geometry": {"coordinates":[74.946,18.081],"type":"Point"}
}