{
  "type": "Feature",
  "properties": {
    "gn:admin1_code":"25.0",
    "gn:admin2_code":"608.0",
    "gn:asciiname":"Nallampalaiyam",
    "gn:country_code":"IN",
    "gn:dem":268,
    "gn:feature_class":"P",
    "gn:feature_code":"PPL",
    "gn:name":"Nall\u0101mp\u0101laiyam",
    "gn:population":0,
    "gn:timezone":"Asia/Kolkata",
    "iso:country":"IN",
    "ks:ks_name":"Nallampalayam",
    "ks:ks_pop":252,
    "ks:ks_type":"HABITATION",
    "name:eng_x_preferred":[
        "Nallampalayam"
    ],
    "name:eng_x_variant":[
        "Nallampalaiyam"
    ],
    "wof:name":"Nallampalayam",
    "wof:placetype":"locality",
    "wof:population":252
},
  "geometry": {"coordinates":[77.773426,11.483617],"type":"Point"}
}