{
  "type": "Feature",
  "properties": {
    "iso:country":"IN",
    "ks:ks_name":"Tapur",
    "ks:ks_pop":233,
    "ks:ks_type":"HABITATION",
    "name:eng_x_preferred":[
        "Tapur"
    ],
    "wof:name":"Tapur",
    "wof:placetype":"locality",
    "wof:population":233
},
  "geometry": {"coordinates":[80.859015,27.129795],"type":"Point"}
}