{
  "type": "Feature",
  "properties": {
    "gn:country":"IN",
    "gn:fcode":"PPL",
    "gn:population":0,
    "iso:country":"IN",
    "name:ara_x_preferred":[
        "\u062f\u0627\u062f\u0648 \u0645\u062d\u0644"
    ],
    "name:ben_bn_x_preferred":[
        "\u09a6\u09be\u09a6\u09c1 \u09ae\u09b9\u09b2"
    ],
    "name:ben_in_x_preferred":[
        "\u09a6\u09be\u09a6\u09c1 \u09ae\u09b9\u09b2"
    ],
    "name:ben_x_preferred":[
        "\u09a6\u09be\u09a6\u09c1 \u099c\u09c7\u09b2\u09be"
    ],
    "name:ceb_x_preferred":[
        "D\u0101du District"
    ],
    "name:deu_x_preferred":[
        "Dadu"
    ],
    "name:fas_x_preferred":[
        "\u0646\u0627\u062d\u06cc\u0647 \u062f\u0627\u062f\u0648"
    ],
    "name:guj_x_preferred":[
        "\u0aa6\u0abe\u0aa6\u0ac1 \u0aae\u0ab9\u0ab2"
    ],
    "name:hin_x_preferred":[
        "\u0926\u093e\u0926\u0942 \u092e\u0939\u0932"
    ],
    "name:kan_x_preferred":[
        "\u0ca6\u0ca6\u0cc1 \u0cae\u0cb9\u0cb2\u0ccd"
    ],
    "name:mal_x_preferred":[
        "\u0d26\u0d3e\u0d26\u0d41 \u0d2e\u0d39\u0d7d"
    ],
    "name:mar_x_preferred":[
        "\u0926\u093e\u0926\u0942 \u092e\u0939\u093e\u0932"
    ],
    "name:pan_x_preferred":[
        "\u0a26\u0a3e\u0a26\u0a42 \u0a2e\u0a3e\u0a39\u0a32"
    ],
    "name:pnb_x_preferred":[
        "\u0636\u0644\u0639 \u062f\u0627\u062f\u0648"
    ],
    "name:pol_x_preferred":[
        "Dystrykt Dadu"
    ],
    "name:rus_x_preferred":[
        "\u0414\u0430\u0434\u0443"
    ],
    "name:snd_x_preferred":[
        "\u062f\u0627\u062f\u0648 \u0636\u0644\u0639\u0648"
    ],
    "name:tam_x_preferred":[
        "\u0b9f\u0bbe\u0b9f\u0bc1 \u0bae\u0b95\u0bbe\u0bb2\u0bcd"
    ],
    "name:tam_x_variant":[
        "\u0ba4\u0bbe\u0ba4\u0bc1 \u0bae\u0bbe\u0bb5\u0b9f\u0bcd\u0b9f\u0bae\u0bcd"
    ],
    "name:tel_x_preferred":[
        "\u0c21\u0c3e\u0c21\u0c41 \u0c2e\u0c39\u0c32\u0c4d"
    ],
    "name:urd_x_preferred":[
        "\u062f\u0627\u062f\u0648 \u0645\u062d\u0644"
    ],
    "name:urd_x_variant":[
        "\u0636\u0644\u0639 \u062f\u0627\u062f\u0648"
    ],
    "name:zho_x_preferred":[
        "\u8fbe\u675c\u53bf"
    ],
    "qs:name":"Dadu Mahal",
    "qs:name_adm0":"India",
    "qs:name_adm1":"Jammu and Kashmir",
    "qs:photos":27,
    "qs:photos_1k":5,
    "qs:photos_9k":1,
    "qs:photos_9r":2,
    "qs:photos_all":27,
    "qs:photos_sr":2,
    "qs:placetype":"Suburb",
    "qs:pop_sr":"0",
    "wd:wordcount":133,
    "wof:name":"Dadu Mahal",
    "wof:placetype":"neighbourhood",
    "wof:population":0
},
  "geometry": {"coordinates":[74.86678000000001,34.14057],"type":"Point"}
}