{
  "type": "Feature",
  "properties": {
    "gn:admin1_code":"35.0",
    "gn:admin2_code":"425",
    "gn:asciiname":"Garrauli",
    "gn:country_code":"IN",
    "gn:dem":214,
    "gn:feature_class":"P",
    "gn:feature_code":"PPL",
    "gn:name":"Garrauli",
    "gn:population":0,
    "gn:timezone":"Asia/Kolkata",
    "iso:country":"IN",
    "wof:name":"Garrauli",
    "wof:placetype":"locality"
},
  "geometry": {"coordinates":[79.34921999999997,25.07987],"type":"Point"}
}