{
  "type": "Feature",
  "properties": {
    "iso:country":"IN",
    "ks:ks_name":"Jandamunda",
    "ks:ks_pop":0,
    "ks:ks_type":"VILLAGE",
    "name:eng_x_preferred":[
        "Jandamunda"
    ],
    "wof:name":"Jandamunda",
    "wof:placetype":"locality",
    "wof:population":0
},
  "geometry": {"coordinates":[84.69254599999999,21.391137],"type":"Point"}
}