{
  "type": "Feature",
  "properties": {
    "iso:country":"IN",
    "ks:ks_name":"Ambekarwadi",
    "ks:ks_pop":68,
    "ks:ks_type":"HABITATION",
    "name:eng_x_preferred":[
        "Ambekarwadi"
    ],
    "wof:name":"Ambekarwadi",
    "wof:placetype":"locality",
    "wof:population":68
},
  "geometry": {"coordinates":[73.58128499999999,16.170572],"type":"Point"}
}