{
  "type": "Feature",
  "properties": {
    "gn:admin1_code":"36",
    "gn:admin2_code":"179.0",
    "gn:asciiname":"Parjun Patti",
    "gn:country_code":"IN",
    "gn:dem":92,
    "gn:feature_class":"P",
    "gn:feature_code":"PPL",
    "gn:name":"Parjun Patti",
    "gn:population":0,
    "gn:timezone":"Asia/Kolkata",
    "iso:country":"IN",
    "ks:ks_name":"Parjan Patti",
    "ks:ks_pop":461,
    "ks:ks_type":"VILLAGE",
    "ks:ks_uagg_main":0,
    "name:eng_x_preferred":[
        "Parjan Patti"
    ],
    "wof:name":"Parjan Patti",
    "wof:placetype":"neighbourhood",
    "wof:population":461
},
  "geometry": {"coordinates":[82.232086,26.101203],"type":"Point"}
}