{
  "type": "Feature",
  "properties": {
    "gn:admin1_code":"39",
    "gn:admin2_code":"67.0",
    "gn:asciiname":"Sheorajpur",
    "gn:country_code":"IN",
    "gn:dem":244,
    "gn:feature_class":"P",
    "gn:feature_code":"PPL",
    "gn:name":"Sheor\u0101jpur",
    "gn:population":0,
    "gn:timezone":"Asia/Kolkata",
    "iso:country":"IN",
    "name:und_x_variant":[
        "Sheor\u0101jpur",
        "Ravid\u0101snagar"
    ],
    "wof:name":"Sheorajpur",
    "wof:placetype":"locality"
},
  "geometry": {"coordinates":[78.89179,29.2651],"type":"Point"}
}