{
  "type": "Feature",
  "properties": {
    "gn:admin1_code":"34.0",
    "gn:admin2_code":"217.0",
    "gn:asciiname":"Chak Dharamnath",
    "gn:country_code":"IN",
    "gn:dem":80,
    "gn:feature_class":"P",
    "gn:feature_code":"PPL",
    "gn:name":"Chak Dharamn\u0101th",
    "gn:population":0,
    "gn:timezone":"Asia/Kolkata",
    "iso:country":"IN",
    "ks:ks_name":"Chak Dharamnath",
    "ks:ks_pop":584,
    "ks:ks_type":"VILLAGE",
    "ks:ks_uagg_main":0,
    "name:eng_x_preferred":[
        "Chak Dharamnath"
    ],
    "wof:name":"Chak Dharamnath",
    "wof:placetype":"neighbourhood",
    "wof:population":584
},
  "geometry": {"coordinates":[84.139888,26.463064],"type":"Point"}
}