{
  "type": "Feature",
  "properties": {
    "iso:country":"IN",
    "ks:ks_name":"Saurakamalasing",
    "ks:ks_pop":56,
    "ks:ks_type":"VILLAGE",
    "name:eng_x_preferred":[
        "Saurakamalasing"
    ],
    "wof:name":"Saurakamalasing",
    "wof:placetype":"locality",
    "wof:population":56
},
  "geometry": {"coordinates":[84.123819,18.923746],"type":"Point"}
}