{
  "type": "Feature",
  "properties": {
    "iso:country":"IN",
    "ks:ks_name":"Kasitoli",
    "ks:ks_pop":123,
    "ks:ks_type":"HABITATION",
    "name:eng_x_preferred":[
        "Kasitoli"
    ],
    "wof:name":"Kasitoli",
    "wof:placetype":"locality",
    "wof:population":123
},
  "geometry": {"coordinates":[84.894971,22.443953],"type":"Point"}
}