{
  "type": "Feature",
  "properties": {
    "iso:country":"IN",
    "ks:ks_name":"Bantana Gaon",
    "ks:ks_pop":98,
    "ks:ks_type":"VILLAGE",
    "name:eng_x_preferred":[
        "Bantana Gaon"
    ],
    "wof:name":"Bantana Gaon",
    "wof:placetype":"locality",
    "wof:population":98
},
  "geometry": {"coordinates":[95.177965,27.350756],"type":"Point"}
}