{
  "type": "Feature",
  "properties": {
    "gn:admin1_code":"39.0",
    "gn:asciiname":"Nigali",
    "gn:country_code":"IN",
    "gn:dem":908,
    "gn:feature_class":"P",
    "gn:feature_code":"PPL",
    "gn:name":"Nig\u0101li",
    "gn:population":0,
    "gn:timezone":"Asia/Kolkata",
    "iso:country":"IN",
    "name:ceb_x_preferred":[
        "Nigali"
    ],
    "name:fra_x_preferred":[
        "Nigali"
    ],
    "name:mai_x_preferred":[
        "\u0928\u093f\u0917\u093e\u0932\u0940"
    ],
    "name:msa_x_preferred":[
        "Nigali"
    ],
    "name:nep_x_preferred":[
        "\u0928\u093f\u0917\u093e\u0932\u0940"
    ],
    "name:new_x_preferred":[
        "\u0928\u093f\u0917\u093e\u0932\u0940"
    ],
    "name:pol_x_preferred":[
        "Nigali"
    ],
    "wof:name":"Nigali",
    "wof:placetype":"locality"
},
  "geometry": {"coordinates":[77.75364999999999,30.57898],"type":"Point"}
}