{
  "type": "Feature",
  "properties": {
    "iso:country":"IN",
    "ks:ks_name":"Borabaribara",
    "ks:ks_pop":131,
    "ks:ks_type":"VILLAGE",
    "name:eng_x_preferred":[
        "Borabaribara"
    ],
    "wof:name":"Borabaribara",
    "wof:placetype":"locality",
    "wof:population":131
},
  "geometry": {"coordinates":[87.081744,22.796453],"type":"Point"}
}