{
  "type": "Feature",
  "properties": {
    "iso:country":"IN",
    "ks:ks_alt_nam":"CHAKI SOHAGPUR",
    "ks:ks_name":"Chaki Sohagpur",
    "ks:ks_pop":3040,
    "ks:ks_type":"HABITATION",
    "name:eng_x_preferred":[
        "Chaki Sohagpur"
    ],
    "wof:name":"Chaki Sohagpur",
    "wof:placetype":"locality",
    "wof:population":3040
},
  "geometry": {"coordinates":[84.96349499999999,26.019574],"type":"Point"}
}