{
  "type": "Feature",
  "properties": {
    "gn:admin1_code":"37",
    "gn:admin2_code":"401.0",
    "gn:asciiname":"Silaju",
    "gn:country_code":"IN",
    "gn:dem":380,
    "gn:feature_class":"P",
    "gn:feature_code":"PPL",
    "gn:name":"Sil\u0101ju",
    "gn:population":0,
    "gn:timezone":"Asia/Kolkata",
    "iso:country":"IN",
    "wof:name":"Silaju",
    "wof:placetype":"locality"
},
  "geometry": {"coordinates":[83.47880000000001,24.00883],"type":"Point"}
}