{
  "type": "Feature",
  "properties": {
    "gn:admin1_code":"37",
    "gn:admin2_code":"401.0",
    "gn:asciiname":"Silaju",
    "gn:country_code":"IN",
    "gn:dem":380,
    "gn:feature_class":"P",
    "gn:feature_code":"PPL",
    "gn:name":"Sil\u0101ju",
    "gn:population":0,
    "gn:timezone":"Asia/Kolkata",
    "iso:country":"IN",
    "ks:ks_alt_nam":"Sil\u0101ju",
    "ks:ks_name":"Silaju",
    "ks:ks_pop":1598,
    "ks:ks_type":"VILLAGE",
    "name:eng_x_preferred":[
        "Silaju"
    ],
    "name:eng_x_variant":[
        "Sil\u0101ju"
    ],
    "wof:name":"Silaju",
    "wof:placetype":"locality",
    "wof:population":1598
},
  "geometry": {"coordinates":[83.47880499999999,24.008829],"type":"Point"}
}