{
  "type": "Feature",
  "properties": {
    "iso:country":"IN",
    "ks:ks_name":"Ubapan",
    "ks:ks_pop":900,
    "ks:ks_type":"HABITATION",
    "name:eng_x_preferred":[
        "Ubapan"
    ],
    "wof:name":"Ubapan",
    "wof:placetype":"locality",
    "wof:population":900
},
  "geometry": {"coordinates":[74.134122,23.4122],"type":"Point"}
}