{
  "type": "Feature",
  "properties": {
    "gn:admin1_code":"23.0",
    "gn:admin2_code":"50.0",
    "gn:asciiname":"Chung",
    "gn:country_code":"IN",
    "gn:dem":214,
    "gn:feature_class":"P",
    "gn:feature_code":"PPL",
    "gn:name":"Chung",
    "gn:population":0,
    "gn:timezone":"Asia/Kolkata",
    "iso:country":"IN",
    "name:ceb_x_preferred":[
        "Chung"
    ],
    "name:deu_x_preferred":[
        "Chung"
    ],
    "name:fra_x_preferred":[
        "Chung"
    ],
    "name:rus_x_preferred":[
        "\u0427\u0436\u0443\u043d"
    ],
    "name:swe_x_preferred":[
        "Chung"
    ],
    "wof:name":"Chung",
    "wof:placetype":"locality"
},
  "geometry": {"coordinates":[74.65156999999998,31.30425],"type":"Point"}
}