{
  "type": "Feature",
  "properties": {
    "gn:admin1_code":"16",
    "gn:admin2_code":"505.0",
    "gn:asciiname":"Hudkeshwar Buzurg",
    "gn:country_code":"IN",
    "gn:dem":287,
    "gn:feature_class":"P",
    "gn:feature_code":"PPL",
    "gn:name":"Hudkeshwar Buzurg",
    "gn:population":0,
    "gn:timezone":"Asia/Kolkata",
    "iso:country":"IN",
    "wof:name":"Hudkeshwar Buzurg",
    "wof:placetype":"neighbourhood"
},
  "geometry": {"coordinates":[79.12736,21.08235],"type":"Point"}
}