{
  "type": "Feature",
  "properties": {
    "gn:admin1_code":"35",
    "gn:admin2_code":"452.0",
    "gn:asciiname":"Khursipar",
    "gn:country_code":"IN",
    "gn:dem":472,
    "gn:feature_class":"P",
    "gn:feature_code":"PPL",
    "gn:name":"Khurs\u012bp\u0101r",
    "gn:population":0,
    "gn:timezone":"Asia/Kolkata",
    "iso:country":"IN",
    "wof:name":"Khursipar",
    "wof:placetype":"locality"
},
  "geometry": {"coordinates":[79.61375,22.87892],"type":"Point"}
}