{
  "type": "Feature",
  "properties": {
    "gn:admin1_code":"03",
    "gn:admin2_code":"306.0",
    "gn:asciiname":"Marangaon",
    "gn:country_code":"IN",
    "gn:dem":94,
    "gn:feature_class":"P",
    "gn:feature_code":"PPL",
    "gn:name":"Marangaon",
    "gn:population":0,
    "gn:timezone":"Asia/Kolkata",
    "iso:country":"IN",
    "wof:name":"Marangaon",
    "wof:placetype":"locality"
},
  "geometry": {"coordinates":[93.29624,26.83072],"type":"Point"}
}