{
  "type": "Feature",
  "properties": {
    "gn:admin1_code":"36.0",
    "gn:admin2_code":"151.0",
    "gn:asciiname":"Daneodarpur",
    "gn:country_code":"IN",
    "gn:dem":176,
    "gn:feature_class":"P",
    "gn:feature_code":"PPL",
    "gn:name":"Daneodarpur",
    "gn:population":0,
    "gn:timezone":"Asia/Kolkata",
    "iso:country":"IN",
    "ks:ks_name":"Daneodarpur",
    "ks:ks_type":"VILLAGE",
    "name:eng_x_preferred":[
        "Daneodarpur"
    ],
    "wof:name":"Daneodarpur",
    "wof:placetype":"locality"
},
  "geometry": {"coordinates":[79.776776,28.485404],"type":"Point"}
}