{
  "type": "Feature",
  "properties": {
    "gn:admin1_code":"36.0",
    "gn:admin2_code":"151.0",
    "gn:asciiname":"Daneodarpur",
    "gn:country_code":"IN",
    "gn:dem":176,
    "gn:feature_class":"P",
    "gn:feature_code":"PPL",
    "gn:name":"Daneodarpur",
    "gn:population":0,
    "gn:timezone":"Asia/Kolkata",
    "iso:country":"IN",
    "wof:name":"Daneodarpur",
    "wof:placetype":"locality"
},
  "geometry": {"coordinates":[79.77678,28.4854],"type":"Point"}
}