{
  "type": "Feature",
  "properties": {
    "iso:country":"IN",
    "ks:ks_name":"Hosuru",
    "ks:ks_pop":10,
    "ks:ks_type":"HABITATION",
    "name:eng_x_preferred":[
        "Hosuru"
    ],
    "wof:name":"Hosuru",
    "wof:placetype":"locality",
    "wof:population":10
},
  "geometry": {"coordinates":[76.06140000000001,13.22459],"type":"Point"}
}