{
  "type": "Feature",
  "properties": {
    "iso:country":"IN",
    "ks:ks_name":"Sangeethampalli",
    "ks:ks_pop":230,
    "ks:ks_type":"HABITATION",
    "name:eng_x_preferred":[
        "Sangeethampalli"
    ],
    "wof:name":"Sangeethampalli",
    "wof:placetype":"locality",
    "wof:population":230
},
  "geometry": {"coordinates":[77.992456,13.950723],"type":"Point"}
}