{
  "type": "Feature",
  "properties": {
    "iso:country":"IN",
    "ks:ks_name":"Tharikalnala",
    "ks:ks_pop":1119,
    "ks:ks_type":"VILLAGE",
    "ks:ks_uagg_main":0,
    "name:eng_x_preferred":[
        "Tharikalnala"
    ],
    "wof:name":"Tharikalnala",
    "wof:placetype":"neighbourhood",
    "wof:population":1119
},
  "geometry": {"coordinates":[76.33515800000001,12.202302],"type":"Point"}
}