{
  "type": "Feature",
  "properties": {
    "gn:admin1_code":"38.0",
    "gn:admin2_code":"358.0",
    "gn:asciiname":"Itahe",
    "gn:country_code":"IN",
    "gn:dem":223,
    "gn:feature_class":"P",
    "gn:feature_code":"PPL",
    "gn:name":"Itahe",
    "gn:population":0,
    "gn:timezone":"Asia/Kolkata",
    "iso:country":"IN",
    "wof:name":"Itahe",
    "wof:placetype":"locality"
},
  "geometry": {"coordinates":[84.17073000000001,24.08857],"type":"Point"}
}