{
  "type": "Feature",
  "properties": {
    "iso:country":"IN",
    "ks:ks_name":"Singaram R",
    "ks:ks_pop":193,
    "ks:ks_type":"HABITATION",
    "name:eng_x_preferred":[
        "Singaram R"
    ],
    "wof:name":"Singaram R",
    "wof:placetype":"locality",
    "wof:population":193
},
  "geometry": {"coordinates":[81.066254,18.406491],"type":"Point"}
}