{
  "type": "Feature",
  "properties": {
    "iso:country":"IN",
    "ks:ks_name":"Khadiasahi",
    "ks:ks_pop":147,
    "ks:ks_type":"HABITATION",
    "name:eng_x_preferred":[
        "Khadiasahi"
    ],
    "wof:name":"Khadiasahi",
    "wof:placetype":"locality",
    "wof:population":147
},
  "geometry": {"coordinates":[86.198662,22.016349],"type":"Point"}
}