{
  "type": "Feature",
  "properties": {
    "iso:country":"IN",
    "ks:ks_name":"Katkarwadi",
    "ks:ks_pop":100,
    "ks:ks_type":"HABITATION",
    "name:eng_x_preferred":[
        "Katkarwadi"
    ],
    "wof:name":"Katkarwadi",
    "wof:placetype":"locality",
    "wof:population":100
},
  "geometry": {"coordinates":[73.269954,18.83315],"type":"Point"}
}