{
  "type": "Feature",
  "properties": {
    "iso:country":"IN",
    "ks:ks_name":"Nankar",
    "ks:ks_pop":284,
    "ks:ks_type":"VILLAGE",
    "name:eng_x_preferred":[
        "Nankar"
    ],
    "wof:name":"Nankar",
    "wof:placetype":"locality",
    "wof:population":284
},
  "geometry": {"coordinates":[87.351201,21.603215],"type":"Point"}
}