{
  "type": "Feature",
  "properties": {
    "iso:country":"IN",
    "ks:ks_name":"Belbarii",
    "ks:ks_pop":2557,
    "ks:ks_type":"HABITATION",
    "name:eng_x_preferred":[
        "Belbarii"
    ],
    "wof:name":"Belbarii",
    "wof:placetype":"locality",
    "wof:population":2557
},
  "geometry": {"coordinates":[88.22635099999999,21.862517],"type":"Point"}
}