{
  "type": "Feature",
  "properties": {
    "gn:admin1_code":"19.0",
    "gn:admin2_code":"574.0",
    "gn:asciiname":"Malatimmanahalli",
    "gn:country_code":"IN",
    "gn:dem":887,
    "gn:feature_class":"P",
    "gn:feature_code":"PPL",
    "gn:name":"Malatimmanahalli",
    "gn:population":0,
    "gn:timezone":"Asia/Kolkata",
    "iso:country":"IN",
    "wof:name":"Malatimmanahalli",
    "wof:placetype":"locality"
},
  "geometry": {"coordinates":[76.13450999999998,12.71979],"type":"Point"}
}