{
  "type": "Feature",
  "properties": {
    "gn:admin1_code":"19.0",
    "gn:admin2_code":"575.0",
    "gn:asciiname":"Ballery",
    "gn:country_code":"IN",
    "gn:dem":85,
    "gn:feature_class":"P",
    "gn:feature_code":"PPL",
    "gn:name":"Ballery",
    "gn:population":0,
    "gn:timezone":"Asia/Kolkata",
    "iso:country":"IN",
    "wof:name":"Ballery",
    "wof:placetype":"locality"
},
  "geometry": {"coordinates":[75.18462,12.71134],"type":"Point"}
}