{
  "type": "Feature",
  "properties": {
    "gn:admin1_code":"11",
    "gn:admin2_code":"33.0",
    "gn:asciiname":"Kaman",
    "gn:country_code":"IN",
    "gn:dem":1310,
    "gn:feature_class":"P",
    "gn:feature_code":"PPL",
    "gn:name":"Kam\u0101n",
    "gn:population":0,
    "gn:timezone":"Asia/Kolkata",
    "iso:country":"IN",
    "name:ben_x_preferred":[
        "\u0995\u09be\u09ae\u09be\u09a8"
    ],
    "name:bpy_x_preferred":[
        "\u0995\u09be\u09ae\u09be\u09a8"
    ],
    "name:ceb_x_preferred":[
        "Kaman"
    ],
    "name:fra_x_preferred":[
        "Kaman"
    ],
    "name:min_x_preferred":[
        "Kaman"
    ],
    "name:new_x_preferred":[
        "\u0915\u092e\u0928"
    ],
    "name:nld_x_preferred":[
        "Kaman"
    ],
    "name:por_x_preferred":[
        "Kaman"
    ],
    "name:swe_x_preferred":[
        "Kaman"
    ],
    "name:tur_x_preferred":[
        "Kaman"
    ],
    "name:vie_x_preferred":[
        "Kaman"
    ],
    "wof:name":"Kaman",
    "wof:placetype":"locality"
},
  "geometry": {"coordinates":[77.67546999999998,30.90368],"type":"Point"}
}