{
  "type": "Feature",
  "properties": {
    "iso:country":"IN",
    "ks:ks_name":"Punnakkad",
    "ks:ks_pop":2235,
    "ks:ks_type":"HABITATION",
    "name:eng_x_preferred":[
        "Punnakkad"
    ],
    "wof:name":"Punnakkad",
    "wof:placetype":"locality",
    "wof:population":2235
},
  "geometry": {"coordinates":[76.155344,10.914099],"type":"Point"}
}