{
  "type": "Feature",
  "properties": {
    "iso:country":"IN",
    "ks:ks_name":"Sajon Basti Dakhin",
    "ks:ks_pop":200,
    "ks:ks_type":"HABITATION",
    "name:eng_x_preferred":[
        "Sajon Basti Dakhin"
    ],
    "wof:name":"Sajon Basti Dakhin",
    "wof:placetype":"locality",
    "wof:population":200
},
  "geometry": {"coordinates":[95.092702,27.057054],"type":"Point"}
}