{
  "type": "Feature",
  "properties": {
    "gn:admin1_code":"35",
    "gn:admin2_code":"428.0",
    "gn:asciiname":"Masandoltola",
    "gn:country_code":"IN",
    "gn:dem":365,
    "gn:feature_class":"P",
    "gn:feature_code":"PPL",
    "gn:name":"Mas\u0101ndoltola",
    "gn:population":0,
    "gn:timezone":"Asia/Kolkata",
    "iso:country":"IN",
    "ks:ks_alt_nam":"Mas\u0101ndoltola",
    "ks:ks_name":"Masandoltola",
    "ks:ks_type":"VILLAGE",
    "name:eng_x_preferred":[
        "Masandoltola"
    ],
    "name:eng_x_variant":[
        "Mas\u0101ndoltola"
    ],
    "wof:name":"Masandoltola",
    "wof:placetype":"locality"
},
  "geometry": {"coordinates":[79.530542,23.775027],"type":"Point"}
}