{
  "type": "Feature",
  "properties": {
    "iso:country":"IN",
    "ks:ks_name":"Goga",
    "ks:ks_pop":55,
    "ks:ks_type":"VILLAGE",
    "name:eng_x_preferred":[
        "Goga"
    ],
    "wof:name":"Goga",
    "wof:placetype":"locality",
    "wof:population":55
},
  "geometry": {"coordinates":[87.64707300000001,24.79214],"type":"Point"}
}