{
  "type": "Feature",
  "properties": {
    "gn:admin1_code":"12.0",
    "gn:admin2_code":"006",
    "gn:asciiname":"Punthil",
    "gn:country_code":"IN",
    "gn:dem":1262,
    "gn:feature_class":"P",
    "gn:feature_code":"PPL",
    "gn:name":"P\u016bnthil",
    "gn:population":0,
    "gn:timezone":"Asia/Kolkata",
    "iso:country":"IN",
    "name:und_x_variant":[
        "P\u016bnthil",
        "Punthil"
    ],
    "wof:name":"Punthil",
    "wof:placetype":"locality"
},
  "geometry": {"coordinates":[74.21185,33.34763],"type":"Point"}
}