{
  "type": "Feature",
  "properties": {
    "gn:admin1_code":"12",
    "gn:admin2_code":"15.0",
    "gn:asciiname":"Aivil",
    "gn:country_code":"IN",
    "gn:dem":2051,
    "gn:feature_class":"P",
    "gn:feature_code":"PPL",
    "gn:name":"Aivil",
    "gn:population":0,
    "gn:timezone":"Asia/Kolkata",
    "iso:country":"IN",
    "wof:name":"Aivil",
    "wof:placetype":"locality"
},
  "geometry": {"coordinates":[74.87435000000001,33.60883],"type":"Point"}
}