{
  "type": "Feature",
  "properties": {
    "iso:country":"IN",
    "ks:ks_alt_nam":"Jogyanaik thanda",
    "ks:ks_name":"Jogyanaik Thanda",
    "ks:ks_pop":95,
    "ks:ks_type":"HABITATION",
    "name:eng_x_preferred":[
        "Jogyanaik Thanda"
    ],
    "wof:name":"Jogyanaik Thanda",
    "wof:placetype":"locality",
    "wof:population":95
},
  "geometry": {"coordinates":[77.981414,16.798379],"type":"Point"}
}