{
  "type": "Feature",
  "properties": {
    "iso:country":"IN",
    "ks:ks_name":"Bhujada Falia",
    "ks:ks_pop":462,
    "ks:ks_type":"HABITATION",
    "ks:ks_uagg_main":0,
    "name:eng_x_preferred":[
        "Bhujada Falia"
    ],
    "wof:name":"Bhujada Falia",
    "wof:placetype":"neighbourhood",
    "wof:population":462
},
  "geometry": {"coordinates":[72.81225000000001,20.254444],"type":"Point"}
}