{
  "type": "Feature",
  "properties": {
    "gn:admin1_code":"12.0",
    "gn:admin2_code":"001",
    "gn:asciiname":"Bandarban",
    "gn:country_code":"IN",
    "gn:dem":2240,
    "gn:feature_class":"P",
    "gn:feature_code":"PPL",
    "gn:name":"Bandarban",
    "gn:population":0,
    "gn:timezone":"Asia/Kolkata",
    "iso:country":"IN",
    "wof:name":"Bandarban",
    "wof:placetype":"locality"
},
  "geometry": {"coordinates":[74.12876999999997,34.32033],"type":"Point"}
}