{
  "type": "Feature",
  "properties": {
    "iso:country":"IN",
    "ks:ks_name":"Majipara",
    "ks:ks_pop":621,
    "ks:ks_type":"HABITATION",
    "ks:ks_uagg_main":0,
    "name:eng_x_preferred":[
        "Majipara"
    ],
    "wof:name":"Majipara",
    "wof:placetype":"neighbourhood",
    "wof:population":621
},
  "geometry": {"coordinates":[88.03676400000001,22.61033],"type":"Point"}
}