{
  "type": "Feature",
  "properties": {
    "gn:admin1_code":"36",
    "gn:admin2_code":"191.0",
    "gn:asciiname":"Kaithauli",
    "gn:country_code":"IN",
    "gn:dem":85,
    "gn:feature_class":"P",
    "gn:feature_code":"PPL",
    "gn:name":"Kaithauli",
    "gn:population":0,
    "gn:timezone":"Asia/Kolkata",
    "iso:country":"IN",
    "ks:ks_name":"Kaithauli",
    "ks:ks_pop":1404,
    "ks:ks_type":"VILLAGE",
    "ks:ks_uagg_main":0,
    "name:eng_x_preferred":[
        "Kaithauli"
    ],
    "wof:name":"Kaithauli",
    "wof:placetype":"neighbourhood",
    "wof:population":1404
},
  "geometry": {"coordinates":[82.98600500000001,26.077097],"type":"Point"}
}