{
  "type": "Feature",
  "properties": {
    "gn:admin1_code":"34.0",
    "gn:admin2_code":"203.0",
    "gn:asciiname":"Bharwalia",
    "gn:country_code":"IN",
    "gn:dem":79,
    "gn:feature_class":"P",
    "gn:feature_code":"PPL",
    "gn:name":"Bharwali\u0101",
    "gn:population":0,
    "gn:timezone":"Asia/Kolkata",
    "iso:country":"IN",
    "ks:ks_alt_nam":"Bharwali\u0101",
    "ks:ks_name":"Bharwalia",
    "ks:ks_pop":2661,
    "ks:ks_type":"VILLAGE",
    "ks:ks_uagg_main":0,
    "name:eng_x_preferred":[
        "Bharwalia"
    ],
    "name:eng_x_variant":[
        "Bharwali\u0101"
    ],
    "wof:name":"Bharwalia",
    "wof:placetype":"neighbourhood",
    "wof:population":2661
},
  "geometry": {"coordinates":[84.625293,26.888204],"type":"Point"}
}