{
  "type": "Feature",
  "properties": {
    "gn:admin1_code":"25",
    "gn:admin2_code":"612.0",
    "gn:asciiname":"Pachchalur",
    "gn:country_code":"IN",
    "gn:dem":1245,
    "gn:feature_class":"P",
    "gn:feature_code":"PPL",
    "gn:name":"P\u0101chchal\u016br",
    "gn:population":0,
    "gn:timezone":"Asia/Kolkata",
    "iso:country":"IN",
    "wof:name":"Pachchalur",
    "wof:placetype":"locality"
},
  "geometry": {"coordinates":[77.66843,10.36809],"type":"Point"}
}