{
  "type": "Feature",
  "properties": {
    "iso:country":"IN",
    "ks:ks_name":"Sonagijaddi",
    "ks:ks_pop":35,
    "ks:ks_type":"HABITATION",
    "name:eng_x_preferred":[
        "Sonagijaddi"
    ],
    "wof:name":"Sonagijaddi",
    "wof:placetype":"locality",
    "wof:population":35
},
  "geometry": {"coordinates":[74.711506,14.791377],"type":"Point"}
}