{
  "type": "Feature",
  "properties": {
    "iso:country":"IN",
    "ks:ks_name":"Gangavaram Colony",
    "ks:ks_pop":18,
    "ks:ks_type":"HABITATION",
    "name:eng_x_preferred":[
        "Gangavaram Colony"
    ],
    "wof:name":"Gangavaram Colony",
    "wof:placetype":"locality",
    "wof:population":18
},
  "geometry": {"coordinates":[80.80594499999999,18.108442],"type":"Point"}
}