{
  "type": "Feature",
  "properties": {
    "gn:admin1_code":"16",
    "gn:admin2_code":"508.0",
    "gn:asciiname":"Pendha",
    "gn:country_code":"IN",
    "gn:dem":236,
    "gn:feature_class":"P",
    "gn:feature_code":"PPL",
    "gn:name":"Pendha",
    "gn:population":0,
    "gn:timezone":"Asia/Kolkata",
    "iso:country":"IN",
    "ks:ks_name":"Pendha",
    "ks:ks_type":"VILLAGE",
    "name:eng_x_preferred":[
        "Pendha"
    ],
    "wof:name":"Pendha",
    "wof:placetype":"locality"
},
  "geometry": {"coordinates":[80.075231,20.661203],"type":"Point"}
}