{
  "type": "Feature",
  "properties": {
    "iso:country":"IN",
    "ks:ks_name":"Guthari",
    "ks:ks_pop":1076,
    "ks:ks_type":"VILLAGE",
    "ks:ks_uagg_main":0,
    "name:eng_x_preferred":[
        "Guthari"
    ],
    "wof:name":"Guthari",
    "wof:placetype":"neighbourhood",
    "wof:population":1076
},
  "geometry": {"coordinates":[88.126772,22.340959],"type":"Point"}
}