{
  "type": "Feature",
  "properties": {
    "gn:country":"IN",
    "gn:fcode":"PPL",
    "gn:population":20824,
    "iso:country":"IN",
    "name:ben_x_preferred":[
        "\u09b9\u09c1\u0995\u09c7\u09b0\u09c0"
    ],
    "name:bpy_x_preferred":[
        "\u09b9\u09c1\u0995\u09c7\u09b0\u09c0"
    ],
    "name:cat_x_preferred":[
        "Hukeri"
    ],
    "name:ceb_x_preferred":[
        "Hukeri"
    ],
    "name:deu_x_preferred":[
        "Hukeri"
    ],
    "name:eng_x_preferred":[
        "Hukeri"
    ],
    "name:fra_x_preferred":[
        "Hukeri"
    ],
    "name:guj_x_preferred":[
        "\u0ab9\u0ac1\u0a95\u0ac7\u0ab0\u0ac0"
    ],
    "name:ita_x_preferred":[
        "Hukeri"
    ],
    "name:jpn_x_preferred":[
        "\u30d5\u30b1\u30ea"
    ],
    "name:kan_x_preferred":[
        "\u0cb9\u0cc1\u0c95\u0ccd\u0c95\u0cc7\u0cb0\u0cbf"
    ],
    "name:kor_x_preferred":[
        "\ud6c4\ucee4\ub9ac"
    ],
    "name:mar_x_preferred":[
        "\u0939\u0941\u0915\u094d\u0915\u0947\u0930\u0940 \u0924\u093e\u0932\u0941\u0915\u093e"
    ],
    "name:mar_x_variant":[
        "\u0939\u0941\u0915\u094d\u0915\u0947\u0930\u0940"
    ],
    "name:mlg_x_preferred":[
        "Hukeri"
    ],
    "name:msa_x_preferred":[
        "Hukeri"
    ],
    "name:nan_x_preferred":[
        "Hukeri"
    ],
    "name:new_x_preferred":[
        "\u0939\u0941\u0915\u0947\u0930\u0940"
    ],
    "name:nld_x_preferred":[
        "Hukeri"
    ],
    "name:por_x_preferred":[
        "Hukeri"
    ],
    "name:rus_x_preferred":[
        "\u0425\u0443\u043a\u0435\u0440\u0438"
    ],
    "name:san_x_preferred":[
        "\u0939\u0941\u0915\u094d\u0915\u0947\u0930\u0940"
    ],
    "name:spa_x_preferred":[
        "Hukeri"
    ],
    "name:swe_x_preferred":[
        "Hukeri"
    ],
    "name:tam_x_preferred":[
        "\u0bb9\u0bc1\u0b95\u0bcd\u0b95\u0bc7\u0bb1\u0bbf"
    ],
    "name:tel_x_preferred":[
        "\u0c39\u0c41\u0c15\u0c47\u0c30\u0c3f"
    ],
    "name:urd_x_preferred":[
        "\u06c1\u06a9\u06cc\u0631\u06cc"
    ],
    "name:vie_x_preferred":[
        "Hukeri"
    ],
    "name:zho_x_preferred":[
        "\u80e1\u51ef\u91cc"
    ],
    "qs:name":"Hulikeri",
    "qs:name_adm0":"India",
    "qs:name_adm1":"Karnataka",
    "qs:photos_9r":0,
    "qs:photos_sr":0,
    "qs:placetype":"Town",
    "qs:pop_sr":"7",
    "wd:wordcount":16,
    "wof:name":"Hulikeri",
    "wof:placetype":"locality",
    "wof:population":20824
},
  "geometry": {"coordinates":[74.60244,16.23082],"type":"Point"}
}