{
  "type": "Feature",
  "properties": {
    "iso:country":"IN",
    "ks:ks_alt_nam":"Shaktibhagdu mal",
    "ks:ks_name":"Shaktibhagdu Mal",
    "ks:ks_pop":486,
    "ks:ks_type":"HABITATION",
    "name:eng_x_preferred":[
        "Shaktibhagdu Mal"
    ],
    "wof:name":"Shaktibhagdu Mal",
    "wof:placetype":"locality",
    "wof:population":486
},
  "geometry": {"coordinates":[80.614536,23.200028],"type":"Point"}
}