{
  "type": "Feature",
  "properties": {
    "iso:country":"IN",
    "ks:ks_name":"Basgohra",
    "ks:ks_pop":416,
    "ks:ks_type":"VILLAGE",
    "name:eng_x_preferred":[
        "Basgohra"
    ],
    "wof:name":"Basgohra",
    "wof:placetype":"locality",
    "wof:population":416
},
  "geometry": {"coordinates":[86.041122,24.137562],"type":"Point"}
}