{
  "type": "Feature",
  "properties": {
    "gn:admin1_code":"2.0",
    "gn:admin2_code":"544.0",
    "gn:asciiname":"Balaparay",
    "gn:country_code":"IN",
    "gn:dem":1094,
    "gn:feature_class":"P",
    "gn:feature_code":"PPL",
    "gn:name":"Balapar\u0101y",
    "gn:population":0,
    "gn:timezone":"Asia/Kolkata",
    "iso:country":"IN",
    "wof:name":"Balaparay",
    "wof:placetype":"locality"
},
  "geometry": {"coordinates":[82.53694,18.21318],"type":"Point"}
}