{
  "type": "Feature",
  "properties": {
    "iso:country":"IN",
    "ks:ks_name":"Modoli",
    "ks:ks_pop":1444,
    "ks:ks_type":"HABITATION",
    "name:eng_x_preferred":[
        "Modoli"
    ],
    "wof:name":"Modoli",
    "wof:placetype":"locality",
    "wof:population":1444
},
  "geometry": {"coordinates":[75.651141,11.863858],"type":"Point"}
}