{
  "type": "Feature",
  "properties": {
    "gn:admin1_code":"34.0",
    "gn:admin2_code":"225.0",
    "gn:asciiname":"Dharmai Chak",
    "gn:country_code":"IN",
    "gn:dem":60,
    "gn:feature_class":"P",
    "gn:feature_code":"PPL",
    "gn:name":"Dharmai Chak",
    "gn:population":0,
    "gn:timezone":"Asia/Kolkata",
    "iso:country":"IN",
    "ks:ks_name":"Dharmai Chak",
    "ks:ks_pop":1048,
    "ks:ks_type":"VILLAGE",
    "name:eng_x_preferred":[
        "Dharmai Chak"
    ],
    "wof:name":"Dharmai Chak",
    "wof:placetype":"locality",
    "wof:population":1048
},
  "geometry": {"coordinates":[87.05000800000001,25.015923],"type":"Point"}
}