{
  "type": "Feature",
  "properties": {
    "iso:country":"IN",
    "ks:ks_name":"Pashim Para",
    "ks:ks_pop":855,
    "ks:ks_type":"HABITATION",
    "ks:ks_uagg_main":0,
    "name:eng_x_preferred":[
        "Pashim Para"
    ],
    "wof:name":"Pashim Para",
    "wof:placetype":"neighbourhood",
    "wof:population":855
},
  "geometry": {"coordinates":[89.123414,26.507207],"type":"Point"}
}