{
  "type": "Feature",
  "properties": {
    "gn:admin1_code":"40.0",
    "gn:admin2_code":"537",
    "gn:asciiname":"Ketreddipalli",
    "gn:country_code":"IN",
    "gn:dem":584,
    "gn:feature_class":"P",
    "gn:feature_code":"PPL",
    "gn:name":"Ketreddipalli",
    "gn:population":0,
    "gn:timezone":"Asia/Kolkata",
    "iso:country":"IN",
    "wof:name":"Ketreddipalli",
    "wof:placetype":"locality"
},
  "geometry": {"coordinates":[78.22410000000001,17.27429],"type":"Point"}
}