{
  "type": "Feature",
  "properties": {
    "iso:country":"IN",
    "ks:ks_name":"Tumballi",
    "ks:ks_pop":33,
    "ks:ks_type":"HABITATION",
    "name:eng_x_preferred":[
        "Tumballi"
    ],
    "wof:name":"Tumballi",
    "wof:placetype":"locality",
    "wof:population":33
},
  "geometry": {"coordinates":[74.742441,14.796488],"type":"Point"}
}