{
  "type": "Feature",
  "properties": {
    "gn:admin1_code":"34.0",
    "gn:admin2_code":"239.0",
    "gn:asciiname":"Atiawan",
    "gn:country_code":"IN",
    "gn:dem":69,
    "gn:feature_class":"P",
    "gn:feature_code":"PPL",
    "gn:name":"Ati\u0101w\u0101n",
    "gn:population":0,
    "gn:timezone":"Asia/Kolkata",
    "iso:country":"IN",
    "ks:ks_alt_nam":"Ati\u0101w\u0101n",
    "ks:ks_name":"Atiawan",
    "ks:ks_pop":1261,
    "ks:ks_type":"VILLAGE",
    "ks:ks_uagg_main":0,
    "name:eng_x_preferred":[
        "Atiawan"
    ],
    "name:eng_x_variant":[
        "Ati\u0101w\u0101n"
    ],
    "wof:name":"Atiawan",
    "wof:placetype":"neighbourhood",
    "wof:population":1261
},
  "geometry": {"coordinates":[85.15058999999999,25.206567],"type":"Point"}
}