{
  "type": "Feature",
  "properties": {
    "iso:country":"IN",
    "ks:ks_name":"Mahadevpara",
    "ks:ks_pop":294,
    "ks:ks_type":"HABITATION",
    "name:eng_x_preferred":[
        "Mahadevpara"
    ],
    "wof:name":"Mahadevpara",
    "wof:placetype":"locality",
    "wof:population":294
},
  "geometry": {"coordinates":[83.795935,22.121293],"type":"Point"}
}