{
  "type": "Feature",
  "properties": {
    "iso:country":"IN",
    "ks:ks_name":"Suddagunna",
    "ks:ks_pop":48,
    "ks:ks_type":"HABITATION",
    "name:eng_x_preferred":[
        "Suddagunna"
    ],
    "wof:name":"Suddagunna",
    "wof:placetype":"locality",
    "wof:population":48
},
  "geometry": {"coordinates":[81.83647000000001,17.323378],"type":"Point"}
}