{
  "type": "Feature",
  "properties": {
    "gn:admin1_code":"37.0",
    "gn:admin2_code":"416.0",
    "gn:asciiname":"Jaram",
    "gn:country_code":"IN",
    "gn:dem":541,
    "gn:feature_class":"P",
    "gn:feature_code":"PPL",
    "gn:name":"J\u0101ram",
    "gn:population":0,
    "gn:timezone":"Asia/Kolkata",
    "iso:country":"IN",
    "ks:ks_alt_nam":"J\u0101ram",
    "ks:ks_name":"Jaram",
    "ks:ks_pop":630,
    "ks:ks_type":"VILLAGE",
    "name:eng_x_preferred":[
        "Jaram"
    ],
    "name:eng_x_variant":[
        "J\u0101ram"
    ],
    "wof:name":"Jaram",
    "wof:placetype":"locality",
    "wof:population":630
},
  "geometry": {"coordinates":[81.49357500000001,18.877016],"type":"Point"}
}