{
  "type": "Feature",
  "properties": {
    "iso:country":"IN",
    "ks:ks_name":"Andaran Debottar",
    "ks:ks_pop":13,
    "ks:ks_type":"VILLAGE",
    "name:eng_x_preferred":[
        "Andaran Debottar"
    ],
    "wof:name":"Andaran Debottar",
    "wof:placetype":"locality",
    "wof:population":13
},
  "geometry": {"coordinates":[88.96855600000001,26.247513],"type":"Point"}
}