{
  "type": "Feature",
  "properties": {
    "gn:admin1_code":"9.0",
    "gn:admin2_code":"493",
    "gn:asciiname":"Amalpada",
    "gn:cc2":"IN",
    "gn:country_code":"IN",
    "gn:dem":96,
    "gn:feature_class":"P",
    "gn:feature_code":"PPL",
    "gn:name":"\u0100malp\u0101da",
    "gn:population":0,
    "gn:timezone":"Asia/Kolkata",
    "iso:country":"IN",
    "name:und_x_variant":[
        "Borg\u0101m",
        "\u0100malp\u0101da"
    ],
    "wof:name":"Amalpada",
    "wof:placetype":"locality"
},
  "geometry": {"coordinates":[73.68333,21.25],"type":"Point"}
}