{
  "type": "Feature",
  "properties": {
    "iso:country":"IN",
    "ks:ks_name":"Jambhulwadi",
    "ks:ks_pop":764,
    "ks:ks_type":"VILLAGE",
    "ks:ks_uagg_main":0,
    "name:eng_x_preferred":[
        "Jambhulwadi"
    ],
    "wof:name":"Jambhulwadi",
    "wof:placetype":"locality",
    "wof:population":764
},
  "geometry": {"coordinates":[73.83863100000001,18.427436],"type":"Point"}
}