{
  "type": "Feature",
  "properties": {
    "iso:country":"IN",
    "ks:ks_name":"Aimmanda",
    "ks:ks_pop":29,
    "ks:ks_type":"HABITATION",
    "name:eng_x_preferred":[
        "Aimmanda"
    ],
    "wof:name":"Aimmanda",
    "wof:placetype":"locality",
    "wof:population":29
},
  "geometry": {"coordinates":[75.804444,12.339722],"type":"Point"}
}