{
  "type": "Feature",
  "properties": {
    "iso:country":"IN",
    "ks:ks_name":"Garhi Jakhoda",
    "ks:ks_pop":783,
    "ks:ks_type":"VILLAGE",
    "name:eng_x_preferred":[
        "Garhi Jakhoda"
    ],
    "wof:name":"Garhi Jakhoda",
    "wof:placetype":"locality",
    "wof:population":783
},
  "geometry": {"coordinates":[77.735781,26.686742],"type":"Point"}
}