{
  "type": "Feature",
  "properties": {
    "gn:admin1_code":"36",
    "gn:admin2_code":"173.0",
    "gn:asciiname":"Marwan",
    "gn:country_code":"IN",
    "gn:dem":92,
    "gn:feature_class":"P",
    "gn:feature_code":"PPL",
    "gn:name":"Marw\u0101n",
    "gn:population":0,
    "gn:timezone":"Asia/Kolkata",
    "iso:country":"IN",
    "ks:ks_alt_nam":"Marw\u0101n",
    "ks:ks_name":"Marwan",
    "ks:ks_type":"VILLAGE",
    "name:eng_x_preferred":[
        "Marwan"
    ],
    "name:eng_x_variant":[
        "Marw\u0101n"
    ],
    "wof:name":"Marwan",
    "wof:placetype":"locality"
},
  "geometry": {"coordinates":[82.06272300000001,25.903732],"type":"Point"}
}