{
  "type": "Feature",
  "properties": {
    "iso:country":"IN",
    "ks:ks_name":"Kidangoor",
    "ks:ks_pop":250,
    "ks:ks_type":"HABITATION",
    "name:eng_x_preferred":[
        "Kidangoor"
    ],
    "wof:name":"Kidangoor",
    "wof:placetype":"locality",
    "wof:population":250
},
  "geometry": {"coordinates":[78.995425,9.90192],"type":"Point"}
}