{
  "type": "Feature",
  "properties": {
    "gn:admin1_code":"16.0",
    "gn:admin2_code":"512.0",
    "gn:asciiname":"Tupa",
    "gn:country_code":"IN",
    "gn:dem":444,
    "gn:feature_class":"P",
    "gn:feature_code":"PPL",
    "gn:name":"T\u016bpa",
    "gn:population":0,
    "gn:timezone":"Asia/Kolkata",
    "iso:country":"IN",
    "name:ceb_x_preferred":[
        "Tupa"
    ],
    "name:deu_x_preferred":[
        "Tupa"
    ],
    "name:fra_x_preferred":[
        "Tupa"
    ],
    "name:ita_x_preferred":[
        "Tupa"
    ],
    "name:nld_x_preferred":[
        "Tup\u00e3"
    ],
    "name:pol_x_preferred":[
        "Tupa"
    ],
    "name:swa_x_preferred":[
        "Tupa"
    ],
    "name:swe_x_preferred":[
        "Tupa"
    ],
    "wof:name":"Tupa",
    "wof:placetype":"locality"
},
  "geometry": {"coordinates":[77.41812,19.62994],"type":"Point"}
}