{
  "type": "Feature",
  "properties": {
    "iso:country":"IN",
    "ks:ks_name":"Gundavu",
    "ks:ks_pop":32,
    "ks:ks_type":"HABITATION",
    "name:eng_x_preferred":[
        "Gundavu"
    ],
    "wof:name":"Gundavu",
    "wof:placetype":"locality",
    "wof:population":32
},
  "geometry": {"coordinates":[75.13685700000001,13.033479],"type":"Point"}
}