{
  "type": "Feature",
  "properties": {
    "gn:admin1_code":"23.0",
    "gn:admin2_code":"49.0",
    "gn:asciiname":"Thariewal",
    "gn:country_code":"IN",
    "gn:dem":237,
    "gn:feature_class":"P",
    "gn:feature_code":"PPL",
    "gn:name":"Thariew\u0101l",
    "gn:population":0,
    "gn:timezone":"Asia/Kolkata",
    "iso:country":"IN",
    "ks:ks_alt_nam":"Thariew\u0101l",
    "ks:ks_name":"Thariewal",
    "ks:ks_type":"VILLAGE",
    "ks:ks_uagg_main":0,
    "name:eng_x_preferred":[
        "Thariewal"
    ],
    "name:eng_x_variant":[
        "Thariew\u0101l"
    ],
    "wof:name":"Thariewal",
    "wof:placetype":"neighbourhood"
},
  "geometry": {"coordinates":[75.061283,31.772182],"type":"Point"}
}