{
  "type": "Feature",
  "properties": {
    "gn:admin1_code":"19.0",
    "gn:admin2_code":"582.0",
    "gn:asciiname":"Pindipapanahalli",
    "gn:country_code":"IN",
    "gn:dem":912,
    "gn:feature_class":"P",
    "gn:feature_code":"PPL",
    "gn:name":"Pindipapanahalli",
    "gn:population":0,
    "gn:timezone":"Asia/Kolkata",
    "iso:country":"IN",
    "wof:name":"Pindipapanahalli",
    "wof:placetype":"locality"
},
  "geometry": {"coordinates":[77.9196,13.4048],"type":"Point"}
}