{
  "type": "Feature",
  "properties": {
    "gn:admin1_code":"35",
    "gn:admin2_code":"453.0",
    "gn:asciiname":"Amaldih",
    "gn:country_code":"IN",
    "gn:dem":799,
    "gn:feature_class":"P",
    "gn:feature_code":"PPL",
    "gn:name":"Amald\u012bh",
    "gn:population":0,
    "gn:timezone":"Asia/Kolkata",
    "iso:country":"IN",
    "wof:name":"Amaldih",
    "wof:placetype":"locality"
},
  "geometry": {"coordinates":[81.55684000000002,22.71862],"type":"Point"}
}