{
  "type": "Feature",
  "properties": {
    "iso:country":"IN",
    "ks:ks_name":"Chanala",
    "ks:ks_pop":596,
    "ks:ks_type":"VILLAGE",
    "ks:ks_uagg_main":0,
    "name:eng_x_preferred":[
        "Chanala"
    ],
    "wof:name":"Chanala",
    "wof:placetype":"neighbourhood",
    "wof:population":596
},
  "geometry": {"coordinates":[92.44323900000001,24.564395],"type":"Point"}
}