{
  "type": "Feature",
  "properties": {
    "gn:admin1_code":"36",
    "gn:admin2_code":"185.0",
    "gn:asciiname":"Gaura",
    "gn:country_code":"IN",
    "gn:dem":91,
    "gn:feature_class":"P",
    "gn:feature_code":"PPL",
    "gn:name":"Gaura",
    "gn:population":0,
    "gn:timezone":"Asia/Kolkata",
    "iso:country":"IN",
    "name:fin_x_preferred":[
        "Kes\u00e4kynttil\u00e4t"
    ],
    "name:fra_x_preferred":[
        "Gaura"
    ],
    "name:ita_x_preferred":[
        "Gaura"
    ],
    "name:jpn_x_preferred":[
        "\u30ac\u30a6\u30e9\u5c5e"
    ],
    "name:por_x_preferred":[
        "Gaura"
    ],
    "name:spa_x_preferred":[
        "Gaura"
    ],
    "name:swe_x_preferred":[
        "Sommarljussl\u00e4ktet"
    ],
    "name:zho_x_preferred":[
        "\u5c71\u6843\u8349\u5c5e"
    ],
    "wof:name":"Gaura",
    "wof:placetype":"locality"
},
  "geometry": {"coordinates":[82.76839,26.85057],"type":"Point"}
}