{
  "type": "Feature",
  "properties": {
    "iso:country":"IN",
    "ks:ks_name":"Upla Chotiya",
    "ks:ks_pop":461,
    "ks:ks_type":"HABITATION",
    "name:eng_x_preferred":[
        "Upla Chotiya"
    ],
    "wof:name":"Upla Chotiya",
    "wof:placetype":"locality",
    "wof:population":461
},
  "geometry": {"coordinates":[73.96831400000001,24.479956],"type":"Point"}
}