{
  "type": "Feature",
  "properties": {
    "iso:country":"IN",
    "ks:ks_alt_nam":"Indakona khaspara",
    "ks:ks_name":"Indakona Khaspara",
    "ks:ks_pop":387,
    "ks:ks_type":"HABITATION",
    "name:eng_x_preferred":[
        "Indakona Khaspara"
    ],
    "wof:name":"Indakona Khaspara",
    "wof:placetype":"locality",
    "wof:population":387
},
  "geometry": {"coordinates":[83.63247200000001,23.341277],"type":"Point"}
}