{
  "type": "Feature",
  "properties": {
    "iso:country":"IN",
    "ks:ks_name":"Ghweri",
    "ks:ks_pop":41,
    "ks:ks_type":"HABITATION",
    "name:eng_x_preferred":[
        "Ghweri"
    ],
    "wof:name":"Ghweri",
    "wof:placetype":"locality",
    "wof:population":41
},
  "geometry": {"coordinates":[79.146041,29.57031],"type":"Point"}
}