{
  "type": "Feature",
  "properties": {
    "iso:country":"IN",
    "ks:ks_name":"Kalathinkadavu",
    "ks:ks_pop":857,
    "ks:ks_type":"HABITATION",
    "name:eng_x_preferred":[
        "Kalathinkadavu"
    ],
    "wof:name":"Kalathinkadavu",
    "wof:placetype":"locality",
    "wof:population":857
},
  "geometry": {"coordinates":[76.2201,11.289178],"type":"Point"}
}