{
  "type": "Feature",
  "properties": {
    "iso:country":"IN",
    "ks:ks_name":"Upala Falia",
    "ks:ks_pop":615,
    "ks:ks_type":"HABITATION",
    "name:eng_x_preferred":[
        "Upala Falia"
    ],
    "wof:name":"Upala Falia",
    "wof:placetype":"locality",
    "wof:population":615
},
  "geometry": {"coordinates":[73.32252800000001,20.607222],"type":"Point"}
}