{
  "type": "Feature",
  "properties": {
    "gn:admin1_code":"39.0",
    "gn:admin2_code":"61.0",
    "gn:asciiname":"Dumnikot",
    "gn:country_code":"IN",
    "gn:dem":1795,
    "gn:feature_class":"P",
    "gn:feature_code":"PPL",
    "gn:name":"Dumn\u012bkot",
    "gn:population":0,
    "gn:timezone":"Asia/Kolkata",
    "iso:country":"IN",
    "ks:ks_alt_nam":"Dumn\u012bkot",
    "ks:ks_name":"Dumnikot",
    "ks:ks_type":"VILLAGE",
    "name:eng_x_preferred":[
        "Dumnikot"
    ],
    "name:eng_x_variant":[
        "Dumn\u012bkot"
    ],
    "wof:name":"Dumnikot",
    "wof:placetype":"locality"
},
  "geometry": {"coordinates":[79.224783,29.96622],"type":"Point"}
}