{
  "type": "Feature",
  "properties": {
    "gn:admin1_code":"3.0",
    "gn:admin2_code":"316.0",
    "gn:asciiname":"Karaikandi",
    "gn:country_code":"IN",
    "gn:dem":30,
    "gn:feature_class":"P",
    "gn:feature_code":"PPL",
    "gn:name":"Karaikandi",
    "gn:population":0,
    "gn:timezone":"Asia/Kolkata",
    "iso:country":"IN",
    "wof:name":"Karaikandi",
    "wof:placetype":"locality"
},
  "geometry": {"coordinates":[92.86749,24.86545],"type":"Point"}
}