{
  "type": "Feature",
  "properties": {
    "iso:country":"IN",
    "ks:ks_name":"Bind Basti",
    "ks:ks_pop":220,
    "ks:ks_type":"HABITATION",
    "name:eng_x_preferred":[
        "Bind Basti"
    ],
    "wof:name":"Bind Basti",
    "wof:placetype":"locality",
    "wof:population":220
},
  "geometry": {"coordinates":[82.072717,25.465189],"type":"Point"}
}