{
  "type": "Feature",
  "properties": {
    "iso:country":"IN",
    "ks:ks_alt_nam":"Deopur -II",
    "ks:ks_name":"Deopur -ii",
    "ks:ks_pop":1199,
    "ks:ks_type":"HABITATION",
    "name:eng_x_preferred":[
        "Deopur -ii"
    ],
    "wof:name":"Deopur -ii",
    "wof:placetype":"locality",
    "wof:population":1199
},
  "geometry": {"coordinates":[79.138036,24.450658],"type":"Point"}
}