{
  "type": "Feature",
  "properties": {
    "iso:country":"IN",
    "ks:ks_name":"Pallapatti",
    "ks:ks_pop":955,
    "ks:ks_type":"VILLAGE",
    "ks:ks_uagg_main":0,
    "name:eng_x_preferred":[
        "Pallapatti"
    ],
    "wof:name":"Pallapatti",
    "wof:placetype":"locality",
    "wof:population":955
},
  "geometry": {"coordinates":[77.954123,10.355638],"type":"Point"}
}