{
  "type": "Feature",
  "properties": {
    "iso:country":"IN",
    "ks:ks_alt_nam":"gura dahar",
    "ks:ks_name":"Gura Dahar",
    "ks:ks_pop":4356,
    "ks:ks_type":"HABITATION",
    "name:eng_x_preferred":[
        "Gura Dahar"
    ],
    "wof:name":"Gura Dahar",
    "wof:placetype":"locality",
    "wof:population":4356
},
  "geometry": {"coordinates":[75.642342,27.831158],"type":"Point"}
}