{
  "type": "Feature",
  "properties": {
    "gn:admin1_code":"39",
    "gn:admin2_code":"61.0",
    "gn:asciiname":"Kande",
    "gn:country_code":"IN",
    "gn:dem":1500,
    "gn:feature_class":"P",
    "gn:feature_code":"PPL",
    "gn:name":"K\u0101nde",
    "gn:population":0,
    "gn:timezone":"Asia/Kolkata",
    "iso:country":"IN",
    "name:ceb_x_preferred":[
        "Kande"
    ],
    "name:swe_x_preferred":[
        "Kande"
    ],
    "wof:name":"Kande",
    "wof:placetype":"locality"
},
  "geometry": {"coordinates":[78.77755000000001,30.15387],"type":"Point"}
}