{
  "type": "Feature",
  "properties": {
    "iso:country":"IN",
    "ks:ks_name":"Kanakula",
    "ks:ks_pop":176,
    "ks:ks_type":"VILLAGE",
    "name:eng_x_preferred":[
        "Kanakula"
    ],
    "wof:name":"Kanakula",
    "wof:placetype":"locality",
    "wof:population":176
},
  "geometry": {"coordinates":[83.289331,22.416058],"type":"Point"}
}