{
  "type": "Feature",
  "properties": {
    "gn:admin1_code":"3.0",
    "gn:admin2_code":"300.0",
    "gn:asciiname":"Harjhora",
    "gn:country_code":"IN",
    "gn:dem":46,
    "gn:feature_class":"P",
    "gn:feature_code":"PPL",
    "gn:name":"H\u0101rjhora",
    "gn:population":0,
    "gn:timezone":"Asia/Kolkata",
    "iso:country":"IN",
    "wof:name":"Harjhora",
    "wof:placetype":"locality"
},
  "geometry": {"coordinates":[89.98523,26.25985],"type":"Point"}
}