{
  "type": "Feature",
  "properties": {
    "iso:country":"IN",
    "ks:ks_alt_nam":"BHATTITOLI",
    "ks:ks_name":"Bhattitoli",
    "ks:ks_pop":101,
    "ks:ks_type":"HABITATION",
    "name:eng_x_preferred":[
        "Bhattitoli"
    ],
    "wof:name":"Bhattitoli",
    "wof:placetype":"locality",
    "wof:population":101
},
  "geometry": {"coordinates":[83.852943,22.812126],"type":"Point"}
}