{
  "type": "Feature",
  "properties": {
    "iso:country":"IN",
    "ks:ks_name":"Juviwadi",
    "ks:ks_pop":250,
    "ks:ks_type":"VILLAGE",
    "name:eng_x_preferred":[
        "Juviwadi"
    ],
    "wof:name":"Juviwadi",
    "wof:placetype":"locality",
    "wof:population":250
},
  "geometry": {"coordinates":[73.48972500000001,16.463004],"type":"Point"}
}