{
  "type": "Feature",
  "properties": {
    "iso:country":"IN",
    "ks:ks_name":"Aranmanaipudur",
    "ks:ks_pop":3709,
    "ks:ks_type":"HABITATION",
    "ks:ks_uagg_main":0,
    "name:eng_x_preferred":[
        "Aranmanaipudur"
    ],
    "wof:name":"Aranmanaipudur",
    "wof:placetype":"locality",
    "wof:population":3709
},
  "geometry": {"coordinates":[77.48867300000001,9.999743],"type":"Point"}
}