{
  "type": "Feature",
  "properties": {
    "gn:admin1_code":"16.0",
    "gn:admin2_code":"509.0",
    "gn:asciiname":"Kitari Mendha",
    "gn:country_code":"IN",
    "gn:dem":261,
    "gn:feature_class":"P",
    "gn:feature_code":"PPL",
    "gn:name":"Kit\u0101ri Mendh\u0101",
    "gn:population":0,
    "gn:timezone":"Asia/Kolkata",
    "iso:country":"IN",
    "wof:name":"Kitari Mendha",
    "wof:placetype":"locality"
},
  "geometry": {"coordinates":[79.72752,20.5186],"type":"Point"}
}