{
  "type": "Feature",
  "properties": {
    "iso:country":"IN",
    "ks:ks_name":"Brahminwadi",
    "ks:ks_pop":68,
    "ks:ks_type":"HABITATION",
    "ks:ks_uagg_main":0,
    "name:eng_x_preferred":[
        "Brahminwadi"
    ],
    "wof:name":"Brahminwadi",
    "wof:placetype":"neighbourhood",
    "wof:population":68
},
  "geometry": {"coordinates":[73.526831,17.329111],"type":"Point"}
}