{
  "type": "Feature",
  "properties": {
    "gn:admin1_code":"28.0",
    "gn:admin2_code":"332.0",
    "gn:asciiname":"Durgapur",
    "gn:country_code":"IN",
    "gn:dem":33,
    "gn:feature_class":"P",
    "gn:feature_code":"PPL",
    "gn:name":"Durg\u0101pur",
    "gn:population":0,
    "gn:timezone":"Asia/Kolkata",
    "iso:country":"IN",
    "wof:name":"Durgapur",
    "wof:placetype":"locality"
},
  "geometry": {"coordinates":[87.90531999999997,25.25236],"type":"Point"}
}