{
  "type": "Feature",
  "properties": {
    "iso:country":"IN",
    "ks:ks_name":"Vaganpada",
    "ks:ks_pop":167,
    "ks:ks_type":"HABITATION",
    "name:eng_x_preferred":[
        "Vaganpada"
    ],
    "wof:name":"Vaganpada",
    "wof:placetype":"locality",
    "wof:population":167
},
  "geometry": {"coordinates":[72.99693499999999,20.046025],"type":"Point"}
}