{
  "type": "Feature",
  "properties": {
    "iso:country":"IN",
    "ks:ks_name":"Kautia",
    "ks:ks_pop":656,
    "ks:ks_type":"VILLAGE",
    "name:eng_x_preferred":[
        "Kautia"
    ],
    "wof:name":"Kautia",
    "wof:placetype":"locality",
    "wof:population":656
},
  "geometry": {"coordinates":[87.42624600000001,21.935431],"type":"Point"}
}