{
  "type": "Feature",
  "properties": {
    "iso:country":"IN",
    "ks:ks_name":"Tola Banarchua",
    "ks:ks_pop":279,
    "ks:ks_type":"VILLAGE",
    "name:eng_x_preferred":[
        "Tola Banarchua"
    ],
    "wof:name":"Tola Banarchua",
    "wof:placetype":"locality",
    "wof:population":279
},
  "geometry": {"coordinates":[86.891925,24.631368],"type":"Point"}
}