{
  "type": "Feature",
  "properties": {
    "gn:admin1_code":"21",
    "gn:admin2_code":"392.0",
    "gn:asciiname":"Rajopali",
    "gn:country_code":"IN",
    "gn:dem":129,
    "gn:feature_class":"P",
    "gn:feature_code":"PPL",
    "gn:name":"Rajop\u0101li",
    "gn:population":0,
    "gn:timezone":"Asia/Kolkata",
    "iso:country":"IN",
    "name:und_x_variant":[
        "Rajop\u0101li",
        "Gulap\u0101ra"
    ],
    "wof:name":"Rajopali",
    "wof:placetype":"locality"
},
  "geometry": {"coordinates":[83.80609,21.04023],"type":"Point"}
}