{
  "type": "Feature",
  "properties": {
    "iso:country":"IN",
    "ks:ks_name":"Panda Deeh",
    "ks:ks_pop":87,
    "ks:ks_type":"HABITATION",
    "name:eng_x_preferred":[
        "Panda Deeh"
    ],
    "wof:name":"Panda Deeh",
    "wof:placetype":"locality",
    "wof:population":87
},
  "geometry": {"coordinates":[82.899576,27.25779],"type":"Point"}
}