{
  "type": "Feature",
  "properties": {
    "gn:admin1_code":"21.0",
    "gn:admin2_code":"396.0",
    "gn:asciiname":"Nilaguda",
    "gn:country_code":"IN",
    "gn:dem":298,
    "gn:feature_class":"P",
    "gn:feature_code":"PPL",
    "gn:name":"N\u012blaguda",
    "gn:population":0,
    "gn:timezone":"Asia/Kolkata",
    "iso:country":"IN",
    "wof:name":"Nilaguda",
    "wof:placetype":"locality"
},
  "geometry": {"coordinates":[83.94926,19.21446],"type":"Point"}
}