{
  "type": "Feature",
  "properties": {
    "gn:admin1_code":"21.0",
    "gn:admin2_code":"396.0",
    "gn:asciiname":"Nilaguda",
    "gn:country_code":"IN",
    "gn:dem":298,
    "gn:feature_class":"P",
    "gn:feature_code":"PPL",
    "gn:name":"N\u012blaguda",
    "gn:population":0,
    "gn:timezone":"Asia/Kolkata",
    "iso:country":"IN",
    "ks:ks_name":"Niluguda",
    "ks:ks_pop":7,
    "ks:ks_type":"VILLAGE",
    "name:eng_x_preferred":[
        "Niluguda"
    ],
    "name:eng_x_variant":[
        "Nilaguda"
    ],
    "wof:name":"Niluguda",
    "wof:placetype":"locality",
    "wof:population":7
},
  "geometry": {"coordinates":[83.947086,19.211945],"type":"Point"}
}