{
  "type": "Feature",
  "properties": {
    "iso:country":"IN",
    "ks:ks_alt_nam":"Barw\u0101m\u0101rni",
    "ks:ks_name":"Barwamarni",
    "ks:ks_pop":390,
    "ks:ks_type":"VILLAGE",
    "name:eng_x_preferred":[
        "Barwamarni"
    ],
    "name:eng_x_variant":[
        "Barw\u0101m\u0101rni"
    ],
    "wof:name":"Barwamarni",
    "wof:placetype":"locality",
    "wof:population":390
},
  "geometry": {"coordinates":[86.957505,24.087091],"type":"Point"}
}