{
  "type": "Feature",
  "properties": {
    "gn:admin1_code":"16.0",
    "gn:admin2_code":"527.0",
    "gn:asciiname":"Pimprad",
    "gn:country_code":"IN",
    "gn:dem":555,
    "gn:feature_class":"P",
    "gn:feature_code":"PPL",
    "gn:name":"Pimprad",
    "gn:population":0,
    "gn:timezone":"Asia/Kolkata",
    "iso:country":"IN",
    "wof:name":"Pimprad",
    "wof:placetype":"locality"
},
  "geometry": {"coordinates":[74.53459000000002,17.98296000000001],"type":"Point"}
}