{
  "type": "Feature",
  "properties": {
    "iso:country":"IN",
    "ks:ks_name":"Astapur",
    "ks:ks_pop":65,
    "ks:ks_type":"HABITATION",
    "name:eng_x_preferred":[
        "Astapur"
    ],
    "wof:name":"Astapur",
    "wof:placetype":"locality",
    "wof:population":65
},
  "geometry": {"coordinates":[79.711476,26.406866],"type":"Point"}
}