{
  "type": "Feature",
  "properties": {
    "iso:country":"IN",
    "ks:ks_name":"Bada",
    "ks:ks_pop":3600,
    "ks:ks_type":"VILLAGE",
    "ks:ks_uagg_main":0,
    "name:eng_x_preferred":[
        "Bada"
    ],
    "wof:name":"Bada",
    "wof:placetype":"neighbourhood",
    "wof:population":3600
},
  "geometry": {"coordinates":[74.76303799999999,13.188378],"type":"Point"}
}