{
  "type": "Feature",
  "properties": {
    "iso:country":"IN",
    "ks:ks_name":"Palaskola",
    "ks:ks_pop":4119,
    "ks:ks_type":"VILLAGE",
    "ks:ks_uagg_main":0,
    "name:eng_x_preferred":[
        "Palaskola"
    ],
    "wof:name":"Palaskola",
    "wof:placetype":"neighbourhood",
    "wof:population":4119
},
  "geometry": {"coordinates":[86.661962,23.495707],"type":"Point"}
}