{
  "type": "Feature",
  "properties": {
    "iso:country":"IN",
    "ks:ks_name":"Milik Gopalpur",
    "ks:ks_pop":103,
    "ks:ks_type":"VILLAGE",
    "name:eng_x_preferred":[
        "Milik Gopalpur"
    ],
    "wof:name":"Milik Gopalpur",
    "wof:placetype":"locality",
    "wof:population":103
},
  "geometry": {"coordinates":[87.855611,24.818099],"type":"Point"}
}