{
  "type": "Feature",
  "properties": {
    "iso:country":"IN",
    "ks:ks_alt_nam":"DAS TOLA",
    "ks:ks_name":"Das Tola",
    "ks:ks_pop":181,
    "ks:ks_type":"HABITATION",
    "name:eng_x_preferred":[
        "Das Tola"
    ],
    "wof:name":"Das Tola",
    "wof:placetype":"locality",
    "wof:population":181
},
  "geometry": {"coordinates":[86.892256,25.229931],"type":"Point"}
}