{
  "type": "Feature",
  "properties": {
    "iso:country":"IN",
    "ks:ks_name":"Berbera",
    "ks:ks_pop":331,
    "ks:ks_type":"VILLAGE",
    "name:eng_x_preferred":[
        "Berbera"
    ],
    "wof:name":"Berbera",
    "wof:placetype":"locality",
    "wof:population":331
},
  "geometry": {"coordinates":[82.947273,20.646756],"type":"Point"}
}