{
  "type": "Feature",
  "properties": {
    "iso:country":"IN",
    "ks:ks_name":"Hannemata",
    "ks:ks_pop":580,
    "ks:ks_type":"HABITATION",
    "name:eng_x_preferred":[
        "Hannemata"
    ],
    "wof:name":"Hannemata",
    "wof:placetype":"locality",
    "wof:population":580
},
  "geometry": {"coordinates":[74.39439900000001,14.447016],"type":"Point"}
}