{
  "type": "Feature",
  "properties": {
    "iso:country":"IN",
    "ks:ks_name":"Nihal Singh Ki Dhani",
    "ks:ks_pop":150,
    "ks:ks_type":"HABITATION",
    "name:eng_x_preferred":[
        "Nihal Singh Ki Dhani"
    ],
    "wof:name":"Nihal Singh Ki Dhani",
    "wof:placetype":"locality",
    "wof:population":150
},
  "geometry": {"coordinates":[75.382864,29.202053],"type":"Point"}
}