{
  "type": "Feature",
  "properties": {
    "iso:country":"IN",
    "ks:ks_name":"Pangarnatha",
    "ks:ks_pop":244,
    "ks:ks_type":"HABITATION",
    "name:eng_x_preferred":[
        "Pangarnatha"
    ],
    "wof:name":"Pangarnatha",
    "wof:placetype":"locality",
    "wof:population":244
},
  "geometry": {"coordinates":[85.90147,21.135332],"type":"Point"}
}