{
  "type": "Feature",
  "properties": {
    "iso:country":"IN",
    "ks:ks_name":"Yaligihundi",
    "ks:ks_pop":998,
    "ks:ks_type":"HABITATION",
    "name:eng_x_preferred":[
        "Yaligihundi"
    ],
    "wof:name":"Yaligihundi",
    "wof:placetype":"locality",
    "wof:population":998
},
  "geometry": {"coordinates":[76.68414199999999,12.253819],"type":"Point"}
}