{
  "type": "Feature",
  "properties": {
    "iso:country":"IN",
    "ks:ks_name":"Suchia Pahar Pt V",
    "ks:ks_pop":272,
    "ks:ks_type":"HABITATION",
    "name:eng_x_preferred":[
        "Suchia Pahar Pt V"
    ],
    "wof:name":"Suchia Pahar Pt V",
    "wof:placetype":"locality",
    "wof:population":272
},
  "geometry": {"coordinates":[90.856686,25.952733],"type":"Point"}
}