{
  "type": "Feature",
  "properties": {
    "gn:admin1_code":"21",
    "gn:admin2_code":"395.0",
    "gn:asciiname":"Sherpadar",
    "gn:country_code":"IN",
    "gn:dem":733,
    "gn:feature_class":"P",
    "gn:feature_code":"PPL",
    "gn:name":"Sherpadar",
    "gn:population":0,
    "gn:timezone":"Asia/Kolkata",
    "iso:country":"IN",
    "wof:name":"Sherpadar",
    "wof:placetype":"locality"
},
  "geometry": {"coordinates":[83.10375000000001,19.58604],"type":"Point"}
}