{
  "type": "Feature",
  "properties": {
    "gn:admin1_code":"36",
    "gn:admin2_code":"173.0",
    "gn:asciiname":"Shah Jamalpur",
    "gn:country_code":"IN",
    "gn:dem":110,
    "gn:feature_class":"P",
    "gn:feature_code":"PPL",
    "gn:name":"Sh\u0101h Jam\u0101lpur",
    "gn:population":0,
    "gn:timezone":"Asia/Kolkata",
    "iso:country":"IN",
    "ks:ks_name":"Sah Jamalpur",
    "ks:ks_pop":677,
    "ks:ks_type":"HABITATION",
    "ks:ks_uagg_main":0,
    "name:eng_x_preferred":[
        "Sah Jamalpur"
    ],
    "wof:name":"Sah Jamalpur",
    "wof:placetype":"neighbourhood",
    "wof:population":677
},
  "geometry": {"coordinates":[81.59066799999999,25.730096],"type":"Point"}
}