{
  "type": "Feature",
  "properties": {
    "iso:country":"IN",
    "ks:ks_name":"Salunkhewasti",
    "ks:ks_pop":275,
    "ks:ks_type":"HABITATION",
    "name:eng_x_preferred":[
        "Salunkhewasti"
    ],
    "wof:name":"Salunkhewasti",
    "wof:placetype":"locality",
    "wof:population":275
},
  "geometry": {"coordinates":[74.11702200000001,18.112594],"type":"Point"}
}