{
  "type": "Feature",
  "properties": {
    "iso:country":"IN",
    "ks:ks_name":"Aramalebetta",
    "ks:ks_pop":260,
    "ks:ks_type":"HABITATION",
    "name:eng_x_preferred":[
        "Aramalebetta"
    ],
    "wof:name":"Aramalebetta",
    "wof:placetype":"locality",
    "wof:population":260
},
  "geometry": {"coordinates":[75.245216,12.987471],"type":"Point"}
}