{
  "type": "Feature",
  "properties": {
    "iso:country":"IN",
    "ks:ks_name":"Kulanar",
    "ks:ks_pop":324,
    "ks:ks_type":"VILLAGE",
    "name:eng_x_preferred":[
        "Kulanar"
    ],
    "wof:name":"Kulanar",
    "wof:placetype":"locality",
    "wof:population":324
},
  "geometry": {"coordinates":[81.44449,19.830726],"type":"Point"}
}