{
  "type": "Feature",
  "properties": {
    "iso:country":"IN",
    "ks:ks_name":"Neladka",
    "ks:ks_pop":95,
    "ks:ks_type":"HABITATION",
    "name:eng_x_preferred":[
        "Neladka"
    ],
    "wof:name":"Neladka",
    "wof:placetype":"locality",
    "wof:population":95
},
  "geometry": {"coordinates":[75.501042,12.719371],"type":"Point"}
}