{
  "type": "Feature",
  "properties": {
    "gn:admin1_code":"34.0",
    "gn:admin2_code":"232.0",
    "gn:asciiname":"Pakhraha",
    "gn:country_code":"IN",
    "gn:dem":66,
    "gn:feature_class":"P",
    "gn:feature_code":"PPL",
    "gn:name":"Pakhr\u0101ha",
    "gn:population":0,
    "gn:timezone":"Asia/Kolkata",
    "iso:country":"IN",
    "ks:ks_alt_nam":"Pakhr\u0101ha",
    "ks:ks_name":"Pakhraha",
    "ks:ks_type":"VILLAGE",
    "ks:ks_uagg_main":0,
    "name:eng_x_preferred":[
        "Pakhraha"
    ],
    "name:eng_x_variant":[
        "Pakhr\u0101ha"
    ],
    "wof:name":"Pakhraha",
    "wof:placetype":"neighbourhood"
},
  "geometry": {"coordinates":[84.32439100000001,25.542974],"type":"Point"}
}