{
  "type": "Feature",
  "properties": {
    "gn:admin1_code":"24.0",
    "gn:admin2_code":"104.0",
    "gn:asciiname":"Chandra Ka Bas",
    "gn:country_code":"IN",
    "gn:dem":237,
    "gn:feature_class":"P",
    "gn:feature_code":"PPL",
    "gn:name":"Chandra Ka B\u0101s",
    "gn:population":0,
    "gn:timezone":"Asia/Kolkata",
    "iso:country":"IN",
    "wof:name":"Chandra Ka Bas",
    "wof:placetype":"locality"
},
  "geometry": {"coordinates":[76.82595999999999,27.43002000000001],"type":"Point"}
}