{
  "type": "Feature",
  "properties": {
    "gn:admin1_code":"16",
    "gn:admin2_code":"510.0",
    "gn:asciiname":"Vaki",
    "gn:country_code":"IN",
    "gn:dem":330,
    "gn:feature_class":"P",
    "gn:feature_code":"PPL",
    "gn:name":"V\u0101ki",
    "gn:population":0,
    "gn:timezone":"Asia/Kolkata",
    "iso:country":"IN",
    "name:ceb_x_preferred":[
        "Vaki"
    ],
    "name:est_x_preferred":[
        "Vaki"
    ],
    "name:fra_x_preferred":[
        "Vaki"
    ],
    "name:hye_x_preferred":[
        "\u054e\u0561\u056f\u056b"
    ],
    "name:pol_x_preferred":[
        "Vaki"
    ],
    "name:spa_x_preferred":[
        "Vaki"
    ],
    "name:swe_x_preferred":[
        "Vaki"
    ],
    "name:vol_x_preferred":[
        "Vaki"
    ],
    "wof:name":"Vaki",
    "wof:placetype":"locality"
},
  "geometry": {"coordinates":[78.36116,20.19903],"type":"Point"}
}