{
  "type": "Feature",
  "properties": {
    "gn:admin1_code":"24.0",
    "gn:admin2_code":"102",
    "gn:asciiname":"Gudhawas",
    "gn:country_code":"IN",
    "gn:dem":239,
    "gn:feature_class":"P",
    "gn:feature_code":"PPL",
    "gn:name":"Gudh\u0101w\u0101s",
    "gn:population":0,
    "gn:timezone":"Asia/Kolkata",
    "iso:country":"IN",
    "name:eng_x_preferred":[
        "Gudh\u0101w\u0101s"
    ],
    "name:und_x_variant":[
        "Gudda",
        "Hemr\u0101nw\u0101s"
    ],
    "wof:name":"Gudhawas",
    "wof:placetype":"locality"
},
  "geometry": {"coordinates":[74.67069000000002,28.54018],"type":"Point"}
}