{
  "type": "Feature",
  "properties": {
    "gn:admin1_code":"11",
    "gn:admin2_code":"33.0",
    "gn:asciiname":"Patkmar Banuni",
    "gn:country_code":"IN",
    "gn:dem":1948,
    "gn:feature_class":"P",
    "gn:feature_code":"PPL",
    "gn:name":"Patkmar Banuni",
    "gn:population":0,
    "gn:timezone":"Asia/Kolkata",
    "iso:country":"IN",
    "wof:name":"Patkmar Banuni",
    "wof:placetype":"locality"
},
  "geometry": {"coordinates":[77.24309000000002,31.08963],"type":"Point"}
}