{
  "type": "Feature",
  "properties": {
    "iso:country":"IN",
    "ks:ks_name":"Borong Tinisti",
    "ks:ks_pop":65,
    "ks:ks_type":"HABITATION",
    "ks:ks_uagg_main":0,
    "name:eng_x_preferred":[
        "Borong Tinisti"
    ],
    "wof:name":"Borong Tinisti",
    "wof:placetype":"neighbourhood",
    "wof:population":65
},
  "geometry": {"coordinates":[95.08278900000001,27.724232],"type":"Point"}
}