{
  "type": "Feature",
  "properties": {
    "iso:country":"IN",
    "ks:ks_name":"Mitihani",
    "ks:ks_pop":198,
    "ks:ks_type":"HABITATION",
    "name:eng_x_preferred":[
        "Mitihani"
    ],
    "wof:name":"Mitihani",
    "wof:placetype":"locality",
    "wof:population":198
},
  "geometry": {"coordinates":[83.324215,24.263213],"type":"Point"}
}