{
  "type": "Feature",
  "properties": {
    "gn:admin1_code":"35.0",
    "gn:admin2_code":"457.0",
    "gn:asciiname":"Rasimata",
    "gn:country_code":"IN",
    "gn:dem":612,
    "gn:feature_class":"P",
    "gn:feature_code":"PPL",
    "gn:name":"R\u0101simata",
    "gn:population":0,
    "gn:timezone":"Asia/Kolkata",
    "iso:country":"IN",
    "ks:ks_name":"Rasimeta",
    "ks:ks_pop":258,
    "ks:ks_type":"VILLAGE",
    "name:eng_x_preferred":[
        "Rasimeta"
    ],
    "name:eng_x_variant":[
        "Rasimata"
    ],
    "wof:name":"Rasimeta",
    "wof:placetype":"locality",
    "wof:population":258
},
  "geometry": {"coordinates":[80.594978,21.736909],"type":"Point"}
}