{
  "type": "Feature",
  "properties": {
    "gn:admin1_code":"34.0",
    "gn:admin2_code":"239.0",
    "gn:asciiname":"Bairam Chak",
    "gn:country_code":"IN",
    "gn:dem":65,
    "gn:feature_class":"P",
    "gn:feature_code":"PPL",
    "gn:name":"Bair\u0101m Chak",
    "gn:population":0,
    "gn:timezone":"Asia/Kolkata",
    "iso:country":"IN",
    "ks:ks_alt_nam":"Bair\u0101m Chak",
    "ks:ks_name":"Bairam Chak",
    "ks:ks_pop":1199,
    "ks:ks_type":"VILLAGE",
    "ks:ks_uagg_main":0,
    "name:eng_x_preferred":[
        "Bairam Chak"
    ],
    "name:eng_x_variant":[
        "Bair\u0101m Chak"
    ],
    "wof:name":"Bairam Chak",
    "wof:placetype":"neighbourhood",
    "wof:population":1199
},
  "geometry": {"coordinates":[85.015336,25.29533],"type":"Point"}
}