{
  "type": "Feature",
  "properties": {
    "iso:country":"IN",
    "ks:ks_name":"Tulsaghat",
    "ks:ks_type":"VILLAGE",
    "name:eng_x_preferred":[
        "Tulsaghat"
    ],
    "wof:name":"Tulsaghat",
    "wof:placetype":"locality"
},
  "geometry": {"coordinates":[81.712141,22.28579],"type":"Point"}
}