{
  "type": "Feature",
  "properties": {
    "gn:admin1_code":"11.0",
    "gn:admin2_code":"33.0",
    "gn:asciiname":"Shanar",
    "gn:country_code":"IN",
    "gn:dem":2275,
    "gn:feature_class":"P",
    "gn:feature_code":"PPL",
    "gn:name":"Shan\u0101r",
    "gn:population":0,
    "gn:timezone":"Asia/Kolkata",
    "iso:country":"IN",
    "wof:name":"Shanar",
    "wof:placetype":"locality"
},
  "geometry": {"coordinates":[77.58098000000003,31.33232000000001],"type":"Point"}
}