{
  "type": "Feature",
  "properties": {
    "gn:admin1_code":"34",
    "gn:admin2_code":"237.0",
    "gn:asciiname":"Worhanpur",
    "gn:country_code":"IN",
    "gn:dem":82,
    "gn:feature_class":"P",
    "gn:feature_code":"PPL",
    "gn:name":"Worhanpur",
    "gn:population":0,
    "gn:timezone":"Asia/Kolkata",
    "iso:country":"IN",
    "wof:name":"Worhanpur",
    "wof:placetype":"locality"
},
  "geometry": {"coordinates":[85.53081999999998,24.95715],"type":"Point"}
}