{
  "type": "Feature",
  "properties": {
    "iso:country":"IN",
    "ks:ks_name":"Lapahari",
    "ks:ks_pop":650,
    "ks:ks_type":"VILLAGE",
    "name:eng_x_preferred":[
        "Lapahari"
    ],
    "wof:name":"Lapahari",
    "wof:placetype":"locality",
    "wof:population":650
},
  "geometry": {"coordinates":[86.798958,23.533851],"type":"Point"}
}