{
  "type": "Feature",
  "properties": {
    "gn:admin1_code":"37.0",
    "gn:admin2_code":"405.0",
    "gn:asciiname":"Pandariya",
    "gn:country_code":"IN",
    "gn:dem":242,
    "gn:feature_class":"P",
    "gn:feature_code":"PPL",
    "gn:name":"Pandariya",
    "gn:population":0,
    "gn:timezone":"Asia/Kolkata",
    "iso:country":"IN",
    "name:ben_x_preferred":[
        "\u09aa\u09be\u09a8\u09cd\u09a1\u09be\u09b0\u09bf\u09af\u09bc\u09be"
    ],
    "name:bpy_x_preferred":[
        "\u09aa\u09be\u09a8\u09cd\u09a1\u09be\u09b0\u09bf\u09af\u09bc\u09be"
    ],
    "name:ceb_x_preferred":[
        "Pandaria"
    ],
    "name:ita_x_preferred":[
        "Pandariya"
    ],
    "name:msa_x_preferred":[
        "Pandariya"
    ],
    "name:nld_x_preferred":[
        "Pandariya"
    ],
    "name:por_x_preferred":[
        "Pandariya"
    ],
    "name:spa_x_preferred":[
        "Pandariya"
    ],
    "name:swe_x_preferred":[
        "Pandaria"
    ],
    "name:tgl_x_preferred":[
        "Pandariya"
    ],
    "name:urd_x_preferred":[
        "\u067e\u0646\u0688\u0627\u0631\u06cc\u0627"
    ],
    "name:vie_x_preferred":[
        "Pandariya"
    ],
    "name:zho_x_preferred":[
        "\u6f58\u8fbe\u91cc\u8036"
    ],
    "wof:name":"Pandariya",
    "wof:placetype":"locality"
},
  "geometry": {"coordinates":[82.86136999999999,21.96112],"type":"Point"}
}