{
  "type": "Feature",
  "properties": {
    "gn:admin1_code":"37.0",
    "gn:admin2_code":"405.0",
    "gn:asciiname":"Pandariya",
    "gn:country_code":"IN",
    "gn:dem":242,
    "gn:feature_class":"P",
    "gn:feature_code":"PPL",
    "gn:name":"Pandariya",
    "gn:population":0,
    "gn:timezone":"Asia/Kolkata",
    "iso:country":"IN",
    "wof:name":"Pandariya",
    "wof:placetype":"locality"
},
  "geometry": {"coordinates":[82.86136999999999,21.96112],"type":"Point"}
}