{
  "type": "Feature",
  "properties": {
    "gn:admin1_code":"35.0",
    "gn:admin2_code":"446",
    "gn:asciiname":"Goharganj",
    "gn:country_code":"IN",
    "gn:dem":463,
    "gn:feature_class":"P",
    "gn:feature_code":"PPL",
    "gn:name":"Goharganj",
    "gn:population":0,
    "gn:timezone":"Asia/Kolkata",
    "iso:country":"IN",
    "wof:name":"Goharganj",
    "wof:placetype":"locality"
},
  "geometry": {"coordinates":[77.67416,23.02672],"type":"Point"}
}