{
  "type": "Feature",
  "properties": {
    "gn:admin1_code":"16.0",
    "gn:admin2_code":"511.0",
    "gn:asciiname":"Pachanda",
    "gn:country_code":"IN",
    "gn:dem":380,
    "gn:feature_class":"P",
    "gn:feature_code":"PPL",
    "gn:name":"Pachanda",
    "gn:population":0,
    "gn:timezone":"Asia/Kolkata",
    "iso:country":"IN",
    "wof:name":"Pachanda",
    "wof:placetype":"locality"
},
  "geometry": {"coordinates":[77.98865000000001,19.74207],"type":"Point"}
}