{
  "type": "Feature",
  "properties": {
    "gn:country":"IN",
    "gn:fcode":"PPL",
    "gn:population":20071,
    "iso:country":"IN",
    "name:ara_x_preferred":[
        "\u0628\u0648\u0644\u0648\u0627\u0645\u0627"
    ],
    "name:ben_x_preferred":[
        "\u09aa\u09c1\u09b2\u09ac\u09be\u09ae\u09be"
    ],
    "name:bho_x_preferred":[
        "\u092a\u0941\u0932\u0935\u093e\u092e\u093e"
    ],
    "name:ceb_x_preferred":[
        "Pulwama"
    ],
    "name:deu_x_preferred":[
        "Pulwama"
    ],
    "name:eng_x_preferred":[
        "Pulwama"
    ],
    "name:fas_x_preferred":[
        "\u067e\u0648\u0644\u0648\u0627\u0645\u0627"
    ],
    "name:fra_x_preferred":[
        "Pulwama"
    ],
    "name:guj_x_preferred":[
        "\u0aaa\u0ac1\u0ab2\u0ab5\u0abe\u0aae\u0abe \u0aa4\u0ab9\u0ac7\u0ab8\u0ac0\u0ab2"
    ],
    "name:hin_x_preferred":[
        "\u092a\u0941\u0932\u0935\u093e\u092e\u093e"
    ],
    "name:ita_x_preferred":[
        "Pulwama"
    ],
    "name:jpn_x_preferred":[
        "\u30d7\u30eb\u30ef\u30de\u30fb\u30c6\u30fc\u30b7\u30eb"
    ],
    "name:kan_x_preferred":[
        "\u0caa\u0cc1\u0cb2\u0ccd\u0cb5\u0cbe\u0cae\u0cbe \u0ca4\u0cc6\u0cb9\u0cb8\u0cc0\u0cb2\u0ccd"
    ],
    "name:kor_x_preferred":[
        "\ud480\ub9c8\ub9c8 \ud14c\uc2e4"
    ],
    "name:mar_x_preferred":[
        "\u092a\u0941\u0932\u0935\u093e\u092e\u093e"
    ],
    "name:mlg_x_preferred":[
        "Pulwama"
    ],
    "name:msa_x_preferred":[
        "Pulwama"
    ],
    "name:nan_x_preferred":[
        "Pulwama"
    ],
    "name:nep_x_preferred":[
        "\u092a\u0941\u0932\u0935\u093e\u092e\u093e"
    ],
    "name:nld_x_preferred":[
        "Pulwama"
    ],
    "name:pan_x_preferred":[
        "\u0a2a\u0a41\u0a32\u0a35\u0a3e\u0a2e\u0a3e"
    ],
    "name:pnb_x_preferred":[
        "\u067e\u0644\u0648\u0627\u0645\u06c1"
    ],
    "name:por_x_preferred":[
        "Pulwama Tehsil"
    ],
    "name:rus_x_preferred":[
        "\u041f\u0443\u043b\u0432\u0430\u043c\u0430"
    ],
    "name:san_x_preferred":[
        "\u092a\u0941\u0932\u0935\u093e\u092e\u093e"
    ],
    "name:spa_x_preferred":[
        "Pulwama"
    ],
    "name:swe_x_preferred":[
        "Pulwama"
    ],
    "name:tam_x_preferred":[
        "\u0baa\u0bc1\u0bb2\u0bcd\u0bb5\u0bbe\u0bae\u0bbe \u0b9f\u0bc6\u0bb9\u0b9a\u0bbf\u0bb2\u0bcd"
    ],
    "name:tel_x_preferred":[
        "\u0c2a\u0c41\u0c32\u0c4d\u0c35\u0c3e\u0c2e\u0c3e \u0c24\u0c46\u0c39\u0c38\u0c3f\u0c32\u0c4d"
    ],
    "name:und_x_variant":[
        "Pulawom"
    ],
    "name:urd_x_preferred":[
        "\u067e\u0644\u0648\u0627\u0645\u06c1"
    ],
    "name:vie_x_preferred":[
        "Pulwama"
    ],
    "name:zho_x_preferred":[
        "\u666e\u5c14\u74e6\u9a6c"
    ],
    "qs:name":"Pulwama",
    "qs:name_adm0":"India",
    "qs:name_adm1":"Jammu and Kashmir",
    "qs:photos_9k":1,
    "qs:photos_9r":1,
    "qs:photos_all":11,
    "qs:photos_sr":0,
    "qs:placetype":"Town",
    "qs:pop_sr":"7",
    "wd:wordcount":619,
    "wof:name":"Pulwama",
    "wof:placetype":"locality",
    "wof:population":20071
},
  "geometry": {"coordinates":[74.89955,33.87405],"type":"Point"}
}