{
  "type": "Feature",
  "properties": {
    "gn:admin1_code":"35.0",
    "gn:admin2_code":"419.0",
    "gn:asciiname":"Chandpur ka Pura",
    "gn:country_code":"IN",
    "gn:dem":190,
    "gn:feature_class":"P",
    "gn:feature_code":"PPL",
    "gn:name":"Chandpur ka Pura",
    "gn:population":0,
    "gn:timezone":"Asia/Kolkata",
    "iso:country":"IN",
    "wof:name":"Chandpur ka Pura",
    "wof:placetype":"locality"
},
  "geometry": {"coordinates":[77.88561,26.31056],"type":"Point"}
}