{
  "type": "Feature",
  "properties": {
    "gn:admin1_code":"37.0",
    "gn:admin2_code":"408.0",
    "gn:asciiname":"Bhave",
    "gn:country_code":"IN",
    "gn:dem":657,
    "gn:feature_class":"P",
    "gn:feature_code":"PPL",
    "gn:name":"Bh\u0101ve",
    "gn:population":0,
    "gn:timezone":"Asia/Kolkata",
    "iso:country":"IN",
    "ks:ks_alt_nam":"Bh\u0101ve",
    "ks:ks_name":"Bhave",
    "ks:ks_type":"VILLAGE",
    "name:eng_x_preferred":[
        "Bhave"
    ],
    "name:eng_x_variant":[
        "Bh\u0101ve"
    ],
    "wof:name":"Bhave",
    "wof:placetype":"locality"
},
  "geometry": {"coordinates":[80.74786400000001,21.512865],"type":"Point"}
}