{
  "type": "Feature",
  "properties": {
    "gn:admin1_code":"2.0",
    "gn:asciiname":"Dodadodi Saparayi",
    "gn:country_code":"IN",
    "gn:dem":664,
    "gn:feature_class":"P",
    "gn:feature_code":"PPL",
    "gn:name":"Dodadodi S\u0101par\u0101yi",
    "gn:population":0,
    "gn:timezone":"Asia/Kolkata",
    "iso:country":"IN",
    "wof:name":"Dodadodi Saparayi",
    "wof:placetype":"locality"
},
  "geometry": {"coordinates":[83.05082,18.54189],"type":"Point"}
}