{
  "type": "Feature",
  "properties": {
    "gn:admin1_code":"34",
    "gn:admin2_code":"232.0",
    "gn:asciiname":"Bihariji ka Dera",
    "gn:country_code":"IN",
    "gn:dem":72,
    "gn:feature_class":"P",
    "gn:feature_code":"PPL",
    "gn:name":"Bih\u0101r\u012bji ka Dera",
    "gn:population":0,
    "gn:timezone":"Asia/Kolkata",
    "iso:country":"IN",
    "wof:name":"Bihariji ka Dera",
    "wof:placetype":"locality"
},
  "geometry": {"coordinates":[83.98432,25.41705],"type":"Point"}
}