{
  "type": "Feature",
  "properties": {
    "iso:country":"IN",
    "ks:ks_name":"Uri Sirtoli",
    "ks:ks_pop":157,
    "ks:ks_type":"VILLAGE",
    "name:eng_x_preferred":[
        "Uri Sirtoli"
    ],
    "wof:name":"Uri Sirtoli",
    "wof:placetype":"locality",
    "wof:population":157
},
  "geometry": {"coordinates":[80.13397000000001,29.893522],"type":"Point"}
}