{
  "type": "Feature",
  "properties": {
    "iso:country":"IN",
    "ks:ks_name":"Kholi Dhar",
    "ks:ks_pop":75,
    "ks:ks_type":"VILLAGE",
    "name:eng_x_preferred":[
        "Kholi Dhar"
    ],
    "wof:name":"Kholi Dhar",
    "wof:placetype":"locality",
    "wof:population":75
},
  "geometry": {"coordinates":[78.955665,30.090654],"type":"Point"}
}