{
  "type": "Feature",
  "properties": {
    "iso:country":"IN",
    "ks:ks_name":"Ollesar",
    "ks:ks_pop":162,
    "ks:ks_type":"HABITATION",
    "name:eng_x_preferred":[
        "Ollesar"
    ],
    "wof:name":"Ollesar",
    "wof:placetype":"locality",
    "wof:population":162
},
  "geometry": {"coordinates":[74.81611599999999,14.848259],"type":"Point"}
}