{
  "type": "Feature",
  "properties": {
    "gn:country":"IN",
    "gn:fcode":"PPL",
    "gn:population":17354,
    "iso:country":"IN",
    "ks:ks_name":"Howli",
    "ks:ks_type":"URBAN",
    "ks:ks_uagg_main":0,
    "name:asm_x_preferred":[
        "\u09b9\u09be\u0989\u09b2\u09c0"
    ],
    "name:bpy_x_preferred":[
        "\u09b9\u09be\u09f1\u09be\u09b2\u09bf"
    ],
    "name:ceb_x_preferred":[
        "Howli"
    ],
    "name:eng_x_preferred":[
        "Howli"
    ],
    "name:hin_x_preferred":[
        "\u0939\u093e\u0909\u0932\u0940"
    ],
    "name:ita_x_preferred":[
        "Howli"
    ],
    "name:msa_x_preferred":[
        "Howli"
    ],
    "name:nan_x_preferred":[
        "Howli"
    ],
    "name:new_x_preferred":[
        "\u0939\u094b\u0935\u094d\u0932\u0940"
    ],
    "name:nld_x_preferred":[
        "Howli"
    ],
    "name:por_x_preferred":[
        "Howli"
    ],
    "name:spa_x_preferred":[
        "Howli"
    ],
    "name:swe_x_preferred":[
        "Howli"
    ],
    "name:vie_x_preferred":[
        "Howli"
    ],
    "name:zho_x_preferred":[
        "\u970d\u6c83\u5229"
    ],
    "qs:name":"Howli",
    "qs:photos_9r":0,
    "qs:photos_sr":0,
    "qs:pop_sr":"6",
    "wof:name":"Howli",
    "wof:placetype":"neighbourhood"
},
  "geometry": {"coordinates":[90.98004400000001,26.422366],"type":"Point"}
}