{
  "type": "Feature",
  "properties": {
    "iso:country":"IN",
    "ks:ks_name":"Bargadi",
    "ks:ks_pop":41,
    "ks:ks_type":"VILLAGE",
    "name:eng_x_preferred":[
        "Bargadi"
    ],
    "wof:name":"Bargadi",
    "wof:placetype":"locality",
    "wof:population":41
},
  "geometry": {"coordinates":[86.671881,21.832417],"type":"Point"}
}