{
  "type": "Feature",
  "properties": {
    "iso:country":"IN",
    "ks:ks_name":"Uravasti",
    "ks:ks_pop":201,
    "ks:ks_type":"HABITATION",
    "ks:ks_uagg_main":0,
    "name:eng_x_preferred":[
        "Uravasti"
    ],
    "wof:name":"Uravasti",
    "wof:placetype":"neighbourhood",
    "wof:population":201
},
  "geometry": {"coordinates":[74.5099,18.2878],"type":"Point"}
}