{
  "type": "Feature",
  "properties": {
    "iso:country":"IN",
    "ks:ks_name":"Ghamyanaik T",
    "ks:ks_pop":200,
    "ks:ks_type":"HABITATION",
    "name:eng_x_preferred":[
        "Ghamyanaik T"
    ],
    "wof:name":"Ghamyanaik T",
    "wof:placetype":"locality",
    "wof:population":200
},
  "geometry": {"coordinates":[77.86769,18.115283],"type":"Point"}
}