{
  "type": "Feature",
  "properties": {
    "gn:admin1_code":"24.0",
    "gn:admin2_code":"101",
    "gn:asciiname":"Khetolai",
    "gn:country_code":"IN",
    "gn:dem":268,
    "gn:feature_class":"P",
    "gn:feature_code":"PPL",
    "gn:name":"Khetol\u0101i",
    "gn:population":0,
    "gn:timezone":"Asia/Kolkata",
    "iso:country":"IN",
    "name:und_x_variant":[
        "Khetol\u0101i",
        "Khetol\u0101i M\u016blv\u0101n"
    ],
    "wof:name":"Khetolai",
    "wof:placetype":"locality"
},
  "geometry": {"coordinates":[72.92376,27.73497],"type":"Point"}
}