{
  "type": "Feature",
  "properties": {
    "iso:country":"IN",
    "ks:ks_alt_nam":"Samundeeswari koil vattam",
    "ks:ks_name":"Samundeeswari Koil Vattam",
    "ks:ks_pop":320,
    "ks:ks_type":"HABITATION",
    "name:eng_x_preferred":[
        "Samundeeswari Koil Vattam"
    ],
    "wof:name":"Samundeeswari Koil Vattam",
    "wof:placetype":"locality",
    "wof:population":320
},
  "geometry": {"coordinates":[78.70157,12.562927],"type":"Point"}
}