{
  "type": "Feature",
  "properties": {
    "gn:admin1_code":"11.0",
    "gn:admin2_code":"27.0",
    "gn:asciiname":"Naras",
    "gn:country_code":"IN",
    "gn:dem":1401,
    "gn:feature_class":"P",
    "gn:feature_code":"PPL",
    "gn:name":"Nar\u0101s",
    "gn:population":0,
    "gn:timezone":"Asia/Kolkata",
    "iso:country":"IN",
    "name:fas_x_preferred":[
        "\u0646\u0631\u0633"
    ],
    "wof:name":"Naras",
    "wof:placetype":"locality"
},
  "geometry": {"coordinates":[77.19431999999998,31.34253],"type":"Point"}
}