{
  "type": "Feature",
  "properties": {
    "iso:country":"IN",
    "ks:ks_name":"Balabettu",
    "ks:ks_pop":60,
    "ks:ks_type":"HABITATION",
    "name:eng_x_preferred":[
        "Balabettu"
    ],
    "wof:name":"Balabettu",
    "wof:placetype":"locality",
    "wof:population":60
},
  "geometry": {"coordinates":[74.948758,13.30959],"type":"Point"}
}