{
  "type": "Feature",
  "properties": {
    "gn:admin1_code":"19.0",
    "gn:admin2_code":"575.0",
    "gn:asciiname":"Bajre",
    "gn:country_code":"IN",
    "gn:dem":85,
    "gn:feature_class":"P",
    "gn:feature_code":"PPLL",
    "gn:name":"Bajre",
    "gn:population":0,
    "gn:timezone":"Asia/Kolkata",
    "iso:country":"IN",
    "ks:ks_name":"Bajire",
    "ks:ks_pop":1828,
    "ks:ks_type":"VILLAGE",
    "name:eng_x_preferred":[
        "Bajire"
    ],
    "name:eng_x_variant":[
        "Bajre"
    ],
    "wof:name":"Bajire",
    "wof:placetype":"locality",
    "wof:population":1828
},
  "geometry": {"coordinates":[75.137192,12.9918],"type":"Point"}
}