{
  "type": "Feature",
  "properties": {
    "gn:admin1_code":"39.0",
    "gn:admin2_code":"061",
    "gn:asciiname":"Jameli",
    "gn:country_code":"IN",
    "gn:dem":1131,
    "gn:feature_class":"P",
    "gn:feature_code":"PPL",
    "gn:name":"Jameli",
    "gn:population":0,
    "gn:timezone":"Asia/Kolkata",
    "iso:country":"IN",
    "name:und_x_variant":[
        "Jamoli"
    ],
    "wof:name":"Jameli",
    "wof:placetype":"locality"
},
  "geometry": {"coordinates":[78.64386999999998,29.89066],"type":"Point"}
}