{
  "type": "Feature",
  "properties": {
    "iso:country":"IN",
    "ks:ks_name":"Hulimane",
    "ks:ks_pop":42,
    "ks:ks_type":"HABITATION",
    "name:eng_x_preferred":[
        "Hulimane"
    ],
    "wof:name":"Hulimane",
    "wof:placetype":"locality",
    "wof:population":42
},
  "geometry": {"coordinates":[74.819211,14.3805],"type":"Point"}
}