{
  "type": "Feature",
  "properties": {
    "iso:country":"IN",
    "ks:ks_name":"Pure Kale Khan",
    "ks:ks_pop":200,
    "ks:ks_type":"HABITATION",
    "name:eng_x_preferred":[
        "Pure Kale Khan"
    ],
    "wof:name":"Pure Kale Khan",
    "wof:placetype":"locality",
    "wof:population":200
},
  "geometry": {"coordinates":[81.68969800000001,26.474641],"type":"Point"}
}