{
  "type": "Feature",
  "properties": {
    "iso:country":"IN",
    "ks:ks_name":"Imamnagar",
    "ks:ks_pop":761,
    "ks:ks_type":"VILLAGE",
    "ks:ks_uagg_main":0,
    "name:eng_x_preferred":[
        "Imamnagar"
    ],
    "wof:name":"Imamnagar",
    "wof:placetype":"neighbourhood",
    "wof:population":761
},
  "geometry": {"coordinates":[87.88566400000001,24.095597],"type":"Point"}
}