{
  "type": "Feature",
  "properties": {
    "iso:country":"IN",
    "ks:ks_name":"Narigudde",
    "ks:ks_pop":53,
    "ks:ks_type":"HABITATION",
    "name:eng_x_preferred":[
        "Narigudde"
    ],
    "wof:name":"Narigudde",
    "wof:placetype":"locality",
    "wof:population":53
},
  "geometry": {"coordinates":[75.46784700000001,13.65544],"type":"Point"}
}