{
  "type": "Feature",
  "properties": {
    "iso:country":"IN",
    "ks:ks_name":"Gondiputtu",
    "ks:ks_pop":14,
    "ks:ks_type":"HABITATION",
    "name:eng_x_preferred":[
        "Gondiputtu"
    ],
    "wof:name":"Gondiputtu",
    "wof:placetype":"locality",
    "wof:population":14
},
  "geometry": {"coordinates":[82.605092,18.356411],"type":"Point"}
}