{
  "type": "Feature",
  "properties": {
    "iso:country":"IN",
    "ks:ks_name":"Gangudi",
    "ks:ks_pop":0,
    "ks:ks_type":"VILLAGE",
    "name:eng_x_preferred":[
        "Gangudi"
    ],
    "wof:name":"Gangudi",
    "wof:placetype":"locality",
    "wof:population":0
},
  "geometry": {"coordinates":[86.27888400000001,23.401038],"type":"Point"}
}