{
  "type": "Feature",
  "properties": {
    "iso:country":"IN",
    "ks:ks_alt_nam":"Chandrapuri UV 56",
    "ks:ks_name":"Chandrapuri Uv 56",
    "ks:ks_pop":417,
    "ks:ks_type":"HABITATION",
    "name:eng_x_preferred":[
        "Chandrapuri Uv 56"
    ],
    "wof:name":"Chandrapuri Uv 56",
    "wof:placetype":"locality",
    "wof:population":417
},
  "geometry": {"coordinates":[82.110998,19.702149],"type":"Point"}
}