{
  "type": "Feature",
  "properties": {
    "iso:country":"IN",
    "ks:ks_name":"Jannagar",
    "ks:ks_pop":3094,
    "ks:ks_type":"VILLAGE",
    "ks:ks_uagg_main":0,
    "name:eng_x_preferred":[
        "Jannagar"
    ],
    "wof:name":"Jannagar",
    "wof:placetype":"neighbourhood",
    "wof:population":3094
},
  "geometry": {"coordinates":[87.916314,25.218636],"type":"Point"}
}