{
  "type": "Feature",
  "properties": {
    "gn:admin1_code":"19.0",
    "gn:admin2_code":"574.0",
    "gn:asciiname":"Biligahalli",
    "gn:country_code":"IN",
    "gn:dem":879,
    "gn:feature_class":"P",
    "gn:feature_code":"PPL",
    "gn:name":"Biligahalli",
    "gn:population":0,
    "gn:timezone":"Asia/Kolkata",
    "iso:country":"IN",
    "wof:name":"Biligahalli",
    "wof:placetype":"neighbourhood"
},
  "geometry": {"coordinates":[76.55141,12.9735],"type":"Point"}
}