{
  "type": "Feature",
  "properties": {
    "gn:admin1_code":"36",
    "gn:admin2_code":"152.0",
    "gn:asciiname":"Khanda Baura",
    "gn:country_code":"IN",
    "gn:dem":149,
    "gn:feature_class":"P",
    "gn:feature_code":"PPL",
    "gn:name":"Kh\u0101nda Baura",
    "gn:population":0,
    "gn:timezone":"Asia/Kolkata",
    "iso:country":"IN",
    "name:und_x_variant":[
        "Kh\u0101nda Baura",
        "Khar Baura"
    ],
    "wof:name":"Khanda Baura",
    "wof:placetype":"locality"
},
  "geometry": {"coordinates":[79.87954000000001,27.79863],"type":"Point"}
}