{
  "type": "Feature",
  "properties": {
    "iso:country":"IN",
    "ks:ks_name":"Malipara",
    "ks:ks_pop":381,
    "ks:ks_type":"HABITATION",
    "ks:ks_uagg_main":0,
    "name:eng_x_preferred":[
        "Malipara"
    ],
    "wof:name":"Malipara",
    "wof:placetype":"locality",
    "wof:population":381
},
  "geometry": {"coordinates":[91.510379,26.087542],"type":"Point"}
}