{
  "type": "Feature",
  "properties": {
    "gn:admin1_code":"24.0",
    "gn:admin2_code":"129",
    "gn:asciiname":"Bairagarh",
    "gn:country_code":"IN",
    "gn:dem":359,
    "gn:feature_class":"P",
    "gn:feature_code":"PPL",
    "gn:name":"Bairagarh",
    "gn:population":0,
    "gn:timezone":"Asia/Kolkata",
    "iso:country":"IN",
    "wof:name":"Bairagarh",
    "wof:placetype":"locality"
},
  "geometry": {"coordinates":[76.43021,24.34733],"type":"Point"}
}