{
  "type": "Feature",
  "properties": {
    "iso:country":"IN",
    "ks:ks_name":"Janagalapalli G",
    "ks:ks_pop":542,
    "ks:ks_type":"HABITATION",
    "ks:ks_uagg_main":0,
    "name:eng_x_preferred":[
        "Janagalapalli G"
    ],
    "wof:name":"Janagalapalli G",
    "wof:placetype":"neighbourhood",
    "wof:population":542
},
  "geometry": {"coordinates":[80.50500599999999,18.435513],"type":"Point"}
}