{
  "type": "Feature",
  "properties": {
    "gn:admin1_code":"35.0",
    "gn:admin2_code":"456.0",
    "gn:asciiname":"Tikrakhapa",
    "gn:country_code":"IN",
    "gn:dem":521,
    "gn:feature_class":"P",
    "gn:feature_code":"PPL",
    "gn:name":"Tikrakh\u0101pa",
    "gn:population":0,
    "gn:timezone":"Asia/Kolkata",
    "iso:country":"IN",
    "wof:name":"Tikrakhapa",
    "wof:placetype":"locality"
},
  "geometry": {"coordinates":[80.02228000000002,22.60611],"type":"Point"}
}