{
  "type": "Feature",
  "properties": {
    "iso:country":"IN",
    "ks:ks_name":"Lourthupuram",
    "ks:ks_pop":12,
    "ks:ks_type":"HABITATION",
    "name:eng_x_preferred":[
        "Lourthupuram"
    ],
    "wof:name":"Lourthupuram",
    "wof:placetype":"locality",
    "wof:population":12
},
  "geometry": {"coordinates":[78.593615,9.396588],"type":"Point"}
}