{
  "type": "Feature",
  "properties": {
    "iso:country":"IN",
    "ks:ks_name":"Hajidanga",
    "ks:ks_pop":2134,
    "ks:ks_type":"VILLAGE",
    "ks:ks_uagg_main":0,
    "name:eng_x_preferred":[
        "Hajidanga"
    ],
    "wof:name":"Hajidanga",
    "wof:placetype":"neighbourhood",
    "wof:population":2134
},
  "geometry": {"coordinates":[88.423114,24.170856],"type":"Point"}
}