{
  "type": "Feature",
  "properties": {
    "iso:country":"IN",
    "ks:ks_name":"Deulpota",
    "ks:ks_pop":420,
    "ks:ks_type":"VILLAGE",
    "name:eng_x_preferred":[
        "Deulpota"
    ],
    "wof:name":"Deulpota",
    "wof:placetype":"locality",
    "wof:population":420
},
  "geometry": {"coordinates":[87.56629,22.10559],"type":"Point"}
}