{
  "type": "Feature",
  "properties": {
    "iso:country":"IN",
    "ks:ks_name":"Chamarauti",
    "ks:ks_pop":349,
    "ks:ks_type":"HABITATION",
    "ks:ks_uagg_main":0,
    "name:eng_x_preferred":[
        "Chamarauti"
    ],
    "wof:name":"Chamarauti",
    "wof:placetype":"neighbourhood",
    "wof:population":349
},
  "geometry": {"coordinates":[82.52972800000001,25.972007],"type":"Point"}
}