{
  "type": "Feature",
  "properties": {
    "gn:admin1_code":"36.0",
    "gn:admin2_code":"183.0",
    "gn:asciiname":"Wachwa",
    "gn:country_code":"IN",
    "gn:dem":108,
    "gn:feature_class":"P",
    "gn:feature_code":"PPL",
    "gn:name":"Wachwa",
    "gn:population":0,
    "gn:timezone":"Asia/Kolkata",
    "iso:country":"IN",
    "name:que_x_preferred":[
        "Wachwa urqu"
    ],
    "name:zho_x_preferred":[
        "\u74e6\u5947\u74e6\u5c71"
    ],
    "wof:name":"Wachwa",
    "wof:placetype":"locality"
},
  "geometry": {"coordinates":[82.11579999999999,27.13259],"type":"Point"}
}