{
  "type": "Feature",
  "properties": {
    "gn:admin1_code":"38.0",
    "gn:admin2_code":"348.0",
    "gn:asciiname":"Kanha Chak",
    "gn:country_code":"IN",
    "gn:dem":394,
    "gn:feature_class":"P",
    "gn:feature_code":"PPL",
    "gn:name":"Kanh\u0101 Chak",
    "gn:population":0,
    "gn:timezone":"Asia/Kolkata",
    "iso:country":"IN",
    "ks:ks_alt_nam":"Kanh\u0101 Chak",
    "ks:ks_name":"Kanha Chak",
    "ks:ks_pop":133,
    "ks:ks_type":"VILLAGE",
    "ks:ks_uagg_main":0,
    "name:eng_x_preferred":[
        "Kanha Chak"
    ],
    "name:eng_x_variant":[
        "Kanh\u0101 Chak"
    ],
    "wof:name":"Kanha Chak",
    "wof:placetype":"neighbourhood",
    "wof:population":133
},
  "geometry": {"coordinates":[85.343673,24.423388],"type":"Point"}
}