{
  "type": "Feature",
  "properties": {
    "gn:admin1_code":"35",
    "gn:admin2_code":"456.0",
    "gn:asciiname":"Kurwa",
    "gn:country_code":"IN",
    "gn:dem":367,
    "gn:feature_class":"P",
    "gn:feature_code":"PPL",
    "gn:name":"Kurwa",
    "gn:population":0,
    "gn:timezone":"Asia/Kolkata",
    "iso:country":"IN",
    "ks:ks_name":"Kudwa",
    "ks:ks_pop":581,
    "ks:ks_type":"VILLAGE",
    "name:eng_x_preferred":[
        "Kudwa"
    ],
    "name:eng_x_variant":[
        "Kurwa"
    ],
    "wof:name":"Kudwa",
    "wof:placetype":"locality",
    "wof:population":581
},
  "geometry": {"coordinates":[79.658045,21.751858],"type":"Point"}
}