{
  "type": "Feature",
  "properties": {
    "iso:country":"IN",
    "ks:ks_name":"Banavat Thanda",
    "ks:ks_pop":115,
    "ks:ks_type":"HABITATION",
    "name:eng_x_preferred":[
        "Banavat Thanda"
    ],
    "wof:name":"Banavat Thanda",
    "wof:placetype":"locality",
    "wof:population":115
},
  "geometry": {"coordinates":[78.50741499999999,18.515245],"type":"Point"}
}