{
  "type": "Feature",
  "properties": {
    "iso:country":"IN",
    "ks:ks_name":"Belaha",
    "ks:ks_pop":23,
    "ks:ks_type":"VILLAGE",
    "name:eng_x_preferred":[
        "Belaha"
    ],
    "wof:name":"Belaha",
    "wof:placetype":"locality",
    "wof:population":23
},
  "geometry": {"coordinates":[81.867867,24.637315],"type":"Point"}
}