{
  "type": "Feature",
  "properties": {
    "gn:admin1_code":"39.0",
    "gn:admin2_code":"64.0",
    "gn:asciiname":"Jol",
    "gn:country_code":"IN",
    "gn:dem":846,
    "gn:feature_class":"P",
    "gn:feature_code":"PPL",
    "gn:name":"Jol",
    "gn:population":0,
    "gn:timezone":"Asia/Kolkata",
    "iso:country":"IN",
    "name:deu_x_preferred":[
        "Jol"
    ],
    "name:fra_x_preferred":[
        "Jol"
    ],
    "name:nld_x_preferred":[
        "Jol"
    ],
    "name:nno_x_preferred":[
        "Jol"
    ],
    "name:nor_x_preferred":[
        "Jol"
    ],
    "wof:name":"Jol",
    "wof:placetype":"locality"
},
  "geometry": {"coordinates":[79.96941,29.48767],"type":"Point"}
}