{
  "type": "Feature",
  "properties": {
    "iso:country":"IN",
    "ks:ks_name":"Kutti Purwa",
    "ks:ks_pop":97,
    "ks:ks_type":"HABITATION",
    "ks:ks_uagg_main":0,
    "name:eng_x_preferred":[
        "Kutti Purwa"
    ],
    "wof:name":"Kutti Purwa",
    "wof:placetype":"neighbourhood",
    "wof:population":97
},
  "geometry": {"coordinates":[81.051087,27.68129],"type":"Point"}
}