{
  "type": "Feature",
  "properties": {
    "iso:country":"IN",
    "ks:ks_name":"Dakhyat Gaon",
    "ks:ks_pop":768,
    "ks:ks_type":"HABITATION",
    "name:eng_x_preferred":[
        "Dakhyat Gaon"
    ],
    "wof:name":"Dakhyat Gaon",
    "wof:placetype":"locality",
    "wof:population":768
},
  "geometry": {"coordinates":[78.230328,30.826819],"type":"Point"}
}