{
  "type": "Feature",
  "properties": {
    "gn:admin1_code":"24.0",
    "gn:admin2_code":"102.0",
    "gn:asciiname":"Bhatwala",
    "gn:country_code":"IN",
    "gn:dem":207,
    "gn:feature_class":"P",
    "gn:feature_code":"PPL",
    "gn:name":"Bh\u0101tw\u0101la",
    "gn:population":0,
    "gn:timezone":"Asia/Kolkata",
    "iso:country":"IN",
    "wof:name":"Bhatwala",
    "wof:placetype":"locality"
},
  "geometry": {"coordinates":[74.19665999999999,28.74038],"type":"Point"}
}