{
  "type": "Feature",
  "properties": {
    "gn:admin1_code":"35",
    "gn:admin2_code":"446.0",
    "gn:asciiname":"Hinotiyamahalpur",
    "gn:country_code":"IN",
    "gn:dem":447,
    "gn:feature_class":"P",
    "gn:feature_code":"PPL",
    "gn:name":"Hinotiy\u0101mahalpur",
    "gn:population":0,
    "gn:timezone":"Asia/Kolkata",
    "iso:country":"IN",
    "wof:name":"Hinotiyamahalpur",
    "wof:placetype":"locality"
},
  "geometry": {"coordinates":[78.01886999999998,23.32346],"type":"Point"}
}