{
  "type": "Feature",
  "properties": {
    "gn:admin1_code":"39.0",
    "gn:admin2_code":"60.0",
    "gn:asciiname":"Kaptwa",
    "gn:country_code":"IN",
    "gn:dem":872,
    "gn:feature_class":"P",
    "gn:feature_code":"PPL",
    "gn:name":"Kaptwa",
    "gn:population":0,
    "gn:timezone":"Asia/Kolkata",
    "iso:country":"IN",
    "wof:name":"Kaptwa",
    "wof:placetype":"locality"
},
  "geometry": {"coordinates":[77.73033000000002,30.73999],"type":"Point"}
}