{
  "type": "Feature",
  "properties": {
    "iso:country":"IN",
    "ks:ks_alt_nam":"SC Colony",
    "ks:ks_name":"Sc Colony",
    "ks:ks_pop":321,
    "ks:ks_type":"HABITATION",
    "name:eng_x_preferred":[
        "Sc Colony"
    ],
    "wof:name":"Sc Colony",
    "wof:placetype":"locality",
    "wof:population":321
},
  "geometry": {"coordinates":[80.47817999999999,17.058524],"type":"Point"}
}