{
  "type": "Feature",
  "properties": {
    "iso:country":"IN",
    "ks:ks_name":"Baij Nath Purva",
    "ks:ks_pop":31,
    "ks:ks_type":"HABITATION",
    "ks:ks_uagg_main":0,
    "name:eng_x_preferred":[
        "Baij Nath Purva"
    ],
    "wof:name":"Baij Nath Purva",
    "wof:placetype":"neighbourhood",
    "wof:population":31
},
  "geometry": {"coordinates":[81.01969200000001,28.363527],"type":"Point"}
}