{
  "type": "Feature",
  "properties": {
    "iso:country":"IN",
    "ks:ks_name":"Khairari",
    "ks:ks_pop":414,
    "ks:ks_type":"VILLAGE",
    "name:eng_x_preferred":[
        "Khairari"
    ],
    "wof:name":"Khairari",
    "wof:placetype":"locality",
    "wof:population":414
},
  "geometry": {"coordinates":[77.55885600000001,26.705921],"type":"Point"}
}