{
  "type": "Feature",
  "properties": {
    "gn:admin1_code":"36",
    "gn:admin2_code":"161.0",
    "gn:asciiname":"Ginja",
    "gn:country_code":"IN",
    "gn:dem":159,
    "gn:feature_class":"P",
    "gn:feature_code":"PPL",
    "gn:name":"G\u012bnja",
    "gn:population":0,
    "gn:timezone":"Asia/Kolkata",
    "iso:country":"IN",
    "wof:name":"Ginja",
    "wof:placetype":"neighbourhood"
},
  "geometry": {"coordinates":[78.93461000000001,26.9566],"type":"Point"}
}