{
  "type": "Feature",
  "properties": {
    "gn:admin1_code":"36",
    "gn:admin2_code":"189.0",
    "gn:asciiname":"Khotha",
    "gn:country_code":"IN",
    "gn:dem":88,
    "gn:feature_class":"P",
    "gn:feature_code":"PPL",
    "gn:name":"Khotha",
    "gn:population":0,
    "gn:timezone":"Asia/Kolkata",
    "iso:country":"IN",
    "wof:name":"Khotha",
    "wof:placetype":"locality"
},
  "geometry": {"coordinates":[83.66201,26.80763],"type":"Point"}
}