{
  "type": "Feature",
  "properties": {
    "iso:country":"IN",
    "name:eng_x_preferred":[
        "Nungambakkam"
    ],
    "name:eng_x_variant":[
        "Nangambaukam",
        "Nangamb\u0101ukam",
        "Nungambaukum",
        "Nungamb\u0101kkam"
    ],
    "name:mal_x_preferred":[
        "\u0d28\u0d41\u0d19\u0d4d\u0d15\u0d2e\u0d4d\u0d2a\u0d3e\u0d15\u0d4d\u0d15\u0d02"
    ],
    "name:tam_x_preferred":[
        "\u0ba8\u0bc1\u0b99\u0bcd\u0b95\u0bae\u0bcd\u0baa\u0bbe\u0b95\u0bcd\u0b95\u0bae\u0bcd"
    ],
    "name:und_x_variant":[
        "Madras Nungambakan"
    ],
    "qs:gn_adm0_cc":"IN",
    "qs:gn_fcode":"PPLX",
    "qs:gn_local":1264527,
    "qs:gn_nam_loc":"Chennai, Chennai, Tamil Nadu, IN",
    "qs:gn_namadm1":"25",
    "qs:gn_name":"Nungamb\u0101kkam",
    "qs:local_max":2138,
    "qs:local_sum":21081,
    "qs:localhoods":47,
    "qs:name":"Nungambakkam",
    "qs:name_adm0":"India",
    "qs:name_adm1":"Tamil Nadu",
    "qs:name_adm2":"Chennai",
    "qs:name_local":"Chennai",
    "qs:photo_max":194,
    "qs:photo_sum":1500,
    "qs:placetype":"Suburb",
    "qs:quad_count":55,
    "qs:woe_adm0":23424848,
    "qs:woe_adm1":2345758,
    "qs:woe_adm2":12586677,
    "qs:woe_lau":0,
    "qs:woe_local":2295424,
    "qs:woe_ver":"7.10.0",
    "wd:wordcount":799,
    "wof:lang":[
        "eng"
    ],
    "wof:name":"Nungambakkam",
    "wof:placetype":"neighbourhood"
},
  "geometry": {"coordinates":[80.239704,13.061822],"type":"Point"}
}