{
  "type": "Feature",
  "properties": {
    "iso:country":"IN",
    "ks:ks_name":"Dumaria",
    "ks:ks_pop":187,
    "ks:ks_type":"VILLAGE",
    "name:eng_x_preferred":[
        "Dumaria"
    ],
    "wof:name":"Dumaria",
    "wof:placetype":"locality",
    "wof:population":187
},
  "geometry": {"coordinates":[87.425055,24.461246],"type":"Point"}
}