{
  "type": "Feature",
  "properties": {
    "iso:country":"IN",
    "ks:ks_name":"Utukurvandlapalli",
    "ks:ks_pop":74,
    "ks:ks_type":"HABITATION",
    "name:eng_x_preferred":[
        "Utukurvandlapalli"
    ],
    "wof:name":"Utukurvandlapalli",
    "wof:placetype":"locality",
    "wof:population":74
},
  "geometry": {"coordinates":[78.75867,14.151126],"type":"Point"}
}