{
  "type": "Feature",
  "properties": {
    "iso:country":"IN",
    "ks:ks_name":"Dasanavatara",
    "ks:ks_pop":19,
    "ks:ks_type":"HABITATION",
    "name:eng_x_preferred":[
        "Dasanavatara"
    ],
    "wof:name":"Dasanavatara",
    "wof:placetype":"locality",
    "wof:population":19
},
  "geometry": {"coordinates":[75.311688,13.538739],"type":"Point"}
}