{
  "type": "Feature",
  "properties": {
    "iso:country":"IN",
    "ks:ks_name":"Sowlukottai",
    "ks:ks_pop":198,
    "ks:ks_type":"HABITATION",
    "name:eng_x_preferred":[
        "Sowlukottai"
    ],
    "wof:name":"Sowlukottai",
    "wof:placetype":"locality",
    "wof:population":198
},
  "geometry": {"coordinates":[78.220753,12.260487],"type":"Point"}
}