{
  "type": "Feature",
  "properties": {
    "iso:country":"IN",
    "ks:ks_name":"Dandikia",
    "ks:ks_pop":610,
    "ks:ks_type":"VILLAGE",
    "name:eng_x_preferred":[
        "Dandikia"
    ],
    "wof:name":"Dandikia",
    "wof:placetype":"locality",
    "wof:population":610
},
  "geometry": {"coordinates":[84.185242,20.235832],"type":"Point"}
}