{
  "type": "Feature",
  "properties": {
    "iso:country":"IN",
    "ks:ks_name":"Amblihonda",
    "ks:ks_pop":133,
    "ks:ks_type":"HABITATION",
    "name:eng_x_preferred":[
        "Amblihonda"
    ],
    "wof:name":"Amblihonda",
    "wof:placetype":"locality",
    "wof:population":133
},
  "geometry": {"coordinates":[74.802588,14.553974],"type":"Point"}
}