{
  "type": "Feature",
  "properties": {
    "iso:country":"IN",
    "ks:ks_name":"Nakkalapalem",
    "ks:ks_pop":91,
    "ks:ks_type":"HABITATION",
    "name:eng_x_preferred":[
        "Nakkalapalem"
    ],
    "wof:name":"Nakkalapalem",
    "wof:placetype":"locality",
    "wof:population":91
},
  "geometry": {"coordinates":[79.574198,13.77637],"type":"Point"}
}