{
  "type": "Feature",
  "properties": {
    "gn:admin1_code":"10.0",
    "gn:admin2_code":"79.0",
    "gn:asciiname":"Nathusiri Kalan",
    "gn:country_code":"IN",
    "gn:dem":203,
    "gn:feature_class":"P",
    "gn:feature_code":"PPL",
    "gn:name":"N\u0101th\u016bsiri Kal\u0101n",
    "gn:population":0,
    "gn:timezone":"Asia/Kolkata",
    "iso:country":"IN",
    "wof:name":"Nathusiri Kalan",
    "wof:placetype":"locality"
},
  "geometry": {"coordinates":[75.1275,29.35069],"type":"Point"}
}