{
  "type": "Feature",
  "properties": {
    "iso:country":"IN",
    "ks:ks_name":"Thiruvalarchipatty",
    "ks:ks_pop":1468,
    "ks:ks_type":"HABITATION",
    "ks:ks_uagg_main":0,
    "name:eng_x_preferred":[
        "Thiruvalarchipatty"
    ],
    "wof:name":"Thiruvalarchipatty",
    "wof:placetype":"locality",
    "wof:population":1468
},
  "geometry": {"coordinates":[78.71583099999999,10.743343],"type":"Point"}
}