{
  "type": "Feature",
  "properties": {
    "gn:admin1_code":"36",
    "gn:admin2_code":"181.0",
    "gn:asciiname":"Bhagwanpur",
    "gn:country_code":"IN",
    "gn:dem":120,
    "gn:feature_class":"P",
    "gn:feature_code":"PPL",
    "gn:name":"Bhagw\u0101npur",
    "gn:population":0,
    "gn:timezone":"Asia/Kolkata",
    "iso:country":"IN",
    "wof:name":"Bhagwanpur",
    "wof:placetype":"locality"
},
  "geometry": {"coordinates":[81.83443,27.67307000000001],"type":"Point"}
}