{
  "type": "Feature",
  "properties": {
    "iso:country":"IN",
    "ks:ks_name":"Khairia",
    "ks:ks_pop":99,
    "ks:ks_type":"HABITATION",
    "name:eng_x_preferred":[
        "Khairia"
    ],
    "wof:name":"Khairia",
    "wof:placetype":"locality",
    "wof:population":99
},
  "geometry": {"coordinates":[79.29615699999999,29.772268],"type":"Point"}
}