{
  "type": "Feature",
  "properties": {
    "gn:admin1_code":"36",
    "gn:admin2_code":"146.0",
    "gn:asciiname":"Nagara",
    "gn:country_code":"IN",
    "gn:dem":158,
    "gn:feature_class":"P",
    "gn:feature_code":"PPL",
    "gn:name":"Nag\u0101ra",
    "gn:population":0,
    "gn:timezone":"Asia/Kolkata",
    "iso:country":"IN",
    "name:cat_x_preferred":[
        "Nagara"
    ],
    "name:jpn_x_preferred":[
        "\u30ca\u30ac\u30e9"
    ],
    "name:swe_x_preferred":[
        "Mudugoppa"
    ],
    "wof:name":"Nagara",
    "wof:placetype":"neighbourhood"
},
  "geometry": {"coordinates":[78.60189,26.81809],"type":"Point"}
}