{
  "type": "Feature",
  "properties": {
    "gn:admin1_code":"12.0",
    "gn:admin2_code":"18.0",
    "gn:asciiname":"Gawar",
    "gn:country_code":"IN",
    "gn:dem":1190,
    "gn:feature_class":"P",
    "gn:feature_code":"PPL",
    "gn:name":"Gawar",
    "gn:population":0,
    "gn:timezone":"Asia/Kolkata",
    "iso:country":"IN",
    "name:fra_x_preferred":[
        "Gawar"
    ],
    "wof:name":"Gawar",
    "wof:placetype":"locality"
},
  "geometry": {"coordinates":[75.81050999999999,33.50882],"type":"Point"}
}