{
  "type": "Feature",
  "properties": {
    "gn:admin1_code":"24.0",
    "gn:admin2_code":"124.0",
    "gn:asciiname":"Dakenmari",
    "gn:country_code":"IN",
    "gn:dem":288,
    "gn:feature_class":"P",
    "gn:feature_code":"PPL",
    "gn:name":"Dakenmari",
    "gn:population":0,
    "gn:timezone":"Asia/Kolkata",
    "iso:country":"IN",
    "wof:name":"Dakenmari",
    "wof:placetype":"locality"
},
  "geometry": {"coordinates":[73.63891,23.65833],"type":"Point"}
}