{
  "type": "Feature",
  "properties": {
    "iso:country":"IN",
    "ks:ks_alt_nam":"AJAGAR TILLA-S",
    "ks:ks_name":"Ajagar Tilla-s",
    "ks:ks_pop":728,
    "ks:ks_type":"HABITATION",
    "name:eng_x_preferred":[
        "Ajagar Tilla-s"
    ],
    "wof:name":"Ajagar Tilla-s",
    "wof:placetype":"locality",
    "wof:population":728
},
  "geometry": {"coordinates":[91.59645399999999,24.048947],"type":"Point"}
}