{
  "type": "Feature",
  "properties": {
    "iso:country":"IN",
    "ks:ks_name":"Krushnnagar",
    "ks:ks_pop":642,
    "ks:ks_type":"VILLAGE",
    "name:eng_x_preferred":[
        "Krushnnagar"
    ],
    "wof:name":"Krushnnagar",
    "wof:placetype":"locality",
    "wof:population":642
},
  "geometry": {"coordinates":[86.150764,20.899479],"type":"Point"}
}