{
  "type": "Feature",
  "properties": {
    "iso:country":"IN",
    "ks:ks_name":"Moodukodi",
    "ks:ks_pop":2537,
    "ks:ks_type":"VILLAGE",
    "name:eng_x_preferred":[
        "Moodukodi"
    ],
    "wof:name":"Moodukodi",
    "wof:placetype":"locality",
    "wof:population":2537
},
  "geometry": {"coordinates":[75.14394799999999,13.030881],"type":"Point"}
}