{
  "type": "Feature",
  "properties": {
    "iso:country":"IN",
    "ks:ks_alt_nam":"NIKAM WADI",
    "ks:ks_name":"Nikam Wadi",
    "ks:ks_pop":1310,
    "ks:ks_type":"HABITATION",
    "ks:ks_uagg_main":0,
    "name:eng_x_preferred":[
        "Nikam Wadi"
    ],
    "wof:name":"Nikam Wadi",
    "wof:placetype":"neighbourhood",
    "wof:population":1310
},
  "geometry": {"coordinates":[74.356971,19.906217],"type":"Point"}
}