{
  "type": "Feature",
  "properties": {
    "iso:country":"IN",
    "ks:ks_name":"Nellikachal",
    "ks:ks_pop":1016,
    "ks:ks_type":"HABITATION",
    "name:eng_x_preferred":[
        "Nellikachal"
    ],
    "wof:name":"Nellikachal",
    "wof:placetype":"locality",
    "wof:population":1016
},
  "geometry": {"coordinates":[75.923219,11.714779],"type":"Point"}
}