{
  "type": "Feature",
  "properties": {
    "iso:country":"IN",
    "ks:ks_name":"Harerampur",
    "ks:ks_pop":498,
    "ks:ks_type":"HABITATION",
    "name:eng_x_preferred":[
        "Harerampur"
    ],
    "wof:name":"Harerampur",
    "wof:placetype":"locality",
    "wof:population":498
},
  "geometry": {"coordinates":[85.43441199999999,26.448704],"type":"Point"}
}