{
  "type": "Feature",
  "properties": {
    "iso:country":"IN",
    "ks:ks_name":"Asniye",
    "ks:ks_pop":892,
    "ks:ks_type":"VILLAGE",
    "name:eng_x_preferred":[
        "Asniye"
    ],
    "wof:name":"Asniye",
    "wof:placetype":"locality",
    "wof:population":892
},
  "geometry": {"coordinates":[73.943296,15.851703],"type":"Point"}
}