{
  "type": "Feature",
  "properties": {
    "iso:country":"IN",
    "ks:ks_name":"Tenebolekoppa",
    "ks:ks_pop":109,
    "ks:ks_type":"HABITATION",
    "name:eng_x_preferred":[
        "Tenebolekoppa"
    ],
    "wof:name":"Tenebolekoppa",
    "wof:placetype":"locality",
    "wof:population":109
},
  "geometry": {"coordinates":[74.39248600000001,14.584712],"type":"Point"}
}