{
  "type": "Feature",
  "properties": {
    "iso:country":"IN",
    "ks:ks_name":"Dumtidoddi",
    "ks:ks_pop":600,
    "ks:ks_type":"HABITATION",
    "name:eng_x_preferred":[
        "Dumtidoddi"
    ],
    "wof:name":"Dumtidoddi",
    "wof:placetype":"locality",
    "wof:population":600
},
  "geometry": {"coordinates":[76.676203,16.29226],"type":"Point"}
}