{
  "type": "Feature",
  "properties": {
    "iso:country":"IN",
    "ks:ks_name":"Paglabari",
    "ks:ks_pop":332,
    "ks:ks_type":"HABITATION",
    "name:eng_x_preferred":[
        "Paglabari"
    ],
    "wof:name":"Paglabari",
    "wof:placetype":"locality",
    "wof:population":332
},
  "geometry": {"coordinates":[91.08914900000001,26.069469],"type":"Point"}
}