{
  "type": "Feature",
  "properties": {
    "gn:admin1_code":"36",
    "gn:admin2_code":"144.0",
    "gn:asciiname":"Rohal",
    "gn:country_code":"IN",
    "gn:dem":183,
    "gn:feature_class":"P",
    "gn:feature_code":"PPL",
    "gn:name":"Rohal",
    "gn:population":0,
    "gn:timezone":"Asia/Kolkata",
    "iso:country":"IN",
    "wof:name":"Rohal",
    "wof:placetype":"locality"
},
  "geometry": {"coordinates":[78.09591,27.73349],"type":"Point"}
}