{
  "type": "Feature",
  "properties": {
    "iso:country":"IN",
    "ks:ks_name":"16 NWD",
    "ks:ks_pop":64,
    "ks:ks_type":"VILLAGE",
    "name:eng_x_preferred":[
        "16 NWD"
    ],
    "wof:name":"16 NWD",
    "wof:placetype":"locality",
    "wof:population":64
},
  "geometry": {"coordinates":[74.377448,29.186279],"type":"Point"}
}