{
  "type": "Feature",
  "properties": {
    "gn:admin1_code":"34.0",
    "gn:admin2_code":"207.0",
    "gn:asciiname":"Indarwa",
    "gn:country_code":"IN",
    "gn:dem":63,
    "gn:feature_class":"P",
    "gn:feature_code":"PPL",
    "gn:name":"Indarwa",
    "gn:population":0,
    "gn:timezone":"Asia/Kolkata",
    "iso:country":"IN",
    "name:tam_x_preferred":[
        "\u0b87\u0ba8\u0bcd\u0ba4\u0bb0\u0bcd\u0bb5\u0bbe"
    ],
    "wof:name":"Indarwa",
    "wof:placetype":"neighbourhood"
},
  "geometry": {"coordinates":[86.26655,26.34329],"type":"Point"}
}