{
  "type": "Feature",
  "properties": {
    "iso:country":"IN",
    "ks:ks_name":"Upala Falia",
    "ks:ks_pop":307,
    "ks:ks_type":"HABITATION",
    "name:eng_x_preferred":[
        "Upala Falia"
    ],
    "wof:name":"Upala Falia",
    "wof:placetype":"locality",
    "wof:population":307
},
  "geometry": {"coordinates":[73.430083,20.892167],"type":"Point"}
}