{
  "type": "Feature",
  "properties": {
    "gn:admin1_code":"34.0",
    "gn:admin2_code":"215.0",
    "gn:asciiname":"Belaur",
    "gn:country_code":"IN",
    "gn:dem":55,
    "gn:feature_class":"P",
    "gn:feature_code":"PPL",
    "gn:name":"Belaur",
    "gn:population":0,
    "gn:timezone":"Asia/Kolkata",
    "iso:country":"IN",
    "name:bul_x_preferred":[
        "\u0411\u0435\u043b\u0430\u0443\u0440"
    ],
    "name:por_x_preferred":[
        "Belaur"
    ],
    "name:rus_x_preferred":[
        "\u0411\u0435\u043b\u0430\u0443\u0440"
    ],
    "name:spa_x_preferred":[
        "Belaur"
    ],
    "name:srp_x_preferred":[
        "\u0411\u0435\u043b\u0430\u0443\u0440"
    ],
    "wof:name":"Belaur",
    "wof:placetype":"locality"
},
  "geometry": {"coordinates":[86.14043000000002,26.20847],"type":"Point"}
}