{
  "type": "Feature",
  "properties": {
    "gn:admin1_code":"38.0",
    "gn:admin2_code":"360.0",
    "gn:asciiname":"Dhanwar",
    "gn:country_code":"IN",
    "gn:dem":431,
    "gn:feature_class":"P",
    "gn:feature_code":"PPL",
    "gn:name":"Dhanwar",
    "gn:population":0,
    "gn:timezone":"Asia/Kolkata",
    "iso:country":"IN",
    "ks:ks_name":"Dhanwar",
    "ks:ks_pop":3676,
    "ks:ks_type":"VILLAGE",
    "ks:ks_uagg_main":0,
    "name:eng_x_preferred":[
        "Dhanwar"
    ],
    "wof:name":"Dhanwar",
    "wof:placetype":"neighbourhood",
    "wof:population":3676
},
  "geometry": {"coordinates":[85.477779,24.251017],"type":"Point"}
}