{
  "type": "Feature",
  "properties": {
    "iso:country":"IN",
    "ks:ks_name":"Boosi",
    "ks:ks_pop":1222,
    "ks:ks_type":"HABITATION",
    "name:eng_x_preferred":[
        "Boosi"
    ],
    "wof:name":"Boosi",
    "wof:placetype":"locality",
    "wof:population":1222
},
  "geometry": {"coordinates":[81.636881,24.425043],"type":"Point"}
}