{
  "type": "Feature",
  "properties": {
    "gn:admin1_code":"35",
    "gn:admin2_code":"449.0",
    "gn:asciiname":"Bhaironpur",
    "gn:country_code":"IN",
    "gn:dem":313,
    "gn:feature_class":"P",
    "gn:feature_code":"PPL",
    "gn:name":"Bhaironpur",
    "gn:population":0,
    "gn:timezone":"Asia/Kolkata",
    "iso:country":"IN",
    "wof:name":"Bhaironpur",
    "wof:placetype":"locality"
},
  "geometry": {"coordinates":[77.39336999999998,22.4482],"type":"Point"}
}