{
  "type": "Feature",
  "properties": {
    "iso:country":"IN",
    "ks:ks_alt_nam":"Karet\u0101",
    "ks:ks_name":"Kareta",
    "ks:ks_type":"VILLAGE",
    "name:eng_x_preferred":[
        "Kareta"
    ],
    "name:eng_x_variant":[
        "Karet\u0101"
    ],
    "wof:name":"Kareta",
    "wof:placetype":"locality"
},
  "geometry": {"coordinates":[82.06423100000001,20.913905],"type":"Point"}
}