{
  "type": "Feature",
  "properties": {
    "iso:country":"IN",
    "ks:ks_name":"Kalyanpur",
    "ks:ks_pop":2016,
    "ks:ks_type":"VILLAGE",
    "ks:ks_uagg_main":0,
    "name:eng_x_preferred":[
        "Kalyanpur"
    ],
    "wof:name":"Kalyanpur",
    "wof:placetype":"neighbourhood",
    "wof:population":2016
},
  "geometry": {"coordinates":[85.864187,20.375701],"type":"Point"}
}