{
  "type": "Feature",
  "properties": {
    "iso:country":"IN",
    "ks:ks_alt_nam":"Muniyan kollai",
    "ks:ks_name":"Muniyan Kollai",
    "ks:ks_pop":350,
    "ks:ks_type":"HABITATION",
    "name:eng_x_preferred":[
        "Muniyan Kollai"
    ],
    "wof:name":"Muniyan Kollai",
    "wof:placetype":"locality",
    "wof:population":350
},
  "geometry": {"coordinates":[78.525328,12.663736],"type":"Point"}
}