{
  "type": "Feature",
  "properties": {
    "iso:country":"IN",
    "ks:ks_alt_nam":"Ras\u016blpur Sadar",
    "ks:ks_name":"Rasulpur Sadar",
    "ks:ks_type":"VILLAGE",
    "name:eng_x_preferred":[
        "Rasulpur Sadar"
    ],
    "name:eng_x_variant":[
        "Ras\u016blpur Sadar"
    ],
    "wof:name":"Rasulpur Sadar",
    "wof:placetype":"locality"
},
  "geometry": {"coordinates":[78.393294,29.243466],"type":"Point"}
}