{
  "type": "Feature",
  "properties": {
    "iso:country":"IN",
    "ks:ks_alt_nam":"Rukkama tanda",
    "ks:ks_name":"Rukkama Tanda",
    "ks:ks_pop":55,
    "ks:ks_type":"HABITATION",
    "name:eng_x_preferred":[
        "Rukkama Tanda"
    ],
    "wof:name":"Rukkama Tanda",
    "wof:placetype":"locality",
    "wof:population":55
},
  "geometry": {"coordinates":[78.061887,16.472506],"type":"Point"}
}