{
  "type": "Feature",
  "properties": {
    "gn:admin1_code":"12.0",
    "gn:admin2_code":"19.0",
    "gn:asciiname":"Thirdu",
    "gn:country_code":"IN",
    "gn:dem":1904,
    "gn:feature_class":"P",
    "gn:feature_code":"PPL",
    "gn:name":"Thirdu",
    "gn:population":0,
    "gn:timezone":"Asia/Kolkata",
    "iso:country":"IN",
    "wof:name":"Thirdu",
    "wof:placetype":"locality"
},
  "geometry": {"coordinates":[75.52216,32.86759],"type":"Point"}
}