{
  "type": "Feature",
  "properties": {
    "iso:country":"IN",
    "ks:ks_alt_nam":"naya tol",
    "ks:ks_name":"Naya Tol",
    "ks:ks_pop":363,
    "ks:ks_type":"HABITATION",
    "name:eng_x_preferred":[
        "Naya Tol"
    ],
    "wof:name":"Naya Tol",
    "wof:placetype":"locality",
    "wof:population":363
},
  "geometry": {"coordinates":[86.08390900000001,25.943274],"type":"Point"}
}