{
  "type": "Feature",
  "properties": {
    "iso:country":"IN",
    "ks:ks_name":"Panisali",
    "ks:ks_pop":719,
    "ks:ks_type":"VILLAGE",
    "ks:ks_uagg_main":0,
    "name:eng_x_preferred":[
        "Panisali"
    ],
    "wof:name":"Panisali",
    "wof:placetype":"neighbourhood",
    "wof:population":719
},
  "geometry": {"coordinates":[90.272313,25.990573],"type":"Point"}
}