{
  "type": "Feature",
  "properties": {
    "gn:admin1_code":"11.0",
    "gn:admin2_code":"32.0",
    "gn:asciiname":"Nau",
    "gn:country_code":"IN",
    "gn:dem":944,
    "gn:feature_class":"P",
    "gn:feature_code":"PPL",
    "gn:name":"N\u0101u",
    "gn:population":0,
    "gn:timezone":"Asia/Kolkata",
    "iso:country":"IN",
    "name:arg_x_preferred":[
        "Nau"
    ],
    "name:cat_x_preferred":[
        "Nau"
    ],
    "name:ceb_x_preferred":[
        "Nau"
    ],
    "name:deu_x_preferred":[
        "Nau"
    ],
    "name:fra_x_preferred":[
        "Nau"
    ],
    "name:nld_x_preferred":[
        "Middenschip"
    ],
    "name:pol_x_preferred":[
        "Nau"
    ],
    "name:ron_x_preferred":[
        "Nau"
    ],
    "name:swe_x_preferred":[
        "Nau"
    ],
    "wof:name":"Nau",
    "wof:placetype":"locality"
},
  "geometry": {"coordinates":[77.76935999999998,30.53559000000001],"type":"Point"}
}