{
  "type": "Feature",
  "properties": {
    "gn:admin1_code":"36.0",
    "gn:admin2_code":"182",
    "gn:asciiname":"Jarwa",
    "gn:country_code":"IN",
    "gn:dem":160,
    "gn:feature_class":"P",
    "gn:feature_code":"PPL",
    "gn:name":"Jarwa",
    "gn:population":0,
    "gn:timezone":"Asia/Kolkata",
    "iso:country":"IN",
    "name:ceb_x_preferred":[
        "Jarwa"
    ],
    "name:swe_x_preferred":[
        "Jarwa"
    ],
    "name:tam_x_preferred":[
        "\u0b9c\u0bbe\u0bb0\u0bcd\u0bb5\u0bbe"
    ],
    "name:urd_x_preferred":[
        "\u062c\u0631\u0648\u0627"
    ],
    "wof:name":"Jarwa",
    "wof:placetype":"neighbourhood"
},
  "geometry": {"coordinates":[82.52419,27.64659],"type":"Point"}
}