{
  "type": "Feature",
  "properties": {
    "iso:country":"IN",
    "ks:ks_alt_nam":"PADMA MOHON PARA",
    "ks:ks_name":"Padma Mohon Para",
    "ks:ks_pop":225,
    "ks:ks_type":"HABITATION",
    "name:eng_x_preferred":[
        "Padma Mohon Para"
    ],
    "wof:name":"Padma Mohon Para",
    "wof:placetype":"locality",
    "wof:population":225
},
  "geometry": {"coordinates":[91.698617,23.920521],"type":"Point"}
}