{
  "type": "Feature",
  "properties": {
    "iso:country":"IN",
    "ks:ks_name":"Panickarambalam",
    "ks:ks_pop":1179,
    "ks:ks_type":"HABITATION",
    "name:eng_x_preferred":[
        "Panickarambalam"
    ],
    "wof:name":"Panickarambalam",
    "wof:placetype":"locality",
    "wof:population":1179
},
  "geometry": {"coordinates":[76.52943399999999,10.056743],"type":"Point"}
}