{
  "type": "Feature",
  "properties": {
    "iso:country":"IN",
    "ks:ks_name":"Badraguthu",
    "ks:ks_pop":43,
    "ks:ks_type":"HABITATION",
    "name:eng_x_preferred":[
        "Badraguthu"
    ],
    "wof:name":"Badraguthu",
    "wof:placetype":"locality",
    "wof:population":43
},
  "geometry": {"coordinates":[74.89797799999999,13.298424],"type":"Point"}
}