{
  "type": "Feature",
  "properties": {
    "iso:country":"IN",
    "ks:ks_name":"Kamchi Gaon",
    "ks:ks_pop":166,
    "ks:ks_type":"VILLAGE",
    "ks:ks_uagg_main":0,
    "name:eng_x_preferred":[
        "Kamchi Gaon"
    ],
    "wof:name":"Kamchi Gaon",
    "wof:placetype":"neighbourhood",
    "wof:population":166
},
  "geometry": {"coordinates":[94.62174899999999,27.544841],"type":"Point"}
}