{
  "type": "Feature",
  "properties": {
    "gn:admin1_code":"19",
    "gn:admin2_code":"563.0",
    "gn:asciiname":"Gonur",
    "gn:country_code":"IN",
    "gn:dem":601,
    "gn:feature_class":"P",
    "gn:feature_code":"PPL",
    "gn:name":"Gon\u016br",
    "gn:population":0,
    "gn:timezone":"Asia/Kolkata",
    "iso:country":"IN",
    "ks:ks_alt_nam":"Gon\u016br",
    "ks:ks_name":"Gonur",
    "ks:ks_pop":319,
    "ks:ks_type":"VILLAGE",
    "name:eng_x_preferred":[
        "Gonur"
    ],
    "name:eng_x_variant":[
        "Gon\u016br"
    ],
    "wof:name":"Gonur",
    "wof:placetype":"locality",
    "wof:population":319
},
  "geometry": {"coordinates":[74.936824,14.636212],"type":"Point"}
}