{
  "type": "Feature",
  "properties": {
    "iso:country":"IN",
    "ks:ks_name":"Paharganj",
    "ks:ks_pop":1845,
    "ks:ks_type":"VILLAGE",
    "ks:ks_uagg_main":0,
    "name:eng_x_preferred":[
        "Paharganj"
    ],
    "wof:name":"Paharganj",
    "wof:placetype":"neighbourhood",
    "wof:population":1845
},
  "geometry": {"coordinates":[89.383725,26.181913],"type":"Point"}
}