{
  "type": "Feature",
  "properties": {
    "iso:country":"IN",
    "ks:ks_alt_nam":"LAGO SAI",
    "ks:ks_name":"Lago Sai",
    "ks:ks_pop":66,
    "ks:ks_type":"HABITATION",
    "name:eng_x_preferred":[
        "Lago Sai"
    ],
    "wof:name":"Lago Sai",
    "wof:placetype":"locality",
    "wof:population":66
},
  "geometry": {"coordinates":[85.89333999999999,22.154573],"type":"Point"}
}