{
  "type": "Feature",
  "properties": {
    "iso:country":"IN",
    "ks:ks_name":"Kurma",
    "ks:ks_pop":98,
    "ks:ks_type":"HABITATION",
    "name:eng_x_preferred":[
        "Kurma"
    ],
    "wof:name":"Kurma",
    "wof:placetype":"locality",
    "wof:population":98
},
  "geometry": {"coordinates":[87.338841,24.519412],"type":"Point"}
}