{
  "type": "Feature",
  "properties": {
    "iso:country":"IN",
    "ks:ks_name":"Chinapattapupalem",
    "ks:ks_pop":500,
    "ks:ks_type":"HABITATION",
    "name:eng_x_preferred":[
        "Chinapattapupalem"
    ],
    "wof:name":"Chinapattapupalem",
    "wof:placetype":"locality",
    "wof:population":500
},
  "geometry": {"coordinates":[80.115837,15.363259],"type":"Point"}
}