{
  "type": "Feature",
  "properties": {
    "iso:country":"IN",
    "ks:ks_alt_nam":"Tarlapalli",
    "ks:ks_name":"Thallapalle",
    "ks:ks_pop":10950,
    "ks:ks_type":"VILLAGE",
    "name:eng_x_preferred":[
        "Thallapalle"
    ],
    "name:eng_x_variant":[
        "Tarlapalli"
    ],
    "wof:name":"Thallapalle",
    "wof:placetype":"locality",
    "wof:population":10950
},
  "geometry": {"coordinates":[79.49068,18.834475],"type":"Point"}
}