{
  "type": "Feature",
  "properties": {
    "gn:admin1_code":"36",
    "gn:admin2_code":"183.0",
    "gn:asciiname":"Karia",
    "gn:country_code":"IN",
    "gn:dem":110,
    "gn:feature_class":"P",
    "gn:feature_code":"PPL",
    "gn:name":"Karia",
    "gn:population":0,
    "gn:timezone":"Asia/Kolkata",
    "iso:country":"IN",
    "name:mar_x_preferred":[
        "\u0915\u0930\u093f\u092f\u093e"
    ],
    "wof:name":"Karia",
    "wof:placetype":"locality"
},
  "geometry": {"coordinates":[81.94401999999999,27.14279],"type":"Point"}
}