{
  "type": "Feature",
  "properties": {
    "gn:admin1_code":"36",
    "gn:admin2_code":"183.0",
    "gn:asciiname":"Karia",
    "gn:country_code":"IN",
    "gn:dem":110,
    "gn:feature_class":"P",
    "gn:feature_code":"PPL",
    "gn:name":"Karia",
    "gn:population":0,
    "gn:timezone":"Asia/Kolkata",
    "iso:country":"IN",
    "name:ara_x_preferred":[
        "\u0643\u0627\u0631\u064a\u0627"
    ],
    "name:ben_bn_x_preferred":[
        "\u0995\u09be\u09b0\u09bf\u09df\u09be"
    ],
    "name:ben_in_x_preferred":[
        "\u0995\u09be\u09b0\u09bf\u09df\u09be"
    ],
    "name:guj_x_preferred":[
        "\u0a95\u0ab0\u0abf\u0aaf\u0abe"
    ],
    "name:hin_x_preferred":[
        "\u0915\u0930\u093f\u092f\u093e"
    ],
    "name:kan_x_preferred":[
        "\u0c95\u0cbe\u0cb0\u0cbf\u0caf\u0cbe"
    ],
    "name:mal_x_preferred":[
        "\u0d15\u0d30\u0d3f\u0d2f"
    ],
    "name:mar_x_preferred":[
        "\u0915\u093e\u0930\u0940\u0906"
    ],
    "name:mar_x_variant":[
        "\u0915\u0930\u093f\u092f\u093e"
    ],
    "name:pan_x_preferred":[
        "\u0a15\u0a30\u0a40\u0a06"
    ],
    "name:tam_x_preferred":[
        "\u0b95\u0bb0\u0bbf\u0baf\u0bbe"
    ],
    "name:tel_x_preferred":[
        "\u0c15\u0c30\u0c3f\u0c2f\u0c3e"
    ],
    "name:urd_x_preferred":[
        "\u06a9\u0631\u06cc\u0627"
    ],
    "wof:name":"Karia",
    "wof:placetype":"locality"
},
  "geometry": {"coordinates":[81.94401999999999,27.14279],"type":"Point"}
}