{
  "type": "Feature",
  "properties": {
    "iso:country":"IN",
    "ks:ks_name":"Bharathipuram",
    "ks:ks_pop":80,
    "ks:ks_type":"HABITATION",
    "name:eng_x_preferred":[
        "Bharathipuram"
    ],
    "wof:name":"Bharathipuram",
    "wof:placetype":"locality",
    "wof:population":80
},
  "geometry": {"coordinates":[78.87142,10.510025],"type":"Point"}
}