{
  "type": "Feature",
  "properties": {
    "iso:country":"IN",
    "ks:ks_name":"Meelavalachery",
    "ks:ks_pop":231,
    "ks:ks_type":"HABITATION",
    "name:eng_x_preferred":[
        "Meelavalachery"
    ],
    "wof:name":"Meelavalachery",
    "wof:placetype":"locality",
    "wof:population":231
},
  "geometry": {"coordinates":[79.496742,10.740545],"type":"Point"}
}