{
  "type": "Feature",
  "properties": {
    "iso:country":"IN",
    "ks:ks_name":"Joscgiri",
    "ks:ks_pop":241,
    "ks:ks_type":"HABITATION",
    "name:eng_x_preferred":[
        "Joscgiri"
    ],
    "wof:name":"Joscgiri",
    "wof:placetype":"locality",
    "wof:population":241
},
  "geometry": {"coordinates":[76.010138,11.418148],"type":"Point"}
}