{
  "type": "Feature",
  "properties": {
    "iso:country":"IN",
    "ks:ks_alt_nam":"KOLEKAR PANDHARE MANE WASTI",
    "ks:ks_name":"Kolekar Pandhare Mane Wasti",
    "ks:ks_pop":82,
    "ks:ks_type":"HABITATION",
    "name:eng_x_preferred":[
        "Kolekar Pandhare Mane Wasti"
    ],
    "wof:name":"Kolekar Pandhare Mane Wasti",
    "wof:placetype":"locality",
    "wof:population":82
},
  "geometry": {"coordinates":[75.072401,17.160658],"type":"Point"}
}