{
  "type": "Feature",
  "properties": {
    "iso:country":"IN",
    "ks:ks_name":"Gapea Japea",
    "ks:ks_pop":228,
    "ks:ks_type":"HABITATION",
    "name:eng_x_preferred":[
        "Gapea Japea"
    ],
    "wof:name":"Gapea Japea",
    "wof:placetype":"locality",
    "wof:population":228
},
  "geometry": {"coordinates":[90.798254,26.351799],"type":"Point"}
}