{
  "type": "Feature",
  "properties": {
    "iso:country":"IN",
    "ks:ks_name":"Tungi",
    "ks:ks_pop":7542,
    "ks:ks_type":"VILLAGE",
    "ks:ks_uagg_main":0,
    "name:eng_x_preferred":[
        "Tungi"
    ],
    "wof:name":"Tungi",
    "wof:placetype":"neighbourhood",
    "wof:population":7542
},
  "geometry": {"coordinates":[88.73162000000001,23.41832],"type":"Point"}
}