{
  "type": "Feature",
  "properties": {
    "iso:country":"IN",
    "ks:ks_name":"Sirpa",
    "ks:ks_pop":393,
    "ks:ks_type":"HABITATION",
    "name:eng_x_preferred":[
        "Sirpa"
    ],
    "wof:name":"Sirpa",
    "wof:placetype":"locality",
    "wof:population":393
},
  "geometry": {"coordinates":[85.551102,23.380268],"type":"Point"}
}