{
  "type": "Feature",
  "properties": {
    "gn:admin1_code":"16.0",
    "gn:admin2_code":"509.0",
    "gn:asciiname":"Sindi",
    "gn:country_code":"IN",
    "gn:dem":181,
    "gn:feature_class":"P",
    "gn:feature_code":"PPL",
    "gn:name":"Sindi",
    "gn:population":0,
    "gn:timezone":"Asia/Kolkata",
    "iso:country":"IN",
    "name:ceb_x_preferred":[
        "Sindi"
    ],
    "name:deu_x_preferred":[
        "Sindi"
    ],
    "name:lav_x_preferred":[
        "Sindi"
    ],
    "name:nld_x_preferred":[
        "Sindi"
    ],
    "name:por_x_preferred":[
        "Sindi"
    ],
    "name:rus_x_preferred":[
        "\u0421\u0438\u043d\u0434\u0438"
    ],
    "name:swe_x_preferred":[
        "Sindi"
    ],
    "name:ukr_x_preferred":[
        "\u0421\u0456\u043d\u0434\u0456"
    ],
    "wof:name":"Sindi",
    "wof:placetype":"locality"
},
  "geometry": {"coordinates":[79.46155999999998,19.65989],"type":"Point"}
}