{
  "type": "Feature",
  "properties": {
    "iso:country":"IN",
    "ks:ks_name":"Godbahara",
    "ks:ks_pop":1029,
    "ks:ks_type":"HABITATION",
    "name:eng_x_preferred":[
        "Godbahara"
    ],
    "wof:name":"Godbahara",
    "wof:placetype":"locality",
    "wof:population":1029
},
  "geometry": {"coordinates":[82.196146,24.097226],"type":"Point"}
}