{
  "type": "Feature",
  "properties": {
    "gn:admin1_code":"12",
    "gn:admin2_code":"20.0",
    "gn:asciiname":"Shajru",
    "gn:country_code":"IN",
    "gn:dem":1699,
    "gn:feature_class":"P",
    "gn:feature_code":"PPL",
    "gn:name":"Shajr\u016b",
    "gn:population":0,
    "gn:timezone":"Asia/Kolkata",
    "iso:country":"IN",
    "wof:name":"Shajru",
    "wof:placetype":"locality"
},
  "geometry": {"coordinates":[74.88651999999998,33.28991],"type":"Point"}
}