{
  "type": "Feature",
  "properties": {
    "iso:country":"IN",
    "ks:ks_name":"Badduthanda",
    "ks:ks_pop":212,
    "ks:ks_type":"HABITATION",
    "name:eng_x_preferred":[
        "Badduthanda"
    ],
    "wof:name":"Badduthanda",
    "wof:placetype":"locality",
    "wof:population":212
},
  "geometry": {"coordinates":[78.80374399999999,17.65429],"type":"Point"}
}