{
  "type": "Feature",
  "properties": {
    "gn:admin1_code":"34.0",
    "gn:admin2_code":"218.0",
    "gn:asciiname":"Muhammadpur",
    "gn:country_code":"IN",
    "gn:dem":63,
    "gn:feature_class":"P",
    "gn:feature_code":"PPL",
    "gn:name":"Muhammadpur",
    "gn:population":0,
    "gn:timezone":"Asia/Kolkata",
    "iso:country":"IN",
    "ks:ks_name":"Mahammadpur",
    "ks:ks_pop":2466,
    "ks:ks_type":"VILLAGE",
    "ks:ks_uagg_main":0,
    "name:eng_x_preferred":[
        "Mahammadpur"
    ],
    "wof:name":"Mahammadpur",
    "wof:placetype":"neighbourhood",
    "wof:population":2466
},
  "geometry": {"coordinates":[84.67250300000001,26.085556],"type":"Point"}
}