{
  "type": "Feature",
  "properties": {
    "iso:country":"IN",
    "ks:ks_name":"Garianchun",
    "ks:ks_pop":691,
    "ks:ks_type":"VILLAGE",
    "name:eng_x_preferred":[
        "Garianchun"
    ],
    "wof:name":"Garianchun",
    "wof:placetype":"locality",
    "wof:population":691
},
  "geometry": {"coordinates":[85.821609,24.563831],"type":"Point"}
}