{
  "type": "Feature",
  "properties": {
    "gn:admin1_code":"11",
    "gn:admin2_code":"27.0",
    "gn:asciiname":"Matlag",
    "gn:country_code":"IN",
    "gn:dem":1253,
    "gn:feature_class":"P",
    "gn:feature_code":"PPL",
    "gn:name":"Matlag",
    "gn:population":0,
    "gn:timezone":"Asia/Kolkata",
    "iso:country":"IN",
    "wof:name":"Matlag",
    "wof:placetype":"locality"
},
  "geometry": {"coordinates":[76.75924999999999,31.69883],"type":"Point"}
}