{
  "type": "Feature",
  "properties": {
    "iso:country":"IN",
    "ks:ks_alt_nam":"BENDIAN  KA PURWA",
    "ks:ks_name":"Bendian Ka Purwa",
    "ks:ks_pop":93,
    "ks:ks_type":"HABITATION",
    "ks:ks_uagg_main":0,
    "name:eng_x_preferred":[
        "Bendian Ka Purwa"
    ],
    "name:eng_x_variant":[
        "BENDIAN  KA PURWA"
    ],
    "wof:name":"Bendian Ka Purwa",
    "wof:placetype":"neighbourhood",
    "wof:population":93
},
  "geometry": {"coordinates":[82.18958000000001,26.297855],"type":"Point"}
}