{
  "type": "Feature",
  "properties": {
    "iso:country":"IN",
    "ks:ks_name":"23 HMH",
    "ks:ks_pop":547,
    "ks:ks_type":"VILLAGE",
    "ks:ks_uagg_main":0,
    "name:eng_x_preferred":[
        "23 HMH"
    ],
    "wof:name":"23 HMH",
    "wof:placetype":"neighbourhood",
    "wof:population":547
},
  "geometry": {"coordinates":[74.24464,29.534547],"type":"Point"}
}