{
  "type": "Feature",
  "properties": {
    "iso:country":"IN",
    "ks:ks_name":"Manmane",
    "ks:ks_pop":28,
    "ks:ks_type":"HABITATION",
    "name:eng_x_preferred":[
        "Manmane"
    ],
    "wof:name":"Manmane",
    "wof:placetype":"locality",
    "wof:population":28
},
  "geometry": {"coordinates":[74.640783,14.920146],"type":"Point"}
}