{
  "type": "Feature",
  "properties": {
    "gn:admin1_code":"38.0",
    "gn:admin2_code":"353.0",
    "gn:asciiname":"Ratanpur",
    "gn:country_code":"IN",
    "gn:dem":60,
    "gn:feature_class":"P",
    "gn:feature_code":"PPL",
    "gn:name":"Ratanpur",
    "gn:population":0,
    "gn:timezone":"Asia/Kolkata",
    "iso:country":"IN",
    "wof:name":"Ratanpur",
    "wof:placetype":"locality"
},
  "geometry": {"coordinates":[87.75801,24.49728],"type":"Point"}
}