{
  "type": "Feature",
  "properties": {
    "gn:admin1_code":"36",
    "gn:admin2_code":"162.0",
    "gn:asciiname":"Mandata Purwa",
    "gn:country_code":"IN",
    "gn:dem":143,
    "gn:feature_class":"P",
    "gn:feature_code":"PPL",
    "gn:name":"M\u0101nd\u0101ta Purwa",
    "gn:population":0,
    "gn:timezone":"Asia/Kolkata",
    "iso:country":"IN",
    "wof:name":"Mandata Purwa",
    "wof:placetype":"locality"
},
  "geometry": {"coordinates":[79.63,26.64314],"type":"Point"}
}