{
  "type": "Feature",
  "properties": {
    "iso:country":"IN",
    "ks:ks_name":"Nishchintpur",
    "ks:ks_pop":68,
    "ks:ks_type":"VILLAGE",
    "name:eng_x_preferred":[
        "Nishchintpur"
    ],
    "wof:name":"Nishchintpur",
    "wof:placetype":"locality",
    "wof:population":68
},
  "geometry": {"coordinates":[85.57195400000001,22.746918],"type":"Point"}
}