{
  "type": "Feature",
  "properties": {
    "iso:country":"IN",
    "ks:ks_alt_nam":"GOURA P",
    "ks:ks_name":"Goura P",
    "ks:ks_pop":2366,
    "ks:ks_type":"HABITATION",
    "name:eng_x_preferred":[
        "Goura P"
    ],
    "wof:name":"Goura P",
    "wof:placetype":"locality",
    "wof:population":2366
},
  "geometry": {"coordinates":[85.97016499999999,25.515255],"type":"Point"}
}