{
  "type": "Feature",
  "properties": {
    "iso:country":"IN",
    "ks:ks_name":"Doodhora",
    "ks:ks_pop":577,
    "ks:ks_type":"HABITATION",
    "name:eng_x_preferred":[
        "Doodhora"
    ],
    "wof:name":"Doodhora",
    "wof:placetype":"locality",
    "wof:population":577
},
  "geometry": {"coordinates":[70.80010299999999,25.988744],"type":"Point"}
}