{
  "type": "Feature",
  "properties": {
    "gn:admin1_code":"36",
    "gn:admin2_code":"155.0",
    "gn:asciiname":"Hattia Haran",
    "gn:country_code":"IN",
    "gn:dem":137,
    "gn:feature_class":"P",
    "gn:feature_code":"PPL",
    "gn:name":"Hattia H\u0101r\u0101n",
    "gn:population":0,
    "gn:timezone":"Asia/Kolkata",
    "iso:country":"IN",
    "ks:ks_name":"Hatyaharan",
    "ks:ks_pop":168,
    "ks:ks_type":"HABITATION",
    "ks:ks_uagg_main":0,
    "name:eng_x_preferred":[
        "Hatyaharan"
    ],
    "wof:name":"Hatyaharan",
    "wof:placetype":"neighbourhood",
    "wof:population":168
},
  "geometry": {"coordinates":[80.522277,27.218991],"type":"Point"}
}