{
  "type": "Feature",
  "properties": {
    "iso:country":"IN",
    "ks:ks_name":"Nathripada",
    "ks:ks_pop":120,
    "ks:ks_type":"HABITATION",
    "name:eng_x_preferred":[
        "Nathripada"
    ],
    "wof:name":"Nathripada",
    "wof:placetype":"locality",
    "wof:population":120
},
  "geometry": {"coordinates":[74.617149,21.017121],"type":"Point"}
}