{
  "type": "Feature",
  "properties": {
    "iso:country":"IN",
    "ks:ks_name":"Choambull",
    "ks:ks_pop":22,
    "ks:ks_type":"HABITATION",
    "name:eng_x_preferred":[
        "Choambull"
    ],
    "wof:name":"Choambull",
    "wof:placetype":"locality",
    "wof:population":22
},
  "geometry": {"coordinates":[74.584413,14.644344],"type":"Point"}
}