{
  "type": "Feature",
  "properties": {
    "iso:country":"IN",
    "ks:ks_name":"Jhaddumuria",
    "ks:ks_pop":506,
    "ks:ks_type":"VILLAGE",
    "name:eng_x_preferred":[
        "Jhaddumuria"
    ],
    "wof:name":"Jhaddumuria",
    "wof:placetype":"locality",
    "wof:population":506
},
  "geometry": {"coordinates":[85.963947,21.787514],"type":"Point"}
}