{
  "type": "Feature",
  "properties": {
    "iso:country":"IN",
    "ks:ks_name":"Adiwasiwadi",
    "ks:ks_pop":46,
    "ks:ks_type":"HABITATION",
    "name:eng_x_preferred":[
        "Adiwasiwadi"
    ],
    "wof:name":"Adiwasiwadi",
    "wof:placetype":"locality",
    "wof:population":46
},
  "geometry": {"coordinates":[73.351558,18.030554],"type":"Point"}
}