{
  "type": "Feature",
  "properties": {
    "gn:admin1_code":"40.0",
    "gn:admin2_code":"540",
    "gn:asciiname":"Chelvai",
    "gn:country_code":"IN",
    "gn:dem":164,
    "gn:feature_class":"P",
    "gn:feature_code":"PPL",
    "gn:name":"Chelvai",
    "gn:population":0,
    "gn:timezone":"Asia/Kolkata",
    "iso:country":"IN",
    "wof:name":"Chelvai",
    "wof:placetype":"locality"
},
  "geometry": {"coordinates":[80.10468,18.20459],"type":"Point"}
}