{
  "type": "Feature",
  "properties": {
    "iso:country":"IN",
    "ks:ks_alt_nam":"BABU PARA",
    "ks:ks_name":"Babu Para",
    "ks:ks_pop":1600,
    "ks:ks_type":"HABITATION",
    "name:eng_x_preferred":[
        "Babu Para"
    ],
    "wof:name":"Babu Para",
    "wof:placetype":"locality",
    "wof:population":1600
},
  "geometry": {"coordinates":[88.594393,26.603103],"type":"Point"}
}