{
  "type": "Feature",
  "properties": {
    "iso:country":"IN",
    "ks:ks_name":"Gidhawa",
    "ks:ks_pop":1241,
    "ks:ks_type":"VILLAGE",
    "name:eng_x_preferred":[
        "Gidhawa"
    ],
    "wof:name":"Gidhawa",
    "wof:placetype":"locality",
    "wof:population":1241
},
  "geometry": {"coordinates":[84.16271,26.716753],"type":"Point"}
}