{
  "type": "Feature",
  "properties": {
    "iso:country":"IN",
    "name:ara_x_preferred":[
        "\u062f\u0627\u0631\u0627\u062c\u0627\u0646\u062c"
    ],
    "name:ben_bn_x_preferred":[
        "\u09a6\u09be\u09b0\u09be\u0997\u099e\u09cd\u099c"
    ],
    "name:ben_in_x_preferred":[
        "\u09a6\u09be\u09b0\u09be\u0997\u099e\u09cd\u099c"
    ],
    "name:bho_x_preferred":[
        "\u0926\u093e\u0930\u093e\u0917\u0902\u091c"
    ],
    "name:eng_x_preferred":[
        "Daraganj"
    ],
    "name:eng_x_variant":[
        "Darhganj"
    ],
    "name:guj_x_preferred":[
        "\u0aa6\u0abe\u0ab0\u0abe\u0a97\u0a82\u0a9c"
    ],
    "name:hin_x_preferred":[
        "\u0926\u0930\u093e\u0917\u0902\u091c"
    ],
    "name:kan_x_preferred":[
        "\u0ca6\u0cbe\u0cb0\u0cbe\u0c97\u0c82\u0c9c\u0ccd"
    ],
    "name:mal_x_preferred":[
        "\u0d26\u0d3e\u0d30\u0d17\u0d1e\u0d4d\u0d1a\u0d4d"
    ],
    "name:mar_x_preferred":[
        "\u0926\u093e\u0930\u093e\u0917\u0902\u091c"
    ],
    "name:nld_x_preferred":[
        "Daraganj"
    ],
    "name:pan_x_preferred":[
        "\u0a26\u0a3e\u0a30\u0a3e\u0a17\u0a70\u0a1c"
    ],
    "name:tam_x_preferred":[
        "\u0b9f\u0bb0\u0bbe\u0b95\u0b9e\u0bcd\u0b9a\u0bcd"
    ],
    "name:tel_x_preferred":[
        "\u0c21\u0c30\u0c3e\u0c17\u0c02\u0c1c\u0c4d"
    ],
    "name:und_x_variant":[
        "D\u0101r\u0101ganj"
    ],
    "name:urd_x_preferred":[
        "\u062f\u0627\u0631\u0627 \u06af\u0646\u062c"
    ],
    "qs:gn_adm0_cc":"IN",
    "qs:gn_local":1278994,
    "qs:gn_nam_loc":"Allahabad, Allahabad, Uttar Pradesh, IN",
    "qs:gn_namadm1":"36",
    "qs:local_max":391,
    "qs:local_sum":573,
    "qs:localhoods":4,
    "qs:name":"Daraganj",
    "qs:name_adm0":"India",
    "qs:name_adm1":"Uttar Pradesh",
    "qs:name_adm2":"Allahabad",
    "qs:name_local":"Allahabad",
    "qs:photo_max":104,
    "qs:photo_sum":391,
    "qs:placetype":"Suburb",
    "qs:quad_count":35,
    "qs:woe_adm0":23424848,
    "qs:woe_adm1":2345760,
    "qs:woe_adm2":12586715,
    "qs:woe_lau":0,
    "qs:woe_local":2295379,
    "qs:woe_ver":"7.10.0",
    "wd:wordcount":1354,
    "wof:lang":[
        "eng"
    ],
    "wof:name":"Daraganj",
    "wof:placetype":"neighbourhood"
},
  "geometry": {"coordinates":[81.890714,25.425616],"type":"Point"}
}