{
  "type": "Feature",
  "properties": {
    "iso:country":"IN",
    "name:eng_x_preferred":[
        "Daraganj"
    ],
    "name:eng_x_variant":[
        "Darhganj"
    ],
    "name:und_x_preferred":[
        "D\u0101r\u0101ganj"
    ],
    "name:unk_x_variant":[
        "Daraganj"
    ],
    "qs:gn_adm0_cc":"IN",
    "qs:gn_local":1278994,
    "qs:gn_nam_loc":"Allahabad, Allahabad, Uttar Pradesh, IN",
    "qs:gn_namadm1":"36",
    "qs:local_max":391,
    "qs:local_sum":573,
    "qs:localhoods":4,
    "qs:name":"Daraganj",
    "qs:name_adm0":"India",
    "qs:name_adm1":"Uttar Pradesh",
    "qs:name_adm2":"Allahabad",
    "qs:name_local":"Allahabad",
    "qs:photo_max":104,
    "qs:photo_sum":391,
    "qs:placetype":"Suburb",
    "qs:quad_count":35,
    "qs:woe_adm0":23424848,
    "qs:woe_adm1":2345760,
    "qs:woe_adm2":12586715,
    "qs:woe_lau":0,
    "qs:woe_local":2295379,
    "qs:woe_ver":"7.10.0",
    "wd:wordcount":1354,
    "wof:lang":[
        "eng"
    ],
    "wof:name":"Daraganj",
    "wof:placetype":"neighbourhood"
},
  "geometry": {"coordinates":[81.890714,25.425616],"type":"Point"}
}