{
  "type": "Feature",
  "properties": {
    "iso:country":"IN",
    "ks:ks_name":"Keraliya",
    "ks:ks_pop":393,
    "ks:ks_type":"VILLAGE",
    "name:eng_x_preferred":[
        "Keraliya"
    ],
    "wof:name":"Keraliya",
    "wof:placetype":"locality",
    "wof:population":393
},
  "geometry": {"coordinates":[71.501419,26.904872],"type":"Point"}
}