{
  "type": "Feature",
  "properties": {
    "gn:admin1_code":"2.0",
    "gn:admin2_code":"547.0",
    "gn:asciiname":"Patapadu",
    "gn:country_code":"IN",
    "gn:dem":30,
    "gn:feature_class":"P",
    "gn:feature_code":"PPL",
    "gn:name":"P\u0101tap\u0101du",
    "gn:population":0,
    "gn:timezone":"Asia/Kolkata",
    "iso:country":"IN",
    "wof:name":"Patapadu",
    "wof:placetype":"locality"
},
  "geometry": {"coordinates":[80.66523000000002,16.57808],"type":"Point"}
}