{
  "type": "Feature",
  "properties": {
    "iso:country":"IN",
    "ks:ks_name":"Paniapalli",
    "ks:ks_pop":0,
    "ks:ks_type":"VILLAGE",
    "name:eng_x_preferred":[
        "Paniapalli"
    ],
    "wof:name":"Paniapalli",
    "wof:placetype":"locality",
    "wof:population":0
},
  "geometry": {"coordinates":[84.54489700000001,19.561569],"type":"Point"}
}