{
  "type": "Feature",
  "properties": {
    "gn:admin1_code":"2.0",
    "gn:asciiname":"Pakkam",
    "gn:country_code":"IN",
    "gn:dem":6,
    "gn:feature_class":"P",
    "gn:feature_code":"PPL",
    "gn:name":"P\u0101kkam",
    "gn:population":0,
    "gn:timezone":"Asia/Kolkata",
    "iso:country":"IN",
    "name:ara_x_preferred":[
        "\u0628\u0627\u0643\u0627\u0645"
    ],
    "name:ben_bn_x_preferred":[
        "\u09aa\u09be\u0995\u09cd\u0995\u09be\u09ae"
    ],
    "name:ben_in_x_preferred":[
        "\u09aa\u09be\u0995\u09cd\u0995\u09be\u09ae"
    ],
    "name:guj_x_preferred":[
        "\u0aaa\u0a95\u0acd\u0a95\u0aae"
    ],
    "name:hin_x_preferred":[
        "\u092a\u0915\u094d\u0915\u092e"
    ],
    "name:kan_x_preferred":[
        "\u0caa\u0c95\u0ccd\u0c95\u0cae\u0ccd"
    ],
    "name:mal_x_preferred":[
        "\u0d2a\u0d3e\u0d15\u0d4d\u0d15\u0d02"
    ],
    "name:mar_x_preferred":[
        "\u092a\u0915\u094d\u0915\u092e"
    ],
    "name:pan_x_preferred":[
        "\u0a2a\u0a71\u0a15\u0a2e"
    ],
    "name:tam_x_preferred":[
        "\u0baa\u0bbe\u0b95\u0bcd\u0b95\u0bae\u0bcd"
    ],
    "name:tel_x_preferred":[
        "\u0c2a\u0c15\u0c4d\u0c15\u0c2e\u0c4d"
    ],
    "name:urd_x_preferred":[
        "\u067e\u0627\u06a9\u0651\u0645"
    ],
    "wof:name":"Pakkam",
    "wof:placetype":"locality"
},
  "geometry": {"coordinates":[80.27771,13.41508],"type":"Point"}
}