{
  "type": "Feature",
  "properties": {
    "iso:country":"IN",
    "ks:ks_name":"Nawadih B",
    "ks:ks_pop":7,
    "ks:ks_type":"HABITATION",
    "name:eng_x_preferred":[
        "Nawadih B"
    ],
    "wof:name":"Nawadih B",
    "wof:placetype":"locality",
    "wof:population":7
},
  "geometry": {"coordinates":[86.77241100000001,24.315338],"type":"Point"}
}