{
  "type": "Feature",
  "properties": {
    "iso:country":"IN",
    "ks:ks_name":"Hotloo",
    "ks:ks_pop":487,
    "ks:ks_type":"VILLAGE",
    "name:eng_x_preferred":[
        "Hotloo"
    ],
    "wof:name":"Hotloo",
    "wof:placetype":"locality",
    "wof:population":487
},
  "geometry": {"coordinates":[72.31925,25.829064],"type":"Point"}
}