{
  "type": "Feature",
  "properties": {
    "gn:admin1_code":"2",
    "gn:admin2_code":"544.0",
    "gn:asciiname":"Gudivada",
    "gn:country_code":"IN",
    "gn:dem":10,
    "gn:feature_class":"P",
    "gn:feature_code":"PPL",
    "gn:name":"Gudiv\u0101da",
    "gn:population":0,
    "gn:timezone":"Asia/Kolkata",
    "iso:country":"IN",
    "name:bih_x_preferred":[
        "\u0917\u0941\u0921\u093f\u0935\u093e\u0921\u093e"
    ],
    "name:bpy_x_preferred":[
        "\u0997\u09c1\u09a6\u09bf\u09ac\u09be\u09a6\u09be"
    ],
    "name:ceb_x_preferred":[
        "Gudiv\u0101da"
    ],
    "name:ita_x_preferred":[
        "Gudivada"
    ],
    "name:msa_x_preferred":[
        "Gudivada"
    ],
    "name:new_x_preferred":[
        "\u0917\u0941\u0921\u093f\u0935\u093e\u0921\u093e"
    ],
    "name:nld_x_preferred":[
        "Gudivada"
    ],
    "name:ori_x_preferred":[
        "\u0b17\u0b41\u0b26\u0b3f\u0b2d\u0b21\u0b3c\u0b3e"
    ],
    "name:pam_x_preferred":[
        "Gudivada"
    ],
    "name:por_x_preferred":[
        "Gudivada"
    ],
    "name:swe_x_preferred":[
        "Gudivada"
    ],
    "name:tam_x_preferred":[
        "\u0b95\u0bc1\u0b9f\u0bbf\u0bb5\u0bbe\u0b9f\u0bbe"
    ],
    "name:tel_x_preferred":[
        "\u0c17\u0c41\u0c21\u0c3f\u0c35\u0c3e\u0c21"
    ],
    "name:tgl_x_preferred":[
        "Gudivada"
    ],
    "name:urd_x_preferred":[
        "\u06af\u0691\u06cc\u0648\u0627\u0688\u0627"
    ],
    "name:vie_x_preferred":[
        "Gudivada"
    ],
    "name:war_x_preferred":[
        "Gudivada"
    ],
    "name:zho_x_preferred":[
        "\u53e4\u8fea\u74e6\u8fbe"
    ],
    "wof:name":"Gudivada",
    "wof:placetype":"locality"
},
  "geometry": {"coordinates":[82.79080999999999,17.39744],"type":"Point"}
}