{
  "type": "Feature",
  "properties": {
    "gn:admin1_code":"34.0",
    "gn:admin2_code":"222.0",
    "gn:asciiname":"Rudauli",
    "gn:country_code":"IN",
    "gn:dem":52,
    "gn:feature_class":"P",
    "gn:feature_code":"PPL",
    "gn:name":"Rudauli",
    "gn:population":0,
    "gn:timezone":"Asia/Kolkata",
    "iso:country":"IN",
    "name:bpy_x_preferred":[
        "\u09b0\u09c1\u09a6\u09be\u0989\u09b2\u09bf"
    ],
    "name:ceb_x_preferred":[
        "Rudauli"
    ],
    "name:hin_x_preferred":[
        "\u0930\u0941\u0926\u094c\u0932\u0940"
    ],
    "name:ita_x_preferred":[
        "Rudauli"
    ],
    "name:mlg_x_preferred":[
        "Rudauli"
    ],
    "name:msa_x_preferred":[
        "Rudauli"
    ],
    "name:nld_x_preferred":[
        "Rudauli"
    ],
    "name:ori_x_preferred":[
        "\u0b30\u0b41\u0b26\u0b3e\u0b09\u0b32\u0b3f"
    ],
    "name:pnb_x_preferred":[
        "\u0631\u0648\u062f\u0648\u0644\u06cc"
    ],
    "name:pol_x_preferred":[
        "Rudauli"
    ],
    "name:por_x_preferred":[
        "Rudauli"
    ],
    "name:swe_x_preferred":[
        "Rudauli"
    ],
    "name:urd_x_preferred":[
        "\u0631\u0648\u062f\u0648\u0644\u06cc"
    ],
    "name:vie_x_preferred":[
        "Rudauli"
    ],
    "name:zho_x_preferred":[
        "\u9c81\u9053\u5229"
    ],
    "wof:name":"Rudauli",
    "wof:placetype":"locality"
},
  "geometry": {"coordinates":[85.95499000000002,25.59599],"type":"Point"}
}