{
  "type": "Feature",
  "properties": {
    "iso:country":"IN",
    "ks:ks_name":"Ramnagariya",
    "ks:ks_pop":39,
    "ks:ks_type":"HABITATION",
    "name:eng_x_preferred":[
        "Ramnagariya"
    ],
    "wof:name":"Ramnagariya",
    "wof:placetype":"locality",
    "wof:population":39
},
  "geometry": {"coordinates":[79.394308,26.799234],"type":"Point"}
}