{
  "type": "Feature",
  "properties": {
    "iso:country":"IN",
    "ks:ks_name":"Chak Arna",
    "ks:ks_pop":11,
    "ks:ks_type":"VILLAGE",
    "ks:ks_uagg_main":0,
    "name:eng_x_preferred":[
        "Chak Arna"
    ],
    "wof:name":"Chak Arna",
    "wof:placetype":"neighbourhood",
    "wof:population":11
},
  "geometry": {"coordinates":[84.903085,25.869449],"type":"Point"}
}