{
  "type": "Feature",
  "properties": {
    "iso:country":"IN",
    "ks:ks_alt_nam":"PURWIHAN PURWA",
    "ks:ks_name":"Purwihan Purwa",
    "ks:ks_pop":63,
    "ks:ks_type":"HABITATION",
    "name:eng_x_preferred":[
        "Purwihan Purwa"
    ],
    "wof:name":"Purwihan Purwa",
    "wof:placetype":"locality",
    "wof:population":63
},
  "geometry": {"coordinates":[81.68830699999999,27.63473],"type":"Point"}
}