{
  "type": "Feature",
  "properties": {
    "iso:country":"IN",
    "ks:ks_name":"Sakhrwadi",
    "ks:ks_pop":136,
    "ks:ks_type":"HABITATION",
    "name:eng_x_preferred":[
        "Sakhrwadi"
    ],
    "wof:name":"Sakhrwadi",
    "wof:placetype":"locality",
    "wof:population":136
},
  "geometry": {"coordinates":[73.17265,19.301715],"type":"Point"}
}