{
  "type": "Feature",
  "properties": {
    "iso:country":"IN",
    "ks:ks_name":"Sadavadihitlu",
    "ks:ks_pop":215,
    "ks:ks_type":"HABITATION",
    "name:eng_x_preferred":[
        "Sadavadihitlu"
    ],
    "wof:name":"Sadavadihitlu",
    "wof:placetype":"locality",
    "wof:population":215
},
  "geometry": {"coordinates":[74.752481,13.261476],"type":"Point"}
}