{
  "type": "Feature",
  "properties": {
    "gn:admin1_code":"11.0",
    "gn:admin2_code":"33.0",
    "gn:asciiname":"Nawan",
    "gn:country_code":"IN",
    "gn:dem":1770,
    "gn:feature_class":"P",
    "gn:feature_code":"PPL",
    "gn:name":"Nawan",
    "gn:population":0,
    "gn:timezone":"Asia/Kolkata",
    "iso:country":"IN",
    "name:fas_x_preferred":[
        "\u0646\u0648\u0627\u0646"
    ],
    "name:hin_x_preferred":[
        "\u0928\u094c\u0935\u093e\u0901"
    ],
    "name:urd_x_preferred":[
        "\u0646\u0648\u0627\u06ba"
    ],
    "wof:name":"Nawan",
    "wof:placetype":"locality"
},
  "geometry": {"coordinates":[77.27481,31.12802000000001],"type":"Point"}
}