{
  "type": "Feature",
  "properties": {
    "gn:admin1_code":"36",
    "gn:admin2_code":"149.0",
    "gn:asciiname":"Khajura",
    "gn:country_code":"IN",
    "gn:dem":147,
    "gn:feature_class":"P",
    "gn:feature_code":"PPL",
    "gn:name":"Khaj\u016bra",
    "gn:population":0,
    "gn:timezone":"Asia/Kolkata",
    "iso:country":"IN",
    "ks:ks_alt_nam":"Khaj\u016bra",
    "ks:ks_name":"Khajura",
    "ks:ks_pop":0,
    "ks:ks_type":"VILLAGE",
    "name:eng_x_preferred":[
        "Khajura"
    ],
    "name:eng_x_variant":[
        "Khaj\u016bra"
    ],
    "wof:name":"Khajura",
    "wof:placetype":"locality",
    "wof:population":0
},
  "geometry": {"coordinates":[79.295073,27.697337],"type":"Point"}
}