{
  "type": "Feature",
  "properties": {
    "iso:country":"IN",
    "ks:ks_alt_nam":"kuttikara kunnu jn",
    "ks:ks_name":"Kuttikara Kunnu Jn",
    "ks:ks_pop":347,
    "ks:ks_type":"HABITATION",
    "name:eng_x_preferred":[
        "Kuttikara Kunnu Jn"
    ],
    "wof:name":"Kuttikara Kunnu Jn",
    "wof:placetype":"locality",
    "wof:population":347
},
  "geometry": {"coordinates":[76.27902899999999,10.275443],"type":"Point"}
}