{
  "type": "Feature",
  "properties": {
    "gn:admin1_code":"24.0",
    "gn:admin2_code":"120.0",
    "gn:asciiname":"Mahapura",
    "gn:country_code":"IN",
    "gn:dem":334,
    "gn:feature_class":"P",
    "gn:feature_code":"PPL",
    "gn:name":"Mah\u0101pura",
    "gn:population":0,
    "gn:timezone":"Asia/Kolkata",
    "iso:country":"IN",
    "wof:name":"Mahapura",
    "wof:placetype":"locality"
},
  "geometry": {"coordinates":[75.40009999999999,26.2452],"type":"Point"}
}