{
  "type": "Feature",
  "properties": {
    "iso:country":"IN",
    "ks:ks_name":"Semara",
    "ks:ks_pop":236,
    "ks:ks_type":"HABITATION",
    "name:eng_x_preferred":[
        "Semara"
    ],
    "wof:name":"Semara",
    "wof:placetype":"locality",
    "wof:population":236
},
  "geometry": {"coordinates":[82.95320100000001,27.279888],"type":"Point"}
}