{
  "type": "Feature",
  "properties": {
    "iso:country":"IN",
    "ks:ks_alt_nam":"Zah\u012br\u0101b\u0101d",
    "ks:ks_name":"Zahirabad",
    "ks:ks_type":"VILLAGE",
    "name:eng_x_preferred":[
        "Zahirabad"
    ],
    "name:eng_x_variant":[
        "Zah\u012br\u0101b\u0101d"
    ],
    "wof:name":"Zahirabad",
    "wof:placetype":"locality"
},
  "geometry": {"coordinates":[78.454385,29.195319],"type":"Point"}
}