{
  "type": "Feature",
  "properties": {
    "iso:country":"IN",
    "ks:ks_name":"Kambakathadam",
    "ks:ks_pop":536,
    "ks:ks_type":"HABITATION",
    "ks:ks_uagg_main":0,
    "name:eng_x_preferred":[
        "Kambakathadam"
    ],
    "wof:name":"Kambakathadam",
    "wof:placetype":"neighbourhood",
    "wof:population":536
},
  "geometry": {"coordinates":[76.987353,8.957404],"type":"Point"}
}