{
  "type": "Feature",
  "properties": {
    "iso:country":"IN",
    "ks:ks_name":"Marikanthai",
    "ks:ks_pop":543,
    "ks:ks_type":"HABITATION",
    "ks:ks_uagg_main":0,
    "name:eng_x_preferred":[
        "Marikanthai"
    ],
    "wof:name":"Marikanthai",
    "wof:placetype":"neighbourhood",
    "wof:population":543
},
  "geometry": {"coordinates":[77.181685,10.713227],"type":"Point"}
}