{
  "type": "Feature",
  "properties": {
    "iso:country":"IN",
    "name:ara_x_preferred":[
        "\u0628\u0627\u0645\u0634\u064a\u062a\u0627"
    ],
    "name:ben_bn_x_preferred":[
        "\u09ac\u09be\u09ae\u09b6\u09bf\u09a4\u09be"
    ],
    "name:ben_in_x_preferred":[
        "\u09ac\u09be\u09ae\u09b6\u09bf\u09a4\u09be"
    ],
    "name:guj_x_preferred":[
        "\u0aac\u0abe\u0aae\u0ab6\u0abf\u0aa4\u0abe"
    ],
    "name:hin_x_preferred":[
        "\u092c\u092e\u094d\u0936\u093f\u0924\u093e"
    ],
    "name:kan_x_preferred":[
        "\u0cac\u0cae\u0ccd"
    ],
    "name:mal_x_preferred":[
        "\u0d2c\u0d02\u0d37\u0d3f\u0d24"
    ],
    "name:mar_x_preferred":[
        "\u092c\u093e\u092e\u0936\u093f\u0924\u093e"
    ],
    "name:pan_x_preferred":[
        "\u0a2c\u0a48\u0a2e\u0a36\u0a3f\u0a1f\u0a3e"
    ],
    "name:tam_x_preferred":[
        "\u0baa\u0bae\u0bcd\u0bb7\u0bbf\u0b9f\u0bbe"
    ],
    "name:tel_x_preferred":[
        "\u0c2c\u0c02\u0c37\u0c3f\u0c1f\u0c3e"
    ],
    "name:urd_x_preferred":[
        "\u0628\u0645\u0634\u06cc\u0627"
    ],
    "qs:name":"Bamshita",
    "qs:name_adm0":"India",
    "qs:name_adm1":"Himachal Pradesh",
    "qs:photos":1,
    "qs:photos_1k":1,
    "qs:photos_9k":1,
    "qs:photos_9r":1,
    "qs:photos_all":1,
    "qs:photos_sr":1,
    "qs:placetype":"Suburb",
    "qs:pop_sr":"0",
    "wof:name":"Bamshita",
    "wof:placetype":"neighbourhood"
},
  "geometry": {"coordinates":[77.11166299999999,31.967056],"type":"Point"}
}