{
  "type": "Feature",
  "properties": {
    "iso:country":"IN",
    "qs:name":"Bamshita",
    "qs:name_adm0":"India",
    "qs:name_adm1":"Himachal Pradesh",
    "qs:photos":1,
    "qs:photos_1k":1,
    "qs:photos_9k":1,
    "qs:photos_9r":1,
    "qs:photos_all":1,
    "qs:photos_sr":1,
    "qs:placetype":"Suburb",
    "qs:pop_sr":"0",
    "wof:name":"Bamshita",
    "wof:placetype":"neighbourhood"
},
  "geometry": {"coordinates":[77.11166299999999,31.967056],"type":"Point"}
}