{
  "type": "Feature",
  "properties": {
    "iso:country":"IN",
    "ks:ks_alt_nam":"Karewadi KK",
    "ks:ks_name":"Karewadi Kk",
    "ks:ks_pop":382,
    "ks:ks_type":"HABITATION",
    "name:eng_x_preferred":[
        "Karewadi Kk"
    ],
    "wof:name":"Karewadi Kk",
    "wof:placetype":"locality",
    "wof:population":382
},
  "geometry": {"coordinates":[74.34880200000001,19.656669],"type":"Point"}
}