{
  "type": "Feature",
  "properties": {
    "gn:admin1_code":"35.0",
    "gn:admin2_code":"454.0",
    "gn:asciiname":"Lalpur",
    "gn:country_code":"IN",
    "gn:dem":420,
    "gn:feature_class":"P",
    "gn:feature_code":"PPL",
    "gn:name":"L\u0101lpur",
    "gn:population":0,
    "gn:timezone":"Asia/Kolkata",
    "iso:country":"IN",
    "ks:ks_alt_nam":"L\u0101lpur",
    "ks:ks_name":"Lalpur",
    "ks:ks_type":"VILLAGE",
    "name:ceb_x_preferred":[
        "Lalpur"
    ],
    "name:eng_x_preferred":[
        "Lalpur"
    ],
    "name:eng_x_variant":[
        "L\u0101lpur"
    ],
    "name:pol_x_preferred":[
        "Lalpur"
    ],
    "name:swe_x_preferred":[
        "Lalpur"
    ],
    "wof:name":"Lalpur",
    "wof:placetype":"locality"
},
  "geometry": {"coordinates":[80.04898799999999,22.849985],"type":"Point"}
}