{
  "type": "Feature",
  "properties": {
    "gn:admin1_code":"36.0",
    "gn:admin2_code":"152",
    "gn:asciiname":"Kilapur Kalan",
    "gn:country_code":"IN",
    "gn:dem":150,
    "gn:feature_class":"P",
    "gn:feature_code":"PPL",
    "gn:name":"Kil\u0101pur Kal\u0101n",
    "gn:population":0,
    "gn:timezone":"Asia/Kolkata",
    "iso:country":"IN",
    "ks:ks_name":"Kilapur Kalan",
    "ks:ks_pop":1974,
    "ks:ks_type":"VILLAGE",
    "name:eng_x_preferred":[
        "Kilapur Kalan"
    ],
    "wof:name":"Kilapur Kalan",
    "wof:placetype":"locality",
    "wof:population":1974
},
  "geometry": {"coordinates":[79.556251,27.719673],"type":"Point"}
}