{
  "type": "Feature",
  "properties": {
    "iso:country":"IN",
    "ks:ks_name":"Bhogaon Nipani",
    "ks:ks_pop":1847,
    "ks:ks_type":"VILLAGE",
    "name:eng_x_preferred":[
        "Bhogaon Nipani"
    ],
    "wof:name":"Bhogaon Nipani",
    "wof:placetype":"locality",
    "wof:population":1847
},
  "geometry": {"coordinates":[75.91762199999999,22.125062],"type":"Point"}
}