{
  "type": "Feature",
  "properties": {
    "iso:country":"IN",
    "ks:ks_alt_nam":"Laloda(K)",
    "ks:ks_name":"Laloda(k)",
    "ks:ks_pop":85,
    "ks:ks_type":"HABITATION",
    "name:eng_x_preferred":[
        "Laloda(k)"
    ],
    "wof:name":"Laloda(k)",
    "wof:placetype":"locality",
    "wof:population":85
},
  "geometry": {"coordinates":[73.00916700000001,23.804028],"type":"Point"}
}