{
  "type": "Feature",
  "properties": {
    "iso:country":"IN",
    "ks:ks_name":"Dhanpur",
    "ks:ks_pop":295,
    "ks:ks_type":"VILLAGE",
    "name:eng_x_preferred":[
        "Dhanpur"
    ],
    "wof:name":"Dhanpur",
    "wof:placetype":"locality",
    "wof:population":295
},
  "geometry": {"coordinates":[78.47726299999999,30.693732],"type":"Point"}
}