{
  "type": "Feature",
  "properties": {
    "iso:country":"IN",
    "ks:ks_name":"Kurian Purwa",
    "ks:ks_pop":357,
    "ks:ks_type":"HABITATION",
    "ks:ks_uagg_main":0,
    "name:eng_x_preferred":[
        "Kurian Purwa"
    ],
    "wof:name":"Kurian Purwa",
    "wof:placetype":"neighbourhood",
    "wof:population":357
},
  "geometry": {"coordinates":[80.043352,26.5196],"type":"Point"}
}