{
  "type": "Feature",
  "properties": {
    "gn:admin1_code":"11",
    "gn:admin2_code":"23.0",
    "gn:asciiname":"Dibri",
    "gn:country_code":"IN",
    "gn:dem":1412,
    "gn:feature_class":"P",
    "gn:feature_code":"PPL",
    "gn:name":"Dibri",
    "gn:population":0,
    "gn:timezone":"Asia/Kolkata",
    "iso:country":"IN",
    "name:ceb_x_preferred":[
        "Dibri"
    ],
    "name:swe_x_preferred":[
        "Dibri"
    ],
    "wof:name":"Dibri",
    "wof:placetype":"locality"
},
  "geometry": {"coordinates":[76.10984999999999,32.53834000000001],"type":"Point"}
}