{
  "type": "Feature",
  "properties": {
    "iso:country":"IN",
    "ks:ks_name":"Patelpara",
    "ks:ks_pop":367,
    "ks:ks_type":"HABITATION",
    "name:eng_x_preferred":[
        "Patelpara"
    ],
    "wof:name":"Patelpara",
    "wof:placetype":"locality",
    "wof:population":367
},
  "geometry": {"coordinates":[81.57269100000001,18.883453],"type":"Point"}
}