{
  "type": "Feature",
  "properties": {
    "iso:country":"IN",
    "ks:ks_name":"Sawrachar Pathar",
    "ks:ks_pop":216,
    "ks:ks_type":"VILLAGE",
    "ks:ks_uagg_main":0,
    "name:eng_x_preferred":[
        "Sawrachar Pathar"
    ],
    "wof:name":"Sawrachar Pathar",
    "wof:placetype":"neighbourhood",
    "wof:population":216
},
  "geometry": {"coordinates":[90.83160599999999,26.277278],"type":"Point"}
}