{
  "type": "Feature",
  "properties": {
    "gn:admin1_code":"21",
    "gn:admin2_code":"372.0",
    "gn:asciiname":"Butitikra",
    "gn:country_code":"IN",
    "gn:dem":180,
    "gn:feature_class":"P",
    "gn:feature_code":"PPL",
    "gn:name":"Butitikra",
    "gn:population":0,
    "gn:timezone":"Asia/Kolkata",
    "iso:country":"IN",
    "wof:name":"Butitikra",
    "wof:placetype":"neighbourhood"
},
  "geometry": {"coordinates":[83.88923,21.4566],"type":"Point"}
}