{
  "type": "Feature",
  "properties": {
    "gn:admin1_code":"39.0",
    "gn:admin2_code":"64.0",
    "gn:asciiname":"Bairon Bakhal",
    "gn:country_code":"IN",
    "gn:dem":845,
    "gn:feature_class":"P",
    "gn:feature_code":"PPL",
    "gn:name":"Bairon B\u0101khal",
    "gn:population":0,
    "gn:timezone":"Asia/Kolkata",
    "iso:country":"IN",
    "wof:name":"Bairon Bakhal",
    "wof:placetype":"locality"
},
  "geometry": {"coordinates":[79.21634,29.63952],"type":"Point"}
}