{
  "type": "Feature",
  "properties": {
    "iso:country":"IN",
    "ks:ks_name":"Khegro Ki Bhagal",
    "ks:ks_pop":829,
    "ks:ks_type":"HABITATION",
    "name:eng_x_preferred":[
        "Khegro Ki Bhagal"
    ],
    "wof:name":"Khegro Ki Bhagal",
    "wof:placetype":"locality",
    "wof:population":829
},
  "geometry": {"coordinates":[73.807236,24.544997],"type":"Point"}
}