{
  "type": "Feature",
  "properties": {
    "iso:country":"IN",
    "ks:ks_name":"Sinkaipur",
    "ks:ks_pop":295,
    "ks:ks_type":"VILLAGE",
    "name:eng_x_preferred":[
        "Sinkaipur"
    ],
    "wof:name":"Sinkaipur",
    "wof:placetype":"locality",
    "wof:population":295
},
  "geometry": {"coordinates":[88.422681,24.20677],"type":"Point"}
}