{
  "type": "Feature",
  "properties": {
    "gn:admin1_code":"25.0",
    "gn:admin2_code":"607.0",
    "gn:asciiname":"Kuppam",
    "gn:country_code":"IN",
    "gn:dem":26,
    "gn:feature_class":"P",
    "gn:feature_code":"PPL",
    "gn:name":"Kuppam",
    "gn:population":0,
    "gn:timezone":"Asia/Kolkata",
    "iso:country":"IN",
    "name:bpy_x_preferred":[
        "\u0995\u09c1\u09aa\u09cd\u09aa\u09be\u09ae"
    ],
    "name:ceb_x_preferred":[
        "Kuppam"
    ],
    "name:hin_x_preferred":[
        "\u0915\u0941\u092a\u094d\u092a\u092e"
    ],
    "name:ita_x_preferred":[
        "Kuppam"
    ],
    "name:kan_x_preferred":[
        "\u0c95\u0cc1\u0caa\u0ccd\u0caa\u0c82"
    ],
    "name:mar_x_preferred":[
        "\u0915\u0941\u092a\u094d\u092a\u092e"
    ],
    "name:mlg_x_preferred":[
        "Kuppam"
    ],
    "name:msa_x_preferred":[
        "Kuppam"
    ],
    "name:new_x_preferred":[
        "\u0915\u0941\u092a\u094d\u092a\u092e"
    ],
    "name:nld_x_preferred":[
        "Kuppam"
    ],
    "name:nor_x_preferred":[
        "Kuppam"
    ],
    "name:por_x_preferred":[
        "Kuppam"
    ],
    "name:swe_x_preferred":[
        "Kuppam"
    ],
    "name:tam_x_preferred":[
        "\u0b95\u0bc1\u0baa\u0bcd\u0baa\u0bae\u0bcd"
    ],
    "name:tel_x_preferred":[
        "\u0c15\u0c41\u0c2a\u0c4d\u0c2a\u0c02"
    ],
    "name:tgl_x_preferred":[
        "Kuppam"
    ],
    "name:urd_x_preferred":[
        "\u06a9\u067e\u0645"
    ],
    "name:vie_x_preferred":[
        "Kuppam"
    ],
    "name:zho_x_preferred":[
        "\u5e93\u666e\u5e15\u59c6"
    ],
    "wof:name":"Kuppam",
    "wof:placetype":"locality"
},
  "geometry": {"coordinates":[79.65755,12.01665],"type":"Point"}
}