{
  "type": "Feature",
  "properties": {
    "iso:country":"IN",
    "ks:ks_name":"Kamargram",
    "ks:ks_pop":0,
    "ks:ks_type":"VILLAGE",
    "name:eng_x_preferred":[
        "Kamargram"
    ],
    "wof:name":"Kamargram",
    "wof:placetype":"locality",
    "wof:population":0
},
  "geometry": {"coordinates":[87.365132,23.246569],"type":"Point"}
}