{
  "type": "Feature",
  "properties": {
    "iso:country":"IN",
    "ks:ks_name":"Pakhiralay",
    "ks:ks_pop":3871,
    "ks:ks_type":"VILLAGE",
    "ks:ks_uagg_main":0,
    "name:eng_x_preferred":[
        "Pakhiralay"
    ],
    "wof:name":"Pakhiralay",
    "wof:placetype":"locality",
    "wof:population":3871
},
  "geometry": {"coordinates":[88.83188699999999,22.145912],"type":"Point"}
}