{
  "type": "Feature",
  "properties": {
    "iso:country":"IN",
    "ks:ks_name":"Gumpula",
    "ks:ks_pop":1109,
    "ks:ks_type":"VILLAGE",
    "ks:ks_uagg_main":0,
    "name:eng_x_preferred":[
        "Gumpula"
    ],
    "wof:name":"Gumpula",
    "wof:placetype":"neighbourhood",
    "wof:population":1109
},
  "geometry": {"coordinates":[79.730014,17.104581],"type":"Point"}
}