{
  "type": "Feature",
  "properties": {
    "gn:admin1_code":"35",
    "gn:admin2_code":"459.0",
    "gn:asciiname":"Khagal",
    "gn:country_code":"IN",
    "gn:dem":393,
    "gn:feature_class":"P",
    "gn:feature_code":"PPL",
    "gn:name":"Kh\u0101gal",
    "gn:population":0,
    "gn:timezone":"Asia/Kolkata",
    "iso:country":"IN",
    "ks:ks_alt_nam":"Kh\u0101gal",
    "ks:ks_name":"Khagal",
    "ks:ks_pop":387,
    "ks:ks_type":"VILLAGE",
    "name:eng_x_preferred":[
        "Khagal"
    ],
    "name:eng_x_variant":[
        "Kh\u0101gal"
    ],
    "wof:name":"Khagal",
    "wof:placetype":"locality",
    "wof:population":387
},
  "geometry": {"coordinates":[78.19167,24.576199],"type":"Point"}
}