{
  "type": "Feature",
  "properties": {
    "gn:admin1_code":"36.0",
    "gn:admin2_code":"150.0",
    "gn:asciiname":"Bujhia Patti Janubi",
    "gn:country_code":"IN",
    "gn:dem":180,
    "gn:feature_class":"P",
    "gn:feature_code":"PPL",
    "gn:name":"Bujhia Patti Jan\u016bbi",
    "gn:population":0,
    "gn:timezone":"Asia/Kolkata",
    "iso:country":"IN",
    "wof:name":"Bujhia Patti Janubi",
    "wof:placetype":"neighbourhood"
},
  "geometry": {"coordinates":[79.46911,28.51281],"type":"Point"}
}