{
  "type": "Feature",
  "properties": {
    "iso:country":"IN",
    "ks:ks_name":"Vaini",
    "ks:ks_pop":348,
    "ks:ks_type":"VILLAGE",
    "name:eng_x_preferred":[
        "Vaini"
    ],
    "wof:name":"Vaini",
    "wof:placetype":"locality",
    "wof:population":348
},
  "geometry": {"coordinates":[74.49154900000001,15.335355],"type":"Point"}
}