{
  "type": "Feature",
  "properties": {
    "gn:admin1_code":"19.0",
    "gn:admin2_code":"575.0",
    "gn:asciiname":"Hiriyadka",
    "gn:country_code":"IN",
    "gn:dem":131,
    "gn:feature_class":"P",
    "gn:feature_code":"PPL",
    "gn:name":"Hiriyadka",
    "gn:population":0,
    "gn:timezone":"Asia/Kolkata",
    "iso:country":"IN",
    "ks:ks_name":"Hirthadka",
    "ks:ks_pop":270,
    "ks:ks_type":"HABITATION",
    "name:eng_x_preferred":[
        "Hirthadka"
    ],
    "name:eng_x_variant":[
        "Hiriyadka"
    ],
    "wof:name":"Hirthadka",
    "wof:placetype":"locality",
    "wof:population":270
},
  "geometry": {"coordinates":[75.52085099999999,12.728719],"type":"Point"}
}