{
  "type": "Feature",
  "properties": {
    "iso:country":"IN",
    "ks:ks_name":"Vadakkalur",
    "ks:ks_pop":1115,
    "ks:ks_type":"VILLAGE",
    "name:eng_x_preferred":[
        "Vadakkalur"
    ],
    "wof:name":"Vadakkalur",
    "wof:placetype":"locality",
    "wof:population":1115
},
  "geometry": {"coordinates":[77.09885800000001,11.266473],"type":"Point"}
}