{
  "type": "Feature",
  "properties": {
    "gn:admin1_code":"12",
    "gn:admin2_code":"15.0",
    "gn:asciiname":"Katsauhalan",
    "gn:country_code":"IN",
    "gn:dem":1796,
    "gn:feature_class":"P",
    "gn:feature_code":"PPL",
    "gn:name":"Katsauh\u0101lan",
    "gn:population":0,
    "gn:timezone":"Asia/Kolkata",
    "iso:country":"IN",
    "wof:name":"Katsauhalan",
    "wof:placetype":"locality"
},
  "geometry": {"coordinates":[74.96146,33.67082],"type":"Point"}
}