{
  "type": "Feature",
  "properties": {
    "iso:country":"IN",
    "ks:ks_name":"Satghara",
    "ks:ks_pop":527,
    "ks:ks_type":"VILLAGE",
    "name:eng_x_preferred":[
        "Satghara"
    ],
    "wof:name":"Satghara",
    "wof:placetype":"locality",
    "wof:population":527
},
  "geometry": {"coordinates":[88.018362,22.332521],"type":"Point"}
}