{
  "type": "Feature",
  "properties": {
    "iso:country":"IN",
    "ks:ks_alt_nam":"5 NTR",
    "ks:ks_name":"5 Ntr",
    "ks:ks_pop":189,
    "ks:ks_type":"HABITATION",
    "name:eng_x_preferred":[
        "5 Ntr"
    ],
    "wof:name":"5 Ntr",
    "wof:placetype":"locality",
    "wof:population":189
},
  "geometry": {"coordinates":[75.0338,29.216094],"type":"Point"}
}