{
  "type": "Feature",
  "properties": {
    "iso:country":"IN",
    "ks:ks_alt_nam":"Shirnath wadi",
    "ks:ks_name":"Shirnath Wadi",
    "ks:ks_pop":268,
    "ks:ks_type":"HABITATION",
    "name:eng_x_preferred":[
        "Shirnath Wadi"
    ],
    "wof:name":"Shirnath Wadi",
    "wof:placetype":"locality",
    "wof:population":268
},
  "geometry": {"coordinates":[73.97474800000001,18.372941],"type":"Point"}
}