{
  "type": "Feature",
  "properties": {
    "iso:country":"IN",
    "ks:ks_name":"Phudwani",
    "ks:ks_pop":23,
    "ks:ks_type":"HABITATION",
    "name:eng_x_preferred":[
        "Phudwani"
    ],
    "wof:name":"Phudwani",
    "wof:placetype":"locality",
    "wof:population":23
},
  "geometry": {"coordinates":[80.52544399999999,24.277881],"type":"Point"}
}