{
  "type": "Feature",
  "properties": {
    "iso:country":"IN",
    "ks:ks_name":"Kusrani",
    "ks:ks_pop":50,
    "ks:ks_type":"VILLAGE",
    "name:eng_x_preferred":[
        "Kusrani"
    ],
    "wof:name":"Kusrani",
    "wof:placetype":"locality",
    "wof:population":50
},
  "geometry": {"coordinates":[79.13518000000001,29.926369],"type":"Point"}
}