{
  "type": "Feature",
  "properties": {
    "gn:admin1_code":"19",
    "gn:admin2_code":"579.0",
    "gn:asciiname":"Gongi",
    "gn:country_code":"IN",
    "gn:dem":459,
    "gn:feature_class":"P",
    "gn:feature_code":"PPL",
    "gn:name":"Gongi",
    "gn:population":0,
    "gn:timezone":"Asia/Kolkata",
    "iso:country":"IN",
    "ks:ks_name":"Gongi",
    "ks:ks_type":"VILLAGE",
    "name:eng_x_preferred":[
        "Gongi"
    ],
    "wof:name":"Gongi",
    "wof:placetype":"locality"
},
  "geometry": {"coordinates":[77.104045,17.490894],"type":"Point"}
}