{
  "type": "Feature",
  "properties": {
    "iso:country":"IN",
    "ks:ks_name":"Madhukata",
    "ks:ks_pop":37,
    "ks:ks_type":"HABITATION",
    "name:eng_x_preferred":[
        "Madhukata"
    ],
    "wof:name":"Madhukata",
    "wof:placetype":"locality",
    "wof:population":37
},
  "geometry": {"coordinates":[86.12595399999999,24.056483],"type":"Point"}
}