{
  "type": "Feature",
  "properties": {
    "gn:admin1_code":"39.0",
    "gn:admin2_code":"061",
    "gn:asciiname":"Batkholu",
    "gn:country_code":"IN",
    "gn:dem":680,
    "gn:feature_class":"P",
    "gn:feature_code":"PPL",
    "gn:name":"Batkholu",
    "gn:population":0,
    "gn:timezone":"Asia/Kolkata",
    "iso:country":"IN",
    "wof:name":"Batkholu",
    "wof:placetype":"locality"
},
  "geometry": {"coordinates":[78.71169,29.93997],"type":"Point"}
}