{
  "type": "Feature",
  "properties": {
    "iso:country":"IN",
    "ks:ks_name":"Jalichapada",
    "ks:ks_pop":265,
    "ks:ks_type":"HABITATION",
    "name:eng_x_preferred":[
        "Jalichapada"
    ],
    "wof:name":"Jalichapada",
    "wof:placetype":"locality",
    "wof:population":265
},
  "geometry": {"coordinates":[73.35829,19.991561],"type":"Point"}
}