{
  "type": "Feature",
  "properties": {
    "iso:country":"IN",
    "ks:ks_name":"Bherepada",
    "ks:ks_pop":40,
    "ks:ks_type":"HABITATION",
    "name:eng_x_preferred":[
        "Bherepada"
    ],
    "wof:name":"Bherepada",
    "wof:placetype":"locality",
    "wof:population":40
},
  "geometry": {"coordinates":[73.42375699999999,19.338405],"type":"Point"}
}