{
  "type": "Feature",
  "properties": {
    "iso:country":"IN",
    "ks:ks_name":"Ganeshmala",
    "ks:ks_pop":438,
    "ks:ks_type":"HABITATION",
    "ks:ks_uagg_main":0,
    "name:eng_x_preferred":[
        "Ganeshmala"
    ],
    "wof:name":"Ganeshmala",
    "wof:placetype":"neighbourhood",
    "wof:population":438
},
  "geometry": {"coordinates":[74.129074,19.516423],"type":"Point"}
}