{
  "type": "Feature",
  "properties": {
    "iso:country":"IN",
    "ks:ks_name":"Thuruthipuram",
    "ks:ks_pop":1354,
    "ks:ks_type":"HABITATION",
    "ks:ks_uagg_main":0,
    "name:eng_x_preferred":[
        "Thuruthipuram"
    ],
    "wof:name":"Thuruthipuram",
    "wof:placetype":"neighbourhood",
    "wof:population":1354
},
  "geometry": {"coordinates":[76.228076,10.112456],"type":"Point"}
}