{
  "type": "Feature",
  "properties": {
    "gn:admin1_code":"24.0",
    "gn:admin2_code":"122.0",
    "gn:asciiname":"Kaulin Amli",
    "gn:country_code":"IN",
    "gn:dem":476,
    "gn:feature_class":"P",
    "gn:feature_code":"PPL",
    "gn:name":"Kaul\u012bn \u0100mli",
    "gn:population":0,
    "gn:timezone":"Asia/Kolkata",
    "iso:country":"IN",
    "wof:name":"Kaulin Amli",
    "wof:placetype":"locality"
},
  "geometry": {"coordinates":[74.36057,25.33045],"type":"Point"}
}