{
  "type": "Feature",
  "properties": {
    "iso:country":"IN",
    "ks:ks_name":"Kalinagar",
    "ks:ks_pop":249,
    "ks:ks_type":"HABITATION",
    "name:eng_x_preferred":[
        "Kalinagar"
    ],
    "wof:name":"Kalinagar",
    "wof:placetype":"locality",
    "wof:population":249
},
  "geometry": {"coordinates":[80.133955,12.495189],"type":"Point"}
}