{
  "type": "Feature",
  "properties": {
    "gn:admin1_code":"11.0",
    "gn:admin2_code":"33.0",
    "gn:asciiname":"Jam Jubar",
    "gn:country_code":"IN",
    "gn:dem":2031,
    "gn:feature_class":"P",
    "gn:feature_code":"PPL",
    "gn:name":"Jam Jubar",
    "gn:population":0,
    "gn:timezone":"Asia/Kolkata",
    "iso:country":"IN",
    "wof:name":"Jam Jubar",
    "wof:placetype":"locality"
},
  "geometry": {"coordinates":[77.22580000000001,30.99943],"type":"Point"}
}