{
  "type": "Feature",
  "properties": {
    "iso:country":"IN",
    "ks:ks_name":"Agar",
    "ks:ks_pop":0,
    "ks:ks_type":"VILLAGE",
    "name:eng_x_preferred":[
        "Agar"
    ],
    "wof:name":"Agar",
    "wof:placetype":"locality",
    "wof:population":0
},
  "geometry": {"coordinates":[86.51195300000001,23.528833],"type":"Point"}
}