{
  "type": "Feature",
  "properties": {
    "iso:country":"IN",
    "ks:ks_alt_nam":"CHENAMPULLY",
    "ks:ks_name":"Chenampully",
    "ks:ks_pop":1773,
    "ks:ks_type":"HABITATION",
    "name:eng_x_preferred":[
        "Chenampully"
    ],
    "wof:name":"Chenampully",
    "wof:placetype":"locality",
    "wof:population":1773
},
  "geometry": {"coordinates":[76.333206,10.814799],"type":"Point"}
}