{
  "type": "Feature",
  "properties": {
    "iso:country":"IN",
    "ks:ks_name":"Rajpura",
    "ks:ks_pop":6,
    "ks:ks_type":"HABITATION",
    "name:eng_x_preferred":[
        "Rajpura"
    ],
    "wof:name":"Rajpura",
    "wof:placetype":"locality",
    "wof:population":6
},
  "geometry": {"coordinates":[76.597216,25.49798],"type":"Point"}
}