{
  "type": "Feature",
  "properties": {
    "iso:country":"IN",
    "ks:ks_name":"Gauripur",
    "ks:ks_pop":444,
    "ks:ks_type":"VILLAGE",
    "ks:ks_uagg_main":0,
    "name:eng_x_preferred":[
        "Gauripur"
    ],
    "wof:name":"Gauripur",
    "wof:placetype":"neighbourhood",
    "wof:population":444
},
  "geometry": {"coordinates":[88.654383,24.059635],"type":"Point"}
}