{
  "type": "Feature",
  "properties": {
    "iso:country":"IN",
    "ks:ks_alt_nam":"Amaliyar falia",
    "ks:ks_name":"Amaliyar Falia",
    "ks:ks_pop":291,
    "ks:ks_type":"HABITATION",
    "name:eng_x_preferred":[
        "Amaliyar Falia"
    ],
    "wof:name":"Amaliyar Falia",
    "wof:placetype":"locality",
    "wof:population":291
},
  "geometry": {"coordinates":[74.299694,22.90625],"type":"Point"}
}