{
  "type": "Feature",
  "properties": {
    "iso:country":"IN",
    "ks:ks_name":"Royan Phala",
    "ks:ks_pop":118,
    "ks:ks_type":"VILLAGE",
    "name:eng_x_preferred":[
        "Royan Phala"
    ],
    "wof:name":"Royan Phala",
    "wof:placetype":"locality",
    "wof:population":118
},
  "geometry": {"coordinates":[74.184808,24.38505],"type":"Point"}
}