{
  "type": "Feature",
  "properties": {
    "iso:country":"IN",
    "name:eng_x_preferred":[
        "Sector 93"
    ],
    "qs:gn_local":0,
    "qs:local_max":676,
    "qs:local_sum":2010,
    "qs:localhoods":13,
    "qs:name":"Sector 93",
    "qs:name_adm0":"India",
    "qs:name_adm1":"Uttar Pradesh",
    "qs:name_adm2":"Gautam Buddha Nagar",
    "qs:name_local":"Noida",
    "qs:photo_max":41,
    "qs:photo_sum":103,
    "qs:placetype":"Suburb",
    "qs:quad_count":10,
    "qs:woe_adm0":23424848,
    "qs:woe_adm1":2345760,
    "qs:woe_adm2":12586743,
    "qs:woe_lau":0,
    "qs:woe_local":24505179,
    "qs:woe_ver":"7.10.0",
    "wof:lang":[
        "eng"
    ],
    "wof:name":"Sector 93",
    "wof:placetype":"neighbourhood"
},
  "geometry": {"coordinates":[77.38716100000001,28.521703],"type":"Point"}
}