{
  "type": "Feature",
  "properties": {
    "iso:country":"IN",
    "ks:ks_name":"Longtong No.2",
    "ks:ks_pop":807,
    "ks:ks_type":"VILLAGE",
    "ks:ks_uagg_main":0,
    "name:eng_x_preferred":[
        "Longtong No.2"
    ],
    "wof:name":"Longtong No.2",
    "wof:placetype":"neighbourhood",
    "wof:population":807
},
  "geometry": {"coordinates":[95.850207,27.360553],"type":"Point"}
}