{
  "type": "Feature",
  "properties": {
    "iso:country":"IN",
    "ks:ks_name":"Hare Krishna Para",
    "ks:ks_pop":273,
    "ks:ks_type":"HABITATION",
    "name:eng_x_preferred":[
        "Hare Krishna Para"
    ],
    "wof:name":"Hare Krishna Para",
    "wof:placetype":"locality",
    "wof:population":273
},
  "geometry": {"coordinates":[91.793691,24.146358],"type":"Point"}
}