{
  "type": "Feature",
  "properties": {
    "iso:country":"IN",
    "ks:ks_name":"Nai Basti Plot",
    "ks:ks_pop":281,
    "ks:ks_type":"HABITATION",
    "name:eng_x_preferred":[
        "Nai Basti Plot"
    ],
    "wof:name":"Nai Basti Plot",
    "wof:placetype":"locality",
    "wof:population":281
},
  "geometry": {"coordinates":[84.318414,25.861025],"type":"Point"}
}