{
  "type": "Feature",
  "properties": {
    "gn:admin1_code":"19.0",
    "gn:admin2_code":"583.0",
    "gn:asciiname":"Kalavanhalli",
    "gn:country_code":"IN",
    "gn:dem":891,
    "gn:feature_class":"P",
    "gn:feature_code":"PPL",
    "gn:name":"Kalavanhalli",
    "gn:population":0,
    "gn:timezone":"Asia/Kolkata",
    "iso:country":"IN",
    "wof:name":"Kalavanhalli",
    "wof:placetype":"locality"
},
  "geometry": {"coordinates":[77.29835,13.17499],"type":"Point"}
}