{
  "type": "Feature",
  "properties": {
    "gn:admin1_code":"36",
    "gn:admin2_code":"154.0",
    "gn:asciiname":"Soharia",
    "gn:country_code":"IN",
    "gn:dem":119,
    "gn:feature_class":"P",
    "gn:feature_code":"PPL",
    "gn:name":"Soharia",
    "gn:population":0,
    "gn:timezone":"Asia/Kolkata",
    "iso:country":"IN",
    "wof:name":"Soharia",
    "wof:placetype":"locality"
},
  "geometry": {"coordinates":[81.32704,27.37643],"type":"Point"}
}