{
  "type": "Feature",
  "properties": {
    "gn:admin1_code":"16.0",
    "gn:admin2_code":"508.0",
    "gn:asciiname":"Hindbhatti",
    "gn:country_code":"IN",
    "gn:dem":222,
    "gn:feature_class":"P",
    "gn:feature_code":"PPL",
    "gn:name":"Hindbhatti",
    "gn:population":0,
    "gn:timezone":"Asia/Kolkata",
    "iso:country":"IN",
    "ks:ks_name":"Hinbhatti",
    "ks:ks_pop":193,
    "ks:ks_type":"HABITATION",
    "name:eng_x_preferred":[
        "Hinbhatti"
    ],
    "name:eng_x_variant":[
        "Hindbhatti"
    ],
    "wof:name":"Hinbhatti",
    "wof:placetype":"locality",
    "wof:population":193
},
  "geometry": {"coordinates":[80.61772000000001,19.40247],"type":"Point"}
}