{
  "type": "Feature",
  "properties": {
    "iso:country":"IN",
    "ks:ks_name":"Cherakuri",
    "ks:ks_pop":3898,
    "ks:ks_type":"VILLAGE",
    "ks:ks_uagg_main":0,
    "name:eng_x_preferred":[
        "Cherakuri"
    ],
    "wof:name":"Cherakuri",
    "wof:placetype":"neighbourhood",
    "wof:population":3898
},
  "geometry": {"coordinates":[92.374105,24.862342],"type":"Point"}
}