{
  "type": "Feature",
  "properties": {
    "iso:country":"IN",
    "ks:ks_name":"Mampur",
    "ks:ks_pop":417,
    "ks:ks_type":"VILLAGE",
    "name:eng_x_preferred":[
        "Mampur"
    ],
    "wof:name":"Mampur",
    "wof:placetype":"locality",
    "wof:population":417
},
  "geometry": {"coordinates":[80.529172,25.968946],"type":"Point"}
}