{
  "type": "Feature",
  "properties": {
    "iso:country":"IN",
    "ks:ks_name":"Pure Matadin",
    "ks:ks_pop":60,
    "ks:ks_type":"HABITATION",
    "name:eng_x_preferred":[
        "Pure Matadin"
    ],
    "wof:name":"Pure Matadin",
    "wof:placetype":"locality",
    "wof:population":60
},
  "geometry": {"coordinates":[81.923708,26.214824],"type":"Point"}
}