{
  "type": "Feature",
  "properties": {
    "iso:country":"IN",
    "ks:ks_name":"Lambanithanda",
    "ks:ks_pop":895,
    "ks:ks_type":"HABITATION",
    "name:eng_x_preferred":[
        "Lambanithanda"
    ],
    "wof:name":"Lambanithanda",
    "wof:placetype":"locality",
    "wof:population":895
},
  "geometry": {"coordinates":[77.248169,12.214992],"type":"Point"}
}