{
  "type": "Feature",
  "properties": {
    "iso:country":"IN",
    "ks:ks_name":"Kuanarchatar",
    "ks:ks_pop":697,
    "ks:ks_type":"HABITATION",
    "name:eng_x_preferred":[
        "Kuanarchatar"
    ],
    "wof:name":"Kuanarchatar",
    "wof:placetype":"locality",
    "wof:population":697
},
  "geometry": {"coordinates":[86.672804,20.897314],"type":"Point"}
}