{
  "type": "Feature",
  "properties": {
    "gn:admin1_code":"38.0",
    "gn:admin2_code":"353.0",
    "gn:asciiname":"Suraidih",
    "gn:country_code":"IN",
    "gn:dem":65,
    "gn:feature_class":"P",
    "gn:feature_code":"PPL",
    "gn:name":"Sur\u0101idih",
    "gn:population":0,
    "gn:timezone":"Asia/Kolkata",
    "iso:country":"IN",
    "ks:ks_alt_nam":"Sur\u0101idih",
    "ks:ks_name":"Suraidih",
    "ks:ks_pop":117,
    "ks:ks_type":"VILLAGE",
    "name:eng_x_preferred":[
        "Suraidih"
    ],
    "name:eng_x_variant":[
        "Sur\u0101idih"
    ],
    "wof:name":"Suraidih",
    "wof:placetype":"locality",
    "wof:population":117
},
  "geometry": {"coordinates":[87.74400300000001,24.695572],"type":"Point"}
}