{
  "type": "Feature",
  "properties": {
    "iso:country":"IN",
    "ks:ks_name":"Ajamat Nagar",
    "ks:ks_pop":251,
    "ks:ks_type":"VILLAGE",
    "ks:ks_uagg_main":0,
    "name:eng_x_preferred":[
        "Ajamat Nagar"
    ],
    "wof:name":"Ajamat Nagar",
    "wof:placetype":"neighbourhood",
    "wof:population":251
},
  "geometry": {"coordinates":[80.770612,26.843882],"type":"Point"}
}