{
  "type": "Feature",
  "properties": {
    "iso:country":"IN",
    "ks:ks_name":"Dorka",
    "ks:ks_pop":142,
    "ks:ks_type":"HABITATION",
    "name:eng_x_preferred":[
        "Dorka"
    ],
    "wof:name":"Dorka",
    "wof:placetype":"locality",
    "wof:population":142
},
  "geometry": {"coordinates":[85.41640099999999,22.871859],"type":"Point"}
}