{
  "type": "Feature",
  "properties": {
    "gn:admin1_code":"35.0",
    "gn:admin2_code":"455.0",
    "gn:asciiname":"Dip",
    "gn:country_code":"IN",
    "gn:dem":601,
    "gn:feature_class":"P",
    "gn:feature_code":"PPL",
    "gn:name":"D\u012bp",
    "gn:population":0,
    "gn:timezone":"Asia/Kolkata",
    "iso:country":"IN",
    "name:cat_x_preferred":[
        "DIP"
    ],
    "name:ceb_x_preferred":[
        "Dip"
    ],
    "name:hrv_x_preferred":[
        "DIP"
    ],
    "name:spa_x_preferred":[
        "Dip"
    ],
    "wof:name":"Dip",
    "wof:placetype":"locality"
},
  "geometry": {"coordinates":[78.59438,22.01397],"type":"Point"}
}