{
  "type": "Feature",
  "properties": {
    "iso:country":"IN",
    "ks:ks_name":"Daldali",
    "ks:ks_pop":222,
    "ks:ks_type":"HABITATION",
    "name:eng_x_preferred":[
        "Daldali"
    ],
    "wof:name":"Daldali",
    "wof:placetype":"locality",
    "wof:population":222
},
  "geometry": {"coordinates":[89.90734999999999,26.258139],"type":"Point"}
}