{
  "type": "Feature",
  "properties": {
    "iso:country":"IN",
    "ks:ks_name":"Haldavade",
    "ks:ks_pop":944,
    "ks:ks_type":"VILLAGE",
    "ks:ks_uagg_main":0,
    "name:eng_x_preferred":[
        "Haldavade"
    ],
    "wof:name":"Haldavade",
    "wof:placetype":"neighbourhood",
    "wof:population":944
},
  "geometry": {"coordinates":[74.234464,16.366661],"type":"Point"}
}