{
  "type": "Feature",
  "properties": {
    "iso:country":"IN",
    "ks:ks_name":"Kafali",
    "ks:ks_pop":13,
    "ks:ks_type":"VILLAGE",
    "name:eng_x_preferred":[
        "Kafali"
    ],
    "wof:name":"Kafali",
    "wof:placetype":"locality",
    "wof:population":13
},
  "geometry": {"coordinates":[79.830155,29.352125],"type":"Point"}
}