{
  "type": "Feature",
  "properties": {
    "iso:country":"IN",
    "ks:ks_name":"Sansingaria",
    "ks:ks_pop":272,
    "ks:ks_type":"VILLAGE",
    "name:eng_x_preferred":[
        "Sansingaria"
    ],
    "wof:name":"Sansingaria",
    "wof:placetype":"locality",
    "wof:population":272
},
  "geometry": {"coordinates":[86.544281,21.629707],"type":"Point"}
}