{
  "type": "Feature",
  "properties": {
    "gn:admin1_code":"11",
    "gn:admin2_code":"23.0",
    "gn:asciiname":"Naini Got",
    "gn:country_code":"IN",
    "gn:dem":3461,
    "gn:feature_class":"P",
    "gn:feature_code":"PPL",
    "gn:name":"Naini Got",
    "gn:population":0,
    "gn:timezone":"Asia/Kolkata",
    "iso:country":"IN",
    "wof:name":"Naini Got",
    "wof:placetype":"locality"
},
  "geometry": {"coordinates":[76.44786999999999,33.06294],"type":"Point"}
}