{
  "type": "Feature",
  "properties": {
    "gn:admin1_code":"35.0",
    "gn:admin2_code":"446.0",
    "gn:asciiname":"Bersala",
    "gn:country_code":"IN",
    "gn:dem":337,
    "gn:feature_class":"P",
    "gn:feature_code":"PPL",
    "gn:name":"Bersala",
    "gn:population":0,
    "gn:timezone":"Asia/Kolkata",
    "iso:country":"IN",
    "wof:name":"Bersala",
    "wof:placetype":"locality"
},
  "geometry": {"coordinates":[78.41461,23.14509],"type":"Point"}
}