{
  "type": "Feature",
  "properties": {
    "gn:admin1_code":"12",
    "gn:admin2_code":"15.0",
    "gn:asciiname":"Bargur",
    "gn:country_code":"IN",
    "gn:dem":2969,
    "gn:feature_class":"P",
    "gn:feature_code":"PPL",
    "gn:name":"Bargur",
    "gn:population":0,
    "gn:timezone":"Asia/Kolkata",
    "iso:country":"IN",
    "name:bpy_x_preferred":[
        "\u09ac\u09be\u09b0\u0997\u09c1\u09b0"
    ],
    "name:ceb_x_preferred":[
        "Barg\u016bru"
    ],
    "name:ita_x_preferred":[
        "Bargur"
    ],
    "name:msa_x_preferred":[
        "Bargur"
    ],
    "name:new_x_preferred":[
        "\u092c\u0930\u0917\u0941\u0930"
    ],
    "name:nld_x_preferred":[
        "Bargur"
    ],
    "name:por_x_preferred":[
        "Bargur"
    ],
    "name:swe_x_preferred":[
        "Barg\u016bru"
    ],
    "name:tam_x_preferred":[
        "\u0baa\u0bb0\u0bcd\u0b95\u0bc2\u0bb0\u0bcd"
    ],
    "name:vie_x_preferred":[
        "Bargur"
    ],
    "name:zho_x_preferred":[
        "\u5df4\u5c14\u53e4\u5c14"
    ],
    "wof:name":"Bargur",
    "wof:placetype":"locality"
},
  "geometry": {"coordinates":[74.90309999999999,33.55413],"type":"Point"}
}