{
  "type": "Feature",
  "properties": {
    "iso:country":"IN",
    "ks:ks_name":"Dumartoli",
    "ks:ks_pop":277,
    "ks:ks_type":"HABITATION",
    "ks:ks_uagg_main":0,
    "name:eng_x_preferred":[
        "Dumartoli"
    ],
    "wof:name":"Dumartoli",
    "wof:placetype":"neighbourhood",
    "wof:population":277
},
  "geometry": {"coordinates":[84.15246399999999,22.672909],"type":"Point"}
}