{
  "type": "Feature",
  "properties": {
    "gn:admin1_code":"24.0",
    "gn:admin2_code":"123.0",
    "gn:asciiname":"Ballan ka Khera",
    "gn:country_code":"IN",
    "gn:dem":595,
    "gn:feature_class":"P",
    "gn:feature_code":"PPL",
    "gn:name":"Ballan ka Khera",
    "gn:population":0,
    "gn:timezone":"Asia/Kolkata",
    "iso:country":"IN",
    "wof:name":"Ballan ka Khera",
    "wof:placetype":"locality"
},
  "geometry": {"coordinates":[73.98801999999998,25.32343],"type":"Point"}
}