{
  "type": "Feature",
  "properties": {
    "iso:country":"IN",
    "ks:ks_name":"Umrod Dewas",
    "ks:ks_pop":908,
    "ks:ks_type":"VILLAGE",
    "name:eng_x_preferred":[
        "Umrod Dewas"
    ],
    "wof:name":"Umrod Dewas",
    "wof:placetype":"locality",
    "wof:population":908
},
  "geometry": {"coordinates":[76.475801,23.195679],"type":"Point"}
}