{
  "type": "Feature",
  "properties": {
    "gn:admin1_code":"16.0",
    "gn:admin2_code":"502.0",
    "gn:asciiname":"Warla",
    "gn:country_code":"IN",
    "gn:dem":499,
    "gn:feature_class":"P",
    "gn:feature_code":"PPL",
    "gn:name":"W\u0101rla",
    "gn:population":0,
    "gn:timezone":"Asia/Kolkata",
    "iso:country":"IN",
    "name:ceb_x_preferred":[
        "Warla"
    ],
    "name:swe_x_preferred":[
        "Warla"
    ],
    "wof:name":"Warla",
    "wof:placetype":"locality"
},
  "geometry": {"coordinates":[77.26108000000001,19.99342],"type":"Point"}
}