{
  "type": "Feature",
  "properties": {
    "gn:admin1_code":"36.0",
    "gn:admin2_code":"193.0",
    "gn:asciiname":"Nasirabad",
    "gn:country_code":"IN",
    "gn:dem":67,
    "gn:feature_class":"P",
    "gn:feature_code":"PPL",
    "gn:name":"Nas\u012br\u0101b\u0101d",
    "gn:population":0,
    "gn:timezone":"Asia/Kolkata",
    "iso:country":"IN",
    "ks:ks_name":"Nasirabad",
    "ks:ks_pop":2277,
    "ks:ks_type":"HABITATION",
    "name:ceb_x_preferred":[
        "Nasirabad"
    ],
    "name:eng_x_preferred":[
        "Nasirabad"
    ],
    "name:fas_x_preferred":[
        "\u0646\u0635\u06cc\u0631\u0622\u0628\u0627\u062f"
    ],
    "name:mzn_x_preferred":[
        "\u0646\u0635\u06cc\u0631\u0622\u0628\u0627\u062f"
    ],
    "name:swe_x_preferred":[
        "Nasirabad"
    ],
    "wof:name":"Nasirabad",
    "wof:placetype":"locality",
    "wof:population":2277
},
  "geometry": {"coordinates":[84.105695,25.7513],"type":"Point"}
}