{
  "type": "Feature",
  "properties": {
    "gn:admin1_code":"19",
    "gn:admin2_code":"580.0",
    "gn:asciiname":"Vandaganur",
    "gn:country_code":"IN",
    "gn:dem":489,
    "gn:feature_class":"P",
    "gn:feature_code":"PPL",
    "gn:name":"Vandagan\u016br",
    "gn:population":0,
    "gn:timezone":"Asia/Kolkata",
    "iso:country":"IN",
    "wof:name":"Vandaganur",
    "wof:placetype":"locality"
},
  "geometry": {"coordinates":[76.44011999999999,16.70433],"type":"Point"}
}