{
  "type": "Feature",
  "properties": {
    "gn:admin1_code":"9",
    "gn:admin2_code":"485.0",
    "gn:asciiname":"Jhab",
    "gn:country_code":"IN",
    "gn:dem":227,
    "gn:feature_class":"P",
    "gn:feature_code":"PPL",
    "gn:name":"Jh\u0101b",
    "gn:population":0,
    "gn:timezone":"Asia/Kolkata",
    "iso:country":"IN",
    "ks:ks_alt_nam":"Jh\u0101b",
    "ks:ks_name":"Jhab",
    "ks:ks_pop":1061,
    "ks:ks_type":"VILLAGE",
    "name:eng_x_preferred":[
        "Jhab"
    ],
    "name:eng_x_variant":[
        "Jh\u0101b"
    ],
    "wof:name":"Jhab",
    "wof:placetype":"locality",
    "wof:population":1061
},
  "geometry": {"coordinates":[74.076735,23.122945],"type":"Point"}
}