{
  "type": "Feature",
  "properties": {
    "iso:country":"IN",
    "ks:ks_alt_nam":"vadugakudi",
    "ks:ks_name":"Vadugakudi",
    "ks:ks_pop":268,
    "ks:ks_type":"HABITATION",
    "name:eng_x_preferred":[
        "Vadugakudi"
    ],
    "wof:name":"Vadugakudi",
    "wof:placetype":"locality",
    "wof:population":268
},
  "geometry": {"coordinates":[79.568882,10.748925],"type":"Point"}
}