{
  "type": "Feature",
  "properties": {
    "gn:admin1_code":"2.0",
    "gn:admin2_code":"549.0",
    "gn:asciiname":"Pulipadu",
    "gn:country_code":"IN",
    "gn:dem":91,
    "gn:feature_class":"P",
    "gn:feature_code":"PPL",
    "gn:name":"Pulip\u0101du",
    "gn:population":0,
    "gn:timezone":"Asia/Kolkata",
    "iso:country":"IN",
    "name:tel_x_preferred":[
        "\u0c2a\u0c41\u0c32\u0c3f\u0c2a\u0c3e\u0c21\u0c41"
    ],
    "wof:name":"Pulipadu",
    "wof:placetype":"locality"
},
  "geometry": {"coordinates":[79.71141999999998,15.78491],"type":"Point"}
}