{
  "type": "Feature",
  "properties": {
    "gn:admin1_code":"39",
    "gn:admin2_code":"61.0",
    "gn:asciiname":"Bhairgaon",
    "gn:country_code":"IN",
    "gn:dem":1361,
    "gn:feature_class":"P",
    "gn:feature_code":"PPL",
    "gn:name":"Bhairgaon",
    "gn:population":0,
    "gn:timezone":"Asia/Kolkata",
    "iso:country":"IN",
    "ks:ks_name":"Bhairgaon",
    "ks:ks_type":"VILLAGE",
    "name:eng_x_preferred":[
        "Bhairgaon"
    ],
    "wof:name":"Bhairgaon",
    "wof:placetype":"locality"
},
  "geometry": {"coordinates":[78.797883,29.7704],"type":"Point"}
}