{
  "type": "Feature",
  "properties": {
    "gn:admin1_code":"36",
    "gn:admin2_code":"191.0",
    "gn:asciiname":"Purwa Garia",
    "gn:country_code":"IN",
    "gn:dem":81,
    "gn:feature_class":"P",
    "gn:feature_code":"PPL",
    "gn:name":"Purwa Garia",
    "gn:population":0,
    "gn:timezone":"Asia/Kolkata",
    "iso:country":"IN",
    "wof:name":"Purwa Garia",
    "wof:placetype":"locality"
},
  "geometry": {"coordinates":[83.20551999999998,26.09428],"type":"Point"}
}