{
  "type": "Feature",
  "properties": {
    "iso:country":"IN",
    "ks:ks_name":"Pipalva",
    "ks:ks_pop":317,
    "ks:ks_type":"VILLAGE",
    "ks:ks_uagg_main":0,
    "name:eng_x_preferred":[
        "Pipalva"
    ],
    "wof:name":"Pipalva",
    "wof:placetype":"neighbourhood",
    "wof:population":317
},
  "geometry": {"coordinates":[71.572444,21.606222],"type":"Point"}
}