{
  "type": "Feature",
  "properties": {
    "gn:admin1_code":"21",
    "gn:admin2_code":"397.0",
    "gn:asciiname":"Kaniki",
    "gn:country_code":"IN",
    "gn:dem":611,
    "gn:feature_class":"P",
    "gn:feature_code":"PPL",
    "gn:name":"Kaniki",
    "gn:population":0,
    "gn:timezone":"Asia/Kolkata",
    "iso:country":"IN",
    "wof:name":"Kaniki",
    "wof:placetype":"locality"
},
  "geometry": {"coordinates":[82.12886,19.44749],"type":"Point"}
}