{
  "type": "Feature",
  "properties": {
    "iso:country":"IN",
    "ks:ks_name":"Ollabhali",
    "ks:ks_pop":123,
    "ks:ks_type":"HABITATION",
    "name:eng_x_preferred":[
        "Ollabhali"
    ],
    "wof:name":"Ollabhali",
    "wof:placetype":"locality",
    "wof:population":123
},
  "geometry": {"coordinates":[83.08051,19.796506],"type":"Point"}
}