{
  "type": "Feature",
  "properties": {
    "iso:country":"IN",
    "ks:ks_alt_nam":"jamdih bhelwadih",
    "ks:ks_name":"Jamdih Bhelwadih",
    "ks:ks_pop":353,
    "ks:ks_type":"HABITATION",
    "name:eng_x_preferred":[
        "Jamdih Bhelwadih"
    ],
    "wof:name":"Jamdih Bhelwadih",
    "wof:placetype":"locality",
    "wof:population":353
},
  "geometry": {"coordinates":[83.646455,23.578794],"type":"Point"}
}