{
  "type": "Feature",
  "properties": {
    "iso:country":"IN",
    "ks:ks_name":"Asuba",
    "ks:ks_pop":1004,
    "ks:ks_type":"VILLAGE",
    "name:eng_x_preferred":[
        "Asuba"
    ],
    "wof:name":"Asuba",
    "wof:placetype":"locality",
    "wof:population":1004
},
  "geometry": {"coordinates":[81.616258,26.947401],"type":"Point"}
}