{
  "type": "Feature",
  "properties": {
    "iso:country":"IN",
    "ks:ks_name":"Subhashpura",
    "ks:ks_pop":742,
    "ks:ks_type":"VILLAGE",
    "name:eng_x_preferred":[
        "Subhashpura"
    ],
    "wof:name":"Subhashpura",
    "wof:placetype":"locality",
    "wof:population":742
},
  "geometry": {"coordinates":[73.663094,27.45496],"type":"Point"}
}