{
  "type": "Feature",
  "properties": {
    "iso:country":"IN",
    "ks:ks_name":"Ramanujapalle",
    "ks:ks_pop":468,
    "ks:ks_type":"VILLAGE",
    "ks:ks_uagg_main":0,
    "name:eng_x_preferred":[
        "Ramanujapalle"
    ],
    "wof:name":"Ramanujapalle",
    "wof:placetype":"neighbourhood",
    "wof:population":468
},
  "geometry": {"coordinates":[79.390562,13.598384],"type":"Point"}
}