{
  "type": "Feature",
  "properties": {
    "iso:country":"IN",
    "ks:ks_name":"Lakshmipur",
    "ks:ks_pop":956,
    "ks:ks_type":"VILLAGE",
    "name:eng_x_preferred":[
        "Lakshmipur"
    ],
    "wof:name":"Lakshmipur",
    "wof:placetype":"locality",
    "wof:population":956
},
  "geometry": {"coordinates":[88.766649,25.315037],"type":"Point"}
}