{
  "type": "Feature",
  "properties": {
    "gn:admin1_code":"35.0",
    "gn:admin2_code":"424",
    "gn:asciiname":"Parsua",
    "gn:country_code":"IN",
    "gn:dem":330,
    "gn:feature_class":"P",
    "gn:feature_code":"PPL",
    "gn:name":"Parsua",
    "gn:population":0,
    "gn:timezone":"Asia/Kolkata",
    "iso:country":"IN",
    "name:und_x_variant":[
        "Parsawan",
        "Parsua",
        "Parsaw\u0101n"
    ],
    "wof:name":"Parsua",
    "wof:placetype":"locality"
},
  "geometry": {"coordinates":[78.96136,24.74374],"type":"Point"}
}