{
  "type": "Feature",
  "properties": {
    "gn:admin1_code":"2.0",
    "gn:admin2_code":"550.0",
    "gn:asciiname":"Basavapalem",
    "gn:country_code":"IN",
    "gn:dem":17,
    "gn:feature_class":"P",
    "gn:feature_code":"PPL",
    "gn:name":"Basavap\u0101lem",
    "gn:population":0,
    "gn:timezone":"Asia/Kolkata",
    "iso:country":"IN",
    "ks:ks_name":"Basavaipalem",
    "ks:ks_pop":421,
    "ks:ks_type":"HABITATION",
    "name:eng_x_preferred":[
        "Basavaipalem"
    ],
    "name:eng_x_variant":[
        "Basavapalem"
    ],
    "wof:name":"Basavaipalem",
    "wof:placetype":"locality",
    "wof:population":421
},
  "geometry": {"coordinates":[80.014652,14.59161],"type":"Point"}
}