{
  "type": "Feature",
  "properties": {
    "gn:admin1_code":"2.0",
    "gn:admin2_code":"553.0",
    "gn:asciiname":"Khairevu",
    "gn:country_code":"IN",
    "gn:dem":567,
    "gn:feature_class":"P",
    "gn:feature_code":"PPL",
    "gn:name":"Khairevu",
    "gn:population":0,
    "gn:timezone":"Asia/Kolkata",
    "iso:country":"IN",
    "wof:name":"Khairevu",
    "wof:placetype":"locality"
},
  "geometry": {"coordinates":[77.03288000000001,14.42421],"type":"Point"}
}