{
  "type": "Feature",
  "properties": {
    "iso:country":"IN",
    "ks:ks_name":"Temla",
    "ks:ks_pop":1740,
    "ks:ks_type":"VILLAGE",
    "name:eng_x_preferred":[
        "Temla"
    ],
    "wof:name":"Temla",
    "wof:placetype":"locality",
    "wof:population":1740
},
  "geometry": {"coordinates":[75.333063,22.014952],"type":"Point"}
}