{
  "type": "Feature",
  "properties": {
    "gn:admin1_code":"34.0",
    "gn:admin2_code":"215.0",
    "gn:asciiname":"Bihata",
    "gn:country_code":"IN",
    "gn:dem":57,
    "gn:feature_class":"P",
    "gn:feature_code":"PPL",
    "gn:name":"Bihata",
    "gn:population":0,
    "gn:timezone":"Asia/Kolkata",
    "iso:country":"IN",
    "ks:ks_name":"Bihta",
    "ks:ks_pop":1586,
    "ks:ks_type":"VILLAGE",
    "name:eng_x_preferred":[
        "Bihta"
    ],
    "name:eng_x_variant":[
        "Bihata"
    ],
    "wof:name":"Bihta",
    "wof:placetype":"locality",
    "wof:population":1586
},
  "geometry": {"coordinates":[86.06516999999999,26.193667],"type":"Point"}
}