{
  "type": "Feature",
  "properties": {
    "iso:country":"IN",
    "ks:ks_name":"Kuligadde",
    "ks:ks_pop":35,
    "ks:ks_type":"HABITATION",
    "name:eng_x_preferred":[
        "Kuligadde"
    ],
    "wof:name":"Kuligadde",
    "wof:placetype":"locality",
    "wof:population":35
},
  "geometry": {"coordinates":[74.658446,14.636856],"type":"Point"}
}