{
  "type": "Feature",
  "properties": {
    "gn:admin1_code":"16",
    "gn:admin2_code":"508.0",
    "gn:asciiname":"Markakasa",
    "gn:country_code":"IN",
    "gn:dem":366,
    "gn:feature_class":"P",
    "gn:feature_code":"PPL",
    "gn:name":"Mark\u0101kasa",
    "gn:population":0,
    "gn:timezone":"Asia/Kolkata",
    "iso:country":"IN",
    "ks:ks_name":"Markekasa",
    "ks:ks_pop":188,
    "ks:ks_type":"VILLAGE",
    "name:eng_x_preferred":[
        "Markekasa"
    ],
    "name:eng_x_variant":[
        "Markakasa"
    ],
    "wof:name":"Markekasa",
    "wof:placetype":"locality",
    "wof:population":188
},
  "geometry": {"coordinates":[80.51717499999999,20.772173],"type":"Point"}
}