{
  "type": "Feature",
  "properties": {
    "iso:country":"IN",
    "ks:ks_name":"Daaban",
    "ks:ks_pop":92,
    "ks:ks_type":"HABITATION",
    "name:eng_x_preferred":[
        "Daaban"
    ],
    "wof:name":"Daaban",
    "wof:placetype":"locality",
    "wof:population":92
},
  "geometry": {"coordinates":[74.252258,14.840815],"type":"Point"}
}