{
  "type": "Feature",
  "properties": {
    "iso:country":"IN",
    "ks:ks_name":"Gadadhar",
    "ks:ks_pop":185,
    "ks:ks_type":"HABITATION",
    "name:eng_x_preferred":[
        "Gadadhar"
    ],
    "wof:name":"Gadadhar",
    "wof:placetype":"locality",
    "wof:population":185
},
  "geometry": {"coordinates":[91.68847100000001,23.668553],"type":"Point"}
}