{
  "type": "Feature",
  "properties": {
    "gn:country":"IN",
    "gn:fcode":"PPL",
    "gn:population":15778,
    "iso:country":"IN",
    "name:anp_x_preferred":[
        "\u0921\u0941\u092e\u0930\u093e"
    ],
    "name:ben_x_preferred":[
        "\u09a6\u09c1\u09ae\u09b0\u09be"
    ],
    "name:bpy_x_preferred":[
        "\u09a6\u09c1\u09ae\u09b0\u09be"
    ],
    "name:ceb_x_preferred":[
        "Dumra"
    ],
    "name:eng_x_preferred":[
        "Dumra"
    ],
    "name:hif_x_preferred":[
        "Dumra"
    ],
    "name:hin_x_preferred":[
        "\u0921\u0941\u092e\u0930\u093e"
    ],
    "name:ita_x_preferred":[
        "Dumra"
    ],
    "name:msa_x_preferred":[
        "Dumra"
    ],
    "name:nan_x_preferred":[
        "Dumra"
    ],
    "name:new_x_preferred":[
        "\u0926\u092e\u094d\u0930\u093e"
    ],
    "name:nld_x_preferred":[
        "Dumra"
    ],
    "name:por_x_preferred":[
        "Dumra"
    ],
    "name:sat_x_preferred":[
        "\u1c70\u1c69\u1c62\u1c68\u1c5f"
    ],
    "name:spa_x_preferred":[
        "Dumra"
    ],
    "name:swe_x_preferred":[
        "Dumra"
    ],
    "name:tam_x_preferred":[
        "\u0ba4\u0bc1\u0bae\u0bcd\u0bb0\u0bbe"
    ],
    "name:vie_x_preferred":[
        "Dumra"
    ],
    "name:zho_x_preferred":[
        "\u675c\u59c6\u62c9"
    ],
    "qs:name":"Dumri",
    "qs:name_adm0":"India",
    "qs:name_adm1":"Bihar",
    "qs:photos_9r":0,
    "qs:photos_sr":0,
    "qs:placetype":"Town",
    "qs:pop_sr":"6",
    "wd:wordcount":40,
    "wof:name":"Dumri",
    "wof:placetype":"neighbourhood",
    "wof:population":15778
},
  "geometry": {"coordinates":[85.5204,26.56708],"type":"Point"}
}