{
  "type": "Feature",
  "properties": {
    "iso:country":"IN",
    "ks:ks_name":"Chalupia",
    "ks:ks_pop":140,
    "ks:ks_type":"HABITATION",
    "name:eng_x_preferred":[
        "Chalupia"
    ],
    "wof:name":"Chalupia",
    "wof:placetype":"locality",
    "wof:population":140
},
  "geometry": {"coordinates":[83.24588799999999,20.035219],"type":"Point"}
}