{
  "type": "Feature",
  "properties": {
    "iso:country":"IN",
    "ks:ks_name":"Yedlonibavi",
    "ks:ks_pop":39,
    "ks:ks_type":"HABITATION",
    "name:eng_x_preferred":[
        "Yedlonibavi"
    ],
    "wof:name":"Yedlonibavi",
    "wof:placetype":"locality",
    "wof:population":39
},
  "geometry": {"coordinates":[79.17799599999999,17.41845],"type":"Point"}
}