{
  "type": "Feature",
  "properties": {
    "iso:country":"IN",
    "ks:ks_alt_nam":"CHHOTI JAINI PURWA",
    "ks:ks_name":"Chhoti Jaini Purwa",
    "ks:ks_pop":63,
    "ks:ks_type":"HABITATION",
    "ks:ks_uagg_main":0,
    "name:eng_x_preferred":[
        "Chhoti Jaini Purwa"
    ],
    "wof:name":"Chhoti Jaini Purwa",
    "wof:placetype":"neighbourhood",
    "wof:population":63
},
  "geometry": {"coordinates":[81.611895,27.3758],"type":"Point"}
}