{
  "type": "Feature",
  "properties": {
    "gn:admin1_code":"36",
    "gn:admin2_code":"187.0",
    "gn:asciiname":"Shiubakhsh Chak",
    "gn:country_code":"IN",
    "gn:dem":88,
    "gn:feature_class":"P",
    "gn:feature_code":"PPL",
    "gn:name":"Shiubakhsh Chak",
    "gn:population":0,
    "gn:timezone":"Asia/Kolkata",
    "iso:country":"IN",
    "wof:name":"Shiubakhsh Chak",
    "wof:placetype":"neighbourhood"
},
  "geometry": {"coordinates":[83.18743000000001,27.21513],"type":"Point"}
}