{
  "type": "Feature",
  "properties": {
    "gn:admin1_code":"12.0",
    "gn:admin2_code":"9.0",
    "gn:asciiname":"Khaiyar",
    "gn:country_code":"IN",
    "gn:dem":1690,
    "gn:feature_class":"P",
    "gn:feature_code":"PPL",
    "gn:name":"Khaiy\u0101r",
    "gn:population":0,
    "gn:timezone":"Asia/Kolkata",
    "iso:country":"IN",
    "name:eng_x_preferred":[
        "Khaiy\u0101r"
    ],
    "wof:name":"Khaiyar",
    "wof:placetype":"locality"
},
  "geometry": {"coordinates":[74.64018,34.44824000000001],"type":"Point"}
}