{
  "type": "Feature",
  "properties": {
    "iso:country":"IN",
    "ks:ks_name":"Yadtremanevatara",
    "ks:ks_pop":363,
    "ks:ks_type":"HABITATION",
    "name:eng_x_preferred":[
        "Yadtremanevatara"
    ],
    "wof:name":"Yadtremanevatara",
    "wof:placetype":"locality",
    "wof:population":363
},
  "geometry": {"coordinates":[74.63336,13.858905],"type":"Point"}
}