{
  "type": "Feature",
  "properties": {
    "iso:country":"IN",
    "ks:ks_name":"Magha Toa",
    "ks:ks_pop":675,
    "ks:ks_type":"HABITATION",
    "ks:ks_uagg_main":0,
    "name:eng_x_preferred":[
        "Magha Toa"
    ],
    "wof:name":"Magha Toa",
    "wof:placetype":"neighbourhood",
    "wof:population":675
},
  "geometry": {"coordinates":[83.643677,26.591976],"type":"Point"}
}