{
  "type": "Feature",
  "properties": {
    "iso:country":"IN",
    "ks:ks_name":"Araji Gaura Raja",
    "ks:ks_pop":0,
    "ks:ks_type":"VILLAGE",
    "name:eng_x_preferred":[
        "Araji Gaura Raja"
    ],
    "wof:name":"Araji Gaura Raja",
    "wof:placetype":"locality",
    "wof:population":0
},
  "geometry": {"coordinates":[82.67457,25.076783],"type":"Point"}
}