{
  "type": "Feature",
  "properties": {
    "iso:country":"IN",
    "ks:ks_name":"Ramnagar",
    "ks:ks_pop":719,
    "ks:ks_type":"VILLAGE",
    "name:eng_x_preferred":[
        "Ramnagar"
    ],
    "wof:name":"Ramnagar",
    "wof:placetype":"locality",
    "wof:population":719
},
  "geometry": {"coordinates":[75.002144,25.307294],"type":"Point"}
}