{
  "type": "Feature",
  "properties": {
    "iso:country":"IN",
    "ks:ks_name":"Tipabadour",
    "ks:ks_pop":390,
    "ks:ks_type":"VILLAGE",
    "name:eng_x_preferred":[
        "Tipabadour"
    ],
    "wof:name":"Tipabadour",
    "wof:placetype":"locality",
    "wof:population":390
},
  "geometry": {"coordinates":[81.792929,24.554618],"type":"Point"}
}