{
  "type": "Feature",
  "properties": {
    "gn:admin1_code":"19.0",
    "gn:admin2_code":"568.0",
    "gn:asciiname":"Dinda",
    "gn:country_code":"IN",
    "gn:dem":652,
    "gn:feature_class":"P",
    "gn:feature_code":"PPL",
    "gn:name":"Dinda",
    "gn:population":0,
    "gn:timezone":"Asia/Kolkata",
    "iso:country":"IN",
    "ks:ks_name":"Dinda",
    "ks:ks_pop":22,
    "ks:ks_type":"HABITATION",
    "name:eng_x_preferred":[
        "Dinda"
    ],
    "name:tgk_x_preferred":[
        "\u0414\u0438\u043d\u0434\u0430"
    ],
    "wof:name":"Dinda",
    "wof:placetype":"locality",
    "wof:population":22
},
  "geometry": {"coordinates":[75.137039,13.662915],"type":"Point"}
}