{
  "type": "Feature",
  "properties": {
    "gn:admin1_code":"19.0",
    "gn:admin2_code":"568.0",
    "gn:asciiname":"Dinda",
    "gn:country_code":"IN",
    "gn:dem":652,
    "gn:feature_class":"P",
    "gn:feature_code":"PPL",
    "gn:name":"Dinda",
    "gn:population":0,
    "gn:timezone":"Asia/Kolkata",
    "iso:country":"IN",
    "name:tgk_x_preferred":[
        "\u0414\u0438\u043d\u0434\u0430"
    ],
    "wof:name":"Dinda",
    "wof:placetype":"locality"
},
  "geometry": {"coordinates":[75.13760000000001,13.65954],"type":"Point"}
}