{
  "type": "Feature",
  "properties": {
    "iso:country":"IN",
    "ks:ks_name":"Bachakarwasti",
    "ks:ks_pop":142,
    "ks:ks_type":"HABITATION",
    "name:eng_x_preferred":[
        "Bachakarwasti"
    ],
    "wof:name":"Bachakarwasti",
    "wof:placetype":"locality",
    "wof:population":142
},
  "geometry": {"coordinates":[74.696479,19.375303],"type":"Point"}
}