{
  "type": "Feature",
  "properties": {
    "iso:country":"IN",
    "ks:ks_alt_nam":"Bhawardh\u0101",
    "ks:ks_name":"Bhawardha",
    "ks:ks_type":"VILLAGE",
    "name:eng_x_preferred":[
        "Bhawardha"
    ],
    "name:eng_x_variant":[
        "Bhawardh\u0101"
    ],
    "wof:name":"Bhawardha",
    "wof:placetype":"locality"
},
  "geometry": {"coordinates":[75.981323,22.160701],"type":"Point"}
}