{
  "type": "Feature",
  "properties": {
    "iso:country":"IN",
    "ks:ks_name":"Uthirambakkam",
    "ks:ks_pop":113,
    "ks:ks_type":"VILLAGE",
    "name:eng_x_preferred":[
        "Uthirambakkam"
    ],
    "wof:name":"Uthirambakkam",
    "wof:placetype":"locality",
    "wof:population":113
},
  "geometry": {"coordinates":[79.836026,12.991892],"type":"Point"}
}