{
  "type": "Feature",
  "properties": {
    "iso:country":"IN",
    "ks:ks_name":"Dia Rajagarh",
    "ks:ks_pop":396,
    "ks:ks_type":"VILLAGE",
    "ks:ks_uagg_main":0,
    "name:eng_x_preferred":[
        "Dia Rajagarh"
    ],
    "wof:name":"Dia Rajagarh",
    "wof:placetype":"neighbourhood",
    "wof:population":396
},
  "geometry": {"coordinates":[86.548497,20.454266],"type":"Point"}
}