{
  "type": "Feature",
  "properties": {
    "iso:country":"IN",
    "ks:ks_alt_nam":"AFREMPUR",
    "ks:ks_name":"Afrempur",
    "ks:ks_pop":224,
    "ks:ks_type":"HABITATION",
    "name:eng_x_preferred":[
        "Afrempur"
    ],
    "wof:name":"Afrempur",
    "wof:placetype":"locality",
    "wof:population":224
},
  "geometry": {"coordinates":[83.84234600000001,22.772058],"type":"Point"}
}