{
  "type": "Feature",
  "properties": {
    "iso:country":"IN",
    "ks:ks_name":"Pagadewadi",
    "ks:ks_pop":149,
    "ks:ks_type":"HABITATION",
    "name:eng_x_preferred":[
        "Pagadewadi"
    ],
    "wof:name":"Pagadewadi",
    "wof:placetype":"locality",
    "wof:population":149
},
  "geometry": {"coordinates":[73.21388899999999,17.486667],"type":"Point"}
}