{
  "type": "Feature",
  "properties": {
    "iso:country":"IN",
    "ks:ks_name":"Begundighi",
    "ks:ks_pop":2358,
    "ks:ks_type":"HABITATION",
    "name:eng_x_preferred":[
        "Begundighi"
    ],
    "wof:name":"Begundighi",
    "wof:placetype":"locality",
    "wof:population":2358
},
  "geometry": {"coordinates":[88.43015699999999,24.290446],"type":"Point"}
}