{
  "type": "Feature",
  "properties": {
    "gn:admin1_code":"11",
    "gn:admin2_code":"27.0",
    "gn:asciiname":"Serli Batahi",
    "gn:country_code":"IN",
    "gn:dem":1496,
    "gn:feature_class":"P",
    "gn:feature_code":"PPL",
    "gn:name":"Serli Bat\u0101hi",
    "gn:population":0,
    "gn:timezone":"Asia/Kolkata",
    "iso:country":"IN",
    "wof:name":"Serli Batahi",
    "wof:placetype":"locality"
},
  "geometry": {"coordinates":[76.80492,31.60783],"type":"Point"}
}