{
  "type": "Feature",
  "properties": {
    "iso:country":"IN",
    "ks:ks_name":"Gawkhera",
    "ks:ks_pop":63,
    "ks:ks_type":"HABITATION",
    "name:eng_x_preferred":[
        "Gawkhera"
    ],
    "wof:name":"Gawkhera",
    "wof:placetype":"locality",
    "wof:population":63
},
  "geometry": {"coordinates":[78.829499,29.926106],"type":"Point"}
}