{
  "type": "Feature",
  "properties": {
    "iso:country":"IN",
    "ks:ks_name":"Pura Natha",
    "ks:ks_pop":1450,
    "ks:ks_type":"HABITATION",
    "name:eng_x_preferred":[
        "Pura Natha"
    ],
    "wof:name":"Pura Natha",
    "wof:placetype":"locality",
    "wof:population":1450
},
  "geometry": {"coordinates":[78.35192600000001,26.92435],"type":"Point"}
}