{
  "type": "Feature",
  "properties": {
    "iso:country":"IN",
    "ks:ks_name":"Malahalli",
    "ks:ks_pop":385,
    "ks:ks_type":"HABITATION",
    "name:eng_x_preferred":[
        "Malahalli"
    ],
    "wof:name":"Malahalli",
    "wof:placetype":"locality",
    "wof:population":385
},
  "geometry": {"coordinates":[75.52446999999999,13.13475],"type":"Point"}
}