{
  "type": "Feature",
  "properties": {
    "iso:country":"IN",
    "ks:ks_name":"Bhanrankula",
    "ks:ks_pop":946,
    "ks:ks_type":"VILLAGE",
    "ks:ks_uagg_main":0,
    "name:eng_x_preferred":[
        "Bhanrankula"
    ],
    "wof:name":"Bhanrankula",
    "wof:placetype":"neighbourhood",
    "wof:population":946
},
  "geometry": {"coordinates":[86.451303,20.265147],"type":"Point"}
}