{
  "type": "Feature",
  "properties": {
    "gn:admin1_code":"21.0",
    "gn:admin2_code":"374",
    "gn:asciiname":"Jharbera",
    "gn:country_code":"IN",
    "gn:dem":356,
    "gn:feature_class":"P",
    "gn:feature_code":"PPL",
    "gn:name":"Jh\u0101rbera",
    "gn:population":0,
    "gn:timezone":"Asia/Kolkata",
    "iso:country":"IN",
    "ks:ks_name":"Jharbeda",
    "ks:ks_pop":727,
    "ks:ks_type":"VILLAGE",
    "name:eng_x_preferred":[
        "Jharbeda"
    ],
    "name:eng_x_variant":[
        "Jharbera"
    ],
    "wof:name":"Jharbeda",
    "wof:placetype":"locality",
    "wof:population":727
},
  "geometry": {"coordinates":[85.024962,22.065106],"type":"Point"}
}