{
  "type": "Feature",
  "properties": {
    "iso:country":"IN",
    "ks:ks_name":"Karandewadi",
    "ks:ks_pop":245,
    "ks:ks_type":"HABITATION",
    "name:eng_x_preferred":[
        "Karandewadi"
    ],
    "wof:name":"Karandewadi",
    "wof:placetype":"locality",
    "wof:population":245
},
  "geometry": {"coordinates":[73.53833299999999,17.230833],"type":"Point"}
}