{
  "type": "Feature",
  "properties": {
    "iso:country":"IN",
    "ks:ks_alt_nam":"Sindholi Khurd",
    "ks:ks_name":"Sindholi",
    "ks:ks_type":"VILLAGE",
    "ks:ks_uagg_main":0,
    "name:eng_x_preferred":[
        "Sindholi"
    ],
    "name:eng_x_variant":[
        "Sindholi Khurd"
    ],
    "wof:name":"Sindholi",
    "wof:placetype":"neighbourhood"
},
  "geometry": {"coordinates":[78.436835,28.073179],"type":"Point"}
}