{
  "type": "Feature",
  "properties": {
    "gn:admin1_code":"36",
    "gn:admin2_code":"175.0",
    "gn:asciiname":"Dhurha",
    "gn:country_code":"IN",
    "gn:dem":95,
    "gn:feature_class":"P",
    "gn:feature_code":"PPL",
    "gn:name":"Dhurh\u0101",
    "gn:population":0,
    "gn:timezone":"Asia/Kolkata",
    "iso:country":"IN",
    "wof:name":"Dhurha",
    "wof:placetype":"neighbourhood"
},
  "geometry": {"coordinates":[82.11991999999999,25.41918],"type":"Point"}
}