{
  "type": "Feature",
  "properties": {
    "gn:admin1_code":"40",
    "gn:admin2_code":"537.0",
    "gn:asciiname":"Musirpet",
    "gn:country_code":"IN",
    "gn:dem":466,
    "gn:feature_class":"P",
    "gn:feature_code":"PPL",
    "gn:name":"M\u016bsirpet",
    "gn:population":0,
    "gn:timezone":"Asia/Kolkata",
    "iso:country":"IN",
    "name:und_x_variant":[
        "M\u016bsirpet",
        "Govindraopet"
    ],
    "wof:name":"Musirpet",
    "wof:placetype":"locality"
},
  "geometry": {"coordinates":[77.64551999999998,17.22009],"type":"Point"}
}