{
  "type": "Feature",
  "properties": {
    "iso:country":"IN",
    "ks:ks_name":"Badmal",
    "ks:ks_pop":243,
    "ks:ks_type":"VILLAGE",
    "name:eng_x_preferred":[
        "Badmal"
    ],
    "wof:name":"Badmal",
    "wof:placetype":"locality",
    "wof:population":243
},
  "geometry": {"coordinates":[84.319288,21.822725],"type":"Point"}
}