{
  "type": "Feature",
  "properties": {
    "iso:country":"IN",
    "ks:ks_alt_nam":"DADWA",
    "ks:ks_name":"Dadwa",
    "ks:ks_pop":63,
    "ks:ks_type":"HABITATION",
    "ks:ks_uagg_main":0,
    "name:eng_x_preferred":[
        "Dadwa"
    ],
    "wof:name":"Dadwa",
    "wof:placetype":"neighbourhood",
    "wof:population":63
},
  "geometry": {"coordinates":[82.16882200000001,26.253933],"type":"Point"}
}