{
  "type": "Feature",
  "properties": {
    "gn:admin1_code":"35.0",
    "gn:admin2_code":"455.0",
    "gn:asciiname":"Sunthia",
    "gn:country_code":"IN",
    "gn:dem":926,
    "gn:feature_class":"P",
    "gn:feature_code":"PPL",
    "gn:name":"Sunthia",
    "gn:population":0,
    "gn:timezone":"Asia/Kolkata",
    "iso:country":"IN",
    "wof:name":"Sunthia",
    "wof:placetype":"neighbourhood"
},
  "geometry": {"coordinates":[78.7418,22.30863],"type":"Point"}
}