{
  "type": "Feature",
  "properties": {
    "iso:country":"IN",
    "ks:ks_alt_nam":"K\u0101likuti",
    "ks:ks_name":"Kalikuti",
    "ks:ks_pop":95,
    "ks:ks_type":"VILLAGE",
    "name:eng_x_preferred":[
        "Kalikuti"
    ],
    "name:eng_x_variant":[
        "K\u0101likuti"
    ],
    "wof:name":"Kalikuti",
    "wof:placetype":"locality",
    "wof:population":95
},
  "geometry": {"coordinates":[83.99883,20.378096],"type":"Point"}
}