{
  "type": "Feature",
  "properties": {
    "iso:country":"IN",
    "ks:ks_name":"155 RDAS",
    "ks:ks_pop":138,
    "ks:ks_type":"VILLAGE",
    "name:eng_x_preferred":[
        "155 RDAS"
    ],
    "wof:name":"155 RDAS",
    "wof:placetype":"locality",
    "wof:population":138
},
  "geometry": {"coordinates":[73.265073,29.124242],"type":"Point"}
}