{
  "type": "Feature",
  "properties": {
    "iso:country":"IN",
    "ks:ks_name":"Dakshin Amarpur",
    "ks:ks_pop":334,
    "ks:ks_type":"VILLAGE",
    "name:eng_x_preferred":[
        "Dakshin Amarpur"
    ],
    "wof:name":"Dakshin Amarpur",
    "wof:placetype":"locality",
    "wof:population":334
},
  "geometry": {"coordinates":[87.648448,23.815043],"type":"Point"}
}