{
  "type": "Feature",
  "properties": {
    "iso:country":"IN",
    "ks:ks_alt_nam":"BADHU SINGH PURWA",
    "ks:ks_name":"Badhu Singh Purwa",
    "ks:ks_pop":45,
    "ks:ks_type":"HABITATION",
    "ks:ks_uagg_main":0,
    "name:eng_x_preferred":[
        "Badhu Singh Purwa"
    ],
    "wof:name":"Badhu Singh Purwa",
    "wof:placetype":"neighbourhood",
    "wof:population":45
},
  "geometry": {"coordinates":[81.61782700000001,27.358112],"type":"Point"}
}