{
  "type": "Feature",
  "properties": {
    "iso:country":"IN",
    "ks:ks_name":"Kantakhamba",
    "ks:ks_pop":57,
    "ks:ks_type":"VILLAGE",
    "name:eng_x_preferred":[
        "Kantakhamba"
    ],
    "wof:name":"Kantakhamba",
    "wof:placetype":"locality",
    "wof:population":57
},
  "geometry": {"coordinates":[84.406706,18.937711],"type":"Point"}
}