{
  "type": "Feature",
  "properties": {
    "iso:country":"IN",
    "ks:ks_name":"Mahmud Chak",
    "ks:ks_pop":404,
    "ks:ks_type":"HABITATION",
    "name:eng_x_preferred":[
        "Mahmud Chak"
    ],
    "wof:name":"Mahmud Chak",
    "wof:placetype":"locality",
    "wof:population":404
},
  "geometry": {"coordinates":[85.074183,25.718086],"type":"Point"}
}