{
  "type": "Feature",
  "properties": {
    "iso:country":"IN",
    "ks:ks_name":"Chwinth",
    "ks:ks_pop":291,
    "ks:ks_type":"VILLAGE",
    "name:eng_x_preferred":[
        "Chwinth"
    ],
    "wof:name":"Chwinth",
    "wof:placetype":"locality",
    "wof:population":291
},
  "geometry": {"coordinates":[78.965243,30.250674],"type":"Point"}
}