{
  "type": "Feature",
  "properties": {
    "iso:country":"IN",
    "ks:ks_name":"Banagattu Kodagibail",
    "ks:ks_pop":35,
    "ks:ks_type":"HABITATION",
    "name:eng_x_preferred":[
        "Banagattu Kodagibail"
    ],
    "wof:name":"Banagattu Kodagibail",
    "wof:placetype":"locality",
    "wof:population":35
},
  "geometry": {"coordinates":[74.75664,14.548319],"type":"Point"}
}