{
  "type": "Feature",
  "properties": {
    "gn:admin1_code":"36",
    "gn:admin2_code":"194.0",
    "gn:asciiname":"Ahirana",
    "gn:country_code":"IN",
    "gn:dem":94,
    "gn:feature_class":"P",
    "gn:feature_code":"PPL",
    "gn:name":"Ahir\u0101na",
    "gn:population":0,
    "gn:timezone":"Asia/Kolkata",
    "iso:country":"IN",
    "wof:name":"Ahirana",
    "wof:placetype":"locality"
},
  "geometry": {"coordinates":[82.50230000000001,26.10458],"type":"Point"}
}