{
  "type": "Feature",
  "properties": {
    "iso:country":"IN",
    "ks:ks_name":"Arari",
    "ks:ks_pop":41,
    "ks:ks_type":"HABITATION",
    "name:eng_x_preferred":[
        "Arari"
    ],
    "wof:name":"Arari",
    "wof:placetype":"locality",
    "wof:population":41
},
  "geometry": {"coordinates":[78.522221,29.972587],"type":"Point"}
}