{
  "type": "Feature",
  "properties": {
    "gn:admin1_code":"19.0",
    "gn:admin2_code":"566.0",
    "gn:asciiname":"Balenahalli",
    "gn:country_code":"IN",
    "gn:dem":631,
    "gn:feature_class":"P",
    "gn:feature_code":"PPL",
    "gn:name":"B\u0101lenahalli",
    "gn:population":0,
    "gn:timezone":"Asia/Kolkata",
    "iso:country":"IN",
    "wof:name":"Balenahalli",
    "wof:placetype":"locality"
},
  "geometry": {"coordinates":[76.55556999999997,14.25231],"type":"Point"}
}