{
  "type": "Feature",
  "properties": {
    "iso:country":"IN",
    "ks:ks_name":"Chandaus",
    "ks:ks_pop":5,
    "ks:ks_type":"HABITATION",
    "name:eng_x_preferred":[
        "Chandaus"
    ],
    "wof:name":"Chandaus",
    "wof:placetype":"locality",
    "wof:population":5
},
  "geometry": {"coordinates":[83.305278,25.163551],"type":"Point"}
}