{
  "type": "Feature",
  "properties": {
    "iso:country":"IN",
    "ks:ks_name":"Baktipara",
    "ks:ks_pop":256,
    "ks:ks_type":"HABITATION",
    "name:eng_x_preferred":[
        "Baktipara"
    ],
    "wof:name":"Baktipara",
    "wof:placetype":"locality",
    "wof:population":256
},
  "geometry": {"coordinates":[81.805853,19.012005],"type":"Point"}
}