{
  "type": "Feature",
  "properties": {
    "gn:admin1_code":"36",
    "gn:admin2_code":"134.0",
    "gn:asciiname":"Mahmuda Khadar",
    "gn:country_code":"IN",
    "gn:dem":218,
    "gn:feature_class":"P",
    "gn:feature_code":"PPL",
    "gn:name":"Mahm\u016bda Kh\u0101dar",
    "gn:population":0,
    "gn:timezone":"Asia/Kolkata",
    "iso:country":"IN",
    "wof:name":"Mahmuda Khadar",
    "wof:placetype":"locality"
},
  "geometry": {"coordinates":[78.14999,29.21536],"type":"Point"}
}