{
  "type": "Feature",
  "properties": {
    "iso:country":"IN",
    "ks:ks_name":"Anniyendal",
    "ks:ks_pop":554,
    "ks:ks_type":"HABITATION",
    "name:eng_x_preferred":[
        "Anniyendal"
    ],
    "wof:name":"Anniyendal",
    "wof:placetype":"locality",
    "wof:population":554
},
  "geometry": {"coordinates":[78.378122,9.757143],"type":"Point"}
}