{
  "type": "Feature",
  "properties": {
    "gn:admin1_code":"37",
    "gn:admin2_code":"404.0",
    "gn:asciiname":"Misia",
    "gn:country_code":"IN",
    "gn:dem":390,
    "gn:feature_class":"P",
    "gn:feature_code":"PPL",
    "gn:name":"Misia",
    "gn:population":0,
    "gn:timezone":"Asia/Kolkata",
    "iso:country":"IN",
    "name:ara_x_preferred":[
        "\u0645\u064a\u0633\u064a\u0627"
    ],
    "name:azb_x_preferred":[
        "\u0645\u06cc\u0633\u06cc\u0627"
    ],
    "name:cat_x_preferred":[
        "Misia"
    ],
    "name:deu_x_preferred":[
        "Misia"
    ],
    "name:ita_x_preferred":[
        "Misia"
    ],
    "name:pol_x_preferred":[
        "Misia"
    ],
    "name:tgl_x_preferred":[
        "Misia"
    ],
    "name:tha_x_preferred":[
        "\u0e21\u0e35\u0e40\u0e0a\u0e35\u0e22"
    ],
    "wof:name":"Misia",
    "wof:placetype":"locality"
},
  "geometry": {"coordinates":[82.47644,22.88253],"type":"Point"}
}