{
  "type": "Feature",
  "properties": {
    "gn:admin1_code":"12.0",
    "gn:admin2_code":"1.0",
    "gn:asciiname":"Kainagrad Forest",
    "gn:country_code":"IN",
    "gn:dem":2958,
    "gn:feature_class":"P",
    "gn:feature_code":"PPL",
    "gn:name":"Kain\u0101gr\u0101d Forest",
    "gn:population":0,
    "gn:timezone":"Asia/Kolkata",
    "iso:country":"IN",
    "wof:name":"Kainagrad Forest",
    "wof:placetype":"locality"
},
  "geometry": {"coordinates":[74.41116,34.59267],"type":"Point"}
}