{
  "type": "Feature",
  "properties": {
    "gn:admin1_code":"38.0",
    "gn:admin2_code":"348.0",
    "gn:asciiname":"Jia Chak",
    "gn:country_code":"IN",
    "gn:dem":402,
    "gn:feature_class":"P",
    "gn:feature_code":"PPL",
    "gn:name":"Ji\u0101 Chak",
    "gn:population":0,
    "gn:timezone":"Asia/Kolkata",
    "iso:country":"IN",
    "ks:ks_name":"Jiachak",
    "ks:ks_pop":359,
    "ks:ks_type":"VILLAGE",
    "name:eng_x_preferred":[
        "Jiachak"
    ],
    "name:eng_x_variant":[
        "Jia Chak"
    ],
    "wof:name":"Jiachak",
    "wof:placetype":"locality",
    "wof:population":359
},
  "geometry": {"coordinates":[85.30435,24.3919],"type":"Point"}
}