{
  "type": "Feature",
  "properties": {
    "iso:country":"IN",
    "ks:ks_name":"Raijhar",
    "ks:ks_pop":964,
    "ks:ks_type":"VILLAGE",
    "name:eng_x_preferred":[
        "Raijhar"
    ],
    "wof:name":"Raijhar",
    "wof:placetype":"locality",
    "wof:population":964
},
  "geometry": {"coordinates":[85.982552,20.677136],"type":"Point"}
}