{
  "type": "Feature",
  "properties": {
    "gn:admin1_code":"35",
    "gn:admin2_code":"445.0",
    "gn:asciiname":"Panchor",
    "gn:country_code":"IN",
    "gn:dem":316,
    "gn:feature_class":"P",
    "gn:feature_code":"PPL",
    "gn:name":"P\u0101nchor",
    "gn:population":0,
    "gn:timezone":"Asia/Kolkata",
    "iso:country":"IN",
    "name:msa_x_preferred":[
        "Panchor"
    ],
    "wof:name":"Panchor",
    "wof:placetype":"locality"
},
  "geometry": {"coordinates":[77.28270999999999,22.76967],"type":"Point"}
}