{
  "type": "Feature",
  "properties": {
    "iso:country":"IN",
    "ks:ks_name":"Gansurewadi",
    "ks:ks_pop":291,
    "ks:ks_type":"HABITATION",
    "name:eng_x_preferred":[
        "Gansurewadi"
    ],
    "wof:name":"Gansurewadi",
    "wof:placetype":"locality",
    "wof:population":291
},
  "geometry": {"coordinates":[73.29798099999999,17.205215],"type":"Point"}
}