{
  "type": "Feature",
  "properties": {
    "iso:country":"IN",
    "ks:ks_name":"F5 Balapur",
    "ks:ks_pop":331,
    "ks:ks_type":"HABITATION",
    "name:eng_x_preferred":[
        "F5 Balapur"
    ],
    "wof:name":"F5 Balapur",
    "wof:placetype":"locality",
    "wof:population":331
},
  "geometry": {"coordinates":[78.59867300000001,21.719882],"type":"Point"}
}