{
  "type": "Feature",
  "properties": {
    "iso:country":"IN",
    "ks:ks_name":"Sengamadai",
    "ks:ks_pop":186,
    "ks:ks_type":"HABITATION",
    "name:eng_x_preferred":[
        "Sengamadai"
    ],
    "wof:name":"Sengamadai",
    "wof:placetype":"locality",
    "wof:population":186
},
  "geometry": {"coordinates":[78.30817999999999,9.672682],"type":"Point"}
}