{
  "type": "Feature",
  "properties": {
    "iso:country":"IN",
    "ks:ks_name":"Bhainsamuda",
    "ks:ks_pop":110,
    "ks:ks_type":"HABITATION",
    "name:eng_x_preferred":[
        "Bhainsamuda"
    ],
    "wof:name":"Bhainsamuda",
    "wof:placetype":"locality",
    "wof:population":110
},
  "geometry": {"coordinates":[83.247511,22.58331],"type":"Point"}
}