{
  "type": "Feature",
  "properties": {
    "iso:country":"IN",
    "ks:ks_name":"Goudarkeri",
    "ks:ks_pop":87,
    "ks:ks_type":"HABITATION",
    "name:eng_x_preferred":[
        "Goudarkeri"
    ],
    "wof:name":"Goudarkeri",
    "wof:placetype":"locality",
    "wof:population":87
},
  "geometry": {"coordinates":[74.597444,14.442305],"type":"Point"}
}