{
  "type": "Feature",
  "properties": {
    "iso:country":"IN",
    "ks:ks_name":"Kuttoor",
    "ks:ks_pop":19974,
    "ks:ks_type":"VILLAGE",
    "name:eng_x_preferred":[
        "Kuttoor"
    ],
    "wof:name":"Kuttoor",
    "wof:placetype":"locality",
    "wof:population":19974
},
  "geometry": {"coordinates":[76.561678,9.365277],"type":"Point"}
}