{
  "type": "Feature",
  "properties": {
    "iso:country":"IN",
    "ks:ks_name":"Dabidubi",
    "ks:ks_pop":239,
    "ks:ks_type":"VILLAGE",
    "ks:ks_uagg_main":0,
    "name:eng_x_preferred":[
        "Dabidubi"
    ],
    "wof:name":"Dabidubi",
    "wof:placetype":"neighbourhood",
    "wof:population":239
},
  "geometry": {"coordinates":[93.895184,26.611123],"type":"Point"}
}