{
  "type": "Feature",
  "properties": {
    "iso:country":"IN",
    "ks:ks_name":"Kokradanga Pt.I",
    "ks:ks_pop":54,
    "ks:ks_type":"VILLAGE",
    "name:eng_x_preferred":[
        "Kokradanga Pt.I"
    ],
    "wof:name":"Kokradanga Pt.I",
    "wof:placetype":"locality",
    "wof:population":54
},
  "geometry": {"coordinates":[89.832921,25.738703],"type":"Point"}
}