{
  "type": "Feature",
  "properties": {
    "iso:country":"IN",
    "ks:ks_name":"Mankanda",
    "ks:ks_pop":174,
    "ks:ks_type":"VILLAGE",
    "name:eng_x_preferred":[
        "Mankanda"
    ],
    "wof:name":"Mankanda",
    "wof:placetype":"locality",
    "wof:population":174
},
  "geometry": {"coordinates":[80.13752100000001,29.232918],"type":"Point"}
}