{
  "type": "Feature",
  "properties": {
    "iso:country":"IN",
    "ks:ks_name":"Nandhikallu",
    "ks:ks_pop":104,
    "ks:ks_type":"HABITATION",
    "name:eng_x_preferred":[
        "Nandhikallu"
    ],
    "wof:name":"Nandhikallu",
    "wof:placetype":"locality",
    "wof:population":104
},
  "geometry": {"coordinates":[75.38436900000001,13.693653],"type":"Point"}
}