{
  "type": "Feature",
  "properties": {
    "iso:country":"IN",
    "ks:ks_name":"Khajane Shivapura",
    "ks:ks_pop":279,
    "ks:ks_type":"HABITATION",
    "name:eng_x_preferred":[
        "Khajane Shivapura"
    ],
    "wof:name":"Khajane Shivapura",
    "wof:placetype":"locality",
    "wof:population":279
},
  "geometry": {"coordinates":[74.957825,13.388504],"type":"Point"}
}