{
  "type": "Feature",
  "properties": {
    "gn:admin1_code":"36",
    "gn:admin2_code":"157.0",
    "gn:asciiname":"Salempur",
    "gn:country_code":"IN",
    "gn:dem":111,
    "gn:feature_class":"P",
    "gn:feature_code":"PPL",
    "gn:name":"Salempur",
    "gn:population":0,
    "gn:timezone":"Asia/Kolkata",
    "iso:country":"IN",
    "ks:ks_name":"Salempur",
    "ks:ks_pop":2046,
    "ks:ks_type":"VILLAGE",
    "ks:ks_uagg_main":0,
    "name:ceb_x_preferred":[
        "Salempur"
    ],
    "name:eng_x_preferred":[
        "Salempur"
    ],
    "name:pol_x_preferred":[
        "Salempur"
    ],
    "name:swe_x_preferred":[
        "Salempur"
    ],
    "wof:name":"Salempur",
    "wof:placetype":"neighbourhood",
    "wof:population":2046
},
  "geometry": {"coordinates":[81.201393,26.728007],"type":"Point"}
}