{
  "type": "Feature",
  "properties": {
    "iso:country":"IN",
    "ks:ks_name":"Durgwadi",
    "ks:ks_pop":170,
    "ks:ks_type":"HABITATION",
    "name:eng_x_preferred":[
        "Durgwadi"
    ],
    "wof:name":"Durgwadi",
    "wof:placetype":"locality",
    "wof:population":170
},
  "geometry": {"coordinates":[73.48243100000001,17.126358],"type":"Point"}
}