{
  "type": "Feature",
  "properties": {
    "iso:country":"IN",
    "ks:ks_name":"Benoda",
    "ks:ks_pop":306,
    "ks:ks_type":"HABITATION",
    "name:eng_x_preferred":[
        "Benoda"
    ],
    "wof:name":"Benoda",
    "wof:placetype":"locality",
    "wof:population":306
},
  "geometry": {"coordinates":[87.553251,23.229552],"type":"Point"}
}