{
  "type": "Feature",
  "properties": {
    "gn:admin1_code":"34.0",
    "gn:admin2_code":"219.0",
    "gn:asciiname":"Ubhwa Saraunja",
    "gn:country_code":"IN",
    "gn:dem":62,
    "gn:feature_class":"P",
    "gn:feature_code":"PPL",
    "gn:name":"Ubhwa Saraunja",
    "gn:population":0,
    "gn:timezone":"Asia/Kolkata",
    "iso:country":"IN",
    "wof:name":"Ubhwa Saraunja",
    "wof:placetype":"locality"
},
  "geometry": {"coordinates":[84.89296999999998,26.14666],"type":"Point"}
}