{
  "type": "Feature",
  "properties": {
    "iso:country":"IN",
    "ks:ks_alt_nam":"Vazhaipuattu nemilli",
    "ks:ks_name":"Vazhaipuattu Nemilli",
    "ks:ks_pop":50,
    "ks:ks_type":"HABITATION",
    "name:eng_x_preferred":[
        "Vazhaipuattu Nemilli"
    ],
    "wof:name":"Vazhaipuattu Nemilli",
    "wof:placetype":"locality",
    "wof:population":50
},
  "geometry": {"coordinates":[79.975314,12.34967],"type":"Point"}
}