{
  "type": "Feature",
  "properties": {
    "gn:admin1_code":"40",
    "gn:admin2_code":"538.0",
    "gn:asciiname":"Venkatreddipalli",
    "gn:country_code":"IN",
    "gn:dem":600,
    "gn:feature_class":"P",
    "gn:feature_code":"PPL",
    "gn:name":"Venkatreddipalli",
    "gn:population":0,
    "gn:timezone":"Asia/Kolkata",
    "iso:country":"IN",
    "wof:name":"Venkatreddipalli",
    "wof:placetype":"locality"
},
  "geometry": {"coordinates":[78.10642,17.01445],"type":"Point"}
}