{
  "type": "Feature",
  "properties": {
    "gn:admin1_code":"34.0",
    "gn:admin2_code":"220.0",
    "gn:asciiname":"Chak Eso",
    "gn:country_code":"IN",
    "gn:dem":52,
    "gn:feature_class":"P",
    "gn:feature_code":"PPL",
    "gn:name":"Chak Eso",
    "gn:population":0,
    "gn:timezone":"Asia/Kolkata",
    "iso:country":"IN",
    "ks:ks_name":"Chak Eso",
    "ks:ks_pop":1255,
    "ks:ks_type":"VILLAGE",
    "name:eng_x_preferred":[
        "Chak Eso"
    ],
    "wof:name":"Chak Eso",
    "wof:placetype":"locality",
    "wof:population":1255
},
  "geometry": {"coordinates":[85.499729,25.603643],"type":"Point"}
}