{
  "type": "Feature",
  "properties": {
    "iso:country":"IN",
    "ks:ks_name":"Dhanauj",
    "ks:ks_pop":542,
    "ks:ks_type":"VILLAGE",
    "name:eng_x_preferred":[
        "Dhanauj"
    ],
    "wof:name":"Dhanauj",
    "wof:placetype":"locality",
    "wof:population":542
},
  "geometry": {"coordinates":[86.429675,25.772504],"type":"Point"}
}