{
  "type": "Feature",
  "properties": {
    "iso:country":"IN",
    "ks:ks_alt_nam":"KRIPALBALRAJFOUJI KI DHANI",
    "ks:ks_name":"Kripalbalrajfouji Ki Dhani",
    "ks:ks_pop":164,
    "ks:ks_type":"HABITATION",
    "name:eng_x_preferred":[
        "Kripalbalrajfouji Ki Dhani"
    ],
    "wof:name":"Kripalbalrajfouji Ki Dhani",
    "wof:placetype":"locality",
    "wof:population":164
},
  "geometry": {"coordinates":[73.92569399999999,30.068822],"type":"Point"}
}