{
  "type": "Feature",
  "properties": {
    "iso:country":"IN",
    "ks:ks_alt_nam":"MAJHATOLI",
    "ks:ks_name":"Majhatoli",
    "ks:ks_pop":479,
    "ks:ks_type":"HABITATION",
    "name:eng_x_preferred":[
        "Majhatoli"
    ],
    "wof:name":"Majhatoli",
    "wof:placetype":"locality",
    "wof:population":479
},
  "geometry": {"coordinates":[83.87571,22.903587],"type":"Point"}
}