{
  "type": "Feature",
  "properties": {
    "iso:country":"IN",
    "ks:ks_name":"Munashyarpur P S",
    "ks:ks_pop":465,
    "ks:ks_type":"HABITATION",
    "name:eng_x_preferred":[
        "Munashyarpur P S"
    ],
    "wof:name":"Munashyarpur P S",
    "wof:placetype":"locality",
    "wof:population":465
},
  "geometry": {"coordinates":[92.49382300000001,24.46003],"type":"Point"}
}