{
  "type": "Feature",
  "properties": {
    "gn:admin1_code":"36",
    "gn:admin2_code":"159.0",
    "gn:asciiname":"Chak Nagla Dusadh",
    "gn:country_code":"IN",
    "gn:dem":149,
    "gn:feature_class":"P",
    "gn:feature_code":"PPL",
    "gn:name":"Chak Nagla D\u016bs\u0101dh",
    "gn:population":0,
    "gn:timezone":"Asia/Kolkata",
    "iso:country":"IN",
    "wof:name":"Chak Nagla Dusadh",
    "wof:placetype":"locality"
},
  "geometry": {"coordinates":[79.32738000000001,27.27322],"type":"Point"}
}