{
  "type": "Feature",
  "properties": {
    "iso:country":"IN",
    "ks:ks_name":"Baingwadi",
    "ks:ks_pop":200,
    "ks:ks_type":"HABITATION",
    "name:eng_x_preferred":[
        "Baingwadi"
    ],
    "wof:name":"Baingwadi",
    "wof:placetype":"locality",
    "wof:population":200
},
  "geometry": {"coordinates":[73.719286,16.9618],"type":"Point"}
}