{
  "type": "Feature",
  "properties": {
    "iso:country":"IN",
    "ks:ks_name":"Krushnachandrapur",
    "ks:ks_pop":840,
    "ks:ks_type":"VILLAGE",
    "ks:ks_uagg_main":0,
    "name:eng_x_preferred":[
        "Krushnachandrapur"
    ],
    "wof:name":"Krushnachandrapur",
    "wof:placetype":"neighbourhood",
    "wof:population":840
},
  "geometry": {"coordinates":[85.84509,20.442359],"type":"Point"}
}