{
  "type": "Feature",
  "properties": {
    "iso:country":"IN",
    "ks:ks_name":"Sanokandulpada",
    "ks:ks_pop":33,
    "ks:ks_type":"VILLAGE",
    "name:eng_x_preferred":[
        "Sanokandulpada"
    ],
    "wof:name":"Sanokandulpada",
    "wof:placetype":"locality",
    "wof:population":33
},
  "geometry": {"coordinates":[83.572507,19.816776],"type":"Point"}
}