{
  "type": "Feature",
  "properties": {
    "gn:country":"IN",
    "gn:fcode":"PPL",
    "gn:pop":13949,
    "iso:country":"IN",
    "name:bpy_x_preferred":[
        "\u09b0\u09be\u09ac\u09c1\u09aa\u09c1\u09b0\u09be"
    ],
    "name:ceb_x_preferred":[
        "Rab\u016bpura"
    ],
    "name:eng_x_preferred":[
        "Rabupura"
    ],
    "name:fra_x_preferred":[
        "Rabupura"
    ],
    "name:hin_x_preferred":[
        "\u0930\u093e\u092c\u0942\u092a\u0941\u0930\u093e"
    ],
    "name:ind_x_preferred":[
        "Rabupura"
    ],
    "name:ita_x_preferred":[
        "Rabupura"
    ],
    "name:mlg_x_preferred":[
        "Rabupura"
    ],
    "name:msa_x_preferred":[
        "Rabupura"
    ],
    "name:nan_x_preferred":[
        "Rabupura"
    ],
    "name:nld_x_preferred":[
        "Rabupura"
    ],
    "name:pol_x_preferred":[
        "Rabupura"
    ],
    "name:por_x_preferred":[
        "Rabupura"
    ],
    "name:swe_x_preferred":[
        "Rab\u016bpura"
    ],
    "name:urd_x_preferred":[
        "\u0631\u0627\u0628\u0648\u067e\u0648\u0631\u0627"
    ],
    "name:vie_x_preferred":[
        "Rabupura"
    ],
    "name:zho_x_preferred":[
        "\u62c9\u5e03\u666e\u62c9"
    ],
    "qs:name":"Rab\u016bpura",
    "qs:photos_9r":0,
    "qs:photos_sr":0,
    "qs:pop_sr":"6",
    "wd:wordcount":144,
    "wof:name":"Rab\u016bpura",
    "wof:placetype":"locality",
    "wof:population":13949
},
  "geometry": {"coordinates":[77.60051,28.25075],"type":"Point"}
}