{
  "type": "Feature",
  "properties": {
    "gn:admin1_code":"35.0",
    "gn:admin2_code":"452.0",
    "gn:asciiname":"Bhilmadhana",
    "gn:country_code":"IN",
    "gn:dem":813,
    "gn:feature_class":"P",
    "gn:feature_code":"PPL",
    "gn:name":"Bhilm\u0101dh\u0101na",
    "gn:population":0,
    "gn:timezone":"Asia/Kolkata",
    "iso:country":"IN",
    "ks:ks_name":"Bhilmadhana",
    "ks:ks_pop":330,
    "ks:ks_type":"VILLAGE",
    "name:eng_x_preferred":[
        "Bhilmadhana"
    ],
    "wof:name":"Bhilmadhana",
    "wof:placetype":"locality",
    "wof:population":330
},
  "geometry": {"coordinates":[78.87554799999999,22.685342],"type":"Point"}
}