{
  "type": "Feature",
  "properties": {
    "gn:admin1_code":"23.0",
    "gn:admin2_code":"48.0",
    "gn:asciiname":"Mahmudpur",
    "gn:country_code":"IN",
    "gn:dem":253,
    "gn:feature_class":"P",
    "gn:feature_code":"PPL",
    "gn:name":"Mahmudpur",
    "gn:population":0,
    "gn:timezone":"Asia/Kolkata",
    "iso:country":"IN",
    "wof:name":"Mahmudpur",
    "wof:placetype":"neighbourhood"
},
  "geometry": {"coordinates":[76.45975,30.24968],"type":"Point"}
}