{
  "type": "Feature",
  "properties": {
    "gn:admin1_code":"21.0",
    "gn:admin2_code":"398.0",
    "gn:asciiname":"Dinaputtu",
    "gn:country_code":"IN",
    "gn:dem":835,
    "gn:feature_class":"P",
    "gn:feature_code":"PPL",
    "gn:name":"D\u012bnaputtu",
    "gn:population":0,
    "gn:timezone":"Asia/Kolkata",
    "iso:country":"IN",
    "wof:name":"Dinaputtu",
    "wof:placetype":"locality"
},
  "geometry": {"coordinates":[82.55119999999999,18.5022],"type":"Point"}
}