{
  "type": "Feature",
  "properties": {
    "gn:admin1_code":"39.0",
    "gn:admin2_code":"59.0",
    "gn:asciiname":"Kolti",
    "gn:country_code":"IN",
    "gn:dem":1517,
    "gn:feature_class":"P",
    "gn:feature_code":"PPL",
    "gn:name":"Kolti",
    "gn:population":0,
    "gn:timezone":"Asia/Kolkata",
    "iso:country":"IN",
    "name:ceb_x_preferred":[
        "Kolti"
    ],
    "name:fra_x_preferred":[
        "Kolti"
    ],
    "name:mai_x_preferred":[
        "\u0915\u094b\u0932\u094d\u091f\u0940"
    ],
    "name:msa_x_preferred":[
        "Kolti"
    ],
    "name:nep_x_preferred":[
        "\u0915\u094b\u0932\u094d\u091f\u0940"
    ],
    "name:new_x_preferred":[
        "\u0915\u094b\u0932\u094d\u091f\u0940"
    ],
    "name:nor_x_preferred":[
        "Kolti"
    ],
    "name:pol_x_preferred":[
        "Kolti"
    ],
    "wof:name":"Kolti",
    "wof:placetype":"locality"
},
  "geometry": {"coordinates":[78.11256999999998,30.47618],"type":"Point"}
}