{
  "type": "Feature",
  "properties": {
    "gn:admin1_code":"35",
    "gn:admin2_code":"425.0",
    "gn:asciiname":"Gangau",
    "gn:country_code":"IN",
    "gn:dem":250,
    "gn:feature_class":"P",
    "gn:feature_code":"PPL",
    "gn:name":"Gangau",
    "gn:population":0,
    "gn:timezone":"Asia/Kolkata",
    "iso:country":"IN",
    "ks:ks_name":"Gagau",
    "ks:ks_pop":91,
    "ks:ks_type":"VILLAGE",
    "name:eng_x_preferred":[
        "Gagau"
    ],
    "name:eng_x_variant":[
        "Gangau"
    ],
    "wof:name":"Gagau",
    "wof:placetype":"locality",
    "wof:population":91
},
  "geometry": {"coordinates":[79.868866,24.612197],"type":"Point"}
}