{
  "type": "Feature",
  "properties": {
    "iso:country":"IN",
    "ks:ks_name":"Khagra Arazi",
    "ks:ks_pop":0,
    "ks:ks_type":"VILLAGE",
    "name:eng_x_preferred":[
        "Khagra Arazi"
    ],
    "wof:name":"Khagra Arazi",
    "wof:placetype":"locality",
    "wof:population":0
},
  "geometry": {"coordinates":[87.060428,25.34399],"type":"Point"}
}