{
  "type": "Feature",
  "properties": {
    "iso:country":"IN",
    "ks:ks_name":"Shindewasti Balawadi",
    "ks:ks_pop":464,
    "ks:ks_type":"HABITATION",
    "name:eng_x_preferred":[
        "Shindewasti Balawadi"
    ],
    "wof:name":"Shindewasti Balawadi",
    "wof:placetype":"locality",
    "wof:population":464
},
  "geometry": {"coordinates":[75.005578,17.409677],"type":"Point"}
}