{
  "type": "Feature",
  "properties": {
    "iso:country":"IN",
    "ks:ks_alt_nam":"KARUMAHUA",
    "ks:ks_name":"Karumahua",
    "ks:ks_pop":414,
    "ks:ks_type":"HABITATION",
    "name:eng_x_preferred":[
        "Karumahua"
    ],
    "wof:name":"Karumahua",
    "wof:placetype":"locality",
    "wof:population":414
},
  "geometry": {"coordinates":[83.46881500000001,22.606301],"type":"Point"}
}