{
  "type": "Feature",
  "properties": {
    "iso:country":"IN",
    "ks:ks_name":"Tangarjuri",
    "ks:ks_pop":325,
    "ks:ks_type":"HABITATION",
    "name:eng_x_preferred":[
        "Tangarjuri"
    ],
    "wof:name":"Tangarjuri",
    "wof:placetype":"locality",
    "wof:population":325
},
  "geometry": {"coordinates":[84.028802,21.298402],"type":"Point"}
}