{
  "type": "Feature",
  "properties": {
    "gn:admin1_code":"35",
    "gn:admin2_code":"449.0",
    "gn:asciiname":"Silkanth",
    "gn:country_code":"IN",
    "gn:dem":289,
    "gn:feature_class":"P",
    "gn:feature_code":"PPL",
    "gn:name":"S\u012blkanth",
    "gn:population":0,
    "gn:timezone":"Asia/Kolkata",
    "iso:country":"IN",
    "wof:name":"Silkanth",
    "wof:placetype":"locality"
},
  "geometry": {"coordinates":[77.24198,22.59357],"type":"Point"}
}