{
  "type": "Feature",
  "properties": {
    "iso:country":"IN",
    "ks:ks_name":"Aam Kho",
    "ks:ks_pop":827,
    "ks:ks_type":"VILLAGE",
    "name:eng_x_preferred":[
        "Aam Kho"
    ],
    "wof:name":"Aam Kho",
    "wof:placetype":"locality",
    "wof:population":827
},
  "geometry": {"coordinates":[75.33438,22.428457],"type":"Point"}
}