{
  "type": "Feature",
  "properties": {
    "gn:admin1_code":"11",
    "gn:admin2_code":"31.0",
    "gn:asciiname":"Dhamroh",
    "gn:country_code":"IN",
    "gn:dem":1067,
    "gn:feature_class":"P",
    "gn:feature_code":"PPL",
    "gn:name":"Dhamroh",
    "gn:population":0,
    "gn:timezone":"Asia/Kolkata",
    "iso:country":"IN",
    "wof:name":"Dhamroh",
    "wof:placetype":"locality"
},
  "geometry": {"coordinates":[76.74218,31.12001],"type":"Point"}
}