{
  "type": "Feature",
  "properties": {
    "iso:country":"IN",
    "ks:ks_alt_nam":"GD palya",
    "ks:ks_name":"Gd Palya",
    "ks:ks_pop":449,
    "ks:ks_type":"HABITATION",
    "name:eng_x_preferred":[
        "Gd Palya"
    ],
    "wof:name":"Gd Palya",
    "wof:placetype":"locality",
    "wof:population":449
},
  "geometry": {"coordinates":[77.139914,13.850917],"type":"Point"}
}