{
  "type": "Feature",
  "properties": {
    "iso:country":"IN",
    "ks:ks_name":"Dhangawa",
    "ks:ks_pop":24,
    "ks:ks_type":"HABITATION",
    "name:eng_x_preferred":[
        "Dhangawa"
    ],
    "wof:name":"Dhangawa",
    "wof:placetype":"locality",
    "wof:population":24
},
  "geometry": {"coordinates":[80.343661,23.582833],"type":"Point"}
}