{
  "type": "Feature",
  "properties": {
    "iso:country":"IN",
    "ks:ks_name":"Krishnai Guria Pt II",
    "ks:ks_pop":2180,
    "ks:ks_type":"VILLAGE",
    "name:eng_x_preferred":[
        "Krishnai Guria Pt II"
    ],
    "wof:name":"Krishnai Guria Pt II",
    "wof:placetype":"locality",
    "wof:population":2180
},
  "geometry": {"coordinates":[90.676982,25.98392],"type":"Point"}
}