{
  "type": "Feature",
  "properties": {
    "iso:country":"IN",
    "ks:ks_alt_nam":"NC No.2 Nanglichar",
    "ks:ks_name":"Nc No.2 Nanglichar",
    "ks:ks_pop":1992,
    "ks:ks_type":"HABITATION",
    "name:eng_x_preferred":[
        "Nc No.2 Nanglichar"
    ],
    "wof:name":"Nc No.2 Nanglichar",
    "wof:placetype":"locality",
    "wof:population":1992
},
  "geometry": {"coordinates":[92.124227,26.396218],"type":"Point"}
}