{
  "type": "Feature",
  "properties": {
    "iso:country":"IN",
    "ks:ks_name":"Sonathar",
    "ks:ks_pop":192,
    "ks:ks_type":"VILLAGE",
    "name:eng_x_preferred":[
        "Sonathar"
    ],
    "wof:name":"Sonathar",
    "wof:placetype":"locality",
    "wof:population":192
},
  "geometry": {"coordinates":[86.823936,23.988642],"type":"Point"}
}