{
  "type": "Feature",
  "properties": {
    "gn:admin1_code":"36.0",
    "gn:admin2_code":"158.0",
    "gn:asciiname":"Kuti Baba Nuhardas",
    "gn:country_code":"IN",
    "gn:dem":118,
    "gn:feature_class":"P",
    "gn:feature_code":"PPL",
    "gn:name":"Kuti B\u0101ba Nuhard\u0101s",
    "gn:population":0,
    "gn:timezone":"Asia/Kolkata",
    "iso:country":"IN",
    "wof:name":"Kuti Baba Nuhardas",
    "wof:placetype":"locality"
},
  "geometry": {"coordinates":[81.34149000000002,26.43505],"type":"Point"}
}