{
  "type": "Feature",
  "properties": {
    "iso:country":"IN",
    "ks:ks_name":"Chowdikoppa",
    "ks:ks_pop":306,
    "ks:ks_type":"VILLAGE",
    "name:eng_x_preferred":[
        "Chowdikoppa"
    ],
    "wof:name":"Chowdikoppa",
    "wof:placetype":"locality",
    "wof:population":306
},
  "geometry": {"coordinates":[75.017267,14.411589],"type":"Point"}
}