{
  "type": "Feature",
  "properties": {
    "iso:country":"IN",
    "ks:ks_name":"Gummanahalli",
    "ks:ks_type":"VILLAGE",
    "name:eng_x_preferred":[
        "Gummanahalli"
    ],
    "wof:name":"Gummanahalli",
    "wof:placetype":"locality"
},
  "geometry": {"coordinates":[77.913085,13.420772],"type":"Point"}
}