{
  "type": "Feature",
  "properties": {
    "gn:admin1_code":"11",
    "gn:admin2_code":"27.0",
    "gn:asciiname":"Mali Dog",
    "gn:country_code":"IN",
    "gn:dem":2258,
    "gn:feature_class":"P",
    "gn:feature_code":"PPL",
    "gn:name":"M\u0101li Dog",
    "gn:population":0,
    "gn:timezone":"Asia/Kolkata",
    "iso:country":"IN",
    "wof:name":"Mali Dog",
    "wof:placetype":"locality"
},
  "geometry": {"coordinates":[76.87441,31.96333],"type":"Point"}
}