{
  "type": "Feature",
  "properties": {
    "iso:country":"IN",
    "ks:ks_name":"Padiabhanga",
    "ks:ks_pop":716,
    "ks:ks_type":"VILLAGE",
    "ks:ks_uagg_main":0,
    "name:eng_x_preferred":[
        "Padiabhanga"
    ],
    "wof:name":"Padiabhanga",
    "wof:placetype":"neighbourhood",
    "wof:population":716
},
  "geometry": {"coordinates":[85.220225,20.893968],"type":"Point"}
}