{
  "type": "Feature",
  "properties": {
    "iso:country":"IN",
    "ks:ks_name":"Purba Dulepara",
    "ks:ks_pop":249,
    "ks:ks_type":"HABITATION",
    "ks:ks_uagg_main":0,
    "name:eng_x_preferred":[
        "Purba Dulepara"
    ],
    "wof:name":"Purba Dulepara",
    "wof:placetype":"neighbourhood",
    "wof:population":249
},
  "geometry": {"coordinates":[88.05685699999999,22.690975],"type":"Point"}
}