{
  "type": "Feature",
  "properties": {
    "gn:admin1_code":"28.0",
    "gn:admin2_code":"332.0",
    "gn:asciiname":"Katakpura",
    "gn:country_code":"IN",
    "gn:dem":32,
    "gn:feature_class":"P",
    "gn:feature_code":"PPL",
    "gn:name":"Katakpura",
    "gn:population":0,
    "gn:timezone":"Asia/Kolkata",
    "iso:country":"IN",
    "wof:name":"Katakpura",
    "wof:placetype":"neighbourhood"
},
  "geometry": {"coordinates":[87.90457000000001,25.49935],"type":"Point"}
}