{
  "type": "Feature",
  "properties": {
    "iso:country":"IN",
    "ks:ks_name":"Navawas",
    "ks:ks_pop":101,
    "ks:ks_type":"VILLAGE",
    "name:eng_x_preferred":[
        "Navawas"
    ],
    "wof:name":"Navawas",
    "wof:placetype":"locality",
    "wof:population":101
},
  "geometry": {"coordinates":[73.081791,24.736724],"type":"Point"}
}