{
  "type": "Feature",
  "properties": {
    "gn:admin1_code":"24.0",
    "gn:admin2_code":"125.0",
    "gn:asciiname":"Govindpura",
    "gn:country_code":"IN",
    "gn:dem":156,
    "gn:feature_class":"P",
    "gn:feature_code":"PPL",
    "gn:name":"Govindpura",
    "gn:population":0,
    "gn:timezone":"Asia/Kolkata",
    "iso:country":"IN",
    "ks:ks_name":"Govindpura",
    "ks:ks_pop":1106,
    "ks:ks_type":"VILLAGE",
    "name:eng_x_preferred":[
        "Govindpura"
    ],
    "wof:name":"Govindpura",
    "wof:placetype":"locality",
    "wof:population":1106
},
  "geometry": {"coordinates":[74.147222,23.484722],"type":"Point"}
}