{
  "type": "Feature",
  "properties": {
    "iso:country":"IN",
    "ks:ks_name":"Paningapalle",
    "ks:ks_pop":1930,
    "ks:ks_type":"VILLAGE",
    "name:eng_x_preferred":[
        "Paningapalle"
    ],
    "wof:name":"Paningapalle",
    "wof:placetype":"locality",
    "wof:population":1930
},
  "geometry": {"coordinates":[82.020905,16.749173],"type":"Point"}
}