{
  "type": "Feature",
  "properties": {
    "gn:admin1_code":"36",
    "gn:admin2_code":"175.0",
    "gn:asciiname":"Konan",
    "gn:country_code":"IN",
    "gn:dem":92,
    "gn:feature_class":"P",
    "gn:feature_code":"PPL",
    "gn:name":"Kon\u0101n",
    "gn:population":0,
    "gn:timezone":"Asia/Kolkata",
    "iso:country":"IN",
    "name:bre_x_preferred":[
        "Konan"
    ],
    "name:ceb_x_preferred":[
        "Konan"
    ],
    "name:deu_x_preferred":[
        "Konan"
    ],
    "name:fra_x_preferred":[
        "Konan"
    ],
    "name:hun_x_preferred":[
        "Konan"
    ],
    "name:ita_x_preferred":[
        "Konan"
    ],
    "name:kor_x_preferred":[
        "\uace0\ub09c\uc2dc"
    ],
    "name:nld_x_preferred":[
        "Konan"
    ],
    "name:por_x_preferred":[
        "Konan"
    ],
    "name:ron_x_preferred":[
        "Konan"
    ],
    "name:rus_x_preferred":[
        "\u041a\u043e\u043d\u0430\u043d"
    ],
    "name:swe_x_preferred":[
        "Konan"
    ],
    "name:tgk_x_preferred":[
        "\u041a\u043e\u043d\u0430\u043d"
    ],
    "name:ukr_x_preferred":[
        "\u041a\u043e\u043d\u0430\u043d"
    ],
    "name:vie_x_preferred":[
        "Konan"
    ],
    "wof:name":"Konan",
    "wof:placetype":"locality"
},
  "geometry": {"coordinates":[82.03518000000003,25.19618],"type":"Point"}
}