{
  "type": "Feature",
  "properties": {
    "gn:admin1_code":"21",
    "gn:admin2_code":"399.0",
    "gn:asciiname":"Tarlakota",
    "gn:country_code":"IN",
    "gn:dem":202,
    "gn:feature_class":"P",
    "gn:feature_code":"PPL",
    "gn:name":"T\u0101rlakota",
    "gn:population":0,
    "gn:timezone":"Asia/Kolkata",
    "iso:country":"IN",
    "ks:ks_alt_nam":"T\u0101rlakota",
    "ks:ks_name":"Tarlakota",
    "ks:ks_pop":1,
    "ks:ks_type":"VILLAGE",
    "name:eng_x_preferred":[
        "Tarlakota"
    ],
    "name:eng_x_variant":[
        "T\u0101rlakota"
    ],
    "wof:name":"Tarlakota",
    "wof:placetype":"locality",
    "wof:population":1
},
  "geometry": {"coordinates":[82.06555899999999,18.28577],"type":"Point"}
}