{
  "type": "Feature",
  "properties": {
    "iso:country":"IN",
    "ks:ks_name":"Samagol",
    "ks:ks_pop":2044,
    "ks:ks_type":"VILLAGE",
    "ks:ks_uagg_main":0,
    "name:eng_x_preferred":[
        "Samagol"
    ],
    "wof:name":"Samagol",
    "wof:placetype":"neighbourhood",
    "wof:population":2044
},
  "geometry": {"coordinates":[86.532681,20.310465],"type":"Point"}
}