{
  "type": "Feature",
  "properties": {
    "iso:country":"IN",
    "ks:ks_name":"Salhe T03",
    "ks:ks_pop":304,
    "ks:ks_type":"HABITATION",
    "name:eng_x_preferred":[
        "Salhe T03"
    ],
    "wof:name":"Salhe T03",
    "wof:placetype":"locality",
    "wof:population":304
},
  "geometry": {"coordinates":[79.363719,21.853863],"type":"Point"}
}