{
  "type": "Feature",
  "properties": {
    "iso:country":"IN",
    "ks:ks_name":"Patgarkeri",
    "ks:ks_pop":203,
    "ks:ks_type":"HABITATION",
    "name:eng_x_preferred":[
        "Patgarkeri"
    ],
    "wof:name":"Patgarkeri",
    "wof:placetype":"locality",
    "wof:population":203
},
  "geometry": {"coordinates":[74.401042,14.502338],"type":"Point"}
}