{
  "type": "Feature",
  "properties": {
    "iso:country":"IN",
    "ks:ks_name":"Morotoliya",
    "ks:ks_pop":346,
    "ks:ks_type":"VILLAGE",
    "name:eng_x_preferred":[
        "Morotoliya"
    ],
    "wof:name":"Morotoliya",
    "wof:placetype":"locality",
    "wof:population":346
},
  "geometry": {"coordinates":[86.48115,22.422858],"type":"Point"}
}