{
  "type": "Feature",
  "properties": {
    "iso:country":"IN",
    "ks:ks_name":"Jamatnagar Peera Nadi",
    "ks:ks_pop":150,
    "ks:ks_type":"HABITATION",
    "name:eng_x_preferred":[
        "Jamatnagar Peera Nadi"
    ],
    "wof:name":"Jamatnagar Peera Nadi",
    "wof:placetype":"locality",
    "wof:population":150
},
  "geometry": {"coordinates":[72.28559199999999,26.138189],"type":"Point"}
}