{
  "type": "Feature",
  "properties": {
    "iso:country":"IN",
    "ks:ks_name":"Patel Para",
    "ks:ks_pop":232,
    "ks:ks_type":"HABITATION",
    "name:eng_x_preferred":[
        "Patel Para"
    ],
    "wof:name":"Patel Para",
    "wof:placetype":"locality",
    "wof:population":232
},
  "geometry": {"coordinates":[81.369101,19.704382],"type":"Point"}
}