{
  "type": "Feature",
  "properties": {
    "gn:admin1_code":"37",
    "gn:admin2_code":"406.0",
    "gn:asciiname":"Barpali",
    "gn:country_code":"IN",
    "gn:dem":348,
    "gn:feature_class":"P",
    "gn:feature_code":"PPL",
    "gn:name":"Barp\u0101li",
    "gn:population":0,
    "gn:timezone":"Asia/Kolkata",
    "iso:country":"IN",
    "ks:ks_alt_nam":"Barp\u0101li",
    "ks:ks_name":"Barpali",
    "ks:ks_type":"VILLAGE",
    "name:eng_x_preferred":[
        "Barpali"
    ],
    "name:eng_x_variant":[
        "Barp\u0101li"
    ],
    "wof:name":"Barpali",
    "wof:placetype":"locality"
},
  "geometry": {"coordinates":[82.050985,22.522225],"type":"Point"}
}