{
  "type": "Feature",
  "properties": {
    "iso:country":"IN",
    "ks:ks_name":"Champajhar",
    "ks:ks_pop":1131,
    "ks:ks_type":"VILLAGE",
    "name:eng_x_preferred":[
        "Champajhar"
    ],
    "wof:name":"Champajhar",
    "wof:placetype":"locality",
    "wof:population":1131
},
  "geometry": {"coordinates":[82.650121,23.318479],"type":"Point"}
}