{
  "type": "Feature",
  "properties": {
    "gn:admin1_code":"35",
    "gn:admin2_code":"459.0",
    "gn:asciiname":"Paharpur",
    "gn:country_code":"IN",
    "gn:dem":359,
    "gn:feature_class":"P",
    "gn:feature_code":"PPL",
    "gn:name":"Pah\u0101rpur",
    "gn:population":0,
    "gn:timezone":"Asia/Kolkata",
    "iso:country":"IN",
    "ks:ks_name":"Pahadpur",
    "ks:ks_pop":266,
    "ks:ks_type":"VILLAGE",
    "name:ben_x_preferred":[
        "\u09aa\u09be\u09b9\u09be\u09a1\u09bc\u09aa\u09c1\u09b0"
    ],
    "name:ceb_x_preferred":[
        "Paharpur"
    ],
    "name:eng_x_preferred":[
        "Pahadpur"
    ],
    "name:eng_x_variant":[
        "Paharpur"
    ],
    "name:nld_x_preferred":[
        "Paharpur"
    ],
    "wof:name":"Pahadpur",
    "wof:placetype":"locality",
    "wof:population":266
},
  "geometry": {"coordinates":[78.088842,24.837646],"type":"Point"}
}