{
  "type": "Feature",
  "properties": {
    "iso:country":"IN",
    "ks:ks_name":"Setlabettu",
    "ks:ks_pop":250,
    "ks:ks_type":"HABITATION",
    "name:eng_x_preferred":[
        "Setlabettu"
    ],
    "wof:name":"Setlabettu",
    "wof:placetype":"locality",
    "wof:population":250
},
  "geometry": {"coordinates":[75.089623,13.148721],"type":"Point"}
}