{
  "type": "Feature",
  "properties": {
    "iso:country":"IN",
    "ks:ks_name":"Korowaya",
    "ks:ks_pop":84,
    "ks:ks_type":"HABITATION",
    "name:eng_x_preferred":[
        "Korowaya"
    ],
    "wof:name":"Korowaya",
    "wof:placetype":"locality",
    "wof:population":84
},
  "geometry": {"coordinates":[80.978331,19.456304],"type":"Point"}
}