{
  "type": "Feature",
  "properties": {
    "iso:country":"IN",
    "ks:ks_name":"Rupsing",
    "ks:ks_pop":2514,
    "ks:ks_type":"VILLAGE",
    "ks:ks_uagg_main":0,
    "name:eng_x_preferred":[
        "Rupsing"
    ],
    "wof:name":"Rupsing",
    "wof:placetype":"locality",
    "wof:population":2514
},
  "geometry": {"coordinates":[88.33996399999999,26.706345],"type":"Point"}
}