{
  "type": "Feature",
  "properties": {
    "gn:admin1_code":"36",
    "gn:admin2_code":"188.0",
    "gn:asciiname":"Raji",
    "gn:country_code":"IN",
    "gn:dem":88,
    "gn:feature_class":"P",
    "gn:feature_code":"PPL",
    "gn:name":"R\u0101ji",
    "gn:population":0,
    "gn:timezone":"Asia/Kolkata",
    "iso:country":"IN",
    "name:ind_x_preferred":[
        "Raji"
    ],
    "wof:name":"Raji",
    "wof:placetype":"locality"
},
  "geometry": {"coordinates":[83.37876,26.94953],"type":"Point"}
}