{
  "type": "Feature",
  "properties": {
    "iso:country":"IN",
    "ks:ks_name":"Khaspara",
    "ks:ks_pop":148,
    "ks:ks_type":"HABITATION",
    "name:eng_x_preferred":[
        "Khaspara"
    ],
    "wof:name":"Khaspara",
    "wof:placetype":"locality",
    "wof:population":148
},
  "geometry": {"coordinates":[81.804407,19.853902],"type":"Point"}
}