{
  "type": "Feature",
  "properties": {
    "gn:admin1_code":"21.0",
    "gn:admin2_code":"398.0",
    "gn:asciiname":"Baghoraguda",
    "gn:country_code":"IN",
    "gn:dem":783,
    "gn:feature_class":"P",
    "gn:feature_code":"PPL",
    "gn:name":"B\u0101ghor\u0101guda",
    "gn:population":0,
    "gn:timezone":"Asia/Kolkata",
    "iso:country":"IN",
    "wof:name":"Baghoraguda",
    "wof:placetype":"locality"
},
  "geometry": {"coordinates":[82.75579999999999,18.83221],"type":"Point"}
}