{
  "type": "Feature",
  "properties": {
    "gn:admin1_code":"37",
    "gn:admin2_code":"410.0",
    "gn:asciiname":"Chapa",
    "gn:country_code":"IN",
    "gn:dem":288,
    "gn:feature_class":"P",
    "gn:feature_code":"PPL",
    "gn:name":"Ch\u0101pa",
    "gn:population":0,
    "gn:timezone":"Asia/Kolkata",
    "iso:country":"IN",
    "name:ceb_x_preferred":[
        "Chapa"
    ],
    "name:deu_x_preferred":[
        "Chapa"
    ],
    "name:glg_x_preferred":[
        "Chapa"
    ],
    "name:nld_x_preferred":[
        "Chapa"
    ],
    "name:por_x_preferred":[
        "Chapa"
    ],
    "name:swe_x_preferred":[
        "Chapa"
    ],
    "wof:name":"Chapa",
    "wof:placetype":"locality"
},
  "geometry": {"coordinates":[81.86816,21.56578],"type":"Point"}
}