{
  "type": "Feature",
  "properties": {
    "iso:country":"IN",
    "ks:ks_name":"Konanakatte",
    "ks:ks_pop":30,
    "ks:ks_type":"HABITATION",
    "name:eng_x_preferred":[
        "Konanakatte"
    ],
    "wof:name":"Konanakatte",
    "wof:placetype":"locality",
    "wof:population":30
},
  "geometry": {"coordinates":[74.860383,14.398774],"type":"Point"}
}