{
  "type": "Feature",
  "properties": {
    "gn:admin1_code":"13.0",
    "gn:admin2_code":"590.0",
    "gn:asciiname":"Irintanattur",
    "gn:country_code":"IN",
    "gn:dem":789,
    "gn:feature_class":"P",
    "gn:feature_code":"PPL",
    "gn:name":"Irintanatt\u016br",
    "gn:population":0,
    "gn:timezone":"Asia/Kolkata",
    "iso:country":"IN",
    "wof:name":"Irintanattur",
    "wof:placetype":"locality"
},
  "geometry": {"coordinates":[75.86126999999998,11.79628],"type":"Point"}
}