{
  "type": "Feature",
  "properties": {
    "iso:country":"IN",
    "ks:ks_name":"Gailwara Khas",
    "ks:ks_pop":1504,
    "ks:ks_type":"VILLAGE",
    "name:eng_x_preferred":[
        "Gailwara Khas"
    ],
    "wof:name":"Gailwara Khas",
    "wof:placetype":"locality",
    "wof:population":1504
},
  "geometry": {"coordinates":[78.804907,25.208284],"type":"Point"}
}