{
  "type": "Feature",
  "properties": {
    "gn:admin1_code":"36.0",
    "gn:admin2_code":"140.0",
    "gn:asciiname":"Patla",
    "gn:country_code":"IN",
    "gn:dem":226,
    "gn:feature_class":"P",
    "gn:feature_code":"PPL",
    "gn:name":"Patla",
    "gn:population":0,
    "gn:timezone":"Asia/Kolkata",
    "iso:country":"IN",
    "name:mal_x_preferred":[
        "\u0d2a\u0d1f\u0d4d\u200c\u0d33"
    ],
    "wof:name":"Patla",
    "wof:placetype":"locality"
},
  "geometry": {"coordinates":[77.50100999999999,28.88658],"type":"Point"}
}