{
  "type": "Feature",
  "properties": {
    "gn:country":"IN",
    "gn:fcode":"PPL",
    "gn:pop":15073,
    "iso:country":"IN",
    "name:bpy_x_preferred":[
        "\u09ae\u09be\u09a8\u09cd\u09a1\u09aa\u09ae"
    ],
    "name:bul_x_preferred":[
        "\u041c\u0430\u043d\u0434\u0430\u043f\u0430\u043c"
    ],
    "name:ceb_x_preferred":[
        "Mandapam"
    ],
    "name:eng_x_preferred":[
        "Mandapam"
    ],
    "name:fra_x_preferred":[
        "Mandapam"
    ],
    "name:hin_x_preferred":[
        "\u092e\u0928\u094d\u0926\u092a\u092e"
    ],
    "name:ita_x_preferred":[
        "Mandapam"
    ],
    "name:msa_x_preferred":[
        "Mandapam"
    ],
    "name:nan_x_preferred":[
        "Mandapam"
    ],
    "name:new_x_preferred":[
        "\u092e\u0928\u094d\u0926\u092a\u092e"
    ],
    "name:nld_x_preferred":[
        "Mandapam"
    ],
    "name:nob_x_preferred":[
        "Mandapam"
    ],
    "name:por_x_preferred":[
        "Mandapam"
    ],
    "name:swe_x_preferred":[
        "Mandapam"
    ],
    "name:tam_x_preferred":[
        "\u0bae\u0ba3\u0bcd\u0b9f\u0baa\u0bae\u0bcd"
    ],
    "name:vie_x_preferred":[
        "Mandapam"
    ],
    "name:zho_x_preferred":[
        "\u66fc\u8fbe\u5e15\u59c6"
    ],
    "qs:name":"Mandapam",
    "qs:photos_9r":0,
    "qs:photos_sr":0,
    "qs:pop_sr":"6",
    "wd:wordcount":198,
    "wof:name":"Mandapam",
    "wof:placetype":"locality",
    "wof:population":15073
},
  "geometry": {"coordinates":[79.12362,9.27571],"type":"Point"}
}