{
  "type": "Feature",
  "properties": {
    "iso:country":"IN",
    "ks:ks_name":"Lavar Falia",
    "ks:ks_pop":620,
    "ks:ks_type":"HABITATION",
    "name:eng_x_preferred":[
        "Lavar Falia"
    ],
    "wof:name":"Lavar Falia",
    "wof:placetype":"locality",
    "wof:population":620
},
  "geometry": {"coordinates":[73.82938300000001,22.771433],"type":"Point"}
}