{
  "type": "Feature",
  "properties": {
    "gn:admin1_code":"19.0",
    "gn:admin2_code":"555",
    "gn:asciiname":"Jamboti",
    "gn:country_code":"IN",
    "gn:dem":849,
    "gn:feature_class":"P",
    "gn:feature_code":"PPL",
    "gn:name":"J\u0101mboti",
    "gn:population":0,
    "gn:timezone":"Asia/Kolkata",
    "iso:country":"IN",
    "name:und_x_variant":[
        "J\u0101mboti"
    ],
    "wof:name":"Jamboti",
    "wof:placetype":"locality"
},
  "geometry": {"coordinates":[74.36814,15.69037],"type":"Point"}
}