{
  "type": "Feature",
  "properties": {
    "gn:admin1_code":"13.0",
    "gn:admin2_code":"590.0",
    "gn:asciiname":"Varakolli",
    "gn:country_code":"IN",
    "gn:dem":764,
    "gn:feature_class":"P",
    "gn:feature_code":"PPL",
    "gn:name":"Varakolli",
    "gn:population":0,
    "gn:timezone":"Asia/Kolkata",
    "iso:country":"IN",
    "wof:name":"Varakolli",
    "wof:placetype":"locality"
},
  "geometry": {"coordinates":[76.17249,11.61105],"type":"Point"}
}