{
  "type": "Feature",
  "properties": {
    "iso:country":"IN",
    "ks:ks_name":"Tiravade Tarf Kharepatan",
    "ks:ks_pop":1019,
    "ks:ks_type":"VILLAGE",
    "name:eng_x_preferred":[
        "Tiravade Tarf Kharepatan"
    ],
    "wof:name":"Tiravade Tarf Kharepatan",
    "wof:placetype":"locality",
    "wof:population":1019
},
  "geometry": {"coordinates":[73.78187699999999,16.554605],"type":"Point"}
}