{
  "type": "Feature",
  "properties": {
    "iso:country":"IN",
    "ks:ks_name":"Kheta",
    "ks:ks_pop":30,
    "ks:ks_type":"HABITATION",
    "name:eng_x_preferred":[
        "Kheta"
    ],
    "wof:name":"Kheta",
    "wof:placetype":"locality",
    "wof:population":30
},
  "geometry": {"coordinates":[80.177623,30.022761],"type":"Point"}
}