{
  "type": "Feature",
  "properties": {
    "iso:country":"IN",
    "ks:ks_alt_nam":"KhadauliKhaspara",
    "ks:ks_name":"Khadaulikhaspara",
    "ks:ks_pop":300,
    "ks:ks_type":"HABITATION",
    "name:eng_x_preferred":[
        "Khadaulikhaspara"
    ],
    "wof:name":"Khadaulikhaspara",
    "wof:placetype":"locality",
    "wof:population":300
},
  "geometry": {"coordinates":[83.01739499999999,23.468842],"type":"Point"}
}