{
  "type": "Feature",
  "properties": {
    "iso:country":"IN",
    "ks:ks_name":"Dube Chak",
    "ks:ks_type":"VILLAGE",
    "name:eng_x_preferred":[
        "Dube Chak"
    ],
    "wof:name":"Dube Chak",
    "wof:placetype":"locality"
},
  "geometry": {"coordinates":[83.47641299999999,25.345418],"type":"Point"}
}