{
  "type": "Feature",
  "properties": {
    "gn:admin1_code":"36.0",
    "gn:admin2_code":"185.0",
    "gn:asciiname":"Daridiha",
    "gn:country_code":"IN",
    "gn:dem":91,
    "gn:feature_class":"P",
    "gn:feature_code":"PPL",
    "gn:name":"Darid\u012bha",
    "gn:population":0,
    "gn:timezone":"Asia/Kolkata",
    "iso:country":"IN",
    "ks:ks_alt_nam":"Darid\u012bha",
    "ks:ks_name":"Daridiha",
    "ks:ks_type":"VILLAGE",
    "ks:ks_uagg_main":0,
    "name:eng_x_preferred":[
        "Daridiha"
    ],
    "name:eng_x_variant":[
        "Darid\u012bha"
    ],
    "wof:name":"Daridiha",
    "wof:placetype":"neighbourhood"
},
  "geometry": {"coordinates":[82.817632,27.04779],"type":"Point"}
}