{
  "type": "Feature",
  "properties": {
    "iso:country":"IN",
    "ks:ks_name":"Midaddu",
    "ks:ks_pop":310,
    "ks:ks_type":"HABITATION",
    "name:eng_x_preferred":[
        "Midaddu"
    ],
    "wof:name":"Midaddu",
    "wof:placetype":"locality",
    "wof:population":310
},
  "geometry": {"coordinates":[74.856413,13.195166],"type":"Point"}
}