{
  "type": "Feature",
  "properties": {
    "gn:admin1_code":"9.0",
    "gn:admin2_code":"480",
    "gn:asciiname":"Kotra Pitha",
    "gn:country_code":"IN",
    "gn:dem":203,
    "gn:feature_class":"P",
    "gn:feature_code":"PPL",
    "gn:name":"Kotra Pitha",
    "gn:population":0,
    "gn:timezone":"Asia/Kolkata",
    "iso:country":"IN",
    "name:und_x_variant":[
        "Kotra Pita",
        "Kotra Pitha"
    ],
    "wof:name":"Kotra Pitha",
    "wof:placetype":"locality"
},
  "geometry": {"coordinates":[71.20397,21.95636],"type":"Point"}
}