{
  "type": "Feature",
  "properties": {
    "gn:admin1_code":"38",
    "gn:admin2_code":"346.0",
    "gn:asciiname":"Besri",
    "gn:country_code":"IN",
    "gn:dem":476,
    "gn:feature_class":"P",
    "gn:feature_code":"PPL",
    "gn:name":"Besri",
    "gn:population":0,
    "gn:timezone":"Asia/Kolkata",
    "iso:country":"IN",
    "name:und_x_variant":[
        "Besrikh\u0101r\u012b"
    ],
    "wof:name":"Besri",
    "wof:placetype":"locality"
},
  "geometry": {"coordinates":[83.61364,23.951],"type":"Point"}
}