{
  "type": "Feature",
  "properties": {
    "iso:country":"IN",
    "ks:ks_name":"Ambrathapali",
    "ks:ks_pop":123,
    "ks:ks_type":"HABITATION",
    "name:eng_x_preferred":[
        "Ambrathapali"
    ],
    "wof:name":"Ambrathapali",
    "wof:placetype":"locality",
    "wof:population":123
},
  "geometry": {"coordinates":[74.491243,15.176661],"type":"Point"}
}