{
  "type": "Feature",
  "properties": {
    "gn:admin1_code":"35.0",
    "gn:admin2_code":"427.0",
    "gn:asciiname":"Bamhori",
    "gn:country_code":"IN",
    "gn:dem":538,
    "gn:feature_class":"P",
    "gn:feature_code":"PPL",
    "gn:name":"Bamhori",
    "gn:population":0,
    "gn:timezone":"Asia/Kolkata",
    "iso:country":"IN",
    "ks:ks_name":"Bamhori",
    "ks:ks_pop":238,
    "ks:ks_type":"VILLAGE",
    "ks:ks_uagg_main":0,
    "name:eng_x_preferred":[
        "Bamhori"
    ],
    "wof:name":"Bamhori",
    "wof:placetype":"neighbourhood",
    "wof:population":238
},
  "geometry": {"coordinates":[78.73813199999999,23.662073],"type":"Point"}
}