{
  "type": "Feature",
  "properties": {
    "iso:country":"IN",
    "ks:ks_alt_nam":"bonthai colony",
    "ks:ks_name":"Bonthai Colony",
    "ks:ks_pop":100,
    "ks:ks_type":"HABITATION",
    "name:eng_x_preferred":[
        "Bonthai Colony"
    ],
    "wof:name":"Bonthai Colony",
    "wof:placetype":"locality",
    "wof:population":100
},
  "geometry": {"coordinates":[79.50294,12.324516],"type":"Point"}
}