{
  "type": "Feature",
  "properties": {
    "iso:country":"IN",
    "ks:ks_name":"Dongpara",
    "ks:ks_pop":47,
    "ks:ks_type":"HABITATION",
    "name:eng_x_preferred":[
        "Dongpara"
    ],
    "wof:name":"Dongpara",
    "wof:placetype":"locality",
    "wof:population":47
},
  "geometry": {"coordinates":[81.71907,19.723228],"type":"Point"}
}