{
  "type": "Feature",
  "properties": {
    "gn:admin1_code":"19",
    "gn:admin2_code":"580.0",
    "gn:asciiname":"Gundahalli",
    "gn:country_code":"IN",
    "gn:dem":413,
    "gn:feature_class":"P",
    "gn:feature_code":"PPL",
    "gn:name":"Gundahalli",
    "gn:population":0,
    "gn:timezone":"Asia/Kolkata",
    "iso:country":"IN",
    "wof:name":"Gundahalli",
    "wof:placetype":"locality"
},
  "geometry": {"coordinates":[76.96679,16.72957],"type":"Point"}
}