{
  "type": "Feature",
  "properties": {
    "gn:admin1_code":"2.0",
    "gn:admin2_code":"544.0",
    "gn:asciiname":"Malkarput",
    "gn:country_code":"IN",
    "gn:dem":944,
    "gn:feature_class":"P",
    "gn:feature_code":"PPL",
    "gn:name":"Malkarput",
    "gn:population":0,
    "gn:timezone":"Asia/Kolkata",
    "iso:country":"IN",
    "wof:name":"Malkarput",
    "wof:placetype":"locality"
},
  "geometry": {"coordinates":[82.59059999999999,18.12817],"type":"Point"}
}