{
  "type": "Feature",
  "properties": {
    "gn:admin1_code":"36.0",
    "gn:admin2_code":"143.0",
    "gn:asciiname":"Haranpur",
    "gn:country_code":"IN",
    "gn:dem":182,
    "gn:feature_class":"P",
    "gn:feature_code":"PPL",
    "gn:name":"H\u0101ranpur",
    "gn:population":0,
    "gn:timezone":"Asia/Kolkata",
    "iso:country":"IN",
    "name:fas_x_preferred":[
        "\u0647\u0631\u0646\u200c\u067e\u0648\u0631"
    ],
    "name:urd_x_preferred":[
        "\u06c1\u0631\u0646 \u067e\u0648\u0631"
    ],
    "wof:name":"Haranpur",
    "wof:placetype":"locality"
},
  "geometry": {"coordinates":[78.5209,28.0351],"type":"Point"}
}