{
  "type": "Feature",
  "properties": {
    "iso:country":"IN",
    "ks:ks_alt_nam":"BHUTRI RESERVE FOREST NORTH",
    "ks:ks_name":"Bhutri Reserve Forest North",
    "ks:ks_pop":544,
    "ks:ks_type":"HABITATION",
    "name:eng_x_preferred":[
        "Bhutri Reserve Forest North"
    ],
    "wof:name":"Bhutri Reserve Forest North",
    "wof:placetype":"locality",
    "wof:population":544
},
  "geometry": {"coordinates":[89.433052,26.779753],"type":"Point"}
}