{
  "type": "Feature",
  "properties": {
    "gn:admin1_code":"19.0",
    "gn:admin2_code":"564.0",
    "gn:asciiname":"Hospet",
    "gn:country_code":"IN",
    "gn:dem":617,
    "gn:feature_class":"P",
    "gn:feature_code":"PPL",
    "gn:name":"Hospet",
    "gn:population":0,
    "gn:timezone":"Asia/Kolkata",
    "iso:country":"IN",
    "name:ben_x_preferred":[
        "\u09b9\u09cb\u09b8\u09aa\u09c7\u09a4"
    ],
    "name:bih_x_preferred":[
        "\u0939\u094b\u0938\u092a\u0947\u091f"
    ],
    "name:bpy_x_preferred":[
        "\u09b9\u09cb\u09b8\u09aa\u09c7\u09a4"
    ],
    "name:cat_x_preferred":[
        "Hosapete"
    ],
    "name:ceb_x_preferred":[
        "Hospet"
    ],
    "name:deu_x_preferred":[
        "Hospet"
    ],
    "name:fas_x_preferred":[
        "\u0647\u0648\u0633\u067e\u062a"
    ],
    "name:fra_x_preferred":[
        "Hospet"
    ],
    "name:hun_x_preferred":[
        "Hoszpet"
    ],
    "name:ita_x_preferred":[
        "Hospet"
    ],
    "name:kan_x_preferred":[
        "\u0cb9\u0cca\u0cb8\u0caa\u0cc7\u0c9f\u0cc6"
    ],
    "name:mar_x_preferred":[
        "\u0939\u094b\u0938\u094d\u092a\u0947\u091f"
    ],
    "name:mlg_x_preferred":[
        "Hospet"
    ],
    "name:msa_x_preferred":[
        "Hospet"
    ],
    "name:new_x_preferred":[
        "\u0939\u094b\u0938\u094d\u092a\u0947\u091f"
    ],
    "name:nld_x_preferred":[
        "Hospet"
    ],
    "name:pnb_x_preferred":[
        "\u06c1\u0648\u0633\u067e\u0679"
    ],
    "name:pol_x_preferred":[
        "Hospet"
    ],
    "name:san_x_preferred":[
        "\u0939\u094b\u0938\u092a\u0947\u091f\u0947"
    ],
    "name:spa_x_preferred":[
        "Hospet"
    ],
    "name:srp_x_preferred":[
        "\u0425\u043e\u0441\u043f\u0435\u0442"
    ],
    "name:swe_x_preferred":[
        "Hosapete"
    ],
    "name:tam_x_preferred":[
        "\u0bb9\u0bcb\u0bb8\u0bcd\u0baa\u0bc7\u0b9f\u0bcd"
    ],
    "name:vie_x_preferred":[
        "Hospet"
    ],
    "name:war_x_preferred":[
        "Hospet"
    ],
    "name:zho_x_preferred":[
        "\u970d\u65af\u4f69\u7279"
    ],
    "wof:name":"Hospet",
    "wof:placetype":"locality"
},
  "geometry": {"coordinates":[75.17054,14.88665],"type":"Point"}
}