{
  "type": "Feature",
  "properties": {
    "iso:country":"IN",
    "ks:ks_name":"Bin Tola.",
    "ks:ks_pop":335,
    "ks:ks_type":"HABITATION",
    "name:eng_x_preferred":[
        "Bin Tola."
    ],
    "wof:name":"Bin Tola.",
    "wof:placetype":"locality",
    "wof:population":335
},
  "geometry": {"coordinates":[86.770702,25.779714],"type":"Point"}
}