{
  "type": "Feature",
  "properties": {
    "iso:country":"IN",
    "ks:ks_name":"Edavachal",
    "ks:ks_pop":235,
    "ks:ks_type":"HABITATION",
    "name:eng_x_preferred":[
        "Edavachal"
    ],
    "wof:name":"Edavachal",
    "wof:placetype":"locality",
    "wof:population":235
},
  "geometry": {"coordinates":[77.156901,8.40135],"type":"Point"}
}