{
  "type": "Feature",
  "properties": {
    "gn:admin1_code":"35",
    "gn:admin2_code":"455.0",
    "gn:asciiname":"Jobnala",
    "gn:country_code":"IN",
    "gn:dem":730,
    "gn:feature_class":"P",
    "gn:feature_code":"PPL",
    "gn:name":"Jobn\u0101la",
    "gn:population":0,
    "gn:timezone":"Asia/Kolkata",
    "iso:country":"IN",
    "ks:ks_alt_nam":"Jobn\u0101la",
    "ks:ks_name":"Jobnala",
    "ks:ks_type":"VILLAGE",
    "name:eng_x_preferred":[
        "Jobnala"
    ],
    "name:eng_x_variant":[
        "Jobn\u0101la"
    ],
    "wof:name":"Jobnala",
    "wof:placetype":"locality"
},
  "geometry": {"coordinates":[79.000837,22.259451],"type":"Point"}
}