{
  "type": "Feature",
  "properties": {
    "gn:country":"IN",
    "gn:fcode":"PPL",
    "gn:population":20424,
    "iso:country":"IN",
    "name:ast_x_preferred":[
        "Nimaj"
    ],
    "name:azb_x_preferred":[
        "\u0646\u06cc\u0645\u0627\u062c"
    ],
    "name:ben_x_preferred":[
        "\u09a8\u09bf\u09ae\u09be\u099c"
    ],
    "name:ceb_x_preferred":[
        "Nimb\u0101j"
    ],
    "name:eng_x_preferred":[
        "Nimaj"
    ],
    "name:hin_x_preferred":[
        "\u0928\u093f\u092e\u093e\u091c"
    ],
    "name:nld_x_preferred":[
        "Nimaj"
    ],
    "name:swe_x_preferred":[
        "Nimb\u0101j"
    ],
    "name:und_x_variant":[
        "N\u012bm\u0101j"
    ],
    "qs:name":"Nimb\u0101j",
    "qs:photos_9r":0,
    "qs:photos_sr":0,
    "qs:pop_sr":"7",
    "wd:elevation":315.0,
    "wd:wordcount":309,
    "wof:name":"Nimb\u0101j",
    "wof:placetype":"locality",
    "wof:population":20424
},
  "geometry": {"coordinates":[74.00152,26.15006],"type":"Point"}
}