{
  "type": "Feature",
  "properties": {
    "gn:country":"IN",
    "gn:fcode":"PPL",
    "gn:pop":20424,
    "iso:country":"IN",
    "name:dut_x_preferred":[
        "Nimaj"
    ],
    "name:eng_x_preferred":[
        "Nimaj"
    ],
    "name:hin_x_preferred":[
        "\u0928\u093f\u092e\u093e\u091c"
    ],
    "name:swe_x_preferred":[
        "Nimb\u0101j"
    ],
    "name:unk_x_variant":[
        "N\u012bm\u0101j"
    ],
    "qs:name":"Nimb\u0101j",
    "qs:photos_9r":0,
    "qs:photos_sr":0,
    "qs:pop_sr":"7",
    "wd:elevation":315.0,
    "wd:wordcount":309,
    "wof:name":"Nimb\u0101j",
    "wof:placetype":"locality",
    "wof:population":20424
},
  "geometry": {"coordinates":[74.00152,26.15006],"type":"Point"}
}