{
  "type": "Feature",
  "properties": {
    "gn:admin1_code":"39.0",
    "gn:admin2_code":"64.0",
    "gn:asciiname":"Shali",
    "gn:country_code":"IN",
    "gn:dem":1346,
    "gn:feature_class":"P",
    "gn:feature_code":"PPL",
    "gn:name":"Sh\u0101li",
    "gn:population":0,
    "gn:timezone":"Asia/Kolkata",
    "iso:country":"IN",
    "name:bel_x_preferred":[
        "\u0428\u0430\u043b\u0456"
    ],
    "name:ceb_x_preferred":[
        "Shali"
    ],
    "name:rus_x_preferred":[
        "\u0428\u0430\u043b\u0438"
    ],
    "name:swe_x_preferred":[
        "Shali"
    ],
    "name:tgl_x_preferred":[
        "Shali"
    ],
    "name:tur_x_preferred":[
        "\u015eali"
    ],
    "name:ukr_x_preferred":[
        "\u0428\u0430\u043b\u0456"
    ],
    "wof:name":"Shali",
    "wof:placetype":"locality"
},
  "geometry": {"coordinates":[79.6336,29.6128],"type":"Point"}
}