{
  "type": "Feature",
  "properties": {
    "iso:country":"IN",
    "ks:ks_name":"Mohitewadi",
    "ks:ks_pop":190,
    "ks:ks_type":"HABITATION",
    "name:eng_x_preferred":[
        "Mohitewadi"
    ],
    "wof:name":"Mohitewadi",
    "wof:placetype":"locality",
    "wof:population":190
},
  "geometry": {"coordinates":[73.692753,16.94728],"type":"Point"}
}