{
  "type": "Feature",
  "properties": {
    "gn:country":"IN",
    "gn:fcode":"PPL",
    "gn:population":0,
    "iso:country":"IN",
    "ks:ks_alt_nam":"Madh\u0101pur",
    "ks:ks_name":"Madhapur",
    "ks:ks_type":"VILLAGE",
    "ks:ks_uagg_main":0,
    "name:eng_x_preferred":[
        "Madhapur"
    ],
    "name:jpn_x_preferred":[
        "\u30de\u30c0\u30d7\u30fc\u30eb"
    ],
    "name:kan_x_preferred":[
        "\u0cae\u0cbe\u0ca7\u0cbe\u0caa\u0cc1\u0cb0"
    ],
    "name:nld_x_preferred":[
        "Madhapur"
    ],
    "name:und_x_variant":[
        "Madh\u0101pur"
    ],
    "name:urd_x_preferred":[
        "\u0645\u062f\u06be\u0627\u067e\u0648\u0631"
    ],
    "qs:name":"Madhapur",
    "qs:name_adm0":"India",
    "qs:name_adm1":"Andhra Pradesh",
    "qs:photos_9k":1,
    "qs:photos_9r":1,
    "qs:photos_all":2,
    "qs:photos_sr":0,
    "qs:placetype":"Town",
    "qs:pop_sr":"0",
    "wd:wordcount":543,
    "wof:name":"Madhapur",
    "wof:placetype":"neighbourhood",
    "wof:population":0
},
  "geometry": {"coordinates":[78.38849,17.44106],"type":"Point"}
}