{
  "type": "Feature",
  "properties": {
    "iso:country":"IN",
    "ks:ks_name":"Dhamri Gopalram",
    "ks:ks_pop":109,
    "ks:ks_type":"VILLAGE",
    "ks:ks_uagg_main":0,
    "name:eng_x_preferred":[
        "Dhamri Gopalram"
    ],
    "wof:name":"Dhamri Gopalram",
    "wof:placetype":"neighbourhood",
    "wof:population":109
},
  "geometry": {"coordinates":[87.391824,25.211465],"type":"Point"}
}