{
  "type": "Feature",
  "properties": {
    "iso:country":"IN",
    "ks:ks_name":"Rupaupur",
    "ks:ks_pop":325,
    "ks:ks_type":"HABITATION",
    "name:eng_x_preferred":[
        "Rupaupur"
    ],
    "wof:name":"Rupaupur",
    "wof:placetype":"locality",
    "wof:population":325
},
  "geometry": {"coordinates":[82.854878,26.663409],"type":"Point"}
}