{
  "type": "Feature",
  "properties": {
    "iso:country":"IN",
    "ks:ks_name":"Thazhathangadi Jn",
    "ks:ks_pop":749,
    "ks:ks_type":"HABITATION",
    "name:eng_x_preferred":[
        "Thazhathangadi Jn"
    ],
    "wof:name":"Thazhathangadi Jn",
    "wof:placetype":"locality",
    "wof:population":749
},
  "geometry": {"coordinates":[76.04602199999999,11.24054],"type":"Point"}
}