{
  "type": "Feature",
  "properties": {
    "gn:admin1_code":"40.0",
    "gn:admin2_code":"533.0",
    "gn:asciiname":"Yellamkunta",
    "gn:country_code":"IN",
    "gn:dem":543,
    "gn:feature_class":"P",
    "gn:feature_code":"PPL",
    "gn:name":"Yellamkunta",
    "gn:population":0,
    "gn:timezone":"Asia/Kolkata",
    "iso:country":"IN",
    "wof:name":"Yellamkunta",
    "wof:placetype":"locality"
},
  "geometry": {"coordinates":[78.16384000000002,18.49566],"type":"Point"}
}