{
  "type": "Feature",
  "properties": {
    "gn:admin1_code":"2",
    "gn:admin2_code":"545.0",
    "gn:asciiname":"Peddavadisakarra",
    "gn:country_code":"IN",
    "gn:dem":276,
    "gn:feature_class":"P",
    "gn:feature_code":"PPL",
    "gn:name":"Peddavadisakarra",
    "gn:population":0,
    "gn:timezone":"Asia/Kolkata",
    "iso:country":"IN",
    "ks:ks_name":"Peddavadisakarra",
    "ks:ks_type":"VILLAGE",
    "name:eng_x_preferred":[
        "Peddavadisakarra"
    ],
    "wof:name":"Peddavadisakarra",
    "wof:placetype":"locality"
},
  "geometry": {"coordinates":[82.00955999999999,17.601991],"type":"Point"}
}