{
  "type": "Feature",
  "properties": {
    "iso:country":"IN",
    "ks:ks_name":"Chichali Falia",
    "ks:ks_pop":52,
    "ks:ks_type":"HABITATION",
    "name:eng_x_preferred":[
        "Chichali Falia"
    ],
    "wof:name":"Chichali Falia",
    "wof:placetype":"locality",
    "wof:population":52
},
  "geometry": {"coordinates":[73.173333,20.317167],"type":"Point"}
}