{
  "type": "Feature",
  "properties": {
    "gn:admin1_code":"19.0",
    "gn:admin2_code":"583.0",
    "gn:asciiname":"Hoshalli",
    "gn:country_code":"IN",
    "gn:dem":880,
    "gn:feature_class":"P",
    "gn:feature_code":"PPL",
    "gn:name":"Hoshalli",
    "gn:population":0,
    "gn:timezone":"Asia/Kolkata",
    "iso:country":"IN",
    "wof:name":"Hoshalli",
    "wof:placetype":"locality"
},
  "geometry": {"coordinates":[77.74930000000001,13.19825],"type":"Point"}
}