{
  "type": "Feature",
  "properties": {
    "iso:country":"IN",
    "ks:ks_name":"Perumadu",
    "ks:ks_pop":58,
    "ks:ks_type":"HABITATION",
    "name:eng_x_preferred":[
        "Perumadu"
    ],
    "wof:name":"Perumadu",
    "wof:placetype":"locality",
    "wof:population":58
},
  "geometry": {"coordinates":[75.348069,12.699733],"type":"Point"}
}