{
  "type": "Feature",
  "properties": {
    "iso:country":"IN",
    "ks:ks_name":"Kalkodu",
    "ks:ks_pop":53,
    "ks:ks_type":"VILLAGE",
    "name:eng_x_preferred":[
        "Kalkodu"
    ],
    "wof:name":"Kalkodu",
    "wof:placetype":"locality",
    "wof:population":53
},
  "geometry": {"coordinates":[76.474462,12.217971],"type":"Point"}
}