{
  "type": "Feature",
  "properties": {
    "iso:country":"IN",
    "ks:ks_alt_nam":"S\u0101mola",
    "ks:ks_name":"Samola",
    "ks:ks_type":"VILLAGE",
    "ks:ks_uagg_main":0,
    "name:eng_x_preferred":[
        "Samola"
    ],
    "name:eng_x_variant":[
        "S\u0101mola"
    ],
    "wof:name":"Samola",
    "wof:placetype":"neighbourhood"
},
  "geometry": {"coordinates":[76.631764,27.537377],"type":"Point"}
}