{
  "type": "Feature",
  "properties": {
    "gn:admin1_code":"36",
    "gn:admin2_code":"134.0",
    "gn:asciiname":"Rahmanpur",
    "gn:country_code":"IN",
    "gn:dem":247,
    "gn:feature_class":"P",
    "gn:feature_code":"PPL",
    "gn:name":"Rahm\u0101npur",
    "gn:population":0,
    "gn:timezone":"Asia/Kolkata",
    "iso:country":"IN",
    "name:und_x_variant":[
        "Rahm\u0101npur",
        "Mauzampur Harbans"
    ],
    "wof:name":"Rahmanpur",
    "wof:placetype":"neighbourhood"
},
  "geometry": {"coordinates":[78.3323,29.43168],"type":"Point"}
}