{
  "type": "Feature",
  "properties": {
    "iso:country":"IN",
    "ks:ks_name":"Azampur Husainpur",
    "ks:ks_pop":1378,
    "ks:ks_type":"HABITATION",
    "name:eng_x_preferred":[
        "Azampur Husainpur"
    ],
    "wof:name":"Azampur Husainpur",
    "wof:placetype":"locality",
    "wof:population":1378
},
  "geometry": {"coordinates":[77.725094,28.334648],"type":"Point"}
}