{
  "type": "Feature",
  "properties": {
    "iso:country":"IN",
    "ks:ks_name":"Anaivadapathi",
    "ks:ks_pop":1004,
    "ks:ks_type":"VILLAGE",
    "ks:ks_uagg_main":0,
    "name:eng_x_preferred":[
        "Anaivadapathi"
    ],
    "wof:name":"Anaivadapathi",
    "wof:placetype":"neighbourhood",
    "wof:population":1004
},
  "geometry": {"coordinates":[79.579179,10.78259],"type":"Point"}
}