{
  "type": "Feature",
  "properties": {
    "gn:admin1_code":"12.0",
    "gn:asciiname":"Sateni",
    "gn:country_code":"IN",
    "gn:dem":2851,
    "gn:feature_class":"P",
    "gn:feature_code":"PPL",
    "gn:name":"Sateni",
    "gn:population":0,
    "gn:timezone":"Asia/Kolkata",
    "iso:country":"IN",
    "wof:name":"Sateni",
    "wof:placetype":"locality"
},
  "geometry": {"coordinates":[75.01513,34.60416],"type":"Point"}
}