{
  "type": "Feature",
  "properties": {
    "gn:admin1_code":"16.0",
    "gn:admin2_code":"497",
    "gn:asciiname":"Borpada",
    "gn:country_code":"IN",
    "gn:dem":211,
    "gn:feature_class":"P",
    "gn:feature_code":"PPL",
    "gn:name":"Borp\u0101da",
    "gn:population":0,
    "gn:timezone":"Asia/Kolkata",
    "iso:country":"IN",
    "wof:name":"Borpada",
    "wof:placetype":"locality"
},
  "geometry": {"coordinates":[73.91755000000001,21.12703],"type":"Point"}
}