{
  "type": "Feature",
  "properties": {
    "gn:admin1_code":"40",
    "gn:admin2_code":"535.0",
    "gn:asciiname":"Tekmal",
    "gn:country_code":"IN",
    "gn:dem":494,
    "gn:feature_class":"P",
    "gn:feature_code":"PPL",
    "gn:name":"Tekm\u0101l",
    "gn:population":0,
    "gn:timezone":"Asia/Kolkata",
    "iso:country":"IN",
    "name:ceb_x_preferred":[
        "Tekm\u0101l"
    ],
    "name:new_x_preferred":[
        "\u091f\u0947\u0915\u094d\u092e\u0932\u094d \u092e\u0923\u094d\u0921\u0932"
    ],
    "name:swe_x_preferred":[
        "Tekm\u0101l"
    ],
    "name:tel_x_preferred":[
        "\u0c1f\u0c47\u0c15\u0c4d\u0c2e\u0c32\u0c4d"
    ],
    "name:und_x_variant":[
        "Tekm\u0101l"
    ],
    "wof:name":"Tekmal",
    "wof:placetype":"locality"
},
  "geometry": {"coordinates":[78.03659,17.97281],"type":"Point"}
}