{
  "type": "Feature",
  "properties": {
    "gn:admin1_code":"40",
    "gn:admin2_code":"535.0",
    "gn:asciiname":"Tekmal",
    "gn:country_code":"IN",
    "gn:dem":494,
    "gn:feature_class":"P",
    "gn:feature_code":"PPL",
    "gn:name":"Tekm\u0101l",
    "gn:population":0,
    "gn:timezone":"Asia/Kolkata",
    "iso:country":"IN",
    "name:und_x_variant":[
        "Tekm\u0101l"
    ],
    "wof:name":"Tekmal",
    "wof:placetype":"locality"
},
  "geometry": {"coordinates":[78.03659,17.97281],"type":"Point"}
}