{
  "type": "Feature",
  "properties": {
    "iso:country":"IN",
    "ks:ks_name":"Malakapura",
    "ks:ks_pop":3,
    "ks:ks_type":"HABITATION",
    "name:eng_x_preferred":[
        "Malakapura"
    ],
    "wof:name":"Malakapura",
    "wof:placetype":"locality",
    "wof:population":3
},
  "geometry": {"coordinates":[75.72924500000001,21.887347],"type":"Point"}
}