{
  "type": "Feature",
  "properties": {
    "iso:country":"IN",
    "ks:ks_name":"Uparla Tola",
    "ks:ks_pop":550,
    "ks:ks_type":"HABITATION",
    "name:eng_x_preferred":[
        "Uparla Tola"
    ],
    "wof:name":"Uparla Tola",
    "wof:placetype":"locality",
    "wof:population":550
},
  "geometry": {"coordinates":[83.483572,24.403913],"type":"Point"}
}