{
  "type": "Feature",
  "properties": {
    "iso:country":"IN",
    "ks:ks_alt_nam":"KHANDOBA VASTI",
    "ks:ks_name":"Khandoba Vasti",
    "ks:ks_pop":85,
    "ks:ks_type":"HABITATION",
    "name:eng_x_preferred":[
        "Khandoba Vasti"
    ],
    "wof:name":"Khandoba Vasti",
    "wof:placetype":"locality",
    "wof:population":85
},
  "geometry": {"coordinates":[74.78755,19.597133],"type":"Point"}
}