{
  "type": "Feature",
  "properties": {
    "gn:admin1_code":"36",
    "gn:admin2_code":"195.0",
    "gn:asciiname":"Dhawa",
    "gn:country_code":"IN",
    "gn:dem":75,
    "gn:feature_class":"P",
    "gn:feature_code":"PPL",
    "gn:name":"Dh\u0101wa",
    "gn:population":0,
    "gn:timezone":"Asia/Kolkata",
    "iso:country":"IN",
    "ks:ks_alt_nam":"Dh\u0101wa",
    "ks:ks_name":"Dhawa",
    "ks:ks_type":"VILLAGE",
    "name:ceb_x_preferred":[
        "Dhawa"
    ],
    "name:eng_x_preferred":[
        "Dhawa"
    ],
    "name:eng_x_variant":[
        "Dh\u0101wa"
    ],
    "name:mai_x_preferred":[
        "\u0927\u093e\u0935\u093e"
    ],
    "name:swe_x_preferred":[
        "Dhawa"
    ],
    "name:und_x_variant":[
        "Dh\u0101wa",
        "Muhammadpur",
        "Malikpura"
    ],
    "wof:name":"Dhawa",
    "wof:placetype":"locality"
},
  "geometry": {"coordinates":[83.46653000000001,25.621384],"type":"Point"}
}