{
  "type": "Feature",
  "properties": {
    "gn:admin1_code":"36",
    "gn:admin2_code":"195.0",
    "gn:asciiname":"Dhawa",
    "gn:country_code":"IN",
    "gn:dem":75,
    "gn:feature_class":"P",
    "gn:feature_code":"PPL",
    "gn:name":"Dh\u0101wa",
    "gn:population":0,
    "gn:timezone":"Asia/Kolkata",
    "iso:country":"IN",
    "name:und_x_variant":[
        "Dh\u0101wa",
        "Muhammadpur",
        "Malikpura"
    ],
    "wof:name":"Dhawa",
    "wof:placetype":"locality"
},
  "geometry": {"coordinates":[83.46653000000001,25.62138],"type":"Point"}
}