{
  "type": "Feature",
  "properties": {
    "iso:country":"IN",
    "ks:ks_name":"Koripur",
    "ks:ks_type":"VILLAGE",
    "name:eng_x_preferred":[
        "Koripur"
    ],
    "wof:name":"Koripur",
    "wof:placetype":"locality"
},
  "geometry": {"coordinates":[80.01196400000001,27.984154],"type":"Point"}
}