{
  "type": "Feature",
  "properties": {
    "iso:country":"IN",
    "ks:ks_name":"Atiabari Girda Adabari",
    "ks:ks_pop":454,
    "ks:ks_type":"VILLAGE",
    "name:eng_x_preferred":[
        "Atiabari Girda Adabari"
    ],
    "wof:name":"Atiabari Girda Adabari",
    "wof:placetype":"locality",
    "wof:population":454
},
  "geometry": {"coordinates":[89.30412699999999,26.138106],"type":"Point"}
}