{
  "type": "Feature",
  "properties": {
    "iso:country":"IN",
    "ks:ks_name":"Pauhar",
    "ks:ks_pop":581,
    "ks:ks_type":"VILLAGE",
    "ks:ks_uagg_main":0,
    "name:eng_x_preferred":[
        "Pauhar"
    ],
    "wof:name":"Pauhar",
    "wof:placetype":"neighbourhood",
    "wof:population":581
},
  "geometry": {"coordinates":[80.447748,26.198487],"type":"Point"}
}