{
  "type": "Feature",
  "properties": {
    "iso:country":"IN",
    "ks:ks_name":"Dhounrighora",
    "ks:ks_pop":144,
    "ks:ks_type":"VILLAGE",
    "name:eng_x_preferred":[
        "Dhounrighora"
    ],
    "wof:name":"Dhounrighora",
    "wof:placetype":"locality",
    "wof:population":144
},
  "geometry": {"coordinates":[78.73415300000001,29.91713],"type":"Point"}
}