{
  "type": "Feature",
  "properties": {
    "gn:admin1_code":"11",
    "gn:admin2_code":"27.0",
    "gn:asciiname":"Gharbasra",
    "gn:country_code":"IN",
    "gn:dem":1397,
    "gn:feature_class":"P",
    "gn:feature_code":"PPL",
    "gn:name":"Gharb\u0101sra",
    "gn:population":0,
    "gn:timezone":"Asia/Kolkata",
    "iso:country":"IN",
    "wof:name":"Gharbasra",
    "wof:placetype":"locality"
},
  "geometry": {"coordinates":[76.83664,31.55915],"type":"Point"}
}