{
  "type": "Feature",
  "properties": {
    "gn:admin1_code":"36.0",
    "gn:admin2_code":"141.0",
    "gn:asciiname":"Mirpur Kachh",
    "gn:country_code":"IN",
    "gn:dem":192,
    "gn:feature_class":"P",
    "gn:feature_code":"PPL",
    "gn:name":"M\u012brpur Kachh",
    "gn:population":0,
    "gn:timezone":"Asia/Kolkata",
    "iso:country":"IN",
    "name:und_x_variant":[
        "M\u012brpur Kachh",
        "K\u0101n\u012bgarhi"
    ],
    "wof:name":"Mirpur Kachh",
    "wof:placetype":"neighbourhood"
},
  "geometry": {"coordinates":[77.51412000000001,28.1322],"type":"Point"}
}