{
  "type": "Feature",
  "properties": {
    "iso:country":"IN",
    "ks:ks_name":"Mudiyani",
    "ks:ks_pop":947,
    "ks:ks_type":"VILLAGE",
    "ks:ks_uagg_main":0,
    "name:eng_x_preferred":[
        "Mudiyani"
    ],
    "wof:name":"Mudiyani",
    "wof:placetype":"neighbourhood",
    "wof:population":947
},
  "geometry": {"coordinates":[80.10004600000001,29.310993],"type":"Point"}
}