{
  "type": "Feature",
  "properties": {
    "iso:country":"IN",
    "ks:ks_name":"Fulewasti",
    "ks:ks_pop":265,
    "ks:ks_type":"HABITATION",
    "name:eng_x_preferred":[
        "Fulewasti"
    ],
    "wof:name":"Fulewasti",
    "wof:placetype":"locality",
    "wof:population":265
},
  "geometry": {"coordinates":[74.738975,17.951026],"type":"Point"}
}