{
  "type": "Feature",
  "properties": {
    "gn:admin1_code":"19",
    "gn:admin2_code":"563.0",
    "gn:asciiname":"Halgesar",
    "gn:country_code":"IN",
    "gn:dem":544,
    "gn:feature_class":"P",
    "gn:feature_code":"PPL",
    "gn:name":"H\u0101lgesar",
    "gn:population":0,
    "gn:timezone":"Asia/Kolkata",
    "iso:country":"IN",
    "ks:ks_name":"Halagesara",
    "ks:ks_pop":38,
    "ks:ks_type":"HABITATION",
    "name:eng_x_preferred":[
        "Halagesara"
    ],
    "name:eng_x_variant":[
        "Halgesar"
    ],
    "wof:name":"Halagesara",
    "wof:placetype":"locality",
    "wof:population":38
},
  "geometry": {"coordinates":[74.87181099999999,14.529595],"type":"Point"}
}