{
  "type": "Feature",
  "properties": {
    "iso:country":"IN",
    "ks:ks_name":"Binayakpur",
    "ks:ks_pop":151,
    "ks:ks_type":"VILLAGE",
    "name:eng_x_preferred":[
        "Binayakpur"
    ],
    "wof:name":"Binayakpur",
    "wof:placetype":"locality",
    "wof:population":151
},
  "geometry": {"coordinates":[83.400198,19.863575],"type":"Point"}
}