{
  "type": "Feature",
  "properties": {
    "gn:admin1_code":"39.0",
    "gn:admin2_code":"060",
    "gn:asciiname":"Lakshmanpur",
    "gn:country_code":"IN",
    "gn:dem":467,
    "gn:feature_class":"P",
    "gn:feature_code":"PPL",
    "gn:name":"Lakshmanpur",
    "gn:population":0,
    "gn:timezone":"Asia/Kolkata",
    "iso:country":"IN",
    "name:ceb_x_preferred":[
        "Laxmanpur"
    ],
    "name:mai_x_preferred":[
        "\u0932\u0915\u094d\u0937\u094d\u092e\u0923\u092a\u0941\u0930"
    ],
    "name:msa_x_preferred":[
        "Laxmanpur"
    ],
    "name:nep_x_preferred":[
        "\u0932\u0915\u094d\u0937\u094d\u092e\u0923\u092a\u0941\u0930"
    ],
    "name:new_x_preferred":[
        "\u0932\u0915\u094d\u0937\u094d\u092e\u0940\u0928\u0917\u0930"
    ],
    "name:pol_x_preferred":[
        "Laxmanpur"
    ],
    "wof:name":"Lakshmanpur",
    "wof:placetype":"locality"
},
  "geometry": {"coordinates":[77.7792,30.47357],"type":"Point"}
}