{
  "type": "Feature",
  "properties": {
    "iso:country":"IN",
    "ks:ks_name":"Chandrapur",
    "ks:ks_pop":925,
    "ks:ks_type":"HABITATION",
    "name:eng_x_preferred":[
        "Chandrapur"
    ],
    "wof:name":"Chandrapur",
    "wof:placetype":"locality",
    "wof:population":925
},
  "geometry": {"coordinates":[91.3463,23.138231],"type":"Point"}
}