{
  "type": "Feature",
  "properties": {
    "iso:country":"IN",
    "ks:ks_name":"Nagal Moginand",
    "ks:ks_pop":595,
    "ks:ks_type":"VILLAGE",
    "ks:ks_uagg_main":0,
    "name:eng_x_preferred":[
        "Nagal Moginand"
    ],
    "wof:name":"Nagal Moginand",
    "wof:placetype":"neighbourhood",
    "wof:population":595
},
  "geometry": {"coordinates":[76.897211,30.672587],"type":"Point"}
}