{
  "type": "Feature",
  "properties": {
    "iso:country":"IN",
    "ks:ks_name":"Paraghat",
    "ks:ks_pop":244,
    "ks:ks_type":"HABITATION",
    "name:eng_x_preferred":[
        "Paraghat"
    ],
    "wof:name":"Paraghat",
    "wof:placetype":"locality",
    "wof:population":244
},
  "geometry": {"coordinates":[77.694148,25.232042],"type":"Point"}
}