{
  "type": "Feature",
  "properties": {
    "iso:country":"IN",
    "ks:ks_name":"Chinnakomal",
    "ks:ks_pop":403,
    "ks:ks_type":"HABITATION",
    "name:eng_x_preferred":[
        "Chinnakomal"
    ],
    "wof:name":"Chinnakomal",
    "wof:placetype":"locality",
    "wof:population":403
},
  "geometry": {"coordinates":[79.577626,11.008463],"type":"Point"}
}