{
  "type": "Feature",
  "properties": {
    "gn:admin1_code":"11",
    "gn:admin2_code":"27.0",
    "gn:asciiname":"Pala Khad",
    "gn:country_code":"IN",
    "gn:dem":2016,
    "gn:feature_class":"P",
    "gn:feature_code":"PPL",
    "gn:name":"Pal\u0101 Khad",
    "gn:population":0,
    "gn:timezone":"Asia/Kolkata",
    "iso:country":"IN",
    "wof:name":"Pala Khad",
    "wof:placetype":"locality"
},
  "geometry": {"coordinates":[76.85300000000002,32.00413],"type":"Point"}
}