{
  "type": "Feature",
  "properties": {
    "gn:admin1_code":"12.0",
    "gn:admin2_code":"17.0",
    "gn:asciiname":"Mulmula Gad",
    "gn:country_code":"IN",
    "gn:dem":1916,
    "gn:feature_class":"P",
    "gn:feature_code":"PPL",
    "gn:name":"Mulmula Gad",
    "gn:population":0,
    "gn:timezone":"Asia/Kolkata",
    "iso:country":"IN",
    "wof:name":"Mulmula Gad",
    "wof:placetype":"locality"
},
  "geometry": {"coordinates":[75.27785,33.25218],"type":"Point"}
}