{
  "type": "Feature",
  "properties": {
    "iso:country":"IN",
    "ks:ks_name":"Chinchpada",
    "ks:ks_pop":82,
    "ks:ks_type":"HABITATION",
    "name:eng_x_preferred":[
        "Chinchpada"
    ],
    "wof:name":"Chinchpada",
    "wof:placetype":"locality",
    "wof:population":82
},
  "geometry": {"coordinates":[73.403611,20.264083],"type":"Point"}
}