{
  "type": "Feature",
  "properties": {
    "iso:country":"IN",
    "ks:ks_name":"Khairpurva",
    "ks:ks_pop":125,
    "ks:ks_type":"HABITATION",
    "name:eng_x_preferred":[
        "Khairpurva"
    ],
    "wof:name":"Khairpurva",
    "wof:placetype":"locality",
    "wof:population":125
},
  "geometry": {"coordinates":[82.120862,27.563532],"type":"Point"}
}