{
  "type": "Feature",
  "properties": {
    "gn:admin1_code":"10.0",
    "gn:admin2_code":"87.0",
    "gn:asciiname":"Biwan",
    "gn:country_code":"IN",
    "gn:dem":196,
    "gn:feature_class":"P",
    "gn:feature_code":"PPL",
    "gn:name":"Biw\u0101n",
    "gn:population":0,
    "gn:timezone":"Asia/Kolkata",
    "iso:country":"IN",
    "wof:name":"Biwan",
    "wof:placetype":"locality"
},
  "geometry": {"coordinates":[76.98265000000001,28.13181],"type":"Point"}
}