{
  "type": "Feature",
  "properties": {
    "iso:country":"IN",
    "ks:ks_name":"Siriyalapeta",
    "ks:ks_pop":10,
    "ks:ks_type":"VILLAGE",
    "ks:ks_uagg_main":0,
    "name:eng_x_preferred":[
        "Siriyalapeta"
    ],
    "wof:name":"Siriyalapeta",
    "wof:placetype":"neighbourhood",
    "wof:population":10
},
  "geometry": {"coordinates":[83.38882700000001,18.105844],"type":"Point"}
}