{
  "type": "Feature",
  "properties": {
    "iso:country":"IN",
    "ks:ks_name":"Savapur",
    "ks:ks_pop":83,
    "ks:ks_type":"HABITATION",
    "name:eng_x_preferred":[
        "Savapur"
    ],
    "wof:name":"Savapur",
    "wof:placetype":"locality",
    "wof:population":83
},
  "geometry": {"coordinates":[73.373667,23.386944],"type":"Point"}
}