{
  "type": "Feature",
  "properties": {
    "iso:country":"IN",
    "ks:ks_alt_nam":"Ramakrishnaiahna doddi",
    "ks:ks_name":"Ramakrishnaiahna Doddi",
    "ks:ks_pop":89,
    "ks:ks_type":"HABITATION",
    "name:eng_x_preferred":[
        "Ramakrishnaiahna Doddi"
    ],
    "wof:name":"Ramakrishnaiahna Doddi",
    "wof:placetype":"locality",
    "wof:population":89
},
  "geometry": {"coordinates":[77.362385,12.768619],"type":"Point"}
}