{
  "type": "Feature",
  "properties": {
    "iso:country":"IN",
    "ks:ks_alt_nam":"KADAM WASTI",
    "ks:ks_name":"Kadam Wasti",
    "ks:ks_pop":156,
    "ks:ks_type":"HABITATION",
    "name:eng_x_preferred":[
        "Kadam Wasti"
    ],
    "wof:name":"Kadam Wasti",
    "wof:placetype":"locality",
    "wof:population":156
},
  "geometry": {"coordinates":[74.47634499999999,19.695443],"type":"Point"}
}