{
  "type": "Feature",
  "properties": {
    "gn:country":"IN",
    "gn:fcode":"PPL",
    "gn:pop":41568,
    "iso:country":"IN",
    "name:ben_x_preferred":[
        "\u09a6\u09c7\u09ac\u09be\u0995\u09cb\u099f\u09cd\u099f\u09be"
    ],
    "name:bpy_x_preferred":[
        "\u09a6\u09c7\u09ac\u0995\u09cb\u09a4\u09cd\u09a4\u09be\u0987"
    ],
    "name:bul_x_preferred":[
        "\u0414\u0435\u0432\u0430\u043a\u043e\u0442\u0430\u0438"
    ],
    "name:deu_x_preferred":[
        "Devakottai"
    ],
    "name:eng_x_preferred":[
        "Devakottai"
    ],
    "name:fra_x_preferred":[
        "Devakottai"
    ],
    "name:guj_x_preferred":[
        "\u0aa6\u0ac7\u0ab5\u0a95\u0acb\u0a9f\u0acd\u0a9f\u0abe\u0a88"
    ],
    "name:ita_x_preferred":[
        "Devakottai"
    ],
    "name:jpn_x_preferred":[
        "\u30c7\u30f4\u30a1\u30b3\u30c3\u30bf\u30a4"
    ],
    "name:kan_x_preferred":[
        "\u0ca6\u0cc7\u0cb5\u0c95\u0ccb\u0c9f\u0cc8"
    ],
    "name:kor_x_preferred":[
        "\ub370\ubc14\ucf54\ud0c0\uc774"
    ],
    "name:mlg_x_preferred":[
        "Devakottai"
    ],
    "name:msa_x_preferred":[
        "Devakottai"
    ],
    "name:new_x_preferred":[
        "\u0926\u0947\u0935\u0915\u094b\u091f\u094d\u091f\u0908"
    ],
    "name:nld_x_preferred":[
        "Devakottai"
    ],
    "name:por_x_preferred":[
        "Devakottai"
    ],
    "name:rus_x_preferred":[
        "\u0414\u0435\u0432\u0430\u043a\u043e\u0442\u0442\u0430\u0438"
    ],
    "name:spa_x_preferred":[
        "Devakottai"
    ],
    "name:swe_x_preferred":[
        "Devakottai"
    ],
    "name:tam_x_preferred":[
        "\u0ba4\u0bc7\u0bb5\u0b95\u0bcb\u0b9f\u0bcd\u0b9f\u0bc8"
    ],
    "name:tel_x_preferred":[
        "\u0c26\u0c47\u0c35\u0c15\u0c4a\u0c1f\u0c4d\u0c1f\u0c3f"
    ],
    "name:unk_x_variant":[
        "Devakottai"
    ],
    "name:urd_x_preferred":[
        "\u062f\u06cc\u0648\u0627\u06a9\u0648\u062a\u062a\u0627\u06cc"
    ],
    "name:vie_x_preferred":[
        "Devakottai"
    ],
    "name:zho_x_preferred":[
        "\u5fb7\u74e6\u79d1\u6cf0"
    ],
    "qs:name":"Severakottai",
    "qs:name_adm0":"India",
    "qs:name_adm1":"Tamil Nadu",
    "qs:photos_9r":0,
    "qs:photos_sr":0,
    "qs:placetype":"Town",
    "qs:pop_sr":"7",
    "wof:name":"Severakottai",
    "wof:placetype":"locality",
    "wof:population":41568
},
  "geometry": {"coordinates":[78.8233,9.94704],"type":"Point"}
}