{
  "type": "Feature",
  "properties": {
    "iso:country":"IN",
    "ks:ks_name":"Bhiyas",
    "ks:ks_pop":476,
    "ks:ks_type":"HABITATION",
    "name:eng_x_preferred":[
        "Bhiyas"
    ],
    "wof:name":"Bhiyas",
    "wof:placetype":"locality",
    "wof:population":476
},
  "geometry": {"coordinates":[73.75975800000001,24.9041],"type":"Point"}
}