{
  "type": "Feature",
  "properties": {
    "gn:admin1_code":"36",
    "gn:admin2_code":"176.0",
    "gn:asciiname":"Wazirabad",
    "gn:country_code":"IN",
    "gn:dem":129,
    "gn:feature_class":"P",
    "gn:feature_code":"PPL",
    "gn:name":"Waz\u012brabad",
    "gn:population":0,
    "gn:timezone":"Asia/Kolkata",
    "iso:country":"IN",
    "name:bel_x_preferred":[
        "\u0412\u0430\u0437\u0456\u0440\u0430\u0431\u0430\u0434"
    ],
    "name:ceb_x_preferred":[
        "Waz\u012br\u0101b\u0101d"
    ],
    "name:deu_x_preferred":[
        "Wazirabad"
    ],
    "name:fas_x_preferred":[
        "\u0648\u0632\u06cc\u0631\u0622\u0628\u0627\u062f"
    ],
    "name:fra_x_preferred":[
        "Wazirabad"
    ],
    "name:hin_x_preferred":[
        "\u0935\u091c\u093c\u0940\u0930\u093e\u092c\u093e\u0926"
    ],
    "name:ita_x_preferred":[
        "Wazirabad"
    ],
    "name:jpn_x_preferred":[
        "\u30ef\u30ba\u30a3\u30fc\u30e9\u30fc\u30d0\u30fc\u30c9"
    ],
    "name:kor_x_preferred":[
        "\uc640\uc9c0\ub77c\ubc14\ub4dc"
    ],
    "name:lit_x_preferred":[
        "Vazirabadas"
    ],
    "name:pan_x_preferred":[
        "\u0a35\u0a1c\u0a3c\u0a40\u0a30\u0a3e\u0a2c\u0a3e\u0a26"
    ],
    "name:pnb_x_preferred":[
        "\u0648\u0632\u06cc\u0631\u0622\u0628\u0627\u062f"
    ],
    "name:pus_x_preferred":[
        "\u0648\u0632\u064a\u0631\u0627\u0628\u0627\u062f"
    ],
    "name:rus_x_preferred":[
        "\u0412\u0430\u0437\u0438\u0440\u0430\u0431\u0430\u0434"
    ],
    "name:snd_x_preferred":[
        "\u0648\u0632\u064a\u0631 \u0622\u0628\u0627\u062f"
    ],
    "name:spa_x_preferred":[
        "Wazirabad"
    ],
    "name:srp_x_preferred":[
        "\u0412\u0430\u0437\u0438\u0440\u0430\u0431\u0430\u0434"
    ],
    "name:swe_x_preferred":[
        "Wazirabad"
    ],
    "name:urd_x_preferred":[
        "\u0648\u0632\u06cc\u0631 \u0622\u0628\u0627\u062f"
    ],
    "name:zho_x_preferred":[
        "\u6c83\u6fdf\u62c9\u5df4\u5fb7"
    ],
    "wof:name":"Wazirabad",
    "wof:placetype":"locality"
},
  "geometry": {"coordinates":[81.04590999999998,27.14942000000001],"type":"Point"}
}