{
  "type": "Feature",
  "properties": {
    "gn:admin1_code":"40",
    "gn:admin2_code":"532.0",
    "gn:asciiname":"Ittalwadi",
    "gn:country_code":"IN",
    "gn:dem":477,
    "gn:feature_class":"P",
    "gn:feature_code":"PPL",
    "gn:name":"Ittalw\u0101di",
    "gn:population":0,
    "gn:timezone":"Asia/Kolkata",
    "iso:country":"IN",
    "wof:name":"Ittalwadi",
    "wof:placetype":"locality"
},
  "geometry": {"coordinates":[78.32047,19.49667],"type":"Point"}
}