{
  "type": "Feature",
  "properties": {
    "iso:country":"IN",
    "ks:ks_name":"Kumartilla-6",
    "ks:ks_pop":816,
    "ks:ks_type":"HABITATION",
    "name:eng_x_preferred":[
        "Kumartilla-6"
    ],
    "wof:name":"Kumartilla-6",
    "wof:placetype":"locality",
    "wof:population":816
},
  "geometry": {"coordinates":[91.595945,23.217379],"type":"Point"}
}