{
  "type": "Feature",
  "properties": {
    "gn:admin1_code":"36",
    "gn:admin2_code":"197.0",
    "gn:asciiname":"Bhusaula",
    "gn:country_code":"IN",
    "gn:dem":87,
    "gn:feature_class":"P",
    "gn:feature_code":"PPL",
    "gn:name":"Bhusaula",
    "gn:population":0,
    "gn:timezone":"Asia/Kolkata",
    "iso:country":"IN",
    "name:und_x_variant":[
        "B\u0101ra D\u012bh"
    ],
    "wof:name":"Bhusaula",
    "wof:placetype":"neighbourhood"
},
  "geometry": {"coordinates":[82.73191,25.37309],"type":"Point"}
}