{
  "type": "Feature",
  "properties": {
    "iso:country":"IN",
    "ks:ks_name":"Karnamvaripalle",
    "ks:ks_pop":45,
    "ks:ks_type":"HABITATION",
    "name:eng_x_preferred":[
        "Karnamvaripalle"
    ],
    "wof:name":"Karnamvaripalle",
    "wof:placetype":"locality",
    "wof:population":45
},
  "geometry": {"coordinates":[79.049155,13.792401],"type":"Point"}
}