{
  "type": "Feature",
  "properties": {
    "gn:admin1_code":"36.0",
    "gn:admin2_code":"189.0",
    "gn:asciiname":"Mahuawa",
    "gn:country_code":"IN",
    "gn:dem":77,
    "gn:feature_class":"P",
    "gn:feature_code":"PPL",
    "gn:name":"Mahu\u0101w\u0101",
    "gn:population":0,
    "gn:timezone":"Asia/Kolkata",
    "iso:country":"IN",
    "name:tam_x_preferred":[
        "\u0bae\u0b95\u0bc1\u0bb5\u0bbe\u0bb5\u0bbe"
    ],
    "wof:name":"Mahuawa",
    "wof:placetype":"locality"
},
  "geometry": {"coordinates":[84.0309,26.65737],"type":"Point"}
}