{
  "type": "Feature",
  "properties": {
    "iso:country":"IN",
    "qs:name":"Karehbari",
    "qs:name_adm0":"India",
    "qs:name_adm1":"Bihar",
    "qs:photos":12,
    "qs:photos_1k":2,
    "qs:photos_9k":1,
    "qs:photos_9r":1,
    "qs:photos_all":12,
    "qs:photos_sr":1,
    "qs:placetype":"Town",
    "qs:pop_sr":"0",
    "wof:name":"Karehbari",
    "wof:placetype":"locality"
},
  "geometry": {"coordinates":[87.908663,26.142768],"type":"Point"}
}