{
  "type": "Feature",
  "properties": {
    "iso:country":"IN",
    "ks:ks_alt_nam":"MOTI KA PURWA",
    "ks:ks_name":"Moti Ka Purwa",
    "ks:ks_pop":127,
    "ks:ks_type":"HABITATION",
    "ks:ks_uagg_main":0,
    "name:eng_x_preferred":[
        "Moti Ka Purwa"
    ],
    "wof:name":"Moti Ka Purwa",
    "wof:placetype":"neighbourhood",
    "wof:population":127
},
  "geometry": {"coordinates":[81.64886,26.398198],"type":"Point"}
}