{
  "type": "Feature",
  "properties": {
    "gn:admin1_code":"36.0",
    "gn:admin2_code":"173.0",
    "gn:asciiname":"Himmat ki Sarai",
    "gn:country_code":"IN",
    "gn:dem":103,
    "gn:feature_class":"P",
    "gn:feature_code":"PPL",
    "gn:name":"Himmat ki Sar\u0101i",
    "gn:population":0,
    "gn:timezone":"Asia/Kolkata",
    "iso:country":"IN",
    "wof:name":"Himmat ki Sarai",
    "wof:placetype":"locality"
},
  "geometry": {"coordinates":[81.68248,25.71674],"type":"Point"}
}