{
  "type": "Feature",
  "properties": {
    "iso:country":"IN",
    "ks:ks_name":"Karikalan",
    "ks:ks_pop":601,
    "ks:ks_type":"HABITATION",
    "name:eng_x_preferred":[
        "Karikalan"
    ],
    "wof:name":"Karikalan",
    "wof:placetype":"locality",
    "wof:population":601
},
  "geometry": {"coordinates":[78.46864600000001,11.495873],"type":"Point"}
}