{
  "type": "Feature",
  "properties": {
    "iso:country":"IN",
    "ks:ks_name":"Naulipada",
    "ks:ks_pop":1400,
    "ks:ks_type":"VILLAGE",
    "name:eng_x_preferred":[
        "Naulipada"
    ],
    "wof:name":"Naulipada",
    "wof:placetype":"locality",
    "wof:population":1400
},
  "geometry": {"coordinates":[84.684169,21.358268],"type":"Point"}
}