{
  "type": "Feature",
  "properties": {
    "iso:country":"IN",
    "ks:ks_name":"Bhadarpada",
    "ks:ks_pop":1122,
    "ks:ks_type":"VILLAGE",
    "name:eng_x_preferred":[
        "Bhadarpada"
    ],
    "wof:name":"Bhadarpada",
    "wof:placetype":"locality",
    "wof:population":1122
},
  "geometry": {"coordinates":[73.571889,20.659694],"type":"Point"}
}