{
  "type": "Feature",
  "properties": {
    "iso:country":"IN",
    "ks:ks_name":"Methawalepada",
    "ks:ks_pop":117,
    "ks:ks_type":"HABITATION",
    "name:eng_x_preferred":[
        "Methawalepada"
    ],
    "wof:name":"Methawalepada",
    "wof:placetype":"locality",
    "wof:population":117
},
  "geometry": {"coordinates":[73.196944,19.495],"type":"Point"}
}