{
  "type": "Feature",
  "properties": {
    "iso:country":"IN",
    "ks:ks_name":"Sharma Para",
    "ks:ks_pop":510,
    "ks:ks_type":"HABITATION",
    "ks:ks_uagg_main":0,
    "name:eng_x_preferred":[
        "Sharma Para"
    ],
    "wof:name":"Sharma Para",
    "wof:placetype":"neighbourhood",
    "wof:population":510
},
  "geometry": {"coordinates":[91.986041,24.131306],"type":"Point"}
}