{
  "type": "Feature",
  "properties": {
    "iso:country":"IN",
    "ks:ks_name":"Didupe",
    "ks:ks_pop":350,
    "ks:ks_type":"HABITATION",
    "name:eng_x_preferred":[
        "Didupe"
    ],
    "wof:name":"Didupe",
    "wof:placetype":"locality",
    "wof:population":350
},
  "geometry": {"coordinates":[75.36929600000001,13.141458],"type":"Point"}
}