{
  "type": "Feature",
  "properties": {
    "iso:country":"IN",
    "ks:ks_name":"Kamardanga",
    "ks:ks_pop":1024,
    "ks:ks_type":"VILLAGE",
    "ks:ks_uagg_main":0,
    "name:eng_x_preferred":[
        "Kamardanga"
    ],
    "wof:name":"Kamardanga",
    "wof:placetype":"neighbourhood",
    "wof:population":1024
},
  "geometry": {"coordinates":[88.58546800000001,22.87399],"type":"Point"}
}