{
  "type": "Feature",
  "properties": {
    "iso:country":"IN",
    "ks:ks_name":"Madhapar",
    "ks:ks_pop":0,
    "ks:ks_type":"VILLAGE",
    "ks:ks_uagg_main":0,
    "name:eng_x_preferred":[
        "Madhapar"
    ],
    "wof:name":"Madhapar",
    "wof:placetype":"locality",
    "wof:population":0
},
  "geometry": {"coordinates":[69.708355,23.222952],"type":"Point"}
}