{
  "type": "Feature",
  "properties": {
    "iso:country":"IN",
    "ks:ks_alt_nam":"Yellappana palya",
    "ks:ks_name":"Yellappana Palya",
    "ks:ks_pop":270,
    "ks:ks_type":"HABITATION",
    "name:eng_x_preferred":[
        "Yellappana Palya"
    ],
    "wof:name":"Yellappana Palya",
    "wof:placetype":"locality",
    "wof:population":270
},
  "geometry": {"coordinates":[77.33618199999999,12.950458],"type":"Point"}
}