{
  "type": "Feature",
  "properties": {
    "gn:admin1_code":"36.0",
    "gn:admin2_code":"183.0",
    "gn:asciiname":"Bhagan",
    "gn:country_code":"IN",
    "gn:dem":109,
    "gn:feature_class":"P",
    "gn:feature_code":"PPL",
    "gn:name":"Bhagan",
    "gn:population":0,
    "gn:timezone":"Asia/Kolkata",
    "iso:country":"IN",
    "ks:ks_name":"Bhagai",
    "ks:ks_pop":246,
    "ks:ks_type":"HABITATION",
    "ks:ks_uagg_main":0,
    "name:eng_x_preferred":[
        "Bhagai"
    ],
    "wof:name":"Bhagai",
    "wof:placetype":"neighbourhood",
    "wof:population":246
},
  "geometry": {"coordinates":[81.71263399999999,27.116138],"type":"Point"}
}