{
  "type": "Feature",
  "properties": {
    "iso:country":"IN",
    "ks:ks_name":"Pilikal",
    "ks:ks_pop":31,
    "ks:ks_type":"VILLAGE",
    "name:eng_x_preferred":[
        "Pilikal"
    ],
    "wof:name":"Pilikal",
    "wof:placetype":"locality",
    "wof:population":31
},
  "geometry": {"coordinates":[76.949798,16.339619],"type":"Point"}
}