{
  "type": "Feature",
  "properties": {
    "gn:admin1_code":"16.0",
    "gn:admin2_code":"508.0",
    "gn:asciiname":"Karampalli",
    "gn:country_code":"IN",
    "gn:dem":220,
    "gn:feature_class":"P",
    "gn:feature_code":"PPL",
    "gn:name":"K\u0101rampalli",
    "gn:population":0,
    "gn:timezone":"Asia/Kolkata",
    "iso:country":"IN",
    "wof:name":"Karampalli",
    "wof:placetype":"locality"
},
  "geometry": {"coordinates":[80.57109,19.45183],"type":"Point"}
}