{
  "type": "Feature",
  "properties": {
    "gn:admin1_code":"16.0",
    "gn:admin2_code":"508.0",
    "gn:asciiname":"Karampalli",
    "gn:country_code":"IN",
    "gn:dem":220,
    "gn:feature_class":"P",
    "gn:feature_code":"PPL",
    "gn:name":"K\u0101rampalli",
    "gn:population":0,
    "gn:timezone":"Asia/Kolkata",
    "iso:country":"IN",
    "ks:ks_alt_nam":"K\u0101rampalli",
    "ks:ks_name":"Karampalli",
    "ks:ks_pop":255,
    "ks:ks_type":"VILLAGE",
    "name:eng_x_preferred":[
        "Karampalli"
    ],
    "name:eng_x_variant":[
        "K\u0101rampalli"
    ],
    "wof:name":"Karampalli",
    "wof:placetype":"locality",
    "wof:population":255
},
  "geometry": {"coordinates":[80.571091,19.451832],"type":"Point"}
}