{
  "type": "Feature",
  "properties": {
    "iso:country":"IN",
    "ks:ks_name":"Kozhithodu",
    "ks:ks_pop":366,
    "ks:ks_type":"HABITATION",
    "name:eng_x_preferred":[
        "Kozhithodu"
    ],
    "wof:name":"Kozhithodu",
    "wof:placetype":"locality",
    "wof:population":366
},
  "geometry": {"coordinates":[76.075667,10.570852],"type":"Point"}
}