{
  "type": "Feature",
  "properties": {
    "iso:country":"IN",
    "ks:ks_name":"Purba Paniparul",
    "ks:ks_pop":3245,
    "ks:ks_type":"HABITATION",
    "ks:ks_uagg_main":0,
    "name:eng_x_preferred":[
        "Purba Paniparul"
    ],
    "wof:name":"Purba Paniparul",
    "wof:placetype":"neighbourhood",
    "wof:population":3245
},
  "geometry": {"coordinates":[87.54071399999999,21.752181],"type":"Point"}
}