{
  "type": "Feature",
  "properties": {
    "iso:country":"IN",
    "ks:ks_name":"Dav Dhabai",
    "ks:ks_pop":65,
    "ks:ks_type":"HABITATION",
    "name:eng_x_preferred":[
        "Dav Dhabai"
    ],
    "wof:name":"Dav Dhabai",
    "wof:placetype":"locality",
    "wof:population":65
},
  "geometry": {"coordinates":[81.96351799999999,23.812322],"type":"Point"}
}