{
  "type": "Feature",
  "properties": {
    "iso:country":"IN",
    "ks:ks_name":"Bedradi",
    "ks:ks_pop":38,
    "ks:ks_type":"HABITATION",
    "name:eng_x_preferred":[
        "Bedradi"
    ],
    "wof:name":"Bedradi",
    "wof:placetype":"locality",
    "wof:population":38
},
  "geometry": {"coordinates":[75.231374,12.581245],"type":"Point"}
}