{
  "type": "Feature",
  "properties": {
    "gn:admin1_code":"34",
    "gn:admin2_code":"234.0",
    "gn:asciiname":"Man Rupaitha",
    "gn:country_code":"IN",
    "gn:dem":93,
    "gn:feature_class":"P",
    "gn:feature_code":"PPL",
    "gn:name":"M\u0101n Rupaitha",
    "gn:population":0,
    "gn:timezone":"Asia/Kolkata",
    "iso:country":"IN",
    "ks:ks_name":"Man Rupaitha",
    "ks:ks_pop":13,
    "ks:ks_type":"VILLAGE",
    "name:eng_x_preferred":[
        "Man Rupaitha"
    ],
    "wof:name":"Man Rupaitha",
    "wof:placetype":"locality",
    "wof:population":13
},
  "geometry": {"coordinates":[83.941807,25.100729],"type":"Point"}
}