{
  "type": "Feature",
  "properties": {
    "gn:admin1_code":"35",
    "gn:admin2_code":"430.0",
    "gn:asciiname":"Pokhari",
    "gn:country_code":"IN",
    "gn:dem":115,
    "gn:feature_class":"P",
    "gn:feature_code":"PPL",
    "gn:name":"Pokhari",
    "gn:population":0,
    "gn:timezone":"Asia/Kolkata",
    "iso:country":"IN",
    "name:ceb_x_preferred":[
        "Pokhari"
    ],
    "name:fra_x_preferred":[
        "Pokhari"
    ],
    "name:ita_x_preferred":[
        "Pokhari"
    ],
    "name:new_x_preferred":[
        "\u092a\u094b\u0916\u0930\u0940"
    ],
    "name:pol_x_preferred":[
        "Pokhari"
    ],
    "wof:name":"Pokhari",
    "wof:placetype":"locality"
},
  "geometry": {"coordinates":[81.71899000000001,24.96018],"type":"Point"}
}