{
  "type": "Feature",
  "properties": {
    "iso:country":"IN",
    "ks:ks_name":"Sarai Baha",
    "ks:ks_pop":363,
    "ks:ks_type":"HABITATION",
    "ks:ks_uagg_main":0,
    "name:eng_x_preferred":[
        "Sarai Baha"
    ],
    "wof:name":"Sarai Baha",
    "wof:placetype":"neighbourhood",
    "wof:population":363
},
  "geometry": {"coordinates":[91.098069,25.885819],"type":"Point"}
}