{
  "type": "Feature",
  "properties": {
    "iso:country":"IN",
    "ks:ks_name":"Uparbila",
    "ks:ks_pop":198,
    "ks:ks_type":"HABITATION",
    "ks:ks_uagg_main":0,
    "name:eng_x_preferred":[
        "Uparbila"
    ],
    "wof:name":"Uparbila",
    "wof:placetype":"neighbourhood",
    "wof:population":198
},
  "geometry": {"coordinates":[86.997569,22.615818],"type":"Point"}
}