{
  "type": "Feature",
  "properties": {
    "gn:admin1_code":"19.0",
    "gn:admin2_code":"568.0",
    "gn:asciiname":"Jambani",
    "gn:country_code":"IN",
    "gn:dem":662,
    "gn:feature_class":"P",
    "gn:feature_code":"PPL",
    "gn:name":"Jamb\u0101ni",
    "gn:population":0,
    "gn:timezone":"Asia/Kolkata",
    "iso:country":"IN",
    "ks:ks_alt_nam":"Jamb\u0101ni",
    "ks:ks_name":"Jambani",
    "ks:ks_pop":447,
    "ks:ks_type":"VILLAGE",
    "name:eng_x_preferred":[
        "Jambani"
    ],
    "name:eng_x_variant":[
        "Jamb\u0101ni"
    ],
    "wof:name":"Jambani",
    "wof:placetype":"locality",
    "wof:population":447
},
  "geometry": {"coordinates":[75.166104,14.225199],"type":"Point"}
}