{
  "type": "Feature",
  "properties": {
    "iso:country":"IN",
    "ks:ks_name":"Balabhadrapur",
    "ks:ks_pop":1008,
    "ks:ks_type":"VILLAGE",
    "ks:ks_uagg_main":0,
    "name:eng_x_preferred":[
        "Balabhadrapur"
    ],
    "wof:name":"Balabhadrapur",
    "wof:placetype":"neighbourhood",
    "wof:population":1008
},
  "geometry": {"coordinates":[87.59971299999999,22.085285],"type":"Point"}
}