{
  "type": "Feature",
  "properties": {
    "iso:country":"IN",
    "ks:ks_name":"Dhadaimari",
    "ks:ks_pop":1428,
    "ks:ks_type":"VILLAGE",
    "name:eng_x_preferred":[
        "Dhadaimari"
    ],
    "wof:name":"Dhadaimari",
    "wof:placetype":"locality",
    "wof:population":1428
},
  "geometry": {"coordinates":[90.013695,25.971036],"type":"Point"}
}