{
  "type": "Feature",
  "properties": {
    "gn:admin1_code":"12.0",
    "gn:admin2_code":"7.0",
    "gn:asciiname":"Kharkal",
    "gn:country_code":"IN",
    "gn:dem":2163,
    "gn:feature_class":"P",
    "gn:feature_code":"PPL",
    "gn:name":"Kharkal",
    "gn:population":0,
    "gn:timezone":"Asia/Kolkata",
    "iso:country":"IN",
    "wof:name":"Kharkal",
    "wof:placetype":"locality"
},
  "geometry": {"coordinates":[75.71769999999999,32.71127],"type":"Point"}
}