{
  "type": "Feature",
  "properties": {
    "iso:country":"IN",
    "qs:name":"Belpu",
    "qs:name_adm0":"India",
    "qs:name_adm1":"Karnataka",
    "qs:photos":13,
    "qs:photos_1k":3,
    "qs:photos_9k":1,
    "qs:photos_9r":1,
    "qs:photos_all":13,
    "qs:photos_sr":1,
    "qs:placetype":"Town",
    "qs:pop_sr":"0",
    "wof:name":"Belpu",
    "wof:placetype":"locality"
},
  "geometry": {"coordinates":[74.74720000000001,13.191213],"type":"Point"}
}