{
  "type": "Feature",
  "properties": {
    "gn:admin1_code":"37",
    "gn:admin2_code":"408.0",
    "gn:asciiname":"Bagijhori",
    "gn:country_code":"IN",
    "gn:dem":343,
    "gn:feature_class":"P",
    "gn:feature_code":"PPL",
    "gn:name":"Bagijhor\u012b",
    "gn:population":0,
    "gn:timezone":"Asia/Kolkata",
    "iso:country":"IN",
    "ks:ks_name":"Bagaijhori",
    "ks:ks_pop":84,
    "ks:ks_type":"VILLAGE",
    "name:eng_x_preferred":[
        "Bagaijhori"
    ],
    "name:eng_x_variant":[
        "Bagijhori"
    ],
    "wof:name":"Bagaijhori",
    "wof:placetype":"locality",
    "wof:population":84
},
  "geometry": {"coordinates":[80.879222,21.331633],"type":"Point"}
}