{
  "type": "Feature",
  "properties": {
    "iso:country":"IN",
    "ks:ks_name":"Birendra Tripura Para-6",
    "ks:ks_pop":357,
    "ks:ks_type":"HABITATION",
    "name:eng_x_preferred":[
        "Birendra Tripura Para-6"
    ],
    "wof:name":"Birendra Tripura Para-6",
    "wof:placetype":"locality",
    "wof:population":357
},
  "geometry": {"coordinates":[91.533187,23.311978],"type":"Point"}
}