{
  "type": "Feature",
  "properties": {
    "gn:admin1_code":"11.0",
    "gn:admin2_code":"32.0",
    "gn:asciiname":"Jabalia",
    "gn:country_code":"IN",
    "gn:dem":1813,
    "gn:feature_class":"P",
    "gn:feature_code":"PPL",
    "gn:name":"Jabalia",
    "gn:population":0,
    "gn:timezone":"Asia/Kolkata",
    "iso:country":"IN",
    "name:ara_x_preferred":[
        "\u062c\u0628\u0627\u0644\u064a\u0627"
    ],
    "name:cat_x_preferred":[
        "Jabalia"
    ],
    "name:ceb_x_preferred":[
        "Jab\u0101ly\u0101"
    ],
    "name:ces_x_preferred":[
        "D\u017eab\u00e1lij\u00e1"
    ],
    "name:cym_x_preferred":[
        "Jabaliya"
    ],
    "name:deu_x_preferred":[
        "Dschabaliya"
    ],
    "name:epo_x_preferred":[
        "\u011cabalija"
    ],
    "name:eus_x_preferred":[
        "Jabalia"
    ],
    "name:fas_x_preferred":[
        "\u062c\u0628\u0627\u0644\u06cc\u0627"
    ],
    "name:heb_x_preferred":[
        "\u05d2'\u05d1\u05d0\u05dc\u05d9\u05d4"
    ],
    "name:ita_x_preferred":[
        "Jabalya"
    ],
    "name:jpn_x_preferred":[
        "\u30b8\u30e3\u30d0\u30ea\u30a2"
    ],
    "name:nld_x_preferred":[
        "Jabalia"
    ],
    "name:nno_x_preferred":[
        "Jabalia"
    ],
    "name:nor_x_preferred":[
        "Jabalia"
    ],
    "name:pnb_x_preferred":[
        "\u062c\u0628\u0627\u0644\u06cc\u06c1"
    ],
    "name:pol_x_preferred":[
        "D\u017cabalija"
    ],
    "name:por_x_preferred":[
        "Jabalia"
    ],
    "name:rus_x_preferred":[
        "\u0414\u0436\u0435\u0431\u0430\u043b\u0438\u044f"
    ],
    "name:sco_x_preferred":[
        "Jabalia"
    ],
    "name:spa_x_preferred":[
        "Jabaliya"
    ],
    "name:tur_x_preferred":[
        "Cibaliye"
    ],
    "name:urd_x_preferred":[
        "\u062c\u0628\u0627\u0644\u06cc\u06c1"
    ],
    "wof:name":"Jabalia",
    "wof:placetype":"locality"
},
  "geometry": {"coordinates":[77.51034,30.70398],"type":"Point"}
}