{
  "type": "Feature",
  "properties": {
    "gn:admin1_code":"29.0",
    "gn:admin2_code":"242.0",
    "gn:asciiname":"Mangbir",
    "gn:country_code":"IN",
    "gn:dem":1012,
    "gn:feature_class":"P",
    "gn:feature_code":"PPL",
    "gn:name":"M\u0101ngb\u012br",
    "gn:population":0,
    "gn:timezone":"Asia/Kolkata",
    "iso:country":"IN",
    "wof:name":"Mangbir",
    "wof:placetype":"locality"
},
  "geometry": {"coordinates":[88.29038,27.20077],"type":"Point"}
}