{
  "type": "Feature",
  "properties": {
    "iso:country":"IN",
    "ks:ks_name":"Manuwa",
    "ks:ks_pop":154,
    "ks:ks_type":"VILLAGE",
    "name:eng_x_preferred":[
        "Manuwa"
    ],
    "wof:name":"Manuwa",
    "wof:placetype":"locality",
    "wof:population":154
},
  "geometry": {"coordinates":[83.00699400000001,25.80855],"type":"Point"}
}