{
  "type": "Feature",
  "properties": {
    "gn:admin1_code":"35",
    "gn:admin2_code":"437.0",
    "gn:asciiname":"Azadnagar",
    "gn:country_code":"IN",
    "gn:dem":508,
    "gn:feature_class":"P",
    "gn:feature_code":"PPL",
    "gn:name":"\u0100z\u0101dnagar",
    "gn:population":0,
    "gn:timezone":"Asia/Kolkata",
    "iso:country":"IN",
    "ks:ks_alt_nam":"\u0100z\u0101dnagar",
    "ks:ks_name":"Azadnagar",
    "ks:ks_type":"VILLAGE",
    "name:ara_x_preferred":[
        "\u0623\u0632\u0627\u062f \u0646\u0627\u062c\u0627\u0631"
    ],
    "name:ben_bn_x_preferred":[
        "\u0986\u099c\u09be\u09a6\u09a8\u0997\u09b0"
    ],
    "name:ben_in_x_preferred":[
        "\u0986\u099c\u09be\u09a6\u09a8\u0997\u09b0"
    ],
    "name:eng_x_preferred":[
        "Azadnagar"
    ],
    "name:eng_x_variant":[
        "\u0100z\u0101dnagar"
    ],
    "name:guj_x_preferred":[
        "\u0a86\u0a9d\u0abe\u0aa6\u0aa8\u0a97\u0ab0"
    ],
    "name:hin_x_preferred":[
        "\u0906\u091c\u093e\u0926 \u0928\u0917\u0930"
    ],
    "name:kan_x_preferred":[
        "\u0c86\u0c9c\u0cbe\u0ca6\u0ccd"
    ],
    "name:mal_x_preferred":[
        "\u0d06\u0d38\u0d3e\u0d26\u0d4d"
    ],
    "name:mar_x_preferred":[
        "\u0906\u091d\u093e\u0926\u0928\u0917\u0930"
    ],
    "name:pan_x_preferred":[
        "\u0a05\u0a1c\u0a3c\u0a3e\u0a26\u0a28\u0a17\u0a30"
    ],
    "name:tam_x_preferred":[
        "\u0b86\u0b9c\u0bbe\u0ba4\u0bcd\u0ba8\u0b95\u0bb0\u0bcd"
    ],
    "name:tel_x_preferred":[
        "\u0c06\u0c1c\u0c3e\u0c26\u0c4d"
    ],
    "name:urd_x_preferred":[
        "\u0622\u0632\u0627\u062f \u0646\u06af\u0631"
    ],
    "wof:name":"Azadnagar",
    "wof:placetype":"locality"
},
  "geometry": {"coordinates":[76.29287600000001,23.154684],"type":"Point"}
}