{
  "type": "Feature",
  "properties": {
    "iso:country":"IN",
    "ks:ks_name":"Ganjulpadi",
    "ks:ks_pop":71,
    "ks:ks_type":"VILLAGE",
    "ks:ks_uagg_main":0,
    "name:eng_x_preferred":[
        "Ganjulpadi"
    ],
    "wof:name":"Ganjulpadi",
    "wof:placetype":"neighbourhood",
    "wof:population":71
},
  "geometry": {"coordinates":[83.925714,20.210017],"type":"Point"}
}