{
  "type": "Feature",
  "properties": {
    "gn:admin1_code":"25.0",
    "gn:admin2_code":"605.0",
    "gn:asciiname":"Kalarapatti",
    "gn:country_code":"IN",
    "gn:dem":511,
    "gn:feature_class":"P",
    "gn:feature_code":"PPL",
    "gn:name":"Kalarapatti",
    "gn:population":0,
    "gn:timezone":"Asia/Kolkata",
    "iso:country":"IN",
    "ks:ks_alt_nam":"Kalarapatti Reserved Forest",
    "ks:ks_name":"Kalarapatti",
    "ks:ks_pop":0,
    "ks:ks_type":"VILLAGE",
    "name:eng_x_preferred":[
        "Kalarapatti"
    ],
    "name:eng_x_variant":[
        "Kalarapatti Reserved Forest"
    ],
    "wof:name":"Kalarapatti",
    "wof:placetype":"locality",
    "wof:population":0
},
  "geometry": {"coordinates":[78.751717,12.592233],"type":"Point"}
}