{
  "type": "Feature",
  "properties": {
    "iso:country":"IN",
    "ks:ks_name":"Ramphal Ka Pura",
    "ks:ks_pop":493,
    "ks:ks_type":"VILLAGE",
    "name:eng_x_preferred":[
        "Ramphal Ka Pura"
    ],
    "wof:name":"Ramphal Ka Pura",
    "wof:placetype":"locality",
    "wof:population":493
},
  "geometry": {"coordinates":[77.557642,26.735739],"type":"Point"}
}