{
  "type": "Feature",
  "properties": {
    "iso:country":"IN",
    "ks:ks_name":"Umriha 59",
    "ks:ks_pop":1165,
    "ks:ks_type":"HABITATION",
    "name:eng_x_preferred":[
        "Umriha 59"
    ],
    "wof:name":"Umriha 59",
    "wof:placetype":"locality",
    "wof:population":1165
},
  "geometry": {"coordinates":[81.60650099999999,24.537048],"type":"Point"}
}