{
  "type": "Feature",
  "properties": {
    "iso:country":"IN",
    "ks:ks_name":"Sugia",
    "ks:ks_pop":2568,
    "ks:ks_type":"VILLAGE",
    "name:eng_x_preferred":[
        "Sugia"
    ],
    "wof:name":"Sugia",
    "wof:placetype":"locality",
    "wof:population":2568
},
  "geometry": {"coordinates":[85.576821,23.655643],"type":"Point"}
}