{
  "type": "Feature",
  "properties": {
    "gn:admin1_code":"25.0",
    "gn:admin2_code":"632.0",
    "gn:asciiname":"Pachchapalaiyam",
    "gn:country_code":"IN",
    "gn:dem":373,
    "gn:feature_class":"P",
    "gn:feature_code":"PPL",
    "gn:name":"Pachch\u0101p\u0101laiyam",
    "gn:population":0,
    "gn:timezone":"Asia/Kolkata",
    "iso:country":"IN",
    "wof:name":"Pachchapalaiyam",
    "wof:placetype":"neighbourhood"
},
  "geometry": {"coordinates":[77.09303,11.12548],"type":"Point"}
}