{
  "type": "Feature",
  "properties": {
    "iso:country":"IN",
    "ks:ks_name":"Hanumantgaon",
    "ks:ks_pop":263,
    "ks:ks_type":"VILLAGE",
    "name:eng_x_preferred":[
        "Hanumantgaon"
    ],
    "wof:name":"Hanumantgaon",
    "wof:placetype":"locality",
    "wof:population":263
},
  "geometry": {"coordinates":[75.257446,19.786612],"type":"Point"}
}