{
  "type": "Feature",
  "properties": {
    "gn:admin1_code":"21.0",
    "gn:admin2_code":"396.0",
    "gn:asciiname":"Pankachatra",
    "gn:country_code":"IN",
    "gn:dem":756,
    "gn:feature_class":"P",
    "gn:feature_code":"PPL",
    "gn:name":"Pankachatra",
    "gn:population":0,
    "gn:timezone":"Asia/Kolkata",
    "iso:country":"IN",
    "ks:ks_name":"Panichatra",
    "ks:ks_pop":658,
    "ks:ks_type":"VILLAGE",
    "name:eng_x_preferred":[
        "Panichatra"
    ],
    "name:eng_x_variant":[
        "Pankachatra"
    ],
    "wof:name":"Panichatra",
    "wof:placetype":"locality",
    "wof:population":658
},
  "geometry": {"coordinates":[83.562017,19.114662],"type":"Point"}
}