{
  "type": "Feature",
  "properties": {
    "iso:country":"IN",
    "ks:ks_name":"Bad Budhikudar",
    "ks:ks_pop":95,
    "ks:ks_type":"VILLAGE",
    "name:eng_x_preferred":[
        "Bad Budhikudar"
    ],
    "wof:name":"Bad Budhikudar",
    "wof:placetype":"locality",
    "wof:population":95
},
  "geometry": {"coordinates":[84.95659499999999,22.179148],"type":"Point"}
}