{
  "type": "Feature",
  "properties": {
    "iso:country":"IN",
    "ks:ks_name":"Kannapagudem",
    "ks:ks_pop":169,
    "ks:ks_type":"HABITATION",
    "name:eng_x_preferred":[
        "Kannapagudem"
    ],
    "wof:name":"Kannapagudem",
    "wof:placetype":"locality",
    "wof:population":169
},
  "geometry": {"coordinates":[81.124269,17.108487],"type":"Point"}
}