{
  "type": "Feature",
  "properties": {
    "gn:admin1_code":"12.0",
    "gn:admin2_code":"7.0",
    "gn:asciiname":"Mandera",
    "gn:country_code":"IN",
    "gn:dem":364,
    "gn:feature_class":"P",
    "gn:feature_code":"PPL",
    "gn:name":"Mandera",
    "gn:population":0,
    "gn:timezone":"Asia/Kolkata",
    "iso:country":"IN",
    "name:azb_x_preferred":[
        "\u0645\u0627\u0646\u062f\u0631\u0627"
    ],
    "name:cat_x_preferred":[
        "Mandera"
    ],
    "name:ceb_x_preferred":[
        "Mandera"
    ],
    "name:deu_x_preferred":[
        "Mandera"
    ],
    "name:fas_x_preferred":[
        "\u0645\u0627\u0646\u062f\u0631\u0627"
    ],
    "name:fra_x_preferred":[
        "Mandera"
    ],
    "name:ita_x_preferred":[
        "Mandera"
    ],
    "name:jpn_x_preferred":[
        "\u30de\u30f3\u30c7\u30e9"
    ],
    "name:kat_x_preferred":[
        "\u10db\u10d0\u10dc\u10d3\u10d4\u10e0\u10d0"
    ],
    "name:nld_x_preferred":[
        "Mandera"
    ],
    "name:nor_x_preferred":[
        "Mandera"
    ],
    "name:pol_x_preferred":[
        "Mandera"
    ],
    "name:por_x_preferred":[
        "Mandera"
    ],
    "name:ron_x_preferred":[
        "Mandera"
    ],
    "name:rus_x_preferred":[
        "\u041c\u0430\u043d\u0434\u0435\u0440\u0430"
    ],
    "name:som_x_preferred":[
        "Mandheera"
    ],
    "name:spa_x_preferred":[
        "Mandera"
    ],
    "name:swa_x_preferred":[
        "Mandera"
    ],
    "name:swe_x_preferred":[
        "Mandera"
    ],
    "name:zho_x_preferred":[
        "\u66fc\u5fb7\u62c9"
    ],
    "wof:name":"Mandera",
    "wof:placetype":"locality"
},
  "geometry": {"coordinates":[75.2671,32.48157],"type":"Point"}
}