{
  "type": "Feature",
  "properties": {
    "iso:country":"IN",
    "ks:ks_name":"Sehagari",
    "ks:ks_pop":2958,
    "ks:ks_type":"VILLAGE",
    "name:eng_x_preferred":[
        "Sehagari"
    ],
    "wof:name":"Sehagari",
    "wof:placetype":"locality",
    "wof:population":2958
},
  "geometry": {"coordinates":[87.962749,22.589356],"type":"Point"}
}