{
  "type": "Feature",
  "properties": {
    "iso:country":"IN",
    "ks:ks_name":"Dangar Keri",
    "ks:ks_pop":1084,
    "ks:ks_type":"VILLAGE",
    "name:eng_x_preferred":[
        "Dangar Keri"
    ],
    "wof:name":"Dangar Keri",
    "wof:placetype":"locality",
    "wof:population":1084
},
  "geometry": {"coordinates":[82.40625199999999,24.995982],"type":"Point"}
}