{
  "type": "Feature",
  "properties": {
    "iso:country":"IN",
    "ks:ks_name":"Shungso",
    "ks:ks_pop":64,
    "ks:ks_type":"HABITATION",
    "ks:ks_uagg_main":0,
    "name:eng_x_preferred":[
        "Shungso"
    ],
    "wof:name":"Shungso",
    "wof:placetype":"neighbourhood",
    "wof:population":64
},
  "geometry": {"coordinates":[93.354834,26.922514],"type":"Point"}
}