{
  "type": "Feature",
  "properties": {
    "iso:country":"IN",
    "ks:ks_alt_nam":"korankel rutadih",
    "ks:ks_name":"Korankel Rutadih",
    "ks:ks_pop":324,
    "ks:ks_type":"HABITATION",
    "name:eng_x_preferred":[
        "Korankel Rutadih"
    ],
    "wof:name":"Korankel Rutadih",
    "wof:placetype":"locality",
    "wof:population":324
},
  "geometry": {"coordinates":[85.29343900000001,22.85558],"type":"Point"}
}