{
  "type": "Feature",
  "properties": {
    "iso:country":"IN",
    "ks:ks_name":"1 BLD",
    "ks:ks_pop":44,
    "ks:ks_type":"VILLAGE",
    "name:eng_x_preferred":[
        "1 BLD"
    ],
    "wof:name":"1 BLD",
    "wof:placetype":"locality",
    "wof:population":44
},
  "geometry": {"coordinates":[73.47750000000001,29.333889],"type":"Point"}
}