{
  "type": "Feature",
  "properties": {
    "iso:country":"IN",
    "ks:ks_name":"Khant Faliya",
    "ks:ks_pop":587,
    "ks:ks_type":"HABITATION",
    "ks:ks_uagg_main":0,
    "name:eng_x_preferred":[
        "Khant Faliya"
    ],
    "wof:name":"Khant Faliya",
    "wof:placetype":"neighbourhood",
    "wof:population":587
},
  "geometry": {"coordinates":[73.93275,23.067667],"type":"Point"}
}