{
  "type": "Feature",
  "properties": {
    "gn:admin1_code":"36",
    "gn:admin2_code":"184.0",
    "gn:asciiname":"Harjanpur",
    "gn:country_code":"IN",
    "gn:dem":85,
    "gn:feature_class":"P",
    "gn:feature_code":"PPL",
    "gn:name":"Harjanpur",
    "gn:population":0,
    "gn:timezone":"Asia/Kolkata",
    "iso:country":"IN",
    "wof:name":"Harjanpur",
    "wof:placetype":"locality"
},
  "geometry": {"coordinates":[83.07789,27.11435],"type":"Point"}
}