{
  "type": "Feature",
  "properties": {
    "iso:country":"IN",
    "ks:ks_alt_nam":"Karanpur Chaudhri",
    "ks:ks_name":"Karampur Chaudhary",
    "ks:ks_pop":4288,
    "ks:ks_type":"VILLAGE",
    "ks:ks_uagg_main":0,
    "name:eng_x_preferred":[
        "Karampur Chaudhary"
    ],
    "name:eng_x_variant":[
        "Karanpur Chaudhri"
    ],
    "wof:name":"Karampur Chaudhary",
    "wof:placetype":"neighbourhood",
    "wof:population":4288
},
  "geometry": {"coordinates":[79.43114799999999,28.427564],"type":"Point"}
}