{
  "type": "Feature",
  "properties": {
    "iso:country":"IN",
    "ks:ks_name":"Gagdispur",
    "ks:ks_pop":286,
    "ks:ks_type":"HABITATION",
    "ks:ks_uagg_main":0,
    "name:eng_x_preferred":[
        "Gagdispur"
    ],
    "wof:name":"Gagdispur",
    "wof:placetype":"neighbourhood",
    "wof:population":286
},
  "geometry": {"coordinates":[84.965065,25.583026],"type":"Point"}
}