{
  "type": "Feature",
  "properties": {
    "iso:country":"IN",
    "ks:ks_name":"Madivalara Kaibulira",
    "ks:ks_pop":115,
    "ks:ks_type":"HABITATION",
    "name:eng_x_preferred":[
        "Madivalara Kaibulira"
    ],
    "wof:name":"Madivalara Kaibulira",
    "wof:placetype":"locality",
    "wof:population":115
},
  "geometry": {"coordinates":[75.629722,12.279722],"type":"Point"}
}