{
  "type": "Feature",
  "properties": {
    "iso:country":"IN",
    "ks:ks_alt_nam":"vakchunda",
    "ks:ks_name":"Vakchunda",
    "ks:ks_pop":2320,
    "ks:ks_type":"HABITATION",
    "name:eng_x_preferred":[
        "Vakchunda"
    ],
    "wof:name":"Vakchunda",
    "wof:placetype":"locality",
    "wof:population":2320
},
  "geometry": {"coordinates":[82.10907,25.222993],"type":"Point"}
}