{
  "type": "Feature",
  "properties": {
    "gn:admin1_code":"2.0",
    "gn:admin2_code":"554.0",
    "gn:asciiname":"Boggalavandlapalli",
    "gn:country_code":"IN",
    "gn:dem":481,
    "gn:feature_class":"P",
    "gn:feature_code":"PPL",
    "gn:name":"Boggalav\u0101ndlapalli",
    "gn:population":0,
    "gn:timezone":"Asia/Kolkata",
    "iso:country":"IN",
    "wof:name":"Boggalavandlapalli",
    "wof:placetype":"locality"
},
  "geometry": {"coordinates":[79.05219,13.81278],"type":"Point"}
}