{
  "type": "Feature",
  "properties": {
    "gn:admin1_code":"2.0",
    "gn:admin2_code":"554.0",
    "gn:asciiname":"Boggalavandlapalli",
    "gn:country_code":"IN",
    "gn:dem":481,
    "gn:feature_class":"P",
    "gn:feature_code":"PPL",
    "gn:name":"Boggalav\u0101ndlapalli",
    "gn:population":0,
    "gn:timezone":"Asia/Kolkata",
    "iso:country":"IN",
    "ks:ks_alt_nam":"Boggalavandla palle",
    "ks:ks_name":"Boggalavandla Palle",
    "ks:ks_pop":79,
    "ks:ks_type":"HABITATION",
    "name:eng_x_preferred":[
        "Boggalavandla Palle"
    ],
    "name:eng_x_variant":[
        "Boggalavandlapalli"
    ],
    "wof:name":"Boggalavandla Palle",
    "wof:placetype":"locality",
    "wof:population":79
},
  "geometry": {"coordinates":[79.05136299999999,13.812636],"type":"Point"}
}