{
  "type": "Feature",
  "properties": {
    "iso:country":"IN",
    "ks:ks_name":"Barakhal",
    "ks:ks_pop":596,
    "ks:ks_type":"VILLAGE",
    "name:eng_x_preferred":[
        "Barakhal"
    ],
    "wof:name":"Barakhal",
    "wof:placetype":"locality",
    "wof:population":596
},
  "geometry": {"coordinates":[83.13632699999999,26.975765],"type":"Point"}
}