{
  "type": "Feature",
  "properties": {
    "iso:country":"IN",
    "ks:ks_name":"Daulatpur",
    "ks:ks_pop":172,
    "ks:ks_type":"HABITATION",
    "name:eng_x_preferred":[
        "Daulatpur"
    ],
    "wof:name":"Daulatpur",
    "wof:placetype":"locality",
    "wof:population":172
},
  "geometry": {"coordinates":[87.04676499999999,24.366589],"type":"Point"}
}