{
  "type": "Feature",
  "properties": {
    "gn:admin1_code":"36",
    "gn:admin2_code":"149.0",
    "gn:asciiname":"Gulabi Nagla",
    "gn:country_code":"IN",
    "gn:dem":151,
    "gn:feature_class":"P",
    "gn:feature_code":"PPL",
    "gn:name":"Gul\u0101bi Nagla",
    "gn:population":0,
    "gn:timezone":"Asia/Kolkata",
    "iso:country":"IN",
    "name:und_x_variant":[
        "Gul\u0101bi Nagla",
        "An\u016bp Nagla"
    ],
    "wof:name":"Gulabi Nagla",
    "wof:placetype":"locality"
},
  "geometry": {"coordinates":[79.3141,27.71031],"type":"Point"}
}