{
  "type": "Feature",
  "properties": {
    "iso:country":"IN",
    "ks:ks_name":"Chipiya",
    "ks:ks_pop":826,
    "ks:ks_type":"VILLAGE",
    "name:eng_x_preferred":[
        "Chipiya"
    ],
    "wof:name":"Chipiya",
    "wof:placetype":"locality",
    "wof:population":826
},
  "geometry": {"coordinates":[83.128309,23.893093],"type":"Point"}
}