{
  "type": "Feature",
  "properties": {
    "gn:admin1_code":"12.0",
    "gn:admin2_code":"19.0",
    "gn:asciiname":"Babai",
    "gn:country_code":"IN",
    "gn:dem":832,
    "gn:feature_class":"P",
    "gn:feature_code":"PPL",
    "gn:name":"Babai",
    "gn:population":0,
    "gn:timezone":"Asia/Kolkata",
    "iso:country":"IN",
    "wof:name":"Babai",
    "wof:placetype":"locality"
},
  "geometry": {"coordinates":[75.35590999999999,32.67247],"type":"Point"}
}