{
  "type": "Feature",
  "properties": {
    "gn:admin1_code":"12.0",
    "gn:admin2_code":"19.0",
    "gn:asciiname":"Babai",
    "gn:country_code":"IN",
    "gn:dem":832,
    "gn:feature_class":"P",
    "gn:feature_code":"PPL",
    "gn:name":"Babai",
    "gn:population":0,
    "gn:timezone":"Asia/Kolkata",
    "iso:country":"IN",
    "name:ceb_x_preferred":[
        "Babai"
    ],
    "name:deu_x_preferred":[
        "Babai"
    ],
    "name:fas_x_preferred":[
        "\u0628\u0627\u0628\u0627\u06cc\u06cc"
    ],
    "name:fra_x_preferred":[
        "Babai"
    ],
    "name:nld_x_preferred":[
        "Babai"
    ],
    "name:rus_x_preferred":[
        "\u0411\u0430\u0431\u0430\u0439"
    ],
    "name:spa_x_preferred":[
        "Babai"
    ],
    "name:swe_x_preferred":[
        "Babai"
    ],
    "name:ukr_x_preferred":[
        "\u0411\u0430\u0431\u0430\u0439"
    ],
    "wof:name":"Babai",
    "wof:placetype":"locality"
},
  "geometry": {"coordinates":[75.35590999999999,32.67247],"type":"Point"}
}