{
  "type": "Feature",
  "properties": {
    "iso:country":"IN",
    "ks:ks_alt_nam":"FAKIR GURA",
    "ks:ks_name":"Fakir Gura",
    "ks:ks_pop":247,
    "ks:ks_type":"HABITATION",
    "name:eng_x_preferred":[
        "Fakir Gura"
    ],
    "wof:name":"Fakir Gura",
    "wof:placetype":"locality",
    "wof:population":247
},
  "geometry": {"coordinates":[88.24645700000001,26.413895],"type":"Point"}
}