{
  "type": "Feature",
  "properties": {
    "iso:country":"IN",
    "ks:ks_name":"Darekarwasti",
    "ks:ks_pop":271,
    "ks:ks_type":"HABITATION",
    "ks:ks_uagg_main":0,
    "name:eng_x_preferred":[
        "Darekarwasti"
    ],
    "wof:name":"Darekarwasti",
    "wof:placetype":"neighbourhood",
    "wof:population":271
},
  "geometry": {"coordinates":[74.019631,18.652333],"type":"Point"}
}