{
  "type": "Feature",
  "properties": {
    "gn:admin1_code":"36",
    "gn:admin2_code":"194.0",
    "gn:asciiname":"Ratauli",
    "gn:country_code":"IN",
    "gn:dem":87,
    "gn:feature_class":"P",
    "gn:feature_code":"PPL",
    "gn:name":"Ratauli",
    "gn:population":0,
    "gn:timezone":"Asia/Kolkata",
    "iso:country":"IN",
    "ks:ks_name":"Ratauli",
    "ks:ks_pop":239,
    "ks:ks_type":"VILLAGE",
    "name:ceb_x_preferred":[
        "Ratauli"
    ],
    "name:eng_x_preferred":[
        "Ratauli"
    ],
    "name:mai_x_preferred":[
        "\u0930\u0924\u094c\u0932\u0940"
    ],
    "name:msa_x_preferred":[
        "Ratauli"
    ],
    "name:new_x_preferred":[
        "\u0930\u0924\u094c\u0932\u0940"
    ],
    "name:pol_x_preferred":[
        "Ratauli"
    ],
    "wof:name":"Ratauli",
    "wof:placetype":"locality",
    "wof:population":239
},
  "geometry": {"coordinates":[82.591345,25.676683],"type":"Point"}
}