{
  "type": "Feature",
  "properties": {
    "gn:admin1_code":"28.0",
    "gn:admin2_code":"337.0",
    "gn:asciiname":"Kalianai",
    "gn:country_code":"IN",
    "gn:dem":8,
    "gn:feature_class":"P",
    "gn:feature_code":"PPL",
    "gn:name":"Kalianai",
    "gn:population":0,
    "gn:timezone":"Asia/Kolkata",
    "iso:country":"IN",
    "wof:name":"Kalianai",
    "wof:placetype":"locality"
},
  "geometry": {"coordinates":[88.55895,22.74748],"type":"Point"}
}