{
  "type": "Feature",
  "properties": {
    "iso:country":"IN",
    "ks:ks_name":"Buddijoy Chowdhury Para",
    "ks:ks_pop":137,
    "ks:ks_type":"HABITATION",
    "name:eng_x_preferred":[
        "Buddijoy Chowdhury Para"
    ],
    "wof:name":"Buddijoy Chowdhury Para",
    "wof:placetype":"locality",
    "wof:population":137
},
  "geometry": {"coordinates":[92.014906,23.686354],"type":"Point"}
}