{
  "type": "Feature",
  "properties": {
    "iso:country":"IN",
    "ks:ks_name":"Hibba",
    "ks:ks_pop":480,
    "ks:ks_type":"VILLAGE",
    "ks:ks_uagg_main":0,
    "name:eng_x_preferred":[
        "Hibba"
    ],
    "wof:name":"Hibba",
    "wof:placetype":"neighbourhood",
    "wof:population":480
},
  "geometry": {"coordinates":[85.989998,26.46139],"type":"Point"}
}