{
  "type": "Feature",
  "properties": {
    "iso:country":"IN",
    "ks:ks_name":"Dokeni",
    "ks:ks_type":"VILLAGE",
    "name:eng_x_preferred":[
        "Dokeni"
    ],
    "wof:name":"Dokeni",
    "wof:placetype":"locality"
},
  "geometry": {"coordinates":[84.05897899999999,20.512967],"type":"Point"}
}