{
  "type": "Feature",
  "properties": {
    "gn:admin1_code":"36",
    "gn:admin2_code":"145.0",
    "gn:asciiname":"Gopalpur",
    "gn:country_code":"IN",
    "gn:dem":177,
    "gn:feature_class":"P",
    "gn:feature_code":"PPL",
    "gn:name":"Gop\u0101lpur",
    "gn:population":0,
    "gn:timezone":"Asia/Kolkata",
    "iso:country":"IN",
    "name:und_x_variant":[
        "Gop\u0101lpur",
        "R\u0101ipurmai"
    ],
    "wof:name":"Gopalpur",
    "wof:placetype":"locality"
},
  "geometry": {"coordinates":[77.72528,27.49367],"type":"Point"}
}