{
  "type": "Feature",
  "properties": {
    "iso:country":"IN",
    "ks:ks_name":"Vaddivarikothuru",
    "ks:ks_pop":96,
    "ks:ks_type":"HABITATION",
    "name:eng_x_preferred":[
        "Vaddivarikothuru"
    ],
    "wof:name":"Vaddivarikothuru",
    "wof:placetype":"locality",
    "wof:population":96
},
  "geometry": {"coordinates":[78.363749,12.891214],"type":"Point"}
}