{
  "type": "Feature",
  "properties": {
    "gn:admin1_code":"2.0",
    "gn:admin2_code":"543.0",
    "gn:asciiname":"Marriguda",
    "gn:country_code":"IN",
    "gn:dem":147,
    "gn:feature_class":"P",
    "gn:feature_code":"PPL",
    "gn:name":"Marrig\u016bda",
    "gn:population":0,
    "gn:timezone":"Asia/Kolkata",
    "iso:country":"IN",
    "name:tel_x_preferred":[
        "\u0c2e\u0c30\u0c4d\u0c30\u0c3f\u0c17\u0c42\u0c21"
    ],
    "wof:name":"Marriguda",
    "wof:placetype":"locality"
},
  "geometry": {"coordinates":[83.51285,18.90601],"type":"Point"}
}