{
  "type": "Feature",
  "properties": {
    "gn:admin1_code":"36.0",
    "gn:admin2_code":"135.0",
    "gn:asciiname":"Hasangarh",
    "gn:country_code":"IN",
    "gn:dem":206,
    "gn:feature_class":"P",
    "gn:feature_code":"PPL",
    "gn:name":"Hasangarh",
    "gn:population":0,
    "gn:timezone":"Asia/Kolkata",
    "iso:country":"IN",
    "name:und_x_variant":[
        "Sikandarpur"
    ],
    "wof:name":"Hasangarh",
    "wof:placetype":"locality"
},
  "geometry": {"coordinates":[78.43574,28.69319],"type":"Point"}
}