{
  "type": "Feature",
  "properties": {
    "iso:country":"IN",
    "ks:ks_name":"Muslim Tola",
    "ks:ks_pop":899,
    "ks:ks_type":"HABITATION",
    "ks:ks_uagg_main":0,
    "name:eng_x_preferred":[
        "Muslim Tola"
    ],
    "wof:name":"Muslim Tola",
    "wof:placetype":"neighbourhood",
    "wof:population":899
},
  "geometry": {"coordinates":[86.687027,25.240263],"type":"Point"}
}