{
  "type": "Feature",
  "properties": {
    "gn:admin1_code":"36",
    "gn:admin2_code":"186.0",
    "gn:asciiname":"Pherusa",
    "gn:country_code":"IN",
    "gn:dem":84,
    "gn:feature_class":"P",
    "gn:feature_code":"PPL",
    "gn:name":"Pherusa",
    "gn:population":0,
    "gn:timezone":"Asia/Kolkata",
    "iso:country":"IN",
    "name:bul_x_preferred":[
        "\u0424\u0435\u0440\u0443\u0437\u0430"
    ],
    "name:cat_x_preferred":[
        "Ferusa"
    ],
    "name:ell_x_preferred":[
        "\u03a6\u03ad\u03c1\u03bf\u03c5\u03c3\u03b1"
    ],
    "name:jpn_x_preferred":[
        "\u30da\u30eb\u30fc\u30b5\u30fc"
    ],
    "name:lat_x_preferred":[
        "Pherusa"
    ],
    "name:lit_x_preferred":[
        "Ferusa"
    ],
    "name:spa_x_preferred":[
        "Ferusa"
    ],
    "name:tur_x_preferred":[
        "Pherusa"
    ],
    "wof:name":"Pherusa",
    "wof:placetype":"locality"
},
  "geometry": {"coordinates":[83.07666999999999,26.73393],"type":"Point"}
}