{
  "type": "Feature",
  "properties": {
    "gn:admin1_code":"34.0",
    "gn:admin2_code":"219.0",
    "gn:asciiname":"Badarzamin",
    "gn:country_code":"IN",
    "gn:dem":62,
    "gn:feature_class":"P",
    "gn:feature_code":"PPL",
    "gn:name":"B\u0101darzamin",
    "gn:population":0,
    "gn:timezone":"Asia/Kolkata",
    "iso:country":"IN",
    "ks:ks_alt_nam":"B\u0101darzamin",
    "ks:ks_name":"Badarzamin",
    "ks:ks_pop":656,
    "ks:ks_type":"VILLAGE",
    "ks:ks_uagg_main":0,
    "name:eng_x_preferred":[
        "Badarzamin"
    ],
    "name:eng_x_variant":[
        "B\u0101darzamin"
    ],
    "wof:name":"Badarzamin",
    "wof:placetype":"neighbourhood",
    "wof:population":656
},
  "geometry": {"coordinates":[84.622778,26.084396],"type":"Point"}
}