{
  "type": "Feature",
  "properties": {
    "iso:country":"IN",
    "ks:ks_name":"Ramchauraha",
    "ks:ks_pop":163,
    "ks:ks_type":"HABITATION",
    "ks:ks_uagg_main":0,
    "name:eng_x_preferred":[
        "Ramchauraha"
    ],
    "wof:name":"Ramchauraha",
    "wof:placetype":"neighbourhood",
    "wof:population":163
},
  "geometry": {"coordinates":[83.23736599999999,27.22493],"type":"Point"}
}