{
  "type": "Feature",
  "properties": {
    "iso:country":"IN",
    "ks:ks_name":"Ojhariya",
    "ks:ks_pop":427,
    "ks:ks_type":"VILLAGE",
    "ks:ks_uagg_main":0,
    "name:eng_x_preferred":[
        "Ojhariya"
    ],
    "wof:name":"Ojhariya",
    "wof:placetype":"locality",
    "wof:population":427
},
  "geometry": {"coordinates":[74.42039200000001,23.551561],"type":"Point"}
}