{
  "type": "Feature",
  "properties": {
    "gn:admin1_code":"36",
    "gn:admin2_code":"174.0",
    "gn:asciiname":"Sanyara Mitthepur",
    "gn:country_code":"IN",
    "gn:dem":109,
    "gn:feature_class":"P",
    "gn:feature_code":"PPL",
    "gn:name":"Sany\u0101ra Mitthepur",
    "gn:population":0,
    "gn:timezone":"Asia/Kolkata",
    "iso:country":"IN",
    "wof:name":"Sanyara Mitthepur",
    "wof:placetype":"neighbourhood"
},
  "geometry": {"coordinates":[81.35026999999999,25.6316],"type":"Point"}
}