{
  "type": "Feature",
  "properties": {
    "iso:country":"IN",
    "ks:ks_name":"Kandkiras",
    "ks:ks_pop":1210,
    "ks:ks_type":"HABITATION",
    "name:eng_x_preferred":[
        "Kandkiras"
    ],
    "wof:name":"Kandkiras",
    "wof:placetype":"locality",
    "wof:population":1210
},
  "geometry": {"coordinates":[81.824202,18.9498],"type":"Point"}
}