{
  "type": "Feature",
  "properties": {
    "iso:country":"IN",
    "ks:ks_name":"Alakapapuram",
    "ks:ks_pop":460,
    "ks:ks_type":"HABITATION",
    "name:eng_x_preferred":[
        "Alakapapuram"
    ],
    "wof:name":"Alakapapuram",
    "wof:placetype":"locality",
    "wof:population":460
},
  "geometry": {"coordinates":[77.625546,8.36511],"type":"Point"}
}