{
  "type": "Feature",
  "properties": {
    "gn:admin1_code":"36.0",
    "gn:admin2_code":"160",
    "gn:asciiname":"Rajaimau Thakurain",
    "gn:country_code":"IN",
    "gn:dem":143,
    "gn:feature_class":"P",
    "gn:feature_code":"PPL",
    "gn:name":"Raja\u012bmau Thakur\u0101in",
    "gn:population":0,
    "gn:timezone":"Asia/Kolkata",
    "iso:country":"IN",
    "ks:ks_name":"Rajaimauthakurain",
    "ks:ks_pop":689,
    "ks:ks_type":"VILLAGE",
    "ks:ks_uagg_main":0,
    "name:eng_x_preferred":[
        "Rajaimauthakurain"
    ],
    "wof:name":"Rajaimauthakurain",
    "wof:placetype":"neighbourhood",
    "wof:population":689
},
  "geometry": {"coordinates":[79.87350600000001,27.004027],"type":"Point"}
}