{
  "type": "Feature",
  "properties": {
    "gn:admin1_code":"36",
    "gn:admin2_code":"152.0",
    "gn:asciiname":"Patti Jhujhar",
    "gn:country_code":"IN",
    "gn:dem":157,
    "gn:feature_class":"P",
    "gn:feature_code":"PPL",
    "gn:name":"Patti Jh\u016bjh\u0101r",
    "gn:population":0,
    "gn:timezone":"Asia/Kolkata",
    "iso:country":"IN",
    "ks:ks_alt_nam":"Patti Jh\u016bjh\u0101r",
    "ks:ks_name":"Patti Jhujhar",
    "ks:ks_type":"VILLAGE",
    "ks:ks_uagg_main":0,
    "name:eng_x_preferred":[
        "Patti Jhujhar"
    ],
    "name:eng_x_variant":[
        "Patti Jh\u016bjh\u0101r"
    ],
    "wof:name":"Patti Jhujhar",
    "wof:placetype":"neighbourhood"
},
  "geometry": {"coordinates":[79.689195,27.803645],"type":"Point"}
}