{
  "type": "Feature",
  "properties": {
    "gn:admin1_code":"11.0",
    "gn:admin2_code":"27.0",
    "gn:asciiname":"Doda",
    "gn:country_code":"IN",
    "gn:dem":859,
    "gn:feature_class":"P",
    "gn:feature_code":"PPL",
    "gn:name":"Doda",
    "gn:population":0,
    "gn:timezone":"Asia/Kolkata",
    "iso:country":"IN",
    "name:ara_x_preferred":[
        "\u062f\u0648\u062f\u0627"
    ],
    "name:bpy_x_preferred":[
        "\u09a6\u09cb\u09a6\u09be"
    ],
    "name:ceb_x_preferred":[
        "Doda"
    ],
    "name:deu_x_preferred":[
        "Doda"
    ],
    "name:fra_x_preferred":[
        "Doda"
    ],
    "name:guj_x_preferred":[
        "\u0aa1\u0acb\u0aa1\u0abe"
    ],
    "name:hin_x_preferred":[
        "\u0921\u094b\u0921\u093e"
    ],
    "name:ind_x_preferred":[
        "Doda"
    ],
    "name:ita_x_preferred":[
        "Doda"
    ],
    "name:mal_x_preferred":[
        "\u0d26\u0d4b\u0d21"
    ],
    "name:mar_x_preferred":[
        "\u0921\u094b\u0921\u093e"
    ],
    "name:msa_x_preferred":[
        "Doda"
    ],
    "name:new_x_preferred":[
        "\u0921\u094b\u0921\u093e"
    ],
    "name:nld_x_preferred":[
        "Doda"
    ],
    "name:pnb_x_preferred":[
        "\u0688\u0648\u0688\u06c1"
    ],
    "name:rus_x_preferred":[
        "\u0414\u043e\u0434\u0430"
    ],
    "name:san_x_preferred":[
        "\u0921\u094b\u0921\u093e"
    ],
    "name:spa_x_preferred":[
        "Doda"
    ],
    "name:swe_x_preferred":[
        "Doda"
    ],
    "name:und_x_variant":[
        "Dh\u016bda"
    ],
    "name:urd_x_preferred":[
        "\u0688\u0648\u0688\u0627"
    ],
    "name:vie_x_preferred":[
        "Doda"
    ],
    "wof:name":"Doda",
    "wof:placetype":"locality"
},
  "geometry": {"coordinates":[77.02815,31.70891],"type":"Point"}
}