{
  "type": "Feature",
  "properties": {
    "iso:country":"IN",
    "ks:ks_name":"Barkagarha",
    "ks:ks_pop":74,
    "ks:ks_type":"HABITATION",
    "name:eng_x_preferred":[
        "Barkagarha"
    ],
    "wof:name":"Barkagarha",
    "wof:placetype":"locality",
    "wof:population":74
},
  "geometry": {"coordinates":[84.16778600000001,22.390193],"type":"Point"}
}