{
  "type": "Feature",
  "properties": {
    "gn:admin1_code":"36",
    "gn:admin2_code":"175.0",
    "gn:asciiname":"Fatuha",
    "gn:country_code":"IN",
    "gn:dem":99,
    "gn:feature_class":"P",
    "gn:feature_code":"PPL",
    "gn:name":"Fat\u016bh\u0101",
    "gn:population":0,
    "gn:timezone":"Asia/Kolkata",
    "iso:country":"IN",
    "name:ben_x_preferred":[
        "\u09ab\u09a4\u0993\u09af\u09bc\u09be"
    ],
    "name:bih_x_preferred":[
        "\u092b\u0924\u0941\u0939\u093e"
    ],
    "name:bpy_x_preferred":[
        "\u09ab\u09a4\u09f1\u09be"
    ],
    "name:hin_x_preferred":[
        "\u092b\u0924\u0941\u0939\u093e"
    ],
    "name:ita_x_preferred":[
        "Fatwah"
    ],
    "name:msa_x_preferred":[
        "Fatwah"
    ],
    "name:new_x_preferred":[
        "\u092b\u0924\u094d\u0935\u093e\u0939"
    ],
    "name:nld_x_preferred":[
        "Fatwah"
    ],
    "name:por_x_preferred":[
        "Fatwah"
    ],
    "name:spa_x_preferred":[
        "Fatwah"
    ],
    "name:urd_x_preferred":[
        "\u0641\u062a\u0648\u06c1"
    ],
    "name:vie_x_preferred":[
        "Fatwah"
    ],
    "wof:name":"Fatuha",
    "wof:placetype":"locality"
},
  "geometry": {"coordinates":[82.04212,25.42837],"type":"Point"}
}