{
  "type": "Feature",
  "properties": {
    "iso:country":"IN",
    "ks:ks_name":"Borkhedi",
    "ks:ks_pop":105,
    "ks:ks_type":"VILLAGE",
    "name:eng_x_preferred":[
        "Borkhedi"
    ],
    "wof:name":"Borkhedi",
    "wof:placetype":"locality",
    "wof:population":105
},
  "geometry": {"coordinates":[75.326616,24.385766],"type":"Point"}
}