{
  "type": "Feature",
  "properties": {
    "gn:admin1_code":"19.0",
    "gn:admin2_code":"569.0",
    "gn:asciiname":"Matebettu",
    "gn:country_code":"IN",
    "gn:dem":52,
    "gn:feature_class":"P",
    "gn:feature_code":"PPL",
    "gn:name":"Mat\u0113bettu",
    "gn:population":0,
    "gn:timezone":"Asia/Kolkata",
    "iso:country":"IN",
    "ks:ks_name":"Mathibettu",
    "ks:ks_pop":180,
    "ks:ks_type":"HABITATION",
    "name:eng_x_preferred":[
        "Mathibettu"
    ],
    "name:eng_x_variant":[
        "Matebettu"
    ],
    "wof:name":"Mathibettu",
    "wof:placetype":"locality",
    "wof:population":180
},
  "geometry": {"coordinates":[75.008109,13.384502],"type":"Point"}
}