{
  "type": "Feature",
  "properties": {
    "gn:admin1_code":"36",
    "gn:admin2_code":"200.0",
    "gn:asciiname":"Chandwar",
    "gn:country_code":"IN",
    "gn:dem":279,
    "gn:feature_class":"P",
    "gn:feature_code":"PPL",
    "gn:name":"Chandwar",
    "gn:population":0,
    "gn:timezone":"Asia/Kolkata",
    "iso:country":"IN",
    "ks:ks_name":"Chanduyar",
    "ks:ks_pop":885,
    "ks:ks_type":"VILLAGE",
    "name:eng_x_preferred":[
        "Chanduyar"
    ],
    "name:eng_x_variant":[
        "Chandwar"
    ],
    "wof:name":"Chanduyar",
    "wof:placetype":"locality",
    "wof:population":885
},
  "geometry": {"coordinates":[82.78603,24.132432],"type":"Point"}
}