{
  "type": "Feature",
  "properties": {
    "iso:country":"IN",
    "ks:ks_name":"Hulugere",
    "ks:ks_pop":44,
    "ks:ks_type":"HABITATION",
    "name:eng_x_preferred":[
        "Hulugere"
    ],
    "wof:name":"Hulugere",
    "wof:placetype":"locality",
    "wof:population":44
},
  "geometry": {"coordinates":[74.35552,14.624832],"type":"Point"}
}