{
  "type": "Feature",
  "properties": {
    "iso:country":"IN",
    "ks:ks_name":"Lakshmipos",
    "ks:ks_pop":427,
    "ks:ks_type":"VILLAGE",
    "ks:ks_uagg_main":0,
    "name:eng_x_preferred":[
        "Lakshmipos"
    ],
    "wof:name":"Lakshmipos",
    "wof:placetype":"neighbourhood",
    "wof:population":427
},
  "geometry": {"coordinates":[85.461861,22.568844],"type":"Point"}
}