{
  "type": "Feature",
  "properties": {
    "iso:country":"IN",
    "ks:ks_name":"Channegowdanadoddi",
    "ks:ks_pop":1077,
    "ks:ks_type":"HABITATION",
    "name:eng_x_preferred":[
        "Channegowdanadoddi"
    ],
    "wof:name":"Channegowdanadoddi",
    "wof:placetype":"locality",
    "wof:population":1077
},
  "geometry": {"coordinates":[77.025716,12.57647],"type":"Point"}
}