{
  "type": "Feature",
  "properties": {
    "iso:country":"IN",
    "ks:ks_name":"Dasanapalli",
    "ks:ks_pop":547,
    "ks:ks_type":"HABITATION",
    "name:eng_x_preferred":[
        "Dasanapalli"
    ],
    "wof:name":"Dasanapalli",
    "wof:placetype":"locality",
    "wof:population":547
},
  "geometry": {"coordinates":[84.69983499999999,19.659819],"type":"Point"}
}