{
  "type": "Feature",
  "properties": {
    "iso:country":"IN",
    "ks:ks_alt_nam":"SHINDE DALWAIVASTI",
    "ks:ks_name":"Shinde Dalwaivasti",
    "ks:ks_pop":52,
    "ks:ks_type":"HABITATION",
    "name:eng_x_preferred":[
        "Shinde Dalwaivasti"
    ],
    "wof:name":"Shinde Dalwaivasti",
    "wof:placetype":"locality",
    "wof:population":52
},
  "geometry": {"coordinates":[75.51478,16.997469],"type":"Point"}
}