{
  "type": "Feature",
  "properties": {
    "iso:country":"IN",
    "ks:ks_alt_nam":"telabhanguni",
    "ks:ks_name":"Telabhanguni",
    "ks:ks_pop":51,
    "ks:ks_type":"HABITATION",
    "name:eng_x_preferred":[
        "Telabhanguni"
    ],
    "wof:name":"Telabhanguni",
    "wof:placetype":"locality",
    "wof:population":51
},
  "geometry": {"coordinates":[84.50774699999999,21.399934],"type":"Point"}
}