{
  "type": "Feature",
  "properties": {
    "iso:country":"IN",
    "ks:ks_alt_nam":"M\u0101kali State Forest",
    "ks:ks_name":"Makali State Forest",
    "ks:ks_pop":674,
    "ks:ks_type":"VILLAGE",
    "name:eng_x_preferred":[
        "Makali State Forest"
    ],
    "name:eng_x_variant":[
        "M\u0101kali State Forest"
    ],
    "wof:name":"Makali State Forest",
    "wof:placetype":"locality",
    "wof:population":674
},
  "geometry": {"coordinates":[77.145847,12.758138],"type":"Point"}
}