{
  "type": "Feature",
  "properties": {
    "iso:country":"IN",
    "ks:ks_name":"Cross Road",
    "ks:ks_pop":200,
    "ks:ks_type":"HABITATION",
    "name:eng_x_preferred":[
        "Cross Road"
    ],
    "wof:name":"Cross Road",
    "wof:placetype":"locality",
    "wof:population":200
},
  "geometry": {"coordinates":[79.07854500000001,13.342681],"type":"Point"}
}