{
  "type": "Feature",
  "properties": {
    "gn:admin1_code":"19.0",
    "gn:admin2_code":"571.0",
    "gn:asciiname":"Mattigattapalya",
    "gn:country_code":"IN",
    "gn:dem":753,
    "gn:feature_class":"P",
    "gn:feature_code":"PPL",
    "gn:name":"Mattigattap\u0101lya",
    "gn:population":0,
    "gn:timezone":"Asia/Kolkata",
    "iso:country":"IN",
    "wof:name":"Mattigattapalya",
    "wof:placetype":"neighbourhood"
},
  "geometry": {"coordinates":[76.48305000000001,13.46077],"type":"Point"}
}