{
  "type": "Feature",
  "properties": {
    "iso:country":"IN",
    "ks:ks_name":"Pikar",
    "ks:ks_pop":758,
    "ks:ks_type":"VILLAGE",
    "name:eng_x_preferred":[
        "Pikar"
    ],
    "wof:name":"Pikar",
    "wof:placetype":"locality",
    "wof:population":758
},
  "geometry": {"coordinates":[83.076775,26.392871],"type":"Point"}
}