{
  "type": "Feature",
  "properties": {
    "gn:admin1_code":"19.0",
    "gn:admin2_code":"564.0",
    "gn:asciiname":"Lambadi Huts",
    "gn:country_code":"IN",
    "gn:dem":566,
    "gn:feature_class":"P",
    "gn:feature_code":"PPL",
    "gn:name":"Lamb\u0101di Huts",
    "gn:population":0,
    "gn:timezone":"Asia/Kolkata",
    "iso:country":"IN",
    "wof:name":"Lambadi Huts",
    "wof:placetype":"locality"
},
  "geometry": {"coordinates":[75.42891999999998,14.95202],"type":"Point"}
}