{
  "type": "Feature",
  "properties": {
    "gn:admin1_code":"19.0",
    "gn:admin2_code":"568.0",
    "gn:asciiname":"Gundmane",
    "gn:country_code":"IN",
    "gn:dem":618,
    "gn:feature_class":"P",
    "gn:feature_code":"PPL",
    "gn:name":"Gundman\u0113",
    "gn:population":0,
    "gn:timezone":"Asia/Kolkata",
    "iso:country":"IN",
    "wof:name":"Gundmane",
    "wof:placetype":"locality"
},
  "geometry": {"coordinates":[75.10191,13.61141],"type":"Point"}
}