{
  "type": "Feature",
  "properties": {
    "gn:admin1_code":"19.0",
    "gn:admin2_code":"568.0",
    "gn:asciiname":"Gundmane",
    "gn:country_code":"IN",
    "gn:dem":618,
    "gn:feature_class":"P",
    "gn:feature_code":"PPL",
    "gn:name":"Gundman\u0113",
    "gn:population":0,
    "gn:timezone":"Asia/Kolkata",
    "iso:country":"IN",
    "ks:ks_name":"Gundumane",
    "ks:ks_pop":28,
    "ks:ks_type":"HABITATION",
    "name:eng_x_preferred":[
        "Gundumane"
    ],
    "name:eng_x_variant":[
        "Gundmane"
    ],
    "wof:name":"Gundumane",
    "wof:placetype":"locality",
    "wof:population":28
},
  "geometry": {"coordinates":[75.105014,13.620341],"type":"Point"}
}