{
  "type": "Feature",
  "properties": {
    "iso:country":"IN",
    "ks:ks_name":"Nutana Basantabana",
    "ks:ks_pop":208,
    "ks:ks_type":"VILLAGE",
    "name:eng_x_preferred":[
        "Nutana Basantabana"
    ],
    "wof:name":"Nutana Basantabana",
    "wof:placetype":"locality",
    "wof:population":208
},
  "geometry": {"coordinates":[85.047281,19.648187],"type":"Point"}
}