{
  "type": "Feature",
  "properties": {
    "iso:country":"IN",
    "ks:ks_alt_nam":"KADAM VASTI",
    "ks:ks_name":"Kadam Vasti",
    "ks:ks_pop":90,
    "ks:ks_type":"HABITATION",
    "name:eng_x_preferred":[
        "Kadam Vasti"
    ],
    "wof:name":"Kadam Vasti",
    "wof:placetype":"locality",
    "wof:population":90
},
  "geometry": {"coordinates":[74.606206,17.298823],"type":"Point"}
}