{
  "type": "Feature",
  "properties": {
    "gn:admin1_code":"40.0",
    "gn:admin2_code":"534.0",
    "gn:asciiname":"Masaipeta",
    "gn:country_code":"IN",
    "gn:dem":315,
    "gn:feature_class":"P",
    "gn:feature_code":"PPL",
    "gn:name":"Mas\u0101ipeta",
    "gn:population":0,
    "gn:timezone":"Asia/Kolkata",
    "iso:country":"IN",
    "wof:name":"Masaipeta",
    "wof:placetype":"locality"
},
  "geometry": {"coordinates":[78.62406,18.79959],"type":"Point"}
}