{
  "type": "Feature",
  "properties": {
    "iso:country":"IN",
    "ks:ks_name":"Madenur",
    "ks:ks_pop":10,
    "ks:ks_type":"HABITATION",
    "name:eng_x_preferred":[
        "Madenur"
    ],
    "wof:name":"Madenur",
    "wof:placetype":"locality",
    "wof:population":10
},
  "geometry": {"coordinates":[74.88666600000001,13.972272],"type":"Point"}
}