{
  "type": "Feature",
  "properties": {
    "iso:country":"IN",
    "ks:ks_name":"Vinobajinagar",
    "ks:ks_pop":1040,
    "ks:ks_type":"HABITATION",
    "name:eng_x_preferred":[
        "Vinobajinagar"
    ],
    "wof:name":"Vinobajinagar",
    "wof:placetype":"locality",
    "wof:population":1040
},
  "geometry": {"coordinates":[77.71684399999999,11.476083],"type":"Point"}
}