{
  "type": "Feature",
  "properties": {
    "gn:admin1_code":"40",
    "gn:admin2_code":"541.0",
    "gn:asciiname":"Kattigudem",
    "gn:country_code":"IN",
    "gn:dem":76,
    "gn:feature_class":"P",
    "gn:feature_code":"PPL",
    "gn:name":"Kattig\u016bdem",
    "gn:population":0,
    "gn:timezone":"Asia/Kolkata",
    "iso:country":"IN",
    "ks:ks_name":"C Kathigudem",
    "ks:ks_pop":1225,
    "ks:ks_type":"HABITATION",
    "name:eng_x_preferred":[
        "C Kathigudem"
    ],
    "name:eng_x_variant":[
        "Kattigudem"
    ],
    "wof:name":"C Kathigudem",
    "wof:placetype":"locality",
    "wof:population":1225
},
  "geometry": {"coordinates":[80.80442499999999,18.084459],"type":"Point"}
}