{
  "type": "Feature",
  "properties": {
    "gn:admin1_code":"11.0",
    "gn:admin2_code":"26.0",
    "gn:asciiname":"Anas",
    "gn:country_code":"IN",
    "gn:dem":1159,
    "gn:feature_class":"P",
    "gn:feature_code":"PPL",
    "gn:name":"\u0100nas",
    "gn:population":0,
    "gn:timezone":"Asia/Kolkata",
    "iso:country":"IN",
    "name:afr_x_preferred":[
        "Anas"
    ],
    "name:ara_x_preferred":[
        "\u0623\u0646\u0633"
    ],
    "name:aze_x_preferred":[
        "\u00c7ay \u00f6rd\u0259yi"
    ],
    "name:ben_x_preferred":[
        "\u0985\u09cd\u09af\u09be\u09a8\u09be\u09b8"
    ],
    "name:bre_x_preferred":[
        "Anas"
    ],
    "name:bul_x_preferred":[
        "\u041f\u0430\u0442\u0438\u0446\u0438"
    ],
    "name:cat_x_preferred":[
        "Anas"
    ],
    "name:ceb_x_preferred":[
        "Anas"
    ],
    "name:ces_x_preferred":[
        "Anas"
    ],
    "name:dan_x_preferred":[
        "Anas"
    ],
    "name:deu_x_preferred":[
        "Eigentliche Enten"
    ],
    "name:epo_x_preferred":[
        "Anas"
    ],
    "name:est_x_preferred":[
        "Part"
    ],
    "name:eus_x_preferred":[
        "Anas"
    ],
    "name:fas_x_preferred":[
        "\u0627\u0646\u0633"
    ],
    "name:fin_x_preferred":[
        "Sorsat"
    ],
    "name:fra_x_preferred":[
        "Anas"
    ],
    "name:fry_x_preferred":[
        "Einen"
    ],
    "name:glg_x_preferred":[
        "Anas"
    ],
    "name:heb_x_preferred":[
        "\u05d1\u05e8\u05d5\u05d5\u05d6"
    ],
    "name:hun_x_preferred":[
        "Anas"
    ],
    "name:ita_x_preferred":[
        "Anas"
    ],
    "name:kaz_x_preferred":[
        "\u04e8\u0437\u0435\u043d \u04af\u0439\u0440\u0435\u043a\u0442\u0435\u0440\u0456"
    ],
    "name:kir_x_preferred":[
        "\u0421\u043e\u043d\u043e\u043b\u043e\u0440"
    ],
    "name:kor_x_preferred":[
        "\uc624\ub9ac\uc18d"
    ],
    "name:lat_x_preferred":[
        "Anas"
    ],
    "name:lav_x_preferred":[
        "Me\u017ea p\u012bles"
    ],
    "name:lit_x_preferred":[
        "Plaukiojan\u010dios antys"
    ],
    "name:nld_x_preferred":[
        "Anas"
    ],
    "name:nno_x_preferred":[
        "Anas"
    ],
    "name:pol_x_preferred":[
        "Anas"
    ],
    "name:por_x_preferred":[
        "Anas"
    ],
    "name:ron_x_preferred":[
        "Anas"
    ],
    "name:rus_x_preferred":[
        "\u0420\u0435\u0447\u043d\u044b\u0435 \u0443\u0442\u043a\u0438"
    ],
    "name:sco_x_preferred":[
        "Anas"
    ],
    "name:spa_x_preferred":[
        "Anas"
    ],
    "name:srp_x_preferred":[
        "\u041f\u043b\u043e\u0432\u043a\u0430"
    ],
    "name:swe_x_preferred":[
        "Anas"
    ],
    "name:tur_x_preferred":[
        "Anas"
    ],
    "name:ukr_x_preferred":[
        "\u041a\u0430\u0447\u043a\u0430"
    ],
    "name:vep_x_preferred":[
        "Sorz"
    ],
    "name:vie_x_preferred":[
        "Anas"
    ],
    "name:war_x_preferred":[
        "Anas"
    ],
    "wof:name":"Anas",
    "wof:placetype":"locality"
},
  "geometry": {"coordinates":[77.53631,31.376],"type":"Point"}
}