{
  "type": "Feature",
  "properties": {
    "iso:country":"IN",
    "ks:ks_name":"Garura",
    "ks:ks_pop":694,
    "ks:ks_type":"VILLAGE",
    "ks:ks_uagg_main":0,
    "name:eng_x_preferred":[
        "Garura"
    ],
    "wof:name":"Garura",
    "wof:placetype":"neighbourhood",
    "wof:population":694
},
  "geometry": {"coordinates":[87.44073400000001,21.861157],"type":"Point"}
}