{
  "type": "Feature",
  "properties": {
    "gn:admin1_code":"12.0",
    "gn:admin2_code":"9.0",
    "gn:asciiname":"Laharwalpur",
    "gn:country_code":"IN",
    "gn:dem":1584,
    "gn:feature_class":"P",
    "gn:feature_code":"PPL",
    "gn:name":"Laharw\u0101lpur",
    "gn:population":0,
    "gn:timezone":"Asia/Kolkata",
    "iso:country":"IN",
    "name:eng_x_preferred":[
        "Laharw\u0101lpur"
    ],
    "wof:name":"Laharwalpur",
    "wof:placetype":"locality"
},
  "geometry": {"coordinates":[74.58808000000001,34.4076],"type":"Point"}
}