{
  "type": "Feature",
  "properties": {
    "gn:admin1_code":"13.0",
    "gn:admin2_code":"588.0",
    "gn:asciiname":"Karingana",
    "gn:country_code":"IN",
    "gn:dem":27,
    "gn:feature_class":"P",
    "gn:feature_code":"PPL",
    "gn:name":"Karingana",
    "gn:population":0,
    "gn:timezone":"Asia/Kolkata",
    "iso:country":"IN",
    "wof:name":"Karingana",
    "wof:placetype":"locality"
},
  "geometry": {"coordinates":[74.99027,12.60433],"type":"Point"}
}