{
  "type": "Feature",
  "properties": {
    "iso:country":"IN",
    "ks:ks_name":"Dhuriwadi",
    "ks:ks_pop":105,
    "ks:ks_type":"HABITATION",
    "name:eng_x_preferred":[
        "Dhuriwadi"
    ],
    "wof:name":"Dhuriwadi",
    "wof:placetype":"locality",
    "wof:population":105
},
  "geometry": {"coordinates":[73.68338,15.897195],"type":"Point"}
}