{
  "type": "Feature",
  "properties": {
    "iso:country":"IN",
    "ks:ks_name":"Dakhin Harijan Tola",
    "ks:ks_pop":336,
    "ks:ks_type":"HABITATION",
    "name:eng_x_preferred":[
        "Dakhin Harijan Tola"
    ],
    "wof:name":"Dakhin Harijan Tola",
    "wof:placetype":"locality",
    "wof:population":336
},
  "geometry": {"coordinates":[84.126823,25.448601],"type":"Point"}
}