{
  "type": "Feature",
  "properties": {
    "gn:admin1_code":"19.0",
    "gn:admin2_code":"568.0",
    "gn:asciiname":"Nantur",
    "gn:country_code":"IN",
    "gn:dem":630,
    "gn:feature_class":"P",
    "gn:feature_code":"PPL",
    "gn:name":"Nantur",
    "gn:population":0,
    "gn:timezone":"Asia/Kolkata",
    "iso:country":"IN",
    "wof:name":"Nantur",
    "wof:placetype":"locality"
},
  "geometry": {"coordinates":[75.16150999999998,13.54359],"type":"Point"}
}