{
  "type": "Feature",
  "properties": {
    "iso:country":"IN",
    "ks:ks_name":"Baliani",
    "ks:ks_pop":296,
    "ks:ks_type":"HABITATION",
    "name:eng_x_preferred":[
        "Baliani"
    ],
    "wof:name":"Baliani",
    "wof:placetype":"locality",
    "wof:population":296
},
  "geometry": {"coordinates":[95.165766,27.067174],"type":"Point"}
}