{
  "type": "Feature",
  "properties": {
    "iso:country":"IN",
    "ks:ks_alt_nam":"Chakhowajar N.C.-2",
    "ks:ks_name":"Chakhowajar N.c.-2",
    "ks:ks_pop":831,
    "ks:ks_type":"HABITATION",
    "ks:ks_uagg_main":0,
    "name:eng_x_preferred":[
        "Chakhowajar N.c.-2"
    ],
    "wof:name":"Chakhowajar N.c.-2",
    "wof:placetype":"neighbourhood",
    "wof:population":831
},
  "geometry": {"coordinates":[90.897256,26.135698],"type":"Point"}
}