{
  "type": "Feature",
  "properties": {
    "iso:country":"IN",
    "ks:ks_name":"Chapalavaripalli",
    "ks:ks_pop":55,
    "ks:ks_type":"HABITATION",
    "name:eng_x_preferred":[
        "Chapalavaripalli"
    ],
    "wof:name":"Chapalavaripalli",
    "wof:placetype":"locality",
    "wof:population":55
},
  "geometry": {"coordinates":[79.342418,14.154584],"type":"Point"}
}