{
  "type": "Feature",
  "properties": {
    "iso:country":"IN",
    "ks:ks_name":"Hathiyara",
    "ks:ks_pop":166,
    "ks:ks_type":"HABITATION",
    "name:eng_x_preferred":[
        "Hathiyara"
    ],
    "wof:name":"Hathiyara",
    "wof:placetype":"locality",
    "wof:population":166
},
  "geometry": {"coordinates":[86.822923,24.386726],"type":"Point"}
}