{
  "type": "Feature",
  "properties": {
    "gn:admin1_code":"19.0",
    "gn:admin2_code":"574.0",
    "gn:asciiname":"Devalkeri",
    "gn:country_code":"IN",
    "gn:dem":983,
    "gn:feature_class":"P",
    "gn:feature_code":"PPL",
    "gn:name":"Devalkeri",
    "gn:population":0,
    "gn:timezone":"Asia/Kolkata",
    "iso:country":"IN",
    "wof:name":"Devalkeri",
    "wof:placetype":"locality"
},
  "geometry": {"coordinates":[75.65572,13.00465],"type":"Point"}
}