{
  "type": "Feature",
  "properties": {
    "gn:admin1_code":"25.0",
    "gn:admin2_code":"611.0",
    "gn:asciiname":"Thoddanni",
    "gn:country_code":"IN",
    "gn:dem":1943,
    "gn:feature_class":"P",
    "gn:feature_code":"PPL",
    "gn:name":"Thoddanni",
    "gn:population":0,
    "gn:timezone":"Asia/Kolkata",
    "iso:country":"IN",
    "wof:name":"Thoddanni",
    "wof:placetype":"locality"
},
  "geometry": {"coordinates":[76.73311,11.35325],"type":"Point"}
}