{
  "type": "Feature",
  "properties": {
    "iso:country":"IN",
    "ks:ks_name":"Hunasanahalli",
    "ks:ks_pop":591,
    "ks:ks_type":"VILLAGE",
    "name:eng_x_preferred":[
        "Hunasanahalli"
    ],
    "wof:name":"Hunasanahalli",
    "wof:placetype":"locality",
    "wof:population":591
},
  "geometry": {"coordinates":[75.63513399999999,13.695717],"type":"Point"}
}