{
  "type": "Feature",
  "properties": {
    "gn:admin1_code":"3.0",
    "gn:admin2_code":"312.0",
    "gn:asciiname":"Latum Chuk",
    "gn:country_code":"IN",
    "gn:dem":100,
    "gn:feature_class":"P",
    "gn:feature_code":"PPL",
    "gn:name":"Latum Chuk",
    "gn:population":0,
    "gn:timezone":"Asia/Kolkata",
    "iso:country":"IN",
    "wof:name":"Latum Chuk",
    "wof:placetype":"locality"
},
  "geometry": {"coordinates":[94.46195,27.0589],"type":"Point"}
}