{
  "type": "Feature",
  "properties": {
    "iso:country":"IN",
    "ks:ks_name":"Morcha",
    "ks:ks_pop":722,
    "ks:ks_type":"HABITATION",
    "name:eng_x_preferred":[
        "Morcha"
    ],
    "wof:name":"Morcha",
    "wof:placetype":"locality",
    "wof:population":722
},
  "geometry": {"coordinates":[81.835854,24.326605],"type":"Point"}
}