{
  "type": "Feature",
  "properties": {
    "gn:admin1_code":"35",
    "gn:admin2_code":"425.0",
    "gn:asciiname":"Maharkhua",
    "gn:country_code":"IN",
    "gn:dem":480,
    "gn:feature_class":"P",
    "gn:feature_code":"PPL",
    "gn:name":"Maharkhua",
    "gn:population":0,
    "gn:timezone":"Asia/Kolkata",
    "iso:country":"IN",
    "name:eng_x_preferred":[
        "Maharkhua"
    ],
    "wof:name":"Maharkhua",
    "wof:placetype":"locality"
},
  "geometry": {"coordinates":[79.80797,24.45506],"type":"Point"}
}