{
  "type": "Feature",
  "properties": {
    "gn:admin1_code":"35",
    "gn:admin2_code":"425.0",
    "gn:asciiname":"Maharkhua",
    "gn:country_code":"IN",
    "gn:dem":480,
    "gn:feature_class":"P",
    "gn:feature_code":"PPL",
    "gn:name":"Maharkhua",
    "gn:population":0,
    "gn:timezone":"Asia/Kolkata",
    "iso:country":"IN",
    "ks:ks_name":"Maharkhuwa",
    "ks:ks_pop":309,
    "ks:ks_type":"HABITATION",
    "name:eng_x_preferred":[
        "Maharkhuwa"
    ],
    "name:eng_x_variant":[
        "Maharkhua"
    ],
    "wof:name":"Maharkhuwa",
    "wof:placetype":"locality",
    "wof:population":309
},
  "geometry": {"coordinates":[79.80843299999999,24.454507],"type":"Point"}
}