{
  "type": "Feature",
  "properties": {
    "iso:country":"IN",
    "ks:ks_name":"Lachiganitanda",
    "ks:ks_pop":89,
    "ks:ks_type":"HABITATION",
    "name:eng_x_preferred":[
        "Lachiganitanda"
    ],
    "wof:name":"Lachiganitanda",
    "wof:placetype":"locality",
    "wof:population":89
},
  "geometry": {"coordinates":[78.24540500000001,16.968877],"type":"Point"}
}