{
  "type": "Feature",
  "properties": {
    "iso:country":"IN",
    "ks:ks_name":"Rangaparadahatti",
    "ks:ks_pop":217,
    "ks:ks_type":"HABITATION",
    "name:eng_x_preferred":[
        "Rangaparadahatti"
    ],
    "wof:name":"Rangaparadahatti",
    "wof:placetype":"locality",
    "wof:population":217
},
  "geometry": {"coordinates":[76.648123,13.550796],"type":"Point"}
}