{
  "type": "Feature",
  "properties": {
    "gn:admin1_code":"16",
    "gn:admin2_code":"524.0",
    "gn:asciiname":"Hudgyachiwadi",
    "gn:country_code":"IN",
    "gn:dem":602,
    "gn:feature_class":"P",
    "gn:feature_code":"PPL",
    "gn:name":"Hudgy\u0101ch\u012bw\u0101di",
    "gn:population":0,
    "gn:timezone":"Asia/Kolkata",
    "iso:country":"IN",
    "wof:name":"Hudgyachiwadi",
    "wof:placetype":"locality"
},
  "geometry": {"coordinates":[76.81428000000002,18.39134],"type":"Point"}
}