{
  "type": "Feature",
  "properties": {
    "iso:country":"IN",
    "ks:ks_name":"Satgaon",
    "ks:ks_pop":2101,
    "ks:ks_type":"VILLAGE",
    "name:eng_x_preferred":[
        "Satgaon"
    ],
    "wof:name":"Satgaon",
    "wof:placetype":"locality",
    "wof:population":2101
},
  "geometry": {"coordinates":[89.17144,26.32865],"type":"Point"}
}