{
  "type": "Feature",
  "properties": {
    "gn:admin1_code":"23.0",
    "gn:admin2_code":"41.0",
    "gn:asciiname":"Rahimabad Kalan",
    "gn:country_code":"IN",
    "gn:dem":254,
    "gn:feature_class":"P",
    "gn:feature_code":"PPL",
    "gn:name":"Rah\u012bm\u0101b\u0101d Kal\u0101n",
    "gn:population":0,
    "gn:timezone":"Asia/Kolkata",
    "iso:country":"IN",
    "wof:name":"Rahimabad Kalan",
    "wof:placetype":"locality"
},
  "geometry": {"coordinates":[76.14806999999998,30.96163],"type":"Point"}
}