{
  "type": "Feature",
  "properties": {
    "iso:country":"IN",
    "ks:ks_alt_nam":"Kotalgadda tanda",
    "ks:ks_name":"Kotalgadda Tanda",
    "ks:ks_pop":105,
    "ks:ks_type":"HABITATION",
    "name:eng_x_preferred":[
        "Kotalgadda Tanda"
    ],
    "wof:name":"Kotalgadda Tanda",
    "wof:placetype":"locality",
    "wof:population":105
},
  "geometry": {"coordinates":[78.16771799999999,18.239008],"type":"Point"}
}