{
  "type": "Feature",
  "properties": {
    "iso:country":"IN",
    "ks:ks_name":"Manikantapuram",
    "ks:ks_pop":146,
    "ks:ks_type":"HABITATION",
    "name:eng_x_preferred":[
        "Manikantapuram"
    ],
    "wof:name":"Manikantapuram",
    "wof:placetype":"locality",
    "wof:population":146
},
  "geometry": {"coordinates":[78.606251,15.556594],"type":"Point"}
}