{
  "type": "Feature",
  "properties": {
    "iso:country":"IN",
    "ks:ks_name":"Thaigirgui",
    "ks:ks_pop":335,
    "ks:ks_type":"HABITATION",
    "name:eng_x_preferred":[
        "Thaigirgui"
    ],
    "wof:name":"Thaigirgui",
    "wof:placetype":"locality",
    "wof:population":335
},
  "geometry": {"coordinates":[93.914705,26.125178],"type":"Point"}
}