{
  "type": "Feature",
  "properties": {
    "iso:country":"IN",
    "ks:ks_name":"Paradhipada",
    "ks:ks_pop":83,
    "ks:ks_type":"HABITATION",
    "name:eng_x_preferred":[
        "Paradhipada"
    ],
    "wof:name":"Paradhipada",
    "wof:placetype":"locality",
    "wof:population":83
},
  "geometry": {"coordinates":[73.23593200000001,19.81044],"type":"Point"}
}