{
  "type": "Feature",
  "properties": {
    "iso:country":"IN",
    "ks:ks_name":"Ayamukku Paadam",
    "ks:ks_pop":719,
    "ks:ks_type":"HABITATION",
    "ks:ks_uagg_main":0,
    "name:eng_x_preferred":[
        "Ayamukku Paadam"
    ],
    "wof:name":"Ayamukku Paadam",
    "wof:placetype":"neighbourhood",
    "wof:population":719
},
  "geometry": {"coordinates":[76.128834,10.648865],"type":"Point"}
}