{
  "type": "Feature",
  "properties": {
    "gn:admin1_code":"3.0",
    "gn:admin2_code":"325.0",
    "gn:asciiname":"Saledal",
    "gn:country_code":"IN",
    "gn:dem":58,
    "gn:feature_class":"P",
    "gn:feature_code":"PPL",
    "gn:name":"Saledal",
    "gn:population":0,
    "gn:timezone":"Asia/Kolkata",
    "iso:country":"IN",
    "wof:name":"Saledal",
    "wof:placetype":"locality"
},
  "geometry": {"coordinates":[91.78124,26.42869],"type":"Point"}
}