{
  "type": "Feature",
  "properties": {
    "gn:admin1_code":"16.0",
    "gn:admin2_code":"523.0",
    "gn:asciiname":"Telgaon",
    "gn:country_code":"IN",
    "gn:dem":434,
    "gn:feature_class":"P",
    "gn:feature_code":"PPL",
    "gn:name":"Telgaon",
    "gn:population":0,
    "gn:timezone":"Asia/Kolkata",
    "iso:country":"IN",
    "name:ben_x_preferred":[
        "\u099f\u09c7\u09b2\u0997\u09be\u0981\u0993"
    ],
    "name:bpy_x_preferred":[
        "\u099f\u09c7\u09b2\u0997\u09be\u0981\u0993"
    ],
    "name:ita_x_preferred":[
        "Telgaon"
    ],
    "name:msa_x_preferred":[
        "Telgaon"
    ],
    "name:nld_x_preferred":[
        "Telgaon"
    ],
    "name:por_x_preferred":[
        "Telgaon"
    ],
    "name:urd_x_preferred":[
        "\u062a\u06cc\u0644 \u06af\u0627\u0624\u06ba"
    ],
    "name:vie_x_preferred":[
        "Telgaon"
    ],
    "name:zho_x_preferred":[
        "\u6cf0\u5c14\u52a0\u5965\u6069"
    ],
    "wof:name":"Telgaon",
    "wof:placetype":"locality"
},
  "geometry": {"coordinates":[76.03714000000002,19.13246],"type":"Point"}
}