{
  "type": "Feature",
  "properties": {
    "iso:country":"IN",
    "ks:ks_name":"Jhirijhira",
    "ks:ks_pop":175,
    "ks:ks_type":"VILLAGE",
    "name:eng_x_preferred":[
        "Jhirijhira"
    ],
    "wof:name":"Jhirijhira",
    "wof:placetype":"locality",
    "wof:population":175
},
  "geometry": {"coordinates":[84.416706,19.557245],"type":"Point"}
}