{
  "type": "Feature",
  "properties": {
    "gn:admin1_code":"35",
    "gn:admin2_code":"428.0",
    "gn:asciiname":"Halgaj",
    "gn:country_code":"IN",
    "gn:dem":345,
    "gn:feature_class":"P",
    "gn:feature_code":"PPL",
    "gn:name":"Halgaj",
    "gn:population":0,
    "gn:timezone":"Asia/Kolkata",
    "iso:country":"IN",
    "wof:name":"Halgaj",
    "wof:placetype":"locality"
},
  "geometry": {"coordinates":[79.60319,23.80126],"type":"Point"}
}