{
  "type": "Feature",
  "properties": {
    "gn:admin1_code":"12.0",
    "gn:admin2_code":"006",
    "gn:asciiname":"Kotli",
    "gn:country_code":"IN",
    "gn:dem":1112,
    "gn:feature_class":"P",
    "gn:feature_code":"PPL",
    "gn:name":"Kotli",
    "gn:population":0,
    "gn:timezone":"Asia/Kolkata",
    "iso:country":"IN",
    "wof:name":"Kotli",
    "wof:placetype":"locality"
},
  "geometry": {"coordinates":[74.18000000000001,33.29414000000001],"type":"Point"}
}