{
  "type": "Feature",
  "properties": {
    "iso:country":"IN",
    "ks:ks_alt_nam":"N\u0101rang\u012bp\u0101li",
    "ks:ks_name":"Narangipali",
    "ks:ks_type":"VILLAGE",
    "name:eng_x_preferred":[
        "Narangipali"
    ],
    "name:eng_x_variant":[
        "N\u0101rang\u012bp\u0101li"
    ],
    "wof:name":"Narangipali",
    "wof:placetype":"locality"
},
  "geometry": {"coordinates":[84.131327,21.221699],"type":"Point"}
}