{
  "type": "Feature",
  "properties": {
    "iso:country":"IN",
    "ks:ks_name":"Damor Falia",
    "ks:ks_pop":390,
    "ks:ks_type":"HABITATION",
    "name:eng_x_preferred":[
        "Damor Falia"
    ],
    "wof:name":"Damor Falia",
    "wof:placetype":"locality",
    "wof:population":390
},
  "geometry": {"coordinates":[73.753967,22.552017],"type":"Point"}
}