{
  "type": "Feature",
  "properties": {
    "iso:country":"IN",
    "ks:ks_name":"Chanraiya",
    "ks:ks_pop":777,
    "ks:ks_type":"VILLAGE",
    "name:eng_x_preferred":[
        "Chanraiya"
    ],
    "wof:name":"Chanraiya",
    "wof:placetype":"locality",
    "wof:population":777
},
  "geometry": {"coordinates":[83.23700100000001,27.323588],"type":"Point"}
}