{
  "type": "Feature",
  "properties": {
    "gn:admin1_code":"16.0",
    "gn:admin2_code":"506.0",
    "gn:asciiname":"Tudmapuri",
    "gn:country_code":"IN",
    "gn:dem":274,
    "gn:feature_class":"P",
    "gn:feature_code":"PPL",
    "gn:name":"Tudm\u0101pur\u012b",
    "gn:population":0,
    "gn:timezone":"Asia/Kolkata",
    "iso:country":"IN",
    "wof:name":"Tudmapuri",
    "wof:placetype":"locality"
},
  "geometry": {"coordinates":[80.02861,21.13664],"type":"Point"}
}