{
  "type": "Feature",
  "properties": {
    "gn:admin1_code":"12.0",
    "gn:admin2_code":"006",
    "gn:asciiname":"Gai",
    "gn:country_code":"IN",
    "gn:dem":1090,
    "gn:feature_class":"P",
    "gn:feature_code":"PPL",
    "gn:name":"Gai",
    "gn:population":0,
    "gn:timezone":"Asia/Kolkata",
    "iso:country":"IN",
    "name:cat_x_preferred":[
        "Gai"
    ],
    "name:ceb_x_preferred":[
        "Gai"
    ],
    "name:fra_x_preferred":[
        "Gai"
    ],
    "name:rus_x_preferred":[
        "\u0413\u0430\u0438"
    ],
    "name:spa_x_preferred":[
        "Gai"
    ],
    "name:swe_x_preferred":[
        "Gai"
    ],
    "name:ukr_x_preferred":[
        "\u0413\u0430\u0457"
    ],
    "name:zho_x_preferred":[
        "Gai"
    ],
    "wof:name":"Gai",
    "wof:placetype":"locality"
},
  "geometry": {"coordinates":[74.24336,33.3495],"type":"Point"}
}