{
  "type": "Feature",
  "properties": {
    "gn:admin1_code":"36.0",
    "gn:admin2_code":"193.0",
    "gn:asciiname":"Khadipur",
    "gn:country_code":"IN",
    "gn:dem":66,
    "gn:feature_class":"P",
    "gn:feature_code":"PPL",
    "gn:name":"Kh\u0101dipur",
    "gn:population":0,
    "gn:timezone":"Asia/Kolkata",
    "iso:country":"IN",
    "ks:ks_alt_nam":"Kh\u0101dipur",
    "ks:ks_name":"Khadipur",
    "ks:ks_pop":897,
    "ks:ks_type":"VILLAGE",
    "ks:ks_uagg_main":0,
    "name:eng_x_preferred":[
        "Khadipur"
    ],
    "name:eng_x_variant":[
        "Kh\u0101dipur"
    ],
    "wof:name":"Khadipur",
    "wof:placetype":"neighbourhood",
    "wof:population":897
},
  "geometry": {"coordinates":[84.21275799999999,25.95221],"type":"Point"}
}