{
  "type": "Feature",
  "properties": {
    "iso:country":"IN",
    "ks:ks_alt_nam":"Dawaguri II",
    "ks:ks_name":"Dawaguri Ii",
    "ks:ks_pop":653,
    "ks:ks_type":"HABITATION",
    "ks:ks_uagg_main":0,
    "name:eng_x_preferred":[
        "Dawaguri Ii"
    ],
    "wof:name":"Dawaguri Ii",
    "wof:placetype":"neighbourhood",
    "wof:population":653
},
  "geometry": {"coordinates":[89.903521,26.459685],"type":"Point"}
}