{
  "type": "Feature",
  "properties": {
    "iso:country":"IN",
    "ks:ks_name":"Peda Buruga-I",
    "ks:ks_pop":33,
    "ks:ks_type":"VILLAGE",
    "name:eng_x_preferred":[
        "Peda Buruga-I"
    ],
    "wof:name":"Peda Buruga-I",
    "wof:placetype":"locality",
    "wof:population":33
},
  "geometry": {"coordinates":[82.975504,18.066521],"type":"Point"}
}