{
  "type": "Feature",
  "properties": {
    "gn:admin1_code":"38.0",
    "gn:admin2_code":"358.0",
    "gn:asciiname":"Kundelwa",
    "gn:country_code":"IN",
    "gn:dem":246,
    "gn:feature_class":"P",
    "gn:feature_code":"PPL",
    "gn:name":"Kundelw\u0101",
    "gn:population":0,
    "gn:timezone":"Asia/Kolkata",
    "iso:country":"IN",
    "ks:ks_alt_nam":"Kundelw\u0101",
    "ks:ks_name":"Kundelwa",
    "ks:ks_pop":2725,
    "ks:ks_type":"VILLAGE",
    "name:eng_x_preferred":[
        "Kundelwa"
    ],
    "name:eng_x_variant":[
        "Kundelw\u0101"
    ],
    "wof:name":"Kundelwa",
    "wof:placetype":"locality",
    "wof:population":2725
},
  "geometry": {"coordinates":[84.188772,24.019731],"type":"Point"}
}