{
  "type": "Feature",
  "properties": {
    "iso:country":"IN",
    "ks:ks_name":"Alaskar Para",
    "ks:ks_pop":1102,
    "ks:ks_type":"HABITATION",
    "name:eng_x_preferred":[
        "Alaskar Para"
    ],
    "wof:name":"Alaskar Para",
    "wof:placetype":"locality",
    "wof:population":1102
},
  "geometry": {"coordinates":[88.70818,22.286693],"type":"Point"}
}