{
  "type": "Feature",
  "properties": {
    "iso:country":"IN",
    "ks:ks_name":"Khintar",
    "ks:ks_type":"VILLAGE",
    "name:eng_x_preferred":[
        "Khintar"
    ],
    "wof:name":"Khintar",
    "wof:placetype":"locality"
},
  "geometry": {"coordinates":[77.413234,26.578167],"type":"Point"}
}