{
  "type": "Feature",
  "properties": {
    "gn:admin1_code":"23",
    "gn:admin2_code":"37.0",
    "gn:asciiname":"Dhinpur",
    "gn:country_code":"IN",
    "gn:dem":240,
    "gn:feature_class":"P",
    "gn:feature_code":"PPL",
    "gn:name":"Dhinpur",
    "gn:population":0,
    "gn:timezone":"Asia/Kolkata",
    "iso:country":"IN",
    "ks:ks_name":"Dhinpur",
    "ks:ks_pop":382,
    "ks:ks_type":"VILLAGE",
    "name:eng_x_preferred":[
        "Dhinpur"
    ],
    "wof:name":"Dhinpur",
    "wof:placetype":"locality",
    "wof:population":382
},
  "geometry": {"coordinates":[75.700498,31.143241],"type":"Point"}
}