{
  "type": "Feature",
  "properties": {
    "gn:admin1_code":"37",
    "gn:admin2_code":"411.0",
    "gn:asciiname":"Matarbahra",
    "gn:country_code":"IN",
    "gn:dem":375,
    "gn:feature_class":"P",
    "gn:feature_code":"PPL",
    "gn:name":"M\u0101tarbahra",
    "gn:population":0,
    "gn:timezone":"Asia/Kolkata",
    "iso:country":"IN",
    "ks:ks_alt_nam":"M\u0101tarbahra",
    "ks:ks_name":"Matarbahra",
    "ks:ks_pop":157,
    "ks:ks_type":"VILLAGE",
    "name:eng_x_preferred":[
        "Matarbahra"
    ],
    "name:eng_x_variant":[
        "M\u0101tarbahra"
    ],
    "wof:name":"Matarbahra",
    "wof:placetype":"locality",
    "wof:population":157
},
  "geometry": {"coordinates":[82.35323099999999,20.94141],"type":"Point"}
}