{
  "type": "Feature",
  "properties": {
    "iso:country":"IN",
    "ks:ks_name":"11 RB",
    "ks:ks_pop":17,
    "ks:ks_type":"VILLAGE",
    "name:eng_x_preferred":[
        "11 RB"
    ],
    "wof:name":"11 RB",
    "wof:placetype":"locality",
    "wof:population":17
},
  "geometry": {"coordinates":[73.51523899999999,29.630189],"type":"Point"}
}