{
  "type": "Feature",
  "properties": {
    "gn:admin1_code":"16.0",
    "gn:admin2_code":"508.0",
    "gn:asciiname":"Gopnar",
    "gn:country_code":"IN",
    "gn:dem":261,
    "gn:feature_class":"P",
    "gn:feature_code":"PPL",
    "gn:name":"Gopn\u0101r",
    "gn:population":0,
    "gn:timezone":"Asia/Kolkata",
    "iso:country":"IN",
    "ks:ks_alt_nam":"Gopn\u0101r",
    "ks:ks_name":"Gopnar",
    "ks:ks_pop":178,
    "ks:ks_type":"VILLAGE",
    "name:eng_x_preferred":[
        "Gopnar"
    ],
    "name:eng_x_variant":[
        "Gopn\u0101r"
    ],
    "wof:name":"Gopnar",
    "wof:placetype":"locality",
    "wof:population":178
},
  "geometry": {"coordinates":[80.705879,19.487943],"type":"Point"}
}