{
  "type": "Feature",
  "properties": {
    "iso:country":"IN",
    "ks:ks_name":"Sarkari Purwa",
    "ks:ks_pop":160,
    "ks:ks_type":"HABITATION",
    "name:eng_x_preferred":[
        "Sarkari Purwa"
    ],
    "wof:name":"Sarkari Purwa",
    "wof:placetype":"locality",
    "wof:population":160
},
  "geometry": {"coordinates":[82.171938,26.913694],"type":"Point"}
}