{
  "type": "Feature",
  "properties": {
    "iso:country":"IN",
    "ks:ks_name":"Salamanda",
    "ks:ks_pop":65,
    "ks:ks_type":"HABITATION",
    "name:eng_x_preferred":[
        "Salamanda"
    ],
    "wof:name":"Salamanda",
    "wof:placetype":"locality",
    "wof:population":65
},
  "geometry": {"coordinates":[82.79673099999999,18.204304],"type":"Point"}
}