{
  "type": "Feature",
  "properties": {
    "iso:country":"IN",
    "ks:ks_name":"Baiju Tola",
    "ks:ks_pop":1000,
    "ks:ks_type":"HABITATION",
    "name:eng_x_preferred":[
        "Baiju Tola"
    ],
    "wof:name":"Baiju Tola",
    "wof:placetype":"locality",
    "wof:population":1000
},
  "geometry": {"coordinates":[84.579444,25.734906],"type":"Point"}
}