{
  "type": "Feature",
  "properties": {
    "iso:country":"IN",
    "ks:ks_name":"Sajankady",
    "ks:ks_pop":396,
    "ks:ks_type":"HABITATION",
    "name:eng_x_preferred":[
        "Sajankady"
    ],
    "wof:name":"Sajankady",
    "wof:placetype":"locality",
    "wof:population":396
},
  "geometry": {"coordinates":[75.23871699999999,12.618568],"type":"Point"}
}