{
  "type": "Feature",
  "properties": {
    "iso:country":"IN",
    "ks:ks_name":"Dhongiamba",
    "ks:ks_pop":812,
    "ks:ks_type":"VILLAGE",
    "name:eng_x_preferred":[
        "Dhongiamba"
    ],
    "wof:name":"Dhongiamba",
    "wof:placetype":"locality",
    "wof:population":812
},
  "geometry": {"coordinates":[73.68427800000001,20.914667],"type":"Point"}
}