{
  "type": "Feature",
  "properties": {
    "gn:admin1_code":"34.0",
    "gn:admin2_code":"221",
    "gn:asciiname":"Karian",
    "gn:country_code":"IN",
    "gn:dem":51,
    "gn:feature_class":"P",
    "gn:feature_code":"PPL",
    "gn:name":"Karian",
    "gn:population":0,
    "gn:timezone":"Asia/Kolkata",
    "iso:country":"IN",
    "ks:ks_name":"Karian",
    "ks:ks_pop":2086,
    "ks:ks_type":"VILLAGE",
    "ks:ks_uagg_main":0,
    "name:eng_x_preferred":[
        "Karian"
    ],
    "wof:name":"Karian",
    "wof:placetype":"neighbourhood",
    "wof:population":2086
},
  "geometry": {"coordinates":[86.00948699999999,25.858921],"type":"Point"}
}