{
  "type": "Feature",
  "properties": {
    "gn:admin1_code":"24",
    "gn:admin2_code":"112.0",
    "gn:asciiname":"Ren",
    "gn:country_code":"IN",
    "gn:dem":315,
    "gn:feature_class":"P",
    "gn:feature_code":"PPL",
    "gn:name":"Ren",
    "gn:population":0,
    "gn:timezone":"Asia/Kolkata",
    "iso:country":"IN",
    "name:deu_x_preferred":[
        "Ren"
    ],
    "name:oci_x_preferred":[
        "Ren"
    ],
    "name:pol_x_preferred":[
        "Ren"
    ],
    "name:por_x_preferred":[
        "Ren"
    ],
    "name:ron_x_preferred":[
        "Ren"
    ],
    "name:rus_x_preferred":[
        "\u0416\u044d\u043d\u044c"
    ],
    "name:srp_x_preferred":[
        "\u0420\u0435\u043d"
    ],
    "name:swe_x_preferred":[
        "Ren"
    ],
    "name:tur_x_preferred":[
        "Ren"
    ],
    "name:ukr_x_preferred":[
        "\u0416\u0435\u043d\u044c"
    ],
    "name:zho_x_preferred":[
        "\u4efb\u6c0f"
    ],
    "wof:name":"Ren",
    "wof:placetype":"locality"
},
  "geometry": {"coordinates":[74.08821,26.78176],"type":"Point"}
}