{
  "type": "Feature",
  "properties": {
    "iso:country":"IN",
    "ks:ks_name":"Gamaising Para",
    "ks:ks_pop":208,
    "ks:ks_type":"HABITATION",
    "name:eng_x_preferred":[
        "Gamaising Para"
    ],
    "wof:name":"Gamaising Para",
    "wof:placetype":"locality",
    "wof:population":208
},
  "geometry": {"coordinates":[91.88418,23.866742],"type":"Point"}
}