{
  "type": "Feature",
  "properties": {
    "iso:country":"IN",
    "ks:ks_name":"Kavelpur",
    "ks:ks_pop":225,
    "ks:ks_type":"HABITATION",
    "name:eng_x_preferred":[
        "Kavelpur"
    ],
    "wof:name":"Kavelpur",
    "wof:placetype":"locality",
    "wof:population":225
},
  "geometry": {"coordinates":[84.169651,25.915778],"type":"Point"}
}