{
  "type": "Feature",
  "properties": {
    "iso:country":"IN",
    "ks:ks_name":"Sonhari",
    "ks:ks_type":"VILLAGE",
    "name:eng_x_preferred":[
        "Sonhari"
    ],
    "wof:name":"Sonhari",
    "wof:placetype":"locality"
},
  "geometry": {"coordinates":[82.02957499999999,23.851125],"type":"Point"}
}