{
  "type": "Feature",
  "properties": {
    "iso:country":"IN",
    "ks:ks_name":"Chandsrikuna Cha",
    "ks:ks_pop":1431,
    "ks:ks_type":"VILLAGE",
    "ks:ks_uagg_main":0,
    "name:eng_x_preferred":[
        "Chandsrikuna Cha"
    ],
    "wof:name":"Chandsrikuna Cha",
    "wof:placetype":"locality",
    "wof:population":1431
},
  "geometry": {"coordinates":[92.337074,24.875706],"type":"Point"}
}