{
  "type": "Feature",
  "properties": {
    "iso:country":"IN",
    "ks:ks_name":"Buchipahari",
    "ks:ks_pop":6,
    "ks:ks_type":"HABITATION",
    "name:eng_x_preferred":[
        "Buchipahari"
    ],
    "wof:name":"Buchipahari",
    "wof:placetype":"locality",
    "wof:population":6
},
  "geometry": {"coordinates":[86.79791299999999,24.328626],"type":"Point"}
}