{
  "type": "Feature",
  "properties": {
    "iso:country":"IN",
    "ks:ks_alt_nam":"Gand\u0101padar",
    "ks:ks_name":"Gandapadar",
    "ks:ks_type":"VILLAGE",
    "name:eng_x_preferred":[
        "Gandapadar"
    ],
    "name:eng_x_variant":[
        "Gand\u0101padar"
    ],
    "wof:name":"Gandapadar",
    "wof:placetype":"locality"
},
  "geometry": {"coordinates":[84.144268,20.691166],"type":"Point"}
}