{
  "type": "Feature",
  "properties": {
    "iso:country":"IN",
    "ks:ks_name":"Seethapalli",
    "ks:ks_pop":495,
    "ks:ks_type":"HABITATION",
    "name:eng_x_preferred":[
        "Seethapalli"
    ],
    "wof:name":"Seethapalli",
    "wof:placetype":"locality",
    "wof:population":495
},
  "geometry": {"coordinates":[81.801377,17.389961],"type":"Point"}
}