{
  "type": "Feature",
  "properties": {
    "gn:country":"IN",
    "gn:fcode":"PPL",
    "gn:population":25537,
    "iso:country":"IN",
    "name:ben_x_preferred":[
        "\u09ae\u09cc\u0997\u099e\u09cd\u099c"
    ],
    "name:bpy_x_preferred":[
        "\u09ae\u09cc\u0997\u099e\u09cd\u099c"
    ],
    "name:ceb_x_preferred":[
        "Mauganj"
    ],
    "name:deu_x_preferred":[
        "Mauganj"
    ],
    "name:eng_x_preferred":[
        "Mauganj"
    ],
    "name:fas_x_preferred":[
        "\u0645\u0648\u06af\u0627\u0646\u062c"
    ],
    "name:fra_x_preferred":[
        "Mauganj"
    ],
    "name:guj_x_preferred":[
        "\u0aae\u0acc\u0a97\u0a82\u0a9c"
    ],
    "name:hin_x_preferred":[
        "\u092e\u090a\u0917\u0902\u091c"
    ],
    "name:ita_x_preferred":[
        "Mauganj"
    ],
    "name:jpn_x_preferred":[
        "\u30e2\u30a6\u30ac\u30f3\u30b8"
    ],
    "name:kan_x_preferred":[
        "\u0cae\u0ccc\u0c97\u0cbe\u0c82\u0c9c\u0ccd"
    ],
    "name:kor_x_preferred":[
        "\ub9c8\uac04\uc988"
    ],
    "name:mlg_x_preferred":[
        "Mauganj"
    ],
    "name:msa_x_preferred":[
        "Mauganj"
    ],
    "name:nan_x_preferred":[
        "Mauganj"
    ],
    "name:new_x_preferred":[
        "\u092e\u094c\u0917\u091e\u094d\u091c"
    ],
    "name:nld_x_preferred":[
        "Mauganj"
    ],
    "name:ori_x_preferred":[
        "\u0b2e\u0b3e\u0b09\u0b17\u0b1e\u0b4d\u0b1c\u0b4d"
    ],
    "name:por_x_preferred":[
        "Mauganj"
    ],
    "name:rus_x_preferred":[
        "\u041c\u0430\u0443\u0433\u0430\u043d\u0434\u0436"
    ],
    "name:spa_x_preferred":[
        "Mauganj"
    ],
    "name:swe_x_preferred":[
        "Mauganj"
    ],
    "name:tam_x_preferred":[
        "\u0bae\u0bc1\u0b95\u0ba9\u0bcd\u0b9c\u0bcd"
    ],
    "name:tel_x_preferred":[
        "\u0c2e\u0c4c\u0c17\u0c02\u0c1c\u0c4d"
    ],
    "name:urd_x_preferred":[
        "\u0645\u0627\u0624 \u06af\u0646\u062c"
    ],
    "name:vie_x_preferred":[
        "Mauganj"
    ],
    "name:zho_x_preferred":[
        "\u6bdb\u7518\u6770"
    ],
    "qs:name":"Daudganj",
    "qs:name_adm0":"India",
    "qs:name_adm1":"Uttar Pradesh",
    "qs:photos_9r":0,
    "qs:photos_sr":0,
    "qs:placetype":"Town",
    "qs:pop_sr":"7",
    "wof:name":"Daudganj",
    "wof:placetype":"locality",
    "wof:population":25537
},
  "geometry": {"coordinates":[81.8741,24.66629],"type":"Point"}
}