{
  "type": "Feature",
  "properties": {
    "iso:country":"IN",
    "ks:ks_name":"Barhauna",
    "ks:ks_pop":264,
    "ks:ks_type":"VILLAGE",
    "ks:ks_uagg_main":0,
    "name:eng_x_preferred":[
        "Barhauna"
    ],
    "wof:name":"Barhauna",
    "wof:placetype":"neighbourhood",
    "wof:population":264
},
  "geometry": {"coordinates":[84.29124,25.444032],"type":"Point"}
}