{
  "type": "Feature",
  "properties": {
    "gn:admin1_code":"9.0",
    "gn:admin2_code":"469.0",
    "gn:asciiname":"Gadh",
    "gn:country_code":"IN",
    "gn:dem":222,
    "gn:feature_class":"P",
    "gn:feature_code":"PPL",
    "gn:name":"Gadh",
    "gn:population":0,
    "gn:timezone":"Asia/Kolkata",
    "iso:country":"IN",
    "ks:ks_name":"Gadh",
    "ks:ks_pop":663,
    "ks:ks_type":"VILLAGE",
    "name:eng_x_preferred":[
        "Gadh"
    ],
    "wof:name":"Gadh",
    "wof:placetype":"locality",
    "wof:population":663
},
  "geometry": {"coordinates":[72.826756,24.122319],"type":"Point"}
}