{
  "type": "Feature",
  "properties": {
    "iso:country":"IN",
    "ks:ks_name":"Bolamalappanadoddi",
    "ks:ks_pop":229,
    "ks:ks_type":"HABITATION",
    "name:eng_x_preferred":[
        "Bolamalappanadoddi"
    ],
    "wof:name":"Bolamalappanadoddi",
    "wof:placetype":"locality",
    "wof:population":229
},
  "geometry": {"coordinates":[77.460967,12.34832],"type":"Point"}
}