{
  "type": "Feature",
  "properties": {
    "iso:country":"IN",
    "ks:ks_name":"Sharavoor",
    "ks:ks_pop":153,
    "ks:ks_type":"HABITATION",
    "name:eng_x_preferred":[
        "Sharavoor"
    ],
    "wof:name":"Sharavoor",
    "wof:placetype":"locality",
    "wof:population":153
},
  "geometry": {"coordinates":[75.347449,12.759787],"type":"Point"}
}