{
  "type": "Feature",
  "properties": {
    "gn:admin1_code":"21.0",
    "gn:admin2_code":"376",
    "gn:asciiname":"Chahala",
    "gn:country_code":"IN",
    "gn:dem":785,
    "gn:feature_class":"P",
    "gn:feature_code":"PPL",
    "gn:name":"Chahal\u0101",
    "gn:population":0,
    "gn:timezone":"Asia/Kolkata",
    "iso:country":"IN",
    "wof:name":"Chahala",
    "wof:placetype":"locality"
},
  "geometry": {"coordinates":[86.29179000000001,21.98538],"type":"Point"}
}