{
  "type": "Feature",
  "properties": {
    "iso:country":"IN",
    "ks:ks_name":"Ankusipur",
    "ks:ks_pop":346,
    "ks:ks_type":"VILLAGE",
    "ks:ks_uagg_main":0,
    "name:eng_x_preferred":[
        "Ankusipur"
    ],
    "wof:name":"Ankusipur",
    "wof:placetype":"neighbourhood",
    "wof:population":346
},
  "geometry": {"coordinates":[85.951419,20.102303],"type":"Point"}
}