{
  "type": "Feature",
  "properties": {
    "gn:admin1_code":"16.0",
    "gn:admin2_code":"508.0",
    "gn:asciiname":"Tamada",
    "gn:country_code":"IN",
    "gn:dem":249,
    "gn:feature_class":"P",
    "gn:feature_code":"PPL",
    "gn:name":"T\u0101mada",
    "gn:population":0,
    "gn:timezone":"Asia/Kolkata",
    "iso:country":"IN",
    "name:aze_x_preferred":[
        "Tamada"
    ],
    "name:bul_x_preferred":[
        "\u0422\u0430\u043c\u0430\u0434\u0430"
    ],
    "name:ces_x_preferred":[
        "Tamada"
    ],
    "name:chv_x_preferred":[
        "\u041a\u0115\u0440\u0435\u043a\u0435\u00e7\u0115"
    ],
    "name:deu_x_preferred":[
        "Tamada"
    ],
    "name:est_x_preferred":[
        "Tamada"
    ],
    "name:hye_x_preferred":[
        "\u0539\u0561\u0574\u0561\u0564\u0561"
    ],
    "name:kat_x_preferred":[
        "\u10d7\u10d0\u10db\u10d0\u10d3\u10d0"
    ],
    "name:kaz_x_preferred":[
        "\u0410\u0441\u0430\u0431\u0430"
    ],
    "name:pol_x_preferred":[
        "Tamada"
    ],
    "name:rus_x_preferred":[
        "\u0422\u0430\u043c\u0430\u0434\u0430"
    ],
    "name:spa_x_preferred":[
        "Tamada"
    ],
    "name:tur_x_preferred":[
        "Tamada"
    ],
    "name:ukr_x_preferred":[
        "\u0422\u0430\u043c\u0430\u0434\u0430"
    ],
    "wof:name":"Tamada",
    "wof:placetype":"locality"
},
  "geometry": {"coordinates":[80.24141999999998,19.67322],"type":"Point"}
}