{
  "type": "Feature",
  "properties": {
    "iso:country":"IN",
    "ks:ks_name":"Khand",
    "ks:ks_pop":327,
    "ks:ks_type":"HABITATION",
    "name:eng_x_preferred":[
        "Khand"
    ],
    "wof:name":"Khand",
    "wof:placetype":"locality",
    "wof:population":327
},
  "geometry": {"coordinates":[78.46118,30.263884],"type":"Point"}
}