{
  "type": "Feature",
  "properties": {
    "gn:admin1_code":"25.0",
    "gn:admin2_code":"610.0",
    "gn:asciiname":"Kannudayampalaiyam",
    "gn:country_code":"IN",
    "gn:dem":180,
    "gn:feature_class":"P",
    "gn:feature_code":"PPL",
    "gn:name":"Kannudayamp\u0101laiyam",
    "gn:population":0,
    "gn:timezone":"Asia/Kolkata",
    "iso:country":"IN",
    "ks:ks_name":"Kannudayampalayam",
    "ks:ks_pop":622,
    "ks:ks_type":"HABITATION",
    "name:eng_x_preferred":[
        "Kannudayampalayam"
    ],
    "name:eng_x_variant":[
        "Kannudayampalaiyam"
    ],
    "wof:name":"Kannudayampalayam",
    "wof:placetype":"locality",
    "wof:population":622
},
  "geometry": {"coordinates":[77.80580500000001,11.228488],"type":"Point"}
}