{
  "type": "Feature",
  "properties": {
    "iso:country":"IN",
    "ks:ks_name":"Gochharati Bhyabla",
    "ks:ks_pop":780,
    "ks:ks_type":"VILLAGE",
    "ks:ks_uagg_main":0,
    "name:eng_x_preferred":[
        "Gochharati Bhyabla"
    ],
    "wof:name":"Gochharati Bhyabla",
    "wof:placetype":"neighbourhood",
    "wof:population":780
},
  "geometry": {"coordinates":[88.845118,22.632095],"type":"Point"}
}