{
  "type": "Feature",
  "properties": {
    "iso:country":"IN",
    "ks:ks_name":"Sadhubahali",
    "ks:ks_pop":341,
    "ks:ks_type":"VILLAGE",
    "name:eng_x_preferred":[
        "Sadhubahali"
    ],
    "wof:name":"Sadhubahali",
    "wof:placetype":"locality",
    "wof:population":341
},
  "geometry": {"coordinates":[84.755903,21.244435],"type":"Point"}
}