{
  "type": "Feature",
  "properties": {
    "gn:admin1_code":"10.0",
    "gn:admin2_code":"69.0",
    "gn:asciiname":"Kajar",
    "gn:country_code":"IN",
    "gn:dem":1029,
    "gn:feature_class":"P",
    "gn:feature_code":"PPL",
    "gn:name":"K\u0101jar",
    "gn:population":0,
    "gn:timezone":"Asia/Kolkata",
    "iso:country":"IN",
    "wof:name":"Kajar",
    "wof:placetype":"locality"
},
  "geometry": {"coordinates":[77.11619,30.65991],"type":"Point"}
}