{
  "type": "Feature",
  "properties": {
    "gn:admin1_code":"36",
    "gn:admin2_code":"147.0",
    "gn:asciiname":"Dahn",
    "gn:country_code":"IN",
    "gn:dem":165,
    "gn:feature_class":"P",
    "gn:feature_code":"PPL",
    "gn:name":"Dahn",
    "gn:population":0,
    "gn:timezone":"Asia/Kolkata",
    "iso:country":"IN",
    "name:ara_x_preferred":[
        "\u062f\u0627\u0646"
    ],
    "name:azb_x_preferred":[
        "\u062f\u0627\u0646"
    ],
    "name:ceb_x_preferred":[
        "Dahn"
    ],
    "name:ces_x_preferred":[
        "Dahn"
    ],
    "name:deu_x_preferred":[
        "Dahn"
    ],
    "name:epo_x_preferred":[
        "Dahn"
    ],
    "name:fas_x_preferred":[
        "\u062f\u0627\u0646"
    ],
    "name:fra_x_preferred":[
        "Dahn"
    ],
    "name:hun_x_preferred":[
        "Dahn"
    ],
    "name:ita_x_preferred":[
        "Dahn"
    ],
    "name:jpn_x_preferred":[
        "\u30c0\u30fc\u30f3"
    ],
    "name:kaz_x_preferred":[
        "\u0414\u0430\u043d"
    ],
    "name:msa_x_preferred":[
        "Dahn"
    ],
    "name:nld_x_preferred":[
        "Dahn"
    ],
    "name:pol_x_preferred":[
        "Dahn"
    ],
    "name:por_x_preferred":[
        "Dahn"
    ],
    "name:ron_x_preferred":[
        "Dahn"
    ],
    "name:rus_x_preferred":[
        "\u0414\u0430\u043d"
    ],
    "name:spa_x_preferred":[
        "Dahn"
    ],
    "name:srp_x_preferred":[
        "\u0414\u0430\u043d"
    ],
    "name:tur_x_preferred":[
        "Dahn"
    ],
    "name:ukr_x_preferred":[
        "\u0414\u0430\u043d"
    ],
    "name:vie_x_preferred":[
        "Dahn"
    ],
    "name:vol_x_preferred":[
        "Dahn"
    ],
    "name:war_x_preferred":[
        "Dahn"
    ],
    "wof:name":"Dahn",
    "wof:placetype":"neighbourhood"
},
  "geometry": {"coordinates":[78.57249,27.06391],"type":"Point"}
}