{
  "type": "Feature",
  "properties": {
    "gn:admin1_code":"40.0",
    "gn:admin2_code":"534.0",
    "gn:asciiname":"Peddapetta",
    "gn:country_code":"IN",
    "gn:dem":159,
    "gn:feature_class":"P",
    "gn:feature_code":"PPL",
    "gn:name":"Peddapetta",
    "gn:population":0,
    "gn:timezone":"Asia/Kolkata",
    "iso:country":"IN",
    "wof:name":"Peddapetta",
    "wof:placetype":"locality"
},
  "geometry": {"coordinates":[79.43377,18.79818],"type":"Point"}
}