{
  "type": "Feature",
  "properties": {
    "iso:country":"IN",
    "name:ast_x_preferred":[
        "Lasara"
    ],
    "name:eng_x_preferred":[
        "Lasara"
    ],
    "name:nld_x_preferred":[
        "Lasara"
    ],
    "qs:name":"Lasara",
    "qs:name_adm0":"India",
    "qs:name_adm1":"Punjab",
    "qs:photos":44,
    "qs:photos_1k":9,
    "qs:photos_9k":1,
    "qs:photos_9r":2,
    "qs:photos_all":44,
    "qs:photos_sr":2,
    "qs:placetype":"Town",
    "qs:pop_sr":"0",
    "wd:wordcount":215,
    "wof:name":"Lasara",
    "wof:placetype":"locality"
},
  "geometry": {"coordinates":[75.951747,31.040616],"type":"Point"}
}