{
  "type": "Feature",
  "properties": {
    "gn:admin1_code":"2.0",
    "gn:admin2_code":"553.0",
    "gn:asciiname":"Gangalakunta",
    "gn:country_code":"IN",
    "gn:dem":365,
    "gn:feature_class":"P",
    "gn:feature_code":"PPL",
    "gn:name":"Gangalakunta",
    "gn:population":0,
    "gn:timezone":"Asia/Kolkata",
    "iso:country":"IN",
    "wof:name":"Gangalakunta",
    "wof:placetype":"locality"
},
  "geometry": {"coordinates":[77.62139000000001,14.61119],"type":"Point"}
}