{
  "type": "Feature",
  "properties": {
    "iso:country":"IN",
    "ks:ks_name":"Pharasgaon Para",
    "ks:ks_pop":374,
    "ks:ks_type":"HABITATION",
    "name:eng_x_preferred":[
        "Pharasgaon Para"
    ],
    "wof:name":"Pharasgaon Para",
    "wof:placetype":"locality",
    "wof:population":374
},
  "geometry": {"coordinates":[81.428507,19.955257],"type":"Point"}
}