{
  "type": "Feature",
  "properties": {
    "gn:admin1_code":"36",
    "gn:admin2_code":"181.0",
    "gn:asciiname":"Khan Purwa",
    "gn:country_code":"IN",
    "gn:dem":119,
    "gn:feature_class":"P",
    "gn:feature_code":"PPL",
    "gn:name":"Kh\u0101n Purwa",
    "gn:population":0,
    "gn:timezone":"Asia/Kolkata",
    "iso:country":"IN",
    "ks:ks_name":"Khan Purwa",
    "ks:ks_pop":155,
    "ks:ks_type":"HABITATION",
    "name:eng_x_preferred":[
        "Khan Purwa"
    ],
    "wof:name":"Khan Purwa",
    "wof:placetype":"locality",
    "wof:population":155
},
  "geometry": {"coordinates":[81.895087,27.682827],"type":"Point"}
}