{
  "type": "Feature",
  "properties": {
    "iso:country":"IN",
    "ks:ks_alt_nam":"HANUMAN NAGAR",
    "ks:ks_name":"Hanuman Nagar",
    "ks:ks_pop":586,
    "ks:ks_type":"HABITATION",
    "name:eng_x_preferred":[
        "Hanuman Nagar"
    ],
    "wof:name":"Hanuman Nagar",
    "wof:placetype":"locality",
    "wof:population":586
},
  "geometry": {"coordinates":[86.246369,26.497311],"type":"Point"}
}