{
  "type": "Feature",
  "properties": {
    "iso:country":"IN",
    "ks:ks_alt_nam":"upper Tola",
    "ks:ks_name":"Upper Tola",
    "ks:ks_pop":125,
    "ks:ks_type":"HABITATION",
    "name:eng_x_preferred":[
        "Upper Tola"
    ],
    "wof:name":"Upper Tola",
    "wof:placetype":"locality",
    "wof:population":125
},
  "geometry": {"coordinates":[86.42715200000001,24.561663],"type":"Point"}
}