{
  "type": "Feature",
  "properties": {
    "gn:admin1_code":"2.0",
    "gn:admin2_code":"554.0",
    "gn:asciiname":"Sugalapalle",
    "gn:country_code":"IN",
    "gn:dem":871,
    "gn:feature_class":"P",
    "gn:feature_code":"PPL",
    "gn:name":"Sugalapalle",
    "gn:population":0,
    "gn:timezone":"Asia/Kolkata",
    "iso:country":"IN",
    "wof:name":"Sugalapalle",
    "wof:placetype":"neighbourhood"
},
  "geometry": {"coordinates":[78.46248,13.48408],"type":"Point"}
}