{
  "type": "Feature",
  "properties": {
    "iso:country":"IN",
    "ks:ks_name":"Bhairabpur",
    "ks:ks_pop":357,
    "ks:ks_type":"VILLAGE",
    "ks:ks_uagg_main":0,
    "name:eng_x_preferred":[
        "Bhairabpur"
    ],
    "wof:name":"Bhairabpur",
    "wof:placetype":"neighbourhood",
    "wof:population":357
},
  "geometry": {"coordinates":[92.117867,26.868098],"type":"Point"}
}