{
  "type": "Feature",
  "properties": {
    "iso:country":"IN",
    "ks:ks_alt_nam":"PURE KHATA",
    "ks:ks_name":"Pure Khata",
    "ks:ks_pop":75,
    "ks:ks_type":"HABITATION",
    "ks:ks_uagg_main":0,
    "name:eng_x_preferred":[
        "Pure Khata"
    ],
    "wof:name":"Pure Khata",
    "wof:placetype":"neighbourhood",
    "wof:population":75
},
  "geometry": {"coordinates":[81.924937,26.322347],"type":"Point"}
}