{
  "type": "Feature",
  "properties": {
    "iso:country":"IN",
    "ks:ks_name":"Methalapadi",
    "ks:ks_pop":105,
    "ks:ks_type":"HABITATION",
    "name:eng_x_preferred":[
        "Methalapadi"
    ],
    "wof:name":"Methalapadi",
    "wof:placetype":"locality",
    "wof:population":105
},
  "geometry": {"coordinates":[76.73621900000001,9.467794],"type":"Point"}
}