{
  "type": "Feature",
  "properties": {
    "iso:country":"IN",
    "ks:ks_name":"Pundi",
    "ks:ks_pop":530,
    "ks:ks_type":"HABITATION",
    "name:eng_x_preferred":[
        "Pundi"
    ],
    "wof:name":"Pundi",
    "wof:placetype":"locality",
    "wof:population":530
},
  "geometry": {"coordinates":[84.269702,23.03915],"type":"Point"}
}