{
  "type": "Feature",
  "properties": {
    "gn:admin1_code":"25.0",
    "gn:admin2_code":"630.0",
    "gn:asciiname":"Manikattiyur",
    "gn:country_code":"IN",
    "gn:dem":476,
    "gn:feature_class":"P",
    "gn:feature_code":"PPL",
    "gn:name":"Manikattiy\u016br",
    "gn:population":0,
    "gn:timezone":"Asia/Kolkata",
    "iso:country":"IN",
    "wof:name":"Manikattiyur",
    "wof:placetype":"locality"
},
  "geometry": {"coordinates":[78.20996,12.32091],"type":"Point"}
}