{
  "type": "Feature",
  "properties": {
    "gn:admin1_code":"19.0",
    "gn:admin2_code":"582.0",
    "gn:asciiname":"Kamanahalli",
    "gn:country_code":"IN",
    "gn:dem":812,
    "gn:feature_class":"P",
    "gn:feature_code":"PPL",
    "gn:name":"Kamanahalli",
    "gn:population":0,
    "gn:timezone":"Asia/Kolkata",
    "iso:country":"IN",
    "wof:name":"Kamanahalli",
    "wof:placetype":"locality"
},
  "geometry": {"coordinates":[77.89369000000001,13.64675],"type":"Point"}
}