{
  "type": "Feature",
  "properties": {
    "gn:admin1_code":"2",
    "gn:admin2_code":"545.0",
    "gn:asciiname":"Chinnuru",
    "gn:country_code":"IN",
    "gn:dem":81,
    "gn:feature_class":"P",
    "gn:feature_code":"PPL",
    "gn:name":"Chinn\u016bru",
    "gn:population":0,
    "gn:timezone":"Asia/Kolkata",
    "iso:country":"IN",
    "wof:name":"Chinnuru",
    "wof:placetype":"locality"
},
  "geometry": {"coordinates":[81.85033,17.29091],"type":"Point"}
}