{
  "type": "Feature",
  "properties": {
    "iso:country":"IN",
    "ks:ks_name":"Kundipada",
    "ks:ks_pop":661,
    "ks:ks_type":"HABITATION",
    "name:eng_x_preferred":[
        "Kundipada"
    ],
    "wof:name":"Kundipada",
    "wof:placetype":"locality",
    "wof:population":661
},
  "geometry": {"coordinates":[74.729877,23.260666],"type":"Point"}
}