{
  "type": "Feature",
  "properties": {
    "iso:country":"IN",
    "ks:ks_name":"Edakkalathur",
    "ks:ks_pop":7510,
    "ks:ks_type":"VILLAGE",
    "ks:ks_uagg_main":0,
    "name:eng_x_preferred":[
        "Edakkalathur"
    ],
    "wof:name":"Edakkalathur",
    "wof:placetype":"locality",
    "wof:population":7510
},
  "geometry": {"coordinates":[76.134643,10.573175],"type":"Point"}
}