{
  "type": "Feature",
  "properties": {
    "gn:admin1_code":"19.0",
    "gn:admin2_code":"581.0",
    "gn:asciiname":"Mallemvaripalli",
    "gn:country_code":"IN",
    "gn:dem":758,
    "gn:feature_class":"P",
    "gn:feature_code":"PPL",
    "gn:name":"Mallemv\u0101ripalli",
    "gn:population":0,
    "gn:timezone":"Asia/Kolkata",
    "iso:country":"IN",
    "wof:name":"Mallemvaripalli",
    "wof:placetype":"locality"
},
  "geometry": {"coordinates":[78.27859000000002,13.51487],"type":"Point"}
}