{
  "type": "Feature",
  "properties": {
    "iso:country":"IN",
    "ks:ks_name":"Santara",
    "ks:ks_pop":565,
    "ks:ks_type":"VILLAGE",
    "name:eng_x_preferred":[
        "Santara"
    ],
    "wof:name":"Santara",
    "wof:placetype":"locality",
    "wof:population":565
},
  "geometry": {"coordinates":[86.01882999999999,21.189442],"type":"Point"}
}