{
  "type": "Feature",
  "properties": {
    "gn:admin1_code":"37",
    "gn:admin2_code":"406.0",
    "gn:asciiname":"Dumra",
    "gn:country_code":"IN",
    "gn:dem":322,
    "gn:feature_class":"P",
    "gn:feature_code":"PPL",
    "gn:name":"Dumra",
    "gn:population":0,
    "gn:timezone":"Asia/Kolkata",
    "iso:country":"IN",
    "ks:ks_name":"Dumrha",
    "ks:ks_pop":964,
    "ks:ks_type":"VILLAGE",
    "name:ben_x_preferred":[
        "\u09a6\u09c1\u09ae\u09b0\u09be"
    ],
    "name:bpy_x_preferred":[
        "\u09a6\u09c1\u09ae\u09b0\u09be"
    ],
    "name:ceb_x_preferred":[
        "Dumra"
    ],
    "name:eng_x_preferred":[
        "Dumrha"
    ],
    "name:eng_x_variant":[
        "Dumra"
    ],
    "name:hif_x_preferred":[
        "Dumra"
    ],
    "name:hin_x_preferred":[
        "\u0921\u0941\u092e\u0930\u093e"
    ],
    "name:ita_x_preferred":[
        "Dumra"
    ],
    "name:msa_x_preferred":[
        "Dumra"
    ],
    "name:new_x_preferred":[
        "\u0926\u092e\u094d\u0930\u093e"
    ],
    "name:nld_x_preferred":[
        "Dumra"
    ],
    "name:por_x_preferred":[
        "Dumra"
    ],
    "name:vie_x_preferred":[
        "Dumra"
    ],
    "name:zho_x_preferred":[
        "\u675c\u59c6\u62c9"
    ],
    "wof:name":"Dumrha",
    "wof:placetype":"locality",
    "wof:population":964
},
  "geometry": {"coordinates":[81.571859,22.205637],"type":"Point"}
}