{
  "type": "Feature",
  "properties": {
    "gn:admin1_code":"37",
    "gn:asciiname":"Rajana",
    "gn:country_code":"IN",
    "gn:dem":267,
    "gn:feature_class":"P",
    "gn:feature_code":"PPL",
    "gn:name":"Rajana",
    "gn:population":0,
    "gn:timezone":"Asia/Kolkata",
    "iso:country":"IN",
    "name:urd_x_preferred":[
        "\u0631\u062c\u0627\u0646\u06c1"
    ],
    "wof:name":"Rajana",
    "wof:placetype":"locality"
},
  "geometry": {"coordinates":[82.61667,20.43333],"type":"Point"}
}