{
  "type": "Feature",
  "properties": {
    "gn:admin1_code":"19.0",
    "gn:admin2_code":"573.0",
    "gn:asciiname":"Boppanahalli",
    "gn:country_code":"IN",
    "gn:dem":1000,
    "gn:feature_class":"P",
    "gn:feature_code":"PPL",
    "gn:name":"Boppanahalli",
    "gn:population":0,
    "gn:timezone":"Asia/Kolkata",
    "iso:country":"IN",
    "wof:name":"Boppanahalli",
    "wof:placetype":"locality"
},
  "geometry": {"coordinates":[76.59364000000002,12.75362],"type":"Point"}
}