{
  "type": "Feature",
  "properties": {
    "gn:country":"IN",
    "gn:fcode":"PPL",
    "gn:pop":17849,
    "iso:country":"IN",
    "name:bpy_x_preferred":[
        "\u09b8\u09b0\u09be\u0987 \u09ae\u09bf\u09b0"
    ],
    "name:eng_x_preferred":[
        "Sarai Mir"
    ],
    "name:fas_x_preferred":[
        "\u0633\u0631\u0627\u06cc \u0645\u06cc\u0631"
    ],
    "name:fra_x_preferred":[
        "Sarai Mir"
    ],
    "name:ita_x_preferred":[
        "Sarai Mir"
    ],
    "name:msa_x_preferred":[
        "Sarai Mir"
    ],
    "name:nan_x_preferred":[
        "Sarai Mir"
    ],
    "name:nld_x_preferred":[
        "Sarai Mir"
    ],
    "name:pol_x_preferred":[
        "Sarai Mir"
    ],
    "name:por_x_preferred":[
        "Sarai Mir"
    ],
    "name:swe_x_preferred":[
        "Sar\u0101i M\u012br"
    ],
    "name:unk_x_variant":[
        "Sar\u0101i M\u012br"
    ],
    "name:urd_x_preferred":[
        "\u0633\u0631\u0627\u0626\u06d2 \u0645\u06cc\u0631"
    ],
    "name:vie_x_preferred":[
        "Sarai Mir"
    ],
    "name:zho_x_preferred":[
        "\u8428\u8d56\u7c73\u5c14"
    ],
    "qs:name":"Sarai Mir",
    "qs:name_adm0":"India",
    "qs:name_adm1":"Uttar Pradesh",
    "qs:photos_9r":0,
    "qs:photos_sr":0,
    "qs:placetype":"Town",
    "qs:pop_sr":"6",
    "wd:wordcount":173,
    "wof:name":"Sarai Mir",
    "wof:placetype":"locality",
    "wof:population":17849
},
  "geometry": {"coordinates":[82.91795,26.02796],"type":"Point"}
}