{
  "type": "Feature",
  "properties": {
    "iso:country":"IN",
    "ks:ks_name":"Kosumguda",
    "ks:ks_pop":144,
    "ks:ks_type":"HABITATION",
    "name:eng_x_preferred":[
        "Kosumguda"
    ],
    "wof:name":"Kosumguda",
    "wof:placetype":"locality",
    "wof:population":144
},
  "geometry": {"coordinates":[82.081936,18.502496],"type":"Point"}
}