{
  "type": "Feature",
  "properties": {
    "gn:admin1_code":"2.0",
    "gn:admin2_code":"550",
    "gn:asciiname":"Bangarupet",
    "gn:country_code":"IN",
    "gn:dem":63,
    "gn:feature_class":"P",
    "gn:feature_code":"PPL",
    "gn:name":"Bang\u0101rupet",
    "gn:population":0,
    "gn:timezone":"Asia/Kolkata",
    "iso:country":"IN",
    "name:und_x_variant":[
        "Bang\u0101rupet",
        "Bangarpett",
        "Bang\u0101rupeta"
    ],
    "wof:name":"Bangarupet",
    "wof:placetype":"locality"
},
  "geometry": {"coordinates":[79.5994,13.96929],"type":"Point"}
}