{
  "type": "Feature",
  "properties": {
    "iso:country":"IN",
    "ks:ks_name":"Gair",
    "ks:ks_pop":32,
    "ks:ks_type":"VILLAGE",
    "name:eng_x_preferred":[
        "Gair"
    ],
    "wof:name":"Gair",
    "wof:placetype":"locality",
    "wof:population":32
},
  "geometry": {"coordinates":[78.709372,30.165426],"type":"Point"}
}