{
  "type": "Feature",
  "properties": {
    "iso:country":"IN",
    "ks:ks_name":"Engaon",
    "ks:ks_pop":168,
    "ks:ks_type":"HABITATION",
    "name:eng_x_preferred":[
        "Engaon"
    ],
    "wof:name":"Engaon",
    "wof:placetype":"locality",
    "wof:population":168
},
  "geometry": {"coordinates":[80.374909,20.248498],"type":"Point"}
}