{
  "type": "Feature",
  "properties": {
    "iso:country":"IN",
    "ks:ks_name":"Brijbhan Purwa",
    "ks:ks_pop":20,
    "ks:ks_type":"HABITATION",
    "name:eng_x_preferred":[
        "Brijbhan Purwa"
    ],
    "wof:name":"Brijbhan Purwa",
    "wof:placetype":"locality",
    "wof:population":20
},
  "geometry": {"coordinates":[81.416213,25.164884],"type":"Point"}
}