{
  "type": "Feature",
  "properties": {
    "iso:country":"IN",
    "ks:ks_name":"Kuberpur",
    "ks:ks_pop":2350,
    "ks:ks_type":"VILLAGE",
    "name:eng_x_preferred":[
        "Kuberpur"
    ],
    "wof:name":"Kuberpur",
    "wof:placetype":"neighbourhood",
    "wof:population":2350
},
  "geometry": {"coordinates":[78.117791,27.216993],"type":"Point"}
}