{
  "type": "Feature",
  "properties": {
    "gn:admin1_code":"11",
    "gn:admin2_code":"24.0",
    "gn:asciiname":"Digar Lahr",
    "gn:country_code":"IN",
    "gn:dem":704,
    "gn:feature_class":"P",
    "gn:feature_code":"PPL",
    "gn:name":"Digar Lahr",
    "gn:population":0,
    "gn:timezone":"Asia/Kolkata",
    "iso:country":"IN",
    "wof:name":"Digar Lahr",
    "wof:placetype":"locality"
},
  "geometry": {"coordinates":[76.3044,32.045],"type":"Point"}
}