{
  "type": "Feature",
  "properties": {
    "iso:country":"IN",
    "ks:ks_name":"Bijjahalli",
    "ks:ks_pop":1002,
    "ks:ks_type":"VILLAGE",
    "name:eng_x_preferred":[
        "Bijjahalli"
    ],
    "wof:name":"Bijjahalli",
    "wof:placetype":"locality",
    "wof:population":1002
},
  "geometry": {"coordinates":[77.60330500000001,12.421838],"type":"Point"}
}