{
  "type": "Feature",
  "properties": {
    "iso:country":"IN",
    "ks:ks_name":"Mainsikhal",
    "ks:ks_pop":20,
    "ks:ks_type":"VILLAGE",
    "name:eng_x_preferred":[
        "Mainsikhal"
    ],
    "wof:name":"Mainsikhal",
    "wof:placetype":"locality",
    "wof:population":20
},
  "geometry": {"coordinates":[82.29441799999999,18.555659],"type":"Point"}
}