{
  "type": "Feature",
  "properties": {
    "gn:admin1_code":"35",
    "gn:admin2_code":"447.0",
    "gn:asciiname":"Chiklar",
    "gn:country_code":"IN",
    "gn:dem":653,
    "gn:feature_class":"P",
    "gn:feature_code":"PPL",
    "gn:name":"Chikl\u0101r",
    "gn:population":0,
    "gn:timezone":"Asia/Kolkata",
    "iso:country":"IN",
    "wof:name":"Chiklar",
    "wof:placetype":"locality"
},
  "geometry": {"coordinates":[77.91821,21.94664],"type":"Point"}
}