{
  "type": "Feature",
  "properties": {
    "iso:country":"IN",
    "ks:ks_name":"Khosewasti",
    "ks:ks_pop":450,
    "ks:ks_type":"HABITATION",
    "name:eng_x_preferred":[
        "Khosewasti"
    ],
    "wof:name":"Khosewasti",
    "wof:placetype":"locality",
    "wof:population":450
},
  "geometry": {"coordinates":[74.344514,19.065351],"type":"Point"}
}