{
  "type": "Feature",
  "properties": {
    "gn:admin1_code":"36.0",
    "gn:admin2_code":"189.0",
    "gn:asciiname":"Urdaha",
    "gn:country_code":"IN",
    "gn:dem":90,
    "gn:feature_class":"P",
    "gn:feature_code":"PPL",
    "gn:name":"Urdaha",
    "gn:population":0,
    "gn:timezone":"Asia/Kolkata",
    "iso:country":"IN",
    "ks:ks_name":"Urdaha",
    "ks:ks_pop":4592,
    "ks:ks_type":"VILLAGE",
    "ks:ks_uagg_main":0,
    "name:eng_x_preferred":[
        "Urdaha"
    ],
    "wof:name":"Urdaha",
    "wof:placetype":"neighbourhood",
    "wof:population":4592
},
  "geometry": {"coordinates":[83.831391,26.902786],"type":"Point"}
}