{
  "type": "Feature",
  "properties": {
    "gn:admin1_code":"16",
    "gn:admin2_code":"501.0",
    "gn:asciiname":"Bhilkhed",
    "gn:country_code":"IN",
    "gn:dem":389,
    "gn:feature_class":"P",
    "gn:feature_code":"PPL",
    "gn:name":"Bhilkhed",
    "gn:population":0,
    "gn:timezone":"Asia/Kolkata",
    "iso:country":"IN",
    "wof:name":"Bhilkhed",
    "wof:placetype":"locality"
},
  "geometry": {"coordinates":[77.11660999999999,21.20069],"type":"Point"}
}