{
  "type": "Feature",
  "properties": {
    "iso:country":"IN",
    "ks:ks_name":"Ambativaripalem",
    "ks:ks_pop":689,
    "ks:ks_type":"HABITATION",
    "name:eng_x_preferred":[
        "Ambativaripalem"
    ],
    "wof:name":"Ambativaripalem",
    "wof:placetype":"locality",
    "wof:population":689
},
  "geometry": {"coordinates":[81.994923,16.612572],"type":"Point"}
}