{
  "type": "Feature",
  "properties": {
    "iso:country":"IN",
    "ks:ks_name":"Fatkara",
    "ks:ks_pop":911,
    "ks:ks_type":"VILLAGE",
    "name:eng_x_preferred":[
        "Fatkara"
    ],
    "wof:name":"Fatkara",
    "wof:placetype":"locality",
    "wof:population":911
},
  "geometry": {"coordinates":[83.6407,20.700474],"type":"Point"}
}