{
  "type": "Feature",
  "properties": {
    "iso:country":"IN",
    "ks:ks_name":"Darjimunda",
    "ks:ks_pop":108,
    "ks:ks_type":"VILLAGE",
    "name:eng_x_preferred":[
        "Darjimunda"
    ],
    "wof:name":"Darjimunda",
    "wof:placetype":"locality",
    "wof:population":108
},
  "geometry": {"coordinates":[84.64975699999999,21.380655],"type":"Point"}
}