{
  "type": "Feature",
  "properties": {
    "iso:country":"IN",
    "ks:ks_name":"Parewa",
    "ks:ks_pop":495,
    "ks:ks_type":"VILLAGE",
    "name:eng_x_preferred":[
        "Parewa"
    ],
    "wof:name":"Parewa",
    "wof:placetype":"locality",
    "wof:population":495
},
  "geometry": {"coordinates":[83.552414,23.220189],"type":"Point"}
}