{
  "type": "Feature",
  "properties": {
    "iso:country":"IN",
    "ks:ks_name":"Purbba Chakla",
    "ks:ks_pop":100,
    "ks:ks_type":"VILLAGE",
    "name:eng_x_preferred":[
        "Purbba Chakla"
    ],
    "wof:name":"Purbba Chakla",
    "wof:placetype":"locality",
    "wof:population":100
},
  "geometry": {"coordinates":[87.465296,22.499267],"type":"Point"}
}