{
  "type": "Feature",
  "properties": {
    "gn:admin1_code":"23.0",
    "gn:admin2_code":"049",
    "gn:asciiname":"Jodhe",
    "gn:country_code":"IN",
    "gn:dem":241,
    "gn:feature_class":"P",
    "gn:feature_code":"PPL",
    "gn:name":"Jodhe",
    "gn:population":0,
    "gn:timezone":"Asia/Kolkata",
    "iso:country":"IN",
    "wof:name":"Jodhe",
    "wof:placetype":"locality"
},
  "geometry": {"coordinates":[75.33117,31.57643],"type":"Point"}
}