{
  "type": "Feature",
  "properties": {
    "gn:admin1_code":"19.0",
    "gn:admin2_code":"575.0",
    "gn:asciiname":"Adyapadi",
    "gn:country_code":"IN",
    "gn:dem":10,
    "gn:feature_class":"P",
    "gn:feature_code":"PPLL",
    "gn:name":"Adyap\u0101di",
    "gn:population":0,
    "gn:timezone":"Asia/Kolkata",
    "iso:country":"IN",
    "wof:name":"Adyapadi",
    "wof:placetype":"locality"
},
  "geometry": {"coordinates":[74.89502,12.94654],"type":"Point"}
}