{
  "type": "Feature",
  "properties": {
    "iso:country":"IN",
    "ks:ks_alt_nam":"karra prolu",
    "ks:ks_name":"Karra Prolu",
    "ks:ks_pop":153,
    "ks:ks_type":"HABITATION",
    "name:eng_x_preferred":[
        "Karra Prolu"
    ],
    "wof:name":"Karra Prolu",
    "wof:placetype":"locality",
    "wof:population":153
},
  "geometry": {"coordinates":[78.94134,15.870062],"type":"Point"}
}