{
  "type": "Feature",
  "properties": {
    "iso:country":"IN",
    "ks:ks_name":"Dongasil",
    "ks:ks_pop":299,
    "ks:ks_type":"HABITATION",
    "name:eng_x_preferred":[
        "Dongasil"
    ],
    "wof:name":"Dongasil",
    "wof:placetype":"locality",
    "wof:population":299
},
  "geometry": {"coordinates":[82.98732099999999,19.22897],"type":"Point"}
}