{
  "type": "Feature",
  "properties": {
    "iso:country":"IN",
    "ks:ks_name":"Panasaputtu",
    "ks:ks_pop":73,
    "ks:ks_type":"HABITATION",
    "name:eng_x_preferred":[
        "Panasaputtu"
    ],
    "wof:name":"Panasaputtu",
    "wof:placetype":"locality",
    "wof:population":73
},
  "geometry": {"coordinates":[82.705938,18.098307],"type":"Point"}
}