{
  "type": "Feature",
  "properties": {
    "iso:country":"IN",
    "ks:ks_name":"Umarpal",
    "ks:ks_pop":488,
    "ks:ks_type":"HABITATION",
    "name:eng_x_preferred":[
        "Umarpal"
    ],
    "wof:name":"Umarpal",
    "wof:placetype":"locality",
    "wof:population":488
},
  "geometry": {"coordinates":[80.841324,20.390095],"type":"Point"}
}