{
  "type": "Feature",
  "properties": {
    "iso:country":"IN",
    "ks:ks_name":"Moyada",
    "ks:ks_pop":739,
    "ks:ks_type":"VILLAGE",
    "name:eng_x_preferred":[
        "Moyada"
    ],
    "wof:name":"Moyada",
    "wof:placetype":"locality",
    "wof:population":739
},
  "geometry": {"coordinates":[75.189982,21.914899],"type":"Point"}
}