{
  "type": "Feature",
  "properties": {
    "gn:admin1_code":"24.0",
    "gn:admin2_code":"123.0",
    "gn:asciiname":"Piprelu",
    "gn:country_code":"IN",
    "gn:dem":765,
    "gn:feature_class":"P",
    "gn:feature_code":"PPL",
    "gn:name":"Piprelu",
    "gn:population":0,
    "gn:timezone":"Asia/Kolkata",
    "iso:country":"IN",
    "ks:ks_name":"Piprelu",
    "ks:ks_pop":438,
    "ks:ks_type":"VILLAGE",
    "name:eng_x_preferred":[
        "Piprelu"
    ],
    "wof:name":"Piprelu",
    "wof:placetype":"locality",
    "wof:population":438
},
  "geometry": {"coordinates":[73.796806,25.416175],"type":"Point"}
}