{
  "type": "Feature",
  "properties": {
    "iso:country":"IN",
    "ks:ks_name":"Niche Tola",
    "ks:ks_pop":387,
    "ks:ks_type":"HABITATION",
    "name:eng_x_preferred":[
        "Niche Tola"
    ],
    "wof:name":"Niche Tola",
    "wof:placetype":"locality",
    "wof:population":387
},
  "geometry": {"coordinates":[85.55265300000001,23.767257],"type":"Point"}
}