{
  "type": "Feature",
  "properties": {
    "iso:country":"IN",
    "ks:ks_name":"Bhatu Bigha",
    "ks:ks_pop":280,
    "ks:ks_type":"HABITATION",
    "name:eng_x_preferred":[
        "Bhatu Bigha"
    ],
    "wof:name":"Bhatu Bigha",
    "wof:placetype":"locality",
    "wof:population":280
},
  "geometry": {"coordinates":[85.293403,25.068939],"type":"Point"}
}