{
  "type": "Feature",
  "properties": {
    "iso:country":"IN",
    "ks:ks_name":"Kharakhara",
    "ks:ks_pop":20,
    "ks:ks_type":"VILLAGE",
    "name:eng_x_preferred":[
        "Kharakhara"
    ],
    "wof:name":"Kharakhara",
    "wof:placetype":"locality",
    "wof:population":20
},
  "geometry": {"coordinates":[86.599346,20.696864],"type":"Point"}
}