{
  "type": "Feature",
  "properties": {
    "iso:country":"IN",
    "ks:ks_name":"Keelalakshmipatti",
    "ks:ks_pop":149,
    "ks:ks_type":"HABITATION",
    "ks:ks_uagg_main":0,
    "name:eng_x_preferred":[
        "Keelalakshmipatti"
    ],
    "wof:name":"Keelalakshmipatti",
    "wof:placetype":"neighbourhood",
    "wof:population":149
},
  "geometry": {"coordinates":[77.371787,8.875126],"type":"Point"}
}