{
  "type": "Feature",
  "properties": {
    "gn:admin1_code":"11.0",
    "gn:admin2_code":"34.0",
    "gn:asciiname":"Leyalang",
    "gn:country_code":"IN",
    "gn:dem":2943,
    "gn:feature_class":"P",
    "gn:feature_code":"PPL",
    "gn:name":"Ley\u0101lang",
    "gn:population":0,
    "gn:timezone":"Asia/Kolkata",
    "iso:country":"IN",
    "wof:name":"Leyalang",
    "wof:placetype":"locality"
},
  "geometry": {"coordinates":[78.02486999999998,31.59216],"type":"Point"}
}