{
  "type": "Feature",
  "properties": {
    "iso:country":"IN",
    "ks:ks_name":"Konipady",
    "ks:ks_pop":1000,
    "ks:ks_type":"HABITATION",
    "name:eng_x_preferred":[
        "Konipady"
    ],
    "wof:name":"Konipady",
    "wof:placetype":"locality",
    "wof:population":1000
},
  "geometry": {"coordinates":[76.69381199999999,10.00263],"type":"Point"}
}