{
  "type": "Feature",
  "properties": {
    "iso:country":"IN",
    "ks:ks_name":"Rai Garsyari",
    "ks:ks_pop":228,
    "ks:ks_type":"VILLAGE",
    "ks:ks_uagg_main":0,
    "name:eng_x_preferred":[
        "Rai Garsyari"
    ],
    "wof:name":"Rai Garsyari",
    "wof:placetype":"neighbourhood",
    "wof:population":228
},
  "geometry": {"coordinates":[80.053962,29.731752],"type":"Point"}
}