{
  "type": "Feature",
  "properties": {
    "iso:country":"IN",
    "ks:ks_name":"Narpat Nagar",
    "ks:ks_pop":748,
    "ks:ks_type":"VILLAGE",
    "ks:ks_uagg_main":0,
    "name:eng_x_preferred":[
        "Narpat Nagar"
    ],
    "wof:name":"Narpat Nagar",
    "wof:placetype":"neighbourhood",
    "wof:population":748
},
  "geometry": {"coordinates":[86.178319,25.767583],"type":"Point"}
}