{
  "type": "Feature",
  "properties": {
    "iso:country":"IN",
    "ks:ks_name":"Baidyapur",
    "ks:ks_pop":0,
    "ks:ks_type":"VILLAGE",
    "name:eng_x_preferred":[
        "Baidyapur"
    ],
    "wof:name":"Baidyapur",
    "wof:placetype":"locality",
    "wof:population":0
},
  "geometry": {"coordinates":[88.17533299999999,23.832962],"type":"Point"}
}