{
  "type": "Feature",
  "properties": {
    "iso:country":"IN",
    "ks:ks_name":"Konganoor",
    "ks:ks_pop":312,
    "ks:ks_type":"HABITATION",
    "name:eng_x_preferred":[
        "Konganoor"
    ],
    "wof:name":"Konganoor",
    "wof:placetype":"locality",
    "wof:population":312
},
  "geometry": {"coordinates":[77.650477,12.051526],"type":"Point"}
}