{
  "type": "Feature",
  "properties": {
    "gn:admin1_code":"36.0",
    "gn:admin2_code":"136.0",
    "gn:asciiname":"Isharpur",
    "gn:country_code":"IN",
    "gn:dem":198,
    "gn:feature_class":"P",
    "gn:feature_code":"PPL",
    "gn:name":"\u012asharpur",
    "gn:population":0,
    "gn:timezone":"Asia/Kolkata",
    "iso:country":"IN",
    "ks:ks_name":"Ishwarpur",
    "ks:ks_pop":1467,
    "ks:ks_type":"VILLAGE",
    "ks:ks_uagg_main":0,
    "name:eng_x_preferred":[
        "Ishwarpur"
    ],
    "wof:name":"Ishwarpur",
    "wof:placetype":"neighbourhood",
    "wof:population":1467
},
  "geometry": {"coordinates":[79.007938,28.909182],"type":"Point"}
}