{
  "type": "Feature",
  "properties": {
    "gn:admin1_code":"36",
    "gn:admin2_code":"195.0",
    "gn:asciiname":"Salari",
    "gn:country_code":"IN",
    "gn:dem":74,
    "gn:feature_class":"P",
    "gn:feature_code":"PPL",
    "gn:name":"Salari",
    "gn:population":0,
    "gn:timezone":"Asia/Kolkata",
    "iso:country":"IN",
    "name:sqi_x_preferred":[
        "Salaria"
    ],
    "wof:name":"Salari",
    "wof:placetype":"locality"
},
  "geometry": {"coordinates":[83.84886999999998,25.72859],"type":"Point"}
}