{
  "type": "Feature",
  "properties": {
    "iso:country":"IN",
    "ks:ks_name":"Kudyala",
    "ks:ks_pop":945,
    "ks:ks_type":"VILLAGE",
    "name:eng_x_preferred":[
        "Kudyala"
    ],
    "wof:name":"Kudyala",
    "wof:placetype":"locality",
    "wof:population":945
},
  "geometry": {"coordinates":[79.217743,24.704779],"type":"Point"}
}