{
  "type": "Feature",
  "properties": {
    "iso:country":"IN",
    "ks:ks_alt_nam":"Keshari tola",
    "ks:ks_name":"Keshari Tola",
    "ks:ks_pop":217,
    "ks:ks_type":"HABITATION",
    "name:eng_x_preferred":[
        "Keshari Tola"
    ],
    "wof:name":"Keshari Tola",
    "wof:placetype":"locality",
    "wof:population":217
},
  "geometry": {"coordinates":[80.282546,20.088553],"type":"Point"}
}