{
  "type": "Feature",
  "properties": {
    "iso:country":"IN",
    "ks:ks_name":"S T Colony",
    "ks:ks_pop":58,
    "ks:ks_type":"HABITATION",
    "name:eng_x_preferred":[
        "S T Colony"
    ],
    "wof:name":"S T Colony",
    "wof:placetype":"locality",
    "wof:population":58
},
  "geometry": {"coordinates":[75.435874,12.952026],"type":"Point"}
}