{
  "type": "Feature",
  "properties": {
    "gn:admin1_code":"19.0",
    "gn:admin2_code":"575.0",
    "gn:asciiname":"Nelyadi",
    "gn:country_code":"IN",
    "gn:dem":142,
    "gn:feature_class":"P",
    "gn:feature_code":"PPLL",
    "gn:name":"Nely\u0101di",
    "gn:population":0,
    "gn:timezone":"Asia/Kolkata",
    "iso:country":"IN",
    "ks:ks_alt_nam":"Nely\u0101di",
    "ks:ks_name":"Nelyadi",
    "ks:ks_pop":4832,
    "ks:ks_type":"VILLAGE",
    "name:eng_x_preferred":[
        "Nelyadi"
    ],
    "name:eng_x_variant":[
        "Nely\u0101di"
    ],
    "wof:name":"Nelyadi",
    "wof:placetype":"locality",
    "wof:population":4832
},
  "geometry": {"coordinates":[75.389078,12.816561],"type":"Point"}
}