{
  "type": "Feature",
  "properties": {
    "gn:admin1_code":"23.0",
    "gn:admin2_code":"47.0",
    "gn:asciiname":"Bhama Kalan",
    "gn:country_code":"IN",
    "gn:dem":216,
    "gn:feature_class":"P",
    "gn:feature_code":"PPL",
    "gn:name":"Bhama Kal\u0101n",
    "gn:population":0,
    "gn:timezone":"Asia/Kolkata",
    "iso:country":"IN",
    "wof:name":"Bhama Kalan",
    "wof:placetype":"locality"
},
  "geometry": {"coordinates":[75.35319,29.87733],"type":"Point"}
}