{
  "type": "Feature",
  "properties": {
    "gn:admin1_code":"19.0",
    "gn:admin2_code":"556.0",
    "gn:asciiname":"Kalas",
    "gn:country_code":"IN",
    "gn:dem":551,
    "gn:feature_class":"P",
    "gn:feature_code":"PPL",
    "gn:name":"Kalas",
    "gn:population":0,
    "gn:timezone":"Asia/Kolkata",
    "iso:country":"IN",
    "name:ceb_x_preferred":[
        "Kalas"
    ],
    "name:ces_x_preferred":[
        "Kala\u0161"
    ],
    "name:deu_x_preferred":[
        "Kalas"
    ],
    "name:fin_x_preferred":[
        "Kalas"
    ],
    "name:pol_x_preferred":[
        "Kalas"
    ],
    "name:srp_x_preferred":[
        "\u041a\u0430\u043b\u0430\u0441"
    ],
    "name:swe_x_preferred":[
        "Kalas"
    ],
    "wof:name":"Kalas",
    "wof:placetype":"locality"
},
  "geometry": {"coordinates":[75.52334,15.85767],"type":"Point"}
}