{
  "type": "Feature",
  "properties": {
    "gn:admin1_code":"36.0",
    "gn:admin2_code":"150.0",
    "gn:asciiname":"Nagaria Ragunath",
    "gn:country_code":"IN",
    "gn:dem":167,
    "gn:feature_class":"P",
    "gn:feature_code":"PPL",
    "gn:name":"Nagaria Ragun\u0101th",
    "gn:population":0,
    "gn:timezone":"Asia/Kolkata",
    "iso:country":"IN",
    "wof:name":"Nagaria Ragunath",
    "wof:placetype":"locality"
},
  "geometry": {"coordinates":[79.67576,28.26442],"type":"Point"}
}