{
  "type": "Feature",
  "properties": {
    "iso:country":"IN",
    "ks:ks_name":"Umadla",
    "ks:ks_pop":254,
    "ks:ks_type":"VILLAGE",
    "name:eng_x_preferred":[
        "Umadla"
    ],
    "wof:name":"Umadla",
    "wof:placetype":"locality",
    "wof:population":254
},
  "geometry": {"coordinates":[77.625823,21.728606],"type":"Point"}
}