{
  "type": "Feature",
  "properties": {
    "iso:country":"IN",
    "ks:ks_alt_nam":"Lila Chauhano ki Fali",
    "ks:ks_name":"Lila Chauhano Ki Fali",
    "ks:ks_pop":334,
    "ks:ks_type":"HABITATION",
    "name:eng_x_preferred":[
        "Lila Chauhano Ki Fali"
    ],
    "wof:name":"Lila Chauhano Ki Fali",
    "wof:placetype":"locality",
    "wof:population":334
},
  "geometry": {"coordinates":[72.642128,24.506761],"type":"Point"}
}