{
  "type": "Feature",
  "properties": {
    "gn:admin1_code":"25.0",
    "gn:admin2_code":"604.0",
    "gn:asciiname":"Melputtur",
    "gn:country_code":"IN",
    "gn:dem":67,
    "gn:feature_class":"P",
    "gn:feature_code":"PPL",
    "gn:name":"Melputt\u016br",
    "gn:population":0,
    "gn:timezone":"Asia/Kolkata",
    "iso:country":"IN",
    "ks:ks_alt_nam":"Melputt\u016br",
    "ks:ks_name":"Melputtur",
    "ks:ks_type":"VILLAGE",
    "ks:ks_uagg_main":0,
    "name:eng_x_preferred":[
        "Melputtur"
    ],
    "name:eng_x_variant":[
        "Melputt\u016br"
    ],
    "wof:name":"Melputtur",
    "wof:placetype":"neighbourhood"
},
  "geometry": {"coordinates":[79.78065100000001,12.761147],"type":"Point"}
}