{
  "type": "Feature",
  "properties": {
    "iso:country":"IN",
    "ks:ks_name":"Baburani",
    "ks:ks_pop":1607,
    "ks:ks_type":"HABITATION",
    "name:eng_x_preferred":[
        "Baburani"
    ],
    "wof:name":"Baburani",
    "wof:placetype":"locality",
    "wof:population":1607
},
  "geometry": {"coordinates":[84.27472400000001,25.710925],"type":"Point"}
}