{
  "type": "Feature",
  "properties": {
    "gn:admin1_code":"25.0",
    "gn:admin2_code":"602.0",
    "gn:asciiname":"Vedatandalam",
    "gn:country_code":"IN",
    "gn:dem":10,
    "gn:feature_class":"P",
    "gn:feature_code":"PPL",
    "gn:name":"Vedatandalam",
    "gn:population":0,
    "gn:timezone":"Asia/Kolkata",
    "iso:country":"IN",
    "ks:ks_name":"Vidathandalam",
    "ks:ks_pop":665,
    "ks:ks_type":"VILLAGE",
    "name:eng_x_preferred":[
        "Vidathandalam"
    ],
    "name:eng_x_variant":[
        "Vedatandalam"
    ],
    "wof:name":"Vidathandalam",
    "wof:placetype":"locality",
    "wof:population":665
},
  "geometry": {"coordinates":[80.20165900000001,13.384832],"type":"Point"}
}