{
  "type": "Feature",
  "properties": {
    "iso:country":"IN",
    "ks:ks_name":"Korchakka",
    "ks:ks_pop":224,
    "ks:ks_type":"HABITATION",
    "name:eng_x_preferred":[
        "Korchakka"
    ],
    "wof:name":"Korchakka",
    "wof:placetype":"locality",
    "wof:population":224
},
  "geometry": {"coordinates":[86.90736800000001,25.518562],"type":"Point"}
}