{
  "type": "Feature",
  "properties": {
    "iso:country":"IN",
    "ks:ks_name":"Jogalewadi",
    "ks:ks_pop":188,
    "ks:ks_type":"HABITATION",
    "name:eng_x_preferred":[
        "Jogalewadi"
    ],
    "wof:name":"Jogalewadi",
    "wof:placetype":"locality",
    "wof:population":188
},
  "geometry": {"coordinates":[73.598056,16.615556],"type":"Point"}
}