{
  "type": "Feature",
  "properties": {
    "gn:admin1_code":"11",
    "gn:admin2_code":"23.0",
    "gn:asciiname":"Sanan Khet",
    "gn:country_code":"IN",
    "gn:dem":937,
    "gn:feature_class":"P",
    "gn:feature_code":"PPL",
    "gn:name":"Sanan Khet",
    "gn:population":0,
    "gn:timezone":"Asia/Kolkata",
    "iso:country":"IN",
    "wof:name":"Sanan Khet",
    "wof:placetype":"locality"
},
  "geometry": {"coordinates":[76.07094000000002,32.29597],"type":"Point"}
}