{
  "type": "Feature",
  "properties": {
    "iso:country":"IN",
    "ks:ks_alt_nam":"Shyamwadi tanda",
    "ks:ks_name":"Shyamwadi Tanda",
    "ks:ks_pop":256,
    "ks:ks_type":"HABITATION",
    "ks:ks_uagg_main":0,
    "name:eng_x_preferred":[
        "Shyamwadi Tanda"
    ],
    "wof:name":"Shyamwadi Tanda",
    "wof:placetype":"neighbourhood",
    "wof:population":256
},
  "geometry": {"coordinates":[75.446127,19.948505],"type":"Point"}
}