{
  "type": "Feature",
  "properties": {
    "iso:country":"IN",
    "ks:ks_alt_nam":"Rehed\u0101g",
    "ks:ks_name":"Rehedag",
    "ks:ks_pop":38,
    "ks:ks_type":"VILLAGE",
    "name:eng_x_preferred":[
        "Rehedag"
    ],
    "name:eng_x_variant":[
        "Rehed\u0101g"
    ],
    "wof:name":"Rehedag",
    "wof:placetype":"locality",
    "wof:population":38
},
  "geometry": {"coordinates":[84.972684,24.30403],"type":"Point"}
}