{
  "type": "Feature",
  "properties": {
    "iso:country":"IN",
    "ks:ks_alt_nam":"BAISAI",
    "ks:ks_name":"Baisai",
    "ks:ks_pop":65,
    "ks:ks_type":"HABITATION",
    "name:eng_x_preferred":[
        "Baisai"
    ],
    "wof:name":"Baisai",
    "wof:placetype":"locality",
    "wof:population":65
},
  "geometry": {"coordinates":[85.90183500000001,22.182671],"type":"Point"}
}