{
  "type": "Feature",
  "properties": {
    "gn:admin1_code":"11.0",
    "gn:admin2_code":"31.0",
    "gn:asciiname":"Naraini",
    "gn:country_code":"IN",
    "gn:dem":789,
    "gn:feature_class":"P",
    "gn:feature_code":"PPL",
    "gn:name":"Nar\u0101ini",
    "gn:population":0,
    "gn:timezone":"Asia/Kolkata",
    "iso:country":"IN",
    "name:bpy_x_preferred":[
        "\u09a8\u09be\u09b0\u09be\u09af\u09bc\u09a8\u09bf"
    ],
    "name:ceb_x_preferred":[
        "Naraini"
    ],
    "name:ita_x_preferred":[
        "Naraini"
    ],
    "name:msa_x_preferred":[
        "Naraini"
    ],
    "name:new_x_preferred":[
        "\u0928\u093e\u0930\u0948\u0928\u0940"
    ],
    "name:nld_x_preferred":[
        "Naraini"
    ],
    "name:pol_x_preferred":[
        "Naraini"
    ],
    "name:por_x_preferred":[
        "Naraini"
    ],
    "name:swe_x_preferred":[
        "Naraini"
    ],
    "name:urd_x_preferred":[
        "\u0646\u0631\u06cc\u0646\u06cc"
    ],
    "name:vie_x_preferred":[
        "Naraini"
    ],
    "name:zho_x_preferred":[
        "\u7eb3\u8d56\u5c3c"
    ],
    "wof:name":"Naraini",
    "wof:placetype":"locality"
},
  "geometry": {"coordinates":[77.01406,30.77134],"type":"Point"}
}