{
  "type": "Feature",
  "properties": {
    "gn:admin1_code":"34.0",
    "gn:admin2_code":"222.0",
    "gn:asciiname":"Asurari",
    "gn:country_code":"IN",
    "gn:dem":45,
    "gn:feature_class":"P",
    "gn:feature_code":"PPL",
    "gn:name":"Asur\u0101ri",
    "gn:population":0,
    "gn:timezone":"Asia/Kolkata",
    "iso:country":"IN",
    "ks:ks_alt_nam":"Asur\u0101ri",
    "ks:ks_name":"Asurari",
    "ks:ks_pop":1168,
    "ks:ks_type":"VILLAGE",
    "ks:ks_uagg_main":1,
    "name:eng_x_preferred":[
        "Asurari"
    ],
    "name:eng_x_variant":[
        "Asur\u0101ri"
    ],
    "wof:name":"Asurari",
    "wof:placetype":"locality",
    "wof:population":1168
},
  "geometry": {"coordinates":[86.01866699999999,25.434061],"type":"Point"}
}