{
  "type": "Feature",
  "properties": {
    "iso:country":"IN",
    "ks:ks_name":"Dima Gaon-1",
    "ks:ks_pop":13,
    "ks:ks_type":"HABITATION",
    "ks:ks_uagg_main":0,
    "name:eng_x_preferred":[
        "Dima Gaon-1"
    ],
    "wof:name":"Dima Gaon-1",
    "wof:placetype":"neighbourhood",
    "wof:population":13
},
  "geometry": {"coordinates":[92.734938,25.906155],"type":"Point"}
}