{
  "type": "Feature",
  "properties": {
    "gn:admin1_code":"36.0",
    "gn:admin2_code":"170.0",
    "gn:asciiname":"Thakuran Purwa",
    "gn:country_code":"IN",
    "gn:dem":129,
    "gn:feature_class":"P",
    "gn:feature_code":"PPL",
    "gn:name":"Thakuran Purwa",
    "gn:population":0,
    "gn:timezone":"Asia/Kolkata",
    "iso:country":"IN",
    "ks:ks_name":"Thakur Purwa",
    "ks:ks_pop":54,
    "ks:ks_type":"HABITATION",
    "name:eng_x_preferred":[
        "Thakur Purwa"
    ],
    "name:eng_x_variant":[
        "Thakuran Purwa"
    ],
    "wof:name":"Thakur Purwa",
    "wof:placetype":"locality",
    "wof:population":54
},
  "geometry": {"coordinates":[80.648709,25.224697],"type":"Point"}
}