{
  "type": "Feature",
  "properties": {
    "gn:admin1_code":"36.0",
    "gn:admin2_code":"170.0",
    "gn:asciiname":"Thakuran Purwa",
    "gn:country_code":"IN",
    "gn:dem":129,
    "gn:feature_class":"P",
    "gn:feature_code":"PPL",
    "gn:name":"Thakuran Purwa",
    "gn:population":0,
    "gn:timezone":"Asia/Kolkata",
    "iso:country":"IN",
    "wof:name":"Thakuran Purwa",
    "wof:placetype":"locality"
},
  "geometry": {"coordinates":[80.64846999999997,25.22486],"type":"Point"}
}