{
  "type": "Feature",
  "properties": {
    "iso:country":"IN",
    "ks:ks_name":"Keelapatti",
    "ks:ks_pop":72,
    "ks:ks_type":"HABITATION",
    "name:eng_x_preferred":[
        "Keelapatti"
    ],
    "wof:name":"Keelapatti",
    "wof:placetype":"locality",
    "wof:population":72
},
  "geometry": {"coordinates":[79.142464,10.596565],"type":"Point"}
}