{
  "type": "Feature",
  "properties": {
    "iso:country":"IN",
    "ks:ks_name":"Gowlidaddi",
    "ks:ks_pop":75,
    "ks:ks_type":"HABITATION",
    "name:eng_x_preferred":[
        "Gowlidaddi"
    ],
    "wof:name":"Gowlidaddi",
    "wof:placetype":"locality",
    "wof:population":75
},
  "geometry": {"coordinates":[74.99182500000001,14.980145],"type":"Point"}
}