{
  "type": "Feature",
  "properties": {
    "iso:country":"IN",
    "ks:ks_name":"Paphadiyana",
    "ks:ks_pop":506,
    "ks:ks_type":"VILLAGE",
    "name:eng_x_preferred":[
        "Paphadiyana"
    ],
    "wof:name":"Paphadiyana",
    "wof:placetype":"locality",
    "wof:population":506
},
  "geometry": {"coordinates":[79.03646000000001,30.007696],"type":"Point"}
}