{
  "type": "Feature",
  "properties": {
    "iso:country":"IN",
    "ks:ks_name":"Chodavaram",
    "ks:ks_pop":451,
    "ks:ks_type":"HABITATION",
    "name:eng_x_preferred":[
        "Chodavaram"
    ],
    "wof:name":"Chodavaram",
    "wof:placetype":"locality",
    "wof:population":451
},
  "geometry": {"coordinates":[81.68150199999999,16.539675],"type":"Point"}
}