{
  "type": "Feature",
  "properties": {
    "gn:admin1_code":"34.0",
    "gn:admin2_code":"222.0",
    "gn:asciiname":"Kumharsan",
    "gn:country_code":"IN",
    "gn:dem":45,
    "gn:feature_class":"P",
    "gn:feature_code":"PPL",
    "gn:name":"Kumharsan",
    "gn:population":0,
    "gn:timezone":"Asia/Kolkata",
    "iso:country":"IN",
    "wof:name":"Kumharsan",
    "wof:placetype":"locality"
},
  "geometry": {"coordinates":[86.19707,25.64208],"type":"Point"}
}