{
  "type": "Feature",
  "properties": {
    "iso:country":"IN",
    "ks:ks_name":"Dev",
    "ks:ks_pop":4699,
    "ks:ks_type":"HABITATION",
    "name:eng_x_preferred":[
        "Dev"
    ],
    "wof:name":"Dev",
    "wof:placetype":"locality",
    "wof:population":4699
},
  "geometry": {"coordinates":[84.350938,25.123152],"type":"Point"}
}