{
  "type": "Feature",
  "properties": {
    "iso:country":"IN",
    "ks:ks_name":"Chikhli Jhojha",
    "ks:ks_pop":761,
    "ks:ks_type":"VILLAGE",
    "name:eng_x_preferred":[
        "Chikhli Jhojha"
    ],
    "wof:name":"Chikhli Jhojha",
    "wof:placetype":"locality",
    "wof:population":761
},
  "geometry": {"coordinates":[73.449456,23.271391],"type":"Point"}
}