{
  "type": "Feature",
  "properties": {
    "iso:country":"IN",
    "ks:ks_alt_nam":"Katthalsar area",
    "ks:ks_name":"Katthalsar Area",
    "ks:ks_pop":574,
    "ks:ks_type":"HABITATION",
    "name:eng_x_preferred":[
        "Katthalsar Area"
    ],
    "wof:name":"Katthalsar Area",
    "wof:placetype":"locality",
    "wof:population":574
},
  "geometry": {"coordinates":[74.900093,13.00039],"type":"Point"}
}