{
  "type": "Feature",
  "properties": {
    "gn:admin1_code":"34.0",
    "gn:admin2_code":"219.0",
    "gn:asciiname":"Bhagwatpur",
    "gn:country_code":"IN",
    "gn:dem":59,
    "gn:feature_class":"P",
    "gn:feature_code":"PPL",
    "gn:name":"Bhagwatpur",
    "gn:population":0,
    "gn:timezone":"Asia/Kolkata",
    "iso:country":"IN",
    "ks:ks_name":"Bhagwatpur",
    "ks:ks_pop":3082,
    "ks:ks_type":"VILLAGE",
    "name:eng_x_preferred":[
        "Bhagwatpur"
    ],
    "wof:name":"Bhagwatpur",
    "wof:placetype":"locality",
    "wof:population":3082
},
  "geometry": {"coordinates":[84.883786,26.028311],"type":"Point"}
}