{
  "type": "Feature",
  "properties": {
    "iso:country":"IN",
    "ks:ks_alt_nam":"BARHI TOLA",
    "ks:ks_name":"Barhi Tola",
    "ks:ks_pop":255,
    "ks:ks_type":"HABITATION",
    "name:eng_x_preferred":[
        "Barhi Tola"
    ],
    "wof:name":"Barhi Tola",
    "wof:placetype":"locality",
    "wof:population":255
},
  "geometry": {"coordinates":[86.34413000000001,24.976279],"type":"Point"}
}