{
  "type": "Feature",
  "properties": {
    "iso:country":"IN",
    "ks:ks_name":"Ganganametta",
    "ks:ks_pop":272,
    "ks:ks_type":"VILLAGE",
    "name:eng_x_preferred":[
        "Ganganametta"
    ],
    "wof:name":"Ganganametta",
    "wof:placetype":"locality",
    "wof:population":272
},
  "geometry": {"coordinates":[81.322548,17.771881],"type":"Point"}
}