{
  "type": "Feature",
  "properties": {
    "iso:country":"IN",
    "ks:ks_name":"Mauli Wasti",
    "ks:ks_pop":80,
    "ks:ks_type":"HABITATION",
    "name:eng_x_preferred":[
        "Mauli Wasti"
    ],
    "wof:name":"Mauli Wasti",
    "wof:placetype":"locality",
    "wof:population":80
},
  "geometry": {"coordinates":[75.493809,19.141427],"type":"Point"}
}