{
  "type": "Feature",
  "properties": {
    "iso:country":"IN",
    "ks:ks_name":"Kothamaddiboinavaripalem",
    "ks:ks_pop":261,
    "ks:ks_type":"HABITATION",
    "ks:ks_uagg_main":0,
    "name:eng_x_preferred":[
        "Kothamaddiboinavaripalem"
    ],
    "wof:name":"Kothamaddiboinavaripalem",
    "wof:placetype":"neighbourhood",
    "wof:population":261
},
  "geometry": {"coordinates":[80.477267,15.875836],"type":"Point"}
}