{
  "type": "Feature",
  "properties": {
    "gn:admin1_code":"36",
    "gn:admin2_code":"188.0",
    "gn:asciiname":"Nadwa",
    "gn:country_code":"IN",
    "gn:dem":79,
    "gn:feature_class":"P",
    "gn:feature_code":"PPL",
    "gn:name":"Nadwa",
    "gn:population":0,
    "gn:timezone":"Asia/Kolkata",
    "iso:country":"IN",
    "name:und_x_variant":[
        "L\u0101lpur T\u012bkar"
    ],
    "wof:name":"Nadwa",
    "wof:placetype":"locality"
},
  "geometry": {"coordinates":[83.39588000000001,26.67745],"type":"Point"}
}