{
  "type": "Feature",
  "properties": {
    "iso:country":"IN",
    "ks:ks_name":"Chamalvarigadda Psgadda",
    "ks:ks_pop":31,
    "ks:ks_type":"HABITATION",
    "name:eng_x_preferred":[
        "Chamalvarigadda Psgadda"
    ],
    "wof:name":"Chamalvarigadda Psgadda",
    "wof:placetype":"locality",
    "wof:population":31
},
  "geometry": {"coordinates":[78.58273199999999,13.21276],"type":"Point"}
}