{
  "type": "Feature",
  "properties": {
    "iso:country":"IN",
    "ks:ks_name":"Oraon Tola",
    "ks:ks_pop":149,
    "ks:ks_type":"HABITATION",
    "name:eng_x_preferred":[
        "Oraon Tola"
    ],
    "wof:name":"Oraon Tola",
    "wof:placetype":"locality",
    "wof:population":149
},
  "geometry": {"coordinates":[83.599611,24.253777],"type":"Point"}
}