{
  "type": "Feature",
  "properties": {
    "iso:country":"IN",
    "ks:ks_name":"Chauki Azampur",
    "ks:ks_pop":1213,
    "ks:ks_type":"HABITATION",
    "name:eng_x_preferred":[
        "Chauki Azampur"
    ],
    "wof:name":"Chauki Azampur",
    "wof:placetype":"locality",
    "wof:population":1213
},
  "geometry": {"coordinates":[79.538448,27.857742],"type":"Point"}
}