{
  "type": "Feature",
  "properties": {
    "gn:admin1_code":"25.0",
    "gn:admin2_code":"606",
    "gn:asciiname":"Kalasapakkam",
    "gn:country_code":"IN",
    "gn:dem":182,
    "gn:feature_class":"P",
    "gn:feature_code":"PPL",
    "gn:name":"Kalasap\u0101kkam",
    "gn:population":0,
    "gn:timezone":"Asia/Kolkata",
    "iso:country":"IN",
    "name:tam_x_preferred":[
        "\u0b95\u0bb2\u0b9a\u0baa\u0bcd\u0baa\u0bbe\u0b95\u0bcd\u0b95\u0bae\u0bcd"
    ],
    "name:und_x_variant":[
        "Kalasapakam",
        "Kalasap\u0101kkam"
    ],
    "wof:name":"Kalasapakkam",
    "wof:placetype":"locality"
},
  "geometry": {"coordinates":[79.10048,12.43398],"type":"Point"}
}