{
  "type": "Feature",
  "properties": {
    "gn:admin1_code":"36.0",
    "gn:admin2_code":"142.0",
    "gn:asciiname":"Mubarakpur",
    "gn:country_code":"IN",
    "gn:dem":197,
    "gn:feature_class":"P",
    "gn:feature_code":"PPL",
    "gn:name":"Mub\u0101rakpur",
    "gn:population":0,
    "gn:timezone":"Asia/Kolkata",
    "iso:country":"IN",
    "name:ara_x_preferred":[
        "\u0645\u0628\u0627\u0631\u0643\u0641\u0648\u0631"
    ],
    "name:bih_x_preferred":[
        "\u092e\u0941\u092c\u093e\u0930\u0915\u092a\u0941\u0930"
    ],
    "name:bpy_x_preferred":[
        "\u09ae\u09c1\u09ac\u09be\u09b0\u0995\u09aa\u09c1\u09b0"
    ],
    "name:ceb_x_preferred":[
        "Mub\u0101rakpur"
    ],
    "name:fas_x_preferred":[
        "\u0645\u0628\u0627\u0631\u06a9\u200c\u067e\u0648\u0631"
    ],
    "name:hin_x_preferred":[
        "\u092e\u0941\u092c\u093e\u0930\u0915\u092a\u0941\u0930"
    ],
    "name:ita_x_preferred":[
        "Mubarakpur"
    ],
    "name:jpn_x_preferred":[
        "\u30e0\u30d0\u30fc\u30e9\u30af\u30d7\u30eb"
    ],
    "name:mlg_x_preferred":[
        "Mubarakpur"
    ],
    "name:msa_x_preferred":[
        "Mubarakpur"
    ],
    "name:new_x_preferred":[
        "\u092e\u0941\u092c\u093e\u0930\u0915\u092a\u0941\u0930"
    ],
    "name:nld_x_preferred":[
        "Mubarakpur"
    ],
    "name:pol_x_preferred":[
        "Mubarakpur"
    ],
    "name:swe_x_preferred":[
        "Mubarakpur"
    ],
    "name:urd_x_preferred":[
        "\u0645\u0628\u0627\u0631\u06a9\u067e\u0648\u0631"
    ],
    "name:vie_x_preferred":[
        "Mubarakpur"
    ],
    "name:zho_x_preferred":[
        "\u7a46\u5df4\u62c9\u514b\u666e\u5c14"
    ],
    "wof:name":"Mubarakpur",
    "wof:placetype":"locality"
},
  "geometry": {"coordinates":[78.27037,28.44699],"type":"Point"}
}