{
  "type": "Feature",
  "properties": {
    "gn:admin1_code":"34.0",
    "gn:admin2_code":"233",
    "gn:asciiname":"Barka Katra",
    "gn:country_code":"IN",
    "gn:dem":82,
    "gn:feature_class":"P",
    "gn:feature_code":"PPL",
    "gn:name":"Barka Katra",
    "gn:population":0,
    "gn:timezone":"Asia/Kolkata",
    "iso:country":"IN",
    "wof:name":"Barka Katra",
    "wof:placetype":"locality"
},
  "geometry": {"coordinates":[83.76794,25.19232],"type":"Point"}
}