{
  "type": "Feature",
  "properties": {
    "iso:country":"IN",
    "ks:ks_name":"Konarpatti",
    "ks:ks_pop":341,
    "ks:ks_type":"HABITATION",
    "name:eng_x_preferred":[
        "Konarpatti"
    ],
    "wof:name":"Konarpatti",
    "wof:placetype":"locality",
    "wof:population":341
},
  "geometry": {"coordinates":[78.338352,9.906155],"type":"Point"}
}