{
  "type": "Feature",
  "properties": {
    "iso:country":"IN",
    "ks:ks_name":"Kumhar Tola",
    "ks:ks_pop":590,
    "ks:ks_type":"HABITATION",
    "ks:ks_uagg_main":0,
    "name:eng_x_preferred":[
        "Kumhar Tola"
    ],
    "wof:name":"Kumhar Tola",
    "wof:placetype":"neighbourhood",
    "wof:population":590
},
  "geometry": {"coordinates":[84.517591,26.771189],"type":"Point"}
}