{
  "type": "Feature",
  "properties": {
    "gn:admin1_code":"19.0",
    "gn:admin2_code":"568.0",
    "gn:asciiname":"Munnur",
    "gn:country_code":"IN",
    "gn:dem":625,
    "gn:feature_class":"P",
    "gn:feature_code":"PPL",
    "gn:name":"Munnur",
    "gn:population":0,
    "gn:timezone":"Asia/Kolkata",
    "iso:country":"IN",
    "name:ben_x_preferred":[
        "\u09ae\u09c1\u09a8\u09cd\u09a8\u09c1\u09b0"
    ],
    "name:bpy_x_preferred":[
        "\u09ae\u09c1\u09a8\u09cd\u09a8\u09c1\u09b0"
    ],
    "name:ind_x_preferred":[
        "Munnur"
    ],
    "name:ita_x_preferred":[
        "Munnur"
    ],
    "name:mlg_x_preferred":[
        "Munnur"
    ],
    "name:msa_x_preferred":[
        "Munnur"
    ],
    "name:new_x_preferred":[
        "\u092e\u0941\u0928\u094d\u0928\u0941\u0930"
    ],
    "name:nld_x_preferred":[
        "Munnur"
    ],
    "name:por_x_preferred":[
        "Munnur"
    ],
    "name:vie_x_preferred":[
        "Munnur"
    ],
    "name:zho_x_preferred":[
        "\u7a46\u6069\u52aa\u5c14"
    ],
    "wof:name":"Munnur",
    "wof:placetype":"locality"
},
  "geometry": {"coordinates":[75.23026999999998,13.66329],"type":"Point"}
}