{
  "type": "Feature",
  "properties": {
    "gn:admin1_code":"19.0",
    "gn:admin2_code":"568.0",
    "gn:asciiname":"Munnur",
    "gn:country_code":"IN",
    "gn:dem":625,
    "gn:feature_class":"P",
    "gn:feature_code":"PPL",
    "gn:name":"Munnur",
    "gn:population":0,
    "gn:timezone":"Asia/Kolkata",
    "iso:country":"IN",
    "wof:name":"Munnur",
    "wof:placetype":"locality"
},
  "geometry": {"coordinates":[75.23026999999998,13.66329],"type":"Point"}
}