{
  "type": "Feature",
  "properties": {
    "iso:country":"IN",
    "ks:ks_name":"Pachkathia",
    "ks:ks_pop":52,
    "ks:ks_type":"HABITATION",
    "name:eng_x_preferred":[
        "Pachkathia"
    ],
    "wof:name":"Pachkathia",
    "wof:placetype":"locality",
    "wof:population":52
},
  "geometry": {"coordinates":[86.48411900000001,24.716104],"type":"Point"}
}