{
  "type": "Feature",
  "properties": {
    "gn:admin1_code":"21",
    "gn:admin2_code":"371.0",
    "gn:asciiname":"Sukalpali",
    "gn:country_code":"IN",
    "gn:dem":213,
    "gn:feature_class":"P",
    "gn:feature_code":"PPL",
    "gn:name":"Sukalp\u0101li",
    "gn:population":0,
    "gn:timezone":"Asia/Kolkata",
    "iso:country":"IN",
    "wof:name":"Sukalpali",
    "wof:placetype":"locality"
},
  "geometry": {"coordinates":[83.60411999999999,21.80166],"type":"Point"}
}