{
  "type": "Feature",
  "properties": {
    "iso:country":"IN",
    "ks:ks_name":"Morlabadwathanda",
    "ks:ks_pop":148,
    "ks:ks_type":"HABITATION",
    "name:eng_x_preferred":[
        "Morlabadwathanda"
    ],
    "wof:name":"Morlabadwathanda",
    "wof:placetype":"locality",
    "wof:population":148
},
  "geometry": {"coordinates":[79.87547000000001,17.774993],"type":"Point"}
}