{
  "type": "Feature",
  "properties": {
    "gn:admin1_code":"11",
    "gn:admin2_code":"24.0",
    "gn:asciiname":"Bulli",
    "gn:country_code":"IN",
    "gn:dem":538,
    "gn:feature_class":"P",
    "gn:feature_code":"PPL",
    "gn:name":"Bulli",
    "gn:population":0,
    "gn:timezone":"Asia/Kolkata",
    "iso:country":"IN",
    "name:ceb_x_preferred":[
        "Bulli"
    ],
    "name:deu_x_preferred":[
        "Bulli"
    ],
    "wof:name":"Bulli",
    "wof:placetype":"locality"
},
  "geometry": {"coordinates":[76.45544,31.80691],"type":"Point"}
}