{
  "type": "Feature",
  "properties": {
    "iso:country":"IN",
    "ks:ks_name":"Kadamane",
    "ks:ks_pop":244,
    "ks:ks_type":"HABITATION",
    "name:eng_x_preferred":[
        "Kadamane"
    ],
    "wof:name":"Kadamane",
    "wof:placetype":"locality",
    "wof:population":244
},
  "geometry": {"coordinates":[75.69237,13.058271],"type":"Point"}
}