{
  "type": "Feature",
  "properties": {
    "iso:country":"IN",
    "ks:ks_name":"Mahuwa Diha",
    "ks:ks_pop":2584,
    "ks:ks_type":"VILLAGE",
    "ks:ks_uagg_main":0,
    "name:eng_x_preferred":[
        "Mahuwa Diha"
    ],
    "wof:name":"Mahuwa Diha",
    "wof:placetype":"neighbourhood",
    "wof:population":2584
},
  "geometry": {"coordinates":[82.11037899999999,25.371243],"type":"Point"}
}