{
  "type": "Feature",
  "properties": {
    "iso:country":"IN",
    "ks:ks_name":"Puthan Kovilakam Road",
    "ks:ks_pop":165,
    "ks:ks_type":"HABITATION",
    "ks:ks_uagg_main":0,
    "name:eng_x_preferred":[
        "Puthan Kovilakam Road"
    ],
    "wof:name":"Puthan Kovilakam Road",
    "wof:placetype":"neighbourhood",
    "wof:population":165
},
  "geometry": {"coordinates":[76.12402899999999,10.457576],"type":"Point"}
}