{
  "type": "Feature",
  "properties": {
    "iso:country":"IN",
    "ks:ks_alt_nam":"Telegu gudicelu",
    "ks:ks_name":"Telegu Gudicelu",
    "ks:ks_pop":97,
    "ks:ks_type":"HABITATION",
    "name:eng_x_preferred":[
        "Telegu Gudicelu"
    ],
    "wof:name":"Telegu Gudicelu",
    "wof:placetype":"locality",
    "wof:population":97
},
  "geometry": {"coordinates":[77.89899800000001,17.009593],"type":"Point"}
}