{
  "type": "Feature",
  "properties": {
    "iso:country":"IN",
    "ks:ks_name":"Mondkarwadi",
    "ks:ks_pop":90,
    "ks:ks_type":"HABITATION",
    "name:eng_x_preferred":[
        "Mondkarwadi"
    ],
    "wof:name":"Mondkarwadi",
    "wof:placetype":"locality",
    "wof:population":90
},
  "geometry": {"coordinates":[73.493008,15.981638],"type":"Point"}
}