{
  "type": "Feature",
  "properties": {
    "iso:country":"IN",
    "ks:ks_name":"Duadia",
    "ks:ks_pop":2282,
    "ks:ks_type":"VILLAGE",
    "ks:ks_uagg_main":0,
    "name:eng_x_preferred":[
        "Duadia"
    ],
    "wof:name":"Duadia",
    "wof:placetype":"neighbourhood",
    "wof:population":2282
},
  "geometry": {"coordinates":[86.540978,20.30779],"type":"Point"}
}