{
  "type": "Feature",
  "properties": {
    "iso:country":"IN",
    "ks:ks_name":"Kol Basti",
    "ks:ks_pop":272,
    "ks:ks_type":"HABITATION",
    "name:eng_x_preferred":[
        "Kol Basti"
    ],
    "wof:name":"Kol Basti",
    "wof:placetype":"locality",
    "wof:population":272
},
  "geometry": {"coordinates":[82.80270899999999,24.76232],"type":"Point"}
}