{
  "type": "Feature",
  "properties": {
    "iso:country":"IN",
    "ks:ks_alt_nam":"NAWA TOLI",
    "ks:ks_name":"Nawa Toli",
    "ks:ks_pop":225,
    "ks:ks_type":"HABITATION",
    "name:eng_x_preferred":[
        "Nawa Toli"
    ],
    "wof:name":"Nawa Toli",
    "wof:placetype":"locality",
    "wof:population":225
},
  "geometry": {"coordinates":[85.52740300000001,22.215596],"type":"Point"}
}