{
  "type": "Feature",
  "properties": {
    "iso:country":"IN",
    "ks:ks_name":"Niginpur",
    "ks:ks_pop":1112,
    "ks:ks_type":"VILLAGE",
    "name:eng_x_preferred":[
        "Niginpur"
    ],
    "wof:name":"Niginpur",
    "wof:placetype":"locality",
    "wof:population":1112
},
  "geometry": {"coordinates":[86.56414700000001,20.479421],"type":"Point"}
}