{
  "type": "Feature",
  "properties": {
    "iso:country":"IN",
    "ks:ks_name":"Ven",
    "ks:ks_pop":627,
    "ks:ks_type":"HABITATION",
    "name:eng_x_preferred":[
        "Ven"
    ],
    "wof:name":"Ven",
    "wof:placetype":"locality",
    "wof:population":627
},
  "geometry": {"coordinates":[74.11794999999999,24.113689],"type":"Point"}
}