{
  "type": "Feature",
  "properties": {
    "iso:country":"IN",
    "ks:ks_name":"Murgiduma",
    "ks:ks_pop":534,
    "ks:ks_type":"VILLAGE",
    "name:eng_x_preferred":[
        "Murgiduma"
    ],
    "wof:name":"Murgiduma",
    "wof:placetype":"locality",
    "wof:population":534
},
  "geometry": {"coordinates":[87.200762,24.494147],"type":"Point"}
}