{
  "type": "Feature",
  "properties": {
    "gn:admin1_code":"28.0",
    "gn:admin2_code":"334.0",
    "gn:asciiname":"Sursal Fakirpur",
    "gn:country_code":"IN",
    "gn:dem":65,
    "gn:feature_class":"P",
    "gn:feature_code":"PPL",
    "gn:name":"Surs\u0101l Fakirpur",
    "gn:population":0,
    "gn:timezone":"Asia/Kolkata",
    "iso:country":"IN",
    "wof:name":"Sursal Fakirpur",
    "wof:placetype":"neighbourhood"
},
  "geometry": {"coordinates":[87.62023000000001,24.04755],"type":"Point"}
}