{
  "type": "Feature",
  "properties": {
    "iso:country":"IN",
    "ks:ks_name":"Dasarmane",
    "ks:ks_pop":21,
    "ks:ks_type":"HABITATION",
    "name:eng_x_preferred":[
        "Dasarmane"
    ],
    "wof:name":"Dasarmane",
    "wof:placetype":"locality",
    "wof:population":21
},
  "geometry": {"coordinates":[74.66949700000001,15.033288],"type":"Point"}
}