{
  "type": "Feature",
  "properties": {
    "gn:admin1_code":"38",
    "gn:admin2_code":"346.0",
    "gn:asciiname":"Talasbaria",
    "gn:country_code":"IN",
    "gn:dem":170,
    "gn:feature_class":"P",
    "gn:feature_code":"PPL",
    "gn:name":"Talasbaria",
    "gn:population":0,
    "gn:timezone":"Asia/Kolkata",
    "iso:country":"IN",
    "ks:ks_name":"Talasbaria",
    "ks:ks_pop":1150,
    "ks:ks_type":"VILLAGE",
    "ks:ks_uagg_main":0,
    "name:eng_x_preferred":[
        "Talasbaria"
    ],
    "wof:name":"Talasbaria",
    "wof:placetype":"neighbourhood",
    "wof:population":1150
},
  "geometry": {"coordinates":[83.788033,24.334737],"type":"Point"}
}