{
  "type": "Feature",
  "properties": {
    "iso:country":"IN",
    "ks:ks_name":"Ranganathapura",
    "ks:ks_pop":174,
    "ks:ks_type":"HABITATION",
    "name:eng_x_preferred":[
        "Ranganathapura"
    ],
    "wof:name":"Ranganathapura",
    "wof:placetype":"locality",
    "wof:population":174
},
  "geometry": {"coordinates":[77.25579500000001,12.942044],"type":"Point"}
}