{
  "type": "Feature",
  "properties": {
    "iso:country":"IN",
    "ks:ks_name":"Kannarakunnu",
    "ks:ks_pop":558,
    "ks:ks_type":"HABITATION",
    "name:eng_x_preferred":[
        "Kannarakunnu"
    ],
    "wof:name":"Kannarakunnu",
    "wof:placetype":"locality",
    "wof:population":558
},
  "geometry": {"coordinates":[76.359104,10.510242],"type":"Point"}
}