{
  "type": "Feature",
  "properties": {
    "gn:admin1_code":"36",
    "gn:admin2_code":"173.0",
    "gn:asciiname":"Ghagarpara",
    "gn:country_code":"IN",
    "gn:dem":89,
    "gn:feature_class":"P",
    "gn:feature_code":"PPL",
    "gn:name":"Gh\u0101garp\u0101ra",
    "gn:population":0,
    "gn:timezone":"Asia/Kolkata",
    "iso:country":"IN",
    "ks:ks_name":"Ghagharpara",
    "ks:ks_pop":471,
    "ks:ks_type":"VILLAGE",
    "ks:ks_uagg_main":0,
    "name:eng_x_preferred":[
        "Ghagharpara"
    ],
    "wof:name":"Ghagharpara",
    "wof:placetype":"neighbourhood",
    "wof:population":471
},
  "geometry": {"coordinates":[82.428623,25.980835],"type":"Point"}
}