{
  "type": "Feature",
  "properties": {
    "gn:admin1_code":"23.0",
    "gn:admin2_code":"41.0",
    "gn:asciiname":"Pamal",
    "gn:country_code":"IN",
    "gn:dem":243,
    "gn:feature_class":"P",
    "gn:feature_code":"PPL",
    "gn:name":"Pam\u0101l",
    "gn:population":0,
    "gn:timezone":"Asia/Kolkata",
    "iso:country":"IN",
    "name:pan_x_preferred":[
        "\u0a2a\u0a2e\u0a3e\u0a32"
    ],
    "name:und_x_variant":[
        "Pam\u0101l"
    ],
    "wof:name":"Pamal",
    "wof:placetype":"locality"
},
  "geometry": {"coordinates":[75.7402,30.83836],"type":"Point"}
}