{
  "type": "Feature",
  "properties": {
    "iso:country":"IN",
    "ks:ks_name":"Shilhat",
    "ks:ks_pop":7,
    "ks:ks_type":"HABITATION",
    "name:eng_x_preferred":[
        "Shilhat"
    ],
    "wof:name":"Shilhat",
    "wof:placetype":"locality",
    "wof:population":7
},
  "geometry": {"coordinates":[83.342814,24.667134],"type":"Point"}
}