{
  "type": "Feature",
  "properties": {
    "iso:country":"IN",
    "ks:ks_name":"Kurar Khanarsichar",
    "ks:ks_pop":747,
    "ks:ks_type":"VILLAGE",
    "name:eng_x_preferred":[
        "Kurar Khanarsichar"
    ],
    "wof:name":"Kurar Khanarsichar",
    "wof:placetype":"locality",
    "wof:population":747
},
  "geometry": {"coordinates":[77.90569000000001,30.722105],"type":"Point"}
}