{
  "type": "Feature",
  "properties": {
    "iso:country":"IN",
    "ks:ks_name":"Bennabalagadde",
    "ks:ks_pop":24,
    "ks:ks_type":"HABITATION",
    "name:eng_x_preferred":[
        "Bennabalagadde"
    ],
    "wof:name":"Bennabalagadde",
    "wof:placetype":"locality",
    "wof:population":24
},
  "geometry": {"coordinates":[74.745144,14.928866],"type":"Point"}
}