{
  "type": "Feature",
  "properties": {
    "iso:country":"IN",
    "ks:ks_name":"Kathewadi",
    "ks:ks_pop":128,
    "ks:ks_type":"HABITATION",
    "name:eng_x_preferred":[
        "Kathewadi"
    ],
    "wof:name":"Kathewadi",
    "wof:placetype":"locality",
    "wof:population":128
},
  "geometry": {"coordinates":[73.67491699999999,19.195008],"type":"Point"}
}