{
  "type": "Feature",
  "properties": {
    "iso:country":"IN",
    "ks:ks_name":"Manakadevi",
    "ks:ks_pop":165,
    "ks:ks_type":"HABITATION",
    "name:eng_x_preferred":[
        "Manakadevi"
    ],
    "wof:name":"Manakadevi",
    "wof:placetype":"locality",
    "wof:population":165
},
  "geometry": {"coordinates":[73.66237099999999,16.002601],"type":"Point"}
}