{
  "type": "Feature",
  "properties": {
    "iso:country":"IN",
    "ks:ks_name":"Dongriguda 5",
    "ks:ks_pop":686,
    "ks:ks_type":"HABITATION",
    "name:eng_x_preferred":[
        "Dongriguda 5"
    ],
    "wof:name":"Dongriguda 5",
    "wof:placetype":"locality",
    "wof:population":686
},
  "geometry": {"coordinates":[82.069971,19.700126],"type":"Point"}
}