{
  "type": "Feature",
  "properties": {
    "iso:country":"IN",
    "qs:name":"Kashi Mitra",
    "qs:name_adm0":"India",
    "qs:name_adm1":"West Bengal",
    "qs:photos":103,
    "qs:photos_1k":21,
    "qs:photos_9k":1,
    "qs:photos_9r":3,
    "qs:photos_all":103,
    "qs:photos_sr":3,
    "qs:placetype":"Suburb",
    "qs:pop_sr":"0",
    "wof:name":"Kashi Mitra",
    "wof:placetype":"neighbourhood"
},
  "geometry": {"coordinates":[88.360805,22.598797],"type":"Point"}
}