{
  "type": "Feature",
  "properties": {
    "iso:country":"IN",
    "ks:ks_name":"Uperpara",
    "ks:ks_pop":44,
    "ks:ks_type":"HABITATION",
    "name:eng_x_preferred":[
        "Uperpara"
    ],
    "wof:name":"Uperpara",
    "wof:placetype":"locality",
    "wof:population":44
},
  "geometry": {"coordinates":[81.188315,19.805738],"type":"Point"}
}