{
  "type": "Feature",
  "properties": {
    "iso:country":"IN",
    "ks:ks_name":"Kelaginavadageri",
    "ks:ks_pop":174,
    "ks:ks_type":"HABITATION",
    "name:eng_x_preferred":[
        "Kelaginavadageri"
    ],
    "wof:name":"Kelaginavadageri",
    "wof:placetype":"locality",
    "wof:population":174
},
  "geometry": {"coordinates":[74.91973400000001,14.394299],"type":"Point"}
}