{
  "type": "Feature",
  "properties": {
    "iso:country":"IN",
    "ks:ks_name":"Teok Gaon Boiragi Habi Road Pt 2",
    "ks:ks_pop":360,
    "ks:ks_type":"HABITATION",
    "name:eng_x_preferred":[
        "Teok Gaon Boiragi Habi Road Pt 2"
    ],
    "wof:name":"Teok Gaon Boiragi Habi Road Pt 2",
    "wof:placetype":"locality",
    "wof:population":360
},
  "geometry": {"coordinates":[95.09081500000001,27.026546],"type":"Point"}
}