{
  "type": "Feature",
  "properties": {
    "gn:admin1_code":"35.0",
    "gn:admin2_code":"418.0",
    "gn:asciiname":"Chak Fatehpur",
    "gn:country_code":"IN",
    "gn:dem":245,
    "gn:feature_class":"P",
    "gn:feature_code":"PPL",
    "gn:name":"Chak Fatehpur",
    "gn:population":0,
    "gn:timezone":"Asia/Kolkata",
    "iso:country":"IN",
    "wof:name":"Chak Fatehpur",
    "wof:placetype":"locality"
},
  "geometry": {"coordinates":[76.73043,25.58916],"type":"Point"}
}