{
  "type": "Feature",
  "properties": {
    "gn:admin1_code":"36",
    "gn:admin2_code":"174.0",
    "gn:asciiname":"Bandhwa Rajbar",
    "gn:country_code":"IN",
    "gn:dem":107,
    "gn:feature_class":"P",
    "gn:feature_code":"PPL",
    "gn:name":"Bandhwa R\u0101jbar",
    "gn:population":0,
    "gn:timezone":"Asia/Kolkata",
    "iso:country":"IN",
    "wof:name":"Bandhwa Rajbar",
    "wof:placetype":"locality"
},
  "geometry": {"coordinates":[81.40434999999999,25.51246],"type":"Point"}
}