{
  "type": "Feature",
  "properties": {
    "gn:admin1_code":"35.0",
    "gn:admin2_code":"418.0",
    "gn:asciiname":"Bahrawda",
    "gn:country_code":"IN",
    "gn:dem":210,
    "gn:feature_class":"P",
    "gn:feature_code":"PPL",
    "gn:name":"Bahr\u0101wda",
    "gn:population":0,
    "gn:timezone":"Asia/Kolkata",
    "iso:country":"IN",
    "wof:name":"Bahrawda",
    "wof:placetype":"locality"
},
  "geometry": {"coordinates":[76.71603,25.83371],"type":"Point"}
}