{
  "type": "Feature",
  "properties": {
    "iso:country":"IN",
    "ks:ks_name":"Kadam Chandra",
    "ks:ks_pop":293,
    "ks:ks_type":"HABITATION",
    "name:eng_x_preferred":[
        "Kadam Chandra"
    ],
    "wof:name":"Kadam Chandra",
    "wof:placetype":"locality",
    "wof:population":293
},
  "geometry": {"coordinates":[91.67210300000001,23.72608],"type":"Point"}
}