{
  "type": "Feature",
  "properties": {
    "iso:country":"IN",
    "ks:ks_name":"Jampani",
    "ks:ks_pop":135,
    "ks:ks_type":"VILLAGE",
    "name:eng_x_preferred":[
        "Jampani"
    ],
    "wof:name":"Jampani",
    "wof:placetype":"locality",
    "wof:population":135
},
  "geometry": {"coordinates":[82.96999099999999,23.461612],"type":"Point"}
}