{
  "type": "Feature",
  "properties": {
    "gn:admin1_code":"23",
    "gn:admin2_code":"51.0",
    "gn:asciiname":"Ganu Mazra",
    "gn:country_code":"IN",
    "gn:dem":275,
    "gn:feature_class":"P",
    "gn:feature_code":"PPL",
    "gn:name":"Ganu M\u0101zra",
    "gn:population":0,
    "gn:timezone":"Asia/Kolkata",
    "iso:country":"IN",
    "wof:name":"Ganu Mazra",
    "wof:placetype":"neighbourhood"
},
  "geometry": {"coordinates":[76.55395,31.02709],"type":"Point"}
}