{
  "type": "Feature",
  "properties": {
    "iso:country":"IN",
    "ks:ks_name":"Amgaon",
    "ks:ks_pop":1737,
    "ks:ks_type":"VILLAGE",
    "name:eng_x_preferred":[
        "Amgaon"
    ],
    "wof:name":"Amgaon",
    "wof:placetype":"locality",
    "wof:population":1737
},
  "geometry": {"coordinates":[82.530908,23.294086],"type":"Point"}
}