{
  "type": "Feature",
  "properties": {
    "iso:country":"IN",
    "ks:ks_name":"Karabylu",
    "ks:ks_pop":347,
    "ks:ks_type":"HABITATION",
    "name:eng_x_preferred":[
        "Karabylu"
    ],
    "wof:name":"Karabylu",
    "wof:placetype":"locality",
    "wof:population":347
},
  "geometry": {"coordinates":[75.425662,13.64951],"type":"Point"}
}