{
  "type": "Feature",
  "properties": {
    "gn:admin1_code":"36.0",
    "gn:admin2_code":"161",
    "gn:asciiname":"Ahliaranpura",
    "gn:country_code":"IN",
    "gn:dem":149,
    "gn:feature_class":"P",
    "gn:feature_code":"PPL",
    "gn:name":"Ahli\u0101ranpura",
    "gn:population":0,
    "gn:timezone":"Asia/Kolkata",
    "iso:country":"IN",
    "name:und_x_variant":[
        "Ahli\u0101ranpura",
        "Aiwranpura"
    ],
    "wof:name":"Ahliaranpura",
    "wof:placetype":"locality"
},
  "geometry": {"coordinates":[79.248,26.87067],"type":"Point"}
}