{
  "type": "Feature",
  "properties": {
    "iso:country":"IN",
    "ks:ks_name":"Rajput Tola",
    "ks:ks_pop":8898,
    "ks:ks_type":"HABITATION",
    "name:eng_x_preferred":[
        "Rajput Tola"
    ],
    "wof:name":"Rajput Tola",
    "wof:placetype":"locality",
    "wof:population":8898
},
  "geometry": {"coordinates":[85.806118,25.610143],"type":"Point"}
}