{
  "type": "Feature",
  "properties": {
    "iso:country":"IN",
    "ks:ks_name":"Nuagan",
    "ks:ks_pop":87,
    "ks:ks_type":"VILLAGE",
    "name:eng_x_preferred":[
        "Nuagan"
    ],
    "wof:name":"Nuagan",
    "wof:placetype":"locality",
    "wof:population":87
},
  "geometry": {"coordinates":[84.104023,19.32572],"type":"Point"}
}