{
  "type": "Feature",
  "properties": {
    "gn:admin1_code":"2.0",
    "gn:admin2_code":"551",
    "gn:asciiname":"Gangireddipalle",
    "gn:country_code":"IN",
    "gn:dem":179,
    "gn:feature_class":"P",
    "gn:feature_code":"PPL",
    "gn:name":"Gangireddipalle",
    "gn:population":0,
    "gn:timezone":"Asia/Kolkata",
    "iso:country":"IN",
    "name:und_x_variant":[
        "Gangireddipalli",
        "Gangireddipalle"
    ],
    "wof:name":"Gangireddipalle",
    "wof:placetype":"locality"
},
  "geometry": {"coordinates":[78.4893,14.51771],"type":"Point"}
}