{
  "type": "Feature",
  "properties": {
    "gn:admin1_code":"34",
    "gn:admin2_code":"211.0",
    "gn:asciiname":"Sarsi Istamrar",
    "gn:country_code":"IN",
    "gn:dem":47,
    "gn:feature_class":"P",
    "gn:feature_code":"PPL",
    "gn:name":"Sarsi Istamr\u0101r",
    "gn:population":0,
    "gn:timezone":"Asia/Kolkata",
    "iso:country":"IN",
    "name:und_x_variant":[
        "Sarsi Istamr\u0101r",
        "Sarsi Istamrar"
    ],
    "wof:name":"Sarsi Istamrar",
    "wof:placetype":"locality"
},
  "geometry": {"coordinates":[87.2902,25.8508],"type":"Point"}
}