{
  "type": "Feature",
  "properties": {
    "gn:admin1_code":"19.0",
    "gn:admin2_code":"583.0",
    "gn:asciiname":"Koltur",
    "gn:country_code":"IN",
    "gn:dem":888,
    "gn:feature_class":"P",
    "gn:feature_code":"PPL",
    "gn:name":"Kolt\u016br",
    "gn:population":0,
    "gn:timezone":"Asia/Kolkata",
    "iso:country":"IN",
    "name:aze_x_preferred":[
        "Koltur adas\u0131"
    ],
    "name:bel_x_preferred":[
        "\u041a\u043e\u043b\u044c\u0442\u0443\u0440"
    ],
    "name:cat_x_preferred":[
        "Koltur"
    ],
    "name:ces_x_preferred":[
        "Koltur"
    ],
    "name:dan_x_preferred":[
        "Koltur"
    ],
    "name:deu_x_preferred":[
        "Koltur"
    ],
    "name:ell_x_preferred":[
        "\u039a\u03cc\u03bb\u03c4\u03bf\u03c5\u03c1"
    ],
    "name:epo_x_preferred":[
        "Koltur"
    ],
    "name:est_x_preferred":[
        "Koltur"
    ],
    "name:fao_x_preferred":[
        "Koltur"
    ],
    "name:fin_x_preferred":[
        "Koltur"
    ],
    "name:fra_x_preferred":[
        "Koltur"
    ],
    "name:fry_x_preferred":[
        "Koltur"
    ],
    "name:gla_x_preferred":[
        "Koltur"
    ],
    "name:gle_x_preferred":[
        "Koltur"
    ],
    "name:heb_x_preferred":[
        "\u05e7\u05d5\u05dc\u05d8\u05d5\u05e8"
    ],
    "name:hun_x_preferred":[
        "Koltur"
    ],
    "name:ind_x_preferred":[
        "Koltur"
    ],
    "name:isl_x_preferred":[
        "Koltur"
    ],
    "name:ita_x_preferred":[
        "Koltur"
    ],
    "name:jpn_x_preferred":[
        "\u30b3\u30eb\u30c8\u30a5\u30eb\u5cf6"
    ],
    "name:kor_x_preferred":[
        "\ucf5c\ud22c\ub974\uc12c"
    ],
    "name:lit_x_preferred":[
        "Kolturas"
    ],
    "name:nld_x_preferred":[
        "Koltur"
    ],
    "name:nno_x_preferred":[
        "Koltur"
    ],
    "name:nor_x_preferred":[
        "Koltur"
    ],
    "name:oss_x_preferred":[
        "\u041a\u043e\u043b\u0442\u0443\u0440"
    ],
    "name:pol_x_preferred":[
        "Koltur"
    ],
    "name:por_x_preferred":[
        "Koltur"
    ],
    "name:ron_x_preferred":[
        "Insula Koltur"
    ],
    "name:rus_x_preferred":[
        "\u041a\u043e\u043b\u044c\u0442\u0443\u0440"
    ],
    "name:sco_x_preferred":[
        "Koltur"
    ],
    "name:slk_x_preferred":[
        "Koltur"
    ],
    "name:spa_x_preferred":[
        "Koltur"
    ],
    "name:srp_x_preferred":[
        "\u041a\u043e\u043b\u0442\u0443\u0440"
    ],
    "name:swe_x_preferred":[
        "Koltur"
    ],
    "name:ukr_x_preferred":[
        "\u041a\u043e\u043b\u044c\u0442\u0443\u0440"
    ],
    "name:vie_x_preferred":[
        "Koltur"
    ],
    "name:zho_x_preferred":[
        "\u79d1\u5c14\u7279\u5c9b"
    ],
    "wof:name":"Koltur",
    "wof:placetype":"locality"
},
  "geometry": {"coordinates":[77.83015999999998,13.07477],"type":"Point"}
}