{
  "type": "Feature",
  "properties": {
    "iso:country":"IN",
    "ks:ks_name":"Bilebenchi Timmayyanadoddi",
    "ks:ks_pop":160,
    "ks:ks_type":"HABITATION",
    "name:eng_x_preferred":[
        "Bilebenchi Timmayyanadoddi"
    ],
    "wof:name":"Bilebenchi Timmayyanadoddi",
    "wof:placetype":"locality",
    "wof:population":160
},
  "geometry": {"coordinates":[76.726502,16.30577],"type":"Point"}
}