{
  "type": "Feature",
  "properties": {
    "iso:country":"IN",
    "ks:ks_name":"Kailsure",
    "ks:ks_pop":194,
    "ks:ks_type":"HABITATION",
    "name:eng_x_preferred":[
        "Kailsure"
    ],
    "wof:name":"Kailsure",
    "wof:placetype":"locality",
    "wof:population":194
},
  "geometry": {"coordinates":[83.76092800000001,20.202056],"type":"Point"}
}