{
  "type": "Feature",
  "properties": {
    "gn:admin1_code":"36.0",
    "gn:admin2_code":"165.0",
    "gn:asciiname":"Khor Mansukhhpura",
    "gn:country_code":"IN",
    "gn:dem":157,
    "gn:feature_class":"P",
    "gn:feature_code":"PPL",
    "gn:name":"Khor Mansukhhpura",
    "gn:population":0,
    "gn:timezone":"Asia/Kolkata",
    "iso:country":"IN",
    "wof:name":"Khor Mansukhhpura",
    "wof:placetype":"neighbourhood"
},
  "geometry": {"coordinates":[79.02249999999999,26.03267],"type":"Point"}
}