{
  "type": "Feature",
  "properties": {
    "iso:country":"IN",
    "ks:ks_name":"Simul Tala",
    "ks:ks_pop":4452,
    "ks:ks_type":"VILLAGE",
    "ks:ks_uagg_main":0,
    "name:eng_x_preferred":[
        "Simul Tala"
    ],
    "wof:name":"Simul Tala",
    "wof:placetype":"locality",
    "wof:population":4452
},
  "geometry": {"coordinates":[88.46120000000001,23.400365],"type":"Point"}
}