{
  "type": "Feature",
  "properties": {
    "gn:admin1_code":"16",
    "gn:admin2_code":"499.0",
    "gn:asciiname":"Ambada",
    "gn:country_code":"IN",
    "gn:dem":207,
    "gn:feature_class":"P",
    "gn:feature_code":"PPL",
    "gn:name":"\u0100mb\u0101da",
    "gn:population":0,
    "gn:timezone":"Asia/Kolkata",
    "iso:country":"IN",
    "name:ben_x_preferred":[
        "\u0986\u09ae\u09ac\u09a1\u09bc\u09be"
    ],
    "name:bpy_x_preferred":[
        "\u0986\u09ae\u09ac\u09a1\u09bc\u09be"
    ],
    "name:fas_x_preferred":[
        "\u0627\u0645\u0628\u0627\u062f\u0627"
    ],
    "name:ita_x_preferred":[
        "Ambada"
    ],
    "name:min_x_preferred":[
        "Ambada"
    ],
    "name:msa_x_preferred":[
        "Ambada"
    ],
    "name:new_x_preferred":[
        "\u0905\u092e\u092c\u093e\u0926\u093e"
    ],
    "name:nld_x_preferred":[
        "Ambada"
    ],
    "name:por_x_preferred":[
        "Ambada"
    ],
    "name:spa_x_preferred":[
        "Ambada"
    ],
    "name:vie_x_preferred":[
        "Ambada"
    ],
    "name:zho_x_preferred":[
        "\u963f\u59c6\u5df4\u8fbe"
    ],
    "wof:name":"Ambada",
    "wof:placetype":"locality"
},
  "geometry": {"coordinates":[75.34940999999998,21.25738],"type":"Point"}
}