{
  "type": "Feature",
  "properties": {
    "gn:admin1_code":"16",
    "gn:admin2_code":"499.0",
    "gn:asciiname":"Ambada",
    "gn:country_code":"IN",
    "gn:dem":207,
    "gn:feature_class":"P",
    "gn:feature_code":"PPL",
    "gn:name":"\u0100mb\u0101da",
    "gn:population":0,
    "gn:timezone":"Asia/Kolkata",
    "iso:country":"IN",
    "wof:name":"Ambada",
    "wof:placetype":"locality"
},
  "geometry": {"coordinates":[75.34940999999998,21.25738],"type":"Point"}
}