{
  "type": "Feature",
  "properties": {
    "gn:admin1_code":"13.0",
    "gn:admin2_code":"590.0",
    "gn:asciiname":"Puthusseri",
    "gn:country_code":"IN",
    "gn:dem":776,
    "gn:feature_class":"P",
    "gn:feature_code":"PPL",
    "gn:name":"Puthusseri",
    "gn:population":0,
    "gn:timezone":"Asia/Kolkata",
    "iso:country":"IN",
    "wof:name":"Puthusseri",
    "wof:placetype":"locality"
},
  "geometry": {"coordinates":[76.18615,11.59514],"type":"Point"}
}