{
  "type": "Feature",
  "properties": {
    "iso:country":"IN",
    "ks:ks_name":"A Jira",
    "ks:ks_pop":122,
    "ks:ks_type":"HABITATION",
    "name:eng_x_preferred":[
        "A Jira"
    ],
    "wof:name":"A Jira",
    "wof:placetype":"locality",
    "wof:population":122
},
  "geometry": {"coordinates":[82.789089,18.406714],"type":"Point"}
}