{
  "type": "Feature",
  "properties": {
    "iso:country":"IN",
    "ks:ks_name":"Phalati",
    "ks:ks_pop":339,
    "ks:ks_type":"VILLAGE",
    "name:eng_x_preferred":[
        "Phalati"
    ],
    "wof:name":"Phalati",
    "wof:placetype":"locality",
    "wof:population":339
},
  "geometry": {"coordinates":[78.99408699999999,30.37429],"type":"Point"}
}