{
  "type": "Feature",
  "properties": {
    "iso:country":"IN",
    "ks:ks_name":"Lakhuria",
    "ks:ks_pop":3214,
    "ks:ks_type":"VILLAGE",
    "name:eng_x_preferred":[
        "Lakhuria"
    ],
    "wof:name":"Lakhuria",
    "wof:placetype":"locality",
    "wof:population":3214
},
  "geometry": {"coordinates":[87.82347300000001,23.55981],"type":"Point"}
}