{
  "type": "Feature",
  "properties": {
    "gn:admin1_code":"10.0",
    "gn:admin2_code":"069",
    "gn:asciiname":"Huripur",
    "gn:country_code":"IN",
    "gn:dem":337,
    "gn:feature_class":"P",
    "gn:feature_code":"PPL",
    "gn:name":"Hur\u012bpur",
    "gn:population":0,
    "gn:timezone":"Asia/Kolkata",
    "iso:country":"IN",
    "name:ara_x_preferred":[
        "\u0647\u0648\u0631\u064a \u0628\u0648\u0631"
    ],
    "name:ben_bn_x_preferred":[
        "\u09b9\u09b0\u09bf\u09aa\u09c1\u09b0"
    ],
    "name:ben_in_x_preferred":[
        "\u09b9\u09b0\u09bf\u09aa\u09c1\u09b0"
    ],
    "name:guj_x_preferred":[
        "\u0ab9\u0ac1\u0ab0\u0abf\u0aaa\u0ac1\u0ab0"
    ],
    "name:hin_x_preferred":[
        "\u0939\u0941\u0930\u0940\u092a\u0941\u0930"
    ],
    "name:kan_x_preferred":[
        "\u0cb9\u0cc1\u0cb0\u0cbf\u0caa\u0cc1\u0cb0"
    ],
    "name:mal_x_preferred":[
        "\u0d39\u0d42\u0d30\u0d3f\u0d2a\u0d42\u0d7c"
    ],
    "name:mar_x_preferred":[
        "\u0939\u0941\u0930\u0940\u092a\u0942\u0930"
    ],
    "name:pan_x_preferred":[
        "\u0a39\u0a41\u0a30\u0a40\u0a2a\u0a41\u0a30"
    ],
    "name:tam_x_preferred":[
        "\u0bb9\u0bb0\u0bbf\u0baa\u0bcd\u0baa\u0bc2\u0bb0\u0bcd"
    ],
    "name:tel_x_preferred":[
        "\u0c39\u0c41\u0c30\u0c3f\u0c2a\u0c42\u0c30\u0c4d"
    ],
    "name:und_x_variant":[
        "Hur\u012bpur",
        "Har\u012bpur"
    ],
    "name:urd_x_preferred":[
        "\u06c1\u0648\u0631\u06cc \u067e\u0648\u0631"
    ],
    "wof:name":"Huripur",
    "wof:placetype":"neighbourhood"
},
  "geometry": {"coordinates":[76.86024,30.68879],"type":"Point"}
}