{
  "type": "Feature",
  "properties": {
    "gn:admin1_code":"10.0",
    "gn:admin2_code":"069",
    "gn:asciiname":"Huripur",
    "gn:country_code":"IN",
    "gn:dem":337,
    "gn:feature_class":"P",
    "gn:feature_code":"PPL",
    "gn:name":"Hur\u012bpur",
    "gn:population":0,
    "gn:timezone":"Asia/Kolkata",
    "iso:country":"IN",
    "name:und_x_variant":[
        "Hur\u012bpur",
        "Har\u012bpur"
    ],
    "wof:name":"Huripur",
    "wof:placetype":"neighbourhood"
},
  "geometry": {"coordinates":[76.86024,30.68879],"type":"Point"}
}