{
  "type": "Feature",
  "properties": {
    "gn:admin1_code":"16.0",
    "gn:admin2_code":"499.0",
    "gn:asciiname":"Khadakdevla Khurd",
    "gn:country_code":"IN",
    "gn:dem":277,
    "gn:feature_class":"P",
    "gn:feature_code":"PPL",
    "gn:name":"Khadakdevla Khurd",
    "gn:population":0,
    "gn:timezone":"Asia/Kolkata",
    "iso:country":"IN",
    "ks:ks_name":"Khadakdevla Khurd",
    "ks:ks_pop":1632,
    "ks:ks_type":"VILLAGE",
    "ks:ks_uagg_main":0,
    "name:eng_x_preferred":[
        "Khadakdevla Khurd"
    ],
    "wof:name":"Khadakdevla Khurd",
    "wof:placetype":"neighbourhood",
    "wof:population":1632
},
  "geometry": {"coordinates":[75.35752100000001,20.605908],"type":"Point"}
}