{
  "type": "Feature",
  "properties": {
    "gn:admin1_code":"2.0",
    "gn:admin2_code":"554.0",
    "gn:asciiname":"Geddakindipalle",
    "gn:country_code":"IN",
    "gn:dem":281,
    "gn:feature_class":"P",
    "gn:feature_code":"PPL",
    "gn:name":"Geddakindipalle",
    "gn:population":0,
    "gn:timezone":"Asia/Kolkata",
    "iso:country":"IN",
    "wof:name":"Geddakindipalle",
    "wof:placetype":"neighbourhood"
},
  "geometry": {"coordinates":[79.28498999999999,13.49027],"type":"Point"}
}