{
  "type": "Feature",
  "properties": {
    "gn:admin1_code":"10.0",
    "gn:admin2_code":"80.0",
    "gn:asciiname":"Taranagar",
    "gn:country_code":"IN",
    "gn:dem":220,
    "gn:feature_class":"P",
    "gn:feature_code":"PPL",
    "gn:name":"T\u0101r\u0101nagar",
    "gn:population":0,
    "gn:timezone":"Asia/Kolkata",
    "iso:country":"IN",
    "wof:name":"Taranagar",
    "wof:placetype":"locality"
},
  "geometry": {"coordinates":[75.80750999999999,29.39088],"type":"Point"}
}