{
  "type": "Feature",
  "properties": {
    "gn:admin1_code":"10.0",
    "gn:admin2_code":"86.0",
    "gn:asciiname":"Bhunkarka",
    "gn:country_code":"IN",
    "gn:dem":239,
    "gn:feature_class":"P",
    "gn:feature_code":"PPL",
    "gn:name":"Bhunkarka",
    "gn:population":0,
    "gn:timezone":"Asia/Kolkata",
    "iso:country":"IN",
    "wof:name":"Bhunkarka",
    "wof:placetype":"locality"
},
  "geometry": {"coordinates":[76.78994,28.27385],"type":"Point"}
}