{
  "type": "Feature",
  "properties": {
    "iso:country":"IN",
    "ks:ks_name":"Holag Sikhi Para",
    "ks:ks_pop":297,
    "ks:ks_type":"HABITATION",
    "ks:ks_uagg_main":0,
    "name:eng_x_preferred":[
        "Holag Sikhi Para"
    ],
    "wof:name":"Holag Sikhi Para",
    "wof:placetype":"neighbourhood",
    "wof:population":297
},
  "geometry": {"coordinates":[91.48231,23.935765],"type":"Point"}
}