{
  "type": "Feature",
  "properties": {
    "iso:country":"IN",
    "ks:ks_name":"J H C Golobettu",
    "ks:ks_pop":316,
    "ks:ks_type":"HABITATION",
    "name:eng_x_preferred":[
        "J H C Golobettu"
    ],
    "wof:name":"J H C Golobettu",
    "wof:placetype":"locality",
    "wof:population":316
},
  "geometry": {"coordinates":[74.703851,13.465366],"type":"Point"}
}