{
  "type": "Feature",
  "properties": {
    "iso:country":"IN",
    "ks:ks_name":"Shisha Tola",
    "ks:ks_pop":625,
    "ks:ks_type":"HABITATION",
    "name:eng_x_preferred":[
        "Shisha Tola"
    ],
    "wof:name":"Shisha Tola",
    "wof:placetype":"locality",
    "wof:population":625
},
  "geometry": {"coordinates":[87.26261100000001,25.748001],"type":"Point"}
}