{
  "type": "Feature",
  "properties": {
    "iso:country":"IN",
    "ks:ks_name":"Nattayatukonam",
    "ks:ks_pop":698,
    "ks:ks_type":"HABITATION",
    "name:eng_x_preferred":[
        "Nattayatukonam"
    ],
    "wof:name":"Nattayatukonam",
    "wof:placetype":"locality",
    "wof:population":698
},
  "geometry": {"coordinates":[77.10665299999999,8.441106],"type":"Point"}
}