{
  "type": "Feature",
  "properties": {
    "iso:country":"IN",
    "ks:ks_name":"Adiwasiwadi",
    "ks:ks_pop":50,
    "ks:ks_type":"HABITATION",
    "name:eng_x_preferred":[
        "Adiwasiwadi"
    ],
    "wof:name":"Adiwasiwadi",
    "wof:placetype":"locality",
    "wof:population":50
},
  "geometry": {"coordinates":[73.41448,18.093995],"type":"Point"}
}