{
  "type": "Feature",
  "properties": {
    "iso:country":"IN",
    "ks:ks_alt_nam":"Kalavara muttoli",
    "ks:ks_name":"Kalavara Muttoli",
    "ks:ks_pop":482,
    "ks:ks_type":"HABITATION",
    "name:eng_x_preferred":[
        "Kalavara Muttoli"
    ],
    "wof:name":"Kalavara Muttoli",
    "wof:placetype":"locality",
    "wof:population":482
},
  "geometry": {"coordinates":[76.018451,11.33016],"type":"Point"}
}