{
  "type": "Feature",
  "properties": {
    "iso:country":"IN",
    "ks:ks_name":"Railghati",
    "ks:ks_pop":77,
    "ks:ks_type":"HABITATION",
    "name:eng_x_preferred":[
        "Railghati"
    ],
    "wof:name":"Railghati",
    "wof:placetype":"locality",
    "wof:population":77
},
  "geometry": {"coordinates":[83.624568,19.636199],"type":"Point"}
}