{
  "type": "Feature",
  "properties": {
    "iso:country":"IN",
    "ks:ks_name":"Dakkhiin Niz Saldah",
    "ks:ks_pop":786,
    "ks:ks_type":"HABITATION",
    "ks:ks_uagg_main":0,
    "name:eng_x_preferred":[
        "Dakkhiin Niz Saldah"
    ],
    "wof:name":"Dakkhiin Niz Saldah",
    "wof:placetype":"neighbourhood",
    "wof:population":786
},
  "geometry": {"coordinates":[91.170846,26.446559],"type":"Point"}
}