{
  "type": "Feature",
  "properties": {
    "iso:country":"IN",
    "ks:ks_name":"Machan",
    "ks:ks_pop":0,
    "ks:ks_type":"VILLAGE",
    "name:eng_x_preferred":[
        "Machan"
    ],
    "wof:name":"Machan",
    "wof:placetype":"locality",
    "wof:population":0
},
  "geometry": {"coordinates":[85.40233499999999,24.584372],"type":"Point"}
}