{
  "type": "Feature",
  "properties": {
    "iso:country":"IN",
    "ks:ks_alt_nam":"latu",
    "ks:ks_name":"Latu",
    "ks:ks_pop":590,
    "ks:ks_type":"HABITATION",
    "name:eng_x_preferred":[
        "Latu"
    ],
    "wof:name":"Latu",
    "wof:placetype":"locality",
    "wof:population":590
},
  "geometry": {"coordinates":[84.34621799999999,22.780957],"type":"Point"}
}