{
  "type": "Feature",
  "properties": {
    "gn:admin1_code":"2.0",
    "gn:admin2_code":"542.0",
    "gn:asciiname":"Badivanipeta",
    "gn:country_code":"IN",
    "gn:dem":16,
    "gn:feature_class":"P",
    "gn:feature_code":"PPL",
    "gn:name":"Badiv\u0101nipeta",
    "gn:population":0,
    "gn:timezone":"Asia/Kolkata",
    "iso:country":"IN",
    "wof:name":"Badivanipeta",
    "wof:placetype":"locality"
},
  "geometry": {"coordinates":[83.83889000000001,18.16895],"type":"Point"}
}