{
  "type": "Feature",
  "properties": {
    "iso:country":"IN",
    "ks:ks_name":"Koam",
    "ks:ks_pop":616,
    "ks:ks_type":"VILLAGE",
    "name:eng_x_preferred":[
        "Koam"
    ],
    "wof:name":"Koam",
    "wof:placetype":"locality",
    "wof:population":616
},
  "geometry": {"coordinates":[87.30305,24.464063],"type":"Point"}
}