{
  "type": "Feature",
  "properties": {
    "iso:country":"IN",
    "ks:ks_name":"Chak Jhoojhanda",
    "ks:ks_pop":46,
    "ks:ks_type":"HABITATION",
    "name:eng_x_preferred":[
        "Chak Jhoojhanda"
    ],
    "wof:name":"Chak Jhoojhanda",
    "wof:placetype":"locality",
    "wof:population":46
},
  "geometry": {"coordinates":[73.751419,26.969213],"type":"Point"}
}