{
  "type": "Feature",
  "properties": {
    "iso:country":"IN",
    "ks:ks_name":"Pichhri",
    "ks:ks_pop":148,
    "ks:ks_type":"VILLAGE",
    "name:eng_x_preferred":[
        "Pichhri"
    ],
    "wof:name":"Pichhri",
    "wof:placetype":"locality",
    "wof:population":148
},
  "geometry": {"coordinates":[86.995542,24.304677],"type":"Point"}
}