{
  "type": "Feature",
  "properties": {
    "gn:admin1_code":"39.0",
    "gn:admin2_code":"64.0",
    "gn:asciiname":"Chulera Sim",
    "gn:country_code":"IN",
    "gn:dem":1113,
    "gn:feature_class":"P",
    "gn:feature_code":"PPL",
    "gn:name":"Chulera S\u012bm",
    "gn:population":0,
    "gn:timezone":"Asia/Kolkata",
    "iso:country":"IN",
    "wof:name":"Chulera Sim",
    "wof:placetype":"locality"
},
  "geometry": {"coordinates":[79.40926,29.93561],"type":"Point"}
}