{
  "type": "Feature",
  "properties": {
    "gn:admin1_code":"25.0",
    "gn:admin2_code":"633.0",
    "gn:asciiname":"Chinnayipallakkattupudur",
    "gn:country_code":"IN",
    "gn:dem":306,
    "gn:feature_class":"P",
    "gn:feature_code":"PPL",
    "gn:name":"Chinn\u0101yipallakk\u0101ttupud\u016br",
    "gn:population":0,
    "gn:timezone":"Asia/Kolkata",
    "iso:country":"IN",
    "wof:name":"Chinnayipallakkattupudur",
    "wof:placetype":"locality"
},
  "geometry": {"coordinates":[77.51824999999999,11.03089],"type":"Point"}
}