{
  "type": "Feature",
  "properties": {
    "gn:admin1_code":"12.0",
    "gn:admin2_code":"008",
    "gn:asciiname":"Sonyan Saidnar",
    "gn:country_code":"IN",
    "gn:dem":1625,
    "gn:feature_class":"P",
    "gn:feature_code":"PPL",
    "gn:name":"Sonyan Saidn\u0101r",
    "gn:population":0,
    "gn:timezone":"Asia/Kolkata",
    "iso:country":"IN",
    "wof:name":"Sonyan Saidnar",
    "wof:placetype":"locality"
},
  "geometry": {"coordinates":[74.31667,34.29861],"type":"Point"}
}