{
  "type": "Feature",
  "properties": {
    "iso:country":"IN",
    "ks:ks_name":"Chhutani Purwa",
    "ks:ks_pop":567,
    "ks:ks_type":"HABITATION",
    "ks:ks_uagg_main":0,
    "name:eng_x_preferred":[
        "Chhutani Purwa"
    ],
    "wof:name":"Chhutani Purwa",
    "wof:placetype":"neighbourhood",
    "wof:population":567
},
  "geometry": {"coordinates":[80.89582799999999,28.145233],"type":"Point"}
}