{
  "type": "Feature",
  "properties": {
    "iso:country":"IN",
    "ks:ks_name":"Gabharwadi",
    "ks:ks_pop":180,
    "ks:ks_type":"HABITATION",
    "name:eng_x_preferred":[
        "Gabharwadi"
    ],
    "wof:name":"Gabharwadi",
    "wof:placetype":"locality",
    "wof:population":180
},
  "geometry": {"coordinates":[73.635278,18.883056],"type":"Point"}
}