{
  "type": "Feature",
  "properties": {
    "iso:country":"IN",
    "ks:ks_alt_nam":"Rash\u012bdpur Garhi",
    "ks:ks_name":"Rashidpur Garhi",
    "ks:ks_type":"VILLAGE",
    "ks:ks_uagg_main":0,
    "name:eng_x_preferred":[
        "Rashidpur Garhi"
    ],
    "name:eng_x_variant":[
        "Rash\u012bdpur Garhi"
    ],
    "wof:name":"Rashidpur Garhi",
    "wof:placetype":"neighbourhood"
},
  "geometry": {"coordinates":[78.16127400000001,29.387827],"type":"Point"}
}