{
  "type": "Feature",
  "properties": {
    "iso:country":"IN",
    "ks:ks_name":"Manickkapangu",
    "ks:ks_pop":186,
    "ks:ks_type":"HABITATION",
    "name:eng_x_preferred":[
        "Manickkapangu"
    ],
    "wof:name":"Manickkapangu",
    "wof:placetype":"locality",
    "wof:population":186
},
  "geometry": {"coordinates":[79.79556100000001,10.704555],"type":"Point"}
}