{
  "type": "Feature",
  "properties": {
    "gn:admin1_code":"11.0",
    "gn:admin2_code":"33.0",
    "gn:asciiname":"Dokri",
    "gn:country_code":"IN",
    "gn:dem":2306,
    "gn:feature_class":"P",
    "gn:feature_code":"PPL",
    "gn:name":"Dokri",
    "gn:population":0,
    "gn:timezone":"Asia/Kolkata",
    "iso:country":"IN",
    "name:ceb_x_preferred":[
        "Dokri"
    ],
    "name:fas_x_preferred":[
        "\u062f\u06a9\u0631\u06cc"
    ],
    "name:fra_x_preferred":[
        "Dokri"
    ],
    "name:hin_x_preferred":[
        "\u0921\u094b\u0915\u0930\u0940"
    ],
    "name:pnb_x_preferred":[
        "\u0688\u0648\u06a9\u0631\u06cc"
    ],
    "name:snd_x_preferred":[
        "\u068f\u0648\u06aa\u0631\u064a"
    ],
    "name:urd_x_preferred":[
        "\u0688\u0648\u06a9\u0631\u06cc"
    ],
    "wof:name":"Dokri",
    "wof:placetype":"locality"
},
  "geometry": {"coordinates":[77.50429,31.27827000000001],"type":"Point"}
}