{
  "type": "Feature",
  "properties": {
    "iso:country":"IN",
    "ks:ks_name":"Sehuda(551)",
    "ks:ks_pop":516,
    "ks:ks_type":"HABITATION",
    "name:eng_x_preferred":[
        "Sehuda(551)"
    ],
    "wof:name":"Sehuda(551)",
    "wof:placetype":"locality",
    "wof:population":516
},
  "geometry": {"coordinates":[81.37976999999999,25.017596],"type":"Point"}
}