{
  "type": "Feature",
  "properties": {
    "iso:country":"IN",
    "ks:ks_name":"Saree Peepli",
    "ks:ks_pop":224,
    "ks:ks_type":"VILLAGE",
    "name:eng_x_preferred":[
        "Saree Peepli"
    ],
    "wof:name":"Saree Peepli",
    "wof:placetype":"locality",
    "wof:population":224
},
  "geometry": {"coordinates":[74.615436,24.2101],"type":"Point"}
}