{
  "type": "Feature",
  "properties": {
    "iso:country":"IN",
    "ks:ks_name":"Kombaithozhu",
    "ks:ks_pop":662,
    "ks:ks_type":"HABITATION",
    "name:eng_x_preferred":[
        "Kombaithozhu"
    ],
    "wof:name":"Kombaithozhu",
    "wof:placetype":"locality",
    "wof:population":662
},
  "geometry": {"coordinates":[77.447267,9.7182],"type":"Point"}
}