{
  "type": "Feature",
  "properties": {
    "iso:country":"IN",
    "ks:ks_name":"Manche",
    "ks:ks_pop":547,
    "ks:ks_type":"HABITATION",
    "name:eng_x_preferred":[
        "Manche"
    ],
    "wof:name":"Manche",
    "wof:placetype":"locality",
    "wof:population":547
},
  "geometry": {"coordinates":[73.556569,16.892656],"type":"Point"}
}