{
  "type": "Feature",
  "properties": {
    "gn:admin1_code":"23.0",
    "gn:admin2_code":"48.0",
    "gn:asciiname":"Khaktan",
    "gn:country_code":"IN",
    "gn:dem":252,
    "gn:feature_class":"P",
    "gn:feature_code":"PPL",
    "gn:name":"Kh\u0101kt\u0101n",
    "gn:population":0,
    "gn:timezone":"Asia/Kolkata",
    "iso:country":"IN",
    "wof:name":"Khaktan",
    "wof:placetype":"locality"
},
  "geometry": {"coordinates":[76.48172,30.23563],"type":"Point"}
}