{
  "type": "Feature",
  "properties": {
    "iso:country":"IN",
    "ks:ks_name":"Jahanpur",
    "ks:ks_pop":276,
    "ks:ks_type":"VILLAGE",
    "ks:ks_uagg_main":0,
    "name:eng_x_preferred":[
        "Jahanpur"
    ],
    "wof:name":"Jahanpur",
    "wof:placetype":"neighbourhood",
    "wof:population":276
},
  "geometry": {"coordinates":[77.535229,21.049177],"type":"Point"}
}