{
  "type": "Feature",
  "properties": {
    "iso:country":"IN",
    "qs:name":"Brindavan Extension",
    "qs:name_adm0":"India",
    "qs:name_adm1":"Karnataka",
    "qs:photos":36,
    "qs:photos_1k":7,
    "qs:photos_9k":1,
    "qs:photos_9r":2,
    "qs:photos_all":36,
    "qs:photos_sr":2,
    "qs:placetype":"Suburb",
    "qs:pop_sr":"0",
    "wof:name":"Brindavan Extension",
    "wof:placetype":"neighbourhood"
},
  "geometry": {"coordinates":[76.64174,12.344068],"type":"Point"}
}