{
  "type": "Feature",
  "properties": {
    "iso:country":"IN",
    "name:ara_x_preferred":[
        "\u0627\u0645\u062a\u062f\u0627\u062f \u0628\u0631\u064a\u0646\u062f\u0627\u0641\u0627\u0646"
    ],
    "name:ben_bn_x_preferred":[
        "\u09ac\u09c3\u09a8\u09cd\u09a6\u09be\u09ac\u09a8 \u098f\u0995\u09cd\u09b8\u099f\u09c7\u09a8\u09b6\u09a8"
    ],
    "name:ben_in_x_preferred":[
        "\u09ac\u09c3\u09a8\u09cd\u09a6\u09be\u09ac\u09a8 \u098f\u0995\u09cd\u09b8\u099f\u09c7\u09a8\u09b6\u09a8"
    ],
    "name:guj_x_preferred":[
        "\u0aac\u0acd\u0ab0\u0abf\u0aa8\u0acd\u0aa6\u0abe\u0ab5\u0aa8 \u0a8f\u0a95\u0acd\u0ab8\u0a9f\u0ac7\u0aa8\u0acd\u0ab6\u0aa8"
    ],
    "name:hin_x_preferred":[
        "\u092c\u094d\u0930\u093f\u0902\u0926\u093e\u0935\u0928 \u090f\u0915\u094d\u0938\u091f\u0947\u0902\u0936\u0928"
    ],
    "name:kan_x_preferred":[
        "\u0cac\u0ccd\u0cb0\u0cbf\u0c82\u0ca6\u0cbe\u0cb5\u0ca8\u0ccd"
    ],
    "name:mal_x_preferred":[
        "\u0d35\u0d43\u0d28\u0d4d\u0d26\u0d3e\u0d35\u0d7b \u0d0e\u0d15\u0d4d\u0d38\u0d4d\u0d31\u0d4d\u0d31\u0d46\u0d7b\u0d37\u0d7a"
    ],
    "name:mar_x_preferred":[
        "\u0935\u0943\u0902\u0926\u093e\u0935\u0928 \u090f\u0915\u094d\u0938\u091f\u0947\u0902\u0936\u0928"
    ],
    "name:pan_x_preferred":[
        "\u0a2c\u0a30\u0a3f\u0a70\u0a26\u0a3e\u0a35\u0a28 \u0a10\u0a15\u0a38\u0a1f\u0a48\u0a02\u0a36\u0a28"
    ],
    "name:tam_x_preferred":[
        "\u0baa\u0bbf\u0bb0\u0bc1\u0ba8\u0bcd\u0ba4\u0bbe\u0bb5\u0ba9\u0bcd \u0bb5\u0bbf\u0bb0\u0bbf\u0bb5\u0bbe\u0b95\u0bcd\u0b95\u0bae\u0bcd"
    ],
    "name:tel_x_preferred":[
        "\u0c2c\u0c43\u0c02\u0c26\u0c3e\u0c35\u0c28\u0c4d \u0c0e\u0c15\u0c4d\u0c38\u0c4d"
    ],
    "name:urd_x_preferred":[
        "\u0628\u0631\u0646\u062f\u0627\u0648\u0646 \u0627\u06cc\u06a9\u0633\u0679\u06cc\u0646\u0634\u0646"
    ],
    "qs:name":"Brindavan Extension",
    "qs:name_adm0":"India",
    "qs:name_adm1":"Karnataka",
    "qs:photos":36,
    "qs:photos_1k":7,
    "qs:photos_9k":1,
    "qs:photos_9r":2,
    "qs:photos_all":36,
    "qs:photos_sr":2,
    "qs:placetype":"Suburb",
    "qs:pop_sr":"0",
    "wof:name":"Brindavan Extension",
    "wof:placetype":"neighbourhood"
},
  "geometry": {"coordinates":[76.64174,12.344068],"type":"Point"}
}