{
  "type": "Feature",
  "properties": {
    "gn:admin1_code":"34.0",
    "gn:admin2_code":"227.0",
    "gn:asciiname":"Gangasarai",
    "gn:country_code":"IN",
    "gn:dem":48,
    "gn:feature_class":"P",
    "gn:feature_code":"PPL",
    "gn:name":"Gang\u0101sarai",
    "gn:population":0,
    "gn:timezone":"Asia/Kolkata",
    "iso:country":"IN",
    "ks:ks_alt_nam":"Gang\u0101sarai",
    "ks:ks_name":"Gangasarai",
    "ks:ks_pop":1302,
    "ks:ks_type":"VILLAGE",
    "ks:ks_uagg_main":0,
    "name:eng_x_preferred":[
        "Gangasarai"
    ],
    "name:eng_x_variant":[
        "Gang\u0101sarai"
    ],
    "wof:name":"Gangasarai",
    "wof:placetype":"neighbourhood",
    "wof:population":1302
},
  "geometry": {"coordinates":[86.032839,25.251755],"type":"Point"}
}