{
  "type": "Feature",
  "properties": {
    "gn:admin1_code":"36.0",
    "gn:admin2_code":"180.0",
    "gn:asciiname":"Barhanpur",
    "gn:country_code":"IN",
    "gn:dem":110,
    "gn:feature_class":"P",
    "gn:feature_code":"PPL",
    "gn:name":"Barhanpur",
    "gn:population":0,
    "gn:timezone":"Asia/Kolkata",
    "iso:country":"IN",
    "wof:name":"Barhanpur",
    "wof:placetype":"locality"
},
  "geometry": {"coordinates":[81.55916999999999,27.17753],"type":"Point"}
}