{
  "type": "Feature",
  "properties": {
    "gn:country":"IN",
    "gn:fcode":"PPL",
    "gn:population":6485,
    "iso:country":"IN",
    "name:ben_x_preferred":[
        "\u099b\u09c1\u0987\u0996\u09be\u09a6\u09be\u09a8"
    ],
    "name:bpy_x_preferred":[
        "\u099b\u09c1\u0987\u0996\u09be\u09a6\u09be\u09a8"
    ],
    "name:ceb_x_preferred":[
        "Chhu\u012bkhad\u0101n"
    ],
    "name:deu_x_preferred":[
        "Chhuikhadan"
    ],
    "name:eng_x_preferred":[
        "Chhuikhadan"
    ],
    "name:fra_x_preferred":[
        "Chhuikhadan"
    ],
    "name:guj_x_preferred":[
        "\u0a9b\u0ac1\u0a87\u0a96\u0abe\u0aa6\u0abe\u0aa8"
    ],
    "name:hin_x_preferred":[
        "\u091b\u0941\u0908\u0916\u0926\u093e\u0928"
    ],
    "name:ita_x_preferred":[
        "Chhuikhadan"
    ],
    "name:jpn_x_preferred":[
        "\u30c1\u30e5\u30a4\u30ab\u30c0\u30f3"
    ],
    "name:kan_x_preferred":[
        "\u0c9b\u0ccd\u0cb9\u0cc1\u0caf\u0cbf\u0c96\u0cbe\u0ca6\u0cbe\u0ca8\u0ccd"
    ],
    "name:kor_x_preferred":[
        "\ucde8\uce74\ub2e8"
    ],
    "name:msa_x_preferred":[
        "Chhuikhadan"
    ],
    "name:nan_x_preferred":[
        "Chhuikhadan"
    ],
    "name:new_x_preferred":[
        "\u091b\u0941\u0907\u0916\u0926\u0928"
    ],
    "name:nld_x_preferred":[
        "Chhuikhadan"
    ],
    "name:por_x_preferred":[
        "Chhuikhadan"
    ],
    "name:rus_x_preferred":[
        "\u0427\u0445\u0443\u0438\u043a\u0445\u0430\u0434\u0430\u043d"
    ],
    "name:spa_x_preferred":[
        "Chhuikhadan"
    ],
    "name:swe_x_preferred":[
        "Chhu\u012bkhad\u0101n"
    ],
    "name:tam_x_preferred":[
        "\u0b9a\u0bb9\u0bc1\u0baf\u0bcd\u0b95\u0bcd\u0bb9\u0bbe\u0b9f\u0ba9\u0bcd"
    ],
    "name:tel_x_preferred":[
        "\u0c1a\u0c41\u0c16\u0c3e\u0c26\u0c28\u0c4d"
    ],
    "name:tgl_x_preferred":[
        "Chhuikhadan"
    ],
    "name:urd_x_preferred":[
        "\u0686\u0648\u0626\u06cc \u06a9\u06be\u062f\u0627\u0646"
    ],
    "name:vie_x_preferred":[
        "Chhuikhadan"
    ],
    "name:zho_x_preferred":[
        "\u5947\u80e1\u4f0a\u5361\u4e39"
    ],
    "qs:name":"Chhuikhadan",
    "qs:name_adm0":"India",
    "qs:name_adm1":"Chhattisgarh",
    "qs:photos_9r":0,
    "qs:photos_sr":0,
    "qs:placetype":"Town",
    "qs:pop_sr":"5",
    "wd:wordcount":218,
    "wof:name":"Chhuikhadan",
    "wof:placetype":"locality",
    "wof:population":6485
},
  "geometry": {"coordinates":[80.99748,21.52249],"type":"Point"}
}