{
  "type": "Feature",
  "properties": {
    "iso:country":"IN",
    "ks:ks_name":"Katauni",
    "ks:ks_pop":535,
    "ks:ks_type":"HABITATION",
    "name:eng_x_preferred":[
        "Katauni"
    ],
    "wof:name":"Katauni",
    "wof:placetype":"locality",
    "wof:population":535
},
  "geometry": {"coordinates":[91.987022,24.275014],"type":"Point"}
}