{
  "type": "Feature",
  "properties": {
    "gn:admin1_code":"37",
    "gn:admin2_code":"408.0",
    "gn:asciiname":"Korramtola",
    "gn:country_code":"IN",
    "gn:dem":383,
    "gn:feature_class":"P",
    "gn:feature_code":"PPL",
    "gn:name":"Korr\u0101mtola",
    "gn:population":0,
    "gn:timezone":"Asia/Kolkata",
    "iso:country":"IN",
    "wof:name":"Korramtola",
    "wof:placetype":"locality"
},
  "geometry": {"coordinates":[80.80625000000001,20.5488],"type":"Point"}
}