{
  "type": "Feature",
  "properties": {
    "iso:country":"IN",
    "ks:ks_alt_nam":"KHOKH NAHA",
    "ks:ks_name":"Khokh Naha",
    "ks:ks_pop":1800,
    "ks:ks_type":"HABITATION",
    "name:eng_x_preferred":[
        "Khokh Naha"
    ],
    "wof:name":"Khokh Naha",
    "wof:placetype":"locality",
    "wof:population":1800
},
  "geometry": {"coordinates":[86.555567,26.200389],"type":"Point"}
}