{
  "type": "Feature",
  "properties": {
    "gn:admin1_code":"19.0",
    "gn:admin2_code":"579",
    "gn:asciiname":"Andola",
    "gn:country_code":"IN",
    "gn:dem":452,
    "gn:feature_class":"P",
    "gn:feature_code":"PPL",
    "gn:name":"Andola",
    "gn:population":0,
    "gn:timezone":"Asia/Kolkata",
    "iso:country":"IN",
    "wof:name":"Andola",
    "wof:placetype":"locality"
},
  "geometry": {"coordinates":[76.83745999999999,16.95203],"type":"Point"}
}