{
  "type": "Feature",
  "properties": {
    "iso:country":"IN",
    "ks:ks_name":"Mundkosiya",
    "ks:ks_pop":467,
    "ks:ks_type":"VILLAGE",
    "name:eng_x_preferred":[
        "Mundkosiya"
    ],
    "wof:name":"Mundkosiya",
    "wof:placetype":"locality",
    "wof:population":467
},
  "geometry": {"coordinates":[73.36792800000001,24.302039],"type":"Point"}
}