{
  "type": "Feature",
  "properties": {
    "iso:country":"IN",
    "ks:ks_name":"Bhanger",
    "ks:ks_pop":1666,
    "ks:ks_type":"HABITATION",
    "name:eng_x_preferred":[
        "Bhanger"
    ],
    "wof:name":"Bhanger",
    "wof:placetype":"locality",
    "wof:population":1666
},
  "geometry": {"coordinates":[74.737015,30.814278],"type":"Point"}
}