{
  "type": "Feature",
  "properties": {
    "iso:country":"IN",
    "ks:ks_alt_nam":"Mes\u0101l",
    "ks:ks_name":"Mesal",
    "ks:ks_pop":686,
    "ks:ks_type":"VILLAGE",
    "ks:ks_uagg_main":0,
    "name:eng_x_preferred":[
        "Mesal"
    ],
    "name:eng_x_variant":[
        "Mes\u0101l"
    ],
    "wof:name":"Mesal",
    "wof:placetype":"neighbourhood",
    "wof:population":686
},
  "geometry": {"coordinates":[85.136135,23.442498],"type":"Point"}
}