{
  "type": "Feature",
  "properties": {
    "iso:country":"IN",
    "ks:ks_name":"Kudiyangallu",
    "ks:ks_pop":249,
    "ks:ks_type":"HABITATION",
    "name:eng_x_preferred":[
        "Kudiyangallu"
    ],
    "wof:name":"Kudiyangallu",
    "wof:placetype":"locality",
    "wof:population":249
},
  "geometry": {"coordinates":[75.416612,12.445461],"type":"Point"}
}