{
  "type": "Feature",
  "properties": {
    "iso:country":"IN",
    "ks:ks_name":"Tisso Gaon Udeng",
    "ks:ks_pop":248,
    "ks:ks_type":"HABITATION",
    "name:eng_x_preferred":[
        "Tisso Gaon Udeng"
    ],
    "wof:name":"Tisso Gaon Udeng",
    "wof:placetype":"locality",
    "wof:population":248
},
  "geometry": {"coordinates":[93.779674,26.207731],"type":"Point"}
}