{
  "type": "Feature",
  "properties": {
    "gn:admin1_code":"10",
    "gn:admin2_code":"84.0",
    "gn:asciiname":"Jawaharnagar",
    "gn:country_code":"IN",
    "gn:dem":281,
    "gn:feature_class":"P",
    "gn:feature_code":"PPL",
    "gn:name":"Jaw\u0101harnagar",
    "gn:population":0,
    "gn:timezone":"Asia/Kolkata",
    "iso:country":"IN",
    "wof:name":"Jawaharnagar",
    "wof:placetype":"locality"
},
  "geometry": {"coordinates":[75.9325,28.3911],"type":"Point"}
}