{
  "type": "Feature",
  "properties": {
    "iso:country":"IN",
    "ks:ks_name":"Arjjunjora",
    "ks:ks_pop":1035,
    "ks:ks_type":"VILLAGE",
    "name:eng_x_preferred":[
        "Arjjunjora"
    ],
    "wof:name":"Arjjunjora",
    "wof:placetype":"locality",
    "wof:population":1035
},
  "geometry": {"coordinates":[86.498294,23.307162],"type":"Point"}
}