{
  "type": "Feature",
  "properties": {
    "gn:admin1_code":"34.0",
    "gn:admin2_code":"237.0",
    "gn:asciiname":"Lodipur",
    "gn:country_code":"IN",
    "gn:dem":117,
    "gn:feature_class":"P",
    "gn:feature_code":"PPL",
    "gn:name":"Lodipur",
    "gn:population":0,
    "gn:timezone":"Asia/Kolkata",
    "iso:country":"IN",
    "ks:ks_name":"Lodipur",
    "ks:ks_pop":1262,
    "ks:ks_type":"VILLAGE",
    "ks:ks_uagg_main":0,
    "name:eng_x_preferred":[
        "Lodipur"
    ],
    "name:hif_x_preferred":[
        "Lodipur"
    ],
    "wof:name":"Lodipur",
    "wof:placetype":"neighbourhood",
    "wof:population":1262
},
  "geometry": {"coordinates":[85.553495,24.763514],"type":"Point"}
}