{
  "type": "Feature",
  "properties": {
    "iso:country":"IN",
    "ks:ks_name":"Nayapakkam",
    "ks:ks_pop":262,
    "ks:ks_type":"VILLAGE",
    "ks:ks_uagg_main":0,
    "name:eng_x_preferred":[
        "Nayapakkam"
    ],
    "wof:name":"Nayapakkam",
    "wof:placetype":"neighbourhood",
    "wof:population":262
},
  "geometry": {"coordinates":[79.85391199999999,13.236831],"type":"Point"}
}