{
  "type": "Feature",
  "properties": {
    "gn:admin1_code":"36.0",
    "gn:admin2_code":"173.0",
    "gn:asciiname":"Pure Gosain",
    "gn:country_code":"IN",
    "gn:dem":101,
    "gn:feature_class":"P",
    "gn:feature_code":"PPL",
    "gn:name":"Pure Gos\u0101\u012bn",
    "gn:population":0,
    "gn:timezone":"Asia/Kolkata",
    "iso:country":"IN",
    "ks:ks_name":"Pure Gosai",
    "ks:ks_pop":443,
    "ks:ks_type":"VILLAGE",
    "ks:ks_uagg_main":0,
    "name:eng_x_preferred":[
        "Pure Gosai"
    ],
    "wof:name":"Pure Gosai",
    "wof:placetype":"neighbourhood",
    "wof:population":443
},
  "geometry": {"coordinates":[81.937156,25.84146],"type":"Point"}
}