{
  "type": "Feature",
  "properties": {
    "iso:country":"IN",
    "ks:ks_alt_nam":"KHUPILONG PARA",
    "ks:ks_name":"Khupilong Para",
    "ks:ks_pop":743,
    "ks:ks_type":"HABITATION",
    "ks:ks_uagg_main":0,
    "name:eng_x_preferred":[
        "Khupilong Para"
    ],
    "wof:name":"Khupilong Para",
    "wof:placetype":"neighbourhood",
    "wof:population":743
},
  "geometry": {"coordinates":[91.50014,23.72079],"type":"Point"}
}