{
  "type": "Feature",
  "properties": {
    "iso:country":"IN",
    "ks:ks_name":"Baurkela",
    "ks:ks_pop":98,
    "ks:ks_type":"VILLAGE",
    "name:eng_x_preferred":[
        "Baurkela"
    ],
    "wof:name":"Baurkela",
    "wof:placetype":"locality",
    "wof:population":98
},
  "geometry": {"coordinates":[85.084357,21.866333],"type":"Point"}
}