{
  "type": "Feature",
  "properties": {
    "gn:admin1_code":"34.0",
    "gn:admin2_code":"217.0",
    "gn:asciiname":"Bhoj Chhapar",
    "gn:country_code":"IN",
    "gn:dem":77,
    "gn:feature_class":"P",
    "gn:feature_code":"PPL",
    "gn:name":"Bhoj Chh\u0101par",
    "gn:population":0,
    "gn:timezone":"Asia/Kolkata",
    "iso:country":"IN",
    "wof:name":"Bhoj Chhapar",
    "wof:placetype":"locality"
},
  "geometry": {"coordinates":[84.36136999999999,26.59877],"type":"Point"}
}