{
  "type": "Feature",
  "properties": {
    "iso:country":"IN",
    "ks:ks_name":"Kittayyatota",
    "ks:ks_pop":107,
    "ks:ks_type":"VILLAGE",
    "name:eng_x_preferred":[
        "Kittayyatota"
    ],
    "wof:name":"Kittayyatota",
    "wof:placetype":"locality",
    "wof:population":107
},
  "geometry": {"coordinates":[83.15123199999999,18.201234],"type":"Point"}
}