{
  "type": "Feature",
  "properties": {
    "gn:admin1_code":"36",
    "gn:admin2_code":"135.0",
    "gn:asciiname":"Nehtaura",
    "gn:country_code":"IN",
    "gn:dem":202,
    "gn:feature_class":"P",
    "gn:feature_code":"PPL",
    "gn:name":"Nehtaura",
    "gn:population":0,
    "gn:timezone":"Asia/Kolkata",
    "iso:country":"IN",
    "ks:ks_name":"Nahtaura",
    "ks:ks_pop":1167,
    "ks:ks_type":"VILLAGE",
    "ks:ks_uagg_main":0,
    "name:eng_x_preferred":[
        "Nahtaura"
    ],
    "wof:name":"Nahtaura",
    "wof:placetype":"neighbourhood",
    "wof:population":1167
},
  "geometry": {"coordinates":[78.785557,28.979026],"type":"Point"}
}