{
  "type": "Feature",
  "properties": {
    "iso:country":"IN",
    "ks:ks_name":"Chaudhari Tola",
    "ks:ks_pop":246,
    "ks:ks_type":"HABITATION",
    "name:eng_x_preferred":[
        "Chaudhari Tola"
    ],
    "wof:name":"Chaudhari Tola",
    "wof:placetype":"locality",
    "wof:population":246
},
  "geometry": {"coordinates":[85.52011,25.682982],"type":"Point"}
}