{
  "type": "Feature",
  "properties": {
    "iso:country":"IN",
    "ks:ks_name":"Mawai Pahara",
    "ks:ks_pop":183,
    "ks:ks_type":"VILLAGE",
    "name:eng_x_preferred":[
        "Mawai Pahara"
    ],
    "wof:name":"Mawai Pahara",
    "wof:placetype":"locality",
    "wof:population":183
},
  "geometry": {"coordinates":[80.75868,25.164635],"type":"Point"}
}