{
  "type": "Feature",
  "properties": {
    "iso:country":"IN",
    "ks:ks_name":"Sheegodu",
    "ks:ks_pop":50,
    "ks:ks_type":"VILLAGE",
    "name:eng_x_preferred":[
        "Sheegodu"
    ],
    "wof:name":"Sheegodu",
    "wof:placetype":"locality",
    "wof:population":50
},
  "geometry": {"coordinates":[76.026118,12.600486],"type":"Point"}
}