{
  "type": "Feature",
  "properties": {
    "gn:admin1_code":"24",
    "gn:admin2_code":"115.0",
    "gn:asciiname":"Sundra",
    "gn:country_code":"IN",
    "gn:dem":76,
    "gn:feature_class":"P",
    "gn:feature_code":"PPL",
    "gn:name":"Sundra",
    "gn:population":0,
    "gn:timezone":"Asia/Kolkata",
    "iso:country":"IN",
    "name:afr_x_preferred":[
        "Sundra"
    ],
    "name:est_x_preferred":[
        "Sundra"
    ],
    "name:nso_x_preferred":[
        "Sundra"
    ],
    "wof:name":"Sundra",
    "wof:placetype":"locality"
},
  "geometry": {"coordinates":[70.22328,26.0873],"type":"Point"}
}