{
  "type": "Feature",
  "properties": {
    "gn:admin1_code":"24",
    "gn:admin2_code":"115.0",
    "gn:asciiname":"Sundra",
    "gn:country_code":"IN",
    "gn:dem":76,
    "gn:feature_class":"P",
    "gn:feature_code":"PPL",
    "gn:name":"Sundra",
    "gn:population":0,
    "gn:timezone":"Asia/Kolkata",
    "iso:country":"IN",
    "ks:ks_name":"Sundra",
    "ks:ks_pop":719,
    "ks:ks_type":"VILLAGE",
    "name:afr_x_preferred":[
        "Sundra"
    ],
    "name:eng_x_preferred":[
        "Sundra"
    ],
    "name:est_x_preferred":[
        "Sundra"
    ],
    "name:nso_x_preferred":[
        "Sundra"
    ],
    "wof:name":"Sundra",
    "wof:placetype":"locality",
    "wof:population":719
},
  "geometry": {"coordinates":[70.22619400000001,26.084872],"type":"Point"}
}