{
  "type": "Feature",
  "properties": {
    "iso:country":"IN",
    "ks:ks_name":"Ramapadar",
    "ks:ks_pop":69,
    "ks:ks_type":"VILLAGE",
    "name:eng_x_preferred":[
        "Ramapadar"
    ],
    "wof:name":"Ramapadar",
    "wof:placetype":"locality",
    "wof:population":69
},
  "geometry": {"coordinates":[84.376819,19.431451],"type":"Point"}
}