{
  "type": "Feature",
  "properties": {
    "gn:admin1_code":"35",
    "gn:admin2_code":"445.0",
    "gn:asciiname":"Gohan",
    "gn:country_code":"IN",
    "gn:dem":310,
    "gn:feature_class":"P",
    "gn:feature_code":"PPL",
    "gn:name":"Gohan",
    "gn:population":0,
    "gn:timezone":"Asia/Kolkata",
    "iso:country":"IN",
    "name:ara_x_preferred":[
        "\u062c\u0648\u0647\u0627\u0646"
    ],
    "name:dan_x_preferred":[
        "Son-Gohan"
    ],
    "name:eus_x_preferred":[
        "Son Gohan"
    ],
    "name:fin_x_preferred":[
        "Son Gohan"
    ],
    "name:fra_x_preferred":[
        "Son Gohan"
    ],
    "name:glg_x_preferred":[
        "Son Gohanda"
    ],
    "name:heb_x_preferred":[
        "\u05e1\u05d5\u05df \u05d2\u05d5\u05d4\u05d0\u05df"
    ],
    "name:hun_x_preferred":[
        "Son Gohan"
    ],
    "name:ind_x_preferred":[
        "Gohan"
    ],
    "name:ita_x_preferred":[
        "Son Gohan"
    ],
    "name:jav_x_preferred":[
        "Gohan"
    ],
    "name:jpn_x_preferred":[
        "\u5b6b\u609f\u98ef"
    ],
    "name:lit_x_preferred":[
        "San Gohanas"
    ],
    "name:msa_x_preferred":[
        "Son Gohan"
    ],
    "name:por_x_preferred":[
        "Son Gohan"
    ],
    "name:spa_x_preferred":[
        "Son Gohan"
    ],
    "name:sqi_x_preferred":[
        "Gohan"
    ],
    "name:srp_x_preferred":[
        "Gohan"
    ],
    "name:tha_x_preferred":[
        "\u0e0b\u0e07 \u0e42\u0e01\u0e2e\u0e31\u0e07"
    ],
    "name:vie_x_preferred":[
        "Son Gohan"
    ],
    "name:zho_x_preferred":[
        "\u5b59\u609f\u996d"
    ],
    "wof:name":"Gohan",
    "wof:placetype":"locality"
},
  "geometry": {"coordinates":[77.34066999999997,22.75883],"type":"Point"}
}