{
  "type": "Feature",
  "properties": {
    "gn:admin1_code":"19.0",
    "gn:admin2_code":"570.0",
    "gn:asciiname":"Heggadehalli",
    "gn:country_code":"IN",
    "gn:dem":741,
    "gn:feature_class":"P",
    "gn:feature_code":"PPL",
    "gn:name":"Heggadehalli",
    "gn:population":0,
    "gn:timezone":"Asia/Kolkata",
    "iso:country":"IN",
    "wof:name":"Heggadehalli",
    "wof:placetype":"locality"
},
  "geometry": {"coordinates":[76.12392,13.7653],"type":"Point"}
}