{
  "type": "Feature",
  "properties": {
    "iso:country":"IN",
    "ks:ks_name":"Goicharcha",
    "ks:ks_pop":95,
    "ks:ks_type":"VILLAGE",
    "name:eng_x_preferred":[
        "Goicharcha"
    ],
    "wof:name":"Goicharcha",
    "wof:placetype":"locality",
    "wof:population":95
},
  "geometry": {"coordinates":[83.298469,19.761826],"type":"Point"}
}