{
  "type": "Feature",
  "properties": {
    "iso:country":"IN",
    "ks:ks_name":"Harekrishnapur",
    "ks:ks_pop":1059,
    "ks:ks_type":"VILLAGE",
    "name:eng_x_preferred":[
        "Harekrishnapur"
    ],
    "wof:name":"Harekrishnapur",
    "wof:placetype":"locality",
    "wof:population":1059
},
  "geometry": {"coordinates":[88.00569900000001,23.052938],"type":"Point"}
}