{
  "type": "Feature",
  "properties": {
    "iso:country":"IN",
    "ks:ks_name":"Bhanur Kuthi",
    "ks:ks_pop":875,
    "ks:ks_type":"VILLAGE",
    "ks:ks_uagg_main":0,
    "name:eng_x_preferred":[
        "Bhanur Kuthi"
    ],
    "wof:name":"Bhanur Kuthi",
    "wof:placetype":"neighbourhood",
    "wof:population":875
},
  "geometry": {"coordinates":[89.24747600000001,26.376864],"type":"Point"}
}