{
  "type": "Feature",
  "properties": {
    "gn:admin1_code":"19.0",
    "gn:admin2_code":"584.0",
    "gn:asciiname":"Kambsagara",
    "gn:country_code":"IN",
    "gn:dem":727,
    "gn:feature_class":"P",
    "gn:feature_code":"PPL",
    "gn:name":"Kambs\u0101gara",
    "gn:population":0,
    "gn:timezone":"Asia/Kolkata",
    "iso:country":"IN",
    "ks:ks_name":"Kamasagara",
    "ks:ks_pop":621,
    "ks:ks_type":"VILLAGE",
    "ks:ks_uagg_main":0,
    "name:eng_x_preferred":[
        "Kamasagara"
    ],
    "wof:name":"Kamasagara",
    "wof:placetype":"neighbourhood",
    "wof:population":621
},
  "geometry": {"coordinates":[77.300082,12.51168],"type":"Point"}
}