{
  "type": "Feature",
  "properties": {
    "iso:country":"IN",
    "ks:ks_name":"Lucknoora",
    "ks:ks_pop":1915,
    "ks:ks_type":"VILLAGE",
    "ks:ks_uagg_main":0,
    "name:eng_x_preferred":[
        "Lucknoora"
    ],
    "wof:name":"Lucknoora",
    "wof:placetype":"neighbourhood",
    "wof:population":1915
},
  "geometry": {"coordinates":[82.77535899999999,26.814844],"type":"Point"}
}