{
  "type": "Feature",
  "properties": {
    "iso:country":"IN",
    "ks:ks_name":"Santapur",
    "ks:ks_pop":274,
    "ks:ks_type":"VILLAGE",
    "ks:ks_uagg_main":0,
    "name:eng_x_preferred":[
        "Santapur"
    ],
    "wof:name":"Santapur",
    "wof:placetype":"neighbourhood",
    "wof:population":274
},
  "geometry": {"coordinates":[88.02069,25.204818],"type":"Point"}
}