{
  "type": "Feature",
  "properties": {
    "iso:country":"IN",
    "ks:ks_name":"Dalakpali",
    "ks:ks_pop":44,
    "ks:ks_type":"VILLAGE",
    "name:eng_x_preferred":[
        "Dalakpali"
    ],
    "wof:name":"Dalakpali",
    "wof:placetype":"locality",
    "wof:population":44
},
  "geometry": {"coordinates":[85.031334,19.9741],"type":"Point"}
}