{
  "type": "Feature",
  "properties": {
    "iso:country":"IN",
    "ks:ks_name":"Milak Fathepur Gawari",
    "ks:ks_pop":204,
    "ks:ks_type":"HABITATION",
    "name:eng_x_preferred":[
        "Milak Fathepur Gawari"
    ],
    "wof:name":"Milak Fathepur Gawari",
    "wof:placetype":"locality",
    "wof:population":204
},
  "geometry": {"coordinates":[78.387762,28.951671],"type":"Point"}
}