{
  "type": "Feature",
  "properties": {
    "iso:country":"IN",
    "ks:ks_name":"Kachler",
    "ks:ks_pop":580,
    "ks:ks_type":"VILLAGE",
    "name:eng_x_preferred":[
        "Kachler"
    ],
    "wof:name":"Kachler",
    "wof:placetype":"locality",
    "wof:population":580
},
  "geometry": {"coordinates":[80.38221299999999,19.74948],"type":"Point"}
}