{
  "type": "Feature",
  "properties": {
    "iso:country":"IN",
    "ks:ks_name":"Syamadanga",
    "ks:ks_pop":697,
    "ks:ks_type":"VILLAGE",
    "name:eng_x_preferred":[
        "Syamadanga"
    ],
    "wof:name":"Syamadanga",
    "wof:placetype":"locality",
    "wof:population":697
},
  "geometry": {"coordinates":[87.68161000000001,23.198773],"type":"Point"}
}