{
  "type": "Feature",
  "properties": {
    "gn:admin1_code":"36.0",
    "gn:admin2_code":"193.0",
    "gn:asciiname":"Mathia",
    "gn:country_code":"IN",
    "gn:dem":68,
    "gn:feature_class":"P",
    "gn:feature_code":"PPL",
    "gn:name":"Mathia",
    "gn:population":0,
    "gn:timezone":"Asia/Kolkata",
    "iso:country":"IN",
    "ks:ks_name":"Mathia",
    "ks:ks_pop":570,
    "ks:ks_type":"HABITATION",
    "name:eng_x_preferred":[
        "Mathia"
    ],
    "wof:name":"Mathia",
    "wof:placetype":"locality",
    "wof:population":570
},
  "geometry": {"coordinates":[83.900721,26.108649],"type":"Point"}
}