{
  "type": "Feature",
  "properties": {
    "gn:gn_country":"IN",
    "gn:gn_fcode":"PPL",
    "gn:gn_pop":0,
    "iso:country":"IN",
    "name:unk_x_variant":[
        "Mori Kal\u0101n"
    ],
    "qs_pg:aaroncc":"IN",
    "qs_pg:gn_country":"IN",
    "qs_pg:gn_fcode":"PPL",
    "qs_pg:gn_pop":0,
    "qs_pg:name":"Mori Kalan",
    "qs_pg:name_adm0":"India",
    "qs_pg:name_adm1":"Rajasthan",
    "qs_pg:photos_9r":0,
    "qs_pg:photos_sr":0,
    "qs_pg:pop_sr":0,
    "qs_pg:qs_pg_placetype":"locality",
    "qs_pg:qs_pg_placetype_gp":"Town",
    "qs_pg:woe_adm0":23424848,
    "woe:adm0_id":23424848,
    "woe:name_adm0":"India",
    "woe:name_adm1":"Rajasthan",
    "woe:placetype":"Town",
    "wof:name":"Mori Kalan",
    "wof:placetype":"locality"
},
  "geometry": {"coordinates":[74.48515,26.67904],"type":"Point"}
}