{
  "type": "Feature",
  "properties": {
    "gn:country":"IN",
    "gn:fcode":"PPL",
    "gn:population":0,
    "iso:country":"IN",
    "name:ast_x_preferred":[
        "Kaggalipura"
    ],
    "name:eng_x_preferred":[
        "Kaggalipura"
    ],
    "name:nld_x_preferred":[
        "Kaggalipura"
    ],
    "qs:name":"Kaggalipura",
    "qs:name_adm0":"India",
    "qs:name_adm1":"Karnataka",
    "qs:photos":44,
    "qs:photos_1k":9,
    "qs:photos_9k":1,
    "qs:photos_9r":2,
    "qs:photos_all":44,
    "qs:photos_sr":2,
    "qs:placetype":"Town",
    "qs:pop_sr":"0",
    "wd:wordcount":289,
    "wof:name":"Kaggalipura",
    "wof:placetype":"locality",
    "wof:population":0
},
  "geometry": {"coordinates":[77.50825,12.80057],"type":"Point"}
}