{
  "type": "Feature",
  "properties": {
    "iso:country":"IN",
    "ks:ks_name":"Sirsia West",
    "ks:ks_pop":632,
    "ks:ks_type":"HABITATION",
    "ks:ks_uagg_main":0,
    "name:eng_x_preferred":[
        "Sirsia West"
    ],
    "wof:name":"Sirsia West",
    "wof:placetype":"neighbourhood",
    "wof:population":632
},
  "geometry": {"coordinates":[83.859784,26.750576],"type":"Point"}
}