{
  "type": "Feature",
  "properties": {
    "gn:admin1_code":"39.0",
    "gn:admin2_code":"63.0",
    "gn:asciiname":"Haneti",
    "gn:country_code":"IN",
    "gn:dem":1372,
    "gn:feature_class":"P",
    "gn:feature_code":"PPL",
    "gn:name":"Haneti",
    "gn:population":0,
    "gn:timezone":"Asia/Kolkata",
    "iso:country":"IN",
    "name:ita_x_preferred":[
        "Haneti"
    ],
    "name:swa_x_preferred":[
        "Haneti"
    ],
    "wof:name":"Haneti",
    "wof:placetype":"locality"
},
  "geometry": {"coordinates":[79.71584,29.83395],"type":"Point"}
}