{
  "type": "Feature",
  "properties": {
    "iso:country":"IN",
    "ks:ks_name":"Gaitra Ryt.",
    "ks:ks_pop":456,
    "ks:ks_type":"VILLAGE",
    "name:eng_x_preferred":[
        "Gaitra Ryt."
    ],
    "wof:name":"Gaitra Ryt.",
    "wof:placetype":"locality",
    "wof:population":456
},
  "geometry": {"coordinates":[80.84226700000001,22.475588],"type":"Point"}
}