{
  "type": "Feature",
  "properties": {
    "iso:country":"IN",
    "ks:ks_name":"Palur",
    "ks:ks_pop":485,
    "ks:ks_type":"HABITATION",
    "name:eng_x_preferred":[
        "Palur"
    ],
    "wof:name":"Palur",
    "wof:placetype":"locality",
    "wof:population":485
},
  "geometry": {"coordinates":[79.536777,11.136237],"type":"Point"}
}