{
  "type": "Feature",
  "properties": {
    "gn:admin1_code":"2.0",
    "gn:admin2_code":"552.0",
    "gn:asciiname":"Kollamvagumetta",
    "gn:country_code":"IN",
    "gn:dem":257,
    "gn:feature_class":"P",
    "gn:feature_code":"PPL",
    "gn:name":"Kollamv\u0101gumetta",
    "gn:population":0,
    "gn:timezone":"Asia/Kolkata",
    "iso:country":"IN",
    "wof:name":"Kollamvagumetta",
    "wof:placetype":"neighbourhood"
},
  "geometry": {"coordinates":[78.31285,15.53608],"type":"Point"}
}