{
  "type": "Feature",
  "properties": {
    "iso:country":"IN",
    "ks:ks_name":"Pillavanaicken Salai",
    "ks:ks_pop":93,
    "ks:ks_type":"HABITATION",
    "name:eng_x_preferred":[
        "Pillavanaicken Salai"
    ],
    "wof:name":"Pillavanaicken Salai",
    "wof:placetype":"locality",
    "wof:population":93
},
  "geometry": {"coordinates":[77.118205,10.554603],"type":"Point"}
}