{
  "type": "Feature",
  "properties": {
    "iso:country":"IN",
    "ks:ks_name":"Thanneerpandhal",
    "ks:ks_pop":154,
    "ks:ks_type":"HABITATION",
    "name:eng_x_preferred":[
        "Thanneerpandhal"
    ],
    "wof:name":"Thanneerpandhal",
    "wof:placetype":"locality",
    "wof:population":154
},
  "geometry": {"coordinates":[78.412661,10.191363],"type":"Point"}
}