{
  "type": "Feature",
  "properties": {
    "iso:country":"IN",
    "ks:ks_name":"Chichtola Kodel",
    "ks:ks_pop":105,
    "ks:ks_type":"HABITATION",
    "name:eng_x_preferred":[
        "Chichtola Kodel"
    ],
    "wof:name":"Chichtola Kodel",
    "wof:placetype":"locality",
    "wof:population":105
},
  "geometry": {"coordinates":[79.90261,21.305587],"type":"Point"}
}