{
  "type": "Feature",
  "properties": {
    "gn:admin1_code":"12.0",
    "gn:admin2_code":"16.0",
    "gn:asciiname":"Kakol",
    "gn:country_code":"IN",
    "gn:dem":2335,
    "gn:feature_class":"P",
    "gn:feature_code":"PPL",
    "gn:name":"K\u0101kol",
    "gn:population":0,
    "gn:timezone":"Asia/Kolkata",
    "iso:country":"IN",
    "wof:name":"Kakol",
    "wof:placetype":"locality"
},
  "geometry": {"coordinates":[75.73889,33.00692],"type":"Point"}
}