{
  "type": "Feature",
  "properties": {
    "iso:country":"IN",
    "ks:ks_name":"Sorsulewadi",
    "ks:ks_pop":108,
    "ks:ks_type":"HABITATION",
    "name:eng_x_preferred":[
        "Sorsulewadi"
    ],
    "wof:name":"Sorsulewadi",
    "wof:placetype":"locality",
    "wof:population":108
},
  "geometry": {"coordinates":[73.640366,15.939443],"type":"Point"}
}