{
  "type": "Feature",
  "properties": {
    "iso:country":"IN",
    "ks:ks_name":"Dodakipara",
    "ks:ks_pop":172,
    "ks:ks_type":"HABITATION",
    "name:eng_x_preferred":[
        "Dodakipara"
    ],
    "wof:name":"Dodakipara",
    "wof:placetype":"locality",
    "wof:population":172
},
  "geometry": {"coordinates":[82.553552,22.974053],"type":"Point"}
}