{
  "type": "Feature",
  "properties": {
    "iso:country":"IN",
    "ks:ks_name":"Therthally",
    "ks:ks_pop":1763,
    "ks:ks_type":"HABITATION",
    "name:eng_x_preferred":[
        "Therthally"
    ],
    "wof:name":"Therthally",
    "wof:placetype":"locality",
    "wof:population":1763
},
  "geometry": {"coordinates":[75.39801300000001,12.224865],"type":"Point"}
}