{
  "type": "Feature",
  "properties": {
    "iso:country":"IN",
    "ks:ks_name":"Mukhrja Chak",
    "ks:ks_pop":1459,
    "ks:ks_type":"HABITATION",
    "name:eng_x_preferred":[
        "Mukhrja Chak"
    ],
    "wof:name":"Mukhrja Chak",
    "wof:placetype":"locality",
    "wof:population":1459
},
  "geometry": {"coordinates":[88.332227,21.948743],"type":"Point"}
}