{
  "type": "Feature",
  "properties": {
    "iso:country":"IN",
    "ks:ks_name":"Purunia",
    "ks:ks_type":"VILLAGE",
    "name:eng_x_preferred":[
        "Purunia"
    ],
    "wof:name":"Purunia",
    "wof:placetype":"locality"
},
  "geometry": {"coordinates":[85.986091,21.990731],"type":"Point"}
}