{
  "type": "Feature",
  "properties": {
    "iso:country":"IN",
    "ks:ks_name":"Choudhurypara",
    "ks:ks_pop":393,
    "ks:ks_type":"HABITATION",
    "ks:ks_uagg_main":0,
    "name:eng_x_preferred":[
        "Choudhurypara"
    ],
    "wof:name":"Choudhurypara",
    "wof:placetype":"neighbourhood",
    "wof:population":393
},
  "geometry": {"coordinates":[91.427943,26.088434],"type":"Point"}
}