{
  "type": "Feature",
  "properties": {
    "iso:country":"IN",
    "ks:ks_name":"Atpukhari",
    "ks:ks_pop":1784,
    "ks:ks_type":"VILLAGE",
    "name:eng_x_preferred":[
        "Atpukhari"
    ],
    "wof:name":"Atpukhari",
    "wof:placetype":"locality",
    "wof:population":1784
},
  "geometry": {"coordinates":[89.235496,26.427243],"type":"Point"}
}