{
  "type": "Feature",
  "properties": {
    "iso:country":"IN",
    "ks:ks_name":"Ramegaon",
    "ks:ks_pop":2062,
    "ks:ks_type":"VILLAGE",
    "name:eng_x_preferred":[
        "Ramegaon"
    ],
    "wof:name":"Ramegaon",
    "wof:placetype":"locality",
    "wof:population":2062
},
  "geometry": {"coordinates":[76.35754300000001,18.414372],"type":"Point"}
}