{
  "type": "Feature",
  "properties": {
    "gn:admin1_code":"11.0",
    "gn:admin2_code":"32.0",
    "gn:asciiname":"Rane ka Thara",
    "gn:country_code":"IN",
    "gn:dem":1655,
    "gn:feature_class":"P",
    "gn:feature_code":"PPL",
    "gn:name":"R\u0101ne ka Thara",
    "gn:population":0,
    "gn:timezone":"Asia/Kolkata",
    "iso:country":"IN",
    "wof:name":"Rane ka Thara",
    "wof:placetype":"locality"
},
  "geometry": {"coordinates":[77.45919000000001,30.78408],"type":"Point"}
}