{
  "type": "Feature",
  "properties": {
    "gn:admin1_code":"11.0",
    "gn:admin2_code":"26.0",
    "gn:asciiname":"Ghult",
    "gn:country_code":"IN",
    "gn:dem":1664,
    "gn:feature_class":"P",
    "gn:feature_code":"PPL",
    "gn:name":"Ghult",
    "gn:population":0,
    "gn:timezone":"Asia/Kolkata",
    "iso:country":"IN",
    "wof:name":"Ghult",
    "wof:placetype":"locality"
},
  "geometry": {"coordinates":[77.46536999999999,31.38526],"type":"Point"}
}