{
  "type": "Feature",
  "properties": {
    "iso:country":"IN",
    "ks:ks_name":"Majimoni Para",
    "ks:ks_pop":345,
    "ks:ks_type":"HABITATION",
    "name:eng_x_preferred":[
        "Majimoni Para"
    ],
    "wof:name":"Majimoni Para",
    "wof:placetype":"locality",
    "wof:population":345
},
  "geometry": {"coordinates":[91.921672,23.559524],"type":"Point"}
}