{
  "type": "Feature",
  "properties": {
    "iso:country":"IN",
    "ks:ks_name":"Asananali",
    "ks:ks_pop":928,
    "ks:ks_type":"VILLAGE",
    "name:eng_x_preferred":[
        "Asananali"
    ],
    "wof:name":"Asananali",
    "wof:placetype":"locality",
    "wof:population":928
},
  "geometry": {"coordinates":[84.87708499999999,21.493043],"type":"Point"}
}