{
  "type": "Feature",
  "properties": {
    "iso:country":"IN",
    "ks:ks_name":"Napama Gaon",
    "ks:ks_pop":110,
    "ks:ks_type":"HABITATION",
    "name:eng_x_preferred":[
        "Napama Gaon"
    ],
    "wof:name":"Napama Gaon",
    "wof:placetype":"locality",
    "wof:population":110
},
  "geometry": {"coordinates":[92.77287,26.249339],"type":"Point"}
}