{
  "type": "Feature",
  "properties": {
    "iso:country":"IN",
    "ks:ks_alt_nam":"chithravidangan",
    "ks:ks_name":"Chithravidangan",
    "ks:ks_pop":160,
    "ks:ks_type":"HABITATION",
    "name:eng_x_preferred":[
        "Chithravidangan"
    ],
    "wof:name":"Chithravidangan",
    "wof:placetype":"locality",
    "wof:population":160
},
  "geometry": {"coordinates":[79.086179,9.976897],"type":"Point"}
}