{
  "type": "Feature",
  "properties": {
    "iso:country":"IN",
    "ks:ks_name":"Bandakaguda",
    "ks:ks_pop":215,
    "ks:ks_type":"HABITATION",
    "name:eng_x_preferred":[
        "Bandakaguda"
    ],
    "wof:name":"Bandakaguda",
    "wof:placetype":"locality",
    "wof:population":215
},
  "geometry": {"coordinates":[82.35642199999999,18.96737],"type":"Point"}
}