{
  "type": "Feature",
  "properties": {
    "iso:country":"IN",
    "ks:ks_name":"Jodtarai",
    "ks:ks_pop":64,
    "ks:ks_type":"VILLAGE",
    "name:eng_x_preferred":[
        "Jodtarai"
    ],
    "wof:name":"Jodtarai",
    "wof:placetype":"locality",
    "wof:population":64
},
  "geometry": {"coordinates":[80.47557,20.684732],"type":"Point"}
}