{
  "type": "Feature",
  "properties": {
    "gn:admin1_code":"12.0",
    "gn:admin2_code":"018",
    "gn:asciiname":"Hanzal",
    "gn:country_code":"IN",
    "gn:dem":2078,
    "gn:feature_class":"P",
    "gn:feature_code":"PPL",
    "gn:name":"Hanzal",
    "gn:population":0,
    "gn:timezone":"Asia/Kolkata",
    "iso:country":"IN",
    "wof:name":"Hanzal",
    "wof:placetype":"locality"
},
  "geometry": {"coordinates":[75.78686,33.56904],"type":"Point"}
}