{
  "type": "Feature",
  "properties": {
    "iso:country":"IN",
    "ks:ks_name":"Halganj",
    "ks:ks_pop":162,
    "ks:ks_type":"HABITATION",
    "ks:ks_uagg_main":0,
    "name:eng_x_preferred":[
        "Halganj"
    ],
    "wof:name":"Halganj",
    "wof:placetype":"neighbourhood",
    "wof:population":162
},
  "geometry": {"coordinates":[81.859804,25.905791],"type":"Point"}
}