{
  "type": "Feature",
  "properties": {
    "gn:admin1_code":"24.0",
    "gn:admin2_code":"112.0",
    "gn:asciiname":"Barun",
    "gn:country_code":"IN",
    "gn:dem":481,
    "gn:feature_class":"P",
    "gn:feature_code":"PPL",
    "gn:name":"Bar\u016bn",
    "gn:population":0,
    "gn:timezone":"Asia/Kolkata",
    "iso:country":"IN",
    "name:ceb_x_preferred":[
        "Barun"
    ],
    "name:deu_x_preferred":[
        "Barun"
    ],
    "name:fra_x_preferred":[
        "Barun"
    ],
    "name:ita_x_preferred":[
        "Barun"
    ],
    "name:jpn_x_preferred":[
        "\u30d0\u30eb\u30f3"
    ],
    "wof:name":"Barun",
    "wof:placetype":"locality"
},
  "geometry": {"coordinates":[74.64972,26.65838],"type":"Point"}
}