{
  "type": "Feature",
  "properties": {
    "iso:country":"IN",
    "ks:ks_alt_nam":"Kollagoundan  korai",
    "ks:ks_name":"Kollagoundan Korai",
    "ks:ks_pop":150,
    "ks:ks_type":"HABITATION",
    "name:eng_x_preferred":[
        "Kollagoundan Korai"
    ],
    "name:eng_x_variant":[
        "Kollagoundan  korai"
    ],
    "wof:name":"Kollagoundan Korai",
    "wof:placetype":"locality",
    "wof:population":150
},
  "geometry": {"coordinates":[77.851731,11.496538],"type":"Point"}
}