{
  "type": "Feature",
  "properties": {
    "iso:country":"IN",
    "ks:ks_name":"Kankeri",
    "ks:ks_pop":79,
    "ks:ks_type":"VILLAGE",
    "name:eng_x_preferred":[
        "Kankeri"
    ],
    "wof:name":"Kankeri",
    "wof:placetype":"locality",
    "wof:population":79
},
  "geometry": {"coordinates":[83.523447,20.061987],"type":"Point"}
}