{
  "type": "Feature",
  "properties": {
    "iso:country":"IN",
    "ks:ks_alt_nam":"BAIN",
    "ks:ks_name":"Bain",
    "ks:ks_pop":722,
    "ks:ks_type":"HABITATION",
    "name:eng_x_preferred":[
        "Bain"
    ],
    "wof:name":"Bain",
    "wof:placetype":"locality",
    "wof:population":722
},
  "geometry": {"coordinates":[85.13387299999999,24.194064],"type":"Point"}
}