{
  "type": "Feature",
  "properties": {
    "iso:country":"IN",
    "ks:ks_name":"Paschim Barachouki",
    "ks:ks_pop":3879,
    "ks:ks_type":"VILLAGE",
    "name:eng_x_preferred":[
        "Paschim Barachouki"
    ],
    "wof:name":"Paschim Barachouki",
    "wof:placetype":"locality",
    "wof:population":3879
},
  "geometry": {"coordinates":[89.57935500000001,26.441121],"type":"Point"}
}