{
  "type": "Feature",
  "properties": {
    "iso:country":"IN",
    "ks:ks_alt_nam":"Gulari\u0101t\u0101nr",
    "ks:ks_name":"Gulariatanr",
    "ks:ks_pop":81,
    "ks:ks_type":"VILLAGE",
    "name:eng_x_preferred":[
        "Gulariatanr"
    ],
    "name:eng_x_variant":[
        "Gulari\u0101t\u0101nr"
    ],
    "wof:name":"Gulariatanr",
    "wof:placetype":"locality",
    "wof:population":81
},
  "geometry": {"coordinates":[84.46575,23.674829],"type":"Point"}
}