{
  "type": "Feature",
  "properties": {
    "gn:admin1_code":"13.0",
    "gn:admin2_code":"599.0",
    "gn:asciiname":"Ilangamangalam",
    "gn:country_code":"IN",
    "gn:dem":23,
    "gn:feature_class":"P",
    "gn:feature_code":"PPL",
    "gn:name":"Ilangamangalam",
    "gn:population":0,
    "gn:timezone":"Asia/Kolkata",
    "iso:country":"IN",
    "wof:name":"Ilangamangalam",
    "wof:placetype":"locality"
},
  "geometry": {"coordinates":[76.77039000000001,9.07571],"type":"Point"}
}