{
  "type": "Feature",
  "properties": {
    "iso:country":"IN",
    "ks:ks_alt_nam":"K\u0101ri",
    "ks:ks_name":"Kari",
    "ks:ks_pop":378,
    "ks:ks_type":"VILLAGE",
    "name:eng_x_preferred":[
        "Kari"
    ],
    "name:eng_x_variant":[
        "K\u0101ri"
    ],
    "wof:name":"Kari",
    "wof:placetype":"locality",
    "wof:population":378
},
  "geometry": {"coordinates":[85.99571299999999,24.492364],"type":"Point"}
}