{
  "type": "Feature",
  "properties": {
    "iso:country":"IN",
    "ks:ks_name":"Gummapadu",
    "ks:ks_pop":441,
    "ks:ks_type":"VILLAGE",
    "ks:ks_uagg_main":0,
    "name:eng_x_preferred":[
        "Gummapadu"
    ],
    "wof:name":"Gummapadu",
    "wof:placetype":"neighbourhood",
    "wof:population":441
},
  "geometry": {"coordinates":[84.015682,18.578532],"type":"Point"}
}