{
  "type": "Feature",
  "properties": {
    "iso:country":"IN",
    "ks:ks_alt_nam":"1 FDM",
    "ks:ks_name":"1 Fdm",
    "ks:ks_pop":351,
    "ks:ks_type":"HABITATION",
    "name:eng_x_preferred":[
        "1 Fdm"
    ],
    "wof:name":"1 Fdm",
    "wof:placetype":"locality",
    "wof:population":351
},
  "geometry": {"coordinates":[73.77495,29.430492],"type":"Point"}
}