{
  "type": "Feature",
  "properties": {
    "iso:country":"IN",
    "ks:ks_name":"Jamane",
    "ks:ks_pop":269,
    "ks:ks_type":"VILLAGE",
    "name:eng_x_preferred":[
        "Jamane"
    ],
    "wof:name":"Jamane",
    "wof:placetype":"locality",
    "wof:population":269
},
  "geometry": {"coordinates":[75.459191,20.674156],"type":"Point"}
}