{
  "type": "Feature",
  "properties": {
    "iso:country":"IN",
    "ks:ks_alt_nam":"MADNAKHAS",
    "ks:ks_name":"Madnakhas",
    "ks:ks_pop":324,
    "ks:ks_type":"HABITATION",
    "name:eng_x_preferred":[
        "Madnakhas"
    ],
    "wof:name":"Madnakhas",
    "wof:placetype":"locality",
    "wof:population":324
},
  "geometry": {"coordinates":[83.07233100000001,23.765324],"type":"Point"}
}