{
  "type": "Feature",
  "properties": {
    "iso:country":"IN",
    "ks:ks_name":"Priyadarshini",
    "ks:ks_pop":60,
    "ks:ks_type":"HABITATION",
    "name:eng_x_preferred":[
        "Priyadarshini"
    ],
    "wof:name":"Priyadarshini",
    "wof:placetype":"locality",
    "wof:population":60
},
  "geometry": {"coordinates":[75.999444,12.155278],"type":"Point"}
}