{
  "type": "Feature",
  "properties": {
    "iso:country":"IN",
    "ks:ks_name":"Ludhuri",
    "ks:ks_pop":50,
    "ks:ks_type":"VILLAGE",
    "name:eng_x_preferred":[
        "Ludhuri"
    ],
    "wof:name":"Ludhuri",
    "wof:placetype":"locality",
    "wof:population":50
},
  "geometry": {"coordinates":[84.179633,19.440506],"type":"Point"}
}