{
  "type": "Feature",
  "properties": {
    "iso:country":"IN",
    "ks:ks_name":"Lanjiberna",
    "ks:ks_pop":977,
    "ks:ks_type":"VILLAGE",
    "name:eng_x_preferred":[
        "Lanjiberna"
    ],
    "wof:name":"Lanjiberna",
    "wof:placetype":"locality",
    "wof:population":977
},
  "geometry": {"coordinates":[84.733152,22.272454],"type":"Point"}
}