{
  "type": "Feature",
  "properties": {
    "iso:country":"IN",
    "ks:ks_name":"Budhawadi",
    "ks:ks_pop":44,
    "ks:ks_type":"HABITATION",
    "name:eng_x_preferred":[
        "Budhawadi"
    ],
    "wof:name":"Budhawadi",
    "wof:placetype":"locality",
    "wof:population":44
},
  "geometry": {"coordinates":[73.47627,16.593962],"type":"Point"}
}