{
  "type": "Feature",
  "properties": {
    "iso:country":"IN",
    "ks:ks_name":"Kompada",
    "ks:ks_pop":423,
    "ks:ks_type":"HABITATION",
    "name:eng_x_preferred":[
        "Kompada"
    ],
    "wof:name":"Kompada",
    "wof:placetype":"locality",
    "wof:population":423
},
  "geometry": {"coordinates":[72.938745,20.017819],"type":"Point"}
}