{
  "type": "Feature",
  "properties": {
    "iso:country":"IN",
    "ks:ks_name":"J. Molhu Kunwar",
    "ks:ks_pop":381,
    "ks:ks_type":"HABITATION",
    "ks:ks_uagg_main":0,
    "name:eng_x_preferred":[
        "J. Molhu Kunwar"
    ],
    "wof:name":"J. Molhu Kunwar",
    "wof:placetype":"neighbourhood",
    "wof:population":381
},
  "geometry": {"coordinates":[83.364602,26.64936],"type":"Point"}
}