{
  "type": "Feature",
  "properties": {
    "iso:country":"IN",
    "ks:ks_alt_nam":"MANEWASTI",
    "ks:ks_name":"Manewasti",
    "ks:ks_pop":76,
    "ks:ks_type":"HABITATION",
    "name:eng_x_preferred":[
        "Manewasti"
    ],
    "wof:name":"Manewasti",
    "wof:placetype":"locality",
    "wof:population":76
},
  "geometry": {"coordinates":[74.72715700000001,16.999996],"type":"Point"}
}