{
  "type": "Feature",
  "properties": {
    "gn:admin1_code":"19.0",
    "gn:admin2_code":"570.0",
    "gn:asciiname":"Hadi",
    "gn:country_code":"IN",
    "gn:dem":729,
    "gn:feature_class":"P",
    "gn:feature_code":"PPL",
    "gn:name":"Hadi",
    "gn:population":0,
    "gn:timezone":"Asia/Kolkata",
    "iso:country":"IN",
    "ks:ks_name":"Hadi",
    "ks:ks_pop":63,
    "ks:ks_type":"VILLAGE",
    "name:bak_x_preferred":[
        "\u04ba\u0430\u0499\u044b\u0435\u0432"
    ],
    "name:eng_x_preferred":[
        "Hadi"
    ],
    "name:fas_x_preferred":[
        "\u0647\u0627\u062f\u06cc"
    ],
    "name:fra_x_preferred":[
        "Hadi"
    ],
    "name:rus_x_preferred":[
        "\u0425\u0430\u0434\u0438"
    ],
    "name:swe_x_preferred":[
        "Hadi"
    ],
    "wof:name":"Hadi",
    "wof:placetype":"locality",
    "wof:population":63
},
  "geometry": {"coordinates":[75.207345,13.32204],"type":"Point"}
}