{
  "type": "Feature",
  "properties": {
    "iso:country":"IN",
    "ks:ks_name":"Anchibarehatty",
    "ks:ks_pop":485,
    "ks:ks_type":"HABITATION",
    "name:eng_x_preferred":[
        "Anchibarehatty"
    ],
    "wof:name":"Anchibarehatty",
    "wof:placetype":"locality",
    "wof:population":485
},
  "geometry": {"coordinates":[76.44366100000001,13.903829],"type":"Point"}
}