{
  "type": "Feature",
  "properties": {
    "iso:country":"IN",
    "ks:ks_name":"Tunang Forest",
    "ks:ks_pop":0,
    "ks:ks_type":"VILLAGE",
    "name:eng_x_preferred":[
        "Tunang Forest"
    ],
    "wof:name":"Tunang Forest",
    "wof:placetype":"locality",
    "wof:population":0
},
  "geometry": {"coordinates":[88.490816,27.007809],"type":"Point"}
}