{
  "type": "Feature",
  "properties": {
    "iso:country":"IN",
    "ks:ks_name":"Nagla Luxman",
    "ks:ks_pop":262,
    "ks:ks_type":"HABITATION",
    "name:eng_x_preferred":[
        "Nagla Luxman"
    ],
    "wof:name":"Nagla Luxman",
    "wof:placetype":"locality",
    "wof:population":262
},
  "geometry": {"coordinates":[78.47748300000001,27.50773],"type":"Point"}
}