{
  "type": "Feature",
  "properties": {
    "gn:admin1_code":"16.0",
    "gn:admin2_code":"510",
    "gn:asciiname":"Bori Arab",
    "gn:country_code":"IN",
    "gn:dem":324,
    "gn:feature_class":"P",
    "gn:feature_code":"PPL",
    "gn:name":"Bori Arab",
    "gn:population":0,
    "gn:timezone":"Asia/Kolkata",
    "iso:country":"IN",
    "name:und_x_variant":[
        "Bori"
    ],
    "wof:name":"Bori Arab",
    "wof:placetype":"locality"
},
  "geometry": {"coordinates":[77.86336,20.34894],"type":"Point"}
}