{
  "type": "Feature",
  "properties": {
    "iso:country":"IN",
    "ks:ks_name":"Bamunjuli T.E.",
    "ks:ks_pop":1286,
    "ks:ks_type":"VILLAGE",
    "ks:ks_uagg_main":0,
    "name:eng_x_preferred":[
        "Bamunjuli T.E."
    ],
    "wof:name":"Bamunjuli T.E.",
    "wof:placetype":"neighbourhood",
    "wof:population":1286
},
  "geometry": {"coordinates":[91.832543,26.809906],"type":"Point"}
}