{
  "type": "Feature",
  "properties": {
    "gn:admin1_code":"35",
    "gn:admin2_code":"419.0",
    "gn:asciiname":"Surapura",
    "gn:country_code":"IN",
    "gn:dem":191,
    "gn:feature_class":"P",
    "gn:feature_code":"PPL",
    "gn:name":"S\u016br\u0101pura",
    "gn:population":0,
    "gn:timezone":"Asia/Kolkata",
    "iso:country":"IN",
    "ks:ks_alt_nam":"S\u016br\u0101pura",
    "ks:ks_name":"Surapura",
    "ks:ks_pop":646,
    "ks:ks_type":"VILLAGE",
    "name:eng_x_preferred":[
        "Surapura"
    ],
    "name:eng_x_variant":[
        "S\u016br\u0101pura"
    ],
    "wof:name":"Surapura",
    "wof:placetype":"locality",
    "wof:population":646
},
  "geometry": {"coordinates":[77.574395,26.280588],"type":"Point"}
}