{
  "type": "Feature",
  "properties": {
    "iso:country":"IN",
    "ks:ks_name":"Chhota Hankol",
    "ks:ks_pop":176,
    "ks:ks_type":"VILLAGE",
    "name:eng_x_preferred":[
        "Chhota Hankol"
    ],
    "wof:name":"Chhota Hankol",
    "wof:placetype":"locality",
    "wof:population":176
},
  "geometry": {"coordinates":[86.030838,23.40402],"type":"Point"}
}