{
  "type": "Feature",
  "properties": {
    "iso:country":"IN",
    "ks:ks_name":"Tekulpad",
    "ks:ks_type":"VILLAGE",
    "name:eng_x_preferred":[
        "Tekulpad"
    ],
    "wof:name":"Tekulpad",
    "wof:placetype":"locality"
},
  "geometry": {"coordinates":[78.13928199999999,19.20414],"type":"Point"}
}