{
  "type": "Feature",
  "properties": {
    "iso:country":"IN",
    "ks:ks_alt_nam":"DUBEY TOLA",
    "ks:ks_name":"Dubey Tola",
    "ks:ks_pop":151,
    "ks:ks_type":"HABITATION",
    "name:eng_x_preferred":[
        "Dubey Tola"
    ],
    "wof:name":"Dubey Tola",
    "wof:placetype":"locality",
    "wof:population":151
},
  "geometry": {"coordinates":[84.805801,26.215418],"type":"Point"}
}