{
  "type": "Feature",
  "properties": {
    "gn:admin1_code":"13.0",
    "gn:admin2_code":"588.0",
    "gn:asciiname":"Kilayyikote",
    "gn:country_code":"IN",
    "gn:dem":27,
    "gn:feature_class":"P",
    "gn:feature_code":"PPL",
    "gn:name":"Kil\u0101yyik\u014dte",
    "gn:population":0,
    "gn:timezone":"Asia/Kolkata",
    "iso:country":"IN",
    "wof:name":"Kilayyikote",
    "wof:placetype":"locality"
},
  "geometry": {"coordinates":[75.17130999999998,12.24051],"type":"Point"}
}