{
  "type": "Feature",
  "properties": {
    "iso:country":"IN",
    "ks:ks_name":"Galijaddi",
    "ks:ks_pop":49,
    "ks:ks_type":"HABITATION",
    "name:eng_x_preferred":[
        "Galijaddi"
    ],
    "wof:name":"Galijaddi",
    "wof:placetype":"locality",
    "wof:population":49
},
  "geometry": {"coordinates":[74.81942600000001,14.436676],"type":"Point"}
}