{
  "type": "Feature",
  "properties": {
    "iso:country":"IN",
    "ks:ks_name":"Soon",
    "ks:ks_pop":234,
    "ks:ks_type":"HABITATION",
    "name:eng_x_preferred":[
        "Soon"
    ],
    "wof:name":"Soon",
    "wof:placetype":"locality",
    "wof:population":234
},
  "geometry": {"coordinates":[79.60913499999999,29.519698],"type":"Point"}
}