{
  "type": "Feature",
  "properties": {
    "iso:country":"IN",
    "ks:ks_alt_nam":"markandari",
    "ks:ks_name":"Markandari",
    "ks:ks_pop":470,
    "ks:ks_type":"HABITATION",
    "name:eng_x_preferred":[
        "Markandari"
    ],
    "wof:name":"Markandari",
    "wof:placetype":"locality",
    "wof:population":470
},
  "geometry": {"coordinates":[75.723034,11.574339],"type":"Point"}
}