{
  "type": "Feature",
  "properties": {
    "iso:country":"IN",
    "ks:ks_name":"Kholivitar",
    "ks:ks_pop":110,
    "ks:ks_type":"HABITATION",
    "name:eng_x_preferred":[
        "Kholivitar"
    ],
    "wof:name":"Kholivitar",
    "wof:placetype":"locality",
    "wof:population":110
},
  "geometry": {"coordinates":[82.558047,20.441642],"type":"Point"}
}