{
  "type": "Feature",
  "properties": {
    "gn:admin1_code":"10",
    "gn:admin2_code":"81.0",
    "gn:asciiname":"Dhigawa Shamiyan",
    "gn:country_code":"IN",
    "gn:dem":245,
    "gn:feature_class":"P",
    "gn:feature_code":"PPL",
    "gn:name":"Dhig\u0101w\u0101 Sh\u0101miy\u0101n",
    "gn:population":0,
    "gn:timezone":"Asia/Kolkata",
    "iso:country":"IN",
    "ks:ks_alt_nam":"Dhig\u0101w\u0101 Sh\u0101miy\u0101n",
    "ks:ks_name":"Dhigawa Shamiyan",
    "ks:ks_pop":1259,
    "ks:ks_type":"VILLAGE",
    "ks:ks_uagg_main":0,
    "name:eng_x_preferred":[
        "Dhigawa Shamiyan"
    ],
    "name:eng_x_variant":[
        "Dhig\u0101w\u0101 Sh\u0101miy\u0101n"
    ],
    "wof:name":"Dhigawa Shamiyan",
    "wof:placetype":"neighbourhood",
    "wof:population":1259
},
  "geometry": {"coordinates":[75.82445800000001,28.574802],"type":"Point"}
}