{
  "type": "Feature",
  "properties": {
    "gn:admin1_code":"40",
    "gn:admin2_code":"539.0",
    "gn:asciiname":"Ramannagudem",
    "gn:country_code":"IN",
    "gn:dem":158,
    "gn:feature_class":"P",
    "gn:feature_code":"PPL",
    "gn:name":"R\u0101mannag\u016bdem",
    "gn:population":0,
    "gn:timezone":"Asia/Kolkata",
    "iso:country":"IN",
    "wof:name":"Ramannagudem",
    "wof:placetype":"locality"
},
  "geometry": {"coordinates":[79.77211,17.04319],"type":"Point"}
}