{
  "type": "Feature",
  "properties": {
    "iso:country":"IN",
    "ks:ks_name":"Gopinathpur",
    "ks:ks_pop":688,
    "ks:ks_type":"VILLAGE",
    "name:eng_x_preferred":[
        "Gopinathpur"
    ],
    "wof:name":"Gopinathpur",
    "wof:placetype":"locality",
    "wof:population":688
},
  "geometry": {"coordinates":[87.420466,23.214587],"type":"Point"}
}