{
  "type": "Feature",
  "properties": {
    "iso:country":"IN",
    "ks:ks_name":"Ghaghra",
    "ks:ks_pop":144,
    "ks:ks_type":"VILLAGE",
    "name:eng_x_preferred":[
        "Ghaghra"
    ],
    "wof:name":"Ghaghra",
    "wof:placetype":"locality",
    "wof:population":144
},
  "geometry": {"coordinates":[87.073408,24.543244],"type":"Point"}
}