{
  "type": "Feature",
  "properties": {
    "gn:admin1_code":"36",
    "gn:admin2_code":"134.0",
    "gn:asciiname":"Milak",
    "gn:country_code":"IN",
    "gn:dem":215,
    "gn:feature_class":"P",
    "gn:feature_code":"PPL",
    "gn:name":"Milak",
    "gn:population":0,
    "gn:timezone":"Asia/Kolkata",
    "iso:country":"IN",
    "wof:name":"Milak",
    "wof:placetype":"locality"
},
  "geometry": {"coordinates":[78.64161999999997,29.23085],"type":"Point"}
}