{
  "type": "Feature",
  "properties": {
    "iso:country":"IN",
    "ks:ks_alt_nam":"ISHARA EAST",
    "ks:ks_name":"Ishara East",
    "ks:ks_pop":51,
    "ks:ks_type":"HABITATION",
    "ks:ks_uagg_main":0,
    "name:eng_x_preferred":[
        "Ishara East"
    ],
    "wof:name":"Ishara East",
    "wof:placetype":"neighbourhood",
    "wof:population":51
},
  "geometry": {"coordinates":[85.809917,26.280559],"type":"Point"}
}