{
  "type": "Feature",
  "properties": {
    "gn:admin1_code":"36.0",
    "gn:admin2_code":"135.0",
    "gn:asciiname":"Dharangpur",
    "gn:country_code":"IN",
    "gn:dem":209,
    "gn:feature_class":"P",
    "gn:feature_code":"PPL",
    "gn:name":"Dh\u0101rangpur",
    "gn:population":0,
    "gn:timezone":"Asia/Kolkata",
    "iso:country":"IN",
    "wof:name":"Dharangpur",
    "wof:placetype":"locality"
},
  "geometry": {"coordinates":[78.42518000000003,28.70215],"type":"Point"}
}