{
  "type": "Feature",
  "properties": {
    "gn:admin1_code":"2.0",
    "gn:admin2_code":"549.0",
    "gn:asciiname":"Ankabhupalapuram",
    "gn:country_code":"IN",
    "gn:dem":82,
    "gn:feature_class":"P",
    "gn:feature_code":"PPL",
    "gn:name":"Ankabh\u016bp\u0101lapuram",
    "gn:population":0,
    "gn:timezone":"Asia/Kolkata",
    "iso:country":"IN",
    "wof:name":"Ankabhupalapuram",
    "wof:placetype":"locality"
},
  "geometry": {"coordinates":[79.68980999999999,15.19657],"type":"Point"}
}