{
  "type": "Feature",
  "properties": {
    "iso:country":"IN",
    "ks:ks_name":"Pravasuni",
    "ks:ks_pop":128,
    "ks:ks_type":"VILLAGE",
    "name:eng_x_preferred":[
        "Pravasuni"
    ],
    "wof:name":"Pravasuni",
    "wof:placetype":"locality",
    "wof:population":128
},
  "geometry": {"coordinates":[85.14605,21.433321],"type":"Point"}
}