{
  "type": "Feature",
  "properties": {
    "gn:admin1_code":"36",
    "gn:admin2_code":"176.0",
    "gn:asciiname":"Bhiknapur",
    "gn:country_code":"IN",
    "gn:dem":114,
    "gn:feature_class":"P",
    "gn:feature_code":"PPL",
    "gn:name":"Bhikn\u0101pur",
    "gn:population":0,
    "gn:timezone":"Asia/Kolkata",
    "iso:country":"IN",
    "wof:name":"Bhiknapur",
    "wof:placetype":"locality"
},
  "geometry": {"coordinates":[81.35786,26.75275],"type":"Point"}
}