{
  "type": "Feature",
  "properties": {
    "gn:admin1_code":"39.0",
    "gn:admin2_code":"64.0",
    "gn:asciiname":"Jakh",
    "gn:country_code":"IN",
    "gn:dem":1289,
    "gn:feature_class":"P",
    "gn:feature_code":"PPL",
    "gn:name":"J\u0101kh",
    "gn:population":0,
    "gn:timezone":"Asia/Kolkata",
    "iso:country":"IN",
    "ks:ks_alt_nam":"J\u0101kh",
    "ks:ks_name":"Jakh",
    "ks:ks_type":"VILLAGE",
    "name:eng_x_preferred":[
        "Jakh"
    ],
    "name:eng_x_variant":[
        "J\u0101kh"
    ],
    "wof:name":"Jakh",
    "wof:placetype":"locality"
},
  "geometry": {"coordinates":[79.802975,29.522472],"type":"Point"}
}