{
  "type": "Feature",
  "properties": {
    "gn:admin1_code":"19.0",
    "gn:admin2_code":"582",
    "gn:asciiname":"Jangamakote",
    "gn:country_code":"IN",
    "gn:dem":886,
    "gn:feature_class":"P",
    "gn:feature_code":"PPL",
    "gn:name":"Jangamakote",
    "gn:population":0,
    "gn:timezone":"Asia/Kolkata",
    "iso:country":"IN",
    "name:ceb_x_preferred":[
        "Jangamakote"
    ],
    "name:swe_x_preferred":[
        "Jangamakote"
    ],
    "name:und_x_variant":[
        "Jangamkote"
    ],
    "name:urd_x_preferred":[
        "\u062c\u0646\u06af\u0645\u06a9\u0648\u062a\u06d2"
    ],
    "wof:name":"Jangamakote",
    "wof:placetype":"locality"
},
  "geometry": {"coordinates":[77.84868,13.26194],"type":"Point"}
}