{
  "type": "Feature",
  "properties": {
    "gn:admin1_code":"23.0",
    "gn:admin2_code":"53.0",
    "gn:asciiname":"Bhagtanwala",
    "gn:country_code":"IN",
    "gn:dem":242,
    "gn:feature_class":"P",
    "gn:feature_code":"PPL",
    "gn:name":"Bhagt\u0101nw\u0101la",
    "gn:population":0,
    "gn:timezone":"Asia/Kolkata",
    "iso:country":"IN",
    "name:und_x_variant":[
        "Bhagt\u0101nw\u0101la",
        "Bhagw\u0101npura"
    ],
    "wof:name":"Bhagtanwala",
    "wof:placetype":"neighbourhood"
},
  "geometry": {"coordinates":[75.68062999999999,30.44532],"type":"Point"}
}