{
  "type": "Feature",
  "properties": {
    "gn:admin1_code":"37",
    "gn:admin2_code":"409.0",
    "gn:asciiname":"Pahanda",
    "gn:country_code":"IN",
    "gn:dem":285,
    "gn:feature_class":"P",
    "gn:feature_code":"PPL",
    "gn:name":"Pahanda",
    "gn:population":0,
    "gn:timezone":"Asia/Kolkata",
    "iso:country":"IN",
    "wof:name":"Pahanda",
    "wof:placetype":"locality"
},
  "geometry": {"coordinates":[81.54255999999999,21.20735],"type":"Point"}
}