{
  "type": "Feature",
  "properties": {
    "iso:country":"IN",
    "ks:ks_name":"Balehithlu",
    "ks:ks_pop":22,
    "ks:ks_type":"HABITATION",
    "name:eng_x_preferred":[
        "Balehithlu"
    ],
    "wof:name":"Balehithlu",
    "wof:placetype":"locality",
    "wof:population":22
},
  "geometry": {"coordinates":[75.321107,13.435274],"type":"Point"}
}