{
  "type": "Feature",
  "properties": {
    "iso:country":"IN",
    "ks:ks_name":"Ilam Khedi",
    "ks:ks_pop":567,
    "ks:ks_type":"HABITATION",
    "name:eng_x_preferred":[
        "Ilam Khedi"
    ],
    "wof:name":"Ilam Khedi",
    "wof:placetype":"locality",
    "wof:population":567
},
  "geometry": {"coordinates":[75.913686,23.525955],"type":"Point"}
}