{
  "type": "Feature",
  "properties": {
    "iso:country":"IN",
    "ks:ks_name":"N.bhagat",
    "ks:ks_pop":101,
    "ks:ks_type":"HABITATION",
    "name:eng_x_preferred":[
        "N.bhagat"
    ],
    "wof:name":"N.bhagat",
    "wof:placetype":"locality",
    "wof:population":101
},
  "geometry": {"coordinates":[79.374514,27.016807],"type":"Point"}
}