{
  "type": "Feature",
  "properties": {
    "iso:country":"IN",
    "ks:ks_name":"Chatakpur",
    "ks:ks_pop":1500,
    "ks:ks_type":"VILLAGE",
    "name:eng_x_preferred":[
        "Chatakpur"
    ],
    "wof:name":"Chatakpur",
    "wof:placetype":"locality",
    "wof:population":1500
},
  "geometry": {"coordinates":[84.064819,23.446135],"type":"Point"}
}