{
  "type": "Feature",
  "properties": {
    "iso:country":"IN",
    "ks:ks_name":"Ipa Valsa",
    "ks:ks_pop":880,
    "ks:ks_type":"HABITATION",
    "name:eng_x_preferred":[
        "Ipa Valsa"
    ],
    "wof:name":"Ipa Valsa",
    "wof:placetype":"locality",
    "wof:population":880
},
  "geometry": {"coordinates":[83.00915500000001,18.492081],"type":"Point"}
}