{
  "type": "Feature",
  "properties": {
    "iso:country":"IN",
    "ks:ks_name":"Velakkaladi",
    "ks:ks_pop":120,
    "ks:ks_type":"HABITATION",
    "name:eng_x_preferred":[
        "Velakkaladi"
    ],
    "wof:name":"Velakkaladi",
    "wof:placetype":"locality",
    "wof:population":120
},
  "geometry": {"coordinates":[76.262855,11.53168],"type":"Point"}
}