{
  "type": "Feature",
  "properties": {
    "iso:country":"IN",
    "ks:ks_name":"Vizvanpar",
    "ks:ks_pop":711,
    "ks:ks_type":"HABITATION",
    "ks:ks_uagg_main":0,
    "name:eng_x_preferred":[
        "Vizvanpar"
    ],
    "wof:name":"Vizvanpar",
    "wof:placetype":"locality",
    "wof:population":711
},
  "geometry": {"coordinates":[85.517489,25.161559],"type":"Point"}
}