{
  "type": "Feature",
  "properties": {
    "iso:country":"IN",
    "ks:ks_name":"Bhuali Tola",
    "ks:ks_pop":754,
    "ks:ks_type":"HABITATION",
    "ks:ks_uagg_main":0,
    "name:eng_x_preferred":[
        "Bhuali Tola"
    ],
    "wof:name":"Bhuali Tola",
    "wof:placetype":"neighbourhood",
    "wof:population":754
},
  "geometry": {"coordinates":[84.521815,26.7569],"type":"Point"}
}