{
  "type": "Feature",
  "properties": {
    "gn:admin1_code":"19.0",
    "gn:admin2_code":"572",
    "gn:asciiname":"Mahatma Gandhi Rd",
    "gn:country_code":"IN",
    "gn:dem":922,
    "gn:feature_class":"P",
    "gn:feature_code":"PPL",
    "gn:name":"Mahatma Gandhi Rd",
    "gn:population":0,
    "gn:timezone":"Asia/Kolkata",
    "iso:country":"IN",
    "wof:name":"Mahatma Gandhi Rd",
    "wof:placetype":"neighbourhood"
},
  "geometry": {"coordinates":[77.60345,12.97627],"type":"Point"}
}