{
  "type": "Feature",
  "properties": {
    "iso:country":"IN",
    "ks:ks_name":"Atanaka",
    "ks:ks_pop":172,
    "ks:ks_type":"VILLAGE",
    "name:eng_x_preferred":[
        "Atanaka"
    ],
    "wof:name":"Atanaka",
    "wof:placetype":"locality",
    "wof:population":172
},
  "geometry": {"coordinates":[85.270347,21.504107],"type":"Point"}
}