{
  "type": "Feature",
  "properties": {
    "gn:admin1_code":"2.0",
    "gn:admin2_code":"551.0",
    "gn:asciiname":"Madigamaddelavallapalle",
    "gn:country_code":"IN",
    "gn:dem":388,
    "gn:feature_class":"P",
    "gn:feature_code":"PPL",
    "gn:name":"Madigamaddelav\u0101llapalle",
    "gn:population":0,
    "gn:timezone":"Asia/Kolkata",
    "iso:country":"IN",
    "wof:name":"Madigamaddelavallapalle",
    "wof:placetype":"locality"
},
  "geometry": {"coordinates":[78.91668,14.06507],"type":"Point"}
}