{
  "type": "Feature",
  "properties": {
    "gn:admin1_code":"34.0",
    "gn:admin2_code":"219.0",
    "gn:asciiname":"Hasanpura",
    "gn:country_code":"IN",
    "gn:dem":60,
    "gn:feature_class":"P",
    "gn:feature_code":"PPL",
    "gn:name":"Hasanpura",
    "gn:population":0,
    "gn:timezone":"Asia/Kolkata",
    "iso:country":"IN",
    "ks:ks_name":"Hasanpura",
    "ks:ks_pop":3060,
    "ks:ks_type":"VILLAGE",
    "ks:ks_uagg_main":0,
    "name:ara_x_preferred":[
        "\u062d\u0633\u0646 \u0628\u0648\u0631\u0627"
    ],
    "name:ben_bn_x_preferred":[
        "\u09b9\u09be\u09b8\u09be\u09a8\u09aa\u09c1\u09b0\u09be"
    ],
    "name:ben_in_x_preferred":[
        "\u09b9\u09be\u09b8\u09be\u09a8\u09aa\u09c1\u09b0\u09be"
    ],
    "name:bih_x_preferred":[
        "\u0939\u0938\u0928\u092a\u0941\u0930\u093e"
    ],
    "name:eng_x_preferred":[
        "Hasanpura"
    ],
    "name:guj_x_preferred":[
        "\u0ab9\u0ab8\u0aa8\u0aaa\u0ac1\u0ab0\u0abe"
    ],
    "name:hin_x_preferred":[
        "\u0939\u0938\u0928\u092a\u0941\u0930\u093e"
    ],
    "name:hin_x_variant":[
        "\u0939\u0938\u0928\u092a\u0941\u0930 \u092a\u094d\u0930\u0916\u0923\u094d\u0921"
    ],
    "name:kan_x_preferred":[
        "\u0cb9\u0cb8\u0ca8\u0ccd"
    ],
    "name:mal_x_preferred":[
        "\u0d39\u0d38\u0d7b\u0d2a\u0d41\u0d30"
    ],
    "name:mar_x_preferred":[
        "\u0939\u0938\u0928\u092a\u0941\u0930\u093e"
    ],
    "name:pan_x_preferred":[
        "\u0a39\u0a38\u0a28\u0a2a\u0a41\u0a30\u0a3e"
    ],
    "name:tam_x_preferred":[
        "\u0bb9\u0bbe\u0b9a\u0ba9\u0bcd\u0baa\u0bc1\u0bb0\u0bbe"
    ],
    "name:tel_x_preferred":[
        "\u0c39\u0c38\u0c28\u0c4d"
    ],
    "name:urd_x_preferred":[
        "\u062d\u0633\u0646 \u067e\u0648\u0631\u06c1"
    ],
    "wof:name":"Hasanpura",
    "wof:placetype":"neighbourhood",
    "wof:population":3060
},
  "geometry": {"coordinates":[84.87029200000001,25.954138],"type":"Point"}
}