{
  "type": "Feature",
  "properties": {
    "iso:country":"IN",
    "ks:ks_alt_nam":"Manal\u016br",
    "ks:ks_name":"Manalur",
    "ks:ks_pop":3267,
    "ks:ks_type":"VILLAGE",
    "name:eng_x_preferred":[
        "Manalur"
    ],
    "name:eng_x_variant":[
        "Manal\u016br"
    ],
    "wof:name":"Manalur",
    "wof:placetype":"locality",
    "wof:population":3267
},
  "geometry": {"coordinates":[77.752701,10.301792],"type":"Point"}
}