{
  "type": "Feature",
  "properties": {
    "iso:country":"IN",
    "ks:ks_name":"Garda",
    "ks:ks_pop":209,
    "ks:ks_type":"VILLAGE",
    "name:eng_x_preferred":[
        "Garda"
    ],
    "wof:name":"Garda",
    "wof:placetype":"locality",
    "wof:population":209
},
  "geometry": {"coordinates":[86.95499,24.448308],"type":"Point"}
}