{
  "type": "Feature",
  "properties": {
    "iso:country":"IN",
    "ks:ks_name":"Enmooru",
    "ks:ks_pop":118,
    "ks:ks_type":"HABITATION",
    "name:eng_x_preferred":[
        "Enmooru"
    ],
    "wof:name":"Enmooru",
    "wof:placetype":"locality",
    "wof:population":118
},
  "geometry": {"coordinates":[75.380092,12.724277],"type":"Point"}
}