{
  "type": "Feature",
  "properties": {
    "iso:country":"IN",
    "ks:ks_name":"Vasani",
    "ks:ks_pop":30,
    "ks:ks_type":"VILLAGE",
    "name:eng_x_preferred":[
        "Vasani"
    ],
    "wof:name":"Vasani",
    "wof:placetype":"locality",
    "wof:population":30
},
  "geometry": {"coordinates":[73.085583,23.627667],"type":"Point"}
}