{
  "type": "Feature",
  "properties": {
    "iso:country":"IN",
    "ks:ks_name":"Bind Tola",
    "ks:ks_pop":396,
    "ks:ks_type":"HABITATION",
    "name:eng_x_preferred":[
        "Bind Tola"
    ],
    "wof:name":"Bind Tola",
    "wof:placetype":"locality",
    "wof:population":396
},
  "geometry": {"coordinates":[84.618589,25.841034],"type":"Point"}
}