{
  "type": "Feature",
  "properties": {
    "iso:country":"IN",
    "ks:ks_name":"Ghodabandha",
    "ks:ks_pop":180,
    "ks:ks_type":"VILLAGE",
    "name:eng_x_preferred":[
        "Ghodabandha"
    ],
    "wof:name":"Ghodabandha",
    "wof:placetype":"locality",
    "wof:population":180
},
  "geometry": {"coordinates":[86.386027,22.103619],"type":"Point"}
}