{
  "type": "Feature",
  "properties": {
    "iso:country":"IN",
    "ks:ks_name":"Naturbona",
    "ks:ks_pop":166,
    "ks:ks_type":"HABITATION",
    "ks:ks_uagg_main":0,
    "name:eng_x_preferred":[
        "Naturbona"
    ],
    "wof:name":"Naturbona",
    "wof:placetype":"neighbourhood",
    "wof:population":166
},
  "geometry": {"coordinates":[87.711681,23.816276],"type":"Point"}
}