{
  "type": "Feature",
  "properties": {
    "gn:admin1_code":"12.0",
    "gn:admin2_code":"005",
    "gn:asciiname":"Hanekutr",
    "gn:country_code":"IN",
    "gn:dem":2240,
    "gn:feature_class":"P",
    "gn:feature_code":"PPL",
    "gn:name":"Hanekutr",
    "gn:population":0,
    "gn:timezone":"Asia/Kolkata",
    "iso:country":"IN",
    "wof:name":"Hanekutr",
    "wof:placetype":"locality"
},
  "geometry": {"coordinates":[74.30181999999998,33.9049],"type":"Point"}
}