{
  "type": "Feature",
  "properties": {
    "iso:country":"IN",
    "ks:ks_name":"Songaon",
    "ks:ks_pop":0,
    "ks:ks_type":"VILLAGE",
    "name:eng_x_preferred":[
        "Songaon"
    ],
    "wof:name":"Songaon",
    "wof:placetype":"locality",
    "wof:population":0
},
  "geometry": {"coordinates":[77.907636,21.2484],"type":"Point"}
}