{
  "type": "Feature",
  "properties": {
    "gn:admin1_code":"34.0",
    "gn:admin2_code":"220.0",
    "gn:asciiname":"Makundpur Bhath",
    "gn:country_code":"IN",
    "gn:dem":53,
    "gn:feature_class":"P",
    "gn:feature_code":"PPL",
    "gn:name":"Makundpur Bh\u0101th",
    "gn:population":0,
    "gn:timezone":"Asia/Kolkata",
    "iso:country":"IN",
    "ks:ks_name":"Mukundpur Bhath",
    "ks:ks_pop":1007,
    "ks:ks_type":"VILLAGE",
    "name:eng_x_preferred":[
        "Mukundpur Bhath"
    ],
    "name:eng_x_variant":[
        "Makundpur Bhath"
    ],
    "wof:name":"Mukundpur Bhath",
    "wof:placetype":"locality",
    "wof:population":1007
},
  "geometry": {"coordinates":[85.475522,25.70593],"type":"Point"}
}