{
  "type": "Feature",
  "properties": {
    "iso:country":"IN",
    "ks:ks_name":"Gobindabasan",
    "ks:ks_pop":803,
    "ks:ks_type":"VILLAGE",
    "ks:ks_uagg_main":0,
    "name:eng_x_preferred":[
        "Gobindabasan"
    ],
    "wof:name":"Gobindabasan",
    "wof:placetype":"neighbourhood",
    "wof:population":803
},
  "geometry": {"coordinates":[87.52992999999999,21.626338],"type":"Point"}
}