{
  "type": "Feature",
  "properties": {
    "iso:country":"IN",
    "ks:ks_alt_nam":"kitkitan",
    "ks:ks_name":"Kitkitan",
    "ks:ks_pop":200,
    "ks:ks_type":"HABITATION",
    "name:eng_x_preferred":[
        "Kitkitan"
    ],
    "wof:name":"Kitkitan",
    "wof:placetype":"locality",
    "wof:population":200
},
  "geometry": {"coordinates":[81.84224,25.57206],"type":"Point"}
}