{
  "type": "Feature",
  "properties": {
    "gn:admin1_code":"2.0",
    "gn:admin2_code":"544.0",
    "gn:asciiname":"Vagepalle",
    "gn:country_code":"IN",
    "gn:dem":954,
    "gn:feature_class":"P",
    "gn:feature_code":"PPL",
    "gn:name":"Vagepalle",
    "gn:population":0,
    "gn:timezone":"Asia/Kolkata",
    "iso:country":"IN",
    "ks:ks_alt_nam":"vakapalle",
    "ks:ks_name":"Vakapalle",
    "ks:ks_pop":77,
    "ks:ks_type":"HABITATION",
    "name:eng_x_preferred":[
        "Vakapalle"
    ],
    "name:eng_x_variant":[
        "Vagepalle"
    ],
    "wof:name":"Vakapalle",
    "wof:placetype":"locality",
    "wof:population":77
},
  "geometry": {"coordinates":[82.620569,18.06619],"type":"Point"}
}