{
  "type": "Feature",
  "properties": {
    "iso:country":"IN",
    "ks:ks_name":"Chibarti",
    "ks:ks_pop":522,
    "ks:ks_type":"HABITATION",
    "name:eng_x_preferred":[
        "Chibarti"
    ],
    "wof:name":"Chibarti",
    "wof:placetype":"locality",
    "wof:population":522
},
  "geometry": {"coordinates":[85.081549,23.609258],"type":"Point"}
}