{
  "type": "Feature",
  "properties": {
    "gn:admin1_code":"19.0",
    "gn:admin2_code":"574.0",
    "gn:asciiname":"Surakodu",
    "gn:country_code":"IN",
    "gn:dem":1030,
    "gn:feature_class":"P",
    "gn:feature_code":"PPL",
    "gn:name":"Surakodu",
    "gn:population":0,
    "gn:timezone":"Asia/Kolkata",
    "iso:country":"IN",
    "wof:name":"Surakodu",
    "wof:placetype":"locality"
},
  "geometry": {"coordinates":[75.84454000000002,13.06258],"type":"Point"}
}