{
  "type": "Feature",
  "properties": {
    "gn:admin1_code":"19.0",
    "gn:admin2_code":"574.0",
    "gn:asciiname":"Surakodu",
    "gn:country_code":"IN",
    "gn:dem":1030,
    "gn:feature_class":"P",
    "gn:feature_code":"PPL",
    "gn:name":"Surakodu",
    "gn:population":0,
    "gn:timezone":"Asia/Kolkata",
    "iso:country":"IN",
    "ks:ks_name":"Surukodu",
    "ks:ks_pop":155,
    "ks:ks_type":"VILLAGE",
    "name:eng_x_preferred":[
        "Surukodu"
    ],
    "name:eng_x_variant":[
        "Surakodu"
    ],
    "wof:name":"Surukodu",
    "wof:placetype":"locality",
    "wof:population":155
},
  "geometry": {"coordinates":[75.845581,13.061797],"type":"Point"}
}