{
  "type": "Feature",
  "properties": {
    "gn:admin1_code":"36",
    "gn:admin2_code":"194.0",
    "gn:asciiname":"Chak Nohar",
    "gn:country_code":"IN",
    "gn:dem":87,
    "gn:feature_class":"P",
    "gn:feature_code":"PPL",
    "gn:name":"Chak Nohar",
    "gn:population":0,
    "gn:timezone":"Asia/Kolkata",
    "iso:country":"IN",
    "ks:ks_name":"Chak Nohar",
    "ks:ks_type":"VILLAGE",
    "name:eng_x_preferred":[
        "Chak Nohar"
    ],
    "wof:name":"Chak Nohar",
    "wof:placetype":"locality"
},
  "geometry": {"coordinates":[82.57650099999999,26.033324],"type":"Point"}
}