{
  "type": "Feature",
  "properties": {
    "gn:admin1_code":"03",
    "gn:admin2_code":"301.0",
    "gn:asciiname":"Raipur",
    "gn:country_code":"IN",
    "gn:dem":31,
    "gn:feature_class":"P",
    "gn:feature_code":"PPL",
    "gn:name":"Raipur",
    "gn:population":0,
    "gn:timezone":"Asia/Kolkata",
    "iso:country":"IN",
    "wof:name":"Raipur",
    "wof:placetype":"locality"
},
  "geometry": {"coordinates":[89.83795000000001,26.14094],"type":"Point"}
}