{
  "type": "Feature",
  "properties": {
    "gn:admin1_code":"13.0",
    "gn:admin2_code":"592.0",
    "gn:asciiname":"Pallikkara",
    "gn:country_code":"IN",
    "gn:dem":11,
    "gn:feature_class":"P",
    "gn:feature_code":"PPL",
    "gn:name":"Pallikkara",
    "gn:population":0,
    "gn:timezone":"Asia/Kolkata",
    "iso:country":"IN",
    "ks:ks_name":"Pallikkara\t",
    "ks:ks_pop":921,
    "ks:ks_type":"HABITATION",
    "name:eng_x_preferred":[
        "Pallikkara\t"
    ],
    "name:eng_x_variant":[
        "Pallikkara"
    ],
    "wof:name":"Pallikkara\t",
    "wof:placetype":"locality",
    "wof:population":921
},
  "geometry": {"coordinates":[76.041726,10.724975],"type":"Point"}
}