{
  "type": "Feature",
  "properties": {
    "gn:admin1_code":"21.0",
    "gn:admin2_code":"399.0",
    "gn:asciiname":"Bapanapalle",
    "gn:country_code":"IN",
    "gn:dem":160,
    "gn:feature_class":"P",
    "gn:feature_code":"PPL",
    "gn:name":"B\u0101panapalle",
    "gn:population":0,
    "gn:timezone":"Asia/Kolkata",
    "iso:country":"IN",
    "wof:name":"Bapanapalle",
    "wof:placetype":"locality"
},
  "geometry": {"coordinates":[81.85361999999998,18.11818],"type":"Point"}
}