{
  "type": "Feature",
  "properties": {
    "iso:country":"IN",
    "ks:ks_name":"Khemaipatti",
    "ks:ks_pop":2173,
    "ks:ks_type":"VILLAGE",
    "name:eng_x_preferred":[
        "Khemaipatti"
    ],
    "wof:name":"Khemaipatti",
    "wof:placetype":"locality",
    "wof:population":2173
},
  "geometry": {"coordinates":[85.365968,26.242281],"type":"Point"}
}