{
  "type": "Feature",
  "properties": {
    "iso:country":"IN",
    "ks:ks_name":"Forest Office",
    "ks:ks_pop":296,
    "ks:ks_type":"HABITATION",
    "ks:ks_uagg_main":0,
    "name:eng_x_preferred":[
        "Forest Office"
    ],
    "wof:name":"Forest Office",
    "wof:placetype":"neighbourhood",
    "wof:population":296
},
  "geometry": {"coordinates":[76.421662,10.300725],"type":"Point"}
}