{
  "type": "Feature",
  "properties": {
    "iso:country":"IN",
    "ks:ks_name":"Masampally",
    "ks:ks_pop":224,
    "ks:ks_type":"HABITATION",
    "name:eng_x_preferred":[
        "Masampally"
    ],
    "wof:name":"Masampally",
    "wof:placetype":"locality",
    "wof:population":224
},
  "geometry": {"coordinates":[80.052648,17.836833],"type":"Point"}
}