{
  "type": "Feature",
  "properties": {
    "gn:admin1_code":"12.0",
    "gn:asciiname":"Fateh ka Dera",
    "gn:country_code":"IN",
    "gn:dem":2779,
    "gn:feature_class":"P",
    "gn:feature_code":"PPL",
    "gn:name":"Fateh ka Dera",
    "gn:population":0,
    "gn:timezone":"Asia/Karachi",
    "iso:country":"IN",
    "wof:name":"Fateh ka Dera",
    "wof:placetype":"locality"
},
  "geometry": {"coordinates":[73.95013,34.01949],"type":"Point"}
}