{
  "type": "Feature",
  "properties": {
    "iso:country":"IN",
    "ks:ks_alt_nam":"Nimraha khas",
    "ks:ks_name":"Nimraha Khas",
    "ks:ks_pop":195,
    "ks:ks_type":"HABITATION",
    "name:eng_x_preferred":[
        "Nimraha Khas"
    ],
    "wof:name":"Nimraha Khas",
    "wof:placetype":"locality",
    "wof:population":195
},
  "geometry": {"coordinates":[84.783717,23.112514],"type":"Point"}
}