{
  "type": "Feature",
  "properties": {
    "gn:admin1_code":"19",
    "gn:admin2_code":"559.0",
    "gn:asciiname":"Pamankallur",
    "gn:country_code":"IN",
    "gn:dem":474,
    "gn:feature_class":"P",
    "gn:feature_code":"PPL",
    "gn:name":"P\u0101mankall\u016br",
    "gn:population":0,
    "gn:timezone":"Asia/Kolkata",
    "iso:country":"IN",
    "name:und_x_variant":[
        "Ramankallur",
        "P\u0101mankall\u016br"
    ],
    "wof:name":"Pamankallur",
    "wof:placetype":"locality"
},
  "geometry": {"coordinates":[76.67803000000001,16.10093],"type":"Point"}
}