{
  "type": "Feature",
  "properties": {
    "iso:country":"IN",
    "ks:ks_name":"Huvenahalli",
    "ks:ks_pop":201,
    "ks:ks_type":"HABITATION",
    "name:eng_x_preferred":[
        "Huvenahalli"
    ],
    "wof:name":"Huvenahalli",
    "wof:placetype":"locality",
    "wof:population":201
},
  "geometry": {"coordinates":[75.802955,13.445496],"type":"Point"}
}