{
  "type": "Feature",
  "properties": {
    "iso:country":"IN",
    "ks:ks_name":"Kuteelu",
    "ks:ks_pop":221,
    "ks:ks_type":"HABITATION",
    "name:eng_x_preferred":[
        "Kuteelu"
    ],
    "wof:name":"Kuteelu",
    "wof:placetype":"locality",
    "wof:population":221
},
  "geometry": {"coordinates":[75.089642,13.021979],"type":"Point"}
}