{
  "type": "Feature",
  "properties": {
    "gn:admin1_code":"2.0",
    "gn:admin2_code":"543.0",
    "gn:asciiname":"Ippalagudivalasa",
    "gn:country_code":"IN",
    "gn:dem":370,
    "gn:feature_class":"P",
    "gn:feature_code":"PPL",
    "gn:name":"Ippalagudivalasa",
    "gn:population":0,
    "gn:timezone":"Asia/Kolkata",
    "iso:country":"IN",
    "wof:name":"Ippalagudivalasa",
    "wof:placetype":"locality"
},
  "geometry": {"coordinates":[83.06249,18.44723],"type":"Point"}
}