{
  "type": "Feature",
  "properties": {
    "iso:country":"IN",
    "ks:ks_name":"Pure Budhram",
    "ks:ks_pop":210,
    "ks:ks_type":"HABITATION",
    "name:eng_x_preferred":[
        "Pure Budhram"
    ],
    "wof:name":"Pure Budhram",
    "wof:placetype":"locality",
    "wof:population":210
},
  "geometry": {"coordinates":[81.569591,26.439974],"type":"Point"}
}