{
  "type": "Feature",
  "properties": {
    "iso:country":"IN",
    "ks:ks_name":"Changa Ppara",
    "ks:ks_pop":654,
    "ks:ks_type":"HABITATION",
    "name:eng_x_preferred":[
        "Changa Ppara"
    ],
    "wof:name":"Changa Ppara",
    "wof:placetype":"locality",
    "wof:population":654
},
  "geometry": {"coordinates":[76.965318,9.056976],"type":"Point"}
}