{
  "type": "Feature",
  "properties": {
    "iso:country":"IN",
    "ks:ks_name":"Bhagiram Gaon",
    "ks:ks_pop":2461,
    "ks:ks_type":"VILLAGE",
    "ks:ks_uagg_main":0,
    "name:eng_x_preferred":[
        "Bhagiram Gaon"
    ],
    "wof:name":"Bhagiram Gaon",
    "wof:placetype":"neighbourhood",
    "wof:population":2461
},
  "geometry": {"coordinates":[92.83793900000001,26.135033],"type":"Point"}
}