{
  "type": "Feature",
  "properties": {
    "iso:country":"IN",
    "ks:ks_name":"Patharkhunya",
    "ks:ks_pop":162,
    "ks:ks_type":"HABITATION",
    "name:eng_x_preferred":[
        "Patharkhunya"
    ],
    "wof:name":"Patharkhunya",
    "wof:placetype":"locality",
    "wof:population":162
},
  "geometry": {"coordinates":[86.69002999999999,23.061575],"type":"Point"}
}