{
  "type": "Feature",
  "properties": {
    "iso:country":"IN",
    "ks:ks_name":"Dilippur",
    "ks:ks_pop":1186,
    "ks:ks_type":"VILLAGE",
    "ks:ks_uagg_main":0,
    "name:eng_x_preferred":[
        "Dilippur"
    ],
    "wof:name":"Dilippur",
    "wof:placetype":"neighbourhood",
    "wof:population":1186
},
  "geometry": {"coordinates":[80.99445900000001,21.451815],"type":"Point"}
}