{
  "type": "Feature",
  "properties": {
    "iso:country":"IN",
    "ks:ks_name":"Kindopada",
    "ks:ks_pop":76,
    "ks:ks_type":"HABITATION",
    "name:eng_x_preferred":[
        "Kindopada"
    ],
    "wof:name":"Kindopada",
    "wof:placetype":"locality",
    "wof:population":76
},
  "geometry": {"coordinates":[84.64727600000001,22.14339],"type":"Point"}
}