{
  "type": "Feature",
  "properties": {
    "iso:country":"IN",
    "ks:ks_name":"Dabba",
    "ks:ks_pop":1676,
    "ks:ks_type":"HABITATION",
    "name:eng_x_preferred":[
        "Dabba"
    ],
    "wof:name":"Dabba",
    "wof:placetype":"locality",
    "wof:population":1676
},
  "geometry": {"coordinates":[79.69084100000001,19.453564],"type":"Point"}
}