{
  "type": "Feature",
  "properties": {
    "iso:country":"IN",
    "ks:ks_name":"Jadhav Wasti",
    "ks:ks_pop":188,
    "ks:ks_type":"HABITATION",
    "name:eng_x_preferred":[
        "Jadhav Wasti"
    ],
    "wof:name":"Jadhav Wasti",
    "wof:placetype":"locality",
    "wof:population":188
},
  "geometry": {"coordinates":[75.22137600000001,17.977759],"type":"Point"}
}