{
  "type": "Feature",
  "properties": {
    "gn:admin1_code":"16",
    "gn:admin2_code":"516.0",
    "gn:asciiname":"Patode",
    "gn:country_code":"IN",
    "gn:dem":571,
    "gn:feature_class":"P",
    "gn:feature_code":"PPL",
    "gn:name":"P\u0101tode",
    "gn:population":0,
    "gn:timezone":"Asia/Kolkata",
    "iso:country":"IN",
    "name:und_x_variant":[
        "P\u0101tode",
        "Patode"
    ],
    "wof:name":"Patode",
    "wof:placetype":"locality"
},
  "geometry": {"coordinates":[74.36434,20.11842],"type":"Point"}
}