{
  "type": "Feature",
  "properties": {
    "iso:country":"IN",
    "ks:ks_name":"Patha Ippalagadda",
    "ks:ks_pop":180,
    "ks:ks_type":"HABITATION",
    "name:eng_x_preferred":[
        "Patha Ippalagadda"
    ],
    "wof:name":"Patha Ippalagadda",
    "wof:placetype":"locality",
    "wof:population":180
},
  "geometry": {"coordinates":[80.152632,18.21425],"type":"Point"}
}