{
  "type": "Feature",
  "properties": {
    "iso:country":"IN",
    "ks:ks_name":"Jamble",
    "ks:ks_pop":324,
    "ks:ks_type":"HABITATION",
    "name:eng_x_preferred":[
        "Jamble"
    ],
    "wof:name":"Jamble",
    "wof:placetype":"locality",
    "wof:population":324
},
  "geometry": {"coordinates":[74.87915099999999,13.653377],"type":"Point"}
}