{
  "type": "Feature",
  "properties": {
    "iso:country":"IN",
    "ks:ks_name":"Melinkeri",
    "ks:ks_pop":448,
    "ks:ks_type":"HABITATION",
    "name:eng_x_preferred":[
        "Melinkeri"
    ],
    "wof:name":"Melinkeri",
    "wof:placetype":"locality",
    "wof:population":448
},
  "geometry": {"coordinates":[74.366732,14.522572],"type":"Point"}
}