{
  "type": "Feature",
  "properties": {
    "gn:admin1_code":"16",
    "gn:admin2_code":"511.0",
    "gn:asciiname":"Bolsa Khurd",
    "gn:country_code":"IN",
    "gn:dem":361,
    "gn:feature_class":"P",
    "gn:feature_code":"PPL",
    "gn:name":"Bolsa Khurd",
    "gn:population":0,
    "gn:timezone":"Asia/Kolkata",
    "iso:country":"IN",
    "ks:ks_name":"Bolsa Khurd",
    "ks:ks_type":"VILLAGE",
    "name:eng_x_preferred":[
        "Bolsa Khurd"
    ],
    "wof:name":"Bolsa Khurd",
    "wof:placetype":"locality"
},
  "geometry": {"coordinates":[77.71042799999999,18.990042],"type":"Point"}
}