{
  "type": "Feature",
  "properties": {
    "gn:admin1_code":"35.0",
    "gn:admin2_code":"457.0",
    "gn:asciiname":"Parsatola",
    "gn:country_code":"IN",
    "gn:dem":577,
    "gn:feature_class":"P",
    "gn:feature_code":"PPL",
    "gn:name":"Pars\u0101tol\u0101",
    "gn:population":0,
    "gn:timezone":"Asia/Kolkata",
    "iso:country":"IN",
    "wof:name":"Parsatola",
    "wof:placetype":"locality"
},
  "geometry": {"coordinates":[80.69368,22.15391],"type":"Point"}
}