{
  "type": "Feature",
  "properties": {
    "gn:admin1_code":"11",
    "gn:admin2_code":"23.0",
    "gn:asciiname":"Chamel Andraru",
    "gn:country_code":"IN",
    "gn:dem":1031,
    "gn:feature_class":"P",
    "gn:feature_code":"PPL",
    "gn:name":"Chamel Andr\u0101ru",
    "gn:population":0,
    "gn:timezone":"Asia/Kolkata",
    "iso:country":"IN",
    "wof:name":"Chamel Andraru",
    "wof:placetype":"locality"
},
  "geometry": {"coordinates":[76.1756,32.59069],"type":"Point"}
}