{
  "type": "Feature",
  "properties": {
    "iso:country":"IN",
    "ks:ks_name":"5 BPM",
    "ks:ks_pop":37,
    "ks:ks_type":"VILLAGE",
    "name:eng_x_preferred":[
        "5 BPM"
    ],
    "wof:name":"5 BPM",
    "wof:placetype":"locality",
    "wof:population":37
},
  "geometry": {"coordinates":[74.493424,29.292532],"type":"Point"}
}