{
  "type": "Feature",
  "properties": {
    "iso:country":"IN",
    "ks:ks_name":"Narayanapara",
    "ks:ks_pop":772,
    "ks:ks_type":"VILLAGE",
    "ks:ks_uagg_main":0,
    "name:eng_x_preferred":[
        "Narayanapara"
    ],
    "wof:name":"Narayanapara",
    "wof:placetype":"neighbourhood",
    "wof:population":772
},
  "geometry": {"coordinates":[82.369187,26.169223],"type":"Point"}
}