{
  "type": "Feature",
  "properties": {
    "iso:country":"IN",
    "ks:ks_name":"Tariyapara",
    "ks:ks_pop":100,
    "ks:ks_type":"HABITATION",
    "name:eng_x_preferred":[
        "Tariyapara"
    ],
    "wof:name":"Tariyapara",
    "wof:placetype":"locality",
    "wof:population":100
},
  "geometry": {"coordinates":[80.782674,20.570865],"type":"Point"}
}