{
  "type": "Feature",
  "properties": {
    "iso:country":"IN",
    "ks:ks_alt_nam":"P\u0101rdi",
    "ks:ks_name":"Pardi",
    "ks:ks_pop":179,
    "ks:ks_type":"VILLAGE",
    "name:eng_x_preferred":[
        "Pardi"
    ],
    "name:eng_x_variant":[
        "P\u0101rdi"
    ],
    "wof:name":"Pardi",
    "wof:placetype":"locality",
    "wof:population":179
},
  "geometry": {"coordinates":[78.889371,21.395978],"type":"Point"}
}