{
  "type": "Feature",
  "properties": {
    "iso:country":"IN",
    "ks:ks_name":"Karmatungri",
    "ks:ks_pop":1504,
    "ks:ks_type":"HABITATION",
    "name:eng_x_preferred":[
        "Karmatungri"
    ],
    "wof:name":"Karmatungri",
    "wof:placetype":"locality",
    "wof:population":1504
},
  "geometry": {"coordinates":[86.066244,23.926928],"type":"Point"}
}