{
  "type": "Feature",
  "properties": {
    "gn:admin1_code":"39.0",
    "gn:admin2_code":"65.0",
    "gn:asciiname":"Kumai Kora",
    "gn:country_code":"IN",
    "gn:dem":1202,
    "gn:feature_class":"P",
    "gn:feature_code":"PPL",
    "gn:name":"Kumai Kora",
    "gn:population":0,
    "gn:timezone":"Asia/Kolkata",
    "iso:country":"IN",
    "wof:name":"Kumai Kora",
    "wof:placetype":"locality"
},
  "geometry": {"coordinates":[79.86201,29.44044],"type":"Point"}
}