{
  "type": "Feature",
  "properties": {
    "gn:admin1_code":"12.0",
    "gn:admin2_code":"021",
    "gn:asciiname":"Pindori Manhasan",
    "gn:country_code":"IN",
    "gn:dem":286,
    "gn:feature_class":"P",
    "gn:feature_code":"PPL",
    "gn:name":"Pindori Manh\u0101s\u0101n",
    "gn:population":0,
    "gn:timezone":"Asia/Kolkata",
    "iso:country":"IN",
    "wof:name":"Pindori Manhasan",
    "wof:placetype":"locality"
},
  "geometry": {"coordinates":[74.86238,32.56041],"type":"Point"}
}