{
  "type": "Feature",
  "properties": {
    "gn:admin1_code":"36",
    "gn:admin2_code":"200.0",
    "gn:asciiname":"Bura",
    "gn:country_code":"IN",
    "gn:dem":296,
    "gn:feature_class":"P",
    "gn:feature_code":"PPL",
    "gn:name":"Bura",
    "gn:population":0,
    "gn:timezone":"Asia/Kolkata",
    "iso:country":"IN",
    "name:ceb_x_preferred":[
        "Bura"
    ],
    "name:deu_x_preferred":[
        "Bura"
    ],
    "name:fra_x_preferred":[
        "Bura"
    ],
    "name:hrv_x_preferred":[
        "Bura"
    ],
    "name:rus_x_preferred":[
        "\u0411\u0443\u0440\u0430"
    ],
    "name:srp_x_preferred":[
        "Bura"
    ],
    "name:swe_x_preferred":[
        "Bura"
    ],
    "name:ukr_x_preferred":[
        "\u0411\u0443\u0440\u0430"
    ],
    "name:vie_x_preferred":[
        "Bura"
    ],
    "wof:name":"Bura",
    "wof:placetype":"locality"
},
  "geometry": {"coordinates":[82.92345999999998,24.04116],"type":"Point"}
}