{
  "type": "Feature",
  "properties": {
    "iso:country":"IN",
    "ks:ks_alt_nam":"Bhaw\u0101nipur",
    "ks:ks_name":"Bhawanipur",
    "ks:ks_type":"VILLAGE",
    "name:eng_x_preferred":[
        "Bhawanipur"
    ],
    "name:eng_x_variant":[
        "Bhaw\u0101nipur"
    ],
    "wof:name":"Bhawanipur",
    "wof:placetype":"locality"
},
  "geometry": {"coordinates":[83.077781,26.309846],"type":"Point"}
}