{
  "type": "Feature",
  "properties": {
    "gn:admin1_code":"28.0",
    "gn:admin2_code":"332.0",
    "gn:asciiname":"Mahendrapur",
    "gn:country_code":"IN",
    "gn:dem":38,
    "gn:feature_class":"P",
    "gn:feature_code":"PPL",
    "gn:name":"Mahendrapur",
    "gn:population":0,
    "gn:timezone":"Asia/Kolkata",
    "iso:country":"IN",
    "wof:name":"Mahendrapur",
    "wof:placetype":"locality"
},
  "geometry": {"coordinates":[87.97034000000002,25.50205],"type":"Point"}
}