{
  "type": "Feature",
  "properties": {
    "iso:country":"IN",
    "ks:ks_name":"Nagur",
    "ks:ks_pop":108,
    "ks:ks_type":"HABITATION",
    "name:eng_x_preferred":[
        "Nagur"
    ],
    "wof:name":"Nagur",
    "wof:placetype":"locality",
    "wof:population":108
},
  "geometry": {"coordinates":[74.453379,14.537046],"type":"Point"}
}