{
  "type": "Feature",
  "properties": {
    "iso:country":"IN",
    "ks:ks_name":"Dakhin Sekhadari No 1",
    "ks:ks_pop":407,
    "ks:ks_type":"VILLAGE",
    "ks:ks_uagg_main":0,
    "name:eng_x_preferred":[
        "Dakhin Sekhadari No 1"
    ],
    "wof:name":"Dakhin Sekhadari No 1",
    "wof:placetype":"neighbourhood",
    "wof:population":407
},
  "geometry": {"coordinates":[91.120671,25.977815],"type":"Point"}
}