{
  "type": "Feature",
  "properties": {
    "gn:admin1_code":"12",
    "gn:admin2_code":"18.0",
    "gn:asciiname":"Halol",
    "gn:country_code":"IN",
    "gn:dem":2196,
    "gn:feature_class":"P",
    "gn:feature_code":"PPL",
    "gn:name":"Hal\u014dl",
    "gn:population":0,
    "gn:timezone":"Asia/Kolkata",
    "iso:country":"IN",
    "wof:name":"Halol",
    "wof:placetype":"locality"
},
  "geometry": {"coordinates":[76.18923000000002,33.31301],"type":"Point"}
}