{
  "type": "Feature",
  "properties": {
    "gn:admin1_code":"12",
    "gn:admin2_code":"18.0",
    "gn:asciiname":"Halol",
    "gn:country_code":"IN",
    "gn:dem":2196,
    "gn:feature_class":"P",
    "gn:feature_code":"PPL",
    "gn:name":"Hal\u014dl",
    "gn:population":0,
    "gn:timezone":"Asia/Kolkata",
    "iso:country":"IN",
    "name:bpy_x_preferred":[
        "\u09b9\u09be\u09b2\u09cb\u09b2"
    ],
    "name:cat_x_preferred":[
        "Halol"
    ],
    "name:ceb_x_preferred":[
        "H\u0101lol"
    ],
    "name:guj_x_preferred":[
        "\u0ab9\u0abe\u0ab2\u0acb\u0ab2"
    ],
    "name:hin_x_preferred":[
        "\u0939\u093e\u0932\u094b\u0932"
    ],
    "name:ita_x_preferred":[
        "Halol"
    ],
    "name:msa_x_preferred":[
        "Halol"
    ],
    "name:new_x_preferred":[
        "\u0939\u093e\u0932\u094b\u0932"
    ],
    "name:por_x_preferred":[
        "Halol"
    ],
    "name:spa_x_preferred":[
        "Halol"
    ],
    "name:swe_x_preferred":[
        "H\u0101lol"
    ],
    "name:vie_x_preferred":[
        "Halol"
    ],
    "name:zho_x_preferred":[
        "\u54c8\u6d1b\u5c14"
    ],
    "wof:name":"Halol",
    "wof:placetype":"locality"
},
  "geometry": {"coordinates":[76.18923000000002,33.31301],"type":"Point"}
}