{
  "type": "Feature",
  "properties": {
    "iso:country":"IN",
    "ks:ks_name":"Nai Basti",
    "ks:ks_pop":113,
    "ks:ks_type":"HABITATION",
    "name:eng_x_preferred":[
        "Nai Basti"
    ],
    "wof:name":"Nai Basti",
    "wof:placetype":"locality",
    "wof:population":113
},
  "geometry": {"coordinates":[84.19319299999999,25.981672],"type":"Point"}
}