{
  "type": "Feature",
  "properties": {
    "iso:country":"IN",
    "ks:ks_name":"Umanur M",
    "ks:ks_pop":98,
    "ks:ks_type":"HABITATION",
    "name:eng_x_preferred":[
        "Umanur M"
    ],
    "wof:name":"Umanur M",
    "wof:placetype":"locality",
    "wof:population":98
},
  "geometry": {"coordinates":[80.073128,19.054944],"type":"Point"}
}