{
  "type": "Feature",
  "properties": {
    "gn:admin1_code":"25.0",
    "gn:admin2_code":"604",
    "gn:asciiname":"Kelambakkam",
    "gn:country_code":"IN",
    "gn:dem":9,
    "gn:feature_class":"P",
    "gn:feature_code":"PPL",
    "gn:name":"Kelamb\u0101kkam",
    "gn:population":0,
    "gn:timezone":"Asia/Kolkata",
    "iso:country":"IN",
    "name:tam_x_preferred":[
        "\u0b95\u0bc7\u0bb3\u0bae\u0bcd\u0baa\u0bbe\u0b95\u0bcd\u0b95\u0bae\u0bcd"
    ],
    "name:und_x_variant":[
        "Kelamb\u0101kkam"
    ],
    "wof:name":"Kelambakkam",
    "wof:placetype":"locality"
},
  "geometry": {"coordinates":[80.22161,12.78725],"type":"Point"}
}