{
  "type": "Feature",
  "properties": {
    "iso:country":"IN",
    "ks:ks_alt_nam":"KATAPAR",
    "ks:ks_name":"Katapar",
    "ks:ks_pop":259,
    "ks:ks_type":"HABITATION",
    "name:eng_x_preferred":[
        "Katapar"
    ],
    "wof:name":"Katapar",
    "wof:placetype":"locality",
    "wof:population":259
},
  "geometry": {"coordinates":[81.48523400000001,22.379195],"type":"Point"}
}