{
  "type": "Feature",
  "properties": {
    "iso:country":"IN",
    "ks:ks_name":"Garudol",
    "ks:ks_pop":339,
    "ks:ks_type":"VILLAGE",
    "name:eng_x_preferred":[
        "Garudol"
    ],
    "wof:name":"Garudol",
    "wof:placetype":"locality",
    "wof:population":339
},
  "geometry": {"coordinates":[82.300012,23.38178],"type":"Point"}
}