{
  "type": "Feature",
  "properties": {
    "gn:admin1_code":"19.0",
    "gn:admin2_code":"574.0",
    "gn:asciiname":"Nellakkihalli",
    "gn:country_code":"IN",
    "gn:dem":917,
    "gn:feature_class":"P",
    "gn:feature_code":"PPL",
    "gn:name":"Nellakkihalli",
    "gn:population":0,
    "gn:timezone":"Asia/Kolkata",
    "iso:country":"IN",
    "name:und_x_variant":[
        "Nelakkihalli"
    ],
    "wof:name":"Nellakkihalli",
    "wof:placetype":"locality"
},
  "geometry": {"coordinates":[76.24868000000002,12.9327],"type":"Point"}
}