{
  "type": "Feature",
  "properties": {
    "gn:admin1_code":"19.0",
    "gn:admin2_code":"574.0",
    "gn:asciiname":"Nellakkihalli",
    "gn:country_code":"IN",
    "gn:dem":917,
    "gn:feature_class":"P",
    "gn:feature_code":"PPL",
    "gn:name":"Nellakkihalli",
    "gn:population":0,
    "gn:timezone":"Asia/Kolkata",
    "iso:country":"IN",
    "ks:ks_name":"Nellakkihalli",
    "ks:ks_pop":186,
    "ks:ks_type":"VILLAGE",
    "name:eng_x_preferred":[
        "Nellakkihalli"
    ],
    "name:und_x_variant":[
        "Nelakkihalli"
    ],
    "wof:name":"Nellakkihalli",
    "wof:placetype":"locality",
    "wof:population":186
},
  "geometry": {"coordinates":[76.25481600000001,12.931562],"type":"Point"}
}