{
  "type": "Feature",
  "properties": {
    "gn:admin1_code":"40.0",
    "gn:admin2_code":"538.0",
    "gn:asciiname":"Tupata Tanda",
    "gn:country_code":"IN",
    "gn:dem":533,
    "gn:feature_class":"P",
    "gn:feature_code":"PPL",
    "gn:name":"Tupata T\u0101nda",
    "gn:population":0,
    "gn:timezone":"Asia/Kolkata",
    "iso:country":"IN",
    "wof:name":"Tupata Tanda",
    "wof:placetype":"locality"
},
  "geometry": {"coordinates":[78.1557,16.67878],"type":"Point"}
}