{
  "type": "Feature",
  "properties": {
    "gn:admin1_code":"25.0",
    "gn:admin2_code":"604.0",
    "gn:asciiname":"Orikkai",
    "gn:country_code":"IN",
    "gn:dem":85,
    "gn:feature_class":"P",
    "gn:feature_code":"PPL",
    "gn:name":"Or\u012bkkai",
    "gn:population":0,
    "gn:timezone":"Asia/Kolkata",
    "iso:country":"IN",
    "ks:ks_alt_nam":"Or\u012bkkai",
    "ks:ks_name":"Orikkai",
    "ks:ks_pop":4607,
    "ks:ks_type":"URBAN",
    "ks:ks_uagg_main":0,
    "name:eng_x_preferred":[
        "Orikkai"
    ],
    "name:eng_x_variant":[
        "Or\u012bkkai"
    ],
    "wof:name":"Orikkai",
    "wof:placetype":"neighbourhood",
    "wof:population":4607
},
  "geometry": {"coordinates":[79.711061,12.801643],"type":"Point"}
}