{
  "type": "Feature",
  "properties": {
    "gn:admin1_code":"11",
    "gn:admin2_code":"23.0",
    "gn:asciiname":"Bichhi Thao",
    "gn:country_code":"IN",
    "gn:dem":2418,
    "gn:feature_class":"P",
    "gn:feature_code":"PPL",
    "gn:name":"Bichhi Thao",
    "gn:population":0,
    "gn:timezone":"Asia/Kolkata",
    "iso:country":"IN",
    "wof:name":"Bichhi Thao",
    "wof:placetype":"locality"
},
  "geometry": {"coordinates":[76.34873,33.12827],"type":"Point"}
}