{
  "type": "Feature",
  "properties": {
    "gn:admin1_code":"23",
    "gn:admin2_code":"50.0",
    "gn:asciiname":"Sarai Amanat Khan",
    "gn:country_code":"IN",
    "gn:dem":220,
    "gn:feature_class":"P",
    "gn:feature_code":"PPL",
    "gn:name":"Sarai Am\u0101nat Kh\u0101n",
    "gn:population":0,
    "gn:timezone":"Asia/Kolkata",
    "iso:country":"IN",
    "name:und_x_variant":[
        "Sarai Am\u0101nat Kh\u0101n",
        "Sar\u0101i Am\u0101nat Kh\u0101n"
    ],
    "wof:name":"Sarai Amanat Khan",
    "wof:placetype":"locality"
},
  "geometry": {"coordinates":[74.69385,31.5111],"type":"Point"}
}