{
  "type": "Feature",
  "properties": {
    "gn:country":"IN",
    "gn:fcode":"PPL",
    "gn:pop":4026,
    "iso:country":"IN",
    "name:ben_x_preferred":[
        "\u09b0\u09be\u0982\u09aa\u09cb"
    ],
    "name:bpy_x_preferred":[
        "\u09b0\u09be\u0982\u09aa\u09cb"
    ],
    "name:bul_x_preferred":[
        "\u0420\u0430\u043d\u0433\u043f\u043e"
    ],
    "name:eng_x_preferred":[
        "Rangpo"
    ],
    "name:fra_x_preferred":[
        "Rangpo"
    ],
    "name:ita_x_preferred":[
        "Rangpo"
    ],
    "name:mlg_x_preferred":[
        "Rangpo"
    ],
    "name:msa_x_preferred":[
        "Rangpo"
    ],
    "name:nld_x_preferred":[
        "Rangpo"
    ],
    "name:swe_x_preferred":[
        "Rangpo"
    ],
    "name:tam_x_preferred":[
        "\u0bb0\u0bbe\u0b99\u0bcd\u0baa\u0bcb"
    ],
    "name:ukr_x_preferred":[
        "\u0420\u0430\u043d\u0491\u043f\u043e"
    ],
    "name:unk_x_variant":[
        "Rungpo"
    ],
    "name:vie_x_preferred":[
        "Rangpo"
    ],
    "name:zho_x_preferred":[
        "\u6717\u683c\u6ce2"
    ],
    "qs:name":"Rangpo",
    "qs:photos_9r":0,
    "qs:photos_sr":0,
    "qs:pop_sr":"4",
    "wd:wordcount":887,
    "wof:name":"Rangpo",
    "wof:placetype":"locality",
    "wof:population":4026
},
  "geometry": {"coordinates":[88.53358,27.17733],"type":"Point"}
}