{
  "type": "Feature",
  "properties": {
    "iso:country":"IN",
    "ks:ks_alt_nam":"N.S.koppa",
    "ks:ks_name":"N.s.koppa",
    "ks:ks_pop":653,
    "ks:ks_type":"HABITATION",
    "name:eng_x_preferred":[
        "N.s.koppa"
    ],
    "wof:name":"N.s.koppa",
    "wof:placetype":"locality",
    "wof:population":653
},
  "geometry": {"coordinates":[74.815579,15.297869],"type":"Point"}
}