{
  "type": "Feature",
  "properties": {
    "gn:admin1_code":"35",
    "gn:admin2_code":"463.0",
    "gn:asciiname":"Biradar",
    "gn:country_code":"IN",
    "gn:dem":368,
    "gn:feature_class":"P",
    "gn:feature_code":"PPL",
    "gn:name":"Bir\u0101d\u0101r",
    "gn:population":0,
    "gn:timezone":"Asia/Kolkata",
    "iso:country":"IN",
    "ks:ks_alt_nam":"Bir\u0101d\u0101r",
    "ks:ks_name":"Biradar",
    "ks:ks_type":"VILLAGE",
    "ks:ks_uagg_main":0,
    "name:eng_x_preferred":[
        "Biradar"
    ],
    "name:eng_x_variant":[
        "Bir\u0101d\u0101r"
    ],
    "wof:name":"Biradar",
    "wof:placetype":"neighbourhood"
},
  "geometry": {"coordinates":[82.39381400000001,24.235033],"type":"Point"}
}