{
  "type": "Feature",
  "properties": {
    "gn:admin1_code":"19.0",
    "gn:admin2_code":"566.0",
    "gn:asciiname":"Kalluhatti",
    "gn:country_code":"IN",
    "gn:dem":693,
    "gn:feature_class":"P",
    "gn:feature_code":"PPL",
    "gn:name":"Kalluhatti",
    "gn:population":0,
    "gn:timezone":"Asia/Kolkata",
    "iso:country":"IN",
    "wof:name":"Kalluhatti",
    "wof:placetype":"locality"
},
  "geometry": {"coordinates":[76.49828000000002,14.08767],"type":"Point"}
}