{
  "type": "Feature",
  "properties": {
    "gn:admin1_code":"39.0",
    "gn:admin2_code":"64.0",
    "gn:asciiname":"Galli",
    "gn:country_code":"IN",
    "gn:dem":1404,
    "gn:feature_class":"P",
    "gn:feature_code":"PPL",
    "gn:name":"Galli",
    "gn:population":0,
    "gn:timezone":"Asia/Kolkata",
    "iso:country":"IN",
    "name:cat_x_preferred":[
        "Gallus"
    ],
    "name:deu_x_preferred":[
        "Galloi"
    ],
    "name:ell_x_preferred":[
        "\u0393\u03ac\u03bb\u03bb\u03bf\u03b9"
    ],
    "name:fra_x_preferred":[
        "Galle"
    ],
    "name:ita_x_preferred":[
        "Gallo"
    ],
    "name:jpn_x_preferred":[
        "\u30ac\u30c3\u30e9\u30a4"
    ],
    "name:kor_x_preferred":[
        "\uac08\ub8e8\uc2a4"
    ],
    "name:lat_x_preferred":[
        "Galli"
    ],
    "name:nld_x_preferred":[
        "Galli"
    ],
    "name:por_x_preferred":[
        "Galo"
    ],
    "name:rus_x_preferred":[
        "\u0413\u0430\u043b\u043b"
    ],
    "name:spa_x_preferred":[
        "Gallo"
    ],
    "name:srp_x_preferred":[
        "\u0413\u0430\u043b\u0438"
    ],
    "name:swe_x_preferred":[
        "Gallus"
    ],
    "wof:name":"Galli",
    "wof:placetype":"locality"
},
  "geometry": {"coordinates":[79.55789,29.70014],"type":"Point"}
}