{
  "type": "Feature",
  "properties": {
    "iso:country":"IN",
    "ks:ks_alt_nam":"North AD Street",
    "ks:ks_name":"North Ad Street",
    "ks:ks_pop":150,
    "ks:ks_type":"HABITATION",
    "name:eng_x_preferred":[
        "North Ad Street"
    ],
    "wof:name":"North Ad Street",
    "wof:placetype":"locality",
    "wof:population":150
},
  "geometry": {"coordinates":[79.505898,10.589582],"type":"Point"}
}