{
  "type": "Feature",
  "properties": {
    "iso:country":"IN",
    "ks:ks_name":"Galandewasti",
    "ks:ks_pop":125,
    "ks:ks_type":"HABITATION",
    "name:eng_x_preferred":[
        "Galandewasti"
    ],
    "wof:name":"Galandewasti",
    "wof:placetype":"locality",
    "wof:population":125
},
  "geometry": {"coordinates":[75.126873,18.26594],"type":"Point"}
}