{
  "type": "Feature",
  "properties": {
    "iso:country":"IN",
    "ks:ks_name":"Puruna Manatira",
    "ks:ks_pop":642,
    "ks:ks_type":"HABITATION",
    "name:eng_x_preferred":[
        "Puruna Manatira"
    ],
    "wof:name":"Puruna Manatira",
    "wof:placetype":"locality",
    "wof:population":642
},
  "geometry": {"coordinates":[86.05377900000001,20.889255],"type":"Point"}
}