{
  "type": "Feature",
  "properties": {
    "iso:country":"IN",
    "ks:ks_name":"Teliya Mahatman",
    "ks:ks_pop":281,
    "ks:ks_type":"VILLAGE",
    "name:eng_x_preferred":[
        "Teliya Mahatman"
    ],
    "wof:name":"Teliya Mahatman",
    "wof:placetype":"locality",
    "wof:population":281
},
  "geometry": {"coordinates":[82.107657,24.635748],"type":"Point"}
}