{
  "type": "Feature",
  "properties": {
    "iso:country":"IN",
    "ks:ks_name":"Reddiyapatti",
    "ks:ks_pop":394,
    "ks:ks_type":"HABITATION",
    "ks:ks_uagg_main":0,
    "name:eng_x_preferred":[
        "Reddiyapatti"
    ],
    "wof:name":"Reddiyapatti",
    "wof:placetype":"neighbourhood",
    "wof:population":394
},
  "geometry": {"coordinates":[77.78197400000001,10.143995],"type":"Point"}
}