{
  "type": "Feature",
  "properties": {
    "gn:admin1_code":"16",
    "gn:admin2_code":"531.0",
    "gn:asciiname":"Langarpeth",
    "gn:country_code":"IN",
    "gn:dem":674,
    "gn:feature_class":"P",
    "gn:feature_code":"PPL",
    "gn:name":"Langarpeth",
    "gn:population":0,
    "gn:timezone":"Asia/Kolkata",
    "iso:country":"IN",
    "wof:name":"Langarpeth",
    "wof:placetype":"locality"
},
  "geometry": {"coordinates":[74.94798,17.07526],"type":"Point"}
}