{
  "type": "Feature",
  "properties": {
    "iso:country":"IN",
    "ks:ks_name":"Samola",
    "ks:ks_pop":1016,
    "ks:ks_type":"VILLAGE",
    "ks:ks_uagg_main":0,
    "name:eng_x_preferred":[
        "Samola"
    ],
    "wof:name":"Samola",
    "wof:placetype":"neighbourhood",
    "wof:population":1016
},
  "geometry": {"coordinates":[77.926931,26.71426],"type":"Point"}
}