{
  "type": "Feature",
  "properties": {
    "iso:country":"IN",
    "ks:ks_name":"Mishra",
    "ks:ks_pop":423,
    "ks:ks_type":"VILLAGE",
    "ks:ks_uagg_main":0,
    "name:eng_x_preferred":[
        "Mishra"
    ],
    "wof:name":"Mishra",
    "wof:placetype":"neighbourhood",
    "wof:population":423
},
  "geometry": {"coordinates":[82.772311,24.136269],"type":"Point"}
}