{
  "type": "Feature",
  "properties": {
    "gn:admin1_code":"36.0",
    "gn:admin2_code":"181.0",
    "gn:asciiname":"Chamar Purwa",
    "gn:country_code":"IN",
    "gn:dem":119,
    "gn:feature_class":"P",
    "gn:feature_code":"PPL",
    "gn:name":"Cham\u0101r Purwa",
    "gn:population":0,
    "gn:timezone":"Asia/Kolkata",
    "iso:country":"IN",
    "ks:ks_name":"Chamaran Purwa",
    "ks:ks_pop":83,
    "ks:ks_type":"HABITATION",
    "name:eng_x_preferred":[
        "Chamaran Purwa"
    ],
    "name:eng_x_variant":[
        "Chamar Purwa"
    ],
    "wof:name":"Chamaran Purwa",
    "wof:placetype":"locality",
    "wof:population":83
},
  "geometry": {"coordinates":[81.810063,27.44424],"type":"Point"}
}