{
  "type": "Feature",
  "properties": {
    "gn:admin1_code":"19.0",
    "gn:admin2_code":"563.0",
    "gn:asciiname":"Hutgar",
    "gn:country_code":"IN",
    "gn:dem":579,
    "gn:feature_class":"P",
    "gn:feature_code":"PPL",
    "gn:name":"Hutg\u0101r",
    "gn:population":0,
    "gn:timezone":"Asia/Kolkata",
    "iso:country":"IN",
    "ks:ks_name":"Hutagar",
    "ks:ks_pop":54,
    "ks:ks_type":"HABITATION",
    "name:eng_x_preferred":[
        "Hutagar"
    ],
    "name:eng_x_variant":[
        "Hutgar"
    ],
    "wof:name":"Hutagar",
    "wof:placetype":"locality",
    "wof:population":54
},
  "geometry": {"coordinates":[74.692846,14.497719],"type":"Point"}
}