{
  "type": "Feature",
  "properties": {
    "iso:country":"IN",
    "ks:ks_name":"Gavaliwada",
    "ks:ks_pop":58,
    "ks:ks_type":"HABITATION",
    "name:eng_x_preferred":[
        "Gavaliwada"
    ],
    "wof:name":"Gavaliwada",
    "wof:placetype":"locality",
    "wof:population":58
},
  "geometry": {"coordinates":[74.494011,15.390107],"type":"Point"}
}