{
  "type": "Feature",
  "properties": {
    "iso:country":"IN",
    "ks:ks_name":"Patisa",
    "ks:ks_pop":479,
    "ks:ks_type":"VILLAGE",
    "ks:ks_uagg_main":0,
    "name:eng_x_preferred":[
        "Patisa"
    ],
    "wof:name":"Patisa",
    "wof:placetype":"neighbourhood",
    "wof:population":479
},
  "geometry": {"coordinates":[84.24679999999999,25.847786],"type":"Point"}
}