{
  "type": "Feature",
  "properties": {
    "gn:admin1_code":"35",
    "gn:admin2_code":"430.0",
    "gn:asciiname":"Shukulgawan",
    "gn:country_code":"IN",
    "gn:dem":305,
    "gn:feature_class":"P",
    "gn:feature_code":"PPL",
    "gn:name":"Shukulgaw\u0101n",
    "gn:population":0,
    "gn:timezone":"Asia/Kolkata",
    "iso:country":"IN",
    "ks:ks_name":"Shukalgawan",
    "ks:ks_pop":631,
    "ks:ks_type":"VILLAGE",
    "ks:ks_uagg_main":0,
    "name:eng_x_preferred":[
        "Shukalgawan"
    ],
    "wof:name":"Shukalgawan",
    "wof:placetype":"neighbourhood",
    "wof:population":631
},
  "geometry": {"coordinates":[81.473141,24.662974],"type":"Point"}
}