{
  "type": "Feature",
  "properties": {
    "gn:admin1_code":"39.0",
    "gn:admin2_code":"60.0",
    "gn:asciiname":"Saula",
    "gn:country_code":"IN",
    "gn:dem":932,
    "gn:feature_class":"P",
    "gn:feature_code":"PPL",
    "gn:name":"Saula",
    "gn:population":0,
    "gn:timezone":"Asia/Kolkata",
    "iso:country":"IN",
    "name:ceb_x_preferred":[
        "Saula"
    ],
    "name:swe_x_preferred":[
        "Saula"
    ],
    "wof:name":"Saula",
    "wof:placetype":"locality"
},
  "geometry": {"coordinates":[78.01249,30.4236],"type":"Point"}
}