{
  "type": "Feature",
  "properties": {
    "iso:country":"IN",
    "ks:ks_name":"Khorahthanda",
    "ks:ks_pop":131,
    "ks:ks_type":"HABITATION",
    "name:eng_x_preferred":[
        "Khorahthanda"
    ],
    "wof:name":"Khorahthanda",
    "wof:placetype":"locality",
    "wof:population":131
},
  "geometry": {"coordinates":[79.24894399999999,18.054765],"type":"Point"}
}