{
  "type": "Feature",
  "properties": {
    "iso:country":"IN",
    "ks:ks_name":"Sonkani",
    "ks:ks_pop":504,
    "ks:ks_type":"VILLAGE",
    "name:eng_x_preferred":[
        "Sonkani"
    ],
    "wof:name":"Sonkani",
    "wof:placetype":"locality",
    "wof:population":504
},
  "geometry": {"coordinates":[91.486276,26.390769],"type":"Point"}
}