{
  "type": "Feature",
  "properties": {
    "iso:country":"IN",
    "ks:ks_name":"Padam Pulikachira",
    "ks:ks_pop":469,
    "ks:ks_type":"HABITATION",
    "name:eng_x_preferred":[
        "Padam Pulikachira"
    ],
    "wof:name":"Padam Pulikachira",
    "wof:placetype":"locality",
    "wof:population":469
},
  "geometry": {"coordinates":[76.189266,10.315705],"type":"Point"}
}