{
  "type": "Feature",
  "properties": {
    "iso:country":"IN",
    "ks:ks_name":"Honnur Vaddarahatti",
    "ks:ks_pop":200,
    "ks:ks_type":"HABITATION",
    "name:eng_x_preferred":[
        "Honnur Vaddarahatti"
    ],
    "wof:name":"Honnur Vaddarahatti",
    "wof:placetype":"locality",
    "wof:population":200
},
  "geometry": {"coordinates":[75.786,14.285],"type":"Point"}
}