{
  "type": "Feature",
  "properties": {
    "gn:admin1_code":"35",
    "gn:admin2_code":"427.0",
    "gn:asciiname":"Malthone",
    "gn:country_code":"IN",
    "gn:dem":457,
    "gn:feature_class":"P",
    "gn:feature_code":"PPL",
    "gn:name":"M\u0101lthone",
    "gn:population":0,
    "gn:timezone":"Asia/Kolkata",
    "iso:country":"IN",
    "name:und_x_variant":[
        "M\u0101lthon",
        "M\u0101lthone"
    ],
    "wof:name":"Malthone",
    "wof:placetype":"locality"
},
  "geometry": {"coordinates":[78.52834,24.30549],"type":"Point"}
}