{
  "type": "Feature",
  "properties": {
    "iso:country":"IN",
    "ks:ks_name":"Aalayam",
    "ks:ks_pop":4500,
    "ks:ks_type":"HABITATION",
    "name:eng_x_preferred":[
        "Aalayam"
    ],
    "wof:name":"Aalayam",
    "wof:placetype":"locality",
    "wof:population":4500
},
  "geometry": {"coordinates":[76.543819,9.30806],"type":"Point"}
}