{
  "type": "Feature",
  "properties": {
    "iso:country":"IN",
    "ks:ks_name":"Nayakammaguda",
    "ks:ks_pop":176,
    "ks:ks_type":"HABITATION",
    "name:eng_x_preferred":[
        "Nayakammaguda"
    ],
    "wof:name":"Nayakammaguda",
    "wof:placetype":"locality",
    "wof:population":176
},
  "geometry": {"coordinates":[83.689984,18.776539],"type":"Point"}
}