{
  "type": "Feature",
  "properties": {
    "gn:admin1_code":"40.0",
    "gn:admin2_code":"541.0",
    "gn:asciiname":"Venkatapuram",
    "gn:country_code":"IN",
    "gn:dem":91,
    "gn:feature_class":"P",
    "gn:feature_code":"PPL",
    "gn:name":"Venkat\u0101puram",
    "gn:population":0,
    "gn:timezone":"Asia/Kolkata",
    "iso:country":"IN",
    "name:tel_x_preferred":[
        "\u0c35\u0c46\u0c02\u0c15\u0c1f\u0c3e\u0c2a\u0c41\u0c30\u0c02(\u0c05\u0c26\u0c4d\u0c26\u0c02\u0c15\u0c3f)"
    ],
    "wof:name":"Venkatapuram",
    "wof:placetype":"locality"
},
  "geometry": {"coordinates":[81.01394000000001,17.75009],"type":"Point"}
}