{
  "type": "Feature",
  "properties": {
    "gn:admin1_code":"16.0",
    "gn:admin2_code":"521",
    "gn:asciiname":"Kamshet",
    "gn:country_code":"IN",
    "gn:dem":619,
    "gn:feature_class":"P",
    "gn:feature_code":"PPL",
    "gn:name":"Kamshet",
    "gn:population":0,
    "gn:timezone":"Asia/Kolkata",
    "iso:country":"IN",
    "name:mar_x_preferred":[
        "\u0915\u093e\u092e\u0936\u0947\u0924"
    ],
    "name:ukr_x_preferred":[
        "\u041a\u0430\u043c\u0448\u0435\u0442"
    ],
    "wof:name":"Kamshet",
    "wof:placetype":"locality"
},
  "geometry": {"coordinates":[73.55394,18.76521],"type":"Point"}
}