{
  "type": "Feature",
  "properties": {
    "iso:country":"IN",
    "ks:ks_name":"Bada Sarumunda",
    "ks:ks_pop":159,
    "ks:ks_type":"VILLAGE",
    "name:eng_x_preferred":[
        "Bada Sarumunda"
    ],
    "wof:name":"Bada Sarumunda",
    "wof:placetype":"locality",
    "wof:population":159
},
  "geometry": {"coordinates":[83.21878700000001,19.02439],"type":"Point"}
}