{
  "type": "Feature",
  "properties": {
    "iso:country":"IN",
    "ks:ks_name":"Chamarhar No 2",
    "ks:ks_pop":140,
    "ks:ks_type":"HABITATION",
    "name:eng_x_preferred":[
        "Chamarhar No 2"
    ],
    "wof:name":"Chamarhar No 2",
    "wof:placetype":"locality",
    "wof:population":140
},
  "geometry": {"coordinates":[81.845747,24.732381],"type":"Point"}
}