{
  "type": "Feature",
  "properties": {
    "iso:country":"IN",
    "ks:ks_name":"Ramulapalli",
    "ks:ks_pop":60,
    "ks:ks_type":"HABITATION",
    "name:eng_x_preferred":[
        "Ramulapalli"
    ],
    "wof:name":"Ramulapalli",
    "wof:placetype":"locality",
    "wof:population":60
},
  "geometry": {"coordinates":[79.227018,18.339074],"type":"Point"}
}