{
  "type": "Feature",
  "properties": {
    "gn:admin1_code":"19.0",
    "gn:admin2_code":"556.0",
    "gn:asciiname":"Shivayogmandir",
    "gn:country_code":"IN",
    "gn:dem":540,
    "gn:feature_class":"P",
    "gn:feature_code":"PPL",
    "gn:name":"Shivayogmandir",
    "gn:population":0,
    "gn:timezone":"Asia/Kolkata",
    "iso:country":"IN",
    "wof:name":"Shivayogmandir",
    "wof:placetype":"locality"
},
  "geometry": {"coordinates":[75.75508000000001,15.91589],"type":"Point"}
}