{
  "type": "Feature",
  "properties": {
    "iso:country":"IN",
    "ks:ks_name":"Moliya",
    "ks:ks_pop":352,
    "ks:ks_type":"VILLAGE",
    "name:eng_x_preferred":[
        "Moliya"
    ],
    "wof:name":"Moliya",
    "wof:placetype":"locality",
    "wof:population":352
},
  "geometry": {"coordinates":[78.48865499999999,30.557062],"type":"Point"}
}