{
  "type": "Feature",
  "properties": {
    "iso:country":"IN",
    "name:eng_x_preferred":[
        "Railway Colony"
    ],
    "name:unk_x_variant":[
        "Railway Colony"
    ],
    "qs:gn_adm0_cc":"IN",
    "qs:gn_local":1258315,
    "qs:gn_nam_loc":"raurkela",
    "qs:gn_namadm1":"21",
    "qs:local_max":112,
    "qs:local_sum":112,
    "qs:localhoods":1,
    "qs:name":"Railway Colony",
    "qs:name_adm0":"India",
    "qs:name_adm1":"Orissa",
    "qs:name_adm2":"Sundargarh",
    "qs:name_local":"Raurkela",
    "qs:photo_max":72,
    "qs:photo_sum":112,
    "qs:placetype":"Suburb",
    "qs:quad_count":9,
    "qs:woe_adm0":23424848,
    "qs:woe_adm1":2345755,
    "qs:woe_adm2":12586626,
    "qs:woe_lau":0,
    "qs:woe_local":2294864,
    "qs:woe_ver":"7.10.0",
    "wd:wordcount":58,
    "wof:lang":[
        "eng"
    ],
    "wof:name":"Railway Colony",
    "wof:placetype":"neighbourhood"
},
  "geometry": {"coordinates":[84.85359200000001,22.246931],"type":"Point"}
}