{
  "type": "Feature",
  "properties": {
    "iso:country":"IN",
    "name:ara_x_preferred":[
        "\u0645\u0633\u062a\u0639\u0645\u0631\u0629 \u0627\u0644\u0633\u0643\u0629 \u0627\u0644\u062d\u062f\u064a\u062f"
    ],
    "name:ben_bn_x_preferred":[
        "\u09b0\u09c7\u09b2\u0993\u09af\u09bc\u09c7 \u0995\u09b2\u09cb\u09a8\u09c0"
    ],
    "name:ben_in_x_preferred":[
        "\u09b0\u09c7\u09b2\u0993\u09af\u09bc\u09c7 \u0995\u09b2\u09cb\u09a8\u09c0"
    ],
    "name:eng_x_preferred":[
        "Railway Colony"
    ],
    "name:eng_x_variant":[
        "City Railway Colony"
    ],
    "name:guj_x_preferred":[
        "\u0ab0\u0ac7\u0ab2\u0acd\u0ab5\u0ac7 \u0a95\u0acb\u0ab2\u0acb\u0aa8\u0ac0"
    ],
    "name:hin_x_preferred":[
        "\u0930\u0947\u0932\u0935\u0947 \u0915\u0949\u0932\u094b\u0928\u0940"
    ],
    "name:kan_x_preferred":[
        "\u0cb0\u0cc8\u0cb2\u0ccd\u0cb5\u0cc6 \u0c95\u0cbe\u0cb2\u0cca\u0ca8\u0cbf"
    ],
    "name:mal_x_preferred":[
        "\u0d31\u0d46\u0d2f\u0d3f\u0d7d\u0d35\u0d47 \u0d15\u0d4b\u0d33\u0d28\u0d3f"
    ],
    "name:mar_x_preferred":[
        "\u0930\u0947\u0932\u094d\u0935\u0947 \u0915\u0949\u0932\u0928\u0940"
    ],
    "name:pan_x_preferred":[
        "\u0a30\u0a47\u0a32\u0a35\u0a47 \u0a15\u0a3e\u0a32\u0a4c\u0a28\u0a40"
    ],
    "name:tam_x_preferred":[
        "\u0bb0\u0baf\u0bbf\u0bb2\u0bcd\u0bb5\u0bc7\u0b95\u0bcd \u0b95\u0bc1\u0b9f\u0bbf\u0baf\u0bbf\u0bb0\u0bc1\u0baa\u0bcd\u0baa\u0bc1"
    ],
    "name:tel_x_preferred":[
        "\u0c30\u0c48\u0c32\u0c4d\u0c35\u0c47 \u0c15\u0c3e\u0c32\u0c28\u0c40"
    ],
    "name:urd_x_preferred":[
        "\u0631\u06cc\u0644\u0648\u06d2 \u06a9\u0627\u0644\u0648\u0646\u06cc"
    ],
    "qs:gn_adm0_cc":"IN",
    "qs:gn_local":1258315,
    "qs:gn_nam_loc":"raurkela",
    "qs:gn_namadm1":"21",
    "qs:local_max":112,
    "qs:local_sum":112,
    "qs:localhoods":1,
    "qs:name":"Railway Colony",
    "qs:name_adm0":"India",
    "qs:name_adm1":"Orissa",
    "qs:name_adm2":"Sundargarh",
    "qs:name_local":"Raurkela",
    "qs:photo_max":72,
    "qs:photo_sum":112,
    "qs:placetype":"Suburb",
    "qs:quad_count":9,
    "qs:woe_adm0":23424848,
    "qs:woe_adm1":2345755,
    "qs:woe_adm2":12586626,
    "qs:woe_lau":0,
    "qs:woe_local":2294864,
    "qs:woe_ver":"7.10.0",
    "wd:wordcount":58,
    "wof:lang":[
        "eng"
    ],
    "wof:name":"Railway Colony",
    "wof:placetype":"neighbourhood"
},
  "geometry": {"coordinates":[84.85359200000001,22.246931],"type":"Point"}
}