{
  "type": "Feature",
  "properties": {
    "iso:country":"IN",
    "ks:ks_alt_nam":"kadne",
    "ks:ks_name":"Kadne",
    "ks:ks_pop":122,
    "ks:ks_type":"HABITATION",
    "name:eng_x_preferred":[
        "Kadne"
    ],
    "wof:name":"Kadne",
    "wof:placetype":"locality",
    "wof:population":122
},
  "geometry": {"coordinates":[74.298985,15.273761],"type":"Point"}
}