{
  "type": "Feature",
  "properties": {
    "gn:admin1_code":"39.0",
    "gn:admin2_code":"64.0",
    "gn:asciiname":"Gognani",
    "gn:country_code":"IN",
    "gn:dem":1461,
    "gn:feature_class":"P",
    "gn:feature_code":"PPL",
    "gn:name":"Gogn\u0101ni",
    "gn:population":0,
    "gn:timezone":"Asia/Kolkata",
    "iso:country":"IN",
    "wof:name":"Gognani",
    "wof:placetype":"locality"
},
  "geometry": {"coordinates":[79.84469,29.54304],"type":"Point"}
}