{
  "type": "Feature",
  "properties": {
    "iso:country":"IN",
    "ks:ks_name":"Kinagari",
    "ks:ks_pop":132,
    "ks:ks_type":"HABITATION",
    "name:eng_x_preferred":[
        "Kinagari"
    ],
    "wof:name":"Kinagari",
    "wof:placetype":"locality",
    "wof:population":132
},
  "geometry": {"coordinates":[82.447534,17.907953],"type":"Point"}
}