{
  "type": "Feature",
  "properties": {
    "iso:country":"IN",
    "ks:ks_alt_nam":"KESORIYA",
    "ks:ks_name":"Kesoriya",
    "ks:ks_pop":510,
    "ks:ks_type":"HABITATION",
    "name:eng_x_preferred":[
        "Kesoriya"
    ],
    "wof:name":"Kesoriya",
    "wof:placetype":"locality",
    "wof:population":510
},
  "geometry": {"coordinates":[85.46375500000001,24.986767],"type":"Point"}
}