{
  "type": "Feature",
  "properties": {
    "iso:country":"IN",
    "ks:ks_name":"Dambapulisi",
    "ks:ks_pop":281,
    "ks:ks_type":"HABITATION",
    "name:eng_x_preferred":[
        "Dambapulisi"
    ],
    "wof:name":"Dambapulisi",
    "wof:placetype":"locality",
    "wof:population":281
},
  "geometry": {"coordinates":[83.600814,19.317899],"type":"Point"}
}