{
  "type": "Feature",
  "properties": {
    "iso:country":"IN",
    "ks:ks_name":"Gungi Dawami",
    "ks:ks_pop":692,
    "ks:ks_type":"VILLAGE",
    "name:eng_x_preferred":[
        "Gungi Dawami"
    ],
    "wof:name":"Gungi Dawami",
    "wof:placetype":"locality",
    "wof:population":692
},
  "geometry": {"coordinates":[78.96385600000001,21.694264],"type":"Point"}
}