{
  "type": "Feature",
  "properties": {
    "iso:country":"IN",
    "ks:ks_name":"Nuagaon Jodapokhari",
    "ks:ks_pop":318,
    "ks:ks_type":"VILLAGE",
    "ks:ks_uagg_main":0,
    "name:eng_x_preferred":[
        "Nuagaon Jodapokhari"
    ],
    "wof:name":"Nuagaon Jodapokhari",
    "wof:placetype":"neighbourhood",
    "wof:population":318
},
  "geometry": {"coordinates":[85.705279,21.440029],"type":"Point"}
}