{
  "type": "Feature",
  "properties": {
    "iso:country":"IN",
    "ks:ks_name":"Bagwadi",
    "ks:ks_pop":196,
    "ks:ks_type":"HABITATION",
    "name:eng_x_preferred":[
        "Bagwadi"
    ],
    "wof:name":"Bagwadi",
    "wof:placetype":"locality",
    "wof:population":196
},
  "geometry": {"coordinates":[73.546955,16.509825],"type":"Point"}
}