{
  "type": "Feature",
  "properties": {
    "iso:country":"IN",
    "ks:ks_name":"Amma",
    "ks:ks_pop":573,
    "ks:ks_type":"VILLAGE",
    "ks:ks_uagg_main":0,
    "name:eng_x_preferred":[
        "Amma"
    ],
    "wof:name":"Amma",
    "wof:placetype":"neighbourhood",
    "wof:population":573
},
  "geometry": {"coordinates":[82.75023899999999,27.008292],"type":"Point"}
}