{
  "type": "Feature",
  "properties": {
    "gn:admin1_code":"37",
    "gn:admin2_code":"404.0",
    "gn:asciiname":"Gurtara",
    "gn:country_code":"IN",
    "gn:dem":318,
    "gn:feature_class":"P",
    "gn:feature_code":"PPL",
    "gn:name":"Gurtar\u0101",
    "gn:population":0,
    "gn:timezone":"Asia/Kolkata",
    "iso:country":"IN",
    "wof:name":"Gurtara",
    "wof:placetype":"locality"
},
  "geometry": {"coordinates":[82.65345000000001,22.51898],"type":"Point"}
}