{
  "type": "Feature",
  "properties": {
    "iso:country":"IN",
    "ks:ks_name":"Mandal Tola West River",
    "ks:ks_pop":400,
    "ks:ks_type":"HABITATION",
    "name:eng_x_preferred":[
        "Mandal Tola West River"
    ],
    "wof:name":"Mandal Tola West River",
    "wof:placetype":"locality",
    "wof:population":400
},
  "geometry": {"coordinates":[86.62697300000001,26.283385],"type":"Point"}
}