{
  "type": "Feature",
  "properties": {
    "iso:country":"IN",
    "ks:ks_alt_nam":"Ab\u016bsa\u012bdpur",
    "ks:ks_name":"Abusaidpur",
    "ks:ks_type":"VILLAGE",
    "name:eng_x_preferred":[
        "Abusaidpur"
    ],
    "name:eng_x_variant":[
        "Ab\u016bsa\u012bdpur"
    ],
    "wof:name":"Abusaidpur",
    "wof:placetype":"locality"
},
  "geometry": {"coordinates":[83.170587,26.016846],"type":"Point"}
}