{
  "type": "Feature",
  "properties": {
    "iso:country":"IN",
    "ks:ks_name":"Tutamunda",
    "ks:ks_pop":34,
    "ks:ks_type":"HABITATION",
    "name:eng_x_preferred":[
        "Tutamunda"
    ],
    "wof:name":"Tutamunda",
    "wof:placetype":"locality",
    "wof:population":34
},
  "geometry": {"coordinates":[84.054897,21.060762],"type":"Point"}
}