{
  "type": "Feature",
  "properties": {
    "gn:admin1_code":"19.0",
    "gn:admin2_code":"574.0",
    "gn:asciiname":"Bantratalal",
    "gn:country_code":"IN",
    "gn:dem":856,
    "gn:feature_class":"P",
    "gn:feature_code":"PPL",
    "gn:name":"Bantratalal",
    "gn:population":0,
    "gn:timezone":"Asia/Kolkata",
    "iso:country":"IN",
    "wof:name":"Bantratalal",
    "wof:placetype":"locality"
},
  "geometry": {"coordinates":[76.30646999999998,12.73082],"type":"Point"}
}