{
  "type": "Feature",
  "properties": {
    "iso:country":"IN",
    "ks:ks_name":"Madhya Mendhi",
    "ks:ks_pop":298,
    "ks:ks_type":"HABITATION",
    "name:eng_x_preferred":[
        "Madhya Mendhi"
    ],
    "wof:name":"Madhya Mendhi",
    "wof:placetype":"locality",
    "wof:population":298
},
  "geometry": {"coordinates":[91.802668,24.012827],"type":"Point"}
}