{
  "type": "Feature",
  "properties": {
    "iso:country":"IN",
    "ks:ks_name":"Guralpada",
    "ks:ks_pop":125,
    "ks:ks_type":"HABITATION",
    "name:eng_x_preferred":[
        "Guralpada"
    ],
    "wof:name":"Guralpada",
    "wof:placetype":"locality",
    "wof:population":125
},
  "geometry": {"coordinates":[74.82188600000001,21.51465],"type":"Point"}
}