{
  "type": "Feature",
  "properties": {
    "gn:admin1_code":"12.0",
    "gn:admin2_code":"1.0",
    "gn:asciiname":"Kashira",
    "gn:country_code":"IN",
    "gn:dem":1811,
    "gn:feature_class":"P",
    "gn:feature_code":"PPL",
    "gn:name":"K\u0101shira",
    "gn:population":0,
    "gn:timezone":"Asia/Kolkata",
    "iso:country":"IN",
    "name:ara_x_preferred":[
        "\u0643\u0627\u0634\u064a\u0631\u0627"
    ],
    "name:azb_x_preferred":[
        "\u06a9\u0627\u0634\u06cc\u0631\u0627"
    ],
    "name:aze_x_preferred":[
        "Ka\u015fira"
    ],
    "name:bel_x_preferred":[
        "\u041a\u0430\u0448\u044b\u0440\u0430"
    ],
    "name:bul_x_preferred":[
        "\u041a\u0430\u0448\u0438\u0440\u0430"
    ],
    "name:ceb_x_preferred":[
        "Kashira"
    ],
    "name:ces_x_preferred":[
        "Ka\u0161ira"
    ],
    "name:che_x_preferred":[
        "\u041a\u0430\u0448\u0438\u0440\u0430"
    ],
    "name:chv_x_preferred":[
        "\u041a\u0430\u0448\u0438\u0440\u0430"
    ],
    "name:deu_x_preferred":[
        "Kaschira"
    ],
    "name:epo_x_preferred":[
        "Ka\u015dira"
    ],
    "name:est_x_preferred":[
        "Ka\u0161ira"
    ],
    "name:fas_x_preferred":[
        "\u06a9\u0627\u0634\u06cc\u0631\u0627"
    ],
    "name:fin_x_preferred":[
        "Ka\u0161ira"
    ],
    "name:fra_x_preferred":[
        "Kachira"
    ],
    "name:hsb_x_preferred":[
        "Ka\u0161ira"
    ],
    "name:ita_x_preferred":[
        "Ka\u0161ira"
    ],
    "name:jpn_x_preferred":[
        "\u30ab\u30b7\u30fc\u30e9"
    ],
    "name:kor_x_preferred":[
        "\uce74\uc26c\ub77c"
    ],
    "name:nno_x_preferred":[
        "Kasjira"
    ],
    "name:nor_x_preferred":[
        "Kasjira"
    ],
    "name:oss_x_preferred":[
        "\u041a\u0430\u0448\u0438\u0440\u00e6"
    ],
    "name:pnb_x_preferred":[
        "\u06a9\u0627\u0634\u06cc\u0631\u0627"
    ],
    "name:pol_x_preferred":[
        "Kaszyra"
    ],
    "name:por_x_preferred":[
        "Kashira"
    ],
    "name:ron_x_preferred":[
        "Ka\u0219ira"
    ],
    "name:rus_x_preferred":[
        "\u041a\u0430\u0448\u0438\u0440\u0430"
    ],
    "name:sah_x_preferred":[
        "\u041a\u0430\u0448\u0438\u0440\u0430"
    ],
    "name:sco_x_preferred":[
        "Kashira"
    ],
    "name:spa_x_preferred":[
        "Kashira"
    ],
    "name:srp_x_preferred":[
        "\u041a\u0430\u0448\u0438\u0440\u0430"
    ],
    "name:swe_x_preferred":[
        "Kasjira"
    ],
    "name:tat_x_preferred":[
        "\u041a\u0430\u0448\u0438\u0440\u0430"
    ],
    "name:tgl_x_preferred":[
        "Kashira"
    ],
    "name:tur_x_preferred":[
        "Ka\u015fira"
    ],
    "name:ukr_x_preferred":[
        "\u041a\u0430\u0448\u0438\u0440\u0430"
    ],
    "name:vie_x_preferred":[
        "Kashira"
    ],
    "name:war_x_preferred":[
        "Kashira"
    ],
    "name:xal_x_preferred":[
        "\u041a\u0430\u0448\u0438\u0440\u0430 \u0431\u0430\u043b\u04bb\u0441\u043d"
    ],
    "name:zho_x_preferred":[
        "\u5361\u5e0c\u62c9"
    ],
    "wof:name":"Kashira",
    "wof:placetype":"locality"
},
  "geometry": {"coordinates":[74.28986999999999,34.56034],"type":"Point"}
}