{
  "type": "Feature",
  "properties": {
    "gn:admin1_code":"36.0",
    "gn:admin2_code":"150.0",
    "gn:asciiname":"Nagaria Kalan",
    "gn:country_code":"IN",
    "gn:dem":174,
    "gn:feature_class":"P",
    "gn:feature_code":"PPL",
    "gn:name":"Nagari\u0101 Kal\u0101n",
    "gn:population":0,
    "gn:timezone":"Asia/Kolkata",
    "iso:country":"IN",
    "ks:ks_alt_nam":"Nagari\u0101 Kal\u0101n",
    "ks:ks_name":"Nagaria Kalan",
    "ks:ks_type":"VILLAGE",
    "ks:ks_uagg_main":0,
    "wof:name":"Nagaria Kalan",
    "wof:placetype":"neighbourhood"
},
  "geometry": {"coordinates":[79.43969,28.4307],"type":"Point"}
}