{
  "type": "Feature",
  "properties": {
    "gn:admin1_code":"40",
    "gn:admin2_code":"537.0",
    "gn:asciiname":"Ambarpet",
    "gn:country_code":"IN",
    "gn:dem":463,
    "gn:feature_class":"P",
    "gn:feature_code":"PPL",
    "gn:name":"Ambarpet",
    "gn:population":0,
    "gn:timezone":"Asia/Kolkata",
    "iso:country":"IN",
    "wof:name":"Ambarpet",
    "wof:placetype":"locality"
},
  "geometry": {"coordinates":[77.60807,17.20669],"type":"Point"}
}