{
  "type": "Feature",
  "properties": {
    "iso:country":"IN",
    "ks:ks_name":"Uchimuchi",
    "ks:ks_pop":32,
    "ks:ks_type":"VILLAGE",
    "name:eng_x_preferred":[
        "Uchimuchi"
    ],
    "wof:name":"Uchimuchi",
    "wof:placetype":"locality",
    "wof:population":32
},
  "geometry": {"coordinates":[83.440522,19.893831],"type":"Point"}
}