{
  "type": "Feature",
  "properties": {
    "gn:admin1_code":"36",
    "gn:admin2_code":"195.0",
    "gn:asciiname":"Kanaun",
    "gn:country_code":"IN",
    "gn:dem":80,
    "gn:feature_class":"P",
    "gn:feature_code":"PPL",
    "gn:name":"Kanaun",
    "gn:population":0,
    "gn:timezone":"Asia/Kolkata",
    "iso:country":"IN",
    "name:por_x_preferred":[
        "Kanaun"
    ],
    "name:und_x_variant":[
        "Kanuw\u0101n"
    ],
    "wof:name":"Kanaun",
    "wof:placetype":"neighbourhood"
},
  "geometry": {"coordinates":[83.39506,25.71637],"type":"Point"}
}