{
  "type": "Feature",
  "properties": {
    "gn:admin1_code":"35.0",
    "gn:admin2_code":"457.0",
    "gn:asciiname":"Kamthi Tola",
    "gn:country_code":"IN",
    "gn:dem":327,
    "gn:feature_class":"P",
    "gn:feature_code":"PPL",
    "gn:name":"K\u0101mth\u012b Tol\u0101",
    "gn:population":0,
    "gn:timezone":"Asia/Kolkata",
    "iso:country":"IN",
    "wof:name":"Kamthi Tola",
    "wof:placetype":"locality"
},
  "geometry": {"coordinates":[80.03283,21.86132000000001],"type":"Point"}
}