{
  "type": "Feature",
  "properties": {
    "gn:admin1_code":"19.0",
    "gn:admin2_code":"574.0",
    "gn:asciiname":"Santhalli",
    "gn:country_code":"IN",
    "gn:dem":964,
    "gn:feature_class":"P",
    "gn:feature_code":"PPL",
    "gn:name":"Santhalli",
    "gn:population":0,
    "gn:timezone":"Asia/Kolkata",
    "iso:country":"IN",
    "ks:ks_name":"Santhahalli",
    "ks:ks_pop":80,
    "ks:ks_type":"VILLAGE",
    "name:eng_x_preferred":[
        "Santhahalli"
    ],
    "name:eng_x_variant":[
        "Santhalli"
    ],
    "wof:name":"Santhahalli",
    "wof:placetype":"locality",
    "wof:population":80
},
  "geometry": {"coordinates":[75.843875,12.72103],"type":"Point"}
}