{
  "type": "Feature",
  "properties": {
    "iso:country":"IN",
    "ks:ks_name":"Sellappampalayam",
    "ks:ks_pop":301,
    "ks:ks_type":"HABITATION",
    "name:eng_x_preferred":[
        "Sellappampalayam"
    ],
    "wof:name":"Sellappampalayam",
    "wof:placetype":"locality",
    "wof:population":301
},
  "geometry": {"coordinates":[77.783979,11.011959],"type":"Point"}
}