{
  "type": "Feature",
  "properties": {
    "gn:admin1_code":"39",
    "gn:admin2_code":"58.0",
    "gn:asciiname":"Gaundar",
    "gn:country_code":"IN",
    "gn:dem":3174,
    "gn:feature_class":"P",
    "gn:feature_code":"PPL",
    "gn:name":"Gaund\u0101r",
    "gn:population":0,
    "gn:timezone":"Asia/Kolkata",
    "iso:country":"IN",
    "wof:name":"Gaundar",
    "wof:placetype":"locality"
},
  "geometry": {"coordinates":[79.25672,30.60447000000001],"type":"Point"}
}