{
  "type": "Feature",
  "properties": {
    "gn:admin1_code":"39",
    "gn:admin2_code":"58.0",
    "gn:asciiname":"Gaundar",
    "gn:country_code":"IN",
    "gn:dem":3174,
    "gn:feature_class":"P",
    "gn:feature_code":"PPL",
    "gn:name":"Gaund\u0101r",
    "gn:population":0,
    "gn:timezone":"Asia/Kolkata",
    "iso:country":"IN",
    "ks:ks_name":"Gaundar",
    "ks:ks_pop":294,
    "ks:ks_type":"VILLAGE",
    "name:eng_x_preferred":[
        "Gaundar"
    ],
    "wof:name":"Gaundar",
    "wof:placetype":"locality",
    "wof:population":294
},
  "geometry": {"coordinates":[79.17993300000001,30.602522],"type":"Point"}
}