{
  "type": "Feature",
  "properties": {
    "gn:admin1_code":"12.0",
    "gn:admin2_code":"005",
    "gn:asciiname":"Dhar Gathun Bauji",
    "gn:country_code":"IN",
    "gn:dem":1331,
    "gn:feature_class":"P",
    "gn:feature_code":"PPL",
    "gn:name":"Dh\u0101r Gathun B\u0101uji",
    "gn:population":0,
    "gn:timezone":"Asia/Kolkata",
    "iso:country":"IN",
    "wof:name":"Dhar Gathun Bauji",
    "wof:placetype":"locality"
},
  "geometry": {"coordinates":[74.18333,33.58333],"type":"Point"}
}