{
  "type": "Feature",
  "properties": {
    "iso:country":"IN",
    "ks:ks_name":"Abhayapur Kachari",
    "ks:ks_pop":56,
    "ks:ks_type":"HABITATION",
    "name:eng_x_preferred":[
        "Abhayapur Kachari"
    ],
    "wof:name":"Abhayapur Kachari",
    "wof:placetype":"locality",
    "wof:population":56
},
  "geometry": {"coordinates":[95.227452,27.776935],"type":"Point"}
}