{
  "type": "Feature",
  "properties": {
    "iso:country":"IN",
    "ks:ks_name":"Srinivasanagar",
    "ks:ks_pop":774,
    "ks:ks_type":"HABITATION",
    "name:eng_x_preferred":[
        "Srinivasanagar"
    ],
    "wof:name":"Srinivasanagar",
    "wof:placetype":"locality",
    "wof:population":774
},
  "geometry": {"coordinates":[81.81737099999999,16.788695],"type":"Point"}
}