{
  "type": "Feature",
  "properties": {
    "iso:country":"IN",
    "ks:ks_name":"Peralda Palke",
    "ks:ks_pop":200,
    "ks:ks_type":"HABITATION",
    "name:eng_x_preferred":[
        "Peralda Palke"
    ],
    "wof:name":"Peralda Palke",
    "wof:placetype":"locality",
    "wof:population":200
},
  "geometry": {"coordinates":[75.32331000000001,12.866468],"type":"Point"}
}