{
  "type": "Feature",
  "properties": {
    "iso:country":"IN",
    "ks:ks_name":"Sevadasnagar",
    "ks:ks_pop":52,
    "ks:ks_type":"HABITATION",
    "name:eng_x_preferred":[
        "Sevadasnagar"
    ],
    "wof:name":"Sevadasnagar",
    "wof:placetype":"locality",
    "wof:population":52
},
  "geometry": {"coordinates":[78.954401,19.314135],"type":"Point"}
}