{
  "type": "Feature",
  "properties": {
    "gn:admin1_code":"12.0",
    "gn:asciiname":"Kandi Bala",
    "gn:country_code":"IN",
    "gn:dem":1700,
    "gn:feature_class":"P",
    "gn:feature_code":"PPL",
    "gn:name":"Kandi B\u0101la",
    "gn:population":0,
    "gn:timezone":"Asia/Kolkata",
    "iso:country":"IN",
    "wof:name":"Kandi Bala",
    "wof:placetype":"locality"
},
  "geometry": {"coordinates":[73.83853000000001,34.39437],"type":"Point"}
}