{
  "type": "Feature",
  "properties": {
    "iso:country":"IN",
    "ks:ks_name":"Mainwadi",
    "ks:ks_pop":310,
    "ks:ks_type":"HABITATION",
    "name:eng_x_preferred":[
        "Mainwadi"
    ],
    "wof:name":"Mainwadi",
    "wof:placetype":"locality",
    "wof:population":310
},
  "geometry": {"coordinates":[73.683978,17.052845],"type":"Point"}
}