{
  "type": "Feature",
  "properties": {
    "iso:country":"IN",
    "ks:ks_name":"Semarihatola",
    "ks:ks_pop":145,
    "ks:ks_type":"HABITATION",
    "name:eng_x_preferred":[
        "Semarihatola"
    ],
    "wof:name":"Semarihatola",
    "wof:placetype":"locality",
    "wof:population":145
},
  "geometry": {"coordinates":[81.826987,23.752932],"type":"Point"}
}