{
  "type": "Feature",
  "properties": {
    "iso:country":"IN",
    "ks:ks_alt_nam":"WEST LANDLESS COLONY",
    "ks:ks_name":"West Landless Colony",
    "ks:ks_pop":496,
    "ks:ks_type":"HABITATION",
    "name:eng_x_preferred":[
        "West Landless Colony"
    ],
    "wof:name":"West Landless Colony",
    "wof:placetype":"locality",
    "wof:population":496
},
  "geometry": {"coordinates":[91.637754,24.032847],"type":"Point"}
}