{
  "type": "Feature",
  "properties": {
    "iso:country":"IN",
    "ks:ks_name":"Uttar Ariapur",
    "ks:ks_pop":1302,
    "ks:ks_type":"HABITATION",
    "name:eng_x_preferred":[
        "Uttar Ariapur"
    ],
    "wof:name":"Uttar Ariapur",
    "wof:placetype":"locality",
    "wof:population":1302
},
  "geometry": {"coordinates":[88.046549,21.66714],"type":"Point"}
}