{
  "type": "Feature",
  "properties": {
    "iso:country":"IN",
    "ks:ks_alt_nam":"MOHITEMALI VASTI",
    "ks:ks_name":"Mohitemali Vasti",
    "ks:ks_pop":377,
    "ks:ks_type":"HABITATION",
    "name:eng_x_preferred":[
        "Mohitemali Vasti"
    ],
    "wof:name":"Mohitemali Vasti",
    "wof:placetype":"locality",
    "wof:population":377
},
  "geometry": {"coordinates":[74.857372,16.819593],"type":"Point"}
}