{
  "type": "Feature",
  "properties": {
    "gn:admin1_code":"02",
    "gn:admin2_code":"547.0",
    "gn:asciiname":"Viravalli",
    "gn:country_code":"IN",
    "gn:dem":24,
    "gn:feature_class":"P",
    "gn:feature_code":"PPL",
    "gn:name":"V\u012bravalli",
    "gn:population":0,
    "gn:timezone":"Asia/Kolkata",
    "iso:country":"IN",
    "name:und_x_variant":[
        "Viravilli",
        "V\u012bravalli"
    ],
    "wof:name":"Viravalli",
    "wof:placetype":"locality"
},
  "geometry": {"coordinates":[80.91818000000001,16.61211],"type":"Point"}
}