{
  "type": "Feature",
  "properties": {
    "gn:country":"IN",
    "gn:fcode":"PPL",
    "gn:pop":13298,
    "iso:country":"IN",
    "name:unk_x_variant":[
        "K\u0101l\u0101garh Project Colony"
    ],
    "qs:name":"Kalagarh",
    "qs:name_adm0":"India",
    "qs:name_adm1":"Uttarakhand",
    "qs:photos_9k":1,
    "qs:photos_9r":4,
    "qs:photos_all":177,
    "qs:photos_sr":0,
    "qs:placetype":"Town",
    "qs:pop_sr":"6",
    "wof:name":"Kalagarh",
    "wof:placetype":"locality",
    "wof:population":13298
},
  "geometry": {"coordinates":[78.78513,29.47737],"type":"Point"}
}