{
  "type": "Feature",
  "properties": {
    "gn:admin1_code":"34.0",
    "gn:admin2_code":"220.0",
    "gn:asciiname":"Bakarh",
    "gn:country_code":"IN",
    "gn:dem":51,
    "gn:feature_class":"P",
    "gn:feature_code":"PPL",
    "gn:name":"Bak\u0101rh",
    "gn:population":0,
    "gn:timezone":"Asia/Kolkata",
    "iso:country":"IN",
    "ks:ks_name":"Bakarh",
    "ks:ks_pop":1286,
    "ks:ks_type":"VILLAGE",
    "name:eng_x_preferred":[
        "Bakarh"
    ],
    "wof:name":"Bakarh",
    "wof:placetype":"locality",
    "wof:population":1286
},
  "geometry": {"coordinates":[85.600381,25.812636],"type":"Point"}
}