{
  "type": "Feature",
  "properties": {
    "iso:country":"IN",
    "ks:ks_name":"Gajendrapura",
    "ks:ks_pop":30,
    "ks:ks_type":"HABITATION",
    "name:eng_x_preferred":[
        "Gajendrapura"
    ],
    "wof:name":"Gajendrapura",
    "wof:placetype":"locality",
    "wof:population":30
},
  "geometry": {"coordinates":[75.8639,13.02787],"type":"Point"}
}