{
  "type": "Feature",
  "properties": {
    "gn:admin1_code":"40.0",
    "gn:admin2_code":"532.0",
    "gn:asciiname":"Savanapalli",
    "gn:country_code":"IN",
    "gn:dem":203,
    "gn:feature_class":"P",
    "gn:feature_code":"PPL",
    "gn:name":"S\u0101vanapalli",
    "gn:population":0,
    "gn:timezone":"Asia/Kolkata",
    "iso:country":"IN",
    "wof:name":"Savanapalli",
    "wof:placetype":"locality"
},
  "geometry": {"coordinates":[79.57115999999998,18.96981],"type":"Point"}
}