{
  "type": "Feature",
  "properties": {
    "gn:admin1_code":"24",
    "gn:admin2_code":"99.0",
    "gn:asciiname":"Sakhi",
    "gn:country_code":"IN",
    "gn:dem":142,
    "gn:feature_class":"P",
    "gn:feature_code":"PPL",
    "gn:name":"S\u0101khi",
    "gn:population":0,
    "gn:timezone":"Asia/Kolkata",
    "iso:country":"IN",
    "wof:name":"Sakhi",
    "wof:placetype":"locality"
},
  "geometry": {"coordinates":[72.87658,28.96065],"type":"Point"}
}