{
  "type": "Feature",
  "properties": {
    "gn:admin1_code":"35",
    "gn:admin2_code":"420.0",
    "gn:asciiname":"Kheriya",
    "gn:country_code":"IN",
    "gn:dem":152,
    "gn:feature_class":"P",
    "gn:feature_code":"PPL",
    "gn:name":"Kheriya",
    "gn:population":0,
    "gn:timezone":"Asia/Kolkata",
    "iso:country":"IN",
    "ks:ks_name":"Kheriya",
    "ks:ks_pop":4948,
    "ks:ks_type":"HABITATION",
    "name:eng_x_preferred":[
        "Kheriya"
    ],
    "wof:name":"Kheriya",
    "wof:placetype":"locality",
    "wof:population":4948
},
  "geometry": {"coordinates":[78.59908299999999,26.50238],"type":"Point"}
}