{
  "type": "Feature",
  "properties": {
    "iso:country":"IN",
    "ks:ks_name":"Telpata",
    "ks:ks_pop":0,
    "ks:ks_type":"VILLAGE",
    "name:eng_x_preferred":[
        "Telpata"
    ],
    "wof:name":"Telpata",
    "wof:placetype":"locality",
    "wof:population":0
},
  "geometry": {"coordinates":[87.25282199999999,21.827155],"type":"Point"}
}