{
  "type": "Feature",
  "properties": {
    "iso:country":"IN",
    "ks:ks_name":"Bedapani",
    "ks:ks_pop":644,
    "ks:ks_type":"VILLAGE",
    "name:eng_x_preferred":[
        "Bedapani"
    ],
    "wof:name":"Bedapani",
    "wof:placetype":"locality",
    "wof:population":644
},
  "geometry": {"coordinates":[72.795534,24.349483],"type":"Point"}
}