{
  "type": "Feature",
  "properties": {
    "gn:admin1_code":"39.0",
    "gn:admin2_code":"062",
    "gn:asciiname":"Buin",
    "gn:country_code":"IN",
    "gn:dem":1905,
    "gn:feature_class":"P",
    "gn:feature_code":"PPL",
    "gn:name":"Buin",
    "gn:population":0,
    "gn:timezone":"Asia/Kolkata",
    "iso:country":"IN",
    "name:ceb_x_preferred":[
        "Buin"
    ],
    "name:deu_x_preferred":[
        "Buin"
    ],
    "name:fas_x_preferred":[
        "\u0628\u0648\u0626\u06cc\u0646"
    ],
    "name:ita_x_preferred":[
        "Buin"
    ],
    "name:jpn_x_preferred":[
        "\u30d6\u30a4\u30f3"
    ],
    "name:kor_x_preferred":[
        "\ubd80\uc778"
    ],
    "name:spa_x_preferred":[
        "Buin"
    ],
    "name:swe_x_preferred":[
        "Buin"
    ],
    "wof:name":"Buin",
    "wof:placetype":"locality"
},
  "geometry": {"coordinates":[80.25711,30.15151],"type":"Point"}
}