{
  "type": "Feature",
  "properties": {
    "iso:country":"IN",
    "ks:ks_name":"Naudiha",
    "ks:ks_pop":355,
    "ks:ks_type":"VILLAGE",
    "ks:ks_uagg_main":0,
    "name:eng_x_preferred":[
        "Naudiha"
    ],
    "wof:name":"Naudiha",
    "wof:placetype":"neighbourhood",
    "wof:population":355
},
  "geometry": {"coordinates":[82.519666,27.093741],"type":"Point"}
}