{
  "type": "Feature",
  "properties": {
    "iso:country":"IN",
    "ks:ks_name":"Ramgad",
    "ks:ks_pop":290,
    "ks:ks_type":"HABITATION",
    "name:eng_x_preferred":[
        "Ramgad"
    ],
    "wof:name":"Ramgad",
    "wof:placetype":"locality",
    "wof:population":290
},
  "geometry": {"coordinates":[76.46225699999999,15.127026],"type":"Point"}
}