{
  "type": "Feature",
  "properties": {
    "iso:country":"IN",
    "ks:ks_name":"Badidih",
    "ks:ks_pop":115,
    "ks:ks_type":"HABITATION",
    "name:eng_x_preferred":[
        "Badidih"
    ],
    "wof:name":"Badidih",
    "wof:placetype":"locality",
    "wof:population":115
},
  "geometry": {"coordinates":[85.34835,22.993229],"type":"Point"}
}