{
  "type": "Feature",
  "properties": {
    "gn:admin1_code":"21.0",
    "gn:admin2_code":"396.0",
    "gn:asciiname":"Jambu",
    "gn:country_code":"IN",
    "gn:dem":347,
    "gn:feature_class":"P",
    "gn:feature_code":"PPL",
    "gn:name":"Jambu",
    "gn:population":0,
    "gn:timezone":"Asia/Kolkata",
    "iso:country":"IN",
    "ks:ks_name":"Jambu",
    "ks:ks_pop":314,
    "ks:ks_type":"VILLAGE",
    "name:ceb_x_preferred":[
        "Jambu"
    ],
    "name:deu_x_preferred":[
        "Jambu"
    ],
    "name:eng_x_preferred":[
        "Jambu"
    ],
    "name:nld_x_preferred":[
        "Jambu"
    ],
    "name:swe_x_preferred":[
        "Jambu"
    ],
    "wof:name":"Jambu",
    "wof:placetype":"locality",
    "wof:population":314
},
  "geometry": {"coordinates":[83.348201,19.197589],"type":"Point"}
}