{
  "type": "Feature",
  "properties": {
    "gn:admin1_code":"36",
    "gn:admin2_code":"180.0",
    "gn:asciiname":"Bhainsahi",
    "gn:country_code":"IN",
    "gn:dem":111,
    "gn:feature_class":"P",
    "gn:feature_code":"PPL",
    "gn:name":"Bhains\u0101hi",
    "gn:population":0,
    "gn:timezone":"Asia/Kolkata",
    "iso:country":"IN",
    "ks:ks_alt_nam":"Bhains\u0101hi",
    "ks:ks_name":"Bhainsahi",
    "ks:ks_pop":151,
    "ks:ks_type":"VILLAGE",
    "ks:ks_uagg_main":0,
    "name:eng_x_preferred":[
        "Bhainsahi"
    ],
    "name:eng_x_variant":[
        "Bhains\u0101hi"
    ],
    "wof:name":"Bhainsahi",
    "wof:placetype":"neighbourhood",
    "wof:population":151
},
  "geometry": {"coordinates":[81.655953,27.32957],"type":"Point"}
}