{
  "type": "Feature",
  "properties": {
    "iso:country":"IN",
    "ks:ks_name":"Nadavaramba",
    "ks:ks_pop":1456,
    "ks:ks_type":"HABITATION",
    "name:eng_x_preferred":[
        "Nadavaramba"
    ],
    "wof:name":"Nadavaramba",
    "wof:placetype":"locality",
    "wof:population":1456
},
  "geometry": {"coordinates":[76.22788,10.212719],"type":"Point"}
}