{
  "type": "Feature",
  "properties": {
    "iso:country":"IN",
    "ks:ks_name":"Kundaki",
    "ks:ks_pop":455,
    "ks:ks_type":"HABITATION",
    "name:eng_x_preferred":[
        "Kundaki"
    ],
    "wof:name":"Kundaki",
    "wof:placetype":"locality",
    "wof:population":455
},
  "geometry": {"coordinates":[71.602114,25.005617],"type":"Point"}
}