{
  "type": "Feature",
  "properties": {
    "iso:country":"IN",
    "ks:ks_name":"Patakhala",
    "ks:ks_pop":168,
    "ks:ks_type":"HABITATION",
    "name:eng_x_preferred":[
        "Patakhala"
    ],
    "wof:name":"Patakhala",
    "wof:placetype":"locality",
    "wof:population":168
},
  "geometry": {"coordinates":[84.400497,19.494509],"type":"Point"}
}