{
  "type": "Feature",
  "properties": {
    "iso:country":"IN",
    "ks:ks_name":"Nangli Parsapur",
    "ks:ks_pop":596,
    "ks:ks_type":"VILLAGE",
    "ks:ks_uagg_main":0,
    "name:eng_x_preferred":[
        "Nangli Parsapur"
    ],
    "wof:name":"Nangli Parsapur",
    "wof:placetype":"neighbourhood",
    "wof:population":596
},
  "geometry": {"coordinates":[76.61437599999999,28.043228],"type":"Point"}
}