{
  "type": "Feature",
  "properties": {
    "iso:country":"IN",
    "ks:ks_name":"Saria",
    "ks:ks_pop":112,
    "ks:ks_type":"HABITATION",
    "name:eng_x_preferred":[
        "Saria"
    ],
    "wof:name":"Saria",
    "wof:placetype":"locality",
    "wof:population":112
},
  "geometry": {"coordinates":[82.50819799999999,18.087254],"type":"Point"}
}