{
  "type": "Feature",
  "properties": {
    "iso:country":"IN",
    "ks:ks_name":"Adhariya",
    "ks:ks_pop":400,
    "ks:ks_type":"VILLAGE",
    "name:eng_x_preferred":[
        "Adhariya"
    ],
    "wof:name":"Adhariya",
    "wof:placetype":"locality",
    "wof:population":400
},
  "geometry": {"coordinates":[79.65961299999999,29.378521],"type":"Point"}
}