{
  "type": "Feature",
  "properties": {
    "gn:admin1_code":"19.0",
    "gn:admin2_code":"564.0",
    "gn:asciiname":"Godachikond",
    "gn:country_code":"IN",
    "gn:dem":633,
    "gn:feature_class":"P",
    "gn:feature_code":"PPL",
    "gn:name":"Godachikond",
    "gn:population":0,
    "gn:timezone":"Asia/Kolkata",
    "iso:country":"IN",
    "wof:name":"Godachikond",
    "wof:placetype":"locality"
},
  "geometry": {"coordinates":[75.37560000000001,14.50074],"type":"Point"}
}