{
  "type": "Feature",
  "properties": {
    "iso:country":"IN",
    "ks:ks_name":"Rasulpur Semri",
    "ks:ks_pop":1737,
    "ks:ks_type":"VILLAGE",
    "name:eng_x_preferred":[
        "Rasulpur Semri"
    ],
    "wof:name":"Rasulpur Semri",
    "wof:placetype":"locality",
    "wof:population":1737
},
  "geometry": {"coordinates":[85.73293700000001,25.643923],"type":"Point"}
}