{
  "type": "Feature",
  "properties": {
    "iso:country":"IN",
    "ks:ks_name":"Dhurian",
    "ks:ks_pop":672,
    "ks:ks_type":"VILLAGE",
    "name:eng_x_preferred":[
        "Dhurian"
    ],
    "wof:name":"Dhurian",
    "wof:placetype":"locality",
    "wof:population":672
},
  "geometry": {"coordinates":[75.743657,31.681641],"type":"Point"}
}