{
  "type": "Feature",
  "properties": {
    "iso:country":"IN",
    "ks:ks_name":"Sarakishorpal",
    "ks:ks_pop":1195,
    "ks:ks_type":"VILLAGE",
    "name:eng_x_preferred":[
        "Sarakishorpal"
    ],
    "wof:name":"Sarakishorpal",
    "wof:placetype":"locality",
    "wof:population":1195
},
  "geometry": {"coordinates":[85.185867,21.043611],"type":"Point"}
}