{
  "type": "Feature",
  "properties": {
    "iso:country":"IN",
    "ks:ks_name":"Purunapoibadi",
    "ks:ks_pop":30,
    "ks:ks_type":"VILLAGE",
    "name:eng_x_preferred":[
        "Purunapoibadi"
    ],
    "wof:name":"Purunapoibadi",
    "wof:placetype":"locality",
    "wof:population":30
},
  "geometry": {"coordinates":[84.855295,20.268975],"type":"Point"}
}