{
  "type": "Feature",
  "properties": {
    "gn:admin1_code":"28.0",
    "gn:admin2_code":"343.0",
    "gn:asciiname":"Garia",
    "gn:country_code":"IN",
    "gn:dem":8,
    "gn:feature_class":"P",
    "gn:feature_code":"PPL",
    "gn:name":"Garia",
    "gn:population":0,
    "gn:timezone":"Asia/Kolkata",
    "iso:country":"IN",
    "name:ben_x_preferred":[
        "\u0997\u09a1\u09bc\u09bf\u09af\u09bc\u09be"
    ],
    "wof:name":"Garia",
    "wof:placetype":"locality"
},
  "geometry": {"coordinates":[88.39788,22.46323],"type":"Point"}
}