{
  "type": "Feature",
  "properties": {
    "gn:admin1_code":"28.0",
    "gn:admin2_code":"338.0",
    "gn:asciiname":"Amdoba",
    "gn:country_code":"IN",
    "gn:dem":17,
    "gn:feature_class":"P",
    "gn:feature_code":"PPL",
    "gn:name":"Amdoba",
    "gn:population":0,
    "gn:timezone":"Asia/Kolkata",
    "iso:country":"IN",
    "wof:name":"Amdoba",
    "wof:placetype":"locality"
},
  "geometry": {"coordinates":[87.73484999999999,22.82702],"type":"Point"}
}