{
  "type": "Feature",
  "properties": {
    "iso:country":"IN",
    "ks:ks_name":"Angar Garia",
    "ks:ks_pop":1950,
    "ks:ks_type":"VILLAGE",
    "ks:ks_uagg_main":0,
    "name:eng_x_preferred":[
        "Angar Garia"
    ],
    "wof:name":"Angar Garia",
    "wof:placetype":"neighbourhood",
    "wof:population":1950
},
  "geometry": {"coordinates":[87.59769799999999,23.972977],"type":"Point"}
}