{
  "type": "Feature",
  "properties": {
    "iso:country":"IN",
    "ks:ks_name":"Barangaya",
    "ks:ks_pop":250,
    "ks:ks_type":"HABITATION",
    "name:eng_x_preferred":[
        "Barangaya"
    ],
    "wof:name":"Barangaya",
    "wof:placetype":"locality",
    "wof:population":250
},
  "geometry": {"coordinates":[75.421672,12.919854],"type":"Point"}
}