{
  "type": "Feature",
  "properties": {
    "iso:country":"IN",
    "ks:ks_alt_nam":"T\u0101digadapa",
    "ks:ks_name":"Tadigadapa",
    "ks:ks_pop":2442,
    "ks:ks_type":"VILLAGE",
    "ks:ks_uagg_main":0,
    "name:eng_x_preferred":[
        "Tadigadapa"
    ],
    "name:eng_x_variant":[
        "T\u0101digadapa"
    ],
    "wof:name":"Tadigadapa",
    "wof:placetype":"neighbourhood",
    "wof:population":2442
},
  "geometry": {"coordinates":[80.697424,16.470855],"type":"Point"}
}