{
  "type": "Feature",
  "properties": {
    "gn:admin1_code":"12.0",
    "gn:admin2_code":"021",
    "gn:asciiname":"Kirpalpur",
    "gn:country_code":"IN",
    "gn:dem":277,
    "gn:feature_class":"P",
    "gn:feature_code":"PPL",
    "gn:name":"Kirp\u0101lpur",
    "gn:population":0,
    "gn:timezone":"Asia/Kolkata",
    "iso:country":"IN",
    "name:mal_x_preferred":[
        "\u0d15\u0d3f\u0d7c\u0d2a\u0d3e\u0d7d\u0d2a\u0d42\u0d7c"
    ],
    "name:und_x_variant":[
        "Kirp\u0101lpur",
        "Kirp\u0101lpur Ch\u0101rk\u0101n"
    ],
    "wof:name":"Kirpalpur",
    "wof:placetype":"locality"
},
  "geometry": {"coordinates":[74.80003000000001,32.70253],"type":"Point"}
}