{
  "type": "Feature",
  "properties": {
    "iso:country":"IN",
    "ks:ks_name":"Hatipanga",
    "ks:ks_pop":48,
    "ks:ks_type":"HABITATION",
    "name:eng_x_preferred":[
        "Hatipanga"
    ],
    "wof:name":"Hatipanga",
    "wof:placetype":"locality",
    "wof:population":48
},
  "geometry": {"coordinates":[83.73356800000001,19.245088],"type":"Point"}
}