{
  "type": "Feature",
  "properties": {
    "iso:country":"IN",
    "ks:ks_name":"Kokadpa",
    "ks:ks_pop":894,
    "ks:ks_type":"VILLAGE",
    "name:eng_x_preferred":[
        "Kokadpa"
    ],
    "wof:name":"Kokadpa",
    "wof:placetype":"locality",
    "wof:population":894
},
  "geometry": {"coordinates":[74.192533,22.459489],"type":"Point"}
}