{
  "type": "Feature",
  "properties": {
    "iso:country":"IN",
    "ks:ks_name":"Mathwa Azrakba Balua Arazi",
    "ks:ks_pop":1025,
    "ks:ks_type":"VILLAGE",
    "ks:ks_uagg_main":0,
    "name:eng_x_preferred":[
        "Mathwa Azrakba Balua Arazi"
    ],
    "wof:name":"Mathwa Azrakba Balua Arazi",
    "wof:placetype":"neighbourhood",
    "wof:population":1025
},
  "geometry": {"coordinates":[85.439302,26.6023],"type":"Point"}
}