{
  "type": "Feature",
  "properties": {
    "iso:country":"IN",
    "ks:ks_alt_nam":"TARAULI",
    "ks:ks_name":"Tarauli",
    "ks:ks_pop":2673,
    "ks:ks_type":"HABITATION",
    "name:eng_x_preferred":[
        "Tarauli"
    ],
    "wof:name":"Tarauli",
    "wof:placetype":"locality",
    "wof:population":2673
},
  "geometry": {"coordinates":[79.92430899999999,27.167978],"type":"Point"}
}