{
  "type": "Feature",
  "properties": {
    "iso:country":"IN",
    "ks:ks_name":"Ledi Khurd",
    "ks:ks_pop":602,
    "ks:ks_type":"VILLAGE",
    "name:eng_x_preferred":[
        "Ledi Khurd"
    ],
    "wof:name":"Ledi Khurd",
    "wof:placetype":"locality",
    "wof:population":602
},
  "geometry": {"coordinates":[75.865549,24.525992],"type":"Point"}
}