{
  "type": "Feature",
  "properties": {
    "gn:admin1_code":"34.0",
    "gn:admin2_code":"211.0",
    "gn:asciiname":"Barna",
    "gn:country_code":"IN",
    "gn:dem":44,
    "gn:feature_class":"P",
    "gn:feature_code":"PPL",
    "gn:name":"Barna",
    "gn:population":0,
    "gn:timezone":"Asia/Kolkata",
    "iso:country":"IN",
    "name:cat_x_preferred":[
        "Bearna"
    ],
    "name:ceb_x_preferred":[
        "Barna"
    ],
    "name:eus_x_preferred":[
        "Bearna"
    ],
    "name:gle_x_preferred":[
        "Bearna"
    ],
    "name:ita_x_preferred":[
        "Bearna"
    ],
    "name:jpn_x_preferred":[
        "\u30d0\u30fc\u30ca"
    ],
    "name:kat_x_preferred":[
        "\u10d1\u10d0\u10e0\u10dc\u10d0"
    ],
    "name:nld_x_preferred":[
        "Bearna"
    ],
    "name:rus_x_preferred":[
        "\u0411\u0430\u0440\u043d\u0430"
    ],
    "name:spa_x_preferred":[
        "Bearna"
    ],
    "name:swe_x_preferred":[
        "Barna"
    ],
    "wof:name":"Barna",
    "wof:placetype":"locality"
},
  "geometry": {"coordinates":[87.08731999999998,25.7329],"type":"Point"}
}