{
  "type": "Feature",
  "properties": {
    "iso:country":"IN",
    "ks:ks_name":"Pado",
    "ks:ks_pop":416,
    "ks:ks_type":"VILLAGE",
    "name:eng_x_preferred":[
        "Pado"
    ],
    "wof:name":"Pado",
    "wof:placetype":"locality",
    "wof:population":416
},
  "geometry": {"coordinates":[80.753602,25.006541],"type":"Point"}
}