{
  "type": "Feature",
  "properties": {
    "iso:country":"IN",
    "ks:ks_alt_nam":"Bamhn bahara",
    "ks:ks_name":"Bamhn Bahara",
    "ks:ks_pop":454,
    "ks:ks_type":"HABITATION",
    "name:eng_x_preferred":[
        "Bamhn Bahara"
    ],
    "wof:name":"Bamhn Bahara",
    "wof:placetype":"locality",
    "wof:population":454
},
  "geometry": {"coordinates":[81.961575,20.246967],"type":"Point"}
}