{
  "type": "Feature",
  "properties": {
    "gn:country":"IN",
    "gn:fcode":"SCHC",
    "gn:pop":1000,
    "iso:country":"IN",
    "qs:name":"Krishnaveni Engineering college for women",
    "qs:photos_9r":0,
    "qs:photos_sr":0,
    "qs:pop_sr":"2",
    "wof:name":"Krishnaveni Engineering college for women",
    "wof:placetype":"locality",
    "wof:population":1000
},
  "geometry": {"coordinates":[80.08768000000001,16.2081],"type":"Point"}
}