{
  "type": "Feature",
  "properties": {
    "iso:country":"IN",
    "ks:ks_name":"Diyagarh",
    "ks:ks_pop":152,
    "ks:ks_type":"VILLAGE",
    "name:eng_x_preferred":[
        "Diyagarh"
    ],
    "wof:name":"Diyagarh",
    "wof:placetype":"locality",
    "wof:population":152
},
  "geometry": {"coordinates":[81.534631,23.402366],"type":"Point"}
}