{
  "type": "Feature",
  "properties": {
    "iso:country":"IN",
    "ks:ks_name":"Sanapatasundarpur",
    "ks:ks_pop":1364,
    "ks:ks_type":"VILLAGE",
    "ks:ks_uagg_main":0,
    "name:eng_x_preferred":[
        "Sanapatasundarpur"
    ],
    "wof:name":"Sanapatasundarpur",
    "wof:placetype":"neighbourhood",
    "wof:population":1364
},
  "geometry": {"coordinates":[85.99063099999999,20.283998],"type":"Point"}
}