{
  "type": "Feature",
  "properties": {
    "iso:country":"IN",
    "ks:ks_name":"Dhwaijhar",
    "ks:ks_pop":564,
    "ks:ks_type":"HABITATION",
    "name:eng_x_preferred":[
        "Dhwaijhar"
    ],
    "wof:name":"Dhwaijhar",
    "wof:placetype":"locality",
    "wof:population":564
},
  "geometry": {"coordinates":[74.60595000000001,23.87882],"type":"Point"}
}