{
  "type": "Feature",
  "properties": {
    "iso:country":"IN",
    "ks:ks_name":"Vengeri",
    "ks:ks_type":"VILLAGE",
    "name:eng_x_preferred":[
        "Vengeri"
    ],
    "wof:name":"Vengeri",
    "wof:placetype":"locality"
},
  "geometry": {"coordinates":[75.800729,11.299375],"type":"Point"}
}