{
  "type": "Feature",
  "properties": {
    "iso:country":"IN",
    "ks:ks_name":"Teetardi",
    "ks:ks_pop":6962,
    "ks:ks_type":"VILLAGE",
    "ks:ks_uagg_main":0,
    "name:eng_x_preferred":[
        "Teetardi"
    ],
    "wof:name":"Teetardi",
    "wof:placetype":"locality",
    "wof:population":6962
},
  "geometry": {"coordinates":[73.717878,24.537264],"type":"Point"}
}