{
  "type": "Feature",
  "properties": {
    "gn:admin1_code":"9.0",
    "gn:admin2_code":"482.0",
    "gn:asciiname":"Kosindra",
    "gn:country_code":"IN",
    "gn:dem":39,
    "gn:feature_class":"P",
    "gn:feature_code":"PPL",
    "gn:name":"Kosindra",
    "gn:population":0,
    "gn:timezone":"Asia/Kolkata",
    "iso:country":"IN",
    "wof:name":"Kosindra",
    "wof:placetype":"locality"
},
  "geometry": {"coordinates":[72.97608000000002,22.37266],"type":"Point"}
}