{
  "type": "Feature",
  "properties": {
    "iso:country":"IN",
    "ks:ks_name":"Musahar Tola",
    "ks:ks_pop":249,
    "ks:ks_type":"HABITATION",
    "name:eng_x_preferred":[
        "Musahar Tola"
    ],
    "wof:name":"Musahar Tola",
    "wof:placetype":"locality",
    "wof:population":249
},
  "geometry": {"coordinates":[86.539203,25.966389],"type":"Point"}
}