{
  "type": "Feature",
  "properties": {
    "iso:country":"IN",
    "ks:ks_alt_nam":"Boglamari supa",
    "ks:ks_name":"Boglamari Supa",
    "ks:ks_pop":442,
    "ks:ks_type":"HABITATION",
    "name:eng_x_preferred":[
        "Boglamari Supa"
    ],
    "wof:name":"Boglamari Supa",
    "wof:placetype":"locality",
    "wof:population":442
},
  "geometry": {"coordinates":[91.644941,26.557116],"type":"Point"}
}