{
  "type": "Feature",
  "properties": {
    "gn:admin1_code":"12.0",
    "gn:admin2_code":"9.0",
    "gn:asciiname":"Samlar",
    "gn:country_code":"IN",
    "gn:dem":1789,
    "gn:feature_class":"P",
    "gn:feature_code":"PPL",
    "gn:name":"Samlar",
    "gn:population":0,
    "gn:timezone":"Asia/Kolkata",
    "iso:country":"IN",
    "name:eng_x_preferred":[
        "Samlar"
    ],
    "wof:name":"Samlar",
    "wof:placetype":"locality"
},
  "geometry": {"coordinates":[74.72233,34.40948],"type":"Point"}
}