{
  "type": "Feature",
  "properties": {
    "gn:admin1_code":"31",
    "gn:admin2_code":"287.0",
    "gn:asciiname":"Tuidang",
    "gn:country_code":"IN",
    "gn:dem":99,
    "gn:feature_class":"P",
    "gn:feature_code":"PPL",
    "gn:name":"Tuidang",
    "gn:population":0,
    "gn:timezone":"Asia/Kolkata",
    "iso:country":"IN",
    "name:und_x_variant":[
        "Longdaw",
        "Tuidang"
    ],
    "wof:name":"Tuidang",
    "wof:placetype":"locality"
},
  "geometry": {"coordinates":[92.82872,22.25444],"type":"Point"}
}