{
  "type": "Feature",
  "properties": {
    "iso:country":"IN",
    "ks:ks_name":"Devaki Marri",
    "ks:ks_pop":56,
    "ks:ks_type":"VILLAGE",
    "name:eng_x_preferred":[
        "Devaki Marri"
    ],
    "wof:name":"Devaki Marri",
    "wof:placetype":"locality",
    "wof:population":56
},
  "geometry": {"coordinates":[79.156678,15.266789],"type":"Point"}
}