{
  "type": "Feature",
  "properties": {
    "gn:admin1_code":"12.0",
    "gn:admin2_code":"005",
    "gn:asciiname":"Sankh",
    "gn:country_code":"IN",
    "gn:dem":2570,
    "gn:feature_class":"P",
    "gn:feature_code":"PPL",
    "gn:name":"Sankh",
    "gn:population":0,
    "gn:timezone":"Asia/Kolkata",
    "iso:country":"IN",
    "name:ara_x_preferred":[
        "\u0633\u0627\u0646\u062e"
    ],
    "name:ben_x_preferred":[
        "\u09b6\u0999\u09cd\u0996"
    ],
    "name:deu_x_preferred":[
        "Sankh River"
    ],
    "name:ell_x_preferred":[
        "\u03a3\u03b1\u03bd\u03ba"
    ],
    "name:fas_x_preferred":[
        "\u0633\u0627\u0646\u062e"
    ],
    "name:fra_x_preferred":[
        "Sankh"
    ],
    "name:heb_x_preferred":[
        "\u05e1\u05d0\u05e0\u05e7"
    ],
    "name:hun_x_preferred":[
        "Sankh"
    ],
    "name:ind_x_preferred":[
        "Sankh"
    ],
    "name:ita_x_preferred":[
        "Sankh"
    ],
    "name:jpn_x_preferred":[
        "\u30b5\u30f3\u30af\u5ddd"
    ],
    "name:kor_x_preferred":[
        "\uc0c1\ud06c"
    ],
    "name:nld_x_preferred":[
        "Sankh"
    ],
    "name:pol_x_preferred":[
        "Sankh"
    ],
    "name:por_x_preferred":[
        "Sankh"
    ],
    "name:rus_x_preferred":[
        "\u0440\u0435\u043a\u0430 \u0421\u0430\u043d\u043a\u0445"
    ],
    "name:spa_x_preferred":[
        "Sankh"
    ],
    "name:swe_x_preferred":[
        "Sankh"
    ],
    "name:tur_x_preferred":[
        "Sankh"
    ],
    "name:ukr_x_preferred":[
        "\u0421\u0430\u043d\u043a\u0445"
    ],
    "name:vie_x_preferred":[
        "S\u00f4ng Sankh"
    ],
    "name:zho_cn_x_preferred":[
        "\u6851\u8d6b\u6cb3"
    ],
    "name:zho_tw_x_preferred":[
        "\u6851\u514b\u6cb3"
    ],
    "wof:name":"Sankh",
    "wof:placetype":"locality"
},
  "geometry": {"coordinates":[74.30278,33.78056],"type":"Point"}
}