{
  "type": "Feature",
  "properties": {
    "gn:admin1_code":"36",
    "gn:admin2_code":"180.0",
    "gn:asciiname":"Tiwari",
    "gn:country_code":"IN",
    "gn:dem":122,
    "gn:feature_class":"P",
    "gn:feature_code":"PPL",
    "gn:name":"Tiw\u0101ri",
    "gn:population":0,
    "gn:timezone":"Asia/Kolkata",
    "iso:country":"IN",
    "name:deu_x_preferred":[
        "Tiwari"
    ],
    "name:hin_x_preferred":[
        "\u0924\u094d\u0930\u093f\u092a\u093e\u0920\u0940"
    ],
    "name:nds_x_preferred":[
        "Tiwari"
    ],
    "name:nep_x_preferred":[
        "\u0924\u094d\u0930\u093f\u092a\u093e\u0920\u0940"
    ],
    "wof:name":"Tiwari",
    "wof:placetype":"locality"
},
  "geometry": {"coordinates":[81.43567,27.8094],"type":"Point"}
}