{
  "type": "Feature",
  "properties": {
    "iso:country":"IN",
    "ks:ks_name":"Pardewadi",
    "ks:ks_pop":610,
    "ks:ks_type":"HABITATION",
    "name:eng_x_preferred":[
        "Pardewadi"
    ],
    "wof:name":"Pardewadi",
    "wof:placetype":"locality",
    "wof:population":610
},
  "geometry": {"coordinates":[74.092974,16.264983],"type":"Point"}
}