{
  "type": "Feature",
  "properties": {
    "gn:admin1_code":"34.0",
    "gn:admin2_code":"203.0",
    "gn:asciiname":"Jharatwa",
    "gn:country_code":"IN",
    "gn:dem":119,
    "gn:feature_class":"P",
    "gn:feature_code":"PPL",
    "gn:name":"Jharatwa",
    "gn:population":0,
    "gn:timezone":"Asia/Kolkata",
    "iso:country":"IN",
    "wof:name":"Jharatwa",
    "wof:placetype":"locality"
},
  "geometry": {"coordinates":[84.34399999999999,27.24814000000001],"type":"Point"}
}