{
  "type": "Feature",
  "properties": {
    "gn:admin1_code":"34.0",
    "gn:admin2_code":"203.0",
    "gn:asciiname":"Jharatwa",
    "gn:country_code":"IN",
    "gn:dem":119,
    "gn:feature_class":"P",
    "gn:feature_code":"PPL",
    "gn:name":"Jharatwa",
    "gn:population":0,
    "gn:timezone":"Asia/Kolkata",
    "iso:country":"IN",
    "ks:ks_name":"Jharatwa",
    "ks:ks_pop":495,
    "ks:ks_type":"VILLAGE",
    "name:eng_x_preferred":[
        "Jharatwa"
    ],
    "wof:name":"Jharatwa",
    "wof:placetype":"locality",
    "wof:population":495
},
  "geometry": {"coordinates":[84.343557,27.254634],"type":"Point"}
}