{
  "type": "Feature",
  "properties": {
    "gn:admin1_code":"2",
    "gn:admin2_code":"546.0",
    "gn:asciiname":"Pandireddigudem",
    "gn:country_code":"IN",
    "gn:dem":53,
    "gn:feature_class":"P",
    "gn:feature_code":"PPL",
    "gn:name":"Pandireddig\u016bdem",
    "gn:population":0,
    "gn:timezone":"Asia/Kolkata",
    "iso:country":"IN",
    "ks:ks_name":"Pandireddigudem",
    "ks:ks_pop":607,
    "ks:ks_type":"HABITATION",
    "name:eng_x_preferred":[
        "Pandireddigudem"
    ],
    "wof:name":"Pandireddigudem",
    "wof:placetype":"locality",
    "wof:population":607
},
  "geometry": {"coordinates":[81.384,16.907808],"type":"Point"}
}