{
  "type": "Feature",
  "properties": {
    "iso:country":"IN",
    "ks:ks_name":"Telekondwadi",
    "ks:ks_pop":30,
    "ks:ks_type":"HABITATION",
    "name:eng_x_preferred":[
        "Telekondwadi"
    ],
    "wof:name":"Telekondwadi",
    "wof:placetype":"locality",
    "wof:population":30
},
  "geometry": {"coordinates":[73.105042,17.924536],"type":"Point"}
}