{
  "type": "Feature",
  "properties": {
    "iso:country":"IN",
    "ks:ks_name":"Alemani Camp",
    "ks:ks_pop":144,
    "ks:ks_type":"HABITATION",
    "name:eng_x_preferred":[
        "Alemani Camp"
    ],
    "wof:name":"Alemani Camp",
    "wof:placetype":"locality",
    "wof:population":144
},
  "geometry": {"coordinates":[76.76739499999999,15.513549],"type":"Point"}
}