{
  "type": "Feature",
  "properties": {
    "iso:country":"IN",
    "ks:ks_name":"Paschim Madhabpur",
    "ks:ks_pop":838,
    "ks:ks_type":"VILLAGE",
    "name:eng_x_preferred":[
        "Paschim Madhabpur"
    ],
    "wof:name":"Paschim Madhabpur",
    "wof:placetype":"locality",
    "wof:population":838
},
  "geometry": {"coordinates":[88.42172100000001,22.343497],"type":"Point"}
}