{
  "type": "Feature",
  "properties": {
    "gn:admin1_code":"34.0",
    "gn:admin2_code":"211.0",
    "gn:asciiname":"Padampur",
    "gn:country_code":"IN",
    "gn:dem":49,
    "gn:feature_class":"P",
    "gn:feature_code":"PPL",
    "gn:name":"Padampur",
    "gn:population":0,
    "gn:timezone":"Asia/Kolkata",
    "iso:country":"IN",
    "name:ceb_x_preferred":[
        "Padampur"
    ],
    "name:swe_x_preferred":[
        "Padampur"
    ],
    "wof:name":"Padampur",
    "wof:placetype":"neighbourhood"
},
  "geometry": {"coordinates":[87.72718999999999,26.10693],"type":"Point"}
}