{
  "type": "Feature",
  "properties": {
    "gn:admin1_code":"13.0",
    "gn:admin2_code":"597.0",
    "gn:asciiname":"Idamala",
    "gn:country_code":"IN",
    "gn:dem":357,
    "gn:feature_class":"P",
    "gn:feature_code":"PPL",
    "gn:name":"Idamala",
    "gn:population":0,
    "gn:timezone":"Asia/Kolkata",
    "iso:country":"IN",
    "wof:name":"Idamala",
    "wof:placetype":"locality"
},
  "geometry": {"coordinates":[76.84616,9.65953],"type":"Point"}
}