{
  "type": "Feature",
  "properties": {
    "gn:admin1_code":"34",
    "gn:admin2_code":"218.0",
    "gn:asciiname":"Mira Chak",
    "gn:country_code":"IN",
    "gn:dem":64,
    "gn:feature_class":"P",
    "gn:feature_code":"PPL",
    "gn:name":"Mira Chak",
    "gn:population":0,
    "gn:timezone":"Asia/Kolkata",
    "iso:country":"IN",
    "ks:ks_name":"Mirachak",
    "ks:ks_pop":438,
    "ks:ks_type":"VILLAGE",
    "name:eng_x_preferred":[
        "Mirachak"
    ],
    "name:eng_x_variant":[
        "Mira Chak"
    ],
    "wof:name":"Mirachak",
    "wof:placetype":"locality",
    "wof:population":438
},
  "geometry": {"coordinates":[84.42632500000001,26.076363],"type":"Point"}
}