{
  "type": "Feature",
  "properties": {
    "gn:admin1_code":"36",
    "gn:admin2_code":"158.0",
    "gn:asciiname":"Alipur Khalsa",
    "gn:country_code":"IN",
    "gn:dem":119,
    "gn:feature_class":"P",
    "gn:feature_code":"PPL",
    "gn:name":"Alipur Khalsa",
    "gn:population":0,
    "gn:timezone":"Asia/Kolkata",
    "iso:country":"IN",
    "ks:ks_name":"Alipur Khalsa",
    "ks:ks_pop":551,
    "ks:ks_type":"VILLAGE",
    "ks:ks_uagg_main":0,
    "name:eng_x_preferred":[
        "Alipur Khalsa"
    ],
    "wof:name":"Alipur Khalsa",
    "wof:placetype":"neighbourhood",
    "wof:population":551
},
  "geometry": {"coordinates":[81.17729,26.296327],"type":"Point"}
}