{
  "type": "Feature",
  "properties": {
    "iso:country":"IN",
    "ks:ks_name":"Upparapalle",
    "ks:ks_pop":99,
    "ks:ks_type":"HABITATION",
    "name:eng_x_preferred":[
        "Upparapalle"
    ],
    "wof:name":"Upparapalle",
    "wof:placetype":"locality",
    "wof:population":99
},
  "geometry": {"coordinates":[79.102222,14.436973],"type":"Point"}
}