{
  "type": "Feature",
  "properties": {
    "gn:admin1_code":"2.0",
    "gn:admin2_code":"547.0",
    "gn:asciiname":"Ramachandrapuram",
    "gn:country_code":"IN",
    "gn:dem":51,
    "gn:feature_class":"P",
    "gn:feature_code":"PPL",
    "gn:name":"R\u0101machandr\u0101puram",
    "gn:population":0,
    "gn:timezone":"Asia/Kolkata",
    "iso:country":"IN",
    "name:ara_x_preferred":[
        "\u0631\u0627\u0645\u0627 \u062a\u0634\u0627\u0646\u062f\u0631\u0627\u0628\u0648\u0631\u0627\u0645"
    ],
    "name:ben_bn_x_preferred":[
        "\u09b0\u09be\u09ae\u099a\u09a8\u09cd\u09a6\u09cd\u09b0\u09aa\u09c1\u09b0\u09ae"
    ],
    "name:ben_in_x_preferred":[
        "\u09b0\u09be\u09ae\u099a\u09a8\u09cd\u09a6\u09cd\u09b0\u09aa\u09c1\u09b0\u09ae"
    ],
    "name:guj_x_preferred":[
        "\u0ab0\u0abe\u0aae\u0a9a\u0a82\u0aa6\u0acd\u0ab0\u0aaa\u0ac1\u0ab0\u0aae"
    ],
    "name:hin_x_preferred":[
        "\u0930\u093e\u092e\u091a\u0902\u0926\u094d\u0930\u092a\u0941\u0930\u092e"
    ],
    "name:ita_x_preferred":[
        "Ramachandrapuram"
    ],
    "name:kan_x_preferred":[
        "\u0cb0\u0cbe\u0cae\u0c9a\u0c82\u0ca6\u0ccd\u0cb0\u0caa\u0cc1\u0cb0\u0c82"
    ],
    "name:mal_x_preferred":[
        "\u0d30\u0d3e\u0d2e\u0d1a\u0d28\u0d4d\u0d26\u0d4d\u0d30\u0d2a\u0d41\u0d30\u0d02"
    ],
    "name:mar_x_preferred":[
        "\u0930\u093e\u092e\u091a\u0902\u0926\u094d\u0930\u092a\u0941\u0930\u092e"
    ],
    "name:pan_x_preferred":[
        "\u0a30\u0a3e\u0a2e\u0a3e\u0a1a\u0a70\u0a26\u0a30\u0a3e\u0a2a\u0a41\u0a30\u0a2e"
    ],
    "name:tam_x_preferred":[
        "\u0bb0\u0bbe\u0bae\u0b9a\u0bcd\u0b9a\u0ba8\u0bcd\u0ba4\u0bbf\u0bb0\u0baa\u0bc1\u0bb0\u0bae\u0bcd"
    ],
    "name:tel_x_preferred":[
        "\u0c30\u0c3e\u0c2e\u0c1a\u0c02\u0c26\u0c4d\u0c30\u0c3e\u0c2a\u0c41\u0c30\u0c02"
    ],
    "name:urd_x_preferred":[
        "\u0631\u0627\u0645 \u0686\u0646\u062f\u0631 \u067e\u0648\u0631\u0645"
    ],
    "name:vie_x_preferred":[
        "Ramachandrapuram"
    ],
    "wof:name":"Ramachandrapuram",
    "wof:placetype":"locality"
},
  "geometry": {"coordinates":[80.99039,16.85073],"type":"Point"}
}