{
  "type": "Feature",
  "properties": {
    "gn:admin1_code":"2.0",
    "gn:admin2_code":"547.0",
    "gn:asciiname":"Ramachandrapuram",
    "gn:country_code":"IN",
    "gn:dem":51,
    "gn:feature_class":"P",
    "gn:feature_code":"PPL",
    "gn:name":"R\u0101machandr\u0101puram",
    "gn:population":0,
    "gn:timezone":"Asia/Kolkata",
    "iso:country":"IN",
    "name:ita_x_preferred":[
        "Ramachandrapuram"
    ],
    "name:vie_x_preferred":[
        "Ramachandrapuram"
    ],
    "wof:name":"Ramachandrapuram",
    "wof:placetype":"locality"
},
  "geometry": {"coordinates":[80.99039,16.85073],"type":"Point"}
}