{
  "type": "Feature",
  "properties": {
    "gn:admin1_code":"25.0",
    "gn:admin2_code":"620.0",
    "gn:asciiname":"Gudalur",
    "gn:country_code":"IN",
    "gn:dem":43,
    "gn:feature_class":"P",
    "gn:feature_code":"PPL",
    "gn:name":"G\u016bdal\u016br",
    "gn:population":0,
    "gn:timezone":"Asia/Kolkata",
    "iso:country":"IN",
    "name:bpy_x_preferred":[
        "\u0997\u09c1\u09a6\u09be\u09b2\u09c1\u09b0"
    ],
    "name:ceb_x_preferred":[
        "Gudalur"
    ],
    "name:ita_x_preferred":[
        "Gudalur"
    ],
    "name:swe_x_preferred":[
        "Gudalur"
    ],
    "wof:name":"Gudalur",
    "wof:placetype":"locality"
},
  "geometry": {"coordinates":[79.16752,10.81198],"type":"Point"}
}