{
  "type": "Feature",
  "properties": {
    "iso:country":"IN",
    "ks:ks_name":"Arasahi",
    "ks:ks_pop":78,
    "ks:ks_type":"VILLAGE",
    "name:eng_x_preferred":[
        "Arasahi"
    ],
    "wof:name":"Arasahi",
    "wof:placetype":"locality",
    "wof:population":78
},
  "geometry": {"coordinates":[85.863682,20.827462],"type":"Point"}
}