{
  "type": "Feature",
  "properties": {
    "iso:country":"IN",
    "ks:ks_name":"Pulinthanam North",
    "ks:ks_pop":755,
    "ks:ks_type":"HABITATION",
    "name:eng_x_preferred":[
        "Pulinthanam North"
    ],
    "wof:name":"Pulinthanam North",
    "wof:placetype":"locality",
    "wof:population":755
},
  "geometry": {"coordinates":[76.66169499999999,10.002013],"type":"Point"}
}