{
  "type": "Feature",
  "properties": {
    "iso:country":"IN",
    "ks:ks_alt_nam":"R\u0101jagiri",
    "ks:ks_name":"Rajagiri",
    "ks:ks_pop":432,
    "ks:ks_type":"VILLAGE",
    "name:eng_x_preferred":[
        "Rajagiri"
    ],
    "name:eng_x_variant":[
        "R\u0101jagiri"
    ],
    "wof:name":"Rajagiri",
    "wof:placetype":"locality",
    "wof:population":432
},
  "geometry": {"coordinates":[78.571432,10.588383],"type":"Point"}
}