{
  "type": "Feature",
  "properties": {
    "gn:admin1_code":"24",
    "gn:admin2_code":"123.0",
    "gn:asciiname":"Kanda ka Talab",
    "gn:country_code":"IN",
    "gn:dem":605,
    "gn:feature_class":"P",
    "gn:feature_code":"PPL",
    "gn:name":"K\u0101nda ka T\u0101l\u0101b",
    "gn:population":0,
    "gn:timezone":"Asia/Kolkata",
    "iso:country":"IN",
    "wof:name":"Kanda ka Talab",
    "wof:placetype":"locality"
},
  "geometry": {"coordinates":[73.77834,25.04311],"type":"Point"}
}