{
  "type": "Feature",
  "properties": {
    "iso:country":"IN",
    "ks:ks_name":"Chetar",
    "ks:ks_type":"VILLAGE",
    "ks:ks_uagg_main":0,
    "name:eng_x_preferred":[
        "Chetar"
    ],
    "wof:name":"Chetar",
    "wof:placetype":"neighbourhood"
},
  "geometry": {"coordinates":[84.533467,23.047022],"type":"Point"}
}