{
  "type": "Feature",
  "properties": {
    "gn:admin1_code":"37.0",
    "gn:admin2_code":"402.0",
    "gn:asciiname":"Gurguri",
    "gn:country_code":"IN",
    "gn:dem":936,
    "gn:feature_class":"P",
    "gn:feature_code":"PPL",
    "gn:name":"Gurguri",
    "gn:population":0,
    "gn:timezone":"Asia/Kolkata",
    "iso:country":"IN",
    "ks:ks_name":"Gurguri",
    "ks:ks_pop":196,
    "ks:ks_type":"VILLAGE",
    "name:eng_x_preferred":[
        "Gurguri"
    ],
    "wof:name":"Gurguri",
    "wof:placetype":"locality",
    "wof:population":196
},
  "geometry": {"coordinates":[83.794111,23.212255],"type":"Point"}
}