{
  "type": "Feature",
  "properties": {
    "iso:country":"IN",
    "ks:ks_name":"Hosdurg",
    "ks:ks_pop":587101,
    "ks:ks_type":"VILLAGE",
    "ks:ks_uagg_main":0,
    "name:eng_x_preferred":[
        "Hosdurg"
    ],
    "name:hin_x_preferred":[
        "\u0939\u094b\u0938\u0926\u0941\u0930\u094d\u0917"
    ],
    "wof:name":"Hosdurg",
    "wof:placetype":"neighbourhood",
    "wof:population":587101
},
  "geometry": {"coordinates":[75.09563300000001,12.309118],"type":"Point"}
}