{
  "type": "Feature",
  "properties": {
    "iso:country":"IN",
    "ks:ks_name":"Vadatheru",
    "ks:ks_pop":570,
    "ks:ks_type":"VILLAGE",
    "name:eng_x_preferred":[
        "Vadatheru"
    ],
    "wof:name":"Vadatheru",
    "wof:placetype":"locality",
    "wof:population":570
},
  "geometry": {"coordinates":[79.097143,10.399081],"type":"Point"}
}