{
  "type": "Feature",
  "properties": {
    "iso:country":"IN",
    "ks:ks_name":"Amanar",
    "ks:ks_pop":222,
    "ks:ks_type":"HABITATION",
    "name:eng_x_preferred":[
        "Amanar"
    ],
    "wof:name":"Amanar",
    "wof:placetype":"locality",
    "wof:population":222
},
  "geometry": {"coordinates":[81.232584,23.801307],"type":"Point"}
}