{
  "type": "Feature",
  "properties": {
    "iso:country":"IN",
    "ks:ks_alt_nam":"Vadakayil mukku",
    "ks:ks_name":"Vadakayil Mukku",
    "ks:ks_pop":770,
    "ks:ks_type":"HABITATION",
    "name:eng_x_preferred":[
        "Vadakayil Mukku"
    ],
    "wof:name":"Vadakayil Mukku",
    "wof:placetype":"locality",
    "wof:population":770
},
  "geometry": {"coordinates":[75.792807,11.482605],"type":"Point"}
}