{
  "type": "Feature",
  "properties": {
    "iso:country":"IN",
    "ks:ks_name":"Tirwalli",
    "ks:ks_pop":30,
    "ks:ks_type":"HABITATION",
    "name:eng_x_preferred":[
        "Tirwalli"
    ],
    "wof:name":"Tirwalli",
    "wof:placetype":"locality",
    "wof:population":30
},
  "geometry": {"coordinates":[74.286962,14.98724],"type":"Point"}
}