{
  "type": "Feature",
  "properties": {
    "iso:country":"IN",
    "ks:ks_alt_nam":"MelaKovanoor",
    "ks:ks_name":"Melakovanoor",
    "ks:ks_pop":211,
    "ks:ks_type":"HABITATION",
    "name:eng_x_preferred":[
        "Melakovanoor"
    ],
    "wof:name":"Melakovanoor",
    "wof:placetype":"locality",
    "wof:population":211
},
  "geometry": {"coordinates":[78.40669,9.823272],"type":"Point"}
}