{
  "type": "Feature",
  "properties": {
    "gn:admin1_code":"35",
    "gn:admin2_code":"463.0",
    "gn:asciiname":"Dilari",
    "gn:country_code":"IN",
    "gn:dem":417,
    "gn:feature_class":"P",
    "gn:feature_code":"PPL",
    "gn:name":"Dil\u0101ri",
    "gn:population":0,
    "gn:timezone":"Asia/Kolkata",
    "iso:country":"IN",
    "ks:ks_name":"Dhilari",
    "ks:ks_pop":1294,
    "ks:ks_type":"VILLAGE",
    "name:eng_x_preferred":[
        "Dhilari"
    ],
    "name:eng_x_variant":[
        "Dilari"
    ],
    "wof:name":"Dhilari",
    "wof:placetype":"locality",
    "wof:population":1294
},
  "geometry": {"coordinates":[82.355762,24.384684],"type":"Point"}
}