{
  "type": "Feature",
  "properties": {
    "iso:country":"IN",
    "ks:ks_name":"Kiratan Purwa",
    "ks:ks_pop":291,
    "ks:ks_type":"HABITATION",
    "ks:ks_uagg_main":0,
    "name:eng_x_preferred":[
        "Kiratan Purwa"
    ],
    "wof:name":"Kiratan Purwa",
    "wof:placetype":"neighbourhood",
    "wof:population":291
},
  "geometry": {"coordinates":[81.386167,26.634786],"type":"Point"}
}