{
  "type": "Feature",
  "properties": {
    "iso:country":"IN",
    "ks:ks_name":"Alaudinpur",
    "ks:ks_pop":51,
    "ks:ks_type":"HABITATION",
    "name:eng_x_preferred":[
        "Alaudinpur"
    ],
    "wof:name":"Alaudinpur",
    "wof:placetype":"locality",
    "wof:population":51
},
  "geometry": {"coordinates":[83.41117199999999,25.881396],"type":"Point"}
}