{
  "type": "Feature",
  "properties": {
    "iso:country":"IN",
    "ks:ks_name":"Edachal",
    "ks:ks_pop":235,
    "ks:ks_type":"HABITATION",
    "name:eng_x_preferred":[
        "Edachal"
    ],
    "wof:name":"Edachal",
    "wof:placetype":"locality",
    "wof:population":235
},
  "geometry": {"coordinates":[76.607952,8.977122],"type":"Point"}
}