{
  "type": "Feature",
  "properties": {
    "gn:admin1_code":"10.0",
    "gn:admin2_code":"76.0",
    "gn:asciiname":"Shafiabad",
    "gn:country_code":"IN",
    "gn:dem":215,
    "gn:feature_class":"P",
    "gn:feature_code":"PPL",
    "gn:name":"Sh\u0101fi\u0101b\u0101d",
    "gn:population":0,
    "gn:timezone":"Asia/Kolkata",
    "iso:country":"IN",
    "name:fas_x_preferred":[
        "\u0634\u0641\u06cc\u0639\u200c\u0622\u0628\u0627\u062f"
    ],
    "wof:name":"Shafiabad",
    "wof:placetype":"locality"
},
  "geometry": {"coordinates":[77.07714,28.88377],"type":"Point"}
}