{
  "type": "Feature",
  "properties": {
    "gn:admin1_code":"16.0",
    "gn:admin2_code":"530.0",
    "gn:asciiname":"Tadasinhal",
    "gn:country_code":"IN",
    "gn:dem":729,
    "gn:feature_class":"P",
    "gn:feature_code":"PPL",
    "gn:name":"Tadasinh\u0101l",
    "gn:population":0,
    "gn:timezone":"Asia/Kolkata",
    "iso:country":"IN",
    "wof:name":"Tadasinhal",
    "wof:placetype":"locality"
},
  "geometry": {"coordinates":[74.34310000000001,15.87898],"type":"Point"}
}