{
  "type": "Feature",
  "properties": {
    "iso:country":"IN",
    "ks:ks_alt_nam":"Nayegaon mal",
    "ks:ks_name":"Nayegaon Mal",
    "ks:ks_pop":286,
    "ks:ks_type":"HABITATION",
    "name:eng_x_preferred":[
        "Nayegaon Mal"
    ],
    "wof:name":"Nayegaon Mal",
    "wof:placetype":"locality",
    "wof:population":286
},
  "geometry": {"coordinates":[81.140575,22.974156],"type":"Point"}
}