{
  "type": "Feature",
  "properties": {
    "iso:country":"IN",
    "ks:ks_name":"Rawattola",
    "ks:ks_pop":461,
    "ks:ks_type":"HABITATION",
    "name:eng_x_preferred":[
        "Rawattola"
    ],
    "wof:name":"Rawattola",
    "wof:placetype":"locality",
    "wof:population":461
},
  "geometry": {"coordinates":[86.1863,24.355176],"type":"Point"}
}