{
  "type": "Feature",
  "properties": {
    "gn:admin1_code":"24.0",
    "gn:admin2_code":"126",
    "gn:asciiname":"Bijaipur",
    "gn:country_code":"IN",
    "gn:dem":470,
    "gn:feature_class":"P",
    "gn:feature_code":"PPL",
    "gn:name":"Bijaipur",
    "gn:population":0,
    "gn:timezone":"Asia/Kolkata",
    "iso:country":"IN",
    "wof:name":"Bijaipur",
    "wof:placetype":"locality"
},
  "geometry": {"coordinates":[74.80662,24.89312],"type":"Point"}
}