{
  "type": "Feature",
  "properties": {
    "iso:country":"IN",
    "ks:ks_name":"Keplakodi",
    "ks:ks_pop":374,
    "ks:ks_type":"HABITATION",
    "name:eng_x_preferred":[
        "Keplakodi"
    ],
    "wof:name":"Keplakodi",
    "wof:placetype":"locality",
    "wof:population":374
},
  "geometry": {"coordinates":[75.08258499999999,12.826549],"type":"Point"}
}