{
  "type": "Feature",
  "properties": {
    "gn:admin1_code":"28.0",
    "gn:admin2_code":"327.0",
    "gn:asciiname":"Sangsar",
    "gn:country_code":"IN",
    "gn:dem":1081,
    "gn:feature_class":"P",
    "gn:feature_code":"PPL",
    "gn:name":"Sangs\u0101r",
    "gn:population":0,
    "gn:timezone":"Asia/Kolkata",
    "iso:country":"IN",
    "name:ara_x_preferred":[
        "\u0633\u0646\u063a\u0633\u0627\u0631"
    ],
    "name:ceb_x_preferred":[
        "Sangs\u0101r"
    ],
    "name:fas_x_preferred":[
        "\u0633\u0646\u06af\u0633\u0627\u0631"
    ],
    "name:swe_x_preferred":[
        "Sangs\u0101r"
    ],
    "wof:name":"Sangsar",
    "wof:placetype":"locality"
},
  "geometry": {"coordinates":[88.53024000000001,27.12213],"type":"Point"}
}