{
  "type": "Feature",
  "properties": {
    "iso:country":"IN",
    "ks:ks_name":"Dasar Gudem",
    "ks:ks_pop":81,
    "ks:ks_type":"HABITATION",
    "ks:ks_uagg_main":0,
    "name:eng_x_preferred":[
        "Dasar Gudem"
    ],
    "wof:name":"Dasar Gudem",
    "wof:placetype":"neighbourhood",
    "wof:population":81
},
  "geometry": {"coordinates":[78.938985,13.623829],"type":"Point"}
}