{
  "type": "Feature",
  "properties": {
    "gn:admin1_code":"36",
    "gn:admin2_code":"162.0",
    "gn:asciiname":"Maharajpur Bidhuna",
    "gn:country_code":"IN",
    "gn:dem":145,
    "gn:feature_class":"P",
    "gn:feature_code":"PPL",
    "gn:name":"Mah\u0101r\u0101jpur Bidh\u016bna",
    "gn:population":0,
    "gn:timezone":"Asia/Kolkata",
    "iso:country":"IN",
    "wof:name":"Maharajpur Bidhuna",
    "wof:placetype":"locality"
},
  "geometry": {"coordinates":[79.68184000000002,26.66411],"type":"Point"}
}