{
  "type": "Feature",
  "properties": {
    "iso:country":"IN",
    "ks:ks_alt_nam":"JHAMATA",
    "ks:ks_name":"Jhamata",
    "ks:ks_pop":922,
    "ks:ks_type":"HABITATION",
    "name:eng_x_preferred":[
        "Jhamata"
    ],
    "wof:name":"Jhamata",
    "wof:placetype":"locality",
    "wof:population":922
},
  "geometry": {"coordinates":[86.576353,25.546559],"type":"Point"}
}