{
  "type": "Feature",
  "properties": {
    "iso:country":"IN",
    "name:ast_x_preferred":[
        "Mulakulam"
    ],
    "name:deu_x_preferred":[
        "Mulakulam"
    ],
    "name:eng_x_preferred":[
        "Mulakulam"
    ],
    "name:mal_x_preferred":[
        "\u0d2e\u0d41\u0d33\u0d15\u0d4d\u0d15\u0d41\u0d33\u0d02"
    ],
    "name:nld_x_preferred":[
        "Mulakulam"
    ],
    "name:zho_x_preferred":[
        "\u5e15\u5c14\u74e6\u8bfa\u5965"
    ],
    "qs:name":"Mulakulam",
    "qs:name_adm0":"India",
    "qs:name_adm1":"Kerala",
    "qs:photos":163,
    "qs:photos_1k":33,
    "qs:photos_9k":1,
    "qs:photos_9r":4,
    "qs:photos_all":163,
    "qs:photos_sr":4,
    "qs:placetype":"Town",
    "qs:pop_sr":"0",
    "wd:wordcount":294,
    "wof:name":"Mulakulam",
    "wof:placetype":"locality"
},
  "geometry": {"coordinates":[76.499611,9.801233],"type":"Point"}
}