{
  "type": "Feature",
  "properties": {
    "gn:admin1_code":"35.0",
    "gn:admin2_code":"457.0",
    "gn:asciiname":"Banjartola",
    "gn:country_code":"IN",
    "gn:dem":324,
    "gn:feature_class":"P",
    "gn:feature_code":"PPL",
    "gn:name":"Banjartol\u0101",
    "gn:population":0,
    "gn:timezone":"Asia/Kolkata",
    "iso:country":"IN",
    "ks:ks_alt_nam":"Banjartol\u0101",
    "ks:ks_name":"Banjartola",
    "ks:ks_type":"VILLAGE",
    "name:eng_x_preferred":[
        "Banjartola"
    ],
    "name:eng_x_variant":[
        "Banjartol\u0101"
    ],
    "wof:name":"Banjartola",
    "wof:placetype":"locality"
},
  "geometry": {"coordinates":[80.638632,21.539838],"type":"Point"}
}