{
  "type": "Feature",
  "properties": {
    "iso:country":"IN",
    "ks:ks_name":"Sialpala",
    "ks:ks_pop":568,
    "ks:ks_type":"VILLAGE",
    "name:eng_x_preferred":[
        "Sialpala"
    ],
    "wof:name":"Sialpala",
    "wof:placetype":"locality",
    "wof:population":568
},
  "geometry": {"coordinates":[83.468878,20.341768],"type":"Point"}
}