{
  "type": "Feature",
  "properties": {
    "gn:admin1_code":"16",
    "gn:admin2_code":"510.0",
    "gn:asciiname":"Mandar",
    "gn:country_code":"IN",
    "gn:dem":202,
    "gn:feature_class":"P",
    "gn:feature_code":"PPL",
    "gn:name":"Mandar",
    "gn:population":0,
    "gn:timezone":"Asia/Kolkata",
    "iso:country":"IN",
    "name:ceb_x_preferred":[
        "Mandar"
    ],
    "name:deu_x_preferred":[
        "Mandar"
    ],
    "name:fra_x_preferred":[
        "Mandar"
    ],
    "name:ind_x_preferred":[
        "Mandar"
    ],
    "name:und_x_variant":[
        "Mand\u0101r"
    ],
    "wof:name":"Mandar",
    "wof:placetype":"locality"
},
  "geometry": {"coordinates":[78.97184,20.00395],"type":"Point"}
}