{
  "type": "Feature",
  "properties": {
    "iso:country":"IN",
    "name:eng_x_preferred":[
        "Power House Block"
    ],
    "name:unk_x_variant":[
        "Power House Block"
    ],
    "qs:gn_adm0_cc":"IN",
    "qs:gn_local":1278985,
    "qs:gn_nam_loc":"Alappuzha, Alappuzha, Kerala, IN",
    "qs:gn_namadm1":"13",
    "qs:local_max":537,
    "qs:local_sum":1737,
    "qs:localhoods":7,
    "qs:name":"Power House Block",
    "qs:name_adm0":"India",
    "qs:name_adm1":"Kerala",
    "qs:name_adm2":"Alappuzha",
    "qs:name_local":"Alappuzha",
    "qs:photo_max":22,
    "qs:photo_sum":77,
    "qs:placetype":"Suburb",
    "qs:quad_count":8,
    "qs:woe_adm0":23424848,
    "qs:woe_adm1":2345747,
    "qs:woe_adm2":12586464,
    "qs:woe_lau":0,
    "qs:woe_local":2294673,
    "qs:woe_ver":"7.10.0",
    "wof:lang":[
        "eng"
    ],
    "wof:name":"Power House Block",
    "wof:placetype":"neighbourhood"
},
  "geometry": {"coordinates":[76.331109,9.504347],"type":"Point"}
}