{
  "type": "Feature",
  "properties": {
    "iso:country":"IN",
    "name:ara_x_preferred":[
        "\u0634\u0631\u0643\u0629 \u0628\u0627\u0648\u0631 \u0647\u0627\u0648\u0633"
    ],
    "name:ben_bn_x_preferred":[
        "\u09aa\u09be\u0993\u09af\u09bc\u09be\u09b0 \u09b9\u09be\u0989\u09b8 \u09ac\u09cd\u09b2\u0995"
    ],
    "name:ben_in_x_preferred":[
        "\u09aa\u09be\u0993\u09af\u09bc\u09be\u09b0 \u09b9\u09be\u0989\u09b8 \u09ac\u09cd\u09b2\u0995"
    ],
    "name:eng_x_preferred":[
        "Power House Block"
    ],
    "name:guj_x_preferred":[
        "\u0aaa\u0abe\u0ab5\u0ab0 \u0ab9\u0abe\u0a89\u0ab8 \u0aac\u0acd\u0ab2\u0acb\u0a95"
    ],
    "name:hin_x_preferred":[
        "\u092a\u0949\u0935\u0930 \u0939\u093e\u0909\u0938 \u092c\u094d\u0932\u0949\u0915"
    ],
    "name:kan_x_preferred":[
        "\u0caa\u0cb5\u0cb0\u0ccd \u0cb9\u0ccc\u0cb8\u0ccd"
    ],
    "name:mal_x_preferred":[
        "\u0d2a\u0d35\u0d7c \u0d39\u0d57\u0d38\u0d4d \u0d2c\u0d4d\u0d32\u0d4b\u0d15\u0d4d\u0d15\u0d4d"
    ],
    "name:mar_x_preferred":[
        "\u092a\u0949\u0935\u0930 \u0939\u093e\u090a\u0938 \u092c\u094d\u0932\u0949\u0915"
    ],
    "name:pan_x_preferred":[
        "\u0a2a\u0a3e\u0a35\u0a30 \u0a39\u0a3e\u0a0a\u0a38 \u0a2c\u0a32\u0a3e\u0a15"
    ],
    "name:tam_x_preferred":[
        "\u0bae\u0bbf\u0ba9\u0bcd\u0b9a\u0bbe\u0bb0 \u0b87\u0bb2\u0bcd\u0bb2\u0ba4\u0bcd \u0ba4\u0bca\u0b95\u0bc1\u0ba4\u0bbf"
    ],
    "name:tel_x_preferred":[
        "\u0c2a\u0c35\u0c30\u0c4d \u0c39\u0c4c\u0c38\u0c4d \u0c2c\u0c4d\u0c32\u0c3e\u0c15\u0c4d"
    ],
    "name:urd_x_preferred":[
        "\u067e\u0627\u0648\u0631 \u06c1\u0627\u0624\u0633 \u0628\u0644\u0627\u06a9"
    ],
    "qs:gn_adm0_cc":"IN",
    "qs:gn_local":1278985,
    "qs:gn_nam_loc":"Alappuzha, Alappuzha, Kerala, IN",
    "qs:gn_namadm1":"13",
    "qs:local_max":537,
    "qs:local_sum":1737,
    "qs:localhoods":7,
    "qs:name":"Power House Block",
    "qs:name_adm0":"India",
    "qs:name_adm1":"Kerala",
    "qs:name_adm2":"Alappuzha",
    "qs:name_local":"Alappuzha",
    "qs:photo_max":22,
    "qs:photo_sum":77,
    "qs:placetype":"Suburb",
    "qs:quad_count":8,
    "qs:woe_adm0":23424848,
    "qs:woe_adm1":2345747,
    "qs:woe_adm2":12586464,
    "qs:woe_lau":0,
    "qs:woe_local":2294673,
    "qs:woe_ver":"7.10.0",
    "wof:lang":[
        "eng"
    ],
    "wof:name":"Power House Block",
    "wof:placetype":"neighbourhood"
},
  "geometry": {"coordinates":[76.331109,9.504347],"type":"Point"}
}