{
  "type": "Feature",
  "properties": {
    "gn:admin1_code":"36",
    "gn:admin2_code":"191.0",
    "gn:asciiname":"Balrampur",
    "gn:country_code":"IN",
    "gn:dem":85,
    "gn:feature_class":"P",
    "gn:feature_code":"PPL",
    "gn:name":"Balr\u0101mpur",
    "gn:population":0,
    "gn:timezone":"Asia/Kolkata",
    "iso:country":"IN",
    "name:bpy_x_preferred":[
        "\u09ac\u09b2\u09b0\u09be\u09ae \u09aa\u09c1\u09b0"
    ],
    "name:cat_x_preferred":[
        "Balrampur"
    ],
    "name:ceb_x_preferred":[
        "Balr\u0101mpur"
    ],
    "name:deu_x_preferred":[
        "Balrampur"
    ],
    "name:fra_x_preferred":[
        "Balrampur"
    ],
    "name:glg_x_preferred":[
        "Balrampur"
    ],
    "name:hin_x_preferred":[
        "\u092c\u0932\u0930\u093e\u092e\u092a\u0941\u0930"
    ],
    "name:ita_x_preferred":[
        "Balrampur"
    ],
    "name:mlg_x_preferred":[
        "Balrampur"
    ],
    "name:msa_x_preferred":[
        "Balrampur"
    ],
    "name:nep_x_preferred":[
        "\u092c\u0932\u0930\u093e\u092e\u092a\u0941\u0930"
    ],
    "name:new_x_preferred":[
        "\u092c\u0932\u0930\u093e\u092e\u092a\u0941\u0930"
    ],
    "name:nld_x_preferred":[
        "Balrampur"
    ],
    "name:pam_x_preferred":[
        "Balrampur"
    ],
    "name:pnb_x_preferred":[
        "\u0628\u0644\u0631\u0627\u0645 \u067e\u0648\u0631"
    ],
    "name:pol_x_preferred":[
        "Balrampur"
    ],
    "name:rus_x_preferred":[
        "\u0411\u0430\u043b\u0440\u0430\u043c\u043f\u0443\u0440"
    ],
    "name:san_x_preferred":[
        "\u092c\u0932\u0930\u093e\u092e\u092a\u0941\u0930\u092e\u094d"
    ],
    "name:spa_x_preferred":[
        "Balrampur"
    ],
    "name:swe_x_preferred":[
        "Balrampur"
    ],
    "name:urd_x_preferred":[
        "\u0628\u0644\u0631\u0627\u0645 \u067e\u0648\u0631"
    ],
    "name:vie_x_preferred":[
        "Balrampur"
    ],
    "name:zho_x_preferred":[
        "\u5df4\u5c14\u62c9\u59c6\u666e\u5c14"
    ],
    "wof:name":"Balrampur",
    "wof:placetype":"locality"
},
  "geometry": {"coordinates":[83.19620999999999,26.09263],"type":"Point"}
}