{
  "type": "Feature",
  "properties": {
    "iso:country":"IN",
    "ks:ks_alt_nam":"Chak H\u0101fiz",
    "ks:ks_name":"Chak Hafiz",
    "ks:ks_type":"VILLAGE",
    "ks:ks_uagg_main":0,
    "name:eng_x_preferred":[
        "Chak Hafiz"
    ],
    "name:eng_x_variant":[
        "Chak H\u0101fiz"
    ],
    "wof:name":"Chak Hafiz",
    "wof:placetype":"neighbourhood"
},
  "geometry": {"coordinates":[84.630571,26.044299],"type":"Point"}
}