{
  "type": "Feature",
  "properties": {
    "gn:admin1_code":"34.0",
    "gn:admin2_code":"221.0",
    "gn:asciiname":"Reriahi",
    "gn:country_code":"IN",
    "gn:dem":50,
    "gn:feature_class":"P",
    "gn:feature_code":"PPL",
    "gn:name":"Reri\u0101hi",
    "gn:population":0,
    "gn:timezone":"Asia/Kolkata",
    "iso:country":"IN",
    "name:eng_x_preferred":[
        "Reri\u0101hi"
    ],
    "wof:name":"Reriahi",
    "wof:placetype":"locality"
},
  "geometry": {"coordinates":[85.61105999999999,25.70166],"type":"Point"}
}