{
  "type": "Feature",
  "properties": {
    "iso:country":"IN",
    "ks:ks_name":"Manain Tola",
    "ks:ks_pop":608,
    "ks:ks_type":"HABITATION",
    "ks:ks_uagg_main":0,
    "name:eng_x_preferred":[
        "Manain Tola"
    ],
    "wof:name":"Manain Tola",
    "wof:placetype":"neighbourhood",
    "wof:population":608
},
  "geometry": {"coordinates":[86.03249099999999,25.791116],"type":"Point"}
}