{
  "type": "Feature",
  "properties": {
    "iso:country":"IN",
    "ks:ks_alt_nam":"SOULMARI JAMURIVITA",
    "ks:ks_name":"Soulmari Jamurivita",
    "ks:ks_pop":403,
    "ks:ks_type":"HABITATION",
    "name:eng_x_preferred":[
        "Soulmari Jamurivita"
    ],
    "wof:name":"Soulmari Jamurivita",
    "wof:placetype":"locality",
    "wof:population":403
},
  "geometry": {"coordinates":[88.541901,26.520715],"type":"Point"}
}