{
  "type": "Feature",
  "properties": {
    "gn:admin1_code":"39.0",
    "gn:admin2_code":"64.0",
    "gn:asciiname":"Sainar",
    "gn:country_code":"IN",
    "gn:dem":1305,
    "gn:feature_class":"P",
    "gn:feature_code":"PPL",
    "gn:name":"Sain\u0101r",
    "gn:population":0,
    "gn:timezone":"Asia/Kolkata",
    "iso:country":"IN",
    "ks:ks_alt_nam":"Sain\u0101r",
    "ks:ks_name":"Sainar",
    "ks:ks_pop":369,
    "ks:ks_type":"VILLAGE",
    "name:eng_x_preferred":[
        "Sainar"
    ],
    "name:eng_x_variant":[
        "Sain\u0101r"
    ],
    "wof:name":"Sainar",
    "wof:placetype":"locality",
    "wof:population":369
},
  "geometry": {"coordinates":[79.62596000000001,29.597168],"type":"Point"}
}