{
  "type": "Feature",
  "properties": {
    "iso:country":"IN",
    "ks:ks_name":"Sriramchandrapur",
    "ks:ks_pop":6794,
    "ks:ks_type":"VILLAGE",
    "name:eng_x_preferred":[
        "Sriramchandrapur"
    ],
    "wof:name":"Sriramchandrapur",
    "wof:placetype":"locality",
    "wof:population":6794
},
  "geometry": {"coordinates":[85.79803699999999,19.940951],"type":"Point"}
}