{
  "type": "Feature",
  "properties": {
    "gn:admin1_code":"17.0",
    "gn:admin2_code":"279",
    "gn:asciiname":"Chassud",
    "gn:country_code":"IN",
    "gn:dem":936,
    "gn:feature_class":"P",
    "gn:feature_code":"PPL",
    "gn:name":"Chassud",
    "gn:population":0,
    "gn:timezone":"Asia/Kolkata",
    "iso:country":"IN",
    "name:und_x_variant":[
        "Chassad",
        "Chassud"
    ],
    "wof:name":"Chassud",
    "wof:placetype":"locality"
},
  "geometry": {"coordinates":[94.50988,24.79776],"type":"Point"}
}