{
  "type": "Feature",
  "properties": {
    "iso:country":"IN",
    "ks:ks_name":"Hiroli",
    "ks:ks_pop":176,
    "ks:ks_type":"HABITATION",
    "name:eng_x_preferred":[
        "Hiroli"
    ],
    "wof:name":"Hiroli",
    "wof:placetype":"locality",
    "wof:population":176
},
  "geometry": {"coordinates":[81.136996,18.726383],"type":"Point"}
}