{
  "type": "Feature",
  "properties": {
    "iso:country":"IN",
    "ks:ks_name":"Mahes Parasi",
    "ks:ks_pop":1227,
    "ks:ks_type":"HABITATION",
    "name:eng_x_preferred":[
        "Mahes Parasi"
    ],
    "wof:name":"Mahes Parasi",
    "wof:placetype":"locality",
    "wof:population":1227
},
  "geometry": {"coordinates":[84.637535,25.039779],"type":"Point"}
}