{
  "type": "Feature",
  "properties": {
    "gn:admin1_code":"40",
    "gn:admin2_code":"532.0",
    "gn:asciiname":"Lakhampur",
    "gn:country_code":"IN",
    "gn:dem":425,
    "gn:feature_class":"P",
    "gn:feature_code":"PPL",
    "gn:name":"Lakhampur",
    "gn:population":0,
    "gn:timezone":"Asia/Kolkata",
    "iso:country":"IN",
    "wof:name":"Lakhampur",
    "wof:placetype":"locality"
},
  "geometry": {"coordinates":[78.41813,19.31496],"type":"Point"}
}