{
  "type": "Feature",
  "properties": {
    "gn:admin1_code":"25.0",
    "gn:admin2_code":"616.0",
    "gn:asciiname":"Vadakkukanjankollai",
    "gn:country_code":"IN",
    "gn:dem":20,
    "gn:feature_class":"P",
    "gn:feature_code":"PPL",
    "gn:name":"Vadakkukanj\u0101nkollai",
    "gn:population":0,
    "gn:timezone":"Asia/Kolkata",
    "iso:country":"IN",
    "ks:ks_name":"Vada Kanjankollai",
    "ks:ks_pop":1265,
    "ks:ks_type":"HABITATION",
    "name:eng_x_preferred":[
        "Vada Kanjankollai"
    ],
    "name:eng_x_variant":[
        "Vadakkukanjankollai"
    ],
    "wof:name":"Vada Kanjankollai",
    "wof:placetype":"locality",
    "wof:population":1265
},
  "geometry": {"coordinates":[79.472846,11.173899],"type":"Point"}
}