{
  "type": "Feature",
  "properties": {
    "iso:country":"IN",
    "ks:ks_name":"Ranjit Dey Para",
    "ks:ks_pop":539,
    "ks:ks_type":"HABITATION",
    "ks:ks_uagg_main":0,
    "name:eng_x_preferred":[
        "Ranjit Dey Para"
    ],
    "wof:name":"Ranjit Dey Para",
    "wof:placetype":"neighbourhood",
    "wof:population":539
},
  "geometry": {"coordinates":[91.473968,23.551404],"type":"Point"}
}