{
  "type": "Feature",
  "properties": {
    "iso:country":"IN",
    "ks:ks_alt_nam":"10 SJM",
    "ks:ks_name":"10 Sjm",
    "ks:ks_pop":476,
    "ks:ks_type":"HABITATION",
    "name:eng_x_preferred":[
        "10 Sjm"
    ],
    "wof:name":"10 Sjm",
    "wof:placetype":"locality",
    "wof:population":476
},
  "geometry": {"coordinates":[73.298333,29.307778],"type":"Point"}
}