{
  "type": "Feature",
  "properties": {
    "gn:admin1_code":"36",
    "gn:admin2_code":"175.0",
    "gn:asciiname":"Muhiuddinpur",
    "gn:country_code":"IN",
    "gn:dem":95,
    "gn:feature_class":"P",
    "gn:feature_code":"PPL",
    "gn:name":"Muh\u012budd\u012bnpur",
    "gn:population":0,
    "gn:timezone":"Asia/Kolkata",
    "iso:country":"IN",
    "wof:name":"Muhiuddinpur",
    "wof:placetype":"locality"
},
  "geometry": {"coordinates":[82.18243000000002,25.49355],"type":"Point"}
}