{
  "type": "Feature",
  "properties": {
    "gn:admin1_code":"10",
    "gn:admin2_code":"83.0",
    "gn:asciiname":"Dhurana",
    "gn:country_code":"IN",
    "gn:dem":221,
    "gn:feature_class":"P",
    "gn:feature_code":"PPL",
    "gn:name":"Dhur\u0101na",
    "gn:population":0,
    "gn:timezone":"Asia/Kolkata",
    "iso:country":"IN",
    "wof:name":"Dhurana",
    "wof:placetype":"locality"
},
  "geometry": {"coordinates":[76.50988000000002,28.73283],"type":"Point"}
}