{
  "type": "Feature",
  "properties": {
    "gn:admin1_code":"24",
    "gn:admin2_code":"110.0",
    "gn:asciiname":"Shikarpura",
    "gn:country_code":"IN",
    "gn:dem":365,
    "gn:feature_class":"P",
    "gn:feature_code":"PPL",
    "gn:name":"Shik\u0101rpura",
    "gn:population":0,
    "gn:timezone":"Asia/Kolkata",
    "iso:country":"IN",
    "wof:name":"Shikarpura",
    "wof:placetype":"locality"
},
  "geometry": {"coordinates":[75.7942,26.77529],"type":"Point"}
}