{
  "type": "Feature",
  "properties": {
    "iso:country":"IN",
    "ks:ks_name":"Murthivaniguda",
    "ks:ks_pop":83,
    "ks:ks_type":"HABITATION",
    "name:eng_x_preferred":[
        "Murthivaniguda"
    ],
    "wof:name":"Murthivaniguda",
    "wof:placetype":"locality",
    "wof:population":83
},
  "geometry": {"coordinates":[83.88760499999999,18.694396],"type":"Point"}
}