{
  "type": "Feature",
  "properties": {
    "iso:country":"IN",
    "ks:ks_name":"Badadewadi",
    "ks:ks_pop":116,
    "ks:ks_type":"HABITATION",
    "name:eng_x_preferred":[
        "Badadewadi"
    ],
    "wof:name":"Badadewadi",
    "wof:placetype":"locality",
    "wof:population":116
},
  "geometry": {"coordinates":[73.584992,17.53925],"type":"Point"}
}