{
  "type": "Feature",
  "properties": {
    "gn:admin1_code":"36.0",
    "gn:admin2_code":"150.0",
    "gn:asciiname":"Hashimpur",
    "gn:country_code":"IN",
    "gn:dem":165,
    "gn:feature_class":"P",
    "gn:feature_code":"PPL",
    "gn:name":"H\u0101shimpur",
    "gn:population":0,
    "gn:timezone":"Asia/Kolkata",
    "iso:country":"IN",
    "ks:ks_alt_nam":"H\u0101shimpur",
    "ks:ks_name":"Hashimpur",
    "ks:ks_pop":237,
    "ks:ks_type":"VILLAGE",
    "name:eng_x_preferred":[
        "Hashimpur"
    ],
    "name:eng_x_variant":[
        "H\u0101shimpur"
    ],
    "wof:name":"Hashimpur",
    "wof:placetype":"locality",
    "wof:population":237
},
  "geometry": {"coordinates":[79.328491,28.224178],"type":"Point"}
}