{
  "type": "Feature",
  "properties": {
    "iso:country":"IN",
    "ks:ks_name":"Dagraha",
    "ks:ks_pop":1392,
    "ks:ks_type":"VILLAGE",
    "ks:ks_uagg_main":0,
    "name:eng_x_preferred":[
        "Dagraha"
    ],
    "wof:name":"Dagraha",
    "wof:placetype":"neighbourhood",
    "wof:population":1392
},
  "geometry": {"coordinates":[85.066,26.342791],"type":"Point"}
}