{
  "type": "Feature",
  "properties": {
    "iso:country":"IN",
    "ks:ks_name":"Randhom Para",
    "ks:ks_pop":271,
    "ks:ks_type":"HABITATION",
    "ks:ks_uagg_main":0,
    "name:eng_x_preferred":[
        "Randhom Para"
    ],
    "wof:name":"Randhom Para",
    "wof:placetype":"neighbourhood",
    "wof:population":271
},
  "geometry": {"coordinates":[91.64331300000001,23.730449],"type":"Point"}
}