{
  "type": "Feature",
  "properties": {
    "gn:admin1_code":"23.0",
    "gn:admin2_code":"043",
    "gn:asciiname":"Bhagu",
    "gn:country_code":"IN",
    "gn:dem":187,
    "gn:feature_class":"P",
    "gn:feature_code":"PPL",
    "gn:name":"Bh\u0101gu",
    "gn:population":0,
    "gn:timezone":"Asia/Kolkata",
    "iso:country":"IN",
    "name:und_x_variant":[
        "Bh\u0101ngu",
        "Bh\u0101gu"
    ],
    "wof:name":"Bhagu",
    "wof:placetype":"locality"
},
  "geometry": {"coordinates":[74.23099000000001,30.03156],"type":"Point"}
}