{
  "type": "Feature",
  "properties": {
    "iso:country":"IN",
    "ks:ks_name":"Anjarvathalai",
    "ks:ks_pop":757,
    "ks:ks_type":"HABITATION",
    "name:eng_x_preferred":[
        "Anjarvathalai"
    ],
    "wof:name":"Anjarvathalai",
    "wof:placetype":"locality",
    "wof:population":757
},
  "geometry": {"coordinates":[79.56427499999999,11.102388],"type":"Point"}
}