{
  "type": "Feature",
  "properties": {
    "iso:country":"IN",
    "ks:ks_name":"Lohatha",
    "ks:ks_pop":0,
    "ks:ks_type":"VILLAGE",
    "name:eng_x_preferred":[
        "Lohatha"
    ],
    "wof:name":"Lohatha",
    "wof:placetype":"locality",
    "wof:population":0
},
  "geometry": {"coordinates":[83.201914,25.715933],"type":"Point"}
}