{
  "type": "Feature",
  "properties": {
    "iso:country":"IN",
    "ks:ks_name":"Neeramakulam",
    "ks:ks_pop":1105,
    "ks:ks_type":"HABITATION",
    "name:eng_x_preferred":[
        "Neeramakulam"
    ],
    "wof:name":"Neeramakulam",
    "wof:placetype":"locality",
    "wof:population":1105
},
  "geometry": {"coordinates":[76.981149,9.201513],"type":"Point"}
}