{
  "type": "Feature",
  "properties": {
    "iso:country":"IN",
    "ks:ks_name":"Thombrewadi",
    "ks:ks_pop":51,
    "ks:ks_type":"HABITATION",
    "name:eng_x_preferred":[
        "Thombrewadi"
    ],
    "wof:name":"Thombrewadi",
    "wof:placetype":"locality",
    "wof:population":51
},
  "geometry": {"coordinates":[73.42042499999999,16.624131],"type":"Point"}
}