{
  "type": "Feature",
  "properties": {
    "iso:country":"IN",
    "ks:ks_alt_nam":"U.S. Durga Nagar Khasia Punji",
    "ks:ks_name":"U.s. Durga Nagar Khasia Punji",
    "ks:ks_pop":150,
    "ks:ks_type":"HABITATION",
    "name:eng_x_preferred":[
        "U.s. Durga Nagar Khasia Punji"
    ],
    "wof:name":"U.s. Durga Nagar Khasia Punji",
    "wof:placetype":"locality",
    "wof:population":150
},
  "geometry": {"coordinates":[93.120407,24.882261],"type":"Point"}
}