{
  "type": "Feature",
  "properties": {
    "iso:country":"IN",
    "ks:ks_name":"Dubekarkatkarwadi",
    "ks:ks_pop":50,
    "ks:ks_type":"HABITATION",
    "name:eng_x_preferred":[
        "Dubekarkatkarwadi"
    ],
    "wof:name":"Dubekarkatkarwadi",
    "wof:placetype":"locality",
    "wof:population":50
},
  "geometry": {"coordinates":[73.28806,18.516923],"type":"Point"}
}