{
  "type": "Feature",
  "properties": {
    "iso:country":"IN",
    "ks:ks_name":"Smashanam Road",
    "ks:ks_pop":815,
    "ks:ks_type":"HABITATION",
    "name:eng_x_preferred":[
        "Smashanam Road"
    ],
    "wof:name":"Smashanam Road",
    "wof:placetype":"locality",
    "wof:population":815
},
  "geometry": {"coordinates":[76.327326,11.101707],"type":"Point"}
}