{
  "type": "Feature",
  "properties": {
    "iso:country":"IN",
    "ks:ks_name":"Byala",
    "ks:ks_pop":211,
    "ks:ks_type":"HABITATION",
    "name:eng_x_preferred":[
        "Byala"
    ],
    "wof:name":"Byala",
    "wof:placetype":"locality",
    "wof:population":211
},
  "geometry": {"coordinates":[77.028373,13.399302],"type":"Point"}
}