{
  "type": "Feature",
  "properties": {
    "gn:admin1_code":"19.0",
    "gn:admin2_code":"577.0",
    "gn:asciiname":"Metkathundi",
    "gn:country_code":"IN",
    "gn:dem":713,
    "gn:feature_class":"P",
    "gn:feature_code":"PPL",
    "gn:name":"Metkathundi",
    "gn:population":0,
    "gn:timezone":"Asia/Kolkata",
    "iso:country":"IN",
    "ks:ks_name":"Netkalhundi",
    "ks:ks_pop":146,
    "ks:ks_type":"VILLAGE",
    "name:eng_x_preferred":[
        "Netkalhundi"
    ],
    "name:eng_x_variant":[
        "Metkathundi"
    ],
    "wof:name":"Netkalhundi",
    "wof:placetype":"locality",
    "wof:population":146
},
  "geometry": {"coordinates":[76.164411,11.872028],"type":"Point"}
}