{
  "type": "Feature",
  "properties": {
    "iso:country":"IN",
    "ks:ks_name":"Bijoypur",
    "ks:ks_pop":2174,
    "ks:ks_type":"VILLAGE",
    "ks:ks_uagg_main":0,
    "name:eng_x_preferred":[
        "Bijoypur"
    ],
    "wof:name":"Bijoypur",
    "wof:placetype":"neighbourhood",
    "wof:population":2174
},
  "geometry": {"coordinates":[88.06187799999999,24.405364],"type":"Point"}
}