{
  "type": "Feature",
  "properties": {
    "iso:country":"IN",
    "ks:ks_name":"Sirishdanga",
    "ks:ks_pop":417,
    "ks:ks_type":"VILLAGE",
    "name:eng_x_preferred":[
        "Sirishdanga"
    ],
    "wof:name":"Sirishdanga",
    "wof:placetype":"locality",
    "wof:population":417
},
  "geometry": {"coordinates":[87.187411,22.438035],"type":"Point"}
}