{
  "type": "Feature",
  "properties": {
    "gn:admin1_code":"36.0",
    "gn:admin2_code":"136.0",
    "gn:asciiname":"Hamidabad",
    "gn:country_code":"IN",
    "gn:dem":203,
    "gn:feature_class":"P",
    "gn:feature_code":"PPL",
    "gn:name":"H\u0101mid\u0101b\u0101d",
    "gn:population":0,
    "gn:timezone":"Asia/Kolkata",
    "iso:country":"IN",
    "ks:ks_alt_nam":"H\u0101mid\u0101b\u0101d",
    "ks:ks_name":"Hamidabad",
    "ks:ks_type":"VILLAGE",
    "name:eng_x_preferred":[
        "Hamidabad"
    ],
    "name:eng_x_variant":[
        "H\u0101mid\u0101b\u0101d"
    ],
    "wof:name":"Hamidabad",
    "wof:placetype":"locality"
},
  "geometry": {"coordinates":[79.27730200000001,28.950323],"type":"Point"}
}