{
  "type": "Feature",
  "properties": {
    "iso:country":"IN",
    "ks:ks_name":"Bhinikpura",
    "ks:ks_pop":0,
    "ks:ks_type":"VILLAGE",
    "name:eng_x_preferred":[
        "Bhinikpura"
    ],
    "wof:name":"Bhinikpura",
    "wof:placetype":"locality",
    "wof:population":0
},
  "geometry": {"coordinates":[84.145386,25.644849],"type":"Point"}
}