{
  "type": "Feature",
  "properties": {
    "gn:admin1_code":"39",
    "gn:admin2_code":"61.0",
    "gn:asciiname":"Japakhet",
    "gn:country_code":"IN",
    "gn:dem":1117,
    "gn:feature_class":"P",
    "gn:feature_code":"PPL",
    "gn:name":"J\u0101p\u0101khet",
    "gn:population":0,
    "gn:timezone":"Asia/Kolkata",
    "iso:country":"IN",
    "wof:name":"Japakhet",
    "wof:placetype":"locality"
},
  "geometry": {"coordinates":[78.87586999999998,29.74572],"type":"Point"}
}