{
  "type": "Feature",
  "properties": {
    "gn:admin1_code":"09",
    "gn:admin2_code":"487.0",
    "gn:asciiname":"Surpan",
    "gn:country_code":"IN",
    "gn:dem":75,
    "gn:feature_class":"P",
    "gn:feature_code":"PPL",
    "gn:name":"Surpan",
    "gn:population":0,
    "gn:timezone":"Asia/Kolkata",
    "iso:country":"IN",
    "wof:name":"Surpan",
    "wof:placetype":"locality"
},
  "geometry": {"coordinates":[73.80309,21.817],"type":"Point"}
}