{
  "type": "Feature",
  "properties": {
    "gn:admin1_code":"09",
    "gn:admin2_code":"487.0",
    "gn:asciiname":"Surpan",
    "gn:country_code":"IN",
    "gn:dem":75,
    "gn:feature_class":"P",
    "gn:feature_code":"PPL",
    "gn:name":"Surpan",
    "gn:population":0,
    "gn:timezone":"Asia/Kolkata",
    "iso:country":"IN",
    "ks:ks_name":"Surpan",
    "ks:ks_pop":288,
    "ks:ks_type":"VILLAGE",
    "name:eng_x_preferred":[
        "Surpan"
    ],
    "wof:name":"Surpan",
    "wof:placetype":"locality",
    "wof:population":288
},
  "geometry": {"coordinates":[73.80308599999999,21.817002],"type":"Point"}
}