{
  "type": "Feature",
  "properties": {
    "iso:country":"IN",
    "ks:ks_name":"Surupada",
    "ks:ks_pop":150,
    "ks:ks_type":"HABITATION",
    "name:eng_x_preferred":[
        "Surupada"
    ],
    "wof:name":"Surupada",
    "wof:placetype":"locality",
    "wof:population":150
},
  "geometry": {"coordinates":[84.54032599999999,21.959144],"type":"Point"}
}