{
  "type": "Feature",
  "properties": {
    "gn:admin1_code":"34.0",
    "gn:admin2_code":"235.0",
    "gn:asciiname":"Jagarnathbigha",
    "gn:country_code":"IN",
    "gn:dem":171,
    "gn:feature_class":"P",
    "gn:feature_code":"PPL",
    "gn:name":"Jagarn\u0101thbigh\u0101",
    "gn:population":0,
    "gn:timezone":"Asia/Kolkata",
    "iso:country":"IN",
    "wof:name":"Jagarnathbigha",
    "wof:placetype":"locality"
},
  "geometry": {"coordinates":[84.1708,24.54957000000001],"type":"Point"}
}