{
  "type": "Feature",
  "properties": {
    "iso:country":"IN",
    "ks:ks_name":"Melasethi",
    "ks:ks_pop":502,
    "ks:ks_type":"HABITATION",
    "name:eng_x_preferred":[
        "Melasethi"
    ],
    "wof:name":"Melasethi",
    "wof:placetype":"locality",
    "wof:population":502
},
  "geometry": {"coordinates":[79.608625,10.669225],"type":"Point"}
}