{
  "type": "Feature",
  "properties": {
    "gn:admin1_code":"25.0",
    "gn:admin2_code":"602.0",
    "gn:asciiname":"Subbanayakakhandriga",
    "gn:country_code":"IN",
    "gn:dem":104,
    "gn:feature_class":"P",
    "gn:feature_code":"PPL",
    "gn:name":"Subban\u0101yakakhandriga",
    "gn:population":0,
    "gn:timezone":"Asia/Kolkata",
    "iso:country":"IN",
    "wof:name":"Subbanayakakhandriga",
    "wof:placetype":"neighbourhood"
},
  "geometry": {"coordinates":[79.56473,13.21232],"type":"Point"}
}