{
  "type": "Feature",
  "properties": {
    "iso:country":"IN",
    "ks:ks_alt_nam":"Indra nagar",
    "ks:ks_name":"Indra Nagar",
    "ks:ks_pop":513,
    "ks:ks_type":"HABITATION",
    "name:eng_x_preferred":[
        "Indra Nagar"
    ],
    "wof:name":"Indra Nagar",
    "wof:placetype":"locality",
    "wof:population":513
},
  "geometry": {"coordinates":[78.632867,11.383893],"type":"Point"}
}