{
  "type": "Feature",
  "properties": {
    "iso:country":"IN",
    "ks:ks_name":"Alampalayam",
    "ks:ks_pop":190,
    "ks:ks_type":"HABITATION",
    "ks:ks_uagg_main":0,
    "name:eng_x_preferred":[
        "Alampalayam"
    ],
    "wof:name":"Alampalayam",
    "wof:placetype":"neighbourhood",
    "wof:population":190
},
  "geometry": {"coordinates":[78.014702,11.002203],"type":"Point"}
}