{
  "type": "Feature",
  "properties": {
    "iso:country":"IN",
    "ks:ks_name":"Pale Tarf Ashtami",
    "ks:ks_pop":437,
    "ks:ks_type":"VILLAGE",
    "name:eng_x_preferred":[
        "Pale Tarf Ashtami"
    ],
    "wof:name":"Pale Tarf Ashtami",
    "wof:placetype":"locality",
    "wof:population":437
},
  "geometry": {"coordinates":[73.09769900000001,18.501781],"type":"Point"}
}