{
  "type": "Feature",
  "properties": {
    "iso:country":"IN",
    "ks:ks_name":"Bibharpur",
    "ks:ks_pop":236,
    "ks:ks_type":"VILLAGE",
    "name:eng_x_preferred":[
        "Bibharpur"
    ],
    "wof:name":"Bibharpur",
    "wof:placetype":"locality",
    "wof:population":236
},
  "geometry": {"coordinates":[87.324783,23.757083],"type":"Point"}
}