{
  "type": "Feature",
  "properties": {
    "gn:admin1_code":"37",
    "gn:admin2_code":"413.0",
    "gn:asciiname":"Pusawahi",
    "gn:country_code":"IN",
    "gn:dem":366,
    "gn:feature_class":"P",
    "gn:feature_code":"PPL",
    "gn:name":"Pusaw\u0101hi",
    "gn:population":0,
    "gn:timezone":"Asia/Kolkata",
    "iso:country":"IN",
    "ks:ks_alt_nam":"Pusaw\u0101hi",
    "ks:ks_name":"Pusawahi",
    "ks:ks_type":"VILLAGE",
    "name:eng_x_preferred":[
        "Pusawahi"
    ],
    "name:eng_x_variant":[
        "Pusaw\u0101hi"
    ],
    "wof:name":"Pusawahi",
    "wof:placetype":"locality"
},
  "geometry": {"coordinates":[81.077004,20.023463],"type":"Point"}
}