{
  "type": "Feature",
  "properties": {
    "iso:country":"IN",
    "ks:ks_name":"Gosaindi",
    "ks:ks_pop":236,
    "ks:ks_type":"VILLAGE",
    "ks:ks_uagg_main":0,
    "name:eng_x_preferred":[
        "Gosaindi"
    ],
    "wof:name":"Gosaindi",
    "wof:placetype":"neighbourhood",
    "wof:population":236
},
  "geometry": {"coordinates":[86.377849,23.241874],"type":"Point"}
}