{
  "type": "Feature",
  "properties": {
    "iso:country":"IN",
    "ks:ks_alt_nam":"chhotaa",
    "ks:ks_name":"Chhotaa",
    "ks:ks_pop":205,
    "ks:ks_type":"HABITATION",
    "ks:ks_uagg_main":0,
    "name:eng_x_preferred":[
        "Chhotaa"
    ],
    "wof:name":"Chhotaa",
    "wof:placetype":"neighbourhood",
    "wof:population":205
},
  "geometry": {"coordinates":[80.72295,26.260927],"type":"Point"}
}