{
  "type": "Feature",
  "properties": {
    "gn:admin1_code":"31.0",
    "gn:admin2_code":"286.0",
    "gn:asciiname":"New Dawn",
    "gn:country_code":"IN",
    "gn:dem":752,
    "gn:feature_class":"P",
    "gn:feature_code":"PPL",
    "gn:name":"New Dawn",
    "gn:population":0,
    "gn:timezone":"Asia/Kolkata",
    "iso:country":"IN",
    "name:deu_x_preferred":[
        "New Dawn"
    ],
    "wof:name":"New Dawn",
    "wof:placetype":"locality"
},
  "geometry": {"coordinates":[92.82868000000001,22.90247],"type":"Point"}
}