{
  "type": "Feature",
  "properties": {
    "iso:country":"IN",
    "ks:ks_name":"Nishantikira",
    "ks:ks_pop":290,
    "ks:ks_type":"HABITATION",
    "name:eng_x_preferred":[
        "Nishantikira"
    ],
    "wof:name":"Nishantikira",
    "wof:placetype":"locality",
    "wof:population":290
},
  "geometry": {"coordinates":[81.96715500000001,19.852411],"type":"Point"}
}