{
  "type": "Feature",
  "properties": {
    "gn:admin1_code":"40.0",
    "gn:admin2_code":"535",
    "gn:asciiname":"Malkapur",
    "gn:country_code":"IN",
    "gn:dem":539,
    "gn:feature_class":"P",
    "gn:feature_code":"PPL",
    "gn:name":"Malk\u0101pur",
    "gn:population":0,
    "gn:timezone":"Asia/Kolkata",
    "iso:country":"IN",
    "name:ita_x_preferred":[
        "Malkapur"
    ],
    "name:nld_x_preferred":[
        "Malkapur"
    ],
    "wof:name":"Malkapur",
    "wof:placetype":"locality"
},
  "geometry": {"coordinates":[78.05606,17.58018],"type":"Point"}
}