{
  "type": "Feature",
  "properties": {
    "iso:country":"IN",
    "ks:ks_name":"Binoli",
    "ks:ks_pop":441,
    "ks:ks_type":"VILLAGE",
    "name:eng_x_preferred":[
        "Binoli"
    ],
    "wof:name":"Binoli",
    "wof:placetype":"locality",
    "wof:population":441
},
  "geometry": {"coordinates":[79.20311700000001,29.666362],"type":"Point"}
}