{
  "type": "Feature",
  "properties": {
    "iso:country":"IN",
    "ks:ks_name":"Langteng",
    "ks:ks_pop":164,
    "ks:ks_type":"HABITATION",
    "name:eng_x_preferred":[
        "Langteng"
    ],
    "wof:name":"Langteng",
    "wof:placetype":"locality",
    "wof:population":164
},
  "geometry": {"coordinates":[92.49234199999999,25.887808],"type":"Point"}
}