{
  "type": "Feature",
  "properties": {
    "iso:country":"IN",
    "ks:ks_name":"Nadthikallu",
    "ks:ks_pop":221,
    "ks:ks_type":"HABITATION",
    "name:eng_x_preferred":[
        "Nadthikallu"
    ],
    "wof:name":"Nadthikallu",
    "wof:placetype":"locality",
    "wof:population":221
},
  "geometry": {"coordinates":[75.09163100000001,13.057823],"type":"Point"}
}