{
  "type": "Feature",
  "properties": {
    "gn:admin1_code":"12.0",
    "gn:asciiname":"Badogam",
    "gn:country_code":"IN",
    "gn:dem":2685,
    "gn:feature_class":"P",
    "gn:feature_code":"PPL",
    "gn:name":"Badog\u0101m",
    "gn:population":0,
    "gn:timezone":"Asia/Kolkata",
    "iso:country":"IN",
    "wof:name":"Badogam",
    "wof:placetype":"locality"
},
  "geometry": {"coordinates":[75.06065,34.55004],"type":"Point"}
}