{
  "type": "Feature",
  "properties": {
    "iso:country":"IN",
    "ks:ks_name":"Dodak",
    "ks:ks_pop":80,
    "ks:ks_type":"HABITATION",
    "name:eng_x_preferred":[
        "Dodak"
    ],
    "wof:name":"Dodak",
    "wof:placetype":"locality",
    "wof:population":80
},
  "geometry": {"coordinates":[81.511118,25.006867],"type":"Point"}
}