{
  "type": "Feature",
  "properties": {
    "iso:country":"IN",
    "ks:ks_name":"Bidyanagar T.E. Pt III",
    "ks:ks_pop":442,
    "ks:ks_type":"VILLAGE",
    "name:eng_x_preferred":[
        "Bidyanagar T.E. Pt III"
    ],
    "wof:name":"Bidyanagar T.E. Pt III",
    "wof:placetype":"locality",
    "wof:population":442
},
  "geometry": {"coordinates":[92.47214,24.532517],"type":"Point"}
}