{
  "type": "Feature",
  "properties": {
    "iso:country":"IN",
    "ks:ks_name":"Bailuvalasa",
    "ks:ks_pop":76,
    "ks:ks_type":"HABITATION",
    "name:eng_x_preferred":[
        "Bailuvalasa"
    ],
    "wof:name":"Bailuvalasa",
    "wof:placetype":"locality",
    "wof:population":76
},
  "geometry": {"coordinates":[82.781355,18.285785],"type":"Point"}
}