{
  "type": "Feature",
  "properties": {
    "iso:country":"IN",
    "ks:ks_name":"Bhagmahima",
    "ks:ks_pop":353,
    "ks:ks_type":"VILLAGE",
    "name:eng_x_preferred":[
        "Bhagmahima"
    ],
    "wof:name":"Bhagmahima",
    "wof:placetype":"locality",
    "wof:population":353
},
  "geometry": {"coordinates":[88.329922,26.260139],"type":"Point"}
}