{
  "type": "Feature",
  "properties": {
    "gn:admin1_code":"19",
    "gn:admin2_code":"563.0",
    "gn:asciiname":"Kanchnalli",
    "gn:country_code":"IN",
    "gn:dem":504,
    "gn:feature_class":"P",
    "gn:feature_code":"PPL",
    "gn:name":"Kanchnalli",
    "gn:population":0,
    "gn:timezone":"Asia/Kolkata",
    "iso:country":"IN",
    "ks:ks_name":"Kanchanalli",
    "ks:ks_pop":61,
    "ks:ks_type":"HABITATION",
    "name:eng_x_preferred":[
        "Kanchanalli"
    ],
    "name:eng_x_variant":[
        "Kanchnalli"
    ],
    "wof:name":"Kanchanalli",
    "wof:placetype":"locality",
    "wof:population":61
},
  "geometry": {"coordinates":[74.77116700000001,14.918736],"type":"Point"}
}