{
  "type": "Feature",
  "properties": {
    "iso:country":"IN",
    "ks:ks_name":"Jogidih",
    "ks:ks_pop":150,
    "ks:ks_type":"HABITATION",
    "name:eng_x_preferred":[
        "Jogidih"
    ],
    "wof:name":"Jogidih",
    "wof:placetype":"locality",
    "wof:population":150
},
  "geometry": {"coordinates":[81.678905,20.658583],"type":"Point"}
}