{
  "type": "Feature",
  "properties": {
    "iso:country":"IN",
    "ks:ks_name":"Kondalike",
    "ks:ks_pop":140,
    "ks:ks_type":"HABITATION",
    "name:eng_x_preferred":[
        "Kondalike"
    ],
    "wof:name":"Kondalike",
    "wof:placetype":"locality",
    "wof:population":140
},
  "geometry": {"coordinates":[75.0117,13.335636],"type":"Point"}
}