{
  "type": "Feature",
  "properties": {
    "gn:admin1_code":"36",
    "gn:admin2_code":"155.0",
    "gn:asciiname":"Rampur Lalji",
    "gn:country_code":"IN",
    "gn:dem":141,
    "gn:feature_class":"P",
    "gn:feature_code":"PPL",
    "gn:name":"R\u0101mpur L\u0101lji",
    "gn:population":0,
    "gn:timezone":"Asia/Kolkata",
    "iso:country":"IN",
    "ks:ks_name":"Ram Pur Lal Ji",
    "ks:ks_pop":428,
    "ks:ks_type":"VILLAGE",
    "ks:ks_uagg_main":0,
    "name:eng_x_preferred":[
        "Ram Pur Lal Ji"
    ],
    "wof:name":"Ram Pur Lal Ji",
    "wof:placetype":"neighbourhood",
    "wof:population":428
},
  "geometry": {"coordinates":[79.879541,27.378804],"type":"Point"}
}