{
  "type": "Feature",
  "properties": {
    "gn:admin1_code":"35",
    "gn:admin2_code":"430.0",
    "gn:asciiname":"Prabhatipurwa",
    "gn:country_code":"IN",
    "gn:dem":311,
    "gn:feature_class":"P",
    "gn:feature_code":"PPL",
    "gn:name":"Prabh\u0101t\u012bpurwa",
    "gn:population":0,
    "gn:timezone":"Asia/Kolkata",
    "iso:country":"IN",
    "wof:name":"Prabhatipurwa",
    "wof:placetype":"locality"
},
  "geometry": {"coordinates":[81.55275999999998,24.79502],"type":"Point"}
}