{
  "type": "Feature",
  "properties": {
    "iso:country":"IN",
    "ks:ks_name":"Kurukkampatti",
    "ks:ks_pop":484,
    "ks:ks_type":"HABITATION",
    "name:eng_x_preferred":[
        "Kurukkampatti"
    ],
    "wof:name":"Kurukkampatti",
    "wof:placetype":"locality",
    "wof:population":484
},
  "geometry": {"coordinates":[77.796468,9.911915],"type":"Point"}
}