{
  "type": "Feature",
  "properties": {
    "iso:country":"IN",
    "ks:ks_name":"Huchanabavi",
    "ks:ks_pop":331,
    "ks:ks_type":"HABITATION",
    "name:eng_x_preferred":[
        "Huchanabavi"
    ],
    "wof:name":"Huchanabavi",
    "wof:placetype":"locality",
    "wof:population":331
},
  "geometry": {"coordinates":[77.07884799999999,13.047387],"type":"Point"}
}