{
  "type": "Feature",
  "properties": {
    "gn:admin1_code":"25.0",
    "gn:admin2_code":"631.0",
    "gn:asciiname":"Devasamudram",
    "gn:country_code":"IN",
    "gn:dem":484,
    "gn:feature_class":"P",
    "gn:feature_code":"PPL",
    "gn:name":"Devasamudram",
    "gn:population":0,
    "gn:timezone":"Asia/Kolkata",
    "iso:country":"IN",
    "ks:ks_name":"Devasamudiram",
    "ks:ks_pop":1500,
    "ks:ks_type":"VILLAGE",
    "ks:ks_uagg_main":0,
    "name:eng_x_preferred":[
        "Devasamudiram"
    ],
    "wof:name":"Devasamudiram",
    "wof:placetype":"locality",
    "wof:population":1500
},
  "geometry": {"coordinates":[78.220163,12.498252],"type":"Point"}
}