{
  "type": "Feature",
  "properties": {
    "gn:admin1_code":"35",
    "gn:admin2_code":"442.0",
    "gn:asciiname":"Devali",
    "gn:country_code":"IN",
    "gn:dem":423,
    "gn:feature_class":"P",
    "gn:feature_code":"PPL",
    "gn:name":"Devali",
    "gn:population":0,
    "gn:timezone":"Asia/Kolkata",
    "iso:country":"IN",
    "wof:name":"Devali",
    "wof:placetype":"neighbourhood"
},
  "geometry": {"coordinates":[76.43315,23.84231],"type":"Point"}
}