{
  "type": "Feature",
  "properties": {
    "iso:country":"IN",
    "ks:ks_name":"Thoralakond",
    "ks:ks_pop":218,
    "ks:ks_type":"HABITATION",
    "name:eng_x_preferred":[
        "Thoralakond"
    ],
    "wof:name":"Thoralakond",
    "wof:placetype":"locality",
    "wof:population":218
},
  "geometry": {"coordinates":[73.241781,17.801386],"type":"Point"}
}