{
  "type": "Feature",
  "properties": {
    "gn:admin1_code":"29.0",
    "gn:admin2_code":"243.0",
    "gn:asciiname":"Phalidanda",
    "gn:country_code":"IN",
    "gn:dem":1691,
    "gn:feature_class":"P",
    "gn:feature_code":"PPL",
    "gn:name":"Ph\u0101l\u012bd\u0101nda",
    "gn:population":0,
    "gn:timezone":"Asia/Kolkata",
    "iso:country":"IN",
    "wof:name":"Phalidanda",
    "wof:placetype":"locality"
},
  "geometry": {"coordinates":[88.38984000000001,27.16983],"type":"Point"}
}