{
  "type": "Feature",
  "properties": {
    "iso:country":"IN",
    "ks:ks_name":"Patelchinta Tanda",
    "ks:ks_pop":256,
    "ks:ks_type":"HABITATION",
    "name:eng_x_preferred":[
        "Patelchinta Tanda"
    ],
    "wof:name":"Patelchinta Tanda",
    "wof:placetype":"locality",
    "wof:population":256
},
  "geometry": {"coordinates":[77.550864,17.146576],"type":"Point"}
}