{
  "type": "Feature",
  "properties": {
    "gn:admin1_code":"24.0",
    "gn:admin2_code":"110",
    "gn:asciiname":"Harbanspura",
    "gn:country_code":"IN",
    "gn:dem":389,
    "gn:feature_class":"P",
    "gn:feature_code":"PPL",
    "gn:name":"Harbanspura",
    "gn:population":0,
    "gn:timezone":"Asia/Kolkata",
    "iso:country":"IN",
    "name:fas_x_preferred":[
        "\u0647\u0631\u0628\u0646\u0633\u200c\u067e\u0648\u0631\u0647"
    ],
    "name:hin_x_preferred":[
        "\u0939\u0930\u092c\u0902\u0938\u092a\u0941\u0930"
    ],
    "name:urd_x_preferred":[
        "\u06c1\u0631\u0628\u0646\u0633 \u067e\u0648\u0631\u06c1"
    ],
    "wof:name":"Harbanspura",
    "wof:placetype":"locality"
},
  "geometry": {"coordinates":[75.70396,26.83628],"type":"Point"}
}