{
  "type": "Feature",
  "properties": {
    "iso:country":"IN",
    "ks:ks_name":"Malhpur",
    "ks:ks_pop":127,
    "ks:ks_type":"VILLAGE",
    "name:eng_x_preferred":[
        "Malhpur"
    ],
    "wof:name":"Malhpur",
    "wof:placetype":"locality",
    "wof:population":127
},
  "geometry": {"coordinates":[80.232061,28.135914],"type":"Point"}
}