{
  "type": "Feature",
  "properties": {
    "iso:country":"IN",
    "ks:ks_alt_nam":"PUNEKARVASTI",
    "ks:ks_name":"Punekarvasti",
    "ks:ks_pop":176,
    "ks:ks_type":"HABITATION",
    "name:eng_x_preferred":[
        "Punekarvasti"
    ],
    "wof:name":"Punekarvasti",
    "wof:placetype":"locality",
    "wof:population":176
},
  "geometry": {"coordinates":[75.58855,17.007278],"type":"Point"}
}