{
  "type": "Feature",
  "properties": {
    "iso:country":"IN",
    "ks:ks_name":"Musajhari",
    "ks:ks_pop":109,
    "ks:ks_type":"VILLAGE",
    "name:eng_x_preferred":[
        "Musajhari"
    ],
    "wof:name":"Musajhari",
    "wof:placetype":"locality",
    "wof:population":109
},
  "geometry": {"coordinates":[85.26748499999999,20.108393],"type":"Point"}
}