{
  "type": "Feature",
  "properties": {
    "iso:country":"IN",
    "ks:ks_name":"Varappetty",
    "ks:ks_pop":16886,
    "ks:ks_type":"VILLAGE",
    "name:eng_x_preferred":[
        "Varappetty"
    ],
    "wof:name":"Varappetty",
    "wof:placetype":"locality",
    "wof:population":16886
},
  "geometry": {"coordinates":[76.63297300000001,10.027335],"type":"Point"}
}