{
  "type": "Feature",
  "properties": {
    "iso:country":"IN",
    "ks:ks_name":"Dighabil Basti",
    "ks:ks_pop":119,
    "ks:ks_type":"HABITATION",
    "ks:ks_uagg_main":0,
    "name:eng_x_preferred":[
        "Dighabil Basti"
    ],
    "wof:name":"Dighabil Basti",
    "wof:placetype":"neighbourhood",
    "wof:population":119
},
  "geometry": {"coordinates":[93.844914,25.93701],"type":"Point"}
}