{
  "type": "Feature",
  "properties": {
    "iso:country":"IN",
    "ks:ks_alt_nam":"Burja UV5",
    "ks:ks_name":"Burja Uv5",
    "ks:ks_pop":1081,
    "ks:ks_type":"HABITATION",
    "name:eng_x_preferred":[
        "Burja Uv5"
    ],
    "wof:name":"Burja Uv5",
    "wof:placetype":"locality",
    "wof:population":1081
},
  "geometry": {"coordinates":[82.188962,19.734566],"type":"Point"}
}