{
  "type": "Feature",
  "properties": {
    "iso:country":"IN",
    "ks:ks_alt_nam":"saluvanpettai",
    "ks:ks_name":"Saluvanpettai",
    "ks:ks_pop":504,
    "ks:ks_type":"HABITATION",
    "name:eng_x_preferred":[
        "Saluvanpettai"
    ],
    "wof:name":"Saluvanpettai",
    "wof:placetype":"locality",
    "wof:population":504
},
  "geometry": {"coordinates":[79.701671,10.913943],"type":"Point"}
}