{
  "type": "Feature",
  "properties": {
    "gn:admin1_code":"34.0",
    "gn:admin2_code":"239.0",
    "gn:asciiname":"Maniari",
    "gn:country_code":"IN",
    "gn:dem":72,
    "gn:feature_class":"P",
    "gn:feature_code":"PPL",
    "gn:name":"Mani\u0101ri",
    "gn:population":0,
    "gn:timezone":"Asia/Kolkata",
    "iso:country":"IN",
    "ks:ks_alt_nam":"Mani\u0101ri",
    "ks:ks_name":"Maniari",
    "ks:ks_pop":823,
    "ks:ks_type":"VILLAGE",
    "ks:ks_uagg_main":0,
    "name:eng_x_preferred":[
        "Maniari"
    ],
    "name:eng_x_variant":[
        "Mani\u0101ri"
    ],
    "wof:name":"Maniari",
    "wof:placetype":"neighbourhood",
    "wof:population":823
},
  "geometry": {"coordinates":[84.99724399999999,25.175919],"type":"Point"}
}