{
  "type": "Feature",
  "properties": {
    "iso:country":"IN",
    "ks:ks_name":"Manipuram",
    "ks:ks_pop":367,
    "ks:ks_type":"HABITATION",
    "name:eng_x_preferred":[
        "Manipuram"
    ],
    "wof:name":"Manipuram",
    "wof:placetype":"locality",
    "wof:population":367
},
  "geometry": {"coordinates":[76.021956,11.499592],"type":"Point"}
}