{
  "type": "Feature",
  "properties": {
    "iso:country":"IN",
    "ks:ks_name":"Nuapada",
    "ks:ks_pop":25,
    "ks:ks_type":"HABITATION",
    "name:eng_x_preferred":[
        "Nuapada"
    ],
    "wof:name":"Nuapada",
    "wof:placetype":"locality",
    "wof:population":25
},
  "geometry": {"coordinates":[82.88554499999999,19.967541],"type":"Point"}
}