{
  "type": "Feature",
  "properties": {
    "gn:admin1_code":"19.0",
    "gn:admin2_code":"568.0",
    "gn:asciiname":"Muguru",
    "gn:country_code":"IN",
    "gn:dem":554,
    "gn:feature_class":"P",
    "gn:feature_code":"PPL",
    "gn:name":"M\u016bg\u016bru",
    "gn:population":0,
    "gn:timezone":"Asia/Kolkata",
    "iso:country":"IN",
    "name:ceb_x_preferred":[
        "M\u016bg\u016bru"
    ],
    "name:swe_x_preferred":[
        "M\u016bg\u016bru"
    ],
    "wof:name":"Muguru",
    "wof:placetype":"locality"
},
  "geometry": {"coordinates":[75.11997,14.59964],"type":"Point"}
}