{
  "type": "Feature",
  "properties": {
    "gn:admin1_code":"36",
    "gn:admin2_code":"188.0",
    "gn:asciiname":"Chapha",
    "gn:country_code":"IN",
    "gn:dem":78,
    "gn:feature_class":"P",
    "gn:feature_code":"PPL",
    "gn:name":"Ch\u0101pha",
    "gn:population":0,
    "gn:timezone":"Asia/Kolkata",
    "iso:country":"IN",
    "ks:ks_alt_nam":"Ch\u0101pha",
    "ks:ks_name":"Chapha",
    "ks:ks_type":"VILLAGE",
    "ks:ks_uagg_main":0,
    "name:eng_x_preferred":[
        "Chapha"
    ],
    "name:eng_x_variant":[
        "Ch\u0101pha"
    ],
    "wof:name":"Chapha",
    "wof:placetype":"neighbourhood"
},
  "geometry": {"coordinates":[83.424002,26.664749],"type":"Point"}
}