{
  "type": "Feature",
  "properties": {
    "iso:country":"IN",
    "ks:ks_name":"Godipokhari",
    "ks:ks_pop":530,
    "ks:ks_type":"VILLAGE",
    "name:eng_x_preferred":[
        "Godipokhari"
    ],
    "wof:name":"Godipokhari",
    "wof:placetype":"locality",
    "wof:population":530
},
  "geometry": {"coordinates":[86.61119100000001,21.926531],"type":"Point"}
}