{
  "type": "Feature",
  "properties": {
    "gn:admin1_code":"25.0",
    "gn:admin2_code":"605.0",
    "gn:asciiname":"Ayyampettai",
    "gn:country_code":"IN",
    "gn:dem":138,
    "gn:feature_class":"P",
    "gn:feature_code":"PPL",
    "gn:name":"Ayyampettai",
    "gn:population":0,
    "gn:timezone":"Asia/Kolkata",
    "iso:country":"IN",
    "wof:name":"Ayyampettai",
    "wof:placetype":"locality"
},
  "geometry": {"coordinates":[79.46344999999999,12.9415],"type":"Point"}
}