{
  "type": "Feature",
  "properties": {
    "iso:country":"IN",
    "ks:ks_name":"Garhi",
    "ks:ks_pop":780,
    "ks:ks_type":"HABITATION",
    "name:eng_x_preferred":[
        "Garhi"
    ],
    "wof:name":"Garhi",
    "wof:placetype":"locality",
    "wof:population":780
},
  "geometry": {"coordinates":[86.71857,24.74151],"type":"Point"}
}