{
  "type": "Feature",
  "properties": {
    "iso:country":"IN",
    "ks:ks_name":"Alliguda",
    "ks:ks_pop":289,
    "ks:ks_type":"HABITATION",
    "name:eng_x_preferred":[
        "Alliguda"
    ],
    "wof:name":"Alliguda",
    "wof:placetype":"locality",
    "wof:population":289
},
  "geometry": {"coordinates":[79.10344600000001,19.460857],"type":"Point"}
}