{
  "type": "Feature",
  "properties": {
    "iso:country":"IN",
    "ks:ks_name":"Khalil Purwa",
    "ks:ks_pop":131,
    "ks:ks_type":"HABITATION",
    "ks:ks_uagg_main":0,
    "name:eng_x_preferred":[
        "Khalil Purwa"
    ],
    "wof:name":"Khalil Purwa",
    "wof:placetype":"neighbourhood",
    "wof:population":131
},
  "geometry": {"coordinates":[81.947716,27.541312],"type":"Point"}
}