{
  "type": "Feature",
  "properties": {
    "gn:admin1_code":"35",
    "gn:admin2_code":"426.0",
    "gn:asciiname":"Jhagra",
    "gn:country_code":"IN",
    "gn:dem":313,
    "gn:feature_class":"P",
    "gn:feature_code":"PPL",
    "gn:name":"Jhagra",
    "gn:population":0,
    "gn:timezone":"Asia/Kolkata",
    "iso:country":"IN",
    "ks:ks_name":"Jhagra",
    "ks:ks_pop":474,
    "ks:ks_type":"VILLAGE",
    "name:eng_x_preferred":[
        "Jhagra"
    ],
    "wof:name":"Jhagra",
    "wof:placetype":"locality",
    "wof:population":474
},
  "geometry": {"coordinates":[80.000326,24.398473],"type":"Point"}
}