{
  "type": "Feature",
  "properties": {
    "iso:country":"IN",
    "ks:ks_name":"Mandadi",
    "ks:ks_pop":66,
    "ks:ks_type":"HABITATION",
    "ks:ks_uagg_main":0,
    "name:eng_x_preferred":[
        "Mandadi"
    ],
    "wof:name":"Mandadi",
    "wof:placetype":"neighbourhood",
    "wof:population":66
},
  "geometry": {"coordinates":[74.62014600000001,13.836316],"type":"Point"}
}