{
  "type": "Feature",
  "properties": {
    "iso:country":"IN",
    "ks:ks_name":"Lonian Purwa",
    "ks:ks_pop":170,
    "ks:ks_type":"HABITATION",
    "name:eng_x_preferred":[
        "Lonian Purwa"
    ],
    "wof:name":"Lonian Purwa",
    "wof:placetype":"locality",
    "wof:population":170
},
  "geometry": {"coordinates":[81.031882,27.732492],"type":"Point"}
}