{
  "type": "Feature",
  "properties": {
    "iso:country":"IN",
    "ks:ks_name":"Taragod",
    "ks:ks_pop":445,
    "ks:ks_type":"HABITATION",
    "name:eng_x_preferred":[
        "Taragod"
    ],
    "wof:name":"Taragod",
    "wof:placetype":"locality",
    "wof:population":445
},
  "geometry": {"coordinates":[74.533289,14.406871],"type":"Point"}
}