{
  "type": "Feature",
  "properties": {
    "gn:admin1_code":"36.0",
    "gn:admin2_code":"160",
    "gn:asciiname":"Raja Purwa",
    "gn:country_code":"IN",
    "gn:dem":135,
    "gn:feature_class":"P",
    "gn:feature_code":"PPL",
    "gn:name":"R\u0101ja Purwa",
    "gn:population":0,
    "gn:timezone":"Asia/Kolkata",
    "iso:country":"IN",
    "wof:name":"Raja Purwa",
    "wof:placetype":"locality"
},
  "geometry": {"coordinates":[79.89509,27.14808],"type":"Point"}
}