{
  "type": "Feature",
  "properties": {
    "gn:admin1_code":"35",
    "gn:admin2_code":"438.0",
    "gn:asciiname":"Bhondiya",
    "gn:country_code":"IN",
    "gn:dem":571,
    "gn:feature_class":"P",
    "gn:feature_code":"PPL",
    "gn:name":"Bhondiya",
    "gn:population":0,
    "gn:timezone":"Asia/Kolkata",
    "iso:country":"IN",
    "wof:name":"Bhondiya",
    "wof:placetype":"locality"
},
  "geometry": {"coordinates":[75.66325000000001,22.59048],"type":"Point"}
}