{
  "type": "Feature",
  "properties": {
    "iso:country":"IN",
    "ks:ks_name":"Aswarthapuram",
    "ks:ks_pop":317,
    "ks:ks_type":"HABITATION",
    "name:eng_x_preferred":[
        "Aswarthapuram"
    ],
    "wof:name":"Aswarthapuram",
    "wof:placetype":"locality",
    "wof:population":317
},
  "geometry": {"coordinates":[78.02027099999999,15.780704],"type":"Point"}
}