{
  "type": "Feature",
  "properties": {
    "iso:country":"IN",
    "ks:ks_alt_nam":"Dadhia F.V.",
    "ks:ks_name":"Dadhia F.v.",
    "ks:ks_pop":3379,
    "ks:ks_type":"HABITATION",
    "name:eng_x_preferred":[
        "Dadhia F.v."
    ],
    "wof:name":"Dadhia F.v.",
    "wof:placetype":"locality",
    "wof:population":3379
},
  "geometry": {"coordinates":[95.21985100000001,27.597531],"type":"Point"}
}