{
  "type": "Feature",
  "properties": {
    "iso:country":"IN",
    "ks:ks_name":"Gochhaka",
    "ks:ks_pop":27,
    "ks:ks_type":"VILLAGE",
    "name:eng_x_preferred":[
        "Gochhaka"
    ],
    "wof:name":"Gochhaka",
    "wof:placetype":"locality",
    "wof:population":27
},
  "geometry": {"coordinates":[83.661457,19.907254],"type":"Point"}
}