{
  "type": "Feature",
  "properties": {
    "iso:country":"IN",
    "ks:ks_name":"Hirlok",
    "ks:ks_pop":1237,
    "ks:ks_type":"VILLAGE",
    "name:eng_x_preferred":[
        "Hirlok"
    ],
    "wof:name":"Hirlok",
    "wof:placetype":"locality",
    "wof:population":1237
},
  "geometry": {"coordinates":[73.78428700000001,16.07008],"type":"Point"}
}