{
  "type": "Feature",
  "properties": {
    "iso:country":"IN",
    "ks:ks_name":"Baimela",
    "ks:ks_pop":243,
    "ks:ks_type":"HABITATION",
    "name:eng_x_preferred":[
        "Baimela"
    ],
    "wof:name":"Baimela",
    "wof:placetype":"locality",
    "wof:population":243
},
  "geometry": {"coordinates":[84.293176,19.835398],"type":"Point"}
}