{
  "type": "Feature",
  "properties": {
    "iso:country":"IN",
    "ks:ks_name":"Dewanganj",
    "ks:ks_pop":2031,
    "ks:ks_type":"VILLAGE",
    "name:eng_x_preferred":[
        "Dewanganj"
    ],
    "wof:name":"Dewanganj",
    "wof:placetype":"locality",
    "wof:population":2031
},
  "geometry": {"coordinates":[88.50400399999999,22.269824],"type":"Point"}
}