{
  "type": "Feature",
  "properties": {
    "iso:country":"IN",
    "ks:ks_name":"Sankaralingapuram S",
    "ks:ks_pop":592,
    "ks:ks_type":"HABITATION",
    "ks:ks_uagg_main":0,
    "name:eng_x_preferred":[
        "Sankaralingapuram S"
    ],
    "wof:name":"Sankaralingapuram S",
    "wof:placetype":"neighbourhood",
    "wof:population":592
},
  "geometry": {"coordinates":[77.72190000000001,9.772015],"type":"Point"}
}