{
  "type": "Feature",
  "properties": {
    "gn:admin1_code":"12.0",
    "gn:admin2_code":"19.0",
    "gn:asciiname":"Dewal",
    "gn:country_code":"IN",
    "gn:dem":1370,
    "gn:feature_class":"P",
    "gn:feature_code":"PPL",
    "gn:name":"Dewal",
    "gn:population":0,
    "gn:timezone":"Asia/Kolkata",
    "iso:country":"IN",
    "name:fas_x_preferred":[
        "\u062f\u06cc\u0648\u0644"
    ],
    "name:pnb_x_preferred":[
        "\u062f\u06cc\u0648\u0627\u0644"
    ],
    "name:urd_x_preferred":[
        "\u062f\u06cc\u0648\u0644"
    ],
    "wof:name":"Dewal",
    "wof:placetype":"locality"
},
  "geometry": {"coordinates":[75.09724,33.07931],"type":"Point"}
}