{
  "type": "Feature",
  "properties": {
    "iso:country":"IN",
    "ks:ks_name":"Kherona I",
    "ks:ks_pop":268,
    "ks:ks_type":"HABITATION",
    "name:eng_x_preferred":[
        "Kherona I"
    ],
    "wof:name":"Kherona I",
    "wof:placetype":"locality",
    "wof:population":268
},
  "geometry": {"coordinates":[86.947255,21.458021],"type":"Point"}
}