{
  "type": "Feature",
  "properties": {
    "iso:country":"IN",
    "ks:ks_alt_nam":"9  NN",
    "ks:ks_name":"9 Nn",
    "ks:ks_pop":99,
    "ks:ks_type":"HABITATION",
    "name:eng_x_preferred":[
        "9 Nn"
    ],
    "name:eng_x_variant":[
        "9  NN"
    ],
    "wof:name":"9 Nn",
    "wof:placetype":"locality",
    "wof:population":99
},
  "geometry": {"coordinates":[73.59327500000001,29.737231],"type":"Point"}
}