{
  "type": "Feature",
  "properties": {
    "iso:country":"IN",
    "ks:ks_name":"Moovappe",
    "ks:ks_pop":27,
    "ks:ks_type":"HABITATION",
    "name:eng_x_preferred":[
        "Moovappe"
    ],
    "wof:name":"Moovappe",
    "wof:placetype":"locality",
    "wof:population":27
},
  "geometry": {"coordinates":[75.375013,12.704112],"type":"Point"}
}