{
  "type": "Feature",
  "properties": {
    "iso:country":"IN",
    "ks:ks_name":"Loyheto",
    "ks:ks_pop":622,
    "ks:ks_type":"HABITATION",
    "name:eng_x_preferred":[
        "Loyheto"
    ],
    "wof:name":"Loyheto",
    "wof:placetype":"locality",
    "wof:population":622
},
  "geometry": {"coordinates":[93.84047200000001,25.936148],"type":"Point"}
}