{
  "type": "Feature",
  "properties": {
    "iso:country":"IN",
    "ks:ks_alt_nam":"PURE GAREALADEEN",
    "ks:ks_name":"Pure Garealadeen",
    "ks:ks_pop":316,
    "ks:ks_type":"HABITATION",
    "name:eng_x_preferred":[
        "Pure Garealadeen"
    ],
    "wof:name":"Pure Garealadeen",
    "wof:placetype":"locality",
    "wof:population":316
},
  "geometry": {"coordinates":[81.4421,26.5289],"type":"Point"}
}