{
  "type": "Feature",
  "properties": {
    "iso:country":"IN",
    "name:ara_x_preferred":[
        "\u0643\u0631\u0648\u0634\u0646\u0627 \u0646\u0627\u062c\u0627\u0631"
    ],
    "name:ben_bn_x_preferred":[
        "\u0995\u09c3\u09b7\u09cd\u09a3\u09be \u09a8\u0997\u09b0"
    ],
    "name:ben_in_x_preferred":[
        "\u0995\u09cb\u09a8\u09cd\u09a6\u0993\u09df\u09be \u09ac\u09c1\u09a6\u09b0\u09c1\u0995 \u0995\u09c3\u09b7\u09cd\u09a3\u09be \u09a8\u0997\u09b0"
    ],
    "name:eng_x_preferred":[
        "Krushna Nagar"
    ],
    "name:guj_x_preferred":[
        "\u0a95\u0ac3\u0ab7\u0acd\u0aa3 \u0aa8\u0a97\u0ab0"
    ],
    "name:hin_x_preferred":[
        "\u0915\u0943\u0937\u094d\u0923\u093e \u0928\u0917\u0930"
    ],
    "name:kan_x_preferred":[
        "\u0c95\u0cc3\u0cb7\u0ccd\u0ca3 \u0ca8\u0c97\u0cb0"
    ],
    "name:mal_x_preferred":[
        "\u0d15\u0d43\u0d37\u0d4d\u0d23 \u0d28\u0d17\u0d7c"
    ],
    "name:mar_x_preferred":[
        "\u0915\u0943\u0937\u094d\u0923\u093e \u0928\u0917\u0930"
    ],
    "name:pan_x_preferred":[
        "\u0a15\u0a30\u0a41\u0a36\u0a28\u0a3e \u0a28\u0a17\u0a30"
    ],
    "name:tam_x_preferred":[
        "\u0b95\u0bcd\u0bb0\u0bc1\u0bb7\u0bcd\u0ba9\u0bbe \u0ba8\u0b95\u0bb0\u0bcd"
    ],
    "name:tel_x_preferred":[
        "\u0c15\u0c43\u0c37\u0c4d\u0c23\u0c3e \u0c28\u0c17\u0c30\u0c4d"
    ],
    "name:urd_x_preferred":[
        "\u06a9\u0631\u0648\u0634\u0646\u0627 \u0646\u06af\u0631"
    ],
    "wof:name":"Krushna Nagar",
    "wof:placetype":"neighbourhood"
},
  "geometry": {"coordinates":[73.91787182491498,18.47360079416922],"type":"Point"}
}