{
  "type": "Feature",
  "properties": {
    "iso:country":"IN",
    "name:eng_x_preferred":[
        "Krushna Nagar"
    ],
    "wof:name":"Krushna Nagar",
    "wof:placetype":"neighbourhood"
},
  "geometry": {"coordinates":[73.91787182491498,18.47360079416922],"type":"Point"}
}