{
  "type": "Feature",
  "properties": {
    "iso:country":"IN",
    "ks:ks_name":"Dotad",
    "ks:ks_pop":2930,
    "ks:ks_type":"VILLAGE",
    "name:eng_x_preferred":[
        "Dotad"
    ],
    "wof:name":"Dotad",
    "wof:placetype":"locality",
    "wof:population":2930
},
  "geometry": {"coordinates":[74.461799,22.709249],"type":"Point"}
}