{
  "type": "Feature",
  "properties": {
    "iso:country":"IN",
    "ks:ks_name":"Keeranallur",
    "ks:ks_pop":421,
    "ks:ks_type":"HABITATION",
    "name:eng_x_preferred":[
        "Keeranallur"
    ],
    "wof:name":"Keeranallur",
    "wof:placetype":"locality",
    "wof:population":421
},
  "geometry": {"coordinates":[79.77020899999999,11.245425],"type":"Point"}
}