{
  "type": "Feature",
  "properties": {
    "gn:admin1_code":"10",
    "gn:admin2_code":"69.0",
    "gn:asciiname":"Qadirpur",
    "gn:country_code":"IN",
    "gn:dem":608,
    "gn:feature_class":"P",
    "gn:feature_code":"PPL",
    "gn:name":"Qadirpur",
    "gn:population":0,
    "gn:timezone":"Asia/Kolkata",
    "iso:country":"IN",
    "name:ceb_x_preferred":[
        "Qad\u012brp\u016br"
    ],
    "name:fas_x_preferred":[
        "\u0642\u062f\u06cc\u0631\u067e\u0648\u0631"
    ],
    "name:swe_x_preferred":[
        "Qad\u012brp\u016br"
    ],
    "wof:name":"Qadirpur",
    "wof:placetype":"locality"
},
  "geometry": {"coordinates":[76.99741999999998,30.75137],"type":"Point"}
}