{
  "type": "Feature",
  "properties": {
    "gn:admin1_code":"35",
    "gn:admin2_code":"426.0",
    "gn:asciiname":"Kalmasan",
    "gn:country_code":"IN",
    "gn:dem":350,
    "gn:feature_class":"P",
    "gn:feature_code":"PPL",
    "gn:name":"Kalm\u0101san",
    "gn:population":0,
    "gn:timezone":"Asia/Kolkata",
    "iso:country":"IN",
    "ks:ks_name":"Kaimasan",
    "ks:ks_pop":204,
    "ks:ks_type":"HABITATION",
    "name:eng_x_preferred":[
        "Kaimasan"
    ],
    "name:eng_x_variant":[
        "Kalmasan"
    ],
    "wof:name":"Kaimasan",
    "wof:placetype":"locality",
    "wof:population":204
},
  "geometry": {"coordinates":[80.052402,24.655658],"type":"Point"}
}