{
  "type": "Feature",
  "properties": {
    "iso:country":"IN",
    "ks:ks_name":"Bhuir Tilla",
    "ks:ks_pop":470,
    "ks:ks_type":"HABITATION",
    "name:eng_x_preferred":[
        "Bhuir Tilla"
    ],
    "wof:name":"Bhuir Tilla",
    "wof:placetype":"locality",
    "wof:population":470
},
  "geometry": {"coordinates":[91.517276,23.364449],"type":"Point"}
}