{
  "type": "Feature",
  "properties": {
    "iso:country":"IN",
    "ks:ks_name":"Ram Nagar",
    "ks:ks_pop":235,
    "ks:ks_type":"HABITATION",
    "name:eng_x_preferred":[
        "Ram Nagar"
    ],
    "wof:name":"Ram Nagar",
    "wof:placetype":"locality",
    "wof:population":235
},
  "geometry": {"coordinates":[80.04406400000001,27.417987],"type":"Point"}
}