{
  "type": "Feature",
  "properties": {
    "iso:country":"IN",
    "ks:ks_name":"Balwant Tola",
    "ks:ks_pop":293,
    "ks:ks_type":"HABITATION",
    "name:eng_x_preferred":[
        "Balwant Tola"
    ],
    "wof:name":"Balwant Tola",
    "wof:placetype":"locality",
    "wof:population":293
},
  "geometry": {"coordinates":[84.500867,26.49723],"type":"Point"}
}