{
  "type": "Feature",
  "properties": {
    "iso:country":"IN",
    "ks:ks_name":"Pal Basti",
    "ks:ks_pop":270,
    "ks:ks_type":"HABITATION",
    "name:eng_x_preferred":[
        "Pal Basti"
    ],
    "wof:name":"Pal Basti",
    "wof:placetype":"locality",
    "wof:population":270
},
  "geometry": {"coordinates":[82.386156,25.905833],"type":"Point"}
}