{
  "type": "Feature",
  "properties": {
    "iso:country":"IN",
    "ks:ks_name":"Shihuliya Mathiya.",
    "ks:ks_pop":565,
    "ks:ks_type":"HABITATION",
    "ks:ks_uagg_main":0,
    "name:eng_x_preferred":[
        "Shihuliya Mathiya."
    ],
    "wof:name":"Shihuliya Mathiya.",
    "wof:placetype":"neighbourhood",
    "wof:population":565
},
  "geometry": {"coordinates":[83.889539,26.858488],"type":"Point"}
}