{
  "type": "Feature",
  "properties": {
    "gn:admin1_code":"16.0",
    "gn:admin2_code":"515.0",
    "gn:asciiname":"Digras",
    "gn:country_code":"IN",
    "gn:dem":638,
    "gn:feature_class":"P",
    "gn:feature_code":"PPL",
    "gn:name":"Digras",
    "gn:population":0,
    "gn:timezone":"Asia/Kolkata",
    "iso:country":"IN",
    "name:ben_x_preferred":[
        "\u09a6\u09bf\u0997\u09cd\u09b0\u09be\u09b8"
    ],
    "name:bpy_x_preferred":[
        "\u09a6\u09bf\u0997\u09cd\u09b0\u09be\u09b8"
    ],
    "name:ceb_x_preferred":[
        "Digras"
    ],
    "name:ita_x_preferred":[
        "Digras"
    ],
    "name:mar_x_preferred":[
        "\u0926\u093f\u0917\u094d\u0930\u0938"
    ],
    "name:mlg_x_preferred":[
        "Digras"
    ],
    "name:msa_x_preferred":[
        "Digras"
    ],
    "name:new_x_preferred":[
        "\u0926\u093f\u0917\u094d\u0930\u0938"
    ],
    "name:nld_x_preferred":[
        "Digras"
    ],
    "name:por_x_preferred":[
        "Digras"
    ],
    "name:swe_x_preferred":[
        "Digras"
    ],
    "name:urd_x_preferred":[
        "\u0688\u06af\u0631\u0633"
    ],
    "name:vie_x_preferred":[
        "Digras"
    ],
    "name:zho_x_preferred":[
        "\u8fea\u683c\u62c9\u65af"
    ],
    "wof:name":"Digras",
    "wof:placetype":"locality"
},
  "geometry": {"coordinates":[75.74446999999998,20.4747],"type":"Point"}
}