{
  "type": "Feature",
  "properties": {
    "iso:country":"IN",
    "ks:ks_name":"Debnath Para",
    "ks:ks_pop":638,
    "ks:ks_type":"HABITATION",
    "name:eng_x_preferred":[
        "Debnath Para"
    ],
    "wof:name":"Debnath Para",
    "wof:placetype":"locality",
    "wof:population":638
},
  "geometry": {"coordinates":[89.472117,26.414779],"type":"Point"}
}