{
  "type": "Feature",
  "properties": {
    "iso:country":"IN",
    "ks:ks_alt_nam":"Anna nagar",
    "ks:ks_name":"Anna Nagar",
    "ks:ks_pop":203,
    "ks:ks_type":"HABITATION",
    "ks:ks_uagg_main":0,
    "name:eng_x_preferred":[
        "Anna Nagar"
    ],
    "wof:name":"Anna Nagar",
    "wof:placetype":"locality",
    "wof:population":203
},
  "geometry": {"coordinates":[77.948914,11.647],"type":"Point"}
}