{
  "type": "Feature",
  "properties": {
    "iso:country":"IN",
    "ks:ks_name":"Errabailu",
    "ks:ks_pop":26,
    "ks:ks_type":"HABITATION",
    "name:eng_x_preferred":[
        "Errabailu"
    ],
    "wof:name":"Errabailu",
    "wof:placetype":"locality",
    "wof:population":26
},
  "geometry": {"coordinates":[82.416184,18.13894],"type":"Point"}
}