{
  "type": "Feature",
  "properties": {
    "gn:admin1_code":"2.0",
    "gn:admin2_code":"544.0",
    "gn:asciiname":"Bandavidi",
    "gn:country_code":"IN",
    "gn:dem":974,
    "gn:feature_class":"P",
    "gn:feature_code":"PPL",
    "gn:name":"Bandav\u012bdi",
    "gn:population":0,
    "gn:timezone":"Asia/Kolkata",
    "iso:country":"IN",
    "wof:name":"Bandavidi",
    "wof:placetype":"locality"
},
  "geometry": {"coordinates":[82.56601999999999,18.05115],"type":"Point"}
}