{
  "type": "Feature",
  "properties": {
    "gn:admin1_code":"12.0",
    "gn:admin2_code":"008",
    "gn:asciiname":"Gagharpur",
    "gn:country_code":"IN",
    "gn:dem":1585,
    "gn:feature_class":"P",
    "gn:feature_code":"PPL",
    "gn:name":"Gagharpur",
    "gn:population":0,
    "gn:timezone":"Asia/Kolkata",
    "iso:country":"IN",
    "wof:name":"Gagharpur",
    "wof:placetype":"locality"
},
  "geometry": {"coordinates":[74.66664,34.11431],"type":"Point"}
}