{
  "type": "Feature",
  "properties": {
    "iso:country":"IN",
    "ks:ks_name":"15 KD-B",
    "ks:ks_pop":92,
    "ks:ks_type":"VILLAGE",
    "name:eng_x_preferred":[
        "15 KD-B"
    ],
    "wof:name":"15 KD-B",
    "wof:placetype":"locality",
    "wof:population":92
},
  "geometry": {"coordinates":[72.83069999999999,28.897541],"type":"Point"}
}