{
  "type": "Feature",
  "properties": {
    "gn:admin1_code":"36.0",
    "gn:admin2_code":"137.0",
    "gn:asciiname":"Santhalpur Bichwali Mandaiyan",
    "gn:country_code":"IN",
    "gn:dem":201,
    "gn:feature_class":"P",
    "gn:feature_code":"PPL",
    "gn:name":"S\u0101nthalpur Bichw\u0101li Mandaiy\u0101n",
    "gn:population":0,
    "gn:timezone":"Asia/Kolkata",
    "iso:country":"IN",
    "wof:name":"Santhalpur Bichwali Mandaiyan",
    "wof:placetype":"neighbourhood"
},
  "geometry": {"coordinates":[78.35851,28.5808],"type":"Point"}
}