{
  "type": "Feature",
  "properties": {
    "gn:admin1_code":"12.0",
    "gn:admin2_code":"17.0",
    "gn:asciiname":"Chakandal",
    "gn:country_code":"IN",
    "gn:dem":1904,
    "gn:feature_class":"P",
    "gn:feature_code":"PPL",
    "gn:name":"Chakandal",
    "gn:population":0,
    "gn:timezone":"Asia/Kolkata",
    "iso:country":"IN",
    "wof:name":"Chakandal",
    "wof:placetype":"locality"
},
  "geometry": {"coordinates":[75.06933000000002,33.28369],"type":"Point"}
}