{
  "type": "Feature",
  "properties": {
    "gn:admin1_code":"11.0",
    "gn:admin2_code":"31.0",
    "gn:asciiname":"Jeniyan",
    "gn:country_code":"IN",
    "gn:dem":1312,
    "gn:feature_class":"P",
    "gn:feature_code":"PPL",
    "gn:name":"Jeniyan",
    "gn:population":0,
    "gn:timezone":"Asia/Kolkata",
    "iso:country":"IN",
    "wof:name":"Jeniyan",
    "wof:placetype":"locality"
},
  "geometry": {"coordinates":[77.08959,30.86142000000001],"type":"Point"}
}