{
  "type": "Feature",
  "properties": {
    "iso:country":"IN",
    "ks:ks_alt_nam":"Mukalbari TE",
    "ks:ks_name":"Mukalbari Te",
    "ks:ks_pop":799,
    "ks:ks_type":"HABITATION",
    "ks:ks_uagg_main":0,
    "name:eng_x_preferred":[
        "Mukalbari Te"
    ],
    "wof:name":"Mukalbari Te",
    "wof:placetype":"neighbourhood",
    "wof:population":799
},
  "geometry": {"coordinates":[95.06630800000001,27.506252],"type":"Point"}
}