{
  "type": "Feature",
  "properties": {
    "iso:country":"IN",
    "ks:ks_name":"Kamreng",
    "ks:ks_pop":97,
    "ks:ks_type":"VILLAGE",
    "name:eng_x_preferred":[
        "Kamreng"
    ],
    "wof:name":"Kamreng",
    "wof:placetype":"locality",
    "wof:population":97
},
  "geometry": {"coordinates":[83.661187,20.298529],"type":"Point"}
}