{
  "type": "Feature",
  "properties": {
    "iso:country":"IN",
    "ks:ks_name":"Barakhairapara",
    "ks:ks_pop":544,
    "ks:ks_type":"VILLAGE",
    "name:eng_x_preferred":[
        "Barakhairapara"
    ],
    "wof:name":"Barakhairapara",
    "wof:placetype":"locality",
    "wof:population":544
},
  "geometry": {"coordinates":[87.657343,24.545031],"type":"Point"}
}