{
  "type": "Feature",
  "properties": {
    "iso:country":"IN",
    "ks:ks_name":"Gangarajuputtu",
    "ks:ks_pop":332,
    "ks:ks_type":"VILLAGE",
    "name:eng_x_preferred":[
        "Gangarajuputtu"
    ],
    "wof:name":"Gangarajuputtu",
    "wof:placetype":"locality",
    "wof:population":332
},
  "geometry": {"coordinates":[82.76385500000001,18.142981],"type":"Point"}
}