{
  "type": "Feature",
  "properties": {
    "iso:country":"IN",
    "ks:ks_name":"Karna Kishore Para",
    "ks:ks_pop":348,
    "ks:ks_type":"HABITATION",
    "name:eng_x_preferred":[
        "Karna Kishore Para"
    ],
    "wof:name":"Karna Kishore Para",
    "wof:placetype":"locality",
    "wof:population":348
},
  "geometry": {"coordinates":[91.881794,23.648562],"type":"Point"}
}