{
  "type": "Feature",
  "properties": {
    "gn:country":"IN",
    "gn:fcode":"PPL",
    "gn:pop":21298,
    "iso:country":"IN",
    "name:bul_x_preferred":[
        "\u0414\u0435\u0432\u043b\u0438"
    ],
    "name:eng_x_preferred":[
        "Deoli"
    ],
    "name:fra_x_preferred":[
        "Deoli"
    ],
    "name:hin_x_preferred":[
        "\u0926\u0947\u0935\u0932\u0940"
    ],
    "name:ita_x_preferred":[
        "Deoli"
    ],
    "name:msa_x_preferred":[
        "Deoli"
    ],
    "name:nld_x_preferred":[
        "Deoli"
    ],
    "name:swe_x_preferred":[
        "Devli"
    ],
    "name:unk_x_variant":[
        "Dioli"
    ],
    "qs:name":"Deoli",
    "qs:name_adm0":"India",
    "qs:name_adm1":"Rajasthan",
    "qs:photos_9r":0,
    "qs:photos_sr":0,
    "qs:placetype":"Town",
    "qs:pop_sr":"7",
    "wd:wordcount":24,
    "wof:name":"Deoli",
    "wof:placetype":"locality",
    "wof:population":21298
},
  "geometry": {"coordinates":[75.38093000000001,25.76042],"type":"Point"}
}