{
  "type": "Feature",
  "properties": {
    "gn:admin1_code":"11.0",
    "gn:admin2_code":"31.0",
    "gn:asciiname":"Kanah",
    "gn:country_code":"IN",
    "gn:dem":1593,
    "gn:feature_class":"P",
    "gn:feature_code":"PPL",
    "gn:name":"K\u0101n\u0101h",
    "gn:population":0,
    "gn:timezone":"Asia/Kolkata",
    "iso:country":"IN",
    "name:jpn_x_preferred":[
        "\u30ab\u30ca"
    ],
    "wof:name":"Kanah",
    "wof:placetype":"locality"
},
  "geometry": {"coordinates":[77.18999000000002,30.94157],"type":"Point"}
}