{
  "type": "Feature",
  "properties": {
    "iso:country":"IN",
    "ks:ks_alt_nam":"JURARAWA",
    "ks:ks_name":"Jurarawa",
    "ks:ks_pop":411,
    "ks:ks_type":"HABITATION",
    "name:eng_x_preferred":[
        "Jurarawa"
    ],
    "wof:name":"Jurarawa",
    "wof:placetype":"locality",
    "wof:population":411
},
  "geometry": {"coordinates":[84.513608,24.597139],"type":"Point"}
}