{
  "type": "Feature",
  "properties": {
    "gn:admin1_code":"34.0",
    "gn:admin2_code":"219.0",
    "gn:asciiname":"Khairanpur",
    "gn:country_code":"IN",
    "gn:dem":62,
    "gn:feature_class":"P",
    "gn:feature_code":"PPL",
    "gn:name":"Khairanpur",
    "gn:population":0,
    "gn:timezone":"Asia/Kolkata",
    "iso:country":"IN",
    "ks:ks_name":"Khairanpur",
    "ks:ks_pop":735,
    "ks:ks_type":"VILLAGE",
    "ks:ks_uagg_main":0,
    "name:eng_x_preferred":[
        "Khairanpur"
    ],
    "wof:name":"Khairanpur",
    "wof:placetype":"neighbourhood",
    "wof:population":735
},
  "geometry": {"coordinates":[84.769469,26.096679],"type":"Point"}
}