{
  "type": "Feature",
  "properties": {
    "iso:country":"IN",
    "ks:ks_name":"Sirasaul Patti Seetaram",
    "ks:ks_pop":3812,
    "ks:ks_type":"VILLAGE",
    "name:eng_x_preferred":[
        "Sirasaul Patti Seetaram"
    ],
    "wof:name":"Sirasaul Patti Seetaram",
    "wof:placetype":"locality",
    "wof:population":3812
},
  "geometry": {"coordinates":[78.933787,28.07119],"type":"Point"}
}