{
  "type": "Feature",
  "properties": {
    "iso:country":"IN",
    "ks:ks_name":"Putakoppakothala",
    "ks:ks_pop":29,
    "ks:ks_type":"HABITATION",
    "name:eng_x_preferred":[
        "Putakoppakothala"
    ],
    "wof:name":"Putakoppakothala",
    "wof:placetype":"locality",
    "wof:population":29
},
  "geometry": {"coordinates":[78.01768300000001,14.250978],"type":"Point"}
}