{
  "type": "Feature",
  "properties": {
    "gn:admin1_code":"35.0",
    "gn:admin2_code":"419.0",
    "gn:asciiname":"Phodi ka Pura",
    "gn:country_code":"IN",
    "gn:dem":218,
    "gn:feature_class":"P",
    "gn:feature_code":"PPL",
    "gn:name":"Phodi ka Pura",
    "gn:population":0,
    "gn:timezone":"Asia/Kolkata",
    "iso:country":"IN",
    "wof:name":"Phodi ka Pura",
    "wof:placetype":"locality"
},
  "geometry": {"coordinates":[77.76243000000002,26.26188],"type":"Point"}
}