{
  "type": "Feature",
  "properties": {
    "iso:country":"IN",
    "ks:ks_name":"Shyamnagar",
    "ks:ks_pop":741,
    "ks:ks_type":"HABITATION",
    "name:eng_x_preferred":[
        "Shyamnagar"
    ],
    "wof:name":"Shyamnagar",
    "wof:placetype":"locality",
    "wof:population":741
},
  "geometry": {"coordinates":[81.761841,18.347925],"type":"Point"}
}