{
  "type": "Feature",
  "properties": {
    "iso:country":"IN",
    "ks:ks_name":"Vanjariguda",
    "ks:ks_pop":50,
    "ks:ks_type":"HABITATION",
    "name:eng_x_preferred":[
        "Vanjariguda"
    ],
    "wof:name":"Vanjariguda",
    "wof:placetype":"locality",
    "wof:population":50
},
  "geometry": {"coordinates":[78.719914,19.622786],"type":"Point"}
}