{
  "type": "Feature",
  "properties": {
    "iso:country":"IN",
    "ks:ks_alt_nam":"Kachchikkuv\u0101chch\u0101n",
    "ks:ks_alt_nam_2":"Kachchikkuvachchan",
    "ks:ks_name":"Kachikkuvachan",
    "ks:ks_pop":747,
    "ks:ks_type":"VILLAGE",
    "ks:ks_uagg_main":0,
    "name:eng_x_preferred":[
        "Kachikkuvachan"
    ],
    "name:eng_x_variant":[
        "Kachchikkuv\u0101chch\u0101n",
        "Kachchikkuvachchan"
    ],
    "wof:name":"Kachikkuvachan",
    "wof:placetype":"neighbourhood",
    "wof:population":747
},
  "geometry": {"coordinates":[79.209613,11.943377],"type":"Point"}
}