{
  "type": "Feature",
  "properties": {
    "gn:admin1_code":"2.0",
    "gn:admin2_code":"554.0",
    "gn:asciiname":"Bukkapatnam",
    "gn:country_code":"IN",
    "gn:dem":279,
    "gn:feature_class":"P",
    "gn:feature_code":"PPL",
    "gn:name":"Bukkapatnam",
    "gn:population":0,
    "gn:timezone":"Asia/Kolkata",
    "iso:country":"IN",
    "name:ceb_x_preferred":[
        "Bukkapatnam"
    ],
    "name:fra_x_preferred":[
        "Bukkapatnam"
    ],
    "name:new_x_preferred":[
        "\u092c\u0941\u0915\u094d\u0915\u092a\u091f\u094d\u0928\u092e\u094d \u092e\u0923\u094d\u0921\u0932"
    ],
    "name:spa_x_preferred":[
        "Bukkapatnam"
    ],
    "name:swe_x_preferred":[
        "Bukkapatnam"
    ],
    "name:tel_x_preferred":[
        "\u0c2c\u0c41\u0c15\u0c4d\u0c15\u0c2a\u0c1f\u0c4d\u0c28\u0c02"
    ],
    "name:tgl_x_preferred":[
        "Bukkapatnam"
    ],
    "name:urd_x_preferred":[
        "\u0628\u0648\u06a9\u0627\u067e\u0679\u0646\u0645"
    ],
    "wof:name":"Bukkapatnam",
    "wof:placetype":"locality"
},
  "geometry": {"coordinates":[79.26331999999999,13.22612],"type":"Point"}
}