{
  "type": "Feature",
  "properties": {
    "iso:country":"IN",
    "ks:ks_name":"Balisuan",
    "ks:ks_pop":256,
    "ks:ks_type":"VILLAGE",
    "ks:ks_uagg_main":0,
    "name:eng_x_preferred":[
        "Balisuan"
    ],
    "wof:name":"Balisuan",
    "wof:placetype":"neighbourhood",
    "wof:population":256
},
  "geometry": {"coordinates":[86.97161699999999,21.563344],"type":"Point"}
}