{
  "type": "Feature",
  "properties": {
    "gn:admin1_code":"11",
    "gn:admin2_code":"31.0",
    "gn:asciiname":"Sangliana",
    "gn:country_code":"IN",
    "gn:dem":1254,
    "gn:feature_class":"P",
    "gn:feature_code":"PPL",
    "gn:name":"Sangl\u012b\u0101na",
    "gn:population":0,
    "gn:timezone":"Asia/Kolkata",
    "iso:country":"IN",
    "wof:name":"Sangliana",
    "wof:placetype":"locality"
},
  "geometry": {"coordinates":[77.05405999999998,31.06263],"type":"Point"}
}