{
  "type": "Feature",
  "properties": {
    "gn:admin1_code":"36",
    "gn:admin2_code":"153.0",
    "gn:asciiname":"Purwa Manak Chand",
    "gn:country_code":"IN",
    "gn:dem":132,
    "gn:feature_class":"P",
    "gn:feature_code":"PPL",
    "gn:name":"Purwa M\u0101nak Chand",
    "gn:population":0,
    "gn:timezone":"Asia/Kolkata",
    "iso:country":"IN",
    "wof:name":"Purwa Manak Chand",
    "wof:placetype":"neighbourhood"
},
  "geometry": {"coordinates":[81.05840999999999,27.93204],"type":"Point"}
}