{
  "type": "Feature",
  "properties": {
    "iso:country":"IN",
    "ks:ks_name":"Dhau",
    "ks:ks_pop":679,
    "ks:ks_type":"VILLAGE",
    "name:eng_x_preferred":[
        "Dhau"
    ],
    "wof:name":"Dhau",
    "wof:placetype":"locality",
    "wof:population":679
},
  "geometry": {"coordinates":[86.854243,22.680478],"type":"Point"}
}