{
  "type": "Feature",
  "properties": {
    "iso:country":"IN",
    "ks:ks_alt_nam":"Tilaiy\u0101",
    "ks:ks_name":"Tilaiya",
    "ks:ks_pop":692,
    "ks:ks_type":"VILLAGE",
    "ks:ks_uagg_main":0,
    "name:eng_x_preferred":[
        "Tilaiya"
    ],
    "name:eng_x_variant":[
        "Tilaiy\u0101"
    ],
    "wof:name":"Tilaiya",
    "wof:placetype":"neighbourhood",
    "wof:population":692
},
  "geometry": {"coordinates":[85.515891,24.012416],"type":"Point"}
}