{
  "type": "Feature",
  "properties": {
    "iso:country":"IN",
    "ks:ks_name":"Bagarijanpara",
    "ks:ks_pop":2075,
    "ks:ks_type":"HABITATION",
    "ks:ks_uagg_main":0,
    "name:eng_x_preferred":[
        "Bagarijanpara"
    ],
    "wof:name":"Bagarijanpara",
    "wof:placetype":"neighbourhood",
    "wof:population":2075
},
  "geometry": {"coordinates":[90.929896,26.361236],"type":"Point"}
}