{
  "type": "Feature",
  "properties": {
    "iso:country":"IN",
    "ks:ks_name":"Byralli",
    "ks:ks_pop":255,
    "ks:ks_type":"HABITATION",
    "name:eng_x_preferred":[
        "Byralli"
    ],
    "wof:name":"Byralli",
    "wof:placetype":"locality",
    "wof:population":255
},
  "geometry": {"coordinates":[75.202873,13.543058],"type":"Point"}
}