{
  "type": "Feature",
  "properties": {
    "iso:country":"IN",
    "ks:ks_name":"Paikapada",
    "ks:ks_pop":60,
    "ks:ks_type":"VILLAGE",
    "name:eng_x_preferred":[
        "Paikapada"
    ],
    "wof:name":"Paikapada",
    "wof:placetype":"locality",
    "wof:population":60
},
  "geometry": {"coordinates":[83.599626,19.902997],"type":"Point"}
}