{
  "type": "Feature",
  "properties": {
    "gn:admin1_code":"35",
    "gn:admin2_code":"455.0",
    "gn:asciiname":"Sagar",
    "gn:country_code":"IN",
    "gn:dem":644,
    "gn:feature_class":"P",
    "gn:feature_code":"PPL",
    "gn:name":"S\u0101gar",
    "gn:population":0,
    "gn:timezone":"Asia/Kolkata",
    "iso:country":"IN",
    "name:ceb_x_preferred":[
        "Sagar"
    ],
    "name:deu_x_preferred":[
        "Sagar"
    ],
    "name:fas_x_preferred":[
        "\u0633\u0627\u063a\u0631"
    ],
    "name:hin_x_preferred":[
        "\u0938\u093e\u0917\u0930"
    ],
    "name:nld_x_preferred":[
        "Sagar"
    ],
    "name:rus_x_preferred":[
        "\u0421\u0435\u0439\u0433\u0430\u0440"
    ],
    "name:swe_x_preferred":[
        "Sagar"
    ],
    "name:vie_x_preferred":[
        "Sagar"
    ],
    "wof:name":"Sagar",
    "wof:placetype":"locality"
},
  "geometry": {"coordinates":[79.28811,22.11315],"type":"Point"}
}