{
  "type": "Feature",
  "properties": {
    "iso:country":"IN",
    "ks:ks_name":"Noojibylu",
    "ks:ks_pop":240,
    "ks:ks_type":"HABITATION",
    "name:eng_x_preferred":[
        "Noojibylu"
    ],
    "wof:name":"Noojibylu",
    "wof:placetype":"locality",
    "wof:population":240
},
  "geometry": {"coordinates":[74.838256,13.41756],"type":"Point"}
}