{
  "type": "Feature",
  "properties": {
    "gn:admin1_code":"36",
    "gn:admin2_code":"188.0",
    "gn:asciiname":"Chhatardhari - Arazi Urf Misrauli",
    "gn:country_code":"IN",
    "gn:dem":86,
    "gn:feature_class":"P",
    "gn:feature_code":"PPL",
    "gn:name":"Chhatardh\u0101ri - Ar\u0101zi Urf Misrauli",
    "gn:population":0,
    "gn:timezone":"Asia/Kolkata",
    "iso:country":"IN",
    "wof:name":"Chhatardhari - Arazi Urf Misrauli",
    "wof:placetype":"neighbourhood"
},
  "geometry": {"coordinates":[83.42965,26.81781],"type":"Point"}
}