{
  "type": "Feature",
  "properties": {
    "gn:admin1_code":"35",
    "gn:admin2_code":"419.0",
    "gn:asciiname":"Babupura",
    "gn:country_code":"IN",
    "gn:dem":192,
    "gn:feature_class":"P",
    "gn:feature_code":"PPL",
    "gn:name":"B\u0101b\u016bpura",
    "gn:population":0,
    "gn:timezone":"Asia/Kolkata",
    "iso:country":"IN",
    "name:und_x_variant":[
        "B\u0101b\u016bpura",
        "Cham\u0101rpura"
    ],
    "wof:name":"Babupura",
    "wof:placetype":"locality"
},
  "geometry": {"coordinates":[77.59251999999999,26.26647],"type":"Point"}
}