{
  "type": "Feature",
  "properties": {
    "iso:country":"IN",
    "ks:ks_name":"Pasaunda",
    "ks:ks_type":"VILLAGE",
    "ks:ks_uagg_main":0,
    "name:eng_x_preferred":[
        "Pasaunda"
    ],
    "wof:name":"Pasaunda",
    "wof:placetype":"neighbourhood"
},
  "geometry": {"coordinates":[77.357738,28.693416],"type":"Point"}
}