{
  "type": "Feature",
  "properties": {
    "iso:country":"IN",
    "ks:ks_alt_nam":"MATHIYA",
    "ks:ks_name":"Mathiya",
    "ks:ks_pop":1593,
    "ks:ks_type":"HABITATION",
    "name:eng_x_preferred":[
        "Mathiya"
    ],
    "wof:name":"Mathiya",
    "wof:placetype":"locality",
    "wof:population":1593
},
  "geometry": {"coordinates":[83.575304,25.68812],"type":"Point"}
}