{
  "type": "Feature",
  "properties": {
    "iso:country":"IN",
    "ks:ks_name":"Karampura",
    "ks:ks_pop":716,
    "ks:ks_type":"VILLAGE",
    "name:eng_x_preferred":[
        "Karampura"
    ],
    "wof:name":"Karampura",
    "wof:placetype":"locality",
    "wof:population":716
},
  "geometry": {"coordinates":[86.958124,24.60534],"type":"Point"}
}