{
  "type": "Feature",
  "properties": {
    "gn:admin1_code":"36",
    "gn:admin2_code":"140.0",
    "gn:asciiname":"Alampur Bhagwantpur",
    "gn:country_code":"IN",
    "gn:dem":204,
    "gn:feature_class":"P",
    "gn:feature_code":"PPL",
    "gn:name":"\u0100lampur Bhagwantpur",
    "gn:population":0,
    "gn:timezone":"Asia/Kolkata",
    "iso:country":"IN",
    "wof:name":"Alampur Bhagwantpur",
    "wof:placetype":"locality"
},
  "geometry": {"coordinates":[78.09401,28.84956],"type":"Point"}
}