{
  "type": "Feature",
  "properties": {
    "iso:country":"IN",
    "ks:ks_name":"Alagera Colony",
    "ks:ks_pop":49,
    "ks:ks_type":"HABITATION",
    "name:eng_x_preferred":[
        "Alagera Colony"
    ],
    "wof:name":"Alagera Colony",
    "wof:placetype":"locality",
    "wof:population":49
},
  "geometry": {"coordinates":[74.327412,14.626624],"type":"Point"}
}