{
  "type": "Feature",
  "properties": {
    "iso:country":"IN",
    "ks:ks_name":"Block Colony Para",
    "ks:ks_pop":269,
    "ks:ks_type":"HABITATION",
    "ks:ks_uagg_main":0,
    "name:eng_x_preferred":[
        "Block Colony Para"
    ],
    "wof:name":"Block Colony Para",
    "wof:placetype":"neighbourhood",
    "wof:population":269
},
  "geometry": {"coordinates":[92.011308,24.026003],"type":"Point"}
}