{
  "type": "Feature",
  "properties": {
    "iso:country":"IN",
    "ks:ks_name":"Dunger Falia",
    "ks:ks_pop":171,
    "ks:ks_type":"HABITATION",
    "name:eng_x_preferred":[
        "Dunger Falia"
    ],
    "wof:name":"Dunger Falia",
    "wof:placetype":"locality",
    "wof:population":171
},
  "geometry": {"coordinates":[73.93347199999999,22.687472],"type":"Point"}
}