{
  "type": "Feature",
  "properties": {
    "iso:country":"IN",
    "ks:ks_name":"Ratanpota",
    "ks:ks_pop":794,
    "ks:ks_type":"VILLAGE",
    "ks:ks_uagg_main":0,
    "name:eng_x_preferred":[
        "Ratanpota"
    ],
    "wof:name":"Ratanpota",
    "wof:placetype":"neighbourhood",
    "wof:population":794
},
  "geometry": {"coordinates":[88.019803,22.632237],"type":"Point"}
}