{
  "type": "Feature",
  "properties": {
    "gn:admin1_code":"9.0",
    "gn:admin2_code":"477",
    "gn:asciiname":"Rajpara",
    "gn:country_code":"IN",
    "gn:dem":31,
    "gn:feature_class":"P",
    "gn:feature_code":"PPL",
    "gn:name":"Rajpara",
    "gn:population":0,
    "gn:timezone":"Asia/Kolkata",
    "iso:country":"IN",
    "name:cat_x_preferred":[
        "Rajpara"
    ],
    "wof:name":"Rajpara",
    "wof:placetype":"locality"
},
  "geometry": {"coordinates":[69.53610999999999,22.02111],"type":"Point"}
}