{
  "type": "Feature",
  "properties": {
    "iso:country":"IN",
    "ks:ks_name":"Khitkari",
    "ks:ks_pop":32,
    "ks:ks_type":"HABITATION",
    "name:eng_x_preferred":[
        "Khitkari"
    ],
    "wof:name":"Khitkari",
    "wof:placetype":"locality",
    "wof:population":32
},
  "geometry": {"coordinates":[80.18789700000001,29.712745],"type":"Point"}
}