{
  "type": "Feature",
  "properties": {
    "gn:admin1_code":"35",
    "gn:admin2_code":"428.0",
    "gn:asciiname":"Singpur",
    "gn:country_code":"IN",
    "gn:dem":504,
    "gn:feature_class":"P",
    "gn:feature_code":"PPL",
    "gn:name":"Singpur",
    "gn:population":0,
    "gn:timezone":"Asia/Kolkata",
    "iso:country":"IN",
    "ks:ks_name":"Singhpur",
    "ks:ks_pop":412,
    "ks:ks_type":"HABITATION",
    "name:eng_x_preferred":[
        "Singhpur"
    ],
    "name:eng_x_variant":[
        "Singpur"
    ],
    "wof:name":"Singhpur",
    "wof:placetype":"locality",
    "wof:population":412
},
  "geometry": {"coordinates":[79.40666899999999,24.222085],"type":"Point"}
}