{
  "type": "Feature",
  "properties": {
    "gn:admin1_code":"2.0",
    "gn:admin2_code":"554.0",
    "gn:asciiname":"Moravabhimaganipalle",
    "gn:country_code":"IN",
    "gn:dem":746,
    "gn:feature_class":"P",
    "gn:feature_code":"PPL",
    "gn:name":"Moravabh\u012bmag\u0101nipalle",
    "gn:population":0,
    "gn:timezone":"Asia/Kolkata",
    "iso:country":"IN",
    "wof:name":"Moravabhimaganipalle",
    "wof:placetype":"locality"
},
  "geometry": {"coordinates":[78.54481,13.39798],"type":"Point"}
}