{
  "type": "Feature",
  "properties": {
    "iso:country":"IN",
    "ks:ks_alt_nam":"Bhoumik supa",
    "ks:ks_name":"Bhoumik Supa",
    "ks:ks_pop":165,
    "ks:ks_type":"HABITATION",
    "name:eng_x_preferred":[
        "Bhoumik Supa"
    ],
    "wof:name":"Bhoumik Supa",
    "wof:placetype":"locality",
    "wof:population":165
},
  "geometry": {"coordinates":[91.62009500000001,26.73204],"type":"Point"}
}