{
  "type": "Feature",
  "properties": {
    "iso:country":"IN",
    "ks:ks_name":"Melasemmangudy",
    "ks:ks_pop":102,
    "ks:ks_type":"HABITATION",
    "name:eng_x_preferred":[
        "Melasemmangudy"
    ],
    "wof:name":"Melasemmangudy",
    "wof:placetype":"locality",
    "wof:population":102
},
  "geometry": {"coordinates":[79.314072,10.864567],"type":"Point"}
}