{
  "type": "Feature",
  "properties": {
    "iso:country":"IN",
    "ks:ks_name":"Satyapur",
    "ks:ks_pop":421,
    "ks:ks_type":"HABITATION",
    "name:eng_x_preferred":[
        "Satyapur"
    ],
    "wof:name":"Satyapur",
    "wof:placetype":"locality",
    "wof:population":421
},
  "geometry": {"coordinates":[90.537614,26.80685],"type":"Point"}
}