{
  "type": "Feature",
  "properties": {
    "gn:admin1_code":"34",
    "gn:admin2_code":"233.0",
    "gn:asciiname":"Maricha",
    "gn:country_code":"IN",
    "gn:dem":77,
    "gn:feature_class":"P",
    "gn:feature_code":"PPL",
    "gn:name":"Maricha",
    "gn:population":0,
    "gn:timezone":"Asia/Kolkata",
    "iso:country":"IN",
    "name:fra_x_preferred":[
        "Maricha"
    ],
    "name:hin_x_preferred":[
        "\u092e\u093e\u0930\u0940\u091a"
    ],
    "name:ind_x_preferred":[
        "Marica"
    ],
    "name:jav_x_preferred":[
        "Marica"
    ],
    "name:jpn_x_preferred":[
        "\u30de\u30fc\u30ea\u30fc\u30c1\u30e3"
    ],
    "name:kan_x_preferred":[
        "\u0cae\u0cbe\u0cb0\u0cc0\u0c9a"
    ],
    "name:mal_x_preferred":[
        "\u0d2e\u0d3e\u0d30\u0d40\u0d1a\u0d7b"
    ],
    "name:pan_x_preferred":[
        "\u0a2e\u0a30\u0a40\u0a1a"
    ],
    "name:rus_x_preferred":[
        "\u041c\u0430\u0440\u0438\u0447\u0430"
    ],
    "name:spa_x_preferred":[
        "Maricha"
    ],
    "name:tam_x_preferred":[
        "\u0bae\u0bbe\u0bb0\u0bc0\u0b9a\u0ba9\u0bcd"
    ],
    "name:tha_x_preferred":[
        "\u0e21\u0e32\u0e23\u0e35\u0e28"
    ],
    "wof:name":"Maricha",
    "wof:placetype":"locality"
},
  "geometry": {"coordinates":[83.70688,25.23351],"type":"Point"}
}