{
  "type": "Feature",
  "properties": {
    "iso:country":"IN",
    "ks:ks_name":"Maholi Uparhar",
    "ks:ks_pop":3845,
    "ks:ks_type":"VILLAGE",
    "ks:ks_uagg_main":0,
    "name:eng_x_preferred":[
        "Maholi Uparhar"
    ],
    "wof:name":"Maholi Uparhar",
    "wof:placetype":"neighbourhood",
    "wof:population":3845
},
  "geometry": {"coordinates":[81.845572,26.794477],"type":"Point"}
}