{
  "type": "Feature",
  "properties": {
    "gn:admin1_code":"38.0",
    "gn:admin2_code":"358.0",
    "gn:asciiname":"Kunwai",
    "gn:country_code":"IN",
    "gn:dem":267,
    "gn:feature_class":"P",
    "gn:feature_code":"PPL",
    "gn:name":"Kunw\u0101\u012b",
    "gn:population":0,
    "gn:timezone":"Asia/Kolkata",
    "iso:country":"IN",
    "ks:ks_name":"Kunwai",
    "ks:ks_pop":4505,
    "ks:ks_type":"VILLAGE",
    "ks:ks_uagg_main":0,
    "name:eng_x_preferred":[
        "Kunwai"
    ],
    "wof:name":"Kunwai",
    "wof:placetype":"neighbourhood",
    "wof:population":4505
},
  "geometry": {"coordinates":[84.38672,24.071634],"type":"Point"}
}