{
  "type": "Feature",
  "properties": {
    "iso:country":"IN",
    "ks:ks_name":"Kepral",
    "ks:ks_pop":43,
    "ks:ks_type":"HABITATION",
    "name:eng_x_preferred":[
        "Kepral"
    ],
    "wof:name":"Kepral",
    "wof:placetype":"locality",
    "wof:population":43
},
  "geometry": {"coordinates":[75.02351299999999,13.288298],"type":"Point"}
}