{
  "type": "Feature",
  "properties": {
    "iso:country":"IN",
    "ks:ks_name":"Valvipada",
    "ks:ks_pop":487,
    "ks:ks_type":"HABITATION",
    "name:eng_x_preferred":[
        "Valvipada"
    ],
    "wof:name":"Valvipada",
    "wof:placetype":"locality",
    "wof:population":487
},
  "geometry": {"coordinates":[72.860162,19.99973],"type":"Point"}
}