{
  "type": "Feature",
  "properties": {
    "iso:country":"IN",
    "ks:ks_name":"Sri Raghunathpura",
    "ks:ks_pop":614,
    "ks:ks_type":"HABITATION",
    "name:eng_x_preferred":[
        "Sri Raghunathpura"
    ],
    "wof:name":"Sri Raghunathpura",
    "wof:placetype":"locality",
    "wof:population":614
},
  "geometry": {"coordinates":[74.470175,27.174044],"type":"Point"}
}