{
  "type": "Feature",
  "properties": {
    "gn:admin1_code":"34.0",
    "gn:admin2_code":"234.0",
    "gn:asciiname":"Salempur",
    "gn:country_code":"IN",
    "gn:dem":81,
    "gn:feature_class":"P",
    "gn:feature_code":"PPL",
    "gn:name":"Salempur",
    "gn:population":0,
    "gn:timezone":"Asia/Kolkata",
    "iso:country":"IN",
    "name:ceb_x_preferred":[
        "Salempur"
    ],
    "name:pol_x_preferred":[
        "Salempur"
    ],
    "name:swe_x_preferred":[
        "Salempur"
    ],
    "wof:name":"Salempur",
    "wof:placetype":"neighbourhood"
},
  "geometry": {"coordinates":[84.08844999999999,25.34041],"type":"Point"}
}