{
  "type": "Feature",
  "properties": {
    "iso:country":"IN",
    "ks:ks_name":"Singimari No 2",
    "ks:ks_pop":231,
    "ks:ks_type":"HABITATION",
    "name:eng_x_preferred":[
        "Singimari No 2"
    ],
    "wof:name":"Singimari No 2",
    "wof:placetype":"locality",
    "wof:population":231
},
  "geometry": {"coordinates":[93.973358,26.172032],"type":"Point"}
}