{
  "type": "Feature",
  "properties": {
    "iso:country":"IN",
    "ks:ks_alt_nam":"Tumbhad pada",
    "ks:ks_name":"Tumbhad Pada",
    "ks:ks_pop":103,
    "ks:ks_type":"HABITATION",
    "name:eng_x_preferred":[
        "Tumbhad Pada"
    ],
    "wof:name":"Tumbhad Pada",
    "wof:placetype":"locality",
    "wof:population":103
},
  "geometry": {"coordinates":[72.921164,19.779853],"type":"Point"}
}