{
  "type": "Feature",
  "properties": {
    "iso:country":"IN",
    "ks:ks_name":"Krishnabati",
    "ks:ks_pop":714,
    "ks:ks_type":"VILLAGE",
    "name:eng_x_preferred":[
        "Krishnabati"
    ],
    "wof:name":"Krishnabati",
    "wof:placetype":"locality",
    "wof:population":714
},
  "geometry": {"coordinates":[87.312684,23.380704],"type":"Point"}
}