{
  "type": "Feature",
  "properties": {
    "iso:country":"IN",
    "ks:ks_alt_nam":"Sarkhi para",
    "ks:ks_name":"Sarkhi Para",
    "ks:ks_pop":60,
    "ks:ks_type":"HABITATION",
    "name:eng_x_preferred":[
        "Sarkhi Para"
    ],
    "wof:name":"Sarkhi Para",
    "wof:placetype":"locality",
    "wof:population":60
},
  "geometry": {"coordinates":[91.661039,23.381881],"type":"Point"}
}