{
  "type": "Feature",
  "properties": {
    "iso:country":"IN",
    "ks:ks_name":"Chikli Camp",
    "ks:ks_pop":101,
    "ks:ks_type":"HABITATION",
    "name:eng_x_preferred":[
        "Chikli Camp"
    ],
    "wof:name":"Chikli Camp",
    "wof:placetype":"locality",
    "wof:population":101
},
  "geometry": {"coordinates":[78.061876,18.832309],"type":"Point"}
}