{
  "type": "Feature",
  "properties": {
    "gn:admin1_code":"34.0",
    "gn:admin2_code":"217.0",
    "gn:asciiname":"Malchaur",
    "gn:country_code":"IN",
    "gn:dem":77,
    "gn:feature_class":"P",
    "gn:feature_code":"PPL",
    "gn:name":"Malchaur",
    "gn:population":0,
    "gn:timezone":"Asia/Kolkata",
    "iso:country":"IN",
    "ks:ks_name":"Malchaur",
    "ks:ks_pop":646,
    "ks:ks_type":"VILLAGE",
    "ks:ks_uagg_main":0,
    "name:eng_x_preferred":[
        "Malchaur"
    ],
    "wof:name":"Malchaur",
    "wof:placetype":"neighbourhood",
    "wof:population":646
},
  "geometry": {"coordinates":[84.07705799999999,26.388721],"type":"Point"}
}