{
  "type": "Feature",
  "properties": {
    "iso:country":"IN",
    "ks:ks_name":"Bohabasti",
    "ks:ks_pop":254,
    "ks:ks_type":"HABITATION",
    "name:eng_x_preferred":[
        "Bohabasti"
    ],
    "wof:name":"Bohabasti",
    "wof:placetype":"locality",
    "wof:population":254
},
  "geometry": {"coordinates":[92.06044,26.798067],"type":"Point"}
}