{
  "type": "Feature",
  "properties": {
    "gn:admin1_code":"36",
    "gn:admin2_code":"147.0",
    "gn:asciiname":"Karanpura",
    "gn:country_code":"IN",
    "gn:dem":170,
    "gn:feature_class":"P",
    "gn:feature_code":"PPL",
    "gn:name":"Karanpura",
    "gn:population":0,
    "gn:timezone":"Asia/Kolkata",
    "iso:country":"IN",
    "ks:ks_name":"Karanpur",
    "ks:ks_pop":304,
    "ks:ks_type":"HABITATION",
    "ks:ks_uagg_main":0,
    "name:eng_x_preferred":[
        "Karanpur"
    ],
    "name:msa_x_preferred":[
        "Karanpura"
    ],
    "wof:name":"Karanpur",
    "wof:placetype":"neighbourhood",
    "wof:population":304
},
  "geometry": {"coordinates":[78.61726,27.436574],"type":"Point"}
}