{
  "type": "Feature",
  "properties": {
    "iso:country":"IN",
    "ks:ks_name":"Santoshipuram",
    "ks:ks_pop":176,
    "ks:ks_type":"VILLAGE",
    "name:eng_x_preferred":[
        "Santoshipuram"
    ],
    "wof:name":"Santoshipuram",
    "wof:placetype":"locality",
    "wof:population":176
},
  "geometry": {"coordinates":[84.322587,18.777474],"type":"Point"}
}