{
  "type": "Feature",
  "properties": {
    "iso:country":"IN",
    "ks:ks_name":"Totro",
    "ks:ks_pop":74,
    "ks:ks_type":"VILLAGE",
    "name:eng_x_preferred":[
        "Totro"
    ],
    "wof:name":"Totro",
    "wof:placetype":"locality",
    "wof:population":74
},
  "geometry": {"coordinates":[84.530737,23.472333],"type":"Point"}
}