{
  "type": "Feature",
  "properties": {
    "iso:country":"IN",
    "ks:ks_name":"Venkateswarapuram",
    "ks:ks_pop":219,
    "ks:ks_type":"HABITATION",
    "name:eng_x_preferred":[
        "Venkateswarapuram"
    ],
    "wof:name":"Venkateswarapuram",
    "wof:placetype":"locality",
    "wof:population":219
},
  "geometry": {"coordinates":[80.155399,14.537767],"type":"Point"}
}