{
  "type": "Feature",
  "properties": {
    "iso:country":"IN",
    "ks:ks_name":"Pankhala Shisha",
    "ks:ks_pop":858,
    "ks:ks_type":"HABITATION",
    "name:eng_x_preferred":[
        "Pankhala Shisha"
    ],
    "wof:name":"Pankhala Shisha",
    "wof:placetype":"locality",
    "wof:population":858
},
  "geometry": {"coordinates":[73.824383,21.681717],"type":"Point"}
}