{
  "type": "Feature",
  "properties": {
    "iso:country":"IN",
    "ks:ks_name":"Maskand Bhanjpur",
    "ks:ks_pop":261,
    "ks:ks_type":"VILLAGE",
    "ks:ks_uagg_main":0,
    "name:eng_x_preferred":[
        "Maskand Bhanjpur"
    ],
    "wof:name":"Maskand Bhanjpur",
    "wof:placetype":"neighbourhood",
    "wof:population":261
},
  "geometry": {"coordinates":[87.28020600000001,25.04383],"type":"Point"}
}