{
  "type": "Feature",
  "properties": {
    "iso:country":"IN",
    "ks:ks_name":"Mindhola Falia",
    "ks:ks_pop":202,
    "ks:ks_type":"HABITATION",
    "name:eng_x_preferred":[
        "Mindhola Falia"
    ],
    "wof:name":"Mindhola Falia",
    "wof:placetype":"locality",
    "wof:population":202
},
  "geometry": {"coordinates":[73.087389,20.894972],"type":"Point"}
}