{
  "type": "Feature",
  "properties": {
    "iso:country":"IN",
    "ks:ks_alt_nam":"melaveli",
    "ks:ks_name":"Melaveli",
    "ks:ks_pop":698,
    "ks:ks_type":"HABITATION",
    "name:eng_x_preferred":[
        "Melaveli"
    ],
    "wof:name":"Melaveli",
    "wof:placetype":"locality",
    "wof:population":698
},
  "geometry": {"coordinates":[79.795573,10.799008],"type":"Point"}
}