{
  "type": "Feature",
  "properties": {
    "iso:country":"IN",
    "ks:ks_name":"Jafar Chak",
    "ks:ks_pop":504,
    "ks:ks_type":"VILLAGE",
    "ks:ks_uagg_main":0,
    "name:eng_x_preferred":[
        "Jafar Chak"
    ],
    "wof:name":"Jafar Chak",
    "wof:placetype":"neighbourhood",
    "wof:population":504
},
  "geometry": {"coordinates":[87.914579,21.837549],"type":"Point"}
}