{
  "type": "Feature",
  "properties": {
    "iso:country":"IN",
    "ks:ks_name":"Turabadi",
    "ks:ks_pop":72,
    "ks:ks_type":"VILLAGE",
    "name:eng_x_preferred":[
        "Turabadi"
    ],
    "wof:name":"Turabadi",
    "wof:placetype":"locality",
    "wof:population":72
},
  "geometry": {"coordinates":[83.613337,19.671295],"type":"Point"}
}