{
  "type": "Feature",
  "properties": {
    "iso:country":"IN",
    "ks:ks_name":"Temtai Bari",
    "ks:ks_pop":87,
    "ks:ks_type":"HABITATION",
    "name:eng_x_preferred":[
        "Temtai Bari"
    ],
    "wof:name":"Temtai Bari",
    "wof:placetype":"locality",
    "wof:population":87
},
  "geometry": {"coordinates":[91.59256499999999,23.572247],"type":"Point"}
}