{
  "type": "Feature",
  "properties": {
    "gn:admin1_code":"34.0",
    "gn:admin2_code":"222.0",
    "gn:asciiname":"Rasalpur",
    "gn:country_code":"IN",
    "gn:dem":48,
    "gn:feature_class":"P",
    "gn:feature_code":"PPL",
    "gn:name":"Rasalpur",
    "gn:population":0,
    "gn:timezone":"Asia/Kolkata",
    "iso:country":"IN",
    "ks:ks_name":"Rasalpur",
    "ks:ks_pop":2233,
    "ks:ks_type":"VILLAGE",
    "name:eng_x_preferred":[
        "Rasalpur"
    ],
    "wof:name":"Rasalpur",
    "wof:placetype":"locality",
    "wof:population":2233
},
  "geometry": {"coordinates":[86.014464,25.525488],"type":"Point"}
}