{
  "type": "Feature",
  "properties": {
    "iso:country":"IN",
    "ks:ks_name":"Adankady Crc",
    "ks:ks_pop":11,
    "ks:ks_type":"HABITATION",
    "name:eng_x_preferred":[
        "Adankady Crc"
    ],
    "wof:name":"Adankady Crc",
    "wof:placetype":"locality",
    "wof:population":11
},
  "geometry": {"coordinates":[75.512119,12.770958],"type":"Point"}
}