{
  "type": "Feature",
  "properties": {
    "iso:country":"IN",
    "ks:ks_alt_nam":"SUBHAS COLLONY",
    "ks:ks_name":"Subhas Collony",
    "ks:ks_pop":257,
    "ks:ks_type":"HABITATION",
    "name:eng_x_preferred":[
        "Subhas Collony"
    ],
    "wof:name":"Subhas Collony",
    "wof:placetype":"locality",
    "wof:population":257
},
  "geometry": {"coordinates":[91.374099,23.470395],"type":"Point"}
}