{
  "type": "Feature",
  "properties": {
    "iso:country":"IN",
    "ks:ks_name":"Regadand",
    "ks:ks_pop":96,
    "ks:ks_type":"VILLAGE",
    "name:eng_x_preferred":[
        "Regadand"
    ],
    "wof:name":"Regadand",
    "wof:placetype":"locality",
    "wof:population":96
},
  "geometry": {"coordinates":[80.37399499999999,20.009379],"type":"Point"}
}