{
  "type": "Feature",
  "properties": {
    "gn:admin1_code":"11",
    "gn:admin2_code":"23.0",
    "gn:asciiname":"Phalunt",
    "gn:country_code":"IN",
    "gn:dem":1304,
    "gn:feature_class":"P",
    "gn:feature_code":"PPL",
    "gn:name":"Phalunt",
    "gn:population":0,
    "gn:timezone":"Asia/Kolkata",
    "iso:country":"IN",
    "wof:name":"Phalunt",
    "wof:placetype":"locality"
},
  "geometry": {"coordinates":[76.00218000000002,32.46446],"type":"Point"}
}