{
  "type": "Feature",
  "properties": {
    "iso:country":"IN",
    "ks:ks_name":"Karhi Tola",
    "ks:ks_pop":449,
    "ks:ks_type":"HABITATION",
    "name:eng_x_preferred":[
        "Karhi Tola"
    ],
    "wof:name":"Karhi Tola",
    "wof:placetype":"locality",
    "wof:population":449
},
  "geometry": {"coordinates":[81.643027,23.398499],"type":"Point"}
}