{
  "type": "Feature",
  "properties": {
    "iso:country":"IN",
    "ks:ks_name":"Vadhaiya Faliyu",
    "ks:ks_pop":229,
    "ks:ks_type":"HABITATION",
    "ks:ks_uagg_main":0,
    "name:eng_x_preferred":[
        "Vadhaiya Faliyu"
    ],
    "wof:name":"Vadhaiya Faliyu",
    "wof:placetype":"neighbourhood",
    "wof:population":229
},
  "geometry": {"coordinates":[72.769172,20.284824],"type":"Point"}
}