{
  "type": "Feature",
  "properties": {
    "iso:country":"IN",
    "ks:ks_name":"Vedagpada",
    "ks:ks_pop":591,
    "ks:ks_type":"HABITATION",
    "name:eng_x_preferred":[
        "Vedagpada"
    ],
    "wof:name":"Vedagpada",
    "wof:placetype":"locality",
    "wof:population":591
},
  "geometry": {"coordinates":[72.936986,20.152055],"type":"Point"}
}