{
  "type": "Feature",
  "properties": {
    "iso:country":"IN",
    "ks:ks_name":"Gerakombe",
    "ks:ks_pop":10,
    "ks:ks_type":"HABITATION",
    "name:eng_x_preferred":[
        "Gerakombe"
    ],
    "wof:name":"Gerakombe",
    "wof:placetype":"locality",
    "wof:population":10
},
  "geometry": {"coordinates":[74.69659299999999,14.984663],"type":"Point"}
}