{
  "type": "Feature",
  "properties": {
    "iso:country":"IN",
    "ks:ks_name":"Alonitola",
    "ks:ks_pop":180,
    "ks:ks_type":"HABITATION",
    "name:eng_x_preferred":[
        "Alonitola"
    ],
    "wof:name":"Alonitola",
    "wof:placetype":"locality",
    "wof:population":180
},
  "geometry": {"coordinates":[80.069761,20.20475],"type":"Point"}
}