{
  "type": "Feature",
  "properties": {
    "gn:admin1_code":"36",
    "gn:admin2_code":"197.0",
    "gn:asciiname":"Dulah Arazi",
    "gn:country_code":"IN",
    "gn:dem":81,
    "gn:feature_class":"P",
    "gn:feature_code":"PPL",
    "gn:name":"D\u016bl\u0101h Ar\u0101z\u012b",
    "gn:population":0,
    "gn:timezone":"Asia/Kolkata",
    "iso:country":"IN",
    "wof:name":"Dulah Arazi",
    "wof:placetype":"neighbourhood"
},
  "geometry": {"coordinates":[82.92049,25.54229],"type":"Point"}
}