{
  "type": "Feature",
  "properties": {
    "iso:country":"IN",
    "ks:ks_alt_nam":"Botlagatla tanda",
    "ks:ks_name":"Botlagatla Tanda",
    "ks:ks_pop":133,
    "ks:ks_type":"HABITATION",
    "name:eng_x_preferred":[
        "Botlagatla Tanda"
    ],
    "wof:name":"Botlagatla Tanda",
    "wof:placetype":"locality",
    "wof:population":133
},
  "geometry": {"coordinates":[77.879361,16.967913],"type":"Point"}
}