{
  "type": "Feature",
  "properties": {
    "iso:country":"IN",
    "ks:ks_name":"Pure Bajrang",
    "ks:ks_pop":59,
    "ks:ks_type":"HABITATION",
    "ks:ks_uagg_main":0,
    "name:eng_x_preferred":[
        "Pure Bajrang"
    ],
    "wof:name":"Pure Bajrang",
    "wof:placetype":"neighbourhood",
    "wof:population":59
},
  "geometry": {"coordinates":[81.479657,26.561441],"type":"Point"}
}