{
  "type": "Feature",
  "properties": {
    "gn:admin1_code":"35",
    "gn:admin2_code":"463.0",
    "gn:asciiname":"Jhurhanar",
    "gn:country_code":"IN",
    "gn:dem":394,
    "gn:feature_class":"P",
    "gn:feature_code":"PPL",
    "gn:name":"Jhurh\u0101n\u0101r",
    "gn:population":0,
    "gn:timezone":"Asia/Kolkata",
    "iso:country":"IN",
    "ks:ks_alt_nam":"Jhurh\u0101n\u0101r",
    "ks:ks_name":"Jhurhanar",
    "ks:ks_pop":560,
    "ks:ks_type":"VILLAGE",
    "name:eng_x_preferred":[
        "Jhurhanar"
    ],
    "name:eng_x_variant":[
        "Jhurh\u0101n\u0101r"
    ],
    "wof:name":"Jhurhanar",
    "wof:placetype":"locality",
    "wof:population":560
},
  "geometry": {"coordinates":[82.22951500000001,24.132373],"type":"Point"}
}