{
  "type": "Feature",
  "properties": {
    "gn:admin1_code":"39.0",
    "gn:admin2_code":"66.0",
    "gn:asciiname":"Peras Rampur",
    "gn:country_code":"IN",
    "gn:dem":290,
    "gn:feature_class":"P",
    "gn:feature_code":"PPL",
    "gn:name":"Peras R\u0101mpur",
    "gn:population":0,
    "gn:timezone":"Asia/Kolkata",
    "iso:country":"IN",
    "ks:ks_name":"Parasurampur",
    "ks:ks_pop":181,
    "ks:ks_type":"VILLAGE",
    "ks:ks_uagg_main":0,
    "name:eng_x_preferred":[
        "Parasurampur"
    ],
    "wof:name":"Parasurampur",
    "wof:placetype":"neighbourhood",
    "wof:population":181
},
  "geometry": {"coordinates":[79.689913,29.105916],"type":"Point"}
}