{
  "type": "Feature",
  "properties": {
    "iso:country":"IN",
    "ks:ks_name":"Rampur Milki",
    "ks:ks_pop":316,
    "ks:ks_type":"VILLAGE",
    "name:eng_x_preferred":[
        "Rampur Milki"
    ],
    "wof:name":"Rampur Milki",
    "wof:placetype":"locality",
    "wof:population":316
},
  "geometry": {"coordinates":[85.1221,25.92678],"type":"Point"}
}