{
  "type": "Feature",
  "properties": {
    "iso:country":"IN",
    "ks:ks_name":"Chirakode",
    "ks:ks_pop":1130,
    "ks:ks_type":"HABITATION",
    "name:eng_x_preferred":[
        "Chirakode"
    ],
    "wof:name":"Chirakode",
    "wof:placetype":"locality",
    "wof:population":1130
},
  "geometry": {"coordinates":[76.484315,10.683212],"type":"Point"}
}