{
  "type": "Feature",
  "properties": {
    "gn:admin1_code":"37.0",
    "gn:admin2_code":"416.0",
    "gn:asciiname":"Mekabeda",
    "gn:country_code":"IN",
    "gn:dem":246,
    "gn:feature_class":"P",
    "gn:feature_code":"PPL",
    "gn:name":"Mekabeda",
    "gn:population":0,
    "gn:timezone":"Asia/Kolkata",
    "iso:country":"IN",
    "wof:name":"Mekabeda",
    "wof:placetype":"locality"
},
  "geometry": {"coordinates":[81.81979,18.61332],"type":"Point"}
}