{
  "type": "Feature",
  "properties": {
    "iso:country":"IN",
    "ks:ks_alt_nam":"H. GUPTA TOLA",
    "ks:ks_name":"H. Gupta Tola",
    "ks:ks_pop":251,
    "ks:ks_type":"HABITATION",
    "ks:ks_uagg_main":0,
    "name:eng_x_preferred":[
        "H. Gupta Tola"
    ],
    "wof:name":"H. Gupta Tola",
    "wof:placetype":"neighbourhood",
    "wof:population":251
},
  "geometry": {"coordinates":[86.653119,26.085395],"type":"Point"}
}