{
  "type": "Feature",
  "properties": {
    "gn:admin1_code":"12.0",
    "gn:admin2_code":"17.0",
    "gn:asciiname":"Mori",
    "gn:country_code":"IN",
    "gn:dem":2837,
    "gn:feature_class":"P",
    "gn:feature_code":"PPL",
    "gn:name":"M\u014dri",
    "gn:population":0,
    "gn:timezone":"Asia/Kolkata",
    "iso:country":"IN",
    "wof:name":"Mori",
    "wof:placetype":"locality"
},
  "geometry": {"coordinates":[75.26748000000001,33.41472],"type":"Point"}
}