{
  "type": "Feature",
  "properties": {
    "iso:country":"IN",
    "ks:ks_name":"Dakshin Tara Nagar Nath Para",
    "ks:ks_pop":1231,
    "ks:ks_type":"HABITATION",
    "name:eng_x_preferred":[
        "Dakshin Tara Nagar Nath Para"
    ],
    "wof:name":"Dakshin Tara Nagar Nath Para",
    "wof:placetype":"locality",
    "wof:population":1231
},
  "geometry": {"coordinates":[88.870873,22.224142],"type":"Point"}
}