{
  "type": "Feature",
  "properties": {
    "iso:country":"IN",
    "ks:ks_name":"1 BPSM",
    "ks:ks_pop":91,
    "ks:ks_type":"VILLAGE",
    "name:eng_x_preferred":[
        "1 BPSM"
    ],
    "wof:name":"1 BPSM",
    "wof:placetype":"locality",
    "wof:population":91
},
  "geometry": {"coordinates":[74.480672,29.305414],"type":"Point"}
}