{
  "type": "Feature",
  "properties": {
    "iso:country":"IN",
    "ks:ks_name":"Banjamunda",
    "ks:ks_pop":132,
    "ks:ks_type":"VILLAGE",
    "name:eng_x_preferred":[
        "Banjamunda"
    ],
    "wof:name":"Banjamunda",
    "wof:placetype":"locality",
    "wof:population":132
},
  "geometry": {"coordinates":[83.606527,20.270918],"type":"Point"}
}