{
  "type": "Feature",
  "properties": {
    "iso:country":"IN",
    "ks:ks_name":"Kosamput",
    "ks:ks_pop":300,
    "ks:ks_type":"HABITATION",
    "name:eng_x_preferred":[
        "Kosamput"
    ],
    "wof:name":"Kosamput",
    "wof:placetype":"locality",
    "wof:population":300
},
  "geometry": {"coordinates":[82.393314,18.435735],"type":"Point"}
}