{
  "type": "Feature",
  "properties": {
    "iso:country":"IN",
    "ks:ks_name":"Gaidpally",
    "ks:ks_pop":131,
    "ks:ks_type":"HABITATION",
    "name:eng_x_preferred":[
        "Gaidpally"
    ],
    "wof:name":"Gaidpally",
    "wof:placetype":"locality",
    "wof:population":131
},
  "geometry": {"coordinates":[78.497276,19.338593],"type":"Point"}
}