{
  "type": "Feature",
  "properties": {
    "iso:country":"IN",
    "ks:ks_name":"Sibalingapur",
    "ks:ks_pop":122,
    "ks:ks_type":"VILLAGE",
    "name:eng_x_preferred":[
        "Sibalingapur"
    ],
    "wof:name":"Sibalingapur",
    "wof:placetype":"locality",
    "wof:population":122
},
  "geometry": {"coordinates":[83.731972,19.350897],"type":"Point"}
}