{
  "type": "Feature",
  "properties": {
    "iso:country":"IN",
    "ks:ks_name":"Kere Katte",
    "ks:ks_pop":227,
    "ks:ks_type":"HABITATION",
    "name:eng_x_preferred":[
        "Kere Katte"
    ],
    "wof:name":"Kere Katte",
    "wof:placetype":"locality",
    "wof:population":227
},
  "geometry": {"coordinates":[74.416493,14.377978],"type":"Point"}
}