{
  "type": "Feature",
  "properties": {
    "iso:country":"IN",
    "ks:ks_alt_nam":"Karipuzha west",
    "ks:ks_name":"Karipuzha West",
    "ks:ks_pop":201,
    "ks:ks_type":"HABITATION",
    "name:eng_x_preferred":[
        "Karipuzha West"
    ],
    "wof:name":"Karipuzha West",
    "wof:placetype":"locality",
    "wof:population":201
},
  "geometry": {"coordinates":[76.48919600000001,9.264465],"type":"Point"}
}