{
  "type": "Feature",
  "properties": {
    "iso:country":"IN",
    "ks:ks_name":"Sau",
    "ks:ks_pop":2688,
    "ks:ks_type":"VILLAGE",
    "ks:ks_uagg_main":0,
    "name:eng_x_preferred":[
        "Sau"
    ],
    "wof:name":"Sau",
    "wof:placetype":"neighbourhood",
    "wof:population":2688
},
  "geometry": {"coordinates":[77.735163,23.785809],"type":"Point"}
}