{
  "type": "Feature",
  "properties": {
    "iso:country":"IN",
    "ks:ks_name":"Saoli Tukum",
    "ks:ks_pop":355,
    "ks:ks_type":"HABITATION",
    "name:eng_x_preferred":[
        "Saoli Tukum"
    ],
    "wof:name":"Saoli Tukum",
    "wof:placetype":"locality",
    "wof:population":355
},
  "geometry": {"coordinates":[79.78707,20.068172],"type":"Point"}
}