{
  "type": "Feature",
  "properties": {
    "iso:country":"IN",
    "ks:ks_name":"Gundalametta",
    "ks:ks_pop":56,
    "ks:ks_type":"HABITATION",
    "name:eng_x_preferred":[
        "Gundalametta"
    ],
    "wof:name":"Gundalametta",
    "wof:placetype":"locality",
    "wof:population":56
},
  "geometry": {"coordinates":[82.470046,18.217863],"type":"Point"}
}