{
  "type": "Feature",
  "properties": {
    "iso:country":"IN",
    "ks:ks_name":"Mundacka North",
    "ks:ks_pop":725,
    "ks:ks_type":"HABITATION",
    "name:eng_x_preferred":[
        "Mundacka North"
    ],
    "wof:name":"Mundacka North",
    "wof:placetype":"locality",
    "wof:population":725
},
  "geometry": {"coordinates":[76.668908,10.297079],"type":"Point"}
}