{
  "type": "Feature",
  "properties": {
    "gn:admin1_code":"36",
    "gn:admin2_code":"158.0",
    "gn:asciiname":"Gosigarh",
    "gn:country_code":"IN",
    "gn:dem":108,
    "gn:feature_class":"P",
    "gn:feature_code":"PPL",
    "gn:name":"Gosigarh",
    "gn:population":0,
    "gn:timezone":"Asia/Kolkata",
    "iso:country":"IN",
    "ks:ks_name":"Ghisi Garh",
    "ks:ks_pop":804,
    "ks:ks_type":"VILLAGE",
    "name:eng_x_preferred":[
        "Ghisi Garh"
    ],
    "name:eng_x_variant":[
        "Gosigarh"
    ],
    "wof:name":"Ghisi Garh",
    "wof:placetype":"locality",
    "wof:population":804
},
  "geometry": {"coordinates":[81.42567099999999,26.091739],"type":"Point"}
}