{
  "type": "Feature",
  "properties": {
    "iso:country":"IN",
    "ks:ks_name":"Major Pandey Dih",
    "ks:ks_pop":194,
    "ks:ks_type":"HABITATION",
    "name:eng_x_preferred":[
        "Major Pandey Dih"
    ],
    "wof:name":"Major Pandey Dih",
    "wof:placetype":"locality",
    "wof:population":194
},
  "geometry": {"coordinates":[82.50308200000001,27.014903],"type":"Point"}
}