{
  "type": "Feature",
  "properties": {
    "iso:country":"IN",
    "ks:ks_name":"Gauli",
    "ks:ks_pop":968,
    "ks:ks_type":"VILLAGE",
    "name:eng_x_preferred":[
        "Gauli"
    ],
    "wof:name":"Gauli",
    "wof:placetype":"locality",
    "wof:population":968
},
  "geometry": {"coordinates":[79.906057,29.565877],"type":"Point"}
}