{
  "type": "Feature",
  "properties": {
    "gn:admin1_code":"23.0",
    "gn:admin2_code":"040",
    "gn:asciiname":"Rajgarh Channa",
    "gn:country_code":"IN",
    "gn:dem":257,
    "gn:feature_class":"P",
    "gn:feature_code":"PPL",
    "gn:name":"R\u0101jgarh Channa",
    "gn:population":0,
    "gn:timezone":"Asia/Kolkata",
    "iso:country":"IN",
    "wof:name":"Rajgarh Channa",
    "wof:placetype":"locality"
},
  "geometry": {"coordinates":[76.17782,30.56551],"type":"Point"}
}