{
  "type": "Feature",
  "properties": {
    "iso:country":"IN",
    "ks:ks_name":"Santikayatpur",
    "ks:ks_pop":0,
    "ks:ks_type":"VILLAGE",
    "name:eng_x_preferred":[
        "Santikayatpur"
    ],
    "wof:name":"Santikayatpur",
    "wof:placetype":"locality",
    "wof:population":0
},
  "geometry": {"coordinates":[87.185248,21.940004],"type":"Point"}
}