{
  "type": "Feature",
  "properties": {
    "gn:admin1_code":"2.0",
    "gn:admin2_code":"544.0",
    "gn:asciiname":"Pallipudungada",
    "gn:country_code":"IN",
    "gn:dem":484,
    "gn:feature_class":"P",
    "gn:feature_code":"PPL",
    "gn:name":"Pallipudung\u0101da",
    "gn:population":0,
    "gn:timezone":"Asia/Kolkata",
    "iso:country":"IN",
    "ks:ks_name":"Pallapudungada",
    "ks:ks_pop":282,
    "ks:ks_type":"HABITATION",
    "name:eng_x_preferred":[
        "Pallapudungada"
    ],
    "name:eng_x_variant":[
        "Pallipudungada"
    ],
    "wof:name":"Pallapudungada",
    "wof:placetype":"locality",
    "wof:population":282
},
  "geometry": {"coordinates":[83.06644900000001,18.137141],"type":"Point"}
}