{
  "type": "Feature",
  "properties": {
    "gn:admin1_code":"11",
    "gn:admin2_code":"24.0",
    "gn:asciiname":"Rayantran Sarajan",
    "gn:country_code":"IN",
    "gn:dem":593,
    "gn:feature_class":"P",
    "gn:feature_code":"PPL",
    "gn:name":"Rayantr\u0101n Sar\u0101j\u0101n",
    "gn:population":0,
    "gn:timezone":"Asia/Kolkata",
    "iso:country":"IN",
    "wof:name":"Rayantran Sarajan",
    "wof:placetype":"locality"
},
  "geometry": {"coordinates":[76.24129000000001,31.79825],"type":"Point"}
}