{
  "type": "Feature",
  "properties": {
    "iso:country":"IN",
    "ks:ks_name":"No.3 Dirpai Chapari",
    "ks:ks_pop":420,
    "ks:ks_type":"VILLAGE",
    "ks:ks_uagg_main":0,
    "name:eng_x_preferred":[
        "No.3 Dirpai Chapari"
    ],
    "wof:name":"No.3 Dirpai Chapari",
    "wof:placetype":"neighbourhood",
    "wof:population":420
},
  "geometry": {"coordinates":[94.322514,27.487973],"type":"Point"}
}