{
  "type": "Feature",
  "properties": {
    "iso:country":"IN",
    "ks:ks_name":"Basdevkona",
    "ks:ks_pop":380,
    "ks:ks_type":"HABITATION",
    "name:eng_x_preferred":[
        "Basdevkona"
    ],
    "wof:name":"Basdevkona",
    "wof:placetype":"locality",
    "wof:population":380
},
  "geometry": {"coordinates":[84.46575,22.921927],"type":"Point"}
}