{
  "type": "Feature",
  "properties": {
    "iso:country":"IN",
    "ks:ks_alt_nam":"JAI BARI",
    "ks:ks_name":"Jai Bari",
    "ks:ks_pop":176,
    "ks:ks_type":"HABITATION",
    "name:eng_x_preferred":[
        "Jai Bari"
    ],
    "wof:name":"Jai Bari",
    "wof:placetype":"locality",
    "wof:population":176
},
  "geometry": {"coordinates":[91.646567,24.020679],"type":"Point"}
}