{
  "type": "Feature",
  "properties": {
    "iso:country":"IN",
    "ks:ks_name":"Amalkuri",
    "ks:ks_pop":378,
    "ks:ks_type":"VILLAGE",
    "ks:ks_uagg_main":0,
    "name:eng_x_preferred":[
        "Amalkuri"
    ],
    "wof:name":"Amalkuri",
    "wof:placetype":"neighbourhood",
    "wof:population":378
},
  "geometry": {"coordinates":[86.129205,23.923246],"type":"Point"}
}