{
  "type": "Feature",
  "properties": {
    "gn:admin1_code":"21",
    "gn:admin2_code":"394.0",
    "gn:asciiname":"Lakhna",
    "gn:country_code":"IN",
    "gn:dem":343,
    "gn:feature_class":"P",
    "gn:feature_code":"PPL",
    "gn:name":"Lakhna",
    "gn:population":0,
    "gn:timezone":"Asia/Kolkata",
    "iso:country":"IN",
    "name:bpy_x_preferred":[
        "\u09b2\u09be\u0996\u09a8\u09be"
    ],
    "name:ceb_x_preferred":[
        "Dakhn\u0101"
    ],
    "name:hif_x_preferred":[
        "Lakhna"
    ],
    "name:hin_x_preferred":[
        "\u0932\u0916\u0928\u093e"
    ],
    "name:ita_x_preferred":[
        "Lakhna"
    ],
    "name:mlg_x_preferred":[
        "Lakhna"
    ],
    "name:msa_x_preferred":[
        "Lakhna"
    ],
    "name:new_x_preferred":[
        "\u0932\u0916\u0928\u093e"
    ],
    "name:nld_x_preferred":[
        "Lakhna"
    ],
    "name:pol_x_preferred":[
        "Lakhna"
    ],
    "name:por_x_preferred":[
        "Lakhna"
    ],
    "name:sco_x_preferred":[
        "Lakhna"
    ],
    "name:swe_x_preferred":[
        "Dakhn\u0101"
    ],
    "name:urd_x_preferred":[
        "\u0644\u06a9\u06be\u0646\u0627"
    ],
    "name:vie_x_preferred":[
        "Lakhna"
    ],
    "name:zho_x_preferred":[
        "\u62c9\u514b\u7eb3"
    ],
    "wof:name":"Lakhna",
    "wof:placetype":"locality"
},
  "geometry": {"coordinates":[82.65124,20.73343],"type":"Point"}
}