{
  "type": "Feature",
  "properties": {
    "iso:country":"IN",
    "ks:ks_name":"Shyamsundarpur",
    "ks:ks_pop":0,
    "ks:ks_type":"VILLAGE",
    "name:eng_x_preferred":[
        "Shyamsundarpur"
    ],
    "wof:name":"Shyamsundarpur",
    "wof:placetype":"locality",
    "wof:population":0
},
  "geometry": {"coordinates":[87.338651,23.310295],"type":"Point"}
}