{
  "type": "Feature",
  "properties": {
    "iso:country":"IN",
    "ks:ks_alt_nam":"PADIYAR VASAHAT",
    "ks:ks_name":"Padiyar Vasahat",
    "ks:ks_pop":487,
    "ks:ks_type":"HABITATION",
    "name:eng_x_preferred":[
        "Padiyar Vasahat"
    ],
    "wof:name":"Padiyar Vasahat",
    "wof:placetype":"locality",
    "wof:population":487
},
  "geometry": {"coordinates":[74.491478,16.70895],"type":"Point"}
}