{
  "type": "Feature",
  "properties": {
    "iso:country":"IN",
    "ks:ks_name":"Nagla Bagh",
    "ks:ks_pop":276,
    "ks:ks_type":"HABITATION",
    "name:eng_x_preferred":[
        "Nagla Bagh"
    ],
    "wof:name":"Nagla Bagh",
    "wof:placetype":"locality",
    "wof:population":276
},
  "geometry": {"coordinates":[78.243846,28.22475],"type":"Point"}
}