{
  "type": "Feature",
  "properties": {
    "iso:country":"IN",
    "ks:ks_alt_nam":"charmkarwadi",
    "ks:ks_name":"Charmkarwadi",
    "ks:ks_pop":80,
    "ks:ks_type":"HABITATION",
    "name:eng_x_preferred":[
        "Charmkarwadi"
    ],
    "wof:name":"Charmkarwadi",
    "wof:placetype":"locality",
    "wof:population":80
},
  "geometry": {"coordinates":[73.652456,16.581497],"type":"Point"}
}