{
  "type": "Feature",
  "properties": {
    "gn:admin1_code":"10",
    "gn:admin2_code":"83.0",
    "gn:asciiname":"Dhaur",
    "gn:country_code":"IN",
    "gn:dem":218,
    "gn:feature_class":"P",
    "gn:feature_code":"PPL",
    "gn:name":"Dhaur",
    "gn:population":0,
    "gn:timezone":"Asia/Kolkata",
    "iso:country":"IN",
    "wof:name":"Dhaur",
    "wof:placetype":"neighbourhood"
},
  "geometry": {"coordinates":[76.60917000000001,28.65551],"type":"Point"}
}