{
  "type": "Feature",
  "properties": {
    "iso:country":"IN",
    "ks:ks_name":"Khand",
    "ks:ks_pop":611,
    "ks:ks_type":"HABITATION",
    "name:eng_x_preferred":[
        "Khand"
    ],
    "wof:name":"Khand",
    "wof:placetype":"locality",
    "wof:population":611
},
  "geometry": {"coordinates":[73.106357,19.780653],"type":"Point"}
}