{
  "type": "Feature",
  "properties": {
    "iso:country":"IN",
    "ks:ks_name":"Gunandapur",
    "ks:ks_pop":2526,
    "ks:ks_type":"VILLAGE",
    "ks:ks_uagg_main":0,
    "name:eng_x_preferred":[
        "Gunandapur"
    ],
    "wof:name":"Gunandapur",
    "wof:placetype":"neighbourhood",
    "wof:population":2526
},
  "geometry": {"coordinates":[87.98087099999999,22.439454],"type":"Point"}
}