{
  "type": "Feature",
  "properties": {
    "iso:country":"IN",
    "ks:ks_name":"1 AMP-B",
    "ks:ks_pop":16,
    "ks:ks_type":"VILLAGE",
    "name:eng_x_preferred":[
        "1 AMP-B"
    ],
    "wof:name":"1 AMP-B",
    "wof:placetype":"locality",
    "wof:population":16
},
  "geometry": {"coordinates":[74.422605,29.880457],"type":"Point"}
}