{
  "type": "Feature",
  "properties": {
    "gn:admin1_code":"34",
    "gn:admin2_code":"218.0",
    "gn:asciiname":"Jasauli Pakauli",
    "gn:country_code":"IN",
    "gn:dem":69,
    "gn:feature_class":"P",
    "gn:feature_code":"PPL",
    "gn:name":"Jasauli Pakauli",
    "gn:population":0,
    "gn:timezone":"Asia/Kolkata",
    "iso:country":"IN",
    "ks:ks_name":"Jasauli Pakauli",
    "ks:ks_pop":3130,
    "ks:ks_type":"VILLAGE",
    "ks:ks_uagg_main":0,
    "name:eng_x_preferred":[
        "Jasauli Pakauli"
    ],
    "wof:name":"Jasauli Pakauli",
    "wof:placetype":"locality",
    "wof:population":3130
},
  "geometry": {"coordinates":[84.40368100000001,26.184443],"type":"Point"}
}