{
  "type": "Feature",
  "properties": {
    "gn:admin1_code":"12.0",
    "gn:admin2_code":"008",
    "gn:asciiname":"Bandi",
    "gn:country_code":"IN",
    "gn:dem":1902,
    "gn:feature_class":"P",
    "gn:feature_code":"PPL",
    "gn:name":"B\u0101ndi",
    "gn:population":0,
    "gn:timezone":"Asia/Kolkata",
    "iso:country":"IN",
    "name:ceb_x_preferred":[
        "Bandi"
    ],
    "name:deu_x_preferred":[
        "Bandi"
    ],
    "name:fra_x_preferred":[
        "Bandi"
    ],
    "name:ita_x_preferred":[
        "Bandi"
    ],
    "name:slv_x_preferred":[
        "Bandi"
    ],
    "name:swe_x_preferred":[
        "Bandi"
    ],
    "name:vie_x_preferred":[
        "Bandi"
    ],
    "wof:name":"Bandi",
    "wof:placetype":"locality"
},
  "geometry": {"coordinates":[74.19143000000003,34.30843],"type":"Point"}
}