{
  "type": "Feature",
  "properties": {
    "iso:country":"IN",
    "ks:ks_name":"Ganjigedda",
    "ks:ks_pop":120,
    "ks:ks_type":"VILLAGE",
    "name:eng_x_preferred":[
        "Ganjigedda"
    ],
    "wof:name":"Ganjigedda",
    "wof:placetype":"locality",
    "wof:population":120
},
  "geometry": {"coordinates":[82.590722,17.910515],"type":"Point"}
}