{
  "type": "Feature",
  "properties": {
    "iso:country":"IN",
    "ks:ks_name":"Sursinga",
    "ks:ks_pop":369,
    "ks:ks_type":"VILLAGE",
    "name:eng_x_preferred":[
        "Sursinga"
    ],
    "wof:name":"Sursinga",
    "wof:placetype":"locality",
    "wof:population":369
},
  "geometry": {"coordinates":[86.606185,22.809606],"type":"Point"}
}