{
  "type": "Feature",
  "properties": {
    "gn:admin1_code":"36",
    "gn:admin2_code":"180.0",
    "gn:asciiname":"Bangla",
    "gn:country_code":"IN",
    "gn:dem":123,
    "gn:feature_class":"P",
    "gn:feature_code":"PPL",
    "gn:name":"Bangla",
    "gn:population":0,
    "gn:timezone":"Asia/Kolkata",
    "iso:country":"IN",
    "name:asm_x_preferred":[
        "\u09ac\u09be\u0982\u09b2\u09be"
    ],
    "name:ben_x_preferred":[
        "\u09ac\u09be\u0982\u09b2\u09be"
    ],
    "name:ceb_x_preferred":[
        "Bangla"
    ],
    "name:ita_x_preferred":[
        "Bangla"
    ],
    "name:swe_x_preferred":[
        "Bangla"
    ],
    "wof:name":"Bangla",
    "wof:placetype":"locality"
},
  "geometry": {"coordinates":[81.5645,27.67771],"type":"Point"}
}