{
  "type": "Feature",
  "properties": {
    "gn:admin1_code":"36",
    "gn:admin2_code":"196.0",
    "gn:asciiname":"Baraipur",
    "gn:country_code":"IN",
    "gn:dem":81,
    "gn:feature_class":"P",
    "gn:feature_code":"PPL",
    "gn:name":"Baraipur",
    "gn:population":0,
    "gn:timezone":"Asia/Kolkata",
    "iso:country":"IN",
    "name:ara_x_preferred":[
        "\u0628\u0627\u0631\u0627\u0628\u0648\u0631"
    ],
    "name:ben_bn_x_preferred":[
        "\u09ac\u09be\u09b0\u09be\u0987\u09aa\u09c1\u09b0"
    ],
    "name:ben_in_x_preferred":[
        "\u09ac\u09be\u09b0\u09be\u0987\u09aa\u09c1\u09b0"
    ],
    "name:ceb_x_preferred":[
        "Baraipur"
    ],
    "name:guj_x_preferred":[
        "\u0aac\u0ac8\u0ab0\u0abe\u0aaa\u0ac1\u0ab0"
    ],
    "name:hin_x_preferred":[
        "\u092c\u0930\u093f\u092f\u093e\u092a\u0941\u0930"
    ],
    "name:kan_x_preferred":[
        "\u0cac\u0cb0\u0cbe\u0caf\u0ccd"
    ],
    "name:mal_x_preferred":[
        "\u0d2c\u0d30\u0d48\u0d2a\u0d42\u0d7c"
    ],
    "name:mar_x_preferred":[
        "\u092c\u0930\u093e\u0908\u092a\u0942\u0930"
    ],
    "name:msa_x_preferred":[
        "Baraipur"
    ],
    "name:pan_x_preferred":[
        "\u0a2c\u0a30\u0a3e\u0a07\u0a2a\u0a41\u0a30"
    ],
    "name:pol_x_preferred":[
        "Baraipur"
    ],
    "name:tam_x_preferred":[
        "\u0baa\u0bb0\u0bbe\u0baf\u0bcd\u0baa\u0bc2\u0bb0\u0bcd"
    ],
    "name:tel_x_preferred":[
        "\u0c2c\u0c30\u0c48\u0c2a\u0c42\u0c30\u0c4d"
    ],
    "name:urd_x_preferred":[
        "\u0628\u0631\u0627\u0626\u06cc\u067e\u0648\u0631"
    ],
    "wof:name":"Baraipur",
    "wof:placetype":"locality"
},
  "geometry": {"coordinates":[83.20411999999997,25.35223],"type":"Point"}
}