{
  "type": "Feature",
  "properties": {
    "gn:admin1_code":"25.0",
    "gn:admin2_code":"630.0",
    "gn:asciiname":"Tadanur",
    "gn:country_code":"IN",
    "gn:dem":426,
    "gn:feature_class":"P",
    "gn:feature_code":"PPL",
    "gn:name":"T\u0101dan\u016br",
    "gn:population":0,
    "gn:timezone":"Asia/Kolkata",
    "iso:country":"IN",
    "wof:name":"Tadanur",
    "wof:placetype":"locality"
},
  "geometry": {"coordinates":[78.36135999999998,12.03799],"type":"Point"}
}