{
  "type": "Feature",
  "properties": {
    "iso:country":"IN",
    "ks:ks_name":"Boneikela",
    "ks:ks_pop":0,
    "ks:ks_type":"VILLAGE",
    "name:eng_x_preferred":[
        "Boneikela"
    ],
    "wof:name":"Boneikela",
    "wof:placetype":"locality",
    "wof:population":0
},
  "geometry": {"coordinates":[84.92438,21.7245],"type":"Point"}
}