{
  "type": "Feature",
  "properties": {
    "iso:country":"IN",
    "ks:ks_name":"Pushpagiri Jn",
    "ks:ks_pop":313,
    "ks:ks_type":"HABITATION",
    "ks:ks_uagg_main":0,
    "name:eng_x_preferred":[
        "Pushpagiri Jn"
    ],
    "wof:name":"Pushpagiri Jn",
    "wof:placetype":"neighbourhood",
    "wof:population":313
},
  "geometry": {"coordinates":[76.38494,10.293693],"type":"Point"}
}