{
  "type": "Feature",
  "properties": {
    "gn:country":"IN",
    "gn:fcode":"PPL",
    "gn:population":10109,
    "iso:country":"IN",
    "name:ben_x_preferred":[
        "\u09ae\u09bf\u09b0\u09bf\u0995"
    ],
    "name:bpy_x_preferred":[
        "\u09ae\u09bf\u09b0\u09bf\u0995"
    ],
    "name:bul_x_preferred":[
        "\u041c\u0438\u0440\u0438\u043a"
    ],
    "name:ceb_x_preferred":[
        "Mirik"
    ],
    "name:eng_x_preferred":[
        "Mirik"
    ],
    "name:fra_x_preferred":[
        "Mirik"
    ],
    "name:guj_x_preferred":[
        "\u0aae\u0abf\u0ab0\u0abf\u0a95"
    ],
    "name:hin_x_preferred":[
        "\u092e\u093f\u0930\u093f\u0915"
    ],
    "name:ita_x_preferred":[
        "Mirik"
    ],
    "name:mlg_x_preferred":[
        "Mirik"
    ],
    "name:msa_x_preferred":[
        "Mirik"
    ],
    "name:nan_x_preferred":[
        "Mirik"
    ],
    "name:new_x_preferred":[
        "\u092e\u093f\u0930\u093f\u0915"
    ],
    "name:nld_x_preferred":[
        "Mirik"
    ],
    "name:pol_x_preferred":[
        "Mirik"
    ],
    "name:swe_x_preferred":[
        "Mirik"
    ],
    "name:tam_x_preferred":[
        "\u0bae\u0bbf\u0bb0\u0bbf\u0b95\u0bcd"
    ],
    "name:vie_x_preferred":[
        "Mirik"
    ],
    "name:zho_x_preferred":[
        "\u7c73\u91cc\u514b"
    ],
    "qs:name":"Mirik",
    "qs:photos_9r":0,
    "qs:photos_sr":0,
    "qs:pop_sr":"6",
    "wd:wordcount":1784,
    "wof:name":"Mirik",
    "wof:placetype":"locality",
    "wof:population":10109
},
  "geometry": {"coordinates":[88.19006,26.88817],"type":"Point"}
}