{
  "type": "Feature",
  "properties": {
    "iso:country":"IN",
    "ks:ks_alt_nam":"Alipur Jeeta HATHAG",
    "ks:ks_name":"Alipur Jeeta Hathag",
    "ks:ks_pop":3028,
    "ks:ks_type":"HABITATION",
    "name:eng_x_preferred":[
        "Alipur Jeeta Hathag"
    ],
    "wof:name":"Alipur Jeeta Hathag",
    "wof:placetype":"locality",
    "wof:population":3028
},
  "geometry": {"coordinates":[81.315315,25.772756],"type":"Point"}
}