{
  "type": "Feature",
  "properties": {
    "iso:country":"IN",
    "ks:ks_name":"Ghatlpada",
    "ks:ks_pop":384,
    "ks:ks_type":"HABITATION",
    "name:eng_x_preferred":[
        "Ghatlpada"
    ],
    "wof:name":"Ghatlpada",
    "wof:placetype":"locality",
    "wof:population":384
},
  "geometry": {"coordinates":[73.056282,19.785696],"type":"Point"}
}