{
  "type": "Feature",
  "properties": {
    "iso:country":"IN",
    "ks:ks_name":"Puhundi",
    "ks:ks_pop":1047,
    "ks:ks_type":"VILLAGE",
    "name:eng_x_preferred":[
        "Puhundi"
    ],
    "wof:name":"Puhundi",
    "wof:placetype":"locality",
    "wof:population":1047
},
  "geometry": {"coordinates":[84.43101,19.176955],"type":"Point"}
}