{
  "type": "Feature",
  "properties": {
    "iso:country":"IN",
    "ks:ks_name":"Bojjiguppa",
    "ks:ks_pop":178,
    "ks:ks_type":"VILLAGE",
    "name:eng_x_preferred":[
        "Bojjiguppa"
    ],
    "wof:name":"Bojjiguppa",
    "wof:placetype":"locality",
    "wof:population":178
},
  "geometry": {"coordinates":[80.98765400000001,17.758442],"type":"Point"}
}