{
  "type": "Feature",
  "properties": {
    "iso:country":"IN",
    "ks:ks_name":"Suvar Bhagat Faliya",
    "ks:ks_pop":283,
    "ks:ks_type":"HABITATION",
    "name:eng_x_preferred":[
        "Suvar Bhagat Faliya"
    ],
    "wof:name":"Suvar Bhagat Faliya",
    "wof:placetype":"locality",
    "wof:population":283
},
  "geometry": {"coordinates":[74.230833,23.141778],"type":"Point"}
}