{
  "type": "Feature",
  "properties": {
    "iso:country":"IN",
    "ks:ks_name":"Tilang",
    "ks:ks_pop":47,
    "ks:ks_type":"VILLAGE",
    "name:eng_x_preferred":[
        "Tilang"
    ],
    "wof:name":"Tilang",
    "wof:placetype":"locality",
    "wof:population":47
},
  "geometry": {"coordinates":[87.53673499999999,23.531349],"type":"Point"}
}