{
  "type": "Feature",
  "properties": {
    "iso:country":"IN",
    "ks:ks_name":"Dhodadih",
    "ks:ks_pop":166,
    "ks:ks_type":"HABITATION",
    "name:eng_x_preferred":[
        "Dhodadih"
    ],
    "wof:name":"Dhodadih",
    "wof:placetype":"locality",
    "wof:population":166
},
  "geometry": {"coordinates":[83.980791,22.651671],"type":"Point"}
}