{
  "type": "Feature",
  "properties": {
    "iso:country":"IN",
    "ks:ks_name":"Mulapaida",
    "ks:ks_pop":133,
    "ks:ks_type":"VILLAGE",
    "ks:ks_uagg_main":0,
    "name:eng_x_preferred":[
        "Mulapaida"
    ],
    "wof:name":"Mulapaida",
    "wof:placetype":"neighbourhood",
    "wof:population":133
},
  "geometry": {"coordinates":[86.108107,20.388601],"type":"Point"}
}