{
  "type": "Feature",
  "properties": {
    "gn:admin1_code":"36",
    "gn:admin2_code":"176.0",
    "gn:asciiname":"Patra",
    "gn:country_code":"IN",
    "gn:dem":102,
    "gn:feature_class":"P",
    "gn:feature_code":"PPL",
    "gn:name":"Patra",
    "gn:population":0,
    "gn:timezone":"Asia/Kolkata",
    "iso:country":"IN",
    "ks:ks_name":"Patra",
    "ks:ks_pop":53,
    "ks:ks_type":"VILLAGE",
    "name:ceb_x_preferred":[
        "Patra"
    ],
    "name:eng_x_preferred":[
        "Patra"
    ],
    "name:fra_x_preferred":[
        "Patra"
    ],
    "name:nld_x_preferred":[
        "Patra"
    ],
    "wof:name":"Patra",
    "wof:placetype":"locality",
    "wof:population":53
},
  "geometry": {"coordinates":[81.68691800000001,26.933418],"type":"Point"}
}