{
  "type": "Feature",
  "properties": {
    "gn:admin1_code":"35",
    "gn:admin2_code":"455.0",
    "gn:asciiname":"Markapathar",
    "gn:country_code":"IN",
    "gn:dem":627,
    "gn:feature_class":"P",
    "gn:feature_code":"PPL",
    "gn:name":"Mark\u0101path\u0101r",
    "gn:population":0,
    "gn:timezone":"Asia/Kolkata",
    "iso:country":"IN",
    "ks:ks_name":"Marka Pathar",
    "ks:ks_pop":243,
    "ks:ks_type":"VILLAGE",
    "name:eng_x_preferred":[
        "Marka Pathar"
    ],
    "name:eng_x_variant":[
        "Markapathar"
    ],
    "wof:name":"Marka Pathar",
    "wof:placetype":"locality",
    "wof:population":243
},
  "geometry": {"coordinates":[79.24002,22.705727],"type":"Point"}
}