{
  "type": "Feature",
  "properties": {
    "iso:country":"IN",
    "ks:ks_alt_nam":"Linga FV",
    "ks:ks_name":"Linga Fv",
    "ks:ks_pop":272,
    "ks:ks_type":"HABITATION",
    "name:eng_x_preferred":[
        "Linga Fv"
    ],
    "wof:name":"Linga Fv",
    "wof:placetype":"locality",
    "wof:population":272
},
  "geometry": {"coordinates":[81.02055900000001,22.241395],"type":"Point"}
}