{
  "type": "Feature",
  "properties": {
    "iso:country":"IN",
    "ks:ks_name":"Sirunesalur",
    "ks:ks_pop":1634,
    "ks:ks_type":"VILLAGE",
    "ks:ks_uagg_main":0,
    "name:eng_x_preferred":[
        "Sirunesalur"
    ],
    "wof:name":"Sirunesalur",
    "wof:placetype":"neighbourhood",
    "wof:population":1634
},
  "geometry": {"coordinates":[79.117154,11.524959],"type":"Point"}
}