{
  "type": "Feature",
  "properties": {
    "iso:country":"IN",
    "ks:ks_name":"Purana Khat Chuk",
    "ks:ks_pop":138,
    "ks:ks_type":"HABITATION",
    "name:eng_x_preferred":[
        "Purana Khat Chuk"
    ],
    "wof:name":"Purana Khat Chuk",
    "wof:placetype":"locality",
    "wof:population":138
},
  "geometry": {"coordinates":[95.093017,27.004453],"type":"Point"}
}