{
  "type": "Feature",
  "properties": {
    "gn:admin1_code":"2.0",
    "gn:admin2_code":"554.0",
    "gn:asciiname":"Kondamarri",
    "gn:country_code":"IN",
    "gn:dem":740,
    "gn:feature_class":"P",
    "gn:feature_code":"PPL",
    "gn:name":"Kond\u0101marri",
    "gn:population":0,
    "gn:timezone":"Asia/Kolkata",
    "iso:country":"IN",
    "wof:name":"Kondamarri",
    "wof:placetype":"locality"
},
  "geometry": {"coordinates":[78.66544,13.4439],"type":"Point"}
}