{
  "type": "Feature",
  "properties": {
    "iso:country":"IN",
    "ks:ks_alt_nam":"Nikam wasti",
    "ks:ks_name":"Nikam Wasti",
    "ks:ks_pop":193,
    "ks:ks_type":"HABITATION",
    "name:eng_x_preferred":[
        "Nikam Wasti"
    ],
    "wof:name":"Nikam Wasti",
    "wof:placetype":"locality",
    "wof:population":193
},
  "geometry": {"coordinates":[75.33545599999999,18.015081],"type":"Point"}
}