{
  "type": "Feature",
  "properties": {
    "gn:admin1_code":"12.0",
    "gn:admin2_code":"005",
    "gn:asciiname":"Nerian",
    "gn:country_code":"IN",
    "gn:dem":2138,
    "gn:feature_class":"P",
    "gn:feature_code":"PPL",
    "gn:name":"Nerian",
    "gn:population":0,
    "gn:timezone":"Asia/Kolkata",
    "iso:country":"IN",
    "name:und_x_variant":[
        "Neri\u0101n",
        "Neriyan"
    ],
    "wof:name":"Nerian",
    "wof:placetype":"locality"
},
  "geometry": {"coordinates":[74.23466999999999,33.80567],"type":"Point"}
}