{
  "type": "Feature",
  "properties": {
    "gn:admin1_code":"16",
    "gn:admin2_code":"529.0",
    "gn:asciiname":"Maneri",
    "gn:country_code":"IN",
    "gn:dem":25,
    "gn:feature_class":"P",
    "gn:feature_code":"PPL",
    "gn:name":"Maneri",
    "gn:population":0,
    "gn:timezone":"Asia/Kolkata",
    "iso:country":"IN",
    "ks:ks_name":"Maneri",
    "ks:ks_pop":1801,
    "ks:ks_type":"VILLAGE",
    "name:eng_x_preferred":[
        "Maneri"
    ],
    "wof:name":"Maneri",
    "wof:placetype":"locality",
    "wof:population":1801
},
  "geometry": {"coordinates":[73.953962,15.704635],"type":"Point"}
}