{
  "type": "Feature",
  "properties": {
    "gn:admin1_code":"16",
    "gn:admin2_code":"529.0",
    "gn:asciiname":"Maneri",
    "gn:country_code":"IN",
    "gn:dem":25,
    "gn:feature_class":"P",
    "gn:feature_code":"PPL",
    "gn:name":"Maneri",
    "gn:population":0,
    "gn:timezone":"Asia/Kolkata",
    "iso:country":"IN",
    "wof:name":"Maneri",
    "wof:placetype":"locality"
},
  "geometry": {"coordinates":[73.95396,15.70463],"type":"Point"}
}