{
  "type": "Feature",
  "properties": {
    "gn:admin1_code":"11.0",
    "gn:admin2_code":"31.0",
    "gn:asciiname":"Kair",
    "gn:country_code":"IN",
    "gn:dem":686,
    "gn:feature_class":"P",
    "gn:feature_code":"PPL",
    "gn:name":"Kair",
    "gn:population":0,
    "gn:timezone":"Asia/Kolkata",
    "iso:country":"IN",
    "name:ara_x_preferred":[
        "\u0643\u0627\u064a\u0631"
    ],
    "name:ben_bn_x_preferred":[
        "\u0995\u09be\u0987\u09b0"
    ],
    "name:ben_in_x_preferred":[
        "\u0995\u09be\u0987\u09b0"
    ],
    "name:guj_x_preferred":[
        "\u0a95\u0ac8\u0ab0"
    ],
    "name:hin_x_preferred":[
        "\u0915\u0948\u0930"
    ],
    "name:kan_x_preferred":[
        "\u0c95\u0cc8\u0cb0\u0ccd"
    ],
    "name:mal_x_preferred":[
        "\u0d15\u0d46\u0d2f\u0d7c"
    ],
    "name:mar_x_preferred":[
        "\u0915\u0948\u0930"
    ],
    "name:pan_x_preferred":[
        "\u0a15\u0a48\u0a07\u0a30"
    ],
    "name:tam_x_preferred":[
        "\u0b95\u0bc8\u0bb0\u0bcd"
    ],
    "name:tel_x_preferred":[
        "\u0c15\u0c48\u0c30\u0c47"
    ],
    "name:urd_x_preferred":[
        "\u06a9\u06cc\u0631"
    ],
    "wof:name":"Kair",
    "wof:placetype":"locality"
},
  "geometry": {"coordinates":[77.02942,30.76172],"type":"Point"}
}