{
  "type": "Feature",
  "properties": {
    "iso:country":"IN",
    "ks:ks_name":"Saidpur Khalsa",
    "ks:ks_pop":975,
    "ks:ks_type":"VILLAGE",
    "ks:ks_uagg_main":0,
    "name:eng_x_preferred":[
        "Saidpur Khalsa"
    ],
    "wof:name":"Saidpur Khalsa",
    "wof:placetype":"neighbourhood",
    "wof:population":975
},
  "geometry": {"coordinates":[86.185723,25.366334],"type":"Point"}
}