{
  "type": "Feature",
  "properties": {
    "iso:country":"IN",
    "ks:ks_alt_nam":"Pathu thanda",
    "ks:ks_name":"Pathu Thanda",
    "ks:ks_pop":133,
    "ks:ks_type":"HABITATION",
    "name:eng_x_preferred":[
        "Pathu Thanda"
    ],
    "wof:name":"Pathu Thanda",
    "wof:placetype":"locality",
    "wof:population":133
},
  "geometry": {"coordinates":[79.663978,17.31231],"type":"Point"}
}