{
  "type": "Feature",
  "properties": {
    "gn:admin1_code":"9.0",
    "gn:admin2_code":"488.0",
    "gn:asciiname":"Tralsa",
    "gn:country_code":"IN",
    "gn:dem":17,
    "gn:feature_class":"P",
    "gn:feature_code":"PPL",
    "gn:name":"Tr\u0101lsa",
    "gn:population":0,
    "gn:timezone":"Asia/Kolkata",
    "iso:country":"IN",
    "wof:name":"Tralsa",
    "wof:placetype":"locality"
},
  "geometry": {"coordinates":[72.962,21.80382],"type":"Point"}
}