{
  "type": "Feature",
  "properties": {
    "gn:admin1_code":"30",
    "gn:admin2_code":"253.0",
    "gn:asciiname":"Yedbuk",
    "gn:country_code":"IN",
    "gn:dem":929,
    "gn:feature_class":"P",
    "gn:feature_code":"PPL",
    "gn:name":"Yedbuk",
    "gn:population":0,
    "gn:timezone":"Asia/Kolkata",
    "iso:country":"IN",
    "name:und_x_variant":[
        "Yediuk",
        "Yedbuk"
    ],
    "wof:name":"Yedbuk",
    "wof:placetype":"locality"
},
  "geometry": {"coordinates":[95.93856,27.13076],"type":"Point"}
}