{
  "type": "Feature",
  "properties": {
    "gn:admin1_code":"37.0",
    "gn:admin2_code":"402.0",
    "gn:asciiname":"Manjhat",
    "gn:country_code":"IN",
    "gn:dem":390,
    "gn:feature_class":"P",
    "gn:feature_code":"PPL",
    "gn:name":"Manjhat",
    "gn:population":0,
    "gn:timezone":"Asia/Kolkata",
    "iso:country":"IN",
    "wof:name":"Manjhat",
    "wof:placetype":"locality"
},
  "geometry": {"coordinates":[83.97559,22.54967000000001],"type":"Point"}
}