{
  "type": "Feature",
  "properties": {
    "gn:admin1_code":"16",
    "gn:admin2_code":"511.0",
    "gn:asciiname":"Saephalkhera",
    "gn:country_code":"IN",
    "gn:dem":270,
    "gn:feature_class":"P",
    "gn:feature_code":"PPL",
    "gn:name":"Saephalkhera",
    "gn:population":0,
    "gn:timezone":"Asia/Kolkata",
    "iso:country":"IN",
    "ks:ks_name":"Saephalkhera",
    "ks:ks_type":"VILLAGE",
    "name:eng_x_preferred":[
        "Saephalkhera"
    ],
    "wof:name":"Saephalkhera",
    "wof:placetype":"locality"
},
  "geometry": {"coordinates":[78.041371,19.914665],"type":"Point"}
}