{
  "type": "Feature",
  "properties": {
    "gn:admin1_code":"36",
    "gn:admin2_code":"183.0",
    "gn:asciiname":"Balak Purwa",
    "gn:country_code":"IN",
    "gn:dem":117,
    "gn:feature_class":"P",
    "gn:feature_code":"PPL",
    "gn:name":"B\u0101lak Purwa",
    "gn:population":0,
    "gn:timezone":"Asia/Kolkata",
    "iso:country":"IN",
    "ks:ks_name":"Balapurwa",
    "ks:ks_pop":157,
    "ks:ks_type":"HABITATION",
    "ks:ks_uagg_main":0,
    "name:eng_x_preferred":[
        "Balapurwa"
    ],
    "wof:name":"Balapurwa",
    "wof:placetype":"neighbourhood",
    "wof:population":157
},
  "geometry": {"coordinates":[81.792782,27.240629],"type":"Point"}
}