{
  "type": "Feature",
  "properties": {
    "iso:country":"IN",
    "ks:ks_name":"Tenginamakki",
    "ks:ks_pop":20,
    "ks:ks_type":"HABITATION",
    "name:eng_x_preferred":[
        "Tenginamakki"
    ],
    "wof:name":"Tenginamakki",
    "wof:placetype":"locality",
    "wof:population":20
},
  "geometry": {"coordinates":[74.802142,14.239614],"type":"Point"}
}