{
  "type": "Feature",
  "properties": {
    "gn:admin1_code":"12.0",
    "gn:admin2_code":"12.0",
    "gn:asciiname":"Mirabagh",
    "gn:country_code":"IN",
    "gn:dem":1593,
    "gn:feature_class":"P",
    "gn:feature_code":"PPL",
    "gn:name":"Mirab\u0101gh",
    "gn:population":0,
    "gn:timezone":"Asia/Kolkata",
    "iso:country":"IN",
    "wof:name":"Mirabagh",
    "wof:placetype":"locality"
},
  "geometry": {"coordinates":[74.93805999999999,33.92971],"type":"Point"}
}