{
  "type": "Feature",
  "properties": {
    "iso:country":"IN",
    "ks:ks_name":"Parspada Falia",
    "ks:ks_pop":330,
    "ks:ks_type":"HABITATION",
    "name:eng_x_preferred":[
        "Parspada Falia"
    ],
    "wof:name":"Parspada Falia",
    "wof:placetype":"locality",
    "wof:population":330
},
  "geometry": {"coordinates":[73.285444,20.277917],"type":"Point"}
}