{
  "type": "Feature",
  "properties": {
    "gn:admin1_code":"35.0",
    "gn:admin2_code":"463.0",
    "gn:asciiname":"Kailashpur",
    "gn:country_code":"IN",
    "gn:dem":368,
    "gn:feature_class":"P",
    "gn:feature_code":"PPL",
    "gn:name":"Kail\u0101shpur",
    "gn:population":0,
    "gn:timezone":"Asia/Kolkata",
    "iso:country":"IN",
    "name:bpy_x_preferred":[
        "\u0995\u09c8\u09b2\u09be\u09b8\u09aa\u09c1\u09b0"
    ],
    "name:ita_x_preferred":[
        "Kailashpur"
    ],
    "name:msa_x_preferred":[
        "Kailashpur"
    ],
    "name:new_x_preferred":[
        "\u0915\u0948\u0932\u093e\u0936\u092a\u0941\u0930"
    ],
    "name:nld_x_preferred":[
        "Kailashpur"
    ],
    "name:pol_x_preferred":[
        "Kailashpur"
    ],
    "name:por_x_preferred":[
        "Kailashpur"
    ],
    "name:tam_x_preferred":[
        "\u0b95\u0bc8\u0bb2\u0bbe\u0bb7\u0bcd\u0baa\u0bc2\u0bb0\u0bcd"
    ],
    "name:urd_x_preferred":[
        "\u06a9\u06cc\u0644\u0627\u0634 \u067e\u0648\u0631"
    ],
    "name:vie_x_preferred":[
        "Kailashpur"
    ],
    "name:zho_x_preferred":[
        "\u51ef\u62c9\u65af\u8d6b\u666e\u5c14"
    ],
    "wof:name":"Kailashpur",
    "wof:placetype":"locality"
},
  "geometry": {"coordinates":[82.59329,24.36735],"type":"Point"}
}