{
  "type": "Feature",
  "properties": {
    "gn:admin1_code":"35.0",
    "gn:admin2_code":"463.0",
    "gn:asciiname":"Kailashpur",
    "gn:country_code":"IN",
    "gn:dem":368,
    "gn:feature_class":"P",
    "gn:feature_code":"PPL",
    "gn:name":"Kail\u0101shpur",
    "gn:population":0,
    "gn:timezone":"Asia/Kolkata",
    "iso:country":"IN",
    "wof:name":"Kailashpur",
    "wof:placetype":"locality"
},
  "geometry": {"coordinates":[82.59329,24.36735],"type":"Point"}
}