{
  "type": "Feature",
  "properties": {
    "gn:admin1_code":"36.0",
    "gn:admin2_code":"175.0",
    "gn:asciiname":"Khandesar",
    "gn:country_code":"IN",
    "gn:dem":104,
    "gn:feature_class":"P",
    "gn:feature_code":"PPL",
    "gn:name":"Khandesar",
    "gn:population":0,
    "gn:timezone":"Asia/Kolkata",
    "iso:country":"IN",
    "wof:name":"Khandesar",
    "wof:placetype":"locality"
},
  "geometry": {"coordinates":[81.69029999999999,25.26893],"type":"Point"}
}