{
  "type": "Feature",
  "properties": {
    "gn:admin1_code":"36.0",
    "gn:admin2_code":"149.0",
    "gn:asciiname":"Bhojipura Pawai",
    "gn:country_code":"IN",
    "gn:dem":179,
    "gn:feature_class":"P",
    "gn:feature_code":"PPL",
    "gn:name":"Bhoj\u012bpura P\u0101wai",
    "gn:population":0,
    "gn:timezone":"Asia/Kolkata",
    "iso:country":"IN",
    "wof:name":"Bhojipura Pawai",
    "wof:placetype":"locality"
},
  "geometry": {"coordinates":[78.65926,28.21544],"type":"Point"}
}