{
  "type": "Feature",
  "properties": {
    "gn:admin1_code":"36.0",
    "gn:admin2_code":"133.0",
    "gn:asciiname":"Sadruddinnagar",
    "gn:country_code":"IN",
    "gn:dem":236,
    "gn:feature_class":"P",
    "gn:feature_code":"PPL",
    "gn:name":"Sadrudd\u012bnnagar",
    "gn:population":0,
    "gn:timezone":"Asia/Kolkata",
    "iso:country":"IN",
    "name:und_x_variant":[
        "Sadrudd\u012bnnagar",
        "M\u0101jra"
    ],
    "wof:name":"Sadruddinnagar",
    "wof:placetype":"locality"
},
  "geometry": {"coordinates":[77.51433,29.39278],"type":"Point"}
}