{
  "type": "Feature",
  "properties": {
    "iso:country":"IN",
    "ks:ks_alt_nam":"Palat pada",
    "ks:ks_name":"Palat Pada",
    "ks:ks_pop":56,
    "ks:ks_type":"HABITATION",
    "name:eng_x_preferred":[
        "Palat Pada"
    ],
    "wof:name":"Palat Pada",
    "wof:placetype":"locality",
    "wof:population":56
},
  "geometry": {"coordinates":[73.067229,19.792203],"type":"Point"}
}