{
  "type": "Feature",
  "properties": {
    "gn:admin1_code":"34.0",
    "gn:admin2_code":"219.0",
    "gn:asciiname":"Sarea Ratnagar",
    "gn:country_code":"IN",
    "gn:dem":60,
    "gn:feature_class":"P",
    "gn:feature_code":"PPL",
    "gn:name":"Sarea Ratn\u0101gar",
    "gn:population":0,
    "gn:timezone":"Asia/Kolkata",
    "iso:country":"IN",
    "wof:name":"Sarea Ratnagar",
    "wof:placetype":"locality"
},
  "geometry": {"coordinates":[84.89591,26.01088],"type":"Point"}
}