{
  "type": "Feature",
  "properties": {
    "iso:country":"IN",
    "ks:ks_name":"Gurudaspur",
    "ks:ks_pop":766,
    "ks:ks_type":"VILLAGE",
    "ks:ks_uagg_main":0,
    "name:eng_x_preferred":[
        "Gurudaspur"
    ],
    "wof:name":"Gurudaspur",
    "wof:placetype":"neighbourhood",
    "wof:population":766
},
  "geometry": {"coordinates":[87.209864,21.845944],"type":"Point"}
}