{
  "type": "Feature",
  "properties": {
    "iso:country":"IN",
    "ks:ks_name":"Barda",
    "ks:ks_pop":4484,
    "ks:ks_type":"VILLAGE",
    "name:eng_x_preferred":[
        "Barda"
    ],
    "wof:name":"Barda",
    "wof:placetype":"locality",
    "wof:population":4484
},
  "geometry": {"coordinates":[88.09978700000001,22.150619],"type":"Point"}
}