{
  "type": "Feature",
  "properties": {
    "gn:admin1_code":"12.0",
    "gn:admin2_code":"21.0",
    "gn:asciiname":"Samani",
    "gn:country_code":"IN",
    "gn:dem":493,
    "gn:feature_class":"P",
    "gn:feature_code":"PPL",
    "gn:name":"Sam\u0101ni",
    "gn:population":0,
    "gn:timezone":"Asia/Kolkata",
    "iso:country":"IN",
    "name:aze_x_preferred":[
        "S\u0259m\u0259ni"
    ],
    "name:kat_x_preferred":[
        "\u10e1\u10d4\u10db\u10d4\u10dc\u10d8"
    ],
    "name:rus_x_preferred":[
        "\u0421\u044d\u043c\u044d\u043d\u0438"
    ],
    "name:tur_x_preferred":[
        "Semeni"
    ],
    "wof:name":"Samani",
    "wof:placetype":"locality"
},
  "geometry": {"coordinates":[75.02614,32.7414],"type":"Point"}
}