{
  "type": "Feature",
  "properties": {
    "gn:admin1_code":"11.0",
    "gn:admin2_code":"027",
    "gn:asciiname":"Aiju",
    "gn:country_code":"IN",
    "gn:dem":1286,
    "gn:feature_class":"P",
    "gn:feature_code":"PPL",
    "gn:name":"Aiju",
    "gn:population":0,
    "gn:timezone":"Asia/Kolkata",
    "iso:country":"IN",
    "wof:name":"Aiju",
    "wof:placetype":"locality"
},
  "geometry": {"coordinates":[76.70419,32.02388],"type":"Point"}
}