{
  "type": "Feature",
  "properties": {
    "iso:country":"IN",
    "ks:ks_alt_nam":"ISHANPUR",
    "ks:ks_name":"Ishanpur",
    "ks:ks_pop":646,
    "ks:ks_type":"HABITATION",
    "ks:ks_uagg_main":0,
    "name:eng_x_preferred":[
        "Ishanpur"
    ],
    "wof:name":"Ishanpur",
    "wof:placetype":"neighbourhood",
    "wof:population":646
},
  "geometry": {"coordinates":[91.40172800000001,24.052543],"type":"Point"}
}