{
  "type": "Feature",
  "properties": {
    "iso:country":"IN",
    "ks:ks_name":"Raharia",
    "ks:ks_pop":741,
    "ks:ks_type":"VILLAGE",
    "name:eng_x_preferred":[
        "Raharia"
    ],
    "wof:name":"Raharia",
    "wof:placetype":"locality",
    "wof:population":741
},
  "geometry": {"coordinates":[86.666939,26.316056],"type":"Point"}
}