{
  "type": "Feature",
  "properties": {
    "gn:admin1_code":"12.0",
    "gn:admin2_code":"6.0",
    "gn:asciiname":"Bal",
    "gn:country_code":"IN",
    "gn:dem":868,
    "gn:feature_class":"P",
    "gn:feature_code":"PPL",
    "gn:name":"Bal",
    "gn:population":0,
    "gn:timezone":"Asia/Kolkata",
    "iso:country":"IN",
    "name:aze_x_preferred":[
        "Bal"
    ],
    "name:ceb_x_preferred":[
        "Bal"
    ],
    "name:fra_x_preferred":[
        "Bal"
    ],
    "name:nld_x_preferred":[
        "Bal"
    ],
    "name:pol_x_preferred":[
        "Bal"
    ],
    "name:rus_x_preferred":[
        "\u0411\u0430\u043b\u044c"
    ],
    "name:swe_x_preferred":[
        "Bal"
    ],
    "name:ukr_x_preferred":[
        "\u0411\u0430\u043b\u044c"
    ],
    "wof:name":"Bal",
    "wof:placetype":"locality"
},
  "geometry": {"coordinates":[74.36227,33.30299],"type":"Point"}
}