{
  "type": "Feature",
  "properties": {
    "iso:country":"IN",
    "ks:ks_name":"Pochapani",
    "ks:ks_pop":219,
    "ks:ks_type":"VILLAGE",
    "name:eng_x_preferred":[
        "Pochapani"
    ],
    "wof:name":"Pochapani",
    "wof:placetype":"locality",
    "wof:population":219
},
  "geometry": {"coordinates":[86.694326,22.575743],"type":"Point"}
}