{
  "type": "Feature",
  "properties": {
    "iso:country":"IN",
    "ks:ks_name":"Harmara Ki Rel",
    "ks:ks_pop":749,
    "ks:ks_type":"VILLAGE",
    "name:eng_x_preferred":[
        "Harmara Ki Rel"
    ],
    "wof:name":"Harmara Ki Rel",
    "wof:placetype":"locality",
    "wof:population":749
},
  "geometry": {"coordinates":[74.629475,24.227194],"type":"Point"}
}