{
  "type": "Feature",
  "properties": {
    "iso:country":"IN",
    "ks:ks_name":"Vangaram",
    "ks:ks_pop":520,
    "ks:ks_type":"HABITATION",
    "name:eng_x_preferred":[
        "Vangaram"
    ],
    "wof:name":"Vangaram",
    "wof:placetype":"locality",
    "wof:population":520
},
  "geometry": {"coordinates":[79.697075,10.727725],"type":"Point"}
}