{
  "type": "Feature",
  "properties": {
    "iso:country":"IN",
    "ks:ks_name":"Lagdipur",
    "ks:ks_pop":397,
    "ks:ks_type":"VILLAGE",
    "name:eng_x_preferred":[
        "Lagdipur"
    ],
    "wof:name":"Lagdipur",
    "wof:placetype":"locality",
    "wof:population":397
},
  "geometry": {"coordinates":[80.867126,28.105902],"type":"Point"}
}