{
  "type": "Feature",
  "properties": {
    "gn:admin1_code":"2",
    "gn:admin2_code":"545.0",
    "gn:asciiname":"Chemagadda",
    "gn:country_code":"IN",
    "gn:dem":320,
    "gn:feature_class":"P",
    "gn:feature_code":"PPL",
    "gn:name":"Chemagadda",
    "gn:population":0,
    "gn:timezone":"Asia/Kolkata",
    "iso:country":"IN",
    "ks:ks_name":"Chamagedda",
    "ks:ks_pop":76,
    "ks:ks_type":"HABITATION",
    "name:eng_x_preferred":[
        "Chamagedda"
    ],
    "name:eng_x_variant":[
        "Chemagadda"
    ],
    "wof:name":"Chamagedda",
    "wof:placetype":"locality",
    "wof:population":76
},
  "geometry": {"coordinates":[81.98407,17.67755],"type":"Point"}
}