{
  "type": "Feature",
  "properties": {
    "gn:admin1_code":"39.0",
    "gn:admin2_code":"64.0",
    "gn:asciiname":"Toli",
    "gn:country_code":"IN",
    "gn:dem":1774,
    "gn:feature_class":"P",
    "gn:feature_code":"PPL",
    "gn:name":"Toli",
    "gn:population":0,
    "gn:timezone":"Asia/Kolkata",
    "iso:country":"IN",
    "name:ceb_x_preferred":[
        "Toli"
    ],
    "name:deu_x_preferred":[
        "Toli"
    ],
    "name:fra_x_preferred":[
        "Toli"
    ],
    "name:swe_x_preferred":[
        "Toli"
    ],
    "wof:name":"Toli",
    "wof:placetype":"locality"
},
  "geometry": {"coordinates":[79.72934000000002,29.56361],"type":"Point"}
}