{
  "type": "Feature",
  "properties": {
    "iso:country":"IN",
    "ks:ks_name":"Phulopani",
    "ks:ks_pop":173,
    "ks:ks_type":"VILLAGE",
    "name:eng_x_preferred":[
        "Phulopani"
    ],
    "wof:name":"Phulopani",
    "wof:placetype":"locality",
    "wof:population":173
},
  "geometry": {"coordinates":[87.25603,24.335937],"type":"Point"}
}