{
  "type": "Feature",
  "properties": {
    "gn:admin1_code":"16.0",
    "gn:admin2_code":"508.0",
    "gn:asciiname":"Handpaili",
    "gn:country_code":"IN",
    "gn:dem":316,
    "gn:feature_class":"P",
    "gn:feature_code":"PPL",
    "gn:name":"Handpaili",
    "gn:population":0,
    "gn:timezone":"Asia/Kolkata",
    "iso:country":"IN",
    "wof:name":"Handpaili",
    "wof:placetype":"locality"
},
  "geometry": {"coordinates":[80.40953,19.9693],"type":"Point"}
}