{
  "type": "Feature",
  "properties": {
    "gn:admin1_code":"16.0",
    "gn:admin2_code":"508.0",
    "gn:asciiname":"Handpaili",
    "gn:country_code":"IN",
    "gn:dem":316,
    "gn:feature_class":"P",
    "gn:feature_code":"PPL",
    "gn:name":"Handpaili",
    "gn:population":0,
    "gn:timezone":"Asia/Kolkata",
    "iso:country":"IN",
    "ks:ks_name":"Hanapaili",
    "ks:ks_pop":85,
    "ks:ks_type":"VILLAGE",
    "name:eng_x_preferred":[
        "Hanapaili"
    ],
    "name:eng_x_variant":[
        "Handpaili"
    ],
    "wof:name":"Hanapaili",
    "wof:placetype":"locality",
    "wof:population":85
},
  "geometry": {"coordinates":[80.409581,19.969224],"type":"Point"}
}