{
  "type": "Feature",
  "properties": {
    "gn:admin1_code":"36.0",
    "gn:admin2_code":"134.0",
    "gn:asciiname":"Madhaura",
    "gn:country_code":"IN",
    "gn:dem":240,
    "gn:feature_class":"P",
    "gn:feature_code":"PPL",
    "gn:name":"Madhaura",
    "gn:population":0,
    "gn:timezone":"Asia/Kolkata",
    "iso:country":"IN",
    "name:und_x_variant":[
        "Sh\u0101h \u0100l\u012bpur Nechal"
    ],
    "wof:name":"Madhaura",
    "wof:placetype":"locality"
},
  "geometry": {"coordinates":[78.53525,29.37689],"type":"Point"}
}