{
  "type": "Feature",
  "properties": {
    "gn:admin1_code":"10.0",
    "gn:admin2_code":"79.0",
    "gn:asciiname":"Rindhawa",
    "gn:country_code":"IN",
    "gn:dem":205,
    "gn:feature_class":"P",
    "gn:feature_code":"PPL",
    "gn:name":"Rindh\u0101wa",
    "gn:population":0,
    "gn:timezone":"Asia/Kolkata",
    "iso:country":"IN",
    "wof:name":"Rindhawa",
    "wof:placetype":"locality"
},
  "geometry": {"coordinates":[75.07080999999999,29.41938],"type":"Point"}
}