{
  "type": "Feature",
  "properties": {
    "gn:admin1_code":"36.0",
    "gn:admin2_code":"133.0",
    "gn:asciiname":"Khanjahanpur",
    "gn:country_code":"IN",
    "gn:dem":240,
    "gn:feature_class":"P",
    "gn:feature_code":"PPL",
    "gn:name":"Kh\u0101njah\u0101npur",
    "gn:population":0,
    "gn:timezone":"Asia/Kolkata",
    "iso:country":"IN",
    "wof:name":"Khanjahanpur",
    "wof:placetype":"locality"
},
  "geometry": {"coordinates":[77.77034,29.30465],"type":"Point"}
}