{
  "type": "Feature",
  "properties": {
    "iso:country":"IN",
    "ks:ks_name":"Nilabash",
    "ks:ks_pop":605,
    "ks:ks_type":"HABITATION",
    "name:eng_x_preferred":[
        "Nilabash"
    ],
    "wof:name":"Nilabash",
    "wof:placetype":"locality",
    "wof:population":605
},
  "geometry": {"coordinates":[88.890362,23.182424],"type":"Point"}
}