{
  "type": "Feature",
  "properties": {
    "iso:country":"IN",
    "ks:ks_name":"Peepripura",
    "ks:ks_pop":879,
    "ks:ks_type":"HABITATION",
    "name:eng_x_preferred":[
        "Peepripura"
    ],
    "wof:name":"Peepripura",
    "wof:placetype":"locality",
    "wof:population":879
},
  "geometry": {"coordinates":[77.616381,26.748181],"type":"Point"}
}