{
  "type": "Feature",
  "properties": {
    "gn:admin1_code":"34.0",
    "gn:admin2_code":"203.0",
    "gn:asciiname":"Bairatwa",
    "gn:country_code":"IN",
    "gn:dem":104,
    "gn:feature_class":"P",
    "gn:feature_code":"PPL",
    "gn:name":"Bairatwa",
    "gn:population":0,
    "gn:timezone":"Asia/Kolkata",
    "iso:country":"IN",
    "ks:ks_name":"Bairatwa",
    "ks:ks_pop":639,
    "ks:ks_type":"VILLAGE",
    "name:eng_x_preferred":[
        "Bairatwa"
    ],
    "wof:name":"Bairatwa",
    "wof:placetype":"locality",
    "wof:population":639
},
  "geometry": {"coordinates":[84.497398,27.236981],"type":"Point"}
}