{
  "type": "Feature",
  "properties": {
    "gn:admin1_code":"28.0",
    "gn:admin2_code":"334.0",
    "gn:asciiname":"Chaiti",
    "gn:country_code":"IN",
    "gn:dem":41,
    "gn:feature_class":"P",
    "gn:feature_code":"PPL",
    "gn:name":"Chaiti",
    "gn:population":0,
    "gn:timezone":"Asia/Kolkata",
    "iso:country":"IN",
    "ks:ks_name":"Chauti",
    "ks:ks_pop":1458,
    "ks:ks_type":"VILLAGE",
    "ks:ks_uagg_main":0,
    "name:bih_x_preferred":[
        "\u091a\u0948\u0924\u0940"
    ],
    "name:eng_x_preferred":[
        "Chauti"
    ],
    "name:hin_x_preferred":[
        "\u091a\u0948\u0924\u0940"
    ],
    "name:urd_x_preferred":[
        "\u0686\u06cc\u062a\u06cc"
    ],
    "wof:name":"Chauti",
    "wof:placetype":"neighbourhood",
    "wof:population":1458
},
  "geometry": {"coordinates":[87.90619700000001,24.361597],"type":"Point"}
}