{
  "type": "Feature",
  "properties": {
    "gn:admin1_code":"36",
    "gn:admin2_code":"194.0",
    "gn:asciiname":"Patkhauli Alamganj",
    "gn:country_code":"IN",
    "gn:dem":91,
    "gn:feature_class":"P",
    "gn:feature_code":"PPL",
    "gn:name":"Patkhauli \u0100lamganj",
    "gn:population":0,
    "gn:timezone":"Asia/Kolkata",
    "iso:country":"IN",
    "wof:name":"Patkhauli Alamganj",
    "wof:placetype":"locality"
},
  "geometry": {"coordinates":[82.50248000000001,25.54191],"type":"Point"}
}