{
  "type": "Feature",
  "properties": {
    "gn:admin1_code":"11",
    "gn:asciiname":"Banoi",
    "gn:country_code":"IN",
    "gn:dem":740,
    "gn:feature_class":"P",
    "gn:feature_code":"PPL",
    "gn:name":"Banoi",
    "gn:population":0,
    "gn:timezone":"Asia/Kolkata",
    "iso:country":"IN",
    "ks:ks_name":"Banoi",
    "ks:ks_type":"VILLAGE",
    "name:eng_x_preferred":[
        "Banoi"
    ],
    "wof:name":"Banoi",
    "wof:placetype":"locality"
},
  "geometry": {"coordinates":[76.915232,30.888691],"type":"Point"}
}