{
  "type": "Feature",
  "properties": {
    "gn:admin1_code":"39.0",
    "gn:admin2_code":"67.0",
    "gn:asciiname":"Rangrhonwala",
    "gn:country_code":"IN",
    "gn:dem":238,
    "gn:feature_class":"P",
    "gn:feature_code":"PPL",
    "gn:name":"R\u0101ngrhonw\u0101la",
    "gn:population":0,
    "gn:timezone":"Asia/Kolkata",
    "iso:country":"IN",
    "name:und_x_variant":[
        "R\u0101ngrhonw\u0101la",
        "Mazra Bhaj\u016b"
    ],
    "wof:name":"Rangrhonwala",
    "wof:placetype":"locality"
},
  "geometry": {"coordinates":[79.11688000000002,29.19787],"type":"Point"}
}