{
  "type": "Feature",
  "properties": {
    "iso:country":"IN",
    "ks:ks_alt_nam":"Gosai Gadhowa Pt-I",
    "ks:ks_name":"Gosai Gadhowa Pt-i",
    "ks:ks_pop":650,
    "ks:ks_type":"HABITATION",
    "name:eng_x_preferred":[
        "Gosai Gadhowa Pt-i"
    ],
    "wof:name":"Gosai Gadhowa Pt-i",
    "wof:placetype":"locality",
    "wof:population":650
},
  "geometry": {"coordinates":[90.487048,26.041317],"type":"Point"}
}