{
  "type": "Feature",
  "properties": {
    "iso:country":"IN",
    "ks:ks_name":"Gamhariya",
    "ks:ks_pop":260,
    "ks:ks_type":"HABITATION",
    "name:eng_x_preferred":[
        "Gamhariya"
    ],
    "wof:name":"Gamhariya",
    "wof:placetype":"locality",
    "wof:population":260
},
  "geometry": {"coordinates":[84.409933,24.611491],"type":"Point"}
}