{
  "type": "Feature",
  "properties": {
    "iso:country":"IN",
    "ks:ks_name":"Keshav Ka Bas",
    "ks:ks_pop":160,
    "ks:ks_type":"VILLAGE",
    "name:eng_x_preferred":[
        "Keshav Ka Bas"
    ],
    "wof:name":"Keshav Ka Bas",
    "wof:placetype":"locality",
    "wof:population":160
},
  "geometry": {"coordinates":[75.212414,27.195789],"type":"Point"}
}