{
  "type": "Feature",
  "properties": {
    "gn:admin1_code":"40.0",
    "gn:admin2_code":"535.0",
    "gn:asciiname":"Kazipet",
    "gn:country_code":"IN",
    "gn:dem":527,
    "gn:feature_class":"P",
    "gn:feature_code":"PPL",
    "gn:name":"K\u0101z\u012bpet",
    "gn:population":0,
    "gn:timezone":"Asia/Kolkata",
    "iso:country":"IN",
    "name:por_x_preferred":[
        "Kazipet"
    ],
    "wof:name":"Kazipet",
    "wof:placetype":"locality"
},
  "geometry": {"coordinates":[78.27388000000001,17.81837],"type":"Point"}
}