{
  "type": "Feature",
  "properties": {
    "gn:admin1_code":"37",
    "gn:admin2_code":"412.0",
    "gn:asciiname":"Birampur",
    "gn:country_code":"IN",
    "gn:dem":445,
    "gn:feature_class":"P",
    "gn:feature_code":"PPL",
    "gn:name":"B\u012brampur",
    "gn:population":0,
    "gn:timezone":"Asia/Kolkata",
    "iso:country":"IN",
    "ks:ks_name":"Biranpur",
    "ks:ks_pop":374,
    "ks:ks_type":"VILLAGE",
    "name:eng_x_preferred":[
        "Biranpur"
    ],
    "name:eng_x_variant":[
        "Birampur"
    ],
    "wof:name":"Biranpur",
    "wof:placetype":"locality",
    "wof:population":374
},
  "geometry": {"coordinates":[81.946692,20.329325],"type":"Point"}
}