{
  "type": "Feature",
  "properties": {
    "gn:admin1_code":"36",
    "gn:admin2_code":"158.0",
    "gn:asciiname":"Gayadin Singh",
    "gn:country_code":"IN",
    "gn:dem":115,
    "gn:feature_class":"P",
    "gn:feature_code":"PPL",
    "gn:name":"Gay\u0101d\u012bn Singh",
    "gn:population":0,
    "gn:timezone":"Asia/Kolkata",
    "iso:country":"IN",
    "wof:name":"Gayadin Singh",
    "wof:placetype":"locality"
},
  "geometry": {"coordinates":[81.53204000000002,26.17776],"type":"Point"}
}