{
  "type": "Feature",
  "properties": {
    "iso:country":"IN",
    "name:ara_x_preferred":[
        "\u0645\u0627\u0646\u062c\u0644\u0627\u062c\u064a\u0631\u064a"
    ],
    "name:ben_bn_x_preferred":[
        "\u09ae\u0999\u09cd\u0997\u09b2\u09be\u0997\u09bf\u09b0\u09bf"
    ],
    "name:ben_in_x_preferred":[
        "\u09ae\u0999\u09cd\u0997\u09b2\u09be\u0997\u09bf\u09b0\u09bf"
    ],
    "name:bpy_x_preferred":[
        "\u09ae\u0999\u09cd\u0997\u09b2\u09be\u0997\u09bf\u09b0\u09bf"
    ],
    "name:bul_x_preferred":[
        "\u041c\u0430\u043d\u0433\u0430\u043b\u0430\u0433\u0438\u0440\u0438"
    ],
    "name:ceb_x_preferred":[
        "Mangalagiri"
    ],
    "name:eng_x_preferred":[
        "Mangalagiri"
    ],
    "name:fra_x_preferred":[
        "Mangalagiri"
    ],
    "name:guj_x_preferred":[
        "\u0aae\u0a82\u0a97\u0ab2\u0a97\u0ac0\u0ab0\u0ac0"
    ],
    "name:hin_x_preferred":[
        "\u092e\u0902\u0917\u0932\u0917\u093f\u0930\u0940"
    ],
    "name:hin_x_variant":[
        "\u092e\u0902\u0917\u0932\u0917\u093f\u0930\u093f",
        "\u092e\u0902\u0917\u0932\u093e\u0917\u093f\u0930\u0940"
    ],
    "name:ita_x_preferred":[
        "Mangalagiri"
    ],
    "name:kan_x_preferred":[
        "\u0cae\u0c82\u0c97\u0cb3\u0c97\u0cbf\u0cb0\u0cbf"
    ],
    "name:mal_x_preferred":[
        "\u0d2e\u0d02\u0d17\u0d32\u0d17\u0d3f\u0d30\u0d3f"
    ],
    "name:mar_x_preferred":[
        "\u092e\u0902\u0917\u0932\u093e\u0917\u093f\u0930\u0940"
    ],
    "name:mlg_x_preferred":[
        "Mangalagiri"
    ],
    "name:msa_x_preferred":[
        "Mangalagiri"
    ],
    "name:new_x_preferred":[
        "\u092e\u0902\u0917\u0932\u0917\u093f\u0930\u0940"
    ],
    "name:nld_x_preferred":[
        "Mangalagiri"
    ],
    "name:pam_x_preferred":[
        "Mangalagiri"
    ],
    "name:pan_x_preferred":[
        "\u0a2e\u0a70\u0a17\u0a32\u0a3e\u0a17\u0a3f\u0a30\u0a40"
    ],
    "name:ron_x_preferred":[
        "Mangalagiri"
    ],
    "name:san_x_preferred":[
        "\u092e\u0928\u094d\u0917\u0932\u0917\u093f\u0930\u093f"
    ],
    "name:swe_x_preferred":[
        "Mangalagiri"
    ],
    "name:tam_x_preferred":[
        "\u0bae\u0b99\u0bcd\u0b95\u0bb3\u0b95\u0bbf\u0bb0\u0bbf"
    ],
    "name:tel_x_preferred":[
        "\u0c2e\u0c02\u0c17\u0c33\u0c17\u0c3f\u0c30\u0c3f"
    ],
    "name:urd_x_preferred":[
        "\u0645\u0646\u06af\u0644\u0627\u06af\u06cc\u0631\u06cc"
    ],
    "name:urd_x_variant":[
        "\u0645\u0646\u06af\u0644\u0627 \u06af\u06cc\u0631\u06cc"
    ],
    "name:vie_x_preferred":[
        "Mangalagiri"
    ],
    "name:zho_x_preferred":[
        "\u8292\u683c\u963f\u62c9\u5409\u91cc"
    ],
    "qs:name":"Mangalagiri",
    "qs:name_adm0":"India",
    "qs:name_adm1":"Andhra Pradesh",
    "qs:photos":1,
    "qs:photos_1k":1,
    "qs:photos_9k":1,
    "qs:photos_9r":1,
    "qs:photos_all":1,
    "qs:photos_sr":1,
    "qs:placetype":"Suburb",
    "qs:pop_sr":"0",
    "wd:wordcount":1368,
    "wof:name":"Mangalagiri",
    "wof:placetype":"neighbourhood"
},
  "geometry": {"coordinates":[80.63793099999999,16.511478],"type":"Point"}
}