{
  "type": "Feature",
  "properties": {
    "iso:country":"IN",
    "qs:name":"Mangalagiri",
    "qs:name_adm0":"India",
    "qs:name_adm1":"Andhra Pradesh",
    "qs:photos":1,
    "qs:photos_1k":1,
    "qs:photos_9k":1,
    "qs:photos_9r":1,
    "qs:photos_all":1,
    "qs:photos_sr":1,
    "qs:placetype":"Suburb",
    "qs:pop_sr":"0",
    "wd:wordcount":1368,
    "wof:name":"Mangalagiri",
    "wof:placetype":"neighbourhood"
},
  "geometry": {"coordinates":[80.63793099999999,16.511478],"type":"Point"}
}