{
  "type": "Feature",
  "properties": {
    "iso:country":"IN",
    "name:bpy_x_preferred":[
        "\u09ae\u0999\u09cd\u0997\u09b2\u09be\u0997\u09bf\u09b0\u09bf"
    ],
    "name:bul_x_preferred":[
        "\u041c\u0430\u043d\u0433\u0430\u043b\u0430\u0433\u0438\u0440\u0438"
    ],
    "name:ceb_x_preferred":[
        "Mangalagiri"
    ],
    "name:eng_x_preferred":[
        "Mangalagiri"
    ],
    "name:fra_x_preferred":[
        "Mangalagiri"
    ],
    "name:hin_x_preferred":[
        "\u092e\u0902\u0917\u0932\u0917\u093f\u0930\u093f"
    ],
    "name:ita_x_preferred":[
        "Mangalagiri"
    ],
    "name:mlg_x_preferred":[
        "Mangalagiri"
    ],
    "name:msa_x_preferred":[
        "Mangalagiri"
    ],
    "name:new_x_preferred":[
        "\u092e\u0902\u0917\u0932\u0917\u093f\u0930\u0940"
    ],
    "name:nld_x_preferred":[
        "Mangalagiri"
    ],
    "name:pam_x_preferred":[
        "Mangalagiri"
    ],
    "name:ron_x_preferred":[
        "Mangalagiri"
    ],
    "name:san_x_preferred":[
        "\u092e\u0928\u094d\u0917\u0932\u0917\u093f\u0930\u093f"
    ],
    "name:swe_x_preferred":[
        "Mangalagiri"
    ],
    "name:tam_x_preferred":[
        "\u0bae\u0b99\u0bcd\u0b95\u0bb3\u0b95\u0bbf\u0bb0\u0bbf"
    ],
    "name:tel_x_preferred":[
        "\u0c2e\u0c02\u0c17\u0c33\u0c17\u0c3f\u0c30\u0c3f"
    ],
    "name:urd_x_preferred":[
        "\u0645\u0646\u06af\u0644\u0627\u06af\u06cc\u0631\u06cc"
    ],
    "name:vie_x_preferred":[
        "Mangalagiri"
    ],
    "name:zho_x_preferred":[
        "\u8292\u683c\u963f\u62c9\u5409\u91cc"
    ],
    "qs:name":"Mangalagiri",
    "qs:name_adm0":"India",
    "qs:name_adm1":"Andhra Pradesh",
    "qs:photos":1,
    "qs:photos_1k":1,
    "qs:photos_9k":1,
    "qs:photos_9r":1,
    "qs:photos_all":1,
    "qs:photos_sr":1,
    "qs:placetype":"Suburb",
    "qs:pop_sr":"0",
    "wd:wordcount":1368,
    "wof:name":"Mangalagiri",
    "wof:placetype":"neighbourhood"
},
  "geometry": {"coordinates":[80.63793099999999,16.511478],"type":"Point"}
}