{
  "type": "Feature",
  "properties": {
    "gn:country":"IN",
    "gn:fcode":"PPL",
    "gn:pop":19281,
    "iso:country":"IN",
    "name:ben_x_preferred":[
        "\u09a7\u09be\u09a8\u09be\u0989\u09b2\u09be"
    ],
    "name:bpy_x_preferred":[
        "\u09a7\u09be\u09a8\u09be\u0989\u09b2\u09be"
    ],
    "name:bul_x_preferred":[
        "\u0414\u0445\u0430\u043d\u0430\u0443\u043b\u0430"
    ],
    "name:chi_x_preferred":[
        "\u8fbe\u7459\u62c9"
    ],
    "name:dut_x_preferred":[
        "Dhanaula"
    ],
    "name:eng_x_preferred":[
        "Dhanaula"
    ],
    "name:ita_x_preferred":[
        "Dhanaula"
    ],
    "name:may_x_preferred":[
        "Dhanaula"
    ],
    "name:mlg_x_preferred":[
        "Dhanaula"
    ],
    "name:nan_x_preferred":[
        "Dhanaula"
    ],
    "name:new_x_preferred":[
        "\u0927\u0928\u094c\u0932\u093e"
    ],
    "name:pan_x_preferred":[
        "\u0a27\u0a28\u0a4c\u0a32\u0a3e"
    ],
    "name:spa_x_preferred":[
        "Dhanaula"
    ],
    "name:swe_x_preferred":[
        "Dhanaula"
    ],
    "name:unk_x_variant":[
        "Dhanaula"
    ],
    "name:vie_x_preferred":[
        "Dhanaula"
    ],
    "qs:name":"Dhaula",
    "qs:name_adm0":"India",
    "qs:name_adm1":"Punjab",
    "qs:photos_9r":0,
    "qs:photos_sr":0,
    "qs:placetype":"Town",
    "qs:pop_sr":"6",
    "wd:elevation":1500.0,
    "wd:wordcount":37,
    "wof:name":"Dhaula",
    "wof:placetype":"locality",
    "wof:population":19281
},
  "geometry": {"coordinates":[75.57454,30.28288],"type":"Point"}
}