{
  "type": "Feature",
  "properties": {
    "iso:country":"IN",
    "ks:ks_alt_nam":"Dhum\u0101dih",
    "ks:ks_name":"Dhumadih",
    "ks:ks_pop":240,
    "ks:ks_type":"VILLAGE",
    "name:eng_x_preferred":[
        "Dhumadih"
    ],
    "name:eng_x_variant":[
        "Dhum\u0101dih"
    ],
    "wof:name":"Dhumadih",
    "wof:placetype":"locality",
    "wof:population":240
},
  "geometry": {"coordinates":[86.370583,24.2988],"type":"Point"}
}