{
  "type": "Feature",
  "properties": {
    "iso:country":"IN",
    "ks:ks_alt_nam":"PIPRA TOLA",
    "ks:ks_name":"Pipra Tola",
    "ks:ks_pop":738,
    "ks:ks_type":"HABITATION",
    "name:eng_x_preferred":[
        "Pipra Tola"
    ],
    "wof:name":"Pipra Tola",
    "wof:placetype":"locality",
    "wof:population":738
},
  "geometry": {"coordinates":[85.362199,24.106626],"type":"Point"}
}