{
  "type": "Feature",
  "properties": {
    "gn:admin1_code":"25.0",
    "gn:admin2_code":"621",
    "gn:asciiname":"Ammapattinam",
    "gn:country_code":"IN",
    "gn:dem":7,
    "gn:feature_class":"P",
    "gn:feature_code":"PPL",
    "gn:name":"Amm\u0101pattinam",
    "gn:population":0,
    "gn:timezone":"Asia/Kolkata",
    "iso:country":"IN",
    "name:und_x_variant":[
        "Ammapatam",
        "Amm\u0101patnam",
        "Amm\u0101pattinam"
    ],
    "wof:name":"Ammapattinam",
    "wof:placetype":"locality"
},
  "geometry": {"coordinates":[79.23137,10.01534],"type":"Point"}
}