{
  "type": "Feature",
  "properties": {
    "iso:country":"IN",
    "ks:ks_name":"Kothiya",
    "ks:ks_pop":621,
    "ks:ks_type":"VILLAGE",
    "name:eng_x_preferred":[
        "Kothiya"
    ],
    "wof:name":"Kothiya",
    "wof:placetype":"locality",
    "wof:population":621
},
  "geometry": {"coordinates":[81.322176,23.97107],"type":"Point"}
}