{
  "type": "Feature",
  "properties": {
    "iso:country":"IN",
    "ks:ks_name":"Karpallam",
    "ks:ks_pop":161,
    "ks:ks_type":"HABITATION",
    "name:eng_x_preferred":[
        "Karpallam"
    ],
    "wof:name":"Karpallam",
    "wof:placetype":"locality",
    "wof:population":161
},
  "geometry": {"coordinates":[79.744479,11.303962],"type":"Point"}
}