{
  "type": "Feature",
  "properties": {
    "iso:country":"IN",
    "ks:ks_name":"Turtipur",
    "ks:ks_type":"VILLAGE",
    "name:eng_x_preferred":[
        "Turtipur"
    ],
    "wof:name":"Turtipur",
    "wof:placetype":"locality"
},
  "geometry": {"coordinates":[78.369495,28.586279],"type":"Point"}
}