{
  "type": "Feature",
  "properties": {
    "gn:admin1_code":"25.0",
    "gn:admin2_code":"611.0",
    "gn:asciiname":"Kudimalmund",
    "gn:country_code":"IN",
    "gn:dem":2160,
    "gn:feature_class":"P",
    "gn:feature_code":"PPL",
    "gn:name":"Kudimalmund",
    "gn:population":0,
    "gn:timezone":"Asia/Kolkata",
    "iso:country":"IN",
    "wof:name":"Kudimalmund",
    "wof:placetype":"locality"
},
  "geometry": {"coordinates":[76.58325000000001,11.45121],"type":"Point"}
}