{
  "type": "Feature",
  "properties": {
    "gn:admin1_code":"39.0",
    "gn:admin2_code":"64.0",
    "gn:asciiname":"Badi Fatehpur",
    "gn:country_code":"IN",
    "gn:dem":1158,
    "gn:feature_class":"P",
    "gn:feature_code":"PPL",
    "gn:name":"B\u0101di Fatehpur",
    "gn:population":0,
    "gn:timezone":"Asia/Kolkata",
    "iso:country":"IN",
    "wof:name":"Badi Fatehpur",
    "wof:placetype":"locality"
},
  "geometry": {"coordinates":[79.63034,29.64614000000001],"type":"Point"}
}