{
  "type": "Feature",
  "properties": {
    "iso:country":"IN",
    "ks:ks_name":"Gereki Gaon",
    "ks:ks_pop":490,
    "ks:ks_type":"VILLAGE",
    "name:eng_x_preferred":[
        "Gereki Gaon"
    ],
    "wof:name":"Gereki Gaon",
    "wof:placetype":"locality",
    "wof:population":490
},
  "geometry": {"coordinates":[95.24708200000001,27.565686],"type":"Point"}
}