{
  "type": "Feature",
  "properties": {
    "iso:country":"IN",
    "ks:ks_alt_nam":"chakla.",
    "ks:ks_name":"Chakla.",
    "ks:ks_pop":752,
    "ks:ks_type":"HABITATION",
    "name:eng_x_preferred":[
        "Chakla."
    ],
    "wof:name":"Chakla.",
    "wof:placetype":"locality",
    "wof:population":752
},
  "geometry": {"coordinates":[86.53318299999999,25.730787],"type":"Point"}
}