{
  "type": "Feature",
  "properties": {
    "iso:country":"IN",
    "name:dut_x_preferred":[
        "Tulapur"
    ],
    "name:eng_x_preferred":[
        "Tulapur"
    ],
    "name:jpn_x_preferred":[
        "\u30c8\u30a5\u30e9\u30fc\u30d7\u30eb"
    ],
    "name:mar_x_preferred":[
        "\u0924\u0941\u0933\u093e\u092a\u0942\u0930"
    ],
    "name:rus_x_preferred":[
        "\u0422\u0443\u043b\u0430\u043f\u0443\u0440"
    ],
    "qs:name":"Tulapur",
    "qs:name_adm0":"India",
    "qs:name_adm1":"Maharashtra",
    "qs:photos":14,
    "qs:photos_1k":3,
    "qs:photos_9k":1,
    "qs:photos_9r":1,
    "qs:photos_all":14,
    "qs:photos_sr":1,
    "qs:placetype":"Town",
    "qs:pop_sr":"0",
    "wd:wordcount":356,
    "wof:name":"Tulapur",
    "wof:placetype":"locality"
},
  "geometry": {"coordinates":[73.99583749999999,18.6724295],"type":"Point"}
}