{
  "type": "Feature",
  "properties": {
    "iso:country":"IN",
    "ks:ks_alt_nam":"patkarpada",
    "ks:ks_name":"Patkarpada",
    "ks:ks_pop":300,
    "ks:ks_type":"HABITATION",
    "name:eng_x_preferred":[
        "Patkarpada"
    ],
    "wof:name":"Patkarpada",
    "wof:placetype":"locality",
    "wof:population":300
},
  "geometry": {"coordinates":[72.89225999999999,19.846235],"type":"Point"}
}