{
  "type": "Feature",
  "properties": {
    "iso:country":"IN",
    "ks:ks_name":"Dagarahan Purwa",
    "ks:ks_pop":170,
    "ks:ks_type":"HABITATION",
    "name:eng_x_preferred":[
        "Dagarahan Purwa"
    ],
    "wof:name":"Dagarahan Purwa",
    "wof:placetype":"locality",
    "wof:population":170
},
  "geometry": {"coordinates":[81.52024,27.48132],"type":"Point"}
}