{
  "type": "Feature",
  "properties": {
    "iso:country":"IN",
    "ks:ks_name":"Garuvupeta",
    "ks:ks_pop":394,
    "ks:ks_type":"HABITATION",
    "name:eng_x_preferred":[
        "Garuvupeta"
    ],
    "wof:name":"Garuvupeta",
    "wof:placetype":"locality",
    "wof:population":394
},
  "geometry": {"coordinates":[82.214692,16.575567],"type":"Point"}
}