{
  "type": "Feature",
  "properties": {
    "iso:country":"IN",
    "ks:ks_name":"Maheshbathna",
    "ks:ks_pop":2114,
    "ks:ks_type":"VILLAGE",
    "name:eng_x_preferred":[
        "Maheshbathna"
    ],
    "wof:name":"Maheshbathna",
    "wof:placetype":"locality",
    "wof:population":2114
},
  "geometry": {"coordinates":[87.921678,25.808768],"type":"Point"}
}