{
  "type": "Feature",
  "properties": {
    "iso:country":"IN",
    "ks:ks_name":"Kabra Urf Sarae-Ranjan",
    "ks:ks_pop":0,
    "ks:ks_type":"VILLAGE",
    "name:eng_x_preferred":[
        "Kabra Urf Sarae-Ranjan"
    ],
    "wof:name":"Kabra Urf Sarae-Ranjan",
    "wof:placetype":"locality",
    "wof:population":0
},
  "geometry": {"coordinates":[85.74656,25.742493],"type":"Point"}
}