{
  "type": "Feature",
  "properties": {
    "iso:country":"IN",
    "ks:ks_name":"Durbin Punjee",
    "ks:ks_pop":235,
    "ks:ks_type":"HABITATION",
    "name:eng_x_preferred":[
        "Durbin Punjee"
    ],
    "wof:name":"Durbin Punjee",
    "wof:placetype":"locality",
    "wof:population":235
},
  "geometry": {"coordinates":[92.54122099999999,24.477897],"type":"Point"}
}