{
  "type": "Feature",
  "properties": {
    "gn:admin1_code":"28.0",
    "gn:admin2_code":"330.0",
    "gn:asciiname":"Sonthaltola",
    "gn:country_code":"IN",
    "gn:dem":44,
    "gn:feature_class":"P",
    "gn:feature_code":"PPL",
    "gn:name":"Sonth\u0101ltola",
    "gn:population":0,
    "gn:timezone":"Asia/Kolkata",
    "iso:country":"IN",
    "wof:name":"Sonthaltola",
    "wof:placetype":"locality"
},
  "geometry": {"coordinates":[87.95255999999998,25.83367],"type":"Point"}
}