{
  "type": "Feature",
  "properties": {
    "gn:admin1_code":"2.0",
    "gn:admin2_code":"554.0",
    "gn:asciiname":"Cheldiganipalli",
    "gn:country_code":"IN",
    "gn:dem":773,
    "gn:feature_class":"P",
    "gn:feature_code":"PPL",
    "gn:name":"Cheldig\u0101nipalli",
    "gn:population":0,
    "gn:timezone":"Asia/Kolkata",
    "iso:country":"IN",
    "wof:name":"Cheldiganipalli",
    "wof:placetype":"locality"
},
  "geometry": {"coordinates":[78.45426999999999,12.93487],"type":"Point"}
}