{
  "type": "Feature",
  "properties": {
    "gn:admin1_code":"36",
    "gn:admin2_code":"179.0",
    "gn:asciiname":"Garma",
    "gn:country_code":"IN",
    "gn:dem":97,
    "gn:feature_class":"P",
    "gn:feature_code":"PPL",
    "gn:name":"Garma",
    "gn:population":0,
    "gn:timezone":"Asia/Kolkata",
    "iso:country":"IN",
    "name:ceb_x_preferred":[
        "Garma"
    ],
    "name:fra_x_preferred":[
        "Garma"
    ],
    "name:swe_x_preferred":[
        "Garma"
    ],
    "wof:name":"Garma",
    "wof:placetype":"neighbourhood"
},
  "geometry": {"coordinates":[82.2944,26.09896],"type":"Point"}
}