{
  "type": "Feature",
  "properties": {
    "gn:admin1_code":"36.0",
    "gn:admin2_code":"194",
    "gn:asciiname":"Badlapur",
    "gn:country_code":"IN",
    "gn:dem":93,
    "gn:feature_class":"P",
    "gn:feature_code":"PPL",
    "gn:name":"Badl\u0101pur",
    "gn:population":0,
    "gn:timezone":"Asia/Kolkata",
    "iso:country":"IN",
    "wof:name":"Badlapur",
    "wof:placetype":"locality"
},
  "geometry": {"coordinates":[82.45283000000001,25.89219],"type":"Point"}
}