{
  "type": "Feature",
  "properties": {
    "gn:admin1_code":"36.0",
    "gn:admin2_code":"194",
    "gn:asciiname":"Badlapur",
    "gn:country_code":"IN",
    "gn:dem":93,
    "gn:feature_class":"P",
    "gn:feature_code":"PPL",
    "gn:name":"Badl\u0101pur",
    "gn:population":0,
    "gn:timezone":"Asia/Kolkata",
    "iso:country":"IN",
    "name:ben_x_preferred":[
        "\u09ac\u09be\u09a6\u09b2\u09be\u09aa\u09c1\u09b0"
    ],
    "name:bih_x_preferred":[
        "\u092c\u0926\u0932\u093e\u092a\u0941\u0930"
    ],
    "name:bpy_x_preferred":[
        "\u09ac\u09be\u09a6\u09b2\u09be\u09aa\u09c1\u09b0"
    ],
    "name:ceb_x_preferred":[
        "Badlapur"
    ],
    "name:ita_x_preferred":[
        "Badlapur"
    ],
    "name:mlg_x_preferred":[
        "Badlapur"
    ],
    "name:msa_x_preferred":[
        "Badlapur"
    ],
    "name:new_x_preferred":[
        "\u092c\u093e\u0926\u0932\u092a\u0941\u0930"
    ],
    "name:nld_x_preferred":[
        "Badlapur"
    ],
    "name:swe_x_preferred":[
        "Badlapur"
    ],
    "name:urd_x_preferred":[
        "\u0628\u062f\u0644\u0627\u067e\u0648\u0631"
    ],
    "name:vie_x_preferred":[
        "Badlapur"
    ],
    "name:zho_x_preferred":[
        "\u5df4\u5fb7\u62c9\u666e\u5c14"
    ],
    "wof:name":"Badlapur",
    "wof:placetype":"locality"
},
  "geometry": {"coordinates":[82.45283000000001,25.89219],"type":"Point"}
}