{
  "type": "Feature",
  "properties": {
    "iso:country":"IN",
    "ks:ks_name":"Gautampur",
    "ks:ks_type":"VILLAGE",
    "name:eng_x_preferred":[
        "Gautampur"
    ],
    "wof:name":"Gautampur",
    "wof:placetype":"locality"
},
  "geometry": {"coordinates":[84.367255,20.859322],"type":"Point"}
}