{
  "type": "Feature",
  "properties": {
    "gn:admin1_code":"39.0",
    "gn:admin2_code":"67.0",
    "gn:asciiname":"Patia",
    "gn:country_code":"IN",
    "gn:dem":217,
    "gn:feature_class":"P",
    "gn:feature_code":"PPL",
    "gn:name":"Pati\u0101",
    "gn:population":0,
    "gn:timezone":"Asia/Kolkata",
    "iso:country":"IN",
    "name:ast_x_preferred":[
        "Patia"
    ],
    "name:ceb_x_preferred":[
        "Patia"
    ],
    "name:fra_x_preferred":[
        "Patia"
    ],
    "name:lat_x_preferred":[
        "Patia"
    ],
    "name:nld_x_preferred":[
        "Patia"
    ],
    "name:nor_x_preferred":[
        "Patia"
    ],
    "name:rus_x_preferred":[
        "Patia"
    ],
    "name:spa_x_preferred":[
        "Patia"
    ],
    "name:swe_x_preferred":[
        "Patia"
    ],
    "name:vie_x_preferred":[
        "Patia"
    ],
    "name:war_x_preferred":[
        "Patia"
    ],
    "name:zho_x_preferred":[
        "\u676f\u7c89\u8776\u5c6c"
    ],
    "wof:name":"Patia",
    "wof:placetype":"locality"
},
  "geometry": {"coordinates":[79.91599000000002,28.97731],"type":"Point"}
}