{
  "type": "Feature",
  "properties": {
    "iso:country":"IN",
    "ks:ks_name":"Sarpatwa",
    "ks:ks_pop":385,
    "ks:ks_type":"HABITATION",
    "name:eng_x_preferred":[
        "Sarpatwa"
    ],
    "wof:name":"Sarpatwa",
    "wof:placetype":"locality",
    "wof:population":385
},
  "geometry": {"coordinates":[82.987092,24.386163],"type":"Point"}
}