{
  "type": "Feature",
  "properties": {
    "iso:country":"IN",
    "ks:ks_name":"Shyampur",
    "ks:ks_pop":372,
    "ks:ks_type":"VILLAGE",
    "name:eng_x_preferred":[
        "Shyampur"
    ],
    "wof:name":"Shyampur",
    "wof:placetype":"locality",
    "wof:population":372
},
  "geometry": {"coordinates":[88.569062,25.420397],"type":"Point"}
}