{
  "type": "Feature",
  "properties": {
    "iso:country":"IN",
    "ks:ks_name":"Nimkuli",
    "ks:ks_pop":356,
    "ks:ks_type":"HABITATION",
    "name:eng_x_preferred":[
        "Nimkuli"
    ],
    "wof:name":"Nimkuli",
    "wof:placetype":"locality",
    "wof:population":356
},
  "geometry": {"coordinates":[86.062338,23.066566],"type":"Point"}
}