{
  "type": "Feature",
  "properties": {
    "iso:country":"IN",
    "ks:ks_name":"Madhye Purana Dak Bangla",
    "ks:ks_pop":9,
    "ks:ks_type":"VILLAGE",
    "ks:ks_uagg_main":0,
    "name:eng_x_preferred":[
        "Madhye Purana Dak Bangla"
    ],
    "wof:name":"Madhye Purana Dak Bangla",
    "wof:placetype":"neighbourhood",
    "wof:population":9
},
  "geometry": {"coordinates":[80.04010599999999,29.65888],"type":"Point"}
}