{
  "type": "Feature",
  "properties": {
    "iso:country":"IN",
    "ks:ks_alt_nam":"B\u0101dha",
    "ks:ks_name":"Badha",
    "ks:ks_pop":1323,
    "ks:ks_type":"VILLAGE",
    "ks:ks_uagg_main":0,
    "name:eng_x_preferred":[
        "Badha"
    ],
    "name:eng_x_variant":[
        "B\u0101dha"
    ],
    "wof:name":"Badha",
    "wof:placetype":"neighbourhood",
    "wof:population":1323
},
  "geometry": {"coordinates":[74.033535,30.41821],"type":"Point"}
}