{
  "type": "Feature",
  "properties": {
    "iso:country":"IN",
    "ks:ks_name":"Pokhara Tola",
    "ks:ks_pop":76,
    "ks:ks_type":"HABITATION",
    "ks:ks_uagg_main":0,
    "name:eng_x_preferred":[
        "Pokhara Tola"
    ],
    "wof:name":"Pokhara Tola",
    "wof:placetype":"neighbourhood",
    "wof:population":76
},
  "geometry": {"coordinates":[83.391453,27.172919],"type":"Point"}
}