{
  "type": "Feature",
  "properties": {
    "gn:admin1_code":"35",
    "gn:admin2_code":"455.0",
    "gn:asciiname":"Tigaon",
    "gn:country_code":"IN",
    "gn:dem":520,
    "gn:feature_class":"P",
    "gn:feature_code":"PPL",
    "gn:name":"T\u012bgaon",
    "gn:population":0,
    "gn:timezone":"Asia/Kolkata",
    "iso:country":"IN",
    "name:ceb_x_preferred":[
        "Tigaon"
    ],
    "wof:name":"Tigaon",
    "wof:placetype":"neighbourhood"
},
  "geometry": {"coordinates":[78.45759,21.64562],"type":"Point"}
}