{
  "type": "Feature",
  "properties": {
    "iso:country":"IN",
    "ks:ks_name":"Shombhu Ch. Para",
    "ks:ks_pop":52,
    "ks:ks_type":"HABITATION",
    "name:eng_x_preferred":[
        "Shombhu Ch. Para"
    ],
    "wof:name":"Shombhu Ch. Para",
    "wof:placetype":"locality",
    "wof:population":52
},
  "geometry": {"coordinates":[91.45048199999999,23.76163],"type":"Point"}
}