{
  "type": "Feature",
  "properties": {
    "iso:country":"IN",
    "ks:ks_name":"Nichala Faliya",
    "ks:ks_pop":82,
    "ks:ks_type":"HABITATION",
    "name:eng_x_preferred":[
        "Nichala Faliya"
    ],
    "wof:name":"Nichala Faliya",
    "wof:placetype":"locality",
    "wof:population":82
},
  "geometry": {"coordinates":[73.405366,20.454006],"type":"Point"}
}