{
  "type": "Feature",
  "properties": {
    "iso:country":"IN",
    "ks:ks_name":"Peepasar Nagar",
    "ks:ks_pop":977,
    "ks:ks_type":"HABITATION",
    "name:eng_x_preferred":[
        "Peepasar Nagar"
    ],
    "wof:name":"Peepasar Nagar",
    "wof:placetype":"locality",
    "wof:population":977
},
  "geometry": {"coordinates":[72.64201,26.879061],"type":"Point"}
}