{
  "type": "Feature",
  "properties": {
    "iso:country":"IN",
    "ks:ks_name":"Mallah Tolla",
    "ks:ks_pop":1616,
    "ks:ks_type":"HABITATION",
    "name:eng_x_preferred":[
        "Mallah Tolla"
    ],
    "wof:name":"Mallah Tolla",
    "wof:placetype":"locality",
    "wof:population":1616
},
  "geometry": {"coordinates":[85.23160300000001,25.7615],"type":"Point"}
}