{
  "type": "Feature",
  "properties": {
    "gn:admin1_code":"36",
    "gn:admin2_code":"185.0",
    "gn:asciiname":"Khamharia",
    "gn:country_code":"IN",
    "gn:dem":89,
    "gn:feature_class":"P",
    "gn:feature_code":"PPL",
    "gn:name":"Khamharia",
    "gn:population":0,
    "gn:timezone":"Asia/Kolkata",
    "iso:country":"IN",
    "name:ceb_x_preferred":[
        "Khamharia"
    ],
    "name:swe_x_preferred":[
        "Khamharia"
    ],
    "wof:name":"Khamharia",
    "wof:placetype":"locality"
},
  "geometry": {"coordinates":[82.79994000000001,26.92209],"type":"Point"}
}