{
  "type": "Feature",
  "properties": {
    "iso:country":"IN",
    "ks:ks_name":"Kunkal",
    "ks:ks_pop":82,
    "ks:ks_type":"HABITATION",
    "name:eng_x_preferred":[
        "Kunkal"
    ],
    "wof:name":"Kunkal",
    "wof:placetype":"locality",
    "wof:population":82
},
  "geometry": {"coordinates":[80.92793899999999,20.472649],"type":"Point"}
}