{
  "type": "Feature",
  "properties": {
    "gn:admin1_code":"36",
    "gn:admin2_code":"159.0",
    "gn:asciiname":"Sankisa Basantpur",
    "gn:country_code":"IN",
    "gn:dem":165,
    "gn:feature_class":"P",
    "gn:feature_code":"PPL",
    "gn:name":"Sank\u012bsa Basantpur",
    "gn:population":0,
    "gn:timezone":"Asia/Kolkata",
    "iso:country":"IN",
    "wof:name":"Sankisa Basantpur",
    "wof:placetype":"locality"
},
  "geometry": {"coordinates":[79.27127,27.33847],"type":"Point"}
}