{
  "type": "Feature",
  "properties": {
    "iso:country":"IN",
    "ks:ks_name":"Balisahi",
    "ks:ks_pop":163,
    "ks:ks_type":"HABITATION",
    "name:eng_x_preferred":[
        "Balisahi"
    ],
    "wof:name":"Balisahi",
    "wof:placetype":"locality",
    "wof:population":163
},
  "geometry": {"coordinates":[85.358689,20.55636],"type":"Point"}
}