{
  "type": "Feature",
  "properties": {
    "iso:country":"IN",
    "ks:ks_name":"Kandiyala",
    "ks:ks_pop":32,
    "ks:ks_type":"HABITATION",
    "name:eng_x_preferred":[
        "Kandiyala"
    ],
    "wof:name":"Kandiyala",
    "wof:placetype":"locality",
    "wof:population":32
},
  "geometry": {"coordinates":[70.8536,27.146589],"type":"Point"}
}