{
  "type": "Feature",
  "properties": {
    "iso:country":"IN",
    "ks:ks_name":"Pattarapunjai",
    "ks:ks_pop":133,
    "ks:ks_type":"HABITATION",
    "name:eng_x_preferred":[
        "Pattarapunjai"
    ],
    "wof:name":"Pattarapunjai",
    "wof:placetype":"locality",
    "wof:population":133
},
  "geometry": {"coordinates":[79.066219,10.390655],"type":"Point"}
}