{
  "type": "Feature",
  "properties": {
    "iso:country":"IN",
    "ks:ks_name":"Yemmerahalli",
    "ks:ks_pop":564,
    "ks:ks_type":"HABITATION",
    "name:eng_x_preferred":[
        "Yemmerahalli"
    ],
    "wof:name":"Yemmerahalli",
    "wof:placetype":"locality",
    "wof:population":564
},
  "geometry": {"coordinates":[76.911858,13.713863],"type":"Point"}
}