{
  "type": "Feature",
  "properties": {
    "iso:country":"IN",
    "ks:ks_alt_nam":"Satipal purwa",
    "ks:ks_name":"Satipal Purwa",
    "ks:ks_pop":14,
    "ks:ks_type":"HABITATION",
    "name:eng_x_preferred":[
        "Satipal Purwa"
    ],
    "wof:name":"Satipal Purwa",
    "wof:placetype":"locality",
    "wof:population":14
},
  "geometry": {"coordinates":[81.81057199999999,27.361773],"type":"Point"}
}