{
  "type": "Feature",
  "properties": {
    "iso:country":"IN",
    "ks:ks_alt_nam":"SUKRI DOHAR",
    "ks:ks_name":"Sukri Dohar",
    "ks:ks_pop":131,
    "ks:ks_type":"HABITATION",
    "name:eng_x_preferred":[
        "Sukri Dohar"
    ],
    "wof:name":"Sukri Dohar",
    "wof:placetype":"locality",
    "wof:population":131
},
  "geometry": {"coordinates":[84.258899,23.667102],"type":"Point"}
}