{
  "type": "Feature",
  "properties": {
    "gn:admin1_code":"19.0",
    "gn:admin2_code":"568.0",
    "gn:asciiname":"Tekkuru",
    "gn:country_code":"IN",
    "gn:dem":597,
    "gn:feature_class":"P",
    "gn:feature_code":"PPL",
    "gn:name":"Tekk\u016bru",
    "gn:population":0,
    "gn:timezone":"Asia/Kolkata",
    "iso:country":"IN",
    "ks:ks_name":"Thekkuru",
    "ks:ks_pop":482,
    "ks:ks_type":"VILLAGE",
    "name:eng_x_preferred":[
        "Thekkuru"
    ],
    "name:eng_x_variant":[
        "Tekkuru"
    ],
    "wof:name":"Thekkuru",
    "wof:placetype":"locality",
    "wof:population":482
},
  "geometry": {"coordinates":[75.05188699999999,14.470794],"type":"Point"}
}