{
  "type": "Feature",
  "properties": {
    "gn:admin1_code":"35",
    "gn:admin2_code":"447.0",
    "gn:asciiname":"Jamulni",
    "gn:country_code":"IN",
    "gn:dem":659,
    "gn:feature_class":"P",
    "gn:feature_code":"PPL",
    "gn:name":"J\u0101mulni",
    "gn:population":0,
    "gn:timezone":"Asia/Kolkata",
    "iso:country":"IN",
    "wof:name":"Jamulni",
    "wof:placetype":"locality"
},
  "geometry": {"coordinates":[77.54244,21.44157],"type":"Point"}
}