{
  "type": "Feature",
  "properties": {
    "iso:country":"IN",
    "ks:ks_name":"Malahi Tola",
    "ks:ks_pop":324,
    "ks:ks_type":"HABITATION",
    "ks:ks_uagg_main":0,
    "name:eng_x_preferred":[
        "Malahi Tola"
    ],
    "wof:name":"Malahi Tola",
    "wof:placetype":"neighbourhood",
    "wof:population":324
},
  "geometry": {"coordinates":[84.87016300000001,26.82635],"type":"Point"}
}