{
  "type": "Feature",
  "properties": {
    "iso:country":"IN",
    "ks:ks_alt_nam":"Bar\u0101b\u0101ni",
    "ks:ks_name":"Barabani",
    "ks:ks_pop":298,
    "ks:ks_type":"VILLAGE",
    "name:eng_x_preferred":[
        "Barabani"
    ],
    "name:eng_x_variant":[
        "Bar\u0101b\u0101ni"
    ],
    "wof:name":"Barabani",
    "wof:placetype":"locality",
    "wof:population":298
},
  "geometry": {"coordinates":[84.383624,20.660951],"type":"Point"}
}