{
  "type": "Feature",
  "properties": {
    "iso:country":"IN",
    "ks:ks_name":"Kahachenar",
    "ks:ks_pop":362,
    "ks:ks_type":"HABITATION",
    "name:eng_x_preferred":[
        "Kahachenar"
    ],
    "wof:name":"Kahachenar",
    "wof:placetype":"locality",
    "wof:population":362
},
  "geometry": {"coordinates":[81.379087,19.252106],"type":"Point"}
}