{
  "type": "Feature",
  "properties": {
    "iso:country":"IN",
    "ks:ks_name":"Lahangepada",
    "ks:ks_pop":187,
    "ks:ks_type":"HABITATION",
    "name:eng_x_preferred":[
        "Lahangepada"
    ],
    "wof:name":"Lahangepada",
    "wof:placetype":"locality",
    "wof:population":187
},
  "geometry": {"coordinates":[72.967224,19.833392],"type":"Point"}
}