{
  "type": "Feature",
  "properties": {
    "iso:country":"IN",
    "ks:ks_name":"Sadargaon",
    "ks:ks_pop":1883,
    "ks:ks_type":"VILLAGE",
    "ks:ks_uagg_main":0,
    "name:eng_x_preferred":[
        "Sadargaon"
    ],
    "wof:name":"Sadargaon",
    "wof:placetype":"neighbourhood",
    "wof:population":1883
},
  "geometry": {"coordinates":[92.903533,26.070061],"type":"Point"}
}