{
  "type": "Feature",
  "properties": {
    "gn:admin1_code":"11.0",
    "gn:admin2_code":"31.0",
    "gn:asciiname":"Anchil",
    "gn:country_code":"IN",
    "gn:dem":1108,
    "gn:feature_class":"P",
    "gn:feature_code":"PPL",
    "gn:name":"Anchil",
    "gn:population":0,
    "gn:timezone":"Asia/Kolkata",
    "iso:country":"IN",
    "wof:name":"Anchil",
    "wof:placetype":"locality"
},
  "geometry": {"coordinates":[77.19258000000001,30.90503],"type":"Point"}
}