{
  "type": "Feature",
  "properties": {
    "iso:country":"IN",
    "ks:ks_name":"Simali",
    "ks:ks_pop":32,
    "ks:ks_type":"HABITATION",
    "name:eng_x_preferred":[
        "Simali"
    ],
    "wof:name":"Simali",
    "wof:placetype":"locality",
    "wof:population":32
},
  "geometry": {"coordinates":[79.96931499999999,29.819957],"type":"Point"}
}