{
  "type": "Feature",
  "properties": {
    "iso:country":"IN",
    "ks:ks_alt_nam":"Peerani Godaron ki Dhani Pirani Lolo Ki Dhani",
    "ks:ks_name":"Peerani Godaron Ki Dhani Pirani Lolo Ki Dhani",
    "ks:ks_pop":190,
    "ks:ks_type":"HABITATION",
    "name:eng_x_preferred":[
        "Peerani Godaron Ki Dhani Pirani Lolo Ki Dhani"
    ],
    "wof:name":"Peerani Godaron Ki Dhani Pirani Lolo Ki Dhani",
    "wof:placetype":"locality",
    "wof:population":190
},
  "geometry": {"coordinates":[71.61957200000001,25.431786],"type":"Point"}
}