{
  "type": "Feature",
  "properties": {
    "gn:admin1_code":"19.0",
    "gn:admin2_code":"574.0",
    "gn:asciiname":"Timmayagaudanakoppal",
    "gn:country_code":"IN",
    "gn:dem":977,
    "gn:feature_class":"P",
    "gn:feature_code":"PPL",
    "gn:name":"Timm\u0101yagaudanakoppal",
    "gn:population":0,
    "gn:timezone":"Asia/Kolkata",
    "iso:country":"IN",
    "wof:name":"Timmayagaudanakoppal",
    "wof:placetype":"locality"
},
  "geometry": {"coordinates":[76.12813,13.01543],"type":"Point"}
}