{
  "type": "Feature",
  "properties": {
    "iso:country":"IN",
    "ks:ks_name":"Sandrewadi",
    "ks:ks_pop":285,
    "ks:ks_type":"HABITATION",
    "name:eng_x_preferred":[
        "Sandrewadi"
    ],
    "wof:name":"Sandrewadi",
    "wof:placetype":"locality",
    "wof:population":285
},
  "geometry": {"coordinates":[73.780485,16.198673],"type":"Point"}
}