{
  "type": "Feature",
  "properties": {
    "iso:country":"IN",
    "ks:ks_name":"Navinagari Gopalbag",
    "ks:ks_pop":822,
    "ks:ks_type":"HABITATION",
    "name:eng_x_preferred":[
        "Navinagari Gopalbag"
    ],
    "wof:name":"Navinagari Gopalbag",
    "wof:placetype":"locality",
    "wof:population":822
},
  "geometry": {"coordinates":[72.74525,20.186417],"type":"Point"}
}