{
  "type": "Feature",
  "properties": {
    "gn:admin1_code":"36",
    "gn:admin2_code":"146.0",
    "gn:asciiname":"Khanda",
    "gn:country_code":"IN",
    "gn:dem":177,
    "gn:feature_class":"P",
    "gn:feature_code":"PPL",
    "gn:name":"Kh\u0101nda",
    "gn:population":0,
    "gn:timezone":"Asia/Kolkata",
    "iso:country":"IN",
    "name:ceb_x_preferred":[
        "Khanda"
    ],
    "name:fas_x_preferred":[
        "\u062e\u0627\u0646\u062f\u0627"
    ],
    "name:hin_x_preferred":[
        "\u0916\u0902\u0921\u093e"
    ],
    "name:ita_x_preferred":[
        "Khanda"
    ],
    "wof:name":"Khanda",
    "wof:placetype":"locality"
},
  "geometry": {"coordinates":[78.15555999999999,27.3657],"type":"Point"}
}