{
  "type": "Feature",
  "properties": {
    "iso:country":"IN",
    "ks:ks_name":"Dubajan",
    "ks:ks_pop":289,
    "ks:ks_type":"HABITATION",
    "name:eng_x_preferred":[
        "Dubajan"
    ],
    "wof:name":"Dubajan",
    "wof:placetype":"locality",
    "wof:population":289
},
  "geometry": {"coordinates":[93.81622299999999,26.141123],"type":"Point"}
}