{
  "type": "Feature",
  "properties": {
    "gn:admin1_code":"16.0",
    "gn:admin2_code":"521.0",
    "gn:asciiname":"Wakad",
    "gn:country_code":"IN",
    "gn:dem":570,
    "gn:feature_class":"P",
    "gn:feature_code":"PPL",
    "gn:name":"Wakad",
    "gn:population":0,
    "gn:timezone":"Asia/Kolkata",
    "iso:country":"IN",
    "name:ara_x_preferred":[
        "\u0648\u0627\u0642\u0648\u062f"
    ],
    "name:ben_bn_x_preferred":[
        "\u0993\u09df\u09be\u0995\u09be\u09dc"
    ],
    "name:ben_in_x_preferred":[
        "\u0993\u09df\u09be\u0995\u09be\u09dc"
    ],
    "name:guj_x_preferred":[
        "\u0ab5\u0abe\u0a95\u0aa1"
    ],
    "name:hin_x_preferred":[
        "\u0935\u093e\u0915\u095c"
    ],
    "name:kan_x_preferred":[
        "\u0cb5\u0c95\u0ca1\u0ccd"
    ],
    "name:mal_x_preferred":[
        "\u0d35\u0d15\u0d3e\u0d26\u0d4d"
    ],
    "name:mar_x_preferred":[
        "\u0935\u093e\u0915\u0921"
    ],
    "name:pan_x_preferred":[
        "\u0a35\u0a3e\u0a15\u0a5c"
    ],
    "name:tam_x_preferred":[
        "\u0bb5\u0b95\u0bbe\u0b9f\u0bcd"
    ],
    "name:tel_x_preferred":[
        "\u0c35\u0c3e\u0c15\u0c21\u0c4d"
    ],
    "name:urd_x_preferred":[
        "\u0648\u0627\u06a9\u0627\u0688"
    ],
    "wof:name":"Wakad",
    "wof:placetype":"neighbourhood"
},
  "geometry": {"coordinates":[73.76255,18.60319],"type":"Point"}
}