{
  "type": "Feature",
  "properties": {
    "iso:country":"IN",
    "ks:ks_name":"Mola Amba",
    "ks:ks_pop":1994,
    "ks:ks_type":"VILLAGE",
    "name:eng_x_preferred":[
        "Mola Amba"
    ],
    "wof:name":"Mola Amba",
    "wof:placetype":"locality",
    "wof:population":1994
},
  "geometry": {"coordinates":[73.34979199999999,20.61986],"type":"Point"}
}