{
  "type": "Feature",
  "properties": {
    "iso:country":"IN",
    "ks:ks_alt_nam":"chamruti",
    "ks:ks_name":"Chamruti",
    "ks:ks_pop":604,
    "ks:ks_type":"HABITATION",
    "name:eng_x_preferred":[
        "Chamruti"
    ],
    "wof:name":"Chamruti",
    "wof:placetype":"locality",
    "wof:population":604
},
  "geometry": {"coordinates":[82.16685,25.3574],"type":"Point"}
}