{
  "type": "Feature",
  "properties": {
    "iso:country":"IN",
    "ks:ks_name":"Chandrauli",
    "ks:ks_pop":1926,
    "ks:ks_type":"VILLAGE",
    "name:eng_x_preferred":[
        "Chandrauli"
    ],
    "wof:name":"Chandrauli",
    "wof:placetype":"locality",
    "wof:population":1926
},
  "geometry": {"coordinates":[77.610955,30.011283],"type":"Point"}
}