{
  "type": "Feature",
  "properties": {
    "gn:admin1_code":"35.0",
    "gn:admin2_code":"442.0",
    "gn:asciiname":"Malhargarh",
    "gn:country_code":"IN",
    "gn:dem":384,
    "gn:feature_class":"P",
    "gn:feature_code":"PPL",
    "gn:name":"Malh\u0101rgarh",
    "gn:population":0,
    "gn:timezone":"Asia/Kolkata",
    "iso:country":"IN",
    "name:ben_x_preferred":[
        "\u09ae\u09be\u09b2\u09b9\u09be\u09b0\u0997\u09a1\u09bc"
    ],
    "name:bpy_x_preferred":[
        "\u09ae\u09be\u09b2\u09b9\u09be\u09b0\u0997\u09a1\u09bc"
    ],
    "name:ceb_x_preferred":[
        "Malh\u0101rgarh"
    ],
    "name:ita_x_preferred":[
        "Malhargarh"
    ],
    "name:mlg_x_preferred":[
        "Malhargarh"
    ],
    "name:msa_x_preferred":[
        "Malhargarh"
    ],
    "name:new_x_preferred":[
        "\u092e\u0932\u094d\u0939\u0930\u0917\u0922"
    ],
    "name:nld_x_preferred":[
        "Malhargarh"
    ],
    "name:por_x_preferred":[
        "Malhargarh"
    ],
    "name:swe_x_preferred":[
        "Malh\u0101rgarh"
    ],
    "name:vie_x_preferred":[
        "Malhargarh"
    ],
    "name:zho_x_preferred":[
        "\u9a6c\u5c14\u54c8\u5c14\u52a0\u5c14"
    ],
    "wof:name":"Malhargarh",
    "wof:placetype":"locality"
},
  "geometry": {"coordinates":[76.27509000000001,24.11696],"type":"Point"}
}