{
  "type": "Feature",
  "properties": {
    "iso:country":"IN",
    "ks:ks_name":"Rutadih",
    "ks:ks_pop":63,
    "ks:ks_type":"HABITATION",
    "name:eng_x_preferred":[
        "Rutadih"
    ],
    "wof:name":"Rutadih",
    "wof:placetype":"locality",
    "wof:population":63
},
  "geometry": {"coordinates":[85.55018200000001,23.047265],"type":"Point"}
}