{
  "type": "Feature",
  "properties": {
    "iso:country":"IN",
    "ks:ks_alt_nam":"Dull\u012btol\u0101 Khurd",
    "ks:ks_name":"Dullitola Khurd",
    "ks:ks_pop":574,
    "ks:ks_type":"VILLAGE",
    "name:eng_x_preferred":[
        "Dullitola Khurd"
    ],
    "name:eng_x_variant":[
        "Dull\u012btol\u0101 Khurd"
    ],
    "wof:name":"Dullitola Khurd",
    "wof:placetype":"locality",
    "wof:population":574
},
  "geometry": {"coordinates":[80.945966,21.415635],"type":"Point"}
}