{
  "type": "Feature",
  "properties": {
    "iso:country":"IN",
    "ks:ks_name":"Baro",
    "ks:ks_pop":958,
    "ks:ks_type":"VILLAGE",
    "name:eng_x_preferred":[
        "Baro"
    ],
    "wof:name":"Baro",
    "wof:placetype":"locality",
    "wof:population":958
},
  "geometry": {"coordinates":[83.861243,22.436615],"type":"Point"}
}