{
  "type": "Feature",
  "properties": {
    "iso:country":"IN",
    "ks:ks_name":"Kodachadri",
    "ks:ks_pop":22,
    "ks:ks_type":"HABITATION",
    "name:eng_x_preferred":[
        "Kodachadri"
    ],
    "wof:name":"Kodachadri",
    "wof:placetype":"locality",
    "wof:population":22
},
  "geometry": {"coordinates":[74.91892300000001,13.865148],"type":"Point"}
}