{
  "type": "Feature",
  "properties": {
    "gn:admin1_code":"39.0",
    "gn:admin2_code":"66.0",
    "gn:asciiname":"Talla Kun",
    "gn:country_code":"IN",
    "gn:dem":1686,
    "gn:feature_class":"P",
    "gn:feature_code":"PPL",
    "gn:name":"Talla K\u016bn",
    "gn:population":0,
    "gn:timezone":"Asia/Kolkata",
    "iso:country":"IN",
    "wof:name":"Talla Kun",
    "wof:placetype":"locality"
},
  "geometry": {"coordinates":[79.40316999999997,29.39289],"type":"Point"}
}