{
  "type": "Feature",
  "properties": {
    "iso:country":"IN",
    "ks:ks_alt_nam":"pratabgorh Line No 7",
    "ks:ks_name":"Pratabgorh Line No 7",
    "ks:ks_pop":1319,
    "ks:ks_type":"HABITATION",
    "name:eng_x_preferred":[
        "Pratabgorh Line No 7"
    ],
    "wof:name":"Pratabgorh Line No 7",
    "wof:placetype":"locality",
    "wof:population":1319
},
  "geometry": {"coordinates":[93.085565,26.766648],"type":"Point"}
}