{
  "type": "Feature",
  "properties": {
    "gn:admin1_code":"35.0",
    "gn:admin2_code":"463.0",
    "gn:asciiname":"Butawa",
    "gn:country_code":"IN",
    "gn:dem":318,
    "gn:feature_class":"P",
    "gn:feature_code":"PPL",
    "gn:name":"Butawa",
    "gn:population":0,
    "gn:timezone":"Asia/Kolkata",
    "iso:country":"IN",
    "ks:ks_name":"Butawa",
    "ks:ks_pop":898,
    "ks:ks_type":"VILLAGE",
    "name:eng_x_preferred":[
        "Butawa"
    ],
    "wof:name":"Butawa",
    "wof:placetype":"locality",
    "wof:population":898
},
  "geometry": {"coordinates":[82.687873,24.44221],"type":"Point"}
}