{
  "type": "Feature",
  "properties": {
    "iso:country":"IN",
    "ks:ks_name":"Bijori Fulla",
    "ks:ks_pop":634,
    "ks:ks_type":"VILLAGE",
    "name:eng_x_preferred":[
        "Bijori Fulla"
    ],
    "wof:name":"Bijori Fulla",
    "wof:placetype":"locality",
    "wof:population":634
},
  "geometry": {"coordinates":[78.894311,22.18731],"type":"Point"}
}