{
  "type": "Feature",
  "properties": {
    "iso:country":"IN",
    "ks:ks_name":"Manjhibhata",
    "ks:ks_pop":41,
    "ks:ks_type":"HABITATION",
    "name:eng_x_preferred":[
        "Manjhibhata"
    ],
    "wof:name":"Manjhibhata",
    "wof:placetype":"locality",
    "wof:population":41
},
  "geometry": {"coordinates":[81.54017399999999,19.012371],"type":"Point"}
}