{
  "type": "Feature",
  "properties": {
    "iso:country":"IN",
    "ks:ks_name":"Mananbar",
    "ks:ks_pop":189,
    "ks:ks_type":"HABITATION",
    "name:eng_x_preferred":[
        "Mananbar"
    ],
    "wof:name":"Mananbar",
    "wof:placetype":"locality",
    "wof:population":189
},
  "geometry": {"coordinates":[86.856002,24.607383],"type":"Point"}
}