{
  "type": "Feature",
  "properties": {
    "gn:admin1_code":"2.0",
    "gn:admin2_code":"554.0",
    "gn:asciiname":"Gonepalli",
    "gn:country_code":"IN",
    "gn:dem":361,
    "gn:feature_class":"P",
    "gn:feature_code":"PPL",
    "gn:name":"Gonepalli",
    "gn:population":0,
    "gn:timezone":"Asia/Kolkata",
    "iso:country":"IN",
    "ks:ks_name":"Gonepalle",
    "ks:ks_pop":55,
    "ks:ks_type":"HABITATION",
    "name:eng_x_preferred":[
        "Gonepalle"
    ],
    "name:eng_x_variant":[
        "Gonepalli"
    ],
    "wof:name":"Gonepalle",
    "wof:placetype":"locality",
    "wof:population":55
},
  "geometry": {"coordinates":[79.008651,13.233793],"type":"Point"}
}