{
  "type": "Feature",
  "properties": {
    "gn:admin1_code":"16.0",
    "gn:admin2_code":"513.0",
    "gn:asciiname":"Kanhegaon",
    "gn:country_code":"IN",
    "gn:dem":377,
    "gn:feature_class":"P",
    "gn:feature_code":"PPL",
    "gn:name":"K\u0101nhegaon",
    "gn:population":0,
    "gn:timezone":"Asia/Kolkata",
    "iso:country":"IN",
    "wof:name":"Kanhegaon",
    "wof:placetype":"locality"
},
  "geometry": {"coordinates":[76.99417,19.20136],"type":"Point"}
}