{
  "type": "Feature",
  "properties": {
    "iso:country":"IN",
    "ks:ks_name":"Chintalamudipi",
    "ks:ks_pop":272,
    "ks:ks_type":"HABITATION",
    "name:eng_x_preferred":[
        "Chintalamudipi"
    ],
    "wof:name":"Chintalamudipi",
    "wof:placetype":"locality",
    "wof:population":272
},
  "geometry": {"coordinates":[79.10839300000001,15.837877],"type":"Point"}
}