{
  "type": "Feature",
  "properties": {
    "gn:admin1_code":"35",
    "gn:admin2_code":"440.0",
    "gn:asciiname":"Pipaliya",
    "gn:country_code":"IN",
    "gn:dem":369,
    "gn:feature_class":"P",
    "gn:feature_code":"PPL",
    "gn:name":"Pipaliya",
    "gn:population":0,
    "gn:timezone":"Asia/Kolkata",
    "iso:country":"IN",
    "ks:ks_name":"Pipaliya",
    "ks:ks_type":"VILLAGE",
    "name:eng_x_preferred":[
        "Pipaliya"
    ],
    "wof:name":"Pipaliya",
    "wof:placetype":"locality"
},
  "geometry": {"coordinates":[76.013784,21.682863],"type":"Point"}
}