{
  "type": "Feature",
  "properties": {
    "iso:country":"IN",
    "ks:ks_name":"Korra Thanda",
    "ks:ks_pop":84,
    "ks:ks_type":"HABITATION",
    "name:eng_x_preferred":[
        "Korra Thanda"
    ],
    "wof:name":"Korra Thanda",
    "wof:placetype":"locality",
    "wof:population":84
},
  "geometry": {"coordinates":[78.17998900000001,17.875447],"type":"Point"}
}