{
  "type": "Feature",
  "properties": {
    "iso:country":"IN",
    "ks:ks_name":"Pure Khatik",
    "ks:ks_pop":434,
    "ks:ks_type":"HABITATION",
    "name:eng_x_preferred":[
        "Pure Khatik"
    ],
    "wof:name":"Pure Khatik",
    "wof:placetype":"locality",
    "wof:population":434
},
  "geometry": {"coordinates":[81.58108300000001,26.464663],"type":"Point"}
}