{
  "type": "Feature",
  "properties": {
    "gn:admin1_code":"12.0",
    "gn:admin2_code":"12.0",
    "gn:asciiname":"Diyor",
    "gn:country_code":"IN",
    "gn:dem":1868,
    "gn:feature_class":"P",
    "gn:feature_code":"PPL",
    "gn:name":"Diyor",
    "gn:population":0,
    "gn:timezone":"Asia/Kolkata",
    "iso:country":"IN",
    "wof:name":"Diyor",
    "wof:placetype":"locality"
},
  "geometry": {"coordinates":[74.83519,33.79037],"type":"Point"}
}