{
  "type": "Feature",
  "properties": {
    "iso:country":"IN",
    "ks:ks_name":"14 GGR",
    "ks:ks_pop":1676,
    "ks:ks_type":"VILLAGE",
    "name:eng_x_preferred":[
        "14 GGR"
    ],
    "wof:name":"14 GGR",
    "wof:placetype":"locality",
    "wof:population":1676
},
  "geometry": {"coordinates":[74.44809600000001,29.526938],"type":"Point"}
}