{
  "type": "Feature",
  "properties": {
    "gn:admin1_code":"34.0",
    "gn:admin2_code":"210.0",
    "gn:asciiname":"Chakchaki",
    "gn:country_code":"IN",
    "gn:dem":59,
    "gn:feature_class":"P",
    "gn:feature_code":"PPL",
    "gn:name":"Chakchaki",
    "gn:population":0,
    "gn:timezone":"Asia/Kolkata",
    "iso:country":"IN",
    "name:bih_x_preferred":[
        "\u091a\u0915\u091a\u0915\u0940"
    ],
    "name:ceb_x_preferred":[
        "Chakchaki"
    ],
    "name:fra_x_preferred":[
        "Chakchaki"
    ],
    "name:hin_x_preferred":[
        "\u091a\u0915\u091a\u0915\u0940"
    ],
    "name:mai_x_preferred":[
        "\u091a\u0915\u091a\u0915\u0940"
    ],
    "name:msa_x_preferred":[
        "Chakchaki"
    ],
    "name:nep_x_preferred":[
        "\u091a\u0915\u091a\u0915\u0940"
    ],
    "name:new_x_preferred":[
        "\u091a\u0915\u091a\u0915\u0940"
    ],
    "name:pol_x_preferred":[
        "Chakchaki"
    ],
    "wof:name":"Chakchaki",
    "wof:placetype":"locality"
},
  "geometry": {"coordinates":[87.7762,26.26371],"type":"Point"}
}