{
  "type": "Feature",
  "properties": {
    "gn:admin1_code":"19.0",
    "gn:admin2_code":"577.0",
    "gn:asciiname":"Yamgumba",
    "gn:country_code":"IN",
    "gn:dem":836,
    "gn:feature_class":"P",
    "gn:feature_code":"PPL",
    "gn:name":"Yamgumba",
    "gn:population":0,
    "gn:timezone":"Asia/Kolkata",
    "iso:country":"IN",
    "wof:name":"Yamgumba",
    "wof:placetype":"locality"
},
  "geometry": {"coordinates":[76.23139,12.35766],"type":"Point"}
}