{
  "type": "Feature",
  "properties": {
    "gn:admin1_code":"21.0",
    "gn:admin2_code":"396.0",
    "gn:asciiname":"Singamundi",
    "gn:country_code":"IN",
    "gn:dem":285,
    "gn:feature_class":"P",
    "gn:feature_code":"PPL",
    "gn:name":"Sing\u0101mundi",
    "gn:population":0,
    "gn:timezone":"Asia/Kolkata",
    "iso:country":"IN",
    "ks:ks_alt_nam":"Sing\u0101mundi",
    "ks:ks_name":"Singamundi",
    "ks:ks_pop":181,
    "ks:ks_type":"VILLAGE",
    "name:eng_x_preferred":[
        "Singamundi"
    ],
    "name:eng_x_variant":[
        "Sing\u0101mundi"
    ],
    "wof:name":"Singamundi",
    "wof:placetype":"locality",
    "wof:population":181
},
  "geometry": {"coordinates":[83.808807,19.524344],"type":"Point"}
}