{
  "type": "Feature",
  "properties": {
    "gn:admin1_code":"12.0",
    "gn:admin2_code":"008",
    "gn:asciiname":"Baba Rafiuddin",
    "gn:country_code":"IN",
    "gn:dem":1849,
    "gn:feature_class":"P",
    "gn:feature_code":"PPL",
    "gn:name":"B\u0101ba Rafiudd\u012bn",
    "gn:population":0,
    "gn:timezone":"Asia/Kolkata",
    "iso:country":"IN",
    "wof:name":"Baba Rafiuddin",
    "wof:placetype":"locality"
},
  "geometry": {"coordinates":[74.60454,34.05149],"type":"Point"}
}