{
  "type": "Feature",
  "properties": {
    "iso:country":"IN",
    "ks:ks_name":"Kanchania South",
    "ks:ks_pop":243,
    "ks:ks_type":"HABITATION",
    "name:eng_x_preferred":[
        "Kanchania South"
    ],
    "wof:name":"Kanchania South",
    "wof:placetype":"locality",
    "wof:population":243
},
  "geometry": {"coordinates":[83.08097600000001,27.410443],"type":"Point"}
}