{
  "type": "Feature",
  "properties": {
    "gn:admin1_code":"39.0",
    "gn:admin2_code":"66.0",
    "gn:asciiname":"Salba",
    "gn:country_code":"IN",
    "gn:dem":1603,
    "gn:feature_class":"P",
    "gn:feature_code":"PPL",
    "gn:name":"Salba",
    "gn:population":0,
    "gn:timezone":"Asia/Kolkata",
    "iso:country":"IN",
    "ks:ks_name":"Salwa",
    "ks:ks_pop":196,
    "ks:ks_type":"VILLAGE",
    "name:eng_x_preferred":[
        "Salwa"
    ],
    "name:eng_x_variant":[
        "Salba"
    ],
    "wof:name":"Salwa",
    "wof:placetype":"locality",
    "wof:population":196
},
  "geometry": {"coordinates":[79.34240200000001,29.459312],"type":"Point"}
}