{
  "type": "Feature",
  "properties": {
    "iso:country":"IN",
    "ks:ks_name":"Telotanr",
    "ks:ks_pop":317,
    "ks:ks_type":"VILLAGE",
    "ks:ks_uagg_main":0,
    "name:eng_x_preferred":[
        "Telotanr"
    ],
    "wof:name":"Telotanr",
    "wof:placetype":"neighbourhood",
    "wof:population":317
},
  "geometry": {"coordinates":[86.205851,23.78919],"type":"Point"}
}