{
  "type": "Feature",
  "properties": {
    "iso:country":"IN",
    "ks:ks_name":"Bhabanipur",
    "ks:ks_pop":409,
    "ks:ks_type":"VILLAGE",
    "ks:ks_uagg_main":0,
    "name:eng_x_preferred":[
        "Bhabanipur"
    ],
    "wof:name":"Bhabanipur",
    "wof:placetype":"neighbourhood",
    "wof:population":409
},
  "geometry": {"coordinates":[86.901875,23.466837],"type":"Point"}
}