{
  "type": "Feature",
  "properties": {
    "gn:admin1_code":"25.0",
    "gn:admin2_code":"619.0",
    "gn:asciiname":"Vaduvakottamangalam",
    "gn:country_code":"IN",
    "gn:dem":8,
    "gn:feature_class":"P",
    "gn:feature_code":"PPL",
    "gn:name":"Vaduv\u0101kottamangalam",
    "gn:population":0,
    "gn:timezone":"Asia/Kolkata",
    "iso:country":"IN",
    "ks:ks_name":"Kaduvakothamangalam",
    "ks:ks_pop":495,
    "ks:ks_type":"HABITATION",
    "name:eng_x_preferred":[
        "Kaduvakothamangalam"
    ],
    "name:eng_x_variant":[
        "Vaduvakottamangalam"
    ],
    "wof:name":"Kaduvakothamangalam",
    "wof:placetype":"locality",
    "wof:population":495
},
  "geometry": {"coordinates":[79.571832,10.5674],"type":"Point"}
}