{
  "type": "Feature",
  "properties": {
    "iso:country":"IN",
    "ks:ks_name":"Raidingia No 1",
    "ks:ks_pop":353,
    "ks:ks_type":"HABITATION",
    "name:eng_x_preferred":[
        "Raidingia No 1"
    ],
    "wof:name":"Raidingia No 1",
    "wof:placetype":"locality",
    "wof:population":353
},
  "geometry": {"coordinates":[95.189109,27.226185],"type":"Point"}
}