{
  "type": "Feature",
  "properties": {
    "gn:admin1_code":"12.0",
    "gn:admin2_code":"21.0",
    "gn:asciiname":"Bhatiari",
    "gn:country_code":"IN",
    "gn:dem":308,
    "gn:feature_class":"P",
    "gn:feature_code":"PPL",
    "gn:name":"Bhati\u0101ri",
    "gn:population":0,
    "gn:timezone":"Asia/Kolkata",
    "iso:country":"IN",
    "name:ben_x_preferred":[
        "\u09ad\u09be\u099f\u09bf\u09af\u09bc\u09be\u09b0\u09c0"
    ],
    "wof:name":"Bhatiari",
    "wof:placetype":"locality"
},
  "geometry": {"coordinates":[74.71536,32.87827],"type":"Point"}
}