{
  "type": "Feature",
  "properties": {
    "gn:admin1_code":"19.0",
    "gn:admin2_code":"583.0",
    "gn:asciiname":"Bennigeri",
    "gn:country_code":"IN",
    "gn:dem":939,
    "gn:feature_class":"P",
    "gn:feature_code":"PPL",
    "gn:name":"Bennigeri",
    "gn:population":0,
    "gn:timezone":"Asia/Kolkata",
    "iso:country":"IN",
    "ks:ks_name":"Bennegere",
    "ks:ks_pop":176,
    "ks:ks_type":"HABITATION",
    "name:eng_x_preferred":[
        "Bennegere"
    ],
    "name:eng_x_variant":[
        "Bennigeri"
    ],
    "wof:name":"Bennegere",
    "wof:placetype":"locality",
    "wof:population":176
},
  "geometry": {"coordinates":[77.26112500000001,13.292061],"type":"Point"}
}