{
  "type": "Feature",
  "properties": {
    "gn:admin1_code":"12.0",
    "gn:admin2_code":"17.0",
    "gn:asciiname":"Charwari",
    "gn:country_code":"IN",
    "gn:dem":2300,
    "gn:feature_class":"P",
    "gn:feature_code":"PPL",
    "gn:name":"Charw\u0101r\u012b",
    "gn:population":0,
    "gn:timezone":"Asia/Kolkata",
    "iso:country":"IN",
    "wof:name":"Charwari",
    "wof:placetype":"locality"
},
  "geometry": {"coordinates":[75.10229,33.38930999999999],"type":"Point"}
}