{
  "type": "Feature",
  "properties": {
    "iso:country":"IN",
    "ks:ks_name":"Lalji Ka Khera",
    "ks:ks_pop":182,
    "ks:ks_type":"VILLAGE",
    "name:eng_x_preferred":[
        "Lalji Ka Khera"
    ],
    "wof:name":"Lalji Ka Khera",
    "wof:placetype":"locality",
    "wof:population":182
},
  "geometry": {"coordinates":[73.97017099999999,25.327734],"type":"Point"}
}