{
  "type": "Feature",
  "properties": {
    "gn:admin1_code":"19.0",
    "gn:admin2_code":"557",
    "gn:asciiname":"Agarkhed",
    "gn:country_code":"IN",
    "gn:dem":424,
    "gn:feature_class":"P",
    "gn:feature_code":"PPL",
    "gn:name":"Agarkhed",
    "gn:population":0,
    "gn:timezone":"Asia/Kolkata",
    "iso:country":"IN",
    "name:kan_x_preferred":[
        "\u0c85\u0c97\u0cb0\u0c96\u0cc7\u0ca1"
    ],
    "name:vie_x_preferred":[
        "Agarkhed"
    ],
    "wof:name":"Agarkhed",
    "wof:placetype":"locality"
},
  "geometry": {"coordinates":[76.06061,17.3134],"type":"Point"}
}