{
  "type": "Feature",
  "properties": {
    "gn:admin1_code":"25.0",
    "gn:admin2_code":"632.0",
    "gn:asciiname":"Mannar",
    "gn:country_code":"IN",
    "gn:dem":487,
    "gn:feature_class":"P",
    "gn:feature_code":"PPL",
    "gn:name":"Mannar",
    "gn:population":0,
    "gn:timezone":"Asia/Kolkata",
    "iso:country":"IN",
    "name:deu_x_preferred":[
        "Mannar"
    ],
    "name:fas_x_preferred":[
        "\u0645\u0646\u0627\u0631"
    ],
    "name:nld_x_preferred":[
        "Mannar"
    ],
    "name:pol_x_preferred":[
        "Mannar"
    ],
    "wof:name":"Mannar",
    "wof:placetype":"locality"
},
  "geometry": {"coordinates":[76.74077,11.22034],"type":"Point"}
}