{
  "type": "Feature",
  "properties": {
    "gn:admin1_code":"35",
    "gn:admin2_code":"423.0",
    "gn:asciiname":"Akhara",
    "gn:country_code":"IN",
    "gn:dem":372,
    "gn:feature_class":"P",
    "gn:feature_code":"PPL",
    "gn:name":"Akh\u0101ra",
    "gn:population":0,
    "gn:timezone":"Asia/Kolkata",
    "iso:country":"IN",
    "name:ara_x_preferred":[
        "\u0623\u062e\u0627\u0631\u0627"
    ],
    "name:ben_bn_x_preferred":[
        "\u0986\u0996\u09be\u09b0\u09be"
    ],
    "name:ben_in_x_preferred":[
        "\u0986\u0996\u09be\u09b0\u09be"
    ],
    "name:bih_x_preferred":[
        "\u0905\u0916\u093e\u0921\u093c\u093e"
    ],
    "name:guj_x_preferred":[
        "\u0a85\u0a96\u0abe\u0ab0\u0abe"
    ],
    "name:guj_x_variant":[
        "\u0a85\u0a96\u0abe\u0aa1\u0acb"
    ],
    "name:hin_x_preferred":[
        "\u0905\u0916\u093e\u095c\u093e"
    ],
    "name:hin_x_variant":[
        "\u0905\u0916\u093e\u0921\u093c\u093e"
    ],
    "name:hun_x_preferred":[
        "Akhara"
    ],
    "name:kan_x_preferred":[
        "\u0c85\u0c96\u0cbe\u0ca1"
    ],
    "name:kan_x_variant":[
        "\u0c85\u0c96\u0cbe\u0ca1\u0cbe"
    ],
    "name:mal_x_preferred":[
        "\u0d05\u0d16\u0d3e\u0d30"
    ],
    "name:mar_x_preferred":[
        "\u0905\u0916\u093e\u0921\u093e"
    ],
    "name:pan_x_preferred":[
        "\u0a05\u0a16\u0a3e\u0a5c\u0a3e"
    ],
    "name:pol_x_preferred":[
        "Akhara"
    ],
    "name:tam_x_preferred":[
        "\u0b85\u0b95\u0bbe\u0bb0\u0bbe"
    ],
    "name:tel_x_preferred":[
        "\u0c05\u0c16\u0c3e\u0c30\u0c3e"
    ],
    "name:urd_x_preferred":[
        "\u0627\u06a9\u06be\u0627\u0691\u06c1"
    ],
    "name:urd_x_variant":[
        "\u0627\u06a9\u06be\u0627\u0691\u0627"
    ],
    "wof:name":"Akhara",
    "wof:placetype":"locality"
},
  "geometry": {"coordinates":[78.08377,25.07607],"type":"Point"}
}