{
  "type": "Feature",
  "properties": {
    "gn:admin1_code":"35",
    "gn:admin2_code":"423.0",
    "gn:asciiname":"Akhara",
    "gn:country_code":"IN",
    "gn:dem":372,
    "gn:feature_class":"P",
    "gn:feature_code":"PPL",
    "gn:name":"Akh\u0101ra",
    "gn:population":0,
    "gn:timezone":"Asia/Kolkata",
    "iso:country":"IN",
    "name:bih_x_preferred":[
        "\u0905\u0916\u093e\u0921\u093c\u093e"
    ],
    "name:guj_x_preferred":[
        "\u0a85\u0a96\u0abe\u0aa1\u0acb"
    ],
    "name:hin_x_preferred":[
        "\u0905\u0916\u093e\u0921\u093c\u093e"
    ],
    "name:hun_x_preferred":[
        "Akhara"
    ],
    "name:kan_x_preferred":[
        "\u0c85\u0c96\u0cbe\u0ca1\u0cbe"
    ],
    "name:pol_x_preferred":[
        "Akhara"
    ],
    "name:urd_x_preferred":[
        "\u0627\u06a9\u06be\u0627\u0691\u0627"
    ],
    "wof:name":"Akhara",
    "wof:placetype":"locality"
},
  "geometry": {"coordinates":[78.08377,25.07607],"type":"Point"}
}