{
  "type": "Feature",
  "properties": {
    "iso:country":"IN",
    "ks:ks_name":"Srinivasapuram",
    "ks:ks_pop":109,
    "ks:ks_type":"HABITATION",
    "ks:ks_uagg_main":0,
    "name:eng_x_preferred":[
        "Srinivasapuram"
    ],
    "wof:name":"Srinivasapuram",
    "wof:placetype":"neighbourhood",
    "wof:population":109
},
  "geometry": {"coordinates":[79.18974300000001,14.161156],"type":"Point"}
}