{
  "type": "Feature",
  "properties": {
    "iso:country":"IN",
    "ks:ks_name":"Yelagudige",
    "ks:ks_pop":800,
    "ks:ks_type":"VILLAGE",
    "name:eng_x_preferred":[
        "Yelagudige"
    ],
    "wof:name":"Yelagudige",
    "wof:placetype":"locality",
    "wof:population":800
},
  "geometry": {"coordinates":[75.65595500000001,13.220085],"type":"Point"}
}