{
  "type": "Feature",
  "properties": {
    "iso:country":"IN",
    "ks:ks_name":"Kolfalia",
    "ks:ks_pop":602,
    "ks:ks_type":"HABITATION",
    "ks:ks_uagg_main":0,
    "name:eng_x_preferred":[
        "Kolfalia"
    ],
    "wof:name":"Kolfalia",
    "wof:placetype":"neighbourhood",
    "wof:population":602
},
  "geometry": {"coordinates":[72.973111,20.541278],"type":"Point"}
}