{
  "type": "Feature",
  "properties": {
    "iso:country":"IN",
    "ks:ks_name":"East Gogulapalli",
    "ks:ks_pop":1976,
    "ks:ks_type":"HABITATION",
    "name:eng_x_preferred":[
        "East Gogulapalli"
    ],
    "wof:name":"East Gogulapalli",
    "wof:placetype":"locality",
    "wof:population":1976
},
  "geometry": {"coordinates":[80.1074,14.674282],"type":"Point"}
}