{
  "type": "Feature",
  "properties": {
    "gn:admin1_code":"40",
    "gn:admin2_code":"537.0",
    "gn:asciiname":"Lalaguda",
    "gn:cc2":"IN",
    "gn:country_code":"IN",
    "gn:dem":521,
    "gn:feature_class":"P",
    "gn:feature_code":"PPL",
    "gn:name":"L\u0101l\u0101guda",
    "gn:population":0,
    "gn:timezone":"Asia/Kolkata",
    "iso:country":"IN",
    "name:und_x_variant":[
        "Lallaguda",
        "L\u0101l\u0101guda"
    ],
    "name:urd_x_preferred":[
        "\u0644\u0627\u0644\u0627\u06af\u0648\u0688\u0627"
    ],
    "wof:name":"Lalaguda",
    "wof:placetype":"locality"
},
  "geometry": {"coordinates":[78.54056,17.43806],"type":"Point"}
}