{
  "type": "Feature",
  "properties": {
    "iso:country":"IN",
    "ks:ks_name":"Masanaboyapalli",
    "ks:ks_pop":26,
    "ks:ks_type":"HABITATION",
    "name:eng_x_preferred":[
        "Masanaboyapalli"
    ],
    "wof:name":"Masanaboyapalli",
    "wof:placetype":"locality",
    "wof:population":26
},
  "geometry": {"coordinates":[78.75402,14.217685],"type":"Point"}
}