{
  "type": "Feature",
  "properties": {
    "iso:country":"IN",
    "ks:ks_alt_nam":"Bhukya thanda",
    "ks:ks_name":"Bhukya Thanda",
    "ks:ks_pop":170,
    "ks:ks_type":"HABITATION",
    "name:eng_x_preferred":[
        "Bhukya Thanda"
    ],
    "wof:name":"Bhukya Thanda",
    "wof:placetype":"locality",
    "wof:population":170
},
  "geometry": {"coordinates":[79.162575,17.788456],"type":"Point"}
}