{
  "type": "Feature",
  "properties": {
    "gn:admin1_code":"36.0",
    "gn:admin2_code":"149.0",
    "gn:asciiname":"Ganeshpur",
    "gn:country_code":"IN",
    "gn:dem":187,
    "gn:feature_class":"P",
    "gn:feature_code":"PPL",
    "gn:name":"Ganeshpur",
    "gn:population":0,
    "gn:timezone":"Asia/Kolkata",
    "iso:country":"IN",
    "ks:ks_name":"Ganeshpur",
    "ks:ks_type":"VILLAGE",
    "name:ceb_x_preferred":[
        "Ganeshpur"
    ],
    "name:eng_x_preferred":[
        "Ganeshpur"
    ],
    "name:nep_x_preferred":[
        "\u0917\u0923\u0947\u0936\u092a\u0941\u0930"
    ],
    "name:pol_x_preferred":[
        "Ganeshpur"
    ],
    "wof:name":"Ganeshpur",
    "wof:placetype":"locality"
},
  "geometry": {"coordinates":[78.80428499999999,28.331734],"type":"Point"}
}