{
  "type": "Feature",
  "properties": {
    "iso:country":"IN",
    "ks:ks_name":"Kasthuripatti",
    "ks:ks_pop":109,
    "ks:ks_type":"HABITATION",
    "name:eng_x_preferred":[
        "Kasthuripatti"
    ],
    "wof:name":"Kasthuripatti",
    "wof:placetype":"locality",
    "wof:population":109
},
  "geometry": {"coordinates":[78.41534299999999,10.56974],"type":"Point"}
}