{
  "type": "Feature",
  "properties": {
    "iso:country":"IN",
    "ks:ks_name":"Munsi Gheri",
    "ks:ks_pop":2949,
    "ks:ks_type":"VILLAGE",
    "name:eng_x_preferred":[
        "Munsi Gheri"
    ],
    "wof:name":"Munsi Gheri",
    "wof:placetype":"locality",
    "wof:population":2949
},
  "geometry": {"coordinates":[88.735878,22.590539],"type":"Point"}
}