{
  "type": "Feature",
  "properties": {
    "gn:admin1_code":"19.0",
    "gn:admin2_code":"555.0",
    "gn:asciiname":"Khudanpur",
    "gn:country_code":"IN",
    "gn:dem":676,
    "gn:feature_class":"P",
    "gn:feature_code":"PPL",
    "gn:name":"Khud\u0101npur",
    "gn:population":0,
    "gn:timezone":"Asia/Kolkata",
    "iso:country":"IN",
    "wof:name":"Khudanpur",
    "wof:placetype":"locality"
},
  "geometry": {"coordinates":[74.84953,15.68265],"type":"Point"}
}