{
  "type": "Feature",
  "properties": {
    "iso:country":"IN",
    "ks:ks_name":"Talanjaddi",
    "ks:ks_pop":25,
    "ks:ks_type":"HABITATION",
    "name:eng_x_preferred":[
        "Talanjaddi"
    ],
    "wof:name":"Talanjaddi",
    "wof:placetype":"locality",
    "wof:population":25
},
  "geometry": {"coordinates":[74.80613200000001,14.392443],"type":"Point"}
}