{
  "type": "Feature",
  "properties": {
    "gn:admin1_code":"11.0",
    "gn:admin2_code":"31.0",
    "gn:asciiname":"Kurar",
    "gn:country_code":"IN",
    "gn:dem":1054,
    "gn:feature_class":"P",
    "gn:feature_code":"PPL",
    "gn:name":"K\u016br\u0101r",
    "gn:population":0,
    "gn:timezone":"Asia/Kolkata",
    "iso:country":"IN",
    "wof:name":"Kurar",
    "wof:placetype":"locality"
},
  "geometry": {"coordinates":[77.01465999999998,30.85855],"type":"Point"}
}