{
  "type": "Feature",
  "properties": {
    "gn:admin1_code":"11.0",
    "gn:admin2_code":"31.0",
    "gn:asciiname":"Kurar",
    "gn:country_code":"IN",
    "gn:dem":1054,
    "gn:feature_class":"P",
    "gn:feature_code":"PPL",
    "gn:name":"K\u016br\u0101r",
    "gn:population":0,
    "gn:timezone":"Asia/Kolkata",
    "iso:country":"IN",
    "name:ara_x_preferred":[
        "\u0643\u0648\u0631\u0627\u0631"
    ],
    "name:ben_bn_x_preferred":[
        "\u0995\u09c1\u09b0\u09be\u09b0"
    ],
    "name:ben_in_x_preferred":[
        "\u0995\u09c1\u09dc\u09be\u09b0"
    ],
    "name:guj_x_preferred":[
        "\u0a95\u0ac1\u0ab0\u0abe\u0ab0"
    ],
    "name:hin_x_preferred":[
        "\u0915\u0941\u0930\u093e\u0930"
    ],
    "name:kan_x_preferred":[
        "\u0c95\u0cc1\u0cb0\u0cbe\u0cb0\u0ccd"
    ],
    "name:mal_x_preferred":[
        "\u0d15\u0d41\u0d30\u0d3e\u0d30\u0d4d\u200d"
    ],
    "name:mar_x_preferred":[
        "\u0915\u0941\u0930\u093e\u0930"
    ],
    "name:pan_x_preferred":[
        "\u0a15\u0a41\u0a30\u0a3e\u0a30"
    ],
    "name:tam_x_preferred":[
        "\u0b95\u0bc1\u0bb0\u0bbe\u0bb0\u0bcd"
    ],
    "name:tel_x_preferred":[
        "\u0c15\u0c41\u0c30\u0c3e\u0c30\u0c4d"
    ],
    "name:urd_x_preferred":[
        "\u06a9\u064f\u0631\u0627\u0631"
    ],
    "wof:name":"Kurar",
    "wof:placetype":"locality"
},
  "geometry": {"coordinates":[77.01465999999998,30.85855],"type":"Point"}
}