{
  "type": "Feature",
  "properties": {
    "iso:country":"IN",
    "ks:ks_name":"Banali",
    "ks:ks_pop":126,
    "ks:ks_type":"HABITATION",
    "name:eng_x_preferred":[
        "Banali"
    ],
    "wof:name":"Banali",
    "wof:placetype":"locality",
    "wof:population":126
},
  "geometry": {"coordinates":[74.8215,13.676994],"type":"Point"}
}