{
  "type": "Feature",
  "properties": {
    "iso:country":"IN",
    "ks:ks_name":"Apaiwadi",
    "ks:ks_pop":265,
    "ks:ks_type":"HABITATION",
    "name:eng_x_preferred":[
        "Apaiwadi"
    ],
    "wof:name":"Apaiwadi",
    "wof:placetype":"locality",
    "wof:population":265
},
  "geometry": {"coordinates":[73.430322,16.224195],"type":"Point"}
}