{
  "type": "Feature",
  "properties": {
    "gn:admin1_code":"36",
    "gn:admin2_code":"197.0",
    "gn:asciiname":"Mallahtola",
    "gn:country_code":"IN",
    "gn:dem":81,
    "gn:feature_class":"P",
    "gn:feature_code":"PPL",
    "gn:name":"Mall\u0101htola",
    "gn:population":0,
    "gn:timezone":"Asia/Kolkata",
    "iso:country":"IN",
    "wof:name":"Mallahtola",
    "wof:placetype":"neighbourhood"
},
  "geometry": {"coordinates":[83.17778,25.36441],"type":"Point"}
}