{
  "type": "Feature",
  "properties": {
    "iso:country":"IN",
    "ks:ks_name":"Chamar Tola",
    "ks:ks_pop":569,
    "ks:ks_type":"HABITATION",
    "ks:ks_uagg_main":0,
    "name:eng_x_preferred":[
        "Chamar Tola"
    ],
    "wof:name":"Chamar Tola",
    "wof:placetype":"neighbourhood",
    "wof:population":569
},
  "geometry": {"coordinates":[84.35216200000001,25.991218],"type":"Point"}
}