{
  "type": "Feature",
  "properties": {
    "gn:admin1_code":"38",
    "gn:admin2_code":"358.0",
    "gn:asciiname":"Chandarpur",
    "gn:country_code":"IN",
    "gn:dem":174,
    "gn:feature_class":"P",
    "gn:feature_code":"PPL",
    "gn:name":"Chandarpur",
    "gn:population":0,
    "gn:timezone":"Asia/Kolkata",
    "iso:country":"IN",
    "ks:ks_name":"Chandarpur",
    "ks:ks_pop":351,
    "ks:ks_type":"VILLAGE",
    "ks:ks_uagg_main":0,
    "name:eng_x_preferred":[
        "Chandarpur"
    ],
    "wof:name":"Chandarpur",
    "wof:placetype":"neighbourhood",
    "wof:population":351
},
  "geometry": {"coordinates":[83.98208099999999,24.466608],"type":"Point"}
}