{
  "type": "Feature",
  "properties": {
    "gn:admin1_code":"36.0",
    "gn:admin2_code":"171.0",
    "gn:asciiname":"Anandpur",
    "gn:country_code":"IN",
    "gn:dem":124,
    "gn:feature_class":"P",
    "gn:feature_code":"PPL",
    "gn:name":"\u0100nandpur",
    "gn:population":0,
    "gn:timezone":"Asia/Kolkata",
    "iso:country":"IN",
    "wof:name":"Anandpur",
    "wof:placetype":"locality"
},
  "geometry": {"coordinates":[81.02484,25.26229],"type":"Point"}
}