{
  "type": "Feature",
  "properties": {
    "iso:country":"IN",
    "ks:ks_name":"Updhi",
    "ks:ks_type":"VILLAGE",
    "name:eng_x_preferred":[
        "Updhi"
    ],
    "wof:name":"Updhi",
    "wof:placetype":"locality"
},
  "geometry": {"coordinates":[83.271041,25.617547],"type":"Point"}
}