{
  "type": "Feature",
  "properties": {
    "iso:country":"IN",
    "ks:ks_name":"Paschim Tola",
    "ks:ks_pop":340,
    "ks:ks_type":"HABITATION",
    "name:eng_x_preferred":[
        "Paschim Tola"
    ],
    "wof:name":"Paschim Tola",
    "wof:placetype":"locality",
    "wof:population":340
},
  "geometry": {"coordinates":[86.85779599999999,25.157446],"type":"Point"}
}