{
  "type": "Feature",
  "properties": {
    "iso:country":"IN",
    "ks:ks_name":"Jharapada",
    "ks:ks_pop":57,
    "ks:ks_type":"HABITATION",
    "name:eng_x_preferred":[
        "Jharapada"
    ],
    "wof:name":"Jharapada",
    "wof:placetype":"locality",
    "wof:population":57
},
  "geometry": {"coordinates":[84.451733,22.278835],"type":"Point"}
}