{
  "type": "Feature",
  "properties": {
    "gn:admin1_code":"11",
    "gn:admin2_code":"32.0",
    "gn:asciiname":"Barwa",
    "gn:country_code":"IN",
    "gn:dem":1569,
    "gn:feature_class":"P",
    "gn:feature_code":"PPL",
    "gn:name":"Barwa",
    "gn:population":0,
    "gn:timezone":"Asia/Kolkata",
    "iso:country":"IN",
    "name:deu_x_preferred":[
        "Barwa"
    ],
    "name:slv_x_preferred":[
        "Barwa"
    ],
    "wof:name":"Barwa",
    "wof:placetype":"locality"
},
  "geometry": {"coordinates":[77.54883000000002,30.75572],"type":"Point"}
}