{
  "type": "Feature",
  "properties": {
    "iso:country":"IN",
    "ks:ks_name":"M Ambel",
    "ks:ks_pop":67,
    "ks:ks_type":"HABITATION",
    "name:eng_x_preferred":[
        "M Ambel"
    ],
    "wof:name":"M Ambel",
    "wof:placetype":"locality",
    "wof:population":67
},
  "geometry": {"coordinates":[82.71083,18.433316],"type":"Point"}
}