{
  "type": "Feature",
  "properties": {
    "iso:country":"IN",
    "ks:ks_name":"Lal Dharee Purwa",
    "ks:ks_pop":78,
    "ks:ks_type":"HABITATION",
    "name:eng_x_preferred":[
        "Lal Dharee Purwa"
    ],
    "wof:name":"Lal Dharee Purwa",
    "wof:placetype":"locality",
    "wof:population":78
},
  "geometry": {"coordinates":[81.59939,27.665635],"type":"Point"}
}