{
  "type": "Feature",
  "properties": {
    "gn:admin1_code":"21.0",
    "gn:admin2_code":"396.0",
    "gn:asciiname":"Konnidi",
    "gn:country_code":"IN",
    "gn:dem":358,
    "gn:feature_class":"P",
    "gn:feature_code":"PPL",
    "gn:name":"Konnidi",
    "gn:population":0,
    "gn:timezone":"Asia/Kolkata",
    "iso:country":"IN",
    "wof:name":"Konnidi",
    "wof:placetype":"neighbourhood"
},
  "geometry": {"coordinates":[83.47056000000001,19.41412],"type":"Point"}
}