{
  "type": "Feature",
  "properties": {
    "gn:admin1_code":"12.0",
    "gn:admin2_code":"006",
    "gn:asciiname":"Neako",
    "gn:country_code":"IN",
    "gn:dem":1567,
    "gn:feature_class":"P",
    "gn:feature_code":"PPL",
    "gn:name":"Neako",
    "gn:population":0,
    "gn:timezone":"Asia/Kolkata",
    "iso:country":"IN",
    "name:hrv_x_preferred":[
        "Neako"
    ],
    "name:und_x_variant":[
        "Neakka",
        "Lambi B\u0101ri"
    ],
    "wof:name":"Neako",
    "wof:placetype":"locality"
},
  "geometry": {"coordinates":[74.20206,33.42336],"type":"Point"}
}