{
  "type": "Feature",
  "properties": {
    "iso:country":"IN",
    "ks:ks_name":"Chak Mehsi",
    "ks:ks_pop":2252,
    "ks:ks_type":"VILLAGE",
    "name:eng_x_preferred":[
        "Chak Mehsi"
    ],
    "wof:name":"Chak Mehsi",
    "wof:placetype":"locality",
    "wof:population":2252
},
  "geometry": {"coordinates":[85.402783,26.059437],"type":"Point"}
}