{
  "type": "Feature",
  "properties": {
    "gn:admin1_code":"39.0",
    "gn:admin2_code":"64.0",
    "gn:asciiname":"Tharar",
    "gn:country_code":"IN",
    "gn:dem":1761,
    "gn:feature_class":"P",
    "gn:feature_code":"PPL",
    "gn:name":"Tharar",
    "gn:population":0,
    "gn:timezone":"Asia/Kolkata",
    "iso:country":"IN",
    "ks:ks_name":"Tharar",
    "ks:ks_type":"VILLAGE",
    "name:eng_x_preferred":[
        "Tharar"
    ],
    "wof:name":"Tharar",
    "wof:placetype":"locality"
},
  "geometry": {"coordinates":[79.440006,29.545128],"type":"Point"}
}