{
  "type": "Feature",
  "properties": {
    "iso:country":"IN",
    "ks:ks_alt_nam":"Pallewaya F.V.",
    "ks:ks_name":"Pallewaya F.v.",
    "ks:ks_pop":311,
    "ks:ks_type":"HABITATION",
    "name:eng_x_preferred":[
        "Pallewaya F.v."
    ],
    "wof:name":"Pallewaya F.v.",
    "wof:placetype":"locality",
    "wof:population":311
},
  "geometry": {"coordinates":[81.163383,19.107856],"type":"Point"}
}