{
  "type": "Feature",
  "properties": {
    "iso:country":"IN",
    "ks:ks_name":"Kadaravalli",
    "ks:ks_pop":20,
    "ks:ks_type":"HABITATION",
    "name:eng_x_preferred":[
        "Kadaravalli"
    ],
    "wof:name":"Kadaravalli",
    "wof:placetype":"locality",
    "wof:population":20
},
  "geometry": {"coordinates":[75.333568,13.450304],"type":"Point"}
}