{
  "type": "Feature",
  "properties": {
    "gn:admin1_code":"39.0",
    "gn:admin2_code":"63.0",
    "gn:asciiname":"Chhatiya",
    "gn:country_code":"IN",
    "gn:dem":1273,
    "gn:feature_class":"P",
    "gn:feature_code":"PPL",
    "gn:name":"Chhatiya",
    "gn:population":0,
    "gn:timezone":"Asia/Kolkata",
    "iso:country":"IN",
    "wof:name":"Chhatiya",
    "wof:placetype":"locality"
},
  "geometry": {"coordinates":[79.62097,29.94498],"type":"Point"}
}