{
  "type": "Feature",
  "properties": {
    "iso:country":"IN",
    "ks:ks_name":"Sajawar",
    "ks:ks_pop":896,
    "ks:ks_type":"VILLAGE",
    "name:eng_x_preferred":[
        "Sajawar"
    ],
    "wof:name":"Sajawar",
    "wof:placetype":"locality",
    "wof:population":896
},
  "geometry": {"coordinates":[82.29021899999999,23.895967],"type":"Point"}
}