{
  "type": "Feature",
  "properties": {
    "iso:country":"IN",
    "ks:ks_name":"Dhamangaon",
    "ks:ks_pop":723,
    "ks:ks_type":"HABITATION",
    "name:eng_x_preferred":[
        "Dhamangaon"
    ],
    "wof:name":"Dhamangaon",
    "wof:placetype":"locality",
    "wof:population":723
},
  "geometry": {"coordinates":[78.839249,20.832844],"type":"Point"}
}