{
  "type": "Feature",
  "properties": {
    "iso:country":"IN",
    "ks:ks_alt_nam":"Halanga Char N.C.",
    "ks:ks_name":"Halanga Char N.c.",
    "ks:ks_pop":167,
    "ks:ks_type":"HABITATION",
    "name:eng_x_preferred":[
        "Halanga Char N.c."
    ],
    "wof:name":"Halanga Char N.c.",
    "wof:placetype":"locality",
    "wof:population":167
},
  "geometry": {"coordinates":[90.40808800000001,26.182619],"type":"Point"}
}