{
  "type": "Feature",
  "properties": {
    "gn:admin1_code":"2.0",
    "gn:admin2_code":"554.0",
    "gn:asciiname":"Marimanda",
    "gn:country_code":"IN",
    "gn:dem":105,
    "gn:feature_class":"P",
    "gn:feature_code":"PPL",
    "gn:name":"Marimanda",
    "gn:population":0,
    "gn:timezone":"Asia/Kolkata",
    "iso:country":"IN",
    "ks:ks_name":"Marrimanda",
    "ks:ks_pop":1097,
    "ks:ks_type":"HABITATION",
    "ks:ks_uagg_main":0,
    "name:eng_x_preferred":[
        "Marrimanda"
    ],
    "wof:name":"Marrimanda",
    "wof:placetype":"neighbourhood",
    "wof:population":1097
},
  "geometry": {"coordinates":[79.552744,13.608791],"type":"Point"}
}