{
  "type": "Feature",
  "properties": {
    "gn:admin1_code":"11.0",
    "gn:admin2_code":"33.0",
    "gn:asciiname":"Lana Bagta",
    "gn:country_code":"IN",
    "gn:dem":2921,
    "gn:feature_class":"P",
    "gn:feature_code":"PPL",
    "gn:name":"L\u0101na B\u0101gta",
    "gn:population":0,
    "gn:timezone":"Asia/Kolkata",
    "iso:country":"IN",
    "wof:name":"Lana Bagta",
    "wof:placetype":"locality"
},
  "geometry": {"coordinates":[77.49258,30.88778],"type":"Point"}
}