{
  "type": "Feature",
  "properties": {
    "iso:country":"IN",
    "ks:ks_name":"Gairi Bash",
    "ks:ks_pop":680,
    "ks:ks_type":"HABITATION",
    "name:eng_x_preferred":[
        "Gairi Bash"
    ],
    "wof:name":"Gairi Bash",
    "wof:placetype":"locality",
    "wof:population":680
},
  "geometry": {"coordinates":[88.868843,27.027478],"type":"Point"}
}