{
  "type": "Feature",
  "properties": {
    "gn:admin1_code":"16.0",
    "gn:admin2_code":"528.0",
    "gn:asciiname":"Kherdi",
    "gn:country_code":"IN",
    "gn:dem":184,
    "gn:feature_class":"P",
    "gn:feature_code":"PPL",
    "gn:name":"Kherdi",
    "gn:population":0,
    "gn:timezone":"Asia/Kolkata",
    "iso:country":"IN",
    "name:ben_x_preferred":[
        "\u0996\u09c7\u09b0\u09a6\u09bf"
    ],
    "name:bpy_x_preferred":[
        "\u0996\u09c7\u09b0\u09a6\u09bf"
    ],
    "name:ita_x_preferred":[
        "Kherdi"
    ],
    "name:msa_x_preferred":[
        "Kherdi"
    ],
    "name:new_x_preferred":[
        "\u0916\u0947\u0930\u094d\u0926\u0940"
    ],
    "name:nld_x_preferred":[
        "Kherdi"
    ],
    "name:por_x_preferred":[
        "Kherdi"
    ],
    "name:urd_x_preferred":[
        "\u06a9\u06be\u06cc\u0631\u0688\u06cc"
    ],
    "name:vie_x_preferred":[
        "Kherdi"
    ],
    "name:zho_x_preferred":[
        "\u51ef\u5c14\u8fea"
    ],
    "wof:name":"Kherdi",
    "wof:placetype":"locality"
},
  "geometry": {"coordinates":[73.27068,17.76144],"type":"Point"}
}