{
  "type": "Feature",
  "properties": {
    "gn:admin1_code":"16.0",
    "gn:admin2_code":"528.0",
    "gn:asciiname":"Kherdi",
    "gn:country_code":"IN",
    "gn:dem":184,
    "gn:feature_class":"P",
    "gn:feature_code":"PPL",
    "gn:name":"Kherdi",
    "gn:population":0,
    "gn:timezone":"Asia/Kolkata",
    "iso:country":"IN",
    "wof:name":"Kherdi",
    "wof:placetype":"locality"
},
  "geometry": {"coordinates":[73.27068,17.76144],"type":"Point"}
}