{
  "type": "Feature",
  "properties": {
    "gn:admin1_code":"37",
    "gn:admin2_code":"406.0",
    "gn:asciiname":"Tulsikapa",
    "gn:country_code":"IN",
    "gn:dem":296,
    "gn:feature_class":"P",
    "gn:feature_code":"PPL",
    "gn:name":"Tuls\u012bk\u0101pa",
    "gn:population":0,
    "gn:timezone":"Asia/Kolkata",
    "iso:country":"IN",
    "ks:ks_alt_nam":"TULSI KAPA",
    "ks:ks_name":"Tulsi Kapa",
    "ks:ks_pop":9,
    "ks:ks_type":"HABITATION",
    "name:eng_x_preferred":[
        "Tulsi Kapa"
    ],
    "name:eng_x_variant":[
        "Tulsikapa"
    ],
    "wof:name":"Tulsi Kapa",
    "wof:placetype":"locality",
    "wof:population":9
},
  "geometry": {"coordinates":[81.595387,22.060184],"type":"Point"}
}