{
  "type": "Feature",
  "properties": {
    "gn:admin1_code":"37",
    "gn:admin2_code":"406.0",
    "gn:asciiname":"Tulsikapa",
    "gn:country_code":"IN",
    "gn:dem":296,
    "gn:feature_class":"P",
    "gn:feature_code":"PPL",
    "gn:name":"Tuls\u012bk\u0101pa",
    "gn:population":0,
    "gn:timezone":"Asia/Kolkata",
    "iso:country":"IN",
    "wof:name":"Tulsikapa",
    "wof:placetype":"locality"
},
  "geometry": {"coordinates":[81.59551999999999,22.06026],"type":"Point"}
}