{
  "type": "Feature",
  "properties": {
    "gn:admin1_code":"35.0",
    "gn:admin2_code":"433",
    "gn:asciiname":"Shri Chaturbhuj",
    "gn:country_code":"IN",
    "gn:dem":440,
    "gn:feature_class":"P",
    "gn:feature_code":"PPL",
    "gn:name":"Shri Chaturbhuj",
    "gn:population":0,
    "gn:timezone":"Asia/Kolkata",
    "iso:country":"IN",
    "wof:name":"Shri Chaturbhuj",
    "wof:placetype":"locality"
},
  "geometry": {"coordinates":[75.67144,24.67451],"type":"Point"}
}