{
  "type": "Feature",
  "properties": {
    "gn:admin1_code":"19.0",
    "gn:admin2_code":"574.0",
    "gn:asciiname":"Timmalapura",
    "gn:country_code":"IN",
    "gn:dem":902,
    "gn:feature_class":"P",
    "gn:feature_code":"PPL",
    "gn:name":"Timmalapura",
    "gn:population":0,
    "gn:timezone":"Asia/Kolkata",
    "iso:country":"IN",
    "name:tat_x_preferred":[
        "\u0422\u0438\u043c\u0430\u043b\u043b\u0430\u043f\u0443\u0440\u0430"
    ],
    "wof:name":"Timmalapura",
    "wof:placetype":"locality"
},
  "geometry": {"coordinates":[76.31539000000002,12.99771],"type":"Point"}
}