{
  "type": "Feature",
  "properties": {
    "gn:admin1_code":"16.0",
    "gn:admin2_code":"499.0",
    "gn:asciiname":"Aklud",
    "gn:country_code":"IN",
    "gn:dem":208,
    "gn:feature_class":"P",
    "gn:feature_code":"PPL",
    "gn:name":"Aklud",
    "gn:population":0,
    "gn:timezone":"Asia/Kolkata",
    "iso:country":"IN",
    "wof:name":"Aklud",
    "wof:placetype":"locality"
},
  "geometry": {"coordinates":[75.78693,21.0754],"type":"Point"}
}