{
  "type": "Feature",
  "properties": {
    "iso:country":"IN",
    "ks:ks_name":"Murku",
    "ks:ks_pop":599,
    "ks:ks_type":"VILLAGE",
    "name:eng_x_preferred":[
        "Murku"
    ],
    "wof:name":"Murku",
    "wof:placetype":"locality",
    "wof:population":599
},
  "geometry": {"coordinates":[87.013514,22.774453],"type":"Point"}
}