{
  "type": "Feature",
  "properties": {
    "gn:admin1_code":"39",
    "gn:admin2_code":"61.0",
    "gn:asciiname":"Airoli",
    "gn:country_code":"IN",
    "gn:dem":896,
    "gn:feature_class":"P",
    "gn:feature_code":"PPL",
    "gn:name":"Airoli",
    "gn:population":0,
    "gn:timezone":"Asia/Kolkata",
    "iso:country":"IN",
    "name:ara_x_preferred":[
        "\u0623\u064a\u0631\u0648\u0644\u064a"
    ],
    "name:ben_bn_x_preferred":[
        "\u0986\u0987\u09b0\u09cb\u09b2\u09bf"
    ],
    "name:ben_in_x_preferred":[
        "\u0986\u0987\u09b0\u09cb\u09b2\u09bf"
    ],
    "name:ceb_x_preferred":[
        "Airoli"
    ],
    "name:fas_x_preferred":[
        "\u0627\u06cc\u0631\u0648\u0644\u06cc"
    ],
    "name:guj_x_preferred":[
        "\u0a8f\u0ab0\u0acb\u0ab2\u0ac0"
    ],
    "name:hin_x_preferred":[
        "\u090f\u092f\u0930\u094b\u0932\u0940"
    ],
    "name:kan_x_preferred":[
        "\u0c90\u0cb0\u0ccb\u0cb2\u0cbf"
    ],
    "name:mal_x_preferred":[
        "\u0d0e\u0d2f\u0d4d"
    ],
    "name:mar_x_preferred":[
        "\u0910\u0930\u094b\u0932\u0940"
    ],
    "name:pan_x_preferred":[
        "\u0a10\u0a30\u0a4c\u0a32\u0a40"
    ],
    "name:swe_x_preferred":[
        "Airoli"
    ],
    "name:tam_x_preferred":[
        "\u0b90\u0bb0\u0bcb\u0bb2\u0bbf"
    ],
    "name:tel_x_preferred":[
        "\u0c10\u0c30\u0c4b\u0c32\u0c3f"
    ],
    "name:urd_x_preferred":[
        "\u0627\u06cc\u0631\u0648\u0644\u06cc"
    ],
    "wof:name":"Airoli",
    "wof:placetype":"locality"
},
  "geometry": {"coordinates":[78.44123,29.91805],"type":"Point"}
}