{
  "type": "Feature",
  "properties": {
    "gn:admin1_code":"39",
    "gn:admin2_code":"61.0",
    "gn:asciiname":"Airoli",
    "gn:country_code":"IN",
    "gn:dem":896,
    "gn:feature_class":"P",
    "gn:feature_code":"PPL",
    "gn:name":"Airoli",
    "gn:population":0,
    "gn:timezone":"Asia/Kolkata",
    "iso:country":"IN",
    "name:ceb_x_preferred":[
        "Airoli"
    ],
    "name:fas_x_preferred":[
        "\u0627\u06cc\u0631\u0648\u0644\u06cc"
    ],
    "name:mar_x_preferred":[
        "\u0910\u0930\u094b\u0932\u0940"
    ],
    "name:swe_x_preferred":[
        "Airoli"
    ],
    "name:urd_x_preferred":[
        "\u0627\u06cc\u0631\u0648\u0644\u06cc"
    ],
    "wof:name":"Airoli",
    "wof:placetype":"locality"
},
  "geometry": {"coordinates":[78.44123,29.91805],"type":"Point"}
}