{
  "type": "Feature",
  "properties": {
    "iso:country":"IN",
    "ks:ks_name":"Jawardi",
    "ks:ks_pop":1113,
    "ks:ks_type":"VILLAGE",
    "ks:ks_uagg_main":0,
    "name:eng_x_preferred":[
        "Jawardi"
    ],
    "wof:name":"Jawardi",
    "wof:placetype":"neighbourhood",
    "wof:population":1113
},
  "geometry": {"coordinates":[91.344064,26.441366],"type":"Point"}
}