{
  "type": "Feature",
  "properties": {
    "gn:admin1_code":"25.0",
    "gn:admin2_code":"631.0",
    "gn:asciiname":"Periyapanamutlu",
    "gn:country_code":"IN",
    "gn:dem":522,
    "gn:feature_class":"P",
    "gn:feature_code":"PPL",
    "gn:name":"Periyapanamutlu",
    "gn:population":0,
    "gn:timezone":"Asia/Kolkata",
    "iso:country":"IN",
    "wof:name":"Periyapanamutlu",
    "wof:placetype":"locality"
},
  "geometry": {"coordinates":[78.26573,12.49716],"type":"Point"}
}