{
  "type": "Feature",
  "properties": {
    "gn:admin1_code":"37.0",
    "gn:admin2_code":"413.0",
    "gn:asciiname":"Dabena",
    "gn:country_code":"IN",
    "gn:dem":412,
    "gn:feature_class":"P",
    "gn:feature_code":"PPL",
    "gn:name":"Dabena",
    "gn:population":0,
    "gn:timezone":"Asia/Kolkata",
    "iso:country":"IN",
    "wof:name":"Dabena",
    "wof:placetype":"locality"
},
  "geometry": {"coordinates":[81.33234,20.32477],"type":"Point"}
}