{
  "type": "Feature",
  "properties": {
    "gn:admin1_code":"34.0",
    "gn:admin2_code":"240.0",
    "gn:asciiname":"Mainpura",
    "gn:country_code":"IN",
    "gn:dem":90,
    "gn:feature_class":"P",
    "gn:feature_code":"PPL",
    "gn:name":"Mainpura",
    "gn:population":0,
    "gn:timezone":"Asia/Kolkata",
    "iso:country":"IN",
    "ks:ks_name":"Mainpura",
    "ks:ks_pop":3061,
    "ks:ks_type":"VILLAGE",
    "name:eng_x_preferred":[
        "Mainpura"
    ],
    "wof:name":"Mainpura",
    "wof:placetype":"locality",
    "wof:population":3061
},
  "geometry": {"coordinates":[84.48412500000001,25.149875],"type":"Point"}
}