{
  "type": "Feature",
  "properties": {
    "iso:country":"IN",
    "ks:ks_name":"Dor",
    "ks:ks_pop":558,
    "ks:ks_type":"HABITATION",
    "name:eng_x_preferred":[
        "Dor"
    ],
    "wof:name":"Dor",
    "wof:placetype":"locality",
    "wof:population":558
},
  "geometry": {"coordinates":[74.73545799999999,24.036558],"type":"Point"}
}