{
  "type": "Feature",
  "properties": {
    "iso:country":"IN",
    "ks:ks_name":"Anulia",
    "ks:ks_pop":4477,
    "ks:ks_type":"VILLAGE",
    "ks:ks_uagg_main":0,
    "name:eng_x_preferred":[
        "Anulia"
    ],
    "wof:name":"Anulia",
    "wof:placetype":"neighbourhood",
    "wof:population":4477
},
  "geometry": {"coordinates":[88.547101,23.15849],"type":"Point"}
}