{
  "type": "Feature",
  "properties": {
    "iso:country":"IN",
    "ks:ks_name":"Dungari",
    "ks:ks_pop":210,
    "ks:ks_type":"HABITATION",
    "name:eng_x_preferred":[
        "Dungari"
    ],
    "wof:name":"Dungari",
    "wof:placetype":"locality",
    "wof:population":210
},
  "geometry": {"coordinates":[79.154853,29.746432],"type":"Point"}
}