{
  "type": "Feature",
  "properties": {
    "gn:admin1_code":"21.0",
    "gn:admin2_code":"396.0",
    "gn:asciiname":"Barikipadar",
    "gn:country_code":"IN",
    "gn:dem":465,
    "gn:feature_class":"P",
    "gn:feature_code":"PPL",
    "gn:name":"Barikipadar",
    "gn:population":0,
    "gn:timezone":"Asia/Kolkata",
    "iso:country":"IN",
    "ks:ks_alt_nam":"Barikipadar",
    "ks:ks_name":"Barikapadar",
    "ks:ks_pop":0,
    "ks:ks_type":"VILLAGE",
    "name:eng_x_preferred":[
        "Barikapadar"
    ],
    "name:eng_x_variant":[
        "Barikipadar"
    ],
    "wof:name":"Barikapadar",
    "wof:placetype":"locality",
    "wof:population":0
},
  "geometry": {"coordinates":[83.635603,19.438468],"type":"Point"}
}