{
  "type": "Feature",
  "properties": {
    "gn:admin1_code":"21.0",
    "gn:admin2_code":"396.0",
    "gn:asciiname":"Barikipadar",
    "gn:country_code":"IN",
    "gn:dem":465,
    "gn:feature_class":"P",
    "gn:feature_code":"PPL",
    "gn:name":"Barikipadar",
    "gn:population":0,
    "gn:timezone":"Asia/Kolkata",
    "iso:country":"IN",
    "wof:name":"Barikipadar",
    "wof:placetype":"locality"
},
  "geometry": {"coordinates":[83.6356,19.43847],"type":"Point"}
}