{
  "type": "Feature",
  "properties": {
    "iso:country":"IN",
    "ks:ks_name":"Nepur",
    "ks:ks_pop":1501,
    "ks:ks_type":"VILLAGE",
    "ks:ks_uagg_main":0,
    "name:eng_x_preferred":[
        "Nepur"
    ],
    "wof:name":"Nepur",
    "wof:placetype":"neighbourhood",
    "wof:population":1501
},
  "geometry": {"coordinates":[86.21446899999999,20.255343],"type":"Point"}
}