{
  "type": "Feature",
  "properties": {
    "gn:admin1_code":"13.0",
    "gn:admin2_code":"594.0",
    "gn:asciiname":"Vettalapara",
    "gn:country_code":"IN",
    "gn:dem":68,
    "gn:feature_class":"P",
    "gn:feature_code":"PPL",
    "gn:name":"Vettalap\u0101ra",
    "gn:population":0,
    "gn:timezone":"Asia/Kolkata",
    "iso:country":"IN",
    "ks:ks_name":"Vettilapara",
    "ks:ks_pop":265,
    "ks:ks_type":"HABITATION",
    "name:eng_x_preferred":[
        "Vettilapara"
    ],
    "name:eng_x_variant":[
        "Vettalapara"
    ],
    "wof:name":"Vettilapara",
    "wof:placetype":"locality",
    "wof:population":265
},
  "geometry": {"coordinates":[76.512539,10.292265],"type":"Point"}
}