{
  "type": "Feature",
  "properties": {
    "iso:country":"IN",
    "ks:ks_name":"Riyar Malla",
    "ks:ks_pop":274,
    "ks:ks_type":"VILLAGE",
    "name:eng_x_preferred":[
        "Riyar Malla"
    ],
    "wof:name":"Riyar Malla",
    "wof:placetype":"locality",
    "wof:population":274
},
  "geometry": {"coordinates":[79.29747500000001,29.446077],"type":"Point"}
}