{
  "type": "Feature",
  "properties": {
    "iso:country":"IN",
    "ks:ks_name":"Bardinga",
    "ks:ks_pop":575,
    "ks:ks_type":"VILLAGE",
    "ks:ks_uagg_main":0,
    "name:eng_x_preferred":[
        "Bardinga"
    ],
    "wof:name":"Bardinga",
    "wof:placetype":"neighbourhood",
    "wof:population":575
},
  "geometry": {"coordinates":[87.679389,25.841441],"type":"Point"}
}