{
  "type": "Feature",
  "properties": {
    "iso:country":"IN",
    "ks:ks_name":"Dixit Purwa",
    "ks:ks_pop":81,
    "ks:ks_type":"HABITATION",
    "name:eng_x_preferred":[
        "Dixit Purwa"
    ],
    "wof:name":"Dixit Purwa",
    "wof:placetype":"locality",
    "wof:population":81
},
  "geometry": {"coordinates":[81.469323,27.528594],"type":"Point"}
}