{
  "type": "Feature",
  "properties": {
    "iso:country":"IN",
    "ks:ks_name":"Manjhipara",
    "ks:ks_pop":403,
    "ks:ks_type":"HABITATION",
    "name:eng_x_preferred":[
        "Manjhipara"
    ],
    "wof:name":"Manjhipara",
    "wof:placetype":"locality",
    "wof:population":403
},
  "geometry": {"coordinates":[81.584614,19.076927],"type":"Point"}
}