{
  "type": "Feature",
  "properties": {
    "iso:country":"IN",
    "ks:ks_name":"Madhopur Musharwa",
    "ks:ks_pop":760,
    "ks:ks_type":"VILLAGE",
    "ks:ks_uagg_main":0,
    "name:eng_x_preferred":[
        "Madhopur Musharwa"
    ],
    "wof:name":"Madhopur Musharwa",
    "wof:placetype":"neighbourhood",
    "wof:population":760
},
  "geometry": {"coordinates":[85.473478,26.718349],"type":"Point"}
}