{
  "type": "Feature",
  "properties": {
    "gn:admin1_code":"25.0",
    "gn:admin2_code":"616.0",
    "gn:asciiname":"Cholamadevi",
    "gn:country_code":"IN",
    "gn:dem":29,
    "gn:feature_class":"P",
    "gn:feature_code":"PPL",
    "gn:name":"Cholam\u0101devi",
    "gn:population":0,
    "gn:timezone":"Asia/Kolkata",
    "iso:country":"IN",
    "name:tam_x_preferred":[
        "\u0b9a\u0bcb\u0bb4\u0bae\u0bbe\u0ba4\u0bc7\u0bb5\u0bbf"
    ],
    "wof:name":"Cholamadevi",
    "wof:placetype":"locality"
},
  "geometry": {"coordinates":[79.39912,11.13228],"type":"Point"}
}