{
  "type": "Feature",
  "properties": {
    "gn:admin1_code":"34.0",
    "gn:admin2_code":"229.0",
    "gn:asciiname":"Bajra Chak",
    "gn:country_code":"IN",
    "gn:dem":66,
    "gn:feature_class":"P",
    "gn:feature_code":"PPL",
    "gn:name":"Bajra Chak",
    "gn:population":0,
    "gn:timezone":"Asia/Kolkata",
    "iso:country":"IN",
    "ks:ks_name":"Bajra Chak",
    "ks:ks_pop":1378,
    "ks:ks_type":"HABITATION",
    "name:eng_x_preferred":[
        "Bajra Chak"
    ],
    "wof:name":"Bajra Chak",
    "wof:placetype":"locality",
    "wof:population":1378
},
  "geometry": {"coordinates":[85.62324599999999,25.077005],"type":"Point"}
}