{
  "type": "Feature",
  "properties": {
    "gn:admin1_code":"35",
    "gn:admin2_code":"456.0",
    "gn:asciiname":"Kuranbhata",
    "gn:country_code":"IN",
    "gn:dem":559,
    "gn:feature_class":"P",
    "gn:feature_code":"PPL",
    "gn:name":"Kuranbhata",
    "gn:population":0,
    "gn:timezone":"Asia/Kolkata",
    "iso:country":"IN",
    "wof:name":"Kuranbhata",
    "wof:placetype":"locality"
},
  "geometry": {"coordinates":[79.85285999999998,22.54847],"type":"Point"}
}