{
  "type": "Feature",
  "properties": {
    "iso:country":"IN",
    "ks:ks_name":"Lalbara",
    "ks:ks_pop":31,
    "ks:ks_type":"VILLAGE",
    "ks:ks_uagg_main":0,
    "name:eng_x_preferred":[
        "Lalbara"
    ],
    "wof:name":"Lalbara",
    "wof:placetype":"neighbourhood",
    "wof:population":31
},
  "geometry": {"coordinates":[84.25749500000001,24.513834],"type":"Point"}
}