{
  "type": "Feature",
  "properties": {
    "iso:country":"IN",
    "ks:ks_name":"Dahara",
    "ks:ks_pop":140,
    "ks:ks_type":"HABITATION",
    "name:eng_x_preferred":[
        "Dahara"
    ],
    "wof:name":"Dahara",
    "wof:placetype":"locality",
    "wof:population":140
},
  "geometry": {"coordinates":[81.92325099999999,27.674283],"type":"Point"}
}