{
  "type": "Feature",
  "properties": {
    "iso:country":"IN",
    "ks:ks_name":"Gundlavai",
    "ks:ks_pop":12,
    "ks:ks_type":"VILLAGE",
    "name:eng_x_preferred":[
        "Gundlavai"
    ],
    "wof:name":"Gundlavai",
    "wof:placetype":"locality",
    "wof:population":12
},
  "geometry": {"coordinates":[81.216436,17.488226],"type":"Point"}
}