{
  "type": "Feature",
  "properties": {
    "gn:admin1_code":"13.0",
    "gn:admin2_code":"590.0",
    "gn:asciiname":"Nenmem",
    "gn:country_code":"IN",
    "gn:dem":892,
    "gn:feature_class":"P",
    "gn:feature_code":"PPL",
    "gn:name":"Nenmem",
    "gn:population":0,
    "gn:timezone":"Asia/Kolkata",
    "iso:country":"IN",
    "wof:name":"Nenmem",
    "wof:placetype":"locality"
},
  "geometry": {"coordinates":[76.24769999999999,11.59163],"type":"Point"}
}