{
  "type": "Feature",
  "properties": {
    "iso:country":"IN",
    "ks:ks_name":"Nanda Kh",
    "ks:ks_pop":28,
    "ks:ks_type":"VILLAGE",
    "name:eng_x_preferred":[
        "Nanda Kh"
    ],
    "wof:name":"Nanda Kh",
    "wof:placetype":"locality",
    "wof:population":28
},
  "geometry": {"coordinates":[78.93432,21.056369],"type":"Point"}
}