{
  "type": "Feature",
  "properties": {
    "gn:admin1_code":"40",
    "gn:admin2_code":"532.0",
    "gn:asciiname":"Narsingapuram",
    "gn:country_code":"IN",
    "gn:dem":207,
    "gn:feature_class":"P",
    "gn:feature_code":"PPL",
    "gn:name":"Narsing\u0101puram",
    "gn:population":0,
    "gn:timezone":"Asia/Kolkata",
    "iso:country":"IN",
    "ks:ks_name":"Narsingapur",
    "ks:ks_pop":192,
    "ks:ks_type":"VILLAGE",
    "name:eng_x_preferred":[
        "Narsingapur"
    ],
    "name:eng_x_variant":[
        "Narsingapuram"
    ],
    "wof:name":"Narsingapur",
    "wof:placetype":"locality",
    "wof:population":192
},
  "geometry": {"coordinates":[78.903126,19.113622],"type":"Point"}
}