{
  "type": "Feature",
  "properties": {
    "gn:admin1_code":"39.0",
    "gn:admin2_code":"132",
    "gn:asciiname":"Tankawala",
    "gn:country_code":"IN",
    "gn:dem":346,
    "gn:feature_class":"P",
    "gn:feature_code":"PPL",
    "gn:name":"T\u0101nkaw\u0101la",
    "gn:population":0,
    "gn:timezone":"Asia/Kolkata",
    "iso:country":"IN",
    "wof:name":"Tankawala",
    "wof:placetype":"locality"
},
  "geometry": {"coordinates":[77.85451999999999,30.12477],"type":"Point"}
}