{
  "type": "Feature",
  "properties": {
    "iso:country":"IN",
    "ks:ks_name":"Tola Kewal",
    "ks:ks_pop":0,
    "ks:ks_type":"VILLAGE",
    "name:eng_x_preferred":[
        "Tola Kewal"
    ],
    "wof:name":"Tola Kewal",
    "wof:placetype":"locality",
    "wof:population":0
},
  "geometry": {"coordinates":[86.48669,24.696408],"type":"Point"}
}