{
  "type": "Feature",
  "properties": {
    "gn:admin1_code":"16",
    "gn:admin2_code":"508.0",
    "gn:asciiname":"Jambulgatta",
    "gn:country_code":"IN",
    "gn:dem":322,
    "gn:feature_class":"P",
    "gn:feature_code":"PPL",
    "gn:name":"J\u0101mbulgatta",
    "gn:population":0,
    "gn:timezone":"Asia/Kolkata",
    "iso:country":"IN",
    "ks:ks_alt_nam":"J\u0101mbulgatta",
    "ks:ks_name":"Jambulgatta",
    "ks:ks_pop":152,
    "ks:ks_type":"VILLAGE",
    "name:eng_x_preferred":[
        "Jambulgatta"
    ],
    "name:eng_x_variant":[
        "J\u0101mbulgatta"
    ],
    "wof:name":"Jambulgatta",
    "wof:placetype":"locality",
    "wof:population":152
},
  "geometry": {"coordinates":[80.382678,20.011328],"type":"Point"}
}