{
  "type": "Feature",
  "properties": {
    "iso:country":"IN",
    "ks:ks_name":"Badshahpur Sirauli",
    "ks:ks_pop":4964,
    "ks:ks_type":"VILLAGE",
    "ks:ks_uagg_main":0,
    "name:eng_x_preferred":[
        "Badshahpur Sirauli"
    ],
    "wof:name":"Badshahpur Sirauli",
    "wof:placetype":"neighbourhood",
    "wof:population":4964
},
  "geometry": {"coordinates":[77.34358400000001,28.789787],"type":"Point"}
}