{
  "type": "Feature",
  "properties": {
    "gn:admin1_code":"19.0",
    "gn:admin2_code":"574.0",
    "gn:asciiname":"Devalapura",
    "gn:country_code":"IN",
    "gn:dem":1010,
    "gn:feature_class":"P",
    "gn:feature_code":"PPL",
    "gn:name":"Deval\u0101pura",
    "gn:population":0,
    "gn:timezone":"Asia/Kolkata",
    "iso:country":"IN",
    "ks:ks_alt_nam":"Deval\u0101pura",
    "ks:ks_alt_nam_2":"Devalapura",
    "ks:ks_name":"Devalapur",
    "ks:ks_type":"VILLAGE",
    "name:eng_x_preferred":[
        "Devalapur"
    ],
    "name:eng_x_variant":[
        "Devalapura",
        "Deval\u0101pura"
    ],
    "wof:name":"Devalapur",
    "wof:placetype":"locality"
},
  "geometry": {"coordinates":[75.788539,13.181273],"type":"Point"}
}