{
  "type": "Feature",
  "properties": {
    "gn:admin1_code":"12.0",
    "gn:admin2_code":"020",
    "gn:asciiname":"Upailanala",
    "gn:country_code":"IN",
    "gn:dem":436,
    "gn:feature_class":"P",
    "gn:feature_code":"PPL",
    "gn:name":"Upail\u0101n\u0101la",
    "gn:population":0,
    "gn:timezone":"Asia/Kolkata",
    "iso:country":"IN",
    "wof:name":"Upailanala",
    "wof:placetype":"locality"
},
  "geometry": {"coordinates":[74.8875,32.875],"type":"Point"}
}