{
  "type": "Feature",
  "properties": {
    "iso:country":"IN",
    "ks:ks_name":"Manikoura",
    "ks:ks_pop":93,
    "ks:ks_type":"HABITATION",
    "name:eng_x_preferred":[
        "Manikoura"
    ],
    "wof:name":"Manikoura",
    "wof:placetype":"locality",
    "wof:population":93
},
  "geometry": {"coordinates":[83.537171,27.439024],"type":"Point"}
}