{
  "type": "Feature",
  "properties": {
    "iso:country":"IN",
    "ks:ks_name":"Mallickpur",
    "ks:ks_pop":730,
    "ks:ks_type":"HABITATION",
    "name:eng_x_preferred":[
        "Mallickpur"
    ],
    "wof:name":"Mallickpur",
    "wof:placetype":"locality",
    "wof:population":730
},
  "geometry": {"coordinates":[87.869856,23.530385],"type":"Point"}
}