{
  "type": "Feature",
  "properties": {
    "gn:admin1_code":"19.0",
    "gn:admin2_code":"559.0",
    "gn:asciiname":"Amrapur",
    "gn:country_code":"IN",
    "gn:dem":384,
    "gn:feature_class":"P",
    "gn:feature_code":"PPL",
    "gn:name":"Amr\u0101pur",
    "gn:population":0,
    "gn:timezone":"Asia/Kolkata",
    "iso:country":"IN",
    "ks:ks_name":"Amarapur",
    "ks:ks_pop":1402,
    "ks:ks_type":"VILLAGE",
    "name:cat_x_preferred":[
        "Amrapur"
    ],
    "name:eng_x_preferred":[
        "Amarapur"
    ],
    "name:eng_x_variant":[
        "Amrapur"
    ],
    "wof:name":"Amarapur",
    "wof:placetype":"locality",
    "wof:population":1402
},
  "geometry": {"coordinates":[76.78178200000001,15.72959],"type":"Point"}
}