{
  "type": "Feature",
  "properties": {
    "iso:country":"IN",
    "ks:ks_name":"Halemane",
    "ks:ks_pop":44,
    "ks:ks_type":"HABITATION",
    "name:eng_x_preferred":[
        "Halemane"
    ],
    "wof:name":"Halemane",
    "wof:placetype":"locality",
    "wof:population":44
},
  "geometry": {"coordinates":[74.6194,14.939848],"type":"Point"}
}