{
  "type": "Feature",
  "properties": {
    "gn:admin1_code":"25.0",
    "gn:admin2_code":"633.0",
    "gn:asciiname":"Vamalakavundanpalaiyam",
    "gn:country_code":"IN",
    "gn:dem":299,
    "gn:feature_class":"P",
    "gn:feature_code":"PPL",
    "gn:name":"V\u0101malakavundanp\u0101laiyam",
    "gn:population":0,
    "gn:timezone":"Asia/Kolkata",
    "iso:country":"IN",
    "wof:name":"Vamalakavundanpalaiyam",
    "wof:placetype":"locality"
},
  "geometry": {"coordinates":[77.43935,11.23732],"type":"Point"}
}