{
  "type": "Feature",
  "properties": {
    "gn:admin1_code":"13.0",
    "gn:admin2_code":"590.0",
    "gn:asciiname":"Nagamani Vayal",
    "gn:country_code":"IN",
    "gn:dem":839,
    "gn:feature_class":"P",
    "gn:feature_code":"PPL",
    "gn:name":"N\u0101gamani Vayal",
    "gn:population":0,
    "gn:timezone":"Asia/Kolkata",
    "iso:country":"IN",
    "wof:name":"Nagamani Vayal",
    "wof:placetype":"locality"
},
  "geometry": {"coordinates":[76.04642,11.92554],"type":"Point"}
}