{
  "type": "Feature",
  "properties": {
    "iso:country":"IN",
    "ks:ks_name":"Mahuha",
    "ks:ks_pop":63,
    "ks:ks_type":"VILLAGE",
    "name:eng_x_preferred":[
        "Mahuha"
    ],
    "wof:name":"Mahuha",
    "wof:placetype":"locality",
    "wof:population":63
},
  "geometry": {"coordinates":[81.47098,24.507035],"type":"Point"}
}