{
  "type": "Feature",
  "properties": {
    "iso:country":"IN",
    "ks:ks_name":"Kompettimala",
    "ks:ks_pop":346,
    "ks:ks_type":"HABITATION",
    "name:eng_x_preferred":[
        "Kompettimala"
    ],
    "wof:name":"Kompettimala",
    "wof:placetype":"locality",
    "wof:population":346
},
  "geometry": {"coordinates":[76.873518,8.935487],"type":"Point"}
}