{
  "type": "Feature",
  "properties": {
    "iso:country":"IN",
    "ks:ks_name":"Mohammadpur Rustampur",
    "ks:ks_pop":3538,
    "ks:ks_type":"VILLAGE",
    "ks:ks_uagg_main":0,
    "name:eng_x_preferred":[
        "Mohammadpur Rustampur"
    ],
    "wof:name":"Mohammadpur Rustampur",
    "wof:placetype":"neighbourhood",
    "wof:population":3538
},
  "geometry": {"coordinates":[78.12014600000001,28.706943],"type":"Point"}
}