{
  "type": "Feature",
  "properties": {
    "iso:country":"IN",
    "ks:ks_name":"Mounde",
    "ks:ks_pop":474,
    "ks:ks_type":"VILLAGE",
    "name:eng_x_preferred":[
        "Mounde"
    ],
    "wof:name":"Mounde",
    "wof:placetype":"locality",
    "wof:population":474
},
  "geometry": {"coordinates":[73.83226999999999,16.604341],"type":"Point"}
}