{
  "type": "Feature",
  "properties": {
    "gn:admin1_code":"13.0",
    "gn:admin2_code":"594.0",
    "gn:asciiname":"Puranattukara",
    "gn:country_code":"IN",
    "gn:dem":14,
    "gn:feature_class":"P",
    "gn:feature_code":"PPL",
    "gn:name":"Puranattukara",
    "gn:population":0,
    "gn:timezone":"Asia/Kolkata",
    "iso:country":"IN",
    "wof:name":"Puranattukara",
    "wof:placetype":"locality"
},
  "geometry": {"coordinates":[76.15225,10.54532],"type":"Point"}
}