{
  "type": "Feature",
  "properties": {
    "iso:country":"IN",
    "ks:ks_name":"Budasan",
    "ks:ks_pop":3436,
    "ks:ks_type":"VILLAGE",
    "ks:ks_uagg_main":0,
    "name:eng_x_preferred":[
        "Budasan"
    ],
    "wof:name":"Budasan",
    "wof:placetype":"locality",
    "wof:population":3436
},
  "geometry": {"coordinates":[72.372817,23.286079],"type":"Point"}
}