{
  "type": "Feature",
  "properties": {
    "iso:country":"IN",
    "ks:ks_name":"Gaburumamidi",
    "ks:ks_pop":53,
    "ks:ks_type":"HABITATION",
    "name:eng_x_preferred":[
        "Gaburumamidi"
    ],
    "wof:name":"Gaburumamidi",
    "wof:placetype":"locality",
    "wof:population":53
},
  "geometry": {"coordinates":[82.371662,18.216518],"type":"Point"}
}