{
  "type": "Feature",
  "properties": {
    "gn:admin1_code":"24.0",
    "gn:admin2_code":"105.0",
    "gn:asciiname":"Nagla Baldev",
    "gn:country_code":"IN",
    "gn:dem":187,
    "gn:feature_class":"P",
    "gn:feature_code":"PPL",
    "gn:name":"Nagla Baldev",
    "gn:population":0,
    "gn:timezone":"Asia/Kolkata",
    "iso:country":"IN",
    "wof:name":"Nagla Baldev",
    "wof:placetype":"locality"
},
  "geometry": {"coordinates":[77.28748,27.73869],"type":"Point"}
}