{
  "type": "Feature",
  "properties": {
    "gn:admin1_code":"36.0",
    "gn:admin2_code":"145.0",
    "gn:asciiname":"Nagla Mewati",
    "gn:country_code":"IN",
    "gn:dem":186,
    "gn:feature_class":"P",
    "gn:feature_code":"PPL",
    "gn:name":"Nagla Mew\u0101ti",
    "gn:population":0,
    "gn:timezone":"Asia/Kolkata",
    "iso:country":"IN",
    "wof:name":"Nagla Mewati",
    "wof:placetype":"locality"
},
  "geometry": {"coordinates":[77.46326999999999,27.63342],"type":"Point"}
}