{
  "type": "Feature",
  "properties": {
    "iso:country":"IN",
    "ks:ks_name":"Gogul",
    "ks:ks_pop":258,
    "ks:ks_type":"HABITATION",
    "name:eng_x_preferred":[
        "Gogul"
    ],
    "wof:name":"Gogul",
    "wof:placetype":"locality",
    "wof:population":258
},
  "geometry": {"coordinates":[73.699322,20.451616],"type":"Point"}
}