{
  "type": "Feature",
  "properties": {
    "gn:admin1_code":"11",
    "gn:admin2_code":"28.0",
    "gn:asciiname":"Dabbar",
    "gn:country_code":"IN",
    "gn:dem":516,
    "gn:feature_class":"P",
    "gn:feature_code":"PPL",
    "gn:name":"Dabbar",
    "gn:population":0,
    "gn:timezone":"Asia/Kolkata",
    "iso:country":"IN",
    "wof:name":"Dabbar",
    "wof:placetype":"locality"
},
  "geometry": {"coordinates":[76.39609,31.76204],"type":"Point"}
}