{
  "type": "Feature",
  "properties": {
    "iso:country":"IN",
    "ks:ks_name":"Pithadangar",
    "ks:ks_type":"VILLAGE",
    "name:eng_x_preferred":[
        "Pithadangar"
    ],
    "wof:name":"Pithadangar",
    "wof:placetype":"locality"
},
  "geometry": {"coordinates":[87.38034500000001,22.410688],"type":"Point"}
}