{
  "type": "Feature",
  "properties": {
    "iso:country":"IN",
    "ks:ks_name":"6FTP",
    "ks:ks_pop":122,
    "ks:ks_type":"VILLAGE",
    "name:eng_x_preferred":[
        "6FTP"
    ],
    "wof:name":"6FTP",
    "wof:placetype":"locality",
    "wof:population":122
},
  "geometry": {"coordinates":[74.508967,29.639661],"type":"Point"}
}