{
  "type": "Feature",
  "properties": {
    "gn:admin1_code":"2.0",
    "gn:admin2_code":"553.0",
    "gn:asciiname":"Erraswamivandlapalle",
    "gn:country_code":"IN",
    "gn:dem":432,
    "gn:feature_class":"P",
    "gn:feature_code":"PPL",
    "gn:name":"Errasw\u0101miv\u0101ndlapalle",
    "gn:population":0,
    "gn:timezone":"Asia/Kolkata",
    "iso:country":"IN",
    "wof:name":"Erraswamivandlapalle",
    "wof:placetype":"locality"
},
  "geometry": {"coordinates":[78.23878000000001,14.25049],"type":"Point"}
}