{
  "type": "Feature",
  "properties": {
    "gn:admin1_code":"25.0",
    "gn:admin2_code":"631.0",
    "gn:asciiname":"Salinayanapalli",
    "gn:country_code":"IN",
    "gn:dem":499,
    "gn:feature_class":"P",
    "gn:feature_code":"PPL",
    "gn:name":"S\u0101linay\u0101napalli",
    "gn:population":0,
    "gn:timezone":"Asia/Kolkata",
    "iso:country":"IN",
    "ks:ks_alt_nam":"S\u0101linay\u0101napalli",
    "ks:ks_name":"Salinayanapalli",
    "ks:ks_pop":5642,
    "ks:ks_type":"VILLAGE",
    "ks:ks_uagg_main":0,
    "name:eng_x_preferred":[
        "Salinayanapalli"
    ],
    "name:eng_x_variant":[
        "S\u0101linay\u0101napalli"
    ],
    "wof:name":"Salinayanapalli",
    "wof:placetype":"locality",
    "wof:population":5642
},
  "geometry": {"coordinates":[78.358317,12.56617],"type":"Point"}
}