{
  "type": "Feature",
  "properties": {
    "iso:country":"IN",
    "ks:ks_alt_nam":"manakadu",
    "ks:ks_name":"Manakadu",
    "ks:ks_pop":320,
    "ks:ks_type":"HABITATION",
    "name:eng_x_preferred":[
        "Manakadu"
    ],
    "wof:name":"Manakadu",
    "wof:placetype":"locality",
    "wof:population":320
},
  "geometry": {"coordinates":[77.397847,11.285758],"type":"Point"}
}