{
  "type": "Feature",
  "properties": {
    "iso:country":"IN",
    "ks:ks_name":"Khoto",
    "ks:ks_pop":789,
    "ks:ks_type":"VILLAGE",
    "name:eng_x_preferred":[
        "Khoto"
    ],
    "wof:name":"Khoto",
    "wof:placetype":"locality",
    "wof:population":789
},
  "geometry": {"coordinates":[86.104766,24.538274],"type":"Point"}
}