{
  "type": "Feature",
  "properties": {
    "gn:admin1_code":"34",
    "gn:admin2_code":"218.0",
    "gn:asciiname":"Puraina",
    "gn:country_code":"IN",
    "gn:dem":64,
    "gn:feature_class":"P",
    "gn:feature_code":"PPL",
    "gn:name":"Puraina",
    "gn:population":0,
    "gn:timezone":"Asia/Kolkata",
    "iso:country":"IN",
    "ks:ks_name":"Puraina",
    "ks:ks_pop":1235,
    "ks:ks_type":"VILLAGE",
    "ks:ks_uagg_main":0,
    "name:ceb_x_preferred":[
        "Puraina"
    ],
    "name:eng_x_preferred":[
        "Puraina"
    ],
    "name:mai_x_preferred":[
        "\u092a\u0941\u0930\u0948\u0928\u093e"
    ],
    "name:msa_x_preferred":[
        "Puraina"
    ],
    "name:nep_x_preferred":[
        "\u092a\u0941\u0930\u0948\u0928\u093e"
    ],
    "name:new_x_preferred":[
        "\u092a\u0941\u0930\u0948\u0928\u093e"
    ],
    "name:pol_x_preferred":[
        "Puraina"
    ],
    "wof:name":"Puraina",
    "wof:placetype":"neighbourhood",
    "wof:population":1235
},
  "geometry": {"coordinates":[84.385378,26.091364],"type":"Point"}
}