{
  "type": "Feature",
  "properties": {
    "gn:admin1_code":"39.0",
    "gn:admin2_code":"65.0",
    "gn:asciiname":"Kadwalgaon",
    "gn:country_code":"IN",
    "gn:dem":1753,
    "gn:feature_class":"P",
    "gn:feature_code":"PPL",
    "gn:name":"Kadw\u0101lgaon",
    "gn:population":0,
    "gn:timezone":"Asia/Kolkata",
    "iso:country":"IN",
    "ks:ks_name":"Karwalgaon",
    "ks:ks_pop":125,
    "ks:ks_type":"VILLAGE",
    "name:eng_x_preferred":[
        "Karwalgaon"
    ],
    "name:eng_x_variant":[
        "Kadwalgaon"
    ],
    "wof:name":"Karwalgaon",
    "wof:placetype":"locality",
    "wof:population":125
},
  "geometry": {"coordinates":[79.99267500000001,29.378353],"type":"Point"}
}