{
  "type": "Feature",
  "properties": {
    "gn:admin1_code":"39.0",
    "gn:admin2_code":"65.0",
    "gn:asciiname":"Kadwalgaon",
    "gn:country_code":"IN",
    "gn:dem":1753,
    "gn:feature_class":"P",
    "gn:feature_code":"PPL",
    "gn:name":"Kadw\u0101lgaon",
    "gn:population":0,
    "gn:timezone":"Asia/Kolkata",
    "iso:country":"IN",
    "wof:name":"Kadwalgaon",
    "wof:placetype":"locality"
},
  "geometry": {"coordinates":[79.98964000000002,29.37816],"type":"Point"}
}