{
  "type": "Feature",
  "properties": {
    "iso:country":"IN",
    "ks:ks_name":"Genchapara",
    "ks:ks_pop":503,
    "ks:ks_type":"HABITATION",
    "name:eng_x_preferred":[
        "Genchapara"
    ],
    "wof:name":"Genchapara",
    "wof:placetype":"locality",
    "wof:population":503
},
  "geometry": {"coordinates":[81.337138,18.652661],"type":"Point"}
}