{
  "type": "Feature",
  "properties": {
    "iso:country":"IN",
    "ks:ks_name":"Asanbani",
    "ks:ks_pop":0,
    "ks:ks_type":"VILLAGE",
    "name:eng_x_preferred":[
        "Asanbani"
    ],
    "wof:name":"Asanbani",
    "wof:placetype":"locality",
    "wof:population":0
},
  "geometry": {"coordinates":[87.180531,23.521554],"type":"Point"}
}