{
  "type": "Feature",
  "properties": {
    "iso:country":"IN",
    "ks:ks_alt_nam":"Kaswon ki Dhani",
    "ks:ks_name":"Kaswon Ki Dhani",
    "ks:ks_pop":20,
    "ks:ks_type":"HABITATION",
    "name:eng_x_preferred":[
        "Kaswon Ki Dhani"
    ],
    "wof:name":"Kaswon Ki Dhani",
    "wof:placetype":"locality",
    "wof:population":20
},
  "geometry": {"coordinates":[74.432877,29.824124],"type":"Point"}
}