{
  "type": "Feature",
  "properties": {
    "iso:country":"IN",
    "ks:ks_name":"Keelapatty",
    "ks:ks_pop":100,
    "ks:ks_type":"HABITATION",
    "name:eng_x_preferred":[
        "Keelapatty"
    ],
    "wof:name":"Keelapatty",
    "wof:placetype":"locality",
    "wof:population":100
},
  "geometry": {"coordinates":[78.680978,10.497031],"type":"Point"}
}