{
  "type": "Feature",
  "properties": {
    "gn:admin1_code":"24",
    "gn:admin2_code":"127.0",
    "gn:asciiname":"Dabri Khurd",
    "gn:country_code":"IN",
    "gn:dem":269,
    "gn:feature_class":"P",
    "gn:feature_code":"PPL",
    "gn:name":"D\u0101bri Khurd",
    "gn:population":0,
    "gn:timezone":"Asia/Kolkata",
    "iso:country":"IN",
    "wof:name":"Dabri Khurd",
    "wof:placetype":"locality"
},
  "geometry": {"coordinates":[76.36038000000001,24.98846],"type":"Point"}
}