{
  "type": "Feature",
  "properties": {
    "gn:admin1_code":"23.0",
    "gn:admin2_code":"49.0",
    "gn:asciiname":"Targar Rampur",
    "gn:country_code":"IN",
    "gn:dem":239,
    "gn:feature_class":"P",
    "gn:feature_code":"PPL",
    "gn:name":"Targar R\u0101mpur",
    "gn:population":0,
    "gn:timezone":"Asia/Kolkata",
    "iso:country":"IN",
    "wof:name":"Targar Rampur",
    "wof:placetype":"locality"
},
  "geometry": {"coordinates":[75.00168000000002,31.76324],"type":"Point"}
}