{
  "type": "Feature",
  "properties": {
    "iso:country":"IN",
    "ks:ks_name":"Giridih",
    "ks:ks_pop":595,
    "ks:ks_type":"HABITATION",
    "name:eng_x_preferred":[
        "Giridih"
    ],
    "wof:name":"Giridih",
    "wof:placetype":"locality",
    "wof:population":595
},
  "geometry": {"coordinates":[87.048869,24.756362],"type":"Point"}
}