{
  "type": "Feature",
  "properties": {
    "iso:country":"IN",
    "ks:ks_name":"Satepada",
    "ks:ks_pop":129,
    "ks:ks_type":"HABITATION",
    "name:eng_x_preferred":[
        "Satepada"
    ],
    "wof:name":"Satepada",
    "wof:placetype":"locality",
    "wof:population":129
},
  "geometry": {"coordinates":[73.064396,20.093199],"type":"Point"}
}