{
  "type": "Feature",
  "properties": {
    "iso:country":"IN",
    "ks:ks_name":"Gulji Ka Pana",
    "ks:ks_pop":284,
    "ks:ks_type":"VILLAGE",
    "name:eng_x_preferred":[
        "Gulji Ka Pana"
    ],
    "wof:name":"Gulji Ka Pana",
    "wof:placetype":"locality",
    "wof:population":284
},
  "geometry": {"coordinates":[71.83575,25.973739],"type":"Point"}
}