{
  "type": "Feature",
  "properties": {
    "iso:country":"IN",
    "ks:ks_name":"Niliyarbawardi",
    "ks:ks_pop":56,
    "ks:ks_type":"HABITATION",
    "name:eng_x_preferred":[
        "Niliyarbawardi"
    ],
    "wof:name":"Niliyarbawardi",
    "wof:placetype":"locality",
    "wof:population":56
},
  "geometry": {"coordinates":[74.896146,21.677223],"type":"Point"}
}