{
  "type": "Feature",
  "properties": {
    "iso:country":"IN",
    "ks:ks_name":"Rayapura",
    "ks:ks_pop":99,
    "ks:ks_type":"HABITATION",
    "name:eng_x_preferred":[
        "Rayapura"
    ],
    "wof:name":"Rayapura",
    "wof:placetype":"locality",
    "wof:population":99
},
  "geometry": {"coordinates":[77.503561,21.268798],"type":"Point"}
}