{
  "type": "Feature",
  "properties": {
    "gn:admin1_code":"36",
    "gn:admin2_code":"191.0",
    "gn:asciiname":"Yusufpur",
    "gn:country_code":"IN",
    "gn:dem":87,
    "gn:feature_class":"P",
    "gn:feature_code":"PPL",
    "gn:name":"Yus\u016bfpur",
    "gn:population":0,
    "gn:timezone":"Asia/Kolkata",
    "iso:country":"IN",
    "name:msa_x_preferred":[
        "Yusufpur"
    ],
    "wof:name":"Yusufpur",
    "wof:placetype":"locality"
},
  "geometry": {"coordinates":[82.84860999999999,26.02225],"type":"Point"}
}