{
  "type": "Feature",
  "properties": {
    "iso:country":"IN",
    "ks:ks_alt_nam":"varchiwadi",
    "ks:ks_name":"Varchiwadi",
    "ks:ks_pop":78,
    "ks:ks_type":"HABITATION",
    "name:eng_x_preferred":[
        "Varchiwadi"
    ],
    "wof:name":"Varchiwadi",
    "wof:placetype":"locality",
    "wof:population":78
},
  "geometry": {"coordinates":[73.5675,17.556389],"type":"Point"}
}