{
  "type": "Feature",
  "properties": {
    "iso:country":"IN",
    "ks:ks_name":"Sardarpada",
    "ks:ks_pop":208,
    "ks:ks_type":"HABITATION",
    "name:eng_x_preferred":[
        "Sardarpada"
    ],
    "wof:name":"Sardarpada",
    "wof:placetype":"locality",
    "wof:population":208
},
  "geometry": {"coordinates":[74.82629799999999,21.546512],"type":"Point"}
}