{
  "type": "Feature",
  "properties": {
    "iso:country":"IN",
    "ks:ks_alt_nam":"C V centre",
    "ks:ks_name":"C V Centre",
    "ks:ks_pop":321,
    "ks:ks_type":"HABITATION",
    "name:eng_x_preferred":[
        "C V Centre"
    ],
    "wof:name":"C V Centre",
    "wof:placetype":"locality",
    "wof:population":321
},
  "geometry": {"coordinates":[76.137142,10.360659],"type":"Point"}
}