{
  "type": "Feature",
  "properties": {
    "iso:country":"IN",
    "ks:ks_name":"Dhonow Purwa",
    "ks:ks_pop":62,
    "ks:ks_type":"HABITATION",
    "name:eng_x_preferred":[
        "Dhonow Purwa"
    ],
    "wof:name":"Dhonow Purwa",
    "wof:placetype":"locality",
    "wof:population":62
},
  "geometry": {"coordinates":[82.56684799999999,26.80315],"type":"Point"}
}