{
  "type": "Feature",
  "properties": {
    "iso:country":"IN",
    "ks:ks_alt_nam":"Kumh\u0101rdih",
    "ks:ks_name":"Kumhardih",
    "ks:ks_pop":556,
    "ks:ks_type":"VILLAGE",
    "name:eng_x_preferred":[
        "Kumhardih"
    ],
    "name:eng_x_variant":[
        "Kumh\u0101rdih"
    ],
    "wof:name":"Kumhardih",
    "wof:placetype":"locality",
    "wof:population":556
},
  "geometry": {"coordinates":[85.224073,22.864104],"type":"Point"}
}