{
  "type": "Feature",
  "properties": {
    "gn:admin1_code":"2.0",
    "gn:admin2_code":"547.0",
    "gn:asciiname":"Vanapamula",
    "gn:country_code":"IN",
    "gn:dem":16,
    "gn:feature_class":"P",
    "gn:feature_code":"PPL",
    "gn:name":"V\u0101nap\u0101mula",
    "gn:population":0,
    "gn:timezone":"Asia/Kolkata",
    "iso:country":"IN",
    "name:hin_x_preferred":[
        "\u0935\u0928\u092a\u092e\u0941\u0932"
    ],
    "name:new_x_preferred":[
        "\u0935\u0928\u092a\u092e\u0941\u0932"
    ],
    "name:tel_x_preferred":[
        "\u0c35\u0c3e\u0c28\u0c2a\u0c3e\u0c2e\u0c41\u0c32"
    ],
    "wof:name":"Vanapamula",
    "wof:placetype":"locality"
},
  "geometry": {"coordinates":[80.92841999999997,16.43765],"type":"Point"}
}