{
  "type": "Feature",
  "properties": {
    "gn:admin1_code":"35",
    "gn:admin2_code":"419.0",
    "gn:asciiname":"Asaram ka Pura",
    "gn:country_code":"IN",
    "gn:dem":172,
    "gn:feature_class":"P",
    "gn:feature_code":"PPL",
    "gn:name":"\u0100s\u0101r\u0101m ka Pura",
    "gn:population":0,
    "gn:timezone":"Asia/Kolkata",
    "iso:country":"IN",
    "wof:name":"Asaram ka Pura",
    "wof:placetype":"locality"
},
  "geometry": {"coordinates":[78.11922,26.62627],"type":"Point"}
}