{
  "type": "Feature",
  "properties": {
    "gn:admin1_code":"19.0",
    "gn:admin2_code":"584.0",
    "gn:asciiname":"Gundilaya",
    "gn:country_code":"IN",
    "gn:dem":803,
    "gn:feature_class":"P",
    "gn:feature_code":"PPL",
    "gn:name":"Gundil\u0101ya",
    "gn:population":0,
    "gn:timezone":"Asia/Kolkata",
    "iso:country":"IN",
    "wof:name":"Gundilaya",
    "wof:placetype":"neighbourhood"
},
  "geometry": {"coordinates":[77.11677,13.09265],"type":"Point"}
}