{
  "type": "Feature",
  "properties": {
    "gn:admin1_code":"37",
    "gn:asciiname":"Kundai",
    "gn:country_code":"IN",
    "gn:dem":648,
    "gn:feature_class":"P",
    "gn:feature_code":"PPL",
    "gn:name":"Kundai",
    "gn:population":0,
    "gn:timezone":"Asia/Kolkata",
    "iso:country":"IN",
    "name:und_x_variant":[
        "Kundei"
    ],
    "wof:name":"Kundai",
    "wof:placetype":"locality"
},
  "geometry": {"coordinates":[81.92501999999998,20.04227],"type":"Point"}
}