{
  "type": "Feature",
  "properties": {
    "gn:admin1_code":"24.0",
    "gn:admin2_code":"105.0",
    "gn:asciiname":"Azizpur",
    "gn:country_code":"IN",
    "gn:dem":190,
    "gn:feature_class":"P",
    "gn:feature_code":"PPL",
    "gn:name":"Az\u012bzpur",
    "gn:population":0,
    "gn:timezone":"Asia/Kolkata",
    "iso:country":"IN",
    "name:bih_x_preferred":[
        "\u0905\u091c\u0940\u091c\u092a\u0941\u0930"
    ],
    "name:bpy_x_preferred":[
        "\u0986\u099c\u09bf\u099c\u09aa\u09c1\u09b0"
    ],
    "name:ceb_x_preferred":[
        "Az\u012bzpur"
    ],
    "name:fas_x_preferred":[
        "\u0639\u0632\u06cc\u0632\u067e\u0648\u0631"
    ],
    "name:ita_x_preferred":[
        "Azizpur"
    ],
    "name:msa_x_preferred":[
        "Azizpur"
    ],
    "name:new_x_preferred":[
        "\u0905\u091c\u093f\u091c\u092a\u0941\u0930"
    ],
    "name:nld_x_preferred":[
        "Azizpur"
    ],
    "name:pol_x_preferred":[
        "Azizpur"
    ],
    "name:por_x_preferred":[
        "Azizpur"
    ],
    "name:swe_x_preferred":[
        "Az\u012bzpur"
    ],
    "name:und_x_variant":[
        "Chak Nandola"
    ],
    "name:urd_x_preferred":[
        "\u0639\u0632\u06cc\u0632 \u067e\u0648\u0631"
    ],
    "name:vie_x_preferred":[
        "Azizpur"
    ],
    "name:zho_x_preferred":[
        "\u963f\u9f50\u5179\u666e\u5c14"
    ],
    "wof:name":"Azizpur",
    "wof:placetype":"neighbourhood"
},
  "geometry": {"coordinates":[77.31466,27.63862],"type":"Point"}
}