{
  "type": "Feature",
  "properties": {
    "gn:admin1_code":"36.0",
    "gn:admin2_code":"179.0",
    "gn:asciiname":"Purwa Ahiran",
    "gn:country_code":"IN",
    "gn:dem":103,
    "gn:feature_class":"P",
    "gn:feature_code":"PPL",
    "gn:name":"Purwa Ah\u012bran",
    "gn:population":0,
    "gn:timezone":"Asia/Kolkata",
    "iso:country":"IN",
    "ks:ks_alt_nam":"PURE AHIRAN",
    "ks:ks_name":"Pure Ahiran",
    "ks:ks_pop":204,
    "ks:ks_type":"HABITATION",
    "ks:ks_uagg_main":0,
    "name:eng_x_preferred":[
        "Pure Ahiran"
    ],
    "wof:name":"Pure Ahiran",
    "wof:placetype":"neighbourhood",
    "wof:population":204
},
  "geometry": {"coordinates":[81.824761,26.092167],"type":"Point"}
}