{
  "type": "Feature",
  "properties": {
    "iso:country":"IN",
    "ks:ks_name":"Bara Nauphari",
    "ks:ks_pop":709,
    "ks:ks_type":"HABITATION",
    "ks:ks_uagg_main":0,
    "name:eng_x_preferred":[
        "Bara Nauphari"
    ],
    "wof:name":"Bara Nauphari",
    "wof:placetype":"neighbourhood",
    "wof:population":709
},
  "geometry": {"coordinates":[78.08214099999999,27.087946],"type":"Point"}
}