{
  "type": "Feature",
  "properties": {
    "iso:country":"IN",
    "ks:ks_name":"Basavasai",
    "ks:ks_pop":241,
    "ks:ks_type":"HABITATION",
    "name:eng_x_preferred":[
        "Basavasai"
    ],
    "wof:name":"Basavasai",
    "wof:placetype":"locality",
    "wof:population":241
},
  "geometry": {"coordinates":[84.37317400000001,18.859395],"type":"Point"}
}