{
  "type": "Feature",
  "properties": {
    "iso:country":"IN",
    "ks:ks_name":"Buriapaju",
    "ks:ks_pop":110,
    "ks:ks_type":"VILLAGE",
    "name:eng_x_preferred":[
        "Buriapaju"
    ],
    "wof:name":"Buriapaju",
    "wof:placetype":"locality",
    "wof:population":110
},
  "geometry": {"coordinates":[84.754312,20.471528],"type":"Point"}
}