{
  "type": "Feature",
  "properties": {
    "gn:admin1_code":"36.0",
    "gn:admin2_code":"152.0",
    "gn:asciiname":"Lakhanpur",
    "gn:country_code":"IN",
    "gn:dem":163,
    "gn:feature_class":"P",
    "gn:feature_code":"PPL",
    "gn:name":"Lakhanpur",
    "gn:population":0,
    "gn:timezone":"Asia/Kolkata",
    "iso:country":"IN",
    "wof:name":"Lakhanpur",
    "wof:placetype":"locality"
},
  "geometry": {"coordinates":[79.64098,28.08973],"type":"Point"}
}