{
  "type": "Feature",
  "properties": {
    "gn:admin1_code":"21",
    "gn:admin2_code":"399.0",
    "gn:asciiname":"Kupliguda",
    "gn:country_code":"IN",
    "gn:dem":257,
    "gn:feature_class":"P",
    "gn:feature_code":"PPL",
    "gn:name":"Kuplig\u016bda",
    "gn:population":0,
    "gn:timezone":"Asia/Kolkata",
    "iso:country":"IN",
    "ks:ks_name":"Kupaliguda",
    "ks:ks_pop":114,
    "ks:ks_type":"HABITATION",
    "name:eng_x_preferred":[
        "Kupaliguda"
    ],
    "name:eng_x_variant":[
        "Kupliguda"
    ],
    "wof:name":"Kupaliguda",
    "wof:placetype":"locality",
    "wof:population":114
},
  "geometry": {"coordinates":[82.105125,18.562282],"type":"Point"}
}