{
  "type": "Feature",
  "properties": {
    "iso:country":"IN",
    "ks:ks_name":"Munna Kheda",
    "ks:ks_pop":102,
    "ks:ks_type":"HABITATION",
    "ks:ks_uagg_main":0,
    "name:eng_x_preferred":[
        "Munna Kheda"
    ],
    "wof:name":"Munna Kheda",
    "wof:placetype":"neighbourhood",
    "wof:population":102
},
  "geometry": {"coordinates":[80.39631,26.633648],"type":"Point"}
}