{
  "type": "Feature",
  "properties": {
    "iso:country":"IN",
    "ks:ks_alt_nam":"HALLANNAMALA",
    "ks:ks_name":"Hallannamala",
    "ks:ks_pop":100,
    "ks:ks_type":"HABITATION",
    "name:eng_x_preferred":[
        "Hallannamala"
    ],
    "wof:name":"Hallannamala",
    "wof:placetype":"locality",
    "wof:population":100
},
  "geometry": {"coordinates":[74.64944,17.048593],"type":"Point"}
}