{
  "type": "Feature",
  "properties": {
    "iso:country":"IN",
    "ks:ks_name":"Kolerwadi",
    "ks:ks_pop":176,
    "ks:ks_type":"HABITATION",
    "name:eng_x_preferred":[
        "Kolerwadi"
    ],
    "wof:name":"Kolerwadi",
    "wof:placetype":"locality",
    "wof:population":176
},
  "geometry": {"coordinates":[73.648483,16.182536],"type":"Point"}
}