{
  "type": "Feature",
  "properties": {
    "iso:country":"IN",
    "ks:ks_name":"Numuigarya",
    "ks:ks_pop":158,
    "ks:ks_type":"VILLAGE",
    "name:eng_x_preferred":[
        "Numuigarya"
    ],
    "wof:name":"Numuigarya",
    "wof:placetype":"locality",
    "wof:population":158
},
  "geometry": {"coordinates":[87.329971,23.384057],"type":"Point"}
}