{
  "type": "Feature",
  "properties": {
    "iso:country":"IN",
    "ks:ks_name":"Panasaloddi",
    "ks:ks_pop":22,
    "ks:ks_type":"HABITATION",
    "name:eng_x_preferred":[
        "Panasaloddi"
    ],
    "wof:name":"Panasaloddi",
    "wof:placetype":"locality",
    "wof:population":22
},
  "geometry": {"coordinates":[82.017899,17.528855],"type":"Point"}
}