{
  "type": "Feature",
  "properties": {
    "iso:country":"IN",
    "ks:ks_name":"Arban",
    "ks:ks_pop":21,
    "ks:ks_type":"VILLAGE",
    "ks:ks_uagg_main":0,
    "name:eng_x_preferred":[
        "Arban"
    ],
    "wof:name":"Arban",
    "wof:placetype":"neighbourhood",
    "wof:population":21
},
  "geometry": {"coordinates":[75.380629,15.703334],"type":"Point"}
}