{
  "type": "Feature",
  "properties": {
    "gn:admin1_code":"11.0",
    "gn:admin2_code":"33.0",
    "gn:asciiname":"Kanchhetu",
    "gn:country_code":"IN",
    "gn:dem":1732,
    "gn:feature_class":"P",
    "gn:feature_code":"PPL",
    "gn:name":"Kanchhetu",
    "gn:population":0,
    "gn:timezone":"Asia/Kolkata",
    "iso:country":"IN",
    "wof:name":"Kanchhetu",
    "wof:placetype":"locality"
},
  "geometry": {"coordinates":[77.65765999999998,31.34571],"type":"Point"}
}