{
  "type": "Feature",
  "properties": {
    "iso:country":"IN",
    "ks:ks_name":"Bendwasti",
    "ks:ks_pop":181,
    "ks:ks_type":"HABITATION",
    "name:eng_x_preferred":[
        "Bendwasti"
    ],
    "wof:name":"Bendwasti",
    "wof:placetype":"locality",
    "wof:population":181
},
  "geometry": {"coordinates":[74.21534800000001,19.070879],"type":"Point"}
}