{
  "type": "Feature",
  "properties": {
    "iso:country":"IN",
    "ks:ks_name":"Baobasa",
    "ks:ks_pop":81,
    "ks:ks_type":"HABITATION",
    "name:eng_x_preferred":[
        "Baobasa"
    ],
    "wof:name":"Baobasa",
    "wof:placetype":"locality",
    "wof:population":81
},
  "geometry": {"coordinates":[85.718093,22.230438],"type":"Point"}
}