{
  "type": "Feature",
  "properties": {
    "iso:country":"IN",
    "ks:ks_name":"Majhi Tari",
    "ks:ks_pop":707,
    "ks:ks_type":"HABITATION",
    "name:eng_x_preferred":[
        "Majhi Tari"
    ],
    "wof:name":"Majhi Tari",
    "wof:placetype":"locality",
    "wof:population":707
},
  "geometry": {"coordinates":[89.323561,26.283419],"type":"Point"}
}