{
  "type": "Feature",
  "properties": {
    "gn:admin1_code":"01",
    "gn:admin2_code":"638.0",
    "gn:asciiname":"Mohean",
    "gn:country_code":"IN",
    "gn:dem":15,
    "gn:feature_class":"P",
    "gn:feature_code":"PPL",
    "gn:name":"Mohean",
    "gn:population":0,
    "gn:timezone":"Asia/Kolkata",
    "iso:country":"IN",
    "wof:name":"Mohean",
    "wof:placetype":"locality"
},
  "geometry": {"coordinates":[93.31667,7.96667],"type":"Point"}
}