{
  "type": "Feature",
  "properties": {
    "iso:country":"IN",
    "ks:ks_name":"Alhaidadpur Khajwa",
    "ks:ks_pop":1304,
    "ks:ks_type":"VILLAGE",
    "name:eng_x_preferred":[
        "Alhaidadpur Khajwa"
    ],
    "wof:name":"Alhaidadpur Khajwa",
    "wof:placetype":"locality",
    "wof:population":1304
},
  "geometry": {"coordinates":[78.505144,29.440622],"type":"Point"}
}