{
  "type": "Feature",
  "properties": {
    "iso:country":"IN",
    "ks:ks_alt_nam":"hanehalli",
    "ks:ks_name":"Hanehalli",
    "ks:ks_pop":136,
    "ks:ks_type":"HABITATION",
    "name:eng_x_preferred":[
        "Hanehalli"
    ],
    "wof:name":"Hanehalli",
    "wof:placetype":"locality",
    "wof:population":136
},
  "geometry": {"coordinates":[74.639467,14.026186],"type":"Point"}
}