{
  "type": "Feature",
  "properties": {
    "iso:country":"IN",
    "ks:ks_name":"Raybandh",
    "ks:ks_pop":0,
    "ks:ks_type":"VILLAGE",
    "name:eng_x_preferred":[
        "Raybandh"
    ],
    "wof:name":"Raybandh",
    "wof:placetype":"locality",
    "wof:population":0
},
  "geometry": {"coordinates":[86.561717,23.583328],"type":"Point"}
}