{
  "type": "Feature",
  "properties": {
    "gn:admin1_code":"21",
    "gn:admin2_code":"370.0",
    "gn:asciiname":"Telanpali",
    "gn:country_code":"IN",
    "gn:dem":181,
    "gn:feature_class":"P",
    "gn:feature_code":"PPL",
    "gn:name":"Telanp\u0101li",
    "gn:population":0,
    "gn:timezone":"Asia/Kolkata",
    "iso:country":"IN",
    "ks:ks_name":"Telenpali",
    "ks:ks_pop":612,
    "ks:ks_type":"VILLAGE",
    "ks:ks_uagg_main":0,
    "name:eng_x_preferred":[
        "Telenpali"
    ],
    "wof:name":"Telenpali",
    "wof:placetype":"neighbourhood",
    "wof:population":612
},
  "geometry": {"coordinates":[83.657594,21.40788],"type":"Point"}
}