{
  "type": "Feature",
  "properties": {
    "iso:country":"IN",
    "ks:ks_name":"Kanti",
    "ks:ks_pop":1248,
    "ks:ks_type":"VILLAGE",
    "name:eng_x_preferred":[
        "Kanti"
    ],
    "wof:name":"Kanti",
    "wof:placetype":"locality",
    "wof:population":1248
},
  "geometry": {"coordinates":[74.80331,22.455856],"type":"Point"}
}