{
  "type": "Feature",
  "properties": {
    "gn:admin1_code":"23.0",
    "gn:admin2_code":"052",
    "gn:asciiname":"Janetpur",
    "gn:country_code":"IN",
    "gn:dem":296,
    "gn:feature_class":"P",
    "gn:feature_code":"PPL",
    "gn:name":"Janetpur",
    "gn:population":0,
    "gn:timezone":"Asia/Kolkata",
    "iso:country":"IN",
    "wof:name":"Janetpur",
    "wof:placetype":"locality"
},
  "geometry": {"coordinates":[76.82037,30.5586],"type":"Point"}
}