{
  "type": "Feature",
  "properties": {
    "gn:admin1_code":"35.0",
    "gn:admin2_code":"427.0",
    "gn:asciiname":"Umarkhoh",
    "gn:country_code":"IN",
    "gn:dem":504,
    "gn:feature_class":"P",
    "gn:feature_code":"PPL",
    "gn:name":"Umarkhoh",
    "gn:population":0,
    "gn:timezone":"Asia/Kolkata",
    "iso:country":"IN",
    "ks:ks_name":"Umarkhoh",
    "ks:ks_pop":234,
    "ks:ks_type":"VILLAGE",
    "name:eng_x_preferred":[
        "Umarkhoh"
    ],
    "wof:name":"Umarkhoh",
    "wof:placetype":"locality",
    "wof:population":234
},
  "geometry": {"coordinates":[78.957267,23.454969],"type":"Point"}
}