{
  "type": "Feature",
  "properties": {
    "iso:country":"IN",
    "ks:ks_alt_nam":"Ghukrakuna Pt IV",
    "ks:ks_name":"Ghukrakuna Pt Iv",
    "ks:ks_pop":103,
    "ks:ks_type":"HABITATION",
    "name:eng_x_preferred":[
        "Ghukrakuna Pt Iv"
    ],
    "wof:name":"Ghukrakuna Pt Iv",
    "wof:placetype":"locality",
    "wof:population":103
},
  "geometry": {"coordinates":[92.306543,24.739474],"type":"Point"}
}