{
  "type": "Feature",
  "properties": {
    "iso:country":"IN",
    "ks:ks_name":"Vada Andappatu",
    "ks:ks_pop":1563,
    "ks:ks_type":"VILLAGE",
    "ks:ks_uagg_main":0,
    "name:eng_x_preferred":[
        "Vada Andappatu"
    ],
    "wof:name":"Vada Andappatu",
    "wof:placetype":"locality",
    "wof:population":1563
},
  "geometry": {"coordinates":[79.087496,12.272033],"type":"Point"}
}