{
  "type": "Feature",
  "properties": {
    "iso:country":"IN",
    "ks:ks_name":"Kirpa Nathpur",
    "ks:ks_pop":0,
    "ks:ks_type":"VILLAGE",
    "ks:ks_uagg_main":0,
    "name:eng_x_preferred":[
        "Kirpa Nathpur"
    ],
    "wof:name":"Kirpa Nathpur",
    "wof:placetype":"locality",
    "wof:population":0
},
  "geometry": {"coordinates":[78.2196,28.838718],"type":"Point"}
}