{
  "type": "Feature",
  "properties": {
    "gn:admin1_code":"25.0",
    "gn:admin2_code":"606.0",
    "gn:asciiname":"Parvatiagaram",
    "gn:country_code":"IN",
    "gn:dem":173,
    "gn:feature_class":"P",
    "gn:feature_code":"PPL",
    "gn:name":"P\u0101rvatiagaram",
    "gn:population":0,
    "gn:timezone":"Asia/Kolkata",
    "iso:country":"IN",
    "ks:ks_name":"Parvathiagaram",
    "ks:ks_pop":559,
    "ks:ks_type":"VILLAGE",
    "ks:ks_uagg_main":0,
    "name:eng_x_preferred":[
        "Parvathiagaram"
    ],
    "wof:name":"Parvathiagaram",
    "wof:placetype":"neighbourhood",
    "wof:population":559
},
  "geometry": {"coordinates":[79.206993,12.661399],"type":"Point"}
}