{
  "type": "Feature",
  "properties": {
    "iso:country":"IN",
    "ks:ks_name":"Isahakpur",
    "ks:ks_pop":552,
    "ks:ks_type":"VILLAGE",
    "name:eng_x_preferred":[
        "Isahakpur"
    ],
    "wof:name":"Isahakpur",
    "wof:placetype":"locality",
    "wof:population":552
},
  "geometry": {"coordinates":[88.428085,25.256826],"type":"Point"}
}