{
  "type": "Feature",
  "properties": {
    "gn:admin1_code":"12.0",
    "gn:admin2_code":"7.0",
    "gn:asciiname":"Nasion",
    "gn:country_code":"IN",
    "gn:dem":772,
    "gn:feature_class":"P",
    "gn:feature_code":"PPL",
    "gn:name":"N\u0101sion",
    "gn:population":0,
    "gn:timezone":"Asia/Kolkata",
    "iso:country":"IN",
    "name:ara_x_preferred":[
        "\u0623\u0646\u064a\u0641\u0649"
    ],
    "name:fas_x_preferred":[
        "\u062f\u0645\u0627\u063a\u06a9"
    ],
    "name:hun_x_preferred":[
        "Nasion"
    ],
    "name:nno_x_preferred":[
        "Naserot"
    ],
    "name:rus_x_preferred":[
        "\u041d\u0430\u0437\u0438\u043e\u043d"
    ],
    "name:spa_x_preferred":[
        "Nasi\u00f3n"
    ],
    "name:tha_x_preferred":[
        "\u0e40\u0e19\u0e0b\u0e34\u0e2d\u0e2d\u0e19"
    ],
    "name:zho_x_preferred":[
        "\u9f3b\u6839\u9ede"
    ],
    "wof:name":"Nasion",
    "wof:placetype":"locality"
},
  "geometry": {"coordinates":[75.41226,32.60392],"type":"Point"}
}