{
  "type": "Feature",
  "properties": {
    "gn:admin1_code":"36",
    "gn:admin2_code":"194.0",
    "gn:asciiname":"Katahri",
    "gn:country_code":"IN",
    "gn:dem":86,
    "gn:feature_class":"P",
    "gn:feature_code":"PPL",
    "gn:name":"Katahri",
    "gn:population":0,
    "gn:timezone":"Asia/Kolkata",
    "iso:country":"IN",
    "ks:ks_name":"Katahri",
    "ks:ks_type":"VILLAGE",
    "name:eng_x_preferred":[
        "Katahri"
    ],
    "wof:name":"Katahri",
    "wof:placetype":"locality"
},
  "geometry": {"coordinates":[82.56990399999999,25.866249],"type":"Point"}
}