{
  "type": "Feature",
  "properties": {
    "gn:admin1_code":"19.0",
    "gn:admin2_code":"568.0",
    "gn:asciiname":"Kusugundi",
    "gn:country_code":"IN",
    "gn:dem":665,
    "gn:feature_class":"P",
    "gn:feature_code":"PPL",
    "gn:name":"Kusugundi",
    "gn:population":0,
    "gn:timezone":"Asia/Kolkata",
    "iso:country":"IN",
    "ks:ks_name":"Kusgundi",
    "ks:ks_pop":709,
    "ks:ks_type":"VILLAGE",
    "name:eng_x_preferred":[
        "Kusgundi"
    ],
    "name:eng_x_variant":[
        "Kusugundi"
    ],
    "wof:name":"Kusgundi",
    "wof:placetype":"locality",
    "wof:population":709
},
  "geometry": {"coordinates":[75.163121,13.950447],"type":"Point"}
}