{
  "type": "Feature",
  "properties": {
    "iso:country":"IN",
    "ks:ks_name":"Bakchar Bagaria Helegachhi",
    "ks:ks_pop":8965,
    "ks:ks_type":"HABITATION",
    "name:eng_x_preferred":[
        "Bakchar Bagaria Helegachhi"
    ],
    "wof:name":"Bakchar Bagaria Helegachhi",
    "wof:placetype":"locality",
    "wof:population":8965
},
  "geometry": {"coordinates":[88.24051300000001,22.157149],"type":"Point"}
}