{
  "type": "Feature",
  "properties": {
    "gn:admin1_code":"10",
    "gn:admin2_code":"75.0",
    "gn:asciiname":"Garhi Nawab",
    "gn:country_code":"IN",
    "gn:dem":231,
    "gn:feature_class":"P",
    "gn:feature_code":"PPL",
    "gn:name":"Garhi Naw\u0101b",
    "gn:population":0,
    "gn:timezone":"Asia/Kolkata",
    "iso:country":"IN",
    "wof:name":"Garhi Nawab",
    "wof:placetype":"locality"
},
  "geometry": {"coordinates":[77.07711,29.30492000000001],"type":"Point"}
}