{
  "type": "Feature",
  "properties": {
    "iso:country":"IN",
    "ks:ks_name":"Maynagadi",
    "ks:ks_pop":3175,
    "ks:ks_type":"VILLAGE",
    "ks:ks_uagg_main":0,
    "name:eng_x_preferred":[
        "Maynagadi"
    ],
    "wof:name":"Maynagadi",
    "wof:placetype":"neighbourhood",
    "wof:population":3175
},
  "geometry": {"coordinates":[88.480395,22.746389],"type":"Point"}
}