{
  "type": "Feature",
  "properties": {
    "iso:country":"IN",
    "ks:ks_name":"Urthal",
    "ks:ks_pop":571,
    "ks:ks_type":"HABITATION",
    "name:eng_x_preferred":[
        "Urthal"
    ],
    "wof:name":"Urthal",
    "wof:placetype":"locality",
    "wof:population":571
},
  "geometry": {"coordinates":[76.84022400000001,14.850169],"type":"Point"}
}