{
  "type": "Feature",
  "properties": {
    "gn:admin1_code":"24.0",
    "gn:admin2_code":"131.0",
    "gn:asciiname":"Arbara",
    "gn:country_code":"IN",
    "gn:dem":210,
    "gn:feature_class":"P",
    "gn:feature_code":"PPL",
    "gn:name":"Arbara",
    "gn:population":0,
    "gn:timezone":"Asia/Kolkata",
    "iso:country":"IN",
    "wof:name":"Arbara",
    "wof:placetype":"locality"
},
  "geometry": {"coordinates":[74.37396,24.05647],"type":"Point"}
}