{
  "type": "Feature",
  "properties": {
    "iso:country":"IN",
    "ks:ks_name":"Bildehar",
    "ks:ks_pop":823,
    "ks:ks_type":"HABITATION",
    "name:eng_x_preferred":[
        "Bildehar"
    ],
    "wof:name":"Bildehar",
    "wof:placetype":"locality",
    "wof:population":823
},
  "geometry": {"coordinates":[88.72324999999999,22.816713],"type":"Point"}
}