{
  "type": "Feature",
  "properties": {
    "iso:country":"IN",
    "ks:ks_name":"Nevadiya",
    "ks:ks_pop":93,
    "ks:ks_type":"VILLAGE",
    "name:eng_x_preferred":[
        "Nevadiya"
    ],
    "wof:name":"Nevadiya",
    "wof:placetype":"locality",
    "wof:population":93
},
  "geometry": {"coordinates":[80.520602,28.406332],"type":"Point"}
}