{
  "type": "Feature",
  "properties": {
    "iso:country":"IN",
    "ks:ks_name":"Kaleyanpur",
    "ks:ks_pop":10382,
    "ks:ks_type":"VILLAGE",
    "ks:ks_uagg_main":0,
    "name:eng_x_preferred":[
        "Kaleyanpur"
    ],
    "wof:name":"Kaleyanpur",
    "wof:placetype":"neighbourhood",
    "wof:population":10382
},
  "geometry": {"coordinates":[84.9234,26.453488],"type":"Point"}
}