{
  "type": "Feature",
  "properties": {
    "iso:country":"IN",
    "ks:ks_name":"Rajendram",
    "ks:ks_type":"VILLAGE",
    "ks:ks_uagg_main":0,
    "name:eng_x_preferred":[
        "Rajendram"
    ],
    "wof:name":"Rajendram",
    "wof:placetype":"neighbourhood"
},
  "geometry": {"coordinates":[78.446068,10.919242],"type":"Point"}
}