{
  "type": "Feature",
  "properties": {
    "iso:country":"IN",
    "ks:ks_name":"Amirti",
    "ks:ks_pop":17,
    "ks:ks_type":"VILLAGE",
    "name:eng_x_preferred":[
        "Amirti"
    ],
    "wof:name":"Amirti",
    "wof:placetype":"locality",
    "wof:population":17
},
  "geometry": {"coordinates":[83.468847,25.224293],"type":"Point"}
}