{
  "type": "Feature",
  "properties": {
    "iso:country":"IN",
    "ks:ks_name":"Joshiyara",
    "ks:ks_pop":1196,
    "ks:ks_type":"VILLAGE",
    "ks:ks_uagg_main":0,
    "name:eng_x_preferred":[
        "Joshiyara"
    ],
    "wof:name":"Joshiyara",
    "wof:placetype":"neighbourhood",
    "wof:population":1196
},
  "geometry": {"coordinates":[78.433543,30.72948],"type":"Point"}
}