{
  "type": "Feature",
  "properties": {
    "iso:country":"IN",
    "ks:ks_name":"Dalkaje",
    "ks:ks_pop":226,
    "ks:ks_type":"HABITATION",
    "name:eng_x_preferred":[
        "Dalkaje"
    ],
    "wof:name":"Dalkaje",
    "wof:placetype":"locality",
    "wof:population":226
},
  "geometry": {"coordinates":[75.15468300000001,12.729641],"type":"Point"}
}