{
  "type": "Feature",
  "properties": {
    "iso:country":"IN",
    "ks:ks_alt_nam":"P\u0101n\u0101pur",
    "ks:ks_name":"Panapur",
    "ks:ks_type":"VILLAGE",
    "name:eng_x_preferred":[
        "Panapur"
    ],
    "name:eng_x_variant":[
        "P\u0101n\u0101pur"
    ],
    "wof:name":"Panapur",
    "wof:placetype":"locality"
},
  "geometry": {"coordinates":[83.826064,24.899212],"type":"Point"}
}