{
  "type": "Feature",
  "properties": {
    "iso:country":"IN",
    "qs:name":"Vaikuntapuram",
    "qs:name_adm0":"India",
    "qs:name_adm1":"Tamil Nadu",
    "qs:photos":46,
    "qs:photos_1k":9,
    "qs:photos_9k":1,
    "qs:photos_9r":2,
    "qs:photos_all":46,
    "qs:photos_sr":2,
    "qs:placetype":"Suburb",
    "qs:pop_sr":"0",
    "wof:name":"Vaikuntapuram",
    "wof:placetype":"neighbourhood"
},
  "geometry": {"coordinates":[80.23743649999999,13.057048],"type":"Point"}
}