{
  "type": "Feature",
  "properties": {
    "iso:country":"IN",
    "ks:ks_name":"Gangarkarwadi",
    "ks:ks_pop":196,
    "ks:ks_type":"HABITATION",
    "name:eng_x_preferred":[
        "Gangarkarwadi"
    ],
    "wof:name":"Gangarkarwadi",
    "wof:placetype":"locality",
    "wof:population":196
},
  "geometry": {"coordinates":[73.480772,16.943274],"type":"Point"}
}