{
  "type": "Feature",
  "properties": {
    "gn:admin1_code":"16",
    "gn:admin2_code":"509.0",
    "gn:asciiname":"Madnapur",
    "gn:country_code":"IN",
    "gn:dem":227,
    "gn:feature_class":"P",
    "gn:feature_code":"PPL",
    "gn:name":"Madn\u0101pur",
    "gn:population":0,
    "gn:timezone":"Asia/Kolkata",
    "iso:country":"IN",
    "name:urd_x_preferred":[
        "\u0645\u062f\u0646\u0627\u067e\u0648\u0631"
    ],
    "wof:name":"Madnapur",
    "wof:placetype":"locality"
},
  "geometry": {"coordinates":[79.40959000000002,20.39145],"type":"Point"}
}