{
  "type": "Feature",
  "properties": {
    "gn:admin1_code":"38.0",
    "gn:admin2_code":"358.0",
    "gn:asciiname":"Kisaini",
    "gn:country_code":"IN",
    "gn:dem":279,
    "gn:feature_class":"P",
    "gn:feature_code":"PPL",
    "gn:name":"Kisain\u012b",
    "gn:population":0,
    "gn:timezone":"Asia/Kolkata",
    "iso:country":"IN",
    "ks:ks_alt_nam":"Kisain\u012b",
    "ks:ks_name":"Kisaini",
    "ks:ks_pop":1097,
    "ks:ks_type":"VILLAGE",
    "name:eng_x_preferred":[
        "Kisaini"
    ],
    "name:eng_x_variant":[
        "Kisain\u012b"
    ],
    "wof:name":"Kisaini",
    "wof:placetype":"locality",
    "wof:population":1097
},
  "geometry": {"coordinates":[84.227058,24.212161],"type":"Point"}
}