{
  "type": "Feature",
  "properties": {
    "gn:admin1_code":"37",
    "gn:admin2_code":"410.0",
    "gn:asciiname":"Pendrabandh",
    "gn:country_code":"IN",
    "gn:dem":243,
    "gn:feature_class":"P",
    "gn:feature_code":"PPL",
    "gn:name":"Pendrabandh",
    "gn:population":0,
    "gn:timezone":"Asia/Kolkata",
    "iso:country":"IN",
    "ks:ks_alt_nam":"Pendrabandh",
    "ks:ks_name":"Pendraban",
    "ks:ks_type":"VILLAGE",
    "ks:ks_uagg_main":0,
    "name:eng_x_preferred":[
        "Pendraban"
    ],
    "name:eng_x_variant":[
        "Pendrabandh"
    ],
    "wof:name":"Pendraban",
    "wof:placetype":"neighbourhood"
},
  "geometry": {"coordinates":[82.93903899999999,21.649867],"type":"Point"}
}