{
  "type": "Feature",
  "properties": {
    "iso:country":"IN",
    "ks:ks_name":"Terali",
    "ks:ks_pop":155,
    "ks:ks_type":"VILLAGE",
    "name:eng_x_preferred":[
        "Terali"
    ],
    "wof:name":"Terali",
    "wof:placetype":"locality",
    "wof:population":155
},
  "geometry": {"coordinates":[74.368759,15.179169],"type":"Point"}
}