{
  "type": "Feature",
  "properties": {
    "iso:country":"IN",
    "ks:ks_name":"Longmura Tokbi",
    "ks:ks_pop":63,
    "ks:ks_type":"HABITATION",
    "name:eng_x_preferred":[
        "Longmura Tokbi"
    ],
    "wof:name":"Longmura Tokbi",
    "wof:placetype":"locality",
    "wof:population":63
},
  "geometry": {"coordinates":[93.663431,26.567554],"type":"Point"}
}