{
  "type": "Feature",
  "properties": {
    "iso:country":"IN",
    "ks:ks_name":"Eachankadu",
    "ks:ks_pop":272,
    "ks:ks_type":"HABITATION",
    "name:eng_x_preferred":[
        "Eachankadu"
    ],
    "wof:name":"Eachankadu",
    "wof:placetype":"locality",
    "wof:population":272
},
  "geometry": {"coordinates":[78.79044500000001,11.308223],"type":"Point"}
}