{
  "type": "Feature",
  "properties": {
    "gn:admin1_code":"36",
    "gn:admin2_code":"191.0",
    "gn:asciiname":"Tandwa",
    "gn:country_code":"IN",
    "gn:dem":82,
    "gn:feature_class":"P",
    "gn:feature_code":"PPL",
    "gn:name":"Tandwa",
    "gn:population":0,
    "gn:timezone":"Asia/Kolkata",
    "iso:country":"IN",
    "ks:ks_name":"Tandwa",
    "ks:ks_type":"VILLAGE",
    "ks:ks_uagg_main":0,
    "wof:name":"Tandwa",
    "wof:placetype":"neighbourhood"
},
  "geometry": {"coordinates":[83.27603000000001,25.89169],"type":"Point"}
}