{
  "type": "Feature",
  "properties": {
    "iso:country":"IN",
    "ks:ks_name":"Billaputtu",
    "ks:ks_pop":152,
    "ks:ks_type":"HABITATION",
    "name:eng_x_preferred":[
        "Billaputtu"
    ],
    "wof:name":"Billaputtu",
    "wof:placetype":"locality",
    "wof:population":152
},
  "geometry": {"coordinates":[82.84054,18.245134],"type":"Point"}
}