{
  "type": "Feature",
  "properties": {
    "gn:admin1_code":"37",
    "gn:admin2_code":"408.0",
    "gn:asciiname":"Paddatola",
    "gn:country_code":"IN",
    "gn:dem":406,
    "gn:feature_class":"P",
    "gn:feature_code":"PPL",
    "gn:name":"Padd\u0101tola",
    "gn:population":0,
    "gn:timezone":"Asia/Kolkata",
    "iso:country":"IN",
    "wof:name":"Paddatola",
    "wof:placetype":"locality"
},
  "geometry": {"coordinates":[80.85191999999998,20.6591],"type":"Point"}
}