{
  "type": "Feature",
  "properties": {
    "iso:country":"IN",
    "ks:ks_name":"Padubettu",
    "ks:ks_pop":110,
    "ks:ks_type":"HABITATION",
    "name:eng_x_preferred":[
        "Padubettu"
    ],
    "wof:name":"Padubettu",
    "wof:placetype":"locality",
    "wof:population":110
},
  "geometry": {"coordinates":[74.852923,13.29333],"type":"Point"}
}