{
  "type": "Feature",
  "properties": {
    "iso:country":"IN",
    "ks:ks_name":"Chaita Mali",
    "ks:ks_pop":483,
    "ks:ks_type":"VILLAGE",
    "name:eng_x_preferred":[
        "Chaita Mali"
    ],
    "wof:name":"Chaita Mali",
    "wof:placetype":"locality",
    "wof:population":483
},
  "geometry": {"coordinates":[87.7056,21.92764],"type":"Point"}
}