{
  "type": "Feature",
  "properties": {
    "iso:country":"IN",
    "ks:ks_alt_nam":"THANJAKKUR",
    "ks:ks_name":"Thanjakkur",
    "ks:ks_pop":747,
    "ks:ks_type":"HABITATION",
    "name:eng_x_preferred":[
        "Thanjakkur"
    ],
    "wof:name":"Thanjakkur",
    "wof:placetype":"locality",
    "wof:population":747
},
  "geometry": {"coordinates":[78.346836,9.719715],"type":"Point"}
}