{
  "type": "Feature",
  "properties": {
    "iso:country":"IN",
    "ks:ks_alt_nam":"LUNRI",
    "ks:ks_name":"Lunri",
    "ks:ks_pop":74,
    "ks:ks_type":"HABITATION",
    "name:eng_x_preferred":[
        "Lunri"
    ],
    "wof:name":"Lunri",
    "wof:placetype":"locality",
    "wof:population":74
},
  "geometry": {"coordinates":[85.27094700000001,23.92779],"type":"Point"}
}