{
  "type": "Feature",
  "properties": {
    "iso:country":"IN",
    "ks:ks_name":"Burumwadi",
    "ks:ks_pop":147,
    "ks:ks_type":"HABITATION",
    "name:eng_x_preferred":[
        "Burumwadi"
    ],
    "wof:name":"Burumwadi",
    "wof:placetype":"locality",
    "wof:population":147
},
  "geometry": {"coordinates":[73.382645,17.801416],"type":"Point"}
}