{
  "type": "Feature",
  "properties": {
    "iso:country":"IN",
    "ks:ks_name":"Rai Srirampur",
    "ks:ks_pop":208,
    "ks:ks_type":"HABITATION",
    "name:eng_x_preferred":[
        "Rai Srirampur"
    ],
    "wof:name":"Rai Srirampur",
    "wof:placetype":"locality",
    "wof:population":208
},
  "geometry": {"coordinates":[85.888499,20.231296],"type":"Point"}
}