{
  "type": "Feature",
  "properties": {
    "iso:country":"IN",
    "ks:ks_name":"Gazipur",
    "ks:ks_pop":312,
    "ks:ks_type":"VILLAGE",
    "name:eng_x_preferred":[
        "Gazipur"
    ],
    "wof:name":"Gazipur",
    "wof:placetype":"locality",
    "wof:population":312
},
  "geometry": {"coordinates":[87.697379,22.059117],"type":"Point"}
}