{
  "type": "Feature",
  "properties": {
    "iso:country":"IN",
    "ks:ks_name":"Siunapada",
    "ks:ks_pop":48,
    "ks:ks_type":"HABITATION",
    "name:eng_x_preferred":[
        "Siunapada"
    ],
    "wof:name":"Siunapada",
    "wof:placetype":"locality",
    "wof:population":48
},
  "geometry": {"coordinates":[82.71832999999999,19.011599],"type":"Point"}
}