{
  "type": "Feature",
  "properties": {
    "gn:admin1_code":"19.0",
    "gn:admin2_code":"572.0",
    "gn:asciiname":"Bilijaji",
    "gn:country_code":"IN",
    "gn:dem":855,
    "gn:feature_class":"P",
    "gn:feature_code":"PPL",
    "gn:name":"Bilij\u0101ji",
    "gn:population":0,
    "gn:timezone":"Asia/Kolkata",
    "iso:country":"IN",
    "ks:ks_alt_nam":"Bilij\u0101ji",
    "ks:ks_name":"Bilijaji",
    "ks:ks_pop":818,
    "ks:ks_type":"VILLAGE",
    "ks:ks_uagg_main":0,
    "name:eng_x_preferred":[
        "Bilijaji"
    ],
    "name:eng_x_variant":[
        "Bilij\u0101ji"
    ],
    "wof:name":"Bilijaji",
    "wof:placetype":"locality",
    "wof:population":818
},
  "geometry": {"coordinates":[77.473844,13.126779],"type":"Point"}
}