{
  "type": "Feature",
  "properties": {
    "iso:country":"IN",
    "ks:ks_name":"Thiruvathipatti",
    "ks:ks_pop":150,
    "ks:ks_type":"HABITATION",
    "name:eng_x_preferred":[
        "Thiruvathipatti"
    ],
    "wof:name":"Thiruvathipatti",
    "wof:placetype":"locality",
    "wof:population":150
},
  "geometry": {"coordinates":[78.84590900000001,10.494882],"type":"Point"}
}