{
  "type": "Feature",
  "properties": {
    "iso:country":"IN",
    "ks:ks_alt_nam":"bommanamanekeri",
    "ks:ks_name":"Bommanamanekeri",
    "ks:ks_pop":145,
    "ks:ks_type":"HABITATION",
    "name:eng_x_preferred":[
        "Bommanamanekeri"
    ],
    "wof:name":"Bommanamanekeri",
    "wof:placetype":"locality",
    "wof:population":145
},
  "geometry": {"coordinates":[74.580787,13.938904],"type":"Point"}
}