{
  "type": "Feature",
  "properties": {
    "iso:country":"IN",
    "ks:ks_name":"Santhal Tola",
    "ks:ks_pop":482,
    "ks:ks_type":"HABITATION",
    "name:eng_x_preferred":[
        "Santhal Tola"
    ],
    "wof:name":"Santhal Tola",
    "wof:placetype":"locality",
    "wof:population":482
},
  "geometry": {"coordinates":[86.38277100000001,24.862453],"type":"Point"}
}