{
  "type": "Feature",
  "properties": {
    "iso:country":"IN",
    "ks:ks_name":"Paidagarh",
    "ks:ks_type":"VILLAGE",
    "name:eng_x_preferred":[
        "Paidagarh"
    ],
    "wof:name":"Paidagarh",
    "wof:placetype":"locality"
},
  "geometry": {"coordinates":[79.14372899999999,29.010861],"type":"Point"}
}