{
  "type": "Feature",
  "properties": {
    "iso:country":"IN",
    "ks:ks_name":"Harisinghpur Tarai",
    "ks:ks_pop":484,
    "ks:ks_type":"VILLAGE",
    "name:eng_x_preferred":[
        "Harisinghpur Tarai"
    ],
    "wof:name":"Harisinghpur Tarai",
    "wof:placetype":"locality",
    "wof:population":484
},
  "geometry": {"coordinates":[79.46653999999999,27.563824],"type":"Point"}
}