{
  "type": "Feature",
  "properties": {
    "gn:admin1_code":"36",
    "gn:admin2_code":"134.0",
    "gn:asciiname":"Faizipur Kasba",
    "gn:country_code":"IN",
    "gn:dem":226,
    "gn:feature_class":"P",
    "gn:feature_code":"PPL",
    "gn:name":"Faiz\u012bpur Kasba",
    "gn:population":0,
    "gn:timezone":"Asia/Kolkata",
    "iso:country":"IN",
    "ks:ks_alt_nam":"Faiz\u012bpur Kasba",
    "ks:ks_name":"Faizipur Kasba",
    "ks:ks_type":"VILLAGE",
    "name:eng_x_preferred":[
        "Faizipur Kasba"
    ],
    "name:eng_x_variant":[
        "Faiz\u012bpur Kasba"
    ],
    "wof:name":"Faizipur Kasba",
    "wof:placetype":"locality"
},
  "geometry": {"coordinates":[78.286354,29.125312],"type":"Point"}
}