{
  "type": "Feature",
  "properties": {
    "gn:admin1_code":"37",
    "gn:admin2_code":"403.0",
    "gn:asciiname":"Kasturamal",
    "gn:country_code":"IN",
    "gn:dem":277,
    "gn:feature_class":"P",
    "gn:feature_code":"PPL",
    "gn:name":"Kasturam\u0101l",
    "gn:population":0,
    "gn:timezone":"Asia/Kolkata",
    "iso:country":"IN",
    "ks:ks_alt_nam":"Kasturam\u0101l",
    "ks:ks_name":"Kasturamal",
    "ks:ks_pop":314,
    "ks:ks_type":"VILLAGE",
    "name:eng_x_preferred":[
        "Kasturamal"
    ],
    "name:eng_x_variant":[
        "Kasturam\u0101l"
    ],
    "wof:name":"Kasturamal",
    "wof:placetype":"locality",
    "wof:population":314
},
  "geometry": {"coordinates":[83.348574,21.448086],"type":"Point"}
}