{
  "type": "Feature",
  "properties": {
    "iso:country":"IN",
    "ks:ks_name":"Khairdungri",
    "ks:ks_pop":464,
    "ks:ks_type":"VILLAGE",
    "name:eng_x_preferred":[
        "Khairdungri"
    ],
    "wof:name":"Khairdungri",
    "wof:placetype":"locality",
    "wof:population":464
},
  "geometry": {"coordinates":[86.914624,22.807409],"type":"Point"}
}