{
  "type": "Feature",
  "properties": {
    "iso:country":"IN",
    "ks:ks_alt_nam":"JHC 41 Shiroor",
    "ks:ks_name":"Jhc 41 Shiroor",
    "ks:ks_pop":245,
    "ks:ks_type":"HABITATION",
    "name:eng_x_preferred":[
        "Jhc 41 Shiroor"
    ],
    "wof:name":"Jhc 41 Shiroor",
    "wof:placetype":"locality",
    "wof:population":245
},
  "geometry": {"coordinates":[74.933758,13.335673],"type":"Point"}
}