{
  "type": "Feature",
  "properties": {
    "iso:country":"IN",
    "ks:ks_name":"Ratwa",
    "ks:ks_pop":31,
    "ks:ks_type":"VILLAGE",
    "name:eng_x_preferred":[
        "Ratwa"
    ],
    "wof:name":"Ratwa",
    "wof:placetype":"locality",
    "wof:population":31
},
  "geometry": {"coordinates":[69.638398,26.976118],"type":"Point"}
}