{
  "type": "Feature",
  "properties": {
    "gn:admin1_code":"11.0",
    "gn:admin2_code":"27.0",
    "gn:asciiname":"Janjohi",
    "gn:country_code":"IN",
    "gn:dem":1539,
    "gn:feature_class":"P",
    "gn:feature_code":"PPL",
    "gn:name":"Janjohi",
    "gn:population":0,
    "gn:timezone":"Asia/Kolkata",
    "iso:country":"IN",
    "wof:name":"Janjohi",
    "wof:placetype":"locality"
},
  "geometry": {"coordinates":[77.02554000000001,31.68286],"type":"Point"}
}