{
  "type": "Feature",
  "properties": {
    "iso:country":"IN",
    "ks:ks_alt_nam":"Kojabi mal",
    "ks:ks_name":"Kojabi Mal",
    "ks:ks_pop":1188,
    "ks:ks_type":"HABITATION",
    "name:eng_x_preferred":[
        "Kojabi Mal"
    ],
    "wof:name":"Kojabi Mal",
    "wof:placetype":"locality",
    "wof:population":1188
},
  "geometry": {"coordinates":[79.626496,20.448722],"type":"Point"}
}