{
  "type": "Feature",
  "properties": {
    "gn:admin1_code":"11",
    "gn:admin2_code":"24.0",
    "gn:asciiname":"Pharehr",
    "gn:country_code":"IN",
    "gn:dem":1011,
    "gn:feature_class":"P",
    "gn:feature_code":"PPL",
    "gn:name":"Pharehr",
    "gn:population":0,
    "gn:timezone":"Asia/Kolkata",
    "iso:country":"IN",
    "wof:name":"Pharehr",
    "wof:placetype":"locality"
},
  "geometry": {"coordinates":[76.47452,32.07700999999999],"type":"Point"}
}