{
  "type": "Feature",
  "properties": {
    "iso:country":"IN",
    "ks:ks_name":"Ramchandrapur",
    "ks:ks_pop":3014,
    "ks:ks_type":"VILLAGE",
    "ks:ks_uagg_main":0,
    "name:eng_x_preferred":[
        "Ramchandrapur"
    ],
    "wof:name":"Ramchandrapur",
    "wof:placetype":"neighbourhood",
    "wof:population":3014
},
  "geometry": {"coordinates":[87.98395499999999,22.457655],"type":"Point"}
}