{
  "type": "Feature",
  "properties": {
    "iso:country":"IN",
    "ks:ks_name":"Jharabaida",
    "ks:ks_pop":50,
    "ks:ks_type":"VILLAGE",
    "name:eng_x_preferred":[
        "Jharabaida"
    ],
    "wof:name":"Jharabaida",
    "wof:placetype":"locality",
    "wof:population":50
},
  "geometry": {"coordinates":[84.186053,19.621495],"type":"Point"}
}