{
  "type": "Feature",
  "properties": {
    "gn:admin1_code":"36",
    "gn:admin2_code":"200.0",
    "gn:asciiname":"Rajkhaur",
    "gn:country_code":"IN",
    "gn:dem":248,
    "gn:feature_class":"P",
    "gn:feature_code":"PPL",
    "gn:name":"Rajkhaur",
    "gn:population":0,
    "gn:timezone":"Asia/Kolkata",
    "iso:country":"IN",
    "ks:ks_name":"Rajkhaur",
    "ks:ks_type":"VILLAGE",
    "name:eng_x_preferred":[
        "Rajkhaur"
    ],
    "wof:name":"Rajkhaur",
    "wof:placetype":"locality"
},
  "geometry": {"coordinates":[83.201807,24.217983],"type":"Point"}
}