{
  "type": "Feature",
  "properties": {
    "iso:country":"IN",
    "ks:ks_name":"Ajeetgarh",
    "ks:ks_pop":1814,
    "ks:ks_type":"VILLAGE",
    "ks:ks_uagg_main":0,
    "name:eng_x_preferred":[
        "Ajeetgarh"
    ],
    "wof:name":"Ajeetgarh",
    "wof:placetype":"neighbourhood",
    "wof:population":1814
},
  "geometry": {"coordinates":[75.183093,27.974091],"type":"Point"}
}