{
  "type": "Feature",
  "properties": {
    "iso:country":"IN",
    "ks:ks_name":"Pujara Ka Uttar Tola",
    "ks:ks_pop":210,
    "ks:ks_type":"HABITATION",
    "ks:ks_uagg_main":0,
    "name:eng_x_preferred":[
        "Pujara Ka Uttar Tola"
    ],
    "wof:name":"Pujara Ka Uttar Tola",
    "wof:placetype":"neighbourhood",
    "wof:population":210
},
  "geometry": {"coordinates":[84.04327600000001,26.988054],"type":"Point"}
}