{
  "type": "Feature",
  "properties": {
    "iso:country":"IN",
    "ks:ks_name":"Banpoi",
    "ks:ks_pop":609,
    "ks:ks_type":"HABITATION",
    "name:eng_x_preferred":[
        "Banpoi"
    ],
    "wof:name":"Banpoi",
    "wof:placetype":"locality",
    "wof:population":609
},
  "geometry": {"coordinates":[79.46270800000001,27.319269],"type":"Point"}
}