{
  "type": "Feature",
  "properties": {
    "iso:country":"IN",
    "ks:ks_name":"Yargod",
    "ks:ks_pop":46,
    "ks:ks_type":"HABITATION",
    "name:eng_x_preferred":[
        "Yargod"
    ],
    "wof:name":"Yargod",
    "wof:placetype":"locality",
    "wof:population":46
},
  "geometry": {"coordinates":[74.52849500000001,14.255374],"type":"Point"}
}