{
  "type": "Feature",
  "properties": {
    "gn:admin1_code":"35",
    "gn:admin2_code":"463.0",
    "gn:asciiname":"Haraiya",
    "gn:country_code":"IN",
    "gn:dem":307,
    "gn:feature_class":"P",
    "gn:feature_code":"PPL",
    "gn:name":"Haraiya",
    "gn:population":0,
    "gn:timezone":"Asia/Kolkata",
    "iso:country":"IN",
    "ks:ks_name":"Haraiya",
    "ks:ks_type":"VILLAGE",
    "name:ceb_x_preferred":[
        "Haraiya"
    ],
    "name:eng_x_preferred":[
        "Haraiya"
    ],
    "name:fra_x_preferred":[
        "Haraiya"
    ],
    "name:hin_x_preferred":[
        "\u0939\u0930\u093f\u092f\u093e"
    ],
    "name:mai_x_preferred":[
        "\u0939\u0930\u0948\u092f\u093e"
    ],
    "name:msa_x_preferred":[
        "Haraiya"
    ],
    "name:nep_x_preferred":[
        "\u0939\u0930\u0948\u092f\u093e"
    ],
    "name:new_x_preferred":[
        "\u0939\u0930\u093f\u092f\u093e"
    ],
    "name:pol_x_preferred":[
        "Haraiya"
    ],
    "wof:name":"Haraiya",
    "wof:placetype":"locality"
},
  "geometry": {"coordinates":[82.523346,24.124012],"type":"Point"}
}