{
  "type": "Feature",
  "properties": {
    "iso:country":"IN",
    "ks:ks_name":"Jhagrahi",
    "ks:ks_pop":237,
    "ks:ks_type":"VILLAGE",
    "name:eng_x_preferred":[
        "Jhagrahi"
    ],
    "wof:name":"Jhagrahi",
    "wof:placetype":"locality",
    "wof:population":237
},
  "geometry": {"coordinates":[87.373959,24.381625],"type":"Point"}
}