{
  "type": "Feature",
  "properties": {
    "iso:country":"IN",
    "ks:ks_name":"Matha Gaon",
    "ks:ks_pop":500,
    "ks:ks_type":"HABITATION",
    "ks:ks_uagg_main":0,
    "name:eng_x_preferred":[
        "Matha Gaon"
    ],
    "wof:name":"Matha Gaon",
    "wof:placetype":"neighbourhood",
    "wof:population":500
},
  "geometry": {"coordinates":[81.400257,26.517095],"type":"Point"}
}