{
  "type": "Feature",
  "properties": {
    "iso:country":"IN",
    "ks:ks_name":"Hosamaru",
    "ks:ks_pop":255,
    "ks:ks_type":"HABITATION",
    "name:eng_x_preferred":[
        "Hosamaru"
    ],
    "wof:name":"Hosamaru",
    "wof:placetype":"locality",
    "wof:population":255
},
  "geometry": {"coordinates":[75.177592,12.939537],"type":"Point"}
}