{
  "type": "Feature",
  "properties": {
    "iso:country":"IN",
    "ks:ks_name":"Sadala Chak",
    "ks:ks_pop":45,
    "ks:ks_type":"HABITATION",
    "ks:ks_uagg_main":0,
    "name:eng_x_preferred":[
        "Sadala Chak"
    ],
    "wof:name":"Sadala Chak",
    "wof:placetype":"neighbourhood",
    "wof:population":45
},
  "geometry": {"coordinates":[85.02971599999999,25.256821],"type":"Point"}
}