{
  "type": "Feature",
  "properties": {
    "gn:admin1_code":"2.0",
    "gn:admin2_code":"551.0",
    "gn:asciiname":"Maddelavandlapalle",
    "gn:country_code":"IN",
    "gn:dem":338,
    "gn:feature_class":"P",
    "gn:feature_code":"PPL",
    "gn:name":"Maddelav\u0101ndlapalle",
    "gn:population":0,
    "gn:timezone":"Asia/Kolkata",
    "iso:country":"IN",
    "wof:name":"Maddelavandlapalle",
    "wof:placetype":"locality"
},
  "geometry": {"coordinates":[78.89790000000001,14.11206],"type":"Point"}
}