{
  "type": "Feature",
  "properties": {
    "iso:country":"IN",
    "ks:ks_name":"Thakur Deen Garerianpurwa",
    "ks:ks_pop":150,
    "ks:ks_type":"HABITATION",
    "ks:ks_uagg_main":0,
    "name:eng_x_preferred":[
        "Thakur Deen Garerianpurwa"
    ],
    "wof:name":"Thakur Deen Garerianpurwa",
    "wof:placetype":"neighbourhood",
    "wof:population":150
},
  "geometry": {"coordinates":[81.90663600000001,27.011926],"type":"Point"}
}