{
  "type": "Feature",
  "properties": {
    "iso:country":"IN",
    "ks:ks_name":"13 FTP",
    "ks:ks_pop":70,
    "ks:ks_type":"VILLAGE",
    "name:eng_x_preferred":[
        "13 FTP"
    ],
    "wof:name":"13 FTP",
    "wof:placetype":"locality",
    "wof:population":70
},
  "geometry": {"coordinates":[74.45904400000001,29.616022],"type":"Point"}
}