{
  "type": "Feature",
  "properties": {
    "iso:country":"IN",
    "ks:ks_name":"Guttigaru Pete",
    "ks:ks_pop":1215,
    "ks:ks_type":"HABITATION",
    "name:eng_x_preferred":[
        "Guttigaru Pete"
    ],
    "wof:name":"Guttigaru Pete",
    "wof:placetype":"locality",
    "wof:population":1215
},
  "geometry": {"coordinates":[75.395813,12.509498],"type":"Point"}
}