{
  "type": "Feature",
  "properties": {
    "iso:country":"IN",
    "ks:ks_name":"Burudihi",
    "ks:ks_pop":82,
    "ks:ks_type":"VILLAGE",
    "name:eng_x_preferred":[
        "Burudihi"
    ],
    "wof:name":"Burudihi",
    "wof:placetype":"locality",
    "wof:population":82
},
  "geometry": {"coordinates":[86.195739,21.788874],"type":"Point"}
}