{
  "type": "Feature",
  "properties": {
    "gn:admin1_code":"34.0",
    "gn:admin2_code":"204.0",
    "gn:asciiname":"Barwa",
    "gn:country_code":"IN",
    "gn:dem":71,
    "gn:feature_class":"P",
    "gn:feature_code":"PPL",
    "gn:name":"B\u0101rwa",
    "gn:population":0,
    "gn:timezone":"Asia/Kolkata",
    "iso:country":"IN",
    "name:deu_x_preferred":[
        "Barwa"
    ],
    "name:slv_x_preferred":[
        "Barwa"
    ],
    "wof:name":"Barwa",
    "wof:placetype":"locality"
},
  "geometry": {"coordinates":[84.82864000000002,26.56478],"type":"Point"}
}