{
  "type": "Feature",
  "properties": {
    "iso:country":"IN",
    "ks:ks_name":"Kotadamakki",
    "ks:ks_pop":296,
    "ks:ks_type":"HABITATION",
    "name:eng_x_preferred":[
        "Kotadamakki"
    ],
    "wof:name":"Kotadamakki",
    "wof:placetype":"locality",
    "wof:population":296
},
  "geometry": {"coordinates":[74.49875900000001,14.076578],"type":"Point"}
}