{
  "type": "Feature",
  "properties": {
    "iso:country":"IN",
    "ks:ks_name":"Bengda",
    "ks:ks_pop":1997,
    "ks:ks_type":"VILLAGE",
    "name:eng_x_preferred":[
        "Bengda"
    ],
    "wof:name":"Bengda",
    "wof:placetype":"locality",
    "wof:population":1997
},
  "geometry": {"coordinates":[87.340799,22.098405],"type":"Point"}
}