{
  "type": "Feature",
  "properties": {
    "gn:admin1_code":"34.0",
    "gn:admin2_code":"206.0",
    "gn:asciiname":"Dumarpatti",
    "gn:country_code":"IN",
    "gn:dem":61,
    "gn:feature_class":"P",
    "gn:feature_code":"PPL",
    "gn:name":"Dumarpatti",
    "gn:population":0,
    "gn:timezone":"Asia/Kolkata",
    "iso:country":"IN",
    "wof:name":"Dumarpatti",
    "wof:placetype":"locality"
},
  "geometry": {"coordinates":[85.74927,26.50144],"type":"Point"}
}