{
  "type": "Feature",
  "properties": {
    "iso:country":"IN",
    "ks:ks_name":"P Gayadeen",
    "ks:ks_pop":112,
    "ks:ks_type":"HABITATION",
    "ks:ks_uagg_main":0,
    "name:eng_x_preferred":[
        "P Gayadeen"
    ],
    "wof:name":"P Gayadeen",
    "wof:placetype":"neighbourhood",
    "wof:population":112
},
  "geometry": {"coordinates":[81.385002,26.209127],"type":"Point"}
}