{
  "type": "Feature",
  "properties": {
    "gn:admin1_code":"36",
    "gn:admin2_code":"153.0",
    "gn:asciiname":"Purwa Badali",
    "gn:country_code":"IN",
    "gn:dem":134,
    "gn:feature_class":"P",
    "gn:feature_code":"PPL",
    "gn:name":"Purwa Bad\u0101li",
    "gn:population":0,
    "gn:timezone":"Asia/Kolkata",
    "iso:country":"IN",
    "wof:name":"Purwa Badali",
    "wof:placetype":"neighbourhood"
},
  "geometry": {"coordinates":[81.01475000000001,27.99066],"type":"Point"}
}