{
  "type": "Feature",
  "properties": {
    "gn:admin1_code":"35",
    "gn:admin2_code":"455.0",
    "gn:asciiname":"Bhimalgarh",
    "gn:country_code":"IN",
    "gn:dem":773,
    "gn:feature_class":"P",
    "gn:feature_code":"PPL",
    "gn:name":"Bh\u012bmalgarh",
    "gn:population":0,
    "gn:timezone":"Asia/Kolkata",
    "iso:country":"IN",
    "ks:ks_alt_nam":"Bh\u012bmalgarh",
    "ks:ks_name":"Bhimalgarh",
    "ks:ks_type":"VILLAGE",
    "name:eng_x_preferred":[
        "Bhimalgarh"
    ],
    "name:eng_x_variant":[
        "Bh\u012bmalgarh"
    ],
    "wof:name":"Bhimalgarh",
    "wof:placetype":"locality"
},
  "geometry": {"coordinates":[78.979105,22.475133],"type":"Point"}
}