{
  "type": "Feature",
  "properties": {
    "gn:admin1_code":"28",
    "gn:admin2_code":"327.0",
    "gn:asciiname":"Panchanai",
    "gn:country_code":"IN",
    "gn:dem":123,
    "gn:feature_class":"P",
    "gn:feature_code":"PPL",
    "gn:name":"Panchanai",
    "gn:population":0,
    "gn:timezone":"Asia/Kolkata",
    "iso:country":"IN",
    "name:und_x_variant":[
        "Panchanai Junction",
        "Panchanai"
    ],
    "wof:name":"Panchanai",
    "wof:placetype":"locality"
},
  "geometry": {"coordinates":[88.40369,26.73482000000001],"type":"Point"}
}