{
  "type": "Feature",
  "properties": {
    "iso:country":"IN",
    "ks:ks_name":"Mugdi",
    "ks:ks_pop":819,
    "ks:ks_type":"VILLAGE",
    "name:eng_x_preferred":[
        "Mugdi"
    ],
    "wof:name":"Mugdi",
    "wof:placetype":"locality",
    "wof:population":819
},
  "geometry": {"coordinates":[91.28318299999999,26.297043],"type":"Point"}
}