{
  "type": "Feature",
  "properties": {
    "iso:country":"IN",
    "ks:ks_name":"Memberpara",
    "ks:ks_pop":187,
    "ks:ks_type":"HABITATION",
    "ks:ks_uagg_main":0,
    "name:eng_x_preferred":[
        "Memberpara"
    ],
    "wof:name":"Memberpara",
    "wof:placetype":"neighbourhood",
    "wof:population":187
},
  "geometry": {"coordinates":[83.236476,22.535307],"type":"Point"}
}