{
  "type": "Feature",
  "properties": {
    "iso:country":"IN",
    "ks:ks_alt_nam":"He\u0101tpur",
    "ks:ks_name":"Heatpur",
    "ks:ks_type":"VILLAGE",
    "name:eng_x_preferred":[
        "Heatpur"
    ],
    "name:eng_x_variant":[
        "He\u0101tpur"
    ],
    "wof:name":"Heatpur",
    "wof:placetype":"locality"
},
  "geometry": {"coordinates":[84.637007,26.014167],"type":"Point"}
}