{
  "type": "Feature",
  "properties": {
    "iso:country":"IN",
    "ks:ks_name":"Sakhaney Kishmipur Teleyagarh",
    "ks:ks_pop":200,
    "ks:ks_type":"HABITATION",
    "name:eng_x_preferred":[
        "Sakhaney Kishmipur Teleyagarh"
    ],
    "wof:name":"Sakhaney Kishmipur Teleyagarh",
    "wof:placetype":"locality",
    "wof:population":200
},
  "geometry": {"coordinates":[82.427536,26.393251],"type":"Point"}
}