{
  "type": "Feature",
  "properties": {
    "iso:country":"IN",
    "ks:ks_name":"Lalpur",
    "ks:ks_pop":453,
    "ks:ks_type":"VILLAGE",
    "name:eng_x_preferred":[
        "Lalpur"
    ],
    "wof:name":"Lalpur",
    "wof:placetype":"locality",
    "wof:population":453
},
  "geometry": {"coordinates":[85.49326000000001,26.217137],"type":"Point"}
}