{
  "type": "Feature",
  "properties": {
    "iso:country":"IN",
    "ks:ks_name":"Thakthaki",
    "ks:ks_pop":0,
    "ks:ks_type":"VILLAGE",
    "name:eng_x_preferred":[
        "Thakthaki"
    ],
    "wof:name":"Thakthaki",
    "wof:placetype":"locality",
    "wof:population":0
},
  "geometry": {"coordinates":[88.131663,26.094164],"type":"Point"}
}