{
  "type": "Feature",
  "properties": {
    "gn:admin1_code":"34.0",
    "gn:admin2_code":"235.0",
    "gn:asciiname":"Sinduria",
    "gn:country_code":"IN",
    "gn:dem":124,
    "gn:feature_class":"P",
    "gn:feature_code":"PPL",
    "gn:name":"Sinduri\u0101",
    "gn:population":0,
    "gn:timezone":"Asia/Kolkata",
    "iso:country":"IN",
    "name:bih_x_preferred":[
        "\u0938\u093f\u0902\u0926\u0941\u0930\u093f\u092f\u093e"
    ],
    "name:bpy_x_preferred":[
        "\u09b8\u09bf\u09a8\u09cd\u09a6\u09c1\u09b0\u09bf\u09af\u09bc\u09be"
    ],
    "name:ita_x_preferred":[
        "Sinduria"
    ],
    "name:msa_x_preferred":[
        "Sinduria"
    ],
    "name:nld_x_preferred":[
        "Sinduria"
    ],
    "name:por_x_preferred":[
        "Sinduria"
    ],
    "name:spa_x_preferred":[
        "Sinduria"
    ],
    "name:vie_x_preferred":[
        "Sinduria"
    ],
    "name:zho_x_preferred":[
        "\u8f9b\u675c\u91cc\u4e9a"
    ],
    "wof:name":"Sinduria",
    "wof:placetype":"locality"
},
  "geometry": {"coordinates":[84.24393000000001,24.71799],"type":"Point"}
}