{
  "type": "Feature",
  "properties": {
    "iso:country":"IN",
    "ks:ks_name":"Khaghwa",
    "ks:ks_pop":303,
    "ks:ks_type":"HABITATION",
    "name:eng_x_preferred":[
        "Khaghwa"
    ],
    "wof:name":"Khaghwa",
    "wof:placetype":"locality",
    "wof:population":303
},
  "geometry": {"coordinates":[82.71514999999999,27.24338],"type":"Point"}
}