{
  "type": "Feature",
  "properties": {
    "gn:admin1_code":"34.0",
    "gn:admin2_code":"211.0",
    "gn:asciiname":"Khutia",
    "gn:country_code":"IN",
    "gn:dem":42,
    "gn:feature_class":"P",
    "gn:feature_code":"PPL",
    "gn:name":"Khutia",
    "gn:population":0,
    "gn:timezone":"Asia/Kolkata",
    "iso:country":"IN",
    "name:hye_x_preferred":[
        "\u053d\u0578\u0582\u057f\u056b\u0561"
    ],
    "name:kat_x_preferred":[
        "\u10ee\u10e3\u10e2\u10d8\u10d0"
    ],
    "name:rus_x_preferred":[
        "\u0425\u0443\u0442\u0438\u044f"
    ],
    "wof:name":"Khutia",
    "wof:placetype":"locality"
},
  "geometry": {"coordinates":[87.74469000000001,25.81547],"type":"Point"}
}