{
  "type": "Feature",
  "properties": {
    "gn:admin1_code":"16",
    "gn:admin2_code":"507.0",
    "gn:asciiname":"Malda",
    "gn:country_code":"IN",
    "gn:dem":241,
    "gn:feature_class":"P",
    "gn:feature_code":"PPL",
    "gn:name":"M\u0101lda",
    "gn:population":0,
    "gn:timezone":"Asia/Kolkata",
    "iso:country":"IN",
    "name:ceb_x_preferred":[
        "Malda"
    ],
    "name:deu_x_preferred":[
        "Malda"
    ],
    "name:eus_x_preferred":[
        "Malda"
    ],
    "name:swe_x_preferred":[
        "Malda"
    ],
    "wof:name":"Malda",
    "wof:placetype":"locality"
},
  "geometry": {"coordinates":[79.92021,20.87473],"type":"Point"}
}