{
  "type": "Feature",
  "properties": {
    "gn:admin1_code":"36.0",
    "gn:admin2_code":"182.0",
    "gn:asciiname":"Kundi",
    "gn:country_code":"IN",
    "gn:dem":102,
    "gn:feature_class":"P",
    "gn:feature_code":"PPL",
    "gn:name":"Kundi",
    "gn:population":0,
    "gn:timezone":"Asia/Kolkata",
    "iso:country":"IN",
    "name:ara_x_preferred":[
        "\u0643\u0648\u0646\u062f\u064a"
    ],
    "name:ben_bn_x_preferred":[
        "\u0995\u09c1\u09a8\u09cd\u09a1\u09bf"
    ],
    "name:ben_in_x_preferred":[
        "\u0995\u09c1\u09a8\u09cd\u09a1\u09bf"
    ],
    "name:ceb_x_preferred":[
        "Kundi"
    ],
    "name:guj_x_preferred":[
        "\u0a95\u0ac1\u0a82\u0aa1\u0ac0"
    ],
    "name:hin_x_preferred":[
        "\u0915\u0941\u0902\u0921\u0940"
    ],
    "name:kan_x_preferred":[
        "\u0c95\u0cc1\u0c82\u0ca1\u0cbf"
    ],
    "name:mal_x_preferred":[
        "\u0d15\u0d41\u0d28\u0d4d\u0d24\u0d3f"
    ],
    "name:mar_x_preferred":[
        "\u0915\u0941\u0902\u0921\u0940"
    ],
    "name:pan_x_preferred":[
        "\u0a15\u0a41\u0a70\u0a21\u0a40"
    ],
    "name:swe_x_preferred":[
        "Kundi"
    ],
    "name:tam_x_preferred":[
        "\u0b95\u0bc6\u0bbe\u0b95\u0bcd\u0b95\u0bbf"
    ],
    "name:tel_x_preferred":[
        "\u0c15\u0c41\u0c02\u0c21\u0c3f"
    ],
    "name:urd_x_preferred":[
        "\u06a9\u0646\u0688\u06cc"
    ],
    "wof:name":"Kundi",
    "wof:placetype":"locality"
},
  "geometry": {"coordinates":[82.48635,27.33439000000001],"type":"Point"}
}