{
  "type": "Feature",
  "properties": {
    "gn:admin1_code":"11.0",
    "gn:admin2_code":"27.0",
    "gn:asciiname":"Bakhluyar",
    "gn:country_code":"IN",
    "gn:dem":2197,
    "gn:feature_class":"P",
    "gn:feature_code":"PPL",
    "gn:name":"Bakhl\u016by\u0101r",
    "gn:population":0,
    "gn:timezone":"Asia/Kolkata",
    "iso:country":"IN",
    "wof:name":"Bakhluyar",
    "wof:placetype":"locality"
},
  "geometry": {"coordinates":[77.19535999999999,31.54312],"type":"Point"}
}