{
  "type": "Feature",
  "properties": {
    "gn:admin1_code":"28.0",
    "gn:admin2_code":"343",
    "gn:asciiname":"Dhamua",
    "gn:country_code":"IN",
    "gn:dem":9,
    "gn:feature_class":"P",
    "gn:feature_code":"PPL",
    "gn:name":"Dh\u0101mua",
    "gn:population":0,
    "gn:timezone":"Asia/Kolkata",
    "iso:country":"IN",
    "ks:ks_name":"Dhamua",
    "ks:ks_pop":8933,
    "ks:ks_type":"URBAN",
    "name:eng_x_preferred":[
        "Dhamua"
    ],
    "wof:name":"Dhamua",
    "wof:placetype":"locality",
    "wof:population":8933
},
  "geometry": {"coordinates":[88.383048,22.298004],"type":"Point"}
}