{
  "type": "Feature",
  "properties": {
    "gn:admin1_code":"35",
    "gn:admin2_code":"425.0",
    "gn:asciiname":"Anta",
    "gn:country_code":"IN",
    "gn:dem":142,
    "gn:feature_class":"P",
    "gn:feature_code":"PPL",
    "gn:name":"Anta",
    "gn:population":0,
    "gn:timezone":"Asia/Kolkata",
    "iso:country":"IN",
    "name:ceb_x_preferred":[
        "Anta"
    ],
    "name:deu_x_preferred":[
        "Anta"
    ],
    "name:eus_x_preferred":[
        "Anta"
    ],
    "name:fra_x_preferred":[
        "Anta"
    ],
    "name:glg_x_preferred":[
        "Anta"
    ],
    "name:ita_x_preferred":[
        "Anta"
    ],
    "name:nld_x_preferred":[
        "Anta"
    ],
    "name:pol_x_preferred":[
        "Anta"
    ],
    "name:por_x_preferred":[
        "Anta"
    ],
    "name:rus_x_preferred":[
        "\u0410\u043d\u0442\u0430"
    ],
    "name:spa_x_preferred":[
        "Anta"
    ],
    "name:swe_x_preferred":[
        "Anta"
    ],
    "name:ukr_x_preferred":[
        "\u0410\u043d\u0442\u0430"
    ],
    "wof:name":"Anta",
    "wof:placetype":"locality"
},
  "geometry": {"coordinates":[80.29064,25.19551],"type":"Point"}
}