{
  "type": "Feature",
  "properties": {
    "gn:admin1_code":"36.0",
    "gn:admin2_code":"161",
    "gn:asciiname":"Akalpur",
    "gn:country_code":"IN",
    "gn:dem":149,
    "gn:feature_class":"P",
    "gn:feature_code":"PPL",
    "gn:name":"\u0100kalpur",
    "gn:population":0,
    "gn:timezone":"Asia/Kolkata",
    "iso:country":"IN",
    "name:pan_x_preferred":[
        "\u0a05\u0a15\u0a32\u0a2a\u0a41\u0a30"
    ],
    "wof:name":"Akalpur",
    "wof:placetype":"locality"
},
  "geometry": {"coordinates":[79.10003,26.82128],"type":"Point"}
}