{
  "type": "Feature",
  "properties": {
    "gn:admin1_code":"19.0",
    "gn:admin2_code":"565.0",
    "gn:asciiname":"Beladari",
    "gn:country_code":"IN",
    "gn:dem":643,
    "gn:feature_class":"P",
    "gn:feature_code":"PPL",
    "gn:name":"Beladari",
    "gn:population":0,
    "gn:timezone":"Asia/Kolkata",
    "iso:country":"IN",
    "wof:name":"Beladari",
    "wof:placetype":"locality"
},
  "geometry": {"coordinates":[76.32103000000002,14.7207],"type":"Point"}
}