{
  "type": "Feature",
  "properties": {
    "iso:country":"IN",
    "ks:ks_alt_nam":"Dakyong II",
    "ks:ks_name":"Dakyong Ii",
    "ks:ks_pop":511,
    "ks:ks_type":"HABITATION",
    "name:eng_x_preferred":[
        "Dakyong Ii"
    ],
    "wof:name":"Dakyong Ii",
    "wof:placetype":"locality",
    "wof:population":511
},
  "geometry": {"coordinates":[88.604984,27.146607],"type":"Point"}
}