{
  "type": "Feature",
  "properties": {
    "iso:country":"IN",
    "ks:ks_name":"Soman Deeh",
    "ks:ks_pop":79,
    "ks:ks_type":"HABITATION",
    "name:eng_x_preferred":[
        "Soman Deeh"
    ],
    "wof:name":"Soman Deeh",
    "wof:placetype":"locality",
    "wof:population":79
},
  "geometry": {"coordinates":[82.49356299999999,27.429015],"type":"Point"}
}