{
  "type": "Feature",
  "properties": {
    "gn:admin1_code":"12.0",
    "gn:admin2_code":"19.0",
    "gn:asciiname":"Suglu-di Lahr",
    "gn:country_code":"IN",
    "gn:dem":1742,
    "gn:feature_class":"P",
    "gn:feature_code":"PPL",
    "gn:name":"Sugl\u016b-d\u012b Lahr",
    "gn:population":0,
    "gn:timezone":"Asia/Kolkata",
    "iso:country":"IN",
    "wof:name":"Suglu-di Lahr",
    "wof:placetype":"locality"
},
  "geometry": {"coordinates":[75.11011999999999,33.02297],"type":"Point"}
}