{
  "type": "Feature",
  "properties": {
    "iso:country":"IN",
    "ks:ks_name":"Kalvit",
    "ks:ks_pop":120,
    "ks:ks_type":"HABITATION",
    "name:eng_x_preferred":[
        "Kalvit"
    ],
    "wof:name":"Kalvit",
    "wof:placetype":"locality",
    "wof:population":120
},
  "geometry": {"coordinates":[74.84089,17.899048],"type":"Point"}
}