{
  "type": "Feature",
  "properties": {
    "iso:country":"IN",
    "ks:ks_name":"Singimari Gaon 1",
    "ks:ks_pop":354,
    "ks:ks_type":"VILLAGE",
    "ks:ks_uagg_main":0,
    "name:eng_x_preferred":[
        "Singimari Gaon 1"
    ],
    "wof:name":"Singimari Gaon 1",
    "wof:placetype":"neighbourhood",
    "wof:population":354
},
  "geometry": {"coordinates":[92.368775,26.671427],"type":"Point"}
}