{
  "type": "Feature",
  "properties": {
    "gn:admin1_code":"36.0",
    "gn:admin2_code":"139.0",
    "gn:asciiname":"Jawaharnagar",
    "gn:country_code":"IN",
    "gn:dem":225,
    "gn:feature_class":"P",
    "gn:feature_code":"PPL",
    "gn:name":"Jaw\u0101harnagar",
    "gn:population":0,
    "gn:timezone":"Asia/Kolkata",
    "iso:country":"IN",
    "wof:name":"Jawaharnagar",
    "wof:placetype":"locality"
},
  "geometry": {"coordinates":[77.22215,28.98857000000001],"type":"Point"}
}