{
  "type": "Feature",
  "properties": {
    "iso:country":"IN",
    "ks:ks_name":"Nagua",
    "ks:ks_pop":232,
    "ks:ks_type":"VILLAGE",
    "name:eng_x_preferred":[
        "Nagua"
    ],
    "wof:name":"Nagua",
    "wof:placetype":"locality",
    "wof:population":232
},
  "geometry": {"coordinates":[88.20357199999999,25.523641],"type":"Point"}
}