{
  "type": "Feature",
  "properties": {
    "iso:country":"IN",
    "ks:ks_name":"Rajpurewadi",
    "ks:ks_pop":20,
    "ks:ks_type":"HABITATION",
    "name:eng_x_preferred":[
        "Rajpurewadi"
    ],
    "wof:name":"Rajpurewadi",
    "wof:placetype":"locality",
    "wof:population":20
},
  "geometry": {"coordinates":[73.35748599999999,17.816753],"type":"Point"}
}