{
  "type": "Feature",
  "properties": {
    "gn:admin1_code":"38.0",
    "gn:asciiname":"Sanaur",
    "gn:country_code":"IN",
    "gn:dem":58,
    "gn:feature_class":"P",
    "gn:feature_code":"PPL",
    "gn:name":"Sanaur",
    "gn:population":0,
    "gn:timezone":"Asia/Kolkata",
    "iso:country":"IN",
    "ks:ks_name":"Sanaur",
    "ks:ks_pop":882,
    "ks:ks_type":"VILLAGE",
    "ks:ks_uagg_main":0,
    "name:ben_x_preferred":[
        "\u09b8\u09be\u09a8\u09be\u0989\u09b0"
    ],
    "name:bpy_x_preferred":[
        "\u09b8\u09be\u09a8\u09be\u0989\u09b0"
    ],
    "name:ceb_x_preferred":[
        "Sanaur"
    ],
    "name:eng_x_preferred":[
        "Sanaur"
    ],
    "name:ita_x_preferred":[
        "Sanaur"
    ],
    "name:msa_x_preferred":[
        "Sanaur"
    ],
    "name:nld_x_preferred":[
        "Sanaur"
    ],
    "name:pan_x_preferred":[
        "\u0a38\u0a28\u0a4c\u0a30"
    ],
    "name:por_x_preferred":[
        "Sanaur"
    ],
    "name:spa_x_preferred":[
        "Sanaur"
    ],
    "name:swe_x_preferred":[
        "Sanaur"
    ],
    "name:vie_x_preferred":[
        "Sanaur"
    ],
    "name:zho_x_preferred":[
        "\u8428\u7459\u5c14"
    ],
    "wof:name":"Sanaur",
    "wof:placetype":"neighbourhood",
    "wof:population":882
},
  "geometry": {"coordinates":[87.154402,24.984139],"type":"Point"}
}