{
  "type": "Feature",
  "properties": {
    "iso:country":"IN",
    "ks:ks_name":"A Pallapacheri",
    "ks:ks_pop":240,
    "ks:ks_type":"HABITATION",
    "name:eng_x_preferred":[
        "A Pallapacheri"
    ],
    "wof:name":"A Pallapacheri",
    "wof:placetype":"neighbourhood",
    "wof:population":240
},
  "geometry": {"coordinates":[78.44765,9.442577],"type":"Point"}
}