{
  "type": "Feature",
  "properties": {
    "iso:country":"IN",
    "ks:ks_name":"Kalchavadi",
    "ks:ks_pop":345,
    "ks:ks_type":"HABITATION",
    "name:eng_x_preferred":[
        "Kalchavadi"
    ],
    "wof:name":"Kalchavadi",
    "wof:placetype":"locality",
    "wof:population":345
},
  "geometry": {"coordinates":[79.334625,11.169319],"type":"Point"}
}