{
  "type": "Feature",
  "properties": {
    "gn:admin1_code":"35",
    "gn:admin2_code":"445.0",
    "gn:asciiname":"Nandgaon",
    "gn:country_code":"IN",
    "gn:dem":300,
    "gn:feature_class":"P",
    "gn:feature_code":"PPL",
    "gn:name":"Nandgaon",
    "gn:population":0,
    "gn:timezone":"Asia/Kolkata",
    "iso:country":"IN",
    "name:ceb_x_preferred":[
        "Nandgaon"
    ],
    "name:pol_x_preferred":[
        "Nandgaon"
    ],
    "name:swe_x_preferred":[
        "Nandgaon"
    ],
    "wof:name":"Nandgaon",
    "wof:placetype":"locality"
},
  "geometry": {"coordinates":[77.32266,22.70989],"type":"Point"}
}