{
  "type": "Feature",
  "properties": {
    "gn:admin1_code":"35",
    "gn:admin2_code":"423.0",
    "gn:asciiname":"Shankarpur",
    "gn:country_code":"IN",
    "gn:dem":393,
    "gn:feature_class":"P",
    "gn:feature_code":"PPL",
    "gn:name":"Shankarpur",
    "gn:population":0,
    "gn:timezone":"Asia/Kolkata",
    "iso:country":"IN",
    "ks:ks_name":"Shankarpur",
    "ks:ks_type":"VILLAGE",
    "name:eng_x_preferred":[
        "Shankarpur"
    ],
    "wof:name":"Shankarpur",
    "wof:placetype":"locality"
},
  "geometry": {"coordinates":[77.592271,25.777258],"type":"Point"}
}