{
  "type": "Feature",
  "properties": {
    "iso:country":"IN",
    "ks:ks_name":"Khatib Chak",
    "ks:ks_pop":1076,
    "ks:ks_type":"VILLAGE",
    "ks:ks_uagg_main":0,
    "name:eng_x_preferred":[
        "Khatib Chak"
    ],
    "wof:name":"Khatib Chak",
    "wof:placetype":"neighbourhood",
    "wof:population":1076
},
  "geometry": {"coordinates":[86.530081,25.372633],"type":"Point"}
}