{
  "type": "Feature",
  "properties": {
    "iso:country":"IN",
    "ks:ks_name":"Boladara",
    "ks:ks_pop":776,
    "ks:ks_type":"HABITATION",
    "name:eng_x_preferred":[
        "Boladara"
    ],
    "wof:name":"Boladara",
    "wof:placetype":"locality",
    "wof:population":776
},
  "geometry": {"coordinates":[73.64103299999999,23.903742],"type":"Point"}
}