{
  "type": "Feature",
  "properties": {
    "iso:country":"IN",
    "ks:ks_name":"Alur",
    "ks:ks_pop":230,
    "ks:ks_type":"VILLAGE",
    "name:eng_x_preferred":[
        "Alur"
    ],
    "wof:name":"Alur",
    "wof:placetype":"locality",
    "wof:population":230
},
  "geometry": {"coordinates":[81.820322,18.387779],"type":"Point"}
}