{
  "type": "Feature",
  "properties": {
    "iso:country":"IN",
    "ks:ks_name":"Paniendula",
    "ks:ks_pop":174,
    "ks:ks_type":"VILLAGE",
    "ks:ks_uagg_main":0,
    "name:eng_x_preferred":[
        "Paniendula"
    ],
    "wof:name":"Paniendula",
    "wof:placetype":"neighbourhood",
    "wof:population":174
},
  "geometry": {"coordinates":[86.38284899999999,20.142243],"type":"Point"}
}