{
  "type": "Feature",
  "properties": {
    "iso:country":"IN",
    "ks:ks_name":"Manuswadi",
    "ks:ks_pop":198,
    "ks:ks_type":"HABITATION",
    "name:eng_x_preferred":[
        "Manuswadi"
    ],
    "wof:name":"Manuswadi",
    "wof:placetype":"locality",
    "wof:population":198
},
  "geometry": {"coordinates":[74.288663,19.409733],"type":"Point"}
}