{
  "type": "Feature",
  "properties": {
    "iso:country":"IN",
    "ks:ks_name":"Kadathur Agraharam",
    "ks:ks_pop":1158,
    "ks:ks_type":"VILLAGE",
    "ks:ks_uagg_main":0,
    "name:eng_x_preferred":[
        "Kadathur Agraharam"
    ],
    "wof:name":"Kadathur Agraharam",
    "wof:placetype":"locality",
    "wof:population":1158
},
  "geometry": {"coordinates":[78.05229,11.570901],"type":"Point"}
}