{
  "type": "Feature",
  "properties": {
    "gn:admin1_code":"19.0",
    "gn:admin2_code":"567.0",
    "gn:asciiname":"Siddapura",
    "gn:country_code":"IN",
    "gn:dem":630,
    "gn:feature_class":"P",
    "gn:feature_code":"PPL",
    "gn:name":"Sidd\u0101pura",
    "gn:population":0,
    "gn:timezone":"Asia/Kolkata",
    "iso:country":"IN",
    "ks:ks_alt_nam":"Sidd\u0101pura",
    "ks:ks_name":"Siddapura",
    "ks:ks_pop":341,
    "ks:ks_type":"VILLAGE",
    "ks:ks_uagg_main":0,
    "name:ara_x_preferred":[
        "\u0633\u064a\u062f\u0628\u0648\u0631\u0627"
    ],
    "name:ben_bn_x_preferred":[
        "\u09b8\u09bf\u09a6\u09cd\u09a6\u09be\u09aa\u09c1\u09b0\u09be"
    ],
    "name:ben_in_x_preferred":[
        "\u09b8\u09bf\u09a6\u09cd\u09a6\u09be\u09aa\u09c1\u09b0\u09be"
    ],
    "name:eng_x_preferred":[
        "Siddapura"
    ],
    "name:eng_x_variant":[
        "Sidd\u0101pura"
    ],
    "name:guj_x_preferred":[
        "\u0ab8\u0abf\u0aa6\u0acd\u0aa6\u0abe\u0aaa\u0ac1\u0ab0\u0abe"
    ],
    "name:hin_x_preferred":[
        "\u0938\u093f\u0926\u094d\u0927\u092a\u0941\u0930\u093e"
    ],
    "name:kan_x_preferred":[
        "\u0cb8\u0cbf\u0ca6\u0ccd\u0ca6\u0cbe\u0caa\u0cc1\u0cb0"
    ],
    "name:mal_x_preferred":[
        "\u0d38\u0d3f\u0d26\u0d4d\u0d27\u0d2a\u0d41\u0d30"
    ],
    "name:mar_x_preferred":[
        "\u0938\u093f\u0926\u094d\u0927\u092a\u0941\u0930\u093e"
    ],
    "name:pan_x_preferred":[
        "\u0a38\u0a3f\u0a71\u0a26\u0a3e\u0a2a\u0a41\u0a30\u0a3e"
    ],
    "name:tam_x_preferred":[
        "\u0b9a\u0bbf\u0ba4\u0bcd\u0ba4\u0baa\u0bc1\u0bb0\u0bbe"
    ],
    "name:tel_x_preferred":[
        "\u0c38\u0c3f\u0c26\u0c4d\u0c27\u0c2a\u0c41\u0c30\u0c3e"
    ],
    "name:urd_x_preferred":[
        "\u0633\u062f\u0651\u0627 \u067e\u0648\u0631\u06c1"
    ],
    "wof:name":"Siddapura",
    "wof:placetype":"neighbourhood",
    "wof:population":341
},
  "geometry": {"coordinates":[75.87027999999999,14.104403],"type":"Point"}
}