{
  "type": "Feature",
  "properties": {
    "iso:country":"IN",
    "ks:ks_name":"Hapjan Parbat Chah Bagisa Nlr 85",
    "ks:ks_pop":1145,
    "ks:ks_type":"HABITATION",
    "name:eng_x_preferred":[
        "Hapjan Parbat Chah Bagisa Nlr 85"
    ],
    "wof:name":"Hapjan Parbat Chah Bagisa Nlr 85",
    "wof:placetype":"locality",
    "wof:population":1145
},
  "geometry": {"coordinates":[95.39143799999999,27.21804],"type":"Point"}
}