{
  "type": "Feature",
  "properties": {
    "iso:country":"IN",
    "ks:ks_name":"Chak Ichchhapura",
    "ks:ks_pop":0,
    "ks:ks_type":"VILLAGE",
    "name:eng_x_preferred":[
        "Chak Ichchhapura"
    ],
    "wof:name":"Chak Ichchhapura",
    "wof:placetype":"locality",
    "wof:population":0
},
  "geometry": {"coordinates":[76.638353,25.665455],"type":"Point"}
}