{
  "type": "Feature",
  "properties": {
    "gn:admin1_code":"35.0",
    "gn:admin2_code":"430.0",
    "gn:asciiname":"Khamhariya",
    "gn:country_code":"IN",
    "gn:dem":305,
    "gn:feature_class":"P",
    "gn:feature_code":"PPL",
    "gn:name":"Khamhariya",
    "gn:population":0,
    "gn:timezone":"Asia/Kolkata",
    "iso:country":"IN",
    "wof:name":"Khamhariya",
    "wof:placetype":"neighbourhood"
},
  "geometry": {"coordinates":[81.07024,24.7984],"type":"Point"}
}