{
  "type": "Feature",
  "properties": {
    "gn:admin1_code":"10.0",
    "gn:admin2_code":"81.0",
    "gn:asciiname":"Devsar",
    "gn:country_code":"IN",
    "gn:dem":215,
    "gn:feature_class":"P",
    "gn:feature_code":"PPL",
    "gn:name":"Devsar",
    "gn:population":0,
    "gn:timezone":"Asia/Kolkata",
    "iso:country":"IN",
    "name:bpy_x_preferred":[
        "\u09a6\u09c7\u09ac\u09b8\u09be\u09b0"
    ],
    "name:guj_x_preferred":[
        "\u0aa6\u0ac7\u0ab5\u0ab8\u0ab0"
    ],
    "name:ind_x_preferred":[
        "Devsar"
    ],
    "name:ita_x_preferred":[
        "Devsar"
    ],
    "name:msa_x_preferred":[
        "Devsar"
    ],
    "name:new_x_preferred":[
        "\u0926\u0947\u0935\u0938\u0930"
    ],
    "name:nld_x_preferred":[
        "Devsar"
    ],
    "name:por_x_preferred":[
        "Devsar"
    ],
    "name:spa_x_preferred":[
        "Devsar"
    ],
    "name:tam_x_preferred":[
        "\u0ba4\u0bc7\u0bb5\u0bcd\u0b9a\u0bb0\u0bcd"
    ],
    "name:tat_x_preferred":[
        "\u0414\u0435\u0432\u0441\u0430\u0440"
    ],
    "name:urd_x_preferred":[
        "\u062f\u06cc\u0648 \u0633\u0631"
    ],
    "name:vie_x_preferred":[
        "Devsar"
    ],
    "name:zho_x_preferred":[
        "\u5fb7\u6c83\u8428\u5c14"
    ],
    "wof:name":"Devsar",
    "wof:placetype":"locality"
},
  "geometry": {"coordinates":[76.08689,28.76302],"type":"Point"}
}