{
  "type": "Feature",
  "properties": {
    "iso:country":"IN",
    "ks:ks_name":"Kalpu Purwa",
    "ks:ks_pop":19,
    "ks:ks_type":"HABITATION",
    "name:eng_x_preferred":[
        "Kalpu Purwa"
    ],
    "wof:name":"Kalpu Purwa",
    "wof:placetype":"locality",
    "wof:population":19
},
  "geometry": {"coordinates":[83.203642,27.316575],"type":"Point"}
}