{
  "type": "Feature",
  "properties": {
    "iso:country":"IN",
    "ks:ks_alt_nam":"jodimamidi",
    "ks:ks_name":"Jodimamidi",
    "ks:ks_pop":71,
    "ks:ks_type":"HABITATION",
    "name:eng_x_preferred":[
        "Jodimamidi"
    ],
    "wof:name":"Jodimamidi",
    "wof:placetype":"locality",
    "wof:population":71
},
  "geometry": {"coordinates":[82.503745,17.773141],"type":"Point"}
}