{
  "type": "Feature",
  "properties": {
    "gn:admin1_code":"9.0",
    "gn:admin2_code":"470.0",
    "gn:asciiname":"Pintharpura",
    "gn:country_code":"IN",
    "gn:dem":78,
    "gn:feature_class":"P",
    "gn:feature_code":"PPL",
    "gn:name":"Pintharpura",
    "gn:population":0,
    "gn:timezone":"Asia/Kolkata",
    "iso:country":"IN",
    "wof:name":"Pintharpura",
    "wof:placetype":"locality"
},
  "geometry": {"coordinates":[72.24292,23.70662],"type":"Point"}
}