{
  "type": "Feature",
  "properties": {
    "iso:country":"IN",
    "ks:ks_name":"Kashta",
    "ks:ks_pop":727,
    "ks:ks_type":"VILLAGE",
    "name:eng_x_preferred":[
        "Kashta"
    ],
    "wof:name":"Kashta",
    "wof:placetype":"locality",
    "wof:population":727
},
  "geometry": {"coordinates":[74.613947,22.044163],"type":"Point"}
}