{
  "type": "Feature",
  "properties": {
    "iso:country":"IN",
    "ks:ks_name":"Mahuwal",
    "ks:ks_pop":910,
    "ks:ks_type":"HABITATION",
    "name:eng_x_preferred":[
        "Mahuwal"
    ],
    "wof:name":"Mahuwal",
    "wof:placetype":"locality",
    "wof:population":910
},
  "geometry": {"coordinates":[74.408733,23.844019],"type":"Point"}
}