{
  "type": "Feature",
  "properties": {
    "iso:country":"IN",
    "ks:ks_alt_nam":"Thurajan TE",
    "ks:ks_name":"Thurajan Te",
    "ks:ks_pop":380,
    "ks:ks_type":"HABITATION",
    "ks:ks_uagg_main":0,
    "name:eng_x_preferred":[
        "Thurajan Te"
    ],
    "wof:name":"Thurajan Te",
    "wof:placetype":"neighbourhood",
    "wof:population":380
},
  "geometry": {"coordinates":[93.91301199999999,26.467454],"type":"Point"}
}