{
  "type": "Feature",
  "properties": {
    "iso:country":"IN",
    "ks:ks_name":"Gunduba",
    "ks:ks_pop":2274,
    "ks:ks_type":"HABITATION",
    "name:eng_x_preferred":[
        "Gunduba"
    ],
    "wof:name":"Gunduba",
    "wof:placetype":"locality",
    "wof:population":2274
},
  "geometry": {"coordinates":[86.699642,23.876222],"type":"Point"}
}