{
  "type": "Feature",
  "properties": {
    "iso:country":"IN",
    "ks:ks_alt_nam":"BRETHI",
    "ks:ks_name":"Brethi",
    "ks:ks_pop":546,
    "ks:ks_type":"HABITATION",
    "ks:ks_uagg_main":0,
    "name:eng_x_preferred":[
        "Brethi"
    ],
    "wof:name":"Brethi",
    "wof:placetype":"neighbourhood",
    "wof:population":546
},
  "geometry": {"coordinates":[81.703672,26.33445],"type":"Point"}
}