{
  "type": "Feature",
  "properties": {
    "iso:country":"IN",
    "ks:ks_alt_nam":"Karoor JN",
    "ks:ks_name":"Karoor Jn",
    "ks:ks_pop":1549,
    "ks:ks_type":"HABITATION",
    "name:eng_x_preferred":[
        "Karoor Jn"
    ],
    "wof:name":"Karoor Jn",
    "wof:placetype":"locality",
    "wof:population":1549
},
  "geometry": {"coordinates":[76.88518500000001,8.626526],"type":"Point"}
}