{
  "type": "Feature",
  "properties": {
    "gn:admin1_code":"36",
    "gn:admin2_code":"200.0",
    "gn:asciiname":"Kusi Nisf",
    "gn:country_code":"IN",
    "gn:dem":311,
    "gn:feature_class":"P",
    "gn:feature_code":"PPL",
    "gn:name":"Kusi Nisf",
    "gn:population":0,
    "gn:timezone":"Asia/Kolkata",
    "iso:country":"IN",
    "wof:name":"Kusi Nisf",
    "wof:placetype":"locality"
},
  "geometry": {"coordinates":[82.90458000000002,24.69914],"type":"Point"}
}