{
  "type": "Feature",
  "properties": {
    "gn:admin1_code":"16",
    "gn:admin2_code":"505.0",
    "gn:asciiname":"Paoni",
    "gn:country_code":"IN",
    "gn:dem":235,
    "gn:feature_class":"P",
    "gn:feature_code":"PPL",
    "gn:name":"Paon\u012b",
    "gn:population":0,
    "gn:timezone":"Asia/Kolkata",
    "iso:country":"IN",
    "name:und_x_variant":[
        "Paon\u012b",
        "Bhoyar"
    ],
    "wof:name":"Paoni",
    "wof:placetype":"locality"
},
  "geometry": {"coordinates":[79.0035,20.75056],"type":"Point"}
}