{
  "type": "Feature",
  "properties": {
    "iso:country":"IN",
    "ks:ks_name":"Santhkodige",
    "ks:ks_pop":141,
    "ks:ks_type":"HABITATION",
    "name:eng_x_preferred":[
        "Santhkodige"
    ],
    "wof:name":"Santhkodige",
    "wof:placetype":"locality",
    "wof:population":141
},
  "geometry": {"coordinates":[75.326977,13.323985],"type":"Point"}
}