{
  "type": "Feature",
  "properties": {
    "iso:country":"IN",
    "ks:ks_name":"Champadihi",
    "ks:ks_pop":95,
    "ks:ks_type":"VILLAGE",
    "name:eng_x_preferred":[
        "Champadihi"
    ],
    "wof:name":"Champadihi",
    "wof:placetype":"locality",
    "wof:population":95
},
  "geometry": {"coordinates":[85.497271,21.881081],"type":"Point"}
}