{
  "type": "Feature",
  "properties": {
    "gn:admin1_code":"35",
    "gn:admin2_code":"428.0",
    "gn:asciiname":"Konrta",
    "gn:country_code":"IN",
    "gn:dem":361,
    "gn:feature_class":"P",
    "gn:feature_code":"PPL",
    "gn:name":"Konrta",
    "gn:population":0,
    "gn:timezone":"Asia/Kolkata",
    "iso:country":"IN",
    "wof:name":"Konrta",
    "wof:placetype":"locality"
},
  "geometry": {"coordinates":[79.65111999999998,23.54001],"type":"Point"}
}