{
  "type": "Feature",
  "properties": {
    "iso:country":"IN",
    "ks:ks_name":"Amarpura",
    "ks:ks_pop":381,
    "ks:ks_type":"VILLAGE",
    "name:eng_x_preferred":[
        "Amarpura"
    ],
    "wof:name":"Amarpura",
    "wof:placetype":"locality",
    "wof:population":381
},
  "geometry": {"coordinates":[74.606398,23.416311],"type":"Point"}
}