{
  "type": "Feature",
  "properties": {
    "iso:country":"IN",
    "ks:ks_name":"Usmapur Small",
    "ks:ks_pop":740,
    "ks:ks_type":"HABITATION",
    "name:eng_x_preferred":[
        "Usmapur Small"
    ],
    "wof:name":"Usmapur Small",
    "wof:placetype":"locality",
    "wof:population":740
},
  "geometry": {"coordinates":[83.176396,25.854775],"type":"Point"}
}