{
  "type": "Feature",
  "properties": {
    "gn:admin1_code":"36",
    "gn:admin2_code":"195.0",
    "gn:asciiname":"Indarpur Chhiri",
    "gn:country_code":"IN",
    "gn:dem":76,
    "gn:feature_class":"P",
    "gn:feature_code":"PPL",
    "gn:name":"Indarpur Chh\u012bri",
    "gn:population":0,
    "gn:timezone":"Asia/Kolkata",
    "iso:country":"IN",
    "ks:ks_name":"Indarpur Chiri",
    "ks:ks_pop":1604,
    "ks:ks_type":"HABITATION",
    "name:eng_x_preferred":[
        "Indarpur Chiri"
    ],
    "name:eng_x_variant":[
        "Indarpur Chhiri"
    ],
    "wof:name":"Indarpur Chiri",
    "wof:placetype":"locality",
    "wof:population":1604
},
  "geometry": {"coordinates":[83.460061,25.642097],"type":"Point"}
}