{
  "type": "Feature",
  "properties": {
    "gn:admin1_code":"36",
    "gn:admin2_code":"145.0",
    "gn:asciiname":"Bati",
    "gn:country_code":"IN",
    "gn:dem":184,
    "gn:feature_class":"P",
    "gn:feature_code":"PPL",
    "gn:name":"B\u0101ti",
    "gn:population":0,
    "gn:timezone":"Asia/Kolkata",
    "iso:country":"IN",
    "name:ceb_x_preferred":[
        "Bati"
    ],
    "name:deu_x_preferred":[
        "Bati"
    ],
    "name:fra_x_preferred":[
        "Bati"
    ],
    "name:srp_x_preferred":[
        "\u0411\u0430\u0442\u0438"
    ],
    "name:swe_x_preferred":[
        "Bati"
    ],
    "wof:name":"Bati",
    "wof:placetype":"locality"
},
  "geometry": {"coordinates":[77.60295000000001,27.53862],"type":"Point"}
}