{
  "type": "Feature",
  "properties": {
    "gn:admin1_code":"36",
    "gn:admin2_code":"145.0",
    "gn:asciiname":"Bati",
    "gn:country_code":"IN",
    "gn:dem":184,
    "gn:feature_class":"P",
    "gn:feature_code":"PPL",
    "gn:name":"B\u0101ti",
    "gn:population":0,
    "gn:timezone":"Asia/Kolkata",
    "iso:country":"IN",
    "name:ben_x_preferred":[
        "\u09ac\u09be\u09a4\u09bf"
    ],
    "name:ceb_x_preferred":[
        "Bati"
    ],
    "name:deu_x_preferred":[
        "Bati"
    ],
    "name:ell_x_preferred":[
        "\u039c\u03c0\u03ac\u03c4\u03b9"
    ],
    "name:fas_x_preferred":[
        "\u0628\u0627\u062a\u06cc"
    ],
    "name:fra_x_preferred":[
        "Bati"
    ],
    "name:heb_x_preferred":[
        "\u05d1\u05d0\u05d8\u05d9"
    ],
    "name:hin_x_preferred":[
        "\u092c\u093e\u0924\u0940"
    ],
    "name:hun_x_preferred":[
        "Bati"
    ],
    "name:ind_x_preferred":[
        "Bati"
    ],
    "name:kor_x_preferred":[
        "\ubc14\ud2f0"
    ],
    "name:rus_x_preferred":[
        "\u0411\u0430\u0442\u0438"
    ],
    "name:srp_x_preferred":[
        "\u0411\u0430\u0442\u0438"
    ],
    "name:swe_x_preferred":[
        "Bati"
    ],
    "name:tur_x_preferred":[
        "Bati"
    ],
    "name:ukr_x_preferred":[
        "\u0411\u0430\u0442\u0456"
    ],
    "name:urd_x_preferred":[
        "\u0628\u0627\u062a\u06cc"
    ],
    "name:vie_x_preferred":[
        "Bati"
    ],
    "wof:name":"Bati",
    "wof:placetype":"locality"
},
  "geometry": {"coordinates":[77.60295000000001,27.53862],"type":"Point"}
}