{
  "type": "Feature",
  "properties": {
    "gn:admin1_code":"11",
    "gn:admin2_code":"31.0",
    "gn:asciiname":"Sunki",
    "gn:country_code":"IN",
    "gn:dem":1394,
    "gn:feature_class":"P",
    "gn:feature_code":"PPL",
    "gn:name":"Sunki",
    "gn:population":0,
    "gn:timezone":"Asia/Kolkata",
    "iso:country":"IN",
    "name:ori_x_preferred":[
        "\u0b38\u0b41\u0b19\u0b4d\u0b15\u0b3f"
    ],
    "wof:name":"Sunki",
    "wof:placetype":"locality"
},
  "geometry": {"coordinates":[77.05424000000002,31.07208],"type":"Point"}
}