{
  "type": "Feature",
  "properties": {
    "iso:country":"IN",
    "ks:ks_name":"Mandalpara",
    "ks:ks_pop":512,
    "ks:ks_type":"HABITATION",
    "ks:ks_uagg_main":0,
    "name:eng_x_preferred":[
        "Mandalpara"
    ],
    "wof:name":"Mandalpara",
    "wof:placetype":"neighbourhood",
    "wof:population":512
},
  "geometry": {"coordinates":[87.964783,22.735081],"type":"Point"}
}