{
  "type": "Feature",
  "properties": {
    "gn:admin1_code":"38.0",
    "gn:admin2_code":"347.0",
    "gn:asciiname":"Khirgara",
    "gn:country_code":"IN",
    "gn:dem":427,
    "gn:feature_class":"P",
    "gn:feature_code":"PPL",
    "gn:name":"Khirgar\u0101",
    "gn:population":0,
    "gn:timezone":"Asia/Kolkata",
    "iso:country":"IN",
    "ks:ks_alt_nam":"Khirgar\u0101",
    "ks:ks_name":"Khirgara",
    "ks:ks_pop":542,
    "ks:ks_type":"VILLAGE",
    "name:eng_x_preferred":[
        "Khirgara"
    ],
    "name:eng_x_variant":[
        "Khirgar\u0101"
    ],
    "wof:name":"Khirgara",
    "wof:placetype":"locality",
    "wof:population":542
},
  "geometry": {"coordinates":[85.011683,24.245569],"type":"Point"}
}