{
  "type": "Feature",
  "properties": {
    "gn:admin1_code":"21",
    "gn:admin2_code":"399.0",
    "gn:asciiname":"Koduguguda",
    "gn:country_code":"IN",
    "gn:dem":250,
    "gn:feature_class":"P",
    "gn:feature_code":"PPL",
    "gn:name":"Kodugug\u016bda",
    "gn:population":0,
    "gn:timezone":"Asia/Kolkata",
    "iso:country":"IN",
    "ks:ks_name":"Kudukguda",
    "ks:ks_pop":147,
    "ks:ks_type":"HABITATION",
    "name:eng_x_preferred":[
        "Kudukguda"
    ],
    "name:eng_x_variant":[
        "Koduguguda"
    ],
    "wof:name":"Kudukguda",
    "wof:placetype":"locality",
    "wof:population":147
},
  "geometry": {"coordinates":[82.15124299999999,18.625708],"type":"Point"}
}