{
  "type": "Feature",
  "properties": {
    "iso:country":"IN",
    "ks:ks_name":"Sikraura",
    "ks:ks_pop":599,
    "ks:ks_type":"VILLAGE",
    "name:eng_x_preferred":[
        "Sikraura"
    ],
    "wof:name":"Sikraura",
    "wof:placetype":"locality",
    "wof:population":599
},
  "geometry": {"coordinates":[83.379531,26.09773],"type":"Point"}
}