{
  "type": "Feature",
  "properties": {
    "iso:country":"IN",
    "ks:ks_alt_nam":"Ambedkar colany",
    "ks:ks_name":"Ambedkar Colany",
    "ks:ks_pop":3210,
    "ks:ks_type":"HABITATION",
    "name:eng_x_preferred":[
        "Ambedkar Colany"
    ],
    "wof:name":"Ambedkar Colany",
    "wof:placetype":"locality",
    "wof:population":3210
},
  "geometry": {"coordinates":[76.122992,10.911924],"type":"Point"}
}