{
  "type": "Feature",
  "properties": {
    "gn:admin1_code":"19.0",
    "gn:admin2_code":"583.0",
    "gn:asciiname":"Shidnayakannhalli",
    "gn:country_code":"IN",
    "gn:dem":902,
    "gn:feature_class":"P",
    "gn:feature_code":"PPL",
    "gn:name":"Shidn\u0101yakannhalli",
    "gn:population":0,
    "gn:timezone":"Asia/Kolkata",
    "iso:country":"IN",
    "wof:name":"Shidnayakannhalli",
    "wof:placetype":"locality"
},
  "geometry": {"coordinates":[77.55046999999998,13.29849],"type":"Point"}
}