{
  "type": "Feature",
  "properties": {
    "gn:admin1_code":"36.0",
    "gn:admin2_code":"158.0",
    "gn:asciiname":"Binnawan",
    "gn:country_code":"IN",
    "gn:dem":120,
    "gn:feature_class":"P",
    "gn:feature_code":"PPL",
    "gn:name":"Binn\u0101w\u0101n",
    "gn:population":0,
    "gn:timezone":"Asia/Kolkata",
    "iso:country":"IN",
    "wof:name":"Binnawan",
    "wof:placetype":"locality"
},
  "geometry": {"coordinates":[81.17449999999999,26.06304],"type":"Point"}
}