{
  "type": "Feature",
  "properties": {
    "gn:admin1_code":"19.0",
    "gn:admin2_code":"560.0",
    "gn:asciiname":"Naganahalli",
    "gn:country_code":"IN",
    "gn:dem":400,
    "gn:feature_class":"P",
    "gn:feature_code":"PPL",
    "gn:name":"N\u0101ganahalli",
    "gn:population":0,
    "gn:timezone":"Asia/Kolkata",
    "iso:country":"IN",
    "wof:name":"Naganahalli",
    "wof:placetype":"locality"
},
  "geometry": {"coordinates":[76.57640000000001,15.41399],"type":"Point"}
}