{
  "type": "Feature",
  "properties": {
    "iso:country":"IN",
    "ks:ks_name":"Jatiapara",
    "ks:ks_pop":151,
    "ks:ks_type":"HABITATION",
    "name:eng_x_preferred":[
        "Jatiapara"
    ],
    "wof:name":"Jatiapara",
    "wof:placetype":"locality",
    "wof:population":151
},
  "geometry": {"coordinates":[84.24332099999999,22.361087],"type":"Point"}
}