{
  "type": "Feature",
  "properties": {
    "gn:admin1_code":"37",
    "gn:asciiname":"Parkor",
    "gn:country_code":"IN",
    "gn:dem":320,
    "gn:feature_class":"P",
    "gn:feature_code":"PPL",
    "gn:name":"Parkor",
    "gn:population":0,
    "gn:timezone":"Asia/Kolkata",
    "iso:country":"IN",
    "name:und_x_variant":[
        "Parkorh"
    ],
    "wof:name":"Parkor",
    "wof:placetype":"locality"
},
  "geometry": {"coordinates":[82.56809,20.93122],"type":"Point"}
}