{
  "type": "Feature",
  "properties": {
    "iso:country":"IN",
    "ks:ks_name":"Badhana",
    "ks:ks_pop":272,
    "ks:ks_type":"HABITATION",
    "name:eng_x_preferred":[
        "Badhana"
    ],
    "wof:name":"Badhana",
    "wof:placetype":"locality",
    "wof:population":272
},
  "geometry": {"coordinates":[77.88504500000001,30.547072],"type":"Point"}
}