{
  "type": "Feature",
  "properties": {
    "iso:country":"IN",
    "ks:ks_name":"Kumathalavandlapalle",
    "ks:ks_pop":58,
    "ks:ks_type":"HABITATION",
    "name:eng_x_preferred":[
        "Kumathalavandlapalle"
    ],
    "wof:name":"Kumathalavandlapalle",
    "wof:placetype":"locality",
    "wof:population":58
},
  "geometry": {"coordinates":[78.847103,13.844814],"type":"Point"}
}