{
  "type": "Feature",
  "properties": {
    "iso:country":"IN",
    "ks:ks_alt_nam":"F3 BERWAN",
    "ks:ks_name":"F3 Berwan",
    "ks:ks_pop":334,
    "ks:ks_type":"HABITATION",
    "name:eng_x_preferred":[
        "F3 Berwan"
    ],
    "wof:name":"F3 Berwan",
    "wof:placetype":"locality",
    "wof:population":334
},
  "geometry": {"coordinates":[79.166034,22.235582],"type":"Point"}
}