{
  "type": "Feature",
  "properties": {
    "iso:country":"IN",
    "ks:ks_name":"Juna Khawasa",
    "ks:ks_pop":362,
    "ks:ks_type":"VILLAGE",
    "name:eng_x_preferred":[
        "Juna Khawasa"
    ],
    "wof:name":"Juna Khawasa",
    "wof:placetype":"locality",
    "wof:population":362
},
  "geometry": {"coordinates":[74.69690199999999,23.1229],"type":"Point"}
}