{
  "type": "Feature",
  "properties": {
    "gn:admin1_code":"34.0",
    "gn:admin2_code":"221.0",
    "gn:asciiname":"Karimnagar",
    "gn:country_code":"IN",
    "gn:dem":51,
    "gn:feature_class":"P",
    "gn:feature_code":"PPL",
    "gn:name":"Kar\u012bmnagar",
    "gn:population":0,
    "gn:timezone":"Asia/Kolkata",
    "iso:country":"IN",
    "name:eng_x_preferred":[
        "Kar\u012bmnagar"
    ],
    "wof:name":"Karimnagar",
    "wof:placetype":"locality"
},
  "geometry": {"coordinates":[85.66474000000002,25.56984],"type":"Point"}
}