{
  "type": "Feature",
  "properties": {
    "gn:admin1_code":"36",
    "gn:admin2_code":"177.0",
    "gn:asciiname":"Narayanpur",
    "gn:country_code":"IN",
    "gn:dem":105,
    "gn:feature_class":"P",
    "gn:feature_code":"PPL",
    "gn:name":"Nar\u0101yanpur",
    "gn:population":0,
    "gn:timezone":"Asia/Kolkata",
    "iso:country":"IN",
    "wof:name":"Narayanpur",
    "wof:placetype":"locality"
},
  "geometry": {"coordinates":[82.17043000000002,26.66835],"type":"Point"}
}