{
  "type": "Feature",
  "properties": {
    "iso:country":"IN",
    "ks:ks_alt_nam":"Khutabari Pt II",
    "ks:ks_name":"Khutabari Pt Ii",
    "ks:ks_pop":962,
    "ks:ks_type":"HABITATION",
    "name:eng_x_preferred":[
        "Khutabari Pt Ii"
    ],
    "wof:name":"Khutabari Pt Ii",
    "wof:placetype":"locality",
    "wof:population":962
},
  "geometry": {"coordinates":[91.067412,26.011151],"type":"Point"}
}