{
  "type": "Feature",
  "properties": {
    "iso:country":"IN",
    "ks:ks_name":"Koraitola",
    "ks:ks_pop":697,
    "ks:ks_type":"VILLAGE",
    "name:eng_x_preferred":[
        "Koraitola"
    ],
    "wof:name":"Koraitola",
    "wof:placetype":"locality",
    "wof:population":697
},
  "geometry": {"coordinates":[90.183054,26.344453],"type":"Point"}
}