{
  "type": "Feature",
  "properties": {
    "iso:country":"IN",
    "ks:ks_name":"Himani Chack Bahantara",
    "ks:ks_pop":13,
    "ks:ks_type":"VILLAGE",
    "name:eng_x_preferred":[
        "Himani Chack Bahantara"
    ],
    "wof:name":"Himani Chack Bahantara",
    "wof:placetype":"locality",
    "wof:population":13
},
  "geometry": {"coordinates":[79.727256,30.146272],"type":"Point"}
}