{
  "type": "Feature",
  "properties": {
    "gn:admin1_code":"12.0",
    "gn:admin2_code":"021",
    "gn:asciiname":"Kanchhalian",
    "gn:country_code":"IN",
    "gn:dem":290,
    "gn:feature_class":"P",
    "gn:feature_code":"PPL",
    "gn:name":"Kanchh\u0101li\u0101n",
    "gn:population":0,
    "gn:timezone":"Asia/Kolkata",
    "iso:country":"IN",
    "name:und_x_variant":[
        "Kanchh\u0101li\u0101n",
        "Kanchh\u0101h\u0101n"
    ],
    "wof:name":"Kanchhalian",
    "wof:placetype":"locality"
},
  "geometry": {"coordinates":[74.61841,32.85443],"type":"Point"}
}