{
  "type": "Feature",
  "properties": {
    "iso:country":"IN",
    "ks:ks_name":"Bagpara",
    "ks:ks_pop":628,
    "ks:ks_type":"HABITATION",
    "name:eng_x_preferred":[
        "Bagpara"
    ],
    "wof:name":"Bagpara",
    "wof:placetype":"locality",
    "wof:population":628
},
  "geometry": {"coordinates":[88.008949,22.61409],"type":"Point"}
}