{
  "type": "Feature",
  "properties": {
    "gn:admin1_code":"36",
    "gn:admin2_code":"154.0",
    "gn:asciiname":"Bichpuri",
    "gn:country_code":"IN",
    "gn:dem":127,
    "gn:feature_class":"P",
    "gn:feature_code":"PPL",
    "gn:name":"Bichpuri",
    "gn:population":0,
    "gn:timezone":"Asia/Kolkata",
    "iso:country":"IN",
    "name:hin_x_preferred":[
        "\u092c\u093f\u091a\u092a\u0941\u0930\u0940"
    ],
    "name:msa_x_preferred":[
        "Bichpuri"
    ],
    "wof:name":"Bichpuri",
    "wof:placetype":"locality"
},
  "geometry": {"coordinates":[81.02073,27.52465],"type":"Point"}
}