{
  "type": "Feature",
  "properties": {
    "iso:country":"IN",
    "ks:ks_alt_nam":"Kant\u0101pur",
    "ks:ks_name":"Kantapur",
    "ks:ks_type":"VILLAGE",
    "name:eng_x_preferred":[
        "Kantapur"
    ],
    "name:eng_x_variant":[
        "Kant\u0101pur"
    ],
    "wof:name":"Kantapur",
    "wof:placetype":"locality"
},
  "geometry": {"coordinates":[82.77206,25.140356],"type":"Point"}
}