{
  "type": "Feature",
  "properties": {
    "gn:admin1_code":"38.0",
    "gn:admin2_code":"347.0",
    "gn:asciiname":"Phulwariya",
    "gn:country_code":"IN",
    "gn:dem":193,
    "gn:feature_class":"P",
    "gn:feature_code":"PPL",
    "gn:name":"Phulw\u0101riya",
    "gn:population":0,
    "gn:timezone":"Asia/Kolkata",
    "iso:country":"IN",
    "ks:ks_name":"Phulwaria",
    "ks:ks_pop":78,
    "ks:ks_type":"VILLAGE",
    "name:eng_x_preferred":[
        "Phulwaria"
    ],
    "name:eng_x_variant":[
        "Phulwariya"
    ],
    "wof:name":"Phulwaria",
    "wof:placetype":"locality",
    "wof:population":78
},
  "geometry": {"coordinates":[84.744578,24.467699],"type":"Point"}
}