{
  "type": "Feature",
  "properties": {
    "iso:country":"IN",
    "ks:ks_name":"Chameli",
    "ks:ks_pop":240,
    "ks:ks_type":"VILLAGE",
    "name:eng_x_preferred":[
        "Chameli"
    ],
    "wof:name":"Chameli",
    "wof:placetype":"locality",
    "wof:population":240
},
  "geometry": {"coordinates":[79.045547,30.393774],"type":"Point"}
}