{
  "type": "Feature",
  "properties": {
    "iso:country":"IN",
    "ks:ks_alt_nam":"Irular colony",
    "ks:ks_name":"Irular Colony",
    "ks:ks_pop":35,
    "ks:ks_type":"HABITATION",
    "name:eng_x_preferred":[
        "Irular Colony"
    ],
    "wof:name":"Irular Colony",
    "wof:placetype":"locality",
    "wof:population":35
},
  "geometry": {"coordinates":[79.986065,13.204614],"type":"Point"}
}