{
  "type": "Feature",
  "properties": {
    "gn:admin1_code":"12.0",
    "gn:admin2_code":"6.0",
    "gn:asciiname":"Madun",
    "gn:country_code":"IN",
    "gn:dem":1854,
    "gn:feature_class":"P",
    "gn:feature_code":"PPL",
    "gn:name":"Madun",
    "gn:population":0,
    "gn:timezone":"Asia/Kolkata",
    "iso:country":"IN",
    "name:ara_x_preferred":[
        "\u0645\u0627\u062f\u0648\u0646"
    ],
    "name:fas_x_preferred":[
        "\u0645\u0627\u062f\u0648\u0646"
    ],
    "name:urd_x_preferred":[
        "\u0645\u06cc\u0688\u0648\u0646"
    ],
    "wof:name":"Madun",
    "wof:placetype":"locality"
},
  "geometry": {"coordinates":[74.42492,33.46546],"type":"Point"}
}