{
  "type": "Feature",
  "properties": {
    "gn:admin1_code":"36.0",
    "gn:admin2_code":"154.0",
    "gn:asciiname":"Mansurnagar",
    "gn:country_code":"IN",
    "gn:dem":137,
    "gn:feature_class":"P",
    "gn:feature_code":"PPL",
    "gn:name":"Mans\u016brnagar",
    "gn:population":0,
    "gn:timezone":"Asia/Kolkata",
    "iso:country":"IN",
    "wof:name":"Mansurnagar",
    "wof:placetype":"locality"
},
  "geometry": {"coordinates":[80.66866,27.31357],"type":"Point"}
}