{
  "type": "Feature",
  "properties": {
    "gn:admin1_code":"35.0",
    "gn:admin2_code":"431.0",
    "gn:asciiname":"Jhala",
    "gn:country_code":"IN",
    "gn:dem":395,
    "gn:feature_class":"P",
    "gn:feature_code":"PPL",
    "gn:name":"Jh\u0101la",
    "gn:population":0,
    "gn:timezone":"Asia/Kolkata",
    "iso:country":"IN",
    "name:nld_x_preferred":[
        "Jhala"
    ],
    "name:spa_x_preferred":[
        "Jhala"
    ],
    "wof:name":"Jhala",
    "wof:placetype":"locality"
},
  "geometry": {"coordinates":[80.75055,23.71346],"type":"Point"}
}