{
  "type": "Feature",
  "properties": {
    "gn:admin1_code":"9.0",
    "gn:admin2_code":"472.0",
    "gn:asciiname":"Narsela Muwara",
    "gn:country_code":"IN",
    "gn:dem":159,
    "gn:feature_class":"P",
    "gn:feature_code":"PPL",
    "gn:name":"Narsela Muwara",
    "gn:population":0,
    "gn:timezone":"Asia/Kolkata",
    "iso:country":"IN",
    "wof:name":"Narsela Muwara",
    "wof:placetype":"neighbourhood"
},
  "geometry": {"coordinates":[73.33663,23.13982],"type":"Point"}
}