{
  "type": "Feature",
  "properties": {
    "iso:country":"IN",
    "ks:ks_name":"Kanapatthi Kurisu",
    "ks:ks_pop":437,
    "ks:ks_type":"HABITATION",
    "ks:ks_uagg_main":0,
    "name:eng_x_preferred":[
        "Kanapatthi Kurisu"
    ],
    "wof:name":"Kanapatthi Kurisu",
    "wof:placetype":"neighbourhood",
    "wof:population":437
},
  "geometry": {"coordinates":[76.839268,9.274964],"type":"Point"}
}