{
  "type": "Feature",
  "properties": {
    "iso:country":"IN",
    "ks:ks_name":"Mata Ka Dera",
    "ks:ks_pop":467,
    "ks:ks_type":"HABITATION",
    "name:eng_x_preferred":[
        "Mata Ka Dera"
    ],
    "wof:name":"Mata Ka Dera",
    "wof:placetype":"locality",
    "wof:population":467
},
  "geometry": {"coordinates":[81.355619,25.466743],"type":"Point"}
}