{
  "type": "Feature",
  "properties": {
    "iso:country":"IN",
    "ks:ks_alt_nam":"paramada",
    "ks:ks_name":"Paramada",
    "ks:ks_pop":840,
    "ks:ks_type":"HABITATION",
    "name:eng_x_preferred":[
        "Paramada"
    ],
    "wof:name":"Paramada",
    "wof:placetype":"locality",
    "wof:population":840
},
  "geometry": {"coordinates":[76.881502,9.83076],"type":"Point"}
}