{
  "type": "Feature",
  "properties": {
    "iso:country":"IN",
    "ks:ks_name":"Dasampura",
    "ks:ks_pop":205,
    "ks:ks_type":"HABITATION",
    "name:eng_x_preferred":[
        "Dasampura"
    ],
    "wof:name":"Dasampura",
    "wof:placetype":"locality",
    "wof:population":205
},
  "geometry": {"coordinates":[72.86238899999999,22.873111],"type":"Point"}
}