{
  "type": "Feature",
  "properties": {
    "iso:country":"IN",
    "ks:ks_alt_nam":"B\u0101dli",
    "ks:ks_name":"Badli",
    "ks:ks_type":"VILLAGE",
    "ks:ks_uagg_main":0,
    "name:eng_x_preferred":[
        "Badli"
    ],
    "name:eng_x_variant":[
        "B\u0101dli"
    ],
    "wof:name":"Badli",
    "wof:placetype":"neighbourhood"
},
  "geometry": {"coordinates":[77.138662,28.747712],"type":"Point"}
}