{
  "type": "Feature",
  "properties": {
    "gn:admin1_code":"35.0",
    "gn:admin2_code":"437.0",
    "gn:asciiname":"Bari",
    "gn:country_code":"IN",
    "gn:dem":525,
    "gn:feature_class":"P",
    "gn:feature_code":"PPL",
    "gn:name":"Bari",
    "gn:population":0,
    "gn:timezone":"Asia/Kolkata",
    "iso:country":"IN",
    "wof:name":"Bari",
    "wof:placetype":"locality"
},
  "geometry": {"coordinates":[76.42551,22.71582],"type":"Point"}
}