{
  "type": "Feature",
  "properties": {
    "gn:admin1_code":"25.0",
    "gn:admin2_code":"633.0",
    "gn:asciiname":"Chenjeriyampalaiyam",
    "gn:country_code":"IN",
    "gn:dem":303,
    "gn:feature_class":"P",
    "gn:feature_code":"PPL",
    "gn:name":"Chenjeriy\u0101mp\u0101laiyam",
    "gn:population":0,
    "gn:timezone":"Asia/Kolkata",
    "iso:country":"IN",
    "wof:name":"Chenjeriyampalaiyam",
    "wof:placetype":"locality"
},
  "geometry": {"coordinates":[77.43052,11.21507],"type":"Point"}
}