{
  "type": "Feature",
  "properties": {
    "iso:country":"IN",
    "ks:ks_name":"Guravwadi",
    "ks:ks_pop":145,
    "ks:ks_type":"HABITATION",
    "name:eng_x_preferred":[
        "Guravwadi"
    ],
    "wof:name":"Guravwadi",
    "wof:placetype":"locality",
    "wof:population":145
},
  "geometry": {"coordinates":[73.498975,17.157211],"type":"Point"}
}