{
  "type": "Feature",
  "properties": {
    "gn:admin1_code":"2.0",
    "gn:admin2_code":"553.0",
    "gn:asciiname":"Venkatampalle",
    "gn:country_code":"IN",
    "gn:dem":476,
    "gn:feature_class":"P",
    "gn:feature_code":"PPL",
    "gn:name":"Venkatampalle",
    "gn:population":0,
    "gn:timezone":"Asia/Kolkata",
    "iso:country":"IN",
    "name:fas_x_preferred":[
        "\u0648\u0646\u06a9\u062a\u0645\u067e\u0644"
    ],
    "name:tel_x_preferred":[
        "\u0c35\u0c46\u0c02\u0c15\u0c1f\u0c02\u0c2a\u0c32\u0c4d\u0c32\u0c46"
    ],
    "wof:name":"Venkatampalle",
    "wof:placetype":"locality"
},
  "geometry": {"coordinates":[77.27833000000003,14.57472],"type":"Point"}
}