{
  "type": "Feature",
  "properties": {
    "gn:admin1_code":"37",
    "gn:admin2_code":"408.0",
    "gn:asciiname":"Warchakutum",
    "gn:country_code":"IN",
    "gn:dem":369,
    "gn:feature_class":"P",
    "gn:feature_code":"PPL",
    "gn:name":"Warch\u0101kutum",
    "gn:population":0,
    "gn:timezone":"Asia/Kolkata",
    "iso:country":"IN",
    "ks:ks_name":"Varchakutumb",
    "ks:ks_pop":93,
    "ks:ks_type":"VILLAGE",
    "name:eng_x_preferred":[
        "Varchakutumb"
    ],
    "name:eng_x_variant":[
        "Warchakutum"
    ],
    "wof:name":"Varchakutumb",
    "wof:placetype":"locality",
    "wof:population":93
},
  "geometry": {"coordinates":[80.75066700000001,20.698244],"type":"Point"}
}