{
  "type": "Feature",
  "properties": {
    "iso:country":"IN",
    "ks:ks_name":"Pahi Jameen Pahi",
    "ks:ks_pop":260,
    "ks:ks_type":"HABITATION",
    "ks:ks_uagg_main":0,
    "name:eng_x_preferred":[
        "Pahi Jameen Pahi"
    ],
    "wof:name":"Pahi Jameen Pahi",
    "wof:placetype":"neighbourhood",
    "wof:population":260
},
  "geometry": {"coordinates":[83.324003,26.101674],"type":"Point"}
}