{
  "type": "Feature",
  "properties": {
    "iso:country":"IN",
    "ks:ks_name":"Harijan Basti",
    "ks:ks_pop":427,
    "ks:ks_type":"HABITATION",
    "name:eng_x_preferred":[
        "Harijan Basti"
    ],
    "wof:name":"Harijan Basti",
    "wof:placetype":"locality",
    "wof:population":427
},
  "geometry": {"coordinates":[83.099453,25.124923],"type":"Point"}
}