{
  "type": "Feature",
  "properties": {
    "iso:country":"IN",
    "ks:ks_name":"Kothavenkatapuram",
    "ks:ks_pop":523,
    "ks:ks_type":"HABITATION",
    "name:eng_x_preferred":[
        "Kothavenkatapuram"
    ],
    "wof:name":"Kothavenkatapuram",
    "wof:placetype":"locality",
    "wof:population":523
},
  "geometry": {"coordinates":[79.09763700000001,13.416957],"type":"Point"}
}