{
  "type": "Feature",
  "properties": {
    "iso:country":"IN",
    "ks:ks_name":"Dakshin Sisubari",
    "ks:ks_pop":1869,
    "ks:ks_type":"VILLAGE",
    "name:eng_x_preferred":[
        "Dakshin Sisubari"
    ],
    "wof:name":"Dakshin Sisubari",
    "wof:placetype":"locality",
    "wof:population":1869
},
  "geometry": {"coordinates":[89.18055099999999,26.676231],"type":"Point"}
}