{
  "type": "Feature",
  "properties": {
    "iso:country":"IN",
    "ks:ks_name":"Kata Chepda",
    "ks:ks_pop":103,
    "ks:ks_type":"HABITATION",
    "name:eng_x_preferred":[
        "Kata Chepda"
    ],
    "wof:name":"Kata Chepda",
    "wof:placetype":"locality",
    "wof:population":103
},
  "geometry": {"coordinates":[82.017668,19.402079],"type":"Point"}
}