{
  "type": "Feature",
  "properties": {
    "gn:admin1_code":"39.0",
    "gn:admin2_code":"63.0",
    "gn:asciiname":"Aran",
    "gn:country_code":"IN",
    "gn:dem":1387,
    "gn:feature_class":"P",
    "gn:feature_code":"PPL",
    "gn:name":"Ar\u0101n",
    "gn:population":0,
    "gn:timezone":"Asia/Kolkata",
    "iso:country":"IN",
    "name:aze_x_preferred":[
        "Aran"
    ],
    "name:bel_x_preferred":[
        "\u0410\u0440\u0430\u043d"
    ],
    "name:bre_x_preferred":[
        "Aran"
    ],
    "name:cat_x_preferred":[
        "Aran"
    ],
    "name:ceb_x_preferred":[
        "Aran"
    ],
    "name:ces_x_preferred":[
        "Aran"
    ],
    "name:cym_x_preferred":[
        "Aran"
    ],
    "name:deu_x_preferred":[
        "Aran"
    ],
    "name:eus_x_preferred":[
        "Aran"
    ],
    "name:fas_x_preferred":[
        "\u0627\u0631\u0627\u0646"
    ],
    "name:fra_x_preferred":[
        "Aran"
    ],
    "name:hye_x_preferred":[
        "\u0531\u0580\u0561\u0576"
    ],
    "name:ita_x_preferred":[
        "Aran"
    ],
    "name:kat_x_preferred":[
        "\u10d0\u10e0\u10d0\u10dc\u10d8"
    ],
    "name:lit_x_preferred":[
        "Aranas"
    ],
    "name:rus_x_preferred":[
        "\u0410\u0440\u0430\u043d"
    ],
    "name:srp_x_preferred":[
        "\u0410\u0440\u0430\u043d"
    ],
    "name:swe_x_preferred":[
        "Aran"
    ],
    "wof:name":"Aran",
    "wof:placetype":"locality"
},
  "geometry": {"coordinates":[79.59588000000002,29.91238],"type":"Point"}
}