{
  "type": "Feature",
  "properties": {
    "iso:country":"IN",
    "ks:ks_name":"Pardi",
    "ks:ks_pop":1202,
    "ks:ks_type":"VILLAGE",
    "name:eng_x_preferred":[
        "Pardi"
    ],
    "wof:name":"Pardi",
    "wof:placetype":"locality",
    "wof:population":1202
},
  "geometry": {"coordinates":[76.91715600000001,19.5566],"type":"Point"}
}