{
  "type": "Feature",
  "properties": {
    "gn:admin1_code":"19",
    "gn:admin2_code":"558.0",
    "gn:asciiname":"Madanewadi",
    "gn:country_code":"IN",
    "gn:dem":625,
    "gn:feature_class":"P",
    "gn:feature_code":"PPL",
    "gn:name":"Madanew\u0101di",
    "gn:population":0,
    "gn:timezone":"Asia/Kolkata",
    "iso:country":"IN",
    "wof:name":"Madanewadi",
    "wof:placetype":"locality"
},
  "geometry": {"coordinates":[76.76179999999999,17.86675],"type":"Point"}
}