{
  "type": "Feature",
  "properties": {
    "iso:country":"IN",
    "ks:ks_name":"Mudanagudi",
    "ks:ks_pop":73,
    "ks:ks_type":"HABITATION",
    "name:eng_x_preferred":[
        "Mudanagudi"
    ],
    "wof:name":"Mudanagudi",
    "wof:placetype":"locality",
    "wof:population":73
},
  "geometry": {"coordinates":[74.475714,14.187558],"type":"Point"}
}