{
  "type": "Feature",
  "properties": {
    "iso:country":"IN",
    "ks:ks_name":"Shimbhua",
    "ks:ks_pop":229,
    "ks:ks_type":"VILLAGE",
    "name:eng_x_preferred":[
        "Shimbhua"
    ],
    "wof:name":"Shimbhua",
    "wof:placetype":"locality",
    "wof:population":229
},
  "geometry": {"coordinates":[80.127872,28.374874],"type":"Point"}
}