{
  "type": "Feature",
  "properties": {
    "gn:country":"IN",
    "gn:fcode":"PPL",
    "gn:pop":20447,
    "iso:country":"IN",
    "name:ben_x_preferred":[
        "\u099a\u09bf\u09a8\u099a\u09cb\u09b2\u09bf"
    ],
    "name:bpy_x_preferred":[
        "\u099a\u09bf\u09a8\u099a\u09cb\u09b2\u09bf"
    ],
    "name:chi_x_preferred":[
        "\u5947\u6069\u4e54\u5229"
    ],
    "name:dut_x_preferred":[
        "Chincholi"
    ],
    "name:eng_x_preferred":[
        "Chincholi"
    ],
    "name:fre_x_preferred":[
        "Chincholi"
    ],
    "name:ger_x_preferred":[
        "Chincholi"
    ],
    "name:guj_x_preferred":[
        "\u0a9a\u0abf\u0aa8\u0acd\u0a95\u0acb\u0ab2\u0ac0"
    ],
    "name:ita_x_preferred":[
        "Chincholi"
    ],
    "name:jpn_x_preferred":[
        "\u30c1\u30f3\u30c1\u30e7\u30ea"
    ],
    "name:kan_x_preferred":[
        "\u0c9a\u0cbf\u0c82\u0c9a\u0ccb\u0cb3\u0cbf"
    ],
    "name:kor_x_preferred":[
        "\uce6d\ucf5c\ub9ac"
    ],
    "name:may_x_preferred":[
        "Chincholi"
    ],
    "name:mlg_x_preferred":[
        "Chincholi"
    ],
    "name:nan_x_preferred":[
        "Chincholi"
    ],
    "name:new_x_preferred":[
        "\u091a\u093f\u0928\u094d\u091a\u094b\u0932\u0940"
    ],
    "name:por_x_preferred":[
        "Chincholi"
    ],
    "name:rus_x_preferred":[
        "\u0427\u0438\u043d\u0447\u043e\u043b\u0438"
    ],
    "name:spa_x_preferred":[
        "Chincholi"
    ],
    "name:swe_x_preferred":[
        "Chincholi Taluk"
    ],
    "name:tam_x_preferred":[
        "\u0b9a\u0bbf\u0ba9\u0bcd\u0b9a\u0bcb\u0bb2\u0bbf"
    ],
    "name:tel_x_preferred":[
        "\u0c1a\u0c3f\u0c02\u0c1a\u0c4b\u0c32\u0c3f"
    ],
    "name:urd_x_preferred":[
        "\u0686\u06cc\u0646\u0686\u0648\u0644\u06cc"
    ],
    "name:vie_x_preferred":[
        "Chincholi"
    ],
    "qs:name":"Chincholi",
    "qs:name_adm0":"India",
    "qs:name_adm1":"Karnataka",
    "qs:photos_9r":0,
    "qs:photos_sr":0,
    "qs:placetype":"Town",
    "qs:pop_sr":"7",
    "wd:wordcount":236,
    "wof:name":"Chincholi",
    "wof:placetype":"locality",
    "wof:population":20447
},
  "geometry": {"coordinates":[77.41895,17.46483],"type":"Point"}
}