{
  "type": "Feature",
  "properties": {
    "iso:country":"IN",
    "ks:ks_alt_nam":"Kaithpur",
    "ks:ks_name":"Kaithpujha",
    "ks:ks_pop":0,
    "ks:ks_type":"VILLAGE",
    "name:eng_x_preferred":[
        "Kaithpujha"
    ],
    "name:eng_x_variant":[
        "Kaithpur"
    ],
    "wof:name":"Kaithpujha",
    "wof:placetype":"locality",
    "wof:population":0
},
  "geometry": {"coordinates":[87.16068799999999,24.895183],"type":"Point"}
}