{
  "type": "Feature",
  "properties": {
    "iso:country":"IN",
    "ks:ks_name":"Kosgai Mandir",
    "ks:ks_pop":1,
    "ks:ks_type":"HABITATION",
    "name:eng_x_preferred":[
        "Kosgai Mandir"
    ],
    "wof:name":"Kosgai Mandir",
    "wof:placetype":"locality",
    "wof:population":1
},
  "geometry": {"coordinates":[82.65218299999999,22.539762],"type":"Point"}
}