{
  "type": "Feature",
  "properties": {
    "iso:country":"IN",
    "ks:ks_name":"Talar F",
    "ks:ks_pop":230,
    "ks:ks_type":"HABITATION",
    "name:eng_x_preferred":[
        "Talar F"
    ],
    "wof:name":"Talar F",
    "wof:placetype":"locality",
    "wof:population":230
},
  "geometry": {"coordinates":[73.7141,23.02935],"type":"Point"}
}