{
  "type": "Feature",
  "properties": {
    "iso:country":"IN",
    "ks:ks_name":"Khalisamari No.1",
    "ks:ks_pop":181,
    "ks:ks_type":"HABITATION",
    "name:eng_x_preferred":[
        "Khalisamari No.1"
    ],
    "wof:name":"Khalisamari No.1",
    "wof:placetype":"locality",
    "wof:population":181
},
  "geometry": {"coordinates":[90.212828,26.081865],"type":"Point"}
}