{
  "type": "Feature",
  "properties": {
    "gn:admin1_code":"35.0",
    "gn:admin2_code":"455.0",
    "gn:asciiname":"Palaspani",
    "gn:country_code":"IN",
    "gn:dem":497,
    "gn:feature_class":"P",
    "gn:feature_code":"PPL",
    "gn:name":"Pal\u0101sp\u0101ni",
    "gn:population":0,
    "gn:timezone":"Asia/Kolkata",
    "iso:country":"IN",
    "ks:ks_alt_nam":"Pal\u0101sp\u0101ni",
    "ks:ks_name":"Palaspani",
    "ks:ks_pop":865,
    "ks:ks_type":"VILLAGE",
    "name:eng_x_preferred":[
        "Palaspani"
    ],
    "name:eng_x_variant":[
        "Pal\u0101sp\u0101ni"
    ],
    "wof:name":"Palaspani",
    "wof:placetype":"locality",
    "wof:population":865
},
  "geometry": {"coordinates":[78.713213,21.838229],"type":"Point"}
}