{
  "type": "Feature",
  "properties": {
    "iso:country":"IN",
    "ks:ks_name":"Sanatikraguda",
    "ks:ks_pop":52,
    "ks:ks_type":"VILLAGE",
    "name:eng_x_preferred":[
        "Sanatikraguda"
    ],
    "wof:name":"Sanatikraguda",
    "wof:placetype":"locality",
    "wof:population":52
},
  "geometry": {"coordinates":[83.01711,19.746263],"type":"Point"}
}