{
  "type": "Feature",
  "properties": {
    "iso:country":"IN",
    "ks:ks_name":"Bhalaur",
    "ks:ks_pop":924,
    "ks:ks_type":"VILLAGE",
    "name:eng_x_preferred":[
        "Bhalaur"
    ],
    "wof:name":"Bhalaur",
    "wof:placetype":"locality",
    "wof:population":924
},
  "geometry": {"coordinates":[82.22165699999999,23.263309],"type":"Point"}
}