{
  "type": "Feature",
  "properties": {
    "iso:country":"IN",
    "ks:ks_alt_nam":"Heranj\u0101l",
    "ks:ks_name":"Heranjal",
    "ks:ks_pop":1647,
    "ks:ks_type":"VILLAGE",
    "name:eng_x_preferred":[
        "Heranjal"
    ],
    "name:eng_x_variant":[
        "Heranj\u0101l"
    ],
    "wof:name":"Heranjal",
    "wof:placetype":"locality",
    "wof:population":1647
},
  "geometry": {"coordinates":[74.66483700000001,13.801497],"type":"Point"}
}