{
  "type": "Feature",
  "properties": {
    "iso:country":"IN",
    "ks:ks_name":"Maslandapur",
    "ks:ks_pop":9509,
    "ks:ks_type":"VILLAGE",
    "ks:ks_uagg_main":0,
    "name:eng_x_preferred":[
        "Maslandapur"
    ],
    "wof:name":"Maslandapur",
    "wof:placetype":"locality",
    "wof:population":9509
},
  "geometry": {"coordinates":[88.75049199999999,22.855797],"type":"Point"}
}