{
  "type": "Feature",
  "properties": {
    "gn:admin1_code":"25.0",
    "gn:admin2_code":"631.0",
    "gn:asciiname":"Papanur",
    "gn:country_code":"IN",
    "gn:dem":432,
    "gn:feature_class":"P",
    "gn:feature_code":"PPL",
    "gn:name":"P\u0101p\u0101n\u016br",
    "gn:population":0,
    "gn:timezone":"Asia/Kolkata",
    "iso:country":"IN",
    "ks:ks_name":"Pappanur",
    "ks:ks_pop":227,
    "ks:ks_type":"HABITATION",
    "name:eng_x_preferred":[
        "Pappanur"
    ],
    "name:eng_x_variant":[
        "Papanur"
    ],
    "wof:name":"Pappanur",
    "wof:placetype":"locality",
    "wof:population":227
},
  "geometry": {"coordinates":[78.324887,12.290152],"type":"Point"}
}