{
  "type": "Feature",
  "properties": {
    "gn:admin1_code":"25.0",
    "gn:admin2_code":"631.0",
    "gn:asciiname":"Papanur",
    "gn:country_code":"IN",
    "gn:dem":432,
    "gn:feature_class":"P",
    "gn:feature_code":"PPL",
    "gn:name":"P\u0101p\u0101n\u016br",
    "gn:population":0,
    "gn:timezone":"Asia/Kolkata",
    "iso:country":"IN",
    "wof:name":"Papanur",
    "wof:placetype":"locality"
},
  "geometry": {"coordinates":[78.34259,12.29463],"type":"Point"}
}