{
  "type": "Feature",
  "properties": {
    "gn:admin1_code":"34.0",
    "gn:admin2_code":"216.0",
    "gn:asciiname":"Basdeopatti",
    "gn:country_code":"IN",
    "gn:dem":57,
    "gn:feature_class":"P",
    "gn:feature_code":"PPL",
    "gn:name":"B\u0101sdeopatti",
    "gn:population":0,
    "gn:timezone":"Asia/Kolkata",
    "iso:country":"IN",
    "ks:ks_name":"Basudeo Patti",
    "ks:ks_pop":1901,
    "ks:ks_type":"VILLAGE",
    "name:eng_x_preferred":[
        "Basudeo Patti"
    ],
    "name:eng_x_variant":[
        "Basdeopatti"
    ],
    "wof:name":"Basudeo Patti",
    "wof:placetype":"locality",
    "wof:population":1901
},
  "geometry": {"coordinates":[85.14643,26.002987],"type":"Point"}
}