{
  "type": "Feature",
  "properties": {
    "iso:country":"IN",
    "ks:ks_name":"Asaniberana",
    "ks:ks_pop":100,
    "ks:ks_type":"HABITATION",
    "name:eng_x_preferred":[
        "Asaniberana"
    ],
    "wof:name":"Asaniberana",
    "wof:placetype":"locality",
    "wof:population":100
},
  "geometry": {"coordinates":[84.751891,20.385113],"type":"Point"}
}