{
  "type": "Feature",
  "properties": {
    "iso:country":"IN",
    "ks:ks_name":"Murgia Chak",
    "ks:ks_pop":169,
    "ks:ks_type":"VILLAGE",
    "name:eng_x_preferred":[
        "Murgia Chak"
    ],
    "wof:name":"Murgia Chak",
    "wof:placetype":"locality",
    "wof:population":169
},
  "geometry": {"coordinates":[85.20421899999999,25.761414],"type":"Point"}
}