{
  "type": "Feature",
  "properties": {
    "iso:country":"IN",
    "ks:ks_name":"Gokulanagar",
    "ks:ks_pop":110,
    "ks:ks_type":"HABITATION",
    "name:eng_x_preferred":[
        "Gokulanagar"
    ],
    "wof:name":"Gokulanagar",
    "wof:placetype":"locality",
    "wof:population":110
},
  "geometry": {"coordinates":[78.62499200000001,19.390126],"type":"Point"}
}