{
  "type": "Feature",
  "properties": {
    "gn:admin1_code":"37.0",
    "gn:admin2_code":"416.0",
    "gn:asciiname":"Dumam",
    "gn:country_code":"IN",
    "gn:dem":512,
    "gn:feature_class":"P",
    "gn:feature_code":"PPL",
    "gn:name":"Dum\u0101m",
    "gn:population":0,
    "gn:timezone":"Asia/Kolkata",
    "iso:country":"IN",
    "ks:ks_alt_nam":"Dum\u0101m",
    "ks:ks_name":"Dumam",
    "ks:ks_pop":523,
    "ks:ks_type":"VILLAGE",
    "name:eng_x_preferred":[
        "Dumam"
    ],
    "name:eng_x_variant":[
        "Dum\u0101m"
    ],
    "wof:name":"Dumam",
    "wof:placetype":"locality",
    "wof:population":523
},
  "geometry": {"coordinates":[81.502669,18.905141],"type":"Point"}
}