{
  "type": "Feature",
  "properties": {
    "gn:admin1_code":"19.0",
    "gn:admin2_code":"566.0",
    "gn:asciiname":"Bedarasivanakere",
    "gn:country_code":"IN",
    "gn:dem":716,
    "gn:feature_class":"P",
    "gn:feature_code":"PPL",
    "gn:name":"Bedarasivanakere",
    "gn:population":0,
    "gn:timezone":"Asia/Kolkata",
    "iso:country":"IN",
    "wof:name":"Bedarasivanakere",
    "wof:placetype":"locality"
},
  "geometry": {"coordinates":[76.21525,14.33172],"type":"Point"}
}