{
  "type": "Feature",
  "properties": {
    "gn:admin1_code":"11",
    "gn:admin2_code":"32.0",
    "gn:asciiname":"Naihna",
    "gn:country_code":"IN",
    "gn:dem":1733,
    "gn:feature_class":"P",
    "gn:feature_code":"PPL",
    "gn:name":"Naihna",
    "gn:population":0,
    "gn:timezone":"Asia/Kolkata",
    "iso:country":"IN",
    "wof:name":"Naihna",
    "wof:placetype":"locality"
},
  "geometry": {"coordinates":[77.66795999999999,30.75624],"type":"Point"}
}