{
  "type": "Feature",
  "properties": {
    "iso:country":"IN",
    "ks:ks_name":"Kayda",
    "ks:ks_pop":671,
    "ks:ks_type":"VILLAGE",
    "name:eng_x_preferred":[
        "Kayda"
    ],
    "wof:name":"Kayda",
    "wof:placetype":"locality",
    "wof:population":671
},
  "geometry": {"coordinates":[85.64582900000001,22.81314],"type":"Point"}
}