{
  "type": "Feature",
  "properties": {
    "gn:admin1_code":"35",
    "gn:admin2_code":"463.0",
    "gn:asciiname":"Muher",
    "gn:country_code":"IN",
    "gn:dem":467,
    "gn:feature_class":"P",
    "gn:feature_code":"PPL",
    "gn:name":"Muher",
    "gn:population":0,
    "gn:timezone":"Asia/Kolkata",
    "iso:country":"IN",
    "wof:name":"Muher",
    "wof:placetype":"locality"
},
  "geometry": {"coordinates":[82.59217,24.18848],"type":"Point"}
}