{
  "type": "Feature",
  "properties": {
    "iso:country":"IN",
    "ks:ks_name":"Barkol Barkalpara",
    "ks:ks_pop":757,
    "ks:ks_type":"HABITATION",
    "name:eng_x_preferred":[
        "Barkol Barkalpara"
    ],
    "wof:name":"Barkol Barkalpara",
    "wof:placetype":"locality",
    "wof:population":757
},
  "geometry": {"coordinates":[83.409666,23.167604],"type":"Point"}
}