{
  "type": "Feature",
  "properties": {
    "iso:country":"IN",
    "ks:ks_name":"Sankaradoddi",
    "ks:ks_pop":74,
    "ks:ks_type":"HABITATION",
    "name:eng_x_preferred":[
        "Sankaradoddi"
    ],
    "wof:name":"Sankaradoddi",
    "wof:placetype":"locality",
    "wof:population":74
},
  "geometry": {"coordinates":[76.968744,16.221497],"type":"Point"}
}