{
  "type": "Feature",
  "properties": {
    "iso:country":"IN",
    "ks:ks_name":"Kodarpura",
    "ks:ks_pop":170,
    "ks:ks_type":"HABITATION",
    "ks:ks_uagg_main":0,
    "name:eng_x_preferred":[
        "Kodarpura"
    ],
    "wof:name":"Kodarpura",
    "wof:placetype":"neighbourhood",
    "wof:population":170
},
  "geometry": {"coordinates":[73.466633,22.783667],"type":"Point"}
}