{
  "type": "Feature",
  "properties": {
    "iso:country":"IN",
    "ks:ks_name":"Balarampur",
    "ks:ks_pop":456,
    "ks:ks_type":"VILLAGE",
    "name:eng_x_preferred":[
        "Balarampur"
    ],
    "wof:name":"Balarampur",
    "wof:placetype":"locality",
    "wof:population":456
},
  "geometry": {"coordinates":[82.983092,19.773511],"type":"Point"}
}