{
  "type": "Feature",
  "properties": {
    "iso:country":"IN",
    "ks:ks_name":"Bridge Road",
    "ks:ks_pop":295,
    "ks:ks_type":"HABITATION",
    "name:eng_x_preferred":[
        "Bridge Road"
    ],
    "wof:name":"Bridge Road",
    "wof:placetype":"locality",
    "wof:population":295
},
  "geometry": {"coordinates":[76.11493900000001,10.62897],"type":"Point"}
}