{
  "type": "Feature",
  "properties": {
    "iso:country":"IN",
    "ks:ks_name":"Vengavayal",
    "ks:ks_type":"VILLAGE",
    "name:eng_x_preferred":[
        "Vengavayal"
    ],
    "wof:name":"Vengavayal",
    "wof:placetype":"locality"
},
  "geometry": {"coordinates":[78.81322900000001,10.465871],"type":"Point"}
}