{
  "type": "Feature",
  "properties": {
    "gn:admin1_code":"16",
    "gn:admin2_code":"503.0",
    "gn:asciiname":"Shivar Buzurg",
    "gn:country_code":"IN",
    "gn:dem":278,
    "gn:feature_class":"P",
    "gn:feature_code":"PPL",
    "gn:name":"Shivar Buzurg",
    "gn:population":0,
    "gn:timezone":"Asia/Kolkata",
    "iso:country":"IN",
    "ks:ks_name":"Shivar Buzurg",
    "ks:ks_pop":1079,
    "ks:ks_type":"VILLAGE",
    "ks:ks_uagg_main":0,
    "name:eng_x_preferred":[
        "Shivar Buzurg"
    ],
    "wof:name":"Shivar Buzurg",
    "wof:placetype":"neighbourhood",
    "wof:population":1079
},
  "geometry": {"coordinates":[77.295717,20.898882],"type":"Point"}
}