{
  "type": "Feature",
  "properties": {
    "iso:country":"IN",
    "ks:ks_name":"Desoi Ronghang",
    "ks:ks_pop":155,
    "ks:ks_type":"HABITATION",
    "name:eng_x_preferred":[
        "Desoi Ronghang"
    ],
    "wof:name":"Desoi Ronghang",
    "wof:placetype":"locality",
    "wof:population":155
},
  "geometry": {"coordinates":[93.509789,25.948426],"type":"Point"}
}