{
  "type": "Feature",
  "properties": {
    "iso:country":"IN",
    "ks:ks_name":"Ayeepatti",
    "ks:ks_pop":40,
    "ks:ks_type":"HABITATION",
    "name:eng_x_preferred":[
        "Ayeepatti"
    ],
    "wof:name":"Ayeepatti",
    "wof:placetype":"locality",
    "wof:population":40
},
  "geometry": {"coordinates":[78.939663,10.69389],"type":"Point"}
}