{
  "type": "Feature",
  "properties": {
    "iso:country":"IN",
    "ks:ks_alt_nam":"RISHAL TOLA",
    "ks:ks_name":"Rishal Tola",
    "ks:ks_pop":875,
    "ks:ks_type":"HABITATION",
    "ks:ks_uagg_main":0,
    "name:eng_x_preferred":[
        "Rishal Tola"
    ],
    "wof:name":"Rishal Tola",
    "wof:placetype":"neighbourhood",
    "wof:population":875
},
  "geometry": {"coordinates":[84.571353,25.783149],"type":"Point"}
}