{
  "type": "Feature",
  "properties": {
    "iso:country":"IN",
    "ks:ks_name":"Gorakhpur Mal.",
    "ks:ks_pop":2520,
    "ks:ks_type":"VILLAGE",
    "name:eng_x_preferred":[
        "Gorakhpur Mal."
    ],
    "wof:name":"Gorakhpur Mal.",
    "wof:placetype":"locality",
    "wof:population":2520
},
  "geometry": {"coordinates":[81.448971,22.752591],"type":"Point"}
}