{
  "type": "Feature",
  "properties": {
    "iso:country":"IN",
    "ks:ks_name":"Zarap",
    "ks:ks_pop":2481,
    "ks:ks_type":"VILLAGE",
    "name:eng_x_preferred":[
        "Zarap"
    ],
    "wof:name":"Zarap",
    "wof:placetype":"locality",
    "wof:population":2481
},
  "geometry": {"coordinates":[73.756936,15.942978],"type":"Point"}
}