{
  "type": "Feature",
  "properties": {
    "iso:country":"IN",
    "ks:ks_alt_nam":"Koli vasti",
    "ks:ks_name":"Koli Vasti",
    "ks:ks_pop":90,
    "ks:ks_type":"HABITATION",
    "name:eng_x_preferred":[
        "Koli Vasti"
    ],
    "wof:name":"Koli Vasti",
    "wof:placetype":"locality",
    "wof:population":90
},
  "geometry": {"coordinates":[74.635503,16.634381],"type":"Point"}
}