{
  "type": "Feature",
  "properties": {
    "gn:admin1_code":"10",
    "gn:admin2_code":"73.0",
    "gn:asciiname":"Chasiala",
    "gn:country_code":"IN",
    "gn:dem":238,
    "gn:feature_class":"P",
    "gn:feature_code":"PPL",
    "gn:name":"Chasi\u0101la",
    "gn:population":0,
    "gn:timezone":"Asia/Kolkata",
    "iso:country":"IN",
    "wof:name":"Chasiala",
    "wof:placetype":"locality"
},
  "geometry": {"coordinates":[76.31931,29.65985],"type":"Point"}
}