{
  "type": "Feature",
  "properties": {
    "iso:country":"IN",
    "ks:ks_name":"Kharda Kallan",
    "ks:ks_pop":226,
    "ks:ks_type":"HABITATION",
    "name:eng_x_preferred":[
        "Kharda Kallan"
    ],
    "wof:name":"Kharda Kallan",
    "wof:placetype":"locality",
    "wof:population":226
},
  "geometry": {"coordinates":[75.16604700000001,27.070717],"type":"Point"}
}