{
  "type": "Feature",
  "properties": {
    "gn:admin1_code":"11",
    "gn:admin2_code":"27.0",
    "gn:asciiname":"Kharnal",
    "gn:country_code":"IN",
    "gn:dem":1476,
    "gn:feature_class":"P",
    "gn:feature_code":"PPL",
    "gn:name":"Kharn\u0101l",
    "gn:population":0,
    "gn:timezone":"Asia/Kolkata",
    "iso:country":"IN",
    "name:hin_x_preferred":[
        "\u0916\u0930\u0928\u093e\u0932"
    ],
    "wof:name":"Kharnal",
    "wof:placetype":"locality"
},
  "geometry": {"coordinates":[76.81059,31.73328],"type":"Point"}
}