{
  "type": "Feature",
  "properties": {
    "iso:country":"IN",
    "ks:ks_name":"Uttar Dawaguri",
    "ks:ks_pop":1792,
    "ks:ks_type":"HABITATION",
    "ks:ks_uagg_main":0,
    "name:eng_x_preferred":[
        "Uttar Dawaguri"
    ],
    "wof:name":"Uttar Dawaguri",
    "wof:placetype":"neighbourhood",
    "wof:population":1792
},
  "geometry": {"coordinates":[89.27604700000001,26.420997],"type":"Point"}
}