{
  "type": "Feature",
  "properties": {
    "gn:admin1_code":"19.0",
    "gn:admin2_code":"565",
    "gn:asciiname":"Chilakanahatti",
    "gn:country_code":"IN",
    "gn:dem":553,
    "gn:feature_class":"P",
    "gn:feature_code":"PPL",
    "gn:name":"Chilakanahatti",
    "gn:population":0,
    "gn:timezone":"Asia/Kolkata",
    "iso:country":"IN",
    "wof:name":"Chilakanahatti",
    "wof:placetype":"locality"
},
  "geometry": {"coordinates":[76.34799,15.07473],"type":"Point"}
}