{
  "type": "Feature",
  "properties": {
    "iso:country":"IN",
    "ks:ks_name":"Shyampura",
    "ks:ks_pop":0,
    "ks:ks_type":"VILLAGE",
    "name:eng_x_preferred":[
        "Shyampura"
    ],
    "wof:name":"Shyampura",
    "wof:placetype":"locality",
    "wof:population":0
},
  "geometry": {"coordinates":[75.162634,24.709439],"type":"Point"}
}