{
  "type": "Feature",
  "properties": {
    "iso:country":"IN",
    "ks:ks_name":"Purba Panchberia",
    "ks:ks_pop":350,
    "ks:ks_type":"HABITATION",
    "name:eng_x_preferred":[
        "Purba Panchberia"
    ],
    "wof:name":"Purba Panchberia",
    "wof:placetype":"locality",
    "wof:population":350
},
  "geometry": {"coordinates":[87.796982,23.98658],"type":"Point"}
}