{
  "type": "Feature",
  "properties": {
    "gn:admin1_code":"16",
    "gn:admin2_code":"507.0",
    "gn:asciiname":"Chicholi",
    "gn:country_code":"IN",
    "gn:dem":240,
    "gn:feature_class":"P",
    "gn:feature_code":"PPL",
    "gn:name":"Chicholi",
    "gn:population":0,
    "gn:timezone":"Asia/Kolkata",
    "iso:country":"IN",
    "name:ben_x_preferred":[
        "\u099a\u09bf\u099a\u09cb\u09b2\u09bf"
    ],
    "name:bpy_x_preferred":[
        "\u099a\u09bf\u099a\u09cb\u09b2\u09bf"
    ],
    "name:ceb_x_preferred":[
        "Ch\u012bcholi"
    ],
    "name:glg_x_preferred":[
        "Chicholi"
    ],
    "name:ind_x_preferred":[
        "Chicholi"
    ],
    "name:ita_x_preferred":[
        "Chicholi"
    ],
    "name:msa_x_preferred":[
        "Chicholi"
    ],
    "name:new_x_preferred":[
        "\u091a\u093f\u091a\u094b\u0932\u0940"
    ],
    "name:nld_x_preferred":[
        "Chicholi"
    ],
    "name:por_x_preferred":[
        "Chicholi"
    ],
    "name:swe_x_preferred":[
        "Ch\u012bcholi"
    ],
    "name:urd_x_preferred":[
        "\u0686\u06cc\u0686\u0648\u0644\u06cc"
    ],
    "name:vie_x_preferred":[
        "Chicholi"
    ],
    "name:zho_x_preferred":[
        "\u5947\u4e54\u5229"
    ],
    "wof:name":"Chicholi",
    "wof:placetype":"locality"
},
  "geometry": {"coordinates":[80.10916999999998,20.75355],"type":"Point"}
}