{
  "type": "Feature",
  "properties": {
    "iso:country":"IN",
    "ks:ks_alt_nam":"kokatepada",
    "ks:ks_name":"Kokatepada",
    "ks:ks_pop":132,
    "ks:ks_type":"HABITATION",
    "name:eng_x_preferred":[
        "Kokatepada"
    ],
    "wof:name":"Kokatepada",
    "wof:placetype":"locality",
    "wof:population":132
},
  "geometry": {"coordinates":[73.167697,19.686189],"type":"Point"}
}