{
  "type": "Feature",
  "properties": {
    "iso:country":"IN",
    "ks:ks_alt_nam":"Siddapur LT vasti",
    "ks:ks_name":"Siddapur Lt Vasti",
    "ks:ks_pop":249,
    "ks:ks_type":"HABITATION",
    "name:eng_x_preferred":[
        "Siddapur Lt Vasti"
    ],
    "wof:name":"Siddapur Lt Vasti",
    "wof:placetype":"locality",
    "wof:population":249
},
  "geometry": {"coordinates":[75.50894700000001,16.363537],"type":"Point"}
}