{
  "type": "Feature",
  "properties": {
    "gn:admin1_code":"34.0",
    "gn:admin2_code":"236.0",
    "gn:asciiname":"Niamatpur",
    "gn:country_code":"IN",
    "gn:dem":99,
    "gn:feature_class":"P",
    "gn:feature_code":"PPL",
    "gn:name":"Ni\u0101matpur",
    "gn:population":0,
    "gn:timezone":"Asia/Kolkata",
    "iso:country":"IN",
    "ks:ks_name":"Niamatpur",
    "ks:ks_pop":808,
    "ks:ks_type":"HABITATION",
    "ks:ks_uagg_main":0,
    "name:eng_x_preferred":[
        "Niamatpur"
    ],
    "name:por_x_preferred":[
        "Niamatpur"
    ],
    "wof:name":"Niamatpur",
    "wof:placetype":"neighbourhood",
    "wof:population":808
},
  "geometry": {"coordinates":[84.98696099999999,24.940338],"type":"Point"}
}