{
  "type": "Feature",
  "properties": {
    "iso:country":"IN",
    "ks:ks_name":"Dhawaia",
    "ks:ks_pop":669,
    "ks:ks_type":"VILLAGE",
    "ks:ks_uagg_main":0,
    "name:eng_x_preferred":[
        "Dhawaia"
    ],
    "wof:name":"Dhawaia",
    "wof:placetype":"neighbourhood",
    "wof:population":669
},
  "geometry": {"coordinates":[85.39986399999999,24.088745],"type":"Point"}
}