{
  "type": "Feature",
  "properties": {
    "gn:admin1_code":"23.0",
    "gn:admin2_code":"43.0",
    "gn:asciiname":"Sadduwala",
    "gn:country_code":"IN",
    "gn:dem":199,
    "gn:feature_class":"P",
    "gn:feature_code":"PPL",
    "gn:name":"Sadd\u016bw\u0101la",
    "gn:population":0,
    "gn:timezone":"Asia/Kolkata",
    "iso:country":"IN",
    "wof:name":"Sadduwala",
    "wof:placetype":"locality"
},
  "geometry": {"coordinates":[74.74852,30.9803],"type":"Point"}
}