{
  "type": "Feature",
  "properties": {
    "iso:country":"IN",
    "ks:ks_name":"Arimara Pathar",
    "ks:ks_pop":828,
    "ks:ks_type":"VILLAGE",
    "name:eng_x_preferred":[
        "Arimara Pathar"
    ],
    "wof:name":"Arimara Pathar",
    "wof:placetype":"locality",
    "wof:population":828
},
  "geometry": {"coordinates":[92.713297,26.652544],"type":"Point"}
}