{
  "type": "Feature",
  "properties": {
    "iso:country":"IN",
    "ks:ks_alt_nam":"HARIJAN TOLA",
    "ks:ks_name":"Harijan Tola",
    "ks:ks_pop":307,
    "ks:ks_type":"HABITATION",
    "name:eng_x_preferred":[
        "Harijan Tola"
    ],
    "wof:name":"Harijan Tola",
    "wof:placetype":"locality",
    "wof:population":307
},
  "geometry": {"coordinates":[83.50257499999999,24.809829],"type":"Point"}
}