{
  "type": "Feature",
  "properties": {
    "iso:country":"IN",
    "ks:ks_name":"Mondalpara",
    "ks:ks_pop":547,
    "ks:ks_type":"HABITATION",
    "name:eng_x_preferred":[
        "Mondalpara"
    ],
    "wof:name":"Mondalpara",
    "wof:placetype":"locality",
    "wof:population":547
},
  "geometry": {"coordinates":[87.924986,22.553806],"type":"Point"}
}