{
  "type": "Feature",
  "properties": {
    "iso:country":"IN",
    "ks:ks_name":"Khirkhiha",
    "ks:ks_pop":562,
    "ks:ks_type":"HABITATION",
    "ks:ks_uagg_main":0,
    "name:eng_x_preferred":[
        "Khirkhiha"
    ],
    "wof:name":"Khirkhiha",
    "wof:placetype":"neighbourhood",
    "wof:population":562
},
  "geometry": {"coordinates":[81.056817,27.094751],"type":"Point"}
}