{
  "type": "Feature",
  "properties": {
    "iso:country":"IN",
    "ks:ks_alt_nam":"Ramalingampatti AD Colony",
    "ks:ks_name":"Ramalingampatti Ad Colony",
    "ks:ks_pop":108,
    "ks:ks_type":"HABITATION",
    "ks:ks_uagg_main":0,
    "name:eng_x_preferred":[
        "Ramalingampatti Ad Colony"
    ],
    "wof:name":"Ramalingampatti Ad Colony",
    "wof:placetype":"neighbourhood",
    "wof:population":108
},
  "geometry": {"coordinates":[77.829407,10.426747],"type":"Point"}
}