{
  "type": "Feature",
  "properties": {
    "iso:country":"IN",
    "ks:ks_alt_nam":"Fatehp\u016br",
    "ks:ks_name":"Fatehpur",
    "ks:ks_type":"VILLAGE",
    "name:eng_x_preferred":[
        "Fatehpur"
    ],
    "name:eng_x_variant":[
        "Fatehp\u016br"
    ],
    "name:hin_x_preferred":[
        "\u095e\u0924\u0947\u0939\u092a\u0941\u0930"
    ],
    "wof:name":"Fatehpur",
    "wof:placetype":"locality"
},
  "geometry": {"coordinates":[78.25843500000001,28.042616],"type":"Point"}
}