{
  "type": "Feature",
  "properties": {
    "iso:country":"IN",
    "ks:ks_name":"Bairaorn",
    "ks:ks_pop":372,
    "ks:ks_type":"HABITATION",
    "name:eng_x_preferred":[
        "Bairaorn"
    ],
    "wof:name":"Bairaorn",
    "wof:placetype":"locality",
    "wof:population":372
},
  "geometry": {"coordinates":[80.03967900000001,29.438809],"type":"Point"}
}