{
  "type": "Feature",
  "properties": {
    "iso:country":"IN",
    "ks:ks_name":"Tangini",
    "ks:ks_pop":148,
    "ks:ks_type":"HABITATION",
    "name:eng_x_preferred":[
        "Tangini"
    ],
    "wof:name":"Tangini",
    "wof:placetype":"locality",
    "wof:population":148
},
  "geometry": {"coordinates":[84.33006,18.775851],"type":"Point"}
}