{
  "type": "Feature",
  "properties": {
    "iso:country":"IN",
    "ks:ks_name":"Vanwasi",
    "ks:ks_pop":16,
    "ks:ks_type":"HABITATION",
    "name:eng_x_preferred":[
        "Vanwasi"
    ],
    "wof:name":"Vanwasi",
    "wof:placetype":"locality",
    "wof:population":16
},
  "geometry": {"coordinates":[82.71543,25.290226],"type":"Point"}
}