{
  "type": "Feature",
  "properties": {
    "gn:admin1_code":"19.0",
    "gn:admin2_code":"563.0",
    "gn:asciiname":"Telginmane",
    "gn:country_code":"IN",
    "gn:dem":518,
    "gn:feature_class":"P",
    "gn:feature_code":"PPL",
    "gn:name":"Telginmane",
    "gn:population":0,
    "gn:timezone":"Asia/Kolkata",
    "iso:country":"IN",
    "ks:ks_name":"Kelginmane",
    "ks:ks_pop":360,
    "ks:ks_type":"VILLAGE",
    "name:eng_x_preferred":[
        "Kelginmane"
    ],
    "name:eng_x_variant":[
        "Telginmane"
    ],
    "wof:name":"Kelginmane",
    "wof:placetype":"locality",
    "wof:population":360
},
  "geometry": {"coordinates":[74.740993,14.325619],"type":"Point"}
}