{
  "type": "Feature",
  "properties": {
    "gn:admin1_code":"36.0",
    "gn:admin2_code":"152",
    "gn:asciiname":"Harnokha",
    "gn:country_code":"IN",
    "gn:dem":151,
    "gn:feature_class":"P",
    "gn:feature_code":"PPL",
    "gn:name":"Harnokha",
    "gn:population":0,
    "gn:timezone":"Asia/Kolkata",
    "iso:country":"IN",
    "wof:name":"Harnokha",
    "wof:placetype":"locality"
},
  "geometry": {"coordinates":[79.43042,27.80614000000001],"type":"Point"}
}