{
  "type": "Feature",
  "properties": {
    "iso:country":"IN",
    "ks:ks_alt_nam":"MGR colony",
    "ks:ks_name":"Mgr Colony",
    "ks:ks_pop":360,
    "ks:ks_type":"HABITATION",
    "ks:ks_uagg_main":0,
    "name:eng_x_preferred":[
        "Mgr Colony"
    ],
    "wof:name":"Mgr Colony",
    "wof:placetype":"neighbourhood",
    "wof:population":360
},
  "geometry": {"coordinates":[79.55816,11.881589],"type":"Point"}
}