{
  "type": "Feature",
  "properties": {
    "iso:country":"IN",
    "ks:ks_name":"Yanaimalai Quarry",
    "ks:ks_pop":502,
    "ks:ks_type":"HABITATION",
    "name:eng_x_preferred":[
        "Yanaimalai Quarry"
    ],
    "wof:name":"Yanaimalai Quarry",
    "wof:placetype":"locality",
    "wof:population":502
},
  "geometry": {"coordinates":[78.194783,9.970983],"type":"Point"}
}