{
  "type": "Feature",
  "properties": {
    "iso:country":"IN",
    "ks:ks_name":"Gadabaguda",
    "ks:ks_pop":40,
    "ks:ks_type":"HABITATION",
    "name:eng_x_preferred":[
        "Gadabaguda"
    ],
    "wof:name":"Gadabaguda",
    "wof:placetype":"locality",
    "wof:population":40
},
  "geometry": {"coordinates":[82.99567399999999,18.535531],"type":"Point"}
}