{
  "type": "Feature",
  "properties": {
    "iso:country":"IN",
    "ks:ks_name":"Metela",
    "ks:ks_pop":1261,
    "ks:ks_type":"VILLAGE",
    "ks:ks_uagg_main":0,
    "name:eng_x_preferred":[
        "Metela"
    ],
    "wof:name":"Metela",
    "wof:placetype":"neighbourhood",
    "wof:population":1261
},
  "geometry": {"coordinates":[87.501414,22.799579],"type":"Point"}
}