{
  "type": "Feature",
  "properties": {
    "iso:country":"IN",
    "ks:ks_name":"Gaddehalla",
    "ks:ks_pop":138,
    "ks:ks_type":"HABITATION",
    "name:eng_x_preferred":[
        "Gaddehalla"
    ],
    "wof:name":"Gaddehalla",
    "wof:placetype":"locality",
    "wof:population":138
},
  "geometry": {"coordinates":[76.384316,11.884443],"type":"Point"}
}