{
  "type": "Feature",
  "properties": {
    "gn:admin1_code":"21.0",
    "gn:admin2_code":"381",
    "gn:asciiname":"Katakiasahi",
    "gn:country_code":"IN",
    "gn:dem":34,
    "gn:feature_class":"P",
    "gn:feature_code":"PPL",
    "gn:name":"Kataki\u0101s\u0101hi",
    "gn:population":0,
    "gn:timezone":"Asia/Kolkata",
    "iso:country":"IN",
    "wof:name":"Katakiasahi",
    "wof:placetype":"locality"
},
  "geometry": {"coordinates":[85.73333000000002,20.46667],"type":"Point"}
}