{
  "type": "Feature",
  "properties": {
    "iso:country":"IN",
    "ks:ks_name":"Ekkal",
    "ks:ks_pop":173,
    "ks:ks_type":"HABITATION",
    "name:eng_x_preferred":[
        "Ekkal"
    ],
    "wof:name":"Ekkal",
    "wof:placetype":"locality",
    "wof:population":173
},
  "geometry": {"coordinates":[79.305376,10.820003],"type":"Point"}
}