{
  "type": "Feature",
  "properties": {
    "iso:country":"IN",
    "ks:ks_name":"Amli Padar",
    "ks:ks_pop":620,
    "ks:ks_type":"HABITATION",
    "name:eng_x_preferred":[
        "Amli Padar"
    ],
    "wof:name":"Amli Padar",
    "wof:placetype":"locality",
    "wof:population":620
},
  "geometry": {"coordinates":[81.653938,19.56114],"type":"Point"}
}