{
  "type": "Feature",
  "properties": {
    "gn:admin1_code":"12",
    "gn:admin2_code":"22.0",
    "gn:asciiname":"Chatgiran",
    "gn:country_code":"IN",
    "gn:dem":282,
    "gn:feature_class":"P",
    "gn:feature_code":"PPL",
    "gn:name":"Ch\u0101tgir\u0101n",
    "gn:population":0,
    "gn:timezone":"Asia/Kolkata",
    "iso:country":"IN",
    "wof:name":"Chatgiran",
    "wof:placetype":"locality"
},
  "geometry": {"coordinates":[74.8775,32.50834],"type":"Point"}
}