{
  "type": "Feature",
  "properties": {
    "gn:country":"IN",
    "gn:fcode":"PPL",
    "gn:pop":11617,
    "iso:country":"IN",
    "name:unk_x_variant":[
        "P\u0101pp\u0101rappatti"
    ],
    "qs:name":"Papparapatti",
    "qs:name_adm0":"India",
    "qs:name_adm1":"Tamil Nadu",
    "qs:photos_9r":0,
    "qs:photos_sr":0,
    "qs:placetype":"Town",
    "qs:pop_sr":"6",
    "wd:wordcount":8,
    "wof:name":"Papparapatti",
    "wof:placetype":"locality",
    "wof:population":11617
},
  "geometry": {"coordinates":[78.05923,12.22093],"type":"Point"}
}