{
  "type": "Feature",
  "properties": {
    "gn:country":"IN",
    "gn:fcode":"PPL",
    "gn:pop":11617,
    "iso:country":"IN",
    "name:bpy_x_preferred":[
        "\u09aa\u09be\u09aa\u09cd\u09aa\u09be\u09b0\u09bf\u09aa\u09be\u09a4\u09cd\u09a4\u09bf"
    ],
    "name:deu_x_preferred":[
        "Papparapatti"
    ],
    "name:eng_x_preferred":[
        "Papparapatti"
    ],
    "name:fra_x_preferred":[
        "Papparapatti"
    ],
    "name:ita_x_preferred":[
        "Papparapatti"
    ],
    "name:nld_x_preferred":[
        "Papparapatti"
    ],
    "name:tam_x_preferred":[
        "\u0baa\u0bbe\u0baa\u0bcd\u0baa\u0bbe\u0bb0\u0baa\u0bcd\u0baa\u0b9f\u0bcd\u0b9f\u0bbf"
    ],
    "name:unk_x_variant":[
        "P\u0101pp\u0101rappatti"
    ],
    "qs:name":"Papparapatti",
    "qs:name_adm0":"India",
    "qs:name_adm1":"Tamil Nadu",
    "qs:photos_9r":0,
    "qs:photos_sr":0,
    "qs:placetype":"Town",
    "qs:pop_sr":"6",
    "wd:wordcount":8,
    "wof:name":"Papparapatti",
    "wof:placetype":"locality",
    "wof:population":11617
},
  "geometry": {"coordinates":[78.05923,12.22093],"type":"Point"}
}