{
  "type": "Feature",
  "properties": {
    "iso:country":"IN",
    "ks:ks_name":"Krishnapur",
    "ks:ks_pop":5248,
    "ks:ks_type":"VILLAGE",
    "name:eng_x_preferred":[
        "Krishnapur"
    ],
    "wof:name":"Krishnapur",
    "wof:placetype":"locality",
    "wof:population":5248
},
  "geometry": {"coordinates":[89.65934300000001,26.234576],"type":"Point"}
}