{
  "type": "Feature",
  "properties": {
    "gn:admin1_code":"36",
    "gn:admin2_code":"201.0",
    "gn:asciiname":"Nagla Lachhu",
    "gn:country_code":"IN",
    "gn:dem":156,
    "gn:feature_class":"P",
    "gn:feature_code":"PPL",
    "gn:name":"Nagla Lachh\u016b",
    "gn:population":0,
    "gn:timezone":"Asia/Kolkata",
    "iso:country":"IN",
    "wof:name":"Nagla Lachhu",
    "wof:placetype":"locality"
},
  "geometry": {"coordinates":[79.23908,27.39092],"type":"Point"}
}