{
  "type": "Feature",
  "properties": {
    "iso:country":"IN",
    "ks:ks_name":"Barnadi",
    "ks:ks_pop":59,
    "ks:ks_type":"VILLAGE",
    "name:eng_x_preferred":[
        "Barnadi"
    ],
    "wof:name":"Barnadi",
    "wof:placetype":"locality",
    "wof:population":59
},
  "geometry": {"coordinates":[87.365844,24.884381],"type":"Point"}
}