{
  "type": "Feature",
  "properties": {
    "gn:admin1_code":"23",
    "gn:admin2_code":"40.0",
    "gn:asciiname":"Jalalpur",
    "gn:country_code":"IN",
    "gn:dem":263,
    "gn:feature_class":"P",
    "gn:feature_code":"PPL",
    "gn:name":"Jal\u0101lpur",
    "gn:population":0,
    "gn:timezone":"Asia/Kolkata",
    "iso:country":"IN",
    "wof:name":"Jalalpur",
    "wof:placetype":"locality"
},
  "geometry": {"coordinates":[76.27096999999998,30.62951],"type":"Point"}
}