{
  "type": "Feature",
  "properties": {
    "iso:country":"IN",
    "ks:ks_name":"Duwakoti",
    "ks:ks_pop":457,
    "ks:ks_type":"HABITATION",
    "name:eng_x_preferred":[
        "Duwakoti"
    ],
    "wof:name":"Duwakoti",
    "wof:placetype":"locality",
    "wof:population":457
},
  "geometry": {"coordinates":[78.43432300000001,30.278943],"type":"Point"}
}