{
  "type": "Feature",
  "properties": {
    "iso:country":"IN",
    "ks:ks_name":"Fateh Ali Khan",
    "ks:ks_pop":0,
    "ks:ks_type":"VILLAGE",
    "name:eng_x_preferred":[
        "Fateh Ali Khan"
    ],
    "wof:name":"Fateh Ali Khan",
    "wof:placetype":"locality",
    "wof:population":0
},
  "geometry": {"coordinates":[75.152587,31.332681],"type":"Point"}
}