{
  "type": "Feature",
  "properties": {
    "iso:country":"IN",
    "ks:ks_name":"Sarkar Bairoji",
    "ks:ks_pop":101,
    "ks:ks_type":"HABITATION",
    "ks:ks_uagg_main":0,
    "name:eng_x_preferred":[
        "Sarkar Bairoji"
    ],
    "wof:name":"Sarkar Bairoji",
    "wof:placetype":"neighbourhood",
    "wof:population":101
},
  "geometry": {"coordinates":[78.07031600000001,11.557629],"type":"Point"}
}