{
  "type": "Feature",
  "properties": {
    "iso:country":"IN",
    "ks:ks_name":"Matarlonga",
    "ks:ks_pop":152,
    "ks:ks_type":"VILLAGE",
    "name:eng_x_preferred":[
        "Matarlonga"
    ],
    "wof:name":"Matarlonga",
    "wof:placetype":"locality",
    "wof:population":152
},
  "geometry": {"coordinates":[83.920085,22.948806],"type":"Point"}
}