{
  "type": "Feature",
  "properties": {
    "gn:admin1_code":"34.0",
    "gn:admin2_code":"203.0",
    "gn:asciiname":"Mukri",
    "gn:country_code":"IN",
    "gn:dem":87,
    "gn:feature_class":"P",
    "gn:feature_code":"PPL",
    "gn:name":"Mukri",
    "gn:population":0,
    "gn:timezone":"Asia/Kolkata",
    "iso:country":"IN",
    "name:hin_x_preferred":[
        "\u092e\u0941\u0915\u0930\u0940"
    ],
    "name:kan_x_preferred":[
        "\u0cae\u0cc1\u0c95\u0ccd\u0cb0\u0cbf"
    ],
    "name:ori_x_preferred":[
        "\u0b2e\u0b41\u0b15\u0b4d\u0b30\u0b40"
    ],
    "name:urd_x_preferred":[
        "\u0645\u0642\u0631\u06cc"
    ],
    "wof:name":"Mukri",
    "wof:placetype":"locality"
},
  "geometry": {"coordinates":[84.15179000000001,26.93958],"type":"Point"}
}