{
  "type": "Feature",
  "properties": {
    "iso:country":"IN",
    "ks:ks_name":"Kaladubi",
    "ks:ks_pop":356,
    "ks:ks_type":"HABITATION",
    "name:eng_x_preferred":[
        "Kaladubi"
    ],
    "wof:name":"Kaladubi",
    "wof:placetype":"locality",
    "wof:population":356
},
  "geometry": {"coordinates":[95.08751100000001,27.118405],"type":"Point"}
}