{
  "type": "Feature",
  "properties": {
    "iso:country":"IN",
    "ks:ks_name":"Layek Bazar",
    "ks:ks_pop":2354,
    "ks:ks_type":"VILLAGE",
    "ks:ks_uagg_main":0,
    "name:eng_x_preferred":[
        "Layek Bazar"
    ],
    "wof:name":"Layek Bazar",
    "wof:placetype":"locality",
    "wof:population":2354
},
  "geometry": {"coordinates":[87.717944,23.673186],"type":"Point"}
}