{
  "type": "Feature",
  "properties": {
    "iso:country":"IN",
    "ks:ks_name":"Thiruvidavasal",
    "ks:ks_pop":2176,
    "ks:ks_type":"VILLAGE",
    "ks:ks_uagg_main":0,
    "name:eng_x_preferred":[
        "Thiruvidavasal"
    ],
    "wof:name":"Thiruvidavasal",
    "wof:placetype":"neighbourhood",
    "wof:population":2176
},
  "geometry": {"coordinates":[79.498294,10.761714],"type":"Point"}
}