{
  "type": "Feature",
  "properties": {
    "gn:admin1_code":"36",
    "gn:admin2_code":"171.0",
    "gn:asciiname":"Kulai",
    "gn:country_code":"IN",
    "gn:dem":147,
    "gn:feature_class":"P",
    "gn:feature_code":"PPL",
    "gn:name":"Kulai",
    "gn:population":0,
    "gn:timezone":"Asia/Kolkata",
    "iso:country":"IN",
    "name:ceb_x_preferred":[
        "Kulai"
    ],
    "name:fas_x_preferred":[
        "\u06a9\u0648\u0644\u0627\u06cc"
    ],
    "name:ind_x_preferred":[
        "Kulai"
    ],
    "name:ita_x_preferred":[
        "Kulai"
    ],
    "name:msa_x_preferred":[
        "Kulai"
    ],
    "name:pol_x_preferred":[
        "Kulai"
    ],
    "name:urd_x_preferred":[
        "\u06a9\u0648\u0644\u0627\u0626\u06cc"
    ],
    "wof:name":"Kulai",
    "wof:placetype":"neighbourhood"
},
  "geometry": {"coordinates":[81.44558000000001,25.12391],"type":"Point"}
}