{
  "type": "Feature",
  "properties": {
    "gn:admin1_code":"36.0",
    "gn:admin2_code":"140.0",
    "gn:asciiname":"Chachoi",
    "gn:country_code":"IN",
    "gn:dem":210,
    "gn:feature_class":"P",
    "gn:feature_code":"PPL",
    "gn:name":"Chachoi",
    "gn:population":0,
    "gn:timezone":"Asia/Kolkata",
    "iso:country":"IN",
    "ks:ks_name":"Chachoi",
    "ks:ks_type":"VILLAGE",
    "name:eng_x_preferred":[
        "Chachoi"
    ],
    "wof:name":"Chachoi",
    "wof:placetype":"locality"
},
  "geometry": {"coordinates":[77.774293,28.609339],"type":"Point"}
}