{
  "type": "Feature",
  "properties": {
    "gn:admin1_code":"25.0",
    "gn:admin2_code":"632",
    "gn:asciiname":"Karumattampatti",
    "gn:country_code":"IN",
    "gn:dem":357,
    "gn:feature_class":"P",
    "gn:feature_code":"PPL",
    "gn:name":"Karumattampatti",
    "gn:population":0,
    "gn:timezone":"Asia/Kolkata",
    "iso:country":"IN",
    "ks:ks_name":"Karumathampatti",
    "ks:ks_pop":26477,
    "ks:ks_type":"VILLAGE",
    "ks:ks_uagg_main":0,
    "name:eng_x_preferred":[
        "Karumathampatti"
    ],
    "wof:name":"Karumathampatti",
    "wof:placetype":"locality",
    "wof:population":26477
},
  "geometry": {"coordinates":[77.17952200000001,11.099749],"type":"Point"}
}