{
  "type": "Feature",
  "properties": {
    "gn:admin1_code":"11.0",
    "gn:admin2_code":"24.0",
    "gn:asciiname":"Raprian-di-Sar",
    "gn:country_code":"IN",
    "gn:dem":476,
    "gn:feature_class":"P",
    "gn:feature_code":"PPL",
    "gn:name":"Rapri\u0101n-di-Sar",
    "gn:population":0,
    "gn:timezone":"Asia/Kolkata",
    "iso:country":"IN",
    "wof:name":"Raprian-di-Sar",
    "wof:placetype":"locality"
},
  "geometry": {"coordinates":[75.80665,32.24045],"type":"Point"}
}