{
  "type": "Feature",
  "properties": {
    "iso:country":"IN",
    "ks:ks_name":"Dehdala",
    "ks:ks_pop":295,
    "ks:ks_type":"VILLAGE",
    "name:eng_x_preferred":[
        "Dehdala"
    ],
    "wof:name":"Dehdala",
    "wof:placetype":"locality",
    "wof:population":295
},
  "geometry": {"coordinates":[74.94372799999999,22.070688],"type":"Point"}
}