{
  "type": "Feature",
  "properties": {
    "iso:country":"IN",
    "ks:ks_name":"Giria Pahi",
    "ks:ks_pop":666,
    "ks:ks_type":"VILLAGE",
    "name:eng_x_preferred":[
        "Giria Pahi"
    ],
    "wof:name":"Giria Pahi",
    "wof:placetype":"locality",
    "wof:population":666
},
  "geometry": {"coordinates":[86.960218,20.733896],"type":"Point"}
}