{
  "type": "Feature",
  "properties": {
    "iso:country":"IN",
    "ks:ks_name":"Kuchimunda",
    "ks:ks_pop":109,
    "ks:ks_type":"VILLAGE",
    "name:eng_x_preferred":[
        "Kuchimunda"
    ],
    "wof:name":"Kuchimunda",
    "wof:placetype":"locality",
    "wof:population":109
},
  "geometry": {"coordinates":[83.483971,20.585015],"type":"Point"}
}