{
  "type": "Feature",
  "properties": {
    "iso:country":"IN",
    "ks:ks_name":"Haridah",
    "ks:ks_pop":962,
    "ks:ks_type":"VILLAGE",
    "name:eng_x_preferred":[
        "Haridah"
    ],
    "wof:name":"Haridah",
    "wof:placetype":"locality",
    "wof:population":962
},
  "geometry": {"coordinates":[93.81111300000001,26.880265],"type":"Point"}
}