{
  "type": "Feature",
  "properties": {
    "iso:country":"IN",
    "ks:ks_alt_nam":"KARTHIKEYAPURAM",
    "ks:ks_name":"Karthikeyapuram",
    "ks:ks_pop":162,
    "ks:ks_type":"HABITATION",
    "ks:ks_uagg_main":0,
    "name:eng_x_preferred":[
        "Karthikeyapuram"
    ],
    "wof:name":"Karthikeyapuram",
    "wof:placetype":"neighbourhood",
    "wof:population":162
},
  "geometry": {"coordinates":[79.18807,13.371998],"type":"Point"}
}