{
  "type": "Feature",
  "properties": {
    "iso:country":"IN",
    "ks:ks_name":"Alagappagoundenpudur",
    "ks:ks_pop":319,
    "ks:ks_type":"HABITATION",
    "name:eng_x_preferred":[
        "Alagappagoundenpudur"
    ],
    "wof:name":"Alagappagoundenpudur",
    "wof:placetype":"locality",
    "wof:population":319
},
  "geometry": {"coordinates":[77.03810799999999,11.26555],"type":"Point"}
}