{
  "type": "Feature",
  "properties": {
    "iso:country":"IN",
    "ks:ks_name":"Kanari Gunth",
    "ks:ks_pop":445,
    "ks:ks_type":"VILLAGE",
    "name:eng_x_preferred":[
        "Kanari Gunth"
    ],
    "wof:name":"Kanari Gunth",
    "wof:placetype":"locality",
    "wof:population":445
},
  "geometry": {"coordinates":[79.94211300000001,29.483239],"type":"Point"}
}