{
  "type": "Feature",
  "properties": {
    "gn:admin1_code":"36",
    "gn:admin2_code":"189.0",
    "gn:asciiname":"Bankatia",
    "gn:country_code":"IN",
    "gn:dem":91,
    "gn:feature_class":"P",
    "gn:feature_code":"PPL",
    "gn:name":"Bankatia",
    "gn:population":0,
    "gn:timezone":"Asia/Kolkata",
    "iso:country":"IN",
    "wof:name":"Bankatia",
    "wof:placetype":"locality"
},
  "geometry": {"coordinates":[83.66545000000001,26.86508],"type":"Point"}
}