{
  "type": "Feature",
  "properties": {
    "gn:admin1_code":"38.0",
    "gn:admin2_code":"353.0",
    "gn:asciiname":"Radhakrishnapur",
    "gn:country_code":"IN",
    "gn:dem":74,
    "gn:feature_class":"P",
    "gn:feature_code":"PPL",
    "gn:name":"Radh\u0101krishn\u0101pur",
    "gn:population":0,
    "gn:timezone":"Asia/Kolkata",
    "iso:country":"IN",
    "ks:ks_alt_nam":"Radh\u0101krishn\u0101pur",
    "ks:ks_name":"Radhakrishnapur",
    "ks:ks_pop":252,
    "ks:ks_type":"VILLAGE",
    "name:eng_x_preferred":[
        "Radhakrishnapur"
    ],
    "name:eng_x_variant":[
        "Radh\u0101krishn\u0101pur"
    ],
    "wof:name":"Radhakrishnapur",
    "wof:placetype":"locality",
    "wof:population":252
},
  "geometry": {"coordinates":[87.665127,24.408127],"type":"Point"}
}