{
  "type": "Feature",
  "properties": {
    "gn:admin1_code":"16.0",
    "gn:admin2_code":"516.0",
    "gn:asciiname":"Vinchur",
    "gn:country_code":"IN",
    "gn:dem":628,
    "gn:feature_class":"P",
    "gn:feature_code":"PPL",
    "gn:name":"Vinch\u016br",
    "gn:population":0,
    "gn:timezone":"Asia/Kolkata",
    "iso:country":"IN",
    "name:cat_x_preferred":[
        "Vinchur"
    ],
    "wof:name":"Vinchur",
    "wof:placetype":"locality"
},
  "geometry": {"coordinates":[74.1069,20.64722],"type":"Point"}
}