{
  "type": "Feature",
  "properties": {
    "iso:country":"IN",
    "ks:ks_name":"Jagannathpur",
    "ks:ks_pop":444,
    "ks:ks_type":"VILLAGE",
    "name:eng_x_preferred":[
        "Jagannathpur"
    ],
    "wof:name":"Jagannathpur",
    "wof:placetype":"locality",
    "wof:population":444
},
  "geometry": {"coordinates":[86.686215,22.001625],"type":"Point"}
}