{
  "type": "Feature",
  "properties": {
    "iso:country":"IN",
    "ks:ks_name":"Mundideula",
    "ks:ks_pop":243,
    "ks:ks_type":"VILLAGE",
    "name:eng_x_preferred":[
        "Mundideula"
    ],
    "wof:name":"Mundideula",
    "wof:placetype":"locality",
    "wof:population":243
},
  "geometry": {"coordinates":[87.029135,21.517359],"type":"Point"}
}