{
  "type": "Feature",
  "properties": {
    "iso:country":"IN",
    "ks:ks_name":"Maichaha Para",
    "ks:ks_pop":280,
    "ks:ks_type":"HABITATION",
    "name:eng_x_preferred":[
        "Maichaha Para"
    ],
    "wof:name":"Maichaha Para",
    "wof:placetype":"locality",
    "wof:population":280
},
  "geometry": {"coordinates":[91.93803200000001,24.056055],"type":"Point"}
}