{
  "type": "Feature",
  "properties": {
    "iso:country":"IN",
    "ks:ks_name":"Keharli",
    "ks:ks_pop":787,
    "ks:ks_type":"HABITATION",
    "name:eng_x_preferred":[
        "Keharli"
    ],
    "wof:name":"Keharli",
    "wof:placetype":"locality",
    "wof:population":787
},
  "geometry": {"coordinates":[72.394722,28.082028],"type":"Point"}
}