{
  "type": "Feature",
  "properties": {
    "iso:country":"IN",
    "ks:ks_name":"Mangalapalli",
    "ks:ks_pop":42,
    "ks:ks_type":"HABITATION",
    "name:eng_x_preferred":[
        "Mangalapalli"
    ],
    "wof:name":"Mangalapalli",
    "wof:placetype":"locality",
    "wof:population":42
},
  "geometry": {"coordinates":[78.475944,14.068457],"type":"Point"}
}