{
  "type": "Feature",
  "properties": {
    "gn:admin1_code":"38",
    "gn:admin2_code":"346.0",
    "gn:asciiname":"Kamat",
    "gn:country_code":"IN",
    "gn:dem":184,
    "gn:feature_class":"P",
    "gn:feature_code":"PPL",
    "gn:name":"K\u0101mat",
    "gn:population":0,
    "gn:timezone":"Asia/Kolkata",
    "iso:country":"IN",
    "ks:ks_alt_nam":"K\u0101mat",
    "ks:ks_name":"Kamat",
    "ks:ks_pop":736,
    "ks:ks_type":"VILLAGE",
    "ks:ks_uagg_main":0,
    "name:eng_x_preferred":[
        "Kamat"
    ],
    "name:eng_x_variant":[
        "K\u0101mat"
    ],
    "wof:name":"Kamat",
    "wof:placetype":"neighbourhood",
    "wof:population":736
},
  "geometry": {"coordinates":[83.772909,24.310124],"type":"Point"}
}