{
  "type": "Feature",
  "properties": {
    "gn:admin1_code":"35.0",
    "gn:admin2_code":"445.0",
    "gn:asciiname":"Sendhokheri",
    "gn:country_code":"IN",
    "gn:dem":495,
    "gn:feature_class":"P",
    "gn:feature_code":"PPL",
    "gn:name":"Sendhokheri",
    "gn:population":0,
    "gn:timezone":"Asia/Kolkata",
    "iso:country":"IN",
    "wof:name":"Sendhokheri",
    "wof:placetype":"neighbourhood"
},
  "geometry": {"coordinates":[76.78537,23.04566],"type":"Point"}
}