{
  "type": "Feature",
  "properties": {
    "iso:country":"IN",
    "ks:ks_name":"Maktalpur",
    "ks:ks_pop":25,
    "ks:ks_type":"VILLAGE",
    "name:eng_x_preferred":[
        "Maktalpur"
    ],
    "wof:name":"Maktalpur",
    "wof:placetype":"locality",
    "wof:population":25
},
  "geometry": {"coordinates":[87.851507,25.689117],"type":"Point"}
}