{
  "type": "Feature",
  "properties": {
    "gn:admin1_code":"39.0",
    "gn:admin2_code":"63.0",
    "gn:asciiname":"Uprara",
    "gn:country_code":"IN",
    "gn:dem":1457,
    "gn:feature_class":"P",
    "gn:feature_code":"PPL",
    "gn:name":"Upr\u0101ra",
    "gn:population":0,
    "gn:timezone":"Asia/Kolkata",
    "iso:country":"IN",
    "ks:ks_alt_nam":"Upr\u0101ra",
    "ks:ks_name":"Uprara",
    "ks:ks_type":"VILLAGE",
    "name:eng_x_preferred":[
        "Uprara"
    ],
    "name:eng_x_variant":[
        "Upr\u0101ra"
    ],
    "wof:name":"Uprara",
    "wof:placetype":"locality"
},
  "geometry": {"coordinates":[79.964232,29.803058],"type":"Point"}
}