{
  "type": "Feature",
  "properties": {
    "gn:admin1_code":"11",
    "gn:admin2_code":"23.0",
    "gn:asciiname":"Pagot",
    "gn:country_code":"IN",
    "gn:dem":1452,
    "gn:feature_class":"P",
    "gn:feature_code":"PPL",
    "gn:name":"Pagot",
    "gn:population":0,
    "gn:timezone":"Asia/Kolkata",
    "iso:country":"IN",
    "wof:name":"Pagot",
    "wof:placetype":"locality"
},
  "geometry": {"coordinates":[76.04904999999999,32.39119],"type":"Point"}
}