{
  "type": "Feature",
  "properties": {
    "iso:country":"IN",
    "ks:ks_name":"Hatimuriagaon",
    "ks:ks_pop":1076,
    "ks:ks_type":"VILLAGE",
    "ks:ks_uagg_main":0,
    "name:eng_x_preferred":[
        "Hatimuriagaon"
    ],
    "wof:name":"Hatimuriagaon",
    "wof:placetype":"locality",
    "wof:population":1076
},
  "geometry": {"coordinates":[94.66725099999999,26.978763],"type":"Point"}
}