{
  "type": "Feature",
  "properties": {
    "gn:admin1_code":"25.0",
    "gn:admin2_code":"630.0",
    "gn:asciiname":"Nayakkanur",
    "gn:country_code":"IN",
    "gn:dem":595,
    "gn:feature_class":"P",
    "gn:feature_code":"PPL",
    "gn:name":"N\u0101yakkan\u016br",
    "gn:population":0,
    "gn:timezone":"Asia/Kolkata",
    "iso:country":"IN",
    "wof:name":"Nayakkanur",
    "wof:placetype":"locality"
},
  "geometry": {"coordinates":[78.03725,12.42347],"type":"Point"}
}