{
  "type": "Feature",
  "properties": {
    "gn:admin1_code":"37",
    "gn:admin2_code":"406.0",
    "gn:asciiname":"Bicharpur",
    "gn:country_code":"IN",
    "gn:dem":285,
    "gn:feature_class":"P",
    "gn:feature_code":"PPL",
    "gn:name":"Bich\u0101rpur",
    "gn:population":0,
    "gn:timezone":"Asia/Kolkata",
    "iso:country":"IN",
    "ks:ks_alt_nam":"VICHARPUR",
    "ks:ks_name":"Vicharpur",
    "ks:ks_pop":562,
    "ks:ks_type":"HABITATION",
    "ks:ks_uagg_main":0,
    "name:eng_x_preferred":[
        "Vicharpur"
    ],
    "wof:name":"Vicharpur",
    "wof:placetype":"neighbourhood",
    "wof:population":562
},
  "geometry": {"coordinates":[81.943214,22.186289],"type":"Point"}
}