{
  "type": "Feature",
  "properties": {
    "gn:admin1_code":"19.0",
    "gn:admin2_code":"568.0",
    "gn:asciiname":"Makkimane",
    "gn:country_code":"IN",
    "gn:dem":602,
    "gn:feature_class":"P",
    "gn:feature_code":"PPL",
    "gn:name":"Makkiman\u0113",
    "gn:population":0,
    "gn:timezone":"Asia/Kolkata",
    "iso:country":"IN",
    "wof:name":"Makkimane",
    "wof:placetype":"locality"
},
  "geometry": {"coordinates":[74.83608000000002,13.93898],"type":"Point"}
}