{
  "type": "Feature",
  "properties": {
    "gn:admin1_code":"2",
    "gn:admin2_code":"544.0",
    "gn:asciiname":"Balrevulu",
    "gn:country_code":"IN",
    "gn:dem":585,
    "gn:feature_class":"P",
    "gn:feature_code":"PPL",
    "gn:name":"Balrevulu",
    "gn:population":0,
    "gn:timezone":"Asia/Kolkata",
    "iso:country":"IN",
    "ks:ks_name":"Balarevulu",
    "ks:ks_pop":255,
    "ks:ks_type":"VILLAGE",
    "name:eng_x_preferred":[
        "Balarevulu"
    ],
    "name:eng_x_variant":[
        "Balrevulu"
    ],
    "wof:name":"Balarevulu",
    "wof:placetype":"locality",
    "wof:population":255
},
  "geometry": {"coordinates":[82.195009,17.716864],"type":"Point"}
}