{
  "type": "Feature",
  "properties": {
    "gn:admin1_code":"35.0",
    "gn:admin2_code":"447.0",
    "gn:asciiname":"Pipariya",
    "gn:country_code":"IN",
    "gn:dem":764,
    "gn:feature_class":"P",
    "gn:feature_code":"PPL",
    "gn:name":"Pipariya",
    "gn:population":0,
    "gn:timezone":"Asia/Kolkata",
    "iso:country":"IN",
    "name:ceb_x_preferred":[
        "Pipariya"
    ],
    "name:hin_x_preferred":[
        "\u092a\u093f\u092a\u0930\u093f\u092f\u093e"
    ],
    "name:ita_x_preferred":[
        "Pipariya"
    ],
    "name:pol_x_preferred":[
        "Pipariya"
    ],
    "wof:name":"Pipariya",
    "wof:placetype":"locality"
},
  "geometry": {"coordinates":[78.37536,21.79489],"type":"Point"}
}