{
  "type": "Feature",
  "properties": {
    "iso:country":"IN",
    "ks:ks_alt_nam":"CHAUGALI PUR",
    "ks:ks_name":"Chaugali Pur",
    "ks:ks_pop":95,
    "ks:ks_type":"HABITATION",
    "ks:ks_uagg_main":0,
    "name:eng_x_preferred":[
        "Chaugali Pur"
    ],
    "wof:name":"Chaugali Pur",
    "wof:placetype":"neighbourhood",
    "wof:population":95
},
  "geometry": {"coordinates":[81.751738,26.50484],"type":"Point"}
}