{
  "type": "Feature",
  "properties": {
    "iso:country":"IN",
    "ks:ks_name":"Hesla A",
    "ks:ks_pop":589,
    "ks:ks_type":"HABITATION",
    "name:eng_x_preferred":[
        "Hesla A"
    ],
    "wof:name":"Hesla A",
    "wof:placetype":"locality",
    "wof:population":589
},
  "geometry": {"coordinates":[84.455443,23.742449],"type":"Point"}
}