{
  "type": "Feature",
  "properties": {
    "iso:country":"IN",
    "ks:ks_name":"Katavadwadi",
    "ks:ks_pop":174,
    "ks:ks_type":"HABITATION",
    "name:eng_x_preferred":[
        "Katavadwadi"
    ],
    "wof:name":"Katavadwadi",
    "wof:placetype":"locality",
    "wof:population":174
},
  "geometry": {"coordinates":[73.77423,15.760509],"type":"Point"}
}