{
  "type": "Feature",
  "properties": {
    "gn:admin1_code":"35.0",
    "gn:admin2_code":"425",
    "gn:asciiname":"Jaitpur",
    "gn:country_code":"IN",
    "gn:dem":316,
    "gn:feature_class":"P",
    "gn:feature_code":"PPL",
    "gn:name":"Jaitpur",
    "gn:population":0,
    "gn:timezone":"Asia/Kolkata",
    "iso:country":"IN",
    "name:eng_x_preferred":[
        "Jaitpur"
    ],
    "name:fra_x_preferred":[
        "Jaitpur"
    ],
    "name:urd_x_preferred":[
        "\u062c\u06cc\u062a\u067e\u0648\u0631"
    ],
    "wof:name":"Jaitpur",
    "wof:placetype":"locality"
},
  "geometry": {"coordinates":[79.85755999999998,24.37651],"type":"Point"}
}