{
  "type": "Feature",
  "properties": {
    "iso:country":"IN",
    "ks:ks_name":"Bilaruwa Tola",
    "ks:ks_pop":100,
    "ks:ks_type":"HABITATION",
    "name:eng_x_preferred":[
        "Bilaruwa Tola"
    ],
    "wof:name":"Bilaruwa Tola",
    "wof:placetype":"locality",
    "wof:population":100
},
  "geometry": {"coordinates":[83.298368,24.237708],"type":"Point"}
}