{
  "type": "Feature",
  "properties": {
    "iso:country":"IN",
    "ks:ks_name":"Sindhi",
    "ks:ks_pop":89,
    "ks:ks_type":"VILLAGE",
    "name:eng_x_preferred":[
        "Sindhi"
    ],
    "wof:name":"Sindhi",
    "wof:placetype":"locality",
    "wof:population":89
},
  "geometry": {"coordinates":[83.726855,20.295789],"type":"Point"}
}