{
  "type": "Feature",
  "properties": {
    "iso:country":"IN",
    "ks:ks_name":"Parupuram",
    "ks:ks_pop":26,
    "ks:ks_type":"HABITATION",
    "name:eng_x_preferred":[
        "Parupuram"
    ],
    "wof:name":"Parupuram",
    "wof:placetype":"locality",
    "wof:population":26
},
  "geometry": {"coordinates":[82.77795399999999,17.983098],"type":"Point"}
}