{
  "type": "Feature",
  "properties": {
    "gn:admin1_code":"38",
    "gn:admin2_code":"362.0",
    "gn:asciiname":"Sikaripara",
    "gn:country_code":"IN",
    "gn:dem":145,
    "gn:feature_class":"P",
    "gn:feature_code":"PPL",
    "gn:name":"Sik\u0101rip\u0101ra",
    "gn:population":0,
    "gn:timezone":"Asia/Kolkata",
    "iso:country":"IN",
    "wof:name":"Sikaripara",
    "wof:placetype":"locality"
},
  "geometry": {"coordinates":[87.47413,24.23855],"type":"Point"}
}