{
  "type": "Feature",
  "properties": {
    "iso:country":"IN",
    "ks:ks_name":"Vijaya Teacherpadi Road",
    "ks:ks_pop":666,
    "ks:ks_type":"HABITATION",
    "name:eng_x_preferred":[
        "Vijaya Teacherpadi Road"
    ],
    "wof:name":"Vijaya Teacherpadi Road",
    "wof:placetype":"locality",
    "wof:population":666
},
  "geometry": {"coordinates":[76.211523,10.732428],"type":"Point"}
}