{
  "type": "Feature",
  "properties": {
    "iso:country":"IN",
    "ks:ks_alt_nam":"Master para -W",
    "ks:ks_name":"Master Para -w",
    "ks:ks_pop":887,
    "ks:ks_type":"HABITATION",
    "name:eng_x_preferred":[
        "Master Para -w"
    ],
    "wof:name":"Master Para -w",
    "wof:placetype":"locality",
    "wof:population":887
},
  "geometry": {"coordinates":[91.40634,23.301092],"type":"Point"}
}