{
  "type": "Feature",
  "properties": {
    "iso:country":"IN",
    "ks:ks_name":"Bharwaliya Urf Tikuiya",
    "ks:ks_pop":480,
    "ks:ks_type":"VILLAGE",
    "ks:ks_uagg_main":0,
    "name:eng_x_preferred":[
        "Bharwaliya Urf Tikuiya"
    ],
    "wof:name":"Bharwaliya Urf Tikuiya",
    "wof:placetype":"neighbourhood",
    "wof:population":480
},
  "geometry": {"coordinates":[82.83962699999999,26.603366],"type":"Point"}
}