{
  "type": "Feature",
  "properties": {
    "iso:country":"IN",
    "ks:ks_name":"Khurshedpur",
    "ks:ks_pop":5,
    "ks:ks_type":"HABITATION",
    "name:eng_x_preferred":[
        "Khurshedpur"
    ],
    "wof:name":"Khurshedpur",
    "wof:placetype":"locality",
    "wof:population":5
},
  "geometry": {"coordinates":[81.63020400000001,25.000874],"type":"Point"}
}