{
  "type": "Feature",
  "properties": {
    "gn:admin1_code":"19.0",
    "gn:admin2_code":"573.0",
    "gn:asciiname":"Dasarahalli",
    "gn:country_code":"IN",
    "gn:dem":922,
    "gn:feature_class":"P",
    "gn:feature_code":"PPL",
    "gn:name":"D\u0101sarahalli",
    "gn:population":0,
    "gn:timezone":"Asia/Kolkata",
    "iso:country":"IN",
    "ks:ks_alt_nam":"Dasara hally",
    "ks:ks_name":"Dasara Hally",
    "ks:ks_pop":192,
    "ks:ks_type":"HABITATION",
    "name:ara_x_preferred":[
        "\u062f\u0633\u0627\u0631\u0627\u0647\u0627\u0644\u064a"
    ],
    "name:ben_bn_x_preferred":[
        "\u09a6\u09be\u09b8\u09be\u09b0\u09be\u09b9\u09be\u09b2\u09cd\u09b2\u09bf"
    ],
    "name:ben_in_x_preferred":[
        "\u09a6\u09be\u09b8\u09be\u09b0\u09be\u09b9\u09be\u09b2\u09cd\u09b2\u09bf"
    ],
    "name:ben_x_preferred":[
        "\u09a6\u09b8\u09b0\u09be\u09b9\u09be\u09b2\u09cd\u09b2\u09bf"
    ],
    "name:bpy_x_preferred":[
        "\u09a6\u09b8\u09b0\u09be\u09b9\u09be\u09b2\u09cd\u09b2\u09bf"
    ],
    "name:ceb_x_preferred":[
        "Dasarahalli"
    ],
    "name:eng_x_preferred":[
        "Dasara Hally"
    ],
    "name:eng_x_variant":[
        "Dasarahalli"
    ],
    "name:fas_x_preferred":[
        "\u062f\u0627\u0633\u0627\u0631\u0627\u0647\u0627\u0644\u06cc"
    ],
    "name:guj_x_preferred":[
        "\u0aa6\u0ab6\u0ab0\u0ab9\u0ab2\u0acd\u0ab2\u0ac0"
    ],
    "name:hin_x_preferred":[
        "\u0926\u0938\u0930\u0939\u0932\u094d\u0932\u0940"
    ],
    "name:ita_x_preferred":[
        "Dasarahalli"
    ],
    "name:kan_x_preferred":[
        "\u0ca6\u0cbe\u0cb8\u0cb0\u0cb9\u0cb3\u0ccd\u0cb3\u0cbf"
    ],
    "name:mal_x_preferred":[
        "\u0d26\u0d38\u0d30\u0d39\u0d33\u0d4d\u0d33\u0d3f"
    ],
    "name:mar_x_preferred":[
        "\u0926\u0938\u0930\u093e\u0939\u0932\u094d\u0932\u0940"
    ],
    "name:mlg_x_preferred":[
        "Dasarahalli"
    ],
    "name:msa_x_preferred":[
        "Dasarahalli"
    ],
    "name:new_x_preferred":[
        "\u0926\u0938\u0930\u0939\u0932\u094d\u0932\u0940"
    ],
    "name:nld_x_preferred":[
        "Dasarahalli"
    ],
    "name:nor_x_preferred":[
        "Dasarahalli"
    ],
    "name:pan_x_preferred":[
        "\u0a26\u0a38\u0a30\u0a39\u0a71\u0a32\u0a40"
    ],
    "name:por_x_preferred":[
        "Dasarahalli"
    ],
    "name:spa_x_preferred":[
        "Dasarahalli"
    ],
    "name:swe_x_preferred":[
        "Dasarahalli"
    ],
    "name:tam_x_preferred":[
        "\u0ba4\u0bbe\u0b9a\u0bb0\u0bb9\u0bb3\u0bcd\u0bb3\u0bbf"
    ],
    "name:tam_x_variant":[
        "\u0ba4\u0b9a\u0bb0\u0bbe\u0bb3\u0bbf"
    ],
    "name:tel_x_preferred":[
        "\u0c26\u0c3e\u0c38\u0c30\u0c39\u0c33\u0c4d\u0c33\u0c3f"
    ],
    "name:urd_x_preferred":[
        "\u062f\u0633\u0627\u0631\u0627 \u06c1\u0644\u0651\u06cc"
    ],
    "name:vie_x_preferred":[
        "Dasarahalli"
    ],
    "name:zho_x_preferred":[
        "\u8fbe\u8428\u62c9\u54c8\u5c14\u5229"
    ],
    "wof:name":"Dasara Hally",
    "wof:placetype":"locality",
    "wof:population":192
},
  "geometry": {"coordinates":[76.625483,12.832965],"type":"Point"}
}