{
  "type": "Feature",
  "properties": {
    "iso:country":"IN",
    "ks:ks_name":"Laman Wasti",
    "ks:ks_pop":285,
    "ks:ks_type":"HABITATION",
    "name:eng_x_preferred":[
        "Laman Wasti"
    ],
    "wof:name":"Laman Wasti",
    "wof:placetype":"locality",
    "wof:population":285
},
  "geometry": {"coordinates":[74.824049,18.114076],"type":"Point"}
}