{
  "type": "Feature",
  "properties": {
    "gn:admin1_code":"2.0",
    "gn:admin2_code":"553.0",
    "gn:asciiname":"Ayyampalle",
    "gn:country_code":"IN",
    "gn:dem":544,
    "gn:feature_class":"P",
    "gn:feature_code":"PPL",
    "gn:name":"Ayyampalle",
    "gn:population":0,
    "gn:timezone":"Asia/Kolkata",
    "iso:country":"IN",
    "wof:name":"Ayyampalle",
    "wof:placetype":"locality"
},
  "geometry": {"coordinates":[77.31028000000001,14.32398],"type":"Point"}
}