{
  "type": "Feature",
  "properties": {
    "gn:admin1_code":"11.0",
    "gn:admin2_code":"34.0",
    "gn:asciiname":"Hikotu Dogri",
    "gn:country_code":"IN",
    "gn:dem":2967,
    "gn:feature_class":"P",
    "gn:feature_code":"PPL",
    "gn:name":"Hikotu Dogri",
    "gn:population":0,
    "gn:timezone":"Asia/Kolkata",
    "iso:country":"IN",
    "wof:name":"Hikotu Dogri",
    "wof:placetype":"locality"
},
  "geometry": {"coordinates":[78.33145,31.4042],"type":"Point"}
}