{
  "type": "Feature",
  "properties": {
    "gn:admin1_code":"36",
    "gn:admin2_code":"165.0",
    "gn:asciiname":"Kamina",
    "gn:country_code":"IN",
    "gn:dem":160,
    "gn:feature_class":"P",
    "gn:feature_code":"PPL",
    "gn:name":"Kam\u012bna",
    "gn:population":0,
    "gn:timezone":"Asia/Kolkata",
    "iso:country":"IN",
    "name:azb_x_preferred":[
        "\u06a9\u0627\u0645\u06cc\u0646\u0627"
    ],
    "name:ceb_x_preferred":[
        "Kamina"
    ],
    "name:deu_x_preferred":[
        "Kamina"
    ],
    "name:epo_x_preferred":[
        "Kamina"
    ],
    "name:est_x_preferred":[
        "Kamina"
    ],
    "name:fas_x_preferred":[
        "\u06a9\u0627\u0645\u06cc\u0646\u0627"
    ],
    "name:fra_x_preferred":[
        "Kamina"
    ],
    "name:heb_x_preferred":[
        "\u05e7\u05e8\u05de\u05d9\u05e0\u05d4"
    ],
    "name:hrv_x_preferred":[
        "Kamina"
    ],
    "name:hun_x_preferred":[
        "Kamina"
    ],
    "name:ita_x_preferred":[
        "Kamina"
    ],
    "name:jpn_x_preferred":[
        "\u30ab\u30df\u30ca"
    ],
    "name:kat_x_preferred":[
        "\u10d9\u10d0\u10db\u10d8\u10dc\u10d0"
    ],
    "name:kon_x_preferred":[
        "Kamina"
    ],
    "name:kor_x_preferred":[
        "\uce74\ubbf8\ub098"
    ],
    "name:nld_x_preferred":[
        "Kamina"
    ],
    "name:pol_x_preferred":[
        "Kamina"
    ],
    "name:ron_x_preferred":[
        "Kamina"
    ],
    "name:rus_x_preferred":[
        "\u041a\u0430\u043c\u0438\u043d\u0430"
    ],
    "name:swa_x_preferred":[
        "Kamina"
    ],
    "name:swe_x_preferred":[
        "Kamina"
    ],
    "name:tgl_x_preferred":[
        "Kamina"
    ],
    "name:ukr_x_preferred":[
        "\u041a\u0430\u043c\u0456\u043d\u0430"
    ],
    "name:und_x_variant":[
        "Kam\u012bna",
        "Kaushalpur"
    ],
    "name:war_x_preferred":[
        "Kamina"
    ],
    "name:xmf_x_preferred":[
        "\u10d9\u10d0\u10db\u10d8\u10dc\u10d0"
    ],
    "name:zho_x_preferred":[
        "\u5361\u7c73\u7d0d"
    ],
    "wof:name":"Kamina",
    "wof:placetype":"neighbourhood"
},
  "geometry": {"coordinates":[79.12468,25.93828],"type":"Point"}
}