{
  "type": "Feature",
  "properties": {
    "iso:country":"IN",
    "ks:ks_name":"Hanumanwadi",
    "ks:ks_pop":128,
    "ks:ks_type":"HABITATION",
    "name:eng_x_preferred":[
        "Hanumanwadi"
    ],
    "wof:name":"Hanumanwadi",
    "wof:placetype":"locality",
    "wof:population":128
},
  "geometry": {"coordinates":[73.368465,16.943176],"type":"Point"}
}