{
  "type": "Feature",
  "properties": {
    "iso:country":"IN",
    "ks:ks_name":"Kapilipadar",
    "ks:ks_pop":79,
    "ks:ks_type":"HABITATION",
    "name:eng_x_preferred":[
        "Kapilipadar"
    ],
    "wof:name":"Kapilipadar",
    "wof:placetype":"locality",
    "wof:population":79
},
  "geometry": {"coordinates":[84.160183,19.254667],"type":"Point"}
}