{
  "type": "Feature",
  "properties": {
    "gn:admin1_code":"38.0",
    "gn:admin2_code":"347.0",
    "gn:asciiname":"Dharpur",
    "gn:country_code":"IN",
    "gn:dem":408,
    "gn:feature_class":"P",
    "gn:feature_code":"PPL",
    "gn:name":"Dh\u0101rpur",
    "gn:population":0,
    "gn:timezone":"Asia/Kolkata",
    "iso:country":"IN",
    "ks:ks_alt_nam":"Dh\u0101rpur",
    "ks:ks_name":"Dharpur",
    "ks:ks_pop":169,
    "ks:ks_type":"VILLAGE",
    "ks:ks_uagg_main":0,
    "name:eng_x_preferred":[
        "Dharpur"
    ],
    "name:eng_x_variant":[
        "Dh\u0101rpur"
    ],
    "wof:name":"Dharpur",
    "wof:placetype":"neighbourhood",
    "wof:population":169
},
  "geometry": {"coordinates":[85.183167,24.321612],"type":"Point"}
}