{
  "type": "Feature",
  "properties": {
    "iso:country":"IN",
    "ks:ks_name":"Dokphodpada",
    "ks:ks_pop":79,
    "ks:ks_type":"HABITATION",
    "name:eng_x_preferred":[
        "Dokphodpada"
    ],
    "wof:name":"Dokphodpada",
    "wof:placetype":"locality",
    "wof:population":79
},
  "geometry": {"coordinates":[73.005425,19.667357],"type":"Point"}
}