{
  "type": "Feature",
  "properties": {
    "iso:country":"IN",
    "ks:ks_name":"Fattepur",
    "ks:ks_pop":469,
    "ks:ks_type":"VILLAGE",
    "name:eng_x_preferred":[
        "Fattepur"
    ],
    "wof:name":"Fattepur",
    "wof:placetype":"locality",
    "wof:population":469
},
  "geometry": {"coordinates":[82.76964099999999,22.823709],"type":"Point"}
}