{
  "type": "Feature",
  "properties": {
    "iso:country":"IN",
    "ks:ks_alt_nam":"Mahra toli",
    "ks:ks_name":"Mahra Toli",
    "ks:ks_pop":146,
    "ks:ks_type":"HABITATION",
    "name:eng_x_preferred":[
        "Mahra Toli"
    ],
    "wof:name":"Mahra Toli",
    "wof:placetype":"locality",
    "wof:population":146
},
  "geometry": {"coordinates":[85.23062899999999,22.94958],"type":"Point"}
}