{
  "type": "Feature",
  "properties": {
    "gn:admin1_code":"36",
    "gn:asciiname":"Patharra",
    "gn:country_code":"IN",
    "gn:dem":202,
    "gn:feature_class":"P",
    "gn:feature_code":"PPL",
    "gn:name":"Patharra",
    "gn:population":0,
    "gn:timezone":"Asia/Kolkata",
    "iso:country":"IN",
    "ks:ks_name":"Patharra",
    "ks:ks_pop":72,
    "ks:ks_type":"VILLAGE",
    "name:eng_x_preferred":[
        "Patharra"
    ],
    "wof:name":"Patharra",
    "wof:placetype":"locality",
    "wof:population":72
},
  "geometry": {"coordinates":[77.51320800000001,26.83175],"type":"Point"}
}