{
  "type": "Feature",
  "properties": {
    "iso:country":"IN",
    "ks:ks_name":"Mulikwasti",
    "ks:ks_pop":155,
    "ks:ks_type":"HABITATION",
    "name:eng_x_preferred":[
        "Mulikwasti"
    ],
    "wof:name":"Mulikwasti",
    "wof:placetype":"locality",
    "wof:population":155
},
  "geometry": {"coordinates":[74.61038600000001,17.731226],"type":"Point"}
}