{
  "type": "Feature",
  "properties": {
    "iso:country":"IN",
    "ks:ks_name":"Turi Tola",
    "ks:ks_pop":291,
    "ks:ks_type":"HABITATION",
    "name:eng_x_preferred":[
        "Turi Tola"
    ],
    "wof:name":"Turi Tola",
    "wof:placetype":"locality",
    "wof:population":291
},
  "geometry": {"coordinates":[85.77012999999999,23.626108],"type":"Point"}
}