{
  "type": "Feature",
  "properties": {
    "iso:country":"IN",
    "ks:ks_name":"Majha Dalpatpur",
    "ks:ks_pop":330,
    "ks:ks_type":"VILLAGE",
    "name:eng_x_preferred":[
        "Majha Dalpatpur"
    ],
    "wof:name":"Majha Dalpatpur",
    "wof:placetype":"locality",
    "wof:population":330
},
  "geometry": {"coordinates":[82.37877400000001,26.681251],"type":"Point"}
}