{
  "type": "Feature",
  "properties": {
    "iso:country":"IN",
    "ks:ks_name":"Chhatra Baterbari",
    "ks:ks_pop":1455,
    "ks:ks_type":"HABITATION",
    "name:eng_x_preferred":[
        "Chhatra Baterbari"
    ],
    "wof:name":"Chhatra Baterbari",
    "wof:placetype":"locality",
    "wof:population":1455
},
  "geometry": {"coordinates":[89.35262299999999,26.231961],"type":"Point"}
}