{
  "type": "Feature",
  "properties": {
    "iso:country":"IN",
    "ks:ks_alt_nam":"Il\u0101ich\u012bpur",
    "ks:ks_name":"Ilaichipur",
    "ks:ks_pop":282,
    "ks:ks_type":"VILLAGE",
    "ks:ks_uagg_main":0,
    "name:eng_x_preferred":[
        "Ilaichipur"
    ],
    "name:eng_x_variant":[
        "Il\u0101ich\u012bpur"
    ],
    "wof:name":"Ilaichipur",
    "wof:placetype":"neighbourhood",
    "wof:population":282
},
  "geometry": {"coordinates":[77.251496,28.762212],"type":"Point"}
}