{
  "type": "Feature",
  "properties": {
    "gn:admin1_code":"36.0",
    "gn:admin2_code":"183.0",
    "gn:asciiname":"Renuwan",
    "gn:country_code":"IN",
    "gn:dem":96,
    "gn:feature_class":"P",
    "gn:feature_code":"PPL",
    "gn:name":"Renuw\u0101n",
    "gn:population":0,
    "gn:timezone":"Asia/Kolkata",
    "iso:country":"IN",
    "ks:ks_alt_nam":"Renuw\u0101n",
    "ks:ks_name":"Renuwan",
    "ks:ks_type":"VILLAGE",
    "ks:ks_uagg_main":0,
    "name:eng_x_preferred":[
        "Renuwan"
    ],
    "name:eng_x_variant":[
        "Renuw\u0101n"
    ],
    "wof:name":"Renuwan",
    "wof:placetype":"neighbourhood"
},
  "geometry": {"coordinates":[82.472728,27.108144],"type":"Point"}
}