{
  "type": "Feature",
  "properties": {
    "gn:admin1_code":"35",
    "gn:admin2_code":"429.0",
    "gn:asciiname":"Kushli",
    "gn:country_code":"IN",
    "gn:dem":330,
    "gn:feature_class":"P",
    "gn:feature_code":"PPL",
    "gn:name":"Kushli",
    "gn:population":0,
    "gn:timezone":"Asia/Kolkata",
    "iso:country":"IN",
    "wof:name":"Kushli",
    "wof:placetype":"locality"
},
  "geometry": {"coordinates":[80.79029,24.32885],"type":"Point"}
}