{
  "type": "Feature",
  "properties": {
    "iso:country":"IN",
    "ks:ks_name":"Ramoshi Vasti",
    "ks:ks_pop":235,
    "ks:ks_type":"HABITATION",
    "ks:ks_uagg_main":0,
    "name:eng_x_preferred":[
        "Ramoshi Vasti"
    ],
    "wof:name":"Ramoshi Vasti",
    "wof:placetype":"neighbourhood",
    "wof:population":235
},
  "geometry": {"coordinates":[73.76340399999999,18.352996],"type":"Point"}
}