{
  "type": "Feature",
  "properties": {
    "iso:country":"IN",
    "name:bpy_x_preferred":[
        "\u09b6\u09cd\u09b0\u09c0\u09b2\u09bf\u0999\u09cd\u0997\u09ae\u09aa\u09be\u09b2\u09cd\u09b2\u09c7"
    ],
    "name:bul_x_preferred":[
        "\u0421\u0435\u0440\u0438\u043b\u0438\u043d\u0433\u0430\u043c\u043f\u0430\u043b\u0435"
    ],
    "name:ceb_x_preferred":[
        "Serilingampalle"
    ],
    "name:eng_x_preferred":[
        "Serilingampally"
    ],
    "name:ita_x_preferred":[
        "Serilingampalle"
    ],
    "name:msa_x_preferred":[
        "Serilingampalle"
    ],
    "name:nld_x_preferred":[
        "Serilingampally"
    ],
    "name:por_x_preferred":[
        "Serilingampalle"
    ],
    "name:swe_x_preferred":[
        "Serilingampalle"
    ],
    "name:tel_x_preferred":[
        "\u0c36\u0c47\u0c30\u0c3f\u0c32\u0c3f\u0c02\u0c17\u0c02\u0c2a\u0c32\u0c4d\u0c32\u0c3f"
    ],
    "name:urd_x_preferred":[
        "\u0633\u06cc\u0631\u06cc\u0644\u0646\u06af\u06af\u0627\u0645 \u067e\u0627\u0644\u06cc"
    ],
    "name:vie_x_preferred":[
        "Serilingampalle"
    ],
    "name:zho_x_preferred":[
        "\u585e\u91cc\u6797\u683c\u963f\u59c6\u5e15\u5c14\u83b1"
    ],
    "qs:gn_adm0_cc":"IN",
    "qs:gn_local":1269843,
    "qs:local_max":1198,
    "qs:local_sum":10545,
    "qs:localhoods":56,
    "qs:name":"Serilingampally",
    "qs:name_adm0":"India",
    "qs:name_adm1":"Andhra Pradesh",
    "qs:name_adm2":"Rangareddi",
    "qs:name_local":"Hyderabad",
    "qs:photo_max":100,
    "qs:photo_sum":462,
    "qs:placetype":"Suburb",
    "qs:quad_count":30,
    "qs:woe_adm0":23424848,
    "qs:woe_adm1":2345740,
    "qs:woe_adm2":12586344,
    "qs:woe_lau":0,
    "qs:woe_local":2295414,
    "qs:woe_ver":"7.10.0",
    "wd:wordcount":256,
    "wof:lang":[
        "eng"
    ],
    "wof:name":"Serilingampally",
    "wof:placetype":"neighbourhood"
},
  "geometry": {"coordinates":[78.330063,17.45587],"type":"Point"}
}