{
  "type": "Feature",
  "properties": {
    "gn:admin1_code":"37",
    "gn:admin2_code":"416.0",
    "gn:asciiname":"Penta",
    "gn:country_code":"IN",
    "gn:dem":122,
    "gn:feature_class":"P",
    "gn:feature_code":"PPL",
    "gn:name":"Penta",
    "gn:population":0,
    "gn:timezone":"Asia/Kolkata",
    "iso:country":"IN",
    "name:urd_x_preferred":[
        "\u067e\u06cc\u0646\u0679\u0627"
    ],
    "wof:name":"Penta",
    "wof:placetype":"locality"
},
  "geometry": {"coordinates":[81.48625,18.12457],"type":"Point"}
}