{
  "type": "Feature",
  "properties": {
    "iso:country":"IN",
    "ks:ks_name":"Banribera",
    "ks:ks_pop":0,
    "ks:ks_type":"VILLAGE",
    "name:eng_x_preferred":[
        "Banribera"
    ],
    "wof:name":"Banribera",
    "wof:placetype":"locality",
    "wof:population":0
},
  "geometry": {"coordinates":[85.578699,22.987963],"type":"Point"}
}