{
  "type": "Feature",
  "properties": {
    "iso:country":"IN",
    "ks:ks_name":"Singapada",
    "ks:ks_pop":103,
    "ks:ks_type":"VILLAGE",
    "name:eng_x_preferred":[
        "Singapada"
    ],
    "wof:name":"Singapada",
    "wof:placetype":"locality",
    "wof:population":103
},
  "geometry": {"coordinates":[84.15181800000001,20.46744],"type":"Point"}
}