{
  "type": "Feature",
  "properties": {
    "iso:country":"IN",
    "ks:ks_alt_nam":"nagamma badavanne",
    "ks:ks_name":"Nagamma Badavanne",
    "ks:ks_pop":583,
    "ks:ks_type":"HABITATION",
    "name:eng_x_preferred":[
        "Nagamma Badavanne"
    ],
    "wof:name":"Nagamma Badavanne",
    "wof:placetype":"locality",
    "wof:population":583
},
  "geometry": {"coordinates":[75.88200000000001,14.433],"type":"Point"}
}