{
  "type": "Feature",
  "properties": {
    "iso:country":"IN",
    "ks:ks_name":"Khandak Akhada",
    "ks:ks_pop":344,
    "ks:ks_type":"HABITATION",
    "name:eng_x_preferred":[
        "Khandak Akhada"
    ],
    "wof:name":"Khandak Akhada",
    "wof:placetype":"locality",
    "wof:population":344
},
  "geometry": {"coordinates":[74.168375,19.578652],"type":"Point"}
}