{
  "type": "Feature",
  "properties": {
    "iso:country":"IN",
    "ks:ks_name":"Vilayathur",
    "ks:ks_pop":90,
    "ks:ks_type":"HABITATION",
    "name:eng_x_preferred":[
        "Vilayathur"
    ],
    "wof:name":"Vilayathur",
    "wof:placetype":"locality",
    "wof:population":90
},
  "geometry": {"coordinates":[75.694343,11.536372],"type":"Point"}
}