{
  "type": "Feature",
  "properties": {
    "iso:country":"IN",
    "ks:ks_name":"Khetaripara",
    "ks:ks_pop":315,
    "ks:ks_type":"HABITATION",
    "name:eng_x_preferred":[
        "Khetaripara"
    ],
    "wof:name":"Khetaripara",
    "wof:placetype":"locality",
    "wof:population":315
},
  "geometry": {"coordinates":[83.56322400000001,22.534862],"type":"Point"}
}