{
  "type": "Feature",
  "properties": {
    "iso:country":"IN",
    "ks:ks_name":"Purba Para",
    "ks:ks_pop":969,
    "ks:ks_type":"HABITATION",
    "name:eng_x_preferred":[
        "Purba Para"
    ],
    "wof:name":"Purba Para",
    "wof:placetype":"locality",
    "wof:population":969
},
  "geometry": {"coordinates":[88.683555,22.169876],"type":"Point"}
}