{
  "type": "Feature",
  "properties": {
    "gn:admin1_code":"24.0",
    "gn:admin2_code":"101",
    "gn:asciiname":"Bhairu Payan",
    "gn:country_code":"IN",
    "gn:dem":180,
    "gn:feature_class":"P",
    "gn:feature_code":"PPL",
    "gn:name":"Bhairu Pay\u0101n",
    "gn:population":0,
    "gn:timezone":"Asia/Kolkata",
    "iso:country":"IN",
    "name:und_x_variant":[
        "Bhairu Pay\u0101n",
        "Bharru"
    ],
    "wof:name":"Bhairu Payan",
    "wof:placetype":"locality"
},
  "geometry": {"coordinates":[73.19955,28.19925],"type":"Point"}
}