{
  "type": "Feature",
  "properties": {
    "iso:country":"IN",
    "ks:ks_alt_nam":"golwada",
    "ks:ks_name":"Golwada",
    "ks:ks_pop":53,
    "ks:ks_type":"HABITATION",
    "name:eng_x_preferred":[
        "Golwada"
    ],
    "wof:name":"Golwada",
    "wof:placetype":"locality",
    "wof:population":53
},
  "geometry": {"coordinates":[73.968861,15.696167],"type":"Point"}
}