{
  "type": "Feature",
  "properties": {
    "iso:country":"IN",
    "ks:ks_name":"Mundamma",
    "ks:ks_pop":74,
    "ks:ks_type":"HABITATION",
    "name:eng_x_preferred":[
        "Mundamma"
    ],
    "wof:name":"Mundamma",
    "wof:placetype":"locality",
    "wof:population":74
},
  "geometry": {"coordinates":[83.860927,19.585938],"type":"Point"}
}