{
  "type": "Feature",
  "properties": {
    "iso:country":"IN",
    "ks:ks_name":"Sinbandh",
    "ks:ks_pop":76,
    "ks:ks_type":"VILLAGE",
    "name:eng_x_preferred":[
        "Sinbandh"
    ],
    "wof:name":"Sinbandh",
    "wof:placetype":"locality",
    "wof:population":76
},
  "geometry": {"coordinates":[73.817352,20.655899],"type":"Point"}
}