{
  "type": "Feature",
  "properties": {
    "iso:country":"IN",
    "ks:ks_name":"Gadiajore",
    "ks:ks_pop":256,
    "ks:ks_type":"VILLAGE",
    "name:eng_x_preferred":[
        "Gadiajore"
    ],
    "wof:name":"Gadiajore",
    "wof:placetype":"locality",
    "wof:population":256
},
  "geometry": {"coordinates":[83.241034,20.869432],"type":"Point"}
}