{
  "type": "Feature",
  "properties": {
    "iso:country":"IN",
    "ks:ks_name":"Lalganj Teghra English",
    "ks:ks_pop":14737,
    "ks:ks_type":"VILLAGE",
    "ks:ks_uagg_main":0,
    "name:eng_x_preferred":[
        "Lalganj Teghra English"
    ],
    "wof:name":"Lalganj Teghra English",
    "wof:placetype":"neighbourhood",
    "wof:population":14737
},
  "geometry": {"coordinates":[87.751125,25.433655],"type":"Point"}
}