{
  "type": "Feature",
  "properties": {
    "iso:country":"IN",
    "ks:ks_alt_nam":"PIRACHE MAL",
    "ks:ks_name":"Pirache Mal",
    "ks:ks_pop":144,
    "ks:ks_type":"HABITATION",
    "name:eng_x_preferred":[
        "Pirache Mal"
    ],
    "wof:name":"Pirache Mal",
    "wof:placetype":"locality",
    "wof:population":144
},
  "geometry": {"coordinates":[74.60677099999999,17.353389],"type":"Point"}
}