{
  "type": "Feature",
  "properties": {
    "gn:admin1_code":"19.0",
    "gn:admin2_code":"575.0",
    "gn:asciiname":"Muda",
    "gn:country_code":"IN",
    "gn:dem":53,
    "gn:feature_class":"P",
    "gn:feature_code":"PPLL",
    "gn:name":"M\u016bda",
    "gn:population":0,
    "gn:timezone":"Asia/Kolkata",
    "iso:country":"IN",
    "name:ceb_x_preferred":[
        "Muda"
    ],
    "name:fra_x_preferred":[
        "Muda"
    ],
    "name:ita_x_preferred":[
        "Muda"
    ],
    "name:nld_x_preferred":[
        "Muda"
    ],
    "name:pol_x_preferred":[
        "Muda"
    ],
    "name:por_x_preferred":[
        "Muda"
    ],
    "name:spa_x_preferred":[
        "Muda"
    ],
    "name:swa_x_preferred":[
        "Muda"
    ],
    "name:swe_x_preferred":[
        "Muda"
    ],
    "name:und_x_variant":[
        "M\u016bda",
        "Per\u0101r"
    ],
    "wof:name":"Muda",
    "wof:placetype":"locality"
},
  "geometry": {"coordinates":[74.93485,12.98514],"type":"Point"}
}