{
  "type": "Feature",
  "properties": {
    "gn:admin1_code":"19.0",
    "gn:admin2_code":"556.0",
    "gn:asciiname":"Rader Timmapur",
    "gn:country_code":"IN",
    "gn:dem":613,
    "gn:feature_class":"P",
    "gn:feature_code":"PPL",
    "gn:name":"Rader Timm\u0101pur",
    "gn:population":0,
    "gn:timezone":"Asia/Kolkata",
    "iso:country":"IN",
    "wof:name":"Rader Timmapur",
    "wof:placetype":"locality"
},
  "geometry": {"coordinates":[75.45168000000002,15.99366],"type":"Point"}
}