{
  "type": "Feature",
  "properties": {
    "iso:country":"IN",
    "ks:ks_name":"Sultanpur Bahengi",
    "ks:ks_pop":390,
    "ks:ks_type":"VILLAGE",
    "name:eng_x_preferred":[
        "Sultanpur Bahengi"
    ],
    "wof:name":"Sultanpur Bahengi",
    "wof:placetype":"locality",
    "wof:population":390
},
  "geometry": {"coordinates":[81.439519,26.552389],"type":"Point"}
}