{
  "type": "Feature",
  "properties": {
    "iso:country":"IN",
    "ks:ks_name":"Milanpur",
    "ks:ks_pop":198,
    "ks:ks_type":"HABITATION",
    "ks:ks_uagg_main":0,
    "name:eng_x_preferred":[
        "Milanpur"
    ],
    "wof:name":"Milanpur",
    "wof:placetype":"neighbourhood",
    "wof:population":198
},
  "geometry": {"coordinates":[91.43222900000001,26.703704],"type":"Point"}
}