{
  "type": "Feature",
  "properties": {
    "iso:country":"IN",
    "ks:ks_name":"Paschim Barkajuli",
    "ks:ks_pop":300,
    "ks:ks_type":"HABITATION",
    "name:eng_x_preferred":[
        "Paschim Barkajuli"
    ],
    "wof:name":"Paschim Barkajuli",
    "wof:placetype":"locality",
    "wof:population":300
},
  "geometry": {"coordinates":[91.52304599999999,26.666105],"type":"Point"}
}