{
  "type": "Feature",
  "properties": {
    "gn:admin1_code":"2.0",
    "gn:admin2_code":"543.0",
    "gn:asciiname":"Enubarru",
    "gn:country_code":"IN",
    "gn:dem":253,
    "gn:feature_class":"P",
    "gn:feature_code":"PPL",
    "gn:name":"Enubarru",
    "gn:population":0,
    "gn:timezone":"Asia/Kolkata",
    "iso:country":"IN",
    "ks:ks_name":"Enubaruvu",
    "ks:ks_pop":156,
    "ks:ks_type":"HABITATION",
    "name:eng_x_preferred":[
        "Enubaruvu"
    ],
    "name:eng_x_variant":[
        "Enubarru"
    ],
    "wof:name":"Enubaruvu",
    "wof:placetype":"locality",
    "wof:population":156
},
  "geometry": {"coordinates":[83.228273,18.431849],"type":"Point"}
}