{
  "type": "Feature",
  "properties": {
    "iso:country":"IN",
    "ks:ks_name":"Lawadih",
    "ks:ks_pop":29,
    "ks:ks_type":"VILLAGE",
    "name:eng_x_preferred":[
        "Lawadih"
    ],
    "wof:name":"Lawadih",
    "wof:placetype":"locality",
    "wof:population":29
},
  "geometry": {"coordinates":[87.36349800000001,24.805126],"type":"Point"}
}