{
  "type": "Feature",
  "properties": {
    "gn:admin1_code":"37.0",
    "gn:admin2_code":"408.0",
    "gn:asciiname":"Kuajhorki",
    "gn:country_code":"IN",
    "gn:dem":311,
    "gn:feature_class":"P",
    "gn:feature_code":"PPL",
    "gn:name":"Ku\u0101jhorki",
    "gn:population":0,
    "gn:timezone":"Asia/Kolkata",
    "iso:country":"IN",
    "wof:name":"Kuajhorki",
    "wof:placetype":"neighbourhood"
},
  "geometry": {"coordinates":[81.03829,21.30596],"type":"Point"}
}