{
  "type": "Feature",
  "properties": {
    "gn:admin1_code":"16",
    "gn:admin2_code":"517.0",
    "gn:asciiname":"Shenwa",
    "gn:country_code":"IN",
    "gn:dem":95,
    "gn:feature_class":"P",
    "gn:feature_code":"PPL",
    "gn:name":"Shenwa",
    "gn:population":0,
    "gn:timezone":"Asia/Kolkata",
    "iso:country":"IN",
    "wof:name":"Shenwa",
    "wof:placetype":"locality"
},
  "geometry": {"coordinates":[73.45848000000002,19.44271],"type":"Point"}
}