{
  "type": "Feature",
  "properties": {
    "gn:admin1_code":"7.0",
    "gn:admin2_code":"98.0",
    "gn:asciiname":"Indrapuri",
    "gn:country_code":"IN",
    "gn:dem":214,
    "gn:feature_class":"P",
    "gn:feature_code":"PPL",
    "gn:name":"Indr\u0101puri",
    "gn:population":0,
    "gn:timezone":"Asia/Kolkata",
    "iso:country":"IN",
    "name:ara_x_preferred":[
        "\u062c\u0633\u0631 \u0625\u0646\u062f\u0631\u0627\u0628\u0648\u0631\u064a"
    ],
    "name:ben_bn_x_preferred":[
        "\u0987\u09a8\u09cd\u09a6\u09cd\u09b0\u09aa\u09c1\u09b0\u09c0"
    ],
    "name:ben_in_x_preferred":[
        "\u0987\u09a8\u09cd\u09a6\u09cd\u09b0\u09aa\u09c1\u09b0\u09c0"
    ],
    "name:guj_x_preferred":[
        "\u0a87\u0aa8\u0acd\u0aa6\u0acd\u0ab0\u0aaa\u0ac1\u0ab0\u0ac0"
    ],
    "name:hin_x_preferred":[
        "\u0907\u0902\u0926\u094d\u0930\u093e\u092a\u0941\u0930\u0940"
    ],
    "name:kan_x_preferred":[
        "\u0c87\u0c82\u0ca6\u0ccd\u0cb0\u0cbe\u0caa\u0cc1\u0cb0\u0cbf"
    ],
    "name:mal_x_preferred":[
        "\u0d07\u0d28\u0d4d\u0d26\u0d4d\u0d30\u0d2a\u0d41\u0d30\u0d3f"
    ],
    "name:mar_x_preferred":[
        "\u0907\u0902\u0926\u094d\u0930\u092a\u0941\u0930\u0940"
    ],
    "name:pan_x_preferred":[
        "\u0a07\u0a70\u0a26\u0a30\u0a3e\u0a2a\u0a41\u0a30\u0a40"
    ],
    "name:tam_x_preferred":[
        "\u0b87\u0ba8\u0bcd\u0ba4\u0bbf\u0bb0\u0baa\u0bc1\u0bb0\u0bbf"
    ],
    "name:tel_x_preferred":[
        "\u0c07\u0c02\u0c26\u0c4d\u0c30\u0c3e\u0c2a\u0c41\u0c30\u0c3f"
    ],
    "name:urd_x_preferred":[
        "\u0627\u0646\u062f\u0631\u0627 \u067e\u0648\u0631\u06cc"
    ],
    "wof:name":"Indrapuri",
    "wof:placetype":"neighbourhood"
},
  "geometry": {"coordinates":[77.30599000000002,28.49148],"type":"Point"}
}