{
  "type": "Feature",
  "properties": {
    "iso:country":"IN",
    "ks:ks_name":"Part I Madhaka",
    "ks:ks_pop":1242,
    "ks:ks_type":"HABITATION",
    "ks:ks_uagg_main":0,
    "name:eng_x_preferred":[
        "Part I Madhaka"
    ],
    "wof:name":"Part I Madhaka",
    "wof:placetype":"neighbourhood",
    "wof:population":1242
},
  "geometry": {"coordinates":[78.09542999999999,27.438306],"type":"Point"}
}