{
  "type": "Feature",
  "properties": {
    "iso:country":"IN",
    "ks:ks_name":"Botei",
    "ks:ks_pop":92,
    "ks:ks_type":"VILLAGE",
    "name:eng_x_preferred":[
        "Botei"
    ],
    "wof:name":"Botei",
    "wof:placetype":"locality",
    "wof:population":92
},
  "geometry": {"coordinates":[85.947391,20.021809],"type":"Point"}
}