{
  "type": "Feature",
  "properties": {
    "gn:admin1_code":"9.0",
    "gn:admin2_code":"486",
    "gn:asciiname":"Gad Boriad",
    "gn:country_code":"IN",
    "gn:dem":114,
    "gn:feature_class":"P",
    "gn:feature_code":"PPL",
    "gn:name":"Gad Bori\u0101d",
    "gn:population":0,
    "gn:timezone":"Asia/Kolkata",
    "iso:country":"IN",
    "wof:name":"Gad Boriad",
    "wof:placetype":"neighbourhood"
},
  "geometry": {"coordinates":[73.83199999999999,22.05572],"type":"Point"}
}