{
  "type": "Feature",
  "properties": {
    "iso:country":"IN",
    "ks:ks_name":"Jagannath Pur",
    "ks:ks_pop":290,
    "ks:ks_type":"VILLAGE",
    "ks:ks_uagg_main":0,
    "name:eng_x_preferred":[
        "Jagannath Pur"
    ],
    "wof:name":"Jagannath Pur",
    "wof:placetype":"neighbourhood",
    "wof:population":290
},
  "geometry": {"coordinates":[86.33705,20.680037],"type":"Point"}
}