{
  "type": "Feature",
  "properties": {
    "gn:admin1_code":"11.0",
    "gn:admin2_code":"32.0",
    "gn:asciiname":"Chunwin Dama",
    "gn:country_code":"IN",
    "gn:dem":1993,
    "gn:feature_class":"P",
    "gn:feature_code":"PPL",
    "gn:name":"Ch\u016bnw\u012bn Dama",
    "gn:population":0,
    "gn:timezone":"Asia/Kolkata",
    "iso:country":"IN",
    "wof:name":"Chunwin Dama",
    "wof:placetype":"locality"
},
  "geometry": {"coordinates":[77.49942,30.77483],"type":"Point"}
}