{
  "type": "Feature",
  "properties": {
    "iso:country":"IN",
    "ks:ks_name":"Mulagadde",
    "ks:ks_pop":255,
    "ks:ks_type":"VILLAGE",
    "name:eng_x_preferred":[
        "Mulagadde"
    ],
    "wof:name":"Mulagadde",
    "wof:placetype":"locality",
    "wof:population":255
},
  "geometry": {"coordinates":[75.044479,13.936973],"type":"Point"}
}