{
  "type": "Feature",
  "properties": {
    "gn:admin1_code":"36",
    "gn:admin2_code":"194.0",
    "gn:asciiname":"Misrpur",
    "gn:country_code":"IN",
    "gn:dem":92,
    "gn:feature_class":"P",
    "gn:feature_code":"PPL",
    "gn:name":"Misrpur",
    "gn:population":0,
    "gn:timezone":"Asia/Kolkata",
    "iso:country":"IN",
    "ks:ks_name":"Misirpur",
    "ks:ks_pop":453,
    "ks:ks_type":"VILLAGE",
    "ks:ks_uagg_main":0,
    "name:eng_x_preferred":[
        "Misirpur"
    ],
    "wof:name":"Misirpur",
    "wof:placetype":"neighbourhood",
    "wof:population":453
},
  "geometry": {"coordinates":[82.49728500000001,26.109466],"type":"Point"}
}