{
  "type": "Feature",
  "properties": {
    "iso:country":"IN",
    "ks:ks_name":"21 F",
    "ks:ks_pop":55,
    "ks:ks_type":"VILLAGE",
    "name:eng_x_preferred":[
        "21 F"
    ],
    "wof:name":"21 F",
    "wof:placetype":"locality",
    "wof:population":55
},
  "geometry": {"coordinates":[73.653631,29.903768],"type":"Point"}
}