{
  "type": "Feature",
  "properties": {
    "iso:country":"IN",
    "ks:ks_alt_nam":"Sakomotha TE 34 92",
    "ks:ks_name":"Sakomotha Te 34 92",
    "ks:ks_pop":1219,
    "ks:ks_type":"HABITATION",
    "name:eng_x_preferred":[
        "Sakomotha Te 34 92"
    ],
    "wof:name":"Sakomotha Te 34 92",
    "wof:placetype":"locality",
    "wof:population":1219
},
  "geometry": {"coordinates":[93.09575100000001,26.774605],"type":"Point"}
}