{
  "type": "Feature",
  "properties": {
    "iso:country":"IN",
    "ks:ks_name":"Nimubhitar Chhat",
    "ks:ks_pop":173,
    "ks:ks_type":"VILLAGE",
    "name:eng_x_preferred":[
        "Nimubhitar Chhat"
    ],
    "wof:name":"Nimubhitar Chhat",
    "wof:placetype":"locality",
    "wof:population":173
},
  "geometry": {"coordinates":[88.258208,26.661267],"type":"Point"}
}