{
  "type": "Feature",
  "properties": {
    "iso:country":"IN",
    "name:ara_x_preferred":[
        "\u0645\u0627\u0647\u0627\u0643\u0627\u0644\u064a\u0634\u0648\u0627\u0631"
    ],
    "name:ben_bn_x_preferred":[
        "\u09ae\u09b9\u09be\u0995\u09be\u09b2\u09c7\u09b6\u09cd\u09ac\u09b0"
    ],
    "name:ben_in_x_preferred":[
        "\u09ae\u09b9\u09be\u0995\u09be\u09b2\u09c7\u09b6\u09cd\u09ac\u09b0"
    ],
    "name:eng_x_preferred":[
        "Mahakaleshwar"
    ],
    "name:guj_x_preferred":[
        "\u0aae\u0ab9\u0abe\u0a95\u0abe\u0ab2\u0ac7\u0ab6\u0acd\u0ab5\u0ab0"
    ],
    "name:hin_x_preferred":[
        "\u092e\u0939\u093e\u0915\u093e\u0932\u0947\u0936\u094d\u0935\u0930"
    ],
    "name:kan_x_preferred":[
        "\u0cae\u0cb9\u0cbe\u0c95\u0cbe\u0cb2\u0cc7\u0cb6\u0ccd\u0cb5\u0cb0\u0ccd"
    ],
    "name:mal_x_preferred":[
        "\u0d2e\u0d39\u0d3e\u0d15\u0d32\u0d47\u0d36\u0d4d\u0d35\u0d7c"
    ],
    "name:mar_x_preferred":[
        "\u092e\u0939\u093e\u0915\u093e\u0932\u0947\u0936\u094d\u0935\u0930"
    ],
    "name:pan_x_preferred":[
        "\u0a2e\u0a39\u0a3e\u0a15\u0a32\u0a47\u0a36\u0a35\u0a30"
    ],
    "name:tam_x_preferred":[
        "\u0bae\u0bb9\u0bbe\u0b95\u0bbe\u0bb2\u0bc7\u0bb7\u0bcd\u0bb5\u0bb0\u0bcd"
    ],
    "name:tel_x_preferred":[
        "\u0c2e\u0c39\u0c3e\u0c15\u0c3e\u0c33\u0c47\u0c36\u0c4d\u0c35\u0c30\u0c4d"
    ],
    "name:urd_x_preferred":[
        "\u0645\u06c1\u0627 \u06a9\u0627\u0644\u06cc\u0634\u0648\u0631"
    ],
    "qs:gn_adm0_cc":"IN",
    "qs:gn_local":1253986,
    "qs:gn_nam_loc":"Udaipur, Udaipur, Rajasthan, IN",
    "qs:gn_namadm1":"24",
    "qs:local_max":4409,
    "qs:local_sum":9770,
    "qs:localhoods":18,
    "qs:name":"Mahakaleshwar",
    "qs:name_adm0":"India",
    "qs:name_adm1":"Rajasthan",
    "qs:name_adm2":"Udaipur",
    "qs:name_local":"Udaipur",
    "qs:photo_max":41,
    "qs:photo_sum":156,
    "qs:placetype":"Suburb",
    "qs:quad_count":13,
    "qs:woe_adm0":23424848,
    "qs:woe_adm1":2345757,
    "qs:woe_adm2":12586676,
    "qs:woe_lau":0,
    "qs:woe_local":2295108,
    "qs:woe_ver":"7.10.0",
    "wof:lang":[
        "eng"
    ],
    "wof:name":"Mahakaleshwar",
    "wof:placetype":"neighbourhood"
},
  "geometry": {"coordinates":[73.672504,24.590064],"type":"Point"}
}