{
  "type": "Feature",
  "properties": {
    "iso:country":"IN",
    "ks:ks_name":"Nelibari",
    "ks:ks_pop":514,
    "ks:ks_type":"HABITATION",
    "name:eng_x_preferred":[
        "Nelibari"
    ],
    "wof:name":"Nelibari",
    "wof:placetype":"locality",
    "wof:population":514
},
  "geometry": {"coordinates":[86.112026,20.907578],"type":"Point"}
}