{
  "type": "Feature",
  "properties": {
    "gn:admin1_code":"7.0",
    "gn:admin2_code":"90.0",
    "gn:asciiname":"Pipal Thola",
    "gn:country_code":"IN",
    "gn:dem":214,
    "gn:feature_class":"P",
    "gn:feature_code":"PPL",
    "gn:name":"Pipal Thola",
    "gn:population":0,
    "gn:timezone":"Asia/Kolkata",
    "iso:country":"IN",
    "name:ara_x_preferred":[
        "\u0628\u064a\u0628\u0627\u0644 \u062a\u0648\u0644\u0627"
    ],
    "name:ben_bn_x_preferred":[
        "\u09aa\u09bf\u09aa\u09be\u09b2 \u09a5\u09cb \u09b2\u09be"
    ],
    "name:ben_in_x_preferred":[
        "\u09aa\u09bf\u09aa\u09be\u09b2 \u09a0\u09cb\u09b2\u09be"
    ],
    "name:guj_x_preferred":[
        "\u0aaa\u0abf\u0aaa\u0ab2 \u0aa5\u0acb\u0ab2\u0abe"
    ],
    "name:hin_x_preferred":[
        "\u092a\u0940\u092a\u0932 \u0920\u094b\u0932\u093e"
    ],
    "name:kan_x_preferred":[
        "\u0caa\u0cbf\u0caa\u0cb2\u0ccd \u0ca5\u0ccb\u0cb2"
    ],
    "name:mal_x_preferred":[
        "\u0d2a\u0d3f\u0d2a\u0d3e\u0d7d \u0d24\u0d4b\u0d32"
    ],
    "name:mar_x_preferred":[
        "\u092a\u093f\u092a\u0932 \u0925\u094b\u0932\u093e"
    ],
    "name:pan_x_preferred":[
        "\u0a2a\u0a3f\u0a2a\u0a32 \u0a20\u0a4b\u0a32\u0a3e"
    ],
    "name:tam_x_preferred":[
        "\u0baa\u0bbf\u0baa\u0bb2\u0bcd \u0ba4\u0bcb\u0bb2\u0bbe"
    ],
    "name:tel_x_preferred":[
        "\u0c2a\u0c3f\u0c2a\u0c3e\u0c32\u0c4d \u0c25\u0c4a\u0c32\u0c3e"
    ],
    "name:urd_x_preferred":[
        "\u067e\u06cc\u067e\u0644 \u0679\u0648\u0644\u06c1"
    ],
    "wof:name":"Pipal Thola",
    "wof:placetype":"neighbourhood"
},
  "geometry": {"coordinates":[77.17099,28.71842],"type":"Point"}
}