{
  "type": "Feature",
  "properties": {
    "iso:country":"IN",
    "ks:ks_name":"Malenga",
    "ks:ks_pop":18,
    "ks:ks_type":"HABITATION",
    "name:eng_x_preferred":[
        "Malenga"
    ],
    "wof:name":"Malenga",
    "wof:placetype":"locality",
    "wof:population":18
},
  "geometry": {"coordinates":[80.711927,19.30919],"type":"Point"}
}