{
  "type": "Feature",
  "properties": {
    "iso:country":"IN",
    "ks:ks_name":"Pale",
    "ks:ks_pop":1009,
    "ks:ks_type":"VILLAGE",
    "ks:ks_uagg_main":0,
    "name:eng_x_preferred":[
        "Pale"
    ],
    "wof:name":"Pale",
    "wof:placetype":"neighbourhood",
    "wof:population":1009
},
  "geometry": {"coordinates":[73.001575,18.841462],"type":"Point"}
}