{
  "type": "Feature",
  "properties": {
    "iso:country":"IN",
    "ks:ks_name":"Digrapada",
    "ks:ks_pop":120,
    "ks:ks_type":"HABITATION",
    "name:eng_x_preferred":[
        "Digrapada"
    ],
    "wof:name":"Digrapada",
    "wof:placetype":"locality",
    "wof:population":120
},
  "geometry": {"coordinates":[82.808348,20.757933],"type":"Point"}
}