{
  "type": "Feature",
  "properties": {
    "gn:admin1_code":"25.0",
    "gn:admin2_code":"605.0",
    "gn:asciiname":"Vadakattapatti",
    "gn:country_code":"IN",
    "gn:dem":281,
    "gn:feature_class":"P",
    "gn:feature_code":"PPL",
    "gn:name":"Vadakattapatti",
    "gn:population":0,
    "gn:timezone":"Asia/Kolkata",
    "iso:country":"IN",
    "ks:ks_name":"Vadakathipatti",
    "ks:ks_pop":368,
    "ks:ks_type":"HABITATION",
    "name:eng_x_preferred":[
        "Vadakathipatti"
    ],
    "name:eng_x_variant":[
        "Vadakattapatti"
    ],
    "wof:name":"Vadakathipatti",
    "wof:placetype":"locality",
    "wof:population":368
},
  "geometry": {"coordinates":[78.868273,12.883765],"type":"Point"}
}