{
  "type": "Feature",
  "properties": {
    "iso:country":"IN",
    "ks:ks_name":"Jethwai",
    "ks:ks_pop":1266,
    "ks:ks_type":"VILLAGE",
    "name:eng_x_preferred":[
        "Jethwai"
    ],
    "wof:name":"Jethwai",
    "wof:placetype":"locality",
    "wof:population":1266
},
  "geometry": {"coordinates":[70.95036500000001,26.998404],"type":"Point"}
}