{
  "type": "Feature",
  "properties": {
    "iso:country":"IN",
    "ks:ks_name":"Behana",
    "ks:ks_pop":4,
    "ks:ks_type":"HABITATION",
    "name:eng_x_preferred":[
        "Behana"
    ],
    "wof:name":"Behana",
    "wof:placetype":"locality",
    "wof:population":4
},
  "geometry": {"coordinates":[81.14447199999999,24.848143],"type":"Point"}
}