{
  "type": "Feature",
  "properties": {
    "iso:country":"IN",
    "ks:ks_name":"Puthyadka",
    "ks:ks_pop":128,
    "ks:ks_type":"HABITATION",
    "name:eng_x_preferred":[
        "Puthyadka"
    ],
    "wof:name":"Puthyadka",
    "wof:placetype":"locality",
    "wof:population":128
},
  "geometry": {"coordinates":[75.252447,12.782773],"type":"Point"}
}