{
  "type": "Feature",
  "properties": {
    "iso:country":"IN",
    "ks:ks_name":"Senakarai",
    "ks:ks_pop":580,
    "ks:ks_type":"HABITATION",
    "name:eng_x_preferred":[
        "Senakarai"
    ],
    "wof:name":"Senakarai",
    "wof:placetype":"locality",
    "wof:population":580
},
  "geometry": {"coordinates":[79.519274,10.67997],"type":"Point"}
}