{
  "type": "Feature",
  "properties": {
    "gn:admin1_code":"36.0",
    "gn:admin2_code":"190.0",
    "gn:asciiname":"Indarwa",
    "gn:country_code":"IN",
    "gn:dem":69,
    "gn:feature_class":"P",
    "gn:feature_code":"PPL",
    "gn:name":"Indarwa",
    "gn:population":0,
    "gn:timezone":"Asia/Kolkata",
    "iso:country":"IN",
    "ks:ks_name":"Indarwa",
    "ks:ks_type":"VILLAGE",
    "ks:ks_uagg_main":0,
    "name:eng_x_preferred":[
        "Indarwa"
    ],
    "name:tam_x_preferred":[
        "\u0b87\u0ba8\u0bcd\u0ba4\u0bb0\u0bcd\u0bb5\u0bbe"
    ],
    "wof:name":"Indarwa",
    "wof:placetype":"neighbourhood"
},
  "geometry": {"coordinates":[84.16309699999999,26.278934],"type":"Point"}
}