{
  "type": "Feature",
  "properties": {
    "gn:admin1_code":"2.0",
    "gn:admin2_code":"544.0",
    "gn:asciiname":"Landiguda",
    "gn:country_code":"IN",
    "gn:dem":925,
    "gn:feature_class":"P",
    "gn:feature_code":"PPL",
    "gn:name":"Landig\u016bda",
    "gn:population":0,
    "gn:timezone":"Asia/Kolkata",
    "iso:country":"IN",
    "ks:ks_name":"Landiguda",
    "ks:ks_pop":115,
    "ks:ks_type":"HABITATION",
    "name:eng_x_preferred":[
        "Landiguda"
    ],
    "wof:name":"Landiguda",
    "wof:placetype":"locality",
    "wof:population":115
},
  "geometry": {"coordinates":[83.068184,18.328333],"type":"Point"}
}