{
  "type": "Feature",
  "properties": {
    "gn:admin1_code":"11.0",
    "gn:admin2_code":"32.0",
    "gn:asciiname":"Dudiyan",
    "gn:country_code":"IN",
    "gn:dem":1356,
    "gn:feature_class":"P",
    "gn:feature_code":"PPL",
    "gn:name":"Dudiy\u0101n",
    "gn:population":0,
    "gn:timezone":"Asia/Kolkata",
    "iso:country":"IN",
    "wof:name":"Dudiyan",
    "wof:placetype":"locality"
},
  "geometry": {"coordinates":[77.62170999999999,30.67571],"type":"Point"}
}