{
  "type": "Feature",
  "properties": {
    "iso:country":"IN",
    "ks:ks_name":"Ramanathapuram",
    "ks:ks_pop":261,
    "ks:ks_type":"HABITATION",
    "name:eng_x_preferred":[
        "Ramanathapuram"
    ],
    "wof:name":"Ramanathapuram",
    "wof:placetype":"locality",
    "wof:population":261
},
  "geometry": {"coordinates":[78.651291,11.283808],"type":"Point"}
}