{
  "type": "Feature",
  "properties": {
    "iso:country":"IN",
    "ks:ks_name":"Kazi Chak",
    "ks:ks_pop":902,
    "ks:ks_type":"VILLAGE",
    "name:eng_x_preferred":[
        "Kazi Chak"
    ],
    "wof:name":"Kazi Chak",
    "wof:placetype":"locality",
    "wof:population":902
},
  "geometry": {"coordinates":[86.276336,25.365742],"type":"Point"}
}