{
  "type": "Feature",
  "properties": {
    "iso:country":"IN",
    "ks:ks_name":"Pasin Dera",
    "ks:ks_pop":160,
    "ks:ks_type":"HABITATION",
    "name:eng_x_preferred":[
        "Pasin Dera"
    ],
    "wof:name":"Pasin Dera",
    "wof:placetype":"locality",
    "wof:population":160
},
  "geometry": {"coordinates":[80.907988,25.712059],"type":"Point"}
}