{
  "type": "Feature",
  "properties": {
    "iso:country":"IN",
    "ks:ks_name":"Bianla",
    "ks:ks_pop":712,
    "ks:ks_type":"HABITATION",
    "name:eng_x_preferred":[
        "Bianla"
    ],
    "wof:name":"Bianla",
    "wof:placetype":"locality",
    "wof:population":712
},
  "geometry": {"coordinates":[86.207521,19.979433],"type":"Point"}
}