{
  "type": "Feature",
  "properties": {
    "iso:country":"IN",
    "ks:ks_name":"Harmadih",
    "ks:ks_pop":572,
    "ks:ks_type":"HABITATION",
    "name:eng_x_preferred":[
        "Harmadih"
    ],
    "wof:name":"Harmadih",
    "wof:placetype":"locality",
    "wof:population":572
},
  "geometry": {"coordinates":[86.41843799999999,22.774254],"type":"Point"}
}