{
  "type": "Feature",
  "properties": {
    "iso:country":"IN",
    "ks:ks_name":"Murathagundi",
    "ks:ks_pop":505,
    "ks:ks_type":"HABITATION",
    "name:eng_x_preferred":[
        "Murathagundi"
    ],
    "wof:name":"Murathagundi",
    "wof:placetype":"locality",
    "wof:population":505
},
  "geometry": {"coordinates":[74.907461,12.776032],"type":"Point"}
}