{
  "type": "Feature",
  "properties": {
    "gn:admin1_code":"35",
    "gn:admin2_code":"458.0",
    "gn:asciiname":"Karela",
    "gn:country_code":"IN",
    "gn:dem":425,
    "gn:feature_class":"P",
    "gn:feature_code":"PPL",
    "gn:name":"Karela",
    "gn:population":0,
    "gn:timezone":"Asia/Kolkata",
    "iso:country":"IN",
    "name:ara_x_preferred":[
        "\u0643\u064a\u0631\u0644\u0627"
    ],
    "name:ben_bn_x_preferred":[
        "\u0995\u09be\u09b0\u09c7\u09b2\u09be"
    ],
    "name:ben_in_x_preferred":[
        "\u0995\u09be\u09b0\u09c7\u09b2\u09be"
    ],
    "name:guj_x_preferred":[
        "\u0a95\u0abe\u0ab0\u0ac7\u0ab2\u0abe"
    ],
    "name:hin_x_preferred":[
        "\u0915\u0930\u0947\u0932\u093e"
    ],
    "name:kan_x_preferred":[
        "\u0c95\u0cb0\u0cc7\u0cb2\u0cbe"
    ],
    "name:mal_x_preferred":[
        "\u0d15\u0d47\u0d30\u0d33"
    ],
    "name:mar_x_preferred":[
        "\u0915\u0930\u0947\u0932\u093e"
    ],
    "name:pan_x_preferred":[
        "\u0a15\u0a47\u0a30\u0a32\u0a3e"
    ],
    "name:tam_x_preferred":[
        "\u0b95\u0bb0\u0bc7\u0bb2\u0bbe"
    ],
    "name:tel_x_preferred":[
        "\u0c15\u0c30\u0c47\u0c32\u0c3e"
    ],
    "name:urd_x_preferred":[
        "\u06a9\u06cc\u0631\u0627\u0644\u06c1"
    ],
    "wof:name":"Karela",
    "wof:placetype":"locality"
},
  "geometry": {"coordinates":[77.20990999999999,24.0812],"type":"Point"}
}