{
  "type": "Feature",
  "properties": {
    "gn:admin1_code":"24.0",
    "gn:admin2_code":"123.0",
    "gn:asciiname":"Lathian ki Kheri",
    "gn:country_code":"IN",
    "gn:dem":491,
    "gn:feature_class":"P",
    "gn:feature_code":"PPL",
    "gn:name":"L\u0101thi\u0101n ki Kheri",
    "gn:population":0,
    "gn:timezone":"Asia/Kolkata",
    "iso:country":"IN",
    "wof:name":"Lathian ki Kheri",
    "wof:placetype":"locality"
},
  "geometry": {"coordinates":[74.13410999999998,25.02088],"type":"Point"}
}