{
  "type": "Feature",
  "properties": {
    "iso:country":"IN",
    "ks:ks_name":"Makundapur",
    "ks:ks_pop":817,
    "ks:ks_type":"VILLAGE",
    "name:eng_x_preferred":[
        "Makundapur"
    ],
    "wof:name":"Makundapur",
    "wof:placetype":"locality",
    "wof:population":817
},
  "geometry": {"coordinates":[86.861468,21.542787],"type":"Point"}
}