{
  "type": "Feature",
  "properties": {
    "gn:admin1_code":"12.0",
    "gn:admin2_code":"19.0",
    "gn:asciiname":"Kadar",
    "gn:country_code":"IN",
    "gn:dem":1456,
    "gn:feature_class":"P",
    "gn:feature_code":"PPL",
    "gn:name":"Kadar",
    "gn:population":0,
    "gn:timezone":"Asia/Kolkata",
    "iso:country":"IN",
    "name:ceb_x_preferred":[
        "Kadar"
    ],
    "name:fra_x_preferred":[
        "Kadar"
    ],
    "name:kor_x_preferred":[
        "\uce74\ub2e4\ub974"
    ],
    "name:swe_x_preferred":[
        "Kadar"
    ],
    "wof:name":"Kadar",
    "wof:placetype":"locality"
},
  "geometry": {"coordinates":[75.51316,32.74663],"type":"Point"}
}