{
  "type": "Feature",
  "properties": {
    "gn:admin1_code":"11",
    "gn:admin2_code":"34.0",
    "gn:asciiname":"Bada Kanda Dogri",
    "gn:country_code":"IN",
    "gn:dem":3366,
    "gn:feature_class":"P",
    "gn:feature_code":"PPL",
    "gn:name":"Bada Kanda Dogri",
    "gn:population":0,
    "gn:timezone":"Asia/Kolkata",
    "iso:country":"IN",
    "wof:name":"Bada Kanda Dogri",
    "wof:placetype":"locality"
},
  "geometry": {"coordinates":[78.32474000000001,31.62248],"type":"Point"}
}