{
  "type": "Feature",
  "properties": {
    "iso:country":"IN",
    "ks:ks_name":"Chewo",
    "ks:ks_pop":140,
    "ks:ks_type":"VILLAGE",
    "name:eng_x_preferred":[
        "Chewo"
    ],
    "wof:name":"Chewo",
    "wof:placetype":"locality",
    "wof:population":140
},
  "geometry": {"coordinates":[87.41033400000001,24.655801],"type":"Point"}
}