{
  "type": "Feature",
  "properties": {
    "iso:country":"IN",
    "ks:ks_alt_nam":"Bhaia R\u0101m Bherih\u0101ri",
    "ks:ks_name":"Bhaia Ram Bherihari",
    "ks:ks_type":"VILLAGE",
    "name:eng_x_preferred":[
        "Bhaia Ram Bherihari"
    ],
    "name:eng_x_variant":[
        "Bhaia R\u0101m Bherih\u0101ri"
    ],
    "wof:name":"Bhaia Ram Bherihari",
    "wof:placetype":"locality"
},
  "geometry": {"coordinates":[84.428239,26.67455],"type":"Point"}
}