{
  "type": "Feature",
  "properties": {
    "gn:admin1_code":"24.0",
    "gn:admin2_code":"122.0",
    "gn:asciiname":"Kotro",
    "gn:country_code":"IN",
    "gn:dem":475,
    "gn:feature_class":"P",
    "gn:feature_code":"PPL",
    "gn:name":"Kotro",
    "gn:population":0,
    "gn:timezone":"Asia/Kolkata",
    "iso:country":"IN",
    "name:und_x_variant":[
        "Lachhm\u012bpura"
    ],
    "wof:name":"Kotro",
    "wof:placetype":"neighbourhood"
},
  "geometry": {"coordinates":[74.34681,25.899],"type":"Point"}
}