{
  "type": "Feature",
  "properties": {
    "iso:country":"IN",
    "ks:ks_name":"Zarimata",
    "ks:ks_pop":834,
    "ks:ks_type":"HABITATION",
    "name:eng_x_preferred":[
        "Zarimata"
    ],
    "wof:name":"Zarimata",
    "wof:placetype":"locality",
    "wof:population":834
},
  "geometry": {"coordinates":[74.96921500000001,21.6266],"type":"Point"}
}