{
  "type": "Feature",
  "properties": {
    "iso:country":"IN",
    "ks:ks_name":"Palliyalthodi Jn",
    "ks:ks_pop":842,
    "ks:ks_type":"HABITATION",
    "name:eng_x_preferred":[
        "Palliyalthodi Jn"
    ],
    "wof:name":"Palliyalthodi Jn",
    "wof:placetype":"locality",
    "wof:population":842
},
  "geometry": {"coordinates":[76.031581,11.09408],"type":"Point"}
}