{
  "type": "Feature",
  "properties": {
    "gn:admin1_code":"34.0",
    "gn:admin2_code":"221.0",
    "gn:asciiname":"Raini",
    "gn:country_code":"IN",
    "gn:dem":51,
    "gn:feature_class":"P",
    "gn:feature_code":"PPL",
    "gn:name":"Raini",
    "gn:population":0,
    "gn:timezone":"Asia/Kolkata",
    "iso:country":"IN",
    "ks:ks_name":"Raini",
    "ks:ks_pop":1545,
    "ks:ks_type":"VILLAGE",
    "name:eng_x_preferred":[
        "Raini"
    ],
    "wof:name":"Raini",
    "wof:placetype":"locality",
    "wof:population":1545
},
  "geometry": {"coordinates":[85.872719,25.863214],"type":"Point"}
}