{
  "type": "Feature",
  "properties": {
    "iso:country":"IN",
    "ks:ks_name":"Dandinabail",
    "ks:ks_pop":36,
    "ks:ks_type":"HABITATION",
    "name:eng_x_preferred":[
        "Dandinabail"
    ],
    "wof:name":"Dandinabail",
    "wof:placetype":"locality",
    "wof:population":36
},
  "geometry": {"coordinates":[74.879276,14.472691],"type":"Point"}
}