{
  "type": "Feature",
  "properties": {
    "gn:admin1_code":"11",
    "gn:admin2_code":"27.0",
    "gn:asciiname":"Bahla Tarf",
    "gn:country_code":"IN",
    "gn:dem":1282,
    "gn:feature_class":"P",
    "gn:feature_code":"PPL",
    "gn:name":"B\u0101hla Tarf",
    "gn:population":0,
    "gn:timezone":"Asia/Kolkata",
    "iso:country":"IN",
    "wof:name":"Bahla Tarf",
    "wof:placetype":"locality"
},
  "geometry": {"coordinates":[76.96289,31.75124000000001],"type":"Point"}
}