{
  "type": "Feature",
  "properties": {
    "iso:country":"IN",
    "ks:ks_alt_nam":"Pariv\u0101rkop",
    "ks:ks_name":"Parivarkop",
    "ks:ks_type":"VILLAGE",
    "name:eng_x_preferred":[
        "Parivarkop"
    ],
    "name:eng_x_variant":[
        "Pariv\u0101rkop"
    ],
    "wof:name":"Parivarkop",
    "wof:placetype":"locality"
},
  "geometry": {"coordinates":[75.183239,14.664833],"type":"Point"}
}