{
  "type": "Feature",
  "properties": {
    "iso:country":"IN",
    "ks:ks_name":"Keutpara",
    "ks:ks_pop":106,
    "ks:ks_type":"HABITATION",
    "name:eng_x_preferred":[
        "Keutpara"
    ],
    "wof:name":"Keutpara",
    "wof:placetype":"locality",
    "wof:population":106
},
  "geometry": {"coordinates":[91.63323200000001,26.212268],"type":"Point"}
}