{
  "type": "Feature",
  "properties": {
    "iso:country":"IN",
    "ks:ks_name":"P Shivgulam",
    "ks:ks_pop":174,
    "ks:ks_type":"HABITATION",
    "name:eng_x_preferred":[
        "P Shivgulam"
    ],
    "wof:name":"P Shivgulam",
    "wof:placetype":"locality",
    "wof:population":174
},
  "geometry": {"coordinates":[81.5441,26.3958],"type":"Point"}
}