{
  "type": "Feature",
  "properties": {
    "gn:admin1_code":"38.0",
    "gn:admin2_code":"362.0",
    "gn:asciiname":"Ranai",
    "gn:country_code":"IN",
    "gn:dem":85,
    "gn:feature_class":"P",
    "gn:feature_code":"PPL",
    "gn:name":"R\u0101nai",
    "gn:population":0,
    "gn:timezone":"Asia/Kolkata",
    "iso:country":"IN",
    "wof:name":"Ranai",
    "wof:placetype":"locality"
},
  "geometry": {"coordinates":[87.55138000000002,24.25524],"type":"Point"}
}