{
  "type": "Feature",
  "properties": {
    "gn:admin1_code":"16",
    "gn:admin2_code":"509.0",
    "gn:asciiname":"Khanabad",
    "gn:country_code":"IN",
    "gn:dem":223,
    "gn:feature_class":"P",
    "gn:feature_code":"PPL",
    "gn:name":"Kh\u0101n\u0101b\u0101d",
    "gn:population":0,
    "gn:timezone":"Asia/Kolkata",
    "iso:country":"IN",
    "name:aze_x_preferred":[
        "Xanabad"
    ],
    "name:ceb_x_preferred":[
        "Khanabad"
    ],
    "name:deu_x_preferred":[
        "Chanabad"
    ],
    "name:fas_x_preferred":[
        "\u062e\u0627\u0646\u200c\u0622\u0628\u0627\u062f"
    ],
    "name:fra_x_preferred":[
        "Khanabad"
    ],
    "name:ita_x_preferred":[
        "Xanabad"
    ],
    "name:kat_x_preferred":[
        "\u10ee\u10d0\u10dc\u10d0\u10d1\u10d0\u10d3\u10d8"
    ],
    "name:rus_x_preferred":[
        "\u0425\u0430\u043d\u0430\u0431\u0430\u0434"
    ],
    "name:swe_x_preferred":[
        "Khanabad"
    ],
    "name:ukr_x_preferred":[
        "\u0425\u0430\u043d\u0430\u0431\u0430\u0434"
    ],
    "name:uzb_x_preferred":[
        "Xonobod"
    ],
    "wof:name":"Khanabad",
    "wof:placetype":"locality"
},
  "geometry": {"coordinates":[79.91150999999998,20.29768],"type":"Point"}
}