{
  "type": "Feature",
  "properties": {
    "iso:country":"IN",
    "ks:ks_name":"Chumarigacha",
    "ks:ks_pop":1538,
    "ks:ks_type":"VILLAGE",
    "ks:ks_uagg_main":0,
    "name:eng_x_preferred":[
        "Chumarigacha"
    ],
    "wof:name":"Chumarigacha",
    "wof:placetype":"neighbourhood",
    "wof:population":1538
},
  "geometry": {"coordinates":[88.187133,23.967194],"type":"Point"}
}