{
  "type": "Feature",
  "properties": {
    "iso:country":"IN",
    "ks:ks_name":"Vishnu Nagar",
    "ks:ks_pop":789,
    "ks:ks_type":"HABITATION",
    "name:eng_x_preferred":[
        "Vishnu Nagar"
    ],
    "wof:name":"Vishnu Nagar",
    "wof:placetype":"locality",
    "wof:population":789
},
  "geometry": {"coordinates":[73.471253,26.305528],"type":"Point"}
}