{
  "type": "Feature",
  "properties": {
    "iso:country":"IN",
    "ks:ks_name":"Rugudipali",
    "ks:ks_pop":288,
    "ks:ks_type":"VILLAGE",
    "name:eng_x_preferred":[
        "Rugudipali"
    ],
    "wof:name":"Rugudipali",
    "wof:placetype":"locality",
    "wof:population":288
},
  "geometry": {"coordinates":[84.05497699999999,21.237965],"type":"Point"}
}