{
  "type": "Feature",
  "properties": {
    "gn:admin1_code":"19.0",
    "gn:admin2_code":"563.0",
    "gn:asciiname":"Bijhala",
    "gn:country_code":"IN",
    "gn:dem":537,
    "gn:feature_class":"P",
    "gn:feature_code":"PPL",
    "gn:name":"Bijh\u0101la",
    "gn:population":0,
    "gn:timezone":"Asia/Kolkata",
    "iso:country":"IN",
    "ks:ks_name":"Bijjala",
    "ks:ks_pop":73,
    "ks:ks_type":"HABITATION",
    "name:eng_x_preferred":[
        "Bijjala"
    ],
    "name:eng_x_variant":[
        "Bijhala"
    ],
    "wof:name":"Bijjala",
    "wof:placetype":"locality",
    "wof:population":73
},
  "geometry": {"coordinates":[74.744711,14.314418],"type":"Point"}
}