{
  "type": "Feature",
  "properties": {
    "gn:admin1_code":"16.0",
    "gn:admin2_code":"498.0",
    "gn:asciiname":"Temblay",
    "gn:country_code":"IN",
    "gn:dem":160,
    "gn:feature_class":"P",
    "gn:feature_code":"PPL",
    "gn:name":"Tembl\u0101y",
    "gn:population":0,
    "gn:timezone":"Asia/Kolkata",
    "iso:country":"IN",
    "wof:name":"Temblay",
    "wof:placetype":"locality"
},
  "geometry": {"coordinates":[74.76975999999998,21.25626],"type":"Point"}
}