{
  "type": "Feature",
  "properties": {
    "gn:admin1_code":"16.0",
    "gn:admin2_code":"498.0",
    "gn:asciiname":"Temblay",
    "gn:country_code":"IN",
    "gn:dem":160,
    "gn:feature_class":"P",
    "gn:feature_code":"PPL",
    "gn:name":"Tembl\u0101y",
    "gn:population":0,
    "gn:timezone":"Asia/Kolkata",
    "iso:country":"IN",
    "ks:ks_name":"Temlay",
    "ks:ks_pop":587,
    "ks:ks_type":"VILLAGE",
    "name:eng_x_preferred":[
        "Temlay"
    ],
    "name:eng_x_variant":[
        "Temblay"
    ],
    "wof:name":"Temlay",
    "wof:placetype":"locality",
    "wof:population":587
},
  "geometry": {"coordinates":[74.77738100000001,21.24901],"type":"Point"}
}