{
  "type": "Feature",
  "properties": {
    "gn:admin1_code":"34.0",
    "gn:admin2_code":"219.0",
    "gn:asciiname":"Sikti Khanjahan",
    "gn:country_code":"IN",
    "gn:dem":61,
    "gn:feature_class":"P",
    "gn:feature_code":"PPL",
    "gn:name":"Sikti Kh\u0101njah\u0101n",
    "gn:population":0,
    "gn:timezone":"Asia/Kolkata",
    "iso:country":"IN",
    "ks:ks_alt_nam":"Sikti Kh\u0101njah\u0101n",
    "ks:ks_name":"Sikti Khanjahan",
    "ks:ks_type":"VILLAGE",
    "ks:ks_uagg_main":0,
    "name:eng_x_preferred":[
        "Sikti Khanjahan"
    ],
    "name:eng_x_variant":[
        "Sikti Kh\u0101njah\u0101n"
    ],
    "wof:name":"Sikti Khanjahan",
    "wof:placetype":"neighbourhood"
},
  "geometry": {"coordinates":[84.76028599999999,26.064092],"type":"Point"}
}