{
  "type": "Feature",
  "properties": {
    "iso:country":"IN",
    "ks:ks_name":"Mondewadi",
    "ks:ks_pop":97,
    "ks:ks_type":"HABITATION",
    "name:eng_x_preferred":[
        "Mondewadi"
    ],
    "wof:name":"Mondewadi",
    "wof:placetype":"locality",
    "wof:population":97
},
  "geometry": {"coordinates":[73.42015000000001,16.5028],"type":"Point"}
}