{
  "type": "Feature",
  "properties": {
    "iso:country":"IN",
    "ks:ks_name":"Kadamtala Pt.I",
    "ks:ks_pop":512,
    "ks:ks_type":"VILLAGE",
    "name:eng_x_preferred":[
        "Kadamtala Pt.I"
    ],
    "wof:name":"Kadamtala Pt.I",
    "wof:placetype":"locality",
    "wof:population":512
},
  "geometry": {"coordinates":[90.202624,26.217077],"type":"Point"}
}