{
  "type": "Feature",
  "properties": {
    "iso:country":"IN",
    "ks:ks_name":"Sagwadi",
    "ks:ks_pop":110,
    "ks:ks_type":"HABITATION",
    "name:eng_x_preferred":[
        "Sagwadi"
    ],
    "wof:name":"Sagwadi",
    "wof:placetype":"locality",
    "wof:population":110
},
  "geometry": {"coordinates":[73.091701,18.900582],"type":"Point"}
}