{
  "type": "Feature",
  "properties": {
    "gn:admin1_code":"25.0",
    "gn:admin2_code":"617.0",
    "gn:asciiname":"Toravalur",
    "gn:country_code":"IN",
    "gn:dem":46,
    "gn:feature_class":"P",
    "gn:feature_code":"PPL",
    "gn:name":"Toraval\u016br",
    "gn:population":0,
    "gn:timezone":"Asia/Kolkata",
    "iso:country":"IN",
    "wof:name":"Toravalur",
    "wof:placetype":"locality"
},
  "geometry": {"coordinates":[79.26361,11.51683],"type":"Point"}
}