{
  "type": "Feature",
  "properties": {
    "iso:country":"IN",
    "ks:ks_name":"Perumbillichira",
    "ks:ks_pop":504,
    "ks:ks_type":"HABITATION",
    "ks:ks_uagg_main":0,
    "name:eng_x_preferred":[
        "Perumbillichira"
    ],
    "wof:name":"Perumbillichira",
    "wof:placetype":"neighbourhood",
    "wof:population":504
},
  "geometry": {"coordinates":[76.715948,9.917824],"type":"Point"}
}