{
  "type": "Feature",
  "properties": {
    "iso:country":"IN",
    "ks:ks_name":"Majhiguda",
    "ks:ks_pop":184,
    "ks:ks_type":"VILLAGE",
    "name:eng_x_preferred":[
        "Majhiguda"
    ],
    "wof:name":"Majhiguda",
    "wof:placetype":"locality",
    "wof:population":184
},
  "geometry": {"coordinates":[82.22648100000001,19.466957],"type":"Point"}
}