{
  "type": "Feature",
  "properties": {
    "gn:admin1_code":"34.0",
    "gn:admin2_code":"216.0",
    "gn:asciiname":"Raja Pakar",
    "gn:country_code":"IN",
    "gn:dem":56,
    "gn:feature_class":"P",
    "gn:feature_code":"PPL",
    "gn:name":"R\u0101ja P\u0101kar",
    "gn:population":0,
    "gn:timezone":"Asia/Kolkata",
    "iso:country":"IN",
    "ks:ks_name":"Raja Padar",
    "ks:ks_pop":3312,
    "ks:ks_type":"VILLAGE",
    "name:eng_x_preferred":[
        "Raja Padar"
    ],
    "name:eng_x_variant":[
        "Raja Pakar"
    ],
    "wof:name":"Raja Padar",
    "wof:placetype":"locality",
    "wof:population":3312
},
  "geometry": {"coordinates":[85.508821,25.925857],"type":"Point"}
}