{
  "type": "Feature",
  "properties": {
    "iso:country":"IN",
    "ks:ks_name":"Kundari Tao Gurgaon",
    "ks:ks_pop":240,
    "ks:ks_type":"HABITATION",
    "name:eng_x_preferred":[
        "Kundari Tao Gurgaon"
    ],
    "wof:name":"Kundari Tao Gurgaon",
    "wof:placetype":"locality",
    "wof:population":240
},
  "geometry": {"coordinates":[79.704044,27.691078],"type":"Point"}
}