{
  "type": "Feature",
  "properties": {
    "gn:admin1_code":"2.0",
    "gn:admin2_code":"542.0",
    "gn:asciiname":"Katakam Ayyappapeta",
    "gn:country_code":"IN",
    "gn:dem":36,
    "gn:feature_class":"P",
    "gn:feature_code":"PPL",
    "gn:name":"Katakam Ayyappapet\u0101",
    "gn:population":0,
    "gn:timezone":"Asia/Kolkata",
    "iso:country":"IN",
    "wof:name":"Katakam Ayyappapeta",
    "wof:placetype":"locality"
},
  "geometry": {"coordinates":[83.89431999999999,18.48118],"type":"Point"}
}