{
  "type": "Feature",
  "properties": {
    "iso:country":"IN",
    "ks:ks_name":"19 SJM",
    "ks:ks_pop":143,
    "ks:ks_type":"VILLAGE",
    "name:eng_x_preferred":[
        "19 SJM"
    ],
    "wof:name":"19 SJM",
    "wof:placetype":"locality",
    "wof:population":143
},
  "geometry": {"coordinates":[73.214669,29.325911],"type":"Point"}
}