{
  "type": "Feature",
  "properties": {
    "iso:country":"IN",
    "ks:ks_name":"Badalewadi",
    "ks:ks_pop":793,
    "ks:ks_type":"HABITATION",
    "name:eng_x_preferred":[
        "Badalewadi"
    ],
    "wof:name":"Badalewadi",
    "wof:placetype":"locality",
    "wof:population":793
},
  "geometry": {"coordinates":[73.70975900000001,18.810362],"type":"Point"}
}