{
  "type": "Feature",
  "properties": {
    "gn:admin1_code":"21.0",
    "gn:admin2_code":"396",
    "gn:asciiname":"Chandragiri",
    "gn:country_code":"IN",
    "gn:dem":715,
    "gn:feature_class":"P",
    "gn:feature_code":"PPL",
    "gn:name":"Chandragiri",
    "gn:population":0,
    "gn:timezone":"Asia/Kolkata",
    "iso:country":"IN",
    "wof:name":"Chandragiri",
    "wof:placetype":"locality"
},
  "geometry": {"coordinates":[82.98409000000002,19.38312],"type":"Point"}
}