{
  "type": "Feature",
  "properties": {
    "iso:country":"IN",
    "ks:ks_name":"Boyyannaguda",
    "ks:ks_pop":42,
    "ks:ks_type":"HABITATION",
    "name:eng_x_preferred":[
        "Boyyannaguda"
    ],
    "wof:name":"Boyyannaguda",
    "wof:placetype":"locality",
    "wof:population":42
},
  "geometry": {"coordinates":[83.830305,18.640592],"type":"Point"}
}