{
  "type": "Feature",
  "properties": {
    "gn:admin1_code":"11",
    "gn:admin2_code":"23.0",
    "gn:asciiname":"Tappa",
    "gn:country_code":"IN",
    "gn:dem":2393,
    "gn:feature_class":"P",
    "gn:feature_code":"PPL",
    "gn:name":"Tappa",
    "gn:population":0,
    "gn:timezone":"Asia/Kolkata",
    "iso:country":"IN",
    "name:ben_x_preferred":[
        "\u099f\u09aa\u09cd\u09aa\u09be \u0997\u09be\u09a8"
    ],
    "name:deu_x_preferred":[
        "Tappa"
    ],
    "name:fra_x_preferred":[
        "Tapp\u00e2"
    ],
    "name:hin_x_preferred":[
        "\u091f\u092a\u094d\u092a\u093e"
    ],
    "name:mal_x_preferred":[
        "\u0d1f\u0d2a\u0d4d\u0d2a"
    ],
    "name:mar_x_preferred":[
        "\u091f\u092a\u094d\u092a\u093e"
    ],
    "name:san_x_preferred":[
        "\u091f\u092a\u094d\u092a\u093e"
    ],
    "name:urd_x_preferred":[
        "\u0679\u067e\u06c1"
    ],
    "wof:name":"Tappa",
    "wof:placetype":"locality"
},
  "geometry": {"coordinates":[76.24410999999998,32.92995999999999],"type":"Point"}
}