{
  "type": "Feature",
  "properties": {
    "iso:country":"IN",
    "ks:ks_name":"Muzhiyanthodpara",
    "ks:ks_pop":695,
    "ks:ks_type":"HABITATION",
    "name:eng_x_preferred":[
        "Muzhiyanthodpara"
    ],
    "wof:name":"Muzhiyanthodpara",
    "wof:placetype":"locality",
    "wof:population":695
},
  "geometry": {"coordinates":[76.12012900000001,10.384908],"type":"Point"}
}