{
  "type": "Feature",
  "properties": {
    "iso:country":"IN",
    "ks:ks_name":"Thalkarwadi",
    "ks:ks_pop":64,
    "ks:ks_type":"HABITATION",
    "name:eng_x_preferred":[
        "Thalkarwadi"
    ],
    "wof:name":"Thalkarwadi",
    "wof:placetype":"locality",
    "wof:population":64
},
  "geometry": {"coordinates":[73.57091200000001,16.06643],"type":"Point"}
}