{
  "type": "Feature",
  "properties": {
    "iso:country":"IN",
    "ks:ks_name":"Sadikhanr Diar",
    "ks:ks_pop":2120,
    "ks:ks_type":"VILLAGE",
    "ks:ks_uagg_main":0,
    "name:eng_x_preferred":[
        "Sadikhanr Diar"
    ],
    "wof:name":"Sadikhanr Diar",
    "wof:placetype":"neighbourhood",
    "wof:population":2120
},
  "geometry": {"coordinates":[88.650424,24.129087],"type":"Point"}
}