{
  "type": "Feature",
  "properties": {
    "gn:admin1_code":"37",
    "gn:admin2_code":"409.0",
    "gn:asciiname":"Salepur",
    "gn:country_code":"IN",
    "gn:dem":281,
    "gn:feature_class":"P",
    "gn:feature_code":"PPL",
    "gn:name":"S\u0101lepur",
    "gn:population":0,
    "gn:timezone":"Asia/Kolkata",
    "iso:country":"IN",
    "name:ceb_x_preferred":[
        "S\u0101lepur"
    ],
    "name:ori_x_preferred":[
        "\u0b38\u0b3e\u0b32\u0b47\u0b2a\u0b41\u0b30"
    ],
    "name:swe_x_preferred":[
        "S\u0101lepur"
    ],
    "wof:name":"Salepur",
    "wof:placetype":"locality"
},
  "geometry": {"coordinates":[81.37191999999997,21.5754],"type":"Point"}
}