{
  "type": "Feature",
  "properties": {
    "iso:country":"IN",
    "ks:ks_name":"No 1 Tezigaon",
    "ks:ks_pop":668,
    "ks:ks_type":"HABITATION",
    "name:eng_x_preferred":[
        "No 1 Tezigaon"
    ],
    "wof:name":"No 1 Tezigaon",
    "wof:placetype":"locality",
    "wof:population":668
},
  "geometry": {"coordinates":[95.66118,27.662534],"type":"Point"}
}