{
  "type": "Feature",
  "properties": {
    "iso:country":"IN",
    "ks:ks_name":"Malia",
    "ks:ks_pop":3948,
    "ks:ks_type":"VILLAGE",
    "ks:ks_uagg_main":0,
    "name:eng_x_preferred":[
        "Malia"
    ],
    "wof:name":"Malia",
    "wof:placetype":"neighbourhood",
    "wof:population":3948
},
  "geometry": {"coordinates":[88.140281,22.824059],"type":"Point"}
}