{
  "type": "Feature",
  "properties": {
    "gn:admin1_code":"11",
    "gn:admin2_code":"27.0",
    "gn:asciiname":"Palohan",
    "gn:country_code":"IN",
    "gn:dem":1034,
    "gn:feature_class":"P",
    "gn:feature_code":"PPL",
    "gn:name":"Palohan",
    "gn:population":0,
    "gn:timezone":"Asia/Kolkata",
    "iso:country":"IN",
    "wof:name":"Palohan",
    "wof:placetype":"locality"
},
  "geometry": {"coordinates":[76.83740999999998,31.86849],"type":"Point"}
}