{
  "type": "Feature",
  "properties": {
    "iso:country":"IN",
    "ks:ks_name":"Brathla Nibri",
    "ks:ks_pop":741,
    "ks:ks_type":"VILLAGE",
    "name:eng_x_preferred":[
        "Brathla Nibri"
    ],
    "wof:name":"Brathla Nibri",
    "wof:placetype":"locality",
    "wof:population":741
},
  "geometry": {"coordinates":[78.60113,28.186287],"type":"Point"}
}