{
  "type": "Feature",
  "properties": {
    "iso:country":"IN",
    "ks:ks_name":"Waila",
    "ks:ks_pop":399,
    "ks:ks_type":"VILLAGE",
    "name:eng_x_preferred":[
        "Waila"
    ],
    "wof:name":"Waila",
    "wof:placetype":"locality",
    "wof:population":399
},
  "geometry": {"coordinates":[79.962086,29.243552],"type":"Point"}
}