{
  "type": "Feature",
  "properties": {
    "iso:country":"IN",
    "ks:ks_name":"Jhintikabari",
    "ks:ks_pop":63,
    "ks:ks_type":"HABITATION",
    "name:eng_x_preferred":[
        "Jhintikabari"
    ],
    "wof:name":"Jhintikabari",
    "wof:placetype":"locality",
    "wof:population":63
},
  "geometry": {"coordinates":[84.736007,20.400262],"type":"Point"}
}