{
  "type": "Feature",
  "properties": {
    "gn:admin1_code":"23.0",
    "gn:admin2_code":"43.0",
    "gn:asciiname":"Roshan Shahwala",
    "gn:country_code":"IN",
    "gn:dem":210,
    "gn:feature_class":"P",
    "gn:feature_code":"PPL",
    "gn:name":"Roshan Sh\u0101hw\u0101la",
    "gn:population":0,
    "gn:timezone":"Asia/Kolkata",
    "iso:country":"IN",
    "name:und_x_variant":[
        "Roshan Sh\u0101hw\u0101la",
        "B\u016btar"
    ],
    "wof:name":"Roshan Shahwala",
    "wof:placetype":"locality"
},
  "geometry": {"coordinates":[74.99691,31.04035],"type":"Point"}
}