{
  "type": "Feature",
  "properties": {
    "gn:admin1_code":"21",
    "gn:admin2_code":"394.0",
    "gn:asciiname":"Jhagrahi",
    "gn:country_code":"IN",
    "gn:dem":306,
    "gn:feature_class":"P",
    "gn:feature_code":"PPL",
    "gn:name":"Jhagr\u0101hi",
    "gn:population":0,
    "gn:timezone":"Asia/Kolkata",
    "iso:country":"IN",
    "ks:ks_alt_nam":"Jhagr\u0101hi",
    "ks:ks_name":"Jhagrahi",
    "ks:ks_type":"VILLAGE",
    "name:eng_x_preferred":[
        "Jhagrahi"
    ],
    "name:eng_x_variant":[
        "Jhagr\u0101hi"
    ],
    "wof:name":"Jhagrahi",
    "wof:placetype":"locality"
},
  "geometry": {"coordinates":[82.593211,20.521016],"type":"Point"}
}