{
  "type": "Feature",
  "properties": {
    "gn:admin1_code":"11.0",
    "gn:admin2_code":"32.0",
    "gn:asciiname":"Shomlati",
    "gn:country_code":"IN",
    "gn:dem":1250,
    "gn:feature_class":"P",
    "gn:feature_code":"PPL",
    "gn:name":"Shoml\u0101ti",
    "gn:population":0,
    "gn:timezone":"Asia/Kolkata",
    "iso:country":"IN",
    "wof:name":"Shomlati",
    "wof:placetype":"locality"
},
  "geometry": {"coordinates":[77.13571999999998,30.80205],"type":"Point"}
}