{
  "type": "Feature",
  "properties": {
    "iso:country":"IN",
    "ks:ks_alt_nam":"Pokkancherry palam",
    "ks:ks_name":"Pokkancherry Palam",
    "ks:ks_pop":422,
    "ks:ks_type":"HABITATION",
    "name:eng_x_preferred":[
        "Pokkancherry Palam"
    ],
    "wof:name":"Pokkancherry Palam",
    "wof:placetype":"locality",
    "wof:population":422
},
  "geometry": {"coordinates":[76.054174,10.486496],"type":"Point"}
}