{
  "type": "Feature",
  "properties": {
    "iso:country":"IN",
    "ks:ks_alt_nam":"PITAMBARA DIH",
    "ks:ks_name":"Pitambara Dih",
    "ks:ks_pop":405,
    "ks:ks_type":"HABITATION",
    "name:eng_x_preferred":[
        "Pitambara Dih"
    ],
    "wof:name":"Pitambara Dih",
    "wof:placetype":"locality",
    "wof:population":405
},
  "geometry": {"coordinates":[84.53631,24.617321],"type":"Point"}
}