{
  "type": "Feature",
  "properties": {
    "gn:admin1_code":"10.0",
    "gn:admin2_code":"74.0",
    "gn:asciiname":"Imratpur Khurd",
    "gn:country_code":"IN",
    "gn:dem":245,
    "gn:feature_class":"P",
    "gn:feature_code":"PPL",
    "gn:name":"Imratpur Khurd",
    "gn:population":0,
    "gn:timezone":"Asia/Kolkata",
    "iso:country":"IN",
    "wof:name":"Imratpur Khurd",
    "wof:placetype":"locality"
},
  "geometry": {"coordinates":[77.06839000000002,29.60342],"type":"Point"}
}