{
  "type": "Feature",
  "properties": {
    "iso:country":"IN",
    "ks:ks_alt_nam":"Bhatthi faliya",
    "ks:ks_name":"Bhatthi Faliya",
    "ks:ks_pop":110,
    "ks:ks_type":"HABITATION",
    "ks:ks_uagg_main":0,
    "name:eng_x_preferred":[
        "Bhatthi Faliya"
    ],
    "wof:name":"Bhatthi Faliya",
    "wof:placetype":"neighbourhood",
    "wof:population":110
},
  "geometry": {"coordinates":[73.19497200000001,20.536955],"type":"Point"}
}