{
  "type": "Feature",
  "properties": {
    "gn:admin1_code":"37.0",
    "gn:admin2_code":"410.0",
    "gn:asciiname":"Kadlimuda",
    "gn:country_code":"IN",
    "gn:dem":281,
    "gn:feature_class":"P",
    "gn:feature_code":"PPL",
    "gn:name":"Kadlimuda",
    "gn:population":0,
    "gn:timezone":"Asia/Kolkata",
    "iso:country":"IN",
    "wof:name":"Kadlimuda",
    "wof:placetype":"locality"
},
  "geometry": {"coordinates":[82.59971,19.9444],"type":"Point"}
}