{
  "type": "Feature",
  "properties": {
    "iso:country":"IN",
    "ks:ks_name":"Loona Kalan",
    "ks:ks_pop":604,
    "ks:ks_type":"VILLAGE",
    "name:eng_x_preferred":[
        "Loona Kalan"
    ],
    "wof:name":"Loona Kalan",
    "wof:placetype":"locality",
    "wof:population":604
},
  "geometry": {"coordinates":[71.574901,26.642797],"type":"Point"}
}