{
  "type": "Feature",
  "properties": {
    "gn:admin1_code":"35.0",
    "gn:admin2_code":"457.0",
    "gn:asciiname":"Mangoli Kalan",
    "gn:country_code":"IN",
    "gn:dem":294,
    "gn:feature_class":"P",
    "gn:feature_code":"PPL",
    "gn:name":"Mangol\u012b Kal\u0101n",
    "gn:population":0,
    "gn:timezone":"Asia/Kolkata",
    "iso:country":"IN",
    "wof:name":"Mangoli Kalan",
    "wof:placetype":"locality"
},
  "geometry": {"coordinates":[80.24245999999999,21.65402000000001],"type":"Point"}
}