{
  "type": "Feature",
  "properties": {
    "iso:country":"IN",
    "ks:ks_alt_nam":"Khurhuri\u0101",
    "ks:ks_name":"Khurhuria",
    "ks:ks_pop":0,
    "ks:ks_type":"VILLAGE",
    "name:eng_x_preferred":[
        "Khurhuria"
    ],
    "name:eng_x_variant":[
        "Khurhuri\u0101"
    ],
    "wof:name":"Khurhuria",
    "wof:placetype":"locality",
    "wof:population":0
},
  "geometry": {"coordinates":[84.41207300000001,27.273359],"type":"Point"}
}