{
  "type": "Feature",
  "properties": {
    "gn:admin1_code":"2.0",
    "gn:admin2_code":"544.0",
    "gn:asciiname":"Machipuram",
    "gn:country_code":"IN",
    "gn:dem":990,
    "gn:feature_class":"P",
    "gn:feature_code":"PPL",
    "gn:name":"Machipuram",
    "gn:population":0,
    "gn:timezone":"Asia/Kolkata",
    "iso:country":"IN",
    "wof:name":"Machipuram",
    "wof:placetype":"locality"
},
  "geometry": {"coordinates":[82.44433000000002,18.31904],"type":"Point"}
}