{
  "type": "Feature",
  "properties": {
    "iso:country":"IN",
    "ks:ks_name":"Chhadiyali",
    "ks:ks_pop":651,
    "ks:ks_type":"VILLAGE",
    "name:eng_x_preferred":[
        "Chhadiyali"
    ],
    "wof:name":"Chhadiyali",
    "wof:placetype":"locality",
    "wof:population":651
},
  "geometry": {"coordinates":[71.429773,22.464853],"type":"Point"}
}