{
  "type": "Feature",
  "properties": {
    "gn:admin1_code":"21.0",
    "gn:admin2_code":"388.0",
    "gn:asciiname":"Amrutulu",
    "gn:country_code":"IN",
    "gn:dem":107,
    "gn:feature_class":"P",
    "gn:feature_code":"PPL",
    "gn:name":"Amrutulu",
    "gn:population":0,
    "gn:timezone":"Asia/Kolkata",
    "iso:country":"IN",
    "name:fas_x_preferred":[
        "\u0627\u0645\u0631\u0627\u0637\u0644\u0648\u0639"
    ],
    "wof:name":"Amrutulu",
    "wof:placetype":"locality"
},
  "geometry": {"coordinates":[84.39310999999999,19.72235],"type":"Point"}
}