{
  "type": "Feature",
  "properties": {
    "iso:country":"IN",
    "ks:ks_name":"Bhimaram",
    "ks:ks_pop":558,
    "ks:ks_type":"VILLAGE",
    "name:eng_x_preferred":[
        "Bhimaram"
    ],
    "wof:name":"Bhimaram",
    "wof:placetype":"locality",
    "wof:population":558
},
  "geometry": {"coordinates":[82.27920899999999,18.122381],"type":"Point"}
}