{
  "type": "Feature",
  "properties": {
    "iso:country":"IN",
    "ks:ks_name":"Kattayankadu Ukkadai",
    "ks:ks_pop":589,
    "ks:ks_type":"VILLAGE",
    "name:eng_x_preferred":[
        "Kattayankadu Ukkadai"
    ],
    "wof:name":"Kattayankadu Ukkadai",
    "wof:placetype":"locality",
    "wof:population":589
},
  "geometry": {"coordinates":[79.25354799999999,10.373234],"type":"Point"}
}