{
  "type": "Feature",
  "properties": {
    "iso:country":"IN",
    "ks:ks_name":"Glata",
    "ks:ks_pop":214,
    "ks:ks_type":"VILLAGE",
    "name:eng_x_preferred":[
        "Glata"
    ],
    "wof:name":"Glata",
    "wof:placetype":"locality",
    "wof:population":214
},
  "geometry": {"coordinates":[83.840287,20.443463],"type":"Point"}
}