{
  "type": "Feature",
  "properties": {
    "iso:country":"IN",
    "ks:ks_name":"Ramanujapuram",
    "ks:ks_pop":45,
    "ks:ks_type":"VILLAGE",
    "name:eng_x_preferred":[
        "Ramanujapuram"
    ],
    "wof:name":"Ramanujapuram",
    "wof:placetype":"locality",
    "wof:population":45
},
  "geometry": {"coordinates":[78.618827,18.335768],"type":"Point"}
}