{
  "type": "Feature",
  "properties": {
    "iso:country":"IN",
    "ks:ks_alt_nam":"Purastamp\u0101li",
    "ks:ks_name":"Purastampali",
    "ks:ks_type":"VILLAGE",
    "name:eng_x_preferred":[
        "Purastampali"
    ],
    "name:eng_x_variant":[
        "Purastamp\u0101li"
    ],
    "wof:name":"Purastampali",
    "wof:placetype":"locality"
},
  "geometry": {"coordinates":[84.09515500000001,20.958251],"type":"Point"}
}