{
  "type": "Feature",
  "properties": {
    "gn:admin1_code":"36.0",
    "gn:admin2_code":"182.0",
    "gn:asciiname":"Aksi",
    "gn:country_code":"IN",
    "gn:dem":107,
    "gn:feature_class":"P",
    "gn:feature_code":"PPL",
    "gn:name":"Aksi",
    "gn:population":0,
    "gn:timezone":"Asia/Kolkata",
    "iso:country":"IN",
    "name:ceb_x_preferred":[
        "Aksi"
    ],
    "name:ces_x_preferred":[
        "Aksi"
    ],
    "name:deu_x_preferred":[
        "Aksi"
    ],
    "name:est_x_preferred":[
        "Aksi"
    ],
    "name:fra_x_preferred":[
        "Aksi"
    ],
    "name:hye_x_preferred":[
        "\u0537\u056f\u057d\u056b \u056f\u0572\u0566\u056b"
    ],
    "name:lav_x_preferred":[
        "Aksi"
    ],
    "name:nno_x_preferred":[
        "Aksi"
    ],
    "name:nor_x_preferred":[
        "Aksi"
    ],
    "name:pol_x_preferred":[
        "Aksi"
    ],
    "name:rus_x_preferred":[
        "\u042d\u043a\u0441\u0438"
    ],
    "name:spa_x_preferred":[
        "Aksi"
    ],
    "name:swe_x_preferred":[
        "Lilla Vrang\u00f6"
    ],
    "wof:name":"Aksi",
    "wof:placetype":"locality"
},
  "geometry": {"coordinates":[82.38239,27.32932000000001],"type":"Point"}
}