{
  "type": "Feature",
  "properties": {
    "iso:country":"IN",
    "ks:ks_name":"Dalai Para",
    "ks:ks_pop":30,
    "ks:ks_type":"HABITATION",
    "name:eng_x_preferred":[
        "Dalai Para"
    ],
    "wof:name":"Dalai Para",
    "wof:placetype":"locality",
    "wof:population":30
},
  "geometry": {"coordinates":[91.61853499999999,23.343916],"type":"Point"}
}