{
  "type": "Feature",
  "properties": {
    "gn:admin1_code":"19.0",
    "gn:admin2_code":"571.0",
    "gn:asciiname":"Hemagiripalya",
    "gn:country_code":"IN",
    "gn:dem":831,
    "gn:feature_class":"P",
    "gn:feature_code":"PPL",
    "gn:name":"Hemagirip\u0101lya",
    "gn:population":0,
    "gn:timezone":"Asia/Kolkata",
    "iso:country":"IN",
    "wof:name":"Hemagiripalya",
    "wof:placetype":"locality"
},
  "geometry": {"coordinates":[77.07491999999998,13.13174],"type":"Point"}
}