{
  "type": "Feature",
  "properties": {
    "iso:country":"IN",
    "ks:ks_name":"Lambaditanda",
    "ks:ks_pop":283,
    "ks:ks_type":"HABITATION",
    "name:eng_x_preferred":[
        "Lambaditanda"
    ],
    "wof:name":"Lambaditanda",
    "wof:placetype":"locality",
    "wof:population":283
},
  "geometry": {"coordinates":[78.866411,19.513151],"type":"Point"}
}