{
  "type": "Feature",
  "properties": {
    "iso:country":"IN",
    "ks:ks_alt_nam":"Boga tola",
    "ks:ks_name":"Boga Tola",
    "ks:ks_pop":117,
    "ks:ks_type":"HABITATION",
    "name:eng_x_preferred":[
        "Boga Tola"
    ],
    "wof:name":"Boga Tola",
    "wof:placetype":"locality",
    "wof:population":117
},
  "geometry": {"coordinates":[80.54218899999999,20.354896],"type":"Point"}
}