{
  "type": "Feature",
  "properties": {
    "iso:country":"IN",
    "ks:ks_name":"Harizen Tola",
    "ks:ks_pop":345,
    "ks:ks_type":"HABITATION",
    "name:eng_x_preferred":[
        "Harizen Tola"
    ],
    "wof:name":"Harizen Tola",
    "wof:placetype":"locality",
    "wof:population":345
},
  "geometry": {"coordinates":[86.145938,25.455973],"type":"Point"}
}