{
  "type": "Feature",
  "properties": {
    "iso:country":"IN",
    "ks:ks_name":"Kendige",
    "ks:ks_pop":442,
    "ks:ks_type":"HABITATION",
    "name:eng_x_preferred":[
        "Kendige"
    ],
    "wof:name":"Kendige",
    "wof:placetype":"locality",
    "wof:population":442
},
  "geometry": {"coordinates":[74.399963,14.616421],"type":"Point"}
}