{
  "type": "Feature",
  "properties": {
    "gn:admin1_code":"36",
    "gn:admin2_code":"191.0",
    "gn:asciiname":"Gaddopur",
    "gn:country_code":"IN",
    "gn:dem":88,
    "gn:feature_class":"P",
    "gn:feature_code":"PPL",
    "gn:name":"Gaddopur",
    "gn:population":0,
    "gn:timezone":"Asia/Kolkata",
    "iso:country":"IN",
    "ks:ks_name":"Gaddopur",
    "ks:ks_pop":530,
    "ks:ks_type":"VILLAGE",
    "ks:ks_uagg_main":0,
    "name:eng_x_preferred":[
        "Gaddopur"
    ],
    "name:hin_x_preferred":[
        "\u0917\u0926\u094d\u0926\u094b\u092a\u0941\u0930"
    ],
    "wof:name":"Gaddopur",
    "wof:placetype":"neighbourhood",
    "wof:population":530
},
  "geometry": {"coordinates":[82.778007,26.151852],"type":"Point"}
}