{
  "type": "Feature",
  "properties": {
    "gn:admin1_code":"24",
    "gn:admin2_code":"107.0",
    "gn:asciiname":"Khubnagar",
    "gn:country_code":"IN",
    "gn:dem":323,
    "gn:feature_class":"P",
    "gn:feature_code":"PPL",
    "gn:name":"Kh\u016bbnagar",
    "gn:population":0,
    "gn:timezone":"Asia/Kolkata",
    "iso:country":"IN",
    "ks:ks_name":"Khoobnagar",
    "ks:ks_pop":1182,
    "ks:ks_type":"VILLAGE",
    "name:eng_x_preferred":[
        "Khoobnagar"
    ],
    "name:eng_x_variant":[
        "Khubnagar"
    ],
    "wof:name":"Khoobnagar",
    "wof:placetype":"locality",
    "wof:population":1182
},
  "geometry": {"coordinates":[77.10679500000001,26.475392],"type":"Point"}
}