{
  "type": "Feature",
  "properties": {
    "gn:admin1_code":"24",
    "gn:admin2_code":"107.0",
    "gn:asciiname":"Khubnagar",
    "gn:country_code":"IN",
    "gn:dem":323,
    "gn:feature_class":"P",
    "gn:feature_code":"PPL",
    "gn:name":"Kh\u016bbnagar",
    "gn:population":0,
    "gn:timezone":"Asia/Kolkata",
    "iso:country":"IN",
    "wof:name":"Khubnagar",
    "wof:placetype":"locality"
},
  "geometry": {"coordinates":[77.10561,26.47422000000001],"type":"Point"}
}