{
  "type": "Feature",
  "properties": {
    "iso:country":"IN",
    "ks:ks_name":"Kodabhata",
    "ks:ks_pop":298,
    "ks:ks_type":"HABITATION",
    "name:eng_x_preferred":[
        "Kodabhata"
    ],
    "wof:name":"Kodabhata",
    "wof:placetype":"locality",
    "wof:population":298
},
  "geometry": {"coordinates":[82.451786,20.347062],"type":"Point"}
}