{
  "type": "Feature",
  "properties": {
    "iso:country":"IN",
    "ks:ks_name":"Sakriya Tala",
    "ks:ks_pop":913,
    "ks:ks_type":"VILLAGE",
    "name:eng_x_preferred":[
        "Sakriya Tala"
    ],
    "wof:name":"Sakriya Tala",
    "wof:placetype":"locality",
    "wof:population":913
},
  "geometry": {"coordinates":[71.2829,25.384465],"type":"Point"}
}