{
  "type": "Feature",
  "properties": {
    "iso:country":"IN",
    "ks:ks_name":"Barimahulpada",
    "ks:ks_pop":13,
    "ks:ks_type":"VILLAGE",
    "name:eng_x_preferred":[
        "Barimahulpada"
    ],
    "wof:name":"Barimahulpada",
    "wof:placetype":"locality",
    "wof:population":13
},
  "geometry": {"coordinates":[84.414755,19.158248],"type":"Point"}
}