{
  "type": "Feature",
  "properties": {
    "gn:admin1_code":"25.0",
    "gn:admin2_code":"605.0",
    "gn:asciiname":"Sundarampalli",
    "gn:country_code":"IN",
    "gn:dem":399,
    "gn:feature_class":"P",
    "gn:feature_code":"PPL",
    "gn:name":"Sundarampalli",
    "gn:population":0,
    "gn:timezone":"Asia/Kolkata",
    "iso:country":"IN",
    "wof:name":"Sundarampalli",
    "wof:placetype":"locality"
},
  "geometry": {"coordinates":[78.45458000000001,12.40656],"type":"Point"}
}