{
  "type": "Feature",
  "properties": {
    "iso:country":"IN",
    "ks:ks_alt_nam":"Sakomatha SPP 6 2",
    "ks:ks_name":"Sakomatha Spp 6 2",
    "ks:ks_pop":596,
    "ks:ks_type":"HABITATION",
    "name:eng_x_preferred":[
        "Sakomatha Spp 6 2"
    ],
    "wof:name":"Sakomatha Spp 6 2",
    "wof:placetype":"locality",
    "wof:population":596
},
  "geometry": {"coordinates":[93.12513300000001,26.76072],"type":"Point"}
}