{
  "type": "Feature",
  "properties": {
    "iso:country":"IN",
    "ks:ks_name":"Bandasale",
    "ks:ks_pop":200,
    "ks:ks_type":"HABITATION",
    "name:eng_x_preferred":[
        "Bandasale"
    ],
    "wof:name":"Bandasale",
    "wof:placetype":"locality",
    "wof:population":200
},
  "geometry": {"coordinates":[74.934236,12.936488],"type":"Point"}
}