{
  "type": "Feature",
  "properties": {
    "iso:country":"IN",
    "ks:ks_name":"Mowai",
    "ks:ks_pop":1709,
    "ks:ks_type":"VILLAGE",
    "name:eng_x_preferred":[
        "Mowai"
    ],
    "wof:name":"Mowai",
    "wof:placetype":"locality",
    "wof:population":1709
},
  "geometry": {"coordinates":[74.89521499999999,23.809511],"type":"Point"}
}