{
  "type": "Feature",
  "properties": {
    "iso:country":"IN",
    "ks:ks_name":"Payarwadi",
    "ks:ks_pop":133,
    "ks:ks_type":"HABITATION",
    "name:eng_x_preferred":[
        "Payarwadi"
    ],
    "wof:name":"Payarwadi",
    "wof:placetype":"locality",
    "wof:population":133
},
  "geometry": {"coordinates":[73.524961,17.627914],"type":"Point"}
}