{
  "type": "Feature",
  "properties": {
    "iso:country":"IN",
    "ks:ks_name":"Disale Wasti",
    "ks:ks_pop":119,
    "ks:ks_type":"HABITATION",
    "name:eng_x_preferred":[
        "Disale Wasti"
    ],
    "wof:name":"Disale Wasti",
    "wof:placetype":"locality",
    "wof:population":119
},
  "geometry": {"coordinates":[75.84855899999999,18.543164],"type":"Point"}
}