{
  "type": "Feature",
  "properties": {
    "gn:admin1_code":"36.0",
    "gn:admin2_code":"180.0",
    "gn:asciiname":"Gaurdin Purwa",
    "gn:country_code":"IN",
    "gn:dem":109,
    "gn:feature_class":"P",
    "gn:feature_code":"PPL",
    "gn:name":"Gaurdin Purwa",
    "gn:population":0,
    "gn:timezone":"Asia/Kolkata",
    "iso:country":"IN",
    "wof:name":"Gaurdin Purwa",
    "wof:placetype":"locality"
},
  "geometry": {"coordinates":[81.55015999999998,27.22059],"type":"Point"}
}