{
  "type": "Feature",
  "properties": {
    "gn:admin1_code":"19",
    "gn:admin2_code":"559.0",
    "gn:asciiname":"Mallapur",
    "gn:country_code":"IN",
    "gn:dem":504,
    "gn:feature_class":"P",
    "gn:feature_code":"PPL",
    "gn:name":"Mall\u0101pur",
    "gn:population":0,
    "gn:timezone":"Asia/Kolkata",
    "iso:country":"IN",
    "name:pam_x_preferred":[
        "Mallapur"
    ],
    "wof:name":"Mallapur",
    "wof:placetype":"locality"
},
  "geometry": {"coordinates":[76.77393000000002,16.21861],"type":"Point"}
}