{
  "type": "Feature",
  "properties": {
    "iso:country":"IN",
    "ks:ks_name":"Kathra Naopara",
    "ks:ks_pop":0,
    "ks:ks_type":"VILLAGE",
    "name:eng_x_preferred":[
        "Kathra Naopara"
    ],
    "wof:name":"Kathra Naopara",
    "wof:placetype":"locality",
    "wof:population":0
},
  "geometry": {"coordinates":[88.372491,25.074389],"type":"Point"}
}