{
  "type": "Feature",
  "properties": {
    "iso:country":"IN",
    "ks:ks_name":"Limbejeddi",
    "ks:ks_pop":24,
    "ks:ks_type":"HABITATION",
    "name:eng_x_preferred":[
        "Limbejeddi"
    ],
    "wof:name":"Limbejeddi",
    "wof:placetype":"locality",
    "wof:population":24
},
  "geometry": {"coordinates":[74.778387,14.849439],"type":"Point"}
}