{
  "type": "Feature",
  "properties": {
    "iso:country":"IN",
    "ks:ks_name":"Jhankarpali",
    "ks:ks_pop":299,
    "ks:ks_type":"HABITATION",
    "name:eng_x_preferred":[
        "Jhankarpali"
    ],
    "wof:name":"Jhankarpali",
    "wof:placetype":"locality",
    "wof:population":299
},
  "geometry": {"coordinates":[83.998931,21.377906],"type":"Point"}
}