{
  "type": "Feature",
  "properties": {
    "iso:country":"IN",
    "ks:ks_name":"Dakhinkuchi",
    "ks:ks_pop":1846,
    "ks:ks_type":"VILLAGE",
    "name:eng_x_preferred":[
        "Dakhinkuchi"
    ],
    "wof:name":"Dakhinkuchi",
    "wof:placetype":"locality",
    "wof:population":1846
},
  "geometry": {"coordinates":[91.42960600000001,26.765364],"type":"Point"}
}