{
  "type": "Feature",
  "properties": {
    "iso:country":"IN",
    "ks:ks_name":"Kalguballi",
    "ks:ks_pop":58,
    "ks:ks_type":"HABITATION",
    "name:eng_x_preferred":[
        "Kalguballi"
    ],
    "wof:name":"Kalguballi",
    "wof:placetype":"locality",
    "wof:population":58
},
  "geometry": {"coordinates":[74.83360399999999,14.376556],"type":"Point"}
}