{
  "type": "Feature",
  "properties": {
    "iso:country":"IN",
    "ks:ks_name":"Ghandiyalwalla",
    "ks:ks_pop":284,
    "ks:ks_type":"VILLAGE",
    "name:eng_x_preferred":[
        "Ghandiyalwalla"
    ],
    "wof:name":"Ghandiyalwalla",
    "wof:placetype":"locality",
    "wof:population":284
},
  "geometry": {"coordinates":[78.90725,29.88749],"type":"Point"}
}