{
  "type": "Feature",
  "properties": {
    "gn:admin1_code":"19.0",
    "gn:admin2_code":"567.0",
    "gn:asciiname":"Bevinahalli",
    "gn:country_code":"IN",
    "gn:dem":574,
    "gn:feature_class":"P",
    "gn:feature_code":"PPL",
    "gn:name":"Bevinahalli",
    "gn:population":0,
    "gn:timezone":"Asia/Kolkata",
    "iso:country":"IN",
    "wof:name":"Bevinahalli",
    "wof:placetype":"locality"
},
  "geometry": {"coordinates":[75.85795999999998,14.74511],"type":"Point"}
}