{
  "type": "Feature",
  "properties": {
    "iso:country":"IN",
    "ks:ks_name":"Baramasia",
    "ks:ks_pop":20,
    "ks:ks_type":"VILLAGE",
    "name:eng_x_preferred":[
        "Baramasia"
    ],
    "wof:name":"Baramasia",
    "wof:placetype":"locality",
    "wof:population":20
},
  "geometry": {"coordinates":[86.293886,24.082555],"type":"Point"}
}