{
  "type": "Feature",
  "properties": {
    "gn:country":"IN",
    "iso:country":"IN",
    "ks:ks_name":"Cansaulim",
    "ks:ks_pop":2333,
    "ks:ks_type":"VILLAGE",
    "ks:ks_uagg_main":0,
    "name:eng_x_preferred":[
        "Cansaulim"
    ],
    "qs:name":"Cansaulim",
    "qs:name_adm0":"India",
    "qs:name_adm1":"Goa",
    "qs:photos":71,
    "qs:photos_1k":14,
    "qs:photos_9k":1,
    "qs:photos_9r":2,
    "qs:photos_all":71,
    "qs:photos_sr":2,
    "qs:placetype":"Town",
    "qs:pop_sr":"0",
    "wof:name":"Cansaulim",
    "wof:placetype":"neighbourhood",
    "wof:population":2333
},
  "geometry": {"coordinates":[73.89952700000001,15.346997],"type":"Point"}
}