{
  "type": "Feature",
  "properties": {
    "iso:country":"IN",
    "ks:ks_name":"Kottayi-II",
    "ks:ks_pop":8831,
    "ks:ks_type":"VILLAGE",
    "ks:ks_uagg_main":0,
    "name:eng_x_preferred":[
        "Kottayi-II"
    ],
    "wof:name":"Kottayi-II",
    "wof:placetype":"locality",
    "wof:population":8831
},
  "geometry": {"coordinates":[76.54973200000001,10.764835],"type":"Point"}
}