{
  "type": "Feature",
  "properties": {
    "iso:country":"IN",
    "ks:ks_name":"Dohar",
    "ks:ks_type":"VILLAGE",
    "name:eng_x_preferred":[
        "Dohar"
    ],
    "wof:name":"Dohar",
    "wof:placetype":"neighbourhood"
},
  "geometry": {"coordinates":[75.855892,31.943447],"type":"Point"}
}