{
  "type": "Feature",
  "properties": {
    "gn:admin1_code":"11",
    "gn:admin2_code":"25.0",
    "gn:asciiname":"Pamo",
    "gn:country_code":"IN",
    "gn:dem":3759,
    "gn:feature_class":"P",
    "gn:feature_code":"PPL",
    "gn:name":"Pamo",
    "gn:population":0,
    "gn:timezone":"Asia/Kolkata",
    "iso:country":"IN",
    "wof:name":"Pamo",
    "wof:placetype":"locality"
},
  "geometry": {"coordinates":[77.92797,32.36272],"type":"Point"}
}