{
  "type": "Feature",
  "properties": {
    "iso:country":"IN",
    "ks:ks_name":"Tadwan Gaon",
    "ks:ks_pop":59,
    "ks:ks_type":"VILLAGE",
    "name:eng_x_preferred":[
        "Tadwan Gaon"
    ],
    "wof:name":"Tadwan Gaon",
    "wof:placetype":"locality",
    "wof:population":59
},
  "geometry": {"coordinates":[78.101905,30.589197],"type":"Point"}
}