{
  "type": "Feature",
  "properties": {
    "gn:admin1_code":"11",
    "gn:admin2_code":"30.0",
    "gn:asciiname":"Ropa",
    "gn:country_code":"IN",
    "gn:dem":687,
    "gn:feature_class":"P",
    "gn:feature_code":"PPL",
    "gn:name":"Ropa",
    "gn:population":0,
    "gn:timezone":"Asia/Kolkata",
    "iso:country":"IN",
    "wof:name":"Ropa",
    "wof:placetype":"locality"
},
  "geometry": {"coordinates":[76.8419,31.38708],"type":"Point"}
}