{
  "type": "Feature",
  "properties": {
    "iso:country":"IN",
    "ks:ks_name":"Kanda Maikhura",
    "ks:ks_pop":577,
    "ks:ks_type":"HABITATION",
    "name:eng_x_preferred":[
        "Kanda Maikhura"
    ],
    "wof:name":"Kanda Maikhura",
    "wof:placetype":"locality",
    "wof:population":577
},
  "geometry": {"coordinates":[79.27010199999999,30.274579],"type":"Point"}
}