{
  "type": "Feature",
  "properties": {
    "iso:country":"IN",
    "ks:ks_alt_nam":"panditan",
    "ks:ks_name":"Panditan",
    "ks:ks_pop":312,
    "ks:ks_type":"HABITATION",
    "name:eng_x_preferred":[
        "Panditan"
    ],
    "wof:name":"Panditan",
    "wof:placetype":"locality",
    "wof:population":312
},
  "geometry": {"coordinates":[81.792312,25.677093],"type":"Point"}
}