{
  "type": "Feature",
  "properties": {
    "gn:admin1_code":"40.0",
    "gn:admin2_code":"539",
    "gn:asciiname":"Tumkuhta",
    "gn:country_code":"IN",
    "gn:dem":529,
    "gn:feature_class":"P",
    "gn:feature_code":"PPL",
    "gn:name":"T\u016bmkuhta",
    "gn:population":0,
    "gn:timezone":"Asia/Kolkata",
    "iso:country":"IN",
    "wof:name":"Tumkuhta",
    "wof:placetype":"neighbourhood"
},
  "geometry": {"coordinates":[78.69855,17.59244],"type":"Point"}
}