{
  "type": "Feature",
  "properties": {
    "iso:country":"IN",
    "ks:ks_alt_nam":"Mulgam Nichala faliya",
    "ks:ks_name":"Mulgam Nichala Faliya",
    "ks:ks_pop":27,
    "ks:ks_type":"HABITATION",
    "name:eng_x_preferred":[
        "Mulgam Nichala Faliya"
    ],
    "wof:name":"Mulgam Nichala Faliya",
    "wof:placetype":"locality",
    "wof:population":27
},
  "geometry": {"coordinates":[73.38687899999999,20.459587],"type":"Point"}
}