{
  "type": "Feature",
  "properties": {
    "gn:admin1_code":"19.0",
    "gn:admin2_code":"583.0",
    "gn:asciiname":"Kangondanhalli",
    "gn:country_code":"IN",
    "gn:dem":900,
    "gn:feature_class":"P",
    "gn:feature_code":"PPL",
    "gn:name":"Kangondanhalli",
    "gn:population":0,
    "gn:timezone":"Asia/Kolkata",
    "iso:country":"IN",
    "wof:name":"Kangondanhalli",
    "wof:placetype":"locality"
},
  "geometry": {"coordinates":[77.38485,13.12988],"type":"Point"}
}