{
  "type": "Feature",
  "properties": {
    "iso:country":"IN",
    "ks:ks_name":"Chungulpura",
    "ks:ks_pop":0,
    "ks:ks_type":"VILLAGE",
    "name:eng_x_preferred":[
        "Chungulpura"
    ],
    "wof:name":"Chungulpura",
    "wof:placetype":"locality",
    "wof:population":0
},
  "geometry": {"coordinates":[84.367266,26.021956],"type":"Point"}
}