{
  "type": "Feature",
  "properties": {
    "gn:admin1_code":"19.0",
    "gn:admin2_code":"582.0",
    "gn:asciiname":"Gollapalli",
    "gn:country_code":"IN",
    "gn:dem":766,
    "gn:feature_class":"P",
    "gn:feature_code":"PPL",
    "gn:name":"Gollapalli",
    "gn:population":0,
    "gn:timezone":"Asia/Kolkata",
    "iso:country":"IN",
    "wof:name":"Gollapalli",
    "wof:placetype":"locality"
},
  "geometry": {"coordinates":[78.08983000000001,13.53388],"type":"Point"}
}