{
  "type": "Feature",
  "properties": {
    "gn:admin1_code":"24.0",
    "gn:admin2_code":"124.0",
    "gn:asciiname":"Moera",
    "gn:country_code":"IN",
    "gn:dem":350,
    "gn:feature_class":"P",
    "gn:feature_code":"PPL",
    "gn:name":"Moera",
    "gn:population":0,
    "gn:timezone":"Asia/Kolkata",
    "iso:country":"IN",
    "wof:name":"Moera",
    "wof:placetype":"locality"
},
  "geometry": {"coordinates":[73.55886,23.92497],"type":"Point"}
}