{
  "type": "Feature",
  "properties": {
    "gn:admin1_code":"11.0",
    "gn:admin2_code":"33.0",
    "gn:asciiname":"Sadali",
    "gn:country_code":"IN",
    "gn:dem":2327,
    "gn:feature_class":"P",
    "gn:feature_code":"PPL",
    "gn:name":"Sad\u0101li",
    "gn:population":0,
    "gn:timezone":"Asia/Kolkata",
    "iso:country":"IN",
    "name:fas_x_preferred":[
        "\u0633\u0627\u062f\u0627\u0644\u06cc"
    ],
    "name:urd_x_preferred":[
        "\u0633\u0688\u0627\u0644\u06cc"
    ],
    "wof:name":"Sadali",
    "wof:placetype":"locality"
},
  "geometry": {"coordinates":[77.69681,31.338],"type":"Point"}
}