{
  "type": "Feature",
  "properties": {
    "iso:country":"IN",
    "ks:ks_name":"Kalite",
    "ks:ks_pop":47,
    "ks:ks_type":"HABITATION",
    "name:eng_x_preferred":[
        "Kalite"
    ],
    "wof:name":"Kalite",
    "wof:placetype":"locality",
    "wof:population":47
},
  "geometry": {"coordinates":[75.940833,12.096944],"type":"Point"}
}