{
  "type": "Feature",
  "properties": {
    "iso:country":"IN",
    "ks:ks_name":"Sikandarpur Mustkil",
    "ks:ks_pop":1287,
    "ks:ks_type":"VILLAGE",
    "name:eng_x_preferred":[
        "Sikandarpur Mustkil"
    ],
    "wof:name":"Sikandarpur Mustkil",
    "wof:placetype":"neighbourhood",
    "wof:population":1287
},
  "geometry": {"coordinates":[78.001605,27.26009],"type":"Point"}
}