{
  "type": "Feature",
  "properties": {
    "iso:country":"IN",
    "ks:ks_name":"Lodha Hat",
    "ks:ks_pop":746,
    "ks:ks_type":"HABITATION",
    "name:eng_x_preferred":[
        "Lodha Hat"
    ],
    "wof:name":"Lodha Hat",
    "wof:placetype":"locality",
    "wof:population":746
},
  "geometry": {"coordinates":[88.19138,26.285411],"type":"Point"}
}