{
  "type": "Feature",
  "properties": {
    "gn:admin1_code":"36",
    "gn:admin2_code":"142.0",
    "gn:asciiname":"Dungarpur",
    "gn:country_code":"IN",
    "gn:dem":196,
    "gn:feature_class":"P",
    "gn:feature_code":"PPL",
    "gn:name":"D\u016bngarpur",
    "gn:population":0,
    "gn:timezone":"Asia/Kolkata",
    "iso:country":"IN",
    "wof:name":"Dungarpur",
    "wof:placetype":"locality"
},
  "geometry": {"coordinates":[78.03144,28.15587],"type":"Point"}
}