{
  "type": "Feature",
  "properties": {
    "iso:country":"IN",
    "ks:ks_name":"Kolanbanda",
    "ks:ks_pop":68,
    "ks:ks_type":"HABITATION",
    "name:eng_x_preferred":[
        "Kolanbanda"
    ],
    "wof:name":"Kolanbanda",
    "wof:placetype":"locality",
    "wof:population":68
},
  "geometry": {"coordinates":[82.402434,17.967437],"type":"Point"}
}