{
  "type": "Feature",
  "properties": {
    "iso:country":"IN",
    "ks:ks_alt_nam":"TIPUTAAN",
    "ks:ks_name":"Tiputaan",
    "ks:ks_pop":149,
    "ks:ks_type":"HABITATION",
    "name:eng_x_preferred":[
        "Tiputaan"
    ],
    "wof:name":"Tiputaan",
    "wof:placetype":"locality",
    "wof:population":149
},
  "geometry": {"coordinates":[84.61758,24.623335],"type":"Point"}
}