{
  "type": "Feature",
  "properties": {
    "gn:admin1_code":"25.0",
    "gn:admin2_code":"633.0",
    "gn:asciiname":"Sadaiyakavundanpudur",
    "gn:country_code":"IN",
    "gn:dem":386,
    "gn:feature_class":"P",
    "gn:feature_code":"PPL",
    "gn:name":"Sadaiyakavundanpud\u016br",
    "gn:population":0,
    "gn:timezone":"Asia/Kolkata",
    "iso:country":"IN",
    "wof:name":"Sadaiyakavundanpudur",
    "wof:placetype":"neighbourhood"
},
  "geometry": {"coordinates":[77.17977999999999,10.59287],"type":"Point"}
}