{
  "type": "Feature",
  "properties": {
    "iso:country":"IN",
    "ks:ks_name":"Barda Faliya",
    "ks:ks_pop":50,
    "ks:ks_type":"HABITATION",
    "name:eng_x_preferred":[
        "Barda Faliya"
    ],
    "wof:name":"Barda Faliya",
    "wof:placetype":"locality",
    "wof:population":50
},
  "geometry": {"coordinates":[73.33221899999999,20.57842],"type":"Point"}
}