{
  "type": "Feature",
  "properties": {
    "iso:country":"IN",
    "ks:ks_name":"Kelginmane",
    "ks:ks_pop":79,
    "ks:ks_type":"HABITATION",
    "name:eng_x_preferred":[
        "Kelginmane"
    ],
    "wof:name":"Kelginmane",
    "wof:placetype":"locality",
    "wof:population":79
},
  "geometry": {"coordinates":[74.779552,14.438444],"type":"Point"}
}