{
  "type": "Feature",
  "properties": {
    "gn:admin1_code":"34.0",
    "gn:admin2_code":"228.0",
    "gn:asciiname":"Akbar Bigha",
    "gn:country_code":"IN",
    "gn:dem":57,
    "gn:feature_class":"P",
    "gn:feature_code":"PPL",
    "gn:name":"Akbar Bigha",
    "gn:population":0,
    "gn:timezone":"Asia/Kolkata",
    "iso:country":"IN",
    "ks:ks_alt_nam":"AKBAR BIGHA",
    "ks:ks_name":"Akbar Bigha",
    "ks:ks_pop":720,
    "ks:ks_type":"HABITATION",
    "name:eng_x_preferred":[
        "Akbar Bigha"
    ],
    "wof:name":"Akbar Bigha",
    "wof:placetype":"locality",
    "wof:population":720
},
  "geometry": {"coordinates":[85.698403,25.169221],"type":"Point"}
}