{
  "type": "Feature",
  "properties": {
    "iso:country":"IN",
    "ks:ks_name":"Illipilayi",
    "ks:ks_pop":542,
    "ks:ks_type":"HABITATION",
    "name:eng_x_preferred":[
        "Illipilayi"
    ],
    "wof:name":"Illipilayi",
    "wof:placetype":"locality",
    "wof:population":542
},
  "geometry": {"coordinates":[75.869169,11.529378],"type":"Point"}
}