{
  "type": "Feature",
  "properties": {
    "iso:country":"IN",
    "ks:ks_name":"Mukundajhola",
    "ks:ks_pop":126,
    "ks:ks_type":"VILLAGE",
    "name:eng_x_preferred":[
        "Mukundajhola"
    ],
    "wof:name":"Mukundajhola",
    "wof:placetype":"locality",
    "wof:population":126
},
  "geometry": {"coordinates":[84.208946,19.383562],"type":"Point"}
}