{
  "type": "Feature",
  "properties": {
    "iso:country":"IN",
    "ks:ks_name":"Halegormane",
    "ks:ks_pop":10,
    "ks:ks_type":"HABITATION",
    "name:eng_x_preferred":[
        "Halegormane"
    ],
    "wof:name":"Halegormane",
    "wof:placetype":"locality",
    "wof:population":10
},
  "geometry": {"coordinates":[75.012299,14.086865],"type":"Point"}
}