{
  "type": "Feature",
  "properties": {
    "iso:country":"IN",
    "ks:ks_name":"Thasakpur",
    "ks:ks_pop":238,
    "ks:ks_type":"VILLAGE",
    "name:eng_x_preferred":[
        "Thasakpur"
    ],
    "wof:name":"Thasakpur",
    "wof:placetype":"locality",
    "wof:population":238
},
  "geometry": {"coordinates":[85.602405,22.685837],"type":"Point"}
}