{
  "type": "Feature",
  "properties": {
    "iso:country":"IN",
    "ks:ks_alt_nam":"RAJBHAR BASTI  PAS 2",
    "ks:ks_name":"Rajbhar Basti Pas 2",
    "ks:ks_pop":354,
    "ks:ks_type":"HABITATION",
    "name:eng_x_preferred":[
        "Rajbhar Basti Pas 2"
    ],
    "name:eng_x_variant":[
        "RAJBHAR BASTI  PAS 2"
    ],
    "wof:name":"Rajbhar Basti Pas 2",
    "wof:placetype":"locality",
    "wof:population":354
},
  "geometry": {"coordinates":[82.92989799999999,25.415015],"type":"Point"}
}