{
  "type": "Feature",
  "properties": {
    "iso:country":"IN",
    "ks:ks_name":"Gopalpurkala",
    "ks:ks_pop":638,
    "ks:ks_type":"HABITATION",
    "name:eng_x_preferred":[
        "Gopalpurkala"
    ],
    "wof:name":"Gopalpurkala",
    "wof:placetype":"locality",
    "wof:population":638
},
  "geometry": {"coordinates":[84.148723,25.889309],"type":"Point"}
}