{
  "type": "Feature",
  "properties": {
    "gn:admin1_code":"02",
    "gn:admin2_code":"552.0",
    "gn:asciiname":"Sirvel",
    "gn:country_code":"IN",
    "gn:dem":209,
    "gn:feature_class":"P",
    "gn:feature_code":"PPL",
    "gn:name":"Sirvel",
    "gn:population":0,
    "gn:timezone":"Asia/Kolkata",
    "iso:country":"IN",
    "name:und_x_variant":[
        "Sirvei",
        "Sirvel"
    ],
    "wof:name":"Sirvel",
    "wof:placetype":"locality"
},
  "geometry": {"coordinates":[78.53439,15.32102],"type":"Point"}
}