{
  "type": "Feature",
  "properties": {
    "iso:country":"IN",
    "ks:ks_alt_nam":"SC Colony Chadupp",
    "ks:ks_name":"Sc Colony Chadupp",
    "ks:ks_pop":90,
    "ks:ks_type":"HABITATION",
    "name:eng_x_preferred":[
        "Sc Colony Chadupp"
    ],
    "wof:name":"Sc Colony Chadupp",
    "wof:placetype":"locality",
    "wof:population":90
},
  "geometry": {"coordinates":[76.985587,9.357312],"type":"Point"}
}