{
  "type": "Feature",
  "properties": {
    "iso:country":"IN",
    "ks:ks_name":"Arazi Biharia",
    "ks:ks_pop":0,
    "ks:ks_type":"VILLAGE",
    "name:eng_x_preferred":[
        "Arazi Biharia"
    ],
    "wof:name":"Arazi Biharia",
    "wof:placetype":"locality",
    "wof:population":0
},
  "geometry": {"coordinates":[88.337035,23.960265],"type":"Point"}
}