{
  "type": "Feature",
  "properties": {
    "iso:country":"IN",
    "ks:ks_name":"Pazhathottam",
    "ks:ks_pop":783,
    "ks:ks_type":"HABITATION",
    "name:eng_x_preferred":[
        "Pazhathottam"
    ],
    "wof:name":"Pazhathottam",
    "wof:placetype":"locality",
    "wof:population":783
},
  "geometry": {"coordinates":[78.541605,11.477653],"type":"Point"}
}