{
  "type": "Feature",
  "properties": {
    "iso:country":"IN",
    "ks:ks_name":"Ilambarakodam",
    "ks:ks_pop":3187,
    "ks:ks_type":"HABITATION",
    "name:eng_x_preferred":[
        "Ilambarakodam"
    ],
    "wof:name":"Ilambarakodam",
    "wof:placetype":"locality",
    "wof:population":3187
},
  "geometry": {"coordinates":[76.69730300000001,9.800529],"type":"Point"}
}