{
  "type": "Feature",
  "properties": {
    "iso:country":"IN",
    "ks:ks_name":"Belghar",
    "ks:ks_pop":473,
    "ks:ks_type":"HABITATION",
    "name:eng_x_preferred":[
        "Belghar"
    ],
    "wof:name":"Belghar",
    "wof:placetype":"locality",
    "wof:population":473
},
  "geometry": {"coordinates":[73.14195100000001,18.25994],"type":"Point"}
}