{
  "type": "Feature",
  "properties": {
    "gn:admin1_code":"16.0",
    "gn:admin2_code":"499",
    "gn:asciiname":"Bahadarpur",
    "gn:country_code":"IN",
    "gn:dem":219,
    "gn:feature_class":"P",
    "gn:feature_code":"PPL",
    "gn:name":"Bah\u0101darpur",
    "gn:population":0,
    "gn:timezone":"Asia/Kolkata",
    "iso:country":"IN",
    "ks:ks_alt_nam":"Bah\u0101darpur",
    "ks:ks_name":"Bahadarpur",
    "ks:ks_pop":2821,
    "ks:ks_type":"VILLAGE",
    "ks:ks_uagg_main":0,
    "name:eng_x_preferred":[
        "Bahadarpur"
    ],
    "name:eng_x_variant":[
        "Bah\u0101darpur"
    ],
    "name:spa_x_preferred":[
        "Bahadarpur"
    ],
    "name:und_x_variant":[
        "Bahardurpur",
        "Bah\u0101darpur",
        "Bah\u0101durpur"
    ],
    "wof:name":"Bahadarpur",
    "wof:placetype":"neighbourhood",
    "wof:population":2821
},
  "geometry": {"coordinates":[75.04172199999999,20.914485],"type":"Point"}
}