{
  "type": "Feature",
  "properties": {
    "gn:admin1_code":"39.0",
    "gn:admin2_code":"64.0",
    "gn:asciiname":"Tunakot",
    "gn:country_code":"IN",
    "gn:dem":1313,
    "gn:feature_class":"P",
    "gn:feature_code":"PPL",
    "gn:name":"Tunakot",
    "gn:population":0,
    "gn:timezone":"Asia/Kolkata",
    "iso:country":"IN",
    "ks:ks_name":"Tunakot",
    "ks:ks_type":"VILLAGE",
    "name:eng_x_preferred":[
        "Tunakot"
    ],
    "wof:name":"Tunakot",
    "wof:placetype":"locality"
},
  "geometry": {"coordinates":[79.470518,29.576151],"type":"Point"}
}