{
  "type": "Feature",
  "properties": {
    "iso:country":"IN",
    "ks:ks_name":"Padinjattumuri Start",
    "ks:ks_pop":524,
    "ks:ks_type":"HABITATION",
    "ks:ks_uagg_main":0,
    "name:eng_x_preferred":[
        "Padinjattumuri Start"
    ],
    "wof:name":"Padinjattumuri Start",
    "wof:placetype":"locality",
    "wof:population":524
},
  "geometry": {"coordinates":[76.20048199999999,10.429839],"type":"Point"}
}