{
  "type": "Feature",
  "properties": {
    "iso:country":"IN",
    "ks:ks_name":"Tentulguri",
    "ks:ks_pop":772,
    "ks:ks_type":"VILLAGE",
    "name:eng_x_preferred":[
        "Tentulguri"
    ],
    "wof:name":"Tentulguri",
    "wof:placetype":"locality",
    "wof:population":772
},
  "geometry": {"coordinates":[88.271383,26.607709],"type":"Point"}
}