{
  "type": "Feature",
  "properties": {
    "iso:country":"IN",
    "ks:ks_name":"Budha Kalsapa",
    "ks:ks_pop":0,
    "ks:ks_type":"VILLAGE",
    "name:eng_x_preferred":[
        "Budha Kalsapa"
    ],
    "wof:name":"Budha Kalsapa",
    "wof:placetype":"locality",
    "wof:population":0
},
  "geometry": {"coordinates":[86.95601000000001,22.753721],"type":"Point"}
}