{
  "type": "Feature",
  "properties": {
    "iso:country":"IN",
    "ks:ks_name":"Pathara Kala",
    "ks:ks_pop":337,
    "ks:ks_type":"HABITATION",
    "name:eng_x_preferred":[
        "Pathara Kala"
    ],
    "wof:name":"Pathara Kala",
    "wof:placetype":"locality",
    "wof:population":337
},
  "geometry": {"coordinates":[79.16704799999999,21.76676],"type":"Point"}
}