{
  "type": "Feature",
  "properties": {
    "iso:country":"IN",
    "ks:ks_name":"Suhas Khas",
    "ks:ks_pop":700,
    "ks:ks_type":"HABITATION",
    "name:eng_x_preferred":[
        "Suhas Khas"
    ],
    "wof:name":"Suhas Khas",
    "wof:placetype":"locality",
    "wof:population":700
},
  "geometry": {"coordinates":[83.158205,27.263763],"type":"Point"}
}