{
  "type": "Feature",
  "properties": {
    "gn:admin1_code":"34.0",
    "gn:admin2_code":"217.0",
    "gn:asciiname":"Misrauli",
    "gn:country_code":"IN",
    "gn:dem":77,
    "gn:feature_class":"P",
    "gn:feature_code":"PPL",
    "gn:name":"Misrauli",
    "gn:population":0,
    "gn:timezone":"Asia/Kolkata",
    "iso:country":"IN",
    "ks:ks_name":"Misrauli",
    "ks:ks_pop":1213,
    "ks:ks_type":"VILLAGE",
    "name:eng_x_preferred":[
        "Misrauli"
    ],
    "wof:name":"Misrauli",
    "wof:placetype":"locality",
    "wof:population":1213
},
  "geometry": {"coordinates":[84.05107700000001,26.526461],"type":"Point"}
}