{
  "type": "Feature",
  "properties": {
    "iso:country":"IN",
    "ks:ks_name":"Piparla",
    "ks:ks_pop":37,
    "ks:ks_type":"VILLAGE",
    "name:eng_x_preferred":[
        "Piparla"
    ],
    "wof:name":"Piparla",
    "wof:placetype":"locality",
    "wof:population":37
},
  "geometry": {"coordinates":[70.909757,26.761736],"type":"Point"}
}