{
  "type": "Feature",
  "properties": {
    "iso:country":"IN",
    "ks:ks_name":"Sital Patti",
    "ks:ks_pop":3293,
    "ks:ks_type":"VILLAGE",
    "ks:ks_uagg_main":0,
    "name:eng_x_preferred":[
        "Sital Patti"
    ],
    "wof:name":"Sital Patti",
    "wof:placetype":"neighbourhood",
    "wof:population":3293
},
  "geometry": {"coordinates":[85.15469,26.677863],"type":"Point"}
}