{
  "type": "Feature",
  "properties": {
    "gn:admin1_code":"36",
    "gn:admin2_code":"180.0",
    "gn:asciiname":"Pura Saroman Singh",
    "gn:country_code":"IN",
    "gn:dem":115,
    "gn:feature_class":"P",
    "gn:feature_code":"PPL",
    "gn:name":"Pura Sarom\u0101n Singh",
    "gn:population":0,
    "gn:timezone":"Asia/Kolkata",
    "iso:country":"IN",
    "wof:name":"Pura Saroman Singh",
    "wof:placetype":"locality"
},
  "geometry": {"coordinates":[81.50961,27.27895],"type":"Point"}
}