{
  "type": "Feature",
  "properties": {
    "iso:country":"IN",
    "ks:ks_name":"Muraun Purwa",
    "ks:ks_pop":20,
    "ks:ks_type":"HABITATION",
    "name:eng_x_preferred":[
        "Muraun Purwa"
    ],
    "wof:name":"Muraun Purwa",
    "wof:placetype":"locality",
    "wof:population":20
},
  "geometry": {"coordinates":[80.68441900000001,27.689801],"type":"Point"}
}