{
  "type": "Feature",
  "properties": {
    "gn:admin1_code":"19.0",
    "gn:admin2_code":"570.0",
    "gn:asciiname":"Yellambalasi",
    "gn:country_code":"IN",
    "gn:dem":729,
    "gn:feature_class":"P",
    "gn:feature_code":"PPL",
    "gn:name":"Yellambalasi",
    "gn:population":0,
    "gn:timezone":"Asia/Kolkata",
    "iso:country":"IN",
    "wof:name":"Yellambalasi",
    "wof:placetype":"neighbourhood"
},
  "geometry": {"coordinates":[76.1073,13.57151],"type":"Point"}
}