{
  "type": "Feature",
  "properties": {
    "gn:admin1_code":"34.0",
    "gn:admin2_code":"220.0",
    "gn:asciiname":"Bishunpur Ghosi",
    "gn:country_code":"IN",
    "gn:dem":57,
    "gn:feature_class":"P",
    "gn:feature_code":"PPL",
    "gn:name":"Bishunpur Ghosi",
    "gn:population":0,
    "gn:timezone":"Asia/Kolkata",
    "iso:country":"IN",
    "name:eng_x_preferred":[
        "Bishunpur Ghosi"
    ],
    "wof:name":"Bishunpur Ghosi",
    "wof:placetype":"locality"
},
  "geometry": {"coordinates":[85.53721,25.66311],"type":"Point"}
}