{
  "type": "Feature",
  "properties": {
    "gn:admin1_code":"34.0",
    "gn:admin2_code":"220.0",
    "gn:asciiname":"Bishunpur Ghosi",
    "gn:country_code":"IN",
    "gn:dem":57,
    "gn:feature_class":"P",
    "gn:feature_code":"PPL",
    "gn:name":"Bishunpur Ghosi",
    "gn:population":0,
    "gn:timezone":"Asia/Kolkata",
    "iso:country":"IN",
    "ks:ks_name":"Bishunpur Ghausi",
    "ks:ks_pop":413,
    "ks:ks_type":"VILLAGE",
    "name:eng_x_preferred":[
        "Bishunpur Ghausi"
    ],
    "name:eng_x_variant":[
        "Bishunpur Ghosi"
    ],
    "wof:name":"Bishunpur Ghausi",
    "wof:placetype":"locality",
    "wof:population":413
},
  "geometry": {"coordinates":[85.537305,25.661024],"type":"Point"}
}