{
  "type": "Feature",
  "properties": {
    "gn:country":"IN",
    "gn:fcode":"PPL",
    "gn:population":45455,
    "iso:country":"IN",
    "name:ben_x_preferred":[
        "\u09b8\u09bf\u09b0\u09cb\u099e\u09cd\u099c"
    ],
    "name:bpy_x_preferred":[
        "\u09b8\u09bf\u09b0\u09cb\u099e\u09cd\u099c"
    ],
    "name:cat_x_preferred":[
        "Sironj"
    ],
    "name:ceb_x_preferred":[
        "Sironj"
    ],
    "name:deu_x_preferred":[
        "Sironj"
    ],
    "name:eng_x_preferred":[
        "Sironj"
    ],
    "name:fra_x_preferred":[
        "Sironj"
    ],
    "name:guj_x_preferred":[
        "\u0ab8\u0abf\u0ab0\u0a82\u0a9c"
    ],
    "name:hif_x_preferred":[
        "Sironj"
    ],
    "name:hin_x_preferred":[
        "\u0938\u093f\u0930\u094b\u0902\u091c"
    ],
    "name:ita_x_preferred":[
        "Sironj"
    ],
    "name:jpn_x_preferred":[
        "\u30b7\u30ed\u30f3\u30b8"
    ],
    "name:kan_x_preferred":[
        "\u0cb8\u0cbf\u0cb0\u0cca\u0c82\u0c9c\u0ccd"
    ],
    "name:kor_x_preferred":[
        "\uc2dc\ub860\uc988"
    ],
    "name:mlg_x_preferred":[
        "Sironj"
    ],
    "name:msa_x_preferred":[
        "Sironj"
    ],
    "name:nan_x_preferred":[
        "Sironj"
    ],
    "name:nld_x_preferred":[
        "Sironj"
    ],
    "name:ori_x_preferred":[
        "\u0b38\u0b3f\u0b30\u0b4b\u0b1e\u0b4d\u0b1c"
    ],
    "name:pam_x_preferred":[
        "Sironj"
    ],
    "name:por_x_preferred":[
        "Sironj"
    ],
    "name:rus_x_preferred":[
        "\u0421\u0438\u0440\u043e\u043d\u0434\u0436"
    ],
    "name:spa_x_preferred":[
        "Sironj"
    ],
    "name:swe_x_preferred":[
        "Sironj"
    ],
    "name:tam_x_preferred":[
        "\u0b9a\u0bbf\u0bb0\u0bcb\u0ba9\u0bcd\u0b9c\u0bcd"
    ],
    "name:tel_x_preferred":[
        "\u0c38\u0c3f\u0c30\u0c4b\u0c28\u0c4d\u0c1c\u0c4d"
    ],
    "name:urd_x_preferred":[
        "\u0633\u06cc\u0631\u0648\u0646\u062c"
    ],
    "name:vie_x_preferred":[
        "Sironj"
    ],
    "name:zho_x_preferred":[
        "\u9521\u9f99\u6770"
    ],
    "qs:name":"Siron",
    "qs:name_adm0":"India",
    "qs:name_adm1":"Uttar Pradesh",
    "qs:photos_9r":0,
    "qs:photos_sr":0,
    "qs:placetype":"Town",
    "qs:pop_sr":"7",
    "wof:name":"Siron",
    "wof:placetype":"locality",
    "wof:population":45455
},
  "geometry": {"coordinates":[77.68959,24.1038],"type":"Point"}
}