{
  "type": "Feature",
  "properties": {
    "iso:country":"IN",
    "ks:ks_name":"Wengurwada",
    "ks:ks_pop":0,
    "ks:ks_type":"VILLAGE",
    "name:eng_x_preferred":[
        "Wengurwada"
    ],
    "wof:name":"Wengurwada",
    "wof:placetype":"locality",
    "wof:population":0
},
  "geometry": {"coordinates":[80.834571,19.485009],"type":"Point"}
}