{
  "type": "Feature",
  "properties": {
    "iso:country":"IN",
    "ks:ks_name":"Champapur",
    "ks:ks_pop":6024,
    "ks:ks_type":"VILLAGE",
    "name:eng_x_preferred":[
        "Champapur"
    ],
    "wof:name":"Champapur",
    "wof:placetype":"locality",
    "wof:population":6024
},
  "geometry": {"coordinates":[85.500556,25.436826],"type":"Point"}
}