{
  "type": "Feature",
  "properties": {
    "iso:country":"IN",
    "ks:ks_alt_nam":"til mil kher",
    "ks:ks_name":"Til Mil Kher",
    "ks:ks_pop":277,
    "ks:ks_type":"HABITATION",
    "name:eng_x_preferred":[
        "Til Mil Kher"
    ],
    "wof:name":"Til Mil Kher",
    "wof:placetype":"locality",
    "wof:population":277
},
  "geometry": {"coordinates":[80.794533,26.310122],"type":"Point"}
}