{
  "type": "Feature",
  "properties": {
    "iso:country":"IN",
    "ks:ks_name":"Arnajharan",
    "ks:ks_pop":120,
    "ks:ks_type":"VILLAGE",
    "name:eng_x_preferred":[
        "Arnajharan"
    ],
    "wof:name":"Arnajharan",
    "wof:placetype":"locality",
    "wof:population":120
},
  "geometry": {"coordinates":[83.565988,20.229276],"type":"Point"}
}