{
  "type": "Feature",
  "properties": {
    "iso:country":"IN",
    "ks:ks_alt_nam":"Mohda tola veerraod",
    "ks:ks_name":"Mohda Tola Veerraod",
    "ks:ks_pop":492,
    "ks:ks_type":"HABITATION",
    "name:eng_x_preferred":[
        "Mohda Tola Veerraod"
    ],
    "wof:name":"Mohda Tola Veerraod",
    "wof:placetype":"locality",
    "wof:population":492
},
  "geometry": {"coordinates":[85.487866,23.668749],"type":"Point"}
}