{
  "type": "Feature",
  "properties": {
    "iso:country":"IN",
    "ks:ks_name":"Kaga Laga Dronagiri",
    "ks:ks_pop":97,
    "ks:ks_type":"VILLAGE",
    "name:eng_x_preferred":[
        "Kaga Laga Dronagiri"
    ],
    "wof:name":"Kaga Laga Dronagiri",
    "wof:placetype":"locality",
    "wof:population":97
},
  "geometry": {"coordinates":[79.823992,30.612136],"type":"Point"}
}