{
  "type": "Feature",
  "properties": {
    "iso:country":"IN",
    "ks:ks_name":"Kantabani Shasan",
    "ks:ks_pop":1917,
    "ks:ks_type":"VILLAGE",
    "name:eng_x_preferred":[
        "Kantabani Shasan"
    ],
    "wof:name":"Kantabani Shasan",
    "wof:placetype":"locality",
    "wof:population":1917
},
  "geometry": {"coordinates":[87.76621299999999,22.436307],"type":"Point"}
}