{
  "type": "Feature",
  "properties": {
    "iso:country":"IN",
    "ks:ks_name":"Purunapani",
    "ks:ks_pop":23,
    "ks:ks_type":"VILLAGE",
    "name:eng_x_preferred":[
        "Purunapani"
    ],
    "wof:name":"Purunapani",
    "wof:placetype":"locality",
    "wof:population":23
},
  "geometry": {"coordinates":[84.31339199999999,20.409095],"type":"Point"}
}