{
  "type": "Feature",
  "properties": {
    "gn:admin1_code":"12",
    "gn:admin2_code":"10.0",
    "gn:asciiname":"Pahlihunth",
    "gn:country_code":"IN",
    "gn:dem":2204,
    "gn:feature_class":"P",
    "gn:feature_code":"PPL",
    "gn:name":"Pahlihunth",
    "gn:population":0,
    "gn:timezone":"Asia/Kolkata",
    "iso:country":"IN",
    "wof:name":"Pahlihunth",
    "wof:placetype":"locality"
},
  "geometry": {"coordinates":[75.00050999999998,34.08344],"type":"Point"}
}