{
  "type": "Feature",
  "properties": {
    "gn:admin1_code":"36.0",
    "gn:admin2_code":"195",
    "gn:asciiname":"Birnon",
    "gn:country_code":"IN",
    "gn:dem":78,
    "gn:feature_class":"P",
    "gn:feature_code":"PPL",
    "gn:name":"Birnon",
    "gn:population":0,
    "gn:timezone":"Asia/Kolkata",
    "iso:country":"IN",
    "wof:name":"Birnon",
    "wof:placetype":"locality"
},
  "geometry": {"coordinates":[83.51713000000002,25.71862],"type":"Point"}
}