{
  "type": "Feature",
  "properties": {
    "iso:country":"IN",
    "ks:ks_name":"Jangal Harbhajan Singh",
    "ks:ks_pop":0,
    "ks:ks_type":"VILLAGE",
    "name:eng_x_preferred":[
        "Jangal Harbhajan Singh"
    ],
    "wof:name":"Jangal Harbhajan Singh",
    "wof:placetype":"locality",
    "wof:population":0
},
  "geometry": {"coordinates":[83.329483,26.782444],"type":"Point"}
}