{
  "type": "Feature",
  "properties": {
    "gn:admin1_code":"19.0",
    "gn:admin2_code":"574.0",
    "gn:asciiname":"Kelgalale",
    "gn:country_code":"IN",
    "gn:dem":939,
    "gn:feature_class":"P",
    "gn:feature_code":"PPL",
    "gn:name":"Kelgalale",
    "gn:population":0,
    "gn:timezone":"Asia/Kolkata",
    "iso:country":"IN",
    "wof:name":"Kelgalale",
    "wof:placetype":"locality"
},
  "geometry": {"coordinates":[75.79873000000001,12.98662],"type":"Point"}
}