{
  "type": "Feature",
  "properties": {
    "iso:country":"IN",
    "ks:ks_name":"Piprirepad Thanda",
    "ks:ks_pop":180,
    "ks:ks_type":"HABITATION",
    "name:eng_x_preferred":[
        "Piprirepad Thanda"
    ],
    "wof:name":"Piprirepad Thanda",
    "wof:placetype":"locality",
    "wof:population":180
},
  "geometry": {"coordinates":[77.966908,18.188784],"type":"Point"}
}