{
  "type": "Feature",
  "properties": {
    "gn:admin1_code":"36.0",
    "gn:admin2_code":"162.0",
    "gn:asciiname":"Akbarpur Danda",
    "gn:country_code":"IN",
    "gn:dem":144,
    "gn:feature_class":"P",
    "gn:feature_code":"PPL",
    "gn:name":"Akbarpur D\u0101nda",
    "gn:population":0,
    "gn:timezone":"Asia/Kolkata",
    "iso:country":"IN",
    "wof:name":"Akbarpur Danda",
    "wof:placetype":"locality"
},
  "geometry": {"coordinates":[79.42613,26.56973],"type":"Point"}
}