{
  "type": "Feature",
  "properties": {
    "iso:country":"IN",
    "ks:ks_name":"Perumalagaram",
    "ks:ks_pop":2844,
    "ks:ks_type":"VILLAGE",
    "ks:ks_uagg_main":0,
    "name:eng_x_preferred":[
        "Perumalagaram"
    ],
    "wof:name":"Perumalagaram",
    "wof:placetype":"neighbourhood",
    "wof:population":2844
},
  "geometry": {"coordinates":[79.501885,10.762125],"type":"Point"}
}