{
  "type": "Feature",
  "properties": {
    "iso:country":"IN",
    "ks:ks_name":"Dhunga",
    "ks:ks_pop":84,
    "ks:ks_type":"HABITATION",
    "name:eng_x_preferred":[
        "Dhunga"
    ],
    "wof:name":"Dhunga",
    "wof:placetype":"locality",
    "wof:population":84
},
  "geometry": {"coordinates":[80.237669,29.838619],"type":"Point"}
}