{
  "type": "Feature",
  "properties": {
    "gn:admin1_code":"34",
    "gn:admin2_code":"233.0",
    "gn:asciiname":"Nimiyan",
    "gn:country_code":"IN",
    "gn:dem":98,
    "gn:feature_class":"P",
    "gn:feature_code":"PPL",
    "gn:name":"Nimiy\u0101n",
    "gn:population":0,
    "gn:timezone":"Asia/Kolkata",
    "iso:country":"IN",
    "wof:name":"Nimiyan",
    "wof:placetype":"locality"
},
  "geometry": {"coordinates":[83.62254,24.95261],"type":"Point"}
}