{
  "type": "Feature",
  "properties": {
    "gn:admin1_code":"34",
    "gn:admin2_code":"233.0",
    "gn:asciiname":"Nimiyan",
    "gn:country_code":"IN",
    "gn:dem":98,
    "gn:feature_class":"P",
    "gn:feature_code":"PPL",
    "gn:name":"Nimiy\u0101n",
    "gn:population":0,
    "gn:timezone":"Asia/Kolkata",
    "iso:country":"IN",
    "ks:ks_name":"Nimian",
    "ks:ks_pop":357,
    "ks:ks_type":"VILLAGE",
    "name:eng_x_preferred":[
        "Nimian"
    ],
    "name:eng_x_variant":[
        "Nimiyan"
    ],
    "wof:name":"Nimian",
    "wof:placetype":"locality",
    "wof:population":357
},
  "geometry": {"coordinates":[83.628445,24.95157],"type":"Point"}
}