{
  "type": "Feature",
  "properties": {
    "iso:country":"IN",
    "ks:ks_name":"Karnipura Chak Charnot",
    "ks:ks_pop":70,
    "ks:ks_type":"VILLAGE",
    "name:eng_x_preferred":[
        "Karnipura Chak Charnot"
    ],
    "wof:name":"Karnipura Chak Charnot",
    "wof:placetype":"locality",
    "wof:population":70
},
  "geometry": {"coordinates":[71.828892,25.766],"type":"Point"}
}