{
  "type": "Feature",
  "properties": {
    "gn:admin1_code":"36",
    "gn:admin2_code":"146.0",
    "gn:asciiname":"Chitpur",
    "gn:country_code":"IN",
    "gn:dem":170,
    "gn:feature_class":"P",
    "gn:feature_code":"PPL",
    "gn:name":"Chitpur",
    "gn:population":0,
    "gn:timezone":"Asia/Kolkata",
    "iso:country":"IN",
    "name:ben_x_preferred":[
        "\u099a\u09bf\u09ce\u09aa\u09c1\u09b0"
    ],
    "wof:name":"Chitpur",
    "wof:placetype":"locality"
},
  "geometry": {"coordinates":[77.85829,27.00617],"type":"Point"}
}