{
  "type": "Feature",
  "properties": {
    "gn:admin1_code":"2.0",
    "gn:admin2_code":"553.0",
    "gn:asciiname":"Cherupullivandlapalle",
    "gn:country_code":"IN",
    "gn:dem":591,
    "gn:feature_class":"P",
    "gn:feature_code":"PPL",
    "gn:name":"Cherupulliv\u0101ndlapalle",
    "gn:population":0,
    "gn:timezone":"Asia/Kolkata",
    "iso:country":"IN",
    "ks:ks_name":"Charupallivandla Palli",
    "ks:ks_pop":6,
    "ks:ks_type":"HABITATION",
    "name:eng_x_preferred":[
        "Charupallivandla Palli"
    ],
    "name:eng_x_variant":[
        "Cherupullivandlapalle"
    ],
    "wof:name":"Charupallivandla Palli",
    "wof:placetype":"locality",
    "wof:population":6
},
  "geometry": {"coordinates":[78.23481200000001,13.917362],"type":"Point"}
}