{
  "type": "Feature",
  "properties": {
    "iso:country":"IN",
    "ks:ks_name":"Kathi Para",
    "ks:ks_pop":600,
    "ks:ks_type":"HABITATION",
    "name:eng_x_preferred":[
        "Kathi Para"
    ],
    "wof:name":"Kathi Para",
    "wof:placetype":"locality",
    "wof:population":600
},
  "geometry": {"coordinates":[88.73114200000001,22.175014],"type":"Point"}
}