{
  "type": "Feature",
  "properties": {
    "iso:country":"IN",
    "ks:ks_name":"Wadajun",
    "ks:ks_pop":168,
    "ks:ks_type":"VILLAGE",
    "name:eng_x_preferred":[
        "Wadajun"
    ],
    "wof:name":"Wadajun",
    "wof:placetype":"locality",
    "wof:population":168
},
  "geometry": {"coordinates":[73.315157,17.077012],"type":"Point"}
}