{
  "type": "Feature",
  "properties": {
    "iso:country":"IN",
    "ks:ks_name":"Narayana",
    "ks:ks_pop":407,
    "ks:ks_type":"HABITATION",
    "name:eng_x_preferred":[
        "Narayana"
    ],
    "wof:name":"Narayana",
    "wof:placetype":"locality",
    "wof:population":407
},
  "geometry": {"coordinates":[83.14787699999999,24.683854],"type":"Point"}
}