{
  "type": "Feature",
  "properties": {
    "iso:country":"IN",
    "ks:ks_alt_nam":"NASAHARA",
    "ks:ks_name":"Nasahara",
    "ks:ks_pop":1295,
    "ks:ks_type":"HABITATION",
    "name:eng_x_preferred":[
        "Nasahara"
    ],
    "wof:name":"Nasahara",
    "wof:placetype":"locality",
    "wof:population":1295
},
  "geometry": {"coordinates":[86.220772,25.975805],"type":"Point"}
}