{
  "type": "Feature",
  "properties": {
    "iso:country":"IN",
    "ks:ks_name":"Babyachil",
    "ks:ks_pop":1040,
    "ks:ks_type":"HABITATION",
    "name:eng_x_preferred":[
        "Babyachil"
    ],
    "wof:name":"Babyachil",
    "wof:placetype":"neighbourhood",
    "wof:population":1040
},
  "geometry": {"coordinates":[74.903879,12.952773],"type":"Point"}
}