{
  "type": "Feature",
  "properties": {
    "gn:admin1_code":"11.0",
    "gn:admin2_code":"27.0",
    "gn:asciiname":"Jamnu",
    "gn:country_code":"IN",
    "gn:dem":1048,
    "gn:feature_class":"P",
    "gn:feature_code":"PPL",
    "gn:name":"Jamnu",
    "gn:population":0,
    "gn:timezone":"Asia/Kolkata",
    "iso:country":"IN",
    "wof:name":"Jamnu",
    "wof:placetype":"locality"
},
  "geometry": {"coordinates":[77.0763,31.2961],"type":"Point"}
}