{
  "type": "Feature",
  "properties": {
    "gn:admin1_code":"11.0",
    "gn:admin2_code":"32.0",
    "gn:asciiname":"Ravna",
    "gn:country_code":"IN",
    "gn:dem":895,
    "gn:feature_class":"P",
    "gn:feature_code":"PPL",
    "gn:name":"R\u0101vna",
    "gn:population":0,
    "gn:timezone":"Asia/Kolkata",
    "iso:country":"IN",
    "name:bos_x_preferred":[
        "Ravna"
    ],
    "name:bul_x_preferred":[
        "\u0420\u0430\u0432\u043d\u0430"
    ],
    "name:ceb_x_preferred":[
        "Ravna"
    ],
    "name:fra_x_preferred":[
        "Ravna"
    ],
    "name:hrv_x_preferred":[
        "Ravna"
    ],
    "name:ron_x_preferred":[
        "Ravna"
    ],
    "name:rus_x_preferred":[
        "\u0420\u0430\u0432\u043d\u0430"
    ],
    "name:slv_x_preferred":[
        "Ravna"
    ],
    "name:srp_x_preferred":[
        "\u0420\u0430\u0432\u043d\u0430"
    ],
    "name:swe_x_preferred":[
        "Ravna"
    ],
    "name:ukr_x_preferred":[
        "\u0420\u0430\u0432\u043d\u0430"
    ],
    "wof:name":"Ravna",
    "wof:placetype":"locality"
},
  "geometry": {"coordinates":[77.26109,30.80392],"type":"Point"}
}