{
  "type": "Feature",
  "properties": {
    "gn:admin1_code":"36.0",
    "gn:admin2_code":"133",
    "gn:asciiname":"Bhanera Uda",
    "gn:country_code":"IN",
    "gn:dem":254,
    "gn:feature_class":"P",
    "gn:feature_code":"PPL",
    "gn:name":"Bhanera \u016ada",
    "gn:population":0,
    "gn:timezone":"Asia/Kolkata",
    "iso:country":"IN",
    "wof:name":"Bhanera Uda",
    "wof:placetype":"locality"
},
  "geometry": {"coordinates":[77.37141,29.62244],"type":"Point"}
}