{
  "type": "Feature",
  "properties": {
    "iso:country":"IN",
    "ks:ks_name":"Kuthirampuzha",
    "ks:ks_pop":840,
    "ks:ks_type":"HABITATION",
    "name:eng_x_preferred":[
        "Kuthirampuzha"
    ],
    "wof:name":"Kuthirampuzha",
    "wof:placetype":"locality",
    "wof:population":840
},
  "geometry": {"coordinates":[76.29520100000001,11.224955],"type":"Point"}
}