{
  "type": "Feature",
  "properties": {
    "iso:country":"IN",
    "ks:ks_name":"Kumhradih",
    "ks:ks_pop":276,
    "ks:ks_type":"VILLAGE",
    "ks:ks_uagg_main":0,
    "name:eng_x_preferred":[
        "Kumhradih"
    ],
    "wof:name":"Kumhradih",
    "wof:placetype":"neighbourhood",
    "wof:population":276
},
  "geometry": {"coordinates":[84.36897999999999,24.088665],"type":"Point"}
}