{
  "type": "Feature",
  "properties": {
    "gn:admin1_code":"36",
    "gn:admin2_code":"135.0",
    "gn:asciiname":"Rustampur Badhmar",
    "gn:country_code":"IN",
    "gn:dem":188,
    "gn:feature_class":"P",
    "gn:feature_code":"PPL",
    "gn:name":"Rustampur Badhm\u0101r",
    "gn:population":0,
    "gn:timezone":"Asia/Kolkata",
    "iso:country":"IN",
    "ks:ks_alt_nam":"Rustampur Badhm\u0101r",
    "ks:ks_name":"Rustampur Badhmar",
    "ks:ks_type":"VILLAGE",
    "name:eng_x_preferred":[
        "Rustampur Badhmar"
    ],
    "name:eng_x_variant":[
        "Rustampur Badhm\u0101r"
    ],
    "wof:name":"Rustampur Badhmar",
    "wof:placetype":"locality"
},
  "geometry": {"coordinates":[78.821659,28.781028],"type":"Point"}
}