{
  "type": "Feature",
  "properties": {
    "iso:country":"IN",
    "ks:ks_name":"Munda Para",
    "ks:ks_pop":545,
    "ks:ks_type":"VILLAGE",
    "ks:ks_uagg_main":0,
    "name:eng_x_preferred":[
        "Munda Para"
    ],
    "wof:name":"Munda Para",
    "wof:placetype":"neighbourhood",
    "wof:population":545
},
  "geometry": {"coordinates":[87.69705399999999,21.988207],"type":"Point"}
}