{
  "type": "Feature",
  "properties": {
    "gn:admin1_code":"12.0",
    "gn:admin2_code":"18.0",
    "gn:asciiname":"Chhatral",
    "gn:country_code":"IN",
    "gn:dem":3015,
    "gn:feature_class":"P",
    "gn:feature_code":"PPL",
    "gn:name":"Chhatr\u0101l",
    "gn:population":0,
    "gn:timezone":"Asia/Kolkata",
    "iso:country":"IN",
    "wof:name":"Chhatral",
    "wof:placetype":"locality"
},
  "geometry": {"coordinates":[75.58313000000003,33.3237],"type":"Point"}
}