{
  "type": "Feature",
  "properties": {
    "gn:admin1_code":"36",
    "gn:admin2_code":"200.0",
    "gn:asciiname":"Muirpur",
    "gn:country_code":"IN",
    "gn:dem":346,
    "gn:feature_class":"P",
    "gn:feature_code":"PPL",
    "gn:name":"Muirpur",
    "gn:population":0,
    "gn:timezone":"Asia/Kolkata",
    "iso:country":"IN",
    "wof:name":"Muirpur",
    "wof:placetype":"neighbourhood"
},
  "geometry": {"coordinates":[83.04993,24.12512],"type":"Point"}
}