{
  "type": "Feature",
  "properties": {
    "gn:admin1_code":"11.0",
    "gn:admin2_code":"32.0",
    "gn:asciiname":"Chhane ka Dal",
    "gn:country_code":"IN",
    "gn:dem":1105,
    "gn:feature_class":"P",
    "gn:feature_code":"PPL",
    "gn:name":"Chhane ka D\u0101l",
    "gn:population":0,
    "gn:timezone":"Asia/Kolkata",
    "iso:country":"IN",
    "wof:name":"Chhane ka Dal",
    "wof:placetype":"locality"
},
  "geometry": {"coordinates":[77.24876,30.70298],"type":"Point"}
}