{
  "type": "Feature",
  "properties": {
    "iso:country":"IN",
    "ks:ks_name":"Kallikadavu Jn",
    "ks:ks_pop":664,
    "ks:ks_type":"HABITATION",
    "name:eng_x_preferred":[
        "Kallikadavu Jn"
    ],
    "wof:name":"Kallikadavu Jn",
    "wof:placetype":"locality",
    "wof:population":664
},
  "geometry": {"coordinates":[76.293076,11.295843],"type":"Point"}
}