{
  "type": "Feature",
  "properties": {
    "gn:admin1_code":"39",
    "gn:admin2_code":"66.0",
    "gn:asciiname":"Kalu Saiyid",
    "gn:country_code":"IN",
    "gn:dem":292,
    "gn:feature_class":"P",
    "gn:feature_code":"PPL",
    "gn:name":"K\u0101lu Saiyid",
    "gn:population":0,
    "gn:timezone":"Asia/Kolkata",
    "iso:country":"IN",
    "wof:name":"Kalu Saiyid",
    "wof:placetype":"locality"
},
  "geometry": {"coordinates":[78.89282,29.3733],"type":"Point"}
}