{
  "type": "Feature",
  "properties": {
    "gn:admin1_code":"36",
    "gn:admin2_code":"148.0",
    "gn:asciiname":"Nagla Hulasi",
    "gn:country_code":"IN",
    "gn:dem":157,
    "gn:feature_class":"P",
    "gn:feature_code":"PPL",
    "gn:name":"Nagla Hul\u0101si",
    "gn:population":0,
    "gn:timezone":"Asia/Kolkata",
    "iso:country":"IN",
    "wof:name":"Nagla Hulasi",
    "wof:placetype":"locality"
},
  "geometry": {"coordinates":[79.11926,27.16971],"type":"Point"}
}