{
  "type": "Feature",
  "properties": {
    "gn:admin1_code":"24.0",
    "gn:admin2_code":"107.0",
    "gn:asciiname":"Misran ki Jhonpri",
    "gn:country_code":"IN",
    "gn:dem":266,
    "gn:feature_class":"P",
    "gn:feature_code":"PPL",
    "gn:name":"Misran ki Jhonpri",
    "gn:population":0,
    "gn:timezone":"Asia/Kolkata",
    "iso:country":"IN",
    "wof:name":"Misran ki Jhonpri",
    "wof:placetype":"locality"
},
  "geometry": {"coordinates":[76.70175999999999,26.36818],"type":"Point"}
}