{
  "type": "Feature",
  "properties": {
    "gn:admin1_code":"12.0",
    "gn:admin2_code":"005",
    "gn:asciiname":"Bara Chhari",
    "gn:country_code":"IN",
    "gn:dem":2107,
    "gn:feature_class":"P",
    "gn:feature_code":"PPL",
    "gn:name":"Bara Chhari",
    "gn:population":0,
    "gn:timezone":"Asia/Kolkata",
    "iso:country":"IN",
    "wof:name":"Bara Chhari",
    "wof:placetype":"locality"
},
  "geometry": {"coordinates":[74.25278,33.84444000000001],"type":"Point"}
}