{
  "type": "Feature",
  "properties": {
    "gn:admin1_code":"21.0",
    "gn:admin2_code":"398.0",
    "gn:asciiname":"Nuaguda",
    "gn:country_code":"IN",
    "gn:dem":1031,
    "gn:feature_class":"P",
    "gn:feature_code":"PPL",
    "gn:name":"Nu\u0101guda",
    "gn:population":0,
    "gn:timezone":"Asia/Kolkata",
    "iso:country":"IN",
    "wof:name":"Nuaguda",
    "wof:placetype":"locality"
},
  "geometry": {"coordinates":[82.75094,18.51944],"type":"Point"}
}