{
  "type": "Feature",
  "properties": {
    "gn:admin1_code":"36.0",
    "gn:admin2_code":"159",
    "gn:asciiname":"Alhadpur",
    "gn:country_code":"IN",
    "gn:dem":144,
    "gn:feature_class":"P",
    "gn:feature_code":"PPL",
    "gn:name":"Alh\u0101dpur",
    "gn:population":0,
    "gn:timezone":"Asia/Kolkata",
    "iso:country":"IN",
    "ks:ks_alt_nam":"Alh\u0101dpur",
    "ks:ks_name":"Alhadpur",
    "ks:ks_type":"VILLAGE",
    "name:eng_x_preferred":[
        "Alhadpur"
    ],
    "name:eng_x_variant":[
        "Alh\u0101dpur"
    ],
    "wof:name":"Alhadpur",
    "wof:placetype":"locality"
},
  "geometry": {"coordinates":[79.646038,27.529742],"type":"Point"}
}