{
  "type": "Feature",
  "properties": {
    "iso:country":"IN",
    "ks:ks_name":"Kosambiya",
    "ks:ks_pop":893,
    "ks:ks_type":"VILLAGE",
    "name:eng_x_preferred":[
        "Kosambiya"
    ],
    "wof:name":"Kosambiya",
    "wof:placetype":"locality",
    "wof:population":893
},
  "geometry": {"coordinates":[73.248341,21.027911],"type":"Point"}
}