{
  "type": "Feature",
  "properties": {
    "iso:country":"IN",
    "ks:ks_name":"Shindewadi",
    "ks:ks_pop":82,
    "ks:ks_type":"HABITATION",
    "name:eng_x_preferred":[
        "Shindewadi"
    ],
    "wof:name":"Shindewadi",
    "wof:placetype":"locality",
    "wof:population":82
},
  "geometry": {"coordinates":[73.454492,17.017903],"type":"Point"}
}