{
  "type": "Feature",
  "properties": {
    "iso:country":"IN",
    "ks:ks_name":"Abettu",
    "ks:ks_pop":630,
    "ks:ks_type":"HABITATION",
    "name:eng_x_preferred":[
        "Abettu"
    ],
    "wof:name":"Abettu",
    "wof:placetype":"locality",
    "wof:population":630
},
  "geometry": {"coordinates":[74.96925899999999,12.897592],"type":"Point"}
}