{
  "type": "Feature",
  "properties": {
    "gn:admin1_code":"11.0",
    "gn:admin2_code":"32.0",
    "gn:asciiname":"Rith",
    "gn:country_code":"IN",
    "gn:dem":1050,
    "gn:feature_class":"P",
    "gn:feature_code":"PPL",
    "gn:name":"Rith",
    "gn:population":0,
    "gn:timezone":"Asia/Kolkata",
    "iso:country":"IN",
    "name:bre_x_preferred":[
        "Rith"
    ],
    "name:cym_x_preferred":[
        "Rith"
    ],
    "name:eus_x_preferred":[
        "Rith"
    ],
    "name:gla_x_preferred":[
        "Rith"
    ],
    "name:glg_x_preferred":[
        "Rith"
    ],
    "name:spa_x_preferred":[
        "Rith"
    ],
    "wof:name":"Rith",
    "wof:placetype":"locality"
},
  "geometry": {"coordinates":[77.61192,30.7405],"type":"Point"}
}