{
  "type": "Feature",
  "properties": {
    "iso:country":"IN",
    "ks:ks_name":"Chak Sansare",
    "ks:ks_pop":124,
    "ks:ks_type":"HABITATION",
    "name:eng_x_preferred":[
        "Chak Sansare"
    ],
    "wof:name":"Chak Sansare",
    "wof:placetype":"locality",
    "wof:population":124
},
  "geometry": {"coordinates":[82.64152799999999,26.580983],"type":"Point"}
}