{
  "type": "Feature",
  "properties": {
    "iso:country":"IN",
    "ks:ks_name":"Sangarwadi",
    "ks:ks_pop":109,
    "ks:ks_type":"HABITATION",
    "name:eng_x_preferred":[
        "Sangarwadi"
    ],
    "wof:name":"Sangarwadi",
    "wof:placetype":"locality",
    "wof:population":109
},
  "geometry": {"coordinates":[73.718763,16.704206],"type":"Point"}
}