{
  "type": "Feature",
  "properties": {
    "gn:admin1_code":"12",
    "gn:asciiname":"Badarali",
    "gn:country_code":"IN",
    "gn:dem":2219,
    "gn:feature_class":"P",
    "gn:feature_code":"PPL",
    "gn:name":"Badar\u0101li",
    "gn:population":0,
    "gn:timezone":"Asia/Kolkata",
    "iso:country":"IN",
    "wof:name":"Badarali",
    "wof:placetype":"locality"
},
  "geometry": {"coordinates":[74.16061999999999,34.17878],"type":"Point"}
}