{
  "type": "Feature",
  "properties": {
    "gn:admin1_code":"36",
    "gn:admin2_code":"134.0",
    "gn:asciiname":"Jattiwala",
    "gn:country_code":"IN",
    "gn:dem":318,
    "gn:feature_class":"P",
    "gn:feature_code":"PPL",
    "gn:name":"Jatt\u012bw\u0101la",
    "gn:population":0,
    "gn:timezone":"Asia/Kolkata",
    "iso:country":"IN",
    "name:und_x_variant":[
        "Jatt\u012bw\u0101la",
        "Muhammad Am\u012bn Kh\u0101npur"
    ],
    "wof:name":"Jattiwala",
    "wof:placetype":"locality"
},
  "geometry": {"coordinates":[78.40040999999999,29.71387],"type":"Point"}
}