{
  "type": "Feature",
  "properties": {
    "gn:admin1_code":"36",
    "gn:admin2_code":"162.0",
    "gn:asciiname":"Dera Tarwarian",
    "gn:country_code":"IN",
    "gn:dem":144,
    "gn:feature_class":"P",
    "gn:feature_code":"PPL",
    "gn:name":"Dera Tarwari\u0101n",
    "gn:population":0,
    "gn:timezone":"Asia/Kolkata",
    "iso:country":"IN",
    "wof:name":"Dera Tarwarian",
    "wof:placetype":"locality"
},
  "geometry": {"coordinates":[79.50024999999999,26.58033],"type":"Point"}
}