{
  "type": "Feature",
  "properties": {
    "iso:country":"IN",
    "ks:ks_name":"Chorda",
    "ks:ks_pop":2087,
    "ks:ks_type":"VILLAGE",
    "name:eng_x_preferred":[
        "Chorda"
    ],
    "wof:name":"Chorda",
    "wof:placetype":"locality",
    "wof:population":2087
},
  "geometry": {"coordinates":[86.035535,23.211586],"type":"Point"}
}