{
  "type": "Feature",
  "properties": {
    "gn:admin1_code":"35.0",
    "gn:admin2_code":"455.0",
    "gn:asciiname":"Bamhani Mal",
    "gn:country_code":"IN",
    "gn:dem":639,
    "gn:feature_class":"P",
    "gn:feature_code":"PPL",
    "gn:name":"Bamhani Mal",
    "gn:population":0,
    "gn:timezone":"Asia/Kolkata",
    "iso:country":"IN",
    "wof:name":"Bamhani Mal",
    "wof:placetype":"locality"
},
  "geometry": {"coordinates":[78.47757,21.99315],"type":"Point"}
}