{
  "type": "Feature",
  "properties": {
    "iso:country":"IN",
    "ks:ks_name":"Dahipod",
    "ks:ks_pop":138,
    "ks:ks_type":"HABITATION",
    "name:eng_x_preferred":[
        "Dahipod"
    ],
    "wof:name":"Dahipod",
    "wof:placetype":"locality",
    "wof:population":138
},
  "geometry": {"coordinates":[78.64444399999999,20.195833],"type":"Point"}
}