{
  "type": "Feature",
  "properties": {
    "gn:admin1_code":"21.0",
    "gn:admin2_code":"393",
    "gn:asciiname":"Daramgara",
    "gn:country_code":"IN",
    "gn:dem":200,
    "gn:feature_class":"P",
    "gn:feature_code":"PPL",
    "gn:name":"Daramgara",
    "gn:population":0,
    "gn:timezone":"Asia/Kolkata",
    "iso:country":"IN",
    "wof:name":"Daramgara",
    "wof:placetype":"neighbourhood"
},
  "geometry": {"coordinates":[83.23793000000001,20.40658],"type":"Point"}
}