{
  "type": "Feature",
  "properties": {
    "gn:admin1_code":"12.0",
    "gn:admin2_code":"18.0",
    "gn:asciiname":"Horne",
    "gn:country_code":"IN",
    "gn:dem":1568,
    "gn:feature_class":"P",
    "gn:feature_code":"PPL",
    "gn:name":"Horn\u0113",
    "gn:population":0,
    "gn:timezone":"Asia/Kolkata",
    "iso:country":"IN",
    "name:ceb_x_preferred":[
        "Horne"
    ],
    "name:dan_x_preferred":[
        "Horne"
    ],
    "name:deu_x_preferred":[
        "Horne"
    ],
    "name:fra_x_preferred":[
        "Horne"
    ],
    "name:ita_x_preferred":[
        "Horne"
    ],
    "name:nds_x_preferred":[
        "Horne"
    ],
    "name:nld_x_preferred":[
        "Horne"
    ],
    "name:swe_x_preferred":[
        "Horne"
    ],
    "wof:name":"Horne",
    "wof:placetype":"locality"
},
  "geometry": {"coordinates":[75.70694,33.40359],"type":"Point"}
}