{
  "type": "Feature",
  "properties": {
    "iso:country":"IN",
    "ks:ks_name":"Dyotung",
    "ks:ks_pop":55,
    "ks:ks_type":"VILLAGE",
    "name:eng_x_preferred":[
        "Dyotung"
    ],
    "wof:name":"Dyotung",
    "wof:placetype":"locality",
    "wof:population":55
},
  "geometry": {"coordinates":[80.019401,29.695036],"type":"Point"}
}