{
  "type": "Feature",
  "properties": {
    "iso:country":"IN",
    "ks:ks_alt_nam":"Kazigaon Pt II",
    "ks:ks_name":"Kazigaon Pt Ii",
    "ks:ks_pop":162,
    "ks:ks_type":"HABITATION",
    "name:eng_x_preferred":[
        "Kazigaon Pt Ii"
    ],
    "wof:name":"Kazigaon Pt Ii",
    "wof:placetype":"locality",
    "wof:population":162
},
  "geometry": {"coordinates":[90.020359,26.182592],"type":"Point"}
}