{
  "type": "Feature",
  "properties": {
    "gn:admin1_code":"34.0",
    "gn:admin2_code":"204",
    "gn:asciiname":"Gunjrauliya",
    "gn:country_code":"IN",
    "gn:dem":77,
    "gn:feature_class":"P",
    "gn:feature_code":"PPL",
    "gn:name":"Gunjrauliy\u0101",
    "gn:population":0,
    "gn:timezone":"Asia/Kolkata",
    "iso:country":"IN",
    "name:und_x_variant":[
        "Tola Gujarwalia",
        "Gunjrauliya",
        "Gunjrauliy\u0101"
    ],
    "wof:name":"Gunjrauliya",
    "wof:placetype":"locality"
},
  "geometry": {"coordinates":[84.55209000000001,26.58119000000001],"type":"Point"}
}