{
  "type": "Feature",
  "properties": {
    "gn:admin1_code":"36",
    "gn:admin2_code":"188.0",
    "gn:asciiname":"Pachisi",
    "gn:country_code":"IN",
    "gn:dem":82,
    "gn:feature_class":"P",
    "gn:feature_code":"PPL",
    "gn:name":"Pach\u012bsi",
    "gn:population":0,
    "gn:timezone":"Asia/Kolkata",
    "iso:country":"IN",
    "ks:ks_alt_nam":"Pach\u012bsi",
    "ks:ks_name":"Pachisi",
    "ks:ks_type":"VILLAGE",
    "ks:ks_uagg_main":0,
    "name:ara_x_preferred":[
        "\u0628\u0627\u062a\u0634\u064a\u0633\u064a"
    ],
    "name:ast_x_preferred":[
        "Pachisi"
    ],
    "name:cat_x_preferred":[
        "Pachisi"
    ],
    "name:deu_x_preferred":[
        "Pachisi"
    ],
    "name:eng_x_preferred":[
        "Pachisi"
    ],
    "name:eng_x_variant":[
        "Pach\u012bsi"
    ],
    "name:fin_x_preferred":[
        "Patsisi"
    ],
    "name:fra_x_preferred":[
        "Pachisi"
    ],
    "name:ita_x_preferred":[
        "Pachisi"
    ],
    "name:jpn_x_preferred":[
        "\u30d1\u30c1\u30fc\u30b7"
    ],
    "name:nld_x_preferred":[
        "Pachisi"
    ],
    "name:nno_x_preferred":[
        "Patsjisi"
    ],
    "name:pol_x_preferred":[
        "Pachisi"
    ],
    "name:por_x_preferred":[
        "Pachisi"
    ],
    "name:rus_x_preferred":[
        "\u041f\u0430\u0447\u0438\u0441\u0438"
    ],
    "name:spa_x_preferred":[
        "Pachisi"
    ],
    "name:tam_x_preferred":[
        "\u0ba4\u0bbe\u0baf\u0bae\u0bcd"
    ],
    "name:ukr_x_preferred":[
        "\u041f\u0430\u0447\u0456\u0441\u0456"
    ],
    "name:wuu_x_preferred":[
        "\u5370\u5ea6\u5341\u5b57\u620f"
    ],
    "name:zho_x_preferred":[
        "\u5370\u5ea6\u5341\u5b57\u6232"
    ],
    "wof:name":"Pachisi",
    "wof:placetype":"neighbourhood"
},
  "geometry": {"coordinates":[83.37873500000001,26.528524],"type":"Point"}
}