{
  "type": "Feature",
  "properties": {
    "iso:country":"IN",
    "ks:ks_name":"Kapsiput",
    "ks:ks_pop":565,
    "ks:ks_type":"VILLAGE",
    "name:eng_x_preferred":[
        "Kapsiput"
    ],
    "wof:name":"Kapsiput",
    "wof:placetype":"locality",
    "wof:population":565
},
  "geometry": {"coordinates":[83.004274,18.865521],"type":"Point"}
}