{
  "type": "Feature",
  "properties": {
    "iso:country":"IN",
    "ks:ks_name":"Edoor",
    "ks:ks_pop":1918,
    "ks:ks_type":"HABITATION",
    "name:eng_x_preferred":[
        "Edoor"
    ],
    "wof:name":"Edoor",
    "wof:placetype":"locality",
    "wof:population":1918
},
  "geometry": {"coordinates":[75.739935,11.952705],"type":"Point"}
}