{
  "type": "Feature",
  "properties": {
    "iso:country":"IN",
    "ks:ks_name":"Kamar Chak Babu Tola",
    "ks:ks_pop":476,
    "ks:ks_type":"HABITATION",
    "ks:ks_uagg_main":0,
    "name:eng_x_preferred":[
        "Kamar Chak Babu Tola"
    ],
    "wof:name":"Kamar Chak Babu Tola",
    "wof:placetype":"neighbourhood",
    "wof:population":476
},
  "geometry": {"coordinates":[84.894195,26.458446],"type":"Point"}
}