{
  "type": "Feature",
  "properties": {
    "gn:admin1_code":"19.0",
    "gn:admin2_code":"582.0",
    "gn:asciiname":"Munganahalli",
    "gn:country_code":"IN",
    "gn:dem":739,
    "gn:feature_class":"P",
    "gn:feature_code":"PPL",
    "gn:name":"Mung\u0101nahalli",
    "gn:population":0,
    "gn:timezone":"Asia/Kolkata",
    "iso:country":"IN",
    "wof:name":"Munganahalli",
    "wof:placetype":"locality"
},
  "geometry": {"coordinates":[78.17845,13.58711],"type":"Point"}
}