{
  "type": "Feature",
  "properties": {
    "iso:country":"IN",
    "ks:ks_name":"Syalkot",
    "ks:ks_pop":160,
    "ks:ks_type":"VILLAGE",
    "name:eng_x_preferred":[
        "Syalkot"
    ],
    "wof:name":"Syalkot",
    "wof:placetype":"locality",
    "wof:population":160
},
  "geometry": {"coordinates":[79.219407,30.155279],"type":"Point"}
}