{
  "type": "Feature",
  "properties": {
    "iso:country":"IN",
    "ks:ks_alt_nam":"Bhavanthula thanda",
    "ks:ks_name":"Bhavanthula Thanda",
    "ks:ks_pop":190,
    "ks:ks_type":"HABITATION",
    "name:eng_x_preferred":[
        "Bhavanthula Thanda"
    ],
    "wof:name":"Bhavanthula Thanda",
    "wof:placetype":"locality",
    "wof:population":190
},
  "geometry": {"coordinates":[79.700452,17.825432],"type":"Point"}
}