{
  "type": "Feature",
  "properties": {
    "gn:admin1_code":"12.0",
    "gn:admin2_code":"001",
    "gn:asciiname":"Kalam Chakla",
    "gn:country_code":"IN",
    "gn:dem":1687,
    "gn:feature_class":"P",
    "gn:feature_code":"PPL",
    "gn:name":"Kalam Chakla",
    "gn:population":0,
    "gn:timezone":"Asia/Kolkata",
    "iso:country":"IN",
    "wof:name":"Kalam Chakla",
    "wof:placetype":"locality"
},
  "geometry": {"coordinates":[74.23304,34.35294],"type":"Point"}
}