{
  "type": "Feature",
  "properties": {
    "iso:country":"IN",
    "ks:ks_name":"Majhgama",
    "ks:ks_pop":62,
    "ks:ks_type":"HABITATION",
    "name:eng_x_preferred":[
        "Majhgama"
    ],
    "wof:name":"Majhgama",
    "wof:placetype":"locality",
    "wof:population":62
},
  "geometry": {"coordinates":[87.693254,25.789217],"type":"Point"}
}