{
  "type": "Feature",
  "properties": {
    "iso:country":"IN",
    "ks:ks_name":"Konakar",
    "ks:ks_pop":130,
    "ks:ks_type":"HABITATION",
    "name:eng_x_preferred":[
        "Konakar"
    ],
    "wof:name":"Konakar",
    "wof:placetype":"locality",
    "wof:population":130
},
  "geometry": {"coordinates":[74.444913,14.306565],"type":"Point"}
}