{
  "type": "Feature",
  "properties": {
    "iso:country":"IN",
    "ks:ks_alt_nam":"poozhithode",
    "ks:ks_name":"Poozhithode",
    "ks:ks_pop":300,
    "ks:ks_type":"HABITATION",
    "name:eng_x_preferred":[
        "Poozhithode"
    ],
    "wof:name":"Poozhithode",
    "wof:placetype":"locality",
    "wof:population":300
},
  "geometry": {"coordinates":[75.857097,11.643834],"type":"Point"}
}