{
  "type": "Feature",
  "properties": {
    "gn:admin1_code":"12.0",
    "gn:admin2_code":"021",
    "gn:asciiname":"Bala",
    "gn:country_code":"IN",
    "gn:dem":497,
    "gn:feature_class":"P",
    "gn:feature_code":"PPL",
    "gn:name":"B\u0101la",
    "gn:population":0,
    "gn:timezone":"Asia/Kolkata",
    "iso:country":"IN",
    "name:bul_x_preferred":[
        "\u0411\u0430\u043b\u0430"
    ],
    "name:ceb_x_preferred":[
        "Bala"
    ],
    "name:ces_x_preferred":[
        "Bala"
    ],
    "name:cym_x_preferred":[
        "Bala"
    ],
    "name:deu_x_preferred":[
        "Bala"
    ],
    "name:epo_x_preferred":[
        "Bala"
    ],
    "name:fra_x_preferred":[
        "Bala"
    ],
    "name:glg_x_preferred":[
        "Bala"
    ],
    "name:hye_x_preferred":[
        "\u0532\u0561\u056c\u0561"
    ],
    "name:ita_x_preferred":[
        "Bala"
    ],
    "name:nld_x_preferred":[
        "Bala"
    ],
    "name:nor_x_preferred":[
        "Bala"
    ],
    "name:pol_x_preferred":[
        "Bala"
    ],
    "name:por_x_preferred":[
        "Bala"
    ],
    "name:ron_x_preferred":[
        "Bala"
    ],
    "name:rus_x_preferred":[
        "\u0411\u0430\u043b\u0430"
    ],
    "name:slv_x_preferred":[
        "Bala"
    ],
    "name:spa_x_preferred":[
        "Bala"
    ],
    "name:srp_x_preferred":[
        "\u0411\u0430\u043b\u0430"
    ],
    "name:swe_x_preferred":[
        "Bala"
    ],
    "name:tur_x_preferred":[
        "Bala"
    ],
    "name:ukr_x_preferred":[
        "\u0411\u0430\u043b\u0430"
    ],
    "wof:name":"Bala",
    "wof:placetype":"locality"
},
  "geometry": {"coordinates":[74.75139,32.97778],"type":"Point"}
}