{
  "type": "Feature",
  "properties": {
    "gn:admin1_code":"2.0",
    "gn:admin2_code":"552.0",
    "gn:asciiname":"Akkarampalle",
    "gn:country_code":"IN",
    "gn:dem":182,
    "gn:feature_class":"P",
    "gn:feature_code":"PPL",
    "gn:name":"Akkarampalle",
    "gn:population":0,
    "gn:timezone":"Asia/Kolkata",
    "iso:country":"IN",
    "name:bpy_x_preferred":[
        "\u0986\u0995\u09cd\u0995\u09be\u09b0\u09be\u09ae\u09aa\u09be\u09b2\u09cd\u09b2\u09c7"
    ],
    "name:ceb_x_preferred":[
        "Akkarampalle"
    ],
    "name:fas_x_preferred":[
        "\u0627\u06a9\u0627\u0631\u0627\u0645\u067e\u0627\u0644"
    ],
    "name:ita_x_preferred":[
        "Akkarampalle"
    ],
    "name:min_x_preferred":[
        "Akkarampalle"
    ],
    "name:msa_x_preferred":[
        "Akkarampalle"
    ],
    "name:new_x_preferred":[
        "\u0905\u0915\u094d\u0915\u0930\u092e\u092a\u0932\u094d\u0932\u0947"
    ],
    "name:nld_x_preferred":[
        "Akkarampalle"
    ],
    "name:por_x_preferred":[
        "Akkarampalle"
    ],
    "name:swe_x_preferred":[
        "Akkarampalle"
    ],
    "name:tam_x_preferred":[
        "\u0b85\u0b95\u0bcd\u0b95\u0bb0\u0bae\u0bcd\u0baa\u0bb2\u0bcd\u0bb2\u0bbf"
    ],
    "name:vie_x_preferred":[
        "Akkarampalle"
    ],
    "name:zho_x_preferred":[
        "\u963f\u514b\u5361\u62c9\u59c6\u5e15\u5c14\u83b1"
    ],
    "wof:name":"Akkarampalle",
    "wof:placetype":"locality"
},
  "geometry": {"coordinates":[78.38749,15.02181],"type":"Point"}
}