{
  "type": "Feature",
  "properties": {
    "iso:country":"IN",
    "ks:ks_name":"Liladoni",
    "ks:ks_pop":61,
    "ks:ks_type":"HABITATION",
    "name:eng_x_preferred":[
        "Liladoni"
    ],
    "wof:name":"Liladoni",
    "wof:placetype":"locality",
    "wof:population":61
},
  "geometry": {"coordinates":[87.43813900000001,24.816708],"type":"Point"}
}