{
  "type": "Feature",
  "properties": {
    "iso:country":"IN",
    "ks:ks_alt_nam":"KHATKHARIA",
    "ks:ks_name":"Khatkharia",
    "ks:ks_pop":38,
    "ks:ks_type":"HABITATION",
    "name:eng_x_preferred":[
        "Khatkharia"
    ],
    "wof:name":"Khatkharia",
    "wof:placetype":"locality",
    "wof:population":38
},
  "geometry": {"coordinates":[83.32390100000001,24.934416],"type":"Point"}
}