{
  "type": "Feature",
  "properties": {
    "gn:admin1_code":"35.0",
    "gn:admin2_code":"464.0",
    "gn:asciiname":"Kalikarai",
    "gn:country_code":"IN",
    "gn:dem":450,
    "gn:feature_class":"P",
    "gn:feature_code":"PPL",
    "gn:name":"K\u0101likarai",
    "gn:population":0,
    "gn:timezone":"Asia/Kolkata",
    "iso:country":"IN",
    "ks:ks_alt_nam":"K\u0101likarai",
    "ks:ks_name":"Kalikarai",
    "ks:ks_pop":220,
    "ks:ks_type":"VILLAGE",
    "name:eng_x_preferred":[
        "Kalikarai"
    ],
    "name:eng_x_variant":[
        "K\u0101likarai"
    ],
    "wof:name":"Kalikarai",
    "wof:placetype":"locality",
    "wof:population":220
},
  "geometry": {"coordinates":[74.97022800000001,22.858909],"type":"Point"}
}