{
  "type": "Feature",
  "properties": {
    "iso:country":"IN",
    "ks:ks_name":"Balbaspur",
    "ks:ks_pop":1169,
    "ks:ks_type":"VILLAGE",
    "name:eng_x_preferred":[
        "Balbaspur"
    ],
    "wof:name":"Balbaspur",
    "wof:placetype":"locality",
    "wof:population":1169
},
  "geometry": {"coordinates":[83.640963,22.039797],"type":"Point"}
}