{
  "type": "Feature",
  "properties": {
    "iso:country":"IN",
    "ks:ks_name":"Chhoto Kanaigachi",
    "ks:ks_pop":969,
    "ks:ks_type":"HABITATION",
    "name:eng_x_preferred":[
        "Chhoto Kanaigachi"
    ],
    "wof:name":"Chhoto Kanaigachi",
    "wof:placetype":"locality",
    "wof:population":969
},
  "geometry": {"coordinates":[88.215853,22.24959],"type":"Point"}
}