{
  "type": "Feature",
  "properties": {
    "gn:admin1_code":"19.0",
    "gn:admin2_code":"574.0",
    "gn:asciiname":"Gire Bommanahalli",
    "gn:country_code":"IN",
    "gn:dem":753,
    "gn:feature_class":"P",
    "gn:feature_code":"PPL",
    "gn:name":"Gire Bommanahalli",
    "gn:population":0,
    "gn:timezone":"Asia/Kolkata",
    "iso:country":"IN",
    "ks:ks_name":"Giribommenahalli",
    "ks:ks_pop":209,
    "ks:ks_type":"VILLAGE",
    "name:eng_x_preferred":[
        "Giribommenahalli"
    ],
    "name:eng_x_variant":[
        "Gire Bommanahalli"
    ],
    "wof:name":"Giribommenahalli",
    "wof:placetype":"locality",
    "wof:population":209
},
  "geometry": {"coordinates":[76.27944100000001,13.497705],"type":"Point"}
}