{
  "type": "Feature",
  "properties": {
    "gn:admin1_code":"19.0",
    "gn:admin2_code":"574.0",
    "gn:asciiname":"Gire Bommanahalli",
    "gn:country_code":"IN",
    "gn:dem":753,
    "gn:feature_class":"P",
    "gn:feature_code":"PPL",
    "gn:name":"Gire Bommanahalli",
    "gn:population":0,
    "gn:timezone":"Asia/Kolkata",
    "iso:country":"IN",
    "wof:name":"Gire Bommanahalli",
    "wof:placetype":"locality"
},
  "geometry": {"coordinates":[76.27934999999999,13.50281],"type":"Point"}
}