{
  "type": "Feature",
  "properties": {
    "iso:country":"IN",
    "name:dut_x_preferred":[
        "Vadakkevila"
    ],
    "name:eng_x_preferred":[
        "Vadakkevila"
    ],
    "qs:name":"Vadakkevila",
    "qs:name_adm0":"India",
    "qs:name_adm1":"Kerala",
    "qs:photos":25,
    "qs:photos_1k":5,
    "qs:photos_9k":1,
    "qs:photos_9r":1,
    "qs:photos_all":25,
    "qs:photos_sr":1,
    "qs:placetype":"Town",
    "qs:pop_sr":"0",
    "wd:wordcount":103,
    "wof:name":"Vadakkevila",
    "wof:placetype":"locality"
},
  "geometry": {"coordinates":[76.66809000000001,8.865736],"type":"Point"}
}