{
  "type": "Feature",
  "properties": {
    "gn:admin1_code":"21.0",
    "gn:admin2_code":"396.0",
    "gn:asciiname":"Khadikajor",
    "gn:country_code":"IN",
    "gn:dem":689,
    "gn:feature_class":"P",
    "gn:feature_code":"PPL",
    "gn:name":"Khadikajor",
    "gn:population":0,
    "gn:timezone":"Asia/Kolkata",
    "iso:country":"IN",
    "wof:name":"Khadikajor",
    "wof:placetype":"locality"
},
  "geometry": {"coordinates":[83.18895000000001,19.15918],"type":"Point"}
}