{
  "type": "Feature",
  "properties": {
    "gn:admin1_code":"2",
    "gn:admin2_code":"544.0",
    "gn:asciiname":"Rambilli",
    "gn:country_code":"IN",
    "gn:dem":23,
    "gn:feature_class":"P",
    "gn:feature_code":"PPL",
    "gn:name":"R\u0101mbilli",
    "gn:population":0,
    "gn:timezone":"Asia/Kolkata",
    "iso:country":"IN",
    "name:new_x_preferred":[
        "\u0930\u093e\u0902\u092c\u093f\u0932\u094d\u0932\u093f \u092e\u0923\u094d\u0921\u0932"
    ],
    "name:tam_x_preferred":[
        "\u0bb0\u0bbe\u0bae\u0bcd\u0baa\u0bbf\u0bb2\u0bcd\u0bb2\u0bbf \u0bae\u0ba3\u0bcd\u0b9f\u0bb2\u0bae\u0bcd"
    ],
    "name:tel_x_preferred":[
        "\u0c30\u0c3e\u0c02\u0c2c\u0c3f\u0c32\u0c4d\u0c32\u0c3f"
    ],
    "name:urd_x_preferred":[
        "\u0631\u0627\u0645\u0628\u0644\u06cc"
    ],
    "name:vie_x_preferred":[
        "Rambilli"
    ],
    "wof:name":"Rambilli",
    "wof:placetype":"locality"
},
  "geometry": {"coordinates":[82.93007,17.46369],"type":"Point"}
}