{
  "type": "Feature",
  "properties": {
    "iso:country":"IN",
    "ks:ks_name":"Birsing Halanga Char Pt-I",
    "ks:ks_pop":1559,
    "ks:ks_type":"VILLAGE",
    "name:eng_x_preferred":[
        "Birsing Halanga Char Pt-I"
    ],
    "wof:name":"Birsing Halanga Char Pt-I",
    "wof:placetype":"locality",
    "wof:population":1559
},
  "geometry": {"coordinates":[90.45483900000001,26.16282],"type":"Point"}
}