{
  "type": "Feature",
  "properties": {
    "gn:admin1_code":"10.0",
    "gn:admin2_code":"70.0",
    "gn:asciiname":"Mukand Majra",
    "gn:country_code":"IN",
    "gn:dem":284,
    "gn:feature_class":"P",
    "gn:feature_code":"PPL",
    "gn:name":"Mukand M\u0101jra",
    "gn:population":0,
    "gn:timezone":"Asia/Kolkata",
    "iso:country":"IN",
    "wof:name":"Mukand Majra",
    "wof:placetype":"locality"
},
  "geometry": {"coordinates":[77.12007,30.27477],"type":"Point"}
}