{
  "type": "Feature",
  "properties": {
    "gn:admin1_code":"36.0",
    "gn:admin2_code":"173.0",
    "gn:asciiname":"Larhwat",
    "gn:country_code":"IN",
    "gn:dem":100,
    "gn:feature_class":"P",
    "gn:feature_code":"PPL",
    "gn:name":"Larhwat",
    "gn:population":0,
    "gn:timezone":"Asia/Kolkata",
    "iso:country":"IN",
    "ks:ks_name":"Ladhwat",
    "ks:ks_pop":337,
    "ks:ks_type":"VILLAGE",
    "name:eng_x_preferred":[
        "Ladhwat"
    ],
    "name:eng_x_variant":[
        "Larhwat"
    ],
    "wof:name":"Ladhwat",
    "wof:placetype":"locality",
    "wof:population":337
},
  "geometry": {"coordinates":[81.759918,26.007039],"type":"Point"}
}