{
  "type": "Feature",
  "properties": {
    "iso:country":"IN",
    "ks:ks_name":"Matasar",
    "ks:ks_pop":827,
    "ks:ks_type":"VILLAGE",
    "name:eng_x_preferred":[
        "Matasar"
    ],
    "wof:name":"Matasar",
    "wof:placetype":"locality",
    "wof:population":827
},
  "geometry": {"coordinates":[71.61026699999999,25.792617],"type":"Point"}
}