{
  "type": "Feature",
  "properties": {
    "gn:admin1_code":"12.0",
    "gn:admin2_code":"7.0",
    "gn:asciiname":"Dhodan",
    "gn:country_code":"IN",
    "gn:dem":688,
    "gn:feature_class":"P",
    "gn:feature_code":"PPL",
    "gn:name":"Dhodan",
    "gn:population":0,
    "gn:timezone":"Asia/Kolkata",
    "iso:country":"IN",
    "wof:name":"Dhodan",
    "wof:placetype":"locality"
},
  "geometry": {"coordinates":[75.45886999999998,32.62539],"type":"Point"}
}