{
  "type": "Feature",
  "properties": {
    "gn:admin1_code":"22",
    "gn:admin2_code":"637.0",
    "gn:asciiname":"Pudutturai",
    "gn:country_code":"IN",
    "gn:dem":5,
    "gn:feature_class":"P",
    "gn:feature_code":"PPL",
    "gn:name":"Pudutturai",
    "gn:population":0,
    "gn:timezone":"Asia/Kolkata",
    "iso:country":"IN",
    "wof:name":"Pudutturai",
    "wof:placetype":"locality"
},
  "geometry": {"coordinates":[79.81711,10.91393],"type":"Point"}
}