{
  "type": "Feature",
  "properties": {
    "iso:country":"IN",
    "ks:ks_name":"Ghisan Ka Purwa",
    "ks:ks_pop":309,
    "ks:ks_type":"HABITATION",
    "ks:ks_uagg_main":0,
    "name:eng_x_preferred":[
        "Ghisan Ka Purwa"
    ],
    "wof:name":"Ghisan Ka Purwa",
    "wof:placetype":"neighbourhood",
    "wof:population":309
},
  "geometry": {"coordinates":[82.122968,25.706207],"type":"Point"}
}