{
  "type": "Feature",
  "properties": {
    "iso:country":"IN",
    "ks:ks_name":"Sitalpur",
    "ks:ks_pop":1622,
    "ks:ks_type":"HABITATION",
    "name:eng_x_preferred":[
        "Sitalpur"
    ],
    "wof:name":"Sitalpur",
    "wof:placetype":"locality",
    "wof:population":1622
},
  "geometry": {"coordinates":[86.35041,24.015359],"type":"Point"}
}