{
  "type": "Feature",
  "properties": {
    "iso:country":"IN",
    "ks:ks_name":"Yanadhi Indulu",
    "ks:ks_pop":158,
    "ks:ks_type":"HABITATION",
    "name:eng_x_preferred":[
        "Yanadhi Indulu"
    ],
    "wof:name":"Yanadhi Indulu",
    "wof:placetype":"locality",
    "wof:population":158
},
  "geometry": {"coordinates":[79.713213,13.262483],"type":"Point"}
}