{
  "type": "Feature",
  "properties": {
    "gn:admin1_code":"36",
    "gn:admin2_code":"196.0",
    "gn:asciiname":"Nenwa Khurd",
    "gn:country_code":"IN",
    "gn:dem":85,
    "gn:feature_class":"P",
    "gn:feature_code":"PPL",
    "gn:name":"Nenwa Khurd",
    "gn:population":0,
    "gn:timezone":"Asia/Kolkata",
    "iso:country":"IN",
    "ks:ks_name":"Ledwa Khurd",
    "ks:ks_pop":70,
    "ks:ks_type":"HABITATION",
    "name:eng_x_preferred":[
        "Ledwa Khurd"
    ],
    "name:eng_x_variant":[
        "Nenwa Khurd"
    ],
    "wof:name":"Ledwa Khurd",
    "wof:placetype":"locality",
    "wof:population":70
},
  "geometry": {"coordinates":[83.305795,25.073267],"type":"Point"}
}