{
  "type": "Feature",
  "properties": {
    "iso:country":"IN",
    "ks:ks_name":"Dakshin Jinanda",
    "ks:ks_pop":1937,
    "ks:ks_type":"VILLAGE",
    "name:eng_x_preferred":[
        "Dakshin Jinanda"
    ],
    "wof:name":"Dakshin Jinanda",
    "wof:placetype":"locality",
    "wof:population":1937
},
  "geometry": {"coordinates":[87.79845299999999,22.413472],"type":"Point"}
}