{
  "type": "Feature",
  "properties": {
    "gn:admin1_code":"24",
    "gn:admin2_code":"101.0",
    "gn:asciiname":"Lakhusar",
    "gn:country_code":"IN",
    "gn:dem":186,
    "gn:feature_class":"P",
    "gn:feature_code":"PPL",
    "gn:name":"Lakhusar",
    "gn:population":0,
    "gn:timezone":"Asia/Kolkata",
    "iso:country":"IN",
    "wof:name":"Lakhusar",
    "wof:placetype":"locality"
},
  "geometry": {"coordinates":[73.19194,28.33048],"type":"Point"}
}