{
  "type": "Feature",
  "properties": {
    "iso:country":"IN",
    "ks:ks_name":"Sahaspur",
    "ks:ks_pop":201,
    "ks:ks_type":"VILLAGE",
    "name:eng_x_preferred":[
        "Sahaspur"
    ],
    "wof:name":"Sahaspur",
    "wof:placetype":"locality",
    "wof:population":201
},
  "geometry": {"coordinates":[86.234532,21.026682],"type":"Point"}
}