{
  "type": "Feature",
  "properties": {
    "gn:admin1_code":"34.0",
    "gn:admin2_code":"234.0",
    "gn:asciiname":"Rupahtha",
    "gn:country_code":"IN",
    "gn:dem":103,
    "gn:feature_class":"P",
    "gn:feature_code":"PPL",
    "gn:name":"Rupahtha",
    "gn:population":0,
    "gn:timezone":"Asia/Kolkata",
    "iso:country":"IN",
    "wof:name":"Rupahtha",
    "wof:placetype":"locality"
},
  "geometry": {"coordinates":[84.03915000000001,25.07837],"type":"Point"}
}