{
  "type": "Feature",
  "properties": {
    "iso:country":"IN",
    "ks:ks_name":"Olambakadavu",
    "ks:ks_pop":1450,
    "ks:ks_type":"HABITATION",
    "name:eng_x_preferred":[
        "Olambakadavu"
    ],
    "wof:name":"Olambakadavu",
    "wof:placetype":"locality",
    "wof:population":1450
},
  "geometry": {"coordinates":[75.982263,10.752066],"type":"Point"}
}