{
  "type": "Feature",
  "properties": {
    "iso:country":"IN",
    "ks:ks_name":"Lvesaal",
    "ks:ks_pop":1029,
    "ks:ks_type":"VILLAGE",
    "ks:ks_uagg_main":0,
    "name:eng_x_preferred":[
        "Lvesaal"
    ],
    "wof:name":"Lvesaal",
    "wof:placetype":"locality",
    "wof:population":1029
},
  "geometry": {"coordinates":[79.532748,29.372905],"type":"Point"}
}