{
  "type": "Feature",
  "properties": {
    "gn:admin1_code":"39.0",
    "gn:admin2_code":"66.0",
    "gn:asciiname":"Gaonia Rao",
    "gn:country_code":"IN",
    "gn:dem":986,
    "gn:feature_class":"P",
    "gn:feature_code":"PPL",
    "gn:name":"Gaonia Rao",
    "gn:population":0,
    "gn:timezone":"Asia/Kolkata",
    "iso:country":"IN",
    "wof:name":"Gaonia Rao",
    "wof:placetype":"locality"
},
  "geometry": {"coordinates":[79.82193000000002,29.18197],"type":"Point"}
}