{
  "type": "Feature",
  "properties": {
    "iso:country":"IN",
    "ks:ks_alt_nam":"BALMUDHUSAI",
    "ks:ks_name":"Balmudhusai",
    "ks:ks_pop":218,
    "ks:ks_type":"HABITATION",
    "name:eng_x_preferred":[
        "Balmudhusai"
    ],
    "wof:name":"Balmudhusai",
    "wof:placetype":"locality",
    "wof:population":218
},
  "geometry": {"coordinates":[85.887339,22.129796],"type":"Point"}
}