{
  "type": "Feature",
  "properties": {
    "iso:country":"IN",
    "ks:ks_name":"Talon Ka Par",
    "ks:ks_pop":345,
    "ks:ks_type":"HABITATION",
    "name:eng_x_preferred":[
        "Talon Ka Par"
    ],
    "wof:name":"Talon Ka Par",
    "wof:placetype":"locality",
    "wof:population":345
},
  "geometry": {"coordinates":[71.23693400000001,26.09064],"type":"Point"}
}