{
  "type": "Feature",
  "properties": {
    "gn:admin1_code":"21",
    "gn:admin2_code":"394.0",
    "gn:asciiname":"Kirkita",
    "gn:country_code":"IN",
    "gn:dem":271,
    "gn:feature_class":"P",
    "gn:feature_code":"PPL",
    "gn:name":"Kirkita",
    "gn:population":0,
    "gn:timezone":"Asia/Kolkata",
    "iso:country":"IN",
    "ks:ks_name":"Kirkita",
    "ks:ks_pop":1608,
    "ks:ks_type":"VILLAGE",
    "name:eng_x_preferred":[
        "Kirkita"
    ],
    "wof:name":"Kirkita",
    "wof:placetype":"locality",
    "wof:population":1608
},
  "geometry": {"coordinates":[82.71911799999999,20.155958],"type":"Point"}
}