{
  "type": "Feature",
  "properties": {
    "iso:country":"IN",
    "ks:ks_name":"Chamraut",
    "ks:ks_pop":273,
    "ks:ks_type":"HABITATION",
    "name:eng_x_preferred":[
        "Chamraut"
    ],
    "wof:name":"Chamraut",
    "wof:placetype":"locality",
    "wof:population":273
},
  "geometry": {"coordinates":[82.60040100000001,26.3191],"type":"Point"}
}