{
  "type": "Feature",
  "properties": {
    "iso:country":"IN",
    "ks:ks_name":"Thonampatti",
    "ks:ks_pop":104,
    "ks:ks_type":"HABITATION",
    "name:eng_x_preferred":[
        "Thonampatti"
    ],
    "wof:name":"Thonampatti",
    "wof:placetype":"locality",
    "wof:population":104
},
  "geometry": {"coordinates":[78.065124,10.660366],"type":"Point"}
}