{
  "type": "Feature",
  "properties": {
    "iso:country":"IN",
    "ks:ks_name":"Sambudhanpur",
    "ks:ks_pop":582,
    "ks:ks_type":"HABITATION",
    "ks:ks_uagg_main":0,
    "name:eng_x_preferred":[
        "Sambudhanpur"
    ],
    "wof:name":"Sambudhanpur",
    "wof:placetype":"neighbourhood",
    "wof:population":582
},
  "geometry": {"coordinates":[93.138493,25.298858],"type":"Point"}
}