{
  "type": "Feature",
  "properties": {
    "iso:country":"IN",
    "ks:ks_name":"Adiwasiwadi",
    "ks:ks_pop":44,
    "ks:ks_type":"HABITATION",
    "name:eng_x_preferred":[
        "Adiwasiwadi"
    ],
    "wof:name":"Adiwasiwadi",
    "wof:placetype":"locality",
    "wof:population":44
},
  "geometry": {"coordinates":[73.201866,18.294836],"type":"Point"}
}