{
  "type": "Feature",
  "properties": {
    "iso:country":"IN",
    "ks:ks_name":"Bothara",
    "ks:ks_pop":841,
    "ks:ks_type":"HABITATION",
    "name:eng_x_preferred":[
        "Bothara"
    ],
    "wof:name":"Bothara",
    "wof:placetype":"locality",
    "wof:population":841
},
  "geometry": {"coordinates":[73.168069,24.836489],"type":"Point"}
}