{
  "type": "Feature",
  "properties": {
    "iso:country":"IN",
    "ks:ks_alt_nam":"Nakkapokala thanda",
    "ks:ks_name":"Nakkapokala Thanda",
    "ks:ks_pop":170,
    "ks:ks_type":"HABITATION",
    "name:eng_x_preferred":[
        "Nakkapokala Thanda"
    ],
    "wof:name":"Nakkapokala Thanda",
    "wof:placetype":"locality",
    "wof:population":170
},
  "geometry": {"coordinates":[79.183251,17.791867],"type":"Point"}
}