{
  "type": "Feature",
  "properties": {
    "iso:country":"IN",
    "ks:ks_name":"Subhanpur Kaseri Chak",
    "ks:ks_pop":447,
    "ks:ks_type":"VILLAGE",
    "name:eng_x_preferred":[
        "Subhanpur Kaseri Chak"
    ],
    "wof:name":"Subhanpur Kaseri Chak",
    "wof:placetype":"locality",
    "wof:population":447
},
  "geometry": {"coordinates":[85.73756299999999,25.156042],"type":"Point"}
}