{
  "type": "Feature",
  "properties": {
    "iso:country":"IN",
    "ks:ks_name":"Kulbadiya",
    "ks:ks_pop":714,
    "ks:ks_type":"VILLAGE",
    "ks:ks_uagg_main":0,
    "name:eng_x_preferred":[
        "Kulbadiya"
    ],
    "wof:name":"Kulbadiya",
    "wof:placetype":"neighbourhood",
    "wof:population":714
},
  "geometry": {"coordinates":[86.78291,22.41379],"type":"Point"}
}