{
  "type": "Feature",
  "properties": {
    "iso:country":"IN",
    "ks:ks_name":"Chhajali",
    "ks:ks_pop":372,
    "ks:ks_type":"VILLAGE",
    "name:eng_x_preferred":[
        "Chhajali"
    ],
    "wof:name":"Chhajali",
    "wof:placetype":"locality",
    "wof:population":372
},
  "geometry": {"coordinates":[73.725088,23.354189],"type":"Point"}
}