{
  "type": "Feature",
  "properties": {
    "gn:admin1_code":"25.0",
    "gn:admin2_code":"617.0",
    "gn:asciiname":"Annangarakuppam",
    "gn:country_code":"IN",
    "gn:dem":67,
    "gn:feature_class":"P",
    "gn:feature_code":"PPL",
    "gn:name":"Annang\u0101rakuppam",
    "gn:population":0,
    "gn:timezone":"Asia/Kolkata",
    "iso:country":"IN",
    "wof:name":"Annangarakuppam",
    "wof:placetype":"locality"
},
  "geometry": {"coordinates":[79.46283000000003,11.69459],"type":"Point"}
}