{
  "type": "Feature",
  "properties": {
    "iso:country":"IN",
    "ks:ks_name":"Peddabaladar",
    "ks:ks_pop":248,
    "ks:ks_type":"HABITATION",
    "ks:ks_uagg_main":0,
    "name:eng_x_preferred":[
        "Peddabaladar"
    ],
    "wof:name":"Peddabaladar",
    "wof:placetype":"neighbourhood",
    "wof:population":248
},
  "geometry": {"coordinates":[78.54563400000001,12.922516],"type":"Point"}
}