{
  "type": "Feature",
  "properties": {
    "iso:country":"IN",
    "ks:ks_name":"Barlapeta",
    "ks:ks_pop":480,
    "ks:ks_type":"HABITATION",
    "name:eng_x_preferred":[
        "Barlapeta"
    ],
    "wof:name":"Barlapeta",
    "wof:placetype":"locality",
    "wof:population":480
},
  "geometry": {"coordinates":[83.36685,17.986566],"type":"Point"}
}