{
  "type": "Feature",
  "properties": {
    "iso:country":"IN",
    "ks:ks_name":"Ponniagoundanur",
    "ks:ks_pop":116,
    "ks:ks_type":"HABITATION",
    "ks:ks_uagg_main":0,
    "name:eng_x_preferred":[
        "Ponniagoundanur"
    ],
    "wof:name":"Ponniagoundanur",
    "wof:placetype":"neighbourhood",
    "wof:population":116
},
  "geometry": {"coordinates":[77.947982,10.752444],"type":"Point"}
}