{
  "type": "Feature",
  "properties": {
    "iso:country":"IN",
    "ks:ks_name":"Ambliambagura",
    "ks:ks_pop":282,
    "ks:ks_type":"VILLAGE",
    "name:eng_x_preferred":[
        "Ambliambagura"
    ],
    "wof:name":"Ambliambagura",
    "wof:placetype":"locality",
    "wof:population":282
},
  "geometry": {"coordinates":[83.05002500000001,18.789377],"type":"Point"}
}