{
  "type": "Feature",
  "properties": {
    "iso:country":"IN",
    "ks:ks_name":"Gohadi",
    "ks:ks_type":"VILLAGE",
    "ks:ks_uagg_main":0,
    "name:eng_x_preferred":[
        "Gohadi"
    ],
    "wof:name":"Gohadi",
    "wof:placetype":"locality"
},
  "geometry": {"coordinates":[78.44204999999999,26.432778],"type":"Point"}
}