{
  "type": "Feature",
  "properties": {
    "iso:country":"IN",
    "qs:name":"Thalaiyari Palaiyam",
    "qs:name_adm0":"India",
    "qs:name_adm1":"Tamil Nadu",
    "qs:photos":24,
    "qs:photos_1k":5,
    "qs:photos_9k":1,
    "qs:photos_9r":1,
    "qs:photos_all":24,
    "qs:photos_sr":1,
    "qs:placetype":"Suburb",
    "qs:pop_sr":"0",
    "wof:name":"Thalaiyari Palaiyam",
    "wof:placetype":"neighbourhood"
},
  "geometry": {"coordinates":[80.2194745,13.04687],"type":"Point"}
}