{
  "type": "Feature",
  "properties": {
    "iso:country":"IN",
    "ks:ks_name":"Morwaniya",
    "ks:ks_pop":2730,
    "ks:ks_type":"VILLAGE",
    "name:eng_x_preferred":[
        "Morwaniya"
    ],
    "wof:name":"Morwaniya",
    "wof:placetype":"locality",
    "wof:population":2730
},
  "geometry": {"coordinates":[74.562945,23.779839],"type":"Point"}
}