{
  "type": "Feature",
  "properties": {
    "iso:country":"IN",
    "ks:ks_name":"Ambeerupadu",
    "ks:ks_pop":93,
    "ks:ks_type":"HABITATION",
    "name:eng_x_preferred":[
        "Ambeerupadu"
    ],
    "wof:name":"Ambeerupadu",
    "wof:placetype":"locality",
    "wof:population":93
},
  "geometry": {"coordinates":[82.37687,18.187118],"type":"Point"}
}