{
  "type": "Feature",
  "properties": {
    "gn:admin1_code":"36.0",
    "gn:admin2_code":"161",
    "gn:asciiname":"Nagla Demar",
    "gn:country_code":"IN",
    "gn:dem":150,
    "gn:feature_class":"P",
    "gn:feature_code":"PPL",
    "gn:name":"Nagla Dem\u0101r",
    "gn:population":0,
    "gn:timezone":"Asia/Kolkata",
    "iso:country":"IN",
    "name:und_x_variant":[
        "Nagla Dem\u0101r",
        "Dim\u0101r"
    ],
    "wof:name":"Nagla Demar",
    "wof:placetype":"neighbourhood"
},
  "geometry": {"coordinates":[79.13078,26.86366],"type":"Point"}
}