{
  "type": "Feature",
  "properties": {
    "gn:admin1_code":"36.0",
    "gn:admin2_code":"184.0",
    "gn:asciiname":"Bardahi Nankar",
    "gn:country_code":"IN",
    "gn:dem":93,
    "gn:feature_class":"P",
    "gn:feature_code":"PPL",
    "gn:name":"Bard\u0101hi N\u0101nk\u0101r",
    "gn:population":0,
    "gn:timezone":"Asia/Kolkata",
    "iso:country":"IN",
    "ks:ks_name":"Bardahi Nankar",
    "ks:ks_pop":1679,
    "ks:ks_type":"VILLAGE",
    "ks:ks_uagg_main":0,
    "name:eng_x_preferred":[
        "Bardahi Nankar"
    ],
    "wof:name":"Bardahi Nankar",
    "wof:placetype":"neighbourhood",
    "wof:population":1679
},
  "geometry": {"coordinates":[82.830128,27.244089],"type":"Point"}
}