{
  "type": "Feature",
  "properties": {
    "iso:country":"IN",
    "ks:ks_name":"Khutabari",
    "ks:ks_pop":356,
    "ks:ks_type":"HABITATION",
    "name:eng_x_preferred":[
        "Khutabari"
    ],
    "wof:name":"Khutabari",
    "wof:placetype":"locality",
    "wof:population":356
},
  "geometry": {"coordinates":[86.90752000000001,24.722299],"type":"Point"}
}