{
  "type": "Feature",
  "properties": {
    "gn:admin1_code":"10.0",
    "gn:admin2_code":"73.0",
    "gn:asciiname":"Ramana Ramani",
    "gn:country_code":"IN",
    "gn:dem":244,
    "gn:feature_class":"P",
    "gn:feature_code":"PPL",
    "gn:name":"Ram\u0101na Ram\u0101ni",
    "gn:population":0,
    "gn:timezone":"Asia/Kolkata",
    "iso:country":"IN",
    "wof:name":"Ramana Ramani",
    "wof:placetype":"locality"
},
  "geometry": {"coordinates":[76.58062,29.65336],"type":"Point"}
}