{
  "type": "Feature",
  "properties": {
    "iso:country":"IN",
    "ks:ks_name":"Syodha",
    "ks:ks_pop":1892,
    "ks:ks_type":"VILLAGE",
    "name:eng_x_preferred":[
        "Syodha"
    ],
    "wof:name":"Syodha",
    "wof:placetype":"locality",
    "wof:population":1892
},
  "geometry": {"coordinates":[80.366541,25.300211],"type":"Point"}
}