{
  "type": "Feature",
  "properties": {
    "iso:country":"IN",
    "ks:ks_name":"Chak Sultan Urf Tisauri",
    "ks:ks_pop":418,
    "ks:ks_type":"VILLAGE",
    "ks:ks_uagg_main":0,
    "name:eng_x_preferred":[
        "Chak Sultan Urf Tisauri"
    ],
    "wof:name":"Chak Sultan Urf Tisauri",
    "wof:placetype":"neighbourhood",
    "wof:population":418
},
  "geometry": {"coordinates":[83.60252699999999,25.484295],"type":"Point"}
}