{
  "type": "Feature",
  "properties": {
    "gn:admin1_code":"39",
    "gn:admin2_code":"61.0",
    "gn:asciiname":"Baunseli",
    "gn:country_code":"IN",
    "gn:dem":1050,
    "gn:feature_class":"P",
    "gn:feature_code":"PPL",
    "gn:name":"Baunseli",
    "gn:population":0,
    "gn:timezone":"Asia/Kolkata",
    "iso:country":"IN",
    "wof:name":"Baunseli",
    "wof:placetype":"locality"
},
  "geometry": {"coordinates":[78.39106,29.95952],"type":"Point"}
}