{
  "type": "Feature",
  "properties": {
    "iso:country":"IN",
    "ks:ks_name":"Borchiwadi",
    "ks:ks_pop":80,
    "ks:ks_type":"HABITATION",
    "name:eng_x_preferred":[
        "Borchiwadi"
    ],
    "wof:name":"Borchiwadi",
    "wof:placetype":"locality",
    "wof:population":80
},
  "geometry": {"coordinates":[73.72612599999999,16.513117],"type":"Point"}
}