{
  "type": "Feature",
  "properties": {
    "iso:country":"IN",
    "ks:ks_name":"Bhola Pura",
    "ks:ks_pop":80,
    "ks:ks_type":"HABITATION",
    "name:eng_x_preferred":[
        "Bhola Pura"
    ],
    "wof:name":"Bhola Pura",
    "wof:placetype":"locality",
    "wof:population":80
},
  "geometry": {"coordinates":[77.669211,26.821094],"type":"Point"}
}