{
  "type": "Feature",
  "properties": {
    "iso:country":"IN",
    "ks:ks_name":"Muppireddigaripalle",
    "ks:ks_pop":78,
    "ks:ks_type":"HABITATION",
    "name:eng_x_preferred":[
        "Muppireddigaripalle"
    ],
    "wof:name":"Muppireddigaripalle",
    "wof:placetype":"locality",
    "wof:population":78
},
  "geometry": {"coordinates":[78.936477,13.842879],"type":"Point"}
}