{
  "type": "Feature",
  "properties": {
    "gn:admin1_code":"2.0",
    "gn:admin2_code":"542.0",
    "gn:asciiname":"Chinna Dusi",
    "gn:country_code":"IN",
    "gn:dem":25,
    "gn:feature_class":"P",
    "gn:feature_code":"PPL",
    "gn:name":"Chinna D\u016bsi",
    "gn:population":0,
    "gn:timezone":"Asia/Kolkata",
    "iso:country":"IN",
    "wof:name":"Chinna Dusi",
    "wof:placetype":"locality"
},
  "geometry": {"coordinates":[83.85289,18.3784],"type":"Point"}
}