{
  "type": "Feature",
  "properties": {
    "gn:admin1_code":"38",
    "gn:admin2_code":"347.0",
    "gn:asciiname":"Pitij",
    "gn:country_code":"IN",
    "gn:dem":422,
    "gn:feature_class":"P",
    "gn:feature_code":"PPL",
    "gn:name":"Pitij",
    "gn:population":0,
    "gn:timezone":"Asia/Kolkata",
    "iso:country":"IN",
    "wof:name":"Pitij",
    "wof:placetype":"locality"
},
  "geometry": {"coordinates":[85.08363,24.25824],"type":"Point"}
}