{
  "type": "Feature",
  "properties": {
    "gn:admin1_code":"34.0",
    "gn:admin2_code":"232.0",
    "gn:asciiname":"Misrauliya",
    "gn:country_code":"IN",
    "gn:dem":62,
    "gn:feature_class":"P",
    "gn:feature_code":"PPL",
    "gn:name":"Misrauliya",
    "gn:population":0,
    "gn:timezone":"Asia/Kolkata",
    "iso:country":"IN",
    "ks:ks_name":"Misrauliya",
    "ks:ks_pop":37,
    "ks:ks_type":"VILLAGE",
    "name:eng_x_preferred":[
        "Misrauliya"
    ],
    "wof:name":"Misrauliya",
    "wof:placetype":"locality",
    "wof:population":37
},
  "geometry": {"coordinates":[84.149113,25.608796],"type":"Point"}
}