{
  "type": "Feature",
  "properties": {
    "gn:admin1_code":"23.0",
    "gn:admin2_code":"48.0",
    "gn:asciiname":"Khaspur",
    "gn:country_code":"IN",
    "gn:dem":232,
    "gn:feature_class":"P",
    "gn:feature_code":"PPL",
    "gn:name":"Kh\u0101spur",
    "gn:population":0,
    "gn:timezone":"Asia/Kolkata",
    "iso:country":"IN",
    "wof:name":"Khaspur",
    "wof:placetype":"locality"
},
  "geometry": {"coordinates":[76.08073,29.94296],"type":"Point"}
}