{
  "type": "Feature",
  "properties": {
    "iso:country":"IN",
    "ks:ks_name":"Dheeya",
    "ks:ks_pop":145,
    "ks:ks_type":"VILLAGE",
    "name:eng_x_preferred":[
        "Dheeya"
    ],
    "wof:name":"Dheeya",
    "wof:placetype":"locality",
    "wof:population":145
},
  "geometry": {"coordinates":[73.195436,24.111103],"type":"Point"}
}