{
  "type": "Feature",
  "properties": {
    "iso:country":"IN",
    "ks:ks_name":"Jasaiya",
    "ks:ks_pop":961,
    "ks:ks_type":"VILLAGE",
    "name:eng_x_preferred":[
        "Jasaiya"
    ],
    "wof:name":"Jasaiya",
    "wof:placetype":"locality",
    "wof:population":961
},
  "geometry": {"coordinates":[77.858813,24.338497],"type":"Point"}
}