{
  "type": "Feature",
  "properties": {
    "iso:country":"IN",
    "ks:ks_name":"Gemmelibaru Rf",
    "ks:ks_pop":96,
    "ks:ks_type":"HABITATION",
    "name:eng_x_preferred":[
        "Gemmelibaru Rf"
    ],
    "wof:name":"Gemmelibaru Rf",
    "wof:placetype":"locality",
    "wof:population":96
},
  "geometry": {"coordinates":[82.63221,17.908754],"type":"Point"}
}