{
  "type": "Feature",
  "properties": {
    "gn:admin1_code":"40.0",
    "gn:admin2_code":"533.0",
    "gn:asciiname":"Amarlabanda",
    "gn:country_code":"IN",
    "gn:dem":576,
    "gn:feature_class":"P",
    "gn:feature_code":"PPL",
    "gn:name":"Amarlabanda",
    "gn:population":0,
    "gn:timezone":"Asia/Kolkata",
    "iso:country":"IN",
    "wof:name":"Amarlabanda",
    "wof:placetype":"locality"
},
  "geometry": {"coordinates":[78.22556,18.37372],"type":"Point"}
}