{
  "type": "Feature",
  "properties": {
    "iso:country":"IN",
    "ks:ks_name":"Beeranapalli",
    "ks:ks_pop":516,
    "ks:ks_type":"HABITATION",
    "name:eng_x_preferred":[
        "Beeranapalli"
    ],
    "wof:name":"Beeranapalli",
    "wof:placetype":"locality",
    "wof:population":516
},
  "geometry": {"coordinates":[77.60657500000001,12.278923],"type":"Point"}
}