{
  "type": "Feature",
  "properties": {
    "iso:country":"IN",
    "ks:ks_name":"Rasulpur Khurd",
    "ks:ks_pop":1399,
    "ks:ks_type":"VILLAGE",
    "ks:ks_uagg_main":0,
    "name:eng_x_preferred":[
        "Rasulpur Khurd"
    ],
    "wof:name":"Rasulpur Khurd",
    "wof:placetype":"neighbourhood",
    "wof:population":1399
},
  "geometry": {"coordinates":[85.91365399999999,26.142731],"type":"Point"}
}