{
  "type": "Feature",
  "properties": {
    "gn:admin1_code":"35.0",
    "gn:admin2_code":"445.0",
    "gn:asciiname":"Ismailkheri",
    "gn:country_code":"IN",
    "gn:dem":507,
    "gn:feature_class":"P",
    "gn:feature_code":"PPL",
    "gn:name":"Ismailkheri",
    "gn:population":0,
    "gn:timezone":"Asia/Kolkata",
    "iso:country":"IN",
    "wof:name":"Ismailkheri",
    "wof:placetype":"locality"
},
  "geometry": {"coordinates":[76.49409,22.95256],"type":"Point"}
}