{
  "type": "Feature",
  "properties": {
    "iso:country":"IN",
    "ks:ks_alt_nam":"Moti molveri",
    "ks:ks_name":"Moti Molveri",
    "ks:ks_pop":40,
    "ks:ks_type":"HABITATION",
    "name:eng_x_preferred":[
        "Moti Molveri"
    ],
    "wof:name":"Moti Molveri",
    "wof:placetype":"locality",
    "wof:population":40
},
  "geometry": {"coordinates":[73.430561,20.59285],"type":"Point"}
}