{
  "type": "Feature",
  "properties": {
    "gn:admin1_code":"3.0",
    "gn:admin2_code":"308.0",
    "gn:asciiname":"Dimow",
    "gn:country_code":"IN",
    "gn:dem":131,
    "gn:feature_class":"P",
    "gn:feature_code":"PPL",
    "gn:name":"Dimow",
    "gn:population":0,
    "gn:timezone":"Asia/Kolkata",
    "iso:country":"IN",
    "wof:name":"Dimow",
    "wof:placetype":"neighbourhood"
},
  "geometry": {"coordinates":[94.81201,27.68239],"type":"Point"}
}