{
  "type": "Feature",
  "properties": {
    "iso:country":"IN",
    "ks:ks_name":"Khaitanpur",
    "ks:ks_pop":583,
    "ks:ks_type":"HABITATION",
    "name:eng_x_preferred":[
        "Khaitanpur"
    ],
    "wof:name":"Khaitanpur",
    "wof:placetype":"locality",
    "wof:population":583
},
  "geometry": {"coordinates":[80.85346,25.738834],"type":"Point"}
}