{
  "type": "Feature",
  "properties": {
    "iso:country":"IN",
    "ks:ks_name":"Thirumalaiahgaripalli",
    "ks:ks_pop":36,
    "ks:ks_type":"HABITATION",
    "name:eng_x_preferred":[
        "Thirumalaiahgaripalli"
    ],
    "wof:name":"Thirumalaiahgaripalli",
    "wof:placetype":"locality",
    "wof:population":36
},
  "geometry": {"coordinates":[79.199462,14.155591],"type":"Point"}
}