{
  "type": "Feature",
  "properties": {
    "iso:country":"IN",
    "ks:ks_name":"Ghunchapal",
    "ks:ks_pop":514,
    "ks:ks_type":"VILLAGE",
    "name:eng_x_preferred":[
        "Ghunchapal"
    ],
    "wof:name":"Ghunchapal",
    "wof:placetype":"locality",
    "wof:population":514
},
  "geometry": {"coordinates":[85.13607399999999,20.883973],"type":"Point"}
}