{
  "type": "Feature",
  "properties": {
    "iso:country":"IN",
    "ks:ks_alt_nam":"Parsakh\u0101r",
    "ks:ks_name":"Parsakhar",
    "ks:ks_pop":385,
    "ks:ks_type":"VILLAGE",
    "name:eng_x_preferred":[
        "Parsakhar"
    ],
    "name:eng_x_variant":[
        "Parsakh\u0101r"
    ],
    "wof:name":"Parsakhar",
    "wof:placetype":"locality",
    "wof:population":385
},
  "geometry": {"coordinates":[84.090222,23.932559],"type":"Point"}
}