{
  "type": "Feature",
  "properties": {
    "iso:country":"IN",
    "ks:ks_name":"Berna Kampa",
    "ks:ks_pop":290,
    "ks:ks_type":"HABITATION",
    "name:eng_x_preferred":[
        "Berna Kampa"
    ],
    "wof:name":"Berna Kampa",
    "wof:placetype":"neighbourhood",
    "wof:population":290
},
  "geometry": {"coordinates":[72.98802499999999,23.609394],"type":"Point"}
}