{
  "type": "Feature",
  "properties": {
    "iso:country":"IN",
    "ks:ks_name":"Jawala Dumala",
    "ks:ks_pop":1748,
    "ks:ks_type":"VILLAGE",
    "name:eng_x_preferred":[
        "Jawala Dumala"
    ],
    "wof:name":"Jawala Dumala",
    "wof:placetype":"locality",
    "wof:population":1748
},
  "geometry": {"coordinates":[76.00462899999999,18.322324],"type":"Point"}
}