{
  "type": "Feature",
  "properties": {
    "iso:country":"IN",
    "ks:ks_name":"Gutumbi",
    "ks:ks_pop":320,
    "ks:ks_type":"HABITATION",
    "name:eng_x_preferred":[
        "Gutumbi"
    ],
    "wof:name":"Gutumbi",
    "wof:placetype":"locality",
    "wof:population":320
},
  "geometry": {"coordinates":[74.184844,14.762195],"type":"Point"}
}