{
  "type": "Feature",
  "properties": {
    "iso:country":"IN",
    "ks:ks_name":"Kadapani",
    "ks:ks_pop":744,
    "ks:ks_type":"VILLAGE",
    "name:eng_x_preferred":[
        "Kadapani"
    ],
    "wof:name":"Kadapani",
    "wof:placetype":"locality",
    "wof:population":744
},
  "geometry": {"coordinates":[86.424105,22.169135],"type":"Point"}
}