{
  "type": "Feature",
  "properties": {
    "gn:admin1_code":"12",
    "gn:admin2_code":"3.0",
    "gn:asciiname":"Naerung",
    "gn:country_code":"IN",
    "gn:dem":3407,
    "gn:feature_class":"P",
    "gn:feature_code":"PPL",
    "gn:name":"Naerung",
    "gn:population":0,
    "gn:timezone":"Asia/Kolkata",
    "iso:country":"IN",
    "wof:name":"Naerung",
    "wof:placetype":"locality"
},
  "geometry": {"coordinates":[76.91336,33.88499],"type":"Point"}
}