{
  "type": "Feature",
  "properties": {
    "iso:country":"IN",
    "ks:ks_name":"Chhotka Purwa m",
    "ks:ks_pop":1011,
    "ks:ks_type":"HABITATION",
    "name:eng_x_preferred":[
        "Chhotka Purwa m"
    ],
    "wof:name":"Chhotka Purwa m",
    "wof:placetype":"locality",
    "wof:population":1011
},
  "geometry": {"coordinates":[82.90488999999999,26.578166],"type":"Point"}
}