{
  "type": "Feature",
  "properties": {
    "iso:country":"IN",
    "ks:ks_name":"Bhabhor Falia",
    "ks:ks_pop":921,
    "ks:ks_type":"HABITATION",
    "name:eng_x_preferred":[
        "Bhabhor Falia"
    ],
    "wof:name":"Bhabhor Falia",
    "wof:placetype":"locality",
    "wof:population":921
},
  "geometry": {"coordinates":[74.401667,22.8845],"type":"Point"}
}