{
  "type": "Feature",
  "properties": {
    "iso:country":"IN",
    "ks:ks_name":"Lohepar",
    "ks:ks_pop":4048,
    "ks:ks_type":"HABITATION",
    "ks:ks_uagg_main":0,
    "name:eng_x_preferred":[
        "Lohepar"
    ],
    "wof:name":"Lohepar",
    "wof:placetype":"neighbourhood",
    "wof:population":4048
},
  "geometry": {"coordinates":[83.76190099999999,27.122881],"type":"Point"}
}