{
  "type": "Feature",
  "properties": {
    "iso:country":"IN",
    "ks:ks_name":"Husepura Jagir",
    "ks:ks_pop":990,
    "ks:ks_type":"VILLAGE",
    "name:eng_x_preferred":[
        "Husepura Jagir"
    ],
    "wof:name":"Husepura Jagir",
    "wof:placetype":"locality",
    "wof:population":990
},
  "geometry": {"coordinates":[79.237565,26.400539],"type":"Point"}
}