{
  "type": "Feature",
  "properties": {
    "gn:admin1_code":"36",
    "gn:admin2_code":"186.0",
    "gn:asciiname":"Ekla Mafi",
    "gn:country_code":"IN",
    "gn:dem":88,
    "gn:feature_class":"P",
    "gn:feature_code":"PPL",
    "gn:name":"Ekla M\u0101fi",
    "gn:population":0,
    "gn:timezone":"Asia/Kolkata",
    "iso:country":"IN",
    "ks:ks_alt_nam":"Ekla M\u0101fi",
    "ks:ks_name":"Ekla Mafi",
    "ks:ks_pop":153,
    "ks:ks_type":"VILLAGE",
    "ks:ks_uagg_main":0,
    "name:eng_x_preferred":[
        "Ekla Mafi"
    ],
    "name:eng_x_variant":[
        "Ekla M\u0101fi"
    ],
    "wof:name":"Ekla Mafi",
    "wof:placetype":"neighbourhood",
    "wof:population":153
},
  "geometry": {"coordinates":[83.11850800000001,26.990301],"type":"Point"}
}