{
  "type": "Feature",
  "properties": {
    "iso:country":"IN",
    "ks:ks_name":"Salimarpur",
    "ks:ks_pop":720,
    "ks:ks_type":"HABITATION",
    "name:eng_x_preferred":[
        "Salimarpur"
    ],
    "wof:name":"Salimarpur",
    "wof:placetype":"locality",
    "wof:population":720
},
  "geometry": {"coordinates":[88.13030500000001,22.305584],"type":"Point"}
}