{
  "type": "Feature",
  "properties": {
    "iso:country":"IN",
    "ks:ks_alt_nam":"D\u016bngi",
    "ks:ks_alt_nam_2":"Dungi",
    "ks:ks_name":"Dongi",
    "ks:ks_pop":0,
    "ks:ks_type":"VILLAGE",
    "name:eng_x_preferred":[
        "Dongi"
    ],
    "name:eng_x_variant":[
        "D\u016bngi",
        "Dungi"
    ],
    "wof:name":"Dongi",
    "wof:placetype":"locality",
    "wof:population":0
},
  "geometry": {"coordinates":[77.271463,19.791252],"type":"Point"}
}