{
  "type": "Feature",
  "properties": {
    "iso:country":"IN",
    "ks:ks_name":"Bander Bhita",
    "ks:ks_pop":1076,
    "ks:ks_type":"HABITATION",
    "name:eng_x_preferred":[
        "Bander Bhita"
    ],
    "wof:name":"Bander Bhita",
    "wof:placetype":"locality",
    "wof:population":1076
},
  "geometry": {"coordinates":[89.59159699999999,26.360085],"type":"Point"}
}