{
  "type": "Feature",
  "properties": {
    "iso:country":"IN",
    "ks:ks_name":"Kubbatti",
    "ks:ks_pop":26,
    "ks:ks_type":"HABITATION",
    "name:eng_x_preferred":[
        "Kubbatti"
    ],
    "wof:name":"Kubbatti",
    "wof:placetype":"locality",
    "wof:population":26
},
  "geometry": {"coordinates":[74.712891,14.87398],"type":"Point"}
}