{
  "type": "Feature",
  "properties": {
    "gn:admin1_code":"19.0",
    "gn:admin2_code":"561.0",
    "gn:asciiname":"Mugli",
    "gn:country_code":"IN",
    "gn:dem":565,
    "gn:feature_class":"P",
    "gn:feature_code":"PPL",
    "gn:name":"Mugli",
    "gn:population":0,
    "gn:timezone":"Asia/Kolkata",
    "iso:country":"IN",
    "wof:name":"Mugli",
    "wof:placetype":"locality"
},
  "geometry": {"coordinates":[75.78391999999999,15.73992],"type":"Point"}
}