{
  "type": "Feature",
  "properties": {
    "gn:admin1_code":"16",
    "gn:admin2_code":"523.0",
    "gn:asciiname":"Talkhed",
    "gn:country_code":"IN",
    "gn:dem":457,
    "gn:feature_class":"P",
    "gn:feature_code":"PPL",
    "gn:name":"T\u0101lkhed",
    "gn:population":0,
    "gn:timezone":"Asia/Kolkata",
    "iso:country":"IN",
    "name:und_x_variant":[
        "Talkhad",
        "T\u0101lkher",
        "T\u0101lkhed"
    ],
    "wof:name":"Talkhed",
    "wof:placetype":"locality"
},
  "geometry": {"coordinates":[76.03368,19.18243],"type":"Point"}
}