{
  "type": "Feature",
  "properties": {
    "iso:country":"IN",
    "ks:ks_name":"Namdhari Keri",
    "ks:ks_pop":387,
    "ks:ks_type":"HABITATION",
    "name:eng_x_preferred":[
        "Namdhari Keri"
    ],
    "wof:name":"Namdhari Keri",
    "wof:placetype":"locality",
    "wof:population":387
},
  "geometry": {"coordinates":[74.38410399999999,14.563439],"type":"Point"}
}