{
  "type": "Feature",
  "properties": {
    "gn:admin1_code":"24",
    "gn:admin2_code":"128.0",
    "gn:asciiname":"Balarpur",
    "gn:country_code":"IN",
    "gn:dem":313,
    "gn:feature_class":"P",
    "gn:feature_code":"PPL",
    "gn:name":"B\u0101l\u0101rpur",
    "gn:population":0,
    "gn:timezone":"Asia/Kolkata",
    "iso:country":"IN",
    "ks:ks_name":"Balharpur",
    "ks:ks_pop":484,
    "ks:ks_type":"VILLAGE",
    "name:eng_x_preferred":[
        "Balharpur"
    ],
    "name:eng_x_variant":[
        "Balarpur"
    ],
    "wof:name":"Balharpur",
    "wof:placetype":"locality",
    "wof:population":484
},
  "geometry": {"coordinates":[77.227035,25.165978],"type":"Point"}
}