{
  "type": "Feature",
  "properties": {
    "iso:country":"IN",
    "ks:ks_name":"Anthara",
    "ks:ks_pop":138,
    "ks:ks_type":"HABITATION",
    "name:eng_x_preferred":[
        "Anthara"
    ],
    "wof:name":"Anthara",
    "wof:placetype":"locality",
    "wof:population":138
},
  "geometry": {"coordinates":[75.146265,12.940605],"type":"Point"}
}