{
  "type": "Feature",
  "properties": {
    "gn:admin1_code":"36.0",
    "gn:admin2_code":"149.0",
    "gn:asciiname":"Jaitpur ki Mandaiyan",
    "gn:country_code":"IN",
    "gn:dem":188,
    "gn:feature_class":"P",
    "gn:feature_code":"PPL",
    "gn:name":"Jaitpur ki Mandaiy\u0101n",
    "gn:population":0,
    "gn:timezone":"Asia/Kolkata",
    "iso:country":"IN",
    "wof:name":"Jaitpur ki Mandaiyan",
    "wof:placetype":"locality"
},
  "geometry": {"coordinates":[78.55412,28.35251],"type":"Point"}
}