{
  "type": "Feature",
  "properties": {
    "gn:admin1_code":"24.0",
    "gn:admin2_code":"104.0",
    "gn:asciiname":"Kala Chhara",
    "gn:country_code":"IN",
    "gn:dem":320,
    "gn:feature_class":"P",
    "gn:feature_code":"PPL",
    "gn:name":"K\u0101la Chh\u0101ra",
    "gn:population":0,
    "gn:timezone":"Asia/Kolkata",
    "iso:country":"IN",
    "ks:ks_alt_nam":"K\u0101la Chh\u0101ra",
    "ks:ks_name":"Kala Chhara",
    "ks:ks_pop":155,
    "ks:ks_type":"VILLAGE",
    "name:eng_x_preferred":[
        "Kala Chhara"
    ],
    "name:eng_x_variant":[
        "K\u0101la Chh\u0101ra"
    ],
    "wof:name":"Kala Chhara",
    "wof:placetype":"locality",
    "wof:population":155
},
  "geometry": {"coordinates":[76.424103,27.436686],"type":"Point"}
}