{
  "type": "Feature",
  "properties": {
    "gn:admin1_code":"19.0",
    "gn:admin2_code":"566.0",
    "gn:asciiname":"Devarahatti",
    "gn:country_code":"IN",
    "gn:dem":604,
    "gn:feature_class":"P",
    "gn:feature_code":"PPL",
    "gn:name":"Devarahatti",
    "gn:population":0,
    "gn:timezone":"Asia/Kolkata",
    "iso:country":"IN",
    "wof:name":"Devarahatti",
    "wof:placetype":"locality"
},
  "geometry": {"coordinates":[76.53393,14.43105],"type":"Point"}
}