{
  "type": "Feature",
  "properties": {
    "iso:country":"IN",
    "ks:ks_name":"Nayagaon",
    "ks:ks_pop":125,
    "ks:ks_type":"HABITATION",
    "name:eng_x_preferred":[
        "Nayagaon"
    ],
    "wof:name":"Nayagaon",
    "wof:placetype":"locality",
    "wof:population":125
},
  "geometry": {"coordinates":[76.403142,24.339035],"type":"Point"}
}