{
  "type": "Feature",
  "properties": {
    "gn:admin1_code":"10",
    "gn:admin2_code":"70.0",
    "gn:asciiname":"Toba",
    "gn:country_code":"IN",
    "gn:dem":287,
    "gn:feature_class":"P",
    "gn:feature_code":"PPL",
    "gn:name":"Toba",
    "gn:population":0,
    "gn:timezone":"Asia/Kolkata",
    "iso:country":"IN",
    "name:cat_x_preferred":[
        "Toba"
    ],
    "name:ceb_x_preferred":[
        "Toba"
    ],
    "name:che_x_preferred":[
        "\u0422\u043e\u0431\u0430"
    ],
    "name:cym_x_preferred":[
        "Toba"
    ],
    "name:deu_x_preferred":[
        "Toba"
    ],
    "name:eus_x_preferred":[
        "Toba"
    ],
    "name:fas_x_preferred":[
        "\u062a\u0648\u0628\u0627"
    ],
    "name:fra_x_preferred":[
        "Toba"
    ],
    "name:hrv_x_preferred":[
        "Toba"
    ],
    "name:ind_x_preferred":[
        "Toba"
    ],
    "name:ita_x_preferred":[
        "Toba"
    ],
    "name:lit_x_preferred":[
        "Toba"
    ],
    "name:mlg_x_preferred":[
        "Toba"
    ],
    "name:nld_x_preferred":[
        "Toba"
    ],
    "name:pol_x_preferred":[
        "Toba"
    ],
    "name:por_x_preferred":[
        "Toba"
    ],
    "name:ron_x_preferred":[
        "Toba"
    ],
    "name:rus_x_preferred":[
        "\u0422\u043e\u0431\u0430"
    ],
    "name:slk_x_preferred":[
        "Toba"
    ],
    "name:spa_x_preferred":[
        "Toba"
    ],
    "name:srp_x_preferred":[
        "\u0422\u043e\u0431\u0430"
    ],
    "name:swa_x_preferred":[
        "Toba"
    ],
    "name:swe_x_preferred":[
        "Toba"
    ],
    "name:tur_x_preferred":[
        "Toba"
    ],
    "wof:name":"Toba",
    "wof:placetype":"locality"
},
  "geometry": {"coordinates":[76.96831,30.35122],"type":"Point"}
}