{
  "type": "Feature",
  "properties": {
    "gn:admin1_code":"39.0",
    "gn:admin2_code":"62.0",
    "gn:asciiname":"Ogla",
    "gn:country_code":"IN",
    "gn:dem":1517,
    "gn:feature_class":"P",
    "gn:feature_code":"PPL",
    "gn:name":"Ogla",
    "gn:population":0,
    "gn:timezone":"Asia/Kolkata",
    "iso:country":"IN",
    "name:guj_x_preferred":[
        "\u0a93\u0a97\u0acd\u0ab2\u0abe"
    ],
    "name:hin_x_preferred":[
        "\u0913\u0917\u0932\u093e"
    ],
    "name:new_x_preferred":[
        "\u0913\u0917\u0932\u093e"
    ],
    "name:swe_x_preferred":[
        "Kumaun"
    ],
    "wof:name":"Ogla",
    "wof:placetype":"locality"
},
  "geometry": {"coordinates":[80.28386999999999,29.75423],"type":"Point"}
}