{
  "type": "Feature",
  "properties": {
    "iso:country":"IN",
    "ks:ks_name":"Radhanagar",
    "ks:ks_pop":154,
    "ks:ks_type":"VILLAGE",
    "name:eng_x_preferred":[
        "Radhanagar"
    ],
    "wof:name":"Radhanagar",
    "wof:placetype":"locality",
    "wof:population":154
},
  "geometry": {"coordinates":[86.011791,22.688726],"type":"Point"}
}