{
  "type": "Feature",
  "properties": {
    "gn:admin1_code":"18.0",
    "gn:admin2_code":"299.0",
    "gn:asciiname":"Mukhla",
    "gn:country_code":"IN",
    "gn:dem":1340,
    "gn:feature_class":"P",
    "gn:feature_code":"PPL",
    "gn:name":"Mukhla",
    "gn:population":0,
    "gn:timezone":"Asia/Kolkata",
    "iso:country":"IN",
    "wof:name":"Mukhla",
    "wof:placetype":"locality"
},
  "geometry": {"coordinates":[92.22028,25.48226],"type":"Point"}
}