{
  "type": "Feature",
  "properties": {
    "iso:country":"IN",
    "ks:ks_name":"Nuniabad",
    "ks:ks_pop":320,
    "ks:ks_type":"VILLAGE",
    "name:eng_x_preferred":[
        "Nuniabad"
    ],
    "wof:name":"Nuniabad",
    "wof:placetype":"locality",
    "wof:population":320
},
  "geometry": {"coordinates":[86.945694,23.164223],"type":"Point"}
}