{
  "type": "Feature",
  "properties": {
    "gn:admin1_code":"39.0",
    "gn:admin2_code":"59.0",
    "gn:asciiname":"Khandanu",
    "gn:country_code":"IN",
    "gn:dem":1688,
    "gn:feature_class":"P",
    "gn:feature_code":"PPL",
    "gn:name":"Kh\u0101ndanu",
    "gn:population":0,
    "gn:timezone":"Asia/Kolkata",
    "iso:country":"IN",
    "wof:name":"Khandanu",
    "wof:placetype":"locality"
},
  "geometry": {"coordinates":[78.24475,30.49787],"type":"Point"}
}