{
  "type": "Feature",
  "properties": {
    "gn:admin1_code":"39.0",
    "gn:admin2_code":"59.0",
    "gn:asciiname":"Khandanu",
    "gn:country_code":"IN",
    "gn:dem":1688,
    "gn:feature_class":"P",
    "gn:feature_code":"PPL",
    "gn:name":"Kh\u0101ndanu",
    "gn:population":0,
    "gn:timezone":"Asia/Kolkata",
    "iso:country":"IN",
    "ks:ks_name":"Khandanu",
    "ks:ks_pop":191,
    "ks:ks_type":"VILLAGE",
    "name:eng_x_preferred":[
        "Khandanu"
    ],
    "wof:name":"Khandanu",
    "wof:placetype":"locality",
    "wof:population":191
},
  "geometry": {"coordinates":[78.23559899999999,30.501906],"type":"Point"}
}