{
  "type": "Feature",
  "properties": {
    "iso:country":"IN",
    "ks:ks_name":"Dagla",
    "ks:ks_pop":504,
    "ks:ks_type":"VILLAGE",
    "name:eng_x_preferred":[
        "Dagla"
    ],
    "wof:name":"Dagla",
    "wof:placetype":"locality",
    "wof:population":504
},
  "geometry": {"coordinates":[73.363528,24.024861],"type":"Point"}
}