{
  "type": "Feature",
  "properties": {
    "gn:admin1_code":"10",
    "gn:admin2_code":"87.0",
    "gn:asciiname":"Jarpuri",
    "gn:country_code":"IN",
    "gn:dem":200,
    "gn:feature_class":"P",
    "gn:feature_code":"PPL",
    "gn:name":"J\u0101rpuri",
    "gn:population":0,
    "gn:timezone":"Asia/Kolkata",
    "iso:country":"IN",
    "ks:ks_name":"Jharpuri",
    "ks:ks_pop":1818,
    "ks:ks_type":"VILLAGE",
    "name:eng_x_preferred":[
        "Jharpuri"
    ],
    "name:eng_x_variant":[
        "Jarpuri"
    ],
    "wof:name":"Jharpuri",
    "wof:placetype":"locality",
    "wof:population":1818
},
  "geometry": {"coordinates":[77.103427,27.860807],"type":"Point"}
}