{
  "type": "Feature",
  "properties": {
    "iso:country":"IN",
    "ks:ks_name":"Paschim Goalgaon",
    "ks:ks_pop":1069,
    "ks:ks_type":"VILLAGE",
    "name:eng_x_preferred":[
        "Paschim Goalgaon"
    ],
    "wof:name":"Paschim Goalgaon",
    "wof:placetype":"locality",
    "wof:population":1069
},
  "geometry": {"coordinates":[87.844505,25.899425],"type":"Point"}
}