{
  "type": "Feature",
  "properties": {
    "iso:country":"IN",
    "ks:ks_name":"Bag",
    "ks:ks_pop":320,
    "ks:ks_type":"HABITATION",
    "name:eng_x_preferred":[
        "Bag"
    ],
    "wof:name":"Bag",
    "wof:placetype":"locality",
    "wof:population":320
},
  "geometry": {"coordinates":[73.18305599999999,17.500556],"type":"Point"}
}