{
  "type": "Feature",
  "properties": {
    "iso:country":"IN",
    "ks:ks_name":"Tola Bathna",
    "ks:ks_pop":330,
    "ks:ks_type":"VILLAGE",
    "name:eng_x_preferred":[
        "Tola Bathna"
    ],
    "wof:name":"Tola Bathna",
    "wof:placetype":"locality",
    "wof:population":330
},
  "geometry": {"coordinates":[86.32107999999999,24.55928],"type":"Point"}
}