{
  "type": "Feature",
  "properties": {
    "iso:country":"IN",
    "ks:ks_name":"Vellegoundenpudur",
    "ks:ks_pop":506,
    "ks:ks_type":"HABITATION",
    "name:eng_x_preferred":[
        "Vellegoundenpudur"
    ],
    "wof:name":"Vellegoundenpudur",
    "wof:placetype":"locality",
    "wof:population":506
},
  "geometry": {"coordinates":[77.109886,10.840829],"type":"Point"}
}