{
  "type": "Feature",
  "properties": {
    "gn:admin1_code":"36.0",
    "gn:admin2_code":"141.0",
    "gn:asciiname":"Chhaprauli",
    "gn:country_code":"IN",
    "gn:dem":203,
    "gn:feature_class":"P",
    "gn:feature_code":"PPL",
    "gn:name":"Chhaprauli",
    "gn:population":0,
    "gn:timezone":"Asia/Kolkata",
    "iso:country":"IN",
    "name:bpy_x_preferred":[
        "\u099b\u09be\u09aa\u09cd\u09b0\u09cc\u09b2\u09bf"
    ],
    "name:ceb_x_preferred":[
        "Chhaprauli"
    ],
    "name:hin_x_preferred":[
        "\u091b\u092a\u0930\u094c\u0932\u0940"
    ],
    "name:ita_x_preferred":[
        "Chhaprauli"
    ],
    "name:mlg_x_preferred":[
        "Chhaprauli"
    ],
    "name:msa_x_preferred":[
        "Chhaprauli"
    ],
    "name:new_x_preferred":[
        "\u091b\u092a\u094d\u0930\u094c\u0932\u0940"
    ],
    "name:nld_x_preferred":[
        "Chhaprauli"
    ],
    "name:pol_x_preferred":[
        "Chhaprauli"
    ],
    "name:por_x_preferred":[
        "Chhaprauli"
    ],
    "name:swe_x_preferred":[
        "Chhaprauli"
    ],
    "name:urd_x_preferred":[
        "\u0686\u06be\u067e\u0631\u0648\u0644\u06cc"
    ],
    "name:vie_x_preferred":[
        "Chhaprauli"
    ],
    "name:zho_x_preferred":[
        "\u6070\u666e\u52b3\u5229"
    ],
    "wof:name":"Chhaprauli",
    "wof:placetype":"locality"
},
  "geometry": {"coordinates":[77.41693000000002,28.49114],"type":"Point"}
}