{
  "type": "Feature",
  "properties": {
    "iso:country":"IN",
    "ks:ks_name":"Matagur",
    "ks:ks_pop":10,
    "ks:ks_type":"HABITATION",
    "name:eng_x_preferred":[
        "Matagur"
    ],
    "wof:name":"Matagur",
    "wof:placetype":"locality",
    "wof:population":10
},
  "geometry": {"coordinates":[75.771529,12.780525],"type":"Point"}
}