{
  "type": "Feature",
  "properties": {
    "gn:admin1_code":"35.0",
    "gn:admin2_code":"439.0",
    "gn:asciiname":"Ahirkheri",
    "gn:country_code":"IN",
    "gn:dem":570,
    "gn:feature_class":"P",
    "gn:feature_code":"PPL",
    "gn:name":"Ah\u012brkheri",
    "gn:population":0,
    "gn:timezone":"Asia/Kolkata",
    "iso:country":"IN",
    "ks:ks_alt_nam":"Ah\u012brkheri",
    "ks:ks_name":"Ahirkheri",
    "ks:ks_type":"VILLAGE",
    "wof:name":"Ahirkheri",
    "wof:placetype":"neighbourhood"
},
  "geometry": {"coordinates":[75.80482000000001,22.68],"type":"Point"}
}