{
  "type": "Feature",
  "properties": {
    "iso:country":"IN",
    "ks:ks_name":"Nagla Swaroop Nagar",
    "ks:ks_pop":383,
    "ks:ks_type":"HABITATION",
    "name:eng_x_preferred":[
        "Nagla Swaroop Nagar"
    ],
    "wof:name":"Nagla Swaroop Nagar",
    "wof:placetype":"locality",
    "wof:population":383
},
  "geometry": {"coordinates":[79.398718,26.456403],"type":"Point"}
}