{
  "type": "Feature",
  "properties": {
    "gn:admin1_code":"36",
    "gn:admin2_code":"200.0",
    "gn:asciiname":"Kashi",
    "gn:country_code":"IN",
    "gn:dem":452,
    "gn:feature_class":"P",
    "gn:feature_code":"PPL",
    "gn:name":"K\u0101shi",
    "gn:population":0,
    "gn:timezone":"Asia/Kolkata",
    "iso:country":"IN",
    "ks:ks_alt_nam":"K\u0101shi",
    "ks:ks_name":"Kashi",
    "ks:ks_pop":266,
    "ks:ks_type":"VILLAGE",
    "name:cat_x_preferred":[
        "Kashi"
    ],
    "name:ceb_x_preferred":[
        "Kashi"
    ],
    "name:deu_x_preferred":[
        "Kashi"
    ],
    "name:eng_x_preferred":[
        "Kashi"
    ],
    "name:eng_x_variant":[
        "K\u0101shi"
    ],
    "name:fra_x_preferred":[
        "Kashi"
    ],
    "name:heb_x_preferred":[
        "\u05e7\u05d0\u05e9\u05d9"
    ],
    "name:hin_x_preferred":[
        "\u0915\u093e\u0936\u0940"
    ],
    "name:ita_x_preferred":[
        "Kashi"
    ],
    "name:nld_x_preferred":[
        "Kashi"
    ],
    "name:sco_x_preferred":[
        "Kashi"
    ],
    "name:swe_x_preferred":[
        "Kashi"
    ],
    "wof:name":"Kashi",
    "wof:placetype":"locality",
    "wof:population":266
},
  "geometry": {"coordinates":[83.36835600000001,24.580148],"type":"Point"}
}