{
  "type": "Feature",
  "properties": {
    "iso:country":"IN",
    "ks:ks_name":"Khadki Falia",
    "ks:ks_pop":610,
    "ks:ks_type":"HABITATION",
    "name:eng_x_preferred":[
        "Khadki Falia"
    ],
    "wof:name":"Khadki Falia",
    "wof:placetype":"locality",
    "wof:population":610
},
  "geometry": {"coordinates":[73.30275,20.261611],"type":"Point"}
}