{
  "type": "Feature",
  "properties": {
    "gn:admin1_code":"35.0",
    "gn:admin2_code":"457.0",
    "gn:asciiname":"Sakri",
    "gn:country_code":"IN",
    "gn:dem":363,
    "gn:feature_class":"P",
    "gn:feature_code":"PPL",
    "gn:name":"Sakr\u012b",
    "gn:population":0,
    "gn:timezone":"Asia/Kolkata",
    "iso:country":"IN",
    "name:guj_x_preferred":[
        "\u0ab8\u0abe\u0a95\u0acd\u0ab0\u0ac0"
    ],
    "name:hin_x_preferred":[
        "\u0938\u093e\u0915\u094d\u0930\u0940"
    ],
    "name:mal_x_preferred":[
        "\u0d38\u0d3e\u0d15\u0d4d\u0d30\u0d3f"
    ],
    "name:mar_x_preferred":[
        "\u0938\u093e\u0915\u094d\u0930\u0940"
    ],
    "name:urd_x_preferred":[
        "\u0633\u0627\u06a9\u0631\u06cc"
    ],
    "wof:name":"Sakri",
    "wof:placetype":"locality"
},
  "geometry": {"coordinates":[80.10856,22.27832],"type":"Point"}
}