{
  "type": "Feature",
  "properties": {
    "iso:country":"IN",
    "ks:ks_name":"Dongripara",
    "ks:ks_pop":46,
    "ks:ks_type":"HABITATION",
    "ks:ks_uagg_main":0,
    "name:eng_x_preferred":[
        "Dongripara"
    ],
    "wof:name":"Dongripara",
    "wof:placetype":"neighbourhood",
    "wof:population":46
},
  "geometry": {"coordinates":[81.87914600000001,19.22007],"type":"Point"}
}