{
  "type": "Feature",
  "properties": {
    "gn:admin1_code":"16",
    "gn:admin2_code":"511.0",
    "gn:asciiname":"Gujri",
    "gn:country_code":"IN",
    "gn:dem":350,
    "gn:feature_class":"P",
    "gn:feature_code":"PPL",
    "gn:name":"Gujri",
    "gn:population":0,
    "gn:timezone":"Asia/Kolkata",
    "iso:country":"IN",
    "ks:ks_name":"Gujri",
    "ks:ks_type":"VILLAGE",
    "name:eng_x_preferred":[
        "Gujri"
    ],
    "wof:name":"Gujri",
    "wof:placetype":"locality"
},
  "geometry": {"coordinates":[77.709838,18.870152],"type":"Point"}
}