{
  "type": "Feature",
  "properties": {
    "iso:country":"IN",
    "ks:ks_alt_nam":"Khatla FV",
    "ks:ks_name":"Khatla Fv",
    "ks:ks_pop":1326,
    "ks:ks_type":"HABITATION",
    "name:eng_x_preferred":[
        "Khatla Fv"
    ],
    "wof:name":"Khatla Fv",
    "wof:placetype":"locality",
    "wof:population":1326
},
  "geometry": {"coordinates":[76.17484,21.505351],"type":"Point"}
}