{
  "type": "Feature",
  "properties": {
    "iso:country":"IN",
    "ks:ks_name":"Gorwar",
    "ks:ks_pop":0,
    "ks:ks_type":"VILLAGE",
    "name:eng_x_preferred":[
        "Gorwar"
    ],
    "wof:name":"Gorwar",
    "wof:placetype":"locality",
    "wof:population":0
},
  "geometry": {"coordinates":[83.715361,24.891006],"type":"Point"}
}