{
  "type": "Feature",
  "properties": {
    "iso:country":"IN",
    "ks:ks_name":"Kesham Girisahi",
    "ks:ks_pop":159,
    "ks:ks_type":"HABITATION",
    "name:eng_x_preferred":[
        "Kesham Girisahi"
    ],
    "wof:name":"Kesham Girisahi",
    "wof:placetype":"locality",
    "wof:population":159
},
  "geometry": {"coordinates":[86.211111,22.044172],"type":"Point"}
}