{
  "type": "Feature",
  "properties": {
    "gn:admin1_code":"35",
    "gn:admin2_code":"452.0",
    "gn:asciiname":"Kana Udal",
    "gn:country_code":"IN",
    "gn:dem":500,
    "gn:feature_class":"P",
    "gn:feature_code":"PPL",
    "gn:name":"K\u0101na \u016adal",
    "gn:population":0,
    "gn:timezone":"Asia/Kolkata",
    "iso:country":"IN",
    "ks:ks_name":"Kana Udal",
    "ks:ks_pop":109,
    "ks:ks_type":"VILLAGE",
    "name:eng_x_preferred":[
        "Kana Udal"
    ],
    "wof:name":"Kana Udal",
    "wof:placetype":"locality",
    "wof:population":109
},
  "geometry": {"coordinates":[79.348758,22.668428],"type":"Point"}
}