{
  "type": "Feature",
  "properties": {
    "iso:country":"IN",
    "ks:ks_alt_nam":"WEST TOLA",
    "ks:ks_name":"West Tola",
    "ks:ks_pop":125,
    "ks:ks_type":"HABITATION",
    "name:eng_x_preferred":[
        "West Tola"
    ],
    "wof:name":"West Tola",
    "wof:placetype":"locality",
    "wof:population":125
},
  "geometry": {"coordinates":[86.17913,25.05082],"type":"Point"}
}