{
  "type": "Feature",
  "properties": {
    "iso:country":"IN",
    "ks:ks_name":"Gobardhanpur",
    "ks:ks_pop":63,
    "ks:ks_type":"VILLAGE",
    "name:eng_x_preferred":[
        "Gobardhanpur"
    ],
    "wof:name":"Gobardhanpur",
    "wof:placetype":"locality",
    "wof:population":63
},
  "geometry": {"coordinates":[84.224723,21.004766],"type":"Point"}
}