{
  "type": "Feature",
  "properties": {
    "gn:admin1_code":"34.0",
    "gn:admin2_code":"234.0",
    "gn:asciiname":"Nadauwani",
    "gn:country_code":"IN",
    "gn:dem":97,
    "gn:feature_class":"P",
    "gn:feature_code":"PPL",
    "gn:name":"Nadauw\u0101ni",
    "gn:population":0,
    "gn:timezone":"Asia/Kolkata",
    "iso:country":"IN",
    "ks:ks_name":"Nadauwan",
    "ks:ks_pop":263,
    "ks:ks_type":"VILLAGE",
    "name:eng_x_preferred":[
        "Nadauwan"
    ],
    "name:eng_x_variant":[
        "Nadauwani"
    ],
    "wof:name":"Nadauwan",
    "wof:placetype":"locality",
    "wof:population":263
},
  "geometry": {"coordinates":[84.134199,25.139864],"type":"Point"}
}