{
  "type": "Feature",
  "properties": {
    "gn:admin1_code":"36",
    "gn:admin2_code":"159.0",
    "gn:asciiname":"Jeonta",
    "gn:country_code":"IN",
    "gn:dem":155,
    "gn:feature_class":"P",
    "gn:feature_code":"PPL",
    "gn:name":"Jeonta",
    "gn:population":0,
    "gn:timezone":"Asia/Kolkata",
    "iso:country":"IN",
    "wof:name":"Jeonta",
    "wof:placetype":"locality"
},
  "geometry": {"coordinates":[79.40722,27.25335],"type":"Point"}
}