{
  "type": "Feature",
  "properties": {
    "gn:admin1_code":"34.0",
    "gn:admin2_code":"236.0",
    "gn:asciiname":"Sadipur",
    "gn:country_code":"IN",
    "gn:dem":84,
    "gn:feature_class":"P",
    "gn:feature_code":"PPL",
    "gn:name":"S\u0101dipur",
    "gn:population":0,
    "gn:timezone":"Asia/Kolkata",
    "iso:country":"IN",
    "ks:ks_alt_nam":"S\u0101dipur",
    "ks:ks_name":"Sadipur",
    "ks:ks_pop":738,
    "ks:ks_type":"VILLAGE",
    "ks:ks_uagg_main":0,
    "name:eng_x_preferred":[
        "Sadipur"
    ],
    "name:eng_x_variant":[
        "S\u0101dipur"
    ],
    "wof:name":"Sadipur",
    "wof:placetype":"neighbourhood",
    "wof:population":738
},
  "geometry": {"coordinates":[84.850291,25.057393],"type":"Point"}
}