{
  "type": "Feature",
  "properties": {
    "iso:country":"IN",
    "ks:ks_alt_nam":"Saradh\u0101munda",
    "ks:ks_name":"Saradhamunda",
    "ks:ks_pop":414,
    "ks:ks_type":"VILLAGE",
    "name:eng_x_preferred":[
        "Saradhamunda"
    ],
    "name:eng_x_variant":[
        "Saradh\u0101munda"
    ],
    "wof:name":"Saradhamunda",
    "wof:placetype":"locality",
    "wof:population":414
},
  "geometry": {"coordinates":[84.734443,20.921586],"type":"Point"}
}