{
  "type": "Feature",
  "properties": {
    "iso:country":"IN",
    "ks:ks_name":"Biral",
    "ks:ks_pop":3739,
    "ks:ks_type":"VILLAGE",
    "ks:ks_uagg_main":0,
    "name:eng_x_preferred":[
        "Biral"
    ],
    "wof:name":"Biral",
    "wof:placetype":"neighbourhood",
    "wof:population":3739
},
  "geometry": {"coordinates":[77.281961,29.192282],"type":"Point"}
}