{
  "type": "Feature",
  "properties": {
    "iso:country":"IN",
    "ks:ks_name":"Dhoora",
    "ks:ks_pop":48,
    "ks:ks_type":"VILLAGE",
    "name:eng_x_preferred":[
        "Dhoora"
    ],
    "wof:name":"Dhoora",
    "wof:placetype":"locality",
    "wof:population":48
},
  "geometry": {"coordinates":[78.82684,29.708866],"type":"Point"}
}