{
  "type": "Feature",
  "properties": {
    "iso:country":"IN",
    "ks:ks_name":"Veldari",
    "ks:ks_pop":205,
    "ks:ks_type":"HABITATION",
    "name:eng_x_preferred":[
        "Veldari"
    ],
    "wof:name":"Veldari",
    "wof:placetype":"locality",
    "wof:population":205
},
  "geometry": {"coordinates":[74.075716,19.361882],"type":"Point"}
}