{
  "type": "Feature",
  "properties": {
    "iso:country":"IN",
    "ks:ks_name":"Vinoba Nagar",
    "ks:ks_pop":312,
    "ks:ks_type":"HABITATION",
    "name:eng_x_preferred":[
        "Vinoba Nagar"
    ],
    "wof:name":"Vinoba Nagar",
    "wof:placetype":"locality",
    "wof:population":312
},
  "geometry": {"coordinates":[78.476528,9.525661],"type":"Point"}
}