{
  "type": "Feature",
  "properties": {
    "iso:country":"IN",
    "ks:ks_name":"Kosmada",
    "ks:ks_pop":107,
    "ks:ks_type":"VILLAGE",
    "name:eng_x_preferred":[
        "Kosmada"
    ],
    "wof:name":"Kosmada",
    "wof:placetype":"locality",
    "wof:population":107
},
  "geometry": {"coordinates":[79.316703,23.242417],"type":"Point"}
}