{
  "type": "Feature",
  "properties": {
    "iso:country":"IN",
    "ks:ks_name":"Dhancherra",
    "ks:ks_pop":880,
    "ks:ks_type":"HABITATION",
    "name:eng_x_preferred":[
        "Dhancherra"
    ],
    "wof:name":"Dhancherra",
    "wof:placetype":"locality",
    "wof:population":880
},
  "geometry": {"coordinates":[91.82277999999999,23.913115],"type":"Point"}
}