{
  "type": "Feature",
  "properties": {
    "iso:country":"IN",
    "ks:ks_name":"Fulsari",
    "ks:ks_pop":915,
    "ks:ks_type":"VILLAGE",
    "name:eng_x_preferred":[
        "Fulsari"
    ],
    "wof:name":"Fulsari",
    "wof:placetype":"locality",
    "wof:population":915
},
  "geometry": {"coordinates":[83.021034,22.455212],"type":"Point"}
}