{
  "type": "Feature",
  "properties": {
    "gn:admin1_code":"23",
    "gn:admin2_code":"40.0",
    "gn:asciiname":"Satis",
    "gn:country_code":"IN",
    "gn:dem":277,
    "gn:feature_class":"P",
    "gn:feature_code":"PPL",
    "gn:name":"Sat\u012bs",
    "gn:population":0,
    "gn:timezone":"Asia/Kolkata",
    "iso:country":"IN",
    "name:ceb_x_preferred":[
        "Satis"
    ],
    "name:deu_x_preferred":[
        "Satis"
    ],
    "name:est_x_preferred":[
        "Satiss"
    ],
    "name:rus_x_preferred":[
        "\u0421\u0430\u0442\u0438\u0441"
    ],
    "wof:name":"Satis",
    "wof:placetype":"locality"
},
  "geometry": {"coordinates":[76.50339,30.64191],"type":"Point"}
}