{
  "type": "Feature",
  "properties": {
    "iso:country":"IN",
    "ks:ks_alt_nam":"KESARGADH",
    "ks:ks_name":"Kesargadh",
    "ks:ks_pop":189,
    "ks:ks_type":"HABITATION",
    "name:eng_x_preferred":[
        "Kesargadh"
    ],
    "wof:name":"Kesargadh",
    "wof:placetype":"locality",
    "wof:population":189
},
  "geometry": {"coordinates":[71.422127,23.961717],"type":"Point"}
}