{
  "type": "Feature",
  "properties": {
    "gn:admin1_code":"39",
    "gn:admin2_code":"67.0",
    "gn:asciiname":"Bhagwantpur",
    "gn:country_code":"IN",
    "gn:dem":253,
    "gn:feature_class":"P",
    "gn:feature_code":"PPL",
    "gn:name":"Bhagwantpur",
    "gn:population":0,
    "gn:timezone":"Asia/Kolkata",
    "iso:country":"IN",
    "ks:ks_name":"Bhagwantpur",
    "ks:ks_type":"VILLAGE",
    "ks:ks_uagg_main":0,
    "name:eng_x_preferred":[
        "Bhagwantpur"
    ],
    "wof:name":"Bhagwantpur",
    "wof:placetype":"neighbourhood"
},
  "geometry": {"coordinates":[78.838813,29.30364],"type":"Point"}
}