{
  "type": "Feature",
  "properties": {
    "iso:country":"IN",
    "ks:ks_name":"Maniyawan",
    "ks:ks_pop":150,
    "ks:ks_type":"HABITATION",
    "name:eng_x_preferred":[
        "Maniyawan"
    ],
    "wof:name":"Maniyawan",
    "wof:placetype":"locality",
    "wof:population":150
},
  "geometry": {"coordinates":[81.971322,26.881098],"type":"Point"}
}