{
  "type": "Feature",
  "properties": {
    "gn:admin1_code":"11",
    "gn:admin2_code":"33.0",
    "gn:asciiname":"Mandlar Khera",
    "gn:country_code":"IN",
    "gn:dem":2231,
    "gn:feature_class":"P",
    "gn:feature_code":"PPL",
    "gn:name":"Mandl\u0101r Khera",
    "gn:population":0,
    "gn:timezone":"Asia/Kolkata",
    "iso:country":"IN",
    "wof:name":"Mandlar Khera",
    "wof:placetype":"locality"
},
  "geometry": {"coordinates":[77.79037,30.90888],"type":"Point"}
}