{
  "type": "Feature",
  "properties": {
    "gn:admin1_code":"36",
    "gn:admin2_code":"147.0",
    "gn:asciiname":"Garhi Daragpur",
    "gn:country_code":"IN",
    "gn:dem":165,
    "gn:feature_class":"P",
    "gn:feature_code":"PPL",
    "gn:name":"Garhi Daragpur",
    "gn:population":0,
    "gn:timezone":"Asia/Kolkata",
    "iso:country":"IN",
    "ks:ks_name":"Garhi Daragpur",
    "ks:ks_pop":479,
    "ks:ks_type":"HABITATION",
    "name:eng_x_preferred":[
        "Garhi Daragpur"
    ],
    "wof:name":"Garhi Daragpur",
    "wof:placetype":"locality",
    "wof:population":479
},
  "geometry": {"coordinates":[78.334192,27.166225],"type":"Point"}
}