{
  "type": "Feature",
  "properties": {
    "gn:admin1_code":"34.0",
    "gn:admin2_code":"231.0",
    "gn:asciiname":"Bihiya",
    "gn:country_code":"IN",
    "gn:dem":67,
    "gn:feature_class":"P",
    "gn:feature_code":"PPL",
    "gn:name":"Bihiya",
    "gn:population":0,
    "gn:timezone":"Asia/Kolkata",
    "iso:country":"IN",
    "name:ben_x_preferred":[
        "\u09ac\u09c7\u09b9\u09c7\u09b0\u09be"
    ],
    "name:bih_x_preferred":[
        "\u092c\u093f\u0939\u093f\u092f\u093e"
    ],
    "name:bpy_x_preferred":[
        "\u09ac\u09c7\u09b9\u09c7\u09b0\u09be"
    ],
    "name:hin_x_preferred":[
        "\u092c\u093f\u0939\u093f\u092f\u093e"
    ],
    "name:ita_x_preferred":[
        "Behea"
    ],
    "name:msa_x_preferred":[
        "Behea"
    ],
    "name:nep_x_preferred":[
        "\u092c\u093f\u0939\u093f\u092f\u093e"
    ],
    "name:new_x_preferred":[
        "\u092c\u0947\u0939\u0947\u092f\u093e"
    ],
    "name:nld_x_preferred":[
        "Behea"
    ],
    "name:por_x_preferred":[
        "Behea"
    ],
    "name:spa_x_preferred":[
        "Behea"
    ],
    "name:urd_x_preferred":[
        "\u0628\u06be\u06cc\u0627"
    ],
    "name:vie_x_preferred":[
        "Behea"
    ],
    "name:zho_x_preferred":[
        "\u8d1d\u8d6b\u963f"
    ],
    "wof:name":"Bihiya",
    "wof:placetype":"locality"
},
  "geometry": {"coordinates":[84.45499000000002,25.55759],"type":"Point"}
}