{
  "type": "Feature",
  "properties": {
    "iso:country":"IN",
    "ks:ks_name":"Ali Nagar Kota",
    "ks:ks_pop":286,
    "ks:ks_type":"HABITATION",
    "name:eng_x_preferred":[
        "Ali Nagar Kota"
    ],
    "wof:name":"Ali Nagar Kota",
    "wof:placetype":"locality",
    "wof:population":286
},
  "geometry": {"coordinates":[79.341649,28.913349],"type":"Point"}
}