{
  "type": "Feature",
  "properties": {
    "gn:admin1_code":"2",
    "gn:admin2_code":"546.0",
    "gn:asciiname":"Krishnapuram",
    "gn:country_code":"IN",
    "gn:dem":52,
    "gn:feature_class":"P",
    "gn:feature_code":"PPL",
    "gn:name":"Krishn\u0101puram",
    "gn:population":0,
    "gn:timezone":"Asia/Kolkata",
    "iso:country":"IN",
    "name:und_x_variant":[
        "Krishn\u0101puram",
        "Kanak\u0101puram"
    ],
    "wof:name":"Krishnapuram",
    "wof:placetype":"locality"
},
  "geometry": {"coordinates":[81.24945,16.88954],"type":"Point"}
}