{
  "type": "Feature",
  "properties": {
    "iso:country":"IN",
    "ks:ks_name":"Bisthan Purwa",
    "ks:ks_pop":73,
    "ks:ks_type":"HABITATION",
    "name:eng_x_preferred":[
        "Bisthan Purwa"
    ],
    "wof:name":"Bisthan Purwa",
    "wof:placetype":"locality",
    "wof:population":73
},
  "geometry": {"coordinates":[80.848955,25.599098],"type":"Point"}
}