{
  "type": "Feature",
  "properties": {
    "iso:country":"IN",
    "ks:ks_name":"Rawatwasti",
    "ks:ks_pop":78,
    "ks:ks_type":"HABITATION",
    "name:eng_x_preferred":[
        "Rawatwasti"
    ],
    "wof:name":"Rawatwasti",
    "wof:placetype":"locality",
    "wof:population":78
},
  "geometry": {"coordinates":[73.783253,19.251118],"type":"Point"}
}