{
  "type": "Feature",
  "properties": {
    "iso:country":"IN",
    "ks:ks_name":"Baria Falia",
    "ks:ks_pop":451,
    "ks:ks_type":"HABITATION",
    "name:eng_x_preferred":[
        "Baria Falia"
    ],
    "wof:name":"Baria Falia",
    "wof:placetype":"locality",
    "wof:population":451
},
  "geometry": {"coordinates":[74.261,23.081],"type":"Point"}
}