{
  "type": "Feature",
  "properties": {
    "iso:country":"IN",
    "ks:ks_name":"Mandanparambu",
    "ks:ks_pop":201,
    "ks:ks_type":"HABITATION",
    "name:eng_x_preferred":[
        "Mandanparambu"
    ],
    "wof:name":"Mandanparambu",
    "wof:placetype":"locality",
    "wof:population":201
},
  "geometry": {"coordinates":[76.16334500000001,10.697976],"type":"Point"}
}