{
  "type": "Feature",
  "properties": {
    "iso:country":"IN",
    "ks:ks_alt_nam":"PURE BHUVA",
    "ks:ks_name":"Pure Bhuva",
    "ks:ks_pop":410,
    "ks:ks_type":"HABITATION",
    "ks:ks_uagg_main":0,
    "name:eng_x_preferred":[
        "Pure Bhuva"
    ],
    "wof:name":"Pure Bhuva",
    "wof:placetype":"neighbourhood",
    "wof:population":410
},
  "geometry": {"coordinates":[81.32494800000001,26.081456],"type":"Point"}
}