{
  "type": "Feature",
  "properties": {
    "gn:admin1_code":"36",
    "gn:admin2_code":"191.0",
    "gn:asciiname":"Baikunthpur",
    "gn:country_code":"IN",
    "gn:dem":79,
    "gn:feature_class":"P",
    "gn:feature_code":"PPL",
    "gn:name":"Baikunthpur",
    "gn:population":0,
    "gn:timezone":"Asia/Kolkata",
    "iso:country":"IN",
    "ks:ks_name":"Baikunthpur",
    "ks:ks_type":"VILLAGE",
    "ks:ks_uagg_main":0,
    "name:ceb_x_preferred":[
        "Baikunthpur"
    ],
    "name:eng_x_preferred":[
        "Baikunthpur"
    ],
    "name:ita_x_preferred":[
        "Baikunthpur"
    ],
    "name:nld_x_preferred":[
        "Baikunthpur"
    ],
    "name:swe_x_preferred":[
        "Baikunthpur"
    ],
    "wof:name":"Baikunthpur",
    "wof:placetype":"neighbourhood"
},
  "geometry": {"coordinates":[83.298557,25.854637],"type":"Point"}
}