{
  "type": "Feature",
  "properties": {
    "iso:country":"IN",
    "ks:ks_name":"Daluarpar",
    "ks:ks_pop":2786,
    "ks:ks_type":"HABITATION",
    "name:eng_x_preferred":[
        "Daluarpar"
    ],
    "wof:name":"Daluarpar",
    "wof:placetype":"locality",
    "wof:population":2786
},
  "geometry": {"coordinates":[89.15725500000001,26.320442],"type":"Point"}
}