{
  "type": "Feature",
  "properties": {
    "iso:country":"IN",
    "ks:ks_name":"Asharikandi",
    "ks:ks_pop":2382,
    "ks:ks_type":"VILLAGE",
    "ks:ks_uagg_main":0,
    "name:eng_x_preferred":[
        "Asharikandi"
    ],
    "wof:name":"Asharikandi",
    "wof:placetype":"neighbourhood",
    "wof:population":2382
},
  "geometry": {"coordinates":[90.009923,26.095987],"type":"Point"}
}