{
  "type": "Feature",
  "properties": {
    "iso:country":"IN",
    "ks:ks_name":"Nedumaram",
    "ks:ks_pop":200,
    "ks:ks_type":"HABITATION",
    "name:eng_x_preferred":[
        "Nedumaram"
    ],
    "wof:name":"Nedumaram",
    "wof:placetype":"locality",
    "wof:population":200
},
  "geometry": {"coordinates":[78.967035,9.873578],"type":"Point"}
}