{
  "type": "Feature",
  "properties": {
    "iso:country":"IN",
    "ks:ks_name":"Nizkainsari",
    "ks:ks_pop":1045,
    "ks:ks_type":"VILLAGE",
    "name:eng_x_preferred":[
        "Nizkainsari"
    ],
    "wof:name":"Nizkainsari",
    "wof:placetype":"locality",
    "wof:population":1045
},
  "geometry": {"coordinates":[86.61608,21.600352],"type":"Point"}
}