{
  "type": "Feature",
  "properties": {
    "gn:admin1_code":"38.0",
    "gn:admin2_code":"349",
    "gn:asciiname":"Baraganda",
    "gn:country_code":"IN",
    "gn:dem":348,
    "gn:feature_class":"P",
    "gn:feature_code":"PPL",
    "gn:name":"Bar\u0101ganda",
    "gn:population":0,
    "gn:timezone":"Asia/Kolkata",
    "iso:country":"IN",
    "name:und_x_variant":[
        "Baragunda",
        "Bar\u0101ganda"
    ],
    "wof:name":"Baraganda",
    "wof:placetype":"locality"
},
  "geometry": {"coordinates":[86.05277,24.0882],"type":"Point"}
}