{
  "type": "Feature",
  "properties": {
    "iso:country":"IN",
    "ks:ks_alt_nam":"Tetal basti",
    "ks:ks_name":"Tetal Basti",
    "ks:ks_pop":434,
    "ks:ks_type":"HABITATION",
    "ks:ks_uagg_main":0,
    "name:eng_x_preferred":[
        "Tetal Basti"
    ],
    "wof:name":"Tetal Basti",
    "wof:placetype":"neighbourhood",
    "wof:population":434
},
  "geometry": {"coordinates":[88.140192,26.266483],"type":"Point"}
}