{
  "type": "Feature",
  "properties": {
    "iso:country":"IN",
    "ks:ks_name":"Larmi",
    "ks:ks_pop":92,
    "ks:ks_type":"VILLAGE",
    "name:eng_x_preferred":[
        "Larmi"
    ],
    "wof:name":"Larmi",
    "wof:placetype":"locality",
    "wof:population":92
},
  "geometry": {"coordinates":[84.108406,24.402247],"type":"Point"}
}