{
  "type": "Feature",
  "properties": {
    "iso:country":"IN",
    "ks:ks_name":"Khajuri",
    "ks:ks_pop":268,
    "ks:ks_type":"HABITATION",
    "name:eng_x_preferred":[
        "Khajuri"
    ],
    "wof:name":"Khajuri",
    "wof:placetype":"locality",
    "wof:population":268
},
  "geometry": {"coordinates":[84.90336000000001,24.937179],"type":"Point"}
}