{
  "type": "Feature",
  "properties": {
    "gn:admin1_code":"37",
    "gn:admin2_code":"410.0",
    "gn:asciiname":"Newari",
    "gn:country_code":"IN",
    "gn:dem":273,
    "gn:feature_class":"P",
    "gn:feature_code":"PPL",
    "gn:name":"New\u0101ri",
    "gn:population":0,
    "gn:timezone":"Asia/Kolkata",
    "iso:country":"IN",
    "name:jpn_x_preferred":[
        "\u30cd\u30ef\u30fc\u30eb"
    ],
    "name:nld_x_preferred":[
        "Newari"
    ],
    "name:rus_x_preferred":[
        "\u041d\u0435\u0432\u0430\u0440\u0438"
    ],
    "wof:name":"Newari",
    "wof:placetype":"locality"
},
  "geometry": {"coordinates":[82.01165999999998,21.5372],"type":"Point"}
}