{
  "type": "Feature",
  "properties": {
    "iso:country":"IN",
    "ks:ks_name":"Korse",
    "ks:ks_pop":258,
    "ks:ks_type":"HABITATION",
    "name:eng_x_preferred":[
        "Korse"
    ],
    "wof:name":"Korse",
    "wof:placetype":"locality",
    "wof:population":258
},
  "geometry": {"coordinates":[74.910566,14.744086],"type":"Point"}
}