{
  "type": "Feature",
  "properties": {
    "gn:admin1_code":"37",
    "gn:admin2_code":"407.0",
    "gn:asciiname":"Wangar",
    "gn:country_code":"IN",
    "gn:dem":785,
    "gn:feature_class":"P",
    "gn:feature_code":"PPL",
    "gn:name":"W\u0101ngar",
    "gn:population":0,
    "gn:timezone":"Asia/Kolkata",
    "iso:country":"IN",
    "ks:ks_alt_nam":"BANGAR",
    "ks:ks_name":"Bangar",
    "ks:ks_pop":746,
    "ks:ks_type":"HABITATION",
    "name:eng_x_preferred":[
        "Bangar"
    ],
    "name:eng_x_variant":[
        "Wangar"
    ],
    "wof:name":"Bangar",
    "wof:placetype":"locality",
    "wof:population":746
},
  "geometry": {"coordinates":[81.298956,22.477366],"type":"Point"}
}