{
  "type": "Feature",
  "properties": {
    "iso:country":"IN",
    "ks:ks_name":"Narauli Dih",
    "ks:ks_pop":1551,
    "ks:ks_type":"VILLAGE",
    "name:eng_x_preferred":[
        "Narauli Dih"
    ],
    "wof:name":"Narauli Dih",
    "wof:placetype":"locality",
    "wof:population":1551
},
  "geometry": {"coordinates":[85.487459,26.084465],"type":"Point"}
}