{
  "type": "Feature",
  "properties": {
    "iso:country":"IN",
    "ks:ks_name":"Jakhal",
    "ks:ks_pop":3078,
    "ks:ks_type":"VILLAGE",
    "name:eng_x_preferred":[
        "Jakhal"
    ],
    "wof:name":"Jakhal",
    "wof:placetype":"locality",
    "wof:population":3078
},
  "geometry": {"coordinates":[71.791297,24.859278],"type":"Point"}
}