{
  "type": "Feature",
  "properties": {
    "iso:country":"IN",
    "ks:ks_name":"Singhari",
    "ks:ks_pop":528,
    "ks:ks_type":"HABITATION",
    "ks:ks_uagg_main":0,
    "name:eng_x_preferred":[
        "Singhari"
    ],
    "wof:name":"Singhari",
    "wof:placetype":"neighbourhood",
    "wof:population":528
},
  "geometry": {"coordinates":[87.741686,26.185912],"type":"Point"}
}