{
  "type": "Feature",
  "properties": {
    "gn:admin1_code":"36.0",
    "gn:admin2_code":"168.0",
    "gn:asciiname":"Nethi",
    "gn:country_code":"IN",
    "gn:dem":117,
    "gn:feature_class":"P",
    "gn:feature_code":"PPL",
    "gn:name":"Nethi",
    "gn:population":0,
    "gn:timezone":"Asia/Kolkata",
    "iso:country":"IN",
    "wof:name":"Nethi",
    "wof:placetype":"locality"
},
  "geometry": {"coordinates":[80.06525000000001,25.91946],"type":"Point"}
}