{
  "type": "Feature",
  "properties": {
    "gn:admin1_code":"40.0",
    "gn:admin2_code":"541.0",
    "gn:asciiname":"Jalluru",
    "gn:country_code":"IN",
    "gn:dem":89,
    "gn:feature_class":"P",
    "gn:feature_code":"PPL",
    "gn:name":"Jall\u016bru",
    "gn:population":0,
    "gn:timezone":"Asia/Kolkata",
    "iso:country":"IN",
    "wof:name":"Jalluru",
    "wof:placetype":"locality"
},
  "geometry": {"coordinates":[80.53416999999997,18.39449],"type":"Point"}
}