{
  "type": "Feature",
  "properties": {
    "iso:country":"IN",
    "ks:ks_name":"Babudih",
    "ks:ks_pop":97,
    "ks:ks_type":"VILLAGE",
    "name:eng_x_preferred":[
        "Babudih"
    ],
    "wof:name":"Babudih",
    "wof:placetype":"locality",
    "wof:population":97
},
  "geometry": {"coordinates":[86.579116,24.50649],"type":"Point"}
}