{
  "type": "Feature",
  "properties": {
    "iso:country":"IN",
    "ks:ks_name":"Undariyones",
    "ks:ks_pop":20,
    "ks:ks_type":"HABITATION",
    "name:eng_x_preferred":[
        "Undariyones"
    ],
    "wof:name":"Undariyones",
    "wof:placetype":"locality",
    "wof:population":20
},
  "geometry": {"coordinates":[69.828694,21.780556],"type":"Point"}
}