{
  "type": "Feature",
  "properties": {
    "iso:country":"IN",
    "ks:ks_name":"Digar",
    "ks:ks_pop":58,
    "ks:ks_type":"HABITATION",
    "name:eng_x_preferred":[
        "Digar"
    ],
    "wof:name":"Digar",
    "wof:placetype":"locality",
    "wof:population":58
},
  "geometry": {"coordinates":[75.762728,22.170123],"type":"Point"}
}