{
  "type": "Feature",
  "properties": {
    "iso:country":"IN",
    "ks:ks_name":"Nidhubani",
    "ks:ks_pop":770,
    "ks:ks_type":"VILLAGE",
    "ks:ks_uagg_main":0,
    "name:eng_x_preferred":[
        "Nidhubani"
    ],
    "wof:name":"Nidhubani",
    "wof:placetype":"locality",
    "wof:population":770
},
  "geometry": {"coordinates":[87.42382600000001,21.681588],"type":"Point"}
}