{
  "type": "Feature",
  "properties": {
    "iso:country":"IN",
    "ks:ks_name":"Lohar Dhwa",
    "ks:ks_pop":184,
    "ks:ks_type":"HABITATION",
    "name:eng_x_preferred":[
        "Lohar Dhwa"
    ],
    "wof:name":"Lohar Dhwa",
    "wof:placetype":"locality",
    "wof:population":184
},
  "geometry": {"coordinates":[83.086384,27.308996],"type":"Point"}
}