{
  "type": "Feature",
  "properties": {
    "gn:admin1_code":"34.0",
    "gn:admin2_code":"225",
    "gn:asciiname":"Jaypur",
    "gn:country_code":"IN",
    "gn:dem":210,
    "gn:feature_class":"P",
    "gn:feature_code":"PPL",
    "gn:name":"Jaypur",
    "gn:population":0,
    "gn:timezone":"Asia/Kolkata",
    "iso:country":"IN",
    "name:und_x_variant":[
        "Jaipur",
        "Jaypur"
    ],
    "wof:name":"Jaypur",
    "wof:placetype":"locality"
},
  "geometry": {"coordinates":[86.84674,24.58415],"type":"Point"}
}