{
  "type": "Feature",
  "properties": {
    "iso:country":"IN",
    "ks:ks_name":"Kolagodu",
    "ks:ks_pop":151,
    "ks:ks_type":"HABITATION",
    "name:eng_x_preferred":[
        "Kolagodu"
    ],
    "wof:name":"Kolagodu",
    "wof:placetype":"locality",
    "wof:population":151
},
  "geometry": {"coordinates":[75.71147999999999,13.17731],"type":"Point"}
}