{
  "type": "Feature",
  "properties": {
    "gn:admin1_code":"34.0",
    "gn:admin2_code":"209.0",
    "gn:asciiname":"Hansa",
    "gn:country_code":"IN",
    "gn:dem":53,
    "gn:feature_class":"P",
    "gn:feature_code":"PPL",
    "gn:name":"H\u0101nsa",
    "gn:population":0,
    "gn:timezone":"Asia/Kolkata",
    "iso:country":"IN",
    "name:deu_x_preferred":[
        "Hansa"
    ],
    "name:fin_x_preferred":[
        "Hansa"
    ],
    "name:fra_x_preferred":[
        "Hansa"
    ],
    "name:ita_x_preferred":[
        "Hansa"
    ],
    "name:nld_x_preferred":[
        "Hansa"
    ],
    "name:pol_x_preferred":[
        "Hansa"
    ],
    "name:por_x_preferred":[
        "Hansa"
    ],
    "name:ron_x_preferred":[
        "Hansa"
    ],
    "name:swe_x_preferred":[
        "Hansa"
    ],
    "name:vie_x_preferred":[
        "Hansa"
    ],
    "wof:name":"Hansa",
    "wof:placetype":"locality"
},
  "geometry": {"coordinates":[87.30891,26.09105],"type":"Point"}
}