{
  "type": "Feature",
  "properties": {
    "iso:country":"IN",
    "ks:ks_name":"Diyara Darauli",
    "ks:ks_pop":26,
    "ks:ks_type":"VILLAGE",
    "name:eng_x_preferred":[
        "Diyara Darauli"
    ],
    "wof:name":"Diyara Darauli",
    "wof:placetype":"locality",
    "wof:population":26
},
  "geometry": {"coordinates":[84.12949,26.053036],"type":"Point"}
}