{
  "type": "Feature",
  "properties": {
    "iso:country":"IN",
    "ks:ks_name":"Dumerigata",
    "ks:ks_pop":67,
    "ks:ks_type":"VILLAGE",
    "name:eng_x_preferred":[
        "Dumerigata"
    ],
    "wof:name":"Dumerigata",
    "wof:placetype":"locality",
    "wof:population":67
},
  "geometry": {"coordinates":[83.97233,20.578227],"type":"Point"}
}