{
  "type": "Feature",
  "properties": {
    "iso:country":"IN",
    "ks:ks_name":"Gondpada",
    "ks:ks_pop":109,
    "ks:ks_type":"HABITATION",
    "name:eng_x_preferred":[
        "Gondpada"
    ],
    "wof:name":"Gondpada",
    "wof:placetype":"locality",
    "wof:population":109
},
  "geometry": {"coordinates":[72.98441699999999,19.80551],"type":"Point"}
}