{
  "type": "Feature",
  "properties": {
    "iso:country":"IN",
    "ks:ks_name":"Melvellar",
    "ks:ks_pop":141,
    "ks:ks_type":"HABITATION",
    "name:eng_x_preferred":[
        "Melvellar"
    ],
    "wof:name":"Melvellar",
    "wof:placetype":"locality",
    "wof:population":141
},
  "geometry": {"coordinates":[78.702291,11.821933],"type":"Point"}
}