{
  "type": "Feature",
  "properties": {
    "iso:country":"IN",
    "ks:ks_name":"Nuaguda",
    "ks:ks_pop":189,
    "ks:ks_type":"VILLAGE",
    "name:eng_x_preferred":[
        "Nuaguda"
    ],
    "wof:name":"Nuaguda",
    "wof:placetype":"locality",
    "wof:population":189
},
  "geometry": {"coordinates":[82.26444600000001,18.253891],"type":"Point"}
}