{
  "type": "Feature",
  "properties": {
    "iso:country":"IN",
    "ks:ks_name":"Kothamadigapalle",
    "ks:ks_pop":60,
    "ks:ks_type":"HABITATION",
    "name:eng_x_preferred":[
        "Kothamadigapalle"
    ],
    "wof:name":"Kothamadigapalle",
    "wof:placetype":"locality",
    "wof:population":60
},
  "geometry": {"coordinates":[78.520849,13.691971],"type":"Point"}
}