{
  "type": "Feature",
  "properties": {
    "iso:country":"IN",
    "ks:ks_name":"Krauti",
    "ks:ks_pop":660,
    "ks:ks_type":"HABITATION",
    "name:eng_x_preferred":[
        "Krauti"
    ],
    "wof:name":"Krauti",
    "wof:placetype":"locality",
    "wof:population":660
},
  "geometry": {"coordinates":[82.988838,26.754588],"type":"Point"}
}