{
  "type": "Feature",
  "properties": {
    "iso:country":"IN",
    "ks:ks_name":"Ottakkal",
    "ks:ks_pop":788,
    "ks:ks_type":"HABITATION",
    "name:eng_x_preferred":[
        "Ottakkal"
    ],
    "wof:name":"Ottakkal",
    "wof:placetype":"locality",
    "wof:population":788
},
  "geometry": {"coordinates":[77.05015,8.971413],"type":"Point"}
}