{
  "type": "Feature",
  "properties": {
    "gn:admin1_code":"36.0",
    "gn:admin2_code":"159",
    "gn:asciiname":"Manglipur",
    "gn:country_code":"IN",
    "gn:dem":145,
    "gn:feature_class":"P",
    "gn:feature_code":"PPL",
    "gn:name":"Mangl\u012bpur",
    "gn:population":0,
    "gn:timezone":"Asia/Kolkata",
    "iso:country":"IN",
    "ks:ks_name":"Mangli Pur",
    "ks:ks_pop":472,
    "ks:ks_type":"HABITATION",
    "name:eng_x_preferred":[
        "Mangli Pur"
    ],
    "name:eng_x_variant":[
        "Manglipur"
    ],
    "wof:name":"Mangli Pur",
    "wof:placetype":"locality",
    "wof:population":472
},
  "geometry": {"coordinates":[79.51414800000001,27.524275],"type":"Point"}
}