{
  "type": "Feature",
  "properties": {
    "gn:admin1_code":"19.0",
    "gn:admin2_code":"571.0",
    "gn:asciiname":"Bhimasamudra",
    "gn:country_code":"IN",
    "gn:dem":780,
    "gn:feature_class":"P",
    "gn:feature_code":"PPL",
    "gn:name":"Bh\u012bmasamudra",
    "gn:population":0,
    "gn:timezone":"Asia/Kolkata",
    "iso:country":"IN",
    "wof:name":"Bhimasamudra",
    "wof:placetype":"neighbourhood"
},
  "geometry": {"coordinates":[76.44121,13.47777],"type":"Point"}
}