{
  "type": "Feature",
  "properties": {
    "gn:admin1_code":"23",
    "gn:admin2_code":"41.0",
    "gn:asciiname":"Kum",
    "gn:country_code":"IN",
    "gn:dem":254,
    "gn:feature_class":"P",
    "gn:feature_code":"PPL",
    "gn:name":"K\u016bm",
    "gn:population":0,
    "gn:timezone":"Asia/Kolkata",
    "iso:country":"IN",
    "name:ceb_x_preferred":[
        "Kum"
    ],
    "name:deu_x_preferred":[
        "Kum"
    ],
    "name:hun_x_preferred":[
        "Kum"
    ],
    "name:kat_x_preferred":[
        "\u10d9\u10e3\u10db\u10d8"
    ],
    "name:swe_x_preferred":[
        "Kum"
    ],
    "wof:name":"Kum",
    "wof:placetype":"locality"
},
  "geometry": {"coordinates":[76.06743,30.91601],"type":"Point"}
}