{
  "type": "Feature",
  "properties": {
    "gn:admin1_code":"10",
    "gn:admin2_code":"73.0",
    "gn:asciiname":"Serta",
    "gn:country_code":"IN",
    "gn:dem":240,
    "gn:feature_class":"P",
    "gn:feature_code":"PPL",
    "gn:name":"Serta",
    "gn:population":0,
    "gn:timezone":"Asia/Kolkata",
    "iso:country":"IN",
    "name:ceb_x_preferred":[
        "Serta"
    ],
    "name:sco_x_preferred":[
        "Serta"
    ],
    "name:swe_x_preferred":[
        "Serta"
    ],
    "wof:name":"Serta",
    "wof:placetype":"locality"
},
  "geometry": {"coordinates":[76.34504,29.8476],"type":"Point"}
}