{
  "type": "Feature",
  "properties": {
    "iso:country":"IN",
    "ks:ks_name":"Veppankulam Kelur",
    "ks:ks_pop":123,
    "ks:ks_type":"HABITATION",
    "ks:ks_uagg_main":0,
    "name:eng_x_preferred":[
        "Veppankulam Kelur"
    ],
    "wof:name":"Veppankulam Kelur",
    "wof:placetype":"neighbourhood",
    "wof:population":123
},
  "geometry": {"coordinates":[77.65586999999999,8.411633],"type":"Point"}
}