{
  "type": "Feature",
  "properties": {
    "gn:admin1_code":"34",
    "gn:admin2_code":"233.0",
    "gn:asciiname":"Khatkhari",
    "gn:country_code":"IN",
    "gn:dem":339,
    "gn:feature_class":"P",
    "gn:feature_code":"PPL",
    "gn:name":"Khatkhari",
    "gn:population":0,
    "gn:timezone":"Asia/Kolkata",
    "iso:country":"IN",
    "ks:ks_name":"Khatkhari",
    "ks:ks_pop":552,
    "ks:ks_type":"VILLAGE",
    "name:eng_x_preferred":[
        "Khatkhari"
    ],
    "wof:name":"Khatkhari",
    "wof:placetype":"locality",
    "wof:population":552
},
  "geometry": {"coordinates":[83.442046,24.78077],"type":"Point"}
}