{
  "type": "Feature",
  "properties": {
    "iso:country":"IN",
    "ks:ks_name":"Balanagar",
    "ks:ks_pop":678,
    "ks:ks_type":"VILLAGE",
    "name:eng_x_preferred":[
        "Balanagar"
    ],
    "wof:name":"Balanagar",
    "wof:placetype":"locality",
    "wof:population":678
},
  "geometry": {"coordinates":[78.296712,17.976704],"type":"Point"}
}