{
  "type": "Feature",
  "properties": {
    "iso:country":"IN",
    "ks:ks_name":"Jot Gokul",
    "ks:ks_type":"VILLAGE",
    "name:eng_x_preferred":[
        "Jot Gokul"
    ],
    "wof:name":"Jot Gokul",
    "wof:placetype":"locality"
},
  "geometry": {"coordinates":[88.28576099999999,24.969592],"type":"Point"}
}