{
  "type": "Feature",
  "properties": {
    "iso:country":"IN",
    "ks:ks_alt_nam":"KATARON KA KHERA -B",
    "ks:ks_name":"Kataron Ka Khera -b",
    "ks:ks_pop":331,
    "ks:ks_type":"HABITATION",
    "name:eng_x_preferred":[
        "Kataron Ka Khera -b"
    ],
    "wof:name":"Kataron Ka Khera -b",
    "wof:placetype":"locality",
    "wof:population":331
},
  "geometry": {"coordinates":[74.696431,23.824587],"type":"Point"}
}