{
  "type": "Feature",
  "properties": {
    "iso:country":"IN",
    "ks:ks_name":"Medarapalli",
    "ks:ks_pop":238,
    "ks:ks_type":"HABITATION",
    "ks:ks_uagg_main":0,
    "name:eng_x_preferred":[
        "Medarapalli"
    ],
    "wof:name":"Medarapalli",
    "wof:placetype":"neighbourhood",
    "wof:population":238
},
  "geometry": {"coordinates":[78.749945,14.220427],"type":"Point"}
}