{
  "type": "Feature",
  "properties": {
    "iso:country":"IN",
    "ks:ks_name":"Mukundapuram",
    "ks:ks_pop":155,
    "ks:ks_type":"VILLAGE",
    "name:eng_x_preferred":[
        "Mukundapuram"
    ],
    "wof:name":"Mukundapuram",
    "wof:placetype":"locality",
    "wof:population":155
},
  "geometry": {"coordinates":[84.300434,18.708124],"type":"Point"}
}