{
  "type": "Feature",
  "properties": {
    "iso:country":"IN",
    "ks:ks_alt_nam":"Kams\u0101npalle",
    "ks:ks_name":"Kamsanpalle",
    "ks:ks_type":"VILLAGE",
    "ks:ks_uagg_main":0,
    "name:eng_x_preferred":[
        "Kamsanpalle"
    ],
    "name:eng_x_variant":[
        "Kams\u0101npalle"
    ],
    "wof:name":"Kamsanpalle",
    "wof:placetype":"neighbourhood"
},
  "geometry": {"coordinates":[77.517669,17.211255],"type":"Point"}
}