{
  "type": "Feature",
  "properties": {
    "iso:country":"IN",
    "ks:ks_name":"Shivantola",
    "ks:ks_pop":251,
    "ks:ks_type":"VILLAGE",
    "ks:ks_uagg_main":0,
    "name:eng_x_preferred":[
        "Shivantola"
    ],
    "wof:name":"Shivantola",
    "wof:placetype":"neighbourhood",
    "wof:population":251
},
  "geometry": {"coordinates":[80.146406,21.207373],"type":"Point"}
}