{
  "type": "Feature",
  "properties": {
    "iso:country":"IN",
    "ks:ks_alt_nam":"Khadar basant-I",
    "ks:ks_name":"Khadar Basant-i",
    "ks:ks_pop":68,
    "ks:ks_type":"HABITATION",
    "ks:ks_uagg_main":0,
    "name:eng_x_preferred":[
        "Khadar Basant-i"
    ],
    "wof:name":"Khadar Basant-i",
    "wof:placetype":"neighbourhood",
    "wof:population":68
},
  "geometry": {"coordinates":[81.99570300000001,26.372981],"type":"Point"}
}