{
  "type": "Feature",
  "properties": {
    "iso:country":"IN",
    "ks:ks_name":"Joydhanpur",
    "ks:ks_pop":2477,
    "ks:ks_type":"VILLAGE",
    "name:eng_x_preferred":[
        "Joydhanpur"
    ],
    "wof:name":"Joydhanpur",
    "wof:placetype":"locality",
    "wof:population":2477
},
  "geometry": {"coordinates":[92.804199,24.541028],"type":"Point"}
}