{
  "type": "Feature",
  "properties": {
    "gn:admin1_code":"10",
    "gn:admin2_code":"83.0",
    "gn:asciiname":"Raiya",
    "gn:country_code":"IN",
    "gn:dem":218,
    "gn:feature_class":"P",
    "gn:feature_code":"PPL",
    "gn:name":"Raiya",
    "gn:population":0,
    "gn:timezone":"Asia/Kolkata",
    "iso:country":"IN",
    "ks:ks_alt_nam":"Raiya Minor",
    "ks:ks_name":"Raiya",
    "ks:ks_pop":1635,
    "ks:ks_type":"VILLAGE",
    "name:eng_x_preferred":[
        "Raiya"
    ],
    "name:eng_x_variant":[
        "Raiya Minor"
    ],
    "wof:name":"Raiya",
    "wof:placetype":"locality",
    "wof:population":1635
},
  "geometry": {"coordinates":[76.6126,28.562564],"type":"Point"}
}