{
  "type": "Feature",
  "properties": {
    "gn:admin1_code":"39",
    "gn:admin2_code":"61.0",
    "gn:asciiname":"Jaikholi",
    "gn:country_code":"IN",
    "gn:dem":1236,
    "gn:feature_class":"P",
    "gn:feature_code":"PPL",
    "gn:name":"Jaikholi",
    "gn:population":0,
    "gn:timezone":"Asia/Kolkata",
    "iso:country":"IN",
    "wof:name":"Jaikholi",
    "wof:placetype":"neighbourhood"
},
  "geometry": {"coordinates":[78.78561999999999,30.15135],"type":"Point"}
}