{
  "type": "Feature",
  "properties": {
    "iso:country":"IN",
    "ks:ks_name":"Guri Pukhuria",
    "ks:ks_pop":48,
    "ks:ks_type":"VILLAGE",
    "name:eng_x_preferred":[
        "Guri Pukhuria"
    ],
    "wof:name":"Guri Pukhuria",
    "wof:placetype":"locality",
    "wof:population":48
},
  "geometry": {"coordinates":[86.798085,22.523506],"type":"Point"}
}