{
  "type": "Feature",
  "properties": {
    "iso:country":"IN",
    "ks:ks_name":"Istaranpur",
    "ks:ks_pop":1694,
    "ks:ks_type":"VILLAGE",
    "name:eng_x_preferred":[
        "Istaranpur"
    ],
    "wof:name":"Istaranpur",
    "wof:placetype":"locality",
    "wof:population":1694
},
  "geometry": {"coordinates":[88.383967,22.052862],"type":"Point"}
}