{
  "type": "Feature",
  "properties": {
    "iso:country":"IN",
    "ks:ks_name":"Krushnanagar",
    "ks:ks_pop":378,
    "ks:ks_type":"VILLAGE",
    "ks:ks_uagg_main":0,
    "name:eng_x_preferred":[
        "Krushnanagar"
    ],
    "wof:name":"Krushnanagar",
    "wof:placetype":"neighbourhood",
    "wof:population":378
},
  "geometry": {"coordinates":[87.234954,21.824694],"type":"Point"}
}