{
  "type": "Feature",
  "properties": {
    "iso:country":"IN",
    "ks:ks_name":"Asramgachh",
    "ks:ks_pop":1660,
    "ks:ks_type":"HABITATION",
    "name:eng_x_preferred":[
        "Asramgachh"
    ],
    "wof:name":"Asramgachh",
    "wof:placetype":"locality",
    "wof:population":1660
},
  "geometry": {"coordinates":[88.426992,26.376173],"type":"Point"}
}