{
  "type": "Feature",
  "properties": {
    "gn:admin1_code":"19",
    "gn:admin2_code":"581.0",
    "gn:asciiname":"Patna",
    "gn:country_code":"IN",
    "gn:dem":824,
    "gn:feature_class":"P",
    "gn:feature_code":"PPL",
    "gn:name":"Patna",
    "gn:population":0,
    "gn:timezone":"Asia/Kolkata",
    "iso:country":"IN",
    "wof:name":"Patna",
    "wof:placetype":"locality"
},
  "geometry": {"coordinates":[78.25274,13.06188],"type":"Point"}
}