{
  "type": "Feature",
  "properties": {
    "iso:country":"IN",
    "ks:ks_alt_nam":"JAGARNATIYA SAW TOLA",
    "ks:ks_name":"Jagarnatiya Saw Tola",
    "ks:ks_pop":210,
    "ks:ks_type":"HABITATION",
    "name:eng_x_preferred":[
        "Jagarnatiya Saw Tola"
    ],
    "wof:name":"Jagarnatiya Saw Tola",
    "wof:placetype":"locality",
    "wof:population":210
},
  "geometry": {"coordinates":[85.022328,24.10145],"type":"Point"}
}