{
  "type": "Feature",
  "properties": {
    "gn:admin1_code":"24.0",
    "gn:admin2_code":"104.0",
    "gn:asciiname":"Nahara",
    "gn:country_code":"IN",
    "gn:dem":238,
    "gn:feature_class":"P",
    "gn:feature_code":"PPL",
    "gn:name":"Nahara",
    "gn:population":0,
    "gn:timezone":"Asia/Kolkata",
    "iso:country":"IN",
    "name:ceb_x_preferred":[
        "Nahara"
    ],
    "name:swe_x_preferred":[
        "Nahara"
    ],
    "wof:name":"Nahara",
    "wof:placetype":"locality"
},
  "geometry": {"coordinates":[76.7958,27.32067],"type":"Point"}
}