{
  "type": "Feature",
  "properties": {
    "iso:country":"IN",
    "ks:ks_name":"Anantapur",
    "ks:ks_pop":2097,
    "ks:ks_type":"VILLAGE",
    "ks:ks_uagg_main":0,
    "name:eng_x_preferred":[
        "Anantapur"
    ],
    "wof:name":"Anantapur",
    "wof:placetype":"neighbourhood",
    "wof:population":2097
},
  "geometry": {"coordinates":[88.631795,23.117618],"type":"Point"}
}