{
  "type": "Feature",
  "properties": {
    "gn:admin1_code":"36.0",
    "gn:admin2_code":"155.0",
    "gn:asciiname":"Gulri Pokhri",
    "gn:country_code":"IN",
    "gn:dem":148,
    "gn:feature_class":"P",
    "gn:feature_code":"PPL",
    "gn:name":"Gulri Pokhri",
    "gn:population":0,
    "gn:timezone":"Asia/Kolkata",
    "iso:country":"IN",
    "ks:ks_name":"Gulri Pokhar",
    "ks:ks_pop":373,
    "ks:ks_type":"HABITATION",
    "name:eng_x_preferred":[
        "Gulri Pokhar"
    ],
    "name:eng_x_variant":[
        "Gulri Pokhri"
    ],
    "wof:name":"Gulri Pokhar",
    "wof:placetype":"locality",
    "wof:population":373
},
  "geometry": {"coordinates":[80.115151,27.488246],"type":"Point"}
}