{
  "type": "Feature",
  "properties": {
    "gn:admin1_code":"12.0",
    "gn:admin2_code":"1.0",
    "gn:asciiname":"Kothi Forest",
    "gn:country_code":"IN",
    "gn:dem":2290,
    "gn:feature_class":"P",
    "gn:feature_code":"PPL",
    "gn:name":"Kothi Forest",
    "gn:population":0,
    "gn:timezone":"Asia/Kolkata",
    "iso:country":"IN",
    "wof:name":"Kothi Forest",
    "wof:placetype":"locality"
},
  "geometry": {"coordinates":[74.44771999999998,34.56426],"type":"Point"}
}