{
  "type": "Feature",
  "properties": {
    "iso:country":"IN",
    "ks:ks_name":"Reddigunta",
    "ks:ks_pop":270,
    "ks:ks_type":"HABITATION",
    "name:eng_x_preferred":[
        "Reddigunta"
    ],
    "wof:name":"Reddigunta",
    "wof:placetype":"locality",
    "wof:population":270
},
  "geometry": {"coordinates":[79.81442,13.753329],"type":"Point"}
}