{
  "type": "Feature",
  "properties": {
    "iso:country":"IN",
    "ks:ks_name":"Malibagicha",
    "ks:ks_pop":0,
    "ks:ks_type":"VILLAGE",
    "name:eng_x_preferred":[
        "Malibagicha"
    ],
    "wof:name":"Malibagicha",
    "wof:placetype":"locality",
    "wof:population":0
},
  "geometry": {"coordinates":[87.280326,22.842085],"type":"Point"}
}