{
  "type": "Feature",
  "properties": {
    "gn:admin1_code":"21",
    "gn:admin2_code":"388.0",
    "gn:asciiname":"Ragada",
    "gn:country_code":"IN",
    "gn:dem":201,
    "gn:feature_class":"P",
    "gn:feature_code":"PPL",
    "gn:name":"Ragada",
    "gn:population":0,
    "gn:timezone":"Asia/Kolkata",
    "iso:country":"IN",
    "name:hin_x_preferred":[
        "\u0930\u0917\u093e\u0921\u093e"
    ],
    "name:tel_x_preferred":[
        "\u0c30\u0c17\u0c21"
    ],
    "wof:name":"Ragada",
    "wof:placetype":"locality"
},
  "geometry": {"coordinates":[84.47468000000001,19.847],"type":"Point"}
}