{
  "type": "Feature",
  "properties": {
    "iso:country":"IN",
    "ks:ks_name":"Etticheri",
    "ks:ks_pop":144,
    "ks:ks_type":"HABITATION",
    "name:eng_x_preferred":[
        "Etticheri"
    ],
    "wof:name":"Etticheri",
    "wof:placetype":"locality",
    "wof:population":144
},
  "geometry": {"coordinates":[79.04955,9.879736],"type":"Point"}
}