{
  "type": "Feature",
  "properties": {
    "iso:country":"IN",
    "ks:ks_name":"Khalidhipa",
    "ks:ks_type":"VILLAGE",
    "name:eng_x_preferred":[
        "Khalidhipa"
    ],
    "wof:name":"Khalidhipa",
    "wof:placetype":"locality"
},
  "geometry": {"coordinates":[84.596796,21.314845],"type":"Point"}
}