{
  "type": "Feature",
  "properties": {
    "iso:country":"IN",
    "ks:ks_name":"Dewangan Para",
    "ks:ks_pop":833,
    "ks:ks_type":"HABITATION",
    "name:eng_x_preferred":[
        "Dewangan Para"
    ],
    "wof:name":"Dewangan Para",
    "wof:placetype":"locality",
    "wof:population":833
},
  "geometry": {"coordinates":[81.766047,19.662908],"type":"Point"}
}