{
  "type": "Feature",
  "properties": {
    "iso:country":"IN",
    "ks:ks_name":"Arapur",
    "ks:ks_pop":332,
    "ks:ks_type":"VILLAGE",
    "name:eng_x_preferred":[
        "Arapur"
    ],
    "wof:name":"Arapur",
    "wof:placetype":"locality",
    "wof:population":332
},
  "geometry": {"coordinates":[87.68826900000001,23.140682],"type":"Point"}
}