{
  "type": "Feature",
  "properties": {
    "iso:country":"IN",
    "ks:ks_name":"Korhobeda",
    "ks:ks_pop":246,
    "ks:ks_type":"VILLAGE",
    "name:eng_x_preferred":[
        "Korhobeda"
    ],
    "wof:name":"Korhobeda",
    "wof:placetype":"locality",
    "wof:population":246
},
  "geometry": {"coordinates":[81.513125,19.559629],"type":"Point"}
}