{
  "type": "Feature",
  "properties": {
    "iso:country":"IN",
    "ks:ks_name":"Mestriwadi",
    "ks:ks_pop":133,
    "ks:ks_type":"HABITATION",
    "name:eng_x_preferred":[
        "Mestriwadi"
    ],
    "wof:name":"Mestriwadi",
    "wof:placetype":"locality",
    "wof:population":133
},
  "geometry": {"coordinates":[73.870013,15.933415],"type":"Point"}
}