{
  "type": "Feature",
  "properties": {
    "iso:country":"IN",
    "ks:ks_alt_nam":"Sonai Chari S.T. Colony",
    "ks:ks_name":"Sonai Chari S.t. Colony",
    "ks:ks_pop":559,
    "ks:ks_type":"HABITATION",
    "name:eng_x_preferred":[
        "Sonai Chari S.t. Colony"
    ],
    "wof:name":"Sonai Chari S.t. Colony",
    "wof:placetype":"locality",
    "wof:population":559
},
  "geometry": {"coordinates":[92.182973,24.490998],"type":"Point"}
}