{
  "type": "Feature",
  "properties": {
    "iso:country":"IN",
    "ks:ks_name":"Punia Part 2",
    "ks:ks_pop":344,
    "ks:ks_type":"HABITATION",
    "name:eng_x_preferred":[
        "Punia Part 2"
    ],
    "wof:name":"Punia Part 2",
    "wof:placetype":"locality",
    "wof:population":344
},
  "geometry": {"coordinates":[91.864977,26.367229],"type":"Point"}
}