{
  "type": "Feature",
  "properties": {
    "iso:country":"IN",
    "ks:ks_name":"Revatipalem",
    "ks:ks_pop":221,
    "ks:ks_type":"VILLAGE",
    "name:eng_x_preferred":[
        "Revatipalem"
    ],
    "wof:name":"Revatipalem",
    "wof:placetype":"locality",
    "wof:population":221
},
  "geometry": {"coordinates":[82.142347,17.483106],"type":"Point"}
}