{
  "type": "Feature",
  "properties": {
    "iso:country":"IN",
    "ks:ks_name":"Jaripada",
    "ks:ks_pop":121,
    "ks:ks_type":"VILLAGE",
    "name:eng_x_preferred":[
        "Jaripada"
    ],
    "wof:name":"Jaripada",
    "wof:placetype":"locality",
    "wof:population":121
},
  "geometry": {"coordinates":[85.189583,19.951211],"type":"Point"}
}