{
  "type": "Feature",
  "properties": {
    "iso:country":"IN",
    "ks:ks_name":"Kittur Hadi",
    "ks:ks_pop":80,
    "ks:ks_type":"HABITATION",
    "name:eng_x_preferred":[
        "Kittur Hadi"
    ],
    "wof:name":"Kittur Hadi",
    "wof:placetype":"locality",
    "wof:population":80
},
  "geometry": {"coordinates":[76.33138599999999,11.928755],"type":"Point"}
}