{
  "type": "Feature",
  "properties": {
    "iso:country":"IN",
    "ks:ks_name":"Nawatanr",
    "ks:ks_pop":7,
    "ks:ks_type":"VILLAGE",
    "name:eng_x_preferred":[
        "Nawatanr"
    ],
    "wof:name":"Nawatanr",
    "wof:placetype":"locality",
    "wof:population":7
},
  "geometry": {"coordinates":[86.48594300000001,24.087291],"type":"Point"}
}