{
  "type": "Feature",
  "properties": {
    "gn:admin1_code":"35",
    "gn:admin2_code":"457.0",
    "gn:asciiname":"Arjunnalatola",
    "gn:country_code":"IN",
    "gn:dem":340,
    "gn:feature_class":"P",
    "gn:feature_code":"PPL",
    "gn:name":"Arjunn\u0101l\u0101tola",
    "gn:population":0,
    "gn:timezone":"Asia/Kolkata",
    "iso:country":"IN",
    "wof:name":"Arjunnalatola",
    "wof:placetype":"locality"
},
  "geometry": {"coordinates":[79.8032,21.7545],"type":"Point"}
}