{
  "type": "Feature",
  "properties": {
    "iso:country":"IN",
    "ks:ks_name":"Sulunga",
    "ks:ks_pop":149,
    "ks:ks_type":"VILLAGE",
    "name:eng_x_preferred":[
        "Sulunga"
    ],
    "wof:name":"Sulunga",
    "wof:placetype":"locality",
    "wof:population":149
},
  "geometry": {"coordinates":[87.48668000000001,24.205427],"type":"Point"}
}