{
  "type": "Feature",
  "properties": {
    "iso:country":"IN",
    "ks:ks_name":"Kothe Khokhar Kalan",
    "ks:ks_pop":94,
    "ks:ks_type":"HABITATION",
    "name:eng_x_preferred":[
        "Kothe Khokhar Kalan"
    ],
    "wof:name":"Kothe Khokhar Kalan",
    "wof:placetype":"locality",
    "wof:population":94
},
  "geometry": {"coordinates":[75.34004,30.01752],"type":"Point"}
}