{
  "type": "Feature",
  "properties": {
    "iso:country":"IN",
    "ks:ks_name":"Timapur",
    "ks:ks_pop":0,
    "ks:ks_type":"VILLAGE",
    "name:eng_x_preferred":[
        "Timapur"
    ],
    "wof:name":"Timapur",
    "wof:placetype":"locality",
    "wof:population":0
},
  "geometry": {"coordinates":[78.390455,20.636264],"type":"Point"}
}