{
  "type": "Feature",
  "properties": {
    "iso:country":"IN",
    "ks:ks_name":"Shembadwadi",
    "ks:ks_pop":354,
    "ks:ks_type":"HABITATION",
    "name:eng_x_preferred":[
        "Shembadwadi"
    ],
    "wof:name":"Shembadwadi",
    "wof:placetype":"locality",
    "wof:population":354
},
  "geometry": {"coordinates":[73.478971,16.117238],"type":"Point"}
}