{
  "type": "Feature",
  "properties": {
    "iso:country":"IN",
    "ks:ks_name":"Dangmode",
    "ks:ks_pop":140,
    "ks:ks_type":"VILLAGE",
    "name:eng_x_preferred":[
        "Dangmode"
    ],
    "wof:name":"Dangmode",
    "wof:placetype":"locality",
    "wof:population":140
},
  "geometry": {"coordinates":[73.52835,16.183897],"type":"Point"}
}