{
  "type": "Feature",
  "properties": {
    "iso:country":"IN",
    "ks:ks_name":"Uttarwarikol",
    "ks:ks_pop":143,
    "ks:ks_type":"VILLAGE",
    "name:eng_x_preferred":[
        "Uttarwarikol"
    ],
    "wof:name":"Uttarwarikol",
    "wof:placetype":"locality",
    "wof:population":143
},
  "geometry": {"coordinates":[87.364028,25.688273],"type":"Point"}
}