{
  "type": "Feature",
  "properties": {
    "iso:country":"IN",
    "ks:ks_name":"Cherala Srimangala",
    "ks:ks_pop":59,
    "ks:ks_type":"HABITATION",
    "name:eng_x_preferred":[
        "Cherala Srimangala"
    ],
    "wof:name":"Cherala Srimangala",
    "wof:placetype":"locality",
    "wof:population":59
},
  "geometry": {"coordinates":[75.82166700000001,12.343611],"type":"Point"}
}