{
  "type": "Feature",
  "properties": {
    "gn:admin1_code":"36",
    "gn:admin2_code":"168.0",
    "gn:asciiname":"Bhitari",
    "gn:country_code":"IN",
    "gn:dem":148,
    "gn:feature_class":"P",
    "gn:feature_code":"PPL",
    "gn:name":"Bhit\u0101ri",
    "gn:population":0,
    "gn:timezone":"Asia/Kolkata",
    "iso:country":"IN",
    "wof:name":"Bhitari",
    "wof:placetype":"locality"
},
  "geometry": {"coordinates":[79.81185000000001,25.63701],"type":"Point"}
}