{
  "type": "Feature",
  "properties": {
    "gn:admin1_code":"19.0",
    "gn:admin2_code":"565.0",
    "gn:asciiname":"Somalapuram",
    "gn:country_code":"IN",
    "gn:dem":555,
    "gn:feature_class":"P",
    "gn:feature_code":"PPL",
    "gn:name":"Somal\u0101puram",
    "gn:population":0,
    "gn:timezone":"Asia/Kolkata",
    "iso:country":"IN",
    "wof:name":"Somalapuram",
    "wof:placetype":"locality"
},
  "geometry": {"coordinates":[76.29639,14.93126],"type":"Point"}
}