{
  "type": "Feature",
  "properties": {
    "iso:country":"IN",
    "ks:ks_name":"Adalpur",
    "ks:ks_pop":716,
    "ks:ks_type":"VILLAGE",
    "ks:ks_uagg_main":0,
    "name:eng_x_preferred":[
        "Adalpur"
    ],
    "wof:name":"Adalpur",
    "wof:placetype":"neighbourhood",
    "wof:population":716
},
  "geometry": {"coordinates":[76.13309700000001,28.39641],"type":"Point"}
}