{
  "type": "Feature",
  "properties": {
    "gn:admin1_code":"2.0",
    "gn:admin2_code":"543.0",
    "gn:asciiname":"Dasupeta",
    "gn:country_code":"IN",
    "gn:dem":88,
    "gn:feature_class":"P",
    "gn:feature_code":"PPL",
    "gn:name":"D\u0101supeta",
    "gn:population":0,
    "gn:timezone":"Asia/Kolkata",
    "iso:country":"IN",
    "ks:ks_alt_nam":"D\u0101supeta",
    "ks:ks_name":"Dasupeta",
    "ks:ks_pop":794,
    "ks:ks_type":"VILLAGE",
    "name:eng_x_preferred":[
        "Dasupeta"
    ],
    "name:eng_x_variant":[
        "D\u0101supeta"
    ],
    "wof:name":"Dasupeta",
    "wof:placetype":"locality",
    "wof:population":794
},
  "geometry": {"coordinates":[83.399674,18.350073],"type":"Point"}
}