{
  "type": "Feature",
  "properties": {
    "gn:admin1_code":"12",
    "gn:admin2_code":"3.0",
    "gn:asciiname":"Skirbuchan",
    "gn:country_code":"IN",
    "gn:dem":2936,
    "gn:feature_class":"P",
    "gn:feature_code":"PPL",
    "gn:name":"Skirbuchan",
    "gn:population":0,
    "gn:timezone":"Asia/Kolkata",
    "iso:country":"IN",
    "wof:name":"Skirbuchan",
    "wof:placetype":"locality"
},
  "geometry": {"coordinates":[76.71808,34.43190999999999],"type":"Point"}
}