{
  "type": "Feature",
  "properties": {
    "iso:country":"IN",
    "ks:ks_name":"Ammayipadi Jn",
    "ks:ks_pop":700,
    "ks:ks_type":"HABITATION",
    "name:eng_x_preferred":[
        "Ammayipadi Jn"
    ],
    "wof:name":"Ammayipadi Jn",
    "wof:placetype":"locality",
    "wof:population":700
},
  "geometry": {"coordinates":[76.33049699999999,11.219076],"type":"Point"}
}