{
  "type": "Feature",
  "properties": {
    "iso:country":"IN",
    "ks:ks_name":"Harpatti Gobindpur",
    "ks:ks_pop":75,
    "ks:ks_type":"VILLAGE",
    "name:eng_x_preferred":[
        "Harpatti Gobindpur"
    ],
    "wof:name":"Harpatti Gobindpur",
    "wof:placetype":"locality",
    "wof:population":75
},
  "geometry": {"coordinates":[86.20411,25.954687],"type":"Point"}
}