{
  "type": "Feature",
  "properties": {
    "iso:country":"IN",
    "name:ara_x_preferred":[
        "\u0645\u0633\u062a\u0639\u0645\u0631\u0629 \u0642\u064a\u0644\u0627"
    ],
    "name:ben_bn_x_preferred":[
        "\u0995\u09bf\u09b2\u09be \u0995\u09b2\u09cb\u09a8\u09c0"
    ],
    "name:ben_in_x_preferred":[
        "\u0995\u09bf\u09b2\u09be \u0995\u09b2\u09cb\u09a8\u09c0"
    ],
    "name:guj_x_preferred":[
        "\u0a95\u0ac0\u0ab2\u0abe \u0a95\u0acb\u0ab2\u0acb\u0aa8\u0ac0"
    ],
    "name:hin_x_preferred":[
        "\u0915\u093f\u0932\u093e \u0915\u0949\u0932\u094b\u0928\u0940"
    ],
    "name:kan_x_preferred":[
        "\u0c96\u0cbf\u0cb2\u0cbe \u0c95\u0cbe\u0cb2\u0cca\u0ca8\u0cbf"
    ],
    "name:mal_x_preferred":[
        "\u0d15\u0d3f\u0d32 \u0d15\u0d4b\u0d33\u0d28\u0d3f"
    ],
    "name:mar_x_preferred":[
        "\u0915\u093f\u0932\u093e \u0915\u0949\u0932\u0928\u0940"
    ],
    "name:pan_x_preferred":[
        "\u0a15\u0a3f\u0a32\u0a3e \u0a15\u0a3e\u0a32\u0a4c\u0a28\u0a40"
    ],
    "name:tam_x_preferred":[
        "\u0b95\u0bcd\u0bb5\u0bbf\u0bb2\u0bbe \u0b95\u0bc1\u0b9f\u0bbf\u0baf\u0bbf\u0bb0\u0bc1\u0baa\u0bcd\u0baa\u0bc1"
    ],
    "name:tel_x_preferred":[
        "\u0c15\u0c3f\u0c32\u0c3e \u0c15\u0c3e\u0c32\u0c28\u0c40"
    ],
    "name:urd_x_preferred":[
        "\u0642\u0644\u0639\u06c1 \u06a9\u0627\u0644\u0648\u0646\u06cc"
    ],
    "qs:name":"Qila Colony",
    "qs:name_adm0":"India",
    "qs:name_adm1":"Uttar Pradesh",
    "qs:photos":67,
    "qs:photos_1k":14,
    "qs:photos_9k":1,
    "qs:photos_9r":2,
    "qs:photos_all":67,
    "qs:photos_sr":2,
    "qs:placetype":"Suburb",
    "qs:pop_sr":"0",
    "wof:name":"Qila Colony",
    "wof:placetype":"neighbourhood"
},
  "geometry": {"coordinates":[83.02938899999999,25.325252],"type":"Point"}
}