{
  "type": "Feature",
  "properties": {
    "iso:country":"IN",
    "qs:name":"Qila Colony",
    "qs:name_adm0":"India",
    "qs:name_adm1":"Uttar Pradesh",
    "qs:photos":67,
    "qs:photos_1k":14,
    "qs:photos_9k":1,
    "qs:photos_9r":2,
    "qs:photos_all":67,
    "qs:photos_sr":2,
    "qs:placetype":"Suburb",
    "qs:pop_sr":"0",
    "wof:name":"Qila Colony",
    "wof:placetype":"neighbourhood"
},
  "geometry": {"coordinates":[83.02938899999999,25.325252],"type":"Point"}
}