{
  "type": "Feature",
  "properties": {
    "gn:admin1_code":"36.0",
    "gn:admin2_code":"185.0",
    "gn:asciiname":"Parsainian",
    "gn:country_code":"IN",
    "gn:dem":95,
    "gn:feature_class":"P",
    "gn:feature_code":"PPL",
    "gn:name":"Parsaini\u0101n",
    "gn:population":0,
    "gn:timezone":"Asia/Kolkata",
    "iso:country":"IN",
    "ks:ks_alt_nam":"Parsaini\u0101n",
    "ks:ks_name":"Parsainian",
    "ks:ks_type":"VILLAGE",
    "ks:ks_uagg_main":0,
    "name:eng_x_preferred":[
        "Parsainian"
    ],
    "name:eng_x_variant":[
        "Parsaini\u0101n"
    ],
    "wof:name":"Parsainian",
    "wof:placetype":"neighbourhood"
},
  "geometry": {"coordinates":[82.67116799999999,27.031119],"type":"Point"}
}