{
  "type": "Feature",
  "properties": {
    "iso:country":"IN",
    "ks:ks_name":"Umarpur",
    "ks:ks_pop":1533,
    "ks:ks_type":"VILLAGE",
    "name:eng_x_preferred":[
        "Umarpur"
    ],
    "wof:name":"Umarpur",
    "wof:placetype":"locality",
    "wof:population":1533
},
  "geometry": {"coordinates":[74.725859,31.800708],"type":"Point"}
}