{
  "type": "Feature",
  "properties": {
    "iso:country":"IN",
    "ks:ks_name":"Retpura",
    "ks:ks_pop":311,
    "ks:ks_type":"HABITATION",
    "name:eng_x_preferred":[
        "Retpura"
    ],
    "wof:name":"Retpura",
    "wof:placetype":"locality",
    "wof:population":311
},
  "geometry": {"coordinates":[75.16418400000001,24.957725],"type":"Point"}
}