{
  "type": "Feature",
  "properties": {
    "iso:country":"IN",
    "ks:ks_alt_nam":"SEETHARAMARJUPALEM",
    "ks:ks_name":"Seetharamarjupalem",
    "ks:ks_pop":104,
    "ks:ks_type":"HABITATION",
    "name:eng_x_preferred":[
        "Seetharamarjupalem"
    ],
    "wof:name":"Seetharamarjupalem",
    "wof:placetype":"locality",
    "wof:population":104
},
  "geometry": {"coordinates":[79.690899,15.92949],"type":"Point"}
}