{
  "type": "Feature",
  "properties": {
    "gn:admin1_code":"36.0",
    "gn:admin2_code":"140.0",
    "gn:asciiname":"Pabhi Sadiqpur",
    "gn:country_code":"IN",
    "gn:dem":216,
    "gn:feature_class":"P",
    "gn:feature_code":"PPL",
    "gn:name":"P\u0101bhi S\u0101diqpur",
    "gn:population":0,
    "gn:timezone":"Asia/Kolkata",
    "iso:country":"IN",
    "ks:ks_alt_nam":"P\u0101bhi S\u0101diqpur",
    "ks:ks_name":"Pabhi Sadiqpur",
    "ks:ks_type":"VILLAGE",
    "ks:ks_uagg_main":0,
    "wof:name":"Pabhi Sadiqpur",
    "wof:placetype":"neighbourhood"
},
  "geometry": {"coordinates":[77.28493,28.77573],"type":"Point"}
}