{
  "type": "Feature",
  "properties": {
    "gn:admin1_code":"21.0",
    "gn:admin2_code":"393.0",
    "gn:asciiname":"Kankara",
    "gn:country_code":"IN",
    "gn:dem":194,
    "gn:feature_class":"P",
    "gn:feature_code":"PPL",
    "gn:name":"Kankara",
    "gn:population":0,
    "gn:timezone":"Asia/Kolkata",
    "iso:country":"IN",
    "wof:name":"Kankara",
    "wof:placetype":"locality"
},
  "geometry": {"coordinates":[83.30143000000002,20.75174],"type":"Point"}
}