{
  "type": "Feature",
  "properties": {
    "gn:admin1_code":"16.0",
    "gn:admin2_code":"516.0",
    "gn:asciiname":"Khirmani",
    "gn:country_code":"IN",
    "gn:dem":602,
    "gn:feature_class":"P",
    "gn:feature_code":"PPL",
    "gn:name":"Khirmani",
    "gn:population":0,
    "gn:timezone":"Asia/Kolkata",
    "iso:country":"IN",
    "wof:name":"Khirmani",
    "wof:placetype":"locality"
},
  "geometry": {"coordinates":[74.28289000000002,20.7059],"type":"Point"}
}