{
  "type": "Feature",
  "properties": {
    "iso:country":"IN",
    "ks:ks_name":"Eka",
    "ks:ks_pop":544,
    "ks:ks_type":"VILLAGE",
    "name:eng_x_preferred":[
        "Eka"
    ],
    "wof:name":"Eka",
    "wof:placetype":"locality",
    "wof:population":544
},
  "geometry": {"coordinates":[72.016487,26.981029],"type":"Point"}
}