{
  "type": "Feature",
  "properties": {
    "iso:country":"IN",
    "ks:ks_name":"Rani Colony",
    "ks:ks_pop":435,
    "ks:ks_type":"HABITATION",
    "name:eng_x_preferred":[
        "Rani Colony"
    ],
    "wof:name":"Rani Colony",
    "wof:placetype":"locality",
    "wof:population":435
},
  "geometry": {"coordinates":[79.709981,11.674662],"type":"Point"}
}