{
  "type": "Feature",
  "properties": {
    "iso:country":"IN",
    "ks:ks_name":"Kitma",
    "ks:ks_pop":0,
    "ks:ks_type":"VILLAGE",
    "name:eng_x_preferred":[
        "Kitma"
    ],
    "wof:name":"Kitma",
    "wof:placetype":"locality",
    "wof:population":0
},
  "geometry": {"coordinates":[85.574713,23.544988],"type":"Point"}
}