{
  "type": "Feature",
  "properties": {
    "gn:admin1_code":"36.0",
    "gn:admin2_code":"170.0",
    "gn:asciiname":"Gobri",
    "gn:country_code":"IN",
    "gn:dem":191,
    "gn:feature_class":"P",
    "gn:feature_code":"PPL",
    "gn:name":"Gobri",
    "gn:population":0,
    "gn:timezone":"Asia/Kolkata",
    "iso:country":"IN",
    "ks:ks_name":"Gobari",
    "ks:ks_pop":276,
    "ks:ks_type":"HABITATION",
    "name:eng_x_preferred":[
        "Gobari"
    ],
    "name:eng_x_variant":[
        "Gobri"
    ],
    "wof:name":"Gobari",
    "wof:placetype":"locality",
    "wof:population":276
},
  "geometry": {"coordinates":[80.70804200000001,25.06845],"type":"Point"}
}