{
  "type": "Feature",
  "properties": {
    "gn:admin1_code":"34.0",
    "gn:admin2_code":"204.0",
    "gn:asciiname":"Rupdih",
    "gn:country_code":"IN",
    "gn:dem":73,
    "gn:feature_class":"P",
    "gn:feature_code":"PPL",
    "gn:name":"R\u016bpd\u012bh",
    "gn:population":0,
    "gn:timezone":"Asia/Kolkata",
    "iso:country":"IN",
    "ks:ks_alt_nam":"R\u016bpd\u012bh",
    "ks:ks_name":"Rupdih",
    "ks:ks_pop":1572,
    "ks:ks_type":"VILLAGE",
    "ks:ks_uagg_main":0,
    "name:eng_x_preferred":[
        "Rupdih"
    ],
    "name:eng_x_variant":[
        "R\u016bpd\u012bh"
    ],
    "wof:name":"Rupdih",
    "wof:placetype":"neighbourhood",
    "wof:population":1572
},
  "geometry": {"coordinates":[84.73560500000001,26.60195],"type":"Point"}
}