{
  "type": "Feature",
  "properties": {
    "gn:admin1_code":"36",
    "gn:admin2_code":"147.0",
    "gn:asciiname":"Ludhauli",
    "gn:country_code":"IN",
    "gn:dem":160,
    "gn:feature_class":"P",
    "gn:feature_code":"PPL",
    "gn:name":"Ludhauli",
    "gn:population":0,
    "gn:timezone":"Asia/Kolkata",
    "iso:country":"IN",
    "wof:name":"Ludhauli",
    "wof:placetype":"locality"
},
  "geometry": {"coordinates":[78.71585999999998,27.03814],"type":"Point"}
}