{
  "type": "Feature",
  "properties": {
    "iso:country":"IN",
    "ks:ks_name":"Dhangarwadi",
    "ks:ks_pop":35,
    "ks:ks_type":"HABITATION",
    "name:eng_x_preferred":[
        "Dhangarwadi"
    ],
    "wof:name":"Dhangarwadi",
    "wof:placetype":"locality",
    "wof:population":35
},
  "geometry": {"coordinates":[73.72340199999999,16.008636],"type":"Point"}
}