{
  "type": "Feature",
  "properties": {
    "iso:country":"IN",
    "ks:ks_name":"Shedi Moole",
    "ks:ks_pop":72,
    "ks:ks_type":"HABITATION",
    "name:eng_x_preferred":[
        "Shedi Moole"
    ],
    "wof:name":"Shedi Moole",
    "wof:placetype":"locality",
    "wof:population":72
},
  "geometry": {"coordinates":[74.420371,14.323269],"type":"Point"}
}