{
  "type": "Feature",
  "properties": {
    "gn:admin1_code":"21.0",
    "gn:admin2_code":"393.0",
    "gn:asciiname":"Ghantabahali",
    "gn:country_code":"IN",
    "gn:dem":272,
    "gn:feature_class":"P",
    "gn:feature_code":"PPL",
    "gn:name":"Ghantabahali",
    "gn:population":0,
    "gn:timezone":"Asia/Kolkata",
    "iso:country":"IN",
    "wof:name":"Ghantabahali",
    "wof:placetype":"locality"
},
  "geometry": {"coordinates":[83.023,20.3899],"type":"Point"}
}