{
  "type": "Feature",
  "properties": {
    "gn:admin1_code":"2",
    "gn:admin2_code":"547.0",
    "gn:asciiname":"Prattipadu",
    "gn:country_code":"IN",
    "gn:dem":9,
    "gn:feature_class":"P",
    "gn:feature_code":"PPL",
    "gn:name":"Prattip\u0101du",
    "gn:population":0,
    "gn:timezone":"Asia/Kolkata",
    "iso:country":"IN",
    "wof:name":"Prattipadu",
    "wof:placetype":"locality"
},
  "geometry": {"coordinates":[81.16786,16.53662000000001],"type":"Point"}
}