{
  "type": "Feature",
  "properties": {
    "gn:admin1_code":"2.0",
    "gn:admin2_code":"545.0",
    "gn:asciiname":"Pidimgoyya",
    "gn:country_code":"IN",
    "gn:dem":63,
    "gn:feature_class":"P",
    "gn:feature_code":"PPL",
    "gn:name":"Pidimgoyya",
    "gn:population":0,
    "gn:timezone":"Asia/Kolkata",
    "iso:country":"IN",
    "name:tel_x_preferred":[
        "\u0c2a\u0c3f\u0c21\u0c3f\u0c02\u0c17\u0c4a\u0c2f\u0c4d\u0c2f\u0c3f"
    ],
    "wof:name":"Pidimgoyya",
    "wof:placetype":"locality"
},
  "geometry": {"coordinates":[81.82969,17.00671],"type":"Point"}
}