{
  "type": "Feature",
  "properties": {
    "gn:admin1_code":"25.0",
    "gn:admin2_code":"620.0",
    "gn:asciiname":"Mel Kadukaval",
    "gn:country_code":"IN",
    "gn:dem":42,
    "gn:feature_class":"P",
    "gn:feature_code":"PPL",
    "gn:name":"Mel K\u0101duk\u0101val",
    "gn:population":0,
    "gn:timezone":"Asia/Kolkata",
    "iso:country":"IN",
    "wof:name":"Mel Kadukaval",
    "wof:placetype":"neighbourhood"
},
  "geometry": {"coordinates":[79.16907999999999,10.7975],"type":"Point"}
}