{
  "type": "Feature",
  "properties": {
    "gn:admin1_code":"2.0",
    "gn:admin2_code":"542.0",
    "gn:asciiname":"Yatapeta",
    "gn:country_code":"IN",
    "gn:dem":24,
    "gn:feature_class":"P",
    "gn:feature_code":"PPL",
    "gn:name":"Y\u0101tapeta",
    "gn:population":0,
    "gn:timezone":"Asia/Kolkata",
    "iso:country":"IN",
    "ks:ks_name":"Yathapeta",
    "ks:ks_pop":1147,
    "ks:ks_type":"HABITATION",
    "name:eng_x_preferred":[
        "Yathapeta"
    ],
    "name:eng_x_variant":[
        "Yatapeta"
    ],
    "wof:name":"Yathapeta",
    "wof:placetype":"locality",
    "wof:population":1147
},
  "geometry": {"coordinates":[83.828658,18.187153],"type":"Point"}
}