{
  "type": "Feature",
  "properties": {
    "iso:country":"IN",
    "ks:ks_name":"Uthandanga",
    "ks:ks_pop":218,
    "ks:ks_type":"VILLAGE",
    "ks:ks_uagg_main":0,
    "name:eng_x_preferred":[
        "Uthandanga"
    ],
    "wof:name":"Uthandanga",
    "wof:placetype":"locality",
    "wof:population":218
},
  "geometry": {"coordinates":[88.553076,22.738989],"type":"Point"}
}