{
  "type": "Feature",
  "properties": {
    "gn:admin1_code":"19.0",
    "gn:admin2_code":"582.0",
    "gn:asciiname":"Kancharlahalli",
    "gn:country_code":"IN",
    "gn:dem":793,
    "gn:feature_class":"P",
    "gn:feature_code":"PPL",
    "gn:name":"Kanch\u0101rlahalli",
    "gn:population":0,
    "gn:timezone":"Asia/Kolkata",
    "iso:country":"IN",
    "wof:name":"Kancharlahalli",
    "wof:placetype":"locality"
},
  "geometry": {"coordinates":[78.069,13.52236],"type":"Point"}
}