{
  "type": "Feature",
  "properties": {
    "iso:country":"IN",
    "ks:ks_name":"Bisunpur",
    "ks:ks_pop":308,
    "ks:ks_type":"HABITATION",
    "ks:ks_uagg_main":0,
    "name:eng_x_preferred":[
        "Bisunpur"
    ],
    "wof:name":"Bisunpur",
    "wof:placetype":"neighbourhood",
    "wof:population":308
},
  "geometry": {"coordinates":[86.622788,25.381357],"type":"Point"}
}