{
  "type": "Feature",
  "properties": {
    "iso:country":"IN",
    "ks:ks_name":"Holejaddi",
    "ks:ks_pop":16,
    "ks:ks_type":"HABITATION",
    "name:eng_x_preferred":[
        "Holejaddi"
    ],
    "wof:name":"Holejaddi",
    "wof:placetype":"locality",
    "wof:population":16
},
  "geometry": {"coordinates":[74.726258,14.465294],"type":"Point"}
}