{
  "type": "Feature",
  "properties": {
    "iso:country":"IN",
    "ks:ks_name":"Kallupalaiyam",
    "ks:ks_pop":679,
    "ks:ks_type":"VILLAGE",
    "name:eng_x_preferred":[
        "Kallupalaiyam"
    ],
    "wof:name":"Kallupalaiyam",
    "wof:placetype":"locality",
    "wof:population":679
},
  "geometry": {"coordinates":[78.112309,11.43416],"type":"Point"}
}