{
  "type": "Feature",
  "properties": {
    "iso:country":"IN",
    "ks:ks_alt_nam":"CHAMAR TOL",
    "ks:ks_name":"Chamar Tol",
    "ks:ks_pop":159,
    "ks:ks_type":"HABITATION",
    "name:eng_x_preferred":[
        "Chamar Tol"
    ],
    "wof:name":"Chamar Tol",
    "wof:placetype":"locality",
    "wof:population":159
},
  "geometry": {"coordinates":[86.134928,25.914974],"type":"Point"}
}