{
  "type": "Feature",
  "properties": {
    "iso:country":"IN",
    "ks:ks_name":"Pohumara",
    "ks:ks_pop":1116,
    "ks:ks_type":"VILLAGE",
    "ks:ks_uagg_main":0,
    "name:eng_x_preferred":[
        "Pohumara"
    ],
    "wof:name":"Pohumara",
    "wof:placetype":"neighbourhood",
    "wof:population":1116
},
  "geometry": {"coordinates":[94.259294,26.978703],"type":"Point"}
}