{
  "type": "Feature",
  "properties": {
    "gn:admin1_code":"35",
    "gn:admin2_code":"429.0",
    "gn:asciiname":"Poinua",
    "gn:country_code":"IN",
    "gn:dem":310,
    "gn:feature_class":"P",
    "gn:feature_code":"PPL",
    "gn:name":"Poinua",
    "gn:population":0,
    "gn:timezone":"Asia/Kolkata",
    "iso:country":"IN",
    "wof:name":"Poinua",
    "wof:placetype":"locality"
},
  "geometry": {"coordinates":[80.90443,24.6456],"type":"Point"}
}