{
  "type": "Feature",
  "properties": {
    "gn:admin1_code":"39.0",
    "gn:admin2_code":"60.0",
    "gn:asciiname":"Bangaon",
    "gn:country_code":"IN",
    "gn:dem":978,
    "gn:feature_class":"P",
    "gn:feature_code":"PPL",
    "gn:name":"Bangaon",
    "gn:population":0,
    "gn:timezone":"Asia/Kolkata",
    "iso:country":"IN",
    "name:ben_x_preferred":[
        "\u09ac\u09a8\u0997\u09be\u0981"
    ],
    "name:bih_x_preferred":[
        "\u092c\u0928\u0917\u093e\u0901\u0935"
    ],
    "name:bpy_x_preferred":[
        "\u09ac\u09a8\u0997\u09be\u0981\u0993"
    ],
    "name:ceb_x_preferred":[
        "Bangaon"
    ],
    "name:fra_x_preferred":[
        "Bangaon"
    ],
    "name:ita_x_preferred":[
        "Bangaon"
    ],
    "name:mlg_x_preferred":[
        "Bangaon"
    ],
    "name:msa_x_preferred":[
        "Bangaon"
    ],
    "name:new_x_preferred":[
        "\u092c\u093e\u0928\u0917\u093e\u0935\u0902"
    ],
    "name:spa_x_preferred":[
        "Bangaon"
    ],
    "name:swe_x_preferred":[
        "Bongaon"
    ],
    "name:vie_x_preferred":[
        "Bangaon"
    ],
    "name:zho_x_preferred":[
        "\u90a6\u683c\u963f\u5965\u6069"
    ],
    "wof:name":"Bangaon",
    "wof:placetype":"locality"
},
  "geometry": {"coordinates":[78.14497,30.31789],"type":"Point"}
}