{
  "type": "Feature",
  "properties": {
    "iso:country":"IN",
    "ks:ks_name":"Khamanmunda",
    "ks:ks_pop":841,
    "ks:ks_type":"HABITATION",
    "name:eng_x_preferred":[
        "Khamanmunda"
    ],
    "wof:name":"Khamanmunda",
    "wof:placetype":"locality",
    "wof:population":841
},
  "geometry": {"coordinates":[84.522293,21.245823],"type":"Point"}
}