{
  "type": "Feature",
  "properties": {
    "iso:country":"IN",
    "ks:ks_name":"Boroladanguri No 2",
    "ks:ks_pop":110,
    "ks:ks_type":"VILLAGE",
    "name:eng_x_preferred":[
        "Boroladanguri No 2"
    ],
    "wof:name":"Boroladanguri No 2",
    "wof:placetype":"locality",
    "wof:population":110
},
  "geometry": {"coordinates":[90.62217,26.614318],"type":"Point"}
}