{
  "type": "Feature",
  "properties": {
    "gn:country":"IN",
    "gn:fcode":"PPL",
    "gn:population":19689,
    "iso:country":"IN",
    "name:und_x_variant":[
        "Vadakku Viravanall\u016br"
    ],
    "qs:name":"Viravanall\u016br",
    "qs:photos_9r":0,
    "qs:photos_sr":0,
    "qs:pop_sr":"6",
    "wof:name":"Viravanall\u016br",
    "wof:placetype":"locality",
    "wof:population":19689
},
  "geometry": {"coordinates":[77.51895,8.6961],"type":"Point"}
}