{
  "type": "Feature",
  "properties": {
    "iso:country":"IN",
    "ks:ks_name":"Sarnon Ki Beri",
    "ks:ks_pop":738,
    "ks:ks_type":"VILLAGE",
    "name:eng_x_preferred":[
        "Sarnon Ki Beri"
    ],
    "wof:name":"Sarnon Ki Beri",
    "wof:placetype":"locality",
    "wof:population":738
},
  "geometry": {"coordinates":[72.188311,26.132583],"type":"Point"}
}