{
  "type": "Feature",
  "properties": {
    "iso:country":"IN",
    "ks:ks_name":"Shanthi Kumbari",
    "ks:ks_pop":499,
    "ks:ks_type":"HABITATION",
    "name:eng_x_preferred":[
        "Shanthi Kumbari"
    ],
    "wof:name":"Shanthi Kumbari",
    "wof:placetype":"locality",
    "wof:population":499
},
  "geometry": {"coordinates":[75.39984800000001,13.273622],"type":"Point"}
}