{
  "type": "Feature",
  "properties": {
    "iso:country":"IN",
    "ks:ks_name":"Sonairai Khil Para",
    "ks:ks_pop":497,
    "ks:ks_type":"HABITATION",
    "ks:ks_uagg_main":0,
    "name:eng_x_preferred":[
        "Sonairai Khil Para"
    ],
    "wof:name":"Sonairai Khil Para",
    "wof:placetype":"neighbourhood",
    "wof:population":497
},
  "geometry": {"coordinates":[91.554614,23.041451],"type":"Point"}
}