{
  "type": "Feature",
  "properties": {
    "gn:admin1_code":"2",
    "gn:admin2_code":"546.0",
    "gn:asciiname":"Bornagondi",
    "gn:country_code":"IN",
    "gn:dem":39,
    "gn:feature_class":"P",
    "gn:feature_code":"PPL",
    "gn:name":"Bornagondi",
    "gn:population":0,
    "gn:timezone":"Asia/Kolkata",
    "iso:country":"IN",
    "wof:name":"Bornagondi",
    "wof:placetype":"locality"
},
  "geometry": {"coordinates":[81.57476,17.40435],"type":"Point"}
}