{
  "type": "Feature",
  "properties": {
    "gn:admin1_code":"34.0",
    "gn:admin2_code":"209.0",
    "gn:asciiname":"Chakla",
    "gn:country_code":"IN",
    "gn:dem":57,
    "gn:feature_class":"P",
    "gn:feature_code":"PPL",
    "gn:name":"Chakla",
    "gn:population":0,
    "gn:timezone":"Asia/Kolkata",
    "iso:country":"IN",
    "wof:name":"Chakla",
    "wof:placetype":"locality"
},
  "geometry": {"coordinates":[87.12741,26.09023],"type":"Point"}
}