{
  "type": "Feature",
  "properties": {
    "gn:admin1_code":"24.0",
    "gn:admin2_code":"110.0",
    "gn:asciiname":"Govindgarh",
    "gn:country_code":"IN",
    "gn:dem":467,
    "gn:feature_class":"P",
    "gn:feature_code":"PPL",
    "gn:name":"Govindgarh",
    "gn:population":0,
    "gn:timezone":"Asia/Kolkata",
    "iso:country":"IN",
    "name:ben_x_preferred":[
        "\u0997\u09cb\u09ac\u09bf\u09a8\u09cd\u09a6\u0997\u09a1\u09bc"
    ],
    "name:cat_x_preferred":[
        "Govindgarh"
    ],
    "name:ceb_x_preferred":[
        "Govindgarh"
    ],
    "name:nld_x_preferred":[
        "Govindgarh"
    ],
    "name:swe_x_preferred":[
        "Govindgarh"
    ],
    "wof:name":"Govindgarh",
    "wof:placetype":"locality"
},
  "geometry": {"coordinates":[75.65068000000002,27.24775],"type":"Point"}
}