{
  "type": "Feature",
  "properties": {
    "iso:country":"IN",
    "ks:ks_name":"Madlamane",
    "ks:ks_pop":25,
    "ks:ks_type":"HABITATION",
    "name:eng_x_preferred":[
        "Madlamane"
    ],
    "wof:name":"Madlamane",
    "wof:placetype":"locality",
    "wof:population":25
},
  "geometry": {"coordinates":[74.83884399999999,14.319253],"type":"Point"}
}