{
  "type": "Feature",
  "properties": {
    "gn:admin1_code":"34.0",
    "gn:admin2_code":"225.0",
    "gn:asciiname":"Amba",
    "gn:country_code":"IN",
    "gn:dem":125,
    "gn:feature_class":"P",
    "gn:feature_code":"PPL",
    "gn:name":"Amba",
    "gn:population":0,
    "gn:timezone":"Asia/Kolkata",
    "iso:country":"IN",
    "name:ceb_x_preferred":[
        "Amba"
    ],
    "name:fra_x_preferred":[
        "Amba"
    ],
    "name:ita_x_preferred":[
        "Amba"
    ],
    "name:pol_x_preferred":[
        "Amba"
    ],
    "name:rus_x_preferred":[
        "\u0410\u043c\u0431\u0430"
    ],
    "name:spa_x_preferred":[
        "Amba"
    ],
    "name:swe_x_preferred":[
        "Amba"
    ],
    "wof:name":"Amba",
    "wof:placetype":"locality"
},
  "geometry": {"coordinates":[87.01746,24.7558],"type":"Point"}
}