{
  "type": "Feature",
  "properties": {
    "iso:country":"IN",
    "ks:ks_alt_nam":"PASWAN TOLA",
    "ks:ks_name":"Paswan Tola",
    "ks:ks_pop":245,
    "ks:ks_type":"HABITATION",
    "name:eng_x_preferred":[
        "Paswan Tola"
    ],
    "wof:name":"Paswan Tola",
    "wof:placetype":"locality",
    "wof:population":245
},
  "geometry": {"coordinates":[84.873372,25.040283],"type":"Point"}
}