{
  "type": "Feature",
  "properties": {
    "iso:country":"IN",
    "ks:ks_alt_nam":"mugulkhand",
    "ks:ks_name":"Mugulkhand",
    "ks:ks_pop":39,
    "ks:ks_type":"HABITATION",
    "name:eng_x_preferred":[
        "Mugulkhand"
    ],
    "wof:name":"Mugulkhand",
    "wof:placetype":"locality",
    "wof:population":39
},
  "geometry": {"coordinates":[74.565545,15.229237],"type":"Point"}
}