{
  "type": "Feature",
  "properties": {
    "gn:admin1_code":"24.0",
    "gn:admin2_code":"130.0",
    "gn:asciiname":"Dobricha",
    "gn:country_code":"IN",
    "gn:dem":430,
    "gn:feature_class":"P",
    "gn:feature_code":"PPL",
    "gn:name":"Dobricha",
    "gn:population":0,
    "gn:timezone":"Asia/Kolkata",
    "iso:country":"IN",
    "ks:ks_name":"Dobdicha",
    "ks:ks_pop":845,
    "ks:ks_type":"HABITATION",
    "name:eng_x_preferred":[
        "Dobdicha"
    ],
    "name:eng_x_variant":[
        "Dobricha"
    ],
    "wof:name":"Dobdicha",
    "wof:placetype":"locality",
    "wof:population":845
},
  "geometry": {"coordinates":[74.202122,24.181958],"type":"Point"}
}