{
  "type": "Feature",
  "properties": {
    "gn:country":"IN",
    "gn:fcode":"PPL",
    "gn:population":29459,
    "iso:country":"IN",
    "ks:ks_alt_nam":"Main\u0101guri",
    "ks:ks_name":"Mainaguri",
    "ks:ks_type":"URBAN",
    "ks:ks_uagg_main":0,
    "name:ben_x_preferred":[
        "\u09ae\u09af\u09bc\u09a8\u09be\u0997\u09c1\u09a1\u09bc\u09bf"
    ],
    "name:bpy_x_preferred":[
        "\u09ae\u09af\u09bc\u09a8\u09be\u0997\u09c1\u09b0\u09bf"
    ],
    "name:ceb_x_preferred":[
        "Main\u0101guri"
    ],
    "name:eng_x_preferred":[
        "Mainaguri"
    ],
    "name:eng_x_variant":[
        "Main\u0101guri"
    ],
    "name:fra_x_preferred":[
        "Mainaguri"
    ],
    "name:hif_x_preferred":[
        "Mainaguri"
    ],
    "name:ita_x_preferred":[
        "Mainaguri"
    ],
    "name:mlg_x_preferred":[
        "Mainaguri"
    ],
    "name:msa_x_preferred":[
        "Mainaguri"
    ],
    "name:nan_x_preferred":[
        "Mainaguri"
    ],
    "name:new_x_preferred":[
        "\u092e\u0948\u0928\u093e\u0917\u0941\u0930\u0940"
    ],
    "name:nld_x_preferred":[
        "Mainaguri"
    ],
    "name:ori_x_preferred":[
        "\u0b2e\u0b3e\u0b07\u0b28\u0b3e\u0b17\u0b41\u0b21\u0b3c\u0b3f"
    ],
    "name:por_x_preferred":[
        "Mainaguri"
    ],
    "name:spa_x_preferred":[
        "Mainaguri"
    ],
    "name:swe_x_preferred":[
        "Main\u0101guri"
    ],
    "name:urd_x_preferred":[
        "\u0645\u0627\u06cc\u0646\u0627\u06af\u0648\u0631\u06cc"
    ],
    "name:vie_x_preferred":[
        "Mainaguri"
    ],
    "name:zho_x_preferred":[
        "\u8fc8\u7eb3\u53e4\u91cc"
    ],
    "qs:name":"Main\u0101guri",
    "qs:photos_9r":0,
    "qs:photos_sr":0,
    "qs:pop_sr":"7",
    "wof:name":"Mainaguri",
    "wof:placetype":"neighbourhood"
},
  "geometry": {"coordinates":[88.820401,26.562632],"type":"Point"}
}