{
  "type": "Feature",
  "properties": {
    "gn:admin1_code":"36.0",
    "gn:admin2_code":"150.0",
    "gn:asciiname":"Tigra",
    "gn:country_code":"IN",
    "gn:dem":173,
    "gn:feature_class":"P",
    "gn:feature_code":"PPL",
    "gn:name":"Tigra",
    "gn:population":0,
    "gn:timezone":"Asia/Kolkata",
    "iso:country":"IN",
    "name:fra_x_preferred":[
        "Tigra"
    ],
    "name:ita_x_preferred":[
        "Tigra"
    ],
    "name:por_x_preferred":[
        "Tigresa"
    ],
    "name:spa_x_preferred":[
        "Tigra"
    ],
    "wof:name":"Tigra",
    "wof:placetype":"locality"
},
  "geometry": {"coordinates":[79.5401,28.42566],"type":"Point"}
}