{
  "type": "Feature",
  "properties": {
    "iso:country":"IN",
    "ks:ks_name":"Daraikocha",
    "ks:ks_pop":183,
    "ks:ks_type":"VILLAGE",
    "name:eng_x_preferred":[
        "Daraikocha"
    ],
    "wof:name":"Daraikocha",
    "wof:placetype":"locality",
    "wof:population":183
},
  "geometry": {"coordinates":[85.977142,22.69962],"type":"Point"}
}