{
  "type": "Feature",
  "properties": {
    "iso:country":"IN",
    "ks:ks_name":"Karra 1",
    "ks:ks_pop":2011,
    "ks:ks_type":"HABITATION",
    "name:eng_x_preferred":[
        "Karra 1"
    ],
    "wof:name":"Karra 1",
    "wof:placetype":"locality",
    "wof:population":2011
},
  "geometry": {"coordinates":[86.399473,24.878497],"type":"Point"}
}