{
  "type": "Feature",
  "properties": {
    "gn:admin1_code":"35.0",
    "gn:admin2_code":"421.0",
    "gn:asciiname":"Maina",
    "gn:country_code":"IN",
    "gn:dem":230,
    "gn:feature_class":"P",
    "gn:feature_code":"PPL",
    "gn:name":"Maina",
    "gn:population":0,
    "gn:timezone":"Asia/Kolkata",
    "iso:country":"IN",
    "name:bul_x_preferred":[
        "\u041c\u0430\u0439\u043d\u0430"
    ],
    "name:ceb_x_preferred":[
        "Maina"
    ],
    "name:deu_x_preferred":[
        "Maina"
    ],
    "name:heb_x_preferred":[
        "\u05de\u05d9\u05d9\u05e0\u05d4"
    ],
    "name:hye_x_preferred":[
        "\u0544\u0561\u0575\u0576\u0561"
    ],
    "name:ita_x_preferred":[
        "Maina"
    ],
    "name:por_x_preferred":[
        "Maina"
    ],
    "name:rus_x_preferred":[
        "\u041c\u0430\u0439\u043d\u0430"
    ],
    "name:swe_x_preferred":[
        "Maina"
    ],
    "name:ukr_x_preferred":[
        "\u041c\u0430\u0439\u043d\u0430"
    ],
    "wof:name":"Maina",
    "wof:placetype":"locality"
},
  "geometry": {"coordinates":[78.1207,25.9179],"type":"Point"}
}