{
  "type": "Feature",
  "properties": {
    "iso:country":"IN",
    "ks:ks_name":"Raigada",
    "ks:ks_pop":250,
    "ks:ks_type":"VILLAGE",
    "name:eng_x_preferred":[
        "Raigada"
    ],
    "wof:name":"Raigada",
    "wof:placetype":"locality",
    "wof:population":250
},
  "geometry": {"coordinates":[84.961628,20.464767],"type":"Point"}
}