{
  "type": "Feature",
  "properties": {
    "iso:country":"IN",
    "ks:ks_name":"Karanala",
    "ks:ks_pop":43,
    "ks:ks_type":"VILLAGE",
    "name:eng_x_preferred":[
        "Karanala"
    ],
    "wof:name":"Karanala",
    "wof:placetype":"locality",
    "wof:population":43
},
  "geometry": {"coordinates":[83.87831199999999,20.44449],"type":"Point"}
}