{
  "type": "Feature",
  "properties": {
    "iso:country":"IN",
    "ks:ks_name":"Girgaon",
    "ks:ks_pop":475,
    "ks:ks_type":"HABITATION",
    "name:eng_x_preferred":[
        "Girgaon"
    ],
    "wof:name":"Girgaon",
    "wof:placetype":"locality",
    "wof:population":475
},
  "geometry": {"coordinates":[80.162734,30.010234],"type":"Point"}
}