{
  "type": "Feature",
  "properties": {
    "gn:admin1_code":"25.0",
    "gn:admin2_code":"631.0",
    "gn:asciiname":"Valathottapalli",
    "gn:country_code":"IN",
    "gn:dem":932,
    "gn:feature_class":"P",
    "gn:feature_code":"PPL",
    "gn:name":"Valathottapalli",
    "gn:population":0,
    "gn:timezone":"Asia/Kolkata",
    "iso:country":"IN",
    "wof:name":"Valathottapalli",
    "wof:placetype":"neighbourhood"
},
  "geometry": {"coordinates":[77.70733,12.50478],"type":"Point"}
}