{
  "type": "Feature",
  "properties": {
    "iso:country":"IN",
    "ks:ks_name":"Edamalla",
    "ks:ks_pop":20,
    "ks:ks_type":"VILLAGE",
    "name:eng_x_preferred":[
        "Edamalla"
    ],
    "wof:name":"Edamalla",
    "wof:placetype":"locality",
    "wof:population":20
},
  "geometry": {"coordinates":[78.484352,29.816081],"type":"Point"}
}