{
  "type": "Feature",
  "properties": {
    "gn:admin1_code":"11.0",
    "gn:admin2_code":"33.0",
    "gn:asciiname":"Tutupani",
    "gn:country_code":"IN",
    "gn:dem":2864,
    "gn:feature_class":"P",
    "gn:feature_code":"PPL",
    "gn:name":"Tutup\u0101ni",
    "gn:population":0,
    "gn:timezone":"Asia/Kolkata",
    "iso:country":"IN",
    "wof:name":"Tutupani",
    "wof:placetype":"locality"
},
  "geometry": {"coordinates":[77.61213000000002,31.25824],"type":"Point"}
}