{
  "type": "Feature",
  "properties": {
    "iso:country":"IN",
    "ks:ks_name":"Dengakul",
    "ks:ks_pop":132,
    "ks:ks_type":"VILLAGE",
    "name:eng_x_preferred":[
        "Dengakul"
    ],
    "wof:name":"Dengakul",
    "wof:placetype":"locality",
    "wof:population":132
},
  "geometry": {"coordinates":[83.9646,19.152895],"type":"Point"}
}