{
  "type": "Feature",
  "properties": {
    "iso:country":"IN",
    "ks:ks_name":"Turetampadu",
    "ks:ks_pop":183,
    "ks:ks_type":"HABITATION",
    "name:eng_x_preferred":[
        "Turetampadu"
    ],
    "wof:name":"Turetampadu",
    "wof:placetype":"locality",
    "wof:population":183
},
  "geometry": {"coordinates":[82.368422,17.947392],"type":"Point"}
}