{
  "type": "Feature",
  "properties": {
    "iso:country":"IN",
    "ks:ks_alt_nam":"Koilisut\u0101",
    "ks:ks_name":"Koilisuta",
    "ks:ks_pop":303,
    "ks:ks_type":"VILLAGE",
    "name:eng_x_preferred":[
        "Koilisuta"
    ],
    "name:eng_x_variant":[
        "Koilisut\u0101"
    ],
    "wof:name":"Koilisuta",
    "wof:placetype":"locality",
    "wof:population":303
},
  "geometry": {"coordinates":[85.36870500000001,21.280427],"type":"Point"}
}