{
  "type": "Feature",
  "properties": {
    "iso:country":"IN",
    "ks:ks_name":"Hebkuli",
    "ks:ks_pop":53,
    "ks:ks_type":"HABITATION",
    "name:eng_x_preferred":[
        "Hebkuli"
    ],
    "wof:name":"Hebkuli",
    "wof:placetype":"locality",
    "wof:population":53
},
  "geometry": {"coordinates":[74.75209099999999,14.382953],"type":"Point"}
}