{
  "type": "Feature",
  "properties": {
    "iso:country":"IN",
    "ks:ks_name":"Chaibari Hindupara",
    "ks:ks_pop":2393,
    "ks:ks_type":"VILLAGE",
    "name:eng_x_preferred":[
        "Chaibari Hindupara"
    ],
    "wof:name":"Chaibari Hindupara",
    "wof:placetype":"locality",
    "wof:population":2393
},
  "geometry": {"coordinates":[90.4294,26.332846],"type":"Point"}
}