{
  "type": "Feature",
  "properties": {
    "iso:country":"IN",
    "ks:ks_name":"Koppaiyur H Colony",
    "ks:ks_pop":35,
    "ks:ks_type":"HABITATION",
    "name:eng_x_preferred":[
        "Koppaiyur H Colony"
    ],
    "wof:name":"Koppaiyur H Colony",
    "wof:placetype":"locality",
    "wof:population":35
},
  "geometry": {"coordinates":[76.978538,11.433396],"type":"Point"}
}