{
  "type": "Feature",
  "properties": {
    "iso:country":"IN",
    "ks:ks_name":"Pokhariya",
    "ks:ks_pop":209,
    "ks:ks_type":"VILLAGE",
    "ks:ks_uagg_main":0,
    "name:eng_x_preferred":[
        "Pokhariya"
    ],
    "wof:name":"Pokhariya",
    "wof:placetype":"neighbourhood",
    "wof:population":209
},
  "geometry": {"coordinates":[86.94744799999999,24.342386],"type":"Point"}
}