{
  "type": "Feature",
  "properties": {
    "gn:admin1_code":"36",
    "gn:admin2_code":"194.0",
    "gn:asciiname":"Barsara",
    "gn:country_code":"IN",
    "gn:dem":85,
    "gn:feature_class":"P",
    "gn:feature_code":"PPL",
    "gn:name":"Barsara",
    "gn:population":0,
    "gn:timezone":"Asia/Kolkata",
    "iso:country":"IN",
    "ks:ks_name":"Barsara",
    "ks:ks_pop":1554,
    "ks:ks_type":"VILLAGE",
    "ks:ks_uagg_main":0,
    "name:eng_x_preferred":[
        "Barsara"
    ],
    "wof:name":"Barsara",
    "wof:placetype":"neighbourhood",
    "wof:population":1554
},
  "geometry": {"coordinates":[82.55561299999999,25.956865],"type":"Point"}
}