{
  "type": "Feature",
  "properties": {
    "iso:country":"IN",
    "ks:ks_name":"Hapakarani",
    "ks:ks_pop":172,
    "ks:ks_type":"HABITATION",
    "name:eng_x_preferred":[
        "Hapakarani"
    ],
    "wof:name":"Hapakarani",
    "wof:placetype":"locality",
    "wof:population":172
},
  "geometry": {"coordinates":[74.40415900000001,15.114906],"type":"Point"}
}