{
  "type": "Feature",
  "properties": {
    "gn:admin1_code":"13.0",
    "gn:admin2_code":"594.0",
    "gn:asciiname":"Mannamangalam",
    "gn:country_code":"IN",
    "gn:dem":86,
    "gn:feature_class":"P",
    "gn:feature_code":"PPL",
    "gn:name":"Mannamangalam",
    "gn:population":0,
    "gn:timezone":"Asia/Kolkata",
    "iso:country":"IN",
    "name:msa_x_preferred":[
        "Mannamangalam"
    ],
    "wof:name":"Mannamangalam",
    "wof:placetype":"locality"
},
  "geometry": {"coordinates":[76.34348,10.48733],"type":"Point"}
}