{
  "type": "Feature",
  "properties": {
    "gn:admin1_code":"34.0",
    "gn:admin2_code":"223.0",
    "gn:asciiname":"Bandhumandar",
    "gn:country_code":"IN",
    "gn:dem":34,
    "gn:feature_class":"P",
    "gn:feature_code":"PPL",
    "gn:name":"B\u0101ndhumandar",
    "gn:population":0,
    "gn:timezone":"Asia/Kolkata",
    "iso:country":"IN",
    "name:und_x_variant":[
        "B\u0101ndhumandar",
        "Math\u0101r"
    ],
    "wof:name":"Bandhumandar",
    "wof:placetype":"locality"
},
  "geometry": {"coordinates":[86.49866,25.43536],"type":"Point"}
}