{
  "type": "Feature",
  "properties": {
    "iso:country":"IN",
    "ks:ks_name":"Goriya",
    "ks:ks_pop":493,
    "ks:ks_type":"VILLAGE",
    "name:eng_x_preferred":[
        "Goriya"
    ],
    "wof:name":"Goriya",
    "wof:placetype":"locality",
    "wof:population":493
},
  "geometry": {"coordinates":[73.17368,24.522568],"type":"Point"}
}