{
  "type": "Feature",
  "properties": {
    "gn:admin1_code":"11.0",
    "gn:admin2_code":"33.0",
    "gn:asciiname":"Depra",
    "gn:country_code":"IN",
    "gn:dem":1839,
    "gn:feature_class":"P",
    "gn:feature_code":"PPL",
    "gn:name":"Depra",
    "gn:population":0,
    "gn:timezone":"Asia/Kolkata",
    "iso:country":"IN",
    "wof:name":"Depra",
    "wof:placetype":"locality"
},
  "geometry": {"coordinates":[77.26716,31.16568],"type":"Point"}
}