{
  "type": "Feature",
  "properties": {
    "gn:admin1_code":"24.0",
    "gn:admin2_code":"118.0",
    "gn:asciiname":"Balwantgarh",
    "gn:country_code":"IN",
    "gn:dem":391,
    "gn:feature_class":"P",
    "gn:feature_code":"PPL",
    "gn:name":"Balwantgarh",
    "gn:population":0,
    "gn:timezone":"Asia/Kolkata",
    "iso:country":"IN",
    "wof:name":"Balwantgarh",
    "wof:placetype":"locality"
},
  "geometry": {"coordinates":[74.26326999999998,26.3144],"type":"Point"}
}