{
  "type": "Feature",
  "properties": {
    "iso:country":"IN",
    "ks:ks_name":"Totpara",
    "ks:ks_pop":846,
    "ks:ks_type":"VILLAGE",
    "name:eng_x_preferred":[
        "Totpara"
    ],
    "wof:name":"Totpara",
    "wof:placetype":"locality",
    "wof:population":846
},
  "geometry": {"coordinates":[90.174475,26.356057],"type":"Point"}
}