{
  "type": "Feature",
  "properties": {
    "iso:country":"IN",
    "ks:ks_name":"Budumgadiguda",
    "ks:ks_pop":74,
    "ks:ks_type":"HABITATION",
    "name:eng_x_preferred":[
        "Budumgadiguda"
    ],
    "wof:name":"Budumgadiguda",
    "wof:placetype":"locality",
    "wof:population":74
},
  "geometry": {"coordinates":[83.721526,18.807394],"type":"Point"}
}