{
  "type": "Feature",
  "properties": {
    "iso:country":"IN",
    "ks:ks_name":"Pangalpata",
    "ks:ks_pop":69,
    "ks:ks_type":"VILLAGE",
    "name:eng_x_preferred":[
        "Pangalpata"
    ],
    "wof:name":"Pangalpata",
    "wof:placetype":"locality",
    "wof:population":69
},
  "geometry": {"coordinates":[84.22087399999999,19.972017],"type":"Point"}
}