{
  "type": "Feature",
  "properties": {
    "gn:admin1_code":"34.0",
    "gn:admin2_code":"235.0",
    "gn:asciiname":"Hetampur",
    "gn:country_code":"IN",
    "gn:dem":111,
    "gn:feature_class":"P",
    "gn:feature_code":"PPL",
    "gn:name":"Hetampur",
    "gn:population":0,
    "gn:timezone":"Asia/Kolkata",
    "iso:country":"IN",
    "name:ben_x_preferred":[
        "\u09b9\u09c7\u09a4\u09ae\u09aa\u09c1\u09b0"
    ],
    "wof:name":"Hetampur",
    "wof:placetype":"locality"
},
  "geometry": {"coordinates":[84.46808,24.73972],"type":"Point"}
}