{
  "type": "Feature",
  "properties": {
    "gn:admin1_code":"24.0",
    "gn:admin2_code":"109.0",
    "gn:asciiname":"Pairiyan Ka Nagla",
    "gn:country_code":"IN",
    "gn:dem":237,
    "gn:feature_class":"P",
    "gn:feature_code":"PPL",
    "gn:name":"Pairiy\u0101n Ka Nagla",
    "gn:population":0,
    "gn:timezone":"Asia/Kolkata",
    "iso:country":"IN",
    "wof:name":"Pairiyan Ka Nagla",
    "wof:placetype":"locality"
},
  "geometry": {"coordinates":[76.90849,26.99091],"type":"Point"}
}