{
  "type": "Feature",
  "properties": {
    "gn:admin1_code":"36.0",
    "gn:admin2_code":"138.0",
    "gn:asciiname":"Nek",
    "gn:country_code":"IN",
    "gn:dem":227,
    "gn:feature_class":"P",
    "gn:feature_code":"PPL",
    "gn:name":"Nek",
    "gn:population":0,
    "gn:timezone":"Asia/Kolkata",
    "iso:country":"IN",
    "name:cat_x_preferred":[
        "Nek"
    ],
    "name:dan_x_preferred":[
        "Nek"
    ],
    "name:deu_x_preferred":[
        "Nek"
    ],
    "name:ell_x_preferred":[
        "Nek"
    ],
    "name:eml_x_preferred":[
        "Nek"
    ],
    "name:epo_x_preferred":[
        "Nek"
    ],
    "name:eus_x_preferred":[
        "Nek"
    ],
    "name:fin_x_preferred":[
        "Nek"
    ],
    "name:fra_x_preferred":[
        "Nek"
    ],
    "name:hun_x_preferred":[
        "Nek"
    ],
    "name:ita_x_preferred":[
        "Nek"
    ],
    "name:kat_x_preferred":[
        "\u10dc\u10d4\u10d9\u10d8"
    ],
    "name:lav_x_preferred":[
        "Neks"
    ],
    "name:nld_x_preferred":[
        "Nek"
    ],
    "name:oci_x_preferred":[
        "Nek"
    ],
    "name:pol_x_preferred":[
        "Nek"
    ],
    "name:por_x_preferred":[
        "Nek"
    ],
    "name:rus_x_preferred":[
        "\u041d\u0435\u043a"
    ],
    "name:sco_x_preferred":[
        "Nek"
    ],
    "name:spa_x_preferred":[
        "Nek"
    ],
    "name:swe_x_preferred":[
        "Nek"
    ],
    "name:tur_x_preferred":[
        "Nek"
    ],
    "name:ukr_x_preferred":[
        "\u0424\u0456\u043b\u0456\u043f\u043f\u043e \u041d\u0435\u0432\u0456\u0430\u043d\u0456"
    ],
    "name:vep_x_preferred":[
        "Nek"
    ],
    "wof:name":"Nek",
    "wof:placetype":"locality"
},
  "geometry": {"coordinates":[77.53449999999999,28.97434],"type":"Point"}
}