{
  "type": "Feature",
  "properties": {
    "iso:country":"IN",
    "ks:ks_name":"Kumharan Purwa",
    "ks:ks_pop":95,
    "ks:ks_type":"HABITATION",
    "name:eng_x_preferred":[
        "Kumharan Purwa"
    ],
    "wof:name":"Kumharan Purwa",
    "wof:placetype":"locality",
    "wof:population":95
},
  "geometry": {"coordinates":[81.31978700000001,27.816958],"type":"Point"}
}