{
  "type": "Feature",
  "properties": {
    "iso:country":"IN",
    "ks:ks_name":"Darura",
    "ks:ks_pop":142,
    "ks:ks_type":"VILLAGE",
    "name:eng_x_preferred":[
        "Darura"
    ],
    "wof:name":"Darura",
    "wof:placetype":"locality",
    "wof:population":142
},
  "geometry": {"coordinates":[77.320089,26.416632],"type":"Point"}
}