{
  "type": "Feature",
  "properties": {
    "iso:country":"IN",
    "ks:ks_name":"Nava Sadulka",
    "ks:ks_pop":4323,
    "ks:ks_type":"VILLAGE",
    "name:eng_x_preferred":[
        "Nava Sadulka"
    ],
    "wof:name":"Nava Sadulka",
    "wof:placetype":"locality",
    "wof:population":4323
},
  "geometry": {"coordinates":[70.826639,22.939351],"type":"Point"}
}