{
  "type": "Feature",
  "properties": {
    "iso:country":"IN",
    "ks:ks_name":"Gopi Nathpur",
    "ks:ks_pop":183,
    "ks:ks_type":"HABITATION",
    "name:eng_x_preferred":[
        "Gopi Nathpur"
    ],
    "wof:name":"Gopi Nathpur",
    "wof:placetype":"locality",
    "wof:population":183
},
  "geometry": {"coordinates":[78.726463,27.014227],"type":"Point"}
}