{
  "type": "Feature",
  "properties": {
    "iso:country":"IN",
    "ks:ks_name":"Purani Baseri Basnal",
    "ks:ks_pop":23,
    "ks:ks_type":"VILLAGE",
    "name:eng_x_preferred":[
        "Purani Baseri Basnal"
    ],
    "wof:name":"Purani Baseri Basnal",
    "wof:placetype":"locality",
    "wof:population":23
},
  "geometry": {"coordinates":[79.236052,29.758184],"type":"Point"}
}