{
  "type": "Feature",
  "properties": {
    "iso:country":"IN",
    "ks:ks_name":"Nakbar",
    "ks:ks_pop":451,
    "ks:ks_type":"VILLAGE",
    "name:eng_x_preferred":[
        "Nakbar"
    ],
    "wof:name":"Nakbar",
    "wof:placetype":"locality",
    "wof:population":451
},
  "geometry": {"coordinates":[83.690252,22.727189],"type":"Point"}
}