{
  "type": "Feature",
  "properties": {
    "iso:country":"IN",
    "ks:ks_name":"Hosabalu",
    "ks:ks_pop":210,
    "ks:ks_type":"HABITATION",
    "name:eng_x_preferred":[
        "Hosabalu"
    ],
    "wof:name":"Hosabalu",
    "wof:placetype":"locality",
    "wof:population":210
},
  "geometry": {"coordinates":[74.960932,13.724572],"type":"Point"}
}