{
  "type": "Feature",
  "properties": {
    "iso:country":"IN",
    "ks:ks_name":"Bhaji Bari",
    "ks:ks_pop":0,
    "ks:ks_type":"VILLAGE",
    "name:eng_x_preferred":[
        "Bhaji Bari"
    ],
    "wof:name":"Bhaji Bari",
    "wof:placetype":"locality",
    "wof:population":0
},
  "geometry": {"coordinates":[87.28236,23.06869],"type":"Point"}
}