{
  "type": "Feature",
  "properties": {
    "iso:country":"IN",
    "ks:ks_name":"Hullarive Kaval",
    "ks:ks_pop":10,
    "ks:ks_type":"HABITATION",
    "name:eng_x_preferred":[
        "Hullarive Kaval"
    ],
    "wof:name":"Hullarive Kaval",
    "wof:placetype":"locality",
    "wof:population":10
},
  "geometry": {"coordinates":[76.742529,13.471037],"type":"Point"}
}