{
  "type": "Feature",
  "properties": {
    "iso:country":"IN",
    "ks:ks_name":"Sagarmatha Supa",
    "ks:ks_pop":347,
    "ks:ks_type":"HABITATION",
    "name:eng_x_preferred":[
        "Sagarmatha Supa"
    ],
    "wof:name":"Sagarmatha Supa",
    "wof:placetype":"locality",
    "wof:population":347
},
  "geometry": {"coordinates":[91.40115299999999,26.735269],"type":"Point"}
}