{
  "type": "Feature",
  "properties": {
    "iso:country":"IN",
    "ks:ks_name":"Kaptanpur Pt V",
    "ks:ks_pop":1040,
    "ks:ks_type":"VILLAGE",
    "ks:ks_uagg_main":0,
    "name:eng_x_preferred":[
        "Kaptanpur Pt V"
    ],
    "wof:name":"Kaptanpur Pt V",
    "wof:placetype":"neighbourhood",
    "wof:population":1040
},
  "geometry": {"coordinates":[92.98841400000001,24.769076],"type":"Point"}
}