{
  "type": "Feature",
  "properties": {
    "iso:country":"IN",
    "ks:ks_name":"Belpada",
    "ks:ks_pop":336,
    "ks:ks_type":"HABITATION",
    "name:eng_x_preferred":[
        "Belpada"
    ],
    "wof:name":"Belpada",
    "wof:placetype":"locality",
    "wof:population":336
},
  "geometry": {"coordinates":[73.063631,20.001266],"type":"Point"}
}