{
  "type": "Feature",
  "properties": {
    "iso:country":"IN",
    "ks:ks_alt_nam":"NAWATOLI",
    "ks:ks_name":"Nawatoli",
    "ks:ks_pop":111,
    "ks:ks_type":"HABITATION",
    "name:eng_x_preferred":[
        "Nawatoli"
    ],
    "wof:name":"Nawatoli",
    "wof:placetype":"locality",
    "wof:population":111
},
  "geometry": {"coordinates":[83.90511600000001,22.644433],"type":"Point"}
}