{
  "type": "Feature",
  "properties": {
    "iso:country":"IN",
    "ks:ks_alt_nam":"Ragimakula ST Colony",
    "ks:ks_name":"Ragimakula St Colony",
    "ks:ks_pop":90,
    "ks:ks_type":"HABITATION",
    "name:eng_x_preferred":[
        "Ragimakula St Colony"
    ],
    "wof:name":"Ragimakula St Colony",
    "wof:placetype":"locality",
    "wof:population":90
},
  "geometry": {"coordinates":[79.281981,13.632425],"type":"Point"}
}