{
  "type": "Feature",
  "properties": {
    "iso:country":"IN",
    "ks:ks_name":"Yadav Gopalpura",
    "ks:ks_pop":944,
    "ks:ks_type":"HABITATION",
    "name:eng_x_preferred":[
        "Yadav Gopalpura"
    ],
    "wof:name":"Yadav Gopalpura",
    "wof:placetype":"locality",
    "wof:population":944
},
  "geometry": {"coordinates":[76.005341,26.370538],"type":"Point"}
}