{
  "type": "Feature",
  "properties": {
    "iso:country":"IN",
    "ks:ks_name":"Kamarguda",
    "ks:ks_pop":362,
    "ks:ks_type":"HABITATION",
    "name:eng_x_preferred":[
        "Kamarguda"
    ],
    "wof:name":"Kamarguda",
    "wof:placetype":"locality",
    "wof:population":362
},
  "geometry": {"coordinates":[81.57832999999999,18.020192],"type":"Point"}
}