{
  "type": "Feature",
  "properties": {
    "iso:country":"IN",
    "ks:ks_name":"Pallihakkal",
    "ks:ks_pop":705,
    "ks:ks_type":"HABITATION",
    "ks:ks_uagg_main":0,
    "name:eng_x_preferred":[
        "Pallihakkal"
    ],
    "wof:name":"Pallihakkal",
    "wof:placetype":"neighbourhood",
    "wof:population":705
},
  "geometry": {"coordinates":[74.518888,14.031704],"type":"Point"}
}