{
  "type": "Feature",
  "properties": {
    "gn:admin1_code":"39.0",
    "gn:admin2_code":"64.0",
    "gn:asciiname":"Naini",
    "gn:country_code":"IN",
    "gn:dem":1430,
    "gn:feature_class":"P",
    "gn:feature_code":"PPL",
    "gn:name":"Naini",
    "gn:population":0,
    "gn:timezone":"Asia/Kolkata",
    "iso:country":"IN",
    "name:bih_x_preferred":[
        "\u0928\u0948\u0928\u0940"
    ],
    "name:hin_x_preferred":[
        "\u0928\u0948\u0928\u0940"
    ],
    "wof:name":"Naini",
    "wof:placetype":"locality"
},
  "geometry": {"coordinates":[79.70851999999999,29.64752],"type":"Point"}
}