{
  "type": "Feature",
  "properties": {
    "iso:country":"IN",
    "ks:ks_name":"Khori Falia",
    "ks:ks_pop":168,
    "ks:ks_type":"HABITATION",
    "name:eng_x_preferred":[
        "Khori Falia"
    ],
    "wof:name":"Khori Falia",
    "wof:placetype":"locality",
    "wof:population":168
},
  "geometry": {"coordinates":[73.390333,20.282361],"type":"Point"}
}