{
  "type": "Feature",
  "properties": {
    "iso:country":"IN",
    "name:ara_x_preferred":[
        "\u0633\u064a\u0646\u062c\u0627\u0631\u0627\u062a\u0628\u0648"
    ],
    "name:ben_bn_x_preferred":[
        "\u09b8\u09bf\u0999\u09cd\u0997\u09be\u09b0\u09be\u099f\u09cb\u09aa\u09cd\u09aa\u09c1"
    ],
    "name:ben_in_x_preferred":[
        "\u09b8\u09bf\u0999\u09cd\u0997\u09be\u09b0\u09be\u099f\u09cb\u09aa\u09cd\u09aa\u09c1"
    ],
    "name:guj_x_preferred":[
        "\u0ab8\u0abf\u0a82\u0a97\u0ab0\u0aa4\u0acd\u0a9f\u0acb\u0aaa\u0ac1"
    ],
    "name:hin_x_preferred":[
        "\u0938\u093f\u0902\u0917\u0930\u094d\u091f\u094d\u091f\u094b\u092a\u094d\u092a\u0942"
    ],
    "name:kan_x_preferred":[
        "\u0cb8\u0cbf\u0c82\u0c97\u0cb0\u0c9f\u0ccd\u0c9f\u0cca\u0caa\u0ccd\u0caa\u0cc1"
    ],
    "name:mal_x_preferred":[
        "\u0d38\u0d3f\u0d02\u0d17\u0d3e\u0d30\u0d1f\u0d4d\u0d1f\u0d4b\u0d2a\u0d4d\u0d2a\u0d4d"
    ],
    "name:mar_x_preferred":[
        "\u0938\u093f\u0902\u0917\u093e\u0930\u091f\u094d\u091f\u094b\u092a\u0941"
    ],
    "name:pan_x_preferred":[
        "\u0a38\u0a3f\u0a70\u0a17\u0a30\u0a3e\u0a1f\u0a4c\u0a2a\u0a42"
    ],
    "name:tam_x_preferred":[
        "\u0b9a\u0bbf\u0b99\u0bcd\u0b95\u0bbe\u0bb0\u0ba4\u0bcd\u0ba4\u0bcb\u0baa\u0bcd\u0baa\u0bc1"
    ],
    "name:tel_x_preferred":[
        "\u0c36\u0c3f\u0c02\u0c17\u0c3e\u0c30\u0c1f\u0c4d\u0c1f\u0c4b\u0c2a\u0c4d\u0c2a\u0c41"
    ],
    "name:urd_x_preferred":[
        "\u0633\u0646\u06af\u0627\u0631\u0627\u0679\u0648\u067e\u0648"
    ],
    "qs:name":"Singarattoppu",
    "qs:name_adm0":"India",
    "qs:name_adm1":"Tamil Nadu",
    "qs:photos":86,
    "qs:photos_1k":17,
    "qs:photos_9k":1,
    "qs:photos_9r":3,
    "qs:photos_all":86,
    "qs:photos_sr":3,
    "qs:placetype":"Suburb",
    "qs:pop_sr":"0",
    "wof:name":"Singarattoppu",
    "wof:placetype":"neighbourhood"
},
  "geometry": {"coordinates":[78.698587,10.826098],"type":"Point"}
}