{
  "type": "Feature",
  "properties": {
    "iso:country":"IN",
    "qs:name":"Singarattoppu",
    "qs:name_adm0":"India",
    "qs:name_adm1":"Tamil Nadu",
    "qs:photos":86,
    "qs:photos_1k":17,
    "qs:photos_9k":1,
    "qs:photos_9r":3,
    "qs:photos_all":86,
    "qs:photos_sr":3,
    "qs:placetype":"Suburb",
    "qs:pop_sr":"0",
    "wof:name":"Singarattoppu",
    "wof:placetype":"neighbourhood"
},
  "geometry": {"coordinates":[78.698587,10.826098],"type":"Point"}
}