{
  "type": "Feature",
  "properties": {
    "iso:country":"IN",
    "ks:ks_name":"4 C",
    "ks:ks_pop":2394,
    "ks:ks_type":"VILLAGE",
    "name:eng_x_preferred":[
        "4 C"
    ],
    "wof:name":"4 C",
    "wof:placetype":"locality",
    "wof:population":2394
},
  "geometry": {"coordinates":[73.91806699999999,30.093392],"type":"Point"}
}