{
  "type": "Feature",
  "properties": {
    "gn:admin1_code":"19.0",
    "gn:admin2_code":"582.0",
    "gn:asciiname":"Chikkakarakamakalahallli",
    "gn:country_code":"IN",
    "gn:dem":864,
    "gn:feature_class":"P",
    "gn:feature_code":"PPL",
    "gn:name":"Chikkakarakam\u0101kalahallli",
    "gn:population":0,
    "gn:timezone":"Asia/Kolkata",
    "iso:country":"IN",
    "wof:name":"Chikkakarakamakalahallli",
    "wof:placetype":"locality"
},
  "geometry": {"coordinates":[78.14728000000002,13.43305],"type":"Point"}
}