{
  "type": "Feature",
  "properties": {
    "iso:country":"IN",
    "ks:ks_name":"Kumaramangalam",
    "ks:ks_pop":675,
    "ks:ks_type":"HABITATION",
    "name:eng_x_preferred":[
        "Kumaramangalam"
    ],
    "wof:name":"Kumaramangalam",
    "wof:placetype":"locality",
    "wof:population":675
},
  "geometry": {"coordinates":[79.540014,11.182212],"type":"Point"}
}