{
  "type": "Feature",
  "properties": {
    "iso:country":"IN",
    "ks:ks_name":"Bocharampatti",
    "ks:ks_pop":496,
    "ks:ks_type":"HABITATION",
    "name:eng_x_preferred":[
        "Bocharampatti"
    ],
    "wof:name":"Bocharampatti",
    "wof:placetype":"locality",
    "wof:population":496
},
  "geometry": {"coordinates":[77.869675,12.094395],"type":"Point"}
}