{
  "type": "Feature",
  "properties": {
    "iso:country":"IN",
    "ks:ks_name":"Attasahipatna",
    "ks:ks_pop":625,
    "ks:ks_type":"VILLAGE",
    "ks:ks_uagg_main":0,
    "name:eng_x_preferred":[
        "Attasahipatna"
    ],
    "wof:name":"Attasahipatna",
    "wof:placetype":"neighbourhood",
    "wof:population":625
},
  "geometry": {"coordinates":[86.072357,21.177506],"type":"Point"}
}