{
  "type": "Feature",
  "properties": {
    "gn:admin1_code":"10.0",
    "gn:admin2_code":"71.0",
    "gn:asciiname":"Shahabuddinpur Khurd",
    "gn:country_code":"IN",
    "gn:dem":308,
    "gn:feature_class":"P",
    "gn:feature_code":"PPL",
    "gn:name":"Shah\u0101budd\u012bnpur Khurd",
    "gn:population":0,
    "gn:timezone":"Asia/Kolkata",
    "iso:country":"IN",
    "ks:ks_alt_nam":"Shah\u0101budd\u012bnpur Khurd",
    "ks:ks_name":"Shahabuddinpur Khurd",
    "ks:ks_type":"VILLAGE",
    "name:eng_x_preferred":[
        "Shahabuddinpur Khurd"
    ],
    "name:eng_x_variant":[
        "Shah\u0101budd\u012bnpur Khurd"
    ],
    "wof:name":"Shahabuddinpur Khurd",
    "wof:placetype":"locality"
},
  "geometry": {"coordinates":[77.43042,30.346423],"type":"Point"}
}