{
  "type": "Feature",
  "properties": {
    "gn:admin1_code":"10.0",
    "gn:admin2_code":"71.0",
    "gn:asciiname":"Shahabuddinpur Khurd",
    "gn:country_code":"IN",
    "gn:dem":308,
    "gn:feature_class":"P",
    "gn:feature_code":"PPL",
    "gn:name":"Shah\u0101budd\u012bnpur Khurd",
    "gn:population":0,
    "gn:timezone":"Asia/Kolkata",
    "iso:country":"IN",
    "wof:name":"Shahabuddinpur Khurd",
    "wof:placetype":"locality"
},
  "geometry": {"coordinates":[77.43042,30.34642],"type":"Point"}
}