{
  "type": "Feature",
  "properties": {
    "iso:country":"IN",
    "ks:ks_name":"Sabo",
    "ks:ks_pop":562,
    "ks:ks_type":"VILLAGE",
    "ks:ks_uagg_main":0,
    "name:eng_x_preferred":[
        "Sabo"
    ],
    "wof:name":"Sabo",
    "wof:placetype":"neighbourhood",
    "wof:population":562
},
  "geometry": {"coordinates":[86.115692,20.615752],"type":"Point"}
}