{
  "type": "Feature",
  "properties": {
    "iso:country":"IN",
    "ks:ks_name":"Bandhatari",
    "ks:ks_pop":198,
    "ks:ks_type":"HABITATION",
    "name:eng_x_preferred":[
        "Bandhatari"
    ],
    "wof:name":"Bandhatari",
    "wof:placetype":"locality",
    "wof:population":198
},
  "geometry": {"coordinates":[83.165047,24.542683],"type":"Point"}
}