{
  "type": "Feature",
  "properties": {
    "iso:country":"IN",
    "ks:ks_name":"Mugilodu",
    "ks:ks_pop":37,
    "ks:ks_type":"VILLAGE",
    "name:eng_x_preferred":[
        "Mugilodu"
    ],
    "wof:name":"Mugilodu",
    "wof:placetype":"locality",
    "wof:population":37
},
  "geometry": {"coordinates":[76.46028200000001,13.699276],"type":"Point"}
}