{
  "type": "Feature",
  "properties": {
    "gn:admin1_code":"39.0",
    "gn:admin2_code":"64.0",
    "gn:asciiname":"Paloli",
    "gn:country_code":"IN",
    "gn:dem":1560,
    "gn:feature_class":"P",
    "gn:feature_code":"PPL",
    "gn:name":"Paloli",
    "gn:population":0,
    "gn:timezone":"Asia/Kolkata",
    "iso:country":"IN",
    "ks:ks_name":"Paloli",
    "ks:ks_type":"VILLAGE",
    "name:eng_x_preferred":[
        "Paloli"
    ],
    "wof:name":"Paloli",
    "wof:placetype":"locality"
},
  "geometry": {"coordinates":[79.85743600000001,29.552146],"type":"Point"}
}