{
  "type": "Feature",
  "properties": {
    "iso:country":"IN",
    "ks:ks_name":"Bodonajhori",
    "ks:ks_pop":184,
    "ks:ks_type":"VILLAGE",
    "name:eng_x_preferred":[
        "Bodonajhori"
    ],
    "wof:name":"Bodonajhori",
    "wof:placetype":"locality",
    "wof:population":184
},
  "geometry": {"coordinates":[83.458094,19.870665],"type":"Point"}
}