{
  "type": "Feature",
  "properties": {
    "iso:country":"IN",
    "ks:ks_name":"Kukrapahari",
    "ks:ks_pop":189,
    "ks:ks_type":"VILLAGE",
    "name:eng_x_preferred":[
        "Kukrapahari"
    ],
    "wof:name":"Kukrapahari",
    "wof:placetype":"locality",
    "wof:population":189
},
  "geometry": {"coordinates":[86.750927,22.508241],"type":"Point"}
}