{
  "type": "Feature",
  "properties": {
    "iso:country":"IN",
    "ks:ks_name":"Shimuldhab North",
    "ks:ks_pop":558,
    "ks:ks_type":"HABITATION",
    "name:eng_x_preferred":[
        "Shimuldhab North"
    ],
    "wof:name":"Shimuldhab North",
    "wof:placetype":"locality",
    "wof:population":558
},
  "geometry": {"coordinates":[88.119893,25.100498],"type":"Point"}
}