{
  "type": "Feature",
  "properties": {
    "gn:admin1_code":"37",
    "gn:admin2_code":"406.0",
    "gn:asciiname":"Ameri",
    "gn:country_code":"IN",
    "gn:dem":275,
    "gn:feature_class":"P",
    "gn:feature_code":"PPL",
    "gn:name":"Amer\u012b",
    "gn:population":0,
    "gn:timezone":"Asia/Kolkata",
    "iso:country":"IN",
    "ks:ks_alt_nam":"Amer\u012b",
    "ks:ks_name":"Ameri",
    "ks:ks_type":"VILLAGE",
    "ks:ks_uagg_main":0,
    "name:eng_x_preferred":[
        "Ameri"
    ],
    "name:eng_x_variant":[
        "Amer\u012b"
    ],
    "name:fas_x_preferred":[
        "\u0639\u0627\u0645\u0631\u06cc"
    ],
    "wof:name":"Ameri",
    "wof:placetype":"locality"
},
  "geometry": {"coordinates":[82.123502,22.08273],"type":"Point"}
}