{
  "type": "Feature",
  "properties": {
    "gn:admin1_code":"13.0",
    "gn:admin2_code":"598.0",
    "gn:asciiname":"Koippalli Karanma",
    "gn:country_code":"IN",
    "gn:dem":16,
    "gn:feature_class":"P",
    "gn:feature_code":"PPL",
    "gn:name":"Koippalli K\u0101r\u0101nma",
    "gn:population":0,
    "gn:timezone":"Asia/Kolkata",
    "iso:country":"IN",
    "wof:name":"Koippalli Karanma",
    "wof:placetype":"locality"
},
  "geometry": {"coordinates":[76.52388000000001,9.19429],"type":"Point"}
}