{
  "type": "Feature",
  "properties": {
    "gn:admin1_code":"31",
    "gn:admin2_code":"283.0",
    "gn:asciiname":"Sesawng",
    "gn:country_code":"IN",
    "gn:dem":826,
    "gn:feature_class":"P",
    "gn:feature_code":"PPL",
    "gn:name":"Sesawng",
    "gn:population":0,
    "gn:timezone":"Asia/Kolkata",
    "iso:country":"IN",
    "wof:name":"Sesawng",
    "wof:placetype":"locality"
},
  "geometry": {"coordinates":[92.85455,23.74569],"type":"Point"}
}