{
  "type": "Feature",
  "properties": {
    "gn:admin1_code":"38.0",
    "gn:admin2_code":"347.0",
    "gn:asciiname":"Siria",
    "gn:country_code":"IN",
    "gn:dem":437,
    "gn:feature_class":"P",
    "gn:feature_code":"PPL",
    "gn:name":"Siri\u0101",
    "gn:population":0,
    "gn:timezone":"Asia/Kolkata",
    "iso:country":"IN",
    "ks:ks_alt_nam":"Siri\u0101",
    "ks:ks_name":"Siria",
    "ks:ks_pop":346,
    "ks:ks_type":"VILLAGE",
    "ks:ks_uagg_main":0,
    "name:eng_x_preferred":[
        "Siria"
    ],
    "name:eng_x_variant":[
        "Siri\u0101"
    ],
    "name:nld_x_preferred":[
        "Siria"
    ],
    "name:vie_x_preferred":[
        "Siria"
    ],
    "wof:name":"Siria",
    "wof:placetype":"neighbourhood",
    "wof:population":346
},
  "geometry": {"coordinates":[85.176919,24.254162],"type":"Point"}
}