{
  "type": "Feature",
  "properties": {
    "iso:country":"IN",
    "ks:ks_name":"Khalchiwadi",
    "ks:ks_pop":132,
    "ks:ks_type":"HABITATION",
    "name:eng_x_preferred":[
        "Khalchiwadi"
    ],
    "wof:name":"Khalchiwadi",
    "wof:placetype":"locality",
    "wof:population":132
},
  "geometry": {"coordinates":[73.77745899999999,15.730853],"type":"Point"}
}