{
  "type": "Feature",
  "properties": {
    "iso:country":"IN",
    "ks:ks_name":"Kabaitari Pt VI",
    "ks:ks_pop":255,
    "ks:ks_type":"VILLAGE",
    "ks:ks_uagg_main":0,
    "name:eng_x_preferred":[
        "Kabaitari Pt VI"
    ],
    "wof:name":"Kabaitari Pt VI",
    "wof:placetype":"neighbourhood",
    "wof:population":255
},
  "geometry": {"coordinates":[90.580275,26.244016],"type":"Point"}
}