{
  "type": "Feature",
  "properties": {
    "iso:country":"IN",
    "ks:ks_name":"Bichhali",
    "ks:ks_pop":429,
    "ks:ks_type":"VILLAGE",
    "name:eng_x_preferred":[
        "Bichhali"
    ],
    "wof:name":"Bichhali",
    "wof:placetype":"locality",
    "wof:population":429
},
  "geometry": {"coordinates":[82.220139,23.285335],"type":"Point"}
}