{
  "type": "Feature",
  "properties": {
    "gn:admin1_code":"23",
    "gn:admin2_code":"38.0",
    "gn:asciiname":"Mahdipur",
    "gn:country_code":"IN",
    "gn:dem":245,
    "gn:feature_class":"P",
    "gn:feature_code":"PPL",
    "gn:name":"Mahdipur",
    "gn:population":0,
    "gn:timezone":"Asia/Kolkata",
    "iso:country":"IN",
    "wof:name":"Mahdipur",
    "wof:placetype":"locality"
},
  "geometry": {"coordinates":[75.55802,31.93144],"type":"Point"}
}