{
  "type": "Feature",
  "properties": {
    "iso:country":"IN",
    "ks:ks_name":"Sangsinghpura",
    "ks:ks_pop":838,
    "ks:ks_type":"VILLAGE",
    "name:eng_x_preferred":[
        "Sangsinghpura"
    ],
    "wof:name":"Sangsinghpura",
    "wof:placetype":"locality",
    "wof:population":838
},
  "geometry": {"coordinates":[72.246878,26.282836],"type":"Point"}
}