{
  "type": "Feature",
  "properties": {
    "iso:country":"IN",
    "ks:ks_alt_nam":"gangatola",
    "ks:ks_name":"Gangatola",
    "ks:ks_pop":106,
    "ks:ks_type":"HABITATION",
    "name:eng_x_preferred":[
        "Gangatola"
    ],
    "wof:name":"Gangatola",
    "wof:placetype":"locality",
    "wof:population":106
},
  "geometry": {"coordinates":[85.335808,22.65256],"type":"Point"}
}