{
  "type": "Feature",
  "properties": {
    "gn:admin1_code":"11.0",
    "gn:admin2_code":"24.0",
    "gn:asciiname":"Bind",
    "gn:country_code":"IN",
    "gn:dem":458,
    "gn:feature_class":"P",
    "gn:feature_code":"PPL",
    "gn:name":"B\u012bnd",
    "gn:population":0,
    "gn:timezone":"Asia/Kolkata",
    "iso:country":"IN",
    "name:deu_x_preferred":[
        "Bind"
    ],
    "name:kor_x_preferred":[
        "\ubc14\uc778\ub4dc"
    ],
    "name:rus_x_preferred":[
        "Bind"
    ],
    "wof:name":"Bind",
    "wof:placetype":"locality"
},
  "geometry": {"coordinates":[75.92737,32.00991],"type":"Point"}
}