{
  "type": "Feature",
  "properties": {
    "iso:country":"IN",
    "ks:ks_name":"Mahatpur",
    "ks:ks_pop":966,
    "ks:ks_type":"VILLAGE",
    "ks:ks_uagg_main":0,
    "name:eng_x_preferred":[
        "Mahatpur"
    ],
    "wof:name":"Mahatpur",
    "wof:placetype":"neighbourhood",
    "wof:population":966
},
  "geometry": {"coordinates":[88.221076,23.815619],"type":"Point"}
}