{
  "type": "Feature",
  "properties": {
    "gn:admin1_code":"11",
    "gn:admin2_code":"23.0",
    "gn:asciiname":"Toru",
    "gn:country_code":"IN",
    "gn:dem":810,
    "gn:feature_class":"P",
    "gn:feature_code":"PPL",
    "gn:name":"Toru",
    "gn:population":0,
    "gn:timezone":"Asia/Kolkata",
    "iso:country":"IN",
    "name:ceb_x_preferred":[
        "Toru"
    ],
    "name:nld_x_preferred":[
        "Toru"
    ],
    "name:swe_x_preferred":[
        "Toru"
    ],
    "wof:name":"Toru",
    "wof:placetype":"locality"
},
  "geometry": {"coordinates":[76.00424,32.62045999999999],"type":"Point"}
}