{
  "type": "Feature",
  "properties": {
    "gn:admin1_code":"24.0",
    "gn:admin2_code":"103",
    "gn:asciiname":"Tibro ki Dhani",
    "gn:country_code":"IN",
    "gn:dem":314,
    "gn:feature_class":"P",
    "gn:feature_code":"PPL",
    "gn:name":"Tibro ki Dh\u0101ni",
    "gn:population":0,
    "gn:timezone":"Asia/Kolkata",
    "iso:country":"IN",
    "name:und_x_variant":[
        "Tibro ki Dh\u0101ni",
        "Tibra ki Dh\u0101ni"
    ],
    "wof:name":"Tibro ki Dhani",
    "wof:placetype":"locality"
},
  "geometry": {"coordinates":[75.44502,28.21537],"type":"Point"}
}