{
  "type": "Feature",
  "properties": {
    "iso:country":"IN",
    "ks:ks_name":"Seal Khurd",
    "ks:ks_pop":144,
    "ks:ks_type":"VILLAGE",
    "name:eng_x_preferred":[
        "Seal Khurd"
    ],
    "wof:name":"Seal Khurd",
    "wof:placetype":"locality",
    "wof:population":144
},
  "geometry": {"coordinates":[85.46044500000001,24.130568],"type":"Point"}
}