{
  "type": "Feature",
  "properties": {
    "gn:admin1_code":"24",
    "gn:admin2_code":"102.0",
    "gn:asciiname":"Soniyasar",
    "gn:country_code":"IN",
    "gn:dem":314,
    "gn:feature_class":"P",
    "gn:feature_code":"PPL",
    "gn:name":"Soniy\u0101sar",
    "gn:population":0,
    "gn:timezone":"Asia/Kolkata",
    "iso:country":"IN",
    "ks:ks_alt_nam":"Soni\u0101sar",
    "ks:ks_name":"Soniasar",
    "ks:ks_type":"VILLAGE",
    "ks:ks_uagg_main":0,
    "name:eng_x_preferred":[
        "Soniasar"
    ],
    "name:eng_x_variant":[
        "Soni\u0101sar"
    ],
    "name:und_x_variant":[
        "Soniy\u0101sar",
        "Soni\u0101sar"
    ],
    "wof:name":"Soniasar",
    "wof:placetype":"neighbourhood"
},
  "geometry": {"coordinates":[74.022338,27.765548],"type":"Point"}
}