{
  "type": "Feature",
  "properties": {
    "iso:country":"IN",
    "ks:ks_name":"Nehulia",
    "ks:ks_pop":149,
    "ks:ks_type":"VILLAGE",
    "ks:ks_uagg_main":0,
    "name:eng_x_preferred":[
        "Nehulia"
    ],
    "wof:name":"Nehulia",
    "wof:placetype":"neighbourhood",
    "wof:population":149
},
  "geometry": {"coordinates":[86.193529,20.35272],"type":"Point"}
}