{
  "type": "Feature",
  "properties": {
    "iso:country":"IN",
    "ks:ks_name":"Anadka1",
    "ks:ks_pop":14,
    "ks:ks_type":"HABITATION",
    "name:eng_x_preferred":[
        "Anadka1"
    ],
    "wof:name":"Anadka1",
    "wof:placetype":"locality",
    "wof:population":14
},
  "geometry": {"coordinates":[75.189679,12.643647],"type":"Point"}
}