{
  "type": "Feature",
  "properties": {
    "iso:country":"IN",
    "ks:ks_name":"Moolavayal",
    "ks:ks_pop":520,
    "ks:ks_type":"HABITATION",
    "name:eng_x_preferred":[
        "Moolavayal"
    ],
    "wof:name":"Moolavayal",
    "wof:placetype":"locality",
    "wof:population":520
},
  "geometry": {"coordinates":[76.067807,11.729266],"type":"Point"}
}