{
  "type": "Feature",
  "properties": {
    "iso:country":"IN",
    "ks:ks_alt_nam":"R\u0101galobanahalli",
    "ks:ks_name":"Ragalobanahalli",
    "ks:ks_pop":39,
    "ks:ks_type":"VILLAGE",
    "name:eng_x_preferred":[
        "Ragalobanahalli"
    ],
    "name:eng_x_variant":[
        "R\u0101galobanahalli"
    ],
    "wof:name":"Ragalobanahalli",
    "wof:placetype":"locality",
    "wof:population":39
},
  "geometry": {"coordinates":[76.489841,14.366289],"type":"Point"}
}