{
  "type": "Feature",
  "properties": {
    "iso:country":"IN",
    "ks:ks_alt_nam":"BAIRAWAN",
    "ks:ks_name":"Bairawan",
    "ks:ks_pop":973,
    "ks:ks_type":"HABITATION",
    "name:eng_x_preferred":[
        "Bairawan"
    ],
    "wof:name":"Bairawan",
    "wof:placetype":"locality",
    "wof:population":973
},
  "geometry": {"coordinates":[84.19956000000001,24.68333],"type":"Point"}
}