{
  "type": "Feature",
  "properties": {
    "gn:admin1_code":"11",
    "gn:admin2_code":"27.0",
    "gn:asciiname":"Kango",
    "gn:country_code":"IN",
    "gn:dem":671,
    "gn:feature_class":"P",
    "gn:feature_code":"PPL",
    "gn:name":"K\u0101ngo",
    "gn:population":0,
    "gn:timezone":"Asia/Kolkata",
    "iso:country":"IN",
    "name:bul_x_preferred":[
        "\u041a\u0430\u043d\u0433\u043e"
    ],
    "name:ceb_x_preferred":[
        "Kango"
    ],
    "name:fra_x_preferred":[
        "Kango"
    ],
    "name:hun_x_preferred":[
        "Kango"
    ],
    "name:ita_x_preferred":[
        "Kango"
    ],
    "name:nld_x_preferred":[
        "Kango"
    ],
    "name:pol_x_preferred":[
        "Kango"
    ],
    "name:rus_x_preferred":[
        "\u041a\u0430\u043d\u0433\u043e"
    ],
    "name:spa_x_preferred":[
        "Kango"
    ],
    "name:swe_x_preferred":[
        "Kango"
    ],
    "wof:name":"Kango",
    "wof:placetype":"locality"
},
  "geometry": {"coordinates":[76.84413000000001,31.43162],"type":"Point"}
}