{
  "type": "Feature",
  "properties": {
    "iso:country":"IN",
    "ks:ks_name":"Thoppuviduthi",
    "ks:ks_pop":2307,
    "ks:ks_type":"HABITATION",
    "name:eng_x_preferred":[
        "Thoppuviduthi"
    ],
    "wof:name":"Thoppuviduthi",
    "wof:placetype":"locality",
    "wof:population":2307
},
  "geometry": {"coordinates":[79.18661899999999,10.525463],"type":"Point"}
}