{
  "type": "Feature",
  "properties": {
    "iso:country":"IN",
    "ks:ks_alt_nam":"Mandi Kabir pur Jadid",
    "ks:ks_name":"Mandi Kabir Pur Jadid",
    "ks:ks_pop":29,
    "ks:ks_type":"HABITATION",
    "name:eng_x_preferred":[
        "Mandi Kabir Pur Jadid"
    ],
    "wof:name":"Mandi Kabir Pur Jadid",
    "wof:placetype":"locality",
    "wof:population":29
},
  "geometry": {"coordinates":[75.11491700000001,31.196672],"type":"Point"}
}