{
  "type": "Feature",
  "properties": {
    "iso:country":"IN",
    "ks:ks_name":"Pandripani",
    "ks:ks_pop":673,
    "ks:ks_type":"HABITATION",
    "name:eng_x_preferred":[
        "Pandripani"
    ],
    "wof:name":"Pandripani",
    "wof:placetype":"locality",
    "wof:population":673
},
  "geometry": {"coordinates":[82.637247,22.311926],"type":"Point"}
}