{
  "type": "Feature",
  "properties": {
    "iso:country":"IN",
    "ks:ks_name":"Birik Forest",
    "ks:ks_pop":93,
    "ks:ks_type":"VILLAGE",
    "name:eng_x_preferred":[
        "Birik Forest"
    ],
    "wof:name":"Birik Forest",
    "wof:placetype":"locality",
    "wof:population":93
},
  "geometry": {"coordinates":[88.424992,26.975561],"type":"Point"}
}