{
  "type": "Feature",
  "properties": {
    "gn:admin1_code":"36",
    "gn:admin2_code":"181.0",
    "gn:asciiname":"Madrahwa",
    "gn:country_code":"IN",
    "gn:dem":127,
    "gn:feature_class":"P",
    "gn:feature_code":"PPL",
    "gn:name":"Madrahwa",
    "gn:population":0,
    "gn:timezone":"Asia/Kolkata",
    "iso:country":"IN",
    "wof:name":"Madrahwa",
    "wof:placetype":"neighbourhood"
},
  "geometry": {"coordinates":[81.88558999999999,27.737],"type":"Point"}
}