{
  "type": "Feature",
  "properties": {
    "gn:admin1_code":"25.0",
    "gn:admin2_code":"630",
    "gn:asciiname":"Adamankottai",
    "gn:country_code":"IN",
    "gn:dem":488,
    "gn:feature_class":"P",
    "gn:feature_code":"PPL",
    "gn:name":"Adamankottai",
    "gn:population":0,
    "gn:timezone":"Asia/Kolkata",
    "iso:country":"IN",
    "name:und_x_variant":[
        "Adamankotta",
        "Adamankottai"
    ],
    "wof:name":"Adamankottai",
    "wof:placetype":"locality"
},
  "geometry": {"coordinates":[78.12366,12.07422],"type":"Point"}
}