{
  "type": "Feature",
  "properties": {
    "gn:admin1_code":"12.0",
    "gn:admin2_code":"004",
    "gn:asciiname":"Ating",
    "gn:country_code":"IN",
    "gn:dem":3612,
    "gn:feature_class":"P",
    "gn:feature_code":"PPL",
    "gn:name":"Ating",
    "gn:population":0,
    "gn:timezone":"Asia/Kolkata",
    "iso:country":"IN",
    "wof:name":"Ating",
    "wof:placetype":"locality"
},
  "geometry": {"coordinates":[76.73524999999999,33.57955],"type":"Point"}
}