{
  "type": "Feature",
  "properties": {
    "gn:admin1_code":"38",
    "gn:admin2_code":"367.0",
    "gn:asciiname":"Kurdeg",
    "gn:country_code":"IN",
    "gn:dem":429,
    "gn:feature_class":"P",
    "gn:feature_code":"PPL",
    "gn:name":"Kurdeg",
    "gn:population":0,
    "gn:timezone":"Asia/Kolkata",
    "iso:country":"IN",
    "wof:name":"Kurdeg",
    "wof:placetype":"locality"
},
  "geometry": {"coordinates":[84.13103000000002,22.56725],"type":"Point"}
}