{
  "type": "Feature",
  "properties": {
    "gn:admin1_code":"11.0",
    "gn:admin2_code":"27.0",
    "gn:asciiname":"Nira",
    "gn:country_code":"IN",
    "gn:dem":1545,
    "gn:feature_class":"P",
    "gn:feature_code":"PPL",
    "gn:name":"Nira",
    "gn:population":0,
    "gn:timezone":"Asia/Kolkata",
    "iso:country":"IN",
    "name:fra_x_preferred":[
        "Nira"
    ],
    "name:ukr_x_preferred":[
        "\u041d\u0456\u0440\u0430"
    ],
    "wof:name":"Nira",
    "wof:placetype":"locality"
},
  "geometry": {"coordinates":[77.19428000000001,31.35731],"type":"Point"}
}