{
  "type": "Feature",
  "properties": {
    "gn:admin1_code":"28",
    "gn:admin2_code":"327.0",
    "gn:asciiname":"Simana Basti",
    "gn:country_code":"IN",
    "gn:dem":2140,
    "gn:feature_class":"P",
    "gn:feature_code":"PPL",
    "gn:name":"Sim\u0101na Basti",
    "gn:population":0,
    "gn:timezone":"Asia/Kolkata",
    "iso:country":"IN",
    "wof:name":"Simana Basti",
    "wof:placetype":"locality"
},
  "geometry": {"coordinates":[88.13526,26.98023],"type":"Point"}
}