{
  "type": "Feature",
  "properties": {
    "iso:country":"IN",
    "ks:ks_name":"Popatpara",
    "ks:ks_pop":101,
    "ks:ks_type":"HABITATION",
    "name:eng_x_preferred":[
        "Popatpara"
    ],
    "wof:name":"Popatpara",
    "wof:placetype":"locality",
    "wof:population":101
},
  "geometry": {"coordinates":[71.972213,23.871652],"type":"Point"}
}