{
  "type": "Feature",
  "properties": {
    "iso:country":"IN",
    "ks:ks_name":"Nankar",
    "ks:ks_pop":286,
    "ks:ks_type":"VILLAGE",
    "ks:ks_uagg_main":0,
    "name:eng_x_preferred":[
        "Nankar"
    ],
    "wof:name":"Nankar",
    "wof:placetype":"neighbourhood",
    "wof:population":286
},
  "geometry": {"coordinates":[86.53778800000001,25.368313],"type":"Point"}
}