{
  "type": "Feature",
  "properties": {
    "gn:admin1_code":"35.0",
    "gn:admin2_code":"423",
    "gn:asciiname":"Garhi Barod",
    "gn:country_code":"IN",
    "gn:dem":407,
    "gn:feature_class":"P",
    "gn:feature_code":"PPL",
    "gn:name":"Garh\u012b Barod",
    "gn:population":0,
    "gn:timezone":"Asia/Kolkata",
    "iso:country":"IN",
    "wof:name":"Garhi Barod",
    "wof:placetype":"locality"
},
  "geometry": {"coordinates":[77.81028000000001,25.34324],"type":"Point"}
}