{
  "type": "Feature",
  "properties": {
    "iso:country":"IN",
    "ks:ks_name":"Madhauwapurwa",
    "ks:ks_pop":268,
    "ks:ks_type":"HABITATION",
    "name:eng_x_preferred":[
        "Madhauwapurwa"
    ],
    "wof:name":"Madhauwapurwa",
    "wof:placetype":"locality",
    "wof:population":268
},
  "geometry": {"coordinates":[80.71305,27.691364],"type":"Point"}
}