{
  "type": "Feature",
  "properties": {
    "gn:admin1_code":"9.0",
    "gn:admin2_code":"472.0",
    "gn:asciiname":"Kathroti",
    "gn:country_code":"IN",
    "gn:dem":255,
    "gn:feature_class":"P",
    "gn:feature_code":"PPL",
    "gn:name":"K\u0101throti",
    "gn:population":0,
    "gn:timezone":"Asia/Kolkata",
    "iso:country":"IN",
    "wof:name":"Kathroti",
    "wof:placetype":"locality"
},
  "geometry": {"coordinates":[73.17152,23.89444],"type":"Point"}
}