{
  "type": "Feature",
  "properties": {
    "gn:admin1_code":"36",
    "gn:admin2_code":"145.0",
    "gn:asciiname":"Radhagarh",
    "gn:country_code":"IN",
    "gn:dem":186,
    "gn:feature_class":"P",
    "gn:feature_code":"PPL",
    "gn:name":"R\u0101dh\u0101garh",
    "gn:population":0,
    "gn:timezone":"Asia/Kolkata",
    "iso:country":"IN",
    "wof:name":"Radhagarh",
    "wof:placetype":"locality"
},
  "geometry": {"coordinates":[77.62679,27.60118],"type":"Point"}
}