{
  "type": "Feature",
  "properties": {
    "gn:admin1_code":"37",
    "gn:admin2_code":"404.0",
    "gn:asciiname":"Puta",
    "gn:country_code":"IN",
    "gn:dem":346,
    "gn:feature_class":"P",
    "gn:feature_code":"PPL",
    "gn:name":"P\u016bt\u0101",
    "gn:population":0,
    "gn:timezone":"Asia/Kolkata",
    "iso:country":"IN",
    "name:ceb_x_preferred":[
        "Puta"
    ],
    "name:por_x_preferred":[
        "Puta"
    ],
    "name:swe_x_preferred":[
        "Puta"
    ],
    "wof:name":"Puta",
    "wof:placetype":"locality"
},
  "geometry": {"coordinates":[82.38663000000003,22.32308],"type":"Point"}
}