{
  "type": "Feature",
  "properties": {
    "iso:country":"IN",
    "ks:ks_name":"Kamal Nayan Bar",
    "ks:ks_pop":603,
    "ks:ks_type":"VILLAGE",
    "ks:ks_uagg_main":0,
    "name:eng_x_preferred":[
        "Kamal Nayan Bar"
    ],
    "wof:name":"Kamal Nayan Bar",
    "wof:placetype":"neighbourhood",
    "wof:population":603
},
  "geometry": {"coordinates":[87.677393,21.989693],"type":"Point"}
}