{
  "type": "Feature",
  "properties": {
    "iso:country":"IN",
    "ks:ks_name":"Durma",
    "ks:ks_pop":126,
    "ks:ks_type":"HABITATION",
    "name:eng_x_preferred":[
        "Durma"
    ],
    "wof:name":"Durma",
    "wof:placetype":"locality",
    "wof:population":126
},
  "geometry": {"coordinates":[83.68335,20.200194],"type":"Point"}
}