{
  "type": "Feature",
  "properties": {
    "iso:country":"IN",
    "ks:ks_name":"Motibar",
    "ks:ks_pop":201,
    "ks:ks_type":"HABITATION",
    "name:eng_x_preferred":[
        "Motibar"
    ],
    "wof:name":"Motibar",
    "wof:placetype":"locality",
    "wof:population":201
},
  "geometry": {"coordinates":[74.209233,22.483012],"type":"Point"}
}