{
  "type": "Feature",
  "properties": {
    "gn:admin1_code":"11",
    "gn:admin2_code":"31.0",
    "gn:asciiname":"Khetpat",
    "gn:country_code":"IN",
    "gn:dem":1130,
    "gn:feature_class":"P",
    "gn:feature_code":"PPL",
    "gn:name":"Khetpat",
    "gn:population":0,
    "gn:timezone":"Asia/Kolkata",
    "iso:country":"IN",
    "wof:name":"Khetpat",
    "wof:placetype":"locality"
},
  "geometry": {"coordinates":[76.96871999999998,30.96109],"type":"Point"}
}