{
  "type": "Feature",
  "properties": {
    "iso:country":"IN",
    "ks:ks_name":"Nadgai Khurd",
    "ks:ks_pop":371,
    "ks:ks_type":"VILLAGE",
    "name:eng_x_preferred":[
        "Nadgai Khurd"
    ],
    "wof:name":"Nadgai Khurd",
    "wof:placetype":"locality",
    "wof:population":371
},
  "geometry": {"coordinates":[79.44435199999999,24.814403],"type":"Point"}
}