{
  "type": "Feature",
  "properties": {
    "iso:country":"IN",
    "ks:ks_name":"Kukunjadka",
    "ks:ks_pop":14,
    "ks:ks_type":"HABITATION",
    "name:eng_x_preferred":[
        "Kukunjadka"
    ],
    "wof:name":"Kukunjadka",
    "wof:placetype":"locality",
    "wof:population":14
},
  "geometry": {"coordinates":[75.61252899999999,12.618926],"type":"Point"}
}