{
  "type": "Feature",
  "properties": {
    "iso:country":"IN",
    "ks:ks_name":"Ramanagara",
    "ks:ks_pop":477,
    "ks:ks_type":"HABITATION",
    "ks:ks_uagg_main":0,
    "name:eng_x_preferred":[
        "Ramanagara"
    ],
    "wof:name":"Ramanagara",
    "wof:placetype":"locality",
    "wof:population":477
},
  "geometry": {"coordinates":[74.795767,13.041872],"type":"Point"}
}