{
  "type": "Feature",
  "properties": {
    "iso:country":"IN",
    "ks:ks_name":"Hire Kattu",
    "ks:ks_pop":36,
    "ks:ks_type":"HABITATION",
    "name:eng_x_preferred":[
        "Hire Kattu"
    ],
    "wof:name":"Hire Kattu",
    "wof:placetype":"locality",
    "wof:population":36
},
  "geometry": {"coordinates":[74.454898,14.386822],"type":"Point"}
}