{
  "type": "Feature",
  "properties": {
    "iso:country":"IN",
    "ks:ks_name":"Malaiyadipatty",
    "ks:ks_pop":360,
    "ks:ks_type":"HABITATION",
    "name:eng_x_preferred":[
        "Malaiyadipatty"
    ],
    "wof:name":"Malaiyadipatty",
    "wof:placetype":"locality",
    "wof:population":360
},
  "geometry": {"coordinates":[78.623048,10.288094],"type":"Point"}
}