{
  "type": "Feature",
  "properties": {
    "gn:country":"IN",
    "gn:fcode":"PPL",
    "gn:pop":134847,
    "iso:country":"IN",
    "name:ben_x_preferred":[
        "\u099b\u09bf\u09a8\u09cd\u09a6\u0993\u09af\u09bc\u09be\u09b0\u09be"
    ],
    "name:bpy_x_preferred":[
        "\u099b\u09bf\u09a8\u09cd\u09a6\u09f1\u09be\u09b0\u09be"
    ],
    "name:cat_x_preferred":[
        "Chhindwara"
    ],
    "name:deu_x_preferred":[
        "Chhindwara"
    ],
    "name:eng_x_preferred":[
        "Chhindwara"
    ],
    "name:fin_x_preferred":[
        "Chhindwara"
    ],
    "name:fra_x_preferred":[
        "Chhindwara"
    ],
    "name:guj_x_preferred":[
        "\u0a9b\u0abf\u0aa8\u0acd\u0aa6\u0ab5\u0abe\u0aa1\u0abe"
    ],
    "name:ita_x_preferred":[
        "Chhindwara"
    ],
    "name:jpn_x_preferred":[
        "\u30c1\u30f3\u30c9\u30ef\u30e9"
    ],
    "name:kan_x_preferred":[
        "\u0c9a\u0cbf\u0c82\u0ca6\u0ccd\u0cb5\u0cbe\u0cb0\u0cbe"
    ],
    "name:kor_x_preferred":[
        "\ud06c\ud78c\uc640\ub974"
    ],
    "name:mar_x_preferred":[
        "\u091b\u093f\u0902\u0926\u0935\u093e\u0921\u093e"
    ],
    "name:mlg_x_preferred":[
        "Chhindwara"
    ],
    "name:msa_x_preferred":[
        "Chhindwara"
    ],
    "name:new_x_preferred":[
        "\u091b\u093f\u0928\u094d\u0926\u094d\u0935\u093e\u0930\u093e"
    ],
    "name:nld_x_preferred":[
        "Chhindwara"
    ],
    "name:pam_x_preferred":[
        "Chhindwara"
    ],
    "name:por_x_preferred":[
        "Chhindwara"
    ],
    "name:rus_x_preferred":[
        "\u0427\u0445\u0438\u043d\u0434\u0432\u0430\u0440\u0430"
    ],
    "name:san_x_preferred":[
        "\u091b\u093f\u0928\u094d\u0926\u0935\u093e\u0921\u093e"
    ],
    "name:spa_x_preferred":[
        "Chhindwara"
    ],
    "name:swe_x_preferred":[
        "Chhindwara"
    ],
    "name:tam_x_preferred":[
        "\u0b9a\u0bb9\u0bbf\u0ba8\u0bcd\u0ba4\u0bc1\u0bb5\u0bbe\u0bb0\u0bbe"
    ],
    "name:tel_x_preferred":[
        "\u0c1a\u0c3f\u0c02\u0c26\u0c4d\u0c35\u0c3e\u0c30\u0c3e"
    ],
    "name:unk_x_variant":[
        "Sindwara"
    ],
    "name:urd_x_preferred":[
        "\u0686\u0646\u062f\u0648\u0627\u0691\u0627"
    ],
    "name:vie_x_preferred":[
        "Chhindwara"
    ],
    "name:zho_x_preferred":[
        "\u94a6\u5fb7\u74e6\u62c9"
    ],
    "qs:name":"Chhindwara",
    "qs:name_adm0":"India",
    "qs:name_adm1":"Madhya Pradesh",
    "qs:photos_9k":1,
    "qs:photos_9r":1,
    "qs:photos_all":3,
    "qs:photos_sr":0,
    "qs:placetype":"Town",
    "qs:pop_sr":"9",
    "wd:wordcount":4022,
    "wof:name":"Chhindwara",
    "wof:placetype":"locality",
    "wof:population":134847
},
  "geometry": {"coordinates":[78.93763,22.05795],"type":"Point"}
}