{
  "type": "Feature",
  "properties": {
    "iso:country":"IN",
    "ks:ks_name":"Mulegadde",
    "ks:ks_pop":106,
    "ks:ks_type":"HABITATION",
    "name:eng_x_preferred":[
        "Mulegadde"
    ],
    "wof:name":"Mulegadde",
    "wof:placetype":"locality",
    "wof:population":106
},
  "geometry": {"coordinates":[74.34771000000001,14.640867],"type":"Point"}
}