{
  "type": "Feature",
  "properties": {
    "iso:country":"IN",
    "ks:ks_name":"Khedi",
    "ks:ks_pop":1666,
    "ks:ks_type":"VILLAGE",
    "name:eng_x_preferred":[
        "Khedi"
    ],
    "wof:name":"Khedi",
    "wof:placetype":"locality",
    "wof:population":1666
},
  "geometry": {"coordinates":[75.019406,21.690522],"type":"Point"}
}