{
  "type": "Feature",
  "properties": {
    "iso:country":"IN",
    "ks:ks_alt_nam":"NAVIVASTI",
    "ks:ks_name":"Navivasti",
    "ks:ks_pop":173,
    "ks:ks_type":"HABITATION",
    "name:eng_x_preferred":[
        "Navivasti"
    ],
    "wof:name":"Navivasti",
    "wof:placetype":"locality",
    "wof:population":173
},
  "geometry": {"coordinates":[75.42151800000001,17.133881],"type":"Point"}
}