{
  "type": "Feature",
  "properties": {
    "iso:country":"IN",
    "ks:ks_alt_nam":"dhemari",
    "ks:ks_name":"Dhemari",
    "ks:ks_pop":38,
    "ks:ks_type":"HABITATION",
    "ks:ks_uagg_main":0,
    "name:eng_x_preferred":[
        "Dhemari"
    ],
    "wof:name":"Dhemari",
    "wof:placetype":"neighbourhood",
    "wof:population":38
},
  "geometry": {"coordinates":[78.563726,27.536347],"type":"Point"}
}