{
  "type": "Feature",
  "properties": {
    "iso:country":"IN",
    "ks:ks_name":"P. Subedar",
    "ks:ks_pop":427,
    "ks:ks_type":"HABITATION",
    "ks:ks_uagg_main":0,
    "name:eng_x_preferred":[
        "P. Subedar"
    ],
    "wof:name":"P. Subedar",
    "wof:placetype":"neighbourhood",
    "wof:population":427
},
  "geometry": {"coordinates":[81.298312,26.275142],"type":"Point"}
}