{
  "type": "Feature",
  "properties": {
    "gn:admin1_code":"13.0",
    "gn:admin2_code":"591.0",
    "gn:asciiname":"Kotancheri",
    "gn:country_code":"IN",
    "gn:dem":74,
    "gn:feature_class":"P",
    "gn:feature_code":"PPL",
    "gn:name":"Kotanch\u0113ri",
    "gn:population":0,
    "gn:timezone":"Asia/Kolkata",
    "iso:country":"IN",
    "ks:ks_name":"Kodencheri",
    "ks:ks_pop":18461,
    "ks:ks_type":"VILLAGE",
    "name:eng_x_preferred":[
        "Kodencheri"
    ],
    "name:eng_x_variant":[
        "Kotancheri"
    ],
    "wof:name":"Kodencheri",
    "wof:placetype":"locality",
    "wof:population":18461
},
  "geometry": {"coordinates":[76.001964,11.429243],"type":"Point"}
}