{
  "type": "Feature",
  "properties": {
    "iso:country":"IN",
    "ks:ks_name":"Sarki Para",
    "ks:ks_pop":847,
    "ks:ks_type":"HABITATION",
    "name:eng_x_preferred":[
        "Sarki Para"
    ],
    "wof:name":"Sarki Para",
    "wof:placetype":"locality",
    "wof:population":847
},
  "geometry": {"coordinates":[92.050757,24.119239],"type":"Point"}
}