{
  "type": "Feature",
  "properties": {
    "gn:admin1_code":"24.0",
    "gn:admin2_code":"114",
    "gn:asciiname":"Teliwara",
    "gn:country_code":"IN",
    "gn:dem":251,
    "gn:feature_class":"P",
    "gn:feature_code":"PPL",
    "gn:name":"Teliw\u0101ra",
    "gn:population":0,
    "gn:timezone":"Asia/Kolkata",
    "iso:country":"IN",
    "ks:ks_name":"Teliwara",
    "ks:ks_pop":889,
    "ks:ks_type":"HABITATION",
    "name:eng_x_preferred":[
        "Teliwara"
    ],
    "wof:name":"Teliwara",
    "wof:placetype":"locality",
    "wof:population":889
},
  "geometry": {"coordinates":[71.86179199999999,26.710489],"type":"Point"}
}