{
  "type": "Feature",
  "properties": {
    "gn:admin1_code":"24.0",
    "gn:admin2_code":"114",
    "gn:asciiname":"Teliwara",
    "gn:country_code":"IN",
    "gn:dem":251,
    "gn:feature_class":"P",
    "gn:feature_code":"PPL",
    "gn:name":"Teliw\u0101ra",
    "gn:population":0,
    "gn:timezone":"Asia/Kolkata",
    "iso:country":"IN",
    "wof:name":"Teliwara",
    "wof:placetype":"locality"
},
  "geometry": {"coordinates":[71.86209000000002,26.71047],"type":"Point"}
}