{
  "type": "Feature",
  "properties": {
    "iso:country":"IN",
    "ks:ks_alt_nam":"Pallakollai vattam",
    "ks:ks_name":"Pallakollai Vattam",
    "ks:ks_pop":130,
    "ks:ks_type":"HABITATION",
    "ks:ks_uagg_main":0,
    "name:eng_x_preferred":[
        "Pallakollai Vattam"
    ],
    "wof:name":"Pallakollai Vattam",
    "wof:placetype":"neighbourhood",
    "wof:population":130
},
  "geometry": {"coordinates":[78.584926,12.710385],"type":"Point"}
}