{
  "type": "Feature",
  "properties": {
    "gn:admin1_code":"11.0",
    "gn:admin2_code":"26.0",
    "gn:asciiname":"Dim",
    "gn:country_code":"IN",
    "gn:dem":2080,
    "gn:feature_class":"P",
    "gn:feature_code":"PPL",
    "gn:name":"D\u012bm",
    "gn:population":0,
    "gn:timezone":"Asia/Kolkata",
    "iso:country":"IN",
    "name:bos_x_preferred":[
        "Dim"
    ],
    "name:ceb_x_preferred":[
        "Dim"
    ],
    "name:fra_x_preferred":[
        "Dim"
    ],
    "name:swe_x_preferred":[
        "Dim"
    ],
    "wof:name":"Dim",
    "wof:placetype":"locality"
},
  "geometry": {"coordinates":[77.56881,31.52005],"type":"Point"}
}