{
  "type": "Feature",
  "properties": {
    "gn:admin1_code":"36",
    "gn:admin2_code":"177.0",
    "gn:asciiname":"Bedauli",
    "gn:country_code":"IN",
    "gn:dem":104,
    "gn:feature_class":"P",
    "gn:feature_code":"PPL",
    "gn:name":"Bedauli",
    "gn:population":0,
    "gn:timezone":"Asia/Kolkata",
    "iso:country":"IN",
    "name:ceb_x_preferred":[
        "Bedauli"
    ],
    "name:msa_x_preferred":[
        "Bedauli"
    ],
    "name:pol_x_preferred":[
        "Bedauli"
    ],
    "wof:name":"Bedauli",
    "wof:placetype":"locality"
},
  "geometry": {"coordinates":[82.15038,26.57229],"type":"Point"}
}