{
  "type": "Feature",
  "properties": {
    "iso:country":"IN",
    "ks:ks_name":"Dhansol",
    "ks:ks_pop":284,
    "ks:ks_type":"VILLAGE",
    "name:eng_x_preferred":[
        "Dhansol"
    ],
    "wof:name":"Dhansol",
    "wof:placetype":"locality",
    "wof:population":284
},
  "geometry": {"coordinates":[87.053383,21.726893],"type":"Point"}
}