{
  "type": "Feature",
  "properties": {
    "gn:admin1_code":"11",
    "gn:admin2_code":"26.0",
    "gn:asciiname":"Shoja",
    "gn:country_code":"IN",
    "gn:dem":2717,
    "gn:feature_class":"P",
    "gn:feature_code":"PPL",
    "gn:name":"Shoja",
    "gn:population":0,
    "gn:timezone":"Asia/Kolkata",
    "iso:country":"IN",
    "wof:name":"Shoja",
    "wof:placetype":"locality"
},
  "geometry": {"coordinates":[77.37532,31.55895],"type":"Point"}
}