{
  "type": "Feature",
  "properties": {
    "iso:country":"IN",
    "ks:ks_name":"Borvita",
    "ks:ks_pop":266,
    "ks:ks_type":"HABITATION",
    "name:eng_x_preferred":[
        "Borvita"
    ],
    "wof:name":"Borvita",
    "wof:placetype":"locality",
    "wof:population":266
},
  "geometry": {"coordinates":[90.04328099999999,25.995142],"type":"Point"}
}