{
  "type": "Feature",
  "properties": {
    "iso:country":"IN",
    "ks:ks_name":"Mohnatanr",
    "ks:ks_pop":164,
    "ks:ks_type":"VILLAGE",
    "name:eng_x_preferred":[
        "Mohnatanr"
    ],
    "wof:name":"Mohnatanr",
    "wof:placetype":"locality",
    "wof:population":164
},
  "geometry": {"coordinates":[86.66187600000001,24.157883],"type":"Point"}
}