{
  "type": "Feature",
  "properties": {
    "iso:country":"IN",
    "ks:ks_name":"Kallikadu",
    "ks:ks_pop":167,
    "ks:ks_type":"HABITATION",
    "name:eng_x_preferred":[
        "Kallikadu"
    ],
    "wof:name":"Kallikadu",
    "wof:placetype":"locality",
    "wof:population":167
},
  "geometry": {"coordinates":[78.47484,10.676198],"type":"Point"}
}