{
  "type": "Feature",
  "properties": {
    "iso:country":"IN",
    "ks:ks_name":"Phulbaria",
    "ks:ks_pop":112,
    "ks:ks_type":"HABITATION",
    "name:eng_x_preferred":[
        "Phulbaria"
    ],
    "wof:name":"Phulbaria",
    "wof:placetype":"locality",
    "wof:population":112
},
  "geometry": {"coordinates":[87.425974,24.756419],"type":"Point"}
}