{
  "type": "Feature",
  "properties": {
    "iso:country":"IN",
    "ks:ks_name":"Shetpalle",
    "ks:ks_pop":962,
    "ks:ks_type":"VILLAGE",
    "name:eng_x_preferred":[
        "Shetpalle"
    ],
    "wof:name":"Shetpalle",
    "wof:placetype":"locality",
    "wof:population":962
},
  "geometry": {"coordinates":[78.67568900000001,19.199605],"type":"Point"}
}