{
  "type": "Feature",
  "properties": {
    "gn:admin1_code":"19.0",
    "gn:admin2_code":"566.0",
    "gn:asciiname":"Gollarahalli",
    "gn:country_code":"IN",
    "gn:dem":698,
    "gn:feature_class":"P",
    "gn:feature_code":"PPL",
    "gn:name":"Gollarahalli",
    "gn:population":0,
    "gn:timezone":"Asia/Kolkata",
    "iso:country":"IN",
    "wof:name":"Gollarahalli",
    "wof:placetype":"locality"
},
  "geometry": {"coordinates":[76.41545000000001,13.69517],"type":"Point"}
}