{
  "type": "Feature",
  "properties": {
    "gn:admin1_code":"19.0",
    "gn:admin2_code":"572",
    "gn:asciiname":"Cantonment",
    "gn:country_code":"IN",
    "gn:dem":929,
    "gn:feature_class":"P",
    "gn:feature_code":"PPL",
    "gn:name":"Cantonment",
    "gn:population":0,
    "gn:timezone":"Asia/Kolkata",
    "iso:country":"IN",
    "wof:name":"Cantonment",
    "wof:placetype":"locality"
},
  "geometry": {"coordinates":[77.59839000000002,12.99435],"type":"Point"}
}