{
  "type": "Feature",
  "properties": {
    "gn:admin1_code":"19.0",
    "gn:admin2_code":"572",
    "gn:asciiname":"Cantonment",
    "gn:country_code":"IN",
    "gn:dem":929,
    "gn:feature_class":"P",
    "gn:feature_code":"PPL",
    "gn:name":"Cantonment",
    "gn:population":0,
    "gn:timezone":"Asia/Kolkata",
    "iso:country":"IN",
    "name:ben_x_preferred":[
        "\u09b8\u09c7\u09a8\u09be\u09a8\u09bf\u09ac\u09be\u09b8"
    ],
    "name:fra_x_preferred":[
        "Cantonment"
    ],
    "name:hin_x_preferred":[
        "\u091b\u093e\u0935\u0928\u0940"
    ],
    "name:ind_x_preferred":[
        "Kantonmen"
    ],
    "name:ita_x_preferred":[
        "Accantonamento"
    ],
    "name:por_x_preferred":[
        "Acantonamento"
    ],
    "name:rus_x_preferred":[
        "\u041a\u0430\u043d\u0442\u043e\u043d\u043c\u0435\u043d\u0442"
    ],
    "name:spa_x_preferred":[
        "Acantonamiento"
    ],
    "name:urd_x_preferred":[
        "\u0686\u06be\u0627\u0624\u0646\u06cc"
    ],
    "wof:name":"Cantonment",
    "wof:placetype":"locality"
},
  "geometry": {"coordinates":[77.59839000000002,12.99435],"type":"Point"}
}