{
  "type": "Feature",
  "properties": {
    "gn:admin1_code":"37.0",
    "gn:admin2_code":"416.0",
    "gn:asciiname":"Nagaram",
    "gn:country_code":"IN",
    "gn:dem":273,
    "gn:feature_class":"P",
    "gn:feature_code":"PPL",
    "gn:name":"Nag\u0101ram",
    "gn:population":0,
    "gn:timezone":"Asia/Kolkata",
    "iso:country":"IN",
    "ks:ks_alt_nam":"Nag\u0101ram",
    "ks:ks_name":"Nagaram",
    "ks:ks_pop":533,
    "ks:ks_type":"VILLAGE",
    "name:eng_x_preferred":[
        "Nagaram"
    ],
    "name:eng_x_variant":[
        "Nag\u0101ram"
    ],
    "name:vie_x_preferred":[
        "Nagaram"
    ],
    "wof:name":"Nagaram",
    "wof:placetype":"locality",
    "wof:population":533
},
  "geometry": {"coordinates":[81.286129,18.360861],"type":"Point"}
}