{
  "type": "Feature",
  "properties": {
    "gn:admin1_code":"16",
    "gn:admin2_code":"504.0",
    "gn:asciiname":"Arvi",
    "gn:country_code":"IN",
    "gn:dem":268,
    "gn:feature_class":"P",
    "gn:feature_code":"PPL",
    "gn:name":"\u0100rv\u012b",
    "gn:population":0,
    "gn:timezone":"Asia/Kolkata",
    "iso:country":"IN",
    "name:ceb_x_preferred":[
        "Arvi"
    ],
    "name:swe_x_preferred":[
        "Arvi"
    ],
    "wof:name":"Arvi",
    "wof:placetype":"locality"
},
  "geometry": {"coordinates":[79.14058,20.63453],"type":"Point"}
}