{
  "type": "Feature",
  "properties": {
    "iso:country":"IN",
    "ks:ks_name":"Chiteibadi",
    "ks:ks_pop":71,
    "ks:ks_type":"VILLAGE",
    "ks:ks_uagg_main":0,
    "name:eng_x_preferred":[
        "Chiteibadi"
    ],
    "wof:name":"Chiteibadi",
    "wof:placetype":"neighbourhood",
    "wof:population":71
},
  "geometry": {"coordinates":[86.15559500000001,22.280802],"type":"Point"}
}