{
  "type": "Feature",
  "properties": {
    "gn:admin1_code":"36",
    "gn:admin2_code":"176.0",
    "gn:asciiname":"Beniganj",
    "gn:country_code":"IN",
    "gn:dem":117,
    "gn:feature_class":"P",
    "gn:feature_code":"PPL",
    "gn:name":"Beniganj",
    "gn:population":0,
    "gn:timezone":"Asia/Kolkata",
    "iso:country":"IN",
    "name:bpy_x_preferred":[
        "\u09ac\u09c7\u09a8\u09bf\u0997\u099e\u09cd\u099c"
    ],
    "name:ceb_x_preferred":[
        "Ben\u012bganj"
    ],
    "name:ita_x_preferred":[
        "Beniganj"
    ],
    "name:mlg_x_preferred":[
        "Beniganj"
    ],
    "name:msa_x_preferred":[
        "Beniganj"
    ],
    "name:new_x_preferred":[
        "\u092c\u0947\u0928\u0940\u0917\u091e\u094d\u091c"
    ],
    "name:nld_x_preferred":[
        "Beniganj"
    ],
    "name:pol_x_preferred":[
        "Beniganj"
    ],
    "name:por_x_preferred":[
        "Beniganj"
    ],
    "name:swe_x_preferred":[
        "Ben\u012bganj"
    ],
    "name:urd_x_preferred":[
        "\u0628\u06cc\u0646\u06cc \u06af\u0646\u062c"
    ],
    "name:vie_x_preferred":[
        "Beniganj"
    ],
    "name:zho_x_preferred":[
        "\u8d1d\u5c3c\u7518\u6770"
    ],
    "wof:name":"Beniganj",
    "wof:placetype":"locality"
},
  "geometry": {"coordinates":[81.22674000000001,26.66092],"type":"Point"}
}