{
  "type": "Feature",
  "properties": {
    "iso:country":"IN",
    "ks:ks_alt_nam":"BIRHOREPARA",
    "ks:ks_name":"Birhorepara",
    "ks:ks_pop":167,
    "ks:ks_type":"HABITATION",
    "name:eng_x_preferred":[
        "Birhorepara"
    ],
    "wof:name":"Birhorepara",
    "wof:placetype":"locality",
    "wof:population":167
},
  "geometry": {"coordinates":[83.689003,22.419813],"type":"Point"}
}