{
  "type": "Feature",
  "properties": {
    "gn:admin1_code":"36.0",
    "gn:admin2_code":"135.0",
    "gn:asciiname":"Nagra",
    "gn:country_code":"IN",
    "gn:dem":192,
    "gn:feature_class":"P",
    "gn:feature_code":"PPL",
    "gn:name":"Nagra",
    "gn:population":0,
    "gn:timezone":"Asia/Kolkata",
    "iso:country":"IN",
    "name:cat_x_preferred":[
        "Nagra"
    ],
    "name:fin_x_preferred":[
        "Nagra"
    ],
    "name:fra_x_preferred":[
        "Nagra"
    ],
    "name:ina_x_preferred":[
        "Nagra"
    ],
    "name:ita_x_preferred":[
        "Nagra"
    ],
    "name:pol_x_preferred":[
        "Nagra"
    ],
    "name:rus_x_preferred":[
        "Nagra"
    ],
    "name:spa_x_preferred":[
        "Nagra"
    ],
    "name:und_x_variant":[
        "Dev\u012bpura"
    ],
    "wof:name":"Nagra",
    "wof:placetype":"locality"
},
  "geometry": {"coordinates":[78.87215999999999,28.61887],"type":"Point"}
}