{
  "type": "Feature",
  "properties": {
    "iso:country":"IN",
    "ks:ks_name":"Chakdaha",
    "ks:ks_pop":32,
    "ks:ks_type":"VILLAGE",
    "name:eng_x_preferred":[
        "Chakdaha"
    ],
    "wof:name":"Chakdaha",
    "wof:placetype":"locality",
    "wof:population":32
},
  "geometry": {"coordinates":[88.269057,25.296895],"type":"Point"}
}