{
  "type": "Feature",
  "properties": {
    "iso:country":"IN",
    "ks:ks_name":"Dharampura",
    "ks:ks_pop":388,
    "ks:ks_type":"VILLAGE",
    "name:eng_x_preferred":[
        "Dharampura"
    ],
    "wof:name":"Dharampura",
    "wof:placetype":"locality",
    "wof:population":388
},
  "geometry": {"coordinates":[76.61272099999999,25.461055],"type":"Point"}
}