{
  "type": "Feature",
  "properties": {
    "gn:admin1_code":"36",
    "gn:admin2_code":"191.0",
    "gn:asciiname":"Umri",
    "gn:country_code":"IN",
    "gn:dem":81,
    "gn:feature_class":"P",
    "gn:feature_code":"PPL",
    "gn:name":"Umri",
    "gn:population":0,
    "gn:timezone":"Asia/Kolkata",
    "iso:country":"IN",
    "ks:ks_name":"Umari",
    "ks:ks_pop":300,
    "ks:ks_type":"VILLAGE",
    "ks:ks_uagg_main":0,
    "name:ceb_x_preferred":[
        "Umri"
    ],
    "name:eng_x_preferred":[
        "Umari"
    ],
    "name:pol_x_preferred":[
        "Umri"
    ],
    "name:swe_x_preferred":[
        "Umri"
    ],
    "wof:name":"Umari",
    "wof:placetype":"neighbourhood",
    "wof:population":300
},
  "geometry": {"coordinates":[83.17108,25.703676],"type":"Point"}
}