{
  "type": "Feature",
  "properties": {
    "iso:country":"IN",
    "ks:ks_name":"Vannapatty",
    "ks:ks_pop":60,
    "ks:ks_type":"HABITATION",
    "name:eng_x_preferred":[
        "Vannapatty"
    ],
    "wof:name":"Vannapatty",
    "wof:placetype":"locality",
    "wof:population":60
},
  "geometry": {"coordinates":[77.78841,10.459883],"type":"Point"}
}