{
  "type": "Feature",
  "properties": {
    "iso:country":"IN",
    "ks:ks_name":"Kummavu",
    "ks:ks_pop":32,
    "ks:ks_type":"HABITATION",
    "name:eng_x_preferred":[
        "Kummavu"
    ],
    "wof:name":"Kummavu",
    "wof:placetype":"locality",
    "wof:population":32
},
  "geometry": {"coordinates":[74.506795,14.211956],"type":"Point"}
}