{
  "type": "Feature",
  "properties": {
    "gn:admin1_code":"35.0",
    "gn:admin2_code":"427.0",
    "gn:asciiname":"Jamanpani",
    "gn:country_code":"IN",
    "gn:dem":478,
    "gn:feature_class":"P",
    "gn:feature_code":"PPL",
    "gn:name":"J\u0101manp\u0101ni",
    "gn:population":0,
    "gn:timezone":"Asia/Kolkata",
    "iso:country":"IN",
    "ks:ks_name":"Jamunpani",
    "ks:ks_pop":266,
    "ks:ks_type":"VILLAGE",
    "name:eng_x_preferred":[
        "Jamunpani"
    ],
    "name:eng_x_variant":[
        "Jamanpani"
    ],
    "wof:name":"Jamunpani",
    "wof:placetype":"locality",
    "wof:population":266
},
  "geometry": {"coordinates":[78.906819,23.406551],"type":"Point"}
}