{
  "type": "Feature",
  "properties": {
    "iso:country":"IN",
    "ks:ks_name":"Kinjalghar",
    "ks:ks_pop":136,
    "ks:ks_type":"VILLAGE",
    "name:eng_x_preferred":[
        "Kinjalghar"
    ],
    "wof:name":"Kinjalghar",
    "wof:placetype":"locality",
    "wof:population":136
},
  "geometry": {"coordinates":[73.160455,18.034474],"type":"Point"}
}