{
  "type": "Feature",
  "properties": {
    "iso:country":"IN",
    "ks:ks_name":"Nagaitha",
    "ks:ks_type":"VILLAGE",
    "name:eng_x_preferred":[
        "Nagaitha"
    ],
    "wof:name":"Nagaitha",
    "wof:placetype":"locality"
},
  "geometry": {"coordinates":[83.62168800000001,25.322299],"type":"Point"}
}