{
  "type": "Feature",
  "properties": {
    "gn:admin1_code":"35",
    "gn:admin2_code":"456.0",
    "gn:asciiname":"Kothar",
    "gn:country_code":"IN",
    "gn:dem":390,
    "gn:feature_class":"P",
    "gn:feature_code":"PPL",
    "gn:name":"Koth\u0101r",
    "gn:population":0,
    "gn:timezone":"Asia/Kolkata",
    "iso:country":"IN",
    "ks:ks_alt_nam":"Koth\u0101r",
    "ks:ks_name":"Kothar",
    "ks:ks_pop":81,
    "ks:ks_type":"VILLAGE",
    "name:eng_x_preferred":[
        "Kothar"
    ],
    "name:eng_x_variant":[
        "Koth\u0101r"
    ],
    "name:snd_x_preferred":[
        "\u0622\u0628 \u06aa\u0648\u062b\u0631"
    ],
    "wof:name":"Kothar",
    "wof:placetype":"locality",
    "wof:population":81
},
  "geometry": {"coordinates":[79.423338,21.695492],"type":"Point"}
}