{
  "type": "Feature",
  "properties": {
    "gn:admin1_code":"35",
    "gn:admin2_code":"456.0",
    "gn:asciiname":"Kothar",
    "gn:country_code":"IN",
    "gn:dem":390,
    "gn:feature_class":"P",
    "gn:feature_code":"PPL",
    "gn:name":"Koth\u0101r",
    "gn:population":0,
    "gn:timezone":"Asia/Kolkata",
    "iso:country":"IN",
    "name:snd_x_preferred":[
        "\u0622\u0628 \u06aa\u0648\u062b\u0631"
    ],
    "wof:name":"Kothar",
    "wof:placetype":"locality"
},
  "geometry": {"coordinates":[79.42355000000001,21.69298],"type":"Point"}
}