{
  "type": "Feature",
  "properties": {
    "iso:country":"IN",
    "ks:ks_alt_nam":"Bisr\u0101mpur",
    "ks:ks_name":"Bisrampur",
    "ks:ks_pop":156,
    "ks:ks_type":"VILLAGE",
    "name:eng_x_preferred":[
        "Bisrampur"
    ],
    "name:eng_x_variant":[
        "Bisr\u0101mpur"
    ],
    "wof:name":"Bisrampur",
    "wof:placetype":"locality",
    "wof:population":156
},
  "geometry": {"coordinates":[84.55180900000001,23.80581],"type":"Point"}
}