{
  "type": "Feature",
  "properties": {
    "gn:admin1_code":"2",
    "gn:admin2_code":"545.0",
    "gn:asciiname":"Chinnarugandi",
    "gn:country_code":"IN",
    "gn:dem":130,
    "gn:feature_class":"P",
    "gn:feature_code":"PPL",
    "gn:name":"Chinn\u0101rugandi",
    "gn:population":0,
    "gn:timezone":"Asia/Kolkata",
    "iso:country":"IN",
    "ks:ks_name":"Chinnarigandi",
    "ks:ks_pop":270,
    "ks:ks_type":"HABITATION",
    "name:eng_x_preferred":[
        "Chinnarigandi"
    ],
    "name:eng_x_variant":[
        "Chinnarugandi"
    ],
    "wof:name":"Chinnarigandi",
    "wof:placetype":"locality",
    "wof:population":270
},
  "geometry": {"coordinates":[81.72298600000001,17.27977],"type":"Point"}
}