{
  "type": "Feature",
  "properties": {
    "iso:country":"IN",
    "ks:ks_alt_nam":"Gobard\u0101ha",
    "ks:ks_name":"Gobardaha",
    "ks:ks_pop":73,
    "ks:ks_type":"VILLAGE",
    "name:eng_x_preferred":[
        "Gobardaha"
    ],
    "name:eng_x_variant":[
        "Gobard\u0101ha"
    ],
    "wof:name":"Gobardaha",
    "wof:placetype":"locality",
    "wof:population":73
},
  "geometry": {"coordinates":[86.488474,24.395142],"type":"Point"}
}