{
  "type": "Feature",
  "properties": {
    "iso:country":"IN",
    "ks:ks_alt_nam":"51 GB",
    "ks:ks_name":"51 Gb",
    "ks:ks_pop":117,
    "ks:ks_type":"HABITATION",
    "name:eng_x_preferred":[
        "51 Gb"
    ],
    "wof:name":"51 Gb",
    "wof:placetype":"locality",
    "wof:population":117
},
  "geometry": {"coordinates":[73.450278,29.159444],"type":"Point"}
}