{
  "type": "Feature",
  "properties": {
    "iso:country":"IN",
    "ks:ks_name":"Punalwadi",
    "ks:ks_pop":145,
    "ks:ks_type":"HABITATION",
    "name:eng_x_preferred":[
        "Punalwadi"
    ],
    "wof:name":"Punalwadi",
    "wof:placetype":"locality",
    "wof:population":145
},
  "geometry": {"coordinates":[73.816182,16.282616],"type":"Point"}
}