{
  "type": "Feature",
  "properties": {
    "gn:admin1_code":"36",
    "gn:admin2_code":"145.0",
    "gn:asciiname":"Mugarra",
    "gn:country_code":"IN",
    "gn:dem":189,
    "gn:feature_class":"P",
    "gn:feature_code":"PPL",
    "gn:name":"Mugarra",
    "gn:population":0,
    "gn:timezone":"Asia/Kolkata",
    "iso:country":"IN",
    "name:bre_x_preferred":[
        "Mugarra"
    ],
    "name:eus_x_preferred":[
        "Mugarra"
    ],
    "name:fra_x_preferred":[
        "Mugarra"
    ],
    "name:nno_x_preferred":[
        "Mugarra"
    ],
    "name:spa_x_preferred":[
        "Mugarra"
    ],
    "name:und_x_variant":[
        "Maghora"
    ],
    "name:zho_x_preferred":[
        "\u7a46\u52a0\u62c9\u5cf0"
    ],
    "wof:name":"Mugarra",
    "wof:placetype":"locality"
},
  "geometry": {"coordinates":[77.56057,27.3585],"type":"Point"}
}