{
  "type": "Feature",
  "properties": {
    "iso:country":"IN",
    "ks:ks_name":"Taldihi",
    "ks:ks_pop":847,
    "ks:ks_type":"VILLAGE",
    "name:eng_x_preferred":[
        "Taldihi"
    ],
    "wof:name":"Taldihi",
    "wof:placetype":"locality",
    "wof:population":847
},
  "geometry": {"coordinates":[85.12973100000001,21.916413],"type":"Point"}
}