{
  "type": "Feature",
  "properties": {
    "iso:country":"IN",
    "ks:ks_name":"Ghagarpur",
    "ks:ks_pop":1247,
    "ks:ks_type":"VILLAGE",
    "name:eng_x_preferred":[
        "Ghagarpur"
    ],
    "wof:name":"Ghagarpur",
    "wof:placetype":"locality",
    "wof:population":1247
},
  "geometry": {"coordinates":[87.858062,22.712884],"type":"Point"}
}