{
  "type": "Feature",
  "properties": {
    "iso:country":"IN",
    "ks:ks_name":"Dhamnagarpada",
    "ks:ks_pop":221,
    "ks:ks_type":"VILLAGE",
    "name:eng_x_preferred":[
        "Dhamnagarpada"
    ],
    "wof:name":"Dhamnagarpada",
    "wof:placetype":"locality",
    "wof:population":221
},
  "geometry": {"coordinates":[86.415218,21.24539],"type":"Point"}
}