{
  "type": "Feature",
  "properties": {
    "gn:admin1_code":"36.0",
    "gn:admin2_code":"189.0",
    "gn:asciiname":"Kurmi",
    "gn:country_code":"IN",
    "gn:dem":80,
    "gn:feature_class":"P",
    "gn:feature_code":"PPL",
    "gn:name":"Kurmi",
    "gn:population":0,
    "gn:timezone":"Asia/Kolkata",
    "iso:country":"IN",
    "name:ara_x_preferred":[
        "\u0643\u0648\u0631\u0645\u064a"
    ],
    "name:hau_x_preferred":[
        "Kurmi"
    ],
    "name:ita_x_preferred":[
        "Kurmi"
    ],
    "name:spa_x_preferred":[
        "Kurmi"
    ],
    "name:swe_x_preferred":[
        "Kurmi"
    ],
    "name:tam_x_preferred":[
        "\u0b95\u0bc1\u0bb0\u0bcd\u0bae\u0bbf \u0bae\u0b95\u0bcd\u0b95\u0bb3\u0bcd"
    ],
    "wof:name":"Kurmi",
    "wof:placetype":"locality"
},
  "geometry": {"coordinates":[84.01246999999999,26.70184],"type":"Point"}
}