{
  "type": "Feature",
  "properties": {
    "iso:country":"IN",
    "ks:ks_name":"Enthem Naga Pather",
    "ks:ks_pop":917,
    "ks:ks_type":"VILLAGE",
    "name:eng_x_preferred":[
        "Enthem Naga Pather"
    ],
    "wof:name":"Enthem Naga Pather",
    "wof:placetype":"locality",
    "wof:population":917
},
  "geometry": {"coordinates":[95.77157699999999,27.387557],"type":"Point"}
}