{
  "type": "Feature",
  "properties": {
    "gn:admin1_code":"36",
    "gn:admin2_code":"147.0",
    "gn:asciiname":"Gadokhar",
    "gn:country_code":"IN",
    "gn:dem":160,
    "gn:feature_class":"P",
    "gn:feature_code":"PPL",
    "gn:name":"Gadokhar",
    "gn:population":0,
    "gn:timezone":"Asia/Kolkata",
    "iso:country":"IN",
    "ks:ks_name":"Gadhakhar",
    "ks:ks_pop":2701,
    "ks:ks_type":"HABITATION",
    "ks:ks_uagg_main":0,
    "name:eng_x_preferred":[
        "Gadhakhar"
    ],
    "wof:name":"Gadhakhar",
    "wof:placetype":"neighbourhood",
    "wof:population":2701
},
  "geometry": {"coordinates":[78.76692300000001,26.945316],"type":"Point"}
}