{
  "type": "Feature",
  "properties": {
    "iso:country":"IN",
    "ks:ks_name":"Sandiyur Attayampatti",
    "ks:ks_pop":3625,
    "ks:ks_type":"VILLAGE",
    "ks:ks_uagg_main":0,
    "name:eng_x_preferred":[
        "Sandiyur Attayampatti"
    ],
    "wof:name":"Sandiyur Attayampatti",
    "wof:placetype":"locality",
    "wof:population":3625
},
  "geometry": {"coordinates":[78.146193,11.566498],"type":"Point"}
}