{
  "type": "Feature",
  "properties": {
    "gn:admin1_code":"40",
    "gn:admin2_code":"533.0",
    "gn:asciiname":"Mahbubpur",
    "gn:country_code":"IN",
    "gn:dem":444,
    "gn:feature_class":"P",
    "gn:feature_code":"PPL",
    "gn:name":"Mahb\u016bbpur",
    "gn:population":0,
    "gn:timezone":"Asia/Kolkata",
    "iso:country":"IN",
    "wof:name":"Mahbubpur",
    "wof:placetype":"locality"
},
  "geometry": {"coordinates":[77.57330999999998,18.33154],"type":"Point"}
}