{
  "type": "Feature",
  "properties": {
    "iso:country":"IN",
    "ks:ks_name":"Chafavade",
    "ks:ks_pop":1011,
    "ks:ks_type":"VILLAGE",
    "name:eng_x_preferred":[
        "Chafavade"
    ],
    "wof:name":"Chafavade",
    "wof:placetype":"locality",
    "wof:population":1011
},
  "geometry": {"coordinates":[74.22990299999999,16.06029],"type":"Point"}
}