{
  "type": "Feature",
  "properties": {
    "iso:country":"IN",
    "ks:ks_name":"Kelabailu",
    "ks:ks_pop":473,
    "ks:ks_type":"HABITATION",
    "name:eng_x_preferred":[
        "Kelabailu"
    ],
    "wof:name":"Kelabailu",
    "wof:placetype":"locality",
    "wof:population":473
},
  "geometry": {"coordinates":[74.757625,13.499594],"type":"Point"}
}