{
  "type": "Feature",
  "properties": {
    "iso:country":"IN",
    "ks:ks_name":"Anjurai Para",
    "ks:ks_pop":7,
    "ks:ks_type":"HABITATION",
    "name:eng_x_preferred":[
        "Anjurai Para"
    ],
    "wof:name":"Anjurai Para",
    "wof:placetype":"locality",
    "wof:population":7
},
  "geometry": {"coordinates":[91.51197999999999,23.776709],"type":"Point"}
}