{
  "type": "Feature",
  "properties": {
    "iso:country":"IN",
    "ks:ks_name":"Karickadu",
    "ks:ks_pop":828,
    "ks:ks_type":"HABITATION",
    "name:eng_x_preferred":[
        "Karickadu"
    ],
    "wof:name":"Karickadu",
    "wof:placetype":"locality",
    "wof:population":828
},
  "geometry": {"coordinates":[76.03276200000001,11.273529],"type":"Point"}
}