{
  "type": "Feature",
  "properties": {
    "gn:admin1_code":"16",
    "gn:admin2_code":"521.0",
    "gn:asciiname":"Pandare",
    "gn:country_code":"IN",
    "gn:dem":559,
    "gn:feature_class":"P",
    "gn:feature_code":"PPL",
    "gn:name":"Pand\u0101re",
    "gn:population":0,
    "gn:timezone":"Asia/Kolkata",
    "iso:country":"IN",
    "name:und_x_variant":[
        "Pandara",
        "Pand\u0101re"
    ],
    "wof:name":"Pandare",
    "wof:placetype":"locality"
},
  "geometry": {"coordinates":[74.46335000000001,18.13729],"type":"Point"}
}