{
  "type": "Feature",
  "properties": {
    "iso:country":"IN",
    "ks:ks_name":"Byadara",
    "ks:ks_pop":98,
    "ks:ks_type":"HABITATION",
    "name:eng_x_preferred":[
        "Byadara"
    ],
    "wof:name":"Byadara",
    "wof:placetype":"locality",
    "wof:population":98
},
  "geometry": {"coordinates":[74.865402,14.02129],"type":"Point"}
}