{
  "type": "Feature",
  "properties": {
    "iso:country":"IN",
    "ks:ks_alt_nam":"CHAUDHRY TOLA",
    "ks:ks_name":"Chaudhry Tola",
    "ks:ks_pop":200,
    "ks:ks_type":"HABITATION",
    "ks:ks_uagg_main":0,
    "name:eng_x_preferred":[
        "Chaudhry Tola"
    ],
    "wof:name":"Chaudhry Tola",
    "wof:placetype":"neighbourhood",
    "wof:population":200
},
  "geometry": {"coordinates":[86.81514,26.272021],"type":"Point"}
}