{
  "type": "Feature",
  "properties": {
    "iso:country":"IN",
    "ks:ks_name":"Thenmudiyanur",
    "ks:ks_pop":3148,
    "ks:ks_type":"VILLAGE",
    "name:eng_x_preferred":[
        "Thenmudiyanur"
    ],
    "wof:name":"Thenmudiyanur",
    "wof:placetype":"locality",
    "wof:population":3148
},
  "geometry": {"coordinates":[78.947839,12.120895],"type":"Point"}
}