{
  "type": "Feature",
  "properties": {
    "gn:admin1_code":"35",
    "gn:admin2_code":"426.0",
    "gn:asciiname":"Mohari",
    "gn:country_code":"IN",
    "gn:dem":580,
    "gn:feature_class":"P",
    "gn:feature_code":"PPL",
    "gn:name":"Moh\u0101ri",
    "gn:population":0,
    "gn:timezone":"Asia/Kolkata",
    "iso:country":"IN",
    "ks:ks_name":"Mouhari",
    "ks:ks_pop":133,
    "ks:ks_type":"HABITATION",
    "name:eng_x_preferred":[
        "Mouhari"
    ],
    "name:eng_x_variant":[
        "Mohari"
    ],
    "wof:name":"Mouhari",
    "wof:placetype":"locality",
    "wof:population":133
},
  "geometry": {"coordinates":[80.56598700000001,24.136039],"type":"Point"}
}