{
  "type": "Feature",
  "properties": {
    "gn:admin1_code":"25.0",
    "gn:admin2_code":"611.0",
    "gn:asciiname":"Thottalingi",
    "gn:country_code":"IN",
    "gn:dem":931,
    "gn:feature_class":"P",
    "gn:feature_code":"PPL",
    "gn:name":"Th\u014dttalingi",
    "gn:population":0,
    "gn:timezone":"Asia/Kolkata",
    "iso:country":"IN",
    "wof:name":"Thottalingi",
    "wof:placetype":"locality"
},
  "geometry": {"coordinates":[76.65600000000001,11.54277],"type":"Point"}
}