{
  "type": "Feature",
  "properties": {
    "gn:admin1_code":"19.0",
    "gn:admin2_code":"581.0",
    "gn:asciiname":"Yaladur",
    "gn:country_code":"IN",
    "gn:dem":820,
    "gn:feature_class":"P",
    "gn:feature_code":"PPL",
    "gn:name":"Yalad\u016br",
    "gn:population":0,
    "gn:timezone":"Asia/Kolkata",
    "iso:country":"IN",
    "wof:name":"Yaladur",
    "wof:placetype":"neighbourhood"
},
  "geometry": {"coordinates":[78.29333,13.28149],"type":"Point"}
}