{
  "type": "Feature",
  "properties": {
    "iso:country":"IN",
    "ks:ks_alt_nam":"kalathota",
    "ks:ks_name":"Kalathota",
    "ks:ks_pop":96,
    "ks:ks_type":"HABITATION",
    "name:eng_x_preferred":[
        "Kalathota"
    ],
    "wof:name":"Kalathota",
    "wof:placetype":"locality",
    "wof:population":96
},
  "geometry": {"coordinates":[74.61251300000001,14.200972],"type":"Point"}
}