{
  "type": "Feature",
  "properties": {
    "iso:country":"IN",
    "ks:ks_name":"Egmore",
    "ks:ks_type":"VILLAGE",
    "ks:ks_uagg_main":0,
    "name:eng_x_preferred":[
        "Egmore"
    ],
    "wof:name":"Egmore",
    "wof:placetype":"neighbourhood"
},
  "geometry": {"coordinates":[80.255556,13.071667],"type":"Point"}
}