{
  "type": "Feature",
  "properties": {
    "iso:country":"IN",
    "ks:ks_alt_nam":"KUKTACHAMALA",
    "ks:ks_name":"Kuktachamala",
    "ks:ks_pop":112,
    "ks:ks_type":"HABITATION",
    "name:eng_x_preferred":[
        "Kuktachamala"
    ],
    "wof:name":"Kuktachamala",
    "wof:placetype":"locality",
    "wof:population":112
},
  "geometry": {"coordinates":[74.679558,17.182093],"type":"Point"}
}