{
  "type": "Feature",
  "properties": {
    "iso:country":"IN",
    "ks:ks_name":"Araze Tandwa",
    "ks:ks_pop":303,
    "ks:ks_type":"HABITATION",
    "name:eng_x_preferred":[
        "Araze Tandwa"
    ],
    "wof:name":"Araze Tandwa",
    "wof:placetype":"locality",
    "wof:population":303
},
  "geometry": {"coordinates":[82.66323300000001,26.500795],"type":"Point"}
}