{
  "type": "Feature",
  "properties": {
    "gn:admin1_code":"21",
    "gn:admin2_code":"370.0",
    "gn:asciiname":"Rengali",
    "gn:country_code":"IN",
    "gn:dem":242,
    "gn:feature_class":"P",
    "gn:feature_code":"PPL",
    "gn:name":"Reng\u0101li",
    "gn:population":0,
    "gn:timezone":"Asia/Kolkata",
    "iso:country":"IN",
    "name:ori_x_preferred":[
        "\u0b30\u0b47\u0b19\u0b4d\u0b17\u0b3e\u0b32\u0b3f"
    ],
    "wof:name":"Rengali",
    "wof:placetype":"locality"
},
  "geometry": {"coordinates":[83.35779000000002,21.33439],"type":"Point"}
}