{
  "type": "Feature",
  "properties": {
    "iso:country":"IN",
    "ks:ks_alt_nam":"Sahjanpur Il\u0101ka Budhauli",
    "ks:ks_name":"Sahjanpur Ilaka Budhauli",
    "ks:ks_type":"VILLAGE",
    "name:eng_x_preferred":[
        "Sahjanpur Ilaka Budhauli"
    ],
    "name:eng_x_variant":[
        "Sahjanpur Il\u0101ka Budhauli"
    ],
    "wof:name":"Sahjanpur Ilaka Budhauli",
    "wof:placetype":"locality"
},
  "geometry": {"coordinates":[79.649129,28.239018],"type":"Point"}
}