{
  "type": "Feature",
  "properties": {
    "iso:country":"IN",
    "ks:ks_name":"Medirkhal",
    "ks:ks_pop":61,
    "ks:ks_type":"HABITATION",
    "name:eng_x_preferred":[
        "Medirkhal"
    ],
    "wof:name":"Medirkhal",
    "wof:placetype":"locality",
    "wof:population":61
},
  "geometry": {"coordinates":[82.039187,18.160993],"type":"Point"}
}