{
  "type": "Feature",
  "properties": {
    "gn:admin1_code":"19.0",
    "gn:admin2_code":"557",
    "gn:asciiname":"Huvin Hippargi",
    "gn:country_code":"IN",
    "gn:dem":591,
    "gn:feature_class":"P",
    "gn:feature_code":"PPL",
    "gn:name":"Huvin Hippargi",
    "gn:population":0,
    "gn:timezone":"Asia/Kolkata",
    "iso:country":"IN",
    "wof:name":"Huvin Hippargi",
    "wof:placetype":"locality"
},
  "geometry": {"coordinates":[76.07606,16.55836],"type":"Point"}
}