{
  "type": "Feature",
  "properties": {
    "iso:country":"IN",
    "ks:ks_name":"Kombuthi",
    "ks:ks_pop":318,
    "ks:ks_type":"HABITATION",
    "name:eng_x_preferred":[
        "Kombuthi"
    ],
    "wof:name":"Kombuthi",
    "wof:placetype":"locality",
    "wof:population":318
},
  "geometry": {"coordinates":[79.362996,11.305394],"type":"Point"}
}