{
  "type": "Feature",
  "properties": {
    "gn:admin1_code":"35",
    "gn:admin2_code":"462.0",
    "gn:asciiname":"Bajrangarh",
    "gn:country_code":"IN",
    "gn:dem":304,
    "gn:feature_class":"P",
    "gn:feature_code":"PPL",
    "gn:name":"Bajrangarh",
    "gn:population":0,
    "gn:timezone":"Asia/Kolkata",
    "iso:country":"IN",
    "ks:ks_name":"Bajranggarh",
    "ks:ks_pop":1233,
    "ks:ks_type":"VILLAGE",
    "name:eng_x_preferred":[
        "Bajranggarh"
    ],
    "name:eng_x_variant":[
        "Bajrangarh"
    ],
    "wof:name":"Bajranggarh",
    "wof:placetype":"locality",
    "wof:population":1233
},
  "geometry": {"coordinates":[81.50427000000001,24.245951],"type":"Point"}
}