{
  "type": "Feature",
  "properties": {
    "iso:country":"IN",
    "ks:ks_alt_nam":"N  seader",
    "ks:ks_name":"N Seader",
    "ks:ks_pop":298,
    "ks:ks_type":"HABITATION",
    "name:eng_x_preferred":[
        "N Seader"
    ],
    "name:eng_x_variant":[
        "N  seader"
    ],
    "wof:name":"N Seader",
    "wof:placetype":"locality",
    "wof:population":298
},
  "geometry": {"coordinates":[78.8995,27.68152],"type":"Point"}
}