{
  "type": "Feature",
  "properties": {
    "gn:country":"IN",
    "gn:fcode":"PPL",
    "gn:population":16411,
    "iso:country":"IN",
    "name:bpy_x_preferred":[
        "\u09ad\u09be\u09b0\u09f1\u09be\u09b0\u09bf"
    ],
    "name:ceb_x_preferred":[
        "Bharw\u0101ri"
    ],
    "name:eng_x_preferred":[
        "Bharwari"
    ],
    "name:fra_x_preferred":[
        "Bharwari"
    ],
    "name:hin_x_preferred":[
        "\u092d\u0930\u0935\u093e\u0930\u0940"
    ],
    "name:ita_x_preferred":[
        "Bharwari"
    ],
    "name:mlg_x_preferred":[
        "Bharwari"
    ],
    "name:msa_x_preferred":[
        "Bharwari"
    ],
    "name:nan_x_preferred":[
        "Bharwari"
    ],
    "name:new_x_preferred":[
        "\u092d\u0930\u094d\u0935\u0930\u0940"
    ],
    "name:nld_x_preferred":[
        "Bharwari"
    ],
    "name:pol_x_preferred":[
        "Bharwari"
    ],
    "name:por_x_preferred":[
        "Bharwari"
    ],
    "name:swe_x_preferred":[
        "Bharw\u0101ri"
    ],
    "name:urd_x_preferred":[
        "\u0628\u06be\u0631\u0648\u0627\u0631\u06cc"
    ],
    "name:vie_x_preferred":[
        "Bharwari"
    ],
    "name:zho_x_preferred":[
        "\u5df4\u5c14\u74e6\u91cc"
    ],
    "qs:name":"Bharari",
    "qs:name_adm0":"India",
    "qs:name_adm1":"Uttar Pradesh",
    "qs:photos_9r":0,
    "qs:photos_sr":0,
    "qs:placetype":"Town",
    "qs:pop_sr":"6",
    "wof:name":"Bharari",
    "wof:placetype":"locality",
    "wof:population":16411
},
  "geometry": {"coordinates":[81.49173999999999,25.5606],"type":"Point"}
}