{
  "type": "Feature",
  "properties": {
    "iso:country":"IN",
    "ks:ks_name":"Duddavalli",
    "ks:ks_pop":110,
    "ks:ks_type":"HABITATION",
    "name:eng_x_preferred":[
        "Duddavalli"
    ],
    "wof:name":"Duddavalli",
    "wof:placetype":"locality",
    "wof:population":110
},
  "geometry": {"coordinates":[75.700355,12.798548],"type":"Point"}
}