{
  "type": "Feature",
  "properties": {
    "iso:country":"IN",
    "ks:ks_name":"Bagauti",
    "ks:ks_pop":446,
    "ks:ks_type":"VILLAGE",
    "name:eng_x_preferred":[
        "Bagauti"
    ],
    "wof:name":"Bagauti",
    "wof:placetype":"locality",
    "wof:population":446
},
  "geometry": {"coordinates":[80.241209,29.39345],"type":"Point"}
}