{
  "type": "Feature",
  "properties": {
    "iso:country":"IN",
    "ks:ks_name":"Koolipura",
    "ks:ks_pop":450,
    "ks:ks_type":"VILLAGE",
    "ks:ks_uagg_main":0,
    "name:eng_x_preferred":[
        "Koolipura"
    ],
    "wof:name":"Koolipura",
    "wof:placetype":"locality",
    "wof:population":450
},
  "geometry": {"coordinates":[77.396739,13.110793],"type":"Point"}
}