{
  "type": "Feature",
  "properties": {
    "gn:admin1_code":"34.0",
    "gn:admin2_code":"208.0",
    "gn:asciiname":"Narhi",
    "gn:country_code":"IN",
    "gn:dem":57,
    "gn:feature_class":"P",
    "gn:feature_code":"PPL",
    "gn:name":"Narhi",
    "gn:population":0,
    "gn:timezone":"Asia/Kolkata",
    "iso:country":"IN",
    "wof:name":"Narhi",
    "wof:placetype":"neighbourhood"
},
  "geometry": {"coordinates":[86.95829999999999,26.11531],"type":"Point"}
}