{
  "type": "Feature",
  "properties": {
    "iso:country":"IN",
    "ks:ks_name":"Kisma",
    "ks:ks_pop":63,
    "ks:ks_type":"VILLAGE",
    "name:eng_x_preferred":[
        "Kisma"
    ],
    "wof:name":"Kisma",
    "wof:placetype":"locality",
    "wof:population":63
},
  "geometry": {"coordinates":[87.41757,24.926496],"type":"Point"}
}