{
  "type": "Feature",
  "properties": {
    "iso:country":"IN",
    "ks:ks_name":"Bara",
    "ks:ks_pop":794,
    "ks:ks_type":"VILLAGE",
    "name:eng_x_preferred":[
        "Bara"
    ],
    "wof:name":"Bara",
    "wof:placetype":"locality",
    "wof:population":794
},
  "geometry": {"coordinates":[86.71311,24.567724],"type":"Point"}
}