{
  "type": "Feature",
  "properties": {
    "gn:admin1_code":"19.0",
    "gn:admin2_code":"574.0",
    "gn:asciiname":"Agrahara",
    "gn:country_code":"IN",
    "gn:dem":773,
    "gn:feature_class":"P",
    "gn:feature_code":"PPL",
    "gn:name":"Agrah\u0101ra",
    "gn:population":0,
    "gn:timezone":"Asia/Kolkata",
    "iso:country":"IN",
    "wof:name":"Agrahara",
    "wof:placetype":"neighbourhood"
},
  "geometry": {"coordinates":[76.20873,13.40723],"type":"Point"}
}