{
  "type": "Feature",
  "properties": {
    "iso:country":"IN",
    "ks:ks_name":"Nava Falia",
    "ks:ks_pop":395,
    "ks:ks_type":"HABITATION",
    "name:eng_x_preferred":[
        "Nava Falia"
    ],
    "wof:name":"Nava Falia",
    "wof:placetype":"locality",
    "wof:population":395
},
  "geometry": {"coordinates":[74.268612,22.885979],"type":"Point"}
}