{
  "type": "Feature",
  "properties": {
    "iso:country":"IN",
    "ks:ks_name":"Karavanagi",
    "ks:ks_pop":57,
    "ks:ks_type":"HABITATION",
    "name:eng_x_preferred":[
        "Karavanagi"
    ],
    "wof:name":"Karavanagi",
    "wof:placetype":"locality",
    "wof:population":57
},
  "geometry": {"coordinates":[74.87724799999999,14.728187],"type":"Point"}
}