{
  "type": "Feature",
  "properties": {
    "iso:country":"IN",
    "ks:ks_name":"Melinuru",
    "ks:ks_pop":15,
    "ks:ks_type":"HABITATION",
    "name:eng_x_preferred":[
        "Melinuru"
    ],
    "wof:name":"Melinuru",
    "wof:placetype":"locality",
    "wof:population":15
},
  "geometry": {"coordinates":[74.780511,14.158502],"type":"Point"}
}