{
  "type": "Feature",
  "properties": {
    "iso:country":"IN",
    "ks:ks_name":"Kadaripara",
    "ks:ks_pop":0,
    "ks:ks_type":"VILLAGE",
    "name:eng_x_preferred":[
        "Kadaripara"
    ],
    "wof:name":"Kadaripara",
    "wof:placetype":"locality",
    "wof:population":0
},
  "geometry": {"coordinates":[88.44693599999999,25.037382],"type":"Point"}
}