{
  "type": "Feature",
  "properties": {
    "iso:country":"IN",
    "ks:ks_alt_nam":"Jampara -B",
    "ks:ks_name":"Jampara -b",
    "ks:ks_pop":186,
    "ks:ks_type":"HABITATION",
    "name:eng_x_preferred":[
        "Jampara -b"
    ],
    "wof:name":"Jampara -b",
    "wof:placetype":"locality",
    "wof:population":186
},
  "geometry": {"coordinates":[82.73584700000001,23.321096],"type":"Point"}
}