{
  "type": "Feature",
  "properties": {
    "iso:country":"IN",
    "ks:ks_name":"Bishunpur Siriram",
    "ks:ks_pop":1580,
    "ks:ks_type":"VILLAGE",
    "name:eng_x_preferred":[
        "Bishunpur Siriram"
    ],
    "wof:name":"Bishunpur Siriram",
    "wof:placetype":"locality",
    "wof:population":1580
},
  "geometry": {"coordinates":[85.509401,26.031731],"type":"Point"}
}