{
  "type": "Feature",
  "properties": {
    "iso:country":"IN",
    "ks:ks_name":"Baragerya",
    "ks:ks_pop":127,
    "ks:ks_type":"VILLAGE",
    "name:eng_x_preferred":[
        "Baragerya"
    ],
    "wof:name":"Baragerya",
    "wof:placetype":"locality",
    "wof:population":127
},
  "geometry": {"coordinates":[87.413297,22.199085],"type":"Point"}
}