{
  "type": "Feature",
  "properties": {
    "gn:admin1_code":"36",
    "gn:admin2_code":"146.0",
    "gn:asciiname":"Dharehra",
    "gn:country_code":"IN",
    "gn:dem":168,
    "gn:feature_class":"P",
    "gn:feature_code":"PPL",
    "gn:name":"Dharehra",
    "gn:population":0,
    "gn:timezone":"Asia/Kolkata",
    "iso:country":"IN",
    "wof:name":"Dharehra",
    "wof:placetype":"locality"
},
  "geometry": {"coordinates":[78.15649999999999,27.24431],"type":"Point"}
}