{
  "type": "Feature",
  "properties": {
    "gn:admin1_code":"36",
    "gn:admin2_code":"146.0",
    "gn:asciiname":"Dharehra",
    "gn:country_code":"IN",
    "gn:dem":168,
    "gn:feature_class":"P",
    "gn:feature_code":"PPL",
    "gn:name":"Dharehra",
    "gn:population":0,
    "gn:timezone":"Asia/Kolkata",
    "iso:country":"IN",
    "ks:ks_name":"Dharera",
    "ks:ks_pop":147,
    "ks:ks_type":"VILLAGE",
    "name:eng_x_preferred":[
        "Dharera"
    ],
    "name:eng_x_variant":[
        "Dharehra"
    ],
    "wof:name":"Dharera",
    "wof:placetype":"locality",
    "wof:population":147
},
  "geometry": {"coordinates":[78.165935,27.247279],"type":"Point"}
}