{
  "type": "Feature",
  "properties": {
    "iso:country":"IN",
    "ks:ks_alt_nam":"DHEEMAR TOLA",
    "ks:ks_name":"Dheemar Tola",
    "ks:ks_pop":75,
    "ks:ks_type":"HABITATION",
    "name:eng_x_preferred":[
        "Dheemar Tola"
    ],
    "wof:name":"Dheemar Tola",
    "wof:placetype":"locality",
    "wof:population":75
},
  "geometry": {"coordinates":[78.700526,26.970285],"type":"Point"}
}