{
  "type": "Feature",
  "properties": {
    "iso:country":"IN",
    "ks:ks_name":"Bojhwa",
    "ks:ks_pop":134,
    "ks:ks_type":"HABITATION",
    "name:eng_x_preferred":[
        "Bojhwa"
    ],
    "wof:name":"Bojhwa",
    "wof:placetype":"locality",
    "wof:population":134
},
  "geometry": {"coordinates":[82.20944900000001,26.504767],"type":"Point"}
}