{
  "type": "Feature",
  "properties": {
    "gn:admin1_code":"20.0",
    "gn:admin2_code":"263",
    "gn:asciiname":"Aichisagami",
    "gn:country_code":"IN",
    "gn:dem":1889,
    "gn:feature_class":"P",
    "gn:feature_code":"PPL",
    "gn:name":"Aich\u012bs\u0101g\u0101mi",
    "gn:population":0,
    "gn:timezone":"Asia/Kolkata",
    "iso:country":"IN",
    "wof:name":"Aichisagami",
    "wof:placetype":"locality"
},
  "geometry": {"coordinates":[94.59223,26.11918],"type":"Point"}
}