{
  "type": "Feature",
  "properties": {
    "iso:country":"IN",
    "ks:ks_name":"Kaunta",
    "ks:ks_pop":528,
    "ks:ks_type":"VILLAGE",
    "name:eng_x_preferred":[
        "Kaunta"
    ],
    "wof:name":"Kaunta",
    "wof:placetype":"locality",
    "wof:population":528
},
  "geometry": {"coordinates":[79.69562000000001,29.222016],"type":"Point"}
}