{
  "type": "Feature",
  "properties": {
    "iso:country":"IN",
    "ks:ks_name":"Jorabertoli",
    "ks:ks_pop":192,
    "ks:ks_type":"HABITATION",
    "name:eng_x_preferred":[
        "Jorabertoli"
    ],
    "wof:name":"Jorabertoli",
    "wof:placetype":"locality",
    "wof:population":192
},
  "geometry": {"coordinates":[84.566058,22.948735],"type":"Point"}
}