{
  "type": "Feature",
  "properties": {
    "gn:admin1_code":"12.0",
    "gn:admin2_code":"18.0",
    "gn:asciiname":"Daribadan",
    "gn:country_code":"IN",
    "gn:dem":1487,
    "gn:feature_class":"P",
    "gn:feature_code":"PPL",
    "gn:name":"Daribad\u0101n",
    "gn:population":0,
    "gn:timezone":"Asia/Kolkata",
    "iso:country":"IN",
    "wof:name":"Daribadan",
    "wof:placetype":"locality"
},
  "geometry": {"coordinates":[75.71710999999998,33.33073],"type":"Point"}
}