{
  "type": "Feature",
  "properties": {
    "iso:country":"IN",
    "ks:ks_name":"Tambalwadi",
    "ks:ks_pop":25,
    "ks:ks_type":"HABITATION",
    "name:eng_x_preferred":[
        "Tambalwadi"
    ],
    "wof:name":"Tambalwadi",
    "wof:placetype":"locality",
    "wof:population":25
},
  "geometry": {"coordinates":[73.69568,16.618279],"type":"Point"}
}