{
  "type": "Feature",
  "properties": {
    "iso:country":"IN",
    "ks:ks_name":"Deolachiwadi",
    "ks:ks_pop":325,
    "ks:ks_type":"HABITATION",
    "name:eng_x_preferred":[
        "Deolachiwadi"
    ],
    "wof:name":"Deolachiwadi",
    "wof:placetype":"locality",
    "wof:population":325
},
  "geometry": {"coordinates":[73.460556,17.177222],"type":"Point"}
}