{
  "type": "Feature",
  "properties": {
    "gn:admin1_code":"19.0",
    "gn:admin2_code":"582.0",
    "gn:asciiname":"Mangalamaduguvandlapalli",
    "gn:country_code":"IN",
    "gn:dem":704,
    "gn:feature_class":"P",
    "gn:feature_code":"PPL",
    "gn:name":"Mangalamaduguv\u0101ndlapalli",
    "gn:population":0,
    "gn:timezone":"Asia/Kolkata",
    "iso:country":"IN",
    "wof:name":"Mangalamaduguvandlapalli",
    "wof:placetype":"locality"
},
  "geometry": {"coordinates":[78.02410999999999,13.77325],"type":"Point"}
}