{
  "type": "Feature",
  "properties": {
    "iso:country":"IN",
    "ks:ks_name":"Atyarai Para",
    "ks:ks_pop":270,
    "ks:ks_type":"HABITATION",
    "ks:ks_uagg_main":0,
    "name:eng_x_preferred":[
        "Atyarai Para"
    ],
    "wof:name":"Atyarai Para",
    "wof:placetype":"neighbourhood",
    "wof:population":270
},
  "geometry": {"coordinates":[91.755824,23.430751],"type":"Point"}
}