{
  "type": "Feature",
  "properties": {
    "iso:country":"IN",
    "ks:ks_name":"Dal",
    "ks:ks_pop":40,
    "ks:ks_type":"VILLAGE",
    "name:eng_x_preferred":[
        "Dal"
    ],
    "wof:name":"Dal",
    "wof:placetype":"locality",
    "wof:population":40
},
  "geometry": {"coordinates":[78.616207,30.027925],"type":"Point"}
}