{
  "type": "Feature",
  "properties": {
    "gn:admin1_code":"36",
    "gn:admin2_code":"178.0",
    "gn:asciiname":"Jagtupur Biltai",
    "gn:country_code":"IN",
    "gn:dem":92,
    "gn:feature_class":"P",
    "gn:feature_code":"PPL",
    "gn:name":"Jagt\u016bpur Biltai",
    "gn:population":0,
    "gn:timezone":"Asia/Kolkata",
    "iso:country":"IN",
    "wof:name":"Jagtupur Biltai",
    "wof:placetype":"neighbourhood"
},
  "geometry": {"coordinates":[82.65761999999999,26.30562],"type":"Point"}
}