{
  "type": "Feature",
  "properties": {
    "iso:country":"IN",
    "ks:ks_name":"Arajibaghaee",
    "ks:ks_pop":131,
    "ks:ks_type":"HABITATION",
    "name:eng_x_preferred":[
        "Arajibaghaee"
    ],
    "wof:name":"Arajibaghaee",
    "wof:placetype":"locality",
    "wof:population":131
},
  "geometry": {"coordinates":[83.179902,25.714093],"type":"Point"}
}