{
  "type": "Feature",
  "properties": {
    "iso:country":"IN",
    "ks:ks_alt_nam":"Saradh falia",
    "ks:ks_name":"Saradh Falia",
    "ks:ks_pop":865,
    "ks:ks_type":"HABITATION",
    "name:eng_x_preferred":[
        "Saradh Falia"
    ],
    "wof:name":"Saradh Falia",
    "wof:placetype":"locality",
    "wof:population":865
},
  "geometry": {"coordinates":[73.153167,20.874056],"type":"Point"}
}