{
  "type": "Feature",
  "properties": {
    "iso:country":"IN",
    "ks:ks_name":"Veeranjanaya Kottala",
    "ks:ks_pop":126,
    "ks:ks_type":"HABITATION",
    "name:eng_x_preferred":[
        "Veeranjanaya Kottala"
    ],
    "wof:name":"Veeranjanaya Kottala",
    "wof:placetype":"locality",
    "wof:population":126
},
  "geometry": {"coordinates":[77.270906,14.66114],"type":"Point"}
}