{
  "type": "Feature",
  "properties": {
    "iso:country":"IN",
    "ks:ks_name":"Bogayanakere",
    "ks:ks_pop":198,
    "ks:ks_type":"HABITATION",
    "name:eng_x_preferred":[
        "Bogayanakere"
    ],
    "wof:name":"Bogayanakere",
    "wof:placetype":"locality",
    "wof:population":198
},
  "geometry": {"coordinates":[75.524821,12.669519],"type":"Point"}
}