{
  "type": "Feature",
  "properties": {
    "iso:country":"IN",
    "ks:ks_name":"Kwiral Gaon",
    "ks:ks_pop":28,
    "ks:ks_type":"VILLAGE",
    "name:eng_x_preferred":[
        "Kwiral Gaon"
    ],
    "wof:name":"Kwiral Gaon",
    "wof:placetype":"locality",
    "wof:population":28
},
  "geometry": {"coordinates":[78.381501,30.05453],"type":"Point"}
}