{
  "type": "Feature",
  "properties": {
    "iso:country":"IN",
    "ks:ks_name":"Bhabi Ka Purva",
    "ks:ks_pop":521,
    "ks:ks_type":"HABITATION",
    "ks:ks_uagg_main":0,
    "name:eng_x_preferred":[
        "Bhabi Ka Purva"
    ],
    "wof:name":"Bhabi Ka Purva",
    "wof:placetype":"neighbourhood",
    "wof:population":521
},
  "geometry": {"coordinates":[81.28596,26.007539],"type":"Point"}
}