{
  "type": "Feature",
  "properties": {
    "gn:admin1_code":"34.0",
    "gn:admin2_code":"203.0",
    "gn:asciiname":"Bhigari",
    "gn:country_code":"IN",
    "gn:dem":77,
    "gn:feature_class":"P",
    "gn:feature_code":"PPL",
    "gn:name":"Bhig\u0101ri",
    "gn:population":0,
    "gn:timezone":"Asia/Kolkata",
    "iso:country":"IN",
    "ks:ks_name":"Bhogari",
    "ks:ks_pop":1760,
    "ks:ks_type":"HABITATION",
    "ks:ks_uagg_main":0,
    "name:eng_x_preferred":[
        "Bhogari"
    ],
    "wof:name":"Bhogari",
    "wof:placetype":"neighbourhood",
    "wof:population":1760
},
  "geometry": {"coordinates":[84.69733100000001,26.860484],"type":"Point"}
}