{
  "type": "Feature",
  "properties": {
    "iso:country":"IN",
    "ks:ks_name":"2 No Kaborugaon",
    "ks:ks_pop":263,
    "ks:ks_type":"HABITATION",
    "ks:ks_uagg_main":0,
    "name:eng_x_preferred":[
        "2 No Kaborugaon"
    ],
    "wof:name":"2 No Kaborugaon",
    "wof:placetype":"neighbourhood",
    "wof:population":263
},
  "geometry": {"coordinates":[94.00662,26.531594],"type":"Point"}
}