{
  "type": "Feature",
  "properties": {
    "iso:country":"IN",
    "ks:ks_name":"Fadki Ryt.",
    "ks:ks_pop":473,
    "ks:ks_type":"VILLAGE",
    "name:eng_x_preferred":[
        "Fadki Ryt."
    ],
    "wof:name":"Fadki Ryt.",
    "wof:placetype":"locality",
    "wof:population":473
},
  "geometry": {"coordinates":[80.50609900000001,22.979413],"type":"Point"}
}