{
  "type": "Feature",
  "properties": {
    "iso:country":"IN",
    "ks:ks_alt_nam":"Bormatia Pt III",
    "ks:ks_name":"Bormatia Pt Iii",
    "ks:ks_pop":973,
    "ks:ks_type":"HABITATION",
    "name:eng_x_preferred":[
        "Bormatia Pt Iii"
    ],
    "wof:name":"Bormatia Pt Iii",
    "wof:placetype":"locality",
    "wof:population":973
},
  "geometry": {"coordinates":[90.76273,25.947896],"type":"Point"}
}