{
  "type": "Feature",
  "properties": {
    "iso:country":"IN",
    "ks:ks_name":"Sahijana",
    "ks:ks_pop":15,
    "ks:ks_type":"VILLAGE",
    "name:eng_x_preferred":[
        "Sahijana"
    ],
    "wof:name":"Sahijana",
    "wof:placetype":"locality",
    "wof:population":15
},
  "geometry": {"coordinates":[85.128533,24.332627],"type":"Point"}
}