{
  "type": "Feature",
  "properties": {
    "iso:country":"IN",
    "ks:ks_name":"Panktor",
    "ks:ks_pop":2494,
    "ks:ks_type":"VILLAGE",
    "name:eng_x_preferred":[
        "Panktor"
    ],
    "wof:name":"Panktor",
    "wof:placetype":"locality",
    "wof:population":2494
},
  "geometry": {"coordinates":[87.151459,23.482439],"type":"Point"}
}