{
  "type": "Feature",
  "properties": {
    "gn:admin1_code":"35",
    "gn:admin2_code":"426.0",
    "gn:asciiname":"Kothi",
    "gn:country_code":"IN",
    "gn:dem":445,
    "gn:feature_class":"P",
    "gn:feature_code":"PPL",
    "gn:name":"Kothi",
    "gn:population":0,
    "gn:timezone":"Asia/Kolkata",
    "iso:country":"IN",
    "ks:ks_name":"Kothi",
    "ks:ks_pop":919,
    "ks:ks_type":"VILLAGE",
    "name:ceb_x_preferred":[
        "Kothi"
    ],
    "name:eng_x_preferred":[
        "Kothi"
    ],
    "name:swe_x_preferred":[
        "Kothi"
    ],
    "wof:name":"Kothi",
    "wof:placetype":"locality",
    "wof:population":919
},
  "geometry": {"coordinates":[80.027772,24.148656],"type":"Point"}
}