{
  "type": "Feature",
  "properties": {
    "iso:country":"IN",
    "ks:ks_name":"Kukada",
    "ks:ks_pop":181,
    "ks:ks_type":"HABITATION",
    "name:eng_x_preferred":[
        "Kukada"
    ],
    "wof:name":"Kukada",
    "wof:placetype":"locality",
    "wof:population":181
},
  "geometry": {"coordinates":[80.328902,22.104259],"type":"Point"}
}