{
  "type": "Feature",
  "properties": {
    "iso:country":"IN",
    "ks:ks_name":"Bazar",
    "ks:ks_pop":215,
    "ks:ks_type":"HABITATION",
    "ks:ks_uagg_main":0,
    "name:eng_x_preferred":[
        "Bazar"
    ],
    "wof:name":"Bazar",
    "wof:placetype":"neighbourhood",
    "wof:population":215
},
  "geometry": {"coordinates":[81.18208799999999,26.000283],"type":"Point"}
}