{
  "type": "Feature",
  "properties": {
    "gn:admin1_code":"36",
    "gn:admin2_code":"160.0",
    "gn:asciiname":"Nandpur",
    "gn:country_code":"IN",
    "gn:dem":144,
    "gn:feature_class":"P",
    "gn:feature_code":"PPL",
    "gn:name":"Nandpur",
    "gn:population":0,
    "gn:timezone":"Asia/Kolkata",
    "iso:country":"IN",
    "wof:name":"Nandpur",
    "wof:placetype":"locality"
},
  "geometry": {"coordinates":[79.77154,26.94979],"type":"Point"}
}