{
  "type": "Feature",
  "properties": {
    "iso:country":"IN",
    "ks:ks_name":"Surve Vasti",
    "ks:ks_pop":174,
    "ks:ks_type":"HABITATION",
    "name:eng_x_preferred":[
        "Surve Vasti"
    ],
    "wof:name":"Surve Vasti",
    "wof:placetype":"locality",
    "wof:population":174
},
  "geometry": {"coordinates":[73.83936,18.360082],"type":"Point"}
}