{
  "type": "Feature",
  "properties": {
    "gn:country":"IN",
    "gn:fcode":"PPL",
    "gn:pop":4831,
    "iso:country":"IN",
    "name:ara_x_preferred":[
        "\u062a\u0627\u0648\u0627\u0646\u062c"
    ],
    "name:asm_x_preferred":[
        "\u099f\u09be\u09f1\u09be\u0982"
    ],
    "name:ben_x_preferred":[
        "\u09a4\u0993\u09af\u09bc\u09be\u0982"
    ],
    "name:bpy_x_preferred":[
        "\u09a4\u09be\u0993\u09af\u09bc\u09be\u0982"
    ],
    "name:deu_x_preferred":[
        "Tawang"
    ],
    "name:ell_x_preferred":[
        "\u03a4\u03b1\u03bf\u03c5\u03ac\u03bd\u03b3\u03ba"
    ],
    "name:eng_x_preferred":[
        "Tawang Town"
    ],
    "name:fra_x_preferred":[
        "Tawang"
    ],
    "name:guj_x_preferred":[
        "\u0aa4\u0ab5\u0abe\u0a82\u0a97"
    ],
    "name:hin_x_preferred":[
        "\u0924\u0935\u093e\u0902\u0917"
    ],
    "name:ind_x_preferred":[
        "Tawang"
    ],
    "name:ita_x_preferred":[
        "Tawang"
    ],
    "name:jpn_x_preferred":[
        "\u30bf\u30ef\u30f3"
    ],
    "name:kan_x_preferred":[
        "\u0ca4\u0cb5\u0cbe\u0c82\u0c97\u0ccd \u0c9f\u0ccc\u0ca8\u0ccd"
    ],
    "name:kor_x_preferred":[
        "\ud0c0\uc655 \ud0c0\uc6b4"
    ],
    "name:mar_x_preferred":[
        "\u0924\u0935\u093e\u0902\u0917"
    ],
    "name:msa_x_preferred":[
        "Tawang"
    ],
    "name:nan_x_preferred":[
        "Tawang"
    ],
    "name:nld_x_preferred":[
        "Tawang"
    ],
    "name:ori_x_preferred":[
        "\u0b24\u0b71\u0b3e\u0b19\u0b4d\u0b17"
    ],
    "name:por_x_preferred":[
        "Tawang Town"
    ],
    "name:rus_x_preferred":[
        "\u0422\u0430\u0432\u0430\u043d\u0433"
    ],
    "name:spa_x_preferred":[
        "Tawang"
    ],
    "name:swe_x_preferred":[
        "Tawang"
    ],
    "name:tam_x_preferred":[
        "\u0b9f\u0bb5\u0bbe\u0b99\u0bcd \u0ba8\u0b95\u0bb0\u0bae\u0bcd"
    ],
    "name:tel_x_preferred":[
        "\u0c24\u0c35\u0c3e\u0c02\u0c17\u0c4d \u0c1f\u0c4c\u0c28\u0c4d"
    ],
    "name:unk_x_variant":[
        "M\u00f6n Tawang"
    ],
    "name:urd_x_preferred":[
        "\u062a\u0627\u0648\u0627\u0646\u062c"
    ],
    "name:vie_x_preferred":[
        "Tawang"
    ],
    "name:zho_x_preferred":[
        "\u8fbe\u65fa\u9547"
    ],
    "qs:name":"Tawang",
    "qs:name_adm0":"India",
    "qs:name_adm1":"Arunachal Pradesh",
    "qs:photos":491,
    "qs:photos_1k":99,
    "qs:photos_9k":2,
    "qs:photos_9r":5,
    "qs:photos_all":491,
    "qs:photos_sr":7,
    "qs:placetype":"Town",
    "qs:pop_sr":"4",
    "wof:name":"Tawang",
    "wof:placetype":"locality",
    "wof:population":4831
},
  "geometry": {"coordinates":[91.92437,27.57417],"type":"Point"}
}