{
  "type": "Feature",
  "properties": {
    "iso:country":"IN",
    "ks:ks_name":"Rangrasia Khas",
    "ks:ks_pop":211,
    "ks:ks_type":"HABITATION",
    "name:eng_x_preferred":[
        "Rangrasia Khas"
    ],
    "wof:name":"Rangrasia Khas",
    "wof:placetype":"locality",
    "wof:population":211
},
  "geometry": {"coordinates":[85.605356,22.641998],"type":"Point"}
}