{
  "type": "Feature",
  "properties": {
    "iso:country":"IN",
    "ks:ks_name":"Barai Bandhawa",
    "ks:ks_pop":1980,
    "ks:ks_type":"HABITATION",
    "name:eng_x_preferred":[
        "Barai Bandhawa"
    ],
    "wof:name":"Barai Bandhawa",
    "wof:placetype":"locality",
    "wof:population":1980
},
  "geometry": {"coordinates":[81.4877,25.4244],"type":"Point"}
}