{
  "type": "Feature",
  "properties": {
    "iso:country":"IN",
    "ks:ks_name":"Talsindhikhunti",
    "ks:ks_pop":14,
    "ks:ks_type":"VILLAGE",
    "name:eng_x_preferred":[
        "Talsindhikhunti"
    ],
    "wof:name":"Talsindhikhunti",
    "wof:placetype":"locality",
    "wof:population":14
},
  "geometry": {"coordinates":[83.26680399999999,19.888991],"type":"Point"}
}