{
  "type": "Feature",
  "properties": {
    "gn:admin1_code":"11.0",
    "gn:admin2_code":"33.0",
    "gn:asciiname":"Karala",
    "gn:country_code":"IN",
    "gn:dem":2046,
    "gn:feature_class":"P",
    "gn:feature_code":"PPL",
    "gn:name":"Kar\u0101la",
    "gn:population":0,
    "gn:timezone":"Asia/Kolkata",
    "iso:country":"IN",
    "name:ita_x_preferred":[
        "Karala"
    ],
    "name:msa_x_preferred":[
        "Karala"
    ],
    "name:spa_x_preferred":[
        "Karala"
    ],
    "wof:name":"Karala",
    "wof:placetype":"locality"
},
  "geometry": {"coordinates":[77.66620999999998,31.25226],"type":"Point"}
}