{
  "type": "Feature",
  "properties": {
    "iso:country":"IN",
    "ks:ks_name":"Chak Dallan",
    "ks:ks_pop":388,
    "ks:ks_type":"VILLAGE",
    "ks:ks_uagg_main":0,
    "name:eng_x_preferred":[
        "Chak Dallan"
    ],
    "wof:name":"Chak Dallan",
    "wof:placetype":"neighbourhood",
    "wof:population":388
},
  "geometry": {"coordinates":[83.629385,25.690331],"type":"Point"}
}