{
  "type": "Feature",
  "properties": {
    "iso:country":"IN",
    "ks:ks_name":"Silinda",
    "ks:ks_pop":7125,
    "ks:ks_type":"VILLAGE",
    "ks:ks_uagg_main":0,
    "name:eng_x_preferred":[
        "Silinda"
    ],
    "wof:name":"Silinda",
    "wof:placetype":"locality",
    "wof:population":7125
},
  "geometry": {"coordinates":[88.653713,23.082098],"type":"Point"}
}