{
  "type": "Feature",
  "properties": {
    "gn:admin1_code":"19.0",
    "gn:admin2_code":"573.0",
    "gn:asciiname":"Hombalesiddegaudanadoddi",
    "gn:country_code":"IN",
    "gn:dem":698,
    "gn:feature_class":"P",
    "gn:feature_code":"PPL",
    "gn:name":"Hombalesiddegaudanadoddi",
    "gn:population":0,
    "gn:timezone":"Asia/Kolkata",
    "iso:country":"IN",
    "wof:name":"Hombalesiddegaudanadoddi",
    "wof:placetype":"locality"
},
  "geometry": {"coordinates":[76.9182,12.64572],"type":"Point"}
}