{
  "type": "Feature",
  "properties": {
    "iso:country":"IN",
    "ks:ks_name":"Waybhatwasti",
    "ks:ks_pop":105,
    "ks:ks_type":"HABITATION",
    "name:eng_x_preferred":[
        "Waybhatwasti"
    ],
    "wof:name":"Waybhatwasti",
    "wof:placetype":"locality",
    "wof:population":105
},
  "geometry": {"coordinates":[75.62663999999999,18.838529],"type":"Point"}
}