{
  "type": "Feature",
  "properties": {
    "iso:country":"IN",
    "ks:ks_name":"Gaddai",
    "ks:ks_pop":57,
    "ks:ks_type":"VILLAGE",
    "name:eng_x_preferred":[
        "Gaddai"
    ],
    "wof:name":"Gaddai",
    "wof:placetype":"locality",
    "wof:population":57
},
  "geometry": {"coordinates":[78.75617200000001,29.905715],"type":"Point"}
}