{
  "type": "Feature",
  "properties": {
    "gn:admin1_code":"34.0",
    "gn:admin2_code":"227.0",
    "gn:asciiname":"Auraiya",
    "gn:country_code":"IN",
    "gn:dem":53,
    "gn:feature_class":"P",
    "gn:feature_code":"PPL",
    "gn:name":"Auraiya",
    "gn:population":0,
    "gn:timezone":"Asia/Kolkata",
    "iso:country":"IN",
    "name:bih_x_preferred":[
        "\u0914\u0930\u0948\u092f\u093e"
    ],
    "name:bpy_x_preferred":[
        "\u0986\u0989\u09b0\u09be\u0987\u09af\u09bc\u09be"
    ],
    "name:ceb_x_preferred":[
        "Auraiya"
    ],
    "name:deu_x_preferred":[
        "Auraiya"
    ],
    "name:guj_x_preferred":[
        "\u0a94\u0ab0\u0ac8\u0aaf\u0abe"
    ],
    "name:hin_x_preferred":[
        "\u0914\u0930\u0948\u092f\u093e"
    ],
    "name:ita_x_preferred":[
        "Auraiya"
    ],
    "name:mar_x_preferred":[
        "\u0914\u0930\u0948\u092f\u093e"
    ],
    "name:mlg_x_preferred":[
        "Auraiya"
    ],
    "name:msa_x_preferred":[
        "Auraiya"
    ],
    "name:new_x_preferred":[
        "\u0914\u0930\u093e\u0907\u092f\u093e"
    ],
    "name:nld_x_preferred":[
        "Auraiya"
    ],
    "name:pan_x_preferred":[
        "\u0a14\u0a30\u0a3f\u0a06"
    ],
    "name:pnb_x_preferred":[
        "\u0627\u0648\u0631\u0627\u06cc\u06c1"
    ],
    "name:pol_x_preferred":[
        "Auraiya"
    ],
    "name:por_x_preferred":[
        "Auraiya"
    ],
    "name:rus_x_preferred":[
        "\u0410\u0443\u0440\u0430\u0439\u044f"
    ],
    "name:san_x_preferred":[
        "\u0914\u0930\u0948\u092f\u093e"
    ],
    "name:swe_x_preferred":[
        "Auraiya"
    ],
    "name:urd_x_preferred":[
        "\u0627\u0648\u0631\u06cc\u0627"
    ],
    "name:vie_x_preferred":[
        "Auraiya"
    ],
    "name:zho_x_preferred":[
        "\u5965\u8d56\u8036"
    ],
    "wof:name":"Auraiya",
    "wof:placetype":"locality"
},
  "geometry": {"coordinates":[86.08065000000001,25.1373],"type":"Point"}
}