{
  "type": "Feature",
  "properties": {
    "iso:country":"IN",
    "ks:ks_name":"Golapada",
    "ks:ks_pop":565,
    "ks:ks_type":"VILLAGE",
    "ks:ks_uagg_main":0,
    "name:eng_x_preferred":[
        "Golapada"
    ],
    "wof:name":"Golapada",
    "wof:placetype":"neighbourhood",
    "wof:population":565
},
  "geometry": {"coordinates":[85.741131,20.124349],"type":"Point"}
}