{
  "type": "Feature",
  "properties": {
    "gn:admin1_code":"25.0",
    "gn:admin2_code":"608.0",
    "gn:asciiname":"Thevur",
    "gn:country_code":"IN",
    "gn:dem":186,
    "gn:feature_class":"P",
    "gn:feature_code":"PPL",
    "gn:name":"Thev\u016br",
    "gn:population":0,
    "gn:timezone":"Asia/Kolkata",
    "iso:country":"IN",
    "name:bpy_x_preferred":[
        "\u09a5\u09c7\u09ac\u09c1\u09b0"
    ],
    "name:ita_x_preferred":[
        "Thevur"
    ],
    "name:msa_x_preferred":[
        "Thevur"
    ],
    "name:nld_x_preferred":[
        "Thevur"
    ],
    "name:por_x_preferred":[
        "Thevur"
    ],
    "name:tam_x_preferred":[
        "\u0ba4\u0bc7\u0bb5\u0bc2\u0bb0\u0bcd"
    ],
    "name:vie_x_preferred":[
        "Thevur"
    ],
    "name:zho_x_preferred":[
        "\u6cf0\u6b66\u5c14"
    ],
    "wof:name":"Thevur",
    "wof:placetype":"locality"
},
  "geometry": {"coordinates":[77.7539,11.52396],"type":"Point"}
}