{
  "type": "Feature",
  "properties": {
    "gn:admin1_code":"36.0",
    "gn:admin2_code":"182.0",
    "gn:asciiname":"Dhampur",
    "gn:country_code":"IN",
    "gn:dem":137,
    "gn:feature_class":"P",
    "gn:feature_code":"PPL",
    "gn:name":"Dh\u0101mpur",
    "gn:population":0,
    "gn:timezone":"Asia/Kolkata",
    "iso:country":"IN",
    "name:bpy_x_preferred":[
        "\u09a7\u09be\u09ae\u09aa\u09c1\u09b0"
    ],
    "name:ceb_x_preferred":[
        "Dh\u0101mpur"
    ],
    "name:hin_x_preferred":[
        "\u0927\u093e\u092e\u092a\u0941\u0930"
    ],
    "name:ita_x_preferred":[
        "Dhampur"
    ],
    "name:msa_x_preferred":[
        "Dhampur"
    ],
    "name:new_x_preferred":[
        "\u0927\u092e\u094d\u092a\u0941\u0930"
    ],
    "name:nld_x_preferred":[
        "Dhampur"
    ],
    "name:pol_x_preferred":[
        "Dhampur"
    ],
    "name:por_x_preferred":[
        "Dhampur"
    ],
    "name:swe_x_preferred":[
        "Dh\u0101mpur"
    ],
    "name:urd_x_preferred":[
        "\u062f\u06be\u0627\u0645 \u067e\u0648\u0631"
    ],
    "name:vie_x_preferred":[
        "Dhampur"
    ],
    "name:zho_x_preferred":[
        "\u8fbe\u59c6\u666e\u5c14"
    ],
    "wof:name":"Dhampur",
    "wof:placetype":"locality"
},
  "geometry": {"coordinates":[82.24498,27.66463],"type":"Point"}
}