{
  "type": "Feature",
  "properties": {
    "gn:admin1_code":"19.0",
    "gn:admin2_code":"572",
    "gn:asciiname":"Hosa Road",
    "gn:country_code":"IN",
    "gn:dem":927,
    "gn:feature_class":"P",
    "gn:feature_code":"PPL",
    "gn:name":"Hosa Road",
    "gn:population":0,
    "gn:timezone":"Asia/Kolkata",
    "iso:country":"IN",
    "wof:name":"Hosa Road",
    "wof:placetype":"neighbourhood"
},
  "geometry": {"coordinates":[77.65411,12.86929],"type":"Point"}
}