{
  "type": "Feature",
  "properties": {
    "iso:country":"IN",
    "ks:ks_name":"Nondelu",
    "ks:ks_pop":185,
    "ks:ks_type":"HABITATION",
    "name:eng_x_preferred":[
        "Nondelu"
    ],
    "wof:name":"Nondelu",
    "wof:placetype":"locality",
    "wof:population":185
},
  "geometry": {"coordinates":[75.264021,12.890729],"type":"Point"}
}