{
  "type": "Feature",
  "properties": {
    "iso:country":"IN",
    "ks:ks_name":"Ghilazaari",
    "ks:ks_pop":215,
    "ks:ks_type":"HABITATION",
    "name:eng_x_preferred":[
        "Ghilazaari"
    ],
    "wof:name":"Ghilazaari",
    "wof:placetype":"locality",
    "wof:population":215
},
  "geometry": {"coordinates":[90.888278,26.4428],"type":"Point"}
}