{
  "type": "Feature",
  "properties": {
    "iso:country":"IN",
    "ks:ks_name":"Bilegod",
    "ks:ks_pop":51,
    "ks:ks_type":"HABITATION",
    "name:eng_x_preferred":[
        "Bilegod"
    ],
    "wof:name":"Bilegod",
    "wof:placetype":"locality",
    "wof:population":51
},
  "geometry": {"coordinates":[74.847168,14.484607],"type":"Point"}
}