{
  "type": "Feature",
  "properties": {
    "iso:country":"IN",
    "ks:ks_alt_nam":"Naai BASTI",
    "ks:ks_name":"Naai Basti",
    "ks:ks_pop":93,
    "ks:ks_type":"HABITATION",
    "name:eng_x_preferred":[
        "Naai Basti"
    ],
    "wof:name":"Naai Basti",
    "wof:placetype":"locality",
    "wof:population":93
},
  "geometry": {"coordinates":[82.72831499999999,25.297746],"type":"Point"}
}