{
  "type": "Feature",
  "properties": {
    "iso:country":"IN",
    "ks:ks_name":"Dudhichua",
    "ks:ks_pop":241,
    "ks:ks_type":"VILLAGE",
    "name:eng_x_preferred":[
        "Dudhichua"
    ],
    "wof:name":"Dudhichua",
    "wof:placetype":"locality",
    "wof:population":241
},
  "geometry": {"coordinates":[86.854783,24.134054],"type":"Point"}
}