{
  "type": "Feature",
  "properties": {
    "iso:country":"IN",
    "ks:ks_name":"Langso Rengma",
    "ks:ks_pop":93,
    "ks:ks_type":"HABITATION",
    "name:eng_x_preferred":[
        "Langso Rengma"
    ],
    "wof:name":"Langso Rengma",
    "wof:placetype":"locality",
    "wof:population":93
},
  "geometry": {"coordinates":[93.536564,26.394813],"type":"Point"}
}