{
  "type": "Feature",
  "properties": {
    "iso:country":"IN",
    "ks:ks_name":"Beedad",
    "ks:ks_pop":95,
    "ks:ks_type":"HABITATION",
    "name:eng_x_preferred":[
        "Beedad"
    ],
    "wof:name":"Beedad",
    "wof:placetype":"locality",
    "wof:population":95
},
  "geometry": {"coordinates":[82.755111,24.574356],"type":"Point"}
}