{
  "type": "Feature",
  "properties": {
    "iso:country":"IN",
    "ks:ks_alt_nam":"Mandali para",
    "ks:ks_name":"Mandali Para",
    "ks:ks_pop":285,
    "ks:ks_type":"HABITATION",
    "ks:ks_uagg_main":0,
    "name:eng_x_preferred":[
        "Mandali Para"
    ],
    "wof:name":"Mandali Para",
    "wof:placetype":"neighbourhood",
    "wof:population":285
},
  "geometry": {"coordinates":[91.65428300000001,23.005864],"type":"Point"}
}