{
  "type": "Feature",
  "properties": {
    "gn:admin1_code":"24.0",
    "gn:admin2_code":"099",
    "gn:asciiname":"Karru",
    "gn:country_code":"IN",
    "gn:dem":196,
    "gn:feature_class":"P",
    "gn:feature_code":"PPL",
    "gn:name":"Karru",
    "gn:population":0,
    "gn:timezone":"Asia/Kolkata",
    "iso:country":"IN",
    "wof:name":"Karru",
    "wof:placetype":"neighbourhood"
},
  "geometry": {"coordinates":[73.94601,29.09059],"type":"Point"}
}