{
  "type": "Feature",
  "properties": {
    "iso:country":"IN",
    "ks:ks_name":"Kokalakhedi",
    "ks:ks_pop":263,
    "ks:ks_type":"HABITATION",
    "name:eng_x_preferred":[
        "Kokalakhedi"
    ],
    "wof:name":"Kokalakhedi",
    "wof:placetype":"locality",
    "wof:population":263
},
  "geometry": {"coordinates":[75.792401,23.073441],"type":"Point"}
}