{
  "type": "Feature",
  "properties": {
    "iso:country":"IN",
    "ks:ks_name":"Eregara Alias Kasiadih",
    "ks:ks_pop":401,
    "ks:ks_type":"VILLAGE",
    "name:eng_x_preferred":[
        "Eregara Alias Kasiadih"
    ],
    "wof:name":"Eregara Alias Kasiadih",
    "wof:placetype":"locality",
    "wof:population":401
},
  "geometry": {"coordinates":[84.81175500000001,23.9884],"type":"Point"}
}