{
  "type": "Feature",
  "properties": {
    "iso:country":"IN",
    "ks:ks_name":"Vaguvoddugudem",
    "ks:ks_pop":98,
    "ks:ks_type":"HABITATION",
    "name:eng_x_preferred":[
        "Vaguvoddugudem"
    ],
    "wof:name":"Vaguvoddugudem",
    "wof:placetype":"locality",
    "wof:population":98
},
  "geometry": {"coordinates":[81.17842,17.403677],"type":"Point"}
}