{
  "type": "Feature",
  "properties": {
    "iso:country":"IN",
    "ks:ks_alt_nam":"Kannara-Moorkanikara Rd Jn3",
    "ks:ks_name":"Kannara-moorkanikara Rd Jn3",
    "ks:ks_pop":636,
    "ks:ks_type":"HABITATION",
    "ks:ks_uagg_main":0,
    "name:eng_x_preferred":[
        "Kannara-moorkanikara Rd Jn3"
    ],
    "wof:name":"Kannara-moorkanikara Rd Jn3",
    "wof:placetype":"neighbourhood",
    "wof:population":636
},
  "geometry": {"coordinates":[76.29629199999999,10.517891],"type":"Point"}
}