{
  "type": "Feature",
  "properties": {
    "iso:country":"IN",
    "ks:ks_name":"Chander Naik Tanda",
    "ks:ks_pop":42,
    "ks:ks_type":"HABITATION",
    "name:eng_x_preferred":[
        "Chander Naik Tanda"
    ],
    "wof:name":"Chander Naik Tanda",
    "wof:placetype":"locality",
    "wof:population":42
},
  "geometry": {"coordinates":[77.38109,17.011912],"type":"Point"}
}