{
  "type": "Feature",
  "properties": {
    "iso:country":"IN",
    "ks:ks_name":"Glass Khali Purba Para",
    "ks:ks_pop":897,
    "ks:ks_type":"HABITATION",
    "ks:ks_uagg_main":0,
    "name:eng_x_preferred":[
        "Glass Khali Purba Para"
    ],
    "wof:name":"Glass Khali Purba Para",
    "wof:placetype":"neighbourhood",
    "wof:population":897
},
  "geometry": {"coordinates":[88.893552,22.115963],"type":"Point"}
}