{
  "type": "Feature",
  "properties": {
    "iso:country":"IN",
    "ks:ks_name":"Madapur",
    "ks:ks_pop":160,
    "ks:ks_type":"HABITATION",
    "name:eng_x_preferred":[
        "Madapur"
    ],
    "wof:name":"Madapur",
    "wof:placetype":"locality",
    "wof:population":160
},
  "geometry": {"coordinates":[73.28697200000001,23.498361],"type":"Point"}
}