{
  "type": "Feature",
  "properties": {
    "gn:admin1_code":"36",
    "gn:admin2_code":"154.0",
    "gn:asciiname":"Dhanipur",
    "gn:country_code":"IN",
    "gn:dem":125,
    "gn:feature_class":"P",
    "gn:feature_code":"PPL",
    "gn:name":"Dhanipur",
    "gn:population":0,
    "gn:timezone":"Asia/Kolkata",
    "iso:country":"IN",
    "ks:ks_name":"Dhanipur",
    "ks:ks_pop":111,
    "ks:ks_type":"HABITATION",
    "ks:ks_uagg_main":0,
    "name:eng_x_preferred":[
        "Dhanipur"
    ],
    "wof:name":"Dhanipur",
    "wof:placetype":"neighbourhood",
    "wof:population":111
},
  "geometry": {"coordinates":[81.05722900000001,27.485848],"type":"Point"}
}