{
  "type": "Feature",
  "properties": {
    "iso:country":"IN",
    "ks:ks_name":"Suransu",
    "ks:ks_pop":101,
    "ks:ks_type":"VILLAGE",
    "name:eng_x_preferred":[
        "Suransu"
    ],
    "wof:name":"Suransu",
    "wof:placetype":"locality",
    "wof:population":101
},
  "geometry": {"coordinates":[78.00970599999999,30.551941],"type":"Point"}
}