{
  "type": "Feature",
  "properties": {
    "gn:admin1_code":"21",
    "gn:admin2_code":"395.0",
    "gn:asciiname":"Goklamma",
    "gn:country_code":"IN",
    "gn:dem":734,
    "gn:feature_class":"P",
    "gn:feature_code":"PPL",
    "gn:name":"Goklamma",
    "gn:population":0,
    "gn:timezone":"Asia/Kolkata",
    "iso:country":"IN",
    "ks:ks_name":"Gokloma",
    "ks:ks_pop":290,
    "ks:ks_type":"VILLAGE",
    "name:eng_x_preferred":[
        "Gokloma"
    ],
    "name:eng_x_variant":[
        "Goklamma"
    ],
    "wof:name":"Gokloma",
    "wof:placetype":"locality",
    "wof:population":290
},
  "geometry": {"coordinates":[83.107708,19.603028],"type":"Point"}
}