{
  "type": "Feature",
  "properties": {
    "gn:admin1_code":"25.0",
    "gn:admin2_code":"632.0",
    "gn:asciiname":"Manjakambai",
    "gn:country_code":"IN",
    "gn:dem":679,
    "gn:feature_class":"P",
    "gn:feature_code":"PPL",
    "gn:name":"Manjakambai",
    "gn:population":0,
    "gn:timezone":"Asia/Kolkata",
    "iso:country":"IN",
    "wof:name":"Manjakambai",
    "wof:placetype":"locality"
},
  "geometry": {"coordinates":[76.70281,11.24515],"type":"Point"}
}