{
  "type": "Feature",
  "properties": {
    "gn:admin1_code":"21",
    "gn:admin2_code":"385.0",
    "gn:asciiname":"Sarankul",
    "gn:country_code":"IN",
    "gn:dem":103,
    "gn:feature_class":"P",
    "gn:feature_code":"PPL",
    "gn:name":"Sarankul",
    "gn:population":0,
    "gn:timezone":"Asia/Kolkata",
    "iso:country":"IN",
    "ks:ks_name":"Sarankul",
    "ks:ks_pop":4058,
    "ks:ks_type":"VILLAGE",
    "ks:ks_uagg_main":0,
    "name:eng_x_preferred":[
        "Sarankul"
    ],
    "name:ori_x_preferred":[
        "\u0b36\u0b30\u0b23\u0b15\u0b41\u0b33"
    ],
    "wof:name":"Sarankul",
    "wof:placetype":"neighbourhood",
    "wof:population":4058
},
  "geometry": {"coordinates":[85.084648,20.032778],"type":"Point"}
}