{
  "type": "Feature",
  "properties": {
    "iso:country":"IN",
    "ks:ks_name":"Satbhaya",
    "ks:ks_pop":267,
    "ks:ks_type":"VILLAGE",
    "name:eng_x_preferred":[
        "Satbhaya"
    ],
    "wof:name":"Satbhaya",
    "wof:placetype":"locality",
    "wof:population":267
},
  "geometry": {"coordinates":[86.593599,22.153182],"type":"Point"}
}