{
  "type": "Feature",
  "properties": {
    "gn:admin1_code":"35",
    "gn:admin2_code":"430.0",
    "gn:asciiname":"Biradei",
    "gn:country_code":"IN",
    "gn:dem":279,
    "gn:feature_class":"P",
    "gn:feature_code":"PPL",
    "gn:name":"B\u012br\u0101dei",
    "gn:population":0,
    "gn:timezone":"Asia/Kolkata",
    "iso:country":"IN",
    "ks:ks_alt_nam":"Bir\u0101dei",
    "ks:ks_name":"Biradei",
    "ks:ks_pop":2664,
    "ks:ks_type":"VILLAGE",
    "name:eng_x_preferred":[
        "Biradei"
    ],
    "name:eng_x_variant":[
        "Bir\u0101dei"
    ],
    "wof:name":"Biradei",
    "wof:placetype":"locality",
    "wof:population":2664
},
  "geometry": {"coordinates":[82.138012,24.626477],"type":"Point"}
}