{
  "type": "Feature",
  "properties": {
    "iso:country":"IN",
    "ks:ks_name":"Mansha Ka Purwa",
    "ks:ks_pop":100,
    "ks:ks_type":"HABITATION",
    "name:eng_x_preferred":[
        "Mansha Ka Purwa"
    ],
    "wof:name":"Mansha Ka Purwa",
    "wof:placetype":"locality",
    "wof:population":100
},
  "geometry": {"coordinates":[82.026832,26.512183],"type":"Point"}
}