{
  "type": "Feature",
  "properties": {
    "iso:country":"IN",
    "ks:ks_alt_nam":"MALLETIPURAM",
    "ks:ks_name":"Malletipuram",
    "ks:ks_pop":289,
    "ks:ks_type":"HABITATION",
    "name:eng_x_preferred":[
        "Malletipuram"
    ],
    "wof:name":"Malletipuram",
    "wof:placetype":"locality",
    "wof:population":289
},
  "geometry": {"coordinates":[76.954492,14.357609],"type":"Point"}
}