{
  "type": "Feature",
  "properties": {
    "iso:country":"IN",
    "ks:ks_name":"Paria",
    "ks:ks_pop":372,
    "ks:ks_type":"VILLAGE",
    "name:eng_x_preferred":[
        "Paria"
    ],
    "wof:name":"Paria",
    "wof:placetype":"locality",
    "wof:population":372
},
  "geometry": {"coordinates":[86.007042,20.650347],"type":"Point"}
}