{
  "type": "Feature",
  "properties": {
    "iso:country":"IN",
    "ks:ks_name":"Banmunda",
    "ks:ks_pop":140,
    "ks:ks_type":"HABITATION",
    "name:eng_x_preferred":[
        "Banmunda"
    ],
    "wof:name":"Banmunda",
    "wof:placetype":"locality",
    "wof:population":140
},
  "geometry": {"coordinates":[84.686654,22.467],"type":"Point"}
}