{
  "type": "Feature",
  "properties": {
    "iso:country":"IN",
    "ks:ks_name":"Phursodih",
    "ks:ks_pop":1053,
    "ks:ks_type":"VILLAGE",
    "ks:ks_uagg_main":0,
    "name:eng_x_preferred":[
        "Phursodih"
    ],
    "wof:name":"Phursodih",
    "wof:placetype":"neighbourhood",
    "wof:population":1053
},
  "geometry": {"coordinates":[86.36691999999999,24.310722],"type":"Point"}
}