{
  "type": "Feature",
  "properties": {
    "iso:country":"IN",
    "ks:ks_name":"Mithibili",
    "ks:ks_pop":1543,
    "ks:ks_type":"VILLAGE",
    "name:eng_x_preferred":[
        "Mithibili"
    ],
    "wof:name":"Mithibili",
    "wof:placetype":"locality",
    "wof:population":1543
},
  "geometry": {"coordinates":[73.07641700000001,24.205389],"type":"Point"}
}