{
  "type": "Feature",
  "properties": {
    "gn:admin1_code":"19.0",
    "gn:admin2_code":"582.0",
    "gn:asciiname":"Guntibilu",
    "gn:country_code":"IN",
    "gn:dem":772,
    "gn:feature_class":"P",
    "gn:feature_code":"PPL",
    "gn:name":"Guntibilu",
    "gn:population":0,
    "gn:timezone":"Asia/Kolkata",
    "iso:country":"IN",
    "wof:name":"Guntibilu",
    "wof:placetype":"locality"
},
  "geometry": {"coordinates":[77.59231,13.47855],"type":"Point"}
}