{
  "type": "Feature",
  "properties": {
    "iso:country":"IN",
    "ks:ks_name":"Durahati",
    "ks:ks_pop":4476,
    "ks:ks_type":"VILLAGE",
    "name:eng_x_preferred":[
        "Durahati"
    ],
    "wof:name":"Durahati",
    "wof:placetype":"locality",
    "wof:population":4476
},
  "geometry": {"coordinates":[89.85597,26.028637],"type":"Point"}
}