{
  "type": "Feature",
  "properties": {
    "iso:country":"IN",
    "ks:ks_name":"20 DPN",
    "ks:ks_pop":48,
    "ks:ks_type":"VILLAGE",
    "name:eng_x_preferred":[
        "20 DPN"
    ],
    "wof:name":"20 DPN",
    "wof:placetype":"locality",
    "wof:population":48
},
  "geometry": {"coordinates":[74.930634,29.192619],"type":"Point"}
}