{
  "type": "Feature",
  "properties": {
    "iso:country":"IN",
    "ks:ks_name":"Khalchiwadi",
    "ks:ks_pop":211,
    "ks:ks_type":"HABITATION",
    "name:eng_x_preferred":[
        "Khalchiwadi"
    ],
    "wof:name":"Khalchiwadi",
    "wof:placetype":"locality",
    "wof:population":211
},
  "geometry": {"coordinates":[73.573919,16.591613],"type":"Point"}
}