{
  "type": "Feature",
  "properties": {
    "gn:admin1_code":"37",
    "gn:admin2_code":"415.0",
    "gn:asciiname":"Alkanhar",
    "gn:country_code":"IN",
    "gn:dem":338,
    "gn:feature_class":"P",
    "gn:feature_code":"PPL",
    "gn:name":"\u0100lkanh\u0101r",
    "gn:population":0,
    "gn:timezone":"Asia/Kolkata",
    "iso:country":"IN",
    "wof:name":"Alkanhar",
    "wof:placetype":"locality"
},
  "geometry": {"coordinates":[80.95263,20.05709],"type":"Point"}
}