{
  "type": "Feature",
  "properties": {
    "iso:country":"IN",
    "ks:ks_alt_nam":"Lodangi bavi",
    "ks:ks_name":"Lodangi Bavi",
    "ks:ks_pop":45,
    "ks:ks_type":"HABITATION",
    "name:eng_x_preferred":[
        "Lodangi Bavi"
    ],
    "wof:name":"Lodangi Bavi",
    "wof:placetype":"locality",
    "wof:population":45
},
  "geometry": {"coordinates":[79.289326,17.334011],"type":"Point"}
}