{
  "type": "Feature",
  "properties": {
    "gn:admin1_code":"37.0",
    "gn:admin2_code":"417.0",
    "gn:asciiname":"Midtul",
    "gn:country_code":"IN",
    "gn:dem":359,
    "gn:feature_class":"P",
    "gn:feature_code":"PPLL",
    "gn:name":"Midtul",
    "gn:population":0,
    "gn:timezone":"Asia/Kolkata",
    "iso:country":"IN",
    "wof:name":"Midtul",
    "wof:placetype":"locality"
},
  "geometry": {"coordinates":[81.16285000000001,18.87558],"type":"Point"}
}