{
  "type": "Feature",
  "properties": {
    "iso:country":"IN",
    "ks:ks_name":"Vichapara",
    "ks:ks_pop":304,
    "ks:ks_type":"HABITATION",
    "name:eng_x_preferred":[
        "Vichapara"
    ],
    "wof:name":"Vichapara",
    "wof:placetype":"locality",
    "wof:population":304
},
  "geometry": {"coordinates":[81.314173,18.602535],"type":"Point"}
}