{
  "type": "Feature",
  "properties": {
    "iso:country":"IN",
    "ks:ks_name":"Bhutipada",
    "ks:ks_pop":5,
    "ks:ks_type":"HABITATION",
    "name:eng_x_preferred":[
        "Bhutipada"
    ],
    "wof:name":"Bhutipada",
    "wof:placetype":"locality",
    "wof:population":5
},
  "geometry": {"coordinates":[86.715463,21.954619],"type":"Point"}
}