{
  "type": "Feature",
  "properties": {
    "iso:country":"IN",
    "ks:ks_alt_nam":"T\u0101lbah\u0101li",
    "ks:ks_name":"Talbahali",
    "ks:ks_type":"VILLAGE",
    "name:eng_x_preferred":[
        "Talbahali"
    ],
    "name:eng_x_variant":[
        "T\u0101lbah\u0101li"
    ],
    "wof:name":"Talbahali",
    "wof:placetype":"locality"
},
  "geometry": {"coordinates":[85.068213,21.793019],"type":"Point"}
}