{
  "type": "Feature",
  "properties": {
    "iso:country":"IN",
    "ks:ks_name":"Balirbond",
    "ks:ks_pop":304,
    "ks:ks_type":"HABITATION",
    "name:eng_x_preferred":[
        "Balirbond"
    ],
    "wof:name":"Balirbond",
    "wof:placetype":"locality",
    "wof:population":304
},
  "geometry": {"coordinates":[92.638639,24.860741],"type":"Point"}
}