{
  "type": "Feature",
  "properties": {
    "iso:country":"IN",
    "ks:ks_name":"Umakant Nagar",
    "ks:ks_pop":64,
    "ks:ks_type":"HABITATION",
    "name:eng_x_preferred":[
        "Umakant Nagar"
    ],
    "wof:name":"Umakant Nagar",
    "wof:placetype":"locality",
    "wof:population":64
},
  "geometry": {"coordinates":[75.96709,17.686118],"type":"Point"}
}