{
  "type": "Feature",
  "properties": {
    "iso:country":"IN",
    "ks:ks_name":"Basai",
    "ks:ks_pop":7833,
    "ks:ks_type":"VILLAGE",
    "ks:ks_uagg_main":0,
    "name:eng_x_preferred":[
        "Basai"
    ],
    "wof:name":"Basai",
    "wof:placetype":"locality",
    "wof:population":7833
},
  "geometry": {"coordinates":[88.31638,22.694503],"type":"Point"}
}