{
  "type": "Feature",
  "properties": {
    "iso:country":"IN",
    "ks:ks_alt_nam":"Chhind\u0101r\u012b",
    "ks:ks_name":"Chhindari",
    "ks:ks_pop":129,
    "ks:ks_type":"VILLAGE",
    "name:eng_x_preferred":[
        "Chhindari"
    ],
    "name:eng_x_variant":[
        "Chhind\u0101r\u012b"
    ],
    "wof:name":"Chhindari",
    "wof:placetype":"locality",
    "wof:population":129
},
  "geometry": {"coordinates":[80.91225799999999,21.543346],"type":"Point"}
}