{
  "type": "Feature",
  "properties": {
    "gn:admin1_code":"11",
    "gn:admin2_code":"27.0",
    "gn:asciiname":"Jaral",
    "gn:country_code":"IN",
    "gn:dem":1149,
    "gn:feature_class":"P",
    "gn:feature_code":"PPL",
    "gn:name":"Jaral",
    "gn:population":0,
    "gn:timezone":"Asia/Kolkata",
    "iso:country":"IN",
    "wof:name":"Jaral",
    "wof:placetype":"locality"
},
  "geometry": {"coordinates":[76.95690999999999,31.49228],"type":"Point"}
}