{
  "type": "Feature",
  "properties": {
    "iso:country":"IN",
    "ks:ks_name":"Tengapur No 1",
    "ks:ks_pop":168,
    "ks:ks_type":"VILLAGE",
    "ks:ks_uagg_main":0,
    "name:eng_x_preferred":[
        "Tengapur No 1"
    ],
    "wof:name":"Tengapur No 1",
    "wof:placetype":"neighbourhood",
    "wof:population":168
},
  "geometry": {"coordinates":[94.474744,27.40468],"type":"Point"}
}