{
  "type": "Feature",
  "properties": {
    "iso:country":"IN",
    "ks:ks_name":"Huthrabail Kuchur",
    "ks:ks_pop":69,
    "ks:ks_type":"HABITATION",
    "name:eng_x_preferred":[
        "Huthrabail Kuchur"
    ],
    "wof:name":"Huthrabail Kuchur",
    "wof:placetype":"locality",
    "wof:population":69
},
  "geometry": {"coordinates":[75.015422,13.501357],"type":"Point"}
}