{
  "type": "Feature",
  "properties": {
    "gn:admin1_code":"35.0",
    "gn:admin2_code":"418.0",
    "gn:asciiname":"Bamauri",
    "gn:country_code":"IN",
    "gn:dem":247,
    "gn:feature_class":"P",
    "gn:feature_code":"PPL",
    "gn:name":"Bamauri",
    "gn:population":0,
    "gn:timezone":"Asia/Kolkata",
    "iso:country":"IN",
    "wof:name":"Bamauri",
    "wof:placetype":"neighbourhood"
},
  "geometry": {"coordinates":[76.67505,25.59278],"type":"Point"}
}