{
  "type": "Feature",
  "properties": {
    "gn:admin1_code":"19.0",
    "gn:admin2_code":"571.0",
    "gn:asciiname":"Manchkalkupi",
    "gn:country_code":"IN",
    "gn:dem":846,
    "gn:feature_class":"P",
    "gn:feature_code":"PPL",
    "gn:name":"Manchkalkupi",
    "gn:population":0,
    "gn:timezone":"Asia/Kolkata",
    "iso:country":"IN",
    "wof:name":"Manchkalkupi",
    "wof:placetype":"locality"
},
  "geometry": {"coordinates":[77.16999,13.29772],"type":"Point"}
}