{
  "type": "Feature",
  "properties": {
    "iso:country":"IN",
    "ks:ks_alt_nam":"PAPER MILL",
    "ks:ks_name":"Paper Mill",
    "ks:ks_pop":50,
    "ks:ks_type":"HABITATION",
    "name:eng_x_preferred":[
        "Paper Mill"
    ],
    "wof:name":"Paper Mill",
    "wof:placetype":"locality",
    "wof:population":50
},
  "geometry": {"coordinates":[74.946883,16.987172],"type":"Point"}
}