{
  "type": "Feature",
  "properties": {
    "iso:country":"IN",
    "ks:ks_alt_nam":"MAHALAXMI COLONY",
    "ks:ks_name":"Mahalaxmi Colony",
    "ks:ks_pop":775,
    "ks:ks_type":"HABITATION",
    "ks:ks_uagg_main":0,
    "name:eng_x_preferred":[
        "Mahalaxmi Colony"
    ],
    "wof:name":"Mahalaxmi Colony",
    "wof:placetype":"neighbourhood",
    "wof:population":775
},
  "geometry": {"coordinates":[88.76465399999999,26.707943],"type":"Point"}
}