{
  "type": "Feature",
  "properties": {
    "gn:admin1_code":"21.0",
    "gn:admin2_code":"385.0",
    "gn:asciiname":"Dalak",
    "gn:country_code":"IN",
    "gn:dem":152,
    "gn:feature_class":"P",
    "gn:feature_code":"PPL",
    "gn:name":"Dalak",
    "gn:population":0,
    "gn:timezone":"Asia/Kolkata",
    "iso:country":"IN",
    "wof:name":"Dalak",
    "wof:placetype":"locality"
},
  "geometry": {"coordinates":[84.98305000000001,20.01137],"type":"Point"}
}