{
  "type": "Feature",
  "properties": {
    "iso:country":"IN",
    "ks:ks_name":"Bhatpurwa Khurd",
    "ks:ks_pop":401,
    "ks:ks_type":"HABITATION",
    "name:eng_x_preferred":[
        "Bhatpurwa Khurd"
    ],
    "wof:name":"Bhatpurwa Khurd",
    "wof:placetype":"locality",
    "wof:population":401
},
  "geometry": {"coordinates":[81.129096,28.019561],"type":"Point"}
}