{
  "type": "Feature",
  "properties": {
    "gn:admin1_code":"39.0",
    "gn:admin2_code":"65.0",
    "gn:asciiname":"Kande",
    "gn:country_code":"IN",
    "gn:dem":1377,
    "gn:feature_class":"P",
    "gn:feature_code":"PPL",
    "gn:name":"K\u0101nde",
    "gn:population":0,
    "gn:timezone":"Asia/Kolkata",
    "iso:country":"IN",
    "name:ceb_x_preferred":[
        "Kande"
    ],
    "name:swe_x_preferred":[
        "Kande"
    ],
    "wof:name":"Kande",
    "wof:placetype":"locality"
},
  "geometry": {"coordinates":[79.93087,29.31167],"type":"Point"}
}