{
  "type": "Feature",
  "properties": {
    "iso:country":"IN",
    "ks:ks_name":"Kenchihalli",
    "ks:ks_type":"VILLAGE",
    "name:eng_x_preferred":[
        "Kenchihalli"
    ],
    "wof:name":"Kenchihalli",
    "wof:placetype":"locality"
},
  "geometry": {"coordinates":[76.35204400000001,13.955814],"type":"Point"}
}