{
  "type": "Feature",
  "properties": {
    "iso:country":"IN",
    "ks:ks_name":"Rud Reserved Forest",
    "ks:ks_type":"VILLAGE",
    "name:eng_x_preferred":[
        "Rud Reserved Forest"
    ],
    "wof:name":"Rud Reserved Forest",
    "wof:placetype":"locality"
},
  "geometry": {"coordinates":[84.282383,23.56191],"type":"Point"}
}