{
  "type": "Feature",
  "properties": {
    "iso:country":"IN",
    "ks:ks_name":"Dadhawa",
    "ks:ks_pop":152,
    "ks:ks_type":"HABITATION",
    "ks:ks_uagg_main":0,
    "name:eng_x_preferred":[
        "Dadhawa"
    ],
    "wof:name":"Dadhawa",
    "wof:placetype":"neighbourhood",
    "wof:population":152
},
  "geometry": {"coordinates":[82.89279999999999,26.354528],"type":"Point"}
}