{
  "type": "Feature",
  "properties": {
    "iso:country":"IN",
    "ks:ks_name":"7 LGW-B",
    "ks:ks_pop":124,
    "ks:ks_type":"VILLAGE",
    "name:eng_x_preferred":[
        "7 LGW-B"
    ],
    "wof:name":"7 LGW-B",
    "wof:placetype":"locality",
    "wof:population":124
},
  "geometry": {"coordinates":[74.06351100000001,29.540172],"type":"Point"}
}