{
  "type": "Feature",
  "properties": {
    "gn:admin1_code":"19.0",
    "gn:admin2_code":"583.0",
    "gn:asciiname":"Vadrapalya",
    "gn:country_code":"IN",
    "gn:dem":889,
    "gn:feature_class":"P",
    "gn:feature_code":"PPL",
    "gn:name":"Vadrap\u0101lya",
    "gn:population":0,
    "gn:timezone":"Asia/Kolkata",
    "iso:country":"IN",
    "ks:ks_name":"Vaddarapalya",
    "ks:ks_pop":257,
    "ks:ks_type":"HABITATION",
    "name:eng_x_preferred":[
        "Vaddarapalya"
    ],
    "name:eng_x_variant":[
        "Vadrapalya"
    ],
    "wof:name":"Vaddarapalya",
    "wof:placetype":"locality",
    "wof:population":257
},
  "geometry": {"coordinates":[77.381913,13.137196],"type":"Point"}
}