{
  "type": "Feature",
  "properties": {
    "iso:country":"IN",
    "ks:ks_name":"Dhundhwani",
    "ks:ks_pop":210,
    "ks:ks_type":"HABITATION",
    "name:eng_x_preferred":[
        "Dhundhwani"
    ],
    "wof:name":"Dhundhwani",
    "wof:placetype":"locality",
    "wof:population":210
},
  "geometry": {"coordinates":[77.990746,22.991889],"type":"Point"}
}