{
  "type": "Feature",
  "properties": {
    "gn:admin1_code":"10.0",
    "gn:admin2_code":"78.0",
    "gn:asciiname":"Bharpur",
    "gn:country_code":"IN",
    "gn:dem":217,
    "gn:feature_class":"P",
    "gn:feature_code":"PPL",
    "gn:name":"Bharpur",
    "gn:population":0,
    "gn:timezone":"Asia/Kolkata",
    "iso:country":"IN",
    "name:fas_x_preferred":[
        "\u0628\u0647\u0631\u067e\u0648\u0631"
    ],
    "name:hin_x_preferred":[
        "\u092d\u0930\u092a\u0941\u0930"
    ],
    "name:urd_x_preferred":[
        "\u0628\u06be\u0631\u067e\u0648\u0631\u06a9\u0644\u0627\u06ba"
    ],
    "wof:name":"Bharpur",
    "wof:placetype":"locality"
},
  "geometry": {"coordinates":[75.53834000000001,29.65711],"type":"Point"}
}