{
  "type": "Feature",
  "properties": {
    "gn:admin1_code":"36.0",
    "gn:admin2_code":"150.0",
    "gn:asciiname":"Ladpur",
    "gn:country_code":"IN",
    "gn:dem":175,
    "gn:feature_class":"P",
    "gn:feature_code":"PPL",
    "gn:name":"L\u0101dpur",
    "gn:population":0,
    "gn:timezone":"Asia/Kolkata",
    "iso:country":"IN",
    "ks:ks_alt_nam":"L\u0101dpur",
    "ks:ks_name":"Ladpur",
    "ks:ks_pop":4044,
    "ks:ks_type":"VILLAGE",
    "name:eng_x_preferred":[
        "Ladpur"
    ],
    "name:eng_x_variant":[
        "L\u0101dpur"
    ],
    "wof:name":"Ladpur",
    "wof:placetype":"locality",
    "wof:population":4044
},
  "geometry": {"coordinates":[79.497883,28.483257],"type":"Point"}
}