{
  "type": "Feature",
  "properties": {
    "gn:admin1_code":"35.0",
    "gn:admin2_code":"466.0",
    "gn:asciiname":"Dukhiya",
    "gn:country_code":"IN",
    "gn:dem":216,
    "gn:feature_class":"P",
    "gn:feature_code":"PPL",
    "gn:name":"Dukh\u012bya",
    "gn:population":0,
    "gn:timezone":"Asia/Kolkata",
    "iso:country":"IN",
    "wof:name":"Dukhiya",
    "wof:placetype":"locality"
},
  "geometry": {"coordinates":[76.14285,22.22981],"type":"Point"}
}