{
  "type": "Feature",
  "properties": {
    "iso:country":"IN",
    "ks:ks_name":"Chatamatha",
    "ks:ks_pop":400,
    "ks:ks_type":"HABITATION",
    "name:eng_x_preferred":[
        "Chatamatha"
    ],
    "wof:name":"Chatamatha",
    "wof:placetype":"locality",
    "wof:population":400
},
  "geometry": {"coordinates":[74.366466,14.501718],"type":"Point"}
}