{
  "type": "Feature",
  "properties": {
    "iso:country":"IN",
    "ks:ks_alt_nam":"kamatchipuram",
    "ks:ks_name":"Kamatchipuram",
    "ks:ks_pop":230,
    "ks:ks_type":"HABITATION",
    "name:eng_x_preferred":[
        "Kamatchipuram"
    ],
    "wof:name":"Kamatchipuram",
    "wof:placetype":"locality",
    "wof:population":230
},
  "geometry": {"coordinates":[77.722567,10.08256],"type":"Point"}
}