{
  "type": "Feature",
  "properties": {
    "iso:country":"IN",
    "ks:ks_alt_nam":"MUSHNADAHA",
    "ks:ks_name":"Mushnadaha",
    "ks:ks_pop":428,
    "ks:ks_type":"HABITATION",
    "name:eng_x_preferred":[
        "Mushnadaha"
    ],
    "wof:name":"Mushnadaha",
    "wof:placetype":"locality",
    "wof:population":428
},
  "geometry": {"coordinates":[87.766656,24.360402],"type":"Point"}
}