{
  "type": "Feature",
  "properties": {
    "gn:admin1_code":"12.0",
    "gn:asciiname":"Langar",
    "gn:country_code":"IN",
    "gn:dem":656,
    "gn:feature_class":"P",
    "gn:feature_code":"PPL",
    "gn:name":"Langar",
    "gn:population":0,
    "gn:timezone":"Asia/Kolkata",
    "iso:country":"IN",
    "name:ceb_x_preferred":[
        "Langar"
    ],
    "name:deu_x_preferred":[
        "Langar"
    ],
    "name:swe_x_preferred":[
        "Langar"
    ],
    "name:urd_x_preferred":[
        "\u0644\u0646\u06af\u0631"
    ],
    "name:uzb_x_preferred":[
        "Langar"
    ],
    "wof:name":"Langar",
    "wof:placetype":"locality"
},
  "geometry": {"coordinates":[74.17666,33.16015],"type":"Point"}
}