{
  "type": "Feature",
  "properties": {
    "iso:country":"IN",
    "ks:ks_name":"Badabandhapali",
    "ks:ks_pop":0,
    "ks:ks_type":"VILLAGE",
    "name:eng_x_preferred":[
        "Badabandhapali"
    ],
    "wof:name":"Badabandhapali",
    "wof:placetype":"locality",
    "wof:population":0
},
  "geometry": {"coordinates":[85.166692,19.847134],"type":"Point"}
}