{
  "type": "Feature",
  "properties": {
    "iso:country":"IN",
    "ks:ks_name":"Yadav Deeh",
    "ks:ks_pop":120,
    "ks:ks_type":"HABITATION",
    "name:eng_x_preferred":[
        "Yadav Deeh"
    ],
    "wof:name":"Yadav Deeh",
    "wof:placetype":"locality",
    "wof:population":120
},
  "geometry": {"coordinates":[83.186181,27.283503],"type":"Point"}
}