{
  "type": "Feature",
  "properties": {
    "gn:admin1_code":"36",
    "gn:admin2_code":"199.0",
    "gn:asciiname":"Tulangi",
    "gn:country_code":"IN",
    "gn:dem":221,
    "gn:feature_class":"P",
    "gn:feature_code":"PPL",
    "gn:name":"Tulangi",
    "gn:population":0,
    "gn:timezone":"Asia/Kolkata",
    "iso:country":"IN",
    "ks:ks_name":"Tulangi",
    "ks:ks_type":"VILLAGE",
    "name:eng_x_preferred":[
        "Tulangi"
    ],
    "wof:name":"Tulangi",
    "wof:placetype":"locality"
},
  "geometry": {"coordinates":[82.502233,24.92179],"type":"Point"}
}