{
  "type": "Feature",
  "properties": {
    "iso:country":"IN",
    "ks:ks_name":"Konganaikandoddi",
    "ks:ks_pop":65,
    "ks:ks_type":"VILLAGE",
    "name:eng_x_preferred":[
        "Konganaikandoddi"
    ],
    "wof:name":"Konganaikandoddi",
    "wof:placetype":"locality",
    "wof:population":65
},
  "geometry": {"coordinates":[76.800338,15.882226],"type":"Point"}
}