{
  "type": "Feature",
  "properties": {
    "gn:admin1_code":"23.0",
    "gn:admin2_code":"41.0",
    "gn:asciiname":"Begowal",
    "gn:country_code":"IN",
    "gn:dem":261,
    "gn:feature_class":"P",
    "gn:feature_code":"PPL",
    "gn:name":"Begow\u0101l",
    "gn:population":0,
    "gn:timezone":"Asia/Kolkata",
    "iso:country":"IN",
    "name:ben_x_preferred":[
        "\u09ac\u09c7\u0997\u09cb\u0993\u09af\u09bc\u09be\u09b2"
    ],
    "name:bpy_x_preferred":[
        "\u09ac\u09c7\u0997\u09cb\u09f1\u09be\u09b2"
    ],
    "name:ceb_x_preferred":[
        "Begow\u0101l"
    ],
    "name:ita_x_preferred":[
        "Begowal"
    ],
    "name:msa_x_preferred":[
        "Begowal"
    ],
    "name:new_x_preferred":[
        "\u092c\u0947\u0917\u094b\u0935\u093e\u0932"
    ],
    "name:nld_x_preferred":[
        "Begowal"
    ],
    "name:por_x_preferred":[
        "Begowal"
    ],
    "name:swe_x_preferred":[
        "Begow\u0101l"
    ],
    "name:vie_x_preferred":[
        "Begowal"
    ],
    "name:zho_x_preferred":[
        "\u8d1d\u6208\u74e6\u5c14"
    ],
    "wof:name":"Begowal",
    "wof:placetype":"locality"
},
  "geometry": {"coordinates":[76.06273,30.81071],"type":"Point"}
}