{
  "type": "Feature",
  "properties": {
    "iso:country":"IN",
    "ks:ks_name":"Chhinari",
    "ks:ks_pop":625,
    "ks:ks_type":"VILLAGE",
    "name:eng_x_preferred":[
        "Chhinari"
    ],
    "wof:name":"Chhinari",
    "wof:placetype":"locality",
    "wof:population":625
},
  "geometry": {"coordinates":[81.421727,19.563005],"type":"Point"}
}