{
  "type": "Feature",
  "properties": {
    "iso:country":"IN",
    "ks:ks_name":"Sekh Toli",
    "ks:ks_pop":1484,
    "ks:ks_type":"HABITATION",
    "ks:ks_uagg_main":0,
    "name:eng_x_preferred":[
        "Sekh Toli"
    ],
    "wof:name":"Sekh Toli",
    "wof:placetype":"neighbourhood",
    "wof:population":1484
},
  "geometry": {"coordinates":[84.633152,26.726379],"type":"Point"}
}