{
  "type": "Feature",
  "properties": {
    "iso:country":"IN",
    "ks:ks_name":"Balwa",
    "ks:ks_pop":2203,
    "ks:ks_type":"VILLAGE",
    "name:eng_x_preferred":[
        "Balwa"
    ],
    "wof:name":"Balwa",
    "wof:placetype":"locality",
    "wof:population":2203
},
  "geometry": {"coordinates":[86.54299399999999,26.132672],"type":"Point"}
}