{
  "type": "Feature",
  "properties": {
    "iso:country":"IN",
    "ks:ks_name":"Rama Ki Bhagal",
    "ks:ks_pop":119,
    "ks:ks_type":"VILLAGE",
    "ks:ks_uagg_main":0,
    "name:eng_x_preferred":[
        "Rama Ki Bhagal"
    ],
    "wof:name":"Rama Ki Bhagal",
    "wof:placetype":"neighbourhood",
    "wof:population":119
},
  "geometry": {"coordinates":[74.20675,24.541664],"type":"Point"}
}