{
  "type": "Feature",
  "properties": {
    "iso:country":"IN",
    "ks:ks_alt_nam":"KHARAT VASTI",
    "ks:ks_name":"Kharat Vasti",
    "ks:ks_pop":76,
    "ks:ks_type":"HABITATION",
    "name:eng_x_preferred":[
        "Kharat Vasti"
    ],
    "wof:name":"Kharat Vasti",
    "wof:placetype":"locality",
    "wof:population":76
},
  "geometry": {"coordinates":[74.93461000000001,16.892843],"type":"Point"}
}