{
  "type": "Feature",
  "properties": {
    "iso:country":"IN",
    "ks:ks_name":"Radhikapur",
    "ks:ks_pop":1735,
    "ks:ks_type":"HABITATION",
    "ks:ks_uagg_main":0,
    "name:eng_x_preferred":[
        "Radhikapur"
    ],
    "wof:name":"Radhikapur",
    "wof:placetype":"neighbourhood",
    "wof:population":1735
},
  "geometry": {"coordinates":[87.846875,25.439783],"type":"Point"}
}