{
  "type": "Feature",
  "properties": {
    "gn:admin1_code":"19.0",
    "gn:admin2_code":"583.0",
    "gn:asciiname":"Karhalli",
    "gn:country_code":"IN",
    "gn:dem":862,
    "gn:feature_class":"P",
    "gn:feature_code":"PPL",
    "gn:name":"Karhalli",
    "gn:population":0,
    "gn:timezone":"Asia/Kolkata",
    "iso:country":"IN",
    "ks:ks_name":"Karehalli",
    "ks:ks_pop":378,
    "ks:ks_type":"VILLAGE",
    "ks:ks_uagg_main":0,
    "name:eng_x_preferred":[
        "Karehalli"
    ],
    "wof:name":"Karehalli",
    "wof:placetype":"neighbourhood",
    "wof:population":378
},
  "geometry": {"coordinates":[77.952388,13.21168],"type":"Point"}
}