{
  "type": "Feature",
  "properties": {
    "iso:country":"IN",
    "ks:ks_name":"Bahora Taluka Arangi",
    "ks:ks_pop":442,
    "ks:ks_type":"VILLAGE",
    "name:eng_x_preferred":[
        "Bahora Taluka Arangi"
    ],
    "wof:name":"Bahora Taluka Arangi",
    "wof:placetype":"locality",
    "wof:population":442
},
  "geometry": {"coordinates":[83.493604,25.315459],"type":"Point"}
}