{
  "type": "Feature",
  "properties": {
    "iso:country":"IN",
    "ks:ks_name":"Kavalli",
    "ks:ks_pop":40,
    "ks:ks_type":"HABITATION",
    "name:eng_x_preferred":[
        "Kavalli"
    ],
    "wof:name":"Kavalli",
    "wof:placetype":"locality",
    "wof:population":40
},
  "geometry": {"coordinates":[74.85175,14.685919],"type":"Point"}
}