{
  "type": "Feature",
  "properties": {
    "iso:country":"IN",
    "ks:ks_name":"Uttar Rampur",
    "ks:ks_pop":454,
    "ks:ks_type":"VILLAGE",
    "name:eng_x_preferred":[
        "Uttar Rampur"
    ],
    "wof:name":"Uttar Rampur",
    "wof:placetype":"locality",
    "wof:population":454
},
  "geometry": {"coordinates":[87.696196,21.842914],"type":"Point"}
}