{
  "type": "Feature",
  "properties": {
    "gn:admin1_code":"23.0",
    "gn:admin2_code":"042",
    "gn:asciiname":"Chirak",
    "gn:country_code":"IN",
    "gn:dem":223,
    "gn:feature_class":"P",
    "gn:feature_code":"PPL",
    "gn:name":"Chirak",
    "gn:population":0,
    "gn:timezone":"Asia/Kolkata",
    "iso:country":"IN",
    "name:eng_x_preferred":[
        "Charik"
    ],
    "name:eng_x_variant":[
        "Chirak"
    ],
    "name:und_x_variant":[
        "Sub-tahsil"
    ],
    "wof:name":"Charik",
    "wof:placetype":"neighbourhood"
},
  "geometry": {"coordinates":[75.17176000000001,30.7206],"type":"Point"}
}