{
  "type": "Feature",
  "properties": {
    "iso:country":"IN",
    "ks:ks_name":"Katamarajumitta",
    "ks:ks_pop":49,
    "ks:ks_type":"HABITATION",
    "ks:ks_uagg_main":0,
    "name:eng_x_preferred":[
        "Katamarajumitta"
    ],
    "wof:name":"Katamarajumitta",
    "wof:placetype":"neighbourhood",
    "wof:population":49
},
  "geometry": {"coordinates":[79.287188,13.614084],"type":"Point"}
}