{
  "type": "Feature",
  "properties": {
    "iso:country":"IN",
    "ks:ks_alt_nam":"YADAV DESAI WASTI",
    "ks:ks_name":"Yadav Desai Wasti",
    "ks:ks_pop":80,
    "ks:ks_type":"HABITATION",
    "name:eng_x_preferred":[
        "Yadav Desai Wasti"
    ],
    "wof:name":"Yadav Desai Wasti",
    "wof:placetype":"locality",
    "wof:population":80
},
  "geometry": {"coordinates":[75.00363299999999,17.141028],"type":"Point"}
}