{
  "type": "Feature",
  "properties": {
    "iso:country":"IN",
    "ks:ks_alt_nam":"D.Nayunivaripalli",
    "ks:ks_name":"D.nayunivaripalli",
    "ks:ks_pop":54,
    "ks:ks_type":"HABITATION",
    "name:eng_x_preferred":[
        "D.nayunivaripalli"
    ],
    "wof:name":"D.nayunivaripalli",
    "wof:placetype":"locality",
    "wof:population":54
},
  "geometry": {"coordinates":[78.883683,14.106636],"type":"Point"}
}