{
  "type": "Feature",
  "properties": {
    "iso:country":"IN",
    "ks:ks_name":"Naval Para Falia",
    "ks:ks_pop":619,
    "ks:ks_type":"HABITATION",
    "name:eng_x_preferred":[
        "Naval Para Falia"
    ],
    "wof:name":"Naval Para Falia",
    "wof:placetype":"locality",
    "wof:population":619
},
  "geometry": {"coordinates":[74.084722,23.242222],"type":"Point"}
}