{
  "type": "Feature",
  "properties": {
    "iso:country":"IN",
    "ks:ks_name":"Sagwara",
    "ks:ks_pop":1185,
    "ks:ks_type":"VILLAGE",
    "name:eng_x_preferred":[
        "Sagwara"
    ],
    "wof:name":"Sagwara",
    "wof:placetype":"locality",
    "wof:population":1185
},
  "geometry": {"coordinates":[73.531098,24.156401],"type":"Point"}
}