{
  "type": "Feature",
  "properties": {
    "iso:country":"IN",
    "ks:ks_name":"N. Maharam",
    "ks:ks_pop":753,
    "ks:ks_type":"HABITATION",
    "ks:ks_uagg_main":0,
    "name:eng_x_preferred":[
        "N. Maharam"
    ],
    "wof:name":"N. Maharam",
    "wof:placetype":"neighbourhood",
    "wof:population":753
},
  "geometry": {"coordinates":[78.655834,26.958067],"type":"Point"}
}