{
  "type": "Feature",
  "properties": {
    "gn:admin1_code":"39.0",
    "gn:admin2_code":"61.0",
    "gn:asciiname":"Antpur",
    "gn:country_code":"IN",
    "gn:dem":1706,
    "gn:feature_class":"P",
    "gn:feature_code":"PPL",
    "gn:name":"Antpur",
    "gn:population":0,
    "gn:timezone":"Asia/Kolkata",
    "iso:country":"IN",
    "ks:ks_name":"Antpur",
    "ks:ks_pop":19,
    "ks:ks_type":"VILLAGE",
    "name:ben_x_preferred":[
        "\u0986\u0981\u099f\u09aa\u09c1\u09b0"
    ],
    "name:deu_x_preferred":[
        "Antpur"
    ],
    "name:eng_x_preferred":[
        "Antpur"
    ],
    "wof:name":"Antpur",
    "wof:placetype":"locality",
    "wof:population":19
},
  "geometry": {"coordinates":[79.002008,29.861252],"type":"Point"}
}