{
  "type": "Feature",
  "properties": {
    "iso:country":"IN",
    "ks:ks_name":"Pitehara",
    "ks:ks_pop":97,
    "ks:ks_type":"VILLAGE",
    "name:eng_x_preferred":[
        "Pitehara"
    ],
    "wof:name":"Pitehara",
    "wof:placetype":"locality",
    "wof:population":97
},
  "geometry": {"coordinates":[79.36952700000001,22.878942],"type":"Point"}
}