{
  "type": "Feature",
  "properties": {
    "iso:country":"IN",
    "ks:ks_name":"Unjapalayam",
    "ks:ks_pop":650,
    "ks:ks_type":"VILLAGE",
    "name:eng_x_preferred":[
        "Unjapalayam"
    ],
    "wof:name":"Unjapalayam",
    "wof:placetype":"locality",
    "wof:population":650
},
  "geometry": {"coordinates":[77.523976,11.326865],"type":"Point"}
}