{
  "type": "Feature",
  "properties": {
    "iso:country":"IN",
    "ks:ks_name":"Chhatra Pal",
    "ks:ks_pop":542,
    "ks:ks_type":"HABITATION",
    "name:eng_x_preferred":[
        "Chhatra Pal"
    ],
    "wof:name":"Chhatra Pal",
    "wof:placetype":"locality",
    "wof:population":542
},
  "geometry": {"coordinates":[86.81152299999999,25.138643],"type":"Point"}
}