{
  "type": "Feature",
  "properties": {
    "iso:country":"IN",
    "ks:ks_name":"Ahamadpur",
    "ks:ks_pop":247,
    "ks:ks_type":"VILLAGE",
    "ks:ks_uagg_main":0,
    "name:eng_x_preferred":[
        "Ahamadpur"
    ],
    "wof:name":"Ahamadpur",
    "wof:placetype":"neighbourhood",
    "wof:population":247
},
  "geometry": {"coordinates":[82.698267,25.812643],"type":"Point"}
}