{
  "type": "Feature",
  "properties": {
    "iso:country":"IN",
    "ks:ks_name":"Sabdhakarpara",
    "ks:ks_pop":52,
    "ks:ks_type":"HABITATION",
    "name:eng_x_preferred":[
        "Sabdhakarpara"
    ],
    "wof:name":"Sabdhakarpara",
    "wof:placetype":"locality",
    "wof:population":52
},
  "geometry": {"coordinates":[92.209344,23.925909],"type":"Point"}
}