{
  "type": "Feature",
  "properties": {
    "iso:country":"IN",
    "ks:ks_name":"8 JM",
    "ks:ks_pop":61,
    "ks:ks_type":"VILLAGE",
    "name:eng_x_preferred":[
        "8 JM"
    ],
    "wof:name":"8 JM",
    "wof:placetype":"locality",
    "wof:population":61
},
  "geometry": {"coordinates":[73.21623599999999,29.018314],"type":"Point"}
}