{
  "type": "Feature",
  "properties": {
    "iso:country":"IN",
    "ks:ks_name":"Paruliya",
    "ks:ks_pop":428,
    "ks:ks_type":"VILLAGE",
    "ks:ks_uagg_main":0,
    "name:eng_x_preferred":[
        "Paruliya"
    ],
    "wof:name":"Paruliya",
    "wof:placetype":"neighbourhood",
    "wof:population":428
},
  "geometry": {"coordinates":[86.717226,22.24132],"type":"Point"}
}