{
  "type": "Feature",
  "properties": {
    "iso:country":"IN",
    "ks:ks_name":"Laxmiprasad",
    "ks:ks_pop":211,
    "ks:ks_type":"VILLAGE",
    "ks:ks_uagg_main":0,
    "name:eng_x_preferred":[
        "Laxmiprasad"
    ],
    "wof:name":"Laxmiprasad",
    "wof:placetype":"neighbourhood",
    "wof:population":211
},
  "geometry": {"coordinates":[86.738817,20.91604],"type":"Point"}
}