{
  "type": "Feature",
  "properties": {
    "gn:admin1_code":"36.0",
    "gn:admin2_code":"167",
    "gn:asciiname":"Mangawan",
    "gn:country_code":"IN",
    "gn:dem":370,
    "gn:feature_class":"P",
    "gn:feature_code":"PPL",
    "gn:name":"Mangaw\u0101n",
    "gn:population":0,
    "gn:timezone":"Asia/Kolkata",
    "iso:country":"IN",
    "name:ben_x_preferred":[
        "\u09ae\u0999\u09cd\u0997\u09be\u0993\u09af\u09bc\u09be\u09a8"
    ],
    "name:bpy_x_preferred":[
        "\u09ae\u0999\u09cd\u0997\u09be\u09f1\u09be\u09a8"
    ],
    "name:ceb_x_preferred":[
        "Mangaw\u0101n"
    ],
    "name:ita_x_preferred":[
        "Mangawan"
    ],
    "name:mlg_x_preferred":[
        "Mangawan"
    ],
    "name:msa_x_preferred":[
        "Mangawan"
    ],
    "name:new_x_preferred":[
        "\u092e\u0902\u0917\u0935\u0928"
    ],
    "name:nld_x_preferred":[
        "Mangawan"
    ],
    "name:por_x_preferred":[
        "Mangawan"
    ],
    "name:swe_x_preferred":[
        "Mangaw\u0101n"
    ],
    "name:vie_x_preferred":[
        "Mangawan"
    ],
    "name:zho_x_preferred":[
        "\u8292\u683c\u963f\u4e07"
    ],
    "wof:name":"Mangawan",
    "wof:placetype":"locality"
},
  "geometry": {"coordinates":[78.35309000000002,24.81954],"type":"Point"}
}