{
  "type": "Feature",
  "properties": {
    "iso:country":"IN",
    "ks:ks_name":"Darpsila",
    "ks:ks_pop":217,
    "ks:ks_type":"HABITATION",
    "name:eng_x_preferred":[
        "Darpsila"
    ],
    "wof:name":"Darpsila",
    "wof:placetype":"locality",
    "wof:population":217
},
  "geometry": {"coordinates":[86.821558,22.599557],"type":"Point"}
}