{
  "type": "Feature",
  "properties": {
    "gn:admin1_code":"36.0",
    "gn:admin2_code":"140.0",
    "gn:asciiname":"Sadiqpur",
    "gn:country_code":"IN",
    "gn:dem":216,
    "gn:feature_class":"P",
    "gn:feature_code":"PPL",
    "gn:name":"S\u0101diqpur",
    "gn:population":0,
    "gn:timezone":"Asia/Kolkata",
    "iso:country":"IN",
    "name:und_x_variant":[
        "S\u0101diqpur",
        "Q\u0101zipura"
    ],
    "wof:name":"Sadiqpur",
    "wof:placetype":"neighbourhood"
},
  "geometry": {"coordinates":[77.49305,28.66708],"type":"Point"}
}