{
  "type": "Feature",
  "properties": {
    "gn:admin1_code":"36.0",
    "gn:admin2_code":"140.0",
    "gn:asciiname":"Sadiqpur",
    "gn:country_code":"IN",
    "gn:dem":216,
    "gn:feature_class":"P",
    "gn:feature_code":"PPL",
    "gn:name":"S\u0101diqpur",
    "gn:population":0,
    "gn:timezone":"Asia/Kolkata",
    "iso:country":"IN",
    "name:ara_x_preferred":[
        "\u0635\u0627\u062f\u0642 \u0628\u0648\u0631"
    ],
    "name:ben_bn_x_preferred":[
        "\u09b8\u09be\u09a6\u09bf\u0995\u09aa\u09c1\u09b0"
    ],
    "name:ben_in_x_preferred":[
        "\u09b8\u09be\u09a6\u09bf\u0995\u09aa\u09c1\u09b0"
    ],
    "name:guj_x_preferred":[
        "\u0ab8\u0abe\u0aa6\u0ac0\u0a95\u0aaa\u0ac1\u0ab0"
    ],
    "name:hin_x_preferred":[
        "\u0938\u093e\u0926\u093f\u0915\u092a\u0941\u0930"
    ],
    "name:kan_x_preferred":[
        "\u0cb8\u0cbe\u0ca6\u0cbf\u0c95\u0ccd"
    ],
    "name:mal_x_preferred":[
        "\u0d38\u0d3e\u0d26\u0d3f\u0d15\u0d4d\u0d2a\u0d42\u0d7c"
    ],
    "name:mar_x_preferred":[
        "\u0938\u093e\u0926\u093f\u0915\u092a\u0942\u0930"
    ],
    "name:pan_x_preferred":[
        "\u0a38\u0a3e\u0a26\u0a3f\u0a15\u0a2a\u0a41\u0a30"
    ],
    "name:tam_x_preferred":[
        "\u0b9a\u0bbe\u0ba4\u0bbf\u0b95\u0bcd\u0baa\u0bc2\u0bb0\u0bcd"
    ],
    "name:tel_x_preferred":[
        "\u0c38\u0c3e\u0c26\u0c3f\u0c15\u0c4d"
    ],
    "name:und_x_variant":[
        "S\u0101diqpur",
        "Q\u0101zipura"
    ],
    "name:urd_x_preferred":[
        "\u0635\u0627\u062f\u0642 \u067e\u0648\u0631"
    ],
    "wof:name":"Sadiqpur",
    "wof:placetype":"neighbourhood"
},
  "geometry": {"coordinates":[77.49305,28.66708],"type":"Point"}
}