{
  "type": "Feature",
  "properties": {
    "gn:admin1_code":"19",
    "gn:admin2_code":"579.0",
    "gn:asciiname":"Banur",
    "gn:country_code":"IN",
    "gn:dem":419,
    "gn:feature_class":"P",
    "gn:feature_code":"PPL",
    "gn:name":"Ban\u016br",
    "gn:population":0,
    "gn:timezone":"Asia/Kolkata",
    "iso:country":"IN",
    "name:pam_x_preferred":[
        "Banur"
    ],
    "name:vie_x_preferred":[
        "Banur"
    ],
    "wof:name":"Banur",
    "wof:placetype":"locality"
},
  "geometry": {"coordinates":[76.47763,17.07353],"type":"Point"}
}