{
  "type": "Feature",
  "properties": {
    "gn:admin1_code":"38.0",
    "gn:admin2_code":"347.0",
    "gn:asciiname":"Taradohar",
    "gn:country_code":"IN",
    "gn:dem":382,
    "gn:feature_class":"P",
    "gn:feature_code":"PPL",
    "gn:name":"T\u0101r\u0101dohar",
    "gn:population":0,
    "gn:timezone":"Asia/Kolkata",
    "iso:country":"IN",
    "ks:ks_alt_nam":"T\u0101r\u0101dohar",
    "ks:ks_name":"Taradohar",
    "ks:ks_type":"VILLAGE",
    "name:eng_x_preferred":[
        "Taradohar"
    ],
    "name:eng_x_variant":[
        "T\u0101r\u0101dohar"
    ],
    "wof:name":"Taradohar",
    "wof:placetype":"locality"
},
  "geometry": {"coordinates":[84.63591700000001,24.222591],"type":"Point"}
}