{
  "type": "Feature",
  "properties": {
    "iso:country":"IN",
    "ks:ks_name":"Damodara",
    "ks:ks_pop":282,
    "ks:ks_type":"VILLAGE",
    "name:eng_x_preferred":[
        "Damodara"
    ],
    "wof:name":"Damodara",
    "wof:placetype":"locality",
    "wof:population":282
},
  "geometry": {"coordinates":[83.957419,26.267577],"type":"Point"}
}