{
  "type": "Feature",
  "properties": {
    "iso:country":"IN",
    "ks:ks_name":"Babupur Tiwaribasa",
    "ks:ks_pop":1575,
    "ks:ks_type":"HABITATION",
    "name:eng_x_preferred":[
        "Babupur Tiwaribasa"
    ],
    "wof:name":"Babupur Tiwaribasa",
    "wof:placetype":"locality",
    "wof:population":1575
},
  "geometry": {"coordinates":[87.381289,25.23702],"type":"Point"}
}