{
  "type": "Feature",
  "properties": {
    "iso:country":"IN",
    "ks:ks_name":"Virpar",
    "ks:ks_pop":2327,
    "ks:ks_type":"VILLAGE",
    "name:eng_x_preferred":[
        "Virpar"
    ],
    "wof:name":"Virpar",
    "wof:placetype":"locality",
    "wof:population":2327
},
  "geometry": {"coordinates":[70.38154299999999,22.388048],"type":"Point"}
}