{
  "type": "Feature",
  "properties": {
    "gn:admin1_code":"36.0",
    "gn:admin2_code":"184.0",
    "gn:asciiname":"Bangawan",
    "gn:country_code":"IN",
    "gn:dem":95,
    "gn:feature_class":"P",
    "gn:feature_code":"PPL",
    "gn:name":"Bangaw\u0101n",
    "gn:population":0,
    "gn:timezone":"Asia/Kolkata",
    "iso:country":"IN",
    "wof:name":"Bangawan",
    "wof:placetype":"locality"
},
  "geometry": {"coordinates":[82.64898000000002,27.18383],"type":"Point"}
}