{
  "type": "Feature",
  "properties": {
    "gn:admin1_code":"36.0",
    "gn:admin2_code":"152",
    "gn:asciiname":"Ranjit Nagla",
    "gn:country_code":"IN",
    "gn:dem":150,
    "gn:feature_class":"P",
    "gn:feature_code":"PPL",
    "gn:name":"Ranj\u012bt Nagla",
    "gn:population":0,
    "gn:timezone":"Asia/Kolkata",
    "iso:country":"IN",
    "wof:name":"Ranjit Nagla",
    "wof:placetype":"locality"
},
  "geometry": {"coordinates":[79.41786,27.81033],"type":"Point"}
}