{
  "type": "Feature",
  "properties": {
    "gn:admin1_code":"19.0",
    "gn:admin2_code":"576.0",
    "gn:asciiname":"Karmadu",
    "gn:country_code":"IN",
    "gn:dem":827,
    "gn:feature_class":"P",
    "gn:feature_code":"PPL",
    "gn:name":"Karmadu",
    "gn:population":0,
    "gn:timezone":"Asia/Kolkata",
    "iso:country":"IN",
    "ks:ks_alt_nam":"karmadu",
    "ks:ks_name":"Karmadu",
    "ks:ks_pop":2694,
    "ks:ks_type":"HABITATION",
    "name:eng_x_preferred":[
        "Karmadu"
    ],
    "wof:name":"Karmadu",
    "wof:placetype":"locality",
    "wof:population":2694
},
  "geometry": {"coordinates":[76.06679099999999,12.104646],"type":"Point"}
}