{
  "type": "Feature",
  "properties": {
    "gn:admin1_code":"36",
    "gn:admin2_code":"202.0",
    "gn:asciiname":"Kantor",
    "gn:country_code":"IN",
    "gn:dem":183,
    "gn:feature_class":"P",
    "gn:feature_code":"PPL",
    "gn:name":"K\u0101ntor",
    "gn:population":0,
    "gn:timezone":"Asia/Kolkata",
    "iso:country":"IN",
    "name:ces_x_preferred":[
        "Kantor"
    ],
    "name:deu_x_preferred":[
        "Kantor"
    ],
    "name:fra_x_preferred":[
        "Kantor"
    ],
    "name:heb_x_preferred":[
        "\u05e7\u05e0\u05d8\u05d5\u05e8"
    ],
    "name:hrv_x_preferred":[
        "Kantor"
    ],
    "name:ita_x_preferred":[
        "Kantor"
    ],
    "name:lav_x_preferred":[
        "Kantors"
    ],
    "name:pol_x_preferred":[
        "Kantor"
    ],
    "name:rus_x_preferred":[
        "\u041a\u0430\u043d\u0442\u043e\u0440"
    ],
    "name:spa_x_preferred":[
        "Kantor"
    ],
    "name:swe_x_preferred":[
        "Kantor"
    ],
    "name:ukr_x_preferred":[
        "\u041a\u0430\u043d\u0442\u043e\u0440"
    ],
    "wof:name":"Kantor",
    "wof:placetype":"locality"
},
  "geometry": {"coordinates":[78.50667,27.75842],"type":"Point"}
}