{
  "type": "Feature",
  "properties": {
    "iso:country":"IN",
    "ks:ks_name":"Barjana Pt I",
    "ks:ks_pop":1608,
    "ks:ks_type":"VILLAGE",
    "ks:ks_uagg_main":0,
    "name:eng_x_preferred":[
        "Barjana Pt I"
    ],
    "wof:name":"Barjana Pt I",
    "wof:placetype":"neighbourhood",
    "wof:population":1608
},
  "geometry": {"coordinates":[90.66919799999999,26.255516],"type":"Point"}
}