{
  "type": "Feature",
  "properties": {
    "iso:country":"IN",
    "ks:ks_name":"Allavankadu",
    "ks:ks_pop":160,
    "ks:ks_type":"HABITATION",
    "name:eng_x_preferred":[
        "Allavankadu"
    ],
    "wof:name":"Allavankadu",
    "wof:placetype":"locality",
    "wof:population":160
},
  "geometry": {"coordinates":[77.785414,11.50126],"type":"Point"}
}