{
  "type": "Feature",
  "properties": {
    "gn:admin1_code":"19.0",
    "gn:admin2_code":"573.0",
    "gn:asciiname":"Darasaguppe",
    "gn:country_code":"IN",
    "gn:dem":717,
    "gn:feature_class":"P",
    "gn:feature_code":"PPL",
    "gn:name":"D\u0101rasaguppe",
    "gn:population":0,
    "gn:timezone":"Asia/Kolkata",
    "iso:country":"IN",
    "ks:ks_alt_nam":"D\u0101rasaguppe",
    "ks:ks_name":"Darasaguppe",
    "ks:ks_pop":1378,
    "ks:ks_type":"VILLAGE",
    "ks:ks_uagg_main":0,
    "name:eng_x_preferred":[
        "Darasaguppe"
    ],
    "name:eng_x_variant":[
        "D\u0101rasaguppe"
    ],
    "wof:name":"Darasaguppe",
    "wof:placetype":"neighbourhood",
    "wof:population":1378
},
  "geometry": {"coordinates":[76.688858,12.453924],"type":"Point"}
}