{
  "type": "Feature",
  "properties": {
    "gn:admin1_code":"36.0",
    "gn:admin2_code":"132.0",
    "gn:asciiname":"Dholapara",
    "gn:country_code":"IN",
    "gn:dem":260,
    "gn:feature_class":"P",
    "gn:feature_code":"PPL",
    "gn:name":"Dhol\u0101para",
    "gn:population":0,
    "gn:timezone":"Asia/Kolkata",
    "iso:country":"IN",
    "wof:name":"Dholapara",
    "wof:placetype":"locality"
},
  "geometry": {"coordinates":[77.28328,29.81031],"type":"Point"}
}