{
  "type": "Feature",
  "properties": {
    "gn:admin1_code":"35",
    "gn:admin2_code":"443.0",
    "gn:asciiname":"Khiriyakhera",
    "gn:country_code":"IN",
    "gn:dem":420,
    "gn:feature_class":"P",
    "gn:feature_code":"PPL",
    "gn:name":"Khiriy\u0101khera",
    "gn:population":0,
    "gn:timezone":"Asia/Kolkata",
    "iso:country":"IN",
    "name:und_x_variant":[
        "Khiriy\u0101khera",
        "Khupura"
    ],
    "wof:name":"Khiriyakhera",
    "wof:placetype":"neighbourhood"
},
  "geometry": {"coordinates":[77.90779999999999,24.23971],"type":"Point"}
}