{
  "type": "Feature",
  "properties": {
    "gn:admin1_code":"34",
    "gn:admin2_code":"234.0",
    "gn:asciiname":"Kusumha",
    "gn:country_code":"IN",
    "gn:dem":408,
    "gn:feature_class":"P",
    "gn:feature_code":"PPL",
    "gn:name":"Kusumha",
    "gn:population":0,
    "gn:timezone":"Asia/Kolkata",
    "iso:country":"IN",
    "wof:name":"Kusumha",
    "wof:placetype":"locality"
},
  "geometry": {"coordinates":[83.84173,24.80431],"type":"Point"}
}