{
  "type": "Feature",
  "properties": {
    "gn:admin1_code":"34",
    "gn:admin2_code":"234.0",
    "gn:asciiname":"Kusumha",
    "gn:country_code":"IN",
    "gn:dem":408,
    "gn:feature_class":"P",
    "gn:feature_code":"PPL",
    "gn:name":"Kusumha",
    "gn:population":0,
    "gn:timezone":"Asia/Kolkata",
    "iso:country":"IN",
    "ks:ks_name":"Kusumha",
    "ks:ks_pop":82,
    "ks:ks_type":"VILLAGE",
    "name:eng_x_preferred":[
        "Kusumha"
    ],
    "wof:name":"Kusumha",
    "wof:placetype":"locality",
    "wof:population":82
},
  "geometry": {"coordinates":[83.841733,24.804313],"type":"Point"}
}