{
  "type": "Feature",
  "properties": {
    "iso:country":"IN",
    "ks:ks_name":"Akona",
    "ks:ks_type":"VILLAGE",
    "name:eng_x_preferred":[
        "Akona"
    ],
    "wof:name":"Akona",
    "wof:placetype":"locality"
},
  "geometry": {"coordinates":[80.11049800000001,25.578108],"type":"Point"}
}