{
  "type": "Feature",
  "properties": {
    "iso:country":"IN",
    "ks:ks_name":"Chinta Haran Para",
    "ks:ks_pop":25,
    "ks:ks_type":"HABITATION",
    "name:eng_x_preferred":[
        "Chinta Haran Para"
    ],
    "wof:name":"Chinta Haran Para",
    "wof:placetype":"locality",
    "wof:population":25
},
  "geometry": {"coordinates":[91.962908,23.968968],"type":"Point"}
}