{
  "type": "Feature",
  "properties": {
    "gn:admin1_code":"38.0",
    "gn:admin2_code":"360.0",
    "gn:asciiname":"Mungarmu",
    "gn:country_code":"IN",
    "gn:dem":441,
    "gn:feature_class":"P",
    "gn:feature_code":"PPL",
    "gn:name":"Mungarmu",
    "gn:population":0,
    "gn:timezone":"Asia/Kolkata",
    "iso:country":"IN",
    "wof:name":"Mungarmu",
    "wof:placetype":"locality"
},
  "geometry": {"coordinates":[85.33695,24.1879],"type":"Point"}
}