{
  "type": "Feature",
  "properties": {
    "gn:admin1_code":"16.0",
    "gn:admin2_code":"514.0",
    "gn:asciiname":"Wadgaon",
    "gn:country_code":"IN",
    "gn:dem":511,
    "gn:feature_class":"P",
    "gn:feature_code":"PPL",
    "gn:name":"Wadgaon",
    "gn:population":0,
    "gn:timezone":"Asia/Kolkata",
    "iso:country":"IN",
    "ks:ks_name":"Wadgaon",
    "ks:ks_pop":622,
    "ks:ks_type":"VILLAGE",
    "name:eng_x_preferred":[
        "Wadgaon"
    ],
    "wof:name":"Wadgaon",
    "wof:placetype":"locality",
    "wof:population":622
},
  "geometry": {"coordinates":[76.05606299999999,19.895565],"type":"Point"}
}