{
  "type": "Feature",
  "properties": {
    "iso:country":"IN",
    "ks:ks_name":"Kurkutemala",
    "ks:ks_pop":712,
    "ks:ks_type":"HABITATION",
    "ks:ks_uagg_main":0,
    "name:eng_x_preferred":[
        "Kurkutemala"
    ],
    "wof:name":"Kurkutemala",
    "wof:placetype":"neighbourhood",
    "wof:population":712
},
  "geometry": {"coordinates":[73.807778,19.073283],"type":"Point"}
}