{
  "type": "Feature",
  "properties": {
    "iso:country":"IN",
    "ks:ks_name":"Doodhiya",
    "ks:ks_pop":415,
    "ks:ks_type":"HABITATION",
    "name:eng_x_preferred":[
        "Doodhiya"
    ],
    "wof:name":"Doodhiya",
    "wof:placetype":"locality",
    "wof:population":415
},
  "geometry": {"coordinates":[71.743077,26.672164],"type":"Point"}
}