{
  "type": "Feature",
  "properties": {
    "iso:country":"IN",
    "ks:ks_alt_nam":"Chichla M\u0101nusm\u0101ri",
    "ks:ks_name":"Chichla Manusmari",
    "ks:ks_type":"VILLAGE",
    "name:eng_x_preferred":[
        "Chichla Manusmari"
    ],
    "name:eng_x_variant":[
        "Chichla M\u0101nusm\u0101ri"
    ],
    "wof:name":"Chichla Manusmari",
    "wof:placetype":"locality"
},
  "geometry": {"coordinates":[79.343853,20.493457],"type":"Point"}
}