{
  "type": "Feature",
  "properties": {
    "gn:admin1_code":"36.0",
    "gn:admin2_code":"159",
    "gn:asciiname":"Nagla Gansahai",
    "gn:country_code":"IN",
    "gn:dem":144,
    "gn:feature_class":"P",
    "gn:feature_code":"PPL",
    "gn:name":"Nagla Gansah\u0101i",
    "gn:population":0,
    "gn:timezone":"Asia/Kolkata",
    "iso:country":"IN",
    "ks:ks_name":"Nagla Gom Sahai",
    "ks:ks_pop":247,
    "ks:ks_type":"HABITATION",
    "ks:ks_uagg_main":0,
    "name:eng_x_preferred":[
        "Nagla Gom Sahai"
    ],
    "wof:name":"Nagla Gom Sahai",
    "wof:placetype":"neighbourhood",
    "wof:population":247
},
  "geometry": {"coordinates":[79.457571,27.218004],"type":"Point"}
}