{
  "type": "Feature",
  "properties": {
    "gn:country":"IN",
    "gn:fcode":"PPL",
    "gn:population":25753,
    "iso:country":"IN",
    "name:bar_x_preferred":[
        "Annigeri"
    ],
    "name:ben_x_preferred":[
        "\u0986\u09a8\u09cd\u09a8\u09bf\u0997\u09c7\u09b0\u09c0"
    ],
    "name:bpy_x_preferred":[
        "\u0986\u09a8\u09cd\u09a8\u09bf\u0997\u09c7\u09b0\u09c0"
    ],
    "name:bul_x_preferred":[
        "\u0410\u043d\u0438\u0433\u0435\u0440\u0438"
    ],
    "name:ceb_x_preferred":[
        "Annigeri"
    ],
    "name:deu_x_preferred":[
        "Annigeri"
    ],
    "name:eng_x_preferred":[
        "Annigeri"
    ],
    "name:fra_x_preferred":[
        "Annigeri"
    ],
    "name:ita_x_preferred":[
        "Annigeri"
    ],
    "name:kan_x_preferred":[
        "\u0c85\u0ca3\u0ccd\u0ca3\u0cbf\u0c97\u0cc7\u0cb0\u0cbf"
    ],
    "name:mlg_x_preferred":[
        "Annigeri"
    ],
    "name:msa_x_preferred":[
        "Annigeri"
    ],
    "name:nan_x_preferred":[
        "Annigeri"
    ],
    "name:new_x_preferred":[
        "\u0905\u0928\u093f\u0917\u0947\u0930\u0940"
    ],
    "name:nld_x_preferred":[
        "Annigeri"
    ],
    "name:por_x_preferred":[
        "Annigeri"
    ],
    "name:spa_x_preferred":[
        "Annigeri"
    ],
    "name:swe_x_preferred":[
        "Annigeri"
    ],
    "name:vie_x_preferred":[
        "Annigeri"
    ],
    "name:zho_x_preferred":[
        "\u5b89\u5c3c\u76d6\u91cc"
    ],
    "qs:name":"Pangeri",
    "qs:name_adm0":"India",
    "qs:name_adm1":"Karnataka",
    "qs:photos_9r":0,
    "qs:photos_sr":0,
    "qs:placetype":"Town",
    "qs:pop_sr":"7",
    "wd:wordcount":25,
    "wof:name":"Pangeri",
    "wof:placetype":"locality",
    "wof:population":25753
},
  "geometry": {"coordinates":[75.4335,15.42513],"type":"Point"}
}