{
  "type": "Feature",
  "properties": {
    "iso:country":"IN",
    "ks:ks_name":"Hunchani",
    "ks:ks_pop":153,
    "ks:ks_type":"HABITATION",
    "name:eng_x_preferred":[
        "Hunchani"
    ],
    "wof:name":"Hunchani",
    "wof:placetype":"locality",
    "wof:population":153
},
  "geometry": {"coordinates":[74.766524,13.799387],"type":"Point"}
}