{
  "type": "Feature",
  "properties": {
    "gn:admin1_code":"36",
    "gn:admin2_code":"175.0",
    "gn:asciiname":"Kotiya",
    "gn:country_code":"IN",
    "gn:dem":118,
    "gn:feature_class":"P",
    "gn:feature_code":"PPL",
    "gn:name":"Kotiya",
    "gn:population":0,
    "gn:timezone":"Asia/Kolkata",
    "iso:country":"IN",
    "wof:name":"Kotiya",
    "wof:placetype":"locality"
},
  "geometry": {"coordinates":[82.05329999999999,24.91957],"type":"Point"}
}