{
  "type": "Feature",
  "properties": {
    "gn:admin1_code":"35",
    "gn:admin2_code":"463.0",
    "gn:asciiname":"Bamhani",
    "gn:country_code":"IN",
    "gn:dem":294,
    "gn:feature_class":"P",
    "gn:feature_code":"PPL",
    "gn:name":"Bamhani",
    "gn:population":0,
    "gn:timezone":"Asia/Kolkata",
    "iso:country":"IN",
    "name:ben_x_preferred":[
        "\u09ac\u09be\u09ae\u09b9\u09be\u09a8\u09bf"
    ],
    "name:bpy_x_preferred":[
        "\u09ac\u09be\u09ae\u09b9\u09be\u09a8\u09bf"
    ],
    "name:hin_x_preferred":[
        "\u092c\u092e\u094d\u0939\u0928\u0940 \u092c\u0902\u091c\u0930"
    ],
    "name:ita_x_preferred":[
        "Bamhani"
    ],
    "name:mlg_x_preferred":[
        "Bamhani"
    ],
    "name:msa_x_preferred":[
        "Bamhani"
    ],
    "name:new_x_preferred":[
        "\u092c\u092e\u094d\u0939\u0928\u0948"
    ],
    "name:nld_x_preferred":[
        "Bamhani"
    ],
    "name:por_x_preferred":[
        "Bamhani"
    ],
    "name:spa_x_preferred":[
        "Bamhani"
    ],
    "name:vie_x_preferred":[
        "Bamhani"
    ],
    "name:zho_x_preferred":[
        "\u5df4\u59c6\u54c8\u5c3c"
    ],
    "wof:name":"Bamhani",
    "wof:placetype":"locality"
},
  "geometry": {"coordinates":[82.34475999999999,24.33767000000001],"type":"Point"}
}