{
  "type": "Feature",
  "properties": {
    "iso:country":"IN",
    "ks:ks_name":"Danushi East",
    "ks:ks_pop":3564,
    "ks:ks_type":"HABITATION",
    "name:eng_x_preferred":[
        "Danushi East"
    ],
    "wof:name":"Danushi East",
    "wof:placetype":"locality",
    "wof:population":3564
},
  "geometry": {"coordinates":[85.192847,25.812212],"type":"Point"}
}