{
  "type": "Feature",
  "properties": {
    "iso:country":"IN",
    "ks:ks_name":"Godugurllametta",
    "ks:ks_pop":116,
    "ks:ks_type":"HABITATION",
    "name:eng_x_preferred":[
        "Godugurllametta"
    ],
    "wof:name":"Godugurllametta",
    "wof:placetype":"locality",
    "wof:population":116
},
  "geometry": {"coordinates":[82.402295,17.964702],"type":"Point"}
}