{
  "type": "Feature",
  "properties": {
    "gn:admin1_code":"36",
    "gn:admin2_code":"173.0",
    "gn:asciiname":"Chaunsa",
    "gn:country_code":"IN",
    "gn:dem":105,
    "gn:feature_class":"P",
    "gn:feature_code":"PPL",
    "gn:name":"Chaunsa",
    "gn:population":0,
    "gn:timezone":"Asia/Kolkata",
    "iso:country":"IN",
    "name:ara_x_preferred":[
        "\u062c\u0648\u0646\u0633\u0627"
    ],
    "name:bih_x_preferred":[
        "\u091a\u094c\u0938\u093e"
    ],
    "wof:name":"Chaunsa",
    "wof:placetype":"locality"
},
  "geometry": {"coordinates":[81.48784000000001,25.71264],"type":"Point"}
}