{
  "type": "Feature",
  "properties": {
    "iso:country":"IN",
    "ks:ks_name":"Vaddimitta",
    "ks:ks_pop":38,
    "ks:ks_type":"HABITATION",
    "name:eng_x_preferred":[
        "Vaddimitta"
    ],
    "wof:name":"Vaddimitta",
    "wof:placetype":"locality",
    "wof:population":38
},
  "geometry": {"coordinates":[79.585069,13.682296],"type":"Point"}
}