{
  "type": "Feature",
  "properties": {
    "iso:country":"IN",
    "ks:ks_name":"Phephariya Khurd",
    "ks:ks_type":"VILLAGE",
    "name:eng_x_preferred":[
        "Phephariya Khurd"
    ],
    "wof:name":"Phephariya Khurd",
    "wof:placetype":"locality"
},
  "geometry": {"coordinates":[76.615572,22.113264],"type":"Point"}
}