{
  "type": "Feature",
  "properties": {
    "gn:admin1_code":"36.0",
    "gn:admin2_code":"202",
    "gn:asciiname":"Dhokar Nagla",
    "gn:country_code":"IN",
    "gn:dem":155,
    "gn:feature_class":"P",
    "gn:feature_code":"PPL",
    "gn:name":"Dhokar Nagla",
    "gn:population":0,
    "gn:timezone":"Asia/Kolkata",
    "iso:country":"IN",
    "wof:name":"Dhokar Nagla",
    "wof:placetype":"neighbourhood"
},
  "geometry": {"coordinates":[79.13383,27.8132],"type":"Point"}
}