{
  "type": "Feature",
  "properties": {
    "gn:admin1_code":"38.0",
    "gn:admin2_code":"362.0",
    "gn:asciiname":"Bathanpahari Chhota",
    "gn:country_code":"IN",
    "gn:dem":162,
    "gn:feature_class":"P",
    "gn:feature_code":"PPL",
    "gn:name":"B\u0101th\u0101npah\u0101ri Chhota",
    "gn:population":0,
    "gn:timezone":"Asia/Kolkata",
    "iso:country":"IN",
    "wof:name":"Bathanpahari Chhota",
    "wof:placetype":"locality"
},
  "geometry": {"coordinates":[87.54892,24.40967],"type":"Point"}
}