{
  "type": "Feature",
  "properties": {
    "iso:country":"IN",
    "ks:ks_name":"Hosathotta",
    "ks:ks_pop":105,
    "ks:ks_type":"HABITATION",
    "name:eng_x_preferred":[
        "Hosathotta"
    ],
    "wof:name":"Hosathotta",
    "wof:placetype":"locality",
    "wof:population":105
},
  "geometry": {"coordinates":[75.372231,13.41019],"type":"Point"}
}