{
  "type": "Feature",
  "properties": {
    "iso:country":"IN",
    "ks:ks_name":"Shikaritola",
    "ks:ks_pop":94,
    "ks:ks_type":"HABITATION",
    "name:eng_x_preferred":[
        "Shikaritola"
    ],
    "wof:name":"Shikaritola",
    "wof:placetype":"locality",
    "wof:population":94
},
  "geometry": {"coordinates":[80.795759,21.068454],"type":"Point"}
}