{
  "type": "Feature",
  "properties": {
    "iso:country":"IN",
    "ks:ks_name":"Jharanaghati",
    "ks:ks_pop":209,
    "ks:ks_type":"HABITATION",
    "name:eng_x_preferred":[
        "Jharanaghati"
    ],
    "wof:name":"Jharanaghati",
    "wof:placetype":"locality",
    "wof:population":209
},
  "geometry": {"coordinates":[86.573533,21.492229],"type":"Point"}
}