{
  "type": "Feature",
  "properties": {
    "iso:country":"IN",
    "ks:ks_alt_nam":"Mochi tola",
    "ks:ks_name":"Mochi Tola",
    "ks:ks_pop":264,
    "ks:ks_type":"HABITATION",
    "name:eng_x_preferred":[
        "Mochi Tola"
    ],
    "wof:name":"Mochi Tola",
    "wof:placetype":"locality",
    "wof:population":264
},
  "geometry": {"coordinates":[86.43434999999999,26.029029],"type":"Point"}
}