{
  "type": "Feature",
  "properties": {
    "iso:country":"IN",
    "ks:ks_name":"Dighali Pathar",
    "ks:ks_pop":457,
    "ks:ks_type":"VILLAGE",
    "ks:ks_uagg_main":0,
    "name:eng_x_preferred":[
        "Dighali Pathar"
    ],
    "wof:name":"Dighali Pathar",
    "wof:placetype":"neighbourhood",
    "wof:population":457
},
  "geometry": {"coordinates":[93.46654599999999,26.825168],"type":"Point"}
}