{
  "type": "Feature",
  "properties": {
    "iso:country":"IN",
    "ks:ks_name":"Chagare Doddi",
    "ks:ks_pop":48,
    "ks:ks_type":"HABITATION",
    "name:eng_x_preferred":[
        "Chagare Doddi"
    ],
    "wof:name":"Chagare Doddi",
    "wof:placetype":"locality",
    "wof:population":48
},
  "geometry": {"coordinates":[77.223997,12.565211],"type":"Point"}
}