{
  "type": "Feature",
  "properties": {
    "gn:admin1_code":"28",
    "gn:admin2_code":"340.0",
    "gn:asciiname":"Sirkabad",
    "gn:country_code":"IN",
    "gn:dem":287,
    "gn:feature_class":"P",
    "gn:feature_code":"PPL",
    "gn:name":"Sirk\u0101b\u0101d",
    "gn:population":0,
    "gn:timezone":"Asia/Kolkata",
    "iso:country":"IN",
    "name:und_x_variant":[
        "Sirk\u0101b\u0101d"
    ],
    "wof:name":"Sirkabad",
    "wof:placetype":"locality"
},
  "geometry": {"coordinates":[86.19833,23.27519],"type":"Point"}
}