{
  "type": "Feature",
  "properties": {
    "iso:country":"IN",
    "ks:ks_name":"Mosigam",
    "ks:ks_pop":92,
    "ks:ks_type":"VILLAGE",
    "name:eng_x_preferred":[
        "Mosigam"
    ],
    "wof:name":"Mosigam",
    "wof:placetype":"locality",
    "wof:population":92
},
  "geometry": {"coordinates":[82.30876600000001,19.035944],"type":"Point"}
}