{
  "type": "Feature",
  "properties": {
    "gn:admin1_code":"19.0",
    "gn:admin2_code":"559.0",
    "gn:asciiname":"Upla",
    "gn:country_code":"IN",
    "gn:dem":357,
    "gn:feature_class":"P",
    "gn:feature_code":"PPL",
    "gn:name":"Upla",
    "gn:population":0,
    "gn:timezone":"Asia/Kolkata",
    "iso:country":"IN",
    "wof:name":"Upla",
    "wof:placetype":"locality"
},
  "geometry": {"coordinates":[76.91974,15.73731],"type":"Point"}
}