{
  "type": "Feature",
  "properties": {
    "iso:country":"IN",
    "ks:ks_name":"Ganeswarpur",
    "ks:ks_pop":81,
    "ks:ks_type":"VILLAGE",
    "ks:ks_uagg_main":0,
    "name:eng_x_preferred":[
        "Ganeswarpur"
    ],
    "wof:name":"Ganeswarpur",
    "wof:placetype":"neighbourhood",
    "wof:population":81
},
  "geometry": {"coordinates":[86.682481,21.19961],"type":"Point"}
}