{
  "type": "Feature",
  "properties": {
    "iso:country":"IN",
    "ks:ks_name":"Danduguda",
    "ks:ks_pop":136,
    "ks:ks_type":"VILLAGE",
    "name:eng_x_preferred":[
        "Danduguda"
    ],
    "wof:name":"Danduguda",
    "wof:placetype":"locality",
    "wof:population":136
},
  "geometry": {"coordinates":[82.74179100000001,18.463439],"type":"Point"}
}