{
  "type": "Feature",
  "properties": {
    "iso:country":"IN",
    "ks:ks_alt_nam":"UTTAR TOLA MIYA",
    "ks:ks_name":"Uttar Tola Miya",
    "ks:ks_pop":200,
    "ks:ks_type":"HABITATION",
    "name:eng_x_preferred":[
        "Uttar Tola Miya"
    ],
    "wof:name":"Uttar Tola Miya",
    "wof:placetype":"locality",
    "wof:population":200
},
  "geometry": {"coordinates":[84.07489099999999,26.435586],"type":"Point"}
}