{
  "type": "Feature",
  "properties": {
    "iso:country":"IN",
    "ks:ks_name":"Salepur",
    "ks:ks_pop":400,
    "ks:ks_type":"HABITATION",
    "name:eng_x_preferred":[
        "Salepur"
    ],
    "wof:name":"Salepur",
    "wof:placetype":"locality",
    "wof:population":400
},
  "geometry": {"coordinates":[92.32778999999999,24.679262],"type":"Point"}
}