{
  "type": "Feature",
  "properties": {
    "iso:country":"IN",
    "ks:ks_alt_nam":"KelperumalCheri ADC",
    "ks:ks_name":"Kelperumalcheri Adc",
    "ks:ks_pop":249,
    "ks:ks_type":"HABITATION",
    "ks:ks_uagg_main":0,
    "name:eng_x_preferred":[
        "Kelperumalcheri Adc"
    ],
    "wof:name":"Kelperumalcheri Adc",
    "wof:placetype":"neighbourhood",
    "wof:population":249
},
  "geometry": {"coordinates":[80.14518,12.525056],"type":"Point"}
}