{
  "type": "Feature",
  "properties": {
    "iso:country":"IN",
    "ks:ks_name":"Mandua",
    "ks:ks_pop":652,
    "ks:ks_type":"VILLAGE",
    "ks:ks_uagg_main":0,
    "name:eng_x_preferred":[
        "Mandua"
    ],
    "wof:name":"Mandua",
    "wof:placetype":"neighbourhood",
    "wof:population":652
},
  "geometry": {"coordinates":[85.626591,21.62983],"type":"Point"}
}