{
  "type": "Feature",
  "properties": {
    "iso:country":"IN",
    "ks:ks_name":"Petha",
    "ks:ks_pop":492,
    "ks:ks_type":"HABITATION",
    "name:eng_x_preferred":[
        "Petha"
    ],
    "wof:name":"Petha",
    "wof:placetype":"locality",
    "wof:population":492
},
  "geometry": {"coordinates":[80.827803,19.1094],"type":"Point"}
}