{
  "type": "Feature",
  "properties": {
    "iso:country":"IN",
    "ks:ks_name":"Bag Poreyghosal Para",
    "ks:ks_pop":1013,
    "ks:ks_type":"HABITATION",
    "name:eng_x_preferred":[
        "Bag Poreyghosal Para"
    ],
    "wof:name":"Bag Poreyghosal Para",
    "wof:placetype":"locality",
    "wof:population":1013
},
  "geometry": {"coordinates":[88.250567,22.345729],"type":"Point"}
}