{
  "type": "Feature",
  "properties": {
    "gn:admin1_code":"24.0",
    "gn:admin2_code":"102.0",
    "gn:asciiname":"Dhandhalkheta",
    "gn:country_code":"IN",
    "gn:dem":232,
    "gn:feature_class":"P",
    "gn:feature_code":"PPL",
    "gn:name":"Dhandh\u0101lkheta",
    "gn:population":0,
    "gn:timezone":"Asia/Kolkata",
    "iso:country":"IN",
    "ks:ks_alt_nam":"Dhandh\u0101lkheta",
    "ks:ks_name":"Dhandhalkheta",
    "ks:ks_type":"VILLAGE",
    "name:eng_x_preferred":[
        "Dhandhalkheta"
    ],
    "name:eng_x_variant":[
        "Dhandh\u0101lkheta"
    ],
    "wof:name":"Dhandhalkheta",
    "wof:placetype":"locality"
},
  "geometry": {"coordinates":[75.382177,28.708604],"type":"Point"}
}