{
  "type": "Feature",
  "properties": {
    "gn:admin1_code":"25.0",
    "gn:admin2_code":"612.0",
    "gn:asciiname":"Balasamudram",
    "gn:country_code":"IN",
    "gn:dem":321,
    "gn:feature_class":"P",
    "gn:feature_code":"PPL",
    "gn:name":"B\u0101lasamudram",
    "gn:population":0,
    "gn:timezone":"Asia/Kolkata",
    "iso:country":"IN",
    "wof:name":"Balasamudram",
    "wof:placetype":"locality"
},
  "geometry": {"coordinates":[77.49916,10.41905],"type":"Point"}
}