{
  "type": "Feature",
  "properties": {
    "iso:country":"IN",
    "ks:ks_name":"Mairura",
    "ks:ks_pop":334,
    "ks:ks_type":"HABITATION",
    "name:eng_x_preferred":[
        "Mairura"
    ],
    "wof:name":"Mairura",
    "wof:placetype":"locality",
    "wof:population":334
},
  "geometry": {"coordinates":[78.783917,29.74377],"type":"Point"}
}