{
  "type": "Feature",
  "properties": {
    "gn:admin1_code":"36.0",
    "gn:admin2_code":"133.0",
    "gn:asciiname":"Govindgarh",
    "gn:country_code":"IN",
    "gn:dem":248,
    "gn:feature_class":"P",
    "gn:feature_code":"PPL",
    "gn:name":"Govindgarh",
    "gn:population":0,
    "gn:timezone":"Asia/Kolkata",
    "iso:country":"IN",
    "name:ben_x_preferred":[
        "\u0997\u09cb\u09ac\u09bf\u09a8\u09cd\u09a6\u0997\u09a1\u09bc"
    ],
    "name:cat_x_preferred":[
        "Govindgarh"
    ],
    "name:ceb_x_preferred":[
        "Govindgarh"
    ],
    "name:nld_x_preferred":[
        "Govindgarh"
    ],
    "name:swe_x_preferred":[
        "Govindgarh"
    ],
    "name:und_x_variant":[
        "Aml\u0101pur"
    ],
    "wof:name":"Govindgarh",
    "wof:placetype":"locality"
},
  "geometry": {"coordinates":[77.19821999999998,29.64561],"type":"Point"}
}