{
  "type": "Feature",
  "properties": {
    "gn:admin1_code":"36",
    "gn:admin2_code":"148.0",
    "gn:asciiname":"Sirsa",
    "gn:country_code":"IN",
    "gn:dem":164,
    "gn:feature_class":"P",
    "gn:feature_code":"PPL",
    "gn:name":"Sirsa",
    "gn:population":0,
    "gn:timezone":"Asia/Kolkata",
    "iso:country":"IN",
    "name:bih_x_preferred":[
        "\u0938\u093f\u0930\u0938\u093e"
    ],
    "name:cat_x_preferred":[
        "Sirsa"
    ],
    "name:ceb_x_preferred":[
        "Sirsa"
    ],
    "name:deu_x_preferred":[
        "Sirsa"
    ],
    "name:fas_x_preferred":[
        "\u0633\u06cc\u0631\u0633\u0627"
    ],
    "name:fra_x_preferred":[
        "Sirsa"
    ],
    "name:hin_x_preferred":[
        "\u0938\u093f\u0930\u0938\u093e"
    ],
    "name:ita_x_preferred":[
        "Sirsa"
    ],
    "name:mar_x_preferred":[
        "\u0938\u093f\u0930\u0938\u093e"
    ],
    "name:msa_x_preferred":[
        "Sirsa"
    ],
    "name:nor_x_preferred":[
        "Sirsa"
    ],
    "name:ori_x_preferred":[
        "\u0b38\u0b3f\u0b30\u0b4d\u0b38\u0b3e"
    ],
    "name:pnb_x_preferred":[
        "\u0636\u0644\u0639 \u0633\u0631\u0633\u06c1"
    ],
    "name:pol_x_preferred":[
        "Sirsa"
    ],
    "name:rus_x_preferred":[
        "\u0421\u0438\u0440\u0441\u0430"
    ],
    "name:san_x_preferred":[
        "\u0938\u093f\u0930\u0938\u093e,\u0939\u0930\u093f\u092f\u093e\u0923\u093e"
    ],
    "name:spa_x_preferred":[
        "Sirsa"
    ],
    "name:swe_x_preferred":[
        "Sirsa"
    ],
    "name:urd_x_preferred":[
        "\u0633\u0631\u0633\u0627"
    ],
    "name:vie_x_preferred":[
        "Sirsa"
    ],
    "name:war_x_preferred":[
        "Sirsa"
    ],
    "name:zho_x_preferred":[
        "\u897f\u5c14\u8428"
    ],
    "wof:name":"Sirsa",
    "wof:placetype":"locality"
},
  "geometry": {"coordinates":[78.99134000000002,27.38726],"type":"Point"}
}