{
  "type": "Feature",
  "properties": {
    "iso:country":"IN",
    "ks:ks_name":"Ray Tola",
    "ks:ks_pop":89,
    "ks:ks_type":"HABITATION",
    "name:eng_x_preferred":[
        "Ray Tola"
    ],
    "wof:name":"Ray Tola",
    "wof:placetype":"locality",
    "wof:population":89
},
  "geometry": {"coordinates":[83.676653,26.997833],"type":"Point"}
}