{
  "type": "Feature",
  "properties": {
    "iso:country":"IN",
    "ks:ks_name":"Janumpiri",
    "ks:ks_pop":355,
    "ks:ks_type":"VILLAGE",
    "name:eng_x_preferred":[
        "Janumpiri"
    ],
    "wof:name":"Janumpiri",
    "wof:placetype":"locality",
    "wof:population":355
},
  "geometry": {"coordinates":[85.40128799999999,23.05574],"type":"Point"}
}