{
  "type": "Feature",
  "properties": {
    "iso:country":"IN",
    "ks:ks_name":"Mahendra Para",
    "ks:ks_pop":66,
    "ks:ks_type":"HABITATION",
    "name:eng_x_preferred":[
        "Mahendra Para"
    ],
    "wof:name":"Mahendra Para",
    "wof:placetype":"locality",
    "wof:population":66
},
  "geometry": {"coordinates":[91.458365,23.783534],"type":"Point"}
}