{
  "type": "Feature",
  "properties": {
    "gn:admin1_code":"24.0",
    "gn:admin2_code":"118.0",
    "gn:asciiname":"Asan",
    "gn:country_code":"IN",
    "gn:dem":457,
    "gn:feature_class":"P",
    "gn:feature_code":"PPL",
    "gn:name":"Asan",
    "gn:population":0,
    "gn:timezone":"Asia/Kolkata",
    "iso:country":"IN",
    "wof:name":"Asan",
    "wof:placetype":"locality"
},
  "geometry": {"coordinates":[74.13428,25.94538],"type":"Point"}
}