{
  "type": "Feature",
  "properties": {
    "gn:admin1_code":"23.0",
    "gn:admin2_code":"43.0",
    "gn:asciiname":"Dharmpura",
    "gn:country_code":"IN",
    "gn:dem":185,
    "gn:feature_class":"P",
    "gn:feature_code":"PPL",
    "gn:name":"Dharmpura",
    "gn:population":0,
    "gn:timezone":"Asia/Kolkata",
    "iso:country":"IN",
    "name:und_x_variant":[
        "Sarupew\u0101la"
    ],
    "wof:name":"Dharmpura",
    "wof:placetype":"locality"
},
  "geometry": {"coordinates":[74.12295,30.08779],"type":"Point"}
}