{
  "type": "Feature",
  "properties": {
    "iso:country":"IN",
    "ks:ks_name":"Dadri",
    "ks:ks_pop":275,
    "ks:ks_type":"HABITATION",
    "name:eng_x_preferred":[
        "Dadri"
    ],
    "wof:name":"Dadri",
    "wof:placetype":"locality",
    "wof:population":275
},
  "geometry": {"coordinates":[73.61919399999999,21.180694],"type":"Point"}
}