{
  "type": "Feature",
  "properties": {
    "gn:admin1_code":"16",
    "gn:admin2_code":"522.0",
    "gn:asciiname":"Takli Dhokeshwar",
    "gn:country_code":"IN",
    "gn:dem":779,
    "gn:feature_class":"P",
    "gn:feature_code":"PPL",
    "gn:name":"T\u0101kli Dhokeshwar",
    "gn:population":0,
    "gn:timezone":"Asia/Kolkata",
    "iso:country":"IN",
    "name:mar_x_preferred":[
        "\u091f\u093e\u0915\u0933\u0940 \u0922\u094b\u0915\u0947\u0936\u094d\u0935\u0930"
    ],
    "name:und_x_variant":[
        "Takali Dhokeshwar",
        "T\u0101kli Dhokeshwar"
    ],
    "name:urd_x_preferred":[
        "\u0679\u0627\u06a9\u0644\u06cc \u062f\u06be\u0648\u06a9\u06cc\u0634\u0648\u0631"
    ],
    "wof:name":"Takli Dhokeshwar",
    "wof:placetype":"locality"
},
  "geometry": {"coordinates":[74.38167,19.15756],"type":"Point"}
}