{
  "type": "Feature",
  "properties": {
    "gn:admin1_code":"16",
    "gn:admin2_code":"522.0",
    "gn:asciiname":"Takli Dhokeshwar",
    "gn:country_code":"IN",
    "gn:dem":779,
    "gn:feature_class":"P",
    "gn:feature_code":"PPL",
    "gn:name":"T\u0101kli Dhokeshwar",
    "gn:population":0,
    "gn:timezone":"Asia/Kolkata",
    "iso:country":"IN",
    "name:und_x_variant":[
        "Takali Dhokeshwar",
        "T\u0101kli Dhokeshwar"
    ],
    "wof:name":"Takli Dhokeshwar",
    "wof:placetype":"locality"
},
  "geometry": {"coordinates":[74.38167,19.15756],"type":"Point"}
}