{
  "type": "Feature",
  "properties": {
    "gn:admin1_code":"36",
    "gn:admin2_code":"163.0",
    "gn:asciiname":"Tarna",
    "gn:country_code":"IN",
    "gn:dem":142,
    "gn:feature_class":"P",
    "gn:feature_code":"PPL",
    "gn:name":"Tarna",
    "gn:population":0,
    "gn:timezone":"Asia/Kolkata",
    "iso:country":"IN",
    "name:ast_x_preferred":[
        "Tarna"
    ],
    "name:spa_x_preferred":[
        "Tarna"
    ],
    "wof:name":"Tarna",
    "wof:placetype":"neighbourhood"
},
  "geometry": {"coordinates":[79.73574000000001,26.56086],"type":"Point"}
}