{
  "type": "Feature",
  "properties": {
    "gn:admin1_code":"36.0",
    "gn:admin2_code":"137.0",
    "gn:asciiname":"Bhurawali Mandaniyan",
    "gn:country_code":"IN",
    "gn:dem":193,
    "gn:feature_class":"P",
    "gn:feature_code":"PPL",
    "gn:name":"Bhur\u0101w\u0101li Mandaniy\u0101n",
    "gn:population":0,
    "gn:timezone":"Asia/Kolkata",
    "iso:country":"IN",
    "wof:name":"Bhurawali Mandaniyan",
    "wof:placetype":"locality"
},
  "geometry": {"coordinates":[78.25681999999998,28.54597],"type":"Point"}
}