{
  "type": "Feature",
  "properties": {
    "iso:country":"IN",
    "ks:ks_name":"Hingni-Digar",
    "ks:ks_pop":707,
    "ks:ks_type":"VILLAGE",
    "name:eng_x_preferred":[
        "Hingni-Digar"
    ],
    "wof:name":"Hingni-Digar",
    "wof:placetype":"locality",
    "wof:population":707
},
  "geometry": {"coordinates":[74.027703,21.488926],"type":"Point"}
}