{
  "type": "Feature",
  "properties": {
    "iso:country":"IN",
    "ks:ks_name":"Kapa",
    "ks:ks_pop":1139,
    "ks:ks_type":"HABITATION",
    "name:eng_x_preferred":[
        "Kapa"
    ],
    "wof:name":"Kapa",
    "wof:placetype":"locality",
    "wof:population":1139
},
  "geometry": {"coordinates":[79.90944399999999,23.402447],"type":"Point"}
}