{
  "type": "Feature",
  "properties": {
    "iso:country":"IN",
    "ks:ks_name":"Asawan",
    "ks:ks_pop":1,
    "ks:ks_type":"VILLAGE",
    "name:eng_x_preferred":[
        "Asawan"
    ],
    "wof:name":"Asawan",
    "wof:placetype":"locality",
    "wof:population":1
},
  "geometry": {"coordinates":[85.634198,25.425128],"type":"Point"}
}