{
  "type": "Feature",
  "properties": {
    "gn:admin1_code":"36",
    "gn:admin2_code":"142.0",
    "gn:asciiname":"Salagpur",
    "gn:country_code":"IN",
    "gn:dem":199,
    "gn:feature_class":"P",
    "gn:feature_code":"PPL",
    "gn:name":"S\u0101lagpur",
    "gn:population":0,
    "gn:timezone":"Asia/Kolkata",
    "iso:country":"IN",
    "ks:ks_name":"Saligpur",
    "ks:ks_pop":278,
    "ks:ks_type":"HABITATION",
    "name:eng_x_preferred":[
        "Saligpur"
    ],
    "name:eng_x_variant":[
        "Salagpur"
    ],
    "wof:name":"Saligpur",
    "wof:placetype":"locality",
    "wof:population":278
},
  "geometry": {"coordinates":[77.993904,28.263694],"type":"Point"}
}