{
  "type": "Feature",
  "properties": {
    "gn:admin1_code":"36",
    "gn:admin2_code":"202.0",
    "gn:asciiname":"Muharia",
    "gn:country_code":"IN",
    "gn:dem":172,
    "gn:feature_class":"P",
    "gn:feature_code":"PPL",
    "gn:name":"Muharia",
    "gn:population":0,
    "gn:timezone":"Asia/Kolkata",
    "iso:country":"IN",
    "wof:name":"Muharia",
    "wof:placetype":"neighbourhood"
},
  "geometry": {"coordinates":[78.88055,27.74129],"type":"Point"}
}