{
  "type": "Feature",
  "properties": {
    "gn:admin1_code":"39.0",
    "gn:admin2_code":"64.0",
    "gn:asciiname":"Bajina",
    "gn:country_code":"IN",
    "gn:dem":1379,
    "gn:feature_class":"P",
    "gn:feature_code":"PPL",
    "gn:name":"Baj\u012bna",
    "gn:population":0,
    "gn:timezone":"Asia/Kolkata",
    "iso:country":"IN",
    "wof:name":"Bajina",
    "wof:placetype":"locality"
},
  "geometry": {"coordinates":[79.48455,29.5754],"type":"Point"}
}