{
  "type": "Feature",
  "properties": {
    "gn:admin1_code":"19.0",
    "gn:admin2_code":"563.0",
    "gn:asciiname":"Gudnakatte",
    "gn:country_code":"IN",
    "gn:dem":10,
    "gn:feature_class":"P",
    "gn:feature_code":"PPL",
    "gn:name":"Gudnakatte",
    "gn:population":0,
    "gn:timezone":"Asia/Kolkata",
    "iso:country":"IN",
    "ks:ks_name":"Gudna Kattu",
    "ks:ks_pop":211,
    "ks:ks_type":"HABITATION",
    "name:eng_x_preferred":[
        "Gudna Kattu"
    ],
    "name:eng_x_variant":[
        "Gudnakatte"
    ],
    "wof:name":"Gudna Kattu",
    "wof:placetype":"locality",
    "wof:population":211
},
  "geometry": {"coordinates":[74.443067,14.381161],"type":"Point"}
}