{
  "type": "Feature",
  "properties": {
    "iso:country":"IN",
    "ks:ks_name":"Palashguri-ii",
    "ks:ks_pop":1579,
    "ks:ks_type":"VILLAGE",
    "ks:ks_uagg_main":0,
    "name:eng_x_preferred":[
        "Palashguri-ii"
    ],
    "wof:name":"Palashguri-ii",
    "wof:placetype":"neighbourhood",
    "wof:population":1579
},
  "geometry": {"coordinates":[89.945705,26.478106],"type":"Point"}
}