{
  "type": "Feature",
  "properties": {
    "gn:admin1_code":"36",
    "gn:admin2_code":"188.0",
    "gn:asciiname":"Djhapur",
    "gn:country_code":"IN",
    "gn:dem":84,
    "gn:feature_class":"P",
    "gn:feature_code":"PPL",
    "gn:name":"Djh\u0101pur",
    "gn:population":0,
    "gn:timezone":"Asia/Kolkata",
    "iso:country":"IN",
    "wof:name":"Djhapur",
    "wof:placetype":"neighbourhood"
},
  "geometry": {"coordinates":[83.23446,26.98022],"type":"Point"}
}