{
  "type": "Feature",
  "properties": {
    "gn:admin1_code":"36",
    "gn:admin2_code":"179.0",
    "gn:asciiname":"Pura Bhagwandin Dube",
    "gn:country_code":"IN",
    "gn:dem":113,
    "gn:feature_class":"P",
    "gn:feature_code":"PPL",
    "gn:name":"Pura Bhagw\u0101nd\u012bn Dube",
    "gn:population":0,
    "gn:timezone":"Asia/Kolkata",
    "iso:country":"IN",
    "wof:name":"Pura Bhagwandin Dube",
    "wof:placetype":"locality"
},
  "geometry": {"coordinates":[81.73596999999999,26.45435],"type":"Point"}
}