{
  "type": "Feature",
  "properties": {
    "iso:country":"IN",
    "ks:ks_alt_nam":"Baba Deen purwa",
    "ks:ks_name":"Baba Deen Purwa",
    "ks:ks_pop":43,
    "ks:ks_type":"HABITATION",
    "name:eng_x_preferred":[
        "Baba Deen Purwa"
    ],
    "wof:name":"Baba Deen Purwa",
    "wof:placetype":"locality",
    "wof:population":43
},
  "geometry": {"coordinates":[81.51603299999999,27.164568],"type":"Point"}
}