{
  "type": "Feature",
  "properties": {
    "iso:country":"IN",
    "ks:ks_alt_nam":"GHALME WASTI",
    "ks:ks_name":"Ghalme Wasti",
    "ks:ks_pop":110,
    "ks:ks_type":"HABITATION",
    "name:eng_x_preferred":[
        "Ghalme Wasti"
    ],
    "wof:name":"Ghalme Wasti",
    "wof:placetype":"locality",
    "wof:population":110
},
  "geometry": {"coordinates":[75.023179,18.479705],"type":"Point"}
}