{
  "type": "Feature",
  "properties": {
    "iso:country":"IN",
    "ks:ks_name":"Shashihittlu",
    "ks:ks_pop":49,
    "ks:ks_type":"HABITATION",
    "name:eng_x_preferred":[
        "Shashihittlu"
    ],
    "wof:name":"Shashihittlu",
    "wof:placetype":"locality",
    "wof:population":49
},
  "geometry": {"coordinates":[74.41114899999999,14.490763],"type":"Point"}
}