{
  "type": "Feature",
  "properties": {
    "gn:admin1_code":"36",
    "gn:admin2_code":"180.0",
    "gn:asciiname":"Kirtanpur",
    "gn:country_code":"IN",
    "gn:dem":117,
    "gn:feature_class":"P",
    "gn:feature_code":"PPL",
    "gn:name":"Kirtanpur",
    "gn:population":0,
    "gn:timezone":"Asia/Kolkata",
    "iso:country":"IN",
    "ks:ks_name":"Kiratanpur",
    "ks:ks_pop":1262,
    "ks:ks_type":"VILLAGE",
    "ks:ks_uagg_main":0,
    "name:eng_x_preferred":[
        "Kiratanpur"
    ],
    "wof:name":"Kiratanpur",
    "wof:placetype":"neighbourhood",
    "wof:population":1262
},
  "geometry": {"coordinates":[81.55662,27.500642],"type":"Point"}
}