{
  "type": "Feature",
  "properties": {
    "iso:country":"IN",
    "ks:ks_name":"Bhadaura",
    "ks:ks_pop":551,
    "ks:ks_type":"VILLAGE",
    "ks:ks_uagg_main":0,
    "name:eng_x_preferred":[
        "Bhadaura"
    ],
    "wof:name":"Bhadaura",
    "wof:placetype":"neighbourhood",
    "wof:population":551
},
  "geometry": {"coordinates":[80.889291,28.311833],"type":"Point"}
}