{
  "type": "Feature",
  "properties": {
    "iso:country":"IN",
    "ks:ks_name":"Kadamdih",
    "ks:ks_pop":1659,
    "ks:ks_type":"VILLAGE",
    "ks:ks_uagg_main":0,
    "name:eng_x_preferred":[
        "Kadamdih"
    ],
    "wof:name":"Kadamdih",
    "wof:placetype":"neighbourhood",
    "wof:population":1659
},
  "geometry": {"coordinates":[86.053946,22.948906],"type":"Point"}
}