{
  "type": "Feature",
  "properties": {
    "gn:admin1_code":"39.0",
    "gn:admin2_code":"57.0",
    "gn:asciiname":"Suki",
    "gn:country_code":"IN",
    "gn:dem":2960,
    "gn:feature_class":"P",
    "gn:feature_code":"PPL",
    "gn:name":"S\u016bki",
    "gn:population":0,
    "gn:timezone":"Asia/Kolkata",
    "iso:country":"IN",
    "name:msa_x_preferred":[
        "Suki"
    ],
    "name:pol_x_preferred":[
        "Suki"
    ],
    "name:spa_x_preferred":[
        "Suki"
    ],
    "wof:name":"Suki",
    "wof:placetype":"locality"
},
  "geometry": {"coordinates":[79.71989000000001,30.51686],"type":"Point"}
}