{
  "type": "Feature",
  "properties": {
    "gn:admin1_code":"39.0",
    "gn:admin2_code":"57.0",
    "gn:asciiname":"Suki",
    "gn:country_code":"IN",
    "gn:dem":2960,
    "gn:feature_class":"P",
    "gn:feature_code":"PPL",
    "gn:name":"S\u016bki",
    "gn:population":0,
    "gn:timezone":"Asia/Kolkata",
    "iso:country":"IN",
    "ks:ks_name":"Sukhi",
    "ks:ks_pop":174,
    "ks:ks_type":"VILLAGE",
    "name:eng_x_preferred":[
        "Sukhi"
    ],
    "name:eng_x_variant":[
        "Suki"
    ],
    "name:msa_x_preferred":[
        "Suki"
    ],
    "name:pol_x_preferred":[
        "Suki"
    ],
    "name:spa_x_preferred":[
        "Suki"
    ],
    "wof:name":"Sukhi",
    "wof:placetype":"locality",
    "wof:population":174
},
  "geometry": {"coordinates":[79.728758,30.520034],"type":"Point"}
}