{
  "type": "Feature",
  "properties": {
    "gn:admin1_code":"16",
    "gn:admin2_code":"511.0",
    "gn:asciiname":"Ratoli",
    "gn:country_code":"IN",
    "gn:dem":373,
    "gn:feature_class":"P",
    "gn:feature_code":"PPL",
    "gn:name":"Ratoli",
    "gn:population":0,
    "gn:timezone":"Asia/Kolkata",
    "iso:country":"IN",
    "wof:name":"Ratoli",
    "wof:placetype":"locality"
},
  "geometry": {"coordinates":[77.45325,18.74851],"type":"Point"}
}