{
  "type": "Feature",
  "properties": {
    "gn:admin1_code":"35",
    "gn:admin2_code":"463.0",
    "gn:asciiname":"Barwatola",
    "gn:country_code":"IN",
    "gn:dem":480,
    "gn:feature_class":"P",
    "gn:feature_code":"PPL",
    "gn:name":"Barw\u0101tola",
    "gn:population":0,
    "gn:timezone":"Asia/Kolkata",
    "iso:country":"IN",
    "ks:ks_alt_nam":"Barw\u0101tola",
    "ks:ks_name":"Barwatola",
    "ks:ks_type":"VILLAGE",
    "name:eng_x_preferred":[
        "Barwatola"
    ],
    "name:eng_x_variant":[
        "Barw\u0101tola"
    ],
    "wof:name":"Barwatola",
    "wof:placetype":"locality"
},
  "geometry": {"coordinates":[82.348423,24.022151],"type":"Point"}
}