{
  "type": "Feature",
  "properties": {
    "iso:country":"IN",
    "ks:ks_name":"Adooda",
    "ks:ks_pop":1334,
    "ks:ks_type":"HABITATION",
    "ks:ks_uagg_main":0,
    "name:eng_x_preferred":[
        "Adooda"
    ],
    "wof:name":"Adooda",
    "wof:placetype":"neighbourhood",
    "wof:population":1334
},
  "geometry": {"coordinates":[76.767099,26.301658],"type":"Point"}
}