{
  "type": "Feature",
  "properties": {
    "gn:admin1_code":"25.0",
    "gn:admin2_code":"631.0",
    "gn:asciiname":"Kattuppatti",
    "gn:country_code":"IN",
    "gn:dem":403,
    "gn:feature_class":"P",
    "gn:feature_code":"PPL",
    "gn:name":"Kattuppatti",
    "gn:population":0,
    "gn:timezone":"Asia/Kolkata",
    "iso:country":"IN",
    "wof:name":"Kattuppatti",
    "wof:placetype":"locality"
},
  "geometry": {"coordinates":[78.41689000000002,12.24798],"type":"Point"}
}