{
  "type": "Feature",
  "properties": {
    "iso:country":"IN",
    "ks:ks_name":"Chandwad",
    "ks:ks_pop":1664,
    "ks:ks_type":"VILLAGE",
    "name:eng_x_preferred":[
        "Chandwad"
    ],
    "wof:name":"Chandwad",
    "wof:placetype":"locality",
    "wof:population":1664
},
  "geometry": {"coordinates":[72.840242,19.959115],"type":"Point"}
}