{
  "type": "Feature",
  "properties": {
    "iso:country":"IN",
    "ks:ks_name":"Kimsera Lagga Baman Gaon",
    "ks:ks_pop":26,
    "ks:ks_type":"VILLAGE",
    "name:eng_x_preferred":[
        "Kimsera Lagga Baman Gaon"
    ],
    "wof:name":"Kimsera Lagga Baman Gaon",
    "wof:placetype":"locality",
    "wof:population":26
},
  "geometry": {"coordinates":[78.887125,29.761893],"type":"Point"}
}