{
  "type": "Feature",
  "properties": {
    "iso:country":"IN",
    "ks:ks_name":"Pohari Khania Gaon",
    "ks:ks_pop":744,
    "ks:ks_type":"HABITATION",
    "ks:ks_uagg_main":0,
    "name:eng_x_preferred":[
        "Pohari Khania Gaon"
    ],
    "wof:name":"Pohari Khania Gaon",
    "wof:placetype":"neighbourhood",
    "wof:population":744
},
  "geometry": {"coordinates":[94.86626699999999,27.451918],"type":"Point"}
}