{
  "type": "Feature",
  "properties": {
    "gn:admin1_code":"19.0",
    "gn:admin2_code":"584.0",
    "gn:asciiname":"Bhimagourdoddi",
    "gn:country_code":"IN",
    "gn:dem":778,
    "gn:feature_class":"P",
    "gn:feature_code":"PPL",
    "gn:name":"Bhimagourdoddi",
    "gn:population":0,
    "gn:timezone":"Asia/Kolkata",
    "iso:country":"IN",
    "wof:name":"Bhimagourdoddi",
    "wof:placetype":"neighbourhood"
},
  "geometry": {"coordinates":[77.57384999999999,12.64539],"type":"Point"}
}