{
  "type": "Feature",
  "properties": {
    "iso:country":"IN",
    "ks:ks_alt_nam":"Al\u0101walpur",
    "ks:ks_name":"Alawalpur",
    "ks:ks_type":"VILLAGE",
    "name:eng_x_preferred":[
        "Alawalpur"
    ],
    "name:eng_x_variant":[
        "Al\u0101walpur"
    ],
    "wof:name":"Alawalpur",
    "wof:placetype":"locality"
},
  "geometry": {"coordinates":[83.765018,25.75325],"type":"Point"}
}