{
  "type": "Feature",
  "properties": {
    "iso:country":"IN",
    "ks:ks_name":"Shekhu Purwa",
    "ks:ks_pop":143,
    "ks:ks_type":"HABITATION",
    "ks:ks_uagg_main":0,
    "name:eng_x_preferred":[
        "Shekhu Purwa"
    ],
    "wof:name":"Shekhu Purwa",
    "wof:placetype":"neighbourhood",
    "wof:population":143
},
  "geometry": {"coordinates":[80.486408,27.245378],"type":"Point"}
}