{
  "type": "Feature",
  "properties": {
    "gn:admin1_code":"11.0",
    "gn:admin2_code":"27.0",
    "gn:asciiname":"Haljoi",
    "gn:country_code":"IN",
    "gn:dem":1661,
    "gn:feature_class":"P",
    "gn:feature_code":"PPL",
    "gn:name":"Haljoi",
    "gn:population":0,
    "gn:timezone":"Asia/Kolkata",
    "iso:country":"IN",
    "wof:name":"Haljoi",
    "wof:placetype":"locality"
},
  "geometry": {"coordinates":[77.01694999999999,31.67044000000001],"type":"Point"}
}