{
  "type": "Feature",
  "properties": {
    "iso:country":"IN",
    "ks:ks_name":"Konkanwada",
    "ks:ks_pop":102,
    "ks:ks_type":"HABITATION",
    "name:eng_x_preferred":[
        "Konkanwada"
    ],
    "wof:name":"Konkanwada",
    "wof:placetype":"locality",
    "wof:population":102
},
  "geometry": {"coordinates":[74.24905,14.835841],"type":"Point"}
}