{
  "type": "Feature",
  "properties": {
    "gn:admin1_code":"38.0",
    "gn:admin2_code":"353.0",
    "gn:asciiname":"Balarampur",
    "gn:country_code":"IN",
    "gn:dem":58,
    "gn:feature_class":"P",
    "gn:feature_code":"PPL",
    "gn:name":"Balar\u0101mpur",
    "gn:population":0,
    "gn:timezone":"Asia/Kolkata",
    "iso:country":"IN",
    "ks:ks_name":"Balrampur",
    "ks:ks_pop":384,
    "ks:ks_type":"VILLAGE",
    "ks:ks_uagg_main":0,
    "name:cat_x_preferred":[
        "Balrampur"
    ],
    "name:ceb_x_preferred":[
        "Balrampur"
    ],
    "name:eng_x_preferred":[
        "Balrampur"
    ],
    "name:hin_x_preferred":[
        "\u092c\u0932\u0930\u093e\u092e\u092a\u0941\u0930"
    ],
    "name:ita_x_preferred":[
        "Balarampur"
    ],
    "name:nld_x_preferred":[
        "Balrampur"
    ],
    "name:pol_x_preferred":[
        "Balarampur"
    ],
    "name:rus_x_preferred":[
        "\u0411\u0430\u043b\u0440\u0430\u043c\u043f\u0443\u0440"
    ],
    "name:swe_x_preferred":[
        "Balrampur"
    ],
    "wof:name":"Balrampur",
    "wof:placetype":"neighbourhood",
    "wof:population":384
},
  "geometry": {"coordinates":[87.792801,24.554379],"type":"Point"}
}