{
  "type": "Feature",
  "properties": {
    "iso:country":"IN",
    "ks:ks_name":"Mipania Milik",
    "ks:ks_pop":766,
    "ks:ks_type":"VILLAGE",
    "name:eng_x_preferred":[
        "Mipania Milik"
    ],
    "wof:name":"Mipania Milik",
    "wof:placetype":"locality",
    "wof:population":766
},
  "geometry": {"coordinates":[87.206129,25.843255],"type":"Point"}
}