{
  "type": "Feature",
  "properties": {
    "iso:country":"IN",
    "ks:ks_name":"Bishnupur",
    "ks:ks_pop":704,
    "ks:ks_type":"HABITATION",
    "name:eng_x_preferred":[
        "Bishnupur"
    ],
    "name:hin_x_preferred":[
        "\u092c\u093f\u0936\u094d\u0928\u0941\u092a\u0941\u0930"
    ],
    "wof:name":"Bishnupur",
    "wof:placetype":"locality",
    "wof:population":704
},
  "geometry": {"coordinates":[86.87845,21.712529],"type":"Point"}
}