{
  "type": "Feature",
  "properties": {
    "iso:country":"IN",
    "ks:ks_alt_nam":"shiwaganwadi",
    "ks:ks_name":"Shiwaganwadi",
    "ks:ks_pop":66,
    "ks:ks_type":"HABITATION",
    "name:eng_x_preferred":[
        "Shiwaganwadi"
    ],
    "wof:name":"Shiwaganwadi",
    "wof:placetype":"locality",
    "wof:population":66
},
  "geometry": {"coordinates":[73.370225,16.620583],"type":"Point"}
}