{
  "type": "Feature",
  "properties": {
    "gn:admin1_code":"25.0",
    "gn:admin2_code":"628",
    "gn:asciiname":"Kudangulam",
    "gn:country_code":"IN",
    "gn:dem":22,
    "gn:feature_class":"P",
    "gn:feature_code":"PPL",
    "gn:name":"K\u016bdangulam",
    "gn:population":0,
    "gn:timezone":"Asia/Kolkata",
    "iso:country":"IN",
    "wof:name":"Kudangulam",
    "wof:placetype":"locality"
},
  "geometry": {"coordinates":[77.70586,8.19233],"type":"Point"}
}