{
  "type": "Feature",
  "properties": {
    "iso:country":"IN",
    "ks:ks_name":"Bahiro",
    "ks:ks_type":"VILLAGE",
    "ks:ks_uagg_main":0,
    "name:eng_x_preferred":[
        "Bahiro"
    ],
    "wof:name":"Bahiro",
    "wof:placetype":"neighbourhood"
},
  "geometry": {"coordinates":[84.675674,25.550312],"type":"Point"}
}