{
  "type": "Feature",
  "properties": {
    "iso:country":"IN",
    "ks:ks_name":"Kattalai Puliyakudi",
    "ks:ks_pop":456,
    "ks:ks_type":"HABITATION",
    "name:eng_x_preferred":[
        "Kattalai Puliyakudi"
    ],
    "wof:name":"Kattalai Puliyakudi",
    "wof:placetype":"locality",
    "wof:population":456
},
  "geometry": {"coordinates":[79.702219,10.87937],"type":"Point"}
}