{
  "type": "Feature",
  "properties": {
    "iso:country":"IN",
    "ks:ks_name":"Chak Deulpotar",
    "ks:ks_pop":323,
    "ks:ks_type":"VILLAGE",
    "ks:ks_uagg_main":0,
    "name:eng_x_preferred":[
        "Chak Deulpotar"
    ],
    "wof:name":"Chak Deulpotar",
    "wof:placetype":"neighbourhood",
    "wof:population":323
},
  "geometry": {"coordinates":[88.153498,22.205446],"type":"Point"}
}