{
  "type": "Feature",
  "properties": {
    "iso:country":"IN",
    "ks:ks_alt_nam":"doddahara",
    "ks:ks_name":"Doddahara",
    "ks:ks_pop":68,
    "ks:ks_type":"HABITATION",
    "name:eng_x_preferred":[
        "Doddahara"
    ],
    "wof:name":"Doddahara",
    "wof:placetype":"locality",
    "wof:population":68
},
  "geometry": {"coordinates":[75.539798,13.399107],"type":"Point"}
}