{
  "type": "Feature",
  "properties": {
    "iso:country":"IN",
    "ks:ks_alt_nam":"Ch\u0101chakpur",
    "ks:ks_name":"Chachakpur",
    "ks:ks_type":"VILLAGE",
    "ks:ks_uagg_main":0,
    "name:eng_x_preferred":[
        "Chachakpur"
    ],
    "name:eng_x_variant":[
        "Ch\u0101chakpur"
    ],
    "wof:name":"Chachakpur",
    "wof:placetype":"neighbourhood"
},
  "geometry": {"coordinates":[82.70052099999999,25.746114],"type":"Point"}
}