{
  "type": "Feature",
  "properties": {
    "iso:country":"IN",
    "ks:ks_alt_nam":"Kadm\u0101",
    "ks:ks_name":"Kadma",
    "ks:ks_type":"VILLAGE",
    "ks:ks_uagg_main":0,
    "name:eng_x_preferred":[
        "Kadma"
    ],
    "name:eng_x_variant":[
        "Kadm\u0101"
    ],
    "wof:name":"Kadma",
    "wof:placetype":"neighbourhood"
},
  "geometry": {"coordinates":[85.345347,23.987351],"type":"Point"}
}