{
  "type": "Feature",
  "properties": {
    "iso:country":"IN",
    "ks:ks_name":"Sahanewadi",
    "ks:ks_pop":191,
    "ks:ks_type":"HABITATION",
    "name:eng_x_preferred":[
        "Sahanewadi"
    ],
    "wof:name":"Sahanewadi",
    "wof:placetype":"locality",
    "wof:population":191
},
  "geometry": {"coordinates":[73.432222,17.399444],"type":"Point"}
}