{
  "type": "Feature",
  "properties": {
    "iso:country":"IN",
    "ks:ks_name":"Katimba",
    "ks:ks_pop":245,
    "ks:ks_type":"VILLAGE",
    "name:eng_x_preferred":[
        "Katimba"
    ],
    "wof:name":"Katimba",
    "wof:placetype":"locality",
    "wof:population":245
},
  "geometry": {"coordinates":[87.071529,24.485569],"type":"Point"}
}