{
  "type": "Feature",
  "properties": {
    "iso:country":"IN",
    "ks:ks_name":"Dholibawadi",
    "ks:ks_pop":573,
    "ks:ks_type":"HABITATION",
    "name:eng_x_preferred":[
        "Dholibawadi"
    ],
    "wof:name":"Dholibawadi",
    "wof:placetype":"locality",
    "wof:population":573
},
  "geometry": {"coordinates":[75.325676,22.321031],"type":"Point"}
}