{
  "type": "Feature",
  "properties": {
    "gn:admin1_code":"11.0",
    "gn:admin2_code":"033",
    "gn:asciiname":"Nalawan",
    "gn:country_code":"IN",
    "gn:dem":1204,
    "gn:feature_class":"P",
    "gn:feature_code":"PPL",
    "gn:name":"Nal\u0101w\u0101n",
    "gn:population":0,
    "gn:timezone":"Asia/Kolkata",
    "iso:country":"IN",
    "name:und_x_variant":[
        "Nal\u0101w\u0101n",
        "Nal\u0101wan"
    ],
    "wof:name":"Nalawan",
    "wof:placetype":"locality"
},
  "geometry": {"coordinates":[77.08219,31.21888],"type":"Point"}
}