{
  "type": "Feature",
  "properties": {
    "iso:country":"IN",
    "ks:ks_name":"Machhiguda",
    "ks:ks_pop":121,
    "ks:ks_type":"HABITATION",
    "name:eng_x_preferred":[
        "Machhiguda"
    ],
    "wof:name":"Machhiguda",
    "wof:placetype":"locality",
    "wof:population":121
},
  "geometry": {"coordinates":[79.197048,19.501627],"type":"Point"}
}