{
  "type": "Feature",
  "properties": {
    "iso:country":"IN",
    "ks:ks_name":"Karhaniya",
    "ks:ks_pop":441,
    "ks:ks_type":"VILLAGE",
    "name:eng_x_preferred":[
        "Karhaniya"
    ],
    "wof:name":"Karhaniya",
    "wof:placetype":"locality",
    "wof:population":441
},
  "geometry": {"coordinates":[82.108227,23.036437],"type":"Point"}
}