{
  "type": "Feature",
  "properties": {
    "gn:admin1_code":"31",
    "gn:admin2_code":"283.0",
    "gn:asciiname":"Tualbung",
    "gn:country_code":"IN",
    "gn:dem":1274,
    "gn:feature_class":"P",
    "gn:feature_code":"PPL",
    "gn:name":"Tualbung",
    "gn:population":0,
    "gn:timezone":"Asia/Kolkata",
    "iso:country":"IN",
    "wof:name":"Tualbung",
    "wof:placetype":"locality"
},
  "geometry": {"coordinates":[92.94045,23.76208],"type":"Point"}
}