{
  "type": "Feature",
  "properties": {
    "iso:country":"IN",
    "ks:ks_name":"Moish Khulipara",
    "ks:ks_pop":436,
    "ks:ks_type":"HABITATION",
    "name:eng_x_preferred":[
        "Moish Khulipara"
    ],
    "wof:name":"Moish Khulipara",
    "wof:placetype":"locality",
    "wof:population":436
},
  "geometry": {"coordinates":[90.915915,25.996521],"type":"Point"}
}