{
  "type": "Feature",
  "properties": {
    "iso:country":"IN",
    "ks:ks_name":"South Thathanaickenpatty",
    "ks:ks_pop":522,
    "ks:ks_type":"HABITATION",
    "name:eng_x_preferred":[
        "South Thathanaickenpatty"
    ],
    "wof:name":"South Thathanaickenpatty",
    "wof:placetype":"locality",
    "wof:population":522
},
  "geometry": {"coordinates":[77.425498,10.425657],"type":"Point"}
}