{
  "type": "Feature",
  "properties": {
    "iso:country":"IN",
    "ks:ks_name":"Honasekoppa",
    "ks:ks_pop":29,
    "ks:ks_type":"HABITATION",
    "name:eng_x_preferred":[
        "Honasekoppa"
    ],
    "wof:name":"Honasekoppa",
    "wof:placetype":"locality",
    "wof:population":29
},
  "geometry": {"coordinates":[75.166517,13.985556],"type":"Point"}
}