{
  "type": "Feature",
  "properties": {
    "iso:country":"IN",
    "ks:ks_name":"Meghana Muvada",
    "ks:ks_pop":293,
    "ks:ks_type":"HABITATION",
    "name:eng_x_preferred":[
        "Meghana Muvada"
    ],
    "wof:name":"Meghana Muvada",
    "wof:placetype":"locality",
    "wof:population":293
},
  "geometry": {"coordinates":[73.512889,23.296194],"type":"Point"}
}