{
  "type": "Feature",
  "properties": {
    "iso:country":"IN",
    "ks:ks_name":"Mali Faliya",
    "ks:ks_pop":790,
    "ks:ks_type":"HABITATION",
    "name:eng_x_preferred":[
        "Mali Faliya"
    ],
    "wof:name":"Mali Faliya",
    "wof:placetype":"locality",
    "wof:population":790
},
  "geometry": {"coordinates":[73.81358299999999,22.767],"type":"Point"}
}