{
  "type": "Feature",
  "properties": {
    "iso:country":"IN",
    "ks:ks_name":"Panchamukhi",
    "ks:ks_pop":110,
    "ks:ks_type":"HABITATION",
    "name:eng_x_preferred":[
        "Panchamukhi"
    ],
    "wof:name":"Panchamukhi",
    "wof:placetype":"locality",
    "wof:population":110
},
  "geometry": {"coordinates":[74.67131000000001,13.761121],"type":"Point"}
}