{
  "type": "Feature",
  "properties": {
    "iso:country":"IN",
    "ks:ks_alt_nam":"lachiram thanda",
    "ks:ks_name":"Lachiram Thanda",
    "ks:ks_pop":94,
    "ks:ks_type":"HABITATION",
    "name:eng_x_preferred":[
        "Lachiram Thanda"
    ],
    "wof:name":"Lachiram Thanda",
    "wof:placetype":"locality",
    "wof:population":94
},
  "geometry": {"coordinates":[77.96596700000001,16.760465],"type":"Point"}
}