{
  "type": "Feature",
  "properties": {
    "iso:country":"IN",
    "ks:ks_name":"Garud Punjee",
    "ks:ks_pop":435,
    "ks:ks_type":"HABITATION",
    "name:eng_x_preferred":[
        "Garud Punjee"
    ],
    "wof:name":"Garud Punjee",
    "wof:placetype":"locality",
    "wof:population":435
},
  "geometry": {"coordinates":[92.52976700000001,24.459673],"type":"Point"}
}