{
  "type": "Feature",
  "properties": {
    "gn:admin1_code":"36",
    "gn:admin2_code":"179.0",
    "gn:asciiname":"Kurwar",
    "gn:country_code":"IN",
    "gn:dem":103,
    "gn:feature_class":"P",
    "gn:feature_code":"PPL",
    "gn:name":"Kurw\u0101r",
    "gn:population":0,
    "gn:timezone":"Asia/Kolkata",
    "iso:country":"IN",
    "name:und_x_variant":[
        "Kurw\u0101r",
        "Kurw\u0101l"
    ],
    "wof:name":"Kurwar",
    "wof:placetype":"locality"
},
  "geometry": {"coordinates":[81.97874,26.3475],"type":"Point"}
}