{
  "type": "Feature",
  "properties": {
    "gn:country":"IN",
    "gn:fcode":"PPL",
    "gn:pop":17537,
    "iso:country":"IN",
    "name:ben_x_preferred":[
        "\u0995\u09cb\u09a6\u09cb\u09b2\u09bf"
    ],
    "name:bpy_x_preferred":[
        "\u0995\u09cb\u09a6\u09cb\u09b2\u09bf"
    ],
    "name:bul_x_preferred":[
        "\u041a\u043e\u0434\u043e\u043b\u0438"
    ],
    "name:chi_x_preferred":[
        "\u79d1\u591a\u5229"
    ],
    "name:dut_x_preferred":[
        "Kodoli"
    ],
    "name:eng_x_preferred":[
        "Kodoli"
    ],
    "name:ita_x_preferred":[
        "Kodoli"
    ],
    "name:may_x_preferred":[
        "Kodoli"
    ],
    "name:nan_x_preferred":[
        "Kodoli"
    ],
    "name:new_x_preferred":[
        "\u0915\u094b\u0926\u094b\u0932\u0940"
    ],
    "name:por_x_preferred":[
        "Kodoli"
    ],
    "name:swe_x_preferred":[
        "Kodoli"
    ],
    "name:urd_x_preferred":[
        "\u06a9\u0648\u0688\u0648\u0644\u06cc"
    ],
    "name:vie_x_preferred":[
        "Kodoli"
    ],
    "qs:name":"Kodoli",
    "qs:name_adm0":"India",
    "qs:name_adm1":"Maharashtra",
    "qs:photos_9r":0,
    "qs:photos_sr":0,
    "qs:placetype":"Town",
    "qs:pop_sr":"6",
    "wd:wordcount":542,
    "wof:name":"Kodoli",
    "wof:placetype":"locality",
    "wof:population":17537
},
  "geometry": {"coordinates":[74.1909,16.8764],"type":"Point"}
}