{
  "type": "Feature",
  "properties": {
    "iso:country":"IN",
    "ks:ks_alt_nam":"Kurat ki Gw\u0101ri",
    "ks:ks_alt_nam_2":"Kurat ki Gwari",
    "ks:ks_name":"Kurat Ki Gwari",
    "ks:ks_type":"VILLAGE",
    "name:eng_x_preferred":[
        "Kurat Ki Gwari"
    ],
    "name:eng_x_variant":[
        "Kurat ki Gw\u0101ri"
    ],
    "wof:name":"Kurat Ki Gwari",
    "wof:placetype":"locality"
},
  "geometry": {"coordinates":[77.05462300000001,26.3006],"type":"Point"}
}