{
  "type": "Feature",
  "properties": {
    "gn:admin1_code":"19.0",
    "gn:admin2_code":"562.0",
    "gn:asciiname":"Belur",
    "gn:country_code":"IN",
    "gn:dem":692,
    "gn:feature_class":"P",
    "gn:feature_code":"PPL",
    "gn:name":"Belur",
    "gn:population":0,
    "gn:timezone":"Asia/Kolkata",
    "iso:country":"IN",
    "name:msa_x_preferred":[
        "Belur"
    ],
    "wof:name":"Belur",
    "wof:placetype":"locality"
},
  "geometry": {"coordinates":[74.91125,15.53065],"type":"Point"}
}