{
  "type": "Feature",
  "properties": {
    "iso:country":"IN",
    "ks:ks_name":"Sundarpur",
    "ks:ks_pop":1210,
    "ks:ks_type":"VILLAGE",
    "name:eng_x_preferred":[
        "Sundarpur"
    ],
    "wof:name":"Sundarpur",
    "wof:placetype":"locality",
    "wof:population":1210
},
  "geometry": {"coordinates":[77.97218100000001,26.731155],"type":"Point"}
}