{
  "type": "Feature",
  "properties": {
    "gn:admin1_code":"37",
    "gn:admin2_code":"417.0",
    "gn:asciiname":"Redi",
    "gn:country_code":"IN",
    "gn:dem":333,
    "gn:feature_class":"P",
    "gn:feature_code":"PPL",
    "gn:name":"Redi",
    "gn:population":0,
    "gn:timezone":"Asia/Kolkata",
    "iso:country":"IN",
    "ks:ks_name":"Reddi",
    "ks:ks_pop":317,
    "ks:ks_type":"VILLAGE",
    "name:deu_x_preferred":[
        "Redi"
    ],
    "name:eng_x_preferred":[
        "Reddi"
    ],
    "name:eng_x_variant":[
        "Redi"
    ],
    "name:fin_x_preferred":[
        "Redi"
    ],
    "name:ita_x_preferred":[
        "Redi"
    ],
    "name:rus_x_preferred":[
        "\u0420\u0435\u0434\u0438"
    ],
    "wof:name":"Reddi",
    "wof:placetype":"locality",
    "wof:population":317
},
  "geometry": {"coordinates":[80.988207,18.803263],"type":"Point"}
}