{
  "type": "Feature",
  "properties": {
    "gn:admin1_code":"13.0",
    "gn:admin2_code":"590.0",
    "gn:asciiname":"Vellankolli",
    "gn:country_code":"IN",
    "gn:dem":767,
    "gn:feature_class":"P",
    "gn:feature_code":"PPL",
    "gn:name":"Vellankolli",
    "gn:population":0,
    "gn:timezone":"Asia/Kolkata",
    "iso:country":"IN",
    "wof:name":"Vellankolli",
    "wof:placetype":"locality"
},
  "geometry": {"coordinates":[76.15621999999998,11.6928],"type":"Point"}
}