{
  "type": "Feature",
  "properties": {
    "gn:admin1_code":"12.0",
    "gn:admin2_code":"021",
    "gn:asciiname":"Kandeal",
    "gn:country_code":"IN",
    "gn:dem":369,
    "gn:feature_class":"P",
    "gn:feature_code":"PPL",
    "gn:name":"Kande\u0101l",
    "gn:population":0,
    "gn:timezone":"Asia/Kolkata",
    "iso:country":"IN",
    "name:und_x_variant":[
        "Kande\u0101l",
        "Kande\u0101i"
    ],
    "wof:name":"Kandeal",
    "wof:placetype":"locality"
},
  "geometry": {"coordinates":[74.55679000000001,32.8761],"type":"Point"}
}