{
  "type": "Feature",
  "properties": {
    "iso:country":"IN",
    "ks:ks_name":"Benawale",
    "ks:ks_pop":827,
    "ks:ks_type":"HABITATION",
    "name:eng_x_preferred":[
        "Benawale"
    ],
    "wof:name":"Benawale",
    "wof:placetype":"locality",
    "wof:population":827
},
  "geometry": {"coordinates":[73.037137,18.755721],"type":"Point"}
}