{
  "type": "Feature",
  "properties": {
    "gn:admin1_code":"23",
    "gn:admin2_code":"50.0",
    "gn:asciiname":"Vairowal",
    "gn:country_code":"IN",
    "gn:dem":232,
    "gn:feature_class":"P",
    "gn:feature_code":"PPL",
    "gn:name":"Vairow\u0101l",
    "gn:population":0,
    "gn:timezone":"Asia/Kolkata",
    "iso:country":"IN",
    "name:und_x_variant":[
        "Vairowa",
        "V\u0101irow\u0101l",
        "Vairow\u0101l"
    ],
    "wof:name":"Vairowal",
    "wof:placetype":"locality"
},
  "geometry": {"coordinates":[75.16164999999999,31.412],"type":"Point"}
}