{
  "type": "Feature",
  "properties": {
    "iso:country":"IN",
    "ks:ks_name":"Gour Sai",
    "ks:ks_pop":172,
    "ks:ks_type":"VILLAGE",
    "ks:ks_uagg_main":0,
    "name:eng_x_preferred":[
        "Gour Sai"
    ],
    "wof:name":"Gour Sai",
    "wof:placetype":"neighbourhood",
    "wof:population":172
},
  "geometry": {"coordinates":[87.11491100000001,21.950744],"type":"Point"}
}