{
  "type": "Feature",
  "properties": {
    "iso:country":"IN",
    "ks:ks_name":"Siharia",
    "ks:ks_type":"VILLAGE",
    "name:eng_x_preferred":[
        "Siharia"
    ],
    "wof:name":"Siharia",
    "wof:placetype":"locality"
},
  "geometry": {"coordinates":[78.40570099999999,28.562327],"type":"Point"}
}