{
  "type": "Feature",
  "properties": {
    "iso:country":"IN",
    "ks:ks_alt_nam":"LOHAR LINE",
    "ks:ks_name":"Lohar Line",
    "ks:ks_pop":815,
    "ks:ks_type":"HABITATION",
    "name:eng_x_preferred":[
        "Lohar Line"
    ],
    "wof:name":"Lohar Line",
    "wof:placetype":"locality",
    "wof:population":815
},
  "geometry": {"coordinates":[88.667064,26.608999],"type":"Point"}
}