{
  "type": "Feature",
  "properties": {
    "gn:admin1_code":"16.0",
    "gn:admin2_code":"503.0",
    "gn:asciiname":"Jahangirpur",
    "gn:country_code":"IN",
    "gn:dem":306,
    "gn:feature_class":"P",
    "gn:feature_code":"PPL",
    "gn:name":"Jah\u0101ng\u012brpur",
    "gn:population":0,
    "gn:timezone":"Asia/Kolkata",
    "iso:country":"IN",
    "wof:name":"Jahangirpur",
    "wof:placetype":"locality"
},
  "geometry": {"coordinates":[78.10659,20.9595],"type":"Point"}
}