{
  "type": "Feature",
  "properties": {
    "gn:admin1_code":"39.0",
    "gn:admin2_code":"66.0",
    "gn:asciiname":"Salkwar",
    "gn:country_code":"IN",
    "gn:dem":1239,
    "gn:feature_class":"P",
    "gn:feature_code":"PPL",
    "gn:name":"Salkw\u0101r",
    "gn:population":0,
    "gn:timezone":"Asia/Kolkata",
    "iso:country":"IN",
    "wof:name":"Salkwar",
    "wof:placetype":"locality"
},
  "geometry": {"coordinates":[79.90488000000001,29.21886],"type":"Point"}
}