{
  "type": "Feature",
  "properties": {
    "iso:country":"IN",
    "ks:ks_name":"Chinna Kottaikarai",
    "ks:ks_pop":181,
    "ks:ks_type":"HABITATION",
    "name:eng_x_preferred":[
        "Chinna Kottaikarai"
    ],
    "wof:name":"Chinna Kottaikarai",
    "wof:placetype":"locality",
    "wof:population":181
},
  "geometry": {"coordinates":[79.0852,12.662984],"type":"Point"}
}