{
  "type": "Feature",
  "properties": {
    "gn:admin1_code":"2.0",
    "gn:admin2_code":"550.0",
    "gn:asciiname":"Josyulavarikhandrika",
    "gn:country_code":"IN",
    "gn:dem":34,
    "gn:feature_class":"P",
    "gn:feature_code":"PPL",
    "gn:name":"Josyulav\u0101rikhandrika",
    "gn:population":0,
    "gn:timezone":"Asia/Kolkata",
    "iso:country":"IN",
    "wof:name":"Josyulavarikhandrika",
    "wof:placetype":"locality"
},
  "geometry": {"coordinates":[79.88508,13.92352],"type":"Point"}
}