{
  "type": "Feature",
  "properties": {
    "iso:country":"IN",
    "ks:ks_name":"Fatehpur",
    "ks:ks_pop":220,
    "ks:ks_type":"VILLAGE",
    "name:eng_x_preferred":[
        "Fatehpur"
    ],
    "wof:name":"Fatehpur",
    "wof:placetype":"locality",
    "wof:population":220
},
  "geometry": {"coordinates":[85.53375200000001,26.135083],"type":"Point"}
}