{
  "type": "Feature",
  "properties": {
    "gn:admin1_code":"24.0",
    "gn:admin2_code":"128.0",
    "gn:asciiname":"Khatoli",
    "gn:country_code":"IN",
    "gn:dem":336,
    "gn:feature_class":"P",
    "gn:feature_code":"PPL",
    "gn:name":"Kh\u0101toli",
    "gn:population":0,
    "gn:timezone":"Asia/Kolkata",
    "iso:country":"IN",
    "ks:ks_alt_nam":"Kh\u0101toli",
    "ks:ks_name":"Khatoli",
    "ks:ks_pop":613,
    "ks:ks_type":"VILLAGE",
    "name:eng_x_preferred":[
        "Khatoli"
    ],
    "name:eng_x_variant":[
        "Kh\u0101toli"
    ],
    "wof:name":"Khatoli",
    "wof:placetype":"locality",
    "wof:population":613
},
  "geometry": {"coordinates":[76.847042,24.709766],"type":"Point"}
}