{
  "type": "Feature",
  "properties": {
    "iso:country":"IN",
    "ks:ks_alt_nam":"B\u0101r\u016bband Reserved Forest",
    "ks:ks_name":"Baruband Reserved Forest",
    "ks:ks_type":"VILLAGE",
    "name:eng_x_preferred":[
        "Baruband Reserved Forest"
    ],
    "name:eng_x_variant":[
        "B\u0101r\u016bband Reserved Forest"
    ],
    "wof:name":"Baruband Reserved Forest",
    "wof:placetype":"locality"
},
  "geometry": {"coordinates":[79.73281299999999,22.488283],"type":"Point"}
}