{
  "type": "Feature",
  "properties": {
    "iso:country":"IN",
    "ks:ks_name":"Lataulamai Chak",
    "ks:ks_pop":34,
    "ks:ks_type":"HABITATION",
    "name:eng_x_preferred":[
        "Lataulamai Chak"
    ],
    "wof:name":"Lataulamai Chak",
    "wof:placetype":"locality",
    "wof:population":34
},
  "geometry": {"coordinates":[79.978363,29.761175],"type":"Point"}
}