{
  "type": "Feature",
  "properties": {
    "iso:country":"IN",
    "ks:ks_name":"Vadakkekat",
    "ks:ks_pop":1860,
    "ks:ks_type":"HABITATION",
    "name:eng_x_preferred":[
        "Vadakkekat"
    ],
    "wof:name":"Vadakkekat",
    "wof:placetype":"locality",
    "wof:population":1860
},
  "geometry": {"coordinates":[76.456976,10.544693],"type":"Point"}
}