{
  "type": "Feature",
  "properties": {
    "iso:country":"IN",
    "ks:ks_name":"Mehendipara",
    "ks:ks_pop":309,
    "ks:ks_type":"VILLAGE",
    "ks:ks_uagg_main":0,
    "name:eng_x_preferred":[
        "Mehendipara"
    ],
    "wof:name":"Mehendipara",
    "wof:placetype":"locality",
    "wof:population":309
},
  "geometry": {"coordinates":[88.278479,25.542118],"type":"Point"}
}