{
  "type": "Feature",
  "properties": {
    "gn:admin1_code":"19.0",
    "gn:admin2_code":"572.0",
    "gn:asciiname":"Shingasandra",
    "gn:country_code":"IN",
    "gn:dem":940,
    "gn:feature_class":"P",
    "gn:feature_code":"PPL",
    "gn:name":"Shingasandra",
    "gn:population":0,
    "gn:timezone":"Asia/Kolkata",
    "iso:country":"IN",
    "wof:name":"Shingasandra",
    "wof:placetype":"locality"
},
  "geometry": {"coordinates":[77.69776999999998,12.6847],"type":"Point"}
}