{
  "type": "Feature",
  "properties": {
    "iso:country":"IN",
    "ks:ks_alt_nam":"Deeplanaik thanda",
    "ks:ks_name":"Deeplanaik Thanda",
    "ks:ks_pop":148,
    "ks:ks_type":"HABITATION",
    "name:eng_x_preferred":[
        "Deeplanaik Thanda"
    ],
    "wof:name":"Deeplanaik Thanda",
    "wof:placetype":"locality",
    "wof:population":148
},
  "geometry": {"coordinates":[77.677831,17.11684],"type":"Point"}
}