{
  "type": "Feature",
  "properties": {
    "gn:admin1_code":"25.0",
    "gn:admin2_code":"620.0",
    "gn:asciiname":"Vittalur",
    "gn:country_code":"IN",
    "gn:dem":25,
    "gn:feature_class":"P",
    "gn:feature_code":"PPL",
    "gn:name":"Vittal\u016br",
    "gn:population":0,
    "gn:timezone":"Asia/Kolkata",
    "iso:country":"IN",
    "name:tam_x_preferred":[
        "\u0bb5\u0bbf\u0b9f\u0bcd\u0b9f\u0bb2\u0bc2\u0bb0\u0bcd"
    ],
    "wof:name":"Vittalur",
    "wof:placetype":"locality"
},
  "geometry": {"coordinates":[79.48210999999998,10.98011],"type":"Point"}
}