{
  "type": "Feature",
  "properties": {
    "iso:country":"IN",
    "ks:ks_name":"Baraibari Pt I",
    "ks:ks_pop":101,
    "ks:ks_type":"HABITATION",
    "name:eng_x_preferred":[
        "Baraibari Pt I"
    ],
    "wof:name":"Baraibari Pt I",
    "wof:placetype":"locality",
    "wof:population":101
},
  "geometry": {"coordinates":[90.043767,26.079031],"type":"Point"}
}