{
  "type": "Feature",
  "properties": {
    "gn:admin1_code":"34.0",
    "gn:admin2_code":"220.0",
    "gn:asciiname":"Basantpur Kakrahta",
    "gn:country_code":"IN",
    "gn:dem":52,
    "gn:feature_class":"P",
    "gn:feature_code":"PPL",
    "gn:name":"Basantpur Kakrahta",
    "gn:population":0,
    "gn:timezone":"Asia/Kolkata",
    "iso:country":"IN",
    "ks:ks_name":"Bishanpur Kakrahta",
    "ks:ks_pop":1707,
    "ks:ks_type":"VILLAGE",
    "name:eng_x_preferred":[
        "Bishanpur Kakrahta"
    ],
    "name:eng_x_variant":[
        "Basantpur Kakrahta"
    ],
    "wof:name":"Bishanpur Kakrahta",
    "wof:placetype":"locality",
    "wof:population":1707
},
  "geometry": {"coordinates":[85.336827,25.66554],"type":"Point"}
}