{
  "type": "Feature",
  "properties": {
    "gn:admin1_code":"34.0",
    "gn:admin2_code":"235.0",
    "gn:asciiname":"Amdiha",
    "gn:country_code":"IN",
    "gn:dem":146,
    "gn:feature_class":"P",
    "gn:feature_code":"PPL",
    "gn:name":"Amd\u012bh\u0101",
    "gn:population":0,
    "gn:timezone":"Asia/Kolkata",
    "iso:country":"IN",
    "ks:ks_alt_nam":"Amd\u012bh\u0101",
    "ks:ks_name":"Amdiha",
    "ks:ks_pop":332,
    "ks:ks_type":"VILLAGE",
    "name:eng_x_preferred":[
        "Amdiha"
    ],
    "name:eng_x_variant":[
        "Amd\u012bh\u0101"
    ],
    "wof:name":"Amdiha",
    "wof:placetype":"locality",
    "wof:population":332
},
  "geometry": {"coordinates":[84.067624,24.592127],"type":"Point"}
}