{
  "type": "Feature",
  "properties": {
    "gn:admin1_code":"11.0",
    "gn:admin2_code":"33.0",
    "gn:asciiname":"Sanai",
    "gn:country_code":"IN",
    "gn:dem":2321,
    "gn:feature_class":"P",
    "gn:feature_code":"PPL",
    "gn:name":"Sanai",
    "gn:population":0,
    "gn:timezone":"Asia/Kolkata",
    "iso:country":"IN",
    "name:ara_x_preferred":[
        "\u0627\u0644\u0633\u0646\u0627\u0626\u064a"
    ],
    "name:azb_x_preferred":[
        "\u0633\u0646\u0627\u06cc\u06cc"
    ],
    "name:aze_x_preferred":[
        "S\u0259nai"
    ],
    "name:epo_x_preferred":[
        "Sanai"
    ],
    "name:fas_x_preferred":[
        "\u0633\u0646\u0627\u06cc\u06cc"
    ],
    "name:fra_x_preferred":[
        "Sana\u00ef"
    ],
    "name:jpn_x_preferred":[
        "\u30b5\u30ca\u30fc\u30a4\u30fc"
    ],
    "name:kor_x_preferred":[
        "\uc0ac\ub098\uc774"
    ],
    "name:new_x_preferred":[
        "\u0938\u093e\u0928\u093e\u0907"
    ],
    "name:nor_x_preferred":[
        "Sana'i"
    ],
    "name:pnb_x_preferred":[
        "\u0633\u0646\u0627\u0626\u06cc \u063a\u0632\u0646\u0648\u06cc"
    ],
    "name:rus_x_preferred":[
        "\u0421\u0430\u043d\u0430\u0438"
    ],
    "name:spa_x_preferred":[
        "Sanai"
    ],
    "name:srp_x_preferred":[
        "\u0421\u0430\u043d\u0430\u0438"
    ],
    "name:swe_x_preferred":[
        "Sana'i"
    ],
    "name:tgk_x_preferred":[
        "\u0421\u0430\u043d\u043e\u04e3"
    ],
    "name:tur_x_preferred":[
        "Sena\u00ee"
    ],
    "name:urd_x_preferred":[
        "\u0633\u0646\u0627\u0626\u06cc \u063a\u0632\u0646\u0648\u06cc"
    ],
    "name:zho_x_preferred":[
        "\u85a9\u7d0d\u4f0a"
    ],
    "wof:name":"Sanai",
    "wof:placetype":"locality"
},
  "geometry": {"coordinates":[77.67784,31.42351],"type":"Point"}
}