{
  "type": "Feature",
  "properties": {
    "iso:country":"IN",
    "ks:ks_name":"Mulgam Falia",
    "ks:ks_pop":102,
    "ks:ks_type":"HABITATION",
    "name:eng_x_preferred":[
        "Mulgam Falia"
    ],
    "wof:name":"Mulgam Falia",
    "wof:placetype":"locality",
    "wof:population":102
},
  "geometry": {"coordinates":[73.266278,20.197861],"type":"Point"}
}