{
  "type": "Feature",
  "properties": {
    "gn:admin1_code":"19.0",
    "gn:admin2_code":"574.0",
    "gn:asciiname":"Jekkahalli",
    "gn:country_code":"IN",
    "gn:dem":946,
    "gn:feature_class":"P",
    "gn:feature_code":"PPL",
    "gn:name":"Jekkahalli",
    "gn:population":0,
    "gn:timezone":"Asia/Kolkata",
    "iso:country":"IN",
    "wof:name":"Jekkahalli",
    "wof:placetype":"locality"
},
  "geometry": {"coordinates":[76.0004,12.68523],"type":"Point"}
}