{
  "type": "Feature",
  "properties": {
    "gn:admin1_code":"12.0",
    "gn:admin2_code":"1.0",
    "gn:asciiname":"Lokut Dardahaj",
    "gn:country_code":"IN",
    "gn:dem":2041,
    "gn:feature_class":"P",
    "gn:feature_code":"PPL",
    "gn:name":"Lokut Dardah\u0101j",
    "gn:population":0,
    "gn:timezone":"Asia/Kolkata",
    "iso:country":"IN",
    "wof:name":"Lokut Dardahaj",
    "wof:placetype":"locality"
},
  "geometry": {"coordinates":[74.1019,34.4189],"type":"Point"}
}