{
  "type": "Feature",
  "properties": {
    "iso:country":"IN",
    "ks:ks_alt_nam":"BIR CHANDRA THAKUR PARA",
    "ks:ks_name":"Bir Chandra Thakur Para",
    "ks:ks_pop":280,
    "ks:ks_type":"HABITATION",
    "ks:ks_uagg_main":0,
    "name:eng_x_preferred":[
        "Bir Chandra Thakur Para"
    ],
    "wof:name":"Bir Chandra Thakur Para",
    "wof:placetype":"neighbourhood",
    "wof:population":280
},
  "geometry": {"coordinates":[91.59334699999999,23.956186],"type":"Point"}
}