{
  "type": "Feature",
  "properties": {
    "iso:country":"IN",
    "ks:ks_name":"Vikaswadi",
    "ks:ks_pop":300,
    "ks:ks_type":"HABITATION",
    "name:eng_x_preferred":[
        "Vikaswadi"
    ],
    "wof:name":"Vikaswadi",
    "wof:placetype":"locality",
    "wof:population":300
},
  "geometry": {"coordinates":[74.232748,19.228128],"type":"Point"}
}