{
  "type": "Feature",
  "properties": {
    "gn:admin1_code":"37",
    "gn:admin2_code":"401.0",
    "gn:asciiname":"Asandih",
    "gn:country_code":"IN",
    "gn:dem":392,
    "gn:feature_class":"P",
    "gn:feature_code":"PPL",
    "gn:name":"Asand\u012bh",
    "gn:population":0,
    "gn:timezone":"Asia/Kolkata",
    "iso:country":"IN",
    "ks:ks_alt_nam":"Asand\u012bh",
    "ks:ks_name":"Asandih",
    "ks:ks_pop":616,
    "ks:ks_type":"VILLAGE",
    "name:eng_x_preferred":[
        "Asandih"
    ],
    "name:eng_x_variant":[
        "Asand\u012bh"
    ],
    "wof:name":"Asandih",
    "wof:placetype":"locality",
    "wof:population":616
},
  "geometry": {"coordinates":[83.14991000000001,23.903097],"type":"Point"}
}