{
  "type": "Feature",
  "properties": {
    "gn:admin1_code":"37",
    "gn:admin2_code":"401.0",
    "gn:asciiname":"Asandih",
    "gn:country_code":"IN",
    "gn:dem":392,
    "gn:feature_class":"P",
    "gn:feature_code":"PPL",
    "gn:name":"Asand\u012bh",
    "gn:population":0,
    "gn:timezone":"Asia/Kolkata",
    "iso:country":"IN",
    "wof:name":"Asandih",
    "wof:placetype":"locality"
},
  "geometry": {"coordinates":[83.15245999999998,23.90178],"type":"Point"}
}