{
  "type": "Feature",
  "properties": {
    "gn:admin1_code":"2.0",
    "gn:admin2_code":"550.0",
    "gn:asciiname":"Parlapadu",
    "gn:country_code":"IN",
    "gn:dem":13,
    "gn:feature_class":"P",
    "gn:feature_code":"PPL",
    "gn:name":"Parlap\u0101du",
    "gn:population":0,
    "gn:timezone":"Asia/Kolkata",
    "iso:country":"IN",
    "ks:ks_alt_nam":"Parlap\u0101du",
    "ks:ks_name":"Parlapadu",
    "ks:ks_pop":360,
    "ks:ks_type":"VILLAGE",
    "name:eng_x_preferred":[
        "Parlapadu"
    ],
    "name:eng_x_variant":[
        "Parlap\u0101du"
    ],
    "wof:name":"Parlapadu",
    "wof:placetype":"locality",
    "wof:population":360
},
  "geometry": {"coordinates":[79.854862,14.267841],"type":"Point"}
}