{
  "type": "Feature",
  "properties": {
    "iso:country":"IN",
    "ks:ks_name":"Maniyangudi",
    "ks:ks_pop":202,
    "ks:ks_type":"HABITATION",
    "name:eng_x_preferred":[
        "Maniyangudi"
    ],
    "wof:name":"Maniyangudi",
    "wof:placetype":"locality",
    "wof:population":202
},
  "geometry": {"coordinates":[78.699445,9.793842],"type":"Point"}
}