{
  "type": "Feature",
  "properties": {
    "iso:country":"IN",
    "ks:ks_name":"Kengaje",
    "ks:ks_pop":50,
    "ks:ks_type":"HABITATION",
    "name:eng_x_preferred":[
        "Kengaje"
    ],
    "wof:name":"Kengaje",
    "wof:placetype":"locality",
    "wof:population":50
},
  "geometry": {"coordinates":[74.96541499999999,13.217752],"type":"Point"}
}