{
  "type": "Feature",
  "properties": {
    "iso:country":"IN",
    "ks:ks_alt_nam":"Sarra FV",
    "ks:ks_name":"Sarra Fv",
    "ks:ks_pop":126,
    "ks:ks_type":"HABITATION",
    "name:eng_x_preferred":[
        "Sarra Fv"
    ],
    "wof:name":"Sarra Fv",
    "wof:placetype":"locality",
    "wof:population":126
},
  "geometry": {"coordinates":[80.35213899999999,21.834428],"type":"Point"}
}