{
  "type": "Feature",
  "properties": {
    "iso:country":"IN",
    "ks:ks_name":"Gitingy Tea Garden",
    "ks:ks_pop":345,
    "ks:ks_type":"VILLAGE",
    "name:eng_x_preferred":[
        "Gitingy Tea Garden"
    ],
    "wof:name":"Gitingy Tea Garden",
    "wof:placetype":"locality",
    "wof:population":345
},
  "geometry": {"coordinates":[88.349554,26.874788],"type":"Point"}
}