{
  "type": "Feature",
  "properties": {
    "gn:admin1_code":"37",
    "gn:admin2_code":"408.0",
    "gn:asciiname":"Bagdoh",
    "gn:country_code":"IN",
    "gn:dem":386,
    "gn:feature_class":"P",
    "gn:feature_code":"PPL",
    "gn:name":"B\u0101gdoh",
    "gn:population":0,
    "gn:timezone":"Asia/Kolkata",
    "iso:country":"IN",
    "ks:ks_alt_nam":"B\u0101gdoh Reserved Forest",
    "ks:ks_alt_nam_2":"Bagdoh Reserved Forest",
    "ks:ks_name":"Bagdoh",
    "ks:ks_pop":208,
    "ks:ks_type":"VILLAGE",
    "name:eng_x_preferred":[
        "Bagdoh"
    ],
    "name:eng_x_variant":[
        "B\u0101gdoh Reserved Forest",
        "Bagdoh Reserved Forest"
    ],
    "wof:name":"Bagdoh",
    "wof:placetype":"locality",
    "wof:population":208
},
  "geometry": {"coordinates":[80.918491,20.661781],"type":"Point"}
}