{
  "type": "Feature",
  "properties": {
    "iso:country":"IN",
    "ks:ks_name":"Chokalamakki",
    "ks:ks_pop":150,
    "ks:ks_type":"HABITATION",
    "name:eng_x_preferred":[
        "Chokalamakki"
    ],
    "wof:name":"Chokalamakki",
    "wof:placetype":"locality",
    "wof:population":150
},
  "geometry": {"coordinates":[74.895347,13.681051],"type":"Point"}
}