{
  "type": "Feature",
  "properties": {
    "iso:country":"IN",
    "ks:ks_name":"Koilpattu",
    "ks:ks_pop":150,
    "ks:ks_type":"HABITATION",
    "name:eng_x_preferred":[
        "Koilpattu"
    ],
    "wof:name":"Koilpattu",
    "wof:placetype":"locality",
    "wof:population":150
},
  "geometry": {"coordinates":[79.560947,11.151727],"type":"Point"}
}