{
  "type": "Feature",
  "properties": {
    "iso:country":"IN",
    "ks:ks_name":"Nishanwadi Malegaon K",
    "ks:ks_pop":262,
    "ks:ks_type":"HABITATION",
    "name:eng_x_preferred":[
        "Nishanwadi Malegaon K"
    ],
    "wof:name":"Nishanwadi Malegaon K",
    "wof:placetype":"locality",
    "wof:population":262
},
  "geometry": {"coordinates":[74.51502499999999,20.206526],"type":"Point"}
}