{
  "type": "Feature",
  "properties": {
    "iso:country":"IN",
    "ks:ks_name":"Dhurwah",
    "ks:ks_pop":277,
    "ks:ks_type":"HABITATION",
    "name:eng_x_preferred":[
        "Dhurwah"
    ],
    "wof:name":"Dhurwah",
    "wof:placetype":"locality",
    "wof:population":277
},
  "geometry": {"coordinates":[82.98869500000001,24.272019],"type":"Point"}
}