{
  "type": "Feature",
  "properties": {
    "iso:country":"IN",
    "ks:ks_name":"Channappara",
    "ks:ks_pop":801,
    "ks:ks_type":"HABITATION",
    "name:eng_x_preferred":[
        "Channappara"
    ],
    "wof:name":"Channappara",
    "wof:placetype":"locality",
    "wof:population":801
},
  "geometry": {"coordinates":[75.76482900000001,11.893606],"type":"Point"}
}