{
  "type": "Feature",
  "properties": {
    "iso:country":"IN",
    "ks:ks_name":"Maravanvayal",
    "ks:ks_pop":273,
    "ks:ks_type":"VILLAGE",
    "name:eng_x_preferred":[
        "Maravanvayal"
    ],
    "wof:name":"Maravanvayal",
    "wof:placetype":"locality",
    "wof:population":273
},
  "geometry": {"coordinates":[79.253063,10.227963],"type":"Point"}
}