{
  "type": "Feature",
  "properties": {
    "gn:admin1_code":"23",
    "gn:admin2_code":"38.0",
    "gn:asciiname":"Dugri",
    "gn:country_code":"IN",
    "gn:dem":256,
    "gn:feature_class":"P",
    "gn:feature_code":"PPL",
    "gn:name":"Dugri",
    "gn:population":0,
    "gn:timezone":"Asia/Kolkata",
    "iso:country":"IN",
    "name:pan_x_preferred":[
        "\u0a26\u0a41\u0a71\u0a17\u0a30\u0a40"
    ],
    "wof:name":"Dugri",
    "wof:placetype":"locality"
},
  "geometry": {"coordinates":[75.61193,31.92511],"type":"Point"}
}