{
  "type": "Feature",
  "properties": {
    "gn:admin1_code":"23.0",
    "gn:admin2_code":"38.0",
    "gn:asciiname":"Dholbaha",
    "gn:country_code":"IN",
    "gn:dem":402,
    "gn:feature_class":"P",
    "gn:feature_code":"PPL",
    "gn:name":"Dholbaha",
    "gn:population":0,
    "gn:timezone":"Asia/Kolkata",
    "iso:country":"IN",
    "wof:name":"Dholbaha",
    "wof:placetype":"locality"
},
  "geometry": {"coordinates":[75.8755,31.73927],"type":"Point"}
}