{
  "type": "Feature",
  "properties": {
    "iso:country":"IN",
    "ks:ks_name":"Jagannathapur",
    "ks:ks_pop":513,
    "ks:ks_type":"VILLAGE",
    "name:eng_x_preferred":[
        "Jagannathapur"
    ],
    "wof:name":"Jagannathapur",
    "wof:placetype":"locality",
    "wof:population":513
},
  "geometry": {"coordinates":[86.706931,20.557449],"type":"Point"}
}