{
  "type": "Feature",
  "properties": {
    "iso:country":"IN",
    "ks:ks_name":"Adachiwadi",
    "ks:ks_pop":140,
    "ks:ks_type":"HABITATION",
    "name:eng_x_preferred":[
        "Adachiwadi"
    ],
    "wof:name":"Adachiwadi",
    "wof:placetype":"locality",
    "wof:population":140
},
  "geometry": {"coordinates":[73.39420200000001,18.030223],"type":"Point"}
}