{
  "type": "Feature",
  "properties": {
    "iso:country":"IN",
    "ks:ks_alt_nam":"warchiwadi",
    "ks:ks_name":"Warchiwadi",
    "ks:ks_pop":219,
    "ks:ks_type":"HABITATION",
    "name:eng_x_preferred":[
        "Warchiwadi"
    ],
    "wof:name":"Warchiwadi",
    "wof:placetype":"locality",
    "wof:population":219
},
  "geometry": {"coordinates":[73.575656,15.926123],"type":"Point"}
}