{
  "type": "Feature",
  "properties": {
    "gn:admin1_code":"19.0",
    "gn:admin2_code":"568.0",
    "gn:asciiname":"Alahalli",
    "gn:country_code":"IN",
    "gn:dem":586,
    "gn:feature_class":"P",
    "gn:feature_code":"PPL",
    "gn:name":"\u0100lahalli",
    "gn:population":0,
    "gn:timezone":"Asia/Kolkata",
    "iso:country":"IN",
    "name:fas_x_preferred":[
        "\u0627\u0644\u0627\u0647\u0627\u0644\u06cc"
    ],
    "name:vie_x_preferred":[
        "Alahalli"
    ],
    "wof:name":"Alahalli",
    "wof:placetype":"locality"
},
  "geometry": {"coordinates":[75.06744,14.63521],"type":"Point"}
}