{
  "type": "Feature",
  "properties": {
    "iso:country":"IN",
    "ks:ks_name":"Nutandih",
    "ks:ks_pop":386,
    "ks:ks_type":"VILLAGE",
    "name:eng_x_preferred":[
        "Nutandih"
    ],
    "wof:name":"Nutandih",
    "wof:placetype":"neighbourhood",
    "wof:population":386
},
  "geometry": {"coordinates":[86.284065,22.791349],"type":"Point"}
}