{
  "type": "Feature",
  "properties": {
    "gn:admin1_code":"36.0",
    "gn:admin2_code":"183.0",
    "gn:asciiname":"Ahraura",
    "gn:country_code":"IN",
    "gn:dem":109,
    "gn:feature_class":"P",
    "gn:feature_code":"PPL",
    "gn:name":"Ahraura",
    "gn:population":0,
    "gn:timezone":"Asia/Kolkata",
    "iso:country":"IN",
    "name:bih_x_preferred":[
        "\u0905\u0939\u0930\u094c\u0930\u093e"
    ],
    "name:bpy_x_preferred":[
        "\u0986\u09b9\u09b0\u09cc\u09b0\u09be"
    ],
    "name:ceb_x_preferred":[
        "Ahraur\u0101"
    ],
    "name:fas_x_preferred":[
        "\u0627\u0647\u0631\u0627\u0648\u0631\u0627"
    ],
    "name:hin_x_preferred":[
        "\u0905\u0939\u0930\u094c\u0930\u093e"
    ],
    "name:ita_x_preferred":[
        "Ahraura"
    ],
    "name:min_x_preferred":[
        "Ahraura"
    ],
    "name:mlg_x_preferred":[
        "Ahraura"
    ],
    "name:msa_x_preferred":[
        "Ahraura"
    ],
    "name:new_x_preferred":[
        "\u0905\u0939\u094d\u0930\u094c\u0930\u093e"
    ],
    "name:nld_x_preferred":[
        "Ahraura"
    ],
    "name:pol_x_preferred":[
        "Ahraura"
    ],
    "name:por_x_preferred":[
        "Ahraura"
    ],
    "name:swe_x_preferred":[
        "Ahraur\u0101"
    ],
    "name:urd_x_preferred":[
        "\u0627\u06c1\u0631\u0648\u0631\u0627"
    ],
    "name:vie_x_preferred":[
        "Ahraura"
    ],
    "name:zho_x_preferred":[
        "\u963f\u8d6b\u52b3\u62c9"
    ],
    "wof:name":"Ahraura",
    "wof:placetype":"locality"
},
  "geometry": {"coordinates":[81.57998000000001,27.10767],"type":"Point"}
}