{
  "type": "Feature",
  "properties": {
    "iso:country":"IN",
    "ks:ks_name":"Legon Ki Dhani",
    "ks:ks_pop":749,
    "ks:ks_type":"VILLAGE",
    "name:eng_x_preferred":[
        "Legon Ki Dhani"
    ],
    "wof:name":"Legon Ki Dhani",
    "wof:placetype":"locality",
    "wof:population":749
},
  "geometry": {"coordinates":[72.766369,26.329561],"type":"Point"}
}