{
  "type": "Feature",
  "properties": {
    "iso:country":"IN",
    "ks:ks_alt_nam":"15 ZWD",
    "ks:ks_name":"15 Zwd",
    "ks:ks_pop":394,
    "ks:ks_type":"HABITATION",
    "name:eng_x_preferred":[
        "15 Zwd"
    ],
    "wof:name":"15 Zwd",
    "wof:placetype":"locality",
    "wof:population":394
},
  "geometry": {"coordinates":[74.159086,29.359139],"type":"Point"}
}