{
  "type": "Feature",
  "properties": {
    "gn:admin1_code":"2.0",
    "gn:admin2_code":"543.0",
    "gn:asciiname":"Chidimanguda",
    "gn:country_code":"IN",
    "gn:dem":218,
    "gn:feature_class":"P",
    "gn:feature_code":"PPL",
    "gn:name":"Ch\u012bdim\u0101ng\u016bda",
    "gn:population":0,
    "gn:timezone":"Asia/Kolkata",
    "iso:country":"IN",
    "ks:ks_name":"Cheedimanuguda",
    "ks:ks_pop":222,
    "ks:ks_type":"HABITATION",
    "name:eng_x_preferred":[
        "Cheedimanuguda"
    ],
    "name:eng_x_variant":[
        "Chidimanguda"
    ],
    "wof:name":"Cheedimanuguda",
    "wof:placetype":"locality",
    "wof:population":222
},
  "geometry": {"coordinates":[83.62661900000001,18.920499],"type":"Point"}
}