{
  "type": "Feature",
  "properties": {
    "iso:country":"IN",
    "ks:ks_alt_nam":"Chepa NC",
    "ks:ks_name":"Chepa Nc",
    "ks:ks_pop":107,
    "ks:ks_type":"HABITATION",
    "name:eng_x_preferred":[
        "Chepa Nc"
    ],
    "wof:name":"Chepa Nc",
    "wof:placetype":"locality",
    "wof:population":107
},
  "geometry": {"coordinates":[91.259704,26.748262],"type":"Point"}
}