{
  "type": "Feature",
  "properties": {
    "iso:country":"IN",
    "ks:ks_name":"Sunapur",
    "ks:ks_pop":151,
    "ks:ks_type":"VILLAGE",
    "name:eng_x_preferred":[
        "Sunapur"
    ],
    "wof:name":"Sunapur",
    "wof:placetype":"locality",
    "wof:population":151
},
  "geometry": {"coordinates":[84.162541,18.990563],"type":"Point"}
}