{
  "type": "Feature",
  "properties": {
    "iso:country":"IN",
    "ks:ks_name":"Turrebeda",
    "ks:ks_pop":220,
    "ks:ks_type":"HABITATION",
    "name:eng_x_preferred":[
        "Turrebeda"
    ],
    "wof:name":"Turrebeda",
    "wof:placetype":"locality",
    "wof:population":220
},
  "geometry": {"coordinates":[81.93066,19.56338],"type":"Point"}
}