{
  "type": "Feature",
  "properties": {
    "gn:admin1_code":"28.0",
    "gn:admin2_code":"333.0",
    "gn:asciiname":"Heta",
    "gn:country_code":"IN",
    "gn:dem":39,
    "gn:feature_class":"P",
    "gn:feature_code":"PPL",
    "gn:name":"Heta",
    "gn:population":0,
    "gn:timezone":"Asia/Kolkata",
    "iso:country":"IN",
    "name:ara_x_preferred":[
        "\u0647\u064a\u062a\u0627"
    ],
    "name:bar_x_preferred":[
        "Heta"
    ],
    "name:bel_x_preferred":[
        "\u0425\u0435\u0442\u0430"
    ],
    "name:bre_x_preferred":[
        "Heta"
    ],
    "name:bul_x_preferred":[
        "\u0425\u0435\u0442\u0430"
    ],
    "name:ckb_x_preferred":[
        "\u06be\u06cc\u062a\u0627"
    ],
    "name:dan_x_preferred":[
        "Heta"
    ],
    "name:deu_x_preferred":[
        "Heta"
    ],
    "name:epo_x_preferred":[
        "Heto"
    ],
    "name:eus_x_preferred":[
        "Heta"
    ],
    "name:fas_x_preferred":[
        "\u0647\u062a\u0627"
    ],
    "name:fin_x_preferred":[
        "Heeta"
    ],
    "name:fra_x_preferred":[
        "H\u00eata"
    ],
    "name:glg_x_preferred":[
        "Heta"
    ],
    "name:heb_x_preferred":[
        "\u05d4\u05d8\u05d0"
    ],
    "name:ind_x_preferred":[
        "Heta"
    ],
    "name:isl_x_preferred":[
        "Heta"
    ],
    "name:ita_x_preferred":[
        "Heta"
    ],
    "name:jpn_x_preferred":[
        "\u30d8\u30fc\u30bf"
    ],
    "name:kom_x_preferred":[
        "\u0425\u0435\u0442\u0430"
    ],
    "name:kur_x_preferred":[
        "Heta"
    ],
    "name:lav_x_preferred":[
        "H\u0113ta"
    ],
    "name:mar_x_preferred":[
        "\u0939\u0947\u091f\u093e"
    ],
    "name:nld_x_preferred":[
        "Heta"
    ],
    "name:nno_x_preferred":[
        "Heta"
    ],
    "name:nor_x_preferred":[
        "Heta"
    ],
    "name:oci_x_preferred":[
        "Eta"
    ],
    "name:pol_x_preferred":[
        "Heta"
    ],
    "name:ron_x_preferred":[
        "Heta"
    ],
    "name:rus_x_preferred":[
        "\u0425\u0435\u0442\u0430"
    ],
    "name:slk_x_preferred":[
        "H\u00e9ta"
    ],
    "name:spa_x_preferred":[
        "Heta"
    ],
    "name:swe_x_preferred":[
        "Heta"
    ],
    "name:tha_x_preferred":[
        "\u0e2e\u0e35\u0e15\u0e32"
    ],
    "name:tur_x_preferred":[
        "Heta"
    ],
    "name:ukr_x_preferred":[
        "\u0425\u0435\u0442\u0430"
    ],
    "name:vie_x_preferred":[
        "Heta"
    ],
    "name:war_x_preferred":[
        "Heta"
    ],
    "wof:name":"Heta",
    "wof:placetype":"neighbourhood"
},
  "geometry": {"coordinates":[87.86668,24.022],"type":"Point"}
}