{
  "type": "Feature",
  "properties": {
    "iso:country":"IN",
    "ks:ks_name":"Totamane",
    "ks:ks_pop":26,
    "ks:ks_type":"HABITATION",
    "name:eng_x_preferred":[
        "Totamane"
    ],
    "wof:name":"Totamane",
    "wof:placetype":"locality",
    "wof:population":26
},
  "geometry": {"coordinates":[74.599568,14.848911],"type":"Point"}
}