{
  "type": "Feature",
  "properties": {
    "iso:country":"IN",
    "ks:ks_name":"Jaraganda",
    "ks:ks_pop":97,
    "ks:ks_type":"VILLAGE",
    "name:eng_x_preferred":[
        "Jaraganda"
    ],
    "wof:name":"Jaraganda",
    "wof:placetype":"locality",
    "wof:population":97
},
  "geometry": {"coordinates":[84.171795,19.382576],"type":"Point"}
}