{
  "type": "Feature",
  "properties": {
    "iso:country":"IN",
    "ks:ks_name":"Maladwadi",
    "ks:ks_pop":130,
    "ks:ks_type":"HABITATION",
    "name:eng_x_preferred":[
        "Maladwadi"
    ],
    "wof:name":"Maladwadi",
    "wof:placetype":"locality",
    "wof:population":130
},
  "geometry": {"coordinates":[73.780312,16.142939],"type":"Point"}
}