{
  "type": "Feature",
  "properties": {
    "iso:country":"IN",
    "ks:ks_name":"Kirichandra Para",
    "ks:ks_pop":89,
    "ks:ks_type":"HABITATION",
    "ks:ks_uagg_main":0,
    "name:eng_x_preferred":[
        "Kirichandra Para"
    ],
    "wof:name":"Kirichandra Para",
    "wof:placetype":"neighbourhood",
    "wof:population":89
},
  "geometry": {"coordinates":[91.558504,23.371695],"type":"Point"}
}