{
  "type": "Feature",
  "properties": {
    "gn:admin1_code":"11.0",
    "gn:admin2_code":"033",
    "gn:asciiname":"Shakrah Hatti",
    "gn:country_code":"IN",
    "gn:dem":1239,
    "gn:feature_class":"P",
    "gn:feature_code":"PPL",
    "gn:name":"Shakr\u0101h Hatti",
    "gn:population":0,
    "gn:timezone":"Asia/Kolkata",
    "iso:country":"IN",
    "name:und_x_variant":[
        "Shakr\u0101h Hatti",
        "Shakr\u0101h"
    ],
    "wof:name":"Shakrah Hatti",
    "wof:placetype":"locality"
},
  "geometry": {"coordinates":[77.04895999999999,31.13929000000001],"type":"Point"}
}