{
  "type": "Feature",
  "properties": {
    "iso:country":"IN",
    "ks:ks_name":"4 e",
    "ks:ks_pop":760,
    "ks:ks_type":"HABITATION",
    "name:eng_x_preferred":[
        "4 e"
    ],
    "wof:name":"4 e",
    "wof:placetype":"locality",
    "wof:population":760
},
  "geometry": {"coordinates":[73.931572,29.903586],"type":"Point"}
}