{
  "type": "Feature",
  "properties": {
    "iso:country":"IN",
    "ks:ks_alt_nam":"CHHOTKI BARATHLI",
    "ks:ks_name":"Chhotki Barathli",
    "ks:ks_pop":696,
    "ks:ks_type":"HABITATION",
    "name:eng_x_preferred":[
        "Chhotki Barathli"
    ],
    "wof:name":"Chhotki Barathli",
    "wof:placetype":"locality",
    "wof:population":696
},
  "geometry": {"coordinates":[86.804378,25.533363],"type":"Point"}
}