{
  "type": "Feature",
  "properties": {
    "iso:country":"IN",
    "ks:ks_name":"Boalimari",
    "ks:ks_pop":185,
    "ks:ks_type":"HABITATION",
    "name:eng_x_preferred":[
        "Boalimari"
    ],
    "wof:name":"Boalimari",
    "wof:placetype":"locality",
    "wof:population":185
},
  "geometry": {"coordinates":[90.078011,26.436315],"type":"Point"}
}