{
  "type": "Feature",
  "properties": {
    "iso:country":"IN",
    "ks:ks_name":"Gawalgundra",
    "ks:ks_pop":173,
    "ks:ks_type":"HABITATION",
    "name:eng_x_preferred":[
        "Gawalgundra"
    ],
    "wof:name":"Gawalgundra",
    "wof:placetype":"locality",
    "wof:population":173
},
  "geometry": {"coordinates":[80.752904,21.743396],"type":"Point"}
}