{
  "type": "Feature",
  "properties": {
    "iso:country":"IN",
    "ks:ks_name":"Sankiri",
    "ks:ks_pop":839,
    "ks:ks_type":"VILLAGE",
    "name:eng_x_preferred":[
        "Sankiri"
    ],
    "wof:name":"Sankiri",
    "wof:placetype":"locality",
    "wof:population":839
},
  "geometry": {"coordinates":[85.64719700000001,21.724293],"type":"Point"}
}