{
  "type": "Feature",
  "properties": {
    "iso:country":"IN",
    "ks:ks_name":"Rangdeo",
    "ks:ks_pop":137,
    "ks:ks_type":"VILLAGE",
    "name:eng_x_preferred":[
        "Rangdeo"
    ],
    "wof:name":"Rangdeo",
    "wof:placetype":"locality",
    "wof:population":137
},
  "geometry": {"coordinates":[79.93754199999999,29.897473],"type":"Point"}
}