{
  "type": "Feature",
  "properties": {
    "iso:country":"IN",
    "ks:ks_name":"Badathingale",
    "ks:ks_pop":24,
    "ks:ks_type":"HABITATION",
    "name:eng_x_preferred":[
        "Badathingale"
    ],
    "wof:name":"Badathingale",
    "wof:placetype":"locality",
    "wof:population":24
},
  "geometry": {"coordinates":[75.067453,13.466598],"type":"Point"}
}