{
  "type": "Feature",
  "properties": {
    "gn:admin1_code":"09",
    "gn:admin2_code":"480.0",
    "gn:asciiname":"Pipavav Bandar",
    "gn:country_code":"IN",
    "gn:dem":4,
    "gn:feature_class":"P",
    "gn:feature_code":"PPL",
    "gn:name":"Pip\u0101v\u0101v Bandar",
    "gn:population":0,
    "gn:timezone":"Asia/Kolkata",
    "iso:country":"IN",
    "name:deu_x_preferred":[
        "Pipavav"
    ],
    "name:guj_x_preferred":[
        "\u0aaa\u0ac0\u0aaa\u0abe\u0ab5\u0abe\u0ab5"
    ],
    "name:nor_x_preferred":[
        "Pipavav"
    ],
    "name:und_x_variant":[
        "Kathiwadar Bandar",
        "Piparav",
        "Pip\u0101v\u0101v Bandar"
    ],
    "wof:name":"Pipavav Bandar",
    "wof:placetype":"locality"
},
  "geometry": {"coordinates":[71.55821999999998,20.97265],"type":"Point"}
}