{
  "type": "Feature",
  "properties": {
    "gn:country":"IN",
    "gn:fcode":"PPL",
    "gn:population":22613,
    "iso:country":"IN",
    "name:ben_x_preferred":[
        "\u099f\u09cb\u09a6\u09be\u09b0\u09be\u09af\u09bc\u09b8\u09bf\u0982"
    ],
    "name:bpy_x_preferred":[
        "\u099f\u09cb\u09a6\u09be\u09b0\u09be\u09af\u09bc\u09b8\u09bf\u0982"
    ],
    "name:bul_x_preferred":[
        "\u0422\u043e\u0434\u0430\u0440\u0430\u0438\u0441\u0438\u043d\u0433\u0445"
    ],
    "name:ceb_x_preferred":[
        "Todaraisingh"
    ],
    "name:deu_x_preferred":[
        "Todaraisingh"
    ],
    "name:eng_x_preferred":[
        "Todaraisingh"
    ],
    "name:fra_x_preferred":[
        "Todaraisingh"
    ],
    "name:guj_x_preferred":[
        "\u0a9f\u0acb\u0aa1\u0ab0\u0abe\u0a88\u0ab8\u0abf\u0a82\u0a97"
    ],
    "name:hin_x_preferred":[
        "\u091f\u094b\u0921\u093e\u0930\u093e\u092f\u0938\u093f\u0902\u0939"
    ],
    "name:ita_x_preferred":[
        "Todaraisingh"
    ],
    "name:jpn_x_preferred":[
        "\u30c8\u30c0\u30fb\u30e9\u30a4\u30b7\u30f3"
    ],
    "name:kan_x_preferred":[
        "\u0ca4\u0ccb\u0ca6\u0cb0\u0cbe\u0caf\u0ccd\u0cb8\u0cbf\u0c82\u0c98\u0ccd"
    ],
    "name:kor_x_preferred":[
        "\ud1a0\ub2e4\ub77c\uc774\uc9d5"
    ],
    "name:mlg_x_preferred":[
        "Todaraisingh"
    ],
    "name:msa_x_preferred":[
        "Todaraisingh"
    ],
    "name:nld_x_preferred":[
        "Todaraisingh"
    ],
    "name:por_x_preferred":[
        "Todaraisingh"
    ],
    "name:rus_x_preferred":[
        "\u0422\u043e\u0434\u0430\u0440\u0430\u0441\u0438\u043d\u0433\u0445"
    ],
    "name:spa_x_preferred":[
        "Todaraisingh"
    ],
    "name:swe_x_preferred":[
        "Todaraisingh"
    ],
    "name:tam_x_preferred":[
        "\u0ba4\u0bca\u0b9f\u0bb0\u0bbe\u0baf\u0bcd\u0b9a\u0bbf\u0b99\u0bcd"
    ],
    "name:tel_x_preferred":[
        "\u0c24\u0c4a\u0c21\u0c30\u0c48\u0c38\u0c3f\u0c02\u0c17\u0c4d"
    ],
    "name:und_x_variant":[
        "Todarasingh"
    ],
    "name:urd_x_preferred":[
        "\u062a\u0648\u0691\u0627\u0631\u0627\u0626\u06d2\u0633\u0646\u06af\u06be"
    ],
    "name:vie_x_preferred":[
        "Todaraisingh"
    ],
    "name:zho_x_preferred":[
        "\u6258\u8fbe\u8d56\u8f9b\u683c"
    ],
    "qs:name":"Todaraisingh",
    "qs:name_adm0":"India",
    "qs:name_adm1":"Rajasthan",
    "qs:photos_9k":1,
    "qs:photos_9r":1,
    "qs:photos_all":1,
    "qs:photos_sr":0,
    "qs:placetype":"Town",
    "qs:pop_sr":"7",
    "wd:wordcount":441,
    "wof:name":"Todaraisingh",
    "wof:placetype":"locality",
    "wof:population":22613
},
  "geometry": {"coordinates":[75.48182,26.02401],"type":"Point"}
}