{
  "type": "Feature",
  "properties": {
    "iso:country":"IN",
    "ks:ks_alt_nam":"BanaMahuldiha",
    "ks:ks_name":"Banamahuldiha",
    "ks:ks_pop":986,
    "ks:ks_type":"HABITATION",
    "name:eng_x_preferred":[
        "Banamahuldiha"
    ],
    "wof:name":"Banamahuldiha",
    "wof:placetype":"locality",
    "wof:population":986
},
  "geometry": {"coordinates":[85.892841,21.504065],"type":"Point"}
}