{
  "type": "Feature",
  "properties": {
    "gn:admin1_code":"34.0",
    "gn:admin2_code":"219.0",
    "gn:asciiname":"Baksanda",
    "gn:country_code":"IN",
    "gn:dem":57,
    "gn:feature_class":"P",
    "gn:feature_code":"PPL",
    "gn:name":"Baksanda",
    "gn:population":0,
    "gn:timezone":"Asia/Kolkata",
    "iso:country":"IN",
    "ks:ks_name":"Baksanda",
    "ks:ks_pop":1223,
    "ks:ks_type":"VILLAGE",
    "name:eng_x_preferred":[
        "Baksanda"
    ],
    "wof:name":"Baksanda",
    "wof:placetype":"locality",
    "wof:population":1223
},
  "geometry": {"coordinates":[84.99201499999999,25.899536],"type":"Point"}
}