{
  "type": "Feature",
  "properties": {
    "gn:admin1_code":"35",
    "gn:admin2_code":"423.0",
    "gn:asciiname":"Bagauda",
    "gn:country_code":"IN",
    "gn:dem":403,
    "gn:feature_class":"P",
    "gn:feature_code":"PPL",
    "gn:name":"B\u0101gauda",
    "gn:population":0,
    "gn:timezone":"Asia/Kolkata",
    "iso:country":"IN",
    "name:ceb_x_preferred":[
        "Bagauda"
    ],
    "name:msa_x_preferred":[
        "Bagauda"
    ],
    "name:new_x_preferred":[
        "\u092c\u0917\u094c\u0921\u093e"
    ],
    "name:pol_x_preferred":[
        "Bagauda"
    ],
    "wof:name":"Bagauda",
    "wof:placetype":"locality"
},
  "geometry": {"coordinates":[77.54015,25.6863],"type":"Point"}
}