{
  "type": "Feature",
  "properties": {
    "iso:country":"IN",
    "ks:ks_name":"Ostagar Para",
    "ks:ks_pop":500,
    "ks:ks_type":"HABITATION",
    "name:eng_x_preferred":[
        "Ostagar Para"
    ],
    "wof:name":"Ostagar Para",
    "wof:placetype":"locality",
    "wof:population":500
},
  "geometry": {"coordinates":[88.742997,22.28325],"type":"Point"}
}