{
  "type": "Feature",
  "properties": {
    "gn:admin1_code":"28.0",
    "gn:admin2_code":"327.0",
    "gn:asciiname":"Parmaguri",
    "gn:country_code":"IN",
    "gn:dem":1663,
    "gn:feature_class":"P",
    "gn:feature_code":"PPL",
    "gn:name":"Parmaguri",
    "gn:population":0,
    "gn:timezone":"Asia/Kolkata",
    "iso:country":"IN",
    "wof:name":"Parmaguri",
    "wof:placetype":"locality"
},
  "geometry": {"coordinates":[88.15701,27.01173],"type":"Point"}
}