{
  "type": "Feature",
  "properties": {
    "gn:country":"IN",
    "gn:fcode":"PPL",
    "gn:pop":9742,
    "iso:country":"IN",
    "qs:name":"Puduv\u0101yal",
    "qs:photos_9r":0,
    "qs:photos_sr":0,
    "qs:pop_sr":"5",
    "wd:wordcount":462,
    "wof:name":"Puduv\u0101yal",
    "wof:placetype":"locality",
    "wof:population":9742
},
  "geometry": {"coordinates":[80.14573,13.33057],"type":"Point"}
}