{
  "type": "Feature",
  "properties": {
    "gn:country":"IN",
    "gn:fcode":"PPL",
    "gn:pop":9742,
    "iso:country":"IN",
    "name:bpy_x_preferred":[
        "\u09aa\u09c1\u09a1\u09bc\u09c1\u09ac\u09be\u09af\u09bc\u09be\u09b2"
    ],
    "name:ita_x_preferred":[
        "Puduvayal"
    ],
    "name:msa_x_preferred":[
        "Puduvayal"
    ],
    "name:nld_x_preferred":[
        "Puduvayal"
    ],
    "name:tam_x_preferred":[
        "\u0baa\u0bc1\u0ba4\u0bc1\u0bb5\u0baf\u0bb2\u0bcd"
    ],
    "name:vie_x_preferred":[
        "Puduvayal"
    ],
    "name:zho_x_preferred":[
        "\u666e\u675c\u74e6\u8036\u5c14"
    ],
    "qs:name":"Puduv\u0101yal",
    "qs:photos_9r":0,
    "qs:photos_sr":0,
    "qs:pop_sr":"5",
    "wd:wordcount":462,
    "wof:name":"Puduv\u0101yal",
    "wof:placetype":"locality",
    "wof:population":9742
},
  "geometry": {"coordinates":[80.14573,13.33057],"type":"Point"}
}