{
  "type": "Feature",
  "properties": {
    "gn:admin1_code":"23.0",
    "gn:admin2_code":"048",
    "gn:asciiname":"Devigarh",
    "gn:country_code":"IN",
    "gn:dem":254,
    "gn:feature_class":"P",
    "gn:feature_code":"PPL",
    "gn:name":"Dev\u012bgarh",
    "gn:population":0,
    "gn:timezone":"Asia/Kolkata",
    "iso:country":"IN",
    "name:und_x_variant":[
        "R\u0101mnagar Chun\u012bw\u0101la",
        "Dev\u012bgarh"
    ],
    "name:zho_x_preferred":[
        "\u6234\u7ef4\u9601\u7687\u5bab"
    ],
    "wof:name":"Devigarh",
    "wof:placetype":"locality"
},
  "geometry": {"coordinates":[76.51692,30.18895],"type":"Point"}
}