{
  "type": "Feature",
  "properties": {
    "gn:admin1_code":"37.0",
    "gn:admin2_code":"407.0",
    "gn:asciiname":"Bodalpani",
    "gn:country_code":"IN",
    "gn:dem":760,
    "gn:feature_class":"P",
    "gn:feature_code":"PPL",
    "gn:name":"Bodalp\u0101n\u012b",
    "gn:population":0,
    "gn:timezone":"Asia/Kolkata",
    "iso:country":"IN",
    "ks:ks_name":"Badalpani",
    "ks:ks_pop":125,
    "ks:ks_type":"VILLAGE",
    "name:eng_x_preferred":[
        "Badalpani"
    ],
    "name:eng_x_variant":[
        "Bodalpani"
    ],
    "wof:name":"Badalpani",
    "wof:placetype":"locality",
    "wof:population":125
},
  "geometry": {"coordinates":[80.99740199999999,22.02594],"type":"Point"}
}