{
  "type": "Feature",
  "properties": {
    "iso:country":"IN",
    "ks:ks_name":"Naadaakannupatti",
    "ks:ks_pop":837,
    "ks:ks_type":"HABITATION",
    "ks:ks_uagg_main":0,
    "name:eng_x_preferred":[
        "Naadaakannupatti"
    ],
    "wof:name":"Naadaakannupatti",
    "wof:placetype":"neighbourhood",
    "wof:population":837
},
  "geometry": {"coordinates":[77.368757,8.87579],"type":"Point"}
}