{
  "type": "Feature",
  "properties": {
    "iso:country":"IN",
    "ks:ks_name":"Karigin Koppa",
    "ks:ks_pop":1025,
    "ks:ks_type":"HABITATION",
    "name:eng_x_preferred":[
        "Karigin Koppa"
    ],
    "wof:name":"Karigin Koppa",
    "wof:placetype":"locality",
    "wof:population":1025
},
  "geometry": {"coordinates":[75.042627,14.939908],"type":"Point"}
}