{
  "type": "Feature",
  "properties": {
    "iso:country":"IN",
    "ks:ks_name":"Jaitpur",
    "ks:ks_pop":135,
    "ks:ks_type":"VILLAGE",
    "name:eng_x_preferred":[
        "Jaitpur"
    ],
    "wof:name":"Jaitpur",
    "wof:placetype":"locality",
    "wof:population":135
},
  "geometry": {"coordinates":[75.37267199999999,32.256412],"type":"Point"}
}