{
  "type": "Feature",
  "properties": {
    "iso:country":"IN",
    "ks:ks_alt_nam":"DARDARIA PARA",
    "ks:ks_name":"Dardaria Para",
    "ks:ks_pop":325,
    "ks:ks_type":"HABITATION",
    "ks:ks_uagg_main":0,
    "name:eng_x_preferred":[
        "Dardaria Para"
    ],
    "wof:name":"Dardaria Para",
    "wof:placetype":"neighbourhood",
    "wof:population":325
},
  "geometry": {"coordinates":[88.50036,26.560366],"type":"Point"}
}