{
  "type": "Feature",
  "properties": {
    "gn:admin1_code":"25",
    "gn:admin2_code":"606.0",
    "gn:asciiname":"Veraiyur",
    "gn:country_code":"IN",
    "gn:dem":123,
    "gn:feature_class":"P",
    "gn:feature_code":"PPL",
    "gn:name":"Veraiy\u016br",
    "gn:population":0,
    "gn:timezone":"Asia/Kolkata",
    "iso:country":"IN",
    "name:und_x_variant":[
        "Veraiy\u016br"
    ],
    "wof:name":"Veraiyur",
    "wof:placetype":"locality"
},
  "geometry": {"coordinates":[79.13089000000002,12.0913],"type":"Point"}
}