{
  "type": "Feature",
  "properties": {
    "gn:admin1_code":"25",
    "gn:admin2_code":"606.0",
    "gn:asciiname":"Veraiyur",
    "gn:country_code":"IN",
    "gn:dem":123,
    "gn:feature_class":"P",
    "gn:feature_code":"PPL",
    "gn:name":"Veraiy\u016br",
    "gn:population":0,
    "gn:timezone":"Asia/Kolkata",
    "iso:country":"IN",
    "ks:ks_name":"Veraiyur",
    "ks:ks_pop":862,
    "ks:ks_type":"HABITATION",
    "name:eng_x_preferred":[
        "Veraiyur"
    ],
    "name:fas_x_preferred":[
        "\u0648\u0631\u06cc\u0648\u0631"
    ],
    "name:tam_x_preferred":[
        "\u0bb5\u0bc6\u0bb1\u0bc8\u0baf\u0bc2\u0bb0\u0bcd"
    ],
    "name:und_x_variant":[
        "Veraiy\u016br"
    ],
    "wof:name":"Veraiyur",
    "wof:placetype":"locality",
    "wof:population":862
},
  "geometry": {"coordinates":[79.118362,12.091315],"type":"Point"}
}