{
  "type": "Feature",
  "properties": {
    "gn:admin1_code":"19.0",
    "gn:admin2_code":"582.0",
    "gn:asciiname":"Hiriyetachenahalli",
    "gn:country_code":"IN",
    "gn:dem":823,
    "gn:feature_class":"P",
    "gn:feature_code":"PPL",
    "gn:name":"Hiriyetachenahalli",
    "gn:population":0,
    "gn:timezone":"Asia/Kolkata",
    "iso:country":"IN",
    "wof:name":"Hiriyetachenahalli",
    "wof:placetype":"locality"
},
  "geometry": {"coordinates":[77.88604000000002,13.56095],"type":"Point"}
}