{
  "type": "Feature",
  "properties": {
    "gn:admin1_code":"40.0",
    "gn:admin2_code":"540",
    "gn:asciiname":"Ramsagar",
    "gn:country_code":"IN",
    "gn:dem":509,
    "gn:feature_class":"P",
    "gn:feature_code":"PPL",
    "gn:name":"R\u0101ms\u0101gar",
    "gn:population":0,
    "gn:timezone":"Asia/Kolkata",
    "iso:country":"IN",
    "name:ben_x_preferred":[
        "\u09b0\u09be\u09ae\u09b8\u09be\u0997\u09b0"
    ],
    "wof:name":"Ramsagar",
    "wof:placetype":"locality"
},
  "geometry": {"coordinates":[78.91611,17.91254],"type":"Point"}
}