{
  "type": "Feature",
  "properties": {
    "iso:country":"IN",
    "ks:ks_name":"Vagge Colony",
    "ks:ks_pop":54,
    "ks:ks_type":"HABITATION",
    "name:eng_x_preferred":[
        "Vagge Colony"
    ],
    "wof:name":"Vagge Colony",
    "wof:placetype":"locality",
    "wof:population":54
},
  "geometry": {"coordinates":[75.846389,12.098889],"type":"Point"}
}