{
  "type": "Feature",
  "properties": {
    "iso:country":"IN",
    "ks:ks_alt_nam":"kallipalya",
    "ks:ks_name":"Kallipalya",
    "ks:ks_pop":89,
    "ks:ks_type":"HABITATION",
    "name:eng_x_preferred":[
        "Kallipalya"
    ],
    "wof:name":"Kallipalya",
    "wof:placetype":"locality",
    "wof:population":89
},
  "geometry": {"coordinates":[77.462035,12.766966],"type":"Point"}
}