{
  "type": "Feature",
  "properties": {
    "iso:country":"IN",
    "ks:ks_alt_nam":"G.Jarakunti",
    "ks:ks_name":"G.jarakunti",
    "ks:ks_pop":1992,
    "ks:ks_type":"HABITATION",
    "name:eng_x_preferred":[
        "G.jarakunti"
    ],
    "wof:name":"G.jarakunti",
    "wof:placetype":"locality",
    "wof:population":1992
},
  "geometry": {"coordinates":[76.070823,15.647587],"type":"Point"}
}