{
  "type": "Feature",
  "properties": {
    "iso:country":"IN",
    "ks:ks_name":"Murla",
    "ks:ks_pop":0,
    "ks:ks_type":"VILLAGE",
    "name:eng_x_preferred":[
        "Murla"
    ],
    "wof:name":"Murla",
    "wof:placetype":"locality",
    "wof:population":0
},
  "geometry": {"coordinates":[86.54473900000001,25.646588],"type":"Point"}
}