{
  "type": "Feature",
  "properties": {
    "iso:country":"IN",
    "ks:ks_name":"Uttar Rangia Gaon",
    "ks:ks_pop":524,
    "ks:ks_type":"HABITATION",
    "name:eng_x_preferred":[
        "Uttar Rangia Gaon"
    ],
    "wof:name":"Uttar Rangia Gaon",
    "wof:placetype":"locality",
    "wof:population":524
},
  "geometry": {"coordinates":[91.132434,26.36682],"type":"Point"}
}