{
  "type": "Feature",
  "properties": {
    "iso:country":"IN",
    "ks:ks_alt_nam":"Mappatti ST Colony",
    "ks:ks_name":"Mappatti St Colony",
    "ks:ks_pop":232,
    "ks:ks_type":"HABITATION",
    "name:eng_x_preferred":[
        "Mappatti St Colony"
    ],
    "wof:name":"Mappatti St Colony",
    "wof:placetype":"locality",
    "wof:population":232
},
  "geometry": {"coordinates":[75.88766699999999,11.749039],"type":"Point"}
}