{
  "type": "Feature",
  "properties": {
    "gn:admin1_code":"25",
    "gn:admin2_code":"619.0",
    "gn:asciiname":"Thiruthuraipoondi",
    "gn:cc2":"IN",
    "gn:country_code":"IN",
    "gn:dem":3,
    "gn:feature_class":"P",
    "gn:feature_code":"PPL",
    "gn:name":"Thiruthuraipoondi",
    "gn:population":0,
    "gn:timezone":"Asia/Kolkata",
    "iso:country":"IN",
    "name:und_x_variant":[
        "Tiruturaipundi",
        "Tirutturaipp\u016bndi"
    ],
    "wof:name":"Thiruthuraipoondi",
    "wof:placetype":"locality"
},
  "geometry": {"coordinates":[79.63268000000002,10.52819],"type":"Point"}
}