{
  "type": "Feature",
  "properties": {
    "gn:admin1_code":"25",
    "gn:admin2_code":"619.0",
    "gn:asciiname":"Thiruthuraipoondi",
    "gn:cc2":"IN",
    "gn:country_code":"IN",
    "gn:dem":3,
    "gn:feature_class":"P",
    "gn:feature_code":"PPL",
    "gn:name":"Thiruthuraipoondi",
    "gn:population":0,
    "gn:timezone":"Asia/Kolkata",
    "iso:country":"IN",
    "name:bpy_x_preferred":[
        "\u09a5\u09bf\u09b0\u09c1\u09a5\u09c1\u09b0\u09be\u0987\u09aa\u09cb\u09a8\u09cd\u09a1\u09bf"
    ],
    "name:hif_x_preferred":[
        "Thiruthuraipoondi"
    ],
    "name:ita_x_preferred":[
        "Thiruthuraipoondi"
    ],
    "name:msa_x_preferred":[
        "Thiruthuraipoondi"
    ],
    "name:por_x_preferred":[
        "Thiruthuraipoondi"
    ],
    "name:tam_x_preferred":[
        "\u0ba4\u0bbf\u0bb0\u0bc1\u0ba4\u0bcd\u0ba4\u0bc1\u0bb1\u0bc8\u0baa\u0bcd\u0baa\u0bc2\u0ba3\u0bcd\u0b9f\u0bbf"
    ],
    "name:und_x_variant":[
        "Tiruturaipundi",
        "Tirutturaipp\u016bndi"
    ],
    "name:urd_x_preferred":[
        "\u062a\u06be\u06cc\u0631\u0648\u062a\u06be\u0648\u0631\u0627\u06cc\u067e\u0648\u0646\u0688\u06cc"
    ],
    "name:vie_x_preferred":[
        "Thiruthuraipoondi"
    ],
    "name:zho_x_preferred":[
        "\u8482\u9c81\u56fe\u8d56\u6ce2\u5965\u6069\u8fea"
    ],
    "wof:name":"Thiruthuraipoondi",
    "wof:placetype":"locality"
},
  "geometry": {"coordinates":[79.63268000000002,10.52819],"type":"Point"}
}