{
  "type": "Feature",
  "properties": {
    "iso:country":"IN",
    "ks:ks_alt_nam":"Balaji nagar",
    "ks:ks_name":"Balaji Nagar",
    "ks:ks_pop":1301,
    "ks:ks_type":"HABITATION",
    "ks:ks_uagg_main":0,
    "name:eng_x_preferred":[
        "Balaji Nagar"
    ],
    "wof:name":"Balaji Nagar",
    "wof:placetype":"locality",
    "wof:population":1301
},
  "geometry": {"coordinates":[80.03698199999999,13.141362],"type":"Point"}
}