{
  "type": "Feature",
  "properties": {
    "gn:admin1_code":"9.0",
    "gn:admin2_code":"471.0",
    "gn:asciiname":"Saldi",
    "gn:country_code":"IN",
    "gn:dem":93,
    "gn:feature_class":"P",
    "gn:feature_code":"PPL",
    "gn:name":"Saldi",
    "gn:population":0,
    "gn:timezone":"Asia/Kolkata",
    "iso:country":"IN",
    "wof:name":"Saldi",
    "wof:placetype":"locality"
},
  "geometry": {"coordinates":[72.52795999999999,23.43009],"type":"Point"}
}