{
  "type": "Feature",
  "properties": {
    "iso:country":"IN",
    "ks:ks_name":"Purusottampur",
    "ks:ks_pop":0,
    "ks:ks_type":"VILLAGE",
    "name:eng_x_preferred":[
        "Purusottampur"
    ],
    "wof:name":"Purusottampur",
    "wof:placetype":"locality",
    "wof:population":0
},
  "geometry": {"coordinates":[85.655288,20.06808],"type":"Point"}
}