{
  "type": "Feature",
  "properties": {
    "iso:country":"IN",
    "ks:ks_name":"Bhattkoti",
    "ks:ks_pop":240,
    "ks:ks_type":"VILLAGE",
    "name:eng_x_preferred":[
        "Bhattkoti"
    ],
    "wof:name":"Bhattkoti",
    "wof:placetype":"locality",
    "wof:population":240
},
  "geometry": {"coordinates":[78.467286,30.359688],"type":"Point"}
}