{
  "type": "Feature",
  "properties": {
    "iso:country":"IN",
    "ks:ks_name":"Taltak",
    "ks:ks_pop":21,
    "ks:ks_type":"VILLAGE",
    "name:eng_x_preferred":[
        "Taltak"
    ],
    "wof:name":"Taltak",
    "wof:placetype":"locality",
    "wof:population":21
},
  "geometry": {"coordinates":[87.73144600000001,24.957708],"type":"Point"}
}