{
  "type": "Feature",
  "properties": {
    "iso:country":"IN",
    "ks:ks_alt_nam":"Tillanch\u0101ng Dw\u012bp",
    "ks:ks_alt_nam_2":"Tillanchang Dwip",
    "ks:ks_name":"Tillanchang",
    "ks:ks_type":"VILLAGE",
    "name:eng_x_preferred":[
        "Tillanchang"
    ],
    "name:eng_x_variant":[
        "Tillanch\u0101ng Dw\u012bp",
        "Tillanchang Dwip"
    ],
    "wof:name":"Tillanchang",
    "wof:placetype":"locality"
},
  "geometry": {"coordinates":[93.630308,8.48567],"type":"Point"}
}