{
  "type": "Feature",
  "properties": {
    "gn:admin1_code":"11.0",
    "gn:admin2_code":"27.0",
    "gn:asciiname":"Samsathi",
    "gn:country_code":"IN",
    "gn:dem":1624,
    "gn:feature_class":"P",
    "gn:feature_code":"PPL",
    "gn:name":"Samsathi",
    "gn:population":0,
    "gn:timezone":"Asia/Kolkata",
    "iso:country":"IN",
    "wof:name":"Samsathi",
    "wof:placetype":"locality"
},
  "geometry": {"coordinates":[77.25768000000002,31.39024],"type":"Point"}
}