{
  "type": "Feature",
  "properties": {
    "gn:admin1_code":"10",
    "gn:admin2_code":"88.0",
    "gn:asciiname":"Juan",
    "gn:country_code":"IN",
    "gn:dem":203,
    "gn:feature_class":"P",
    "gn:feature_code":"PPL",
    "gn:name":"J\u016b\u0101n",
    "gn:population":0,
    "gn:timezone":"Asia/Kolkata",
    "iso:country":"IN",
    "wof:name":"Juan",
    "wof:placetype":"locality"
},
  "geometry": {"coordinates":[77.39748,28.23344],"type":"Point"}
}