{
  "type": "Feature",
  "properties": {
    "gn:admin1_code":"12.0",
    "gn:admin2_code":"20.0",
    "gn:asciiname":"Saral",
    "gn:country_code":"IN",
    "gn:dem":1202,
    "gn:feature_class":"P",
    "gn:feature_code":"PPL",
    "gn:name":"Saral",
    "gn:population":0,
    "gn:timezone":"Asia/Kolkata",
    "iso:country":"IN",
    "name:aze_x_preferred":[
        "Saral"
    ],
    "name:fas_x_preferred":[
        "\u0633\u0627\u0631\u0627\u0644"
    ],
    "name:fra_x_preferred":[
        "Saral"
    ],
    "wof:name":"Saral",
    "wof:placetype":"locality"
},
  "geometry": {"coordinates":[74.68655,33.3591],"type":"Point"}
}