{
  "type": "Feature",
  "properties": {
    "iso:country":"IN",
    "ks:ks_name":"Paschim Deeh",
    "ks:ks_pop":600,
    "ks:ks_type":"HABITATION",
    "name:eng_x_preferred":[
        "Paschim Deeh"
    ],
    "wof:name":"Paschim Deeh",
    "wof:placetype":"locality",
    "wof:population":600
},
  "geometry": {"coordinates":[82.903648,27.318402],"type":"Point"}
}