{
  "type": "Feature",
  "properties": {
    "iso:country":"IN",
    "ks:ks_alt_nam":"jyothinagar mallanakuppe",
    "ks:ks_name":"Jyothinagar Mallanakuppe",
    "ks:ks_pop":146,
    "ks:ks_type":"HABITATION",
    "name:eng_x_preferred":[
        "Jyothinagar Mallanakuppe"
    ],
    "wof:name":"Jyothinagar Mallanakuppe",
    "wof:placetype":"locality",
    "wof:population":146
},
  "geometry": {"coordinates":[77.03964000000001,12.741002],"type":"Point"}
}