{
  "type": "Feature",
  "properties": {
    "iso:country":"IN",
    "ks:ks_name":"Majhgaw",
    "ks:ks_pop":325,
    "ks:ks_type":"VILLAGE",
    "name:eng_x_preferred":[
        "Majhgaw"
    ],
    "wof:name":"Majhgaw",
    "wof:placetype":"locality",
    "wof:population":325
},
  "geometry": {"coordinates":[83.092361,26.582285],"type":"Point"}
}