{
  "type": "Feature",
  "properties": {
    "gn:admin1_code":"16.0",
    "gn:admin2_code":"497.0",
    "gn:asciiname":"Hol",
    "gn:country_code":"IN",
    "gn:dem":150,
    "gn:feature_class":"P",
    "gn:feature_code":"PPL",
    "gn:name":"Hol",
    "gn:population":0,
    "gn:timezone":"Asia/Kolkata",
    "iso:country":"IN",
    "ks:ks_name":"Hol",
    "ks:ks_type":"VILLAGE",
    "name:ara_x_preferred":[
        "\u0647\u0648\u0644\u0626"
    ],
    "name:bpy_x_preferred":[
        "\u09b9\u09cb\u09b2"
    ],
    "name:cat_x_preferred":[
        "Hol"
    ],
    "name:ceb_x_preferred":[
        "Hol"
    ],
    "name:dan_x_preferred":[
        "Hol"
    ],
    "name:deu_x_preferred":[
        "Hol"
    ],
    "name:eng_x_preferred":[
        "Hol"
    ],
    "name:epo_x_preferred":[
        "Hol"
    ],
    "name:eus_x_preferred":[
        "Hol"
    ],
    "name:fin_x_preferred":[
        "Hol"
    ],
    "name:fra_x_preferred":[
        "Hol"
    ],
    "name:hye_x_preferred":[
        "\u0540\u0578\u0582\u056c"
    ],
    "name:ita_x_preferred":[
        "Hol"
    ],
    "name:jav_x_preferred":[
        "Hol"
    ],
    "name:lat_x_preferred":[
        "Hol"
    ],
    "name:lim_x_preferred":[
        "Hol"
    ],
    "name:msa_x_preferred":[
        "Hol"
    ],
    "name:nds_x_preferred":[
        "Kommun Hol"
    ],
    "name:nld_x_preferred":[
        "Hol"
    ],
    "name:nno_x_preferred":[
        "Hol kommune"
    ],
    "name:nor_x_preferred":[
        "Hol"
    ],
    "name:pol_x_preferred":[
        "Hol"
    ],
    "name:por_x_preferred":[
        "Hol"
    ],
    "name:ron_x_preferred":[
        "Hol"
    ],
    "name:rus_x_preferred":[
        "\u0425\u0443\u043b\u044c"
    ],
    "name:slv_x_preferred":[
        "Hol"
    ],
    "name:sme_x_preferred":[
        "Hol"
    ],
    "name:spa_x_preferred":[
        "Hol"
    ],
    "name:sqi_x_preferred":[
        "Hol"
    ],
    "name:swe_x_preferred":[
        "Hols kommun"
    ],
    "name:vie_x_preferred":[
        "Hol"
    ],
    "name:war_x_preferred":[
        "Hol"
    ],
    "wof:name":"Hol",
    "wof:placetype":"locality"
},
  "geometry": {"coordinates":[74.481934,21.572637],"type":"Point"}
}