{
  "type": "Feature",
  "properties": {
    "iso:country":"IN",
    "ks:ks_name":"Buddibanda",
    "ks:ks_pop":168,
    "ks:ks_type":"VILLAGE",
    "name:eng_x_preferred":[
        "Buddibanda"
    ],
    "wof:name":"Buddibanda",
    "wof:placetype":"locality",
    "wof:population":168
},
  "geometry": {"coordinates":[82.766088,17.830001],"type":"Point"}
}