{
  "type": "Feature",
  "properties": {
    "iso:country":"IN",
    "ks:ks_name":"Chak Hanumatpura",
    "ks:ks_pop":321,
    "ks:ks_type":"HABITATION",
    "name:eng_x_preferred":[
        "Chak Hanumatpura"
    ],
    "wof:name":"Chak Hanumatpura",
    "wof:placetype":"locality",
    "wof:population":321
},
  "geometry": {"coordinates":[77.303847,24.725801],"type":"Point"}
}