{
  "type": "Feature",
  "properties": {
    "iso:country":"IN",
    "ks:ks_name":"Dakshin Mohanpur Pt X",
    "ks:ks_pop":1699,
    "ks:ks_type":"VILLAGE",
    "name:eng_x_preferred":[
        "Dakshin Mohanpur Pt X"
    ],
    "wof:name":"Dakshin Mohanpur Pt X",
    "wof:placetype":"locality",
    "wof:population":1699
},
  "geometry": {"coordinates":[92.93419,24.709655],"type":"Point"}
}