{
  "type": "Feature",
  "properties": {
    "iso:country":"IN",
    "ks:ks_alt_nam":"KASHID WASTI",
    "ks:ks_name":"Kashid Wasti",
    "ks:ks_pop":113,
    "ks:ks_type":"HABITATION",
    "name:eng_x_preferred":[
        "Kashid Wasti"
    ],
    "wof:name":"Kashid Wasti",
    "wof:placetype":"locality",
    "wof:population":113
},
  "geometry": {"coordinates":[74.82147399999999,16.988836],"type":"Point"}
}