{
  "type": "Feature",
  "properties": {
    "iso:country":"IN",
    "ks:ks_name":"Maranery",
    "ks:ks_pop":1253,
    "ks:ks_type":"HABITATION",
    "name:eng_x_preferred":[
        "Maranery"
    ],
    "wof:name":"Maranery",
    "wof:placetype":"locality",
    "wof:population":1253
},
  "geometry": {"coordinates":[78.908098,10.792525],"type":"Point"}
}