{
  "type": "Feature",
  "properties": {
    "iso:country":"IN",
    "ks:ks_name":"Tinkonia Para",
    "ks:ks_pop":2635,
    "ks:ks_type":"VILLAGE",
    "ks:ks_uagg_main":0,
    "name:eng_x_preferred":[
        "Tinkonia Para"
    ],
    "wof:name":"Tinkonia Para",
    "wof:placetype":"neighbourhood",
    "wof:population":2635
},
  "geometry": {"coordinates":[90.729777,26.102228],"type":"Point"}
}