{
  "type": "Feature",
  "properties": {
    "gn:admin1_code":"21.0",
    "gn:admin2_code":"396.0",
    "gn:asciiname":"Kenduguda",
    "gn:country_code":"IN",
    "gn:dem":331,
    "gn:feature_class":"P",
    "gn:feature_code":"PPL",
    "gn:name":"Kenduguda",
    "gn:population":0,
    "gn:timezone":"Asia/Kolkata",
    "iso:country":"IN",
    "wof:name":"Kenduguda",
    "wof:placetype":"neighbourhood"
},
  "geometry": {"coordinates":[83.31431000000001,19.43386],"type":"Point"}
}