{
  "type": "Feature",
  "properties": {
    "iso:country":"IN",
    "ks:ks_name":"Baridih",
    "ks:ks_pop":130,
    "ks:ks_type":"HABITATION",
    "name:eng_x_preferred":[
        "Baridih"
    ],
    "wof:name":"Baridih",
    "wof:placetype":"locality",
    "wof:population":130
},
  "geometry": {"coordinates":[85.675135,22.967528],"type":"Point"}
}