{
  "type": "Feature",
  "properties": {
    "iso:country":"IN",
    "ks:ks_name":"Mahroopur",
    "ks:ks_pop":117,
    "ks:ks_type":"HABITATION",
    "ks:ks_uagg_main":0,
    "name:eng_x_preferred":[
        "Mahroopur"
    ],
    "wof:name":"Mahroopur",
    "wof:placetype":"neighbourhood",
    "wof:population":117
},
  "geometry": {"coordinates":[83.390775,26.0986],"type":"Point"}
}