{
  "type": "Feature",
  "properties": {
    "iso:country":"IN",
    "ks:ks_name":"Cherukumpakalu",
    "ks:ks_pop":99,
    "ks:ks_type":"HABITATION",
    "name:eng_x_preferred":[
        "Cherukumpakalu"
    ],
    "wof:name":"Cherukumpakalu",
    "wof:placetype":"locality",
    "wof:population":99
},
  "geometry": {"coordinates":[82.19080700000001,17.833184],"type":"Point"}
}