{
  "type": "Feature",
  "properties": {
    "iso:country":"IN",
    "ks:ks_name":"Korikanakurmiraja Puram",
    "ks:ks_pop":609,
    "ks:ks_type":"VILLAGE",
    "ks:ks_uagg_main":0,
    "name:eng_x_preferred":[
        "Korikanakurmiraja Puram"
    ],
    "wof:name":"Korikanakurmiraja Puram",
    "wof:placetype":"neighbourhood",
    "wof:population":609
},
  "geometry": {"coordinates":[83.82674900000001,18.528755],"type":"Point"}
}