{
  "type": "Feature",
  "properties": {
    "iso:country":"IN",
    "ks:ks_name":"Palaya Ramachandrapuram",
    "ks:ks_pop":254,
    "ks:ks_type":"HABITATION",
    "name:eng_x_preferred":[
        "Palaya Ramachandrapuram"
    ],
    "wof:name":"Palaya Ramachandrapuram",
    "wof:placetype":"locality",
    "wof:population":254
},
  "geometry": {"coordinates":[77.516069,9.914479],"type":"Point"}
}