{
  "type": "Feature",
  "properties": {
    "iso:country":"IN",
    "ks:ks_name":"Katphorwa",
    "ks:ks_pop":0,
    "ks:ks_type":"VILLAGE",
    "name:eng_x_preferred":[
        "Katphorwa"
    ],
    "wof:name":"Katphorwa",
    "wof:placetype":"locality",
    "wof:population":0
},
  "geometry": {"coordinates":[84.053251,27.189887],"type":"Point"}
}