{
  "type": "Feature",
  "properties": {
    "gn:admin1_code":"37",
    "gn:admin2_code":"408.0",
    "gn:asciiname":"Bijnapur",
    "gn:country_code":"IN",
    "gn:dem":352,
    "gn:feature_class":"P",
    "gn:feature_code":"PPL",
    "gn:name":"Bijn\u0101pur",
    "gn:population":0,
    "gn:timezone":"Asia/Kolkata",
    "iso:country":"IN",
    "ks:ks_alt_nam":"Bijn\u0101pur",
    "ks:ks_name":"Bijnapur",
    "ks:ks_pop":945,
    "ks:ks_type":"VILLAGE",
    "name:eng_x_preferred":[
        "Bijnapur"
    ],
    "name:eng_x_variant":[
        "Bijn\u0101pur"
    ],
    "wof:name":"Bijnapur",
    "wof:placetype":"locality",
    "wof:population":945
},
  "geometry": {"coordinates":[80.884708,21.25681],"type":"Point"}
}