{
  "type": "Feature",
  "properties": {
    "gn:admin1_code":"37",
    "gn:admin2_code":"408.0",
    "gn:asciiname":"Bijnapur",
    "gn:country_code":"IN",
    "gn:dem":352,
    "gn:feature_class":"P",
    "gn:feature_code":"PPL",
    "gn:name":"Bijn\u0101pur",
    "gn:population":0,
    "gn:timezone":"Asia/Kolkata",
    "iso:country":"IN",
    "wof:name":"Bijnapur",
    "wof:placetype":"locality"
},
  "geometry": {"coordinates":[80.88766,21.25542],"type":"Point"}
}