{
  "type": "Feature",
  "properties": {
    "gn:admin1_code":"19.0",
    "gn:admin2_code":"569.0",
    "gn:asciiname":"Barkala",
    "gn:country_code":"IN",
    "gn:dem":114,
    "gn:feature_class":"P",
    "gn:feature_code":"PPL",
    "gn:name":"Barkala",
    "gn:population":0,
    "gn:timezone":"Asia/Kolkata",
    "iso:country":"IN",
    "name:ceb_x_preferred":[
        "B\u0101rkal\u0101"
    ],
    "name:fas_x_preferred":[
        "\u0628\u0627\u0631\u06a9\u0644\u0627"
    ],
    "name:swe_x_preferred":[
        "B\u0101rkal\u0101"
    ],
    "wof:name":"Barkala",
    "wof:placetype":"locality"
},
  "geometry": {"coordinates":[74.97804000000002,13.10447],"type":"Point"}
}