{
  "type": "Feature",
  "properties": {
    "iso:country":"IN",
    "ks:ks_name":"Muzhakkom",
    "ks:ks_pop":1564,
    "ks:ks_type":"HABITATION",
    "name:eng_x_preferred":[
        "Muzhakkom"
    ],
    "wof:name":"Muzhakkom",
    "wof:placetype":"locality",
    "wof:population":1564
},
  "geometry": {"coordinates":[75.170362,12.254129],"type":"Point"}
}