{
  "type": "Feature",
  "properties": {
    "gn:admin1_code":"13.0",
    "gn:admin2_code":"590.0",
    "gn:asciiname":"Kirapatta",
    "gn:country_code":"IN",
    "gn:dem":747,
    "gn:feature_class":"P",
    "gn:feature_code":"PPL",
    "gn:name":"Kirapatta",
    "gn:population":0,
    "gn:timezone":"Asia/Kolkata",
    "iso:country":"IN",
    "wof:name":"Kirapatta",
    "wof:placetype":"locality"
},
  "geometry": {"coordinates":[76.11651999999999,11.69757],"type":"Point"}
}