{
  "type": "Feature",
  "properties": {
    "gn:admin1_code":"23",
    "gn:admin2_code":"38.0",
    "gn:asciiname":"Kathana",
    "gn:country_code":"IN",
    "gn:dem":241,
    "gn:feature_class":"P",
    "gn:feature_code":"PPL",
    "gn:name":"Kath\u0101na",
    "gn:population":0,
    "gn:timezone":"Asia/Kolkata",
    "iso:country":"IN",
    "ks:ks_alt_nam":"Kath\u0101na",
    "ks:ks_name":"Kathana",
    "ks:ks_type":"VILLAGE",
    "name:ben_x_preferred":[
        "\u0995\u09be\u09a5\u09a8\u09be \u09a8\u09a6\u09c0"
    ],
    "name:eng_x_preferred":[
        "Kathana"
    ],
    "name:eng_x_variant":[
        "Kath\u0101na"
    ],
    "name:hin_x_preferred":[
        "\u0915\u0920\u0928\u093e \u0928\u0926\u0940"
    ],
    "wof:name":"Kathana",
    "wof:placetype":"locality"
},
  "geometry": {"coordinates":[75.565878,31.846798],"type":"Point"}
}