{
  "type": "Feature",
  "properties": {
    "iso:country":"IN",
    "ks:ks_name":"Tulapur",
    "ks:ks_pop":547,
    "ks:ks_type":"VILLAGE",
    "name:eng_x_preferred":[
        "Tulapur"
    ],
    "wof:name":"Tulapur",
    "wof:placetype":"locality",
    "wof:population":547
},
  "geometry": {"coordinates":[81.904788,26.621442],"type":"Point"}
}