{
  "type": "Feature",
  "properties": {
    "gn:admin1_code":"25.0",
    "gn:admin2_code":"621.0",
    "gn:asciiname":"Kallakkottai",
    "gn:country_code":"IN",
    "gn:dem":60,
    "gn:feature_class":"P",
    "gn:feature_code":"PPL",
    "gn:name":"Kall\u0101kkottai",
    "gn:population":0,
    "gn:timezone":"Asia/Kolkata",
    "iso:country":"IN",
    "wof:name":"Kallakkottai",
    "wof:placetype":"locality"
},
  "geometry": {"coordinates":[79.10603,10.51981],"type":"Point"}
}