{
  "type": "Feature",
  "properties": {
    "gn:admin1_code":"16",
    "gn:admin2_code":"530.0",
    "gn:asciiname":"Unchagao",
    "gn:country_code":"IN",
    "gn:dem":561,
    "gn:feature_class":"P",
    "gn:feature_code":"PPL",
    "gn:name":"Unchagao",
    "gn:population":0,
    "gn:timezone":"Asia/Kolkata",
    "iso:country":"IN",
    "name:und_x_variant":[
        "Unchagoa",
        "Unchagao"
    ],
    "wof:name":"Unchagao",
    "wof:placetype":"neighbourhood"
},
  "geometry": {"coordinates":[74.27325,16.69746],"type":"Point"}
}