{
  "type": "Feature",
  "properties": {
    "iso:country":"IN",
    "ks:ks_alt_nam":"Cholanavayal mellimudi",
    "ks:ks_name":"Cholanavayal Mellimudi",
    "ks:ks_pop":300,
    "ks:ks_type":"HABITATION",
    "name:eng_x_preferred":[
        "Cholanavayal Mellimudi"
    ],
    "wof:name":"Cholanavayal Mellimudi",
    "wof:placetype":"locality",
    "wof:population":300
},
  "geometry": {"coordinates":[76.833197,9.382265],"type":"Point"}
}