{
  "type": "Feature",
  "properties": {
    "iso:country":"IN",
    "ks:ks_name":"Undewasti West",
    "ks:ks_pop":169,
    "ks:ks_type":"HABITATION",
    "name:eng_x_preferred":[
        "Undewasti West"
    ],
    "wof:name":"Undewasti West",
    "wof:placetype":"locality",
    "wof:population":169
},
  "geometry": {"coordinates":[74.584231,18.680629],"type":"Point"}
}