{
  "type": "Feature",
  "properties": {
    "gn:admin1_code":"28.0",
    "gn:admin2_code":"334.0",
    "gn:asciiname":"Sripur",
    "gn:country_code":"IN",
    "gn:dem":42,
    "gn:feature_class":"P",
    "gn:feature_code":"PPL",
    "gn:name":"Sripur",
    "gn:population":0,
    "gn:timezone":"Asia/Kolkata",
    "iso:country":"IN",
    "name:bih_x_preferred":[
        "\u0936\u094d\u0930\u0940\u092a\u0941\u0930"
    ],
    "wof:name":"Sripur",
    "wof:placetype":"locality"
},
  "geometry": {"coordinates":[87.89806999999998,24.29944],"type":"Point"}
}