{
  "type": "Feature",
  "properties": {
    "iso:country":"IN",
    "ks:ks_name":"Hawai Bari",
    "ks:ks_pop":680,
    "ks:ks_type":"HABITATION",
    "name:eng_x_preferred":[
        "Hawai Bari"
    ],
    "wof:name":"Hawai Bari",
    "wof:placetype":"locality",
    "wof:population":680
},
  "geometry": {"coordinates":[91.6087,23.139803],"type":"Point"}
}