{
  "type": "Feature",
  "properties": {
    "iso:country":"IN",
    "ks:ks_name":"Mettuppatti",
    "ks:ks_pop":160,
    "ks:ks_type":"HABITATION",
    "name:eng_x_preferred":[
        "Mettuppatti"
    ],
    "wof:name":"Mettuppatti",
    "wof:placetype":"locality",
    "wof:population":160
},
  "geometry": {"coordinates":[79.03293499999999,10.489172],"type":"Point"}
}