{
  "type": "Feature",
  "properties": {
    "iso:country":"IN",
    "ks:ks_name":"Baroan",
    "ks:ks_pop":292,
    "ks:ks_type":"VILLAGE",
    "name:eng_x_preferred":[
        "Baroan"
    ],
    "wof:name":"Baroan",
    "wof:placetype":"locality",
    "wof:population":292
},
  "geometry": {"coordinates":[86.981494,24.043023],"type":"Point"}
}