{
  "type": "Feature",
  "properties": {
    "gn:admin1_code":"19.0",
    "gn:admin2_code":"577.0",
    "gn:asciiname":"Siddagaudanhundi",
    "gn:country_code":"IN",
    "gn:dem":744,
    "gn:feature_class":"P",
    "gn:feature_code":"PPL",
    "gn:name":"Sidd\u0101gaudanhundi",
    "gn:population":0,
    "gn:timezone":"Asia/Kolkata",
    "iso:country":"IN",
    "wof:name":"Siddagaudanhundi",
    "wof:placetype":"locality"
},
  "geometry": {"coordinates":[76.55159999999999,11.99651],"type":"Point"}
}