{
  "type": "Feature",
  "properties": {
    "gn:admin1_code":"24.0",
    "gn:admin2_code":"130.0",
    "gn:asciiname":"Lalpura",
    "gn:country_code":"IN",
    "gn:dem":391,
    "gn:feature_class":"P",
    "gn:feature_code":"PPL",
    "gn:name":"L\u0101lpura",
    "gn:population":0,
    "gn:timezone":"Asia/Kolkata",
    "iso:country":"IN",
    "ks:ks_alt_nam":"L\u0101lpura",
    "ks:ks_name":"Lalpura",
    "ks:ks_type":"VILLAGE",
    "name:eng_x_preferred":[
        "Lalpura"
    ],
    "name:eng_x_variant":[
        "L\u0101lpura"
    ],
    "wof:name":"Lalpura",
    "wof:placetype":"locality"
},
  "geometry": {"coordinates":[74.33201,24.202851],"type":"Point"}
}