{
  "type": "Feature",
  "properties": {
    "gn:admin1_code":"2.0",
    "gn:admin2_code":"549.0",
    "gn:asciiname":"Pennikavandlapalle",
    "gn:country_code":"IN",
    "gn:dem":72,
    "gn:feature_class":"P",
    "gn:feature_code":"PPL",
    "gn:name":"Pennikav\u0101ndlapalle",
    "gn:population":0,
    "gn:timezone":"Asia/Kolkata",
    "iso:country":"IN",
    "wof:name":"Pennikavandlapalle",
    "wof:placetype":"neighbourhood"
},
  "geometry": {"coordinates":[79.68192999999999,15.54952],"type":"Point"}
}