{
  "type": "Feature",
  "properties": {
    "iso:country":"IN",
    "ks:ks_name":"Thundil Jn",
    "ks:ks_pop":1025,
    "ks:ks_type":"HABITATION",
    "name:eng_x_preferred":[
        "Thundil Jn"
    ],
    "wof:name":"Thundil Jn",
    "wof:placetype":"locality",
    "wof:population":1025
},
  "geometry": {"coordinates":[76.669905,8.910214],"type":"Point"}
}