{
  "type": "Feature",
  "properties": {
    "iso:country":"IN",
    "ks:ks_name":"Sullyody",
    "ks:ks_pop":100,
    "ks:ks_type":"HABITATION",
    "name:eng_x_preferred":[
        "Sullyody"
    ],
    "wof:name":"Sullyody",
    "wof:placetype":"locality",
    "wof:population":100
},
  "geometry": {"coordinates":[75.309715,13.067893],"type":"Point"}
}