{
  "type": "Feature",
  "properties": {
    "gn:admin1_code":"2.0",
    "gn:admin2_code":"553.0",
    "gn:asciiname":"Papasanapalle",
    "gn:country_code":"IN",
    "gn:dem":706,
    "gn:feature_class":"P",
    "gn:feature_code":"PPL",
    "gn:name":"P\u0101pasanapalle",
    "gn:population":0,
    "gn:timezone":"Asia/Kolkata",
    "iso:country":"IN",
    "wof:name":"Papasanapalle",
    "wof:placetype":"locality"
},
  "geometry": {"coordinates":[77.21799,13.93512],"type":"Point"}
}