{
  "type": "Feature",
  "properties": {
    "iso:country":"IN",
    "ks:ks_name":"Salgerya",
    "ks:ks_pop":636,
    "ks:ks_type":"HABITATION",
    "name:eng_x_preferred":[
        "Salgerya"
    ],
    "wof:name":"Salgerya",
    "wof:placetype":"locality",
    "wof:population":636
},
  "geometry": {"coordinates":[86.89981299999999,22.176354],"type":"Point"}
}