{
  "type": "Feature",
  "properties": {
    "gn:admin1_code":"16.0",
    "gn:admin2_code":"498.0",
    "gn:asciiname":"Vikhran Khurd",
    "gn:country_code":"IN",
    "gn:dem":165,
    "gn:feature_class":"P",
    "gn:feature_code":"PPL",
    "gn:name":"Vikhran Khurd",
    "gn:population":0,
    "gn:timezone":"Asia/Kolkata",
    "iso:country":"IN",
    "wof:name":"Vikhran Khurd",
    "wof:placetype":"neighbourhood"
},
  "geometry": {"coordinates":[74.79089999999999,21.41579],"type":"Point"}
}