{
  "type": "Feature",
  "properties": {
    "iso:country":"IN",
    "ks:ks_name":"Konangi",
    "ks:ks_pop":199,
    "ks:ks_type":"VILLAGE",
    "name:eng_x_preferred":[
        "Konangi"
    ],
    "wof:name":"Konangi",
    "wof:placetype":"locality",
    "wof:population":199
},
  "geometry": {"coordinates":[84.14967900000001,18.670609],"type":"Point"}
}