{
  "type": "Feature",
  "properties": {
    "iso:country":"IN",
    "ks:ks_name":"Adwaria Najari",
    "ks:ks_pop":347,
    "ks:ks_type":"HABITATION",
    "name:eng_x_preferred":[
        "Adwaria Najari"
    ],
    "wof:name":"Adwaria Najari",
    "wof:placetype":"locality",
    "wof:population":347
},
  "geometry": {"coordinates":[86.40543099999999,25.04745],"type":"Point"}
}