{
  "type": "Feature",
  "properties": {
    "iso:country":"IN",
    "ks:ks_name":"Bhelvatikara",
    "ks:ks_pop":153,
    "ks:ks_type":"HABITATION",
    "name:eng_x_preferred":[
        "Bhelvatikara"
    ],
    "wof:name":"Bhelvatikara",
    "wof:placetype":"locality",
    "wof:population":153
},
  "geometry": {"coordinates":[83.59151300000001,22.240814],"type":"Point"}
}