{
  "type": "Feature",
  "properties": {
    "gn:admin1_code":"24.0",
    "gn:admin2_code":"119.0",
    "gn:asciiname":"Rupaheli Khurd",
    "gn:country_code":"IN",
    "gn:dem":470,
    "gn:feature_class":"P",
    "gn:feature_code":"PPL",
    "gn:name":"R\u016bp\u0101heli Khurd",
    "gn:population":0,
    "gn:timezone":"Asia/Kolkata",
    "iso:country":"IN",
    "wof:name":"Rupaheli Khurd",
    "wof:placetype":"locality"
},
  "geometry": {"coordinates":[74.39439,25.98253],"type":"Point"}
}