{
  "type": "Feature",
  "properties": {
    "gn:admin1_code":"19.0",
    "gn:admin2_code":"582.0",
    "gn:asciiname":"Krishnahalli",
    "gn:country_code":"IN",
    "gn:dem":898,
    "gn:feature_class":"P",
    "gn:feature_code":"PPL",
    "gn:name":"Krishnahalli",
    "gn:population":0,
    "gn:timezone":"Asia/Kolkata",
    "iso:country":"IN",
    "wof:name":"Krishnahalli",
    "wof:placetype":"locality"
},
  "geometry": {"coordinates":[77.90151999999998,13.28703],"type":"Point"}
}