{
  "type": "Feature",
  "properties": {
    "iso:country":"IN",
    "ks:ks_alt_nam":"Tamultikuchi NC",
    "ks:ks_name":"Tamultikuchi Nc",
    "ks:ks_pop":1020,
    "ks:ks_type":"HABITATION",
    "name:eng_x_preferred":[
        "Tamultikuchi Nc"
    ],
    "wof:name":"Tamultikuchi Nc",
    "wof:placetype":"locality",
    "wof:population":1020
},
  "geometry": {"coordinates":[91.91064900000001,26.084549],"type":"Point"}
}