{
  "type": "Feature",
  "properties": {
    "iso:country":"IN",
    "ks:ks_name":"Hapanada",
    "ks:ks_pop":1036,
    "ks:ks_type":"VILLAGE",
    "name:eng_x_preferred":[
        "Hapanada"
    ],
    "wof:name":"Hapanada",
    "wof:placetype":"locality",
    "wof:population":1036
},
  "geometry": {"coordinates":[72.515075,26.281583],"type":"Point"}
}