{
  "type": "Feature",
  "properties": {
    "gn:admin1_code":"12.0",
    "gn:admin2_code":"16.0",
    "gn:asciiname":"Lotira",
    "gn:country_code":"IN",
    "gn:dem":1589,
    "gn:feature_class":"P",
    "gn:feature_code":"PPL",
    "gn:name":"L\u014dtira",
    "gn:population":0,
    "gn:timezone":"Asia/Kolkata",
    "iso:country":"IN",
    "wof:name":"Lotira",
    "wof:placetype":"locality"
},
  "geometry": {"coordinates":[75.75333000000001,33.13107],"type":"Point"}
}