{
  "type": "Feature",
  "properties": {
    "iso:country":"IN",
    "ks:ks_name":"Satgabari",
    "ks:ks_pop":1839,
    "ks:ks_type":"VILLAGE",
    "ks:ks_uagg_main":0,
    "name:eng_x_preferred":[
        "Satgabari"
    ],
    "wof:name":"Satgabari",
    "wof:placetype":"neighbourhood",
    "wof:population":1839
},
  "geometry": {"coordinates":[87.92870000000001,21.964512],"type":"Point"}
}