{
  "type": "Feature",
  "properties": {
    "gn:admin1_code":"2",
    "gn:admin2_code":"544.0",
    "gn:asciiname":"Vijayaramarajupeta",
    "gn:country_code":"IN",
    "gn:dem":56,
    "gn:feature_class":"P",
    "gn:feature_code":"PPL",
    "gn:name":"Vijayar\u0101mar\u0101jupeta",
    "gn:population":0,
    "gn:timezone":"Asia/Kolkata",
    "iso:country":"IN",
    "wof:name":"Vijayaramarajupeta",
    "wof:placetype":"locality"
},
  "geometry": {"coordinates":[82.88056999999998,17.85584],"type":"Point"}
}