{
  "type": "Feature",
  "properties": {
    "iso:country":"IN",
    "ks:ks_alt_nam":"DHURACHA TANDA",
    "ks:ks_name":"Dhuracha Tanda",
    "ks:ks_pop":162,
    "ks:ks_type":"HABITATION",
    "name:eng_x_preferred":[
        "Dhuracha Tanda"
    ],
    "wof:name":"Dhuracha Tanda",
    "wof:placetype":"locality",
    "wof:population":162
},
  "geometry": {"coordinates":[76.320975,17.883391],"type":"Point"}
}