{
  "type": "Feature",
  "properties": {
    "gn:admin1_code":"35.0",
    "gn:admin2_code":"454.0",
    "gn:asciiname":"Bastara",
    "gn:country_code":"IN",
    "gn:dem":689,
    "gn:feature_class":"P",
    "gn:feature_code":"PPL",
    "gn:name":"Bastara",
    "gn:population":0,
    "gn:timezone":"Asia/Kolkata",
    "iso:country":"IN",
    "ks:ks_name":"Bastara",
    "ks:ks_pop":606,
    "ks:ks_type":"VILLAGE",
    "name:eng_x_preferred":[
        "Bastara"
    ],
    "wof:name":"Bastara",
    "wof:placetype":"locality",
    "wof:population":606
},
  "geometry": {"coordinates":[80.358012,22.984428],"type":"Point"}
}