{
  "type": "Feature",
  "properties": {
    "iso:country":"IN",
    "name:ast_x_preferred":[
        "Anjarle"
    ],
    "name:ceb_x_preferred":[
        "\u0100njarle"
    ],
    "name:eng_x_preferred":[
        "Anjarle"
    ],
    "name:nld_x_preferred":[
        "Anjarle"
    ],
    "name:swe_x_preferred":[
        "\u0100njarle"
    ],
    "qs:name":"Anjarla",
    "qs:name_adm0":"India",
    "qs:name_adm1":"Maharashtra",
    "qs:photos":15,
    "qs:photos_1k":3,
    "qs:photos_9k":1,
    "qs:photos_9r":1,
    "qs:photos_all":15,
    "qs:photos_sr":1,
    "qs:placetype":"Town",
    "qs:pop_sr":"0",
    "wd:elevation":36.0,
    "wd:wordcount":470,
    "wof:name":"Anjarla",
    "wof:placetype":"locality"
},
  "geometry": {"coordinates":[73.088092,17.846069],"type":"Point"}
}