{
  "type": "Feature",
  "properties": {
    "iso:country":"IN",
    "ks:ks_name":"Anjarla",
    "ks:ks_pop":1654,
    "ks:ks_type":"VILLAGE",
    "name:ast_x_preferred":[
        "Anjarle"
    ],
    "name:azb_x_preferred":[
        "\u0622\u0646\u062c\u0627\u0631\u0644"
    ],
    "name:ceb_x_preferred":[
        "\u0100njarle"
    ],
    "name:eng_x_preferred":[
        "Anjarla"
    ],
    "name:eng_x_variant":[
        "Anjarle"
    ],
    "name:hin_x_preferred":[
        "\u0906\u0902\u091c\u0930\u094d\u0932\u0947"
    ],
    "name:kan_x_preferred":[
        "\u0c86\u0c82\u0c9c\u0cb0\u0ccd\u0cb2\u0cc6"
    ],
    "name:mar_x_preferred":[
        "\u0906\u0902\u091c\u0930\u094d\u0932\u0947"
    ],
    "name:nld_x_preferred":[
        "Anjarle"
    ],
    "name:swe_x_preferred":[
        "\u0100njarle"
    ],
    "qs:name":"Anjarla",
    "qs:name_adm0":"India",
    "qs:name_adm1":"Maharashtra",
    "qs:photos":15,
    "qs:photos_1k":3,
    "qs:photos_9k":1,
    "qs:photos_9r":1,
    "qs:photos_all":15,
    "qs:photos_sr":1,
    "qs:placetype":"Town",
    "qs:pop_sr":"0",
    "wd:elevation":36.0,
    "wd:wordcount":470,
    "wof:name":"Anjarla",
    "wof:placetype":"locality",
    "wof:population":1654
},
  "geometry": {"coordinates":[73.09076899999999,17.847641],"type":"Point"}
}