{
  "type": "Feature",
  "properties": {
    "iso:country":"IN",
    "ks:ks_name":"Mepu",
    "ks:ks_pop":90,
    "ks:ks_type":"HABITATION",
    "ks:ks_uagg_main":0,
    "name:eng_x_preferred":[
        "Mepu"
    ],
    "wof:name":"Mepu",
    "wof:placetype":"neighbourhood",
    "wof:population":90
},
  "geometry": {"coordinates":[74.712181,13.592007],"type":"Point"}
}