{
  "type": "Feature",
  "properties": {
    "iso:country":"IN",
    "ks:ks_name":"Kesarpura",
    "ks:ks_pop":2774,
    "ks:ks_type":"VILLAGE",
    "ks:ks_uagg_main":0,
    "name:eng_x_preferred":[
        "Kesarpura"
    ],
    "wof:name":"Kesarpura",
    "wof:placetype":"neighbourhood",
    "wof:population":2774
},
  "geometry": {"coordinates":[73.062817,25.124822],"type":"Point"}
}