{
  "type": "Feature",
  "properties": {
    "gn:admin1_code":"21.0",
    "gn:admin2_code":"398.0",
    "gn:asciiname":"Oripara",
    "gn:country_code":"IN",
    "gn:dem":878,
    "gn:feature_class":"P",
    "gn:feature_code":"PPL",
    "gn:name":"Orip\u0101ra",
    "gn:population":0,
    "gn:timezone":"Asia/Kolkata",
    "iso:country":"IN",
    "wof:name":"Oripara",
    "wof:placetype":"neighbourhood"
},
  "geometry": {"coordinates":[82.57147999999999,18.57785],"type":"Point"}
}