{
  "type": "Feature",
  "properties": {
    "gn:admin1_code":"36.0",
    "gn:admin2_code":"183.0",
    "gn:asciiname":"Ramgarhwa Sridat Singh",
    "gn:country_code":"IN",
    "gn:dem":108,
    "gn:feature_class":"P",
    "gn:feature_code":"PPL",
    "gn:name":"R\u0101mgarhwa Sr\u012bdat Singh",
    "gn:population":0,
    "gn:timezone":"Asia/Kolkata",
    "iso:country":"IN",
    "wof:name":"Ramgarhwa Sridat Singh",
    "wof:placetype":"locality"
},
  "geometry": {"coordinates":[82.16535999999998,27.18582],"type":"Point"}
}