{
  "type": "Feature",
  "properties": {
    "iso:country":"IN",
    "ks:ks_name":"Shirlkarwadi",
    "ks:ks_pop":192,
    "ks:ks_type":"HABITATION",
    "name:eng_x_preferred":[
        "Shirlkarwadi"
    ],
    "wof:name":"Shirlkarwadi",
    "wof:placetype":"locality",
    "wof:population":192
},
  "geometry": {"coordinates":[73.45916699999999,17.518889],"type":"Point"}
}