{
  "type": "Feature",
  "properties": {
    "gn:admin1_code":"24",
    "gn:admin2_code":"119.0",
    "gn:asciiname":"Surajpura",
    "gn:country_code":"IN",
    "gn:dem":439,
    "gn:feature_class":"P",
    "gn:feature_code":"PPL",
    "gn:name":"S\u016brajpura",
    "gn:population":0,
    "gn:timezone":"Asia/Kolkata",
    "iso:country":"IN",
    "wof:name":"Surajpura",
    "wof:placetype":"locality"
},
  "geometry": {"coordinates":[74.4943,26.00257],"type":"Point"}
}