{
  "type": "Feature",
  "properties": {
    "iso:country":"IN",
    "ks:ks_alt_nam":"Mushari tola",
    "ks:ks_name":"Mushari Tola",
    "ks:ks_pop":106,
    "ks:ks_type":"HABITATION",
    "name:eng_x_preferred":[
        "Mushari Tola"
    ],
    "wof:name":"Mushari Tola",
    "wof:placetype":"locality",
    "wof:population":106
},
  "geometry": {"coordinates":[86.37751799999999,26.288513],"type":"Point"}
}