{
  "type": "Feature",
  "properties": {
    "gn:admin1_code":"19",
    "gn:admin2_code":"563.0",
    "gn:asciiname":"Hasragod",
    "gn:country_code":"IN",
    "gn:dem":509,
    "gn:feature_class":"P",
    "gn:feature_code":"PPL",
    "gn:name":"Hasragod",
    "gn:population":0,
    "gn:timezone":"Asia/Kolkata",
    "iso:country":"IN",
    "ks:ks_name":"Hasargod",
    "ks:ks_pop":850,
    "ks:ks_type":"VILLAGE",
    "name:eng_x_preferred":[
        "Hasargod"
    ],
    "name:eng_x_variant":[
        "Hasragod"
    ],
    "wof:name":"Hasargod",
    "wof:placetype":"locality",
    "wof:population":850
},
  "geometry": {"coordinates":[74.79248200000001,14.498231],"type":"Point"}
}