{
  "type": "Feature",
  "properties": {
    "iso:country":"IN",
    "ks:ks_name":"Diguvapatrapalli",
    "ks:ks_pop":86,
    "ks:ks_type":"HABITATION",
    "ks:ks_uagg_main":0,
    "name:eng_x_preferred":[
        "Diguvapatrapalli"
    ],
    "wof:name":"Diguvapatrapalli",
    "wof:placetype":"neighbourhood",
    "wof:population":86
},
  "geometry": {"coordinates":[78.519587,13.423714],"type":"Point"}
}