{
  "type": "Feature",
  "properties": {
    "gn:admin1_code":"37.0",
    "gn:admin2_code":"414.0",
    "gn:asciiname":"Taraibera",
    "gn:country_code":"IN",
    "gn:dem":645,
    "gn:feature_class":"P",
    "gn:feature_code":"PPL",
    "gn:name":"Taraibera",
    "gn:population":0,
    "gn:timezone":"Asia/Kolkata",
    "iso:country":"IN",
    "wof:name":"Taraibera",
    "wof:placetype":"locality"
},
  "geometry": {"coordinates":[81.80153,19.94106],"type":"Point"}
}