{
  "type": "Feature",
  "properties": {
    "gn:admin1_code":"2.0",
    "gn:admin2_code":"553.0",
    "gn:asciiname":"Tangamvandlapalle",
    "gn:country_code":"IN",
    "gn:dem":471,
    "gn:feature_class":"P",
    "gn:feature_code":"PPL",
    "gn:name":"Tangamv\u0101ndlapalle",
    "gn:population":0,
    "gn:timezone":"Asia/Kolkata",
    "iso:country":"IN",
    "wof:name":"Tangamvandlapalle",
    "wof:placetype":"locality"
},
  "geometry": {"coordinates":[77.86962,14.25994],"type":"Point"}
}