{
  "type": "Feature",
  "properties": {
    "gn:admin1_code":"7.0",
    "gn:admin2_code":"90.0",
    "gn:asciiname":"Bazidpur Thakuran",
    "gn:country_code":"IN",
    "gn:dem":221,
    "gn:feature_class":"P",
    "gn:feature_code":"PPL",
    "gn:name":"B\u0101z\u012bdpur Th\u0101kur\u0101n",
    "gn:population":0,
    "gn:timezone":"Asia/Kolkata",
    "iso:country":"IN",
    "wof:name":"Bazidpur Thakuran",
    "wof:placetype":"neighbourhood"
},
  "geometry": {"coordinates":[77.00261999999999,28.8061],"type":"Point"}
}