{
  "type": "Feature",
  "properties": {
    "iso:country":"IN",
    "ks:ks_alt_nam":"Visal\u016br",
    "ks:ks_name":"Visalur",
    "ks:ks_pop":388,
    "ks:ks_type":"VILLAGE",
    "name:eng_x_preferred":[
        "Visalur"
    ],
    "name:eng_x_variant":[
        "Visal\u016br"
    ],
    "wof:name":"Visalur",
    "wof:placetype":"locality",
    "wof:population":388
},
  "geometry": {"coordinates":[78.85699700000001,10.646557],"type":"Point"}
}