{
  "type": "Feature",
  "properties": {
    "iso:country":"IN",
    "ks:ks_name":"Udegiri",
    "ks:ks_pop":100,
    "ks:ks_type":"VILLAGE",
    "name:eng_x_preferred":[
        "Udegiri"
    ],
    "wof:name":"Udegiri",
    "wof:placetype":"locality",
    "wof:population":100
},
  "geometry": {"coordinates":[83.627419,20.020718],"type":"Point"}
}