{
  "type": "Feature",
  "properties": {
    "iso:country":"IN",
    "ks:ks_name":"Sialtari",
    "ks:ks_pop":28,
    "ks:ks_type":"HABITATION",
    "name:eng_x_preferred":[
        "Sialtari"
    ],
    "wof:name":"Sialtari",
    "wof:placetype":"locality",
    "wof:population":28
},
  "geometry": {"coordinates":[90.087208,26.026499],"type":"Point"}
}