{
  "type": "Feature",
  "properties": {
    "gn:admin1_code":"12.0",
    "gn:admin2_code":"021",
    "gn:asciiname":"Kalianpur",
    "gn:country_code":"IN",
    "gn:dem":294,
    "gn:feature_class":"P",
    "gn:feature_code":"PPL",
    "gn:name":"Kali\u0101npur",
    "gn:population":0,
    "gn:timezone":"Asia/Kolkata",
    "iso:country":"IN",
    "wof:name":"Kalianpur",
    "wof:placetype":"locality"
},
  "geometry": {"coordinates":[74.72971,32.82283],"type":"Point"}
}