{
  "type": "Feature",
  "properties": {
    "gn:admin1_code":"12.0",
    "gn:admin2_code":"2.0",
    "gn:asciiname":"Laspur",
    "gn:country_code":"IN",
    "gn:dem":2072,
    "gn:feature_class":"P",
    "gn:feature_code":"PPL",
    "gn:name":"Laspur",
    "gn:population":0,
    "gn:timezone":"Asia/Kolkata",
    "iso:country":"IN",
    "name:fas_x_preferred":[
        "\u0644\u0627\u0633\u067e\u0648\u0631"
    ],
    "name:urd_x_preferred":[
        "\u0644\u0627\u0633\u067e\u0648\u0631"
    ],
    "wof:name":"Laspur",
    "wof:placetype":"locality"
},
  "geometry": {"coordinates":[74.55403000000003,33.95142],"type":"Point"}
}