{
  "type": "Feature",
  "properties": {
    "iso:country":"IN",
    "ks:ks_name":"Dakshin Bherbheri",
    "ks:ks_pop":346,
    "ks:ks_type":"VILLAGE",
    "name:eng_x_preferred":[
        "Dakshin Bherbheri"
    ],
    "wof:name":"Dakshin Bherbheri",
    "wof:placetype":"locality",
    "wof:population":346
},
  "geometry": {"coordinates":[90.85213,26.451873],"type":"Point"}
}