{
  "type": "Feature",
  "properties": {
    "iso:country":"IN",
    "ks:ks_name":"Tikari",
    "ks:ks_pop":125,
    "ks:ks_type":"VILLAGE",
    "name:eng_x_preferred":[
        "Tikari"
    ],
    "wof:name":"Tikari",
    "wof:placetype":"locality",
    "wof:population":125
},
  "geometry": {"coordinates":[80.887525,25.025182],"type":"Point"}
}