{
  "type": "Feature",
  "properties": {
    "iso:country":"IN",
    "ks:ks_name":"Sakpalwadi",
    "ks:ks_pop":120,
    "ks:ks_type":"HABITATION",
    "name:eng_x_preferred":[
        "Sakpalwadi"
    ],
    "wof:name":"Sakpalwadi",
    "wof:placetype":"locality",
    "wof:population":120
},
  "geometry": {"coordinates":[73.406333,17.903528],"type":"Point"}
}