{
  "type": "Feature",
  "properties": {
    "iso:country":"IN",
    "ks:ks_name":"Koaiduba",
    "ks:ks_pop":156,
    "ks:ks_type":"HABITATION",
    "name:eng_x_preferred":[
        "Koaiduba"
    ],
    "wof:name":"Koaiduba",
    "wof:placetype":"locality",
    "wof:population":156
},
  "geometry": {"coordinates":[84.358796,22.811955],"type":"Point"}
}