{
  "type": "Feature",
  "properties": {
    "gn:admin1_code":"2.0",
    "gn:admin2_code":"548.0",
    "gn:asciiname":"Chinnakancherla",
    "gn:country_code":"IN",
    "gn:dem":77,
    "gn:feature_class":"P",
    "gn:feature_code":"PPL",
    "gn:name":"Chinnakancherla",
    "gn:population":0,
    "gn:timezone":"Asia/Kolkata",
    "iso:country":"IN",
    "ks:ks_name":"Chinakancherla",
    "ks:ks_pop":1238,
    "ks:ks_type":"HABITATION",
    "ks:ks_uagg_main":0,
    "name:eng_x_preferred":[
        "Chinakancherla"
    ],
    "wof:name":"Chinakancherla",
    "wof:placetype":"neighbourhood",
    "wof:population":1238
},
  "geometry": {"coordinates":[79.82842599999999,16.061749],"type":"Point"}
}