{
  "type": "Feature",
  "properties": {
    "iso:country":"IN",
    "ks:ks_alt_nam":"NABAJOY PARA",
    "ks:ks_name":"Nabajoy Para",
    "ks:ks_pop":159,
    "ks:ks_type":"HABITATION",
    "name:eng_x_preferred":[
        "Nabajoy Para"
    ],
    "wof:name":"Nabajoy Para",
    "wof:placetype":"locality",
    "wof:population":159
},
  "geometry": {"coordinates":[91.7608,23.748585],"type":"Point"}
}