{
  "type": "Feature",
  "properties": {
    "gn:admin1_code":"16.0",
    "gn:admin2_code":"497.0",
    "gn:asciiname":"Padamund",
    "gn:country_code":"IN",
    "gn:dem":660,
    "gn:feature_class":"P",
    "gn:feature_code":"PPL",
    "gn:name":"P\u0101d\u0101mund",
    "gn:population":0,
    "gn:timezone":"Asia/Kolkata",
    "iso:country":"IN",
    "wof:name":"Padamund",
    "wof:placetype":"locality"
},
  "geometry": {"coordinates":[74.13065999999998,21.73211],"type":"Point"}
}