{
  "type": "Feature",
  "properties": {
    "gn:admin1_code":"16.0",
    "gn:admin2_code":"497.0",
    "gn:asciiname":"Padamund",
    "gn:country_code":"IN",
    "gn:dem":660,
    "gn:feature_class":"P",
    "gn:feature_code":"PPL",
    "gn:name":"P\u0101d\u0101mund",
    "gn:population":0,
    "gn:timezone":"Asia/Kolkata",
    "iso:country":"IN",
    "ks:ks_alt_nam":"P\u0101d\u0101mund",
    "ks:ks_name":"Padamund",
    "ks:ks_pop":463,
    "ks:ks_type":"VILLAGE",
    "name:eng_x_preferred":[
        "Padamund"
    ],
    "name:eng_x_variant":[
        "P\u0101d\u0101mund"
    ],
    "wof:name":"Padamund",
    "wof:placetype":"locality",
    "wof:population":463
},
  "geometry": {"coordinates":[74.13065899999999,21.732106],"type":"Point"}
}