{
  "type": "Feature",
  "properties": {
    "iso:country":"IN",
    "ks:ks_name":"Kamalapuram",
    "ks:ks_pop":2678,
    "ks:ks_type":"VILLAGE",
    "ks:ks_uagg_main":0,
    "name:eng_x_preferred":[
        "Kamalapuram"
    ],
    "wof:name":"Kamalapuram",
    "wof:placetype":"neighbourhood",
    "wof:population":2678
},
  "geometry": {"coordinates":[78.06147,11.768493],"type":"Point"}
}