{
  "type": "Feature",
  "properties": {
    "iso:country":"IN",
    "ks:ks_name":"Risapat",
    "ks:ks_pop":442,
    "ks:ks_type":"HABITATION",
    "name:eng_x_preferred":[
        "Risapat"
    ],
    "wof:name":"Risapat",
    "wof:placetype":"locality",
    "wof:population":442
},
  "geometry": {"coordinates":[84.423525,23.39906],"type":"Point"}
}