{
  "type": "Feature",
  "properties": {
    "iso:country":"IN",
    "ks:ks_name":"Inna Deeh",
    "ks:ks_pop":138,
    "ks:ks_type":"VILLAGE",
    "ks:ks_uagg_main":0,
    "name:eng_x_preferred":[
        "Inna Deeh"
    ],
    "wof:name":"Inna Deeh",
    "wof:placetype":"neighbourhood",
    "wof:population":138
},
  "geometry": {"coordinates":[83.280903,26.58725],"type":"Point"}
}