{
  "type": "Feature",
  "properties": {
    "gn:admin1_code":"10",
    "gn:admin2_code":"80.0",
    "gn:asciiname":"Kheri Gangan",
    "gn:country_code":"IN",
    "gn:dem":219,
    "gn:feature_class":"P",
    "gn:feature_code":"PPL",
    "gn:name":"Kheri Gangan",
    "gn:population":0,
    "gn:timezone":"Asia/Kolkata",
    "iso:country":"IN",
    "wof:name":"Kheri Gangan",
    "wof:placetype":"locality"
},
  "geometry": {"coordinates":[76.03361,29.14216],"type":"Point"}
}