{
  "type": "Feature",
  "properties": {
    "iso:country":"IN",
    "ks:ks_name":"Thaniyakunnu",
    "ks:ks_pop":846,
    "ks:ks_type":"HABITATION",
    "name:eng_x_preferred":[
        "Thaniyakunnu"
    ],
    "wof:name":"Thaniyakunnu",
    "wof:placetype":"locality",
    "wof:population":846
},
  "geometry": {"coordinates":[75.862555,11.527888],"type":"Point"}
}