{
  "type": "Feature",
  "properties": {
    "iso:country":"IN",
    "ks:ks_name":"Ringkingpong Forest",
    "ks:ks_pop":917,
    "ks:ks_type":"HABITATION",
    "name:eng_x_preferred":[
        "Ringkingpong Forest"
    ],
    "wof:name":"Ringkingpong Forest",
    "wof:placetype":"locality",
    "wof:population":917
},
  "geometry": {"coordinates":[88.473044,27.027191],"type":"Point"}
}