{
  "type": "Feature",
  "properties": {
    "iso:country":"IN",
    "ks:ks_name":"Kokan Falia",
    "ks:ks_pop":190,
    "ks:ks_type":"HABITATION",
    "name:eng_x_preferred":[
        "Kokan Falia"
    ],
    "wof:name":"Kokan Falia",
    "wof:placetype":"locality",
    "wof:population":190
},
  "geometry": {"coordinates":[73.224,20.357056],"type":"Point"}
}