{
  "type": "Feature",
  "properties": {
    "gn:admin1_code":"37",
    "gn:admin2_code":"406.0",
    "gn:asciiname":"Salka",
    "gn:country_code":"IN",
    "gn:dem":345,
    "gn:feature_class":"P",
    "gn:feature_code":"PPL",
    "gn:name":"Salk\u0101",
    "gn:population":0,
    "gn:timezone":"Asia/Kolkata",
    "iso:country":"IN",
    "name:cat_x_preferred":[
        "Salka"
    ],
    "name:deu_x_preferred":[
        "Salka"
    ],
    "name:epo_x_preferred":[
        "Salka"
    ],
    "name:eus_x_preferred":[
        "Salka"
    ],
    "name:fra_x_preferred":[
        "Salka"
    ],
    "name:hun_x_preferred":[
        "Ipolyszalka"
    ],
    "name:ita_x_preferred":[
        "Salka"
    ],
    "name:msa_x_preferred":[
        "Salka"
    ],
    "name:nld_x_preferred":[
        "Salka"
    ],
    "name:ron_x_preferred":[
        "Salka"
    ],
    "name:rus_x_preferred":[
        "\u0421\u0430\u043b\u043a\u0430"
    ],
    "name:slk_x_preferred":[
        "Salka"
    ],
    "name:spa_x_preferred":[
        "Salka"
    ],
    "name:srp_x_preferred":[
        "\u0421\u0430\u043b\u043a\u0430"
    ],
    "name:war_x_preferred":[
        "Salka"
    ],
    "wof:name":"Salka",
    "wof:placetype":"locality"
},
  "geometry": {"coordinates":[82.02136999999998,22.36656],"type":"Point"}
}