{
  "type": "Feature",
  "properties": {
    "gn:admin1_code":"12.0",
    "gn:admin2_code":"20.0",
    "gn:asciiname":"Chandial Kot",
    "gn:country_code":"IN",
    "gn:dem":1504,
    "gn:feature_class":"P",
    "gn:feature_code":"PPL",
    "gn:name":"Chand\u012b\u0101l Kot",
    "gn:population":0,
    "gn:timezone":"Asia/Kolkata",
    "iso:country":"IN",
    "wof:name":"Chandial Kot",
    "wof:placetype":"locality"
},
  "geometry": {"coordinates":[74.72385,33.40637],"type":"Point"}
}