{
  "type": "Feature",
  "properties": {
    "iso:country":"IN",
    "ks:ks_name":"Charpali",
    "ks:ks_pop":1077,
    "ks:ks_type":"VILLAGE",
    "name:eng_x_preferred":[
        "Charpali"
    ],
    "wof:name":"Charpali",
    "wof:placetype":"locality",
    "wof:population":1077
},
  "geometry": {"coordinates":[82.777017,20.090463],"type":"Point"}
}