{
  "type": "Feature",
  "properties": {
    "gn:admin1_code":"13.0",
    "gn:admin2_code":"590.0",
    "gn:asciiname":"Ontangadi",
    "gn:country_code":"IN",
    "gn:dem":769,
    "gn:feature_class":"P",
    "gn:feature_code":"PPL",
    "gn:name":"Ontang\u0101di",
    "gn:population":0,
    "gn:timezone":"Asia/Kolkata",
    "iso:country":"IN",
    "wof:name":"Ontangadi",
    "wof:placetype":"locality"
},
  "geometry": {"coordinates":[76.02423,11.82629],"type":"Point"}
}