{
  "type": "Feature",
  "properties": {
    "iso:country":"IN",
    "ks:ks_name":"Balerikeri",
    "ks:ks_pop":430,
    "ks:ks_type":"HABITATION",
    "name:eng_x_preferred":[
        "Balerikeri"
    ],
    "wof:name":"Balerikeri",
    "wof:placetype":"locality",
    "wof:population":430
},
  "geometry": {"coordinates":[74.40934799999999,14.491916],"type":"Point"}
}