{
  "type": "Feature",
  "properties": {
    "gn:admin1_code":"36",
    "gn:admin2_code":"193.0",
    "gn:asciiname":"Pakri Halakh Basant",
    "gn:country_code":"IN",
    "gn:dem":70,
    "gn:feature_class":"P",
    "gn:feature_code":"PPL",
    "gn:name":"Pakr\u012b Hal\u0101kh Bas\u0101nt",
    "gn:population":0,
    "gn:timezone":"Asia/Kolkata",
    "iso:country":"IN",
    "wof:name":"Pakri Halakh Basant",
    "wof:placetype":"neighbourhood"
},
  "geometry": {"coordinates":[83.94512,25.95106],"type":"Point"}
}