{
  "type": "Feature",
  "properties": {
    "iso:country":"IN",
    "ks:ks_name":"Prithviraj Ka Bera",
    "ks:ks_pop":243,
    "ks:ks_type":"HABITATION",
    "name:eng_x_preferred":[
        "Prithviraj Ka Bera"
    ],
    "wof:name":"Prithviraj Ka Bera",
    "wof:placetype":"locality",
    "wof:population":243
},
  "geometry": {"coordinates":[72.64194999999999,28.102892],"type":"Point"}
}