{
  "type": "Feature",
  "properties": {
    "iso:country":"IN",
    "ks:ks_name":"Piyariya Purwa",
    "ks:ks_pop":300,
    "ks:ks_type":"HABITATION",
    "name:eng_x_preferred":[
        "Piyariya Purwa"
    ],
    "wof:name":"Piyariya Purwa",
    "wof:placetype":"locality",
    "wof:population":300
},
  "geometry": {"coordinates":[81.19678500000001,25.303921],"type":"Point"}
}