{
  "type": "Feature",
  "properties": {
    "iso:country":"IN",
    "ks:ks_name":"Berenga Pt I",
    "ks:ks_pop":2372,
    "ks:ks_type":"VILLAGE",
    "ks:ks_uagg_main":0,
    "name:eng_x_preferred":[
        "Berenga Pt I"
    ],
    "wof:name":"Berenga Pt I",
    "wof:placetype":"neighbourhood",
    "wof:population":2372
},
  "geometry": {"coordinates":[92.834551,24.814716],"type":"Point"}
}