{
  "type": "Feature",
  "properties": {
    "iso:country":"IN",
    "ks:ks_name":"Siruvanur",
    "ks:ks_pop":458,
    "ks:ks_type":"HABITATION",
    "name:eng_x_preferred":[
        "Siruvanur"
    ],
    "wof:name":"Siruvanur",
    "wof:placetype":"locality",
    "wof:population":458
},
  "geometry": {"coordinates":[78.274005,9.687597],"type":"Point"}
}