{
  "type": "Feature",
  "properties": {
    "iso:country":"IN",
    "ks:ks_alt_nam":"khamkar wasti",
    "ks:ks_name":"Khamkar Wasti",
    "ks:ks_pop":159,
    "ks:ks_type":"HABITATION",
    "name:eng_x_preferred":[
        "Khamkar Wasti"
    ],
    "wof:name":"Khamkar Wasti",
    "wof:placetype":"locality",
    "wof:population":159
},
  "geometry": {"coordinates":[76.112447,18.524725],"type":"Point"}
}