{
  "type": "Feature",
  "properties": {
    "iso:country":"IN",
    "ks:ks_name":"Adivasipoda",
    "ks:ks_pop":354,
    "ks:ks_type":"HABITATION",
    "name:eng_x_preferred":[
        "Adivasipoda"
    ],
    "wof:name":"Adivasipoda",
    "wof:placetype":"locality",
    "wof:population":354
},
  "geometry": {"coordinates":[82.263953,19.637968],"type":"Point"}
}