{
  "type": "Feature",
  "properties": {
    "iso:country":"IN",
    "ks:ks_alt_nam":"Devarahalli kaval",
    "ks:ks_name":"Devarahalli Kaval",
    "ks:ks_pop":1675,
    "ks:ks_type":"HABITATION",
    "name:eng_x_preferred":[
        "Devarahalli Kaval"
    ],
    "wof:name":"Devarahalli Kaval",
    "wof:placetype":"locality",
    "wof:population":1675
},
  "geometry": {"coordinates":[76.192318,13.455743],"type":"Point"}
}