{
  "type": "Feature",
  "properties": {
    "gn:admin1_code":"38.0",
    "gn:admin2_code":"358.0",
    "gn:asciiname":"Maradag",
    "gn:country_code":"IN",
    "gn:dem":316,
    "gn:feature_class":"P",
    "gn:feature_code":"PPL",
    "gn:name":"M\u0101r\u0101d\u0101g",
    "gn:population":0,
    "gn:timezone":"Asia/Kolkata",
    "iso:country":"IN",
    "ks:ks_alt_nam":"M\u0101r\u0101d\u0101g",
    "ks:ks_name":"Maradag",
    "ks:ks_pop":534,
    "ks:ks_type":"VILLAGE",
    "name:eng_x_preferred":[
        "Maradag"
    ],
    "name:eng_x_variant":[
        "M\u0101r\u0101d\u0101g"
    ],
    "wof:name":"Maradag",
    "wof:placetype":"locality",
    "wof:population":534
},
  "geometry": {"coordinates":[84.36353,24.343534],"type":"Point"}
}