{
  "type": "Feature",
  "properties": {
    "iso:country":"IN",
    "ks:ks_name":"Chitpil",
    "ks:ks_pop":572,
    "ks:ks_type":"VILLAGE",
    "name:eng_x_preferred":[
        "Chitpil"
    ],
    "wof:name":"Chitpil",
    "wof:placetype":"locality",
    "wof:population":572
},
  "geometry": {"coordinates":[85.540477,22.799467],"type":"Point"}
}