{
  "type": "Feature",
  "properties": {
    "iso:country":"IN",
    "ks:ks_name":"Narendrabhog",
    "ks:ks_pop":201,
    "ks:ks_type":"VILLAGE",
    "ks:ks_uagg_main":0,
    "name:eng_x_preferred":[
        "Narendrabhog"
    ],
    "wof:name":"Narendrabhog",
    "wof:placetype":"neighbourhood",
    "wof:population":201
},
  "geometry": {"coordinates":[86.16916999999999,21.028537],"type":"Point"}
}