{
  "type": "Feature",
  "properties": {
    "gn:admin1_code":"34.0",
    "gn:admin2_code":"203.0",
    "gn:asciiname":"Banwa",
    "gn:country_code":"IN",
    "gn:dem":79,
    "gn:feature_class":"P",
    "gn:feature_code":"PPL",
    "gn:name":"Banwa",
    "gn:population":0,
    "gn:timezone":"Asia/Kolkata",
    "iso:country":"IN",
    "wof:name":"Banwa",
    "wof:placetype":"locality"
},
  "geometry": {"coordinates":[84.58459000000001,26.87283],"type":"Point"}
}