{
  "type": "Feature",
  "properties": {
    "iso:country":"IN",
    "ks:ks_alt_nam":"RADHAMADABPUR WEST",
    "ks:ks_name":"Radhamadabpur West",
    "ks:ks_pop":402,
    "ks:ks_type":"HABITATION",
    "ks:ks_uagg_main":0,
    "name:eng_x_preferred":[
        "Radhamadabpur West"
    ],
    "wof:name":"Radhamadabpur West",
    "wof:placetype":"neighbourhood",
    "wof:population":402
},
  "geometry": {"coordinates":[92.303945,24.358454],"type":"Point"}
}