{
  "type": "Feature",
  "properties": {
    "gn:admin1_code":"36",
    "gn:admin2_code":"195.0",
    "gn:asciiname":"Jamsara",
    "gn:country_code":"IN",
    "gn:dem":75,
    "gn:feature_class":"P",
    "gn:feature_code":"PPL",
    "gn:name":"Jamsara",
    "gn:population":0,
    "gn:timezone":"Asia/Kolkata",
    "iso:country":"IN",
    "ks:ks_name":"Jamsara",
    "ks:ks_pop":1540,
    "ks:ks_type":"VILLAGE",
    "ks:ks_uagg_main":0,
    "name:eng_x_preferred":[
        "Jamsara"
    ],
    "wof:name":"Jamsara",
    "wof:placetype":"neighbourhood",
    "wof:population":1540
},
  "geometry": {"coordinates":[83.44132999999999,25.779738],"type":"Point"}
}