{
  "type": "Feature",
  "properties": {
    "iso:country":"IN",
    "ks:ks_name":"Muvadi",
    "ks:ks_pop":960,
    "ks:ks_type":"HABITATION",
    "name:eng_x_preferred":[
        "Muvadi"
    ],
    "wof:name":"Muvadi",
    "wof:placetype":"locality",
    "wof:population":960
},
  "geometry": {"coordinates":[73.853667,22.975556],"type":"Point"}
}