{
  "type": "Feature",
  "properties": {
    "iso:country":"IN",
    "ks:ks_alt_nam":"Sansare Dive wasti",
    "ks:ks_name":"Sansare Dive Wasti",
    "ks:ks_pop":287,
    "ks:ks_type":"HABITATION",
    "name:eng_x_preferred":[
        "Sansare Dive Wasti"
    ],
    "wof:name":"Sansare Dive Wasti",
    "wof:placetype":"locality",
    "wof:population":287
},
  "geometry": {"coordinates":[74.481713,19.466072],"type":"Point"}
}