{
  "type": "Feature",
  "properties": {
    "iso:country":"IN",
    "ks:ks_name":"Karanjkot",
    "ks:ks_pop":270,
    "ks:ks_type":"VILLAGE",
    "name:eng_x_preferred":[
        "Karanjkot"
    ],
    "wof:name":"Karanjkot",
    "wof:placetype":"locality",
    "wof:population":270
},
  "geometry": {"coordinates":[82.93714799999999,20.05092],"type":"Point"}
}