{
  "type": "Feature",
  "properties": {
    "iso:country":"IN",
    "ks:ks_name":"Uttar Suba",
    "ks:ks_pop":502,
    "ks:ks_type":"HABITATION",
    "name:eng_x_preferred":[
        "Uttar Suba"
    ],
    "wof:name":"Uttar Suba",
    "wof:placetype":"locality",
    "wof:population":502
},
  "geometry": {"coordinates":[91.17370200000001,26.066439],"type":"Point"}
}