{
  "type": "Feature",
  "properties": {
    "iso:country":"IN",
    "ks:ks_name":"Shiv Nagar",
    "ks:ks_pop":1278,
    "ks:ks_type":"VILLAGE",
    "name:eng_x_preferred":[
        "Shiv Nagar"
    ],
    "wof:name":"Shiv Nagar",
    "wof:placetype":"locality",
    "wof:population":1278
},
  "geometry": {"coordinates":[74.58728600000001,25.886381],"type":"Point"}
}