{
  "type": "Feature",
  "properties": {
    "gn:admin1_code":"19.0",
    "gn:admin2_code":"560.0",
    "gn:asciiname":"Tumarikop",
    "gn:country_code":"IN",
    "gn:dem":656,
    "gn:feature_class":"P",
    "gn:feature_code":"PPL",
    "gn:name":"Tumarikop",
    "gn:population":0,
    "gn:timezone":"Asia/Kolkata",
    "iso:country":"IN",
    "wof:name":"Tumarikop",
    "wof:placetype":"neighbourhood"
},
  "geometry": {"coordinates":[75.96146,15.82852],"type":"Point"}
}