{
  "type": "Feature",
  "properties": {
    "iso:country":"IN",
    "ks:ks_name":"Tilak Tanda Ahirana I",
    "ks:ks_pop":100,
    "ks:ks_type":"HABITATION",
    "name:eng_x_preferred":[
        "Tilak Tanda Ahirana I"
    ],
    "wof:name":"Tilak Tanda Ahirana I",
    "wof:placetype":"locality",
    "wof:population":100
},
  "geometry": {"coordinates":[82.957605,26.412157],"type":"Point"}
}