{
  "type": "Feature",
  "properties": {
    "iso:country":"IN",
    "ks:ks_name":"Liohakaichi",
    "ks:ks_pop":0,
    "ks:ks_type":"VILLAGE",
    "name:eng_x_preferred":[
        "Liohakaichi"
    ],
    "wof:name":"Liohakaichi",
    "wof:placetype":"locality",
    "wof:population":0
},
  "geometry": {"coordinates":[88.308758,26.672225],"type":"Point"}
}