{
  "type": "Feature",
  "properties": {
    "iso:country":"IN",
    "ks:ks_name":"Makkalpatti",
    "ks:ks_pop":224,
    "ks:ks_type":"HABITATION",
    "ks:ks_uagg_main":0,
    "name:eng_x_preferred":[
        "Makkalpatti"
    ],
    "wof:name":"Makkalpatti",
    "wof:placetype":"neighbourhood",
    "wof:population":224
},
  "geometry": {"coordinates":[77.89718499999999,11.898235],"type":"Point"}
}