{
  "type": "Feature",
  "properties": {
    "iso:country":"IN",
    "ks:ks_alt_nam":"Nuri chak",
    "ks:ks_name":"Nuri Chak",
    "ks:ks_pop":627,
    "ks:ks_type":"HABITATION",
    "name:eng_x_preferred":[
        "Nuri Chak"
    ],
    "wof:name":"Nuri Chak",
    "wof:placetype":"locality",
    "wof:population":627
},
  "geometry": {"coordinates":[85.135896,25.460626],"type":"Point"}
}