{
  "type": "Feature",
  "properties": {
    "iso:country":"IN",
    "ks:ks_name":"Parsauni Purwa",
    "ks:ks_pop":154,
    "ks:ks_type":"HABITATION",
    "name:eng_x_preferred":[
        "Parsauni Purwa"
    ],
    "wof:name":"Parsauni Purwa",
    "wof:placetype":"locality",
    "wof:population":154
},
  "geometry": {"coordinates":[81.85011299999999,27.198362],"type":"Point"}
}