{
  "type": "Feature",
  "properties": {
    "gn:admin1_code":"25.0",
    "gn:admin2_code":"621.0",
    "gn:asciiname":"Irungulanvidudi",
    "gn:country_code":"IN",
    "gn:dem":45,
    "gn:feature_class":"P",
    "gn:feature_code":"PPL",
    "gn:name":"Irungulanvidudi",
    "gn:population":0,
    "gn:timezone":"Asia/Kolkata",
    "iso:country":"IN",
    "name:und_x_variant":[
        "Tirupp\u0101kkovil"
    ],
    "wof:name":"Irungulanvidudi",
    "wof:placetype":"locality"
},
  "geometry": {"coordinates":[79.16381,10.54111],"type":"Point"}
}