{
  "type": "Feature",
  "properties": {
    "gn:admin1_code":"25.0",
    "gn:admin2_code":"632.0",
    "gn:asciiname":"Kadamparai",
    "gn:country_code":"IN",
    "gn:dem":1118,
    "gn:feature_class":"P",
    "gn:feature_code":"PPL",
    "gn:name":"K\u0101damp\u0101rai",
    "gn:population":0,
    "gn:timezone":"Asia/Kolkata",
    "iso:country":"IN",
    "wof:name":"Kadamparai",
    "wof:placetype":"locality"
},
  "geometry": {"coordinates":[77.04550999999999,10.39275],"type":"Point"}
}