{
  "type": "Feature",
  "properties": {
    "iso:country":"IN",
    "ks:ks_name":"Badajharan",
    "ks:ks_pop":168,
    "ks:ks_type":"VILLAGE",
    "name:eng_x_preferred":[
        "Badajharan"
    ],
    "wof:name":"Badajharan",
    "wof:placetype":"locality",
    "wof:population":168
},
  "geometry": {"coordinates":[85.066518,20.913433],"type":"Point"}
}