{
  "type": "Feature",
  "properties": {
    "iso:country":"IN",
    "ks:ks_name":"Motiyoniyon Ka Tala",
    "ks:ks_pop":991,
    "ks:ks_type":"HABITATION",
    "name:eng_x_preferred":[
        "Motiyoniyon Ka Tala"
    ],
    "wof:name":"Motiyoniyon Ka Tala",
    "wof:placetype":"locality",
    "wof:population":991
},
  "geometry": {"coordinates":[71.658517,25.622872],"type":"Point"}
}