{
  "type": "Feature",
  "properties": {
    "gn:admin1_code":"11.0",
    "gn:admin2_code":"32.0",
    "gn:asciiname":"Mandi Ke Pas",
    "gn:country_code":"IN",
    "gn:dem":1733,
    "gn:feature_class":"P",
    "gn:feature_code":"PPL",
    "gn:name":"M\u0101ndi Ke P\u0101s",
    "gn:population":0,
    "gn:timezone":"Asia/Kolkata",
    "iso:country":"IN",
    "wof:name":"Mandi Ke Pas",
    "wof:placetype":"locality"
},
  "geometry": {"coordinates":[77.56926,30.67538],"type":"Point"}
}