{
  "type": "Feature",
  "properties": {
    "iso:country":"IN",
    "ks:ks_alt_nam":"Kumarappanal east",
    "ks:ks_name":"Kumarappanal East",
    "ks:ks_pop":680,
    "ks:ks_type":"HABITATION",
    "ks:ks_uagg_main":0,
    "name:eng_x_preferred":[
        "Kumarappanal East"
    ],
    "wof:name":"Kumarappanal East",
    "wof:placetype":"neighbourhood",
    "wof:population":680
},
  "geometry": {"coordinates":[76.233186,10.714488],"type":"Point"}
}