{
  "type": "Feature",
  "properties": {
    "iso:country":"IN",
    "ks:ks_alt_nam":"BRAHAMANBASTI",
    "ks:ks_name":"Brahamanbasti",
    "ks:ks_pop":345,
    "ks:ks_type":"HABITATION",
    "ks:ks_uagg_main":0,
    "name:eng_x_preferred":[
        "Brahamanbasti"
    ],
    "wof:name":"Brahamanbasti",
    "wof:placetype":"neighbourhood",
    "wof:population":345
},
  "geometry": {"coordinates":[83.063874,25.371777],"type":"Point"}
}