{
  "type": "Feature",
  "properties": {
    "iso:country":"IN",
    "ks:ks_name":"Gayalkund",
    "ks:ks_pop":499,
    "ks:ks_type":"VILLAGE",
    "name:eng_x_preferred":[
        "Gayalkund"
    ],
    "wof:name":"Gayalkund",
    "wof:placetype":"locality",
    "wof:population":499
},
  "geometry": {"coordinates":[86.01389399999999,21.648351],"type":"Point"}
}