{
  "type": "Feature",
  "properties": {
    "gn:admin1_code":"11",
    "gn:admin2_code":"31.0",
    "gn:asciiname":"Kohla",
    "gn:country_code":"IN",
    "gn:dem":1054,
    "gn:feature_class":"P",
    "gn:feature_code":"PPL",
    "gn:name":"Kohla",
    "gn:population":0,
    "gn:timezone":"Asia/Kolkata",
    "iso:country":"IN",
    "wof:name":"Kohla",
    "wof:placetype":"locality"
},
  "geometry": {"coordinates":[76.73398,31.23773],"type":"Point"}
}