{
  "type": "Feature",
  "properties": {
    "iso:country":"IN",
    "ks:ks_alt_nam":"Markari Tandi urf Karmahia Tandi",
    "ks:ks_name":"Markari Tandi Urf Karmahia Tandi",
    "ks:ks_pop":400,
    "ks:ks_type":"HABITATION",
    "name:eng_x_preferred":[
        "Markari Tandi Urf Karmahia Tandi"
    ],
    "wof:name":"Markari Tandi Urf Karmahia Tandi",
    "wof:placetype":"locality",
    "wof:population":400
},
  "geometry": {"coordinates":[83.363722,26.553565],"type":"Point"}
}