{
  "type": "Feature",
  "properties": {
    "iso:country":"IN",
    "ks:ks_name":"Keeta",
    "ks:ks_pop":600,
    "ks:ks_type":"VILLAGE",
    "name:eng_x_preferred":[
        "Keeta"
    ],
    "wof:name":"Keeta",
    "wof:placetype":"locality",
    "wof:population":600
},
  "geometry": {"coordinates":[71.02103,26.713492],"type":"Point"}
}