{
  "type": "Feature",
  "properties": {
    "iso:country":"IN",
    "ks:ks_name":"Kata Khola Suba",
    "ks:ks_pop":348,
    "ks:ks_type":"HABITATION",
    "name:eng_x_preferred":[
        "Kata Khola Suba"
    ],
    "wof:name":"Kata Khola Suba",
    "wof:placetype":"locality",
    "wof:population":348
},
  "geometry": {"coordinates":[90.985547,26.063168],"type":"Point"}
}