{
  "type": "Feature",
  "properties": {
    "gn:admin1_code":"36",
    "gn:admin2_code":"147.0",
    "gn:asciiname":"Wazirpur Jehalpur",
    "gn:country_code":"IN",
    "gn:dem":168,
    "gn:feature_class":"P",
    "gn:feature_code":"PPL",
    "gn:name":"Waz\u012brpur Jehalpur",
    "gn:population":0,
    "gn:timezone":"Asia/Kolkata",
    "iso:country":"IN",
    "wof:name":"Wazirpur Jehalpur",
    "wof:placetype":"locality"
},
  "geometry": {"coordinates":[78.45052,27.14635],"type":"Point"}
}