{
  "type": "Feature",
  "properties": {
    "gn:admin1_code":"21",
    "gn:admin2_code":"394.0",
    "gn:asciiname":"Silda",
    "gn:country_code":"IN",
    "gn:dem":334,
    "gn:feature_class":"P",
    "gn:feature_code":"PPL",
    "gn:name":"Silda",
    "gn:population":0,
    "gn:timezone":"Asia/Kolkata",
    "iso:country":"IN",
    "name:ceb_x_preferred":[
        "Silda"
    ],
    "name:deu_x_preferred":[
        "Silda"
    ],
    "name:nor_x_preferred":[
        "Silda"
    ],
    "wof:name":"Silda",
    "wof:placetype":"locality"
},
  "geometry": {"coordinates":[82.52694,20.84263],"type":"Point"}
}