{
  "type": "Feature",
  "properties": {
    "iso:country":"IN",
    "ks:ks_alt_nam":"Mohar singh ki Thar",
    "ks:ks_name":"Mohar Singh Ki Thar",
    "ks:ks_pop":150,
    "ks:ks_type":"HABITATION",
    "name:eng_x_preferred":[
        "Mohar Singh Ki Thar"
    ],
    "wof:name":"Mohar Singh Ki Thar",
    "wof:placetype":"locality",
    "wof:population":150
},
  "geometry": {"coordinates":[78.142966,26.947777],"type":"Point"}
}