{
  "type": "Feature",
  "properties": {
    "iso:country":"IN",
    "ks:ks_name":"Mijikajan T E 281 321",
    "ks:ks_pop":698,
    "ks:ks_type":"HABITATION",
    "ks:ks_uagg_main":0,
    "name:eng_x_preferred":[
        "Mijikajan T E 281 321"
    ],
    "wof:name":"Mijikajan T E 281 321",
    "wof:placetype":"neighbourhood",
    "wof:population":698
},
  "geometry": {"coordinates":[93.190797,26.838278],"type":"Point"}
}