{
  "type": "Feature",
  "properties": {
    "iso:country":"IN",
    "ks:ks_name":"Kumbarapalya",
    "ks:ks_pop":9,
    "ks:ks_type":"HABITATION",
    "name:eng_x_preferred":[
        "Kumbarapalya"
    ],
    "wof:name":"Kumbarapalya",
    "wof:placetype":"locality",
    "wof:population":9
},
  "geometry": {"coordinates":[76.957414,13.489439],"type":"Point"}
}