{
  "type": "Feature",
  "properties": {
    "iso:country":"IN",
    "ks:ks_name":"Nathawaton Ka Khera",
    "ks:ks_pop":23,
    "ks:ks_type":"HABITATION",
    "name:eng_x_preferred":[
        "Nathawaton Ka Khera"
    ],
    "wof:name":"Nathawaton Ka Khera",
    "wof:placetype":"locality",
    "wof:population":23
},
  "geometry": {"coordinates":[74.894289,25.090908],"type":"Point"}
}