{
  "type": "Feature",
  "properties": {
    "gn:admin1_code":"28.0",
    "gn:admin2_code":"337",
    "gn:asciiname":"Digpala",
    "gn:country_code":"IN",
    "gn:dem":13,
    "gn:feature_class":"P",
    "gn:feature_code":"PPL",
    "gn:name":"Digp\u0101la",
    "gn:population":0,
    "gn:timezone":"Asia/Kolkata",
    "iso:country":"IN",
    "wof:name":"Digpala",
    "wof:placetype":"locality"
},
  "geometry": {"coordinates":[88.50825,22.91936],"type":"Point"}
}