{
  "type": "Feature",
  "properties": {
    "iso:country":"IN",
    "ks:ks_name":"Gamtal",
    "ks:ks_pop":1413,
    "ks:ks_type":"HABITATION",
    "name:eng_x_preferred":[
        "Gamtal"
    ],
    "wof:name":"Gamtal",
    "wof:placetype":"locality",
    "wof:population":1413
},
  "geometry": {"coordinates":[73.803639,22.913972],"type":"Point"}
}