{
  "type": "Feature",
  "properties": {
    "iso:country":"IN",
    "ks:ks_alt_nam":"PASIPURWA",
    "ks:ks_name":"Pasipurwa",
    "ks:ks_pop":60,
    "ks:ks_type":"HABITATION",
    "name:eng_x_preferred":[
        "Pasipurwa"
    ],
    "wof:name":"Pasipurwa",
    "wof:placetype":"locality",
    "wof:population":60
},
  "geometry": {"coordinates":[81.594302,27.31944],"type":"Point"}
}