{
  "type": "Feature",
  "properties": {
    "iso:country":"IN",
    "ks:ks_name":"Ramnagar",
    "ks:ks_pop":708,
    "ks:ks_type":"HABITATION",
    "name:eng_x_preferred":[
        "Ramnagar"
    ],
    "name:hin_x_preferred":[
        "\u0930\u093e\u092e\u0928\u0917\u0930"
    ],
    "wof:name":"Ramnagar",
    "wof:placetype":"locality",
    "wof:population":708
},
  "geometry": {"coordinates":[75.826733,16.982215],"type":"Point"}
}