{
  "type": "Feature",
  "properties": {
    "iso:country":"IN",
    "ks:ks_name":"Chak Saidpur Rajauli",
    "ks:ks_pop":437,
    "ks:ks_type":"VILLAGE",
    "name:eng_x_preferred":[
        "Chak Saidpur Rajauli"
    ],
    "wof:name":"Chak Saidpur Rajauli",
    "wof:placetype":"locality",
    "wof:population":437
},
  "geometry": {"coordinates":[85.26161,25.7292],"type":"Point"}
}