{
  "type": "Feature",
  "properties": {
    "iso:country":"IN",
    "ks:ks_name":"Makakan",
    "ks:ks_pop":170,
    "ks:ks_type":"HABITATION",
    "name:eng_x_preferred":[
        "Makakan"
    ],
    "wof:name":"Makakan",
    "wof:placetype":"locality",
    "wof:population":170
},
  "geometry": {"coordinates":[82.86024500000001,19.11863],"type":"Point"}
}