{
  "type": "Feature",
  "properties": {
    "iso:country":"IN",
    "ks:ks_alt_nam":"Path\u0101npur",
    "ks:ks_name":"Pathanpur",
    "ks:ks_type":"VILLAGE",
    "ks:ks_uagg_main":0,
    "name:eng_x_preferred":[
        "Pathanpur"
    ],
    "name:eng_x_variant":[
        "Path\u0101npur"
    ],
    "wof:name":"Pathanpur",
    "wof:placetype":"neighbourhood"
},
  "geometry": {"coordinates":[82.92708,25.917688],"type":"Point"}
}