{
  "type": "Feature",
  "properties": {
    "iso:country":"IN",
    "ks:ks_name":"Bera Chapori Kachari",
    "ks:ks_pop":261,
    "ks:ks_type":"VILLAGE",
    "name:eng_x_preferred":[
        "Bera Chapori Kachari"
    ],
    "wof:name":"Bera Chapori Kachari",
    "wof:placetype":"locality",
    "wof:population":261
},
  "geometry": {"coordinates":[95.260712,27.757346],"type":"Point"}
}