{
  "type": "Feature",
  "properties": {
    "gn:admin1_code":"11.0",
    "gn:admin2_code":"26.0",
    "gn:asciiname":"Koltha",
    "gn:country_code":"IN",
    "gn:dem":2375,
    "gn:feature_class":"P",
    "gn:feature_code":"PPL",
    "gn:name":"Koltha",
    "gn:population":0,
    "gn:timezone":"Asia/Kolkata",
    "iso:country":"IN",
    "wof:name":"Koltha",
    "wof:placetype":"locality"
},
  "geometry": {"coordinates":[77.34135999999999,31.494],"type":"Point"}
}