{
  "type": "Feature",
  "properties": {
    "gn:admin1_code":"38",
    "gn:admin2_code":"347.0",
    "gn:asciiname":"Mahesa",
    "gn:country_code":"IN",
    "gn:dem":423,
    "gn:feature_class":"P",
    "gn:feature_code":"PPL",
    "gn:name":"Mahes\u0101",
    "gn:population":0,
    "gn:timezone":"Asia/Kolkata",
    "iso:country":"IN",
    "wof:name":"Mahesa",
    "wof:placetype":"locality"
},
  "geometry": {"coordinates":[85.28180999999999,24.22203],"type":"Point"}
}