{
  "type": "Feature",
  "properties": {
    "iso:country":"IN",
    "ks:ks_name":"Gumuraput",
    "ks:ks_pop":17,
    "ks:ks_type":"VILLAGE",
    "name:eng_x_preferred":[
        "Gumuraput"
    ],
    "wof:name":"Gumuraput",
    "wof:placetype":"locality",
    "wof:population":17
},
  "geometry": {"coordinates":[83.14937999999999,19.233317],"type":"Point"}
}