{
  "type": "Feature",
  "properties": {
    "iso:country":"IN",
    "ks:ks_name":"Harani Buzurg",
    "ks:ks_pop":1168,
    "ks:ks_type":"VILLAGE",
    "name:eng_x_preferred":[
        "Harani Buzurg"
    ],
    "wof:name":"Harani Buzurg",
    "wof:placetype":"locality",
    "wof:population":1168
},
  "geometry": {"coordinates":[83.044219,27.185182],"type":"Point"}
}