{
  "type": "Feature",
  "properties": {
    "iso:country":"IN",
    "ks:ks_name":"Madhukupuda",
    "ks:ks_pop":430,
    "ks:ks_type":"HABITATION",
    "name:eng_x_preferred":[
        "Madhukupuda"
    ],
    "wof:name":"Madhukupuda",
    "wof:placetype":"locality",
    "wof:population":430
},
  "geometry": {"coordinates":[83.879391,19.408615],"type":"Point"}
}