{
  "type": "Feature",
  "properties": {
    "iso:country":"IN",
    "ks:ks_name":"Sharanda Roaja Para",
    "ks:ks_pop":407,
    "ks:ks_type":"HABITATION",
    "name:eng_x_preferred":[
        "Sharanda Roaja Para"
    ],
    "wof:name":"Sharanda Roaja Para",
    "wof:placetype":"locality",
    "wof:population":407
},
  "geometry": {"coordinates":[91.861418,23.418202],"type":"Point"}
}