{
  "type": "Feature",
  "properties": {
    "iso:country":"IN",
    "ks:ks_name":"Sarasatia",
    "ks:ks_pop":839,
    "ks:ks_type":"VILLAGE",
    "name:eng_x_preferred":[
        "Sarasatia"
    ],
    "wof:name":"Sarasatia",
    "wof:placetype":"locality",
    "wof:population":839
},
  "geometry": {"coordinates":[86.55059,21.134617],"type":"Point"}
}