{
  "type": "Feature",
  "properties": {
    "iso:country":"IN",
    "ks:ks_name":"Dhanaisuli",
    "ks:ks_pop":15,
    "ks:ks_type":"VILLAGE",
    "name:eng_x_preferred":[
        "Dhanaisuli"
    ],
    "wof:name":"Dhanaisuli",
    "wof:placetype":"locality",
    "wof:population":15
},
  "geometry": {"coordinates":[87.115167,23.271793],"type":"Point"}
}