{
  "type": "Feature",
  "properties": {
    "iso:country":"IN",
    "ks:ks_name":"Hardharpur",
    "ks:ks_pop":288,
    "ks:ks_type":"VILLAGE",
    "name:eng_x_preferred":[
        "Hardharpur"
    ],
    "wof:name":"Hardharpur",
    "wof:placetype":"locality",
    "wof:population":288
},
  "geometry": {"coordinates":[83.97313699999999,25.747023],"type":"Point"}
}