{
  "type": "Feature",
  "properties": {
    "iso:country":"IN",
    "ks:ks_name":"Hirehittal",
    "ks:ks_pop":210,
    "ks:ks_type":"HABITATION",
    "name:eng_x_preferred":[
        "Hirehittal"
    ],
    "wof:name":"Hirehittal",
    "wof:placetype":"locality",
    "wof:population":210
},
  "geometry": {"coordinates":[74.507285,14.276414],"type":"Point"}
}