{
  "type": "Feature",
  "properties": {
    "iso:country":"IN",
    "ks:ks_alt_nam":"Kodw\u0101r\u012b",
    "ks:ks_alt_nam_2":"Kodwari",
    "ks:ks_name":"Kodw",
    "ks:ks_type":"VILLAGE",
    "name:eng_x_preferred":[
        "Kodw"
    ],
    "name:eng_x_variant":[
        "Kodw\u0101r\u012b",
        "Kodwari"
    ],
    "wof:name":"Kodw",
    "wof:placetype":"locality"
},
  "geometry": {"coordinates":[84.901999,24.037248],"type":"Point"}
}