{
  "type": "Feature",
  "properties": {
    "gn:admin1_code":"36.0",
    "gn:admin2_code":"189.0",
    "gn:asciiname":"Dumar Bhar",
    "gn:country_code":"IN",
    "gn:dem":85,
    "gn:feature_class":"P",
    "gn:feature_code":"PPL",
    "gn:name":"Dumar Bhar",
    "gn:population":0,
    "gn:timezone":"Asia/Kolkata",
    "iso:country":"IN",
    "ks:ks_name":"Dumar Bhar",
    "ks:ks_pop":4036,
    "ks:ks_type":"VILLAGE",
    "ks:ks_uagg_main":0,
    "name:eng_x_preferred":[
        "Dumar Bhar"
    ],
    "wof:name":"Dumar Bhar",
    "wof:placetype":"neighbourhood",
    "wof:population":4036
},
  "geometry": {"coordinates":[83.927904,26.849404],"type":"Point"}
}