{
  "type": "Feature",
  "properties": {
    "iso:country":"IN",
    "ks:ks_name":"Ranpur",
    "ks:ks_pop":198,
    "ks:ks_type":"VILLAGE",
    "name:eng_x_preferred":[
        "Ranpur"
    ],
    "wof:name":"Ranpur",
    "wof:placetype":"locality",
    "wof:population":198
},
  "geometry": {"coordinates":[74.608541,23.682315],"type":"Point"}
}