{
  "type": "Feature",
  "properties": {
    "iso:country":"IN",
    "ks:ks_name":"Barkhetri Banekuchi Pub",
    "ks:ks_pop":300,
    "ks:ks_type":"VILLAGE",
    "ks:ks_uagg_main":0,
    "name:eng_x_preferred":[
        "Barkhetri Banekuchi Pub"
    ],
    "wof:name":"Barkhetri Banekuchi Pub",
    "wof:placetype":"neighbourhood",
    "wof:population":300
},
  "geometry": {"coordinates":[91.387019,26.468815],"type":"Point"}
}