{
  "type": "Feature",
  "properties": {
    "iso:country":"IN",
    "ks:ks_name":"Tinghara.",
    "ks:ks_pop":257,
    "ks:ks_type":"HABITATION",
    "name:eng_x_preferred":[
        "Tinghara."
    ],
    "wof:name":"Tinghara.",
    "wof:placetype":"locality",
    "wof:population":257
},
  "geometry": {"coordinates":[86.934015,24.439752],"type":"Point"}
}