{
  "type": "Feature",
  "properties": {
    "iso:country":"IN",
    "ks:ks_name":"Dhanberwa",
    "ks:ks_pop":899,
    "ks:ks_type":"HABITATION",
    "name:eng_x_preferred":[
        "Dhanberwa"
    ],
    "wof:name":"Dhanberwa",
    "wof:placetype":"locality",
    "wof:population":899
},
  "geometry": {"coordinates":[85.52494799999999,23.692662],"type":"Point"}
}