{
  "type": "Feature",
  "properties": {
    "iso:country":"IN",
    "ks:ks_name":"Sumeda Kalan",
    "ks:ks_pop":540,
    "ks:ks_type":"VILLAGE",
    "name:eng_x_preferred":[
        "Sumeda Kalan"
    ],
    "wof:name":"Sumeda Kalan",
    "wof:placetype":"locality",
    "wof:population":540
},
  "geometry": {"coordinates":[81.798265,24.766303],"type":"Point"}
}