{
  "type": "Feature",
  "properties": {
    "iso:country":"IN",
    "ks:ks_name":"Sadupara",
    "ks:ks_pop":250,
    "ks:ks_type":"HABITATION",
    "name:eng_x_preferred":[
        "Sadupara"
    ],
    "wof:name":"Sadupara",
    "wof:placetype":"locality",
    "wof:population":250
},
  "geometry": {"coordinates":[90.862081,26.635141],"type":"Point"}
}