{
  "type": "Feature",
  "properties": {
    "gn:admin1_code":"2.0",
    "gn:admin2_code":"543.0",
    "gn:asciiname":"Vepada",
    "gn:country_code":"IN",
    "gn:dem":77,
    "gn:feature_class":"P",
    "gn:feature_code":"PPL",
    "gn:name":"Vep\u0101da",
    "gn:population":0,
    "gn:timezone":"Asia/Kolkata",
    "iso:country":"IN",
    "name:fas_x_preferred":[
        "\u0648\u067e\u062f\u0627"
    ],
    "name:new_x_preferred":[
        "\u0935\u0947\u092a\u093e\u0921 \u092e\u0923\u094d\u0921\u0932"
    ],
    "name:tam_x_preferred":[
        "\u0bb5\u0bc7\u0baa\u0bbe\u0b9f\u0bbe"
    ],
    "name:tel_x_preferred":[
        "\u0c35\u0c47\u0c2a\u0c3e\u0c21"
    ],
    "name:urd_x_preferred":[
        "\u0648\u06cc\u067e\u0627\u0688\u0627"
    ],
    "wof:name":"Vepada",
    "wof:placetype":"locality"
},
  "geometry": {"coordinates":[83.08535999999999,18.00845],"type":"Point"}
}