{
  "type": "Feature",
  "properties": {
    "iso:country":"IN",
    "ks:ks_name":"Chitrathagelu",
    "ks:ks_pop":92,
    "ks:ks_type":"HABITATION",
    "name:eng_x_preferred":[
        "Chitrathagelu"
    ],
    "wof:name":"Chitrathagelu",
    "wof:placetype":"locality",
    "wof:population":92
},
  "geometry": {"coordinates":[80.134795,13.787255],"type":"Point"}
}