{
  "type": "Feature",
  "properties": {
    "gn:admin1_code":"19.0",
    "gn:admin2_code":"574.0",
    "gn:asciiname":"Ulikala",
    "gn:country_code":"IN",
    "gn:dem":892,
    "gn:feature_class":"P",
    "gn:feature_code":"PPL",
    "gn:name":"Ulik\u0101la",
    "gn:population":0,
    "gn:timezone":"Asia/Kolkata",
    "iso:country":"IN",
    "ks:ks_name":"Ulivala",
    "ks:ks_pop":88,
    "ks:ks_type":"VILLAGE",
    "name:eng_x_preferred":[
        "Ulivala"
    ],
    "name:eng_x_variant":[
        "Ulikala"
    ],
    "wof:name":"Ulivala",
    "wof:placetype":"locality",
    "wof:population":88
},
  "geometry": {"coordinates":[76.037942,12.799776],"type":"Point"}
}