{
  "type": "Feature",
  "properties": {
    "gn:admin1_code":"39.0",
    "gn:admin2_code":"68.0",
    "gn:asciiname":"Iqbalpur Kamelpur",
    "gn:country_code":"IN",
    "gn:dem":269,
    "gn:feature_class":"P",
    "gn:feature_code":"PPL",
    "gn:name":"Iqb\u0101lpur Kamelpur",
    "gn:population":0,
    "gn:timezone":"Asia/Kolkata",
    "iso:country":"IN",
    "wof:name":"Iqbalpur Kamelpur",
    "wof:placetype":"locality"
},
  "geometry": {"coordinates":[77.83126,29.87382],"type":"Point"}
}