{
  "type": "Feature",
  "properties": {
    "iso:country":"IN",
    "ks:ks_name":"Jainu Pete",
    "ks:ks_pop":363,
    "ks:ks_type":"HABITATION",
    "name:eng_x_preferred":[
        "Jainu Pete"
    ],
    "wof:name":"Jainu Pete",
    "wof:placetype":"locality",
    "wof:population":363
},
  "geometry": {"coordinates":[75.259811,12.985811],"type":"Point"}
}