{
  "type": "Feature",
  "properties": {
    "gn:admin1_code":"36",
    "gn:admin2_code":"166.0",
    "gn:asciiname":"Birgawan",
    "gn:country_code":"IN",
    "gn:dem":208,
    "gn:feature_class":"P",
    "gn:feature_code":"PPL",
    "gn:name":"Birgaw\u0101n",
    "gn:population":0,
    "gn:timezone":"Asia/Kolkata",
    "iso:country":"IN",
    "ks:ks_name":"Birguan",
    "ks:ks_pop":1094,
    "ks:ks_type":"VILLAGE",
    "name:eng_x_preferred":[
        "Birguan"
    ],
    "name:eng_x_variant":[
        "Birgawan"
    ],
    "wof:name":"Birguan",
    "wof:placetype":"locality",
    "wof:population":1094
},
  "geometry": {"coordinates":[79.291194,25.166659],"type":"Point"}
}