{
  "type": "Feature",
  "properties": {
    "gn:admin1_code":"13.0",
    "gn:admin2_code":"593.0",
    "gn:asciiname":"Parappantorai",
    "gn:country_code":"IN",
    "gn:dem":526,
    "gn:feature_class":"P",
    "gn:feature_code":"PPL",
    "gn:name":"Parappantorai",
    "gn:population":0,
    "gn:timezone":"Asia/Kolkata",
    "iso:country":"IN",
    "wof:name":"Parappantorai",
    "wof:placetype":"locality"
},
  "geometry": {"coordinates":[76.61563000000002,11.12135],"type":"Point"}
}