{
  "type": "Feature",
  "properties": {
    "gn:admin1_code":"34.0",
    "gn:admin2_code":"235.0",
    "gn:asciiname":"Teka Bigha",
    "gn:country_code":"IN",
    "gn:dem":124,
    "gn:feature_class":"P",
    "gn:feature_code":"PPL",
    "gn:name":"Teka Bigha",
    "gn:population":0,
    "gn:timezone":"Asia/Kolkata",
    "iso:country":"IN",
    "ks:ks_name":"Teka Bigha",
    "ks:ks_pop":344,
    "ks:ks_type":"VILLAGE",
    "name:eng_x_preferred":[
        "Teka Bigha"
    ],
    "wof:name":"Teka Bigha",
    "wof:placetype":"locality",
    "wof:population":344
},
  "geometry": {"coordinates":[84.694794,24.687779],"type":"Point"}
}