{
  "type": "Feature",
  "properties": {
    "iso:country":"IN",
    "ks:ks_alt_nam":"S.G.Puram",
    "ks:ks_name":"S.g.puram",
    "ks:ks_pop":406,
    "ks:ks_type":"HABITATION",
    "name:eng_x_preferred":[
        "S.g.puram"
    ],
    "wof:name":"S.g.puram",
    "wof:placetype":"locality",
    "wof:population":406
},
  "geometry": {"coordinates":[84.404415,18.736451],"type":"Point"}
}