{
  "type": "Feature",
  "properties": {
    "gn:admin1_code":"19.0",
    "gn:admin2_code":"571.0",
    "gn:asciiname":"Somedevarpalya",
    "gn:country_code":"IN",
    "gn:dem":781,
    "gn:feature_class":"P",
    "gn:feature_code":"PPL",
    "gn:name":"Somedevarp\u0101lya",
    "gn:population":0,
    "gn:timezone":"Asia/Kolkata",
    "iso:country":"IN",
    "wof:name":"Somedevarpalya",
    "wof:placetype":"locality"
},
  "geometry": {"coordinates":[77.07285,13.0099],"type":"Point"}
}