{
  "type": "Feature",
  "properties": {
    "iso:country":"IN",
    "ks:ks_name":"Az Rakbe Lakhanpur",
    "ks:ks_pop":576,
    "ks:ks_type":"VILLAGE",
    "name:eng_x_preferred":[
        "Az Rakbe Lakhanpur"
    ],
    "wof:name":"Az Rakbe Lakhanpur",
    "wof:placetype":"locality",
    "wof:population":576
},
  "geometry": {"coordinates":[85.691345,26.276509],"type":"Point"}
}