{
  "type": "Feature",
  "properties": {
    "iso:country":"IN",
    "ks:ks_name":"Somdar No 2",
    "ks:ks_pop":311,
    "ks:ks_type":"HABITATION",
    "name:eng_x_preferred":[
        "Somdar No 2"
    ],
    "wof:name":"Somdar No 2",
    "wof:placetype":"locality",
    "wof:population":311
},
  "geometry": {"coordinates":[95.32119,27.162713],"type":"Point"}
}