{
  "type": "Feature",
  "properties": {
    "iso:country":"IN",
    "ks:ks_name":"Braha",
    "ks:ks_pop":66,
    "ks:ks_type":"HABITATION",
    "ks:ks_uagg_main":0,
    "name:eng_x_preferred":[
        "Braha"
    ],
    "wof:name":"Braha",
    "wof:placetype":"neighbourhood",
    "wof:population":66
},
  "geometry": {"coordinates":[82.89912200000001,25.707469],"type":"Point"}
}