{
  "type": "Feature",
  "properties": {
    "gn:admin1_code":"36.0",
    "gn:admin2_code":"179.0",
    "gn:asciiname":"Katra",
    "gn:country_code":"IN",
    "gn:dem":98,
    "gn:feature_class":"P",
    "gn:feature_code":"PPL",
    "gn:name":"Katra",
    "gn:population":0,
    "gn:timezone":"Asia/Kolkata",
    "iso:country":"IN",
    "name:bpy_x_preferred":[
        "\u0995\u09be\u09a4\u09cd\u09b0\u09be"
    ],
    "name:ceb_x_preferred":[
        "Katra"
    ],
    "name:deu_x_preferred":[
        "Katra"
    ],
    "name:heb_x_preferred":[
        "\u05e7\u05d8\u05e8\u05d4"
    ],
    "name:new_x_preferred":[
        "\u0915\u0924\u094d\u0930\u093e"
    ],
    "name:nld_x_preferred":[
        "Katra"
    ],
    "name:pol_x_preferred":[
        "Katra"
    ],
    "name:rus_x_preferred":[
        "\u041a\u0430\u0442\u0440\u0430"
    ],
    "name:sco_x_preferred":[
        "Katra"
    ],
    "name:swe_x_preferred":[
        "Katra"
    ],
    "name:vie_x_preferred":[
        "Katra"
    ],
    "wof:name":"Katra",
    "wof:placetype":"locality"
},
  "geometry": {"coordinates":[81.82359,26.42388],"type":"Point"}
}