{
  "type": "Feature",
  "properties": {
    "iso:country":"IN",
    "ks:ks_name":"Jhinkipita",
    "ks:ks_pop":948,
    "ks:ks_type":"VILLAGE",
    "name:eng_x_preferred":[
        "Jhinkipita"
    ],
    "wof:name":"Jhinkipita",
    "wof:placetype":"locality",
    "wof:population":948
},
  "geometry": {"coordinates":[86.02710500000001,21.250879],"type":"Point"}
}