{
  "type": "Feature",
  "properties": {
    "gn:admin1_code":"16",
    "gn:admin2_code":"524.0",
    "gn:asciiname":"Pandharwadi",
    "gn:country_code":"IN",
    "gn:dem":600,
    "gn:feature_class":"P",
    "gn:feature_code":"PPL",
    "gn:name":"P\u0101ndharw\u0101di",
    "gn:population":0,
    "gn:timezone":"Asia/Kolkata",
    "iso:country":"IN",
    "wof:name":"Pandharwadi",
    "wof:placetype":"locality"
},
  "geometry": {"coordinates":[76.87586999999998,18.34342],"type":"Point"}
}