{
  "type": "Feature",
  "properties": {
    "gn:admin1_code":"12.0",
    "gn:admin2_code":"16.0",
    "gn:asciiname":"Kapra",
    "gn:country_code":"IN",
    "gn:dem":1691,
    "gn:feature_class":"P",
    "gn:feature_code":"PPL",
    "gn:name":"Kapra",
    "gn:population":0,
    "gn:timezone":"Asia/Kolkata",
    "iso:country":"IN",
    "name:ara_x_preferred":[
        "\u0643\u0627\u0628\u0631\u0627"
    ],
    "name:ben_bn_x_preferred":[
        "\u0995\u09be\u09aa\u09cd\u09b0\u09be"
    ],
    "name:ben_in_x_preferred":[
        "\u0995\u09be\u09aa\u09b0\u09be"
    ],
    "name:bpy_x_preferred":[
        "\u0995\u09be\u09aa\u09b0\u09be"
    ],
    "name:ceb_x_preferred":[
        "K\u0101pra"
    ],
    "name:fas_x_preferred":[
        "\u06a9\u0627\u067e\u0631\u0627"
    ],
    "name:fra_x_preferred":[
        "Kapra"
    ],
    "name:guj_x_preferred":[
        "\u0a95\u0aaa\u0ab0\u0abe"
    ],
    "name:hin_x_preferred":[
        "\u0915\u092a\u0930\u093e"
    ],
    "name:hin_x_variant":[
        "\u0915\u093e\u092a\u0930\u093e"
    ],
    "name:ita_x_preferred":[
        "Kapra"
    ],
    "name:kan_x_preferred":[
        "\u0c95\u0caa\u0ccd\u0cb0\u0cbe"
    ],
    "name:mal_x_preferred":[
        "\u0d15\u0d2a\u0d4d\u0d30"
    ],
    "name:mar_x_preferred":[
        "\u0915\u093e\u092a\u094d\u0930\u093e"
    ],
    "name:mlg_x_preferred":[
        "Kapra"
    ],
    "name:msa_x_preferred":[
        "Kapra"
    ],
    "name:new_x_preferred":[
        "\u0915\u092a\u094d\u0930\u093e"
    ],
    "name:pan_x_preferred":[
        "\u0a15\u0a3e\u0a2a\u0a30\u0a3e"
    ],
    "name:pnb_x_preferred":[
        "\u06a9\u067e\u0631\u0627"
    ],
    "name:por_x_preferred":[
        "Kapra"
    ],
    "name:swe_x_preferred":[
        "K\u0101pra"
    ],
    "name:tam_x_preferred":[
        "\u0b95\u0bbe\u0baa\u0bcd\u0bb0\u0bbe"
    ],
    "name:tel_x_preferred":[
        "\u0c15\u0c3e\u0c2a\u0c4d\u0c30\u0c3e"
    ],
    "name:urd_x_preferred":[
        "\u06a9\u0627\u067e\u0631\u0627"
    ],
    "name:urd_x_variant":[
        "\u06a9\u067e\u0631\u0627"
    ],
    "name:vie_x_preferred":[
        "Kapra"
    ],
    "name:zho_x_preferred":[
        "\u5361\u666e\u62c9"
    ],
    "wof:name":"Kapra",
    "wof:placetype":"locality"
},
  "geometry": {"coordinates":[75.69884999999999,33.01772],"type":"Point"}
}