{
  "type": "Feature",
  "properties": {
    "iso:country":"IN",
    "ks:ks_name":"Jurripara",
    "ks:ks_pop":122,
    "ks:ks_type":"HABITATION",
    "name:eng_x_preferred":[
        "Jurripara"
    ],
    "wof:name":"Jurripara",
    "wof:placetype":"locality",
    "wof:population":122
},
  "geometry": {"coordinates":[81.37829000000001,19.073773],"type":"Point"}
}