{
  "type": "Feature",
  "properties": {
    "iso:country":"IN",
    "ks:ks_name":"Pazhumoodu",
    "ks:ks_pop":590,
    "ks:ks_type":"HABITATION",
    "name:eng_x_preferred":[
        "Pazhumoodu"
    ],
    "wof:name":"Pazhumoodu",
    "wof:placetype":"locality",
    "wof:population":590
},
  "geometry": {"coordinates":[76.928895,8.720584],"type":"Point"}
}