{
  "type": "Feature",
  "properties": {
    "gn:admin1_code":"13.0",
    "gn:admin2_code":"591.0",
    "gn:asciiname":"Kunnathra",
    "gn:country_code":"IN",
    "gn:dem":19,
    "gn:feature_class":"P",
    "gn:feature_code":"PPL",
    "gn:name":"Kunnathra",
    "gn:population":0,
    "gn:timezone":"Asia/Kolkata",
    "iso:country":"IN",
    "ks:ks_alt_nam":"kunnathara",
    "ks:ks_name":"Kunnathara",
    "ks:ks_pop":950,
    "ks:ks_type":"HABITATION",
    "name:eng_x_preferred":[
        "Kunnathara"
    ],
    "name:eng_x_variant":[
        "Kunnathra"
    ],
    "wof:name":"Kunnathara",
    "wof:placetype":"locality",
    "wof:population":950
},
  "geometry": {"coordinates":[75.779123,11.420621],"type":"Point"}
}