{
  "type": "Feature",
  "properties": {
    "iso:country":"IN",
    "ks:ks_alt_nam":"Rekya tanda",
    "ks:ks_name":"Rekya Tanda",
    "ks:ks_pop":50,
    "ks:ks_type":"HABITATION",
    "name:eng_x_preferred":[
        "Rekya Tanda"
    ],
    "wof:name":"Rekya Tanda",
    "wof:placetype":"locality",
    "wof:population":50
},
  "geometry": {"coordinates":[77.988302,16.473605],"type":"Point"}
}