{
  "type": "Feature",
  "properties": {
    "gn:admin1_code":"25.0",
    "gn:admin2_code":"632.0",
    "gn:asciiname":"Ayyampalaiyam",
    "gn:country_code":"IN",
    "gn:dem":256,
    "gn:feature_class":"P",
    "gn:feature_code":"PPL",
    "gn:name":"Ayyamp\u0101laiyam",
    "gn:population":0,
    "gn:timezone":"Asia/Kolkata",
    "iso:country":"IN",
    "wof:name":"Ayyampalaiyam",
    "wof:placetype":"locality"
},
  "geometry": {"coordinates":[76.95317,10.67409],"type":"Point"}
}