{
  "type": "Feature",
  "properties": {
    "iso:country":"IN",
    "ks:ks_name":"Baori",
    "ks:ks_pop":3944,
    "ks:ks_type":"HABITATION",
    "name:eng_x_preferred":[
        "Baori"
    ],
    "wof:name":"Baori",
    "wof:placetype":"locality",
    "wof:population":3944
},
  "geometry": {"coordinates":[73.908987,23.392596],"type":"Point"}
}