{
  "type": "Feature",
  "properties": {
    "gn:admin1_code":"36",
    "gn:admin2_code":"147.0",
    "gn:asciiname":"Nagla Nai",
    "gn:country_code":"IN",
    "gn:dem":163,
    "gn:feature_class":"P",
    "gn:feature_code":"PPL",
    "gn:name":"Nagla N\u0101i",
    "gn:population":0,
    "gn:timezone":"Asia/Kolkata",
    "iso:country":"IN",
    "wof:name":"Nagla Nai",
    "wof:placetype":"locality"
},
  "geometry": {"coordinates":[78.51181,27.30232],"type":"Point"}
}