{
  "type": "Feature",
  "properties": {
    "iso:country":"IN",
    "ks:ks_name":"Kareeriya",
    "ks:ks_pop":429,
    "ks:ks_type":"VILLAGE",
    "name:eng_x_preferred":[
        "Kareeriya"
    ],
    "wof:name":"Kareeriya",
    "wof:placetype":"locality",
    "wof:population":429
},
  "geometry": {"coordinates":[75.96082800000001,26.147286],"type":"Point"}
}