{
  "type": "Feature",
  "properties": {
    "iso:country":"IN",
    "ks:ks_name":"Bagdiya",
    "ks:ks_pop":36,
    "ks:ks_type":"HABITATION",
    "name:eng_x_preferred":[
        "Bagdiya"
    ],
    "wof:name":"Bagdiya",
    "wof:placetype":"locality",
    "wof:population":36
},
  "geometry": {"coordinates":[77.390326,25.530902],"type":"Point"}
}