{
  "type": "Feature",
  "properties": {
    "iso:country":"IN",
    "ks:ks_name":"Bhati Kuruah Part 2",
    "ks:ks_pop":1066,
    "ks:ks_type":"HABITATION",
    "name:eng_x_preferred":[
        "Bhati Kuruah Part 2"
    ],
    "wof:name":"Bhati Kuruah Part 2",
    "wof:placetype":"locality",
    "wof:population":1066
},
  "geometry": {"coordinates":[91.83465099999999,26.250067],"type":"Point"}
}