{
  "type": "Feature",
  "properties": {
    "iso:country":"IN",
    "ks:ks_name":"Parsotampur",
    "ks:ks_type":"VILLAGE",
    "name:eng_x_preferred":[
        "Parsotampur"
    ],
    "wof:name":"Parsotampur",
    "wof:placetype":"locality"
},
  "geometry": {"coordinates":[83.166811,25.088507],"type":"Point"}
}