{
  "type": "Feature",
  "properties": {
    "gn:admin1_code":"11.0",
    "gn:admin2_code":"27.0",
    "gn:asciiname":"Bhakloti",
    "gn:country_code":"IN",
    "gn:dem":1911,
    "gn:feature_class":"P",
    "gn:feature_code":"PPL",
    "gn:name":"Bhakloti",
    "gn:population":0,
    "gn:timezone":"Asia/Kolkata",
    "iso:country":"IN",
    "wof:name":"Bhakloti",
    "wof:placetype":"locality"
},
  "geometry": {"coordinates":[77.24854000000001,31.40425],"type":"Point"}
}