{
  "type": "Feature",
  "properties": {
    "iso:country":"IN",
    "ks:ks_name":"Tbasavanapur",
    "ks:ks_pop":87,
    "ks:ks_type":"HABITATION",
    "name:eng_x_preferred":[
        "Tbasavanapur"
    ],
    "wof:name":"Tbasavanapur",
    "wof:placetype":"locality",
    "wof:population":87
},
  "geometry": {"coordinates":[77.88823600000001,12.365688],"type":"Point"}
}