{
  "type": "Feature",
  "properties": {
    "iso:country":"IN",
    "ks:ks_alt_nam":"KURIYAM KHURD",
    "ks:ks_name":"Kuriyam Khurd",
    "ks:ks_pop":758,
    "ks:ks_type":"HABITATION",
    "name:eng_x_preferred":[
        "Kuriyam Khurd"
    ],
    "wof:name":"Kuriyam Khurd",
    "wof:placetype":"locality",
    "wof:population":758
},
  "geometry": {"coordinates":[84.662577,23.800918],"type":"Point"}
}