{
  "type": "Feature",
  "properties": {
    "gn:admin1_code":"9.0",
    "gn:admin2_code":"469.0",
    "gn:asciiname":"Vasai",
    "gn:country_code":"IN",
    "gn:dem":215,
    "gn:feature_class":"P",
    "gn:feature_code":"PPL",
    "gn:name":"Vasai",
    "gn:population":0,
    "gn:timezone":"Asia/Kolkata",
    "iso:country":"IN",
    "name:ara_x_preferred":[
        "\u0641\u0627\u0633\u0627\u064a"
    ],
    "name:ben_bn_x_preferred":[
        "\u09ac\u09be\u09b8\u09be\u0987"
    ],
    "name:ben_in_x_preferred":[
        "\u09ad\u09be\u09b8\u09be\u0987"
    ],
    "name:ben_x_preferred":[
        "\u0993\u09af\u09bc\u09be\u09b8\u09be\u0987"
    ],
    "name:bpy_x_preferred":[
        "\u09f1\u09be\u09b8\u09be\u0987"
    ],
    "name:cat_x_preferred":[
        "Vasai-Virar"
    ],
    "name:fas_x_preferred":[
        "\u0648\u0633\u0627\u0626\u06cc"
    ],
    "name:guj_x_preferred":[
        "\u0ab5\u0ab8\u0a88"
    ],
    "name:hin_x_preferred":[
        "\u0935\u0938\u093e\u0908"
    ],
    "name:ind_x_preferred":[
        "Vasai"
    ],
    "name:ita_x_preferred":[
        "Vasai"
    ],
    "name:jpn_x_preferred":[
        "\u30f4\u30a1\u30b5\u30a4\u30fc"
    ],
    "name:kan_x_preferred":[
        "\u0cb5\u0cbe\u0cb8\u0cc8"
    ],
    "name:mal_x_preferred":[
        "\u0d35\u0d3e\u0d38\u0d48"
    ],
    "name:mar_x_preferred":[
        "\u0935\u0938\u0908"
    ],
    "name:msa_x_preferred":[
        "Vasai"
    ],
    "name:new_x_preferred":[
        "\u0935\u0938\u093e\u0907"
    ],
    "name:nld_x_preferred":[
        "Vasai"
    ],
    "name:nor_x_preferred":[
        "Vasai-Virar"
    ],
    "name:pam_x_preferred":[
        "Vasai"
    ],
    "name:pan_x_preferred":[
        "\u0a35\u0a3e\u0a38\u0a3e\u0a08"
    ],
    "name:por_x_preferred":[
        "Ba\u00e7aim"
    ],
    "name:spa_x_preferred":[
        "Vasai"
    ],
    "name:tam_x_preferred":[
        "\u0bb5\u0b9a\u0baf\u0bcd"
    ],
    "name:tel_x_preferred":[
        "\u0c35\u0c38\u0c3e\u0c2f\u0c4d"
    ],
    "name:urd_x_preferred":[
        "\u0648\u0627\u0633\u06cc"
    ],
    "name:urd_x_variant":[
        "\u0648\u0633\u0626\u06cc"
    ],
    "name:vie_x_preferred":[
        "Vasai"
    ],
    "name:zho_x_preferred":[
        "\u74e6\u8d5b"
    ],
    "wof:name":"Vasai",
    "wof:placetype":"locality"
},
  "geometry": {"coordinates":[72.63175,24.05488],"type":"Point"}
}