{
  "type": "Feature",
  "properties": {
    "iso:country":"IN",
    "ks:ks_name":"Dindla",
    "ks:ks_pop":426,
    "ks:ks_type":"HABITATION",
    "name:eng_x_preferred":[
        "Dindla"
    ],
    "wof:name":"Dindla",
    "wof:placetype":"locality",
    "wof:population":426
},
  "geometry": {"coordinates":[81.590931,16.362808],"type":"Point"}
}