{
  "type": "Feature",
  "properties": {
    "gn:admin1_code":"11.0",
    "gn:admin2_code":"27.0",
    "gn:asciiname":"Ukri",
    "gn:country_code":"IN",
    "gn:dem":1607,
    "gn:feature_class":"P",
    "gn:feature_code":"PPL",
    "gn:name":"Ukri",
    "gn:population":0,
    "gn:timezone":"Asia/Kolkata",
    "iso:country":"IN",
    "wof:name":"Ukri",
    "wof:placetype":"locality"
},
  "geometry": {"coordinates":[77.0609,31.35932],"type":"Point"}
}