{
  "type": "Feature",
  "properties": {
    "gn:admin1_code":"36",
    "gn:admin2_code":"132.0",
    "gn:asciiname":"Ishaqpur Chenchi",
    "gn:country_code":"IN",
    "gn:dem":294,
    "gn:feature_class":"P",
    "gn:feature_code":"PPL",
    "gn:name":"Ish\u0101qpur Chenchi",
    "gn:population":0,
    "gn:timezone":"Asia/Kolkata",
    "iso:country":"IN",
    "wof:name":"Ishaqpur Chenchi",
    "wof:placetype":"locality"
},
  "geometry": {"coordinates":[77.56966,30.17648],"type":"Point"}
}