{
  "type": "Feature",
  "properties": {
    "iso:country":"IN",
    "ks:ks_name":"Borrapara",
    "ks:ks_pop":222,
    "ks:ks_type":"HABITATION",
    "name:eng_x_preferred":[
        "Borrapara"
    ],
    "wof:name":"Borrapara",
    "wof:placetype":"locality",
    "wof:population":222
},
  "geometry": {"coordinates":[81.47608200000001,18.531634],"type":"Point"}
}