{
  "type": "Feature",
  "properties": {
    "iso:country":"IN",
    "ks:ks_name":"Chaparam",
    "ks:ks_pop":639,
    "ks:ks_type":"HABITATION",
    "ks:ks_uagg_main":0,
    "name:eng_x_preferred":[
        "Chaparam"
    ],
    "wof:name":"Chaparam",
    "wof:placetype":"neighbourhood",
    "wof:population":639
},
  "geometry": {"coordinates":[83.913579,18.327132],"type":"Point"}
}