{
  "type": "Feature",
  "properties": {
    "gn:admin1_code":"31.0",
    "gn:admin2_code":"283.0",
    "gn:asciiname":"Vanbawng",
    "gn:country_code":"IN",
    "gn:dem":764,
    "gn:feature_class":"P",
    "gn:feature_code":"PPL",
    "gn:name":"Vanbawng",
    "gn:population":0,
    "gn:timezone":"Asia/Kolkata",
    "iso:country":"IN",
    "wof:name":"Vanbawng",
    "wof:placetype":"locality"
},
  "geometry": {"coordinates":[93.06041999999999,24.04087],"type":"Point"}
}