{
  "type": "Feature",
  "properties": {
    "gn:admin1_code":"35",
    "gn:admin2_code":"443.0",
    "gn:asciiname":"Bhurapani",
    "gn:country_code":"IN",
    "gn:dem":484,
    "gn:feature_class":"P",
    "gn:feature_code":"PPL",
    "gn:name":"Bh\u016br\u0101p\u0101ni",
    "gn:population":0,
    "gn:timezone":"Asia/Kolkata",
    "iso:country":"IN",
    "wof:name":"Bhurapani",
    "wof:placetype":"locality"
},
  "geometry": {"coordinates":[77.3232,24.01102],"type":"Point"}
}