{
  "type": "Feature",
  "properties": {
    "gn:admin1_code":"36",
    "gn:admin2_code":"159.0",
    "gn:asciiname":"Gandua",
    "gn:country_code":"IN",
    "gn:dem":151,
    "gn:feature_class":"P",
    "gn:feature_code":"PPL",
    "gn:name":"Gandua",
    "gn:population":0,
    "gn:timezone":"Asia/Kolkata",
    "iso:country":"IN",
    "ks:ks_name":"Gandua",
    "ks:ks_pop":242,
    "ks:ks_type":"HABITATION",
    "ks:ks_uagg_main":0,
    "name:eng_x_preferred":[
        "Gandua"
    ],
    "wof:name":"Gandua",
    "wof:placetype":"neighbourhood",
    "wof:population":242
},
  "geometry": {"coordinates":[79.37832,27.605433],"type":"Point"}
}