{
  "type": "Feature",
  "properties": {
    "gn:admin1_code":"36.0",
    "gn:admin2_code":"134.0",
    "gn:asciiname":"Biharipur",
    "gn:country_code":"IN",
    "gn:dem":221,
    "gn:feature_class":"P",
    "gn:feature_code":"PPL",
    "gn:name":"Bih\u0101ripur",
    "gn:population":0,
    "gn:timezone":"Asia/Kolkata",
    "iso:country":"IN",
    "ks:ks_alt_nam":"Bih\u0101ripur",
    "ks:ks_name":"Biharipur",
    "ks:ks_type":"VILLAGE",
    "name:eng_x_preferred":[
        "Biharipur"
    ],
    "name:eng_x_variant":[
        "Bih\u0101ripur"
    ],
    "wof:name":"Biharipur",
    "wof:placetype":"locality"
},
  "geometry": {"coordinates":[78.622756,29.299672],"type":"Point"}
}