{
  "type": "Feature",
  "properties": {
    "iso:country":"IN",
    "ks:ks_name":"Hathini Reserved Forest",
    "ks:ks_type":"VILLAGE",
    "name:eng_x_preferred":[
        "Hathini Reserved Forest"
    ],
    "wof:name":"Hathini Reserved Forest",
    "wof:placetype":"locality"
},
  "geometry": {"coordinates":[83.179447,25.027697],"type":"Point"}
}