{
  "type": "Feature",
  "properties": {
    "gn:admin1_code":"39.0",
    "gn:admin2_code":"67.0",
    "gn:asciiname":"Kishanpur",
    "gn:country_code":"IN",
    "gn:dem":207,
    "gn:feature_class":"P",
    "gn:feature_code":"PPL",
    "gn:name":"Kishanpur",
    "gn:population":0,
    "gn:timezone":"Asia/Kolkata",
    "iso:country":"IN",
    "ks:ks_name":"Kishanpur",
    "ks:ks_pop":647,
    "ks:ks_type":"VILLAGE",
    "name:eng_x_preferred":[
        "Kishanpur"
    ],
    "wof:name":"Kishanpur",
    "wof:placetype":"locality",
    "wof:population":647
},
  "geometry": {"coordinates":[79.50555799999999,28.930012],"type":"Point"}
}