{
  "type": "Feature",
  "properties": {
    "gn:admin1_code":"10.0",
    "gn:admin2_code":"072",
    "gn:asciiname":"Bijarpur",
    "gn:country_code":"IN",
    "gn:dem":260,
    "gn:feature_class":"P",
    "gn:feature_code":"PPL",
    "gn:name":"B\u012bjarpur",
    "gn:population":0,
    "gn:timezone":"Asia/Kolkata",
    "iso:country":"IN",
    "ks:ks_alt_nam":"B\u012bjarpur",
    "ks:ks_name":"Bijarpur",
    "ks:ks_type":"VILLAGE",
    "ks:ks_uagg_main":0,
    "name:eng_x_preferred":[
        "Bijarpur"
    ],
    "name:eng_x_variant":[
        "B\u012bjarpur"
    ],
    "wof:name":"Bijarpur",
    "wof:placetype":"neighbourhood"
},
  "geometry": {"coordinates":[76.764032,30.164548],"type":"Point"}
}