{
  "type": "Feature",
  "properties": {
    "gn:admin1_code":"19.0",
    "gn:admin2_code":"577.0",
    "gn:asciiname":"Benakanahalli",
    "gn:country_code":"IN",
    "gn:dem":652,
    "gn:feature_class":"P",
    "gn:feature_code":"PPL",
    "gn:name":"Benakanahalli",
    "gn:population":0,
    "gn:timezone":"Asia/Kolkata",
    "iso:country":"IN",
    "name:vie_x_preferred":[
        "Benakanahalli"
    ],
    "wof:name":"Benakanahalli",
    "wof:placetype":"locality"
},
  "geometry": {"coordinates":[76.92373000000001,12.22757],"type":"Point"}
}