{
  "type": "Feature",
  "properties": {
    "iso:country":"IN",
    "ks:ks_name":"Bordighi",
    "ks:ks_pop":1207,
    "ks:ks_type":"HABITATION",
    "name:eng_x_preferred":[
        "Bordighi"
    ],
    "wof:name":"Bordighi",
    "wof:placetype":"locality",
    "wof:population":1207
},
  "geometry": {"coordinates":[87.762737,23.293568],"type":"Point"}
}