{
  "type": "Feature",
  "properties": {
    "iso:country":"IN",
    "ks:ks_name":"Narasinghtaila",
    "ks:ks_pop":122,
    "ks:ks_type":"VILLAGE",
    "name:eng_x_preferred":[
        "Narasinghtaila"
    ],
    "wof:name":"Narasinghtaila",
    "wof:placetype":"locality",
    "wof:population":122
},
  "geometry": {"coordinates":[84.59047700000001,21.263304],"type":"Point"}
}