{
  "type": "Feature",
  "properties": {
    "iso:country":"IN",
    "ks:ks_name":"Batakuravapalle",
    "ks:ks_pop":4,
    "ks:ks_type":"HABITATION",
    "ks:ks_uagg_main":0,
    "name:eng_x_preferred":[
        "Batakuravapalle"
    ],
    "wof:name":"Batakuravapalle",
    "wof:placetype":"neighbourhood",
    "wof:population":4
},
  "geometry": {"coordinates":[78.87867199999999,13.858934],"type":"Point"}
}