{
  "type": "Feature",
  "properties": {
    "iso:country":"IN",
    "ks:ks_name":"Jaganathpur",
    "ks:ks_pop":70,
    "ks:ks_type":"VILLAGE",
    "ks:ks_uagg_main":0,
    "name:eng_x_preferred":[
        "Jaganathpur"
    ],
    "wof:name":"Jaganathpur",
    "wof:placetype":"neighbourhood",
    "wof:population":70
},
  "geometry": {"coordinates":[84.66127899999999,19.69888],"type":"Point"}
}