{
  "type": "Feature",
  "properties": {
    "iso:country":"IN",
    "ks:ks_alt_nam":"Ch\u0101tuni",
    "ks:ks_name":"Chatuni",
    "ks:ks_type":"VILLAGE",
    "name:eng_x_preferred":[
        "Chatuni"
    ],
    "name:eng_x_variant":[
        "Ch\u0101tuni"
    ],
    "wof:name":"Chatuni",
    "wof:placetype":"locality"
},
  "geometry": {"coordinates":[84.30538900000001,21.070362],"type":"Point"}
}