{
  "type": "Feature",
  "properties": {
    "gn:admin1_code":"2",
    "gn:admin2_code":"544.0",
    "gn:asciiname":"Gunagummi",
    "gn:country_code":"IN",
    "gn:dem":998,
    "gn:feature_class":"P",
    "gn:feature_code":"PPL",
    "gn:name":"Gunagummi",
    "gn:population":0,
    "gn:timezone":"Asia/Kolkata",
    "iso:country":"IN",
    "wof:name":"Gunagummi",
    "wof:placetype":"locality"
},
  "geometry": {"coordinates":[82.80199,18.03903],"type":"Point"}
}