{
  "type": "Feature",
  "properties": {
    "gn:admin1_code":"31",
    "gn:admin2_code":"283.0",
    "gn:asciiname":"Phuaibuang",
    "gn:country_code":"IN",
    "gn:dem":1392,
    "gn:feature_class":"P",
    "gn:feature_code":"PPL",
    "gn:name":"Phuaibuang",
    "gn:population":0,
    "gn:timezone":"Asia/Kolkata",
    "iso:country":"IN",
    "name:und_x_variant":[
        "Phuaibnang",
        "Phuaibuang"
    ],
    "wof:name":"Phuaibuang",
    "wof:placetype":"locality"
},
  "geometry": {"coordinates":[93.12206999999999,23.92642],"type":"Point"}
}