{
  "type": "Feature",
  "properties": {
    "iso:country":"IN",
    "ks:ks_name":"Veerampur",
    "ks:ks_pop":415,
    "ks:ks_type":"HABITATION",
    "name:eng_x_preferred":[
        "Veerampur"
    ],
    "wof:name":"Veerampur",
    "wof:placetype":"locality",
    "wof:population":415
},
  "geometry": {"coordinates":[81.887986,26.219349],"type":"Point"}
}