{
  "type": "Feature",
  "properties": {
    "iso:country":"IN",
    "ks:ks_name":"Kothi Gadhni",
    "ks:ks_pop":125,
    "ks:ks_type":"VILLAGE",
    "name:eng_x_preferred":[
        "Kothi Gadhni"
    ],
    "wof:name":"Kothi Gadhni",
    "wof:placetype":"locality",
    "wof:population":125
},
  "geometry": {"coordinates":[78.66575,30.257272],"type":"Point"}
}