{
  "type": "Feature",
  "properties": {
    "gn:admin1_code":"36.0",
    "gn:admin2_code":"183.0",
    "gn:asciiname":"Ghuchwapur",
    "gn:country_code":"IN",
    "gn:dem":117,
    "gn:feature_class":"P",
    "gn:feature_code":"PPL",
    "gn:name":"Ghuchw\u0101pur",
    "gn:population":0,
    "gn:timezone":"Asia/Kolkata",
    "iso:country":"IN",
    "wof:name":"Ghuchwapur",
    "wof:placetype":"locality"
},
  "geometry": {"coordinates":[81.87470999999999,27.32213],"type":"Point"}
}