{
  "type": "Feature",
  "properties": {
    "gn:admin1_code":"38",
    "gn:admin2_code":"346.0",
    "gn:asciiname":"Halmanta Khurd",
    "gn:country_code":"IN",
    "gn:dem":271,
    "gn:feature_class":"P",
    "gn:feature_code":"PPL",
    "gn:name":"Halm\u0101nta Khurd",
    "gn:population":0,
    "gn:timezone":"Asia/Kolkata",
    "iso:country":"IN",
    "wof:name":"Halmanta Khurd",
    "wof:placetype":"locality"
},
  "geometry": {"coordinates":[83.44099,24.26948],"type":"Point"}
}