{
  "type": "Feature",
  "properties": {
    "gn:admin1_code":"38",
    "gn:admin2_code":"346.0",
    "gn:asciiname":"Halmanta Khurd",
    "gn:country_code":"IN",
    "gn:dem":271,
    "gn:feature_class":"P",
    "gn:feature_code":"PPL",
    "gn:name":"Halm\u0101nta Khurd",
    "gn:population":0,
    "gn:timezone":"Asia/Kolkata",
    "iso:country":"IN",
    "ks:ks_name":"Halwanta Khurd",
    "ks:ks_pop":567,
    "ks:ks_type":"VILLAGE",
    "name:eng_x_preferred":[
        "Halwanta Khurd"
    ],
    "name:eng_x_variant":[
        "Halmanta Khurd"
    ],
    "wof:name":"Halwanta Khurd",
    "wof:placetype":"locality",
    "wof:population":567
},
  "geometry": {"coordinates":[83.43993399999999,24.277881],"type":"Point"}
}