{
  "type": "Feature",
  "properties": {
    "iso:country":"IN",
    "ks:ks_name":"Gichad",
    "ks:ks_pop":642,
    "ks:ks_type":"VILLAGE",
    "name:eng_x_preferred":[
        "Gichad"
    ],
    "wof:name":"Gichad",
    "wof:placetype":"locality",
    "wof:population":642
},
  "geometry": {"coordinates":[73.68088899999999,21.719694],"type":"Point"}
}