{
  "type": "Feature",
  "properties": {
    "gn:admin1_code":"28.0",
    "gn:admin2_code":"332.0",
    "gn:asciiname":"Uttar Bhakuria",
    "gn:country_code":"IN",
    "gn:dem":31,
    "gn:feature_class":"P",
    "gn:feature_code":"PPL",
    "gn:name":"Uttar Bhakuria",
    "gn:population":0,
    "gn:timezone":"Asia/Kolkata",
    "iso:country":"IN",
    "ks:ks_name":"Uttar Bhakuria",
    "ks:ks_pop":706,
    "ks:ks_type":"VILLAGE",
    "ks:ks_uagg_main":0,
    "name:eng_x_preferred":[
        "Uttar Bhakuria"
    ],
    "wof:name":"Uttar Bhakuria",
    "wof:placetype":"neighbourhood",
    "wof:population":706
},
  "geometry": {"coordinates":[87.7962,25.340602],"type":"Point"}
}