{
  "type": "Feature",
  "properties": {
    "gn:admin1_code":"37",
    "gn:admin2_code":"406.0",
    "gn:asciiname":"Tikar Khurd",
    "gn:country_code":"IN",
    "gn:dem":676,
    "gn:feature_class":"P",
    "gn:feature_code":"PPL",
    "gn:name":"T\u012bkar Khurd",
    "gn:population":0,
    "gn:timezone":"Asia/Kolkata",
    "iso:country":"IN",
    "ks:ks_alt_nam":"TEEKARKHURD",
    "ks:ks_name":"Teekarkhurd",
    "ks:ks_pop":471,
    "ks:ks_type":"HABITATION",
    "name:eng_x_preferred":[
        "Teekarkhurd"
    ],
    "name:eng_x_variant":[
        "Tikar Khurd"
    ],
    "wof:name":"Teekarkhurd",
    "wof:placetype":"locality",
    "wof:population":471
},
  "geometry": {"coordinates":[82.207414,22.639601],"type":"Point"}
}