{
  "type": "Feature",
  "properties": {
    "gn:admin1_code":"30.0",
    "gn:admin2_code":"256.0",
    "gn:asciiname":"Pemir",
    "gn:country_code":"IN",
    "gn:dem":892,
    "gn:feature_class":"P",
    "gn:feature_code":"PPL",
    "gn:name":"Pemir",
    "gn:population":0,
    "gn:timezone":"Asia/Kolkata",
    "iso:country":"IN",
    "wof:name":"Pemir",
    "wof:placetype":"locality"
},
  "geometry": {"coordinates":[93.9593,27.75131],"type":"Point"}
}