{
  "type": "Feature",
  "properties": {
    "iso:country":"IN",
    "ks:ks_name":"Kodakkadu",
    "ks:ks_pop":1080,
    "ks:ks_type":"HABITATION",
    "ks:ks_uagg_main":0,
    "name:eng_x_preferred":[
        "Kodakkadu"
    ],
    "wof:name":"Kodakkadu",
    "wof:placetype":"neighbourhood",
    "wof:population":1080
},
  "geometry": {"coordinates":[75.86600300000001,11.087755],"type":"Point"}
}