{
  "type": "Feature",
  "properties": {
    "gn:admin1_code":"34.0",
    "gn:admin2_code":"234.0",
    "gn:asciiname":"Hatiya",
    "gn:country_code":"IN",
    "gn:dem":94,
    "gn:feature_class":"P",
    "gn:feature_code":"PPL",
    "gn:name":"Hatiya",
    "gn:population":0,
    "gn:timezone":"Asia/Kolkata",
    "iso:country":"IN",
    "name:ceb_x_preferred":[
        "Hatiya"
    ],
    "name:fra_x_preferred":[
        "Hatiya"
    ],
    "name:pol_x_preferred":[
        "Hatiya"
    ],
    "name:swe_x_preferred":[
        "Hatiya"
    ],
    "wof:name":"Hatiya",
    "wof:placetype":"locality"
},
  "geometry": {"coordinates":[84.33828000000003,25.14147],"type":"Point"}
}