{
  "type": "Feature",
  "properties": {
    "iso:country":"IN",
    "ks:ks_name":"Dudabahar",
    "ks:ks_pop":308,
    "ks:ks_type":"HABITATION",
    "name:eng_x_preferred":[
        "Dudabahar"
    ],
    "wof:name":"Dudabahar",
    "wof:placetype":"locality",
    "wof:population":308
},
  "geometry": {"coordinates":[83.369111,22.629538],"type":"Point"}
}