{
  "type": "Feature",
  "properties": {
    "gn:admin1_code":"24",
    "gn:admin2_code":"114.0",
    "gn:asciiname":"Khuri",
    "gn:country_code":"IN",
    "gn:dem":230,
    "gn:feature_class":"P",
    "gn:feature_code":"PPL",
    "gn:name":"Khuri",
    "gn:population":0,
    "gn:timezone":"Asia/Kolkata",
    "iso:country":"IN",
    "name:eng_x_preferred":[
        "Khuri"
    ],
    "name:fra_x_preferred":[
        "Khuri"
    ],
    "name:und_x_variant":[
        "K\u016bri"
    ],
    "wof:name":"Khuri",
    "wof:placetype":"locality"
},
  "geometry": {"coordinates":[70.71524000000002,26.61404000000001],"type":"Point"}
}