{
  "type": "Feature",
  "properties": {
    "iso:country":"IN",
    "ks:ks_alt_nam":"chinnamutaku",
    "ks:ks_name":"Chinnamutaku",
    "ks:ks_pop":122,
    "ks:ks_type":"HABITATION",
    "name:eng_x_preferred":[
        "Chinnamutaku"
    ],
    "wof:name":"Chinnamutaku",
    "wof:placetype":"locality",
    "wof:population":122
},
  "geometry": {"coordinates":[77.383167,10.089556],"type":"Point"}
}