{
  "type": "Feature",
  "properties": {
    "gn:admin1_code":"16",
    "gn:admin2_code":"524.0",
    "gn:asciiname":"Ambegaon",
    "gn:country_code":"IN",
    "gn:dem":594,
    "gn:feature_class":"P",
    "gn:feature_code":"PPL",
    "gn:name":"\u0100mbegaon",
    "gn:population":0,
    "gn:timezone":"Asia/Kolkata",
    "iso:country":"IN",
    "name:fas_x_preferred":[
        "\u0627\u0645\u0628\u06af\u0627\u0626\u0648\u0646"
    ],
    "name:mar_x_preferred":[
        "\u0906\u0902\u092c\u0947\u0917\u093e\u0935"
    ],
    "name:ukr_x_preferred":[
        "\u0410\u043c\u0431\u0435\u0491\u0430\u043e\u043d"
    ],
    "name:urd_x_preferred":[
        "\u0627\u0645\u0628\u06d2 \u06af\u0627\u0624\u06ba"
    ],
    "wof:name":"Ambegaon",
    "wof:placetype":"locality"
},
  "geometry": {"coordinates":[76.73209,18.23723],"type":"Point"}
}