{
  "type": "Feature",
  "properties": {
    "gn:admin1_code":"16",
    "gn:admin2_code":"524.0",
    "gn:asciiname":"Ambegaon",
    "gn:country_code":"IN",
    "gn:dem":594,
    "gn:feature_class":"P",
    "gn:feature_code":"PPL",
    "gn:name":"\u0100mbegaon",
    "gn:population":0,
    "gn:timezone":"Asia/Kolkata",
    "iso:country":"IN",
    "wof:name":"Ambegaon",
    "wof:placetype":"locality"
},
  "geometry": {"coordinates":[76.73209,18.23723],"type":"Point"}
}