{
  "type": "Feature",
  "properties": {
    "iso:country":"IN",
    "ks:ks_name":"Narhen",
    "ks:ks_pop":1251,
    "ks:ks_type":"VILLAGE",
    "name:eng_x_preferred":[
        "Narhen"
    ],
    "wof:name":"Narhen",
    "wof:placetype":"neighbourhood",
    "wof:population":1251
},
  "geometry": {"coordinates":[73.117587,19.133573],"type":"Point"}
}