{
  "type": "Feature",
  "properties": {
    "iso:country":"IN",
    "ks:ks_name":"Sannamakki",
    "ks:ks_pop":26,
    "ks:ks_type":"HABITATION",
    "name:eng_x_preferred":[
        "Sannamakki"
    ],
    "wof:name":"Sannamakki",
    "wof:placetype":"locality",
    "wof:population":26
},
  "geometry": {"coordinates":[74.599476,14.654429],"type":"Point"}
}