{
  "type": "Feature",
  "properties": {
    "iso:country":"IN",
    "ks:ks_name":"Turra Bandh",
    "ks:ks_pop":15,
    "ks:ks_type":"HABITATION",
    "name:eng_x_preferred":[
        "Turra Bandh"
    ],
    "wof:name":"Turra Bandh",
    "wof:placetype":"locality",
    "wof:population":15
},
  "geometry": {"coordinates":[82.01217800000001,24.559945],"type":"Point"}
}