{
  "type": "Feature",
  "properties": {
    "gn:admin1_code":"16.0",
    "gn:admin2_code":"510.0",
    "gn:asciiname":"Khatkhed",
    "gn:country_code":"IN",
    "gn:dem":340,
    "gn:feature_class":"P",
    "gn:feature_code":"PPL",
    "gn:name":"Kh\u0101tkhed",
    "gn:population":0,
    "gn:timezone":"Asia/Kolkata",
    "iso:country":"IN",
    "ks:ks_name":"Katkheda",
    "ks:ks_pop":743,
    "ks:ks_type":"VILLAGE",
    "name:eng_x_preferred":[
        "Katkheda"
    ],
    "name:eng_x_variant":[
        "Khatkhed"
    ],
    "wof:name":"Katkheda",
    "wof:placetype":"locality",
    "wof:population":743
},
  "geometry": {"coordinates":[77.628193,19.914404],"type":"Point"}
}