{
  "type": "Feature",
  "properties": {
    "gn:admin1_code":"12.0",
    "gn:admin2_code":"005",
    "gn:asciiname":"Dinga Tirkana",
    "gn:country_code":"IN",
    "gn:dem":3055,
    "gn:feature_class":"P",
    "gn:feature_code":"PPL",
    "gn:name":"D\u012bnga Tirkana",
    "gn:population":0,
    "gn:timezone":"Asia/Kolkata",
    "iso:country":"IN",
    "wof:name":"Dinga Tirkana",
    "wof:placetype":"locality"
},
  "geometry": {"coordinates":[74.33471999999998,33.90139],"type":"Point"}
}