{
  "type": "Feature",
  "properties": {
    "gn:admin1_code":"24",
    "gn:admin2_code":"122.0",
    "gn:asciiname":"Intria",
    "gn:country_code":"IN",
    "gn:dem":381,
    "gn:feature_class":"P",
    "gn:feature_code":"PPL",
    "gn:name":"Intria",
    "gn:population":0,
    "gn:timezone":"Asia/Kolkata",
    "iso:country":"IN",
    "wof:name":"Intria",
    "wof:placetype":"neighbourhood"
},
  "geometry": {"coordinates":[74.81939,25.85883],"type":"Point"}
}