{
  "type": "Feature",
  "properties": {
    "gn:admin1_code":"19",
    "gn:admin2_code":"556.0",
    "gn:asciiname":"Kodihal",
    "gn:country_code":"IN",
    "gn:dem":508,
    "gn:feature_class":"P",
    "gn:feature_code":"PPL",
    "gn:name":"Kodih\u0101l",
    "gn:population":0,
    "gn:timezone":"Asia/Kolkata",
    "iso:country":"IN",
    "wof:name":"Kodihal",
    "wof:placetype":"locality"
},
  "geometry": {"coordinates":[76.30365999999999,16.09512999999999],"type":"Point"}
}