{
  "type": "Feature",
  "properties": {
    "iso:country":"IN",
    "ks:ks_name":"Chodirai",
    "ks:ks_pop":173,
    "ks:ks_type":"VILLAGE",
    "name:eng_x_preferred":[
        "Chodirai"
    ],
    "wof:name":"Chodirai",
    "wof:placetype":"locality",
    "wof:population":173
},
  "geometry": {"coordinates":[82.06474300000001,17.964939],"type":"Point"}
}