{
  "type": "Feature",
  "properties": {
    "iso:country":"IN",
    "ks:ks_name":"Chirkura",
    "ks:ks_pop":201,
    "ks:ks_type":"HABITATION",
    "name:eng_x_preferred":[
        "Chirkura"
    ],
    "wof:name":"Chirkura",
    "wof:placetype":"locality",
    "wof:population":201
},
  "geometry": {"coordinates":[82.856314,24.362675],"type":"Point"}
}