{
  "type": "Feature",
  "properties": {
    "iso:country":"IN",
    "ks:ks_name":"Chak Jangipur",
    "ks:ks_pop":75,
    "ks:ks_type":"VILLAGE",
    "name:eng_x_preferred":[
        "Chak Jangipur"
    ],
    "wof:name":"Chak Jangipur",
    "wof:placetype":"locality",
    "wof:population":75
},
  "geometry": {"coordinates":[78.389779,25.986189],"type":"Point"}
}