{
  "type": "Feature",
  "properties": {
    "gn:admin1_code":"40.0",
    "gn:admin2_code":"534.0",
    "gn:asciiname":"Yenkapalli",
    "gn:country_code":"IN",
    "gn:dem":110,
    "gn:feature_class":"P",
    "gn:feature_code":"PPL",
    "gn:name":"Yenk\u0101palli",
    "gn:population":0,
    "gn:timezone":"Asia/Kolkata",
    "iso:country":"IN",
    "ks:ks_name":"Yenkepalle",
    "ks:ks_pop":579,
    "ks:ks_type":"VILLAGE",
    "name:eng_x_preferred":[
        "Yenkepalle"
    ],
    "name:eng_x_variant":[
        "Yenkapalli"
    ],
    "wof:name":"Yenkepalle",
    "wof:placetype":"locality",
    "wof:population":579
},
  "geometry": {"coordinates":[80.047175,18.667309],"type":"Point"}
}