{
  "type": "Feature",
  "properties": {
    "gn:admin1_code":"12.0",
    "gn:admin2_code":"001",
    "gn:asciiname":"Hanji Shat",
    "gn:country_code":"IN",
    "gn:dem":1594,
    "gn:feature_class":"P",
    "gn:feature_code":"PPL",
    "gn:name":"Hanji Sh\u0101t",
    "gn:population":0,
    "gn:timezone":"Asia/Kolkata",
    "iso:country":"IN",
    "wof:name":"Hanji Shat",
    "wof:placetype":"locality"
},
  "geometry": {"coordinates":[74.34075,34.39298],"type":"Point"}
}