{
  "type": "Feature",
  "properties": {
    "iso:country":"IN",
    "ks:ks_name":"Yehiapur",
    "ks:ks_pop":4757,
    "ks:ks_type":"VILLAGE",
    "name:eng_x_preferred":[
        "Yehiapur"
    ],
    "wof:name":"Yehiapur",
    "wof:placetype":"locality",
    "wof:population":4757
},
  "geometry": {"coordinates":[85.395051,26.149013],"type":"Point"}
}