{
  "type": "Feature",
  "properties": {
    "iso:country":"IN",
    "ks:ks_name":"No2 Palashbari",
    "ks:ks_pop":298,
    "ks:ks_type":"HABITATION",
    "name:eng_x_preferred":[
        "No2 Palashbari"
    ],
    "wof:name":"No2 Palashbari",
    "wof:placetype":"locality",
    "wof:population":298
},
  "geometry": {"coordinates":[91.51899400000001,26.75864],"type":"Point"}
}