{
  "type": "Feature",
  "properties": {
    "iso:country":"IN",
    "ks:ks_name":"Oraon Toli",
    "ks:ks_pop":22,
    "ks:ks_type":"HABITATION",
    "name:eng_x_preferred":[
        "Oraon Toli"
    ],
    "wof:name":"Oraon Toli",
    "wof:placetype":"locality",
    "wof:population":22
},
  "geometry": {"coordinates":[85.54100800000001,23.370724],"type":"Point"}
}