{
  "type": "Feature",
  "properties": {
    "gn:admin1_code":"37",
    "gn:admin2_code":"401.0",
    "gn:asciiname":"Saoltikra",
    "gn:country_code":"IN",
    "gn:dem":544,
    "gn:feature_class":"P",
    "gn:feature_code":"PPL",
    "gn:name":"Saoltikra",
    "gn:population":0,
    "gn:timezone":"Asia/Kolkata",
    "iso:country":"IN",
    "wof:name":"Saoltikra",
    "wof:placetype":"locality"
},
  "geometry": {"coordinates":[82.95,23.18333],"type":"Point"}
}