{
  "type": "Feature",
  "properties": {
    "iso:country":"IN",
    "ks:ks_alt_nam":"Dupin III Silogaon",
    "ks:ks_name":"Dupin Iii Silogaon",
    "ks:ks_pop":420,
    "ks:ks_type":"HABITATION",
    "name:eng_x_preferred":[
        "Dupin Iii Silogaon"
    ],
    "wof:name":"Dupin Iii Silogaon",
    "wof:placetype":"locality",
    "wof:population":420
},
  "geometry": {"coordinates":[88.215531,26.901943],"type":"Point"}
}