{
  "type": "Feature",
  "properties": {
    "iso:country":"IN",
    "ks:ks_name":"Sera",
    "ks:ks_pop":110,
    "ks:ks_type":"VILLAGE",
    "name:eng_x_preferred":[
        "Sera"
    ],
    "wof:name":"Sera",
    "wof:placetype":"locality",
    "wof:population":110
},
  "geometry": {"coordinates":[79.413284,30.271456],"type":"Point"}
}