{
  "type": "Feature",
  "properties": {
    "gn:country":"IN",
    "gn:fcode":"PPL",
    "gn:population":0,
    "iso:country":"IN",
    "qs:name":"Agarvado",
    "qs:name_adm0":"India",
    "qs:name_adm1":"Goa",
    "qs:photos_9r":0,
    "qs:photos_sr":0,
    "qs:placetype":"Town",
    "qs:pop_sr":"0",
    "wof:name":"Agarvado",
    "wof:placetype":"locality",
    "wof:population":0
},
  "geometry": {"coordinates":[73.79306,15.64746],"type":"Point"}
}