{
  "type": "Feature",
  "properties": {
    "iso:country":"IN",
    "ks:ks_name":"Pahartoli",
    "ks:ks_pop":103,
    "ks:ks_type":"HABITATION",
    "name:eng_x_preferred":[
        "Pahartoli"
    ],
    "wof:name":"Pahartoli",
    "wof:placetype":"locality",
    "wof:population":103
},
  "geometry": {"coordinates":[84.92142200000001,22.453074],"type":"Point"}
}