{
  "type": "Feature",
  "properties": {
    "iso:country":"IN",
    "ks:ks_name":"Alampara",
    "ks:ks_pop":2210,
    "ks:ks_type":"HABITATION",
    "name:eng_x_preferred":[
        "Alampara"
    ],
    "wof:name":"Alampara",
    "wof:placetype":"locality",
    "wof:population":2210
},
  "geometry": {"coordinates":[77.01814899999999,8.700108],"type":"Point"}
}