{
  "type": "Feature",
  "properties": {
    "iso:country":"IN",
    "ks:ks_alt_nam":"SALUNKHE THOMBAREWASTI.",
    "ks:ks_name":"Salunkhe Thombarewasti.",
    "ks:ks_pop":76,
    "ks:ks_type":"HABITATION",
    "name:eng_x_preferred":[
        "Salunkhe Thombarewasti."
    ],
    "wof:name":"Salunkhe Thombarewasti.",
    "wof:placetype":"locality",
    "wof:population":76
},
  "geometry": {"coordinates":[74.146738,17.098028],"type":"Point"}
}