{
  "type": "Feature",
  "properties": {
    "gn:admin1_code":"11",
    "gn:admin2_code":"24.0",
    "gn:asciiname":"Mansimbal",
    "gn:country_code":"IN",
    "gn:dem":989,
    "gn:feature_class":"P",
    "gn:feature_code":"PPL",
    "gn:name":"Mansimbal",
    "gn:population":0,
    "gn:timezone":"Asia/Kolkata",
    "iso:country":"IN",
    "wof:name":"Mansimbal",
    "wof:placetype":"locality"
},
  "geometry": {"coordinates":[76.49731,32.05146],"type":"Point"}
}