{
  "type": "Feature",
  "properties": {
    "iso:country":"IN",
    "ks:ks_name":"Kathiaralga Pt 3",
    "ks:ks_pop":464,
    "ks:ks_type":"HABITATION",
    "name:eng_x_preferred":[
        "Kathiaralga Pt 3"
    ],
    "wof:name":"Kathiaralga Pt 3",
    "wof:placetype":"locality",
    "wof:population":464
},
  "geometry": {"coordinates":[89.89956100000001,25.861027],"type":"Point"}
}