{
  "type": "Feature",
  "properties": {
    "iso:country":"IN",
    "ks:ks_name":"Parajaguda",
    "ks:ks_pop":166,
    "ks:ks_type":"HABITATION",
    "name:eng_x_preferred":[
        "Parajaguda"
    ],
    "wof:name":"Parajaguda",
    "wof:placetype":"locality",
    "wof:population":166
},
  "geometry": {"coordinates":[82.565797,18.998482],"type":"Point"}
}