{
  "type": "Feature",
  "properties": {
    "iso:country":"IN",
    "ks:ks_name":"Mukhiyaji Tola",
    "ks:ks_pop":237,
    "ks:ks_type":"HABITATION",
    "ks:ks_uagg_main":0,
    "name:eng_x_preferred":[
        "Mukhiyaji Tola"
    ],
    "wof:name":"Mukhiyaji Tola",
    "wof:placetype":"neighbourhood",
    "wof:population":237
},
  "geometry": {"coordinates":[84.34687,26.5014],"type":"Point"}
}