{
  "type": "Feature",
  "properties": {
    "iso:country":"IN",
    "ks:ks_name":"Chinnur",
    "ks:ks_pop":550,
    "ks:ks_type":"HABITATION",
    "name:eng_x_preferred":[
        "Chinnur"
    ],
    "wof:name":"Chinnur",
    "wof:placetype":"locality",
    "wof:population":550
},
  "geometry": {"coordinates":[78.438957,12.494859],"type":"Point"}
}