{
  "type": "Feature",
  "properties": {
    "gn:admin1_code":"38.0",
    "gn:admin2_code":"351.0",
    "gn:asciiname":"Singhpur",
    "gn:country_code":"IN",
    "gn:dem":54,
    "gn:feature_class":"P",
    "gn:feature_code":"PPL",
    "gn:name":"Singhpur",
    "gn:population":0,
    "gn:timezone":"Asia/Kolkata",
    "iso:country":"IN",
    "ks:ks_name":"Singpur",
    "ks:ks_pop":2333,
    "ks:ks_type":"VILLAGE",
    "name:eng_x_preferred":[
        "Singpur"
    ],
    "name:eng_x_variant":[
        "Singhpur"
    ],
    "wof:name":"Singpur",
    "wof:placetype":"locality",
    "wof:population":2333
},
  "geometry": {"coordinates":[87.289889,25.081925],"type":"Point"}
}