{
  "type": "Feature",
  "properties": {
    "iso:country":"IN",
    "ks:ks_name":"Gadaghat Para",
    "ks:ks_pop":206,
    "ks:ks_type":"HABITATION",
    "name:eng_x_preferred":[
        "Gadaghat Para"
    ],
    "wof:name":"Gadaghat Para",
    "wof:placetype":"locality",
    "wof:population":206
},
  "geometry": {"coordinates":[81.689976,19.259328],"type":"Point"}
}