{
  "type": "Feature",
  "properties": {
    "gn:admin1_code":"24.0",
    "gn:admin2_code":"104.0",
    "gn:asciiname":"Silgaon Chhota",
    "gn:country_code":"IN",
    "gn:dem":276,
    "gn:feature_class":"P",
    "gn:feature_code":"PPL",
    "gn:name":"S\u012blgaon Chhota",
    "gn:population":0,
    "gn:timezone":"Asia/Kolkata",
    "iso:country":"IN",
    "wof:name":"Silgaon Chhota",
    "wof:placetype":"locality"
},
  "geometry": {"coordinates":[76.61516999999998,27.97357],"type":"Point"}
}