{
  "type": "Feature",
  "properties": {
    "gn:admin1_code":"37.0",
    "gn:admin2_code":"409.0",
    "gn:asciiname":"Sarbada",
    "gn:country_code":"IN",
    "gn:dem":320,
    "gn:feature_class":"P",
    "gn:feature_code":"PPL",
    "gn:name":"Sarbada",
    "gn:population":0,
    "gn:timezone":"Asia/Kolkata",
    "iso:country":"IN",
    "ks:ks_name":"Sarbada",
    "ks:ks_pop":963,
    "ks:ks_type":"VILLAGE",
    "name:eng_x_preferred":[
        "Sarbada"
    ],
    "wof:name":"Sarbada",
    "wof:placetype":"locality",
    "wof:population":963
},
  "geometry": {"coordinates":[81.44794400000001,20.720309],"type":"Point"}
}