{
  "type": "Feature",
  "properties": {
    "gn:admin1_code":"36",
    "gn:admin2_code":"174.0",
    "gn:asciiname":"Ambanwan Pachhim",
    "gn:country_code":"IN",
    "gn:dem":107,
    "gn:feature_class":"P",
    "gn:feature_code":"PPL",
    "gn:name":"Amb\u0101nw\u0101n Pachhim",
    "gn:population":0,
    "gn:timezone":"Asia/Kolkata",
    "iso:country":"IN",
    "wof:name":"Ambanwan Pachhim",
    "wof:placetype":"locality"
},
  "geometry": {"coordinates":[81.42565,25.52667000000001],"type":"Point"}
}