{
  "type": "Feature",
  "properties": {
    "gn:admin1_code":"12",
    "gn:admin2_code":"15.0",
    "gn:asciiname":"Panditpur",
    "gn:country_code":"IN",
    "gn:dem":1694,
    "gn:feature_class":"P",
    "gn:feature_code":"PPL",
    "gn:name":"Panditpur",
    "gn:population":0,
    "gn:timezone":"Asia/Kolkata",
    "iso:country":"IN",
    "wof:name":"Panditpur",
    "wof:placetype":"locality"
},
  "geometry": {"coordinates":[75.00138000000003,33.70884],"type":"Point"}
}