{
  "type": "Feature",
  "properties": {
    "gn:admin1_code":"36",
    "gn:admin2_code":"147.0",
    "gn:asciiname":"Nagla Himmat",
    "gn:country_code":"IN",
    "gn:dem":165,
    "gn:feature_class":"P",
    "gn:feature_code":"PPL",
    "gn:name":"Nagla Himmat",
    "gn:population":0,
    "gn:timezone":"Asia/Kolkata",
    "iso:country":"IN",
    "ks:ks_name":"Nagla Himmat",
    "ks:ks_pop":1573,
    "ks:ks_type":"VILLAGE",
    "ks:ks_uagg_main":0,
    "name:eng_x_preferred":[
        "Nagla Himmat"
    ],
    "wof:name":"Nagla Himmat",
    "wof:placetype":"neighbourhood",
    "wof:population":1573
},
  "geometry": {"coordinates":[78.482071,27.191333],"type":"Point"}
}