{
  "type": "Feature",
  "properties": {
    "iso:country":"IN",
    "ks:ks_alt_nam":"Noojadi HC",
    "ks:ks_name":"Noojadi Hc",
    "ks:ks_pop":295,
    "ks:ks_type":"HABITATION",
    "name:eng_x_preferred":[
        "Noojadi Hc"
    ],
    "wof:name":"Noojadi Hc",
    "wof:placetype":"locality",
    "wof:population":295
},
  "geometry": {"coordinates":[75.418271,12.695898],"type":"Point"}
}