{
  "type": "Feature",
  "properties": {
    "iso:country":"IN",
    "ks:ks_name":"Khola Khamar",
    "ks:ks_pop":112,
    "ks:ks_type":"VILLAGE",
    "name:eng_x_preferred":[
        "Khola Khamar"
    ],
    "wof:name":"Khola Khamar",
    "wof:placetype":"locality",
    "wof:population":112
},
  "geometry": {"coordinates":[86.968654,23.890279],"type":"Point"}
}