{
  "type": "Feature",
  "properties": {
    "gn:admin1_code":"36.0",
    "gn:admin2_code":"155.0",
    "gn:asciiname":"Fatehpur",
    "gn:country_code":"IN",
    "gn:dem":147,
    "gn:feature_class":"P",
    "gn:feature_code":"PPL",
    "gn:name":"Fatehpur",
    "gn:population":0,
    "gn:timezone":"Asia/Kolkata",
    "iso:country":"IN",
    "name:ben_x_preferred":[
        "\u09ab\u09a4\u09c7\u09b9\u09aa\u09c1\u09b0"
    ],
    "name:bih_x_preferred":[
        "\u092b\u0924\u0947\u0939\u092a\u0941\u0930"
    ],
    "name:ceb_x_preferred":[
        "Fatehpur"
    ],
    "name:deu_x_preferred":[
        "Fatehpur"
    ],
    "name:new_x_preferred":[
        "\u092b\u0924\u0947\u0939\u092a\u0941\u0930"
    ],
    "name:nld_x_preferred":[
        "Fatehpur"
    ],
    "name:pnb_x_preferred":[
        "\u0641\u062a\u062d \u067e\u0648\u0631"
    ],
    "name:pol_x_preferred":[
        "Fatehpur"
    ],
    "name:spa_x_preferred":[
        "Fatehpur"
    ],
    "name:swe_x_preferred":[
        "Fatehpur"
    ],
    "wof:name":"Fatehpur",
    "wof:placetype":"locality"
},
  "geometry": {"coordinates":[80.20104000000001,27.58524],"type":"Point"}
}