{
  "type": "Feature",
  "properties": {
    "gn:admin1_code":"36.0",
    "gn:admin2_code":"138.0",
    "gn:asciiname":"Chandauripatti Dalu",
    "gn:country_code":"IN",
    "gn:dem":228,
    "gn:feature_class":"P",
    "gn:feature_code":"PPL",
    "gn:name":"Chandauripatti D\u0101lu",
    "gn:population":0,
    "gn:timezone":"Asia/Kolkata",
    "iso:country":"IN",
    "ks:ks_alt_nam":"Chandauripatti D\u0101lu",
    "ks:ks_name":"Chandauripatti Dalu",
    "ks:ks_type":"VILLAGE",
    "ks:ks_uagg_main":0,
    "name:eng_x_preferred":[
        "Chandauripatti Dalu"
    ],
    "name:eng_x_variant":[
        "Chandauripatti D\u0101lu"
    ],
    "wof:name":"Chandauripatti Dalu",
    "wof:placetype":"neighbourhood"
},
  "geometry": {"coordinates":[77.51777,29.035711],"type":"Point"}
}