{
  "type": "Feature",
  "properties": {
    "iso:country":"IN",
    "ks:ks_name":"Fakirna",
    "ks:ks_pop":2362,
    "ks:ks_type":"VILLAGE",
    "name:eng_x_preferred":[
        "Fakirna"
    ],
    "wof:name":"Fakirna",
    "wof:placetype":"locality",
    "wof:population":2362
},
  "geometry": {"coordinates":[86.880304,26.356493],"type":"Point"}
}