{
  "type": "Feature",
  "properties": {
    "iso:country":"IN",
    "ks:ks_name":"Mungani",
    "ks:ks_pop":3163,
    "ks:ks_type":"VILLAGE",
    "ks:ks_uagg_main":0,
    "name:eng_x_preferred":[
        "Mungani"
    ],
    "wof:name":"Mungani",
    "wof:placetype":"neighbourhood",
    "wof:population":3163
},
  "geometry": {"coordinates":[69.83113899999999,22.414],"type":"Point"}
}