{
  "type": "Feature",
  "properties": {
    "gn:admin1_code":"35.0",
    "gn:admin2_code":"457.0",
    "gn:asciiname":"Pandrapani",
    "gn:country_code":"IN",
    "gn:dem":370,
    "gn:feature_class":"P",
    "gn:feature_code":"PPL",
    "gn:name":"Pandr\u0101p\u0101n\u012b",
    "gn:population":0,
    "gn:timezone":"Asia/Kolkata",
    "iso:country":"IN",
    "wof:name":"Pandrapani",
    "wof:placetype":"locality"
},
  "geometry": {"coordinates":[80.1644,22.10991],"type":"Point"}
}