{
  "type": "Feature",
  "properties": {
    "iso:country":"IN",
    "ks:ks_alt_nam":"kaipra",
    "ks:ks_name":"Kaipra",
    "ks:ks_pop":2000,
    "ks:ks_type":"HABITATION",
    "ks:ks_uagg_main":0,
    "name:eng_x_preferred":[
        "Kaipra"
    ],
    "wof:name":"Kaipra",
    "wof:placetype":"neighbourhood",
    "wof:population":2000
},
  "geometry": {"coordinates":[76.429939,10.13001],"type":"Point"}
}