{
  "type": "Feature",
  "properties": {
    "gn:admin1_code":"36.0",
    "gn:admin2_code":"173.0",
    "gn:asciiname":"Katata",
    "gn:country_code":"IN",
    "gn:dem":100,
    "gn:feature_class":"P",
    "gn:feature_code":"PPL",
    "gn:name":"Kat\u0101ta",
    "gn:population":0,
    "gn:timezone":"Asia/Kolkata",
    "iso:country":"IN",
    "ks:ks_name":"Katata",
    "ks:ks_pop":216,
    "ks:ks_type":"VILLAGE",
    "name:eng_x_preferred":[
        "Katata"
    ],
    "wof:name":"Katata",
    "wof:placetype":"locality",
    "wof:population":216
},
  "geometry": {"coordinates":[81.90618600000001,25.960624],"type":"Point"}
}