{
  "type": "Feature",
  "properties": {
    "iso:country":"IN",
    "ks:ks_name":"Pakardih",
    "ks:ks_pop":244,
    "ks:ks_type":"VILLAGE",
    "ks:ks_uagg_main":0,
    "name:eng_x_preferred":[
        "Pakardih"
    ],
    "wof:name":"Pakardih",
    "wof:placetype":"neighbourhood",
    "wof:population":244
},
  "geometry": {"coordinates":[84.17404000000001,23.472715],"type":"Point"}
}