{
  "type": "Feature",
  "properties": {
    "gn:admin1_code":"19.0",
    "gn:admin2_code":"582.0",
    "gn:asciiname":"Jodi Pulthamanahalli",
    "gn:country_code":"IN",
    "gn:dem":930,
    "gn:feature_class":"P",
    "gn:feature_code":"PPL",
    "gn:name":"Jodi Pulth\u0101manahalli",
    "gn:population":0,
    "gn:timezone":"Asia/Kolkata",
    "iso:country":"IN",
    "wof:name":"Jodi Pulthamanahalli",
    "wof:placetype":"neighbourhood"
},
  "geometry": {"coordinates":[77.77739,13.48574],"type":"Point"}
}