{
  "type": "Feature",
  "properties": {
    "gn:admin1_code":"35",
    "gn:admin2_code":"446.0",
    "gn:asciiname":"Surmapar",
    "gn:country_code":"IN",
    "gn:dem":327,
    "gn:feature_class":"P",
    "gn:feature_code":"PPL",
    "gn:name":"Surm\u0101p\u0101r",
    "gn:population":0,
    "gn:timezone":"Asia/Kolkata",
    "iso:country":"IN",
    "ks:ks_name":"Surmapar",
    "ks:ks_pop":6,
    "ks:ks_type":"HABITATION",
    "name:eng_x_preferred":[
        "Surmapar"
    ],
    "wof:name":"Surmapar",
    "wof:placetype":"locality",
    "wof:population":6
},
  "geometry": {"coordinates":[78.21816099999999,23.043912],"type":"Point"}
}