{
  "type": "Feature",
  "properties": {
    "gn:admin1_code":"35.0",
    "gn:admin2_code":"438.0",
    "gn:asciiname":"Kalmi",
    "gn:country_code":"IN",
    "gn:dem":244,
    "gn:feature_class":"P",
    "gn:feature_code":"PPL",
    "gn:name":"Kalmi",
    "gn:population":0,
    "gn:timezone":"Asia/Kolkata",
    "iso:country":"IN",
    "ks:ks_name":"Kalmi",
    "ks:ks_pop":1424,
    "ks:ks_type":"VILLAGE",
    "name:eng_x_preferred":[
        "Kalmi"
    ],
    "wof:name":"Kalmi",
    "wof:placetype":"locality",
    "wof:population":1424
},
  "geometry": {"coordinates":[74.58864199999999,22.216569],"type":"Point"}
}