{
  "type": "Feature",
  "properties": {
    "gn:admin1_code":"2.0",
    "gn:admin2_code":"544.0",
    "gn:asciiname":"Iskagur",
    "gn:country_code":"IN",
    "gn:dem":964,
    "gn:feature_class":"P",
    "gn:feature_code":"PPL",
    "gn:name":"Iskagur",
    "gn:population":0,
    "gn:timezone":"Asia/Kolkata",
    "iso:country":"IN",
    "wof:name":"Iskagur",
    "wof:placetype":"locality"
},
  "geometry": {"coordinates":[82.57684999999999,18.07442],"type":"Point"}
}