{
  "type": "Feature",
  "properties": {
    "iso:country":"IN",
    "ks:ks_name":"Lokabati",
    "ks:ks_pop":1801,
    "ks:ks_type":"VILLAGE",
    "ks:ks_uagg_main":0,
    "name:eng_x_preferred":[
        "Lokabati"
    ],
    "wof:name":"Lokabati",
    "wof:placetype":"neighbourhood",
    "wof:population":1801
},
  "geometry": {"coordinates":[88.096705,22.995478],"type":"Point"}
}