{
  "type": "Feature",
  "properties": {
    "iso:country":"IN",
    "ks:ks_name":"Jegya Thanda",
    "ks:ks_pop":199,
    "ks:ks_type":"HABITATION",
    "name:eng_x_preferred":[
        "Jegya Thanda"
    ],
    "wof:name":"Jegya Thanda",
    "wof:placetype":"locality",
    "wof:population":199
},
  "geometry": {"coordinates":[78.26935,17.848726],"type":"Point"}
}