{
  "type": "Feature",
  "properties": {
    "iso:country":"IN",
    "ks:ks_name":"Kalianti",
    "ks:ks_pop":351,
    "ks:ks_type":"VILLAGE",
    "name:eng_x_preferred":[
        "Kalianti"
    ],
    "wof:name":"Kalianti",
    "wof:placetype":"locality",
    "wof:population":351
},
  "geometry": {"coordinates":[87.07450900000001,21.708294],"type":"Point"}
}