{
  "type": "Feature",
  "properties": {
    "iso:country":"IN",
    "ks:ks_name":"Kunchi Shole",
    "ks:ks_pop":537,
    "ks:ks_type":"VILLAGE",
    "name:eng_x_preferred":[
        "Kunchi Shole"
    ],
    "wof:name":"Kunchi Shole",
    "wof:placetype":"locality",
    "wof:population":537
},
  "geometry": {"coordinates":[87.23704600000001,23.193823],"type":"Point"}
}