{
  "type": "Feature",
  "properties": {
    "iso:country":"IN",
    "ks:ks_name":"Honnehakkal",
    "ks:ks_pop":27,
    "ks:ks_type":"HABITATION",
    "name:eng_x_preferred":[
        "Honnehakkal"
    ],
    "wof:name":"Honnehakkal",
    "wof:placetype":"locality",
    "wof:population":27
},
  "geometry": {"coordinates":[74.738039,14.821954],"type":"Point"}
}