{
  "type": "Feature",
  "properties": {
    "iso:country":"IN",
    "ks:ks_name":"Barpara",
    "ks:ks_pop":664,
    "ks:ks_type":"HABITATION",
    "name:eng_x_preferred":[
        "Barpara"
    ],
    "wof:name":"Barpara",
    "wof:placetype":"locality",
    "wof:population":664
},
  "geometry": {"coordinates":[83.41894499999999,23.041501],"type":"Point"}
}