{
  "type": "Feature",
  "properties": {
    "gn:admin1_code":"36",
    "gn:admin2_code":"158.0",
    "gn:asciiname":"Narai",
    "gn:country_code":"IN",
    "gn:dem":121,
    "gn:feature_class":"P",
    "gn:feature_code":"PPL",
    "gn:name":"Nar\u0101i",
    "gn:population":0,
    "gn:timezone":"Asia/Kolkata",
    "iso:country":"IN",
    "name:deu_x_preferred":[
        "Narai"
    ],
    "name:fra_x_preferred":[
        "Narai"
    ],
    "name:ind_x_preferred":[
        "Narai"
    ],
    "name:ita_x_preferred":[
        "Narai"
    ],
    "name:jpn_x_preferred":[
        "\u30ca\u30fc\u30e9\u30fc\u30a4"
    ],
    "name:khm_x_preferred":[
        "\u1793\u17b6\u179a\u17b6\u1799\u178e\u17cd"
    ],
    "name:nld_x_preferred":[
        "Narai"
    ],
    "name:nor_x_preferred":[
        "Narai"
    ],
    "name:rus_x_preferred":[
        "\u041d\u0430\u0440\u0430\u0439"
    ],
    "name:spa_x_preferred":[
        "Narai"
    ],
    "name:swe_x_preferred":[
        "Narai"
    ],
    "name:tha_x_preferred":[
        "\u0e2a\u0e21\u0e40\u0e14\u0e47\u0e08\u0e1e\u0e23\u0e30\u0e19\u0e32\u0e23\u0e32\u0e22\u0e13\u0e4c\u0e21\u0e2b\u0e32\u0e23\u0e32\u0e0a"
    ],
    "name:ukr_x_preferred":[
        "\u041d\u0430\u0440\u0430\u0439"
    ],
    "name:vie_x_preferred":[
        "Narai"
    ],
    "name:yor_x_preferred":[
        "Narai"
    ],
    "name:zha_x_preferred":[
        "Narai"
    ],
    "name:zho_x_preferred":[
        "\u90a3\u83b1\u738b"
    ],
    "wof:name":"Narai",
    "wof:placetype":"locality"
},
  "geometry": {"coordinates":[81.23863,26.35697],"type":"Point"}
}