{
  "type": "Feature",
  "properties": {
    "gn:admin1_code":"28.0",
    "gn:admin2_code":"327.0",
    "gn:asciiname":"Sidim",
    "gn:country_code":"IN",
    "gn:dem":1296,
    "gn:feature_class":"P",
    "gn:feature_code":"PPL",
    "gn:name":"Sidim",
    "gn:population":0,
    "gn:timezone":"Asia/Kolkata",
    "iso:country":"IN",
    "wof:name":"Sidim",
    "wof:placetype":"neighbourhood"
},
  "geometry": {"coordinates":[88.57658000000001,27.04442],"type":"Point"}
}