{
  "type": "Feature",
  "properties": {
    "gn:admin1_code":"34.0",
    "gn:admin2_code":"211.0",
    "gn:asciiname":"Amna",
    "gn:country_code":"IN",
    "gn:dem":40,
    "gn:feature_class":"P",
    "gn:feature_code":"PPL",
    "gn:name":"Amna",
    "gn:population":0,
    "gn:timezone":"Asia/Kolkata",
    "iso:country":"IN",
    "wof:name":"Amna",
    "wof:placetype":"neighbourhood"
},
  "geometry": {"coordinates":[87.67627,25.73642],"type":"Point"}
}