{
  "type": "Feature",
  "properties": {
    "gn:admin1_code":"11.0",
    "gn:admin2_code":"26.0",
    "gn:asciiname":"Dharli",
    "gn:country_code":"IN",
    "gn:dem":2153,
    "gn:feature_class":"P",
    "gn:feature_code":"PPL",
    "gn:name":"Dh\u0101rli",
    "gn:population":0,
    "gn:timezone":"Asia/Kolkata",
    "iso:country":"IN",
    "wof:name":"Dharli",
    "wof:placetype":"locality"
},
  "geometry": {"coordinates":[77.45048,31.48186],"type":"Point"}
}