{
  "type": "Feature",
  "properties": {
    "iso:country":"IN",
    "ks:ks_name":"Rallapuram",
    "ks:ks_pop":121,
    "ks:ks_type":"HABITATION",
    "name:eng_x_preferred":[
        "Rallapuram"
    ],
    "wof:name":"Rallapuram",
    "wof:placetype":"locality",
    "wof:population":121
},
  "geometry": {"coordinates":[80.887901,18.103206],"type":"Point"}
}