{
  "type": "Feature",
  "properties": {
    "gn:admin1_code":"35.0",
    "gn:admin2_code":"465.0",
    "gn:asciiname":"Jhameri",
    "gn:country_code":"IN",
    "gn:dem":387,
    "gn:feature_class":"P",
    "gn:feature_code":"PPL",
    "gn:name":"Jhameri",
    "gn:population":0,
    "gn:timezone":"Asia/Kolkata",
    "iso:country":"IN",
    "ks:ks_name":"Jameri",
    "ks:ks_pop":745,
    "ks:ks_type":"VILLAGE",
    "name:eng_x_preferred":[
        "Jameri"
    ],
    "name:eng_x_variant":[
        "Jhameri"
    ],
    "wof:name":"Jameri",
    "wof:placetype":"locality",
    "wof:population":745
},
  "geometry": {"coordinates":[74.643704,22.424248],"type":"Point"}
}