{
  "type": "Feature",
  "properties": {
    "iso:country":"IN",
    "ks:ks_alt_nam":"JAKAIDEVALAY",
    "ks:ks_name":"Jakaidevalay",
    "ks:ks_pop":100,
    "ks:ks_type":"HABITATION",
    "name:eng_x_preferred":[
        "Jakaidevalay"
    ],
    "wof:name":"Jakaidevalay",
    "wof:placetype":"locality",
    "wof:population":100
},
  "geometry": {"coordinates":[74.30743099999999,17.182501],"type":"Point"}
}