{
  "type": "Feature",
  "properties": {
    "gn:admin1_code":"36.0",
    "gn:admin2_code":"188.0",
    "gn:asciiname":"Dadri",
    "gn:country_code":"IN",
    "gn:dem":75,
    "gn:feature_class":"P",
    "gn:feature_code":"PPL",
    "gn:name":"Dadri",
    "gn:population":0,
    "gn:timezone":"Asia/Kolkata",
    "iso:country":"IN",
    "name:bpy_x_preferred":[
        "\u09a6\u09be\u09a6\u09cd\u09b0\u09bf"
    ],
    "name:ceb_x_preferred":[
        "D\u0101dri"
    ],
    "name:hin_x_preferred":[
        "\u0926\u093e\u0926\u0930\u0940"
    ],
    "name:ind_x_preferred":[
        "Dadri"
    ],
    "name:ita_x_preferred":[
        "Dadri"
    ],
    "name:mlg_x_preferred":[
        "Dadri"
    ],
    "name:msa_x_preferred":[
        "Dadri"
    ],
    "name:new_x_preferred":[
        "\u0926\u093e\u0926\u094d\u0930\u0940"
    ],
    "name:nld_x_preferred":[
        "Dadri"
    ],
    "name:pol_x_preferred":[
        "Dadri"
    ],
    "name:por_x_preferred":[
        "Dadri"
    ],
    "name:swe_x_preferred":[
        "Dadri"
    ],
    "name:urd_x_preferred":[
        "\u062f\u0627\u062f\u0631\u06cc"
    ],
    "name:vie_x_preferred":[
        "Dadri"
    ],
    "name:zho_x_preferred":[
        "\u8fbe\u5fb7\u91cc"
    ],
    "wof:name":"Dadri",
    "wof:placetype":"locality"
},
  "geometry": {"coordinates":[83.57514,26.37633],"type":"Point"}
}