{
  "type": "Feature",
  "properties": {
    "iso:country":"IN",
    "ks:ks_name":"Baniabandha",
    "ks:ks_pop":294,
    "ks:ks_type":"VILLAGE",
    "name:eng_x_preferred":[
        "Baniabandha"
    ],
    "wof:name":"Baniabandha",
    "wof:placetype":"locality",
    "wof:population":294
},
  "geometry": {"coordinates":[84.320589,20.997674],"type":"Point"}
}