{
  "type": "Feature",
  "properties": {
    "iso:country":"IN",
    "ks:ks_name":"Rayanapeta",
    "ks:ks_pop":290,
    "ks:ks_type":"HABITATION",
    "name:eng_x_preferred":[
        "Rayanapeta"
    ],
    "wof:name":"Rayanapeta",
    "wof:placetype":"locality",
    "wof:population":290
},
  "geometry": {"coordinates":[80.595268,18.04809],"type":"Point"}
}