{
  "type": "Feature",
  "properties": {
    "iso:country":"IN",
    "ks:ks_name":"Morewadi",
    "ks:ks_pop":125,
    "ks:ks_type":"HABITATION",
    "name:eng_x_preferred":[
        "Morewadi"
    ],
    "wof:name":"Morewadi",
    "wof:placetype":"locality",
    "wof:population":125
},
  "geometry": {"coordinates":[73.4975,17.499444],"type":"Point"}
}