{
  "type": "Feature",
  "properties": {
    "iso:country":"IN",
    "ks:ks_alt_nam":"NAYA GANJ",
    "ks:ks_name":"Naya Ganj",
    "ks:ks_pop":283,
    "ks:ks_type":"HABITATION",
    "name:eng_x_preferred":[
        "Naya Ganj"
    ],
    "wof:name":"Naya Ganj",
    "wof:placetype":"locality",
    "wof:population":283
},
  "geometry": {"coordinates":[88.00147200000001,26.326172],"type":"Point"}
}