{
  "type": "Feature",
  "properties": {
    "iso:country":"IN",
    "ks:ks_name":"Neelampeta",
    "ks:ks_pop":608,
    "ks:ks_type":"HABITATION",
    "name:eng_x_preferred":[
        "Neelampeta"
    ],
    "wof:name":"Neelampeta",
    "wof:placetype":"locality",
    "wof:population":608
},
  "geometry": {"coordinates":[83.734571,18.15889],"type":"Point"}
}