{
  "type": "Feature",
  "properties": {
    "iso:country":"IN",
    "ks:ks_name":"Banya Kheda",
    "ks:ks_pop":307,
    "ks:ks_type":"VILLAGE",
    "name:eng_x_preferred":[
        "Banya Kheda"
    ],
    "wof:name":"Banya Kheda",
    "wof:placetype":"locality",
    "wof:population":307
},
  "geometry": {"coordinates":[75.00193299999999,23.107065],"type":"Point"}
}