{
  "type": "Feature",
  "properties": {
    "iso:country":"IN",
    "ks:ks_name":"Gulawara",
    "ks:ks_pop":606,
    "ks:ks_type":"VILLAGE",
    "name:eng_x_preferred":[
        "Gulawara"
    ],
    "wof:name":"Gulawara",
    "wof:placetype":"locality",
    "wof:population":606
},
  "geometry": {"coordinates":[82.936818,26.701794],"type":"Point"}
}