{
  "type": "Feature",
  "properties": {
    "gn:admin1_code":"35.0",
    "gn:admin2_code":"424.0",
    "gn:asciiname":"Balwantpura Khas",
    "gn:country_code":"IN",
    "gn:dem":325,
    "gn:feature_class":"P",
    "gn:feature_code":"PPL",
    "gn:name":"Balwantpura Khas",
    "gn:population":0,
    "gn:timezone":"Asia/Kolkata",
    "iso:country":"IN",
    "wof:name":"Balwantpura Khas",
    "wof:placetype":"locality"
},
  "geometry": {"coordinates":[79.07786999999998,24.81759],"type":"Point"}
}