{
  "type": "Feature",
  "properties": {
    "iso:country":"IN",
    "ks:ks_name":"Barkhabal",
    "ks:ks_pop":2364,
    "ks:ks_type":"VILLAGE",
    "ks:ks_uagg_main":0,
    "name:eng_x_preferred":[
        "Barkhabal"
    ],
    "wof:name":"Barkhabal",
    "wof:placetype":"neighbourhood",
    "wof:population":2364
},
  "geometry": {"coordinates":[92.340159,26.418802],"type":"Point"}
}