{
  "type": "Feature",
  "properties": {
    "iso:country":"IN",
    "ks:ks_name":"Bahuda Project",
    "ks:ks_pop":4,
    "ks:ks_type":"HABITATION",
    "name:eng_x_preferred":[
        "Bahuda Project"
    ],
    "wof:name":"Bahuda Project",
    "wof:placetype":"locality",
    "wof:population":4
},
  "geometry": {"coordinates":[78.628838,13.563638],"type":"Point"}
}