{
  "type": "Feature",
  "properties": {
    "iso:country":"IN",
    "ks:ks_name":"Peraniya Dev",
    "ks:ks_pop":284,
    "ks:ks_type":"VILLAGE",
    "name:eng_x_preferred":[
        "Peraniya Dev"
    ],
    "wof:name":"Peraniya Dev",
    "wof:placetype":"locality",
    "wof:population":284
},
  "geometry": {"coordinates":[74.556235,23.272475],"type":"Point"}
}