{
  "type": "Feature",
  "properties": {
    "iso:country":"IN",
    "ks:ks_alt_nam":"paninora2",
    "ks:ks_name":"Paninora2",
    "ks:ks_pop":525,
    "ks:ks_type":"HABITATION",
    "ks:ks_uagg_main":0,
    "name:eng_x_preferred":[
        "Paninora2"
    ],
    "wof:name":"Paninora2",
    "wof:placetype":"neighbourhood",
    "wof:population":525
},
  "geometry": {"coordinates":[94.28097699999999,26.564163],"type":"Point"}
}