{
  "type": "Feature",
  "properties": {
    "iso:country":"IN",
    "ks:ks_name":"Kukurkachua",
    "ks:ks_pop":1405,
    "ks:ks_type":"VILLAGE",
    "name:eng_x_preferred":[
        "Kukurkachua"
    ],
    "wof:name":"Kukurkachua",
    "wof:placetype":"locality",
    "wof:population":1405
},
  "geometry": {"coordinates":[89.534352,26.194476],"type":"Point"}
}