{
  "type": "Feature",
  "properties": {
    "iso:country":"IN",
    "ks:ks_name":"Bamnachamala",
    "ks:ks_pop":119,
    "ks:ks_type":"HABITATION",
    "name:eng_x_preferred":[
        "Bamnachamala"
    ],
    "wof:name":"Bamnachamala",
    "wof:placetype":"locality",
    "wof:population":119
},
  "geometry": {"coordinates":[74.477294,17.517018],"type":"Point"}
}