{
  "type": "Feature",
  "properties": {
    "gn:admin1_code":"12.0",
    "gn:admin2_code":"003",
    "gn:asciiname":"Alchi Goempa",
    "gn:country_code":"IN",
    "gn:dem":3152,
    "gn:feature_class":"P",
    "gn:feature_code":"PPL",
    "gn:name":"Alchi G\u00f6mpa",
    "gn:population":0,
    "gn:timezone":"Asia/Kolkata",
    "iso:country":"IN",
    "name:ben_x_preferred":[
        "\u0986\u09b2\u099a\u09bf \u09ac\u09cc\u09a6\u09cd\u09a7\u09ac\u09bf\u09b9\u09be\u09b0"
    ],
    "name:fra_x_preferred":[
        "Alchi"
    ],
    "name:nld_x_preferred":[
        "Alchi"
    ],
    "name:rus_x_preferred":[
        "\u0410\u043b\u0447\u0438-\u0413\u043e\u043c\u043f\u0430"
    ],
    "name:und_x_variant":[
        "Alchi G\u00f6mpa"
    ],
    "wof:name":"Alchi Goempa",
    "wof:placetype":"locality"
},
  "geometry": {"coordinates":[77.16625999999999,34.23082],"type":"Point"}
}