{
  "type": "Feature",
  "properties": {
    "iso:country":"IN",
    "ks:ks_name":"Kanaula",
    "ks:ks_pop":0,
    "ks:ks_type":"VILLAGE",
    "name:eng_x_preferred":[
        "Kanaula"
    ],
    "wof:name":"Kanaula",
    "wof:placetype":"locality",
    "wof:population":0
},
  "geometry": {"coordinates":[87.012029,24.541625],"type":"Point"}
}