{
  "type": "Feature",
  "properties": {
    "iso:country":"IN",
    "ks:ks_alt_nam":"DIHWA",
    "ks:ks_name":"Dihwa",
    "ks:ks_pop":443,
    "ks:ks_type":"HABITATION",
    "name:eng_x_preferred":[
        "Dihwa"
    ],
    "wof:name":"Dihwa",
    "wof:placetype":"locality",
    "wof:population":443
},
  "geometry": {"coordinates":[82.61030700000001,27.500637],"type":"Point"}
}