{
  "type": "Feature",
  "properties": {
    "gn:admin1_code":"19.0",
    "gn:admin2_code":"563.0",
    "gn:asciiname":"Gunjipal",
    "gn:country_code":"IN",
    "gn:dem":558,
    "gn:feature_class":"P",
    "gn:feature_code":"PPL",
    "gn:name":"Gunjip\u0101l",
    "gn:population":0,
    "gn:timezone":"Asia/Kolkata",
    "iso:country":"IN",
    "ks:ks_name":"Gungipal",
    "ks:ks_pop":36,
    "ks:ks_type":"HABITATION",
    "name:eng_x_preferred":[
        "Gungipal"
    ],
    "name:eng_x_variant":[
        "Gunjipal"
    ],
    "wof:name":"Gungipal",
    "wof:placetype":"locality",
    "wof:population":36
},
  "geometry": {"coordinates":[74.52591700000001,14.793251],"type":"Point"}
}