{
  "type": "Feature",
  "properties": {
    "iso:country":"IN",
    "ks:ks_name":"Parisavaripalem",
    "ks:ks_pop":320,
    "ks:ks_type":"HABITATION",
    "name:eng_x_preferred":[
        "Parisavaripalem"
    ],
    "wof:name":"Parisavaripalem",
    "wof:placetype":"locality",
    "wof:population":320
},
  "geometry": {"coordinates":[80.645831,15.994345],"type":"Point"}
}