{
  "type": "Feature",
  "properties": {
    "gn:admin1_code":"19.0",
    "gn:admin2_code":"563.0",
    "gn:asciiname":"Kammani",
    "gn:country_code":"IN",
    "gn:dem":94,
    "gn:feature_class":"P",
    "gn:feature_code":"PPL",
    "gn:name":"Kamm\u0101ni",
    "gn:population":0,
    "gn:timezone":"Asia/Kolkata",
    "iso:country":"IN",
    "ks:ks_alt_nam":"Kamm\u0101ni",
    "ks:ks_name":"Kammani",
    "ks:ks_pop":184,
    "ks:ks_type":"VILLAGE",
    "name:eng_x_preferred":[
        "Kammani"
    ],
    "name:eng_x_variant":[
        "Kamm\u0101ni"
    ],
    "wof:name":"Kammani",
    "wof:placetype":"locality",
    "wof:population":184
},
  "geometry": {"coordinates":[74.594688,14.707864],"type":"Point"}
}