{
  "type": "Feature",
  "properties": {
    "gn:admin1_code":"12.0",
    "gn:asciiname":"Badhani",
    "gn:country_code":"IN",
    "gn:dem":696,
    "gn:feature_class":"P",
    "gn:feature_code":"PPL",
    "gn:name":"Badh\u0101ni",
    "gn:population":0,
    "gn:timezone":"Asia/Kolkata",
    "iso:country":"IN",
    "name:und_x_variant":[
        "Badh\u0101ni",
        "R\u0101dh\u0101ni"
    ],
    "wof:name":"Badhani",
    "wof:placetype":"locality"
},
  "geometry": {"coordinates":[74.14879999999999,33.18215],"type":"Point"}
}