{
  "type": "Feature",
  "properties": {
    "gn:admin1_code":"36.0",
    "gn:admin2_code":"150.0",
    "gn:asciiname":"Lakheri",
    "gn:country_code":"IN",
    "gn:dem":198,
    "gn:feature_class":"P",
    "gn:feature_code":"PPL",
    "gn:name":"Lakheri",
    "gn:population":0,
    "gn:timezone":"Asia/Kolkata",
    "iso:country":"IN",
    "name:ben_x_preferred":[
        "\u09b2\u09be\u0996\u09c7\u09b0\u09bf"
    ],
    "name:bpy_x_preferred":[
        "\u09b2\u09be\u0996\u09c7\u09b0\u09bf"
    ],
    "name:ceb_x_preferred":[
        "L\u0101kheri"
    ],
    "name:hif_x_preferred":[
        "Lakheri"
    ],
    "name:hin_x_preferred":[
        "\u0932\u093e\u0916\u0947\u0930\u0940"
    ],
    "name:ita_x_preferred":[
        "Lakheri"
    ],
    "name:jpn_x_preferred":[
        "\u30e9\u30fc\u30b1\u30fc\u30ea\u30fc"
    ],
    "name:mlg_x_preferred":[
        "Lakheri"
    ],
    "name:msa_x_preferred":[
        "Lakheri"
    ],
    "name:new_x_preferred":[
        "\u0932\u0916\u0947\u0930\u0940"
    ],
    "name:ori_x_preferred":[
        "\u0b32\u0b3e\u0b16\u0b47\u0b30\u0b3f"
    ],
    "name:por_x_preferred":[
        "Lakheri"
    ],
    "name:swe_x_preferred":[
        "L\u0101kheri"
    ],
    "name:urd_x_preferred":[
        "\u0644\u06a9\u06be\u06cc\u0631\u06cc"
    ],
    "name:vie_x_preferred":[
        "Lakheri"
    ],
    "name:zho_x_preferred":[
        "\u62c9\u51ef\u91cc"
    ],
    "wof:name":"Lakheri",
    "wof:placetype":"locality"
},
  "geometry": {"coordinates":[79.57946,28.83096],"type":"Point"}
}