{
  "type": "Feature",
  "properties": {
    "iso:country":"IN",
    "ks:ks_alt_nam":"pub moirajhar",
    "ks:ks_name":"Pub Moirajhar",
    "ks:ks_pop":1215,
    "ks:ks_type":"HABITATION",
    "name:eng_x_preferred":[
        "Pub Moirajhar"
    ],
    "wof:name":"Pub Moirajhar",
    "wof:placetype":"locality",
    "wof:population":1215
},
  "geometry": {"coordinates":[91.00551900000001,26.514112],"type":"Point"}
}