{
  "type": "Feature",
  "properties": {
    "iso:country":"IN",
    "ks:ks_name":"Venukuram Thanda",
    "ks:ks_pop":162,
    "ks:ks_type":"HABITATION",
    "name:eng_x_preferred":[
        "Venukuram Thanda"
    ],
    "wof:name":"Venukuram Thanda",
    "wof:placetype":"locality",
    "wof:population":162
},
  "geometry": {"coordinates":[79.811939,17.397276],"type":"Point"}
}