{
  "type": "Feature",
  "properties": {
    "iso:country":"IN",
    "ks:ks_name":"Nagla Vrindavan",
    "ks:ks_pop":504,
    "ks:ks_type":"HABITATION",
    "name:eng_x_preferred":[
        "Nagla Vrindavan"
    ],
    "wof:name":"Nagla Vrindavan",
    "wof:placetype":"neighbourhood",
    "wof:population":504
},
  "geometry": {"coordinates":[78.027801,27.101364],"type":"Point"}
}