{
  "type": "Feature",
  "properties": {
    "iso:country":"IN",
    "ks:ks_name":"Chak Shama",
    "ks:ks_pop":549,
    "ks:ks_type":"VILLAGE",
    "name:eng_x_preferred":[
        "Chak Shama"
    ],
    "wof:name":"Chak Shama",
    "wof:placetype":"locality",
    "wof:population":549
},
  "geometry": {"coordinates":[85.197879,25.775809],"type":"Point"}
}