{
  "type": "Feature",
  "properties": {
    "gn:admin1_code":"37",
    "gn:admin2_code":"404.0",
    "gn:asciiname":"Aurabhata",
    "gn:country_code":"IN",
    "gn:dem":361,
    "gn:feature_class":"P",
    "gn:feature_code":"PPL",
    "gn:name":"Aur\u0101bh\u0101t\u0101",
    "gn:population":0,
    "gn:timezone":"Asia/Kolkata",
    "iso:country":"IN",
    "ks:ks_name":"Aurabhatha",
    "ks:ks_pop":64,
    "ks:ks_type":"VILLAGE",
    "name:eng_x_preferred":[
        "Aurabhatha"
    ],
    "name:eng_x_variant":[
        "Aurabhata"
    ],
    "wof:name":"Aurabhatha",
    "wof:placetype":"locality",
    "wof:population":64
},
  "geometry": {"coordinates":[82.29584699999999,22.45752],"type":"Point"}
}