{
  "type": "Feature",
  "properties": {
    "iso:country":"IN",
    "ks:ks_name":"Bhetwalia",
    "ks:ks_pop":959,
    "ks:ks_type":"VILLAGE",
    "ks:ks_uagg_main":0,
    "name:eng_x_preferred":[
        "Bhetwalia"
    ],
    "wof:name":"Bhetwalia",
    "wof:placetype":"neighbourhood",
    "wof:population":959
},
  "geometry": {"coordinates":[84.98648,25.837971],"type":"Point"}
}