{
  "type": "Feature",
  "properties": {
    "iso:country":"IN",
    "ks:ks_name":"Amdega",
    "ks:ks_pop":125,
    "ks:ks_type":"VILLAGE",
    "name:eng_x_preferred":[
        "Amdega"
    ],
    "wof:name":"Amdega",
    "wof:placetype":"locality",
    "wof:population":125
},
  "geometry": {"coordinates":[84.857839,22.792822],"type":"Point"}
}