{
  "type": "Feature",
  "properties": {
    "iso:country":"IN",
    "ks:ks_name":"Syunigaon",
    "ks:ks_pop":98,
    "ks:ks_type":"HABITATION",
    "name:eng_x_preferred":[
        "Syunigaon"
    ],
    "wof:name":"Syunigaon",
    "wof:placetype":"locality",
    "wof:population":98
},
  "geometry": {"coordinates":[79.963984,29.906974],"type":"Point"}
}