{
  "type": "Feature",
  "properties": {
    "iso:country":"IN",
    "ks:ks_name":"Mardwani Ryt",
    "ks:ks_pop":94,
    "ks:ks_type":"VILLAGE",
    "name:eng_x_preferred":[
        "Mardwani Ryt"
    ],
    "wof:name":"Mardwani Ryt",
    "wof:placetype":"locality",
    "wof:population":94
},
  "geometry": {"coordinates":[77.911281,22.0115],"type":"Point"}
}