{
  "type": "Feature",
  "properties": {
    "gn:admin1_code":"40.0",
    "gn:admin2_code":"535",
    "gn:asciiname":"Ittigola",
    "gn:country_code":"IN",
    "gn:dem":534,
    "gn:feature_class":"P",
    "gn:feature_code":"PPL",
    "gn:name":"Ittigola",
    "gn:population":0,
    "gn:timezone":"Asia/Kolkata",
    "iso:country":"IN",
    "wof:name":"Ittigola",
    "wof:placetype":"neighbourhood"
},
  "geometry": {"coordinates":[78.02433000000001,17.78083],"type":"Point"}
}