{
  "type": "Feature",
  "properties": {
    "iso:country":"IN",
    "ks:ks_name":"Krishnapuram",
    "ks:ks_pop":112,
    "ks:ks_type":"HABITATION",
    "name:eng_x_preferred":[
        "Krishnapuram"
    ],
    "wof:name":"Krishnapuram",
    "wof:placetype":"locality",
    "wof:population":112
},
  "geometry": {"coordinates":[79.526915,10.787039],"type":"Point"}
}