{
  "type": "Feature",
  "properties": {
    "iso:country":"IN",
    "ks:ks_alt_nam":"Op\u0101",
    "ks:ks_name":"Opa",
    "ks:ks_pop":716,
    "ks:ks_type":"VILLAGE",
    "ks:ks_uagg_main":0,
    "name:eng_x_preferred":[
        "Opa"
    ],
    "name:eng_x_variant":[
        "Op\u0101"
    ],
    "wof:name":"Opa",
    "wof:placetype":"neighbourhood",
    "wof:population":716
},
  "geometry": {"coordinates":[84.961445,23.512617],"type":"Point"}
}