{
  "type": "Feature",
  "properties": {
    "iso:country":"IN",
    "ks:ks_alt_nam":"DOKABASA",
    "ks:ks_name":"Dokabasa",
    "ks:ks_pop":66,
    "ks:ks_type":"HABITATION",
    "name:eng_x_preferred":[
        "Dokabasa"
    ],
    "wof:name":"Dokabasa",
    "wof:placetype":"locality",
    "wof:population":66
},
  "geometry": {"coordinates":[85.824348,22.657227],"type":"Point"}
}