{
  "type": "Feature",
  "properties": {
    "iso:country":"IN",
    "ks:ks_name":"Dobwadi",
    "ks:ks_pop":59,
    "ks:ks_type":"HABITATION",
    "name:eng_x_preferred":[
        "Dobwadi"
    ],
    "wof:name":"Dobwadi",
    "wof:placetype":"locality",
    "wof:population":59
},
  "geometry": {"coordinates":[73.53196,16.38256],"type":"Point"}
}