{
  "type": "Feature",
  "properties": {
    "iso:country":"IN",
    "ks:ks_name":"Badarpura",
    "ks:ks_pop":667,
    "ks:ks_type":"VILLAGE",
    "name:eng_x_preferred":[
        "Badarpura"
    ],
    "wof:name":"Badarpura",
    "wof:placetype":"locality",
    "wof:population":667
},
  "geometry": {"coordinates":[72.571072,24.017333],"type":"Point"}
}