{
  "type": "Feature",
  "properties": {
    "iso:country":"IN",
    "ks:ks_name":"Kilinjikuppam",
    "ks:ks_pop":832,
    "ks:ks_type":"VILLAGE",
    "ks:ks_uagg_main":0,
    "name:eng_x_preferred":[
        "Kilinjikuppam"
    ],
    "wof:name":"Kilinjikuppam",
    "wof:placetype":"neighbourhood",
    "wof:population":832
},
  "geometry": {"coordinates":[79.773083,11.888768],"type":"Point"}
}