{
  "type": "Feature",
  "properties": {
    "iso:country":"IN",
    "ks:ks_alt_nam":"PADDAKUMAR PARA",
    "ks:ks_name":"Paddakumar Para",
    "ks:ks_pop":155,
    "ks:ks_type":"HABITATION",
    "ks:ks_uagg_main":0,
    "name:eng_x_preferred":[
        "Paddakumar Para"
    ],
    "wof:name":"Paddakumar Para",
    "wof:placetype":"neighbourhood",
    "wof:population":155
},
  "geometry": {"coordinates":[91.421781,23.620116],"type":"Point"}
}