{
  "type": "Feature",
  "properties": {
    "iso:country":"IN",
    "ks:ks_name":"Salapura",
    "ks:ks_pop":17,
    "ks:ks_type":"VILLAGE",
    "ks:ks_uagg_main":0,
    "name:eng_x_preferred":[
        "Salapura"
    ],
    "wof:name":"Salapura",
    "wof:placetype":"neighbourhood",
    "wof:population":17
},
  "geometry": {"coordinates":[76.74587699999999,13.634466],"type":"Point"}
}