{
  "type": "Feature",
  "properties": {
    "gn:admin1_code":"21",
    "gn:admin2_code":"395.0",
    "gn:asciiname":"Parmanandpur",
    "gn:country_code":"IN",
    "gn:dem":264,
    "gn:feature_class":"P",
    "gn:feature_code":"PPL",
    "gn:name":"Parmanandpur",
    "gn:population":0,
    "gn:timezone":"Asia/Kolkata",
    "iso:country":"IN",
    "ks:ks_name":"Paramanandapur",
    "ks:ks_pop":3660,
    "ks:ks_type":"VILLAGE",
    "ks:ks_uagg_main":0,
    "name:eng_x_preferred":[
        "Paramanandapur"
    ],
    "wof:name":"Paramanandapur",
    "wof:placetype":"locality",
    "wof:population":3660
},
  "geometry": {"coordinates":[83.180769,19.924375],"type":"Point"}
}