{
  "type": "Feature",
  "properties": {
    "gn:admin1_code":"34",
    "gn:admin2_code":"233.0",
    "gn:asciiname":"Surkur Khurd",
    "gn:country_code":"IN",
    "gn:dem":357,
    "gn:feature_class":"P",
    "gn:feature_code":"PPL",
    "gn:name":"Surkur Khurd",
    "gn:population":0,
    "gn:timezone":"Asia/Kolkata",
    "iso:country":"IN",
    "ks:ks_name":"Surkur Khurd",
    "ks:ks_type":"VILLAGE",
    "name:eng_x_preferred":[
        "Surkur Khurd"
    ],
    "wof:name":"Surkur Khurd",
    "wof:placetype":"locality"
},
  "geometry": {"coordinates":[83.655334,24.800578],"type":"Point"}
}