{
  "type": "Feature",
  "properties": {
    "iso:country":"IN",
    "ks:ks_name":"Daha Phirojpur",
    "ks:ks_pop":1532,
    "ks:ks_type":"VILLAGE",
    "ks:ks_uagg_main":0,
    "name:eng_x_preferred":[
        "Daha Phirojpur"
    ],
    "wof:name":"Daha Phirojpur",
    "wof:placetype":"neighbourhood",
    "wof:population":1532
},
  "geometry": {"coordinates":[81.998074,26.283424],"type":"Point"}
}