{
  "type": "Feature",
  "properties": {
    "iso:country":"IN",
    "ks:ks_name":"Pundlik Shinde Vasti",
    "ks:ks_pop":140,
    "ks:ks_type":"HABITATION",
    "name:eng_x_preferred":[
        "Pundlik Shinde Vasti"
    ],
    "wof:name":"Pundlik Shinde Vasti",
    "wof:placetype":"locality",
    "wof:population":140
},
  "geometry": {"coordinates":[75.34440600000001,17.002677],"type":"Point"}
}