{
  "type": "Feature",
  "properties": {
    "iso:country":"IN",
    "ks:ks_name":"Kannimarcholai",
    "ks:ks_pop":1505,
    "ks:ks_type":"HABITATION",
    "name:eng_x_preferred":[
        "Kannimarcholai"
    ],
    "wof:name":"Kannimarcholai",
    "wof:placetype":"locality",
    "wof:population":1505
},
  "geometry": {"coordinates":[77.099208,9.621675],"type":"Point"}
}