{
  "type": "Feature",
  "properties": {
    "iso:country":"IN",
    "ks:ks_name":"Malpamunda",
    "ks:ks_pop":500,
    "ks:ks_type":"VILLAGE",
    "name:eng_x_preferred":[
        "Malpamunda"
    ],
    "wof:name":"Malpamunda",
    "wof:placetype":"locality",
    "wof:population":500
},
  "geometry": {"coordinates":[82.861957,20.463562],"type":"Point"}
}