{
  "type": "Feature",
  "properties": {
    "iso:country":"IN",
    "ks:ks_name":"Ajnaur Khas",
    "ks:ks_pop":2480,
    "ks:ks_type":"VILLAGE",
    "name:eng_x_preferred":[
        "Ajnaur Khas"
    ],
    "wof:name":"Ajnaur Khas",
    "wof:placetype":"locality",
    "wof:population":2480
},
  "geometry": {"coordinates":[78.94138599999999,24.611814],"type":"Point"}
}