{
  "type": "Feature",
  "properties": {
    "iso:country":"IN",
    "ks:ks_name":"Patilwasti",
    "ks:ks_pop":176,
    "ks:ks_type":"HABITATION",
    "name:eng_x_preferred":[
        "Patilwasti"
    ],
    "wof:name":"Patilwasti",
    "wof:placetype":"locality",
    "wof:population":176
},
  "geometry": {"coordinates":[74.12203,17.989276],"type":"Point"}
}