{
  "type": "Feature",
  "properties": {
    "iso:country":"IN",
    "ks:ks_name":"Safapani",
    "ks:ks_pop":451,
    "ks:ks_type":"HABITATION",
    "name:eng_x_preferred":[
        "Safapani"
    ],
    "wof:name":"Safapani",
    "wof:placetype":"locality",
    "wof:population":451
},
  "geometry": {"coordinates":[93.770444,26.206527],"type":"Point"}
}