{
  "type": "Feature",
  "properties": {
    "iso:country":"IN",
    "ks:ks_alt_nam":"sarsa",
    "ks:ks_name":"Sarsa",
    "ks:ks_pop":346,
    "ks:ks_type":"HABITATION",
    "name:eng_x_preferred":[
        "Sarsa"
    ],
    "wof:name":"Sarsa",
    "wof:placetype":"locality",
    "wof:population":346
},
  "geometry": {"coordinates":[86.840598,24.411715],"type":"Point"}
}