{
  "type": "Feature",
  "properties": {
    "gn:admin1_code":"35",
    "gn:admin2_code":"423.0",
    "gn:asciiname":"Machhaoli",
    "gn:country_code":"IN",
    "gn:dem":255,
    "gn:feature_class":"P",
    "gn:feature_code":"PPL",
    "gn:name":"Machh\u0101oli",
    "gn:population":0,
    "gn:timezone":"Asia/Kolkata",
    "iso:country":"IN",
    "wof:name":"Machhaoli",
    "wof:placetype":"locality"
},
  "geometry": {"coordinates":[78.18590999999998,25.52726],"type":"Point"}
}