{
  "type": "Feature",
  "properties": {
    "gn:admin1_code":"37",
    "gn:admin2_code":"406.0",
    "gn:asciiname":"Bhawradih",
    "gn:country_code":"IN",
    "gn:dem":264,
    "gn:feature_class":"P",
    "gn:feature_code":"PPL",
    "gn:name":"Bhawr\u0101d\u012bh",
    "gn:population":0,
    "gn:timezone":"Asia/Kolkata",
    "iso:country":"IN",
    "ks:ks_alt_nam":"BHOURADIH",
    "ks:ks_name":"Bhouradih",
    "ks:ks_pop":558,
    "ks:ks_type":"HABITATION",
    "name:eng_x_preferred":[
        "Bhouradih"
    ],
    "name:eng_x_variant":[
        "Bhawradih"
    ],
    "wof:name":"Bhouradih",
    "wof:placetype":"locality",
    "wof:population":558
},
  "geometry": {"coordinates":[82.36082399999999,22.141574],"type":"Point"}
}