{
  "type": "Feature",
  "properties": {
    "iso:country":"IN",
    "ks:ks_name":"Panavayal",
    "ks:ks_pop":20,
    "ks:ks_type":"HABITATION",
    "name:eng_x_preferred":[
        "Panavayal"
    ],
    "wof:name":"Panavayal",
    "wof:placetype":"locality",
    "wof:population":20
},
  "geometry": {"coordinates":[78.708063,10.321093],"type":"Point"}
}