{
  "type": "Feature",
  "properties": {
    "gn:admin1_code":"24.0",
    "gn:admin2_code":"117.0",
    "gn:asciiname":"Isri",
    "gn:country_code":"IN",
    "gn:dem":377,
    "gn:feature_class":"P",
    "gn:feature_code":"PPL",
    "gn:name":"Isri",
    "gn:population":0,
    "gn:timezone":"Asia/Kolkata",
    "iso:country":"IN",
    "name:bih_x_preferred":[
        "\u0907\u0938\u0930\u0940"
    ],
    "name:bpy_x_preferred":[
        "\u0987\u09b8\u09b0\u09bf"
    ],
    "name:ita_x_preferred":[
        "Isri"
    ],
    "name:msa_x_preferred":[
        "Isri"
    ],
    "name:new_x_preferred":[
        "\u0907\u0938\u094d\u0930\u0940"
    ],
    "name:nld_x_preferred":[
        "Isri"
    ],
    "name:por_x_preferred":[
        "Isri"
    ],
    "name:vie_x_preferred":[
        "Isri"
    ],
    "name:zho_x_preferred":[
        "\u4f0a\u65af\u91cc"
    ],
    "wof:name":"Isri",
    "wof:placetype":"locality"
},
  "geometry": {"coordinates":[72.81164,24.73415],"type":"Point"}
}