{
  "type": "Feature",
  "properties": {
    "gn:admin1_code":"21.0",
    "gn:admin2_code":"381",
    "gn:asciiname":"Bandha Chhada",
    "gn:country_code":"IN",
    "gn:dem":21,
    "gn:feature_class":"P",
    "gn:feature_code":"PPL",
    "gn:name":"Bandha Chhada",
    "gn:population":0,
    "gn:timezone":"Asia/Kolkata",
    "iso:country":"IN",
    "wof:name":"Bandha Chhada",
    "wof:placetype":"locality"
},
  "geometry": {"coordinates":[85.88333,20.36667000000001],"type":"Point"}
}