{
  "type": "Feature",
  "properties": {
    "gn:admin1_code":"34.0",
    "gn:admin2_code":"222.0",
    "gn:asciiname":"Ahmadpur",
    "gn:country_code":"IN",
    "gn:dem":46,
    "gn:feature_class":"P",
    "gn:feature_code":"PPL",
    "gn:name":"Ahmadpur",
    "gn:population":0,
    "gn:timezone":"Asia/Kolkata",
    "iso:country":"IN",
    "ks:ks_name":"Ahmadpur",
    "ks:ks_pop":326,
    "ks:ks_type":"VILLAGE",
    "ks:ks_uagg_main":0,
    "name:eng_x_preferred":[
        "Ahmadpur"
    ],
    "wof:name":"Ahmadpur",
    "wof:placetype":"neighbourhood",
    "wof:population":326
},
  "geometry": {"coordinates":[86.24014699999999,25.602043],"type":"Point"}
}