{
  "type": "Feature",
  "properties": {
    "gn:admin1_code":"35.0",
    "gn:admin2_code":"447.0",
    "gn:asciiname":"Imlikhera",
    "gn:country_code":"IN",
    "gn:dem":458,
    "gn:feature_class":"P",
    "gn:feature_code":"PPL",
    "gn:name":"Iml\u012bkhera",
    "gn:population":0,
    "gn:timezone":"Asia/Kolkata",
    "iso:country":"IN",
    "wof:name":"Imlikhera",
    "wof:placetype":"locality"
},
  "geometry": {"coordinates":[78.18318000000002,22.23678],"type":"Point"}
}