{
  "type": "Feature",
  "properties": {
    "iso:country":"IN",
    "ks:ks_name":"Dubari Kala",
    "ks:ks_pop":831,
    "ks:ks_type":"HABITATION",
    "name:eng_x_preferred":[
        "Dubari Kala"
    ],
    "wof:name":"Dubari Kala",
    "wof:placetype":"locality",
    "wof:population":831
},
  "geometry": {"coordinates":[81.53296899999999,24.002929],"type":"Point"}
}