{
  "type": "Feature",
  "properties": {
    "iso:country":"IN",
    "ks:ks_name":"Sukni",
    "ks:ks_pop":192,
    "ks:ks_type":"HABITATION",
    "name:eng_x_preferred":[
        "Sukni"
    ],
    "wof:name":"Sukni",
    "wof:placetype":"locality",
    "wof:population":192
},
  "geometry": {"coordinates":[79.99560700000001,29.189906],"type":"Point"}
}