{
  "type": "Feature",
  "properties": {
    "iso:country":"IN",
    "ks:ks_name":"Tarapur",
    "ks:ks_pop":2996,
    "ks:ks_type":"VILLAGE",
    "ks:ks_uagg_main":0,
    "name:eng_x_preferred":[
        "Tarapur"
    ],
    "name:hin_x_preferred":[
        "\u0924\u093e\u0930\u093e\u092a\u0941\u0930"
    ],
    "wof:name":"Tarapur",
    "wof:placetype":"neighbourhood",
    "wof:population":2996
},
  "geometry": {"coordinates":[92.56126500000001,24.965951],"type":"Point"}
}