{
  "type": "Feature",
  "properties": {
    "gn:admin1_code":"36",
    "gn:admin2_code":"194.0",
    "gn:asciiname":"Tait",
    "gn:country_code":"IN",
    "gn:dem":86,
    "gn:feature_class":"P",
    "gn:feature_code":"PPL",
    "gn:name":"Tait",
    "gn:population":0,
    "gn:timezone":"Asia/Kolkata",
    "iso:country":"IN",
    "name:deu_x_preferred":[
        "Tait"
    ],
    "name:fra_x_preferred":[
        "Tait"
    ],
    "name:jpn_x_preferred":[
        "\u30c6\u30a4\u30c8"
    ],
    "name:pol_x_preferred":[
        "Tait"
    ],
    "name:spa_x_preferred":[
        "Tait"
    ],
    "name:swe_x_preferred":[
        "Tait"
    ],
    "wof:name":"Tait",
    "wof:placetype":"neighbourhood"
},
  "geometry": {"coordinates":[82.70044,25.53707],"type":"Point"}
}