{
  "type": "Feature",
  "properties": {
    "iso:country":"IN",
    "ks:ks_name":"Kanpala",
    "ks:ks_pop":215,
    "ks:ks_type":"VILLAGE",
    "name:eng_x_preferred":[
        "Kanpala"
    ],
    "wof:name":"Kanpala",
    "wof:placetype":"locality",
    "wof:population":215
},
  "geometry": {"coordinates":[83.01097799999999,21.155583],"type":"Point"}
}