{
  "type": "Feature",
  "properties": {
    "gn:admin1_code":"35.0",
    "gn:admin2_code":"424.0",
    "gn:asciiname":"Karmauriyakhera",
    "gn:country_code":"IN",
    "gn:dem":310,
    "gn:feature_class":"P",
    "gn:feature_code":"PPL",
    "gn:name":"Karmauriy\u0101khera",
    "gn:population":0,
    "gn:timezone":"Asia/Kolkata",
    "iso:country":"IN",
    "wof:name":"Karmauriyakhera",
    "wof:placetype":"locality"
},
  "geometry": {"coordinates":[79.21183000000001,24.70086],"type":"Point"}
}