{
  "type": "Feature",
  "properties": {
    "gn:admin1_code":"10",
    "gn:admin2_code":"87.0",
    "gn:asciiname":"Biharipur",
    "gn:country_code":"IN",
    "gn:dem":201,
    "gn:feature_class":"P",
    "gn:feature_code":"PPL",
    "gn:name":"Bih\u0101r\u012bpur",
    "gn:population":0,
    "gn:timezone":"Asia/Kolkata",
    "iso:country":"IN",
    "wof:name":"Biharipur",
    "wof:placetype":"locality"
},
  "geometry": {"coordinates":[77.01841999999998,27.8564],"type":"Point"}
}