{
  "type": "Feature",
  "properties": {
    "iso:country":"IN",
    "ks:ks_alt_nam":"Naua Sh\u0101hmal",
    "ks:ks_name":"Naua Shahmal",
    "ks:ks_pop":0,
    "ks:ks_type":"VILLAGE",
    "name:eng_x_preferred":[
        "Naua Shahmal"
    ],
    "name:eng_x_variant":[
        "Naua Sh\u0101hmal"
    ],
    "wof:name":"Naua Shahmal",
    "wof:placetype":"locality",
    "wof:population":0
},
  "geometry": {"coordinates":[83.578779,25.087795],"type":"Point"}
}