{
  "type": "Feature",
  "properties": {
    "iso:country":"IN",
    "ks:ks_name":"Totapada",
    "ks:ks_pop":498,
    "ks:ks_type":"VILLAGE",
    "ks:ks_uagg_main":0,
    "name:eng_x_preferred":[
        "Totapada"
    ],
    "wof:name":"Totapada",
    "wof:placetype":"neighbourhood",
    "wof:population":498
},
  "geometry": {"coordinates":[85.185974,19.720827],"type":"Point"}
}