{
  "type": "Feature",
  "properties": {
    "gn:admin1_code":"24.0",
    "gn:admin2_code":"107.0",
    "gn:asciiname":"Sahjanpur Ka Pura",
    "gn:country_code":"IN",
    "gn:dem":224,
    "gn:feature_class":"P",
    "gn:feature_code":"PPL",
    "gn:name":"Sahjanpur Ka Pura",
    "gn:population":0,
    "gn:timezone":"Asia/Kolkata",
    "iso:country":"IN",
    "wof:name":"Sahjanpur Ka Pura",
    "wof:placetype":"locality"
},
  "geometry": {"coordinates":[76.89960000000001,26.75658],"type":"Point"}
}