{
  "type": "Feature",
  "properties": {
    "iso:country":"IN",
    "ks:ks_name":"Ramdev Nagar",
    "ks:ks_pop":432,
    "ks:ks_type":"VILLAGE",
    "name:eng_x_preferred":[
        "Ramdev Nagar"
    ],
    "wof:name":"Ramdev Nagar",
    "wof:placetype":"locality",
    "wof:population":432
},
  "geometry": {"coordinates":[71.28879999999999,25.185844],"type":"Point"}
}