{
  "type": "Feature",
  "properties": {
    "iso:country":"IN",
    "ks:ks_name":"Dhoparkhol",
    "ks:ks_pop":145,
    "ks:ks_type":"HABITATION",
    "name:eng_x_preferred":[
        "Dhoparkhol"
    ],
    "wof:name":"Dhoparkhol",
    "wof:placetype":"locality",
    "wof:population":145
},
  "geometry": {"coordinates":[73.46555600000001,17.240833],"type":"Point"}
}