{
  "type": "Feature",
  "properties": {
    "iso:country":"IN",
    "ks:ks_name":"Thubbacombai",
    "ks:ks_pop":390,
    "ks:ks_type":"HABITATION",
    "name:eng_x_preferred":[
        "Thubbacombai"
    ],
    "wof:name":"Thubbacombai",
    "wof:placetype":"locality",
    "wof:population":390
},
  "geometry": {"coordinates":[76.894493,11.398583],"type":"Point"}
}