{
  "type": "Feature",
  "properties": {
    "iso:country":"IN",
    "name:ast_x_preferred":[
        "Nimaj"
    ],
    "name:ceb_x_preferred":[
        "Nimb\u0101j"
    ],
    "name:eng_x_preferred":[
        "Nimaj"
    ],
    "name:hin_x_preferred":[
        "\u0928\u093f\u092e\u093e\u091c"
    ],
    "name:nld_x_preferred":[
        "Nimaj"
    ],
    "name:swe_x_preferred":[
        "Nimb\u0101j"
    ],
    "qs:name":"Nimaj",
    "qs:name_adm0":"India",
    "qs:name_adm1":"Rajasthan",
    "qs:photos":95,
    "qs:photos_1k":19,
    "qs:photos_9k":1,
    "qs:photos_9r":3,
    "qs:photos_all":95,
    "qs:photos_sr":3,
    "qs:placetype":"Town",
    "qs:pop_sr":"0",
    "wd:elevation":315.0,
    "wd:wordcount":309,
    "wof:name":"Nimaj",
    "wof:placetype":"locality"
},
  "geometry": {"coordinates":[74.00270399999999,26.15003],"type":"Point"}
}