{
  "type": "Feature",
  "properties": {
    "iso:country":"IN",
    "name:ara_x_preferred":[
        "\u0645\u0643\u062a\u0628 \u062f\u0627\u0644\u0647\u0648\u0632\u064a \u0643\u0627\u0646\u062a\u0648\u0646\u0645\u064a\u0646\u062a \u0627\u0644\u062d\u0643\u0648\u0645\u064a"
    ],
    "name:ben_bn_x_preferred":[
        "\u09a1\u09be\u09b2\u09b9\u09be\u0989\u09b8\u09bf \u0995\u09cd\u09af\u09be\u09a8\u09cd\u099f\u09a8\u09ae\u09c7\u09a8\u09cd\u099f"
    ],
    "name:ben_in_x_preferred":[
        "\u09a1\u09be\u09b2\u09b9\u09be\u0989\u09b8\u09bf \u0995\u09cd\u09af\u09be\u09a8\u09cd\u099f\u09a8\u09ae\u09c7\u09a8\u09cd\u099f"
    ],
    "name:ben_x_preferred":[
        "\u09a1\u09be\u09b2\u09b9\u09cc\u09b8\u09bf \u09b8\u09c7\u09a8\u09be\u09a8\u09bf\u09ac\u09be\u09b8"
    ],
    "name:bpy_x_preferred":[
        "\u09a6\u09be\u09b2\u09b9\u09cc\u09b8\u09bf \u09b8\u09c7\u09a8\u09be\u09a8\u09bf\u09ac\u09be\u09b8"
    ],
    "name:eng_x_preferred":[
        "Dalhousie Cantonment"
    ],
    "name:guj_x_preferred":[
        "\u0aa1\u0abe\u0ab2\u0ab9\u0acc\u0ab8\u0ac0 \u0a95\u0ac7\u0aa8\u0acd\u0a9f\u0acb\u0aa8\u0aae\u0ac7\u0aa8\u0acd\u0a9f"
    ],
    "name:hin_x_preferred":[
        "\u0921\u0932\u0939\u094c\u095b\u0940 \u0915\u0948\u0902\u091f\u0949\u0928\u094d\u092e\u0947\u0902\u091f"
    ],
    "name:ita_x_preferred":[
        "Dalhousie"
    ],
    "name:kan_x_preferred":[
        "\u0ca1\u0cbe\u0cb2\u0ccd"
    ],
    "name:mal_x_preferred":[
        "\u0d21\u0d7d\u0d39\u0d57\u0d38\u0d3f \u0d15\u0d28\u0d4d\u0d31\u0d4b\u0d7a\u0d2e\u0d46\u0d28\u0d4d\u0d31\u0d4d"
    ],
    "name:mar_x_preferred":[
        "\u0921\u0932\u0939\u094c\u0938\u0940 \u0915\u0945\u0928\u094d\u091f\u094b\u0928\u094d\u092e\u0947\u0902\u091f"
    ],
    "name:nld_x_preferred":[
        "Dalhousie Cantonment"
    ],
    "name:pan_x_preferred":[
        "\u0a21\u0a32\u0a39\u0a4c\u0a1c\u0a3c\u0a40 \u0a15\u0a48\u0a02\u0a1f\u0a4c\u0a28\u0a2e\u0a48\u0a02\u0a1f"
    ],
    "name:tam_x_preferred":[
        "\u0b9f\u0bb2\u0bcd\u0bb9\u0bcc\u0b9a\u0bbf \u0bae\u0bc1\u0b95\u0bbe\u0bae\u0bcd"
    ],
    "name:tel_x_preferred":[
        "\u0c21\u0c32\u0c4d\u0c39\u0c4c\u0c38\u0c40 \u0c15\u0c02\u0c1f\u0c4b\u0c28\u0c4d\u0c2e\u0c46\u0c02\u0c1f\u0c4d"
    ],
    "name:urd_x_preferred":[
        "\u0688\u0644\u06c1\u0648\u0632\u06cc \u0686\u06be\u0627\u0624\u0646\u06cc"
    ],
    "qs:gn_local":0,
    "qs:local_max":181,
    "qs:local_sum":219,
    "qs:localhoods":3,
    "qs:name":"Dalhousie Cantonment",
    "qs:name_adm0":"India",
    "qs:name_adm1":"Himachal Pradesh",
    "qs:name_adm2":"Chamba",
    "qs:name_local":"Dalhousie",
    "qs:photo_max":4,
    "qs:photo_sum":10,
    "qs:placetype":"Suburb",
    "qs:quad_count":5,
    "qs:woe_adm0":23424848,
    "qs:woe_adm1":2345745,
    "qs:woe_adm2":24505129,
    "qs:woe_lau":0,
    "qs:woe_local":2290562,
    "qs:woe_ver":"7.10.0",
    "wd:wordcount":625,
    "wof:lang":[
        "eng"
    ],
    "wof:name":"Dalhousie Cantonment",
    "wof:placetype":"neighbourhood"
},
  "geometry": {"coordinates":[75.96661400000001,32.54774],"type":"Point"}
}