{
  "type": "Feature",
  "properties": {
    "iso:country":"IN",
    "name:ben_x_preferred":[
        "\u09a1\u09be\u09b2\u09b9\u09cc\u09b8\u09bf \u09b8\u09c7\u09a8\u09be\u09a8\u09bf\u09ac\u09be\u09b8"
    ],
    "name:bpy_x_preferred":[
        "\u09a6\u09be\u09b2\u09b9\u09cc\u09b8\u09bf \u09b8\u09c7\u09a8\u09be\u09a8\u09bf\u09ac\u09be\u09b8"
    ],
    "name:eng_x_preferred":[
        "Dalhousie Cantonment"
    ],
    "name:ita_x_preferred":[
        "Dalhousie"
    ],
    "name:nld_x_preferred":[
        "Dalhousie Cantonment"
    ],
    "name:unk_x_variant":[
        "Dalhousie Cantonment"
    ],
    "qs:gn_local":0,
    "qs:local_max":181,
    "qs:local_sum":219,
    "qs:localhoods":3,
    "qs:name":"Dalhousie Cantonment",
    "qs:name_adm0":"India",
    "qs:name_adm1":"Himachal Pradesh",
    "qs:name_adm2":"Chamba",
    "qs:name_local":"Dalhousie",
    "qs:photo_max":4,
    "qs:photo_sum":10,
    "qs:placetype":"Suburb",
    "qs:quad_count":5,
    "qs:woe_adm0":23424848,
    "qs:woe_adm1":2345745,
    "qs:woe_adm2":24505129,
    "qs:woe_lau":0,
    "qs:woe_local":2290562,
    "qs:woe_ver":"7.10.0",
    "wd:wordcount":625,
    "wof:lang":[
        "eng"
    ],
    "wof:name":"Dalhousie Cantonment",
    "wof:placetype":"neighbourhood"
},
  "geometry": {"coordinates":[75.96661400000001,32.54774],"type":"Point"}
}