{
  "type": "Feature",
  "properties": {
    "iso:country":"IN",
    "ks:ks_name":"Bhatkayasthan",
    "ks:ks_pop":12,
    "ks:ks_type":"HABITATION",
    "name:eng_x_preferred":[
        "Bhatkayasthan"
    ],
    "wof:name":"Bhatkayasthan",
    "wof:placetype":"locality",
    "wof:population":12
},
  "geometry": {"coordinates":[81.670383,24.72074],"type":"Point"}
}