{
  "type": "Feature",
  "properties": {
    "gn:admin1_code":"2.0",
    "gn:admin2_code":"543.0",
    "gn:asciiname":"Madalangi",
    "gn:country_code":"IN",
    "gn:dem":132,
    "gn:feature_class":"P",
    "gn:feature_code":"PPL",
    "gn:name":"M\u0101dalangi",
    "gn:population":0,
    "gn:timezone":"Asia/Kolkata",
    "iso:country":"IN",
    "wof:name":"Madalangi",
    "wof:placetype":"locality"
},
  "geometry": {"coordinates":[83.49566999999998,18.89621],"type":"Point"}
}