{
  "type": "Feature",
  "properties": {
    "iso:country":"IN",
    "ks:ks_name":"Upartapanda",
    "ks:ks_pop":677,
    "ks:ks_type":"VILLAGE",
    "ks:ks_uagg_main":0,
    "name:eng_x_preferred":[
        "Upartapanda"
    ],
    "wof:name":"Upartapanda",
    "wof:placetype":"neighbourhood",
    "wof:population":677
},
  "geometry": {"coordinates":[87.062941,21.681001],"type":"Point"}
}