{
  "type": "Feature",
  "properties": {
    "gn:admin1_code":"34.0",
    "gn:admin2_code":"221.0",
    "gn:asciiname":"Kawas Nizamat",
    "gn:country_code":"IN",
    "gn:dem":49,
    "gn:feature_class":"P",
    "gn:feature_code":"PPL",
    "gn:name":"Kaw\u0101s Niz\u0101mat",
    "gn:population":0,
    "gn:timezone":"Asia/Kolkata",
    "iso:country":"IN",
    "ks:ks_name":"Kewas Nizamat",
    "ks:ks_pop":5204,
    "ks:ks_type":"VILLAGE",
    "name:eng_x_preferred":[
        "Kewas Nizamat"
    ],
    "name:eng_x_variant":[
        "Kawas Nizamat"
    ],
    "wof:name":"Kewas Nizamat",
    "wof:placetype":"locality",
    "wof:population":5204
},
  "geometry": {"coordinates":[85.863463,25.833222],"type":"Point"}
}