{
  "type": "Feature",
  "properties": {
    "gn:country":"IN",
    "gn:fcode":"PPL",
    "gn:population":10000,
    "iso:country":"IN",
    "name:ast_x_preferred":[
        "Vadlamuru"
    ],
    "name:bul_x_preferred":[
        "\u0412\u0430\u0434\u043b\u0430\u043c\u0443\u0440\u0443"
    ],
    "name:ceb_x_preferred":[
        "Vadlamuru"
    ],
    "name:eng_x_preferred":[
        "Vadlamuru"
    ],
    "name:nld_x_preferred":[
        "Vadlamuru"
    ],
    "name:swe_x_preferred":[
        "Vadlamuru"
    ],
    "name:tel_x_preferred":[
        "\u0c35\u0c21\u0c4d\u0c32\u0c2e\u0c42\u0c30\u0c41"
    ],
    "qs:name":"Vadlamuru",
    "qs:name_adm0":"India",
    "qs:name_adm1":"Andhra Pradesh",
    "qs:photos_9k":1,
    "qs:photos_9r":2,
    "qs:photos_all":27,
    "qs:photos_sr":0,
    "qs:placetype":"Town",
    "qs:pop_sr":"5",
    "wd:wordcount":16,
    "wof:name":"Vadlamuru",
    "wof:placetype":"locality",
    "wof:population":10000
},
  "geometry": {"coordinates":[82.16565,17.09545],"type":"Point"}
}