{
  "type": "Feature",
  "properties": {
    "iso:country":"IN",
    "ks:ks_name":"Bhasho",
    "ks:ks_pop":66,
    "ks:ks_type":"VILLAGE",
    "name:eng_x_preferred":[
        "Bhasho"
    ],
    "wof:name":"Bhasho",
    "wof:placetype":"locality",
    "wof:population":66
},
  "geometry": {"coordinates":[78.49069299999999,30.287838],"type":"Point"}
}