{
  "type": "Feature",
  "properties": {
    "iso:country":"IN",
    "ks:ks_name":"Pipariya",
    "ks:ks_pop":36,
    "ks:ks_type":"HABITATION",
    "name:eng_x_preferred":[
        "Pipariya"
    ],
    "wof:name":"Pipariya",
    "wof:placetype":"locality",
    "wof:population":36
},
  "geometry": {"coordinates":[80.46368200000001,24.595296],"type":"Point"}
}