{
  "type": "Feature",
  "properties": {
    "gn:admin1_code":"11.0",
    "gn:admin2_code":"33.0",
    "gn:asciiname":"Soi",
    "gn:country_code":"IN",
    "gn:dem":1883,
    "gn:feature_class":"P",
    "gn:feature_code":"PPL",
    "gn:name":"Soi",
    "gn:population":0,
    "gn:timezone":"Asia/Kolkata",
    "iso:country":"IN",
    "name:ara_x_preferred":[
        "\u0633\u0648\u064a"
    ],
    "name:deu_x_preferred":[
        "Soi"
    ],
    "name:fra_x_preferred":[
        "Soi"
    ],
    "name:nld_x_preferred":[
        "Soi"
    ],
    "name:nor_x_preferred":[
        "Soi"
    ],
    "wof:name":"Soi",
    "wof:placetype":"locality"
},
  "geometry": {"coordinates":[77.34402,31.17969],"type":"Point"}
}