{
  "type": "Feature",
  "properties": {
    "iso:country":"IN",
    "ks:ks_name":"Orabari",
    "ks:ks_pop":273,
    "ks:ks_type":"VILLAGE",
    "ks:ks_uagg_main":0,
    "name:eng_x_preferred":[
        "Orabari"
    ],
    "wof:name":"Orabari",
    "wof:placetype":"neighbourhood",
    "wof:population":273
},
  "geometry": {"coordinates":[86.115624,20.523135],"type":"Point"}
}