{
  "type": "Feature",
  "properties": {
    "iso:country":"IN",
    "ks:ks_name":"Chak Bijai",
    "ks:ks_type":"VILLAGE",
    "ks:ks_uagg_main":0,
    "name:eng_x_preferred":[
        "Chak Bijai"
    ],
    "wof:name":"Chak Bijai",
    "wof:placetype":"locality"
},
  "geometry": {"coordinates":[82.411703,25.291481],"type":"Point"}
}