{
  "type": "Feature",
  "properties": {
    "iso:country":"IN",
    "ks:ks_alt_nam":"Bhogabanpur Punjee Pt II",
    "ks:ks_name":"Bhogabanpur Punjee Pt Ii",
    "ks:ks_pop":196,
    "ks:ks_type":"HABITATION",
    "name:eng_x_preferred":[
        "Bhogabanpur Punjee Pt Ii"
    ],
    "wof:name":"Bhogabanpur Punjee Pt Ii",
    "wof:placetype":"locality",
    "wof:population":196
},
  "geometry": {"coordinates":[92.52000099999999,24.388809],"type":"Point"}
}