{
  "type": "Feature",
  "properties": {
    "iso:country":"IN",
    "ks:ks_alt_nam":"PACHU BIGHA",
    "ks:ks_name":"Pachu Bigha",
    "ks:ks_pop":606,
    "ks:ks_type":"HABITATION",
    "name:eng_x_preferred":[
        "Pachu Bigha"
    ],
    "wof:name":"Pachu Bigha",
    "wof:placetype":"locality",
    "wof:population":606
},
  "geometry": {"coordinates":[85.39171899999999,24.885529],"type":"Point"}
}