{
  "type": "Feature",
  "properties": {
    "gn:admin1_code":"2.0",
    "gn:admin2_code":"542",
    "gn:asciiname":"Chinna Palipeta",
    "gn:cc2":"IN",
    "gn:country_code":"IN",
    "gn:dem":6,
    "gn:feature_class":"P",
    "gn:feature_code":"PPL",
    "gn:name":"Chinna P\u0101lipeta",
    "gn:population":0,
    "gn:timezone":"Asia/Kolkata",
    "iso:country":"IN",
    "name:und_x_variant":[
        "Chinnapalli Petta",
        "Chinna P\u0101lipeta"
    ],
    "wof:name":"Chinna Palipeta",
    "wof:placetype":"locality"
},
  "geometry": {"coordinates":[84.11667,18.33333],"type":"Point"}
}