{
  "type": "Feature",
  "properties": {
    "iso:country":"IN",
    "ks:ks_name":"Tossipudi",
    "ks:ks_pop":2247,
    "ks:ks_type":"VILLAGE",
    "ks:ks_uagg_main":0,
    "name:eng_x_preferred":[
        "Tossipudi"
    ],
    "wof:name":"Tossipudi",
    "wof:placetype":"neighbourhood",
    "wof:population":2247
},
  "geometry": {"coordinates":[82.011228,16.928384],"type":"Point"}
}