{
  "type": "Feature",
  "properties": {
    "iso:country":"IN",
    "ks:ks_alt_nam":"Jhana tola",
    "ks:ks_name":"Jhana Tola",
    "ks:ks_pop":1326,
    "ks:ks_type":"HABITATION",
    "ks:ks_uagg_main":0,
    "name:eng_x_preferred":[
        "Jhana Tola"
    ],
    "wof:name":"Jhana Tola",
    "wof:placetype":"neighbourhood",
    "wof:population":1326
},
  "geometry": {"coordinates":[87.46084399999999,26.236075],"type":"Point"}
}