{
  "type": "Feature",
  "properties": {
    "gn:admin1_code":"36.0",
    "gn:admin2_code":"170.0",
    "gn:asciiname":"Gonda",
    "gn:country_code":"IN",
    "gn:dem":155,
    "gn:feature_class":"P",
    "gn:feature_code":"PPL",
    "gn:name":"Gonda",
    "gn:population":0,
    "gn:timezone":"Asia/Kolkata",
    "iso:country":"IN",
    "wof:name":"Gonda",
    "wof:placetype":"locality"
},
  "geometry": {"coordinates":[80.74039,25.20501],"type":"Point"}
}