{
  "type": "Feature",
  "properties": {
    "gn:admin1_code":"35.0",
    "gn:admin2_code":"461",
    "gn:asciiname":"Chilpa",
    "gn:country_code":"IN",
    "gn:dem":541,
    "gn:feature_class":"P",
    "gn:feature_code":"PPL",
    "gn:name":"Chilpa",
    "gn:population":0,
    "gn:timezone":"Asia/Kolkata",
    "iso:country":"IN",
    "wof:name":"Chilpa",
    "wof:placetype":"locality"
},
  "geometry": {"coordinates":[81.82123,23.24976],"type":"Point"}
}