{
  "type": "Feature",
  "properties": {
    "iso:country":"IN",
    "ks:ks_name":"Naraharimunda",
    "ks:ks_pop":132,
    "ks:ks_type":"VILLAGE",
    "name:eng_x_preferred":[
        "Naraharimunda"
    ],
    "wof:name":"Naraharimunda",
    "wof:placetype":"locality",
    "wof:population":132
},
  "geometry": {"coordinates":[87.276505,22.065079],"type":"Point"}
}