{
  "type": "Feature",
  "properties": {
    "gn:admin1_code":"24.0",
    "gn:admin2_code":"122.0",
    "gn:asciiname":"Mokhampura",
    "gn:country_code":"IN",
    "gn:dem":526,
    "gn:feature_class":"P",
    "gn:feature_code":"PPL",
    "gn:name":"Mokhampura",
    "gn:population":0,
    "gn:timezone":"Asia/Kolkata",
    "iso:country":"IN",
    "wof:name":"Mokhampura",
    "wof:placetype":"locality"
},
  "geometry": {"coordinates":[74.23007,25.42376],"type":"Point"}
}