{
  "type": "Feature",
  "properties": {
    "gn:admin1_code":"23.0",
    "gn:admin2_code":"45.0",
    "gn:asciiname":"Hari Nau",
    "gn:country_code":"IN",
    "gn:dem":207,
    "gn:feature_class":"P",
    "gn:feature_code":"PPL",
    "gn:name":"Hari N\u0101u",
    "gn:population":0,
    "gn:timezone":"Asia/Kolkata",
    "iso:country":"IN",
    "wof:name":"Hari Nau",
    "wof:placetype":"locality"
},
  "geometry": {"coordinates":[74.79434999999999,30.49756],"type":"Point"}
}