{
  "type": "Feature",
  "properties": {
    "iso:country":"IN",
    "ks:ks_name":"Sultanpur",
    "ks:ks_pop":1283,
    "ks:ks_type":"VILLAGE",
    "ks:ks_uagg_main":0,
    "name:eng_x_preferred":[
        "Sultanpur"
    ],
    "wof:name":"Sultanpur",
    "wof:placetype":"locality",
    "wof:population":1283
},
  "geometry": {"coordinates":[88.441835,22.38516],"type":"Point"}
}