{
  "type": "Feature",
  "properties": {
    "gn:admin1_code":"11",
    "gn:admin2_code":"24.0",
    "gn:asciiname":"Taqipur Khas",
    "gn:country_code":"IN",
    "gn:dem":615,
    "gn:feature_class":"P",
    "gn:feature_code":"PPL",
    "gn:name":"Taqipur Kh\u0101s",
    "gn:population":0,
    "gn:timezone":"Asia/Kolkata",
    "iso:country":"IN",
    "wof:name":"Taqipur Khas",
    "wof:placetype":"locality"
},
  "geometry": {"coordinates":[76.25735999999998,32.03634],"type":"Point"}
}