{
  "type": "Feature",
  "properties": {
    "iso:country":"IN",
    "ks:ks_name":"Tetuliatanr",
    "ks:ks_pop":214,
    "ks:ks_type":"VILLAGE",
    "name:eng_x_preferred":[
        "Tetuliatanr"
    ],
    "wof:name":"Tetuliatanr",
    "wof:placetype":"locality",
    "wof:population":214
},
  "geometry": {"coordinates":[86.741998,23.97484],"type":"Point"}
}