{
  "type": "Feature",
  "properties": {
    "iso:country":"IN",
    "ks:ks_name":"Rowthampatti",
    "ks:ks_pop":593,
    "ks:ks_type":"HABITATION",
    "name:eng_x_preferred":[
        "Rowthampatti"
    ],
    "wof:name":"Rowthampatti",
    "wof:placetype":"locality",
    "wof:population":593
},
  "geometry": {"coordinates":[78.16821,10.226175],"type":"Point"}
}