{
  "type": "Feature",
  "properties": {
    "iso:country":"IN",
    "ks:ks_name":"Mahuldiha",
    "ks:ks_pop":238,
    "ks:ks_type":"VILLAGE",
    "name:eng_x_preferred":[
        "Mahuldiha"
    ],
    "wof:name":"Mahuldiha",
    "wof:placetype":"locality",
    "wof:population":238
},
  "geometry": {"coordinates":[85.867681,22.703475],"type":"Point"}
}