{
  "type": "Feature",
  "properties": {
    "gn:admin1_code":"34.0",
    "gn:admin2_code":"203.0",
    "gn:asciiname":"Mathiya",
    "gn:country_code":"IN",
    "gn:dem":115,
    "gn:feature_class":"P",
    "gn:feature_code":"PPL",
    "gn:name":"Mathiy\u0101",
    "gn:population":0,
    "gn:timezone":"Asia/Kolkata",
    "iso:country":"IN",
    "name:ceb_x_preferred":[
        "Mathiya"
    ],
    "name:mai_x_preferred":[
        "\u092e\u0920\u093f\u092f\u093e"
    ],
    "name:msa_x_preferred":[
        "Mathiya"
    ],
    "name:pol_x_preferred":[
        "Mathiya"
    ],
    "wof:name":"Mathiya",
    "wof:placetype":"locality"
},
  "geometry": {"coordinates":[84.35088,27.23644],"type":"Point"}
}