{
  "type": "Feature",
  "properties": {
    "gn:admin1_code":"10.0",
    "gn:admin2_code":"76.0",
    "gn:asciiname":"Dobheta",
    "gn:country_code":"IN",
    "gn:dem":230,
    "gn:feature_class":"P",
    "gn:feature_code":"PPL",
    "gn:name":"Dobheta",
    "gn:population":0,
    "gn:timezone":"Asia/Kolkata",
    "iso:country":"IN",
    "wof:name":"Dobheta",
    "wof:placetype":"locality"
},
  "geometry": {"coordinates":[76.86487,29.12612],"type":"Point"}
}