{
  "type": "Feature",
  "properties": {
    "iso:country":"IN",
    "ks:ks_name":"Chaiman",
    "ks:ks_pop":17,
    "ks:ks_type":"HABITATION",
    "name:eng_x_preferred":[
        "Chaiman"
    ],
    "wof:name":"Chaiman",
    "wof:placetype":"locality",
    "wof:population":17
},
  "geometry": {"coordinates":[84.469815,21.420534],"type":"Point"}
}