{
  "type": "Feature",
  "properties": {
    "gn:admin1_code":"35",
    "gn:admin2_code":"423.0",
    "gn:asciiname":"Besni",
    "gn:country_code":"IN",
    "gn:dem":439,
    "gn:feature_class":"P",
    "gn:feature_code":"PPL",
    "gn:name":"Besni",
    "gn:population":0,
    "gn:timezone":"Asia/Kolkata",
    "iso:country":"IN",
    "name:ara_x_preferred":[
        "\u0628\u064a\u0633\u0646\u064a"
    ],
    "name:cat_x_preferred":[
        "Besni"
    ],
    "name:ceb_x_preferred":[
        "Besni \u0130l\u00e7esi"
    ],
    "name:ckb_x_preferred":[
        "\u0628\u06ce\u0633\u0646\u06cc"
    ],
    "name:deu_x_preferred":[
        "Besni"
    ],
    "name:diq_x_preferred":[
        "B\u00easni"
    ],
    "name:epo_x_preferred":[
        "Behesni"
    ],
    "name:fas_x_preferred":[
        "\u0628\u0633\u0646\u06cc"
    ],
    "name:fra_x_preferred":[
        "Besni"
    ],
    "name:ita_x_preferred":[
        "Besni"
    ],
    "name:kaz_x_preferred":[
        "\u0411\u0435\u0441\u043d\u0438"
    ],
    "name:kur_x_preferred":[
        "B\u00easn\u00ee"
    ],
    "name:lbe_x_preferred":[
        "\u0411\u0435\u0441\u043d\u0438"
    ],
    "name:min_x_preferred":[
        "Besni"
    ],
    "name:mrj_x_preferred":[
        "\u0411\u0435\u0441\u043d\u0438"
    ],
    "name:msa_x_preferred":[
        "Besni"
    ],
    "name:nno_x_preferred":[
        "Besni"
    ],
    "name:nor_x_preferred":[
        "Besni"
    ],
    "name:pnb_x_preferred":[
        "\u0636\u0644\u0639 \u0628\u0633\u0646\u06cc"
    ],
    "name:pol_x_preferred":[
        "Besni"
    ],
    "name:ron_x_preferred":[
        "Besni"
    ],
    "name:rus_x_preferred":[
        "\u0411\u0435\u0441\u043d\u0438"
    ],
    "name:spa_x_preferred":[
        "Besni"
    ],
    "name:swa_x_preferred":[
        "Besni"
    ],
    "name:tur_x_preferred":[
        "Besni"
    ],
    "name:urd_x_preferred":[
        "\u0628\u0633\u0646\u06cc"
    ],
    "name:vie_x_preferred":[
        "Besni"
    ],
    "name:zho_x_preferred":[
        "\u8c9d\u65af\u5c3c"
    ],
    "wof:name":"Besni",
    "wof:placetype":"locality"
},
  "geometry": {"coordinates":[77.38509999999999,25.45522],"type":"Point"}
}