{
  "type": "Feature",
  "properties": {
    "iso:country":"IN",
    "ks:ks_name":"Hattipada",
    "ks:ks_pop":497,
    "ks:ks_type":"HABITATION",
    "name:eng_x_preferred":[
        "Hattipada"
    ],
    "wof:name":"Hattipada",
    "wof:placetype":"locality",
    "wof:population":497
},
  "geometry": {"coordinates":[73.344131,19.963735],"type":"Point"}
}