{
  "type": "Feature",
  "properties": {
    "gn:admin1_code":"38.0",
    "gn:admin2_code":"352.0",
    "gn:asciiname":"Rajon",
    "gn:country_code":"IN",
    "gn:dem":88,
    "gn:feature_class":"P",
    "gn:feature_code":"PPL",
    "gn:name":"R\u0101jon",
    "gn:population":0,
    "gn:timezone":"Asia/Kolkata",
    "iso:country":"IN",
    "name:ces_x_preferred":[
        "Raj\u00f3n"
    ],
    "name:slk_x_preferred":[
        "Raj\u00f3n"
    ],
    "name:srp_x_preferred":[
        "\u0420\u0430\u0458\u043e\u043d"
    ],
    "wof:name":"Rajon",
    "wof:placetype":"locality"
},
  "geometry": {"coordinates":[87.54921999999998,25.03389],"type":"Point"}
}