{
  "type": "Feature",
  "properties": {
    "gn:admin1_code":"38.0",
    "gn:admin2_code":"352.0",
    "gn:asciiname":"Rajon",
    "gn:country_code":"IN",
    "gn:dem":88,
    "gn:feature_class":"P",
    "gn:feature_code":"PPL",
    "gn:name":"R\u0101jon",
    "gn:population":0,
    "gn:timezone":"Asia/Kolkata",
    "iso:country":"IN",
    "ks:ks_name":"Rajan",
    "ks:ks_pop":845,
    "ks:ks_type":"VILLAGE",
    "name:ces_x_preferred":[
        "Raj\u00f3n"
    ],
    "name:eng_x_preferred":[
        "Rajan"
    ],
    "name:eng_x_variant":[
        "Rajon"
    ],
    "name:slk_x_preferred":[
        "Raj\u00f3n"
    ],
    "name:srp_x_preferred":[
        "\u0420\u0430\u0458\u043e\u043d"
    ],
    "wof:name":"Rajan",
    "wof:placetype":"locality",
    "wof:population":845
},
  "geometry": {"coordinates":[87.545177,25.035603],"type":"Point"}
}