{
  "type": "Feature",
  "properties": {
    "gn:admin1_code":"09",
    "gn:admin2_code":"490.0",
    "gn:asciiname":"Matwad",
    "gn:country_code":"IN",
    "gn:dem":9,
    "gn:feature_class":"P",
    "gn:feature_code":"PPL",
    "gn:name":"Matw\u0101d",
    "gn:population":0,
    "gn:timezone":"Asia/Kolkata",
    "iso:country":"IN",
    "name:und_x_variant":[
        "Matvad",
        "Matw\u0101d"
    ],
    "wof:name":"Matwad",
    "wof:placetype":"locality"
},
  "geometry": {"coordinates":[72.83071,20.92301],"type":"Point"}
}