{
  "type": "Feature",
  "properties": {
    "iso:country":"IN",
    "ks:ks_name":"Ambivaliwadi",
    "ks:ks_pop":166,
    "ks:ks_type":"HABITATION",
    "name:eng_x_preferred":[
        "Ambivaliwadi"
    ],
    "wof:name":"Ambivaliwadi",
    "wof:placetype":"locality",
    "wof:population":166
},
  "geometry": {"coordinates":[73.285836,18.502357],"type":"Point"}
}