{
  "type": "Feature",
  "properties": {
    "gn:admin1_code":"37",
    "gn:admin2_code":"411.0",
    "gn:asciiname":"Bare Temri",
    "gn:country_code":"IN",
    "gn:dem":283,
    "gn:feature_class":"P",
    "gn:feature_code":"PPL",
    "gn:name":"Bare Temri",
    "gn:population":0,
    "gn:timezone":"Asia/Kolkata",
    "iso:country":"IN",
    "wof:name":"Bare Temri",
    "wof:placetype":"locality"
},
  "geometry": {"coordinates":[82.6708,21.30618],"type":"Point"}
}