{
  "type": "Feature",
  "properties": {
    "iso:country":"IN",
    "ks:ks_name":"Vairagoundampatti",
    "ks:ks_pop":120,
    "ks:ks_type":"HABITATION",
    "name:eng_x_preferred":[
        "Vairagoundampatti"
    ],
    "wof:name":"Vairagoundampatti",
    "wof:placetype":"locality",
    "wof:population":120
},
  "geometry": {"coordinates":[78.338266,10.493326],"type":"Point"}
}