{
  "type": "Feature",
  "properties": {
    "iso:country":"IN",
    "ks:ks_name":"Palattikundu",
    "ks:ks_pop":269,
    "ks:ks_type":"HABITATION",
    "ks:ks_uagg_main":0,
    "name:eng_x_preferred":[
        "Palattikundu"
    ],
    "wof:name":"Palattikundu",
    "wof:placetype":"neighbourhood",
    "wof:population":269
},
  "geometry": {"coordinates":[76.402698,10.285033],"type":"Point"}
}