{
  "type": "Feature",
  "properties": {
    "iso:country":"IN",
    "ks:ks_alt_nam":"Guttala cheruvu",
    "ks:ks_name":"Guttala Cheruvu",
    "ks:ks_pop":183,
    "ks:ks_type":"HABITATION",
    "name:eng_x_preferred":[
        "Guttala Cheruvu"
    ],
    "wof:name":"Guttala Cheruvu",
    "wof:placetype":"locality",
    "wof:population":183
},
  "geometry": {"coordinates":[79.07095200000001,16.164425],"type":"Point"}
}