{
  "type": "Feature",
  "properties": {
    "iso:country":"IN",
    "ks:ks_name":"Ramendra Nagar Purba Para",
    "ks:ks_pop":401,
    "ks:ks_type":"HABITATION",
    "name:eng_x_preferred":[
        "Ramendra Nagar Purba Para"
    ],
    "wof:name":"Ramendra Nagar Purba Para",
    "wof:placetype":"locality",
    "wof:population":401
},
  "geometry": {"coordinates":[91.66818600000001,22.987864],"type":"Point"}
}