{
  "type": "Feature",
  "properties": {
    "iso:country":"IN",
    "ks:ks_name":"2 RTP",
    "ks:ks_pop":212,
    "ks:ks_type":"VILLAGE",
    "name:eng_x_preferred":[
        "2 RTP"
    ],
    "wof:name":"2 RTP",
    "wof:placetype":"locality",
    "wof:population":212
},
  "geometry": {"coordinates":[74.49259499999999,29.82722],"type":"Point"}
}