{
  "type": "Feature",
  "properties": {
    "gn:admin1_code":"12",
    "gn:admin2_code":"13.0",
    "gn:asciiname":"Abalwon",
    "gn:country_code":"IN",
    "gn:dem":1862,
    "gn:feature_class":"P",
    "gn:feature_code":"PPL",
    "gn:name":"Abalw\u014dn",
    "gn:population":0,
    "gn:timezone":"Asia/Kolkata",
    "iso:country":"IN",
    "wof:name":"Abalwon",
    "wof:placetype":"locality"
},
  "geometry": {"coordinates":[74.93413000000002,33.71106],"type":"Point"}
}