{
  "type": "Feature",
  "properties": {
    "iso:country":"IN",
    "ks:ks_name":"Kengre",
    "ks:ks_pop":160,
    "ks:ks_type":"HABITATION",
    "name:eng_x_preferred":[
        "Kengre"
    ],
    "wof:name":"Kengre",
    "wof:placetype":"locality",
    "wof:population":160
},
  "geometry": {"coordinates":[74.750033,14.663156],"type":"Point"}
}