{
  "type": "Feature",
  "properties": {
    "iso:country":"IN",
    "ks:ks_name":"Gaybuda",
    "ks:ks_pop":562,
    "ks:ks_type":"VILLAGE",
    "name:eng_x_preferred":[
        "Gaybuda"
    ],
    "wof:name":"Gaybuda",
    "wof:placetype":"locality",
    "wof:population":562
},
  "geometry": {"coordinates":[83.545573,23.046898],"type":"Point"}
}