{
  "type": "Feature",
  "properties": {
    "iso:country":"IN",
    "ks:ks_name":"Kotakana",
    "ks:ks_pop":0,
    "ks:ks_type":"VILLAGE",
    "name:eng_x_preferred":[
        "Kotakana"
    ],
    "wof:name":"Kotakana",
    "wof:placetype":"locality",
    "wof:population":0
},
  "geometry": {"coordinates":[85.98279100000001,20.132012],"type":"Point"}
}