{
  "type": "Feature",
  "properties": {
    "iso:country":"IN",
    "ks:ks_name":"Ulundangudi",
    "ks:ks_type":"VILLAGE",
    "ks:ks_uagg_main":0,
    "name:eng_x_preferred":[
        "Ulundangudi"
    ],
    "wof:name":"Ulundangudi",
    "wof:placetype":"neighbourhood"
},
  "geometry": {"coordinates":[78.687629,10.911277],"type":"Point"}
}