{
  "type": "Feature",
  "properties": {
    "gn:admin1_code":"21",
    "gn:admin2_code":"394.0",
    "gn:asciiname":"Silyaribahra",
    "gn:country_code":"IN",
    "gn:dem":371,
    "gn:feature_class":"P",
    "gn:feature_code":"PPL",
    "gn:name":"Sily\u0101ribahra",
    "gn:population":0,
    "gn:timezone":"Asia/Kolkata",
    "iso:country":"IN",
    "ks:ks_name":"Siliaribahara",
    "ks:ks_pop":75,
    "ks:ks_type":"VILLAGE",
    "name:eng_x_preferred":[
        "Siliaribahara"
    ],
    "name:eng_x_variant":[
        "Silyaribahra"
    ],
    "wof:name":"Siliaribahara",
    "wof:placetype":"locality",
    "wof:population":75
},
  "geometry": {"coordinates":[82.39764099999999,20.713467],"type":"Point"}
}