{
  "type": "Feature",
  "properties": {
    "gn:admin1_code":"30",
    "gn:admin2_code":"247.0",
    "gn:asciiname":"Lapung",
    "gn:country_code":"IN",
    "gn:dem":1071,
    "gn:feature_class":"P",
    "gn:feature_code":"PPL",
    "gn:name":"Lapung",
    "gn:population":0,
    "gn:timezone":"Asia/Kolkata",
    "iso:country":"IN",
    "wof:name":"Lapung",
    "wof:placetype":"locality"
},
  "geometry": {"coordinates":[92.90000000000001,27.55],"type":"Point"}
}