{
  "type": "Feature",
  "properties": {
    "iso:country":"IN",
    "ks:ks_name":"Baratoli",
    "ks:ks_pop":219,
    "ks:ks_type":"HABITATION",
    "ks:ks_uagg_main":0,
    "name:eng_x_preferred":[
        "Baratoli"
    ],
    "wof:name":"Baratoli",
    "wof:placetype":"neighbourhood",
    "wof:population":219
},
  "geometry": {"coordinates":[84.811463,23.154236],"type":"Point"}
}