{
  "type": "Feature",
  "properties": {
    "gn:admin1_code":"19.0",
    "gn:admin2_code":"567.0",
    "gn:asciiname":"Kurubarahalli",
    "gn:country_code":"IN",
    "gn:dem":544,
    "gn:feature_class":"P",
    "gn:feature_code":"PPL",
    "gn:name":"Kurubarahalli",
    "gn:population":0,
    "gn:timezone":"Asia/Kolkata",
    "iso:country":"IN",
    "wof:name":"Kurubarahalli",
    "wof:placetype":"locality"
},
  "geometry": {"coordinates":[75.84543000000002,14.59661],"type":"Point"}
}