{
  "type": "Feature",
  "properties": {
    "iso:country":"IN",
    "ks:ks_name":"Kolimi Madigapalle",
    "ks:ks_pop":68,
    "ks:ks_type":"HABITATION",
    "name:eng_x_preferred":[
        "Kolimi Madigapalle"
    ],
    "wof:name":"Kolimi Madigapalle",
    "wof:placetype":"locality",
    "wof:population":68
},
  "geometry": {"coordinates":[78.89264799999999,14.048554],"type":"Point"}
}