{
  "type": "Feature",
  "properties": {
    "iso:country":"IN",
    "ks:ks_alt_nam":"Chadheibhol Adivasi sahi",
    "ks:ks_name":"Chadheibhol Adivasi Sahi",
    "ks:ks_pop":124,
    "ks:ks_type":"HABITATION",
    "name:eng_x_preferred":[
        "Chadheibhol Adivasi Sahi"
    ],
    "wof:name":"Chadheibhol Adivasi Sahi",
    "wof:placetype":"locality",
    "wof:population":124
},
  "geometry": {"coordinates":[85.992043,21.688452],"type":"Point"}
}