{
  "type": "Feature",
  "properties": {
    "iso:country":"IN",
    "ks:ks_name":"Jarahadih Khaspara",
    "ks:ks_pop":620,
    "ks:ks_type":"HABITATION",
    "name:eng_x_preferred":[
        "Jarahadih Khaspara"
    ],
    "wof:name":"Jarahadih Khaspara",
    "wof:placetype":"locality",
    "wof:population":620
},
  "geometry": {"coordinates":[83.66555200000001,23.304057],"type":"Point"}
}