{
  "type": "Feature",
  "properties": {
    "gn:admin1_code":"11.0",
    "gn:admin2_code":"32.0",
    "gn:asciiname":"Shilla",
    "gn:country_code":"IN",
    "gn:dem":1500,
    "gn:feature_class":"P",
    "gn:feature_code":"PPL",
    "gn:name":"Shilla",
    "gn:population":0,
    "gn:timezone":"Asia/Kolkata",
    "iso:country":"IN",
    "name:ceb_x_preferred":[
        "Shilla"
    ],
    "name:rus_x_preferred":[
        "\u0428\u0438\u043b\u043b\u0430"
    ],
    "name:swe_x_preferred":[
        "Shilla"
    ],
    "wof:name":"Shilla",
    "wof:placetype":"locality"
},
  "geometry": {"coordinates":[77.38512,30.78736],"type":"Point"}
}