{
  "type": "Feature",
  "properties": {
    "iso:country":"IN",
    "ks:ks_name":"Putritoli",
    "ks:ks_pop":143,
    "ks:ks_type":"HABITATION",
    "name:eng_x_preferred":[
        "Putritoli"
    ],
    "wof:name":"Putritoli",
    "wof:placetype":"locality",
    "wof:population":143
},
  "geometry": {"coordinates":[84.73732800000001,22.760789],"type":"Point"}
}