{
  "type": "Feature",
  "properties": {
    "iso:country":"IN",
    "ks:ks_name":"Moshiwadia",
    "ks:ks_pop":250,
    "ks:ks_type":"HABITATION",
    "name:eng_x_preferred":[
        "Moshiwadia"
    ],
    "wof:name":"Moshiwadia",
    "wof:placetype":"locality",
    "wof:population":250
},
  "geometry": {"coordinates":[73.64733200000001,22.914928],"type":"Point"}
}