{
  "type": "Feature",
  "properties": {
    "gn:admin1_code":"36",
    "gn:admin2_code":"196.0",
    "gn:asciiname":"Bisaripur",
    "gn:country_code":"IN",
    "gn:dem":79,
    "gn:feature_class":"P",
    "gn:feature_code":"PPL",
    "gn:name":"Bis\u0101r\u012bpur",
    "gn:population":0,
    "gn:timezone":"Asia/Kolkata",
    "iso:country":"IN",
    "wof:name":"Bisaripur",
    "wof:placetype":"locality"
},
  "geometry": {"coordinates":[83.26344,25.27817000000001],"type":"Point"}
}