{
  "type": "Feature",
  "properties": {
    "gn:admin1_code":"39.0",
    "gn:admin2_code":"57.0",
    "gn:asciiname":"Sonala",
    "gn:country_code":"IN",
    "gn:dem":1968,
    "gn:feature_class":"P",
    "gn:feature_code":"PPL",
    "gn:name":"Sonala",
    "gn:population":0,
    "gn:timezone":"Asia/Kolkata",
    "iso:country":"IN",
    "name:new_x_preferred":[
        "\u0938\u0902\u0917\u094d\u0930\u093e\u092e\u092a\u0941\u0930"
    ],
    "wof:name":"Sonala",
    "wof:placetype":"locality"
},
  "geometry": {"coordinates":[79.51966,30.08627000000001],"type":"Point"}
}