{
  "type": "Feature",
  "properties": {
    "iso:country":"IN",
    "ks:ks_name":"Chamiari",
    "ks:ks_pop":342,
    "ks:ks_type":"HABITATION",
    "name:eng_x_preferred":[
        "Chamiari"
    ],
    "wof:name":"Chamiari",
    "wof:placetype":"locality",
    "wof:population":342
},
  "geometry": {"coordinates":[75.40845299999999,31.862391],"type":"Point"}
}