{
  "type": "Feature",
  "properties": {
    "gn:admin1_code":"39.0",
    "gn:admin2_code":"57.0",
    "gn:asciiname":"Ratgoan",
    "gn:country_code":"IN",
    "gn:dem":2889,
    "gn:feature_class":"P",
    "gn:feature_code":"PPL",
    "gn:name":"Ratgoan",
    "gn:population":0,
    "gn:timezone":"Asia/Kolkata",
    "iso:country":"IN",
    "wof:name":"Ratgoan",
    "wof:placetype":"locality"
},
  "geometry": {"coordinates":[79.57856,30.13663],"type":"Point"}
}