{
  "type": "Feature",
  "properties": {
    "iso:country":"IN",
    "ks:ks_name":"Kaichana",
    "ks:ks_pop":0,
    "ks:ks_type":"VILLAGE",
    "name:eng_x_preferred":[
        "Kaichana"
    ],
    "wof:name":"Kaichana",
    "wof:placetype":"locality",
    "wof:population":0
},
  "geometry": {"coordinates":[88.399433,24.975976],"type":"Point"}
}