{
  "type": "Feature",
  "properties": {
    "iso:country":"IN",
    "ks:ks_name":"Kutudaganda",
    "ks:ks_pop":93,
    "ks:ks_type":"HABITATION",
    "name:eng_x_preferred":[
        "Kutudaganda"
    ],
    "wof:name":"Kutudaganda",
    "wof:placetype":"locality",
    "wof:population":93
},
  "geometry": {"coordinates":[83.66712200000001,19.33828],"type":"Point"}
}