{
  "type": "Feature",
  "properties": {
    "gn:admin1_code":"19.0",
    "gn:admin2_code":"569.0",
    "gn:asciiname":"Kunjali",
    "gn:country_code":"IN",
    "gn:dem":67,
    "gn:feature_class":"P",
    "gn:feature_code":"PPL",
    "gn:name":"Kunjali",
    "gn:population":0,
    "gn:timezone":"Asia/Kolkata",
    "iso:country":"IN",
    "ks:ks_name":"Kunjalli",
    "ks:ks_pop":152,
    "ks:ks_type":"HABITATION",
    "name:eng_x_preferred":[
        "Kunjalli"
    ],
    "name:eng_x_variant":[
        "Kunjali"
    ],
    "wof:name":"Kunjalli",
    "wof:placetype":"locality",
    "wof:population":152
},
  "geometry": {"coordinates":[74.664402,13.901624],"type":"Point"}
}