{
  "type": "Feature",
  "properties": {
    "iso:country":"IN",
    "ks:ks_name":"Shedepada",
    "ks:ks_pop":287,
    "ks:ks_type":"HABITATION",
    "ks:ks_uagg_main":0,
    "name:eng_x_preferred":[
        "Shedepada"
    ],
    "wof:name":"Shedepada",
    "wof:placetype":"neighbourhood",
    "wof:population":287
},
  "geometry": {"coordinates":[72.792016,19.863205],"type":"Point"}
}