{
  "type": "Feature",
  "properties": {
    "gn:admin1_code":"23",
    "gn:admin2_code":"40.0",
    "gn:asciiname":"Bambe Mazra",
    "gn:country_code":"IN",
    "gn:dem":275,
    "gn:feature_class":"P",
    "gn:feature_code":"PPL",
    "gn:name":"Bambe Mazra",
    "gn:population":0,
    "gn:timezone":"Asia/Kolkata",
    "iso:country":"IN",
    "ks:ks_name":"Bambe Mazra",
    "ks:ks_type":"VILLAGE",
    "name:eng_x_preferred":[
        "Bambe Mazra"
    ],
    "wof:name":"Bambe Mazra",
    "wof:placetype":"locality"
},
  "geometry": {"coordinates":[76.479384,30.638073],"type":"Point"}
}