{
  "type": "Feature",
  "properties": {
    "gn:admin1_code":"36.0",
    "gn:admin2_code":"149",
    "gn:asciiname":"Baghaura",
    "gn:country_code":"IN",
    "gn:dem":156,
    "gn:feature_class":"P",
    "gn:feature_code":"PPL",
    "gn:name":"Baghaura",
    "gn:population":0,
    "gn:timezone":"Asia/Kolkata",
    "iso:country":"IN",
    "name:und_x_variant":[
        "Ghausganj",
        "Baghaura"
    ],
    "wof:name":"Baghaura",
    "wof:placetype":"locality"
},
  "geometry": {"coordinates":[79.40940000000001,27.86558],"type":"Point"}
}