{
  "type": "Feature",
  "properties": {
    "iso:country":"IN",
    "ks:ks_name":"Sathabi",
    "ks:ks_pop":241,
    "ks:ks_type":"VILLAGE",
    "name:eng_x_preferred":[
        "Sathabi"
    ],
    "wof:name":"Sathabi",
    "wof:placetype":"locality",
    "wof:population":241
},
  "geometry": {"coordinates":[83.12063499999999,18.3621],"type":"Point"}
}