{
  "type": "Feature",
  "properties": {
    "gn:admin1_code":"25.0",
    "gn:admin2_code":"606.0",
    "gn:asciiname":"Kalingaleri",
    "gn:country_code":"IN",
    "gn:dem":145,
    "gn:feature_class":"P",
    "gn:feature_code":"PPL",
    "gn:name":"Kalingaleri",
    "gn:population":0,
    "gn:timezone":"Asia/Kolkata",
    "iso:country":"IN",
    "ks:ks_name":"Kalingaleri",
    "ks:ks_type":"VILLAGE",
    "name:eng_x_preferred":[
        "Kalingaleri"
    ],
    "wof:name":"Kalingaleri",
    "wof:placetype":"locality"
},
  "geometry": {"coordinates":[79.14742699999999,12.193367],"type":"Point"}
}