{
  "type": "Feature",
  "properties": {
    "gn:admin1_code":"36.0",
    "gn:admin2_code":"143.0",
    "gn:asciiname":"Jiwaram ka Nagla",
    "gn:country_code":"IN",
    "gn:dem":185,
    "gn:feature_class":"P",
    "gn:feature_code":"PPL",
    "gn:name":"Jiw\u0101r\u0101m ka Nagla",
    "gn:population":0,
    "gn:timezone":"Asia/Kolkata",
    "iso:country":"IN",
    "wof:name":"Jiwaram ka Nagla",
    "wof:placetype":"locality"
},
  "geometry": {"coordinates":[78.50690999999998,28.02737],"type":"Point"}
}