{
  "type": "Feature",
  "properties": {
    "iso:country":"IN",
    "ks:ks_name":"Hudagod",
    "ks:ks_pop":570,
    "ks:ks_type":"HABITATION",
    "name:eng_x_preferred":[
        "Hudagod"
    ],
    "wof:name":"Hudagod",
    "wof:placetype":"locality",
    "wof:population":570
},
  "geometry": {"coordinates":[74.515759,14.293773],"type":"Point"}
}