{
  "type": "Feature",
  "properties": {
    "iso:country":"IN",
    "ks:ks_alt_nam":"kushwahon Ka Purwa",
    "ks:ks_name":"Kushwahon Ka Purwa",
    "ks:ks_pop":60,
    "ks:ks_type":"HABITATION",
    "name:eng_x_preferred":[
        "Kushwahon Ka Purwa"
    ],
    "wof:name":"Kushwahon Ka Purwa",
    "wof:placetype":"locality",
    "wof:population":60
},
  "geometry": {"coordinates":[80.864137,25.229585],"type":"Point"}
}