{
  "type": "Feature",
  "properties": {
    "gn:admin1_code":"36",
    "gn:admin2_code":"199.0",
    "gn:asciiname":"Baghaura Rajman",
    "gn:country_code":"IN",
    "gn:dem":92,
    "gn:feature_class":"P",
    "gn:feature_code":"PPL",
    "gn:name":"Baghaura R\u0101jman",
    "gn:population":0,
    "gn:timezone":"Asia/Kolkata",
    "iso:country":"IN",
    "ks:ks_alt_nam":"Baghaura R\u0101jman",
    "ks:ks_name":"Baghaura Rajman",
    "ks:ks_pop":833,
    "ks:ks_type":"VILLAGE",
    "ks:ks_uagg_main":0,
    "name:eng_x_preferred":[
        "Baghaura Rajman"
    ],
    "name:eng_x_variant":[
        "Baghaura R\u0101jman"
    ],
    "wof:name":"Baghaura Rajman",
    "wof:placetype":"neighbourhood",
    "wof:population":833
},
  "geometry": {"coordinates":[82.290442,25.159582],"type":"Point"}
}