{
  "type": "Feature",
  "properties": {
    "iso:country":"IN",
    "ks:ks_name":"Patdi Falia",
    "ks:ks_pop":297,
    "ks:ks_type":"HABITATION",
    "name:eng_x_preferred":[
        "Patdi Falia"
    ],
    "wof:name":"Patdi Falia",
    "wof:placetype":"locality",
    "wof:population":297
},
  "geometry": {"coordinates":[73.31097200000001,20.610583],"type":"Point"}
}