{
  "type": "Feature",
  "properties": {
    "iso:country":"IN",
    "ks:ks_name":"Chakri",
    "ks:ks_pop":631,
    "ks:ks_type":"VILLAGE",
    "name:eng_x_preferred":[
        "Chakri"
    ],
    "wof:name":"Chakri",
    "wof:placetype":"locality",
    "wof:population":631
},
  "geometry": {"coordinates":[86.451016,22.386706],"type":"Point"}
}