{
  "type": "Feature",
  "properties": {
    "iso:country":"IN",
    "ks:ks_name":"Vidyagiri",
    "ks:ks_pop":554,
    "ks:ks_type":"HABITATION",
    "name:eng_x_preferred":[
        "Vidyagiri"
    ],
    "wof:name":"Vidyagiri",
    "wof:placetype":"locality",
    "wof:population":554
},
  "geometry": {"coordinates":[74.925,13.096495],"type":"Point"}
}