{
  "type": "Feature",
  "properties": {
    "iso:country":"IN",
    "ks:ks_name":"Dabri",
    "ks:ks_pop":312,
    "ks:ks_type":"VILLAGE",
    "name:eng_x_preferred":[
        "Dabri"
    ],
    "wof:name":"Dabri",
    "wof:placetype":"locality",
    "wof:population":312
},
  "geometry": {"coordinates":[84.279241,26.98515],"type":"Point"}
}