{
  "type": "Feature",
  "properties": {
    "iso:country":"IN",
    "ks:ks_name":"Parbatpara",
    "ks:ks_pop":389,
    "ks:ks_type":"HABITATION",
    "name:eng_x_preferred":[
        "Parbatpara"
    ],
    "wof:name":"Parbatpara",
    "wof:placetype":"locality",
    "wof:population":389
},
  "geometry": {"coordinates":[88.076131,22.498196],"type":"Point"}
}