{
  "type": "Feature",
  "properties": {
    "iso:country":"IN",
    "ks:ks_name":"Amkholi",
    "ks:ks_pop":49,
    "ks:ks_type":"VILLAGE",
    "name:eng_x_preferred":[
        "Amkholi"
    ],
    "wof:name":"Amkholi",
    "wof:placetype":"locality",
    "wof:population":49
},
  "geometry": {"coordinates":[78.50660000000001,30.042499],"type":"Point"}
}