{
  "type": "Feature",
  "properties": {
    "iso:country":"IN",
    "ks:ks_alt_nam":"Goda thanda",
    "ks:ks_name":"Goda Thanda",
    "ks:ks_pop":155,
    "ks:ks_type":"HABITATION",
    "ks:ks_uagg_main":0,
    "name:eng_x_preferred":[
        "Goda Thanda"
    ],
    "wof:name":"Goda Thanda",
    "wof:placetype":"neighbourhood",
    "wof:population":155
},
  "geometry": {"coordinates":[80.103685,17.488927],"type":"Point"}
}