{
  "type": "Feature",
  "properties": {
    "gn:admin1_code":"11",
    "gn:admin2_code":"24.0",
    "gn:asciiname":"Banara",
    "gn:country_code":"IN",
    "gn:dem":512,
    "gn:feature_class":"P",
    "gn:feature_code":"PPL",
    "gn:name":"Banara",
    "gn:population":0,
    "gn:timezone":"Asia/Kolkata",
    "iso:country":"IN",
    "name:ara_x_preferred":[
        "\u0628\u0627\u0646\u0627\u0631\u0629"
    ],
    "name:ceb_x_preferred":[
        "Banara"
    ],
    "name:por_x_preferred":[
        "Banara"
    ],
    "name:spa_x_preferred":[
        "Banara"
    ],
    "name:war_x_preferred":[
        "Banara"
    ],
    "wof:name":"Banara",
    "wof:placetype":"locality"
},
  "geometry": {"coordinates":[75.93184000000002,31.99867],"type":"Point"}
}