{
  "type": "Feature",
  "properties": {
    "iso:country":"IN",
    "ks:ks_name":"Dudhisole",
    "ks:ks_pop":216,
    "ks:ks_type":"HABITATION",
    "name:eng_x_preferred":[
        "Dudhisole"
    ],
    "wof:name":"Dudhisole",
    "wof:placetype":"locality",
    "wof:population":216
},
  "geometry": {"coordinates":[87.013097,21.919002],"type":"Point"}
}