{
  "type": "Feature",
  "properties": {
    "iso:country":"IN",
    "ks:ks_name":"Kesrodaga",
    "ks:ks_pop":71,
    "ks:ks_type":"VILLAGE",
    "name:eng_x_preferred":[
        "Kesrodaga"
    ],
    "wof:name":"Kesrodaga",
    "wof:placetype":"locality",
    "wof:population":71
},
  "geometry": {"coordinates":[74.62454700000001,15.354094],"type":"Point"}
}