{
  "type": "Feature",
  "properties": {
    "gn:admin1_code":"37.0",
    "gn:admin2_code":"413.0",
    "gn:asciiname":"Warchegondi",
    "gn:country_code":"IN",
    "gn:dem":440,
    "gn:feature_class":"P",
    "gn:feature_code":"PPL",
    "gn:name":"Warchegondi",
    "gn:population":0,
    "gn:timezone":"Asia/Kolkata",
    "iso:country":"IN",
    "wof:name":"Warchegondi",
    "wof:placetype":"locality"
},
  "geometry": {"coordinates":[81.34318,20.26212],"type":"Point"}
}