{
  "type": "Feature",
  "properties": {
    "gn:admin1_code":"36",
    "gn:admin2_code":"155.0",
    "gn:asciiname":"Bakwa",
    "gn:country_code":"IN",
    "gn:dem":130,
    "gn:feature_class":"P",
    "gn:feature_code":"PPL",
    "gn:name":"Bakw\u0101",
    "gn:population":0,
    "gn:timezone":"Asia/Kolkata",
    "iso:country":"IN",
    "ks:ks_alt_nam":"Bakw\u0101",
    "ks:ks_name":"Bakwa",
    "ks:ks_pop":584,
    "ks:ks_type":"VILLAGE",
    "ks:ks_uagg_main":0,
    "name:eng_x_preferred":[
        "Bakwa"
    ],
    "name:eng_x_variant":[
        "Bakw\u0101"
    ],
    "wof:name":"Bakwa",
    "wof:placetype":"neighbourhood",
    "wof:population":584
},
  "geometry": {"coordinates":[80.741743,27.117339],"type":"Point"}
}