{
  "type": "Feature",
  "properties": {
    "gn:admin1_code":"36.0",
    "gn:admin2_code":"151.0",
    "gn:asciiname":"Damunpura",
    "gn:country_code":"IN",
    "gn:dem":172,
    "gn:feature_class":"P",
    "gn:feature_code":"PPL",
    "gn:name":"Dam\u016bnpura",
    "gn:population":0,
    "gn:timezone":"Asia/Kolkata",
    "iso:country":"IN",
    "ks:ks_alt_nam":"Dam\u016bnpura",
    "ks:ks_name":"Damunpura",
    "ks:ks_type":"VILLAGE",
    "name:eng_x_preferred":[
        "Damunpura"
    ],
    "name:eng_x_variant":[
        "Dam\u016bnpura"
    ],
    "wof:name":"Damunpura",
    "wof:placetype":"locality"
},
  "geometry": {"coordinates":[79.907977,28.307066],"type":"Point"}
}