{
  "type": "Feature",
  "properties": {
    "iso:country":"IN",
    "ks:ks_name":"Chak Chariyala",
    "ks:ks_pop":639,
    "ks:ks_type":"HABITATION",
    "name:eng_x_preferred":[
        "Chak Chariyala"
    ],
    "wof:name":"Chak Chariyala",
    "wof:placetype":"locality",
    "wof:population":639
},
  "geometry": {"coordinates":[73.830687,23.484789],"type":"Point"}
}