{
  "type": "Feature",
  "properties": {
    "iso:country":"IN",
    "ks:ks_alt_nam":"Borakhowa gaon",
    "ks:ks_name":"Borakhowa Gaon",
    "ks:ks_pop":806,
    "ks:ks_type":"HABITATION",
    "ks:ks_uagg_main":0,
    "name:eng_x_preferred":[
        "Borakhowa Gaon"
    ],
    "wof:name":"Borakhowa Gaon",
    "wof:placetype":"neighbourhood",
    "wof:population":806
},
  "geometry": {"coordinates":[94.66931599999999,26.901331],"type":"Point"}
}