{
  "type": "Feature",
  "properties": {
    "iso:country":"IN",
    "ks:ks_alt_nam":"T\u0101r\u0101nagar",
    "ks:ks_name":"Taranagar",
    "ks:ks_type":"VILLAGE",
    "ks:ks_uagg_main":0,
    "name:eng_x_preferred":[
        "Taranagar"
    ],
    "name:eng_x_variant":[
        "T\u0101r\u0101nagar"
    ],
    "wof:name":"Taranagar",
    "wof:placetype":"neighbourhood"
},
  "geometry": {"coordinates":[78.317137,17.490891],"type":"Point"}
}