{
  "type": "Feature",
  "properties": {
    "gn:admin1_code":"03",
    "gn:admin2_code":"318.0",
    "gn:asciiname":"Kukichara",
    "gn:country_code":"IN",
    "gn:dem":42,
    "gn:feature_class":"P",
    "gn:feature_code":"PPL",
    "gn:name":"K\u016bkichara",
    "gn:population":0,
    "gn:timezone":"Asia/Kolkata",
    "iso:country":"IN",
    "wof:name":"Kukichara",
    "wof:placetype":"locality"
},
  "geometry": {"coordinates":[92.56326,24.38653],"type":"Point"}
}