{
  "type": "Feature",
  "properties": {
    "iso:country":"IN",
    "ks:ks_name":"Palkarwadi",
    "ks:ks_pop":53,
    "ks:ks_type":"HABITATION",
    "name:eng_x_preferred":[
        "Palkarwadi"
    ],
    "wof:name":"Palkarwadi",
    "wof:placetype":"locality",
    "wof:population":53
},
  "geometry": {"coordinates":[73.606739,16.776558],"type":"Point"}
}