{
  "type": "Feature",
  "properties": {
    "gn:admin1_code":"11",
    "gn:admin2_code":"24.0",
    "gn:asciiname":"Sadhed Khas",
    "gn:country_code":"IN",
    "gn:dem":1155,
    "gn:feature_class":"P",
    "gn:feature_code":"PPL",
    "gn:name":"Sadhed Kh\u0101s",
    "gn:population":0,
    "gn:timezone":"Asia/Kolkata",
    "iso:country":"IN",
    "wof:name":"Sadhed Khas",
    "wof:placetype":"locality"
},
  "geometry": {"coordinates":[76.30755000000001,32.21588],"type":"Point"}
}