{
  "type": "Feature",
  "properties": {
    "iso:country":"IN",
    "ks:ks_name":"Bhawanitanda",
    "ks:ks_pop":474,
    "ks:ks_type":"HABITATION",
    "name:eng_x_preferred":[
        "Bhawanitanda"
    ],
    "wof:name":"Bhawanitanda",
    "wof:placetype":"locality",
    "wof:population":474
},
  "geometry": {"coordinates":[80.88764500000001,28.064998],"type":"Point"}
}