{
  "type": "Feature",
  "properties": {
    "iso:country":"IN",
    "ks:ks_name":"Bara Khairbani",
    "ks:ks_pop":214,
    "ks:ks_type":"VILLAGE",
    "name:eng_x_preferred":[
        "Bara Khairbani"
    ],
    "wof:name":"Bara Khairbani",
    "wof:placetype":"locality",
    "wof:population":214
},
  "geometry": {"coordinates":[87.353454,24.989892],"type":"Point"}
}