{
  "type": "Feature",
  "properties": {
    "iso:country":"IN",
    "ks:ks_alt_nam":"Niche bara tola",
    "ks:ks_name":"Niche Bara Tola",
    "ks:ks_pop":560,
    "ks:ks_type":"HABITATION",
    "ks:ks_uagg_main":0,
    "name:eng_x_preferred":[
        "Niche Bara Tola"
    ],
    "wof:name":"Niche Bara Tola",
    "wof:placetype":"neighbourhood",
    "wof:population":560
},
  "geometry": {"coordinates":[86.66701,24.803429],"type":"Point"}
}