{
  "type": "Feature",
  "properties": {
    "gn:admin1_code":"19.0",
    "gn:admin2_code":"561.0",
    "gn:asciiname":"Majur",
    "gn:country_code":"IN",
    "gn:dem":601,
    "gn:feature_class":"P",
    "gn:feature_code":"PPL",
    "gn:name":"Maj\u016br",
    "gn:population":0,
    "gn:timezone":"Asia/Kolkata",
    "iso:country":"IN",
    "name:bos_x_preferred":[
        "Majur"
    ],
    "name:fra_x_preferred":[
        "Majur"
    ],
    "name:hun_x_preferred":[
        "Majur"
    ],
    "name:nld_x_preferred":[
        "Majur"
    ],
    "name:slv_x_preferred":[
        "Majur"
    ],
    "name:srp_x_preferred":[
        "\u041c\u0430\u0458\u0443\u0440"
    ],
    "name:swe_x_preferred":[
        "Majur"
    ],
    "wof:name":"Majur",
    "wof:placetype":"locality"
},
  "geometry": {"coordinates":[75.64121999999998,15.17533],"type":"Point"}
}