{
  "type": "Feature",
  "properties": {
    "gn:admin1_code":"23.0",
    "gn:admin2_code":"35.0",
    "gn:asciiname":"Shahabpur",
    "gn:country_code":"IN",
    "gn:dem":243,
    "gn:feature_class":"P",
    "gn:feature_code":"PPL",
    "gn:name":"Shah\u0101bpur",
    "gn:population":0,
    "gn:timezone":"Asia/Kolkata",
    "iso:country":"IN",
    "ks:ks_alt_nam":"Shah\u0101bpur",
    "ks:ks_name":"Shahabpur",
    "ks:ks_type":"VILLAGE",
    "ks:ks_uagg_main":0,
    "name:eng_x_preferred":[
        "Shahabpur"
    ],
    "name:eng_x_variant":[
        "Shah\u0101bpur"
    ],
    "name:fas_x_preferred":[
        "\u0634\u0647\u0627\u0628\u067e\u0648\u0631"
    ],
    "name:por_x_preferred":[
        "Shahabpur"
    ],
    "wof:name":"Shahabpur",
    "wof:placetype":"locality"
},
  "geometry": {"coordinates":[75.16968900000001,31.801036],"type":"Point"}
}