{
  "type": "Feature",
  "properties": {
    "iso:country":"IN",
    "ks:ks_alt_nam":"RANIPATRA BAZAR",
    "ks:ks_name":"Ranipatra Bazar",
    "ks:ks_pop":594,
    "ks:ks_type":"HABITATION",
    "ks:ks_uagg_main":0,
    "name:eng_x_preferred":[
        "Ranipatra Bazar"
    ],
    "wof:name":"Ranipatra Bazar",
    "wof:placetype":"neighbourhood",
    "wof:population":594
},
  "geometry": {"coordinates":[87.51192500000001,25.7251],"type":"Point"}
}