{
  "type": "Feature",
  "properties": {
    "iso:country":"IN",
    "ks:ks_name":"Bhenkatraipur",
    "ks:ks_pop":1451,
    "ks:ks_type":"HABITATION",
    "name:eng_x_preferred":[
        "Bhenkatraipur"
    ],
    "wof:name":"Bhenkatraipur",
    "wof:placetype":"locality",
    "wof:population":1451
},
  "geometry": {"coordinates":[86.014034,20.113552],"type":"Point"}
}