{
  "type": "Feature",
  "properties": {
    "iso:country":"IN",
    "ks:ks_name":"Sarhamarni",
    "ks:ks_pop":0,
    "ks:ks_type":"VILLAGE",
    "name:eng_x_preferred":[
        "Sarhamarni"
    ],
    "wof:name":"Sarhamarni",
    "wof:placetype":"locality",
    "wof:population":0
},
  "geometry": {"coordinates":[86.787119,24.250485],"type":"Point"}
}