{
  "type": "Feature",
  "properties": {
    "gn:admin1_code":"24",
    "gn:admin2_code":"106.0",
    "gn:asciiname":"Nimkhera",
    "gn:country_code":"IN",
    "gn:dem":178,
    "gn:feature_class":"P",
    "gn:feature_code":"PPL",
    "gn:name":"N\u012bmkhera",
    "gn:population":0,
    "gn:timezone":"Asia/Kolkata",
    "iso:country":"IN",
    "name:cat_x_preferred":[
        "Nimkhera"
    ],
    "name:ita_x_preferred":[
        "Nimkhera"
    ],
    "wof:name":"Nimkhera",
    "wof:placetype":"locality"
},
  "geometry": {"coordinates":[77.75324999999999,26.76174],"type":"Point"}
}