{
  "type": "Feature",
  "properties": {
    "iso:country":"IN",
    "ks:ks_name":"Palu",
    "ks:ks_pop":1219,
    "ks:ks_type":"VILLAGE",
    "name:eng_x_preferred":[
        "Palu"
    ],
    "wof:name":"Palu",
    "wof:placetype":"locality",
    "wof:population":1219
},
  "geometry": {"coordinates":[73.68234699999999,16.895534],"type":"Point"}
}