{
  "type": "Feature",
  "properties": {
    "iso:country":"IN",
    "ks:ks_name":"Hatikhuli No.3",
    "ks:ks_pop":1010,
    "ks:ks_type":"VILLAGE",
    "ks:ks_uagg_main":0,
    "name:eng_x_preferred":[
        "Hatikhuli No.3"
    ],
    "wof:name":"Hatikhuli No.3",
    "wof:placetype":"neighbourhood",
    "wof:population":1010
},
  "geometry": {"coordinates":[93.143045,25.774262],"type":"Point"}
}