{
  "type": "Feature",
  "properties": {
    "iso:country":"IN",
    "ks:ks_name":"Nakapara",
    "ks:ks_pop":222,
    "ks:ks_type":"HABITATION",
    "name:eng_x_preferred":[
        "Nakapara"
    ],
    "wof:name":"Nakapara",
    "wof:placetype":"locality",
    "wof:population":222
},
  "geometry": {"coordinates":[81.833246,19.825967],"type":"Point"}
}