{
  "type": "Feature",
  "properties": {
    "gn:admin1_code":"19",
    "gn:admin2_code":"581.0",
    "gn:asciiname":"Vakkaleri",
    "gn:country_code":"IN",
    "gn:dem":911,
    "gn:feature_class":"P",
    "gn:feature_code":"PPL",
    "gn:name":"Vakkaleri",
    "gn:population":0,
    "gn:timezone":"Asia/Kolkata",
    "iso:country":"IN",
    "wof:name":"Vakkaleri",
    "wof:placetype":"locality"
},
  "geometry": {"coordinates":[78.0373,13.07091],"type":"Point"}
}