{
  "type": "Feature",
  "properties": {
    "iso:country":"IN",
    "ks:ks_name":"Nousariya",
    "ks:ks_pop":107,
    "ks:ks_type":"HABITATION",
    "name:eng_x_preferred":[
        "Nousariya"
    ],
    "wof:name":"Nousariya",
    "wof:placetype":"locality",
    "wof:population":107
},
  "geometry": {"coordinates":[83.39878299999999,27.422454],"type":"Point"}
}