{
  "type": "Feature",
  "properties": {
    "gn:admin1_code":"12.0",
    "gn:admin2_code":"001",
    "gn:asciiname":"Wolyas Kaonar",
    "gn:country_code":"IN",
    "gn:dem":1857,
    "gn:feature_class":"P",
    "gn:feature_code":"PPL",
    "gn:name":"Wolyas Kaon\u0101r",
    "gn:population":0,
    "gn:timezone":"Asia/Kolkata",
    "iso:country":"IN",
    "wof:name":"Wolyas Kaonar",
    "wof:placetype":"locality"
},
  "geometry": {"coordinates":[74.14801999999997,34.44551],"type":"Point"}
}