{
  "type": "Feature",
  "properties": {
    "iso:country":"IN",
    "ks:ks_name":"Gopimohanpur",
    "ks:ks_pop":1629,
    "ks:ks_type":"VILLAGE",
    "name:eng_x_preferred":[
        "Gopimohanpur"
    ],
    "wof:name":"Gopimohanpur",
    "wof:placetype":"locality",
    "wof:population":1629
},
  "geometry": {"coordinates":[87.253298,21.758396],"type":"Point"}
}