{
  "type": "Feature",
  "properties": {
    "iso:country":"IN",
    "ks:ks_name":"Lauthor",
    "ks:ks_pop":594,
    "ks:ks_type":"HABITATION",
    "name:eng_x_preferred":[
        "Lauthor"
    ],
    "wof:name":"Lauthor",
    "wof:placetype":"locality",
    "wof:population":594
},
  "geometry": {"coordinates":[77.676557,28.496555],"type":"Point"}
}