{
  "type": "Feature",
  "properties": {
    "gn:admin1_code":"37.0",
    "gn:admin2_code":"405.0",
    "gn:asciiname":"Kadari",
    "gn:country_code":"IN",
    "gn:dem":256,
    "gn:feature_class":"P",
    "gn:feature_code":"PPL",
    "gn:name":"Kadari",
    "gn:population":0,
    "gn:timezone":"Asia/Kolkata",
    "iso:country":"IN",
    "wof:name":"Kadari",
    "wof:placetype":"locality"
},
  "geometry": {"coordinates":[82.76976999999999,22.05195],"type":"Point"}
}