{
  "type": "Feature",
  "properties": {
    "iso:country":"IN",
    "name:eng_x_preferred":[
        "Tilak Nagar"
    ],
    "name:unk_x_variant":[
        "Tilaknagar",
        "Tilak Nagar"
    ],
    "qs:gn_adm0_cc":"IN",
    "qs:gn_local":1262321,
    "qs:gn_nam_loc":"Mysore, Karnataka, Mysore, IN",
    "qs:gn_namadm1":"19",
    "qs:local_max":3824,
    "qs:local_sum":6741,
    "qs:localhoods":11,
    "qs:name":"Tilak Nagar",
    "qs:name_adm0":"India",
    "qs:name_adm1":"Karnataka",
    "qs:name_adm2":"Mysore",
    "qs:name_local":"Mysore",
    "qs:photo_max":86,
    "qs:photo_sum":229,
    "qs:placetype":"Suburb",
    "qs:quad_count":5,
    "qs:woe_adm0":23424848,
    "qs:woe_adm1":2345753,
    "qs:woe_adm2":12586586,
    "qs:woe_lau":0,
    "qs:woe_local":2295421,
    "qs:woe_ver":"7.10.0",
    "wd:wordcount":44,
    "wof:lang":[
        "eng"
    ],
    "wof:name":"Tilak Nagar",
    "wof:placetype":"neighbourhood"
},
  "geometry": {"coordinates":[76.650662,12.310491],"type":"Point"}
}