{
  "type": "Feature",
  "properties": {
    "iso:country":"IN",
    "name:ara_x_preferred":[
        "\u062a\u064a\u0644\u0627\u0643 \u0646\u0627\u062c\u0627\u0631"
    ],
    "name:ben_bn_x_preferred":[
        "\u09a4\u09bf\u09b2\u0995 \u09a8\u0997\u09b0"
    ],
    "name:ben_in_x_preferred":[
        "\u09a4\u09bf\u09b2\u0995 \u09a8\u0997\u09b0"
    ],
    "name:eng_x_preferred":[
        "Tilak Nagar"
    ],
    "name:guj_x_preferred":[
        "\u0aa4\u0abf\u0ab2\u0a95 \u0aa8\u0a97\u0ab0"
    ],
    "name:hin_x_preferred":[
        "\u0924\u093f\u0932\u0915 \u0928\u0917\u0930"
    ],
    "name:kan_x_preferred":[
        "\u0ca4\u0cbf\u0cb2\u0c95\u0ccd \u0ca8\u0c97\u0cb0"
    ],
    "name:mal_x_preferred":[
        "\u0d24\u0d3f\u0d32\u0d15\u0d4d \u0d28\u0d17\u0d7c"
    ],
    "name:mar_x_preferred":[
        "\u0924\u093f\u0932\u0915 \u0928\u0917\u0930"
    ],
    "name:pan_x_preferred":[
        "\u0a24\u0a3f\u0a32\u0a15 \u0a28\u0a17\u0a30"
    ],
    "name:tam_x_preferred":[
        "\u0ba4\u0bbf\u0bb2\u0b95\u0bcd \u0ba8\u0b95\u0bb0\u0bcd"
    ],
    "name:tel_x_preferred":[
        "\u0c24\u0c3f\u0c32\u0c15\u0c4d \u0c28\u0c17\u0c30\u0c4d"
    ],
    "name:und_x_variant":[
        "Tilaknagar"
    ],
    "name:urd_x_preferred":[
        "\u062a\u0644\u06a9 \u0646\u06af\u0631"
    ],
    "qs:gn_adm0_cc":"IN",
    "qs:gn_local":1262321,
    "qs:gn_nam_loc":"Mysore, Karnataka, Mysore, IN",
    "qs:gn_namadm1":"19",
    "qs:local_max":3824,
    "qs:local_sum":6741,
    "qs:localhoods":11,
    "qs:name":"Tilak Nagar",
    "qs:name_adm0":"India",
    "qs:name_adm1":"Karnataka",
    "qs:name_adm2":"Mysore",
    "qs:name_local":"Mysore",
    "qs:photo_max":86,
    "qs:photo_sum":229,
    "qs:placetype":"Suburb",
    "qs:quad_count":5,
    "qs:woe_adm0":23424848,
    "qs:woe_adm1":2345753,
    "qs:woe_adm2":12586586,
    "qs:woe_lau":0,
    "qs:woe_local":2295421,
    "qs:woe_ver":"7.10.0",
    "wd:wordcount":44,
    "wof:lang":[
        "eng"
    ],
    "wof:name":"Tilak Nagar",
    "wof:placetype":"neighbourhood"
},
  "geometry": {"coordinates":[76.650662,12.310491],"type":"Point"}
}