{
  "type": "Feature",
  "properties": {
    "iso:country":"IN",
    "ks:ks_alt_nam":"S Kodikulam AD Colony",
    "ks:ks_name":"S Kodikulam Ad Colony",
    "ks:ks_pop":78,
    "ks:ks_type":"HABITATION",
    "ks:ks_uagg_main":0,
    "name:eng_x_preferred":[
        "S Kodikulam Ad Colony"
    ],
    "wof:name":"S Kodikulam Ad Colony",
    "wof:placetype":"neighbourhood",
    "wof:population":78
},
  "geometry": {"coordinates":[78.697422,9.355875],"type":"Point"}
}