{
  "type": "Feature",
  "properties": {
    "gn:admin1_code":"37",
    "gn:admin2_code":"410.0",
    "gn:asciiname":"Birodar",
    "gn:country_code":"IN",
    "gn:dem":375,
    "gn:feature_class":"P",
    "gn:feature_code":"PPL",
    "gn:name":"Birodar",
    "gn:population":0,
    "gn:timezone":"Asia/Kolkata",
    "iso:country":"IN",
    "wof:name":"Birodar",
    "wof:placetype":"locality"
},
  "geometry": {"coordinates":[82.15389,20.75894],"type":"Point"}
}