{
  "type": "Feature",
  "properties": {
    "gn:admin1_code":"16",
    "gn:admin2_code":"508.0",
    "gn:asciiname":"Bhimankhoji",
    "gn:country_code":"IN",
    "gn:dem":407,
    "gn:feature_class":"P",
    "gn:feature_code":"PPL",
    "gn:name":"Bh\u012bm\u0101nkhoji",
    "gn:population":0,
    "gn:timezone":"Asia/Kolkata",
    "iso:country":"IN",
    "wof:name":"Bhimankhoji",
    "wof:placetype":"locality"
},
  "geometry": {"coordinates":[80.57143000000001,20.48097000000001],"type":"Point"}
}