{
  "type": "Feature",
  "properties": {
    "gn:admin1_code":"16",
    "gn:admin2_code":"508.0",
    "gn:asciiname":"Bhimankhoji",
    "gn:country_code":"IN",
    "gn:dem":407,
    "gn:feature_class":"P",
    "gn:feature_code":"PPL",
    "gn:name":"Bh\u012bm\u0101nkhoji",
    "gn:population":0,
    "gn:timezone":"Asia/Kolkata",
    "iso:country":"IN",
    "ks:ks_name":"Bhimankhoji",
    "ks:ks_pop":93,
    "ks:ks_type":"HABITATION",
    "name:eng_x_preferred":[
        "Bhimankhoji"
    ],
    "wof:name":"Bhimankhoji",
    "wof:placetype":"locality",
    "wof:population":93
},
  "geometry": {"coordinates":[80.573292,20.470455],"type":"Point"}
}