{
  "type": "Feature",
  "properties": {
    "gn:admin1_code":"9",
    "gn:admin2_code":"485.0",
    "gn:asciiname":"Ibhapan",
    "gn:country_code":"IN",
    "gn:dem":291,
    "gn:feature_class":"P",
    "gn:feature_code":"PPL",
    "gn:name":"\u012abh\u0101p\u0101n",
    "gn:population":0,
    "gn:timezone":"Asia/Kolkata",
    "iso:country":"IN",
    "wof:name":"Ibhapan",
    "wof:placetype":"locality"
},
  "geometry": {"coordinates":[74.10023000000002,23.20675],"type":"Point"}
}