{
  "type": "Feature",
  "properties": {
    "gn:admin1_code":"30",
    "gn:admin2_code":"253.0",
    "gn:asciiname":"Nring",
    "gn:country_code":"IN",
    "gn:dem":215,
    "gn:feature_class":"P",
    "gn:feature_code":"PPL",
    "gn:name":"Nring",
    "gn:population":0,
    "gn:timezone":"Asia/Kolkata",
    "iso:country":"IN",
    "wof:name":"Nring",
    "wof:placetype":"locality"
},
  "geometry": {"coordinates":[96.10301,27.54746],"type":"Point"}
}