{
  "type": "Feature",
  "properties": {
    "gn:admin1_code":"16",
    "gn:admin2_code":"508.0",
    "gn:asciiname":"Tekabedal",
    "gn:country_code":"IN",
    "gn:dem":356,
    "gn:feature_class":"P",
    "gn:feature_code":"PPL",
    "gn:name":"Tek\u0101bed\u0101l",
    "gn:population":0,
    "gn:timezone":"Asia/Kolkata",
    "iso:country":"IN",
    "ks:ks_alt_nam":"Tek\u0101bed\u0101l",
    "ks:ks_name":"Tekabedal",
    "ks:ks_pop":259,
    "ks:ks_type":"VILLAGE",
    "name:eng_x_preferred":[
        "Tekabedal"
    ],
    "name:eng_x_variant":[
        "Tek\u0101bed\u0101l"
    ],
    "wof:name":"Tekabedal",
    "wof:placetype":"locality",
    "wof:population":259
},
  "geometry": {"coordinates":[80.548884,20.741098],"type":"Point"}
}