{
  "type": "Feature",
  "properties": {
    "gn:admin1_code":"35",
    "gn:admin2_code":"423.0",
    "gn:asciiname":"Andar",
    "gn:country_code":"IN",
    "gn:dem":264,
    "gn:feature_class":"P",
    "gn:feature_code":"PPL",
    "gn:name":"Andar",
    "gn:population":0,
    "gn:timezone":"Asia/Kolkata",
    "iso:country":"IN",
    "wof:name":"Andar",
    "wof:placetype":"locality"
},
  "geometry": {"coordinates":[78.08662,25.54483],"type":"Point"}
}