{
  "type": "Feature",
  "properties": {
    "iso:country":"IN",
    "ks:ks_name":"Khabdela",
    "ks:ks_pop":56,
    "ks:ks_type":"HABITATION",
    "name:eng_x_preferred":[
        "Khabdela"
    ],
    "wof:name":"Khabdela",
    "wof:placetype":"locality",
    "wof:population":56
},
  "geometry": {"coordinates":[69.964922,26.646787],"type":"Point"}
}