{
  "type": "Feature",
  "properties": {
    "iso:country":"IN",
    "ks:ks_name":"Chapegali",
    "ks:ks_pop":32,
    "ks:ks_type":"HABITATION",
    "name:eng_x_preferred":[
        "Chapegali"
    ],
    "wof:name":"Chapegali",
    "wof:placetype":"locality",
    "wof:population":32
},
  "geometry": {"coordinates":[74.67314399999999,15.046562],"type":"Point"}
}