{
  "type": "Feature",
  "properties": {
    "gn:admin1_code":"36.0",
    "gn:admin2_code":"152",
    "gn:asciiname":"Gulabnagar",
    "gn:country_code":"IN",
    "gn:dem":147,
    "gn:feature_class":"P",
    "gn:feature_code":"PPL",
    "gn:name":"Gul\u0101bnagar",
    "gn:population":0,
    "gn:timezone":"Asia/Kolkata",
    "iso:country":"IN",
    "wof:name":"Gulabnagar",
    "wof:placetype":"locality"
},
  "geometry": {"coordinates":[79.58575999999999,27.6454],"type":"Point"}
}