{
  "type": "Feature",
  "properties": {
    "gn:admin1_code":"16",
    "gn:admin2_code":"505.0",
    "gn:asciiname":"Kosari",
    "gn:country_code":"IN",
    "gn:dem":275,
    "gn:feature_class":"P",
    "gn:feature_code":"PPL",
    "gn:name":"Kos\u0101ri",
    "gn:population":0,
    "gn:timezone":"Asia/Kolkata",
    "iso:country":"IN",
    "ks:ks_alt_nam":"Kos\u0101ri",
    "ks:ks_name":"Kosari",
    "ks:ks_type":"VILLAGE",
    "name:eng_x_preferred":[
        "Kosari"
    ],
    "name:eng_x_variant":[
        "Kos\u0101ri"
    ],
    "name:und_x_variant":[
        "Kos\u0101ri",
        "Butitola"
    ],
    "wof:name":"Kosari",
    "wof:placetype":"locality"
},
  "geometry": {"coordinates":[79.466943,20.888136],"type":"Point"}
}