{
  "type": "Feature",
  "properties": {
    "gn:admin1_code":"38.0",
    "gn:admin2_code":"358.0",
    "gn:asciiname":"Takia",
    "gn:country_code":"IN",
    "gn:dem":151,
    "gn:feature_class":"P",
    "gn:feature_code":"PPL",
    "gn:name":"Taki\u0101",
    "gn:population":0,
    "gn:timezone":"Asia/Kolkata",
    "iso:country":"IN",
    "name:ceb_x_preferred":[
        "Takia"
    ],
    "name:deu_x_preferred":[
        "Takia"
    ],
    "name:swe_x_preferred":[
        "Takia"
    ],
    "wof:name":"Takia",
    "wof:placetype":"locality"
},
  "geometry": {"coordinates":[84.07216,24.56081],"type":"Point"}
}