{
  "type": "Feature",
  "properties": {
    "iso:country":"IN",
    "ks:ks_name":"Tankali Falia",
    "ks:ks_pop":344,
    "ks:ks_type":"HABITATION",
    "name:eng_x_preferred":[
        "Tankali Falia"
    ],
    "wof:name":"Tankali Falia",
    "wof:placetype":"locality",
    "wof:population":344
},
  "geometry": {"coordinates":[73.437056,20.769194],"type":"Point"}
}