{
  "type": "Feature",
  "properties": {
    "gn:admin1_code":"36.0",
    "gn:admin2_code":"159",
    "gn:asciiname":"Sanaura Ishari",
    "gn:country_code":"IN",
    "gn:dem":149,
    "gn:feature_class":"P",
    "gn:feature_code":"PPL",
    "gn:name":"Sanaura Ishari",
    "gn:population":0,
    "gn:timezone":"Asia/Kolkata",
    "iso:country":"IN",
    "wof:name":"Sanaura Ishari",
    "wof:placetype":"locality"
},
  "geometry": {"coordinates":[79.38946999999997,27.22548],"type":"Point"}
}