{
  "type": "Feature",
  "properties": {
    "gn:admin1_code":"18",
    "gn:admin2_code":"299.0",
    "gn:asciiname":"Tongseng",
    "gn:country_code":"IN",
    "gn:dem":1205,
    "gn:feature_class":"P",
    "gn:feature_code":"PPL",
    "gn:name":"Tongseng",
    "gn:population":0,
    "gn:timezone":"Asia/Kolkata",
    "iso:country":"IN",
    "name:fra_x_preferred":[
        "Tongseng"
    ],
    "name:ind_x_preferred":[
        "Tongseng"
    ],
    "name:jav_x_preferred":[
        "Tongs\u00e8ng"
    ],
    "name:rus_x_preferred":[
        "\u0422\u043e\u043d\u0441\u0435\u043d\u0433"
    ],
    "wof:name":"Tongseng",
    "wof:placetype":"locality"
},
  "geometry": {"coordinates":[92.50206,25.32391],"type":"Point"}
}