{
  "type": "Feature",
  "properties": {
    "iso:country":"IN",
    "ks:ks_name":"Lalapettai",
    "ks:ks_pop":101,
    "ks:ks_type":"HABITATION",
    "ks:ks_uagg_main":0,
    "name:eng_x_preferred":[
        "Lalapettai"
    ],
    "wof:name":"Lalapettai",
    "wof:placetype":"neighbourhood",
    "wof:population":101
},
  "geometry": {"coordinates":[79.610845,11.792711],"type":"Point"}
}