{
  "type": "Feature",
  "properties": {
    "gn:admin1_code":"34.0",
    "gn:asciiname":"Banjaria",
    "gn:country_code":"IN",
    "gn:dem":78,
    "gn:feature_class":"P",
    "gn:feature_code":"PPL",
    "gn:name":"Banjari\u0101",
    "gn:population":0,
    "gn:timezone":"Asia/Kolkata",
    "iso:country":"IN",
    "wof:name":"Banjaria",
    "wof:placetype":"locality"
},
  "geometry": {"coordinates":[83.96592,26.61803],"type":"Point"}
}