{
  "type": "Feature",
  "properties": {
    "iso:country":"IN",
    "ks:ks_name":"Kelaginajaddi",
    "ks:ks_pop":24,
    "ks:ks_type":"HABITATION",
    "name:eng_x_preferred":[
        "Kelaginajaddi"
    ],
    "wof:name":"Kelaginajaddi",
    "wof:placetype":"locality",
    "wof:population":24
},
  "geometry": {"coordinates":[74.729111,14.802009],"type":"Point"}
}