{
  "type": "Feature",
  "properties": {
    "iso:country":"IN",
    "ks:ks_name":"Choolakalam",
    "ks:ks_pop":294,
    "ks:ks_type":"HABITATION",
    "name:eng_x_preferred":[
        "Choolakalam"
    ],
    "wof:name":"Choolakalam",
    "wof:placetype":"locality",
    "wof:population":294
},
  "geometry": {"coordinates":[76.31825000000001,10.919982],"type":"Point"}
}