{
  "type": "Feature",
  "properties": {
    "gn:admin1_code":"35.0",
    "gn:admin2_code":"429.0",
    "gn:asciiname":"Kutai",
    "gn:country_code":"IN",
    "gn:dem":351,
    "gn:feature_class":"P",
    "gn:feature_code":"PPL",
    "gn:name":"Kut\u0101i",
    "gn:population":0,
    "gn:timezone":"Asia/Kolkata",
    "iso:country":"IN",
    "name:bjn_x_preferred":[
        "Karajaan Kutai"
    ],
    "name:cat_x_preferred":[
        "Kutai"
    ],
    "name:deu_x_preferred":[
        "Kutei"
    ],
    "name:ind_x_preferred":[
        "Kerajaan Kutai"
    ],
    "name:jav_x_preferred":[
        "Praja Kutai"
    ],
    "name:jpn_x_preferred":[
        "\u30af\u30bf\u30a4\u738b\u56fd"
    ],
    "name:msa_x_preferred":[
        "Kerajaan Kutai"
    ],
    "name:sun_x_preferred":[
        "Kutai"
    ],
    "wof:name":"Kutai",
    "wof:placetype":"locality"
},
  "geometry": {"coordinates":[80.76136,24.21673],"type":"Point"}
}