{
  "type": "Feature",
  "properties": {
    "iso:country":"IN",
    "ks:ks_alt_nam":"CHAUBEY TOLA",
    "ks:ks_name":"Chaubey Tola",
    "ks:ks_pop":2616,
    "ks:ks_type":"HABITATION",
    "ks:ks_uagg_main":0,
    "name:eng_x_preferred":[
        "Chaubey Tola"
    ],
    "wof:name":"Chaubey Tola",
    "wof:placetype":"neighbourhood",
    "wof:population":2616
},
  "geometry": {"coordinates":[83.974283,26.712725],"type":"Point"}
}