{
  "type": "Feature",
  "properties": {
    "iso:country":"IN",
    "ks:ks_name":"Jagdish Chak",
    "ks:ks_pop":0,
    "ks:ks_type":"VILLAGE",
    "name:eng_x_preferred":[
        "Jagdish Chak"
    ],
    "wof:name":"Jagdish Chak",
    "wof:placetype":"locality",
    "wof:population":0
},
  "geometry": {"coordinates":[86.80316999999999,25.290628],"type":"Point"}
}