{
  "type": "Feature",
  "properties": {
    "gn:admin1_code":"36.0",
    "gn:admin2_code":"195.0",
    "gn:asciiname":"Didohar",
    "gn:country_code":"IN",
    "gn:dem":77,
    "gn:feature_class":"P",
    "gn:feature_code":"PPL",
    "gn:name":"Didohar",
    "gn:population":0,
    "gn:timezone":"Asia/Kolkata",
    "iso:country":"IN",
    "wof:name":"Didohar",
    "wof:placetype":"locality"
},
  "geometry": {"coordinates":[83.55569,25.70236],"type":"Point"}
}