{
  "type": "Feature",
  "properties": {
    "iso:country":"IN",
    "ks:ks_name":"Goddha",
    "ks:ks_pop":1779,
    "ks:ks_type":"VILLAGE",
    "name:eng_x_preferred":[
        "Goddha"
    ],
    "wof:name":"Goddha",
    "wof:placetype":"locality",
    "wof:population":1779
},
  "geometry": {"coordinates":[73.29886500000001,21.340077],"type":"Point"}
}