{
  "type": "Feature",
  "properties": {
    "iso:country":"IN",
    "ks:ks_name":"Nagor",
    "ks:ks_pop":658,
    "ks:ks_type":"HABITATION",
    "name:eng_x_preferred":[
        "Nagor"
    ],
    "wof:name":"Nagor",
    "wof:placetype":"locality",
    "wof:population":658
},
  "geometry": {"coordinates":[78.20322299999999,26.121898],"type":"Point"}
}