{
  "type": "Feature",
  "properties": {
    "gn:admin1_code":"11",
    "gn:admin2_code":"32.0",
    "gn:asciiname":"Rasat",
    "gn:country_code":"IN",
    "gn:dem":1294,
    "gn:feature_class":"P",
    "gn:feature_code":"PPL",
    "gn:name":"Rasat",
    "gn:population":0,
    "gn:timezone":"Asia/Kolkata",
    "iso:country":"IN",
    "wof:name":"Rasat",
    "wof:placetype":"locality"
},
  "geometry": {"coordinates":[77.65465999999998,30.75447],"type":"Point"}
}