{
  "type": "Feature",
  "properties": {
    "iso:country":"IN",
    "ks:ks_name":"Niz Rongkhang",
    "ks:ks_pop":249,
    "ks:ks_type":"HABITATION",
    "name:eng_x_preferred":[
        "Niz Rongkhang"
    ],
    "wof:name":"Niz Rongkhang",
    "wof:placetype":"locality",
    "wof:population":249
},
  "geometry": {"coordinates":[92.547375,25.803479],"type":"Point"}
}