{
  "type": "Feature",
  "properties": {
    "iso:country":"IN",
    "ks:ks_alt_nam":"Pandey Purwa mishran Raj Purwa",
    "ks:ks_name":"Pandey Purwa Mishran Raj Purwa",
    "ks:ks_pop":137,
    "ks:ks_type":"HABITATION",
    "ks:ks_uagg_main":0,
    "name:eng_x_preferred":[
        "Pandey Purwa Mishran Raj Purwa"
    ],
    "wof:name":"Pandey Purwa Mishran Raj Purwa",
    "wof:placetype":"neighbourhood",
    "wof:population":137
},
  "geometry": {"coordinates":[82.02215700000001,27.209026],"type":"Point"}
}