{
  "type": "Feature",
  "properties": {
    "gn:admin1_code":"35.0",
    "gn:admin2_code":"457.0",
    "gn:asciiname":"Jhura Khera",
    "gn:country_code":"IN",
    "gn:dem":558,
    "gn:feature_class":"P",
    "gn:feature_code":"PPL",
    "gn:name":"Jhur\u0101 Kher\u0101",
    "gn:population":0,
    "gn:timezone":"Asia/Kolkata",
    "iso:country":"IN",
    "ks:ks_name":"Jharakheda",
    "ks:ks_pop":207,
    "ks:ks_type":"VILLAGE",
    "name:eng_x_preferred":[
        "Jharakheda"
    ],
    "name:eng_x_variant":[
        "Jhura Khera"
    ],
    "wof:name":"Jharakheda",
    "wof:placetype":"locality",
    "wof:population":207
},
  "geometry": {"coordinates":[80.505656,22.115292],"type":"Point"}
}