{
  "type": "Feature",
  "properties": {
    "iso:country":"IN",
    "ks:ks_name":"Othiyod Palam",
    "ks:ks_pop":246,
    "ks:ks_type":"HABITATION",
    "name:eng_x_preferred":[
        "Othiyod Palam"
    ],
    "wof:name":"Othiyod Palam",
    "wof:placetype":"locality",
    "wof:population":246
},
  "geometry": {"coordinates":[75.746053,11.663524],"type":"Point"}
}