{
  "type": "Feature",
  "properties": {
    "iso:country":"IN",
    "ks:ks_name":"Chandwa",
    "ks:ks_pop":0,
    "ks:ks_type":"VILLAGE",
    "name:eng_x_preferred":[
        "Chandwa"
    ],
    "wof:name":"Chandwa",
    "wof:placetype":"locality",
    "wof:population":0
},
  "geometry": {"coordinates":[86.748367,25.43704],"type":"Point"}
}