{
  "type": "Feature",
  "properties": {
    "iso:country":"IN",
    "ks:ks_name":"Rabankocha",
    "ks:ks_pop":241,
    "ks:ks_type":"VILLAGE",
    "name:eng_x_preferred":[
        "Rabankocha"
    ],
    "wof:name":"Rabankocha",
    "wof:placetype":"locality",
    "wof:population":241
},
  "geometry": {"coordinates":[86.038134,22.601075],"type":"Point"}
}