{
  "type": "Feature",
  "properties": {
    "iso:country":"IN",
    "ks:ks_alt_nam":"AHIR TOLA",
    "ks:ks_name":"Ahir Tola",
    "ks:ks_pop":53,
    "ks:ks_type":"HABITATION",
    "name:eng_x_preferred":[
        "Ahir Tola"
    ],
    "wof:name":"Ahir Tola",
    "wof:placetype":"locality",
    "wof:population":53
},
  "geometry": {"coordinates":[83.790891,26.075142],"type":"Point"}
}