{
  "type": "Feature",
  "properties": {
    "iso:country":"IN",
    "ks:ks_name":"Pallithazham",
    "ks:ks_pop":1055,
    "ks:ks_type":"HABITATION",
    "ks:ks_uagg_main":0,
    "name:eng_x_preferred":[
        "Pallithazham"
    ],
    "wof:name":"Pallithazham",
    "wof:placetype":"neighbourhood",
    "wof:population":1055
},
  "geometry": {"coordinates":[76.520644,9.922078],"type":"Point"}
}