{
  "type": "Feature",
  "properties": {
    "gn:admin1_code":"13.0",
    "gn:admin2_code":"594.0",
    "gn:asciiname":"Pallipuram",
    "gn:country_code":"IN",
    "gn:dem":18,
    "gn:feature_class":"P",
    "gn:feature_code":"PPL",
    "gn:name":"Pallipuram",
    "gn:population":0,
    "gn:timezone":"Asia/Kolkata",
    "iso:country":"IN",
    "ks:ks_alt_nam":"Pallipuram",
    "ks:ks_name":"Pallippuram",
    "ks:ks_pop":7622,
    "ks:ks_type":"VILLAGE",
    "name:eng_x_preferred":[
        "Pallippuram"
    ],
    "name:eng_x_variant":[
        "Pallipuram"
    ],
    "wof:name":"Pallippuram",
    "wof:placetype":"locality",
    "wof:population":7622
},
  "geometry": {"coordinates":[76.25946399999999,10.23402],"type":"Point"}
}