{
  "type": "Feature",
  "properties": {
    "iso:country":"IN",
    "ks:ks_name":"Galyachapada",
    "ks:ks_pop":378,
    "ks:ks_type":"HABITATION",
    "name:eng_x_preferred":[
        "Galyachapada"
    ],
    "wof:name":"Galyachapada",
    "wof:placetype":"locality",
    "wof:population":378
},
  "geometry": {"coordinates":[73.20520500000001,19.727858],"type":"Point"}
}