{
  "type": "Feature",
  "properties": {
    "iso:country":"IN",
    "ks:ks_name":"Puranabagara",
    "ks:ks_pop":315,
    "ks:ks_type":"VILLAGE",
    "ks:ks_uagg_main":0,
    "name:eng_x_preferred":[
        "Puranabagara"
    ],
    "wof:name":"Puranabagara",
    "wof:placetype":"neighbourhood",
    "wof:population":315
},
  "geometry": {"coordinates":[86.81103,24.456568],"type":"Point"}
}