{
  "type": "Feature",
  "properties": {
    "iso:country":"IN",
    "ks:ks_name":"Itikabedda",
    "ks:ks_pop":21,
    "ks:ks_type":"VILLAGE",
    "name:eng_x_preferred":[
        "Itikabedda"
    ],
    "wof:name":"Itikabedda",
    "wof:placetype":"locality",
    "wof:population":21
},
  "geometry": {"coordinates":[82.322277,18.040443],"type":"Point"}
}