{
  "type": "Feature",
  "properties": {
    "iso:country":"IN",
    "ks:ks_name":"Morjkarwadi",
    "ks:ks_pop":345,
    "ks:ks_type":"HABITATION",
    "name:eng_x_preferred":[
        "Morjkarwadi"
    ],
    "wof:name":"Morjkarwadi",
    "wof:placetype":"locality",
    "wof:population":345
},
  "geometry": {"coordinates":[73.699305,15.983681],"type":"Point"}
}