{
  "type": "Feature",
  "properties": {
    "iso:country":"IN",
    "ks:ks_alt_nam":"MundaMuska",
    "ks:ks_name":"Mundamuska",
    "ks:ks_pop":17,
    "ks:ks_type":"HABITATION",
    "name:eng_x_preferred":[
        "Mundamuska"
    ],
    "wof:name":"Mundamuska",
    "wof:placetype":"locality",
    "wof:population":17
},
  "geometry": {"coordinates":[83.70694399999999,20.219981],"type":"Point"}
}