{
  "type": "Feature",
  "properties": {
    "gn:admin1_code":"25.0",
    "gn:admin2_code":"609.0",
    "gn:asciiname":"Sendampalaiyam",
    "gn:country_code":"IN",
    "gn:dem":272,
    "gn:feature_class":"P",
    "gn:feature_code":"PPL",
    "gn:name":"Sendamp\u0101laiyam",
    "gn:population":0,
    "gn:timezone":"Asia/Kolkata",
    "iso:country":"IN",
    "wof:name":"Sendampalaiyam",
    "wof:placetype":"neighbourhood"
},
  "geometry": {"coordinates":[77.91678,11.42327],"type":"Point"}
}