{
  "type": "Feature",
  "properties": {
    "iso:country":"IN",
    "ks:ks_name":"Sherpur Aheer",
    "ks:ks_pop":1798,
    "ks:ks_type":"HABITATION",
    "name:eng_x_preferred":[
        "Sherpur Aheer"
    ],
    "wof:name":"Sherpur Aheer",
    "wof:placetype":"locality",
    "wof:population":1798
},
  "geometry": {"coordinates":[79.380723,26.255256],"type":"Point"}
}