{
  "type": "Feature",
  "properties": {
    "iso:country":"IN",
    "ks:ks_alt_nam":"MUSHHARI TOLA",
    "ks:ks_name":"Mushhari Tola",
    "ks:ks_pop":317,
    "ks:ks_type":"HABITATION",
    "name:eng_x_preferred":[
        "Mushhari Tola"
    ],
    "wof:name":"Mushhari Tola",
    "wof:placetype":"locality",
    "wof:population":317
},
  "geometry": {"coordinates":[84.593861,26.67324],"type":"Point"}
}