{
  "type": "Feature",
  "properties": {
    "iso:country":"IN",
    "ks:ks_name":"Gadhaha Kund",
    "ks:ks_pop":445,
    "ks:ks_type":"VILLAGE",
    "name:eng_x_preferred":[
        "Gadhaha Kund"
    ],
    "wof:name":"Gadhaha Kund",
    "wof:placetype":"locality",
    "wof:population":445
},
  "geometry": {"coordinates":[81.75059400000001,23.318864],"type":"Point"}
}