{
  "type": "Feature",
  "properties": {
    "gn:admin1_code":"38",
    "gn:admin2_code":"346.0",
    "gn:asciiname":"Bhauraha",
    "gn:country_code":"IN",
    "gn:dem":278,
    "gn:feature_class":"P",
    "gn:feature_code":"PPL",
    "gn:name":"Bhauraha",
    "gn:population":0,
    "gn:timezone":"Asia/Kolkata",
    "iso:country":"IN",
    "ks:ks_name":"Bhaunraha",
    "ks:ks_pop":76,
    "ks:ks_type":"VILLAGE",
    "name:eng_x_preferred":[
        "Bhaunraha"
    ],
    "name:eng_x_variant":[
        "Bhauraha"
    ],
    "wof:name":"Bhaunraha",
    "wof:placetype":"locality",
    "wof:population":76
},
  "geometry": {"coordinates":[83.75799499999999,24.091172],"type":"Point"}
}