{
  "type": "Feature",
  "properties": {
    "iso:country":"IN",
    "ks:ks_name":"Asram Para",
    "ks:ks_pop":506,
    "ks:ks_type":"HABITATION",
    "name:eng_x_preferred":[
        "Asram Para"
    ],
    "wof:name":"Asram Para",
    "wof:placetype":"locality",
    "wof:population":506
},
  "geometry": {"coordinates":[91.527891,23.106578],"type":"Point"}
}