{
  "type": "Feature",
  "properties": {
    "iso:country":"IN",
    "ks:ks_name":"Kanibidika",
    "ks:ks_pop":390,
    "ks:ks_type":"VILLAGE",
    "name:eng_x_preferred":[
        "Kanibidika"
    ],
    "wof:name":"Kanibidika",
    "wof:placetype":"locality",
    "wof:population":390
},
  "geometry": {"coordinates":[84.155283,20.204487],"type":"Point"}
}