{
  "type": "Feature",
  "properties": {
    "iso:country":"IN",
    "ks:ks_name":"Gawadeyashe Hagarewasti",
    "ks:ks_pop":200,
    "ks:ks_type":"HABITATION",
    "name:eng_x_preferred":[
        "Gawadeyashe Hagarewasti"
    ],
    "wof:name":"Gawadeyashe Hagarewasti",
    "wof:placetype":"locality",
    "wof:population":200
},
  "geometry": {"coordinates":[74.854,18.133],"type":"Point"}
}