{
  "type": "Feature",
  "properties": {
    "iso:country":"IN",
    "ks:ks_name":"Thummiguda",
    "ks:ks_pop":52,
    "ks:ks_type":"HABITATION",
    "name:eng_x_preferred":[
        "Thummiguda"
    ],
    "wof:name":"Thummiguda",
    "wof:placetype":"locality",
    "wof:population":52
},
  "geometry": {"coordinates":[83.54123300000001,18.966016],"type":"Point"}
}