{
  "type": "Feature",
  "properties": {
    "iso:country":"IN",
    "ks:ks_alt_nam":"Pacherchar Pt. II",
    "ks:ks_name":"Pacherchar Pt. Ii",
    "ks:ks_pop":574,
    "ks:ks_type":"HABITATION",
    "name:eng_x_preferred":[
        "Pacherchar Pt. Ii"
    ],
    "wof:name":"Pacherchar Pt. Ii",
    "wof:placetype":"locality",
    "wof:population":574
},
  "geometry": {"coordinates":[89.919302,25.896751],"type":"Point"}
}