{
  "type": "Feature",
  "properties": {
    "gn:admin1_code":"24",
    "gn:admin2_code":"116.0",
    "gn:asciiname":"Pantheri",
    "gn:country_code":"IN",
    "gn:dem":114,
    "gn:feature_class":"P",
    "gn:feature_code":"PPL",
    "gn:name":"Pantheri",
    "gn:population":0,
    "gn:timezone":"Asia/Kolkata",
    "iso:country":"IN",
    "wof:name":"Pantheri",
    "wof:placetype":"locality"
},
  "geometry": {"coordinates":[72.27275,25.19919],"type":"Point"}
}