{
  "type": "Feature",
  "properties": {
    "iso:country":"IN",
    "ks:ks_name":"Girijapada",
    "ks:ks_pop":45,
    "ks:ks_type":"HABITATION",
    "name:eng_x_preferred":[
        "Girijapada"
    ],
    "wof:name":"Girijapada",
    "wof:placetype":"locality",
    "wof:population":45
},
  "geometry": {"coordinates":[84.70377999999999,22.34626],"type":"Point"}
}