{
  "type": "Feature",
  "properties": {
    "iso:country":"IN",
    "ks:ks_name":"Chhabauli",
    "ks:ks_pop":360,
    "ks:ks_type":"VILLAGE",
    "ks:ks_uagg_main":0,
    "name:eng_x_preferred":[
        "Chhabauli"
    ],
    "wof:name":"Chhabauli",
    "wof:placetype":"neighbourhood",
    "wof:population":360
},
  "geometry": {"coordinates":[83.88566899999999,26.652804],"type":"Point"}
}