{
  "type": "Feature",
  "properties": {
    "gn:admin1_code":"13.0",
    "gn:admin2_code":"589",
    "gn:asciiname":"Kokkanissheri",
    "gn:country_code":"IN",
    "gn:dem":11,
    "gn:feature_class":"P",
    "gn:feature_code":"PPL",
    "gn:name":"Kokk\u0101nissh\u0113ri",
    "gn:population":0,
    "gn:timezone":"Asia/Kolkata",
    "iso:country":"IN",
    "name:und_x_variant":[
        "Kokk\u0101nissh\u0113ri",
        "Kokk\u0101nisseri"
    ],
    "wof:name":"Kokkanissheri",
    "wof:placetype":"locality"
},
  "geometry": {"coordinates":[75.20916,12.10938],"type":"Point"}
}