{
  "type": "Feature",
  "properties": {
    "gn:admin1_code":"19.0",
    "gn:admin2_code":"565.0",
    "gn:asciiname":"Chikka Jogihalli",
    "gn:country_code":"IN",
    "gn:dem":642,
    "gn:feature_class":"P",
    "gn:feature_code":"PPL",
    "gn:name":"Chikka Jogihalli",
    "gn:population":0,
    "gn:timezone":"Asia/Kolkata",
    "iso:country":"IN",
    "wof:name":"Chikka Jogihalli",
    "wof:placetype":"neighbourhood"
},
  "geometry": {"coordinates":[76.49195,14.71834],"type":"Point"}
}