{
  "type": "Feature",
  "properties": {
    "iso:country":"IN",
    "ks:ks_name":"Manya",
    "ks:ks_pop":4038,
    "ks:ks_type":"HABITATION",
    "name:eng_x_preferred":[
        "Manya"
    ],
    "wof:name":"Manya",
    "wof:placetype":"locality",
    "wof:population":4038
},
  "geometry": {"coordinates":[75.050342,12.561968],"type":"Point"}
}