{
  "type": "Feature",
  "properties": {
    "iso:country":"IN",
    "ks:ks_alt_nam":"DUBATIYA",
    "ks:ks_name":"Dubatiya",
    "ks:ks_pop":265,
    "ks:ks_type":"HABITATION",
    "name:eng_x_preferred":[
        "Dubatiya"
    ],
    "wof:name":"Dubatiya",
    "wof:placetype":"locality",
    "wof:population":265
},
  "geometry": {"coordinates":[81.987587,22.80944],"type":"Point"}
}