{
  "type": "Feature",
  "properties": {
    "iso:country":"IN",
    "ks:ks_name":"Barkhera",
    "ks:ks_pop":0,
    "ks:ks_type":"VILLAGE",
    "name:eng_x_preferred":[
        "Barkhera"
    ],
    "wof:name":"Barkhera",
    "wof:placetype":"locality",
    "wof:population":0
},
  "geometry": {"coordinates":[78.473595,24.394966],"type":"Point"}
}