{
  "type": "Feature",
  "properties": {
    "iso:country":"IN",
    "ks:ks_alt_nam":"MATU LINE",
    "ks:ks_name":"Matu Line",
    "ks:ks_pop":869,
    "ks:ks_type":"HABITATION",
    "name:eng_x_preferred":[
        "Matu Line"
    ],
    "wof:name":"Matu Line",
    "wof:placetype":"locality",
    "wof:population":869
},
  "geometry": {"coordinates":[88.98835800000001,26.903184],"type":"Point"}
}