{
  "type": "Feature",
  "properties": {
    "gn:admin1_code":"19.0",
    "gn:admin2_code":"572",
    "gn:asciiname":"kalidasa Layout",
    "gn:country_code":"IN",
    "gn:dem":865,
    "gn:feature_class":"P",
    "gn:feature_code":"PPL",
    "gn:name":"kalidasa Layout",
    "gn:population":0,
    "gn:timezone":"Asia/Kolkata",
    "iso:country":"IN",
    "wof:name":"kalidasa Layout",
    "wof:placetype":"locality"
},
  "geometry": {"coordinates":[77.55084000000002,12.94821],"type":"Point"}
}