{
  "type": "Feature",
  "properties": {
    "iso:country":"IN",
    "ks:ks_alt_nam":"P.Muthulingapuram",
    "ks:ks_name":"P.muthulingapuram",
    "ks:ks_pop":648,
    "ks:ks_type":"HABITATION",
    "name:eng_x_preferred":[
        "P.muthulingapuram"
    ],
    "wof:name":"P.muthulingapuram",
    "wof:placetype":"locality",
    "wof:population":648
},
  "geometry": {"coordinates":[77.834599,9.753357],"type":"Point"}
}