{
  "type": "Feature",
  "properties": {
    "iso:country":"IN",
    "ks:ks_name":"Palwa",
    "ks:ks_pop":490,
    "ks:ks_type":"VILLAGE",
    "name:eng_x_preferred":[
        "Palwa"
    ],
    "wof:name":"Palwa",
    "wof:placetype":"locality",
    "wof:population":490
},
  "geometry": {"coordinates":[74.78485000000001,23.477066],"type":"Point"}
}