{
  "type": "Feature",
  "properties": {
    "iso:country":"IN",
    "ks:ks_name":"Kannapulanka",
    "ks:ks_pop":1089,
    "ks:ks_type":"HABITATION",
    "name:eng_x_preferred":[
        "Kannapulanka"
    ],
    "wof:name":"Kannapulanka",
    "wof:placetype":"locality",
    "wof:population":1089
},
  "geometry": {"coordinates":[82.178281,16.647469],"type":"Point"}
}