{
  "type": "Feature",
  "properties": {
    "iso:country":"IN",
    "ks:ks_alt_nam":"SeethiSahib",
    "ks:ks_name":"Seethisahib",
    "ks:ks_pop":924,
    "ks:ks_type":"HABITATION",
    "name:eng_x_preferred":[
        "Seethisahib"
    ],
    "wof:name":"Seethisahib",
    "wof:placetype":"neighbourhood",
    "wof:population":924
},
  "geometry": {"coordinates":[76.170744,10.194842],"type":"Point"}
}