{
  "type": "Feature",
  "properties": {
    "iso:country":"IN",
    "ks:ks_name":"Jammunda",
    "ks:ks_pop":404,
    "ks:ks_type":"VILLAGE",
    "name:eng_x_preferred":[
        "Jammunda"
    ],
    "wof:name":"Jammunda",
    "wof:placetype":"locality",
    "wof:population":404
},
  "geometry": {"coordinates":[83.49284,20.413307],"type":"Point"}
}