{
  "type": "Feature",
  "properties": {
    "iso:country":"IN",
    "ks:ks_name":"Mahdewa",
    "ks:ks_pop":1775,
    "ks:ks_type":"VILLAGE",
    "ks:ks_uagg_main":0,
    "name:eng_x_preferred":[
        "Mahdewa"
    ],
    "wof:name":"Mahdewa",
    "wof:placetype":"neighbourhood",
    "wof:population":1775
},
  "geometry": {"coordinates":[84.022622,27.307428],"type":"Point"}
}