{
  "type": "Feature",
  "properties": {
    "gn:admin1_code":"11",
    "gn:admin2_code":"33.0",
    "gn:asciiname":"Thaprala",
    "gn:country_code":"IN",
    "gn:dem":1686,
    "gn:feature_class":"P",
    "gn:feature_code":"PPL",
    "gn:name":"Thapr\u0101la",
    "gn:population":0,
    "gn:timezone":"Asia/Kolkata",
    "iso:country":"IN",
    "wof:name":"Thaprala",
    "wof:placetype":"locality"
},
  "geometry": {"coordinates":[77.13845000000001,31.0398],"type":"Point"}
}