{
  "type": "Feature",
  "properties": {
    "iso:country":"IN",
    "ks:ks_name":"Kesharpura",
    "ks:ks_pop":360,
    "ks:ks_type":"HABITATION",
    "name:eng_x_preferred":[
        "Kesharpura"
    ],
    "wof:name":"Kesharpura",
    "wof:placetype":"locality",
    "wof:population":360
},
  "geometry": {"coordinates":[73.856697,23.679356],"type":"Point"}
}