{
  "type": "Feature",
  "properties": {
    "gn:admin1_code":"36",
    "gn:admin2_code":"179.0",
    "gn:asciiname":"Hardaspur",
    "gn:country_code":"IN",
    "gn:dem":92,
    "gn:feature_class":"P",
    "gn:feature_code":"PPL",
    "gn:name":"Hard\u0101spur",
    "gn:population":0,
    "gn:timezone":"Asia/Kolkata",
    "iso:country":"IN",
    "ks:ks_name":"Hardaspur",
    "ks:ks_pop":262,
    "ks:ks_type":"VILLAGE",
    "ks:ks_uagg_main":0,
    "name:eng_x_preferred":[
        "Hardaspur"
    ],
    "wof:name":"Hardaspur",
    "wof:placetype":"neighbourhood",
    "wof:population":262
},
  "geometry": {"coordinates":[82.245375,26.065691],"type":"Point"}
}