{
  "type": "Feature",
  "properties": {
    "iso:country":"IN",
    "ks:ks_alt_nam":"Bellubbi tota",
    "ks:ks_name":"Bellubbi Tota",
    "ks:ks_pop":250,
    "ks:ks_type":"HABITATION",
    "name:eng_x_preferred":[
        "Bellubbi Tota"
    ],
    "wof:name":"Bellubbi Tota",
    "wof:placetype":"locality",
    "wof:population":250
},
  "geometry": {"coordinates":[75.62060099999999,16.473907],"type":"Point"}
}