{
  "type": "Feature",
  "properties": {
    "gn:admin1_code":"36",
    "gn:admin2_code":"132.0",
    "gn:asciiname":"Landhaura Zunardar",
    "gn:country_code":"IN",
    "gn:dem":295,
    "gn:feature_class":"P",
    "gn:feature_code":"PPL",
    "gn:name":"Landhaura Zun\u0101rd\u0101r",
    "gn:population":0,
    "gn:timezone":"Asia/Kolkata",
    "iso:country":"IN",
    "wof:name":"Landhaura Zunardar",
    "wof:placetype":"locality"
},
  "geometry": {"coordinates":[77.64792,30.07301],"type":"Point"}
}