{
  "type": "Feature",
  "properties": {
    "iso:country":"IN",
    "ks:ks_name":"Ujjiramane",
    "ks:ks_pop":41,
    "ks:ks_type":"HABITATION",
    "name:eng_x_preferred":[
        "Ujjiramane"
    ],
    "wof:name":"Ujjiramane",
    "wof:placetype":"locality",
    "wof:population":41
},
  "geometry": {"coordinates":[75.476124,13.428005],"type":"Point"}
}