{
  "type": "Feature",
  "properties": {
    "iso:country":"IN",
    "ks:ks_name":"Ghosgawan",
    "ks:ks_type":"VILLAGE",
    "name:eng_x_preferred":[
        "Ghosgawan"
    ],
    "wof:name":"Ghosgawan",
    "wof:placetype":"locality"
},
  "geometry": {"coordinates":[79.84804200000001,27.960831],"type":"Point"}
}