{
  "type": "Feature",
  "properties": {
    "gn:admin1_code":"12.0",
    "gn:admin2_code":"18.0",
    "gn:asciiname":"Natas",
    "gn:country_code":"IN",
    "gn:dem":1496,
    "gn:feature_class":"P",
    "gn:feature_code":"PPL",
    "gn:name":"Natas",
    "gn:population":0,
    "gn:timezone":"Asia/Kolkata",
    "iso:country":"IN",
    "name:fra_x_preferred":[
        "Natas"
    ],
    "name:ron_x_preferred":[
        "Natas"
    ],
    "wof:name":"Natas",
    "wof:placetype":"locality"
},
  "geometry": {"coordinates":[75.81905,33.3562],"type":"Point"}
}