{
  "type": "Feature",
  "properties": {
    "iso:country":"IN",
    "ks:ks_name":"T Gopinathapur",
    "ks:ks_pop":30,
    "ks:ks_type":"HABITATION",
    "name:eng_x_preferred":[
        "T Gopinathapur"
    ],
    "wof:name":"T Gopinathapur",
    "wof:placetype":"locality",
    "wof:population":30
},
  "geometry": {"coordinates":[84.90956799999999,21.055897],"type":"Point"}
}