{
  "type": "Feature",
  "properties": {
    "iso:country":"IN",
    "ks:ks_name":"Kusumveri",
    "ks:ks_pop":343,
    "ks:ks_type":"HABITATION",
    "name:eng_x_preferred":[
        "Kusumveri"
    ],
    "wof:name":"Kusumveri",
    "wof:placetype":"locality",
    "wof:population":343
},
  "geometry": {"coordinates":[74.19750000000001,21.797914],"type":"Point"}
}