{
  "type": "Feature",
  "properties": {
    "iso:country":"IN",
    "ks:ks_name":"Kanjooru",
    "ks:ks_pop":24,
    "ks:ks_type":"HABITATION",
    "name:eng_x_preferred":[
        "Kanjooru"
    ],
    "wof:name":"Kanjooru",
    "wof:placetype":"locality",
    "wof:population":24
},
  "geometry": {"coordinates":[75.206148,12.796911],"type":"Point"}
}