{
  "type": "Feature",
  "properties": {
    "iso:country":"IN",
    "ks:ks_name":"Sher Pur",
    "ks:ks_pop":226,
    "ks:ks_type":"HABITATION",
    "name:eng_x_preferred":[
        "Sher Pur"
    ],
    "wof:name":"Sher Pur",
    "wof:placetype":"locality",
    "wof:population":226
},
  "geometry": {"coordinates":[78.087299,29.212236],"type":"Point"}
}