{
  "type": "Feature",
  "properties": {
    "iso:country":"IN",
    "ks:ks_name":"4ML",
    "ks:ks_pop":909,
    "ks:ks_type":"VILLAGE",
    "name:eng_x_preferred":[
        "4ML"
    ],
    "wof:name":"4ML",
    "wof:placetype":"locality",
    "wof:population":909
},
  "geometry": {"coordinates":[73.90365,29.87055],"type":"Point"}
}