{
  "type": "Feature",
  "properties": {
    "iso:country":"IN",
    "ks:ks_name":"Paji Gerega",
    "ks:ks_pop":120,
    "ks:ks_type":"VILLAGE",
    "name:eng_x_preferred":[
        "Paji Gerega"
    ],
    "wof:name":"Paji Gerega",
    "wof:placetype":"locality",
    "wof:population":120
},
  "geometry": {"coordinates":[83.67313,19.660234],"type":"Point"}
}