{
  "type": "Feature",
  "properties": {
    "gn:admin1_code":"35",
    "gn:admin2_code":"427.0",
    "gn:asciiname":"Bartuma",
    "gn:country_code":"IN",
    "gn:dem":548,
    "gn:feature_class":"P",
    "gn:feature_code":"PPL",
    "gn:name":"Bart\u016bma",
    "gn:population":0,
    "gn:timezone":"Asia/Kolkata",
    "iso:country":"IN",
    "wof:name":"Bartuma",
    "wof:placetype":"locality"
},
  "geometry": {"coordinates":[78.80889999999999,23.83964],"type":"Point"}
}