{
  "type": "Feature",
  "properties": {
    "gn:admin1_code":"28",
    "gn:admin2_code":"328.0",
    "gn:asciiname":"Lankapara Hat",
    "gn:country_code":"IN",
    "gn:dem":298,
    "gn:feature_class":"P",
    "gn:feature_code":"PPL",
    "gn:name":"Lank\u0101p\u0101ra H\u0101t",
    "gn:population":0,
    "gn:timezone":"Asia/Kolkata",
    "iso:country":"IN",
    "name:und_x_variant":[
        "Lankapara",
        "Lank\u0101p\u0101ra H\u0101t"
    ],
    "wof:name":"Lankapara Hat",
    "wof:placetype":"locality"
},
  "geometry": {"coordinates":[89.22983000000001,26.79487],"type":"Point"}
}