{
  "type": "Feature",
  "properties": {
    "iso:country":"IN",
    "ks:ks_name":"Elavampadam",
    "ks:ks_pop":1636,
    "ks:ks_type":"HABITATION",
    "ks:ks_uagg_main":0,
    "name:eng_x_preferred":[
        "Elavampadam"
    ],
    "wof:name":"Elavampadam",
    "wof:placetype":"neighbourhood",
    "wof:population":1636
},
  "geometry": {"coordinates":[76.514926,10.557316],"type":"Point"}
}