{
  "type": "Feature",
  "properties": {
    "iso:country":"IN",
    "ks:ks_alt_nam":"KALYANPUR TOLA",
    "ks:ks_name":"Kalyanpur Tola",
    "ks:ks_pop":982,
    "ks:ks_type":"HABITATION",
    "name:eng_x_preferred":[
        "Kalyanpur Tola"
    ],
    "wof:name":"Kalyanpur Tola",
    "wof:placetype":"locality",
    "wof:population":982
},
  "geometry": {"coordinates":[86.70358899999999,25.540545],"type":"Point"}
}