{
  "type": "Feature",
  "properties": {
    "gn:admin1_code":"36",
    "gn:admin2_code":"142.0",
    "gn:asciiname":"Nagla Chhittu",
    "gn:country_code":"IN",
    "gn:dem":192,
    "gn:feature_class":"P",
    "gn:feature_code":"PPL",
    "gn:name":"Nagla Chhittu",
    "gn:population":0,
    "gn:timezone":"Asia/Kolkata",
    "iso:country":"IN",
    "ks:ks_name":"Nagla Chhattu",
    "ks:ks_pop":241,
    "ks:ks_type":"VILLAGE",
    "name:eng_x_preferred":[
        "Nagla Chhattu"
    ],
    "name:eng_x_variant":[
        "Nagla Chhittu"
    ],
    "wof:name":"Nagla Chhattu",
    "wof:placetype":"locality",
    "wof:population":241
},
  "geometry": {"coordinates":[78.22743,28.146637],"type":"Point"}
}