{
  "type": "Feature",
  "properties": {
    "iso:country":"IN",
    "ks:ks_alt_nam":"LADWASTI YERALA RIVER GP WASTI MORE MALA",
    "ks:ks_name":"Ladwasti Yerala River Gp Wasti More Mala",
    "ks:ks_pop":50,
    "ks:ks_type":"HABITATION",
    "name:eng_x_preferred":[
        "Ladwasti Yerala River Gp Wasti More Mala"
    ],
    "wof:name":"Ladwasti Yerala River Gp Wasti More Mala",
    "wof:placetype":"locality",
    "wof:population":50
},
  "geometry": {"coordinates":[74.543761,17.099709],"type":"Point"}
}