{
  "type": "Feature",
  "properties": {
    "gn:admin1_code":"36",
    "gn:admin2_code":"178.0",
    "gn:asciiname":"Punthar",
    "gn:country_code":"IN",
    "gn:dem":90,
    "gn:feature_class":"P",
    "gn:feature_code":"PPL",
    "gn:name":"Punthar",
    "gn:population":0,
    "gn:timezone":"Asia/Kolkata",
    "iso:country":"IN",
    "ks:ks_name":"Punthar",
    "ks:ks_pop":2687,
    "ks:ks_type":"VILLAGE",
    "name:eng_x_preferred":[
        "Punthar"
    ],
    "wof:name":"Punthar",
    "wof:placetype":"locality",
    "wof:population":2687
},
  "geometry": {"coordinates":[82.677997,26.529649],"type":"Point"}
}