{
  "type": "Feature",
  "properties": {
    "gn:admin1_code":"23.0",
    "gn:admin2_code":"043",
    "gn:asciiname":"Usman Khera",
    "gn:country_code":"IN",
    "gn:dem":175,
    "gn:feature_class":"P",
    "gn:feature_code":"PPL",
    "gn:name":"Usm\u0101n Khera",
    "gn:population":0,
    "gn:timezone":"Asia/Kolkata",
    "iso:country":"IN",
    "ks:ks_alt_nam":"Usm\u0101n Khera",
    "ks:ks_name":"Usman Khera",
    "ks:ks_pop":2156,
    "ks:ks_type":"VILLAGE",
    "name:eng_x_preferred":[
        "Usman Khera"
    ],
    "name:eng_x_variant":[
        "Usm\u0101n Khera"
    ],
    "wof:name":"Usman Khera",
    "wof:placetype":"locality",
    "wof:population":2156
},
  "geometry": {"coordinates":[73.90767099999999,30.021612],"type":"Point"}
}