{
  "type": "Feature",
  "properties": {
    "iso:country":"IN",
    "ks:ks_name":"Jifalta",
    "ks:ks_pop":113,
    "ks:ks_type":"HABITATION",
    "name:eng_x_preferred":[
        "Jifalta"
    ],
    "wof:name":"Jifalta",
    "wof:placetype":"locality",
    "wof:population":113
},
  "geometry": {"coordinates":[79.706073,29.52498],"type":"Point"}
}