{
  "type": "Feature",
  "properties": {
    "gn:admin1_code":"35.0",
    "gn:admin2_code":"455.0",
    "gn:asciiname":"Bhandkhapa",
    "gn:country_code":"IN",
    "gn:dem":618,
    "gn:feature_class":"P",
    "gn:feature_code":"PPL",
    "gn:name":"Bh\u0101ndkh\u0101pa",
    "gn:population":0,
    "gn:timezone":"Asia/Kolkata",
    "iso:country":"IN",
    "wof:name":"Bhandkhapa",
    "wof:placetype":"locality"
},
  "geometry": {"coordinates":[78.97943000000002,21.92548],"type":"Point"}
}