{
  "type": "Feature",
  "properties": {
    "gn:admin1_code":"35.0",
    "gn:admin2_code":"431.0",
    "gn:asciiname":"Chirhula",
    "gn:country_code":"IN",
    "gn:dem":516,
    "gn:feature_class":"P",
    "gn:feature_code":"PPL",
    "gn:name":"Chirhula",
    "gn:population":0,
    "gn:timezone":"Asia/Kolkata",
    "iso:country":"IN",
    "wof:name":"Chirhula",
    "wof:placetype":"locality"
},
  "geometry": {"coordinates":[80.84629,23.39092],"type":"Point"}
}