{
  "type": "Feature",
  "properties": {
    "iso:country":"IN",
    "ks:ks_name":"Athagandi",
    "ks:ks_pop":99,
    "ks:ks_type":"VILLAGE",
    "name:eng_x_preferred":[
        "Athagandi"
    ],
    "wof:name":"Athagandi",
    "wof:placetype":"locality",
    "wof:population":99
},
  "geometry": {"coordinates":[86.68535300000001,22.035528],"type":"Point"}
}