{
  "type": "Feature",
  "properties": {
    "iso:country":"IN",
    "ks:ks_name":"15 NGC",
    "ks:ks_pop":9,
    "ks:ks_type":"VILLAGE",
    "name:eng_x_preferred":[
        "15 NGC"
    ],
    "wof:name":"15 NGC",
    "wof:placetype":"locality",
    "wof:population":9
},
  "geometry": {"coordinates":[74.50347499999999,29.585005],"type":"Point"}
}