{
  "type": "Feature",
  "properties": {
    "gn:admin1_code":"36.0",
    "gn:admin2_code":"135.0",
    "gn:asciiname":"Jaitwara",
    "gn:country_code":"IN",
    "gn:dem":190,
    "gn:feature_class":"P",
    "gn:feature_code":"PPL",
    "gn:name":"Jaitw\u0101ra",
    "gn:population":0,
    "gn:timezone":"Asia/Kolkata",
    "iso:country":"IN",
    "name:ben_x_preferred":[
        "\u099c\u09be\u09af\u09bc\u09bf\u09a4\u0993\u09af\u09bc\u09be\u09b0\u09be"
    ],
    "name:bpy_x_preferred":[
        "\u099c\u09be\u09af\u09bc\u09bf\u09a4\u09f1\u09be\u09b0\u09be"
    ],
    "name:hin_x_preferred":[
        "\u091c\u0948\u0924\u0935\u093e\u0930\u093e"
    ],
    "name:ita_x_preferred":[
        "Jaitwara"
    ],
    "name:mlg_x_preferred":[
        "Jaitwara"
    ],
    "name:msa_x_preferred":[
        "Jaitwara"
    ],
    "name:new_x_preferred":[
        "\u091c\u0948\u0924\u0935\u093e\u0930\u093e"
    ],
    "name:nld_x_preferred":[
        "Jaitwara"
    ],
    "name:por_x_preferred":[
        "Jaitwara"
    ],
    "name:urd_x_preferred":[
        "\u062c\u06cc\u062a\u0648\u0627\u0631\u06c1"
    ],
    "name:vie_x_preferred":[
        "Jaitwara"
    ],
    "name:zho_x_preferred":[
        "\u8d3e\u4f0a\u7279\u74e6\u62c9"
    ],
    "wof:name":"Jaitwara",
    "wof:placetype":"locality"
},
  "geometry": {"coordinates":[78.83796,28.71271],"type":"Point"}
}