{
  "type": "Feature",
  "properties": {
    "iso:country":"IN",
    "ks:ks_name":"Belami",
    "ks:ks_pop":25,
    "ks:ks_type":"HABITATION",
    "name:eng_x_preferred":[
        "Belami"
    ],
    "wof:name":"Belami",
    "wof:placetype":"locality",
    "wof:population":25
},
  "geometry": {"coordinates":[82.644188,23.526668],"type":"Point"}
}