{
  "type": "Feature",
  "properties": {
    "gn:admin1_code":"36.0",
    "gn:admin2_code":"150.0",
    "gn:asciiname":"Meondi Kalan",
    "gn:country_code":"IN",
    "gn:dem":174,
    "gn:feature_class":"P",
    "gn:feature_code":"PPL",
    "gn:name":"Meondi Kal\u0101n",
    "gn:population":0,
    "gn:timezone":"Asia/Kolkata",
    "iso:country":"IN",
    "ks:ks_alt_nam":"Meondi Kal\u0101n",
    "ks:ks_name":"Meondi Kalan",
    "ks:ks_type":"VILLAGE",
    "name:eng_x_preferred":[
        "Meondi Kalan"
    ],
    "name:eng_x_variant":[
        "Meondi Kal\u0101n"
    ],
    "wof:name":"Meondi Kalan",
    "wof:placetype":"locality"
},
  "geometry": {"coordinates":[79.567442,28.354982],"type":"Point"}
}