{
  "type": "Feature",
  "properties": {
    "gn:admin1_code":"13.0",
    "gn:admin2_code":"595.0",
    "gn:asciiname":"Pottanikad",
    "gn:country_code":"IN",
    "gn:dem":40,
    "gn:feature_class":"P",
    "gn:feature_code":"PPL",
    "gn:name":"Pottanik\u0101d",
    "gn:population":0,
    "gn:timezone":"Asia/Kolkata",
    "iso:country":"IN",
    "ks:ks_name":"Pothanikkad",
    "ks:ks_pop":17563,
    "ks:ks_type":"VILLAGE",
    "name:eng_x_preferred":[
        "Pothanikkad"
    ],
    "name:eng_x_variant":[
        "Pottanikad"
    ],
    "wof:name":"Pothanikkad",
    "wof:placetype":"locality",
    "wof:population":17563
},
  "geometry": {"coordinates":[76.682084,10.02024],"type":"Point"}
}