{
  "type": "Feature",
  "properties": {
    "gn:admin1_code":"38.0",
    "gn:admin2_code":"358.0",
    "gn:asciiname":"Majhauli",
    "gn:country_code":"IN",
    "gn:dem":240,
    "gn:feature_class":"P",
    "gn:feature_code":"PPL",
    "gn:name":"Majhaul\u012b",
    "gn:population":0,
    "gn:timezone":"Asia/Kolkata",
    "iso:country":"IN",
    "ks:ks_alt_nam":"Majhaul\u012b",
    "ks:ks_name":"Majhauli",
    "ks:ks_pop":811,
    "ks:ks_type":"VILLAGE",
    "ks:ks_uagg_main":0,
    "name:eng_x_preferred":[
        "Majhauli"
    ],
    "name:eng_x_variant":[
        "Majhaul\u012b"
    ],
    "wof:name":"Majhauli",
    "wof:placetype":"neighbourhood",
    "wof:population":811
},
  "geometry": {"coordinates":[84.131614,24.166542],"type":"Point"}
}