{
  "type": "Feature",
  "properties": {
    "gn:admin1_code":"23",
    "gn:admin2_code":"41.0",
    "gn:asciiname":"Alaur",
    "gn:country_code":"IN",
    "gn:dem":264,
    "gn:feature_class":"P",
    "gn:feature_code":"PPL",
    "gn:name":"Alaur",
    "gn:population":0,
    "gn:timezone":"Asia/Kolkata",
    "iso:country":"IN",
    "ks:ks_name":"Alaur",
    "ks:ks_pop":1644,
    "ks:ks_type":"VILLAGE",
    "ks:ks_uagg_main":0,
    "name:eng_x_preferred":[
        "Alaur"
    ],
    "name:pan_x_preferred":[
        "\u0a05\u0a32\u0a4c\u0a5c"
    ],
    "wof:name":"Alaur",
    "wof:placetype":"locality",
    "wof:population":1644
},
  "geometry": {"coordinates":[76.273105,30.680942],"type":"Point"}
}