{
  "type": "Feature",
  "properties": {
    "iso:country":"IN",
    "ks:ks_name":"Lakkibeelu",
    "ks:ks_pop":18,
    "ks:ks_type":"HABITATION",
    "name:eng_x_preferred":[
        "Lakkibeelu"
    ],
    "wof:name":"Lakkibeelu",
    "wof:placetype":"locality",
    "wof:population":18
},
  "geometry": {"coordinates":[75.241266,13.671087],"type":"Point"}
}