{
  "type": "Feature",
  "properties": {
    "gn:admin1_code":"35",
    "gn:admin2_code":"423.0",
    "gn:asciiname":"Gongoi",
    "gn:country_code":"IN",
    "gn:dem":445,
    "gn:feature_class":"P",
    "gn:feature_code":"PPL",
    "gn:name":"Gongoi",
    "gn:population":0,
    "gn:timezone":"Asia/Kolkata",
    "iso:country":"IN",
    "name:und_x_variant":[
        "Godh\u0101ri"
    ],
    "wof:name":"Gongoi",
    "wof:placetype":"locality"
},
  "geometry": {"coordinates":[77.45311,25.3215],"type":"Point"}
}