{
  "type": "Feature",
  "properties": {
    "iso:country":"IN",
    "ks:ks_alt_nam":"Beeggai vattam",
    "ks:ks_name":"Beeggai Vattam",
    "ks:ks_pop":110,
    "ks:ks_type":"HABITATION",
    "name:eng_x_preferred":[
        "Beeggai Vattam"
    ],
    "wof:name":"Beeggai Vattam",
    "wof:placetype":"locality",
    "wof:population":110
},
  "geometry": {"coordinates":[78.529887,12.578637],"type":"Point"}
}