{
  "type": "Feature",
  "properties": {
    "iso:country":"IN",
    "ks:ks_name":"Rala",
    "ks:ks_pop":132,
    "ks:ks_type":"VILLAGE",
    "name:eng_x_preferred":[
        "Rala"
    ],
    "wof:name":"Rala",
    "wof:placetype":"locality",
    "wof:population":132
},
  "geometry": {"coordinates":[78.216577,31.16711],"type":"Point"}
}