{
  "type": "Feature",
  "properties": {
    "iso:country":"IN",
    "ks:ks_name":"Hathikhana",
    "ks:ks_pop":0,
    "ks:ks_type":"VILLAGE",
    "name:eng_x_preferred":[
        "Hathikhana"
    ],
    "wof:name":"Hathikhana",
    "wof:placetype":"locality",
    "wof:population":0
},
  "geometry": {"coordinates":[87.14342499999999,22.807725],"type":"Point"}
}