{
  "type": "Feature",
  "properties": {
    "iso:country":"IN",
    "ks:ks_alt_nam":"HARIDAS TEA ESTATE",
    "ks:ks_name":"Haridas Tea Estate",
    "ks:ks_pop":346,
    "ks:ks_type":"HABITATION",
    "name:eng_x_preferred":[
        "Haridas Tea Estate"
    ],
    "wof:name":"Haridas Tea Estate",
    "wof:placetype":"locality",
    "wof:population":346
},
  "geometry": {"coordinates":[91.34357799999999,23.973925],"type":"Point"}
}