{
  "type": "Feature",
  "properties": {
    "iso:country":"IN",
    "ks:ks_name":"Shantipura",
    "ks:ks_pop":571,
    "ks:ks_type":"HABITATION",
    "name:eng_x_preferred":[
        "Shantipura"
    ],
    "wof:name":"Shantipura",
    "wof:placetype":"locality",
    "wof:population":571
},
  "geometry": {"coordinates":[72.615475,22.888464],"type":"Point"}
}