{
  "type": "Feature",
  "properties": {
    "iso:country":"IN",
    "ks:ks_name":"Andwa Puraini",
    "ks:ks_pop":80,
    "ks:ks_type":"VILLAGE",
    "name:eng_x_preferred":[
        "Andwa Puraini"
    ],
    "wof:name":"Andwa Puraini",
    "wof:placetype":"locality",
    "wof:population":80
},
  "geometry": {"coordinates":[78.1006,26.756808],"type":"Point"}
}