{
  "type": "Feature",
  "properties": {
    "iso:country":"IN",
    "ks:ks_name":"Sattiyakkudi",
    "ks:ks_pop":90,
    "ks:ks_type":"HABITATION",
    "name:eng_x_preferred":[
        "Sattiyakkudi"
    ],
    "wof:name":"Sattiyakkudi",
    "wof:placetype":"locality",
    "wof:population":90
},
  "geometry": {"coordinates":[79.058645,10.00946],"type":"Point"}
}