{
  "type": "Feature",
  "properties": {
    "gn:admin1_code":"12",
    "gn:admin2_code":"14.0",
    "gn:asciiname":"Zabilpur",
    "gn:country_code":"IN",
    "gn:dem":1601,
    "gn:feature_class":"P",
    "gn:feature_code":"PPL",
    "gn:name":"Zabilpur",
    "gn:population":0,
    "gn:timezone":"Asia/Kolkata",
    "iso:country":"IN",
    "wof:name":"Zabilpur",
    "wof:placetype":"locality"
},
  "geometry": {"coordinates":[75.09954999999999,33.78222],"type":"Point"}
}