{
  "type": "Feature",
  "properties": {
    "iso:country":"IN",
    "ks:ks_name":"Gubbimane",
    "ks:ks_pop":55,
    "ks:ks_type":"HABITATION",
    "name:eng_x_preferred":[
        "Gubbimane"
    ],
    "wof:name":"Gubbimane",
    "wof:placetype":"locality",
    "wof:population":55
},
  "geometry": {"coordinates":[74.746045,14.553479],"type":"Point"}
}