{
  "type": "Feature",
  "properties": {
    "iso:country":"IN",
    "ks:ks_name":"Tola Hethbatia",
    "ks:ks_pop":226,
    "ks:ks_type":"VILLAGE",
    "name:eng_x_preferred":[
        "Tola Hethbatia"
    ],
    "wof:name":"Tola Hethbatia",
    "wof:placetype":"locality",
    "wof:population":226
},
  "geometry": {"coordinates":[86.378056,24.620121],"type":"Point"}
}