{
  "type": "Feature",
  "properties": {
    "iso:country":"IN",
    "ks:ks_alt_nam":"Janardhanswamy nagarr",
    "ks:ks_name":"Janardhanswamy Nagarr",
    "ks:ks_pop":384,
    "ks:ks_type":"HABITATION",
    "name:eng_x_preferred":[
        "Janardhanswamy Nagarr"
    ],
    "wof:name":"Janardhanswamy Nagarr",
    "wof:placetype":"locality",
    "wof:population":384
},
  "geometry": {"coordinates":[74.0732,20.0749],"type":"Point"}
}