{
  "type": "Feature",
  "properties": {
    "iso:country":"IN",
    "ks:ks_name":"North Tola",
    "ks:ks_pop":769,
    "ks:ks_type":"HABITATION",
    "name:eng_x_preferred":[
        "North Tola"
    ],
    "wof:name":"North Tola",
    "wof:placetype":"locality",
    "wof:population":769
},
  "geometry": {"coordinates":[85.828029,25.86063],"type":"Point"}
}