{
  "type": "Feature",
  "properties": {
    "iso:country":"IN",
    "ks:ks_alt_nam":"1 SVSM-B",
    "ks:ks_name":"1 Svsm-b",
    "ks:ks_pop":25,
    "ks:ks_type":"HABITATION",
    "name:eng_x_preferred":[
        "1 Svsm-b"
    ],
    "wof:name":"1 Svsm-b",
    "wof:placetype":"locality",
    "wof:population":25
},
  "geometry": {"coordinates":[73.55805599999999,29.266111],"type":"Point"}
}