{
  "type": "Feature",
  "properties": {
    "iso:country":"IN",
    "ks:ks_alt_nam":"Pure Ghouri ka Misra",
    "ks:ks_name":"Pure Ghouri Ka Misra",
    "ks:ks_pop":160,
    "ks:ks_type":"HABITATION",
    "name:eng_x_preferred":[
        "Pure Ghouri Ka Misra"
    ],
    "wof:name":"Pure Ghouri Ka Misra",
    "wof:placetype":"locality",
    "wof:population":160
},
  "geometry": {"coordinates":[82.080809,26.438091],"type":"Point"}
}