{
  "type": "Feature",
  "properties": {
    "iso:country":"IN",
    "ks:ks_name":"Kharbanda",
    "ks:ks_pop":652,
    "ks:ks_type":"HABITATION",
    "name:eng_x_preferred":[
        "Kharbanda"
    ],
    "wof:name":"Kharbanda",
    "wof:placetype":"locality",
    "wof:population":652
},
  "geometry": {"coordinates":[86.586928,22.386181],"type":"Point"}
}