{
  "type": "Feature",
  "properties": {
    "gn:admin1_code":"23.0",
    "gn:admin2_code":"49.0",
    "gn:asciiname":"Rasulpur",
    "gn:country_code":"IN",
    "gn:dem":239,
    "gn:feature_class":"P",
    "gn:feature_code":"PPL",
    "gn:name":"Ras\u016blpur",
    "gn:population":0,
    "gn:timezone":"Asia/Kolkata",
    "iso:country":"IN",
    "wof:name":"Rasulpur",
    "wof:placetype":"locality"
},
  "geometry": {"coordinates":[75.12143,31.62032],"type":"Point"}
}