{
  "type": "Feature",
  "properties": {
    "iso:country":"IN",
    "ks:ks_name":"Umjhar",
    "ks:ks_pop":462,
    "ks:ks_type":"VILLAGE",
    "name:eng_x_preferred":[
        "Umjhar"
    ],
    "wof:name":"Umjhar",
    "wof:placetype":"locality",
    "wof:population":462
},
  "geometry": {"coordinates":[82.59731600000001,23.752138],"type":"Point"}
}