{
  "type": "Feature",
  "properties": {
    "iso:country":"IN",
    "ks:ks_name":"Udlakhedi",
    "ks:ks_pop":169,
    "ks:ks_type":"VILLAGE",
    "name:eng_x_preferred":[
        "Udlakhedi"
    ],
    "wof:name":"Udlakhedi",
    "wof:placetype":"locality",
    "wof:population":169
},
  "geometry": {"coordinates":[77.572929,23.60605],"type":"Point"}
}