{
  "type": "Feature",
  "properties": {
    "iso:country":"IN",
    "ks:ks_name":"Khapari Jarani",
    "ks:ks_pop":923,
    "ks:ks_type":"VILLAGE",
    "name:eng_x_preferred":[
        "Khapari Jarani"
    ],
    "wof:name":"Khapari Jarani",
    "wof:placetype":"locality",
    "wof:population":923
},
  "geometry": {"coordinates":[92.528278,26.163278],"type":"Point"}
}