{
  "type": "Feature",
  "properties": {
    "gn:admin1_code":"19.0",
    "gn:admin2_code":"561.0",
    "gn:asciiname":"Upnal",
    "gn:country_code":"IN",
    "gn:dem":626,
    "gn:feature_class":"P",
    "gn:feature_code":"PPL",
    "gn:name":"Upn\u0101l",
    "gn:population":0,
    "gn:timezone":"Asia/Kolkata",
    "iso:country":"IN",
    "ks:ks_alt_nam":"Upn\u0101l",
    "ks:ks_name":"Upnal",
    "ks:ks_type":"VILLAGE",
    "name:eng_x_preferred":[
        "Upnal"
    ],
    "name:eng_x_variant":[
        "Upn\u0101l"
    ],
    "wof:name":"Upnal",
    "wof:placetype":"locality"
},
  "geometry": {"coordinates":[75.43928,15.073145],"type":"Point"}
}