{
  "type": "Feature",
  "properties": {
    "gn:admin1_code":"35.0",
    "gn:admin2_code":"433",
    "gn:asciiname":"Digau Kalan",
    "gn:country_code":"IN",
    "gn:dem":446,
    "gn:feature_class":"P",
    "gn:feature_code":"PPL",
    "gn:name":"Dig\u0101u Kal\u0101n",
    "gn:population":0,
    "gn:timezone":"Asia/Kolkata",
    "iso:country":"IN",
    "name:und_x_variant":[
        "Dig\u0101u",
        "Dig\u0101u Kal\u0101n"
    ],
    "wof:name":"Digau Kalan",
    "wof:placetype":"locality"
},
  "geometry": {"coordinates":[75.15264999999999,24.0434],"type":"Point"}
}