{
  "type": "Feature",
  "properties": {
    "iso:country":"IN",
    "ks:ks_alt_nam":"sathiyavadi",
    "ks:ks_name":"Sathiyavadi",
    "ks:ks_pop":502,
    "ks:ks_type":"HABITATION",
    "name:eng_x_preferred":[
        "Sathiyavadi"
    ],
    "wof:name":"Sathiyavadi",
    "wof:placetype":"locality",
    "wof:population":502
},
  "geometry": {"coordinates":[79.542613,10.785008],"type":"Point"}
}