{
  "type": "Feature",
  "properties": {
    "gn:admin1_code":"36.0",
    "gn:admin2_code":"150.0",
    "gn:asciiname":"Kashipur",
    "gn:country_code":"IN",
    "gn:dem":176,
    "gn:feature_class":"P",
    "gn:feature_code":"PPL",
    "gn:name":"K\u0101sh\u012bpur",
    "gn:population":0,
    "gn:timezone":"Asia/Kolkata",
    "iso:country":"IN",
    "name:hin_x_preferred":[
        "\u0915\u093e\u0936\u0940\u092a\u0941\u0930"
    ],
    "name:rus_x_preferred":[
        "\u041a\u0430\u0448\u0438\u043f\u0443\u0440"
    ],
    "wof:name":"Kashipur",
    "wof:placetype":"neighbourhood"
},
  "geometry": {"coordinates":[79.29178,28.57113],"type":"Point"}
}