{
  "type": "Feature",
  "properties": {
    "gn:admin1_code":"9.0",
    "gn:admin2_code":"477.0",
    "gn:asciiname":"Vadinar",
    "gn:country_code":"IN",
    "gn:dem":20,
    "gn:feature_class":"P",
    "gn:feature_code":"PPL",
    "gn:name":"Vadinar",
    "gn:population":0,
    "gn:timezone":"Asia/Kolkata",
    "iso:country":"IN",
    "wof:name":"Vadinar",
    "wof:placetype":"locality"
},
  "geometry": {"coordinates":[69.71954000000001,22.39754],"type":"Point"}
}