{
  "type": "Feature",
  "properties": {
    "iso:country":"IN",
    "ks:ks_name":"Gaothanwadi",
    "ks:ks_pop":191,
    "ks:ks_type":"HABITATION",
    "name:eng_x_preferred":[
        "Gaothanwadi"
    ],
    "wof:name":"Gaothanwadi",
    "wof:placetype":"locality",
    "wof:population":191
},
  "geometry": {"coordinates":[73.908794,15.854629],"type":"Point"}
}