{
  "type": "Feature",
  "properties": {
    "gn:admin1_code":"24",
    "gn:admin2_code":"112.0",
    "gn:asciiname":"Kurchi",
    "gn:country_code":"IN",
    "gn:dem":307,
    "gn:feature_class":"P",
    "gn:feature_code":"PPL",
    "gn:name":"Kurchi",
    "gn:population":0,
    "gn:timezone":"Asia/Kolkata",
    "iso:country":"IN",
    "wof:name":"Kurchi",
    "wof:placetype":"locality"
},
  "geometry": {"coordinates":[73.24061,26.88745],"type":"Point"}
}