{
  "type": "Feature",
  "properties": {
    "iso:country":"IN",
    "ks:ks_name":"Saraiya",
    "ks:ks_pop":1263,
    "ks:ks_type":"HABITATION",
    "name:eng_x_preferred":[
        "Saraiya"
    ],
    "wof:name":"Saraiya",
    "wof:placetype":"locality",
    "wof:population":1263
},
  "geometry": {"coordinates":[80.56448899999999,27.967785],"type":"Point"}
}