{
  "type": "Feature",
  "properties": {
    "iso:country":"IN",
    "ks:ks_name":"Jagadish Nagar",
    "ks:ks_pop":609,
    "ks:ks_type":"VILLAGE",
    "name:eng_x_preferred":[
        "Jagadish Nagar"
    ],
    "wof:name":"Jagadish Nagar",
    "wof:placetype":"locality",
    "wof:population":609
},
  "geometry": {"coordinates":[88.274582,22.247895],"type":"Point"}
}