{
  "type": "Feature",
  "properties": {
    "iso:country":"IN",
    "ks:ks_name":"Dangjuri",
    "ks:ks_pop":0,
    "ks:ks_type":"VILLAGE",
    "name:eng_x_preferred":[
        "Dangjuri"
    ],
    "wof:name":"Dangjuri",
    "wof:placetype":"locality",
    "wof:population":0
},
  "geometry": {"coordinates":[87.019671,23.058365],"type":"Point"}
}