{
  "type": "Feature",
  "properties": {
    "gn:admin1_code":"21.0",
    "gn:admin2_code":"389.0",
    "gn:asciiname":"Tumiringara",
    "gn:country_code":"IN",
    "gn:dem":447,
    "gn:feature_class":"P",
    "gn:feature_code":"PPL",
    "gn:name":"Tumiringara",
    "gn:population":0,
    "gn:timezone":"Asia/Kolkata",
    "iso:country":"IN",
    "wof:name":"Tumiringara",
    "wof:placetype":"locality"
},
  "geometry": {"coordinates":[83.96809,18.89474],"type":"Point"}
}