{
  "type": "Feature",
  "properties": {
    "gn:admin1_code":"40",
    "gn:admin2_code":"532.0",
    "gn:asciiname":"Mamda",
    "gn:country_code":"IN",
    "gn:dem":338,
    "gn:feature_class":"P",
    "gn:feature_code":"PPL",
    "gn:name":"M\u0101mda",
    "gn:population":0,
    "gn:timezone":"Asia/Kolkata",
    "iso:country":"IN",
    "name:ceb_x_preferred":[
        "M\u0101mda"
    ],
    "name:new_x_preferred":[
        "\u092e\u093e\u092e\u0921 \u092e\u0923\u094d\u0921\u0932"
    ],
    "name:pam_x_preferred":[
        "Mamda"
    ],
    "name:spa_x_preferred":[
        "Mamda"
    ],
    "name:swe_x_preferred":[
        "M\u0101mda"
    ],
    "name:tel_x_preferred":[
        "\u0c2e\u0c3e\u0c2e\u0c21 \u0c2e\u0c02\u0c21\u0c32\u0c02"
    ],
    "name:und_x_variant":[
        "M\u0101mda"
    ],
    "wof:name":"Mamda",
    "wof:placetype":"locality"
},
  "geometry": {"coordinates":[78.5219,19.07626],"type":"Point"}
}