{
  "type": "Feature",
  "properties": {
    "iso:country":"IN",
    "ks:ks_alt_nam":"CHANDANIYON KA TALA",
    "ks:ks_name":"Chandaniyon Ka Tala",
    "ks:ks_pop":533,
    "ks:ks_type":"HABITATION",
    "name:eng_x_preferred":[
        "Chandaniyon Ka Tala"
    ],
    "wof:name":"Chandaniyon Ka Tala",
    "wof:placetype":"locality",
    "wof:population":533
},
  "geometry": {"coordinates":[70.99620299999999,25.38897],"type":"Point"}
}