{
  "type": "Feature",
  "properties": {
    "iso:country":"IN",
    "ks:ks_name":"Chak Khetab",
    "ks:ks_pop":124,
    "ks:ks_type":"VILLAGE",
    "name:eng_x_preferred":[
        "Chak Khetab"
    ],
    "wof:name":"Chak Khetab",
    "wof:placetype":"locality",
    "wof:population":124
},
  "geometry": {"coordinates":[88.867152,25.227186],"type":"Point"}
}