{
  "type": "Feature",
  "properties": {
    "iso:country":"IN",
    "ks:ks_name":"Dhangadpada",
    "ks:ks_pop":254,
    "ks:ks_type":"HABITATION",
    "name:eng_x_preferred":[
        "Dhangadpada"
    ],
    "wof:name":"Dhangadpada",
    "wof:placetype":"locality",
    "wof:population":254
},
  "geometry": {"coordinates":[72.914174,19.894312],"type":"Point"}
}