{
  "type": "Feature",
  "properties": {
    "iso:country":"IN",
    "qs:name":"Beeramballi",
    "qs:name_adm0":"India",
    "qs:name_adm1":"Karnataka",
    "qs:photos":78,
    "qs:photos_1k":16,
    "qs:photos_9k":1,
    "qs:photos_9r":3,
    "qs:photos_all":78,
    "qs:photos_sr":3,
    "qs:placetype":"Town",
    "qs:pop_sr":"0",
    "wof:name":"Beeramballi",
    "wof:placetype":"locality"
},
  "geometry": {"coordinates":[76.266918,11.92547],"type":"Point"}
}