{
  "type": "Feature",
  "properties": {
    "iso:country":"IN",
    "ks:ks_name":"Tanti Tola 2",
    "ks:ks_pop":72,
    "ks:ks_type":"HABITATION",
    "ks:ks_uagg_main":0,
    "name:eng_x_preferred":[
        "Tanti Tola 2"
    ],
    "wof:name":"Tanti Tola 2",
    "wof:placetype":"neighbourhood",
    "wof:population":72
},
  "geometry": {"coordinates":[86.59350999999999,25.793465],"type":"Point"}
}