{
  "type": "Feature",
  "properties": {
    "iso:country":"IN",
    "ks:ks_name":"Naladiapalanda",
    "ks:ks_pop":596,
    "ks:ks_type":"VILLAGE",
    "name:eng_x_preferred":[
        "Naladiapalanda"
    ],
    "wof:name":"Naladiapalanda",
    "wof:placetype":"locality",
    "wof:population":596
},
  "geometry": {"coordinates":[86.488023,20.334074],"type":"Point"}
}