{
  "type": "Feature",
  "properties": {
    "gn:admin1_code":"21",
    "gn:admin2_code":"371.0",
    "gn:asciiname":"Kholjamkani",
    "gn:country_code":"IN",
    "gn:dem":215,
    "gn:feature_class":"P",
    "gn:feature_code":"PPL",
    "gn:name":"Kholjamk\u0101ni",
    "gn:population":0,
    "gn:timezone":"Asia/Kolkata",
    "iso:country":"IN",
    "ks:ks_alt_nam":"Kholjamk\u0101ni",
    "ks:ks_name":"Kholjamkani",
    "ks:ks_pop":73,
    "ks:ks_type":"VILLAGE",
    "name:eng_x_preferred":[
        "Kholjamkani"
    ],
    "name:eng_x_variant":[
        "Kholjamk\u0101ni"
    ],
    "wof:name":"Kholjamkani",
    "wof:placetype":"locality",
    "wof:population":73
},
  "geometry": {"coordinates":[83.74112,21.759244],"type":"Point"}
}