{
  "type": "Feature",
  "properties": {
    "gn:admin1_code":"21",
    "gn:admin2_code":"371.0",
    "gn:asciiname":"Kholjamkani",
    "gn:country_code":"IN",
    "gn:dem":215,
    "gn:feature_class":"P",
    "gn:feature_code":"PPL",
    "gn:name":"Kholjamk\u0101ni",
    "gn:population":0,
    "gn:timezone":"Asia/Kolkata",
    "iso:country":"IN",
    "wof:name":"Kholjamkani",
    "wof:placetype":"locality"
},
  "geometry": {"coordinates":[83.74112,21.75917],"type":"Point"}
}