{
  "type": "Feature",
  "properties": {
    "iso:country":"IN",
    "ks:ks_name":"Pang Bank Padi Rd End",
    "ks:ks_pop":837,
    "ks:ks_type":"HABITATION",
    "ks:ks_uagg_main":0,
    "name:eng_x_preferred":[
        "Pang Bank Padi Rd End"
    ],
    "wof:name":"Pang Bank Padi Rd End",
    "wof:placetype":"neighbourhood",
    "wof:population":837
},
  "geometry": {"coordinates":[76.08407699999999,10.970052],"type":"Point"}
}