{
  "type": "Feature",
  "properties": {
    "iso:country":"IN",
    "ks:ks_name":"Dodaki",
    "ks:ks_pop":2699,
    "ks:ks_type":"VILLAGE",
    "name:eng_x_preferred":[
        "Dodaki"
    ],
    "wof:name":"Dodaki",
    "wof:placetype":"locality",
    "wof:population":2699
},
  "geometry": {"coordinates":[82.151731,24.335937],"type":"Point"}
}