{
  "type": "Feature",
  "properties": {
    "iso:country":"IN",
    "ks:ks_name":"Manjuguda",
    "ks:ks_pop":283,
    "ks:ks_type":"VILLAGE",
    "name:eng_x_preferred":[
        "Manjuguda"
    ],
    "wof:name":"Manjuguda",
    "wof:placetype":"locality",
    "wof:population":283
},
  "geometry": {"coordinates":[82.901982,18.259081],"type":"Point"}
}