{
  "type": "Feature",
  "properties": {
    "gn:admin1_code":"11.0",
    "gn:admin2_code":"32.0",
    "gn:asciiname":"Nihalgarh",
    "gn:country_code":"IN",
    "gn:dem":446,
    "gn:feature_class":"P",
    "gn:feature_code":"PPL",
    "gn:name":"Nih\u0101lgarh",
    "gn:population":0,
    "gn:timezone":"Asia/Kolkata",
    "iso:country":"IN",
    "name:mal_x_preferred":[
        "\u0d28\u0d3f\u0d39\u0d7d\u0d17\u0d7c"
    ],
    "wof:name":"Nihalgarh",
    "wof:placetype":"locality"
},
  "geometry": {"coordinates":[77.6331,30.47202],"type":"Point"}
}