{
  "type": "Feature",
  "properties": {
    "iso:country":"IN",
    "ks:ks_name":"Kodaipur",
    "ks:ks_pop":1242,
    "ks:ks_type":"VILLAGE",
    "ks:ks_uagg_main":0,
    "name:eng_x_preferred":[
        "Kodaipur"
    ],
    "wof:name":"Kodaipur",
    "wof:placetype":"neighbourhood",
    "wof:population":1242
},
  "geometry": {"coordinates":[87.59486200000001,23.851931],"type":"Point"}
}