{
  "type": "Feature",
  "properties": {
    "gn:admin1_code":"36",
    "gn:admin2_code":"144.0",
    "gn:asciiname":"Sajawalpur",
    "gn:country_code":"IN",
    "gn:dem":178,
    "gn:feature_class":"P",
    "gn:feature_code":"PPL",
    "gn:name":"Saj\u0101walpur",
    "gn:population":0,
    "gn:timezone":"Asia/Kolkata",
    "iso:country":"IN",
    "name:por_x_preferred":[
        "Sajawalpur"
    ],
    "wof:name":"Sajawalpur",
    "wof:placetype":"neighbourhood"
},
  "geometry": {"coordinates":[78.43572,27.79942],"type":"Point"}
}