{
  "type": "Feature",
  "properties": {
    "gn:admin1_code":"16",
    "gn:admin2_code":"513.0",
    "gn:asciiname":"Borgaon",
    "gn:country_code":"IN",
    "gn:dem":391,
    "gn:feature_class":"P",
    "gn:feature_code":"PPL",
    "gn:name":"Borgaon",
    "gn:population":0,
    "gn:timezone":"Asia/Kolkata",
    "iso:country":"IN",
    "ks:ks_name":"Borgaon",
    "ks:ks_type":"VILLAGE",
    "name:eng_x_preferred":[
        "Borgaon"
    ],
    "wof:name":"Borgaon",
    "wof:placetype":"locality"
},
  "geometry": {"coordinates":[76.86325600000001,18.911508],"type":"Point"}
}