{
  "type": "Feature",
  "properties": {
    "gn:admin1_code":"2.0",
    "gn:admin2_code":"553.0",
    "gn:asciiname":"Jambulapadu",
    "gn:country_code":"IN",
    "gn:dem":233,
    "gn:feature_class":"P",
    "gn:feature_code":"PPL",
    "gn:name":"Jambulap\u0101du",
    "gn:population":0,
    "gn:timezone":"Asia/Kolkata",
    "iso:country":"IN",
    "ks:ks_alt_nam":"Jambulap\u0101du",
    "ks:ks_name":"Jambulapadu",
    "ks:ks_pop":254,
    "ks:ks_type":"VILLAGE",
    "ks:ks_uagg_main":0,
    "name:eng_x_preferred":[
        "Jambulapadu"
    ],
    "name:eng_x_variant":[
        "Jambulap\u0101du"
    ],
    "wof:name":"Jambulapadu",
    "wof:placetype":"neighbourhood",
    "wof:population":254
},
  "geometry": {"coordinates":[78.04499,14.867078],"type":"Point"}
}