{
  "type": "Feature",
  "properties": {
    "iso:country":"IN",
    "ks:ks_name":"Dusadh Tola",
    "ks:ks_pop":630,
    "ks:ks_type":"HABITATION",
    "name:eng_x_preferred":[
        "Dusadh Tola"
    ],
    "wof:name":"Dusadh Tola",
    "wof:placetype":"locality",
    "wof:population":630
},
  "geometry": {"coordinates":[85.45521599999999,26.727771],"type":"Point"}
}