{
  "type": "Feature",
  "properties": {
    "iso:country":"IN",
    "ks:ks_name":"Sesau",
    "ks:ks_pop":68,
    "ks:ks_type":"VILLAGE",
    "name:eng_x_preferred":[
        "Sesau"
    ],
    "wof:name":"Sesau",
    "wof:placetype":"locality",
    "wof:population":68
},
  "geometry": {"coordinates":[71.027072,26.000244],"type":"Point"}
}