{
  "type": "Feature",
  "properties": {
    "iso:country":"IN",
    "ks:ks_alt_nam":"Ng.Dutar",
    "ks:ks_name":"Ng.dutar",
    "ks:ks_pop":214,
    "ks:ks_type":"HABITATION",
    "name:eng_x_preferred":[
        "Ng.dutar"
    ],
    "wof:name":"Ng.dutar",
    "wof:placetype":"locality",
    "wof:population":214
},
  "geometry": {"coordinates":[78.934695,27.862377],"type":"Point"}
}