{
  "type": "Feature",
  "properties": {
    "iso:country":"IN",
    "ks:ks_name":"Bheempur",
    "ks:ks_pop":96,
    "ks:ks_type":"HABITATION",
    "name:eng_x_preferred":[
        "Bheempur"
    ],
    "wof:name":"Bheempur",
    "wof:placetype":"locality",
    "wof:population":96
},
  "geometry": {"coordinates":[78.48968499999999,19.493755],"type":"Point"}
}