{
  "type": "Feature",
  "properties": {
    "iso:country":"IN",
    "ks:ks_name":"Wajenthriwada",
    "ks:ks_pop":315,
    "ks:ks_type":"HABITATION",
    "name:eng_x_preferred":[
        "Wajenthriwada"
    ],
    "wof:name":"Wajenthriwada",
    "wof:placetype":"locality",
    "wof:population":315
},
  "geometry": {"coordinates":[74.105979,14.880572],"type":"Point"}
}