{
  "type": "Feature",
  "properties": {
    "iso:country":"IN",
    "ks:ks_name":"Chikhali",
    "ks:ks_pop":125,
    "ks:ks_type":"VILLAGE",
    "name:eng_x_preferred":[
        "Chikhali"
    ],
    "wof:name":"Chikhali",
    "wof:placetype":"locality",
    "wof:population":125
},
  "geometry": {"coordinates":[73.53776999999999,18.00884],"type":"Point"}
}