{
  "type": "Feature",
  "properties": {
    "iso:country":"IN",
    "ks:ks_name":"Pandua Purba",
    "ks:ks_pop":528,
    "ks:ks_type":"HABITATION",
    "ks:ks_uagg_main":0,
    "name:eng_x_preferred":[
        "Pandua Purba"
    ],
    "wof:name":"Pandua Purba",
    "wof:placetype":"neighbourhood",
    "wof:population":528
},
  "geometry": {"coordinates":[87.478814,21.780276],"type":"Point"}
}