{
  "type": "Feature",
  "properties": {
    "iso:country":"IN",
    "ks:ks_name":"Mota Khera",
    "ks:ks_pop":132,
    "ks:ks_type":"VILLAGE",
    "ks:ks_uagg_main":0,
    "name:eng_x_preferred":[
        "Mota Khera"
    ],
    "wof:name":"Mota Khera",
    "wof:placetype":"neighbourhood",
    "wof:population":132
},
  "geometry": {"coordinates":[74.31634699999999,24.361172],"type":"Point"}
}