{
  "type": "Feature",
  "properties": {
    "iso:country":"IN",
    "ks:ks_name":"Bagmari",
    "ks:ks_pop":0,
    "ks:ks_type":"VILLAGE",
    "name:eng_x_preferred":[
        "Bagmari"
    ],
    "wof:name":"Bagmari",
    "wof:placetype":"locality",
    "wof:population":0
},
  "geometry": {"coordinates":[87.558712,23.192304],"type":"Point"}
}