{
  "type": "Feature",
  "properties": {
    "iso:country":"IN",
    "ks:ks_name":"Thalipadapu",
    "ks:ks_pop":40,
    "ks:ks_type":"HABITATION",
    "name:eng_x_preferred":[
        "Thalipadapu"
    ],
    "wof:name":"Thalipadapu",
    "wof:placetype":"locality",
    "wof:population":40
},
  "geometry": {"coordinates":[75.10855599999999,13.02057],"type":"Point"}
}