{
  "type": "Feature",
  "properties": {
    "iso:country":"IN",
    "ks:ks_name":"7 KSD",
    "ks:ks_pop":196,
    "ks:ks_type":"VILLAGE",
    "name:eng_x_preferred":[
        "7 KSD"
    ],
    "wof:name":"7 KSD",
    "wof:placetype":"locality",
    "wof:population":196
},
  "geometry": {"coordinates":[73.338447,29.354043],"type":"Point"}
}