{
  "type": "Feature",
  "properties": {
    "gn:admin1_code":"12.0",
    "gn:admin2_code":"18.0",
    "gn:asciiname":"Banpore",
    "gn:country_code":"IN",
    "gn:dem":2381,
    "gn:feature_class":"P",
    "gn:feature_code":"PPL",
    "gn:name":"Banp\u014dr\u0113",
    "gn:population":0,
    "gn:timezone":"Asia/Kolkata",
    "iso:country":"IN",
    "wof:name":"Banpore",
    "wof:placetype":"locality"
},
  "geometry": {"coordinates":[75.88473,33.23627],"type":"Point"}
}