{
  "type": "Feature",
  "properties": {
    "gn:admin1_code":"35.0",
    "gn:admin2_code":"427",
    "gn:asciiname":"Padrai",
    "gn:country_code":"IN",
    "gn:dem":483,
    "gn:feature_class":"P",
    "gn:feature_code":"PPL",
    "gn:name":"Padrai",
    "gn:population":0,
    "gn:timezone":"Asia/Kolkata",
    "iso:country":"IN",
    "ks:ks_name":"Padrai",
    "ks:ks_pop":219,
    "ks:ks_type":"VILLAGE",
    "name:eng_x_preferred":[
        "Padrai"
    ],
    "wof:name":"Padrai",
    "wof:placetype":"locality",
    "wof:population":219
},
  "geometry": {"coordinates":[78.991006,24.217716],"type":"Point"}
}