{
  "type": "Feature",
  "properties": {
    "gn:admin1_code":"35.0",
    "gn:admin2_code":"427",
    "gn:asciiname":"Padrai",
    "gn:country_code":"IN",
    "gn:dem":483,
    "gn:feature_class":"P",
    "gn:feature_code":"PPL",
    "gn:name":"Padrai",
    "gn:population":0,
    "gn:timezone":"Asia/Kolkata",
    "iso:country":"IN",
    "wof:name":"Padrai",
    "wof:placetype":"locality"
},
  "geometry": {"coordinates":[78.99086,24.21707],"type":"Point"}
}