{
  "type": "Feature",
  "properties": {
    "gn:admin1_code":"2",
    "gn:admin2_code":"544.0",
    "gn:asciiname":"Buchchi Rajypeta",
    "gn:country_code":"IN",
    "gn:dem":14,
    "gn:feature_class":"P",
    "gn:feature_code":"PPL",
    "gn:name":"Buchchi R\u0101jypeta",
    "gn:population":0,
    "gn:timezone":"Asia/Kolkata",
    "iso:country":"IN",
    "wof:name":"Buchchi Rajypeta",
    "wof:placetype":"neighbourhood"
},
  "geometry": {"coordinates":[82.71184,17.37079],"type":"Point"}
}