{
  "type": "Feature",
  "properties": {
    "iso:country":"IN",
    "ks:ks_name":"Aslapuram",
    "ks:ks_pop":68,
    "ks:ks_type":"HABITATION",
    "ks:ks_uagg_main":0,
    "name:eng_x_preferred":[
        "Aslapuram"
    ],
    "wof:name":"Aslapuram",
    "wof:placetype":"neighbourhood",
    "wof:population":68
},
  "geometry": {"coordinates":[79.225486,13.293637],"type":"Point"}
}