{
  "type": "Feature",
  "properties": {
    "gn:admin1_code":"40.0",
    "gn:admin2_code":"540",
    "gn:asciiname":"Lingampalli",
    "gn:country_code":"IN",
    "gn:dem":519,
    "gn:feature_class":"P",
    "gn:feature_code":"PPL",
    "gn:name":"Lingampalli",
    "gn:population":0,
    "gn:timezone":"Asia/Kolkata",
    "iso:country":"IN",
    "wof:name":"Lingampalli",
    "wof:placetype":"locality"
},
  "geometry": {"coordinates":[78.92635,17.82777],"type":"Point"}
}