{
  "type": "Feature",
  "properties": {
    "iso:country":"IN",
    "ks:ks_name":"Tinsara",
    "ks:ks_pop":26,
    "ks:ks_type":"HABITATION",
    "name:eng_x_preferred":[
        "Tinsara"
    ],
    "wof:name":"Tinsara",
    "wof:placetype":"locality",
    "wof:population":26
},
  "geometry": {"coordinates":[79.186875,22.910181],"type":"Point"}
}