{
  "type": "Feature",
  "properties": {
    "iso:country":"IN",
    "ks:ks_name":"Kadambodai",
    "ks:ks_pop":971,
    "ks:ks_type":"HABITATION",
    "name:eng_x_preferred":[
        "Kadambodai"
    ],
    "wof:name":"Kadambodai",
    "wof:placetype":"locality",
    "wof:population":971
},
  "geometry": {"coordinates":[78.671155,9.315702],"type":"Point"}
}