{
  "type": "Feature",
  "properties": {
    "gn:admin1_code":"35.0",
    "gn:admin2_code":"442.0",
    "gn:asciiname":"Kachnari",
    "gn:country_code":"IN",
    "gn:dem":395,
    "gn:feature_class":"P",
    "gn:feature_code":"PPL",
    "gn:name":"Kachn\u0101ri",
    "gn:population":0,
    "gn:timezone":"Asia/Kolkata",
    "iso:country":"IN",
    "wof:name":"Kachnari",
    "wof:placetype":"neighbourhood"
},
  "geometry": {"coordinates":[76.34723,24.14638],"type":"Point"}
}