{
  "type": "Feature",
  "properties": {
    "gn:admin1_code":"31.0",
    "gn:admin2_code":"286",
    "gn:asciiname":"Demagiri",
    "gn:country_code":"IN",
    "gn:dem":51,
    "gn:feature_class":"P",
    "gn:feature_code":"PPL",
    "gn:name":"Dem\u0101giri",
    "gn:population":0,
    "gn:timezone":"Asia/Kolkata",
    "iso:country":"IN",
    "wof:name":"Demagiri",
    "wof:placetype":"locality"
},
  "geometry": {"coordinates":[92.46579,22.90742],"type":"Point"}
}