{
  "type": "Feature",
  "properties": {
    "iso:country":"IN",
    "ks:ks_alt_nam":"sakharipada",
    "ks:ks_name":"Sakharipada",
    "ks:ks_pop":528,
    "ks:ks_type":"HABITATION",
    "name:eng_x_preferred":[
        "Sakharipada"
    ],
    "wof:name":"Sakharipada",
    "wof:placetype":"locality",
    "wof:population":528
},
  "geometry": {"coordinates":[73.125209,20.075698],"type":"Point"}
}