{
  "type": "Feature",
  "properties": {
    "iso:country":"IN",
    "ks:ks_name":"Kinnir",
    "ks:ks_pop":55,
    "ks:ks_type":"HABITATION",
    "name:eng_x_preferred":[
        "Kinnir"
    ],
    "wof:name":"Kinnir",
    "wof:placetype":"locality",
    "wof:population":55
},
  "geometry": {"coordinates":[74.472775,14.436342],"type":"Point"}
}