{
  "type": "Feature",
  "properties": {
    "gn:admin1_code":"12",
    "gn:admin2_code":"18.0",
    "gn:asciiname":"Muthil",
    "gn:country_code":"IN",
    "gn:dem":3413,
    "gn:feature_class":"P",
    "gn:feature_code":"PPL",
    "gn:name":"Muthil",
    "gn:population":0,
    "gn:timezone":"Asia/Kolkata",
    "iso:country":"IN",
    "wof:name":"Muthil",
    "wof:placetype":"locality"
},
  "geometry": {"coordinates":[76.07456999999999,33.27506],"type":"Point"}
}