{
  "type": "Feature",
  "properties": {
    "iso:country":"IN",
    "ks:ks_name":"Pirachiwadi",
    "ks:ks_pop":158,
    "ks:ks_type":"HABITATION",
    "name:eng_x_preferred":[
        "Pirachiwadi"
    ],
    "wof:name":"Pirachiwadi",
    "wof:placetype":"locality",
    "wof:population":158
},
  "geometry": {"coordinates":[74.33347999999999,18.56292],"type":"Point"}
}