{
  "type": "Feature",
  "properties": {
    "iso:country":"IN",
    "ks:ks_name":"Dodda Mallaiahnapalya",
    "ks:ks_pop":280,
    "ks:ks_type":"HABITATION",
    "name:eng_x_preferred":[
        "Dodda Mallaiahnapalya"
    ],
    "wof:name":"Dodda Mallaiahnapalya",
    "wof:placetype":"locality",
    "wof:population":280
},
  "geometry": {"coordinates":[77.24443100000001,13.500228],"type":"Point"}
}