{
  "type": "Feature",
  "properties": {
    "iso:country":"IN",
    "ks:ks_name":"Doki",
    "ks:ks_pop":9,
    "ks:ks_type":"VILLAGE",
    "name:eng_x_preferred":[
        "Doki"
    ],
    "wof:name":"Doki",
    "wof:placetype":"locality",
    "wof:population":9
},
  "geometry": {"coordinates":[83.88441400000001,24.045951],"type":"Point"}
}