{
  "type": "Feature",
  "properties": {
    "iso:country":"IN",
    "ks:ks_name":"Kaminaidupeta",
    "ks:ks_pop":578,
    "ks:ks_type":"HABITATION",
    "ks:ks_uagg_main":0,
    "name:eng_x_preferred":[
        "Kaminaidupeta"
    ],
    "wof:name":"Kaminaidupeta",
    "wof:placetype":"neighbourhood",
    "wof:population":578
},
  "geometry": {"coordinates":[83.992428,18.525227],"type":"Point"}
}