{
  "type": "Feature",
  "properties": {
    "gn:admin1_code":"35",
    "gn:admin2_code":"462.0",
    "gn:asciiname":"Harbaro",
    "gn:country_code":"IN",
    "gn:dem":287,
    "gn:feature_class":"P",
    "gn:feature_code":"PPL",
    "gn:name":"Harbaro",
    "gn:population":0,
    "gn:timezone":"Asia/Kolkata",
    "iso:country":"IN",
    "wof:name":"Harbaro",
    "wof:placetype":"neighbourhood"
},
  "geometry": {"coordinates":[81.94126,24.41143],"type":"Point"}
}