{
  "type": "Feature",
  "properties": {
    "gn:admin1_code":"39.0",
    "gn:admin2_code":"65.0",
    "gn:asciiname":"Kachal",
    "gn:country_code":"IN",
    "gn:dem":760,
    "gn:feature_class":"P",
    "gn:feature_code":"PPL",
    "gn:name":"Kach\u0101l",
    "gn:population":0,
    "gn:timezone":"Asia/Kolkata",
    "iso:country":"IN",
    "name:ceb_x_preferred":[
        "Kachal"
    ],
    "name:hin_x_preferred":[
        "\u0915\u091a\u0932"
    ],
    "name:msa_x_preferred":[
        "Kachal"
    ],
    "name:nep_x_preferred":[
        "\u0915\u091a\u0932"
    ],
    "name:new_x_preferred":[
        "\u0915\u091a\u0932"
    ],
    "name:pol_x_preferred":[
        "Kachal"
    ],
    "wof:name":"Kachal",
    "wof:placetype":"locality"
},
  "geometry": {"coordinates":[80.18984,29.16063],"type":"Point"}
}