{
  "type": "Feature",
  "properties": {
    "gn:admin1_code":"16.0",
    "gn:admin2_code":"530",
    "gn:asciiname":"Anaskura",
    "gn:country_code":"IN",
    "gn:dem":584,
    "gn:feature_class":"P",
    "gn:feature_code":"PPL",
    "gn:name":"Anaskura",
    "gn:population":0,
    "gn:timezone":"Asia/Kolkata",
    "iso:country":"IN",
    "wof:name":"Anaskura",
    "wof:placetype":"locality"
},
  "geometry": {"coordinates":[73.81076,16.78197999999999],"type":"Point"}
}