{
  "type": "Feature",
  "properties": {
    "gn:admin1_code":"16.0",
    "gn:admin2_code":"530",
    "gn:asciiname":"Anaskura",
    "gn:country_code":"IN",
    "gn:dem":584,
    "gn:feature_class":"P",
    "gn:feature_code":"PPL",
    "gn:name":"Anaskura",
    "gn:population":0,
    "gn:timezone":"Asia/Kolkata",
    "iso:country":"IN",
    "ks:ks_name":"Anuskura",
    "ks:ks_pop":900,
    "ks:ks_type":"HABITATION",
    "name:eng_x_preferred":[
        "Anuskura"
    ],
    "name:eng_x_variant":[
        "Anaskura"
    ],
    "wof:name":"Anuskura",
    "wof:placetype":"locality",
    "wof:population":900
},
  "geometry": {"coordinates":[73.808785,16.782318],"type":"Point"}
}