{
  "type": "Feature",
  "properties": {
    "iso:country":"IN",
    "ks:ks_name":"Birma",
    "ks:ks_pop":48,
    "ks:ks_type":"VILLAGE",
    "name:eng_x_preferred":[
        "Birma"
    ],
    "wof:name":"Birma",
    "wof:placetype":"locality",
    "wof:population":48
},
  "geometry": {"coordinates":[69.788968,26.961818],"type":"Point"}
}