{
  "type": "Feature",
  "properties": {
    "iso:country":"IN",
    "ks:ks_name":"Ayyankadu",
    "ks:ks_pop":450,
    "ks:ks_type":"HABITATION",
    "name:eng_x_preferred":[
        "Ayyankadu"
    ],
    "wof:name":"Ayyankadu",
    "wof:placetype":"locality",
    "wof:population":450
},
  "geometry": {"coordinates":[78.99414,10.433078],"type":"Point"}
}