{
  "type": "Feature",
  "properties": {
    "iso:country":"IN",
    "ks:ks_name":"Pragnapur",
    "ks:ks_pop":5446,
    "ks:ks_type":"VILLAGE",
    "ks:ks_uagg_main":0,
    "name:eng_x_preferred":[
        "Pragnapur"
    ],
    "wof:name":"Pragnapur",
    "wof:placetype":"neighbourhood",
    "wof:population":5446
},
  "geometry": {"coordinates":[78.696213,17.836992],"type":"Point"}
}