{
  "type": "Feature",
  "properties": {
    "gn:admin1_code":"39.0",
    "gn:admin2_code":"64.0",
    "gn:asciiname":"Khatiari",
    "gn:country_code":"IN",
    "gn:dem":1333,
    "gn:feature_class":"P",
    "gn:feature_code":"PPL",
    "gn:name":"Khati\u0101ri",
    "gn:population":0,
    "gn:timezone":"Asia/Kolkata",
    "iso:country":"IN",
    "ks:ks_alt_nam":"Khati\u0101ri",
    "ks:ks_name":"Khatiari",
    "ks:ks_type":"VILLAGE",
    "name:eng_x_preferred":[
        "Khatiari"
    ],
    "name:eng_x_variant":[
        "Khati\u0101ri"
    ],
    "wof:name":"Khatiari",
    "wof:placetype":"locality"
},
  "geometry": {"coordinates":[79.29951800000001,29.888403],"type":"Point"}
}