{
  "type": "Feature",
  "properties": {
    "iso:country":"IN",
    "ks:ks_name":"Chak Gopal",
    "ks:ks_pop":1138,
    "ks:ks_type":"VILLAGE",
    "ks:ks_uagg_main":0,
    "name:eng_x_preferred":[
        "Chak Gopal"
    ],
    "wof:name":"Chak Gopal",
    "wof:placetype":"neighbourhood",
    "wof:population":1138
},
  "geometry": {"coordinates":[87.718829,22.487957],"type":"Point"}
}