{
  "type": "Feature",
  "properties": {
    "iso:country":"IN",
    "ks:ks_name":"Gadagewadi",
    "ks:ks_pop":110,
    "ks:ks_type":"HABITATION",
    "name:eng_x_preferred":[
        "Gadagewadi"
    ],
    "wof:name":"Gadagewadi",
    "wof:placetype":"locality",
    "wof:population":110
},
  "geometry": {"coordinates":[73.518889,17.219167],"type":"Point"}
}