{
  "type": "Feature",
  "properties": {
    "iso:country":"IN",
    "ks:ks_alt_nam":"G jagannadhapuram",
    "ks:ks_name":"G Jagannadhapuram",
    "ks:ks_pop":66,
    "ks:ks_type":"HABITATION",
    "name:eng_x_preferred":[
        "G Jagannadhapuram"
    ],
    "wof:name":"G Jagannadhapuram",
    "wof:placetype":"locality",
    "wof:population":66
},
  "geometry": {"coordinates":[84.221389,18.683499],"type":"Point"}
}