{
  "type": "Feature",
  "properties": {
    "iso:country":"IN",
    "ks:ks_name":"Karaiyatanr",
    "ks:ks_pop":91,
    "ks:ks_type":"VILLAGE",
    "ks:ks_uagg_main":0,
    "name:eng_x_preferred":[
        "Karaiyatanr"
    ],
    "wof:name":"Karaiyatanr",
    "wof:placetype":"neighbourhood",
    "wof:population":91
},
  "geometry": {"coordinates":[86.719399,24.24321],"type":"Point"}
}