{
  "type": "Feature",
  "properties": {
    "iso:country":"IN",
    "ks:ks_name":"Waderayanahalli",
    "ks:ks_pop":497,
    "ks:ks_type":"VILLAGE",
    "ks:ks_uagg_main":0,
    "name:eng_x_preferred":[
        "Waderayanahalli"
    ],
    "wof:name":"Waderayanahalli",
    "wof:placetype":"neighbourhood",
    "wof:population":497
},
  "geometry": {"coordinates":[75.76667399999999,14.548586],"type":"Point"}
}