{
  "type": "Feature",
  "properties": {
    "iso:country":"IN",
    "ks:ks_name":"Kolinda Talla",
    "ks:ks_pop":181,
    "ks:ks_type":"VILLAGE",
    "name:eng_x_preferred":[
        "Kolinda Talla"
    ],
    "wof:name":"Kolinda Talla",
    "wof:placetype":"locality",
    "wof:population":181
},
  "geometry": {"coordinates":[79.031147,29.968224],"type":"Point"}
}