{
  "type": "Feature",
  "properties": {
    "gn:admin1_code":"19.0",
    "gn:admin2_code":"568.0",
    "gn:asciiname":"Nedaravalli",
    "gn:country_code":"IN",
    "gn:dem":641,
    "gn:feature_class":"P",
    "gn:feature_code":"PPL",
    "gn:name":"Ned\u0101ravalli",
    "gn:population":0,
    "gn:timezone":"Asia/Kolkata",
    "iso:country":"IN",
    "wof:name":"Nedaravalli",
    "wof:placetype":"locality"
},
  "geometry": {"coordinates":[75.14086999999998,14.12405],"type":"Point"}
}