{
  "type": "Feature",
  "properties": {
    "gn:admin1_code":"19.0",
    "gn:admin2_code":"568.0",
    "gn:asciiname":"Nedaravalli",
    "gn:country_code":"IN",
    "gn:dem":641,
    "gn:feature_class":"P",
    "gn:feature_code":"PPL",
    "gn:name":"Ned\u0101ravalli",
    "gn:population":0,
    "gn:timezone":"Asia/Kolkata",
    "iso:country":"IN",
    "ks:ks_alt_nam":"Ned\u0101ravalli",
    "ks:ks_name":"Nedaravalli",
    "ks:ks_pop":319,
    "ks:ks_type":"VILLAGE",
    "name:eng_x_preferred":[
        "Nedaravalli"
    ],
    "name:eng_x_variant":[
        "Ned\u0101ravalli"
    ],
    "wof:name":"Nedaravalli",
    "wof:placetype":"locality",
    "wof:population":319
},
  "geometry": {"coordinates":[75.140867,14.124047],"type":"Point"}
}