{
  "type": "Feature",
  "properties": {
    "iso:country":"IN",
    "ks:ks_name":"Bokanoi",
    "ks:ks_pop":380,
    "ks:ks_type":"VILLAGE",
    "name:eng_x_preferred":[
        "Bokanoi"
    ],
    "wof:name":"Bokanoi",
    "wof:placetype":"locality",
    "wof:population":380
},
  "geometry": {"coordinates":[93.967984,27.145356],"type":"Point"}
}