{
  "type": "Feature",
  "properties": {
    "gn:admin1_code":"2",
    "gn:admin2_code":"544.0",
    "gn:asciiname":"Rasipanuku",
    "gn:country_code":"IN",
    "gn:dem":787,
    "gn:feature_class":"P",
    "gn:feature_code":"PPL",
    "gn:name":"R\u0101sipanuku",
    "gn:population":0,
    "gn:timezone":"Asia/Kolkata",
    "iso:country":"IN",
    "ks:ks_alt_nam":"R\u0101sipanuku",
    "ks:ks_name":"Rasipanuku",
    "ks:ks_type":"VILLAGE",
    "name:eng_x_preferred":[
        "Rasipanuku"
    ],
    "name:eng_x_variant":[
        "R\u0101sipanuku"
    ],
    "wof:name":"Rasipanuku",
    "wof:placetype":"locality"
},
  "geometry": {"coordinates":[82.507649,17.84942],"type":"Point"}
}