{
  "type": "Feature",
  "properties": {
    "iso:country":"IN",
    "ks:ks_name":"Sankodige",
    "ks:ks_pop":37,
    "ks:ks_type":"HABITATION",
    "name:eng_x_preferred":[
        "Sankodige"
    ],
    "wof:name":"Sankodige",
    "wof:placetype":"locality",
    "wof:population":37
},
  "geometry": {"coordinates":[75.195898,13.421059],"type":"Point"}
}