{
  "type": "Feature",
  "properties": {
    "gn:admin1_code":"39.0",
    "gn:admin2_code":"64.0",
    "gn:asciiname":"Basela",
    "gn:country_code":"IN",
    "gn:dem":662,
    "gn:feature_class":"P",
    "gn:feature_code":"PPL",
    "gn:name":"Basela",
    "gn:population":0,
    "gn:timezone":"Asia/Kolkata",
    "iso:country":"IN",
    "wof:name":"Basela",
    "wof:placetype":"locality"
},
  "geometry": {"coordinates":[79.22320000000001,29.52411],"type":"Point"}
}