{
  "type": "Feature",
  "properties": {
    "iso:country":"IN",
    "ks:ks_alt_nam":"Sasthiri nagar",
    "ks:ks_name":"Sasthiri Nagar",
    "ks:ks_pop":89,
    "ks:ks_type":"HABITATION",
    "ks:ks_uagg_main":0,
    "name:eng_x_preferred":[
        "Sasthiri Nagar"
    ],
    "wof:name":"Sasthiri Nagar",
    "wof:placetype":"neighbourhood",
    "wof:population":89
},
  "geometry": {"coordinates":[77.53775,9.47144],"type":"Point"}
}