{
  "type": "Feature",
  "properties": {
    "iso:country":"IN",
    "ks:ks_name":"Raynarayanchak",
    "ks:ks_pop":1032,
    "ks:ks_type":"HABITATION",
    "name:eng_x_preferred":[
        "Raynarayanchak"
    ],
    "wof:name":"Raynarayanchak",
    "wof:placetype":"locality",
    "wof:population":1032
},
  "geometry": {"coordinates":[87.780041,22.302217],"type":"Point"}
}