{
  "type": "Feature",
  "properties": {
    "gn:admin1_code":"36",
    "gn:admin2_code":"172.0",
    "gn:asciiname":"Kaunrerwa",
    "gn:country_code":"IN",
    "gn:dem":118,
    "gn:feature_class":"P",
    "gn:feature_code":"PPL",
    "gn:name":"Kaunrerw\u0101",
    "gn:population":0,
    "gn:timezone":"Asia/Kolkata",
    "iso:country":"IN",
    "wof:name":"Kaunrerwa",
    "wof:placetype":"locality"
},
  "geometry": {"coordinates":[80.84784000000001,25.96608],"type":"Point"}
}