{
  "type": "Feature",
  "properties": {
    "iso:country":"IN",
    "ks:ks_alt_nam":"Hor\u016br",
    "ks:ks_name":"Horur",
    "ks:ks_pop":1455,
    "ks:ks_type":"VILLAGE",
    "name:eng_x_preferred":[
        "Horur"
    ],
    "name:eng_x_variant":[
        "Hor\u016br"
    ],
    "wof:name":"Horur",
    "wof:placetype":"locality",
    "wof:population":1455
},
  "geometry": {"coordinates":[75.81495,12.419332],"type":"Point"}
}