{
  "type": "Feature",
  "properties": {
    "iso:country":"IN",
    "ks:ks_name":"Dingdinga",
    "ks:ks_pop":4000,
    "ks:ks_type":"VILLAGE",
    "name:eng_x_preferred":[
        "Dingdinga"
    ],
    "wof:name":"Dingdinga",
    "wof:placetype":"locality",
    "wof:population":4000
},
  "geometry": {"coordinates":[90.16612000000001,26.004513],"type":"Point"}
}