{
  "type": "Feature",
  "properties": {
    "iso:country":"IN",
    "ks:ks_name":"Pudukuppam",
    "ks:ks_pop":1177,
    "ks:ks_type":"HABITATION",
    "name:eng_x_preferred":[
        "Pudukuppam"
    ],
    "wof:name":"Pudukuppam",
    "wof:placetype":"locality",
    "wof:population":1177
},
  "geometry": {"coordinates":[79.647167,11.985046],"type":"Point"}
}