{
  "type": "Feature",
  "properties": {
    "iso:country":"IN",
    "ks:ks_name":"Kullegoundanur",
    "ks:ks_pop":160,
    "ks:ks_type":"HABITATION",
    "name:eng_x_preferred":[
        "Kullegoundanur"
    ],
    "wof:name":"Kullegoundanur",
    "wof:placetype":"locality",
    "wof:population":160
},
  "geometry": {"coordinates":[77.19833800000001,11.416712],"type":"Point"}
}