{
  "type": "Feature",
  "properties": {
    "gn:admin1_code":"19",
    "gn:admin2_code":"557.0",
    "gn:asciiname":"Yarnal",
    "gn:country_code":"IN",
    "gn:dem":530,
    "gn:feature_class":"P",
    "gn:feature_code":"PPL",
    "gn:name":"Yarn\u0101l",
    "gn:population":0,
    "gn:timezone":"Asia/Kolkata",
    "iso:country":"IN",
    "name:urd_x_preferred":[
        "\u06cc\u0627\u0631\u0646\u0644"
    ],
    "wof:name":"Yarnal",
    "wof:placetype":"locality"
},
  "geometry": {"coordinates":[76.09243000000002,16.80932],"type":"Point"}
}