{
  "type": "Feature",
  "properties": {
    "iso:country":"IN",
    "ks:ks_name":"Jalalpur Talluque Badshshnager",
    "ks:ks_pop":661,
    "ks:ks_type":"VILLAGE",
    "ks:ks_uagg_main":0,
    "name:eng_x_preferred":[
        "Jalalpur Talluque Badshshnager"
    ],
    "wof:name":"Jalalpur Talluque Badshshnager",
    "wof:placetype":"neighbourhood",
    "wof:population":661
},
  "geometry": {"coordinates":[79.934335,27.796548],"type":"Point"}
}