{
  "type": "Feature",
  "properties": {
    "iso:country":"IN",
    "ks:ks_name":"Mannor",
    "ks:ks_pop":643,
    "ks:ks_type":"HABITATION",
    "name:eng_x_preferred":[
        "Mannor"
    ],
    "wof:name":"Mannor",
    "wof:placetype":"locality",
    "wof:population":643
},
  "geometry": {"coordinates":[81.641181,23.589663],"type":"Point"}
}