{
  "type": "Feature",
  "properties": {
    "iso:country":"IN",
    "ks:ks_name":"Babupur",
    "ks:ks_pop":175,
    "ks:ks_type":"HABITATION",
    "name:eng_x_preferred":[
        "Babupur"
    ],
    "wof:name":"Babupur",
    "wof:placetype":"locality",
    "wof:population":175
},
  "geometry": {"coordinates":[81.87090499999999,27.225955],"type":"Point"}
}