{
  "type": "Feature",
  "properties": {
    "gn:admin1_code":"24.0",
    "gn:admin2_code":"115",
    "gn:asciiname":"Chaitrori",
    "gn:country_code":"IN",
    "gn:dem":143,
    "gn:feature_class":"P",
    "gn:feature_code":"PPL",
    "gn:name":"Chaitrori",
    "gn:population":0,
    "gn:timezone":"Asia/Kolkata",
    "iso:country":"IN",
    "wof:name":"Chaitrori",
    "wof:placetype":"locality"
},
  "geometry": {"coordinates":[70.5934,25.96129],"type":"Point"}
}