{
  "type": "Feature",
  "properties": {
    "gn:admin1_code":"37",
    "gn:admin2_code":"409.0",
    "gn:asciiname":"Dangania",
    "gn:country_code":"IN",
    "gn:dem":304,
    "gn:feature_class":"P",
    "gn:feature_code":"PPL",
    "gn:name":"Dangania",
    "gn:population":0,
    "gn:timezone":"Asia/Kolkata",
    "iso:country":"IN",
    "wof:name":"Dangania",
    "wof:placetype":"locality"
},
  "geometry": {"coordinates":[81.28617,21.01292],"type":"Point"}
}