{
  "type": "Feature",
  "properties": {
    "gn:admin1_code":"19.0",
    "gn:admin2_code":"574.0",
    "gn:asciiname":"Hirihalli",
    "gn:country_code":"IN",
    "gn:dem":914,
    "gn:feature_class":"P",
    "gn:feature_code":"PPL",
    "gn:name":"H\u012brihalli",
    "gn:population":0,
    "gn:timezone":"Asia/Kolkata",
    "iso:country":"IN",
    "wof:name":"Hirihalli",
    "wof:placetype":"locality"
},
  "geometry": {"coordinates":[76.15849,12.94316],"type":"Point"}
}