{
  "type": "Feature",
  "properties": {
    "iso:country":"IN",
    "ks:ks_name":"Tuburuda",
    "ks:ks_pop":95,
    "ks:ks_type":"VILLAGE",
    "name:eng_x_preferred":[
        "Tuburuda"
    ],
    "wof:name":"Tuburuda",
    "wof:placetype":"locality",
    "wof:population":95
},
  "geometry": {"coordinates":[84.254147,18.947965],"type":"Point"}
}