{
  "type": "Feature",
  "properties": {
    "gn:admin1_code":"39.0",
    "gn:admin2_code":"61.0",
    "gn:asciiname":"Palasi",
    "gn:country_code":"IN",
    "gn:dem":1153,
    "gn:feature_class":"P",
    "gn:feature_code":"PPL",
    "gn:name":"Pal\u0101si",
    "gn:population":0,
    "gn:timezone":"Asia/Kolkata",
    "iso:country":"IN",
    "ks:ks_alt_nam":"Pal\u0101si",
    "ks:ks_name":"Palasi",
    "ks:ks_pop":336,
    "ks:ks_type":"VILLAGE",
    "name:eng_x_preferred":[
        "Palasi"
    ],
    "name:eng_x_variant":[
        "Pal\u0101si"
    ],
    "name:hif_x_preferred":[
        "Palasi"
    ],
    "wof:name":"Palasi",
    "wof:placetype":"locality",
    "wof:population":336
},
  "geometry": {"coordinates":[79.076718,29.708194],"type":"Point"}
}