{
  "type": "Feature",
  "properties": {
    "iso:country":"IN",
    "ks:ks_name":"Sivnikhurd",
    "ks:ks_pop":540,
    "ks:ks_type":"VILLAGE",
    "ks:ks_uagg_main":0,
    "name:eng_x_preferred":[
        "Sivnikhurd"
    ],
    "wof:name":"Sivnikhurd",
    "wof:placetype":"neighbourhood",
    "wof:population":540
},
  "geometry": {"coordinates":[80.878192,21.10822],"type":"Point"}
}