{
  "type": "Feature",
  "properties": {
    "iso:country":"IN",
    "ks:ks_name":"Borramamidi",
    "ks:ks_pop":112,
    "ks:ks_type":"HABITATION",
    "name:eng_x_preferred":[
        "Borramamidi"
    ],
    "wof:name":"Borramamidi",
    "wof:placetype":"locality",
    "wof:population":112
},
  "geometry": {"coordinates":[82.494316,17.777162],"type":"Point"}
}