{
  "type": "Feature",
  "properties": {
    "gn:admin1_code":"11.0",
    "gn:admin2_code":"32.0",
    "gn:asciiname":"Bara Chhatar",
    "gn:country_code":"IN",
    "gn:dem":1391,
    "gn:feature_class":"P",
    "gn:feature_code":"PPL",
    "gn:name":"B\u0101ra Chhatar",
    "gn:population":0,
    "gn:timezone":"Asia/Kolkata",
    "iso:country":"IN",
    "wof:name":"Bara Chhatar",
    "wof:placetype":"locality"
},
  "geometry": {"coordinates":[77.67853000000002,30.55298],"type":"Point"}
}