{
  "type": "Feature",
  "properties": {
    "iso:country":"IN",
    "qs:name":"Haldwani (Kathgodam)",
    "qs:name_adm0":"India",
    "qs:name_adm1":"Uttarakhand",
    "qs:photos":69,
    "qs:photos_1k":14,
    "qs:photos_9k":1,
    "qs:photos_9r":2,
    "qs:photos_all":69,
    "qs:photos_sr":2,
    "qs:placetype":"Town",
    "qs:pop_sr":"0",
    "wof:name":"Haldwani (Kathgodam)",
    "wof:placetype":"neighbourhood"
},
  "geometry": {"coordinates":[79.532432,29.23623],"type":"Point"}
}