{
  "type": "Feature",
  "properties": {
    "iso:country":"IN",
    "ks:ks_name":"Nayanamarni",
    "ks:ks_pop":73,
    "ks:ks_type":"VILLAGE",
    "name:eng_x_preferred":[
        "Nayanamarni"
    ],
    "wof:name":"Nayanamarni",
    "wof:placetype":"locality",
    "wof:population":73
},
  "geometry": {"coordinates":[86.608125,24.102764],"type":"Point"}
}