{
  "type": "Feature",
  "properties": {
    "gn:admin1_code":"12",
    "gn:admin2_code":"20.0",
    "gn:asciiname":"Serni",
    "gn:country_code":"IN",
    "gn:dem":1967,
    "gn:feature_class":"P",
    "gn:feature_code":"PPL",
    "gn:name":"Sern\u012b",
    "gn:population":0,
    "gn:timezone":"Asia/Kolkata",
    "iso:country":"IN",
    "name:fra_x_preferred":[
        "Serni"
    ],
    "wof:name":"Serni",
    "wof:placetype":"locality"
},
  "geometry": {"coordinates":[74.92196,33.31929],"type":"Point"}
}