{
  "type": "Feature",
  "properties": {
    "iso:country":"IN",
    "ks:ks_name":"Phogera",
    "ks:ks_pop":1996,
    "ks:ks_type":"VILLAGE",
    "name:eng_x_preferred":[
        "Phogera"
    ],
    "wof:name":"Phogera",
    "wof:placetype":"locality",
    "wof:population":1996
},
  "geometry": {"coordinates":[70.957652,25.967637],"type":"Point"}
}