{
  "type": "Feature",
  "properties": {
    "iso:country":"IN",
    "ks:ks_name":"Charahat Kalan",
    "ks:ks_pop":715,
    "ks:ks_type":"VILLAGE",
    "name:eng_x_preferred":[
        "Charahat Kalan"
    ],
    "wof:name":"Charahat Kalan",
    "wof:placetype":"locality",
    "wof:population":715
},
  "geometry": {"coordinates":[83.90230200000001,23.422465],"type":"Point"}
}