{
  "type": "Feature",
  "properties": {
    "iso:country":"IN",
    "ks:ks_name":"Dungari Falia",
    "ks:ks_pop":284,
    "ks:ks_type":"HABITATION",
    "name:eng_x_preferred":[
        "Dungari Falia"
    ],
    "wof:name":"Dungari Falia",
    "wof:placetype":"locality",
    "wof:population":284
},
  "geometry": {"coordinates":[73.229167,20.608389],"type":"Point"}
}