{
  "type": "Feature",
  "properties": {
    "gn:admin1_code":"16.0",
    "gn:admin2_code":"514.0",
    "gn:asciiname":"Sindiwadgaon",
    "gn:country_code":"IN",
    "gn:dem":472,
    "gn:feature_class":"P",
    "gn:feature_code":"PPL",
    "gn:name":"Sind\u012bwadgaon",
    "gn:population":0,
    "gn:timezone":"Asia/Kolkata",
    "iso:country":"IN",
    "name:eng_x_preferred":[
        "Sind\u012bwadgaon"
    ],
    "wof:name":"Sindiwadgaon",
    "wof:placetype":"locality"
},
  "geometry": {"coordinates":[75.99996,19.60973],"type":"Point"}
}