{
  "type": "Feature",
  "properties": {
    "iso:country":"IN",
    "ks:ks_name":"Kapsi",
    "ks:ks_pop":385,
    "ks:ks_type":"VILLAGE",
    "name:eng_x_preferred":[
        "Kapsi"
    ],
    "wof:name":"Kapsi",
    "wof:placetype":"locality",
    "wof:population":385
},
  "geometry": {"coordinates":[81.324168,19.640517],"type":"Point"}
}