{
  "type": "Feature",
  "properties": {
    "iso:country":"IN",
    "ks:ks_alt_nam":"Lataul\u012b",
    "ks:ks_name":"Latauli",
    "ks:ks_pop":632,
    "ks:ks_type":"VILLAGE",
    "name:eng_x_preferred":[
        "Latauli"
    ],
    "name:eng_x_variant":[
        "Lataul\u012b"
    ],
    "wof:name":"Latauli",
    "wof:placetype":"locality",
    "wof:population":632
},
  "geometry": {"coordinates":[85.17377,22.887364],"type":"Point"}
}