{
  "type": "Feature",
  "properties": {
    "iso:country":"IN",
    "ks:ks_name":"Vadakku Veepilankulam",
    "ks:ks_pop":380,
    "ks:ks_type":"HABITATION",
    "ks:ks_uagg_main":0,
    "name:eng_x_preferred":[
        "Vadakku Veepilankulam"
    ],
    "wof:name":"Vadakku Veepilankulam",
    "wof:placetype":"neighbourhood",
    "wof:population":380
},
  "geometry": {"coordinates":[77.61896900000001,8.305426],"type":"Point"}
}