{
  "type": "Feature",
  "properties": {
    "iso:country":"IN",
    "ks:ks_alt_nam":"PATIL VASTI",
    "ks:ks_name":"Patil Vasti",
    "ks:ks_pop":176,
    "ks:ks_type":"HABITATION",
    "name:eng_x_preferred":[
        "Patil Vasti"
    ],
    "wof:name":"Patil Vasti",
    "wof:placetype":"locality",
    "wof:population":176
},
  "geometry": {"coordinates":[75.133419,16.901129],"type":"Point"}
}