{
  "type": "Feature",
  "properties": {
    "iso:country":"IN",
    "ks:ks_name":"Tirasi Tola",
    "ks:ks_pop":518,
    "ks:ks_type":"HABITATION",
    "ks:ks_uagg_main":0,
    "name:eng_x_preferred":[
        "Tirasi Tola"
    ],
    "wof:name":"Tirasi Tola",
    "wof:placetype":"neighbourhood",
    "wof:population":518
},
  "geometry": {"coordinates":[86.448965,25.729557],"type":"Point"}
}