{
  "type": "Feature",
  "properties": {
    "gn:admin1_code":"36.0",
    "gn:admin2_code":"175.0",
    "gn:asciiname":"Kamaldipur",
    "gn:country_code":"IN",
    "gn:dem":99,
    "gn:feature_class":"P",
    "gn:feature_code":"PPL",
    "gn:name":"Kam\u0101ld\u012bpur",
    "gn:population":0,
    "gn:timezone":"Asia/Kolkata",
    "iso:country":"IN",
    "name:und_x_variant":[
        "Kam\u0101ld\u012bpur",
        "Chak Chur\u0101man"
    ],
    "wof:name":"Kamaldipur",
    "wof:placetype":"locality"
},
  "geometry": {"coordinates":[81.94798,25.3971],"type":"Point"}
}