{
  "type": "Feature",
  "properties": {
    "gn:admin1_code":"36.0",
    "gn:admin2_code":"175.0",
    "gn:asciiname":"Kamaldipur",
    "gn:country_code":"IN",
    "gn:dem":99,
    "gn:feature_class":"P",
    "gn:feature_code":"PPL",
    "gn:name":"Kam\u0101ld\u012bpur",
    "gn:population":0,
    "gn:timezone":"Asia/Kolkata",
    "iso:country":"IN",
    "ks:ks_name":"Kamaldi Pur",
    "ks:ks_pop":167,
    "ks:ks_type":"HABITATION",
    "name:eng_x_preferred":[
        "Kamaldi Pur"
    ],
    "name:eng_x_variant":[
        "Kamaldipur"
    ],
    "name:und_x_variant":[
        "Kam\u0101ld\u012bpur",
        "Chak Chur\u0101man"
    ],
    "wof:name":"Kamaldi Pur",
    "wof:placetype":"locality",
    "wof:population":167
},
  "geometry": {"coordinates":[81.948634,25.398776],"type":"Point"}
}