{
  "type": "Feature",
  "properties": {
    "iso:country":"IN",
    "ks:ks_name":"Pub Khagrabari",
    "ks:ks_pop":1098,
    "ks:ks_type":"VILLAGE",
    "ks:ks_uagg_main":0,
    "name:eng_x_preferred":[
        "Pub Khagrabari"
    ],
    "wof:name":"Pub Khagrabari",
    "wof:placetype":"neighbourhood",
    "wof:population":1098
},
  "geometry": {"coordinates":[91.22886099999999,26.630073],"type":"Point"}
}