{
  "type": "Feature",
  "properties": {
    "iso:country":"IN",
    "ks:ks_name":"Mundageri",
    "ks:ks_pop":80,
    "ks:ks_type":"HABITATION",
    "name:eng_x_preferred":[
        "Mundageri"
    ],
    "wof:name":"Mundageri",
    "wof:placetype":"locality",
    "wof:population":80
},
  "geometry": {"coordinates":[74.596987,14.566742],"type":"Point"}
}