{
  "type": "Feature",
  "properties": {
    "gn:admin1_code":"36.0",
    "gn:admin2_code":"161",
    "gn:asciiname":"Tulshipur",
    "gn:country_code":"IN",
    "gn:dem":152,
    "gn:feature_class":"P",
    "gn:feature_code":"PPL",
    "gn:name":"Tulshipur",
    "gn:population":0,
    "gn:timezone":"Asia/Kolkata",
    "iso:country":"IN",
    "name:und_x_variant":[
        "Tuls\u012bpur"
    ],
    "wof:name":"Tulshipur",
    "wof:placetype":"locality"
},
  "geometry": {"coordinates":[79.05518000000002,26.90106],"type":"Point"}
}