{
  "type": "Feature",
  "properties": {
    "iso:country":"IN",
    "ks:ks_alt_nam":"LOWER BISODAH",
    "ks:ks_name":"Lower Bisodah",
    "ks:ks_pop":230,
    "ks:ks_type":"HABITATION",
    "name:eng_x_preferred":[
        "Lower Bisodah"
    ],
    "wof:name":"Lower Bisodah",
    "wof:placetype":"locality",
    "wof:population":230
},
  "geometry": {"coordinates":[86.457223,24.634567],"type":"Point"}
}