{
  "type": "Feature",
  "properties": {
    "gn:admin1_code":"19.0",
    "gn:admin2_code":"573.0",
    "gn:asciiname":"Hammadihalli",
    "gn:country_code":"IN",
    "gn:dem":880,
    "gn:feature_class":"P",
    "gn:feature_code":"PPL",
    "gn:name":"Hammadihalli",
    "gn:population":0,
    "gn:timezone":"Asia/Kolkata",
    "iso:country":"IN",
    "ks:ks_name":"Hemmadahalli",
    "ks:ks_pop":158,
    "ks:ks_type":"VILLAGE",
    "name:eng_x_preferred":[
        "Hemmadahalli"
    ],
    "name:eng_x_variant":[
        "Hammadihalli"
    ],
    "wof:name":"Hemmadahalli",
    "wof:placetype":"locality",
    "wof:population":158
},
  "geometry": {"coordinates":[76.588967,12.660455],"type":"Point"}
}