{
  "type": "Feature",
  "properties": {
    "gn:admin1_code":"12.0",
    "gn:admin2_code":"006",
    "gn:asciiname":"Chamba",
    "gn:country_code":"IN",
    "gn:dem":1182,
    "gn:feature_class":"P",
    "gn:feature_code":"PPL",
    "gn:name":"Chamba",
    "gn:population":0,
    "gn:timezone":"Asia/Kolkata",
    "iso:country":"IN",
    "name:ara_x_preferred":[
        "\u062a\u0634\u0627\u0645\u0628\u0627"
    ],
    "name:ara_x_variant":[
        "\u0634\u0627\u0645\u0628\u0627"
    ],
    "name:ben_bn_x_preferred":[
        "\u099a\u09be\u09ae\u09cd\u09ac\u09be"
    ],
    "name:ben_in_x_preferred":[
        "\u099a\u09be\u09ae\u09cd\u09ac\u09be"
    ],
    "name:ben_x_preferred":[
        "\u099a\u09be\u09ae\u09cd\u09ac\u09be"
    ],
    "name:ceb_x_preferred":[
        "Chamba"
    ],
    "name:deu_x_preferred":[
        "Chamba"
    ],
    "name:fra_x_preferred":[
        "Chamba"
    ],
    "name:guj_x_preferred":[
        "\u0a9a\u0a82\u0aac\u0abe"
    ],
    "name:hin_x_preferred":[
        "\u091a\u0902\u092c\u093e"
    ],
    "name:ita_x_preferred":[
        "Chamba"
    ],
    "name:kan_x_preferred":[
        "\u0c9a\u0c82\u0cac\u0cbe"
    ],
    "name:mal_x_preferred":[
        "\u0d1a\u0d2e\u0d4d\u0d2a"
    ],
    "name:mar_x_preferred":[
        "\u091a\u0902\u092c\u093e"
    ],
    "name:nld_x_preferred":[
        "Chamba"
    ],
    "name:pan_x_preferred":[
        "\u0a1a\u0a70\u0a2c\u0a3e"
    ],
    "name:pol_x_preferred":[
        "Chamba"
    ],
    "name:spa_x_preferred":[
        "Chamba"
    ],
    "name:swe_x_preferred":[
        "Chamba"
    ],
    "name:tam_x_preferred":[
        "\u0b9a\u0bae\u0bcd\u0baa\u0bbe"
    ],
    "name:tel_x_preferred":[
        "\u0c1a\u0c02\u0c2c\u0c3e"
    ],
    "name:urd_x_preferred":[
        "\u0686\u0645\u0628\u0627"
    ],
    "wof:name":"Chamba",
    "wof:placetype":"locality"
},
  "geometry": {"coordinates":[74.22119000000001,33.42229],"type":"Point"}
}