{
  "type": "Feature",
  "properties": {
    "gn:admin1_code":"12.0",
    "gn:admin2_code":"006",
    "gn:asciiname":"Chamba",
    "gn:country_code":"IN",
    "gn:dem":1182,
    "gn:feature_class":"P",
    "gn:feature_code":"PPL",
    "gn:name":"Chamba",
    "gn:population":0,
    "gn:timezone":"Asia/Kolkata",
    "iso:country":"IN",
    "wof:name":"Chamba",
    "wof:placetype":"locality"
},
  "geometry": {"coordinates":[74.22119000000001,33.42229],"type":"Point"}
}