{
  "type": "Feature",
  "properties": {
    "gn:admin1_code":"34.0",
    "gn:admin2_code":"212.0",
    "gn:asciiname":"Janamghuti",
    "gn:country_code":"IN",
    "gn:dem":34,
    "gn:feature_class":"P",
    "gn:feature_code":"PPL",
    "gn:name":"Janamghuti",
    "gn:population":0,
    "gn:timezone":"Asia/Kolkata",
    "iso:country":"IN",
    "ks:ks_alt_nam":"JANAM GHUTTI",
    "ks:ks_name":"Janam Ghutti",
    "ks:ks_pop":1584,
    "ks:ks_type":"HABITATION",
    "name:eng_x_preferred":[
        "Janam Ghutti"
    ],
    "name:eng_x_variant":[
        "Janamghuti"
    ],
    "wof:name":"Janam Ghutti",
    "wof:placetype":"locality",
    "wof:population":1584
},
  "geometry": {"coordinates":[87.462226,25.502624],"type":"Point"}
}