{
  "type": "Feature",
  "properties": {
    "iso:country":"IN",
    "name:eng_x_preferred":[
        "Nishat Bagh"
    ],
    "name:fra_x_preferred":[
        "Nishat Bagh"
    ],
    "name:hin_x_preferred":[
        "\u0928\u093f\u0936\u093e\u0924"
    ],
    "name:ita_x_preferred":[
        "Nishat Bagh"
    ],
    "name:msa_x_preferred":[
        "Nishat Bagh"
    ],
    "name:nld_x_preferred":[
        "Nishat Bagh"
    ],
    "name:san_x_preferred":[
        "nishat"
    ],
    "name:unk_x_variant":[
        "Nishat Bagh"
    ],
    "qs:gn_adm0_cc":"IN",
    "qs:gn_local":1255634,
    "qs:gn_nam_loc":"Srinagar, Srinagar, Jammu and Kashmir, IN",
    "qs:gn_namadm1":"12",
    "qs:local_max":800,
    "qs:local_sum":2636,
    "qs:localhoods":18,
    "qs:name":"Nishat Bagh",
    "qs:name_adm0":"India",
    "qs:name_adm1":"Jammu and Kashmir",
    "qs:name_adm2":"Srinagar",
    "qs:name_local":"Srinagar",
    "qs:photo_max":64,
    "qs:photo_sum":115,
    "qs:placetype":"Suburb",
    "qs:quad_count":9,
    "qs:woe_adm0":23424848,
    "qs:woe_adm1":2345746,
    "qs:woe_adm2":12586462,
    "qs:woe_lau":0,
    "qs:woe_local":2295387,
    "qs:woe_ver":"7.10.0",
    "wd:wordcount":1518,
    "wof:lang":[
        "eng"
    ],
    "wof:name":"Nishat Bagh",
    "wof:placetype":"neighbourhood"
},
  "geometry": {"coordinates":[74.879098,34.128916],"type":"Point"}
}