{
  "type": "Feature",
  "properties": {
    "iso:country":"IN",
    "name:ara_x_preferred":[
        "\u0646\u064a\u0634\u0627\u062a \u0628\u0627\u063a"
    ],
    "name:ben_bn_x_preferred":[
        "\u09a8\u09bf\u09b6\u09be\u09a4 \u09ac\u09be\u0997"
    ],
    "name:ben_in_x_preferred":[
        "\u09a8\u09bf\u09b6\u09be\u09a4 \u09ac\u09be\u0998"
    ],
    "name:eng_x_preferred":[
        "Nishat Bagh"
    ],
    "name:fra_x_preferred":[
        "Nishat Bagh"
    ],
    "name:guj_x_preferred":[
        "\u0aa8\u0abf\u0ab6\u0abe\u0aa4 \u0aac\u0abe\u0a97"
    ],
    "name:hin_x_preferred":[
        "\u0928\u093f\u0936\u093e\u0924 \u092c\u093e\u0917"
    ],
    "name:hin_x_variant":[
        "\u0928\u093f\u0936\u093e\u0924"
    ],
    "name:ita_x_preferred":[
        "Nishat Bagh"
    ],
    "name:kan_x_preferred":[
        "\u0ca8\u0cbf\u0cb6\u0cbe\u0c82\u0ca4\u0ccd \u0cac\u0cbe\u0c98\u0ccd"
    ],
    "name:mal_x_preferred":[
        "\u0d28\u0d3f\u0d37\u0d3e\u0d24\u0d4d\u0d24\u0d4d \u0d2c\u0d3e\u0d17\u0d4d"
    ],
    "name:mar_x_preferred":[
        "\u0928\u093f\u0936\u093e\u0924 \u092c\u093e\u0917"
    ],
    "name:msa_x_preferred":[
        "Nishat Bagh"
    ],
    "name:nld_x_preferred":[
        "Nishat Bagh"
    ],
    "name:pan_x_preferred":[
        "\u0a28\u0a3f\u0a36\u0a3e\u0a24 \u0a2c\u0a3e\u0a17"
    ],
    "name:san_x_preferred":[
        "nishat"
    ],
    "name:tam_x_preferred":[
        "\u0ba8\u0bbf\u0bb7\u0bbe\u0ba4\u0bcd \u0baa\u0bbe\u0b95\u0bcd"
    ],
    "name:tel_x_preferred":[
        "\u0c28\u0c3f\u0c37\u0c1f\u0c4d \u0c2c\u0c3e\u0c17\u0c4d"
    ],
    "name:urd_x_preferred":[
        "\u0646\u0634\u0627\u0637 \u0628\u0627\u063a"
    ],
    "qs:gn_adm0_cc":"IN",
    "qs:gn_local":1255634,
    "qs:gn_nam_loc":"Srinagar, Srinagar, Jammu and Kashmir, IN",
    "qs:gn_namadm1":"12",
    "qs:local_max":800,
    "qs:local_sum":2636,
    "qs:localhoods":18,
    "qs:name":"Nishat Bagh",
    "qs:name_adm0":"India",
    "qs:name_adm1":"Jammu and Kashmir",
    "qs:name_adm2":"Srinagar",
    "qs:name_local":"Srinagar",
    "qs:photo_max":64,
    "qs:photo_sum":115,
    "qs:placetype":"Suburb",
    "qs:quad_count":9,
    "qs:woe_adm0":23424848,
    "qs:woe_adm1":2345746,
    "qs:woe_adm2":12586462,
    "qs:woe_lau":0,
    "qs:woe_local":2295387,
    "qs:woe_ver":"7.10.0",
    "wd:wordcount":1518,
    "wof:lang":[
        "eng"
    ],
    "wof:name":"Nishat Bagh",
    "wof:placetype":"neighbourhood"
},
  "geometry": {"coordinates":[74.879098,34.128916],"type":"Point"}
}