{
  "type": "Feature",
  "properties": {
    "iso:country":"IN",
    "ks:ks_alt_nam":"N  MURAHI",
    "ks:ks_name":"N Murahi",
    "ks:ks_pop":332,
    "ks:ks_type":"HABITATION",
    "ks:ks_uagg_main":0,
    "name:eng_x_preferred":[
        "N Murahi"
    ],
    "name:eng_x_variant":[
        "N  MURAHI"
    ],
    "wof:name":"N Murahi",
    "wof:placetype":"neighbourhood",
    "wof:population":332
},
  "geometry": {"coordinates":[78.9387,27.61134],"type":"Point"}
}