{
  "type": "Feature",
  "properties": {
    "iso:country":"IN",
    "ks:ks_name":"Khuravpada",
    "ks:ks_pop":244,
    "ks:ks_type":"HABITATION",
    "name:eng_x_preferred":[
        "Khuravpada"
    ],
    "wof:name":"Khuravpada",
    "wof:placetype":"locality",
    "wof:population":244
},
  "geometry": {"coordinates":[73.028003,19.981189],"type":"Point"}
}