{
  "type": "Feature",
  "properties": {
    "gn:admin1_code":"11.0",
    "gn:admin2_code":"33.0",
    "gn:asciiname":"Kunli",
    "gn:country_code":"IN",
    "gn:dem":2260,
    "gn:feature_class":"P",
    "gn:feature_code":"PPL",
    "gn:name":"Kunli",
    "gn:population":0,
    "gn:timezone":"Asia/Kolkata",
    "iso:country":"IN",
    "wof:name":"Kunli",
    "wof:placetype":"locality"
},
  "geometry": {"coordinates":[77.34357,31.1315],"type":"Point"}
}