{
  "type": "Feature",
  "properties": {
    "gn:admin1_code":"11",
    "gn:admin2_code":"23.0",
    "gn:asciiname":"Rihara",
    "gn:country_code":"IN",
    "gn:dem":1164,
    "gn:feature_class":"P",
    "gn:feature_code":"PPL",
    "gn:name":"Rih\u0101ra",
    "gn:population":0,
    "gn:timezone":"Asia/Kolkata",
    "iso:country":"IN",
    "wof:name":"Rihara",
    "wof:placetype":"locality"
},
  "geometry": {"coordinates":[76.10928,32.28275],"type":"Point"}
}