{
  "type": "Feature",
  "properties": {
    "iso:country":"IN",
    "ks:ks_name":"Chandu Tola",
    "ks:ks_pop":149,
    "ks:ks_type":"HABITATION",
    "name:eng_x_preferred":[
        "Chandu Tola"
    ],
    "wof:name":"Chandu Tola",
    "wof:placetype":"locality",
    "wof:population":149
},
  "geometry": {"coordinates":[85.18893300000001,25.387385],"type":"Point"}
}