{
  "type": "Feature",
  "properties": {
    "gn:admin1_code":"34.0",
    "gn:admin2_code":"235.0",
    "gn:asciiname":"Dowal",
    "gn:country_code":"IN",
    "gn:dem":93,
    "gn:feature_class":"P",
    "gn:feature_code":"PPL",
    "gn:name":"Dow\u0101l",
    "gn:population":0,
    "gn:timezone":"Asia/Kolkata",
    "iso:country":"IN",
    "name:fas_x_preferred":[
        "\u062f\u0648\u0627\u0644"
    ],
    "name:urd_x_preferred":[
        "\u0688\u0627\u0624\u0644"
    ],
    "wof:name":"Dowal",
    "wof:placetype":"locality"
},
  "geometry": {"coordinates":[84.72895,24.96394],"type":"Point"}
}