{
  "type": "Feature",
  "properties": {
    "iso:country":"IN",
    "ks:ks_name":"Vadakkunanallur",
    "ks:ks_pop":325,
    "ks:ks_type":"HABITATION",
    "name:eng_x_preferred":[
        "Vadakkunanallur"
    ],
    "wof:name":"Vadakkunanallur",
    "wof:placetype":"locality",
    "wof:population":325
},
  "geometry": {"coordinates":[79.535698,10.524022],"type":"Point"}
}