{
  "type": "Feature",
  "properties": {
    "gn:admin1_code":"39",
    "gn:admin2_code":"60.0",
    "gn:asciiname":"Aithani",
    "gn:country_code":"IN",
    "gn:dem":2017,
    "gn:feature_class":"P",
    "gn:feature_code":"PPL",
    "gn:name":"Aith\u0101ni",
    "gn:population":0,
    "gn:timezone":"Asia/Kolkata",
    "iso:country":"IN",
    "ks:ks_alt_nam":"Aith\u0101ni",
    "ks:ks_alt_nam_2":"Aithani",
    "ks:ks_name":"Aithan",
    "ks:ks_type":"VILLAGE",
    "name:eng_x_preferred":[
        "Aithan"
    ],
    "name:eng_x_variant":[
        "Aithani",
        "Aith\u0101ni"
    ],
    "wof:name":"Aithan",
    "wof:placetype":"locality"
},
  "geometry": {"coordinates":[77.95609899999999,30.868538],"type":"Point"}
}