{
  "type": "Feature",
  "properties": {
    "iso:country":"IN",
    "ks:ks_name":"Musapapuli",
    "ks:ks_pop":1441,
    "ks:ks_type":"VILLAGE",
    "ks:ks_uagg_main":0,
    "name:eng_x_preferred":[
        "Musapapuli"
    ],
    "wof:name":"Musapapuli",
    "wof:placetype":"neighbourhood",
    "wof:population":1441
},
  "geometry": {"coordinates":[85.032065,20.820152],"type":"Point"}
}