{
  "type": "Feature",
  "properties": {
    "gn:admin1_code":"11.0",
    "gn:admin2_code":"32.0",
    "gn:asciiname":"Dohar",
    "gn:country_code":"IN",
    "gn:dem":1587,
    "gn:feature_class":"P",
    "gn:feature_code":"PPL",
    "gn:name":"Dohar",
    "gn:population":0,
    "gn:timezone":"Asia/Kolkata",
    "iso:country":"IN",
    "wof:name":"Dohar",
    "wof:placetype":"locality"
},
  "geometry": {"coordinates":[77.31985999999998,30.86451],"type":"Point"}
}