{
  "type": "Feature",
  "properties": {
    "iso:country":"IN",
    "ks:ks_name":"Nidaya",
    "ks:ks_pop":648,
    "ks:ks_type":"VILLAGE",
    "name:eng_x_preferred":[
        "Nidaya"
    ],
    "wof:name":"Nidaya",
    "wof:placetype":"locality",
    "wof:population":648
},
  "geometry": {"coordinates":[86.964102,23.271768],"type":"Point"}
}