{
  "type": "Feature",
  "properties": {
    "iso:country":"IN",
    "ks:ks_name":"Kherali Falia",
    "ks:ks_pop":1226,
    "ks:ks_type":"HABITATION",
    "name:eng_x_preferred":[
        "Kherali Falia"
    ],
    "wof:name":"Kherali Falia",
    "wof:placetype":"locality",
    "wof:population":1226
},
  "geometry": {"coordinates":[74.10724999999999,22.626861],"type":"Point"}
}