{
  "type": "Feature",
  "properties": {
    "gn:admin1_code":"36",
    "gn:admin2_code":"179.0",
    "gn:asciiname":"Narsinghdaspur",
    "gn:country_code":"IN",
    "gn:dem":96,
    "gn:feature_class":"P",
    "gn:feature_code":"PPL",
    "gn:name":"Narsinghdaspur",
    "gn:population":0,
    "gn:timezone":"Asia/Kolkata",
    "iso:country":"IN",
    "ks:ks_name":"Narsinghpur",
    "ks:ks_pop":593,
    "ks:ks_type":"VILLAGE",
    "name:eng_x_preferred":[
        "Narsinghpur"
    ],
    "name:eng_x_variant":[
        "Narsinghdaspur"
    ],
    "wof:name":"Narsinghpur",
    "wof:placetype":"locality",
    "wof:population":593
},
  "geometry": {"coordinates":[82.391177,26.367785],"type":"Point"}
}