{
  "type": "Feature",
  "properties": {
    "iso:country":"IN",
    "ks:ks_alt_nam":"heggalu",
    "ks:ks_name":"Heggalu",
    "ks:ks_pop":245,
    "ks:ks_type":"HABITATION",
    "name:eng_x_preferred":[
        "Heggalu"
    ],
    "wof:name":"Heggalu",
    "wof:placetype":"locality",
    "wof:population":245
},
  "geometry": {"coordinates":[74.53701100000001,14.016094],"type":"Point"}
}