{
  "type": "Feature",
  "properties": {
    "gn:admin1_code":"34.0",
    "gn:admin2_code":"221.0",
    "gn:asciiname":"Songar",
    "gn:country_code":"IN",
    "gn:dem":53,
    "gn:feature_class":"P",
    "gn:feature_code":"PPL",
    "gn:name":"Songar",
    "gn:population":0,
    "gn:timezone":"Asia/Kolkata",
    "iso:country":"IN",
    "name:nno_x_preferred":[
        "Songar"
    ],
    "wof:name":"Songar",
    "wof:placetype":"locality"
},
  "geometry": {"coordinates":[85.64478000000003,25.82051],"type":"Point"}
}