{
  "type": "Feature",
  "properties": {
    "gn:admin1_code":"34.0",
    "gn:admin2_code":"221.0",
    "gn:asciiname":"Songar",
    "gn:country_code":"IN",
    "gn:dem":53,
    "gn:feature_class":"P",
    "gn:feature_code":"PPL",
    "gn:name":"Songar",
    "gn:population":0,
    "gn:timezone":"Asia/Kolkata",
    "iso:country":"IN",
    "ks:ks_name":"Songar",
    "ks:ks_pop":2509,
    "ks:ks_type":"VILLAGE",
    "name:eng_x_preferred":[
        "Songar"
    ],
    "name:nno_x_preferred":[
        "Songar"
    ],
    "wof:name":"Songar",
    "wof:placetype":"locality",
    "wof:population":2509
},
  "geometry": {"coordinates":[85.63523499999999,25.815291],"type":"Point"}
}