{
  "type": "Feature",
  "properties": {
    "gn:admin1_code":"2.0",
    "gn:admin2_code":"544.0",
    "gn:asciiname":"Nadividi",
    "gn:country_code":"IN",
    "gn:dem":922,
    "gn:feature_class":"P",
    "gn:feature_code":"PPL",
    "gn:name":"Nadiv\u012bdi",
    "gn:population":0,
    "gn:timezone":"Asia/Kolkata",
    "iso:country":"IN",
    "wof:name":"Nadividi",
    "wof:placetype":"locality"
},
  "geometry": {"coordinates":[82.72315,18.14594],"type":"Point"}
}