{
  "type": "Feature",
  "properties": {
    "iso:country":"IN",
    "ks:ks_name":"Babua Patti",
    "ks:ks_pop":52,
    "ks:ks_type":"VILLAGE",
    "name:eng_x_preferred":[
        "Babua Patti"
    ],
    "wof:name":"Babua Patti",
    "wof:placetype":"locality",
    "wof:population":52
},
  "geometry": {"coordinates":[83.532481,25.711599],"type":"Point"}
}