{
  "type": "Feature",
  "properties": {
    "iso:country":"IN",
    "ks:ks_name":"Giru",
    "ks:ks_pop":247,
    "ks:ks_type":"VILLAGE",
    "name:eng_x_preferred":[
        "Giru"
    ],
    "wof:name":"Giru",
    "wof:placetype":"locality",
    "wof:population":247
},
  "geometry": {"coordinates":[85.216105,22.69303],"type":"Point"}
}