{
  "type": "Feature",
  "properties": {
    "gn:admin1_code":"19.0",
    "gn:admin2_code":"570.0",
    "gn:asciiname":"Kamalapur",
    "gn:country_code":"IN",
    "gn:dem":692,
    "gn:feature_class":"P",
    "gn:feature_code":"PPL",
    "gn:name":"K\u0101mal\u0101pur",
    "gn:population":0,
    "gn:timezone":"Asia/Kolkata",
    "iso:country":"IN",
    "ks:ks_name":"Kamalapura",
    "ks:ks_pop":446,
    "ks:ks_type":"VILLAGE",
    "name:eng_x_preferred":[
        "Kamalapura"
    ],
    "name:eng_x_variant":[
        "Kamalapur"
    ],
    "wof:name":"Kamalapura",
    "wof:placetype":"locality",
    "wof:population":446
},
  "geometry": {"coordinates":[75.414619,13.586639],"type":"Point"}
}