{
  "type": "Feature",
  "properties": {
    "gn:admin1_code":"24.0",
    "gn:admin2_code":"108.0",
    "gn:asciiname":"Bad",
    "gn:country_code":"IN",
    "gn:dem":234,
    "gn:feature_class":"P",
    "gn:feature_code":"PPL",
    "gn:name":"B\u0101d",
    "gn:population":0,
    "gn:timezone":"Asia/Kolkata",
    "iso:country":"IN",
    "name:aze_x_preferred":[
        "Bad"
    ],
    "name:ceb_x_preferred":[
        "Bad"
    ],
    "name:ces_x_preferred":[
        "Bad"
    ],
    "name:dan_x_preferred":[
        "Bad"
    ],
    "name:deu_x_preferred":[
        "Bad"
    ],
    "name:fra_x_preferred":[
        "Bad"
    ],
    "name:jpn_x_preferred":[
        "\u30d0\u30c3\u30c9"
    ],
    "name:kor_x_preferred":[
        "Bad"
    ],
    "name:new_x_preferred":[
        "\u092c\u093e\u0926"
    ],
    "name:nld_x_preferred":[
        "Bad"
    ],
    "name:nno_x_preferred":[
        "Bad"
    ],
    "name:pol_x_preferred":[
        "Bad"
    ],
    "name:por_x_preferred":[
        "Bad"
    ],
    "name:rus_x_preferred":[
        "Bad"
    ],
    "name:spa_x_preferred":[
        "Bad"
    ],
    "name:tha_x_preferred":[
        "\u0e41\u0e1a\u0e14"
    ],
    "name:tur_x_preferred":[
        "Bad"
    ],
    "wof:name":"Bad",
    "wof:placetype":"locality"
},
  "geometry": {"coordinates":[76.56480000000001,26.31161],"type":"Point"}
}