{
  "type": "Feature",
  "properties": {
    "iso:country":"IN",
    "ks:ks_name":"Garasangi",
    "ks:ks_pop":697,
    "ks:ks_type":"VILLAGE",
    "name:eng_x_preferred":[
        "Garasangi"
    ],
    "wof:name":"Garasangi",
    "wof:placetype":"locality",
    "wof:population":697
},
  "geometry": {"coordinates":[75.71324300000001,16.494834],"type":"Point"}
}