{
  "type": "Feature",
  "properties": {
    "iso:country":"IN",
    "ks:ks_name":"Chinna Kattu Palayam",
    "ks:ks_pop":564,
    "ks:ks_type":"HABITATION",
    "name:eng_x_preferred":[
        "Chinna Kattu Palayam"
    ],
    "wof:name":"Chinna Kattu Palayam",
    "wof:placetype":"locality",
    "wof:population":564
},
  "geometry": {"coordinates":[77.38153,10.988634],"type":"Point"}
}