{
  "type": "Feature",
  "properties": {
    "gn:admin1_code":"23.0",
    "gn:admin2_code":"41.0",
    "gn:asciiname":"Ajnaud",
    "gn:country_code":"IN",
    "gn:dem":258,
    "gn:feature_class":"P",
    "gn:feature_code":"PPL",
    "gn:name":"Ajnaud",
    "gn:population":0,
    "gn:timezone":"Asia/Kolkata",
    "iso:country":"IN",
    "wof:name":"Ajnaud",
    "wof:placetype":"locality"
},
  "geometry": {"coordinates":[75.97591,30.79885],"type":"Point"}
}