{
  "type": "Feature",
  "properties": {
    "iso:country":"IN",
    "ks:ks_name":"Odupara",
    "ks:ks_pop":741,
    "ks:ks_type":"HABITATION",
    "name:eng_x_preferred":[
        "Odupara"
    ],
    "wof:name":"Odupara",
    "wof:placetype":"locality",
    "wof:population":741
},
  "geometry": {"coordinates":[75.859354,11.390974],"type":"Point"}
}