{
  "type": "Feature",
  "properties": {
    "iso:country":"IN",
    "ks:ks_name":"Phalu Ka Pura",
    "ks:ks_pop":600,
    "ks:ks_type":"HABITATION",
    "name:eng_x_preferred":[
        "Phalu Ka Pura"
    ],
    "wof:name":"Phalu Ka Pura",
    "wof:placetype":"locality",
    "wof:population":600
},
  "geometry": {"coordinates":[81.90563400000001,25.188045],"type":"Point"}
}