{
  "type": "Feature",
  "properties": {
    "iso:country":"IN",
    "ks:ks_name":"Perdadka",
    "ks:ks_pop":10,
    "ks:ks_type":"HABITATION",
    "name:eng_x_preferred":[
        "Perdadka"
    ],
    "wof:name":"Perdadka",
    "wof:placetype":"locality",
    "wof:population":10
},
  "geometry": {"coordinates":[75.272666,12.901593],"type":"Point"}
}