{
  "type": "Feature",
  "properties": {
    "iso:country":"IN",
    "ks:ks_name":"Banshibaripathar",
    "ks:ks_pop":293,
    "ks:ks_type":"HABITATION",
    "name:eng_x_preferred":[
        "Banshibaripathar"
    ],
    "wof:name":"Banshibaripathar",
    "wof:placetype":"locality",
    "wof:population":293
},
  "geometry": {"coordinates":[91.00382,26.559643],"type":"Point"}
}