{
  "type": "Feature",
  "properties": {
    "iso:country":"IN",
    "ks:ks_alt_nam":"MATIKACHHAR",
    "ks:ks_name":"Matikachhar",
    "ks:ks_pop":609,
    "ks:ks_type":"HABITATION",
    "ks:ks_uagg_main":0,
    "name:eng_x_preferred":[
        "Matikachhar"
    ],
    "wof:name":"Matikachhar",
    "wof:placetype":"neighbourhood",
    "wof:population":609
},
  "geometry": {"coordinates":[81.86790499999999,22.744181],"type":"Point"}
}