{
  "type": "Feature",
  "properties": {
    "iso:country":"IN",
    "ks:ks_name":"Adani",
    "ks:ks_pop":767,
    "ks:ks_type":"VILLAGE",
    "ks:ks_uagg_main":0,
    "name:eng_x_preferred":[
        "Adani"
    ],
    "wof:name":"Adani",
    "wof:placetype":"neighbourhood",
    "wof:population":767
},
  "geometry": {"coordinates":[74.76068600000001,26.957192],"type":"Point"}
}