{
  "type": "Feature",
  "properties": {
    "iso:country":"IN",
    "ks:ks_alt_nam":"MANIYANPARA JN",
    "ks:ks_name":"Maniyanpara Jn",
    "ks:ks_pop":1000,
    "ks:ks_type":"HABITATION",
    "ks:ks_uagg_main":0,
    "name:eng_x_preferred":[
        "Maniyanpara Jn"
    ],
    "wof:name":"Maniyanpara Jn",
    "wof:placetype":"neighbourhood",
    "wof:population":1000
},
  "geometry": {"coordinates":[76.51033,10.741609],"type":"Point"}
}