{
  "type": "Feature",
  "properties": {
    "iso:country":"IN",
    "ks:ks_name":"Thumbakuni",
    "ks:ks_pop":950,
    "ks:ks_type":"HABITATION",
    "name:eng_x_preferred":[
        "Thumbakuni"
    ],
    "wof:name":"Thumbakuni",
    "wof:placetype":"locality",
    "wof:population":950
},
  "geometry": {"coordinates":[76.158507,11.682371],"type":"Point"}
}