{
  "type": "Feature",
  "properties": {
    "gn:admin1_code":"3.0",
    "gn:admin2_code":"321.0",
    "gn:asciiname":"Helesa",
    "gn:country_code":"IN",
    "gn:dem":58,
    "gn:feature_class":"P",
    "gn:feature_code":"PPL",
    "gn:name":"Helesa",
    "gn:population":0,
    "gn:timezone":"Asia/Kolkata",
    "iso:country":"IN",
    "wof:name":"Helesa",
    "wof:placetype":"locality"
},
  "geometry": {"coordinates":[91.62144000000001,26.33501],"type":"Point"}
}