{
  "type": "Feature",
  "properties": {
    "gn:admin1_code":"39.0",
    "gn:admin2_code":"64.0",
    "gn:asciiname":"Kupi",
    "gn:country_code":"IN",
    "gn:dem":697,
    "gn:feature_class":"P",
    "gn:feature_code":"PPL",
    "gn:name":"K\u016bpi",
    "gn:population":0,
    "gn:timezone":"Asia/Kolkata",
    "iso:country":"IN",
    "ks:ks_name":"Kopi",
    "ks:ks_pop":146,
    "ks:ks_type":"VILLAGE",
    "name:eng_x_preferred":[
        "Kopi"
    ],
    "name:eng_x_variant":[
        "Kupi"
    ],
    "wof:name":"Kopi",
    "wof:placetype":"locality",
    "wof:population":146
},
  "geometry": {"coordinates":[79.102632,29.619265],"type":"Point"}
}