{
  "type": "Feature",
  "properties": {
    "gn:admin1_code":"34.0",
    "gn:admin2_code":"222.0",
    "gn:asciiname":"Ajitpur",
    "gn:country_code":"IN",
    "gn:dem":50,
    "gn:feature_class":"P",
    "gn:feature_code":"PPL",
    "gn:name":"Ajitpur",
    "gn:population":0,
    "gn:timezone":"Asia/Kolkata",
    "iso:country":"IN",
    "ks:ks_name":"Ajitpur",
    "ks:ks_type":"VILLAGE",
    "name:eng_x_preferred":[
        "Ajitpur"
    ],
    "wof:name":"Ajitpur",
    "wof:placetype":"locality"
},
  "geometry": {"coordinates":[85.82819600000001,25.562058],"type":"Point"}
}