{
  "type": "Feature",
  "properties": {
    "iso:country":"IN",
    "ks:ks_name":"Joba",
    "ks:ks_pop":2045,
    "ks:ks_type":"VILLAGE",
    "name:eng_x_preferred":[
        "Joba"
    ],
    "wof:name":"Joba",
    "wof:placetype":"locality",
    "wof:population":2045
},
  "geometry": {"coordinates":[81.779753,19.445274],"type":"Point"}
}