{
  "type": "Feature",
  "properties": {
    "iso:country":"IN",
    "ks:ks_name":"Rajganj",
    "ks:ks_pop":0,
    "ks:ks_type":"VILLAGE",
    "name:eng_x_preferred":[
        "Rajganj"
    ],
    "wof:name":"Rajganj",
    "wof:placetype":"locality",
    "wof:population":0
},
  "geometry": {"coordinates":[86.717377,25.210439],"type":"Point"}
}