{
  "type": "Feature",
  "properties": {
    "iso:country":"IN",
    "ks:ks_name":"Bara Hariharpur",
    "ks:ks_pop":372,
    "ks:ks_type":"VILLAGE",
    "name:eng_x_preferred":[
        "Bara Hariharpur"
    ],
    "wof:name":"Bara Hariharpur",
    "wof:placetype":"locality",
    "wof:population":372
},
  "geometry": {"coordinates":[86.056588,22.832185],"type":"Point"}
}