{
  "type": "Feature",
  "properties": {
    "iso:country":"IN",
    "ks:ks_alt_nam":"Mucherlakunta tanda",
    "ks:ks_name":"Mucherlakunta Tanda",
    "ks:ks_pop":304,
    "ks:ks_type":"HABITATION",
    "name:eng_x_preferred":[
        "Mucherlakunta Tanda"
    ],
    "wof:name":"Mucherlakunta Tanda",
    "wof:placetype":"locality",
    "wof:population":304
},
  "geometry": {"coordinates":[78.816698,17.10903],"type":"Point"}
}