{
  "type": "Feature",
  "properties": {
    "iso:country":"IN",
    "ks:ks_name":"Akkinakodlu",
    "ks:ks_pop":84,
    "ks:ks_type":"HABITATION",
    "name:eng_x_preferred":[
        "Akkinakodlu"
    ],
    "wof:name":"Akkinakodlu",
    "wof:placetype":"locality",
    "wof:population":84
},
  "geometry": {"coordinates":[74.890179,13.736884],"type":"Point"}
}