{
  "type": "Feature",
  "properties": {
    "iso:country":"IN",
    "ks:ks_name":"Gourikere",
    "ks:ks_pop":16,
    "ks:ks_type":"HABITATION",
    "name:eng_x_preferred":[
        "Gourikere"
    ],
    "wof:name":"Gourikere",
    "wof:placetype":"locality",
    "wof:population":16
},
  "geometry": {"coordinates":[75.313565,14.008924],"type":"Point"}
}