{
  "type": "Feature",
  "properties": {
    "gn:admin1_code":"19.0",
    "gn:admin2_code":"564.0",
    "gn:asciiname":"Chennapur",
    "gn:country_code":"IN",
    "gn:dem":559,
    "gn:feature_class":"P",
    "gn:feature_code":"PPL",
    "gn:name":"Chenn\u0101pur",
    "gn:population":0,
    "gn:timezone":"Asia/Kolkata",
    "iso:country":"IN",
    "ks:ks_name":"Channapur",
    "ks:ks_pop":573,
    "ks:ks_type":"VILLAGE",
    "name:eng_x_preferred":[
        "Channapur"
    ],
    "name:eng_x_variant":[
        "Chennapur"
    ],
    "name:vie_x_preferred":[
        "Chennapur"
    ],
    "wof:name":"Channapur",
    "wof:placetype":"locality",
    "wof:population":573
},
  "geometry": {"coordinates":[75.219854,14.781336],"type":"Point"}
}