{
  "type": "Feature",
  "properties": {
    "iso:country":"IN",
    "ks:ks_name":"Lotar",
    "ks:ks_pop":268,
    "ks:ks_type":"VILLAGE",
    "name:eng_x_preferred":[
        "Lotar"
    ],
    "wof:name":"Lotar",
    "wof:placetype":"locality",
    "wof:population":268
},
  "geometry": {"coordinates":[84.00591900000001,24.21003],"type":"Point"}
}