{
  "type": "Feature",
  "properties": {
    "iso:country":"IN",
    "ks:ks_name":"Mundasahi",
    "ks:ks_pop":247,
    "ks:ks_type":"HABITATION",
    "name:eng_x_preferred":[
        "Mundasahi"
    ],
    "wof:name":"Mundasahi",
    "wof:placetype":"locality",
    "wof:population":247
},
  "geometry": {"coordinates":[85.19725800000001,21.926071],"type":"Point"}
}