{
  "type": "Feature",
  "properties": {
    "iso:country":"IN",
    "ks:ks_name":"Ratwely",
    "ks:ks_pop":645,
    "ks:ks_type":"HABITATION",
    "name:eng_x_preferred":[
        "Ratwely"
    ],
    "wof:name":"Ratwely",
    "wof:placetype":"locality",
    "wof:population":645
},
  "geometry": {"coordinates":[87.483397,25.940259],"type":"Point"}
}