{
  "type": "Feature",
  "properties": {
    "gn:admin1_code":"20",
    "gn:admin2_code":"266.0",
    "gn:asciiname":"Zulhami",
    "gn:country_code":"IN",
    "gn:dem":1733,
    "gn:feature_class":"P",
    "gn:feature_code":"PPL",
    "gn:name":"Zulhami",
    "gn:population":0,
    "gn:timezone":"Asia/Kolkata",
    "iso:country":"IN",
    "wof:name":"Zulhami",
    "wof:placetype":"locality"
},
  "geometry": {"coordinates":[94.39098,25.82455],"type":"Point"}
}