{
  "type": "Feature",
  "properties": {
    "iso:country":"IN",
    "ks:ks_name":"Balesar",
    "ks:ks_pop":32,
    "ks:ks_type":"HABITATION",
    "name:eng_x_preferred":[
        "Balesar"
    ],
    "wof:name":"Balesar",
    "wof:placetype":"locality",
    "wof:population":32
},
  "geometry": {"coordinates":[74.72235999999999,14.886761],"type":"Point"}
}