{
  "type": "Feature",
  "properties": {
    "iso:country":"IN",
    "ks:ks_name":"Naya Khera",
    "ks:ks_pop":189,
    "ks:ks_type":"HABITATION",
    "name:eng_x_preferred":[
        "Naya Khera"
    ],
    "wof:name":"Naya Khera",
    "wof:placetype":"locality",
    "wof:population":189
},
  "geometry": {"coordinates":[76.336344,24.274317],"type":"Point"}
}