{
  "type": "Feature",
  "properties": {
    "gn:admin1_code":"12.0",
    "gn:admin2_code":"001",
    "gn:asciiname":"Ananwan",
    "gn:country_code":"IN",
    "gn:dem":1617,
    "gn:feature_class":"P",
    "gn:feature_code":"PPL",
    "gn:name":"Ananwan",
    "gn:population":0,
    "gn:timezone":"Asia/Kolkata",
    "iso:country":"IN",
    "wof:name":"Ananwan",
    "wof:placetype":"locality"
},
  "geometry": {"coordinates":[74.31959999999999,34.34947],"type":"Point"}
}