{
  "type": "Feature",
  "properties": {
    "iso:country":"IN",
    "ks:ks_name":"Phulwaria",
    "ks:ks_pop":177,
    "ks:ks_type":"HABITATION",
    "name:eng_x_preferred":[
        "Phulwaria"
    ],
    "wof:name":"Phulwaria",
    "wof:placetype":"locality",
    "wof:population":177
},
  "geometry": {"coordinates":[83.029448,27.405365],"type":"Point"}
}