{
  "type": "Feature",
  "properties": {
    "gn:admin1_code":"34.0",
    "gn:admin2_code":"231.0",
    "gn:asciiname":"Mahuli",
    "gn:country_code":"IN",
    "gn:dem":57,
    "gn:feature_class":"P",
    "gn:feature_code":"PPL",
    "gn:name":"Mahuli",
    "gn:population":0,
    "gn:timezone":"Asia/Kolkata",
    "iso:country":"IN",
    "ks:ks_name":"Mahuli",
    "ks:ks_pop":900,
    "ks:ks_type":"HABITATION",
    "name:eng_x_preferred":[
        "Mahuli"
    ],
    "name:guj_x_preferred":[
        "\u0aae\u0abe\u0ab9\u0ac1\u0ab2\u0ac0\u0a97\u0aa1"
    ],
    "name:mar_x_preferred":[
        "\u092e\u093e\u0939\u0941\u0932\u0940\u0917\u0921"
    ],
    "wof:name":"Mahuli",
    "wof:placetype":"locality",
    "wof:population":900
},
  "geometry": {"coordinates":[84.58579400000001,25.685442],"type":"Point"}
}