{
  "type": "Feature",
  "properties": {
    "iso:country":"IN",
    "ks:ks_name":"Gabi",
    "ks:ks_pop":79,
    "ks:ks_type":"HABITATION",
    "ks:ks_uagg_main":0,
    "name:eng_x_preferred":[
        "Gabi"
    ],
    "wof:name":"Gabi",
    "wof:placetype":"neighbourhood",
    "wof:population":79
},
  "geometry": {"coordinates":[81.861136,25.89989],"type":"Point"}
}