{
  "type": "Feature",
  "properties": {
    "gn:admin1_code":"25.0",
    "gn:admin2_code":"617.0",
    "gn:asciiname":"Kachchiperumalnattam",
    "gn:country_code":"IN",
    "gn:dem":50,
    "gn:feature_class":"P",
    "gn:feature_code":"PPL",
    "gn:name":"Kachchiperum\u0101lnattam",
    "gn:population":0,
    "gn:timezone":"Asia/Kolkata",
    "iso:country":"IN",
    "wof:name":"Kachchiperumalnattam",
    "wof:placetype":"locality"
},
  "geometry": {"coordinates":[79.25248000000001,11.54656],"type":"Point"}
}