{
  "type": "Feature",
  "properties": {
    "iso:country":"IN",
    "ks:ks_name":"Jaithram Tanda",
    "ks:ks_pop":148,
    "ks:ks_type":"HABITATION",
    "name:eng_x_preferred":[
        "Jaithram Tanda"
    ],
    "wof:name":"Jaithram Tanda",
    "wof:placetype":"locality",
    "wof:population":148
},
  "geometry": {"coordinates":[78.666467,19.446331],"type":"Point"}
}