{
  "type": "Feature",
  "properties": {
    "iso:country":"IN",
    "ks:ks_alt_nam":"NAU NAGAR",
    "ks:ks_name":"Nau Nagar",
    "ks:ks_pop":2686,
    "ks:ks_type":"HABITATION",
    "name:eng_x_preferred":[
        "Nau Nagar"
    ],
    "wof:name":"Nau Nagar",
    "wof:placetype":"locality",
    "wof:population":2686
},
  "geometry": {"coordinates":[86.327949,26.332664],"type":"Point"}
}