{
  "type": "Feature",
  "properties": {
    "gn:country":"IN",
    "gn:fcode":"PPL",
    "gn:population":0,
    "iso:country":"IN",
    "name:ara_x_preferred":[
        "\u0623\u0646\u0648\u062c\u064a\u063a\u0648\u062f\u0627"
    ],
    "name:ben_bn_x_preferred":[
        "\u0986\u09a8\u09cd\u09a8\u099c\u09bf\u0997\u09c1\u09a1\u09be"
    ],
    "name:ben_in_x_preferred":[
        "\u0986\u09a8\u09cd\u09a8\u099c\u09bf\u0997\u09c1\u09a1\u09be"
    ],
    "name:guj_x_preferred":[
        "\u0a85\u0aa8\u0acd\u0aa8\u0acb\u0a9c\u0ac0\u0a97\u0ac1\u0aa1\u0ac1\u0abe"
    ],
    "name:hin_x_preferred":[
        "\u0905\u0928\u094d\u0928\u094b\u091c\u0940\u0917\u0941\u095c\u093e"
    ],
    "name:kan_x_preferred":[
        "\u0c85\u0ca3\u0ccd\u0ca3\u0ccb\u0c9c\u0cbf\u0c97\u0ccc\u0ca1"
    ],
    "name:mal_x_preferred":[
        "\u0d05\u0d28\u0d4d\u0d28\u0d4b\u0d1c\u0d3f\u0d17\u0d41\u0d21"
    ],
    "name:mar_x_preferred":[
        "\u0905\u0928\u094b\u091c\u0940\u0917\u0941\u0921\u093e"
    ],
    "name:pan_x_preferred":[
        "\u0a05\u0a28\u0a4c\u0a1c\u0a40\u0a17\u0a41\u0a21\u0a3e"
    ],
    "name:tam_x_preferred":[
        "\u0b85\u0ba9\u0bcd\u0ba9\u0bcb\u0b9c\u0bbf\u0b95\u0bc1\u0b9f\u0bbe"
    ],
    "name:tel_x_preferred":[
        "\u0c05\u0c28\u0c4d\u0c28\u0c4b\u0c1c\u0c3f\u0c17\u0c42\u0c21"
    ],
    "name:urd_x_preferred":[
        "\u0627\u0646\u0651\u0648\u062c\u06cc \u06af\u0688\u0627"
    ],
    "qs:name":"Annojiguda",
    "qs:name_adm0":"India",
    "qs:name_adm1":"Andhra Pradesh",
    "qs:photos":1,
    "qs:photos_1k":1,
    "qs:photos_9k":1,
    "qs:photos_9r":1,
    "qs:photos_all":1,
    "qs:photos_sr":1,
    "qs:placetype":"Suburb",
    "qs:pop_sr":"0",
    "wof:name":"Annojiguda",
    "wof:placetype":"neighbourhood",
    "wof:population":0
},
  "geometry": {"coordinates":[78.65595,17.43358],"type":"Point"}
}