{
  "type": "Feature",
  "properties": {
    "gn:admin1_code":"37",
    "gn:admin2_code":"412.0",
    "gn:asciiname":"Lakhanpuri",
    "gn:country_code":"IN",
    "gn:dem":467,
    "gn:feature_class":"P",
    "gn:feature_code":"PPL",
    "gn:name":"Lakhanpuri",
    "gn:population":0,
    "gn:timezone":"Asia/Kolkata",
    "iso:country":"IN",
    "name:urd_x_preferred":[
        "\u0644\u06a9\u06be\u0646 \u067e\u0648\u0631\u06cc"
    ],
    "wof:name":"Lakhanpuri",
    "wof:placetype":"locality"
},
  "geometry": {"coordinates":[81.95302,20.23837],"type":"Point"}
}