{
  "type": "Feature",
  "properties": {
    "gn:admin1_code":"11",
    "gn:admin2_code":"24.0",
    "gn:asciiname":"Gadiara",
    "gn:country_code":"IN",
    "gn:dem":823,
    "gn:feature_class":"P",
    "gn:feature_code":"PPL",
    "gn:name":"Gadi\u0101ra",
    "gn:population":0,
    "gn:timezone":"Asia/Kolkata",
    "iso:country":"IN",
    "wof:name":"Gadiara",
    "wof:placetype":"locality"
},
  "geometry": {"coordinates":[76.47651,31.99354000000001],"type":"Point"}
}