{
  "type": "Feature",
  "properties": {
    "iso:country":"IN",
    "ks:ks_name":"Baroo",
    "ks:ks_pop":3782,
    "ks:ks_type":"VILLAGE",
    "name:eng_x_preferred":[
        "Baroo"
    ],
    "wof:name":"Baroo",
    "wof:placetype":"locality",
    "wof:population":3782
},
  "geometry": {"coordinates":[71.887142,27.362694],"type":"Point"}
}