{
  "type": "Feature",
  "properties": {
    "iso:country":"IN",
    "ks:ks_alt_nam":"Puthenpurackal padi",
    "ks:ks_name":"Puthenpurackal Padi",
    "ks:ks_pop":158,
    "ks:ks_type":"HABITATION",
    "name:eng_x_preferred":[
        "Puthenpurackal Padi"
    ],
    "wof:name":"Puthenpurackal Padi",
    "wof:placetype":"locality",
    "wof:population":158
},
  "geometry": {"coordinates":[76.71534699999999,9.23012],"type":"Point"}
}