{
  "type": "Feature",
  "properties": {
    "gn:admin1_code":"24.0",
    "gn:admin2_code":"102",
    "gn:asciiname":"Phogan",
    "gn:country_code":"IN",
    "gn:dem":241,
    "gn:feature_class":"P",
    "gn:feature_code":"PPL",
    "gn:name":"Phog\u0101n",
    "gn:population":0,
    "gn:timezone":"Asia/Kolkata",
    "iso:country":"IN",
    "name:und_x_variant":[
        "Phog\u0101n",
        "Phag\u0101n"
    ],
    "wof:name":"Phogan",
    "wof:placetype":"locality"
},
  "geometry": {"coordinates":[74.66046999999998,28.54128],"type":"Point"}
}