{
  "type": "Feature",
  "properties": {
    "iso:country":"IN",
    "ks:ks_name":"Rajulagaruvu",
    "ks:ks_pop":476,
    "ks:ks_type":"HABITATION",
    "name:eng_x_preferred":[
        "Rajulagaruvu"
    ],
    "wof:name":"Rajulagaruvu",
    "wof:placetype":"locality",
    "wof:population":476
},
  "geometry": {"coordinates":[81.571584,16.469692],"type":"Point"}
}