{
  "type": "Feature",
  "properties": {
    "gn:admin1_code":"39.0",
    "gn:admin2_code":"57.0",
    "gn:asciiname":"Hom Kundi",
    "gn:country_code":"IN",
    "gn:dem":4237,
    "gn:feature_class":"P",
    "gn:feature_code":"PPL",
    "gn:name":"Hom Kundi",
    "gn:population":0,
    "gn:timezone":"Asia/Kolkata",
    "iso:country":"IN",
    "wof:name":"Hom Kundi",
    "wof:placetype":"locality"
},
  "geometry": {"coordinates":[79.73968000000001,30.31366],"type":"Point"}
}