{
  "type": "Feature",
  "properties": {
    "iso:country":"IN",
    "ks:ks_name":"Lalpura",
    "ks:ks_pop":103,
    "ks:ks_type":"VILLAGE",
    "name:eng_x_preferred":[
        "Lalpura"
    ],
    "wof:name":"Lalpura",
    "wof:placetype":"locality",
    "wof:population":103
},
  "geometry": {"coordinates":[76.242358,25.75973],"type":"Point"}
}