{
  "type": "Feature",
  "properties": {
    "gn:admin1_code":"35.0",
    "gn:admin2_code":"418.0",
    "gn:asciiname":"Baldeopura",
    "gn:country_code":"IN",
    "gn:dem":182,
    "gn:feature_class":"P",
    "gn:feature_code":"PPL",
    "gn:name":"Baldeopura",
    "gn:population":0,
    "gn:timezone":"Asia/Kolkata",
    "iso:country":"IN",
    "wof:name":"Baldeopura",
    "wof:placetype":"locality"
},
  "geometry": {"coordinates":[76.95203000000002,26.09003],"type":"Point"}
}