{
  "type": "Feature",
  "properties": {
    "gn:admin1_code":"2.0",
    "gn:admin2_code":"545.0",
    "gn:asciiname":"Kondukuduru",
    "gn:country_code":"IN",
    "gn:dem":11,
    "gn:feature_class":"P",
    "gn:feature_code":"PPL",
    "gn:name":"Kondukuduru",
    "gn:population":0,
    "gn:timezone":"Asia/Kolkata",
    "iso:country":"IN",
    "wof:name":"Kondukuduru",
    "wof:placetype":"locality"
},
  "geometry": {"coordinates":[82.07637,16.66077],"type":"Point"}
}