{
  "type": "Feature",
  "properties": {
    "gn:admin1_code":"19.0",
    "gn:admin2_code":"581.0",
    "gn:asciiname":"Nayakanahalli",
    "gn:country_code":"IN",
    "gn:dem":817,
    "gn:feature_class":"P",
    "gn:feature_code":"PPL",
    "gn:name":"N\u0101yakanahalli",
    "gn:population":0,
    "gn:timezone":"Asia/Kolkata",
    "iso:country":"IN",
    "wof:name":"Nayakanahalli",
    "wof:placetype":"locality"
},
  "geometry": {"coordinates":[78.22589000000001,13.19973],"type":"Point"}
}