{
  "type": "Feature",
  "properties": {
    "iso:country":"IN",
    "ks:ks_alt_nam":"Arjun raja camp",
    "ks:ks_name":"Arjun Raja Camp",
    "ks:ks_pop":280,
    "ks:ks_type":"HABITATION",
    "name:eng_x_preferred":[
        "Arjun Raja Camp"
    ],
    "wof:name":"Arjun Raja Camp",
    "wof:placetype":"locality",
    "wof:population":280
},
  "geometry": {"coordinates":[76.790583,15.401752],"type":"Point"}
}