{
  "type": "Feature",
  "properties": {
    "iso:country":"IN",
    "ks:ks_name":"Timleth",
    "ks:ks_pop":25,
    "ks:ks_type":"HABITATION",
    "name:eng_x_preferred":[
        "Timleth"
    ],
    "wof:name":"Timleth",
    "wof:placetype":"locality",
    "wof:population":25
},
  "geometry": {"coordinates":[78.908084,30.101363],"type":"Point"}
}