{
  "type": "Feature",
  "properties": {
    "iso:country":"IN",
    "ks:ks_name":"Kanora",
    "ks:ks_pop":719,
    "ks:ks_type":"VILLAGE",
    "name:eng_x_preferred":[
        "Kanora"
    ],
    "wof:name":"Kanora",
    "wof:placetype":"locality",
    "wof:population":719
},
  "geometry": {"coordinates":[71.168391,25.898978],"type":"Point"}
}