{
  "type": "Feature",
  "properties": {
    "iso:country":"IN",
    "ks:ks_name":"Uchakot",
    "ks:ks_pop":137,
    "ks:ks_type":"VILLAGE",
    "name:eng_x_preferred":[
        "Uchakot"
    ],
    "wof:name":"Uchakot",
    "wof:placetype":"locality",
    "wof:population":137
},
  "geometry": {"coordinates":[78.450903,30.050453],"type":"Point"}
}