{
  "type": "Feature",
  "properties": {
    "gn:admin1_code":"37.0",
    "gn:admin2_code":"403.0",
    "gn:asciiname":"Newar",
    "gn:country_code":"IN",
    "gn:dem":224,
    "gn:feature_class":"P",
    "gn:feature_code":"PPL",
    "gn:name":"Newar",
    "gn:population":0,
    "gn:timezone":"Asia/Kolkata",
    "iso:country":"IN",
    "wof:name":"Newar",
    "wof:placetype":"neighbourhood"
},
  "geometry": {"coordinates":[83.39525,21.89567],"type":"Point"}
}