{
  "type": "Feature",
  "properties": {
    "iso:country":"IN",
    "ks:ks_name":"Nandapaju",
    "ks:ks_pop":93,
    "ks:ks_type":"HABITATION",
    "name:eng_x_preferred":[
        "Nandapaju"
    ],
    "wof:name":"Nandapaju",
    "wof:placetype":"locality",
    "wof:population":93
},
  "geometry": {"coordinates":[84.41613700000001,20.265385],"type":"Point"}
}