{
  "type": "Feature",
  "properties": {
    "iso:country":"IN",
    "ks:ks_name":"Uteipur",
    "ks:ks_pop":1813,
    "ks:ks_type":"VILLAGE",
    "name:eng_x_preferred":[
        "Uteipur"
    ],
    "wof:name":"Uteipur",
    "wof:placetype":"locality",
    "wof:population":1813
},
  "geometry": {"coordinates":[86.413023,20.859576],"type":"Point"}
}