{
  "type": "Feature",
  "properties": {
    "gn:admin1_code":"21",
    "gn:admin2_code":"394.0",
    "gn:asciiname":"Karangabhata",
    "gn:country_code":"IN",
    "gn:dem":330,
    "gn:feature_class":"P",
    "gn:feature_code":"PPL",
    "gn:name":"Karang\u0101bh\u0101ta",
    "gn:population":0,
    "gn:timezone":"Asia/Kolkata",
    "iso:country":"IN",
    "ks:ks_alt_nam":"Karang\u0101bh\u0101ta",
    "ks:ks_name":"Karangabhata",
    "ks:ks_pop":922,
    "ks:ks_type":"VILLAGE",
    "name:eng_x_preferred":[
        "Karangabhata"
    ],
    "name:eng_x_variant":[
        "Karang\u0101bh\u0101ta"
    ],
    "wof:name":"Karangabhata",
    "wof:placetype":"locality",
    "wof:population":922
},
  "geometry": {"coordinates":[82.578598,20.667709],"type":"Point"}
}