{
  "type": "Feature",
  "properties": {
    "gn:admin1_code":"39",
    "gn:admin2_code":"61.0",
    "gn:asciiname":"Andarson",
    "gn:country_code":"IN",
    "gn:dem":1565,
    "gn:feature_class":"P",
    "gn:feature_code":"PPL",
    "gn:name":"Andarson",
    "gn:population":0,
    "gn:timezone":"Asia/Kolkata",
    "iso:country":"IN",
    "wof:name":"Andarson",
    "wof:placetype":"locality"
},
  "geometry": {"coordinates":[78.84213000000003,29.80215],"type":"Point"}
}