{
  "type": "Feature",
  "properties": {
    "iso:country":"IN",
    "ks:ks_name":"Hetampur",
    "ks:ks_pop":1067,
    "ks:ks_type":"HABITATION",
    "ks:ks_uagg_main":0,
    "name:eng_x_preferred":[
        "Hetampur"
    ],
    "wof:name":"Hetampur",
    "wof:placetype":"neighbourhood",
    "wof:population":1067
},
  "geometry": {"coordinates":[84.58021100000001,25.670912],"type":"Point"}
}