{
  "type": "Feature",
  "properties": {
    "iso:country":"IN",
    "ks:ks_name":"Kudhwadih",
    "ks:ks_pop":1108,
    "ks:ks_type":"HABITATION",
    "name:eng_x_preferred":[
        "Kudhwadih"
    ],
    "wof:name":"Kudhwadih",
    "wof:placetype":"locality",
    "wof:population":1108
},
  "geometry": {"coordinates":[85.987966,24.905662],"type":"Point"}
}