{
  "type": "Feature",
  "properties": {
    "iso:country":"IN",
    "ks:ks_name":"Appachiwadi",
    "ks:ks_pop":132,
    "ks:ks_type":"HABITATION",
    "name:eng_x_preferred":[
        "Appachiwadi"
    ],
    "wof:name":"Appachiwadi",
    "wof:placetype":"locality",
    "wof:population":132
},
  "geometry": {"coordinates":[74.09138,16.348182],"type":"Point"}
}