{
  "type": "Feature",
  "properties": {
    "iso:country":"IN",
    "ks:ks_name":"Mota Vanta",
    "ks:ks_pop":1026,
    "ks:ks_type":"VILLAGE",
    "name:eng_x_preferred":[
        "Mota Vanta"
    ],
    "wof:name":"Mota Vanta",
    "wof:placetype":"locality",
    "wof:population":1026
},
  "geometry": {"coordinates":[73.940684,22.123661],"type":"Point"}
}