{
  "type": "Feature",
  "properties": {
    "iso:country":"IN",
    "ks:ks_name":"Bukdawada Khedi",
    "ks:ks_pop":638,
    "ks:ks_type":"VILLAGE",
    "ks:ks_uagg_main":0,
    "name:eng_x_preferred":[
        "Bukdawada Khedi"
    ],
    "wof:name":"Bukdawada Khedi",
    "wof:placetype":"neighbourhood",
    "wof:population":638
},
  "geometry": {"coordinates":[75.266732,22.944035],"type":"Point"}
}