{
  "type": "Feature",
  "properties": {
    "gn:admin1_code":"36.0",
    "gn:admin2_code":"189.0",
    "gn:asciiname":"Basdila",
    "gn:country_code":"IN",
    "gn:dem":88,
    "gn:feature_class":"P",
    "gn:feature_code":"PPL",
    "gn:name":"Basdila",
    "gn:population":0,
    "gn:timezone":"Asia/Kolkata",
    "iso:country":"IN",
    "ks:ks_name":"Basdila",
    "ks:ks_type":"VILLAGE",
    "name:eng_x_preferred":[
        "Basdila"
    ],
    "wof:name":"Basdila",
    "wof:placetype":"locality"
},
  "geometry": {"coordinates":[83.97095400000001,26.856934],"type":"Point"}
}