{
  "type": "Feature",
  "properties": {
    "iso:country":"IN",
    "ks:ks_name":"Kuldiha",
    "ks:ks_pop":465,
    "ks:ks_type":"VILLAGE",
    "name:eng_x_preferred":[
        "Kuldiha"
    ],
    "wof:name":"Kuldiha",
    "wof:placetype":"locality",
    "wof:population":465
},
  "geometry": {"coordinates":[87.553838,22.425187],"type":"Point"}
}