{
  "type": "Feature",
  "properties": {
    "iso:country":"IN",
    "ks:ks_name":"Siyolo Ki Dhani",
    "ks:ks_pop":331,
    "ks:ks_type":"HABITATION",
    "name:eng_x_preferred":[
        "Siyolo Ki Dhani"
    ],
    "wof:name":"Siyolo Ki Dhani",
    "wof:placetype":"locality",
    "wof:population":331
},
  "geometry": {"coordinates":[71.911017,26.297956],"type":"Point"}
}