{
  "type": "Feature",
  "properties": {
    "gn:admin1_code":"28.0",
    "gn:admin2_code":"327.0",
    "gn:asciiname":"Sangse",
    "gn:country_code":"IN",
    "gn:dem":871,
    "gn:feature_class":"P",
    "gn:feature_code":"PPL",
    "gn:name":"Sangse",
    "gn:population":0,
    "gn:timezone":"Asia/Kolkata",
    "iso:country":"IN",
    "name:und_x_variant":[
        "Sangs\u0101r"
    ],
    "wof:name":"Sangse",
    "wof:placetype":"locality"
},
  "geometry": {"coordinates":[88.49119,27.10745],"type":"Point"}
}