{
  "type": "Feature",
  "properties": {
    "iso:country":"IN",
    "ks:ks_name":"Madoda",
    "ks:ks_pop":287,
    "ks:ks_type":"HABITATION",
    "name:eng_x_preferred":[
        "Madoda"
    ],
    "wof:name":"Madoda",
    "wof:placetype":"locality",
    "wof:population":287
},
  "geometry": {"coordinates":[81.48493999999999,19.368433],"type":"Point"}
}