{
  "type": "Feature",
  "properties": {
    "gn:admin1_code":"36",
    "gn:admin2_code":"154.0",
    "gn:asciiname":"Anbhia Purwa",
    "gn:country_code":"IN",
    "gn:dem":143,
    "gn:feature_class":"P",
    "gn:feature_code":"PPL",
    "gn:name":"Anbhia Purwa",
    "gn:population":0,
    "gn:timezone":"Asia/Kolkata",
    "iso:country":"IN",
    "wof:name":"Anbhia Purwa",
    "wof:placetype":"locality"
},
  "geometry": {"coordinates":[80.80315999999998,27.68463],"type":"Point"}
}