{
  "type": "Feature",
  "properties": {
    "iso:country":"IN",
    "ks:ks_name":"Kusunpur",
    "ks:ks_pop":685,
    "ks:ks_type":"VILLAGE",
    "ks:ks_uagg_main":0,
    "name:eng_x_preferred":[
        "Kusunpur"
    ],
    "wof:name":"Kusunpur",
    "wof:placetype":"neighbourhood",
    "wof:population":685
},
  "geometry": {"coordinates":[86.28283500000001,20.579937],"type":"Point"}
}