{
  "type": "Feature",
  "properties": {
    "iso:country":"IN",
    "ks:ks_name":"Panchayat Boundary",
    "ks:ks_pop":1526,
    "ks:ks_type":"HABITATION",
    "name:eng_x_preferred":[
        "Panchayat Boundary"
    ],
    "wof:name":"Panchayat Boundary",
    "wof:placetype":"locality",
    "wof:population":1526
},
  "geometry": {"coordinates":[75.871833,11.098818],"type":"Point"}
}