{
  "type": "Feature",
  "properties": {
    "gn:admin1_code":"19.0",
    "gn:admin2_code":"583.0",
    "gn:asciiname":"Bullahalli",
    "gn:country_code":"IN",
    "gn:dem":911,
    "gn:feature_class":"P",
    "gn:feature_code":"PPL",
    "gn:name":"Bullahalli",
    "gn:population":0,
    "gn:timezone":"Asia/Kolkata",
    "iso:country":"IN",
    "wof:name":"Bullahalli",
    "wof:placetype":"locality"
},
  "geometry": {"coordinates":[77.73121,13.30716],"type":"Point"}
}