{
  "type": "Feature",
  "properties": {
    "iso:country":"IN",
    "ks:ks_name":"Andola",
    "ks:ks_pop":1121,
    "ks:ks_type":"VILLAGE",
    "name:eng_x_preferred":[
        "Andola"
    ],
    "wof:name":"Andola",
    "wof:placetype":"locality",
    "wof:population":1121
},
  "geometry": {"coordinates":[86.803563,20.985813],"type":"Point"}
}