{
  "type": "Feature",
  "properties": {
    "iso:country":"IN",
    "ks:ks_name":"Koluru Nanjundapura",
    "ks:ks_pop":9,
    "ks:ks_type":"HABITATION",
    "name:eng_x_preferred":[
        "Koluru Nanjundapura"
    ],
    "wof:name":"Koluru Nanjundapura",
    "wof:placetype":"locality",
    "wof:population":9
},
  "geometry": {"coordinates":[77.398753,12.890275],"type":"Point"}
}