{
  "type": "Feature",
  "properties": {
    "iso:country":"IN",
    "ks:ks_name":"Baraektal",
    "ks:ks_pop":571,
    "ks:ks_type":"VILLAGE",
    "ks:ks_uagg_main":0,
    "name:eng_x_preferred":[
        "Baraektal"
    ],
    "wof:name":"Baraektal",
    "wof:placetype":"neighbourhood",
    "wof:population":571
},
  "geometry": {"coordinates":[86.947001,22.317145],"type":"Point"}
}