{
  "type": "Feature",
  "properties": {
    "iso:country":"IN",
    "ks:ks_name":"Ramji Tola",
    "ks:ks_pop":333,
    "ks:ks_type":"HABITATION",
    "name:eng_x_preferred":[
        "Ramji Tola"
    ],
    "wof:name":"Ramji Tola",
    "wof:placetype":"locality",
    "wof:population":333
},
  "geometry": {"coordinates":[86.40812200000001,25.984355],"type":"Point"}
}