{
  "type": "Feature",
  "properties": {
    "gn:admin1_code":"19.0",
    "gn:admin2_code":"568.0",
    "gn:asciiname":"Mattiga",
    "gn:country_code":"IN",
    "gn:dem":622,
    "gn:feature_class":"P",
    "gn:feature_code":"PPL",
    "gn:name":"Mattiga",
    "gn:population":0,
    "gn:timezone":"Asia/Kolkata",
    "iso:country":"IN",
    "ks:ks_name":"Mathiga",
    "ks:ks_pop":47,
    "ks:ks_type":"HABITATION",
    "name:eng_x_preferred":[
        "Mathiga"
    ],
    "name:eng_x_variant":[
        "Mattiga"
    ],
    "wof:name":"Mathiga",
    "wof:placetype":"locality",
    "wof:population":47
},
  "geometry": {"coordinates":[75.134319,13.836334],"type":"Point"}
}