{
  "type": "Feature",
  "properties": {
    "iso:country":"IN",
    "ks:ks_name":"Pura Bhajanlal",
    "ks:ks_pop":150,
    "ks:ks_type":"HABITATION",
    "name:eng_x_preferred":[
        "Pura Bhajanlal"
    ],
    "wof:name":"Pura Bhajanlal",
    "wof:placetype":"locality",
    "wof:population":150
},
  "geometry": {"coordinates":[78.060756,26.969859],"type":"Point"}
}