{
  "type": "Feature",
  "properties": {
    "iso:country":"IN",
    "ks:ks_name":"Buradagummi",
    "ks:ks_pop":84,
    "ks:ks_type":"HABITATION",
    "name:eng_x_preferred":[
        "Buradagummi"
    ],
    "wof:name":"Buradagummi",
    "wof:placetype":"locality",
    "wof:population":84
},
  "geometry": {"coordinates":[82.819823,18.13069],"type":"Point"}
}