{
  "type": "Feature",
  "properties": {
    "gn:admin1_code":"11",
    "gn:admin2_code":"31.0",
    "gn:asciiname":"Bagetu",
    "gn:country_code":"IN",
    "gn:dem":1513,
    "gn:feature_class":"P",
    "gn:feature_code":"PPL",
    "gn:name":"Bagetu",
    "gn:population":0,
    "gn:timezone":"Asia/Kolkata",
    "iso:country":"IN",
    "wof:name":"Bagetu",
    "wof:placetype":"locality"
},
  "geometry": {"coordinates":[77.13239,31.00628],"type":"Point"}
}