{
  "type": "Feature",
  "properties": {
    "iso:country":"IN",
    "ks:ks_name":"Vitthalwadi",
    "ks:ks_pop":100,
    "ks:ks_type":"HABITATION",
    "name:eng_x_preferred":[
        "Vitthalwadi"
    ],
    "wof:name":"Vitthalwadi",
    "wof:placetype":"locality",
    "wof:population":100
},
  "geometry": {"coordinates":[75.868494,19.964981],"type":"Point"}
}