{
  "type": "Feature",
  "properties": {
    "iso:country":"IN",
    "ks:ks_name":"Chekkadi",
    "ks:ks_pop":319,
    "ks:ks_type":"HABITATION",
    "ks:ks_uagg_main":0,
    "name:eng_x_preferred":[
        "Chekkadi"
    ],
    "wof:name":"Chekkadi",
    "wof:placetype":"neighbourhood",
    "wof:population":319
},
  "geometry": {"coordinates":[77.421032,8.314787],"type":"Point"}
}