{
  "type": "Feature",
  "properties": {
    "iso:country":"IN",
    "ks:ks_name":"Arasahi",
    "ks:ks_pop":237,
    "ks:ks_type":"VILLAGE",
    "ks:ks_uagg_main":0,
    "name:eng_x_preferred":[
        "Arasahi"
    ],
    "wof:name":"Arasahi",
    "wof:placetype":"neighbourhood",
    "wof:population":237
},
  "geometry": {"coordinates":[85.664945,20.901921],"type":"Point"}
}