{
  "type": "Feature",
  "properties": {
    "iso:country":"IN",
    "ks:ks_name":"Bhaliapada",
    "ks:ks_pop":48,
    "ks:ks_type":"VILLAGE",
    "name:eng_x_preferred":[
        "Bhaliapada"
    ],
    "wof:name":"Bhaliapada",
    "wof:placetype":"locality",
    "wof:population":48
},
  "geometry": {"coordinates":[85.02557400000001,19.752182],"type":"Point"}
}