{
  "type": "Feature",
  "properties": {
    "gn:admin1_code":"13.0",
    "gn:admin2_code":"594.0",
    "gn:asciiname":"Velur",
    "gn:country_code":"IN",
    "gn:dem":28,
    "gn:feature_class":"P",
    "gn:feature_code":"PPL",
    "gn:name":"Vel\u016br",
    "gn:population":0,
    "gn:timezone":"Asia/Kolkata",
    "iso:country":"IN",
    "ks:ks_alt_nam":"Vel\u016br",
    "ks:ks_name":"Velur",
    "ks:ks_pop":12121,
    "ks:ks_type":"VILLAGE",
    "ks:ks_uagg_main":0,
    "name:deu_x_preferred":[
        "Velur"
    ],
    "name:eng_x_preferred":[
        "Velur"
    ],
    "name:eng_x_variant":[
        "Vel\u016br"
    ],
    "wof:name":"Velur",
    "wof:placetype":"locality",
    "wof:population":12121
},
  "geometry": {"coordinates":[76.171015,10.640759],"type":"Point"}
}