{
  "type": "Feature",
  "properties": {
    "iso:country":"IN",
    "ks:ks_name":"Harina Pokhari",
    "ks:ks_pop":334,
    "ks:ks_type":"VILLAGE",
    "name:eng_x_preferred":[
        "Harina Pokhari"
    ],
    "wof:name":"Harina Pokhari",
    "wof:placetype":"locality",
    "wof:population":334
},
  "geometry": {"coordinates":[86.93085000000001,20.729837],"type":"Point"}
}