{
  "type": "Feature",
  "properties": {
    "iso:country":"IN",
    "ks:ks_name":"Devenpur",
    "ks:ks_pop":757,
    "ks:ks_type":"VILLAGE",
    "ks:ks_uagg_main":0,
    "name:eng_x_preferred":[
        "Devenpur"
    ],
    "wof:name":"Devenpur",
    "wof:placetype":"neighbourhood",
    "wof:population":757
},
  "geometry": {"coordinates":[83.10079,26.234558],"type":"Point"}
}