{
  "type": "Feature",
  "properties": {
    "iso:country":"IN",
    "ks:ks_alt_nam":"BHADIA",
    "ks:ks_name":"Bhadia",
    "ks:ks_pop":90,
    "ks:ks_type":"HABITATION",
    "name:eng_x_preferred":[
        "Bhadia"
    ],
    "wof:name":"Bhadia",
    "wof:placetype":"locality",
    "wof:population":90
},
  "geometry": {"coordinates":[80.76926400000001,26.393021],"type":"Point"}
}