{
  "type": "Feature",
  "properties": {
    "iso:country":"IN",
    "ks:ks_alt_nam":"MALLAUTI 1",
    "ks:ks_name":"Mallauti 1",
    "ks:ks_pop":18,
    "ks:ks_type":"HABITATION",
    "ks:ks_uagg_main":0,
    "name:eng_x_preferred":[
        "Mallauti 1"
    ],
    "wof:name":"Mallauti 1",
    "wof:placetype":"neighbourhood",
    "wof:population":18
},
  "geometry": {"coordinates":[82.155742,26.244906],"type":"Point"}
}