{
  "type": "Feature",
  "properties": {
    "gn:admin1_code":"37.0",
    "gn:admin2_code":"407.0",
    "gn:asciiname":"Bendarchi",
    "gn:country_code":"IN",
    "gn:dem":367,
    "gn:feature_class":"P",
    "gn:feature_code":"PPL",
    "gn:name":"Bendarchi",
    "gn:population":0,
    "gn:timezone":"Asia/Kolkata",
    "iso:country":"IN",
    "wof:name":"Bendarchi",
    "wof:placetype":"locality"
},
  "geometry": {"coordinates":[81.18302,22.02151],"type":"Point"}
}