{
  "type": "Feature",
  "properties": {
    "gn:admin1_code":"21.0",
    "gn:admin2_code":"390.0",
    "gn:asciiname":"Simanbadi",
    "gn:country_code":"IN",
    "gn:dem":673,
    "gn:feature_class":"P",
    "gn:feature_code":"PPL",
    "gn:name":"Simanbadi",
    "gn:population":0,
    "gn:timezone":"Asia/Kolkata",
    "iso:country":"IN",
    "ks:ks_name":"Samanabadi",
    "ks:ks_pop":268,
    "ks:ks_type":"VILLAGE",
    "name:eng_x_preferred":[
        "Samanabadi"
    ],
    "name:eng_x_variant":[
        "Simanbadi"
    ],
    "wof:name":"Samanabadi",
    "wof:placetype":"locality",
    "wof:population":268
},
  "geometry": {"coordinates":[83.961033,19.994642],"type":"Point"}
}