{
  "type": "Feature",
  "properties": {
    "gn:admin1_code":"21.0",
    "gn:admin2_code":"390.0",
    "gn:asciiname":"Simanbadi",
    "gn:country_code":"IN",
    "gn:dem":673,
    "gn:feature_class":"P",
    "gn:feature_code":"PPL",
    "gn:name":"Simanbadi",
    "gn:population":0,
    "gn:timezone":"Asia/Kolkata",
    "iso:country":"IN",
    "wof:name":"Simanbadi",
    "wof:placetype":"locality"
},
  "geometry": {"coordinates":[83.96134000000001,19.99497],"type":"Point"}
}