{
  "type": "Feature",
  "properties": {
    "gn:admin1_code":"38.0",
    "gn:admin2_code":"347.0",
    "gn:asciiname":"Sidki",
    "gn:country_code":"IN",
    "gn:dem":402,
    "gn:feature_class":"P",
    "gn:feature_code":"PPL",
    "gn:name":"Sidk\u012b",
    "gn:population":0,
    "gn:timezone":"Asia/Kolkata",
    "iso:country":"IN",
    "ks:ks_alt_nam":"Sidk\u012b",
    "ks:ks_name":"Sidki",
    "ks:ks_pop":9,
    "ks:ks_type":"VILLAGE",
    "name:eng_x_preferred":[
        "Sidki"
    ],
    "name:eng_x_variant":[
        "Sidk\u012b"
    ],
    "wof:name":"Sidki",
    "wof:placetype":"locality",
    "wof:population":9
},
  "geometry": {"coordinates":[84.675939,24.18048],"type":"Point"}
}