{
  "type": "Feature",
  "properties": {
    "gn:admin1_code":"34.0",
    "gn:admin2_code":"229.0",
    "gn:asciiname":"Aladia Sarai",
    "gn:country_code":"IN",
    "gn:dem":57,
    "gn:feature_class":"P",
    "gn:feature_code":"PPL",
    "gn:name":"Aladia Sarai",
    "gn:population":0,
    "gn:timezone":"Asia/Kolkata",
    "iso:country":"IN",
    "ks:ks_name":"Alahdia Sarai",
    "ks:ks_pop":1426,
    "ks:ks_type":"VILLAGE",
    "ks:ks_uagg_main":0,
    "name:eng_x_preferred":[
        "Alahdia Sarai"
    ],
    "wof:name":"Alahdia Sarai",
    "wof:placetype":"neighbourhood",
    "wof:population":1426
},
  "geometry": {"coordinates":[85.55927699999999,25.181932],"type":"Point"}
}