{
  "type": "Feature",
  "properties": {
    "iso:country":"IN",
    "ks:ks_name":"Sirikijhola",
    "ks:ks_pop":46,
    "ks:ks_type":"VILLAGE",
    "name:eng_x_preferred":[
        "Sirikijhola"
    ],
    "wof:name":"Sirikijhola",
    "wof:placetype":"locality",
    "wof:population":46
},
  "geometry": {"coordinates":[83.286843,19.680106],"type":"Point"}
}