{
  "type": "Feature",
  "properties": {
    "iso:country":"IN",
    "ks:ks_name":"Kalakkanmoi",
    "ks:ks_pop":122,
    "ks:ks_type":"HABITATION",
    "ks:ks_uagg_main":0,
    "name:eng_x_preferred":[
        "Kalakkanmoi"
    ],
    "wof:name":"Kalakkanmoi",
    "wof:placetype":"neighbourhood",
    "wof:population":122
},
  "geometry": {"coordinates":[78.64902600000001,9.891505],"type":"Point"}
}