{
  "type": "Feature",
  "properties": {
    "iso:country":"IN",
    "ks:ks_name":"Bagoli",
    "ks:ks_pop":35,
    "ks:ks_type":"HABITATION",
    "name:eng_x_preferred":[
        "Bagoli"
    ],
    "wof:name":"Bagoli",
    "wof:placetype":"locality",
    "wof:population":35
},
  "geometry": {"coordinates":[78.804147,30.163407],"type":"Point"}
}