{
  "type": "Feature",
  "properties": {
    "gn:admin1_code":"34",
    "gn:admin2_code":"232.0",
    "gn:asciiname":"Narbatpur",
    "gn:country_code":"IN",
    "gn:dem":74,
    "gn:feature_class":"P",
    "gn:feature_code":"PPL",
    "gn:name":"Narbatpur",
    "gn:population":0,
    "gn:timezone":"Asia/Kolkata",
    "iso:country":"IN",
    "ks:ks_name":"Narbatpur",
    "ks:ks_pop":3441,
    "ks:ks_type":"VILLAGE",
    "ks:ks_uagg_main":0,
    "name:eng_x_preferred":[
        "Narbatpur"
    ],
    "wof:name":"Narbatpur",
    "wof:placetype":"neighbourhood",
    "wof:population":3441
},
  "geometry": {"coordinates":[83.88673,25.510464],"type":"Point"}
}