{
  "type": "Feature",
  "properties": {
    "gn:admin1_code":"36",
    "gn:admin2_code":"192.0",
    "gn:asciiname":"Bhanti Khurd",
    "gn:country_code":"IN",
    "gn:dem":77,
    "gn:feature_class":"P",
    "gn:feature_code":"PPL",
    "gn:name":"Bh\u0101nti Khurd",
    "gn:population":0,
    "gn:timezone":"Asia/Kolkata",
    "iso:country":"IN",
    "ks:ks_alt_nam":"Bh\u0101nti Khurd",
    "ks:ks_name":"Bhanti Khurd",
    "ks:ks_type":"VILLAGE",
    "name:eng_x_preferred":[
        "Bhanti Khurd"
    ],
    "name:eng_x_variant":[
        "Bh\u0101nti Khurd"
    ],
    "wof:name":"Bhanti Khurd",
    "wof:placetype":"locality"
},
  "geometry": {"coordinates":[83.388634,25.980781],"type":"Point"}
}