{
  "type": "Feature",
  "properties": {
    "iso:country":"IN",
    "ks:ks_name":"Jhariapani",
    "ks:ks_pop":218,
    "ks:ks_type":"VILLAGE",
    "name:eng_x_preferred":[
        "Jhariapani"
    ],
    "wof:name":"Jhariapani",
    "wof:placetype":"locality",
    "wof:population":218
},
  "geometry": {"coordinates":[87.467285,24.436176],"type":"Point"}
}