{
  "type": "Feature",
  "properties": {
    "gn:admin1_code":"36.0",
    "gn:admin2_code":"190.0",
    "gn:asciiname":"Chaudhar",
    "gn:country_code":"IN",
    "gn:dem":72,
    "gn:feature_class":"P",
    "gn:feature_code":"PPL",
    "gn:name":"Chaudhar",
    "gn:population":0,
    "gn:timezone":"Asia/Kolkata",
    "iso:country":"IN",
    "name:und_x_variant":[
        "Chh\u0101pra"
    ],
    "wof:name":"Chaudhar",
    "wof:placetype":"locality"
},
  "geometry": {"coordinates":[84.04888000000003,26.24062],"type":"Point"}
}