{
  "type": "Feature",
  "properties": {
    "iso:country":"IN",
    "ks:ks_name":"Ramannapalem",
    "ks:ks_pop":48,
    "ks:ks_type":"HABITATION",
    "name:eng_x_preferred":[
        "Ramannapalem"
    ],
    "wof:name":"Ramannapalem",
    "wof:placetype":"locality",
    "wof:population":48
},
  "geometry": {"coordinates":[83.15697400000001,18.164457],"type":"Point"}
}