{
  "type": "Feature",
  "properties": {
    "gn:admin1_code":"10",
    "gn:admin2_code":"81.0",
    "gn:asciiname":"Jhanjra Nayawas",
    "gn:country_code":"IN",
    "gn:dem":262,
    "gn:feature_class":"P",
    "gn:feature_code":"PPL",
    "gn:name":"Jh\u0101njra Nay\u0101w\u0101s",
    "gn:population":0,
    "gn:timezone":"Asia/Kolkata",
    "iso:country":"IN",
    "wof:name":"Jhanjra Nayawas",
    "wof:placetype":"locality"
},
  "geometry": {"coordinates":[75.77099,28.50268],"type":"Point"}
}