{
  "type": "Feature",
  "properties": {
    "gn:admin1_code":"36.0",
    "gn:admin2_code":"139.0",
    "gn:asciiname":"Ibrahimabad Gaonri",
    "gn:country_code":"IN",
    "gn:dem":228,
    "gn:feature_class":"P",
    "gn:feature_code":"PPL",
    "gn:name":"Ibr\u0101him\u0101b\u0101d Gaonri",
    "gn:population":0,
    "gn:timezone":"Asia/Kolkata",
    "iso:country":"IN",
    "wof:name":"Ibrahimabad Gaonri",
    "wof:placetype":"locality"
},
  "geometry": {"coordinates":[77.39718000000001,29.04102],"type":"Point"}
}