{
  "type": "Feature",
  "properties": {
    "iso:country":"IN",
    "ks:ks_name":"Zulam",
    "ks:ks_pop":3105,
    "ks:ks_type":"HABITATION",
    "name:eng_x_preferred":[
        "Zulam"
    ],
    "wof:name":"Zulam",
    "wof:placetype":"locality",
    "wof:population":3105
},
  "geometry": {"coordinates":[76.53746,9.949873],"type":"Point"}
}