{
  "type": "Feature",
  "properties": {
    "iso:country":"IN",
    "ks:ks_name":"Syal Dhuri",
    "ks:ks_pop":77,
    "ks:ks_type":"VILLAGE",
    "name:eng_x_preferred":[
        "Syal Dhuri"
    ],
    "wof:name":"Syal Dhuri",
    "wof:placetype":"locality",
    "wof:population":77
},
  "geometry": {"coordinates":[78.884884,30.401797],"type":"Point"}
}