{
  "type": "Feature",
  "properties": {
    "gn:admin1_code":"19",
    "gn:admin2_code":"579.0",
    "gn:asciiname":"Bidnur",
    "gn:country_code":"IN",
    "gn:dem":415,
    "gn:feature_class":"P",
    "gn:feature_code":"PPL",
    "gn:name":"Bidn\u016br",
    "gn:population":0,
    "gn:timezone":"Asia/Kolkata",
    "iso:country":"IN",
    "wof:name":"Bidnur",
    "wof:placetype":"locality"
},
  "geometry": {"coordinates":[76.66769000000002,17.21015],"type":"Point"}
}