{
  "type": "Feature",
  "properties": {
    "gn:admin1_code":"19.0",
    "gn:admin2_code":"581.0",
    "gn:asciiname":"Virapura",
    "gn:country_code":"IN",
    "gn:dem":831,
    "gn:feature_class":"P",
    "gn:feature_code":"PPL",
    "gn:name":"V\u012br\u0101pura",
    "gn:population":0,
    "gn:timezone":"Asia/Kolkata",
    "iso:country":"IN",
    "wof:name":"Virapura",
    "wof:placetype":"locality"
},
  "geometry": {"coordinates":[78.15040999999999,13.18847],"type":"Point"}
}