{
  "type": "Feature",
  "properties": {
    "iso:country":"IN",
    "ks:ks_name":"Paraipatty",
    "ks:ks_pop":686,
    "ks:ks_type":"HABITATION",
    "name:eng_x_preferred":[
        "Paraipatty"
    ],
    "wof:name":"Paraipatty",
    "wof:placetype":"locality",
    "wof:population":686
},
  "geometry": {"coordinates":[77.502757,10.528601],"type":"Point"}
}