{
  "type": "Feature",
  "properties": {
    "iso:country":"IN",
    "ks:ks_name":"Salana",
    "ks:ks_pop":171,
    "ks:ks_type":"VILLAGE",
    "name:eng_x_preferred":[
        "Salana"
    ],
    "wof:name":"Salana",
    "wof:placetype":"locality",
    "wof:population":171
},
  "geometry": {"coordinates":[78.97739199999999,29.74538],"type":"Point"}
}