{
  "type": "Feature",
  "properties": {
    "iso:country":"IN",
    "ks:ks_name":"Goal Khar",
    "ks:ks_pop":219,
    "ks:ks_type":"VILLAGE",
    "name:eng_x_preferred":[
        "Goal Khar"
    ],
    "wof:name":"Goal Khar",
    "wof:placetype":"locality",
    "wof:population":219
},
  "geometry": {"coordinates":[84.058877,23.377643],"type":"Point"}
}