{
  "type": "Feature",
  "properties": {
    "iso:country":"IN",
    "ks:ks_name":"Minsi R",
    "ks:ks_pop":126,
    "ks:ks_type":"HABITATION",
    "name:eng_x_preferred":[
        "Minsi R"
    ],
    "wof:name":"Minsi R",
    "wof:placetype":"locality",
    "wof:population":126
},
  "geometry": {"coordinates":[79.38330000000001,21.352224],"type":"Point"}
}