{
  "type": "Feature",
  "properties": {
    "iso:country":"IN",
    "ks:ks_name":"Jamadapal",
    "ks:ks_pop":326,
    "ks:ks_type":"VILLAGE",
    "name:eng_x_preferred":[
        "Jamadapal"
    ],
    "wof:name":"Jamadapal",
    "wof:placetype":"locality",
    "wof:population":326
},
  "geometry": {"coordinates":[86.558055,22.138429],"type":"Point"}
}