{
  "type": "Feature",
  "properties": {
    "iso:country":"IN",
    "ks:ks_alt_nam":"Murwari mal",
    "ks:ks_name":"Murwari Mal",
    "ks:ks_pop":215,
    "ks:ks_type":"HABITATION",
    "name:eng_x_preferred":[
        "Murwari Mal"
    ],
    "wof:name":"Murwari Mal",
    "wof:placetype":"locality",
    "wof:population":215
},
  "geometry": {"coordinates":[79.66294499999999,22.262087],"type":"Point"}
}