{
  "type": "Feature",
  "properties": {
    "gn:admin1_code":"25.0",
    "gn:admin2_code":"631.0",
    "gn:asciiname":"Avalnayakkampatti",
    "gn:country_code":"IN",
    "gn:dem":388,
    "gn:feature_class":"P",
    "gn:feature_code":"PPL",
    "gn:name":"Avaln\u0101yakkampatti",
    "gn:population":0,
    "gn:timezone":"Asia/Kolkata",
    "iso:country":"IN",
    "wof:name":"Avalnayakkampatti",
    "wof:placetype":"locality"
},
  "geometry": {"coordinates":[78.48368000000001,12.31002],"type":"Point"}
}