{
  "type": "Feature",
  "properties": {
    "iso:country":"IN",
    "ks:ks_name":"Mehtar Tola",
    "ks:ks_pop":134,
    "ks:ks_type":"HABITATION",
    "name:eng_x_preferred":[
        "Mehtar Tola"
    ],
    "wof:name":"Mehtar Tola",
    "wof:placetype":"locality",
    "wof:population":134
},
  "geometry": {"coordinates":[79.851522,26.680369],"type":"Point"}
}