{
  "type": "Feature",
  "properties": {
    "iso:country":"IN",
    "ks:ks_name":"Hathbandha",
    "ks:ks_pop":382,
    "ks:ks_type":"VILLAGE",
    "name:eng_x_preferred":[
        "Hathbandha"
    ],
    "wof:name":"Hathbandha",
    "wof:placetype":"locality",
    "wof:population":382
},
  "geometry": {"coordinates":[81.35083899999999,23.022675],"type":"Point"}
}