{
  "type": "Feature",
  "properties": {
    "gn:admin1_code":"25.0",
    "gn:admin2_code":"631.0",
    "gn:asciiname":"Torapalli",
    "gn:country_code":"IN",
    "gn:dem":814,
    "gn:feature_class":"P",
    "gn:feature_code":"PPL",
    "gn:name":"Torapalli",
    "gn:population":0,
    "gn:timezone":"Asia/Kolkata",
    "iso:country":"IN",
    "wof:name":"Torapalli",
    "wof:placetype":"locality"
},
  "geometry": {"coordinates":[77.88046999999997,12.68636],"type":"Point"}
}