{
  "type": "Feature",
  "properties": {
    "gn:admin1_code":"12.0",
    "gn:admin2_code":"13.0",
    "gn:asciiname":"Bijbrari",
    "gn:country_code":"IN",
    "gn:dem":2444,
    "gn:feature_class":"P",
    "gn:feature_code":"PPL",
    "gn:name":"Bijbrari",
    "gn:population":0,
    "gn:timezone":"Asia/Kolkata",
    "iso:country":"IN",
    "wof:name":"Bijbrari",
    "wof:placetype":"locality"
},
  "geometry": {"coordinates":[74.69818000000002,33.73524],"type":"Point"}
}