{
  "type": "Feature",
  "properties": {
    "gn:admin1_code":"13.0",
    "gn:admin2_code":"595.0",
    "gn:asciiname":"Edayar",
    "gn:country_code":"IN",
    "gn:dem":18,
    "gn:feature_class":"P",
    "gn:feature_code":"PPL",
    "gn:name":"Edayar",
    "gn:population":0,
    "gn:timezone":"Asia/Kolkata",
    "iso:country":"IN",
    "name:mal_x_preferred":[
        "\u0d0e\u0d1f\u0d2f\u0d3e\u0d7c"
    ],
    "wof:name":"Edayar",
    "wof:placetype":"locality"
},
  "geometry": {"coordinates":[76.55055,9.87216],"type":"Point"}
}