{
  "type": "Feature",
  "properties": {
    "iso:country":"IN",
    "ks:ks_name":"Gopinathpur",
    "ks:ks_pop":26,
    "ks:ks_type":"VILLAGE",
    "name:eng_x_preferred":[
        "Gopinathpur"
    ],
    "wof:name":"Gopinathpur",
    "wof:placetype":"locality",
    "wof:population":26
},
  "geometry": {"coordinates":[84.695142,19.891672],"type":"Point"}
}