{
  "type": "Feature",
  "properties": {
    "gn:admin1_code":"37",
    "gn:admin2_code":"413.0",
    "gn:asciiname":"Barkai",
    "gn:country_code":"IN",
    "gn:dem":410,
    "gn:feature_class":"P",
    "gn:feature_code":"PPL",
    "gn:name":"Barkai",
    "gn:population":0,
    "gn:timezone":"Asia/Kolkata",
    "iso:country":"IN",
    "name:ces_x_preferred":[
        "Barkaj"
    ],
    "name:heb_x_preferred":[
        "\u05d1\u05e8\u05e7\u05d0\u05d9"
    ],
    "name:nno_x_preferred":[
        "Barkai"
    ],
    "name:pol_x_preferred":[
        "Barkaj"
    ],
    "wof:name":"Barkai",
    "wof:placetype":"locality"
},
  "geometry": {"coordinates":[81.71294,20.29479],"type":"Point"}
}