{
  "type": "Feature",
  "properties": {
    "iso:country":"IN",
    "ks:ks_alt_nam":"Pipal bawdi",
    "ks:ks_name":"Pipal Bawdi",
    "ks:ks_pop":490,
    "ks:ks_type":"HABITATION",
    "name:eng_x_preferred":[
        "Pipal Bawdi"
    ],
    "wof:name":"Pipal Bawdi",
    "wof:placetype":"locality",
    "wof:population":490
},
  "geometry": {"coordinates":[77.293491,25.925584],"type":"Point"}
}