{
  "type": "Feature",
  "properties": {
    "iso:country":"IN",
    "ks:ks_name":"Harishpur Madhya",
    "ks:ks_pop":758,
    "ks:ks_type":"HABITATION",
    "name:eng_x_preferred":[
        "Harishpur Madhya"
    ],
    "wof:name":"Harishpur Madhya",
    "wof:placetype":"locality",
    "wof:population":758
},
  "geometry": {"coordinates":[88.882693,22.78883],"type":"Point"}
}