{
  "type": "Feature",
  "properties": {
    "iso:country":"IN",
    "ks:ks_name":"Vidhishyama",
    "ks:ks_pop":494,
    "ks:ks_type":"VILLAGE",
    "ks:ks_uagg_main":0,
    "name:eng_x_preferred":[
        "Vidhishyama"
    ],
    "wof:name":"Vidhishyama",
    "wof:placetype":"neighbourhood",
    "wof:population":494
},
  "geometry": {"coordinates":[80.729727,27.020208],"type":"Point"}
}