{
  "type": "Feature",
  "properties": {
    "gn:admin1_code":"38.0",
    "gn:admin2_code":"364",
    "gn:asciiname":"Getalsud",
    "gn:country_code":"IN",
    "gn:dem":599,
    "gn:feature_class":"P",
    "gn:feature_code":"PPL",
    "gn:name":"Getalsud",
    "gn:population":0,
    "gn:timezone":"Asia/Kolkata",
    "iso:country":"IN",
    "wof:name":"Getalsud",
    "wof:placetype":"locality"
},
  "geometry": {"coordinates":[85.54568,23.44548],"type":"Point"}
}