{
  "type": "Feature",
  "properties": {
    "gn:admin1_code":"11.0",
    "gn:admin2_code":"024",
    "gn:asciiname":"Nagrota Bagwan",
    "gn:country_code":"IN",
    "gn:dem":861,
    "gn:feature_class":"P",
    "gn:feature_code":"PPL",
    "gn:name":"Nagrota Bagw\u0101n",
    "gn:population":0,
    "gn:timezone":"Asia/Kolkata",
    "iso:country":"IN",
    "name:und_x_variant":[
        "Nagrota Kh\u0101s",
        "Nagrota",
        "Kh\u0101s Nagrota",
        "Nagrota Bagw\u0101n"
    ],
    "wof:name":"Nagrota Bagwan",
    "wof:placetype":"locality"
},
  "geometry": {"coordinates":[76.37657,32.10720999999999],"type":"Point"}
}