{
  "type": "Feature",
  "properties": {
    "gn:admin1_code":"11.0",
    "gn:admin2_code":"024",
    "gn:asciiname":"Nagrota Bagwan",
    "gn:country_code":"IN",
    "gn:dem":861,
    "gn:feature_class":"P",
    "gn:feature_code":"PPL",
    "gn:name":"Nagrota Bagw\u0101n",
    "gn:population":0,
    "gn:timezone":"Asia/Kolkata",
    "iso:country":"IN",
    "name:ben_x_preferred":[
        "\u09a8\u0997\u09cd\u09b0\u09a4\u09be \u09ac\u0997\u0993\u09af\u09bc\u09be\u09a8"
    ],
    "name:bpy_x_preferred":[
        "\u09a8\u0997\u09cd\u09b0\u09a4\u09be \u09ac\u0997\u09f1\u09be\u09b0"
    ],
    "name:ita_x_preferred":[
        "Nagrota Bagwan"
    ],
    "name:msa_x_preferred":[
        "Nagrota Bagwan"
    ],
    "name:new_x_preferred":[
        "\u0928\u0917\u094d\u0930\u094b\u0924\u093e \u092c\u0917\u094d\u0935\u093e\u0928"
    ],
    "name:nld_x_preferred":[
        "Nagrota Bagwan"
    ],
    "name:pol_x_preferred":[
        "Nagrota Bagwan"
    ],
    "name:por_x_preferred":[
        "Nagrota Bagwan"
    ],
    "name:tam_x_preferred":[
        "\u0ba8\u0b95\u0bcd\u0bb0\u0bcb\u0b9f\u0bcd\u0b9f\u0bbe \u0baa\u0b95\u0bcd\u0bb5\u0bbe\u0ba9\u0bcd"
    ],
    "name:und_x_variant":[
        "Nagrota Kh\u0101s",
        "Nagrota",
        "Kh\u0101s Nagrota",
        "Nagrota Bagw\u0101n"
    ],
    "name:vie_x_preferred":[
        "Nagrota Bagwan"
    ],
    "name:zho_x_preferred":[
        "\u7eb3\u683c\u7f57\u5854\u5df4\u683c\u4e07"
    ],
    "wof:name":"Nagrota Bagwan",
    "wof:placetype":"locality"
},
  "geometry": {"coordinates":[76.37657,32.10720999999999],"type":"Point"}
}