{
  "type": "Feature",
  "properties": {
    "gn:admin1_code":"21.0",
    "gn:admin2_code":"377.0",
    "gn:asciiname":"Bateswar",
    "gn:country_code":"IN",
    "gn:dem":22,
    "gn:feature_class":"P",
    "gn:feature_code":"PPL",
    "gn:name":"Bateswar",
    "gn:population":0,
    "gn:timezone":"Asia/Kolkata",
    "iso:country":"IN",
    "wof:name":"Bateswar",
    "wof:placetype":"locality"
},
  "geometry": {"coordinates":[86.94246,21.48943],"type":"Point"}
}