{
  "type": "Feature",
  "properties": {
    "gn:admin1_code":"35",
    "gn:admin2_code":"446.0",
    "gn:asciiname":"Bagwara",
    "gn:country_code":"IN",
    "gn:dem":394,
    "gn:feature_class":"P",
    "gn:feature_code":"PPL",
    "gn:name":"Bagw\u0101ra",
    "gn:population":0,
    "gn:timezone":"Asia/Kolkata",
    "iso:country":"IN",
    "ks:ks_alt_nam":"Bagw\u0101ra",
    "ks:ks_name":"Bagwara",
    "ks:ks_pop":707,
    "ks:ks_type":"VILLAGE",
    "name:eng_x_preferred":[
        "Bagwara"
    ],
    "name:eng_x_variant":[
        "Bagw\u0101ra"
    ],
    "wof:name":"Bagwara",
    "wof:placetype":"locality",
    "wof:population":707
},
  "geometry": {"coordinates":[77.977783,23.228642],"type":"Point"}
}