{
  "type": "Feature",
  "properties": {
    "iso:country":"IN",
    "ks:ks_name":"Gavathanwadi",
    "ks:ks_pop":422,
    "ks:ks_type":"HABITATION",
    "name:eng_x_preferred":[
        "Gavathanwadi"
    ],
    "wof:name":"Gavathanwadi",
    "wof:placetype":"locality",
    "wof:population":422
},
  "geometry": {"coordinates":[73.695031,15.924788],"type":"Point"}
}