{
  "type": "Feature",
  "properties": {
    "gn:admin1_code":"11.0",
    "gn:admin2_code":"27.0",
    "gn:asciiname":"Khaneoli",
    "gn:country_code":"IN",
    "gn:dem":1705,
    "gn:feature_class":"P",
    "gn:feature_code":"PPL",
    "gn:name":"Khaneoli",
    "gn:population":0,
    "gn:timezone":"Asia/Kolkata",
    "iso:country":"IN",
    "wof:name":"Khaneoli",
    "wof:placetype":"locality"
},
  "geometry": {"coordinates":[77.31043000000003,31.30491],"type":"Point"}
}