{
  "type": "Feature",
  "properties": {
    "gn:admin1_code":"23.0",
    "gn:admin2_code":"36.0",
    "gn:asciiname":"Raman",
    "gn:country_code":"IN",
    "gn:dem":210,
    "gn:feature_class":"P",
    "gn:feature_code":"PPL",
    "gn:name":"R\u0101m\u0101n",
    "gn:population":0,
    "gn:timezone":"Asia/Kolkata",
    "iso:country":"IN",
    "name:bel_x_preferred":[
        "\u0420\u0430\u043c\u0430\u043d"
    ],
    "name:ceb_x_preferred":[
        "Raman"
    ],
    "name:deu_x_preferred":[
        "Raman"
    ],
    "name:fas_x_preferred":[
        "\u0631\u0627\u0645\u0627\u0646"
    ],
    "name:ita_x_preferred":[
        "Raman"
    ],
    "name:jpn_x_preferred":[
        "\u30e9\u30de\u30f3"
    ],
    "name:nld_x_preferred":[
        "Raman"
    ],
    "name:slv_x_preferred":[
        "Raman"
    ],
    "name:spa_x_preferred":[
        "Raman"
    ],
    "name:swe_x_preferred":[
        "Raman"
    ],
    "name:ukr_x_preferred":[
        "\u0420\u0430\u043c\u0430\u043d"
    ],
    "wof:name":"Raman",
    "wof:placetype":"locality"
},
  "geometry": {"coordinates":[75.15394000000001,31.19649],"type":"Point"}
}