{
  "type": "Feature",
  "properties": {
    "gn:admin1_code":"36",
    "gn:admin2_code":"134.0",
    "gn:asciiname":"Sadullah Khanpur",
    "gn:country_code":"IN",
    "gn:dem":234,
    "gn:feature_class":"P",
    "gn:feature_code":"PPL",
    "gn:name":"S\u0101dull\u0101h Kh\u0101npur",
    "gn:population":0,
    "gn:timezone":"Asia/Kolkata",
    "iso:country":"IN",
    "name:und_x_variant":[
        "S\u0101dull\u0101h Kh\u0101npur",
        "Madhi"
    ],
    "wof:name":"Sadullah Khanpur",
    "wof:placetype":"locality"
},
  "geometry": {"coordinates":[78.46654000000002,29.28906],"type":"Point"}
}