{
  "type": "Feature",
  "properties": {
    "iso:country":"IN",
    "ks:ks_name":"Sanyasi Tola",
    "ks:ks_pop":341,
    "ks:ks_type":"HABITATION",
    "name:eng_x_preferred":[
        "Sanyasi Tola"
    ],
    "wof:name":"Sanyasi Tola",
    "wof:placetype":"locality",
    "wof:population":341
},
  "geometry": {"coordinates":[87.628407,26.27678],"type":"Point"}
}