{
  "type": "Feature",
  "properties": {
    "iso:country":"IN",
    "ks:ks_name":"Mainwadi",
    "ks:ks_pop":105,
    "ks:ks_type":"HABITATION",
    "name:eng_x_preferred":[
        "Mainwadi"
    ],
    "wof:name":"Mainwadi",
    "wof:placetype":"locality",
    "wof:population":105
},
  "geometry": {"coordinates":[73.753558,16.683485],"type":"Point"}
}