{
  "type": "Feature",
  "properties": {
    "gn:admin1_code":"12",
    "gn:admin2_code":"20.0",
    "gn:asciiname":"Gunzan",
    "gn:country_code":"IN",
    "gn:dem":1531,
    "gn:feature_class":"P",
    "gn:feature_code":"PPL",
    "gn:name":"Gunzan",
    "gn:population":0,
    "gn:timezone":"Asia/Kolkata",
    "iso:country":"IN",
    "wof:name":"Gunzan",
    "wof:placetype":"locality"
},
  "geometry": {"coordinates":[74.9066,33.40372],"type":"Point"}
}