{
  "type": "Feature",
  "properties": {
    "gn:admin1_code":"36",
    "gn:admin2_code":"188.0",
    "gn:asciiname":"Rajgarh",
    "gn:country_code":"IN",
    "gn:dem":80,
    "gn:feature_class":"P",
    "gn:feature_code":"PPL",
    "gn:name":"R\u0101jgarh",
    "gn:population":0,
    "gn:timezone":"Asia/Kolkata",
    "iso:country":"IN",
    "name:deu_x_preferred":[
        "Rajgarh"
    ],
    "name:ita_x_preferred":[
        "Rajgarh"
    ],
    "name:nld_x_preferred":[
        "Rajgarh"
    ],
    "name:pol_x_preferred":[
        "Rajgarh"
    ],
    "name:por_x_preferred":[
        "Rajgarh"
    ],
    "name:urd_x_preferred":[
        "\u0631\u0627\u062c\u06af\u0691\u06be"
    ],
    "wof:name":"Rajgarh",
    "wof:placetype":"locality"
},
  "geometry": {"coordinates":[83.38316999999998,26.42181],"type":"Point"}
}