{
  "type": "Feature",
  "properties": {
    "iso:country":"IN",
    "ks:ks_name":"Shaktinagar",
    "ks:ks_pop":303,
    "ks:ks_type":"HABITATION",
    "name:eng_x_preferred":[
        "Shaktinagar"
    ],
    "wof:name":"Shaktinagar",
    "wof:placetype":"locality",
    "wof:population":303
},
  "geometry": {"coordinates":[72.487922,27.213128],"type":"Point"}
}