{
  "type": "Feature",
  "properties": {
    "gn:admin1_code":"21",
    "gn:admin2_code":"393.0",
    "gn:asciiname":"Rinbachan",
    "gn:country_code":"IN",
    "gn:dem":161,
    "gn:feature_class":"P",
    "gn:feature_code":"PPL",
    "gn:name":"Rinbachan",
    "gn:population":0,
    "gn:timezone":"Asia/Kolkata",
    "iso:country":"IN",
    "wof:name":"Rinbachan",
    "wof:placetype":"locality"
},
  "geometry": {"coordinates":[83.43548,21.02916],"type":"Point"}
}