{
  "type": "Feature",
  "properties": {
    "gn:admin1_code":"2.0",
    "gn:admin2_code":"543.0",
    "gn:asciiname":"Regulapadu",
    "gn:country_code":"IN",
    "gn:dem":198,
    "gn:feature_class":"P",
    "gn:feature_code":"PPL",
    "gn:name":"Regulap\u0101du",
    "gn:population":0,
    "gn:timezone":"Asia/Kolkata",
    "iso:country":"IN",
    "ks:ks_name":"Ragulapadu",
    "ks:ks_pop":61,
    "ks:ks_type":"HABITATION",
    "name:eng_x_preferred":[
        "Ragulapadu"
    ],
    "name:eng_x_variant":[
        "Regulapadu"
    ],
    "wof:name":"Ragulapadu",
    "wof:placetype":"locality",
    "wof:population":61
},
  "geometry": {"coordinates":[83.23035900000001,18.393905],"type":"Point"}
}