{
  "type": "Feature",
  "properties": {
    "gn:admin1_code":"28.0",
    "gn:admin2_code":"336",
    "gn:asciiname":"Dattapulia",
    "gn:country_code":"IN",
    "gn:dem":14,
    "gn:feature_class":"P",
    "gn:feature_code":"PPL",
    "gn:name":"Dattapulia",
    "gn:population":0,
    "gn:timezone":"Asia/Kolkata",
    "iso:country":"IN",
    "name:und_x_variant":[
        "Dattapulla",
        "Dattapulia"
    ],
    "wof:name":"Dattapulia",
    "wof:placetype":"locality"
},
  "geometry": {"coordinates":[88.70653,23.2368],"type":"Point"}
}