{
  "type": "Feature",
  "properties": {
    "iso:country":"IN",
    "ks:ks_name":"Jamrehi Teer Danda",
    "ks:ks_pop":449,
    "ks:ks_type":"VILLAGE",
    "name:eng_x_preferred":[
        "Jamrehi Teer Danda"
    ],
    "wof:name":"Jamrehi Teer Danda",
    "wof:placetype":"locality",
    "wof:population":449
},
  "geometry": {"coordinates":[80.09582,26.056793],"type":"Point"}
}