{
  "type": "Feature",
  "properties": {
    "iso:country":"IN",
    "ks:ks_alt_nam":"dharumane",
    "ks:ks_name":"Dharumane",
    "ks:ks_pop":226,
    "ks:ks_type":"HABITATION",
    "name:eng_x_preferred":[
        "Dharumane"
    ],
    "wof:name":"Dharumane",
    "wof:placetype":"locality",
    "wof:population":226
},
  "geometry": {"coordinates":[74.562337,13.955903],"type":"Point"}
}