{
  "type": "Feature",
  "properties": {
    "gn:admin1_code":"2",
    "gn:admin2_code":"544.0",
    "gn:asciiname":"Tandapalem",
    "gn:country_code":"IN",
    "gn:dem":977,
    "gn:feature_class":"P",
    "gn:feature_code":"PPL",
    "gn:name":"Tandap\u0101lem",
    "gn:population":0,
    "gn:timezone":"Asia/Kolkata",
    "iso:country":"IN",
    "wof:name":"Tandapalem",
    "wof:placetype":"locality"
},
  "geometry": {"coordinates":[82.48201999999998,17.9202],"type":"Point"}
}