{
  "type": "Feature",
  "properties": {
    "iso:country":"IN",
    "ks:ks_name":"Aravanazhi",
    "ks:ks_pop":497,
    "ks:ks_type":"HABITATION",
    "name:eng_x_preferred":[
        "Aravanazhi"
    ],
    "wof:name":"Aravanazhi",
    "wof:placetype":"locality",
    "wof:population":497
},
  "geometry": {"coordinates":[76.000107,11.90236],"type":"Point"}
}