{
  "type": "Feature",
  "properties": {
    "iso:country":"IN",
    "ks:ks_name":"Sukhuapata",
    "ks:ks_pop":1120,
    "ks:ks_type":"VILLAGE",
    "name:eng_x_preferred":[
        "Sukhuapata"
    ],
    "wof:name":"Sukhuapata",
    "wof:placetype":"locality",
    "wof:population":1120
},
  "geometry": {"coordinates":[86.302334,21.3822],"type":"Point"}
}