{
  "type": "Feature",
  "properties": {
    "iso:country":"IN",
    "ks:ks_alt_nam":"PATIL WASTI",
    "ks:ks_name":"Patil Wasti",
    "ks:ks_pop":100,
    "ks:ks_type":"HABITATION",
    "name:eng_x_preferred":[
        "Patil Wasti"
    ],
    "wof:name":"Patil Wasti",
    "wof:placetype":"locality",
    "wof:population":100
},
  "geometry": {"coordinates":[74.509878,17.153197],"type":"Point"}
}