{
  "type": "Feature",
  "properties": {
    "iso:country":"IN",
    "ks:ks_name":"Haripur",
    "ks:ks_pop":1076,
    "ks:ks_type":"VILLAGE",
    "name:eng_x_preferred":[
        "Haripur"
    ],
    "wof:name":"Haripur",
    "wof:placetype":"locality",
    "wof:population":1076
},
  "geometry": {"coordinates":[87.953734,23.455518],"type":"Point"}
}