{
  "type": "Feature",
  "properties": {
    "iso:country":"IN",
    "ks:ks_name":"Chereapahari",
    "ks:ks_pop":990,
    "ks:ks_type":"VILLAGE",
    "name:eng_x_preferred":[
        "Chereapahari"
    ],
    "wof:name":"Chereapahari",
    "wof:placetype":"locality",
    "wof:population":990
},
  "geometry": {"coordinates":[85.80715499999999,22.421082],"type":"Point"}
}