{
  "type": "Feature",
  "properties": {
    "iso:country":"IN",
    "ks:ks_name":"Biswanathpur",
    "ks:ks_pop":290,
    "ks:ks_type":"VILLAGE",
    "name:eng_x_preferred":[
        "Biswanathpur"
    ],
    "wof:name":"Biswanathpur",
    "wof:placetype":"locality",
    "wof:population":290
},
  "geometry": {"coordinates":[87.442476,21.646307],"type":"Point"}
}