{
  "type": "Feature",
  "properties": {
    "gn:admin1_code":"24.0",
    "gn:admin2_code":"103",
    "gn:asciiname":"Bharunda Khurd",
    "gn:country_code":"IN",
    "gn:dem":344,
    "gn:feature_class":"P",
    "gn:feature_code":"PPL",
    "gn:name":"Bhar\u016bnda Khurd",
    "gn:population":0,
    "gn:timezone":"Asia/Kolkata",
    "iso:country":"IN",
    "name:und_x_variant":[
        "Bhar\u016bnda Khurd",
        "Bharunda Khurd"
    ],
    "wof:name":"Bharunda Khurd",
    "wof:placetype":"locality"
},
  "geometry": {"coordinates":[75.53205,28.10506],"type":"Point"}
}