{
  "type": "Feature",
  "properties": {
    "gn:admin1_code":"29",
    "gn:admin2_code":"243.0",
    "gn:asciiname":"Melli Bazar",
    "gn:country_code":"IN",
    "gn:dem":241,
    "gn:feature_class":"P",
    "gn:feature_code":"PPL",
    "gn:name":"Melli B\u0101z\u0101r",
    "gn:population":0,
    "gn:timezone":"Asia/Kolkata",
    "iso:country":"IN",
    "name:und_x_variant":[
        "Bazar",
        "Melli",
        "Melli B\u0101z\u0101r"
    ],
    "wof:name":"Melli Bazar",
    "wof:placetype":"locality"
},
  "geometry": {"coordinates":[88.45741,27.09122],"type":"Point"}
}