{
  "type": "Feature",
  "properties": {
    "iso:country":"IN",
    "ks:ks_name":"Tezi Gaon No-1",
    "ks:ks_pop":766,
    "ks:ks_type":"VILLAGE",
    "name:eng_x_preferred":[
        "Tezi Gaon No-1"
    ],
    "wof:name":"Tezi Gaon No-1",
    "wof:placetype":"locality",
    "wof:population":766
},
  "geometry": {"coordinates":[95.65994000000001,27.662528],"type":"Point"}
}