{
  "type": "Feature",
  "properties": {
    "gn:admin1_code":"16.0",
    "gn:admin2_code":"510.0",
    "gn:asciiname":"Mudana",
    "gn:country_code":"IN",
    "gn:dem":302,
    "gn:feature_class":"P",
    "gn:feature_code":"PPL",
    "gn:name":"Mud\u0101na",
    "gn:population":0,
    "gn:timezone":"Asia/Kolkata",
    "iso:country":"IN",
    "name:guj_x_preferred":[
        "\u0aae\u0ac1\u0aa1\u0abe\u0aa3\u0abe"
    ],
    "wof:name":"Mudana",
    "wof:placetype":"locality"
},
  "geometry": {"coordinates":[77.75204000000002,19.75227000000001],"type":"Point"}
}