{
  "type": "Feature",
  "properties": {
    "iso:country":"IN",
    "ks:ks_name":"Vrafali",
    "ks:ks_pop":80,
    "ks:ks_type":"HABITATION",
    "name:eng_x_preferred":[
        "Vrafali"
    ],
    "wof:name":"Vrafali",
    "wof:placetype":"locality",
    "wof:population":80
},
  "geometry": {"coordinates":[72.904647,24.36665],"type":"Point"}
}