{
  "type": "Feature",
  "properties": {
    "gn:admin1_code":"36",
    "gn:admin2_code":"185.0",
    "gn:asciiname":"Pakri Sangram",
    "gn:country_code":"IN",
    "gn:dem":91,
    "gn:feature_class":"P",
    "gn:feature_code":"PPL",
    "gn:name":"Pakri Sangr\u0101m",
    "gn:population":0,
    "gn:timezone":"Asia/Kolkata",
    "iso:country":"IN",
    "ks:ks_alt_nam":"Pipri Sangr\u0101m",
    "ks:ks_name":"Pipri Sangram",
    "ks:ks_type":"VILLAGE",
    "name:eng_x_preferred":[
        "Pipri Sangram"
    ],
    "name:eng_x_variant":[
        "Pakri Sangram",
        "Pipri Sangr\u0101m"
    ],
    "wof:name":"Pipri Sangram",
    "wof:placetype":"locality"
},
  "geometry": {"coordinates":[82.310492,26.734238],"type":"Point"}
}