{
  "type": "Feature",
  "properties": {
    "gn:admin1_code":"24.0",
    "gn:admin2_code":"108.0",
    "gn:asciiname":"Ramzanipura ki Jhonpari",
    "gn:country_code":"IN",
    "gn:dem":258,
    "gn:feature_class":"P",
    "gn:feature_code":"PPL",
    "gn:name":"Ramz\u0101n\u012bpura ki Jhonpari",
    "gn:population":0,
    "gn:timezone":"Asia/Kolkata",
    "iso:country":"IN",
    "wof:name":"Ramzanipura ki Jhonpari",
    "wof:placetype":"locality"
},
  "geometry": {"coordinates":[76.49455999999998,26.47843],"type":"Point"}
}