{
  "type": "Feature",
  "properties": {
    "iso:country":"IN",
    "ks:ks_name":"Gramachavadi",
    "ks:ks_pop":552,
    "ks:ks_type":"HABITATION",
    "ks:ks_uagg_main":0,
    "name:eng_x_preferred":[
        "Gramachavadi"
    ],
    "wof:name":"Gramachavadi",
    "wof:placetype":"neighbourhood",
    "wof:population":552
},
  "geometry": {"coordinates":[75.062355,12.772845],"type":"Point"}
}