{
  "type": "Feature",
  "properties": {
    "gn:admin1_code":"35.0",
    "gn:admin2_code":"428.0",
    "gn:asciiname":"Saunrai",
    "gn:country_code":"IN",
    "gn:dem":498,
    "gn:feature_class":"P",
    "gn:feature_code":"PPL",
    "gn:name":"Saunrai",
    "gn:population":0,
    "gn:timezone":"Asia/Kolkata",
    "iso:country":"IN",
    "ks:ks_name":"Saunrai",
    "ks:ks_type":"VILLAGE",
    "name:eng_x_preferred":[
        "Saunrai"
    ],
    "wof:name":"Saunrai",
    "wof:placetype":"locality"
},
  "geometry": {"coordinates":[79.22059,24.123465],"type":"Point"}
}