{
  "type": "Feature",
  "properties": {
    "iso:country":"IN",
    "ks:ks_name":"Chakdha",
    "ks:ks_pop":613,
    "ks:ks_type":"HABITATION",
    "name:eng_x_preferred":[
        "Chakdha"
    ],
    "wof:name":"Chakdha",
    "wof:placetype":"locality",
    "wof:population":613
},
  "geometry": {"coordinates":[85.869286,25.307345],"type":"Point"}
}