{
  "type": "Feature",
  "properties": {
    "gn:admin1_code":"24",
    "gn:admin2_code":"120.0",
    "gn:asciiname":"Bandiara Khurd",
    "gn:country_code":"IN",
    "gn:dem":317,
    "gn:feature_class":"P",
    "gn:feature_code":"PPL",
    "gn:name":"Bandi\u0101ra Khurd",
    "gn:population":0,
    "gn:timezone":"Asia/Kolkata",
    "iso:country":"IN",
    "wof:name":"Bandiara Khurd",
    "wof:placetype":"locality"
},
  "geometry": {"coordinates":[75.37982,25.91277],"type":"Point"}
}