{
  "type": "Feature",
  "properties": {
    "gn:admin1_code":"35",
    "gn:admin2_code":"428.0",
    "gn:asciiname":"Bhadauli",
    "gn:country_code":"IN",
    "gn:dem":362,
    "gn:feature_class":"P",
    "gn:feature_code":"PPL",
    "gn:name":"Bhadauli",
    "gn:population":0,
    "gn:timezone":"Asia/Kolkata",
    "iso:country":"IN",
    "ks:ks_name":"Bhadauli",
    "ks:ks_pop":1756,
    "ks:ks_type":"VILLAGE",
    "name:eng_x_preferred":[
        "Bhadauli"
    ],
    "wof:name":"Bhadauli",
    "wof:placetype":"locality",
    "wof:population":1756
},
  "geometry": {"coordinates":[79.51758700000001,23.852844],"type":"Point"}
}