{
  "type": "Feature",
  "properties": {
    "gn:admin1_code":"39.0",
    "gn:admin2_code":"65.0",
    "gn:asciiname":"Baramtora",
    "gn:country_code":"IN",
    "gn:dem":1635,
    "gn:feature_class":"P",
    "gn:feature_code":"PPL",
    "gn:name":"Baramtora",
    "gn:population":0,
    "gn:timezone":"Asia/Kolkata",
    "iso:country":"IN",
    "ks:ks_name":"Barmtora",
    "ks:ks_pop":97,
    "ks:ks_type":"VILLAGE",
    "name:eng_x_preferred":[
        "Barmtora"
    ],
    "name:eng_x_variant":[
        "Baramtora"
    ],
    "wof:name":"Barmtora",
    "wof:placetype":"locality",
    "wof:population":97
},
  "geometry": {"coordinates":[79.96770100000001,29.398975],"type":"Point"}
}