{
  "type": "Feature",
  "properties": {
    "gn:admin1_code":"39.0",
    "gn:admin2_code":"65.0",
    "gn:asciiname":"Baramtora",
    "gn:country_code":"IN",
    "gn:dem":1635,
    "gn:feature_class":"P",
    "gn:feature_code":"PPL",
    "gn:name":"Baramtora",
    "gn:population":0,
    "gn:timezone":"Asia/Kolkata",
    "iso:country":"IN",
    "wof:name":"Baramtora",
    "wof:placetype":"locality"
},
  "geometry": {"coordinates":[79.96883000000003,29.39953],"type":"Point"}
}