{
  "type": "Feature",
  "properties": {
    "iso:country":"IN",
    "ks:ks_name":"Chambharwadi",
    "ks:ks_pop":209,
    "ks:ks_type":"HABITATION",
    "name:eng_x_preferred":[
        "Chambharwadi"
    ],
    "wof:name":"Chambharwadi",
    "wof:placetype":"locality",
    "wof:population":209
},
  "geometry": {"coordinates":[73.541389,17.169722],"type":"Point"}
}