{
  "type": "Feature",
  "properties": {
    "iso:country":"IN",
    "ks:ks_alt_nam":"Y\u0101q\u016btpur",
    "ks:ks_name":"Yaqutpur",
    "ks:ks_type":"VILLAGE",
    "name:eng_x_preferred":[
        "Yaqutpur"
    ],
    "name:eng_x_variant":[
        "Y\u0101q\u016btpur"
    ],
    "wof:name":"Yaqutpur",
    "wof:placetype":"neighbourhood"
},
  "geometry": {"coordinates":[77.421858,28.472479],"type":"Point"}
}