{
  "type": "Feature",
  "properties": {
    "gn:country":"IN",
    "gn:fcode":"PPL",
    "gn:population":7163,
    "iso:country":"IN",
    "name:ara_x_preferred":[
        "\u062c\u0648\u0628\u0627\u0644\u0628\u0648\u0631"
    ],
    "name:ast_x_preferred":[
        "Gopalpur"
    ],
    "name:ben_bn_x_preferred":[
        "\u0997\u09cb\u09aa\u09be\u09b2\u09aa\u09c1\u09b0"
    ],
    "name:ben_in_x_preferred":[
        "\u0997\u09cb\u09aa\u09be\u09b2\u09aa\u09c1\u09b0"
    ],
    "name:ben_x_preferred":[
        "\u0997\u09cb\u09aa\u09be\u09b2\u09aa\u09c1\u09b0"
    ],
    "name:cat_x_preferred":[
        "Gopalpur"
    ],
    "name:ceb_x_preferred":[
        "Gop\u0101lpur"
    ],
    "name:eng_x_preferred":[
        "Gopalpur"
    ],
    "name:fra_x_preferred":[
        "Gopalpur"
    ],
    "name:guj_x_preferred":[
        "\u0a97\u0acb\u0aaa\u0abe\u0ab2\u0aaa\u0ac1\u0ab0"
    ],
    "name:heb_x_preferred":[
        "\u05d2\u05d5\u05e4\u05dc\u05e4\u05d5\u05e8"
    ],
    "name:hin_x_preferred":[
        "\u0917\u094b\u092a\u093e\u0932\u092a\u0941\u0930"
    ],
    "name:ita_x_preferred":[
        "Gopalpur-on-Sea"
    ],
    "name:kan_x_preferred":[
        "\u0c97\u0ccb\u0caa\u0cbe\u0cb2\u0ccd"
    ],
    "name:mal_x_preferred":[
        "\u0d17\u0d4b\u0d2a\u0d3e\u0d7d\u0d2a\u0d42\u0d7c"
    ],
    "name:mar_x_preferred":[
        "\u0917\u094b\u092a\u093e\u0933\u092a\u0942\u0930"
    ],
    "name:mlg_x_preferred":[
        "Gopalpur-on-Sea"
    ],
    "name:msa_x_preferred":[
        "Gopalpur"
    ],
    "name:nld_x_preferred":[
        "Gopalpur-on-Sea"
    ],
    "name:ori_x_preferred":[
        "\u0b17\u0b4b\u0b2a\u0b3e\u0b33\u0b2a\u0b41\u0b30 \u0b2c\u0b47\u0b33\u0b3e\u0b2d\u0b42\u0b2e\u0b3f"
    ],
    "name:pan_x_preferred":[
        "\u0a17\u0a4b\u0a2a\u0a3e\u0a32\u0a2a\u0a41\u0a30"
    ],
    "name:spa_x_preferred":[
        "Gopalpur"
    ],
    "name:swe_x_preferred":[
        "Gop\u0101lpur"
    ],
    "name:tam_x_preferred":[
        "\u0b95\u0bcb\u0baa\u0bbe\u0bb2\u0bcd\u0baa\u0bc2\u0bb0\u0bcd"
    ],
    "name:tel_x_preferred":[
        "\u0c17\u0c4b\u0c2a\u0c3e\u0c32\u0c4d"
    ],
    "name:und_x_variant":[
        "Gop\u0101lpur-on-Sea"
    ],
    "name:urd_x_preferred":[
        "\u06af\u0648\u067e\u0627\u0644 \u067e\u0648\u0631"
    ],
    "qs:name":"Gopalpur",
    "qs:name_adm0":"India",
    "qs:name_adm1":"Orissa",
    "qs:photos":111,
    "qs:photos_1k":22,
    "qs:photos_9k":1,
    "qs:photos_9r":3,
    "qs:photos_all":111,
    "qs:photos_sr":3,
    "qs:placetype":"Town",
    "qs:pop_sr":"5",
    "wd:wordcount":164,
    "wof:name":"Gopalpur",
    "wof:placetype":"locality",
    "wof:population":7163
},
  "geometry": {"coordinates":[84.90517,19.25861],"type":"Point"}
}