{
  "type": "Feature",
  "properties": {
    "gn:country":"IN",
    "gn:fcode":"PPL",
    "gn:pop":7163,
    "iso:country":"IN",
    "name:ben_x_preferred":[
        "\u0997\u09cb\u09aa\u09be\u09b2\u09aa\u09c1\u09b0"
    ],
    "name:cat_x_preferred":[
        "Gopalpur"
    ],
    "name:eng_x_preferred":[
        "Gopalpur"
    ],
    "name:fra_x_preferred":[
        "Gopalpur"
    ],
    "name:ita_x_preferred":[
        "Gopalpur-on-Sea"
    ],
    "name:mlg_x_preferred":[
        "Gopalpur-on-Sea"
    ],
    "name:msa_x_preferred":[
        "Gopalpur"
    ],
    "name:nld_x_preferred":[
        "Gopalpur-on-Sea"
    ],
    "name:ori_x_preferred":[
        "\u0b17\u0b4b\u0b2a\u0b3e\u0b33\u0b2a\u0b41\u0b30 \u0b2c\u0b47\u0b33\u0b3e\u0b2d\u0b42\u0b2e\u0b3f"
    ],
    "name:spa_x_preferred":[
        "Gopalpur"
    ],
    "name:swe_x_preferred":[
        "Gop\u0101lpur"
    ],
    "name:unk_x_variant":[
        "Gop\u0101lpur-on-Sea"
    ],
    "qs:name":"Gopalpur",
    "qs:name_adm0":"India",
    "qs:name_adm1":"Orissa",
    "qs:photos":111,
    "qs:photos_1k":22,
    "qs:photos_9k":1,
    "qs:photos_9r":3,
    "qs:photos_all":111,
    "qs:photos_sr":3,
    "qs:placetype":"Town",
    "qs:pop_sr":"5",
    "wd:wordcount":164,
    "wof:name":"Gopalpur",
    "wof:placetype":"locality",
    "wof:population":7163
},
  "geometry": {"coordinates":[84.90517,19.25861],"type":"Point"}
}