{
  "type": "Feature",
  "properties": {
    "gn:admin1_code":"21.0",
    "gn:admin2_code":"374",
    "gn:asciiname":"Hingir",
    "gn:country_code":"IN",
    "gn:dem":353,
    "gn:feature_class":"P",
    "gn:feature_code":"PPL",
    "gn:name":"Hing\u012br",
    "gn:population":0,
    "gn:timezone":"Asia/Kolkata",
    "iso:country":"IN",
    "name:und_x_variant":[
        "Hing\u012br",
        "Hemagiri",
        "Himgir"
    ],
    "wof:name":"Hingir",
    "wof:placetype":"neighbourhood"
},
  "geometry": {"coordinates":[83.70035,21.94877],"type":"Point"}
}