{
  "type": "Feature",
  "properties": {
    "gn:admin1_code":"21.0",
    "gn:admin2_code":"389",
    "gn:asciiname":"Guluba",
    "gn:country_code":"IN",
    "gn:dem":503,
    "gn:feature_class":"P",
    "gn:feature_code":"PPL",
    "gn:name":"Guluba",
    "gn:population":0,
    "gn:timezone":"Asia/Kolkata",
    "iso:country":"IN",
    "wof:name":"Guluba",
    "wof:placetype":"locality"
},
  "geometry": {"coordinates":[84.09141,19.41703],"type":"Point"}
}