{
  "type": "Feature",
  "properties": {
    "iso:country":"IN",
    "ks:ks_name":"Kiravalewadi",
    "ks:ks_pop":252,
    "ks:ks_type":"VILLAGE",
    "name:eng_x_preferred":[
        "Kiravalewadi"
    ],
    "wof:name":"Kiravalewadi",
    "wof:placetype":"locality",
    "wof:population":252
},
  "geometry": {"coordinates":[73.31255,17.429958],"type":"Point"}
}