{
  "type": "Feature",
  "properties": {
    "gn:admin1_code":"37",
    "gn:admin2_code":"412.0",
    "gn:asciiname":"Hathband",
    "gn:country_code":"IN",
    "gn:dem":315,
    "gn:feature_class":"P",
    "gn:feature_code":"PPL",
    "gn:name":"Hathband",
    "gn:population":0,
    "gn:timezone":"Asia/Kolkata",
    "iso:country":"IN",
    "wof:name":"Hathband",
    "wof:placetype":"locality"
},
  "geometry": {"coordinates":[81.9404,20.73298],"type":"Point"}
}