{
  "type": "Feature",
  "properties": {
    "iso:country":"IN",
    "ks:ks_name":"Chopta",
    "ks:ks_type":"VILLAGE",
    "name:eng_x_preferred":[
        "Chopta"
    ],
    "wof:name":"Chopta",
    "wof:placetype":"locality"
},
  "geometry": {"coordinates":[79.20014399999999,30.485424],"type":"Point"}
}