{
  "type": "Feature",
  "properties": {
    "iso:country":"IN",
    "ks:ks_name":"Nandigiri",
    "ks:ks_pop":107,
    "ks:ks_type":"VILLAGE",
    "name:eng_x_preferred":[
        "Nandigiri"
    ],
    "wof:name":"Nandigiri",
    "wof:placetype":"locality",
    "wof:population":107
},
  "geometry": {"coordinates":[85.000311,19.91095],"type":"Point"}
}