{
  "type": "Feature",
  "properties": {
    "iso:country":"IN",
    "ks:ks_name":"Borong Muktiar",
    "ks:ks_pop":134,
    "ks:ks_type":"VILLAGE",
    "name:eng_x_preferred":[
        "Borong Muktiar"
    ],
    "wof:name":"Borong Muktiar",
    "wof:placetype":"locality",
    "wof:population":134
},
  "geometry": {"coordinates":[95.06634699999999,27.706293],"type":"Point"}
}