{
  "type": "Feature",
  "properties": {
    "iso:country":"IN",
    "ks:ks_alt_nam":"Kamini para",
    "ks:ks_name":"Kamini Para",
    "ks:ks_pop":201,
    "ks:ks_type":"HABITATION",
    "name:eng_x_preferred":[
        "Kamini Para"
    ],
    "wof:name":"Kamini Para",
    "wof:placetype":"locality",
    "wof:population":201
},
  "geometry": {"coordinates":[91.72345799999999,23.083939],"type":"Point"}
}