{
  "type": "Feature",
  "properties": {
    "gn:admin1_code":"11",
    "gn:admin2_code":"34.0",
    "gn:asciiname":"Bhinang Dogri",
    "gn:country_code":"IN",
    "gn:dem":3119,
    "gn:feature_class":"P",
    "gn:feature_code":"PPL",
    "gn:name":"Bh\u012bnang Dogri",
    "gn:population":0,
    "gn:timezone":"Asia/Kolkata",
    "iso:country":"IN",
    "wof:name":"Bhinang Dogri",
    "wof:placetype":"locality"
},
  "geometry": {"coordinates":[78.36048000000002,31.67571],"type":"Point"}
}