{
  "type": "Feature",
  "properties": {
    "iso:country":"IN",
    "ks:ks_name":"Amragachhi",
    "ks:ks_pop":947,
    "ks:ks_type":"VILLAGE",
    "ks:ks_uagg_main":0,
    "name:eng_x_preferred":[
        "Amragachhi"
    ],
    "wof:name":"Amragachhi",
    "wof:placetype":"neighbourhood",
    "wof:population":947
},
  "geometry": {"coordinates":[88.55658,22.914695],"type":"Point"}
}