{
  "type": "Feature",
  "properties": {
    "iso:country":"IN",
    "ks:ks_name":"Dhajak",
    "ks:ks_pop":358,
    "ks:ks_type":"HABITATION",
    "name:eng_x_preferred":[
        "Dhajak"
    ],
    "wof:name":"Dhajak",
    "wof:placetype":"locality",
    "wof:population":358
},
  "geometry": {"coordinates":[82.630154,22.79174],"type":"Point"}
}