{
  "type": "Feature",
  "properties": {
    "iso:country":"IN",
    "ks:ks_name":"Poomathiyanvilai",
    "ks:ks_pop":412,
    "ks:ks_type":"HABITATION",
    "name:eng_x_preferred":[
        "Poomathiyanvilai"
    ],
    "wof:name":"Poomathiyanvilai",
    "wof:placetype":"locality",
    "wof:population":412
},
  "geometry": {"coordinates":[77.386748,8.122345],"type":"Point"}
}