{
  "type": "Feature",
  "properties": {
    "iso:country":"IN",
    "ks:ks_name":"Lalmatiyapara",
    "ks:ks_pop":140,
    "ks:ks_type":"HABITATION",
    "name:eng_x_preferred":[
        "Lalmatiyapara"
    ],
    "wof:name":"Lalmatiyapara",
    "wof:placetype":"locality",
    "wof:population":140
},
  "geometry": {"coordinates":[82.502916,22.783081],"type":"Point"}
}