{
  "type": "Feature",
  "properties": {
    "iso:country":"IN",
    "ks:ks_name":"Bakeya",
    "ks:ks_pop":459,
    "ks:ks_type":"HABITATION",
    "ks:ks_uagg_main":0,
    "name:eng_x_preferred":[
        "Bakeya"
    ],
    "wof:name":"Bakeya",
    "wof:placetype":"neighbourhood",
    "wof:population":459
},
  "geometry": {"coordinates":[84.675625,25.173661],"type":"Point"}
}