{
  "type": "Feature",
  "properties": {
    "iso:country":"IN",
    "ks:ks_alt_nam":"Vadaya kandi",
    "ks:ks_name":"Vadaya Kandi",
    "ks:ks_pop":665,
    "ks:ks_type":"HABITATION",
    "name:eng_x_preferred":[
        "Vadaya Kandi"
    ],
    "wof:name":"Vadaya Kandi",
    "wof:placetype":"locality",
    "wof:population":665
},
  "geometry": {"coordinates":[75.579213,11.619585],"type":"Point"}
}