{
  "type": "Feature",
  "properties": {
    "gn:admin1_code":"19.0",
    "gn:admin2_code":"582.0",
    "gn:asciiname":"Boyinavaripalli",
    "gn:country_code":"IN",
    "gn:dem":726,
    "gn:feature_class":"P",
    "gn:feature_code":"PPL",
    "gn:name":"Boyinav\u0101ripalli",
    "gn:population":0,
    "gn:timezone":"Asia/Kolkata",
    "iso:country":"IN",
    "wof:name":"Boyinavaripalli",
    "wof:placetype":"locality"
},
  "geometry": {"coordinates":[77.83634000000001,13.82791],"type":"Point"}
}