{
  "type": "Feature",
  "properties": {
    "iso:country":"IN",
    "ks:ks_name":"Keshkund",
    "ks:ks_pop":216,
    "ks:ks_type":"HABITATION",
    "name:eng_x_preferred":[
        "Keshkund"
    ],
    "wof:name":"Keshkund",
    "wof:placetype":"locality",
    "wof:population":216
},
  "geometry": {"coordinates":[81.46122699999999,19.082284],"type":"Point"}
}