{
  "type": "Feature",
  "properties": {
    "iso:country":"IN",
    "ks:ks_name":"Mustafabad Tappa Ahamadnagar",
    "ks:ks_pop":371,
    "ks:ks_type":"VILLAGE",
    "ks:ks_uagg_main":0,
    "name:eng_x_preferred":[
        "Mustafabad Tappa Ahamadnagar"
    ],
    "wof:name":"Mustafabad Tappa Ahamadnagar",
    "wof:placetype":"neighbourhood",
    "wof:population":371
},
  "geometry": {"coordinates":[78.93589900000001,28.033986],"type":"Point"}
}