{
  "type": "Feature",
  "properties": {
    "iso:country":"IN",
    "ks:ks_alt_nam":"Savalasang LT1",
    "ks:ks_name":"Savalasang Lt1",
    "ks:ks_pop":356,
    "ks:ks_type":"HABITATION",
    "name:eng_x_preferred":[
        "Savalasang Lt1"
    ],
    "wof:name":"Savalasang Lt1",
    "wof:placetype":"locality",
    "wof:population":356
},
  "geometry": {"coordinates":[75.699091,17.098957],"type":"Point"}
}