{
  "type": "Feature",
  "properties": {
    "iso:country":"IN",
    "ks:ks_name":"Barman Pahtar",
    "ks:ks_pop":200,
    "ks:ks_type":"VILLAGE",
    "name:eng_x_preferred":[
        "Barman Pahtar"
    ],
    "wof:name":"Barman Pahtar",
    "wof:placetype":"locality",
    "wof:population":200
},
  "geometry": {"coordinates":[92.957475,25.880337],"type":"Point"}
}