{
  "type": "Feature",
  "properties": {
    "gn:admin1_code":"11",
    "gn:admin2_code":"33.0",
    "gn:asciiname":"Ganiog",
    "gn:country_code":"IN",
    "gn:dem":1604,
    "gn:feature_class":"P",
    "gn:feature_code":"PPL",
    "gn:name":"Gan\u012bog",
    "gn:population":0,
    "gn:timezone":"Asia/Kolkata",
    "iso:country":"IN",
    "wof:name":"Ganiog",
    "wof:placetype":"locality"
},
  "geometry": {"coordinates":[77.0939,31.16539],"type":"Point"}
}