{
  "type": "Feature",
  "properties": {
    "gn:admin1_code":"36",
    "gn:admin2_code":"159.0",
    "gn:asciiname":"Saidpur Rahmandadpur",
    "gn:country_code":"IN",
    "gn:dem":147,
    "gn:feature_class":"P",
    "gn:feature_code":"PPL",
    "gn:name":"Saidpur Rahm\u0101nd\u0101dpur",
    "gn:population":0,
    "gn:timezone":"Asia/Kolkata",
    "iso:country":"IN",
    "wof:name":"Saidpur Rahmandadpur",
    "wof:placetype":"locality"
},
  "geometry": {"coordinates":[79.42001999999999,27.55924000000001],"type":"Point"}
}