{
  "type": "Feature",
  "properties": {
    "iso:country":"IN",
    "ks:ks_name":"Ramkhiriya Ryt",
    "ks:ks_pop":1029,
    "ks:ks_type":"HABITATION",
    "name:eng_x_preferred":[
        "Ramkhiriya Ryt"
    ],
    "wof:name":"Ramkhiriya Ryt",
    "wof:placetype":"locality",
    "wof:population":1029
},
  "geometry": {"coordinates":[80.567877,22.722918],"type":"Point"}
}