{
  "type": "Feature",
  "properties": {
    "gn:admin1_code":"39.0",
    "gn:admin2_code":"67.0",
    "gn:asciiname":"Gangapur Chamaran",
    "gn:country_code":"IN",
    "gn:dem":212,
    "gn:feature_class":"P",
    "gn:feature_code":"PPL",
    "gn:name":"Gang\u0101pur Cham\u0101r\u0101n",
    "gn:population":0,
    "gn:timezone":"Asia/Kolkata",
    "iso:country":"IN",
    "wof:name":"Gangapur Chamaran",
    "wof:placetype":"locality"
},
  "geometry": {"coordinates":[79.5668,28.94365],"type":"Point"}
}