{
  "type": "Feature",
  "properties": {
    "iso:country":"IN",
    "ks:ks_name":"Washiwali",
    "ks:ks_pop":100,
    "ks:ks_type":"VILLAGE",
    "name:eng_x_preferred":[
        "Washiwali"
    ],
    "wof:name":"Washiwali",
    "wof:placetype":"locality",
    "wof:population":100
},
  "geometry": {"coordinates":[73.175988,18.773919],"type":"Point"}
}