{
  "type": "Feature",
  "properties": {
    "gn:admin1_code":"35",
    "gn:admin2_code":"447.0",
    "gn:asciiname":"Chhindkhera",
    "gn:country_code":"IN",
    "gn:dem":672,
    "gn:feature_class":"P",
    "gn:feature_code":"PPL",
    "gn:name":"Chhindkhera",
    "gn:population":0,
    "gn:timezone":"Asia/Kolkata",
    "iso:country":"IN",
    "ks:ks_name":"Chhindkheda",
    "ks:ks_pop":1430,
    "ks:ks_type":"VILLAGE",
    "name:eng_x_preferred":[
        "Chhindkheda"
    ],
    "name:eng_x_variant":[
        "Chhindkhera"
    ],
    "wof:name":"Chhindkheda",
    "wof:placetype":"locality",
    "wof:population":1430
},
  "geometry": {"coordinates":[78.11145500000001,21.716165],"type":"Point"}
}