{
  "type": "Feature",
  "properties": {
    "iso:country":"IN",
    "ks:ks_name":"Dumariya",
    "ks:ks_pop":142,
    "ks:ks_type":"VILLAGE",
    "name:eng_x_preferred":[
        "Dumariya"
    ],
    "wof:name":"Dumariya",
    "wof:placetype":"locality",
    "wof:population":142
},
  "geometry": {"coordinates":[87.023589,24.610122],"type":"Point"}
}