{
  "type": "Feature",
  "properties": {
    "gn:admin1_code":"35",
    "gn:admin2_code":"428.0",
    "gn:asciiname":"Rampura",
    "gn:country_code":"IN",
    "gn:dem":327,
    "gn:feature_class":"P",
    "gn:feature_code":"PPL",
    "gn:name":"Rampura",
    "gn:population":0,
    "gn:timezone":"Asia/Kolkata",
    "iso:country":"IN",
    "name:cat_x_preferred":[
        "Rampura"
    ],
    "name:pol_x_preferred":[
        "Rampura"
    ],
    "wof:name":"Rampura",
    "wof:placetype":"locality"
},
  "geometry": {"coordinates":[79.70900999999998,24.00261],"type":"Point"}
}