{
  "type": "Feature",
  "properties": {
    "iso:country":"IN",
    "ks:ks_name":"Sanaborasingi",
    "ks:ks_pop":1719,
    "ks:ks_type":"VILLAGE",
    "name:eng_x_preferred":[
        "Sanaborasingi"
    ],
    "wof:name":"Sanaborasingi",
    "wof:placetype":"locality",
    "wof:population":1719
},
  "geometry": {"coordinates":[84.547673,19.831456],"type":"Point"}
}