{
  "type": "Feature",
  "properties": {
    "iso:country":"IN",
    "ks:ks_name":"Nauparia Gaon",
    "ks:ks_pop":129,
    "ks:ks_type":"HABITATION",
    "name:eng_x_preferred":[
        "Nauparia Gaon"
    ],
    "wof:name":"Nauparia Gaon",
    "wof:placetype":"locality",
    "wof:population":129
},
  "geometry": {"coordinates":[94.627773,27.573006],"type":"Point"}
}