{
  "type": "Feature",
  "properties": {
    "iso:country":"IN",
    "ks:ks_name":"Mahespur",
    "ks:ks_pop":3605,
    "ks:ks_type":"VILLAGE",
    "ks:ks_uagg_main":0,
    "name:eng_x_preferred":[
        "Mahespur"
    ],
    "wof:name":"Mahespur",
    "wof:placetype":"neighbourhood",
    "wof:population":3605
},
  "geometry": {"coordinates":[88.23928100000001,23.971942],"type":"Point"}
}