{
  "type": "Feature",
  "properties": {
    "iso:country":"IN",
    "ks:ks_alt_nam":"Gend\u012bdh\u0101na",
    "ks:ks_name":"Gendidhana",
    "ks:ks_type":"VILLAGE",
    "name:eng_x_preferred":[
        "Gendidhana"
    ],
    "name:eng_x_variant":[
        "Gend\u012bdh\u0101na"
    ],
    "wof:name":"Gendidhana",
    "wof:placetype":"locality"
},
  "geometry": {"coordinates":[79.10514499999999,22.590345],"type":"Point"}
}