{
  "type": "Feature",
  "properties": {
    "gn:admin1_code":"16",
    "gn:admin2_code":"503.0",
    "gn:asciiname":"Rajura",
    "gn:country_code":"IN",
    "gn:dem":292,
    "gn:feature_class":"P",
    "gn:feature_code":"PPL",
    "gn:name":"R\u0101jura",
    "gn:population":0,
    "gn:timezone":"Asia/Kolkata",
    "iso:country":"IN",
    "name:ben_x_preferred":[
        "\u09b0\u09be\u099c\u09c1\u09b0\u09be"
    ],
    "name:bpy_x_preferred":[
        "\u09b0\u09be\u099c\u09c1\u09b0\u09be"
    ],
    "name:ceb_x_preferred":[
        "R\u0101j\u016bra"
    ],
    "name:guj_x_preferred":[
        "\u0ab0\u0abe\u0a9c\u0ac1\u0ab0\u0abe"
    ],
    "name:hif_x_preferred":[
        "Rajura"
    ],
    "name:ita_x_preferred":[
        "Rajura"
    ],
    "name:mar_x_preferred":[
        "\u0930\u093e\u091c\u0941\u0930\u093e"
    ],
    "name:msa_x_preferred":[
        "Rajura"
    ],
    "name:nld_x_preferred":[
        "Rajura"
    ],
    "name:ori_x_preferred":[
        "\u0b30\u0b3e\u0b1c\u0b41\u0b30\u0b3e"
    ],
    "name:por_x_preferred":[
        "Rajura"
    ],
    "name:urd_x_preferred":[
        "\u0631\u0627\u062c\u0648\u0631\u0627"
    ],
    "name:vie_x_preferred":[
        "Rajura"
    ],
    "wof:name":"Rajura",
    "wof:placetype":"locality"
},
  "geometry": {"coordinates":[77.93034,20.70336],"type":"Point"}
}