{
  "type": "Feature",
  "properties": {
    "gn:admin1_code":"34.0",
    "gn:admin2_code":"211.0",
    "gn:asciiname":"Bahadurpur",
    "gn:country_code":"IN",
    "gn:dem":44,
    "gn:feature_class":"P",
    "gn:feature_code":"PPL",
    "gn:name":"Bah\u0101durpur",
    "gn:population":0,
    "gn:timezone":"Asia/Kolkata",
    "iso:country":"IN",
    "ks:ks_name":"Bahadurpur",
    "ks:ks_pop":441,
    "ks:ks_type":"VILLAGE",
    "ks:ks_uagg_main":0,
    "name:eng_x_preferred":[
        "Bahadurpur"
    ],
    "name:fra_x_preferred":[
        "Bahadurpur"
    ],
    "name:pol_x_preferred":[
        "Bahadurpur"
    ],
    "wof:name":"Bahadurpur",
    "wof:placetype":"neighbourhood",
    "wof:population":441
},
  "geometry": {"coordinates":[87.66144199999999,25.88867],"type":"Point"}
}