{
  "type": "Feature",
  "properties": {
    "gn:country":"IN",
    "gn:fcode":"PPL",
    "gn:pop":18182,
    "iso:country":"IN",
    "name:bpy_x_preferred":[
        "\u09ac\u09a1\u09bc\u0995\u09be\u0995\u09be\u09a8"
    ],
    "name:chi_x_preferred":[
        "\u5df4\u5c14\u5361\u5361\u7eb3"
    ],
    "name:dut_x_preferred":[
        "Barkakana"
    ],
    "name:eng_x_preferred":[
        "Barkakana"
    ],
    "name:fre_x_preferred":[
        "Barkakana"
    ],
    "name:ind_x_preferred":[
        "Barkakana"
    ],
    "name:ita_x_preferred":[
        "Barkakana"
    ],
    "name:may_x_preferred":[
        "Barkakana"
    ],
    "name:nan_x_preferred":[
        "Barkakana"
    ],
    "name:new_x_preferred":[
        "\u092c\u0930\u094d\u0915\u093e\u0915\u093e\u0928\u093e"
    ],
    "name:por_x_preferred":[
        "Barkakana"
    ],
    "name:spa_x_preferred":[
        "Barkakana"
    ],
    "name:vie_x_preferred":[
        "Barkakana"
    ],
    "qs:name":"Barkakana",
    "qs:name_adm0":"India",
    "qs:name_adm1":"Jharkhand",
    "qs:photos_9k":1,
    "qs:photos_9r":1,
    "qs:photos_all":13,
    "qs:photos_sr":0,
    "qs:placetype":"Town",
    "qs:pop_sr":"6",
    "wd:wordcount":593,
    "wof:name":"Barkakana",
    "wof:placetype":"locality",
    "wof:population":18182
},
  "geometry": {"coordinates":[85.46714,23.62199],"type":"Point"}
}