{
  "type": "Feature",
  "properties": {
    "iso:country":"IN",
    "ks:ks_name":"Thiruppanipettai",
    "ks:ks_pop":1029,
    "ks:ks_type":"HABITATION",
    "name:eng_x_preferred":[
        "Thiruppanipettai"
    ],
    "wof:name":"Thiruppanipettai",
    "wof:placetype":"locality",
    "wof:population":1029
},
  "geometry": {"coordinates":[79.572175,10.880766],"type":"Point"}
}