{
  "type": "Feature",
  "properties": {
    "iso:country":"IN",
    "ks:ks_alt_nam":"therkku udaipirappu",
    "ks:ks_name":"Therkku Udaipirappu",
    "ks:ks_pop":59,
    "ks:ks_type":"HABITATION",
    "name:eng_x_preferred":[
        "Therkku Udaipirappu"
    ],
    "wof:name":"Therkku Udaipirappu",
    "wof:placetype":"locality",
    "wof:population":59
},
  "geometry": {"coordinates":[77.963431,8.380307],"type":"Point"}
}