{
  "type": "Feature",
  "properties": {
    "gn:admin1_code":"24",
    "gn:admin2_code":"127.0",
    "gn:asciiname":"Nagalheri",
    "gn:country_code":"IN",
    "gn:dem":260,
    "gn:feature_class":"P",
    "gn:feature_code":"PPL",
    "gn:name":"N\u0101galheri",
    "gn:population":0,
    "gn:timezone":"Asia/Kolkata",
    "iso:country":"IN",
    "wof:name":"Nagalheri",
    "wof:placetype":"locality"
},
  "geometry": {"coordinates":[76.25905,24.96962000000001],"type":"Point"}
}