{
  "type": "Feature",
  "properties": {
    "gn:admin1_code":"34.0",
    "gn:admin2_code":"222.0",
    "gn:asciiname":"Kesabe",
    "gn:country_code":"IN",
    "gn:dem":46,
    "gn:feature_class":"P",
    "gn:feature_code":"PPL",
    "gn:name":"Kes\u0101be",
    "gn:population":0,
    "gn:timezone":"Asia/Kolkata",
    "iso:country":"IN",
    "ks:ks_alt_nam":"Kes\u0101be",
    "ks:ks_name":"Kesabe",
    "ks:ks_type":"VILLAGE",
    "ks:ks_uagg_main":0,
    "name:eng_x_preferred":[
        "Kesabe"
    ],
    "name:eng_x_variant":[
        "Kes\u0101be"
    ],
    "wof:name":"Kesabe",
    "wof:placetype":"neighbourhood"
},
  "geometry": {"coordinates":[86.07644500000001,25.424919],"type":"Point"}
}