{
  "type": "Feature",
  "properties": {
    "gn:admin1_code":"36",
    "gn:admin2_code":"163.0",
    "gn:asciiname":"Mansukh Purwa",
    "gn:country_code":"IN",
    "gn:dem":133,
    "gn:feature_class":"P",
    "gn:feature_code":"PPL",
    "gn:name":"Mansukh Purwa",
    "gn:population":0,
    "gn:timezone":"Asia/Kolkata",
    "iso:country":"IN",
    "ks:ks_name":"Mansukhpurwa",
    "ks:ks_pop":200,
    "ks:ks_type":"HABITATION",
    "name:eng_x_preferred":[
        "Mansukhpurwa"
    ],
    "name:eng_x_variant":[
        "Mansukh Purwa"
    ],
    "wof:name":"Mansukhpurwa",
    "wof:placetype":"locality",
    "wof:population":200
},
  "geometry": {"coordinates":[79.890626,26.361171],"type":"Point"}
}