{
  "type": "Feature",
  "properties": {
    "gn:admin1_code":"12.0",
    "gn:admin2_code":"7.0",
    "gn:asciiname":"Salari",
    "gn:country_code":"IN",
    "gn:dem":788,
    "gn:feature_class":"P",
    "gn:feature_code":"PPL",
    "gn:name":"Sal\u0101ri",
    "gn:population":0,
    "gn:timezone":"Asia/Kolkata",
    "iso:country":"IN",
    "name:sqi_x_preferred":[
        "Salaria"
    ],
    "wof:name":"Salari",
    "wof:placetype":"locality"
},
  "geometry": {"coordinates":[75.60550000000001,32.53928],"type":"Point"}
}