{
  "type": "Feature",
  "properties": {
    "iso:country":"IN",
    "ks:ks_name":"Patleswar",
    "ks:ks_pop":290,
    "ks:ks_type":"HABITATION",
    "name:eng_x_preferred":[
        "Patleswar"
    ],
    "wof:name":"Patleswar",
    "wof:placetype":"locality",
    "wof:population":290
},
  "geometry": {"coordinates":[73.248333,23.741667],"type":"Point"}
}