{
  "type": "Feature",
  "properties": {
    "iso:country":"IN",
    "ks:ks_name":"Gandhinagara",
    "ks:ks_pop":55,
    "ks:ks_type":"HABITATION",
    "name:eng_x_preferred":[
        "Gandhinagara"
    ],
    "wof:name":"Gandhinagara",
    "wof:placetype":"locality",
    "wof:population":55
},
  "geometry": {"coordinates":[78.213205,13.477198],"type":"Point"}
}