{
  "type": "Feature",
  "properties": {
    "iso:country":"IN",
    "ks:ks_alt_nam":"NAKKUPATHI ST GRAMAM",
    "ks:ks_name":"Nakkupathi St Gramam",
    "ks:ks_pop":50,
    "ks:ks_type":"HABITATION",
    "name:eng_x_preferred":[
        "Nakkupathi St Gramam"
    ],
    "wof:name":"Nakkupathi St Gramam",
    "wof:placetype":"locality",
    "wof:population":50
},
  "geometry": {"coordinates":[76.631005,11.089885],"type":"Point"}
}