{
  "type": "Feature",
  "properties": {
    "gn:admin1_code":"24.0",
    "gn:admin2_code":"99.0",
    "gn:asciiname":"Chak Five-Six K K",
    "gn:country_code":"IN",
    "gn:dem":173,
    "gn:feature_class":"P",
    "gn:feature_code":"PPL",
    "gn:name":"Chak Five-Six K K",
    "gn:population":0,
    "gn:timezone":"Asia/Kolkata",
    "iso:country":"IN",
    "name:und_x_variant":[
        "B\u016btar\u0101n"
    ],
    "wof:name":"Chak Five-Six K K",
    "wof:placetype":"locality"
},
  "geometry": {"coordinates":[73.7538,29.7326],"type":"Point"}
}