{
  "type": "Feature",
  "properties": {
    "iso:country":"IN",
    "ks:ks_name":"Dachhin Tola",
    "ks:ks_pop":115,
    "ks:ks_type":"HABITATION",
    "name:eng_x_preferred":[
        "Dachhin Tola"
    ],
    "wof:name":"Dachhin Tola",
    "wof:placetype":"locality",
    "wof:population":115
},
  "geometry": {"coordinates":[83.23253200000001,24.602334],"type":"Point"}
}