{
  "type": "Feature",
  "properties": {
    "iso:country":"IN",
    "ks:ks_alt_nam":"(b) Gondwan Tolaa",
    "ks:ks_name":"Gondwan Tolaa",
    "ks:ks_pop":80,
    "ks:ks_type":"HABITATION",
    "name:eng_x_preferred":[
        "Gondwan Tolaa"
    ],
    "name:eng_x_variant":[
        "(b) Gondwan Tolaa"
    ],
    "wof:name":"Gondwan Tolaa",
    "wof:placetype":"locality",
    "wof:population":80
},
  "geometry": {"coordinates":[83.186727,24.77971],"type":"Point"}
}