{
  "type": "Feature",
  "properties": {
    "gn:gn_country":"IN",
    "gn:gn_fcode":"PPL",
    "gn:gn_pop":0,
    "iso:country":"IN",
    "name:bul_x_preferred":[
        "\u041d\u0435\u0440\u0438\u044f\u043c\u0430\u043d\u0433\u0430\u043b\u0430\u043c"
    ],
    "name:dut_x_preferred":[
        "Neriamangalam"
    ],
    "name:eng_x_preferred":[
        "Neriamangalam"
    ],
    "name:mal_x_preferred":[
        "\u0d28\u0d47\u0d30\u0d4d\u0d2f\u0d2e\u0d02\u0d17\u0d32\u0d02"
    ],
    "name:swe_x_preferred":[
        "Neriyamangalam"
    ],
    "name:unk_x_variant":[
        "Nerimangalam"
    ],
    "qs_pg:aaroncc":"IN",
    "qs_pg:gn_country":"IN",
    "qs_pg:gn_fcode":"PPL",
    "qs_pg:gn_pop":0,
    "qs_pg:name":"Jeyamangalam",
    "qs_pg:name_adm0":"India",
    "qs_pg:name_adm1":"Tamil Nadu",
    "qs_pg:photos_9r":0,
    "qs_pg:photos_sr":0,
    "qs_pg:pop_sr":0,
    "qs_pg:qs_pg_placetype":"locality",
    "qs_pg:qs_pg_placetype_gp":"Town",
    "qs_pg:woe_adm0":23424848,
    "woe:adm0_id":23424848,
    "woe:name_adm0":"India",
    "woe:name_adm1":"Tamil Nadu",
    "woe:placetype":"Town",
    "wof:name":"Jeyamangalam",
    "wof:placetype":"locality"
},
  "geometry": {"coordinates":[76.77549,10.05125],"type":"Point"}
}