{
  "type": "Feature",
  "properties": {
    "gn:admin1_code":"19.0",
    "gn:admin2_code":"567.0",
    "gn:asciiname":"Haralahalli",
    "gn:country_code":"IN",
    "gn:dem":564,
    "gn:feature_class":"P",
    "gn:feature_code":"PPL",
    "gn:name":"Haralahalli",
    "gn:population":0,
    "gn:timezone":"Asia/Kolkata",
    "iso:country":"IN",
    "wof:name":"Haralahalli",
    "wof:placetype":"locality"
},
  "geometry": {"coordinates":[75.66323,14.19265],"type":"Point"}
}