{
  "type": "Feature",
  "properties": {
    "iso:country":"IN",
    "ks:ks_name":"Vaduguvaripalem",
    "ks:ks_pop":178,
    "ks:ks_type":"HABITATION",
    "name:eng_x_preferred":[
        "Vaduguvaripalem"
    ],
    "wof:name":"Vaduguvaripalem",
    "wof:placetype":"locality",
    "wof:population":178
},
  "geometry": {"coordinates":[80.961,16.043249],"type":"Point"}
}