{
  "type": "Feature",
  "properties": {
    "iso:country":"IN",
    "ks:ks_name":"Siyaraha Yb Ii",
    "ks:ks_pop":320,
    "ks:ks_type":"HABITATION",
    "name:eng_x_preferred":[
        "Siyaraha Yb Ii"
    ],
    "wof:name":"Siyaraha Yb Ii",
    "wof:placetype":"locality",
    "wof:population":320
},
  "geometry": {"coordinates":[83.242237,26.168987],"type":"Point"}
}