{
  "type": "Feature",
  "properties": {
    "iso:country":"IN",
    "ks:ks_name":"Gourbasti",
    "ks:ks_pop":129,
    "ks:ks_type":"HABITATION",
    "name:eng_x_preferred":[
        "Gourbasti"
    ],
    "wof:name":"Gourbasti",
    "wof:placetype":"locality",
    "wof:population":129
},
  "geometry": {"coordinates":[92.126285,24.228038],"type":"Point"}
}