{
  "type": "Feature",
  "properties": {
    "gn:admin1_code":"36.0",
    "gn:admin2_code":"189.0",
    "gn:asciiname":"Parsauni",
    "gn:country_code":"IN",
    "gn:dem":79,
    "gn:feature_class":"P",
    "gn:feature_code":"PPL",
    "gn:name":"Parsauni",
    "gn:population":0,
    "gn:timezone":"Asia/Kolkata",
    "iso:country":"IN",
    "name:msa_x_preferred":[
        "Parsauni"
    ],
    "name:nep_x_preferred":[
        "\u092a\u0938\u094c\u0930\u0928\u0940"
    ],
    "name:new_x_preferred":[
        "\u092a\u0930\u094d\u0938\u094c\u0928\u0940"
    ],
    "name:pol_x_preferred":[
        "Parsauni"
    ],
    "wof:name":"Parsauni",
    "wof:placetype":"locality"
},
  "geometry": {"coordinates":[84.0587,26.66997000000001],"type":"Point"}
}