{
  "type": "Feature",
  "properties": {
    "iso:country":"IN",
    "ks:ks_name":"Pacha Para",
    "ks:ks_pop":725,
    "ks:ks_type":"HABITATION",
    "name:eng_x_preferred":[
        "Pacha Para"
    ],
    "wof:name":"Pacha Para",
    "wof:placetype":"locality",
    "wof:population":725
},
  "geometry": {"coordinates":[88.756749,22.186607],"type":"Point"}
}