{
  "type": "Feature",
  "properties": {
    "iso:country":"IN",
    "ks:ks_name":"Athirkad",
    "ks:ks_pop":2203,
    "ks:ks_type":"HABITATION",
    "ks:ks_uagg_main":0,
    "name:eng_x_preferred":[
        "Athirkad"
    ],
    "wof:name":"Athirkad",
    "wof:placetype":"locality",
    "wof:population":2203
},
  "geometry": {"coordinates":[76.47658,10.780527],"type":"Point"}
}