{
  "type": "Feature",
  "properties": {
    "iso:country":"IN",
    "ks:ks_name":"Kurkuta",
    "ks:ks_pop":295,
    "ks:ks_type":"VILLAGE",
    "name:eng_x_preferred":[
        "Kurkuta"
    ],
    "wof:name":"Kurkuta",
    "wof:placetype":"locality",
    "wof:population":295
},
  "geometry": {"coordinates":[85.45411,23.089525],"type":"Point"}
}