{
  "type": "Feature",
  "properties": {
    "gn:admin1_code":"37",
    "gn:admin2_code":"403.0",
    "gn:asciiname":"Chanamura",
    "gn:country_code":"IN",
    "gn:dem":228,
    "gn:feature_class":"P",
    "gn:feature_code":"PPL",
    "gn:name":"Chanamura",
    "gn:population":0,
    "gn:timezone":"Asia/Kolkata",
    "iso:country":"IN",
    "ks:ks_name":"Chanamuda",
    "ks:ks_pop":164,
    "ks:ks_type":"VILLAGE",
    "ks:ks_uagg_main":0,
    "name:eng_x_preferred":[
        "Chanamuda"
    ],
    "wof:name":"Chanamuda",
    "wof:placetype":"neighbourhood",
    "wof:population":164
},
  "geometry": {"coordinates":[83.015062,21.660977],"type":"Point"}
}