{
  "type": "Feature",
  "properties": {
    "iso:country":"IN",
    "ks:ks_alt_nam":"\u0100r\u0101",
    "ks:ks_name":"Ara",
    "ks:ks_pop":236,
    "ks:ks_type":"VILLAGE",
    "name:eng_x_preferred":[
        "Ara"
    ],
    "name:eng_x_variant":[
        "\u0100r\u0101"
    ],
    "wof:name":"Ara",
    "wof:placetype":"locality",
    "wof:population":236
},
  "geometry": {"coordinates":[84.86005400000001,23.610523],"type":"Point"}
}