{
  "type": "Feature",
  "properties": {
    "gn:admin1_code":"24.0",
    "gn:admin2_code":"110.0",
    "gn:asciiname":"Paragpura",
    "gn:country_code":"IN",
    "gn:dem":452,
    "gn:feature_class":"P",
    "gn:feature_code":"PPL",
    "gn:name":"Par\u0101gpura",
    "gn:population":0,
    "gn:timezone":"Asia/Kolkata",
    "iso:country":"IN",
    "wof:name":"Paragpura",
    "wof:placetype":"locality"
},
  "geometry": {"coordinates":[75.63726,27.17169],"type":"Point"}
}