{
  "type": "Feature",
  "properties": {
    "iso:country":"IN",
    "ks:ks_alt_nam":"Sal\u0101hpur M\u0101jra",
    "ks:ks_name":"Salahpur Majra",
    "ks:ks_type":"VILLAGE",
    "name:eng_x_preferred":[
        "Salahpur Majra"
    ],
    "name:eng_x_variant":[
        "Sal\u0101hpur M\u0101jra"
    ],
    "wof:name":"Salahpur Majra",
    "wof:placetype":"neighbourhood"
},
  "geometry": {"coordinates":[76.995834,28.770239],"type":"Point"}
}