{
  "type": "Feature",
  "properties": {
    "gn:admin1_code":"36.0",
    "gn:admin2_code":"149.0",
    "gn:asciiname":"Nagla",
    "gn:country_code":"IN",
    "gn:dem":159,
    "gn:feature_class":"P",
    "gn:feature_code":"PPL",
    "gn:name":"Nagla",
    "gn:population":0,
    "gn:timezone":"Asia/Kolkata",
    "iso:country":"IN",
    "name:bpy_x_preferred":[
        "\u09a8\u09be\u0982\u09b2\u09be"
    ],
    "name:hif_x_preferred":[
        "Nagla"
    ],
    "name:hin_x_preferred":[
        "\u0928\u093e\u0917\u094d\u0932\u093e"
    ],
    "name:ita_x_preferred":[
        "Nagla"
    ],
    "name:mlg_x_preferred":[
        "Nagla"
    ],
    "name:msa_x_preferred":[
        "Nagla"
    ],
    "name:new_x_preferred":[
        "\u0928\u093e\u0917\u094d\u0932\u093e"
    ],
    "name:nld_x_preferred":[
        "Nagla"
    ],
    "name:ori_x_preferred":[
        "\u0b28\u0b3e\u0b17\u0b4d\u0b32\u0b3e"
    ],
    "name:pol_x_preferred":[
        "Nagla"
    ],
    "name:por_x_preferred":[
        "Nagla"
    ],
    "name:urd_x_preferred":[
        "\u0646\u0627\u06af\u0644\u0627"
    ],
    "name:vie_x_preferred":[
        "Nagla"
    ],
    "name:zho_x_preferred":[
        "\u7eb3\u683c\u62c9"
    ],
    "wof:name":"Nagla",
    "wof:placetype":"locality"
},
  "geometry": {"coordinates":[79.42158000000001,28.05657],"type":"Point"}
}