{
  "type": "Feature",
  "properties": {
    "iso:country":"IN",
    "ks:ks_name":"Shanagar",
    "ks:ks_pop":320,
    "ks:ks_type":"HABITATION",
    "name:eng_x_preferred":[
        "Shanagar"
    ],
    "wof:name":"Shanagar",
    "wof:placetype":"locality",
    "wof:population":320
},
  "geometry": {"coordinates":[80.091193,12.526897],"type":"Point"}
}