{
  "type": "Feature",
  "properties": {
    "iso:country":"IN",
    "ks:ks_name":"Maremma Camp",
    "ks:ks_pop":118,
    "ks:ks_type":"HABITATION",
    "name:eng_x_preferred":[
        "Maremma Camp"
    ],
    "wof:name":"Maremma Camp",
    "wof:placetype":"locality",
    "wof:population":118
},
  "geometry": {"coordinates":[76.95730500000001,15.497212],"type":"Point"}
}