{
  "type": "Feature",
  "properties": {
    "iso:country":"IN",
    "ks:ks_alt_nam":"MADANE VASTI",
    "ks:ks_name":"Madane Vasti",
    "ks:ks_pop":215,
    "ks:ks_type":"HABITATION",
    "name:eng_x_preferred":[
        "Madane Vasti"
    ],
    "wof:name":"Madane Vasti",
    "wof:placetype":"locality",
    "wof:population":215
},
  "geometry": {"coordinates":[74.142152,16.901416],"type":"Point"}
}