{
  "type": "Feature",
  "properties": {
    "iso:country":"IN",
    "ks:ks_name":"Diguvapalem",
    "ks:ks_pop":338,
    "ks:ks_type":"VILLAGE",
    "name:eng_x_preferred":[
        "Diguvapalem"
    ],
    "wof:name":"Diguvapalem",
    "wof:placetype":"locality",
    "wof:population":338
},
  "geometry": {"coordinates":[78.33231600000001,13.824795],"type":"Point"}
}