{
  "type": "Feature",
  "properties": {
    "iso:country":"IN",
    "ks:ks_name":"Chak Simla",
    "ks:ks_pop":99,
    "ks:ks_type":"VILLAGE",
    "ks:ks_uagg_main":0,
    "name:eng_x_preferred":[
        "Chak Simla"
    ],
    "wof:name":"Chak Simla",
    "wof:placetype":"neighbourhood",
    "wof:population":99
},
  "geometry": {"coordinates":[88.36419600000001,23.170084],"type":"Point"}
}