{
  "type": "Feature",
  "properties": {
    "iso:country":"IN",
    "ks:ks_name":"East Radhapur",
    "ks:ks_pop":769,
    "ks:ks_type":"HABITATION",
    "name:eng_x_preferred":[
        "East Radhapur"
    ],
    "wof:name":"East Radhapur",
    "wof:placetype":"locality",
    "wof:population":769
},
  "geometry": {"coordinates":[92.15385000000001,24.345669],"type":"Point"}
}