{
  "type": "Feature",
  "properties": {
    "iso:country":"IN",
    "ks:ks_name":"Mahua Kachrati",
    "ks:ks_pop":2147,
    "ks:ks_type":"VILLAGE",
    "name:eng_x_preferred":[
        "Mahua Kachrati"
    ],
    "wof:name":"Mahua Kachrati",
    "wof:placetype":"locality",
    "wof:population":2147
},
  "geometry": {"coordinates":[87.133641,24.949579],"type":"Point"}
}