{
  "type": "Feature",
  "properties": {
    "iso:country":"IN",
    "ks:ks_name":"Ambling",
    "ks:ks_pop":182,
    "ks:ks_type":"HABITATION",
    "name:eng_x_preferred":[
        "Ambling"
    ],
    "wof:name":"Ambling",
    "wof:placetype":"locality",
    "wof:population":182
},
  "geometry": {"coordinates":[84.33559,21.517924],"type":"Point"}
}