{
  "type": "Feature",
  "properties": {
    "gn:admin1_code":"39",
    "gn:admin2_code":"60.0",
    "gn:asciiname":"Suker Khera",
    "gn:country_code":"IN",
    "gn:dem":1207,
    "gn:feature_class":"P",
    "gn:feature_code":"PPL",
    "gn:name":"Suker Khera",
    "gn:population":0,
    "gn:timezone":"Asia/Kolkata",
    "iso:country":"IN",
    "wof:name":"Suker Khera",
    "wof:placetype":"locality"
},
  "geometry": {"coordinates":[77.8497,30.90922],"type":"Point"}
}