{
  "type": "Feature",
  "properties": {
    "iso:country":"IN",
    "name:eng_x_preferred":[
        "Senchal Lake"
    ],
    "name:unk_x_variant":[
        "Senchal Lake"
    ],
    "qs:gn_adm0_cc":"IN",
    "qs:gn_local":1273467,
    "qs:gn_nam_loc":"Darjeeling, Darjeeling, West Bengal, IN",
    "qs:gn_namadm1":"28",
    "qs:local_max":1773,
    "qs:local_sum":2908,
    "qs:localhoods":6,
    "qs:name":"Senchal Lake",
    "qs:name_adm0":"India",
    "qs:name_adm1":"West Bengal",
    "qs:name_adm2":"Darjeeling",
    "qs:name_local":"Darjeeling",
    "qs:photo_max":24,
    "qs:photo_sum":50,
    "qs:placetype":"Suburb",
    "qs:quad_count":3,
    "qs:woe_adm0":23424848,
    "qs:woe_adm1":2345761,
    "qs:woe_adm2":12586800,
    "qs:woe_lau":0,
    "qs:woe_local":2294818,
    "qs:woe_ver":"7.10.0",
    "wd:wordcount":83,
    "wof:lang":[
        "eng"
    ],
    "wof:name":"Senchal Lake",
    "wof:placetype":"neighbourhood"
},
  "geometry": {"coordinates":[88.249661,27.010099],"type":"Point"}
}