{
  "type": "Feature",
  "properties": {
    "iso:country":"IN",
    "name:ara_x_preferred":[
        "\u0628\u062d\u064a\u0631\u0629 \u0633\u0646\u0634\u0627\u0644"
    ],
    "name:eng_x_preferred":[
        "Senchal Lake"
    ],
    "name:guj_x_preferred":[
        "\u0ab8\u0ac7\u0a82\u0a9a\u0ab2 \u0aa4\u0ab3\u0abe\u0ab5"
    ],
    "name:tam_x_preferred":[
        "\u0b9a\u0bc6\u0b9e\u0bcd\u0b9a\u0bbe\u0bb2\u0bcd \u0b8f\u0bb0\u0bbf"
    ],
    "qs:gn_adm0_cc":"IN",
    "qs:gn_local":1273467,
    "qs:gn_nam_loc":"Darjeeling, Darjeeling, West Bengal, IN",
    "qs:gn_namadm1":"28",
    "qs:local_max":1773,
    "qs:local_sum":2908,
    "qs:localhoods":6,
    "qs:name":"Senchal Lake",
    "qs:name_adm0":"India",
    "qs:name_adm1":"West Bengal",
    "qs:name_adm2":"Darjeeling",
    "qs:name_local":"Darjeeling",
    "qs:photo_max":24,
    "qs:photo_sum":50,
    "qs:placetype":"Suburb",
    "qs:quad_count":3,
    "qs:woe_adm0":23424848,
    "qs:woe_adm1":2345761,
    "qs:woe_adm2":12586800,
    "qs:woe_lau":0,
    "qs:woe_local":2294818,
    "qs:woe_ver":"7.10.0",
    "wd:wordcount":83,
    "wof:lang":[
        "eng"
    ],
    "wof:name":"Senchal Lake",
    "wof:placetype":"neighbourhood"
},
  "geometry": {"coordinates":[88.249661,27.010099],"type":"Point"}
}