{
  "type": "Feature",
  "properties": {
    "iso:country":"IN",
    "name:ara_x_preferred":[
        "\u0628\u062d\u064a\u0631\u0629 \u0633\u0646\u0634\u0627\u0644"
    ],
    "name:ben_bn_x_preferred":[
        "\u09b8\u09c7\u09a8\u099a\u09b2 \u09b2\u09c7\u0995"
    ],
    "name:ben_in_x_preferred":[
        "\u09b8\u09c7\u09a8\u099a\u09b2 \u09b2\u09c7\u0995"
    ],
    "name:eng_x_preferred":[
        "Senchal Lake"
    ],
    "name:guj_x_preferred":[
        "\u0ab8\u0ac7\u0a82\u0a9a\u0abe\u0ab2 \u0ab2\u0ac7\u0a95"
    ],
    "name:guj_x_variant":[
        "\u0ab8\u0ac7\u0a82\u0a9a\u0ab2 \u0aa4\u0ab3\u0abe\u0ab5"
    ],
    "name:hin_x_preferred":[
        "\u0938\u0947\u0902\u091a\u0932 \u0932\u0947\u0915"
    ],
    "name:kan_x_preferred":[
        "\u0cb8\u0cc6\u0c82\u0c9a\u0cb2\u0ccd \u0cb2\u0cc7\u0c95\u0ccd"
    ],
    "name:mal_x_preferred":[
        "\u0d38\u0d46\u0d1e\u0d4d\u0d1a\u0d7d \u0d24\u0d1f\u0d3e\u0d15\u0d02"
    ],
    "name:mar_x_preferred":[
        "\u0938\u0947\u0902\u091a\u0932 \u0932\u0947\u0915"
    ],
    "name:pan_x_preferred":[
        "\u0a38\u0a48\u0a02\u0a1a\u0a32 \u0a32\u0a47\u0a15"
    ],
    "name:tam_x_preferred":[
        "\u0b9a\u0bc6\u0b9e\u0bcd\u0b9a\u0bb2\u0bcd \u0b8f\u0bb0\u0bbf"
    ],
    "name:tam_x_variant":[
        "\u0b9a\u0bc6\u0b9e\u0bcd\u0b9a\u0bbe\u0bb2\u0bcd \u0b8f\u0bb0\u0bbf"
    ],
    "name:tel_x_preferred":[
        "\u0c38\u0c46\u0c02\u0c1a\u0c3e\u0c32\u0c4d \u0c38\u0c30\u0c38\u0c4d\u0c38\u0c41"
    ],
    "name:urd_x_preferred":[
        "\u0633\u06cc\u0646\u0686\u0644 \u0644\u06cc\u06a9"
    ],
    "qs:gn_adm0_cc":"IN",
    "qs:gn_local":1273467,
    "qs:gn_nam_loc":"Darjeeling, Darjeeling, West Bengal, IN",
    "qs:gn_namadm1":"28",
    "qs:local_max":1773,
    "qs:local_sum":2908,
    "qs:localhoods":6,
    "qs:name":"Senchal Lake",
    "qs:name_adm0":"India",
    "qs:name_adm1":"West Bengal",
    "qs:name_adm2":"Darjeeling",
    "qs:name_local":"Darjeeling",
    "qs:photo_max":24,
    "qs:photo_sum":50,
    "qs:placetype":"Suburb",
    "qs:quad_count":3,
    "qs:woe_adm0":23424848,
    "qs:woe_adm1":2345761,
    "qs:woe_adm2":12586800,
    "qs:woe_lau":0,
    "qs:woe_local":2294818,
    "qs:woe_ver":"7.10.0",
    "wd:wordcount":83,
    "wof:lang":[
        "eng"
    ],
    "wof:name":"Senchal Lake",
    "wof:placetype":"neighbourhood"
},
  "geometry": {"coordinates":[88.249661,27.010099],"type":"Point"}
}