{
  "type": "Feature",
  "properties": {
    "iso:country":"IN",
    "ks:ks_name":"Rungurunga Paikara Pur",
    "ks:ks_pop":0,
    "ks:ks_type":"VILLAGE",
    "name:eng_x_preferred":[
        "Rungurunga Paikara Pur"
    ],
    "wof:name":"Rungurunga Paikara Pur",
    "wof:placetype":"locality",
    "wof:population":0
},
  "geometry": {"coordinates":[86.070713,20.830349],"type":"Point"}
}