{
  "type": "Feature",
  "properties": {
    "iso:country":"IN",
    "ks:ks_name":"Hawang Teron",
    "ks:ks_pop":212,
    "ks:ks_type":"HABITATION",
    "name:eng_x_preferred":[
        "Hawang Teron"
    ],
    "wof:name":"Hawang Teron",
    "wof:placetype":"locality",
    "wof:population":212
},
  "geometry": {"coordinates":[93.785099,26.354836],"type":"Point"}
}