{
  "type": "Feature",
  "properties": {
    "iso:country":"IN",
    "ks:ks_name":"Basudebpur",
    "ks:ks_pop":123,
    "ks:ks_type":"VILLAGE",
    "name:eng_x_preferred":[
        "Basudebpur"
    ],
    "wof:name":"Basudebpur",
    "wof:placetype":"locality",
    "wof:population":123
},
  "geometry": {"coordinates":[85.923564,22.711985],"type":"Point"}
}