{
  "type": "Feature",
  "properties": {
    "iso:country":"IN",
    "ks:ks_name":"Mohamadpur Paru",
    "ks:ks_pop":868,
    "ks:ks_type":"VILLAGE",
    "ks:ks_uagg_main":0,
    "name:eng_x_preferred":[
        "Mohamadpur Paru"
    ],
    "wof:name":"Mohamadpur Paru",
    "wof:placetype":"neighbourhood",
    "wof:population":868
},
  "geometry": {"coordinates":[85.10912500000001,26.104341],"type":"Point"}
}