{
  "type": "Feature",
  "properties": {
    "iso:country":"IN",
    "ks:ks_name":"Banjuvasai",
    "ks:ks_pop":100,
    "ks:ks_type":"HABITATION",
    "name:eng_x_preferred":[
        "Banjuvasai"
    ],
    "wof:name":"Banjuvasai",
    "wof:placetype":"locality",
    "wof:population":100
},
  "geometry": {"coordinates":[84.429196,19.008812],"type":"Point"}
}