{
  "type": "Feature",
  "properties": {
    "iso:country":"IN",
    "ks:ks_name":"Chakbahadurpur",
    "ks:ks_pop":1408,
    "ks:ks_type":"VILLAGE",
    "ks:ks_uagg_main":0,
    "name:eng_x_preferred":[
        "Chakbahadurpur"
    ],
    "wof:name":"Chakbahadurpur",
    "wof:placetype":"neighbourhood",
    "wof:population":1408
},
  "geometry": {"coordinates":[88.068517,24.53619],"type":"Point"}
}