{
  "type": "Feature",
  "properties": {
    "iso:country":"IN",
    "ks:ks_name":"Jattha",
    "ks:ks_pop":298,
    "ks:ks_type":"HABITATION",
    "name:eng_x_preferred":[
        "Jattha"
    ],
    "wof:name":"Jattha",
    "wof:placetype":"locality",
    "wof:population":298
},
  "geometry": {"coordinates":[82.167323,24.681663],"type":"Point"}
}