{
  "type": "Feature",
  "properties": {
    "gn:admin1_code":"21",
    "gn:admin2_code":"370.0",
    "gn:asciiname":"Kudla",
    "gn:country_code":"IN",
    "gn:dem":172,
    "gn:feature_class":"P",
    "gn:feature_code":"PPL",
    "gn:name":"Kudla",
    "gn:population":0,
    "gn:timezone":"Asia/Kolkata",
    "iso:country":"IN",
    "name:ces_x_preferred":[
        "Kudla"
    ],
    "name:deu_x_preferred":[
        "Kudla"
    ],
    "name:rus_x_preferred":[
        "\u041a\u0443\u0434\u043b\u0430"
    ],
    "wof:name":"Kudla",
    "wof:placetype":"locality"
},
  "geometry": {"coordinates":[83.33020999999999,20.94809],"type":"Point"}
}