{
  "type": "Feature",
  "properties": {
    "iso:country":"IN",
    "ks:ks_name":"Taliya Baj",
    "ks:ks_pop":231,
    "ks:ks_type":"VILLAGE",
    "name:eng_x_preferred":[
        "Taliya Baj"
    ],
    "wof:name":"Taliya Baj",
    "wof:placetype":"locality",
    "wof:population":231
},
  "geometry": {"coordinates":[80.043609,29.172096],"type":"Point"}
}