{
  "type": "Feature",
  "properties": {
    "iso:country":"IN",
    "ks:ks_name":"Mahuwa Tali Hb",
    "ks:ks_pop":182,
    "ks:ks_type":"HABITATION",
    "name:eng_x_preferred":[
        "Mahuwa Tali Hb"
    ],
    "wof:name":"Mahuwa Tali Hb",
    "wof:placetype":"locality",
    "wof:population":182
},
  "geometry": {"coordinates":[83.038192,25.719245],"type":"Point"}
}