{
  "type": "Feature",
  "properties": {
    "iso:country":"IN",
    "ks:ks_name":"Sukaila",
    "ks:ks_type":"VILLAGE",
    "name:eng_x_preferred":[
        "Sukaila"
    ],
    "wof:name":"Sukaila",
    "wof:placetype":"locality"
},
  "geometry": {"coordinates":[86.54848200000001,26.168517],"type":"Point"}
}