{
  "type": "Feature",
  "properties": {
    "gn:admin1_code":"36.0",
    "gn:admin2_code":"137.0",
    "gn:asciiname":"Malesia",
    "gn:country_code":"IN",
    "gn:dem":222,
    "gn:feature_class":"P",
    "gn:feature_code":"PPL",
    "gn:name":"Malesia",
    "gn:population":0,
    "gn:timezone":"Asia/Kolkata",
    "iso:country":"IN",
    "name:cat_x_preferred":[
        "Mal\u00e8sia"
    ],
    "name:deu_x_preferred":[
        "Malesien"
    ],
    "name:epo_x_preferred":[
        "Malesio"
    ],
    "name:fas_x_preferred":[
        "\u0645\u0627\u0644\u0633\u06cc\u0627"
    ],
    "name:fra_x_preferred":[
        "Mal\u00e9sie"
    ],
    "name:ind_x_preferred":[
        "Malesia"
    ],
    "name:ita_x_preferred":[
        "Malesia"
    ],
    "name:jpn_x_preferred":[
        "\u30de\u30ec\u30b7\u30a2\u690d\u7269\u533a\u7cfb\u533a"
    ],
    "name:lat_x_preferred":[
        "Malesia"
    ],
    "name:lav_x_preferred":[
        "Mal\u0113zija"
    ],
    "name:lit_x_preferred":[
        "Malezija"
    ],
    "name:mal_x_preferred":[
        "\u0d2e\u0d32\u0d40\u0d37\u0d4d\u0d2f"
    ],
    "name:msa_x_preferred":[
        "Malesia"
    ],
    "name:nld_x_preferred":[
        "Malesi\u00eb"
    ],
    "name:por_x_preferred":[
        "Mal\u00e9sia"
    ],
    "name:rus_x_preferred":[
        "\u041c\u0430\u043b\u0435\u0437\u0438\u0439\u0441\u043a\u0430\u044f \u043e\u0431\u043b\u0430\u0441\u0442\u044c"
    ],
    "name:spa_x_preferred":[
        "Malesia"
    ],
    "name:tam_x_preferred":[
        "\u0bae\u0bc7\u0bb2\u0bc7\u0b9a\u0bbf\u0baf\u0bbe"
    ],
    "name:ukr_x_preferred":[
        "\u041c\u0430\u043b\u0435\u0437\u0456\u0439\u0441\u044c\u043a\u0430 \u043e\u0431\u043b\u0430\u0441\u0442\u044c"
    ],
    "name:vie_x_preferred":[
        "Malesia"
    ],
    "wof:name":"Malesia",
    "wof:placetype":"neighbourhood"
},
  "geometry": {"coordinates":[78.28453,28.93946],"type":"Point"}
}