{
  "type": "Feature",
  "properties": {
    "gn:admin1_code":"19.0",
    "gn:admin2_code":"576.0",
    "gn:asciiname":"Choudlu",
    "gn:country_code":"IN",
    "gn:dem":1149,
    "gn:feature_class":"P",
    "gn:feature_code":"PPL",
    "gn:name":"Choudlu",
    "gn:population":0,
    "gn:timezone":"Asia/Kolkata",
    "iso:country":"IN",
    "ks:ks_name":"Choudlu",
    "ks:ks_pop":5351,
    "ks:ks_type":"VILLAGE",
    "name:eng_x_preferred":[
        "Choudlu"
    ],
    "name:vie_x_preferred":[
        "Choudlu"
    ],
    "wof:name":"Choudlu",
    "wof:placetype":"locality",
    "wof:population":5351
},
  "geometry": {"coordinates":[75.862815,12.609079],"type":"Point"}
}