{
  "type": "Feature",
  "properties": {
    "iso:country":"IN",
    "ks:ks_name":"Khariodih",
    "ks:ks_pop":232,
    "ks:ks_type":"VILLAGE",
    "ks:ks_uagg_main":0,
    "name:eng_x_preferred":[
        "Khariodih"
    ],
    "wof:name":"Khariodih",
    "wof:placetype":"neighbourhood",
    "wof:population":232
},
  "geometry": {"coordinates":[86.05488099999999,24.239195],"type":"Point"}
}