{
  "type": "Feature",
  "properties": {
    "gn:admin1_code":"02",
    "gn:admin2_code":"553.0",
    "gn:asciiname":"Palasamudram",
    "gn:country_code":"IN",
    "gn:dem":683,
    "gn:feature_class":"P",
    "gn:feature_code":"PPL",
    "gn:name":"P\u0101lasamudram",
    "gn:population":0,
    "gn:timezone":"Asia/Kolkata",
    "iso:country":"IN",
    "name:new_x_preferred":[
        "\u092a\u093e\u0932\u0938\u092e\u0941\u0926\u094d\u0930\u0902 \u092e\u0923\u094d\u0921\u0932"
    ],
    "name:pam_x_preferred":[
        "Palasamudram"
    ],
    "name:tam_x_preferred":[
        "\u0baa\u0bbe\u0bb2\u0b9a\u0bae\u0bc1\u0ba4\u0bcd\u0ba4\u0bbf\u0bb0\u0bae\u0bcd \u0bae\u0ba3\u0bcd\u0b9f\u0bb2\u0bae\u0bcd"
    ],
    "name:tel_x_preferred":[
        "\u0c2a\u0c3e\u0c32\u0c38\u0c2e\u0c41\u0c26\u0c4d\u0c30\u0c02"
    ],
    "name:tgl_x_preferred":[
        "Palasamudram"
    ],
    "name:und_x_variant":[
        "P\u0101lasamudram",
        "P\u0101lasmudram"
    ],
    "name:urd_x_preferred":[
        "\u067e\u0627\u0644\u0627\u0633\u0645\u062f\u0631\u0645"
    ],
    "name:vie_x_preferred":[
        "Palasamudram"
    ],
    "wof:name":"Palasamudram",
    "wof:placetype":"locality"
},
  "geometry": {"coordinates":[77.67514,13.95896],"type":"Point"}
}