{
  "type": "Feature",
  "properties": {
    "gn:admin1_code":"02",
    "gn:admin2_code":"553.0",
    "gn:asciiname":"Palasamudram",
    "gn:country_code":"IN",
    "gn:dem":683,
    "gn:feature_class":"P",
    "gn:feature_code":"PPL",
    "gn:name":"P\u0101lasamudram",
    "gn:population":0,
    "gn:timezone":"Asia/Kolkata",
    "iso:country":"IN",
    "name:und_x_variant":[
        "P\u0101lasamudram",
        "P\u0101lasmudram"
    ],
    "wof:name":"Palasamudram",
    "wof:placetype":"locality"
},
  "geometry": {"coordinates":[77.67514,13.95896],"type":"Point"}
}