{
  "type": "Feature",
  "properties": {
    "iso:country":"IN",
    "ks:ks_name":"Bojya Thanda",
    "ks:ks_pop":104,
    "ks:ks_type":"HABITATION",
    "ks:ks_uagg_main":0,
    "name:eng_x_preferred":[
        "Bojya Thanda"
    ],
    "wof:name":"Bojya Thanda",
    "wof:placetype":"neighbourhood",
    "wof:population":104
},
  "geometry": {"coordinates":[79.812117,17.401117],"type":"Point"}
}