{
  "type": "Feature",
  "properties": {
    "gn:admin1_code":"38.0",
    "gn:admin2_code":"353.0",
    "gn:asciiname":"Dhawadangal",
    "gn:country_code":"IN",
    "gn:dem":86,
    "gn:feature_class":"P",
    "gn:feature_code":"PPL",
    "gn:name":"Dhaw\u0101d\u0101ngal",
    "gn:population":0,
    "gn:timezone":"Asia/Kolkata",
    "iso:country":"IN",
    "ks:ks_alt_nam":"Dhaw\u0101d\u0101ngal",
    "ks:ks_name":"Dhawadangal",
    "ks:ks_pop":830,
    "ks:ks_type":"VILLAGE",
    "name:eng_x_preferred":[
        "Dhawadangal"
    ],
    "name:eng_x_variant":[
        "Dhaw\u0101d\u0101ngal"
    ],
    "wof:name":"Dhawadangal",
    "wof:placetype":"locality",
    "wof:population":830
},
  "geometry": {"coordinates":[87.648978,24.389797],"type":"Point"}
}