{
  "type": "Feature",
  "properties": {
    "iso:country":"IN",
    "ks:ks_name":"Kakwada",
    "ks:ks_pop":474,
    "ks:ks_type":"VILLAGE",
    "name:eng_x_preferred":[
        "Kakwada"
    ],
    "wof:name":"Kakwada",
    "wof:placetype":"locality",
    "wof:population":474
},
  "geometry": {"coordinates":[75.65503,22.276861],"type":"Point"}
}