{
  "type": "Feature",
  "properties": {
    "gn:admin1_code":"35.0",
    "gn:admin2_code":"457.0",
    "gn:asciiname":"Bodaljhola",
    "gn:country_code":"IN",
    "gn:dem":637,
    "gn:feature_class":"P",
    "gn:feature_code":"PPL",
    "gn:name":"Bodaljhol\u0101",
    "gn:population":0,
    "gn:timezone":"Asia/Kolkata",
    "iso:country":"IN",
    "ks:ks_name":"Bodal Jhola",
    "ks:ks_pop":153,
    "ks:ks_type":"VILLAGE",
    "name:eng_x_preferred":[
        "Bodal Jhola"
    ],
    "name:eng_x_variant":[
        "Bodaljhola"
    ],
    "wof:name":"Bodal Jhola",
    "wof:placetype":"locality",
    "wof:population":153
},
  "geometry": {"coordinates":[80.49550600000001,21.704381],"type":"Point"}
}