{
  "type": "Feature",
  "properties": {
    "iso:country":"IN",
    "ks:ks_name":"Balipur",
    "ks:ks_pop":467,
    "ks:ks_type":"VILLAGE",
    "ks:ks_uagg_main":0,
    "name:eng_x_preferred":[
        "Balipur"
    ],
    "wof:name":"Balipur",
    "wof:placetype":"neighbourhood",
    "wof:population":467
},
  "geometry": {"coordinates":[86.652537,21.314906],"type":"Point"}
}