{
  "type": "Feature",
  "properties": {
    "iso:country":"IN",
    "ks:ks_name":"Emmenahonda",
    "ks:ks_pop":46,
    "ks:ks_type":"HABITATION",
    "name:eng_x_preferred":[
        "Emmenahonda"
    ],
    "wof:name":"Emmenahonda",
    "wof:placetype":"locality",
    "wof:population":46
},
  "geometry": {"coordinates":[74.790716,14.510368],"type":"Point"}
}