{
  "type": "Feature",
  "properties": {
    "iso:country":"IN",
    "ks:ks_name":"Sakati Bhatipara",
    "ks:ks_pop":317,
    "ks:ks_type":"VILLAGE",
    "name:eng_x_preferred":[
        "Sakati Bhatipara"
    ],
    "wof:name":"Sakati Bhatipara",
    "wof:placetype":"locality",
    "wof:population":317
},
  "geometry": {"coordinates":[90.414815,26.490867],"type":"Point"}
}