{
  "type": "Feature",
  "properties": {
    "iso:country":"IN",
    "ks:ks_name":"Jambani",
    "ks:ks_pop":0,
    "ks:ks_type":"VILLAGE",
    "name:eng_x_preferred":[
        "Jambani"
    ],
    "wof:name":"Jambani",
    "wof:placetype":"locality",
    "wof:population":0
},
  "geometry": {"coordinates":[87.43707000000001,22.824511],"type":"Point"}
}