{
  "type": "Feature",
  "properties": {
    "iso:country":"IN",
    "ks:ks_name":"Thakurbari",
    "ks:ks_pop":0,
    "ks:ks_type":"VILLAGE",
    "name:eng_x_preferred":[
        "Thakurbari"
    ],
    "wof:name":"Thakurbari",
    "wof:placetype":"locality",
    "wof:population":0
},
  "geometry": {"coordinates":[86.995801,22.662655],"type":"Point"}
}