{
  "type": "Feature",
  "properties": {
    "gn:admin1_code":"36",
    "gn:admin2_code":"157.0",
    "gn:asciiname":"Kalli Purab",
    "gn:country_code":"IN",
    "gn:dem":126,
    "gn:feature_class":"P",
    "gn:feature_code":"PPL",
    "gn:name":"Kalli Purab",
    "gn:population":0,
    "gn:timezone":"Asia/Kolkata",
    "iso:country":"IN",
    "name:und_x_variant":[
        "Chagha"
    ],
    "wof:name":"Kalli Purab",
    "wof:placetype":"locality"
},
  "geometry": {"coordinates":[80.95241999999998,26.72037000000001],"type":"Point"}
}