{
  "type": "Feature",
  "properties": {
    "iso:country":"IN",
    "ks:ks_name":"Dhani Gumansingh",
    "ks:ks_pop":1021,
    "ks:ks_type":"HABITATION",
    "name:eng_x_preferred":[
        "Dhani Gumansingh"
    ],
    "wof:name":"Dhani Gumansingh",
    "wof:placetype":"locality",
    "wof:population":1021
},
  "geometry": {"coordinates":[75.584022,27.678176],"type":"Point"}
}