{
  "type": "Feature",
  "properties": {
    "iso:country":"IN",
    "ks:ks_name":"Andimadakkadu",
    "ks:ks_pop":100,
    "ks:ks_type":"HABITATION",
    "name:eng_x_preferred":[
        "Andimadakkadu"
    ],
    "wof:name":"Andimadakkadu",
    "wof:placetype":"locality",
    "wof:population":100
},
  "geometry": {"coordinates":[77.58331800000001,11.049893],"type":"Point"}
}