{
  "type": "Feature",
  "properties": {
    "iso:country":"IN",
    "ks:ks_name":"Umberu",
    "ks:ks_pop":57,
    "ks:ks_type":"HABITATION",
    "name:eng_x_preferred":[
        "Umberu"
    ],
    "wof:name":"Umberu",
    "wof:placetype":"locality",
    "wof:population":57
},
  "geometry": {"coordinates":[83.49787000000001,19.937817],"type":"Point"}
}