{
  "type": "Feature",
  "properties": {
    "iso:country":"IN",
    "ks:ks_name":"Kultala",
    "ks:ks_pop":1856,
    "ks:ks_type":"VILLAGE",
    "ks:ks_uagg_main":0,
    "name:eng_x_preferred":[
        "Kultala"
    ],
    "wof:name":"Kultala",
    "wof:placetype":"locality",
    "wof:population":1856
},
  "geometry": {"coordinates":[88.651871,22.786991],"type":"Point"}
}