{
  "type": "Feature",
  "properties": {
    "iso:country":"IN",
    "ks:ks_name":"Honnekodige",
    "ks:ks_pop":39,
    "ks:ks_type":"HABITATION",
    "name:eng_x_preferred":[
        "Honnekodige"
    ],
    "wof:name":"Honnekodige",
    "wof:placetype":"locality",
    "wof:population":39
},
  "geometry": {"coordinates":[75.206823,13.436322],"type":"Point"}
}