{
  "type": "Feature",
  "properties": {
    "gn:country":"IN",
    "gn:fcode":"PPL",
    "gn:population":57361,
    "iso:country":"IN",
    "name:bpy_x_preferred":[
        "\u09b6\u09c7\u09b0\u0995\u09cb\u099f"
    ],
    "name:bul_x_preferred":[
        "\u0428\u0435\u0440\u043a\u043e\u0442"
    ],
    "name:ceb_x_preferred":[
        "Sherkot"
    ],
    "name:eng_x_preferred":[
        "Sherkot"
    ],
    "name:fas_x_preferred":[
        "\u0634\u06cc\u0631\u06a9\u0648\u062a"
    ],
    "name:fra_x_preferred":[
        "Sherkot"
    ],
    "name:hif_x_preferred":[
        "Sherkot"
    ],
    "name:ita_x_preferred":[
        "Sherkot"
    ],
    "name:mlg_x_preferred":[
        "Sherkot"
    ],
    "name:msa_x_preferred":[
        "Sherkot"
    ],
    "name:nan_x_preferred":[
        "Sherkot"
    ],
    "name:nld_x_preferred":[
        "Sherkot"
    ],
    "name:ori_x_preferred":[
        "\u0b36\u0b47\u0b30\u0b15\u0b4b\u0b1f"
    ],
    "name:pnb_x_preferred":[
        "\u0634\u06cc\u0631\u06a9\u0648\u0679"
    ],
    "name:pol_x_preferred":[
        "Sherkot"
    ],
    "name:por_x_preferred":[
        "Sherkot"
    ],
    "name:swe_x_preferred":[
        "Sherkot"
    ],
    "name:und_x_variant":[
        "Bijnor"
    ],
    "name:urd_x_preferred":[
        "\u0634\u06cc\u0631\u06a9\u0648\u0679"
    ],
    "name:vie_x_preferred":[
        "Sherkot"
    ],
    "name:zho_x_preferred":[
        "\u65af\u8d6b\u5c14\u79d1\u7279"
    ],
    "qs:name":"Sherkot",
    "qs:name_adm0":"India",
    "qs:name_adm1":"Uttar Pradesh",
    "qs:photos_9k":1,
    "qs:photos_9r":1,
    "qs:photos_all":1,
    "qs:photos_sr":0,
    "qs:placetype":"Town",
    "qs:pop_sr":"8",
    "wd:wordcount":488,
    "wof:name":"Sherkot",
    "wof:placetype":"locality",
    "wof:population":57361
},
  "geometry": {"coordinates":[78.57447999999999,29.32627],"type":"Point"}
}