{
  "type": "Feature",
  "properties": {
    "gn:country":"IN",
    "gn:fcode":"PPL",
    "gn:pop":57361,
    "iso:country":"IN",
    "name:unk_x_variant":[
        "Bijnor"
    ],
    "qs:name":"Sherkot",
    "qs:name_adm0":"India",
    "qs:name_adm1":"Uttar Pradesh",
    "qs:photos_9k":1,
    "qs:photos_9r":1,
    "qs:photos_all":1,
    "qs:photos_sr":0,
    "qs:placetype":"Town",
    "qs:pop_sr":"8",
    "wd:wordcount":488,
    "wof:name":"Sherkot",
    "wof:placetype":"locality",
    "wof:population":57361
},
  "geometry": {"coordinates":[78.57447999999999,29.32627],"type":"Point"}
}