{
  "type": "Feature",
  "properties": {
    "iso:country":"IN",
    "ks:ks_name":"Nagileru Yanadicolony",
    "ks:ks_pop":105,
    "ks:ks_type":"HABITATION",
    "name:eng_x_preferred":[
        "Nagileru Yanadicolony"
    ],
    "wof:name":"Nagileru Yanadicolony",
    "wof:placetype":"locality",
    "wof:population":105
},
  "geometry": {"coordinates":[79.60453099999999,13.435489],"type":"Point"}
}