{
  "type": "Feature",
  "properties": {
    "iso:country":"IN",
    "ks:ks_name":"Bengooru",
    "ks:ks_pop":1433,
    "ks:ks_type":"VILLAGE",
    "name:eng_x_preferred":[
        "Bengooru"
    ],
    "wof:name":"Bengooru",
    "wof:placetype":"locality",
    "wof:population":1433
},
  "geometry": {"coordinates":[75.630638,12.349021],"type":"Point"}
}