{
  "type": "Feature",
  "properties": {
    "gn:admin1_code":"09",
    "gn:admin2_code":"477.0",
    "gn:asciiname":"Nikava",
    "gn:country_code":"IN",
    "gn:dem":125,
    "gn:feature_class":"P",
    "gn:feature_code":"PPL",
    "gn:name":"Nik\u0101va",
    "gn:population":0,
    "gn:timezone":"Asia/Kolkata",
    "iso:country":"IN",
    "name:und_x_variant":[
        "Nik\u0101ra",
        "Nik\u0101va"
    ],
    "wof:name":"Nikava",
    "wof:placetype":"locality"
},
  "geometry": {"coordinates":[70.53404999999999,22.19216],"type":"Point"}
}