{
  "type": "Feature",
  "properties": {
    "iso:country":"IN",
    "ks:ks_name":"Jambhulwadi",
    "ks:ks_pop":250,
    "ks:ks_type":"HABITATION",
    "name:eng_x_preferred":[
        "Jambhulwadi"
    ],
    "wof:name":"Jambhulwadi",
    "wof:placetype":"locality",
    "wof:population":250
},
  "geometry": {"coordinates":[73.975556,18.828056],"type":"Point"}
}