{
  "type": "Feature",
  "properties": {
    "iso:country":"IN",
    "ks:ks_name":"Gumti",
    "ks:ks_pop":912,
    "ks:ks_type":"HABITATION",
    "name:eng_x_preferred":[
        "Gumti"
    ],
    "wof:name":"Gumti",
    "wof:placetype":"locality",
    "wof:population":912
},
  "geometry": {"coordinates":[88.322278,26.878111],"type":"Point"}
}