{
  "type": "Feature",
  "properties": {
    "gn:admin1_code":"34.0",
    "gn:admin2_code":"235.0",
    "gn:asciiname":"Gangahar",
    "gn:country_code":"IN",
    "gn:dem":144,
    "gn:feature_class":"P",
    "gn:feature_code":"PPL",
    "gn:name":"Gangahar",
    "gn:population":0,
    "gn:timezone":"Asia/Kolkata",
    "iso:country":"IN",
    "wof:name":"Gangahar",
    "wof:placetype":"locality"
},
  "geometry": {"coordinates":[84.30614,24.61632],"type":"Point"}
}