{
  "type": "Feature",
  "properties": {
    "iso:country":"IN",
    "ks:ks_name":"Raghabpur",
    "ks:ks_pop":5748,
    "ks:ks_type":"VILLAGE",
    "ks:ks_uagg_main":0,
    "name:eng_x_preferred":[
        "Raghabpur"
    ],
    "wof:name":"Raghabpur",
    "wof:placetype":"locality",
    "wof:population":5748
},
  "geometry": {"coordinates":[86.36225,23.351029],"type":"Point"}
}