{
  "type": "Feature",
  "properties": {
    "iso:country":"IN",
    "ks:ks_name":"Bakuna",
    "ks:ks_pop":446,
    "ks:ks_type":"VILLAGE",
    "name:eng_x_preferred":[
        "Bakuna"
    ],
    "wof:name":"Bakuna",
    "wof:placetype":"locality",
    "wof:population":446
},
  "geometry": {"coordinates":[84.03089799999999,22.667988],"type":"Point"}
}