{
  "type": "Feature",
  "properties": {
    "iso:country":"IN",
    "ks:ks_name":"Vadkkukailasapuram",
    "ks:ks_pop":362,
    "ks:ks_type":"HABITATION",
    "name:eng_x_preferred":[
        "Vadkkukailasapuram"
    ],
    "wof:name":"Vadkkukailasapuram",
    "wof:placetype":"locality",
    "wof:population":362
},
  "geometry": {"coordinates":[77.962504,8.987028],"type":"Point"}
}