{
  "type": "Feature",
  "properties": {
    "iso:country":"IN",
    "ks:ks_name":"Ghotani Falia",
    "ks:ks_pop":102,
    "ks:ks_type":"HABITATION",
    "name:eng_x_preferred":[
        "Ghotani Falia"
    ],
    "wof:name":"Ghotani Falia",
    "wof:placetype":"locality",
    "wof:population":102
},
  "geometry": {"coordinates":[73.22577800000001,20.179583],"type":"Point"}
}