{
  "type": "Feature",
  "properties": {
    "iso:country":"IN",
    "ks:ks_name":"Kachhiyana",
    "ks:ks_pop":216,
    "ks:ks_type":"HABITATION",
    "ks:ks_uagg_main":0,
    "name:eng_x_preferred":[
        "Kachhiyana"
    ],
    "wof:name":"Kachhiyana",
    "wof:placetype":"neighbourhood",
    "wof:population":216
},
  "geometry": {"coordinates":[78.55558000000001,27.664991],"type":"Point"}
}