{
  "type": "Feature",
  "properties": {
    "iso:country":"IN",
    "ks:ks_alt_nam":"Ky\u0101lasanhalli",
    "ks:ks_name":"Kyalasanhalli",
    "ks:ks_type":"VILLAGE",
    "ks:ks_uagg_main":0,
    "name:eng_x_preferred":[
        "Kyalasanhalli"
    ],
    "name:eng_x_variant":[
        "Ky\u0101lasanhalli"
    ],
    "wof:name":"Kyalasanhalli",
    "wof:placetype":"neighbourhood"
},
  "geometry": {"coordinates":[77.658524,13.05687],"type":"Point"}
}