{
  "type": "Feature",
  "properties": {
    "iso:country":"IN",
    "ks:ks_name":"Narainpur",
    "ks:ks_pop":741,
    "ks:ks_type":"HABITATION",
    "name:eng_x_preferred":[
        "Narainpur"
    ],
    "wof:name":"Narainpur",
    "wof:placetype":"locality",
    "wof:population":741
},
  "geometry": {"coordinates":[92.356651,24.571492],"type":"Point"}
}