{
  "type": "Feature",
  "properties": {
    "iso:country":"IN",
    "ks:ks_name":"Kaldiha",
    "ks:ks_pop":32,
    "ks:ks_type":"VILLAGE",
    "name:eng_x_preferred":[
        "Kaldiha"
    ],
    "wof:name":"Kaldiha",
    "wof:placetype":"locality",
    "wof:population":32
},
  "geometry": {"coordinates":[87.310897,22.057619],"type":"Point"}
}