{
  "type": "Feature",
  "properties": {
    "gn:admin1_code":"12.0",
    "gn:admin2_code":"001",
    "gn:asciiname":"Peth Shatagand",
    "gn:country_code":"IN",
    "gn:dem":1681,
    "gn:feature_class":"P",
    "gn:feature_code":"PPL",
    "gn:name":"Peth Sh\u0101tagand",
    "gn:population":0,
    "gn:timezone":"Asia/Kolkata",
    "iso:country":"IN",
    "wof:name":"Peth Shatagand",
    "wof:placetype":"locality"
},
  "geometry": {"coordinates":[74.24389000000002,34.33929000000001],"type":"Point"}
}