{
  "type": "Feature",
  "properties": {
    "gn:admin1_code":"19.0",
    "gn:admin2_code":"573.0",
    "gn:asciiname":"Kammanayakanahalli",
    "gn:country_code":"IN",
    "gn:dem":674,
    "gn:feature_class":"P",
    "gn:feature_code":"PPL",
    "gn:name":"Kamman\u0101yakanahalli",
    "gn:population":0,
    "gn:timezone":"Asia/Kolkata",
    "iso:country":"IN",
    "ks:ks_name":"Kammanaiyakanhalli",
    "ks:ks_pop":475,
    "ks:ks_type":"VILLAGE",
    "name:eng_x_preferred":[
        "Kammanaiyakanhalli"
    ],
    "name:eng_x_variant":[
        "Kammanayakanahalli"
    ],
    "wof:name":"Kammanaiyakanhalli",
    "wof:placetype":"locality",
    "wof:population":475
},
  "geometry": {"coordinates":[76.93536,12.505288],"type":"Point"}
}