{
  "type": "Feature",
  "properties": {
    "gn:admin1_code":"37",
    "gn:admin2_code":"407.0",
    "gn:asciiname":"Pandripani",
    "gn:country_code":"IN",
    "gn:dem":677,
    "gn:feature_class":"P",
    "gn:feature_code":"PPL",
    "gn:name":"Pandr\u012bp\u0101n\u012b",
    "gn:population":0,
    "gn:timezone":"Asia/Kolkata",
    "iso:country":"IN",
    "ks:ks_name":"Pandaripani",
    "ks:ks_pop":294,
    "ks:ks_type":"VILLAGE",
    "name:eng_x_preferred":[
        "Pandaripani"
    ],
    "name:eng_x_variant":[
        "Pandripani"
    ],
    "wof:name":"Pandaripani",
    "wof:placetype":"locality",
    "wof:population":294
},
  "geometry": {"coordinates":[80.980446,21.959124],"type":"Point"}
}