{
  "type": "Feature",
  "properties": {
    "iso:country":"IN",
    "ks:ks_name":"Betei",
    "ks:ks_pop":1018,
    "ks:ks_type":"VILLAGE",
    "name:eng_x_preferred":[
        "Betei"
    ],
    "wof:name":"Betei",
    "wof:placetype":"locality",
    "wof:population":1018
},
  "geometry": {"coordinates":[86.497467,21.388737],"type":"Point"}
}