{
  "type": "Feature",
  "properties": {
    "iso:country":"IN",
    "ks:ks_name":"Sarva Naik Thanda",
    "ks:ks_pop":68,
    "ks:ks_type":"HABITATION",
    "name:eng_x_preferred":[
        "Sarva Naik Thanda"
    ],
    "wof:name":"Sarva Naik Thanda",
    "wof:placetype":"locality",
    "wof:population":68
},
  "geometry": {"coordinates":[78.032313,17.758125],"type":"Point"}
}