{
  "type": "Feature",
  "properties": {
    "gn:admin1_code":"19",
    "gn:admin2_code":"563.0",
    "gn:asciiname":"Hulgol",
    "gn:country_code":"IN",
    "gn:dem":489,
    "gn:feature_class":"P",
    "gn:feature_code":"PPL",
    "gn:name":"Hulgol",
    "gn:population":0,
    "gn:timezone":"Asia/Kolkata",
    "iso:country":"IN",
    "ks:ks_name":"Hulgol",
    "ks:ks_pop":849,
    "ks:ks_type":"VILLAGE",
    "name:eng_x_preferred":[
        "Hulgol"
    ],
    "wof:name":"Hulgol",
    "wof:placetype":"locality",
    "wof:population":849
},
  "geometry": {"coordinates":[74.81729900000001,14.715058],"type":"Point"}
}