{
  "type": "Feature",
  "properties": {
    "gn:admin1_code":"19.0",
    "gn:admin2_code":"566.0",
    "gn:asciiname":"Mustalagummi",
    "gn:country_code":"IN",
    "gn:dem":596,
    "gn:feature_class":"P",
    "gn:feature_code":"PPL",
    "gn:name":"Mustalagummi",
    "gn:population":0,
    "gn:timezone":"Asia/Kolkata",
    "iso:country":"IN",
    "wof:name":"Mustalagummi",
    "wof:placetype":"locality"
},
  "geometry": {"coordinates":[76.58288,14.60888],"type":"Point"}
}