{
  "type": "Feature",
  "properties": {
    "iso:country":"IN",
    "ks:ks_alt_nam":"BARWABANDH",
    "ks:ks_name":"Barwabandh",
    "ks:ks_pop":2022,
    "ks:ks_type":"HABITATION",
    "ks:ks_uagg_main":0,
    "name:eng_x_preferred":[
        "Barwabandh"
    ],
    "wof:name":"Barwabandh",
    "wof:placetype":"neighbourhood",
    "wof:population":2022
},
  "geometry": {"coordinates":[83.557979,24.372576],"type":"Point"}
}