{
  "type": "Feature",
  "properties": {
    "iso:country":"IN",
    "ks:ks_name":"Upkabhata",
    "ks:ks_pop":355,
    "ks:ks_type":"VILLAGE",
    "name:eng_x_preferred":[
        "Upkabhata"
    ],
    "wof:name":"Upkabhata",
    "wof:placetype":"locality",
    "wof:population":355
},
  "geometry": {"coordinates":[83.22667199999999,19.950334],"type":"Point"}
}