{
  "type": "Feature",
  "properties": {
    "iso:country":"IN",
    "ks:ks_name":"Menare",
    "ks:ks_pop":50,
    "ks:ks_type":"HABITATION",
    "name:eng_x_preferred":[
        "Menare"
    ],
    "wof:name":"Menare",
    "wof:placetype":"locality",
    "wof:population":50
},
  "geometry": {"coordinates":[74.47237800000001,15.10452],"type":"Point"}
}