{
  "type": "Feature",
  "properties": {
    "iso:country":"IN",
    "ks:ks_name":"Abhimanpur",
    "ks:ks_pop":78,
    "ks:ks_type":"VILLAGE",
    "name:eng_x_preferred":[
        "Abhimanpur"
    ],
    "wof:name":"Abhimanpur",
    "wof:placetype":"locality",
    "wof:population":78
},
  "geometry": {"coordinates":[85.116759,20.456546],"type":"Point"}
}