{
  "type": "Feature",
  "properties": {
    "iso:country":"IN",
    "ks:ks_name":"Thalanjoo",
    "ks:ks_pop":1567,
    "ks:ks_type":"VILLAGE",
    "name:eng_x_preferred":[
        "Thalanjoo"
    ],
    "wof:name":"Thalanjoo",
    "wof:placetype":"locality",
    "wof:population":1567
},
  "geometry": {"coordinates":[73.52996400000001,27.280431],"type":"Point"}
}