{
  "type": "Feature",
  "properties": {
    "iso:country":"IN",
    "ks:ks_name":"Gazi Saray Milk",
    "ks:ks_pop":0,
    "ks:ks_type":"VILLAGE",
    "name:eng_x_preferred":[
        "Gazi Saray Milk"
    ],
    "wof:name":"Gazi Saray Milk",
    "wof:placetype":"locality",
    "wof:population":0
},
  "geometry": {"coordinates":[85.064414,25.167044],"type":"Point"}
}