{
  "type": "Feature",
  "properties": {
    "gn:admin1_code":"2.0",
    "gn:admin2_code":"544",
    "gn:asciiname":"Jalaripeta",
    "gn:cc2":"IN",
    "gn:country_code":"IN",
    "gn:dem":-9999,
    "gn:feature_class":"P",
    "gn:feature_code":"PPL",
    "gn:name":"Jal\u0101ripeta",
    "gn:population":0,
    "gn:timezone":"Asia/Kolkata",
    "iso:country":"IN",
    "name:und_x_variant":[
        "Jalar Petta",
        "Jal\u0101ripeta"
    ],
    "wof:name":"Jalaripeta",
    "wof:placetype":"locality"
},
  "geometry": {"coordinates":[83.34999999999999,17.73333],"type":"Point"}
}