{
  "type": "Feature",
  "properties": {
    "gn:admin1_code":"39",
    "gn:admin2_code":"61.0",
    "gn:asciiname":"Salni",
    "gn:country_code":"IN",
    "gn:dem":1324,
    "gn:feature_class":"P",
    "gn:feature_code":"PPL",
    "gn:name":"Salni",
    "gn:population":0,
    "gn:timezone":"Asia/Kolkata",
    "iso:country":"IN",
    "ks:ks_name":"Salni",
    "ks:ks_type":"VILLAGE",
    "name:eng_x_preferred":[
        "Salni"
    ],
    "wof:name":"Salni",
    "wof:placetype":"locality"
},
  "geometry": {"coordinates":[78.431315,29.873036],"type":"Point"}
}