{
  "type": "Feature",
  "properties": {
    "gn:admin1_code":"31",
    "gn:admin2_code":"286.0",
    "gn:asciiname":"Ralvawng",
    "gn:country_code":"IN",
    "gn:dem":1064,
    "gn:feature_class":"P",
    "gn:feature_code":"PPL",
    "gn:name":"R\u0101lvawng",
    "gn:population":0,
    "gn:timezone":"Asia/Kolkata",
    "iso:country":"IN",
    "wof:name":"Ralvawng",
    "wof:placetype":"locality"
},
  "geometry": {"coordinates":[92.86109999999999,22.9498],"type":"Point"}
}