{
  "type": "Feature",
  "properties": {
    "iso:country":"IN",
    "ks:ks_name":"Kanayamvayal",
    "ks:ks_pop":150,
    "ks:ks_type":"HABITATION",
    "name:eng_x_preferred":[
        "Kanayamvayal"
    ],
    "wof:name":"Kanayamvayal",
    "wof:placetype":"locality",
    "wof:population":150
},
  "geometry": {"coordinates":[76.332674,11.573523],"type":"Point"}
}