{
  "type": "Feature",
  "properties": {
    "iso:country":"IN",
    "ks:ks_alt_nam":"Mushahri tola Guria",
    "ks:ks_name":"Mushahri Tola Guria",
    "ks:ks_pop":148,
    "ks:ks_type":"HABITATION",
    "name:eng_x_preferred":[
        "Mushahri Tola Guria"
    ],
    "wof:name":"Mushahri Tola Guria",
    "wof:placetype":"locality",
    "wof:population":148
},
  "geometry": {"coordinates":[86.39065100000001,24.978831],"type":"Point"}
}