{
  "type": "Feature",
  "properties": {
    "gn:admin1_code":"19",
    "gn:admin2_code":"568.0",
    "gn:asciiname":"Megarvalli",
    "gn:country_code":"IN",
    "gn:dem":634,
    "gn:feature_class":"P",
    "gn:feature_code":"PPL",
    "gn:name":"M\u0113garvalli",
    "gn:population":0,
    "gn:timezone":"Asia/Kolkata",
    "iso:country":"IN",
    "name:und_x_variant":[
        "M\u0113garvalli",
        "Megarvalli"
    ],
    "wof:name":"Megarvalli",
    "wof:placetype":"locality"
},
  "geometry": {"coordinates":[75.15011,13.62153],"type":"Point"}
}