{
  "type": "Feature",
  "properties": {
    "iso:country":"IN",
    "ks:ks_alt_nam":"KHATIK VASTI",
    "ks:ks_name":"Khatik Vasti",
    "ks:ks_pop":101,
    "ks:ks_type":"HABITATION",
    "name:eng_x_preferred":[
        "Khatik Vasti"
    ],
    "wof:name":"Khatik Vasti",
    "wof:placetype":"locality",
    "wof:population":101
},
  "geometry": {"coordinates":[75.091222,19.473944],"type":"Point"}
}