{
  "type": "Feature",
  "properties": {
    "iso:country":"IN",
    "ks:ks_name":"Undriyasara",
    "ks:ks_pop":541,
    "ks:ks_type":"VILLAGE",
    "name:eng_x_preferred":[
        "Undriyasara"
    ],
    "wof:name":"Undriyasara",
    "wof:placetype":"locality",
    "wof:population":541
},
  "geometry": {"coordinates":[71.857969,25.754303],"type":"Point"}
}