{
  "type": "Feature",
  "properties": {
    "iso:country":"IN",
    "ks:ks_name":"Harizan Tola",
    "ks:ks_pop":572,
    "ks:ks_type":"HABITATION",
    "ks:ks_uagg_main":0,
    "name:eng_x_preferred":[
        "Harizan Tola"
    ],
    "wof:name":"Harizan Tola",
    "wof:placetype":"neighbourhood",
    "wof:population":572
},
  "geometry": {"coordinates":[87.144263,25.400447],"type":"Point"}
}