{
  "type": "Feature",
  "properties": {
    "iso:country":"IN",
    "ks:ks_name":"Dasagalapura",
    "ks:ks_pop":129,
    "ks:ks_type":"HABITATION",
    "name:eng_x_preferred":[
        "Dasagalapura"
    ],
    "wof:name":"Dasagalapura",
    "wof:placetype":"locality",
    "wof:population":129
},
  "geometry": {"coordinates":[76.375,12.825],"type":"Point"}
}