{
  "type": "Feature",
  "properties": {
    "iso:country":"IN",
    "ks:ks_alt_nam":"Hirnoda (Myana)",
    "ks:ks_name":"Hirnoda (myana)",
    "ks:ks_pop":281,
    "ks:ks_type":"HABITATION",
    "name:eng_x_preferred":[
        "Hirnoda (myana)"
    ],
    "wof:name":"Hirnoda (myana)",
    "wof:placetype":"locality",
    "wof:population":281
},
  "geometry": {"coordinates":[77.42106099999999,24.883931],"type":"Point"}
}