{
  "type": "Feature",
  "properties": {
    "gn:admin1_code":"19.0",
    "gn:admin2_code":"570.0",
    "gn:asciiname":"Hanchanuru",
    "gn:country_code":"IN",
    "gn:dem":679,
    "gn:feature_class":"P",
    "gn:feature_code":"PPL",
    "gn:name":"Hanchan\u016bru",
    "gn:population":0,
    "gn:timezone":"Asia/Kolkata",
    "iso:country":"IN",
    "ks:ks_name":"Hanchanur",
    "ks:ks_pop":45,
    "ks:ks_type":"HABITATION",
    "name:eng_x_preferred":[
        "Hanchanur"
    ],
    "name:eng_x_variant":[
        "Hanchanuru"
    ],
    "wof:name":"Hanchanur",
    "wof:placetype":"locality",
    "wof:population":45
},
  "geometry": {"coordinates":[75.329678,13.41066],"type":"Point"}
}