{
  "type": "Feature",
  "properties": {
    "gn:admin1_code":"25.0",
    "gn:admin2_code":"604.0",
    "gn:asciiname":"Bavasahibpettai",
    "gn:country_code":"IN",
    "gn:dem":70,
    "gn:feature_class":"P",
    "gn:feature_code":"PPL",
    "gn:name":"B\u0101v\u0101s\u0101hibpettai",
    "gn:population":0,
    "gn:timezone":"Asia/Kolkata",
    "iso:country":"IN",
    "wof:name":"Bavasahibpettai",
    "wof:placetype":"locality"
},
  "geometry": {"coordinates":[79.78245,12.80277],"type":"Point"}
}