{
  "type": "Feature",
  "properties": {
    "gn:admin1_code":"40.0",
    "gn:admin2_code":"537",
    "gn:asciiname":"Japal",
    "gn:country_code":"IN",
    "gn:dem":608,
    "gn:feature_class":"P",
    "gn:feature_code":"PPL",
    "gn:name":"J\u0101pal",
    "gn:population":0,
    "gn:timezone":"Asia/Kolkata",
    "iso:country":"IN",
    "name:und_x_variant":[
        "J\u0101pal"
    ],
    "name:urd_x_preferred":[
        "\u062c\u067e\u0644"
    ],
    "wof:name":"Japal",
    "wof:placetype":"locality"
},
  "geometry": {"coordinates":[78.71843,17.12009],"type":"Point"}
}