{
  "type": "Feature",
  "properties": {
    "iso:country":"IN",
    "ks:ks_name":"Palia Nidhu",
    "ks:ks_pop":302,
    "ks:ks_type":"HABITATION",
    "name:eng_x_preferred":[
        "Palia Nidhu"
    ],
    "wof:name":"Palia Nidhu",
    "wof:placetype":"locality",
    "wof:population":302
},
  "geometry": {"coordinates":[83.00454999999999,27.308057],"type":"Point"}
}