{
  "type": "Feature",
  "properties": {
    "iso:country":"IN",
    "ks:ks_alt_nam":"LAGAI BHAR KA TOLA",
    "ks:ks_name":"Lagai Bhar Ka Tola",
    "ks:ks_pop":105,
    "ks:ks_type":"HABITATION",
    "ks:ks_uagg_main":0,
    "name:eng_x_preferred":[
        "Lagai Bhar Ka Tola"
    ],
    "wof:name":"Lagai Bhar Ka Tola",
    "wof:placetype":"neighbourhood",
    "wof:population":105
},
  "geometry": {"coordinates":[83.70177099999999,25.926452],"type":"Point"}
}