{
  "type": "Feature",
  "properties": {
    "iso:country":"IN",
    "ks:ks_name":"Bharathipuram",
    "ks:ks_pop":170,
    "ks:ks_type":"HABITATION",
    "name:eng_x_preferred":[
        "Bharathipuram"
    ],
    "wof:name":"Bharathipuram",
    "wof:placetype":"locality",
    "wof:population":170
},
  "geometry": {"coordinates":[77.687116,11.044477],"type":"Point"}
}