{
  "type": "Feature",
  "properties": {
    "iso:country":"IN",
    "ks:ks_name":"Mukkam",
    "ks:ks_pop":735,
    "ks:ks_type":"HABITATION",
    "ks:ks_uagg_main":0,
    "name:eng_x_preferred":[
        "Mukkam"
    ],
    "wof:name":"Mukkam",
    "wof:placetype":"neighbourhood",
    "wof:population":735
},
  "geometry": {"coordinates":[76.36945799999999,9.835823],"type":"Point"}
}