{
  "type": "Feature",
  "properties": {
    "iso:country":"IN",
    "ks:ks_name":"Bura Tisso",
    "ks:ks_pop":168,
    "ks:ks_type":"HABITATION",
    "name:eng_x_preferred":[
        "Bura Tisso"
    ],
    "wof:name":"Bura Tisso",
    "wof:placetype":"locality",
    "wof:population":168
},
  "geometry": {"coordinates":[93.145596,26.027618],"type":"Point"}
}