{
  "type": "Feature",
  "properties": {
    "gn:admin1_code":"36",
    "gn:admin2_code":"156.0",
    "gn:asciiname":"Dundi Khera",
    "gn:country_code":"IN",
    "gn:dem":123,
    "gn:feature_class":"P",
    "gn:feature_code":"PPL",
    "gn:name":"Dundi Khera",
    "gn:population":0,
    "gn:timezone":"Asia/Kolkata",
    "iso:country":"IN",
    "ks:ks_name":"Dundi Khera",
    "ks:ks_pop":168,
    "ks:ks_type":"HABITATION",
    "ks:ks_uagg_main":0,
    "name:eng_x_preferred":[
        "Dundi Khera"
    ],
    "wof:name":"Dundi Khera",
    "wof:placetype":"neighbourhood",
    "wof:population":168
},
  "geometry": {"coordinates":[80.852795,26.425168],"type":"Point"}
}