{
  "type": "Feature",
  "properties": {
    "iso:country":"IN",
    "ks:ks_name":"Amenpur Chhiwalaha",
    "ks:ks_pop":293,
    "ks:ks_type":"VILLAGE",
    "name:eng_x_preferred":[
        "Amenpur Chhiwalaha"
    ],
    "wof:name":"Amenpur Chhiwalaha",
    "wof:placetype":"locality",
    "wof:population":293
},
  "geometry": {"coordinates":[80.78374700000001,25.174421],"type":"Point"}
}