{
  "type": "Feature",
  "properties": {
    "gn:admin1_code":"2.0",
    "gn:admin2_code":"553.0",
    "gn:asciiname":"Kodigenahalli",
    "gn:country_code":"IN",
    "gn:dem":626,
    "gn:feature_class":"P",
    "gn:feature_code":"PPL",
    "gn:name":"Kodigenahalli",
    "gn:population":0,
    "gn:timezone":"Asia/Kolkata",
    "iso:country":"IN",
    "name:ben_x_preferred":[
        "\u0995\u09cb\u09a1\u09bf\u099c\u09c7\u09a8\u09be\u09b9\u09be\u09b2\u09cd\u09b2\u09bf"
    ],
    "name:bpy_x_preferred":[
        "\u0995\u09cb\u09a1\u09bf\u099c\u09c7\u09a8\u09be\u09b9\u09be\u09b2\u09cd\u09b2\u09bf"
    ],
    "name:ceb_x_preferred":[
        "Kodigenahalli"
    ],
    "name:ita_x_preferred":[
        "Kodigenahalli"
    ],
    "name:mlg_x_preferred":[
        "Kodigenahalli"
    ],
    "name:msa_x_preferred":[
        "Kodigenahalli"
    ],
    "name:new_x_preferred":[
        "\u0915\u094b\u0926\u093f\u0917\u0947\u0928\u093e\u0939\u0932\u094d\u0932\u0940"
    ],
    "name:nld_x_preferred":[
        "Kodigenahalli"
    ],
    "name:por_x_preferred":[
        "Kodigenahalli"
    ],
    "name:swe_x_preferred":[
        "Kodigenahalli"
    ],
    "name:vie_x_preferred":[
        "Kodigenahalli"
    ],
    "name:zho_x_preferred":[
        "\u79d1\u8fea\u76d6\u7eb3\u54c8\u5c14\u5229"
    ],
    "wof:name":"Kodigenahalli",
    "wof:placetype":"neighbourhood"
},
  "geometry": {"coordinates":[77.40396,13.86161],"type":"Point"}
}