{
  "type": "Feature",
  "properties": {
    "gn:admin1_code":"19.0",
    "gn:admin2_code":"570.0",
    "gn:asciiname":"Banagi",
    "gn:country_code":"IN",
    "gn:dem":638,
    "gn:feature_class":"P",
    "gn:feature_code":"PPL",
    "gn:name":"Banagi",
    "gn:population":0,
    "gn:timezone":"Asia/Kolkata",
    "iso:country":"IN",
    "ks:ks_name":"Banage",
    "ks:ks_pop":61,
    "ks:ks_type":"HABITATION",
    "name:eng_x_preferred":[
        "Banage"
    ],
    "name:eng_x_variant":[
        "Banagi"
    ],
    "wof:name":"Banage",
    "wof:placetype":"locality",
    "wof:population":61
},
  "geometry": {"coordinates":[75.479367,13.655589],"type":"Point"}
}