{
  "type": "Feature",
  "properties": {
    "gn:admin1_code":"12.0",
    "gn:admin2_code":"16.0",
    "gn:asciiname":"Gallu",
    "gn:country_code":"IN",
    "gn:dem":2259,
    "gn:feature_class":"P",
    "gn:feature_code":"PPL",
    "gn:name":"Gall\u016b",
    "gn:population":0,
    "gn:timezone":"Asia/Kolkata",
    "iso:country":"IN",
    "name:bul_x_preferred":[
        "\u0413\u0430\u043b\u043b\u0443"
    ],
    "name:fra_x_preferred":[
        "Gallu"
    ],
    "name:spa_x_preferred":[
        "Gallu"
    ],
    "name:tur_x_preferred":[
        "Gallu"
    ],
    "wof:name":"Gallu",
    "wof:placetype":"locality"
},
  "geometry": {"coordinates":[75.80861,33.10932],"type":"Point"}
}