{
  "type": "Feature",
  "properties": {
    "gn:admin1_code":"37",
    "gn:admin2_code":"408.0",
    "gn:asciiname":"Pandharwani",
    "gn:country_code":"IN",
    "gn:dem":393,
    "gn:feature_class":"P",
    "gn:feature_code":"PPL",
    "gn:name":"P\u0101ndharw\u0101ni",
    "gn:population":0,
    "gn:timezone":"Asia/Kolkata",
    "iso:country":"IN",
    "ks:ks_alt_nam":"P\u0101ndharw\u0101ni",
    "ks:ks_name":"Pandharwani",
    "ks:ks_type":"VILLAGE",
    "name:eng_x_preferred":[
        "Pandharwani"
    ],
    "name:eng_x_variant":[
        "P\u0101ndharw\u0101ni"
    ],
    "wof:name":"Pandharwani",
    "wof:placetype":"locality"
},
  "geometry": {"coordinates":[80.579949,20.615851],"type":"Point"}
}