{
  "type": "Feature",
  "properties": {
    "iso:country":"IN",
    "ks:ks_name":"Kol Basti",
    "ks:ks_pop":495,
    "ks:ks_type":"HABITATION",
    "name:eng_x_preferred":[
        "Kol Basti"
    ],
    "wof:name":"Kol Basti",
    "wof:placetype":"locality",
    "wof:population":495
},
  "geometry": {"coordinates":[82.56580599999999,24.920259],"type":"Point"}
}