{
  "type": "Feature",
  "properties": {
    "iso:country":"IN",
    "ks:ks_name":"Uparbandhi",
    "ks:ks_pop":32,
    "ks:ks_type":"VILLAGE",
    "ks:ks_uagg_main":0,
    "name:eng_x_preferred":[
        "Uparbandhi"
    ],
    "wof:name":"Uparbandhi",
    "wof:placetype":"neighbourhood",
    "wof:population":32
},
  "geometry": {"coordinates":[86.761611,24.228542],"type":"Point"}
}