{
  "type": "Feature",
  "properties": {
    "iso:country":"IN",
    "ks:ks_name":"Latapalli",
    "ks:ks_pop":217,
    "ks:ks_type":"VILLAGE",
    "name:eng_x_preferred":[
        "Latapalli"
    ],
    "wof:name":"Latapalli",
    "wof:placetype":"locality",
    "wof:population":217
},
  "geometry": {"coordinates":[84.562883,19.700282],"type":"Point"}
}