{
  "type": "Feature",
  "properties": {
    "gn:admin1_code":"25.0",
    "gn:admin2_code":"606.0",
    "gn:asciiname":"Attanur",
    "gn:country_code":"IN",
    "gn:dem":263,
    "gn:feature_class":"P",
    "gn:feature_code":"PPL",
    "gn:name":"\u0100tt\u0101n\u016br",
    "gn:population":0,
    "gn:timezone":"Asia/Kolkata",
    "iso:country":"IN",
    "wof:name":"Attanur",
    "wof:placetype":"locality"
},
  "geometry": {"coordinates":[78.72538,12.07569],"type":"Point"}
}