{
  "type": "Feature",
  "properties": {
    "gn:admin1_code":"34.0",
    "gn:admin2_code":"203.0",
    "gn:asciiname":"Lohiaria",
    "gn:country_code":"IN",
    "gn:dem":82,
    "gn:feature_class":"P",
    "gn:feature_code":"PPL",
    "gn:name":"Lohiari\u0101",
    "gn:population":0,
    "gn:timezone":"Asia/Kolkata",
    "iso:country":"IN",
    "ks:ks_alt_nam":"Lohiari\u0101",
    "ks:ks_name":"Lohiaria",
    "ks:ks_type":"VILLAGE",
    "ks:ks_uagg_main":0,
    "name:eng_x_preferred":[
        "Lohiaria"
    ],
    "name:eng_x_variant":[
        "Lohiari\u0101"
    ],
    "wof:name":"Lohiaria",
    "wof:placetype":"neighbourhood"
},
  "geometry": {"coordinates":[84.56632500000001,26.895563],"type":"Point"}
}