{
  "type": "Feature",
  "properties": {
    "iso:country":"IN",
    "ks:ks_name":"Paraspani Bich Tola",
    "ks:ks_pop":206,
    "ks:ks_type":"HABITATION",
    "name:eng_x_preferred":[
        "Paraspani Bich Tola"
    ],
    "wof:name":"Paraspani Bich Tola",
    "wof:placetype":"locality",
    "wof:population":206
},
  "geometry": {"coordinates":[83.37128,24.135605],"type":"Point"}
}