{
  "type": "Feature",
  "properties": {
    "iso:country":"IN",
    "name:ara_x_preferred":[
        "\u0628\u0648\u0634\u0628\u0627 \u0646\u0627\u062c\u0627\u0631 \u0643\u0648\u0644\u0648\u0646\u064a"
    ],
    "name:ben_bn_x_preferred":[
        "\u09aa\u09c1\u09b6\u09aa\u09be \u09a8\u0997\u09b0 \u0995\u09b2\u09cb\u09a8\u09c0"
    ],
    "name:ben_in_x_preferred":[
        "\u09aa\u09c1\u09b6\u09aa\u09be \u09a8\u0997\u09b0 \u0995\u09b2\u09cb\u09a8\u09c0"
    ],
    "name:eng_x_preferred":[
        "Pushpa Nagar Colony"
    ],
    "name:guj_x_preferred":[
        "\u0aaa\u0ac1\u0ab7\u0acd\u0aaa\u0abe \u0aa8\u0a97\u0ab0 \u0a95\u0acb\u0ab2\u0acb\u0aa8\u0ac0"
    ],
    "name:hin_x_preferred":[
        "\u092a\u0941\u0937\u094d\u092a\u093e \u0928\u0917\u0930 \u0915\u0949\u0932\u094b\u0928\u0940"
    ],
    "name:kan_x_preferred":[
        "\u0caa\u0cc1\u0cb7\u0ccd\u0caa\u0cbe \u0ca8\u0c97\u0cb0 \u0c95\u0cbe\u0cb2\u0cca\u0ca8\u0cbf"
    ],
    "name:mal_x_preferred":[
        "\u0d2a\u0d41\u0d37\u0d4d\u0d2a \u0d28\u0d17\u0d7c \u0d15\u0d4b\u0d33\u0d28\u0d3f"
    ],
    "name:mar_x_preferred":[
        "\u092a\u0941\u0937\u094d\u092a\u093e \u0928\u0917\u0930 \u0915\u0949\u0932\u0928\u0940"
    ],
    "name:pan_x_preferred":[
        "\u0a2a\u0a41\u0a36\u0a2a\u0a3e \u0a28\u0a17\u0a30 \u0a15\u0a3e\u0a32\u0a4c\u0a28\u0a40"
    ],
    "name:tam_x_preferred":[
        "\u0baa\u0bc1\u0bb7\u0bcd\u0baa\u0bbe \u0ba8\u0b95\u0bb0\u0bcd \u0b95\u0bc1\u0b9f\u0bbf\u0baf\u0bbf\u0bb0\u0bc1\u0baa\u0bcd\u0baa\u0bc1"
    ],
    "name:tel_x_preferred":[
        "\u0c2a\u0c41\u0c37\u0c4d\u0c2a\u0c3e \u0c28\u0c17\u0c30\u0c4d \u0c15\u0c3e\u0c32\u0c28\u0c40"
    ],
    "name:urd_x_preferred":[
        "\u067e\u0634\u067e \u0646\u06af\u0631 \u06a9\u0627\u0644\u0648\u0646\u06cc"
    ],
    "qs:gn_adm0_cc":"IN",
    "qs:gn_local":1254163,
    "qs:gn_nam_loc":"Thiruvananthapuram, Thiruvananthapuram, Kerala, IN",
    "qs:gn_namadm1":"13",
    "qs:local_max":394,
    "qs:local_sum":1454,
    "qs:localhoods":15,
    "qs:name":"Pushpa Nagar Colony",
    "qs:name_adm0":"India",
    "qs:name_adm1":"Kerala",
    "qs:name_adm2":"Thiruvananthapuram",
    "qs:name_local":"Thiruvananthapuram",
    "qs:photo_max":136,
    "qs:photo_sum":394,
    "qs:placetype":"Suburb",
    "qs:quad_count":17,
    "qs:woe_adm0":23424848,
    "qs:woe_adm1":2345747,
    "qs:woe_adm2":12586476,
    "qs:woe_lau":0,
    "qs:woe_local":2295426,
    "qs:woe_ver":"7.10.0",
    "wof:lang":[
        "eng"
    ],
    "wof:name":"Pushpa Nagar Colony",
    "wof:placetype":"neighbourhood"
},
  "geometry": {"coordinates":[76.951171,8.511761],"type":"Point"}
}