{
  "type": "Feature",
  "properties": {
    "gn:admin1_code":"35.0",
    "gn:admin2_code":"438.0",
    "gn:asciiname":"Teki",
    "gn:country_code":"IN",
    "gn:dem":192,
    "gn:feature_class":"P",
    "gn:feature_code":"PPL",
    "gn:name":"Teki",
    "gn:population":0,
    "gn:timezone":"Asia/Kolkata",
    "iso:country":"IN",
    "wof:name":"Teki",
    "wof:placetype":"locality"
},
  "geometry": {"coordinates":[74.88406999999999,22.25453],"type":"Point"}
}