{
  "type": "Feature",
  "properties": {
    "iso:country":"IN",
    "ks:ks_name":"Rajapur",
    "ks:ks_pop":425,
    "ks:ks_type":"HABITATION",
    "ks:ks_uagg_main":0,
    "name:eng_x_preferred":[
        "Rajapur"
    ],
    "wof:name":"Rajapur",
    "wof:placetype":"neighbourhood",
    "wof:population":425
},
  "geometry": {"coordinates":[80.97816,27.887383],"type":"Point"}
}