{
  "type": "Feature",
  "properties": {
    "iso:country":"IN",
    "ks:ks_alt_nam":"Jagabandhu para",
    "ks:ks_name":"Jagabandhu Para",
    "ks:ks_pop":495,
    "ks:ks_type":"HABITATION",
    "name:eng_x_preferred":[
        "Jagabandhu Para"
    ],
    "wof:name":"Jagabandhu Para",
    "wof:placetype":"locality",
    "wof:population":495
},
  "geometry": {"coordinates":[91.549633,23.065093],"type":"Point"}
}