{
  "type": "Feature",
  "properties": {
    "gn:admin1_code":"35",
    "gn:admin2_code":"435.0",
    "gn:asciiname":"Kharkana",
    "gn:country_code":"IN",
    "gn:dem":493,
    "gn:feature_class":"P",
    "gn:feature_code":"PPL",
    "gn:name":"Khark\u0101na",
    "gn:population":0,
    "gn:timezone":"Asia/Kolkata",
    "iso:country":"IN",
    "wof:name":"Kharkana",
    "wof:placetype":"neighbourhood"
},
  "geometry": {"coordinates":[75.40470999999999,23.1641],"type":"Point"}
}