{
  "type": "Feature",
  "properties": {
    "iso:country":"IN",
    "ks:ks_name":"Pipaldar",
    "ks:ks_pop":1765,
    "ks:ks_type":"VILLAGE",
    "ks:ks_uagg_main":0,
    "name:eng_x_preferred":[
        "Pipaldar"
    ],
    "wof:name":"Pipaldar",
    "wof:placetype":"neighbourhood",
    "wof:population":1765
},
  "geometry": {"coordinates":[72.72383000000001,23.76725],"type":"Point"}
}