{
  "type": "Feature",
  "properties": {
    "iso:country":"IN",
    "ks:ks_name":"Chhotkoi",
    "ks:ks_type":"VILLAGE",
    "name:eng_x_preferred":[
        "Chhotkoi"
    ],
    "wof:name":"Chhotkoi",
    "wof:placetype":"locality"
},
  "geometry": {"coordinates":[84.880578,20.634749],"type":"Point"}
}