{
  "type": "Feature",
  "properties": {
    "iso:country":"IN",
    "ks:ks_name":"Kusumput",
    "ks:ks_pop":47,
    "ks:ks_type":"VILLAGE",
    "name:eng_x_preferred":[
        "Kusumput"
    ],
    "wof:name":"Kusumput",
    "wof:placetype":"locality",
    "wof:population":47
},
  "geometry": {"coordinates":[82.974159,19.01156],"type":"Point"}
}