{
  "type": "Feature",
  "properties": {
    "iso:country":"IN",
    "ks:ks_name":"Mahupadar",
    "ks:ks_pop":300,
    "ks:ks_type":"HABITATION",
    "name:eng_x_preferred":[
        "Mahupadar"
    ],
    "wof:name":"Mahupadar",
    "wof:placetype":"locality",
    "wof:population":300
},
  "geometry": {"coordinates":[82.064911,18.306944],"type":"Point"}
}