{
  "type": "Feature",
  "properties": {
    "iso:country":"IN",
    "ks:ks_name":"Shettigudde",
    "ks:ks_pop":346,
    "ks:ks_type":"HABITATION",
    "name:eng_x_preferred":[
        "Shettigudde"
    ],
    "wof:name":"Shettigudde",
    "wof:placetype":"locality",
    "wof:population":346
},
  "geometry": {"coordinates":[74.904836,13.090746],"type":"Point"}
}