{
  "type": "Feature",
  "properties": {
    "gn:admin1_code":"36.0",
    "gn:admin2_code":"150.0",
    "gn:asciiname":"Birpur Makruka",
    "gn:country_code":"IN",
    "gn:dem":172,
    "gn:feature_class":"P",
    "gn:feature_code":"PPL",
    "gn:name":"B\u012brpur Makr\u016bka",
    "gn:population":0,
    "gn:timezone":"Asia/Kolkata",
    "iso:country":"IN",
    "ks:ks_alt_nam":"B\u012brpur Makr\u016bka",
    "ks:ks_name":"Birpur Makruka",
    "ks:ks_type":"VILLAGE",
    "name:eng_x_preferred":[
        "Birpur Makruka"
    ],
    "name:eng_x_variant":[
        "B\u012brpur Makr\u016bka"
    ],
    "wof:name":"Birpur Makruka",
    "wof:placetype":"locality"
},
  "geometry": {"coordinates":[79.381491,28.491269],"type":"Point"}
}