{
  "type": "Feature",
  "properties": {
    "iso:country":"IN",
    "ks:ks_alt_nam":"Baburi purwa",
    "ks:ks_name":"Baburi Purwa",
    "ks:ks_pop":97,
    "ks:ks_type":"HABITATION",
    "name:eng_x_preferred":[
        "Baburi Purwa"
    ],
    "wof:name":"Baburi Purwa",
    "wof:placetype":"locality",
    "wof:population":97
},
  "geometry": {"coordinates":[80.807962,27.778574],"type":"Point"}
}