{
  "type": "Feature",
  "properties": {
    "gn:admin1_code":"11",
    "gn:admin2_code":"25.0",
    "gn:asciiname":"Tumru",
    "gn:country_code":"IN",
    "gn:dem":2977,
    "gn:feature_class":"P",
    "gn:feature_code":"PPL",
    "gn:name":"Tumru",
    "gn:population":0,
    "gn:timezone":"Asia/Kolkata",
    "iso:country":"IN",
    "wof:name":"Tumru",
    "wof:placetype":"locality"
},
  "geometry": {"coordinates":[76.71155999999998,32.77289],"type":"Point"}
}