{
  "type": "Feature",
  "properties": {
    "gn:admin1_code":"37.0",
    "gn:admin2_code":"417.0",
    "gn:asciiname":"Gudipal",
    "gn:country_code":"IN",
    "gn:dem":216,
    "gn:feature_class":"P",
    "gn:feature_code":"PPL",
    "gn:name":"Gud\u012bp\u0101l",
    "gn:population":0,
    "gn:timezone":"Asia/Kolkata",
    "iso:country":"IN",
    "ks:ks_name":"Guddipal",
    "ks:ks_pop":343,
    "ks:ks_type":"VILLAGE",
    "name:eng_x_preferred":[
        "Guddipal"
    ],
    "name:eng_x_variant":[
        "Gudipal"
    ],
    "wof:name":"Guddipal",
    "wof:placetype":"locality",
    "wof:population":343
},
  "geometry": {"coordinates":[80.698846,18.831481],"type":"Point"}
}