{
  "type": "Feature",
  "properties": {
    "iso:country":"IN",
    "ks:ks_name":"Dakshin Kalinagar",
    "ks:ks_pop":0,
    "ks:ks_type":"VILLAGE",
    "name:eng_x_preferred":[
        "Dakshin Kalinagar"
    ],
    "wof:name":"Dakshin Kalinagar",
    "wof:placetype":"locality",
    "wof:population":0
},
  "geometry": {"coordinates":[88.090699,22.120275],"type":"Point"}
}