{
  "type": "Feature",
  "properties": {
    "iso:country":"IN",
    "ks:ks_name":"Pujaripara",
    "ks:ks_pop":643,
    "ks:ks_type":"HABITATION",
    "name:eng_x_preferred":[
        "Pujaripara"
    ],
    "wof:name":"Pujaripara",
    "wof:placetype":"locality",
    "wof:population":643
},
  "geometry": {"coordinates":[81.652297,19.049957],"type":"Point"}
}