{
  "type": "Feature",
  "properties": {
    "iso:country":"IN",
    "ks:ks_name":"M Madigapalle",
    "ks:ks_pop":321,
    "ks:ks_type":"HABITATION",
    "name:eng_x_preferred":[
        "M Madigapalle"
    ],
    "wof:name":"M Madigapalle",
    "wof:placetype":"locality",
    "wof:population":321
},
  "geometry": {"coordinates":[79.00493,13.926164],"type":"Point"}
}