{
  "type": "Feature",
  "properties": {
    "iso:country":"IN",
    "ks:ks_alt_nam":"PURNA CHANDRA PARA",
    "ks:ks_name":"Purna Chandra Para",
    "ks:ks_pop":465,
    "ks:ks_type":"HABITATION",
    "name:eng_x_preferred":[
        "Purna Chandra Para"
    ],
    "wof:name":"Purna Chandra Para",
    "wof:placetype":"locality",
    "wof:population":465
},
  "geometry": {"coordinates":[91.63603000000001,23.960177],"type":"Point"}
}