{
  "type": "Feature",
  "properties": {
    "gn:admin1_code":"35.0",
    "gn:admin2_code":"433",
    "gn:asciiname":"Kanwarpura",
    "gn:country_code":"IN",
    "gn:dem":434,
    "gn:feature_class":"P",
    "gn:feature_code":"PPL",
    "gn:name":"Kanwarpura",
    "gn:population":0,
    "gn:timezone":"Asia/Kolkata",
    "iso:country":"IN",
    "wof:name":"Kanwarpura",
    "wof:placetype":"locality"
},
  "geometry": {"coordinates":[75.70853000000002,24.53512000000001],"type":"Point"}
}