{
  "type": "Feature",
  "properties": {
    "iso:country":"IN",
    "ks:ks_name":"Ramgawan Biku",
    "ks:ks_pop":850,
    "ks:ks_type":"VILLAGE",
    "name:eng_x_preferred":[
        "Ramgawan Biku"
    ],
    "wof:name":"Ramgawan Biku",
    "wof:placetype":"locality",
    "wof:population":850
},
  "geometry": {"coordinates":[85.675657,25.614907],"type":"Point"}
}