{
  "type": "Feature",
  "properties": {
    "gn:admin1_code":"40",
    "gn:admin2_code":"538.0",
    "gn:asciiname":"Sangaipalle",
    "gn:country_code":"IN",
    "gn:dem":533,
    "gn:feature_class":"P",
    "gn:feature_code":"PPL",
    "gn:name":"Sang\u0101ipalle",
    "gn:population":0,
    "gn:timezone":"Asia/Kolkata",
    "iso:country":"IN",
    "wof:name":"Sangaipalle",
    "wof:placetype":"locality"
},
  "geometry": {"coordinates":[77.61187,17.03064],"type":"Point"}
}