{
  "type": "Feature",
  "properties": {
    "iso:country":"IN",
    "ks:ks_alt_nam":"M\u0101sekera",
    "ks:ks_name":"Masekera",
    "ks:ks_pop":210,
    "ks:ks_type":"VILLAGE",
    "name:eng_x_preferred":[
        "Masekera"
    ],
    "name:eng_x_variant":[
        "M\u0101sekera"
    ],
    "wof:name":"Masekera",
    "wof:placetype":"locality",
    "wof:population":210
},
  "geometry": {"coordinates":[84.339493,22.686889],"type":"Point"}
}