{
  "type": "Feature",
  "properties": {
    "iso:country":"IN",
    "ks:ks_name":"Kudarkhosa",
    "ks:ks_pop":258,
    "ks:ks_type":"HABITATION",
    "name:eng_x_preferred":[
        "Kudarkhosa"
    ],
    "wof:name":"Kudarkhosa",
    "wof:placetype":"locality",
    "wof:population":258
},
  "geometry": {"coordinates":[86.908136,24.563021],"type":"Point"}
}