{
  "type": "Feature",
  "properties": {
    "gn:admin1_code":"12.0",
    "gn:admin2_code":"17.0",
    "gn:asciiname":"Piristhan",
    "gn:country_code":"IN",
    "gn:dem":2214,
    "gn:feature_class":"P",
    "gn:feature_code":"PPL",
    "gn:name":"Piristh\u0101n",
    "gn:population":0,
    "gn:timezone":"Asia/Kolkata",
    "iso:country":"IN",
    "wof:name":"Piristhan",
    "wof:placetype":"locality"
},
  "geometry": {"coordinates":[75.33648000000002,33.31967],"type":"Point"}
}