{
  "type": "Feature",
  "properties": {
    "iso:country":"IN",
    "ks:ks_name":"Chhayan",
    "ks:ks_pop":435,
    "ks:ks_type":"VILLAGE",
    "name:eng_x_preferred":[
        "Chhayan"
    ],
    "wof:name":"Chhayan",
    "wof:placetype":"locality",
    "wof:population":435
},
  "geometry": {"coordinates":[74.701066,23.93062],"type":"Point"}
}