{
  "type": "Feature",
  "properties": {
    "iso:country":"IN",
    "ks:ks_name":"Kalarpara",
    "ks:ks_pop":60,
    "ks:ks_type":"HABITATION",
    "name:eng_x_preferred":[
        "Kalarpara"
    ],
    "wof:name":"Kalarpara",
    "wof:placetype":"locality",
    "wof:population":60
},
  "geometry": {"coordinates":[81.41963800000001,19.64046],"type":"Point"}
}