{
  "type": "Feature",
  "properties": {
    "gn:admin1_code":"39.0",
    "gn:admin2_code":"64.0",
    "gn:asciiname":"Malla Daud",
    "gn:country_code":"IN",
    "gn:dem":1337,
    "gn:feature_class":"P",
    "gn:feature_code":"PPL",
    "gn:name":"Malla Daud",
    "gn:population":0,
    "gn:timezone":"Asia/Kolkata",
    "iso:country":"IN",
    "wof:name":"Malla Daud",
    "wof:placetype":"locality"
},
  "geometry": {"coordinates":[79.34792,29.66815],"type":"Point"}
}