{
  "type": "Feature",
  "properties": {
    "gn:admin1_code":"39.0",
    "gn:admin2_code":"64.0",
    "gn:asciiname":"Malla Daud",
    "gn:country_code":"IN",
    "gn:dem":1337,
    "gn:feature_class":"P",
    "gn:feature_code":"PPL",
    "gn:name":"Malla Daud",
    "gn:population":0,
    "gn:timezone":"Asia/Kolkata",
    "iso:country":"IN",
    "ks:ks_name":"Talla Dauda",
    "ks:ks_pop":50,
    "ks:ks_type":"VILLAGE",
    "name:eng_x_preferred":[
        "Talla Dauda"
    ],
    "name:eng_x_variant":[
        "Malla Daud"
    ],
    "wof:name":"Talla Dauda",
    "wof:placetype":"locality",
    "wof:population":50
},
  "geometry": {"coordinates":[79.34816499999999,29.667474],"type":"Point"}
}