{
  "type": "Feature",
  "properties": {
    "gn:admin1_code":"2.0",
    "gn:admin2_code":"554",
    "gn:asciiname":"Kangundi",
    "gn:country_code":"IN",
    "gn:dem":690,
    "gn:feature_class":"P",
    "gn:feature_code":"PPL",
    "gn:name":"Kangundi",
    "gn:population":0,
    "gn:timezone":"Asia/Kolkata",
    "iso:country":"IN",
    "wof:name":"Kangundi",
    "wof:placetype":"locality"
},
  "geometry": {"coordinates":[78.43463,12.76945],"type":"Point"}
}