{
  "type": "Feature",
  "properties": {
    "gn:admin1_code":"37.0",
    "gn:admin2_code":"413.0",
    "gn:asciiname":"Dargahan",
    "gn:country_code":"IN",
    "gn:dem":364,
    "gn:feature_class":"P",
    "gn:feature_code":"PPL",
    "gn:name":"Dargahan",
    "gn:population":0,
    "gn:timezone":"Asia/Kolkata",
    "iso:country":"IN",
    "name:ara_x_preferred":[
        "\u062f\u0631\u0643\u0647\u0627\u0646"
    ],
    "name:aze_x_preferred":[
        "D\u0259rgahan"
    ],
    "name:ceb_x_preferred":[
        "Dargah\u0101n"
    ],
    "name:fas_x_preferred":[
        "\u062f\u0631\u06af\u0647\u0627\u0646"
    ],
    "name:ita_x_preferred":[
        "Dargahan"
    ],
    "name:mlg_x_preferred":[
        "Dargahan"
    ],
    "name:msa_x_preferred":[
        "Dargahan"
    ],
    "name:pol_x_preferred":[
        "Dargahan"
    ],
    "name:rus_x_preferred":[
        "\u0414\u0435\u0440\u0433\u0435\u0445\u0430\u043d"
    ],
    "name:swe_x_preferred":[
        "Dargah\u0101n"
    ],
    "name:tur_x_preferred":[
        "Dergahan"
    ],
    "name:zho_x_preferred":[
        "\u5fb7\u723e\u683c\u842c"
    ],
    "wof:name":"Dargahan",
    "wof:placetype":"locality"
},
  "geometry": {"coordinates":[81.36577,20.47957],"type":"Point"}
}