{
  "type": "Feature",
  "properties": {
    "iso:country":"IN",
    "ks:ks_name":"Kakramari",
    "ks:ks_pop":6750,
    "ks:ks_type":"URBAN",
    "ks:ks_uagg_main":0,
    "name:eng_x_preferred":[
        "Kakramari"
    ],
    "wof:name":"Kakramari",
    "wof:placetype":"neighbourhood",
    "wof:population":6750
},
  "geometry": {"coordinates":[88.062054,24.577085],"type":"Point"}
}