{
  "type": "Feature",
  "properties": {
    "gn:admin1_code":"12",
    "gn:admin2_code":"14.0",
    "gn:asciiname":"Naushahar",
    "gn:country_code":"IN",
    "gn:dem":1764,
    "gn:feature_class":"P",
    "gn:feature_code":"PPL",
    "gn:name":"Naushahar",
    "gn:population":0,
    "gn:timezone":"Asia/Kolkata",
    "iso:country":"IN",
    "wof:name":"Naushahar",
    "wof:placetype":"locality"
},
  "geometry": {"coordinates":[75.17779,33.84042],"type":"Point"}
}