{
  "type": "Feature",
  "properties": {
    "iso:country":"IN",
    "ks:ks_name":"Bajivago",
    "ks:ks_pop":214,
    "ks:ks_type":"HABITATION",
    "name:eng_x_preferred":[
        "Bajivago"
    ],
    "wof:name":"Bajivago",
    "wof:placetype":"locality",
    "wof:population":214
},
  "geometry": {"coordinates":[72.933167,22.413806],"type":"Point"}
}