{
  "type": "Feature",
  "properties": {
    "gn:admin1_code":"11.0",
    "gn:admin2_code":"27.0",
    "gn:asciiname":"Jwal",
    "gn:country_code":"IN",
    "gn:dem":1905,
    "gn:feature_class":"P",
    "gn:feature_code":"PPL",
    "gn:name":"Jw\u0101l",
    "gn:population":0,
    "gn:timezone":"Asia/Kolkata",
    "iso:country":"IN",
    "wof:name":"Jwal",
    "wof:placetype":"locality"
},
  "geometry": {"coordinates":[77.12864999999999,31.56201],"type":"Point"}
}