{
  "type": "Feature",
  "properties": {
    "iso:country":"IN",
    "ks:ks_alt_nam":"L\u0101kh\u0101pur",
    "ks:ks_name":"Lakhapur",
    "ks:ks_type":"VILLAGE",
    "name:eng_x_preferred":[
        "Lakhapur"
    ],
    "name:eng_x_variant":[
        "L\u0101kh\u0101pur"
    ],
    "wof:name":"Lakhapur",
    "wof:placetype":"locality"
},
  "geometry": {"coordinates":[74.321988,21.667834],"type":"Point"}
}