{
  "type": "Feature",
  "properties": {
    "gn:admin1_code":"37",
    "gn:admin2_code":"413.0",
    "gn:asciiname":"Bhandardiggi",
    "gn:country_code":"IN",
    "gn:dem":370,
    "gn:feature_class":"P",
    "gn:feature_code":"PPL",
    "gn:name":"Bhand\u0101rdiggi",
    "gn:population":0,
    "gn:timezone":"Asia/Kolkata",
    "iso:country":"IN",
    "ks:ks_name":"Bhandardigi",
    "ks:ks_pop":722,
    "ks:ks_type":"HABITATION",
    "name:eng_x_preferred":[
        "Bhandardigi"
    ],
    "name:eng_x_variant":[
        "Bhandardiggi"
    ],
    "wof:name":"Bhandardigi",
    "wof:placetype":"locality",
    "wof:population":722
},
  "geometry": {"coordinates":[80.958259,20.240964],"type":"Point"}
}