{
  "type": "Feature",
  "properties": {
    "iso:country":"IN",
    "ks:ks_name":"Guwara Pakhal",
    "ks:ks_pop":132,
    "ks:ks_type":"HABITATION",
    "name:eng_x_preferred":[
        "Guwara Pakhal"
    ],
    "wof:name":"Guwara Pakhal",
    "wof:placetype":"locality",
    "wof:population":132
},
  "geometry": {"coordinates":[76.291389,27.215],"type":"Point"}
}