{
  "type": "Feature",
  "properties": {
    "iso:country":"IN",
    "ks:ks_name":"Damodarpura",
    "ks:ks_pop":180,
    "ks:ks_type":"VILLAGE",
    "name:eng_x_preferred":[
        "Damodarpura"
    ],
    "wof:name":"Damodarpura",
    "wof:placetype":"locality",
    "wof:population":180
},
  "geometry": {"coordinates":[75.86826600000001,24.875627],"type":"Point"}
}