{
  "type": "Feature",
  "properties": {
    "gn:admin1_code":"36.0",
    "gn:admin2_code":"165.0",
    "gn:asciiname":"Gayar",
    "gn:country_code":"IN",
    "gn:dem":145,
    "gn:feature_class":"P",
    "gn:feature_code":"PPL",
    "gn:name":"G\u0101yar",
    "gn:population":0,
    "gn:timezone":"Asia/Kolkata",
    "iso:country":"IN",
    "wof:name":"Gayar",
    "wof:placetype":"locality"
},
  "geometry": {"coordinates":[79.34928000000002,26.08819],"type":"Point"}
}