{
  "type": "Feature",
  "properties": {
    "gn:admin1_code":"36",
    "gn:admin2_code":"200.0",
    "gn:asciiname":"Dhankhur",
    "gn:country_code":"IN",
    "gn:dem":373,
    "gn:feature_class":"P",
    "gn:feature_code":"PPL",
    "gn:name":"Dhankhur",
    "gn:population":0,
    "gn:timezone":"Asia/Kolkata",
    "iso:country":"IN",
    "ks:ks_name":"Dhankhor",
    "ks:ks_pop":1053,
    "ks:ks_type":"VILLAGE",
    "name:eng_x_preferred":[
        "Dhankhor"
    ],
    "name:eng_x_variant":[
        "Dhankhur"
    ],
    "wof:name":"Dhankhor",
    "wof:placetype":"locality",
    "wof:population":1053
},
  "geometry": {"coordinates":[83.160443,24.03192],"type":"Point"}
}