{
  "type": "Feature",
  "properties": {
    "iso:country":"IN",
    "ks:ks_name":"Bharouli",
    "ks:ks_pop":1288,
    "ks:ks_type":"VILLAGE",
    "ks:ks_uagg_main":0,
    "name:eng_x_preferred":[
        "Bharouli"
    ],
    "wof:name":"Bharouli",
    "wof:placetype":"neighbourhood",
    "wof:population":1288
},
  "geometry": {"coordinates":[83.886231,26.384211],"type":"Point"}
}