{
  "type": "Feature",
  "properties": {
    "iso:country":"IN",
    "ks:ks_name":"Katkarwadi",
    "ks:ks_pop":79,
    "ks:ks_type":"HABITATION",
    "name:eng_x_preferred":[
        "Katkarwadi"
    ],
    "wof:name":"Katkarwadi",
    "wof:placetype":"locality",
    "wof:population":79
},
  "geometry": {"coordinates":[73.364042,17.928456],"type":"Point"}
}