{
  "type": "Feature",
  "properties": {
    "iso:country":"IN",
    "ks:ks_name":"Mahulposi",
    "ks:ks_pop":261,
    "ks:ks_type":"HABITATION",
    "name:eng_x_preferred":[
        "Mahulposi"
    ],
    "wof:name":"Mahulposi",
    "wof:placetype":"locality",
    "wof:population":261
},
  "geometry": {"coordinates":[86.048321,21.199176],"type":"Point"}
}