{
  "type": "Feature",
  "properties": {
    "iso:country":"IN",
    "ks:ks_alt_nam":"Major Chapori N.C.",
    "ks:ks_name":"Major Chapori N.c.",
    "ks:ks_pop":561,
    "ks:ks_type":"HABITATION",
    "name:eng_x_preferred":[
        "Major Chapori N.c."
    ],
    "wof:name":"Major Chapori N.c.",
    "wof:placetype":"locality",
    "wof:population":561
},
  "geometry": {"coordinates":[94.230447,27.116874],"type":"Point"}
}