{
  "type": "Feature",
  "properties": {
    "iso:country":"IN",
    "ks:ks_name":"Baramasia",
    "ks:ks_pop":429,
    "ks:ks_type":"VILLAGE",
    "ks:ks_uagg_main":0,
    "name:eng_x_preferred":[
        "Baramasia"
    ],
    "wof:name":"Baramasia",
    "wof:placetype":"neighbourhood",
    "wof:population":429
},
  "geometry": {"coordinates":[86.93922499999999,24.153859],"type":"Point"}
}