{
  "type": "Feature",
  "properties": {
    "iso:country":"IN",
    "ks:ks_alt_nam":"Tippa Girijana colony",
    "ks:ks_name":"Tippa Girijana Colony",
    "ks:ks_pop":449,
    "ks:ks_type":"HABITATION",
    "ks:ks_uagg_main":0,
    "name:eng_x_preferred":[
        "Tippa Girijana Colony"
    ],
    "wof:name":"Tippa Girijana Colony",
    "wof:placetype":"neighbourhood",
    "wof:population":449
},
  "geometry": {"coordinates":[79.668695,14.83299],"type":"Point"}
}