{
  "type": "Feature",
  "properties": {
    "iso:country":"IN",
    "ks:ks_name":"Sialikudar",
    "ks:ks_pop":0,
    "ks:ks_type":"VILLAGE",
    "name:eng_x_preferred":[
        "Sialikudar"
    ],
    "wof:name":"Sialikudar",
    "wof:placetype":"locality",
    "wof:population":0
},
  "geometry": {"coordinates":[84.846358,21.900784],"type":"Point"}
}