{
  "type": "Feature",
  "properties": {
    "iso:country":"IN",
    "ks:ks_alt_nam":"nellikkunnu",
    "ks:ks_name":"Nellikkunnu",
    "ks:ks_pop":2094,
    "ks:ks_type":"HABITATION",
    "name:eng_x_preferred":[
        "Nellikkunnu"
    ],
    "wof:name":"Nellikkunnu",
    "wof:placetype":"locality",
    "wof:population":2094
},
  "geometry": {"coordinates":[75.4008,12.4722],"type":"Point"}
}