{
  "type": "Feature",
  "properties": {
    "gn:admin1_code":"25.0",
    "gn:admin2_code":"620.0",
    "gn:asciiname":"Tirumangalakkottai Melaiyur",
    "gn:country_code":"IN",
    "gn:dem":29,
    "gn:feature_class":"P",
    "gn:feature_code":"PPL",
    "gn:name":"Tirumangalakkottai Melaiy\u016br",
    "gn:population":0,
    "gn:timezone":"Asia/Kolkata",
    "iso:country":"IN",
    "wof:name":"Tirumangalakkottai Melaiyur",
    "wof:placetype":"locality"
},
  "geometry": {"coordinates":[79.32240999999998,10.59024],"type":"Point"}
}