{
  "type": "Feature",
  "properties": {
    "iso:country":"IN",
    "ks:ks_alt_nam":"Road Continues To four Km",
    "ks:ks_name":"Road Continues To Four Km",
    "ks:ks_pop":710,
    "ks:ks_type":"HABITATION",
    "ks:ks_uagg_main":0,
    "name:eng_x_preferred":[
        "Road Continues To Four Km"
    ],
    "wof:name":"Road Continues To Four Km",
    "wof:placetype":"neighbourhood",
    "wof:population":710
},
  "geometry": {"coordinates":[76.291217,11.121798],"type":"Point"}
}