{
  "type": "Feature",
  "properties": {
    "iso:country":"IN",
    "ks:ks_name":"Daiwadi",
    "ks:ks_pop":8,
    "ks:ks_type":"HABITATION",
    "name:eng_x_preferred":[
        "Daiwadi"
    ],
    "wof:name":"Daiwadi",
    "wof:placetype":"locality",
    "wof:population":8
},
  "geometry": {"coordinates":[78.26208099999999,21.505011],"type":"Point"}
}