{
  "type": "Feature",
  "properties": {
    "iso:country":"IN",
    "ks:ks_name":"Bandho",
    "ks:ks_pop":30,
    "ks:ks_type":"HABITATION",
    "name:eng_x_preferred":[
        "Bandho"
    ],
    "wof:name":"Bandho",
    "wof:placetype":"locality",
    "wof:population":30
},
  "geometry": {"coordinates":[68.812181,23.289939],"type":"Point"}
}