{
  "type": "Feature",
  "properties": {
    "iso:country":"IN",
    "ks:ks_alt_nam":"Hathesingh ni muvadi",
    "ks:ks_name":"Hathesingh Ni Muvadi",
    "ks:ks_pop":200,
    "ks:ks_type":"HABITATION",
    "ks:ks_uagg_main":0,
    "name:eng_x_preferred":[
        "Hathesingh Ni Muvadi"
    ],
    "wof:name":"Hathesingh Ni Muvadi",
    "wof:placetype":"neighbourhood",
    "wof:population":200
},
  "geometry": {"coordinates":[73.39607100000001,22.726101],"type":"Point"}
}