{
  "type": "Feature",
  "properties": {
    "iso:country":"IN",
    "ks:ks_name":"Parredora",
    "ks:ks_pop":75,
    "ks:ks_type":"HABITATION",
    "name:eng_x_preferred":[
        "Parredora"
    ],
    "wof:name":"Parredora",
    "wof:placetype":"locality",
    "wof:population":75
},
  "geometry": {"coordinates":[81.661902,20.16299],"type":"Point"}
}