{
  "type": "Feature",
  "properties": {
    "gn:admin1_code":"25.0",
    "gn:admin2_code":"610.0",
    "gn:asciiname":"Nanjundapuram",
    "gn:country_code":"IN",
    "gn:dem":263,
    "gn:feature_class":"P",
    "gn:feature_code":"PPL",
    "gn:name":"Nanjundapuram",
    "gn:population":0,
    "gn:timezone":"Asia/Kolkata",
    "iso:country":"IN",
    "ks:ks_name":"Nanjundapuram",
    "ks:ks_pop":216,
    "ks:ks_type":"HABITATION",
    "name:eng_x_preferred":[
        "Nanjundapuram"
    ],
    "wof:name":"Nanjundapuram",
    "wof:placetype":"locality",
    "wof:population":216
},
  "geometry": {"coordinates":[77.522582,11.150665],"type":"Point"}
}