{
  "type": "Feature",
  "properties": {
    "iso:country":"IN",
    "ks:ks_alt_nam":"JALDATOLA",
    "ks:ks_name":"Jaldatola",
    "ks:ks_pop":244,
    "ks:ks_type":"HABITATION",
    "name:eng_x_preferred":[
        "Jaldatola"
    ],
    "wof:name":"Jaldatola",
    "wof:placetype":"locality",
    "wof:population":244
},
  "geometry": {"coordinates":[81.988741,23.032938],"type":"Point"}
}