{
  "type": "Feature",
  "properties": {
    "iso:country":"IN",
    "ks:ks_alt_nam":"Barsi falia",
    "ks:ks_name":"Barsi Falia",
    "ks:ks_pop":526,
    "ks:ks_type":"HABITATION",
    "name:eng_x_preferred":[
        "Barsi Falia"
    ],
    "wof:name":"Barsi Falia",
    "wof:placetype":"locality",
    "wof:population":526
},
  "geometry": {"coordinates":[73.317949,21.192003],"type":"Point"}
}