{
  "type": "Feature",
  "properties": {
    "iso:country":"IN",
    "ks:ks_name":"Saidpur",
    "ks:ks_type":"VILLAGE",
    "name:eng_x_preferred":[
        "Saidpur"
    ],
    "wof:name":"Saidpur",
    "wof:placetype":"locality"
},
  "geometry": {"coordinates":[82.633188,27.165031],"type":"Point"}
}