{
  "type": "Feature",
  "properties": {
    "iso:country":"IN",
    "ks:ks_name":"Joshpur",
    "ks:ks_pop":307,
    "ks:ks_type":"HABITATION",
    "ks:ks_uagg_main":0,
    "name:eng_x_preferred":[
        "Joshpur"
    ],
    "wof:name":"Joshpur",
    "wof:placetype":"neighbourhood",
    "wof:population":307
},
  "geometry": {"coordinates":[87.052359,22.493464],"type":"Point"}
}