{
  "type": "Feature",
  "properties": {
    "iso:country":"IN",
    "ks:ks_name":"Sarai Ryt",
    "ks:ks_pop":334,
    "ks:ks_type":"HABITATION",
    "name:eng_x_preferred":[
        "Sarai Ryt"
    ],
    "wof:name":"Sarai Ryt",
    "wof:placetype":"locality",
    "wof:population":334
},
  "geometry": {"coordinates":[80.922562,22.436078],"type":"Point"}
}