{
  "type": "Feature",
  "properties": {
    "iso:country":"IN",
    "ks:ks_alt_nam":"Gh\u0101gi",
    "ks:ks_name":"Ghagi",
    "ks:ks_pop":1028,
    "ks:ks_type":"VILLAGE",
    "name:eng_x_preferred":[
        "Ghagi"
    ],
    "name:eng_x_variant":[
        "Gh\u0101gi"
    ],
    "wof:name":"Ghagi",
    "wof:placetype":"locality",
    "wof:population":1028
},
  "geometry": {"coordinates":[85.869221,21.849387],"type":"Point"}
}