{
  "type": "Feature",
  "properties": {
    "iso:country":"IN",
    "ks:ks_name":"Karibil Nepali",
    "ks:ks_pop":1720,
    "ks:ks_type":"VILLAGE",
    "ks:ks_uagg_main":0,
    "name:eng_x_preferred":[
        "Karibil Nepali"
    ],
    "wof:name":"Karibil Nepali",
    "wof:placetype":"neighbourhood",
    "wof:population":1720
},
  "geometry": {"coordinates":[93.442187,26.891607],"type":"Point"}
}