{
  "type": "Feature",
  "properties": {
    "iso:country":"IN",
    "ks:ks_name":"Thundathur",
    "ks:ks_pop":115,
    "ks:ks_type":"HABITATION",
    "name:eng_x_preferred":[
        "Thundathur"
    ],
    "wof:name":"Thundathur",
    "wof:placetype":"locality",
    "wof:population":115
},
  "geometry": {"coordinates":[79.552325,10.78302],"type":"Point"}
}