{
  "type": "Feature",
  "properties": {
    "iso:country":"IN",
    "ks:ks_name":"Pinjoli Walli",
    "ks:ks_pop":107,
    "ks:ks_type":"VILLAGE",
    "name:eng_x_preferred":[
        "Pinjoli Walli"
    ],
    "wof:name":"Pinjoli Walli",
    "wof:placetype":"locality",
    "wof:population":107
},
  "geometry": {"coordinates":[79.10996400000001,29.710857],"type":"Point"}
}