{
  "type": "Feature",
  "properties": {
    "iso:country":"IN",
    "ks:ks_name":"Kanchotiya",
    "ks:ks_pop":261,
    "ks:ks_type":"HABITATION",
    "name:eng_x_preferred":[
        "Kanchotiya"
    ],
    "wof:name":"Kanchotiya",
    "wof:placetype":"locality",
    "wof:population":261
},
  "geometry": {"coordinates":[71.942111,21.735028],"type":"Point"}
}