{
  "type": "Feature",
  "properties": {
    "gn:admin1_code":"19.0",
    "gn:admin2_code":"581.0",
    "gn:asciiname":"Naravamakalapalli",
    "gn:country_code":"IN",
    "gn:dem":842,
    "gn:feature_class":"P",
    "gn:feature_code":"PPL",
    "gn:name":"N\u0101ravam\u0101kalapalli",
    "gn:population":0,
    "gn:timezone":"Asia/Kolkata",
    "iso:country":"IN",
    "wof:name":"Naravamakalapalli",
    "wof:placetype":"locality"
},
  "geometry": {"coordinates":[78.27763,13.40561],"type":"Point"}
}