{
  "type": "Feature",
  "properties": {
    "gn:admin1_code":"10",
    "gn:admin2_code":"70.0",
    "gn:asciiname":"Ratangarh",
    "gn:country_code":"IN",
    "gn:dem":270,
    "gn:feature_class":"P",
    "gn:feature_code":"PPL",
    "gn:name":"Ratangarh",
    "gn:population":0,
    "gn:timezone":"Asia/Kolkata",
    "iso:country":"IN",
    "name:ben_x_preferred":[
        "\u09b0\u09a4\u09a8\u0997\u09a1\u09bc"
    ],
    "name:bpy_x_preferred":[
        "\u09b0\u09a4\u09a8\u0997\u09a1\u09bc"
    ],
    "name:ceb_x_preferred":[
        "Ratangarh"
    ],
    "name:deu_x_preferred":[
        "Ratangarh"
    ],
    "name:hin_x_preferred":[
        "\u0930\u0924\u0928\u0917\u0922\u093c"
    ],
    "name:por_x_preferred":[
        "Ratangarh"
    ],
    "name:swe_x_preferred":[
        "Ratangarh"
    ],
    "wof:name":"Ratangarh",
    "wof:placetype":"locality"
},
  "geometry": {"coordinates":[76.77058,30.36068],"type":"Point"}
}