{
  "type": "Feature",
  "properties": {
    "iso:country":"IN",
    "ks:ks_name":"Mahulbani 2",
    "ks:ks_pop":33,
    "ks:ks_type":"HABITATION",
    "name:eng_x_preferred":[
        "Mahulbani 2"
    ],
    "wof:name":"Mahulbani 2",
    "wof:placetype":"locality",
    "wof:population":33
},
  "geometry": {"coordinates":[87.080912,22.549444],"type":"Point"}
}