{
  "type": "Feature",
  "properties": {
    "iso:country":"IN",
    "ks:ks_name":"Makrikhoh",
    "ks:ks_pop":841,
    "ks:ks_type":"VILLAGE",
    "name:eng_x_preferred":[
        "Makrikhoh"
    ],
    "wof:name":"Makrikhoh",
    "wof:placetype":"locality",
    "wof:population":841
},
  "geometry": {"coordinates":[83.5213,24.934153],"type":"Point"}
}