{
  "type": "Feature",
  "properties": {
    "iso:country":"IN",
    "ks:ks_name":"Maje Bari Fv",
    "ks:ks_pop":128,
    "ks:ks_type":"HABITATION",
    "name:eng_x_preferred":[
        "Maje Bari Fv"
    ],
    "wof:name":"Maje Bari Fv",
    "wof:placetype":"locality",
    "wof:population":128
},
  "geometry": {"coordinates":[91.343273,26.006026],"type":"Point"}
}