{
  "type": "Feature",
  "properties": {
    "iso:country":"IN",
    "ks:ks_alt_nam":"CHAVAN VASTI",
    "ks:ks_name":"Chavan Vasti",
    "ks:ks_pop":77,
    "ks:ks_type":"HABITATION",
    "name:eng_x_preferred":[
        "Chavan Vasti"
    ],
    "wof:name":"Chavan Vasti",
    "wof:placetype":"locality",
    "wof:population":77
},
  "geometry": {"coordinates":[75.490116,17.204897],"type":"Point"}
}