{
  "type": "Feature",
  "properties": {
    "gn:admin1_code":"24.0",
    "gn:admin2_code":"104.0",
    "gn:asciiname":"Hanspur Kalan",
    "gn:country_code":"IN",
    "gn:dem":293,
    "gn:feature_class":"P",
    "gn:feature_code":"PPL",
    "gn:name":"H\u0101nspur Kal\u0101n",
    "gn:population":0,
    "gn:timezone":"Asia/Kolkata",
    "iso:country":"IN",
    "wof:name":"Hanspur Kalan",
    "wof:placetype":"locality"
},
  "geometry": {"coordinates":[76.60953000000001,27.83489],"type":"Point"}
}