{
  "type": "Feature",
  "properties": {
    "gn:admin1_code":"10.0",
    "gn:admin2_code":"77.0",
    "gn:asciiname":"Pathri",
    "gn:country_code":"IN",
    "gn:dem":230,
    "gn:feature_class":"P",
    "gn:feature_code":"PPL",
    "gn:name":"Pathri",
    "gn:population":0,
    "gn:timezone":"Asia/Kolkata",
    "iso:country":"IN",
    "name:ben_x_preferred":[
        "\u09aa\u09be\u09a5\u09be\u09b0\u09bf"
    ],
    "name:bpy_x_preferred":[
        "\u09aa\u09be\u09a5\u09be\u09b0\u09bf"
    ],
    "name:ceb_x_preferred":[
        "P\u0101thri"
    ],
    "name:hif_x_preferred":[
        "Pathri"
    ],
    "name:ita_x_preferred":[
        "Pathri"
    ],
    "name:msa_x_preferred":[
        "Pathri"
    ],
    "name:nld_x_preferred":[
        "Pathri"
    ],
    "name:ori_x_preferred":[
        "\u0b2a\u0b3e\u0b25\u0b30\u0b3f"
    ],
    "name:por_x_preferred":[
        "Pathri"
    ],
    "name:swe_x_preferred":[
        "P\u0101thri"
    ],
    "name:und_x_variant":[
        "Lakhm\u012brw\u0101la"
    ],
    "name:urd_x_preferred":[
        "\u067e\u0627\u062a\u06be\u0631\u06cc"
    ],
    "name:vie_x_preferred":[
        "Pathri"
    ],
    "name:zho_x_preferred":[
        "\u5e15\u7279\u91cc"
    ],
    "wof:name":"Pathri",
    "wof:placetype":"neighbourhood"
},
  "geometry": {"coordinates":[76.38955,29.32833],"type":"Point"}
}