{
  "type": "Feature",
  "properties": {
    "iso:country":"IN",
    "ks:ks_name":"Bidyadharpur",
    "ks:ks_pop":293,
    "ks:ks_type":"VILLAGE",
    "ks:ks_uagg_main":0,
    "name:eng_x_preferred":[
        "Bidyadharpur"
    ],
    "wof:name":"Bidyadharpur",
    "wof:placetype":"neighbourhood",
    "wof:population":293
},
  "geometry": {"coordinates":[86.248955,20.573548],"type":"Point"}
}