{
  "type": "Feature",
  "properties": {
    "iso:country":"IN",
    "ks:ks_name":"Mahalaxmi Devsthan",
    "ks:ks_pop":300,
    "ks:ks_type":"HABITATION",
    "name:eng_x_preferred":[
        "Mahalaxmi Devsthan"
    ],
    "wof:name":"Mahalaxmi Devsthan",
    "wof:placetype":"locality",
    "wof:population":300
},
  "geometry": {"coordinates":[74.938564,17.664249],"type":"Point"}
}