{
  "type": "Feature",
  "properties": {
    "gn:admin1_code":"39",
    "gn:admin2_code":"61.0",
    "gn:asciiname":"Kamraneon",
    "gn:country_code":"IN",
    "gn:dem":950,
    "gn:feature_class":"P",
    "gn:feature_code":"PPL",
    "gn:name":"Kamr\u0101neon",
    "gn:population":0,
    "gn:timezone":"Asia/Kolkata",
    "iso:country":"IN",
    "wof:name":"Kamraneon",
    "wof:placetype":"locality"
},
  "geometry": {"coordinates":[78.84439,30.22676],"type":"Point"}
}