{
  "type": "Feature",
  "properties": {
    "iso:country":"IN",
    "ks:ks_alt_nam":"AMTALA",
    "ks:ks_name":"Amtala",
    "ks:ks_pop":586,
    "ks:ks_type":"HABITATION",
    "name:eng_x_preferred":[
        "Amtala"
    ],
    "wof:name":"Amtala",
    "wof:placetype":"locality",
    "wof:population":586
},
  "geometry": {"coordinates":[92.34775399999999,24.358313],"type":"Point"}
}