{
  "type": "Feature",
  "properties": {
    "gn:admin1_code":"36.0",
    "gn:admin2_code":"185.0",
    "gn:asciiname":"Malpura",
    "gn:country_code":"IN",
    "gn:dem":94,
    "gn:feature_class":"P",
    "gn:feature_code":"PPL",
    "gn:name":"Malpura",
    "gn:population":0,
    "gn:timezone":"Asia/Kolkata",
    "iso:country":"IN",
    "ks:ks_name":"Malpurwa",
    "ks:ks_pop":432,
    "ks:ks_type":"HABITATION",
    "name:ben_x_preferred":[
        "\u09ae\u09be\u09b2\u09aa\u09c1\u09b0\u09be"
    ],
    "name:bpy_x_preferred":[
        "\u09ae\u09be\u09b2\u09aa\u09c1\u09b0\u09be"
    ],
    "name:ceb_x_preferred":[
        "M\u0101lpura"
    ],
    "name:eng_x_preferred":[
        "Malpurwa"
    ],
    "name:eng_x_variant":[
        "Malpura"
    ],
    "name:hin_x_preferred":[
        "\u092e\u093e\u0932\u092a\u0941\u0930\u093e"
    ],
    "name:ita_x_preferred":[
        "Malpura"
    ],
    "name:mlg_x_preferred":[
        "Malpura"
    ],
    "name:msa_x_preferred":[
        "Malpura"
    ],
    "name:new_x_preferred":[
        "\u092e\u0932\u094d\u092a\u0941\u0930\u093e"
    ],
    "name:ori_x_preferred":[
        "\u0b2e\u0b3e\u0b32\u0b4d\u200c\u0b2a\u0b41\u0b30\u0b3e"
    ],
    "name:por_x_preferred":[
        "Malpura"
    ],
    "name:swe_x_preferred":[
        "M\u0101lpura"
    ],
    "name:urd_x_preferred":[
        "\u0645\u0627\u0644\u067e\u0648\u0631\u06c1"
    ],
    "name:vie_x_preferred":[
        "Malpura"
    ],
    "name:zho_x_preferred":[
        "\u9a6c\u5c14\u666e\u62c9"
    ],
    "wof:name":"Malpurwa",
    "wof:placetype":"locality",
    "wof:population":432
},
  "geometry": {"coordinates":[82.664924,27.046668],"type":"Point"}
}