{
  "type": "Feature",
  "properties": {
    "iso:country":"IN",
    "ks:ks_name":"Bellavi Plantation",
    "ks:ks_pop":18,
    "ks:ks_type":"HABITATION",
    "name:eng_x_preferred":[
        "Bellavi Plantation"
    ],
    "wof:name":"Bellavi Plantation",
    "wof:placetype":"locality",
    "wof:population":18
},
  "geometry": {"coordinates":[77.917839,13.049695],"type":"Point"}
}