{
  "type": "Feature",
  "properties": {
    "gn:admin1_code":"38",
    "gn:admin2_code":"358.0",
    "gn:asciiname":"Pachghara Khurd",
    "gn:country_code":"IN",
    "gn:dem":234,
    "gn:feature_class":"P",
    "gn:feature_code":"PPL",
    "gn:name":"Pachgh\u0101ra Khurd",
    "gn:population":0,
    "gn:timezone":"Asia/Kolkata",
    "iso:country":"IN",
    "ks:ks_alt_nam":"Pachgh\u0101ra Khurd",
    "ks:ks_name":"Pachghara Khurd",
    "ks:ks_type":"VILLAGE",
    "name:eng_x_preferred":[
        "Pachghara Khurd"
    ],
    "name:eng_x_variant":[
        "Pachgh\u0101ra Khurd"
    ],
    "wof:name":"Pachghara Khurd",
    "wof:placetype":"locality"
},
  "geometry": {"coordinates":[83.95389900000001,24.243403],"type":"Point"}
}