{
  "type": "Feature",
  "properties": {
    "iso:country":"IN",
    "ks:ks_name":"Lalki Damar",
    "ks:ks_pop":193,
    "ks:ks_type":"HABITATION",
    "name:eng_x_preferred":[
        "Lalki Damar"
    ],
    "wof:name":"Lalki Damar",
    "wof:placetype":"locality",
    "wof:population":193
},
  "geometry": {"coordinates":[82.813711,24.573831],"type":"Point"}
}