{
  "type": "Feature",
  "properties": {
    "iso:country":"IN",
    "ks:ks_name":"Gavalibadiya",
    "ks:ks_pop":130,
    "ks:ks_type":"HABITATION",
    "name:eng_x_preferred":[
        "Gavalibadiya"
    ],
    "wof:name":"Gavalibadiya",
    "wof:placetype":"locality",
    "wof:population":130
},
  "geometry": {"coordinates":[74.22431899999999,26.132819],"type":"Point"}
}