{
  "type": "Feature",
  "properties": {
    "iso:country":"IN",
    "ks:ks_alt_nam":"P\u0101ndepur",
    "ks:ks_name":"Pandepur",
    "ks:ks_type":"VILLAGE",
    "name:eng_x_preferred":[
        "Pandepur"
    ],
    "name:eng_x_variant":[
        "P\u0101ndepur"
    ],
    "wof:name":"Pandepur",
    "wof:placetype":"locality"
},
  "geometry": {"coordinates":[83.58801699999999,25.354725],"type":"Point"}
}