{
  "type": "Feature",
  "properties": {
    "iso:country":"IN",
    "ks:ks_name":"Ledimahul",
    "ks:ks_type":"VILLAGE",
    "name:eng_x_preferred":[
        "Ledimahul"
    ],
    "wof:name":"Ledimahul",
    "wof:placetype":"locality"
},
  "geometry": {"coordinates":[84.29215000000001,21.54846],"type":"Point"}
}