{
  "type": "Feature",
  "properties": {
    "iso:country":"IN",
    "ks:ks_alt_nam":"D. CHAKOLA TOLA",
    "ks:ks_name":"D. Chakola Tola",
    "ks:ks_pop":819,
    "ks:ks_type":"HABITATION",
    "name:eng_x_preferred":[
        "D. Chakola Tola"
    ],
    "wof:name":"D. Chakola Tola",
    "wof:placetype":"locality",
    "wof:population":819
},
  "geometry": {"coordinates":[86.583626,26.158973],"type":"Point"}
}