{
  "type": "Feature",
  "properties": {
    "iso:country":"IN",
    "ks:ks_name":"Kindangi",
    "ks:ks_pop":161,
    "ks:ks_type":"VILLAGE",
    "name:eng_x_preferred":[
        "Kindangi"
    ],
    "wof:name":"Kindangi",
    "wof:placetype":"locality",
    "wof:population":161
},
  "geometry": {"coordinates":[82.227203,17.755278],"type":"Point"}
}