{
  "type": "Feature",
  "properties": {
    "iso:country":"IN",
    "ks:ks_name":"Chak Nabasan",
    "ks:ks_pop":2473,
    "ks:ks_type":"VILLAGE",
    "ks:ks_uagg_main":0,
    "name:eng_x_preferred":[
        "Chak Nabasan"
    ],
    "wof:name":"Chak Nabasan",
    "wof:placetype":"locality",
    "wof:population":2473
},
  "geometry": {"coordinates":[88.211141,22.484571],"type":"Point"}
}