{
  "type": "Feature",
  "properties": {
    "iso:country":"IN",
    "ks:ks_alt_nam":"Holi falia",
    "ks:ks_name":"Holi Falia",
    "ks:ks_pop":148,
    "ks:ks_type":"HABITATION",
    "name:eng_x_preferred":[
        "Holi Falia"
    ],
    "wof:name":"Holi Falia",
    "wof:placetype":"locality",
    "wof:population":148
},
  "geometry": {"coordinates":[74.36111099999999,22.711167],"type":"Point"}
}