{
  "type": "Feature",
  "properties": {
    "gn:admin1_code":"13.0",
    "gn:admin2_code":"598.0",
    "gn:asciiname":"Kodukulanji",
    "gn:country_code":"IN",
    "gn:dem":12,
    "gn:feature_class":"P",
    "gn:feature_code":"PPL",
    "gn:name":"Kodukulanji",
    "gn:population":0,
    "gn:timezone":"Asia/Kolkata",
    "iso:country":"IN",
    "name:mal_x_preferred":[
        "\u0d15\u0d4b\u0d1f\u0d41\u0d15\u0d41\u0d33\u0d1e\u0d4d\u0d1e\u0d3f"
    ],
    "wof:name":"Kodukulanji",
    "wof:placetype":"locality"
},
  "geometry": {"coordinates":[76.61123000000001,9.26947],"type":"Point"}
}