{
  "type": "Feature",
  "properties": {
    "gn:admin1_code":"36",
    "gn:admin2_code":"160.0",
    "gn:asciiname":"Sakhauli",
    "gn:country_code":"IN",
    "gn:dem":141,
    "gn:feature_class":"P",
    "gn:feature_code":"PPL",
    "gn:name":"Sakhauli",
    "gn:population":0,
    "gn:timezone":"Asia/Kolkata",
    "iso:country":"IN",
    "ks:ks_name":"Sakhauli",
    "ks:ks_pop":960,
    "ks:ks_type":"VILLAGE",
    "ks:ks_uagg_main":0,
    "name:eng_x_preferred":[
        "Sakhauli"
    ],
    "wof:name":"Sakhauli",
    "wof:placetype":"neighbourhood",
    "wof:population":960
},
  "geometry": {"coordinates":[79.814359,26.978668],"type":"Point"}
}