{
  "type": "Feature",
  "properties": {
    "gn:country":"IN",
    "gn:fcode":"PPL",
    "gn:population":10862,
    "iso:country":"IN",
    "name:ast_x_preferred":[
        "Paliad"
    ],
    "name:eng_x_preferred":[
        "Paliad"
    ],
    "name:guj_x_preferred":[
        "\u0aaa\u0abe\u0ab3\u0ac0\u0aaf\u0abe\u0aa6"
    ],
    "name:nld_x_preferred":[
        "Paliad"
    ],
    "qs:name":"Paliyad",
    "qs:name_adm0":"India",
    "qs:name_adm1":"Gujarat",
    "qs:photos_9r":0,
    "qs:photos_sr":0,
    "qs:placetype":"Town",
    "qs:pop_sr":"6",
    "wd:wordcount":215,
    "wof:name":"Paliyad",
    "wof:placetype":"locality",
    "wof:population":10862
},
  "geometry": {"coordinates":[71.56023999999999,22.25757],"type":"Point"}
}