{
  "type": "Feature",
  "properties": {
    "iso:country":"IN",
    "ks:ks_name":"Bhalukhola",
    "ks:ks_pop":109,
    "ks:ks_type":"VILLAGE",
    "name:eng_x_preferred":[
        "Bhalukhola"
    ],
    "wof:name":"Bhalukhola",
    "wof:placetype":"locality",
    "wof:population":109
},
  "geometry": {"coordinates":[84.612756,21.502824],"type":"Point"}
}