{
  "type": "Feature",
  "properties": {
    "iso:country":"IN",
    "ks:ks_name":"Roy Para",
    "ks:ks_pop":502,
    "ks:ks_type":"HABITATION",
    "name:eng_x_preferred":[
        "Roy Para"
    ],
    "wof:name":"Roy Para",
    "wof:placetype":"locality",
    "wof:population":502
},
  "geometry": {"coordinates":[89.49483499999999,26.20312],"type":"Point"}
}