{
  "type": "Feature",
  "properties": {
    "iso:country":"IN",
    "ks:ks_name":"Bhikha Bandi",
    "ks:ks_pop":348,
    "ks:ks_type":"HABITATION",
    "name:eng_x_preferred":[
        "Bhikha Bandi"
    ],
    "wof:name":"Bhikha Bandi",
    "wof:placetype":"locality",
    "wof:population":348
},
  "geometry": {"coordinates":[84.95346600000001,25.639106],"type":"Point"}
}