{
  "type": "Feature",
  "properties": {
    "iso:country":"IN",
    "ks:ks_name":"Iswarguda",
    "ks:ks_pop":45,
    "ks:ks_type":"VILLAGE",
    "name:eng_x_preferred":[
        "Iswarguda"
    ],
    "wof:name":"Iswarguda",
    "wof:placetype":"locality",
    "wof:population":45
},
  "geometry": {"coordinates":[82.15413700000001,18.103826],"type":"Point"}
}