{
  "type": "Feature",
  "properties": {
    "iso:country":"IN",
    "ks:ks_name":"Khalimunda",
    "ks:ks_pop":315,
    "ks:ks_type":"HABITATION",
    "name:eng_x_preferred":[
        "Khalimunda"
    ],
    "wof:name":"Khalimunda",
    "wof:placetype":"locality",
    "wof:population":315
},
  "geometry": {"coordinates":[83.677938,20.264492],"type":"Point"}
}