{
  "type": "Feature",
  "properties": {
    "gn:admin1_code":"35.0",
    "gn:admin2_code":"457.0",
    "gn:asciiname":"Siwa Tola",
    "gn:country_code":"IN",
    "gn:dem":312,
    "gn:feature_class":"P",
    "gn:feature_code":"PPL",
    "gn:name":"S\u012bw\u0101 Tol\u0101",
    "gn:population":0,
    "gn:timezone":"Asia/Kolkata",
    "iso:country":"IN",
    "wof:name":"Siwa Tola",
    "wof:placetype":"locality"
},
  "geometry": {"coordinates":[80.02768,21.82948],"type":"Point"}
}