{
  "type": "Feature",
  "properties": {
    "iso:country":"IN",
    "ks:ks_name":"Sikrel",
    "ks:ks_pop":478,
    "ks:ks_type":"VILLAGE",
    "name:eng_x_preferred":[
        "Sikrel"
    ],
    "wof:name":"Sikrel",
    "wof:placetype":"locality",
    "wof:population":478
},
  "geometry": {"coordinates":[82.424201,18.595294],"type":"Point"}
}