{
  "type": "Feature",
  "properties": {
    "gn:admin1_code":"17",
    "gn:admin2_code":"273.0",
    "gn:asciiname":"Sempang",
    "gn:country_code":"IN",
    "gn:dem":704,
    "gn:feature_class":"P",
    "gn:feature_code":"PPL",
    "gn:name":"Sempang",
    "gn:population":0,
    "gn:timezone":"Asia/Kolkata",
    "iso:country":"IN",
    "wof:name":"Sempang",
    "wof:placetype":"locality"
},
  "geometry": {"coordinates":[93.43192999999999,24.85507],"type":"Point"}
}