{
  "type": "Feature",
  "properties": {
    "gn:admin1_code":"12.0",
    "gn:admin2_code":"006",
    "gn:asciiname":"Chingeri Gala",
    "gn:country_code":"IN",
    "gn:dem":880,
    "gn:feature_class":"P",
    "gn:feature_code":"PPL",
    "gn:name":"Chingeri G\u0101la",
    "gn:population":0,
    "gn:timezone":"Asia/Kolkata",
    "iso:country":"IN",
    "wof:name":"Chingeri Gala",
    "wof:placetype":"locality"
},
  "geometry": {"coordinates":[74.34166999999999,33.18889],"type":"Point"}
}