{
  "type": "Feature",
  "properties": {
    "iso:country":"IN",
    "ks:ks_name":"Baliya",
    "ks:ks_pop":66,
    "ks:ks_type":"VILLAGE",
    "name:eng_x_preferred":[
        "Baliya"
    ],
    "wof:name":"Baliya",
    "wof:placetype":"locality",
    "wof:population":66
},
  "geometry": {"coordinates":[79.793223,29.604423],"type":"Point"}
}