{
  "type": "Feature",
  "properties": {
    "iso:country":"IN",
    "ks:ks_name":"East Suniti",
    "ks:ks_pop":144,
    "ks:ks_type":"HABITATION",
    "name:eng_x_preferred":[
        "East Suniti"
    ],
    "wof:name":"East Suniti",
    "wof:placetype":"locality",
    "wof:population":144
},
  "geometry": {"coordinates":[86.72351399999999,20.462124],"type":"Point"}
}