{
  "type": "Feature",
  "properties": {
    "gn:admin1_code":"36",
    "gn:admin2_code":"191.0",
    "gn:asciiname":"Bandhwa Islam",
    "gn:country_code":"IN",
    "gn:dem":89,
    "gn:feature_class":"P",
    "gn:feature_code":"PPL",
    "gn:name":"Bandhwa Isl\u0101m",
    "gn:population":0,
    "gn:timezone":"Asia/Kolkata",
    "iso:country":"IN",
    "ks:ks_alt_nam":"Bandhwa Isl\u0101m",
    "ks:ks_name":"Bandhwa Islam",
    "ks:ks_type":"VILLAGE",
    "ks:ks_uagg_main":0,
    "name:eng_x_preferred":[
        "Bandhwa Islam"
    ],
    "name:eng_x_variant":[
        "Bandhwa Isl\u0101m"
    ],
    "wof:name":"Bandhwa Islam",
    "wof:placetype":"neighbourhood"
},
  "geometry": {"coordinates":[82.808447,25.861203],"type":"Point"}
}