{
  "type": "Feature",
  "properties": {
    "iso:country":"IN",
    "ks:ks_name":"Baraipur",
    "ks:ks_pop":181,
    "ks:ks_type":"HABITATION",
    "name:eng_x_preferred":[
        "Baraipur"
    ],
    "wof:name":"Baraipur",
    "wof:placetype":"locality",
    "wof:population":181
},
  "geometry": {"coordinates":[83.155047,27.449497],"type":"Point"}
}