{
  "type": "Feature",
  "properties": {
    "iso:country":"IN",
    "ks:ks_name":"Keriyawas",
    "ks:ks_pop":956,
    "ks:ks_type":"HABITATION",
    "name:eng_x_preferred":[
        "Keriyawas"
    ],
    "wof:name":"Keriyawas",
    "wof:placetype":"locality",
    "wof:population":956
},
  "geometry": {"coordinates":[75.059731,27.118332],"type":"Point"}
}