{
  "type": "Feature",
  "properties": {
    "iso:country":"IN",
    "ks:ks_name":"Komarada",
    "ks:ks_pop":1383,
    "ks:ks_type":"VILLAGE",
    "name:eng_x_preferred":[
        "Komarada"
    ],
    "wof:name":"Komarada",
    "wof:placetype":"locality",
    "wof:population":1383
},
  "geometry": {"coordinates":[81.929565,16.476195],"type":"Point"}
}