{
  "type": "Feature",
  "properties": {
    "gn:admin1_code":"34.0",
    "gn:admin2_code":"230.0",
    "gn:asciiname":"Mithapur",
    "gn:country_code":"IN",
    "gn:dem":66,
    "gn:feature_class":"P",
    "gn:feature_code":"PPL",
    "gn:name":"Mith\u0101pur",
    "gn:population":0,
    "gn:timezone":"Asia/Kolkata",
    "iso:country":"IN",
    "name:bpy_x_preferred":[
        "\u09ae\u09bf\u09a0\u09be\u09aa\u09c1\u09b0"
    ],
    "name:ita_x_preferred":[
        "Mithapur"
    ],
    "name:msa_x_preferred":[
        "Mithapur"
    ],
    "name:new_x_preferred":[
        "\u092e\u0940\u0920\u093e\u092a\u0941\u0930"
    ],
    "name:nld_x_preferred":[
        "Mithapur"
    ],
    "name:por_x_preferred":[
        "Mithapur"
    ],
    "name:vie_x_preferred":[
        "Mithapur"
    ],
    "name:zho_x_preferred":[
        "\u7c73\u5854\u666e\u5c14"
    ],
    "wof:name":"Mithapur",
    "wof:placetype":"locality"
},
  "geometry": {"coordinates":[84.81698,25.50568],"type":"Point"}
}