{
  "type": "Feature",
  "properties": {
    "gn:admin1_code":"16.0",
    "gn:admin2_code":"510.0",
    "gn:asciiname":"Dhanora",
    "gn:country_code":"IN",
    "gn:dem":390,
    "gn:feature_class":"P",
    "gn:feature_code":"PPL",
    "gn:name":"Dh\u0101nora",
    "gn:population":0,
    "gn:timezone":"Asia/Kolkata",
    "iso:country":"IN",
    "name:mar_x_preferred":[
        "\u0927\u093e\u0928\u094b\u0930\u093e"
    ],
    "wof:name":"Dhanora",
    "wof:placetype":"locality"
},
  "geometry": {"coordinates":[77.44226,19.96705],"type":"Point"}
}