{
  "type": "Feature",
  "properties": {
    "iso:country":"IN",
    "ks:ks_name":"Sitapanga",
    "ks:ks_pop":138,
    "ks:ks_type":"VILLAGE",
    "name:eng_x_preferred":[
        "Sitapanga"
    ],
    "wof:name":"Sitapanga",
    "wof:placetype":"locality",
    "wof:population":138
},
  "geometry": {"coordinates":[84.125772,20.007546],"type":"Point"}
}