{
  "type": "Feature",
  "properties": {
    "iso:country":"IN",
    "ks:ks_name":"10 LLW",
    "ks:ks_pop":106,
    "ks:ks_type":"VILLAGE",
    "name:eng_x_preferred":[
        "10 LLW"
    ],
    "wof:name":"10 LLW",
    "wof:placetype":"locality",
    "wof:population":106
},
  "geometry": {"coordinates":[74.29868500000001,29.678056],"type":"Point"}
}