{
  "type": "Feature",
  "properties": {
    "gn:admin1_code":"35.0",
    "gn:admin2_code":"458.0",
    "gn:asciiname":"Bhogipura",
    "gn:country_code":"IN",
    "gn:dem":423,
    "gn:feature_class":"P",
    "gn:feature_code":"PPL",
    "gn:name":"Bhogipura",
    "gn:population":0,
    "gn:timezone":"Asia/Kolkata",
    "iso:country":"IN",
    "ks:ks_name":"Bhogipura",
    "ks:ks_pop":588,
    "ks:ks_type":"VILLAGE",
    "name:eng_x_preferred":[
        "Bhogipura"
    ],
    "wof:name":"Bhogipura",
    "wof:placetype":"locality",
    "wof:population":588
},
  "geometry": {"coordinates":[76.90012,24.411189],"type":"Point"}
}