{
  "type": "Feature",
  "properties": {
    "gn:admin1_code":"19",
    "gn:admin2_code":"568.0",
    "gn:asciiname":"Kanale",
    "gn:country_code":"IN",
    "gn:dem":581,
    "gn:feature_class":"P",
    "gn:feature_code":"PPL",
    "gn:name":"Kanale",
    "gn:population":0,
    "gn:timezone":"Asia/Kolkata",
    "iso:country":"IN",
    "ks:ks_name":"Kanle",
    "ks:ks_pop":407,
    "ks:ks_type":"VILLAGE",
    "name:eng_x_preferred":[
        "Kanle"
    ],
    "name:eng_x_variant":[
        "Kanale"
    ],
    "wof:name":"Kanle",
    "wof:placetype":"locality",
    "wof:population":407
},
  "geometry": {"coordinates":[74.959101,14.222087],"type":"Point"}
}