{
  "type": "Feature",
  "properties": {
    "gn:admin1_code":"40",
    "gn:admin2_code":"538.0",
    "gn:asciiname":"Vemula",
    "gn:country_code":"IN",
    "gn:dem":508,
    "gn:feature_class":"P",
    "gn:feature_code":"PPL",
    "gn:name":"Vemula",
    "gn:population":0,
    "gn:timezone":"Asia/Kolkata",
    "iso:country":"IN",
    "name:fas_x_preferred":[
        "\u0648\u0645\u0648\u0644\u0627"
    ],
    "name:new_x_preferred":[
        "\u0935\u0947\u092e\u0941\u0932 \u092e\u0923\u094d\u0921\u0932"
    ],
    "name:pam_x_preferred":[
        "Vemula"
    ],
    "name:tel_x_preferred":[
        "\u0c35\u0c47\u0c2e\u0c41\u0c32"
    ],
    "name:tgl_x_preferred":[
        "Vemula"
    ],
    "name:urd_x_preferred":[
        "\u0648\u06cc\u0645\u0648\u0644\u0627"
    ],
    "wof:name":"Vemula",
    "wof:placetype":"locality"
},
  "geometry": {"coordinates":[78.31871,16.78466],"type":"Point"}
}