{
  "type": "Feature",
  "properties": {
    "iso:country":"IN",
    "ks:ks_alt_nam":"WARCHIWADI",
    "ks:ks_name":"Warchiwadi",
    "ks:ks_pop":441,
    "ks:ks_type":"HABITATION",
    "name:eng_x_preferred":[
        "Warchiwadi"
    ],
    "wof:name":"Warchiwadi",
    "wof:placetype":"locality",
    "wof:population":441
},
  "geometry": {"coordinates":[73.215278,17.469722],"type":"Point"}
}