{
  "type": "Feature",
  "properties": {
    "iso:country":"IN",
    "ks:ks_alt_nam":"SALGA BIRHOR TANR",
    "ks:ks_name":"Salga Birhor Tanr",
    "ks:ks_pop":196,
    "ks:ks_type":"HABITATION",
    "name:eng_x_preferred":[
        "Salga Birhor Tanr"
    ],
    "wof:name":"Salga Birhor Tanr",
    "wof:placetype":"locality",
    "wof:population":196
},
  "geometry": {"coordinates":[85.256342,23.997456],"type":"Point"}
}