{
  "type": "Feature",
  "properties": {
    "iso:country":"IN",
    "ks:ks_name":"Banjariya",
    "ks:ks_pop":655,
    "ks:ks_type":"VILLAGE",
    "name:eng_x_preferred":[
        "Banjariya"
    ],
    "wof:name":"Banjariya",
    "wof:placetype":"locality",
    "wof:population":655
},
  "geometry": {"coordinates":[84.432311,26.266062],"type":"Point"}
}