{
  "type": "Feature",
  "properties": {
    "gn:admin1_code":"36.0",
    "gn:admin2_code":"160",
    "gn:asciiname":"Mianganj",
    "gn:country_code":"IN",
    "gn:dem":144,
    "gn:feature_class":"P",
    "gn:feature_code":"PPL",
    "gn:name":"Mi\u0101nganj",
    "gn:population":0,
    "gn:timezone":"Asia/Kolkata",
    "iso:country":"IN",
    "wof:name":"Mianganj",
    "wof:placetype":"neighbourhood"
},
  "geometry": {"coordinates":[79.97338999999999,27.00015],"type":"Point"}
}