{
  "type": "Feature",
  "properties": {
    "gn:admin1_code":"24.0",
    "gn:admin2_code":"120.0",
    "gn:asciiname":"Thuni",
    "gn:country_code":"IN",
    "gn:dem":302,
    "gn:feature_class":"P",
    "gn:feature_code":"PPL",
    "gn:name":"Thuni",
    "gn:population":0,
    "gn:timezone":"Asia/Kolkata",
    "iso:country":"IN",
    "name:und_x_variant":[
        "R\u0101dh\u0101gov\u012bndpura"
    ],
    "wof:name":"Thuni",
    "wof:placetype":"neighbourhood"
},
  "geometry": {"coordinates":[76.00452,26.42035],"type":"Point"}
}