{
  "type": "Feature",
  "properties": {
    "iso:country":"IN",
    "ks:ks_name":"8 GM-B",
    "ks:ks_pop":80,
    "ks:ks_type":"VILLAGE",
    "name:eng_x_preferred":[
        "8 GM-B"
    ],
    "wof:name":"8 GM-B",
    "wof:placetype":"locality",
    "wof:population":80
},
  "geometry": {"coordinates":[72.95054500000001,28.963101],"type":"Point"}
}