{
  "type": "Feature",
  "properties": {
    "iso:country":"IN",
    "ks:ks_name":"Schoolpara",
    "ks:ks_pop":514,
    "ks:ks_type":"HABITATION",
    "name:eng_x_preferred":[
        "Schoolpara"
    ],
    "wof:name":"Schoolpara",
    "wof:placetype":"locality",
    "wof:population":514
},
  "geometry": {"coordinates":[81.19293,20.08651],"type":"Point"}
}