{
  "type": "Feature",
  "properties": {
    "iso:country":"IN",
    "ks:ks_name":"Sahajpurwadi",
    "ks:ks_pop":2968,
    "ks:ks_type":"VILLAGE",
    "name:eng_x_preferred":[
        "Sahajpurwadi"
    ],
    "wof:name":"Sahajpurwadi",
    "wof:placetype":"locality",
    "wof:population":2968
},
  "geometry": {"coordinates":[74.18732,18.50317],"type":"Point"}
}