{
  "type": "Feature",
  "properties": {
    "iso:country":"IN",
    "ks:ks_name":"Pangulu",
    "ks:ks_pop":314,
    "ks:ks_type":"VILLAGE",
    "name:eng_x_preferred":[
        "Pangulu"
    ],
    "wof:name":"Pangulu",
    "wof:placetype":"locality",
    "wof:population":314
},
  "geometry": {"coordinates":[84.194829,19.531203],"type":"Point"}
}