{
  "type": "Feature",
  "properties": {
    "gn:admin1_code":"2.0",
    "gn:admin2_code":"554.0",
    "gn:asciiname":"Javukulakota",
    "gn:country_code":"IN",
    "gn:dem":585,
    "gn:feature_class":"P",
    "gn:feature_code":"PPL",
    "gn:name":"Javukulakota",
    "gn:population":0,
    "gn:timezone":"Asia/Kolkata",
    "iso:country":"IN",
    "wof:name":"Javukulakota",
    "wof:placetype":"locality"
},
  "geometry": {"coordinates":[78.28498,13.82734],"type":"Point"}
}