{
  "type": "Feature",
  "properties": {
    "iso:country":"IN",
    "ks:ks_name":"Godhiya",
    "ks:ks_pop":1284,
    "ks:ks_type":"HABITATION",
    "name:eng_x_preferred":[
        "Godhiya"
    ],
    "wof:name":"Godhiya",
    "wof:placetype":"locality",
    "wof:population":1284
},
  "geometry": {"coordinates":[86.67367299999999,26.435722],"type":"Point"}
}