{
  "type": "Feature",
  "properties": {
    "gn:admin1_code":"36",
    "gn:admin2_code":"177.0",
    "gn:asciiname":"Purwa Jhau",
    "gn:country_code":"IN",
    "gn:dem":106,
    "gn:feature_class":"P",
    "gn:feature_code":"PPL",
    "gn:name":"Purwa Jh\u0101u",
    "gn:population":0,
    "gn:timezone":"Asia/Kolkata",
    "iso:country":"IN",
    "wof:name":"Purwa Jhau",
    "wof:placetype":"neighbourhood"
},
  "geometry": {"coordinates":[82.08174,26.53443],"type":"Point"}
}