{
  "type": "Feature",
  "properties": {
    "iso:country":"IN",
    "ks:ks_name":"Jhanjrola",
    "ks:ks_pop":2587,
    "ks:ks_type":"VILLAGE",
    "name:eng_x_preferred":[
        "Jhanjrola"
    ],
    "wof:name":"Jhanjrola",
    "wof:placetype":"neighbourhood",
    "wof:population":2587
},
  "geometry": {"coordinates":[76.861583,28.486295],"type":"Point"}
}