{
  "type": "Feature",
  "properties": {
    "gn:admin1_code":"23",
    "gn:admin2_code":"50.0",
    "gn:asciiname":"Marhana",
    "gn:country_code":"IN",
    "gn:dem":222,
    "gn:feature_class":"P",
    "gn:feature_code":"PPL",
    "gn:name":"Marh\u0101na",
    "gn:population":0,
    "gn:timezone":"Asia/Kolkata",
    "iso:country":"IN",
    "wof:name":"Marhana",
    "wof:placetype":"locality"
},
  "geometry": {"coordinates":[74.96193000000002,31.20306],"type":"Point"}
}