{
  "type": "Feature",
  "properties": {
    "iso:country":"IN",
    "ks:ks_alt_nam":"M\u0101valli",
    "ks:ks_name":"Mavalli",
    "ks:ks_pop":805,
    "ks:ks_type":"VILLAGE",
    "name:eng_x_preferred":[
        "Mavalli"
    ],
    "name:eng_x_variant":[
        "M\u0101valli"
    ],
    "wof:name":"Mavalli",
    "wof:placetype":"locality",
    "wof:population":805
},
  "geometry": {"coordinates":[74.487374,14.102024],"type":"Point"}
}