{
  "type": "Feature",
  "properties": {
    "iso:country":"IN",
    "ks:ks_name":"Boudhawadi",
    "ks:ks_pop":119,
    "ks:ks_type":"HABITATION",
    "name:eng_x_preferred":[
        "Boudhawadi"
    ],
    "wof:name":"Boudhawadi",
    "wof:placetype":"locality",
    "wof:population":119
},
  "geometry": {"coordinates":[73.388333,17.530556],"type":"Point"}
}