{
  "type": "Feature",
  "properties": {
    "iso:country":"IN",
    "ks:ks_name":"Sonito",
    "ks:ks_pop":341,
    "ks:ks_type":"HABITATION",
    "ks:ks_uagg_main":0,
    "name:eng_x_preferred":[
        "Sonito"
    ],
    "wof:name":"Sonito",
    "wof:placetype":"neighbourhood",
    "wof:population":341
},
  "geometry": {"coordinates":[93.84871200000001,25.910913],"type":"Point"}
}