{
  "type": "Feature",
  "properties": {
    "gn:admin1_code":"36",
    "gn:admin2_code":"179.0",
    "gn:asciiname":"Futkipur",
    "gn:country_code":"IN",
    "gn:dem":109,
    "gn:feature_class":"P",
    "gn:feature_code":"PPL",
    "gn:name":"Futkipur",
    "gn:population":0,
    "gn:timezone":"Asia/Kolkata",
    "iso:country":"IN",
    "name:und_x_variant":[
        "Medin Mawai"
    ],
    "wof:name":"Futkipur",
    "wof:placetype":"neighbourhood"
},
  "geometry": {"coordinates":[81.72472999999999,26.19921],"type":"Point"}
}