{
  "type": "Feature",
  "properties": {
    "iso:country":"IN",
    "ks:ks_name":"Kakularampalle",
    "ks:ks_pop":106,
    "ks:ks_type":"HABITATION",
    "name:eng_x_preferred":[
        "Kakularampalle"
    ],
    "wof:name":"Kakularampalle",
    "wof:placetype":"locality",
    "wof:population":106
},
  "geometry": {"coordinates":[79.05613200000001,13.697459],"type":"Point"}
}