{
  "type": "Feature",
  "properties": {
    "gn:admin1_code":"28",
    "gn:admin2_code":"327.0",
    "gn:asciiname":"Pedong",
    "gn:country_code":"IN",
    "gn:dem":1407,
    "gn:feature_class":"P",
    "gn:feature_code":"PPL",
    "gn:name":"Pedong",
    "gn:population":0,
    "gn:timezone":"Asia/Kolkata",
    "iso:country":"IN",
    "wof:name":"Pedong",
    "wof:placetype":"locality"
},
  "geometry": {"coordinates":[88.61448,27.15393],"type":"Point"}
}