{
  "type": "Feature",
  "properties": {
    "iso:country":"IN",
    "ks:ks_name":"Kallane",
    "ks:ks_type":"VILLAGE",
    "name:eng_x_preferred":[
        "Kallane"
    ],
    "wof:name":"Kallane",
    "wof:placetype":"locality"
},
  "geometry": {"coordinates":[76.779934,13.16629],"type":"Point"}
}