{
  "type": "Feature",
  "properties": {
    "iso:country":"IN",
    "ks:ks_name":"Kelavali",
    "ks:ks_pop":539,
    "ks:ks_type":"VILLAGE",
    "name:eng_x_preferred":[
        "Kelavali"
    ],
    "wof:name":"Kelavali",
    "wof:placetype":"locality",
    "wof:population":539
},
  "geometry": {"coordinates":[73.320415,18.84405],"type":"Point"}
}