{
  "type": "Feature",
  "properties": {
    "iso:country":"IN",
    "ks:ks_name":"3 KKM",
    "ks:ks_pop":108,
    "ks:ks_type":"VILLAGE",
    "name:eng_x_preferred":[
        "3 KKM"
    ],
    "wof:name":"3 KKM",
    "wof:placetype":"locality",
    "wof:population":108
},
  "geometry": {"coordinates":[74.44266399999999,29.119067],"type":"Point"}
}