{
  "type": "Feature",
  "properties": {
    "iso:country":"IN",
    "ks:ks_name":"Ambatoli",
    "ks:ks_pop":125,
    "ks:ks_type":"HABITATION",
    "name:eng_x_preferred":[
        "Ambatoli"
    ],
    "wof:name":"Ambatoli",
    "wof:placetype":"locality",
    "wof:population":125
},
  "geometry": {"coordinates":[85.02946799999999,23.101152],"type":"Point"}
}