{
  "type": "Feature",
  "properties": {
    "iso:country":"IN",
    "ks:ks_name":"Paunsakuli Oraf Ratankuli",
    "ks:ks_pop":445,
    "ks:ks_type":"VILLAGE",
    "ks:ks_uagg_main":0,
    "name:eng_x_preferred":[
        "Paunsakuli Oraf Ratankuli"
    ],
    "wof:name":"Paunsakuli Oraf Ratankuli",
    "wof:placetype":"neighbourhood",
    "wof:population":445
},
  "geometry": {"coordinates":[87.167948,21.715868],"type":"Point"}
}