{
  "type": "Feature",
  "properties": {
    "gn:admin1_code":"36.0",
    "gn:admin2_code":"141.0",
    "gn:asciiname":"Khora",
    "gn:country_code":"IN",
    "gn:dem":204,
    "gn:feature_class":"P",
    "gn:feature_code":"PPL",
    "gn:name":"Khora",
    "gn:population":0,
    "gn:timezone":"Asia/Kolkata",
    "iso:country":"IN",
    "name:bih_x_preferred":[
        "\u0916\u094b\u0930\u093e"
    ],
    "wof:name":"Khora",
    "wof:placetype":"locality"
},
  "geometry": {"coordinates":[77.35370999999998,28.62275],"type":"Point"}
}