{
  "type": "Feature",
  "properties": {
    "iso:country":"IN",
    "ks:ks_name":"Lakhnasara",
    "ks:ks_pop":88,
    "ks:ks_type":"VILLAGE",
    "name:eng_x_preferred":[
        "Lakhnasara"
    ],
    "wof:name":"Lakhnasara",
    "wof:placetype":"locality",
    "wof:population":88
},
  "geometry": {"coordinates":[87.533012,24.113539],"type":"Point"}
}