{
  "type": "Feature",
  "properties": {
    "iso:country":"IN",
    "ks:ks_name":"Sukidevi Faliya",
    "ks:ks_pop":918,
    "ks:ks_type":"HABITATION",
    "name:eng_x_preferred":[
        "Sukidevi Faliya"
    ],
    "wof:name":"Sukidevi Faliya",
    "wof:placetype":"locality",
    "wof:population":918
},
  "geometry": {"coordinates":[73.84944400000001,23.156778],"type":"Point"}
}