{
  "type": "Feature",
  "properties": {
    "iso:country":"IN",
    "ks:ks_name":"Nalpada",
    "ks:ks_pop":412,
    "ks:ks_type":"HABITATION",
    "name:eng_x_preferred":[
        "Nalpada"
    ],
    "wof:name":"Nalpada",
    "wof:placetype":"locality",
    "wof:population":412
},
  "geometry": {"coordinates":[74.64187800000001,23.454492],"type":"Point"}
}