{
  "type": "Feature",
  "properties": {
    "iso:country":"IN",
    "ks:ks_name":"Nayapurwa",
    "ks:ks_pop":187,
    "ks:ks_type":"HABITATION",
    "name:eng_x_preferred":[
        "Nayapurwa"
    ],
    "wof:name":"Nayapurwa",
    "wof:placetype":"locality",
    "wof:population":187
},
  "geometry": {"coordinates":[81.10590500000001,27.87151],"type":"Point"}
}