{
  "type": "Feature",
  "properties": {
    "gn:admin1_code":"37.0",
    "gn:admin2_code":"416.0",
    "gn:asciiname":"Kondasanvali",
    "gn:country_code":"IN",
    "gn:dem":257,
    "gn:feature_class":"P",
    "gn:feature_code":"PPL",
    "gn:name":"Kondas\u0101nvali",
    "gn:population":0,
    "gn:timezone":"Asia/Kolkata",
    "iso:country":"IN",
    "ks:ks_name":"Kondasawali",
    "ks:ks_pop":351,
    "ks:ks_type":"VILLAGE",
    "name:eng_x_preferred":[
        "Kondasawali"
    ],
    "name:eng_x_variant":[
        "Kondasanvali"
    ],
    "wof:name":"Kondasawali",
    "wof:placetype":"locality",
    "wof:population":351
},
  "geometry": {"coordinates":[81.223026,18.487329],"type":"Point"}
}