{
  "type": "Feature",
  "properties": {
    "gn:admin1_code":"37.0",
    "gn:admin2_code":"416.0",
    "gn:asciiname":"Kondasanvali",
    "gn:country_code":"IN",
    "gn:dem":257,
    "gn:feature_class":"P",
    "gn:feature_code":"PPL",
    "gn:name":"Kondas\u0101nvali",
    "gn:population":0,
    "gn:timezone":"Asia/Kolkata",
    "iso:country":"IN",
    "wof:name":"Kondasanvali",
    "wof:placetype":"locality"
},
  "geometry": {"coordinates":[81.21769999999999,18.48841],"type":"Point"}
}