{
  "type": "Feature",
  "properties": {
    "gn:admin1_code":"36.0",
    "gn:admin2_code":"150.0",
    "gn:asciiname":"Sanehia Mewa Kuar",
    "gn:country_code":"IN",
    "gn:dem":175,
    "gn:feature_class":"P",
    "gn:feature_code":"PPL",
    "gn:name":"Sanehia Mewa Ku\u0101r",
    "gn:population":0,
    "gn:timezone":"Asia/Kolkata",
    "iso:country":"IN",
    "wof:name":"Sanehia Mewa Kuar",
    "wof:placetype":"neighbourhood"
},
  "geometry": {"coordinates":[79.38754,28.41356],"type":"Point"}
}