{
  "type": "Feature",
  "properties": {
    "iso:country":"IN",
    "ks:ks_alt_nam":"VICTORIA",
    "ks:ks_name":"Victoria",
    "ks:ks_pop":275,
    "ks:ks_type":"HABITATION",
    "name:eng_x_preferred":[
        "Victoria"
    ],
    "wof:name":"Victoria",
    "wof:placetype":"locality",
    "wof:population":275
},
  "geometry": {"coordinates":[76.67257499999999,10.48055],"type":"Point"}
}