{
  "type": "Feature",
  "properties": {
    "iso:country":"IN",
    "ks:ks_name":"Manjinakanu",
    "ks:ks_pop":308,
    "ks:ks_type":"HABITATION",
    "name:eng_x_preferred":[
        "Manjinakanu"
    ],
    "wof:name":"Manjinakanu",
    "wof:placetype":"locality",
    "wof:population":308
},
  "geometry": {"coordinates":[74.886404,14.196465],"type":"Point"}
}