{
  "type": "Feature",
  "properties": {
    "iso:country":"IN",
    "ks:ks_alt_nam":"dinapurwa",
    "ks:ks_name":"Dinapurwa",
    "ks:ks_pop":21,
    "ks:ks_type":"HABITATION",
    "name:eng_x_preferred":[
        "Dinapurwa"
    ],
    "wof:name":"Dinapurwa",
    "wof:placetype":"locality",
    "wof:population":21
},
  "geometry": {"coordinates":[81.949183,27.446957],"type":"Point"}
}