{
  "type": "Feature",
  "properties": {
    "iso:country":"IN",
    "ks:ks_name":"Kheraj Shahpur",
    "ks:ks_pop":1201,
    "ks:ks_type":"VILLAGE",
    "ks:ks_uagg_main":0,
    "name:eng_x_preferred":[
        "Kheraj Shahpur"
    ],
    "wof:name":"Kheraj Shahpur",
    "wof:placetype":"neighbourhood",
    "wof:population":1201
},
  "geometry": {"coordinates":[85.843486,26.187803],"type":"Point"}
}