{
  "type": "Feature",
  "properties": {
    "gn:admin1_code":"36.0",
    "gn:admin2_code":"135.0",
    "gn:asciiname":"Daboi Khurd",
    "gn:country_code":"IN",
    "gn:dem":205,
    "gn:feature_class":"P",
    "gn:feature_code":"PPL",
    "gn:name":"Daboi Khurd",
    "gn:population":0,
    "gn:timezone":"Asia/Kolkata",
    "iso:country":"IN",
    "wof:name":"Daboi Khurd",
    "wof:placetype":"locality"
},
  "geometry": {"coordinates":[78.51665,28.72733],"type":"Point"}
}