{
  "type": "Feature",
  "properties": {
    "iso:country":"IN",
    "ks:ks_name":"Kudige Circle",
    "ks:ks_pop":22,
    "ks:ks_type":"HABITATION",
    "name:eng_x_preferred":[
        "Kudige Circle"
    ],
    "wof:name":"Kudige Circle",
    "wof:placetype":"locality",
    "wof:population":22
},
  "geometry": {"coordinates":[75.988056,12.5025],"type":"Point"}
}