{
  "type": "Feature",
  "properties": {
    "gn:admin1_code":"36.0",
    "gn:admin2_code":"142.0",
    "gn:asciiname":"Machar",
    "gn:country_code":"IN",
    "gn:dem":197,
    "gn:feature_class":"P",
    "gn:feature_code":"PPL",
    "gn:name":"M\u0101char",
    "gn:population":0,
    "gn:timezone":"Asia/Kolkata",
    "iso:country":"IN",
    "ks:ks_name":"Machar",
    "ks:ks_pop":2151,
    "ks:ks_type":"HABITATION",
    "name:deu_x_preferred":[
        "Machar"
    ],
    "name:eng_x_preferred":[
        "Machar"
    ],
    "name:fra_x_preferred":[
        "Machar"
    ],
    "wof:name":"Machar",
    "wof:placetype":"locality",
    "wof:population":2151
},
  "geometry": {"coordinates":[77.70675199999999,28.109193],"type":"Point"}
}