{
  "type": "Feature",
  "properties": {
    "gn:admin1_code":"36.0",
    "gn:admin2_code":"142.0",
    "gn:asciiname":"Machar",
    "gn:country_code":"IN",
    "gn:dem":197,
    "gn:feature_class":"P",
    "gn:feature_code":"PPL",
    "gn:name":"M\u0101char",
    "gn:population":0,
    "gn:timezone":"Asia/Kolkata",
    "iso:country":"IN",
    "name:deu_x_preferred":[
        "Machar"
    ],
    "name:fra_x_preferred":[
        "Machar"
    ],
    "wof:name":"Machar",
    "wof:placetype":"locality"
},
  "geometry": {"coordinates":[77.69561,28.09989],"type":"Point"}
}