{
  "type": "Feature",
  "properties": {
    "iso:country":"IN",
    "ks:ks_name":"Hingala",
    "ks:ks_pop":311,
    "ks:ks_type":"HABITATION",
    "ks:ks_uagg_main":0,
    "name:eng_x_preferred":[
        "Hingala"
    ],
    "wof:name":"Hingala",
    "wof:placetype":"neighbourhood",
    "wof:population":311
},
  "geometry": {"coordinates":[74.045472,23.123417],"type":"Point"}
}