{
  "type": "Feature",
  "properties": {
    "gn:admin1_code":"36.0",
    "gn:admin2_code":"164.0",
    "gn:asciiname":"Phupwar Sui Thok",
    "gn:country_code":"IN",
    "gn:dem":125,
    "gn:feature_class":"P",
    "gn:feature_code":"PPL",
    "gn:name":"Phupw\u0101r Sui Thok",
    "gn:population":0,
    "gn:timezone":"Asia/Kolkata",
    "iso:country":"IN",
    "wof:name":"Phupwar Sui Thok",
    "wof:placetype":"locality"
},
  "geometry": {"coordinates":[80.44658000000003,26.30251],"type":"Point"}
}