{
  "type": "Feature",
  "properties": {
    "iso:country":"IN",
    "ks:ks_name":"Umar",
    "ks:ks_pop":2418,
    "ks:ks_type":"VILLAGE",
    "ks:ks_uagg_main":0,
    "name:eng_x_preferred":[
        "Umar"
    ],
    "wof:name":"Umar",
    "wof:placetype":"neighbourhood",
    "wof:population":2418
},
  "geometry": {"coordinates":[86.207196,20.519681],"type":"Point"}
}