{
  "type": "Feature",
  "properties": {
    "iso:country":"IN",
    "ks:ks_name":"Rudi",
    "ks:ks_pop":448,
    "ks:ks_type":"VILLAGE",
    "name:eng_x_preferred":[
        "Rudi"
    ],
    "wof:name":"Rudi",
    "wof:placetype":"locality",
    "wof:population":448
},
  "geometry": {"coordinates":[85.309145,23.83647],"type":"Point"}
}