{
  "type": "Feature",
  "properties": {
    "gn:admin1_code":"36.0",
    "gn:admin2_code":"140.0",
    "gn:asciiname":"Ubarpur",
    "gn:country_code":"IN",
    "gn:dem":212,
    "gn:feature_class":"P",
    "gn:feature_code":"PPL",
    "gn:name":"Ub\u0101rpur",
    "gn:population":0,
    "gn:timezone":"Asia/Kolkata",
    "iso:country":"IN",
    "wof:name":"Ubarpur",
    "wof:placetype":"locality"
},
  "geometry": {"coordinates":[77.75766,28.67723],"type":"Point"}
}