{
  "type": "Feature",
  "properties": {
    "iso:country":"IN",
    "ks:ks_alt_nam":"arunthathiyar colony",
    "ks:ks_name":"Arunthathiyar Colony",
    "ks:ks_pop":88,
    "ks:ks_type":"HABITATION",
    "name:eng_x_preferred":[
        "Arunthathiyar Colony"
    ],
    "wof:name":"Arunthathiyar Colony",
    "wof:placetype":"locality",
    "wof:population":88
},
  "geometry": {"coordinates":[79.513891,12.19785],"type":"Point"}
}