{
  "type": "Feature",
  "properties": {
    "iso:country":"IN",
    "ks:ks_name":"N. Bhurha",
    "ks:ks_pop":65,
    "ks:ks_type":"HABITATION",
    "name:eng_x_preferred":[
        "N. Bhurha"
    ],
    "wof:name":"N. Bhurha",
    "wof:placetype":"locality",
    "wof:population":65
},
  "geometry": {"coordinates":[79.346603,27.118314],"type":"Point"}
}