{
  "type": "Feature",
  "properties": {
    "iso:country":"IN",
    "ks:ks_name":"Hadwalewasti",
    "ks:ks_pop":165,
    "ks:ks_type":"HABITATION",
    "name:eng_x_preferred":[
        "Hadwalewasti"
    ],
    "wof:name":"Hadwalewasti",
    "wof:placetype":"locality",
    "wof:population":165
},
  "geometry": {"coordinates":[73.92416799999999,19.192622],"type":"Point"}
}