{
  "type": "Feature",
  "properties": {
    "gn:admin1_code":"23.0",
    "gn:admin2_code":"35.0",
    "gn:asciiname":"Talwandi Bharath",
    "gn:country_code":"IN",
    "gn:dem":245,
    "gn:feature_class":"P",
    "gn:feature_code":"PPL",
    "gn:name":"Talwandi Bh\u0101rath",
    "gn:population":0,
    "gn:timezone":"Asia/Kolkata",
    "iso:country":"IN",
    "wof:name":"Talwandi Bharath",
    "wof:placetype":"locality"
},
  "geometry": {"coordinates":[75.09484999999999,31.82387],"type":"Point"}
}