{
  "type": "Feature",
  "properties": {
    "gn:admin1_code":"39.0",
    "gn:admin2_code":"63.0",
    "gn:asciiname":"Maniakhet",
    "gn:country_code":"IN",
    "gn:dem":1291,
    "gn:feature_class":"P",
    "gn:feature_code":"PPL",
    "gn:name":"Maniakhet",
    "gn:population":0,
    "gn:timezone":"Asia/Kolkata",
    "iso:country":"IN",
    "wof:name":"Maniakhet",
    "wof:placetype":"locality"
},
  "geometry": {"coordinates":[79.59968000000001,29.94751],"type":"Point"}
}