{
  "type": "Feature",
  "properties": {
    "iso:country":"IN",
    "ks:ks_name":"Pedanaidupalem",
    "ks:ks_pop":2042,
    "ks:ks_type":"HABITATION",
    "name:eng_x_preferred":[
        "Pedanaidupalem"
    ],
    "wof:name":"Pedanaidupalem",
    "wof:placetype":"neighbourhood",
    "wof:population":2042
},
  "geometry": {"coordinates":[83.139059,17.794087],"type":"Point"}
}