{
  "type": "Feature",
  "properties": {
    "iso:country":"IN",
    "ks:ks_name":"Utari Gaon",
    "ks:ks_pop":184,
    "ks:ks_type":"VILLAGE",
    "ks:ks_uagg_main":0,
    "name:eng_x_preferred":[
        "Utari Gaon"
    ],
    "wof:name":"Utari Gaon",
    "wof:placetype":"locality",
    "wof:population":184
},
  "geometry": {"coordinates":[78.060576,30.399431],"type":"Point"}
}