{
  "type": "Feature",
  "properties": {
    "iso:country":"IN",
    "ks:ks_name":"Veerabhadrapuram",
    "ks:ks_pop":66,
    "ks:ks_type":"HABITATION",
    "name:eng_x_preferred":[
        "Veerabhadrapuram"
    ],
    "wof:name":"Veerabhadrapuram",
    "wof:placetype":"locality",
    "wof:population":66
},
  "geometry": {"coordinates":[80.51067399999999,17.388144],"type":"Point"}
}