{
  "type": "Feature",
  "properties": {
    "iso:country":"IN",
    "ks:ks_name":"Chhotepotenar",
    "ks:ks_pop":277,
    "ks:ks_type":"HABITATION",
    "name:eng_x_preferred":[
        "Chhotepotenar"
    ],
    "wof:name":"Chhotepotenar",
    "wof:placetype":"locality",
    "wof:population":277
},
  "geometry": {"coordinates":[80.871162,19.037421],"type":"Point"}
}