{
  "type": "Feature",
  "properties": {
    "iso:country":"IN",
    "ks:ks_alt_nam":"12-Card Para",
    "ks:ks_name":"12-card Para",
    "ks:ks_pop":372,
    "ks:ks_type":"HABITATION",
    "name:eng_x_preferred":[
        "12-card Para"
    ],
    "wof:name":"12-card Para",
    "wof:placetype":"locality",
    "wof:population":372
},
  "geometry": {"coordinates":[92.042968,24.00873],"type":"Point"}
}