{
  "type": "Feature",
  "properties": {
    "iso:country":"IN",
    "ks:ks_name":"Sajangolu",
    "ks:ks_pop":363,
    "ks:ks_type":"HABITATION",
    "name:eng_x_preferred":[
        "Sajangolu"
    ],
    "wof:name":"Sajangolu",
    "wof:placetype":"locality",
    "wof:population":363
},
  "geometry": {"coordinates":[75.295905,12.698205],"type":"Point"}
}