{
  "type": "Feature",
  "properties": {
    "iso:country":"IN",
    "ks:ks_name":"Bhalipanka",
    "ks:ks_pop":174,
    "ks:ks_type":"VILLAGE",
    "name:eng_x_preferred":[
        "Bhalipanka"
    ],
    "wof:name":"Bhalipanka",
    "wof:placetype":"locality",
    "wof:population":174
},
  "geometry": {"coordinates":[84.093097,19.529402],"type":"Point"}
}