{
  "type": "Feature",
  "properties": {
    "iso:country":"IN",
    "ks:ks_name":"Tuniya Laga Angtoli",
    "ks:ks_pop":9,
    "ks:ks_type":"HABITATION",
    "name:eng_x_preferred":[
        "Tuniya Laga Angtoli"
    ],
    "wof:name":"Tuniya Laga Angtoli",
    "wof:placetype":"locality",
    "wof:population":9
},
  "geometry": {"coordinates":[79.438233,30.138538],"type":"Point"}
}