{
  "type": "Feature",
  "properties": {
    "gn:admin1_code":"34.0",
    "gn:admin2_code":"224.0",
    "gn:asciiname":"Jamsi",
    "gn:country_code":"IN",
    "gn:dem":38,
    "gn:feature_class":"P",
    "gn:feature_code":"PPL",
    "gn:name":"Jamsi",
    "gn:population":0,
    "gn:timezone":"Asia/Kolkata",
    "iso:country":"IN",
    "name:ara_x_preferred":[
        "\u062c\u0645\u0633\u064a"
    ],
    "name:fas_x_preferred":[
        "\u062c\u0645\u0633\u06cc"
    ],
    "name:msa_x_preferred":[
        "Jamsi"
    ],
    "name:urd_x_preferred":[
        "\u062c\u0645\u0633\u06cc"
    ],
    "wof:name":"Jamsi",
    "wof:placetype":"locality"
},
  "geometry": {"coordinates":[87.0361,25.20614],"type":"Point"}
}