{
  "type": "Feature",
  "properties": {
    "iso:country":"IN",
    "ks:ks_name":"Vuasahi",
    "ks:ks_pop":301,
    "ks:ks_type":"HABITATION",
    "name:eng_x_preferred":[
        "Vuasahi"
    ],
    "wof:name":"Vuasahi",
    "wof:placetype":"locality",
    "wof:population":301
},
  "geometry": {"coordinates":[85.356059,20.645202],"type":"Point"}
}