{
  "type": "Feature",
  "properties": {
    "iso:country":"IN",
    "ks:ks_name":"Tingapakhan",
    "ks:ks_pop":189,
    "ks:ks_type":"HABITATION",
    "name:eng_x_preferred":[
        "Tingapakhan"
    ],
    "wof:name":"Tingapakhan",
    "wof:placetype":"locality",
    "wof:population":189
},
  "geometry": {"coordinates":[82.685382,19.465369],"type":"Point"}
}