{
  "type": "Feature",
  "properties": {
    "gn:admin1_code":"12",
    "gn:admin2_code":"14.0",
    "gn:asciiname":"Vidai",
    "gn:country_code":"IN",
    "gn:dem":1702,
    "gn:feature_class":"P",
    "gn:feature_code":"PPL",
    "gn:name":"Vidai",
    "gn:population":0,
    "gn:timezone":"Asia/Kolkata",
    "iso:country":"IN",
    "name:cat_x_preferred":[
        "Vidai"
    ],
    "name:ceb_x_preferred":[
        "Vidai"
    ],
    "name:deu_x_preferred":[
        "Vidai"
    ],
    "name:eus_x_preferred":[
        "Vidai"
    ],
    "name:fra_x_preferred":[
        "Vidai"
    ],
    "name:hun_x_preferred":[
        "Vidai"
    ],
    "name:ind_x_preferred":[
        "Vidai"
    ],
    "name:ita_x_preferred":[
        "Vidai"
    ],
    "name:kaz_x_preferred":[
        "\u0412\u0438\u0434\u0435"
    ],
    "name:lat_x_preferred":[
        "Vidai"
    ],
    "name:msa_x_preferred":[
        "Vidai"
    ],
    "name:nld_x_preferred":[
        "Vidai"
    ],
    "name:oci_x_preferred":[
        "Vidai"
    ],
    "name:pms_x_preferred":[
        "Vidai"
    ],
    "name:pol_x_preferred":[
        "Vidai"
    ],
    "name:por_x_preferred":[
        "Vidai"
    ],
    "name:ron_x_preferred":[
        "Vidai"
    ],
    "name:slk_x_preferred":[
        "Vidai"
    ],
    "name:spa_x_preferred":[
        "Vidai"
    ],
    "name:swe_x_preferred":[
        "Vidai"
    ],
    "name:ukr_x_preferred":[
        "\u0412\u0456\u0434\u0435"
    ],
    "name:uzb_x_preferred":[
        "Vidai"
    ],
    "name:vie_x_preferred":[
        "Vidai"
    ],
    "name:vol_x_preferred":[
        "Vidai"
    ],
    "name:war_x_preferred":[
        "Vidai"
    ],
    "name:zho_x_preferred":[
        "\u7ef4\u4ee3"
    ],
    "wof:name":"Vidai",
    "wof:placetype":"locality"
},
  "geometry": {"coordinates":[75.21066,33.81674],"type":"Point"}
}