{
  "type": "Feature",
  "properties": {
    "gn:admin1_code":"24.0",
    "gn:admin2_code":"105.0",
    "gn:asciiname":"Tirkha Ka Nagla",
    "gn:country_code":"IN",
    "gn:dem":201,
    "gn:feature_class":"P",
    "gn:feature_code":"PPL",
    "gn:name":"Tirkha Ka Nagla",
    "gn:population":0,
    "gn:timezone":"Asia/Kolkata",
    "iso:country":"IN",
    "wof:name":"Tirkha Ka Nagla",
    "wof:placetype":"neighbourhood"
},
  "geometry": {"coordinates":[77.27558999999999,26.97563],"type":"Point"}
}