{
  "type": "Feature",
  "properties": {
    "gn:admin1_code":"10.0",
    "gn:admin2_code":"76.0",
    "gn:asciiname":"Chhapra",
    "gn:country_code":"IN",
    "gn:dem":228,
    "gn:feature_class":"P",
    "gn:feature_code":"PPL",
    "gn:name":"Chhapra",
    "gn:population":0,
    "gn:timezone":"Asia/Kolkata",
    "iso:country":"IN",
    "name:ben_x_preferred":[
        "\u099b\u09be\u09aa\u09b0\u09be"
    ],
    "name:bih_x_preferred":[
        "\u091b\u092a\u0930\u093e"
    ],
    "name:bpy_x_preferred":[
        "\u099a\u09be\u09aa\u09b0\u09be"
    ],
    "name:ceb_x_preferred":[
        "Chhapra"
    ],
    "name:deu_x_preferred":[
        "Chhapra"
    ],
    "name:fas_x_preferred":[
        "\u0686\u0627\u067e\u0631\u0627"
    ],
    "name:fra_x_preferred":[
        "Chhapra"
    ],
    "name:hif_x_preferred":[
        "Chhapra"
    ],
    "name:hin_x_preferred":[
        "\u091b\u092a\u0930\u093e"
    ],
    "name:ita_x_preferred":[
        "Chapra"
    ],
    "name:mai_x_preferred":[
        "\u091b\u092a\u0930\u093e"
    ],
    "name:mar_x_preferred":[
        "\u091b\u092a\u094d\u0930\u093e"
    ],
    "name:nep_x_preferred":[
        "\u091b\u092a\u0930\u093e"
    ],
    "name:new_x_preferred":[
        "\u091b\u092a\u0930\u093e"
    ],
    "name:nld_x_preferred":[
        "Chhapra"
    ],
    "name:ori_x_preferred":[
        "\u0b1b\u0b2a\u0b4d\u0b30\u0b3e"
    ],
    "name:pam_x_preferred":[
        "Chapra"
    ],
    "name:pnb_x_preferred":[
        "\u0686\u06be\u0627\u067e\u0631\u0627"
    ],
    "name:pol_x_preferred":[
        "Chhapra"
    ],
    "name:por_x_preferred":[
        "Chapra"
    ],
    "name:rus_x_preferred":[
        "\u0427\u0445\u0430\u043f\u0440\u0430"
    ],
    "name:san_x_preferred":[
        "\u091b\u092a\u0930\u093e"
    ],
    "name:spa_x_preferred":[
        "Chhapra"
    ],
    "name:srp_x_preferred":[
        "\u0427\u0430\u043f\u0440\u0430"
    ],
    "name:swe_x_preferred":[
        "Chapra"
    ],
    "name:tam_x_preferred":[
        "\u0b9a\u0baa\u0bcd\u0bb0\u0bbe"
    ],
    "name:tgl_x_preferred":[
        "Chhapra"
    ],
    "name:ukr_x_preferred":[
        "\u0427\u0445\u0430\u043f\u0440\u0430"
    ],
    "name:urd_x_preferred":[
        "\u0686\u06be\u0627\u067e\u0631\u0627"
    ],
    "name:vie_x_preferred":[
        "Chapra"
    ],
    "name:war_x_preferred":[
        "Chhapra"
    ],
    "name:zho_x_preferred":[
        "\u6070\u666e\u62c9"
    ],
    "wof:name":"Chhapra",
    "wof:placetype":"locality"
},
  "geometry": {"coordinates":[76.54295999999999,29.12561],"type":"Point"}
}