{
  "type": "Feature",
  "properties": {
    "iso:country":"IN",
    "ks:ks_alt_nam":"Nunai FV",
    "ks:ks_name":"Nunai Fv",
    "ks:ks_pop":6924,
    "ks:ks_type":"HABITATION",
    "name:eng_x_preferred":[
        "Nunai Fv"
    ],
    "wof:name":"Nunai Fv",
    "wof:placetype":"locality",
    "wof:population":6924
},
  "geometry": {"coordinates":[92.66689100000001,24.496869],"type":"Point"}
}