{
  "type": "Feature",
  "properties": {
    "iso:country":"IN",
    "ks:ks_name":"Cherai Jn",
    "ks:ks_pop":560,
    "ks:ks_type":"HABITATION",
    "name:eng_x_preferred":[
        "Cherai Jn"
    ],
    "wof:name":"Cherai Jn",
    "wof:placetype":"locality",
    "wof:population":560
},
  "geometry": {"coordinates":[76.26233999999999,11.24478],"type":"Point"}
}