{
  "type": "Feature",
  "properties": {
    "iso:country":"IN",
    "ks:ks_name":"Sacred Hill Rd Jn",
    "ks:ks_pop":246,
    "ks:ks_type":"HABITATION",
    "ks:ks_uagg_main":0,
    "name:eng_x_preferred":[
        "Sacred Hill Rd Jn"
    ],
    "wof:name":"Sacred Hill Rd Jn",
    "wof:placetype":"locality",
    "wof:population":246
},
  "geometry": {"coordinates":[76.313884,10.425582],"type":"Point"}
}