{
  "type": "Feature",
  "properties": {
    "iso:country":"IN",
    "ks:ks_alt_nam":"Panery T.E.",
    "ks:ks_name":"Panery T.e.",
    "ks:ks_pop":4454,
    "ks:ks_type":"HABITATION",
    "ks:ks_uagg_main":0,
    "name:eng_x_preferred":[
        "Panery T.e."
    ],
    "wof:name":"Panery T.e.",
    "wof:placetype":"neighbourhood",
    "wof:population":4454
},
  "geometry": {"coordinates":[91.896985,26.745382],"type":"Point"}
}