{
  "type": "Feature",
  "properties": {
    "gn:admin1_code":"39.0",
    "gn:admin2_code":"64.0",
    "gn:asciiname":"Bajina",
    "gn:country_code":"IN",
    "gn:dem":1157,
    "gn:feature_class":"P",
    "gn:feature_code":"PPL",
    "gn:name":"Baj\u012bna",
    "gn:population":0,
    "gn:timezone":"Asia/Kolkata",
    "iso:country":"IN",
    "ks:ks_alt_nam":"Baj\u012bna",
    "ks:ks_name":"Bajina",
    "ks:ks_type":"VILLAGE",
    "name:eng_x_preferred":[
        "Bajina"
    ],
    "name:eng_x_variant":[
        "Baj\u012bna"
    ],
    "wof:name":"Bajina",
    "wof:placetype":"locality"
},
  "geometry": {"coordinates":[79.35928800000001,29.743219],"type":"Point"}
}