{
  "type": "Feature",
  "properties": {
    "iso:country":"IN",
    "ks:ks_name":"Karkhana Bharatgarh",
    "ks:ks_pop":0,
    "ks:ks_type":"VILLAGE",
    "name:eng_x_preferred":[
        "Karkhana Bharatgarh"
    ],
    "wof:name":"Karkhana Bharatgarh",
    "wof:placetype":"locality",
    "wof:population":0
},
  "geometry": {"coordinates":[76.427469,30.966497],"type":"Point"}
}