{
  "type": "Feature",
  "properties": {
    "iso:country":"IN",
    "ks:ks_name":"Pondi",
    "ks:ks_pop":1396,
    "ks:ks_type":"HABITATION",
    "name:eng_x_preferred":[
        "Pondi"
    ],
    "wof:name":"Pondi",
    "wof:placetype":"locality",
    "wof:population":1396
},
  "geometry": {"coordinates":[80.90871300000001,24.044275],"type":"Point"}
}