{
  "type": "Feature",
  "properties": {
    "gn:admin1_code":"34.0",
    "gn:admin2_code":"221.0",
    "gn:asciiname":"Bharwari",
    "gn:country_code":"IN",
    "gn:dem":49,
    "gn:feature_class":"P",
    "gn:feature_code":"PPL",
    "gn:name":"Bharw\u0101ri",
    "gn:population":0,
    "gn:timezone":"Asia/Kolkata",
    "iso:country":"IN",
    "name:bpy_x_preferred":[
        "\u09ad\u09be\u09b0\u09f1\u09be\u09b0\u09bf"
    ],
    "name:ceb_x_preferred":[
        "Bharw\u0101ri"
    ],
    "name:hin_x_preferred":[
        "\u092d\u0930\u0935\u093e\u0930\u0940"
    ],
    "name:ita_x_preferred":[
        "Bharwari"
    ],
    "name:mlg_x_preferred":[
        "Bharwari"
    ],
    "name:msa_x_preferred":[
        "Bharwari"
    ],
    "name:new_x_preferred":[
        "\u092d\u0930\u094d\u0935\u0930\u0940"
    ],
    "name:nld_x_preferred":[
        "Bharwari"
    ],
    "name:pol_x_preferred":[
        "Bharwari"
    ],
    "name:por_x_preferred":[
        "Bharwari"
    ],
    "name:swe_x_preferred":[
        "Bharw\u0101ri"
    ],
    "name:urd_x_preferred":[
        "\u0628\u06be\u0631\u0648\u0627\u0631\u06cc"
    ],
    "name:vie_x_preferred":[
        "Bharwari"
    ],
    "name:zho_x_preferred":[
        "\u5df4\u5c14\u74e6\u91cc"
    ],
    "wof:name":"Bharwari",
    "wof:placetype":"locality"
},
  "geometry": {"coordinates":[86.08723000000001,25.8052],"type":"Point"}
}