{
  "type": "Feature",
  "properties": {
    "iso:country":"IN",
    "ks:ks_name":"Kallidumbu Jn",
    "ks:ks_pop":925,
    "ks:ks_type":"HABITATION",
    "name:eng_x_preferred":[
        "Kallidumbu Jn"
    ],
    "wof:name":"Kallidumbu Jn",
    "wof:placetype":"locality",
    "wof:population":925
},
  "geometry": {"coordinates":[76.12971,11.214577],"type":"Point"}
}