{
  "type": "Feature",
  "properties": {
    "iso:country":"IN",
    "ks:ks_name":"Samiti Khera",
    "ks:ks_pop":60,
    "ks:ks_type":"HABITATION",
    "name:eng_x_preferred":[
        "Samiti Khera"
    ],
    "wof:name":"Samiti Khera",
    "wof:placetype":"locality",
    "wof:population":60
},
  "geometry": {"coordinates":[72.78268300000001,24.718703],"type":"Point"}
}