{
  "type": "Feature",
  "properties": {
    "iso:country":"IN",
    "ks:ks_name":"Naranjivalasa",
    "ks:ks_pop":60,
    "ks:ks_type":"HABITATION",
    "name:eng_x_preferred":[
        "Naranjivalasa"
    ],
    "wof:name":"Naranjivalasa",
    "wof:placetype":"locality",
    "wof:population":60
},
  "geometry": {"coordinates":[82.815956,18.317789],"type":"Point"}
}