{
  "type": "Feature",
  "properties": {
    "gn:admin1_code":"36.0",
    "gn:admin2_code":"133.0",
    "gn:asciiname":"Grahi Majra Mimla",
    "gn:country_code":"IN",
    "gn:dem":241,
    "gn:feature_class":"P",
    "gn:feature_code":"PPL",
    "gn:name":"Grahi M\u0101jra M\u012bmla",
    "gn:population":0,
    "gn:timezone":"Asia/Kolkata",
    "iso:country":"IN",
    "wof:name":"Grahi Majra Mimla",
    "wof:placetype":"locality"
},
  "geometry": {"coordinates":[77.30759999999999,29.3676],"type":"Point"}
}