{
  "type": "Feature",
  "properties": {
    "gn:admin1_code":"35.0",
    "gn:admin2_code":"422.0",
    "gn:asciiname":"Mau Dera",
    "gn:country_code":"IN",
    "gn:dem":195,
    "gn:feature_class":"P",
    "gn:feature_code":"PPL",
    "gn:name":"Mau Dera",
    "gn:population":0,
    "gn:timezone":"Asia/Kolkata",
    "iso:country":"IN",
    "wof:name":"Mau Dera",
    "wof:placetype":"locality"
},
  "geometry": {"coordinates":[78.46384999999999,25.88819],"type":"Point"}
}