{
  "type": "Feature",
  "properties": {
    "iso:country":"IN",
    "ks:ks_name":"Chamarhi",
    "ks:ks_pop":189,
    "ks:ks_type":"HABITATION",
    "name:eng_x_preferred":[
        "Chamarhi"
    ],
    "wof:name":"Chamarhi",
    "wof:placetype":"locality",
    "wof:population":189
},
  "geometry": {"coordinates":[81.391397,27.075519],"type":"Point"}
}