{
  "type": "Feature",
  "properties": {
    "iso:country":"IN",
    "ks:ks_name":"Melmegur",
    "ks:ks_pop":69,
    "ks:ks_type":"HABITATION",
    "name:eng_x_preferred":[
        "Melmegur"
    ],
    "wof:name":"Melmegur",
    "wof:placetype":"locality",
    "wof:population":69
},
  "geometry": {"coordinates":[75.302525,13.326379],"type":"Point"}
}