{
  "type": "Feature",
  "properties": {
    "iso:country":"IN",
    "ks:ks_name":"Devaragadde",
    "ks:ks_pop":22,
    "ks:ks_type":"HABITATION",
    "name:eng_x_preferred":[
        "Devaragadde"
    ],
    "wof:name":"Devaragadde",
    "wof:placetype":"locality",
    "wof:population":22
},
  "geometry": {"coordinates":[74.660183,14.971141],"type":"Point"}
}