{
  "type": "Feature",
  "properties": {
    "iso:country":"IN",
    "ks:ks_name":"Danijhola",
    "ks:ks_pop":69,
    "ks:ks_type":"VILLAGE",
    "name:eng_x_preferred":[
        "Danijhola"
    ],
    "wof:name":"Danijhola",
    "wof:placetype":"locality",
    "wof:population":69
},
  "geometry": {"coordinates":[83.297388,19.061726],"type":"Point"}
}