{
  "type": "Feature",
  "properties": {
    "iso:country":"IN",
    "ks:ks_name":"Chinthamanivari Palle",
    "ks:ks_pop":177,
    "ks:ks_type":"HABITATION",
    "name:eng_x_preferred":[
        "Chinthamanivari Palle"
    ],
    "wof:name":"Chinthamanivari Palle",
    "wof:placetype":"locality",
    "wof:population":177
},
  "geometry": {"coordinates":[78.567651,13.850897],"type":"Point"}
}