{
  "type": "Feature",
  "properties": {
    "gn:admin1_code":"35",
    "gn:admin2_code":"426.0",
    "gn:asciiname":"Bilha",
    "gn:country_code":"IN",
    "gn:dem":338,
    "gn:feature_class":"P",
    "gn:feature_code":"PPL",
    "gn:name":"Bilha",
    "gn:population":0,
    "gn:timezone":"Asia/Kolkata",
    "iso:country":"IN",
    "name:ben_x_preferred":[
        "\u09ac\u09bf\u09b2\u09b9\u09be"
    ],
    "name:ita_x_preferred":[
        "Bilha"
    ],
    "name:mlg_x_preferred":[
        "Bilha"
    ],
    "name:msa_x_preferred":[
        "Bilha"
    ],
    "name:nld_x_preferred":[
        "Bilha"
    ],
    "name:spa_x_preferred":[
        "Bilha"
    ],
    "name:urd_x_preferred":[
        "\u0628\u0644\u06c1\u0627"
    ],
    "name:vie_x_preferred":[
        "Bilha"
    ],
    "name:zho_x_preferred":[
        "\u6bd4\u5c14\u54c8"
    ],
    "wof:name":"Bilha",
    "wof:placetype":"locality"
},
  "geometry": {"coordinates":[80.29312,24.51801],"type":"Point"}
}