{
  "type": "Feature",
  "properties": {
    "gn:admin1_code":"11",
    "gn:admin2_code":"23.0",
    "gn:asciiname":"Sukwas",
    "gn:country_code":"IN",
    "gn:dem":3040,
    "gn:feature_class":"P",
    "gn:feature_code":"PPL",
    "gn:name":"Sukw\u0101s",
    "gn:population":0,
    "gn:timezone":"Asia/Kolkata",
    "iso:country":"IN",
    "wof:name":"Sukwas",
    "wof:placetype":"locality"
},
  "geometry": {"coordinates":[76.57004000000001,32.96272],"type":"Point"}
}