{
  "type": "Feature",
  "properties": {
    "gn:admin1_code":"11.0",
    "gn:admin2_code":"26.0",
    "gn:asciiname":"Shakoti",
    "gn:country_code":"IN",
    "gn:dem":1561,
    "gn:feature_class":"P",
    "gn:feature_code":"PPL",
    "gn:name":"Shakoti",
    "gn:population":0,
    "gn:timezone":"Asia/Kolkata",
    "iso:country":"IN",
    "wof:name":"Shakoti",
    "wof:placetype":"locality"
},
  "geometry": {"coordinates":[77.57711999999999,31.42908],"type":"Point"}
}