{
  "type": "Feature",
  "properties": {
    "iso:country":"IN",
    "ks:ks_alt_nam":"Nirmali na mu",
    "ks:ks_name":"Nirmali Na Mu",
    "ks:ks_pop":149,
    "ks:ks_type":"HABITATION",
    "name:eng_x_preferred":[
        "Nirmali Na Mu"
    ],
    "wof:name":"Nirmali Na Mu",
    "wof:placetype":"locality",
    "wof:population":149
},
  "geometry": {"coordinates":[73.191194,23.043639],"type":"Point"}
}