{
  "type": "Feature",
  "properties": {
    "iso:country":"IN",
    "ks:ks_name":"Varachiwadi",
    "ks:ks_pop":156,
    "ks:ks_type":"HABITATION",
    "name:eng_x_preferred":[
        "Varachiwadi"
    ],
    "wof:name":"Varachiwadi",
    "wof:placetype":"locality",
    "wof:population":156
},
  "geometry": {"coordinates":[73.758819,15.739171],"type":"Point"}
}