{
  "type": "Feature",
  "properties": {
    "gn:admin1_code":"24.0",
    "gn:admin2_code":"104.0",
    "gn:asciiname":"Bijwar",
    "gn:country_code":"IN",
    "gn:dem":272,
    "gn:feature_class":"P",
    "gn:feature_code":"PPL",
    "gn:name":"B\u012bjw\u0101r",
    "gn:population":0,
    "gn:timezone":"Asia/Kolkata",
    "iso:country":"IN",
    "wof:name":"Bijwar",
    "wof:placetype":"neighbourhood"
},
  "geometry": {"coordinates":[76.58932,27.40401],"type":"Point"}
}