{
  "type": "Feature",
  "properties": {
    "iso:country":"IN",
    "ks:ks_name":"Barail",
    "ks:ks_pop":368,
    "ks:ks_type":"VILLAGE",
    "ks:ks_uagg_main":0,
    "name:eng_x_preferred":[
        "Barail"
    ],
    "wof:name":"Barail",
    "wof:placetype":"neighbourhood",
    "wof:population":368
},
  "geometry": {"coordinates":[86.572693,25.281991],"type":"Point"}
}