{
  "type": "Feature",
  "properties": {
    "iso:country":"IN",
    "ks:ks_name":"Patel Falia",
    "ks:ks_pop":596,
    "ks:ks_type":"HABITATION",
    "name:eng_x_preferred":[
        "Patel Falia"
    ],
    "wof:name":"Patel Falia",
    "wof:placetype":"locality",
    "wof:population":596
},
  "geometry": {"coordinates":[73.293944,20.787306],"type":"Point"}
}