{
  "type": "Feature",
  "properties": {
    "iso:country":"IN",
    "ks:ks_name":"Poovayeepatty",
    "ks:ks_pop":80,
    "ks:ks_type":"HABITATION",
    "name:eng_x_preferred":[
        "Poovayeepatty"
    ],
    "wof:name":"Poovayeepatty",
    "wof:placetype":"locality",
    "wof:population":80
},
  "geometry": {"coordinates":[78.468813,10.781468],"type":"Point"}
}