{
  "type": "Feature",
  "properties": {
    "iso:country":"IN",
    "ks:ks_name":"Lala Tola",
    "ks:ks_pop":201,
    "ks:ks_type":"HABITATION",
    "name:eng_x_preferred":[
        "Lala Tola"
    ],
    "wof:name":"Lala Tola",
    "wof:placetype":"locality",
    "wof:population":201
},
  "geometry": {"coordinates":[86.130128,24.274345],"type":"Point"}
}