{
  "type": "Feature",
  "properties": {
    "gn:admin1_code":"23",
    "gn:admin2_code":"38.0",
    "gn:asciiname":"Thitanwala",
    "gn:country_code":"IN",
    "gn:dem":483,
    "gn:feature_class":"P",
    "gn:feature_code":"PPL",
    "gn:name":"Thitanw\u0101la",
    "gn:population":0,
    "gn:timezone":"Asia/Kolkata",
    "iso:country":"IN",
    "wof:name":"Thitanwala",
    "wof:placetype":"locality"
},
  "geometry": {"coordinates":[75.90488000000001,31.76406],"type":"Point"}
}