{
  "type": "Feature",
  "properties": {
    "iso:country":"IN",
    "ks:ks_name":"Beeranahalli",
    "ks:ks_type":"VILLAGE",
    "name:eng_x_preferred":[
        "Beeranahalli"
    ],
    "wof:name":"Beeranahalli",
    "wof:placetype":"locality"
},
  "geometry": {"coordinates":[76.68489700000001,12.567155],"type":"Point"}
}