{
  "type": "Feature",
  "properties": {
    "iso:country":"IN",
    "ks:ks_name":"Kerigoda",
    "ks:ks_pop":14,
    "ks:ks_type":"VILLAGE",
    "name:eng_x_preferred":[
        "Kerigoda"
    ],
    "wof:name":"Kerigoda",
    "wof:placetype":"locality",
    "wof:population":14
},
  "geometry": {"coordinates":[87.579065,25.134177],"type":"Point"}
}