{
  "type": "Feature",
  "properties": {
    "iso:country":"IN",
    "ks:ks_name":"Dhansagar",
    "ks:ks_pop":276,
    "ks:ks_type":"HABITATION",
    "name:eng_x_preferred":[
        "Dhansagar"
    ],
    "wof:name":"Dhansagar",
    "wof:placetype":"locality",
    "wof:population":276
},
  "geometry": {"coordinates":[72.317111,26.765875],"type":"Point"}
}