{
  "type": "Feature",
  "properties": {
    "iso:country":"IN",
    "ks:ks_name":"Vadugani",
    "ks:ks_pop":212,
    "ks:ks_type":"HABITATION",
    "name:eng_x_preferred":[
        "Vadugani"
    ],
    "wof:name":"Vadugani",
    "wof:placetype":"locality",
    "wof:population":212
},
  "geometry": {"coordinates":[78.83405500000001,9.934725],"type":"Point"}
}