{
  "type": "Feature",
  "properties": {
    "iso:country":"IN",
    "ks:ks_alt_nam":"LAVATE WASTI",
    "ks:ks_name":"Lavate Wasti",
    "ks:ks_pop":124,
    "ks:ks_type":"HABITATION",
    "name:eng_x_preferred":[
        "Lavate Wasti"
    ],
    "wof:name":"Lavate Wasti",
    "wof:placetype":"locality",
    "wof:population":124
},
  "geometry": {"coordinates":[75.13400900000001,16.976725],"type":"Point"}
}