{
  "type": "Feature",
  "properties": {
    "iso:country":"IN",
    "ks:ks_name":"Jagatpur",
    "ks:ks_pop":639,
    "ks:ks_type":"VILLAGE",
    "name:eng_x_preferred":[
        "Jagatpur"
    ],
    "wof:name":"Jagatpur",
    "wof:placetype":"locality",
    "wof:population":639
},
  "geometry": {"coordinates":[87.397182,22.102707],"type":"Point"}
}