{
  "type": "Feature",
  "properties": {
    "iso:country":"IN",
    "ks:ks_name":"Kaud",
    "ks:ks_pop":31,
    "ks:ks_type":"HABITATION",
    "name:eng_x_preferred":[
        "Kaud"
    ],
    "wof:name":"Kaud",
    "wof:placetype":"locality",
    "wof:population":31
},
  "geometry": {"coordinates":[78.364203,30.291983],"type":"Point"}
}