{
  "type": "Feature",
  "properties": {
    "gn:admin1_code":"36",
    "gn:admin2_code":"201.0",
    "gn:asciiname":"Nainpur",
    "gn:country_code":"IN",
    "gn:dem":168,
    "gn:feature_class":"P",
    "gn:feature_code":"PPL",
    "gn:name":"Nainpur",
    "gn:population":0,
    "gn:timezone":"Asia/Kolkata",
    "iso:country":"IN",
    "name:ben_x_preferred":[
        "\u09a8\u09af\u09bc\u09a8\u09aa\u09c1\u09b0"
    ],
    "name:bpy_x_preferred":[
        "\u09a8\u09af\u09bc\u09a8\u09aa\u09c1\u09b0"
    ],
    "name:ceb_x_preferred":[
        "Nainpur"
    ],
    "name:hin_x_preferred":[
        "\u0928\u0948\u0928\u092a\u0941\u0930"
    ],
    "name:ita_x_preferred":[
        "Nainpur"
    ],
    "name:msa_x_preferred":[
        "Nainpur"
    ],
    "name:new_x_preferred":[
        "\u0928\u0948\u0928\u092a\u0941\u0930"
    ],
    "name:ori_x_preferred":[
        "\u0b28\u0b48\u0b28\u0b2a\u0b41\u0b30"
    ],
    "name:por_x_preferred":[
        "Nainpur"
    ],
    "name:spa_x_preferred":[
        "Nainpur"
    ],
    "name:swe_x_preferred":[
        "Nainpur"
    ],
    "name:urd_x_preferred":[
        "\u0646\u06cc\u0646 \u067e\u0648\u0631"
    ],
    "name:vie_x_preferred":[
        "Nainpur"
    ],
    "name:zho_x_preferred":[
        "\u5948\u6069\u666e\u5c14"
    ],
    "wof:name":"Nainpur",
    "wof:placetype":"locality"
},
  "geometry": {"coordinates":[78.73145,27.45688],"type":"Point"}
}