{
  "type": "Feature",
  "properties": {
    "iso:country":"IN",
    "ks:ks_name":"Lakhan Khera",
    "ks:ks_pop":766,
    "ks:ks_type":"HABITATION",
    "name:eng_x_preferred":[
        "Lakhan Khera"
    ],
    "wof:name":"Lakhan Khera",
    "wof:placetype":"locality",
    "wof:population":766
},
  "geometry": {"coordinates":[80.266667,26.1825],"type":"Point"}
}