{
  "type": "Feature",
  "properties": {
    "gn:admin1_code":"11",
    "gn:admin2_code":"31.0",
    "gn:asciiname":"Palashta",
    "gn:country_code":"IN",
    "gn:dem":1270,
    "gn:feature_class":"P",
    "gn:feature_code":"PPL",
    "gn:name":"Palashta",
    "gn:population":0,
    "gn:timezone":"Asia/Kolkata",
    "iso:country":"IN",
    "wof:name":"Palashta",
    "wof:placetype":"locality"
},
  "geometry": {"coordinates":[76.94880999999999,30.99266],"type":"Point"}
}