{
  "type": "Feature",
  "properties": {
    "gn:admin1_code":"11.0",
    "gn:admin2_code":"32.0",
    "gn:asciiname":"Lanad Kasar",
    "gn:country_code":"IN",
    "gn:dem":1169,
    "gn:feature_class":"P",
    "gn:feature_code":"PPL",
    "gn:name":"L\u0101nad Kas\u0101r",
    "gn:population":0,
    "gn:timezone":"Asia/Kolkata",
    "iso:country":"IN",
    "wof:name":"Lanad Kasar",
    "wof:placetype":"locality"
},
  "geometry": {"coordinates":[77.2328,30.84292],"type":"Point"}
}