{
  "type": "Feature",
  "properties": {
    "iso:country":"IN",
    "ks:ks_name":"Bandwaguda",
    "ks:ks_pop":46,
    "ks:ks_type":"HABITATION",
    "ks:ks_uagg_main":0,
    "name:eng_x_preferred":[
        "Bandwaguda"
    ],
    "wof:name":"Bandwaguda",
    "wof:placetype":"neighbourhood",
    "wof:population":46
},
  "geometry": {"coordinates":[82.09675,19.026326],"type":"Point"}
}