{
  "type": "Feature",
  "properties": {
    "iso:country":"IN",
    "ks:ks_name":"Thar Manohar",
    "ks:ks_pop":110,
    "ks:ks_type":"HABITATION",
    "name:eng_x_preferred":[
        "Thar Manohar"
    ],
    "wof:name":"Thar Manohar",
    "wof:placetype":"locality",
    "wof:population":110
},
  "geometry": {"coordinates":[78.54400699999999,27.034821],"type":"Point"}
}