{
  "type": "Feature",
  "properties": {
    "iso:country":"IN",
    "ks:ks_alt_nam":"Mulla gudde",
    "ks:ks_name":"Mulla Gudde",
    "ks:ks_pop":1012,
    "ks:ks_type":"HABITATION",
    "name:eng_x_preferred":[
        "Mulla Gudde"
    ],
    "wof:name":"Mulla Gudde",
    "wof:placetype":"locality",
    "wof:population":1012
},
  "geometry": {"coordinates":[74.956014,12.944305],"type":"Point"}
}