{
  "type": "Feature",
  "properties": {
    "gn:admin1_code":"37",
    "gn:admin2_code":"413.0",
    "gn:asciiname":"Kauro Khasgaon",
    "gn:country_code":"IN",
    "gn:dem":374,
    "gn:feature_class":"P",
    "gn:feature_code":"PPL",
    "gn:name":"Kauro Khasgaon",
    "gn:population":0,
    "gn:timezone":"Asia/Kolkata",
    "iso:country":"IN",
    "wof:name":"Kauro Khasgaon",
    "wof:placetype":"neighbourhood"
},
  "geometry": {"coordinates":[81.12299,20.10143],"type":"Point"}
}