{
  "type": "Feature",
  "properties": {
    "gn:admin1_code":"12",
    "gn:admin2_code":"7.0",
    "gn:asciiname":"Then",
    "gn:country_code":"IN",
    "gn:dem":555,
    "gn:feature_class":"P",
    "gn:feature_code":"PPL",
    "gn:name":"Then",
    "gn:population":0,
    "gn:timezone":"Asia/Kolkata",
    "iso:country":"IN",
    "name:deu_x_preferred":[
        "Then"
    ],
    "name:ita_x_preferred":[
        "Then"
    ],
    "wof:name":"Then",
    "wof:placetype":"locality"
},
  "geometry": {"coordinates":[75.7243,32.43775],"type":"Point"}
}