{
  "type": "Feature",
  "properties": {
    "gn:admin1_code":"36",
    "gn:admin2_code":"186.0",
    "gn:asciiname":"Bakuchi",
    "gn:country_code":"IN",
    "gn:dem":77,
    "gn:feature_class":"P",
    "gn:feature_code":"PPL",
    "gn:name":"Bakuchi",
    "gn:population":0,
    "gn:timezone":"Asia/Kolkata",
    "iso:country":"IN",
    "wof:name":"Bakuchi",
    "wof:placetype":"locality"
},
  "geometry": {"coordinates":[83.05558000000001,26.85934],"type":"Point"}
}