{
  "type": "Feature",
  "properties": {
    "iso:country":"IN",
    "ks:ks_name":"Hatibari",
    "ks:ks_pop":16,
    "ks:ks_type":"VILLAGE",
    "name:eng_x_preferred":[
        "Hatibari"
    ],
    "wof:name":"Hatibari",
    "wof:placetype":"locality",
    "wof:population":16
},
  "geometry": {"coordinates":[86.64009799999999,22.597013],"type":"Point"}
}