{
  "type": "Feature",
  "properties": {
    "iso:country":"IN",
    "ks:ks_name":"Gadimane",
    "ks:ks_pop":277,
    "ks:ks_type":"HABITATION",
    "name:eng_x_preferred":[
        "Gadimane"
    ],
    "wof:name":"Gadimane",
    "wof:placetype":"locality",
    "wof:population":277
},
  "geometry": {"coordinates":[74.954016,14.227249],"type":"Point"}
}