{
  "type": "Feature",
  "properties": {
    "gn:admin1_code":"34.0",
    "gn:admin2_code":"215.0",
    "gn:asciiname":"Katwasa",
    "gn:country_code":"IN",
    "gn:dem":52,
    "gn:feature_class":"P",
    "gn:feature_code":"PPL",
    "gn:name":"Katw\u0101sa",
    "gn:population":0,
    "gn:timezone":"Asia/Kolkata",
    "iso:country":"IN",
    "ks:ks_name":"Katwasa",
    "ks:ks_pop":1343,
    "ks:ks_type":"VILLAGE",
    "ks:ks_uagg_main":0,
    "name:eng_x_preferred":[
        "Katwasa"
    ],
    "wof:name":"Katwasa",
    "wof:placetype":"neighbourhood",
    "wof:population":1343
},
  "geometry": {"coordinates":[86.12609399999999,26.019879],"type":"Point"}
}