{
  "type": "Feature",
  "properties": {
    "gn:admin1_code":"36.0",
    "gn:admin2_code":"150.0",
    "gn:asciiname":"Ghor",
    "gn:country_code":"IN",
    "gn:dem":183,
    "gn:feature_class":"P",
    "gn:feature_code":"PPL",
    "gn:name":"Ghor",
    "gn:population":0,
    "gn:timezone":"Asia/Kolkata",
    "iso:country":"IN",
    "name:hun_x_preferred":[
        "Ghor"
    ],
    "wof:name":"Ghor",
    "wof:placetype":"locality"
},
  "geometry": {"coordinates":[79.43992,28.54659],"type":"Point"}
}