{
  "type": "Feature",
  "properties": {
    "iso:country":"IN",
    "ks:ks_name":"Bahabal Pur",
    "ks:ks_pop":964,
    "ks:ks_type":"HABITATION",
    "name:eng_x_preferred":[
        "Bahabal Pur"
    ],
    "wof:name":"Bahabal Pur",
    "wof:placetype":"locality",
    "wof:population":964
},
  "geometry": {"coordinates":[80.001009,26.323155],"type":"Point"}
}