{
  "type": "Feature",
  "properties": {
    "iso:country":"IN",
    "ks:ks_name":"Nallamvaripalle",
    "ks:ks_pop":91,
    "ks:ks_type":"HABITATION",
    "ks:ks_uagg_main":0,
    "name:eng_x_preferred":[
        "Nallamvaripalle"
    ],
    "wof:name":"Nallamvaripalle",
    "wof:placetype":"neighbourhood",
    "wof:population":91
},
  "geometry": {"coordinates":[78.650136,13.621109],"type":"Point"}
}