{
  "type": "Feature",
  "properties": {
    "iso:country":"IN",
    "ks:ks_name":"Sindhising",
    "ks:ks_pop":68,
    "ks:ks_type":"VILLAGE",
    "name:eng_x_preferred":[
        "Sindhising"
    ],
    "wof:name":"Sindhising",
    "wof:placetype":"locality",
    "wof:population":68
},
  "geometry": {"coordinates":[84.17608,19.004685],"type":"Point"}
}