{
  "type": "Feature",
  "properties": {
    "gn:admin1_code":"34.0",
    "gn:admin2_code":"213.0",
    "gn:asciiname":"Shyam",
    "gn:country_code":"IN",
    "gn:dem":42,
    "gn:feature_class":"P",
    "gn:feature_code":"PPL",
    "gn:name":"Shy\u0101m",
    "gn:population":0,
    "gn:timezone":"Asia/Kolkata",
    "iso:country":"IN",
    "name:bih_x_preferred":[
        "\u0936\u094d\u092f\u093e\u092e\u093e"
    ],
    "wof:name":"Shyam",
    "wof:placetype":"locality"
},
  "geometry": {"coordinates":[86.88412,25.71257],"type":"Point"}
}