{
  "type": "Feature",
  "properties": {
    "iso:country":"IN",
    "ks:ks_name":"Yerebailu",
    "ks:ks_pop":246,
    "ks:ks_type":"VILLAGE",
    "name:eng_x_preferred":[
        "Yerebailu"
    ],
    "wof:name":"Yerebailu",
    "wof:placetype":"locality",
    "wof:population":246
},
  "geometry": {"coordinates":[75.756152,13.731657],"type":"Point"}
}