{
  "type": "Feature",
  "properties": {
    "iso:country":"IN",
    "ks:ks_name":"Karlamane",
    "ks:ks_pop":194,
    "ks:ks_type":"HABITATION",
    "name:eng_x_preferred":[
        "Karlamane"
    ],
    "wof:name":"Karlamane",
    "wof:placetype":"locality",
    "wof:population":194
},
  "geometry": {"coordinates":[74.686339,14.414035],"type":"Point"}
}