{
  "type": "Feature",
  "properties": {
    "iso:country":"IN",
    "ks:ks_name":"Satgharia No.1",
    "ks:ks_pop":37,
    "ks:ks_type":"HABITATION",
    "name:eng_x_preferred":[
        "Satgharia No.1"
    ],
    "wof:name":"Satgharia No.1",
    "wof:placetype":"locality",
    "wof:population":37
},
  "geometry": {"coordinates":[91.483442,26.179161],"type":"Point"}
}