{
  "type": "Feature",
  "properties": {
    "gn:admin1_code":"36.0",
    "gn:admin2_code":"184.0",
    "gn:asciiname":"Khanta",
    "gn:country_code":"IN",
    "gn:dem":101,
    "gn:feature_class":"P",
    "gn:feature_code":"PPL",
    "gn:name":"Khanta",
    "gn:population":0,
    "gn:timezone":"Asia/Kolkata",
    "iso:country":"IN",
    "ks:ks_name":"Khanta",
    "ks:ks_pop":496,
    "ks:ks_type":"VILLAGE",
    "name:eng_x_preferred":[
        "Khanta"
    ],
    "wof:name":"Khanta",
    "wof:placetype":"locality",
    "wof:population":496
},
  "geometry": {"coordinates":[82.501212,27.290375],"type":"Point"}
}