{
  "type": "Feature",
  "properties": {
    "gn:admin1_code":"09",
    "gn:admin2_code":"468.0",
    "gn:asciiname":"Tuna",
    "gn:country_code":"IN",
    "gn:dem":15,
    "gn:feature_class":"P",
    "gn:feature_code":"PPL",
    "gn:name":"Tuna",
    "gn:population":0,
    "gn:timezone":"Asia/Kolkata",
    "iso:country":"IN",
    "name:bel_x_preferred":[
        "\u0422\u0443\u043d\u0446\u044b"
    ],
    "name:ben_x_preferred":[
        "\u099f\u09c1\u09a8\u09be"
    ],
    "name:ckb_x_preferred":[
        "\u062a\u0648\u0646\u06d5"
    ],
    "name:deu_x_preferred":[
        "Thunfische"
    ],
    "name:ell_x_preferred":[
        "\u03a4\u03cc\u03bd\u03bf\u03c2"
    ],
    "name:fas_x_preferred":[
        "\u0645\u0627\u0647\u06cc \u062a\u0646"
    ],
    "name:fij_x_preferred":[
        "Urau"
    ],
    "name:fin_x_preferred":[
        "Tonnikalat"
    ],
    "name:fra_x_preferred":[
        "Thunnini"
    ],
    "name:heb_x_preferred":[
        "\u05d8\u05d5\u05e0\u05d4"
    ],
    "name:ind_x_preferred":[
        "Tuna"
    ],
    "name:kan_x_preferred":[
        "\u0c9f\u0ccd\u0caf\u0cc2\u0ca8 \u0cae\u0cc0\u0ca8\u0cc1"
    ],
    "name:kor_x_preferred":[
        "\ub2e4\ub791\uc5b4"
    ],
    "name:mal_x_preferred":[
        "\u0d1a\u0d42\u0d30"
    ],
    "name:msa_x_preferred":[
        "Tuna"
    ],
    "name:pnb_x_preferred":[
        "\u0679\u0648\u0646\u0627"
    ],
    "name:pol_x_preferred":[
        "Tu\u0144czyki"
    ],
    "name:por_x_preferred":[
        "Thunnini"
    ],
    "name:rus_x_preferred":[
        "\u0422\u0443\u043d\u0446\u044b"
    ],
    "name:sco_x_preferred":[
        "Tuna"
    ],
    "name:spa_x_preferred":[
        "Thunini"
    ],
    "name:sun_x_preferred":[
        "Tuna"
    ],
    "name:tam_x_preferred":[
        "\u0b9a\u0bc2\u0bb0\u0bc8"
    ],
    "name:tgl_x_preferred":[
        "Tulingan"
    ],
    "name:tha_x_preferred":[
        "\u0e1b\u0e25\u0e32\u0e17\u0e39\u0e19\u0e48\u0e32"
    ],
    "wof:name":"Tuna",
    "wof:placetype":"locality"
},
  "geometry": {"coordinates":[70.08074999999999,22.98673],"type":"Point"}
}