{
  "type": "Feature",
  "properties": {
    "iso:country":"IN",
    "ks:ks_name":"Naringjhola",
    "ks:ks_pop":109,
    "ks:ks_type":"HABITATION",
    "name:eng_x_preferred":[
        "Naringjhola"
    ],
    "wof:name":"Naringjhola",
    "wof:placetype":"locality",
    "wof:population":109
},
  "geometry": {"coordinates":[82.79093399999999,19.255442],"type":"Point"}
}