{
  "type": "Feature",
  "properties": {
    "iso:country":"IN",
    "ks:ks_name":"Barkian Tanur",
    "ks:ks_pop":0,
    "ks:ks_type":"VILLAGE",
    "name:eng_x_preferred":[
        "Barkian Tanur"
    ],
    "wof:name":"Barkian Tanur",
    "wof:placetype":"locality",
    "wof:population":0
},
  "geometry": {"coordinates":[75.974951,31.469631],"type":"Point"}
}