{
  "type": "Feature",
  "properties": {
    "gn:admin1_code":"23.0",
    "gn:admin2_code":"43.0",
    "gn:asciiname":"Mansurdewa",
    "gn:country_code":"IN",
    "gn:dem":210,
    "gn:feature_class":"P",
    "gn:feature_code":"PPL",
    "gn:name":"Mans\u016brdewa",
    "gn:population":0,
    "gn:timezone":"Asia/Kolkata",
    "iso:country":"IN",
    "wof:name":"Mansurdewa",
    "wof:placetype":"neighbourhood"
},
  "geometry": {"coordinates":[75.00935,30.95572],"type":"Point"}
}