{
  "type": "Feature",
  "properties": {
    "iso:country":"IN",
    "ks:ks_name":"Pdengtleit",
    "ks:ks_pop":349,
    "ks:ks_type":"HABITATION",
    "name:eng_x_preferred":[
        "Pdengtleit"
    ],
    "wof:name":"Pdengtleit",
    "wof:placetype":"locality",
    "wof:population":349
},
  "geometry": {"coordinates":[92.20999999999999,25.82],"type":"Point"}
}