{
  "type": "Feature",
  "properties": {
    "iso:country":"IN",
    "ks:ks_name":"Jamphar",
    "ks:ks_pop":196,
    "ks:ks_type":"VILLAGE",
    "name:eng_x_preferred":[
        "Jamphar"
    ],
    "wof:name":"Jamphar",
    "wof:placetype":"locality",
    "wof:population":196
},
  "geometry": {"coordinates":[86.276764,20.085356],"type":"Point"}
}