{
  "type": "Feature",
  "properties": {
    "iso:country":"IN",
    "ks:ks_name":"P Natan",
    "ks:ks_pop":222,
    "ks:ks_type":"HABITATION",
    "ks:ks_uagg_main":0,
    "name:eng_x_preferred":[
        "P Natan"
    ],
    "wof:name":"P Natan",
    "wof:placetype":"neighbourhood",
    "wof:population":222
},
  "geometry": {"coordinates":[81.539157,26.327156],"type":"Point"}
}