{
  "type": "Feature",
  "properties": {
    "iso:country":"IN",
    "ks:ks_alt_nam":"Era dighalpani",
    "ks:ks_name":"Era Dighalpani",
    "ks:ks_pop":884,
    "ks:ks_type":"HABITATION",
    "name:eng_x_preferred":[
        "Era Dighalpani"
    ],
    "wof:name":"Era Dighalpani",
    "wof:placetype":"locality",
    "wof:population":884
},
  "geometry": {"coordinates":[93.05843900000001,26.154721],"type":"Point"}
}