{
  "type": "Feature",
  "properties": {
    "gn:admin1_code":"34.0",
    "gn:admin2_code":"232.0",
    "gn:asciiname":"Partapsagar",
    "gn:country_code":"IN",
    "gn:dem":66,
    "gn:feature_class":"P",
    "gn:feature_code":"PPL",
    "gn:name":"Part\u0101ps\u0101gar",
    "gn:population":0,
    "gn:timezone":"Asia/Kolkata",
    "iso:country":"IN",
    "wof:name":"Partapsagar",
    "wof:placetype":"locality"
},
  "geometry": {"coordinates":[84.09626,25.58386],"type":"Point"}
}