{
  "type": "Feature",
  "properties": {
    "iso:country":"IN",
    "ks:ks_name":"Silingjhora",
    "ks:ks_pop":72,
    "ks:ks_type":"VILLAGE",
    "name:eng_x_preferred":[
        "Silingjhora"
    ],
    "wof:name":"Silingjhora",
    "wof:placetype":"locality",
    "wof:population":72
},
  "geometry": {"coordinates":[90.034082,26.222886],"type":"Point"}
}