{
  "type": "Feature",
  "properties": {
    "gn:admin1_code":"34.0",
    "gn:admin2_code":"235.0",
    "gn:asciiname":"Tendua",
    "gn:country_code":"IN",
    "gn:dem":105,
    "gn:feature_class":"P",
    "gn:feature_code":"PPL",
    "gn:name":"Tendua",
    "gn:population":0,
    "gn:timezone":"Asia/Kolkata",
    "iso:country":"IN",
    "ks:ks_name":"Tendua",
    "ks:ks_pop":910,
    "ks:ks_type":"VILLAGE",
    "name:eng_x_preferred":[
        "Tendua"
    ],
    "wof:name":"Tendua",
    "wof:placetype":"locality",
    "wof:population":910
},
  "geometry": {"coordinates":[84.38121700000001,24.8124],"type":"Point"}
}