{
  "type": "Feature",
  "properties": {
    "iso:country":"IN",
    "ks:ks_name":"Tarlapal",
    "ks:ks_pop":355,
    "ks:ks_type":"VILLAGE",
    "name:eng_x_preferred":[
        "Tarlapal"
    ],
    "wof:name":"Tarlapal",
    "wof:placetype":"locality",
    "wof:population":355
},
  "geometry": {"coordinates":[81.272524,19.06328],"type":"Point"}
}