{
  "type": "Feature",
  "properties": {
    "iso:country":"IN",
    "ks:ks_name":"Silaua Jagir",
    "ks:ks_pop":944,
    "ks:ks_type":"VILLAGE",
    "name:eng_x_preferred":[
        "Silaua Jagir"
    ],
    "wof:name":"Silaua Jagir",
    "wof:placetype":"locality",
    "wof:population":944
},
  "geometry": {"coordinates":[79.344173,26.397367],"type":"Point"}
}