{
  "type": "Feature",
  "properties": {
    "gn:admin1_code":"2.0",
    "gn:admin2_code":"553.0",
    "gn:asciiname":"Obulapuram",
    "gn:country_code":"IN",
    "gn:dem":302,
    "gn:feature_class":"P",
    "gn:feature_code":"PPL",
    "gn:name":"Obul\u0101puram",
    "gn:population":0,
    "gn:timezone":"Asia/Kolkata",
    "iso:country":"IN",
    "name:tel_x_preferred":[
        "\u0c13\u0c2c\u0c41\u0c33\u0c3e\u0c2a\u0c41\u0c30\u0c02"
    ],
    "wof:name":"Obulapuram",
    "wof:placetype":"neighbourhood"
},
  "geometry": {"coordinates":[77.67345,14.97485],"type":"Point"}
}