{
  "type": "Feature",
  "properties": {
    "iso:country":"IN",
    "ks:ks_name":"Takiya South",
    "ks:ks_pop":356,
    "ks:ks_type":"HABITATION",
    "name:eng_x_preferred":[
        "Takiya South"
    ],
    "wof:name":"Takiya South",
    "wof:placetype":"locality",
    "wof:population":356
},
  "geometry": {"coordinates":[82.114211,27.811356],"type":"Point"}
}