{
  "type": "Feature",
  "properties": {
    "iso:country":"IN",
    "ks:ks_name":"Chandrapur",
    "ks:ks_type":"VILLAGE",
    "name:eng_x_preferred":[
        "Chandrapur"
    ],
    "wof:name":"Chandrapur",
    "wof:placetype":"locality"
},
  "geometry": {"coordinates":[83.229467,20.994039],"type":"Point"}
}