{
  "type": "Feature",
  "properties": {
    "iso:country":"IN",
    "ks:ks_alt_nam":"VADKARAMAL",
    "ks:ks_name":"Vadkaramal",
    "ks:ks_pop":277,
    "ks:ks_type":"HABITATION",
    "name:eng_x_preferred":[
        "Vadkaramal"
    ],
    "wof:name":"Vadkaramal",
    "wof:placetype":"locality",
    "wof:population":277
},
  "geometry": {"coordinates":[74.118548,16.639256],"type":"Point"}
}