{
  "type": "Feature",
  "properties": {
    "gn:admin1_code":"36.0",
    "gn:admin2_code":"155.0",
    "gn:asciiname":"Chunaha",
    "gn:country_code":"IN",
    "gn:dem":147,
    "gn:feature_class":"P",
    "gn:feature_code":"PPL",
    "gn:name":"Chun\u0101ha",
    "gn:population":0,
    "gn:timezone":"Asia/Kolkata",
    "iso:country":"IN",
    "wof:name":"Chunaha",
    "wof:placetype":"locality"
},
  "geometry": {"coordinates":[80.06439,27.7303],"type":"Point"}
}