{
  "type": "Feature",
  "properties": {
    "iso:country":"IN",
    "ks:ks_alt_nam":"USRA",
    "ks:ks_name":"Usra",
    "ks:ks_pop":90,
    "ks:ks_type":"HABITATION",
    "name:eng_x_preferred":[
        "Usra"
    ],
    "wof:name":"Usra",
    "wof:placetype":"locality",
    "wof:population":90
},
  "geometry": {"coordinates":[82.03591299999999,26.122974],"type":"Point"}
}