{
  "type": "Feature",
  "properties": {
    "iso:country":"IN",
    "ks:ks_name":"Puriyag Maphi",
    "ks:ks_pop":76,
    "ks:ks_type":"HABITATION",
    "name:eng_x_preferred":[
        "Puriyag Maphi"
    ],
    "wof:name":"Puriyag Maphi",
    "wof:placetype":"locality",
    "wof:population":76
},
  "geometry": {"coordinates":[80.077755,29.786713],"type":"Point"}
}