{
  "type": "Feature",
  "properties": {
    "iso:country":"IN",
    "ks:ks_name":"Settipalle",
    "ks:ks_pop":111,
    "ks:ks_type":"HABITATION",
    "name:eng_x_preferred":[
        "Settipalle"
    ],
    "wof:name":"Settipalle",
    "wof:placetype":"locality",
    "wof:population":111
},
  "geometry": {"coordinates":[79.039464,13.860298],"type":"Point"}
}