{
  "type": "Feature",
  "properties": {
    "iso:country":"IN",
    "ks:ks_name":"Padri Khurd",
    "ks:ks_pop":1616,
    "ks:ks_type":"VILLAGE",
    "name:eng_x_preferred":[
        "Padri Khurd"
    ],
    "wof:name":"Padri Khurd",
    "wof:placetype":"locality",
    "wof:population":1616
},
  "geometry": {"coordinates":[82.70301600000001,24.618277],"type":"Point"}
}