{
  "type": "Feature",
  "properties": {
    "iso:country":"IN",
    "ks:ks_name":"Kansa",
    "ks:ks_pop":524,
    "ks:ks_type":"VILLAGE",
    "name:eng_x_preferred":[
        "Kansa"
    ],
    "wof:name":"Kansa",
    "wof:placetype":"locality",
    "wof:population":524
},
  "geometry": {"coordinates":[85.621549,21.547638],"type":"Point"}
}