{
  "type": "Feature",
  "properties": {
    "iso:country":"IN",
    "ks:ks_name":"Sawane",
    "ks:ks_pop":413,
    "ks:ks_type":"HABITATION",
    "name:eng_x_preferred":[
        "Sawane"
    ],
    "wof:name":"Sawane",
    "wof:placetype":"locality",
    "wof:population":413
},
  "geometry": {"coordinates":[73.513976,18.136316],"type":"Point"}
}