{
  "type": "Feature",
  "properties": {
    "iso:country":"IN",
    "ks:ks_name":"Chhotegodre",
    "ks:ks_pop":100,
    "ks:ks_type":"VILLAGE",
    "name:eng_x_preferred":[
        "Chhotegodre"
    ],
    "wof:name":"Chhotegodre",
    "wof:placetype":"locality",
    "wof:population":100
},
  "geometry": {"coordinates":[81.43817199999999,18.829208],"type":"Point"}
}