{
  "type": "Feature",
  "properties": {
    "iso:country":"IN",
    "ks:ks_name":"Chitadungri",
    "ks:ks_pop":327,
    "ks:ks_type":"VILLAGE",
    "ks:ks_uagg_main":0,
    "name:eng_x_preferred":[
        "Chitadungri"
    ],
    "wof:name":"Chitadungri",
    "wof:placetype":"neighbourhood",
    "wof:population":327
},
  "geometry": {"coordinates":[83.14784299999999,20.696551],"type":"Point"}
}