{
  "type": "Feature",
  "properties": {
    "gn:admin1_code":"19.0",
    "gn:admin2_code":"582.0",
    "gn:asciiname":"Totlaganhalli",
    "gn:country_code":"IN",
    "gn:dem":889,
    "gn:feature_class":"P",
    "gn:feature_code":"PPL",
    "gn:name":"Totlag\u0101nhalli",
    "gn:population":0,
    "gn:timezone":"Asia/Kolkata",
    "iso:country":"IN",
    "ks:ks_name":"Thotliganahalli",
    "ks:ks_pop":920,
    "ks:ks_type":"VILLAGE",
    "name:eng_x_preferred":[
        "Thotliganahalli"
    ],
    "name:eng_x_variant":[
        "Totlaganhalli"
    ],
    "wof:name":"Thotliganahalli",
    "wof:placetype":"locality",
    "wof:population":920
},
  "geometry": {"coordinates":[77.849357,13.30985],"type":"Point"}
}