{
  "type": "Feature",
  "properties": {
    "iso:country":"IN",
    "ks:ks_name":"Naya Para",
    "ks:ks_pop":175,
    "ks:ks_type":"VILLAGE",
    "name:eng_x_preferred":[
        "Naya Para"
    ],
    "wof:name":"Naya Para",
    "wof:placetype":"locality",
    "wof:population":175
},
  "geometry": {"coordinates":[87.27926100000001,22.010025],"type":"Point"}
}