{
  "type": "Feature",
  "properties": {
    "iso:country":"IN",
    "ks:ks_alt_nam":"hale kolenahalli",
    "ks:ks_name":"Hale Kolenahalli",
    "ks:ks_pop":219,
    "ks:ks_type":"HABITATION",
    "name:eng_x_preferred":[
        "Hale Kolenahalli"
    ],
    "wof:name":"Hale Kolenahalli",
    "wof:placetype":"locality",
    "wof:population":219
},
  "geometry": {"coordinates":[75.864,14.344],"type":"Point"}
}