{
  "type": "Feature",
  "properties": {
    "iso:country":"IN",
    "ks:ks_name":"Mahespur",
    "ks:ks_pop":226,
    "ks:ks_type":"HABITATION",
    "ks:ks_uagg_main":0,
    "name:eng_x_preferred":[
        "Mahespur"
    ],
    "wof:name":"Mahespur",
    "wof:placetype":"neighbourhood",
    "wof:population":226
},
  "geometry": {"coordinates":[87.319146,23.751761],"type":"Point"}
}