{
  "type": "Feature",
  "properties": {
    "gn:admin1_code":"36.0",
    "gn:admin2_code":"141.0",
    "gn:asciiname":"Dhanpur",
    "gn:country_code":"IN",
    "gn:dem":209,
    "gn:feature_class":"P",
    "gn:feature_code":"PPL",
    "gn:name":"Dhanpur",
    "gn:population":0,
    "gn:timezone":"Asia/Kolkata",
    "iso:country":"IN",
    "wof:name":"Dhanpur",
    "wof:placetype":"locality"
},
  "geometry": {"coordinates":[77.64737,28.4907],"type":"Point"}
}