{
  "type": "Feature",
  "properties": {
    "iso:country":"IN",
    "ks:ks_name":"Chilnar",
    "ks:ks_pop":174,
    "ks:ks_type":"VILLAGE",
    "name:eng_x_preferred":[
        "Chilnar"
    ],
    "wof:name":"Chilnar",
    "wof:placetype":"locality",
    "wof:population":174
},
  "geometry": {"coordinates":[80.87341499999999,18.768064],"type":"Point"}
}