{
  "type": "Feature",
  "properties": {
    "iso:country":"IN",
    "ks:ks_name":"Ravkantoli",
    "ks:ks_pop":141,
    "ks:ks_type":"HABITATION",
    "name:eng_x_preferred":[
        "Ravkantoli"
    ],
    "wof:name":"Ravkantoli",
    "wof:placetype":"locality",
    "wof:population":141
},
  "geometry": {"coordinates":[84.55594000000001,22.556022],"type":"Point"}
}