{
  "type": "Feature",
  "properties": {
    "gn:admin1_code":"12.0",
    "gn:admin2_code":"002",
    "gn:asciiname":"Sonapah",
    "gn:country_code":"IN",
    "gn:dem":1783,
    "gn:feature_class":"P",
    "gn:feature_code":"PPL",
    "gn:name":"Sonap\u0101h",
    "gn:population":0,
    "gn:timezone":"Asia/Kolkata",
    "iso:country":"IN",
    "wof:name":"Sonapah",
    "wof:placetype":"locality"
},
  "geometry": {"coordinates":[74.60485,34.01008],"type":"Point"}
}