{
  "type": "Feature",
  "properties": {
    "iso:country":"IN",
    "ks:ks_name":"Deoli",
    "ks:ks_pop":3,
    "ks:ks_type":"HABITATION",
    "name:eng_x_preferred":[
        "Deoli"
    ],
    "wof:name":"Deoli",
    "wof:placetype":"locality",
    "wof:population":3
},
  "geometry": {"coordinates":[78.167956,21.704509],"type":"Point"}
}