{
  "type": "Feature",
  "properties": {
    "iso:country":"IN",
    "ks:ks_name":"Zola",
    "ks:ks_pop":46,
    "ks:ks_type":"VILLAGE",
    "name:eng_x_preferred":[
        "Zola"
    ],
    "wof:name":"Zola",
    "wof:placetype":"locality",
    "wof:population":46
},
  "geometry": {"coordinates":[78.166838,20.465043],"type":"Point"}
}