{
  "type": "Feature",
  "properties": {
    "gn:admin1_code":"37",
    "gn:admin2_code":"409.0",
    "gn:asciiname":"Deori",
    "gn:country_code":"IN",
    "gn:dem":299,
    "gn:feature_class":"P",
    "gn:feature_code":"PPL",
    "gn:name":"Deori",
    "gn:population":0,
    "gn:timezone":"Asia/Kolkata",
    "iso:country":"IN",
    "name:cat_x_preferred":[
        "Deori"
    ],
    "name:ceb_x_preferred":[
        "Deori"
    ],
    "name:por_x_preferred":[
        "Deori"
    ],
    "name:swe_x_preferred":[
        "Deori"
    ],
    "wof:name":"Deori",
    "wof:placetype":"neighbourhood"
},
  "geometry": {"coordinates":[81.15007,21.06066],"type":"Point"}
}