{
  "type": "Feature",
  "properties": {
    "gn:admin1_code":"35",
    "gn:admin2_code":"457.0",
    "gn:asciiname":"Ranwahi",
    "gn:country_code":"IN",
    "gn:dem":782,
    "gn:feature_class":"P",
    "gn:feature_code":"PPL",
    "gn:name":"Ranw\u0101hi",
    "gn:population":0,
    "gn:timezone":"Asia/Kolkata",
    "iso:country":"IN",
    "ks:ks_alt_nam":"Ranw\u0101hi",
    "ks:ks_name":"Ranwahi",
    "ks:ks_pop":333,
    "ks:ks_type":"VILLAGE",
    "name:eng_x_preferred":[
        "Ranwahi"
    ],
    "name:eng_x_variant":[
        "Ranw\u0101hi"
    ],
    "wof:name":"Ranwahi",
    "wof:placetype":"locality",
    "wof:population":333
},
  "geometry": {"coordinates":[81.006968,22.135944],"type":"Point"}
}