{
  "type": "Feature",
  "properties": {
    "gn:admin1_code":"35",
    "gn:admin2_code":"457.0",
    "gn:asciiname":"Ranwahi",
    "gn:country_code":"IN",
    "gn:dem":782,
    "gn:feature_class":"P",
    "gn:feature_code":"PPL",
    "gn:name":"Ranw\u0101hi",
    "gn:population":0,
    "gn:timezone":"Asia/Kolkata",
    "iso:country":"IN",
    "wof:name":"Ranwahi",
    "wof:placetype":"locality"
},
  "geometry": {"coordinates":[81.00823000000003,22.1337],"type":"Point"}
}