{
  "type": "Feature",
  "properties": {
    "gn:admin1_code":"25.0",
    "gn:admin2_code":"602.0",
    "gn:asciiname":"Kavanur",
    "gn:country_code":"IN",
    "gn:dem":39,
    "gn:feature_class":"P",
    "gn:feature_code":"PPL",
    "gn:name":"K\u0101van\u016br",
    "gn:population":0,
    "gn:timezone":"Asia/Kolkata",
    "iso:country":"IN",
    "name:ara_x_preferred":[
        "\u0643\u0627\u0641\u0646\u0648\u0631"
    ],
    "name:ben_bn_x_preferred":[
        "\u0995\u09be\u09ad\u09be\u09a8\u09c1\u09b0"
    ],
    "name:ben_in_x_preferred":[
        "\u0995\u09be\u09ad\u09be\u09a8\u09c1\u09b0"
    ],
    "name:ceb_x_preferred":[
        "Kavanur"
    ],
    "name:guj_x_preferred":[
        "\u0a95\u0ab5\u0aa8\u0ac1\u0ab0"
    ],
    "name:hin_x_preferred":[
        "\u0915\u0935\u0928\u0942\u0930"
    ],
    "name:kan_x_preferred":[
        "\u0c95\u0cb5\u0ca8\u0cc2\u0cb0\u0ccd"
    ],
    "name:mal_x_preferred":[
        "\u0d15\u0d3e\u0d35\u0d28\u0d42\u0d7c"
    ],
    "name:mar_x_preferred":[
        "\u0915\u0935\u0928\u0942\u0930"
    ],
    "name:pan_x_preferred":[
        "\u0a15\u0a3e\u0a35\u0a3e\u0a28\u0a42\u0a30"
    ],
    "name:swe_x_preferred":[
        "Kavanur"
    ],
    "name:tam_x_preferred":[
        "\u0b95\u0bbe\u0bb5\u0ba9\u0bc2\u0bb0\u0bcd"
    ],
    "name:tel_x_preferred":[
        "\u0c15\u0c35\u0c28\u0c42\u0c30\u0c4d"
    ],
    "name:urd_x_preferred":[
        "\u06a9\u0648\u0627\u0646\u0648\u0631"
    ],
    "wof:name":"Kavanur",
    "wof:placetype":"neighbourhood"
},
  "geometry": {"coordinates":[79.96474000000001,13.29158],"type":"Point"}
}