{
  "type": "Feature",
  "properties": {
    "iso:country":"IN",
    "ks:ks_alt_nam":"jamunia Tola",
    "ks:ks_name":"Jamunia Tola",
    "ks:ks_pop":757,
    "ks:ks_type":"HABITATION",
    "name:eng_x_preferred":[
        "Jamunia Tola"
    ],
    "wof:name":"Jamunia Tola",
    "wof:placetype":"locality",
    "wof:population":757
},
  "geometry": {"coordinates":[85.56559,23.73888],"type":"Point"}
}