{
  "type": "Feature",
  "properties": {
    "iso:country":"IN",
    "ks:ks_name":"Ratnapara",
    "ks:ks_pop":92,
    "ks:ks_type":"HABITATION",
    "name:eng_x_preferred":[
        "Ratnapara"
    ],
    "wof:name":"Ratnapara",
    "wof:placetype":"locality",
    "wof:population":92
},
  "geometry": {"coordinates":[87.42437,24.689201],"type":"Point"}
}