{
  "type": "Feature",
  "properties": {
    "gn:admin1_code":"37.0",
    "gn:admin2_code":"407.0",
    "gn:asciiname":"Khariya",
    "gn:country_code":"IN",
    "gn:dem":407,
    "gn:feature_class":"P",
    "gn:feature_code":"PPL",
    "gn:name":"Khariya",
    "gn:population":0,
    "gn:timezone":"Asia/Kolkata",
    "iso:country":"IN",
    "wof:name":"Khariya",
    "wof:placetype":"locality"
},
  "geometry": {"coordinates":[81.25601,22.21606],"type":"Point"}
}