{
  "type": "Feature",
  "properties": {
    "iso:country":"IN",
    "ks:ks_name":"Sambayyanagadde",
    "ks:ks_pop":16,
    "ks:ks_type":"HABITATION",
    "name:eng_x_preferred":[
        "Sambayyanagadde"
    ],
    "wof:name":"Sambayyanagadde",
    "wof:placetype":"locality",
    "wof:population":16
},
  "geometry": {"coordinates":[74.701477,14.653889],"type":"Point"}
}