{
  "type": "Feature",
  "properties": {
    "iso:country":"IN",
    "ks:ks_alt_nam":"Kadamguri supa",
    "ks:ks_name":"Kadamguri Supa",
    "ks:ks_pop":539,
    "ks:ks_type":"HABITATION",
    "name:eng_x_preferred":[
        "Kadamguri Supa"
    ],
    "wof:name":"Kadamguri Supa",
    "wof:placetype":"locality",
    "wof:population":539
},
  "geometry": {"coordinates":[91.439475,26.741909],"type":"Point"}
}