{
  "type": "Feature",
  "properties": {
    "iso:country":"IN",
    "ks:ks_alt_nam":"KAMBLE VASTI",
    "ks:ks_name":"Kamble Vasti",
    "ks:ks_pop":106,
    "ks:ks_type":"HABITATION",
    "name:eng_x_preferred":[
        "Kamble Vasti"
    ],
    "wof:name":"Kamble Vasti",
    "wof:placetype":"locality",
    "wof:population":106
},
  "geometry": {"coordinates":[74.709098,16.840272],"type":"Point"}
}