{
  "type": "Feature",
  "properties": {
    "gn:admin1_code":"34.0",
    "gn:admin2_code":"214.0",
    "gn:asciiname":"Hatta",
    "gn:country_code":"IN",
    "gn:dem":47,
    "gn:feature_class":"P",
    "gn:feature_code":"PPL",
    "gn:name":"Hatta",
    "gn:population":0,
    "gn:timezone":"Asia/Kolkata",
    "iso:country":"IN",
    "name:cat_x_preferred":[
        "Hatta"
    ],
    "name:ceb_x_preferred":[
        "Hatta"
    ],
    "name:deu_x_preferred":[
        "Hatta"
    ],
    "name:fra_x_preferred":[
        "Hatta"
    ],
    "name:ind_x_preferred":[
        "Hatta"
    ],
    "name:ita_x_preferred":[
        "Hatta"
    ],
    "name:nld_x_preferred":[
        "Hatta"
    ],
    "name:rus_x_preferred":[
        "\u0425\u0430\u0442\u0442\u0430"
    ],
    "name:spa_x_preferred":[
        "Hatta"
    ],
    "name:swe_x_preferred":[
        "Hatta"
    ],
    "name:ukr_x_preferred":[
        "\u0425\u0430\u0442\u0442\u0430"
    ],
    "wof:name":"Hatta",
    "wof:placetype":"neighbourhood"
},
  "geometry": {"coordinates":[86.84701,25.83517],"type":"Point"}
}