{
  "type": "Feature",
  "properties": {
    "iso:country":"IN",
    "ks:ks_alt_nam":"Sarnam ka pura",
    "ks:ks_name":"Sarnam Ka Pura",
    "ks:ks_pop":200,
    "ks:ks_type":"HABITATION",
    "ks:ks_uagg_main":0,
    "name:eng_x_preferred":[
        "Sarnam Ka Pura"
    ],
    "wof:name":"Sarnam Ka Pura",
    "wof:placetype":"neighbourhood",
    "wof:population":200
},
  "geometry": {"coordinates":[81.81530600000001,25.73517],"type":"Point"}
}