{
  "type": "Feature",
  "properties": {
    "iso:country":"IN",
    "ks:ks_name":"Pipri",
    "ks:ks_type":"VILLAGE",
    "ks:ks_uagg_main":0,
    "name:eng_x_preferred":[
        "Pipri"
    ],
    "wof:name":"Pipri",
    "wof:placetype":"neighbourhood"
},
  "geometry": {"coordinates":[82.747438,26.818524],"type":"Point"}
}