{
  "type": "Feature",
  "properties": {
    "gn:admin1_code":"39.0",
    "gn:admin2_code":"64.0",
    "gn:asciiname":"Singara",
    "gn:country_code":"IN",
    "gn:dem":1697,
    "gn:feature_class":"P",
    "gn:feature_code":"PPL",
    "gn:name":"Singara",
    "gn:population":0,
    "gn:timezone":"Asia/Kolkata",
    "iso:country":"IN",
    "name:deu_x_preferred":[
        "Singara"
    ],
    "name:ell_x_preferred":[
        "\u03a3\u03af\u03bd\u03b3\u03ba\u03b1\u03c1\u03b1"
    ],
    "name:fra_x_preferred":[
        "Singara"
    ],
    "name:ita_x_preferred":[
        "Singara"
    ],
    "name:nld_x_preferred":[
        "Singara"
    ],
    "name:nor_x_preferred":[
        "Singara"
    ],
    "name:por_x_preferred":[
        "Singara"
    ],
    "name:rus_x_preferred":[
        "\u0421\u0438\u043d\u0433\u0430\u0440\u0430"
    ],
    "name:spa_x_preferred":[
        "Singara"
    ],
    "name:ukr_x_preferred":[
        "\u0421\u0438\u043d\u0433\u0430\u0440\u0430"
    ],
    "wof:name":"Singara",
    "wof:placetype":"locality"
},
  "geometry": {"coordinates":[79.56416,29.71736],"type":"Point"}
}