{
  "type": "Feature",
  "properties": {
    "gn:admin1_code":"36.0",
    "gn:admin2_code":"192.0",
    "gn:asciiname":"Bherkur Sultanpur",
    "gn:country_code":"IN",
    "gn:dem":71,
    "gn:feature_class":"P",
    "gn:feature_code":"PPL",
    "gn:name":"Bherkur Sult\u0101npur",
    "gn:population":0,
    "gn:timezone":"Asia/Kolkata",
    "iso:country":"IN",
    "ks:ks_alt_nam":"Bherkur Sult\u0101npur",
    "ks:ks_name":"Bherkur Sultanpur",
    "ks:ks_type":"VILLAGE",
    "ks:ks_uagg_main":0,
    "name:eng_x_preferred":[
        "Bherkur Sultanpur"
    ],
    "name:eng_x_variant":[
        "Bherkur Sult\u0101npur"
    ],
    "wof:name":"Bherkur Sultanpur",
    "wof:placetype":"neighbourhood"
},
  "geometry": {"coordinates":[83.77510700000001,26.187025],"type":"Point"}
}