{
  "type": "Feature",
  "properties": {
    "gn:admin1_code":"9.0",
    "gn:admin2_code":"484.0",
    "gn:asciiname":"Moyalajina Muwara",
    "gn:country_code":"IN",
    "gn:dem":150,
    "gn:feature_class":"P",
    "gn:feature_code":"PPL",
    "gn:name":"Moyal\u0101jina Muw\u0101ra",
    "gn:population":0,
    "gn:timezone":"Asia/Kolkata",
    "iso:country":"IN",
    "wof:name":"Moyalajina Muwara",
    "wof:placetype":"locality"
},
  "geometry": {"coordinates":[73.78493,23.15017000000001],"type":"Point"}
}