{
  "type": "Feature",
  "properties": {
    "iso:country":"IN",
    "ks:ks_name":"Banheti",
    "ks:ks_pop":461,
    "ks:ks_type":"VILLAGE",
    "ks:ks_uagg_main":0,
    "name:eng_x_preferred":[
        "Banheti"
    ],
    "wof:name":"Banheti",
    "wof:placetype":"neighbourhood",
    "wof:population":461
},
  "geometry": {"coordinates":[86.636371,24.937588],"type":"Point"}
}