{
  "type": "Feature",
  "properties": {
    "iso:country":"IN",
    "ks:ks_name":"Tarobara",
    "ks:ks_pop":225,
    "ks:ks_type":"VILLAGE",
    "name:eng_x_preferred":[
        "Tarobara"
    ],
    "wof:name":"Tarobara",
    "wof:placetype":"locality",
    "wof:population":225
},
  "geometry": {"coordinates":[85.447767,22.814646],"type":"Point"}
}