{
  "type": "Feature",
  "properties": {
    "iso:country":"IN",
    "ks:ks_name":"Durgamvaripalle",
    "ks:ks_pop":38,
    "ks:ks_type":"HABITATION",
    "name:eng_x_preferred":[
        "Durgamvaripalle"
    ],
    "wof:name":"Durgamvaripalle",
    "wof:placetype":"locality",
    "wof:population":38
},
  "geometry": {"coordinates":[78.880836,13.709623],"type":"Point"}
}