{
  "type": "Feature",
  "properties": {
    "iso:country":"IN",
    "ks:ks_name":"Pungampadi",
    "ks:ks_pop":503,
    "ks:ks_type":"HABITATION",
    "name:eng_x_preferred":[
        "Pungampadi"
    ],
    "wof:name":"Pungampadi",
    "wof:placetype":"locality",
    "wof:population":503
},
  "geometry": {"coordinates":[78.34193399999999,10.594698],"type":"Point"}
}