{
  "type": "Feature",
  "properties": {
    "iso:country":"IN",
    "ks:ks_name":"Nand Ram Purwa",
    "ks:ks_pop":115,
    "ks:ks_type":"HABITATION",
    "name:eng_x_preferred":[
        "Nand Ram Purwa"
    ],
    "wof:name":"Nand Ram Purwa",
    "wof:placetype":"locality",
    "wof:population":115
},
  "geometry": {"coordinates":[81.82470600000001,27.237047],"type":"Point"}
}