{
  "type": "Feature",
  "properties": {
    "gn:admin1_code":"39.0",
    "gn:admin2_code":"60.0",
    "gn:asciiname":"Dhobighat",
    "gn:country_code":"IN",
    "gn:dem":1650,
    "gn:feature_class":"P",
    "gn:feature_code":"PPL",
    "gn:name":"Dhob\u012bgh\u0101t",
    "gn:population":0,
    "gn:timezone":"Asia/Kolkata",
    "iso:country":"IN",
    "wof:name":"Dhobighat",
    "wof:placetype":"locality"
},
  "geometry": {"coordinates":[78.03497,30.46887000000001],"type":"Point"}
}