{
  "type": "Feature",
  "properties": {
    "iso:country":"IN",
    "ks:ks_name":"Chakundajhola",
    "ks:ks_pop":157,
    "ks:ks_type":"VILLAGE",
    "name:eng_x_preferred":[
        "Chakundajhola"
    ],
    "wof:name":"Chakundajhola",
    "wof:placetype":"locality",
    "wof:population":157
},
  "geometry": {"coordinates":[84.88153800000001,19.645506],"type":"Point"}
}