{
  "type": "Feature",
  "properties": {
    "iso:country":"IN",
    "ks:ks_name":"Chandarpara",
    "ks:ks_pop":81,
    "ks:ks_type":"HABITATION",
    "name:eng_x_preferred":[
        "Chandarpara"
    ],
    "wof:name":"Chandarpara",
    "wof:placetype":"locality",
    "wof:population":81
},
  "geometry": {"coordinates":[81.392115,19.093628],"type":"Point"}
}