{
  "type": "Feature",
  "properties": {
    "iso:country":"IN",
    "ks:ks_name":"Andaballi",
    "ks:ks_pop":197,
    "ks:ks_type":"HABITATION",
    "name:eng_x_preferred":[
        "Andaballi"
    ],
    "wof:name":"Andaballi",
    "wof:placetype":"locality",
    "wof:population":197
},
  "geometry": {"coordinates":[74.621095,14.354642],"type":"Point"}
}