{
  "type": "Feature",
  "properties": {
    "gn:admin1_code":"36",
    "gn:admin2_code":"196.0",
    "gn:asciiname":"Sonia",
    "gn:country_code":"IN",
    "gn:dem":316,
    "gn:feature_class":"P",
    "gn:feature_code":"PPL",
    "gn:name":"Sonia",
    "gn:population":0,
    "gn:timezone":"Asia/Kolkata",
    "iso:country":"IN",
    "name:ceb_x_preferred":[
        "Sonia"
    ],
    "name:fra_x_preferred":[
        "Sonia"
    ],
    "name:ind_x_preferred":[
        "Sonia"
    ],
    "name:ita_x_preferred":[
        "Sonia"
    ],
    "name:jpn_x_preferred":[
        "\u30bd\u30cb\u30a2"
    ],
    "name:spa_x_preferred":[
        "Sonia"
    ],
    "name:swe_x_preferred":[
        "Sonia"
    ],
    "wof:name":"Sonia",
    "wof:placetype":"locality"
},
  "geometry": {"coordinates":[83.18015,24.72052],"type":"Point"}
}