{
  "type": "Feature",
  "properties": {
    "iso:country":"IN",
    "ks:ks_name":"Nikoli",
    "ks:ks_pop":131,
    "ks:ks_type":"HABITATION",
    "name:eng_x_preferred":[
        "Nikoli"
    ],
    "wof:name":"Nikoli",
    "wof:placetype":"locality",
    "wof:population":131
},
  "geometry": {"coordinates":[73.150694,21.666889],"type":"Point"}
}