{
  "type": "Feature",
  "properties": {
    "iso:country":"IN",
    "ks:ks_name":"Simiriya",
    "ks:ks_pop":198,
    "ks:ks_type":"HABITATION",
    "name:eng_x_preferred":[
        "Simiriya"
    ],
    "wof:name":"Simiriya",
    "wof:placetype":"locality",
    "wof:population":198
},
  "geometry": {"coordinates":[77.812168,24.543814],"type":"Point"}
}