{
  "type": "Feature",
  "properties": {
    "gn:admin1_code":"10.0",
    "gn:admin2_code":"71.0",
    "gn:asciiname":"Majri",
    "gn:country_code":"IN",
    "gn:dem":301,
    "gn:feature_class":"P",
    "gn:feature_code":"PPL",
    "gn:name":"M\u0101jri",
    "gn:population":0,
    "gn:timezone":"Asia/Kolkata",
    "iso:country":"IN",
    "wof:name":"Majri",
    "wof:placetype":"locality"
},
  "geometry": {"coordinates":[77.1896,30.37383],"type":"Point"}
}