{
  "type": "Feature",
  "properties": {
    "gn:admin1_code":"39.0",
    "gn:admin2_code":"62.0",
    "gn:asciiname":"Godigad",
    "gn:country_code":"IN",
    "gn:dem":977,
    "gn:feature_class":"P",
    "gn:feature_code":"PPL",
    "gn:name":"Godig\u0101d",
    "gn:population":0,
    "gn:timezone":"Asia/Kolkata",
    "iso:country":"IN",
    "ks:ks_alt_nam":"Godig\u0101d",
    "ks:ks_name":"Godigad",
    "ks:ks_type":"VILLAGE",
    "name:eng_x_preferred":[
        "Godigad"
    ],
    "name:eng_x_variant":[
        "Godig\u0101d"
    ],
    "wof:name":"Godigad",
    "wof:placetype":"locality"
},
  "geometry": {"coordinates":[79.958394,29.717728],"type":"Point"}
}