{
  "type": "Feature",
  "properties": {
    "gn:admin1_code":"39.0",
    "gn:admin2_code":"62.0",
    "gn:asciiname":"Godigad",
    "gn:country_code":"IN",
    "gn:dem":977,
    "gn:feature_class":"P",
    "gn:feature_code":"PPL",
    "gn:name":"Godig\u0101d",
    "gn:population":0,
    "gn:timezone":"Asia/Kolkata",
    "iso:country":"IN",
    "wof:name":"Godigad",
    "wof:placetype":"locality"
},
  "geometry": {"coordinates":[79.95839000000002,29.71773],"type":"Point"}
}