{
  "type": "Feature",
  "properties": {
    "gn:admin1_code":"36",
    "gn:admin2_code":"157.0",
    "gn:asciiname":"Rahimabad",
    "gn:country_code":"IN",
    "gn:dem":127,
    "gn:feature_class":"P",
    "gn:feature_code":"PPL",
    "gn:name":"Rahim\u0101b\u0101d",
    "gn:population":0,
    "gn:timezone":"Asia/Kolkata",
    "iso:country":"IN",
    "name:aze_x_preferred":[
        "R\u0259himabad"
    ],
    "name:fas_x_preferred":[
        "\u0631\u062d\u06cc\u0645\u200c\u0622\u0628\u0627\u062f"
    ],
    "wof:name":"Rahimabad",
    "wof:placetype":"neighbourhood"
},
  "geometry": {"coordinates":[80.88453,26.74923],"type":"Point"}
}