{
  "type": "Feature",
  "properties": {
    "gn:admin1_code":"34",
    "gn:admin2_code":"208.0",
    "gn:asciiname":"Tharbitia",
    "gn:country_code":"IN",
    "gn:dem":59,
    "gn:feature_class":"P",
    "gn:feature_code":"PPL",
    "gn:name":"Tharbitia",
    "gn:population":0,
    "gn:timezone":"Asia/Kolkata",
    "iso:country":"IN",
    "wof:name":"Tharbitia",
    "wof:placetype":"locality"
},
  "geometry": {"coordinates":[86.65645000000001,26.21937],"type":"Point"}
}