{
  "type": "Feature",
  "properties": {
    "iso:country":"IN",
    "ks:ks_alt_nam":"LAXMIPUR",
    "ks:ks_name":"Laxmipur",
    "ks:ks_pop":289,
    "ks:ks_type":"HABITATION",
    "name:eng_x_preferred":[
        "Laxmipur"
    ],
    "wof:name":"Laxmipur",
    "wof:placetype":"locality",
    "wof:population":289
},
  "geometry": {"coordinates":[85.467164,24.915267],"type":"Point"}
}