{
  "type": "Feature",
  "properties": {
    "iso:country":"IN",
    "ks:ks_name":"Sargibai",
    "ks:ks_pop":36,
    "ks:ks_type":"HABITATION",
    "name:eng_x_preferred":[
        "Sargibai"
    ],
    "wof:name":"Sargibai",
    "wof:placetype":"locality",
    "wof:population":36
},
  "geometry": {"coordinates":[83.597781,19.284478],"type":"Point"}
}