{
  "type": "Feature",
  "properties": {
    "iso:country":"IN",
    "ks:ks_name":"Arbetai",
    "ks:ks_pop":4388,
    "ks:ks_type":"VILLAGE",
    "ks:ks_uagg_main":0,
    "name:eng_x_preferred":[
        "Arbetai"
    ],
    "wof:name":"Arbetai",
    "wof:placetype":"neighbourhood",
    "wof:population":4388
},
  "geometry": {"coordinates":[88.405187,23.712159],"type":"Point"}
}