{
  "type": "Feature",
  "properties": {
    "iso:country":"IN",
    "ks:ks_name":"Jatamari",
    "ks:ks_pop":2314,
    "ks:ks_type":"VILLAGE",
    "name:eng_x_preferred":[
        "Jatamari"
    ],
    "wof:name":"Jatamari",
    "wof:placetype":"locality",
    "wof:population":2314
},
  "geometry": {"coordinates":[89.18802700000001,26.276032],"type":"Point"}
}