{
  "type": "Feature",
  "properties": {
    "iso:country":"IN",
    "ks:ks_name":"Ramnagar",
    "ks:ks_pop":217,
    "ks:ks_type":"HABITATION",
    "ks:ks_uagg_main":0,
    "name:eng_x_preferred":[
        "Ramnagar"
    ],
    "wof:name":"Ramnagar",
    "wof:placetype":"neighbourhood",
    "wof:population":217
},
  "geometry": {"coordinates":[73.572823,16.380083],"type":"Point"}
}