{
  "type": "Feature",
  "properties": {
    "iso:country":"IN",
    "ks:ks_name":"E Mettupatti",
    "ks:ks_pop":190,
    "ks:ks_type":"HABITATION",
    "name:eng_x_preferred":[
        "E Mettupatti"
    ],
    "wof:name":"E Mettupatti",
    "wof:placetype":"locality",
    "wof:population":190
},
  "geometry": {"coordinates":[78.59159699999999,10.642652],"type":"Point"}
}