{
  "type": "Feature",
  "properties": {
    "gn:admin1_code":"37",
    "gn:admin2_code":"404.0",
    "gn:asciiname":"Biadand",
    "gn:country_code":"IN",
    "gn:dem":517,
    "gn:feature_class":"P",
    "gn:feature_code":"PPL",
    "gn:name":"B\u012bad\u0101nd",
    "gn:population":0,
    "gn:timezone":"Asia/Kolkata",
    "iso:country":"IN",
    "ks:ks_name":"Bijadand",
    "ks:ks_pop":394,
    "ks:ks_type":"VILLAGE",
    "name:eng_x_preferred":[
        "Bijadand"
    ],
    "name:eng_x_variant":[
        "Biadand"
    ],
    "wof:name":"Bijadand",
    "wof:placetype":"locality",
    "wof:population":394
},
  "geometry": {"coordinates":[82.336173,22.850688],"type":"Point"}
}