{
  "type": "Feature",
  "properties": {
    "iso:country":"IN",
    "ks:ks_name":"Thamaraikulam",
    "ks:ks_pop":632,
    "ks:ks_type":"HABITATION",
    "name:eng_x_preferred":[
        "Thamaraikulam"
    ],
    "wof:name":"Thamaraikulam",
    "wof:placetype":"locality",
    "wof:population":632
},
  "geometry": {"coordinates":[79.108932,11.168788],"type":"Point"}
}