{
  "type": "Feature",
  "properties": {
    "iso:country":"IN",
    "name:ben_x_preferred":[
        "\u09ae\u09be\u09b9\u09bf\u09ae"
    ],
    "name:cat_x_preferred":[
        "Mahim"
    ],
    "name:eng_x_preferred":[
        "Mahim"
    ],
    "name:eng_x_variant":[
        "Bombay Mahim",
        "Mahikavati"
    ],
    "name:hin_x_preferred":[
        "\u092e\u093e\u0939\u0940\u092e"
    ],
    "name:mar_x_preferred":[
        "\u092e\u093e\u0939\u0940\u092e"
    ],
    "name:por_x_preferred":[
        "Maim"
    ],
    "name:und_x_preferred":[
        "M\u0101h\u012bm"
    ],
    "name:unk_x_variant":[
        "Bombay Mahim",
        "Mahim"
    ],
    "qs:gn_adm0_cc":"IN",
    "qs:gn_fcode":"PPLX",
    "qs:gn_local":1275339,
    "qs:gn_namadm1":"16",
    "qs:gn_name":"M\u0101h\u012bm",
    "qs:local_max":3819,
    "qs:local_sum":50908,
    "qs:localhoods":70,
    "qs:name":"Mahim",
    "qs:name_adm0":"India",
    "qs:name_adm1":"Maharashtra",
    "qs:name_adm2":"Mumbai",
    "qs:name_local":"Mumbai",
    "qs:photo_max":169,
    "qs:photo_sum":666,
    "qs:placetype":"Suburb",
    "qs:quad_count":21,
    "qs:woe_adm0":23424848,
    "qs:woe_adm1":2345750,
    "qs:woe_adm2":12586539,
    "qs:woe_lau":0,
    "qs:woe_local":2295411,
    "qs:woe_ver":"7.10.0",
    "wd:wordcount":1249,
    "wof:lang":[
        "eng"
    ],
    "wof:name":"Mahim",
    "wof:placetype":"neighbourhood"
},
  "geometry": {"coordinates":[72.844213,19.04201],"type":"Point"}
}