{
  "type": "Feature",
  "properties": {
    "gn:admin1_code":"36.0",
    "gn:admin2_code":"149.0",
    "gn:asciiname":"Mirzapur Bela",
    "gn:country_code":"IN",
    "gn:dem":169,
    "gn:feature_class":"P",
    "gn:feature_code":"PPL",
    "gn:name":"Mirz\u0101pur Bela",
    "gn:population":0,
    "gn:timezone":"Asia/Kolkata",
    "iso:country":"IN",
    "wof:name":"Mirzapur Bela",
    "wof:placetype":"locality"
},
  "geometry": {"coordinates":[78.75459000000002,28.0079],"type":"Point"}
}