{
  "type": "Feature",
  "properties": {
    "iso:country":"IN",
    "ks:ks_name":"Patharchapti",
    "ks:ks_pop":436,
    "ks:ks_type":"VILLAGE",
    "ks:ks_uagg_main":0,
    "name:eng_x_preferred":[
        "Patharchapti"
    ],
    "wof:name":"Patharchapti",
    "wof:placetype":"locality",
    "wof:population":436
},
  "geometry": {"coordinates":[86.74396400000001,24.496463],"type":"Point"}
}