{
  "type": "Feature",
  "properties": {
    "iso:country":"IN",
    "ks:ks_name":"Kamalapuram",
    "ks:ks_pop":57,
    "ks:ks_type":"HABITATION",
    "name:eng_x_preferred":[
        "Kamalapuram"
    ],
    "wof:name":"Kamalapuram",
    "wof:placetype":"locality",
    "wof:population":57
},
  "geometry": {"coordinates":[78.711546,13.18862],"type":"Point"}
}