{
  "type": "Feature",
  "properties": {
    "iso:country":"IN",
    "ks:ks_alt_nam":"nhekil",
    "ks:ks_name":"Nhekil",
    "ks:ks_pop":1728,
    "ks:ks_type":"HABITATION",
    "name:eng_x_preferred":[
        "Nhekil"
    ],
    "wof:name":"Nhekil",
    "wof:placetype":"locality",
    "wof:population":1728
},
  "geometry": {"coordinates":[75.329981,12.243531],"type":"Point"}
}