{
  "type": "Feature",
  "properties": {
    "iso:country":"IN",
    "qs:name":"A C Guards",
    "qs:name_adm0":"India",
    "qs:name_adm1":"Andhra Pradesh",
    "qs:photos":11,
    "qs:photos_1k":2,
    "qs:photos_9k":1,
    "qs:photos_9r":1,
    "qs:photos_all":11,
    "qs:photos_sr":1,
    "qs:placetype":"Suburb",
    "qs:pop_sr":"0",
    "wd:wordcount":518,
    "wof:name":"A C Guards",
    "wof:placetype":"neighbourhood"
},
  "geometry": {"coordinates":[78.459087,17.401568],"type":"Point"}
}