{
  "type": "Feature",
  "properties": {
    "gn:admin1_code":"36.0",
    "gn:admin2_code":"177.0",
    "gn:asciiname":"Pura Lodh",
    "gn:country_code":"IN",
    "gn:dem":115,
    "gn:feature_class":"P",
    "gn:feature_code":"PPL",
    "gn:name":"Pura Lodh",
    "gn:population":0,
    "gn:timezone":"Asia/Kolkata",
    "iso:country":"IN",
    "ks:ks_name":"Pure Lodh",
    "ks:ks_pop":308,
    "ks:ks_type":"HABITATION",
    "name:eng_x_preferred":[
        "Pure Lodh"
    ],
    "name:eng_x_variant":[
        "Pura Lodh"
    ],
    "wof:name":"Pure Lodh",
    "wof:placetype":"locality",
    "wof:population":308
},
  "geometry": {"coordinates":[81.65689,26.680997],"type":"Point"}
}