{
  "type": "Feature",
  "properties": {
    "gn:admin1_code":"10.0",
    "gn:admin2_code":"83.0",
    "gn:asciiname":"Kaliawas",
    "gn:country_code":"IN",
    "gn:dem":217,
    "gn:feature_class":"P",
    "gn:feature_code":"PPL",
    "gn:name":"K\u0101li\u0101w\u0101s",
    "gn:population":0,
    "gn:timezone":"Asia/Kolkata",
    "iso:country":"IN",
    "name:ara_x_preferred":[
        "\u0643\u0627\u0644\u064a\u0627\u0648\u0633"
    ],
    "name:ben_bn_x_preferred":[
        "\u0995\u09be\u09b2\u09bf\u09df\u09be\u0993\u09df\u09be\u09b8"
    ],
    "name:ben_in_x_preferred":[
        "\u0995\u09be\u09b2\u09bf\u09df\u09be\u0993\u09df\u09be\u09b8"
    ],
    "name:guj_x_preferred":[
        "\u0a95\u0abe\u0ab2\u0abf\u0aaf\u0abe\u0ab5\u0abe\u0ab8"
    ],
    "name:hin_x_preferred":[
        "\u0915\u0948\u0932\u093e\u0935\u093e\u0938"
    ],
    "name:kan_x_preferred":[
        "\u0c95\u0cbe\u0cb2\u0cbf\u0caf\u0cbe\u0cb5\u0cb8\u0ccd"
    ],
    "name:mal_x_preferred":[
        "\u0d15\u0d32\u0d3f\u0d2f\u0d35\u0d3e\u0d38\u0d4d"
    ],
    "name:mar_x_preferred":[
        "\u0915\u093e\u0932\u093f\u092f\u093e\u0935\u093e\u0938"
    ],
    "name:pan_x_preferred":[
        "\u0a15\u0a3e\u0a32\u0a40\u0a06\u0a35\u0a3e\u0a38"
    ],
    "name:tam_x_preferred":[
        "\u0b95\u0bb2\u0bbf\u0baf\u0bbe\u0bb5\u0bb8\u0bcd"
    ],
    "name:tel_x_preferred":[
        "\u0c15\u0c32\u0c3f\u0c2f\u0c3e\u0c35\u0c3e\u0c38\u0c4d"
    ],
    "name:urd_x_preferred":[
        "\u06a9\u0627\u0644\u06cc\u0627\u0648\u0627\u0633"
    ],
    "wof:name":"Kaliawas",
    "wof:placetype":"locality"
},
  "geometry": {"coordinates":[76.35853,28.59856],"type":"Point"}
}