{
  "type": "Feature",
  "properties": {
    "iso:country":"IN",
    "ks:ks_name":"Kola",
    "ks:ks_pop":1164,
    "ks:ks_type":"VILLAGE",
    "name:eng_x_preferred":[
        "Kola"
    ],
    "wof:name":"Kola",
    "wof:placetype":"locality",
    "wof:population":1164
},
  "geometry": {"coordinates":[88.59137,22.764956],"type":"Point"}
}