{
  "type": "Feature",
  "properties": {
    "gn:admin1_code":"36.0",
    "gn:admin2_code":"183.0",
    "gn:asciiname":"Agaya",
    "gn:country_code":"IN",
    "gn:dem":100,
    "gn:feature_class":"P",
    "gn:feature_code":"PPL",
    "gn:name":"Agaya",
    "gn:population":0,
    "gn:timezone":"Asia/Kolkata",
    "iso:country":"IN",
    "name:ben_x_preferred":[
        "\u0985\u0997\u09af\u09bc\u09be"
    ],
    "wof:name":"Agaya",
    "wof:placetype":"locality"
},
  "geometry": {"coordinates":[82.53191,27.01082],"type":"Point"}
}