{
  "type": "Feature",
  "properties": {
    "gn:admin1_code":"2.0",
    "gn:admin2_code":"544.0",
    "gn:asciiname":"Pedda Garuvu",
    "gn:country_code":"IN",
    "gn:dem":974,
    "gn:feature_class":"P",
    "gn:feature_code":"PPL",
    "gn:name":"Pedda Garuvu",
    "gn:population":0,
    "gn:timezone":"Asia/Kolkata",
    "iso:country":"IN",
    "wof:name":"Pedda Garuvu",
    "wof:placetype":"locality"
},
  "geometry": {"coordinates":[82.47519,18.18887],"type":"Point"}
}