{
  "type": "Feature",
  "properties": {
    "iso:country":"IN",
    "ks:ks_alt_nam":"USARI NORTH",
    "ks:ks_name":"Usari North",
    "ks:ks_pop":323,
    "ks:ks_type":"HABITATION",
    "name:eng_x_preferred":[
        "Usari North"
    ],
    "wof:name":"Usari North",
    "wof:placetype":"locality",
    "wof:population":323
},
  "geometry": {"coordinates":[86.35451399999999,25.803546],"type":"Point"}
}