{
  "type": "Feature",
  "properties": {
    "iso:country":"IN",
    "ks:ks_alt_nam":"MUNDA BASTI",
    "ks:ks_name":"Munda Basti",
    "ks:ks_pop":200,
    "ks:ks_type":"HABITATION",
    "name:eng_x_preferred":[
        "Munda Basti"
    ],
    "wof:name":"Munda Basti",
    "wof:placetype":"locality",
    "wof:population":200
},
  "geometry": {"coordinates":[91.657562,24.088684],"type":"Point"}
}