{
  "type": "Feature",
  "properties": {
    "gn:country":"IN",
    "gn:fcode":"PPL",
    "gn:population":10764,
    "iso:country":"IN",
    "name:ben_x_preferred":[
        "\u09ac\u09be\u0997\u09cd\u09b2\u09c0"
    ],
    "name:cat_x_preferred":[
        "Bagli"
    ],
    "name:ceb_x_preferred":[
        "B\u0101gli"
    ],
    "name:deu_x_preferred":[
        "Bagli"
    ],
    "name:eng_x_preferred":[
        "Bagli"
    ],
    "name:fra_x_preferred":[
        "Bagli"
    ],
    "name:guj_x_preferred":[
        "\u0aac\u0abe\u0a97\u0ab2\u0ac0"
    ],
    "name:ita_x_preferred":[
        "Bagli"
    ],
    "name:jpn_x_preferred":[
        "\u30d0\u30b0\u30ea"
    ],
    "name:kan_x_preferred":[
        "\u0cac\u0c97\u0ccd\u0cb2\u0cbf"
    ],
    "name:kor_x_preferred":[
        "\ubc14\uae00\ub9ac"
    ],
    "name:msa_x_preferred":[
        "Bagli"
    ],
    "name:nan_x_preferred":[
        "Bagli"
    ],
    "name:new_x_preferred":[
        "\u092c\u093e\u0917\u0932\u0940"
    ],
    "name:nld_x_preferred":[
        "Bagli"
    ],
    "name:por_x_preferred":[
        "Bagli"
    ],
    "name:rus_x_preferred":[
        "\u0411\u0430\u0433\u043b\u0438"
    ],
    "name:spa_x_preferred":[
        "Bagli"
    ],
    "name:swe_x_preferred":[
        "B\u0101gli"
    ],
    "name:tam_x_preferred":[
        "\u0baa\u0b95\u0bcd\u0bb2\u0bbf"
    ],
    "name:tel_x_preferred":[
        "\u0c2c\u0c3e\u0c17\u0c4d\u0c32\u0c3f"
    ],
    "name:urd_x_preferred":[
        "\u0628\u0627\u062c\u0644\u06cc"
    ],
    "name:vie_x_preferred":[
        "Bagli"
    ],
    "name:zho_x_preferred":[
        "\u5df4\u683c\u5229"
    ],
    "qs:name":"Bagli",
    "qs:name_adm0":"India",
    "qs:name_adm1":"Madhya Pradesh",
    "qs:photos_9k":1,
    "qs:photos_9r":1,
    "qs:photos_all":4,
    "qs:photos_sr":0,
    "qs:placetype":"Town",
    "qs:pop_sr":"6",
    "wd:wordcount":24,
    "wof:name":"Bagli",
    "wof:placetype":"locality",
    "wof:population":10764
},
  "geometry": {"coordinates":[76.34778,22.64141],"type":"Point"}
}