{
  "type": "Feature",
  "properties": {
    "gn:admin1_code":"10",
    "gn:admin2_code":"89.0",
    "gn:asciiname":"Gugera",
    "gn:country_code":"IN",
    "gn:dem":195,
    "gn:feature_class":"P",
    "gn:feature_code":"PPL",
    "gn:name":"Gugera",
    "gn:population":0,
    "gn:timezone":"Asia/Kolkata",
    "iso:country":"IN",
    "wof:name":"Gugera",
    "wof:placetype":"locality"
},
  "geometry": {"coordinates":[77.28216,28.16472000000001],"type":"Point"}
}