{
  "type": "Feature",
  "properties": {
    "iso:country":"IN",
    "ks:ks_name":"Muriya Khera",
    "ks:ks_pop":1397,
    "ks:ks_type":"HABITATION",
    "name:eng_x_preferred":[
        "Muriya Khera"
    ],
    "wof:name":"Muriya Khera",
    "wof:placetype":"locality",
    "wof:population":1397
},
  "geometry": {"coordinates":[80.172498,27.062802],"type":"Point"}
}