{
  "type": "Feature",
  "properties": {
    "gn:admin1_code":"16",
    "gn:admin2_code":"503.0",
    "gn:asciiname":"Dhamangaon",
    "gn:country_code":"IN",
    "gn:dem":443,
    "gn:feature_class":"P",
    "gn:feature_code":"PPL",
    "gn:name":"Dh\u0101mangaon",
    "gn:population":0,
    "gn:timezone":"Asia/Kolkata",
    "iso:country":"IN",
    "wof:name":"Dhamangaon",
    "wof:placetype":"locality"
},
  "geometry": {"coordinates":[77.44202,21.3457],"type":"Point"}
}