{
  "type": "Feature",
  "properties": {
    "iso:country":"IN",
    "ks:ks_alt_nam":"TILAK SARDAR",
    "ks:ks_name":"Tilak Sardar",
    "ks:ks_pop":126,
    "ks:ks_type":"HABITATION",
    "name:eng_x_preferred":[
        "Tilak Sardar"
    ],
    "wof:name":"Tilak Sardar",
    "wof:placetype":"locality",
    "wof:population":126
},
  "geometry": {"coordinates":[91.39586300000001,23.858702],"type":"Point"}
}