{
  "type": "Feature",
  "properties": {
    "iso:country":"IN",
    "ks:ks_name":"Limdi Timba Gamtal",
    "ks:ks_pop":927,
    "ks:ks_type":"HABITATION",
    "name:eng_x_preferred":[
        "Limdi Timba Gamtal"
    ],
    "wof:name":"Limdi Timba Gamtal",
    "wof:placetype":"locality",
    "wof:population":927
},
  "geometry": {"coordinates":[73.65853799999999,23.415586],"type":"Point"}
}