{
  "type": "Feature",
  "properties": {
    "gn:admin1_code":"39.0",
    "gn:admin2_code":"60.0",
    "gn:asciiname":"Lakhsyari",
    "gn:country_code":"IN",
    "gn:dem":1257,
    "gn:feature_class":"P",
    "gn:feature_code":"PPL",
    "gn:name":"Lakhsy\u0101ri",
    "gn:population":0,
    "gn:timezone":"Asia/Kolkata",
    "iso:country":"IN",
    "wof:name":"Lakhsyari",
    "wof:placetype":"locality"
},
  "geometry": {"coordinates":[77.96736999999997,30.54749],"type":"Point"}
}