{
  "type": "Feature",
  "properties": {
    "gn:admin1_code":"36",
    "gn:admin2_code":"180.0",
    "gn:asciiname":"Mankapur",
    "gn:country_code":"IN",
    "gn:dem":119,
    "gn:feature_class":"P",
    "gn:feature_code":"PPL",
    "gn:name":"M\u0101nk\u0101pur",
    "gn:population":0,
    "gn:timezone":"Asia/Kolkata",
    "iso:country":"IN",
    "name:bpy_x_preferred":[
        "\u09ae\u09be\u09a8\u0995\u09be\u09aa\u09c1\u09b0"
    ],
    "name:cat_x_preferred":[
        "Mankapur"
    ],
    "name:ceb_x_preferred":[
        "Mank\u0101pur"
    ],
    "name:hin_x_preferred":[
        "\u092e\u0928\u0915\u093e\u092a\u0941\u0930"
    ],
    "name:ita_x_preferred":[
        "Mankapur"
    ],
    "name:mlg_x_preferred":[
        "Mankapur"
    ],
    "name:msa_x_preferred":[
        "Mankapur"
    ],
    "name:new_x_preferred":[
        "\u092e\u0902\u0915\u093e\u092a\u0941\u0930"
    ],
    "name:nld_x_preferred":[
        "Mankapur"
    ],
    "name:pol_x_preferred":[
        "Mankapur"
    ],
    "name:por_x_preferred":[
        "Mankapur"
    ],
    "name:swe_x_preferred":[
        "Mank\u0101pur"
    ],
    "name:urd_x_preferred":[
        "\u0645\u0627\u0646\u06a9\u0627\u067e\u0648\u0631"
    ],
    "name:vie_x_preferred":[
        "Mankapur"
    ],
    "name:zho_x_preferred":[
        "\u66fc\u5361\u666e\u5c14"
    ],
    "wof:name":"Mankapur",
    "wof:placetype":"neighbourhood"
},
  "geometry": {"coordinates":[81.50387000000001,27.58568],"type":"Point"}
}