{
  "type": "Feature",
  "properties": {
    "iso:country":"IN",
    "ks:ks_name":"Marla Kummeru",
    "ks:ks_pop":24,
    "ks:ks_type":"HABITATION",
    "name:eng_x_preferred":[
        "Marla Kummeru"
    ],
    "wof:name":"Marla Kummeru",
    "wof:placetype":"locality",
    "wof:population":24
},
  "geometry": {"coordinates":[75.204722,12.643735],"type":"Point"}
}