{
  "type": "Feature",
  "properties": {
    "gn:admin1_code":"40.0",
    "gn:admin2_code":"535.0",
    "gn:asciiname":"Koplapalli",
    "gn:country_code":"IN",
    "gn:dem":512,
    "gn:feature_class":"P",
    "gn:feature_code":"PPL",
    "gn:name":"Koplapalli",
    "gn:population":0,
    "gn:timezone":"Asia/Kolkata",
    "iso:country":"IN",
    "wof:name":"Koplapalli",
    "wof:placetype":"neighbourhood"
},
  "geometry": {"coordinates":[78.42872,17.89361],"type":"Point"}
}