{
  "type": "Feature",
  "properties": {
    "iso:country":"IN",
    "ks:ks_name":"Thermala",
    "ks:ks_pop":1646,
    "ks:ks_type":"HABITATION",
    "name:eng_x_preferred":[
        "Thermala"
    ],
    "wof:name":"Thermala",
    "wof:placetype":"locality",
    "wof:population":1646
},
  "geometry": {"coordinates":[75.634019,12.02833],"type":"Point"}
}