{
  "type": "Feature",
  "properties": {
    "iso:country":"IN",
    "ks:ks_name":"Yadav Tol West",
    "ks:ks_pop":850,
    "ks:ks_type":"HABITATION",
    "ks:ks_uagg_main":0,
    "name:eng_x_preferred":[
        "Yadav Tol West"
    ],
    "wof:name":"Yadav Tol West",
    "wof:placetype":"neighbourhood",
    "wof:population":850
},
  "geometry": {"coordinates":[87.09041499999999,25.458203],"type":"Point"}
}