{
  "type": "Feature",
  "properties": {
    "iso:country":"IN",
    "ks:ks_name":"Barkela",
    "ks:ks_pop":567,
    "ks:ks_type":"VILLAGE",
    "name:eng_x_preferred":[
        "Barkela"
    ],
    "wof:name":"Barkela",
    "wof:placetype":"locality",
    "wof:population":567
},
  "geometry": {"coordinates":[82.26150199999999,23.222917],"type":"Point"}
}