{
  "type": "Feature",
  "properties": {
    "gn:admin1_code":"24.0",
    "gn:admin2_code":"122.0",
    "gn:asciiname":"Bhaironpura",
    "gn:country_code":"IN",
    "gn:dem":466,
    "gn:feature_class":"P",
    "gn:feature_code":"PPL",
    "gn:name":"Bhaironpura",
    "gn:population":0,
    "gn:timezone":"Asia/Kolkata",
    "iso:country":"IN",
    "ks:ks_alt_nam":"Bhaironpura",
    "ks:ks_name":"Bhairoo Pura",
    "ks:ks_pop":158,
    "ks:ks_type":"VILLAGE",
    "name:eng_x_preferred":[
        "Bhairoo Pura"
    ],
    "name:eng_x_variant":[
        "Bhaironpura"
    ],
    "wof:name":"Bhairoo Pura",
    "wof:placetype":"locality",
    "wof:population":158
},
  "geometry": {"coordinates":[74.351151,25.915565],"type":"Point"}
}