{
  "type": "Feature",
  "properties": {
    "gn:admin1_code":"34.0",
    "gn:admin2_code":"224.0",
    "gn:asciiname":"Dhanaura",
    "gn:country_code":"IN",
    "gn:dem":40,
    "gn:feature_class":"P",
    "gn:feature_code":"PPL",
    "gn:name":"Dhanaura",
    "gn:population":0,
    "gn:timezone":"Asia/Kolkata",
    "iso:country":"IN",
    "name:bpy_x_preferred":[
        "\u09a7\u09be\u09a8\u09cc\u09b0\u09be"
    ],
    "name:ceb_x_preferred":[
        "Dhanaura"
    ],
    "name:hin_x_preferred":[
        "\u0927\u0928\u094c\u0930\u093e"
    ],
    "name:ita_x_preferred":[
        "Dhanaura"
    ],
    "name:mlg_x_preferred":[
        "Dhanaura"
    ],
    "name:msa_x_preferred":[
        "Dhanaura"
    ],
    "name:new_x_preferred":[
        "\u0927\u0928\u094c\u0930\u093e"
    ],
    "name:nld_x_preferred":[
        "Dhanaura"
    ],
    "name:pol_x_preferred":[
        "Dhanaura"
    ],
    "name:por_x_preferred":[
        "Dhanaura"
    ],
    "name:swe_x_preferred":[
        "Dhanaura"
    ],
    "name:urd_x_preferred":[
        "\u062f\u06be\u0646\u0648\u0631\u0627"
    ],
    "name:vie_x_preferred":[
        "Dhanaura"
    ],
    "wof:name":"Dhanaura",
    "wof:placetype":"locality"
},
  "geometry": {"coordinates":[87.25950999999998,25.19047],"type":"Point"}
}