{
  "type": "Feature",
  "properties": {
    "gn:admin1_code":"34.0",
    "gn:admin2_code":"214.0",
    "gn:asciiname":"Anadpur",
    "gn:country_code":"IN",
    "gn:dem":41,
    "gn:feature_class":"P",
    "gn:feature_code":"PPL",
    "gn:name":"Anadpur",
    "gn:population":0,
    "gn:timezone":"Asia/Kolkata",
    "iso:country":"IN",
    "wof:name":"Anadpur",
    "wof:placetype":"locality"
},
  "geometry": {"coordinates":[86.73874000000001,25.66767],"type":"Point"}
}