{
  "type": "Feature",
  "properties": {
    "iso:country":"IN",
    "ks:ks_name":"Kongam",
    "ks:ks_pop":215,
    "ks:ks_type":"HABITATION",
    "name:eng_x_preferred":[
        "Kongam"
    ],
    "wof:name":"Kongam",
    "wof:placetype":"locality",
    "wof:population":215
},
  "geometry": {"coordinates":[83.381753,19.381191],"type":"Point"}
}