{
  "type": "Feature",
  "properties": {
    "iso:country":"IN",
    "ks:ks_name":"Chinnachoderaimanu",
    "ks:ks_pop":34,
    "ks:ks_type":"HABITATION",
    "name:eng_x_preferred":[
        "Chinnachoderaimanu"
    ],
    "wof:name":"Chinnachoderaimanu",
    "wof:placetype":"locality",
    "wof:population":34
},
  "geometry": {"coordinates":[82.399289,17.98115],"type":"Point"}
}