{
  "type": "Feature",
  "properties": {
    "iso:country":"IN",
    "ks:ks_name":"Gasi",
    "ks:ks_pop":626,
    "ks:ks_type":"VILLAGE",
    "name:eng_x_preferred":[
        "Gasi"
    ],
    "wof:name":"Gasi",
    "wof:placetype":"locality",
    "wof:population":626
},
  "geometry": {"coordinates":[79.970204,30.041495],"type":"Point"}
}