{
  "type": "Feature",
  "properties": {
    "gn:admin1_code":"38.0",
    "gn:admin2_code":"358.0",
    "gn:asciiname":"Dema",
    "gn:country_code":"IN",
    "gn:dem":339,
    "gn:feature_class":"P",
    "gn:feature_code":"PPL",
    "gn:name":"Dem\u0101",
    "gn:population":0,
    "gn:timezone":"Asia/Kolkata",
    "iso:country":"IN",
    "ks:ks_alt_nam":"Dem\u0101",
    "ks:ks_name":"Dema",
    "ks:ks_pop":184,
    "ks:ks_type":"VILLAGE",
    "name:ceb_x_preferred":[
        "Dema"
    ],
    "name:deu_x_preferred":[
        "Dema"
    ],
    "name:eng_x_preferred":[
        "Dema"
    ],
    "name:eng_x_variant":[
        "Dem\u0101"
    ],
    "name:fra_x_preferred":[
        "Dema"
    ],
    "name:ita_x_preferred":[
        "Dema"
    ],
    "name:swe_x_preferred":[
        "Dema"
    ],
    "wof:name":"Dema",
    "wof:placetype":"locality",
    "wof:population":184
},
  "geometry": {"coordinates":[84.382311,24.00038],"type":"Point"}
}