{
  "type": "Feature",
  "properties": {
    "iso:country":"IN",
    "ks:ks_name":"Sadak Banjari",
    "ks:ks_type":"VILLAGE",
    "ks:ks_uagg_main":0,
    "name:eng_x_preferred":[
        "Sadak Banjari"
    ],
    "wof:name":"Sadak Banjari",
    "wof:placetype":"neighbourhood"
},
  "geometry": {"coordinates":[80.60809,21.082133],"type":"Point"}
}