{
  "type": "Feature",
  "properties": {
    "iso:country":"IN",
    "ks:ks_name":"Dihipara",
    "ks:ks_pop":252,
    "ks:ks_type":"HABITATION",
    "name:eng_x_preferred":[
        "Dihipara"
    ],
    "wof:name":"Dihipara",
    "wof:placetype":"locality",
    "wof:population":252
},
  "geometry": {"coordinates":[81.48087700000001,20.434361],"type":"Point"}
}