{
  "type": "Feature",
  "properties": {
    "iso:country":"IN",
    "ks:ks_name":"Janpar Suba 2",
    "ks:ks_pop":132,
    "ks:ks_type":"HABITATION",
    "name:eng_x_preferred":[
        "Janpar Suba 2"
    ],
    "wof:name":"Janpar Suba 2",
    "wof:placetype":"locality",
    "wof:population":132
},
  "geometry": {"coordinates":[91.750872,26.357048],"type":"Point"}
}