{
  "type": "Feature",
  "properties": {
    "iso:country":"IN",
    "ks:ks_name":"Nuadoliamb",
    "ks:ks_pop":373,
    "ks:ks_type":"VILLAGE",
    "name:eng_x_preferred":[
        "Nuadoliamb"
    ],
    "wof:name":"Nuadoliamb",
    "wof:placetype":"locality",
    "wof:population":373
},
  "geometry": {"coordinates":[82.28968,18.122936],"type":"Point"}
}