{
  "type": "Feature",
  "properties": {
    "gn:admin1_code":"2.0",
    "gn:admin2_code":"544.0",
    "gn:asciiname":"Talarsing",
    "gn:country_code":"IN",
    "gn:dem":939,
    "gn:feature_class":"P",
    "gn:feature_code":"PPL",
    "gn:name":"Talarsing",
    "gn:population":0,
    "gn:timezone":"Asia/Kolkata",
    "iso:country":"IN",
    "ks:ks_name":"Talarisingi",
    "ks:ks_pop":1772,
    "ks:ks_type":"VILLAGE",
    "ks:ks_uagg_main":0,
    "name:eng_x_preferred":[
        "Talarisingi"
    ],
    "wof:name":"Talarisingi",
    "wof:placetype":"neighbourhood",
    "wof:population":1772
},
  "geometry": {"coordinates":[82.66969400000001,18.09209],"type":"Point"}
}