{
  "type": "Feature",
  "properties": {
    "gn:admin1_code":"39.0",
    "gn:admin2_code":"60.0",
    "gn:asciiname":"Ramtapara",
    "gn:country_code":"IN",
    "gn:dem":1084,
    "gn:feature_class":"P",
    "gn:feature_code":"PPL",
    "gn:name":"R\u0101mt\u0101para",
    "gn:population":0,
    "gn:timezone":"Asia/Kolkata",
    "iso:country":"IN",
    "wof:name":"Ramtapara",
    "wof:placetype":"locality"
},
  "geometry": {"coordinates":[77.76364000000002,30.70219],"type":"Point"}
}