{
  "type": "Feature",
  "properties": {
    "iso:country":"IN",
    "ks:ks_alt_nam":"Rangagarah gaon Dakhin",
    "ks:ks_name":"Rangagarah Gaon Dakhin",
    "ks:ks_pop":500,
    "ks:ks_type":"HABITATION",
    "name:eng_x_preferred":[
        "Rangagarah Gaon Dakhin"
    ],
    "wof:name":"Rangagarah Gaon Dakhin",
    "wof:placetype":"locality",
    "wof:population":500
},
  "geometry": {"coordinates":[92.88339000000001,26.422655],"type":"Point"}
}