{
  "type": "Feature",
  "properties": {
    "iso:country":"IN",
    "ks:ks_name":"Patdi",
    "ks:ks_pop":1165,
    "ks:ks_type":"VILLAGE",
    "name:eng_x_preferred":[
        "Patdi"
    ],
    "wof:name":"Patdi",
    "wof:placetype":"locality",
    "wof:population":1165
},
  "geometry": {"coordinates":[74.73611200000001,23.413391],"type":"Point"}
}