{
  "type": "Feature",
  "properties": {
    "iso:country":"IN",
    "ks:ks_name":"Bodduvenkatesupeta",
    "ks:ks_pop":139,
    "ks:ks_type":"HABITATION",
    "name:eng_x_preferred":[
        "Bodduvenkatesupeta"
    ],
    "wof:name":"Bodduvenkatesupeta",
    "wof:placetype":"locality",
    "wof:population":139
},
  "geometry": {"coordinates":[83.569056,18.015092],"type":"Point"}
}