{
  "type": "Feature",
  "properties": {
    "gn:admin1_code":"35.0",
    "gn:admin2_code":"464.0",
    "gn:asciiname":"Satseria",
    "gn:country_code":"IN",
    "gn:dem":291,
    "gn:feature_class":"P",
    "gn:feature_code":"PPL",
    "gn:name":"S\u0101tseria",
    "gn:population":0,
    "gn:timezone":"Asia/Kolkata",
    "iso:country":"IN",
    "ks:ks_name":"Satsera",
    "ks:ks_pop":1780,
    "ks:ks_type":"VILLAGE",
    "name:eng_x_preferred":[
        "Satsera"
    ],
    "name:eng_x_variant":[
        "Satseria"
    ],
    "wof:name":"Satsera",
    "wof:placetype":"locality",
    "wof:population":1780
},
  "geometry": {"coordinates":[74.347902,22.951615],"type":"Point"}
}