{
  "type": "Feature",
  "properties": {
    "iso:country":"IN",
    "ks:ks_name":"No.3 Uppar Tinsukia",
    "ks:ks_pop":334,
    "ks:ks_type":"VILLAGE",
    "name:eng_x_preferred":[
        "No.3 Uppar Tinsukia"
    ],
    "wof:name":"No.3 Uppar Tinsukia",
    "wof:placetype":"locality",
    "wof:population":334
},
  "geometry": {"coordinates":[93.735933,26.815545],"type":"Point"}
}