{
  "type": "Feature",
  "properties": {
    "iso:country":"IN",
    "ks:ks_name":"Chhakaiya Harijan Basti",
    "ks:ks_pop":120,
    "ks:ks_type":"HABITATION",
    "ks:ks_uagg_main":0,
    "name:eng_x_preferred":[
        "Chhakaiya Harijan Basti"
    ],
    "wof:name":"Chhakaiya Harijan Basti",
    "wof:placetype":"neighbourhood",
    "wof:population":120
},
  "geometry": {"coordinates":[82.867183,26.263664],"type":"Point"}
}