{
  "type": "Feature",
  "properties": {
    "iso:country":"IN",
    "ks:ks_name":"Chamaran Tola",
    "ks:ks_pop":192,
    "ks:ks_type":"HABITATION",
    "name:eng_x_preferred":[
        "Chamaran Tola"
    ],
    "wof:name":"Chamaran Tola",
    "wof:placetype":"locality",
    "wof:population":192
},
  "geometry": {"coordinates":[81.884439,27.101046],"type":"Point"}
}