{
  "type": "Feature",
  "properties": {
    "iso:country":"IN",
    "ks:ks_name":"Akhtyarpur Dilpur",
    "ks:ks_pop":1519,
    "ks:ks_type":"VILLAGE",
    "ks:ks_uagg_main":0,
    "name:eng_x_preferred":[
        "Akhtyarpur Dilpur"
    ],
    "wof:name":"Akhtyarpur Dilpur",
    "wof:placetype":"neighbourhood",
    "wof:population":1519
},
  "geometry": {"coordinates":[78.532667,28.624913],"type":"Point"}
}