{
  "type": "Feature",
  "properties": {
    "gn:admin1_code":"23.0",
    "gn:admin2_code":"048",
    "gn:asciiname":"Chirwa",
    "gn:country_code":"IN",
    "gn:dem":258,
    "gn:feature_class":"P",
    "gn:feature_code":"PPL",
    "gn:name":"Chirwa",
    "gn:population":0,
    "gn:timezone":"Asia/Kolkata",
    "iso:country":"IN",
    "wof:name":"Chirwa",
    "wof:placetype":"locality"
},
  "geometry": {"coordinates":[76.58306999999998,30.23987],"type":"Point"}
}