{
  "type": "Feature",
  "properties": {
    "iso:country":"IN",
    "ks:ks_alt_nam":"Poomankollai South AD Street",
    "ks:ks_name":"Poomankollai South Ad Street",
    "ks:ks_pop":48,
    "ks:ks_type":"HABITATION",
    "name:eng_x_preferred":[
        "Poomankollai South Ad Street"
    ],
    "wof:name":"Poomankollai South Ad Street",
    "wof:placetype":"locality",
    "wof:population":48
},
  "geometry": {"coordinates":[79.09551999999999,10.21566],"type":"Point"}
}