{
  "type": "Feature",
  "properties": {
    "gn:admin1_code":"35.0",
    "gn:admin2_code":"419.0",
    "gn:asciiname":"Dongarpur",
    "gn:country_code":"IN",
    "gn:dem":194,
    "gn:feature_class":"P",
    "gn:feature_code":"PPL",
    "gn:name":"Dongarpur",
    "gn:population":0,
    "gn:timezone":"Asia/Kolkata",
    "iso:country":"IN",
    "ks:ks_name":"Dongarpur",
    "ks:ks_type":"VILLAGE",
    "name:eng_x_preferred":[
        "Dongarpur"
    ],
    "wof:name":"Dongarpur",
    "wof:placetype":"locality"
},
  "geometry": {"coordinates":[77.760987,26.290649],"type":"Point"}
}