{
  "type": "Feature",
  "properties": {
    "gn:admin1_code":"37.0",
    "gn:admin2_code":"416.0",
    "gn:asciiname":"Michiguda",
    "gn:country_code":"IN",
    "gn:dem":641,
    "gn:feature_class":"P",
    "gn:feature_code":"PPL",
    "gn:name":"M\u012bchig\u016bda",
    "gn:population":0,
    "gn:timezone":"Asia/Kolkata",
    "iso:country":"IN",
    "ks:ks_alt_nam":"M\u012bchig\u016bda",
    "ks:ks_name":"Michiguda",
    "ks:ks_type":"VILLAGE",
    "name:eng_x_preferred":[
        "Michiguda"
    ],
    "name:eng_x_variant":[
        "M\u012bchig\u016bda"
    ],
    "wof:name":"Michiguda",
    "wof:placetype":"locality"
},
  "geometry": {"coordinates":[81.388969,18.385521],"type":"Point"}
}