{
  "type": "Feature",
  "properties": {
    "gn:admin1_code":"2",
    "gn:admin2_code":"546.0",
    "gn:asciiname":"Surappagudem",
    "gn:country_code":"IN",
    "gn:dem":17,
    "gn:feature_class":"P",
    "gn:feature_code":"PPL",
    "gn:name":"Surappagudem",
    "gn:population":0,
    "gn:timezone":"Asia/Kolkata",
    "iso:country":"IN",
    "name:tel_x_preferred":[
        "\u0c38\u0c42\u0c30\u0c2a\u0c4d\u0c2a\u0c17\u0c42\u0c21\u0c46\u0c02"
    ],
    "wof:name":"Surappagudem",
    "wof:placetype":"locality"
},
  "geometry": {"coordinates":[81.24200999999999,16.80862],"type":"Point"}
}