{
  "type": "Feature",
  "properties": {
    "iso:country":"IN",
    "ks:ks_name":"Sabarpada",
    "ks:ks_pop":25,
    "ks:ks_type":"HABITATION",
    "name:eng_x_preferred":[
        "Sabarpada"
    ],
    "wof:name":"Sabarpada",
    "wof:placetype":"locality",
    "wof:population":25
},
  "geometry": {"coordinates":[83.392979,19.986067],"type":"Point"}
}