{
  "type": "Feature",
  "properties": {
    "iso:country":"IN",
    "ks:ks_name":"Kerla",
    "ks:ks_pop":190,
    "ks:ks_type":"VILLAGE",
    "name:eng_x_preferred":[
        "Kerla"
    ],
    "wof:name":"Kerla",
    "wof:placetype":"locality",
    "wof:population":190
},
  "geometry": {"coordinates":[72.814611,27.088675],"type":"Point"}
}