{
  "type": "Feature",
  "properties": {
    "iso:country":"IN",
    "ks:ks_name":"Madhalawathar",
    "ks:ks_pop":226,
    "ks:ks_type":"HABITATION",
    "name:eng_x_preferred":[
        "Madhalawathar"
    ],
    "wof:name":"Madhalawathar",
    "wof:placetype":"locality",
    "wof:population":226
},
  "geometry": {"coordinates":[73.34116899999999,16.932843],"type":"Point"}
}