{
  "type": "Feature",
  "properties": {
    "gn:admin1_code":"36.0",
    "gn:admin2_code":"193.0",
    "gn:asciiname":"Senduriya",
    "gn:country_code":"IN",
    "gn:dem":70,
    "gn:feature_class":"P",
    "gn:feature_code":"PPL",
    "gn:name":"Senduriya",
    "gn:population":0,
    "gn:timezone":"Asia/Kolkata",
    "iso:country":"IN",
    "ks:ks_name":"Senduria",
    "ks:ks_pop":1894,
    "ks:ks_type":"VILLAGE",
    "ks:ks_uagg_main":0,
    "name:eng_x_preferred":[
        "Senduria"
    ],
    "wof:name":"Senduria",
    "wof:placetype":"neighbourhood",
    "wof:population":1894
},
  "geometry": {"coordinates":[84.002138,25.640718],"type":"Point"}
}