{
  "type": "Feature",
  "properties": {
    "iso:country":"IN",
    "ks:ks_name":"Piarapur",
    "ks:ks_pop":1598,
    "ks:ks_type":"VILLAGE",
    "name:eng_x_preferred":[
        "Piarapur"
    ],
    "wof:name":"Piarapur",
    "wof:placetype":"locality",
    "wof:population":1598
},
  "geometry": {"coordinates":[87.950907,22.732237],"type":"Point"}
}