{
  "type": "Feature",
  "properties": {
    "iso:country":"IN",
    "ks:ks_name":"Kalandiambo",
    "ks:ks_pop":62,
    "ks:ks_type":"VILLAGE",
    "name:eng_x_preferred":[
        "Kalandiambo"
    ],
    "wof:name":"Kalandiambo",
    "wof:placetype":"locality",
    "wof:population":62
},
  "geometry": {"coordinates":[83.018979,19.386687],"type":"Point"}
}