{
  "type": "Feature",
  "properties": {
    "gn:admin1_code":"9.0",
    "gn:admin2_code":"469.0",
    "gn:asciiname":"Wadhna",
    "gn:country_code":"IN",
    "gn:dem":188,
    "gn:feature_class":"P",
    "gn:feature_code":"PPL",
    "gn:name":"W\u0101dhna",
    "gn:population":0,
    "gn:timezone":"Asia/Kolkata",
    "iso:country":"IN",
    "wof:name":"Wadhna",
    "wof:placetype":"locality"
},
  "geometry": {"coordinates":[72.36225,24.23884],"type":"Point"}
}