{
  "type": "Feature",
  "properties": {
    "iso:country":"IN",
    "ks:ks_alt_nam":"Sukha purwa",
    "ks:ks_name":"Sukha Purwa",
    "ks:ks_pop":112,
    "ks:ks_type":"HABITATION",
    "ks:ks_uagg_main":0,
    "name:eng_x_preferred":[
        "Sukha Purwa"
    ],
    "wof:name":"Sukha Purwa",
    "wof:placetype":"neighbourhood",
    "wof:population":112
},
  "geometry": {"coordinates":[79.84674200000001,26.952612],"type":"Point"}
}