{
  "type": "Feature",
  "properties": {
    "iso:country":"IN",
    "ks:ks_name":"Guragirdhari",
    "ks:ks_pop":68,
    "ks:ks_type":"VILLAGE",
    "name:eng_x_preferred":[
        "Guragirdhari"
    ],
    "wof:name":"Guragirdhari",
    "wof:placetype":"locality",
    "wof:population":68
},
  "geometry": {"coordinates":[73.47620000000001,25.614963],"type":"Point"}
}