{
  "type": "Feature",
  "properties": {
    "iso:country":"IN",
    "ks:ks_name":"Berachapa",
    "ks:ks_pop":289,
    "ks:ks_type":"VILLAGE",
    "ks:ks_uagg_main":0,
    "name:eng_x_preferred":[
        "Berachapa"
    ],
    "wof:name":"Berachapa",
    "wof:placetype":"neighbourhood",
    "wof:population":289
},
  "geometry": {"coordinates":[87.378918,22.890837],"type":"Point"}
}