{
  "type": "Feature",
  "properties": {
    "gn:admin1_code":"16",
    "gn:admin2_code":"526.0",
    "gn:asciiname":"Gogaon",
    "gn:country_code":"IN",
    "gn:dem":532,
    "gn:feature_class":"P",
    "gn:feature_code":"PPL",
    "gn:name":"Gogaon",
    "gn:population":0,
    "gn:timezone":"Asia/Kolkata",
    "iso:country":"IN",
    "name:ben_x_preferred":[
        "\u0997\u09cb\u0997\u09be\u0981\u0993"
    ],
    "name:bpy_x_preferred":[
        "\u0997\u09cb\u0997\u09be\u0981\u0993"
    ],
    "name:hin_x_preferred":[
        "\u0917\u094b\u0917\u093e\u0901\u0935"
    ],
    "name:ita_x_preferred":[
        "Gogaon"
    ],
    "name:msa_x_preferred":[
        "Gogaon"
    ],
    "name:new_x_preferred":[
        "\u0917\u094b\u0917\u093e\u0902\u0935"
    ],
    "name:nld_x_preferred":[
        "Gogaon"
    ],
    "name:por_x_preferred":[
        "Gogaon"
    ],
    "name:spa_x_preferred":[
        "Gogaon"
    ],
    "name:tgl_x_preferred":[
        "Gogaon"
    ],
    "name:urd_x_preferred":[
        "\u06af\u0648\u06af\u0627\u0624\u06ba"
    ],
    "name:vie_x_preferred":[
        "Gogaon"
    ],
    "name:zho_x_preferred":[
        "\u6208\u52a0\u5965\u6069"
    ],
    "wof:name":"Gogaon",
    "wof:placetype":"locality"
},
  "geometry": {"coordinates":[76.39981999999998,17.62312],"type":"Point"}
}