{
  "type": "Feature",
  "properties": {
    "gn:admin1_code":"16",
    "gn:admin2_code":"501.0",
    "gn:asciiname":"Pati",
    "gn:country_code":"IN",
    "gn:dem":267,
    "gn:feature_class":"P",
    "gn:feature_code":"PPL",
    "gn:name":"P\u0101ti",
    "gn:population":0,
    "gn:timezone":"Asia/Kolkata",
    "iso:country":"IN",
    "name:ceb_x_preferred":[
        "Pati"
    ],
    "name:deu_x_preferred":[
        "Pati"
    ],
    "name:fas_x_preferred":[
        "\u067e\u0627\u062a\u06cc"
    ],
    "name:fas_x_variant":[
        "\u067e\u062a\u06cc"
    ],
    "name:fra_x_preferred":[
        "Pati"
    ],
    "name:heb_x_preferred":[
        "\u05e4\u05d8\u05d9"
    ],
    "name:hin_x_preferred":[
        "\u092a\u093e\u091f\u0940"
    ],
    "name:hun_x_preferred":[
        "Pati"
    ],
    "name:ind_x_preferred":[
        "Pati"
    ],
    "name:ita_x_preferred":[
        "Pati"
    ],
    "name:kor_x_preferred":[
        "\ud30c\ud2f0"
    ],
    "name:mlg_x_preferred":[
        "Pati"
    ],
    "name:nld_x_preferred":[
        "Pati"
    ],
    "name:pol_x_preferred":[
        "Pati"
    ],
    "name:por_x_preferred":[
        "Pati"
    ],
    "name:rus_x_preferred":[
        "\u041f\u0430\u0442\u0438"
    ],
    "name:swe_x_preferred":[
        "Pati"
    ],
    "name:tur_x_preferred":[
        "Pati"
    ],
    "name:ukr_x_preferred":[
        "\u041f\u0430\u0442\u0456"
    ],
    "name:urd_x_preferred":[
        "\u067e\u0627\u062a\u06cc"
    ],
    "name:vie_x_preferred":[
        "Pati"
    ],
    "name:zho_cn_x_preferred":[
        "\u5df4\u8482"
    ],
    "name:zho_tw_x_preferred":[
        "\u5e15\u8482"
    ],
    "wof:name":"Pati",
    "wof:placetype":"locality"
},
  "geometry": {"coordinates":[77.07286000000001,20.86639],"type":"Point"}
}