{
  "type": "Feature",
  "properties": {
    "gn:admin1_code":"16",
    "gn:admin2_code":"501.0",
    "gn:asciiname":"Pati",
    "gn:country_code":"IN",
    "gn:dem":267,
    "gn:feature_class":"P",
    "gn:feature_code":"PPL",
    "gn:name":"P\u0101ti",
    "gn:population":0,
    "gn:timezone":"Asia/Kolkata",
    "iso:country":"IN",
    "name:ceb_x_preferred":[
        "Pati"
    ],
    "name:deu_x_preferred":[
        "Pati"
    ],
    "name:fas_x_preferred":[
        "\u067e\u062a\u06cc"
    ],
    "name:fra_x_preferred":[
        "Pati"
    ],
    "name:ind_x_preferred":[
        "Pati"
    ],
    "name:mlg_x_preferred":[
        "Pati"
    ],
    "name:nld_x_preferred":[
        "Pati"
    ],
    "name:swe_x_preferred":[
        "Pati"
    ],
    "wof:name":"Pati",
    "wof:placetype":"locality"
},
  "geometry": {"coordinates":[77.07285999999998,20.86639],"type":"Point"}
}