{
  "type": "Feature",
  "properties": {
    "iso:country":"IN",
    "ks:ks_name":"Sultan Nagar",
    "ks:ks_pop":51,
    "ks:ks_type":"VILLAGE",
    "ks:ks_uagg_main":0,
    "name:eng_x_preferred":[
        "Sultan Nagar"
    ],
    "wof:name":"Sultan Nagar",
    "wof:placetype":"neighbourhood",
    "wof:population":51
},
  "geometry": {"coordinates":[83.349723,25.872353],"type":"Point"}
}