{
  "type": "Feature",
  "properties": {
    "gn:admin1_code":"34.0",
    "gn:admin2_code":"237.0",
    "gn:asciiname":"Domawar",
    "gn:country_code":"IN",
    "gn:dem":76,
    "gn:feature_class":"P",
    "gn:feature_code":"PPL",
    "gn:name":"Domawar",
    "gn:population":0,
    "gn:timezone":"Asia/Kolkata",
    "iso:country":"IN",
    "ks:ks_name":"Domawar",
    "ks:ks_type":"VILLAGE",
    "name:eng_x_preferred":[
        "Domawar"
    ],
    "wof:name":"Domawar",
    "wof:placetype":"locality"
},
  "geometry": {"coordinates":[85.47164100000001,24.977005],"type":"Point"}
}