{
  "type": "Feature",
  "properties": {
    "gn:admin1_code":"25.0",
    "gn:admin2_code":"611.0",
    "gn:asciiname":"Ariakottu",
    "gn:country_code":"IN",
    "gn:dem":960,
    "gn:feature_class":"P",
    "gn:feature_code":"PPL",
    "gn:name":"Ariakottu",
    "gn:population":0,
    "gn:timezone":"Asia/Kolkata",
    "iso:country":"IN",
    "wof:name":"Ariakottu",
    "wof:placetype":"locality"
},
  "geometry": {"coordinates":[76.4508,11.57032],"type":"Point"}
}