{
  "type": "Feature",
  "properties": {
    "iso:country":"IN",
    "ks:ks_name":"Chintapalle Reserved Forest",
    "ks:ks_type":"VILLAGE",
    "name:eng_x_preferred":[
        "Chintapalle Reserved Forest"
    ],
    "wof:name":"Chintapalle Reserved Forest",
    "wof:placetype":"locality"
},
  "geometry": {"coordinates":[82.32270200000001,17.905059],"type":"Point"}
}