{
  "type": "Feature",
  "properties": {
    "gn:admin1_code":"12.0",
    "gn:admin2_code":"13.0",
    "gn:asciiname":"Alshipur",
    "gn:country_code":"IN",
    "gn:dem":1761,
    "gn:feature_class":"P",
    "gn:feature_code":"PPL",
    "gn:name":"Alshipur",
    "gn:population":0,
    "gn:timezone":"Asia/Kolkata",
    "iso:country":"IN",
    "wof:name":"Alshipur",
    "wof:placetype":"locality"
},
  "geometry": {"coordinates":[74.95437,33.75327],"type":"Point"}
}