{
  "type": "Feature",
  "properties": {
    "iso:country":"IN",
    "ks:ks_name":"Bahupatti",
    "ks:ks_pop":1371,
    "ks:ks_type":"VILLAGE",
    "name:eng_x_preferred":[
        "Bahupatti"
    ],
    "wof:name":"Bahupatti",
    "wof:placetype":"locality",
    "wof:population":1371
},
  "geometry": {"coordinates":[85.847966,26.065915],"type":"Point"}
}