{
  "type": "Feature",
  "properties": {
    "gn:admin1_code":"19.0",
    "gn:admin2_code":"575.0",
    "gn:asciiname":"Narikombu",
    "gn:country_code":"IN",
    "gn:dem":26,
    "gn:feature_class":"P",
    "gn:feature_code":"PPLL",
    "gn:name":"Narikombu",
    "gn:population":0,
    "gn:timezone":"Asia/Kolkata",
    "iso:country":"IN",
    "ks:ks_name":"Narikombu",
    "ks:ks_pop":7021,
    "ks:ks_type":"URBAN",
    "name:eng_x_preferred":[
        "Narikombu"
    ],
    "name:vie_x_preferred":[
        "Narikombu"
    ],
    "wof:name":"Narikombu",
    "wof:placetype":"locality",
    "wof:population":7021
},
  "geometry": {"coordinates":[75.06120799999999,12.881578],"type":"Point"}
}