{
  "type": "Feature",
  "properties": {
    "gn:admin1_code":"19.0",
    "gn:admin2_code":"575.0",
    "gn:asciiname":"Narikombu",
    "gn:country_code":"IN",
    "gn:dem":26,
    "gn:feature_class":"P",
    "gn:feature_code":"PPLL",
    "gn:name":"Narikombu",
    "gn:population":0,
    "gn:timezone":"Asia/Kolkata",
    "iso:country":"IN",
    "wof:name":"Narikombu",
    "wof:placetype":"locality"
},
  "geometry": {"coordinates":[75.05423,12.88458],"type":"Point"}
}