{
  "type": "Feature",
  "properties": {
    "iso:country":"IN",
    "ks:ks_name":"Erthan",
    "ks:ks_pop":845,
    "ks:ks_type":"VILLAGE",
    "name:eng_x_preferred":[
        "Erthan"
    ],
    "wof:name":"Erthan",
    "wof:placetype":"neighbourhood",
    "wof:population":845
},
  "geometry": {"coordinates":[72.9496,21.119979],"type":"Point"}
}