{
  "type": "Feature",
  "properties": {
    "gn:admin1_code":"36.0",
    "gn:admin2_code":"161",
    "gn:asciiname":"Jaitupur Khuajji",
    "gn:country_code":"IN",
    "gn:dem":149,
    "gn:feature_class":"P",
    "gn:feature_code":"PPL",
    "gn:name":"Jaitupur Khu\u0101jji",
    "gn:population":0,
    "gn:timezone":"Asia/Kolkata",
    "iso:country":"IN",
    "name:und_x_variant":[
        "Jaitupur Khu\u0101jji",
        "Jait\u016bpura"
    ],
    "wof:name":"Jaitupur Khuajji",
    "wof:placetype":"locality"
},
  "geometry": {"coordinates":[79.21169999999999,26.79432000000001],"type":"Point"}
}