{
  "type": "Feature",
  "properties": {
    "gn:admin1_code":"2.0",
    "gn:admin2_code":"554.0",
    "gn:asciiname":"Tettu",
    "gn:country_code":"IN",
    "gn:dem":735,
    "gn:feature_class":"P",
    "gn:feature_code":"PPL",
    "gn:name":"Tettu",
    "gn:population":0,
    "gn:timezone":"Asia/Kolkata",
    "iso:country":"IN",
    "wof:name":"Tettu",
    "wof:placetype":"locality"
},
  "geometry": {"coordinates":[78.43214999999999,13.62752],"type":"Point"}
}