{
  "type": "Feature",
  "properties": {
    "gn:admin1_code":"11.0",
    "gn:admin2_code":"32.0",
    "gn:asciiname":"Satkuphaina",
    "gn:country_code":"IN",
    "gn:dem":2021,
    "gn:feature_class":"P",
    "gn:feature_code":"PPL",
    "gn:name":"Satkuphaina",
    "gn:population":0,
    "gn:timezone":"Asia/Kolkata",
    "iso:country":"IN",
    "wof:name":"Satkuphaina",
    "wof:placetype":"locality"
},
  "geometry": {"coordinates":[77.67534999999999,30.73515],"type":"Point"}
}