{
  "type": "Feature",
  "properties": {
    "gn:admin1_code":"35.0",
    "gn:admin2_code":"425",
    "gn:asciiname":"Dongwa",
    "gn:country_code":"IN",
    "gn:dem":192,
    "gn:feature_class":"P",
    "gn:feature_code":"PPL",
    "gn:name":"Dongwa",
    "gn:population":0,
    "gn:timezone":"Asia/Kolkata",
    "iso:country":"IN",
    "name:und_x_variant":[
        "Dhogwa"
    ],
    "wof:name":"Dongwa",
    "wof:placetype":"locality"
},
  "geometry": {"coordinates":[80.05278,24.86412],"type":"Point"}
}