{
  "type": "Feature",
  "properties": {
    "gn:admin1_code":"25.0",
    "gn:admin2_code":"631.0",
    "gn:asciiname":"Chinna Ullugurikki",
    "gn:country_code":"IN",
    "gn:dem":752,
    "gn:feature_class":"P",
    "gn:feature_code":"PPL",
    "gn:name":"Chinna Ullugurikki",
    "gn:population":0,
    "gn:timezone":"Asia/Kolkata",
    "iso:country":"IN",
    "ks:ks_name":"Chinnaullukurukkai",
    "ks:ks_pop":608,
    "ks:ks_type":"HABITATION",
    "name:eng_x_preferred":[
        "Chinnaullukurukkai"
    ],
    "name:eng_x_variant":[
        "Chinna Ullugurikki"
    ],
    "wof:name":"Chinnaullukurukkai",
    "wof:placetype":"locality",
    "wof:population":608
},
  "geometry": {"coordinates":[77.967642,12.543595],"type":"Point"}
}