{
  "type": "Feature",
  "properties": {
    "iso:country":"IN",
    "ks:ks_name":"Duthar",
    "ks:ks_pop":180,
    "ks:ks_type":"VILLAGE",
    "name:eng_x_preferred":[
        "Duthar"
    ],
    "wof:name":"Duthar",
    "wof:placetype":"locality",
    "wof:population":180
},
  "geometry": {"coordinates":[73.624833,21.710167],"type":"Point"}
}