{
  "type": "Feature",
  "properties": {
    "iso:country":"IN",
    "ks:ks_name":"Hittalkai",
    "ks:ks_pop":38,
    "ks:ks_type":"HABITATION",
    "name:eng_x_preferred":[
        "Hittalkai"
    ],
    "wof:name":"Hittalkai",
    "wof:placetype":"locality",
    "wof:population":38
},
  "geometry": {"coordinates":[74.77124499999999,14.551051],"type":"Point"}
}