{
  "type": "Feature",
  "properties": {
    "gn:admin1_code":"11.0",
    "gn:admin2_code":"33.0",
    "gn:asciiname":"Kathera",
    "gn:country_code":"IN",
    "gn:dem":1534,
    "gn:feature_class":"P",
    "gn:feature_code":"PPL",
    "gn:name":"Kathera",
    "gn:population":0,
    "gn:timezone":"Asia/Kolkata",
    "iso:country":"IN",
    "name:bpy_x_preferred":[
        "\u0995\u09be\u09a5\u09c7\u09b0\u09be"
    ],
    "name:ita_x_preferred":[
        "Kathera"
    ],
    "name:msa_x_preferred":[
        "Kathera"
    ],
    "name:new_x_preferred":[
        "\u0915\u0920\u0947\u0930\u093e"
    ],
    "name:nld_x_preferred":[
        "Kathera"
    ],
    "name:pol_x_preferred":[
        "Kathera"
    ],
    "name:por_x_preferred":[
        "Kathera"
    ],
    "name:urd_x_preferred":[
        "\u06a9\u0679\u06be\u06cc\u0631\u0627"
    ],
    "name:vie_x_preferred":[
        "Kathera"
    ],
    "name:zho_x_preferred":[
        "\u5361\u6cf0\u62c9"
    ],
    "wof:name":"Kathera",
    "wof:placetype":"locality"
},
  "geometry": {"coordinates":[77.30261,31.15686],"type":"Point"}
}