{
  "type": "Feature",
  "properties": {
    "iso:country":"IN",
    "ks:ks_name":"Wada Kerpoi",
    "ks:ks_pop":178,
    "ks:ks_type":"HABITATION",
    "name:eng_x_preferred":[
        "Wada Kerpoi"
    ],
    "wof:name":"Wada Kerpoi",
    "wof:placetype":"locality",
    "wof:population":178
},
  "geometry": {"coordinates":[73.41158,16.50934],"type":"Point"}
}