{
  "type": "Feature",
  "properties": {
    "gn:admin1_code":"35.0",
    "gn:admin2_code":"464.0",
    "gn:asciiname":"Pawagoi Chhota",
    "gn:country_code":"IN",
    "gn:dem":276,
    "gn:feature_class":"P",
    "gn:feature_code":"PPL",
    "gn:name":"Pawagoi Chhota",
    "gn:population":0,
    "gn:timezone":"Asia/Kolkata",
    "iso:country":"IN",
    "ks:ks_name":"Pawagoi Chhoti",
    "ks:ks_pop":1489,
    "ks:ks_type":"VILLAGE",
    "name:eng_x_preferred":[
        "Pawagoi Chhoti"
    ],
    "name:eng_x_variant":[
        "Pawagoi Chhota"
    ],
    "wof:name":"Pawagoi Chhoti",
    "wof:placetype":"locality",
    "wof:population":1489
},
  "geometry": {"coordinates":[74.514128,22.992677],"type":"Point"}
}