{
  "type": "Feature",
  "properties": {
    "iso:country":"IN",
    "ks:ks_name":"Kuchipara",
    "ks:ks_pop":245,
    "ks:ks_type":"HABITATION",
    "ks:ks_uagg_main":0,
    "name:eng_x_preferred":[
        "Kuchipara"
    ],
    "wof:name":"Kuchipara",
    "wof:placetype":"neighbourhood",
    "wof:population":245
},
  "geometry": {"coordinates":[91.11664,26.669023],"type":"Point"}
}