{
  "type": "Feature",
  "properties": {
    "iso:country":"IN",
    "ks:ks_name":"Zimanpada Falia",
    "ks:ks_pop":116,
    "ks:ks_type":"HABITATION",
    "name:eng_x_preferred":[
        "Zimanpada Falia"
    ],
    "wof:name":"Zimanpada Falia",
    "wof:placetype":"locality",
    "wof:population":116
},
  "geometry": {"coordinates":[73.313121,20.284756],"type":"Point"}
}