{
  "type": "Feature",
  "properties": {
    "gn:admin1_code":"12.0",
    "gn:admin2_code":"004",
    "gn:asciiname":"Chomortan",
    "gn:country_code":"IN",
    "gn:dem":3244,
    "gn:feature_class":"P",
    "gn:feature_code":"PPL",
    "gn:name":"Chomortan",
    "gn:population":0,
    "gn:timezone":"Asia/Kolkata",
    "iso:country":"IN",
    "wof:name":"Chomortan",
    "wof:placetype":"locality"
},
  "geometry": {"coordinates":[76.49215,34.49495],"type":"Point"}
}