{
  "type": "Feature",
  "properties": {
    "gn:admin1_code":"12.0",
    "gn:admin2_code":"17.0",
    "gn:asciiname":"Nagantar",
    "gn:country_code":"IN",
    "gn:dem":2098,
    "gn:feature_class":"P",
    "gn:feature_code":"PPL",
    "gn:name":"N\u0101gantar",
    "gn:population":0,
    "gn:timezone":"Asia/Kolkata",
    "iso:country":"IN",
    "wof:name":"Nagantar",
    "wof:placetype":"locality"
},
  "geometry": {"coordinates":[75.29593,33.33339],"type":"Point"}
}