{
  "type": "Feature",
  "properties": {
    "gn:admin1_code":"24.0",
    "gn:admin2_code":"125.0",
    "gn:asciiname":"Nal",
    "gn:country_code":"IN",
    "gn:dem":258,
    "gn:feature_class":"P",
    "gn:feature_code":"PPL",
    "gn:name":"Nal",
    "gn:population":0,
    "gn:timezone":"Asia/Kolkata",
    "iso:country":"IN",
    "ks:ks_name":"Nal",
    "ks:ks_pop":2171,
    "ks:ks_type":"VILLAGE",
    "name:eng_x_preferred":[
        "Nal"
    ],
    "wof:name":"Nal",
    "wof:placetype":"locality",
    "wof:population":2171
},
  "geometry": {"coordinates":[74.353381,23.355308],"type":"Point"}
}