{
  "type": "Feature",
  "properties": {
    "iso:country":"IN",
    "ks:ks_name":"Chinnamelakudikadu",
    "ks:ks_pop":243,
    "ks:ks_type":"HABITATION",
    "name:eng_x_preferred":[
        "Chinnamelakudikadu"
    ],
    "wof:name":"Chinnamelakudikadu",
    "wof:placetype":"locality",
    "wof:population":243
},
  "geometry": {"coordinates":[79.23921,11.349594],"type":"Point"}
}