{
  "type": "Feature",
  "properties": {
    "iso:country":"IN",
    "ks:ks_name":"Aranda",
    "ks:ks_pop":529,
    "ks:ks_type":"VILLAGE",
    "name:eng_x_preferred":[
        "Aranda"
    ],
    "wof:name":"Aranda",
    "wof:placetype":"locality",
    "wof:population":529
},
  "geometry": {"coordinates":[83.95119800000001,18.861678],"type":"Point"}
}