{
  "type": "Feature",
  "properties": {
    "gn:admin1_code":"11",
    "gn:admin2_code":"24.0",
    "gn:asciiname":"Jol",
    "gn:country_code":"IN",
    "gn:dem":1398,
    "gn:feature_class":"P",
    "gn:feature_code":"PPL",
    "gn:name":"Jol",
    "gn:population":0,
    "gn:timezone":"Asia/Kolkata",
    "iso:country":"IN",
    "name:deu_x_preferred":[
        "Jol"
    ],
    "name:fra_x_preferred":[
        "Jol"
    ],
    "name:nld_x_preferred":[
        "Jol"
    ],
    "name:nno_x_preferred":[
        "Jol"
    ],
    "name:nor_x_preferred":[
        "Jol"
    ],
    "wof:name":"Jol",
    "wof:placetype":"locality"
},
  "geometry": {"coordinates":[76.44129000000002,32.1655],"type":"Point"}
}