{
  "type": "Feature",
  "properties": {
    "iso:country":"IN",
    "ks:ks_alt_nam":"MUSLIM TOLA",
    "ks:ks_name":"Muslim Tola",
    "ks:ks_pop":100,
    "ks:ks_type":"HABITATION",
    "name:eng_x_preferred":[
        "Muslim Tola"
    ],
    "wof:name":"Muslim Tola",
    "wof:placetype":"locality",
    "wof:population":100
},
  "geometry": {"coordinates":[83.817116,23.940136],"type":"Point"}
}