{
  "type": "Feature",
  "properties": {
    "iso:country":"IN",
    "ks:ks_alt_nam":"keelasemponmari",
    "ks:ks_name":"Keelasemponmari",
    "ks:ks_pop":298,
    "ks:ks_type":"HABITATION",
    "ks:ks_uagg_main":0,
    "name:eng_x_preferred":[
        "Keelasemponmari"
    ],
    "wof:name":"Keelasemponmari",
    "wof:placetype":"neighbourhood",
    "wof:population":298
},
  "geometry": {"coordinates":[78.824438,9.973995],"type":"Point"}
}