{
  "type": "Feature",
  "properties": {
    "iso:country":"IN",
    "ks:ks_name":"Rayalam",
    "ks:ks_pop":5866,
    "ks:ks_type":"VILLAGE",
    "ks:ks_uagg_main":0,
    "name:eng_x_preferred":[
        "Rayalam"
    ],
    "wof:name":"Rayalam",
    "wof:placetype":"neighbourhood",
    "wof:population":5866
},
  "geometry": {"coordinates":[81.50642000000001,16.535461],"type":"Point"}
}