{
  "type": "Feature",
  "properties": {
    "iso:country":"IN",
    "ks:ks_alt_nam":"Niz Sariha north",
    "ks:ks_name":"Niz Sariha North",
    "ks:ks_pop":480,
    "ks:ks_type":"HABITATION",
    "ks:ks_uagg_main":0,
    "name:eng_x_preferred":[
        "Niz Sariha North"
    ],
    "wof:name":"Niz Sariha North",
    "wof:placetype":"neighbourhood",
    "wof:population":480
},
  "geometry": {"coordinates":[91.229634,26.504467],"type":"Point"}
}