{
  "type": "Feature",
  "properties": {
    "gn:admin1_code":"23.0",
    "gn:admin2_code":"51.0",
    "gn:asciiname":"Dhangwali Majri",
    "gn:country_code":"IN",
    "gn:dem":362,
    "gn:feature_class":"P",
    "gn:feature_code":"PPL",
    "gn:name":"Dh\u0101ngwali M\u0101jri",
    "gn:population":0,
    "gn:timezone":"Asia/Kolkata",
    "iso:country":"IN",
    "wof:name":"Dhangwali Majri",
    "wof:placetype":"locality"
},
  "geometry": {"coordinates":[76.70428000000003,30.93781],"type":"Point"}
}