{
  "type": "Feature",
  "properties": {
    "iso:country":"IN",
    "ks:ks_name":"Muthiraiyarpatti",
    "ks:ks_pop":158,
    "ks:ks_type":"HABITATION",
    "name:eng_x_preferred":[
        "Muthiraiyarpatti"
    ],
    "wof:name":"Muthiraiyarpatti",
    "wof:placetype":"locality",
    "wof:population":158
},
  "geometry": {"coordinates":[78.955359,12.949698],"type":"Point"}
}