{
  "type": "Feature",
  "properties": {
    "iso:country":"IN",
    "ks:ks_name":"Chhidpur",
    "ks:ks_pop":34,
    "ks:ks_type":"HABITATION",
    "name:eng_x_preferred":[
        "Chhidpur"
    ],
    "wof:name":"Chhidpur",
    "wof:placetype":"locality",
    "wof:population":34
},
  "geometry": {"coordinates":[81.073519,19.32063],"type":"Point"}
}