{
  "type": "Feature",
  "properties": {
    "iso:country":"IN",
    "ks:ks_name":"Thativarigudem",
    "ks:ks_pop":281,
    "ks:ks_type":"HABITATION",
    "name:eng_x_preferred":[
        "Thativarigudem"
    ],
    "wof:name":"Thativarigudem",
    "wof:placetype":"locality",
    "wof:population":281
},
  "geometry": {"coordinates":[80.94958699999999,17.899048],"type":"Point"}
}