{
  "type": "Feature",
  "properties": {
    "gn:admin1_code":"10.0",
    "gn:admin2_code":"83.0",
    "gn:asciiname":"Dhanirwas",
    "gn:country_code":"IN",
    "gn:dem":225,
    "gn:feature_class":"P",
    "gn:feature_code":"PPL",
    "gn:name":"Dhan\u012brw\u0101s",
    "gn:population":0,
    "gn:timezone":"Asia/Kolkata",
    "iso:country":"IN",
    "wof:name":"Dhanirwas",
    "wof:placetype":"locality"
},
  "geometry": {"coordinates":[76.46174999999999,28.46681],"type":"Point"}
}