{
  "type": "Feature",
  "properties": {
    "iso:country":"IN",
    "ks:ks_name":"Pollukatta Yanadisangam",
    "ks:ks_pop":245,
    "ks:ks_type":"HABITATION",
    "name:eng_x_preferred":[
        "Pollukatta Yanadisangam"
    ],
    "wof:name":"Pollukatta Yanadisangam",
    "wof:placetype":"locality",
    "wof:population":245
},
  "geometry": {"coordinates":[80.043026,15.180348],"type":"Point"}
}