{
  "type": "Feature",
  "properties": {
    "iso:country":"IN",
    "ks:ks_name":"Pure Pilla Kori",
    "ks:ks_pop":195,
    "ks:ks_type":"HABITATION",
    "name:eng_x_preferred":[
        "Pure Pilla Kori"
    ],
    "wof:name":"Pure Pilla Kori",
    "wof:placetype":"locality",
    "wof:population":195
},
  "geometry": {"coordinates":[81.555306,26.425585],"type":"Point"}
}