{
  "type": "Feature",
  "properties": {
    "iso:country":"IN",
    "ks:ks_name":"Devtekere",
    "ks:ks_pop":59,
    "ks:ks_type":"HABITATION",
    "name:eng_x_preferred":[
        "Devtekere"
    ],
    "wof:name":"Devtekere",
    "wof:placetype":"locality",
    "wof:population":59
},
  "geometry": {"coordinates":[74.47422400000001,14.360931],"type":"Point"}
}