{
  "type": "Feature",
  "properties": {
    "gn:admin1_code":"19.0",
    "gn:admin2_code":"574.0",
    "gn:asciiname":"Pura",
    "gn:country_code":"IN",
    "gn:dem":779,
    "gn:feature_class":"P",
    "gn:feature_code":"PPL",
    "gn:name":"Pura",
    "gn:population":0,
    "gn:timezone":"Asia/Kolkata",
    "iso:country":"IN",
    "name:ceb_x_preferred":[
        "Pura"
    ],
    "name:deu_x_preferred":[
        "Pura"
    ],
    "name:epo_x_preferred":[
        "Pura"
    ],
    "name:est_x_preferred":[
        "Pura"
    ],
    "name:eus_x_preferred":[
        "Pura"
    ],
    "name:fra_x_preferred":[
        "Pura"
    ],
    "name:ita_x_preferred":[
        "Pura"
    ],
    "name:nld_x_preferred":[
        "Pura"
    ],
    "name:por_x_preferred":[
        "Pura"
    ],
    "name:rus_x_preferred":[
        "\u041f\u0443\u0440\u0430"
    ],
    "name:spa_x_preferred":[
        "Pura"
    ],
    "name:swe_x_preferred":[
        "Pura"
    ],
    "name:ukr_x_preferred":[
        "\u041f\u0443\u0440\u0430"
    ],
    "name:war_x_preferred":[
        "Pura"
    ],
    "wof:name":"Pura",
    "wof:placetype":"locality"
},
  "geometry": {"coordinates":[76.21344999999999,13.45312],"type":"Point"}
}