{
  "type": "Feature",
  "properties": {
    "iso:country":"IN",
    "ks:ks_name":"Fuskar Mukh NC",
    "ks:ks_pop":131,
    "ks:ks_type":"VILLAGE",
    "ks:ks_uagg_main":0,
    "name:eng_x_preferred":[
        "Fuskar Mukh NC"
    ],
    "wof:name":"Fuskar Mukh NC",
    "wof:placetype":"neighbourhood",
    "wof:population":131
},
  "geometry": {"coordinates":[94.34368499999999,27.232946],"type":"Point"}
}