{
  "type": "Feature",
  "properties": {
    "iso:country":"IN",
    "ks:ks_name":"Darukere",
    "ks:ks_pop":188,
    "ks:ks_type":"HABITATION",
    "name:eng_x_preferred":[
        "Darukere"
    ],
    "wof:name":"Darukere",
    "wof:placetype":"locality",
    "wof:population":188
},
  "geometry": {"coordinates":[75.921297,13.191332],"type":"Point"}
}