{
  "type": "Feature",
  "properties": {
    "iso:country":"IN",
    "ks:ks_name":"Kallapu Palli",
    "ks:ks_pop":150,
    "ks:ks_type":"HABITATION",
    "name:eng_x_preferred":[
        "Kallapu Palli"
    ],
    "wof:name":"Kallapu Palli",
    "wof:placetype":"locality",
    "wof:population":150
},
  "geometry": {"coordinates":[74.89640799999999,13.232249],"type":"Point"}
}