{
  "type": "Feature",
  "properties": {
    "iso:country":"IN",
    "ks:ks_name":"Bantrothuputtu",
    "ks:ks_pop":126,
    "ks:ks_type":"HABITATION",
    "name:eng_x_preferred":[
        "Bantrothuputtu"
    ],
    "wof:name":"Bantrothuputtu",
    "wof:placetype":"locality",
    "wof:population":126
},
  "geometry": {"coordinates":[82.54843700000001,18.134427],"type":"Point"}
}