{
  "type": "Feature",
  "properties": {
    "iso:country":"IN",
    "ks:ks_name":"Raghuvanapalya",
    "ks:ks_pop":171,
    "ks:ks_type":"VILLAGE",
    "ks:ks_uagg_main":0,
    "name:eng_x_preferred":[
        "Raghuvanapalya"
    ],
    "wof:name":"Raghuvanapalya",
    "wof:placetype":"neighbourhood",
    "wof:population":171
},
  "geometry": {"coordinates":[77.545951,12.882433],"type":"Point"}
}