{
  "type": "Feature",
  "properties": {
    "iso:country":"IN",
    "ks:ks_name":"Sukala",
    "ks:ks_pop":1663,
    "ks:ks_type":"VILLAGE",
    "ks:ks_uagg_main":0,
    "name:eng_x_preferred":[
        "Sukala"
    ],
    "wof:name":"Sukala",
    "wof:placetype":"neighbourhood",
    "wof:population":1663
},
  "geometry": {"coordinates":[86.358087,20.666569],"type":"Point"}
}