{
  "type": "Feature",
  "properties": {
    "iso:country":"IN",
    "ks:ks_name":"Akbrabad",
    "ks:ks_pop":740,
    "ks:ks_type":"VILLAGE",
    "ks:ks_uagg_main":0,
    "name:eng_x_preferred":[
        "Akbrabad"
    ],
    "wof:name":"Akbrabad",
    "wof:placetype":"locality",
    "wof:population":740
},
  "geometry": {"coordinates":[79.507132,28.769507],"type":"Point"}
}