{
  "type": "Feature",
  "properties": {
    "iso:country":"IN",
    "ks:ks_name":"Pookayam",
    "ks:ks_pop":1352,
    "ks:ks_type":"HABITATION",
    "name:eng_x_preferred":[
        "Pookayam"
    ],
    "wof:name":"Pookayam",
    "wof:placetype":"locality",
    "wof:population":1352
},
  "geometry": {"coordinates":[75.26879,12.45416],"type":"Point"}
}