{
  "type": "Feature",
  "properties": {
    "iso:country":"IN",
    "ks:ks_alt_nam":"EKDARI",
    "ks:ks_name":"Ekdari",
    "ks:ks_pop":176,
    "ks:ks_type":"HABITATION",
    "name:eng_x_preferred":[
        "Ekdari"
    ],
    "wof:name":"Ekdari",
    "wof:placetype":"locality",
    "wof:population":176
},
  "geometry": {"coordinates":[84.12372000000001,24.53327],"type":"Point"}
}