{
  "type": "Feature",
  "properties": {
    "gn:admin1_code":"34.0",
    "gn:admin2_code":"234",
    "gn:asciiname":"Karwandiya",
    "gn:country_code":"IN",
    "gn:dem":113,
    "gn:feature_class":"P",
    "gn:feature_code":"PPL",
    "gn:name":"Karwandiya",
    "gn:population":0,
    "gn:timezone":"Asia/Kolkata",
    "iso:country":"IN",
    "name:und_x_variant":[
        "Karwandia",
        "Karwandiya"
    ],
    "wof:name":"Karwandiya",
    "wof:placetype":"neighbourhood"
},
  "geometry": {"coordinates":[84.09433,24.94648],"type":"Point"}
}