{
  "type": "Feature",
  "properties": {
    "iso:country":"IN",
    "ks:ks_name":"Benum",
    "ks:ks_pop":61,
    "ks:ks_type":"VILLAGE",
    "name:eng_x_preferred":[
        "Benum"
    ],
    "wof:name":"Benum",
    "wof:placetype":"locality",
    "wof:population":61
},
  "geometry": {"coordinates":[84.817144,22.025805],"type":"Point"}
}