{
  "type": "Feature",
  "properties": {
    "iso:country":"IN",
    "ks:ks_alt_nam":"N.Mottur",
    "ks:ks_name":"N.mottur",
    "ks:ks_pop":700,
    "ks:ks_type":"HABITATION",
    "name:eng_x_preferred":[
        "N.mottur"
    ],
    "wof:name":"N.mottur",
    "wof:placetype":"locality",
    "wof:population":700
},
  "geometry": {"coordinates":[78.25837799999999,12.386027],"type":"Point"}
}