{
  "type": "Feature",
  "properties": {
    "iso:country":"IN",
    "ks:ks_alt_nam":"HATIRLEDA",
    "ks:ks_name":"Hatirleda",
    "ks:ks_pop":163,
    "ks:ks_type":"HABITATION",
    "name:eng_x_preferred":[
        "Hatirleda"
    ],
    "wof:name":"Hatirleda",
    "wof:placetype":"locality",
    "wof:population":163
},
  "geometry": {"coordinates":[91.285922,23.757435],"type":"Point"}
}