{
  "type": "Feature",
  "properties": {
    "gn:admin1_code":"39.0",
    "gn:admin2_code":"63.0",
    "gn:asciiname":"Simali",
    "gn:country_code":"IN",
    "gn:dem":1215,
    "gn:feature_class":"P",
    "gn:feature_code":"PPL",
    "gn:name":"S\u012bm\u0101li",
    "gn:population":0,
    "gn:timezone":"Asia/Kolkata",
    "iso:country":"IN",
    "ks:ks_alt_nam":"S\u012bm\u0101li",
    "ks:ks_name":"Simali",
    "ks:ks_type":"VILLAGE",
    "name:eng_x_preferred":[
        "Simali"
    ],
    "name:eng_x_variant":[
        "S\u012bm\u0101li"
    ],
    "wof:name":"Simali",
    "wof:placetype":"locality"
},
  "geometry": {"coordinates":[79.993762,29.781644],"type":"Point"}
}