{
  "type": "Feature",
  "properties": {
    "iso:country":"IN",
    "ks:ks_name":"Gobinddih",
    "ks:ks_pop":180,
    "ks:ks_type":"VILLAGE",
    "name:eng_x_preferred":[
        "Gobinddih"
    ],
    "wof:name":"Gobinddih",
    "wof:placetype":"locality",
    "wof:population":180
},
  "geometry": {"coordinates":[86.467311,24.162595],"type":"Point"}
}