{
  "type": "Feature",
  "properties": {
    "iso:country":"IN",
    "ks:ks_name":"Mashanzurwa",
    "ks:ks_pop":60,
    "ks:ks_type":"HABITATION",
    "name:eng_x_preferred":[
        "Mashanzurwa"
    ],
    "wof:name":"Mashanzurwa",
    "wof:placetype":"locality",
    "wof:population":60
},
  "geometry": {"coordinates":[80.23873500000001,21.031478],"type":"Point"}
}