{
  "type": "Feature",
  "properties": {
    "iso:country":"IN",
    "ks:ks_name":"Guddeangady",
    "ks:ks_pop":935,
    "ks:ks_type":"HABITATION",
    "name:eng_x_preferred":[
        "Guddeangady"
    ],
    "wof:name":"Guddeangady",
    "wof:placetype":"locality",
    "wof:population":935
},
  "geometry": {"coordinates":[74.85915300000001,13.465805],"type":"Point"}
}