{
  "type": "Feature",
  "properties": {
    "iso:country":"IN",
    "ks:ks_name":"Ujanu",
    "ks:ks_pop":650,
    "ks:ks_type":"VILLAGE",
    "ks:ks_uagg_main":0,
    "name:eng_x_preferred":[
        "Ujanu"
    ],
    "wof:name":"Ujanu",
    "wof:placetype":"neighbourhood",
    "wof:population":650
},
  "geometry": {"coordinates":[88.40292599999999,26.734292],"type":"Point"}
}