{
  "type": "Feature",
  "properties": {
    "gn:admin1_code":"34.0",
    "gn:admin2_code":"229.0",
    "gn:asciiname":"Bheditola",
    "gn:country_code":"IN",
    "gn:dem":69,
    "gn:feature_class":"P",
    "gn:feature_code":"PPL",
    "gn:name":"Bheditola",
    "gn:population":0,
    "gn:timezone":"Asia/Kolkata",
    "iso:country":"IN",
    "wof:name":"Bheditola",
    "wof:placetype":"locality"
},
  "geometry": {"coordinates":[85.59093,25.06132],"type":"Point"}
}