{
  "type": "Feature",
  "properties": {
    "iso:country":"IN",
    "ks:ks_name":"Mathutoli",
    "ks:ks_pop":100,
    "ks:ks_type":"HABITATION",
    "name:eng_x_preferred":[
        "Mathutoli"
    ],
    "wof:name":"Mathutoli",
    "wof:placetype":"locality",
    "wof:population":100
},
  "geometry": {"coordinates":[84.903645,22.722942],"type":"Point"}
}