{
  "type": "Feature",
  "properties": {
    "iso:country":"IN",
    "ks:ks_name":"Pottalpatcheri",
    "ks:ks_pop":406,
    "ks:ks_type":"HABITATION",
    "name:eng_x_preferred":[
        "Pottalpatcheri"
    ],
    "wof:name":"Pottalpatcheri",
    "wof:placetype":"locality",
    "wof:population":406
},
  "geometry": {"coordinates":[78.620898,9.249966],"type":"Point"}
}