{
  "type": "Feature",
  "properties": {
    "iso:country":"IN",
    "ks:ks_name":"Dakkhin Gaon Mau",
    "ks:ks_pop":2572,
    "ks:ks_type":"VILLAGE",
    "name:eng_x_preferred":[
        "Dakkhin Gaon Mau"
    ],
    "wof:name":"Dakkhin Gaon Mau",
    "wof:placetype":"locality",
    "wof:population":2572
},
  "geometry": {"coordinates":[81.63063,26.416257],"type":"Point"}
}