{
  "type": "Feature",
  "properties": {
    "iso:country":"IN",
    "ks:ks_name":"Pullanginerudulova",
    "ks:ks_pop":158,
    "ks:ks_type":"VILLAGE",
    "name:eng_x_preferred":[
        "Pullanginerudulova"
    ],
    "wof:name":"Pullanginerudulova",
    "wof:placetype":"locality",
    "wof:population":158
},
  "geometry": {"coordinates":[84.225882,18.724866],"type":"Point"}
}