{
  "type": "Feature",
  "properties": {
    "gn:admin1_code":"36.0",
    "gn:admin2_code":"163.0",
    "gn:asciiname":"Nawada Kachhwain",
    "gn:country_code":"IN",
    "gn:dem":139,
    "gn:feature_class":"P",
    "gn:feature_code":"PPL",
    "gn:name":"Naw\u0101da Kachhw\u0101in",
    "gn:population":0,
    "gn:timezone":"Asia/Kolkata",
    "iso:country":"IN",
    "wof:name":"Nawada Kachhwain",
    "wof:placetype":"locality"
},
  "geometry": {"coordinates":[79.79378,26.71548],"type":"Point"}
}