{
  "type": "Feature",
  "properties": {
    "iso:country":"IN",
    "ks:ks_name":"Pater",
    "ks:ks_pop":47,
    "ks:ks_type":"VILLAGE",
    "name:eng_x_preferred":[
        "Pater"
    ],
    "wof:name":"Pater",
    "wof:placetype":"locality",
    "wof:population":47
},
  "geometry": {"coordinates":[78.320567,30.169659],"type":"Point"}
}