{
  "type": "Feature",
  "properties": {
    "iso:country":"IN",
    "ks:ks_name":"Musari Kudar",
    "ks:ks_pop":248,
    "ks:ks_type":"VILLAGE",
    "name:eng_x_preferred":[
        "Musari Kudar"
    ],
    "wof:name":"Musari Kudar",
    "wof:placetype":"locality",
    "wof:population":248
},
  "geometry": {"coordinates":[86.113809,22.843397],"type":"Point"}
}