{
  "type": "Feature",
  "properties": {
    "iso:country":"IN",
    "ks:ks_alt_nam":"BAIHRADIH",
    "ks:ks_name":"Baihradih",
    "ks:ks_pop":380,
    "ks:ks_type":"HABITATION",
    "name:eng_x_preferred":[
        "Baihradih"
    ],
    "wof:name":"Baihradih",
    "wof:placetype":"locality",
    "wof:population":380
},
  "geometry": {"coordinates":[84.982748,24.616819],"type":"Point"}
}