{
  "type": "Feature",
  "properties": {
    "iso:country":"IN",
    "ks:ks_alt_nam":"Dhan Ch.Uchoi Para",
    "ks:ks_name":"Dhan Ch.uchoi Para",
    "ks:ks_pop":381,
    "ks:ks_type":"HABITATION",
    "name:eng_x_preferred":[
        "Dhan Ch.uchoi Para"
    ],
    "wof:name":"Dhan Ch.uchoi Para",
    "wof:placetype":"locality",
    "wof:population":381
},
  "geometry": {"coordinates":[91.738364,23.385364],"type":"Point"}
}