{
  "type": "Feature",
  "properties": {
    "gn:admin1_code":"24.0",
    "gn:admin2_code":"107.0",
    "gn:asciiname":"Bas",
    "gn:country_code":"IN",
    "gn:dem":262,
    "gn:feature_class":"P",
    "gn:feature_code":"PPL",
    "gn:name":"B\u0101s",
    "gn:population":0,
    "gn:timezone":"Asia/Kolkata",
    "iso:country":"IN",
    "name:bel_x_preferred":[
        "\u0411\u0430\u0441"
    ],
    "name:bos_x_preferred":[
        "Bas"
    ],
    "name:bul_x_preferred":[
        "\u0411\u0430\u0441"
    ],
    "name:cat_x_preferred":[
        "Bas"
    ],
    "name:ceb_x_preferred":[
        "Bas"
    ],
    "name:dan_x_preferred":[
        "Bas"
    ],
    "name:deu_x_preferred":[
        "Bas"
    ],
    "name:hrv_x_preferred":[
        "Bas"
    ],
    "name:jpn_x_preferred":[
        "\u30d9\u30fc\u30b9"
    ],
    "name:nld_x_preferred":[
        "Bas"
    ],
    "name:pol_x_preferred":[
        "Bas"
    ],
    "name:por_x_preferred":[
        "Bas"
    ],
    "name:ron_x_preferred":[
        "Bas"
    ],
    "name:slk_x_preferred":[
        "Bas"
    ],
    "name:slv_x_preferred":[
        "Bas"
    ],
    "name:swe_x_preferred":[
        "Bas"
    ],
    "name:tur_x_preferred":[
        "Bas"
    ],
    "wof:name":"Bas",
    "wof:placetype":"locality"
},
  "geometry": {"coordinates":[76.64775999999998,26.64137],"type":"Point"}
}