{
  "type": "Feature",
  "properties": {
    "iso:country":"IN",
    "ks:ks_name":"Jagahat",
    "ks:ks_pop":93,
    "ks:ks_type":"VILLAGE",
    "name:eng_x_preferred":[
        "Jagahat"
    ],
    "wof:name":"Jagahat",
    "wof:placetype":"locality",
    "wof:population":93
},
  "geometry": {"coordinates":[81.984032,24.805312],"type":"Point"}
}