{
  "type": "Feature",
  "properties": {
    "gn:admin1_code":"36",
    "gn:admin2_code":"147.0",
    "gn:asciiname":"Duri",
    "gn:country_code":"IN",
    "gn:dem":169,
    "gn:feature_class":"P",
    "gn:feature_code":"PPL",
    "gn:name":"Duri",
    "gn:population":0,
    "gn:timezone":"Asia/Kolkata",
    "iso:country":"IN",
    "name:ceb_x_preferred":[
        "Duri"
    ],
    "name:deu_x_preferred":[
        "Duri"
    ],
    "name:ind_x_preferred":[
        "Duri"
    ],
    "name:ita_x_preferred":[
        "Duri"
    ],
    "name:kor_x_preferred":[
        "\ub450\ub9ac"
    ],
    "name:swe_x_preferred":[
        "Duri"
    ],
    "wof:name":"Duri",
    "wof:placetype":"locality"
},
  "geometry": {"coordinates":[78.5916,27.30887],"type":"Point"}
}