{
  "type": "Feature",
  "properties": {
    "gn:admin1_code":"35.0",
    "gn:admin2_code":"457.0",
    "gn:asciiname":"Serpar",
    "gn:country_code":"IN",
    "gn:dem":582,
    "gn:feature_class":"P",
    "gn:feature_code":"PPL",
    "gn:name":"Serp\u0101r",
    "gn:population":0,
    "gn:timezone":"Asia/Kolkata",
    "iso:country":"IN",
    "ks:ks_alt_nam":"Serp\u0101r",
    "ks:ks_name":"Serpar",
    "ks:ks_pop":405,
    "ks:ks_type":"VILLAGE",
    "name:eng_x_preferred":[
        "Serpar"
    ],
    "name:eng_x_variant":[
        "Serp\u0101r"
    ],
    "wof:name":"Serpar",
    "wof:placetype":"locality",
    "wof:population":405
},
  "geometry": {"coordinates":[80.74787999999999,21.92119],"type":"Point"}
}