{
  "type": "Feature",
  "properties": {
    "gn:admin1_code":"37",
    "gn:admin2_code":"406.0",
    "gn:asciiname":"Kaya",
    "gn:country_code":"IN",
    "gn:dem":265,
    "gn:feature_class":"P",
    "gn:feature_code":"PPL",
    "gn:name":"Kaya",
    "gn:population":0,
    "gn:timezone":"Asia/Kolkata",
    "iso:country":"IN",
    "wof:name":"Kaya",
    "wof:placetype":"locality"
},
  "geometry": {"coordinates":[82.14435999999998,21.93832],"type":"Point"}
}