{
  "type": "Feature",
  "properties": {
    "iso:country":"IN",
    "ks:ks_name":"Kumhadi",
    "ks:ks_pop":0,
    "ks:ks_type":"VILLAGE",
    "name:eng_x_preferred":[
        "Kumhadi"
    ],
    "wof:name":"Kumhadi",
    "wof:placetype":"locality",
    "wof:population":0
},
  "geometry": {"coordinates":[78.866421,23.03148],"type":"Point"}
}