{
  "type": "Feature",
  "properties": {
    "iso:country":"IN",
    "ks:ks_name":"Bagichatoli",
    "ks:ks_pop":612,
    "ks:ks_type":"HABITATION",
    "name:eng_x_preferred":[
        "Bagichatoli"
    ],
    "wof:name":"Bagichatoli",
    "wof:placetype":"locality",
    "wof:population":612
},
  "geometry": {"coordinates":[85.08394199999999,23.362469],"type":"Point"}
}