{
  "type": "Feature",
  "properties": {
    "iso:country":"IN",
    "ks:ks_name":"Putimari",
    "ks:ks_pop":0,
    "ks:ks_type":"VILLAGE",
    "name:eng_x_preferred":[
        "Putimari"
    ],
    "wof:name":"Putimari",
    "wof:placetype":"locality",
    "wof:population":0
},
  "geometry": {"coordinates":[88.137417,24.271639],"type":"Point"}
}