{
  "type": "Feature",
  "properties": {
    "iso:country":"IN",
    "ks:ks_name":"Baliari",
    "ks:ks_pop":39,
    "ks:ks_type":"VILLAGE",
    "name:eng_x_preferred":[
        "Baliari"
    ],
    "wof:name":"Baliari",
    "wof:placetype":"locality",
    "wof:population":39
},
  "geometry": {"coordinates":[86.254746,24.562876],"type":"Point"}
}