{
  "type": "Feature",
  "properties": {
    "gn:admin1_code":"11.0",
    "gn:admin2_code":"33.0",
    "gn:asciiname":"Chul",
    "gn:country_code":"IN",
    "gn:dem":2332,
    "gn:feature_class":"P",
    "gn:feature_code":"PPL",
    "gn:name":"Ch\u016bl",
    "gn:population":0,
    "gn:timezone":"Asia/Kolkata",
    "iso:country":"IN",
    "wof:name":"Chul",
    "wof:placetype":"locality"
},
  "geometry": {"coordinates":[77.55815,31.17221],"type":"Point"}
}