{
  "type": "Feature",
  "properties": {
    "iso:country":"IN",
    "ks:ks_alt_nam":"vatsaala nagar",
    "ks:ks_name":"Vatsaala Nagar",
    "ks:ks_pop":206,
    "ks:ks_type":"HABITATION",
    "ks:ks_uagg_main":0,
    "name:eng_x_preferred":[
        "Vatsaala Nagar"
    ],
    "wof:name":"Vatsaala Nagar",
    "wof:placetype":"neighbourhood",
    "wof:population":206
},
  "geometry": {"coordinates":[76.232096,17.819054],"type":"Point"}
}