{
  "type": "Feature",
  "properties": {
    "gn:admin1_code":"2",
    "gn:admin2_code":"544.0",
    "gn:asciiname":"Godda",
    "gn:country_code":"IN",
    "gn:dem":1206,
    "gn:feature_class":"P",
    "gn:feature_code":"PPL",
    "gn:name":"Godda",
    "gn:population":0,
    "gn:timezone":"Asia/Kolkata",
    "iso:country":"IN",
    "name:bih_x_preferred":[
        "\u0917\u094b\u0921\u094d\u0921\u093e"
    ],
    "name:bpy_x_preferred":[
        "\u0997\u09cb\u09a6\u09cd\u09a6\u09be"
    ],
    "name:ceb_x_preferred":[
        "Godd\u0101"
    ],
    "name:fra_x_preferred":[
        "Godda"
    ],
    "name:guj_x_preferred":[
        "\u0a97\u0acb\u0aa1\u0acd\u0aa1\u0abe"
    ],
    "name:hin_x_preferred":[
        "\u0917\u094b\u0921\u094d\u0921\u093e"
    ],
    "name:ita_x_preferred":[
        "Godda"
    ],
    "name:mar_x_preferred":[
        "\u0917\u094b\u0921\u094d\u0921\u093e"
    ],
    "name:mlg_x_preferred":[
        "Godda"
    ],
    "name:msa_x_preferred":[
        "Godda"
    ],
    "name:new_x_preferred":[
        "\u0917\u094b\u0921\u094d\u0921\u093e"
    ],
    "name:rus_x_preferred":[
        "\u0413\u043e\u0434\u0434\u0430"
    ],
    "name:san_x_preferred":[
        "\u0917\u094b\u0921\u094d\u0921\u093e"
    ],
    "name:spa_x_preferred":[
        "Godda"
    ],
    "name:urd_x_preferred":[
        "\u06af\u0688\u0627"
    ],
    "name:vie_x_preferred":[
        "Godda"
    ],
    "name:zho_x_preferred":[
        "\u6208\u5fb7\u8fbe"
    ],
    "wof:name":"Godda",
    "wof:placetype":"locality"
},
  "geometry": {"coordinates":[82.56831,17.94494],"type":"Point"}
}