{
  "type": "Feature",
  "properties": {
    "iso:country":"IN",
    "ks:ks_name":"Dundi",
    "ks:ks_pop":365,
    "ks:ks_type":"VILLAGE",
    "name:eng_x_preferred":[
        "Dundi"
    ],
    "wof:name":"Dundi",
    "wof:placetype":"locality",
    "wof:population":365
},
  "geometry": {"coordinates":[85.220676,24.299708],"type":"Point"}
}