{
  "type": "Feature",
  "properties": {
    "gn:admin1_code":"34.0",
    "gn:admin2_code":"229.0",
    "gn:asciiname":"Lachhmipur",
    "gn:country_code":"IN",
    "gn:dem":74,
    "gn:feature_class":"P",
    "gn:feature_code":"PPL",
    "gn:name":"Lachhmipur",
    "gn:population":0,
    "gn:timezone":"Asia/Kolkata",
    "iso:country":"IN",
    "ks:ks_name":"Lachhmipur",
    "ks:ks_pop":147,
    "ks:ks_type":"VILLAGE",
    "name:eng_x_preferred":[
        "Lachhmipur"
    ],
    "wof:name":"Lachhmipur",
    "wof:placetype":"locality",
    "wof:population":147
},
  "geometry": {"coordinates":[85.49475700000001,25.044703],"type":"Point"}
}