{
  "type": "Feature",
  "properties": {
    "iso:country":"IN",
    "ks:ks_name":"Tilangpur",
    "ks:ks_pop":126,
    "ks:ks_type":"HABITATION",
    "name:eng_x_preferred":[
        "Tilangpur"
    ],
    "wof:name":"Tilangpur",
    "wof:placetype":"locality",
    "wof:population":126
},
  "geometry": {"coordinates":[80.13702600000001,25.1751],"type":"Point"}
}