{
  "type": "Feature",
  "properties": {
    "gn:admin1_code":"2.0",
    "gn:admin2_code":"551.0",
    "gn:asciiname":"Pondaluruvenkatampalli",
    "gn:country_code":"IN",
    "gn:dem":130,
    "gn:feature_class":"P",
    "gn:feature_code":"PPL",
    "gn:name":"Pondal\u016bruvenkatampalli",
    "gn:population":0,
    "gn:timezone":"Asia/Kolkata",
    "iso:country":"IN",
    "wof:name":"Pondaluruvenkatampalli",
    "wof:placetype":"locality"
},
  "geometry": {"coordinates":[79.15603,14.21224],"type":"Point"}
}