{
  "type": "Feature",
  "properties": {
    "iso:country":"IN",
    "ks:ks_name":"Thakurkhera",
    "ks:ks_pop":539,
    "ks:ks_type":"VILLAGE",
    "ks:ks_uagg_main":0,
    "name:eng_x_preferred":[
        "Thakurkhera"
    ],
    "wof:name":"Thakurkhera",
    "wof:placetype":"neighbourhood",
    "wof:population":539
},
  "geometry": {"coordinates":[80.692071,26.439658],"type":"Point"}
}