{
  "type": "Feature",
  "properties": {
    "gn:admin1_code":"19.0",
    "gn:admin2_code":"574.0",
    "gn:asciiname":"Kitgere",
    "gn:country_code":"IN",
    "gn:dem":910,
    "gn:feature_class":"P",
    "gn:feature_code":"PPL",
    "gn:name":"Kitgere",
    "gn:population":0,
    "gn:timezone":"Asia/Kolkata",
    "iso:country":"IN",
    "ks:ks_name":"Kitgere",
    "ks:ks_type":"VILLAGE",
    "name:eng_x_preferred":[
        "Kitgere"
    ],
    "wof:name":"Kitgere",
    "wof:placetype":"locality"
},
  "geometry": {"coordinates":[75.83784199999999,12.860376],"type":"Point"}
}