{
  "type": "Feature",
  "properties": {
    "iso:country":"IN",
    "ks:ks_name":"Tulopara",
    "ks:ks_pop":379,
    "ks:ks_type":"HABITATION",
    "name:eng_x_preferred":[
        "Tulopara"
    ],
    "wof:name":"Tulopara",
    "wof:placetype":"locality",
    "wof:population":379
},
  "geometry": {"coordinates":[91.108282,26.009918],"type":"Point"}
}