{
  "type": "Feature",
  "properties": {
    "iso:country":"IN",
    "ks:ks_alt_nam":"N\u0101r\u0101inpur",
    "ks:ks_name":"Narainpur",
    "ks:ks_pop":583,
    "ks:ks_type":"VILLAGE",
    "name:eng_x_preferred":[
        "Narainpur"
    ],
    "name:eng_x_variant":[
        "N\u0101r\u0101inpur"
    ],
    "wof:name":"Narainpur",
    "wof:placetype":"locality",
    "wof:population":583
},
  "geometry": {"coordinates":[86.24717200000001,24.548844],"type":"Point"}
}