{
  "type": "Feature",
  "properties": {
    "gn:admin1_code":"36",
    "gn:admin2_code":"188.0",
    "gn:asciiname":"Akbarabad",
    "gn:country_code":"IN",
    "gn:dem":77,
    "gn:feature_class":"P",
    "gn:feature_code":"PPL",
    "gn:name":"Akbar\u0101b\u0101d",
    "gn:population":0,
    "gn:timezone":"Asia/Kolkata",
    "iso:country":"IN",
    "wof:name":"Akbarabad",
    "wof:placetype":"locality"
},
  "geometry": {"coordinates":[83.42525999999999,26.34181],"type":"Point"}
}