{
  "type": "Feature",
  "properties": {
    "gn:admin1_code":"36",
    "gn:admin2_code":"188.0",
    "gn:asciiname":"Akbarabad",
    "gn:country_code":"IN",
    "gn:dem":77,
    "gn:feature_class":"P",
    "gn:feature_code":"PPL",
    "gn:name":"Akbar\u0101b\u0101d",
    "gn:population":0,
    "gn:timezone":"Asia/Kolkata",
    "iso:country":"IN",
    "name:ara_x_preferred":[
        "\u0623\u06a9\u0628\u0631 \u0623\u0628\u0627\u062f"
    ],
    "name:fas_x_preferred":[
        "\u0627\u06a9\u0628\u0631\u0622\u0628\u0627\u062f"
    ],
    "name:ron_x_preferred":[
        "Akbarabad"
    ],
    "wof:name":"Akbarabad",
    "wof:placetype":"locality"
},
  "geometry": {"coordinates":[83.42525999999999,26.34181],"type":"Point"}
}