{
  "type": "Feature",
  "properties": {
    "gn:admin1_code":"35",
    "gn:admin2_code":"435.0",
    "gn:asciiname":"Simlaoda",
    "gn:country_code":"IN",
    "gn:dem":488,
    "gn:feature_class":"P",
    "gn:feature_code":"PPL",
    "gn:name":"Simlaoda",
    "gn:population":0,
    "gn:timezone":"Asia/Kolkata",
    "iso:country":"IN",
    "wof:name":"Simlaoda",
    "wof:placetype":"locality"
},
  "geometry": {"coordinates":[75.41861,23.17442],"type":"Point"}
}