{
  "type": "Feature",
  "properties": {
    "iso:country":"IN",
    "ks:ks_name":"Tagakia",
    "ks:ks_pop":167,
    "ks:ks_type":"VILLAGE",
    "name:eng_x_preferred":[
        "Tagakia"
    ],
    "wof:name":"Tagakia",
    "wof:placetype":"locality",
    "wof:population":167
},
  "geometry": {"coordinates":[83.84238499999999,20.287049],"type":"Point"}
}