{
  "type": "Feature",
  "properties": {
    "iso:country":"IN",
    "ks:ks_name":"Kanive",
    "ks:ks_pop":60,
    "ks:ks_type":"HABITATION",
    "name:eng_x_preferred":[
        "Kanive"
    ],
    "wof:name":"Kanive",
    "wof:placetype":"locality",
    "wof:population":60
},
  "geometry": {"coordinates":[77.258623,12.556655],"type":"Point"}
}