{
  "type": "Feature",
  "properties": {
    "gn:admin1_code":"12.0",
    "gn:asciiname":"Ghikot",
    "gn:country_code":"IN",
    "gn:dem":2256,
    "gn:feature_class":"P",
    "gn:feature_code":"PPL",
    "gn:name":"Gh\u012bkot",
    "gn:population":0,
    "gn:timezone":"Asia/Kolkata",
    "iso:country":"IN",
    "wof:name":"Ghikot",
    "wof:placetype":"locality"
},
  "geometry": {"coordinates":[73.97967,34.01585],"type":"Point"}
}