{
  "type": "Feature",
  "properties": {
    "iso:country":"IN",
    "ks:ks_name":"Kunnumpuram Colony",
    "ks:ks_pop":415,
    "ks:ks_type":"HABITATION",
    "name:eng_x_preferred":[
        "Kunnumpuram Colony"
    ],
    "wof:name":"Kunnumpuram Colony",
    "wof:placetype":"locality",
    "wof:population":415
},
  "geometry": {"coordinates":[76.835868,8.907637],"type":"Point"}
}