{
  "type": "Feature",
  "properties": {
    "iso:country":"IN",
    "ks:ks_alt_nam":"HaleKangod",
    "ks:ks_name":"Halekangod",
    "ks:ks_pop":76,
    "ks:ks_type":"HABITATION",
    "name:eng_x_preferred":[
        "Halekangod"
    ],
    "wof:name":"Halekangod",
    "wof:placetype":"locality",
    "wof:population":76
},
  "geometry": {"coordinates":[74.83095,14.565208],"type":"Point"}
}