{
  "type": "Feature",
  "properties": {
    "iso:country":"IN",
    "ks:ks_name":"Kashitanr",
    "ks:ks_pop":749,
    "ks:ks_type":"HABITATION",
    "name:eng_x_preferred":[
        "Kashitanr"
    ],
    "wof:name":"Kashitanr",
    "wof:placetype":"locality",
    "wof:population":749
},
  "geometry": {"coordinates":[86.543307,23.888097],"type":"Point"}
}