{
  "type": "Feature",
  "properties": {
    "iso:country":"IN",
    "ks:ks_name":"Anjan Mal",
    "ks:ks_pop":520,
    "ks:ks_type":"VILLAGE",
    "name:eng_x_preferred":[
        "Anjan Mal"
    ],
    "wof:name":"Anjan Mal",
    "wof:placetype":"locality",
    "wof:population":520
},
  "geometry": {"coordinates":[74.897267,22.563921],"type":"Point"}
}