{
  "type": "Feature",
  "properties": {
    "iso:country":"IN",
    "ks:ks_name":"Chikirakatolakala",
    "ks:ks_pop":250,
    "ks:ks_type":"HABITATION",
    "name:eng_x_preferred":[
        "Chikirakatolakala"
    ],
    "wof:name":"Chikirakatolakala",
    "wof:placetype":"locality",
    "wof:population":250
},
  "geometry": {"coordinates":[81.780472,24.769649],"type":"Point"}
}