{
  "type": "Feature",
  "properties": {
    "iso:country":"IN",
    "ks:ks_name":"Baneriya Khurd",
    "ks:ks_pop":1311,
    "ks:ks_type":"VILLAGE",
    "name:eng_x_preferred":[
        "Baneriya Khurd"
    ],
    "wof:name":"Baneriya Khurd",
    "wof:placetype":"locality",
    "wof:population":1311
},
  "geometry": {"coordinates":[75.364729,25.900985],"type":"Point"}
}