{
  "type": "Feature",
  "properties": {
    "gn:admin1_code":"19.0",
    "gn:admin2_code":"569.0",
    "gn:asciiname":"Paladka",
    "gn:country_code":"IN",
    "gn:dem":76,
    "gn:feature_class":"P",
    "gn:feature_code":"PPLL",
    "gn:name":"P\u0101ladka",
    "gn:population":0,
    "gn:timezone":"Asia/Kolkata",
    "iso:country":"IN",
    "ks:ks_alt_nam":"P\u0101ladka",
    "ks:ks_name":"Paladka",
    "ks:ks_pop":248,
    "ks:ks_type":"VILLAGE",
    "name:eng_x_preferred":[
        "Paladka"
    ],
    "name:eng_x_variant":[
        "P\u0101ladka"
    ],
    "wof:name":"Paladka",
    "wof:placetype":"locality",
    "wof:population":248
},
  "geometry": {"coordinates":[74.93921400000001,13.113347],"type":"Point"}
}