{
  "type": "Feature",
  "properties": {
    "iso:country":"IN",
    "ks:ks_name":"Sadewadi",
    "ks:ks_pop":279,
    "ks:ks_type":"HABITATION",
    "name:eng_x_preferred":[
        "Sadewadi"
    ],
    "wof:name":"Sadewadi",
    "wof:placetype":"locality",
    "wof:population":279
},
  "geometry": {"coordinates":[73.44194400000001,17.283056],"type":"Point"}
}