{
  "type": "Feature",
  "properties": {
    "gn:admin1_code":"19.0",
    "gn:admin2_code":"571.0",
    "gn:asciiname":"Edigarpalya",
    "gn:country_code":"IN",
    "gn:dem":804,
    "gn:feature_class":"P",
    "gn:feature_code":"PPL",
    "gn:name":"Edigarp\u0101lya",
    "gn:population":0,
    "gn:timezone":"Asia/Kolkata",
    "iso:country":"IN",
    "ks:ks_name":"Edigarapalya",
    "ks:ks_pop":80,
    "ks:ks_type":"HABITATION",
    "name:eng_x_preferred":[
        "Edigarapalya"
    ],
    "name:eng_x_variant":[
        "Edigarpalya"
    ],
    "wof:name":"Edigarapalya",
    "wof:placetype":"locality",
    "wof:population":80
},
  "geometry": {"coordinates":[77.091093,12.982808],"type":"Point"}
}