{
  "type": "Feature",
  "properties": {
    "iso:country":"IN",
    "ks:ks_name":"Hattipada",
    "ks:ks_pop":526,
    "ks:ks_type":"HABITATION",
    "name:eng_x_preferred":[
        "Hattipada"
    ],
    "wof:name":"Hattipada",
    "wof:placetype":"locality",
    "wof:population":526
},
  "geometry": {"coordinates":[72.94615,19.493184],"type":"Point"}
}