{
  "type": "Feature",
  "properties": {
    "iso:country":"IN",
    "ks:ks_name":"Bhakta Mohan",
    "ks:ks_pop":158,
    "ks:ks_type":"HABITATION",
    "name:eng_x_preferred":[
        "Bhakta Mohan"
    ],
    "wof:name":"Bhakta Mohan",
    "wof:placetype":"locality",
    "wof:population":158
},
  "geometry": {"coordinates":[91.658676,23.70528],"type":"Point"}
}