{
  "type": "Feature",
  "properties": {
    "gn:admin1_code":"19.0",
    "gn:admin2_code":"570.0",
    "gn:asciiname":"Hogarekhangiri",
    "gn:country_code":"IN",
    "gn:dem":1263,
    "gn:feature_class":"P",
    "gn:feature_code":"PPL",
    "gn:name":"Hogarekh\u0101ngiri",
    "gn:population":0,
    "gn:timezone":"Asia/Kolkata",
    "iso:country":"IN",
    "ks:ks_name":"Hogarekhangiri",
    "ks:ks_pop":1457,
    "ks:ks_type":"HABITATION",
    "name:eng_x_preferred":[
        "Hogarekhangiri"
    ],
    "wof:name":"Hogarekhangiri",
    "wof:placetype":"locality",
    "wof:population":1457
},
  "geometry": {"coordinates":[75.873374,13.544396],"type":"Point"}
}