{
  "type": "Feature",
  "properties": {
    "gn:admin1_code":"19.0",
    "gn:admin2_code":"570.0",
    "gn:asciiname":"Hogarekhangiri",
    "gn:country_code":"IN",
    "gn:dem":1263,
    "gn:feature_class":"P",
    "gn:feature_code":"PPL",
    "gn:name":"Hogarekh\u0101ngiri",
    "gn:population":0,
    "gn:timezone":"Asia/Kolkata",
    "iso:country":"IN",
    "wof:name":"Hogarekhangiri",
    "wof:placetype":"locality"
},
  "geometry": {"coordinates":[75.87451999999998,13.54344],"type":"Point"}
}