{
  "type": "Feature",
  "properties": {
    "iso:country":"IN",
    "ks:ks_name":"12 MLD-B",
    "ks:ks_pop":173,
    "ks:ks_type":"VILLAGE",
    "name:eng_x_preferred":[
        "12 MLD-B"
    ],
    "wof:name":"12 MLD-B",
    "wof:placetype":"locality",
    "wof:population":173
},
  "geometry": {"coordinates":[72.982274,28.919038],"type":"Point"}
}