{
  "type": "Feature",
  "properties": {
    "iso:country":"IN",
    "ks:ks_name":"Palahur",
    "ks:ks_pop":114,
    "ks:ks_type":"HABITATION",
    "name:eng_x_preferred":[
        "Palahur"
    ],
    "wof:name":"Palahur",
    "wof:placetype":"locality",
    "wof:population":114
},
  "geometry": {"coordinates":[80.88478600000001,19.430216],"type":"Point"}
}