{
  "type": "Feature",
  "properties": {
    "iso:country":"IN",
    "ks:ks_name":"Ghigharukot",
    "ks:ks_pop":94,
    "ks:ks_type":"VILLAGE",
    "name:eng_x_preferred":[
        "Ghigharukot"
    ],
    "wof:name":"Ghigharukot",
    "wof:placetype":"locality",
    "wof:population":94
},
  "geometry": {"coordinates":[79.91409299999999,29.421365],"type":"Point"}
}