{
  "type": "Feature",
  "properties": {
    "gn:admin1_code":"21.0",
    "gn:admin2_code":"396.0",
    "gn:asciiname":"Kumbhabhata",
    "gn:country_code":"IN",
    "gn:dem":502,
    "gn:feature_class":"P",
    "gn:feature_code":"PPL",
    "gn:name":"Kumbh\u0101bhata",
    "gn:population":0,
    "gn:timezone":"Asia/Kolkata",
    "iso:country":"IN",
    "wof:name":"Kumbhabhata",
    "wof:placetype":"locality"
},
  "geometry": {"coordinates":[83.30476,19.29981],"type":"Point"}
}