{
  "type": "Feature",
  "properties": {
    "gn:admin1_code":"24.0",
    "gn:admin2_code":"127.0",
    "gn:asciiname":"Ganesh Khera",
    "gn:country_code":"IN",
    "gn:dem":230,
    "gn:feature_class":"P",
    "gn:feature_code":"PPL",
    "gn:name":"Ganesh Khera",
    "gn:population":0,
    "gn:timezone":"Asia/Kolkata",
    "iso:country":"IN",
    "wof:name":"Ganesh Khera",
    "wof:placetype":"locality"
},
  "geometry": {"coordinates":[76.4897,25.48872],"type":"Point"}
}