{
  "type": "Feature",
  "properties": {
    "iso:country":"IN",
    "ks:ks_name":"Angar Berya",
    "ks:ks_pop":902,
    "ks:ks_type":"VILLAGE",
    "ks:ks_uagg_main":0,
    "name:eng_x_preferred":[
        "Angar Berya"
    ],
    "wof:name":"Angar Berya",
    "wof:placetype":"neighbourhood",
    "wof:population":902
},
  "geometry": {"coordinates":[87.72247400000001,21.992043],"type":"Point"}
}