{
  "type": "Feature",
  "properties": {
    "iso:country":"IN",
    "ks:ks_name":"Darkhaspalle",
    "ks:ks_pop":47,
    "ks:ks_type":"HABITATION",
    "name:eng_x_preferred":[
        "Darkhaspalle"
    ],
    "wof:name":"Darkhaspalle",
    "wof:placetype":"locality",
    "wof:population":47
},
  "geometry": {"coordinates":[78.031437,17.820116],"type":"Point"}
}