{
  "type": "Feature",
  "properties": {
    "iso:country":"IN",
    "ks:ks_name":"Jankapur",
    "ks:ks_pop":476,
    "ks:ks_type":"VILLAGE",
    "name:eng_x_preferred":[
        "Jankapur"
    ],
    "wof:name":"Jankapur",
    "wof:placetype":"locality",
    "wof:population":476
},
  "geometry": {"coordinates":[79.86878400000001,20.286836],"type":"Point"}
}