{
  "type": "Feature",
  "properties": {
    "iso:country":"IN",
    "ks:ks_name":"Amguri II",
    "ks:ks_pop":1114,
    "ks:ks_type":"VILLAGE",
    "name:eng_x_preferred":[
        "Amguri II"
    ],
    "wof:name":"Amguri II",
    "wof:placetype":"locality",
    "wof:population":1114
},
  "geometry": {"coordinates":[90.446326,26.496356],"type":"Point"}
}