{
  "type": "Feature",
  "properties": {
    "iso:country":"IN",
    "ks:ks_name":"Cherlopalli",
    "ks:ks_pop":577,
    "ks:ks_type":"HABITATION",
    "name:eng_x_preferred":[
        "Cherlopalli"
    ],
    "wof:name":"Cherlopalli",
    "wof:placetype":"locality",
    "wof:population":577
},
  "geometry": {"coordinates":[77.54208300000001,15.119087],"type":"Point"}
}