{
  "type": "Feature",
  "properties": {
    "iso:country":"IN",
    "ks:ks_name":"Athikal",
    "ks:ks_pop":240,
    "ks:ks_type":"HABITATION",
    "name:eng_x_preferred":[
        "Athikal"
    ],
    "wof:name":"Athikal",
    "wof:placetype":"locality",
    "wof:population":240
},
  "geometry": {"coordinates":[76.667097,11.469535],"type":"Point"}
}