{
  "type": "Feature",
  "properties": {
    "gn:admin1_code":"35.0",
    "gn:admin2_code":"436.0",
    "gn:asciiname":"Chitoni",
    "gn:country_code":"IN",
    "gn:dem":452,
    "gn:feature_class":"P",
    "gn:feature_code":"PPL",
    "gn:name":"Chitoni",
    "gn:population":0,
    "gn:timezone":"Asia/Kolkata",
    "iso:country":"IN",
    "ks:ks_name":"Chitouni",
    "ks:ks_pop":988,
    "ks:ks_type":"VILLAGE",
    "name:eng_x_preferred":[
        "Chitouni"
    ],
    "name:eng_x_variant":[
        "Chitoni"
    ],
    "wof:name":"Chitouni",
    "wof:placetype":"locality",
    "wof:population":988
},
  "geometry": {"coordinates":[76.751313,23.453377],"type":"Point"}
}