{
  "type": "Feature",
  "properties": {
    "iso:country":"IN",
    "ks:ks_name":"Lakkavaram",
    "ks:ks_pop":103,
    "ks:ks_type":"HABITATION",
    "name:eng_x_preferred":[
        "Lakkavaram"
    ],
    "wof:name":"Lakkavaram",
    "wof:placetype":"locality",
    "wof:population":103
},
  "geometry": {"coordinates":[82.542801,17.830274],"type":"Point"}
}