{
  "type": "Feature",
  "properties": {
    "gn:admin1_code":"38.0",
    "gn:admin2_code":"348.0",
    "gn:asciiname":"Chaukhandi",
    "gn:country_code":"IN",
    "gn:dem":398,
    "gn:feature_class":"P",
    "gn:feature_code":"PPL",
    "gn:name":"Chaukhandi",
    "gn:population":0,
    "gn:timezone":"Asia/Kolkata",
    "iso:country":"IN",
    "ks:ks_name":"Chaukhandi",
    "ks:ks_pop":52,
    "ks:ks_type":"VILLAGE",
    "ks:ks_uagg_main":0,
    "name:ara_x_preferred":[
        "\u062a\u0634\u0648\u0643\u062e\u0627\u0646\u062f\u064a"
    ],
    "name:ben_bn_x_preferred":[
        "\u099a\u09cc\u0996\u09be\u09a3\u09cd\u09a1\u09bf"
    ],
    "name:ben_in_x_preferred":[
        "\u099a\u09cc\u0996\u09be\u09a3\u09cd\u09a1\u09bf"
    ],
    "name:eng_x_preferred":[
        "Chaukhandi"
    ],
    "name:guj_x_preferred":[
        "\u0a9a\u0acc\u0a96\u0a82\u0aa1\u0ac0"
    ],
    "name:hin_x_preferred":[
        "\u091a\u094c\u0916\u0902\u0921\u0940"
    ],
    "name:kan_x_preferred":[
        "\u0c9a\u0ccc\u0c96\u0c82\u0ca1\u0cbf"
    ],
    "name:mal_x_preferred":[
        "\u0d1a\u0d57\u0d16\u0d23\u0d4d\u0d1f\u0d3f"
    ],
    "name:mar_x_preferred":[
        "\u091a\u094c\u0916\u0902\u0921\u0940"
    ],
    "name:pan_x_preferred":[
        "\u0a1a\u0a4c\u0a16\u0a70\u0a21\u0a40"
    ],
    "name:tam_x_preferred":[
        "\u0b9a\u0bcc\u0b95\u0ba9\u0bcd\u0b9f\u0bbf"
    ],
    "name:tel_x_preferred":[
        "\u0c1a\u0c4c\u0c16\u0c02\u0c21\u0c3f"
    ],
    "name:urd_x_preferred":[
        "\u0686\u0648\u06a9\u06be\u0646\u0688\u06cc"
    ],
    "wof:name":"Chaukhandi",
    "wof:placetype":"neighbourhood",
    "wof:population":52
},
  "geometry": {"coordinates":[85.46487500000001,24.434012],"type":"Point"}
}