{
  "type": "Feature",
  "properties": {
    "gn:admin1_code":"36.0",
    "gn:admin2_code":"140.0",
    "gn:asciiname":"Bisokhar",
    "gn:country_code":"IN",
    "gn:dem":222,
    "gn:feature_class":"P",
    "gn:feature_code":"PPL",
    "gn:name":"Bisokhar",
    "gn:population":0,
    "gn:timezone":"Asia/Kolkata",
    "iso:country":"IN",
    "name:bpy_x_preferred":[
        "\u09ac\u09bf\u09b8\u09cb\u0996\u09be\u09b0"
    ],
    "name:hin_x_preferred":[
        "\u092c\u093f\u0938\u094b\u0916\u093e\u0930"
    ],
    "name:ita_x_preferred":[
        "Bisokhar"
    ],
    "name:msa_x_preferred":[
        "Bisokhar"
    ],
    "name:new_x_preferred":[
        "\u0935\u093f\u0936\u094b\u0916\u0930"
    ],
    "name:nld_x_preferred":[
        "Bisokhar"
    ],
    "name:pol_x_preferred":[
        "Bisokhar"
    ],
    "name:por_x_preferred":[
        "Bisokhar"
    ],
    "name:urd_x_preferred":[
        "\u0628\u0633\u0648\u06a9\u06be\u0631"
    ],
    "name:vie_x_preferred":[
        "Bisokhar"
    ],
    "name:zho_x_preferred":[
        "\u6bd4\u7d22\u5361\u5c14"
    ],
    "wof:name":"Bisokhar",
    "wof:placetype":"locality"
},
  "geometry": {"coordinates":[77.5842,28.8515],"type":"Point"}
}