{
  "type": "Feature",
  "properties": {
    "iso:country":"IN",
    "ks:ks_alt_nam":"AJMERIEEDAS",
    "ks:ks_name":"Ajmerieedas",
    "ks:ks_pop":115,
    "ks:ks_type":"HABITATION",
    "ks:ks_uagg_main":0,
    "name:eng_x_preferred":[
        "Ajmerieedas"
    ],
    "wof:name":"Ajmerieedas",
    "wof:placetype":"neighbourhood",
    "wof:population":115
},
  "geometry": {"coordinates":[81.53943,27.691603],"type":"Point"}
}