{
  "type": "Feature",
  "properties": {
    "iso:country":"IN",
    "ks:ks_alt_nam":"pure satan ganj",
    "ks:ks_name":"Pure Satan Ganj",
    "ks:ks_pop":134,
    "ks:ks_type":"HABITATION",
    "name:eng_x_preferred":[
        "Pure Satan Ganj"
    ],
    "wof:name":"Pure Satan Ganj",
    "wof:placetype":"locality",
    "wof:population":134
},
  "geometry": {"coordinates":[81.371,26.493],"type":"Point"}
}