{
  "type": "Feature",
  "properties": {
    "iso:country":"IN",
    "ks:ks_alt_nam":"Indira nagar",
    "ks:ks_name":"Indira Nagar",
    "ks:ks_pop":230,
    "ks:ks_type":"HABITATION",
    "name:eng_x_preferred":[
        "Indira Nagar"
    ],
    "wof:name":"Indira Nagar",
    "wof:placetype":"locality",
    "wof:population":230
},
  "geometry": {"coordinates":[76.03723599999999,17.433891],"type":"Point"}
}