{
  "type": "Feature",
  "properties": {
    "iso:country":"IN",
    "ks:ks_alt_nam":"Hat mohida",
    "ks:ks_name":"Hat Mohida",
    "ks:ks_pop":963,
    "ks:ks_type":"HABITATION",
    "name:eng_x_preferred":[
        "Hat Mohida"
    ],
    "wof:name":"Hat Mohida",
    "wof:placetype":"locality",
    "wof:population":963
},
  "geometry": {"coordinates":[74.39739299999999,21.455046],"type":"Point"}
}