{
  "type": "Feature",
  "properties": {
    "iso:country":"IN",
    "ks:ks_name":"Sadakpara",
    "ks:ks_pop":258,
    "ks:ks_type":"HABITATION",
    "name:eng_x_preferred":[
        "Sadakpara"
    ],
    "wof:name":"Sadakpara",
    "wof:placetype":"locality",
    "wof:population":258
},
  "geometry": {"coordinates":[83.257892,22.600212],"type":"Point"}
}