{
  "type": "Feature",
  "properties": {
    "iso:country":"IN",
    "ks:ks_name":"Girvanewadi",
    "ks:ks_pop":23,
    "ks:ks_type":"HABITATION",
    "name:eng_x_preferred":[
        "Girvanewadi"
    ],
    "wof:name":"Girvanewadi",
    "wof:placetype":"locality",
    "wof:population":23
},
  "geometry": {"coordinates":[73.29860600000001,17.280247],"type":"Point"}
}