{
  "type": "Feature",
  "properties": {
    "iso:country":"IN",
    "ks:ks_alt_nam":"Hiradabri khas",
    "ks:ks_name":"Hiradabri Khas",
    "ks:ks_pop":223,
    "ks:ks_type":"HABITATION",
    "name:eng_x_preferred":[
        "Hiradabri Khas"
    ],
    "wof:name":"Hiradabri Khas",
    "wof:placetype":"locality",
    "wof:population":223
},
  "geometry": {"coordinates":[83.082921,23.201625],"type":"Point"}
}