{
  "type": "Feature",
  "properties": {
    "iso:country":"IN",
    "ks:ks_name":"Beedinakere",
    "ks:ks_pop":284,
    "ks:ks_type":"HABITATION",
    "ks:ks_uagg_main":0,
    "name:eng_x_preferred":[
        "Beedinakere"
    ],
    "wof:name":"Beedinakere",
    "wof:placetype":"neighbourhood",
    "wof:population":284
},
  "geometry": {"coordinates":[74.75196800000001,13.173938],"type":"Point"}
}