{
  "type": "Feature",
  "properties": {
    "gn:admin1_code":"36",
    "gn:admin2_code":"194.0",
    "gn:asciiname":"Chak Moghlani",
    "gn:country_code":"IN",
    "gn:dem":88,
    "gn:feature_class":"P",
    "gn:feature_code":"PPL",
    "gn:name":"Chak Moghl\u0101ni",
    "gn:population":0,
    "gn:timezone":"Asia/Kolkata",
    "iso:country":"IN",
    "ks:ks_name":"Chak Muglani",
    "ks:ks_pop":125,
    "ks:ks_type":"VILLAGE",
    "name:eng_x_preferred":[
        "Chak Muglani"
    ],
    "name:eng_x_variant":[
        "Chak Moghlani"
    ],
    "wof:name":"Chak Muglani",
    "wof:placetype":"locality",
    "wof:population":125
},
  "geometry": {"coordinates":[82.62137300000001,25.825603],"type":"Point"}
}