{
  "type": "Feature",
  "properties": {
    "iso:country":"IN",
    "ks:ks_alt_nam":"Besr\u0101d\u012bh",
    "ks:ks_name":"Besradih",
    "ks:ks_pop":215,
    "ks:ks_type":"VILLAGE",
    "name:eng_x_preferred":[
        "Besradih"
    ],
    "name:eng_x_variant":[
        "Besr\u0101d\u012bh"
    ],
    "wof:name":"Besradih",
    "wof:placetype":"locality",
    "wof:population":215
},
  "geometry": {"coordinates":[85.539907,23.229707],"type":"Point"}
}