{
  "type": "Feature",
  "properties": {
    "iso:country":"IN",
    "qs:name":"New Friends Colony",
    "qs:name_adm0":"India",
    "qs:name_adm1":"Delhi",
    "qs:photos":63,
    "qs:photos_1k":13,
    "qs:photos_9k":1,
    "qs:photos_9r":2,
    "qs:photos_all":63,
    "qs:photos_sr":2,
    "qs:placetype":"Suburb",
    "qs:pop_sr":"0",
    "wd:wordcount":553,
    "wof:name":"New Friends Colony",
    "wof:placetype":"neighbourhood"
},
  "geometry": {"coordinates":[77.271137,28.563114],"type":"Point"}
}