{
  "type": "Feature",
  "properties": {
    "iso:country":"IN",
    "name:eng_x_preferred":[
        "New Friends Colony"
    ],
    "name:hin_x_preferred":[
        "\u0928\u094d\u092f\u0942 \u092b\u094d\u0930\u0947\u0902\u0921\u094d\u0938 \u0915\u093e\u0932\u094b\u0928\u0940"
    ],
    "name:urd_x_preferred":[
        "\u0646\u06cc\u0648 \u0641\u0631\u06cc\u0646\u0688\u0632 \u06a9\u0627\u0644\u0648\u0646\u06cc"
    ],
    "qs:name":"New Friends Colony",
    "qs:name_adm0":"India",
    "qs:name_adm1":"Delhi",
    "qs:photos":63,
    "qs:photos_1k":13,
    "qs:photos_9k":1,
    "qs:photos_9r":2,
    "qs:photos_all":63,
    "qs:photos_sr":2,
    "qs:placetype":"Suburb",
    "qs:pop_sr":"0",
    "wd:wordcount":553,
    "wof:name":"New Friends Colony",
    "wof:placetype":"neighbourhood"
},
  "geometry": {"coordinates":[77.271137,28.563114],"type":"Point"}
}