{
  "type": "Feature",
  "properties": {
    "gn:admin1_code":"13.0",
    "gn:admin2_code":"593.0",
    "gn:asciiname":"Mundakottakurisshi",
    "gn:country_code":"IN",
    "gn:dem":54,
    "gn:feature_class":"P",
    "gn:feature_code":"PPL",
    "gn:name":"Mundak\u014dttakurisshi",
    "gn:population":0,
    "gn:timezone":"Asia/Kolkata",
    "iso:country":"IN",
    "wof:name":"Mundakottakurisshi",
    "wof:placetype":"neighbourhood"
},
  "geometry": {"coordinates":[76.27813999999999,10.84094],"type":"Point"}
}