{
  "type": "Feature",
  "properties": {
    "iso:country":"IN",
    "ks:ks_name":"Jalgaokarwadi",
    "ks:ks_pop":25,
    "ks:ks_type":"HABITATION",
    "name:eng_x_preferred":[
        "Jalgaokarwadi"
    ],
    "wof:name":"Jalgaokarwadi",
    "wof:placetype":"locality",
    "wof:population":25
},
  "geometry": {"coordinates":[73.262125,17.376244],"type":"Point"}
}