{
  "type": "Feature",
  "properties": {
    "gn:country":"IN",
    "gn:fcode":"PPL",
    "gn:pop":8048,
    "iso:country":"IN",
    "name:bpy_x_preferred":[
        "\u0986\u09b0\u09bf\u09ae\u09b2\u09ae"
    ],
    "name:bul_x_preferred":[
        "\u0410\u0440\u0438\u043c\u0430\u043b\u0430\u043c"
    ],
    "name:eng_x_preferred":[
        "Arimalam"
    ],
    "name:fra_x_preferred":[
        "Arimalam"
    ],
    "name:ita_x_preferred":[
        "Arimalam"
    ],
    "name:msa_x_preferred":[
        "Arimalam"
    ],
    "name:nan_x_preferred":[
        "Arimalam"
    ],
    "name:new_x_preferred":[
        "\u0905\u0930\u093f\u092e\u0932\u092e"
    ],
    "name:nld_x_preferred":[
        "Arimalam"
    ],
    "name:por_x_preferred":[
        "Arimalam"
    ],
    "name:swe_x_preferred":[
        "Arimalam"
    ],
    "name:tam_x_preferred":[
        "\u0b85\u0bb0\u0bbf\u0bae\u0bb3\u0bae\u0bcd"
    ],
    "name:vie_x_preferred":[
        "Arimalam"
    ],
    "name:zho_x_preferred":[
        "\u963f\u91cc\u9a6c\u62c9\u59c6"
    ],
    "qs:name":"Arimalam",
    "qs:name_adm0":"India",
    "qs:name_adm1":"Tamil Nadu",
    "qs:photos_9k":1,
    "qs:photos_9r":1,
    "qs:photos_all":21,
    "qs:photos_sr":0,
    "qs:placetype":"Town",
    "qs:pop_sr":"5",
    "wd:wordcount":878,
    "wof:name":"Arimalam",
    "wof:placetype":"locality",
    "wof:population":8048
},
  "geometry": {"coordinates":[78.88712,10.25639],"type":"Point"}
}