{
  "type": "Feature",
  "properties": {
    "iso:country":"IN",
    "ks:ks_name":"Awalpada",
    "ks:ks_pop":1682,
    "ks:ks_type":"HABITATION",
    "name:eng_x_preferred":[
        "Awalpada"
    ],
    "wof:name":"Awalpada",
    "wof:placetype":"locality",
    "wof:population":1682
},
  "geometry": {"coordinates":[73.32282600000001,20.067851],"type":"Point"}
}