{
  "type": "Feature",
  "properties": {
    "gn:admin1_code":"34.0",
    "gn:admin2_code":"224.0",
    "gn:asciiname":"Chapar",
    "gn:country_code":"IN",
    "gn:dem":36,
    "gn:feature_class":"P",
    "gn:feature_code":"PPL",
    "gn:name":"Chapar",
    "gn:population":0,
    "gn:timezone":"Asia/Kolkata",
    "iso:country":"IN",
    "name:ceb_x_preferred":[
        "Chapar"
    ],
    "name:fas_x_preferred":[
        "\u0686\u067e\u0631"
    ],
    "name:swe_x_preferred":[
        "Chapar"
    ],
    "wof:name":"Chapar",
    "wof:placetype":"locality"
},
  "geometry": {"coordinates":[87.20631,25.40685],"type":"Point"}
}