{
  "type": "Feature",
  "properties": {
    "gn:admin1_code":"21",
    "gn:admin2_code":"385.0",
    "gn:asciiname":"Kutri",
    "gn:country_code":"IN",
    "gn:dem":83,
    "gn:feature_class":"P",
    "gn:feature_code":"PPL",
    "gn:name":"Kutri",
    "gn:population":0,
    "gn:timezone":"Asia/Kolkata",
    "iso:country":"IN",
    "ks:ks_name":"Kuturi",
    "ks:ks_pop":102,
    "ks:ks_type":"VILLAGE",
    "name:eng_x_preferred":[
        "Kuturi"
    ],
    "name:eng_x_variant":[
        "Kutri"
    ],
    "wof:name":"Kuturi",
    "wof:placetype":"locality",
    "wof:population":102
},
  "geometry": {"coordinates":[84.819959,20.553724],"type":"Point"}
}