{
  "type": "Feature",
  "properties": {
    "gn:admin1_code":"21",
    "gn:admin2_code":"385.0",
    "gn:asciiname":"Kutri",
    "gn:country_code":"IN",
    "gn:dem":83,
    "gn:feature_class":"P",
    "gn:feature_code":"PPL",
    "gn:name":"Kutri",
    "gn:population":0,
    "gn:timezone":"Asia/Kolkata",
    "iso:country":"IN",
    "wof:name":"Kutri",
    "wof:placetype":"locality"
},
  "geometry": {"coordinates":[84.81986999999999,20.55356],"type":"Point"}
}