{
  "type": "Feature",
  "properties": {
    "iso:country":"IN",
    "ks:ks_name":"Kakledi",
    "ks:ks_pop":389,
    "ks:ks_type":"HABITATION",
    "name:eng_x_preferred":[
        "Kakledi"
    ],
    "wof:name":"Kakledi",
    "wof:placetype":"locality",
    "wof:population":389
},
  "geometry": {"coordinates":[81.692712,23.576816],"type":"Point"}
}