{
  "type": "Feature",
  "properties": {
    "gn:admin1_code":"36.0",
    "gn:admin2_code":"155",
    "gn:asciiname":"Karanpur",
    "gn:country_code":"IN",
    "gn:dem":135,
    "gn:feature_class":"P",
    "gn:feature_code":"PPL",
    "gn:name":"Karanpur",
    "gn:population":0,
    "gn:timezone":"Asia/Kolkata",
    "iso:country":"IN",
    "name:ben_x_preferred":[
        "\u0995\u09b0\u09a8\u09aa\u09c1\u09b0"
    ],
    "name:bpy_x_preferred":[
        "\u0995\u09b0\u09a8\u09aa\u09c1\u09b0"
    ],
    "name:ceb_x_preferred":[
        "Karanpur"
    ],
    "name:hin_x_preferred":[
        "\u0936\u094d\u0930\u0940 \u0915\u0930\u0923\u092a\u0941\u0930"
    ],
    "name:ita_x_preferred":[
        "Karanpur"
    ],
    "name:msa_x_preferred":[
        "Karanpur"
    ],
    "name:new_x_preferred":[
        "\u0915\u0930\u0928\u092a\u0941\u0930"
    ],
    "name:por_x_preferred":[
        "Karanpur"
    ],
    "name:swe_x_preferred":[
        "Karanpur"
    ],
    "name:vie_x_preferred":[
        "Karanpur"
    ],
    "name:zho_x_preferred":[
        "\u5361\u5170\u666e\u5c14"
    ],
    "wof:name":"Karanpur",
    "wof:placetype":"locality"
},
  "geometry": {"coordinates":[79.90448000000001,27.23867000000001],"type":"Point"}
}