{
  "type": "Feature",
  "properties": {
    "iso:country":"IN",
    "ks:ks_name":"Girdharpur",
    "ks:ks_pop":1435,
    "ks:ks_type":"VILLAGE",
    "ks:ks_uagg_main":0,
    "name:eng_x_preferred":[
        "Girdharpur"
    ],
    "wof:name":"Girdharpur",
    "wof:placetype":"neighbourhood",
    "wof:population":1435
},
  "geometry": {"coordinates":[77.488131,28.634958],"type":"Point"}
}