{
  "type": "Feature",
  "properties": {
    "iso:country":"IN",
    "ks:ks_name":"Telabali",
    "ks:ks_pop":368,
    "ks:ks_type":"VILLAGE",
    "name:eng_x_preferred":[
        "Telabali"
    ],
    "wof:name":"Telabali",
    "wof:placetype":"locality",
    "wof:population":368
},
  "geometry": {"coordinates":[83.571409,20.598812],"type":"Point"}
}