{
  "type": "Feature",
  "properties": {
    "gn:admin1_code":"21.0",
    "gn:admin2_code":"376",
    "gn:asciiname":"Bodobil",
    "gn:country_code":"IN",
    "gn:dem":405,
    "gn:feature_class":"P",
    "gn:feature_code":"PPL",
    "gn:name":"Bodobil",
    "gn:population":0,
    "gn:timezone":"Asia/Kolkata",
    "iso:country":"IN",
    "wof:name":"Bodobil",
    "wof:placetype":"neighbourhood"
},
  "geometry": {"coordinates":[85.89503000000001,21.85911],"type":"Point"}
}