{
  "type": "Feature",
  "properties": {
    "iso:country":"IN",
    "ks:ks_alt_nam":"Biskut pt II",
    "ks:ks_name":"Biskut Pt Ii",
    "ks:ks_pop":526,
    "ks:ks_type":"HABITATION",
    "name:eng_x_preferred":[
        "Biskut Pt Ii"
    ],
    "wof:name":"Biskut Pt Ii",
    "wof:placetype":"locality",
    "wof:population":526
},
  "geometry": {"coordinates":[92.32205399999999,24.83249],"type":"Point"}
}