{
  "type": "Feature",
  "properties": {
    "iso:country":"IN",
    "ks:ks_name":"Hanumanpura",
    "ks:ks_pop":178,
    "ks:ks_type":"HABITATION",
    "name:eng_x_preferred":[
        "Hanumanpura"
    ],
    "wof:name":"Hanumanpura",
    "wof:placetype":"locality",
    "wof:population":178
},
  "geometry": {"coordinates":[71.661941,23.990286],"type":"Point"}
}