{
  "type": "Feature",
  "properties": {
    "iso:country":"IN",
    "ks:ks_name":"Hasanpur",
    "ks:ks_pop":1045,
    "ks:ks_type":"HABITATION",
    "name:eng_x_preferred":[
        "Hasanpur"
    ],
    "wof:name":"Hasanpur",
    "wof:placetype":"locality",
    "wof:population":1045
},
  "geometry": {"coordinates":[81.812612,27.82859],"type":"Point"}
}