{
  "type": "Feature",
  "properties": {
    "iso:country":"IN",
    "ks:ks_name":"33 PS",
    "ks:ks_pop":115,
    "ks:ks_type":"VILLAGE",
    "name:eng_x_preferred":[
        "33 PS"
    ],
    "wof:name":"33 PS",
    "wof:placetype":"locality",
    "wof:population":115
},
  "geometry": {"coordinates":[73.31562,29.514262],"type":"Point"}
}