{
  "type": "Feature",
  "properties": {
    "gn:admin1_code":"36",
    "gn:admin2_code":"159.0",
    "gn:asciiname":"Sabalpur",
    "gn:country_code":"IN",
    "gn:dem":137,
    "gn:feature_class":"P",
    "gn:feature_code":"PPL",
    "gn:name":"Sabalpur",
    "gn:population":0,
    "gn:timezone":"Asia/Kolkata",
    "iso:country":"IN",
    "ks:ks_name":"Sabalpur",
    "ks:ks_type":"VILLAGE",
    "name:ceb_x_preferred":[
        "Sabalpur"
    ],
    "name:eng_x_preferred":[
        "Sabalpur"
    ],
    "name:spa_x_preferred":[
        "Sabalpur"
    ],
    "name:swe_x_preferred":[
        "Sabalpur"
    ],
    "name:urd_x_preferred":[
        "\u0633\u0628\u0644\u067e\u0648\u0631"
    ],
    "wof:name":"Sabalpur",
    "wof:placetype":"locality"
},
  "geometry": {"coordinates":[79.62982100000001,27.449655],"type":"Point"}
}