{
  "type": "Feature",
  "properties": {
    "iso:country":"IN",
    "ks:ks_name":"Karimbara",
    "ks:ks_pop":865,
    "ks:ks_type":"HABITATION",
    "name:eng_x_preferred":[
        "Karimbara"
    ],
    "wof:name":"Karimbara",
    "wof:placetype":"locality",
    "wof:population":865
},
  "geometry": {"coordinates":[76.592089,10.535029],"type":"Point"}
}