{
  "type": "Feature",
  "properties": {
    "iso:country":"IN",
    "ks:ks_alt_nam":"JALDAPARA",
    "ks:ks_name":"Jaldapara",
    "ks:ks_pop":146,
    "ks:ks_type":"HABITATION",
    "name:eng_x_preferred":[
        "Jaldapara"
    ],
    "wof:name":"Jaldapara",
    "wof:placetype":"locality",
    "wof:population":146
},
  "geometry": {"coordinates":[82.143879,22.612662],"type":"Point"}
}