{
  "type": "Feature",
  "properties": {
    "iso:country":"IN",
    "ks:ks_name":"Komatlavarigudem",
    "ks:ks_pop":265,
    "ks:ks_type":"HABITATION",
    "ks:ks_uagg_main":0,
    "name:eng_x_preferred":[
        "Komatlavarigudem"
    ],
    "wof:name":"Komatlavarigudem",
    "wof:placetype":"neighbourhood",
    "wof:population":265
},
  "geometry": {"coordinates":[81.299633,17.24775],"type":"Point"}
}