{
  "type": "Feature",
  "properties": {
    "gn:admin1_code":"21",
    "gn:admin2_code":"374.0",
    "gn:asciiname":"Khuntjharia",
    "gn:country_code":"IN",
    "gn:dem":251,
    "gn:feature_class":"P",
    "gn:feature_code":"PPL",
    "gn:name":"Khuntjharia",
    "gn:population":0,
    "gn:timezone":"Asia/Kolkata",
    "iso:country":"IN",
    "wof:name":"Khuntjharia",
    "wof:placetype":"locality"
},
  "geometry": {"coordinates":[83.81374,21.922],"type":"Point"}
}