{
  "type": "Feature",
  "properties": {
    "iso:country":"IN",
    "ks:ks_name":"Kepli",
    "ks:ks_pop":45,
    "ks:ks_type":"HABITATION",
    "name:eng_x_preferred":[
        "Kepli"
    ],
    "wof:name":"Kepli",
    "wof:placetype":"locality",
    "wof:population":45
},
  "geometry": {"coordinates":[75.03820899999999,13.497294],"type":"Point"}
}