{
  "type": "Feature",
  "properties": {
    "gn:country":"IN",
    "gn:fcode":"PPL",
    "gn:population":24209,
    "iso:country":"IN",
    "name:ben_x_preferred":[
        "\u09a8\u09a8\u09cd\u09a6\u0997\u09be\u0981\u0993"
    ],
    "name:ceb_x_preferred":[
        "N\u0101ndgaon"
    ],
    "name:deu_x_preferred":[
        "Nandgaon"
    ],
    "name:eng_x_preferred":[
        "Nandgaon"
    ],
    "name:fas_x_preferred":[
        "\u0646\u0627\u0646\u062f\u06af\u0627\u0626\u0648\u0646"
    ],
    "name:fra_x_preferred":[
        "Nandgaon"
    ],
    "name:guj_x_preferred":[
        "\u0aa8\u0a82\u0aa6\u0a97\u0abe\u0a82\u0ab5"
    ],
    "name:hif_x_preferred":[
        "Nandgaon"
    ],
    "name:ita_x_preferred":[
        "Nandgaon"
    ],
    "name:jpn_x_preferred":[
        "\u30ca\u30f3\u30c9\u30ac\u30aa\u30f3"
    ],
    "name:kan_x_preferred":[
        "\u0ca8\u0c82\u0ca6\u0c97\u0cbe\u0cb5\u0ccd"
    ],
    "name:kor_x_preferred":[
        "\ub09c\ub4dc\uac00\uc628"
    ],
    "name:mar_x_preferred":[
        "\u0928\u093e\u0902\u0926\u0917\u093e\u0935"
    ],
    "name:msa_x_preferred":[
        "Nandgaon"
    ],
    "name:new_x_preferred":[
        "\u0928\u0928\u094d\u0926\u0917\u093e\u0902\u0935"
    ],
    "name:nld_x_preferred":[
        "Nandgaon"
    ],
    "name:ori_x_preferred":[
        "\u0b28\u0b28\u0b4d\u0b26\u0b17\u0b3e\u0b13\u0b01"
    ],
    "name:por_x_preferred":[
        "Nandgaon"
    ],
    "name:rus_x_preferred":[
        "\u041c\u0430\u0440\u0433\u0430\u043e"
    ],
    "name:rus_x_variant":[
        "\u041d\u0430\u043d\u0434\u0433\u0430\u043e\u043d"
    ],
    "name:spa_x_preferred":[
        "Nandgaon"
    ],
    "name:swe_x_preferred":[
        "N\u0101ndgaon"
    ],
    "name:tam_x_preferred":[
        "\u0ba8\u0ba8\u0bcd\u0ba4\u0b95\u0bbe\u0ba9\u0bcd"
    ],
    "name:tel_x_preferred":[
        "\u0c28\u0c02\u0c26\u0c17\u0c3e\u0c35\u0c4d"
    ],
    "name:urd_x_preferred":[
        "\u0646\u0627\u0646 \u06af\u0627\u0624\u06ba\u060c \u0645\u06c1\u0627\u0631\u0627\u0634\u0679\u0631"
    ],
    "name:urd_x_variant":[
        "\u0646\u0627\u0646 \u06af\u0627\u0624\u06ba"
    ],
    "name:vie_x_preferred":[
        "Nandgaon"
    ],
    "name:zho_x_preferred":[
        "\u5357\u5fb7\u52a0\u5965\u6069"
    ],
    "qs:name":"Nandgaon",
    "qs:name_adm0":"India",
    "qs:name_adm1":"Maharashtra",
    "qs:photos_9r":0,
    "qs:photos_sr":0,
    "qs:placetype":"Town",
    "qs:pop_sr":"7",
    "wd:wordcount":78,
    "wof:name":"Nandgaon",
    "wof:placetype":"locality",
    "wof:population":24209
},
  "geometry": {"coordinates":[74.65733,20.30713],"type":"Point"}
}