{
  "type": "Feature",
  "properties": {
    "gn:admin1_code":"2.0",
    "gn:admin2_code":"544.0",
    "gn:asciiname":"Bhimosingi",
    "gn:country_code":"IN",
    "gn:dem":919,
    "gn:feature_class":"P",
    "gn:feature_code":"PPL",
    "gn:name":"Bh\u012bmosingi",
    "gn:population":0,
    "gn:timezone":"Asia/Kolkata",
    "iso:country":"IN",
    "wof:name":"Bhimosingi",
    "wof:placetype":"neighbourhood"
},
  "geometry": {"coordinates":[82.67252999999999,18.10384],"type":"Point"}
}