{
  "type": "Feature",
  "properties": {
    "iso:country":"IN",
    "ks:ks_name":"Kothakurru Pattapupalem",
    "ks:ks_pop":728,
    "ks:ks_type":"HABITATION",
    "ks:ks_uagg_main":0,
    "name:eng_x_preferred":[
        "Kothakurru Pattapupalem"
    ],
    "wof:name":"Kothakurru Pattapupalem",
    "wof:placetype":"neighbourhood",
    "wof:population":728
},
  "geometry": {"coordinates":[80.10018100000001,14.722611],"type":"Point"}
}