{
  "type": "Feature",
  "properties": {
    "iso:country":"IN",
    "ks:ks_name":"Haingadde",
    "ks:ks_pop":101,
    "ks:ks_type":"HABITATION",
    "name:eng_x_preferred":[
        "Haingadde"
    ],
    "wof:name":"Haingadde",
    "wof:placetype":"locality",
    "wof:population":101
},
  "geometry": {"coordinates":[74.52113799999999,14.32796],"type":"Point"}
}