{
  "type": "Feature",
  "properties": {
    "gn:admin1_code":"36",
    "gn:admin2_code":"193.0",
    "gn:asciiname":"Sandauli",
    "gn:country_code":"IN",
    "gn:dem":73,
    "gn:feature_class":"P",
    "gn:feature_code":"PPL",
    "gn:name":"Sandaul\u012b",
    "gn:population":0,
    "gn:timezone":"Asia/Kolkata",
    "iso:country":"IN",
    "ks:ks_alt_nam":"Sandaul\u012b",
    "ks:ks_name":"Sandauli",
    "ks:ks_type":"VILLAGE",
    "ks:ks_uagg_main":0,
    "name:eng_x_preferred":[
        "Sandauli"
    ],
    "name:eng_x_variant":[
        "Sandaul\u012b"
    ],
    "wof:name":"Sandauli",
    "wof:placetype":"neighbourhood"
},
  "geometry": {"coordinates":[83.87339,25.847477],"type":"Point"}
}