{
  "type": "Feature",
  "properties": {
    "iso:country":"IN",
    "ks:ks_name":"Gangubela",
    "ks:ks_pop":33,
    "ks:ks_type":"VILLAGE",
    "name:eng_x_preferred":[
        "Gangubela"
    ],
    "wof:name":"Gangubela",
    "wof:placetype":"locality",
    "wof:population":33
},
  "geometry": {"coordinates":[87.353844,21.770093],"type":"Point"}
}