{
  "type": "Feature",
  "properties": {
    "gn:admin1_code":"12.0",
    "gn:admin2_code":"021",
    "gn:asciiname":"Thalal",
    "gn:country_code":"IN",
    "gn:dem":347,
    "gn:feature_class":"P",
    "gn:feature_code":"PPL",
    "gn:name":"Thal\u0101l",
    "gn:population":0,
    "gn:timezone":"Asia/Kolkata",
    "iso:country":"IN",
    "wof:name":"Thalal",
    "wof:placetype":"locality"
},
  "geometry": {"coordinates":[74.95609,32.78128],"type":"Point"}
}