{
  "type": "Feature",
  "properties": {
    "gn:admin1_code":"21",
    "gn:admin2_code":"374.0",
    "gn:asciiname":"Kusumdih",
    "gn:country_code":"IN",
    "gn:dem":574,
    "gn:feature_class":"P",
    "gn:feature_code":"PPL",
    "gn:name":"Kusumdih",
    "gn:population":0,
    "gn:timezone":"Asia/Kolkata",
    "iso:country":"IN",
    "ks:ks_name":"Kusumdihi",
    "ks:ks_pop":858,
    "ks:ks_type":"VILLAGE",
    "name:eng_x_preferred":[
        "Kusumdihi"
    ],
    "name:eng_x_variant":[
        "Kusumdih"
    ],
    "wof:name":"Kusumdihi",
    "wof:placetype":"locality",
    "wof:population":858
},
  "geometry": {"coordinates":[85.233603,21.945377],"type":"Point"}
}