{
  "type": "Feature",
  "properties": {
    "iso:country":"IN",
    "ks:ks_alt_nam":"KHATABE TOLA",
    "ks:ks_name":"Khatabe Tola",
    "ks:ks_pop":300,
    "ks:ks_type":"HABITATION",
    "ks:ks_uagg_main":0,
    "name:eng_x_preferred":[
        "Khatabe Tola"
    ],
    "wof:name":"Khatabe Tola",
    "wof:placetype":"neighbourhood",
    "wof:population":300
},
  "geometry": {"coordinates":[86.88598500000001,26.425383],"type":"Point"}
}