{
  "type": "Feature",
  "properties": {
    "iso:country":"IN",
    "ks:ks_name":"Vathar",
    "ks:ks_pop":762,
    "ks:ks_type":"VILLAGE",
    "name:eng_x_preferred":[
        "Vathar"
    ],
    "wof:name":"Vathar",
    "wof:placetype":"locality",
    "wof:population":762
},
  "geometry": {"coordinates":[73.784175,18.126939],"type":"Point"}
}