{
  "type": "Feature",
  "properties": {
    "gn:admin1_code":"39.0",
    "gn:admin2_code":"64.0",
    "gn:asciiname":"Naguakhet",
    "gn:country_code":"IN",
    "gn:dem":1034,
    "gn:feature_class":"P",
    "gn:feature_code":"PPL",
    "gn:name":"Nagu\u0101khet",
    "gn:population":0,
    "gn:timezone":"Asia/Kolkata",
    "iso:country":"IN",
    "wof:name":"Naguakhet",
    "wof:placetype":"locality"
},
  "geometry": {"coordinates":[79.92838,29.53334000000001],"type":"Point"}
}