{
  "type": "Feature",
  "properties": {
    "gn:admin1_code":"36.0",
    "gn:admin2_code":"160.0",
    "gn:asciiname":"Mawa Bilwari",
    "gn:country_code":"IN",
    "gn:dem":148,
    "gn:feature_class":"P",
    "gn:feature_code":"PPL",
    "gn:name":"Mawa Bilw\u0101ri",
    "gn:population":0,
    "gn:timezone":"Asia/Kolkata",
    "iso:country":"IN",
    "wof:name":"Mawa Bilwari",
    "wof:placetype":"locality"
},
  "geometry": {"coordinates":[79.68783000000001,26.88547],"type":"Point"}
}