{
  "type": "Feature",
  "properties": {
    "iso:country":"IN",
    "ks:ks_name":"Mushari",
    "ks:ks_pop":252,
    "ks:ks_type":"HABITATION",
    "ks:ks_uagg_main":0,
    "name:eng_x_preferred":[
        "Mushari"
    ],
    "wof:name":"Mushari",
    "wof:placetype":"neighbourhood",
    "wof:population":252
},
  "geometry": {"coordinates":[87.13420000000001,25.8739],"type":"Point"}
}