{
  "type": "Feature",
  "properties": {
    "iso:country":"IN",
    "ks:ks_name":"Kaguvalasa",
    "ks:ks_pop":123,
    "ks:ks_type":"VILLAGE",
    "name:eng_x_preferred":[
        "Kaguvalasa"
    ],
    "wof:name":"Kaguvalasa",
    "wof:placetype":"locality",
    "wof:population":123
},
  "geometry": {"coordinates":[83.065361,18.337464],"type":"Point"}
}