{
  "type": "Feature",
  "properties": {
    "iso:country":"IN",
    "ks:ks_alt_nam":"CHAK KHANDELSAR",
    "ks:ks_name":"Chak Khandelsar",
    "ks:ks_pop":18,
    "ks:ks_type":"HABITATION",
    "name:eng_x_preferred":[
        "Chak Khandelsar"
    ],
    "wof:name":"Chak Khandelsar",
    "wof:placetype":"locality",
    "wof:population":18
},
  "geometry": {"coordinates":[75.258903,27.485842],"type":"Point"}
}