{
  "type": "Feature",
  "properties": {
    "gn:admin1_code":"3.0",
    "gn:admin2_code":"310.0",
    "gn:asciiname":"Tingrai Borhula",
    "gn:country_code":"IN",
    "gn:dem":117,
    "gn:feature_class":"P",
    "gn:feature_code":"PPL",
    "gn:name":"Tingrai Borhula",
    "gn:population":0,
    "gn:timezone":"Asia/Kolkata",
    "iso:country":"IN",
    "wof:name":"Tingrai Borhula",
    "wof:placetype":"locality"
},
  "geometry": {"coordinates":[95.2345,27.40173],"type":"Point"}
}