{
  "type": "Feature",
  "properties": {
    "iso:country":"IN",
    "ks:ks_name":"Sokhoi",
    "ks:ks_pop":210,
    "ks:ks_type":"HABITATION",
    "name:eng_x_preferred":[
        "Sokhoi"
    ],
    "wof:name":"Sokhoi",
    "wof:placetype":"locality",
    "wof:population":210
},
  "geometry": {"coordinates":[93.865675,26.059667],"type":"Point"}
}