{
  "type": "Feature",
  "properties": {
    "iso:country":"IN",
    "ks:ks_name":"Pah Ershanand",
    "ks:ks_pop":0,
    "ks:ks_type":"VILLAGE",
    "name:eng_x_preferred":[
        "Pah Ershanand"
    ],
    "wof:name":"Pah Ershanand",
    "wof:placetype":"locality",
    "wof:population":0
},
  "geometry": {"coordinates":[83.753039,25.811177],"type":"Point"}
}