{
  "type": "Feature",
  "properties": {
    "iso:country":"IN",
    "ks:ks_name":"Miyungpur",
    "ks:ks_pop":360,
    "ks:ks_type":"HABITATION",
    "ks:ks_uagg_main":0,
    "name:eng_x_preferred":[
        "Miyungpur"
    ],
    "wof:name":"Miyungpur",
    "wof:placetype":"neighbourhood",
    "wof:population":360
},
  "geometry": {"coordinates":[92.751295,25.511554],"type":"Point"}
}