{
  "type": "Feature",
  "properties": {
    "iso:country":"IN",
    "ks:ks_name":"Vaghelpura",
    "ks:ks_pop":725,
    "ks:ks_type":"HABITATION",
    "name:eng_x_preferred":[
        "Vaghelpura"
    ],
    "wof:name":"Vaghelpura",
    "wof:placetype":"locality",
    "wof:population":725
},
  "geometry": {"coordinates":[72.799806,22.273778],"type":"Point"}
}