{
  "type": "Feature",
  "properties": {
    "gn:admin1_code":"12",
    "gn:asciiname":"Pran Kutrian",
    "gn:country_code":"IN",
    "gn:dem":1665,
    "gn:feature_class":"P",
    "gn:feature_code":"PPL",
    "gn:name":"Pr\u0101n Kutri\u0101n",
    "gn:population":0,
    "gn:timezone":"Asia/Kolkata",
    "iso:country":"IN",
    "wof:name":"Pran Kutrian",
    "wof:placetype":"locality"
},
  "geometry": {"coordinates":[74.19271999999999,34.11482],"type":"Point"}
}