{
  "type": "Feature",
  "properties": {
    "gn:gn_country":"IN",
    "gn:gn_fcode":"PPL",
    "gn:gn_pop":23546,
    "gn:population":23546,
    "iso:country":"IN",
    "name:ben_x_preferred":[
        "\u09a8\u0997\u09b0"
    ],
    "name:chi_x_preferred":[
        "\u7eb3\u52a0\u5c14"
    ],
    "name:dut_x_preferred":[
        "Nagar"
    ],
    "name:eng_x_preferred":[
        "Nagar"
    ],
    "name:fre_x_preferred":[
        "Nagar"
    ],
    "name:ger_x_preferred":[
        "Nagar"
    ],
    "name:guj_x_preferred":[
        "\u0aa8\u0a97\u0ab0"
    ],
    "name:ita_x_preferred":[
        "Nagar"
    ],
    "name:jpn_x_preferred":[
        "\u30ca\u30ac\u30fc\u30eb"
    ],
    "name:kan_x_preferred":[
        "\u0ca8\u0c97\u0cb0\u0ccd"
    ],
    "name:kor_x_preferred":[
        "\ub098\uac00\ub974"
    ],
    "name:ori_x_preferred":[
        "\u200c\u200c\u0b28\u0b17\u0b30"
    ],
    "name:por_x_preferred":[
        "Nagar"
    ],
    "name:rus_x_preferred":[
        "\u041d\u0430\u0433\u0430\u0440"
    ],
    "name:spa_x_preferred":[
        "Nagar"
    ],
    "name:swe_x_preferred":[
        "Nagar"
    ],
    "name:tam_x_preferred":[
        "Nagar"
    ],
    "name:tel_x_preferred":[
        "\u0c28\u0c17\u0c30\u0c4d"
    ],
    "name:urd_x_preferred":[
        "\u0646\u06af\u0631\u060c \u0631\u0627\u062c\u0633\u062a\u06be\u0627\u0646"
    ],
    "name:vie_x_preferred":[
        "Nagar"
    ],
    "qs_pg:aaroncc":"IN",
    "qs_pg:gn_country":"IN",
    "qs_pg:gn_fcode":"PPL",
    "qs_pg:gn_pop":23546,
    "qs_pg:name":"Nagar",
    "qs_pg:name_adm0":"India",
    "qs_pg:name_adm1":"Rajasthan",
    "qs_pg:photos_9k":1,
    "qs_pg:photos_9r":1,
    "qs_pg:photos_all":6,
    "qs_pg:photos_sr":0,
    "qs_pg:pop_sr":7,
    "qs_pg:qs_pg_placetype":"locality",
    "qs_pg:qs_pg_placetype_gp":"Town",
    "qs_pg:woe_adm0":23424848,
    "woe:adm0_id":23424848,
    "woe:name_adm0":"India",
    "woe:name_adm1":"Rajasthan",
    "woe:placetype":"Town",
    "wof:name":"Nagar",
    "wof:placetype":"locality",
    "wof:population":23546
},
  "geometry": {"coordinates":[77.09922,27.42397],"type":"Point"}
}