{
  "type": "Feature",
  "properties": {
    "gn:admin1_code":"38.0",
    "gn:admin2_code":"358.0",
    "gn:asciiname":"Jolah Khap",
    "gn:country_code":"IN",
    "gn:dem":248,
    "gn:feature_class":"P",
    "gn:feature_code":"PPL",
    "gn:name":"Jol\u0101h Kh\u0101p",
    "gn:population":0,
    "gn:timezone":"Asia/Kolkata",
    "iso:country":"IN",
    "wof:name":"Jolah Khap",
    "wof:placetype":"locality"
},
  "geometry": {"coordinates":[84.27337,24.39234],"type":"Point"}
}