{
  "type": "Feature",
  "properties": {
    "gn:admin1_code":"2.0",
    "gn:admin2_code":"545.0",
    "gn:asciiname":"Narendrapuram",
    "gn:country_code":"IN",
    "gn:dem":44,
    "gn:feature_class":"P",
    "gn:feature_code":"PPL",
    "gn:name":"Narendrapuram",
    "gn:population":0,
    "gn:timezone":"Asia/Kolkata",
    "iso:country":"IN",
    "name:tel_x_preferred":[
        "\u0c28\u0c30\u0c47\u0c02\u0c26\u0c4d\u0c30\u0c2a\u0c41\u0c30\u0c02"
    ],
    "wof:name":"Narendrapuram",
    "wof:placetype":"locality"
},
  "geometry": {"coordinates":[81.88089000000002,17.09604],"type":"Point"}
}