{
  "type": "Feature",
  "properties": {
    "iso:country":"IN",
    "ks:ks_name":"Bitra",
    "ks:ks_type":"VILLAGE",
    "name:eng_x_preferred":[
        "Bitra"
    ],
    "wof:name":"Bitra",
    "wof:placetype":"locality"
},
  "geometry": {"coordinates":[72.185597,11.598277],"type":"Point"}
}