{
  "type": "Feature",
  "properties": {
    "iso:country":"IN",
    "ks:ks_name":"Kathhava",
    "ks:ks_pop":55,
    "ks:ks_type":"HABITATION",
    "ks:ks_uagg_main":0,
    "name:eng_x_preferred":[
        "Kathhava"
    ],
    "wof:name":"Kathhava",
    "wof:placetype":"neighbourhood",
    "wof:population":55
},
  "geometry": {"coordinates":[83.221975,27.245924],"type":"Point"}
}