{
  "type": "Feature",
  "properties": {
    "iso:country":"IN",
    "ks:ks_name":"Tanda Barri",
    "ks:ks_pop":0,
    "ks:ks_type":"VILLAGE",
    "name:eng_x_preferred":[
        "Tanda Barri"
    ],
    "wof:name":"Tanda Barri",
    "wof:placetype":"locality",
    "wof:population":0
},
  "geometry": {"coordinates":[77.250229,23.900896],"type":"Point"}
}