{
  "type": "Feature",
  "properties": {
    "gn:admin1_code":"37",
    "gn:admin2_code":"406.0",
    "gn:asciiname":"Amaru",
    "gn:country_code":"IN",
    "gn:dem":580,
    "gn:feature_class":"P",
    "gn:feature_code":"PPL",
    "gn:name":"Am\u0101ru",
    "gn:population":0,
    "gn:timezone":"Asia/Kolkata",
    "iso:country":"IN",
    "ks:ks_alt_nam":"Am\u0101ru",
    "ks:ks_name":"Amaru",
    "ks:ks_type":"VILLAGE",
    "name:ceb_x_preferred":[
        "Amaru"
    ],
    "name:eng_x_preferred":[
        "Amaru"
    ],
    "name:eng_x_variant":[
        "Am\u0101ru"
    ],
    "name:jpn_x_preferred":[
        "\u30a2\u30de\u30eb"
    ],
    "name:ron_x_preferred":[
        "Amaru"
    ],
    "name:rus_x_preferred":[
        "\u0410\u043c\u0430\u0440\u0443"
    ],
    "name:spa_x_preferred":[
        "Amaru"
    ],
    "name:tur_x_preferred":[
        "Amaru"
    ],
    "name:ukr_x_preferred":[
        "\u0410\u043c\u0430\u0440\u0443"
    ],
    "name:vie_x_preferred":[
        "Amaru"
    ],
    "wof:name":"Amaru",
    "wof:placetype":"locality"
},
  "geometry": {"coordinates":[82.08888899999999,22.751221],"type":"Point"}
}