{
  "type": "Feature",
  "properties": {
    "iso:country":"IN",
    "ks:ks_name":"Chekkal Kadavu South",
    "ks:ks_pop":2048,
    "ks:ks_type":"HABITATION",
    "name:eng_x_preferred":[
        "Chekkal Kadavu South"
    ],
    "wof:name":"Chekkal Kadavu South",
    "wof:placetype":"locality",
    "wof:population":2048
},
  "geometry": {"coordinates":[76.657921,9.027788],"type":"Point"}
}