{
  "type": "Feature",
  "properties": {
    "iso:country":"IN",
    "ks:ks_name":"Baladhadi",
    "ks:ks_pop":320,
    "ks:ks_type":"VILLAGE",
    "name:eng_x_preferred":[
        "Baladhadi"
    ],
    "wof:name":"Baladhadi",
    "wof:placetype":"locality",
    "wof:population":320
},
  "geometry": {"coordinates":[85.45695000000001,20.081769],"type":"Point"}
}