{
  "type": "Feature",
  "properties": {
    "iso:country":"IN",
    "ks:ks_name":"Manupur Manjhan",
    "ks:ks_pop":1228,
    "ks:ks_type":"VILLAGE",
    "ks:ks_uagg_main":0,
    "name:eng_x_preferred":[
        "Manupur Manjhan"
    ],
    "wof:name":"Manupur Manjhan",
    "wof:placetype":"locality",
    "wof:population":1228
},
  "geometry": {"coordinates":[84.84622299999999,25.752477],"type":"Point"}
}