{
  "type": "Feature",
  "properties": {
    "iso:country":"IN",
    "ks:ks_name":"Telkot",
    "ks:ks_pop":12,
    "ks:ks_type":"VILLAGE",
    "name:eng_x_preferred":[
        "Telkot"
    ],
    "wof:name":"Telkot",
    "wof:placetype":"locality",
    "wof:population":12
},
  "geometry": {"coordinates":[80.25764100000001,30.084723],"type":"Point"}
}