{
  "type": "Feature",
  "properties": {
    "iso:country":"IN",
    "ks:ks_alt_nam":"Tilka grant",
    "ks:ks_name":"Tilka Grant",
    "ks:ks_pop":1674,
    "ks:ks_type":"HABITATION",
    "name:eng_x_preferred":[
        "Tilka Grant"
    ],
    "wof:name":"Tilka Grant",
    "wof:placetype":"locality",
    "wof:population":1674
},
  "geometry": {"coordinates":[93.005116,24.744407],"type":"Point"}
}