{
  "type": "Feature",
  "properties": {
    "iso:country":"IN",
    "ks:ks_name":"Manikunda",
    "ks:ks_pop":1714,
    "ks:ks_type":"VILLAGE",
    "name:eng_x_preferred":[
        "Manikunda"
    ],
    "wof:name":"Manikunda",
    "wof:placetype":"locality",
    "wof:population":1714
},
  "geometry": {"coordinates":[86.46114799999999,20.441733],"type":"Point"}
}