{
  "type": "Feature",
  "properties": {
    "iso:country":"IN",
    "ks:ks_name":"Chakhiramoni",
    "ks:ks_pop":496,
    "ks:ks_type":"HABITATION",
    "name:eng_x_preferred":[
        "Chakhiramoni"
    ],
    "wof:name":"Chakhiramoni",
    "wof:placetype":"locality",
    "wof:population":496
},
  "geometry": {"coordinates":[87.63018700000001,22.511404],"type":"Point"}
}