{
  "type": "Feature",
  "properties": {
    "iso:country":"IN",
    "ks:ks_name":"Bachchakuhi Raiyat",
    "ks:ks_pop":75,
    "ks:ks_type":"HABITATION",
    "name:eng_x_preferred":[
        "Bachchakuhi Raiyat"
    ],
    "wof:name":"Bachchakuhi Raiyat",
    "wof:placetype":"locality",
    "wof:population":75
},
  "geometry": {"coordinates":[79.128721,21.825983],"type":"Point"}
}