{
  "type": "Feature",
  "properties": {
    "gn:admin1_code":"34.0",
    "gn:admin2_code":"236.0",
    "gn:asciiname":"Kazi Bigha",
    "gn:country_code":"IN",
    "gn:dem":118,
    "gn:feature_class":"P",
    "gn:feature_code":"PPL",
    "gn:name":"K\u0101zi Bigha",
    "gn:population":0,
    "gn:timezone":"Asia/Kolkata",
    "iso:country":"IN",
    "ks:ks_name":"Kaji Bigha",
    "ks:ks_pop":269,
    "ks:ks_type":"VILLAGE",
    "name:eng_x_preferred":[
        "Kaji Bigha"
    ],
    "name:eng_x_variant":[
        "Kazi Bigha"
    ],
    "wof:name":"Kaji Bigha",
    "wof:placetype":"locality",
    "wof:population":269
},
  "geometry": {"coordinates":[85.12997,24.720934],"type":"Point"}
}