{
  "type": "Feature",
  "properties": {
    "iso:country":"IN",
    "ks:ks_name":"Parakkulambu",
    "ks:ks_pop":785,
    "ks:ks_type":"HABITATION",
    "ks:ks_uagg_main":0,
    "name:eng_x_preferred":[
        "Parakkulambu"
    ],
    "wof:name":"Parakkulambu",
    "wof:placetype":"neighbourhood",
    "wof:population":785
},
  "geometry": {"coordinates":[76.748969,10.633717],"type":"Point"}
}