{
  "type": "Feature",
  "properties": {
    "gn:admin1_code":"36.0",
    "gn:admin2_code":"150.0",
    "gn:asciiname":"Kairua",
    "gn:country_code":"IN",
    "gn:dem":167,
    "gn:feature_class":"P",
    "gn:feature_code":"PPL",
    "gn:name":"Kairua",
    "gn:population":0,
    "gn:timezone":"Asia/Kolkata",
    "iso:country":"IN",
    "ks:ks_name":"Kairua",
    "ks:ks_type":"VILLAGE",
    "name:eng_x_preferred":[
        "Kairua"
    ],
    "wof:name":"Kairua",
    "wof:placetype":"locality"
},
  "geometry": {"coordinates":[79.605144,28.222795],"type":"Point"}
}