{
  "type": "Feature",
  "properties": {
    "iso:country":"IN",
    "qs:name":"Nemam",
    "qs:name_adm0":"India",
    "qs:name_adm1":"Kerala",
    "qs:photos":250,
    "qs:photos_1k":51,
    "qs:photos_9k":1,
    "qs:photos_9r":4,
    "qs:photos_all":250,
    "qs:photos_sr":4,
    "qs:placetype":"Town",
    "qs:pop_sr":"0",
    "wd:wordcount":26,
    "wof:name":"Nemam",
    "wof:placetype":"locality"
},
  "geometry": {"coordinates":[76.971706,8.401251],"type":"Point"}
}