{
  "type": "Feature",
  "properties": {
    "gn:admin1_code":"9.0",
    "gn:admin2_code":"468.0",
    "gn:asciiname":"Kidianagaru",
    "gn:country_code":"IN",
    "gn:dem":83,
    "gn:feature_class":"P",
    "gn:feature_code":"PPL",
    "gn:name":"Kidi\u0101nagaru",
    "gn:population":0,
    "gn:timezone":"Asia/Kolkata",
    "iso:country":"IN",
    "wof:name":"Kidianagaru",
    "wof:placetype":"locality"
},
  "geometry": {"coordinates":[70.77804,23.47828],"type":"Point"}
}