{
  "type": "Feature",
  "properties": {
    "gn:admin1_code":"34.0",
    "gn:admin2_code":"227.0",
    "gn:asciiname":"Lai",
    "gn:country_code":"IN",
    "gn:dem":52,
    "gn:feature_class":"P",
    "gn:feature_code":"PPL",
    "gn:name":"Lai",
    "gn:population":0,
    "gn:timezone":"Asia/Kolkata",
    "iso:country":"IN",
    "name:deu_x_preferred":[
        "Lai"
    ],
    "name:est_x_preferred":[
        "Lai"
    ],
    "name:fra_x_preferred":[
        "Lai"
    ],
    "name:nld_x_preferred":[
        "Lai"
    ],
    "name:nor_x_preferred":[
        "Lai"
    ],
    "name:por_x_preferred":[
        "Lai"
    ],
    "name:rus_x_preferred":[
        "\u041b\u0430\u0439"
    ],
    "name:spa_x_preferred":[
        "Lai"
    ],
    "wof:name":"Lai",
    "wof:placetype":"locality"
},
  "geometry": {"coordinates":[86.19734,25.15969],"type":"Point"}
}