{
  "type": "Feature",
  "properties": {
    "iso:country":"IN",
    "ks:ks_name":"Kharakuva",
    "ks:ks_pop":267,
    "ks:ks_type":"HABITATION",
    "name:eng_x_preferred":[
        "Kharakuva"
    ],
    "wof:name":"Kharakuva",
    "wof:placetype":"locality",
    "wof:population":267
},
  "geometry": {"coordinates":[70.597364,23.549833],"type":"Point"}
}