{
  "type": "Feature",
  "properties": {
    "gn:admin1_code":"36",
    "gn:admin2_code":"191.0",
    "gn:asciiname":"Gaddopur",
    "gn:country_code":"IN",
    "gn:dem":88,
    "gn:feature_class":"P",
    "gn:feature_code":"PPL",
    "gn:name":"Gaddopur",
    "gn:population":0,
    "gn:timezone":"Asia/Kolkata",
    "iso:country":"IN",
    "name:hin_x_preferred":[
        "\u0917\u0926\u094d\u0926\u094b\u092a\u0941\u0930"
    ],
    "wof:name":"Gaddopur",
    "wof:placetype":"locality"
},
  "geometry": {"coordinates":[82.77760000000001,26.15227],"type":"Point"}
}