{
  "type": "Feature",
  "properties": {
    "gn:admin1_code":"25.0",
    "gn:admin2_code":"627.0",
    "gn:asciiname":"Mudalur",
    "gn:country_code":"IN",
    "gn:dem":16,
    "gn:feature_class":"P",
    "gn:feature_code":"PPL",
    "gn:name":"Mudalur",
    "gn:population":0,
    "gn:timezone":"Asia/Kolkata",
    "iso:country":"IN",
    "wof:name":"Mudalur",
    "wof:placetype":"locality"
},
  "geometry": {"coordinates":[77.94929,8.41894],"type":"Point"}
}