{
  "type": "Feature",
  "properties": {
    "iso:country":"IN",
    "ks:ks_name":"Kalewangpara",
    "ks:ks_pop":344,
    "ks:ks_type":"HABITATION",
    "name:eng_x_preferred":[
        "Kalewangpara"
    ],
    "wof:name":"Kalewangpara",
    "wof:placetype":"locality",
    "wof:population":344
},
  "geometry": {"coordinates":[81.899517,18.536698],"type":"Point"}
}