{
  "type": "Feature",
  "properties": {
    "iso:country":"IN",
    "ks:ks_name":"Samuguri",
    "ks:ks_pop":452,
    "ks:ks_type":"HABITATION",
    "name:eng_x_preferred":[
        "Samuguri"
    ],
    "wof:name":"Samuguri",
    "wof:placetype":"locality",
    "wof:population":452
},
  "geometry": {"coordinates":[94.867547,27.063063],"type":"Point"}
}