{
  "type": "Feature",
  "properties": {
    "iso:country":"IN",
    "ks:ks_name":"Laxmi Nagar",
    "ks:ks_pop":200,
    "ks:ks_type":"HABITATION",
    "name:eng_x_preferred":[
        "Laxmi Nagar"
    ],
    "wof:name":"Laxmi Nagar",
    "wof:placetype":"locality",
    "wof:population":200
},
  "geometry": {"coordinates":[74.827326,16.532392],"type":"Point"}
}