{
  "type": "Feature",
  "properties": {
    "gn:admin1_code":"40",
    "gn:admin2_code":"538.0",
    "gn:asciiname":"Avusulonipalli",
    "gn:country_code":"IN",
    "gn:dem":549,
    "gn:feature_class":"P",
    "gn:feature_code":"PPL",
    "gn:name":"Avusulonipalli",
    "gn:population":0,
    "gn:timezone":"Asia/Kolkata",
    "iso:country":"IN",
    "wof:name":"Avusulonipalli",
    "wof:placetype":"locality"
},
  "geometry": {"coordinates":[77.53565999999999,16.87513],"type":"Point"}
}