{
  "type": "Feature",
  "properties": {
    "gn:admin1_code":"39.0",
    "gn:admin2_code":"60.0",
    "gn:asciiname":"Simiand",
    "gn:country_code":"IN",
    "gn:dem":1008,
    "gn:feature_class":"P",
    "gn:feature_code":"PPL",
    "gn:name":"Simiand",
    "gn:population":0,
    "gn:timezone":"Asia/Kolkata",
    "iso:country":"IN",
    "ks:ks_name":"Simiand",
    "ks:ks_type":"VILLAGE",
    "name:eng_x_preferred":[
        "Simiand"
    ],
    "wof:name":"Simiand",
    "wof:placetype":"locality"
},
  "geometry": {"coordinates":[78.20868400000001,30.265422],"type":"Point"}
}