{
  "type": "Feature",
  "properties": {
    "iso:country":"IN",
    "ks:ks_name":"Cheekupanasa",
    "ks:ks_pop":53,
    "ks:ks_type":"VILLAGE",
    "name:eng_x_preferred":[
        "Cheekupanasa"
    ],
    "wof:name":"Cheekupanasa",
    "wof:placetype":"locality",
    "wof:population":53
},
  "geometry": {"coordinates":[82.806428,17.977799],"type":"Point"}
}