{
  "type": "Feature",
  "properties": {
    "iso:country":"IN",
    "ks:ks_name":"Argupura",
    "ks:ks_pop":0,
    "ks:ks_type":"VILLAGE",
    "name:eng_x_preferred":[
        "Argupura"
    ],
    "wof:name":"Argupura",
    "wof:placetype":"locality",
    "wof:population":0
},
  "geometry": {"coordinates":[78.28948800000001,29.482781],"type":"Point"}
}