{
  "type": "Feature",
  "properties": {
    "iso:country":"IN",
    "ks:ks_name":"Titona",
    "ks:ks_pop":19,
    "ks:ks_type":"VILLAGE",
    "name:eng_x_preferred":[
        "Titona"
    ],
    "wof:name":"Titona",
    "wof:placetype":"locality",
    "wof:population":19
},
  "geometry": {"coordinates":[78.30909800000001,21.006223],"type":"Point"}
}