{
  "type": "Feature",
  "properties": {
    "iso:country":"IN",
    "ks:ks_alt_nam":"MURIARI TOLA",
    "ks:ks_name":"Muriari Tola",
    "ks:ks_pop":341,
    "ks:ks_type":"HABITATION",
    "ks:ks_uagg_main":0,
    "name:eng_x_preferred":[
        "Muriari Tola"
    ],
    "wof:name":"Muriari Tola",
    "wof:placetype":"locality",
    "wof:population":341
},
  "geometry": {"coordinates":[87.44918800000001,25.73494],"type":"Point"}
}