{
  "type": "Feature",
  "properties": {
    "iso:country":"IN",
    "ks:ks_alt_nam":"JHAPATTOLI",
    "ks:ks_name":"Jhapattoli",
    "ks:ks_pop":278,
    "ks:ks_type":"HABITATION",
    "name:eng_x_preferred":[
        "Jhapattoli"
    ],
    "wof:name":"Jhapattoli",
    "wof:placetype":"locality",
    "wof:population":278
},
  "geometry": {"coordinates":[83.79841,22.377696],"type":"Point"}
}