{
  "type": "Feature",
  "properties": {
    "iso:country":"IN",
    "ks:ks_name":"Kerajharia",
    "ks:ks_pop":156,
    "ks:ks_type":"VILLAGE",
    "name:eng_x_preferred":[
        "Kerajharia"
    ],
    "wof:name":"Kerajharia",
    "wof:placetype":"locality",
    "wof:population":156
},
  "geometry": {"coordinates":[82.50783199999999,23.36621],"type":"Point"}
}