{
  "type": "Feature",
  "properties": {
    "iso:country":"IN",
    "ks:ks_name":"Bypalle",
    "ks:ks_pop":1455,
    "ks:ks_type":"VILLAGE",
    "ks:ks_uagg_main":0,
    "name:eng_x_preferred":[
        "Bypalle"
    ],
    "wof:name":"Bypalle",
    "wof:placetype":"neighbourhood",
    "wof:population":1455
},
  "geometry": {"coordinates":[84.484347,18.749191],"type":"Point"}
}