{
  "type": "Feature",
  "properties": {
    "iso:country":"IN",
    "ks:ks_name":"Ahirwas",
    "ks:ks_pop":331,
    "ks:ks_type":"HABITATION",
    "name:eng_x_preferred":[
        "Ahirwas"
    ],
    "wof:name":"Ahirwas",
    "wof:placetype":"locality",
    "wof:population":331
},
  "geometry": {"coordinates":[72.95627500000001,20.92675],"type":"Point"}
}