{
  "type": "Feature",
  "properties": {
    "iso:country":"IN",
    "ks:ks_name":"Bogajamin",
    "ks:ks_pop":174,
    "ks:ks_type":"HABITATION",
    "name:eng_x_preferred":[
        "Bogajamin"
    ],
    "wof:name":"Bogajamin",
    "wof:placetype":"locality",
    "wof:population":174
},
  "geometry": {"coordinates":[92.35499,26.007535],"type":"Point"}
}