{
  "type": "Feature",
  "properties": {
    "gn:admin1_code":"25",
    "gn:admin2_code":"605.0",
    "gn:asciiname":"Patchur",
    "gn:country_code":"IN",
    "gn:dem":501,
    "gn:feature_class":"P",
    "gn:feature_code":"PPL",
    "gn:name":"Patch\u016br",
    "gn:population":0,
    "gn:timezone":"Asia/Kolkata",
    "iso:country":"IN",
    "ks:ks_name":"Patchur",
    "ks:ks_pop":2297,
    "ks:ks_type":"HABITATION",
    "ks:ks_uagg_main":0,
    "name:eng_x_preferred":[
        "Patchur"
    ],
    "name:und_x_variant":[
        "Pachur",
        "Patch\u016br"
    ],
    "wof:name":"Patchur",
    "wof:placetype":"neighbourhood",
    "wof:population":2297
},
  "geometry": {"coordinates":[78.4627,12.593426],"type":"Point"}
}