{
  "type": "Feature",
  "properties": {
    "gn:admin1_code":"9.0",
    "gn:admin2_code":"480",
    "gn:asciiname":"Dharabandar",
    "gn:country_code":"IN",
    "gn:dem":8,
    "gn:feature_class":"P",
    "gn:feature_code":"PPL",
    "gn:name":"Dh\u0101r\u0101bandar",
    "gn:population":0,
    "gn:timezone":"Asia/Kolkata",
    "iso:country":"IN",
    "wof:name":"Dharabandar",
    "wof:placetype":"locality"
},
  "geometry": {"coordinates":[71.22975,20.81465],"type":"Point"}
}