{
  "type": "Feature",
  "properties": {
    "iso:country":"IN",
    "ks:ks_name":"Khopifata",
    "ks:ks_pop":284,
    "ks:ks_type":"HABITATION",
    "ks:ks_uagg_main":0,
    "name:eng_x_preferred":[
        "Khopifata"
    ],
    "wof:name":"Khopifata",
    "wof:placetype":"neighbourhood",
    "wof:population":284
},
  "geometry": {"coordinates":[73.411625,17.710747],"type":"Point"}
}