{
  "type": "Feature",
  "properties": {
    "iso:country":"IN",
    "ks:ks_name":"Bandhanvadi",
    "ks:ks_pop":290,
    "ks:ks_type":"HABITATION",
    "name:eng_x_preferred":[
        "Bandhanvadi"
    ],
    "wof:name":"Bandhanvadi",
    "wof:placetype":"locality",
    "wof:population":290
},
  "geometry": {"coordinates":[73.154049,19.119328],"type":"Point"}
}