{
  "type": "Feature",
  "properties": {
    "iso:country":"IN",
    "ks:ks_alt_nam":"PURA SHIWA",
    "ks:ks_name":"Pura Shiwa",
    "ks:ks_pop":357,
    "ks:ks_type":"HABITATION",
    "name:eng_x_preferred":[
        "Pura Shiwa"
    ],
    "wof:name":"Pura Shiwa",
    "wof:placetype":"locality",
    "wof:population":357
},
  "geometry": {"coordinates":[81.581872,26.557172],"type":"Point"}
}