{
  "type": "Feature",
  "properties": {
    "iso:country":"IN",
    "ks:ks_alt_nam":"Sakru tanda",
    "ks:ks_name":"Sakru Tanda",
    "ks:ks_pop":270,
    "ks:ks_type":"HABITATION",
    "name:eng_x_preferred":[
        "Sakru Tanda"
    ],
    "wof:name":"Sakru Tanda",
    "wof:placetype":"locality",
    "wof:population":270
},
  "geometry": {"coordinates":[78.014465,16.479757],"type":"Point"}
}