{
  "type": "Feature",
  "properties": {
    "iso:country":"IN",
    "ks:ks_name":"S C Colony Avarse",
    "ks:ks_pop":70,
    "ks:ks_type":"HABITATION",
    "name:eng_x_preferred":[
        "S C Colony Avarse"
    ],
    "wof:name":"S C Colony Avarse",
    "wof:placetype":"locality",
    "wof:population":70
},
  "geometry": {"coordinates":[74.864693,13.531947],"type":"Point"}
}