{
  "type": "Feature",
  "properties": {
    "iso:country":"IN",
    "ks:ks_name":"Kaliakuva",
    "ks:ks_pop":86,
    "ks:ks_type":"HABITATION",
    "name:eng_x_preferred":[
        "Kaliakuva"
    ],
    "wof:name":"Kaliakuva",
    "wof:placetype":"locality",
    "wof:population":86
},
  "geometry": {"coordinates":[73.905917,22.591778],"type":"Point"}
}