{
  "type": "Feature",
  "properties": {
    "iso:country":"IN",
    "ks:ks_name":"Kariguda",
    "ks:ks_pop":347,
    "ks:ks_type":"HABITATION",
    "name:eng_x_preferred":[
        "Kariguda"
    ],
    "wof:name":"Kariguda",
    "wof:placetype":"locality",
    "wof:population":347
},
  "geometry": {"coordinates":[83.877906,18.737694],"type":"Point"}
}