{
  "type": "Feature",
  "properties": {
    "gn:admin1_code":"12.0",
    "gn:admin2_code":"18.0",
    "gn:asciiname":"Rale",
    "gn:country_code":"IN",
    "gn:dem":2684,
    "gn:feature_class":"P",
    "gn:feature_code":"PPL",
    "gn:name":"R\u0101l\u0113",
    "gn:population":0,
    "gn:timezone":"Asia/Kolkata",
    "iso:country":"IN",
    "wof:name":"Rale",
    "wof:placetype":"locality"
},
  "geometry": {"coordinates":[75.91701999999999,33.32174000000001],"type":"Point"}
}