{
  "type": "Feature",
  "properties": {
    "iso:country":"IN",
    "ks:ks_name":"Bingeppanahalli",
    "ks:ks_pop":50,
    "ks:ks_type":"HABITATION",
    "name:eng_x_preferred":[
        "Bingeppanahalli"
    ],
    "wof:name":"Bingeppanahalli",
    "wof:placetype":"locality",
    "wof:population":50
},
  "geometry": {"coordinates":[75.973,16.5175],"type":"Point"}
}