{
  "type": "Feature",
  "properties": {
    "iso:country":"IN",
    "ks:ks_name":"Champa Beri",
    "ks:ks_pop":514,
    "ks:ks_type":"VILLAGE",
    "name:eng_x_preferred":[
        "Champa Beri"
    ],
    "wof:name":"Champa Beri",
    "wof:placetype":"locality",
    "wof:population":514
},
  "geometry": {"coordinates":[72.213927,25.997037],"type":"Point"}
}