{
  "type": "Feature",
  "properties": {
    "gn:admin1_code":"12.0",
    "gn:admin2_code":"001",
    "gn:asciiname":"Chail",
    "gn:country_code":"IN",
    "gn:dem":1725,
    "gn:feature_class":"P",
    "gn:feature_code":"PPL",
    "gn:name":"Ch\u0101il",
    "gn:population":0,
    "gn:timezone":"Asia/Kolkata",
    "iso:country":"IN",
    "name:ceb_x_preferred":[
        "Chail"
    ],
    "name:nld_x_preferred":[
        "Chail"
    ],
    "name:pol_x_preferred":[
        "Chail"
    ],
    "name:swe_x_preferred":[
        "Chail"
    ],
    "wof:name":"Chail",
    "wof:placetype":"locality"
},
  "geometry": {"coordinates":[74.30554000000002,34.49537],"type":"Point"}
}