{
  "type": "Feature",
  "properties": {
    "iso:country":"IN",
    "ks:ks_name":"Shivanagar",
    "ks:ks_pop":1906,
    "ks:ks_type":"HABITATION",
    "name:eng_x_preferred":[
        "Shivanagar"
    ],
    "wof:name":"Shivanagar",
    "wof:placetype":"locality",
    "wof:population":1906
},
  "geometry": {"coordinates":[75.401979,14.727483],"type":"Point"}
}