{
  "type": "Feature",
  "properties": {
    "iso:country":"IN",
    "ks:ks_name":"5 SDR",
    "ks:ks_pop":12,
    "ks:ks_type":"VILLAGE",
    "name:eng_x_preferred":[
        "5 SDR"
    ],
    "wof:name":"5 SDR",
    "wof:placetype":"locality",
    "wof:population":12
},
  "geometry": {"coordinates":[75.1996,29.238728],"type":"Point"}
}