{
  "type": "Feature",
  "properties": {
    "iso:country":"IN",
    "ks:ks_name":"Rampudi",
    "ks:ks_pop":119,
    "ks:ks_type":"VILLAGE",
    "name:eng_x_preferred":[
        "Rampudi"
    ],
    "wof:name":"Rampudi",
    "wof:placetype":"locality",
    "wof:population":119
},
  "geometry": {"coordinates":[84.97264300000001,19.779844],"type":"Point"}
}