{
  "type": "Feature",
  "properties": {
    "iso:country":"IN",
    "ks:ks_name":"Patra Samantasheik Para",
    "ks:ks_pop":943,
    "ks:ks_type":"HABITATION",
    "name:eng_x_preferred":[
        "Patra Samantasheik Para"
    ],
    "wof:name":"Patra Samantasheik Para",
    "wof:placetype":"locality",
    "wof:population":943
},
  "geometry": {"coordinates":[88.247033,22.335351],"type":"Point"}
}