{
  "type": "Feature",
  "properties": {
    "iso:country":"IN",
    "ks:ks_name":"Bhagat Fa",
    "ks:ks_pop":828,
    "ks:ks_type":"HABITATION",
    "name:eng_x_preferred":[
        "Bhagat Fa"
    ],
    "wof:name":"Bhagat Fa",
    "wof:placetype":"locality",
    "wof:population":828
},
  "geometry": {"coordinates":[72.996194,20.339194],"type":"Point"}
}