{
  "type": "Feature",
  "properties": {
    "iso:country":"IN",
    "ks:ks_name":"Uska",
    "ks:ks_pop":3375,
    "ks:ks_type":"VILLAGE",
    "ks:ks_uagg_main":0,
    "name:eng_x_preferred":[
        "Uska"
    ],
    "wof:name":"Uska",
    "wof:placetype":"neighbourhood",
    "wof:population":3375
},
  "geometry": {"coordinates":[83.966919,26.360494],"type":"Point"}
}