{
  "type": "Feature",
  "properties": {
    "iso:country":"IN",
    "ks:ks_alt_nam":"UTTAR TOLA",
    "ks:ks_name":"Uttar Tola",
    "ks:ks_pop":400,
    "ks:ks_type":"HABITATION",
    "name:eng_x_preferred":[
        "Uttar Tola"
    ],
    "wof:name":"Uttar Tola",
    "wof:placetype":"locality",
    "wof:population":400
},
  "geometry": {"coordinates":[86.723614,25.553801],"type":"Point"}
}