{
  "type": "Feature",
  "properties": {
    "iso:country":"IN",
    "ks:ks_alt_nam":"Thathanur ADC",
    "ks:ks_name":"Thathanur Adc",
    "ks:ks_pop":334,
    "ks:ks_type":"HABITATION",
    "name:eng_x_preferred":[
        "Thathanur Adc"
    ],
    "wof:name":"Thathanur Adc",
    "wof:placetype":"locality",
    "wof:population":334
},
  "geometry": {"coordinates":[79.098817,11.862414],"type":"Point"}
}