{
  "type": "Feature",
  "properties": {
    "iso:country":"IN",
    "ks:ks_alt_nam":"NARGADBASA",
    "ks:ks_name":"Nargadbasa",
    "ks:ks_pop":169,
    "ks:ks_type":"HABITATION",
    "name:eng_x_preferred":[
        "Nargadbasa"
    ],
    "wof:name":"Nargadbasa",
    "wof:placetype":"locality",
    "wof:population":169
},
  "geometry": {"coordinates":[85.92234500000001,22.358585],"type":"Point"}
}