{
  "type": "Feature",
  "properties": {
    "iso:country":"IN",
    "ks:ks_alt_nam":"Aurang\u0101b\u0101d",
    "ks:ks_name":"Aurangabad",
    "ks:ks_type":"VILLAGE",
    "name:eng_x_preferred":[
        "Aurangabad"
    ],
    "name:eng_x_variant":[
        "Aurang\u0101b\u0101d"
    ],
    "name:hin_x_preferred":[
        "\u0914\u0930\u0902\u0917\u093e\u092c\u093e\u0926"
    ],
    "name:mar_x_preferred":[
        "\u0914\u0930\u0902\u0917\u093e\u092c\u093e\u0926"
    ],
    "wof:name":"Aurangabad",
    "wof:placetype":"locality"
},
  "geometry": {"coordinates":[83.195983,26.21864],"type":"Point"}
}