{
  "type": "Feature",
  "properties": {
    "gn:admin1_code":"2",
    "gn:admin2_code":"544.0",
    "gn:asciiname":"Ganugulu",
    "gn:country_code":"IN",
    "gn:dem":232,
    "gn:feature_class":"P",
    "gn:feature_code":"PPL",
    "gn:name":"G\u0101nugulu",
    "gn:population":0,
    "gn:timezone":"Asia/Kolkata",
    "iso:country":"IN",
    "ks:ks_name":"Ganugula",
    "ks:ks_pop":146,
    "ks:ks_type":"VILLAGE",
    "name:eng_x_preferred":[
        "Ganugula"
    ],
    "name:eng_x_variant":[
        "Ganugulu"
    ],
    "wof:name":"Ganugula",
    "wof:placetype":"locality",
    "wof:population":146
},
  "geometry": {"coordinates":[82.39614400000001,17.725128],"type":"Point"}
}