{
  "type": "Feature",
  "properties": {
    "iso:country":"IN",
    "ks:ks_alt_nam":"Putr\u0101r",
    "ks:ks_name":"Putrar",
    "ks:ks_pop":700,
    "ks:ks_type":"VILLAGE",
    "name:eng_x_preferred":[
        "Putrar"
    ],
    "name:eng_x_variant":[
        "Putr\u0101r"
    ],
    "wof:name":"Putrar",
    "wof:placetype":"locality",
    "wof:population":700
},
  "geometry": {"coordinates":[84.489366,23.547811],"type":"Point"}
}