{
  "type": "Feature",
  "properties": {
    "iso:country":"IN",
    "ks:ks_name":"Sodipur",
    "ks:ks_pop":305,
    "ks:ks_type":"VILLAGE",
    "name:eng_x_preferred":[
        "Sodipur"
    ],
    "wof:name":"Sodipur",
    "wof:placetype":"locality",
    "wof:population":305
},
  "geometry": {"coordinates":[79.76150800000001,21.495839],"type":"Point"}
}