{
  "type": "Feature",
  "properties": {
    "gn:admin1_code":"11",
    "gn:admin2_code":"23.0",
    "gn:asciiname":"Sainiaur",
    "gn:country_code":"IN",
    "gn:dem":1842,
    "gn:feature_class":"P",
    "gn:feature_code":"PPL",
    "gn:name":"Sainiaur",
    "gn:population":0,
    "gn:timezone":"Asia/Kolkata",
    "iso:country":"IN",
    "wof:name":"Sainiaur",
    "wof:placetype":"locality"
},
  "geometry": {"coordinates":[76.49639000000001,32.41335],"type":"Point"}
}