{
  "type": "Feature",
  "properties": {
    "iso:country":"IN",
    "ks:ks_name":"Jogaulia Tola Gulab Khan",
    "ks:ks_pop":2358,
    "ks:ks_type":"VILLAGE",
    "ks:ks_uagg_main":0,
    "name:eng_x_preferred":[
        "Jogaulia Tola Gulab Khan"
    ],
    "wof:name":"Jogaulia Tola Gulab Khan",
    "wof:placetype":"neighbourhood",
    "wof:population":2358
},
  "geometry": {"coordinates":[85.088036,26.458279],"type":"Point"}
}