{
  "type": "Feature",
  "properties": {
    "iso:country":"IN",
    "ks:ks_name":"Moti Sasad",
    "ks:ks_pop":190,
    "ks:ks_type":"HABITATION",
    "name:eng_x_preferred":[
        "Moti Sasad"
    ],
    "wof:name":"Moti Sasad",
    "wof:placetype":"locality",
    "wof:population":190
},
  "geometry": {"coordinates":[84.167252,25.493906],"type":"Point"}
}