{
  "type": "Feature",
  "properties": {
    "iso:country":"IN",
    "ks:ks_name":"Sakalpur",
    "ks:ks_pop":667,
    "ks:ks_type":"HABITATION",
    "name:eng_x_preferred":[
        "Sakalpur"
    ],
    "wof:name":"Sakalpur",
    "wof:placetype":"locality",
    "wof:population":667
},
  "geometry": {"coordinates":[92.395006,24.469295],"type":"Point"}
}