{
  "type": "Feature",
  "properties": {
    "iso:country":"IN",
    "ks:ks_name":"Mahadi Bigha",
    "ks:ks_pop":349,
    "ks:ks_type":"HABITATION",
    "name:eng_x_preferred":[
        "Mahadi Bigha"
    ],
    "wof:name":"Mahadi Bigha",
    "wof:placetype":"locality",
    "wof:population":349
},
  "geometry": {"coordinates":[85.039835,24.912689],"type":"Point"}
}