{
  "type": "Feature",
  "properties": {
    "gn:admin1_code":"35",
    "gn:admin2_code":"424.0",
    "gn:asciiname":"Mandri",
    "gn:country_code":"IN",
    "gn:dem":192,
    "gn:feature_class":"P",
    "gn:feature_code":"PPL",
    "gn:name":"M\u0101ndri",
    "gn:population":0,
    "gn:timezone":"Asia/Kolkata",
    "iso:country":"IN",
    "ks:ks_alt_nam":"M\u0101ndri",
    "ks:ks_name":"Mandri",
    "ks:ks_type":"VILLAGE",
    "name:eng_x_preferred":[
        "Mandri"
    ],
    "name:eng_x_variant":[
        "M\u0101ndri"
    ],
    "wof:name":"Mandri",
    "wof:placetype":"locality"
},
  "geometry": {"coordinates":[78.894738,25.527532],"type":"Point"}
}