{
  "type": "Feature",
  "properties": {
    "iso:country":"IN",
    "ks:ks_alt_nam":"Sh\u0101hnagar",
    "ks:ks_name":"Shahnagar",
    "ks:ks_type":"VILLAGE",
    "ks:ks_uagg_main":0,
    "name:eng_x_preferred":[
        "Shahnagar"
    ],
    "name:eng_x_variant":[
        "Sh\u0101hnagar"
    ],
    "wof:name":"Shahnagar",
    "wof:placetype":"locality"
},
  "geometry": {"coordinates":[78.057203,30.289809],"type":"Point"}
}