{
  "type": "Feature",
  "properties": {
    "gn:admin1_code":"2.0",
    "gn:admin2_code":"554.0",
    "gn:asciiname":"Ketumalmaharajupuram",
    "gn:country_code":"IN",
    "gn:dem":191,
    "gn:feature_class":"P",
    "gn:feature_code":"PPL",
    "gn:name":"Ketum\u0101lmah\u0101rajupuram",
    "gn:population":0,
    "gn:timezone":"Asia/Kolkata",
    "iso:country":"IN",
    "wof:name":"Ketumalmaharajupuram",
    "wof:placetype":"locality"
},
  "geometry": {"coordinates":[79.45517,13.38431],"type":"Point"}
}