{
  "type": "Feature",
  "properties": {
    "iso:country":"IN",
    "ks:ks_alt_nam":"MORKAHI",
    "ks:ks_name":"Morkahi",
    "ks:ks_pop":1777,
    "ks:ks_type":"HABITATION",
    "name:eng_x_preferred":[
        "Morkahi"
    ],
    "wof:name":"Morkahi",
    "wof:placetype":"locality",
    "wof:population":1777
},
  "geometry": {"coordinates":[86.402147,25.670552],"type":"Point"}
}