{
  "type": "Feature",
  "properties": {
    "gn:admin1_code":"36.0",
    "gn:admin2_code":"179.0",
    "gn:asciiname":"Fatehpur",
    "gn:country_code":"IN",
    "gn:dem":112,
    "gn:feature_class":"P",
    "gn:feature_code":"PPL",
    "gn:name":"Fatehpur",
    "gn:population":0,
    "gn:timezone":"Asia/Kolkata",
    "iso:country":"IN",
    "wof:name":"Fatehpur",
    "wof:placetype":"locality"
},
  "geometry": {"coordinates":[81.60014,26.55706],"type":"Point"}
}