{
  "type": "Feature",
  "properties": {
    "iso:country":"IN",
    "ks:ks_name":"Barsal Nagar",
    "ks:ks_pop":71,
    "ks:ks_type":"HABITATION",
    "name:eng_x_preferred":[
        "Barsal Nagar"
    ],
    "wof:name":"Barsal Nagar",
    "wof:placetype":"locality",
    "wof:population":71
},
  "geometry": {"coordinates":[71.693117,27.590933],"type":"Point"}
}