{
  "type": "Feature",
  "properties": {
    "iso:country":"IN",
    "ks:ks_name":"Jalalpur Derapur",
    "ks:ks_pop":698,
    "ks:ks_type":"VILLAGE",
    "name:eng_x_preferred":[
        "Jalalpur Derapur"
    ],
    "wof:name":"Jalalpur Derapur",
    "wof:placetype":"locality",
    "wof:population":698
},
  "geometry": {"coordinates":[79.671071,26.409852],"type":"Point"}
}