{
  "type": "Feature",
  "properties": {
    "gn:admin1_code":"24.0",
    "gn:admin2_code":"102",
    "gn:asciiname":"Bebra",
    "gn:country_code":"IN",
    "gn:dem":257,
    "gn:feature_class":"P",
    "gn:feature_code":"PPL",
    "gn:name":"Bebra",
    "gn:population":0,
    "gn:timezone":"Asia/Kolkata",
    "iso:country":"IN",
    "name:ara_x_preferred":[
        "\u0628\u064a\u0628\u0631\u0627"
    ],
    "name:azb_x_preferred":[
        "\u0628\u0628\u0631\u0627"
    ],
    "name:bel_x_preferred":[
        "\u0411\u0435\u0431\u0440\u0430"
    ],
    "name:ceb_x_preferred":[
        "Bebra"
    ],
    "name:deu_x_preferred":[
        "Bebra"
    ],
    "name:epo_x_preferred":[
        "Bebra"
    ],
    "name:fas_x_preferred":[
        "\u0628\u0628\u0631\u0627"
    ],
    "name:fin_x_preferred":[
        "Bebra"
    ],
    "name:fra_x_preferred":[
        "Bebra"
    ],
    "name:hun_x_preferred":[
        "Bebra"
    ],
    "name:ita_x_preferred":[
        "Bebra"
    ],
    "name:jpn_x_preferred":[
        "\u30d9\u30fc\u30d6\u30e9"
    ],
    "name:kaz_x_preferred":[
        "\u0411\u0435\u0431\u0440\u0430"
    ],
    "name:kir_x_preferred":[
        "\u0411\u0435\u0431\u0440\u0430"
    ],
    "name:lat_x_preferred":[
        "Byvera"
    ],
    "name:msa_x_preferred":[
        "Bebra"
    ],
    "name:nld_x_preferred":[
        "Bebra"
    ],
    "name:pol_x_preferred":[
        "Bebra"
    ],
    "name:ron_x_preferred":[
        "Bebra"
    ],
    "name:rus_x_preferred":[
        "\u0411\u0435\u0431\u0440\u0430"
    ],
    "name:spa_x_preferred":[
        "Bebra"
    ],
    "name:srp_x_preferred":[
        "\u0411\u0435\u0431\u0440\u0430"
    ],
    "name:tur_x_preferred":[
        "Bebra"
    ],
    "name:ukr_x_preferred":[
        "\u0411\u0435\u0431\u0440\u0430"
    ],
    "name:uzb_x_preferred":[
        "Bebra"
    ],
    "name:vol_x_preferred":[
        "Bebra"
    ],
    "name:war_x_preferred":[
        "Bebra"
    ],
    "name:zho_x_preferred":[
        "\u8d1d\u5e03\u62c9"
    ],
    "wof:name":"Bebra",
    "wof:placetype":"locality"
},
  "geometry": {"coordinates":[74.55806,28.46389000000001],"type":"Point"}
}