{
  "type": "Feature",
  "properties": {
    "iso:country":"IN",
    "ks:ks_name":"Kunnaru South",
    "ks:ks_pop":350,
    "ks:ks_type":"HABITATION",
    "ks:ks_uagg_main":0,
    "name:eng_x_preferred":[
        "Kunnaru South"
    ],
    "wof:name":"Kunnaru South",
    "wof:placetype":"neighbourhood",
    "wof:population":350
},
  "geometry": {"coordinates":[75.217676,12.05951],"type":"Point"}
}