{
  "type": "Feature",
  "properties": {
    "iso:country":"IN",
    "ks:ks_name":"Bahora",
    "ks:ks_type":"VILLAGE",
    "name:eng_x_preferred":[
        "Bahora"
    ],
    "wof:name":"Bahora",
    "wof:placetype":"locality"
},
  "geometry": {"coordinates":[83.404045,25.32507],"type":"Point"}
}