{
  "type": "Feature",
  "properties": {
    "iso:country":"IN",
    "ks:ks_name":"Ranidera",
    "ks:ks_pop":0,
    "ks:ks_type":"VILLAGE",
    "name:eng_x_preferred":[
        "Ranidera"
    ],
    "wof:name":"Ranidera",
    "wof:placetype":"locality",
    "wof:population":0
},
  "geometry": {"coordinates":[84.997967,23.142227],"type":"Point"}
}