{
  "type": "Feature",
  "properties": {
    "iso:country":"IN",
    "ks:ks_name":"Yadav Tola",
    "ks:ks_pop":217,
    "ks:ks_type":"HABITATION",
    "ks:ks_uagg_main":0,
    "name:eng_x_preferred":[
        "Yadav Tola"
    ],
    "wof:name":"Yadav Tola",
    "wof:placetype":"neighbourhood",
    "wof:population":217
},
  "geometry": {"coordinates":[83.237088,26.581078],"type":"Point"}
}