{
  "type": "Feature",
  "properties": {
    "gn:admin1_code":"35",
    "gn:admin2_code":"447.0",
    "gn:asciiname":"Ghorida",
    "gn:country_code":"IN",
    "gn:dem":380,
    "gn:feature_class":"P",
    "gn:feature_code":"PPL",
    "gn:name":"Ghor\u012bda",
    "gn:population":0,
    "gn:timezone":"Asia/Kolkata",
    "iso:country":"IN",
    "wof:name":"Ghorida",
    "wof:placetype":"locality"
},
  "geometry": {"coordinates":[77.27578000000003,21.74321],"type":"Point"}
}