{
  "type": "Feature",
  "properties": {
    "iso:country":"IN",
    "ks:ks_name":"Chittampadu",
    "ks:ks_pop":113,
    "ks:ks_type":"VILLAGE",
    "name:eng_x_preferred":[
        "Chittampadu"
    ],
    "wof:name":"Chittampadu",
    "wof:placetype":"locality",
    "wof:population":113
},
  "geometry": {"coordinates":[82.76490099999999,18.130819],"type":"Point"}
}