{
  "type": "Feature",
  "properties": {
    "gn:admin1_code":"34.0",
    "gn:admin2_code":"209.0",
    "gn:asciiname":"Paiktola",
    "gn:country_code":"IN",
    "gn:dem":47,
    "gn:feature_class":"P",
    "gn:feature_code":"PPL",
    "gn:name":"Paiktola",
    "gn:population":0,
    "gn:timezone":"Asia/Kolkata",
    "iso:country":"IN",
    "wof:name":"Paiktola",
    "wof:placetype":"locality"
},
  "geometry": {"coordinates":[87.46406999999998,26.01618],"type":"Point"}
}