{
  "type": "Feature",
  "properties": {
    "iso:country":"IN",
    "ks:ks_name":"Panikkarmoola End",
    "ks:ks_pop":305,
    "ks:ks_type":"HABITATION",
    "name:eng_x_preferred":[
        "Panikkarmoola End"
    ],
    "wof:name":"Panikkarmoola End",
    "wof:placetype":"locality",
    "wof:population":305
},
  "geometry": {"coordinates":[76.16381800000001,10.393145],"type":"Point"}
}