{
  "type": "Feature",
  "properties": {
    "iso:country":"IN",
    "ks:ks_name":"Ahilypura",
    "ks:ks_pop":169,
    "ks:ks_type":"HABITATION",
    "name:eng_x_preferred":[
        "Ahilypura"
    ],
    "wof:name":"Ahilypura",
    "wof:placetype":"locality",
    "wof:population":169
},
  "geometry": {"coordinates":[75.59837,22.418604],"type":"Point"}
}