{
  "type": "Feature",
  "properties": {
    "iso:country":"IN",
    "ks:ks_name":"Monsing Teron",
    "ks:ks_pop":314,
    "ks:ks_type":"HABITATION",
    "ks:ks_uagg_main":0,
    "name:eng_x_preferred":[
        "Monsing Teron"
    ],
    "wof:name":"Monsing Teron",
    "wof:placetype":"neighbourhood",
    "wof:population":314
},
  "geometry": {"coordinates":[93.80258499999999,26.18293],"type":"Point"}
}