{
  "type": "Feature",
  "properties": {
    "iso:country":"IN",
    "ks:ks_alt_nam":"BABIYAAV",
    "ks:ks_name":"Babiyaav",
    "ks:ks_pop":1464,
    "ks:ks_type":"HABITATION",
    "name:eng_x_preferred":[
        "Babiyaav"
    ],
    "wof:name":"Babiyaav",
    "wof:placetype":"locality",
    "wof:population":1464
},
  "geometry": {"coordinates":[83.034665,25.494964],"type":"Point"}
}