{
  "type": "Feature",
  "properties": {
    "iso:country":"IN",
    "ks:ks_alt_nam":"veemulapudi YC",
    "ks:ks_name":"Veemulapudi Yc",
    "ks:ks_pop":51,
    "ks:ks_type":"HABITATION",
    "name:eng_x_preferred":[
        "Veemulapudi Yc"
    ],
    "wof:name":"Veemulapudi Yc",
    "wof:placetype":"locality",
    "wof:population":51
},
  "geometry": {"coordinates":[79.704707,13.555012],"type":"Point"}
}