{
  "type": "Feature",
  "properties": {
    "iso:country":"IN",
    "ks:ks_name":"Chhoti Marpakala",
    "ks:ks_pop":430,
    "ks:ks_type":"HABITATION",
    "name:eng_x_preferred":[
        "Chhoti Marpakala"
    ],
    "wof:name":"Chhoti Marpakala",
    "wof:placetype":"locality",
    "wof:population":430
},
  "geometry": {"coordinates":[86.450598,25.234462],"type":"Point"}
}