{
  "type": "Feature",
  "properties": {
    "iso:country":"IN",
    "ks:ks_name":"Senapadi",
    "ks:ks_pop":91,
    "ks:ks_type":"VILLAGE",
    "name:eng_x_preferred":[
        "Senapadi"
    ],
    "wof:name":"Senapadi",
    "wof:placetype":"locality",
    "wof:population":91
},
  "geometry": {"coordinates":[83.863484,20.171198],"type":"Point"}
}