{
  "type": "Feature",
  "properties": {
    "gn:admin1_code":"35.0",
    "gn:admin2_code":"428.0",
    "gn:asciiname":"Kirola",
    "gn:country_code":"IN",
    "gn:dem":366,
    "gn:feature_class":"P",
    "gn:feature_code":"PPL",
    "gn:name":"Kirola",
    "gn:population":0,
    "gn:timezone":"Asia/Kolkata",
    "iso:country":"IN",
    "ks:ks_name":"Kirola",
    "ks:ks_type":"VILLAGE",
    "name:eng_x_preferred":[
        "Kirola"
    ],
    "wof:name":"Kirola",
    "wof:placetype":"locality"
},
  "geometry": {"coordinates":[79.229848,24.030094],"type":"Point"}
}