{
  "type": "Feature",
  "properties": {
    "iso:country":"IN",
    "ks:ks_name":"Sujapur",
    "ks:ks_pop":0,
    "ks:ks_type":"VILLAGE",
    "name:eng_x_preferred":[
        "Sujapur"
    ],
    "wof:name":"Sujapur",
    "wof:placetype":"locality",
    "wof:population":0
},
  "geometry": {"coordinates":[83.52973299999999,25.341392],"type":"Point"}
}