{
  "type": "Feature",
  "properties": {
    "gn:admin1_code":"12.0",
    "gn:admin2_code":"14.0",
    "gn:asciiname":"Daisir",
    "gn:country_code":"IN",
    "gn:dem":1844,
    "gn:feature_class":"P",
    "gn:feature_code":"PPL",
    "gn:name":"Dais\u012br",
    "gn:population":0,
    "gn:timezone":"Asia/Kolkata",
    "iso:country":"IN",
    "wof:name":"Daisir",
    "wof:placetype":"locality"
},
  "geometry": {"coordinates":[75.26739000000001,33.8934],"type":"Point"}
}