{
  "type": "Feature",
  "properties": {
    "iso:country":"IN",
    "ks:ks_name":"Thanjare",
    "ks:ks_pop":200,
    "ks:ks_type":"HABITATION",
    "name:eng_x_preferred":[
        "Thanjare"
    ],
    "wof:name":"Thanjare",
    "wof:placetype":"locality",
    "wof:population":200
},
  "geometry": {"coordinates":[74.940569,12.838109],"type":"Point"}
}