{
  "type": "Feature",
  "properties": {
    "iso:country":"IN",
    "qs:name":"Hauz Khas Enclave",
    "qs:name_adm0":"India",
    "qs:name_adm1":"Delhi",
    "qs:photos":32,
    "qs:photos_1k":6,
    "qs:photos_9k":1,
    "qs:photos_9r":2,
    "qs:photos_all":32,
    "qs:photos_sr":2,
    "qs:placetype":"Suburb",
    "qs:pop_sr":"0",
    "wof:name":"Hauz Khas Enclave",
    "wof:placetype":"neighbourhood"
},
  "geometry": {"coordinates":[77.20188400000001,28.552783],"type":"Point"}
}