{
  "type": "Feature",
  "properties": {
    "iso:country":"IN",
    "ks:ks_name":"Pitadei",
    "ks:ks_pop":36,
    "ks:ks_type":"VILLAGE",
    "name:eng_x_preferred":[
        "Pitadei"
    ],
    "wof:name":"Pitadei",
    "wof:placetype":"locality",
    "wof:population":36
},
  "geometry": {"coordinates":[84.414371,20.23807],"type":"Point"}
}