{
  "type": "Feature",
  "properties": {
    "gn:admin1_code":"16.0",
    "gn:admin2_code":"515.0",
    "gn:asciiname":"Vakhad",
    "gn:country_code":"IN",
    "gn:dem":634,
    "gn:feature_class":"P",
    "gn:feature_code":"PPL",
    "gn:name":"V\u0101khad",
    "gn:population":0,
    "gn:timezone":"Asia/Kolkata",
    "iso:country":"IN",
    "wof:name":"Vakhad",
    "wof:placetype":"neighbourhood"
},
  "geometry": {"coordinates":[75.41495999999999,20.38015],"type":"Point"}
}