{
  "type": "Feature",
  "properties": {
    "iso:country":"IN",
    "ks:ks_name":"Dakhin Tokererchara Pt.IV B",
    "ks:ks_pop":700,
    "ks:ks_type":"VILLAGE",
    "ks:ks_uagg_main":0,
    "name:eng_x_preferred":[
        "Dakhin Tokererchara Pt.IV B"
    ],
    "wof:name":"Dakhin Tokererchara Pt.IV B",
    "wof:placetype":"neighbourhood",
    "wof:population":700
},
  "geometry": {"coordinates":[89.828125,26.094418],"type":"Point"}
}