{
  "type": "Feature",
  "properties": {
    "iso:country":"IN",
    "ks:ks_name":"Hatibari",
    "ks:ks_pop":395,
    "ks:ks_type":"VILLAGE",
    "ks:ks_uagg_main":0,
    "name:eng_x_preferred":[
        "Hatibari"
    ],
    "wof:name":"Hatibari",
    "wof:placetype":"neighbourhood",
    "wof:population":395
},
  "geometry": {"coordinates":[86.551496,23.308241],"type":"Point"}
}