{
  "type": "Feature",
  "properties": {
    "gn:admin1_code":"21",
    "gn:admin2_code":"374.0",
    "gn:asciiname":"Sardhapali",
    "gn:country_code":"IN",
    "gn:dem":235,
    "gn:feature_class":"P",
    "gn:feature_code":"PPL",
    "gn:name":"Sardh\u0101p\u0101li",
    "gn:population":0,
    "gn:timezone":"Asia/Kolkata",
    "iso:country":"IN",
    "wof:name":"Sardhapali",
    "wof:placetype":"locality"
},
  "geometry": {"coordinates":[83.96948,21.99603],"type":"Point"}
}