{
  "type": "Feature",
  "properties": {
    "iso:country":"IN",
    "ks:ks_name":"Machad",
    "ks:ks_pop":2190,
    "ks:ks_type":"HABITATION",
    "name:eng_x_preferred":[
        "Machad"
    ],
    "wof:name":"Machad",
    "wof:placetype":"locality",
    "wof:population":2190
},
  "geometry": {"coordinates":[77.703622,28.109002],"type":"Point"}
}