{
  "type": "Feature",
  "properties": {
    "iso:country":"IN",
    "ks:ks_name":"Maralli",
    "ks:ks_pop":454,
    "ks:ks_type":"HABITATION",
    "name:eng_x_preferred":[
        "Maralli"
    ],
    "wof:name":"Maralli",
    "wof:placetype":"locality",
    "wof:population":454
},
  "geometry": {"coordinates":[77.340947,11.914382],"type":"Point"}
}