{
  "type": "Feature",
  "properties": {
    "gn:admin1_code":"12",
    "gn:admin2_code":"15.0",
    "gn:asciiname":"Ramahom",
    "gn:country_code":"IN",
    "gn:dem":1930,
    "gn:feature_class":"P",
    "gn:feature_code":"PPL",
    "gn:name":"Ramah\u014dm",
    "gn:population":0,
    "gn:timezone":"Asia/Kolkata",
    "iso:country":"IN",
    "wof:name":"Ramahom",
    "wof:placetype":"locality"
},
  "geometry": {"coordinates":[74.90817,33.63764],"type":"Point"}
}