{
  "type": "Feature",
  "properties": {
    "iso:country":"IN",
    "ks:ks_name":"Maldeh",
    "ks:ks_pop":389,
    "ks:ks_type":"HABITATION",
    "name:eng_x_preferred":[
        "Maldeh"
    ],
    "wof:name":"Maldeh",
    "wof:placetype":"locality",
    "wof:population":389
},
  "geometry": {"coordinates":[84.115379,25.754874],"type":"Point"}
}