{
  "type": "Feature",
  "properties": {
    "gn:admin1_code":"11.0",
    "gn:admin2_code":"33.0",
    "gn:asciiname":"Phagu",
    "gn:country_code":"IN",
    "gn:dem":2406,
    "gn:feature_class":"P",
    "gn:feature_code":"PPL",
    "gn:name":"Ph\u0101gu",
    "gn:population":0,
    "gn:timezone":"Asia/Kolkata",
    "iso:country":"IN",
    "wof:name":"Phagu",
    "wof:placetype":"locality"
},
  "geometry": {"coordinates":[77.30393000000002,31.08998],"type":"Point"}
}