{
  "type": "Feature",
  "properties": {
    "iso:country":"IN",
    "ks:ks_name":"Gullekodige",
    "ks:ks_pop":10,
    "ks:ks_type":"HABITATION",
    "name:eng_x_preferred":[
        "Gullekodige"
    ],
    "wof:name":"Gullekodige",
    "wof:placetype":"locality",
    "wof:population":10
},
  "geometry": {"coordinates":[75.33556799999999,13.381786],"type":"Point"}
}