{
  "type": "Feature",
  "properties": {
    "iso:country":"IN",
    "ks:ks_name":"Iluppaiyurani",
    "ks:ks_pop":12005,
    "ks:ks_type":"URBAN",
    "ks:ks_uagg_main":0,
    "name:eng_x_preferred":[
        "Iluppaiyurani"
    ],
    "wof:name":"Iluppaiyurani",
    "wof:placetype":"neighbourhood",
    "wof:population":12005
},
  "geometry": {"coordinates":[77.892466,9.187985],"type":"Point"}
}