{
  "type": "Feature",
  "properties": {
    "iso:country":"IN",
    "ks:ks_name":"Kanalpalam",
    "ks:ks_pop":328,
    "ks:ks_type":"HABITATION",
    "ks:ks_uagg_main":0,
    "name:eng_x_preferred":[
        "Kanalpalam"
    ],
    "wof:name":"Kanalpalam",
    "wof:placetype":"neighbourhood",
    "wof:population":328
},
  "geometry": {"coordinates":[76.116518,10.469473],"type":"Point"}
}