{
  "type": "Feature",
  "properties": {
    "iso:country":"IN",
    "ks:ks_name":"Karbal Khora",
    "ks:ks_pop":1463,
    "ks:ks_type":"VILLAGE",
    "name:eng_x_preferred":[
        "Karbal Khora"
    ],
    "wof:name":"Karbal Khora",
    "wof:placetype":"locality",
    "wof:population":1463
},
  "geometry": {"coordinates":[74.595445,23.418408],"type":"Point"}
}