{
  "type": "Feature",
  "properties": {
    "iso:country":"IN",
    "ks:ks_name":"Bilju",
    "ks:ks_pop":38,
    "ks:ks_type":"VILLAGE",
    "name:eng_x_preferred":[
        "Bilju"
    ],
    "wof:name":"Bilju",
    "wof:placetype":"locality",
    "wof:population":38
},
  "geometry": {"coordinates":[80.165177,30.394625],"type":"Point"}
}