{
  "type": "Feature",
  "properties": {
    "gn:admin1_code":"38.0",
    "gn:admin2_code":"347.0",
    "gn:asciiname":"Serka",
    "gn:country_code":"IN",
    "gn:dem":436,
    "gn:feature_class":"P",
    "gn:feature_code":"PPL",
    "gn:name":"Serk\u0101",
    "gn:population":0,
    "gn:timezone":"Asia/Kolkata",
    "iso:country":"IN",
    "ks:ks_alt_nam":"Serk\u0101",
    "ks:ks_name":"Serka",
    "ks:ks_pop":149,
    "ks:ks_type":"VILLAGE",
    "name:eng_x_preferred":[
        "Serka"
    ],
    "name:eng_x_variant":[
        "Serk\u0101"
    ],
    "wof:name":"Serka",
    "wof:placetype":"locality",
    "wof:population":149
},
  "geometry": {"coordinates":[84.726074,24.122371],"type":"Point"}
}