{
  "type": "Feature",
  "properties": {
    "gn:admin1_code":"40",
    "gn:admin2_code":"535.0",
    "gn:asciiname":"Chilwer",
    "gn:country_code":"IN",
    "gn:dem":526,
    "gn:feature_class":"P",
    "gn:feature_code":"PPL",
    "gn:name":"Chilwer",
    "gn:population":0,
    "gn:timezone":"Asia/Kolkata",
    "iso:country":"IN",
    "wof:name":"Chilwer",
    "wof:placetype":"neighbourhood"
},
  "geometry": {"coordinates":[77.95708999999999,17.94739],"type":"Point"}
}