{
  "type": "Feature",
  "properties": {
    "gn:admin1_code":"19.0",
    "gn:admin2_code":"570.0",
    "gn:asciiname":"Handi",
    "gn:country_code":"IN",
    "gn:dem":1142,
    "gn:feature_class":"P",
    "gn:feature_code":"PPL",
    "gn:name":"Handi",
    "gn:population":0,
    "gn:timezone":"Asia/Kolkata",
    "iso:country":"IN",
    "name:hin_x_preferred":[
        "\u0939\u093e\u0902\u0921\u093c\u0940"
    ],
    "name:mal_x_preferred":[
        "\u0d39\u0d23\u0d4d\u0d1f\u0d3f"
    ],
    "name:pnb_x_preferred":[
        "\u06c1\u0627\u0646\u0688\u06cc"
    ],
    "name:spa_x_preferred":[
        "Handi"
    ],
    "name:vie_x_preferred":[
        "Handi"
    ],
    "wof:name":"Handi",
    "wof:placetype":"locality"
},
  "geometry": {"coordinates":[75.6739,13.18281],"type":"Point"}
}