{
  "type": "Feature",
  "properties": {
    "iso:country":"IN",
    "ks:ks_name":"Harilal Tanda",
    "ks:ks_pop":382,
    "ks:ks_type":"HABITATION",
    "name:eng_x_preferred":[
        "Harilal Tanda"
    ],
    "wof:name":"Harilal Tanda",
    "wof:placetype":"locality",
    "wof:population":382
},
  "geometry": {"coordinates":[77.221898,18.6776],"type":"Point"}
}