{
  "type": "Feature",
  "properties": {
    "iso:country":"IN",
    "ks:ks_name":"Kante",
    "ks:ks_pop":0,
    "ks:ks_type":"VILLAGE",
    "name:eng_x_preferred":[
        "Kante"
    ],
    "wof:name":"Kante",
    "wof:placetype":"locality",
    "wof:population":0
},
  "geometry": {"coordinates":[84.269796,23.573756],"type":"Point"}
}