{
  "type": "Feature",
  "properties": {
    "iso:country":"IN",
    "ks:ks_name":"Malawa",
    "ks:ks_pop":51,
    "ks:ks_type":"VILLAGE",
    "name:eng_x_preferred":[
        "Malawa"
    ],
    "wof:name":"Malawa",
    "wof:placetype":"locality",
    "wof:population":51
},
  "geometry": {"coordinates":[78.83494899999999,29.852569],"type":"Point"}
}