{
  "type": "Feature",
  "properties": {
    "gn:admin1_code":"37.0",
    "gn:asciiname":"Hingir",
    "gn:cc2":"IN",
    "gn:country_code":"IN",
    "gn:dem":337,
    "gn:feature_class":"P",
    "gn:feature_code":"PPL",
    "gn:name":"Hing\u012br",
    "gn:population":0,
    "gn:timezone":"Asia/Kolkata",
    "iso:country":"IN",
    "name:und_x_variant":[
        "Himgir",
        "Hing\u012br"
    ],
    "wof:name":"Hingir",
    "wof:placetype":"locality"
},
  "geometry": {"coordinates":[83.68333,21.95],"type":"Point"}
}