{
  "type": "Feature",
  "properties": {
    "gn:admin1_code":"13.0",
    "gn:admin2_code":"590.0",
    "gn:asciiname":"Ukkini",
    "gn:country_code":"IN",
    "gn:dem":733,
    "gn:feature_class":"P",
    "gn:feature_code":"PPL",
    "gn:name":"Ukkini",
    "gn:population":0,
    "gn:timezone":"Asia/Kolkata",
    "iso:country":"IN",
    "wof:name":"Ukkini",
    "wof:placetype":"locality"
},
  "geometry": {"coordinates":[76.02883,11.71436],"type":"Point"}
}