{
  "type": "Feature",
  "properties": {
    "iso:country":"IN",
    "ks:ks_name":"Rowta Forest Gate",
    "ks:ks_pop":1725,
    "ks:ks_type":"HABITATION",
    "name:eng_x_preferred":[
        "Rowta Forest Gate"
    ],
    "wof:name":"Rowta Forest Gate",
    "wof:placetype":"locality",
    "wof:population":1725
},
  "geometry": {"coordinates":[92.23412999999999,26.736512],"type":"Point"}
}