{
  "type": "Feature",
  "properties": {
    "iso:country":"IN",
    "ks:ks_name":"Hosalli",
    "ks:ks_pop":31,
    "ks:ks_type":"HABITATION",
    "name:eng_x_preferred":[
        "Hosalli"
    ],
    "wof:name":"Hosalli",
    "wof:placetype":"locality",
    "wof:population":31
},
  "geometry": {"coordinates":[74.846524,14.574019],"type":"Point"}
}