{
  "type": "Feature",
  "properties": {
    "iso:country":"IN",
    "ks:ks_name":"Shashihittal",
    "ks:ks_pop":705,
    "ks:ks_type":"HABITATION",
    "name:eng_x_preferred":[
        "Shashihittal"
    ],
    "wof:name":"Shashihittal",
    "wof:placetype":"locality",
    "wof:population":705
},
  "geometry": {"coordinates":[74.287228,14.62958],"type":"Point"}
}