{
  "type": "Feature",
  "properties": {
    "iso:country":"IN",
    "ks:ks_name":"Kalikapur Kadamkhandi",
    "ks:ks_pop":4258,
    "ks:ks_type":"VILLAGE",
    "ks:ks_uagg_main":0,
    "name:eng_x_preferred":[
        "Kalikapur Kadamkhandi"
    ],
    "wof:name":"Kalikapur Kadamkhandi",
    "wof:placetype":"neighbourhood",
    "wof:population":4258
},
  "geometry": {"coordinates":[88.276487,24.119592],"type":"Point"}
}