{
  "type": "Feature",
  "properties": {
    "gn:admin1_code":"12.0",
    "gn:admin2_code":"7.0",
    "gn:asciiname":"Maror",
    "gn:country_code":"IN",
    "gn:dem":1706,
    "gn:feature_class":"P",
    "gn:feature_code":"PPLL",
    "gn:name":"Maror",
    "gn:population":0,
    "gn:timezone":"Asia/Kolkata",
    "iso:country":"IN",
    "wof:name":"Maror",
    "wof:placetype":"locality"
},
  "geometry": {"coordinates":[75.51572,32.69428],"type":"Point"}
}