{
  "type": "Feature",
  "properties": {
    "iso:country":"IN",
    "ks:ks_name":"Kathapada",
    "ks:ks_pop":74,
    "ks:ks_type":"HABITATION",
    "name:eng_x_preferred":[
        "Kathapada"
    ],
    "wof:name":"Kathapada",
    "wof:placetype":"locality",
    "wof:population":74
},
  "geometry": {"coordinates":[72.768863,20.003087],"type":"Point"}
}