{
  "type": "Feature",
  "properties": {
    "gn:admin1_code":"11",
    "gn:admin2_code":"27.0",
    "gn:asciiname":"Satahli",
    "gn:country_code":"IN",
    "gn:dem":1427,
    "gn:feature_class":"P",
    "gn:feature_code":"PPL",
    "gn:name":"Sat\u0101hli",
    "gn:population":0,
    "gn:timezone":"Asia/Kolkata",
    "iso:country":"IN",
    "wof:name":"Satahli",
    "wof:placetype":"locality"
},
  "geometry": {"coordinates":[76.83289000000001,31.49715],"type":"Point"}
}