{
  "type": "Feature",
  "properties": {
    "iso:country":"IN",
    "ks:ks_name":"Sarlu Rongpi",
    "ks:ks_pop":130,
    "ks:ks_type":"HABITATION",
    "name:eng_x_preferred":[
        "Sarlu Rongpi"
    ],
    "wof:name":"Sarlu Rongpi",
    "wof:placetype":"locality",
    "wof:population":130
},
  "geometry": {"coordinates":[92.97689800000001,26.274663],"type":"Point"}
}