{
  "type": "Feature",
  "properties": {
    "gn:admin1_code":"13.0",
    "gn:admin2_code":"598.0",
    "gn:asciiname":"Chakkachampakka",
    "gn:country_code":"IN",
    "gn:dem":7,
    "gn:feature_class":"P",
    "gn:feature_code":"PPL",
    "gn:name":"Chakkachampakka",
    "gn:population":0,
    "gn:timezone":"Asia/Kolkata",
    "iso:country":"IN",
    "ks:ks_alt_nam":"ChakkaM chambaka",
    "ks:ks_name":"Chakkam Chambaka",
    "ks:ks_pop":1020,
    "ks:ks_type":"HABITATION",
    "name:eng_x_preferred":[
        "Chakkam Chambaka"
    ],
    "name:eng_x_variant":[
        "Chakkachampakka"
    ],
    "wof:name":"Chakkam Chambaka",
    "wof:placetype":"locality",
    "wof:population":1020
},
  "geometry": {"coordinates":[76.487649,9.49392],"type":"Point"}
}