{
  "type": "Feature",
  "properties": {
    "iso:country":"IN",
    "ks:ks_alt_nam":"Dhorbai na mu",
    "ks:ks_name":"Dhorbai Na Mu",
    "ks:ks_pop":1214,
    "ks:ks_type":"HABITATION",
    "name:eng_x_preferred":[
        "Dhorbai Na Mu"
    ],
    "wof:name":"Dhorbai Na Mu",
    "wof:placetype":"locality",
    "wof:population":1214
},
  "geometry": {"coordinates":[73.27286100000001,23.020361],"type":"Point"}
}