{
  "type": "Feature",
  "properties": {
    "iso:country":"IN",
    "ks:ks_name":"Kalkoppa",
    "ks:ks_pop":602,
    "ks:ks_type":"VILLAGE",
    "name:eng_x_preferred":[
        "Kalkoppa"
    ],
    "wof:name":"Kalkoppa",
    "wof:placetype":"locality",
    "wof:population":602
},
  "geometry": {"coordinates":[75.040069,14.78011],"type":"Point"}
}