{
  "type": "Feature",
  "properties": {
    "iso:country":"IN",
    "ks:ks_name":"Shampur Urf Mansurpur",
    "ks:ks_pop":1670,
    "ks:ks_type":"VILLAGE",
    "name:eng_x_preferred":[
        "Shampur Urf Mansurpur"
    ],
    "wof:name":"Shampur Urf Mansurpur",
    "wof:placetype":"locality",
    "wof:population":1670
},
  "geometry": {"coordinates":[85.358536,25.686952],"type":"Point"}
}