{
  "type": "Feature",
  "properties": {
    "iso:country":"IN",
    "ks:ks_alt_nam":"Knarua purwa",
    "ks:ks_name":"Knarua Purwa",
    "ks:ks_pop":151,
    "ks:ks_type":"HABITATION",
    "name:eng_x_preferred":[
        "Knarua Purwa"
    ],
    "wof:name":"Knarua Purwa",
    "wof:placetype":"locality",
    "wof:population":151
},
  "geometry": {"coordinates":[79.784251,26.902117],"type":"Point"}
}