{
  "type": "Feature",
  "properties": {
    "gn:admin1_code":"10.0",
    "gn:admin2_code":"074",
    "gn:asciiname":"Burhanpur Sikri",
    "gn:country_code":"IN",
    "gn:dem":259,
    "gn:feature_class":"P",
    "gn:feature_code":"PPL",
    "gn:name":"Burhanpur S\u012bkri",
    "gn:population":0,
    "gn:timezone":"Asia/Kolkata",
    "iso:country":"IN",
    "wof:name":"Burhanpur Sikri",
    "wof:placetype":"locality"
},
  "geometry": {"coordinates":[77.0176,29.89013],"type":"Point"}
}