{
  "type": "Feature",
  "properties": {
    "gn:admin1_code":"21",
    "gn:admin2_code":"395.0",
    "gn:asciiname":"Kutraguda",
    "gn:country_code":"IN",
    "gn:dem":326,
    "gn:feature_class":"P",
    "gn:feature_code":"PPL",
    "gn:name":"Kutraguda",
    "gn:population":0,
    "gn:timezone":"Asia/Kolkata",
    "iso:country":"IN",
    "ks:ks_name":"Kuturuguda",
    "ks:ks_pop":94,
    "ks:ks_type":"VILLAGE",
    "name:eng_x_preferred":[
        "Kuturuguda"
    ],
    "name:eng_x_variant":[
        "Kutraguda"
    ],
    "wof:name":"Kuturuguda",
    "wof:placetype":"locality",
    "wof:population":94
},
  "geometry": {"coordinates":[83.20438300000001,19.840568],"type":"Point"}
}