{
  "type": "Feature",
  "properties": {
    "iso:country":"IN",
    "ks:ks_name":"Jaifarpur",
    "ks:ks_pop":2520,
    "ks:ks_type":"VILLAGE",
    "name:eng_x_preferred":[
        "Jaifarpur"
    ],
    "wof:name":"Jaifarpur",
    "wof:placetype":"locality",
    "wof:population":2520
},
  "geometry": {"coordinates":[92.761118,24.784813],"type":"Point"}
}