{
  "type": "Feature",
  "properties": {
    "iso:country":"IN",
    "ks:ks_alt_nam":"Narhani\u0101n",
    "ks:ks_name":"Narhanian",
    "ks:ks_type":"VILLAGE",
    "name:eng_x_preferred":[
        "Narhanian"
    ],
    "name:eng_x_variant":[
        "Narhani\u0101n"
    ],
    "wof:name":"Narhanian",
    "wof:placetype":"locality"
},
  "geometry": {"coordinates":[83.83801699999999,25.062273],"type":"Point"}
}