{
  "type": "Feature",
  "properties": {
    "iso:country":"IN",
    "ks:ks_name":"Erabar",
    "ks:ks_pop":626,
    "ks:ks_type":"VILLAGE",
    "ks:ks_uagg_main":0,
    "name:eng_x_preferred":[
        "Erabar"
    ],
    "wof:name":"Erabar",
    "wof:placetype":"neighbourhood",
    "wof:population":626
},
  "geometry": {"coordinates":[87.651664,21.970714],"type":"Point"}
}