{
  "type": "Feature",
  "properties": {
    "iso:country":"IN",
    "ks:ks_name":"Chhadna",
    "ks:ks_pop":322,
    "ks:ks_type":"VILLAGE",
    "name:eng_x_preferred":[
        "Chhadna"
    ],
    "wof:name":"Chhadna",
    "wof:placetype":"locality",
    "wof:population":322
},
  "geometry": {"coordinates":[82.330877,24.195894],"type":"Point"}
}