{
  "type": "Feature",
  "properties": {
    "gn:admin1_code":"35.0",
    "gn:admin2_code":"432.0",
    "gn:asciiname":"Kothadi Istmurar",
    "gn:country_code":"IN",
    "gn:dem":458,
    "gn:feature_class":"P",
    "gn:feature_code":"PPL",
    "gn:name":"Kothadi Istmurar",
    "gn:population":0,
    "gn:timezone":"Asia/Kolkata",
    "iso:country":"IN",
    "wof:name":"Kothadi Istmurar",
    "wof:placetype":"locality"
},
  "geometry": {"coordinates":[74.91211,24.36844],"type":"Point"}
}