{
  "type": "Feature",
  "properties": {
    "iso:country":"IN",
    "ks:ks_name":"Ubgari",
    "ks:ks_pop":903,
    "ks:ks_type":"VILLAGE",
    "name:eng_x_preferred":[
        "Ubgari"
    ],
    "wof:name":"Ubgari",
    "wof:placetype":"locality",
    "wof:population":903
},
  "geometry": {"coordinates":[74.48206,22.47014],"type":"Point"}
}