{
  "type": "Feature",
  "properties": {
    "iso:country":"IN",
    "ks:ks_alt_nam":"SAVLAJKARWASTI",
    "ks:ks_name":"Savlajkarwasti",
    "ks:ks_pop":125,
    "ks:ks_type":"HABITATION",
    "name:eng_x_preferred":[
        "Savlajkarwasti"
    ],
    "wof:name":"Savlajkarwasti",
    "wof:placetype":"locality",
    "wof:population":125
},
  "geometry": {"coordinates":[74.82933199999999,16.972721],"type":"Point"}
}