{
  "type": "Feature",
  "properties": {
    "iso:country":"IN",
    "ks:ks_name":"Dimakuchigaon",
    "ks:ks_pop":1489,
    "ks:ks_type":"VILLAGE",
    "ks:ks_uagg_main":0,
    "name:eng_x_preferred":[
        "Dimakuchigaon"
    ],
    "wof:name":"Dimakuchigaon",
    "wof:placetype":"neighbourhood",
    "wof:population":1489
},
  "geometry": {"coordinates":[91.83672300000001,26.744877],"type":"Point"}
}