{
  "type": "Feature",
  "properties": {
    "iso:country":"IN",
    "ks:ks_name":"Satvasewadi",
    "ks:ks_pop":73,
    "ks:ks_type":"HABITATION",
    "name:eng_x_preferred":[
        "Satvasewadi"
    ],
    "wof:name":"Satvasewadi",
    "wof:placetype":"locality",
    "wof:population":73
},
  "geometry": {"coordinates":[73.75257499999999,16.231722],"type":"Point"}
}