{
  "type": "Feature",
  "properties": {
    "iso:country":"IN",
    "ks:ks_name":"Bapujicolony",
    "ks:ks_pop":284,
    "ks:ks_type":"HABITATION",
    "name:eng_x_preferred":[
        "Bapujicolony"
    ],
    "wof:name":"Bapujicolony",
    "wof:placetype":"locality",
    "wof:population":284
},
  "geometry": {"coordinates":[80.592303,15.887193],"type":"Point"}
}