{
  "type": "Feature",
  "properties": {
    "iso:country":"IN",
    "ks:ks_name":"Kaalchivadi",
    "ks:ks_pop":181,
    "ks:ks_type":"HABITATION",
    "name:eng_x_preferred":[
        "Kaalchivadi"
    ],
    "wof:name":"Kaalchivadi",
    "wof:placetype":"locality",
    "wof:population":181
},
  "geometry": {"coordinates":[73.340189,16.711858],"type":"Point"}
}