{
  "type": "Feature",
  "properties": {
    "iso:country":"IN",
    "ks:ks_name":"Serpur",
    "ks:ks_pop":279,
    "ks:ks_type":"VILLAGE",
    "name:eng_x_preferred":[
        "Serpur"
    ],
    "wof:name":"Serpur",
    "wof:placetype":"locality",
    "wof:population":279
},
  "geometry": {"coordinates":[85.245,25.6737],"type":"Point"}
}