{
  "type": "Feature",
  "properties": {
    "iso:country":"IN",
    "ks:ks_name":"Papagara",
    "ks:ks_pop":234,
    "ks:ks_type":"VILLAGE",
    "name:eng_x_preferred":[
        "Papagara"
    ],
    "wof:name":"Papagara",
    "wof:placetype":"locality",
    "wof:population":234
},
  "geometry": {"coordinates":[85.79423800000001,22.317117],"type":"Point"}
}