{
  "type": "Feature",
  "properties": {
    "iso:country":"IN",
    "ks:ks_name":"Kabirai Para",
    "ks:ks_pop":226,
    "ks:ks_type":"HABITATION",
    "name:eng_x_preferred":[
        "Kabirai Para"
    ],
    "wof:name":"Kabirai Para",
    "wof:placetype":"locality",
    "wof:population":226
},
  "geometry": {"coordinates":[91.715244,23.467874],"type":"Point"}
}