{
  "type": "Feature",
  "properties": {
    "gn:admin1_code":"38.0",
    "gn:admin2_code":"352.0",
    "gn:asciiname":"Ghatiari",
    "gn:country_code":"IN",
    "gn:dem":85,
    "gn:feature_class":"P",
    "gn:feature_code":"PPL",
    "gn:name":"Ghati\u0101ri",
    "gn:population":0,
    "gn:timezone":"Asia/Kolkata",
    "iso:country":"IN",
    "ks:ks_alt_nam":"Ghati\u0101ri",
    "ks:ks_name":"Ghatiari",
    "ks:ks_pop":830,
    "ks:ks_type":"VILLAGE",
    "name:eng_x_preferred":[
        "Ghatiari"
    ],
    "name:eng_x_variant":[
        "Ghati\u0101ri"
    ],
    "wof:name":"Ghatiari",
    "wof:placetype":"locality",
    "wof:population":830
},
  "geometry": {"coordinates":[87.538419,25.182984],"type":"Point"}
}