{
  "type": "Feature",
  "properties": {
    "gn:admin1_code":"11.0",
    "gn:admin2_code":"32.0",
    "gn:asciiname":"Sahna",
    "gn:country_code":"IN",
    "gn:dem":1164,
    "gn:feature_class":"P",
    "gn:feature_code":"PPL",
    "gn:name":"Sahna",
    "gn:population":0,
    "gn:timezone":"Asia/Kolkata",
    "iso:country":"IN",
    "name:cat_x_preferred":[
        "Sahna"
    ],
    "name:fas_x_preferred":[
        "\u0633\u0647\u0646\u0627"
    ],
    "name:urd_x_preferred":[
        "\u0633\u06c1\u0646\u0627"
    ],
    "wof:name":"Sahna",
    "wof:placetype":"locality"
},
  "geometry": {"coordinates":[77.74852,30.65028],"type":"Point"}
}