{
  "type": "Feature",
  "properties": {
    "gn:admin1_code":"17.0",
    "gn:admin2_code":"274.0",
    "gn:asciiname":"Mongon",
    "gn:country_code":"IN",
    "gn:dem":1056,
    "gn:feature_class":"P",
    "gn:feature_code":"PPL",
    "gn:name":"Mongon",
    "gn:population":0,
    "gn:timezone":"Asia/Kolkata",
    "iso:country":"IN",
    "wof:name":"Mongon",
    "wof:placetype":"locality"
},
  "geometry": {"coordinates":[93.36862000000001,24.29059],"type":"Point"}
}