{
  "type": "Feature",
  "properties": {
    "iso:country":"IN",
    "ks:ks_alt_nam":"JUWAJHAR F.V.",
    "ks:ks_name":"Juwajhar F.v.",
    "ks:ks_pop":245,
    "ks:ks_type":"HABITATION",
    "name:eng_x_preferred":[
        "Juwajhar F.v."
    ],
    "wof:name":"Juwajhar F.v.",
    "wof:placetype":"locality",
    "wof:population":245
},
  "geometry": {"coordinates":[78.182001,22.07818],"type":"Point"}
}