{
  "type": "Feature",
  "properties": {
    "gn:admin1_code":"36",
    "gn:admin2_code":"171.0",
    "gn:asciiname":"Bira",
    "gn:country_code":"IN",
    "gn:dem":129,
    "gn:feature_class":"P",
    "gn:feature_code":"PPL",
    "gn:name":"B\u012bra",
    "gn:population":0,
    "gn:timezone":"Asia/Kolkata",
    "iso:country":"IN",
    "name:ceb_x_preferred":[
        "Bira"
    ],
    "name:dan_x_preferred":[
        "Bira"
    ],
    "name:deu_x_preferred":[
        "Bira"
    ],
    "name:fra_x_preferred":[
        "Bira"
    ],
    "name:ind_x_preferred":[
        "Bira"
    ],
    "name:ita_x_preferred":[
        "Bira"
    ],
    "name:por_x_preferred":[
        "Bira"
    ],
    "name:sco_x_preferred":[
        "Bira"
    ],
    "name:spa_x_preferred":[
        "Bira"
    ],
    "name:swe_x_preferred":[
        "Bira"
    ],
    "wof:name":"Bira",
    "wof:placetype":"locality"
},
  "geometry": {"coordinates":[80.85378,25.27954],"type":"Point"}
}