{
  "type": "Feature",
  "properties": {
    "iso:country":"IN",
    "ks:ks_name":"Thakur Purwa",
    "ks:ks_pop":190,
    "ks:ks_type":"HABITATION",
    "name:eng_x_preferred":[
        "Thakur Purwa"
    ],
    "wof:name":"Thakur Purwa",
    "wof:placetype":"locality",
    "wof:population":190
},
  "geometry": {"coordinates":[81.995018,27.501919],"type":"Point"}
}