{
  "type": "Feature",
  "properties": {
    "gn:country":"IN",
    "gn:fcode":"PPL",
    "gn:population":10365,
    "iso:country":"IN",
    "name:ben_x_preferred":[
        "\u0987\u09b8\u0997\u09a1\u09bc"
    ],
    "name:bpy_x_preferred":[
        "\u0987\u09b8\u0997\u09a1\u09bc"
    ],
    "name:ceb_x_preferred":[
        "Is\u0101garh"
    ],
    "name:eng_x_preferred":[
        "Isagarh"
    ],
    "name:fra_x_preferred":[
        "Isagarh"
    ],
    "name:ita_x_preferred":[
        "Isagarh"
    ],
    "name:msa_x_preferred":[
        "Isagarh"
    ],
    "name:nan_x_preferred":[
        "Isagarh"
    ],
    "name:new_x_preferred":[
        "\u0907\u0938\u093e\u0917\u0922"
    ],
    "name:nld_x_preferred":[
        "Isagarh"
    ],
    "name:por_x_preferred":[
        "Isagarh"
    ],
    "name:swe_x_preferred":[
        "Is\u0101garh"
    ],
    "name:vie_x_preferred":[
        "Isagarh"
    ],
    "name:zho_x_preferred":[
        "\u4f0a\u8428\u52a0\u5c14"
    ],
    "qs:name":"Is\u0101garh",
    "qs:photos_9r":0,
    "qs:photos_sr":0,
    "qs:pop_sr":"6",
    "wd:wordcount":221,
    "wof:name":"Is\u0101garh",
    "wof:placetype":"locality",
    "wof:population":10365
},
  "geometry": {"coordinates":[77.88274,24.83906],"type":"Point"}
}