{
  "type": "Feature",
  "properties": {
    "iso:country":"IN",
    "ks:ks_name":"Ranip",
    "ks:ks_pop":87906,
    "ks:ks_type":"VILLAGE",
    "ks:ks_uagg_main":0,
    "name:eng_x_preferred":[
        "Ranip"
    ],
    "wof:name":"Ranip",
    "wof:placetype":"neighbourhood",
    "wof:population":87906
},
  "geometry": {"coordinates":[72.574517,23.079789],"type":"Point"}
}