{
  "type": "Feature",
  "properties": {
    "iso:country":"IN",
    "ks:ks_name":"Mannarkulakudi",
    "ks:ks_pop":2382,
    "ks:ks_type":"VILLAGE",
    "ks:ks_uagg_main":0,
    "name:eng_x_preferred":[
        "Mannarkulakudi"
    ],
    "wof:name":"Mannarkulakudi",
    "wof:placetype":"neighbourhood",
    "wof:population":2382
},
  "geometry": {"coordinates":[79.56402300000001,11.285956],"type":"Point"}
}