{
  "type": "Feature",
  "properties": {
    "iso:country":"IN",
    "ks:ks_name":"Pandawa",
    "ks:ks_pop":1385,
    "ks:ks_type":"VILLAGE",
    "name:eng_x_preferred":[
        "Pandawa"
    ],
    "wof:name":"Pandawa",
    "wof:placetype":"locality",
    "wof:population":1385
},
  "geometry": {"coordinates":[74.550146,23.922816],"type":"Point"}
}