{
  "type": "Feature",
  "properties": {
    "iso:country":"IN",
    "ks:ks_name":"Brittihuda",
    "ks:ks_pop":6296,
    "ks:ks_type":"VILLAGE",
    "name:eng_x_preferred":[
        "Brittihuda"
    ],
    "wof:name":"Brittihuda",
    "wof:placetype":"locality",
    "wof:population":6296
},
  "geometry": {"coordinates":[88.49749300000001,23.554221],"type":"Point"}
}