{
  "type": "Feature",
  "properties": {
    "gn:admin1_code":"11",
    "gn:admin2_code":"24.0",
    "gn:asciiname":"Kalar",
    "gn:country_code":"IN",
    "gn:dem":519,
    "gn:feature_class":"P",
    "gn:feature_code":"PPL",
    "gn:name":"Kalar",
    "gn:population":0,
    "gn:timezone":"Asia/Kolkata",
    "iso:country":"IN",
    "name:ceb_x_preferred":[
        "Kalar"
    ],
    "name:swe_x_preferred":[
        "Kalar"
    ],
    "wof:name":"Kalar",
    "wof:placetype":"locality"
},
  "geometry": {"coordinates":[76.19263000000002,31.96573],"type":"Point"}
}