{
  "type": "Feature",
  "properties": {
    "iso:country":"IN",
    "ks:ks_name":"Dhena Tanda",
    "ks:ks_pop":68,
    "ks:ks_type":"HABITATION",
    "name:eng_x_preferred":[
        "Dhena Tanda"
    ],
    "wof:name":"Dhena Tanda",
    "wof:placetype":"locality",
    "wof:population":68
},
  "geometry": {"coordinates":[77.141409,18.409901],"type":"Point"}
}