{
  "type": "Feature",
  "properties": {
    "gn:admin1_code":"28.0",
    "gn:admin2_code":"341.0",
    "gn:asciiname":"Udaynarayanp",
    "gn:country_code":"IN",
    "gn:dem":17,
    "gn:feature_class":"P",
    "gn:feature_code":"PPL",
    "gn:name":"Udaynarayanp",
    "gn:population":0,
    "gn:timezone":"Asia/Kolkata",
    "iso:country":"IN",
    "ks:ks_name":"Udaynarayanpur",
    "ks:ks_pop":1439,
    "ks:ks_type":"VILLAGE",
    "ks:ks_uagg_main":0,
    "name:eng_x_preferred":[
        "Udaynarayanpur"
    ],
    "wof:name":"Udaynarayanpur",
    "wof:placetype":"neighbourhood",
    "wof:population":1439
},
  "geometry": {"coordinates":[87.97461800000001,22.71562],"type":"Point"}
}