{
  "type": "Feature",
  "properties": {
    "iso:country":"IN",
    "ks:ks_alt_nam":"HASARBARI",
    "ks:ks_name":"Hasarbari",
    "ks:ks_pop":786,
    "ks:ks_type":"HABITATION",
    "name:eng_x_preferred":[
        "Hasarbari"
    ],
    "wof:name":"Hasarbari",
    "wof:placetype":"locality",
    "wof:population":786
},
  "geometry": {"coordinates":[88.923467,26.474692],"type":"Point"}
}