{
  "type": "Feature",
  "properties": {
    "gn:admin1_code":"40.0",
    "gn:admin2_code":"539",
    "gn:asciiname":"Devalamma Nagaram",
    "gn:country_code":"IN",
    "gn:dem":417,
    "gn:feature_class":"P",
    "gn:feature_code":"PPL",
    "gn:name":"Devalamma N\u0101g\u0101ram",
    "gn:population":0,
    "gn:timezone":"Asia/Kolkata",
    "iso:country":"IN",
    "wof:name":"Devalamma Nagaram",
    "wof:placetype":"locality"
},
  "geometry": {"coordinates":[78.84721999999999,17.24361],"type":"Point"}
}