{
  "type": "Feature",
  "properties": {
    "gn:admin1_code":"10.0",
    "gn:admin2_code":"70.0",
    "gn:asciiname":"Dhoi",
    "gn:country_code":"IN",
    "gn:dem":274,
    "gn:feature_class":"P",
    "gn:feature_code":"PPL",
    "gn:name":"Dhoi",
    "gn:population":0,
    "gn:timezone":"Asia/Kolkata",
    "iso:country":"IN",
    "wof:name":"Dhoi",
    "wof:placetype":"locality"
},
  "geometry": {"coordinates":[77.01904999999999,30.19083],"type":"Point"}
}