{
  "type": "Feature",
  "properties": {
    "iso:country":"IN",
    "ks:ks_name":"Chinna Wattoli",
    "ks:ks_pop":159,
    "ks:ks_type":"HABITATION",
    "name:eng_x_preferred":[
        "Chinna Wattoli"
    ],
    "wof:name":"Chinna Wattoli",
    "wof:placetype":"locality",
    "wof:population":159
},
  "geometry": {"coordinates":[78.066332,18.968473],"type":"Point"}
}