{
  "type": "Feature",
  "properties": {
    "gn:admin1_code":"24.0",
    "gn:admin2_code":"116",
    "gn:asciiname":"Jaswantpura",
    "gn:country_code":"IN",
    "gn:dem":274,
    "gn:feature_class":"P",
    "gn:feature_code":"PPL",
    "gn:name":"Jaswantpura",
    "gn:population":0,
    "gn:timezone":"Asia/Kolkata",
    "iso:country":"IN",
    "wof:name":"Jaswantpura",
    "wof:placetype":"locality"
},
  "geometry": {"coordinates":[72.45998,24.80364],"type":"Point"}
}