{
  "type": "Feature",
  "properties": {
    "iso:country":"IN",
    "ks:ks_alt_nam":"mall khera",
    "ks:ks_name":"Mall Khera",
    "ks:ks_pop":335,
    "ks:ks_type":"HABITATION",
    "name:eng_x_preferred":[
        "Mall Khera"
    ],
    "wof:name":"Mall Khera",
    "wof:placetype":"locality",
    "wof:population":335
},
  "geometry": {"coordinates":[80.60032699999999,26.509453],"type":"Point"}
}