{
  "type": "Feature",
  "properties": {
    "gn:admin1_code":"33.0",
    "gn:admin2_code":"586.0",
    "gn:asciiname":"Kavat",
    "gn:country_code":"IN",
    "gn:dem":22,
    "gn:feature_class":"P",
    "gn:feature_code":"PPL",
    "gn:name":"Kavat",
    "gn:population":0,
    "gn:timezone":"Asia/Kolkata",
    "iso:country":"IN",
    "name:ceb_x_preferred":[
        "Kav\u0101rt"
    ],
    "name:fas_x_preferred":[
        "\u06a9\u0648\u0627\u062a"
    ],
    "name:mzn_x_preferred":[
        "\u06a9\u0648\u0627\u062a"
    ],
    "name:swe_x_preferred":[
        "Kav\u0101rt"
    ],
    "wof:name":"Kavat",
    "wof:placetype":"locality"
},
  "geometry": {"coordinates":[74.10214999999999,14.96009],"type":"Point"}
}