{
  "type": "Feature",
  "properties": {
    "iso:country":"IN",
    "ks:ks_alt_nam":"Yadav toli",
    "ks:ks_name":"Yadav Toli",
    "ks:ks_pop":204,
    "ks:ks_type":"HABITATION",
    "name:eng_x_preferred":[
        "Yadav Toli"
    ],
    "wof:name":"Yadav Toli",
    "wof:placetype":"locality",
    "wof:population":204
},
  "geometry": {"coordinates":[86.50012599999999,25.991952],"type":"Point"}
}