{
  "type": "Feature",
  "properties": {
    "gn:admin1_code":"36.0",
    "gn:admin2_code":"148",
    "gn:asciiname":"Takia",
    "gn:country_code":"IN",
    "gn:dem":154,
    "gn:feature_class":"P",
    "gn:feature_code":"PPL",
    "gn:name":"Takia",
    "gn:population":0,
    "gn:timezone":"Asia/Kolkata",
    "iso:country":"IN",
    "wof:name":"Takia",
    "wof:placetype":"locality"
},
  "geometry": {"coordinates":[79.26609999999999,27.06679],"type":"Point"}
}