{
  "type": "Feature",
  "properties": {
    "iso:country":"IN",
    "ks:ks_name":"Atahani",
    "ks:ks_pop":1768,
    "ks:ks_type":"HABITATION",
    "name:eng_x_preferred":[
        "Atahani"
    ],
    "wof:name":"Atahani",
    "wof:placetype":"locality",
    "wof:population":1768
},
  "geometry": {"coordinates":[75.932067,11.062352],"type":"Point"}
}