{
  "type": "Feature",
  "properties": {
    "gn:admin1_code":"24",
    "gn:admin2_code":"99.0",
    "gn:asciiname":"Retwala",
    "gn:country_code":"IN",
    "gn:dem":173,
    "gn:feature_class":"P",
    "gn:feature_code":"PPL",
    "gn:name":"Retw\u0101la",
    "gn:population":0,
    "gn:timezone":"Asia/Kolkata",
    "iso:country":"IN",
    "wof:name":"Retwala",
    "wof:placetype":"locality"
},
  "geometry": {"coordinates":[73.73526,29.75883],"type":"Point"}
}