{
  "type": "Feature",
  "properties": {
    "iso:country":"IN",
    "ks:ks_name":"Kelil",
    "ks:ks_pop":383,
    "ks:ks_type":"VILLAGE",
    "name:eng_x_preferred":[
        "Kelil"
    ],
    "wof:name":"Kelil",
    "wof:placetype":"locality",
    "wof:population":383
},
  "geometry": {"coordinates":[73.23454,17.631469],"type":"Point"}
}