{
  "type": "Feature",
  "properties": {
    "gn:admin1_code":"24.0",
    "gn:admin2_code":"129.0",
    "gn:asciiname":"Mori",
    "gn:country_code":"IN",
    "gn:dem":296,
    "gn:feature_class":"P",
    "gn:feature_code":"PPL",
    "gn:name":"Mori",
    "gn:population":0,
    "gn:timezone":"Asia/Kolkata",
    "iso:country":"IN",
    "name:ces_x_preferred":[
        "Mori"
    ],
    "name:lit_x_preferred":[
        "Mori"
    ],
    "name:slk_x_preferred":[
        "Mori"
    ],
    "name:slv_x_preferred":[
        "Mori"
    ],
    "name:spa_x_preferred":[
        "Mori"
    ],
    "wof:name":"Mori",
    "wof:placetype":"locality"
},
  "geometry": {"coordinates":[76.33768000000001,24.57246],"type":"Point"}
}