{
  "type": "Feature",
  "properties": {
    "gn:admin1_code":"36.0",
    "gn:admin2_code":"188",
    "gn:asciiname":"Kauriram",
    "gn:country_code":"IN",
    "gn:dem":80,
    "gn:feature_class":"P",
    "gn:feature_code":"PPL",
    "gn:name":"Kaurir\u0101m",
    "gn:population":0,
    "gn:timezone":"Asia/Kolkata",
    "iso:country":"IN",
    "ks:ks_alt_nam":"Kaurir\u0101m",
    "ks:ks_name":"Kauriram",
    "ks:ks_pop":1371,
    "ks:ks_type":"VILLAGE",
    "ks:ks_uagg_main":0,
    "name:eng_x_preferred":[
        "Kauriram"
    ],
    "name:eng_x_variant":[
        "Kaurir\u0101m"
    ],
    "wof:name":"Kauriram",
    "wof:placetype":"neighbourhood",
    "wof:population":1371
},
  "geometry": {"coordinates":[83.41056500000001,26.534386],"type":"Point"}
}