{
  "type": "Feature",
  "properties": {
    "gn:admin1_code":"39.0",
    "gn:admin2_code":"061",
    "gn:asciiname":"Pali Talli",
    "gn:country_code":"IN",
    "gn:dem":1273,
    "gn:feature_class":"P",
    "gn:feature_code":"PPL",
    "gn:name":"P\u0101li Talli",
    "gn:population":0,
    "gn:timezone":"Asia/Kolkata",
    "iso:country":"IN",
    "wof:name":"Pali Talli",
    "wof:placetype":"locality"
},
  "geometry": {"coordinates":[78.65980999999999,29.86247],"type":"Point"}
}