{
  "type": "Feature",
  "properties": {
    "iso:country":"IN",
    "ks:ks_name":"Chapla",
    "ks:ks_pop":100,
    "ks:ks_type":"HABITATION",
    "name:eng_x_preferred":[
        "Chapla"
    ],
    "wof:name":"Chapla",
    "wof:placetype":"locality",
    "wof:population":100
},
  "geometry": {"coordinates":[82.44633,25.062539],"type":"Point"}
}