{
  "type": "Feature",
  "properties": {
    "gn:admin1_code":"36",
    "gn:admin2_code":"142.0",
    "gn:asciiname":"Maman Khurd",
    "gn:country_code":"IN",
    "gn:dem":204,
    "gn:feature_class":"P",
    "gn:feature_code":"PPL",
    "gn:name":"M\u0101man Khurd",
    "gn:population":0,
    "gn:timezone":"Asia/Kolkata",
    "iso:country":"IN",
    "wof:name":"Maman Khurd",
    "wof:placetype":"locality"
},
  "geometry": {"coordinates":[77.84658,28.3313],"type":"Point"}
}