{
  "type": "Feature",
  "properties": {
    "iso:country":"IN",
    "ks:ks_name":"Lodhan Purwa",
    "ks:ks_pop":97,
    "ks:ks_type":"HABITATION",
    "name:eng_x_preferred":[
        "Lodhan Purwa"
    ],
    "wof:name":"Lodhan Purwa",
    "wof:placetype":"locality",
    "wof:population":97
},
  "geometry": {"coordinates":[79.994863,26.696657],"type":"Point"}
}