{
  "type": "Feature",
  "properties": {
    "iso:country":"IN",
    "ks:ks_name":"Badigeddulapalle",
    "ks:ks_pop":38,
    "ks:ks_type":"HABITATION",
    "name:eng_x_preferred":[
        "Badigeddulapalle"
    ],
    "wof:name":"Badigeddulapalle",
    "wof:placetype":"locality",
    "wof:population":38
},
  "geometry": {"coordinates":[78.28964499999999,13.615585],"type":"Point"}
}