{
  "type": "Feature",
  "properties": {
    "gn:admin1_code":"19.0",
    "gn:admin2_code":"570.0",
    "gn:asciiname":"Hunasvalli",
    "gn:country_code":"IN",
    "gn:dem":735,
    "gn:feature_class":"P",
    "gn:feature_code":"PPL",
    "gn:name":"Hunasvalli",
    "gn:population":0,
    "gn:timezone":"Asia/Kolkata",
    "iso:country":"IN",
    "ks:ks_name":"Hunasehalli",
    "ks:ks_pop":325,
    "ks:ks_type":"HABITATION",
    "name:eng_x_preferred":[
        "Hunasehalli"
    ],
    "name:eng_x_variant":[
        "Hunasvalli"
    ],
    "wof:name":"Hunasehalli",
    "wof:placetype":"locality",
    "wof:population":325
},
  "geometry": {"coordinates":[75.555775,13.328151],"type":"Point"}
}