{
  "type": "Feature",
  "properties": {
    "gn:admin1_code":"24.0",
    "gn:admin2_code":"129.0",
    "gn:asciiname":"Miyara",
    "gn:country_code":"IN",
    "gn:dem":292,
    "gn:feature_class":"P",
    "gn:feature_code":"PPL",
    "gn:name":"Miy\u0101ra",
    "gn:population":0,
    "gn:timezone":"Asia/Kolkata",
    "iso:country":"IN",
    "wof:name":"Miyara",
    "wof:placetype":"locality"
},
  "geometry": {"coordinates":[76.31206,24.63144],"type":"Point"}
}