{
  "type": "Feature",
  "properties": {
    "gn:admin1_code":"34.0",
    "gn:admin2_code":"212.0",
    "gn:asciiname":"Tehargaon",
    "gn:country_code":"IN",
    "gn:dem":26,
    "gn:feature_class":"P",
    "gn:feature_code":"PPL",
    "gn:name":"Tehargaon",
    "gn:population":0,
    "gn:timezone":"Asia/Kolkata",
    "iso:country":"IN",
    "ks:ks_name":"Tehargaon",
    "ks:ks_pop":5,
    "ks:ks_type":"VILLAGE",
    "name:eng_x_preferred":[
        "Tehargaon"
    ],
    "wof:name":"Tehargaon",
    "wof:placetype":"locality",
    "wof:population":5
},
  "geometry": {"coordinates":[87.758636,25.506034],"type":"Point"}
}