{
  "type": "Feature",
  "properties": {
    "iso:country":"IN",
    "ks:ks_name":"Chakra Pur",
    "ks:ks_pop":437,
    "ks:ks_type":"VILLAGE",
    "name:eng_x_preferred":[
        "Chakra Pur"
    ],
    "wof:name":"Chakra Pur",
    "wof:placetype":"locality",
    "wof:population":437
},
  "geometry": {"coordinates":[86.43889299999999,20.685467],"type":"Point"}
}