{
  "type": "Feature",
  "properties": {
    "gn:admin1_code":"38.0",
    "gn:admin2_code":"347.0",
    "gn:asciiname":"Bartoli",
    "gn:country_code":"IN",
    "gn:dem":358,
    "gn:feature_class":"P",
    "gn:feature_code":"PPL",
    "gn:name":"Bartoli",
    "gn:population":0,
    "gn:timezone":"Asia/Kolkata",
    "iso:country":"IN",
    "name:cos_x_preferred":[
        "Bartoli"
    ],
    "name:deu_x_preferred":[
        "Bartoli"
    ],
    "name:fra_x_preferred":[
        "Bartoli"
    ],
    "name:ita_x_preferred":[
        "Bartoli"
    ],
    "name:jpn_x_preferred":[
        "\u30d0\u30eb\u30c8\u30ea"
    ],
    "name:lav_x_preferred":[
        "Bartoli"
    ],
    "name:nds_x_preferred":[
        "Bartoli"
    ],
    "name:rus_x_preferred":[
        "\u0411\u0430\u0440\u0442\u043e\u043b\u0438"
    ],
    "name:slv_x_preferred":[
        "Bartoli"
    ],
    "name:spa_x_preferred":[
        "Bartoli"
    ],
    "name:swe_x_preferred":[
        "Bartoli"
    ],
    "name:ukr_x_preferred":[
        "\u0411\u0430\u0440\u0442\u043e\u043b\u0456"
    ],
    "wof:name":"Bartoli",
    "wof:placetype":"locality"
},
  "geometry": {"coordinates":[84.66743000000002,24.12761],"type":"Point"}
}