{
  "type": "Feature",
  "properties": {
    "iso:country":"IN",
    "ks:ks_name":"Gowai Chak",
    "ks:ks_pop":793,
    "ks:ks_type":"HABITATION",
    "ks:ks_uagg_main":0,
    "name:eng_x_preferred":[
        "Gowai Chak"
    ],
    "wof:name":"Gowai Chak",
    "wof:placetype":"neighbourhood",
    "wof:population":793
},
  "geometry": {"coordinates":[84.927778,25.404722],"type":"Point"}
}