{
  "type": "Feature",
  "properties": {
    "iso:country":"IN",
    "ks:ks_name":"Nirpur",
    "ks:ks_pop":2472,
    "ks:ks_type":"VILLAGE",
    "ks:ks_uagg_main":0,
    "name:eng_x_preferred":[
        "Nirpur"
    ],
    "wof:name":"Nirpur",
    "wof:placetype":"neighbourhood",
    "wof:population":2472
},
  "geometry": {"coordinates":[86.590191,25.270873],"type":"Point"}
}