{
  "type": "Feature",
  "properties": {
    "iso:country":"IN",
    "ks:ks_name":"Ramnagor",
    "ks:ks_pop":1154,
    "ks:ks_type":"VILLAGE",
    "name:eng_x_preferred":[
        "Ramnagor"
    ],
    "wof:name":"Ramnagor",
    "wof:placetype":"locality",
    "wof:population":1154
},
  "geometry": {"coordinates":[86.102687,23.898679],"type":"Point"}
}