{
  "type": "Feature",
  "properties": {
    "iso:country":"IN",
    "ks:ks_name":"Gonikodlu",
    "ks:ks_pop":118,
    "ks:ks_type":"HABITATION",
    "name:eng_x_preferred":[
        "Gonikodlu"
    ],
    "wof:name":"Gonikodlu",
    "wof:placetype":"locality",
    "wof:population":118
},
  "geometry": {"coordinates":[75.40632100000001,13.307571],"type":"Point"}
}