{
  "type": "Feature",
  "properties": {
    "gn:admin1_code":"2.0",
    "gn:admin2_code":"544.0",
    "gn:asciiname":"Vanjarba",
    "gn:country_code":"IN",
    "gn:dem":1067,
    "gn:feature_class":"P",
    "gn:feature_code":"PPL",
    "gn:name":"Vanjarba",
    "gn:population":0,
    "gn:timezone":"Asia/Kolkata",
    "iso:country":"IN",
    "ks:ks_name":"Vanjarbha",
    "ks:ks_pop":39,
    "ks:ks_type":"HABITATION",
    "name:eng_x_preferred":[
        "Vanjarbha"
    ],
    "name:eng_x_variant":[
        "Vanjarba"
    ],
    "wof:name":"Vanjarbha",
    "wof:placetype":"locality",
    "wof:population":39
},
  "geometry": {"coordinates":[82.506207,18.092294],"type":"Point"}
}