{
  "type": "Feature",
  "properties": {
    "gn:admin1_code":"2.0",
    "gn:admin2_code":"544.0",
    "gn:asciiname":"Vanjarba",
    "gn:country_code":"IN",
    "gn:dem":1067,
    "gn:feature_class":"P",
    "gn:feature_code":"PPL",
    "gn:name":"Vanjarba",
    "gn:population":0,
    "gn:timezone":"Asia/Kolkata",
    "iso:country":"IN",
    "wof:name":"Vanjarba",
    "wof:placetype":"locality"
},
  "geometry": {"coordinates":[82.50834,18.09277],"type":"Point"}
}