{
  "type": "Feature",
  "properties": {
    "iso:country":"IN",
    "ks:ks_name":"Veerapuram",
    "ks:ks_pop":220,
    "ks:ks_type":"HABITATION",
    "name:eng_x_preferred":[
        "Veerapuram"
    ],
    "wof:name":"Veerapuram",
    "wof:placetype":"locality",
    "wof:population":220
},
  "geometry": {"coordinates":[80.786244,18.073007],"type":"Point"}
}