{
  "type": "Feature",
  "properties": {
    "gn:admin1_code":"12.0",
    "gn:admin2_code":"19.0",
    "gn:asciiname":"Lahr",
    "gn:country_code":"IN",
    "gn:dem":999,
    "gn:feature_class":"P",
    "gn:feature_code":"PPL",
    "gn:name":"Lahr",
    "gn:population":0,
    "gn:timezone":"Asia/Kolkata",
    "iso:country":"IN",
    "name:als_x_preferred":[
        "Lahr/Schwarzwald"
    ],
    "name:ara_x_preferred":[
        "\u0644\u0627\u0631"
    ],
    "name:azb_x_preferred":[
        "\u0644\u0627\u0631"
    ],
    "name:bul_x_preferred":[
        "\u041b\u0430\u0440"
    ],
    "name:ceb_x_preferred":[
        "Lahr"
    ],
    "name:deu_x_preferred":[
        "Lahr/Schwarzwald"
    ],
    "name:epo_x_preferred":[
        "Lahr"
    ],
    "name:eus_x_preferred":[
        "Lahr"
    ],
    "name:fas_x_preferred":[
        "\u0644\u0627\u0631"
    ],
    "name:fra_x_preferred":[
        "Lahr/Schwarzwald"
    ],
    "name:hrv_x_preferred":[
        "Lahr"
    ],
    "name:hun_x_preferred":[
        "Lahr"
    ],
    "name:ita_x_preferred":[
        "Lahr/Schwarzwald"
    ],
    "name:lat_x_preferred":[
        "Lahr"
    ],
    "name:lmo_x_preferred":[
        "Lahr/Schwarzwald"
    ],
    "name:msa_x_preferred":[
        "Lahr"
    ],
    "name:nld_x_preferred":[
        "Lahr/Schwarzwald"
    ],
    "name:pol_x_preferred":[
        "Lahr/Schwarzwald"
    ],
    "name:por_x_preferred":[
        "Lahr"
    ],
    "name:ron_x_preferred":[
        "Lahr/Schwarzwald"
    ],
    "name:rus_x_preferred":[
        "\u041b\u0430\u0440"
    ],
    "name:spa_x_preferred":[
        "Lahr"
    ],
    "name:srp_x_preferred":[
        "\u041b\u0430\u0440"
    ],
    "name:swa_x_preferred":[
        "Lahr"
    ],
    "name:swe_x_preferred":[
        "Lahr"
    ],
    "name:tat_x_preferred":[
        "\u041b\u0430\u0440"
    ],
    "name:tur_x_preferred":[
        "Lahr"
    ],
    "name:ukr_x_preferred":[
        "\u041b\u0430\u0440"
    ],
    "name:uzb_x_preferred":[
        "Lahr"
    ],
    "name:vol_x_preferred":[
        "Lahr/Schwarzwald"
    ],
    "name:war_x_preferred":[
        "Lahr"
    ],
    "name:zho_x_preferred":[
        "\u9ed1\u6797\u5c71\u533a\u62c9\u5c14"
    ],
    "wof:name":"Lahr",
    "wof:placetype":"locality"
},
  "geometry": {"coordinates":[75.10051,33.09556],"type":"Point"}
}