{
  "type": "Feature",
  "properties": {
    "iso:country":"IN",
    "ks:ks_name":"Jasnath Nagar Beniwalo Ki Dhani",
    "ks:ks_pop":339,
    "ks:ks_type":"HABITATION",
    "name:eng_x_preferred":[
        "Jasnath Nagar Beniwalo Ki Dhani"
    ],
    "wof:name":"Jasnath Nagar Beniwalo Ki Dhani",
    "wof:placetype":"locality",
    "wof:population":339
},
  "geometry": {"coordinates":[71.859472,25.607575],"type":"Point"}
}