{
  "type": "Feature",
  "properties": {
    "iso:country":"IN",
    "ks:ks_name":"Ayolpadi",
    "ks:ks_pop":340,
    "ks:ks_type":"HABITATION",
    "name:eng_x_preferred":[
        "Ayolpadi"
    ],
    "wof:name":"Ayolpadi",
    "wof:placetype":"locality",
    "wof:population":340
},
  "geometry": {"coordinates":[75.70715,11.556849],"type":"Point"}
}