{
  "type": "Feature",
  "properties": {
    "iso:country":"IN",
    "ks:ks_name":"Valasapadu",
    "ks:ks_pop":52,
    "ks:ks_type":"HABITATION",
    "name:eng_x_preferred":[
        "Valasapadu"
    ],
    "wof:name":"Valasapadu",
    "wof:placetype":"locality",
    "wof:population":52
},
  "geometry": {"coordinates":[82.66779699999999,17.770903],"type":"Point"}
}