{
  "type": "Feature",
  "properties": {
    "iso:country":"IN",
    "ks:ks_name":"Durga Prasad",
    "ks:ks_pop":42,
    "ks:ks_type":"VILLAGE",
    "name:eng_x_preferred":[
        "Durga Prasad"
    ],
    "wof:name":"Durga Prasad",
    "wof:placetype":"locality",
    "wof:population":42
},
  "geometry": {"coordinates":[86.844433,20.743482],"type":"Point"}
}