{
  "type": "Feature",
  "properties": {
    "gn:admin1_code":"19.0",
    "gn:admin2_code":"568.0",
    "gn:asciiname":"Chilanur",
    "gn:country_code":"IN",
    "gn:dem":604,
    "gn:feature_class":"P",
    "gn:feature_code":"PPL",
    "gn:name":"Ch\u012blan\u016br",
    "gn:population":0,
    "gn:timezone":"Asia/Kolkata",
    "iso:country":"IN",
    "ks:ks_name":"Chilnur",
    "ks:ks_pop":260,
    "ks:ks_type":"VILLAGE",
    "name:eng_x_preferred":[
        "Chilnur"
    ],
    "name:eng_x_variant":[
        "Chilanur"
    ],
    "wof:name":"Chilnur",
    "wof:placetype":"locality",
    "wof:population":260
},
  "geometry": {"coordinates":[75.08035700000001,14.33969],"type":"Point"}
}