{
  "type": "Feature",
  "properties": {
    "gn:admin1_code":"36.0",
    "gn:admin2_code":"134.0",
    "gn:asciiname":"Bhojawala",
    "gn:country_code":"IN",
    "gn:dem":255,
    "gn:feature_class":"P",
    "gn:feature_code":"PPL",
    "gn:name":"Bhoj\u0101w\u0101la",
    "gn:population":0,
    "gn:timezone":"Asia/Kolkata",
    "iso:country":"IN",
    "name:und_x_variant":[
        "Bhoj\u0101w\u0101la",
        "Mirza Al\u012bpur"
    ],
    "wof:name":"Bhojawala",
    "wof:placetype":"locality"
},
  "geometry": {"coordinates":[78.54693,29.43162],"type":"Point"}
}