{
  "type": "Feature",
  "properties": {
    "iso:country":"IN",
    "ks:ks_name":"Ramogodo",
    "ks:ks_pop":249,
    "ks:ks_type":"VILLAGE",
    "name:eng_x_preferred":[
        "Ramogodo"
    ],
    "wof:name":"Ramogodo",
    "wof:placetype":"locality",
    "wof:population":249
},
  "geometry": {"coordinates":[82.608242,18.925722],"type":"Point"}
}