{
  "type": "Feature",
  "properties": {
    "iso:country":"IN",
    "ks:ks_name":"Udranga",
    "ks:ks_pop":1574,
    "ks:ks_type":"VILLAGE",
    "ks:ks_uagg_main":0,
    "name:eng_x_preferred":[
        "Udranga"
    ],
    "wof:name":"Udranga",
    "wof:placetype":"neighbourhood",
    "wof:population":1574
},
  "geometry": {"coordinates":[86.428759,20.790646],"type":"Point"}
}