{
  "type": "Feature",
  "properties": {
    "gn:admin1_code":"36",
    "gn:admin2_code":"198.0",
    "gn:asciiname":"Danupurpatti",
    "gn:country_code":"IN",
    "gn:dem":90,
    "gn:feature_class":"P",
    "gn:feature_code":"PPL",
    "gn:name":"D\u0101n\u016bpurpatti",
    "gn:population":0,
    "gn:timezone":"Asia/Kolkata",
    "iso:country":"IN",
    "ks:ks_alt_nam":"D\u0101n\u016bpurpatti",
    "ks:ks_name":"Danupurpatti",
    "ks:ks_type":"VILLAGE",
    "ks:ks_uagg_main":0,
    "name:eng_x_preferred":[
        "Danupurpatti"
    ],
    "name:eng_x_variant":[
        "D\u0101n\u016bpurpatti"
    ],
    "wof:name":"Danupurpatti",
    "wof:placetype":"neighbourhood"
},
  "geometry": {"coordinates":[82.393331,25.405175],"type":"Point"}
}