{
  "type": "Feature",
  "properties": {
    "iso:country":"IN",
    "ks:ks_name":"10 DWD",
    "ks:ks_pop":254,
    "ks:ks_type":"VILLAGE",
    "name:eng_x_preferred":[
        "10 DWD"
    ],
    "wof:name":"10 DWD",
    "wof:placetype":"locality",
    "wof:population":254
},
  "geometry": {"coordinates":[74.468301,29.222868],"type":"Point"}
}