{
  "type": "Feature",
  "properties": {
    "gn:country":"IN",
    "gn:fcode":"PPL",
    "gn:pop":8518,
    "iso:country":"IN",
    "name:unk_x_variant":[
        "Adampur"
    ],
    "qs:name":"Sultanpur",
    "qs:name_adm0":"India",
    "qs:name_adm1":"Uttar Pradesh",
    "qs:photos_9r":0,
    "qs:photos_sr":0,
    "qs:placetype":"Town",
    "qs:pop_sr":"5",
    "wd:wordcount":96,
    "wof:name":"Sultanpur",
    "wof:placetype":"locality",
    "wof:population":8518
},
  "geometry": {"coordinates":[78.10894,29.75603],"type":"Point"}
}