{
  "type": "Feature",
  "properties": {
    "gn:country":"IN",
    "gn:fcode":"PPL",
    "gn:population":8518,
    "iso:country":"IN",
    "name:ben_x_preferred":[
        "\u09b8\u09c1\u09b2\u09a4\u09be\u09a8\u09aa\u09c1\u09b0"
    ],
    "name:bih_x_preferred":[
        "\u0938\u0941\u0932\u094d\u0924\u093e\u0928\u092a\u0941\u0930"
    ],
    "name:bpy_x_preferred":[
        "\u09b8\u09c1\u09b2\u09a4\u09be\u09a8\u09aa\u09c1\u09b0"
    ],
    "name:ceb_x_preferred":[
        "Sultanpur"
    ],
    "name:deu_x_preferred":[
        "Sultanpur"
    ],
    "name:ita_x_preferred":[
        "Sultanpur"
    ],
    "name:jpn_x_preferred":[
        "\u30b9\u30eb\u30bf\u30fc\u30f3\u30d7\u30eb"
    ],
    "name:nld_x_preferred":[
        "Sultanpur"
    ],
    "name:pol_x_preferred":[
        "Sultanpur"
    ],
    "name:rus_x_preferred":[
        "\u0421\u0443\u043b\u0442\u0430\u043d\u043f\u0443\u0440"
    ],
    "name:swe_x_preferred":[
        "Sultanpur"
    ],
    "name:und_x_variant":[
        "Adampur"
    ],
    "qs:name":"Sultanpur",
    "qs:name_adm0":"India",
    "qs:name_adm1":"Uttar Pradesh",
    "qs:photos_9r":0,
    "qs:photos_sr":0,
    "qs:placetype":"Town",
    "qs:pop_sr":"5",
    "wd:wordcount":96,
    "wof:name":"Sultanpur",
    "wof:placetype":"locality",
    "wof:population":8518
},
  "geometry": {"coordinates":[78.10894,29.75603],"type":"Point"}
}