{
  "type": "Feature",
  "properties": {
    "iso:country":"IN",
    "ks:ks_name":"Udayapur",
    "ks:ks_pop":283,
    "ks:ks_type":"VILLAGE",
    "name:eng_x_preferred":[
        "Udayapur"
    ],
    "wof:name":"Udayapur",
    "wof:placetype":"locality",
    "wof:population":283
},
  "geometry": {"coordinates":[86.302924,20.747875],"type":"Point"}
}