{
  "type": "Feature",
  "properties": {
    "iso:country":"IN",
    "ks:ks_name":"Panna",
    "ks:ks_pop":737,
    "ks:ks_type":"VILLAGE",
    "name:eng_x_preferred":[
        "Panna"
    ],
    "wof:name":"Panna",
    "wof:placetype":"locality",
    "wof:population":737
},
  "geometry": {"coordinates":[72.059106,27.857197],"type":"Point"}
}