{
  "type": "Feature",
  "properties": {
    "iso:country":"IN",
    "ks:ks_alt_nam":"GANDHI NAGAR",
    "ks:ks_name":"Gandhi Nagar",
    "ks:ks_pop":422,
    "ks:ks_type":"HABITATION",
    "name:eng_x_preferred":[
        "Gandhi Nagar"
    ],
    "wof:name":"Gandhi Nagar",
    "wof:placetype":"locality",
    "wof:population":422
},
  "geometry": {"coordinates":[84.575648,24.678685],"type":"Point"}
}