{
  "type": "Feature",
  "properties": {
    "iso:country":"IN",
    "ks:ks_name":"Bharkot Walla",
    "ks:ks_pop":20,
    "ks:ks_type":"VILLAGE",
    "ks:ks_uagg_main":0,
    "name:eng_x_preferred":[
        "Bharkot Walla"
    ],
    "wof:name":"Bharkot Walla",
    "wof:placetype":"neighbourhood",
    "wof:population":20
},
  "geometry": {"coordinates":[78.668762,30.155111],"type":"Point"}
}