{
  "type": "Feature",
  "properties": {
    "gn:admin1_code":"34.0",
    "gn:admin2_code":"207.0",
    "gn:asciiname":"Saharwa",
    "gn:country_code":"IN",
    "gn:dem":84,
    "gn:feature_class":"P",
    "gn:feature_code":"PPL",
    "gn:name":"Saharwa",
    "gn:population":0,
    "gn:timezone":"Asia/Kolkata",
    "iso:country":"IN",
    "ks:ks_alt_nam":"SAHARBA",
    "ks:ks_name":"Saharba",
    "ks:ks_pop":856,
    "ks:ks_type":"HABITATION",
    "name:eng_x_preferred":[
        "Saharba"
    ],
    "name:eng_x_variant":[
        "Saharwa"
    ],
    "wof:name":"Saharba",
    "wof:placetype":"locality",
    "wof:population":856
},
  "geometry": {"coordinates":[86.461333,26.538178],"type":"Point"}
}