{
  "type": "Feature",
  "properties": {
    "gn:admin1_code":"36",
    "gn:admin2_code":"154.0",
    "gn:asciiname":"Kothar",
    "gn:country_code":"IN",
    "gn:dem":125,
    "gn:feature_class":"P",
    "gn:feature_code":"PPL",
    "gn:name":"Kothar",
    "gn:population":0,
    "gn:timezone":"Asia/Kolkata",
    "iso:country":"IN",
    "name:snd_x_preferred":[
        "\u0622\u0628 \u06aa\u0648\u062b\u0631"
    ],
    "wof:name":"Kothar",
    "wof:placetype":"neighbourhood"
},
  "geometry": {"coordinates":[81.06957,27.52152],"type":"Point"}
}