{
  "type": "Feature",
  "properties": {
    "iso:country":"IN",
    "ks:ks_name":"Bramhchari Ka Pura",
    "ks:ks_pop":138,
    "ks:ks_type":"HABITATION",
    "ks:ks_uagg_main":0,
    "name:eng_x_preferred":[
        "Bramhchari Ka Pura"
    ],
    "wof:name":"Bramhchari Ka Pura",
    "wof:placetype":"neighbourhood",
    "wof:population":138
},
  "geometry": {"coordinates":[81.684872,26.330197],"type":"Point"}
}