{
  "type": "Feature",
  "properties": {
    "iso:country":"IN",
    "ks:ks_name":"Meteldebighata",
    "ks:ks_pop":243,
    "ks:ks_type":"VILLAGE",
    "name:eng_x_preferred":[
        "Meteldebighata"
    ],
    "wof:name":"Meteldebighata",
    "wof:placetype":"locality",
    "wof:population":243
},
  "geometry": {"coordinates":[87.337407,22.475289],"type":"Point"}
}