{
  "type": "Feature",
  "properties": {
    "iso:country":"IN",
    "ks:ks_name":"Gudgudpara",
    "ks:ks_pop":141,
    "ks:ks_type":"HABITATION",
    "name:eng_x_preferred":[
        "Gudgudpara"
    ],
    "wof:name":"Gudgudpara",
    "wof:placetype":"locality",
    "wof:population":141
},
  "geometry": {"coordinates":[84.21954100000001,22.372535],"type":"Point"}
}