{
  "type": "Feature",
  "properties": {
    "gn:admin1_code":"19.0",
    "gn:admin2_code":"576.0",
    "gn:asciiname":"Kyatanahalli",
    "gn:country_code":"IN",
    "gn:dem":971,
    "gn:feature_class":"P",
    "gn:feature_code":"PPL",
    "gn:name":"Kyatanahalli",
    "gn:population":0,
    "gn:timezone":"Asia/Kolkata",
    "iso:country":"IN",
    "ks:ks_name":"Kyathanahalli",
    "ks:ks_pop":211,
    "ks:ks_type":"HABITATION",
    "name:eng_x_preferred":[
        "Kyathanahalli"
    ],
    "name:eng_x_variant":[
        "Kyatanahalli"
    ],
    "wof:name":"Kyathanahalli",
    "wof:placetype":"locality",
    "wof:population":211
},
  "geometry": {"coordinates":[75.93944399999999,12.722222],"type":"Point"}
}