{
  "type": "Feature",
  "properties": {
    "gn:admin1_code":"19.0",
    "gn:admin2_code":"576.0",
    "gn:asciiname":"Kyatanahalli",
    "gn:country_code":"IN",
    "gn:dem":971,
    "gn:feature_class":"P",
    "gn:feature_code":"PPL",
    "gn:name":"Kyatanahalli",
    "gn:population":0,
    "gn:timezone":"Asia/Kolkata",
    "iso:country":"IN",
    "wof:name":"Kyatanahalli",
    "wof:placetype":"locality"
},
  "geometry": {"coordinates":[75.93252,12.71469],"type":"Point"}
}