{
  "type": "Feature",
  "properties": {
    "iso:country":"IN",
    "ks:ks_name":"Mendheghar",
    "ks:ks_pop":272,
    "ks:ks_type":"VILLAGE",
    "ks:ks_uagg_main":0,
    "name:eng_x_preferred":[
        "Mendheghar"
    ],
    "wof:name":"Mendheghar",
    "wof:placetype":"neighbourhood",
    "wof:population":272
},
  "geometry": {"coordinates":[73.726765,17.373405],"type":"Point"}
}