{
  "type": "Feature",
  "properties": {
    "gn:admin1_code":"19.0",
    "gn:admin2_code":"574.0",
    "gn:asciiname":"Guddenahalli",
    "gn:country_code":"IN",
    "gn:dem":905,
    "gn:feature_class":"P",
    "gn:feature_code":"PPL",
    "gn:name":"Guddenahalli",
    "gn:population":0,
    "gn:timezone":"Asia/Kolkata",
    "iso:country":"IN",
    "wof:name":"Guddenahalli",
    "wof:placetype":"neighbourhood"
},
  "geometry": {"coordinates":[76.19935,12.89297],"type":"Point"}
}