{
  "type": "Feature",
  "properties": {
    "iso:country":"IN",
    "ks:ks_name":"Kotra Purwa",
    "ks:ks_pop":87,
    "ks:ks_type":"HABITATION",
    "ks:ks_uagg_main":0,
    "name:eng_x_preferred":[
        "Kotra Purwa"
    ],
    "wof:name":"Kotra Purwa",
    "wof:placetype":"neighbourhood",
    "wof:population":87
},
  "geometry": {"coordinates":[80.97496700000001,27.535754],"type":"Point"}
}