{
  "type": "Feature",
  "properties": {
    "iso:country":"IN",
    "ks:ks_name":"Kharagpur",
    "ks:ks_pop":873,
    "ks:ks_type":"VILLAGE",
    "ks:ks_uagg_main":0,
    "name:eng_x_preferred":[
        "Kharagpur"
    ],
    "wof:name":"Kharagpur",
    "wof:placetype":"neighbourhood",
    "wof:population":873
},
  "geometry": {"coordinates":[78.12064700000001,26.399247],"type":"Point"}
}