{
  "type": "Feature",
  "properties": {
    "gn:admin1_code":"11.0",
    "gn:admin2_code":"32.0",
    "gn:asciiname":"Karauli",
    "gn:country_code":"IN",
    "gn:dem":748,
    "gn:feature_class":"P",
    "gn:feature_code":"PPL",
    "gn:name":"Karauli",
    "gn:population":0,
    "gn:timezone":"Asia/Kolkata",
    "iso:country":"IN",
    "name:ben_x_preferred":[
        "\u0995\u09be\u09b0\u09cc\u09b2\u09bf"
    ],
    "name:bpy_x_preferred":[
        "\u0995\u09be\u09b0\u09cc\u09b2\u09bf"
    ],
    "name:cat_x_preferred":[
        "Karauli"
    ],
    "name:ceb_x_preferred":[
        "Karauli"
    ],
    "name:deu_x_preferred":[
        "Karauli"
    ],
    "name:fra_x_preferred":[
        "Karauli"
    ],
    "name:guj_x_preferred":[
        "\u0a95\u0ab0\u0acc\u0ab2\u0ac0"
    ],
    "name:hin_x_preferred":[
        "\u0915\u0930\u094c\u0932\u0940"
    ],
    "name:ita_x_preferred":[
        "Karauli"
    ],
    "name:mar_x_preferred":[
        "\u0915\u0930\u094c\u0932\u0940"
    ],
    "name:mlg_x_preferred":[
        "Karauli"
    ],
    "name:msa_x_preferred":[
        "Karauli"
    ],
    "name:new_x_preferred":[
        "\u0915\u0930\u094c\u0932\u0940"
    ],
    "name:rus_x_preferred":[
        "\u041a\u0430\u0440\u0430\u0443\u043b\u0438"
    ],
    "name:san_x_preferred":[
        "\u0915\u0930\u094c\u0932\u0940"
    ],
    "name:swe_x_preferred":[
        "Karauli"
    ],
    "name:urd_x_preferred":[
        "\u06a9\u0627\u0631\u0648\u0644\u06cc"
    ],
    "name:vie_x_preferred":[
        "Karauli"
    ],
    "name:xmf_x_preferred":[
        "\u10d9\u10d0\u10e0\u10d0\u10e3\u10da\u10d8"
    ],
    "name:zho_x_preferred":[
        "\u5361\u52b3\u5229"
    ],
    "wof:name":"Karauli",
    "wof:placetype":"locality"
},
  "geometry": {"coordinates":[77.27379999999999,30.59798],"type":"Point"}
}