{
  "type": "Feature",
  "properties": {
    "iso:country":"IN",
    "ks:ks_alt_nam":"Thacherampattu ADC",
    "ks:ks_name":"Thacherampattu Adc",
    "ks:ks_pop":174,
    "ks:ks_type":"HABITATION",
    "name:eng_x_preferred":[
        "Thacherampattu Adc"
    ],
    "wof:name":"Thacherampattu Adc",
    "wof:placetype":"locality",
    "wof:population":174
},
  "geometry": {"coordinates":[79.218524,12.657404],"type":"Point"}
}