{
  "type": "Feature",
  "properties": {
    "gn:admin1_code":"23.0",
    "gn:admin2_code":"43.0",
    "gn:asciiname":"Sodhiwala",
    "gn:country_code":"IN",
    "gn:dem":192,
    "gn:feature_class":"P",
    "gn:feature_code":"PPL",
    "gn:name":"Sodh\u012bw\u0101la",
    "gn:population":0,
    "gn:timezone":"Asia/Kolkata",
    "iso:country":"IN",
    "ks:ks_alt_nam":"Sodh\u012bw\u0101la",
    "ks:ks_name":"Sodhiwala",
    "ks:ks_type":"VILLAGE",
    "name:eng_x_preferred":[
        "Sodhiwala"
    ],
    "name:eng_x_variant":[
        "Sodh\u012bw\u0101la"
    ],
    "wof:name":"Sodhiwala",
    "wof:placetype":"locality"
},
  "geometry": {"coordinates":[74.539181,30.908894],"type":"Point"}
}