{
  "type": "Feature",
  "properties": {
    "gn:admin1_code":"25.0",
    "gn:admin2_code":"605.0",
    "gn:asciiname":"Padi",
    "gn:country_code":"IN",
    "gn:dem":175,
    "gn:feature_class":"P",
    "gn:feature_code":"PPL",
    "gn:name":"P\u0101di",
    "gn:population":0,
    "gn:timezone":"Asia/Kolkata",
    "iso:country":"IN",
    "name:ceb_x_preferred":[
        "Padi"
    ],
    "name:deu_x_preferred":[
        "PADI"
    ],
    "name:ind_x_preferred":[
        "Padi"
    ],
    "name:msa_x_preferred":[
        "Padi sawah"
    ],
    "name:nld_x_preferred":[
        "Padi"
    ],
    "name:rus_x_preferred":[
        "PADI"
    ],
    "name:swe_x_preferred":[
        "Padi"
    ],
    "name:vie_x_preferred":[
        "Padi"
    ],
    "wof:name":"Padi",
    "wof:placetype":"locality"
},
  "geometry": {"coordinates":[79.29288000000003,12.82548],"type":"Point"}
}