{
  "type": "Feature",
  "properties": {
    "iso:country":"IN",
    "ks:ks_name":"Koduka",
    "ks:ks_pop":150,
    "ks:ks_type":"VILLAGE",
    "name:eng_x_preferred":[
        "Koduka"
    ],
    "wof:name":"Koduka",
    "wof:placetype":"locality",
    "wof:population":150
},
  "geometry": {"coordinates":[72.289922,26.044239],"type":"Point"}
}