{
  "type": "Feature",
  "properties": {
    "gn:admin1_code":"25.0",
    "gn:admin2_code":"610.0",
    "gn:asciiname":"Unjalur",
    "gn:country_code":"IN",
    "gn:dem":148,
    "gn:feature_class":"P",
    "gn:feature_code":"PPL",
    "gn:name":"Unjal\u016br",
    "gn:population":0,
    "gn:timezone":"Asia/Kolkata",
    "iso:country":"IN",
    "name:bpy_x_preferred":[
        "\u0989\u09a8\u09cd\u099c\u09be\u09b2\u09c1\u09b0"
    ],
    "name:ind_x_preferred":[
        "Unjalaur"
    ],
    "name:ita_x_preferred":[
        "Unjalur"
    ],
    "name:msa_x_preferred":[
        "Unjalaur"
    ],
    "name:nld_x_preferred":[
        "Unjalaur"
    ],
    "name:por_x_preferred":[
        "Unjalaur"
    ],
    "name:tam_x_preferred":[
        "\u0b8a\u0b9e\u0bcd\u0b9a\u0bb2\u0bc2\u0bb0\u0bcd"
    ],
    "name:vie_x_preferred":[
        "Unjalaur"
    ],
    "name:zho_x_preferred":[
        "\u4e4c\u6069\u8d3e\u52b3\u5c14"
    ],
    "wof:name":"Unjalur",
    "wof:placetype":"locality"
},
  "geometry": {"coordinates":[77.86959,11.1278],"type":"Point"}
}