{
  "type": "Feature",
  "properties": {
    "iso:country":"IN",
    "ks:ks_name":"Ranewadi",
    "ks:ks_pop":90,
    "ks:ks_type":"HABITATION",
    "name:eng_x_preferred":[
        "Ranewadi"
    ],
    "wof:name":"Ranewadi",
    "wof:placetype":"locality",
    "wof:population":90
},
  "geometry": {"coordinates":[73.481696,16.441056],"type":"Point"}
}