{
  "type": "Feature",
  "properties": {
    "iso:country":"IN",
    "ks:ks_name":"Masarmanekeri",
    "ks:ks_pop":13,
    "ks:ks_type":"HABITATION",
    "name:eng_x_preferred":[
        "Masarmanekeri"
    ],
    "wof:name":"Masarmanekeri",
    "wof:placetype":"locality",
    "wof:population":13
},
  "geometry": {"coordinates":[74.41569699999999,14.469663],"type":"Point"}
}