{
  "type": "Feature",
  "properties": {
    "iso:country":"IN",
    "ks:ks_name":"Brigadur Farm",
    "ks:ks_pop":98,
    "ks:ks_type":"HABITATION",
    "name:eng_x_preferred":[
        "Brigadur Farm"
    ],
    "wof:name":"Brigadur Farm",
    "wof:placetype":"locality",
    "wof:population":98
},
  "geometry": {"coordinates":[79.225705,28.934927],"type":"Point"}
}