{
  "type": "Feature",
  "properties": {
    "iso:country":"IN",
    "ks:ks_name":"Convent Rd",
    "ks:ks_pop":245,
    "ks:ks_type":"HABITATION",
    "ks:ks_uagg_main":0,
    "name:eng_x_preferred":[
        "Convent Rd"
    ],
    "wof:name":"Convent Rd",
    "wof:placetype":"neighbourhood",
    "wof:population":245
},
  "geometry": {"coordinates":[76.29191400000001,10.429389],"type":"Point"}
}