{
  "type": "Feature",
  "properties": {
    "gn:admin1_code":"19",
    "gn:admin2_code":"556.0",
    "gn:asciiname":"Amaravadgi",
    "gn:country_code":"IN",
    "gn:dem":495,
    "gn:feature_class":"P",
    "gn:feature_code":"PPL",
    "gn:name":"Amar\u0101v\u0101dgi",
    "gn:population":0,
    "gn:timezone":"Asia/Kolkata",
    "iso:country":"IN",
    "wof:name":"Amaravadgi",
    "wof:placetype":"locality"
},
  "geometry": {"coordinates":[76.22431999999998,16.15405],"type":"Point"}
}