{
  "type": "Feature",
  "properties": {
    "gn:admin1_code":"39.0",
    "gn:admin2_code":"64.0",
    "gn:asciiname":"Kaligaon",
    "gn:country_code":"IN",
    "gn:dem":1318,
    "gn:feature_class":"P",
    "gn:feature_code":"PPL",
    "gn:name":"K\u0101l\u012bgaon",
    "gn:population":0,
    "gn:timezone":"Asia/Kolkata",
    "iso:country":"IN",
    "ks:ks_name":"Kaligaon",
    "ks:ks_pop":155,
    "ks:ks_type":"HABITATION",
    "name:eng_x_preferred":[
        "Kaligaon"
    ],
    "wof:name":"Kaligaon",
    "wof:placetype":"locality",
    "wof:population":155
},
  "geometry": {"coordinates":[79.156278,29.696053],"type":"Point"}
}