{
  "type": "Feature",
  "properties": {
    "gn:admin1_code":"11.0",
    "gn:admin2_code":"33.0",
    "gn:asciiname":"Cheonabadlaug",
    "gn:country_code":"IN",
    "gn:dem":2205,
    "gn:feature_class":"P",
    "gn:feature_code":"PPL",
    "gn:name":"Cheon\u0101badlaug",
    "gn:population":0,
    "gn:timezone":"Asia/Kolkata",
    "iso:country":"IN",
    "wof:name":"Cheonabadlaug",
    "wof:placetype":"locality"
},
  "geometry": {"coordinates":[77.48679,31.00749],"type":"Point"}
}