{
  "type": "Feature",
  "properties": {
    "iso:country":"IN",
    "ks:ks_name":"Yedlavanipeta",
    "ks:ks_pop":170,
    "ks:ks_type":"HABITATION",
    "name:eng_x_preferred":[
        "Yedlavanipeta"
    ],
    "wof:name":"Yedlavanipeta",
    "wof:placetype":"locality",
    "wof:population":170
},
  "geometry": {"coordinates":[84.02836000000001,18.536255],"type":"Point"}
}