{
  "type": "Feature",
  "properties": {
    "iso:country":"IN",
    "ks:ks_alt_nam":"bankati",
    "ks:ks_name":"Bankati",
    "ks:ks_pop":104,
    "ks:ks_type":"HABITATION",
    "name:eng_x_preferred":[
        "Bankati"
    ],
    "wof:name":"Bankati",
    "wof:placetype":"locality",
    "wof:population":104
},
  "geometry": {"coordinates":[86.947602,24.087847],"type":"Point"}
}