{
  "type": "Feature",
  "properties": {
    "iso:country":"IN",
    "ks:ks_name":"Kagra",
    "ks:ks_pop":507,
    "ks:ks_type":"VILLAGE",
    "name:eng_x_preferred":[
        "Kagra"
    ],
    "wof:name":"Kagra",
    "wof:placetype":"locality",
    "wof:population":507
},
  "geometry": {"coordinates":[74.121022,24.157742],"type":"Point"}
}