{
  "type": "Feature",
  "properties": {
    "gn:admin1_code":"03",
    "gn:admin2_code":"323.0",
    "gn:asciiname":"Ulubari",
    "gn:country_code":"IN",
    "gn:dem":49,
    "gn:feature_class":"P",
    "gn:feature_code":"PPL",
    "gn:name":"Ulub\u0101ri",
    "gn:population":0,
    "gn:timezone":"Asia/Kolkata",
    "iso:country":"IN",
    "wof:name":"Ulubari",
    "wof:placetype":"neighbourhood"
},
  "geometry": {"coordinates":[91.27173999999999,26.36996],"type":"Point"}
}