{
  "type": "Feature",
  "properties": {
    "iso:country":"IN",
    "ks:ks_name":"Shrungarwasti",
    "ks:ks_pop":313,
    "ks:ks_type":"HABITATION",
    "name:eng_x_preferred":[
        "Shrungarwasti"
    ],
    "wof:name":"Shrungarwasti",
    "wof:placetype":"locality",
    "wof:population":313
},
  "geometry": {"coordinates":[74.561431,19.376312],"type":"Point"}
}