{
  "type": "Feature",
  "properties": {
    "iso:country":"IN",
    "ks:ks_name":"Zarligaon",
    "ks:ks_pop":355,
    "ks:ks_type":"HABITATION",
    "name:eng_x_preferred":[
        "Zarligaon"
    ],
    "wof:name":"Zarligaon",
    "wof:placetype":"locality",
    "wof:population":355
},
  "geometry": {"coordinates":[72.763313,20.036737],"type":"Point"}
}