{
  "type": "Feature",
  "properties": {
    "iso:country":"IN",
    "ks:ks_name":"Khandoli",
    "ks:ks_pop":8,
    "ks:ks_type":"VILLAGE",
    "name:eng_x_preferred":[
        "Khandoli"
    ],
    "wof:name":"Khandoli",
    "wof:placetype":"locality",
    "wof:population":8
},
  "geometry": {"coordinates":[78.833022,29.99954],"type":"Point"}
}