{
  "type": "Feature",
  "properties": {
    "iso:country":"IN",
    "ks:ks_name":"Dhaneda",
    "ks:ks_pop":713,
    "ks:ks_type":"VILLAGE",
    "name:eng_x_preferred":[
        "Dhaneda"
    ],
    "wof:name":"Dhaneda",
    "wof:placetype":"locality",
    "wof:population":713
},
  "geometry": {"coordinates":[81.25017800000001,23.926817],"type":"Point"}
}