{
  "type": "Feature",
  "properties": {
    "iso:country":"IN",
    "ks:ks_name":"Inani Khera",
    "ks:ks_pop":696,
    "ks:ks_type":"VILLAGE",
    "name:eng_x_preferred":[
        "Inani Khera"
    ],
    "wof:name":"Inani Khera",
    "wof:placetype":"locality",
    "wof:population":696
},
  "geometry": {"coordinates":[74.519103,25.708025],"type":"Point"}
}