{
  "type": "Feature",
  "properties": {
    "iso:country":"IN",
    "ks:ks_name":"Kuzhiyodu",
    "ks:ks_pop":769,
    "ks:ks_type":"HABITATION",
    "name:eng_x_preferred":[
        "Kuzhiyodu"
    ],
    "wof:name":"Kuzhiyodu",
    "wof:placetype":"locality",
    "wof:population":769
},
  "geometry": {"coordinates":[76.26708000000001,10.672006],"type":"Point"}
}