{
  "type": "Feature",
  "properties": {
    "gn:admin1_code":"38.0",
    "gn:admin2_code":"347.0",
    "gn:asciiname":"Sonpura Bigha",
    "gn:country_code":"IN",
    "gn:dem":221,
    "gn:feature_class":"P",
    "gn:feature_code":"PPL",
    "gn:name":"Sonpura Bigha",
    "gn:population":0,
    "gn:timezone":"Asia/Kolkata",
    "iso:country":"IN",
    "ks:ks_name":"Sonepurbigha",
    "ks:ks_pop":784,
    "ks:ks_type":"VILLAGE",
    "ks:ks_uagg_main":0,
    "name:eng_x_preferred":[
        "Sonepurbigha"
    ],
    "wof:name":"Sonepurbigha",
    "wof:placetype":"neighbourhood",
    "wof:population":784
},
  "geometry": {"coordinates":[84.686409,24.389561],"type":"Point"}
}