{
  "type": "Feature",
  "properties": {
    "iso:country":"IN",
    "ks:ks_alt_nam":"panyya",
    "ks:ks_name":"Panyya",
    "ks:ks_pop":235,
    "ks:ks_type":"HABITATION",
    "name:eng_x_preferred":[
        "Panyya"
    ],
    "wof:name":"Panyya",
    "wof:placetype":"locality",
    "wof:population":235
},
  "geometry": {"coordinates":[75.829215,12.47143],"type":"Point"}
}