{
  "type": "Feature",
  "properties": {
    "gn:admin1_code":"25.0",
    "gn:admin2_code":"611.0",
    "gn:asciiname":"Kerayada",
    "gn:country_code":"IN",
    "gn:dem":2031,
    "gn:feature_class":"P",
    "gn:feature_code":"PPL",
    "gn:name":"Keray\u0101da",
    "gn:population":0,
    "gn:timezone":"Asia/Kolkata",
    "iso:country":"IN",
    "name:ara_x_preferred":[
        "\u0643\u064a\u0631\u0627\u064a\u0627\u062f\u0627"
    ],
    "name:ben_bn_x_preferred":[
        "\u0995\u09c7\u09b0\u09be\u09df\u09be\u09a1\u09be"
    ],
    "name:ben_in_x_preferred":[
        "\u0995\u09c7\u09b0\u09be\u09df\u09be\u09a1\u09be"
    ],
    "name:guj_x_preferred":[
        "\u0a95\u0ac7\u0ab0\u0abe\u0aaf\u0aa6\u0abe"
    ],
    "name:hin_x_preferred":[
        "\u0915\u0947\u0930\u093e\u092f\u0926\u093e"
    ],
    "name:kan_x_preferred":[
        "\u0c95\u0cc6\u0cb0\u0caf\u0cbe\u0ca6"
    ],
    "name:mal_x_preferred":[
        "\u0d15\u0d46\u0d30\u0d2f\u0d1f"
    ],
    "name:mar_x_preferred":[
        "\u0915\u0947\u0930\u092f\u0926\u093e"
    ],
    "name:pan_x_preferred":[
        "\u0a15\u0a48\u0a30\u0a3e\u0a2f\u0a3e\u0a26\u0a3e"
    ],
    "name:tam_x_preferred":[
        "\u0b95\u0bc6\u0bb0\u0baf\u0b9f\u0bbe"
    ],
    "name:tel_x_preferred":[
        "\u0c15\u0c46\u0c30\u0c2f\u0c3e\u0c21\u0c3e"
    ],
    "name:urd_x_preferred":[
        "\u06a9\u06cc\u0631\u0627\u06cc\u0627\u0688\u0627"
    ],
    "wof:name":"Kerayada",
    "wof:placetype":"locality"
},
  "geometry": {"coordinates":[76.71499,11.37525],"type":"Point"}
}