{
  "type": "Feature",
  "properties": {
    "gn:admin1_code":"12.0",
    "gn:admin2_code":"5.0",
    "gn:asciiname":"Gurndwara",
    "gn:country_code":"IN",
    "gn:dem":1112,
    "gn:feature_class":"P",
    "gn:feature_code":"PPL",
    "gn:name":"Gurndwara",
    "gn:population":0,
    "gn:timezone":"Asia/Kolkata",
    "iso:country":"IN",
    "wof:name":"Gurndwara",
    "wof:placetype":"locality"
},
  "geometry": {"coordinates":[74.14423000000002,33.77177],"type":"Point"}
}