{
  "type": "Feature",
  "properties": {
    "iso:country":"IN",
    "ks:ks_name":"East Dharmabarerkuthi",
    "ks:ks_pop":1452,
    "ks:ks_type":"HABITATION",
    "name:eng_x_preferred":[
        "East Dharmabarerkuthi"
    ],
    "wof:name":"East Dharmabarerkuthi",
    "wof:placetype":"locality",
    "wof:population":1452
},
  "geometry": {"coordinates":[89.50646,26.414345],"type":"Point"}
}