{
  "type": "Feature",
  "properties": {
    "iso:country":"IN",
    "ks:ks_name":"3 CYM",
    "ks:ks_pop":13,
    "ks:ks_type":"VILLAGE",
    "name:eng_x_preferred":[
        "3 CYM"
    ],
    "wof:name":"3 CYM",
    "wof:placetype":"locality",
    "wof:population":13
},
  "geometry": {"coordinates":[74.47281,29.241851],"type":"Point"}
}