{
  "type": "Feature",
  "properties": {
    "iso:country":"IN",
    "ks:ks_name":"Noorpur Ki Madhiyan",
    "ks:ks_pop":1120,
    "ks:ks_type":"HABITATION",
    "name:eng_x_preferred":[
        "Noorpur Ki Madhiyan"
    ],
    "wof:name":"Noorpur Ki Madhiyan",
    "wof:placetype":"locality",
    "wof:population":1120
},
  "geometry": {"coordinates":[77.834219,28.544368],"type":"Point"}
}