{
  "type": "Feature",
  "properties": {
    "iso:country":"IN",
    "ks:ks_name":"Pylapeta",
    "ks:ks_pop":214,
    "ks:ks_type":"HABITATION",
    "name:eng_x_preferred":[
        "Pylapeta"
    ],
    "wof:name":"Pylapeta",
    "wof:placetype":"locality",
    "wof:population":214
},
  "geometry": {"coordinates":[83.338554,17.910489],"type":"Point"}
}