{
  "type": "Feature",
  "properties": {
    "iso:country":"IN",
    "ks:ks_name":"Chichekatta",
    "ks:ks_pop":81,
    "ks:ks_type":"HABITATION",
    "name:eng_x_preferred":[
        "Chichekatta"
    ],
    "wof:name":"Chichekatta",
    "wof:placetype":"locality",
    "wof:population":81
},
  "geometry": {"coordinates":[80.59880099999999,19.908825],"type":"Point"}
}