{
  "type": "Feature",
  "properties": {
    "gn:admin1_code":"19",
    "gn:admin2_code":"556.0",
    "gn:asciiname":"Kamaldini",
    "gn:country_code":"IN",
    "gn:dem":501,
    "gn:feature_class":"P",
    "gn:feature_code":"PPL",
    "gn:name":"Kamaldini",
    "gn:population":0,
    "gn:timezone":"Asia/Kolkata",
    "iso:country":"IN",
    "wof:name":"Kamaldini",
    "wof:placetype":"locality"
},
  "geometry": {"coordinates":[76.18909000000002,16.14061],"type":"Point"}
}