{
  "type": "Feature",
  "properties": {
    "iso:country":"IN",
    "ks:ks_name":"Kotesara",
    "ks:ks_pop":35,
    "ks:ks_type":"HABITATION",
    "name:eng_x_preferred":[
        "Kotesara"
    ],
    "wof:name":"Kotesara",
    "wof:placetype":"locality",
    "wof:population":35
},
  "geometry": {"coordinates":[74.908147,14.688616],"type":"Point"}
}