{
  "type": "Feature",
  "properties": {
    "iso:country":"IN",
    "ks:ks_name":"Jamkani Parsapara",
    "ks:ks_pop":406,
    "ks:ks_type":"HABITATION",
    "name:eng_x_preferred":[
        "Jamkani Parsapara"
    ],
    "wof:name":"Jamkani Parsapara",
    "wof:placetype":"locality",
    "wof:population":406
},
  "geometry": {"coordinates":[83.381517,22.663807],"type":"Point"}
}