{
  "type": "Feature",
  "properties": {
    "iso:country":"IN",
    "ks:ks_name":"Tujer",
    "ks:ks_pop":294,
    "ks:ks_type":"VILLAGE",
    "name:eng_x_preferred":[
        "Tujer"
    ],
    "wof:name":"Tujer",
    "wof:placetype":"locality",
    "wof:population":294
},
  "geometry": {"coordinates":[82.972769,19.425539],"type":"Point"}
}