{
  "type": "Feature",
  "properties": {
    "gn:admin1_code":"13.0",
    "gn:admin2_code":"592.0",
    "gn:asciiname":"Valambur",
    "gn:country_code":"IN",
    "gn:dem":50,
    "gn:feature_class":"P",
    "gn:feature_code":"PPL",
    "gn:name":"Valambur",
    "gn:population":0,
    "gn:timezone":"Asia/Kolkata",
    "iso:country":"IN",
    "name:mal_x_preferred":[
        "\u0d35\u0d32\u0d2e\u0d4d\u0d2a\u0d42\u0d7c"
    ],
    "wof:name":"Valambur",
    "wof:placetype":"locality"
},
  "geometry": {"coordinates":[76.21110999999998,11.00812],"type":"Point"}
}