{
  "type": "Feature",
  "properties": {
    "gn:admin1_code":"13.0",
    "gn:admin2_code":"592.0",
    "gn:asciiname":"Valambur",
    "gn:country_code":"IN",
    "gn:dem":50,
    "gn:feature_class":"P",
    "gn:feature_code":"PPL",
    "gn:name":"Valambur",
    "gn:population":0,
    "gn:timezone":"Asia/Kolkata",
    "iso:country":"IN",
    "ks:ks_name":"Valambur",
    "ks:ks_pop":24841,
    "ks:ks_type":"VILLAGE",
    "name:eng_x_preferred":[
        "Valambur"
    ],
    "name:mal_x_preferred":[
        "\u0d35\u0d32\u0d2e\u0d4d\u0d2a\u0d42\u0d7c"
    ],
    "wof:name":"Valambur",
    "wof:placetype":"locality",
    "wof:population":24841
},
  "geometry": {"coordinates":[76.206986,11.009955],"type":"Point"}
}