{
  "type": "Feature",
  "properties": {
    "gn:admin1_code":"36",
    "gn:admin2_code":"182.0",
    "gn:asciiname":"Raniganj",
    "gn:country_code":"IN",
    "gn:dem":177,
    "gn:feature_class":"P",
    "gn:feature_code":"PPL",
    "gn:name":"R\u0101n\u012bganj",
    "gn:population":0,
    "gn:timezone":"Asia/Kolkata",
    "iso:country":"IN",
    "wof:name":"Raniganj",
    "wof:placetype":"locality"
},
  "geometry": {"coordinates":[82.51666999999998,27.65],"type":"Point"}
}