{
  "type": "Feature",
  "properties": {
    "gn:admin1_code":"36.0",
    "gn:admin2_code":"162",
    "gn:asciiname":"Rahtauli",
    "gn:country_code":"IN",
    "gn:dem":139,
    "gn:feature_class":"P",
    "gn:feature_code":"PPL",
    "gn:name":"Rahtauli",
    "gn:population":0,
    "gn:timezone":"Asia/Kolkata",
    "iso:country":"IN",
    "wof:name":"Rahtauli",
    "wof:placetype":"locality"
},
  "geometry": {"coordinates":[79.36763000000001,26.45193],"type":"Point"}
}