{
  "type": "Feature",
  "properties": {
    "iso:country":"IN",
    "ks:ks_name":"Kumar Tola",
    "ks:ks_pop":1000,
    "ks:ks_type":"HABITATION",
    "name:eng_x_preferred":[
        "Kumar Tola"
    ],
    "wof:name":"Kumar Tola",
    "wof:placetype":"locality",
    "wof:population":1000
},
  "geometry": {"coordinates":[86.159181,25.378469],"type":"Point"}
}