{
  "type": "Feature",
  "properties": {
    "iso:country":"IN",
    "ks:ks_name":"Pokhnapadar",
    "ks:ks_pop":157,
    "ks:ks_type":"HABITATION",
    "name:eng_x_preferred":[
        "Pokhnapadar"
    ],
    "wof:name":"Pokhnapadar",
    "wof:placetype":"locality",
    "wof:population":157
},
  "geometry": {"coordinates":[82.35898400000001,20.742378],"type":"Point"}
}