{
  "type": "Feature",
  "properties": {
    "gn:admin1_code":"19",
    "gn:admin2_code":"558.0",
    "gn:asciiname":"Khanapurwadi",
    "gn:country_code":"IN",
    "gn:dem":670,
    "gn:feature_class":"P",
    "gn:feature_code":"PPL",
    "gn:name":"Kh\u0101n\u0101purw\u0101di",
    "gn:population":0,
    "gn:timezone":"Asia/Kolkata",
    "iso:country":"IN",
    "wof:name":"Khanapurwadi",
    "wof:placetype":"locality"
},
  "geometry": {"coordinates":[76.90484000000002,17.84992],"type":"Point"}
}