{
  "type": "Feature",
  "properties": {
    "iso:country":"IN",
    "ks:ks_name":"Doddakundur",
    "ks:ks_pop":911,
    "ks:ks_type":"VILLAGE",
    "ks:ks_uagg_main":0,
    "name:eng_x_preferred":[
        "Doddakundur"
    ],
    "wof:name":"Doddakundur",
    "wof:placetype":"neighbourhood",
    "wof:population":911
},
  "geometry": {"coordinates":[75.654625,13.697118],"type":"Point"}
}