{
  "type": "Feature",
  "properties": {
    "gn:admin1_code":"34.0",
    "gn:admin2_code":"207.0",
    "gn:asciiname":"Auraha",
    "gn:country_code":"IN",
    "gn:dem":74,
    "gn:feature_class":"P",
    "gn:feature_code":"PPL",
    "gn:name":"Aur\u0101ha",
    "gn:population":0,
    "gn:timezone":"Asia/Kolkata",
    "iso:country":"IN",
    "name:ceb_x_preferred":[
        "Auraha"
    ],
    "name:fra_x_preferred":[
        "Auraha"
    ],
    "name:mai_x_preferred":[
        "\u0914\u0930\u093e\u0939\u093e"
    ],
    "name:msa_x_preferred":[
        "Auraha"
    ],
    "name:nep_x_preferred":[
        "\u0914\u0930\u093e\u0939\u093e"
    ],
    "name:new_x_preferred":[
        "\u0914\u0930\u093e\u0939\u093e"
    ],
    "name:pol_x_preferred":[
        "Auraha"
    ],
    "wof:name":"Auraha",
    "wof:placetype":"locality"
},
  "geometry": {"coordinates":[86.24750999999998,26.50119],"type":"Point"}
}