{
  "type": "Feature",
  "properties": {
    "iso:country":"IN",
    "ks:ks_name":"Tandoli Khalsa",
    "ks:ks_pop":960,
    "ks:ks_type":"VILLAGE",
    "name:eng_x_preferred":[
        "Tandoli Khalsa"
    ],
    "wof:name":"Tandoli Khalsa",
    "wof:placetype":"locality",
    "wof:population":960
},
  "geometry": {"coordinates":[78.60781900000001,27.797856],"type":"Point"}
}