{
  "type": "Feature",
  "properties": {
    "gn:admin1_code":"39.0",
    "gn:admin2_code":"060",
    "gn:asciiname":"Jitgarh",
    "gn:country_code":"IN",
    "gn:dem":486,
    "gn:feature_class":"P",
    "gn:feature_code":"PPL",
    "gn:name":"J\u012btgarh",
    "gn:population":0,
    "gn:timezone":"Asia/Kolkata",
    "iso:country":"IN",
    "name:und_x_variant":[
        "J\u012btgarh",
        "J\u012bgarh"
    ],
    "wof:name":"Jitgarh",
    "wof:placetype":"locality"
},
  "geometry": {"coordinates":[77.79477,30.4485],"type":"Point"}
}