{
  "type": "Feature",
  "properties": {
    "iso:country":"IN",
    "ks:ks_name":"Harodih",
    "ks:ks_pop":366,
    "ks:ks_type":"VILLAGE",
    "name:eng_x_preferred":[
        "Harodih"
    ],
    "wof:name":"Harodih",
    "wof:placetype":"locality",
    "wof:population":366
},
  "geometry": {"coordinates":[86.840954,24.406854],"type":"Point"}
}