{
  "type": "Feature",
  "properties": {
    "iso:country":"IN",
    "ks:ks_name":"Sankpur",
    "ks:ks_pop":843,
    "ks:ks_type":"VILLAGE",
    "name:eng_x_preferred":[
        "Sankpur"
    ],
    "wof:name":"Sankpur",
    "wof:placetype":"locality",
    "wof:population":843
},
  "geometry": {"coordinates":[88.305418,23.031262],"type":"Point"}
}