{
  "type": "Feature",
  "properties": {
    "iso:country":"IN",
    "ks:ks_name":"Dongaritola",
    "ks:ks_pop":234,
    "ks:ks_type":"VILLAGE",
    "name:eng_x_preferred":[
        "Dongaritola"
    ],
    "wof:name":"Dongaritola",
    "wof:placetype":"locality",
    "wof:population":234
},
  "geometry": {"coordinates":[81.504621,23.460848],"type":"Point"}
}