{
  "type": "Feature",
  "properties": {
    "gn:admin1_code":"34.0",
    "gn:admin2_code":"237.0",
    "gn:asciiname":"Sonwe",
    "gn:country_code":"IN",
    "gn:dem":129,
    "gn:feature_class":"P",
    "gn:feature_code":"PPL",
    "gn:name":"Sonwe",
    "gn:population":0,
    "gn:timezone":"Asia/Kolkata",
    "iso:country":"IN",
    "ks:ks_name":"Sonwe",
    "ks:ks_pop":524,
    "ks:ks_type":"VILLAGE",
    "ks:ks_uagg_main":0,
    "name:eng_x_preferred":[
        "Sonwe"
    ],
    "wof:name":"Sonwe",
    "wof:placetype":"neighbourhood",
    "wof:population":524
},
  "geometry": {"coordinates":[85.42051600000001,24.679051],"type":"Point"}
}