{
  "type": "Feature",
  "properties": {
    "iso:country":"IN",
    "ks:ks_name":"Majarekoppa",
    "ks:ks_pop":367,
    "ks:ks_type":"HABITATION",
    "name:eng_x_preferred":[
        "Majarekoppa"
    ],
    "wof:name":"Majarekoppa",
    "wof:placetype":"locality",
    "wof:population":367
},
  "geometry": {"coordinates":[75.832717,16.367586],"type":"Point"}
}