{
  "type": "Feature",
  "properties": {
    "iso:country":"IN",
    "ks:ks_name":"Baba Ka Dhora",
    "ks:ks_pop":508,
    "ks:ks_type":"HABITATION",
    "name:eng_x_preferred":[
        "Baba Ka Dhora"
    ],
    "wof:name":"Baba Ka Dhora",
    "wof:placetype":"locality",
    "wof:population":508
},
  "geometry": {"coordinates":[72.686661,27.441614],"type":"Point"}
}