{
  "type": "Feature",
  "properties": {
    "gn:country":"IN",
    "gn:fcode":"PPL",
    "gn:pop":10720,
    "iso:country":"IN",
    "name:bpy_x_preferred":[
        "\u09ae\u09be\u09a8\u09ac\u09b2\u0995\u09c1\u09b0\u09bf\u099a\u09bf"
    ],
    "name:bul_x_preferred":[
        "\u041c\u0430\u043d\u0430\u0432\u0430\u043b\u0430\u043a\u0443\u0440\u0438\u0447\u0438"
    ],
    "name:eng_x_preferred":[
        "Manavalakurichi"
    ],
    "name:fin_x_preferred":[
        "Manavalakurichi"
    ],
    "name:fra_x_preferred":[
        "Manavalakurichi"
    ],
    "name:ita_x_preferred":[
        "Manavalakurichi"
    ],
    "name:msa_x_preferred":[
        "Manavalakurichi"
    ],
    "name:nan_x_preferred":[
        "Manavalakurichi"
    ],
    "name:new_x_preferred":[
        "\u092e\u0928\u0935\u0932\u0915\u0941\u0930\u093f\u091a\u0940"
    ],
    "name:nld_x_preferred":[
        "Manavalakurichi"
    ],
    "name:por_x_preferred":[
        "Manavalakurichi"
    ],
    "name:swe_x_preferred":[
        "Manavalakurichi"
    ],
    "name:tam_x_preferred":[
        "\u0bae\u0ba3\u0bb5\u0bbe\u0bb3\u0b95\u0bcd\u0b95\u0bc1\u0bb1\u0bbf\u0b9a\u0bcd\u0b9a\u0bbf"
    ],
    "name:unk_x_variant":[
        "Manavalakurichi"
    ],
    "name:vie_x_preferred":[
        "Manavalakurichi"
    ],
    "name:zho_x_preferred":[
        "\u9a6c\u7eb3\u74e6\u62c9\u5e93\u91cc\u5947"
    ],
    "qs:name":"Madhavakurichi",
    "qs:name_adm0":"India",
    "qs:name_adm1":"Tamil Nadu",
    "qs:photos_9r":0,
    "qs:photos_sr":0,
    "qs:placetype":"Town",
    "qs:pop_sr":"6",
    "wof:name":"Madhavakurichi",
    "wof:placetype":"locality",
    "wof:population":10720
},
  "geometry": {"coordinates":[77.30634000000001,8.14812],"type":"Point"}
}