{
  "type": "Feature",
  "properties": {
    "iso:country":"IN",
    "ks:ks_name":"Myundi",
    "ks:ks_pop":151,
    "ks:ks_type":"VILLAGE",
    "name:eng_x_preferred":[
        "Myundi"
    ],
    "wof:name":"Myundi",
    "wof:placetype":"locality",
    "wof:population":151
},
  "geometry": {"coordinates":[78.56282,30.451934],"type":"Point"}
}