{
  "type": "Feature",
  "properties": {
    "iso:country":"IN",
    "ks:ks_name":"Shelpi Bwadi",
    "ks:ks_pop":769,
    "ks:ks_type":"HABITATION",
    "name:eng_x_preferred":[
        "Shelpi Bwadi"
    ],
    "wof:name":"Shelpi Bwadi",
    "wof:placetype":"locality",
    "wof:population":769
},
  "geometry": {"coordinates":[74.031068,15.69454],"type":"Point"}
}