{
  "type": "Feature",
  "properties": {
    "gn:admin1_code":"34.0",
    "gn:admin2_code":"221.0",
    "gn:asciiname":"Muhammadpur Birauli",
    "gn:country_code":"IN",
    "gn:dem":54,
    "gn:feature_class":"P",
    "gn:feature_code":"PPL",
    "gn:name":"Muhammadpur Birauli",
    "gn:population":0,
    "gn:timezone":"Asia/Kolkata",
    "iso:country":"IN",
    "ks:ks_name":"Mahamadpur Birauli",
    "ks:ks_pop":1830,
    "ks:ks_type":"VILLAGE",
    "name:eng_x_preferred":[
        "Mahamadpur Birauli"
    ],
    "name:eng_x_variant":[
        "Muhammadpur Birauli"
    ],
    "wof:name":"Mahamadpur Birauli",
    "wof:placetype":"locality",
    "wof:population":1830
},
  "geometry": {"coordinates":[85.679411,25.952211],"type":"Point"}
}