{
  "type": "Feature",
  "properties": {
    "gn:admin1_code":"25.0",
    "gn:admin2_code":"602.0",
    "gn:asciiname":"Karani",
    "gn:country_code":"IN",
    "gn:dem":30,
    "gn:feature_class":"P",
    "gn:feature_code":"PPL",
    "gn:name":"Karani",
    "gn:population":0,
    "gn:timezone":"Asia/Kolkata",
    "iso:country":"IN",
    "ks:ks_name":"Karani",
    "ks:ks_pop":704,
    "ks:ks_type":"VILLAGE",
    "ks:ks_uagg_main":0,
    "name:ara_x_preferred":[
        "\u0643\u0627\u0631\u0627\u0646\u064a"
    ],
    "name:eng_x_preferred":[
        "Karani"
    ],
    "name:fas_x_preferred":[
        "\u06a9\u0627\u0631\u0627\u0646\u06cc"
    ],
    "wof:name":"Karani",
    "wof:placetype":"neighbourhood",
    "wof:population":704
},
  "geometry": {"coordinates":[80.05814700000001,13.328654],"type":"Point"}
}