{
  "type": "Feature",
  "properties": {
    "gn:admin1_code":"28.0",
    "gn:admin2_code":"327.0",
    "gn:asciiname":"Dawaipani",
    "gn:country_code":"IN",
    "gn:dem":1192,
    "gn:feature_class":"P",
    "gn:feature_code":"PPL",
    "gn:name":"Dawaipani",
    "gn:population":0,
    "gn:timezone":"Asia/Kolkata",
    "iso:country":"IN",
    "wof:name":"Dawaipani",
    "wof:placetype":"locality"
},
  "geometry": {"coordinates":[88.31885,27.04734],"type":"Point"}
}