{
  "type": "Feature",
  "properties": {
    "iso:country":"IN",
    "ks:ks_name":"Bara Kendua",
    "ks:ks_pop":782,
    "ks:ks_type":"VILLAGE",
    "ks:ks_uagg_main":0,
    "name:eng_x_preferred":[
        "Bara Kendua"
    ],
    "wof:name":"Bara Kendua",
    "wof:placetype":"neighbourhood",
    "wof:population":782
},
  "geometry": {"coordinates":[87.33513000000001,24.949136],"type":"Point"}
}