{
  "type": "Feature",
  "properties": {
    "gn:admin1_code":"25",
    "gn:admin2_code":"612.0",
    "gn:asciiname":"Thandikudi",
    "gn:country_code":"IN",
    "gn:dem":1317,
    "gn:feature_class":"P",
    "gn:feature_code":"PPL",
    "gn:name":"Thandikudi",
    "gn:population":0,
    "gn:timezone":"Asia/Kolkata",
    "iso:country":"IN",
    "wof:name":"Thandikudi",
    "wof:placetype":"locality"
},
  "geometry": {"coordinates":[77.64287,10.31095],"type":"Point"}
}