{
  "type": "Feature",
  "properties": {
    "iso:country":"IN",
    "qs:name":"Chottupara Town",
    "qs:name_adm0":"India",
    "qs:name_adm1":"Kerala",
    "qs:photos":43,
    "qs:photos_1k":9,
    "qs:photos_9k":1,
    "qs:photos_9r":2,
    "qs:photos_all":43,
    "qs:photos_sr":2,
    "qs:placetype":"Town",
    "qs:pop_sr":"0",
    "wof:name":"Chottupara Town",
    "wof:placetype":"locality"
},
  "geometry": {"coordinates":[77.13659699999999,9.619177],"type":"Point"}
}