{
  "type": "Feature",
  "properties": {
    "gn:admin1_code":"11.0",
    "gn:admin2_code":"33.0",
    "gn:asciiname":"Kachogli",
    "gn:country_code":"IN",
    "gn:dem":2172,
    "gn:feature_class":"P",
    "gn:feature_code":"PPL",
    "gn:name":"Kachogli",
    "gn:population":0,
    "gn:timezone":"Asia/Kolkata",
    "iso:country":"IN",
    "wof:name":"Kachogli",
    "wof:placetype":"locality"
},
  "geometry": {"coordinates":[77.33060999999999,31.19918],"type":"Point"}
}