{
  "type": "Feature",
  "properties": {
    "gn:admin1_code":"19.0",
    "gn:admin2_code":"581",
    "gn:asciiname":"Budikote",
    "gn:country_code":"IN",
    "gn:dem":793,
    "gn:feature_class":"P",
    "gn:feature_code":"PPL",
    "gn:name":"B\u016bdikote",
    "gn:population":0,
    "gn:timezone":"Asia/Kolkata",
    "iso:country":"IN",
    "name:und_x_variant":[
        "B\u016bdikote"
    ],
    "wof:name":"Budikote",
    "wof:placetype":"locality"
},
  "geometry": {"coordinates":[78.12665,12.90655],"type":"Point"}
}