{
  "type": "Feature",
  "properties": {
    "gn:admin1_code":"19.0",
    "gn:admin2_code":"581",
    "gn:asciiname":"Budikote",
    "gn:country_code":"IN",
    "gn:dem":793,
    "gn:feature_class":"P",
    "gn:feature_code":"PPL",
    "gn:name":"B\u016bdikote",
    "gn:population":0,
    "gn:timezone":"Asia/Kolkata",
    "iso:country":"IN",
    "name:jpn_x_preferred":[
        "\u30d6\u30fc\u30c7\u30a3\u30b3\u30fc\u30c6"
    ],
    "name:kan_x_preferred":[
        "\u0cac\u0cc2\u0ca6\u0cbf\u0c95\u0ccb\u0c9f\u0cc6"
    ],
    "name:mar_x_preferred":[
        "\u092c\u0941\u0926\u093f\u0915\u094b\u091f\u0947"
    ],
    "name:und_x_variant":[
        "B\u016bdikote"
    ],
    "name:vie_x_preferred":[
        "Budikote"
    ],
    "wof:name":"Budikote",
    "wof:placetype":"locality"
},
  "geometry": {"coordinates":[78.12665,12.90655],"type":"Point"}
}