{
  "type": "Feature",
  "properties": {
    "iso:country":"IN",
    "ks:ks_name":"Sipu",
    "ks:ks_pop":70,
    "ks:ks_type":"HABITATION",
    "name:eng_x_preferred":[
        "Sipu"
    ],
    "wof:name":"Sipu",
    "wof:placetype":"locality",
    "wof:population":70
},
  "geometry": {"coordinates":[80.480362,29.796877],"type":"Point"}
}