{
  "type": "Feature",
  "properties": {
    "iso:country":"IN",
    "ks:ks_name":"Brundamamedi",
    "ks:ks_pop":190,
    "ks:ks_type":"VILLAGE",
    "name:eng_x_preferred":[
        "Brundamamedi"
    ],
    "wof:name":"Brundamamedi",
    "wof:placetype":"locality",
    "wof:population":190
},
  "geometry": {"coordinates":[81.91044599999999,18.073035],"type":"Point"}
}