{
  "type": "Feature",
  "properties": {
    "gn:admin1_code":"35",
    "gn:admin2_code":"449.0",
    "gn:asciiname":"Sukhdongar",
    "gn:country_code":"IN",
    "gn:dem":592,
    "gn:feature_class":"P",
    "gn:feature_code":"PPL",
    "gn:name":"Sukhdongar",
    "gn:population":0,
    "gn:timezone":"Asia/Kolkata",
    "iso:country":"IN",
    "wof:name":"Sukhdongar",
    "wof:placetype":"locality"
},
  "geometry": {"coordinates":[78.48363000000001,22.39458],"type":"Point"}
}