{
  "type": "Feature",
  "properties": {
    "iso:country":"IN",
    "ks:ks_alt_nam":"TIKULIHAR TOLA",
    "ks:ks_name":"Tikulihar Tola",
    "ks:ks_pop":317,
    "ks:ks_type":"HABITATION",
    "name:eng_x_preferred":[
        "Tikulihar Tola"
    ],
    "wof:name":"Tikulihar Tola",
    "wof:placetype":"locality",
    "wof:population":317
},
  "geometry": {"coordinates":[84.986215,25.933471],"type":"Point"}
}