{
  "type": "Feature",
  "properties": {
    "iso:country":"IN",
    "ks:ks_alt_nam":"Gandhi nagar",
    "ks:ks_name":"Gandhi Nagar",
    "ks:ks_pop":250,
    "ks:ks_type":"HABITATION",
    "name:eng_x_preferred":[
        "Gandhi Nagar"
    ],
    "wof:name":"Gandhi Nagar",
    "wof:placetype":"locality",
    "wof:population":250
},
  "geometry": {"coordinates":[78.507268,12.692928],"type":"Point"}
}