{
  "type": "Feature",
  "properties": {
    "iso:country":"IN",
    "ks:ks_name":"Gandhi Nagar",
    "ks:ks_pop":251,
    "ks:ks_type":"HABITATION",
    "ks:ks_uagg_main":0,
    "name:eng_x_preferred":[
        "Gandhi Nagar"
    ],
    "wof:name":"Gandhi Nagar",
    "wof:placetype":"neighbourhood",
    "wof:population":251
},
  "geometry": {"coordinates":[78.751283,10.832684],"type":"Point"}
}