{
  "type": "Feature",
  "properties": {
    "gn:admin1_code":"19.0",
    "gn:admin2_code":"582.0",
    "gn:asciiname":"Samchenahalli",
    "gn:country_code":"IN",
    "gn:dem":916,
    "gn:feature_class":"P",
    "gn:feature_code":"PPL",
    "gn:name":"Samchenahalli",
    "gn:population":0,
    "gn:timezone":"Asia/Kolkata",
    "iso:country":"IN",
    "wof:name":"Samchenahalli",
    "wof:placetype":"locality"
},
  "geometry": {"coordinates":[77.78052,13.54034],"type":"Point"}
}