{
  "type": "Feature",
  "properties": {
    "iso:country":"IN",
    "ks:ks_name":"Paschim Panditpur",
    "ks:ks_pop":129,
    "ks:ks_type":"VILLAGE",
    "ks:ks_uagg_main":0,
    "name:eng_x_preferred":[
        "Paschim Panditpur"
    ],
    "wof:name":"Paschim Panditpur",
    "wof:placetype":"neighbourhood",
    "wof:population":129
},
  "geometry": {"coordinates":[88.479187,23.472646],"type":"Point"}
}