{
  "type": "Feature",
  "properties": {
    "iso:country":"IN",
    "ks:ks_name":"Basalpur",
    "ks:ks_pop":45,
    "ks:ks_type":"VILLAGE",
    "name:eng_x_preferred":[
        "Basalpur"
    ],
    "wof:name":"Basalpur",
    "wof:placetype":"locality",
    "wof:population":45
},
  "geometry": {"coordinates":[86.55961499999999,21.009767],"type":"Point"}
}