{
  "type": "Feature",
  "properties": {
    "iso:country":"IN",
    "ks:ks_name":"Jharjharaghat",
    "ks:ks_pop":16,
    "ks:ks_type":"HABITATION",
    "name:eng_x_preferred":[
        "Jharjharaghat"
    ],
    "wof:name":"Jharjharaghat",
    "wof:placetype":"locality",
    "wof:population":16
},
  "geometry": {"coordinates":[80.91836000000001,21.395022],"type":"Point"}
}