{
  "type": "Feature",
  "properties": {
    "iso:country":"IN",
    "ks:ks_alt_nam":"Bar\u0101dih",
    "ks:ks_name":"Baradih",
    "ks:ks_pop":1907,
    "ks:ks_type":"VILLAGE",
    "name:eng_x_preferred":[
        "Baradih"
    ],
    "name:eng_x_variant":[
        "Bar\u0101dih"
    ],
    "wof:name":"Baradih",
    "wof:placetype":"locality",
    "wof:population":1907
},
  "geometry": {"coordinates":[86.116218,24.10369],"type":"Point"}
}