{
  "type": "Feature",
  "properties": {
    "gn:admin1_code":"25.0",
    "gn:admin2_code":"607.0",
    "gn:asciiname":"Nemali",
    "gn:country_code":"IN",
    "gn:dem":41,
    "gn:feature_class":"P",
    "gn:feature_code":"PPL",
    "gn:name":"Nemali",
    "gn:population":0,
    "gn:timezone":"Asia/Kolkata",
    "iso:country":"IN",
    "ks:ks_name":"Nemili",
    "ks:ks_pop":944,
    "ks:ks_type":"VILLAGE",
    "ks:ks_uagg_main":0,
    "name:eng_x_preferred":[
        "Nemili"
    ],
    "name:hin_x_preferred":[
        "\u0928\u0946\u092e\u0932\u093f"
    ],
    "name:new_x_preferred":[
        "\u0928\u0946\u092e\u0932\u093f"
    ],
    "name:tel_x_preferred":[
        "\u0c28\u0c46\u0c2e\u0c32\u0c3f"
    ],
    "wof:name":"Nemili",
    "wof:placetype":"neighbourhood",
    "wof:population":944
},
  "geometry": {"coordinates":[79.653144,12.05623],"type":"Point"}
}