{
  "type": "Feature",
  "properties": {
    "iso:country":"IN",
    "ks:ks_name":"Mathali Palli",
    "ks:ks_pop":46,
    "ks:ks_type":"HABITATION",
    "name:eng_x_preferred":[
        "Mathali Palli"
    ],
    "wof:name":"Mathali Palli",
    "wof:placetype":"locality",
    "wof:population":46
},
  "geometry": {"coordinates":[78.718592,29.848089],"type":"Point"}
}