{
  "type": "Feature",
  "properties": {
    "iso:country":"IN",
    "ks:ks_name":"Pahupuri Khaiti",
    "ks:ks_pop":626,
    "ks:ks_type":"VILLAGE",
    "name:eng_x_preferred":[
        "Pahupuri Khaiti"
    ],
    "wof:name":"Pahupuri Khaiti",
    "wof:placetype":"locality",
    "wof:population":626
},
  "geometry": {"coordinates":[92.577455,26.22644],"type":"Point"}
}