{
  "type": "Feature",
  "properties": {
    "iso:country":"IN",
    "ks:ks_name":"Rajabar",
    "ks:ks_pop":483,
    "ks:ks_type":"VILLAGE",
    "name:eng_x_preferred":[
        "Rajabar"
    ],
    "wof:name":"Rajabar",
    "wof:placetype":"locality",
    "wof:population":483
},
  "geometry": {"coordinates":[80.84675,21.744155],"type":"Point"}
}