{
  "type": "Feature",
  "properties": {
    "gn:admin1_code":"36",
    "gn:admin2_code":"173.0",
    "gn:asciiname":"Kuria",
    "gn:country_code":"IN",
    "gn:dem":108,
    "gn:feature_class":"P",
    "gn:feature_code":"PPL",
    "gn:name":"Kuria",
    "gn:population":0,
    "gn:timezone":"Asia/Kolkata",
    "iso:country":"IN",
    "name:ceb_x_preferred":[
        "Kuria"
    ],
    "name:deu_x_preferred":[
        "Kuria"
    ],
    "name:fra_x_preferred":[
        "Kuria"
    ],
    "name:nld_x_preferred":[
        "Kuria"
    ],
    "name:pol_x_preferred":[
        "Kuria"
    ],
    "name:por_x_preferred":[
        "Kuria"
    ],
    "name:swe_x_preferred":[
        "Kuria"
    ],
    "wof:name":"Kuria",
    "wof:placetype":"locality"
},
  "geometry": {"coordinates":[81.50700999999999,25.83475],"type":"Point"}
}