{
  "type": "Feature",
  "properties": {
    "gn:admin1_code":"25",
    "gn:admin2_code":"626.0",
    "gn:asciiname":"Tiruppullani",
    "gn:country_code":"IN",
    "gn:dem":8,
    "gn:feature_class":"P",
    "gn:feature_code":"PPL",
    "gn:name":"Tiruppullani",
    "gn:population":0,
    "gn:timezone":"Asia/Kolkata",
    "iso:country":"IN",
    "name:und_x_variant":[
        "Tiruppullany",
        "Tiruppullani"
    ],
    "wof:name":"Tiruppullani",
    "wof:placetype":"locality"
},
  "geometry": {"coordinates":[78.82361999999998,9.28354],"type":"Point"}
}