{
  "type": "Feature",
  "properties": {
    "iso:country":"IN",
    "ks:ks_alt_nam":"Mahm\u016bdpur",
    "ks:ks_name":"Mahmudpur",
    "ks:ks_type":"VILLAGE",
    "ks:ks_uagg_main":0,
    "name:eng_x_preferred":[
        "Mahmudpur"
    ],
    "name:eng_x_variant":[
        "Mahm\u016bdpur"
    ],
    "wof:name":"Mahmudpur",
    "wof:placetype":"neighbourhood"
},
  "geometry": {"coordinates":[75.835188,30.836292],"type":"Point"}
}