{
  "type": "Feature",
  "properties": {
    "iso:country":"IN",
    "ks:ks_name":"Kachikuppam",
    "ks:ks_pop":678,
    "ks:ks_type":"HABITATION",
    "name:eng_x_preferred":[
        "Kachikuppam"
    ],
    "wof:name":"Kachikuppam",
    "wof:placetype":"locality",
    "wof:population":678
},
  "geometry": {"coordinates":[79.21014,11.913145],"type":"Point"}
}