{
  "type": "Feature",
  "properties": {
    "iso:country":"IN",
    "ks:ks_name":"Moolakkal",
    "ks:ks_pop":268,
    "ks:ks_type":"HABITATION",
    "name:eng_x_preferred":[
        "Moolakkal"
    ],
    "wof:name":"Moolakkal",
    "wof:placetype":"locality",
    "wof:population":268
},
  "geometry": {"coordinates":[79.384747,10.84208],"type":"Point"}
}