{
  "type": "Feature",
  "properties": {
    "iso:country":"IN",
    "ks:ks_name":"Dipatoli",
    "ks:ks_pop":844,
    "ks:ks_type":"VILLAGE",
    "ks:ks_uagg_main":0,
    "name:eng_x_preferred":[
        "Dipatoli"
    ],
    "wof:name":"Dipatoli",
    "wof:placetype":"neighbourhood",
    "wof:population":844
},
  "geometry": {"coordinates":[84.113343,23.401853],"type":"Point"}
}