{
  "type": "Feature",
  "properties": {
    "iso:country":"IN",
    "ks:ks_name":"Paritewasti",
    "ks:ks_pop":128,
    "ks:ks_type":"HABITATION",
    "name:eng_x_preferred":[
        "Paritewasti"
    ],
    "wof:name":"Paritewasti",
    "wof:placetype":"locality",
    "wof:population":128
},
  "geometry": {"coordinates":[75.249072,17.951008],"type":"Point"}
}