{
  "type": "Feature",
  "properties": {
    "iso:country":"IN",
    "ks:ks_name":"Garanga Bagan",
    "ks:ks_pop":1507,
    "ks:ks_type":"VILLAGE",
    "name:eng_x_preferred":[
        "Garanga Bagan"
    ],
    "wof:name":"Garanga Bagan",
    "wof:placetype":"locality",
    "wof:population":1507
},
  "geometry": {"coordinates":[93.857964,26.521873],"type":"Point"}
}