{
  "type": "Feature",
  "properties": {
    "iso:country":"IN",
    "ks:ks_name":"Paraya",
    "ks:ks_pop":200,
    "ks:ks_type":"HABITATION",
    "name:eng_x_preferred":[
        "Paraya"
    ],
    "wof:name":"Paraya",
    "wof:placetype":"locality",
    "wof:population":200
},
  "geometry": {"coordinates":[83.05781,27.371589],"type":"Point"}
}