{
  "type": "Feature",
  "properties": {
    "iso:country":"IN",
    "ks:ks_name":"Gokalpura",
    "ks:ks_pop":312,
    "ks:ks_type":"HABITATION",
    "name:eng_x_preferred":[
        "Gokalpura"
    ],
    "wof:name":"Gokalpura",
    "wof:placetype":"locality",
    "wof:population":312
},
  "geometry": {"coordinates":[72.510391,24.186257],"type":"Point"}
}