{
  "type": "Feature",
  "properties": {
    "iso:country":"IN",
    "ks:ks_name":"Kadanthethi",
    "ks:ks_pop":1299,
    "ks:ks_type":"VILLAGE",
    "name:eng_x_preferred":[
        "Kadanthethi"
    ],
    "wof:name":"Kadanthethi",
    "wof:placetype":"locality",
    "wof:population":1299
},
  "geometry": {"coordinates":[79.757276,10.576197],"type":"Point"}
}