{
  "type": "Feature",
  "properties": {
    "gn:admin1_code":"24.0",
    "gn:admin2_code":"115.0",
    "gn:asciiname":"Umedpurd",
    "gn:country_code":"IN",
    "gn:dem":165,
    "gn:feature_class":"P",
    "gn:feature_code":"PPL",
    "gn:name":"Umedpurd",
    "gn:population":0,
    "gn:timezone":"Asia/Kolkata",
    "iso:country":"IN",
    "ks:ks_name":"Ummedpura",
    "ks:ks_pop":405,
    "ks:ks_type":"VILLAGE",
    "name:eng_x_preferred":[
        "Ummedpura"
    ],
    "name:eng_x_variant":[
        "Umedpurd"
    ],
    "wof:name":"Ummedpura",
    "wof:placetype":"locality",
    "wof:population":405
},
  "geometry": {"coordinates":[70.676283,25.393985],"type":"Point"}
}