{
  "type": "Feature",
  "properties": {
    "gn:admin1_code":"24.0",
    "gn:admin2_code":"115.0",
    "gn:asciiname":"Umedpurd",
    "gn:country_code":"IN",
    "gn:dem":165,
    "gn:feature_class":"P",
    "gn:feature_code":"PPL",
    "gn:name":"Umedpurd",
    "gn:population":0,
    "gn:timezone":"Asia/Kolkata",
    "iso:country":"IN",
    "wof:name":"Umedpurd",
    "wof:placetype":"locality"
},
  "geometry": {"coordinates":[70.68160999999998,25.39332000000001],"type":"Point"}
}