{
  "type": "Feature",
  "properties": {
    "iso:country":"IN",
    "ks:ks_name":"Mukulish",
    "ks:ks_pop":467,
    "ks:ks_type":"VILLAGE",
    "ks:ks_uagg_main":0,
    "name:eng_x_preferred":[
        "Mukulish"
    ],
    "wof:name":"Mukulish",
    "wof:placetype":"neighbourhood",
    "wof:population":467
},
  "geometry": {"coordinates":[87.13094700000001,21.677106],"type":"Point"}
}