{
  "type": "Feature",
  "properties": {
    "iso:country":"IN",
    "ks:ks_alt_nam":"RSC 19",
    "ks:ks_name":"Rsc 19",
    "ks:ks_pop":250,
    "ks:ks_type":"HABITATION",
    "name:eng_x_preferred":[
        "Rsc 19"
    ],
    "wof:name":"Rsc 19",
    "wof:placetype":"locality",
    "wof:population":250
},
  "geometry": {"coordinates":[82.037133,18.129977],"type":"Point"}
}