{
  "type": "Feature",
  "properties": {
    "iso:country":"IN",
    "ks:ks_name":"Kunded",
    "ks:ks_pop":435,
    "ks:ks_type":"VILLAGE",
    "name:eng_x_preferred":[
        "Kunded"
    ],
    "wof:name":"Kunded",
    "wof:placetype":"locality",
    "wof:population":435
},
  "geometry": {"coordinates":[81.14708,18.455384],"type":"Point"}
}