{
  "type": "Feature",
  "properties": {
    "iso:country":"IN",
    "ks:ks_name":"Bansbari Pt I",
    "ks:ks_pop":605,
    "ks:ks_type":"VILLAGE",
    "name:eng_x_preferred":[
        "Bansbari Pt I"
    ],
    "wof:name":"Bansbari Pt I",
    "wof:placetype":"locality",
    "wof:population":605
},
  "geometry": {"coordinates":[92.553624,24.747231],"type":"Point"}
}