{
  "type": "Feature",
  "properties": {
    "iso:country":"IN",
    "ks:ks_name":"Jonekareng Lalitimorang",
    "ks:ks_pop":519,
    "ks:ks_type":"HABITATION",
    "ks:ks_uagg_main":0,
    "name:eng_x_preferred":[
        "Jonekareng Lalitimorang"
    ],
    "wof:name":"Jonekareng Lalitimorang",
    "wof:placetype":"neighbourhood",
    "wof:population":519
},
  "geometry": {"coordinates":[95.16318,27.78853],"type":"Point"}
}