{
  "type": "Feature",
  "properties": {
    "iso:country":"IN",
    "ks:ks_alt_nam":"neelkod",
    "ks:ks_name":"Neelkod",
    "ks:ks_pop":49,
    "ks:ks_type":"HABITATION",
    "name:eng_x_preferred":[
        "Neelkod"
    ],
    "wof:name":"Neelkod",
    "wof:placetype":"locality",
    "wof:population":49
},
  "geometry": {"coordinates":[74.473446,14.284415],"type":"Point"}
}