{
  "type": "Feature",
  "properties": {
    "gn:admin1_code":"36",
    "gn:admin2_code":"188.0",
    "gn:asciiname":"Bhainsa",
    "gn:country_code":"IN",
    "gn:dem":84,
    "gn:feature_class":"P",
    "gn:feature_code":"PPL",
    "gn:name":"Bhainsa",
    "gn:population":0,
    "gn:timezone":"Asia/Kolkata",
    "iso:country":"IN",
    "ks:ks_name":"Bhainsa",
    "ks:ks_type":"VILLAGE",
    "ks:ks_uagg_main":0,
    "name:bpy_x_preferred":[
        "\u09ad\u09be\u09b9\u09bf\u09a8\u09b8\u09be"
    ],
    "name:ceb_x_preferred":[
        "Bhaisa"
    ],
    "name:eng_x_preferred":[
        "Bhainsa"
    ],
    "name:hif_x_preferred":[
        "Bhainsa"
    ],
    "name:ind_x_preferred":[
        "Bhainsa"
    ],
    "name:ita_x_preferred":[
        "Bhainsa"
    ],
    "name:msa_x_preferred":[
        "Bhainsa"
    ],
    "name:new_x_preferred":[
        "\u092d\u0948\u0928\u094d\u0938\u093e"
    ],
    "name:ori_x_preferred":[
        "\u0b2d\u0b3e\u0b07\u0b28\u0b4d\u0b38\u0b3e"
    ],
    "name:pam_x_preferred":[
        "Bhainsa"
    ],
    "name:por_x_preferred":[
        "Bhainsa"
    ],
    "name:spa_x_preferred":[
        "Bhainsa"
    ],
    "name:swe_x_preferred":[
        "Bhaisa"
    ],
    "name:urd_x_preferred":[
        "\u0628\u06be\u0627\u0626\u0646\u0633\u06c1"
    ],
    "name:vie_x_preferred":[
        "Bhainsa"
    ],
    "name:zho_x_preferred":[
        "\u62dc\u6069\u8428"
    ],
    "wof:name":"Bhainsa",
    "wof:placetype":"neighbourhood"
},
  "geometry": {"coordinates":[83.315287,26.543622],"type":"Point"}
}