{
  "type": "Feature",
  "properties": {
    "gn:admin1_code":"34.0",
    "gn:admin2_code":"230.0",
    "gn:asciiname":"Madarpur",
    "gn:country_code":"IN",
    "gn:dem":57,
    "gn:feature_class":"P",
    "gn:feature_code":"PPL",
    "gn:name":"Mad\u0101rpur",
    "gn:population":0,
    "gn:timezone":"Asia/Kolkata",
    "iso:country":"IN",
    "name:fra_x_preferred":[
        "Madarpur"
    ],
    "name:hif_x_preferred":[
        "Madarpur"
    ],
    "wof:name":"Madarpur",
    "wof:placetype":"locality"
},
  "geometry": {"coordinates":[85.10937,25.46696],"type":"Point"}
}