{
  "type": "Feature",
  "properties": {
    "gn:admin1_code":"36",
    "gn:admin2_code":"194.0",
    "gn:asciiname":"Salarpur",
    "gn:country_code":"IN",
    "gn:dem":91,
    "gn:feature_class":"P",
    "gn:feature_code":"PPL",
    "gn:name":"Sal\u0101rpur",
    "gn:population":0,
    "gn:timezone":"Asia/Kolkata",
    "iso:country":"IN",
    "name:urd_x_preferred":[
        "\u0633\u0627\u0644\u0627\u0631 \u067e\u0648\u0631"
    ],
    "wof:name":"Salarpur",
    "wof:placetype":"locality"
},
  "geometry": {"coordinates":[82.36774,25.76344],"type":"Point"}
}