{
  "type": "Feature",
  "properties": {
    "iso:country":"IN",
    "ks:ks_name":"Wansifalia",
    "ks:ks_pop":549,
    "ks:ks_type":"HABITATION",
    "ks:ks_uagg_main":0,
    "name:eng_x_preferred":[
        "Wansifalia"
    ],
    "wof:name":"Wansifalia",
    "wof:placetype":"neighbourhood",
    "wof:population":549
},
  "geometry": {"coordinates":[72.91325000000001,20.719639],"type":"Point"}
}