{
  "type": "Feature",
  "properties": {
    "iso:country":"IN",
    "ks:ks_name":"Sreegram V",
    "ks:ks_pop":1870,
    "ks:ks_type":"HABITATION",
    "name:eng_x_preferred":[
        "Sreegram V"
    ],
    "wof:name":"Sreegram V",
    "wof:placetype":"locality",
    "wof:population":1870
},
  "geometry": {"coordinates":[90.35076100000001,26.26978],"type":"Point"}
}