{
  "type": "Feature",
  "properties": {
    "iso:country":"IN",
    "ks:ks_name":"Khandvapada",
    "ks:ks_pop":255,
    "ks:ks_type":"HABITATION",
    "name:eng_x_preferred":[
        "Khandvapada"
    ],
    "wof:name":"Khandvapada",
    "wof:placetype":"locality",
    "wof:population":255
},
  "geometry": {"coordinates":[72.73927399999999,19.867448],"type":"Point"}
}