{
  "type": "Feature",
  "properties": {
    "gn:admin1_code":"24",
    "gn:admin2_code":"129.0",
    "gn:asciiname":"Sumar",
    "gn:country_code":"IN",
    "gn:dem":285,
    "gn:feature_class":"P",
    "gn:feature_code":"PPL",
    "gn:name":"S\u016bmar",
    "gn:population":0,
    "gn:timezone":"Asia/Kolkata",
    "iso:country":"IN",
    "name:ceb_x_preferred":[
        "Sumar"
    ],
    "name:deu_x_preferred":[
        "Sumar"
    ],
    "name:und_x_variant":[
        "S\u016bmar"
    ],
    "wof:name":"Sumar",
    "wof:placetype":"neighbourhood"
},
  "geometry": {"coordinates":[76.39422999999999,24.78543],"type":"Point"}
}