{
  "type": "Feature",
  "properties": {
    "gn:admin1_code":"36.0",
    "gn:admin2_code":"173.0",
    "gn:asciiname":"Raiyapur",
    "gn:country_code":"IN",
    "gn:dem":106,
    "gn:feature_class":"P",
    "gn:feature_code":"PPL",
    "gn:name":"Raiy\u0101pur",
    "gn:population":0,
    "gn:timezone":"Asia/Kolkata",
    "iso:country":"IN",
    "wof:name":"Raiyapur",
    "wof:placetype":"locality"
},
  "geometry": {"coordinates":[81.59047,25.69998],"type":"Point"}
}