{
  "type": "Feature",
  "properties": {
    "iso:country":"IN",
    "ks:ks_name":"Muddumaranahalli",
    "ks:ks_pop":134,
    "ks:ks_type":"HABITATION",
    "name:eng_x_preferred":[
        "Muddumaranahalli"
    ],
    "wof:name":"Muddumaranahalli",
    "wof:placetype":"locality",
    "wof:population":134
},
  "geometry": {"coordinates":[76.665965,13.069695],"type":"Point"}
}