{
  "type": "Feature",
  "properties": {
    "gn:admin1_code":"35.0",
    "gn:admin2_code":"445.0",
    "gn:asciiname":"Gokhalapura",
    "gn:country_code":"IN",
    "gn:dem":511,
    "gn:feature_class":"P",
    "gn:feature_code":"PPL",
    "gn:name":"Gokhal\u0101pura",
    "gn:population":0,
    "gn:timezone":"Asia/Kolkata",
    "iso:country":"IN",
    "wof:name":"Gokhalapura",
    "wof:placetype":"neighbourhood"
},
  "geometry": {"coordinates":[76.68246000000001,22.81708],"type":"Point"}
}