{
  "type": "Feature",
  "properties": {
    "iso:country":"IN",
    "ks:ks_name":"Bhursila",
    "ks:ks_pop":78,
    "ks:ks_type":"HABITATION",
    "name:eng_x_preferred":[
        "Bhursila"
    ],
    "wof:name":"Bhursila",
    "wof:placetype":"locality",
    "wof:population":78
},
  "geometry": {"coordinates":[84.38754299999999,22.341607],"type":"Point"}
}