{
  "type": "Feature",
  "properties": {
    "iso:country":"IN",
    "ks:ks_name":"Sahoo Pada",
    "ks:ks_pop":0,
    "ks:ks_type":"VILLAGE",
    "name:eng_x_preferred":[
        "Sahoo Pada"
    ],
    "wof:name":"Sahoo Pada",
    "wof:placetype":"locality",
    "wof:population":0
},
  "geometry": {"coordinates":[86.603759,20.485209],"type":"Point"}
}