{
  "type": "Feature",
  "properties": {
    "iso:country":"IN",
    "ks:ks_name":"Dakshin Tajpur",
    "ks:ks_type":"VILLAGE",
    "name:eng_x_preferred":[
        "Dakshin Tajpur"
    ],
    "wof:name":"Dakshin Tajpur",
    "wof:placetype":"locality"
},
  "geometry": {"coordinates":[88.665958,23.886259],"type":"Point"}
}