{
  "type": "Feature",
  "properties": {
    "iso:country":"IN",
    "ks:ks_alt_nam":"DHEKIDIPA",
    "ks:ks_name":"Dhekidipa",
    "ks:ks_pop":159,
    "ks:ks_type":"HABITATION",
    "name:eng_x_preferred":[
        "Dhekidipa"
    ],
    "wof:name":"Dhekidipa",
    "wof:placetype":"locality",
    "wof:population":159
},
  "geometry": {"coordinates":[83.72712300000001,23.160825],"type":"Point"}
}