{
  "type": "Feature",
  "properties": {
    "gn:admin1_code":"2.0",
    "gn:admin2_code":"554.0",
    "gn:asciiname":"Diguvamasapalle",
    "gn:country_code":"IN",
    "gn:dem":280,
    "gn:feature_class":"P",
    "gn:feature_code":"PPL",
    "gn:name":"Diguvamasapalle",
    "gn:population":0,
    "gn:timezone":"Asia/Kolkata",
    "iso:country":"IN",
    "name:tel_x_preferred":[
        "\u0c26\u0c3f\u0c17\u0c41\u0c35\u0c2e\u0c3e\u0c38\u0c2a\u0c32\u0c4d\u0c32\u0c46"
    ],
    "wof:name":"Diguvamasapalle",
    "wof:placetype":"locality"
},
  "geometry": {"coordinates":[79.15958000000001,13.20313],"type":"Point"}
}