{
  "type": "Feature",
  "properties": {
    "gn:admin1_code":"11",
    "gn:admin2_code":"33.0",
    "gn:asciiname":"Rinjat",
    "gn:country_code":"IN",
    "gn:dem":1980,
    "gn:feature_class":"P",
    "gn:feature_code":"PPL",
    "gn:name":"Rinjat",
    "gn:population":0,
    "gn:timezone":"Asia/Kolkata",
    "iso:country":"IN",
    "wof:name":"Rinjat",
    "wof:placetype":"locality"
},
  "geometry": {"coordinates":[77.62895,30.8986],"type":"Point"}
}