{
  "type": "Feature",
  "properties": {
    "iso:country":"IN",
    "ks:ks_name":"Phatka",
    "ks:ks_pop":665,
    "ks:ks_type":"VILLAGE",
    "name:eng_x_preferred":[
        "Phatka"
    ],
    "wof:name":"Phatka",
    "wof:placetype":"locality",
    "wof:population":665
},
  "geometry": {"coordinates":[85.187566,22.841303],"type":"Point"}
}