{
  "type": "Feature",
  "properties": {
    "iso:country":"IN",
    "ks:ks_name":"Pachhtira",
    "ks:ks_pop":556,
    "ks:ks_type":"HABITATION",
    "name:eng_x_preferred":[
        "Pachhtira"
    ],
    "wof:name":"Pachhtira",
    "wof:placetype":"locality",
    "wof:population":556
},
  "geometry": {"coordinates":[86.382272,21.035245],"type":"Point"}
}