{
  "type": "Feature",
  "properties": {
    "iso:country":"IN",
    "ks:ks_name":"Nar Singh Ki Dhani",
    "ks:ks_pop":20,
    "ks:ks_type":"HABITATION",
    "name:eng_x_preferred":[
        "Nar Singh Ki Dhani"
    ],
    "wof:name":"Nar Singh Ki Dhani",
    "wof:placetype":"locality",
    "wof:population":20
},
  "geometry": {"coordinates":[74.521052,29.869609],"type":"Point"}
}