{
  "type": "Feature",
  "properties": {
    "iso:country":"IN",
    "ks:ks_name":"Jodia",
    "ks:ks_pop":1127,
    "ks:ks_type":"VILLAGE",
    "name:eng_x_preferred":[
        "Jodia"
    ],
    "wof:name":"Jodia",
    "wof:placetype":"locality",
    "wof:population":1127
},
  "geometry": {"coordinates":[86.38422199999999,22.202376],"type":"Point"}
}