{
  "type": "Feature",
  "properties": {
    "gn:admin1_code":"21.0",
    "gn:admin2_code":"378",
    "gn:asciiname":"Kaupur",
    "gn:country_code":"IN",
    "gn:dem":32,
    "gn:feature_class":"P",
    "gn:feature_code":"PPL",
    "gn:name":"K\u0101upur",
    "gn:population":0,
    "gn:timezone":"Asia/Kolkata",
    "iso:country":"IN",
    "ks:ks_name":"Kaupur",
    "ks:ks_pop":3406,
    "ks:ks_type":"VILLAGE",
    "name:eng_x_preferred":[
        "Kaupur"
    ],
    "wof:name":"Kaupur",
    "wof:placetype":"locality",
    "wof:population":3406
},
  "geometry": {"coordinates":[86.42878899999999,21.128835],"type":"Point"}
}