{
  "type": "Feature",
  "properties": {
    "iso:country":"IN",
    "ks:ks_alt_nam":"TISIA",
    "ks:ks_name":"Tisia",
    "ks:ks_pop":281,
    "ks:ks_type":"HABITATION",
    "name:eng_x_preferred":[
        "Tisia"
    ],
    "wof:name":"Tisia",
    "wof:placetype":"locality",
    "wof:population":281
},
  "geometry": {"coordinates":[84.073044,23.577823],"type":"Point"}
}