{
  "type": "Feature",
  "properties": {
    "iso:country":"IN",
    "ks:ks_name":"Eakdarya",
    "ks:ks_pop":250,
    "ks:ks_type":"HABITATION",
    "name:eng_x_preferred":[
        "Eakdarya"
    ],
    "wof:name":"Eakdarya",
    "wof:placetype":"locality",
    "wof:population":250
},
  "geometry": {"coordinates":[82.824944,27.012302],"type":"Point"}
}