{
  "type": "Feature",
  "properties": {
    "iso:country":"IN",
    "ks:ks_name":"Ilanchiyamangalam",
    "ks:ks_pop":150,
    "ks:ks_type":"HABITATION",
    "name:eng_x_preferred":[
        "Ilanchiyamangalam"
    ],
    "wof:name":"Ilanchiyamangalam",
    "wof:placetype":"locality",
    "wof:population":150
},
  "geometry": {"coordinates":[78.992615,9.904973],"type":"Point"}
}