{
  "type": "Feature",
  "properties": {
    "gn:admin1_code":"35.0",
    "gn:admin2_code":"450.0",
    "gn:asciiname":"Sahdar",
    "gn:country_code":"IN",
    "gn:dem":522,
    "gn:feature_class":"P",
    "gn:feature_code":"PPL",
    "gn:name":"S\u0101hd\u0101r",
    "gn:population":0,
    "gn:timezone":"Asia/Kolkata",
    "iso:country":"IN",
    "ks:ks_name":"Shahdar",
    "ks:ks_pop":48,
    "ks:ks_type":"VILLAGE",
    "name:eng_x_preferred":[
        "Shahdar"
    ],
    "name:eng_x_variant":[
        "Sahdar"
    ],
    "wof:name":"Shahdar",
    "wof:placetype":"locality",
    "wof:population":48
},
  "geometry": {"coordinates":[80.386465,23.573449],"type":"Point"}
}