{
  "type": "Feature",
  "properties": {
    "iso:country":"IN",
    "ks:ks_name":"Eraligool Pt II",
    "ks:ks_pop":1131,
    "ks:ks_type":"VILLAGE",
    "name:eng_x_preferred":[
        "Eraligool Pt II"
    ],
    "wof:name":"Eraligool Pt II",
    "wof:placetype":"locality",
    "wof:population":1131
},
  "geometry": {"coordinates":[92.40601700000001,24.671307],"type":"Point"}
}