{
  "type": "Feature",
  "properties": {
    "gn:admin1_code":"24.0",
    "gn:admin2_code":"119.0",
    "gn:asciiname":"Chandolai",
    "gn:country_code":"IN",
    "gn:dem":359,
    "gn:feature_class":"P",
    "gn:feature_code":"PPL",
    "gn:name":"Chandolai",
    "gn:population":0,
    "gn:timezone":"Asia/Kolkata",
    "iso:country":"IN",
    "wof:name":"Chandolai",
    "wof:placetype":"locality"
},
  "geometry": {"coordinates":[75.09305999999999,26.16236],"type":"Point"}
}