{
  "type": "Feature",
  "properties": {
    "gn:admin1_code":"36",
    "gn:admin2_code":"183.0",
    "gn:asciiname":"Rani Jot",
    "gn:country_code":"IN",
    "gn:dem":104,
    "gn:feature_class":"P",
    "gn:feature_code":"PPL",
    "gn:name":"R\u0101ni Jot",
    "gn:population":0,
    "gn:timezone":"Asia/Kolkata",
    "iso:country":"IN",
    "name:und_x_variant":[
        "R\u0101ni Jot",
        "R\u0101n\u012b Jot"
    ],
    "wof:name":"Rani Jot",
    "wof:placetype":"locality"
},
  "geometry": {"coordinates":[82.35605,27.00652],"type":"Point"}
}