{
  "type": "Feature",
  "properties": {
    "iso:country":"IN",
    "ks:ks_alt_nam":"It\u0101wa",
    "ks:ks_name":"Itawa",
    "ks:ks_type":"VILLAGE",
    "ks:ks_uagg_main":0,
    "name:eng_x_preferred":[
        "Itawa"
    ],
    "name:eng_x_variant":[
        "It\u0101wa"
    ],
    "wof:name":"Itawa",
    "wof:placetype":"neighbourhood"
},
  "geometry": {"coordinates":[76.035472,22.979446],"type":"Point"}
}