{
  "type": "Feature",
  "properties": {
    "iso:country":"IN",
    "ks:ks_name":"Bheempuram",
    "ks:ks_pop":323,
    "ks:ks_type":"VILLAGE",
    "name:eng_x_preferred":[
        "Bheempuram"
    ],
    "wof:name":"Bheempuram",
    "wof:placetype":"locality",
    "wof:population":323
},
  "geometry": {"coordinates":[84.178877,18.649803],"type":"Point"}
}