{
  "type": "Feature",
  "properties": {
    "iso:country":"IN",
    "ks:ks_name":"Ladwari Tal",
    "ks:ks_pop":56,
    "ks:ks_type":"HABITATION",
    "name:eng_x_preferred":[
        "Ladwari Tal"
    ],
    "wof:name":"Ladwari Tal",
    "wof:placetype":"locality",
    "wof:population":56
},
  "geometry": {"coordinates":[78.71427300000001,25.213207],"type":"Point"}
}