{
  "type": "Feature",
  "properties": {
    "iso:country":"IN",
    "ks:ks_name":"Palagondi",
    "ks:ks_pop":50,
    "ks:ks_type":"HABITATION",
    "name:eng_x_preferred":[
        "Palagondi"
    ],
    "wof:name":"Palagondi",
    "wof:placetype":"locality",
    "wof:population":50
},
  "geometry": {"coordinates":[81.935934,17.926255],"type":"Point"}
}