{
  "type": "Feature",
  "properties": {
    "iso:country":"IN",
    "ks:ks_alt_nam":"middle tola",
    "ks:ks_name":"Middle Tola",
    "ks:ks_pop":100,
    "ks:ks_type":"HABITATION",
    "name:eng_x_preferred":[
        "Middle Tola"
    ],
    "wof:name":"Middle Tola",
    "wof:placetype":"locality",
    "wof:population":100
},
  "geometry": {"coordinates":[86.46454199999999,24.612632],"type":"Point"}
}