{
  "type": "Feature",
  "properties": {
    "gn:admin1_code":"11.0",
    "gn:admin2_code":"31.0",
    "gn:asciiname":"Bashad",
    "gn:country_code":"IN",
    "gn:dem":1331,
    "gn:feature_class":"P",
    "gn:feature_code":"PPL",
    "gn:name":"Bash\u0101d",
    "gn:population":0,
    "gn:timezone":"Asia/Kolkata",
    "iso:country":"IN",
    "wof:name":"Bashad",
    "wof:placetype":"locality"
},
  "geometry": {"coordinates":[77.02667,30.93802],"type":"Point"}
}