{
  "type": "Feature",
  "properties": {
    "iso:country":"IN",
    "ks:ks_name":"Oras Kh.",
    "ks:ks_pop":342,
    "ks:ks_type":"VILLAGE",
    "name:eng_x_preferred":[
        "Oras Kh."
    ],
    "wof:name":"Oras Kh.",
    "wof:placetype":"locality",
    "wof:population":342
},
  "geometry": {"coordinates":[73.740084,16.118922],"type":"Point"}
}