{
  "type": "Feature",
  "properties": {
    "iso:country":"IN",
    "ks:ks_name":"Brahmanwadi",
    "ks:ks_pop":93,
    "ks:ks_type":"HABITATION",
    "name:eng_x_preferred":[
        "Brahmanwadi"
    ],
    "wof:name":"Brahmanwadi",
    "wof:placetype":"locality",
    "wof:population":93
},
  "geometry": {"coordinates":[73.421667,17.1125],"type":"Point"}
}