{
  "type": "Feature",
  "properties": {
    "iso:country":"IN",
    "ks:ks_name":"Sivagiri",
    "ks:ks_pop":212,
    "ks:ks_type":"HABITATION",
    "name:eng_x_preferred":[
        "Sivagiri"
    ],
    "wof:name":"Sivagiri",
    "wof:placetype":"locality",
    "wof:population":212
},
  "geometry": {"coordinates":[79.52663699999999,14.010469],"type":"Point"}
}