{
  "type": "Feature",
  "properties": {
    "iso:country":"IN",
    "ks:ks_alt_nam":"samanthipuram",
    "ks:ks_name":"Samanthipuram",
    "ks:ks_pop":200,
    "ks:ks_type":"HABITATION",
    "ks:ks_uagg_main":0,
    "name:eng_x_preferred":[
        "Samanthipuram"
    ],
    "wof:name":"Samanthipuram",
    "wof:placetype":"neighbourhood",
    "wof:population":200
},
  "geometry": {"coordinates":[79.48357300000001,12.299293],"type":"Point"}
}