{
  "type": "Feature",
  "properties": {
    "iso:country":"IN",
    "ks:ks_name":"Tamgaon",
    "ks:ks_pop":1106,
    "ks:ks_type":"VILLAGE",
    "ks:ks_uagg_main":0,
    "name:eng_x_preferred":[
        "Tamgaon"
    ],
    "wof:name":"Tamgaon",
    "wof:placetype":"neighbourhood",
    "wof:population":1106
},
  "geometry": {"coordinates":[76.674435,21.030067],"type":"Point"}
}