{
  "type": "Feature",
  "properties": {
    "gn:admin1_code":"37",
    "gn:admin2_code":"409.0",
    "gn:asciiname":"Bamhni",
    "gn:country_code":"IN",
    "gn:dem":292,
    "gn:feature_class":"P",
    "gn:feature_code":"PPL",
    "gn:name":"Bamhni",
    "gn:population":0,
    "gn:timezone":"Asia/Kolkata",
    "iso:country":"IN",
    "ks:ks_name":"Bamhni",
    "ks:ks_type":"VILLAGE",
    "name:eng_x_preferred":[
        "Bamhni"
    ],
    "wof:name":"Bamhni",
    "wof:placetype":"locality"
},
  "geometry": {"coordinates":[81.412036,21.823051],"type":"Point"}
}