{
  "type": "Feature",
  "properties": {
    "iso:country":"IN",
    "ks:ks_name":"Ambao",
    "ks:ks_pop":330,
    "ks:ks_type":"VILLAGE",
    "name:eng_x_preferred":[
        "Ambao"
    ],
    "wof:name":"Ambao",
    "wof:placetype":"locality",
    "wof:population":330
},
  "geometry": {"coordinates":[74.33222499999999,23.990497],"type":"Point"}
}