{
  "type": "Feature",
  "properties": {
    "iso:country":"IN",
    "ks:ks_name":"Pavithreswaram",
    "ks:ks_pop":26082,
    "ks:ks_type":"VILLAGE",
    "name:eng_x_preferred":[
        "Pavithreswaram"
    ],
    "wof:name":"Pavithreswaram",
    "wof:placetype":"locality",
    "wof:population":26082
},
  "geometry": {"coordinates":[76.68879099999999,9.024494],"type":"Point"}
}