{
  "type": "Feature",
  "properties": {
    "gn:admin1_code":"19.0",
    "gn:admin2_code":"575.0",
    "gn:asciiname":"Aranthamajlu",
    "gn:country_code":"IN",
    "gn:dem":107,
    "gn:feature_class":"P",
    "gn:feature_code":"PPL",
    "gn:name":"Aranthamajlu",
    "gn:population":0,
    "gn:timezone":"Asia/Kolkata",
    "iso:country":"IN",
    "ks:ks_name":"Iranthamajalu",
    "ks:ks_pop":270,
    "ks:ks_type":"HABITATION",
    "name:eng_x_preferred":[
        "Iranthamajalu"
    ],
    "name:eng_x_variant":[
        "Aranthamajlu"
    ],
    "wof:name":"Iranthamajalu",
    "wof:placetype":"locality",
    "wof:population":270
},
  "geometry": {"coordinates":[75.36039599999999,12.549138],"type":"Point"}
}