{
  "type": "Feature",
  "properties": {
    "gn:admin1_code":"25.0",
    "gn:admin2_code":"606",
    "gn:asciiname":"Kariyamangalam",
    "gn:country_code":"IN",
    "gn:dem":260,
    "gn:feature_class":"P",
    "gn:feature_code":"PPL",
    "gn:name":"Kariyamangalam",
    "gn:population":0,
    "gn:timezone":"Asia/Kolkata",
    "iso:country":"IN",
    "ks:ks_name":"Kariyamangalam",
    "ks:ks_pop":2269,
    "ks:ks_type":"URBAN",
    "name:eng_x_preferred":[
        "Kariyamangalam"
    ],
    "name:und_x_variant":[
        "Karivamangalam",
        "Kariyamangalam"
    ],
    "wof:name":"Kariyamangalam",
    "wof:placetype":"locality",
    "wof:population":2269
},
  "geometry": {"coordinates":[78.83263599999999,12.292911],"type":"Point"}
}