{
  "type": "Feature",
  "properties": {
    "gn:admin1_code":"25.0",
    "gn:admin2_code":"606",
    "gn:asciiname":"Kariyamangalam",
    "gn:country_code":"IN",
    "gn:dem":260,
    "gn:feature_class":"P",
    "gn:feature_code":"PPL",
    "gn:name":"Kariyamangalam",
    "gn:population":0,
    "gn:timezone":"Asia/Kolkata",
    "iso:country":"IN",
    "name:und_x_variant":[
        "Karivamangalam",
        "Kariyamangalam"
    ],
    "wof:name":"Kariyamangalam",
    "wof:placetype":"locality"
},
  "geometry": {"coordinates":[78.84314000000001,12.283],"type":"Point"}
}