{
  "type": "Feature",
  "properties": {
    "iso:country":"IN",
    "ks:ks_name":"Aitanmane",
    "ks:ks_pop":2470,
    "ks:ks_type":"HABITATION",
    "name:eng_x_preferred":[
        "Aitanmane"
    ],
    "wof:name":"Aitanmane",
    "wof:placetype":"locality",
    "wof:population":2470
},
  "geometry": {"coordinates":[74.769993,14.444336],"type":"Point"}
}