{
  "type": "Feature",
  "properties": {
    "gn:admin1_code":"13.0",
    "gn:admin2_code":"600.0",
    "gn:asciiname":"Ezhukone",
    "gn:country_code":"IN",
    "gn:dem":54,
    "gn:feature_class":"P",
    "gn:feature_code":"PPL",
    "gn:name":"Ezhukone",
    "gn:population":0,
    "gn:timezone":"Asia/Kolkata",
    "iso:country":"IN",
    "ks:ks_name":"Ezhukone",
    "ks:ks_pop":892,
    "ks:ks_type":"VILLAGE",
    "name:eng_x_preferred":[
        "Ezhukone"
    ],
    "name:mal_x_preferred":[
        "\u0d0e\u0d34\u0d41\u0d15\u0d4b\u0d7a"
    ],
    "wof:name":"Ezhukone",
    "wof:placetype":"locality",
    "wof:population":892
},
  "geometry": {"coordinates":[76.71524599999999,8.979377],"type":"Point"}
}