{
  "type": "Feature",
  "properties": {
    "gn:admin1_code":"13.0",
    "gn:admin2_code":"600.0",
    "gn:asciiname":"Ezhukone",
    "gn:country_code":"IN",
    "gn:dem":54,
    "gn:feature_class":"P",
    "gn:feature_code":"PPL",
    "gn:name":"Ezhukone",
    "gn:population":0,
    "gn:timezone":"Asia/Kolkata",
    "iso:country":"IN",
    "wof:name":"Ezhukone",
    "wof:placetype":"locality"
},
  "geometry": {"coordinates":[76.72145999999999,8.98036],"type":"Point"}
}