{
  "type": "Feature",
  "properties": {
    "iso:country":"IN",
    "ks:ks_alt_nam":"kuruthikulam",
    "ks:ks_name":"Kuruthikulam",
    "ks:ks_pop":100,
    "ks:ks_type":"HABITATION",
    "ks:ks_uagg_main":0,
    "name:eng_x_preferred":[
        "Kuruthikulam"
    ],
    "wof:name":"Kuruthikulam",
    "wof:placetype":"neighbourhood",
    "wof:population":100
},
  "geometry": {"coordinates":[78.500556,10.536853],"type":"Point"}
}