{
  "type": "Feature",
  "properties": {
    "gn:admin1_code":"40",
    "gn:admin2_code":"539.0",
    "gn:asciiname":"Durajpalli",
    "gn:country_code":"IN",
    "gn:dem":182,
    "gn:feature_class":"P",
    "gn:feature_code":"PPL",
    "gn:name":"Dur\u0101jpalli",
    "gn:population":0,
    "gn:timezone":"Asia/Kolkata",
    "iso:country":"IN",
    "wof:name":"Durajpalli",
    "wof:placetype":"locality"
},
  "geometry": {"coordinates":[79.66113,17.11049],"type":"Point"}
}