{
  "type": "Feature",
  "properties": {
    "iso:country":"IN",
    "ks:ks_name":"Somaradi",
    "ks:ks_pop":706,
    "ks:ks_type":"VILLAGE",
    "name:eng_x_preferred":[
        "Somaradi"
    ],
    "wof:name":"Somaradi",
    "wof:placetype":"locality",
    "wof:population":706
},
  "geometry": {"coordinates":[71.43547,25.003378],"type":"Point"}
}