{
  "type": "Feature",
  "properties": {
    "iso:country":"IN",
    "ks:ks_name":"Mauhariya",
    "ks:ks_pop":239,
    "ks:ks_type":"HABITATION",
    "name:eng_x_preferred":[
        "Mauhariya"
    ],
    "wof:name":"Mauhariya",
    "wof:placetype":"locality",
    "wof:population":239
},
  "geometry": {"coordinates":[81.422045,25.051183],"type":"Point"}
}