{
  "type": "Feature",
  "properties": {
    "iso:country":"IN",
    "ks:ks_name":"Bhangagara",
    "ks:ks_pop":3295,
    "ks:ks_type":"VILLAGE",
    "name:eng_x_preferred":[
        "Bhangagara"
    ],
    "wof:name":"Bhangagara",
    "wof:placetype":"locality",
    "wof:population":3295
},
  "geometry": {"coordinates":[88.073897,22.181402],"type":"Point"}
}