{
  "type": "Feature",
  "properties": {
    "iso:country":"IN",
    "ks:ks_alt_nam":"Pandit para",
    "ks:ks_name":"Pandit Para",
    "ks:ks_pop":664,
    "ks:ks_type":"HABITATION",
    "ks:ks_uagg_main":0,
    "name:eng_x_preferred":[
        "Pandit Para"
    ],
    "wof:name":"Pandit Para",
    "wof:placetype":"neighbourhood",
    "wof:population":664
},
  "geometry": {"coordinates":[88.192218,22.655527],"type":"Point"}
}