{
  "type": "Feature",
  "properties": {
    "iso:country":"IN",
    "ks:ks_name":"Jamghad",
    "ks:ks_pop":2,
    "ks:ks_type":"HABITATION",
    "name:eng_x_preferred":[
        "Jamghad"
    ],
    "wof:name":"Jamghad",
    "wof:placetype":"locality",
    "wof:population":2
},
  "geometry": {"coordinates":[77.29237000000001,22.262044],"type":"Point"}
}