{
  "type": "Feature",
  "properties": {
    "iso:country":"IN",
    "ks:ks_alt_nam":"M\u0101k\u0101ram",
    "ks:ks_name":"Makaram",
    "ks:ks_type":"VILLAGE",
    "name:eng_x_preferred":[
        "Makaram"
    ],
    "name:eng_x_variant":[
        "M\u0101k\u0101ram"
    ],
    "wof:name":"Makaram",
    "wof:placetype":"locality"
},
  "geometry": {"coordinates":[82.057304,17.626743],"type":"Point"}
}