{
  "type": "Feature",
  "properties": {
    "iso:country":"IN",
    "ks:ks_alt_nam":"Angarapeta colony",
    "ks:ks_name":"Angarapeta Colony",
    "ks:ks_pop":292,
    "ks:ks_type":"HABITATION",
    "name:eng_x_preferred":[
        "Angarapeta Colony"
    ],
    "wof:name":"Angarapeta Colony",
    "wof:placetype":"locality",
    "wof:population":292
},
  "geometry": {"coordinates":[81.906284,16.682032],"type":"Point"}
}