{
  "type": "Feature",
  "properties": {
    "iso:country":"IN",
    "ks:ks_name":"Karattappadi",
    "ks:ks_pop":428,
    "ks:ks_type":"HABITATION",
    "name:eng_x_preferred":[
        "Karattappadi"
    ],
    "wof:name":"Karattappadi",
    "wof:placetype":"locality",
    "wof:population":428
},
  "geometry": {"coordinates":[76.03085400000001,11.647724],"type":"Point"}
}