{
  "type": "Feature",
  "properties": {
    "iso:country":"IN",
    "ks:ks_name":"Rahangi F.V.",
    "ks:ks_pop":337,
    "ks:ks_type":"VILLAGE",
    "name:eng_x_preferred":[
        "Rahangi F.V."
    ],
    "wof:name":"Rahangi F.V.",
    "wof:placetype":"locality",
    "wof:population":337
},
  "geometry": {"coordinates":[80.993786,22.457927],"type":"Point"}
}