{
  "type": "Feature",
  "properties": {
    "iso:country":"IN",
    "ks:ks_name":"Tankotola",
    "ks:ks_pop":313,
    "ks:ks_type":"HABITATION",
    "name:eng_x_preferred":[
        "Tankotola"
    ],
    "wof:name":"Tankotola",
    "wof:placetype":"locality",
    "wof:population":313
},
  "geometry": {"coordinates":[84.929142,22.144716],"type":"Point"}
}