{
  "type": "Feature",
  "properties": {
    "gn:admin1_code":"11",
    "gn:admin2_code":"24.0",
    "gn:asciiname":"Keri",
    "gn:country_code":"IN",
    "gn:dem":785,
    "gn:feature_class":"P",
    "gn:feature_code":"PPL",
    "gn:name":"Keri",
    "gn:population":0,
    "gn:timezone":"Asia/Kolkata",
    "iso:country":"IN",
    "wof:name":"Keri",
    "wof:placetype":"locality"
},
  "geometry": {"coordinates":[76.16818000000001,32.20892],"type":"Point"}
}