{
  "type": "Feature",
  "properties": {
    "gn:admin1_code":"2.0",
    "gn:admin2_code":"542",
    "gn:asciiname":"Avagudem",
    "gn:country_code":"IN",
    "gn:dem":136,
    "gn:feature_class":"P",
    "gn:feature_code":"PPL",
    "gn:name":"Avag\u016bdem",
    "gn:population":0,
    "gn:timezone":"Asia/Kolkata",
    "iso:country":"IN",
    "wof:name":"Avagudem",
    "wof:placetype":"locality"
},
  "geometry": {"coordinates":[83.54488000000001,18.36113],"type":"Point"}
}