{
  "type": "Feature",
  "properties": {
    "iso:country":"IN",
    "ks:ks_name":"Veettiyoor St Colony",
    "ks:ks_pop":870,
    "ks:ks_type":"HABITATION",
    "name:eng_x_preferred":[
        "Veettiyoor St Colony"
    ],
    "wof:name":"Veettiyoor St Colony",
    "wof:placetype":"locality",
    "wof:population":870
},
  "geometry": {"coordinates":[76.58450499999999,11.088335],"type":"Point"}
}