{
  "type": "Feature",
  "properties": {
    "iso:country":"IN",
    "ks:ks_name":"Sangampalayam",
    "ks:ks_pop":2268,
    "ks:ks_type":"VILLAGE",
    "ks:ks_uagg_main":0,
    "name:eng_x_preferred":[
        "Sangampalayam"
    ],
    "wof:name":"Sangampalayam",
    "wof:placetype":"locality",
    "wof:population":2268
},
  "geometry": {"coordinates":[77.001975,10.685018],"type":"Point"}
}