{
  "type": "Feature",
  "properties": {
    "iso:country":"IN",
    "ks:ks_name":"Simro",
    "ks:ks_pop":2423,
    "ks:ks_type":"HABITATION",
    "name:eng_x_preferred":[
        "Simro"
    ],
    "wof:name":"Simro",
    "wof:placetype":"locality",
    "wof:population":2423
},
  "geometry": {"coordinates":[87.14354,25.202358],"type":"Point"}
}