{
  "type": "Feature",
  "properties": {
    "iso:country":"IN",
    "ks:ks_alt_nam":"MENDER",
    "ks:ks_name":"Mender",
    "ks:ks_pop":1081,
    "ks:ks_type":"HABITATION",
    "name:eng_x_preferred":[
        "Mender"
    ],
    "wof:name":"Mender",
    "wof:placetype":"locality",
    "wof:population":1081
},
  "geometry": {"coordinates":[83.85084000000001,22.351043],"type":"Point"}
}