{
  "type": "Feature",
  "properties": {
    "iso:country":"IN",
    "ks:ks_name":"Mand Rampur",
    "ks:ks_pop":20,
    "ks:ks_type":"VILLAGE",
    "name:eng_x_preferred":[
        "Mand Rampur"
    ],
    "wof:name":"Mand Rampur",
    "wof:placetype":"locality",
    "wof:population":20
},
  "geometry": {"coordinates":[75.30395900000001,31.502915],"type":"Point"}
}