{
  "type": "Feature",
  "properties": {
    "iso:country":"IN",
    "ks:ks_name":"Narayanpur",
    "ks:ks_pop":423,
    "ks:ks_type":"VILLAGE",
    "name:eng_x_preferred":[
        "Narayanpur"
    ],
    "wof:name":"Narayanpur",
    "wof:placetype":"locality",
    "wof:population":423
},
  "geometry": {"coordinates":[72.92243499999999,23.909335],"type":"Point"}
}