{
  "type": "Feature",
  "properties": {
    "iso:country":"IN",
    "ks:ks_alt_nam":"khadehra",
    "ks:ks_name":"Khadehra",
    "ks:ks_pop":600,
    "ks:ks_type":"HABITATION",
    "name:eng_x_preferred":[
        "Khadehra"
    ],
    "wof:name":"Khadehra",
    "wof:placetype":"locality",
    "wof:population":600
},
  "geometry": {"coordinates":[82.14301399999999,25.098752],"type":"Point"}
}