{
  "type": "Feature",
  "properties": {
    "iso:country":"IN",
    "ks:ks_alt_nam":"harijan Basti",
    "ks:ks_name":"Harijan Basti",
    "ks:ks_pop":57,
    "ks:ks_type":"HABITATION",
    "name:eng_x_preferred":[
        "Harijan Basti"
    ],
    "wof:name":"Harijan Basti",
    "wof:placetype":"locality",
    "wof:population":57
},
  "geometry": {"coordinates":[83.15356199999999,24.650355],"type":"Point"}
}