{
  "type": "Feature",
  "properties": {
    "iso:country":"IN",
    "ks:ks_name":"Khandabara",
    "ks:ks_pop":482,
    "ks:ks_type":"VILLAGE",
    "name:eng_x_preferred":[
        "Khandabara"
    ],
    "wof:name":"Khandabara",
    "wof:placetype":"locality",
    "wof:population":482
},
  "geometry": {"coordinates":[84.77803,20.942533],"type":"Point"}
}