{
  "type": "Feature",
  "properties": {
    "iso:country":"IN",
    "ks:ks_name":"Kottampara St Clny",
    "ks:ks_pop":962,
    "ks:ks_type":"HABITATION",
    "name:eng_x_preferred":[
        "Kottampara St Clny"
    ],
    "wof:name":"Kottampara St Clny",
    "wof:placetype":"locality",
    "wof:population":962
},
  "geometry": {"coordinates":[77.012034,9.200233],"type":"Point"}
}