{
  "type": "Feature",
  "properties": {
    "iso:country":"IN",
    "ks:ks_name":"Sadullahpur",
    "ks:ks_pop":49,
    "ks:ks_type":"VILLAGE",
    "name:eng_x_preferred":[
        "Sadullahpur"
    ],
    "wof:name":"Sadullahpur",
    "wof:placetype":"locality",
    "wof:population":49
},
  "geometry": {"coordinates":[85.28641,25.911269],"type":"Point"}
}