{
  "type": "Feature",
  "properties": {
    "iso:country":"IN",
    "ks:ks_name":"Asakbari Dwitiakhanda",
    "ks:ks_pop":1146,
    "ks:ks_type":"VILLAGE",
    "name:eng_x_preferred":[
        "Asakbari Dwitiakhanda"
    ],
    "wof:name":"Asakbari Dwitiakhanda",
    "wof:placetype":"locality",
    "wof:population":1146
},
  "geometry": {"coordinates":[89.131579,26.366811],"type":"Point"}
}