{
  "type": "Feature",
  "properties": {
    "iso:country":"IN",
    "ks:ks_name":"Hadouli",
    "ks:ks_pop":531,
    "ks:ks_type":"HABITATION",
    "name:eng_x_preferred":[
        "Hadouli"
    ],
    "wof:name":"Hadouli",
    "wof:placetype":"locality",
    "wof:population":531
},
  "geometry": {"coordinates":[79.70576800000001,29.706523],"type":"Point"}
}