{
  "type": "Feature",
  "properties": {
    "iso:country":"IN",
    "ks:ks_name":"Chandukattemole",
    "ks:ks_pop":697,
    "ks:ks_type":"HABITATION",
    "name:eng_x_preferred":[
        "Chandukattemole"
    ],
    "wof:name":"Chandukattemole",
    "wof:placetype":"locality",
    "wof:population":697
},
  "geometry": {"coordinates":[76.963086,11.895082],"type":"Point"}
}