{
  "type": "Feature",
  "properties": {
    "iso:country":"IN",
    "ks:ks_name":"Dohana",
    "ks:ks_pop":174,
    "ks:ks_type":"VILLAGE",
    "name:eng_x_preferred":[
        "Dohana"
    ],
    "wof:name":"Dohana",
    "wof:placetype":"locality",
    "wof:population":174
},
  "geometry": {"coordinates":[76.735108,28.236767],"type":"Point"}
}