{
  "type": "Feature",
  "properties": {
    "iso:country":"IN",
    "ks:ks_name":"Silagam",
    "ks:ks_pop":487,
    "ks:ks_type":"HABITATION",
    "ks:ks_uagg_main":0,
    "name:eng_x_preferred":[
        "Silagam"
    ],
    "wof:name":"Silagam",
    "wof:placetype":"neighbourhood",
    "wof:population":487
},
  "geometry": {"coordinates":[84.10127,18.339056],"type":"Point"}
}