{
  "type": "Feature",
  "properties": {
    "gn:admin1_code":"35",
    "gn:admin2_code":"445.0",
    "gn:asciiname":"Thikri",
    "gn:country_code":"IN",
    "gn:dem":316,
    "gn:feature_class":"P",
    "gn:feature_code":"PPL",
    "gn:name":"Thikri",
    "gn:population":0,
    "gn:timezone":"Asia/Kolkata",
    "iso:country":"IN",
    "name:ceb_x_preferred":[
        "Th\u012bkri"
    ],
    "name:swe_x_preferred":[
        "Th\u012bkri"
    ],
    "wof:name":"Thikri",
    "wof:placetype":"locality"
},
  "geometry": {"coordinates":[77.99169000000001,22.85532000000001],"type":"Point"}
}