{
  "type": "Feature",
  "properties": {
    "iso:country":"IN",
    "ks:ks_alt_nam":"Kannan\u016br",
    "ks:ks_name":"Kannanur",
    "ks:ks_pop":0,
    "ks:ks_type":"VILLAGE",
    "ks:ks_uagg_main":0,
    "name:eng_x_preferred":[
        "Kannanur"
    ],
    "name:eng_x_variant":[
        "Kannan\u016br"
    ],
    "wof:name":"Kannanur",
    "wof:placetype":"neighbourhood",
    "wof:population":0
},
  "geometry": {"coordinates":[78.741831,10.919852],"type":"Point"}
}