{
  "type": "Feature",
  "properties": {
    "iso:country":"IN",
    "ks:ks_name":"Shishviya",
    "ks:ks_pop":603,
    "ks:ks_type":"VILLAGE",
    "name:eng_x_preferred":[
        "Shishviya"
    ],
    "wof:name":"Shishviya",
    "wof:placetype":"locality",
    "wof:population":603
},
  "geometry": {"coordinates":[73.212463,24.256425],"type":"Point"}
}