{
  "type": "Feature",
  "properties": {
    "iso:country":"IN",
    "ks:ks_name":"Balapada",
    "ks:ks_pop":1281,
    "ks:ks_type":"HABITATION",
    "name:eng_x_preferred":[
        "Balapada"
    ],
    "wof:name":"Balapada",
    "wof:placetype":"locality",
    "wof:population":1281
},
  "geometry": {"coordinates":[73.39749999999999,20.065278],"type":"Point"}
}