{
  "type": "Feature",
  "properties": {
    "iso:country":"IN",
    "ks:ks_name":"Chak Kutubpur",
    "ks:ks_pop":0,
    "ks:ks_type":"VILLAGE",
    "name:eng_x_preferred":[
        "Chak Kutubpur"
    ],
    "wof:name":"Chak Kutubpur",
    "wof:placetype":"locality",
    "wof:population":0
},
  "geometry": {"coordinates":[88.147088,24.453928],"type":"Point"}
}