{
  "type": "Feature",
  "properties": {
    "iso:country":"IN",
    "ks:ks_alt_nam":"BAGALI BANDH KORASI",
    "ks:ks_name":"Bagali Bandh Korasi",
    "ks:ks_pop":200,
    "ks:ks_type":"HABITATION",
    "name:eng_x_preferred":[
        "Bagali Bandh Korasi"
    ],
    "wof:name":"Bagali Bandh Korasi",
    "wof:placetype":"locality",
    "wof:population":200
},
  "geometry": {"coordinates":[86.35779100000001,25.193457],"type":"Point"}
}