{
  "type": "Feature",
  "properties": {
    "iso:country":"IN",
    "ks:ks_name":"Tarauni",
    "ks:ks_pop":380,
    "ks:ks_type":"HABITATION",
    "name:eng_x_preferred":[
        "Tarauni"
    ],
    "wof:name":"Tarauni",
    "wof:placetype":"locality",
    "wof:population":380
},
  "geometry": {"coordinates":[85.59562099999999,25.073164],"type":"Point"}
}