{
  "type": "Feature",
  "properties": {
    "iso:country":"IN",
    "ks:ks_name":"Malitola",
    "ks:ks_pop":75,
    "ks:ks_type":"HABITATION",
    "name:eng_x_preferred":[
        "Malitola"
    ],
    "wof:name":"Malitola",
    "wof:placetype":"locality",
    "wof:population":75
},
  "geometry": {"coordinates":[84.904822,25.114014],"type":"Point"}
}