{
  "type": "Feature",
  "properties": {
    "gn:admin1_code":"12.0",
    "gn:admin2_code":"021",
    "gn:asciiname":"Nibali",
    "gn:country_code":"IN",
    "gn:dem":474,
    "gn:feature_class":"P",
    "gn:feature_code":"PPL",
    "gn:name":"Nib\u0101li",
    "gn:population":0,
    "gn:timezone":"Asia/Kolkata",
    "iso:country":"IN",
    "name:deu_x_preferred":[
        "Nibali"
    ],
    "name:fra_x_preferred":[
        "Nibali"
    ],
    "name:ita_x_preferred":[
        "Nibali"
    ],
    "name:nds_x_preferred":[
        "Nibali"
    ],
    "wof:name":"Nibali",
    "wof:placetype":"locality"
},
  "geometry": {"coordinates":[74.90139000000001,32.73333],"type":"Point"}
}