{
  "type": "Feature",
  "properties": {
    "gn:admin1_code":"11.0",
    "gn:admin2_code":"25.0",
    "gn:asciiname":"Chaling",
    "gn:country_code":"IN",
    "gn:dem":3478,
    "gn:feature_class":"P",
    "gn:feature_code":"PPL",
    "gn:name":"Ch\u0101ling",
    "gn:population":0,
    "gn:timezone":"Asia/Kolkata",
    "iso:country":"IN",
    "wof:name":"Chaling",
    "wof:placetype":"locality"
},
  "geometry": {"coordinates":[76.82628000000003,32.85716],"type":"Point"}
}