{
  "type": "Feature",
  "properties": {
    "iso:country":"IN",
    "ks:ks_name":"Murzar",
    "ks:ks_pop":26,
    "ks:ks_type":"VILLAGE",
    "name:eng_x_preferred":[
        "Murzar"
    ],
    "wof:name":"Murzar",
    "wof:placetype":"locality",
    "wof:population":26
},
  "geometry": {"coordinates":[80.46893300000001,20.419838],"type":"Point"}
}