{
  "type": "Feature",
  "properties": {
    "iso:country":"IN",
    "ks:ks_alt_nam":"Gadabhanja  IV",
    "ks:ks_name":"Gadabhanja Iv",
    "ks:ks_pop":299,
    "ks:ks_type":"HABITATION",
    "name:eng_x_preferred":[
        "Gadabhanja Iv"
    ],
    "name:eng_x_variant":[
        "Gadabhanja  IV"
    ],
    "wof:name":"Gadabhanja Iv",
    "wof:placetype":"locality",
    "wof:population":299
},
  "geometry": {"coordinates":[86.816582,21.418947],"type":"Point"}
}