{
  "type": "Feature",
  "properties": {
    "iso:country":"IN",
    "ks:ks_name":"Bhikhanpura",
    "ks:ks_pop":0,
    "ks:ks_type":"VILLAGE",
    "name:eng_x_preferred":[
        "Bhikhanpura"
    ],
    "wof:name":"Bhikhanpura",
    "wof:placetype":"locality",
    "wof:population":0
},
  "geometry": {"coordinates":[84.003142,25.002855],"type":"Point"}
}