{
  "type": "Feature",
  "properties": {
    "iso:country":"IN",
    "ks:ks_name":"Koniwadi",
    "ks:ks_pop":49,
    "ks:ks_type":"HABITATION",
    "name:eng_x_preferred":[
        "Koniwadi"
    ],
    "wof:name":"Koniwadi",
    "wof:placetype":"locality",
    "wof:population":49
},
  "geometry": {"coordinates":[73.62962899999999,16.111345],"type":"Point"}
}