{
  "type": "Feature",
  "properties": {
    "gn:admin1_code":"12.0",
    "gn:admin2_code":"14.0",
    "gn:asciiname":"Ganamandu",
    "gn:country_code":"IN",
    "gn:dem":2698,
    "gn:feature_class":"P",
    "gn:feature_code":"PPL",
    "gn:name":"Ganamandu",
    "gn:population":0,
    "gn:timezone":"Asia/Kolkata",
    "iso:country":"IN",
    "wof:name":"Ganamandu",
    "wof:placetype":"locality"
},
  "geometry": {"coordinates":[75.42345999999998,33.77747],"type":"Point"}
}