{
  "type": "Feature",
  "properties": {
    "iso:country":"IN",
    "ks:ks_name":"Malenalli",
    "ks:ks_pop":152,
    "ks:ks_type":"HABITATION",
    "name:eng_x_preferred":[
        "Malenalli"
    ],
    "wof:name":"Malenalli",
    "wof:placetype":"locality",
    "wof:population":152
},
  "geometry": {"coordinates":[74.825661,14.566228],"type":"Point"}
}