{
  "type": "Feature",
  "properties": {
    "iso:country":"IN",
    "ks:ks_name":"Ghori",
    "ks:ks_pop":1362,
    "ks:ks_type":"VILLAGE",
    "name:eng_x_preferred":[
        "Ghori"
    ],
    "wof:name":"Ghori",
    "wof:placetype":"locality",
    "wof:population":1362
},
  "geometry": {"coordinates":[74.66830299999999,23.653213],"type":"Point"}
}