{
  "type": "Feature",
  "properties": {
    "iso:country":"IN",
    "ks:ks_name":"Budung",
    "ks:ks_pop":49,
    "ks:ks_type":"VILLAGE",
    "name:eng_x_preferred":[
        "Budung"
    ],
    "wof:name":"Budung",
    "wof:placetype":"locality",
    "wof:population":49
},
  "geometry": {"coordinates":[83.663219,20.161732],"type":"Point"}
}