{
  "type": "Feature",
  "properties": {
    "iso:country":"IN",
    "ks:ks_alt_nam":"bhattipada",
    "ks:ks_name":"Bhattipada",
    "ks:ks_pop":100,
    "ks:ks_type":"HABITATION",
    "name:eng_x_preferred":[
        "Bhattipada"
    ],
    "wof:name":"Bhattipada",
    "wof:placetype":"locality",
    "wof:population":100
},
  "geometry": {"coordinates":[73.261661,19.838109],"type":"Point"}
}