{
  "type": "Feature",
  "properties": {
    "iso:country":"IN",
    "ks:ks_name":"Aniganahally",
    "ks:ks_pop":47,
    "ks:ks_type":"HABITATION",
    "name:eng_x_preferred":[
        "Aniganahally"
    ],
    "wof:name":"Aniganahally",
    "wof:placetype":"locality",
    "wof:population":47
},
  "geometry": {"coordinates":[75.962993,12.905432],"type":"Point"}
}