{
  "type": "Feature",
  "properties": {
    "iso:country":"IN",
    "ks:ks_name":"Mata Temple",
    "ks:ks_pop":125,
    "ks:ks_type":"HABITATION",
    "name:eng_x_preferred":[
        "Mata Temple"
    ],
    "wof:name":"Mata Temple",
    "wof:placetype":"locality",
    "wof:population":125
},
  "geometry": {"coordinates":[75.45777,12.965827],"type":"Point"}
}