{
  "type": "Feature",
  "properties": {
    "iso:country":"IN",
    "ks:ks_name":"Punarwasan",
    "ks:ks_pop":1030,
    "ks:ks_type":"HABITATION",
    "ks:ks_uagg_main":0,
    "name:eng_x_preferred":[
        "Punarwasan"
    ],
    "wof:name":"Punarwasan",
    "wof:placetype":"neighbourhood",
    "wof:population":1030
},
  "geometry": {"coordinates":[74.58936,18.43338],"type":"Point"}
}