{
  "type": "Feature",
  "properties": {
    "iso:country":"IN",
    "ks:ks_alt_nam":"Giria para",
    "ks:ks_name":"Giria Para",
    "ks:ks_pop":1005,
    "ks:ks_type":"HABITATION",
    "name:eng_x_preferred":[
        "Giria Para"
    ],
    "wof:name":"Giria Para",
    "wof:placetype":"locality",
    "wof:population":1005
},
  "geometry": {"coordinates":[71.22194399999999,21.617778],"type":"Point"}
}