{
  "type": "Feature",
  "properties": {
    "gn:admin1_code":"2.0",
    "gn:admin2_code":"554.0",
    "gn:asciiname":"Diguvakammapalle",
    "gn:country_code":"IN",
    "gn:dem":850,
    "gn:feature_class":"P",
    "gn:feature_code":"PPL",
    "gn:name":"Diguvakammapalle",
    "gn:population":0,
    "gn:timezone":"Asia/Kolkata",
    "iso:country":"IN",
    "wof:name":"Diguvakammapalle",
    "wof:placetype":"neighbourhood"
},
  "geometry": {"coordinates":[78.39961,13.40637],"type":"Point"}
}