{
  "type": "Feature",
  "properties": {
    "gn:admin1_code":"23.0",
    "gn:admin2_code":"41.0",
    "gn:asciiname":"Khakat",
    "gn:country_code":"IN",
    "gn:dem":255,
    "gn:feature_class":"P",
    "gn:feature_code":"PPL",
    "gn:name":"Kh\u0101kat",
    "gn:population":0,
    "gn:timezone":"Asia/Kolkata",
    "iso:country":"IN",
    "ks:ks_alt_nam":"Kh\u0101kat",
    "ks:ks_name":"Khakat",
    "ks:ks_type":"VILLAGE",
    "ks:ks_uagg_main":0,
    "name:eng_x_preferred":[
        "Khakat"
    ],
    "name:eng_x_variant":[
        "Kh\u0101kat"
    ],
    "wof:name":"Khakat",
    "wof:placetype":"locality"
},
  "geometry": {"coordinates":[75.951764,30.846997],"type":"Point"}
}