{
  "type": "Feature",
  "properties": {
    "iso:country":"IN",
    "ks:ks_alt_nam":"Kach pada",
    "ks:ks_name":"Kach Pada",
    "ks:ks_pop":295,
    "ks:ks_type":"HABITATION",
    "name:eng_x_preferred":[
        "Kach Pada"
    ],
    "wof:name":"Kach Pada",
    "wof:placetype":"locality",
    "wof:population":295
},
  "geometry": {"coordinates":[72.81775,20.15275],"type":"Point"}
}