{
  "type": "Feature",
  "properties": {
    "iso:country":"IN",
    "ks:ks_name":"Sunkaradi",
    "ks:ks_pop":11,
    "ks:ks_type":"HABITATION",
    "name:eng_x_preferred":[
        "Sunkaradi"
    ],
    "wof:name":"Sunkaradi",
    "wof:placetype":"locality",
    "wof:population":11
},
  "geometry": {"coordinates":[75.368274,13.493709],"type":"Point"}
}