{
  "type": "Feature",
  "properties": {
    "iso:country":"IN",
    "ks:ks_name":"Dimiripatia",
    "ks:ks_pop":24,
    "ks:ks_type":"HABITATION",
    "name:eng_x_preferred":[
        "Dimiripatia"
    ],
    "wof:name":"Dimiripatia",
    "wof:placetype":"locality",
    "wof:population":24
},
  "geometry": {"coordinates":[84.781526,20.472507],"type":"Point"}
}