{
  "type": "Feature",
  "properties": {
    "iso:country":"IN",
    "ks:ks_name":"Patilpada",
    "ks:ks_pop":67,
    "ks:ks_type":"HABITATION",
    "name:eng_x_preferred":[
        "Patilpada"
    ],
    "wof:name":"Patilpada",
    "wof:placetype":"locality",
    "wof:population":67
},
  "geometry": {"coordinates":[73.02723899999999,19.905596],"type":"Point"}
}