{
  "type": "Feature",
  "properties": {
    "iso:country":"IN",
    "ks:ks_name":"Sharambera",
    "ks:ks_pop":54,
    "ks:ks_type":"HABITATION",
    "name:eng_x_preferred":[
        "Sharambera"
    ],
    "wof:name":"Sharambera",
    "wof:placetype":"locality",
    "wof:population":54
},
  "geometry": {"coordinates":[85.453504,23.151955],"type":"Point"}
}