{
  "type": "Feature",
  "properties": {
    "iso:country":"IN",
    "ks:ks_name":"Jairam Bakhl",
    "ks:ks_pop":43,
    "ks:ks_type":"VILLAGE",
    "name:eng_x_preferred":[
        "Jairam Bakhl"
    ],
    "wof:name":"Jairam Bakhl",
    "wof:placetype":"locality",
    "wof:population":43
},
  "geometry": {"coordinates":[79.30765700000001,29.898633],"type":"Point"}
}