{
  "type": "Feature",
  "properties": {
    "gn:admin1_code":"21",
    "gn:admin2_code":"374.0",
    "gn:asciiname":"Dambahal",
    "gn:country_code":"IN",
    "gn:dem":227,
    "gn:feature_class":"P",
    "gn:feature_code":"PPL",
    "gn:name":"Dambah\u0101l",
    "gn:population":0,
    "gn:timezone":"Asia/Kolkata",
    "iso:country":"IN",
    "ks:ks_name":"Dambahal",
    "ks:ks_pop":681,
    "ks:ks_type":"VILLAGE",
    "name:eng_x_preferred":[
        "Dambahal"
    ],
    "wof:name":"Dambahal",
    "wof:placetype":"locality",
    "wof:population":681
},
  "geometry": {"coordinates":[84.00507500000001,21.992957],"type":"Point"}
}