{
  "type": "Feature",
  "properties": {
    "iso:country":"IN",
    "ks:ks_name":"Solavampalayam",
    "ks:ks_pop":1876,
    "ks:ks_type":"HABITATION",
    "name:eng_x_preferred":[
        "Solavampalayam"
    ],
    "wof:name":"Solavampalayam",
    "wof:placetype":"locality",
    "wof:population":1876
},
  "geometry": {"coordinates":[77.005005,10.830425],"type":"Point"}
}