{
  "type": "Feature",
  "properties": {
    "gn:admin1_code":"35.0",
    "gn:admin2_code":"440",
    "gn:asciiname":"Bamanda",
    "gn:country_code":"IN",
    "gn:dem":189,
    "gn:feature_class":"P",
    "gn:feature_code":"PPL",
    "gn:name":"B\u0101manda",
    "gn:population":0,
    "gn:timezone":"Asia/Kolkata",
    "iso:country":"IN",
    "ks:ks_alt_nam":"B\u0101manda",
    "ks:ks_name":"Bamanda",
    "ks:ks_pop":1408,
    "ks:ks_type":"VILLAGE",
    "ks:ks_uagg_main":0,
    "name:eng_x_preferred":[
        "Bamanda"
    ],
    "name:eng_x_variant":[
        "B\u0101manda"
    ],
    "name:und_x_variant":[
        "B\u0101manda"
    ],
    "wof:name":"Bamanda",
    "wof:placetype":"neighbourhood",
    "wof:population":1408
},
  "geometry": {"coordinates":[75.54495799999999,22.065413],"type":"Point"}
}