{
  "type": "Feature",
  "properties": {
    "gn:admin1_code":"40",
    "gn:admin2_code":"533.0",
    "gn:asciiname":"Gundur",
    "gn:country_code":"IN",
    "gn:dem":449,
    "gn:feature_class":"P",
    "gn:feature_code":"PPL",
    "gn:name":"Gund\u016br",
    "gn:population":0,
    "gn:timezone":"Asia/Kolkata",
    "iso:country":"IN",
    "name:jpn_x_preferred":[
        "\u30b0\u30f3\u30c9\u30a5\u30fc\u30eb"
    ],
    "name:vie_x_preferred":[
        "Gundur"
    ],
    "wof:name":"Gundur",
    "wof:placetype":"neighbourhood"
},
  "geometry": {"coordinates":[77.56587,18.34571],"type":"Point"}
}