{
  "type": "Feature",
  "properties": {
    "gn:admin1_code":"2.0",
    "gn:admin2_code":"554.0",
    "gn:asciiname":"Chimaganipalle",
    "gn:country_code":"IN",
    "gn:dem":743,
    "gn:feature_class":"P",
    "gn:feature_code":"PPL",
    "gn:name":"Chimag\u0101nipalle",
    "gn:population":0,
    "gn:timezone":"Asia/Kolkata",
    "iso:country":"IN",
    "wof:name":"Chimaganipalle",
    "wof:placetype":"locality"
},
  "geometry": {"coordinates":[78.58684000000002,13.18953],"type":"Point"}
}