{
  "type": "Feature",
  "properties": {
    "gn:admin1_code":"2.0",
    "gn:admin2_code":"550",
    "gn:asciiname":"Chinnakraka",
    "gn:country_code":"IN",
    "gn:dem":29,
    "gn:feature_class":"P",
    "gn:feature_code":"PPL",
    "gn:name":"Chinnakr\u0101ka",
    "gn:population":0,
    "gn:timezone":"Asia/Kolkata",
    "iso:country":"IN",
    "wof:name":"Chinnakraka",
    "wof:placetype":"locality"
},
  "geometry": {"coordinates":[79.84591999999998,14.8518],"type":"Point"}
}