{
  "type": "Feature",
  "properties": {
    "iso:country":"IN",
    "ks:ks_name":"Hulidevara Honda",
    "ks:ks_pop":4,
    "ks:ks_type":"HABITATION",
    "name:eng_x_preferred":[
        "Hulidevara Honda"
    ],
    "wof:name":"Hulidevara Honda",
    "wof:placetype":"locality",
    "wof:population":4
},
  "geometry": {"coordinates":[74.65787899999999,14.371461],"type":"Point"}
}