{
  "type": "Feature",
  "properties": {
    "iso:country":"IN",
    "ks:ks_name":"Kakor Khurd",
    "ks:ks_pop":386,
    "ks:ks_type":"VILLAGE",
    "ks:ks_uagg_main":0,
    "name:eng_x_preferred":[
        "Kakor Khurd"
    ],
    "wof:name":"Kakor Khurd",
    "wof:placetype":"neighbourhood",
    "wof:population":386
},
  "geometry": {"coordinates":[79.559059,26.53023],"type":"Point"}
}