{
  "type": "Feature",
  "properties": {
    "gn:admin1_code":"36.0",
    "gn:admin2_code":"189.0",
    "gn:asciiname":"Mohani",
    "gn:country_code":"IN",
    "gn:dem":89,
    "gn:feature_class":"P",
    "gn:feature_code":"PPL",
    "gn:name":"Mohani",
    "gn:population":0,
    "gn:timezone":"Asia/Kolkata",
    "iso:country":"IN",
    "name:tam_x_preferred":[
        "\u0bae\u0bcb\u0b95\u0bbe\u0ba9\u0bbf"
    ],
    "wof:name":"Mohani",
    "wof:placetype":"locality"
},
  "geometry": {"coordinates":[83.77445999999998,26.89682],"type":"Point"}
}