{
  "type": "Feature",
  "properties": {
    "gn:admin1_code":"37.0",
    "gn:admin2_code":"414.0",
    "gn:asciiname":"Kapanapara",
    "gn:country_code":"IN",
    "gn:dem":650,
    "gn:feature_class":"P",
    "gn:feature_code":"PPL",
    "gn:name":"Kap\u0101nap\u0101ra",
    "gn:population":0,
    "gn:timezone":"Asia/Kolkata",
    "iso:country":"IN",
    "ks:ks_name":"Kapenpara",
    "ks:ks_pop":553,
    "ks:ks_type":"HABITATION",
    "name:eng_x_preferred":[
        "Kapenpara"
    ],
    "name:eng_x_variant":[
        "Kapanapara"
    ],
    "wof:name":"Kapenpara",
    "wof:placetype":"locality",
    "wof:population":553
},
  "geometry": {"coordinates":[81.908412,19.830459],"type":"Point"}
}