{
  "type": "Feature",
  "properties": {
    "gn:admin1_code":"35.0",
    "gn:admin2_code":"445.0",
    "gn:asciiname":"Khachrod",
    "gn:country_code":"IN",
    "gn:dem":524,
    "gn:feature_class":"P",
    "gn:feature_code":"PPL",
    "gn:name":"Kh\u0101chrod",
    "gn:population":0,
    "gn:timezone":"Asia/Kolkata",
    "iso:country":"IN",
    "name:ben_x_preferred":[
        "\u0996\u09be\u099a\u09b0\u09cb\u09a1"
    ],
    "name:bpy_x_preferred":[
        "\u0996\u09be\u099a\u09b0\u09cb\u09a1"
    ],
    "name:ceb_x_preferred":[
        "Kh\u0101chrod"
    ],
    "name:ita_x_preferred":[
        "Khacharod"
    ],
    "name:msa_x_preferred":[
        "Khachrod"
    ],
    "name:new_x_preferred":[
        "\u0916\u093e\u091a\u0930\u094b\u0926"
    ],
    "name:por_x_preferred":[
        "Khachrod"
    ],
    "name:spa_x_preferred":[
        "Khachrod"
    ],
    "name:swe_x_preferred":[
        "Kh\u0101chrod"
    ],
    "name:vie_x_preferred":[
        "Khachrod"
    ],
    "name:zho_x_preferred":[
        "\u5361\u5947\u7f57\u5fb7"
    ],
    "wof:name":"Khachrod",
    "wof:placetype":"locality"
},
  "geometry": {"coordinates":[76.71223000000001,22.87275],"type":"Point"}
}