{
  "type": "Feature",
  "properties": {
    "iso:country":"IN",
    "ks:ks_name":"Agavayal",
    "ks:ks_pop":55,
    "ks:ks_type":"VILLAGE",
    "name:eng_x_preferred":[
        "Agavayal"
    ],
    "wof:name":"Agavayal",
    "wof:placetype":"locality",
    "wof:population":55
},
  "geometry": {"coordinates":[78.918764,10.233792],"type":"Point"}
}