{
  "type": "Feature",
  "properties": {
    "gn:admin1_code":"39.0",
    "gn:admin2_code":"63.0",
    "gn:asciiname":"Harkhola",
    "gn:country_code":"IN",
    "gn:dem":1313,
    "gn:feature_class":"P",
    "gn:feature_code":"PPL",
    "gn:name":"Harkhola",
    "gn:population":0,
    "gn:timezone":"Asia/Kolkata",
    "iso:country":"IN",
    "ks:ks_name":"Harkhola",
    "ks:ks_pop":57,
    "ks:ks_type":"VILLAGE",
    "name:eng_x_preferred":[
        "Harkhola"
    ],
    "wof:name":"Harkhola",
    "wof:placetype":"locality",
    "wof:population":57
},
  "geometry": {"coordinates":[79.725093,29.756251],"type":"Point"}
}