{
  "type": "Feature",
  "properties": {
    "gn:admin1_code":"36",
    "gn:admin2_code":"197.0",
    "gn:asciiname":"Tikri Kalan",
    "gn:country_code":"IN",
    "gn:dem":85,
    "gn:feature_class":"P",
    "gn:feature_code":"PPL",
    "gn:name":"Tikri Kal\u0101n",
    "gn:population":0,
    "gn:timezone":"Asia/Kolkata",
    "iso:country":"IN",
    "name:und_x_variant":[
        "Tikri",
        "Tikri Kal\u0101n"
    ],
    "wof:name":"Tikri Kalan",
    "wof:placetype":"locality"
},
  "geometry": {"coordinates":[82.83717,25.41941],"type":"Point"}
}