{
  "type": "Feature",
  "properties": {
    "iso:country":"IN",
    "ks:ks_alt_nam":"PACHHIM TOLA",
    "ks:ks_name":"Pachhim Tola",
    "ks:ks_pop":200,
    "ks:ks_type":"HABITATION",
    "name:eng_x_preferred":[
        "Pachhim Tola"
    ],
    "wof:name":"Pachhim Tola",
    "wof:placetype":"locality",
    "wof:population":200
},
  "geometry": {"coordinates":[84.111754,25.364312],"type":"Point"}
}