{
  "type": "Feature",
  "properties": {
    "iso:country":"IN",
    "ks:ks_name":"Rorebasa",
    "ks:ks_pop":471,
    "ks:ks_type":"HABITATION",
    "name:eng_x_preferred":[
        "Rorebasa"
    ],
    "wof:name":"Rorebasa",
    "wof:placetype":"locality",
    "wof:population":471
},
  "geometry": {"coordinates":[85.77722799999999,22.279109],"type":"Point"}
}