{
  "type": "Feature",
  "properties": {
    "gn:admin1_code":"36",
    "gn:admin2_code":"157.0",
    "gn:asciiname":"Sarayan",
    "gn:country_code":"IN",
    "gn:dem":129,
    "gn:feature_class":"P",
    "gn:feature_code":"PPL",
    "gn:name":"Sar\u0101yan",
    "gn:population":0,
    "gn:timezone":"Asia/Kolkata",
    "iso:country":"IN",
    "name:ara_x_preferred":[
        "\u0633\u0631\u0627\u064a\u0627\u0646"
    ],
    "name:aze_x_preferred":[
        "Sarayan"
    ],
    "name:ceb_x_preferred":[
        "Sar\u0101y\u0101n"
    ],
    "name:fas_x_preferred":[
        "\u0633\u0631\u0627\u06cc\u0627\u0646"
    ],
    "name:ita_x_preferred":[
        "Sarayan"
    ],
    "name:mlg_x_preferred":[
        "Sarayan"
    ],
    "name:pnb_x_preferred":[
        "\u0633\u0631\u0627\u06cc\u0627\u0646"
    ],
    "name:tur_x_preferred":[
        "Serayan"
    ],
    "name:urd_x_preferred":[
        "\u0633\u0631\u0627\u06cc\u0627\u0646"
    ],
    "wof:name":"Sarayan",
    "wof:placetype":"locality"
},
  "geometry": {"coordinates":[81.03048000000003,27.09648],"type":"Point"}
}