{
  "type": "Feature",
  "properties": {
    "iso:country":"IN",
    "ks:ks_alt_nam":"Amaliyar falia",
    "ks:ks_name":"Amaliyar Falia",
    "ks:ks_pop":1307,
    "ks:ks_type":"HABITATION",
    "name:eng_x_preferred":[
        "Amaliyar Falia"
    ],
    "wof:name":"Amaliyar Falia",
    "wof:placetype":"locality",
    "wof:population":1307
},
  "geometry": {"coordinates":[74.38158300000001,22.77075],"type":"Point"}
}