{
  "type": "Feature",
  "properties": {
    "gn:admin1_code":"35.0",
    "gn:admin2_code":"447.0",
    "gn:asciiname":"Humanpeth",
    "gn:country_code":"IN",
    "gn:dem":738,
    "gn:feature_class":"P",
    "gn:feature_code":"PPL",
    "gn:name":"Humanpeth",
    "gn:population":0,
    "gn:timezone":"Asia/Kolkata",
    "iso:country":"IN",
    "wof:name":"Humanpeth",
    "wof:placetype":"locality"
},
  "geometry": {"coordinates":[78.10319,21.80482],"type":"Point"}
}