{
  "type": "Feature",
  "properties": {
    "iso:country":"IN",
    "ks:ks_name":"Kheema Gurha",
    "ks:ks_pop":338,
    "ks:ks_type":"VILLAGE",
    "name:eng_x_preferred":[
        "Kheema Gurha"
    ],
    "wof:name":"Kheema Gurha",
    "wof:placetype":"locality",
    "wof:population":338
},
  "geometry": {"coordinates":[73.829823,25.534849],"type":"Point"}
}