{
  "type": "Feature",
  "properties": {
    "iso:country":"IN",
    "ks:ks_name":"Sunder Radhe Ka Dera",
    "ks:ks_pop":100,
    "ks:ks_type":"HABITATION",
    "name:eng_x_preferred":[
        "Sunder Radhe Ka Dera"
    ],
    "wof:name":"Sunder Radhe Ka Dera",
    "wof:placetype":"locality",
    "wof:population":100
},
  "geometry": {"coordinates":[80.83290100000001,25.141825],"type":"Point"}
}