{
  "type": "Feature",
  "properties": {
    "iso:country":"IN",
    "ks:ks_name":"Khutuariguda",
    "ks:ks_pop":387,
    "ks:ks_type":"HABITATION",
    "name:eng_x_preferred":[
        "Khutuariguda"
    ],
    "wof:name":"Khutuariguda",
    "wof:placetype":"locality",
    "wof:population":387
},
  "geometry": {"coordinates":[82.145336,19.580934],"type":"Point"}
}