{
  "type": "Feature",
  "properties": {
    "gn:admin1_code":"38",
    "gn:admin2_code":"356.0",
    "gn:asciiname":"Nagjua",
    "gn:country_code":"IN",
    "gn:dem":703,
    "gn:feature_class":"P",
    "gn:feature_code":"PPL",
    "gn:name":"Nagju\u0101",
    "gn:population":0,
    "gn:timezone":"Asia/Kolkata",
    "iso:country":"IN",
    "wof:name":"Nagjua",
    "wof:placetype":"locality"
},
  "geometry": {"coordinates":[84.88205000000001,23.38272000000001],"type":"Point"}
}