{
  "type": "Feature",
  "properties": {
    "iso:country":"IN",
    "ks:ks_name":"Rajnagar",
    "ks:ks_pop":656,
    "ks:ks_type":"VILLAGE",
    "name:eng_x_preferred":[
        "Rajnagar"
    ],
    "wof:name":"Rajnagar",
    "wof:placetype":"locality",
    "wof:population":656
},
  "geometry": {"coordinates":[86.744226,20.932739],"type":"Point"}
}