{
  "type": "Feature",
  "properties": {
    "gn:admin1_code":"34.0",
    "gn:admin2_code":"231.0",
    "gn:asciiname":"Jagatpur",
    "gn:country_code":"IN",
    "gn:dem":61,
    "gn:feature_class":"P",
    "gn:feature_code":"PPL",
    "gn:name":"Jagatpur",
    "gn:population":0,
    "gn:timezone":"Asia/Kolkata",
    "iso:country":"IN",
    "name:ceb_x_preferred":[
        "Jagatpur"
    ],
    "name:pol_x_preferred":[
        "Jagatpur"
    ],
    "name:swe_x_preferred":[
        "Jagatpur"
    ],
    "wof:name":"Jagatpur",
    "wof:placetype":"locality"
},
  "geometry": {"coordinates":[84.59759,25.67113],"type":"Point"}
}