{
  "type": "Feature",
  "properties": {
    "gn:admin1_code":"25.0",
    "gn:admin2_code":"615.0",
    "gn:asciiname":"V.Kalathur",
    "gn:country_code":"IN",
    "gn:dem":100,
    "gn:feature_class":"P",
    "gn:feature_code":"PPL",
    "gn:name":"V.Kalathur",
    "gn:population":0,
    "gn:timezone":"Asia/Kolkata",
    "iso:country":"IN",
    "wof:name":"V.Kalathur",
    "wof:placetype":"locality"
},
  "geometry": {"coordinates":[78.92518000000003,11.40176],"type":"Point"}
}