{
  "type": "Feature",
  "properties": {
    "iso:country":"IN",
    "ks:ks_name":"Kesharuwa",
    "ks:ks_pop":200,
    "ks:ks_type":"HABITATION",
    "name:eng_x_preferred":[
        "Kesharuwa"
    ],
    "wof:name":"Kesharuwa",
    "wof:placetype":"locality",
    "wof:population":200
},
  "geometry": {"coordinates":[81.155781,25.078328],"type":"Point"}
}