{
  "type": "Feature",
  "properties": {
    "iso:country":"IN",
    "ks:ks_name":"Obadenahally",
    "ks:ks_pop":577,
    "ks:ks_type":"VILLAGE",
    "ks:ks_uagg_main":0,
    "name:eng_x_preferred":[
        "Obadenahally"
    ],
    "wof:name":"Obadenahally",
    "wof:placetype":"locality",
    "wof:population":577
},
  "geometry": {"coordinates":[77.57696799999999,13.275218],"type":"Point"}
}