{
  "type": "Feature",
  "properties": {
    "iso:country":"IN",
    "ks:ks_name":"Kootelu",
    "ks:ks_pop":330,
    "ks:ks_type":"HABITATION",
    "name:eng_x_preferred":[
        "Kootelu"
    ],
    "wof:name":"Kootelu",
    "wof:placetype":"locality",
    "wof:population":330
},
  "geometry": {"coordinates":[75.427232,12.606161],"type":"Point"}
}