{
  "type": "Feature",
  "properties": {
    "iso:country":"IN",
    "ks:ks_name":"Kishorepur",
    "ks:ks_pop":578,
    "ks:ks_type":"HABITATION",
    "name:eng_x_preferred":[
        "Kishorepur"
    ],
    "wof:name":"Kishorepur",
    "wof:placetype":"locality",
    "wof:population":578
},
  "geometry": {"coordinates":[92.386877,24.340831],"type":"Point"}
}