{
  "type": "Feature",
  "properties": {
    "gn:admin1_code":"35.0",
    "gn:admin2_code":"465.0",
    "gn:asciiname":"Aghran",
    "gn:country_code":"IN",
    "gn:dem":454,
    "gn:feature_class":"P",
    "gn:feature_code":"PPL",
    "gn:name":"Aghran",
    "gn:population":0,
    "gn:timezone":"Asia/Kolkata",
    "iso:country":"IN",
    "ks:ks_name":"Agran",
    "ks:ks_pop":481,
    "ks:ks_type":"VILLAGE",
    "name:eng_x_preferred":[
        "Agran"
    ],
    "name:eng_x_variant":[
        "Aghran"
    ],
    "wof:name":"Agran",
    "wof:placetype":"locality",
    "wof:population":481
},
  "geometry": {"coordinates":[74.22397599999999,22.513294],"type":"Point"}
}