{
  "type": "Feature",
  "properties": {
    "iso:country":"IN",
    "ks:ks_name":"Chilangia Alia Dharhakola",
    "ks:ks_pop":1762,
    "ks:ks_type":"HABITATION",
    "name:eng_x_preferred":[
        "Chilangia Alia Dharhakola"
    ],
    "wof:name":"Chilangia Alia Dharhakola",
    "wof:placetype":"locality",
    "wof:population":1762
},
  "geometry": {"coordinates":[85.68516200000001,24.52962],"type":"Point"}
}