{
  "type": "Feature",
  "properties": {
    "gn:admin1_code":"19.0",
    "gn:admin2_code":"572.0",
    "gn:asciiname":"Guniagrahar",
    "gn:country_code":"IN",
    "gn:dem":893,
    "gn:feature_class":"P",
    "gn:feature_code":"PPL",
    "gn:name":"Guniagrah\u0101r",
    "gn:population":0,
    "gn:timezone":"Asia/Kolkata",
    "iso:country":"IN",
    "ks:ks_name":"Guniagrahara",
    "ks:ks_pop":733,
    "ks:ks_type":"VILLAGE",
    "ks:ks_uagg_main":0,
    "name:eng_x_preferred":[
        "Guniagrahara"
    ],
    "wof:name":"Guniagrahara",
    "wof:placetype":"locality",
    "wof:population":733
},
  "geometry": {"coordinates":[77.523104,13.09908],"type":"Point"}
}