{
  "type": "Feature",
  "properties": {
    "gn:admin1_code":"2",
    "gn:admin2_code":"544.0",
    "gn:asciiname":"Doddimamidi",
    "gn:country_code":"IN",
    "gn:dem":1139,
    "gn:feature_class":"P",
    "gn:feature_code":"PPL",
    "gn:name":"Doddim\u0101midi",
    "gn:population":0,
    "gn:timezone":"Asia/Kolkata",
    "iso:country":"IN",
    "wof:name":"Doddimamidi",
    "wof:placetype":"locality"
},
  "geometry": {"coordinates":[82.96444,18.2797],"type":"Point"}
}