{
  "type": "Feature",
  "properties": {
    "iso:country":"IN",
    "ks:ks_name":"Sanjunaposi",
    "ks:ks_pop":223,
    "ks:ks_type":"VILLAGE",
    "name:eng_x_preferred":[
        "Sanjunaposi"
    ],
    "wof:name":"Sanjunaposi",
    "wof:placetype":"locality",
    "wof:population":223
},
  "geometry": {"coordinates":[86.031515,21.976948],"type":"Point"}
}