{
  "type": "Feature",
  "properties": {
    "iso:country":"IN",
    "ks:ks_name":"Sikhar Patra Bar",
    "ks:ks_pop":768,
    "ks:ks_type":"VILLAGE",
    "name:eng_x_preferred":[
        "Sikhar Patra Bar"
    ],
    "wof:name":"Sikhar Patra Bar",
    "wof:placetype":"locality",
    "wof:population":768
},
  "geometry": {"coordinates":[87.70493,21.890835],"type":"Point"}
}