{
  "type": "Feature",
  "properties": {
    "iso:country":"IN",
    "ks:ks_alt_nam":"Yadav tola",
    "ks:ks_name":"Yadav Tola",
    "ks:ks_pop":894,
    "ks:ks_type":"HABITATION",
    "name:eng_x_preferred":[
        "Yadav Tola"
    ],
    "wof:name":"Yadav Tola",
    "wof:placetype":"locality",
    "wof:population":894
},
  "geometry": {"coordinates":[87.409571,26.312206],"type":"Point"}
}