{
  "type": "Feature",
  "properties": {
    "iso:country":"IN",
    "ks:ks_name":"Mekhali Gaon",
    "ks:ks_pop":500,
    "ks:ks_type":"VILLAGE",
    "name:eng_x_preferred":[
        "Mekhali Gaon"
    ],
    "wof:name":"Mekhali Gaon",
    "wof:placetype":"locality",
    "wof:population":500
},
  "geometry": {"coordinates":[94.266682,26.952546],"type":"Point"}
}