{
  "type": "Feature",
  "properties": {
    "gn:admin1_code":"36",
    "gn:admin2_code":"159.0",
    "gn:asciiname":"Birsinghpur",
    "gn:country_code":"IN",
    "gn:dem":156,
    "gn:feature_class":"P",
    "gn:feature_code":"PPL",
    "gn:name":"B\u012brsinghpur",
    "gn:population":0,
    "gn:timezone":"Asia/Kolkata",
    "iso:country":"IN",
    "name:ben_x_preferred":[
        "\u09ac\u09c0\u09b0\u09b8\u09bf\u0982\u09b9\u09aa\u09c1\u09b0"
    ],
    "name:bpy_x_preferred":[
        "\u09ac\u09c0\u09b0\u09b8\u09bf\u0982\u09b9\u09aa\u09c1\u09b0"
    ],
    "name:hin_x_preferred":[
        "\u092c\u0940\u0930\u0938\u093f\u0902\u0939\u092a\u0941\u0930"
    ],
    "name:ita_x_preferred":[
        "Birsinghpur"
    ],
    "name:msa_x_preferred":[
        "Birsinghpur"
    ],
    "name:new_x_preferred":[
        "\u0935\u0940\u0930\u0938\u093f\u0902\u0939\u092a\u0941\u0930"
    ],
    "name:nld_x_preferred":[
        "Birsinghpur"
    ],
    "name:por_x_preferred":[
        "Birsinghpur"
    ],
    "name:spa_x_preferred":[
        "Birsinghpur"
    ],
    "name:vie_x_preferred":[
        "Birsinghpur"
    ],
    "name:zho_x_preferred":[
        "\u6bd4\u5c14\u8f9b\u683c\u666e\u5c14"
    ],
    "wof:name":"Birsinghpur",
    "wof:placetype":"locality"
},
  "geometry": {"coordinates":[79.38287,27.44436],"type":"Point"}
}