{
  "type": "Feature",
  "properties": {
    "iso:country":"IN",
    "name:ara_x_preferred":[
        "\u0633\u0648\u0634\u0627\u0646\u062a \u0644\u0648\u0643"
    ],
    "name:ben_bn_x_preferred":[
        "\u09b8\u09c1\u09b6\u09be\u09a8\u09cd\u09a4 \u09b2\u09cb\u0995"
    ],
    "name:ben_in_x_preferred":[
        "\u09b8\u09c1\u09b6\u09be\u09a8\u09cd\u09a4 \u09b2\u09cb\u0995"
    ],
    "name:eng_x_preferred":[
        "Sushant Lok"
    ],
    "name:guj_x_preferred":[
        "\u0ab8\u0ac1\u0ab6\u0abe\u0a82\u0aa4 \u0ab2\u0acb\u0a95"
    ],
    "name:hin_x_preferred":[
        "\u0938\u0941\u0936\u093e\u0902\u0924 \u0932\u094b\u0915"
    ],
    "name:kan_x_preferred":[
        "\u0cb8\u0cc1\u0cb7\u0cbe\u0c82\u0ca4\u0ccd \u0cb2\u0ccb\u0c95\u0ccd"
    ],
    "name:mal_x_preferred":[
        "\u0d38\u0d41\u0d36\u0d3e\u0d28\u0d4d\u0d24\u0d4d \u0d32\u0d4b\u0d15\u0d4d"
    ],
    "name:mar_x_preferred":[
        "\u0938\u0941\u0936\u093e\u0902\u0924 \u0932\u094b\u0915"
    ],
    "name:pan_x_preferred":[
        "\u0a38\u0a41\u0a36\u0a3e\u0a02\u0a24 \u0a32\u0a4b\u0a15"
    ],
    "name:tam_x_preferred":[
        "\u0b9a\u0bc1\u0bb7\u0bbe\u0ba8\u0bcd\u0ba4\u0bcd \u0bb2\u0bcb\u0b95\u0bcd"
    ],
    "name:tel_x_preferred":[
        "\u0c38\u0c41\u0c36\u0c3e\u0c02\u0c24\u0c4d \u0c32\u0c4b\u0c15\u0c4d"
    ],
    "name:urd_x_preferred":[
        "\u0633\u064f\u0634\u0646\u0627\u0646\u062a \u0644\u0648\u06a9"
    ],
    "qs:gn_adm0_cc":"IN",
    "qs:gn_local":1270642,
    "qs:gn_nam_loc":"Gurgaon, Gurgaon, Haryana, IN",
    "qs:gn_namadm1":"10",
    "qs:local_max":764,
    "qs:local_sum":4037,
    "qs:localhoods":24,
    "qs:name":"Sushant Lok",
    "qs:name_adm0":"India",
    "qs:name_adm1":"Haryana",
    "qs:name_adm2":"Gurgaon",
    "qs:name_local":"Gurgaon",
    "qs:photo_max":21,
    "qs:photo_sum":64,
    "qs:placetype":"Suburb",
    "qs:quad_count":7,
    "qs:woe_adm0":23424848,
    "qs:woe_adm1":2345744,
    "qs:woe_adm2":12586441,
    "qs:woe_lau":0,
    "qs:woe_local":2295020,
    "qs:woe_ver":"7.10.0",
    "wof:lang":[
        "eng"
    ],
    "wof:name":"Sushant Lok",
    "wof:placetype":"neighbourhood"
},
  "geometry": {"coordinates":[77.077547,28.467206],"type":"Point"}
}