{
  "type": "Feature",
  "properties": {
    "gn:admin1_code":"36",
    "gn:admin2_code":"132.0",
    "gn:asciiname":"Ladwa",
    "gn:country_code":"IN",
    "gn:dem":292,
    "gn:feature_class":"P",
    "gn:feature_code":"PPL",
    "gn:name":"Ladwa",
    "gn:population":0,
    "gn:timezone":"Asia/Kolkata",
    "iso:country":"IN",
    "name:ben_x_preferred":[
        "\u09b2\u09be\u09a6\u09c1\u0993\u09af\u09bc\u09be"
    ],
    "name:bpy_x_preferred":[
        "\u09b2\u09be\u09a6\u09c1\u09f1\u09be"
    ],
    "name:ceb_x_preferred":[
        "L\u0101dwa"
    ],
    "name:hin_x_preferred":[
        "\u0932\u093e\u0921\u0935\u093e"
    ],
    "name:ita_x_preferred":[
        "Ladwa"
    ],
    "name:msa_x_preferred":[
        "Ladwa"
    ],
    "name:new_x_preferred":[
        "\u0932\u0926\u094d\u0935\u093e"
    ],
    "name:nld_x_preferred":[
        "Ladwa"
    ],
    "name:ori_x_preferred":[
        "\u0b32\u0b3e\u0b26\u0b4d\u0b71\u0b3e"
    ],
    "name:por_x_preferred":[
        "Ladwa"
    ],
    "name:spa_x_preferred":[
        "Ladwa"
    ],
    "name:swe_x_preferred":[
        "L\u0101dwa"
    ],
    "name:urd_x_preferred":[
        "\u0644\u0627\u0688\u0648\u0627"
    ],
    "name:vie_x_preferred":[
        "Ladwa"
    ],
    "name:zho_x_preferred":[
        "\u62c9\u5fb7\u74e6"
    ],
    "wof:name":"Ladwa",
    "wof:placetype":"locality"
},
  "geometry": {"coordinates":[77.63096,30.06213],"type":"Point"}
}