{
  "type": "Feature",
  "properties": {
    "iso:country":"IN",
    "ks:ks_name":"Rikhai Tola",
    "ks:ks_pop":964,
    "ks:ks_type":"VILLAGE",
    "name:eng_x_preferred":[
        "Rikhai Tola"
    ],
    "wof:name":"Rikhai Tola",
    "wof:placetype":"locality",
    "wof:population":964
},
  "geometry": {"coordinates":[84.40075899999999,26.425918],"type":"Point"}
}