{
  "type": "Feature",
  "properties": {
    "iso:country":"IN",
    "ks:ks_name":"Dhakhinwari Tola",
    "ks:ks_pop":266,
    "ks:ks_type":"HABITATION",
    "name:eng_x_preferred":[
        "Dhakhinwari Tola"
    ],
    "wof:name":"Dhakhinwari Tola",
    "wof:placetype":"locality",
    "wof:population":266
},
  "geometry": {"coordinates":[84.581092,26.9885],"type":"Point"}
}