{
  "type": "Feature",
  "properties": {
    "gn:admin1_code":"35.0",
    "gn:admin2_code":"441.0",
    "gn:asciiname":"Jhagarkheda",
    "gn:country_code":"IN",
    "gn:dem":384,
    "gn:feature_class":"P",
    "gn:feature_code":"PPL",
    "gn:name":"Jh\u0101garkheda",
    "gn:population":0,
    "gn:timezone":"Asia/Kolkata",
    "iso:country":"IN",
    "ks:ks_name":"Ghaghar Kheda",
    "ks:ks_pop":917,
    "ks:ks_type":"VILLAGE",
    "name:eng_x_preferred":[
        "Ghaghar Kheda"
    ],
    "name:eng_x_variant":[
        "Jhagarkheda"
    ],
    "wof:name":"Ghaghar Kheda",
    "wof:placetype":"locality",
    "wof:population":917
},
  "geometry": {"coordinates":[75.04444700000001,21.809296],"type":"Point"}
}