{
  "type": "Feature",
  "properties": {
    "iso:country":"IN",
    "ks:ks_alt_nam":"Koma  longjon",
    "ks:ks_name":"Koma Longjon",
    "ks:ks_pop":148,
    "ks:ks_type":"HABITATION",
    "name:eng_x_preferred":[
        "Koma Longjon"
    ],
    "name:eng_x_variant":[
        "Koma  longjon"
    ],
    "wof:name":"Koma Longjon",
    "wof:placetype":"locality",
    "wof:population":148
},
  "geometry": {"coordinates":[92.558206,25.641102],"type":"Point"}
}