{
  "type": "Feature",
  "properties": {
    "iso:country":"IN",
    "ks:ks_name":"Pankhad",
    "ks:ks_pop":154,
    "ks:ks_type":"HABITATION",
    "name:eng_x_preferred":[
        "Pankhad"
    ],
    "wof:name":"Pankhad",
    "wof:placetype":"locality",
    "wof:population":154
},
  "geometry": {"coordinates":[73.503972,22.152417],"type":"Point"}
}