{
  "type": "Feature",
  "properties": {
    "iso:country":"IN",
    "ks:ks_name":"Nangaguda",
    "ks:ks_pop":26,
    "ks:ks_type":"HABITATION",
    "name:eng_x_preferred":[
        "Nangaguda"
    ],
    "wof:name":"Nangaguda",
    "wof:placetype":"locality",
    "wof:population":26
},
  "geometry": {"coordinates":[82.380134,19.644193],"type":"Point"}
}