{
  "type": "Feature",
  "properties": {
    "iso:country":"IN",
    "ks:ks_name":"Mathapari",
    "ks:ks_pop":6689,
    "ks:ks_type":"URBAN",
    "name:eng_x_preferred":[
        "Mathapari"
    ],
    "wof:name":"Mathapari",
    "wof:placetype":"neighbourhood",
    "wof:population":6689
},
  "geometry": {"coordinates":[88.38529699999999,26.713628],"type":"Point"}
}