{
  "type": "Feature",
  "properties": {
    "iso:country":"IN",
    "ks:ks_name":"Bhimgali",
    "ks:ks_pop":41,
    "ks:ks_type":"HABITATION",
    "name:eng_x_preferred":[
        "Bhimgali"
    ],
    "wof:name":"Bhimgali",
    "wof:placetype":"locality",
    "wof:population":41
},
  "geometry": {"coordinates":[74.430668,15.073544],"type":"Point"}
}