{
  "type": "Feature",
  "properties": {
    "iso:country":"IN",
    "ks:ks_name":"Ramachandrapur",
    "ks:ks_pop":316,
    "ks:ks_type":"VILLAGE",
    "name:eng_x_preferred":[
        "Ramachandrapur"
    ],
    "wof:name":"Ramachandrapur",
    "wof:placetype":"locality",
    "wof:population":316
},
  "geometry": {"coordinates":[84.33344099999999,19.424111],"type":"Point"}
}