{
  "type": "Feature",
  "properties": {
    "iso:country":"IN",
    "ks:ks_name":"Siyangkel",
    "ks:ks_pop":126,
    "ks:ks_type":"VILLAGE",
    "name:eng_x_preferred":[
        "Siyangkel"
    ],
    "wof:name":"Siyangkel",
    "wof:placetype":"locality",
    "wof:population":126
},
  "geometry": {"coordinates":[85.286821,22.74154],"type":"Point"}
}