{
  "type": "Feature",
  "properties": {
    "iso:country":"IN",
    "ks:ks_name":"Charan Singh Para",
    "ks:ks_pop":332,
    "ks:ks_type":"HABITATION",
    "name:eng_x_preferred":[
        "Charan Singh Para"
    ],
    "wof:name":"Charan Singh Para",
    "wof:placetype":"locality",
    "wof:population":332
},
  "geometry": {"coordinates":[91.545124,23.212136],"type":"Point"}
}