{
  "type": "Feature",
  "properties": {
    "gn:admin1_code":"36.0",
    "gn:admin2_code":"151.0",
    "gn:asciiname":"Bhagautipur Kasba",
    "gn:country_code":"IN",
    "gn:dem":187,
    "gn:feature_class":"P",
    "gn:feature_code":"PPL",
    "gn:name":"Bhagaut\u012bpur Kasba",
    "gn:population":0,
    "gn:timezone":"Asia/Kolkata",
    "iso:country":"IN",
    "wof:name":"Bhagautipur Kasba",
    "wof:placetype":"locality"
},
  "geometry": {"coordinates":[79.69882,28.66621],"type":"Point"}
}