{
  "type": "Feature",
  "properties": {
    "gn:admin1_code":"36.0",
    "gn:admin2_code":"151.0",
    "gn:asciiname":"Bhagautipur Kasba",
    "gn:country_code":"IN",
    "gn:dem":187,
    "gn:feature_class":"P",
    "gn:feature_code":"PPL",
    "gn:name":"Bhagaut\u012bpur Kasba",
    "gn:population":0,
    "gn:timezone":"Asia/Kolkata",
    "iso:country":"IN",
    "ks:ks_alt_nam":"Bhagaut\u012bpur Kasba",
    "ks:ks_name":"Bhagautipur Kasba",
    "ks:ks_type":"VILLAGE",
    "name:eng_x_preferred":[
        "Bhagautipur Kasba"
    ],
    "name:eng_x_variant":[
        "Bhagaut\u012bpur Kasba"
    ],
    "wof:name":"Bhagautipur Kasba",
    "wof:placetype":"locality"
},
  "geometry": {"coordinates":[79.698823,28.666212],"type":"Point"}
}