{
  "type": "Feature",
  "properties": {
    "gn:admin1_code":"39",
    "gn:admin2_code":"61.0",
    "gn:asciiname":"Kimgaon",
    "gn:country_code":"IN",
    "gn:dem":1510,
    "gn:feature_class":"P",
    "gn:feature_code":"PPL",
    "gn:name":"Kimgaon",
    "gn:population":0,
    "gn:timezone":"Asia/Kolkata",
    "iso:country":"IN",
    "ks:ks_name":"Kim Gaon",
    "ks:ks_pop":128,
    "ks:ks_type":"VILLAGE",
    "name:eng_x_preferred":[
        "Kim Gaon"
    ],
    "name:eng_x_variant":[
        "Kimgaon"
    ],
    "wof:name":"Kim Gaon",
    "wof:placetype":"locality",
    "wof:population":128
},
  "geometry": {"coordinates":[78.901837,29.77205],"type":"Point"}
}