{
  "type": "Feature",
  "properties": {
    "iso:country":"IN",
    "ks:ks_alt_nam":"Pohuchungi deoghoria",
    "ks:ks_name":"Pohuchungi Deoghoria",
    "ks:ks_pop":470,
    "ks:ks_type":"HABITATION",
    "name:eng_x_preferred":[
        "Pohuchungi Deoghoria"
    ],
    "wof:name":"Pohuchungi Deoghoria",
    "wof:placetype":"locality",
    "wof:population":470
},
  "geometry": {"coordinates":[95.026461,27.098314],"type":"Point"}
}