{
  "type": "Feature",
  "properties": {
    "iso:country":"IN",
    "ks:ks_name":"Dhit Gerya",
    "ks:ks_pop":351,
    "ks:ks_type":"VILLAGE",
    "name:eng_x_preferred":[
        "Dhit Gerya"
    ],
    "wof:name":"Dhit Gerya",
    "wof:placetype":"locality",
    "wof:population":351
},
  "geometry": {"coordinates":[87.553624,22.436834],"type":"Point"}
}