{
  "type": "Feature",
  "properties": {
    "gn:admin1_code":"39.0",
    "gn:admin2_code":"66.0",
    "gn:asciiname":"Pajena",
    "gn:country_code":"IN",
    "gn:dem":1707,
    "gn:feature_class":"P",
    "gn:feature_code":"PPL",
    "gn:name":"Pajena",
    "gn:population":0,
    "gn:timezone":"Asia/Kolkata",
    "iso:country":"IN",
    "ks:ks_name":"Pajena",
    "ks:ks_pop":272,
    "ks:ks_type":"VILLAGE",
    "name:eng_x_preferred":[
        "Pajena"
    ],
    "wof:name":"Pajena",
    "wof:placetype":"locality",
    "wof:population":272
},
  "geometry": {"coordinates":[79.86326,29.363139],"type":"Point"}
}