{
  "type": "Feature",
  "properties": {
    "gn:admin1_code":"25.0",
    "gn:admin2_code":"619.0",
    "gn:asciiname":"Malavachcheri",
    "gn:country_code":"IN",
    "gn:dem":21,
    "gn:feature_class":"P",
    "gn:feature_code":"PPL",
    "gn:name":"Malavachcheri",
    "gn:population":0,
    "gn:timezone":"Asia/Kolkata",
    "iso:country":"IN",
    "wof:name":"Malavachcheri",
    "wof:placetype":"locality"
},
  "geometry": {"coordinates":[79.49554000000001,10.84899],"type":"Point"}
}