{
  "type": "Feature",
  "properties": {
    "gn:admin1_code":"25.0",
    "gn:admin2_code":"619.0",
    "gn:asciiname":"Malavachcheri",
    "gn:country_code":"IN",
    "gn:dem":21,
    "gn:feature_class":"P",
    "gn:feature_code":"PPL",
    "gn:name":"Malavachcheri",
    "gn:population":0,
    "gn:timezone":"Asia/Kolkata",
    "iso:country":"IN",
    "ks:ks_name":"Malavacheri",
    "ks:ks_pop":150,
    "ks:ks_type":"HABITATION",
    "name:eng_x_preferred":[
        "Malavacheri"
    ],
    "name:eng_x_variant":[
        "Malavachcheri"
    ],
    "wof:name":"Malavacheri",
    "wof:placetype":"locality",
    "wof:population":150
},
  "geometry": {"coordinates":[79.497085,10.846928],"type":"Point"}
}