{
  "type": "Feature",
  "properties": {
    "gn:admin1_code":"24.0",
    "gn:admin2_code":"110",
    "gn:asciiname":"Bhudarpura",
    "gn:country_code":"IN",
    "gn:dem":432,
    "gn:feature_class":"P",
    "gn:feature_code":"PPL",
    "gn:name":"Bh\u016bdarpura",
    "gn:population":0,
    "gn:timezone":"Asia/Kolkata",
    "iso:country":"IN",
    "ks:ks_name":"Bhoodarpura",
    "ks:ks_pop":666,
    "ks:ks_type":"HABITATION",
    "name:eng_x_preferred":[
        "Bhoodarpura"
    ],
    "name:eng_x_variant":[
        "Bhudarpura"
    ],
    "wof:name":"Bhoodarpura",
    "wof:placetype":"locality",
    "wof:population":666
},
  "geometry": {"coordinates":[75.670261,26.989406],"type":"Point"}
}