{
  "type": "Feature",
  "properties": {
    "gn:admin1_code":"24.0",
    "gn:admin2_code":"102",
    "gn:asciiname":"Loha",
    "gn:country_code":"IN",
    "gn:dem":313,
    "gn:feature_class":"P",
    "gn:feature_code":"PPL",
    "gn:name":"Loha",
    "gn:population":0,
    "gn:timezone":"Asia/Kolkata",
    "iso:country":"IN",
    "name:ceb_x_preferred":[
        "Loha"
    ],
    "name:swe_x_preferred":[
        "Loha"
    ],
    "name:und_x_variant":[
        "Loa"
    ],
    "wof:name":"Loha",
    "wof:placetype":"locality"
},
  "geometry": {"coordinates":[74.61247,28.00391],"type":"Point"}
}