{
  "type": "Feature",
  "properties": {
    "gn:admin1_code":"36",
    "gn:admin2_code":"185.0",
    "gn:asciiname":"Bhitia Khurd",
    "gn:country_code":"IN",
    "gn:dem":95,
    "gn:feature_class":"P",
    "gn:feature_code":"PPL",
    "gn:name":"Bhitia Khurd",
    "gn:population":0,
    "gn:timezone":"Asia/Kolkata",
    "iso:country":"IN",
    "ks:ks_name":"Bhiriya Khurd",
    "ks:ks_pop":25,
    "ks:ks_type":"VILLAGE",
    "name:eng_x_preferred":[
        "Bhiriya Khurd"
    ],
    "name:eng_x_variant":[
        "Bhitia Khurd"
    ],
    "wof:name":"Bhiriya Khurd",
    "wof:placetype":"locality",
    "wof:population":25
},
  "geometry": {"coordinates":[82.732457,26.855896],"type":"Point"}
}