{
  "type": "Feature",
  "properties": {
    "iso:country":"IN",
    "ks:ks_name":"Tadpara",
    "ks:ks_pop":414,
    "ks:ks_type":"HABITATION",
    "name:eng_x_preferred":[
        "Tadpara"
    ],
    "wof:name":"Tadpara",
    "wof:placetype":"locality",
    "wof:population":414
},
  "geometry": {"coordinates":[81.64437599999999,18.652284],"type":"Point"}
}