{
  "type": "Feature",
  "properties": {
    "gn:admin1_code":"39.0",
    "gn:admin2_code":"63.0",
    "gn:asciiname":"Katarmal",
    "gn:country_code":"IN",
    "gn:dem":1529,
    "gn:feature_class":"P",
    "gn:feature_code":"PPL",
    "gn:name":"Kat\u0101rmal",
    "gn:population":0,
    "gn:timezone":"Asia/Kolkata",
    "iso:country":"IN",
    "ks:ks_name":"Katarmal",
    "ks:ks_pop":280,
    "ks:ks_type":"VILLAGE",
    "name:eng_x_preferred":[
        "Katarmal"
    ],
    "wof:name":"Katarmal",
    "wof:placetype":"locality",
    "wof:population":280
},
  "geometry": {"coordinates":[79.63001199999999,29.869778],"type":"Point"}
}