{
  "type": "Feature",
  "properties": {
    "iso:country":"IN",
    "ks:ks_name":"Mettupalayam",
    "ks:ks_pop":365,
    "ks:ks_type":"HABITATION",
    "name:eng_x_preferred":[
        "Mettupalayam"
    ],
    "name:hin_x_preferred":[
        "\u092e\u0947\u091f\u094d\u091f\u0941\u092a\u0932\u092f\u092e"
    ],
    "name:tam_x_preferred":[
        "\u0bae\u0bc7\u0b9f\u0bcd\u0b9f\u0bc1\u0baa\u0bcd\u0baa\u0bbe\u0bb3\u0bc8\u0baf\u0bae\u0bcd"
    ],
    "wof:name":"Mettupalayam",
    "wof:placetype":"locality",
    "wof:population":365
},
  "geometry": {"coordinates":[77.743067,11.546357],"type":"Point"}
}