{
  "type": "Feature",
  "properties": {
    "iso:country":"IN",
    "ks:ks_name":"Mettupalayam",
    "ks:ks_pop":365,
    "ks:ks_type":"HABITATION",
    "name:eng_x_preferred":[
        "Mettupalayam"
    ],
    "wof:name":"Mettupalayam",
    "wof:placetype":"locality",
    "wof:population":365
},
  "geometry": {"coordinates":[77.743067,11.546357],"type":"Point"}
}