{
  "type": "Feature",
  "properties": {
    "gn:admin1_code":"34.0",
    "gn:admin2_code":"217.0",
    "gn:asciiname":"Munja",
    "gn:country_code":"IN",
    "gn:dem":65,
    "gn:feature_class":"P",
    "gn:feature_code":"PPL",
    "gn:name":"Munja",
    "gn:population":0,
    "gn:timezone":"Asia/Kolkata",
    "iso:country":"IN",
    "ks:ks_name":"Munja",
    "ks:ks_pop":1302,
    "ks:ks_type":"VILLAGE",
    "name:eng_x_preferred":[
        "Munja"
    ],
    "wof:name":"Munja",
    "wof:placetype":"locality",
    "wof:population":1302
},
  "geometry": {"coordinates":[84.841793,26.230416],"type":"Point"}
}