{
  "type": "Feature",
  "properties": {
    "gn:admin1_code":"34.0",
    "gn:admin2_code":"219.0",
    "gn:asciiname":"Lala",
    "gn:country_code":"IN",
    "gn:dem":61,
    "gn:feature_class":"P",
    "gn:feature_code":"PPL",
    "gn:name":"Lala",
    "gn:population":0,
    "gn:timezone":"Asia/Kolkata",
    "iso:country":"IN",
    "name:bak_x_preferred":[
        "\u041b\u04d9\u043b\u04d9"
    ],
    "name:ceb_x_preferred":[
        "Lala"
    ],
    "name:deu_x_preferred":[
        "Lala"
    ],
    "name:fra_x_preferred":[
        "Lala"
    ],
    "name:ind_x_preferred":[
        "Lala"
    ],
    "name:ita_x_preferred":[
        "Lala"
    ],
    "name:nld_x_preferred":[
        "Lala"
    ],
    "name:rus_x_preferred":[
        "\u041b\u044f\u043b\u044f"
    ],
    "name:spa_x_preferred":[
        "Lala"
    ],
    "name:swe_x_preferred":[
        "Lala"
    ],
    "wof:name":"Lala",
    "wof:placetype":"locality"
},
  "geometry": {"coordinates":[84.92357,26.08884],"type":"Point"}
}