{
  "type": "Feature",
  "properties": {
    "gn:admin1_code":"39",
    "gn:admin2_code":"60.0",
    "gn:asciiname":"Chilar",
    "gn:country_code":"IN",
    "gn:dem":1545,
    "gn:feature_class":"P",
    "gn:feature_code":"PPL",
    "gn:name":"Chil\u0101r",
    "gn:population":0,
    "gn:timezone":"Asia/Kolkata",
    "iso:country":"IN",
    "wof:name":"Chilar",
    "wof:placetype":"neighbourhood"
},
  "geometry": {"coordinates":[77.83280999999999,30.85893],"type":"Point"}
}