{
  "type": "Feature",
  "properties": {
    "iso:country":"IN",
    "ks:ks_name":"Morewadi",
    "ks:ks_pop":45,
    "ks:ks_type":"HABITATION",
    "name:eng_x_preferred":[
        "Morewadi"
    ],
    "wof:name":"Morewadi",
    "wof:placetype":"locality",
    "wof:population":45
},
  "geometry": {"coordinates":[73.437967,17.225467],"type":"Point"}
}