{
  "type": "Feature",
  "properties": {
    "gn:admin1_code":"19.0",
    "gn:admin2_code":"568.0",
    "gn:asciiname":"Majivana",
    "gn:country_code":"IN",
    "gn:dem":605,
    "gn:feature_class":"P",
    "gn:feature_code":"PPL",
    "gn:name":"Majivana",
    "gn:population":0,
    "gn:timezone":"Asia/Kolkata",
    "iso:country":"IN",
    "ks:ks_name":"Majavana",
    "ks:ks_pop":72,
    "ks:ks_type":"VILLAGE",
    "name:eng_x_preferred":[
        "Majavana"
    ],
    "name:eng_x_variant":[
        "Majivana"
    ],
    "wof:name":"Majavana",
    "wof:placetype":"locality",
    "wof:population":72
},
  "geometry": {"coordinates":[75.151195,13.988149],"type":"Point"}
}