{
  "type": "Feature",
  "properties": {
    "gn:admin1_code":"16",
    "gn:admin2_code":"504.0",
    "gn:asciiname":"Umri",
    "gn:country_code":"IN",
    "gn:dem":240,
    "gn:feature_class":"P",
    "gn:feature_code":"PPL",
    "gn:name":"Umr\u012b",
    "gn:population":0,
    "gn:timezone":"Asia/Kolkata",
    "iso:country":"IN",
    "name:ceb_x_preferred":[
        "Umri"
    ],
    "name:pol_x_preferred":[
        "Umri"
    ],
    "name:swe_x_preferred":[
        "Umri"
    ],
    "wof:name":"Umri",
    "wof:placetype":"locality"
},
  "geometry": {"coordinates":[79.0787,20.528],"type":"Point"}
}