{
  "type": "Feature",
  "properties": {
    "gn:admin1_code":"24.0",
    "gn:admin2_code":"130.0",
    "gn:asciiname":"Makri",
    "gn:country_code":"IN",
    "gn:dem":561,
    "gn:feature_class":"P",
    "gn:feature_code":"PPL",
    "gn:name":"Makri",
    "gn:population":0,
    "gn:timezone":"Asia/Kolkata",
    "iso:country":"IN",
    "ks:ks_name":"Makri",
    "ks:ks_pop":508,
    "ks:ks_type":"VILLAGE",
    "name:eng_x_preferred":[
        "Makri"
    ],
    "name:fra_x_preferred":[
        "Makri"
    ],
    "wof:name":"Makri",
    "wof:placetype":"locality",
    "wof:population":508
},
  "geometry": {"coordinates":[73.463722,24.190153],"type":"Point"}
}