{
  "type": "Feature",
  "properties": {
    "iso:country":"IN",
    "ks:ks_name":"Deypursasan",
    "ks:ks_pop":663,
    "ks:ks_type":"VILLAGE",
    "name:eng_x_preferred":[
        "Deypursasan"
    ],
    "wof:name":"Deypursasan",
    "wof:placetype":"locality",
    "wof:population":663
},
  "geometry": {"coordinates":[85.790199,19.985456],"type":"Point"}
}