{
  "type": "Feature",
  "properties": {
    "iso:country":"IN",
    "ks:ks_name":"Bichkoria",
    "ks:ks_pop":428,
    "ks:ks_type":"VILLAGE",
    "name:eng_x_preferred":[
        "Bichkoria"
    ],
    "wof:name":"Bichkoria",
    "wof:placetype":"locality",
    "wof:population":428
},
  "geometry": {"coordinates":[86.94091,24.144398],"type":"Point"}
}