{
  "type": "Feature",
  "properties": {
    "iso:country":"IN",
    "ks:ks_name":"Hebre",
    "ks:ks_pop":85,
    "ks:ks_type":"HABITATION",
    "name:eng_x_preferred":[
        "Hebre"
    ],
    "wof:name":"Hebre",
    "wof:placetype":"locality",
    "wof:population":85
},
  "geometry": {"coordinates":[74.589241,14.489993],"type":"Point"}
}