{
  "type": "Feature",
  "properties": {
    "iso:country":"IN",
    "ks:ks_name":"Vedullapalli",
    "ks:ks_pop":43,
    "ks:ks_type":"HABITATION",
    "name:eng_x_preferred":[
        "Vedullapalli"
    ],
    "wof:name":"Vedullapalli",
    "wof:placetype":"locality",
    "wof:population":43
},
  "geometry": {"coordinates":[81.881355,17.594907],"type":"Point"}
}