{
  "type": "Feature",
  "properties": {
    "iso:country":"IN",
    "ks:ks_alt_nam":"Guna kyark",
    "ks:ks_name":"Guna Kyark",
    "ks:ks_pop":52,
    "ks:ks_type":"HABITATION",
    "name:eng_x_preferred":[
        "Guna Kyark"
    ],
    "wof:name":"Guna Kyark",
    "wof:placetype":"locality",
    "wof:population":52
},
  "geometry": {"coordinates":[79.068563,30.420528],"type":"Point"}
}