{
  "type": "Feature",
  "properties": {
    "iso:country":"IN",
    "ks:ks_name":"Kakadpada",
    "ks:ks_pop":800,
    "ks:ks_type":"HABITATION",
    "name:eng_x_preferred":[
        "Kakadpada"
    ],
    "wof:name":"Kakadpada",
    "wof:placetype":"locality",
    "wof:population":800
},
  "geometry": {"coordinates":[72.947596,20.135276],"type":"Point"}
}