{
  "type": "Feature",
  "properties": {
    "gn:admin1_code":"37",
    "gn:admin2_code":"414.0",
    "gn:asciiname":"Bhataguda",
    "gn:country_code":"IN",
    "gn:dem":556,
    "gn:feature_class":"P",
    "gn:feature_code":"PPL",
    "gn:name":"Bhataguda",
    "gn:population":0,
    "gn:timezone":"Asia/Kolkata",
    "iso:country":"IN",
    "wof:name":"Bhataguda",
    "wof:placetype":"locality"
},
  "geometry": {"coordinates":[82.06197,19.11134],"type":"Point"}
}