{
  "type": "Feature",
  "properties": {
    "iso:country":"IN",
    "ks:ks_name":"Geddehundi",
    "ks:ks_pop":95,
    "ks:ks_type":"HABITATION",
    "name:eng_x_preferred":[
        "Geddehundi"
    ],
    "wof:name":"Geddehundi",
    "wof:placetype":"locality",
    "wof:population":95
},
  "geometry": {"coordinates":[76.99574200000001,12.203655],"type":"Point"}
}