{
  "type": "Feature",
  "properties": {
    "iso:country":"IN",
    "ks:ks_name":"No 3 G B Para",
    "ks:ks_pop":1740,
    "ks:ks_type":"HABITATION",
    "name:eng_x_preferred":[
        "No 3 G B Para"
    ],
    "wof:name":"No 3 G B Para",
    "wof:placetype":"locality",
    "wof:population":1740
},
  "geometry": {"coordinates":[88.656374,22.156742],"type":"Point"}
}