{
  "type": "Feature",
  "properties": {
    "gn:admin1_code":"21",
    "gn:admin2_code":"398.0",
    "gn:asciiname":"Isariguda",
    "gn:country_code":"IN",
    "gn:dem":627,
    "gn:feature_class":"P",
    "gn:feature_code":"PPL",
    "gn:name":"Is\u0101rig\u016bda",
    "gn:population":0,
    "gn:timezone":"Asia/Kolkata",
    "iso:country":"IN",
    "wof:name":"Isariguda",
    "wof:placetype":"neighbourhood"
},
  "geometry": {"coordinates":[82.21248,18.71345],"type":"Point"}
}