{
  "type": "Feature",
  "properties": {
    "iso:country":"IN",
    "ks:ks_name":"Khamrua",
    "ks:ks_pop":612,
    "ks:ks_type":"VILLAGE",
    "name:eng_x_preferred":[
        "Khamrua"
    ],
    "wof:name":"Khamrua",
    "wof:placetype":"locality",
    "wof:population":612
},
  "geometry": {"coordinates":[88.152086,25.453388],"type":"Point"}
}