{
  "type": "Feature",
  "properties": {
    "iso:country":"IN",
    "ks:ks_name":"Khalisamari",
    "ks:ks_pop":503,
    "ks:ks_type":"HABITATION",
    "name:eng_x_preferred":[
        "Khalisamari"
    ],
    "wof:name":"Khalisamari",
    "wof:placetype":"locality",
    "wof:population":503
},
  "geometry": {"coordinates":[90.60705900000001,26.063007],"type":"Point"}
}