{
  "type": "Feature",
  "properties": {
    "iso:country":"IN",
    "ks:ks_alt_nam":"BEHDA FV",
    "ks:ks_name":"Behda Fv",
    "ks:ks_pop":618,
    "ks:ks_type":"HABITATION",
    "name:eng_x_preferred":[
        "Behda Fv"
    ],
    "wof:name":"Behda Fv",
    "wof:placetype":"locality",
    "wof:population":618
},
  "geometry": {"coordinates":[77.159671,21.721838],"type":"Point"}
}