{
  "type": "Feature",
  "properties": {
    "iso:country":"IN",
    "ks:ks_name":"Kundaint Gaon",
    "ks:ks_pop":2553,
    "ks:ks_type":"VILLAGE",
    "name:eng_x_preferred":[
        "Kundaint Gaon"
    ],
    "wof:name":"Kundaint Gaon",
    "wof:placetype":"locality",
    "wof:population":2553
},
  "geometry": {"coordinates":[80.76733,26.785747],"type":"Point"}
}