{
  "type": "Feature",
  "properties": {
    "iso:country":"IN",
    "ks:ks_name":"Dhanagarwada",
    "ks:ks_pop":58,
    "ks:ks_type":"HABITATION",
    "name:eng_x_preferred":[
        "Dhanagarwada"
    ],
    "wof:name":"Dhanagarwada",
    "wof:placetype":"locality",
    "wof:population":58
},
  "geometry": {"coordinates":[73.944092,16.167511],"type":"Point"}
}