{
  "type": "Feature",
  "properties": {
    "iso:country":"IN",
    "ks:ks_name":"Nailgaveli",
    "ks:ks_pop":227,
    "ks:ks_type":"VILLAGE",
    "ks:ks_uagg_main":0,
    "name:eng_x_preferred":[
        "Nailgaveli"
    ],
    "wof:name":"Nailgaveli",
    "wof:placetype":"neighbourhood",
    "wof:population":227
},
  "geometry": {"coordinates":[78.742142,30.383364],"type":"Point"}
}