{
  "type": "Feature",
  "properties": {
    "iso:country":"IN",
    "ks:ks_name":"Kherbari",
    "ks:ks_pop":453,
    "ks:ks_type":"HABITATION",
    "name:eng_x_preferred":[
        "Kherbari"
    ],
    "wof:name":"Kherbari",
    "wof:placetype":"locality",
    "wof:population":453
},
  "geometry": {"coordinates":[93.56234000000001,25.753835],"type":"Point"}
}