{
  "type": "Feature",
  "properties": {
    "iso:country":"IN",
    "ks:ks_name":"Nahisodobra",
    "ks:ks_pop":581,
    "ks:ks_type":"HABITATION",
    "name:eng_x_preferred":[
        "Nahisodobra"
    ],
    "wof:name":"Nahisodobra",
    "wof:placetype":"locality",
    "wof:population":581
},
  "geometry": {"coordinates":[87.000276,23.105805],"type":"Point"}
}