{
  "type": "Feature",
  "properties": {
    "iso:country":"IN",
    "ks:ks_name":"Somsa Wadi",
    "ks:ks_pop":385,
    "ks:ks_type":"HABITATION",
    "name:eng_x_preferred":[
        "Somsa Wadi"
    ],
    "wof:name":"Somsa Wadi",
    "wof:placetype":"locality",
    "wof:population":385
},
  "geometry": {"coordinates":[77.828919,19.313223],"type":"Point"}
}