{
  "type": "Feature",
  "properties": {
    "iso:country":"IN",
    "ks:ks_name":"Thiruvaki",
    "ks:ks_pop":68,
    "ks:ks_type":"HABITATION",
    "name:eng_x_preferred":[
        "Thiruvaki"
    ],
    "wof:name":"Thiruvaki",
    "wof:placetype":"locality",
    "wof:population":68
},
  "geometry": {"coordinates":[78.54487,9.381682],"type":"Point"}
}