{
  "type": "Feature",
  "properties": {
    "gn:admin1_code":"34.0",
    "gn:admin2_code":"234.0",
    "gn:asciiname":"Dehra",
    "gn:country_code":"IN",
    "gn:dem":89,
    "gn:feature_class":"P",
    "gn:feature_code":"PPL",
    "gn:name":"Dehra",
    "gn:population":0,
    "gn:timezone":"Asia/Kolkata",
    "iso:country":"IN",
    "name:ara_x_preferred":[
        "\u062f\u064a\u0647\u0631\u0627"
    ],
    "name:ben_bn_x_preferred":[
        "\u09a6\u09c7\u09b9\u09b0\u09be"
    ],
    "name:ben_in_x_preferred":[
        "\u09a6\u09c7\u09b9\u09b0\u09be"
    ],
    "name:guj_x_preferred":[
        "\u0aa6\u0ac7\u0ab9\u0ab0\u0abe"
    ],
    "name:hin_x_preferred":[
        "\u0926\u0947\u0939\u0930\u093e"
    ],
    "name:kan_x_preferred":[
        "\u0ca6\u0cc7\u0cb9\u0ccd\u0cb0\u0cbe"
    ],
    "name:mal_x_preferred":[
        "\u0d21\u0d46\u0d31\u0d3e"
    ],
    "name:mar_x_preferred":[
        "\u0921\u0947\u0939\u0930\u093e"
    ],
    "name:pan_x_preferred":[
        "\u0a26\u0a47\u0a39\u0a30\u0a3e"
    ],
    "name:tam_x_preferred":[
        "\u0b9f\u0bc6\u0bb9\u0bcd\u0bb0\u0bbe"
    ],
    "name:tel_x_preferred":[
        "\u0c21\u0c46\u0c39\u0c4d\u0c30\u0c3e"
    ],
    "name:urd_x_preferred":[
        "\u0688\u06cc\u06c1\u0631\u0627"
    ],
    "wof:name":"Dehra",
    "wof:placetype":"locality"
},
  "geometry": {"coordinates":[84.31639,25.28089],"type":"Point"}
}