{
  "type": "Feature",
  "properties": {
    "gn:admin1_code":"39.0",
    "gn:admin2_code":"64.0",
    "gn:asciiname":"Jaune",
    "gn:country_code":"IN",
    "gn:dem":1079,
    "gn:feature_class":"P",
    "gn:feature_code":"PPL",
    "gn:name":"Jaune",
    "gn:population":0,
    "gn:timezone":"Asia/Kolkata",
    "iso:country":"IN",
    "name:deu_x_preferred":[
        "Jaune"
    ],
    "name:fra_x_preferred":[
        "Jaune"
    ],
    "wof:name":"Jaune",
    "wof:placetype":"locality"
},
  "geometry": {"coordinates":[79.36879999999999,29.65763],"type":"Point"}
}