{
  "type": "Feature",
  "properties": {
    "iso:country":"IN",
    "ks:ks_name":"Manpura",
    "ks:ks_pop":425,
    "ks:ks_type":"VILLAGE",
    "name:eng_x_preferred":[
        "Manpura"
    ],
    "wof:name":"Manpura",
    "wof:placetype":"locality",
    "wof:population":425
},
  "geometry": {"coordinates":[76.868008,24.231874],"type":"Point"}
}