{
  "type": "Feature",
  "properties": {
    "gn:admin1_code":"23.0",
    "gn:admin2_code":"47.0",
    "gn:asciiname":"Malkon",
    "gn:country_code":"IN",
    "gn:dem":220,
    "gn:feature_class":"P",
    "gn:feature_code":"PPL",
    "gn:name":"Malkon",
    "gn:population":0,
    "gn:timezone":"Asia/Kolkata",
    "iso:country":"IN",
    "wof:name":"Malkon",
    "wof:placetype":"locality"
},
  "geometry": {"coordinates":[75.44566999999998,29.80836],"type":"Point"}
}