{
  "type": "Feature",
  "properties": {
    "iso:country":"IN",
    "ks:ks_name":"Kherra",
    "ks:ks_pop":537,
    "ks:ks_type":"HABITATION",
    "name:eng_x_preferred":[
        "Kherra"
    ],
    "wof:name":"Kherra",
    "wof:placetype":"locality",
    "wof:population":537
},
  "geometry": {"coordinates":[77.71977800000001,26.920365],"type":"Point"}
}