{
  "type": "Feature",
  "properties": {
    "iso:country":"IN",
    "ks:ks_alt_nam":"MAHUWAPATH",
    "ks:ks_name":"Mahuwapath",
    "ks:ks_pop":138,
    "ks:ks_type":"HABITATION",
    "name:eng_x_preferred":[
        "Mahuwapath"
    ],
    "wof:name":"Mahuwapath",
    "wof:placetype":"locality",
    "wof:population":138
},
  "geometry": {"coordinates":[83.619502,23.118561],"type":"Point"}
}