{
  "type": "Feature",
  "properties": {
    "gn:admin1_code":"17",
    "gn:admin2_code":"273.0",
    "gn:asciiname":"Pabram",
    "gn:country_code":"IN",
    "gn:dem":816,
    "gn:feature_class":"P",
    "gn:feature_code":"PPL",
    "gn:name":"Pabram",
    "gn:population":0,
    "gn:timezone":"Asia/Kolkata",
    "iso:country":"IN",
    "wof:name":"Pabram",
    "wof:placetype":"locality"
},
  "geometry": {"coordinates":[93.36642999999999,24.9498],"type":"Point"}
}