{
  "type": "Feature",
  "properties": {
    "iso:country":"IN",
    "ks:ks_alt_nam":"ahiranpurwa1",
    "ks:ks_name":"Ahiranpurwa1",
    "ks:ks_pop":71,
    "ks:ks_type":"HABITATION",
    "ks:ks_uagg_main":0,
    "name:eng_x_preferred":[
        "Ahiranpurwa1"
    ],
    "wof:name":"Ahiranpurwa1",
    "wof:placetype":"neighbourhood",
    "wof:population":71
},
  "geometry": {"coordinates":[81.951832,27.493562],"type":"Point"}
}