{
  "type": "Feature",
  "properties": {
    "iso:country":"IN",
    "ks:ks_name":"Tembwadi",
    "ks:ks_pop":254,
    "ks:ks_type":"HABITATION",
    "name:eng_x_preferred":[
        "Tembwadi"
    ],
    "wof:name":"Tembwadi",
    "wof:placetype":"locality",
    "wof:population":254
},
  "geometry": {"coordinates":[73.87625,15.858556],"type":"Point"}
}