{
  "type": "Feature",
  "properties": {
    "iso:country":"IN",
    "ks:ks_alt_nam":"KUDWA",
    "ks:ks_name":"Kudwa",
    "ks:ks_pop":186,
    "ks:ks_type":"HABITATION",
    "name:eng_x_preferred":[
        "Kudwa"
    ],
    "wof:name":"Kudwa",
    "wof:placetype":"locality",
    "wof:population":186
},
  "geometry": {"coordinates":[81.749922,26.129386],"type":"Point"}
}