{
  "type": "Feature",
  "properties": {
    "iso:country":"IN",
    "ks:ks_name":"Gandhinagar",
    "ks:ks_pop":147,
    "ks:ks_type":"HABITATION",
    "name:eng_x_preferred":[
        "Gandhinagar"
    ],
    "wof:name":"Gandhinagar",
    "wof:placetype":"locality",
    "wof:population":147
},
  "geometry": {"coordinates":[77.746914,9.494579],"type":"Point"}
}