{
  "type": "Feature",
  "properties": {
    "gn:admin1_code":"19.0",
    "gn:admin2_code":"566",
    "gn:asciiname":"Elladakere",
    "gn:country_code":"IN",
    "gn:dem":683,
    "gn:feature_class":"P",
    "gn:feature_code":"PPL",
    "gn:name":"Elladakere",
    "gn:population":0,
    "gn:timezone":"Asia/Kolkata",
    "iso:country":"IN",
    "wof:name":"Elladakere",
    "wof:placetype":"locality"
},
  "geometry": {"coordinates":[76.56704999999999,13.78724],"type":"Point"}
}