{
  "type": "Feature",
  "properties": {
    "iso:country":"IN",
    "ks:ks_name":"Yadiyuru",
    "ks:ks_pop":110,
    "ks:ks_type":"HABITATION",
    "name:eng_x_preferred":[
        "Yadiyuru"
    ],
    "wof:name":"Yadiyuru",
    "wof:placetype":"locality",
    "wof:population":110
},
  "geometry": {"coordinates":[76.04885299999999,12.613538],"type":"Point"}
}