{
  "type": "Feature",
  "properties": {
    "iso:country":"IN",
    "ks:ks_name":"Ganpatiwadi",
    "ks:ks_pop":80,
    "ks:ks_type":"HABITATION",
    "name:eng_x_preferred":[
        "Ganpatiwadi"
    ],
    "wof:name":"Ganpatiwadi",
    "wof:placetype":"locality",
    "wof:population":80
},
  "geometry": {"coordinates":[73.604519,17.605531],"type":"Point"}
}