{
  "type": "Feature",
  "properties": {
    "gn:admin1_code":"12.0",
    "gn:admin2_code":"006",
    "gn:asciiname":"Muttor Thul",
    "gn:country_code":"IN",
    "gn:dem":1444,
    "gn:feature_class":"P",
    "gn:feature_code":"PPL",
    "gn:name":"Muttor Thul",
    "gn:population":0,
    "gn:timezone":"Asia/Kolkata",
    "iso:country":"IN",
    "name:und_x_variant":[
        "Mutta Thul"
    ],
    "wof:name":"Muttor Thul",
    "wof:placetype":"locality"
},
  "geometry": {"coordinates":[74.16413,33.29768],"type":"Point"}
}