{
  "type": "Feature",
  "properties": {
    "gn:admin1_code":"36.0",
    "gn:admin2_code":"149.0",
    "gn:asciiname":"Mainpuri",
    "gn:country_code":"IN",
    "gn:dem":183,
    "gn:feature_class":"P",
    "gn:feature_code":"PPL",
    "gn:name":"Mainpuri",
    "gn:population":0,
    "gn:timezone":"Asia/Kolkata",
    "iso:country":"IN",
    "name:bih_x_preferred":[
        "\u092e\u0948\u0928\u092a\u0941\u0930\u0940"
    ],
    "name:bpy_x_preferred":[
        "\u09ae\u0987\u09a8\u09aa\u09c1\u09b0\u09bf"
    ],
    "name:cat_x_preferred":[
        "Mainpuri"
    ],
    "name:ceb_x_preferred":[
        "Mainpuri"
    ],
    "name:deu_x_preferred":[
        "Mainpuri"
    ],
    "name:fra_x_preferred":[
        "Mainpuri"
    ],
    "name:guj_x_preferred":[
        "\u0aae\u0ac8\u0aa8\u0aaa\u0ac1\u0ab0\u0ac0"
    ],
    "name:hin_x_preferred":[
        "\u092e\u0948\u0928\u092a\u0941\u0930\u0940"
    ],
    "name:ita_x_preferred":[
        "Mainpuri"
    ],
    "name:mar_x_preferred":[
        "\u092e\u0948\u0928\u092a\u0941\u0930\u0940"
    ],
    "name:mlg_x_preferred":[
        "Mainpuri"
    ],
    "name:msa_x_preferred":[
        "Mainpuri"
    ],
    "name:nep_x_preferred":[
        "\u092e\u0948\u0928\u092a\u0941\u0930\u0940"
    ],
    "name:new_x_preferred":[
        "\u092e\u0948\u0928\u094d\u092a\u0941\u0930\u0940"
    ],
    "name:nld_x_preferred":[
        "Mainpuri"
    ],
    "name:pol_x_preferred":[
        "Mainpuri"
    ],
    "name:rus_x_preferred":[
        "\u041c\u0430\u0439\u043d\u043f\u0443\u0440\u0438"
    ],
    "name:san_x_preferred":[
        "\u092e\u0948\u0928\u092a\u0941\u0930\u0940"
    ],
    "name:swe_x_preferred":[
        "Mainpuri"
    ],
    "name:tam_x_preferred":[
        "\u0bae\u0bc8\u0ba9\u0bcd\u0baa\u0bc1\u0bb0\u0bbf"
    ],
    "name:urd_x_preferred":[
        "\u0645\u06cc\u0646 \u067e\u0648\u0631\u06cc"
    ],
    "name:vie_x_preferred":[
        "Mainpuri"
    ],
    "name:zho_x_preferred":[
        "\u8fc8\u6069\u666e\u91cc"
    ],
    "wof:name":"Mainpuri",
    "wof:placetype":"locality"
},
  "geometry": {"coordinates":[79.01796,28.32826],"type":"Point"}
}