{
  "type": "Feature",
  "properties": {
    "iso:country":"IN",
    "ks:ks_name":"Dwaraka",
    "ks:ks_pop":82,
    "ks:ks_type":"HABITATION",
    "name:eng_x_preferred":[
        "Dwaraka"
    ],
    "wof:name":"Dwaraka",
    "wof:placetype":"locality",
    "wof:population":82
},
  "geometry": {"coordinates":[81.04301599999999,15.968087],"type":"Point"}
}