{
  "type": "Feature",
  "properties": {
    "iso:country":"IN",
    "ks:ks_name":"Aliha",
    "ks:ks_pop":205,
    "ks:ks_type":"HABITATION",
    "name:eng_x_preferred":[
        "Aliha"
    ],
    "wof:name":"Aliha",
    "wof:placetype":"locality",
    "wof:population":205
},
  "geometry": {"coordinates":[91.468107,25.989684],"type":"Point"}
}