{
  "type": "Feature",
  "properties": {
    "iso:country":"IN",
    "ks:ks_name":"Dehodhar Block",
    "ks:ks_pop":1655,
    "ks:ks_type":"HABITATION",
    "name:eng_x_preferred":[
        "Dehodhar Block"
    ],
    "wof:name":"Dehodhar Block",
    "wof:placetype":"locality",
    "wof:population":1655
},
  "geometry": {"coordinates":[75.29271300000001,24.49386],"type":"Point"}
}