{
  "type": "Feature",
  "properties": {
    "iso:country":"IN",
    "ks:ks_name":"Markampal",
    "ks:ks_pop":144,
    "ks:ks_type":"HABITATION",
    "name:eng_x_preferred":[
        "Markampal"
    ],
    "wof:name":"Markampal",
    "wof:placetype":"locality",
    "wof:population":144
},
  "geometry": {"coordinates":[81.526034,19.271948],"type":"Point"}
}