{
  "type": "Feature",
  "properties": {
    "iso:country":"IN",
    "ks:ks_alt_nam":"sonarwadi",
    "ks:ks_name":"Sonarwadi",
    "ks:ks_pop":64,
    "ks:ks_type":"HABITATION",
    "name:eng_x_preferred":[
        "Sonarwadi"
    ],
    "wof:name":"Sonarwadi",
    "wof:placetype":"locality",
    "wof:population":64
},
  "geometry": {"coordinates":[73.551467,16.761295],"type":"Point"}
}