{
  "type": "Feature",
  "properties": {
    "gn:admin1_code":"25.0",
    "gn:admin2_code":"602.0",
    "gn:asciiname":"Lingasamudram",
    "gn:country_code":"IN",
    "gn:dem":10,
    "gn:feature_class":"P",
    "gn:feature_code":"PPL",
    "gn:name":"Lingasamudram",
    "gn:population":0,
    "gn:timezone":"Asia/Kolkata",
    "iso:country":"IN",
    "name:new_x_preferred":[
        "\u0932\u093f\u0902\u0917\u0938\u092e\u0941\u0926\u094d\u0930\u092e\u0941 \u092e\u0923\u094d\u0921\u0932"
    ],
    "name:tel_x_preferred":[
        "\u0c32\u0c3f\u0c02\u0c17\u0c38\u0c2e\u0c41\u0c26\u0c4d\u0c30\u0c2e\u0c41"
    ],
    "name:tgl_x_preferred":[
        "Lingasamudram"
    ],
    "name:urd_x_preferred":[
        "\u0644\u0646\u06af\u0627\u0633\u0645\u062f\u0631\u0645"
    ],
    "wof:name":"Lingasamudram",
    "wof:placetype":"locality"
},
  "geometry": {"coordinates":[80.21541999999999,13.33957],"type":"Point"}
}