{
  "type": "Feature",
  "properties": {
    "gn:admin1_code":"25.0",
    "gn:admin2_code":"605.0",
    "gn:asciiname":"Isalapuram",
    "gn:country_code":"IN",
    "gn:dem":95,
    "gn:feature_class":"P",
    "gn:feature_code":"PPL",
    "gn:name":"Isalapuram",
    "gn:population":0,
    "gn:timezone":"Asia/Kolkata",
    "iso:country":"IN",
    "wof:name":"Isalapuram",
    "wof:placetype":"locality"
},
  "geometry": {"coordinates":[79.60764,13.11748],"type":"Point"}
}