{
  "type": "Feature",
  "properties": {
    "iso:country":"IN",
    "ks:ks_name":"Sisaiya",
    "ks:ks_pop":324,
    "ks:ks_type":"VILLAGE",
    "name:eng_x_preferred":[
        "Sisaiya"
    ],
    "wof:name":"Sisaiya",
    "wof:placetype":"locality",
    "wof:population":324
},
  "geometry": {"coordinates":[81.627646,27.944222],"type":"Point"}
}