{
  "type": "Feature",
  "properties": {
    "gn:admin1_code":"39.0",
    "gn:admin2_code":"64.0",
    "gn:asciiname":"Paksha",
    "gn:country_code":"IN",
    "gn:dem":1267,
    "gn:feature_class":"P",
    "gn:feature_code":"PPL",
    "gn:name":"Paksha",
    "gn:population":0,
    "gn:timezone":"Asia/Kolkata",
    "iso:country":"IN",
    "name:ben_x_preferred":[
        "\u09aa\u0995\u09cd\u09b7"
    ],
    "name:hin_x_preferred":[
        "\u092a\u0915\u094d\u0937"
    ],
    "name:kan_x_preferred":[
        "\u0caa\u0c95\u0ccd\u0cb7"
    ],
    "name:ori_x_preferred":[
        "\u0b2a\u0b15\u0b4d\u0b37"
    ],
    "name:san_x_preferred":[
        "\u092a\u0915\u094d\u0937\u094c"
    ],
    "name:spa_x_preferred":[
        "Shukla"
    ],
    "wof:name":"Paksha",
    "wof:placetype":"locality"
},
  "geometry": {"coordinates":[79.51674,29.70861],"type":"Point"}
}