{
  "type": "Feature",
  "properties": {
    "iso:country":"IN",
    "ks:ks_name":"Marora",
    "ks:ks_pop":338,
    "ks:ks_type":"HABITATION",
    "name:eng_x_preferred":[
        "Marora"
    ],
    "wof:name":"Marora",
    "wof:placetype":"locality",
    "wof:population":338
},
  "geometry": {"coordinates":[78.504622,30.317827],"type":"Point"}
}