{
  "type": "Feature",
  "properties": {
    "gn:admin1_code":"9.0",
    "gn:admin2_code":"471.0",
    "gn:asciiname":"Sardarpur",
    "gn:country_code":"IN",
    "gn:dem":221,
    "gn:feature_class":"P",
    "gn:feature_code":"PPL",
    "gn:name":"Sardarpur",
    "gn:population":0,
    "gn:timezone":"Asia/Kolkata",
    "iso:country":"IN",
    "name:ben_x_preferred":[
        "\u09b8\u09b0\u09a6\u09be\u09b0\u09aa\u09c1\u09b0"
    ],
    "name:bpy_x_preferred":[
        "\u09b8\u09b0\u09a6\u09be\u09b0\u09aa\u09c1\u09b0"
    ],
    "name:cat_x_preferred":[
        "Sardarpur"
    ],
    "name:ceb_x_preferred":[
        "Sird\u0101rpore"
    ],
    "name:ita_x_preferred":[
        "Sardarpur"
    ],
    "name:mlg_x_preferred":[
        "Sardarpur"
    ],
    "name:msa_x_preferred":[
        "Sardarpur"
    ],
    "name:nld_x_preferred":[
        "Sardarpur"
    ],
    "name:por_x_preferred":[
        "Sardarpur"
    ],
    "name:swe_x_preferred":[
        "Sird\u0101rpore"
    ],
    "name:und_x_variant":[
        "Chikni"
    ],
    "name:vie_x_preferred":[
        "Sardarpur"
    ],
    "name:zho_x_preferred":[
        "\u8428\u5c14\u8fbe\u5c14\u666e\u5c14"
    ],
    "wof:name":"Sardarpur",
    "wof:placetype":"locality"
},
  "geometry": {"coordinates":[72.65394000000001,24.01402],"type":"Point"}
}