{
  "type": "Feature",
  "properties": {
    "gn:admin1_code":"38.0",
    "gn:admin2_code":"347.0",
    "gn:asciiname":"Sonpura Khurd",
    "gn:country_code":"IN",
    "gn:dem":413,
    "gn:feature_class":"P",
    "gn:feature_code":"PPL",
    "gn:name":"Sonpur\u0101 Khurd",
    "gn:population":0,
    "gn:timezone":"Asia/Kolkata",
    "iso:country":"IN",
    "ks:ks_name":"Sonpura Khurd",
    "ks:ks_pop":324,
    "ks:ks_type":"VILLAGE",
    "name:eng_x_preferred":[
        "Sonpura Khurd"
    ],
    "wof:name":"Sonpura Khurd",
    "wof:placetype":"locality",
    "wof:population":324
},
  "geometry": {"coordinates":[85.28119,24.263252],"type":"Point"}
}