{
  "type": "Feature",
  "properties": {
    "gn:admin1_code":"38.0",
    "gn:admin2_code":"347.0",
    "gn:asciiname":"Sonpura Khurd",
    "gn:country_code":"IN",
    "gn:dem":413,
    "gn:feature_class":"P",
    "gn:feature_code":"PPL",
    "gn:name":"Sonpur\u0101 Khurd",
    "gn:population":0,
    "gn:timezone":"Asia/Kolkata",
    "iso:country":"IN",
    "wof:name":"Sonpura Khurd",
    "wof:placetype":"locality"
},
  "geometry": {"coordinates":[85.27709,24.26419],"type":"Point"}
}