{
  "type": "Feature",
  "properties": {
    "gn:admin1_code":"19.0",
    "gn:admin2_code":"568",
    "gn:asciiname":"Karur",
    "gn:country_code":"IN",
    "gn:dem":595,
    "gn:feature_class":"P",
    "gn:feature_code":"PPL",
    "gn:name":"Kar\u016br",
    "gn:population":0,
    "gn:timezone":"Asia/Kolkata",
    "iso:country":"IN",
    "name:ara_x_preferred":[
        "\u0643\u0631\u0648\u0631"
    ],
    "name:bpy_x_preferred":[
        "\u0995\u09be\u09b0\u09c1\u09b0"
    ],
    "name:cat_x_preferred":[
        "Karur"
    ],
    "name:ceb_x_preferred":[
        "Karur"
    ],
    "name:deu_x_preferred":[
        "Karur"
    ],
    "name:fas_x_preferred":[
        "\u06a9\u0627\u0631\u0648\u0631"
    ],
    "name:fra_x_preferred":[
        "Karur"
    ],
    "name:guj_x_preferred":[
        "\u0a95\u0ab0\u0ac1\u0ab0"
    ],
    "name:hin_x_preferred":[
        "\u0915\u0930\u0942\u0930"
    ],
    "name:ita_x_preferred":[
        "Karur"
    ],
    "name:jpn_x_preferred":[
        "\u30ab\u30eb\u30fc\u30eb"
    ],
    "name:kan_x_preferred":[
        "\u0c95\u0cb0\u0cc2\u0cb0\u0ccd"
    ],
    "name:kor_x_preferred":[
        "\uce74\ub8e8\ub974"
    ],
    "name:mal_x_preferred":[
        "\u0d15\u0d30\u0d42\u0d7c"
    ],
    "name:mar_x_preferred":[
        "\u0915\u0930\u0941\u0930"
    ],
    "name:mlg_x_preferred":[
        "Karur"
    ],
    "name:msa_x_preferred":[
        "Karur"
    ],
    "name:new_x_preferred":[
        "\u0915\u0930\u0941\u0930"
    ],
    "name:ori_x_preferred":[
        "\u0b15\u0b3e\u0b30\u0b41\u0b30\u0b4d"
    ],
    "name:pam_x_preferred":[
        "Karur"
    ],
    "name:pol_x_preferred":[
        "Karur"
    ],
    "name:por_x_preferred":[
        "Karur"
    ],
    "name:ron_x_preferred":[
        "Karur"
    ],
    "name:rus_x_preferred":[
        "\u041a\u0430\u0440\u0443\u0440"
    ],
    "name:san_x_preferred":[
        "\u0915\u0930\u0942\u0930\u0941"
    ],
    "name:spa_x_preferred":[
        "Karur"
    ],
    "name:swe_x_preferred":[
        "Karur"
    ],
    "name:tam_x_preferred":[
        "\u0b95\u0bb0\u0bc2\u0bb0\u0bcd"
    ],
    "name:ukr_x_preferred":[
        "\u041a\u0430\u0440\u0443\u0440"
    ],
    "name:urd_x_preferred":[
        "\u06a9\u0631\u0648\u0631"
    ],
    "name:vie_x_preferred":[
        "Karur"
    ],
    "name:war_x_preferred":[
        "Karur"
    ],
    "name:zho_x_preferred":[
        "\u5361\u9c81\u5c14"
    ],
    "wof:name":"Karur",
    "wof:placetype":"locality"
},
  "geometry": {"coordinates":[74.89437,14.01686],"type":"Point"}
}