{
  "type": "Feature",
  "properties": {
    "iso:country":"IN",
    "ks:ks_name":"Duvia",
    "ks:ks_pop":535,
    "ks:ks_type":"VILLAGE",
    "name:eng_x_preferred":[
        "Duvia"
    ],
    "wof:name":"Duvia",
    "wof:placetype":"locality",
    "wof:population":535
},
  "geometry": {"coordinates":[86.760441,21.845368],"type":"Point"}
}