{
  "type": "Feature",
  "properties": {
    "gn:admin1_code":"38.0",
    "gn:admin2_code":"347.0",
    "gn:asciiname":"Purni Hesag",
    "gn:country_code":"IN",
    "gn:dem":429,
    "gn:feature_class":"P",
    "gn:feature_code":"PPL",
    "gn:name":"Purni Hes\u0101g",
    "gn:population":0,
    "gn:timezone":"Asia/Kolkata",
    "iso:country":"IN",
    "ks:ks_alt_nam":"PURANIHESANG",
    "ks:ks_name":"Puranihesang",
    "ks:ks_pop":218,
    "ks:ks_type":"HABITATION",
    "name:eng_x_preferred":[
        "Puranihesang"
    ],
    "name:eng_x_variant":[
        "Purni Hesag"
    ],
    "wof:name":"Puranihesang",
    "wof:placetype":"locality",
    "wof:population":218
},
  "geometry": {"coordinates":[85.03858200000001,24.308731],"type":"Point"}
}