{
  "type": "Feature",
  "properties": {
    "iso:country":"IN",
    "ks:ks_name":"Valaiya",
    "ks:ks_pop":1666,
    "ks:ks_type":"VILLAGE",
    "name:eng_x_preferred":[
        "Valaiya"
    ],
    "wof:name":"Valaiya",
    "wof:placetype":"locality",
    "wof:population":1666
},
  "geometry": {"coordinates":[73.812155,23.027218],"type":"Point"}
}