{
  "type": "Feature",
  "properties": {
    "gn:admin1_code":"36",
    "gn:admin2_code":"152.0",
    "gn:asciiname":"Beharipur Mundia",
    "gn:country_code":"IN",
    "gn:dem":157,
    "gn:feature_class":"P",
    "gn:feature_code":"PPL",
    "gn:name":"Beh\u0101r\u012bpur Mundia",
    "gn:population":0,
    "gn:timezone":"Asia/Kolkata",
    "iso:country":"IN",
    "wof:name":"Beharipur Mundia",
    "wof:placetype":"locality"
},
  "geometry": {"coordinates":[79.78914,27.96829],"type":"Point"}
}