{
  "type": "Feature",
  "properties": {
    "iso:country":"IN",
    "ks:ks_alt_nam":"DULUCHERRA",
    "ks:ks_name":"Dulucherra",
    "ks:ks_pop":179,
    "ks:ks_type":"HABITATION",
    "name:eng_x_preferred":[
        "Dulucherra"
    ],
    "wof:name":"Dulucherra",
    "wof:placetype":"locality",
    "wof:population":179
},
  "geometry": {"coordinates":[91.67486599999999,24.017782],"type":"Point"}
}