{
  "type": "Feature",
  "properties": {
    "gn:admin1_code":"40",
    "gn:admin2_code":"540.0",
    "gn:asciiname":"Madharam",
    "gn:country_code":"IN",
    "gn:dem":379,
    "gn:feature_class":"P",
    "gn:feature_code":"PPL",
    "gn:name":"M\u0101dh\u0101ram",
    "gn:population":0,
    "gn:timezone":"Asia/Kolkata",
    "iso:country":"IN",
    "name:urd_x_preferred":[
        "\u0645\u062f\u06be\u0627\u0631\u0627\u0645"
    ],
    "wof:name":"Madharam",
    "wof:placetype":"locality"
},
  "geometry": {"coordinates":[79.22505,17.77616],"type":"Point"}
}