{
  "type": "Feature",
  "properties": {
    "iso:country":"IN",
    "ks:ks_name":"No.1 Sensowa Gaon",
    "ks:ks_pop":1469,
    "ks:ks_type":"VILLAGE",
    "ks:ks_uagg_main":0,
    "name:eng_x_preferred":[
        "No.1 Sensowa Gaon"
    ],
    "wof:name":"No.1 Sensowa Gaon",
    "wof:placetype":"locality",
    "wof:population":1469
},
  "geometry": {"coordinates":[93.916827,26.547826],"type":"Point"}
}