{
  "type": "Feature",
  "properties": {
    "gn:admin1_code":"23",
    "gn:admin2_code":"37.0",
    "gn:asciiname":"Durgawal",
    "gn:country_code":"IN",
    "gn:dem":227,
    "gn:feature_class":"P",
    "gn:feature_code":"PPL",
    "gn:name":"Durg\u0101w\u0101l",
    "gn:population":0,
    "gn:timezone":"Asia/Kolkata",
    "iso:country":"IN",
    "ks:ks_alt_nam":"Durg\u0101w\u0101l",
    "ks:ks_name":"Durgawal",
    "ks:ks_type":"VILLAGE",
    "ks:ks_uagg_main":0,
    "name:eng_x_preferred":[
        "Durgawal"
    ],
    "name:eng_x_variant":[
        "Durg\u0101w\u0101l"
    ],
    "wof:name":"Durgawal",
    "wof:placetype":"neighbourhood"
},
  "geometry": {"coordinates":[75.43588800000001,31.146903],"type":"Point"}
}