{
  "type": "Feature",
  "properties": {
    "iso:country":"IN",
    "ks:ks_name":"Basthikatte Marne",
    "ks:ks_pop":145,
    "ks:ks_type":"HABITATION",
    "name:eng_x_preferred":[
        "Basthikatte Marne"
    ],
    "wof:name":"Basthikatte Marne",
    "wof:placetype":"locality",
    "wof:population":145
},
  "geometry": {"coordinates":[75.05990799999999,13.274446],"type":"Point"}
}