{
  "type": "Feature",
  "properties": {
    "iso:country":"IN",
    "ks:ks_name":"Bhajanpur",
    "ks:ks_pop":2110,
    "ks:ks_type":"VILLAGE",
    "ks:ks_uagg_main":0,
    "name:eng_x_preferred":[
        "Bhajanpur"
    ],
    "wof:name":"Bhajanpur",
    "wof:placetype":"neighbourhood",
    "wof:population":2110
},
  "geometry": {"coordinates":[78.89577800000001,28.648322],"type":"Point"}
}