{
  "type": "Feature",
  "properties": {
    "gn:admin1_code":"35.0",
    "gn:admin2_code":"438.0",
    "gn:asciiname":"Baripura",
    "gn:country_code":"IN",
    "gn:dem":267,
    "gn:feature_class":"P",
    "gn:feature_code":"PPL",
    "gn:name":"Bar\u012bpura",
    "gn:population":0,
    "gn:timezone":"Asia/Kolkata",
    "iso:country":"IN",
    "wof:name":"Baripura",
    "wof:placetype":"locality"
},
  "geometry": {"coordinates":[74.68977,22.16718],"type":"Point"}
}