{
  "type": "Feature",
  "properties": {
    "gn:admin1_code":"12.0",
    "gn:admin2_code":"7.0",
    "gn:asciiname":"Dhaman",
    "gn:country_code":"IN",
    "gn:dem":1771,
    "gn:feature_class":"P",
    "gn:feature_code":"PPL",
    "gn:name":"Dham\u0101n",
    "gn:population":0,
    "gn:timezone":"Asia/Kolkata",
    "iso:country":"IN",
    "wof:name":"Dhaman",
    "wof:placetype":"locality"
},
  "geometry": {"coordinates":[75.72459000000001,32.7142],"type":"Point"}
}