{
  "type": "Feature",
  "properties": {
    "gn:admin1_code":"2",
    "gn:admin2_code":"544.0",
    "gn:asciiname":"Gotivada Agraharam",
    "gn:country_code":"IN",
    "gn:dem":61,
    "gn:feature_class":"P",
    "gn:feature_code":"PPL",
    "gn:name":"Gotiv\u0101da Agrah\u0101ram",
    "gn:population":0,
    "gn:timezone":"Asia/Kolkata",
    "iso:country":"IN",
    "wof:name":"Gotivada Agraharam",
    "wof:placetype":"locality"
},
  "geometry": {"coordinates":[82.83129,17.86077000000001],"type":"Point"}
}