{
  "type": "Feature",
  "properties": {
    "iso:country":"IN",
    "ks:ks_name":"Era",
    "ks:ks_pop":949,
    "ks:ks_type":"VILLAGE",
    "ks:ks_uagg_main":0,
    "name:eng_x_preferred":[
        "Era"
    ],
    "wof:name":"Era",
    "wof:placetype":"neighbourhood",
    "wof:population":949
},
  "geometry": {"coordinates":[86.500055,20.509273],"type":"Point"}
}