{
  "type": "Feature",
  "properties": {
    "gn:admin1_code":"40.0",
    "gn:admin2_code":"538",
    "gn:asciiname":"Darur",
    "gn:country_code":"IN",
    "gn:dem":364,
    "gn:feature_class":"P",
    "gn:feature_code":"PPL",
    "gn:name":"D\u0101r\u016br",
    "gn:population":0,
    "gn:timezone":"Asia/Kolkata",
    "iso:country":"IN",
    "name:und_x_variant":[
        "Dharur",
        "D\u0101r\u016br"
    ],
    "name:vie_x_preferred":[
        "Darur"
    ],
    "wof:name":"Darur",
    "wof:placetype":"locality"
},
  "geometry": {"coordinates":[77.69596,16.23378],"type":"Point"}
}