{
  "type": "Feature",
  "properties": {
    "gn:admin1_code":"2",
    "gn:admin2_code":"545.0",
    "gn:asciiname":"Kottapalle",
    "gn:country_code":"IN",
    "gn:dem":179,
    "gn:feature_class":"P",
    "gn:feature_code":"PPL",
    "gn:name":"Kottapalle",
    "gn:population":0,
    "gn:timezone":"Asia/Kolkata",
    "iso:country":"IN",
    "ks:ks_name":"Kothapalle",
    "ks:ks_pop":207,
    "ks:ks_type":"VILLAGE",
    "name:eng_x_preferred":[
        "Kothapalle"
    ],
    "name:eng_x_variant":[
        "Kottapalle"
    ],
    "wof:name":"Kothapalle",
    "wof:placetype":"locality",
    "wof:population":207
},
  "geometry": {"coordinates":[82.21280400000001,17.408331],"type":"Point"}
}