{
  "type": "Feature",
  "properties": {
    "iso:country":"IN",
    "ks:ks_name":"Nainthal",
    "ks:ks_pop":6,
    "ks:ks_type":"HABITATION",
    "name:eng_x_preferred":[
        "Nainthal"
    ],
    "wof:name":"Nainthal",
    "wof:placetype":"locality",
    "wof:population":6
},
  "geometry": {"coordinates":[80.20461899999999,29.89055],"type":"Point"}
}