{
  "type": "Feature",
  "properties": {
    "iso:country":"IN",
    "ks:ks_name":"Kalkanamuvada",
    "ks:ks_pop":394,
    "ks:ks_type":"HABITATION",
    "ks:ks_uagg_main":0,
    "name:eng_x_preferred":[
        "Kalkanamuvada"
    ],
    "wof:name":"Kalkanamuvada",
    "wof:placetype":"neighbourhood",
    "wof:population":394
},
  "geometry": {"coordinates":[73.109556,23.010972],"type":"Point"}
}