{
  "type": "Feature",
  "properties": {
    "iso:country":"IN",
    "ks:ks_name":"Mathavali",
    "ks:ks_pop":888,
    "ks:ks_type":"VILLAGE",
    "name:eng_x_preferred":[
        "Mathavali"
    ],
    "wof:name":"Mathavali",
    "wof:placetype":"locality",
    "wof:population":888
},
  "geometry": {"coordinates":[73.759917,21.674967],"type":"Point"}
}