{
  "type": "Feature",
  "properties": {
    "gn:admin1_code":"16",
    "gn:admin2_code":"529.0",
    "gn:asciiname":"Vadachapat",
    "gn:country_code":"IN",
    "gn:dem":27,
    "gn:feature_class":"P",
    "gn:feature_code":"PPL",
    "gn:name":"Vad\u0101ch\u0101pat",
    "gn:population":0,
    "gn:timezone":"Asia/Kolkata",
    "iso:country":"IN",
    "ks:ks_name":"Wadachapat",
    "ks:ks_pop":1086,
    "ks:ks_type":"VILLAGE",
    "name:eng_x_preferred":[
        "Wadachapat"
    ],
    "name:eng_x_variant":[
        "Vadachapat"
    ],
    "wof:name":"Wadachapat",
    "wof:placetype":"locality",
    "wof:population":1086
},
  "geometry": {"coordinates":[73.57284799999999,16.156302],"type":"Point"}
}