{
  "type": "Feature",
  "properties": {
    "gn:admin1_code":"37",
    "gn:admin2_code":"405.0",
    "gn:asciiname":"Komo",
    "gn:country_code":"IN",
    "gn:dem":234,
    "gn:feature_class":"P",
    "gn:feature_code":"PPL",
    "gn:name":"Komo",
    "gn:population":0,
    "gn:timezone":"Asia/Kolkata",
    "iso:country":"IN",
    "name:bul_x_preferred":[
        "\u041a\u043e\u043c\u043e"
    ],
    "name:deu_x_preferred":[
        "Komo"
    ],
    "name:fra_x_preferred":[
        "Komo"
    ],
    "name:lav_x_preferred":[
        "Komo"
    ],
    "name:mkd_x_preferred":[
        "\u041a\u043e\u043c\u043e"
    ],
    "name:oss_x_preferred":[
        "\u041a\u043e\u043c\u043e"
    ],
    "name:rus_x_preferred":[
        "\u041a\u043e\u043c\u043e"
    ],
    "name:srp_x_preferred":[
        "\u041a\u043e\u043c\u043e"
    ],
    "name:swe_x_preferred":[
        "Komo"
    ],
    "name:ukr_x_preferred":[
        "\u041a\u043e\u043c\u043e"
    ],
    "wof:name":"Komo",
    "wof:placetype":"locality"
},
  "geometry": {"coordinates":[83.16656999999999,21.87547],"type":"Point"}
}