{
  "type": "Feature",
  "properties": {
    "gn:admin1_code":"36",
    "gn:admin2_code":"195.0",
    "gn:asciiname":"Bogna",
    "gn:country_code":"IN",
    "gn:dem":78,
    "gn:feature_class":"P",
    "gn:feature_code":"PPL",
    "gn:name":"Bogna",
    "gn:population":0,
    "gn:timezone":"Asia/Kolkata",
    "iso:country":"IN",
    "name:deu_x_preferred":[
        "Bogna"
    ],
    "name:pol_x_preferred":[
        "Bogna"
    ],
    "name:spa_x_preferred":[
        "Bogna"
    ],
    "wof:name":"Bogna",
    "wof:placetype":"neighbourhood"
},
  "geometry": {"coordinates":[83.52625999999999,25.78403],"type":"Point"}
}