{
  "type": "Feature",
  "properties": {
    "iso:country":"IN",
    "ks:ks_name":"Mamari Mu. Devpura",
    "ks:ks_pop":253,
    "ks:ks_type":"VILLAGE",
    "name:eng_x_preferred":[
        "Mamari Mu. Devpura"
    ],
    "wof:name":"Mamari Mu. Devpura",
    "wof:placetype":"locality",
    "wof:population":253
},
  "geometry": {"coordinates":[82.74111600000001,24.876778],"type":"Point"}
}