{
  "type": "Feature",
  "properties": {
    "gn:admin1_code":"12",
    "gn:admin2_code":"14.0",
    "gn:asciiname":"Gangabal",
    "gn:country_code":"IN",
    "gn:dem":1615,
    "gn:feature_class":"P",
    "gn:feature_code":"PPL",
    "gn:name":"Gangabal",
    "gn:population":0,
    "gn:timezone":"Asia/Kolkata",
    "iso:country":"IN",
    "wof:name":"Gangabal",
    "wof:placetype":"locality"
},
  "geometry": {"coordinates":[75.13398000000002,33.6874],"type":"Point"}
}