{
  "type": "Feature",
  "properties": {
    "iso:country":"IN",
    "ks:ks_alt_nam":"chilmud gaon",
    "ks:ks_name":"Chilmud Gaon",
    "ks:ks_pop":360,
    "ks:ks_type":"HABITATION",
    "name:eng_x_preferred":[
        "Chilmud Gaon"
    ],
    "wof:name":"Chilmud Gaon",
    "wof:placetype":"locality",
    "wof:population":360
},
  "geometry": {"coordinates":[78.42312200000001,30.665052],"type":"Point"}
}