{
  "type": "Feature",
  "properties": {
    "gn:admin1_code":"24",
    "gn:admin2_code":"110.0",
    "gn:asciiname":"Gawar",
    "gn:country_code":"IN",
    "gn:dem":361,
    "gn:feature_class":"P",
    "gn:feature_code":"PPL",
    "gn:name":"Gaw\u0101r",
    "gn:population":0,
    "gn:timezone":"Asia/Kolkata",
    "iso:country":"IN",
    "name:fra_x_preferred":[
        "Gawar"
    ],
    "wof:name":"Gawar",
    "wof:placetype":"locality"
},
  "geometry": {"coordinates":[75.79148000000001,26.75814],"type":"Point"}
}