{
  "type": "Feature",
  "properties": {
    "gn:admin1_code":"10.0",
    "gn:admin2_code":"083",
    "gn:asciiname":"Jasaur",
    "gn:country_code":"IN",
    "gn:dem":221,
    "gn:feature_class":"P",
    "gn:feature_code":"PPL",
    "gn:name":"Jasaur",
    "gn:population":0,
    "gn:timezone":"Asia/Kolkata",
    "iso:country":"IN",
    "ks:ks_name":"Jasaur",
    "ks:ks_pop":3972,
    "ks:ks_type":"VILLAGE",
    "ks:ks_uagg_main":0,
    "name:eng_x_preferred":[
        "Jasaur"
    ],
    "wof:name":"Jasaur",
    "wof:placetype":"neighbourhood",
    "wof:population":3972
},
  "geometry": {"coordinates":[76.866958,28.78042],"type":"Point"}
}