{
  "type": "Feature",
  "properties": {
    "iso:country":"IN",
    "ks:ks_alt_nam":"lobhipada",
    "ks:ks_name":"Lobhipada",
    "ks:ks_pop":59,
    "ks:ks_type":"HABITATION",
    "name:eng_x_preferred":[
        "Lobhipada"
    ],
    "wof:name":"Lobhipada",
    "wof:placetype":"locality",
    "wof:population":59
},
  "geometry": {"coordinates":[73.31444399999999,19.693383],"type":"Point"}
}