{
  "type": "Feature",
  "properties": {
    "gn:admin1_code":"16",
    "gn:admin2_code":"524.0",
    "gn:asciiname":"Ari",
    "gn:country_code":"IN",
    "gn:dem":618,
    "gn:feature_class":"P",
    "gn:feature_code":"PPL",
    "gn:name":"\u0100ri",
    "gn:population":0,
    "gn:timezone":"Asia/Kolkata",
    "iso:country":"IN",
    "name:cat_x_preferred":[
        "Ari"
    ],
    "name:ceb_x_preferred":[
        "Ari"
    ],
    "name:heb_x_preferred":[
        "\u05d0\u05e8\u05d9"
    ],
    "name:ita_x_preferred":[
        "Ari"
    ],
    "name:lim_x_preferred":[
        "Ari"
    ],
    "name:nld_x_preferred":[
        "Ari"
    ],
    "name:pol_x_preferred":[
        "Ari"
    ],
    "name:por_x_preferred":[
        "Ari"
    ],
    "name:rus_x_preferred":[
        "\u0410\u0440\u0438"
    ],
    "name:slk_x_preferred":[
        "Ari"
    ],
    "name:srp_x_preferred":[
        "\u0410\u0440\u0438"
    ],
    "name:swe_x_preferred":[
        "Ari"
    ],
    "name:ukr_x_preferred":[
        "\u0410\u0440\u0456"
    ],
    "name:zho_x_preferred":[
        "Ari"
    ],
    "wof:name":"Ari",
    "wof:placetype":"neighbourhood"
},
  "geometry": {"coordinates":[76.79671,18.34307],"type":"Point"}
}