{
  "type": "Feature",
  "properties": {
    "iso:country":"IN",
    "ks:ks_name":"Thakrekond",
    "ks:ks_pop":115,
    "ks:ks_type":"HABITATION",
    "name:eng_x_preferred":[
        "Thakrekond"
    ],
    "wof:name":"Thakrekond",
    "wof:placetype":"locality",
    "wof:population":115
},
  "geometry": {"coordinates":[73.39970599999999,17.998085],"type":"Point"}
}