{
  "type": "Feature",
  "properties": {
    "iso:country":"IN",
    "ks:ks_name":"Kaudikhal",
    "ks:ks_pop":184,
    "ks:ks_type":"HABITATION",
    "name:eng_x_preferred":[
        "Kaudikhal"
    ],
    "wof:name":"Kaudikhal",
    "wof:placetype":"locality",
    "wof:population":184
},
  "geometry": {"coordinates":[82.74554500000001,18.53687],"type":"Point"}
}