{
  "type": "Feature",
  "properties": {
    "iso:country":"IN",
    "ks:ks_name":"Manickapuram",
    "ks:ks_pop":110,
    "ks:ks_type":"HABITATION",
    "name:eng_x_preferred":[
        "Manickapuram"
    ],
    "wof:name":"Manickapuram",
    "wof:placetype":"locality",
    "wof:population":110
},
  "geometry": {"coordinates":[77.89082000000001,8.336742],"type":"Point"}
}