{
  "type": "Feature",
  "properties": {
    "gn:admin1_code":"36.0",
    "gn:admin2_code":"141.0",
    "gn:asciiname":"Rohillapur",
    "gn:country_code":"IN",
    "gn:dem":198,
    "gn:feature_class":"P",
    "gn:feature_code":"PPL",
    "gn:name":"Rohill\u0101pur",
    "gn:population":0,
    "gn:timezone":"Asia/Kolkata",
    "iso:country":"IN",
    "name:ara_x_preferred":[
        "\u0631\u0648\u0647\u064a\u0644 \u0628\u0648\u0631"
    ],
    "name:ben_bn_x_preferred":[
        "\u09b0\u09cb\u09b9\u09bf\u09b2\u09cd\u09b2\u09be\u09aa\u09c1\u09b0"
    ],
    "name:ben_in_x_preferred":[
        "\u09b0\u09cb\u09b9\u09bf\u09b2\u09cd\u09b2\u09be\u09aa\u09c1\u09b0"
    ],
    "name:guj_x_preferred":[
        "\u0ab0\u0acb\u0ab9\u0abe\u0ab2\u0acd\u0ab2\u0abe\u0aaa\u0ac1\u0ab0"
    ],
    "name:hin_x_preferred":[
        "\u0930\u094b\u0939\u093f\u0932\u094d\u0932\u093e\u092a\u0941\u0930"
    ],
    "name:kan_x_preferred":[
        "\u0cb0\u0cca\u0cb9\u0cbf\u0cb2\u0ccd\u0cb2\u0cbe\u0caa\u0cc1\u0cb0"
    ],
    "name:mal_x_preferred":[
        "\u0d30\u0d4b\u0d39\u0d3f\u0d32\u0d3e\u0d2a\u0d42\u0d7c"
    ],
    "name:mar_x_preferred":[
        "\u0930\u094b\u0939\u093f\u0932\u094d\u0932\u093e\u092a\u0942\u0930"
    ],
    "name:pan_x_preferred":[
        "\u0a30\u0a4b\u0a39\u0a3f\u0a32\u0a3e\u0a2a\u0a41\u0a30"
    ],
    "name:tam_x_preferred":[
        "\u0bb0\u0bcb\u0bb9\u0bbf\u0bb2\u0bcd\u0bb2\u0bbe\u0baa\u0bc2\u0bb0\u0bcd"
    ],
    "name:tel_x_preferred":[
        "\u0c30\u0c4b\u0c39\u0c3f\u0c32\u0c4d\u0c32\u0c3e\u0c2a\u0c42\u0c30\u0c4d"
    ],
    "name:urd_x_preferred":[
        "\u0631\u0648\u06c1\u06cc\u0644\u06c1 \u067e\u0648\u0631"
    ],
    "wof:name":"Rohillapur",
    "wof:placetype":"neighbourhood"
},
  "geometry": {"coordinates":[77.37748000000001,28.51162],"type":"Point"}
}