{
  "type": "Feature",
  "properties": {
    "gn:admin1_code":"36",
    "gn:admin2_code":"154.0",
    "gn:asciiname":"Andhanan",
    "gn:country_code":"IN",
    "gn:dem":138,
    "gn:feature_class":"P",
    "gn:feature_code":"PPL",
    "gn:name":"Andhan\u0101n",
    "gn:population":0,
    "gn:timezone":"Asia/Kolkata",
    "iso:country":"IN",
    "ks:ks_name":"Andhana",
    "ks:ks_pop":700,
    "ks:ks_type":"VILLAGE",
    "ks:ks_uagg_main":0,
    "name:eng_x_preferred":[
        "Andhana"
    ],
    "wof:name":"Andhana",
    "wof:placetype":"neighbourhood",
    "wof:population":700
},
  "geometry": {"coordinates":[80.916162,27.329363],"type":"Point"}
}