{
  "type": "Feature",
  "properties": {
    "iso:country":"IN",
    "ks:ks_name":"Sunnalu",
    "ks:ks_pop":216,
    "ks:ks_type":"HABITATION",
    "name:eng_x_preferred":[
        "Sunnalu"
    ],
    "wof:name":"Sunnalu",
    "wof:placetype":"locality",
    "wof:population":216
},
  "geometry": {"coordinates":[75.293487,12.943594],"type":"Point"}
}