{
  "type": "Feature",
  "properties": {
    "iso:country":"IN",
    "ks:ks_alt_nam":"PARASSERY",
    "ks:ks_name":"Parassery",
    "ks:ks_pop":250,
    "ks:ks_type":"HABITATION",
    "name:eng_x_preferred":[
        "Parassery"
    ],
    "wof:name":"Parassery",
    "wof:placetype":"locality",
    "wof:population":250
},
  "geometry": {"coordinates":[76.62845799999999,10.594024],"type":"Point"}
}