{
  "type": "Feature",
  "properties": {
    "iso:country":"IN",
    "ks:ks_name":"Patna",
    "ks:ks_pop":0,
    "ks:ks_type":"VILLAGE",
    "name:eng_x_preferred":[
        "Patna"
    ],
    "name:hin_x_preferred":[
        "\u092a\u091f\u0928\u093e"
    ],
    "wof:name":"Patna",
    "wof:placetype":"locality",
    "wof:population":0
},
  "geometry": {"coordinates":[85.56582,22.745804],"type":"Point"}
}