{
  "type": "Feature",
  "properties": {
    "gn:admin1_code":"11.0",
    "gn:admin2_code":"33.0",
    "gn:asciiname":"Arshala",
    "gn:country_code":"IN",
    "gn:dem":2560,
    "gn:feature_class":"P",
    "gn:feature_code":"PPL",
    "gn:name":"Arsh\u0101la",
    "gn:population":0,
    "gn:timezone":"Asia/Kolkata",
    "iso:country":"IN",
    "wof:name":"Arshala",
    "wof:placetype":"locality"
},
  "geometry": {"coordinates":[77.46368000000002,31.02379],"type":"Point"}
}