{
  "type": "Feature",
  "properties": {
    "iso:country":"IN",
    "ks:ks_name":"Chakpanchapada",
    "ks:ks_pop":46,
    "ks:ks_type":"VILLAGE",
    "name:eng_x_preferred":[
        "Chakpanchapada"
    ],
    "wof:name":"Chakpanchapada",
    "wof:placetype":"locality",
    "wof:population":46
},
  "geometry": {"coordinates":[87.081718,21.581514],"type":"Point"}
}