{
  "type": "Feature",
  "properties": {
    "iso:country":"IN",
    "ks:ks_alt_nam":"Baher bigha",
    "ks:ks_name":"Baher Bigha",
    "ks:ks_pop":150,
    "ks:ks_type":"HABITATION",
    "name:eng_x_preferred":[
        "Baher Bigha"
    ],
    "wof:name":"Baher Bigha",
    "wof:placetype":"locality",
    "wof:population":150
},
  "geometry": {"coordinates":[84.571702,24.892144],"type":"Point"}
}