{
  "type": "Feature",
  "properties": {
    "gn:admin1_code":"36",
    "gn:admin2_code":"178.0",
    "gn:asciiname":"Tikri",
    "gn:country_code":"IN",
    "gn:dem":98,
    "gn:feature_class":"P",
    "gn:feature_code":"PPL",
    "gn:name":"Tikri",
    "gn:population":0,
    "gn:timezone":"Asia/Kolkata",
    "iso:country":"IN",
    "ks:ks_name":"Tikari",
    "ks:ks_pop":735,
    "ks:ks_type":"HABITATION",
    "name:ceb_x_preferred":[
        "Tikri"
    ],
    "name:eng_x_preferred":[
        "Tikari"
    ],
    "name:eng_x_variant":[
        "Tikri"
    ],
    "name:swe_x_preferred":[
        "Tikri"
    ],
    "wof:name":"Tikari",
    "wof:placetype":"locality",
    "wof:population":735
},
  "geometry": {"coordinates":[82.389657,26.467326],"type":"Point"}
}