{
  "type": "Feature",
  "properties": {
    "gn:admin1_code":"16.0",
    "gn:admin2_code":"498.0",
    "gn:asciiname":"Vaghadi Khurd",
    "gn:country_code":"IN",
    "gn:dem":224,
    "gn:feature_class":"P",
    "gn:feature_code":"PPL",
    "gn:name":"V\u0101gh\u0101di Khurd",
    "gn:population":0,
    "gn:timezone":"Asia/Kolkata",
    "iso:country":"IN",
    "wof:name":"Vaghadi Khurd",
    "wof:placetype":"neighbourhood"
},
  "geometry": {"coordinates":[74.81516999999999,21.09606],"type":"Point"}
}