{
  "type": "Feature",
  "properties": {
    "iso:country":"IN",
    "ks:ks_name":"Kudna Pur",
    "ks:ks_pop":129,
    "ks:ks_type":"HABITATION",
    "name:eng_x_preferred":[
        "Kudna Pur"
    ],
    "wof:name":"Kudna Pur",
    "wof:placetype":"locality",
    "wof:population":129
},
  "geometry": {"coordinates":[80.07574700000001,27.423994],"type":"Point"}
}