{
  "type": "Feature",
  "properties": {
    "iso:country":"IN",
    "ks:ks_name":"Bas Kishnu",
    "ks:ks_pop":115,
    "ks:ks_type":"HABITATION",
    "name:eng_x_preferred":[
        "Bas Kishnu"
    ],
    "wof:name":"Bas Kishnu",
    "wof:placetype":"locality",
    "wof:population":115
},
  "geometry": {"coordinates":[78.033315,27.011118],"type":"Point"}
}