{
  "type": "Feature",
  "properties": {
    "iso:country":"IN",
    "ks:ks_alt_nam":"LOKHANDE WASTI",
    "ks:ks_name":"Lokhande Wasti",
    "ks:ks_pop":75,
    "ks:ks_type":"HABITATION",
    "name:eng_x_preferred":[
        "Lokhande Wasti"
    ],
    "wof:name":"Lokhande Wasti",
    "wof:placetype":"locality",
    "wof:population":75
},
  "geometry": {"coordinates":[75.14419700000001,16.931294],"type":"Point"}
}