{
  "type": "Feature",
  "properties": {
    "iso:country":"IN",
    "ks:ks_name":"Battucheruvu",
    "ks:ks_pop":994,
    "ks:ks_type":"HABITATION",
    "name:eng_x_preferred":[
        "Battucheruvu"
    ],
    "wof:name":"Battucheruvu",
    "wof:placetype":"locality",
    "wof:population":994
},
  "geometry": {"coordinates":[82.21283699999999,16.610264],"type":"Point"}
}