{
  "type": "Feature",
  "properties": {
    "gn:admin1_code":"12.0",
    "gn:admin2_code":"16.0",
    "gn:asciiname":"Khalheni",
    "gn:country_code":"IN",
    "gn:dem":1447,
    "gn:feature_class":"P",
    "gn:feature_code":"PPL",
    "gn:name":"Khalh\u0113ni",
    "gn:population":0,
    "gn:timezone":"Asia/Kolkata",
    "iso:country":"IN",
    "wof:name":"Khalheni",
    "wof:placetype":"locality"
},
  "geometry": {"coordinates":[75.62505,33.05749],"type":"Point"}
}