{
  "type": "Feature",
  "properties": {
    "iso:country":"IN",
    "ks:ks_name":"Sarkhadi",
    "ks:ks_pop":251,
    "ks:ks_type":"VILLAGE",
    "name:eng_x_preferred":[
        "Sarkhadi"
    ],
    "wof:name":"Sarkhadi",
    "wof:placetype":"locality",
    "wof:population":251
},
  "geometry": {"coordinates":[78.612616,23.373633],"type":"Point"}
}