{
  "type": "Feature",
  "properties": {
    "iso:country":"IN",
    "ks:ks_alt_nam":"Naw\u0101d\u012bh",
    "ks:ks_name":"Nawadih",
    "ks:ks_type":"VILLAGE",
    "ks:ks_uagg_main":0,
    "name:eng_x_preferred":[
        "Nawadih"
    ],
    "name:eng_x_variant":[
        "Naw\u0101d\u012bh"
    ],
    "wof:name":"Nawadih",
    "wof:placetype":"neighbourhood"
},
  "geometry": {"coordinates":[85.698469,23.130124],"type":"Point"}
}