{
  "type": "Feature",
  "properties": {
    "iso:country":"IN",
    "ks:ks_name":"Kanakikodi",
    "ks:ks_pop":498,
    "ks:ks_type":"HABITATION",
    "name:eng_x_preferred":[
        "Kanakikodi"
    ],
    "wof:name":"Kanakikodi",
    "wof:placetype":"locality",
    "wof:population":498
},
  "geometry": {"coordinates":[74.70734400000001,16.384881],"type":"Point"}
}