{
  "type": "Feature",
  "properties": {
    "iso:country":"IN",
    "ks:ks_name":"Adivasi Tola",
    "ks:ks_pop":103,
    "ks:ks_type":"HABITATION",
    "name:eng_x_preferred":[
        "Adivasi Tola"
    ],
    "wof:name":"Adivasi Tola",
    "wof:placetype":"locality",
    "wof:population":103
},
  "geometry": {"coordinates":[83.61641,24.254772],"type":"Point"}
}