{
  "type": "Feature",
  "properties": {
    "iso:country":"IN",
    "ks:ks_name":"Ayankeel Puliyangudi",
    "ks:ks_pop":270,
    "ks:ks_type":"HABITATION",
    "name:eng_x_preferred":[
        "Ayankeel Puliyangudi"
    ],
    "wof:name":"Ayankeel Puliyangudi",
    "wof:placetype":"locality",
    "wof:population":270
},
  "geometry": {"coordinates":[79.400188,11.416868],"type":"Point"}
}