{
  "type": "Feature",
  "properties": {
    "iso:country":"IN",
    "ks:ks_alt_nam":"NAIBAYAKAMI PARA",
    "ks:ks_name":"Naibayakami Para",
    "ks:ks_pop":366,
    "ks:ks_type":"HABITATION",
    "name:eng_x_preferred":[
        "Naibayakami Para"
    ],
    "wof:name":"Naibayakami Para",
    "wof:placetype":"locality",
    "wof:population":366
},
  "geometry": {"coordinates":[91.709659,23.88479],"type":"Point"}
}