{
  "type": "Feature",
  "properties": {
    "gn:admin1_code":"35",
    "gn:admin2_code":"453.0",
    "gn:asciiname":"Pandripani",
    "gn:country_code":"IN",
    "gn:dem":913,
    "gn:feature_class":"P",
    "gn:feature_code":"PPL",
    "gn:name":"Pandr\u012bp\u0101ni",
    "gn:population":0,
    "gn:timezone":"Asia/Kolkata",
    "iso:country":"IN",
    "ks:ks_name":"Pandari Pani",
    "ks:ks_pop":468,
    "ks:ks_type":"HABITATION",
    "name:eng_x_preferred":[
        "Pandari Pani"
    ],
    "name:eng_x_variant":[
        "Pandripani"
    ],
    "wof:name":"Pandari Pani",
    "wof:placetype":"locality",
    "wof:population":468
},
  "geometry": {"coordinates":[81.420185,22.490032],"type":"Point"}
}