{
  "type": "Feature",
  "properties": {
    "gn:admin1_code":"35",
    "gn:admin2_code":"466.0",
    "gn:asciiname":"Maujwari",
    "gn:country_code":"IN",
    "gn:dem":283,
    "gn:feature_class":"P",
    "gn:feature_code":"PPL",
    "gn:name":"Maujw\u0101ri",
    "gn:population":0,
    "gn:timezone":"Asia/Kolkata",
    "iso:country":"IN",
    "wof:name":"Maujwari",
    "wof:placetype":"neighbourhood"
},
  "geometry": {"coordinates":[76.7762,22.03438],"type":"Point"}
}