{
  "type": "Feature",
  "properties": {
    "iso:country":"IN",
    "ks:ks_name":"Maniram Ki Thar",
    "ks:ks_pop":82,
    "ks:ks_type":"HABITATION",
    "name:eng_x_preferred":[
        "Maniram Ki Thar"
    ],
    "wof:name":"Maniram Ki Thar",
    "wof:placetype":"locality",
    "wof:population":82
},
  "geometry": {"coordinates":[78.588183,26.831356],"type":"Point"}
}