{
  "type": "Feature",
  "properties": {
    "gn:admin1_code":"36",
    "gn:admin2_code":"187.0",
    "gn:asciiname":"Belaspur",
    "gn:country_code":"IN",
    "gn:dem":91,
    "gn:feature_class":"P",
    "gn:feature_code":"PPL",
    "gn:name":"Bel\u0101spur",
    "gn:population":0,
    "gn:timezone":"Asia/Kolkata",
    "iso:country":"IN",
    "name:msa_x_preferred":[
        "Belaspur"
    ],
    "wof:name":"Belaspur",
    "wof:placetype":"locality"
},
  "geometry": {"coordinates":[83.19379000000001,27.22498],"type":"Point"}
}