{
  "type": "Feature",
  "properties": {
    "gn:admin1_code":"34.0",
    "gn:admin2_code":"210.0",
    "gn:asciiname":"Mahesh Bathna",
    "gn:country_code":"IN",
    "gn:dem":52,
    "gn:feature_class":"P",
    "gn:feature_code":"PPL",
    "gn:name":"Mahesh Bathna",
    "gn:population":0,
    "gn:timezone":"Asia/Kolkata",
    "iso:country":"IN",
    "ks:ks_name":"Mahesh Bathna",
    "ks:ks_pop":192,
    "ks:ks_type":"VILLAGE",
    "name:eng_x_preferred":[
        "Mahesh Bathna"
    ],
    "wof:name":"Mahesh Bathna",
    "wof:placetype":"locality",
    "wof:population":192
},
  "geometry": {"coordinates":[87.93850999999999,26.147042],"type":"Point"}
}