{
  "type": "Feature",
  "properties": {
    "iso:country":"IN",
    "ks:ks_alt_nam":"Gorimillakunta tanda",
    "ks:ks_name":"Gorimillakunta Tanda",
    "ks:ks_pop":40,
    "ks:ks_type":"HABITATION",
    "name:eng_x_preferred":[
        "Gorimillakunta Tanda"
    ],
    "wof:name":"Gorimillakunta Tanda",
    "wof:placetype":"locality",
    "wof:population":40
},
  "geometry": {"coordinates":[77.97672900000001,16.497293],"type":"Point"}
}