{
  "type": "Feature",
  "properties": {
    "gn:admin1_code":"19",
    "gn:admin2_code":"568.0",
    "gn:asciiname":"Kelagina Golagodu",
    "gn:country_code":"IN",
    "gn:dem":609,
    "gn:feature_class":"P",
    "gn:feature_code":"PPL",
    "gn:name":"Kelagina Golagodu",
    "gn:population":0,
    "gn:timezone":"Asia/Kolkata",
    "iso:country":"IN",
    "ks:ks_name":"Kelagina Golagodu",
    "ks:ks_type":"VILLAGE",
    "name:eng_x_preferred":[
        "Kelagina Golagodu"
    ],
    "wof:name":"Kelagina Golagodu",
    "wof:placetype":"locality"
},
  "geometry": {"coordinates":[74.968121,14.164492],"type":"Point"}
}