{
  "type": "Feature",
  "properties": {
    "gn:admin1_code":"13.0",
    "gn:admin2_code":"589.0",
    "gn:asciiname":"Kannirod",
    "gn:country_code":"IN",
    "gn:dem":18,
    "gn:feature_class":"P",
    "gn:feature_code":"PPL",
    "gn:name":"Kannirod",
    "gn:population":0,
    "gn:timezone":"Asia/Kolkata",
    "iso:country":"IN",
    "ks:ks_name":"Kanhirod",
    "ks:ks_pop":13955,
    "ks:ks_type":"VILLAGE",
    "name:eng_x_preferred":[
        "Kanhirod"
    ],
    "name:eng_x_variant":[
        "Kannirod"
    ],
    "wof:name":"Kanhirod",
    "wof:placetype":"locality",
    "wof:population":13955
},
  "geometry": {"coordinates":[75.466312,11.89768],"type":"Point"}
}