{
  "type": "Feature",
  "properties": {
    "gn:admin1_code":"13.0",
    "gn:admin2_code":"589.0",
    "gn:asciiname":"Kannirod",
    "gn:country_code":"IN",
    "gn:dem":18,
    "gn:feature_class":"P",
    "gn:feature_code":"PPL",
    "gn:name":"Kannirod",
    "gn:population":0,
    "gn:timezone":"Asia/Kolkata",
    "iso:country":"IN",
    "wof:name":"Kannirod",
    "wof:placetype":"locality"
},
  "geometry": {"coordinates":[75.46473,11.91672],"type":"Point"}
}