{
  "type": "Feature",
  "properties": {
    "iso:country":"IN",
    "ks:ks_name":"Talwada",
    "ks:ks_pop":456,
    "ks:ks_type":"HABITATION",
    "name:eng_x_preferred":[
        "Talwada"
    ],
    "wof:name":"Talwada",
    "wof:placetype":"locality",
    "wof:population":456
},
  "geometry": {"coordinates":[80.136751,19.402669],"type":"Point"}
}