{
  "type": "Feature",
  "properties": {
    "gn:admin1_code":"37.0",
    "gn:admin2_code":"402.0",
    "gn:asciiname":"Sajbahar",
    "gn:country_code":"IN",
    "gn:dem":371,
    "gn:feature_class":"P",
    "gn:feature_code":"PPL",
    "gn:name":"Sajbahar",
    "gn:population":0,
    "gn:timezone":"Asia/Kolkata",
    "iso:country":"IN",
    "wof:name":"Sajbahar",
    "wof:placetype":"locality"
},
  "geometry": {"coordinates":[83.95855,22.5246],"type":"Point"}
}