{
  "type": "Feature",
  "properties": {
    "iso:country":"IN",
    "ks:ks_name":"Padiyadipalayampudur",
    "ks:ks_pop":152,
    "ks:ks_type":"HABITATION",
    "name:eng_x_preferred":[
        "Padiyadipalayampudur"
    ],
    "wof:name":"Padiyadipalayampudur",
    "wof:placetype":"locality",
    "wof:population":152
},
  "geometry": {"coordinates":[77.585489,11.006235],"type":"Point"}
}