{
  "type": "Feature",
  "properties": {
    "gn:admin1_code":"40",
    "gn:admin2_code":"539.0",
    "gn:asciiname":"Kodandaramapuram",
    "gn:country_code":"IN",
    "gn:dem":141,
    "gn:feature_class":"P",
    "gn:feature_code":"PPL",
    "gn:name":"Kodandar\u0101m\u0101puram",
    "gn:population":0,
    "gn:timezone":"Asia/Kolkata",
    "iso:country":"IN",
    "wof:name":"Kodandaramapuram",
    "wof:placetype":"locality"
},
  "geometry": {"coordinates":[79.90379,17.02572],"type":"Point"}
}