{
  "type": "Feature",
  "properties": {
    "iso:country":"IN",
    "ks:ks_alt_nam":"BOUDDHAWADI",
    "ks:ks_name":"Bouddhawadi",
    "ks:ks_pop":57,
    "ks:ks_type":"HABITATION",
    "name:eng_x_preferred":[
        "Bouddhawadi"
    ],
    "wof:name":"Bouddhawadi",
    "wof:placetype":"locality",
    "wof:population":57
},
  "geometry": {"coordinates":[73.51334199999999,16.75226],"type":"Point"}
}