{
  "type": "Feature",
  "properties": {
    "gn:admin1_code":"2.0",
    "gn:admin2_code":"554.0",
    "gn:asciiname":"Oratur",
    "gn:country_code":"IN",
    "gn:dem":21,
    "gn:feature_class":"P",
    "gn:feature_code":"PPL",
    "gn:name":"Orat\u016br",
    "gn:population":0,
    "gn:timezone":"Asia/Kolkata",
    "iso:country":"IN",
    "wof:name":"Oratur",
    "wof:placetype":"neighbourhood"
},
  "geometry": {"coordinates":[79.89955999999999,13.65165],"type":"Point"}
}