{
  "type": "Feature",
  "properties": {
    "iso:country":"IN",
    "ks:ks_name":"Badasikharapanga",
    "ks:ks_pop":53,
    "ks:ks_type":"VILLAGE",
    "name:eng_x_preferred":[
        "Badasikharapanga"
    ],
    "wof:name":"Badasikharapanga",
    "wof:placetype":"locality",
    "wof:population":53
},
  "geometry": {"coordinates":[84.62713100000001,20.193991],"type":"Point"}
}