{
  "type": "Feature",
  "properties": {
    "iso:country":"IN",
    "ks:ks_name":"Chandigarh Plot",
    "ks:ks_pop":151,
    "ks:ks_type":"HABITATION",
    "name:eng_x_preferred":[
        "Chandigarh Plot"
    ],
    "wof:name":"Chandigarh Plot",
    "wof:placetype":"locality",
    "wof:population":151
},
  "geometry": {"coordinates":[76.422939,30.159924],"type":"Point"}
}