{
  "type": "Feature",
  "properties": {
    "iso:country":"IN",
    "ks:ks_name":"Sabia",
    "ks:ks_pop":4269,
    "ks:ks_type":"VILLAGE",
    "ks:ks_uagg_main":0,
    "name:eng_x_preferred":[
        "Sabia"
    ],
    "wof:name":"Sabia",
    "wof:placetype":"neighbourhood",
    "wof:population":4269
},
  "geometry": {"coordinates":[83.919996,26.734143],"type":"Point"}
}