{
  "type": "Feature",
  "properties": {
    "gn:admin1_code":"35",
    "gn:admin2_code":"421.0",
    "gn:asciiname":"Khiria Sahib",
    "gn:country_code":"IN",
    "gn:dem":187,
    "gn:feature_class":"P",
    "gn:feature_code":"PPL",
    "gn:name":"Khiria S\u0101hib",
    "gn:population":0,
    "gn:timezone":"Asia/Kolkata",
    "iso:country":"IN",
    "wof:name":"Khiria Sahib",
    "wof:placetype":"locality"
},
  "geometry": {"coordinates":[78.72863000000002,25.68072],"type":"Point"}
}