{
  "type": "Feature",
  "properties": {
    "gn:admin1_code":"37.0",
    "gn:admin2_code":"414.0",
    "gn:asciiname":"Kilepal",
    "gn:country_code":"IN",
    "gn:dem":814,
    "gn:feature_class":"P",
    "gn:feature_code":"PPLL",
    "gn:name":"Kilep\u0101l",
    "gn:population":0,
    "gn:timezone":"Asia/Kolkata",
    "iso:country":"IN",
    "wof:name":"Kilepal",
    "wof:placetype":"locality"
},
  "geometry": {"coordinates":[81.70505,18.93193],"type":"Point"}
}