{
  "type": "Feature",
  "properties": {
    "iso:country":"IN",
    "ks:ks_name":"Balakapai",
    "ks:ks_pop":100,
    "ks:ks_type":"VILLAGE",
    "name:eng_x_preferred":[
        "Balakapai"
    ],
    "wof:name":"Balakapai",
    "wof:placetype":"locality",
    "wof:population":100
},
  "geometry": {"coordinates":[83.169701,19.263655],"type":"Point"}
}