{
  "type": "Feature",
  "properties": {
    "gn:admin1_code":"40.0",
    "gn:admin2_code":"537",
    "gn:asciiname":"Dundigal",
    "gn:country_code":"IN",
    "gn:dem":611,
    "gn:feature_class":"P",
    "gn:feature_code":"PPL",
    "gn:name":"Dundigal",
    "gn:population":0,
    "gn:timezone":"Asia/Kolkata",
    "iso:country":"IN",
    "name:und_x_variant":[
        "Dhundgol",
        "Dundigal"
    ],
    "wof:name":"Dundigal",
    "wof:placetype":"locality"
},
  "geometry": {"coordinates":[78.41461,17.60802],"type":"Point"}
}