{
  "type": "Feature",
  "properties": {
    "iso:country":"IN",
    "ks:ks_name":"Kevtan Purwa",
    "ks:ks_pop":294,
    "ks:ks_type":"HABITATION",
    "name:eng_x_preferred":[
        "Kevtan Purwa"
    ],
    "wof:name":"Kevtan Purwa",
    "wof:placetype":"locality",
    "wof:population":294
},
  "geometry": {"coordinates":[80.880971,25.402899],"type":"Point"}
}