{
  "type": "Feature",
  "properties": {
    "gn:admin1_code":"11.0",
    "gn:admin2_code":"32.0",
    "gn:asciiname":"Shilor Rangar",
    "gn:country_code":"IN",
    "gn:dem":1261,
    "gn:feature_class":"P",
    "gn:feature_code":"PPL",
    "gn:name":"Shilor Rangar",
    "gn:population":0,
    "gn:timezone":"Asia/Kolkata",
    "iso:country":"IN",
    "wof:name":"Shilor Rangar",
    "wof:placetype":"locality"
},
  "geometry": {"coordinates":[77.12699000000001,30.76435],"type":"Point"}
}