{
  "type": "Feature",
  "properties": {
    "iso:country":"IN",
    "ks:ks_name":"Bhalua Pahari",
    "ks:ks_pop":379,
    "ks:ks_type":"HABITATION",
    "name:eng_x_preferred":[
        "Bhalua Pahari"
    ],
    "wof:name":"Bhalua Pahari",
    "wof:placetype":"locality",
    "wof:population":379
},
  "geometry": {"coordinates":[86.23031899999999,24.006058],"type":"Point"}
}