{
  "type": "Feature",
  "properties": {
    "iso:country":"IN",
    "ks:ks_name":"Anantharajupuram",
    "ks:ks_pop":3487,
    "ks:ks_type":"VILLAGE",
    "ks:ks_uagg_main":0,
    "name:eng_x_preferred":[
        "Anantharajupuram"
    ],
    "wof:name":"Anantharajupuram",
    "wof:placetype":"neighbourhood",
    "wof:population":3487
},
  "geometry": {"coordinates":[79.06576699999999,14.745176],"type":"Point"}
}