{
  "type": "Feature",
  "properties": {
    "iso:country":"IN",
    "ks:ks_name":"Pandewadi",
    "ks:ks_pop":174,
    "ks:ks_type":"HABITATION",
    "name:eng_x_preferred":[
        "Pandewadi"
    ],
    "wof:name":"Pandewadi",
    "wof:placetype":"locality",
    "wof:population":174
},
  "geometry": {"coordinates":[75.28895799999999,18.821835],"type":"Point"}
}