{
  "type": "Feature",
  "properties": {
    "iso:country":"IN",
    "ks:ks_name":"Angarasingi",
    "ks:ks_pop":5,
    "ks:ks_type":"HABITATION",
    "name:eng_x_preferred":[
        "Angarasingi"
    ],
    "wof:name":"Angarasingi",
    "wof:placetype":"locality",
    "wof:population":5
},
  "geometry": {"coordinates":[84.11484900000001,18.75245],"type":"Point"}
}