{
  "type": "Feature",
  "properties": {
    "iso:country":"IN",
    "ks:ks_alt_nam":"Sayong Patir NC",
    "ks:ks_name":"Sayong Patir Nc",
    "ks:ks_pop":560,
    "ks:ks_type":"HABITATION",
    "name:eng_x_preferred":[
        "Sayong Patir Nc"
    ],
    "wof:name":"Sayong Patir Nc",
    "wof:placetype":"locality",
    "wof:population":560
},
  "geometry": {"coordinates":[93.878545,26.883659],"type":"Point"}
}