{
  "type": "Feature",
  "properties": {
    "gn:admin1_code":"2.0",
    "gn:admin2_code":"554.0",
    "gn:asciiname":"Kattaruvandlapalli",
    "gn:country_code":"IN",
    "gn:dem":576,
    "gn:feature_class":"P",
    "gn:feature_code":"PPL",
    "gn:name":"Kattaruv\u0101ndlapalli",
    "gn:population":0,
    "gn:timezone":"Asia/Kolkata",
    "iso:country":"IN",
    "ks:ks_name":"Kataruvandlapalle",
    "ks:ks_pop":99,
    "ks:ks_type":"HABITATION",
    "name:eng_x_preferred":[
        "Kataruvandlapalle"
    ],
    "name:eng_x_variant":[
        "Kattaruvandlapalli"
    ],
    "wof:name":"Kataruvandlapalle",
    "wof:placetype":"locality",
    "wof:population":99
},
  "geometry": {"coordinates":[79.112345,13.720273],"type":"Point"}
}