{
  "type": "Feature",
  "properties": {
    "iso:country":"IN",
    "ks:ks_name":"Dasarai",
    "ks:ks_pop":289,
    "ks:ks_type":"VILLAGE",
    "name:eng_x_preferred":[
        "Dasarai"
    ],
    "wof:name":"Dasarai",
    "wof:placetype":"locality",
    "wof:population":289
},
  "geometry": {"coordinates":[88.856071,25.325623],"type":"Point"}
}