{
  "type": "Feature",
  "properties": {
    "gn:admin1_code":"19.0",
    "gn:admin2_code":"571.0",
    "gn:asciiname":"Haleur",
    "gn:country_code":"IN",
    "gn:dem":703,
    "gn:feature_class":"P",
    "gn:feature_code":"PPL",
    "gn:name":"Hale\u016br",
    "gn:population":0,
    "gn:timezone":"Asia/Kolkata",
    "iso:country":"IN",
    "wof:name":"Haleur",
    "wof:placetype":"locality"
},
  "geometry": {"coordinates":[77.0184,12.84017],"type":"Point"}
}