{
  "type": "Feature",
  "properties": {
    "iso:country":"IN",
    "ks:ks_name":"Bhabanipur",
    "ks:ks_pop":78,
    "ks:ks_type":"VILLAGE",
    "name:eng_x_preferred":[
        "Bhabanipur"
    ],
    "wof:name":"Bhabanipur",
    "wof:placetype":"locality",
    "wof:population":78
},
  "geometry": {"coordinates":[87.536828,23.076211],"type":"Point"}
}