{
  "type": "Feature",
  "properties": {
    "iso:country":"IN",
    "ks:ks_name":"Thayyullathil Mukku",
    "ks:ks_pop":440,
    "ks:ks_type":"HABITATION",
    "ks:ks_uagg_main":0,
    "name:eng_x_preferred":[
        "Thayyullathil Mukku"
    ],
    "wof:name":"Thayyullathil Mukku",
    "wof:placetype":"neighbourhood",
    "wof:population":440
},
  "geometry": {"coordinates":[75.70793399999999,11.613565],"type":"Point"}
}