{
  "type": "Feature",
  "properties": {
    "iso:country":"IN",
    "ks:ks_name":"Alur Rampur",
    "ks:ks_pop":249,
    "ks:ks_type":"HABITATION",
    "name:eng_x_preferred":[
        "Alur Rampur"
    ],
    "wof:name":"Alur Rampur",
    "wof:placetype":"locality",
    "wof:population":249
},
  "geometry": {"coordinates":[75.88828599999999,16.314196],"type":"Point"}
}