{
  "type": "Feature",
  "properties": {
    "gn:admin1_code":"34.0",
    "gn:admin2_code":"221.0",
    "gn:asciiname":"Bazidpur",
    "gn:country_code":"IN",
    "gn:dem":53,
    "gn:feature_class":"P",
    "gn:feature_code":"PPL",
    "gn:name":"B\u0101zidpur",
    "gn:population":0,
    "gn:timezone":"Asia/Kolkata",
    "iso:country":"IN",
    "ks:ks_alt_nam":"B\u0101zidpur",
    "ks:ks_name":"Bazidpur",
    "ks:ks_pop":1839,
    "ks:ks_type":"VILLAGE",
    "name:ara_x_preferred":[
        "\u0628\u0627\u0632\u062f\u0628\u0648\u0631"
    ],
    "name:ben_bn_x_preferred":[
        "\u09ac\u09be\u099c\u09bf\u09a6\u09aa\u09c1\u09b0"
    ],
    "name:ben_in_x_preferred":[
        "\u09ac\u09be\u099c\u09bf\u09a6\u09aa\u09c1\u09b0"
    ],
    "name:eng_x_preferred":[
        "Bazidpur"
    ],
    "name:eng_x_variant":[
        "B\u0101zidpur"
    ],
    "name:fas_x_preferred":[
        "\u0628\u0627\u0632\u06cc\u062f\u067e\u0648\u0631"
    ],
    "name:guj_x_preferred":[
        "\u0aac\u0abe\u0a9d\u0abf\u0aa6\u0aaa\u0ac1\u0ab0"
    ],
    "name:hin_x_preferred":[
        "\u092c\u093e\u091c\u093f\u0926\u092a\u0941\u0930"
    ],
    "name:kan_x_preferred":[
        "\u0cac\u0c9c\u0cbf\u0ca6\u0ccd"
    ],
    "name:mal_x_preferred":[
        "\u0d2c\u0d3e\u0d38\u0d3f\u0d26\u0d4d"
    ],
    "name:mar_x_preferred":[
        "\u092c\u093e\u091c\u0940\u0926\u092a\u0942\u0930"
    ],
    "name:pan_x_preferred":[
        "\u0a2c\u0a1c\u0a3c\u0a40\u0a26\u0a2a\u0a41\u0a30"
    ],
    "name:tam_x_preferred":[
        "\u0baa\u0bbe\u0b9c\u0bbf\u0ba4\u0bcd\u0baa\u0bc2\u0bb0\u0bcd"
    ],
    "name:tel_x_preferred":[
        "\u0c2c\u0c1c\u0c40\u0c26\u0c4d"
    ],
    "name:urd_x_preferred":[
        "\u0628\u0627\u0632\u06cc\u062f \u067e\u0648\u0631"
    ],
    "wof:name":"Bazidpur",
    "wof:placetype":"locality",
    "wof:population":1839
},
  "geometry": {"coordinates":[85.747344,25.960183],"type":"Point"}
}