{
  "type": "Feature",
  "properties": {
    "iso:country":"IN",
    "ks:ks_name":"Ghumna",
    "ks:ks_pop":0,
    "ks:ks_type":"VILLAGE",
    "name:eng_x_preferred":[
        "Ghumna"
    ],
    "wof:name":"Ghumna",
    "wof:placetype":"locality",
    "wof:population":0
},
  "geometry": {"coordinates":[81.78085799999999,27.902401],"type":"Point"}
}