{
  "type": "Feature",
  "properties": {
    "iso:country":"IN",
    "ks:ks_name":"Neemri Bidawatan",
    "ks:ks_pop":130,
    "ks:ks_type":"VILLAGE",
    "name:eng_x_preferred":[
        "Neemri Bidawatan"
    ],
    "wof:name":"Neemri Bidawatan",
    "wof:placetype":"locality",
    "wof:population":130
},
  "geometry": {"coordinates":[74.521114,27.812481],"type":"Point"}
}