{
  "type": "Feature",
  "properties": {
    "iso:country":"IN",
    "ks:ks_name":"Ayyampatti",
    "ks:ks_pop":190,
    "ks:ks_type":"HABITATION",
    "name:eng_x_preferred":[
        "Ayyampatti"
    ],
    "wof:name":"Ayyampatti",
    "wof:placetype":"locality",
    "wof:population":190
},
  "geometry": {"coordinates":[78.232198,10.064595],"type":"Point"}
}