{
  "type": "Feature",
  "properties": {
    "gn:admin1_code":"38",
    "gn:admin2_code":"364.0",
    "gn:asciiname":"Tamar",
    "gn:country_code":"IN",
    "gn:dem":261,
    "gn:feature_class":"P",
    "gn:feature_code":"PPL",
    "gn:name":"Tam\u0101r",
    "gn:population":0,
    "gn:timezone":"Asia/Kolkata",
    "iso:country":"IN",
    "name:cat_x_preferred":[
        "Tamar"
    ],
    "name:ceb_x_preferred":[
        "Tamar"
    ],
    "name:ces_x_preferred":[
        "Tamar"
    ],
    "name:deu_x_preferred":[
        "Tamar"
    ],
    "name:fin_x_preferred":[
        "Tamar"
    ],
    "name:fra_x_preferred":[
        "Tamar"
    ],
    "name:heb_x_preferred":[
        "\u05ea\u05de\u05e8"
    ],
    "name:hun_x_preferred":[
        "Tamar"
    ],
    "name:ita_x_preferred":[
        "Tamar"
    ],
    "name:jpn_x_preferred":[
        "\u30bf\u30de\u30eb"
    ],
    "name:kor_x_preferred":[
        "\ud0c0\ub9c8\ub974"
    ],
    "name:nld_x_preferred":[
        "Tamar"
    ],
    "name:nor_x_preferred":[
        "Tamar"
    ],
    "name:nrm_x_preferred":[
        "Tamar"
    ],
    "name:pol_x_preferred":[
        "Tamar"
    ],
    "name:rus_x_preferred":[
        "\u0422\u0430\u043c\u0430\u0440"
    ],
    "name:slk_x_preferred":[
        "Tamar"
    ],
    "name:slv_x_preferred":[
        "Tamar"
    ],
    "name:spa_x_preferred":[
        "Tamar"
    ],
    "name:swe_x_preferred":[
        "Tamar"
    ],
    "name:ukr_x_preferred":[
        "\u0422\u0430\u043c\u0430\u0440"
    ],
    "wof:name":"Tamar",
    "wof:placetype":"locality"
},
  "geometry": {"coordinates":[85.64898000000002,23.04878],"type":"Point"}
}