{
  "type": "Feature",
  "properties": {
    "gn:admin1_code":"16",
    "gn:admin2_code":"503.0",
    "gn:asciiname":"Nazarpur",
    "gn:country_code":"IN",
    "gn:dem":374,
    "gn:feature_class":"P",
    "gn:feature_code":"PPL",
    "gn:name":"Nazarpur",
    "gn:population":0,
    "gn:timezone":"Asia/Kolkata",
    "iso:country":"IN",
    "name:und_x_variant":[
        "Mitz\u0101pur"
    ],
    "wof:name":"Nazarpur",
    "wof:placetype":"locality"
},
  "geometry": {"coordinates":[77.77359,21.23305],"type":"Point"}
}