{
  "type": "Feature",
  "properties": {
    "iso:country":"IN",
    "ks:ks_name":"K Dakuluguda Harijanpada",
    "ks:ks_pop":90,
    "ks:ks_type":"HABITATION",
    "name:eng_x_preferred":[
        "K Dakuluguda Harijanpada"
    ],
    "wof:name":"K Dakuluguda Harijanpada",
    "wof:placetype":"locality",
    "wof:population":90
},
  "geometry": {"coordinates":[83.53089,19.580922],"type":"Point"}
}