{
  "type": "Feature",
  "properties": {
    "iso:country":"IN",
    "ks:ks_alt_nam":"merangutu",
    "ks:ks_name":"Merangutu",
    "ks:ks_pop":179,
    "ks:ks_type":"HABITATION",
    "name:eng_x_preferred":[
        "Merangutu"
    ],
    "wof:name":"Merangutu",
    "wof:placetype":"locality",
    "wof:population":179
},
  "geometry": {"coordinates":[85.351202,22.862409],"type":"Point"}
}