{
  "type": "Feature",
  "properties": {
    "iso:country":"IN",
    "ks:ks_name":"Yadavwadi",
    "ks:ks_pop":287,
    "ks:ks_type":"VILLAGE",
    "name:eng_x_preferred":[
        "Yadavwadi"
    ],
    "wof:name":"Yadavwadi",
    "wof:placetype":"locality",
    "wof:population":287
},
  "geometry": {"coordinates":[74.182716,17.3887],"type":"Point"}
}