{
  "type": "Feature",
  "properties": {
    "gn:admin1_code":"36",
    "gn:admin2_code":"158.0",
    "gn:asciiname":"Pura Darshan Singh",
    "gn:country_code":"IN",
    "gn:dem":116,
    "gn:feature_class":"P",
    "gn:feature_code":"PPL",
    "gn:name":"Pura Darshan Singh",
    "gn:population":0,
    "gn:timezone":"Asia/Kolkata",
    "iso:country":"IN",
    "wof:name":"Pura Darshan Singh",
    "wof:placetype":"locality"
},
  "geometry": {"coordinates":[81.08951999999999,26.31038],"type":"Point"}
}