{
  "type": "Feature",
  "properties": {
    "iso:country":"IN",
    "ks:ks_name":"Geneshpur",
    "ks:ks_pop":725,
    "ks:ks_type":"VILLAGE",
    "name:eng_x_preferred":[
        "Geneshpur"
    ],
    "wof:name":"Geneshpur",
    "wof:placetype":"locality",
    "wof:population":725
},
  "geometry": {"coordinates":[82.480074,23.10924],"type":"Point"}
}