{
  "type": "Feature",
  "properties": {
    "iso:country":"IN",
    "ks:ks_name":"Kotakana",
    "ks:ks_pop":259,
    "ks:ks_type":"VILLAGE",
    "name:eng_x_preferred":[
        "Kotakana"
    ],
    "wof:name":"Kotakana",
    "wof:placetype":"locality",
    "wof:population":259
},
  "geometry": {"coordinates":[85.90478,20.316281],"type":"Point"}
}