{
  "type": "Feature",
  "properties": {
    "gn:admin1_code":"36.0",
    "gn:admin2_code":"202",
    "gn:asciiname":"Bhagwant Nagla",
    "gn:country_code":"IN",
    "gn:dem":156,
    "gn:feature_class":"P",
    "gn:feature_code":"PPL",
    "gn:name":"Bhagwant Nagla",
    "gn:population":0,
    "gn:timezone":"Asia/Kolkata",
    "iso:country":"IN",
    "wof:name":"Bhagwant Nagla",
    "wof:placetype":"locality"
},
  "geometry": {"coordinates":[79.08601999999998,27.83216],"type":"Point"}
}