{
  "type": "Feature",
  "properties": {
    "gn:admin1_code":"23.0",
    "gn:admin2_code":"49.0",
    "gn:asciiname":"Kaler",
    "gn:country_code":"IN",
    "gn:dem":235,
    "gn:feature_class":"P",
    "gn:feature_code":"PPL",
    "gn:name":"Kaler",
    "gn:population":0,
    "gn:timezone":"Asia/Kolkata",
    "iso:country":"IN",
    "name:ceb_x_preferred":[
        "Kaler"
    ],
    "name:hye_x_preferred":[
        "\u053f\u0561\u056c\u0565\u0580"
    ],
    "name:rus_x_preferred":[
        "\u041a\u0430\u043b\u0435\u0440"
    ],
    "wof:name":"Kaler",
    "wof:placetype":"locality"
},
  "geometry": {"coordinates":[75.22934000000002,31.56306],"type":"Point"}
}