{
  "type": "Feature",
  "properties": {
    "iso:country":"IN",
    "ks:ks_name":"Tilpukhuri",
    "ks:ks_pop":274,
    "ks:ks_type":"VILLAGE",
    "name:eng_x_preferred":[
        "Tilpukhuri"
    ],
    "wof:name":"Tilpukhuri",
    "wof:placetype":"locality",
    "wof:population":274
},
  "geometry": {"coordinates":[90.74602400000001,26.392917],"type":"Point"}
}