{
  "type": "Feature",
  "properties": {
    "iso:country":"IN",
    "ks:ks_name":"Pipalbandh",
    "ks:ks_pop":773,
    "ks:ks_type":"HABITATION",
    "name:eng_x_preferred":[
        "Pipalbandh"
    ],
    "wof:name":"Pipalbandh",
    "wof:placetype":"locality",
    "wof:population":773
},
  "geometry": {"coordinates":[83.188125,20.36095],"type":"Point"}
}