{
  "type": "Feature",
  "properties": {
    "gn:admin1_code":"36.0",
    "gn:admin2_code":"181.0",
    "gn:asciiname":"Neza",
    "gn:country_code":"IN",
    "gn:dem":117,
    "gn:feature_class":"P",
    "gn:feature_code":"PPL",
    "gn:name":"Neza",
    "gn:population":0,
    "gn:timezone":"Asia/Kolkata",
    "iso:country":"IN",
    "ks:ks_name":"Neza",
    "ks:ks_type":"VILLAGE",
    "name:eng_x_preferred":[
        "Neza"
    ],
    "wof:name":"Neza",
    "wof:placetype":"locality"
},
  "geometry": {"coordinates":[81.86340199999999,27.453748],"type":"Point"}
}