{
  "type": "Feature",
  "properties": {
    "gn:admin1_code":"6.0",
    "gn:admin2_code":"496",
    "gn:asciiname":"Chikhli",
    "gn:country_code":"IN",
    "gn:dem":54,
    "gn:feature_class":"P",
    "gn:feature_code":"PPL",
    "gn:name":"Chikhli",
    "gn:population":0,
    "gn:timezone":"Asia/Kolkata",
    "iso:country":"IN",
    "name:ben_x_preferred":[
        "\u099a\u09bf\u0996\u09b2\u09bf"
    ],
    "name:bpy_x_preferred":[
        "\u099a\u09bf\u0996\u09b2\u09bf"
    ],
    "name:ceb_x_preferred":[
        "Chikhli"
    ],
    "name:nld_x_preferred":[
        "Chikhli"
    ],
    "name:swe_x_preferred":[
        "Chikhli"
    ],
    "name:und_x_variant":[
        "Chicli",
        "Chikli",
        "Chikhli"
    ],
    "wof:name":"Chikhli",
    "wof:placetype":"locality"
},
  "geometry": {"coordinates":[73.01760999999998,20.18363],"type":"Point"}
}