{
  "type": "Feature",
  "properties": {
    "iso:country":"IN",
    "ks:ks_name":"Borwa",
    "ks:ks_pop":535,
    "ks:ks_type":"VILLAGE",
    "name:eng_x_preferred":[
        "Borwa"
    ],
    "wof:name":"Borwa",
    "wof:placetype":"locality",
    "wof:population":535
},
  "geometry": {"coordinates":[74.789602,23.190465],"type":"Point"}
}