{
  "type": "Feature",
  "properties": {
    "gn:admin1_code":"19.0",
    "gn:admin2_code":"570.0",
    "gn:asciiname":"Mavinaguni",
    "gn:country_code":"IN",
    "gn:dem":1143,
    "gn:feature_class":"P",
    "gn:feature_code":"PPL",
    "gn:name":"M\u0101vinaguni",
    "gn:population":0,
    "gn:timezone":"Asia/Kolkata",
    "iso:country":"IN",
    "ks:ks_name":"Mavinaguni",
    "ks:ks_pop":222,
    "ks:ks_type":"HABITATION",
    "name:eng_x_preferred":[
        "Mavinaguni"
    ],
    "wof:name":"Mavinaguni",
    "wof:placetype":"locality",
    "wof:population":222
},
  "geometry": {"coordinates":[75.65401,13.298053],"type":"Point"}
}