{
  "type": "Feature",
  "properties": {
    "iso:country":"IN",
    "ks:ks_alt_nam":"katakarwadi",
    "ks:ks_name":"Katakarwadi",
    "ks:ks_pop":30,
    "ks:ks_type":"HABITATION",
    "name:eng_x_preferred":[
        "Katakarwadi"
    ],
    "wof:name":"Katakarwadi",
    "wof:placetype":"locality",
    "wof:population":30
},
  "geometry": {"coordinates":[73.26345600000001,17.863781],"type":"Point"}
}