{
  "type": "Feature",
  "properties": {
    "gn:admin1_code":"12.0",
    "gn:asciiname":"Dehra",
    "gn:country_code":"IN",
    "gn:dem":752,
    "gn:feature_class":"P",
    "gn:feature_code":"PPL",
    "gn:name":"Dehra",
    "gn:population":0,
    "gn:timezone":"Asia/Kolkata",
    "iso:country":"IN",
    "wof:name":"Dehra",
    "wof:placetype":"locality"
},
  "geometry": {"coordinates":[74.08513000000001,33.21946],"type":"Point"}
}