{
  "type": "Feature",
  "properties": {
    "iso:country":"IN",
    "ks:ks_alt_nam":"GURAV WASTI",
    "ks:ks_name":"Gurav Wasti",
    "ks:ks_pop":60,
    "ks:ks_type":"HABITATION",
    "name:eng_x_preferred":[
        "Gurav Wasti"
    ],
    "wof:name":"Gurav Wasti",
    "wof:placetype":"locality",
    "wof:population":60
},
  "geometry": {"coordinates":[74.826864,17.222023],"type":"Point"}
}