{
  "type": "Feature",
  "properties": {
    "iso:country":"IN",
    "ks:ks_name":"Siddalingamnanadoddi",
    "ks:ks_pop":125,
    "ks:ks_type":"HABITATION",
    "name:eng_x_preferred":[
        "Siddalingamnanadoddi"
    ],
    "wof:name":"Siddalingamnanadoddi",
    "wof:placetype":"locality",
    "wof:population":125
},
  "geometry": {"coordinates":[77.593114,12.365618],"type":"Point"}
}