{
  "type": "Feature",
  "properties": {
    "iso:country":"IN",
    "ks:ks_name":"Neeland",
    "ks:ks_pop":1222,
    "ks:ks_type":"HABITATION",
    "name:eng_x_preferred":[
        "Neeland"
    ],
    "wof:name":"Neeland",
    "wof:placetype":"locality",
    "wof:population":1222
},
  "geometry": {"coordinates":[75.69532599999999,11.74111],"type":"Point"}
}