{
  "type": "Feature",
  "properties": {
    "iso:country":"IN",
    "ks:ks_name":"Kadnil",
    "ks:ks_pop":25,
    "ks:ks_type":"HABITATION",
    "name:eng_x_preferred":[
        "Kadnil"
    ],
    "wof:name":"Kadnil",
    "wof:placetype":"locality",
    "wof:population":25
},
  "geometry": {"coordinates":[82.817297,19.247416],"type":"Point"}
}