{
  "type": "Feature",
  "properties": {
    "gn:admin1_code":"24.0",
    "gn:admin2_code":"125.0",
    "gn:asciiname":"Chikhli",
    "gn:country_code":"IN",
    "gn:dem":209,
    "gn:feature_class":"P",
    "gn:feature_code":"PPL",
    "gn:name":"Ch\u012bkhli",
    "gn:population":0,
    "gn:timezone":"Asia/Kolkata",
    "iso:country":"IN",
    "name:ben_x_preferred":[
        "\u099a\u09bf\u0996\u09b2\u09bf"
    ],
    "name:bpy_x_preferred":[
        "\u099a\u09bf\u0996\u09b2\u09bf"
    ],
    "name:ceb_x_preferred":[
        "Chikhli"
    ],
    "name:hin_x_preferred":[
        "\u091a\u093f\u0916\u0932\u0940"
    ],
    "name:mar_x_preferred":[
        "\u091a\u093f\u0916\u0932\u0940"
    ],
    "name:nld_x_preferred":[
        "Chikhli"
    ],
    "name:swe_x_preferred":[
        "Chikhli"
    ],
    "wof:name":"Chikhli",
    "wof:placetype":"locality"
},
  "geometry": {"coordinates":[74.07049000000001,23.30732],"type":"Point"}
}