{
  "type": "Feature",
  "properties": {
    "gn:admin1_code":"19",
    "gn:admin2_code":"557.0",
    "gn:asciiname":"Otihal",
    "gn:country_code":"IN",
    "gn:dem":492,
    "gn:feature_class":"P",
    "gn:feature_code":"PPL",
    "gn:name":"Otih\u0101l",
    "gn:population":0,
    "gn:timezone":"Asia/Kolkata",
    "iso:country":"IN",
    "wof:name":"Otihal",
    "wof:placetype":"locality"
},
  "geometry": {"coordinates":[76.1422,16.89272],"type":"Point"}
}