{
  "type": "Feature",
  "properties": {
    "iso:country":"IN",
    "ks:ks_name":"Juvewadi",
    "ks:ks_pop":150,
    "ks:ks_type":"HABITATION",
    "name:eng_x_preferred":[
        "Juvewadi"
    ],
    "wof:name":"Juvewadi",
    "wof:placetype":"locality",
    "wof:population":150
},
  "geometry": {"coordinates":[73.28444399999999,17.445556],"type":"Point"}
}