{
  "type": "Feature",
  "properties": {
    "gn:admin1_code":"36",
    "gn:admin2_code":"154.0",
    "gn:asciiname":"Marela",
    "gn:country_code":"IN",
    "gn:dem":133,
    "gn:feature_class":"P",
    "gn:feature_code":"PPL",
    "gn:name":"Marela",
    "gn:population":0,
    "gn:timezone":"Asia/Kolkata",
    "iso:country":"IN",
    "name:ita_x_preferred":[
        "Marela"
    ],
    "name:msa_x_preferred":[
        "Marela"
    ],
    "name:spa_x_preferred":[
        "Mar\u00e9la"
    ],
    "wof:name":"Marela",
    "wof:placetype":"locality"
},
  "geometry": {"coordinates":[80.96795999999998,27.28289],"type":"Point"}
}