{
  "type": "Feature",
  "properties": {
    "gn:admin1_code":"36",
    "gn:admin2_code":"152.0",
    "gn:asciiname":"Gurha",
    "gn:country_code":"IN",
    "gn:dem":144,
    "gn:feature_class":"P",
    "gn:feature_code":"PPL",
    "gn:name":"Gurha",
    "gn:population":0,
    "gn:timezone":"Asia/Kolkata",
    "iso:country":"IN",
    "ks:ks_name":"Gurha",
    "ks:ks_pop":960,
    "ks:ks_type":"VILLAGE",
    "name:eng_x_preferred":[
        "Gurha"
    ],
    "wof:name":"Gurha",
    "wof:placetype":"locality",
    "wof:population":960
},
  "geometry": {"coordinates":[79.85961399999999,27.658253],"type":"Point"}
}