{
  "type": "Feature",
  "properties": {
    "iso:country":"IN",
    "ks:ks_name":"Yenugubayalu",
    "ks:ks_pop":1050,
    "ks:ks_type":"HABITATION",
    "name:eng_x_preferred":[
        "Yenugubayalu"
    ],
    "wof:name":"Yenugubayalu",
    "wof:placetype":"locality",
    "wof:population":1050
},
  "geometry": {"coordinates":[82.09362299999999,17.989656],"type":"Point"}
}