{
  "type": "Feature",
  "properties": {
    "gn:admin1_code":"36.0",
    "gn:admin2_code":"135.0",
    "gn:asciiname":"Bangar",
    "gn:country_code":"IN",
    "gn:dem":199,
    "gn:feature_class":"P",
    "gn:feature_code":"PPL",
    "gn:name":"B\u0101ngar",
    "gn:population":0,
    "gn:timezone":"Asia/Kolkata",
    "iso:country":"IN",
    "name:ceb_x_preferred":[
        "Bangar"
    ],
    "name:hin_x_preferred":[
        "\u092c\u093e\u0902\u0917\u0921"
    ],
    "name:ita_x_preferred":[
        "Bangar"
    ],
    "name:nld_x_preferred":[
        "Bangar"
    ],
    "name:por_x_preferred":[
        "Bangar"
    ],
    "name:rus_x_preferred":[
        "\u0411\u0430\u043d\u0433\u0430\u0440"
    ],
    "name:swe_x_preferred":[
        "Bangar"
    ],
    "name:und_x_variant":[
        "B\u0101ngar",
        "Is\u0101garh"
    ],
    "name:war_x_preferred":[
        "Bangar"
    ],
    "wof:name":"Bangar",
    "wof:placetype":"locality"
},
  "geometry": {"coordinates":[78.69126999999997,28.69878],"type":"Point"}
}