{
  "type": "Feature",
  "properties": {
    "iso:country":"IN",
    "ks:ks_name":"Indravas",
    "ks:ks_pop":395,
    "ks:ks_type":"VILLAGE",
    "name:eng_x_preferred":[
        "Indravas"
    ],
    "wof:name":"Indravas",
    "wof:placetype":"locality",
    "wof:population":395
},
  "geometry": {"coordinates":[71.04352799999999,25.651078],"type":"Point"}
}