{
  "type": "Feature",
  "properties": {
    "iso:country":"IN",
    "ks:ks_name":"Raghunathpur Bhelura",
    "ks:ks_pop":1417,
    "ks:ks_type":"HABITATION",
    "name:eng_x_preferred":[
        "Raghunathpur Bhelura"
    ],
    "wof:name":"Raghunathpur Bhelura",
    "wof:placetype":"locality",
    "wof:population":1417
},
  "geometry": {"coordinates":[84.961843,25.539836],"type":"Point"}
}