{
  "type": "Feature",
  "properties": {
    "gn:admin1_code":"24",
    "gn:admin2_code":"100.0",
    "gn:asciiname":"Surawala",
    "gn:country_code":"IN",
    "gn:dem":192,
    "gn:feature_class":"P",
    "gn:feature_code":"PPL",
    "gn:name":"Suraw\u0101la",
    "gn:population":0,
    "gn:timezone":"Asia/Kolkata",
    "iso:country":"IN",
    "wof:name":"Surawala",
    "wof:placetype":"neighbourhood"
},
  "geometry": {"coordinates":[74.54613999999999,29.5936],"type":"Point"}
}