{
  "type": "Feature",
  "properties": {
    "iso:country":"IN",
    "ks:ks_name":"Kolamguda",
    "ks:ks_pop":223,
    "ks:ks_type":"HABITATION",
    "name:eng_x_preferred":[
        "Kolamguda"
    ],
    "wof:name":"Kolamguda",
    "wof:placetype":"locality",
    "wof:population":223
},
  "geometry": {"coordinates":[79.08678,19.435972],"type":"Point"}
}