{
  "type": "Feature",
  "properties": {
    "gn:admin1_code":"11",
    "gn:admin2_code":"23.0",
    "gn:asciiname":"Gudhra",
    "gn:country_code":"IN",
    "gn:dem":1786,
    "gn:feature_class":"P",
    "gn:feature_code":"PPL",
    "gn:name":"Gudhra",
    "gn:population":0,
    "gn:timezone":"Asia/Kolkata",
    "iso:country":"IN",
    "wof:name":"Gudhra",
    "wof:placetype":"locality"
},
  "geometry": {"coordinates":[76.16876999999999,32.55840999999999],"type":"Point"}
}