{
  "type": "Feature",
  "properties": {
    "iso:country":"IN",
    "ks:ks_name":"Laxmipuram",
    "ks:ks_pop":106,
    "ks:ks_type":"HABITATION",
    "ks:ks_uagg_main":0,
    "name:eng_x_preferred":[
        "Laxmipuram"
    ],
    "wof:name":"Laxmipuram",
    "wof:placetype":"neighbourhood",
    "wof:population":106
},
  "geometry": {"coordinates":[78.973772,14.411951],"type":"Point"}
}