{
  "type": "Feature",
  "properties": {
    "gn:admin1_code":"23",
    "gn:admin2_code":"39.0",
    "gn:asciiname":"Chak Mandher",
    "gn:country_code":"IN",
    "gn:dem":244,
    "gn:feature_class":"P",
    "gn:feature_code":"PPL",
    "gn:name":"Chak Mandher",
    "gn:population":0,
    "gn:timezone":"Asia/Kolkata",
    "iso:country":"IN",
    "ks:ks_name":"Chak Mandher",
    "ks:ks_pop":723,
    "ks:ks_type":"VILLAGE",
    "name:eng_x_preferred":[
        "Chak Mandher"
    ],
    "wof:name":"Chak Mandher",
    "wof:placetype":"locality",
    "wof:population":723
},
  "geometry": {"coordinates":[75.85593799999999,31.208403],"type":"Point"}
}