{
  "type": "Feature",
  "properties": {
    "iso:country":"IN",
    "ks:ks_name":"Choukitanr",
    "ks:ks_pop":559,
    "ks:ks_type":"HABITATION",
    "name:eng_x_preferred":[
        "Choukitanr"
    ],
    "wof:name":"Choukitanr",
    "wof:placetype":"locality",
    "wof:population":559
},
  "geometry": {"coordinates":[85.090811,23.642167],"type":"Point"}
}