{
  "type": "Feature",
  "properties": {
    "iso:country":"IN",
    "ks:ks_name":"Malbahal",
    "ks:ks_pop":643,
    "ks:ks_type":"VILLAGE",
    "ks:ks_uagg_main":0,
    "name:eng_x_preferred":[
        "Malbahal"
    ],
    "wof:name":"Malbahal",
    "wof:placetype":"neighbourhood",
    "wof:population":643
},
  "geometry": {"coordinates":[86.893479,23.816934],"type":"Point"}
}