{
  "type": "Feature",
  "properties": {
    "iso:country":"IN",
    "ks:ks_name":"Lachka",
    "ks:ks_pop":1034,
    "ks:ks_type":"VILLAGE",
    "ks:ks_uagg_main":0,
    "name:eng_x_preferred":[
        "Lachka"
    ],
    "wof:name":"Lachka",
    "wof:placetype":"locality",
    "wof:population":1034
},
  "geometry": {"coordinates":[88.331318,26.733437],"type":"Point"}
}