{
  "type": "Feature",
  "properties": {
    "iso:country":"IN",
    "ks:ks_alt_nam":"4 BPM",
    "ks:ks_name":"4 Bpm",
    "ks:ks_pop":229,
    "ks:ks_type":"HABITATION",
    "name:eng_x_preferred":[
        "4 Bpm"
    ],
    "wof:name":"4 Bpm",
    "wof:placetype":"locality",
    "wof:population":229
},
  "geometry": {"coordinates":[73.527117,29.09077],"type":"Point"}
}