{
  "type": "Feature",
  "properties": {
    "gn:admin1_code":"23.0",
    "gn:admin2_code":"46.0",
    "gn:asciiname":"Mian",
    "gn:country_code":"IN",
    "gn:dem":205,
    "gn:feature_class":"P",
    "gn:feature_code":"PPL",
    "gn:name":"Mi\u0101n",
    "gn:population":0,
    "gn:timezone":"Asia/Kolkata",
    "iso:country":"IN",
    "name:ceb_x_preferred":[
        "Mian"
    ],
    "name:deu_x_preferred":[
        "Mian"
    ],
    "name:fra_x_preferred":[
        "Mian"
    ],
    "wof:name":"Mian",
    "wof:placetype":"locality"
},
  "geometry": {"coordinates":[74.8616,30.16351],"type":"Point"}
}