{
  "type": "Feature",
  "properties": {
    "iso:country":"IN",
    "ks:ks_name":"Ganpatpur",
    "ks:ks_pop":158,
    "ks:ks_type":"VILLAGE",
    "name:eng_x_preferred":[
        "Ganpatpur"
    ],
    "wof:name":"Ganpatpur",
    "wof:placetype":"locality",
    "wof:population":158
},
  "geometry": {"coordinates":[82.533367,22.980106],"type":"Point"}
}