{
  "type": "Feature",
  "properties": {
    "iso:country":"IN",
    "ks:ks_name":"Temjai Mandir",
    "ks:ks_pop":150,
    "ks:ks_type":"HABITATION",
    "name:eng_x_preferred":[
        "Temjai Mandir"
    ],
    "wof:name":"Temjai Mandir",
    "wof:placetype":"locality",
    "wof:population":150
},
  "geometry": {"coordinates":[74.22020000000001,18.429521],"type":"Point"}
}