{
  "type": "Feature",
  "properties": {
    "gn:admin1_code":"12.0",
    "gn:admin2_code":"7.0",
    "gn:asciiname":"Patlari",
    "gn:country_code":"IN",
    "gn:dem":928,
    "gn:feature_class":"P",
    "gn:feature_code":"PPL",
    "gn:name":"Patl\u0101ri",
    "gn:population":0,
    "gn:timezone":"Asia/Kolkata",
    "iso:country":"IN",
    "wof:name":"Patlari",
    "wof:placetype":"locality"
},
  "geometry": {"coordinates":[75.57845999999998,32.65215999999999],"type":"Point"}
}