{
  "type": "Feature",
  "properties": {
    "iso:country":"IN",
    "ks:ks_name":"Jagusama",
    "ks:ks_pop":9,
    "ks:ks_type":"VILLAGE",
    "name:eng_x_preferred":[
        "Jagusama"
    ],
    "wof:name":"Jagusama",
    "wof:placetype":"locality",
    "wof:population":9
},
  "geometry": {"coordinates":[87.410419,24.555376],"type":"Point"}
}