{
  "type": "Feature",
  "properties": {
    "iso:country":"IN",
    "ks:ks_alt_nam":"Misr\u0101dih",
    "ks:ks_name":"Misradih",
    "ks:ks_pop":71,
    "ks:ks_type":"VILLAGE",
    "ks:ks_uagg_main":0,
    "name:eng_x_preferred":[
        "Misradih"
    ],
    "name:eng_x_variant":[
        "Misr\u0101dih"
    ],
    "wof:name":"Misradih",
    "wof:placetype":"neighbourhood",
    "wof:population":71
},
  "geometry": {"coordinates":[86.218245,24.010122],"type":"Point"}
}