{
  "type": "Feature",
  "properties": {
    "iso:country":"IN",
    "ks:ks_name":"Jamdar Wasti",
    "ks:ks_pop":155,
    "ks:ks_type":"HABITATION",
    "name:eng_x_preferred":[
        "Jamdar Wasti"
    ],
    "wof:name":"Jamdar Wasti",
    "wof:placetype":"locality",
    "wof:population":155
},
  "geometry": {"coordinates":[74.714,18.091],"type":"Point"}
}