{
  "type": "Feature",
  "properties": {
    "iso:country":"IN",
    "ks:ks_alt_nam":"Karni singh nagar",
    "ks:ks_name":"Karni Singh Nagar",
    "ks:ks_pop":438,
    "ks:ks_type":"HABITATION",
    "name:eng_x_preferred":[
        "Karni Singh Nagar"
    ],
    "wof:name":"Karni Singh Nagar",
    "wof:placetype":"locality",
    "wof:population":438
},
  "geometry": {"coordinates":[72.457942,26.783592],"type":"Point"}
}