{
  "type": "Feature",
  "properties": {
    "iso:country":"IN",
    "ks:ks_name":"Kushumkut",
    "ks:ks_pop":22,
    "ks:ks_type":"HABITATION",
    "name:eng_x_preferred":[
        "Kushumkut"
    ],
    "wof:name":"Kushumkut",
    "wof:placetype":"locality",
    "wof:population":22
},
  "geometry": {"coordinates":[92.989761,24.643584],"type":"Point"}
}