{
  "type": "Feature",
  "properties": {
    "gn:admin1_code":"35",
    "gn:admin2_code":"450.0",
    "gn:asciiname":"Baghraj",
    "gn:country_code":"IN",
    "gn:dem":441,
    "gn:feature_class":"P",
    "gn:feature_code":"PPL",
    "gn:name":"Baghr\u0101j",
    "gn:population":0,
    "gn:timezone":"Asia/Kolkata",
    "iso:country":"IN",
    "wof:name":"Baghraj",
    "wof:placetype":"locality"
},
  "geometry": {"coordinates":[79.89946999999999,23.74582],"type":"Point"}
}