{
  "type": "Feature",
  "properties": {
    "iso:country":"IN",
    "ks:ks_name":"Babarayanagowdana Koppalu",
    "ks:ks_pop":145,
    "ks:ks_type":"HABITATION",
    "name:eng_x_preferred":[
        "Babarayanagowdana Koppalu"
    ],
    "wof:name":"Babarayanagowdana Koppalu",
    "wof:placetype":"locality",
    "wof:population":145
},
  "geometry": {"coordinates":[75.947791,13.17669],"type":"Point"}
}