{
  "type": "Feature",
  "properties": {
    "iso:country":"IN",
    "ks:ks_name":"Lakhimpuria",
    "ks:ks_pop":350,
    "ks:ks_type":"HABITATION",
    "name:eng_x_preferred":[
        "Lakhimpuria"
    ],
    "wof:name":"Lakhimpuria",
    "wof:placetype":"locality",
    "wof:population":350
},
  "geometry": {"coordinates":[95.73743399999999,27.824433],"type":"Point"}
}