{
  "type": "Feature",
  "properties": {
    "gn:admin1_code":"36",
    "gn:admin2_code":"172.0",
    "gn:asciiname":"Purain",
    "gn:country_code":"IN",
    "gn:dem":113,
    "gn:feature_class":"P",
    "gn:feature_code":"PPL",
    "gn:name":"Purain",
    "gn:population":0,
    "gn:timezone":"Asia/Kolkata",
    "iso:country":"IN",
    "name:pan_x_preferred":[
        "\u0a2a\u0a5c\u0a48\u0a23"
    ],
    "wof:name":"Purain",
    "wof:placetype":"locality"
},
  "geometry": {"coordinates":[81.18221,25.72865],"type":"Point"}
}