{
  "type": "Feature",
  "properties": {
    "iso:country":"IN",
    "ks:ks_alt_nam":"GHASPURAB",
    "ks:ks_name":"Ghaspurab",
    "ks:ks_pop":125,
    "ks:ks_type":"HABITATION",
    "name:eng_x_preferred":[
        "Ghaspurab"
    ],
    "wof:name":"Ghaspurab",
    "wof:placetype":"locality",
    "wof:population":125
},
  "geometry": {"coordinates":[81.375832,25.604348],"type":"Point"}
}