{
  "type": "Feature",
  "properties": {
    "iso:country":"IN",
    "ks:ks_name":"Veeri With Chak",
    "ks:ks_pop":1147,
    "ks:ks_type":"VILLAGE",
    "name:eng_x_preferred":[
        "Veeri With Chak"
    ],
    "wof:name":"Veeri With Chak",
    "wof:placetype":"locality",
    "wof:population":1147
},
  "geometry": {"coordinates":[73.76692,23.754413],"type":"Point"}
}