{
  "type": "Feature",
  "properties": {
    "iso:country":"IN",
    "ks:ks_name":"Erannanapalya",
    "ks:ks_pop":194,
    "ks:ks_type":"HABITATION",
    "name:eng_x_preferred":[
        "Erannanapalya"
    ],
    "wof:name":"Erannanapalya",
    "wof:placetype":"locality",
    "wof:population":194
},
  "geometry": {"coordinates":[76.352222,13.692778],"type":"Point"}
}