{
  "type": "Feature",
  "properties": {
    "iso:country":"IN",
    "ks:ks_name":"Bairakha",
    "ks:ks_pop":786,
    "ks:ks_type":"VILLAGE",
    "ks:ks_uagg_main":0,
    "name:eng_x_preferred":[
        "Bairakha"
    ],
    "wof:name":"Bairakha",
    "wof:placetype":"neighbourhood",
    "wof:population":786
},
  "geometry": {"coordinates":[86.33292299999999,20.022787],"type":"Point"}
}