{
  "type": "Feature",
  "properties": {
    "iso:country":"IN",
    "ks:ks_name":"Kantharikavala",
    "ks:ks_pop":515,
    "ks:ks_type":"HABITATION",
    "name:eng_x_preferred":[
        "Kantharikavala"
    ],
    "wof:name":"Kantharikavala",
    "wof:placetype":"locality",
    "wof:population":515
},
  "geometry": {"coordinates":[77.06976400000001,10.006146],"type":"Point"}
}