{
  "type": "Feature",
  "properties": {
    "gn:admin1_code":"40",
    "gn:admin2_code":"538.0",
    "gn:asciiname":"Kondonibhawi",
    "gn:country_code":"IN",
    "gn:dem":631,
    "gn:feature_class":"P",
    "gn:feature_code":"PPL",
    "gn:name":"Kondonibh\u0101wi",
    "gn:population":0,
    "gn:timezone":"Asia/Kolkata",
    "iso:country":"IN",
    "name:und_x_variant":[
        "Kondonibh\u0101wi",
        "Lakshmidevipalli"
    ],
    "wof:name":"Kondonibhawi",
    "wof:placetype":"locality"
},
  "geometry": {"coordinates":[78.03560999999998,17.01677],"type":"Point"}
}