{
  "type": "Feature",
  "properties": {
    "iso:country":"IN",
    "ks:ks_alt_nam":"PASIYAN",
    "ks:ks_name":"Pasiyan",
    "ks:ks_pop":89,
    "ks:ks_type":"HABITATION",
    "name:eng_x_preferred":[
        "Pasiyan"
    ],
    "wof:name":"Pasiyan",
    "wof:placetype":"locality",
    "wof:population":89
},
  "geometry": {"coordinates":[81.98396099999999,25.298723],"type":"Point"}
}