{
  "type": "Feature",
  "properties": {
    "gn:admin1_code":"35.0",
    "gn:admin2_code":"438",
    "gn:asciiname":"Datigaon",
    "gn:country_code":"IN",
    "gn:dem":539,
    "gn:feature_class":"P",
    "gn:feature_code":"PPL",
    "gn:name":"Datigaon",
    "gn:population":0,
    "gn:timezone":"Asia/Kolkata",
    "iso:country":"IN",
    "name:und_x_variant":[
        "Dattigaon"
    ],
    "wof:name":"Datigaon",
    "wof:placetype":"locality"
},
  "geometry": {"coordinates":[74.8537,22.72773],"type":"Point"}
}