{
  "type": "Feature",
  "properties": {
    "iso:country":"IN",
    "ks:ks_name":"Meerpura",
    "ks:ks_pop":51,
    "ks:ks_type":"HABITATION",
    "name:eng_x_preferred":[
        "Meerpura"
    ],
    "wof:name":"Meerpura",
    "wof:placetype":"locality",
    "wof:population":51
},
  "geometry": {"coordinates":[76.080472,24.147965],"type":"Point"}
}