{
  "type": "Feature",
  "properties": {
    "gn:admin1_code":"39",
    "gn:admin2_code":"66.0",
    "gn:asciiname":"Phaton",
    "gn:country_code":"IN",
    "gn:dem":289,
    "gn:feature_class":"P",
    "gn:feature_code":"PPL",
    "gn:name":"Ph\u0101ton",
    "gn:population":0,
    "gn:timezone":"Asia/Kolkata",
    "iso:country":"IN",
    "wof:name":"Phaton",
    "wof:placetype":"locality"
},
  "geometry": {"coordinates":[78.92509,29.38369],"type":"Point"}
}