{
  "type": "Feature",
  "properties": {
    "iso:country":"IN",
    "ks:ks_name":"Jainpur",
    "ks:ks_pop":509,
    "ks:ks_type":"HABITATION",
    "ks:ks_uagg_main":0,
    "name:eng_x_preferred":[
        "Jainpur"
    ],
    "wof:name":"Jainpur",
    "wof:placetype":"neighbourhood",
    "wof:population":509
},
  "geometry": {"coordinates":[80.731695,27.510684],"type":"Point"}
}