{
  "type": "Feature",
  "properties": {
    "gn:admin1_code":"12.0",
    "gn:admin2_code":"1.0",
    "gn:asciiname":"Kaeshu Thalyan",
    "gn:country_code":"IN",
    "gn:dem":1797,
    "gn:feature_class":"P",
    "gn:feature_code":"PPL",
    "gn:name":"K\u00e4shu Thalyan",
    "gn:population":0,
    "gn:timezone":"Asia/Kolkata",
    "iso:country":"IN",
    "wof:name":"Kaeshu Thalyan",
    "wof:placetype":"locality"
},
  "geometry": {"coordinates":[74.33296999999997,34.59133],"type":"Point"}
}