{
  "type": "Feature",
  "properties": {
    "gn:admin1_code":"39.0",
    "gn:admin2_code":"64.0",
    "gn:asciiname":"Oleni",
    "gn:country_code":"IN",
    "gn:dem":1162,
    "gn:feature_class":"P",
    "gn:feature_code":"PPL",
    "gn:name":"Oleni",
    "gn:population":0,
    "gn:timezone":"Asia/Kolkata",
    "iso:country":"IN",
    "ks:ks_name":"Oleni",
    "ks:ks_type":"VILLAGE",
    "name:ell_x_preferred":[
        "\u03a9\u03bb\u03ad\u03bd\u03b7 \u0397\u03bb\u03b5\u03af\u03b1\u03c2"
    ],
    "name:eng_x_preferred":[
        "Oleni"
    ],
    "name:fin_x_preferred":[
        "Ol\u00e9ni"
    ],
    "name:ita_x_preferred":[
        "Oleni"
    ],
    "name:nld_x_preferred":[
        "Oleni"
    ],
    "name:nno_x_preferred":[
        "Ol\u00e9ni"
    ],
    "name:ron_x_preferred":[
        "Oleni"
    ],
    "wof:name":"Oleni",
    "wof:placetype":"locality"
},
  "geometry": {"coordinates":[79.40613,29.829989],"type":"Point"}
}