{
  "type": "Feature",
  "properties": {
    "iso:country":"IN",
    "ks:ks_name":"Karlamal 1",
    "ks:ks_pop":160,
    "ks:ks_type":"VILLAGE",
    "name:eng_x_preferred":[
        "Karlamal 1"
    ],
    "wof:name":"Karlamal 1",
    "wof:placetype":"locality",
    "wof:population":160
},
  "geometry": {"coordinates":[82.241951,18.108398],"type":"Point"}
}