{
  "type": "Feature",
  "properties": {
    "iso:country":"IN",
    "ks:ks_name":"Parauti Upadhyay Basti",
    "ks:ks_pop":275,
    "ks:ks_type":"HABITATION",
    "name:eng_x_preferred":[
        "Parauti Upadhyay Basti"
    ],
    "wof:name":"Parauti Upadhyay Basti",
    "wof:placetype":"locality",
    "wof:population":275
},
  "geometry": {"coordinates":[82.31688699999999,25.200622],"type":"Point"}
}