{
  "type": "Feature",
  "properties": {
    "iso:country":"IN",
    "ks:ks_name":"Badamachhamara",
    "ks:ks_pop":11,
    "ks:ks_type":"VILLAGE",
    "name:eng_x_preferred":[
        "Badamachhamara"
    ],
    "wof:name":"Badamachhamara",
    "wof:placetype":"locality",
    "wof:population":11
},
  "geometry": {"coordinates":[86.101851,19.963725],"type":"Point"}
}