{
  "type": "Feature",
  "properties": {
    "gn:admin1_code":"36",
    "gn:admin2_code":"180.0",
    "gn:asciiname":"Bazar",
    "gn:country_code":"IN",
    "gn:dem":112,
    "gn:feature_class":"P",
    "gn:feature_code":"PPL",
    "gn:name":"B\u0101zar",
    "gn:population":0,
    "gn:timezone":"Asia/Kolkata",
    "iso:country":"IN",
    "name:aze_x_preferred":[
        "Bazar"
    ],
    "name:cat_x_preferred":[
        "Bazar"
    ],
    "name:ceb_x_preferred":[
        "Bazar"
    ],
    "name:eus_x_preferred":[
        "Bazar"
    ],
    "name:fra_x_preferred":[
        "Bazar"
    ],
    "name:glg_x_preferred":[
        "Bazar"
    ],
    "name:kat_x_preferred":[
        "\u10d1\u10d0\u10d6\u10d0\u10e0\u10d8"
    ],
    "name:nld_x_preferred":[
        "Bazar"
    ],
    "name:nor_x_preferred":[
        "Bazar"
    ],
    "name:ron_x_preferred":[
        "Bazar"
    ],
    "name:slv_x_preferred":[
        "Bazar"
    ],
    "name:spa_x_preferred":[
        "Bazar"
    ],
    "name:swe_x_preferred":[
        "Bazar"
    ],
    "wof:name":"Bazar",
    "wof:placetype":"locality"
},
  "geometry": {"coordinates":[81.53591999999998,27.25049000000001],"type":"Point"}
}