{
  "type": "Feature",
  "properties": {
    "iso:country":"IN",
    "name:eng_x_preferred":[
        "Kharadi"
    ],
    "qs:gn_adm0_cc":"IN",
    "qs:gn_local":1259229,
    "qs:gn_nam_loc":"Pune, Pune, Maharashtra, IN",
    "qs:gn_namadm1":"16",
    "qs:local_max":2969,
    "qs:local_sum":13446,
    "qs:localhoods":37,
    "qs:name":"Kharadi",
    "qs:name_adm0":"India",
    "qs:name_adm1":"Maharashtra",
    "qs:name_adm2":"Pune",
    "qs:name_local":"Pune",
    "qs:photo_max":39,
    "qs:photo_sum":84,
    "qs:placetype":"Suburb",
    "qs:quad_count":7,
    "qs:woe_adm0":23424848,
    "qs:woe_adm1":2345750,
    "qs:woe_adm2":12586544,
    "qs:woe_lau":0,
    "qs:woe_local":2295412,
    "qs:woe_ver":"7.10.0",
    "wof:lang":[
        "eng"
    ],
    "wof:name":"Kharadi",
    "wof:placetype":"neighbourhood"
},
  "geometry": {"coordinates":[73.94142585742139,18.55047365947191],"type":"Point"}
}