{
  "type": "Feature",
  "properties": {
    "iso:country":"IN",
    "ks:ks_name":"Anandapur",
    "ks:ks_pop":430,
    "ks:ks_type":"VILLAGE",
    "name:eng_x_preferred":[
        "Anandapur"
    ],
    "wof:name":"Anandapur",
    "wof:placetype":"locality",
    "wof:population":430
},
  "geometry": {"coordinates":[86.82629799999999,23.622548],"type":"Point"}
}