{
  "type": "Feature",
  "properties": {
    "iso:country":"IN",
    "ks:ks_alt_nam":"Gondahali vasti",
    "ks:ks_name":"Gondahali Vasti",
    "ks:ks_pop":289,
    "ks:ks_type":"HABITATION",
    "name:eng_x_preferred":[
        "Gondahali Vasti"
    ],
    "wof:name":"Gondahali Vasti",
    "wof:placetype":"locality",
    "wof:population":289
},
  "geometry": {"coordinates":[75.06466,16.906032],"type":"Point"}
}