{
  "type": "Feature",
  "properties": {
    "gn:admin1_code":"24.0",
    "gn:admin2_code":"112.0",
    "gn:asciiname":"Charanwas",
    "gn:country_code":"IN",
    "gn:dem":491,
    "gn:feature_class":"P",
    "gn:feature_code":"PPL",
    "gn:name":"Ch\u0101ranw\u0101s",
    "gn:population":0,
    "gn:timezone":"Asia/Kolkata",
    "iso:country":"IN",
    "wof:name":"Charanwas",
    "wof:placetype":"locality"
},
  "geometry": {"coordinates":[74.68276,26.65924],"type":"Point"}
}