{
  "type": "Feature",
  "properties": {
    "iso:country":"IN",
    "ks:ks_alt_nam":"satyachi wasti",
    "ks:ks_name":"Satyachi Wasti",
    "ks:ks_pop":140,
    "ks:ks_type":"HABITATION",
    "name:eng_x_preferred":[
        "Satyachi Wasti"
    ],
    "wof:name":"Satyachi Wasti",
    "wof:placetype":"locality",
    "wof:population":140
},
  "geometry": {"coordinates":[74.567228,18.944977],"type":"Point"}
}