{
  "type": "Feature",
  "properties": {
    "iso:country":"IN",
    "ks:ks_name":"Munnumukku",
    "ks:ks_pop":2813,
    "ks:ks_type":"HABITATION",
    "name:eng_x_preferred":[
        "Munnumukku"
    ],
    "wof:name":"Munnumukku",
    "wof:placetype":"locality",
    "wof:population":2813
},
  "geometry": {"coordinates":[76.653986,9.015574],"type":"Point"}
}