{
  "type": "Feature",
  "properties": {
    "iso:country":"IN",
    "ks:ks_name":"Commanding",
    "ks:ks_pop":2142,
    "ks:ks_type":"HABITATION",
    "name:eng_x_preferred":[
        "Commanding"
    ],
    "wof:name":"Commanding",
    "wof:placetype":"locality",
    "wof:population":2142
},
  "geometry": {"coordinates":[93.909965,26.033147],"type":"Point"}
}