{
  "type": "Feature",
  "properties": {
    "gn:admin1_code":"19.0",
    "gn:admin2_code":"579",
    "gn:asciiname":"Ijeri",
    "gn:country_code":"IN",
    "gn:dem":492,
    "gn:feature_class":"P",
    "gn:feature_code":"PPL",
    "gn:name":"Ijeri",
    "gn:population":0,
    "gn:timezone":"Asia/Kolkata",
    "iso:country":"IN",
    "wof:name":"Ijeri",
    "wof:placetype":"locality"
},
  "geometry": {"coordinates":[76.69958000000003,16.90934],"type":"Point"}
}