{
  "type": "Feature",
  "properties": {
    "gn:admin1_code":"12",
    "gn:admin2_code":"18.0",
    "gn:asciiname":"Wuchir",
    "gn:country_code":"IN",
    "gn:dem":3349,
    "gn:feature_class":"P",
    "gn:feature_code":"PPL",
    "gn:name":"Wuchir",
    "gn:population":0,
    "gn:timezone":"Asia/Kolkata",
    "iso:country":"IN",
    "wof:name":"Wuchir",
    "wof:placetype":"locality"
},
  "geometry": {"coordinates":[76.21005,33.25992],"type":"Point"}
}