{
  "type": "Feature",
  "properties": {
    "iso:country":"IN",
    "ks:ks_name":"Tupadih",
    "ks:ks_pop":360,
    "ks:ks_type":"HABITATION",
    "name:eng_x_preferred":[
        "Tupadih"
    ],
    "wof:name":"Tupadih",
    "wof:placetype":"locality",
    "wof:population":360
},
  "geometry": {"coordinates":[87.005805,24.797795],"type":"Point"}
}