{
  "type": "Feature",
  "properties": {
    "iso:country":"IN",
    "ks:ks_name":"Babhani",
    "ks:ks_pop":506,
    "ks:ks_type":"VILLAGE",
    "name:eng_x_preferred":[
        "Babhani"
    ],
    "wof:name":"Babhani",
    "wof:placetype":"locality",
    "wof:population":506
},
  "geometry": {"coordinates":[82.98124799999999,27.346044],"type":"Point"}
}