{
  "type": "Feature",
  "properties": {
    "iso:country":"IN",
    "ks:ks_name":"Garadwadi",
    "ks:ks_pop":189,
    "ks:ks_type":"HABITATION",
    "name:eng_x_preferred":[
        "Garadwadi"
    ],
    "wof:name":"Garadwadi",
    "wof:placetype":"locality",
    "wof:population":189
},
  "geometry": {"coordinates":[73.464167,19.779722],"type":"Point"}
}