{
  "type": "Feature",
  "properties": {
    "iso:country":"IN",
    "ks:ks_name":"Nayabahal",
    "ks:ks_pop":43,
    "ks:ks_type":"HABITATION",
    "name:eng_x_preferred":[
        "Nayabahal"
    ],
    "wof:name":"Nayabahal",
    "wof:placetype":"locality",
    "wof:population":43
},
  "geometry": {"coordinates":[86.432856,23.996772],"type":"Point"}
}