{
  "type": "Feature",
  "properties": {
    "gn:admin1_code":"30.0",
    "gn:admin2_code":"258.0",
    "gn:asciiname":"Roing",
    "gn:country_code":"IN",
    "gn:dem":403,
    "gn:feature_class":"P",
    "gn:feature_code":"PPL",
    "gn:name":"Roing",
    "gn:population":0,
    "gn:timezone":"Asia/Kolkata",
    "iso:country":"IN",
    "name:ben_x_preferred":[
        "\u09b0\u0987\u0982"
    ],
    "name:bpy_x_preferred":[
        "\u09b0\u0987\u0982"
    ],
    "name:fra_x_preferred":[
        "Roing"
    ],
    "name:guj_x_preferred":[
        "\u0ab0\u0acb\u0a87\u0aa8\u0acd\u0a97"
    ],
    "name:hin_x_preferred":[
        "\u0930\u094b\u0907\u0902\u0917"
    ],
    "name:ita_x_preferred":[
        "Roing"
    ],
    "name:mar_x_preferred":[
        "\u0930\u094b\u0907\u0902\u0917"
    ],
    "name:msa_x_preferred":[
        "Roing"
    ],
    "name:nld_x_preferred":[
        "Roing"
    ],
    "name:por_x_preferred":[
        "Roing"
    ],
    "name:rus_x_preferred":[
        "\u0420\u043e\u0438\u043d\u0433"
    ],
    "name:spa_x_preferred":[
        "Roing"
    ],
    "name:urd_x_preferred":[
        "\u0631\u0648\u06cc\u0646\u06af"
    ],
    "name:vie_x_preferred":[
        "Roing"
    ],
    "wof:name":"Roing",
    "wof:placetype":"locality"
},
  "geometry": {"coordinates":[95.84468,28.14318],"type":"Point"}
}