{
  "type": "Feature",
  "properties": {
    "iso:country":"IN",
    "ks:ks_name":"Igarji",
    "ks:ks_pop":140,
    "ks:ks_type":"HABITATION",
    "name:eng_x_preferred":[
        "Igarji"
    ],
    "wof:name":"Igarji",
    "wof:placetype":"locality",
    "wof:population":140
},
  "geometry": {"coordinates":[74.632946,14.246776],"type":"Point"}
}