{
  "type": "Feature",
  "properties": {
    "iso:country":"IN",
    "ks:ks_name":"Puliyamarathur",
    "ks:ks_pop":255,
    "ks:ks_type":"HABITATION",
    "name:eng_x_preferred":[
        "Puliyamarathur"
    ],
    "wof:name":"Puliyamarathur",
    "wof:placetype":"locality",
    "wof:population":255
},
  "geometry": {"coordinates":[79.112099,12.987281],"type":"Point"}
}