{
  "type": "Feature",
  "properties": {
    "gn:admin1_code":"12.0",
    "gn:admin2_code":"020",
    "gn:asciiname":"Gul",
    "gn:country_code":"IN",
    "gn:dem":1990,
    "gn:feature_class":"P",
    "gn:feature_code":"PPL",
    "gn:name":"G\u016bl",
    "gn:population":0,
    "gn:timezone":"Asia/Kolkata",
    "iso:country":"IN",
    "name:aze_x_preferred":[
        "G\u00fcl"
    ],
    "name:ceb_x_preferred":[
        "Gul"
    ],
    "name:deu_x_preferred":[
        "Gul"
    ],
    "name:epo_x_preferred":[
        "Gul"
    ],
    "name:fas_x_preferred":[
        "\u06af\u0644"
    ],
    "name:rus_x_preferred":[
        "\u0413\u044e\u043b\u044c"
    ],
    "name:swe_x_preferred":[
        "Gul"
    ],
    "name:und_x_variant":[
        "G\u016bl"
    ],
    "name:uzb_x_preferred":[
        "Gul"
    ],
    "wof:name":"Gul",
    "wof:placetype":"locality"
},
  "geometry": {"coordinates":[74.9987,33.27139],"type":"Point"}
}