{
  "type": "Feature",
  "properties": {
    "gn:admin1_code":"11.0",
    "gn:admin2_code":"33.0",
    "gn:asciiname":"Doi",
    "gn:country_code":"IN",
    "gn:dem":1441,
    "gn:feature_class":"P",
    "gn:feature_code":"PPL",
    "gn:name":"Doi",
    "gn:population":0,
    "gn:timezone":"Asia/Kolkata",
    "iso:country":"IN",
    "wof:name":"Doi",
    "wof:placetype":"locality"
},
  "geometry": {"coordinates":[77.57117,31.36873],"type":"Point"}
}