{
  "type": "Feature",
  "properties": {
    "iso:country":"IN",
    "ks:ks_name":"Swarka",
    "ks:ks_pop":96,
    "ks:ks_type":"HABITATION",
    "name:eng_x_preferred":[
        "Swarka"
    ],
    "wof:name":"Swarka",
    "wof:placetype":"locality",
    "wof:population":96
},
  "geometry": {"coordinates":[79.270216,30.207179],"type":"Point"}
}