{
  "type": "Feature",
  "properties": {
    "gn:admin1_code":"36.0",
    "gn:admin2_code":"160",
    "gn:asciiname":"Nagla Mahwa",
    "gn:country_code":"IN",
    "gn:dem":142,
    "gn:feature_class":"P",
    "gn:feature_code":"PPL",
    "gn:name":"Nagla Mahwa",
    "gn:population":0,
    "gn:timezone":"Asia/Kolkata",
    "iso:country":"IN",
    "ks:ks_name":"Nagla Mahuwa",
    "ks:ks_pop":196,
    "ks:ks_type":"HABITATION",
    "name:eng_x_preferred":[
        "Nagla Mahuwa"
    ],
    "name:eng_x_variant":[
        "Nagla Mahwa"
    ],
    "wof:name":"Nagla Mahuwa",
    "wof:placetype":"locality",
    "wof:population":196
},
  "geometry": {"coordinates":[79.499275,27.203131],"type":"Point"}
}