{
  "type": "Feature",
  "properties": {
    "iso:country":"IN",
    "ks:ks_alt_nam":"Orpa NV",
    "ks:ks_name":"Orpa Nv",
    "ks:ks_pop":566,
    "ks:ks_type":"HABITATION",
    "name:eng_x_preferred":[
        "Orpa Nv"
    ],
    "wof:name":"Orpa Nv",
    "wof:placetype":"locality",
    "wof:population":566
},
  "geometry": {"coordinates":[74.103889,21.707586],"type":"Point"}
}