{
  "type": "Feature",
  "properties": {
    "iso:country":"IN",
    "ks:ks_name":"Amakhoh Ryt.",
    "ks:ks_pop":438,
    "ks:ks_type":"VILLAGE",
    "name:eng_x_preferred":[
        "Amakhoh Ryt."
    ],
    "wof:name":"Amakhoh Ryt.",
    "wof:placetype":"locality",
    "wof:population":438
},
  "geometry": {"coordinates":[80.96050099999999,22.651531],"type":"Point"}
}