{
  "type": "Feature",
  "properties": {
    "iso:country":"IN",
    "ks:ks_name":"Kayalvaram",
    "ks:ks_pop":1045,
    "ks:ks_type":"HABITATION",
    "name:eng_x_preferred":[
        "Kayalvaram"
    ],
    "wof:name":"Kayalvaram",
    "wof:placetype":"locality",
    "wof:population":1045
},
  "geometry": {"coordinates":[76.53504100000001,8.967423],"type":"Point"}
}