{
  "type": "Feature",
  "properties": {
    "iso:country":"IN",
    "ks:ks_name":"Khuchidih",
    "ks:ks_pop":1197,
    "ks:ks_type":"VILLAGE",
    "name:eng_x_preferred":[
        "Khuchidih"
    ],
    "wof:name":"Khuchidih",
    "wof:placetype":"locality",
    "wof:population":1197
},
  "geometry": {"coordinates":[86.02605699999999,22.894281],"type":"Point"}
}