{
  "type": "Feature",
  "properties": {
    "gn:admin1_code":"9.0",
    "gn:admin2_code":"469.0",
    "gn:asciiname":"Bhatvas",
    "gn:country_code":"IN",
    "gn:dem":215,
    "gn:feature_class":"P",
    "gn:feature_code":"PPL",
    "gn:name":"Bh\u0101tv\u0101s",
    "gn:population":0,
    "gn:timezone":"Asia/Kolkata",
    "iso:country":"IN",
    "ks:ks_alt_nam":"Bh\u0101tv\u0101s",
    "ks:ks_name":"Bhatvas",
    "ks:ks_type":"VILLAGE",
    "name:eng_x_preferred":[
        "Bhatvas"
    ],
    "name:eng_x_variant":[
        "Bh\u0101tv\u0101s"
    ],
    "wof:name":"Bhatvas",
    "wof:placetype":"locality"
},
  "geometry": {"coordinates":[72.626992,24.079687],"type":"Point"}
}