{
  "type": "Feature",
  "properties": {
    "iso:country":"IN",
    "ks:ks_name":"Katwadwadi",
    "ks:ks_pop":480,
    "ks:ks_type":"HABITATION",
    "name:eng_x_preferred":[
        "Katwadwadi"
    ],
    "wof:name":"Katwadwadi",
    "wof:placetype":"locality",
    "wof:population":480
},
  "geometry": {"coordinates":[73.488891,16.10048],"type":"Point"}
}