{
  "type": "Feature",
  "properties": {
    "iso:country":"IN",
    "ks:ks_alt_nam":"Seetharampuram(Sr.Puram",
    "ks:ks_name":"Seetharampuram(sr.puram",
    "ks:ks_pop":91,
    "ks:ks_type":"HABITATION",
    "ks:ks_uagg_main":0,
    "name:eng_x_preferred":[
        "Seetharampuram(sr.puram"
    ],
    "wof:name":"Seetharampuram(sr.puram",
    "wof:placetype":"neighbourhood",
    "wof:population":91
},
  "geometry": {"coordinates":[79.307642,14.186594],"type":"Point"}
}