{
  "type": "Feature",
  "properties": {
    "iso:country":"IN",
    "ks:ks_name":"Majgaon",
    "ks:ks_pop":713,
    "ks:ks_type":"VILLAGE",
    "ks:ks_uagg_main":0,
    "name:eng_x_preferred":[
        "Majgaon"
    ],
    "wof:name":"Majgaon",
    "wof:placetype":"neighbourhood",
    "wof:population":713
},
  "geometry": {"coordinates":[94.04782899999999,27.191546],"type":"Point"}
}