{
  "type": "Feature",
  "properties": {
    "iso:country":"IN",
    "ks:ks_alt_nam":"CHAMAR TOLI",
    "ks:ks_name":"Chamar Toli",
    "ks:ks_pop":218,
    "ks:ks_type":"HABITATION",
    "name:eng_x_preferred":[
        "Chamar Toli"
    ],
    "wof:name":"Chamar Toli",
    "wof:placetype":"locality",
    "wof:population":218
},
  "geometry": {"coordinates":[84.711763,26.24595],"type":"Point"}
}