{
  "type": "Feature",
  "properties": {
    "iso:country":"IN",
    "ks:ks_name":"Dhirandeeh",
    "ks:ks_pop":138,
    "ks:ks_type":"HABITATION",
    "name:eng_x_preferred":[
        "Dhirandeeh"
    ],
    "wof:name":"Dhirandeeh",
    "wof:placetype":"locality",
    "wof:population":138
},
  "geometry": {"coordinates":[82.33987500000001,27.161118],"type":"Point"}
}