{
  "type": "Feature",
  "properties": {
    "gn:admin1_code":"38.0",
    "gn:admin2_code":"362.0",
    "gn:asciiname":"Amjhari",
    "gn:country_code":"IN",
    "gn:dem":122,
    "gn:feature_class":"P",
    "gn:feature_code":"PPL",
    "gn:name":"Amjhari",
    "gn:population":0,
    "gn:timezone":"Asia/Kolkata",
    "iso:country":"IN",
    "ks:ks_name":"Amjhari",
    "ks:ks_pop":288,
    "ks:ks_type":"VILLAGE",
    "name:eng_x_preferred":[
        "Amjhari"
    ],
    "wof:name":"Amjhari",
    "wof:placetype":"locality",
    "wof:population":288
},
  "geometry": {"coordinates":[87.565001,24.469369],"type":"Point"}
}