{
  "type": "Feature",
  "properties": {
    "gn:admin1_code":"36",
    "gn:admin2_code":"173.0",
    "gn:asciiname":"Bhat Purwa",
    "gn:country_code":"IN",
    "gn:dem":88,
    "gn:feature_class":"P",
    "gn:feature_code":"PPL",
    "gn:name":"Bhat Purwa",
    "gn:population":0,
    "gn:timezone":"Asia/Kolkata",
    "iso:country":"IN",
    "ks:ks_name":"Bhat Purwa",
    "ks:ks_pop":444,
    "ks:ks_type":"VILLAGE",
    "name:eng_x_preferred":[
        "Bhat Purwa"
    ],
    "wof:name":"Bhat Purwa",
    "wof:placetype":"locality",
    "wof:population":444
},
  "geometry": {"coordinates":[82.11065600000001,25.893885],"type":"Point"}
}