{
  "type": "Feature",
  "properties": {
    "iso:country":"IN",
    "ks:ks_alt_nam":"gadran",
    "ks:ks_name":"Gadran",
    "ks:ks_pop":202,
    "ks:ks_type":"HABITATION",
    "name:eng_x_preferred":[
        "Gadran"
    ],
    "wof:name":"Gadran",
    "wof:placetype":"locality",
    "wof:population":202
},
  "geometry": {"coordinates":[81.84249,25.58237],"type":"Point"}
}