{
  "type": "Feature",
  "properties": {
    "iso:country":"IN",
    "ks:ks_name":"Khata Khedi",
    "ks:ks_pop":561,
    "ks:ks_type":"VILLAGE",
    "name:eng_x_preferred":[
        "Khata Khedi"
    ],
    "wof:name":"Khata Khedi",
    "wof:placetype":"locality",
    "wof:population":561
},
  "geometry": {"coordinates":[77.558317,23.829935],"type":"Point"}
}