{
  "type": "Feature",
  "properties": {
    "gn:admin1_code":"16",
    "gn:admin2_code":"499.0",
    "gn:asciiname":"Vaghli",
    "gn:country_code":"IN",
    "gn:dem":314,
    "gn:feature_class":"P",
    "gn:feature_code":"PPL",
    "gn:name":"V\u0101ghli",
    "gn:population":0,
    "gn:timezone":"Asia/Kolkata",
    "iso:country":"IN",
    "name:und_x_variant":[
        "V\u0101ghli",
        "V\u0101ghh"
    ],
    "wof:name":"Vaghli",
    "wof:placetype":"neighbourhood"
},
  "geometry": {"coordinates":[75.1053,20.50809],"type":"Point"}
}