{
  "type": "Feature",
  "properties": {
    "iso:country":"IN",
    "ks:ks_name":"Sampesar",
    "ks:ks_pop":22,
    "ks:ks_type":"HABITATION",
    "name:eng_x_preferred":[
        "Sampesar"
    ],
    "wof:name":"Sampesar",
    "wof:placetype":"locality",
    "wof:population":22
},
  "geometry": {"coordinates":[74.82880400000001,14.810367],"type":"Point"}
}