{
  "type": "Feature",
  "properties": {
    "gn:admin1_code":"2.0",
    "gn:admin2_code":"544.0",
    "gn:asciiname":"Burugumetta",
    "gn:country_code":"IN",
    "gn:dem":724,
    "gn:feature_class":"P",
    "gn:feature_code":"PPL",
    "gn:name":"Burugumetta",
    "gn:population":0,
    "gn:timezone":"Asia/Kolkata",
    "iso:country":"IN",
    "wof:name":"Burugumetta",
    "wof:placetype":"locality"
},
  "geometry": {"coordinates":[82.39220999999998,18.27024],"type":"Point"}
}