{
  "type": "Feature",
  "properties": {
    "gn:admin1_code":"2.0",
    "gn:admin2_code":"544.0",
    "gn:asciiname":"Burugumetta",
    "gn:country_code":"IN",
    "gn:dem":724,
    "gn:feature_class":"P",
    "gn:feature_code":"PPL",
    "gn:name":"Burugumetta",
    "gn:population":0,
    "gn:timezone":"Asia/Kolkata",
    "iso:country":"IN",
    "ks:ks_name":"Burugumetta",
    "ks:ks_pop":83,
    "ks:ks_type":"HABITATION",
    "name:eng_x_preferred":[
        "Burugumetta"
    ],
    "wof:name":"Burugumetta",
    "wof:placetype":"locality",
    "wof:population":83
},
  "geometry": {"coordinates":[82.39292500000001,18.270869],"type":"Point"}
}