{
  "type": "Feature",
  "properties": {
    "gn:admin1_code":"40.0",
    "gn:admin2_code":"533.0",
    "gn:asciiname":"Srirampuram",
    "gn:country_code":"IN",
    "gn:dem":329,
    "gn:feature_class":"P",
    "gn:feature_code":"PPL",
    "gn:name":"Srir\u0101mpuram",
    "gn:population":0,
    "gn:timezone":"Asia/Kolkata",
    "iso:country":"IN",
    "ks:ks_alt_nam":"Srir\u0101mpuram",
    "ks:ks_alt_nam_2":"Srirampuram",
    "ks:ks_name":"Srirampur",
    "ks:ks_pop":0,
    "ks:ks_type":"VILLAGE",
    "name:eng_x_preferred":[
        "Srirampur"
    ],
    "name:eng_x_variant":[
        "Srirampuram",
        "Srir\u0101mpuram"
    ],
    "wof:name":"Srirampur",
    "wof:placetype":"locality",
    "wof:population":0
},
  "geometry": {"coordinates":[78.253345,18.937495],"type":"Point"}
}