{
  "type": "Feature",
  "properties": {
    "iso:country":"IN",
    "ks:ks_name":"Chakitwal",
    "ks:ks_pop":1417,
    "ks:ks_type":"HABITATION",
    "name:eng_x_preferred":[
        "Chakitwal"
    ],
    "wof:name":"Chakitwal",
    "wof:placetype":"locality",
    "wof:population":1417
},
  "geometry": {"coordinates":[85.199416,26.612666],"type":"Point"}
}