{
  "type": "Feature",
  "properties": {
    "gn:admin1_code":"2.0",
    "gn:admin2_code":"553.0",
    "gn:asciiname":"Brahmasamudram",
    "gn:country_code":"IN",
    "gn:dem":510,
    "gn:feature_class":"P",
    "gn:feature_code":"PPL",
    "gn:name":"Brahmasamudram",
    "gn:population":0,
    "gn:timezone":"Asia/Kolkata",
    "iso:country":"IN",
    "name:new_x_preferred":[
        "\u092c\u094d\u0930\u0939\u094d\u092e\u0938\u092e\u0941\u0926\u094d\u0930\u092e\u094d \u092e\u0923\u094d\u0921\u0932"
    ],
    "name:tam_x_preferred":[
        "\u0baa\u0bbf\u0bb0\u0bae\u0bcd\u0bae\u0b9a\u0bae\u0bc1\u0ba4\u0bcd\u0ba4\u0bbf\u0bb0\u0bae\u0bcd"
    ],
    "name:tel_x_preferred":[
        "\u0c2c\u0c4d\u0c30\u0c39\u0c4d\u0c2e\u0c38\u0c2e\u0c41\u0c26\u0c4d\u0c30\u0c02"
    ],
    "name:tgl_x_preferred":[
        "Brahmasamudram"
    ],
    "name:urd_x_preferred":[
        "\u0628\u0631\u06c1\u0645\u0627\u0633\u0645\u062f\u0631\u0645"
    ],
    "wof:name":"Brahmasamudram",
    "wof:placetype":"locality"
},
  "geometry": {"coordinates":[76.94750999999999,14.53798],"type":"Point"}
}