{
  "type": "Feature",
  "properties": {
    "iso:country":"IN",
    "ks:ks_name":"Kotambi",
    "ks:ks_pop":542,
    "ks:ks_type":"VILLAGE",
    "name:eng_x_preferred":[
        "Kotambi"
    ],
    "wof:name":"Kotambi",
    "wof:placetype":"locality",
    "wof:population":542
},
  "geometry": {"coordinates":[73.49960400000001,20.419716],"type":"Point"}
}