{
  "type": "Feature",
  "properties": {
    "iso:country":"IN",
    "ks:ks_name":"Dhanupooja",
    "ks:ks_pop":234,
    "ks:ks_type":"HABITATION",
    "name:eng_x_preferred":[
        "Dhanupooja"
    ],
    "wof:name":"Dhanupooja",
    "wof:placetype":"locality",
    "wof:population":234
},
  "geometry": {"coordinates":[74.987075,12.924667],"type":"Point"}
}