{
  "type": "Feature",
  "properties": {
    "iso:country":"IN",
    "ks:ks_name":"Markande",
    "ks:ks_type":"VILLAGE",
    "name:eng_x_preferred":[
        "Markande"
    ],
    "wof:name":"Markande",
    "wof:placetype":"locality"
},
  "geometry": {"coordinates":[75.390191,14.183765],"type":"Point"}
}