{
  "type": "Feature",
  "properties": {
    "gn:admin1_code":"16",
    "gn:admin2_code":"521.0",
    "gn:asciiname":"Shikrapur",
    "gn:country_code":"IN",
    "gn:dem":579,
    "gn:feature_class":"P",
    "gn:feature_code":"PPL",
    "gn:name":"Shikrapur",
    "gn:population":0,
    "gn:timezone":"Asia/Kolkata",
    "iso:country":"IN",
    "name:ceb_x_preferred":[
        "Shikrapur"
    ],
    "name:swe_x_preferred":[
        "Shikrapur"
    ],
    "wof:name":"Shikrapur",
    "wof:placetype":"locality"
},
  "geometry": {"coordinates":[74.13813,18.69355],"type":"Point"}
}