{
  "type": "Feature",
  "properties": {
    "iso:country":"IN",
    "ks:ks_name":"Nangarsahi",
    "ks:ks_pop":714,
    "ks:ks_type":"VILLAGE",
    "name:eng_x_preferred":[
        "Nangarsahi"
    ],
    "wof:name":"Nangarsahi",
    "wof:placetype":"locality",
    "wof:population":714
},
  "geometry": {"coordinates":[87.254336,21.83764],"type":"Point"}
}