{
  "type": "Feature",
  "properties": {
    "iso:country":"IN",
    "ks:ks_alt_nam":"Harijan basti 2",
    "ks:ks_name":"Harijan Basti 2",
    "ks:ks_pop":302,
    "ks:ks_type":"HABITATION",
    "name:eng_x_preferred":[
        "Harijan Basti 2"
    ],
    "wof:name":"Harijan Basti 2",
    "wof:placetype":"locality",
    "wof:population":302
},
  "geometry": {"coordinates":[82.979387,25.520694],"type":"Point"}
}