{
  "type": "Feature",
  "properties": {
    "iso:country":"IN",
    "ks:ks_name":"Kadwali Khurd",
    "ks:ks_pop":289,
    "ks:ks_type":"VILLAGE",
    "name:eng_x_preferred":[
        "Kadwali Khurd"
    ],
    "wof:name":"Kadwali Khurd",
    "wof:placetype":"locality",
    "wof:population":289
},
  "geometry": {"coordinates":[74.694097,23.259908],"type":"Point"}
}