{
  "type": "Feature",
  "properties": {
    "gn:admin1_code":"35",
    "gn:admin2_code":"425.0",
    "gn:asciiname":"Dibiyapurwa",
    "gn:country_code":"IN",
    "gn:dem":213,
    "gn:feature_class":"P",
    "gn:feature_code":"PPL",
    "gn:name":"Dibiy\u0101purwa",
    "gn:population":0,
    "gn:timezone":"Asia/Kolkata",
    "iso:country":"IN",
    "ks:ks_name":"Diviya Purwa",
    "ks:ks_pop":267,
    "ks:ks_type":"HABITATION",
    "name:eng_x_preferred":[
        "Diviya Purwa"
    ],
    "name:eng_x_variant":[
        "Dibiyapurwa"
    ],
    "wof:name":"Diviya Purwa",
    "wof:placetype":"locality",
    "wof:population":267
},
  "geometry": {"coordinates":[79.94884999999999,24.882222],"type":"Point"}
}