{
  "type": "Feature",
  "properties": {
    "iso:country":"IN",
    "ks:ks_name":"Barkatoli",
    "ks:ks_pop":353,
    "ks:ks_type":"HABITATION",
    "name:eng_x_preferred":[
        "Barkatoli"
    ],
    "wof:name":"Barkatoli",
    "wof:placetype":"locality",
    "wof:population":353
},
  "geometry": {"coordinates":[85.01022399999999,22.874909],"type":"Point"}
}