{
  "type": "Feature",
  "properties": {
    "gn:admin1_code":"16",
    "gn:admin2_code":"511.0",
    "gn:asciiname":"Hadoli",
    "gn:country_code":"IN",
    "gn:dem":436,
    "gn:feature_class":"P",
    "gn:feature_code":"PPL",
    "gn:name":"Hadoli",
    "gn:population":0,
    "gn:timezone":"Asia/Kolkata",
    "iso:country":"IN",
    "wof:name":"Hadoli",
    "wof:placetype":"locality"
},
  "geometry": {"coordinates":[77.11004,18.87874],"type":"Point"}
}