{
  "type": "Feature",
  "properties": {
    "gn:admin1_code":"19.0",
    "gn:admin2_code":"564.0",
    "gn:asciiname":"Katenhalli",
    "gn:country_code":"IN",
    "gn:dem":669,
    "gn:feature_class":"P",
    "gn:feature_code":"PPL",
    "gn:name":"K\u0101tenhalli",
    "gn:population":0,
    "gn:timezone":"Asia/Kolkata",
    "iso:country":"IN",
    "wof:name":"Katenhalli",
    "wof:placetype":"locality"
},
  "geometry": {"coordinates":[75.42031999999998,14.59958],"type":"Point"}
}