{
  "type": "Feature",
  "properties": {
    "gn:admin1_code":"34.0",
    "gn:admin2_code":"221.0",
    "gn:asciiname":"Khatuaha",
    "gn:country_code":"IN",
    "gn:dem":50,
    "gn:feature_class":"P",
    "gn:feature_code":"PPL",
    "gn:name":"Khatu\u0101ha",
    "gn:population":0,
    "gn:timezone":"Asia/Kolkata",
    "iso:country":"IN",
    "wof:name":"Khatuaha",
    "wof:placetype":"locality"
},
  "geometry": {"coordinates":[85.90799,25.88093],"type":"Point"}
}