{
  "type": "Feature",
  "properties": {
    "iso:country":"IN",
    "ks:ks_name":"Dihwa",
    "ks:ks_pop":170,
    "ks:ks_type":"HABITATION",
    "ks:ks_uagg_main":0,
    "name:eng_x_preferred":[
        "Dihwa"
    ],
    "wof:name":"Dihwa",
    "wof:placetype":"neighbourhood",
    "wof:population":170
},
  "geometry": {"coordinates":[82.04049999999999,25.76472],"type":"Point"}
}