{
  "type": "Feature",
  "properties": {
    "iso:country":"IN",
    "ks:ks_name":"Barki",
    "ks:ks_pop":80,
    "ks:ks_type":"HABITATION",
    "name:eng_x_preferred":[
        "Barki"
    ],
    "wof:name":"Barki",
    "wof:placetype":"locality",
    "wof:population":80
},
  "geometry": {"coordinates":[83.819909,24.577977],"type":"Point"}
}