{
  "type": "Feature",
  "properties": {
    "iso:country":"IN",
    "ks:ks_name":"Bhusar",
    "ks:ks_pop":48,
    "ks:ks_type":"VILLAGE",
    "name:eng_x_preferred":[
        "Bhusar"
    ],
    "wof:name":"Bhusar",
    "wof:placetype":"locality",
    "wof:population":48
},
  "geometry": {"coordinates":[86.006154,24.153423],"type":"Point"}
}