{
  "type": "Feature",
  "properties": {
    "iso:country":"IN",
    "ks:ks_alt_nam":"PV 51-52 Jaipur",
    "ks:ks_name":"Pv 51-52 Jaipur",
    "ks:ks_pop":1106,
    "ks:ks_type":"HABITATION",
    "name:eng_x_preferred":[
        "Pv 51-52 Jaipur"
    ],
    "wof:name":"Pv 51-52 Jaipur",
    "wof:placetype":"locality",
    "wof:population":1106
},
  "geometry": {"coordinates":[80.60596700000001,20.159564],"type":"Point"}
}