{
  "type": "Feature",
  "properties": {
    "iso:country":"IN",
    "ks:ks_name":"Bizala",
    "ks:ks_pop":1212,
    "ks:ks_type":"HABITATION",
    "name:eng_x_preferred":[
        "Bizala"
    ],
    "wof:name":"Bizala",
    "wof:placetype":"locality",
    "wof:population":1212
},
  "geometry": {"coordinates":[78.368594,26.854155],"type":"Point"}
}