{
  "type": "Feature",
  "properties": {
    "iso:country":"IN",
    "ks:ks_name":"51000 RD",
    "ks:ks_pop":366,
    "ks:ks_type":"VILLAGE",
    "name:eng_x_preferred":[
        "51000 RD"
    ],
    "wof:name":"51000 RD",
    "wof:placetype":"locality",
    "wof:population":366
},
  "geometry": {"coordinates":[74.229525,29.369622],"type":"Point"}
}