{
  "type": "Feature",
  "properties": {
    "gn:admin1_code":"40.0",
    "gn:admin2_code":"538.0",
    "gn:asciiname":"Chinnapadu",
    "gn:country_code":"IN",
    "gn:dem":301,
    "gn:feature_class":"P",
    "gn:feature_code":"PPL",
    "gn:name":"Chinnap\u0101du",
    "gn:population":0,
    "gn:timezone":"Asia/Kolkata",
    "iso:country":"IN",
    "wof:name":"Chinnapadu",
    "wof:placetype":"locality"
},
  "geometry": {"coordinates":[77.95673000000002,15.94642],"type":"Point"}
}