{
  "type": "Feature",
  "properties": {
    "gn:admin1_code":"11.0",
    "gn:admin2_code":"32.0",
    "gn:asciiname":"Kandon",
    "gn:country_code":"IN",
    "gn:dem":1418,
    "gn:feature_class":"P",
    "gn:feature_code":"PPL",
    "gn:name":"K\u0101ndon",
    "gn:population":0,
    "gn:timezone":"Asia/Kolkata",
    "iso:country":"IN",
    "wof:name":"Kandon",
    "wof:placetype":"locality"
},
  "geometry": {"coordinates":[77.71672,30.70892000000001],"type":"Point"}
}