{
  "type": "Feature",
  "properties": {
    "iso:country":"IN",
    "name:ceb_x_preferred":[
        "P\u016bndi"
    ],
    "name:swe_x_preferred":[
        "P\u016bndi"
    ],
    "qs:name":"Poondi",
    "qs:name_adm0":"India",
    "qs:name_adm1":"Tamil Nadu",
    "qs:photos":15,
    "qs:photos_1k":3,
    "qs:photos_9k":1,
    "qs:photos_9r":1,
    "qs:photos_all":15,
    "qs:photos_sr":1,
    "qs:placetype":"Town",
    "qs:pop_sr":"0",
    "wd:wordcount":58,
    "wof:name":"Poondi",
    "wof:placetype":"locality"
},
  "geometry": {"coordinates":[79.874897,13.208027],"type":"Point"}
}