{
  "type": "Feature",
  "properties": {
    "iso:country":"IN",
    "ks:ks_name":"Belpukhuria",
    "ks:ks_pop":0,
    "ks:ks_type":"VILLAGE",
    "name:eng_x_preferred":[
        "Belpukhuria"
    ],
    "wof:name":"Belpukhuria",
    "wof:placetype":"locality",
    "wof:population":0
},
  "geometry": {"coordinates":[88.87267199999999,25.335141],"type":"Point"}
}