{
  "type": "Feature",
  "properties": {
    "iso:country":"IN",
    "ks:ks_alt_nam":"PACHUA   BRAL MIN TOLA",
    "ks:ks_name":"Pachua Bral Min Tola",
    "ks:ks_pop":900,
    "ks:ks_type":"HABITATION",
    "name:eng_x_preferred":[
        "Pachua Bral Min Tola"
    ],
    "name:eng_x_variant":[
        "PACHUA   BRAL MIN TOLA"
    ],
    "wof:name":"Pachua Bral Min Tola",
    "wof:placetype":"locality",
    "wof:population":900
},
  "geometry": {"coordinates":[84.48350000000001,26.0166],"type":"Point"}
}