{
  "type": "Feature",
  "properties": {
    "iso:country":"IN",
    "ks:ks_name":"Katnamane",
    "ks:ks_pop":249,
    "ks:ks_type":"HABITATION",
    "name:eng_x_preferred":[
        "Katnamane"
    ],
    "wof:name":"Katnamane",
    "wof:placetype":"locality",
    "wof:population":249
},
  "geometry": {"coordinates":[75.906667,12.818889],"type":"Point"}
}