{
  "type": "Feature",
  "properties": {
    "iso:country":"IN",
    "ks:ks_name":"Muthuramalingapatti",
    "ks:ks_pop":351,
    "ks:ks_type":"HABITATION",
    "name:eng_x_preferred":[
        "Muthuramalingapatti"
    ],
    "wof:name":"Muthuramalingapatti",
    "wof:placetype":"locality",
    "wof:population":351
},
  "geometry": {"coordinates":[78.58411099999999,9.450226],"type":"Point"}
}