{
  "type": "Feature",
  "properties": {
    "gn:admin1_code":"16",
    "gn:admin2_code":"506.0",
    "gn:asciiname":"Khodgaon",
    "gn:country_code":"IN",
    "gn:dem":257,
    "gn:feature_class":"P",
    "gn:feature_code":"PPL",
    "gn:name":"Khodgaon",
    "gn:population":0,
    "gn:timezone":"Asia/Kolkata",
    "iso:country":"IN",
    "wof:name":"Khodgaon",
    "wof:placetype":"locality"
},
  "geometry": {"coordinates":[79.64983000000002,21.27701],"type":"Point"}
}