{
  "type": "Feature",
  "properties": {
    "iso:country":"IN",
    "ks:ks_name":"Lachchamanpur",
    "ks:ks_pop":462,
    "ks:ks_type":"HABITATION",
    "name:eng_x_preferred":[
        "Lachchamanpur"
    ],
    "wof:name":"Lachchamanpur",
    "wof:placetype":"locality",
    "wof:population":462
},
  "geometry": {"coordinates":[80.071111,26.229167],"type":"Point"}
}