{
  "type": "Feature",
  "properties": {
    "gn:admin1_code":"19.0",
    "gn:admin2_code":"567.0",
    "gn:asciiname":"Ramagondanahalli",
    "gn:country_code":"IN",
    "gn:dem":609,
    "gn:feature_class":"P",
    "gn:feature_code":"PPL",
    "gn:name":"R\u0101magondanahalli",
    "gn:population":0,
    "gn:timezone":"Asia/Kolkata",
    "iso:country":"IN",
    "wof:name":"Ramagondanahalli",
    "wof:placetype":"locality"
},
  "geometry": {"coordinates":[75.99481999999998,14.30802],"type":"Point"}
}