{
  "type": "Feature",
  "properties": {
    "iso:country":"IN",
    "ks:ks_name":"Bologara",
    "ks:ks_pop":3759,
    "ks:ks_type":"VILLAGE",
    "ks:ks_uagg_main":0,
    "name:eng_x_preferred":[
        "Bologara"
    ],
    "wof:name":"Bologara",
    "wof:placetype":"neighbourhood",
    "wof:population":3759
},
  "geometry": {"coordinates":[92.13830299999999,26.512763],"type":"Point"}
}