{
  "type": "Feature",
  "properties": {
    "iso:country":"IN",
    "ks:ks_name":"Ankisa Chak",
    "ks:ks_pop":999,
    "ks:ks_type":"VILLAGE",
    "name:eng_x_preferred":[
        "Ankisa Chak"
    ],
    "wof:name":"Ankisa Chak",
    "wof:placetype":"locality",
    "wof:population":999
},
  "geometry": {"coordinates":[80.155067,18.740809],"type":"Point"}
}