{
  "type": "Feature",
  "properties": {
    "gn:admin1_code":"2",
    "gn:asciiname":"Bilaputtu",
    "gn:country_code":"IN",
    "gn:dem":944,
    "gn:feature_class":"P",
    "gn:feature_code":"PPL",
    "gn:name":"Bilaputtu",
    "gn:population":0,
    "gn:timezone":"Asia/Kolkata",
    "iso:country":"IN",
    "ks:ks_name":"Billaputt",
    "ks:ks_pop":25,
    "ks:ks_type":"HABITATION",
    "name:eng_x_preferred":[
        "Billaputt"
    ],
    "name:eng_x_variant":[
        "Bilaputtu"
    ],
    "wof:name":"Billaputt",
    "wof:placetype":"locality",
    "wof:population":25
},
  "geometry": {"coordinates":[82.78707199999999,18.356658],"type":"Point"}
}