{
  "type": "Feature",
  "properties": {
    "iso:country":"IN",
    "ks:ks_name":"Chainpur Gulaura",
    "ks:ks_pop":1912,
    "ks:ks_type":"VILLAGE",
    "ks:ks_uagg_main":0,
    "name:eng_x_preferred":[
        "Chainpur Gulaura"
    ],
    "wof:name":"Chainpur Gulaura",
    "wof:placetype":"neighbourhood",
    "wof:population":1912
},
  "geometry": {"coordinates":[83.826211,26.176556],"type":"Point"}
}