{
  "type": "Feature",
  "properties": {
    "iso:country":"IN",
    "ks:ks_name":"Sadak Para",
    "ks:ks_pop":84,
    "ks:ks_type":"HABITATION",
    "name:eng_x_preferred":[
        "Sadak Para"
    ],
    "wof:name":"Sadak Para",
    "wof:placetype":"locality",
    "wof:population":84
},
  "geometry": {"coordinates":[81.38633799999999,19.478354],"type":"Point"}
}