{
  "type": "Feature",
  "properties": {
    "gn:admin1_code":"25.0",
    "gn:admin2_code":"612.0",
    "gn:asciiname":"Kilanavayal",
    "gn:country_code":"IN",
    "gn:dem":1741,
    "gn:feature_class":"P",
    "gn:feature_code":"PPL",
    "gn:name":"K\u012bl\u0101navayal",
    "gn:population":0,
    "gn:timezone":"Asia/Kolkata",
    "iso:country":"IN",
    "wof:name":"Kilanavayal",
    "wof:placetype":"locality"
},
  "geometry": {"coordinates":[77.33029999999999,10.26161],"type":"Point"}
}