{
  "type": "Feature",
  "properties": {
    "iso:country":"IN",
    "ks:ks_name":"Thasaliyur",
    "ks:ks_pop":640,
    "ks:ks_type":"HABITATION",
    "ks:ks_uagg_main":0,
    "name:eng_x_preferred":[
        "Thasaliyur"
    ],
    "wof:name":"Thasaliyur",
    "wof:placetype":"neighbourhood",
    "wof:population":640
},
  "geometry": {"coordinates":[77.571888,11.562147],"type":"Point"}
}