{
  "type": "Feature",
  "properties": {
    "iso:country":"IN",
    "ks:ks_name":"Jalasuan",
    "ks:ks_pop":874,
    "ks:ks_type":"VILLAGE",
    "ks:ks_uagg_main":0,
    "name:eng_x_preferred":[
        "Jalasuan"
    ],
    "wof:name":"Jalasuan",
    "wof:placetype":"neighbourhood",
    "wof:population":874
},
  "geometry": {"coordinates":[86.023149,21.143034],"type":"Point"}
}