{
  "type": "Feature",
  "properties": {
    "iso:country":"IN",
    "ks:ks_name":"Chowkimali",
    "ks:ks_pop":600,
    "ks:ks_type":"HABITATION",
    "name:eng_x_preferred":[
        "Chowkimali"
    ],
    "wof:name":"Chowkimali",
    "wof:placetype":"locality",
    "wof:population":600
},
  "geometry": {"coordinates":[73.646933,21.674967],"type":"Point"}
}