{
  "type": "Feature",
  "properties": {
    "iso:country":"IN",
    "ks:ks_name":"Mollapara",
    "ks:ks_pop":1000,
    "ks:ks_type":"HABITATION",
    "name:eng_x_preferred":[
        "Mollapara"
    ],
    "wof:name":"Mollapara",
    "wof:placetype":"locality",
    "wof:population":1000
},
  "geometry": {"coordinates":[88.689881,22.410961],"type":"Point"}
}