{
  "type": "Feature",
  "properties": {
    "iso:country":"IN",
    "ks:ks_name":"Nawagarh",
    "ks:ks_pop":758,
    "ks:ks_type":"VILLAGE",
    "name:eng_x_preferred":[
        "Nawagarh"
    ],
    "wof:name":"Nawagarh",
    "wof:placetype":"locality",
    "wof:population":758
},
  "geometry": {"coordinates":[81.548537,19.934238],"type":"Point"}
}