{
  "type": "Feature",
  "properties": {
    "iso:country":"IN",
    "ks:ks_name":"Biunria",
    "ks:ks_pop":0,
    "ks:ks_type":"VILLAGE",
    "name:eng_x_preferred":[
        "Biunria"
    ],
    "wof:name":"Biunria",
    "wof:placetype":"locality",
    "wof:population":0
},
  "geometry": {"coordinates":[86.027942,21.840197],"type":"Point"}
}