{
  "type": "Feature",
  "properties": {
    "iso:country":"IN",
    "ks:ks_name":"Gorho Tola",
    "ks:ks_pop":320,
    "ks:ks_type":"HABITATION",
    "ks:ks_uagg_main":0,
    "name:eng_x_preferred":[
        "Gorho Tola"
    ],
    "wof:name":"Gorho Tola",
    "wof:placetype":"neighbourhood",
    "wof:population":320
},
  "geometry": {"coordinates":[86.491512,25.865591],"type":"Point"}
}