{
  "type": "Feature",
  "properties": {
    "gn:admin1_code":"35.0",
    "gn:admin2_code":"454.0",
    "gn:asciiname":"Luri",
    "gn:country_code":"IN",
    "gn:dem":651,
    "gn:feature_class":"P",
    "gn:feature_code":"PPL",
    "gn:name":"L\u016bri",
    "gn:population":0,
    "gn:timezone":"Asia/Kolkata",
    "iso:country":"IN",
    "ks:ks_alt_nam":"L\u016bri",
    "ks:ks_name":"Luri",
    "ks:ks_pop":588,
    "ks:ks_type":"VILLAGE",
    "name:eng_x_preferred":[
        "Luri"
    ],
    "name:eng_x_variant":[
        "L\u016bri"
    ],
    "wof:name":"Luri",
    "wof:placetype":"locality",
    "wof:population":588
},
  "geometry": {"coordinates":[80.905474,22.450842],"type":"Point"}
}