{
  "type": "Feature",
  "properties": {
    "iso:country":"IN",
    "ks:ks_name":"Baba Kutti",
    "ks:ks_pop":165,
    "ks:ks_type":"HABITATION",
    "name:eng_x_preferred":[
        "Baba Kutti"
    ],
    "wof:name":"Baba Kutti",
    "wof:placetype":"locality",
    "wof:population":165
},
  "geometry": {"coordinates":[81.577778,27.189045],"type":"Point"}
}