{
  "type": "Feature",
  "properties": {
    "iso:country":"IN",
    "ks:ks_alt_nam":"S\u0101ma",
    "ks:ks_name":"Sama",
    "ks:ks_type":"VILLAGE",
    "name:eng_x_preferred":[
        "Sama"
    ],
    "name:eng_x_variant":[
        "S\u0101ma"
    ],
    "wof:name":"Sama",
    "wof:placetype":"locality"
},
  "geometry": {"coordinates":[80.03694,30.018189],"type":"Point"}
}