{
  "type": "Feature",
  "properties": {
    "iso:country":"IN",
    "ks:ks_name":"Factory Vala",
    "ks:ks_pop":90,
    "ks:ks_type":"HABITATION",
    "name:eng_x_preferred":[
        "Factory Vala"
    ],
    "wof:name":"Factory Vala",
    "wof:placetype":"locality",
    "wof:population":90
},
  "geometry": {"coordinates":[73.40012,23.279111],"type":"Point"}
}