{
  "type": "Feature",
  "properties": {
    "iso:country":"IN",
    "ks:ks_name":"Holegadde",
    "ks:ks_pop":15,
    "ks:ks_type":"HABITATION",
    "name:eng_x_preferred":[
        "Holegadde"
    ],
    "wof:name":"Holegadde",
    "wof:placetype":"locality",
    "wof:population":15
},
  "geometry": {"coordinates":[75.189026,13.495293],"type":"Point"}
}