{
  "type": "Feature",
  "properties": {
    "iso:country":"IN",
    "ks:ks_name":"Vaddivaripeta",
    "ks:ks_pop":352,
    "ks:ks_type":"HABITATION",
    "name:eng_x_preferred":[
        "Vaddivaripeta"
    ],
    "wof:name":"Vaddivaripeta",
    "wof:placetype":"locality",
    "wof:population":352
},
  "geometry": {"coordinates":[82.113851,16.60059],"type":"Point"}
}