{
  "type": "Feature",
  "properties": {
    "gn:admin1_code":"23",
    "gn:admin2_code":"38.0",
    "gn:asciiname":"Baring",
    "gn:country_code":"IN",
    "gn:dem":668,
    "gn:feature_class":"P",
    "gn:feature_code":"PPL",
    "gn:name":"Baring",
    "gn:population":0,
    "gn:timezone":"Asia/Kolkata",
    "iso:country":"IN",
    "name:ceb_x_preferred":[
        "Baring"
    ],
    "name:deu_x_preferred":[
        "Baring"
    ],
    "name:fra_x_preferred":[
        "Baring"
    ],
    "name:ita_x_preferred":[
        "Baring"
    ],
    "name:nld_x_preferred":[
        "Baring"
    ],
    "name:por_x_preferred":[
        "Baring"
    ],
    "name:rus_x_preferred":[
        "\u0411\u044d\u0440\u0438\u043d\u0433"
    ],
    "name:ukr_x_preferred":[
        "\u0411\u0430\u0440\u0456\u043d\u0433"
    ],
    "name:urd_x_preferred":[
        "\u0628\u0627\u0631\u0646\u06af"
    ],
    "name:vol_x_preferred":[
        "Baring"
    ],
    "wof:name":"Baring",
    "wof:placetype":"locality"
},
  "geometry": {"coordinates":[75.87661999999997,31.88328],"type":"Point"}
}