{
  "type": "Feature",
  "properties": {
    "iso:country":"IN",
    "ks:ks_alt_nam":"Sihauli mb",
    "ks:ks_name":"Sihauli Mb",
    "ks:ks_pop":372,
    "ks:ks_type":"HABITATION",
    "name:eng_x_preferred":[
        "Sihauli Mb"
    ],
    "wof:name":"Sihauli Mb",
    "wof:placetype":"locality",
    "wof:population":372
},
  "geometry": {"coordinates":[82.93007,25.670745],"type":"Point"}
}