{
  "type": "Feature",
  "properties": {
    "iso:country":"IN",
    "ks:ks_name":"Brahmapur",
    "ks:ks_pop":0,
    "ks:ks_type":"VILLAGE",
    "name:eng_x_preferred":[
        "Brahmapur"
    ],
    "wof:name":"Brahmapur",
    "wof:placetype":"locality",
    "wof:population":0
},
  "geometry": {"coordinates":[88.334249,22.026808],"type":"Point"}
}