{
  "type": "Feature",
  "properties": {
    "iso:country":"IN",
    "ks:ks_name":"Mahamadpur Badal",
    "ks:ks_type":"VILLAGE",
    "name:eng_x_preferred":[
        "Mahamadpur Badal"
    ],
    "wof:name":"Mahamadpur Badal",
    "wof:placetype":"locality"
},
  "geometry": {"coordinates":[85.502275,26.039109],"type":"Point"}
}