{
  "type": "Feature",
  "properties": {
    "gn:admin1_code":"36",
    "gn:admin2_code":"160.0",
    "gn:asciiname":"Harbatiapur",
    "gn:country_code":"IN",
    "gn:dem":145,
    "gn:feature_class":"P",
    "gn:feature_code":"PPL",
    "gn:name":"Harbati\u0101pur",
    "gn:population":0,
    "gn:timezone":"Asia/Kolkata",
    "iso:country":"IN",
    "wof:name":"Harbatiapur",
    "wof:placetype":"neighbourhood"
},
  "geometry": {"coordinates":[79.60684999999999,27.01149],"type":"Point"}
}