{
  "type": "Feature",
  "properties": {
    "iso:country":"IN",
    "ks:ks_alt_nam":"Olmor\u0101",
    "ks:ks_name":"Olmora",
    "ks:ks_pop":240,
    "ks:ks_type":"VILLAGE",
    "name:eng_x_preferred":[
        "Olmora"
    ],
    "name:eng_x_variant":[
        "Olmor\u0101"
    ],
    "wof:name":"Olmora",
    "wof:placetype":"locality",
    "wof:population":240
},
  "geometry": {"coordinates":[84.820823,23.055923],"type":"Point"}
}