{
  "type": "Feature",
  "properties": {
    "iso:country":"IN",
    "ks:ks_name":"Bahrampurwa",
    "ks:ks_pop":58,
    "ks:ks_type":"HABITATION",
    "name:eng_x_preferred":[
        "Bahrampurwa"
    ],
    "wof:name":"Bahrampurwa",
    "wof:placetype":"locality",
    "wof:population":58
},
  "geometry": {"coordinates":[81.615211,27.681946],"type":"Point"}
}