{
  "type": "Feature",
  "properties": {
    "iso:country":"IN",
    "ks:ks_name":"Kundeigarh",
    "ks:ks_pop":244,
    "ks:ks_type":"VILLAGE",
    "name:eng_x_preferred":[
        "Kundeigarh"
    ],
    "wof:name":"Kundeigarh",
    "wof:placetype":"locality",
    "wof:population":244
},
  "geometry": {"coordinates":[83.617323,20.656564],"type":"Point"}
}