{
  "type": "Feature",
  "properties": {
    "iso:country":"IN",
    "ks:ks_name":"Makki",
    "ks:ks_pop":224,
    "ks:ks_type":"HABITATION",
    "name:eng_x_preferred":[
        "Makki"
    ],
    "wof:name":"Makki",
    "wof:placetype":"locality",
    "wof:population":224
},
  "geometry": {"coordinates":[75.088514,13.093],"type":"Point"}
}