{
  "type": "Feature",
  "properties": {
    "iso:country":"IN",
    "ks:ks_name":"Mahapura",
    "ks:ks_pop":1601,
    "ks:ks_type":"VILLAGE",
    "name:eng_x_preferred":[
        "Mahapura"
    ],
    "wof:name":"Mahapura",
    "wof:placetype":"neighbourhood",
    "wof:population":1601
},
  "geometry": {"coordinates":[73.102653,22.305299],"type":"Point"}
}