{
  "type": "Feature",
  "properties": {
    "gn:admin1_code":"35.0",
    "gn:admin2_code":"421",
    "gn:asciiname":"Behat",
    "gn:country_code":"IN",
    "gn:dem":212,
    "gn:feature_class":"P",
    "gn:feature_code":"PPL",
    "gn:name":"Behat",
    "gn:population":0,
    "gn:timezone":"Asia/Kolkata",
    "iso:country":"IN",
    "name:und_x_variant":[
        "Talbahat",
        "Behat"
    ],
    "wof:name":"Behat",
    "wof:placetype":"locality"
},
  "geometry": {"coordinates":[78.53775999999998,26.17372],"type":"Point"}
}