{
  "type": "Feature",
  "properties": {
    "iso:country":"IN",
    "ks:ks_name":"Milanpur",
    "ks:ks_pop":3,
    "ks:ks_type":"HABITATION",
    "name:eng_x_preferred":[
        "Milanpur"
    ],
    "wof:name":"Milanpur",
    "wof:placetype":"locality",
    "wof:population":3
},
  "geometry": {"coordinates":[78.186044,21.302025],"type":"Point"}
}