{
  "type": "Feature",
  "properties": {
    "gn:admin1_code":"25.0",
    "gn:admin2_code":"610.0",
    "gn:asciiname":"Vedikkaranpalaiyam",
    "gn:country_code":"IN",
    "gn:dem":229,
    "gn:feature_class":"P",
    "gn:feature_code":"PPL",
    "gn:name":"Vedikk\u0101ranp\u0101laiyam",
    "gn:population":0,
    "gn:timezone":"Asia/Kolkata",
    "iso:country":"IN",
    "wof:name":"Vedikkaranpalaiyam",
    "wof:placetype":"locality"
},
  "geometry": {"coordinates":[77.72013000000003,11.17398],"type":"Point"}
}