{
  "type": "Feature",
  "properties": {
    "iso:country":"IN",
    "ks:ks_name":"Golidady",
    "ks:ks_pop":242,
    "ks:ks_type":"HABITATION",
    "name:eng_x_preferred":[
        "Golidady"
    ],
    "wof:name":"Golidady",
    "wof:placetype":"locality",
    "wof:population":242
},
  "geometry": {"coordinates":[75.033331,13.235275],"type":"Point"}
}