{
  "type": "Feature",
  "properties": {
    "iso:country":"IN",
    "ks:ks_name":"Koiri Tola",
    "ks:ks_pop":579,
    "ks:ks_type":"HABITATION",
    "name:eng_x_preferred":[
        "Koiri Tola"
    ],
    "wof:name":"Koiri Tola",
    "wof:placetype":"locality",
    "wof:population":579
},
  "geometry": {"coordinates":[86.063503,24.409022],"type":"Point"}
}