{
  "type": "Feature",
  "properties": {
    "gn:admin1_code":"36",
    "gn:admin2_code":"187.0",
    "gn:asciiname":"Channi",
    "gn:country_code":"IN",
    "gn:dem":84,
    "gn:feature_class":"P",
    "gn:feature_code":"PPL",
    "gn:name":"Channi",
    "gn:population":0,
    "gn:timezone":"Asia/Kolkata",
    "iso:country":"IN",
    "wof:name":"Channi",
    "wof:placetype":"locality"
},
  "geometry": {"coordinates":[83.40489000000002,27.00474],"type":"Point"}
}