{
  "type": "Feature",
  "properties": {
    "iso:country":"IN",
    "ks:ks_name":"Mathini",
    "ks:ks_pop":190,
    "ks:ks_type":"HABITATION",
    "name:eng_x_preferred":[
        "Mathini"
    ],
    "wof:name":"Mathini",
    "wof:placetype":"locality",
    "wof:population":190
},
  "geometry": {"coordinates":[78.71485,9.922778],"type":"Point"}
}