{
  "type": "Feature",
  "properties": {
    "iso:country":"IN",
    "ks:ks_name":"Chak Gandharajpur",
    "ks:ks_pop":295,
    "ks:ks_type":"VILLAGE",
    "ks:ks_uagg_main":0,
    "name:eng_x_preferred":[
        "Chak Gandharajpur"
    ],
    "wof:name":"Chak Gandharajpur",
    "wof:placetype":"neighbourhood",
    "wof:population":295
},
  "geometry": {"coordinates":[88.632808,23.945498],"type":"Point"}
}