{
  "type": "Feature",
  "properties": {
    "gn:admin1_code":"35",
    "gn:admin2_code":"436.0",
    "gn:asciiname":"Bor Kheri Kabal",
    "gn:country_code":"IN",
    "gn:dem":407,
    "gn:feature_class":"P",
    "gn:feature_code":"PPL",
    "gn:name":"Bor Kheri K\u0101bal",
    "gn:population":0,
    "gn:timezone":"Asia/Kolkata",
    "iso:country":"IN",
    "wof:name":"Bor Kheri Kabal",
    "wof:placetype":"locality"
},
  "geometry": {"coordinates":[76.07396,23.98676],"type":"Point"}
}