{
  "type": "Feature",
  "properties": {
    "iso:country":"IN",
    "ks:ks_name":"Manpur",
    "ks:ks_pop":360,
    "ks:ks_type":"VILLAGE",
    "ks:ks_uagg_main":0,
    "name:eng_x_preferred":[
        "Manpur"
    ],
    "wof:name":"Manpur",
    "wof:placetype":"neighbourhood",
    "wof:population":360
},
  "geometry": {"coordinates":[86.610338,24.109164],"type":"Point"}
}