{
  "type": "Feature",
  "properties": {
    "iso:country":"IN",
    "ks:ks_name":"Badrampala",
    "ks:ks_pop":815,
    "ks:ks_type":"HABITATION",
    "name:eng_x_preferred":[
        "Badrampala"
    ],
    "wof:name":"Badrampala",
    "wof:placetype":"locality",
    "wof:population":815
},
  "geometry": {"coordinates":[75.072368,12.651015],"type":"Point"}
}