{
  "type": "Feature",
  "properties": {
    "gn:admin1_code":"2",
    "gn:admin2_code":"544.0",
    "gn:asciiname":"Kakanuru",
    "gn:country_code":"IN",
    "gn:dem":478,
    "gn:feature_class":"P",
    "gn:feature_code":"PPL",
    "gn:name":"K\u0101kan\u016bru",
    "gn:population":0,
    "gn:timezone":"Asia/Kolkata",
    "iso:country":"IN",
    "ks:ks_alt_nam":"K\u0101kan\u016bru",
    "ks:ks_name":"Kakanuru",
    "ks:ks_pop":262,
    "ks:ks_type":"VILLAGE",
    "name:eng_x_preferred":[
        "Kakanuru"
    ],
    "name:eng_x_variant":[
        "K\u0101kan\u016bru"
    ],
    "wof:name":"Kakanuru",
    "wof:placetype":"locality",
    "wof:population":262
},
  "geometry": {"coordinates":[82.010694,17.905007],"type":"Point"}
}