{
  "type": "Feature",
  "properties": {
    "iso:country":"IN",
    "ks:ks_alt_nam":"High school Junction",
    "ks:ks_name":"High School Junction",
    "ks:ks_pop":315,
    "ks:ks_type":"HABITATION",
    "name:eng_x_preferred":[
        "High School Junction"
    ],
    "wof:name":"High School Junction",
    "wof:placetype":"locality",
    "wof:population":315
},
  "geometry": {"coordinates":[76.3013,10.23468],"type":"Point"}
}