{
  "type": "Feature",
  "properties": {
    "iso:country":"IN",
    "ks:ks_name":"Karpadi",
    "ks:ks_pop":300,
    "ks:ks_type":"HABITATION",
    "name:eng_x_preferred":[
        "Karpadi"
    ],
    "wof:name":"Karpadi",
    "wof:placetype":"locality",
    "wof:population":300
},
  "geometry": {"coordinates":[75.21556699999999,12.886861],"type":"Point"}
}