{
  "type": "Feature",
  "properties": {
    "iso:country":"IN",
    "ks:ks_name":"Mridha Para",
    "ks:ks_pop":857,
    "ks:ks_type":"HABITATION",
    "name:eng_x_preferred":[
        "Mridha Para"
    ],
    "wof:name":"Mridha Para",
    "wof:placetype":"locality",
    "wof:population":857
},
  "geometry": {"coordinates":[88.87745200000001,22.179837],"type":"Point"}
}