{
  "type": "Feature",
  "properties": {
    "iso:country":"IN",
    "ks:ks_name":"Heggadde",
    "ks:ks_pop":2466,
    "ks:ks_type":"VILLAGE",
    "name:eng_x_preferred":[
        "Heggadde"
    ],
    "wof:name":"Heggadde",
    "wof:placetype":"locality",
    "wof:population":2466
},
  "geometry": {"coordinates":[75.67138199999999,12.884707],"type":"Point"}
}