{
  "type": "Feature",
  "properties": {
    "iso:country":"IN",
    "ks:ks_alt_nam":"Malaim\u0101chchampatti",
    "ks:ks_alt_nam_2":"Malaimachchampatti",
    "ks:ks_name":"Othakalmandapam",
    "ks:ks_pop":10320,
    "ks:ks_type":"VILLAGE",
    "ks:ks_uagg_main":0,
    "name:eng_x_preferred":[
        "Othakalmandapam"
    ],
    "name:eng_x_variant":[
        "Malaim\u0101chchampatti",
        "Malaimachchampatti"
    ],
    "wof:name":"Othakalmandapam",
    "wof:placetype":"locality",
    "wof:population":10320
},
  "geometry": {"coordinates":[77.004986,10.905779],"type":"Point"}
}