{
  "type": "Feature",
  "properties": {
    "iso:country":"IN",
    "ks:ks_name":"Rongchek",
    "ks:ks_pop":500,
    "ks:ks_type":"HABITATION",
    "name:eng_x_preferred":[
        "Rongchek"
    ],
    "wof:name":"Rongchek",
    "wof:placetype":"locality",
    "wof:population":500
},
  "geometry": {"coordinates":[92.46819600000001,25.873783],"type":"Point"}
}