{
  "type": "Feature",
  "properties": {
    "gn:admin1_code":"2.0",
    "gn:admin2_code":"546.0",
    "gn:asciiname":"Tatiakalagudem",
    "gn:country_code":"IN",
    "gn:dem":161,
    "gn:feature_class":"P",
    "gn:feature_code":"PPL",
    "gn:name":"T\u0101ti\u0101kalag\u016bdem",
    "gn:population":0,
    "gn:timezone":"Asia/Kolkata",
    "iso:country":"IN",
    "ks:ks_name":"Tatiyakulagudem",
    "ks:ks_pop":1324,
    "ks:ks_type":"VILLAGE",
    "ks:ks_uagg_main":0,
    "name:eng_x_preferred":[
        "Tatiyakulagudem"
    ],
    "wof:name":"Tatiyakulagudem",
    "wof:placetype":"neighbourhood",
    "wof:population":1324
},
  "geometry": {"coordinates":[81.129524,17.21821],"type":"Point"}
}