{
  "type": "Feature",
  "properties": {
    "gn:admin1_code":"35",
    "gn:admin2_code":"423.0",
    "gn:asciiname":"Jamla",
    "gn:country_code":"IN",
    "gn:dem":324,
    "gn:feature_class":"P",
    "gn:feature_code":"PPL",
    "gn:name":"Jamla",
    "gn:population":0,
    "gn:timezone":"Asia/Kolkata",
    "iso:country":"IN",
    "name:heb_x_preferred":[
        "\u05d2'\u05de\u05dc\u05d4"
    ],
    "name:pol_x_preferred":[
        "D\u017camla"
    ],
    "name:urd_x_preferred":[
        "\u062c\u0645\u0644\u0627"
    ],
    "name:vie_x_preferred":[
        "Jamla"
    ],
    "wof:name":"Jamla",
    "wof:placetype":"locality"
},
  "geometry": {"coordinates":[78.21120999999999,25.31749],"type":"Point"}
}