{
  "type": "Feature",
  "properties": {
    "iso:country":"IN",
    "ks:ks_name":"Bighaper",
    "ks:ks_pop":124,
    "ks:ks_type":"HABITATION",
    "name:eng_x_preferred":[
        "Bighaper"
    ],
    "wof:name":"Bighaper",
    "wof:placetype":"locality",
    "wof:population":124
},
  "geometry": {"coordinates":[85.24633799999999,24.674797],"type":"Point"}
}