{
  "type": "Feature",
  "properties": {
    "gn:admin1_code":"39.0",
    "gn:admin2_code":"66.0",
    "gn:asciiname":"Seti Bhandar",
    "gn:country_code":"IN",
    "gn:dem":715,
    "gn:feature_class":"P",
    "gn:feature_code":"PPL",
    "gn:name":"Seti Bhand\u0101r",
    "gn:population":0,
    "gn:timezone":"Asia/Kolkata",
    "iso:country":"IN",
    "ks:ks_alt_nam":"Seti Bhand\u0101r",
    "ks:ks_name":"Seti Bhandar",
    "ks:ks_pop":62,
    "ks:ks_type":"VILLAGE",
    "name:eng_x_preferred":[
        "Seti Bhandar"
    ],
    "name:eng_x_variant":[
        "Seti Bhand\u0101r"
    ],
    "wof:name":"Seti Bhandar",
    "wof:placetype":"locality",
    "wof:population":62
},
  "geometry": {"coordinates":[79.30633,29.556477],"type":"Point"}
}