{
  "type": "Feature",
  "properties": {
    "iso:country":"IN",
    "ks:ks_alt_nam":"C S Pura AKC",
    "ks:ks_name":"C S Pura Akc",
    "ks:ks_pop":419,
    "ks:ks_type":"HABITATION",
    "name:eng_x_preferred":[
        "C S Pura Akc"
    ],
    "wof:name":"C S Pura Akc",
    "wof:placetype":"locality",
    "wof:population":419
},
  "geometry": {"coordinates":[76.877358,13.147039],"type":"Point"}
}