{
  "type": "Feature",
  "properties": {
    "iso:country":"IN",
    "ks:ks_alt_nam":"Doddachepi tanda",
    "ks:ks_name":"Doddachepi Tanda",
    "ks:ks_pop":215,
    "ks:ks_type":"HABITATION",
    "name:eng_x_preferred":[
        "Doddachepi Tanda"
    ],
    "wof:name":"Doddachepi Tanda",
    "wof:placetype":"locality",
    "wof:population":215
},
  "geometry": {"coordinates":[76.337282,16.279896],"type":"Point"}
}