{
  "type": "Feature",
  "properties": {
    "iso:country":"IN",
    "ks:ks_name":"Madgaon",
    "ks:ks_pop":124,
    "ks:ks_type":"VILLAGE",
    "name:eng_x_preferred":[
        "Madgaon"
    ],
    "wof:name":"Madgaon",
    "wof:placetype":"locality",
    "wof:population":124
},
  "geometry": {"coordinates":[81.414787,20.103492],"type":"Point"}
}