{
  "type": "Feature",
  "properties": {
    "iso:country":"IN",
    "ks:ks_name":"Risdi",
    "ks:ks_type":"VILLAGE",
    "ks:ks_uagg_main":0,
    "name:eng_x_preferred":[
        "Risdi"
    ],
    "wof:name":"Risdi",
    "wof:placetype":"neighbourhood"
},
  "geometry": {"coordinates":[82.75813100000001,22.369747],"type":"Point"}
}