{
  "type": "Feature",
  "properties": {
    "gn:admin1_code":"19.0",
    "gn:admin2_code":"577.0",
    "gn:asciiname":"Megala Koppal",
    "gn:country_code":"IN",
    "gn:dem":689,
    "gn:feature_class":"P",
    "gn:feature_code":"PPL",
    "gn:name":"Megala Koppal",
    "gn:population":0,
    "gn:timezone":"Asia/Kolkata",
    "iso:country":"IN",
    "wof:name":"Megala Koppal",
    "wof:placetype":"neighbourhood"
},
  "geometry": {"coordinates":[76.89906000000001,12.31637],"type":"Point"}
}