{
  "type": "Feature",
  "properties": {
    "iso:country":"IN",
    "ks:ks_name":"Charna",
    "ks:ks_pop":932,
    "ks:ks_type":"HABITATION",
    "name:eng_x_preferred":[
        "Charna"
    ],
    "wof:name":"Charna",
    "wof:placetype":"locality",
    "wof:population":932
},
  "geometry": {"coordinates":[79.59201,29.955221],"type":"Point"}
}