{
  "type": "Feature",
  "properties": {
    "iso:country":"IN",
    "ks:ks_name":"Kristopur",
    "ks:ks_pop":465,
    "ks:ks_type":"VILLAGE",
    "name:eng_x_preferred":[
        "Kristopur"
    ],
    "wof:name":"Kristopur",
    "wof:placetype":"locality",
    "wof:population":465
},
  "geometry": {"coordinates":[87.845198,24.958702],"type":"Point"}
}