{
  "type": "Feature",
  "properties": {
    "gn:admin1_code":"40.0",
    "gn:admin2_code":"541.0",
    "gn:asciiname":"Kotturu",
    "gn:country_code":"IN",
    "gn:dem":26,
    "gn:feature_class":"P",
    "gn:feature_code":"PPL",
    "gn:name":"Kott\u016bru",
    "gn:population":0,
    "gn:timezone":"Asia/Kolkata",
    "iso:country":"IN",
    "ks:ks_name":"Kothuru",
    "ks:ks_pop":19,
    "ks:ks_type":"VILLAGE",
    "name:eng_x_preferred":[
        "Kothuru"
    ],
    "name:eng_x_variant":[
        "Kotturu"
    ],
    "wof:name":"Kothuru",
    "wof:placetype":"locality",
    "wof:population":19
},
  "geometry": {"coordinates":[81.29868,17.509093],"type":"Point"}
}