{
  "type": "Feature",
  "properties": {
    "iso:country":"IN",
    "ks:ks_name":"Heggar",
    "ks:ks_pop":50,
    "ks:ks_type":"HABITATION",
    "name:eng_x_preferred":[
        "Heggar"
    ],
    "wof:name":"Heggar",
    "wof:placetype":"locality",
    "wof:population":50
},
  "geometry": {"coordinates":[75.292869,13.403625],"type":"Point"}
}