{
  "type": "Feature",
  "properties": {
    "iso:country":"IN",
    "ks:ks_name":"Keelur",
    "ks:ks_pop":553,
    "ks:ks_type":"HABITATION",
    "name:eng_x_preferred":[
        "Keelur"
    ],
    "wof:name":"Keelur",
    "wof:placetype":"locality",
    "wof:population":553
},
  "geometry": {"coordinates":[77.747196,9.491901],"type":"Point"}
}