{
  "type": "Feature",
  "properties": {
    "iso:country":"IN",
    "ks:ks_name":"Kala Kota",
    "ks:ks_pop":54,
    "ks:ks_type":"HABITATION",
    "name:eng_x_preferred":[
        "Kala Kota"
    ],
    "wof:name":"Kala Kota",
    "wof:placetype":"locality",
    "wof:population":54
},
  "geometry": {"coordinates":[75.94906400000001,27.658276],"type":"Point"}
}