{
  "type": "Feature",
  "properties": {
    "iso:country":"IN",
    "ks:ks_name":"Paschim Para",
    "ks:ks_pop":582,
    "ks:ks_type":"HABITATION",
    "name:eng_x_preferred":[
        "Paschim Para"
    ],
    "wof:name":"Paschim Para",
    "wof:placetype":"locality",
    "wof:population":582
},
  "geometry": {"coordinates":[91.455771,23.220991],"type":"Point"}
}