{
  "type": "Feature",
  "properties": {
    "iso:country":"IN",
    "ks:ks_name":"Deopada",
    "ks:ks_pop":1338,
    "ks:ks_type":"HABITATION",
    "name:eng_x_preferred":[
        "Deopada"
    ],
    "wof:name":"Deopada",
    "wof:placetype":"locality",
    "wof:population":1338
},
  "geometry": {"coordinates":[73.367643,19.060875],"type":"Point"}
}