{
  "type": "Feature",
  "properties": {
    "iso:country":"IN",
    "ks:ks_name":"Karimabad",
    "ks:ks_pop":90,
    "ks:ks_type":"VILLAGE",
    "name:eng_x_preferred":[
        "Karimabad"
    ],
    "wof:name":"Karimabad",
    "wof:placetype":"locality",
    "wof:population":90
},
  "geometry": {"coordinates":[86.092645,20.505399],"type":"Point"}
}