{
  "type": "Feature",
  "properties": {
    "iso:country":"IN",
    "ks:ks_name":"Tambapur",
    "ks:ks_pop":202,
    "ks:ks_type":"VILLAGE",
    "name:eng_x_preferred":[
        "Tambapur"
    ],
    "wof:name":"Tambapur",
    "wof:placetype":"locality",
    "wof:population":202
},
  "geometry": {"coordinates":[84.473446,19.144722],"type":"Point"}
}