{
  "type": "Feature",
  "properties": {
    "gn:admin1_code":"35.0",
    "gn:admin2_code":"440.0",
    "gn:asciiname":"Tiraniya",
    "gn:country_code":"IN",
    "gn:dem":229,
    "gn:feature_class":"P",
    "gn:feature_code":"PPL",
    "gn:name":"Tir\u0101niya",
    "gn:population":0,
    "gn:timezone":"Asia/Kolkata",
    "iso:country":"IN",
    "ks:ks_name":"Toraniya",
    "ks:ks_pop":371,
    "ks:ks_type":"HABITATION",
    "name:eng_x_preferred":[
        "Toraniya"
    ],
    "name:eng_x_variant":[
        "Tiraniya"
    ],
    "wof:name":"Toraniya",
    "wof:placetype":"locality",
    "wof:population":371
},
  "geometry": {"coordinates":[76.22210699999999,22.404138],"type":"Point"}
}