{
  "type": "Feature",
  "properties": {
    "gn:admin1_code":"23.0",
    "gn:admin2_code":"53.0",
    "gn:asciiname":"Bhasaur",
    "gn:country_code":"IN",
    "gn:dem":245,
    "gn:feature_class":"P",
    "gn:feature_code":"PPL",
    "gn:name":"Bhasaur",
    "gn:population":0,
    "gn:timezone":"Asia/Kolkata",
    "iso:country":"IN",
    "name:pan_x_preferred":[
        "\u0a2d\u0a38\u0a4c\u0a5c"
    ],
    "wof:name":"Bhasaur",
    "wof:placetype":"locality"
},
  "geometry": {"coordinates":[75.89426,30.43819],"type":"Point"}
}