{
  "type": "Feature",
  "properties": {
    "iso:country":"IN",
    "ks:ks_name":"Kaithakkal Center",
    "ks:ks_pop":306,
    "ks:ks_type":"HABITATION",
    "name:eng_x_preferred":[
        "Kaithakkal Center"
    ],
    "wof:name":"Kaithakkal Center",
    "wof:placetype":"locality",
    "wof:population":306
},
  "geometry": {"coordinates":[76.084166,10.438658],"type":"Point"}
}