{
  "type": "Feature",
  "properties": {
    "iso:country":"IN",
    "ks:ks_name":"Go Toli",
    "ks:ks_pop":1949,
    "ks:ks_type":"HABITATION",
    "name:eng_x_preferred":[
        "Go Toli"
    ],
    "wof:name":"Go Toli",
    "wof:placetype":"locality",
    "wof:population":1949
},
  "geometry": {"coordinates":[85.626997,26.139128],"type":"Point"}
}