{
  "type": "Feature",
  "properties": {
    "iso:country":"IN",
    "ks:ks_name":"Tekaratoli",
    "ks:ks_pop":466,
    "ks:ks_type":"HABITATION",
    "name:eng_x_preferred":[
        "Tekaratoli"
    ],
    "wof:name":"Tekaratoli",
    "wof:placetype":"locality",
    "wof:population":466
},
  "geometry": {"coordinates":[84.638625,22.939542],"type":"Point"}
}