{
  "type": "Feature",
  "properties": {
    "iso:country":"IN",
    "ks:ks_alt_nam":"Barhaigarh mal",
    "ks:ks_name":"Barhaigarh Mal",
    "ks:ks_pop":343,
    "ks:ks_type":"HABITATION",
    "name:eng_x_preferred":[
        "Barhaigarh Mal"
    ],
    "wof:name":"Barhaigarh Mal",
    "wof:placetype":"locality",
    "wof:population":343
},
  "geometry": {"coordinates":[80.719058,23.267153],"type":"Point"}
}