{
  "type": "Feature",
  "properties": {
    "iso:country":"IN",
    "ks:ks_name":"Belpushkarini",
    "ks:ks_pop":147,
    "ks:ks_type":"VILLAGE",
    "name:eng_x_preferred":[
        "Belpushkarini"
    ],
    "wof:name":"Belpushkarini",
    "wof:placetype":"locality",
    "wof:population":147
},
  "geometry": {"coordinates":[87.648382,22.98989],"type":"Point"}
}