{
  "type": "Feature",
  "properties": {
    "iso:country":"IN",
    "ks:ks_name":"Raowadi",
    "ks:ks_pop":40,
    "ks:ks_type":"HABITATION",
    "name:eng_x_preferred":[
        "Raowadi"
    ],
    "wof:name":"Raowadi",
    "wof:placetype":"locality",
    "wof:population":40
},
  "geometry": {"coordinates":[73.664925,16.850158],"type":"Point"}
}