{
  "type": "Feature",
  "properties": {
    "iso:country":"IN",
    "ks:ks_name":"Kotehakkalu",
    "ks:ks_pop":40,
    "ks:ks_type":"HABITATION",
    "name:eng_x_preferred":[
        "Kotehakkalu"
    ],
    "wof:name":"Kotehakkalu",
    "wof:placetype":"locality",
    "wof:population":40
},
  "geometry": {"coordinates":[74.796876,13.981623],"type":"Point"}
}