{
  "type": "Feature",
  "properties": {
    "gn:admin1_code":"40",
    "gn:admin2_code":"540.0",
    "gn:asciiname":"Kottapalli",
    "gn:country_code":"IN",
    "gn:dem":388,
    "gn:feature_class":"P",
    "gn:feature_code":"PPL",
    "gn:name":"Kott\u0101palli",
    "gn:population":0,
    "gn:timezone":"Asia/Kolkata",
    "iso:country":"IN",
    "wof:name":"Kottapalli",
    "wof:placetype":"locality"
},
  "geometry": {"coordinates":[79.28586,17.92845],"type":"Point"}
}