{
  "type": "Feature",
  "properties": {
    "gn:admin1_code":"40",
    "gn:admin2_code":"540.0",
    "gn:asciiname":"Kottapalli",
    "gn:country_code":"IN",
    "gn:dem":388,
    "gn:feature_class":"P",
    "gn:feature_code":"PPL",
    "gn:name":"Kott\u0101palli",
    "gn:population":0,
    "gn:timezone":"Asia/Kolkata",
    "iso:country":"IN",
    "ks:ks_name":"Kothapally",
    "ks:ks_pop":170,
    "ks:ks_type":"HABITATION",
    "name:eng_x_preferred":[
        "Kothapally"
    ],
    "name:eng_x_variant":[
        "Kottapalli"
    ],
    "wof:name":"Kothapally",
    "wof:placetype":"locality",
    "wof:population":170
},
  "geometry": {"coordinates":[79.285675,17.927882],"type":"Point"}
}