{
  "type": "Feature",
  "properties": {
    "iso:country":"IN",
    "ks:ks_name":"Naricha",
    "ks:ks_pop":0,
    "ks:ks_type":"VILLAGE",
    "name:eng_x_preferred":[
        "Naricha"
    ],
    "wof:name":"Naricha",
    "wof:placetype":"locality",
    "wof:population":0
},
  "geometry": {"coordinates":[86.956985,24.620879],"type":"Point"}
}