{
  "type": "Feature",
  "properties": {
    "gn:admin1_code":"21",
    "gn:admin2_code":"370.0",
    "gn:asciiname":"Rengalipali",
    "gn:country_code":"IN",
    "gn:dem":191,
    "gn:feature_class":"P",
    "gn:feature_code":"PPL",
    "gn:name":"Reng\u0101lip\u0101li",
    "gn:population":0,
    "gn:timezone":"Asia/Kolkata",
    "iso:country":"IN",
    "wof:name":"Rengalipali",
    "wof:placetype":"locality"
},
  "geometry": {"coordinates":[83.40302,21.16595],"type":"Point"}
}