{
  "type": "Feature",
  "properties": {
    "iso:country":"IN",
    "ks:ks_name":"Bhatikuda",
    "ks:ks_pop":641,
    "ks:ks_type":"VILLAGE",
    "name:eng_x_preferred":[
        "Bhatikuda"
    ],
    "wof:name":"Bhatikuda",
    "wof:placetype":"locality",
    "wof:population":641
},
  "geometry": {"coordinates":[82.62894900000001,22.263832],"type":"Point"}
}