{
  "type": "Feature",
  "properties": {
    "iso:country":"IN",
    "ks:ks_name":"Suli",
    "ks:ks_pop":6,
    "ks:ks_type":"VILLAGE",
    "name:eng_x_preferred":[
        "Suli"
    ],
    "wof:name":"Suli",
    "wof:placetype":"locality",
    "wof:population":6
},
  "geometry": {"coordinates":[83.838132,20.034161],"type":"Point"}
}