{
  "type": "Feature",
  "properties": {
    "gn:admin1_code":"28.0",
    "gn:admin2_code":"330.0",
    "gn:asciiname":"Jamira",
    "gn:country_code":"IN",
    "gn:dem":45,
    "gn:feature_class":"P",
    "gn:feature_code":"PPL",
    "gn:name":"Jamira",
    "gn:population":0,
    "gn:timezone":"Asia/Kolkata",
    "iso:country":"IN",
    "wof:name":"Jamira",
    "wof:placetype":"locality"
},
  "geometry": {"coordinates":[87.93095,25.96157],"type":"Point"}
}