{
  "type": "Feature",
  "properties": {
    "iso:country":"IN",
    "ks:ks_name":"Dadar",
    "ks:ks_pop":24,
    "ks:ks_type":"VILLAGE",
    "name:eng_x_preferred":[
        "Dadar"
    ],
    "wof:name":"Dadar",
    "wof:placetype":"locality",
    "wof:population":24
},
  "geometry": {"coordinates":[79.105512,29.669405],"type":"Point"}
}