{
  "type": "Feature",
  "properties": {
    "iso:country":"IN",
    "ks:ks_alt_nam":"CHINASPALLAY THANDA",
    "ks:ks_name":"Chinaspallay Thanda",
    "ks:ks_pop":247,
    "ks:ks_type":"HABITATION",
    "name:eng_x_preferred":[
        "Chinaspallay Thanda"
    ],
    "wof:name":"Chinaspallay Thanda",
    "wof:placetype":"locality",
    "wof:population":247
},
  "geometry": {"coordinates":[78.213544,16.721626],"type":"Point"}
}