{
  "type": "Feature",
  "properties": {
    "gn:admin1_code":"37.0",
    "gn:admin2_code":"402",
    "gn:asciiname":"Bele",
    "gn:country_code":"IN",
    "gn:dem":497,
    "gn:feature_class":"P",
    "gn:feature_code":"PPL",
    "gn:name":"Bele",
    "gn:population":0,
    "gn:timezone":"Asia/Kolkata",
    "iso:country":"IN",
    "name:ceb_x_preferred":[
        "Bele"
    ],
    "name:swe_x_preferred":[
        "Bele"
    ],
    "wof:name":"Bele",
    "wof:placetype":"locality"
},
  "geometry": {"coordinates":[83.78333000000001,22.65],"type":"Point"}
}