{
  "type": "Feature",
  "properties": {
    "iso:country":"IN",
    "ks:ks_name":"Khadkui",
    "ks:ks_pop":1428,
    "ks:ks_type":"VILLAGE",
    "name:eng_x_preferred":[
        "Khadkui"
    ],
    "wof:name":"Khadkui",
    "wof:placetype":"locality",
    "wof:population":1428
},
  "geometry": {"coordinates":[74.585421,22.653764],"type":"Point"}
}