{
  "type": "Feature",
  "properties": {
    "gn:admin1_code":"21.0",
    "gn:admin2_code":"398",
    "gn:asciiname":"Chemma",
    "gn:country_code":"IN",
    "gn:dem":923,
    "gn:feature_class":"P",
    "gn:feature_code":"PPL",
    "gn:name":"Chemma",
    "gn:population":0,
    "gn:timezone":"Asia/Kolkata",
    "iso:country":"IN",
    "wof:name":"Chemma",
    "wof:placetype":"neighbourhood"
},
  "geometry": {"coordinates":[83.04389,19.04544],"type":"Point"}
}