{
  "type": "Feature",
  "properties": {
    "gn:admin1_code":"11.0",
    "gn:admin2_code":"33.0",
    "gn:asciiname":"Gadra",
    "gn:country_code":"IN",
    "gn:dem":1841,
    "gn:feature_class":"P",
    "gn:feature_code":"PPL",
    "gn:name":"Gadra",
    "gn:population":0,
    "gn:timezone":"Asia/Kolkata",
    "iso:country":"IN",
    "wof:name":"Gadra",
    "wof:placetype":"locality"
},
  "geometry": {"coordinates":[77.32254,31.18142000000001],"type":"Point"}
}