{
  "type": "Feature",
  "properties": {
    "iso:country":"IN",
    "ks:ks_alt_nam":"BODRABASA",
    "ks:ks_name":"Bodrabasa",
    "ks:ks_pop":165,
    "ks:ks_type":"HABITATION",
    "name:eng_x_preferred":[
        "Bodrabasa"
    ],
    "wof:name":"Bodrabasa",
    "wof:placetype":"locality",
    "wof:population":165
},
  "geometry": {"coordinates":[85.83748,22.685511],"type":"Point"}
}