{
  "type": "Feature",
  "properties": {
    "iso:country":"IN",
    "ks:ks_alt_nam":"aravtwadi",
    "ks:ks_name":"Aravtwadi",
    "ks:ks_pop":52,
    "ks:ks_type":"HABITATION",
    "ks:ks_uagg_main":0,
    "name:eng_x_preferred":[
        "Aravtwadi"
    ],
    "wof:name":"Aravtwadi",
    "wof:placetype":"neighbourhood",
    "wof:population":52
},
  "geometry": {"coordinates":[73.596958,17.456433],"type":"Point"}
}