{
  "type": "Feature",
  "properties": {
    "gn:admin1_code":"28.0",
    "gn:admin2_code":"332.0",
    "gn:asciiname":"Uttar Talsur",
    "gn:country_code":"IN",
    "gn:dem":31,
    "gn:feature_class":"P",
    "gn:feature_code":"PPL",
    "gn:name":"Uttar T\u0101lsur",
    "gn:population":0,
    "gn:timezone":"Asia/Kolkata",
    "iso:country":"IN",
    "wof:name":"Uttar Talsur",
    "wof:placetype":"neighbourhood"
},
  "geometry": {"coordinates":[87.85071000000001,25.37838],"type":"Point"}
}