{
  "type": "Feature",
  "properties": {
    "iso:country":"IN",
    "ks:ks_alt_nam":"ARAJUN KA PURWA",
    "ks:ks_name":"Arajun Ka Purwa",
    "ks:ks_pop":17,
    "ks:ks_type":"HABITATION",
    "ks:ks_uagg_main":0,
    "name:eng_x_preferred":[
        "Arajun Ka Purwa"
    ],
    "wof:name":"Arajun Ka Purwa",
    "wof:placetype":"neighbourhood",
    "wof:population":17
},
  "geometry": {"coordinates":[82.094435,26.35075],"type":"Point"}
}