{
  "type": "Feature",
  "properties": {
    "gn:admin1_code":"24.0",
    "gn:admin2_code":"131.0",
    "gn:asciiname":"Dagra",
    "gn:country_code":"IN",
    "gn:dem":237,
    "gn:feature_class":"P",
    "gn:feature_code":"PPL",
    "gn:name":"Dagra",
    "gn:population":0,
    "gn:timezone":"Asia/Kolkata",
    "iso:country":"IN",
    "wof:name":"Dagra",
    "wof:placetype":"locality"
},
  "geometry": {"coordinates":[74.42882,24.12992],"type":"Point"}
}