{
  "type": "Feature",
  "properties": {
    "iso:country":"IN",
    "ks:ks_name":"Navi Vasahat",
    "ks:ks_pop":150,
    "ks:ks_type":"HABITATION",
    "name:eng_x_preferred":[
        "Navi Vasahat"
    ],
    "wof:name":"Navi Vasahat",
    "wof:placetype":"locality",
    "wof:population":150
},
  "geometry": {"coordinates":[73.539817,22.7636],"type":"Point"}
}