{
  "type": "Feature",
  "properties": {
    "gn:admin1_code":"35.0",
    "gn:admin2_code":"457.0",
    "gn:asciiname":"Lachhi Tola",
    "gn:country_code":"IN",
    "gn:dem":592,
    "gn:feature_class":"P",
    "gn:feature_code":"PPL",
    "gn:name":"Lachh\u012b Tol\u0101",
    "gn:population":0,
    "gn:timezone":"Asia/Kolkata",
    "iso:country":"IN",
    "wof:name":"Lachhi Tola",
    "wof:placetype":"locality"
},
  "geometry": {"coordinates":[80.25747,22.20175],"type":"Point"}
}