{
  "type": "Feature",
  "properties": {
    "gn:admin1_code":"23.0",
    "gn:admin2_code":"46.0",
    "gn:asciiname":"Anup Dhiangarh",
    "gn:country_code":"IN",
    "gn:dem":202,
    "gn:feature_class":"P",
    "gn:feature_code":"PPL",
    "gn:name":"An\u016bp Dhi\u0101ngarh",
    "gn:population":0,
    "gn:timezone":"Asia/Kolkata",
    "iso:country":"IN",
    "name:und_x_variant":[
        "An\u016bp Dhi\u0101ngarh",
        "Machhi\u0101na"
    ],
    "wof:name":"Anup Dhiangarh",
    "wof:placetype":"locality"
},
  "geometry": {"coordinates":[74.86581,30.0593],"type":"Point"}
}