{
  "type": "Feature",
  "properties": {
    "gn:admin1_code":"9.0",
    "gn:admin2_code":"469.0",
    "gn:asciiname":"Bhagrodia",
    "gn:country_code":"IN",
    "gn:dem":200,
    "gn:feature_class":"P",
    "gn:feature_code":"PPL",
    "gn:name":"Bh\u0101grodia",
    "gn:population":0,
    "gn:timezone":"Asia/Kolkata",
    "iso:country":"IN",
    "wof:name":"Bhagrodia",
    "wof:placetype":"locality"
},
  "geometry": {"coordinates":[72.44473000000001,24.07287],"type":"Point"}
}