{
  "type": "Feature",
  "properties": {
    "gn:admin1_code":"11.0",
    "gn:admin2_code":"33.0",
    "gn:asciiname":"Khol",
    "gn:country_code":"IN",
    "gn:dem":2057,
    "gn:feature_class":"P",
    "gn:feature_code":"PPL",
    "gn:name":"Khol",
    "gn:population":0,
    "gn:timezone":"Asia/Kolkata",
    "iso:country":"IN",
    "name:asm_x_preferred":[
        "\u0996\u09cb\u09b2"
    ],
    "name:aze_x_preferred":[
        "M\u0131rdanqa"
    ],
    "name:ben_x_preferred":[
        "\u0996\u09cb\u09b2"
    ],
    "name:ces_x_preferred":[
        "Mridanga"
    ],
    "name:deu_x_preferred":[
        "Khol"
    ],
    "name:nno_x_preferred":[
        "Khol"
    ],
    "name:pol_x_preferred":[
        "Mridanga"
    ],
    "name:spa_x_preferred":[
        "Mridanga"
    ],
    "wof:name":"Khol",
    "wof:placetype":"locality"
},
  "geometry": {"coordinates":[77.31319999999999,31.14267000000001],"type":"Point"}
}