{
  "type": "Feature",
  "properties": {
    "iso:country":"IN",
    "ks:ks_name":"Benti",
    "ks:ks_pop":555,
    "ks:ks_type":"VILLAGE",
    "name:eng_x_preferred":[
        "Benti"
    ],
    "wof:name":"Benti",
    "wof:placetype":"locality",
    "wof:population":555
},
  "geometry": {"coordinates":[85.23548599999999,23.589075],"type":"Point"}
}