{
  "type": "Feature",
  "properties": {
    "iso:country":"IN",
    "ks:ks_name":"Ramchandra Sahu Tola",
    "ks:ks_pop":113,
    "ks:ks_type":"HABITATION",
    "name:eng_x_preferred":[
        "Ramchandra Sahu Tola"
    ],
    "wof:name":"Ramchandra Sahu Tola",
    "wof:placetype":"locality",
    "wof:population":113
},
  "geometry": {"coordinates":[84.501813,26.48716],"type":"Point"}
}