{
  "type": "Feature",
  "properties": {
    "iso:country":"IN",
    "name:ara_x_preferred":[
        "\u062b\u0646\u062f\u0627\u0644\u0627\u0645 \u0643\u0631\u064a\u0634\u0646\u0627\u0628\u0648\u0631\u0627\u0645"
    ],
    "name:ben_bn_x_preferred":[
        "\u09a5\u09be\u09a8\u09cd\u09a1\u09be\u09b2\u09be\u09ae\u0995\u09c3\u09b7\u09cd\u09a3\u09aa\u09c1\u09b0\u09ae"
    ],
    "name:ben_in_x_preferred":[
        "\u09a5\u09be\u09a8\u09cd\u09a1\u09be\u09b2\u09be\u09ae\u0995\u09c3\u09b7\u09cd\u09a3\u09aa\u09c1\u09b0\u09ae"
    ],
    "name:eng_x_preferred":[
        "Thandalamkrishnapuram"
    ],
    "name:guj_x_preferred":[
        "\u0aa5\u0a82\u0aa1\u0ab2\u0aae\u0a95\u0ac3\u0ab7\u0acd\u0aa3\u0aaa\u0ac1\u0ab0\u0aae\u0acd"
    ],
    "name:hin_x_preferred":[
        "\u0925\u0902\u0921\u0932\u092e\u0915\u0943\u0937\u094d\u0923\u093e\u092a\u0941\u0930\u092e"
    ],
    "name:kan_x_preferred":[
        "\u0ca4\u0cbe\u0c82\u0ca1\u0cbe\u0cb2\u0cae\u0ccd"
    ],
    "name:mal_x_preferred":[
        "\u0d24\u0d23\u0d4d\u0d1f\u0d32\u0d3e\u0d2e\u0d15\u0d43\u0d37\u0d4d\u0d23\u0d2a\u0d41\u0d30\u0d02"
    ],
    "name:mar_x_preferred":[
        "\u0925\u0902\u0921\u093e\u0932\u092e \u0915\u0943\u0937\u094d\u0923\u092a\u0941\u0930\u092e"
    ],
    "name:pan_x_preferred":[
        "\u0a20\u0a70\u0a21\u0a32\u0a2e\u0a15\u0a30\u0a3f\u0a36\u0a28\u0a3e\u0a2a\u0a41\u0a30\u0a2e"
    ],
    "name:tam_x_preferred":[
        "\u0ba4\u0ba3\u0bcd\u0b9f\u0bb2\u0bae\u0bcd\u0b95\u0bbf\u0bb0\u0bc1\u0bb7\u0bcd\u0ba3\u0baa\u0bc1\u0bb0\u0bae\u0bcd"
    ],
    "name:tel_x_preferred":[
        "\u0c25\u0c02\u0c21\u0c3e\u0c32\u0c02\u0c15\u0c43\u0c37\u0c4d\u0c23\u0c3e\u0c2a\u0c41\u0c30\u0c02"
    ],
    "name:urd_x_preferred":[
        "\u0679\u06be\u0646\u0688\u0644\u0645 \u06a9\u0631\u0634\u0646\u0627 \u067e\u0648\u0631\u0645"
    ],
    "qs:gn_local":0,
    "qs:local_max":1,
    "qs:local_sum":1,
    "qs:localhoods":1,
    "qs:name":"Thandalamkrishnapuram",
    "qs:name_adm0":"India",
    "qs:name_adm1":"Tamil Nadu",
    "qs:name_adm2":"Vellore",
    "qs:name_local":"Gandhinagar",
    "qs:photo_max":1,
    "qs:photo_sum":1,
    "qs:placetype":"Suburb",
    "qs:quad_count":1,
    "qs:woe_adm0":23424848,
    "qs:woe_adm1":2345758,
    "qs:woe_adm2":12586706,
    "qs:woe_lau":0,
    "qs:woe_local":29000227,
    "qs:woe_ver":"7.10.0",
    "wof:lang":[
        "eng"
    ],
    "wof:name":"Thandalamkrishnapuram",
    "wof:placetype":"neighbourhood"
},
  "geometry": {"coordinates":[79.109802,12.921583],"type":"Point"}
}