{
  "type": "Feature",
  "properties": {
    "iso:country":"IN",
    "name:eng_x_preferred":[
        "Thandalamkrishnapuram"
    ],
    "name:unk_x_variant":[
        "Thandalamkrishnapuram"
    ],
    "qs:gn_local":0,
    "qs:local_max":1,
    "qs:local_sum":1,
    "qs:localhoods":1,
    "qs:name":"Thandalamkrishnapuram",
    "qs:name_adm0":"India",
    "qs:name_adm1":"Tamil Nadu",
    "qs:name_adm2":"Vellore",
    "qs:name_local":"Gandhinagar",
    "qs:photo_max":1,
    "qs:photo_sum":1,
    "qs:placetype":"Suburb",
    "qs:quad_count":1,
    "qs:woe_adm0":23424848,
    "qs:woe_adm1":2345758,
    "qs:woe_adm2":12586706,
    "qs:woe_lau":0,
    "qs:woe_local":29000227,
    "qs:woe_ver":"7.10.0",
    "wof:lang":[
        "eng"
    ],
    "wof:name":"Thandalamkrishnapuram",
    "wof:placetype":"neighbourhood"
},
  "geometry": {"coordinates":[79.109802,12.921583],"type":"Point"}
}