{
  "type": "Feature",
  "properties": {
    "iso:country":"IN",
    "ks:ks_name":"Digwar",
    "ks:ks_pop":1835,
    "ks:ks_type":"VILLAGE",
    "name:eng_x_preferred":[
        "Digwar"
    ],
    "wof:name":"Digwar",
    "wof:placetype":"locality",
    "wof:population":1835
},
  "geometry": {"coordinates":[77.316901,26.282892],"type":"Point"}
}