{
  "type": "Feature",
  "properties": {
    "iso:country":"IN",
    "ks:ks_name":"Deonathpur",
    "ks:ks_pop":258,
    "ks:ks_type":"VILLAGE",
    "name:eng_x_preferred":[
        "Deonathpur"
    ],
    "wof:name":"Deonathpur",
    "wof:placetype":"locality",
    "wof:population":258
},
  "geometry": {"coordinates":[82.25186100000001,26.867095],"type":"Point"}
}