{
  "type": "Feature",
  "properties": {
    "gn:admin1_code":"35.0",
    "gn:admin2_code":"455.0",
    "gn:asciiname":"Kevlarijagannath",
    "gn:country_code":"IN",
    "gn:dem":761,
    "gn:feature_class":"P",
    "gn:feature_code":"PPL",
    "gn:name":"Kevl\u0101r\u012bjagann\u0101th",
    "gn:population":0,
    "gn:timezone":"Asia/Kolkata",
    "iso:country":"IN",
    "wof:name":"Kevlarijagannath",
    "wof:placetype":"locality"
},
  "geometry": {"coordinates":[79.27535,22.33273],"type":"Point"}
}