{
  "type": "Feature",
  "properties": {
    "iso:country":"IN",
    "ks:ks_name":"Gagraha",
    "ks:ks_pop":1373,
    "ks:ks_type":"HABITATION",
    "name:eng_x_preferred":[
        "Gagraha"
    ],
    "wof:name":"Gagraha",
    "wof:placetype":"locality",
    "wof:population":1373
},
  "geometry": {"coordinates":[85.683302,26.090033],"type":"Point"}
}