{
  "type": "Feature",
  "properties": {
    "gn:admin1_code":"36",
    "gn:admin2_code":"188.0",
    "gn:asciiname":"Chautara Babu",
    "gn:country_code":"IN",
    "gn:dem":83,
    "gn:feature_class":"P",
    "gn:feature_code":"PPL",
    "gn:name":"Chautara B\u0101bu",
    "gn:population":0,
    "gn:timezone":"Asia/Kolkata",
    "iso:country":"IN",
    "ks:ks_alt_nam":"Chautara B\u0101bu",
    "ks:ks_name":"Chautara Babu",
    "ks:ks_type":"VILLAGE",
    "ks:ks_uagg_main":0,
    "name:eng_x_preferred":[
        "Chautara Babu"
    ],
    "name:eng_x_variant":[
        "Chautara B\u0101bu"
    ],
    "wof:name":"Chautara Babu",
    "wof:placetype":"neighbourhood"
},
  "geometry": {"coordinates":[83.10765600000001,26.40946],"type":"Point"}
}