{
  "type": "Feature",
  "properties": {
    "iso:country":"IN",
    "ks:ks_name":"Rikamari",
    "ks:ks_pop":1437,
    "ks:ks_type":"VILLAGE",
    "ks:ks_uagg_main":0,
    "name:eng_x_preferred":[
        "Rikamari"
    ],
    "wof:name":"Rikamari",
    "wof:placetype":"neighbourhood",
    "wof:population":1437
},
  "geometry": {"coordinates":[92.579565,26.85858],"type":"Point"}
}