{
  "type": "Feature",
  "properties": {
    "iso:country":"IN",
    "ks:ks_name":"Netaji Colony",
    "ks:ks_pop":667,
    "ks:ks_type":"HABITATION",
    "name:eng_x_preferred":[
        "Netaji Colony"
    ],
    "wof:name":"Netaji Colony",
    "wof:placetype":"locality",
    "wof:population":667
},
  "geometry": {"coordinates":[88.865954,22.100995],"type":"Point"}
}