{
  "type": "Feature",
  "properties": {
    "iso:country":"IN",
    "ks:ks_name":"Nadibag",
    "ks:ks_pop":507,
    "ks:ks_type":"HABITATION",
    "ks:ks_uagg_main":0,
    "name:eng_x_preferred":[
        "Nadibag"
    ],
    "wof:name":"Nadibag",
    "wof:placetype":"neighbourhood",
    "wof:population":507
},
  "geometry": {"coordinates":[74.285113,14.641739],"type":"Point"}
}