{
  "type": "Feature",
  "properties": {
    "iso:country":"IN",
    "ks:ks_name":"143 RD",
    "ks:ks_pop":111,
    "ks:ks_type":"VILLAGE",
    "name:eng_x_preferred":[
        "143 RD"
    ],
    "wof:name":"143 RD",
    "wof:placetype":"locality",
    "wof:population":111
},
  "geometry": {"coordinates":[74.173906,29.237595],"type":"Point"}
}