{
  "type": "Feature",
  "properties": {
    "iso:country":"IN",
    "ks:ks_alt_nam":"Singrapam supa",
    "ks:ks_name":"Singrapam Supa",
    "ks:ks_pop":353,
    "ks:ks_type":"HABITATION",
    "ks:ks_uagg_main":0,
    "name:eng_x_preferred":[
        "Singrapam Supa"
    ],
    "wof:name":"Singrapam Supa",
    "wof:placetype":"neighbourhood",
    "wof:population":353
},
  "geometry": {"coordinates":[91.647589,26.567425],"type":"Point"}
}