{
  "type": "Feature",
  "properties": {
    "gn:admin1_code":"39.0",
    "gn:admin2_code":"68.0",
    "gn:asciiname":"Dallawala Khurd",
    "gn:country_code":"IN",
    "gn:dem":228,
    "gn:feature_class":"P",
    "gn:feature_code":"PPL",
    "gn:name":"Dall\u0101w\u0101la Khurd",
    "gn:population":0,
    "gn:timezone":"Asia/Kolkata",
    "iso:country":"IN",
    "wof:name":"Dallawala Khurd",
    "wof:placetype":"locality"
},
  "geometry": {"coordinates":[77.98408000000001,29.59434000000001],"type":"Point"}
}