{
  "type": "Feature",
  "properties": {
    "iso:country":"IN",
    "ks:ks_name":"Dalipur",
    "ks:ks_pop":1068,
    "ks:ks_type":"HABITATION",
    "name:eng_x_preferred":[
        "Dalipur"
    ],
    "wof:name":"Dalipur",
    "wof:placetype":"locality",
    "wof:population":1068
},
  "geometry": {"coordinates":[82.78674100000001,25.414674],"type":"Point"}
}