{
  "type": "Feature",
  "properties": {
    "gn:admin1_code":"35",
    "gn:admin2_code":"455.0",
    "gn:asciiname":"Buchanwari",
    "gn:country_code":"IN",
    "gn:dem":790,
    "gn:feature_class":"P",
    "gn:feature_code":"PPL",
    "gn:name":"B\u016bchanw\u0101ri",
    "gn:population":0,
    "gn:timezone":"Asia/Kolkata",
    "iso:country":"IN",
    "ks:ks_name":"Buchanwadi",
    "ks:ks_pop":301,
    "ks:ks_type":"VILLAGE",
    "name:eng_x_preferred":[
        "Buchanwadi"
    ],
    "name:eng_x_variant":[
        "Buchanwari"
    ],
    "wof:name":"Buchanwadi",
    "wof:placetype":"locality",
    "wof:population":301
},
  "geometry": {"coordinates":[78.37081499999999,22.058884],"type":"Point"}
}