{
  "type": "Feature",
  "properties": {
    "iso:country":"IN",
    "ks:ks_name":"Surajbalipur",
    "ks:ks_pop":200,
    "ks:ks_type":"HABITATION",
    "name:eng_x_preferred":[
        "Surajbalipur"
    ],
    "wof:name":"Surajbalipur",
    "wof:placetype":"locality",
    "wof:population":200
},
  "geometry": {"coordinates":[80.92399399999999,27.763783],"type":"Point"}
}