{
  "type": "Feature",
  "properties": {
    "gn:admin1_code":"35",
    "gn:admin2_code":"456.0",
    "gn:asciiname":"Kharrapat",
    "gn:country_code":"IN",
    "gn:dem":526,
    "gn:feature_class":"P",
    "gn:feature_code":"PPL",
    "gn:name":"Kharr\u0101p\u0101t",
    "gn:population":0,
    "gn:timezone":"Asia/Kolkata",
    "iso:country":"IN",
    "wof:name":"Kharrapat",
    "wof:placetype":"locality"
},
  "geometry": {"coordinates":[79.72584999999999,22.07935],"type":"Point"}
}