{
  "type": "Feature",
  "properties": {
    "iso:country":"IN",
    "ks:ks_alt_nam":"Kootamveli north",
    "ks:ks_name":"Kootamveli North",
    "ks:ks_pop":1105,
    "ks:ks_type":"HABITATION",
    "name:eng_x_preferred":[
        "Kootamveli North"
    ],
    "wof:name":"Kootamveli North",
    "wof:placetype":"locality",
    "wof:population":1105
},
  "geometry": {"coordinates":[76.695851,10.042064],"type":"Point"}
}