{
  "type": "Feature",
  "properties": {
    "gn:admin1_code":"11",
    "gn:admin2_code":"33.0",
    "gn:asciiname":"Jajwara",
    "gn:country_code":"IN",
    "gn:dem":1261,
    "gn:feature_class":"P",
    "gn:feature_code":"PPL",
    "gn:name":"Jajwara",
    "gn:population":0,
    "gn:timezone":"Asia/Kolkata",
    "iso:country":"IN",
    "wof:name":"Jajwara",
    "wof:placetype":"locality"
},
  "geometry": {"coordinates":[77.05343000000001,31.09589],"type":"Point"}
}