{
  "type": "Feature",
  "properties": {
    "gn:admin1_code":"40.0",
    "gn:admin2_code":"533.0",
    "gn:asciiname":"Kuknur",
    "gn:country_code":"IN",
    "gn:dem":335,
    "gn:feature_class":"P",
    "gn:feature_code":"PPL",
    "gn:name":"K\u016bkn\u016br",
    "gn:population":0,
    "gn:timezone":"Asia/Kolkata",
    "iso:country":"IN",
    "name:ceb_x_preferred":[
        "Kukn\u016br"
    ],
    "name:deu_x_preferred":[
        "Kuknur"
    ],
    "name:kan_x_preferred":[
        "\u0c95\u0cc2\u0c95\u0ca8\u0cc2\u0cb0"
    ],
    "name:mal_x_preferred":[
        "\u0d15\u0d41\u0d15\u0d4d\u0d28\u0d42\u0d7c"
    ],
    "name:swe_x_preferred":[
        "Kukn\u016br"
    ],
    "wof:name":"Kuknur",
    "wof:placetype":"locality"
},
  "geometry": {"coordinates":[78.41896,18.7988],"type":"Point"}
}