{
  "type": "Feature",
  "properties": {
    "iso:country":"IN",
    "ks:ks_name":"Manjhitola",
    "ks:ks_pop":121,
    "ks:ks_type":"HABITATION",
    "name:eng_x_preferred":[
        "Manjhitola"
    ],
    "wof:name":"Manjhitola",
    "wof:placetype":"locality",
    "wof:population":121
},
  "geometry": {"coordinates":[85.181817,23.636839],"type":"Point"}
}