{
  "type": "Feature",
  "properties": {
    "gn:admin1_code":"11",
    "gn:admin2_code":"34.0",
    "gn:asciiname":"Tahsil",
    "gn:country_code":"IN",
    "gn:dem":2497,
    "gn:feature_class":"P",
    "gn:feature_code":"PPL",
    "gn:name":"Tahs\u012bl",
    "gn:population":0,
    "gn:timezone":"Asia/Kolkata",
    "iso:country":"IN",
    "wof:name":"Tahsil",
    "wof:placetype":"locality"
},
  "geometry": {"coordinates":[78.44846,31.60153],"type":"Point"}
}