{
  "type": "Feature",
  "properties": {
    "iso:country":"IN",
    "ks:ks_name":"Rajgiri",
    "ks:ks_pop":1365,
    "ks:ks_type":"HABITATION",
    "name:eng_x_preferred":[
        "Rajgiri"
    ],
    "wof:name":"Rajgiri",
    "wof:placetype":"locality",
    "wof:population":1365
},
  "geometry": {"coordinates":[76.87096099999999,9.136994],"type":"Point"}
}