{
  "type": "Feature",
  "properties": {
    "gn:admin1_code":"24",
    "gn:admin2_code":"125.0",
    "gn:asciiname":"Rati Mauri",
    "gn:country_code":"IN",
    "gn:dem":262,
    "gn:feature_class":"P",
    "gn:feature_code":"PPL",
    "gn:name":"R\u0101ti Mauri",
    "gn:population":0,
    "gn:timezone":"Asia/Kolkata",
    "iso:country":"IN",
    "ks:ks_name":"Rati Mahuri",
    "ks:ks_pop":608,
    "ks:ks_type":"VILLAGE",
    "name:eng_x_preferred":[
        "Rati Mahuri"
    ],
    "name:eng_x_variant":[
        "Rati Mauri"
    ],
    "wof:name":"Rati Mahuri",
    "wof:placetype":"locality",
    "wof:population":608
},
  "geometry": {"coordinates":[74.402447,23.204794],"type":"Point"}
}