{
  "type": "Feature",
  "properties": {
    "gn:admin1_code":"13.0",
    "gn:admin2_code":"588.0",
    "gn:asciiname":"Majibailu",
    "gn:country_code":"IN",
    "gn:dem":23,
    "gn:feature_class":"P",
    "gn:feature_code":"PPLL",
    "gn:name":"Majibailu",
    "gn:population":0,
    "gn:timezone":"Asia/Kolkata",
    "iso:country":"IN",
    "ks:ks_name":"Majibail",
    "ks:ks_pop":1099,
    "ks:ks_type":"HABITATION",
    "name:eng_x_preferred":[
        "Majibail"
    ],
    "name:eng_x_variant":[
        "Majibailu"
    ],
    "wof:name":"Majibail",
    "wof:placetype":"locality",
    "wof:population":1099
},
  "geometry": {"coordinates":[74.910737,12.691099],"type":"Point"}
}