{
  "type": "Feature",
  "properties": {
    "gn:admin1_code":"11",
    "gn:admin2_code":"23.0",
    "gn:asciiname":"Dalen",
    "gn:country_code":"IN",
    "gn:dem":2054,
    "gn:feature_class":"P",
    "gn:feature_code":"PPL",
    "gn:name":"Dalen",
    "gn:population":0,
    "gn:timezone":"Asia/Kolkata",
    "iso:country":"IN",
    "name:ceb_x_preferred":[
        "Dalen"
    ],
    "name:cym_x_preferred":[
        "Dalen"
    ],
    "name:fra_x_preferred":[
        "Dalen"
    ],
    "name:fry_x_preferred":[
        "Dalen"
    ],
    "name:ita_x_preferred":[
        "Dalen"
    ],
    "name:nld_x_preferred":[
        "Dalen"
    ],
    "name:pol_x_preferred":[
        "Dalen"
    ],
    "wof:name":"Dalen",
    "wof:placetype":"locality"
},
  "geometry": {"coordinates":[76.27412,32.56662],"type":"Point"}
}