{
  "type": "Feature",
  "properties": {
    "gn:admin1_code":"24.0",
    "gn:admin2_code":"120",
    "gn:asciiname":"Bamolaya",
    "gn:country_code":"IN",
    "gn:dem":314,
    "gn:feature_class":"P",
    "gn:feature_code":"PPL",
    "gn:name":"B\u0101mol\u0101ya",
    "gn:population":0,
    "gn:timezone":"Asia/Kolkata",
    "iso:country":"IN",
    "name:und_x_variant":[
        "B\u0101mol\u0101ya",
        "B\u0101mcl\u0101ya"
    ],
    "wof:name":"Bamolaya",
    "wof:placetype":"locality"
},
  "geometry": {"coordinates":[75.66054,25.82695],"type":"Point"}
}