{
  "type": "Feature",
  "properties": {
    "iso:country":"IN",
    "ks:ks_name":"Kauli Kanyal",
    "ks:ks_pop":1130,
    "ks:ks_type":"VILLAGE",
    "name:eng_x_preferred":[
        "Kauli Kanyal"
    ],
    "wof:name":"Kauli Kanyal",
    "wof:placetype":"locality",
    "wof:population":1130
},
  "geometry": {"coordinates":[80.358086,29.826795],"type":"Point"}
}