{
  "type": "Feature",
  "properties": {
    "iso:country":"IN",
    "ks:ks_name":"Malibaritari",
    "ks:ks_pop":666,
    "ks:ks_type":"VILLAGE",
    "ks:ks_uagg_main":0,
    "name:eng_x_preferred":[
        "Malibaritari"
    ],
    "wof:name":"Malibaritari",
    "wof:placetype":"neighbourhood",
    "wof:population":666
},
  "geometry": {"coordinates":[91.795085,26.469938],"type":"Point"}
}