{
  "type": "Feature",
  "properties": {
    "iso:country":"IN",
    "ks:ks_name":"Chak Berain",
    "ks:ks_pop":306,
    "ks:ks_type":"HABITATION",
    "name:eng_x_preferred":[
        "Chak Berain"
    ],
    "wof:name":"Chak Berain",
    "wof:placetype":"locality",
    "wof:population":306
},
  "geometry": {"coordinates":[86.852448,25.180802],"type":"Point"}
}