{
  "type": "Feature",
  "properties": {
    "iso:country":"IN",
    "ks:ks_name":"Badkhera Mal.",
    "ks:ks_pop":880,
    "ks:ks_type":"VILLAGE",
    "name:eng_x_preferred":[
        "Badkhera Mal."
    ],
    "wof:name":"Badkhera Mal.",
    "wof:placetype":"locality",
    "wof:population":880
},
  "geometry": {"coordinates":[80.644352,23.166056],"type":"Point"}
}