{
  "type": "Feature",
  "properties": {
    "gn:admin1_code":"11.0",
    "gn:admin2_code":"023",
    "gn:asciiname":"Almi",
    "gn:country_code":"IN",
    "gn:dem":1353,
    "gn:feature_class":"P",
    "gn:feature_code":"PPL",
    "gn:name":"Almi",
    "gn:population":0,
    "gn:timezone":"Asia/Kolkata",
    "iso:country":"IN",
    "name:und_x_variant":[
        "Almai"
    ],
    "wof:name":"Almi",
    "wof:placetype":"locality"
},
  "geometry": {"coordinates":[76.3849,32.5493],"type":"Point"}
}