{
  "type": "Feature",
  "properties": {
    "iso:country":"IN",
    "ks:ks_name":"P Venkatayapalli",
    "ks:ks_pop":512,
    "ks:ks_type":"HABITATION",
    "name:eng_x_preferred":[
        "P Venkatayapalli"
    ],
    "wof:name":"P Venkatayapalli",
    "wof:placetype":"locality",
    "wof:population":512
},
  "geometry": {"coordinates":[79.239081,15.492385],"type":"Point"}
}