{
  "type": "Feature",
  "properties": {
    "iso:country":"IN",
    "ks:ks_alt_nam":"Barahtha kala",
    "ks:ks_name":"Barahtha Kala",
    "ks:ks_pop":295,
    "ks:ks_type":"HABITATION",
    "name:eng_x_preferred":[
        "Barahtha Kala"
    ],
    "wof:name":"Barahtha Kala",
    "wof:placetype":"locality",
    "wof:population":295
},
  "geometry": {"coordinates":[80.674718,24.849222],"type":"Point"}
}