{
  "type": "Feature",
  "properties": {
    "iso:country":"IN",
    "ks:ks_name":"Loniyan Purwa",
    "ks:ks_pop":140,
    "ks:ks_type":"HABITATION",
    "name:eng_x_preferred":[
        "Loniyan Purwa"
    ],
    "wof:name":"Loniyan Purwa",
    "wof:placetype":"locality",
    "wof:population":140
},
  "geometry": {"coordinates":[81.50326200000001,27.487188],"type":"Point"}
}