{
  "type": "Feature",
  "properties": {
    "iso:country":"IN",
    "ks:ks_name":"Pudur",
    "ks:ks_pop":325,
    "ks:ks_type":"HABITATION",
    "name:eng_x_preferred":[
        "Pudur"
    ],
    "wof:name":"Pudur",
    "wof:placetype":"locality",
    "wof:population":325
},
  "geometry": {"coordinates":[78.916605,12.997016],"type":"Point"}
}