{
  "type": "Feature",
  "properties": {
    "iso:country":"IN",
    "ks:ks_name":"Kudyachamach",
    "ks:ks_pop":122,
    "ks:ks_type":"HABITATION",
    "name:eng_x_preferred":[
        "Kudyachamach"
    ],
    "wof:name":"Kudyachamach",
    "wof:placetype":"locality",
    "wof:population":122
},
  "geometry": {"coordinates":[73.685,17.017778],"type":"Point"}
}