{
  "type": "Feature",
  "properties": {
    "iso:country":"IN",
    "ks:ks_name":"Kalron Ki Dhani",
    "ks:ks_pop":97,
    "ks:ks_type":"HABITATION",
    "name:eng_x_preferred":[
        "Kalron Ki Dhani"
    ],
    "wof:name":"Kalron Ki Dhani",
    "wof:placetype":"locality",
    "wof:population":97
},
  "geometry": {"coordinates":[71.491652,27.761364],"type":"Point"}
}