{
  "type": "Feature",
  "properties": {
    "gn:admin1_code":"34.0",
    "gn:admin2_code":"210.0",
    "gn:asciiname":"Kajla",
    "gn:country_code":"IN",
    "gn:dem":81,
    "gn:feature_class":"P",
    "gn:feature_code":"PPL",
    "gn:name":"Kajla",
    "gn:population":0,
    "gn:timezone":"Asia/Kolkata",
    "iso:country":"IN",
    "name:por_x_preferred":[
        "Kajla"
    ],
    "wof:name":"Kajla",
    "wof:placetype":"neighbourhood"
},
  "geometry": {"coordinates":[87.88160999999999,26.4611],"type":"Point"}
}