{
  "type": "Feature",
  "properties": {
    "gn:admin1_code":"2",
    "gn:admin2_code":"545.0",
    "gn:asciiname":"Polava",
    "gn:country_code":"IN",
    "gn:dem":1113,
    "gn:feature_class":"P",
    "gn:feature_code":"PPL",
    "gn:name":"Polava",
    "gn:population":0,
    "gn:timezone":"Asia/Kolkata",
    "iso:country":"IN",
    "wof:name":"Polava",
    "wof:placetype":"locality"
},
  "geometry": {"coordinates":[81.90666,17.82857000000001],"type":"Point"}
}