{
  "type": "Feature",
  "properties": {
    "iso:country":"IN",
    "ks:ks_name":"Vinayakabattrumane",
    "ks:ks_pop":25,
    "ks:ks_type":"HABITATION",
    "name:eng_x_preferred":[
        "Vinayakabattrumane"
    ],
    "wof:name":"Vinayakabattrumane",
    "wof:placetype":"locality",
    "wof:population":25
},
  "geometry": {"coordinates":[74.925414,13.881264],"type":"Point"}
}