{
  "type": "Feature",
  "properties": {
    "gn:admin1_code":"36",
    "gn:admin2_code":"188.0",
    "gn:asciiname":"Pipra Nandu",
    "gn:country_code":"IN",
    "gn:dem":83,
    "gn:feature_class":"P",
    "gn:feature_code":"PPL",
    "gn:name":"Pipra Nandu",
    "gn:population":0,
    "gn:timezone":"Asia/Kolkata",
    "iso:country":"IN",
    "ks:ks_name":"Pipra Nandu",
    "ks:ks_type":"VILLAGE",
    "ks:ks_uagg_main":0,
    "name:eng_x_preferred":[
        "Pipra Nandu"
    ],
    "wof:name":"Pipra Nandu",
    "wof:placetype":"neighbourhood"
},
  "geometry": {"coordinates":[83.22248999999999,26.43711],"type":"Point"}
}