{
  "type": "Feature",
  "properties": {
    "gn:admin1_code":"11.0",
    "gn:admin2_code":"26.0",
    "gn:asciiname":"Dahgaon",
    "gn:country_code":"IN",
    "gn:dem":1151,
    "gn:feature_class":"P",
    "gn:feature_code":"PPL",
    "gn:name":"Dahgaon",
    "gn:population":0,
    "gn:timezone":"Asia/Kolkata",
    "iso:country":"IN",
    "wof:name":"Dahgaon",
    "wof:placetype":"locality"
},
  "geometry": {"coordinates":[77.55154,31.43787],"type":"Point"}
}