{
  "type": "Feature",
  "properties": {
    "gn:admin1_code":"16.0",
    "gn:admin2_code":"497.0",
    "gn:asciiname":"Khairala",
    "gn:country_code":"IN",
    "gn:dem":251,
    "gn:feature_class":"P",
    "gn:feature_code":"PPL",
    "gn:name":"Khair\u0101la",
    "gn:population":0,
    "gn:timezone":"Asia/Kolkata",
    "iso:country":"IN",
    "name:ceb_x_preferred":[
        "Khairala"
    ],
    "name:mai_x_preferred":[
        "\u0916\u0948\u0930\u093e\u0932\u093e"
    ],
    "name:msa_x_preferred":[
        "Khairala"
    ],
    "name:nep_x_preferred":[
        "\u0916\u0948\u0930\u093e\u0932\u093e"
    ],
    "name:new_x_preferred":[
        "\u0916\u0948\u0930\u093e\u0932\u093e"
    ],
    "name:pol_x_preferred":[
        "Khairala"
    ],
    "wof:name":"Khairala",
    "wof:placetype":"locality"
},
  "geometry": {"coordinates":[74.1478,21.3107],"type":"Point"}
}