{
  "type": "Feature",
  "properties": {
    "gn:admin1_code":"40",
    "gn:admin2_code":"540.0",
    "gn:asciiname":"Kotta Tanda",
    "gn:country_code":"IN",
    "gn:dem":470,
    "gn:feature_class":"P",
    "gn:feature_code":"PPL",
    "gn:name":"Kotta T\u0101nda",
    "gn:population":0,
    "gn:timezone":"Asia/Kolkata",
    "iso:country":"IN",
    "wof:name":"Kotta Tanda",
    "wof:placetype":"locality"
},
  "geometry": {"coordinates":[79.18194,17.97184],"type":"Point"}
}