{
  "type": "Feature",
  "properties": {
    "gn:admin1_code":"39.0",
    "gn:admin2_code":"061",
    "gn:asciiname":"Purankot",
    "gn:country_code":"IN",
    "gn:dem":1042,
    "gn:feature_class":"P",
    "gn:feature_code":"PPL",
    "gn:name":"Pur\u0101nkot",
    "gn:population":0,
    "gn:timezone":"Asia/Kolkata",
    "iso:country":"IN",
    "ks:ks_alt_nam":"Pur\u0101nkot",
    "ks:ks_name":"Purankot",
    "ks:ks_type":"VILLAGE",
    "name:eng_x_preferred":[
        "Purankot"
    ],
    "name:eng_x_variant":[
        "Pur\u0101nkot"
    ],
    "wof:name":"Purankot",
    "wof:placetype":"locality"
},
  "geometry": {"coordinates":[78.57642800000001,29.834753],"type":"Point"}
}