{
  "type": "Feature",
  "properties": {
    "iso:country":"IN",
    "ks:ks_name":"Abadi Khas",
    "ks:ks_pop":122,
    "ks:ks_type":"HABITATION",
    "name:eng_x_preferred":[
        "Abadi Khas"
    ],
    "wof:name":"Abadi Khas",
    "wof:placetype":"locality",
    "wof:population":122
},
  "geometry": {"coordinates":[83.50773100000001,23.947343],"type":"Point"}
}