{
  "type": "Feature",
  "properties": {
    "gn:admin1_code":"36",
    "gn:asciiname":"Parasidhai",
    "gn:country_code":"IN",
    "gn:dem":314,
    "gn:feature_class":"P",
    "gn:feature_code":"PPL",
    "gn:name":"Parasidh\u0101i",
    "gn:population":0,
    "gn:timezone":"Asia/Kolkata",
    "iso:country":"IN",
    "ks:ks_alt_nam":"Parasidh\u0101i",
    "ks:ks_name":"Parasidhai",
    "ks:ks_type":"VILLAGE",
    "name:eng_x_preferred":[
        "Parasidhai"
    ],
    "name:eng_x_variant":[
        "Parasidh\u0101i"
    ],
    "wof:name":"Parasidhai",
    "wof:placetype":"locality"
},
  "geometry": {"coordinates":[82.763177,24.333882],"type":"Point"}
}