{
  "type": "Feature",
  "properties": {
    "iso:country":"IN",
    "ks:ks_name":"Motipura Gamtal",
    "ks:ks_pop":253,
    "ks:ks_type":"HABITATION",
    "name:eng_x_preferred":[
        "Motipura Gamtal"
    ],
    "wof:name":"Motipura Gamtal",
    "wof:placetype":"locality",
    "wof:population":253
},
  "geometry": {"coordinates":[73.591972,23.37425],"type":"Point"}
}