{
  "type": "Feature",
  "properties": {
    "gn:admin1_code":"19.0",
    "gn:admin2_code":"571.0",
    "gn:asciiname":"Aslipur",
    "gn:country_code":"IN",
    "gn:dem":800,
    "gn:feature_class":"P",
    "gn:feature_code":"PPL",
    "gn:name":"Aslipur",
    "gn:population":0,
    "gn:timezone":"Asia/Kolkata",
    "iso:country":"IN",
    "wof:name":"Aslipur",
    "wof:placetype":"locality"
},
  "geometry": {"coordinates":[77.00355999999999,13.39153],"type":"Point"}
}