{
  "type": "Feature",
  "properties": {
    "iso:country":"IN",
    "ks:ks_name":"Edayanvayal",
    "ks:ks_pop":126,
    "ks:ks_type":"VILLAGE",
    "name:eng_x_preferred":[
        "Edayanvayal"
    ],
    "wof:name":"Edayanvayal",
    "wof:placetype":"locality",
    "wof:population":126
},
  "geometry": {"coordinates":[78.945348,10.137237],"type":"Point"}
}