{
  "type": "Feature",
  "properties": {
    "iso:country":"IN",
    "ks:ks_name":"Srirampuram",
    "ks:ks_pop":162,
    "ks:ks_type":"HABITATION",
    "name:eng_x_preferred":[
        "Srirampuram"
    ],
    "wof:name":"Srirampuram",
    "wof:placetype":"locality",
    "wof:population":162
},
  "geometry": {"coordinates":[82.641524,17.485882],"type":"Point"}
}