{
  "type": "Feature",
  "properties": {
    "iso:country":"IN",
    "qs:name":"Jambuladinne",
    "qs:name_adm0":"India",
    "qs:name_adm1":"Andhra Pradesh",
    "qs:photos":1,
    "qs:photos_1k":1,
    "qs:photos_9k":1,
    "qs:photos_9r":1,
    "qs:photos_all":1,
    "qs:photos_sr":1,
    "qs:placetype":"Town",
    "qs:pop_sr":"0",
    "wof:name":"Jambuladinne",
    "wof:placetype":"locality"
},
  "geometry": {"coordinates":[77.59888100000001,14.829464],"type":"Point"}
}