{
  "type": "Feature",
  "properties": {
    "gn:admin1_code":"38.0",
    "gn:admin2_code":"353.0",
    "gn:asciiname":"Karipahari",
    "gn:country_code":"IN",
    "gn:dem":166,
    "gn:feature_class":"P",
    "gn:feature_code":"PPL",
    "gn:name":"K\u0101ripah\u0101ri",
    "gn:population":0,
    "gn:timezone":"Asia/Kolkata",
    "iso:country":"IN",
    "ks:ks_alt_nam":"K\u0101ripah\u0101ri",
    "ks:ks_name":"Karipahari",
    "ks:ks_pop":495,
    "ks:ks_type":"VILLAGE",
    "name:eng_x_preferred":[
        "Karipahari"
    ],
    "name:eng_x_variant":[
        "K\u0101ripah\u0101ri"
    ],
    "wof:name":"Karipahari",
    "wof:placetype":"locality",
    "wof:population":495
},
  "geometry": {"coordinates":[87.57941599999999,24.630738],"type":"Point"}
}