{
  "type": "Feature",
  "properties": {
    "gn:admin1_code":"38.0",
    "gn:admin2_code":"348.0",
    "gn:asciiname":"Semaria",
    "gn:country_code":"IN",
    "gn:dem":367,
    "gn:feature_class":"P",
    "gn:feature_code":"PPL",
    "gn:name":"Semari\u0101",
    "gn:population":0,
    "gn:timezone":"Asia/Kolkata",
    "iso:country":"IN",
    "name:ben_x_preferred":[
        "\u09b8\u09c7\u09ae\u09be\u09b0\u09bf\u09af\u09bc\u09be"
    ],
    "name:bpy_x_preferred":[
        "\u09b8\u09c7\u09ae\u09be\u09b0\u09bf\u09af\u09bc\u09be"
    ],
    "name:ceb_x_preferred":[
        "Simaria"
    ],
    "name:hin_x_preferred":[
        "\u0938\u0947\u092e\u0930\u093f\u092f\u093e"
    ],
    "name:ita_x_preferred":[
        "Semaria"
    ],
    "name:mlg_x_preferred":[
        "Semaria"
    ],
    "name:msa_x_preferred":[
        "Semaria"
    ],
    "name:nld_x_preferred":[
        "Semaria"
    ],
    "name:por_x_preferred":[
        "Semaria"
    ],
    "name:swe_x_preferred":[
        "Simaria"
    ],
    "name:vie_x_preferred":[
        "Semaria"
    ],
    "name:zho_x_preferred":[
        "\u585e\u9a6c\u91cc\u4e9a"
    ],
    "wof:name":"Semaria",
    "wof:placetype":"locality"
},
  "geometry": {"coordinates":[85.52155,24.33997],"type":"Point"}
}