{
  "type": "Feature",
  "properties": {
    "gn:admin1_code":"40.0",
    "gn:admin2_code":"532.0",
    "gn:asciiname":"Digra",
    "gn:country_code":"IN",
    "gn:dem":132,
    "gn:feature_class":"P",
    "gn:feature_code":"PPL",
    "gn:name":"Digra",
    "gn:population":0,
    "gn:timezone":"Asia/Kolkata",
    "iso:country":"IN",
    "wof:name":"Digra",
    "wof:placetype":"locality"
},
  "geometry": {"coordinates":[79.87671,19.22378],"type":"Point"}
}