{
  "type": "Feature",
  "properties": {
    "gn:admin1_code":"25.0",
    "gn:admin2_code":"611.0",
    "gn:asciiname":"Kannamvayal",
    "gn:country_code":"IN",
    "gn:dem":930,
    "gn:feature_class":"P",
    "gn:feature_code":"PPL",
    "gn:name":"Kannamvayal",
    "gn:population":0,
    "gn:timezone":"Asia/Kolkata",
    "iso:country":"IN",
    "wof:name":"Kannamvayal",
    "wof:placetype":"locality"
},
  "geometry": {"coordinates":[76.45038000000002,11.52779],"type":"Point"}
}