{
  "type": "Feature",
  "properties": {
    "gn:admin1_code":"35.0",
    "gn:admin2_code":"440",
    "gn:asciiname":"Bamnala",
    "gn:country_code":"IN",
    "gn:dem":253,
    "gn:feature_class":"P",
    "gn:feature_code":"PPL",
    "gn:name":"Bamn\u0101la",
    "gn:population":0,
    "gn:timezone":"Asia/Kolkata",
    "iso:country":"IN",
    "name:und_x_variant":[
        "Banm\u0101la",
        "Bamn\u0101la"
    ],
    "wof:name":"Bamnala",
    "wof:placetype":"locality"
},
  "geometry": {"coordinates":[75.8661,21.81575],"type":"Point"}
}