{
  "type": "Feature",
  "properties": {
    "gn:admin1_code":"19.0",
    "gn:admin2_code":"574.0",
    "gn:asciiname":"Mudenahalli",
    "gn:country_code":"IN",
    "gn:dem":835,
    "gn:feature_class":"P",
    "gn:feature_code":"PPL",
    "gn:name":"Mudenahalli",
    "gn:population":0,
    "gn:timezone":"Asia/Kolkata",
    "iso:country":"IN",
    "ks:ks_name":"Muddanahalli",
    "ks:ks_pop":1042,
    "ks:ks_type":"VILLAGE",
    "name:eng_x_preferred":[
        "Muddanahalli"
    ],
    "name:eng_x_variant":[
        "Mudenahalli"
    ],
    "wof:name":"Muddanahalli",
    "wof:placetype":"locality",
    "wof:population":1042
},
  "geometry": {"coordinates":[76.247321,13.300901],"type":"Point"}
}