{
  "type": "Feature",
  "properties": {
    "gn:admin1_code":"36.0",
    "gn:admin2_code":"186.0",
    "gn:asciiname":"Pasnara",
    "gn:country_code":"IN",
    "gn:dem":89,
    "gn:feature_class":"P",
    "gn:feature_code":"PPL",
    "gn:name":"Pasn\u0101ra",
    "gn:population":0,
    "gn:timezone":"Asia/Kolkata",
    "iso:country":"IN",
    "ks:ks_alt_nam":"Pasn\u0101ra",
    "ks:ks_name":"Pasnara",
    "ks:ks_pop":995,
    "ks:ks_type":"VILLAGE",
    "ks:ks_uagg_main":0,
    "name:eng_x_preferred":[
        "Pasnara"
    ],
    "name:eng_x_variant":[
        "Pasn\u0101ra"
    ],
    "wof:name":"Pasnara",
    "wof:placetype":"neighbourhood",
    "wof:population":995
},
  "geometry": {"coordinates":[82.982677,27.027151],"type":"Point"}
}