{
  "type": "Feature",
  "properties": {
    "iso:country":"IN",
    "ks:ks_name":"Timapenta",
    "ks:ks_pop":104,
    "ks:ks_type":"HABITATION",
    "name:eng_x_preferred":[
        "Timapenta"
    ],
    "wof:name":"Timapenta",
    "wof:placetype":"locality",
    "wof:population":104
},
  "geometry": {"coordinates":[81.32984999999999,18.365903],"type":"Point"}
}