{
  "type": "Feature",
  "properties": {
    "gn:admin1_code":"38.0",
    "gn:admin2_code":"360.0",
    "gn:asciiname":"Donai Kalan",
    "gn:country_code":"IN",
    "gn:dem":441,
    "gn:feature_class":"P",
    "gn:feature_code":"PPL",
    "gn:name":"Donai Kal\u0101n",
    "gn:population":0,
    "gn:timezone":"Asia/Kolkata",
    "iso:country":"IN",
    "ks:ks_alt_nam":"Donai Kal\u0101n",
    "ks:ks_name":"Donai Kalan",
    "ks:ks_pop":1278,
    "ks:ks_type":"VILLAGE",
    "ks:ks_uagg_main":0,
    "name:eng_x_preferred":[
        "Donai Kalan"
    ],
    "name:eng_x_variant":[
        "Donai Kal\u0101n"
    ],
    "wof:name":"Donai Kalan",
    "wof:placetype":"neighbourhood",
    "wof:population":1278
},
  "geometry": {"coordinates":[85.324556,24.173373],"type":"Point"}
}