{
  "type": "Feature",
  "properties": {
    "iso:country":"IN",
    "ks:ks_name":"Meherban Ka Purwa",
    "ks:ks_pop":294,
    "ks:ks_type":"HABITATION",
    "ks:ks_uagg_main":0,
    "name:eng_x_preferred":[
        "Meherban Ka Purwa"
    ],
    "wof:name":"Meherban Ka Purwa",
    "wof:placetype":"neighbourhood",
    "wof:population":294
},
  "geometry": {"coordinates":[81.327316,26.552139],"type":"Point"}
}