{
  "type": "Feature",
  "properties": {
    "iso:country":"IN",
    "ks:ks_alt_nam":"UPPARA MADDIGATLA",
    "ks:ks_name":"Uppara Maddigatla",
    "ks:ks_pop":246,
    "ks:ks_type":"HABITATION",
    "name:eng_x_preferred":[
        "Uppara Maddigatla"
    ],
    "wof:name":"Uppara Maddigatla",
    "wof:placetype":"locality",
    "wof:population":246
},
  "geometry": {"coordinates":[81.22445,17.54652],"type":"Point"}
}