{
  "type": "Feature",
  "properties": {
    "gn:admin1_code":"9.0",
    "gn:admin2_code":"492.0",
    "gn:asciiname":"Kadodara",
    "gn:country_code":"IN",
    "gn:dem":24,
    "gn:feature_class":"P",
    "gn:feature_code":"PPL",
    "gn:name":"Kadodara",
    "gn:population":0,
    "gn:timezone":"Asia/Kolkata",
    "iso:country":"IN",
    "wof:name":"Kadodara",
    "wof:placetype":"locality"
},
  "geometry": {"coordinates":[72.9623,21.1616],"type":"Point"}
}