{
  "type": "Feature",
  "properties": {
    "gn:admin1_code":"9.0",
    "gn:admin2_code":"492.0",
    "gn:asciiname":"Kadodara",
    "gn:country_code":"IN",
    "gn:dem":24,
    "gn:feature_class":"P",
    "gn:feature_code":"PPL",
    "gn:name":"Kadodara",
    "gn:population":0,
    "gn:timezone":"Asia/Kolkata",
    "iso:country":"IN",
    "ks:ks_name":"Kadodara",
    "ks:ks_pop":14819,
    "ks:ks_type":"URBAN",
    "ks:ks_uagg_main":1,
    "name:bpy_x_preferred":[
        "\u0995\u09be\u09a6\u09cb\u09a6\u09be\u09b0\u09be"
    ],
    "name:eng_x_preferred":[
        "Kadodara"
    ],
    "name:ita_x_preferred":[
        "Kadodara"
    ],
    "name:msa_x_preferred":[
        "Kadodara"
    ],
    "name:new_x_preferred":[
        "\u0915\u0926\u094b\u0926\u0930\u093e"
    ],
    "name:nld_x_preferred":[
        "Kadodara"
    ],
    "name:por_x_preferred":[
        "Kadodara"
    ],
    "name:tam_x_preferred":[
        "\u0b95\u0ba4\u0bcb\u0ba4\u0bb0\u0bbe"
    ],
    "name:vie_x_preferred":[
        "Kadodara"
    ],
    "name:zho_x_preferred":[
        "\u5361\u591a\u8fbe\u62c9"
    ],
    "wof:name":"Kadodara",
    "wof:placetype":"locality",
    "wof:population":14819
},
  "geometry": {"coordinates":[72.99210600000001,21.162383],"type":"Point"}
}