{
  "type": "Feature",
  "properties": {
    "gn:admin1_code":"12.0",
    "gn:admin2_code":"8.0",
    "gn:asciiname":"Madwan",
    "gn:country_code":"IN",
    "gn:dem":1583,
    "gn:feature_class":"P",
    "gn:feature_code":"PPL",
    "gn:name":"Madwan",
    "gn:population":0,
    "gn:timezone":"Asia/Kolkata",
    "iso:country":"IN",
    "name:eng_x_preferred":[
        "Madwan"
    ],
    "wof:name":"Madwan",
    "wof:placetype":"locality"
},
  "geometry": {"coordinates":[74.62730999999999,34.33162],"type":"Point"}
}