{
  "type": "Feature",
  "properties": {
    "iso:country":"IN",
    "ks:ks_name":"Vijaiyapar",
    "ks:ks_pop":165,
    "ks:ks_type":"VILLAGE",
    "ks:ks_uagg_main":0,
    "name:eng_x_preferred":[
        "Vijaiyapar"
    ],
    "wof:name":"Vijaiyapar",
    "wof:placetype":"neighbourhood",
    "wof:population":165
},
  "geometry": {"coordinates":[83.271702,26.205195],"type":"Point"}
}