{
  "type": "Feature",
  "properties": {
    "iso:country":"IN",
    "ks:ks_name":"Chak Husen",
    "ks:ks_pop":0,
    "ks:ks_type":"VILLAGE",
    "name:eng_x_preferred":[
        "Chak Husen"
    ],
    "wof:name":"Chak Husen",
    "wof:placetype":"locality",
    "wof:population":0
},
  "geometry": {"coordinates":[86.631286,25.409678],"type":"Point"}
}