{
  "type": "Feature",
  "properties": {
    "gn:admin1_code":"24.0",
    "gn:admin2_code":"103",
    "gn:asciiname":"Bharunda Kalan",
    "gn:country_code":"IN",
    "gn:dem":357,
    "gn:feature_class":"P",
    "gn:feature_code":"PPL",
    "gn:name":"Bhar\u016bnda Kal\u0101n",
    "gn:population":0,
    "gn:timezone":"Asia/Kolkata",
    "iso:country":"IN",
    "name:und_x_variant":[
        "Bhar\u016bnda Kal\u0101n",
        "Bharunda Kal\u0101n"
    ],
    "wof:name":"Bharunda Kalan",
    "wof:placetype":"locality"
},
  "geometry": {"coordinates":[75.52859000000002,28.07234],"type":"Point"}
}