{
  "type": "Feature",
  "properties": {
    "iso:country":"IN",
    "ks:ks_name":"Bendonara",
    "ks:ks_pop":123,
    "ks:ks_type":"HABITATION",
    "name:eng_x_preferred":[
        "Bendonara"
    ],
    "wof:name":"Bendonara",
    "wof:placetype":"locality",
    "wof:population":123
},
  "geometry": {"coordinates":[83.2753,22.544016],"type":"Point"}
}