{
  "type": "Feature",
  "properties": {
    "iso:country":"IN",
    "ks:ks_alt_nam":"Adamtilla DLF",
    "ks:ks_name":"Adamtilla Dlf",
    "ks:ks_pop":1350,
    "ks:ks_type":"HABITATION",
    "name:eng_x_preferred":[
        "Adamtilla Dlf"
    ],
    "wof:name":"Adamtilla Dlf",
    "wof:placetype":"locality",
    "wof:population":1350
},
  "geometry": {"coordinates":[92.270016,24.564574],"type":"Point"}
}