{
  "type": "Feature",
  "properties": {
    "iso:country":"IN",
    "ks:ks_alt_nam":"Sardh\u0101b\u0101r",
    "ks:ks_name":"Sardhabar",
    "ks:ks_pop":495,
    "ks:ks_type":"VILLAGE",
    "name:eng_x_preferred":[
        "Sardhabar"
    ],
    "name:eng_x_variant":[
        "Sardh\u0101b\u0101r"
    ],
    "wof:name":"Sardhabar",
    "wof:placetype":"locality",
    "wof:population":495
},
  "geometry": {"coordinates":[84.63543300000001,23.884748],"type":"Point"}
}