{
  "type": "Feature",
  "properties": {
    "iso:country":"IN",
    "ks:ks_name":"Bahrai",
    "ks:ks_pop":605,
    "ks:ks_type":"HABITATION",
    "name:eng_x_preferred":[
        "Bahrai"
    ],
    "wof:name":"Bahrai",
    "wof:placetype":"locality",
    "wof:population":605
},
  "geometry": {"coordinates":[77.152936,26.557716],"type":"Point"}
}