{
  "type": "Feature",
  "properties": {
    "iso:country":"IN",
    "ks:ks_name":"Kewtan",
    "ks:ks_pop":105,
    "ks:ks_type":"HABITATION",
    "ks:ks_uagg_main":0,
    "name:eng_x_preferred":[
        "Kewtan"
    ],
    "wof:name":"Kewtan",
    "wof:placetype":"neighbourhood",
    "wof:population":105
},
  "geometry": {"coordinates":[82.67498399999999,25.169435],"type":"Point"}
}