{
  "type": "Feature",
  "properties": {
    "iso:country":"IN",
    "ks:ks_name":"Vepalagadda",
    "ks:ks_pop":471,
    "ks:ks_type":"HABITATION",
    "name:eng_x_preferred":[
        "Vepalagadda"
    ],
    "wof:name":"Vepalagadda",
    "wof:placetype":"locality",
    "wof:population":471
},
  "geometry": {"coordinates":[80.804956,17.64266],"type":"Point"}
}