{
  "type": "Feature",
  "properties": {
    "gn:admin1_code":"11.0",
    "gn:admin2_code":"27.0",
    "gn:asciiname":"Salana",
    "gn:country_code":"IN",
    "gn:dem":1191,
    "gn:feature_class":"P",
    "gn:feature_code":"PPL",
    "gn:name":"Sal\u0101na",
    "gn:population":0,
    "gn:timezone":"Asia/Kolkata",
    "iso:country":"IN",
    "wof:name":"Salana",
    "wof:placetype":"locality"
},
  "geometry": {"coordinates":[77.24965999999998,31.32319],"type":"Point"}
}