{
  "type": "Feature",
  "properties": {
    "iso:country":"IN",
    "ks:ks_name":"Rampur Brit",
    "ks:ks_pop":2223,
    "ks:ks_type":"VILLAGE",
    "ks:ks_uagg_main":0,
    "name:eng_x_preferred":[
        "Rampur Brit"
    ],
    "wof:name":"Rampur Brit",
    "wof:placetype":"neighbourhood",
    "wof:population":2223
},
  "geometry": {"coordinates":[85.850072,26.595102],"type":"Point"}
}