{
  "type": "Feature",
  "properties": {
    "iso:country":"IN",
    "ks:ks_name":"Kentarai",
    "ks:ks_pop":15,
    "ks:ks_type":"HABITATION",
    "name:eng_x_preferred":[
        "Kentarai"
    ],
    "wof:name":"Kentarai",
    "wof:placetype":"locality",
    "wof:population":15
},
  "geometry": {"coordinates":[80.410355,23.978368],"type":"Point"}
}