{
  "type": "Feature",
  "properties": {
    "iso:country":"IN",
    "ks:ks_name":"Paramandpur",
    "ks:ks_pop":215,
    "ks:ks_type":"HABITATION",
    "name:eng_x_preferred":[
        "Paramandpur"
    ],
    "wof:name":"Paramandpur",
    "wof:placetype":"locality",
    "wof:population":215
},
  "geometry": {"coordinates":[83.516032,20.355568],"type":"Point"}
}