{
  "type": "Feature",
  "properties": {
    "iso:country":"IN",
    "ks:ks_name":"Katte Devastankeri",
    "ks:ks_pop":139,
    "ks:ks_type":"HABITATION",
    "name:eng_x_preferred":[
        "Katte Devastankeri"
    ],
    "wof:name":"Katte Devastankeri",
    "wof:placetype":"locality",
    "wof:population":139
},
  "geometry": {"coordinates":[74.45122499999999,14.363857],"type":"Point"}
}