{
  "type": "Feature",
  "properties": {
    "gn:admin1_code":"35.0",
    "gn:admin2_code":"464.0",
    "gn:asciiname":"Palasiapara",
    "gn:country_code":"IN",
    "gn:dem":287,
    "gn:feature_class":"P",
    "gn:feature_code":"PPL",
    "gn:name":"Palasiapara",
    "gn:population":0,
    "gn:timezone":"Asia/Kolkata",
    "iso:country":"IN",
    "ks:ks_name":"Palasiapara",
    "ks:ks_type":"VILLAGE",
    "name:eng_x_preferred":[
        "Palasiapara"
    ],
    "wof:name":"Palasiapara",
    "wof:placetype":"locality"
},
  "geometry": {"coordinates":[74.51437300000001,22.976009],"type":"Point"}
}