{
  "type": "Feature",
  "properties": {
    "iso:country":"IN",
    "ks:ks_name":"Pure Jorawar",
    "ks:ks_pop":237,
    "ks:ks_type":"HABITATION",
    "name:eng_x_preferred":[
        "Pure Jorawar"
    ],
    "wof:name":"Pure Jorawar",
    "wof:placetype":"locality",
    "wof:population":237
},
  "geometry": {"coordinates":[81.48050000000001,26.4607],"type":"Point"}
}