{
  "type": "Feature",
  "properties": {
    "iso:country":"IN",
    "ks:ks_name":"Kuyilongi",
    "ks:ks_pop":77,
    "ks:ks_type":"HABITATION",
    "name:eng_x_preferred":[
        "Kuyilongi"
    ],
    "wof:name":"Kuyilongi",
    "wof:placetype":"locality",
    "wof:population":77
},
  "geometry": {"coordinates":[82.527,18.425305],"type":"Point"}
}