{
  "type": "Feature",
  "properties": {
    "iso:country":"IN",
    "ks:ks_name":"Surkichapada",
    "ks:ks_pop":1270,
    "ks:ks_type":"HABITATION",
    "ks:ks_uagg_main":0,
    "name:eng_x_preferred":[
        "Surkichapada"
    ],
    "wof:name":"Surkichapada",
    "wof:placetype":"neighbourhood",
    "wof:population":1270
},
  "geometry": {"coordinates":[72.949764,18.848005],"type":"Point"}
}