{
  "type": "Feature",
  "properties": {
    "gn:admin1_code":"24.0",
    "gn:admin2_code":"113.0",
    "gn:asciiname":"Bijasni",
    "gn:country_code":"IN",
    "gn:dem":261,
    "gn:feature_class":"P",
    "gn:feature_code":"PPL",
    "gn:name":"Bij\u0101sni",
    "gn:population":0,
    "gn:timezone":"Asia/Kolkata",
    "iso:country":"IN",
    "wof:name":"Bijasni",
    "wof:placetype":"neighbourhood"
},
  "geometry": {"coordinates":[73.64134,26.14863],"type":"Point"}
}