{
  "type": "Feature",
  "properties": {
    "gn:admin1_code":"35.0",
    "gn:admin2_code":"451.0",
    "gn:asciiname":"Lilkhera",
    "gn:country_code":"IN",
    "gn:dem":394,
    "gn:feature_class":"P",
    "gn:feature_code":"PPL",
    "gn:name":"L\u012blkhera",
    "gn:population":0,
    "gn:timezone":"Asia/Kolkata",
    "iso:country":"IN",
    "ks:ks_name":"Lilkheda",
    "ks:ks_pop":43,
    "ks:ks_type":"VILLAGE",
    "name:eng_x_preferred":[
        "Lilkheda"
    ],
    "name:eng_x_variant":[
        "Lilkhera"
    ],
    "wof:name":"Lilkheda",
    "wof:placetype":"locality",
    "wof:population":43
},
  "geometry": {"coordinates":[80.001447,23.240756],"type":"Point"}
}