{
  "type": "Feature",
  "properties": {
    "gn:admin1_code":"36",
    "gn:admin2_code":"191.0",
    "gn:asciiname":"Khalilabad",
    "gn:country_code":"IN",
    "gn:dem":83,
    "gn:feature_class":"P",
    "gn:feature_code":"PPL",
    "gn:name":"Khal\u012bl\u0101b\u0101d",
    "gn:population":0,
    "gn:timezone":"Asia/Kolkata",
    "iso:country":"IN",
    "name:aze_x_preferred":[
        "X\u0259lilabad"
    ],
    "name:ceb_x_preferred":[
        "Khalilabad"
    ],
    "name:fas_x_preferred":[
        "\u062e\u0644\u06cc\u0644\u200c\u0622\u0628\u0627\u062f"
    ],
    "name:swe_x_preferred":[
        "Khalilabad"
    ],
    "wof:name":"Khalilabad",
    "wof:placetype":"locality"
},
  "geometry": {"coordinates":[82.96675,25.99777000000001],"type":"Point"}
}