{
  "type": "Feature",
  "properties": {
    "iso:country":"IN",
    "ks:ks_name":"Sahaband Chak",
    "ks:ks_pop":2627,
    "ks:ks_type":"VILLAGE",
    "ks:ks_uagg_main":0,
    "name:eng_x_preferred":[
        "Sahaband Chak"
    ],
    "wof:name":"Sahaband Chak",
    "wof:placetype":"neighbourhood",
    "wof:population":2627
},
  "geometry": {"coordinates":[88.01134,24.807154],"type":"Point"}
}