{
  "type": "Feature",
  "properties": {
    "gn:admin1_code":"36",
    "gn:admin2_code":"194.0",
    "gn:asciiname":"Shamaspur",
    "gn:country_code":"IN",
    "gn:dem":87,
    "gn:feature_class":"P",
    "gn:feature_code":"PPL",
    "gn:name":"Shamaspur",
    "gn:population":0,
    "gn:timezone":"Asia/Kolkata",
    "iso:country":"IN",
    "ks:ks_name":"Samaspur",
    "ks:ks_pop":973,
    "ks:ks_type":"VILLAGE",
    "ks:ks_uagg_main":0,
    "name:eng_x_preferred":[
        "Samaspur"
    ],
    "name:fas_x_preferred":[
        "\u0634\u0645\u0633\u200c\u067e\u0648\u0631"
    ],
    "name:urd_x_preferred":[
        "\u0634\u0645\u0633 \u067e\u0648\u0631"
    ],
    "wof:name":"Samaspur",
    "wof:placetype":"neighbourhood",
    "wof:population":973
},
  "geometry": {"coordinates":[82.719173,25.83298],"type":"Point"}
}