{
  "type": "Feature",
  "properties": {
    "iso:country":"IN",
    "ks:ks_name":"Shamaspur",
    "ks:ks_pop":17,
    "ks:ks_type":"VILLAGE",
    "ks:ks_uagg_main":0,
    "name:eng_x_preferred":[
        "Shamaspur"
    ],
    "wof:name":"Shamaspur",
    "wof:placetype":"neighbourhood",
    "wof:population":17
},
  "geometry": {"coordinates":[76.009421,31.448946],"type":"Point"}
}