{
  "type": "Feature",
  "properties": {
    "iso:country":"IN",
    "ks:ks_alt_nam":"AD Kudiyruppu",
    "ks:ks_name":"Ad Kudiyruppu",
    "ks:ks_pop":378,
    "ks:ks_type":"HABITATION",
    "ks:ks_uagg_main":0,
    "name:eng_x_preferred":[
        "Ad Kudiyruppu"
    ],
    "wof:name":"Ad Kudiyruppu",
    "wof:placetype":"neighbourhood",
    "wof:population":378
},
  "geometry": {"coordinates":[79.796361,12.812022],"type":"Point"}
}