{
  "type": "Feature",
  "properties": {
    "iso:country":"IN",
    "ks:ks_name":"Malapalle",
    "ks:ks_pop":99,
    "ks:ks_type":"HABITATION",
    "name:eng_x_preferred":[
        "Malapalle"
    ],
    "wof:name":"Malapalle",
    "wof:placetype":"locality",
    "wof:population":99
},
  "geometry": {"coordinates":[78.71478399999999,13.773665],"type":"Point"}
}