{
  "type": "Feature",
  "properties": {
    "iso:country":"IN",
    "ks:ks_alt_nam":"SUKHWASUTOLI",
    "ks:ks_name":"Sukhwasutoli",
    "ks:ks_pop":180,
    "ks:ks_type":"HABITATION",
    "name:eng_x_preferred":[
        "Sukhwasutoli"
    ],
    "wof:name":"Sukhwasutoli",
    "wof:placetype":"locality",
    "wof:population":180
},
  "geometry": {"coordinates":[83.838803,22.431992],"type":"Point"}
}