{
  "type": "Feature",
  "properties": {
    "iso:country":"IN",
    "ks:ks_alt_nam":"BADAPAR",
    "ks:ks_name":"Badapar",
    "ks:ks_pop":217,
    "ks:ks_type":"HABITATION",
    "name:eng_x_preferred":[
        "Badapar"
    ],
    "wof:name":"Badapar",
    "wof:placetype":"locality",
    "wof:population":217
},
  "geometry": {"coordinates":[81.998948,22.635462],"type":"Point"}
}