{
  "type": "Feature",
  "properties": {
    "iso:country":"IN",
    "ks:ks_name":"Lakra",
    "ks:ks_pop":102,
    "ks:ks_type":"VILLAGE",
    "name:eng_x_preferred":[
        "Lakra"
    ],
    "wof:name":"Lakra",
    "wof:placetype":"locality",
    "wof:population":102
},
  "geometry": {"coordinates":[86.767813,24.232514],"type":"Point"}
}