{
  "type": "Feature",
  "properties": {
    "gn:admin1_code":"36.0",
    "gn:admin2_code":"132.0",
    "gn:asciiname":"Chandarpai Kheri",
    "gn:country_code":"IN",
    "gn:dem":267,
    "gn:feature_class":"P",
    "gn:feature_code":"PPL",
    "gn:name":"Chandarp\u0101i Kheri",
    "gn:population":0,
    "gn:timezone":"Asia/Kolkata",
    "iso:country":"IN",
    "ks:ks_name":"Chandrapal Kheri",
    "ks:ks_pop":337,
    "ks:ks_type":"VILLAGE",
    "ks:ks_uagg_main":0,
    "name:eng_x_preferred":[
        "Chandrapal Kheri"
    ],
    "wof:name":"Chandrapal Kheri",
    "wof:placetype":"neighbourhood",
    "wof:population":337
},
  "geometry": {"coordinates":[77.297984,29.911549],"type":"Point"}
}