{
  "type": "Feature",
  "properties": {
    "iso:country":"IN",
    "ks:ks_name":"Naurangia",
    "ks:ks_pop":4761,
    "ks:ks_type":"VILLAGE",
    "name:eng_x_preferred":[
        "Naurangia"
    ],
    "wof:name":"Naurangia",
    "wof:placetype":"locality",
    "wof:population":4761
},
  "geometry": {"coordinates":[83.89293600000001,27.028052],"type":"Point"}
}