{
  "type": "Feature",
  "properties": {
    "iso:country":"IN",
    "ks:ks_name":"Mardiyones",
    "ks:ks_pop":31,
    "ks:ks_type":"HABITATION",
    "name:eng_x_preferred":[
        "Mardiyones"
    ],
    "wof:name":"Mardiyones",
    "wof:placetype":"locality",
    "wof:population":31
},
  "geometry": {"coordinates":[69.699472,21.840306],"type":"Point"}
}