{
  "type": "Feature",
  "properties": {
    "iso:country":"IN",
    "ks:ks_name":"Parmedia",
    "ks:ks_pop":457,
    "ks:ks_type":"VILLAGE",
    "ks:ks_uagg_main":0,
    "name:eng_x_preferred":[
        "Parmedia"
    ],
    "wof:name":"Parmedia",
    "wof:placetype":"neighbourhood",
    "wof:population":457
},
  "geometry": {"coordinates":[88.36313699999999,23.367736],"type":"Point"}
}