{
  "type": "Feature",
  "properties": {
    "iso:country":"IN",
    "ks:ks_name":"Mirdadpur",
    "ks:ks_pop":3316,
    "ks:ks_type":"VILLAGE",
    "name:eng_x_preferred":[
        "Mirdadpur"
    ],
    "wof:name":"Mirdadpur",
    "wof:placetype":"locality",
    "wof:population":3316
},
  "geometry": {"coordinates":[87.98121,25.125841],"type":"Point"}
}