{
  "type": "Feature",
  "properties": {
    "gn:admin1_code":"36",
    "gn:admin2_code":"174.0",
    "gn:asciiname":"Khalispur",
    "gn:country_code":"IN",
    "gn:dem":101,
    "gn:feature_class":"P",
    "gn:feature_code":"PPL",
    "gn:name":"Kh\u0101lispur",
    "gn:population":0,
    "gn:timezone":"Asia/Kolkata",
    "iso:country":"IN",
    "wof:name":"Khalispur",
    "wof:placetype":"neighbourhood"
},
  "geometry": {"coordinates":[81.49451000000001,25.61623],"type":"Point"}
}