{
  "type": "Feature",
  "properties": {
    "gn:admin1_code":"36",
    "gn:admin2_code":"154.0",
    "gn:asciiname":"Samdha",
    "gn:country_code":"IN",
    "gn:dem":130,
    "gn:feature_class":"P",
    "gn:feature_code":"PPL",
    "gn:name":"Samdha",
    "gn:population":0,
    "gn:timezone":"Asia/Kolkata",
    "iso:country":"IN",
    "name:mai_x_preferred":[
        "\u0938\u093e\u0901\u0922\u093e"
    ],
    "name:msa_x_preferred":[
        "Samdha"
    ],
    "wof:name":"Samdha",
    "wof:placetype":"locality"
},
  "geometry": {"coordinates":[81.00111,27.53729],"type":"Point"}
}