{
  "type": "Feature",
  "properties": {
    "iso:country":"IN",
    "ks:ks_name":"Sripur",
    "ks:ks_pop":1082,
    "ks:ks_type":"VILLAGE",
    "ks:ks_uagg_main":0,
    "name:eng_x_preferred":[
        "Sripur"
    ],
    "wof:name":"Sripur",
    "wof:placetype":"neighbourhood",
    "wof:population":1082
},
  "geometry": {"coordinates":[92.338013,24.591756],"type":"Point"}
}