{
  "type": "Feature",
  "properties": {
    "gn:admin1_code":"10.0",
    "gn:admin2_code":"075",
    "gn:asciiname":"Simla Maulana",
    "gn:country_code":"IN",
    "gn:dem":238,
    "gn:feature_class":"P",
    "gn:feature_code":"PPL",
    "gn:name":"Simla Maul\u0101na",
    "gn:population":0,
    "gn:timezone":"Asia/Kolkata",
    "iso:country":"IN",
    "ks:ks_alt_nam":"Simla Maul\u0101na",
    "ks:ks_name":"Simla Maulana",
    "ks:ks_pop":1269,
    "ks:ks_type":"VILLAGE",
    "ks:ks_uagg_main":0,
    "name:eng_x_preferred":[
        "Simla Maulana"
    ],
    "name:eng_x_variant":[
        "Simla Maul\u0101na"
    ],
    "wof:name":"Simla Maulana",
    "wof:placetype":"locality",
    "wof:population":1269
},
  "geometry": {"coordinates":[76.983695,29.454162],"type":"Point"}
}