{
  "type": "Feature",
  "properties": {
    "iso:country":"IN",
    "ks:ks_name":"Simtola",
    "ks:ks_pop":69,
    "ks:ks_type":"VILLAGE",
    "name:eng_x_preferred":[
        "Simtola"
    ],
    "wof:name":"Simtola",
    "wof:placetype":"locality",
    "wof:population":69
},
  "geometry": {"coordinates":[79.840958,29.866469],"type":"Point"}
}