{
  "type": "Feature",
  "properties": {
    "iso:country":"IN",
    "ks:ks_name":"Krishnapur",
    "ks:ks_pop":194,
    "ks:ks_type":"HABITATION",
    "name:eng_x_preferred":[
        "Krishnapur"
    ],
    "wof:name":"Krishnapur",
    "wof:placetype":"locality",
    "wof:population":194
},
  "geometry": {"coordinates":[91.996415,24.382639],"type":"Point"}
}