{
  "type": "Feature",
  "properties": {
    "iso:country":"IN",
    "ks:ks_name":"Gandhi Nagar",
    "ks:ks_pop":63,
    "ks:ks_type":"HABITATION",
    "ks:ks_uagg_main":0,
    "name:eng_x_preferred":[
        "Gandhi Nagar"
    ],
    "wof:name":"Gandhi Nagar",
    "wof:placetype":"neighbourhood",
    "wof:population":63
},
  "geometry": {"coordinates":[79.37709099999999,26.515867],"type":"Point"}
}