{
  "type": "Feature",
  "properties": {
    "gn:admin1_code":"36",
    "gn:admin2_code":"149.0",
    "gn:asciiname":"Batruiya",
    "gn:country_code":"IN",
    "gn:dem":167,
    "gn:feature_class":"P",
    "gn:feature_code":"PPL",
    "gn:name":"Batruiya",
    "gn:population":0,
    "gn:timezone":"Asia/Kolkata",
    "iso:country":"IN",
    "ks:ks_name":"Batruiya",
    "ks:ks_type":"VILLAGE",
    "name:eng_x_preferred":[
        "Batruiya"
    ],
    "wof:name":"Batruiya",
    "wof:placetype":"locality"
},
  "geometry": {"coordinates":[78.80501700000001,27.993087],"type":"Point"}
}