{
  "type": "Feature",
  "properties": {
    "iso:country":"IN",
    "ks:ks_name":"Uttari Tola",
    "ks:ks_pop":45,
    "ks:ks_type":"HABITATION",
    "ks:ks_uagg_main":0,
    "name:eng_x_preferred":[
        "Uttari Tola"
    ],
    "wof:name":"Uttari Tola",
    "wof:placetype":"neighbourhood",
    "wof:population":45
},
  "geometry": {"coordinates":[83.22781000000001,26.660079],"type":"Point"}
}