{
  "type": "Feature",
  "properties": {
    "gn:admin1_code":"10.0",
    "gn:admin2_code":"70.0",
    "gn:asciiname":"Kamasi",
    "gn:country_code":"IN",
    "gn:dem":273,
    "gn:feature_class":"P",
    "gn:feature_code":"PPL",
    "gn:name":"Kam\u0101si",
    "gn:population":0,
    "gn:timezone":"Asia/Kolkata",
    "iso:country":"IN",
    "name:ara_x_preferred":[
        "\u0643\u0645\u0627\u0633\u064a"
    ],
    "name:fas_x_preferred":[
        "\u06a9\u0645\u0627\u0633\u06cc"
    ],
    "name:msa_x_preferred":[
        "Kamasi"
    ],
    "wof:name":"Kamasi",
    "wof:placetype":"locality"
},
  "geometry": {"coordinates":[77.01284,30.17381],"type":"Point"}
}