{
  "type": "Feature",
  "properties": {
    "iso:country":"IN",
    "ks:ks_name":"Bhamanya",
    "ks:ks_pop":931,
    "ks:ks_type":"VILLAGE",
    "name:eng_x_preferred":[
        "Bhamanya"
    ],
    "wof:name":"Bhamanya",
    "wof:placetype":"locality",
    "wof:population":931
},
  "geometry": {"coordinates":[75.12853200000001,21.62737],"type":"Point"}
}