{
  "type": "Feature",
  "properties": {
    "gn:admin1_code":"16.0",
    "gn:admin2_code":"523.0",
    "gn:asciiname":"Amla",
    "gn:country_code":"IN",
    "gn:dem":503,
    "gn:feature_class":"P",
    "gn:feature_code":"PPL",
    "gn:name":"\u0100mla",
    "gn:population":0,
    "gn:timezone":"Asia/Kolkata",
    "iso:country":"IN",
    "name:ben_x_preferred":[
        "\u0986\u09ae\u09b2\u09be"
    ],
    "name:fra_x_preferred":[
        "Amla"
    ],
    "wof:name":"Amla",
    "wof:placetype":"locality"
},
  "geometry": {"coordinates":[76.28948000000003,18.91677],"type":"Point"}
}