{
  "type": "Feature",
  "properties": {
    "gn:admin1_code":"36",
    "gn:admin2_code":"201.0",
    "gn:asciiname":"Begampur",
    "gn:country_code":"IN",
    "gn:dem":160,
    "gn:feature_class":"P",
    "gn:feature_code":"PPL",
    "gn:name":"Begampur",
    "gn:population":0,
    "gn:timezone":"Asia/Kolkata",
    "iso:country":"IN",
    "wof:name":"Begampur",
    "wof:placetype":"neighbourhood"
},
  "geometry": {"coordinates":[78.97398,27.42343],"type":"Point"}
}