{
  "type": "Feature",
  "properties": {
    "gn:admin1_code":"21",
    "gn:admin2_code":"394.0",
    "gn:asciiname":"Rengabahal",
    "gn:country_code":"IN",
    "gn:dem":324,
    "gn:feature_class":"P",
    "gn:feature_code":"PPL",
    "gn:name":"Reng\u0101bah\u0101l",
    "gn:population":0,
    "gn:timezone":"Asia/Kolkata",
    "iso:country":"IN",
    "ks:ks_name":"Rengbahal",
    "ks:ks_pop":222,
    "ks:ks_type":"HABITATION",
    "name:eng_x_preferred":[
        "Rengbahal"
    ],
    "name:eng_x_variant":[
        "Rengabahal"
    ],
    "wof:name":"Rengbahal",
    "wof:placetype":"locality",
    "wof:population":222
},
  "geometry": {"coordinates":[82.57280299999999,20.635729],"type":"Point"}
}