{
  "type": "Feature",
  "properties": {
    "iso:country":"IN",
    "ks:ks_name":"Mana Patti",
    "ks:ks_pop":727,
    "ks:ks_type":"VILLAGE",
    "name:eng_x_preferred":[
        "Mana Patti"
    ],
    "wof:name":"Mana Patti",
    "wof:placetype":"locality",
    "wof:population":727
},
  "geometry": {"coordinates":[82.015717,25.837223],"type":"Point"}
}