{
  "type": "Feature",
  "properties": {
    "iso:country":"IN",
    "ks:ks_name":"Khajohri",
    "ks:ks_pop":1778,
    "ks:ks_type":"VILLAGE",
    "ks:ks_uagg_main":0,
    "name:eng_x_preferred":[
        "Khajohri"
    ],
    "wof:name":"Khajohri",
    "wof:placetype":"neighbourhood",
    "wof:population":1778
},
  "geometry": {"coordinates":[81.945071,25.867202],"type":"Point"}
}