{
  "type": "Feature",
  "properties": {
    "iso:country":"IN",
    "ks:ks_name":"Kuber Datta Bhera",
    "ks:ks_pop":605,
    "ks:ks_type":"VILLAGE",
    "name:eng_x_preferred":[
        "Kuber Datta Bhera"
    ],
    "wof:name":"Kuber Datta Bhera",
    "wof:placetype":"locality",
    "wof:population":605
},
  "geometry": {"coordinates":[87.726632,22.108857],"type":"Point"}
}