{
  "type": "Feature",
  "properties": {
    "iso:country":"IN",
    "ks:ks_name":"Basudevpur",
    "ks:ks_pop":201,
    "ks:ks_type":"VILLAGE",
    "name:eng_x_preferred":[
        "Basudevpur"
    ],
    "wof:name":"Basudevpur",
    "wof:placetype":"locality",
    "wof:population":201
},
  "geometry": {"coordinates":[86.53808600000001,21.25232],"type":"Point"}
}