{
  "type": "Feature",
  "properties": {
    "gn:admin1_code":"24.0",
    "gn:admin2_code":"102.0",
    "gn:asciiname":"Bara Patlisar ki Dhani",
    "gn:country_code":"IN",
    "gn:dem":278,
    "gn:feature_class":"P",
    "gn:feature_code":"PPL",
    "gn:name":"Bara P\u0101tl\u012bsar ki Dh\u0101ni",
    "gn:population":0,
    "gn:timezone":"Asia/Kolkata",
    "iso:country":"IN",
    "wof:name":"Bara Patlisar ki Dhani",
    "wof:placetype":"locality"
},
  "geometry": {"coordinates":[74.39869,28.25581],"type":"Point"}
}