{
  "type": "Feature",
  "properties": {
    "gn:admin1_code":"39.0",
    "gn:admin2_code":"67.0",
    "gn:asciiname":"Bhura",
    "gn:country_code":"IN",
    "gn:dem":215,
    "gn:feature_class":"P",
    "gn:feature_code":"PPL",
    "gn:name":"Bh\u016bra",
    "gn:population":0,
    "gn:timezone":"Asia/Kolkata",
    "iso:country":"IN",
    "wof:name":"Bhura",
    "wof:placetype":"locality"
},
  "geometry": {"coordinates":[79.50084,28.95206],"type":"Point"}
}