{
  "type": "Feature",
  "properties": {
    "gn:admin1_code":"39.0",
    "gn:admin2_code":"67.0",
    "gn:asciiname":"Bhura",
    "gn:country_code":"IN",
    "gn:dem":215,
    "gn:feature_class":"P",
    "gn:feature_code":"PPL",
    "gn:name":"Bh\u016bra",
    "gn:population":0,
    "gn:timezone":"Asia/Kolkata",
    "iso:country":"IN",
    "ks:ks_alt_nam":"Bh\u016bra",
    "ks:ks_name":"Bhura",
    "ks:ks_type":"VILLAGE",
    "name:eng_x_preferred":[
        "Bhura"
    ],
    "name:eng_x_variant":[
        "Bh\u016bra"
    ],
    "wof:name":"Bhura",
    "wof:placetype":"locality"
},
  "geometry": {"coordinates":[79.50084099999999,28.952058],"type":"Point"}
}