{
  "type": "Feature",
  "properties": {
    "iso:country":"IN",
    "ks:ks_name":"Bnurawali",
    "ks:ks_pop":172,
    "ks:ks_type":"HABITATION",
    "name:eng_x_preferred":[
        "Bnurawali"
    ],
    "wof:name":"Bnurawali",
    "wof:placetype":"locality",
    "wof:population":172
},
  "geometry": {"coordinates":[82.812203,27.370518],"type":"Point"}
}