{
  "type": "Feature",
  "properties": {
    "iso:country":"IN",
    "ks:ks_name":"Kunardi",
    "ks:ks_pop":692,
    "ks:ks_type":"VILLAGE",
    "ks:ks_uagg_main":0,
    "name:eng_x_preferred":[
        "Kunardi"
    ],
    "wof:name":"Kunardi",
    "wof:placetype":"neighbourhood",
    "wof:population":692
},
  "geometry": {"coordinates":[86.69291,23.566907],"type":"Point"}
}