{
  "type": "Feature",
  "properties": {
    "gn:admin1_code":"40",
    "gn:admin2_code":"533.0",
    "gn:asciiname":"Lingampalli",
    "gn:country_code":"IN",
    "gn:dem":423,
    "gn:feature_class":"P",
    "gn:feature_code":"PPL",
    "gn:name":"Lingampalli",
    "gn:population":0,
    "gn:timezone":"Asia/Kolkata",
    "iso:country":"IN",
    "ks:ks_name":"Lingampally",
    "ks:ks_pop":563,
    "ks:ks_type":"HABITATION",
    "name:eng_x_preferred":[
        "Lingampally"
    ],
    "name:eng_x_variant":[
        "Lingampalli"
    ],
    "wof:name":"Lingampally",
    "wof:placetype":"locality",
    "wof:population":563
},
  "geometry": {"coordinates":[77.90938800000001,18.198821],"type":"Point"}
}