{
  "type": "Feature",
  "properties": {
    "gn:admin1_code":"33.0",
    "gn:admin2_code":"586",
    "gn:asciiname":"Bandoli",
    "gn:country_code":"IN",
    "gn:dem":97,
    "gn:feature_class":"P",
    "gn:feature_code":"PPL",
    "gn:name":"Bandoli",
    "gn:population":0,
    "gn:timezone":"Asia/Kolkata",
    "iso:country":"IN",
    "ks:ks_name":"Bandoli",
    "ks:ks_pop":1268,
    "ks:ks_type":"VILLAGE",
    "name:eng_x_preferred":[
        "Bandoli"
    ],
    "wof:name":"Bandoli",
    "wof:placetype":"locality",
    "wof:population":1268
},
  "geometry": {"coordinates":[74.11983499999999,15.305458],"type":"Point"}
}