{
  "type": "Feature",
  "properties": {
    "gn:admin1_code":"35",
    "gn:admin2_code":"462.0",
    "gn:asciiname":"Bharuhi",
    "gn:country_code":"IN",
    "gn:dem":262,
    "gn:feature_class":"P",
    "gn:feature_code":"PPL",
    "gn:name":"Bhar\u016bhi",
    "gn:population":0,
    "gn:timezone":"Asia/Kolkata",
    "iso:country":"IN",
    "ks:ks_alt_nam":"Bhar\u016bhi",
    "ks:ks_name":"Bharuhi",
    "ks:ks_pop":1370,
    "ks:ks_type":"VILLAGE",
    "name:eng_x_preferred":[
        "Bharuhi"
    ],
    "name:eng_x_variant":[
        "Bhar\u016bhi"
    ],
    "wof:name":"Bharuhi",
    "wof:placetype":"locality",
    "wof:population":1370
},
  "geometry": {"coordinates":[82.140424,24.378929],"type":"Point"}
}