{
  "type": "Feature",
  "properties": {
    "iso:country":"IN",
    "ks:ks_name":"Bedadi",
    "ks:ks_pop":37,
    "ks:ks_type":"VILLAGE",
    "name:eng_x_preferred":[
        "Bedadi"
    ],
    "wof:name":"Bedadi",
    "wof:placetype":"locality",
    "wof:population":37
},
  "geometry": {"coordinates":[84.703534,20.47136],"type":"Point"}
}