{
  "type": "Feature",
  "properties": {
    "gn:admin1_code":"12.0",
    "gn:admin2_code":"021",
    "gn:asciiname":"Hamirpur Sidhar",
    "gn:country_code":"IN",
    "gn:dem":255,
    "gn:feature_class":"P",
    "gn:feature_code":"PPL",
    "gn:name":"Ham\u012brpur S\u012bdhar",
    "gn:population":0,
    "gn:timezone":"Asia/Kolkata",
    "iso:country":"IN",
    "wof:name":"Hamirpur Sidhar",
    "wof:placetype":"locality"
},
  "geometry": {"coordinates":[74.52543,32.77682],"type":"Point"}
}