{
  "type": "Feature",
  "properties": {
    "iso:country":"IN",
    "ks:ks_name":"Patrapada",
    "ks:ks_pop":141,
    "ks:ks_type":"VILLAGE",
    "name:eng_x_preferred":[
        "Patrapada"
    ],
    "wof:name":"Patrapada",
    "wof:placetype":"locality",
    "wof:population":141
},
  "geometry": {"coordinates":[85.457069,19.970829],"type":"Point"}
}