{
  "type": "Feature",
  "properties": {
    "iso:country":"IN",
    "ks:ks_alt_nam":"Jipu\u0101",
    "ks:ks_name":"Jipua",
    "ks:ks_pop":1180,
    "ks:ks_type":"VILLAGE",
    "ks:ks_uagg_main":0,
    "name:eng_x_preferred":[
        "Jipua"
    ],
    "name:eng_x_variant":[
        "Jipu\u0101"
    ],
    "wof:name":"Jipua",
    "wof:placetype":"neighbourhood",
    "wof:population":1180
},
  "geometry": {"coordinates":[84.88640100000001,23.761919],"type":"Point"}
}