{
  "type": "Feature",
  "properties": {
    "gn:admin1_code":"12.0",
    "gn:admin2_code":"20.0",
    "gn:asciiname":"Iohni",
    "gn:country_code":"IN",
    "gn:dem":2402,
    "gn:feature_class":"P",
    "gn:feature_code":"PPL",
    "gn:name":"Iohn\u012b",
    "gn:population":0,
    "gn:timezone":"Asia/Kolkata",
    "iso:country":"IN",
    "wof:name":"Iohni",
    "wof:placetype":"locality"
},
  "geometry": {"coordinates":[74.71136,33.4643],"type":"Point"}
}