{
  "type": "Feature",
  "properties": {
    "iso:country":"IN",
    "ks:ks_name":"Galagar",
    "ks:ks_pop":281,
    "ks:ks_type":"HABITATION",
    "name:eng_x_preferred":[
        "Galagar"
    ],
    "wof:name":"Galagar",
    "wof:placetype":"locality",
    "wof:population":281
},
  "geometry": {"coordinates":[80.410141,29.796459],"type":"Point"}
}