{
  "type": "Feature",
  "properties": {
    "iso:country":"IN",
    "ks:ks_alt_nam":"KATHA MUSAHARI",
    "ks:ks_name":"Katha Musahari",
    "ks:ks_pop":76,
    "ks:ks_type":"HABITATION",
    "ks:ks_uagg_main":0,
    "name:eng_x_preferred":[
        "Katha Musahari"
    ],
    "wof:name":"Katha Musahari",
    "wof:placetype":"neighbourhood",
    "wof:population":76
},
  "geometry": {"coordinates":[87.31004,25.886472],"type":"Point"}
}