{
  "type": "Feature",
  "properties": {
    "gn:admin1_code":"36",
    "gn:admin2_code":"197.0",
    "gn:asciiname":"Tandia",
    "gn:country_code":"IN",
    "gn:dem":87,
    "gn:feature_class":"P",
    "gn:feature_code":"PPL",
    "gn:name":"Tandia",
    "gn:population":0,
    "gn:timezone":"Asia/Kolkata",
    "iso:country":"IN",
    "ks:ks_alt_nam":"tandia",
    "ks:ks_name":"Tandia",
    "ks:ks_pop":500,
    "ks:ks_type":"HABITATION",
    "name:eng_x_preferred":[
        "Tandia"
    ],
    "wof:name":"Tandia",
    "wof:placetype":"locality",
    "wof:population":500
},
  "geometry": {"coordinates":[82.855817,25.217999],"type":"Point"}
}