{
  "type": "Feature",
  "properties": {
    "iso:country":"IN",
    "ks:ks_alt_nam":"Bomanji H.C.",
    "ks:ks_name":"Bomanji H.c.",
    "ks:ks_pop":84,
    "ks:ks_type":"HABITATION",
    "name:eng_x_preferred":[
        "Bomanji H.c."
    ],
    "wof:name":"Bomanji H.c.",
    "wof:placetype":"locality",
    "wof:population":84
},
  "geometry": {"coordinates":[75.921667,12.0275],"type":"Point"}
}