{
  "type": "Feature",
  "properties": {
    "iso:country":"IN",
    "ks:ks_name":"Madara Vankar Faliya",
    "ks:ks_pop":610,
    "ks:ks_type":"HABITATION",
    "ks:ks_uagg_main":0,
    "name:eng_x_preferred":[
        "Madara Vankar Faliya"
    ],
    "wof:name":"Madara Vankar Faliya",
    "wof:placetype":"neighbourhood",
    "wof:population":610
},
  "geometry": {"coordinates":[73.8265,22.801556],"type":"Point"}
}