{
  "type": "Feature",
  "properties": {
    "gn:admin1_code":"16.0",
    "gn:admin2_code":"510.0",
    "gn:asciiname":"Kawadsi",
    "gn:country_code":"IN",
    "gn:dem":193,
    "gn:feature_class":"P",
    "gn:feature_code":"PPL",
    "gn:name":"Kawadsi",
    "gn:population":0,
    "gn:timezone":"Asia/Kolkata",
    "iso:country":"IN",
    "wof:name":"Kawadsi",
    "wof:placetype":"locality"
},
  "geometry": {"coordinates":[79.06239000000002,19.92692000000001],"type":"Point"}
}