{
  "type": "Feature",
  "properties": {
    "gn:admin1_code":"35.0",
    "gn:admin2_code":"452.0",
    "gn:asciiname":"Bamhori",
    "gn:country_code":"IN",
    "gn:dem":336,
    "gn:feature_class":"P",
    "gn:feature_code":"PPL",
    "gn:name":"Bamhori",
    "gn:population":0,
    "gn:timezone":"Asia/Kolkata",
    "iso:country":"IN",
    "wof:name":"Bamhori",
    "wof:placetype":"locality"
},
  "geometry": {"coordinates":[78.71374,22.99203],"type":"Point"}
}