{
  "type": "Feature",
  "properties": {
    "gn:country":"IN",
    "gn:fcode":"PPL",
    "gn:pop":0,
    "iso:country":"IN",
    "name:unk_x_variant":[
        "Mur\u016bd"
    ],
    "qs:name":"Murud",
    "qs:name_adm0":"India",
    "qs:name_adm1":"Maharashtra",
    "qs:photos":28,
    "qs:photos_1k":6,
    "qs:photos_9k":1,
    "qs:photos_9r":2,
    "qs:photos_all":28,
    "qs:photos_sr":2,
    "qs:placetype":"Town",
    "qs:pop_sr":"0",
    "wd:wordcount":54,
    "wof:name":"Murud",
    "wof:placetype":"locality",
    "wof:population":0
},
  "geometry": {"coordinates":[73.11975,17.77138],"type":"Point"}
}