{
  "type": "Feature",
  "properties": {
    "gn:admin1_code":"25.0",
    "gn:admin2_code":"613.0",
    "gn:asciiname":"Karuvaypalaiyam",
    "gn:country_code":"IN",
    "gn:dem":173,
    "gn:feature_class":"P",
    "gn:feature_code":"PPL",
    "gn:name":"Karuv\u0101yp\u0101laiyam",
    "gn:population":0,
    "gn:timezone":"Asia/Kolkata",
    "iso:country":"IN",
    "wof:name":"Karuvaypalaiyam",
    "wof:placetype":"neighbourhood"
},
  "geometry": {"coordinates":[77.81059,11.06593],"type":"Point"}
}