{
  "type": "Feature",
  "properties": {
    "iso:country":"IN",
    "ks:ks_alt_nam":"PIPRAR PATI",
    "ks:ks_name":"Piprar Pati",
    "ks:ks_pop":180,
    "ks:ks_type":"HABITATION",
    "ks:ks_uagg_main":0,
    "name:eng_x_preferred":[
        "Piprar Pati"
    ],
    "wof:name":"Piprar Pati",
    "wof:placetype":"neighbourhood",
    "wof:population":180
},
  "geometry": {"coordinates":[87.398886,25.958556],"type":"Point"}
}