{
  "type": "Feature",
  "properties": {
    "gn:admin1_code":"19.0",
    "gn:admin2_code":"581.0",
    "gn:asciiname":"Krishnarajapuram",
    "gn:country_code":"IN",
    "gn:dem":839,
    "gn:feature_class":"P",
    "gn:feature_code":"PPL",
    "gn:name":"Krishnar\u0101japuram",
    "gn:population":0,
    "gn:timezone":"Asia/Kolkata",
    "iso:country":"IN",
    "name:ben_x_preferred":[
        "\u0995\u09c3\u09b7\u09cd\u09a3\u09b0\u09be\u099c\u09aa\u09c1\u09b0\u09be"
    ],
    "name:bpy_x_preferred":[
        "\u0995\u09c3\u09b7\u09cd\u09a3\u09b0\u09be\u099c\u09aa\u09c1\u09b0\u09be"
    ],
    "name:fas_x_preferred":[
        "\u06a9\u0631\u06cc\u0634\u0646\u0627\u0631\u0627\u062c\u0627\u067e\u0648\u0631\u0627"
    ],
    "name:ita_x_preferred":[
        "Krishnarajapura"
    ],
    "name:mlg_x_preferred":[
        "Krishnarajapura"
    ],
    "name:msa_x_preferred":[
        "Krishnarajapura"
    ],
    "name:new_x_preferred":[
        "\u0915\u0943\u0937\u094d\u0923\u0930\u093e\u091c\u092a\u0941\u0930\u093e"
    ],
    "name:nld_x_preferred":[
        "Krishnarajapura"
    ],
    "name:por_x_preferred":[
        "Krishnarajapura"
    ],
    "name:spa_x_preferred":[
        "Krishnarajapura"
    ],
    "name:tam_x_preferred":[
        "\u0b95\u0bc7.\u0b86\u0bb0\u0bcd \u0baa\u0bc1\u0bb0\u0bae\u0bcd"
    ],
    "name:vie_x_preferred":[
        "Krishnarajapura"
    ],
    "name:zho_x_preferred":[
        "\u514b\u91cc\u65af\u8d6b\u7eb3\u62c9\u8d3e\u666e\u62c9"
    ],
    "wof:name":"Krishnarajapuram",
    "wof:placetype":"locality"
},
  "geometry": {"coordinates":[78.2593,12.99869],"type":"Point"}
}