{
  "type": "Feature",
  "properties": {
    "gn:admin1_code":"19.0",
    "gn:admin2_code":"581.0",
    "gn:asciiname":"Krishnarajapuram",
    "gn:country_code":"IN",
    "gn:dem":839,
    "gn:feature_class":"P",
    "gn:feature_code":"PPL",
    "gn:name":"Krishnar\u0101japuram",
    "gn:population":0,
    "gn:timezone":"Asia/Kolkata",
    "iso:country":"IN",
    "wof:name":"Krishnarajapuram",
    "wof:placetype":"locality"
},
  "geometry": {"coordinates":[78.2593,12.99869],"type":"Point"}
}