{
  "type": "Feature",
  "properties": {
    "iso:country":"IN",
    "ks:ks_name":"Pallikuppam",
    "ks:ks_pop":165,
    "ks:ks_type":"HABITATION",
    "name:eng_x_preferred":[
        "Pallikuppam"
    ],
    "wof:name":"Pallikuppam",
    "wof:placetype":"locality",
    "wof:population":165
},
  "geometry": {"coordinates":[80.225903,13.377289],"type":"Point"}
}