{
  "type": "Feature",
  "properties": {
    "iso:country":"IN",
    "ks:ks_name":"Lodh Purwa",
    "ks:ks_pop":200,
    "ks:ks_type":"HABITATION",
    "name:eng_x_preferred":[
        "Lodh Purwa"
    ],
    "wof:name":"Lodh Purwa",
    "wof:placetype":"locality",
    "wof:population":200
},
  "geometry": {"coordinates":[81.09159699999999,27.737965],"type":"Point"}
}