{
  "type": "Feature",
  "properties": {
    "iso:country":"IN",
    "ks:ks_alt_nam":"Kakkan theru",
    "ks:ks_name":"Kakkan Theru",
    "ks:ks_pop":250,
    "ks:ks_type":"HABITATION",
    "name:eng_x_preferred":[
        "Kakkan Theru"
    ],
    "wof:name":"Kakkan Theru",
    "wof:placetype":"locality",
    "wof:population":250
},
  "geometry": {"coordinates":[78.946742,10.703737],"type":"Point"}
}