{
  "type": "Feature",
  "properties": {
    "iso:country":"IN",
    "ks:ks_name":"Kaivatta",
    "ks:ks_pop":550,
    "ks:ks_type":"HABITATION",
    "ks:ks_uagg_main":0,
    "name:eng_x_preferred":[
        "Kaivatta"
    ],
    "wof:name":"Kaivatta",
    "wof:placetype":"neighbourhood",
    "wof:population":550
},
  "geometry": {"coordinates":[76.37545299999999,11.569601],"type":"Point"}
}