{
  "type": "Feature",
  "properties": {
    "gn:admin1_code":"35",
    "gn:admin2_code":"427.0",
    "gn:asciiname":"Nirandpur",
    "gn:country_code":"IN",
    "gn:dem":452,
    "gn:feature_class":"P",
    "gn:feature_code":"PPL",
    "gn:name":"Nirandpur",
    "gn:population":0,
    "gn:timezone":"Asia/Kolkata",
    "iso:country":"IN",
    "wof:name":"Nirandpur",
    "wof:placetype":"locality"
},
  "geometry": {"coordinates":[79.07415999999998,23.22917],"type":"Point"}
}