{
  "type": "Feature",
  "properties": {
    "iso:country":"IN",
    "ks:ks_name":"Byranaikanahalli",
    "ks:ks_pop":712,
    "ks:ks_type":"VILLAGE",
    "name:eng_x_preferred":[
        "Byranaikanahalli"
    ],
    "wof:name":"Byranaikanahalli",
    "wof:placetype":"locality",
    "wof:population":712
},
  "geometry": {"coordinates":[76.45929099999999,13.291038],"type":"Point"}
}