{
  "type": "Feature",
  "properties": {
    "iso:country":"IN",
    "ks:ks_alt_nam":"chattanmane",
    "ks:ks_name":"Chattanmane",
    "ks:ks_pop":38,
    "ks:ks_type":"HABITATION",
    "name:eng_x_preferred":[
        "Chattanmane"
    ],
    "wof:name":"Chattanmane",
    "wof:placetype":"locality",
    "wof:population":38
},
  "geometry": {"coordinates":[74.631484,14.756747],"type":"Point"}
}