{
  "type": "Feature",
  "properties": {
    "gn:admin1_code":"35.0",
    "gn:admin2_code":"455.0",
    "gn:asciiname":"Poama",
    "gn:country_code":"IN",
    "gn:dem":700,
    "gn:feature_class":"P",
    "gn:feature_code":"PPL",
    "gn:name":"Po\u0101ma",
    "gn:population":0,
    "gn:timezone":"Asia/Kolkata",
    "iso:country":"IN",
    "ks:ks_alt_nam":"Po\u0101ma",
    "ks:ks_name":"Poama",
    "ks:ks_pop":1611,
    "ks:ks_type":"VILLAGE",
    "ks:ks_uagg_main":0,
    "name:deu_x_preferred":[
        "Poama"
    ],
    "name:eng_x_preferred":[
        "Poama"
    ],
    "name:eng_x_variant":[
        "Po\u0101ma"
    ],
    "name:est_x_preferred":[
        "Poama"
    ],
    "name:hye_x_preferred":[
        "\u054a\u0578\u0561\u0574\u0561"
    ],
    "name:pol_x_preferred":[
        "Poama"
    ],
    "name:spa_x_preferred":[
        "Poama"
    ],
    "name:vol_x_preferred":[
        "Poama"
    ],
    "wof:name":"Poama",
    "wof:placetype":"locality",
    "wof:population":1611
},
  "geometry": {"coordinates":[78.885092,22.069167],"type":"Point"}
}