{
  "type": "Feature",
  "properties": {
    "gn:admin1_code":"36.0",
    "gn:admin2_code":"169.0",
    "gn:asciiname":"Saragpura",
    "gn:country_code":"IN",
    "gn:dem":179,
    "gn:feature_class":"P",
    "gn:feature_code":"PPL",
    "gn:name":"Saragpura",
    "gn:population":0,
    "gn:timezone":"Asia/Kolkata",
    "iso:country":"IN",
    "ks:ks_name":"Saragpura",
    "ks:ks_pop":306,
    "ks:ks_type":"VILLAGE",
    "name:eng_x_preferred":[
        "Saragpura"
    ],
    "wof:name":"Saragpura",
    "wof:placetype":"locality",
    "wof:population":306
},
  "geometry": {"coordinates":[79.471613,25.402064],"type":"Point"}
}