{
  "type": "Feature",
  "properties": {
    "iso:country":"IN",
    "ks:ks_name":"Harsauli",
    "ks:ks_pop":210,
    "ks:ks_type":"VILLAGE",
    "name:eng_x_preferred":[
        "Harsauli"
    ],
    "wof:name":"Harsauli",
    "wof:placetype":"locality",
    "wof:population":210
},
  "geometry": {"coordinates":[80.82989499999999,25.182775],"type":"Point"}
}