{
  "type": "Feature",
  "properties": {
    "iso:country":"IN",
    "ks:ks_name":"Saheed Ki Dhani",
    "ks:ks_pop":40,
    "ks:ks_type":"HABITATION",
    "name:eng_x_preferred":[
        "Saheed Ki Dhani"
    ],
    "wof:name":"Saheed Ki Dhani",
    "wof:placetype":"locality",
    "wof:population":40
},
  "geometry": {"coordinates":[71.05544999999999,25.807372],"type":"Point"}
}