{
  "type": "Feature",
  "properties": {
    "gn:admin1_code":"36",
    "gn:admin2_code":"195.0",
    "gn:asciiname":"Palhantari",
    "gn:country_code":"IN",
    "gn:dem":75,
    "gn:feature_class":"P",
    "gn:feature_code":"PPL",
    "gn:name":"P\u0101lhantari",
    "gn:population":0,
    "gn:timezone":"Asia/Kolkata",
    "iso:country":"IN",
    "wof:name":"Palhantari",
    "wof:placetype":"locality"
},
  "geometry": {"coordinates":[83.37810999999998,25.68757],"type":"Point"}
}