{
  "type": "Feature",
  "properties": {
    "iso:country":"IN",
    "ks:ks_name":"Revandkarwadi",
    "ks:ks_pop":126,
    "ks:ks_type":"HABITATION",
    "name:eng_x_preferred":[
        "Revandkarwadi"
    ],
    "wof:name":"Revandkarwadi",
    "wof:placetype":"locality",
    "wof:population":126
},
  "geometry": {"coordinates":[73.484438,16.04018],"type":"Point"}
}