{
  "type": "Feature",
  "properties": {
    "iso:country":"IN",
    "ks:ks_alt_nam":"KULTE VASTI",
    "ks:ks_name":"Kulte Vasti",
    "ks:ks_pop":123,
    "ks:ks_type":"HABITATION",
    "name:eng_x_preferred":[
        "Kulte Vasti"
    ],
    "wof:name":"Kulte Vasti",
    "wof:placetype":"locality",
    "wof:population":123
},
  "geometry": {"coordinates":[74.921734,19.620272],"type":"Point"}
}