{
  "type": "Feature",
  "properties": {
    "gn:admin1_code":"11",
    "gn:admin2_code":"23.0",
    "gn:asciiname":"Mulki",
    "gn:country_code":"IN",
    "gn:dem":1514,
    "gn:feature_class":"P",
    "gn:feature_code":"PPL",
    "gn:name":"Mulki",
    "gn:population":0,
    "gn:timezone":"Asia/Kolkata",
    "iso:country":"IN",
    "name:deu_x_preferred":[
        "Mulki"
    ],
    "wof:name":"Mulki",
    "wof:placetype":"locality"
},
  "geometry": {"coordinates":[76.13613000000002,32.65716],"type":"Point"}
}