{
  "type": "Feature",
  "properties": {
    "gn:country":"IN",
    "gn:fcode":"PPL",
    "gn:population":19234,
    "iso:country":"IN",
    "name:ben_x_preferred":[
        "\u09ac\u09be\u0999\u09be"
    ],
    "name:ceb_x_preferred":[
        "Banga"
    ],
    "name:eng_x_preferred":[
        "Banga"
    ],
    "name:ita_x_preferred":[
        "Banga"
    ],
    "name:msa_x_preferred":[
        "Banga"
    ],
    "name:nld_x_preferred":[
        "Banga"
    ],
    "name:spa_x_preferred":[
        "Banga"
    ],
    "name:swe_x_preferred":[
        "Banga"
    ],
    "qs_pg:aaroncc":"IN",
    "qs_pg:gn_country":"IN",
    "qs_pg:gn_fcode":"PPL",
    "qs_pg:gn_pop":19234,
    "qs_pg:name":"Bagga",
    "qs_pg:name_adm0":"India",
    "qs_pg:name_adm1":"Punjab",
    "qs_pg:photos_9r":0,
    "qs_pg:photos_sr":0,
    "qs_pg:pop_sr":6,
    "qs_pg:qs_pg_placetype":"locality",
    "qs_pg:qs_pg_placetype_gp":"Town",
    "qs_pg:woe_adm0":23424848,
    "woe:adm0_id":23424848,
    "woe:name_adm0":"India",
    "woe:name_adm1":"Punjab",
    "woe:placetype":"Town",
    "wof:name":"Bagga",
    "wof:placetype":"locality",
    "wof:population":19234
},
  "geometry": {"coordinates":[75.99643,31.18602],"type":"Point"}
}