{
  "type": "Feature",
  "properties": {
    "iso:country":"IN",
    "ks:ks_alt_nam":"barhi tola",
    "ks:ks_name":"Barhi Tola",
    "ks:ks_pop":269,
    "ks:ks_type":"HABITATION",
    "name:eng_x_preferred":[
        "Barhi Tola"
    ],
    "wof:name":"Barhi Tola",
    "wof:placetype":"locality",
    "wof:population":269
},
  "geometry": {"coordinates":[85.74683,25.806551],"type":"Point"}
}