{
  "type": "Feature",
  "properties": {
    "gn:admin1_code":"36.0",
    "gn:admin2_code":"136.0",
    "gn:asciiname":"Harirain -ka-Mazra",
    "gn:country_code":"IN",
    "gn:dem":211,
    "gn:feature_class":"P",
    "gn:feature_code":"PPL",
    "gn:name":"Harir\u0101\u012bn -k\u0101-Mazra",
    "gn:population":0,
    "gn:timezone":"Asia/Kolkata",
    "iso:country":"IN",
    "wof:name":"Harirain -ka-Mazra",
    "wof:placetype":"locality"
},
  "geometry": {"coordinates":[79.13781999999998,29.05661],"type":"Point"}
}