{
  "type": "Feature",
  "properties": {
    "iso:country":"IN",
    "ks:ks_name":"Badera",
    "ks:ks_pop":165,
    "ks:ks_type":"VILLAGE",
    "name:eng_x_preferred":[
        "Badera"
    ],
    "wof:name":"Badera",
    "wof:placetype":"locality",
    "wof:population":165
},
  "geometry": {"coordinates":[82.224148,23.613912],"type":"Point"}
}