{
  "type": "Feature",
  "properties": {
    "iso:country":"IN",
    "ks:ks_alt_nam":"Kaikalathangal ADC",
    "ks:ks_name":"Kaikalathangal Adc",
    "ks:ks_pop":1176,
    "ks:ks_type":"HABITATION",
    "name:eng_x_preferred":[
        "Kaikalathangal Adc"
    ],
    "wof:name":"Kaikalathangal Adc",
    "wof:placetype":"locality",
    "wof:population":1176
},
  "geometry": {"coordinates":[79.24427,12.655871],"type":"Point"}
}