{
  "type": "Feature",
  "properties": {
    "gn:admin1_code":"36.0",
    "gn:admin2_code":"158.0",
    "gn:asciiname":"Mirza",
    "gn:country_code":"IN",
    "gn:dem":117,
    "gn:feature_class":"P",
    "gn:feature_code":"PPL",
    "gn:name":"Mirza",
    "gn:population":0,
    "gn:timezone":"Asia/Kolkata",
    "iso:country":"IN",
    "name:ara_x_preferred":[
        "\u0645\u064a\u0631\u0632\u0627"
    ],
    "name:bel_x_preferred":[
        "\u041c\u0456\u0440\u0437\u0430"
    ],
    "name:ben_x_preferred":[
        "\u09ae\u09c0\u09b0\u09cd\u099c\u09be"
    ],
    "name:fas_x_preferred":[
        "\u0645\u06cc\u0631\u0632\u0627"
    ],
    "name:hin_x_preferred":[
        "\u092e\u093f\u0930\u094d\u091c\u093c\u093e"
    ],
    "name:mar_x_preferred":[
        "\u092e\u093f\u0930\u094d\u091d\u093e"
    ],
    "name:pan_x_preferred":[
        "\u0a2e\u0a3f\u0a30\u0a1c\u0a3c\u0a3e"
    ],
    "name:rus_x_preferred":[
        "\u041c\u0443\u0440\u0437\u0430"
    ],
    "name:slv_x_preferred":[
        "Mirza"
    ],
    "name:tam_x_preferred":[
        "\u0bae\u0bc0\u0bb0\u0bcd\u0b9a\u0bbe"
    ],
    "name:tel_x_preferred":[
        "\u0c2e\u0c3f\u0c30\u0c4d\u0c1c\u0c3e"
    ],
    "name:urd_x_preferred":[
        "\u0645\u06cc\u0631\u0632\u0627"
    ],
    "name:zho_x_preferred":[
        "\u7c73\u5c14\u624e"
    ],
    "wof:name":"Mirza",
    "wof:placetype":"locality"
},
  "geometry": {"coordinates":[81.24630000000001,25.94869],"type":"Point"}
}