{
  "type": "Feature",
  "properties": {
    "iso:country":"IN",
    "ks:ks_name":"Samse",
    "ks:ks_pop":72,
    "ks:ks_type":"HABITATION",
    "name:eng_x_preferred":[
        "Samse"
    ],
    "wof:name":"Samse",
    "wof:placetype":"locality",
    "wof:population":72
},
  "geometry": {"coordinates":[74.81358,14.054661],"type":"Point"}
}