{
  "type": "Feature",
  "properties": {
    "iso:country":"IN",
    "ks:ks_name":"Maheripar",
    "ks:ks_pop":5171,
    "ks:ks_type":"VILLAGE",
    "name:eng_x_preferred":[
        "Maheripar"
    ],
    "wof:name":"Maheripar",
    "wof:placetype":"locality",
    "wof:population":5171
},
  "geometry": {"coordinates":[92.681963,26.458222],"type":"Point"}
}