{
  "type": "Feature",
  "properties": {
    "gn:admin1_code":"19.0",
    "gn:admin2_code":"581.0",
    "gn:asciiname":"Darenahalli",
    "gn:country_code":"IN",
    "gn:dem":785,
    "gn:feature_class":"P",
    "gn:feature_code":"PPL",
    "gn:name":"D\u0101renahalli",
    "gn:population":0,
    "gn:timezone":"Asia/Kolkata",
    "iso:country":"IN",
    "ks:ks_alt_nam":"D\u0101renahalli",
    "ks:ks_name":"Darenahalli",
    "ks:ks_pop":87,
    "ks:ks_type":"VILLAGE",
    "name:eng_x_preferred":[
        "Darenahalli"
    ],
    "name:eng_x_variant":[
        "D\u0101renahalli"
    ],
    "wof:name":"Darenahalli",
    "wof:placetype":"locality",
    "wof:population":87
},
  "geometry": {"coordinates":[78.42062199999999,13.182068],"type":"Point"}
}