{
  "type": "Feature",
  "properties": {
    "iso:country":"IN",
    "ks:ks_name":"Shinganmakki",
    "ks:ks_pop":227,
    "ks:ks_type":"VILLAGE",
    "name:eng_x_preferred":[
        "Shinganmakki"
    ],
    "wof:name":"Shinganmakki",
    "wof:placetype":"locality",
    "wof:population":227
},
  "geometry": {"coordinates":[74.318243,14.619803],"type":"Point"}
}