{
  "type": "Feature",
  "properties": {
    "iso:country":"IN",
    "ks:ks_name":"Chabbishpur",
    "ks:ks_pop":3563,
    "ks:ks_type":"VILLAGE",
    "name:eng_x_preferred":[
        "Chabbishpur"
    ],
    "wof:name":"Chabbishpur",
    "wof:placetype":"locality",
    "wof:population":3563
},
  "geometry": {"coordinates":[87.924423,22.699686],"type":"Point"}
}