{
  "type": "Feature",
  "properties": {
    "iso:country":"IN",
    "ks:ks_name":"Panasi Bari",
    "ks:ks_pop":509,
    "ks:ks_type":"VILLAGE",
    "name:eng_x_preferred":[
        "Panasi Bari"
    ],
    "wof:name":"Panasi Bari",
    "wof:placetype":"locality",
    "wof:population":509
},
  "geometry": {"coordinates":[74.275954,23.542549],"type":"Point"}
}