{
  "type": "Feature",
  "properties": {
    "gn:admin1_code":"36.0",
    "gn:admin2_code":"132.0",
    "gn:asciiname":"Baliakheri",
    "gn:country_code":"IN",
    "gn:dem":277,
    "gn:feature_class":"P",
    "gn:feature_code":"PPL",
    "gn:name":"Baliakheri",
    "gn:population":0,
    "gn:timezone":"Asia/Kolkata",
    "iso:country":"IN",
    "name:urd_x_preferred":[
        "\u0628\u0627\u0644\u06cc\u0627\u06a9\u06be\u06cc\u0631\u06cc"
    ],
    "wof:name":"Baliakheri",
    "wof:placetype":"locality"
},
  "geometry": {"coordinates":[77.63785,29.92481],"type":"Point"}
}