{
  "type": "Feature",
  "properties": {
    "iso:country":"IN",
    "ks:ks_name":"No.1 Samuka",
    "ks:ks_pop":1269,
    "ks:ks_type":"VILLAGE",
    "name:eng_x_preferred":[
        "No.1 Samuka"
    ],
    "wof:name":"No.1 Samuka",
    "wof:placetype":"locality",
    "wof:population":1269
},
  "geometry": {"coordinates":[91.16291200000001,25.884924],"type":"Point"}
}