{
  "type": "Feature",
  "properties": {
    "iso:country":"IN",
    "ks:ks_name":"Surumunda",
    "ks:ks_pop":17,
    "ks:ks_type":"HABITATION",
    "name:eng_x_preferred":[
        "Surumunda"
    ],
    "wof:name":"Surumunda",
    "wof:placetype":"locality",
    "wof:population":17
},
  "geometry": {"coordinates":[82.42465900000001,19.650983],"type":"Point"}
}