{
  "type": "Feature",
  "properties": {
    "iso:country":"IN",
    "ks:ks_name":"Nadigadi",
    "ks:ks_pop":798,
    "ks:ks_type":"HABITATION",
    "name:eng_x_preferred":[
        "Nadigadi"
    ],
    "wof:name":"Nadigadi",
    "wof:placetype":"locality",
    "wof:population":798
},
  "geometry": {"coordinates":[81.876395,16.576482],"type":"Point"}
}