{
  "type": "Feature",
  "properties": {
    "iso:country":"IN",
    "ks:ks_name":"Silapas",
    "ks:ks_pop":333,
    "ks:ks_type":"VILLAGE",
    "name:eng_x_preferred":[
        "Silapas"
    ],
    "wof:name":"Silapas",
    "wof:placetype":"locality",
    "wof:population":333
},
  "geometry": {"coordinates":[82.97422400000001,19.304396],"type":"Point"}
}