{
  "type": "Feature",
  "properties": {
    "iso:country":"IN",
    "ks:ks_name":"Danpura",
    "ks:ks_pop":1365,
    "ks:ks_type":"VILLAGE",
    "name:eng_x_preferred":[
        "Danpura"
    ],
    "wof:name":"Danpura",
    "wof:placetype":"locality",
    "wof:population":1365
},
  "geometry": {"coordinates":[71.988283,26.237942],"type":"Point"}
}