{
  "type": "Feature",
  "properties": {
    "gn:admin1_code":"36",
    "gn:admin2_code":"175.0",
    "gn:asciiname":"Bhausara Jagir",
    "gn:country_code":"IN",
    "gn:dem":153,
    "gn:feature_class":"P",
    "gn:feature_code":"PPL",
    "gn:name":"Bhausara J\u0101g\u012br",
    "gn:population":0,
    "gn:timezone":"Asia/Kolkata",
    "iso:country":"IN",
    "wof:name":"Bhausara Jagir",
    "wof:placetype":"locality"
},
  "geometry": {"coordinates":[82.25728000000002,25.02303],"type":"Point"}
}