{
  "type": "Feature",
  "properties": {
    "iso:country":"IN",
    "ks:ks_name":"Karzupatola",
    "ks:ks_pop":640,
    "ks:ks_type":"HABITATION",
    "ks:ks_uagg_main":0,
    "name:eng_x_preferred":[
        "Karzupatola"
    ],
    "wof:name":"Karzupatola",
    "wof:placetype":"neighbourhood",
    "wof:population":640
},
  "geometry": {"coordinates":[85.17281,23.51523],"type":"Point"}
}