{
  "type": "Feature",
  "properties": {
    "iso:country":"IN",
    "ks:ks_name":"Gayatrinagar",
    "ks:ks_pop":207,
    "ks:ks_type":"HABITATION",
    "ks:ks_uagg_main":0,
    "name:eng_x_preferred":[
        "Gayatrinagar"
    ],
    "wof:name":"Gayatrinagar",
    "wof:placetype":"neighbourhood",
    "wof:population":207
},
  "geometry": {"coordinates":[70.365477,22.407008],"type":"Point"}
}