{
  "type": "Feature",
  "properties": {
    "gn:admin1_code":"9.0",
    "gn:admin2_code":"478",
    "gn:asciiname":"Bakharla",
    "gn:country_code":"IN",
    "gn:dem":37,
    "gn:feature_class":"P",
    "gn:feature_code":"PPL",
    "gn:name":"B\u0101kharla",
    "gn:population":0,
    "gn:timezone":"Asia/Kolkata",
    "iso:country":"IN",
    "name:ceb_x_preferred":[
        "B\u0101kharla"
    ],
    "name:guj_x_preferred":[
        "\u0aac\u0a96\u0ab0\u0ab2\u0abe"
    ],
    "name:swe_x_preferred":[
        "B\u0101kharla"
    ],
    "name:und_x_variant":[
        "B\u0101kharla",
        "Bakharia"
    ],
    "wof:name":"Bakharla",
    "wof:placetype":"locality"
},
  "geometry": {"coordinates":[69.6354,21.73159],"type":"Point"}
}