{
  "type": "Feature",
  "properties": {
    "gn:admin1_code":"21.0",
    "gn:admin2_code":"398.0",
    "gn:asciiname":"Kusumoguda",
    "gn:country_code":"IN",
    "gn:dem":653,
    "gn:feature_class":"P",
    "gn:feature_code":"PPL",
    "gn:name":"Kusumoguda",
    "gn:population":0,
    "gn:timezone":"Asia/Kolkata",
    "iso:country":"IN",
    "wof:name":"Kusumoguda",
    "wof:placetype":"locality"
},
  "geometry": {"coordinates":[82.69324,18.9173],"type":"Point"}
}