{
  "type": "Feature",
  "properties": {
    "gn:admin1_code":"36.0",
    "gn:admin2_code":"150.0",
    "gn:asciiname":"Kamalpur Janubi",
    "gn:country_code":"IN",
    "gn:dem":182,
    "gn:feature_class":"P",
    "gn:feature_code":"PPL",
    "gn:name":"Kam\u0101lpur Jan\u016bbi",
    "gn:population":0,
    "gn:timezone":"Asia/Kolkata",
    "iso:country":"IN",
    "ks:ks_alt_nam":"Kam\u0101lpur Jan\u016bbi",
    "ks:ks_name":"Kamalpur Janubi",
    "ks:ks_type":"VILLAGE",
    "name:eng_x_preferred":[
        "Kamalpur Janubi"
    ],
    "name:eng_x_variant":[
        "Kam\u0101lpur Jan\u016bbi"
    ],
    "wof:name":"Kamalpur Janubi",
    "wof:placetype":"locality"
},
  "geometry": {"coordinates":[79.440395,28.644786],"type":"Point"}
}