{
  "type": "Feature",
  "properties": {
    "iso:country":"IN",
    "ks:ks_name":"Balapur",
    "ks:ks_pop":0,
    "ks:ks_type":"VILLAGE",
    "name:eng_x_preferred":[
        "Balapur"
    ],
    "wof:name":"Balapur",
    "wof:placetype":"locality",
    "wof:population":0
},
  "geometry": {"coordinates":[78.011017,20.932327],"type":"Point"}
}