{
  "type": "Feature",
  "properties": {
    "iso:country":"IN",
    "ks:ks_name":"Podugampatti",
    "ks:ks_pop":127,
    "ks:ks_type":"HABITATION",
    "name:eng_x_preferred":[
        "Podugampatti"
    ],
    "wof:name":"Podugampatti",
    "wof:placetype":"locality",
    "wof:population":127
},
  "geometry": {"coordinates":[78.167126,10.110536],"type":"Point"}
}