{
  "type": "Feature",
  "properties": {
    "iso:country":"IN",
    "ks:ks_name":"Tulasibani",
    "ks:ks_pop":642,
    "ks:ks_type":"VILLAGE",
    "name:eng_x_preferred":[
        "Tulasibani"
    ],
    "wof:name":"Tulasibani",
    "wof:placetype":"locality",
    "wof:population":642
},
  "geometry": {"coordinates":[86.156147,21.966772],"type":"Point"}
}