{
  "type": "Feature",
  "properties": {
    "iso:country":"IN",
    "ks:ks_name":"Jamansonda",
    "ks:ks_pop":494,
    "ks:ks_type":"HABITATION",
    "name:eng_x_preferred":[
        "Jamansonda"
    ],
    "wof:name":"Jamansonda",
    "wof:placetype":"locality",
    "wof:population":494
},
  "geometry": {"coordinates":[73.85941699999999,20.916194],"type":"Point"}
}