{
  "type": "Feature",
  "properties": {
    "gn:admin1_code":"36",
    "gn:admin2_code":"199.0",
    "gn:asciiname":"Chaura",
    "gn:country_code":"IN",
    "gn:dem":89,
    "gn:feature_class":"P",
    "gn:feature_code":"PPL",
    "gn:name":"Chaura",
    "gn:population":0,
    "gn:timezone":"Asia/Kolkata",
    "iso:country":"IN",
    "name:ceb_x_preferred":[
        "Chaura"
    ],
    "name:swe_x_preferred":[
        "Chaura"
    ],
    "wof:name":"Chaura",
    "wof:placetype":"locality"
},
  "geometry": {"coordinates":[82.64471,25.11977000000001],"type":"Point"}
}