{
  "type": "Feature",
  "properties": {
    "iso:country":"IN",
    "ks:ks_name":"Amti Falia",
    "ks:ks_pop":251,
    "ks:ks_type":"HABITATION",
    "ks:ks_uagg_main":0,
    "name:eng_x_preferred":[
        "Amti Falia"
    ],
    "wof:name":"Amti Falia",
    "wof:placetype":"neighbourhood",
    "wof:population":251
},
  "geometry": {"coordinates":[73.369417,20.308222],"type":"Point"}
}