{
  "type": "Feature",
  "properties": {
    "gn:admin1_code":"24.0",
    "gn:admin2_code":"102.0",
    "gn:asciiname":"Saiuwo",
    "gn:country_code":"IN",
    "gn:dem":242,
    "gn:feature_class":"P",
    "gn:feature_code":"PPL",
    "gn:name":"Saiuwo",
    "gn:population":0,
    "gn:timezone":"Asia/Kolkata",
    "iso:country":"IN",
    "wof:name":"Saiuwo",
    "wof:placetype":"neighbourhood"
},
  "geometry": {"coordinates":[75.15877,28.63546],"type":"Point"}
}