{
  "type": "Feature",
  "properties": {
    "gn:admin1_code":"2.0",
    "gn:admin2_code":"550.0",
    "gn:asciiname":"Gemallavarikatta",
    "gn:country_code":"IN",
    "gn:dem":7,
    "gn:feature_class":"P",
    "gn:feature_code":"PPL",
    "gn:name":"Gemallav\u0101rikatta",
    "gn:population":0,
    "gn:timezone":"Asia/Kolkata",
    "iso:country":"IN",
    "wof:name":"Gemallavarikatta",
    "wof:placetype":"locality"
},
  "geometry": {"coordinates":[79.98643,13.67494],"type":"Point"}
}