{
  "type": "Feature",
  "properties": {
    "iso:country":"IN",
    "ks:ks_name":"Kawada",
    "ks:ks_pop":10,
    "ks:ks_type":"HABITATION",
    "name:eng_x_preferred":[
        "Kawada"
    ],
    "wof:name":"Kawada",
    "wof:placetype":"locality",
    "wof:population":10
},
  "geometry": {"coordinates":[74.468779,14.834586],"type":"Point"}
}