{
  "type": "Feature",
  "properties": {
    "iso:country":"IN",
    "ks:ks_name":"Bavadi Kheda Kalan",
    "ks:ks_pop":627,
    "ks:ks_type":"VILLAGE",
    "name:eng_x_preferred":[
        "Bavadi Kheda Kalan"
    ],
    "wof:name":"Bavadi Kheda Kalan",
    "wof:placetype":"locality",
    "wof:population":627
},
  "geometry": {"coordinates":[74.752121,23.513559],"type":"Point"}
}