{
  "type": "Feature",
  "properties": {
    "gn:admin1_code":"23.0",
    "gn:admin2_code":"35.0",
    "gn:asciiname":"Nathpur",
    "gn:country_code":"IN",
    "gn:dem":254,
    "gn:feature_class":"P",
    "gn:feature_code":"PPL",
    "gn:name":"Nathpur",
    "gn:population":0,
    "gn:timezone":"Asia/Kolkata",
    "iso:country":"IN",
    "ks:ks_name":"Nathpur",
    "ks:ks_pop":1825,
    "ks:ks_type":"VILLAGE",
    "ks:ks_uagg_main":0,
    "name:eng_x_preferred":[
        "Nathpur"
    ],
    "wof:name":"Nathpur",
    "wof:placetype":"neighbourhood",
    "wof:population":1825
},
  "geometry": {"coordinates":[75.36306999999999,31.818696],"type":"Point"}
}