{
  "type": "Feature",
  "properties": {
    "iso:country":"IN",
    "ks:ks_name":"Amiwara",
    "ks:ks_pop":214,
    "ks:ks_type":"HABITATION",
    "name:eng_x_preferred":[
        "Amiwara"
    ],
    "wof:name":"Amiwara",
    "wof:placetype":"locality",
    "wof:population":214
},
  "geometry": {"coordinates":[73.375292,24.295603],"type":"Point"}
}