{
  "type": "Feature",
  "properties": {
    "gn:admin1_code":"39.0",
    "gn:admin2_code":"64.0",
    "gn:asciiname":"Bhainsora",
    "gn:country_code":"IN",
    "gn:dem":1484,
    "gn:feature_class":"P",
    "gn:feature_code":"PPL",
    "gn:name":"Bhainsora",
    "gn:population":0,
    "gn:timezone":"Asia/Kolkata",
    "iso:country":"IN",
    "ks:ks_name":"Bhaisora",
    "ks:ks_pop":160,
    "ks:ks_type":"VILLAGE",
    "name:eng_x_preferred":[
        "Bhaisora"
    ],
    "name:eng_x_variant":[
        "Bhainsora"
    ],
    "wof:name":"Bhaisora",
    "wof:placetype":"locality",
    "wof:population":160
},
  "geometry": {"coordinates":[79.671322,29.556038],"type":"Point"}
}