{
  "type": "Feature",
  "properties": {
    "iso:country":"IN",
    "ks:ks_name":"Hesaba",
    "ks:ks_pop":2132,
    "ks:ks_type":"HABITATION",
    "name:eng_x_preferred":[
        "Hesaba"
    ],
    "wof:name":"Hesaba",
    "wof:placetype":"locality",
    "wof:population":2132
},
  "geometry": {"coordinates":[73.253559,27.0847],"type":"Point"}
}