{
  "type": "Feature",
  "properties": {
    "iso:country":"IN",
    "ks:ks_name":"Pallapu Indlu",
    "ks:ks_pop":137,
    "ks:ks_type":"HABITATION",
    "name:eng_x_preferred":[
        "Pallapu Indlu"
    ],
    "wof:name":"Pallapu Indlu",
    "wof:placetype":"locality",
    "wof:population":137
},
  "geometry": {"coordinates":[79.34823400000001,13.395034],"type":"Point"}
}