{
  "type": "Feature",
  "properties": {
    "iso:country":"IN",
    "ks:ks_alt_nam":"SOSOPI",
    "ks:ks_name":"Sosopi",
    "ks:ks_pop":29,
    "ks:ks_type":"HABITATION",
    "ks:ks_uagg_main":0,
    "name:eng_x_preferred":[
        "Sosopi"
    ],
    "wof:name":"Sosopi",
    "wof:placetype":"neighbourhood",
    "wof:population":29
},
  "geometry": {"coordinates":[85.9408,22.214659],"type":"Point"}
}