{
  "type": "Feature",
  "properties": {
    "iso:country":"IN",
    "ks:ks_name":"Chatra",
    "ks:ks_pop":103,
    "ks:ks_type":"HABITATION",
    "name:eng_x_preferred":[
        "Chatra"
    ],
    "wof:name":"Chatra",
    "wof:placetype":"locality",
    "wof:population":103
},
  "geometry": {"coordinates":[87.519397,25.103644],"type":"Point"}
}