{
  "type": "Feature",
  "properties": {
    "gn:admin1_code":"36",
    "gn:admin2_code":"173.0",
    "gn:asciiname":"Barupur",
    "gn:country_code":"IN",
    "gn:dem":109,
    "gn:feature_class":"P",
    "gn:feature_code":"PPL",
    "gn:name":"Bar\u016bpur",
    "gn:population":0,
    "gn:timezone":"Asia/Kolkata",
    "iso:country":"IN",
    "name:und_x_variant":[
        "Bar\u016bpur",
        "Waz\u012brpur"
    ],
    "wof:name":"Barupur",
    "wof:placetype":"locality"
},
  "geometry": {"coordinates":[81.55816,25.74006],"type":"Point"}
}