{
  "type": "Feature",
  "properties": {
    "gn:admin1_code":"12.0",
    "gn:admin2_code":"007",
    "gn:asciiname":"Bilaur",
    "gn:country_code":"IN",
    "gn:dem":735,
    "gn:feature_class":"P",
    "gn:feature_code":"PPL",
    "gn:name":"Bilaur",
    "gn:population":0,
    "gn:timezone":"Asia/Kolkata",
    "iso:country":"IN",
    "name:und_x_variant":[
        "B\u012blaur"
    ],
    "wof:name":"Bilaur",
    "wof:placetype":"locality"
},
  "geometry": {"coordinates":[75.60494,32.61384],"type":"Point"}
}