{
  "type": "Feature",
  "properties": {
    "iso:country":"IN",
    "ks:ks_name":"Kaimara",
    "ks:ks_pop":115,
    "ks:ks_type":"HABITATION",
    "name:eng_x_preferred":[
        "Kaimara"
    ],
    "wof:name":"Kaimara",
    "wof:placetype":"locality",
    "wof:population":115
},
  "geometry": {"coordinates":[76.484118,13.440974],"type":"Point"}
}