{
  "type": "Feature",
  "properties": {
    "gn:admin1_code":"36.0",
    "gn:admin2_code":"185.0",
    "gn:asciiname":"Purwa Kusauna",
    "gn:country_code":"IN",
    "gn:dem":88,
    "gn:feature_class":"P",
    "gn:feature_code":"PPL",
    "gn:name":"Purwa Kusauna",
    "gn:population":0,
    "gn:timezone":"Asia/Kolkata",
    "iso:country":"IN",
    "wof:name":"Purwa Kusauna",
    "wof:placetype":"locality"
},
  "geometry": {"coordinates":[82.86751,27.02051],"type":"Point"}
}