{
  "type": "Feature",
  "properties": {
    "iso:country":"IN",
    "ks:ks_name":"Dighi",
    "ks:ks_pop":170,
    "ks:ks_type":"VILLAGE",
    "name:eng_x_preferred":[
        "Dighi"
    ],
    "wof:name":"Dighi",
    "wof:placetype":"locality",
    "wof:population":170
},
  "geometry": {"coordinates":[85.292579,22.812528],"type":"Point"}
}