{
  "type": "Feature",
  "properties": {
    "gn:admin1_code":"12.0",
    "gn:asciiname":"Jabda",
    "gn:country_code":"IN",
    "gn:dem":1391,
    "gn:feature_class":"P",
    "gn:feature_code":"PPL",
    "gn:name":"Jabda",
    "gn:population":0,
    "gn:timezone":"Asia/Kolkata",
    "iso:country":"IN",
    "wof:name":"Jabda",
    "wof:placetype":"locality"
},
  "geometry": {"coordinates":[73.97738000000003,34.11499],"type":"Point"}
}