{
  "type": "Feature",
  "properties": {
    "iso:country":"IN",
    "ks:ks_name":"Lodh Deeh",
    "ks:ks_pop":420,
    "ks:ks_type":"HABITATION",
    "name:eng_x_preferred":[
        "Lodh Deeh"
    ],
    "wof:name":"Lodh Deeh",
    "wof:placetype":"locality",
    "wof:population":420
},
  "geometry": {"coordinates":[83.149574,27.212542],"type":"Point"}
}