{
  "type": "Feature",
  "properties": {
    "iso:country":"IN",
    "ks:ks_name":"Ludriamunda",
    "ks:ks_pop":0,
    "ks:ks_type":"VILLAGE",
    "name:eng_x_preferred":[
        "Ludriamunda"
    ],
    "wof:name":"Ludriamunda",
    "wof:placetype":"locality",
    "wof:population":0
},
  "geometry": {"coordinates":[83.69384700000001,20.682607],"type":"Point"}
}