{
  "type": "Feature",
  "properties": {
    "gn:admin1_code":"35",
    "gn:admin2_code":"464.0",
    "gn:asciiname":"Bhimpura",
    "gn:country_code":"IN",
    "gn:dem":282,
    "gn:feature_class":"P",
    "gn:feature_code":"PPL",
    "gn:name":"Bh\u012bmpura",
    "gn:population":0,
    "gn:timezone":"Asia/Kolkata",
    "iso:country":"IN",
    "ks:ks_alt_nam":"Bh\u012bmpura",
    "ks:ks_name":"Bhimpura",
    "ks:ks_pop":297,
    "ks:ks_type":"VILLAGE",
    "name:eng_x_preferred":[
        "Bhimpura"
    ],
    "name:eng_x_variant":[
        "Bh\u012bmpura"
    ],
    "wof:name":"Bhimpura",
    "wof:placetype":"locality",
    "wof:population":297
},
  "geometry": {"coordinates":[74.39078000000001,23.064864],"type":"Point"}
}