{
  "type": "Feature",
  "properties": {
    "iso:country":"IN",
    "ks:ks_name":"Sundara",
    "ks:ks_pop":219,
    "ks:ks_type":"VILLAGE",
    "ks:ks_uagg_main":0,
    "name:eng_x_preferred":[
        "Sundara"
    ],
    "wof:name":"Sundara",
    "wof:placetype":"neighbourhood",
    "wof:population":219
},
  "geometry": {"coordinates":[87.782786,23.905981],"type":"Point"}
}