{
  "type": "Feature",
  "properties": {
    "iso:country":"IN",
    "ks:ks_name":"Teloi Kinar Bangali",
    "ks:ks_pop":440,
    "ks:ks_type":"HABITATION",
    "name:eng_x_preferred":[
        "Teloi Kinar Bangali"
    ],
    "wof:name":"Teloi Kinar Bangali",
    "wof:placetype":"locality",
    "wof:population":440
},
  "geometry": {"coordinates":[94.95844,27.253993],"type":"Point"}
}