{
  "type": "Feature",
  "properties": {
    "iso:country":"IN",
    "ks:ks_name":"Pathak Tola",
    "ks:ks_pop":279,
    "ks:ks_type":"HABITATION",
    "ks:ks_uagg_main":0,
    "name:eng_x_preferred":[
        "Pathak Tola"
    ],
    "wof:name":"Pathak Tola",
    "wof:placetype":"neighbourhood",
    "wof:population":279
},
  "geometry": {"coordinates":[84.855098,26.694517],"type":"Point"}
}