{
  "type": "Feature",
  "properties": {
    "iso:country":"IN",
    "ks:ks_alt_nam":"TENUDIH I",
    "ks:ks_name":"Tenudih I",
    "ks:ks_pop":1054,
    "ks:ks_type":"HABITATION",
    "name:eng_x_preferred":[
        "Tenudih I"
    ],
    "wof:name":"Tenudih I",
    "wof:placetype":"locality",
    "wof:population":1054
},
  "geometry": {"coordinates":[84.239242,24.380171],"type":"Point"}
}