{
  "type": "Feature",
  "properties": {
    "iso:country":"IN",
    "ks:ks_name":"Dhanavadewadi",
    "ks:ks_pop":120,
    "ks:ks_type":"HABITATION",
    "name:eng_x_preferred":[
        "Dhanavadewadi"
    ],
    "wof:name":"Dhanavadewadi",
    "wof:placetype":"locality",
    "wof:population":120
},
  "geometry": {"coordinates":[73.594167,16.995278],"type":"Point"}
}