{
  "type": "Feature",
  "properties": {
    "gn:admin1_code":"23",
    "gn:admin2_code":"37.0",
    "gn:asciiname":"Lohar",
    "gn:country_code":"IN",
    "gn:dem":246,
    "gn:feature_class":"P",
    "gn:feature_code":"PPL",
    "gn:name":"Loh\u0101r",
    "gn:population":0,
    "gn:timezone":"Asia/Kolkata",
    "iso:country":"IN",
    "name:fra_x_preferred":[
        "Lohar"
    ],
    "name:nep_x_preferred":[
        "\u0932\u094b\u0939\u093e\u0930"
    ],
    "wof:name":"Lohar",
    "wof:placetype":"locality"
},
  "geometry": {"coordinates":[75.67718000000001,31.51019],"type":"Point"}
}