{
  "type": "Feature",
  "properties": {
    "iso:country":"IN",
    "ks:ks_name":"Kurna",
    "ks:ks_pop":669,
    "ks:ks_type":"VILLAGE",
    "name:eng_x_preferred":[
        "Kurna"
    ],
    "wof:name":"Kurna",
    "wof:placetype":"locality",
    "wof:population":669
},
  "geometry": {"coordinates":[85.173603,22.437351],"type":"Point"}
}