{
  "type": "Feature",
  "properties": {
    "iso:country":"IN",
    "ks:ks_name":"Gopalpur Gopal",
    "ks:ks_pop":1300,
    "ks:ks_type":"HABITATION",
    "name:eng_x_preferred":[
        "Gopalpur Gopal"
    ],
    "wof:name":"Gopalpur Gopal",
    "wof:placetype":"locality",
    "wof:population":1300
},
  "geometry": {"coordinates":[85.53781499999999,26.12239],"type":"Point"}
}