{
  "type": "Feature",
  "properties": {
    "iso:country":"IN",
    "ks:ks_alt_nam":"MAHATISAI",
    "ks:ks_name":"Mahatisai",
    "ks:ks_pop":283,
    "ks:ks_type":"HABITATION",
    "name:eng_x_preferred":[
        "Mahatisai"
    ],
    "wof:name":"Mahatisai",
    "wof:placetype":"locality",
    "wof:population":283
},
  "geometry": {"coordinates":[85.694757,22.137991],"type":"Point"}
}