{
  "type": "Feature",
  "properties": {
    "gn:admin1_code":"16.0",
    "gn:admin2_code":"505",
    "gn:asciiname":"Guguldoh",
    "gn:country_code":"IN",
    "gn:dem":331,
    "gn:feature_class":"P",
    "gn:feature_code":"PPL",
    "gn:name":"Guguldoh",
    "gn:population":0,
    "gn:timezone":"Asia/Kolkata",
    "iso:country":"IN",
    "name:und_x_variant":[
        "Guguldoho",
        "Ghogra",
        "Guguldoh"
    ],
    "wof:name":"Guguldoh",
    "wof:placetype":"locality"
},
  "geometry": {"coordinates":[79.43340000000001,21.42047],"type":"Point"}
}