{
  "type": "Feature",
  "properties": {
    "gn:admin1_code":"34.0",
    "gn:admin2_code":"236.0",
    "gn:asciiname":"Karman",
    "gn:country_code":"IN",
    "gn:dem":167,
    "gn:feature_class":"P",
    "gn:feature_code":"PPL",
    "gn:name":"Karm\u0101n",
    "gn:population":0,
    "gn:timezone":"Asia/Kolkata",
    "iso:country":"IN",
    "ks:ks_alt_nam":"Karm\u0101n",
    "ks:ks_name":"Karman",
    "ks:ks_type":"VILLAGE",
    "ks:ks_uagg_main":0,
    "name:eng_x_preferred":[
        "Karman"
    ],
    "name:eng_x_variant":[
        "Karm\u0101n"
    ],
    "wof:name":"Karman",
    "wof:placetype":"neighbourhood"
},
  "geometry": {"coordinates":[84.95177200000001,24.514657],"type":"Point"}
}