{
  "type": "Feature",
  "properties": {
    "iso:country":"IN",
    "ks:ks_name":"Bar Kot",
    "ks:ks_pop":170,
    "ks:ks_type":"VILLAGE",
    "name:eng_x_preferred":[
        "Bar Kot"
    ],
    "wof:name":"Bar Kot",
    "wof:placetype":"locality",
    "wof:population":170
},
  "geometry": {"coordinates":[78.67943,30.050199],"type":"Point"}
}