{
  "type": "Feature",
  "properties": {
    "gn:admin1_code":"19.0",
    "gn:admin2_code":"573.0",
    "gn:asciiname":"Kanchaghalli",
    "gn:country_code":"IN",
    "gn:dem":662,
    "gn:feature_class":"P",
    "gn:feature_code":"PPL",
    "gn:name":"Kanchaghalli",
    "gn:population":0,
    "gn:timezone":"Asia/Kolkata",
    "iso:country":"IN",
    "wof:name":"Kanchaghalli",
    "wof:placetype":"locality"
},
  "geometry": {"coordinates":[77.07717,12.28501],"type":"Point"}
}