{
  "type": "Feature",
  "properties": {
    "iso:country":"IN",
    "ks:ks_name":"Ganeshpura",
    "ks:ks_pop":610,
    "ks:ks_type":"VILLAGE",
    "ks:ks_uagg_main":0,
    "name:eng_x_preferred":[
        "Ganeshpura"
    ],
    "wof:name":"Ganeshpura",
    "wof:placetype":"neighbourhood",
    "wof:population":610
},
  "geometry": {"coordinates":[72.079702,23.518323],"type":"Point"}
}