{
  "type": "Feature",
  "properties": {
    "gn:admin1_code":"19.0",
    "gn:admin2_code":"574.0",
    "gn:asciiname":"Banageri",
    "gn:country_code":"IN",
    "gn:dem":950,
    "gn:feature_class":"P",
    "gn:feature_code":"PPL",
    "gn:name":"Banageri",
    "gn:population":0,
    "gn:timezone":"Asia/Kolkata",
    "iso:country":"IN",
    "wof:name":"Banageri",
    "wof:placetype":"locality"
},
  "geometry": {"coordinates":[75.74698000000002,12.69585],"type":"Point"}
}