{
  "type": "Feature",
  "properties": {
    "gn:admin1_code":"19.0",
    "gn:admin2_code":"574.0",
    "gn:asciiname":"Banageri",
    "gn:country_code":"IN",
    "gn:dem":950,
    "gn:feature_class":"P",
    "gn:feature_code":"PPL",
    "gn:name":"Banageri",
    "gn:population":0,
    "gn:timezone":"Asia/Kolkata",
    "iso:country":"IN",
    "ks:ks_name":"Banagere",
    "ks:ks_pop":384,
    "ks:ks_type":"VILLAGE",
    "name:eng_x_preferred":[
        "Banagere"
    ],
    "name:eng_x_variant":[
        "Banageri"
    ],
    "wof:name":"Banagere",
    "wof:placetype":"locality",
    "wof:population":384
},
  "geometry": {"coordinates":[75.74116100000001,12.698208],"type":"Point"}
}