{
  "type": "Feature",
  "properties": {
    "gn:admin1_code":"37",
    "gn:admin2_code":"408.0",
    "gn:asciiname":"Teka",
    "gn:country_code":"IN",
    "gn:dem":317,
    "gn:feature_class":"P",
    "gn:feature_code":"PPL",
    "gn:name":"Teka",
    "gn:population":0,
    "gn:timezone":"Asia/Kolkata",
    "iso:country":"IN",
    "name:ell_x_preferred":[
        "Teka"
    ],
    "name:eus_x_preferred":[
        "Teka"
    ],
    "name:fas_x_preferred":[
        "\u062a\u06a9\u0627"
    ],
    "name:fra_x_preferred":[
        "Teka"
    ],
    "name:ind_x_preferred":[
        "Teka"
    ],
    "name:por_x_preferred":[
        "Teka"
    ],
    "name:spa_x_preferred":[
        "Teka"
    ],
    "name:ukr_x_preferred":[
        "Teka"
    ],
    "name:zho_x_preferred":[
        "\u5fb7\u683c\u96c6\u5718"
    ],
    "wof:name":"Teka",
    "wof:placetype":"locality"
},
  "geometry": {"coordinates":[80.91615,21.14342000000001],"type":"Point"}
}