{
  "type": "Feature",
  "properties": {
    "iso:country":"IN",
    "ks:ks_name":"Padhansahi",
    "ks:ks_pop":3414,
    "ks:ks_type":"VILLAGE",
    "ks:ks_uagg_main":0,
    "name:eng_x_preferred":[
        "Padhansahi"
    ],
    "wof:name":"Padhansahi",
    "wof:placetype":"neighbourhood",
    "wof:population":3414
},
  "geometry": {"coordinates":[86.10249399999999,20.079208],"type":"Point"}
}