{
  "type": "Feature",
  "properties": {
    "gn:admin1_code":"25.0",
    "gn:admin2_code":"607.0",
    "gn:asciiname":"Kaipanikuppam",
    "gn:country_code":"IN",
    "gn:dem":9,
    "gn:feature_class":"P",
    "gn:feature_code":"PPL",
    "gn:name":"Kaipanikuppam",
    "gn:population":0,
    "gn:timezone":"Asia/Kolkata",
    "iso:country":"IN",
    "wof:name":"Kaipanikuppam",
    "wof:placetype":"locality"
},
  "geometry": {"coordinates":[79.98235,12.21644],"type":"Point"}
}