{
  "type": "Feature",
  "properties": {
    "iso:country":"IN",
    "ks:ks_name":"Jhanjhar",
    "ks:ks_pop":0,
    "ks:ks_type":"VILLAGE",
    "name:eng_x_preferred":[
        "Jhanjhar"
    ],
    "wof:name":"Jhanjhar",
    "wof:placetype":"locality",
    "wof:population":0
},
  "geometry": {"coordinates":[86.086662,26.001732],"type":"Point"}
}