{
  "type": "Feature",
  "properties": {
    "iso:country":"IN",
    "ks:ks_name":"Honnemalahadi",
    "ks:ks_pop":73,
    "ks:ks_type":"HABITATION",
    "name:eng_x_preferred":[
        "Honnemalahadi"
    ],
    "wof:name":"Honnemalahadi",
    "wof:placetype":"locality",
    "wof:population":73
},
  "geometry": {"coordinates":[76.21629,11.950377],"type":"Point"}
}