{
  "type": "Feature",
  "properties": {
    "iso:country":"IN",
    "ks:ks_name":"Bahaliyan Nagla",
    "ks:ks_pop":477,
    "ks:ks_type":"HABITATION",
    "name:eng_x_preferred":[
        "Bahaliyan Nagla"
    ],
    "wof:name":"Bahaliyan Nagla",
    "wof:placetype":"locality",
    "wof:population":477
},
  "geometry": {"coordinates":[79.39191599999999,27.277364],"type":"Point"}
}