{
  "type": "Feature",
  "properties": {
    "iso:country":"IN",
    "ks:ks_name":"Pandritarai",
    "ks:ks_pop":552,
    "ks:ks_type":"VILLAGE",
    "name:eng_x_preferred":[
        "Pandritarai"
    ],
    "wof:name":"Pandritarai",
    "wof:placetype":"locality",
    "wof:population":552
},
  "geometry": {"coordinates":[81.962441,20.823625],"type":"Point"}
}