{
  "type": "Feature",
  "properties": {
    "iso:country":"IN",
    "ks:ks_name":"Gangaprasad",
    "ks:ks_pop":1309,
    "ks:ks_type":"VILLAGE",
    "ks:ks_uagg_main":0,
    "name:eng_x_preferred":[
        "Gangaprasad"
    ],
    "wof:name":"Gangaprasad",
    "wof:placetype":"neighbourhood",
    "wof:population":1309
},
  "geometry": {"coordinates":[87.90944500000001,25.101921],"type":"Point"}
}