{
  "type": "Feature",
  "properties": {
    "iso:country":"IN",
    "ks:ks_name":"Bahadkho Khurd",
    "ks:ks_pop":959,
    "ks:ks_type":"VILLAGE",
    "name:eng_x_preferred":[
        "Bahadkho Khurd"
    ],
    "wof:name":"Bahadkho Khurd",
    "wof:placetype":"locality",
    "wof:population":959
},
  "geometry": {"coordinates":[76.783117,27.2284],"type":"Point"}
}