{
  "type": "Feature",
  "properties": {
    "iso:country":"IN",
    "ks:ks_name":"Chikhal Guda Para",
    "ks:ks_pop":184,
    "ks:ks_type":"HABITATION",
    "name:eng_x_preferred":[
        "Chikhal Guda Para"
    ],
    "wof:name":"Chikhal Guda Para",
    "wof:placetype":"locality",
    "wof:population":184
},
  "geometry": {"coordinates":[82.014483,19.374266],"type":"Point"}
}