{
  "type": "Feature",
  "properties": {
    "iso:country":"IN",
    "ks:ks_name":"Machipada",
    "ks:ks_pop":157,
    "ks:ks_type":"HABITATION",
    "name:eng_x_preferred":[
        "Machipada"
    ],
    "wof:name":"Machipada",
    "wof:placetype":"locality",
    "wof:population":157
},
  "geometry": {"coordinates":[72.80604200000001,19.861297],"type":"Point"}
}