{
  "type": "Feature",
  "properties": {
    "gn:admin1_code":"36",
    "gn:admin2_code":"146.0",
    "gn:asciiname":"Tulsigarhi",
    "gn:country_code":"IN",
    "gn:dem":169,
    "gn:feature_class":"P",
    "gn:feature_code":"PPL",
    "gn:name":"Tuls\u012bgarhi",
    "gn:population":0,
    "gn:timezone":"Asia/Kolkata",
    "iso:country":"IN",
    "wof:name":"Tulsigarhi",
    "wof:placetype":"locality"
},
  "geometry": {"coordinates":[77.73296999999999,26.96353],"type":"Point"}
}