{
  "type": "Feature",
  "properties": {
    "iso:country":"IN",
    "ks:ks_name":"Imdakunda",
    "ks:ks_pop":180,
    "ks:ks_type":"HABITATION",
    "name:eng_x_preferred":[
        "Imdakunda"
    ],
    "wof:name":"Imdakunda",
    "wof:placetype":"locality",
    "wof:population":180
},
  "geometry": {"coordinates":[74.714108,13.564906],"type":"Point"}
}