{
  "type": "Feature",
  "properties": {
    "iso:country":"IN",
    "ks:ks_alt_nam":"Kam\u0101lpur",
    "ks:ks_name":"Kamalpur",
    "ks:ks_pop":623,
    "ks:ks_type":"VILLAGE",
    "ks:ks_uagg_main":0,
    "name:eng_x_preferred":[
        "Kamalpur"
    ],
    "name:eng_x_variant":[
        "Kam\u0101lpur"
    ],
    "wof:name":"Kamalpur",
    "wof:placetype":"neighbourhood",
    "wof:population":623
},
  "geometry": {"coordinates":[76.696292,27.527889],"type":"Point"}
}