{
  "type": "Feature",
  "properties": {
    "gn:admin1_code":"36",
    "gn:admin2_code":"165.0",
    "gn:asciiname":"Bamhaura",
    "gn:country_code":"IN",
    "gn:dem":129,
    "gn:feature_class":"P",
    "gn:feature_code":"PPL",
    "gn:name":"Bamhaura",
    "gn:population":0,
    "gn:timezone":"Asia/Kolkata",
    "iso:country":"IN",
    "wof:name":"Bamhaura",
    "wof:placetype":"locality"
},
  "geometry": {"coordinates":[79.54301,26.18795],"type":"Point"}
}