{
  "type": "Feature",
  "properties": {
    "gn:admin1_code":"36.0",
    "gn:admin2_code":"140.0",
    "gn:asciiname":"Nurpur ki Marhaivan",
    "gn:country_code":"IN",
    "gn:dem":214,
    "gn:feature_class":"P",
    "gn:feature_code":"PPL",
    "gn:name":"N\u016brpur ki Marhaiv\u0101n",
    "gn:population":0,
    "gn:timezone":"Asia/Kolkata",
    "iso:country":"IN",
    "wof:name":"Nurpur ki Marhaivan",
    "wof:placetype":"neighbourhood"
},
  "geometry": {"coordinates":[77.8694,28.66509],"type":"Point"}
}