{
  "type": "Feature",
  "properties": {
    "iso:country":"IN",
    "ks:ks_alt_nam":"Mahibull\u0101h Chak",
    "ks:ks_name":"Mahibullah Chak",
    "ks:ks_type":"VILLAGE",
    "ks:ks_uagg_main":0,
    "name:eng_x_preferred":[
        "Mahibullah Chak"
    ],
    "name:eng_x_variant":[
        "Mahibull\u0101h Chak"
    ],
    "wof:name":"Mahibullah Chak",
    "wof:placetype":"neighbourhood"
},
  "geometry": {"coordinates":[83.64360600000001,25.46321],"type":"Point"}
}