{
  "type": "Feature",
  "properties": {
    "gn:admin1_code":"35.0",
    "gn:admin2_code":"450.0",
    "gn:asciiname":"Salaiya",
    "gn:country_code":"IN",
    "gn:dem":462,
    "gn:feature_class":"P",
    "gn:feature_code":"PPL",
    "gn:name":"Salaiya",
    "gn:population":0,
    "gn:timezone":"Asia/Kolkata",
    "iso:country":"IN",
    "wof:name":"Salaiya",
    "wof:placetype":"neighbourhood"
},
  "geometry": {"coordinates":[80.02252,23.74215],"type":"Point"}
}