{
  "type": "Feature",
  "properties": {
    "iso:country":"IN",
    "ks:ks_name":"Durgani",
    "ks:ks_pop":308,
    "ks:ks_type":"HABITATION",
    "name:eng_x_preferred":[
        "Durgani"
    ],
    "wof:name":"Durgani",
    "wof:placetype":"locality",
    "wof:population":308
},
  "geometry": {"coordinates":[72.005605,27.252395],"type":"Point"}
}