{
  "type": "Feature",
  "properties": {
    "gn:admin1_code":"24.0",
    "gn:admin2_code":"127.0",
    "gn:asciiname":"Dabri",
    "gn:country_code":"IN",
    "gn:dem":267,
    "gn:feature_class":"P",
    "gn:feature_code":"PPL",
    "gn:name":"D\u0101bri",
    "gn:population":0,
    "gn:timezone":"Asia/Kolkata",
    "iso:country":"IN",
    "name:ara_x_preferred":[
        "\u062f\u0627\u0628\u0631\u064a"
    ],
    "name:ben_bn_x_preferred":[
        "\u09a1\u09be\u09ac\u09b0\u09bf"
    ],
    "name:ben_in_x_preferred":[
        "\u09a1\u09be\u09ac\u09b0\u09bf"
    ],
    "name:guj_x_preferred":[
        "\u0aa1\u0abe\u0aac\u0ab0\u0ac0"
    ],
    "name:hin_x_preferred":[
        "\u0921\u092c\u0930\u0940"
    ],
    "name:kan_x_preferred":[
        "\u0ca6\u0cac\u0ccd\u0cb0\u0cbf"
    ],
    "name:mal_x_preferred":[
        "\u0d21\u0d3e\u0d2c\u0d4d\u0d30\u0d3f"
    ],
    "name:mar_x_preferred":[
        "\u0921\u093e\u092c\u0930\u0940"
    ],
    "name:pan_x_preferred":[
        "\u0a21\u0a3e\u0a2c\u0a30\u0a40"
    ],
    "name:tam_x_preferred":[
        "\u0b9f\u0baa\u0bcd\u0bb0\u0bbf"
    ],
    "name:tel_x_preferred":[
        "\u0c21\u0c2c\u0c4d\u0c30\u0c3f"
    ],
    "name:urd_x_preferred":[
        "\u0688\u0627\u0628\u0631\u06cc"
    ],
    "name:urd_x_variant":[
        "\u062f\u0627\u0628\u0691\u06cc"
    ],
    "wof:name":"Dabri",
    "wof:placetype":"locality"
},
  "geometry": {"coordinates":[76.23987,24.93837000000001],"type":"Point"}
}