{
  "type": "Feature",
  "properties": {
    "iso:country":"IN",
    "ks:ks_name":"Pallathadka",
    "ks:ks_pop":250,
    "ks:ks_type":"HABITATION",
    "name:eng_x_preferred":[
        "Pallathadka"
    ],
    "wof:name":"Pallathadka",
    "wof:placetype":"locality",
    "wof:population":250
},
  "geometry": {"coordinates":[75.39993,12.669241],"type":"Point"}
}