{
  "type": "Feature",
  "properties": {
    "gn:admin1_code":"34",
    "gn:admin2_code":"234.0",
    "gn:asciiname":"Ram Dihri",
    "gn:country_code":"IN",
    "gn:dem":95,
    "gn:feature_class":"P",
    "gn:feature_code":"PPL",
    "gn:name":"R\u0101m D\u012bhri",
    "gn:population":0,
    "gn:timezone":"Asia/Kolkata",
    "iso:country":"IN",
    "ks:ks_name":"Ramdehri",
    "ks:ks_pop":179,
    "ks:ks_type":"VILLAGE",
    "name:eng_x_preferred":[
        "Ramdehri"
    ],
    "name:eng_x_variant":[
        "Ram Dihri"
    ],
    "wof:name":"Ramdehri",
    "wof:placetype":"locality",
    "wof:population":179
},
  "geometry": {"coordinates":[83.857462,25.011845],"type":"Point"}
}