{
  "type": "Feature",
  "properties": {
    "iso:country":"IN",
    "ks:ks_name":"Gohmi",
    "ks:ks_pop":313,
    "ks:ks_type":"HABITATION",
    "ks:ks_uagg_main":0,
    "name:eng_x_preferred":[
        "Gohmi"
    ],
    "wof:name":"Gohmi",
    "wof:placetype":"neighbourhood",
    "wof:population":313
},
  "geometry": {"coordinates":[87.061272,22.524999],"type":"Point"}
}