{
  "type": "Feature",
  "properties": {
    "iso:country":"IN",
    "ks:ks_name":"11 ZWD",
    "ks:ks_pop":834,
    "ks:ks_type":"VILLAGE",
    "ks:ks_uagg_main":0,
    "name:eng_x_preferred":[
        "11 ZWD"
    ],
    "wof:name":"11 ZWD",
    "wof:placetype":"neighbourhood",
    "wof:population":834
},
  "geometry": {"coordinates":[74.20547500000001,29.34875],"type":"Point"}
}