{
  "type": "Feature",
  "properties": {
    "gn:admin1_code":"12",
    "gn:admin2_code":"15.0",
    "gn:asciiname":"Ponyu",
    "gn:country_code":"IN",
    "gn:dem":1698,
    "gn:feature_class":"P",
    "gn:feature_code":"PPL",
    "gn:name":"Ponyu",
    "gn:population":0,
    "gn:timezone":"Asia/Kolkata",
    "iso:country":"IN",
    "wof:name":"Ponyu",
    "wof:placetype":"locality"
},
  "geometry": {"coordinates":[75.02534,33.67856],"type":"Point"}
}