{
  "type": "Feature",
  "properties": {
    "gn:admin1_code":"36.0",
    "gn:admin2_code":"192.0",
    "gn:asciiname":"Daraunda Madhupur",
    "gn:country_code":"IN",
    "gn:dem":78,
    "gn:feature_class":"P",
    "gn:feature_code":"PPL",
    "gn:name":"Daraunda M\u0101dhupur",
    "gn:population":0,
    "gn:timezone":"Asia/Kolkata",
    "iso:country":"IN",
    "wof:name":"Daraunda Madhupur",
    "wof:placetype":"locality"
},
  "geometry": {"coordinates":[83.62153000000001,26.12468],"type":"Point"}
}