{
  "type": "Feature",
  "properties": {
    "gn:admin1_code":"19.0",
    "gn:admin2_code":"563.0",
    "gn:asciiname":"Mundguli",
    "gn:country_code":"IN",
    "gn:dem":91,
    "gn:feature_class":"P",
    "gn:feature_code":"PPL",
    "gn:name":"Mundguli",
    "gn:population":0,
    "gn:timezone":"Asia/Kolkata",
    "iso:country":"IN",
    "wof:name":"Mundguli",
    "wof:placetype":"locality"
},
  "geometry": {"coordinates":[74.58556,14.82748],"type":"Point"}
}