{
  "type": "Feature",
  "properties": {
    "iso:country":"IN",
    "ks:ks_alt_nam":"ADIVASI TOLA",
    "ks:ks_name":"Adivasi Tola",
    "ks:ks_pop":81,
    "ks:ks_type":"HABITATION",
    "name:eng_x_preferred":[
        "Adivasi Tola"
    ],
    "wof:name":"Adivasi Tola",
    "wof:placetype":"locality",
    "wof:population":81
},
  "geometry": {"coordinates":[83.720116,24.761678],"type":"Point"}
}