{
  "type": "Feature",
  "properties": {
    "gn:admin1_code":"11",
    "gn:admin2_code":"27.0",
    "gn:asciiname":"Kurara",
    "gn:country_code":"IN",
    "gn:dem":783,
    "gn:feature_class":"P",
    "gn:feature_code":"PPL",
    "gn:name":"Kur\u0101ra",
    "gn:population":0,
    "gn:timezone":"Asia/Kolkata",
    "iso:country":"IN",
    "name:ceb_x_preferred":[
        "Kur\u0101ra"
    ],
    "name:ita_x_preferred":[
        "Kurara"
    ],
    "name:mlg_x_preferred":[
        "Kurara"
    ],
    "name:msa_x_preferred":[
        "Kurara"
    ],
    "name:new_x_preferred":[
        "\u0915\u0941\u0930\u093e\u0930\u093e"
    ],
    "name:nld_x_preferred":[
        "Kurara"
    ],
    "name:pol_x_preferred":[
        "Kurara"
    ],
    "name:swe_x_preferred":[
        "Kur\u0101ra"
    ],
    "name:urd_x_preferred":[
        "\u06a9\u0648\u0631\u0627\u0631\u0627"
    ],
    "name:vie_x_preferred":[
        "Kurara"
    ],
    "name:zho_x_preferred":[
        "\u5e93\u62c9\u62c9"
    ],
    "wof:name":"Kurara",
    "wof:placetype":"locality"
},
  "geometry": {"coordinates":[76.87006,31.48796],"type":"Point"}
}