{
  "type": "Feature",
  "properties": {
    "iso:country":"IN",
    "ks:ks_name":"Sagbehri",
    "ks:ks_pop":222,
    "ks:ks_type":"VILLAGE",
    "name:eng_x_preferred":[
        "Sagbehri"
    ],
    "wof:name":"Sagbehri",
    "wof:placetype":"locality",
    "wof:population":222
},
  "geometry": {"coordinates":[86.476744,23.98059],"type":"Point"}
}