{
  "type": "Feature",
  "properties": {
    "gn:admin1_code":"35",
    "gn:admin2_code":"443.0",
    "gn:asciiname":"Sinduriya",
    "gn:country_code":"IN",
    "gn:dem":454,
    "gn:feature_class":"P",
    "gn:feature_code":"PPL",
    "gn:name":"Sind\u016briya",
    "gn:population":0,
    "gn:timezone":"Asia/Kolkata",
    "iso:country":"IN",
    "name:hif_x_preferred":[
        "Sinduriya"
    ],
    "wof:name":"Sinduriya",
    "wof:placetype":"locality"
},
  "geometry": {"coordinates":[78.22851999999997,23.67683],"type":"Point"}
}