{
  "type": "Feature",
  "properties": {
    "iso:country":"IN",
    "ks:ks_name":"Kasmir Chak",
    "ks:ks_pop":0,
    "ks:ks_type":"VILLAGE",
    "name:eng_x_preferred":[
        "Kasmir Chak"
    ],
    "wof:name":"Kasmir Chak",
    "wof:placetype":"locality",
    "wof:population":0
},
  "geometry": {"coordinates":[87.36283400000001,25.136526],"type":"Point"}
}