{
  "type": "Feature",
  "properties": {
    "iso:country":"IN",
    "ks:ks_name":"N. Kewal",
    "ks:ks_pop":366,
    "ks:ks_type":"HABITATION",
    "ks:ks_uagg_main":0,
    "name:eng_x_preferred":[
        "N. Kewal"
    ],
    "wof:name":"N. Kewal",
    "wof:placetype":"neighbourhood",
    "wof:population":366
},
  "geometry": {"coordinates":[78.565355,27.443246],"type":"Point"}
}