{
  "type": "Feature",
  "properties": {
    "iso:country":"IN",
    "ks:ks_name":"Upper Dalapchand",
    "ks:ks_pop":1500,
    "ks:ks_type":"HABITATION",
    "name:eng_x_preferred":[
        "Upper Dalapchand"
    ],
    "wof:name":"Upper Dalapchand",
    "wof:placetype":"locality",
    "wof:population":1500
},
  "geometry": {"coordinates":[88.53524400000001,27.093571],"type":"Point"}
}