{
  "type": "Feature",
  "properties": {
    "gn:admin1_code":"34.0",
    "gn:admin2_code":"226.0",
    "gn:asciiname":"Mahespur",
    "gn:country_code":"IN",
    "gn:dem":53,
    "gn:feature_class":"P",
    "gn:feature_code":"PPL",
    "gn:name":"Mahespur",
    "gn:population":0,
    "gn:timezone":"Asia/Kolkata",
    "iso:country":"IN",
    "ks:ks_name":"Maheshpur",
    "ks:ks_pop":623,
    "ks:ks_type":"VILLAGE",
    "name:eng_x_preferred":[
        "Maheshpur"
    ],
    "name:eng_x_variant":[
        "Mahespur"
    ],
    "wof:name":"Maheshpur",
    "wof:placetype":"locality",
    "wof:population":623
},
  "geometry": {"coordinates":[86.628596,25.11087],"type":"Point"}
}