{
  "type": "Feature",
  "properties": {
    "gn:admin1_code":"34.0",
    "gn:admin2_code":"226.0",
    "gn:asciiname":"Mahespur",
    "gn:country_code":"IN",
    "gn:dem":53,
    "gn:feature_class":"P",
    "gn:feature_code":"PPL",
    "gn:name":"Mahespur",
    "gn:population":0,
    "gn:timezone":"Asia/Kolkata",
    "iso:country":"IN",
    "wof:name":"Mahespur",
    "wof:placetype":"locality"
},
  "geometry": {"coordinates":[86.63036,25.10918],"type":"Point"}
}