{
  "type": "Feature",
  "properties": {
    "gn:admin1_code":"11",
    "gn:admin2_code":"23.0",
    "gn:asciiname":"Bhararon",
    "gn:country_code":"IN",
    "gn:dem":1904,
    "gn:feature_class":"P",
    "gn:feature_code":"PPL",
    "gn:name":"Bhar\u0101ron",
    "gn:population":0,
    "gn:timezone":"Asia/Kolkata",
    "iso:country":"IN",
    "wof:name":"Bhararon",
    "wof:placetype":"locality"
},
  "geometry": {"coordinates":[76.09069000000002,32.83946],"type":"Point"}
}