{
  "type": "Feature",
  "properties": {
    "iso:country":"IN",
    "ks:ks_name":"Bhutonde",
    "ks:ks_pop":326,
    "ks:ks_type":"VILLAGE",
    "name:eng_x_preferred":[
        "Bhutonde"
    ],
    "wof:name":"Bhutonde",
    "wof:placetype":"locality",
    "wof:population":326
},
  "geometry": {"coordinates":[73.65106299999999,18.213721],"type":"Point"}
}