{
  "type": "Feature",
  "properties": {
    "gn:admin1_code":"03",
    "gn:admin2_code":"305.0",
    "gn:asciiname":"Phulaguri",
    "gn:country_code":"IN",
    "gn:dem":66,
    "gn:feature_class":"P",
    "gn:feature_code":"PPL",
    "gn:name":"Phulaguri",
    "gn:population":0,
    "gn:timezone":"Asia/Kolkata",
    "iso:country":"IN",
    "ks:ks_name":"Phulaguri",
    "ks:ks_pop":1535,
    "ks:ks_type":"VILLAGE",
    "name:eng_x_preferred":[
        "Phulaguri"
    ],
    "wof:name":"Phulaguri",
    "wof:placetype":"locality",
    "wof:population":1535
},
  "geometry": {"coordinates":[92.58150000000001,26.262874],"type":"Point"}
}