{
  "type": "Feature",
  "properties": {
    "iso:country":"IN",
    "ks:ks_name":"Bhurunga Mari",
    "ks:ks_type":"VILLAGE",
    "ks:ks_uagg_main":0,
    "name:eng_x_preferred":[
        "Bhurunga Mari"
    ],
    "wof:name":"Bhurunga Mari",
    "wof:placetype":"neighbourhood"
},
  "geometry": {"coordinates":[89.251332,26.294],"type":"Point"}
}