{
  "type": "Feature",
  "properties": {
    "iso:country":"IN",
    "ks:ks_name":"Ray Band",
    "ks:ks_pop":654,
    "ks:ks_type":"VILLAGE",
    "name:eng_x_preferred":[
        "Ray Band"
    ],
    "wof:name":"Ray Band",
    "wof:placetype":"locality",
    "wof:population":654
},
  "geometry": {"coordinates":[87.038758,23.309419],"type":"Point"}
}