{
  "type": "Feature",
  "properties": {
    "gn:admin1_code":"11.0",
    "gn:admin2_code":"27.0",
    "gn:asciiname":"Kajut",
    "gn:country_code":"IN",
    "gn:dem":2253,
    "gn:feature_class":"P",
    "gn:feature_code":"PPL",
    "gn:name":"Kaj\u016bt",
    "gn:population":0,
    "gn:timezone":"Asia/Kolkata",
    "iso:country":"IN",
    "name:azb_x_preferred":[
        "\u06a9\u062c\u0648\u062a"
    ],
    "name:aze_x_preferred":[
        "Kacut"
    ],
    "name:fas_x_preferred":[
        "\u06a9\u062c\u0648\u062a"
    ],
    "name:msa_x_preferred":[
        "Kajut"
    ],
    "wof:name":"Kajut",
    "wof:placetype":"locality"
},
  "geometry": {"coordinates":[77.18565,31.54495],"type":"Point"}
}