{
  "type": "Feature",
  "properties": {
    "gn:admin1_code":"39.0",
    "gn:admin2_code":"068",
    "gn:asciiname":"Alawalpur",
    "gn:country_code":"IN",
    "gn:dem":295,
    "gn:feature_class":"P",
    "gn:feature_code":"PPL",
    "gn:name":"Al\u0101walpur",
    "gn:population":0,
    "gn:timezone":"Asia/Kolkata",
    "iso:country":"IN",
    "name:ben_x_preferred":[
        "\u0986\u09b2\u09be\u09f1\u09b2\u09aa\u09c1\u09b0"
    ],
    "name:bpy_x_preferred":[
        "\u0986\u09b2\u09be\u09f1\u09b2\u09aa\u09c1\u09b0"
    ],
    "name:ceb_x_preferred":[
        "Al\u0101walpur"
    ],
    "name:fas_x_preferred":[
        "\u0627\u0627\u0644\u0627\u0648\u0627\u0644\u200c\u067e\u0648\u0631"
    ],
    "name:ita_x_preferred":[
        "Alawalpur"
    ],
    "name:min_x_preferred":[
        "Alawalpur"
    ],
    "name:mlg_x_preferred":[
        "Alawalpur"
    ],
    "name:msa_x_preferred":[
        "Alawalpur"
    ],
    "name:new_x_preferred":[
        "\u0905\u0932\u0935\u0932\u092a\u0941\u0930"
    ],
    "name:nld_x_preferred":[
        "Alawalpur"
    ],
    "name:por_x_preferred":[
        "Alawalpur"
    ],
    "name:swe_x_preferred":[
        "Al\u0101walpur"
    ],
    "name:vie_x_preferred":[
        "Alawalpur"
    ],
    "name:zho_x_preferred":[
        "\u963f\u62c9\u74e6\u5c14\u666e\u5c14"
    ],
    "wof:name":"Alawalpur",
    "wof:placetype":"locality"
},
  "geometry": {"coordinates":[77.77772,30.0421],"type":"Point"}
}