{
  "type": "Feature",
  "properties": {
    "iso:country":"IN",
    "ks:ks_name":"Chhayan",
    "ks:ks_pop":0,
    "ks:ks_type":"VILLAGE",
    "name:eng_x_preferred":[
        "Chhayan"
    ],
    "wof:name":"Chhayan",
    "wof:placetype":"locality",
    "wof:population":0
},
  "geometry": {"coordinates":[78.837889,24.441413],"type":"Point"}
}