{
  "type": "Feature",
  "properties": {
    "gn:admin1_code":"35",
    "gn:admin2_code":"420.0",
    "gn:asciiname":"Rajpura",
    "gn:country_code":"IN",
    "gn:dem":158,
    "gn:feature_class":"P",
    "gn:feature_code":"PPL",
    "gn:name":"R\u0101jpura",
    "gn:population":0,
    "gn:timezone":"Asia/Kolkata",
    "iso:country":"IN",
    "wof:name":"Rajpura",
    "wof:placetype":"locality"
},
  "geometry": {"coordinates":[78.64784,26.58218],"type":"Point"}
}