{
  "type": "Feature",
  "properties": {
    "iso:country":"IN",
    "ks:ks_name":"Teli Tola",
    "ks:ks_pop":665,
    "ks:ks_type":"HABITATION",
    "name:eng_x_preferred":[
        "Teli Tola"
    ],
    "wof:name":"Teli Tola",
    "wof:placetype":"locality",
    "wof:population":665
},
  "geometry": {"coordinates":[86.91023300000001,25.253809],"type":"Point"}
}