{
  "type": "Feature",
  "properties": {
    "iso:country":"IN",
    "ks:ks_name":"Nabagram Colony",
    "ks:ks_pop":31924,
    "ks:ks_type":"VILLAGE",
    "ks:ks_uagg_main":0,
    "name:eng_x_preferred":[
        "Nabagram Colony"
    ],
    "wof:name":"Nabagram Colony",
    "wof:placetype":"locality",
    "wof:population":31924
},
  "geometry": {"coordinates":[88.33898499999999,22.700986],"type":"Point"}
}