{
  "type": "Feature",
  "properties": {
    "gn:admin1_code":"35",
    "gn:admin2_code":"427.0",
    "gn:asciiname":"Baheria",
    "gn:country_code":"IN",
    "gn:dem":518,
    "gn:feature_class":"P",
    "gn:feature_code":"PPL",
    "gn:name":"Baheria",
    "gn:population":0,
    "gn:timezone":"Asia/Kolkata",
    "iso:country":"IN",
    "ks:ks_name":"Baheriya",
    "ks:ks_pop":0,
    "ks:ks_type":"VILLAGE",
    "name:eng_x_preferred":[
        "Baheriya"
    ],
    "name:eng_x_variant":[
        "Baheria"
    ],
    "wof:name":"Baheriya",
    "wof:placetype":"locality",
    "wof:population":0
},
  "geometry": {"coordinates":[78.772206,23.985551],"type":"Point"}
}