{
  "type": "Feature",
  "properties": {
    "gn:admin1_code":"24",
    "gn:admin2_code":"108.0",
    "gn:asciiname":"Pilauda",
    "gn:country_code":"IN",
    "gn:dem":256,
    "gn:feature_class":"P",
    "gn:feature_code":"PPL",
    "gn:name":"Pilauda",
    "gn:population":0,
    "gn:timezone":"Asia/Kolkata",
    "iso:country":"IN",
    "wof:name":"Pilauda",
    "wof:placetype":"locality"
},
  "geometry": {"coordinates":[76.83725,26.59543],"type":"Point"}
}