{
  "type": "Feature",
  "properties": {
    "iso:country":"IN",
    "ks:ks_name":"Kkili",
    "ks:ks_pop":48,
    "ks:ks_type":"HABITATION",
    "name:eng_x_preferred":[
        "Kkili"
    ],
    "wof:name":"Kkili",
    "wof:placetype":"locality",
    "wof:population":48
},
  "geometry": {"coordinates":[85.471468,22.821028],"type":"Point"}
}