{
  "type": "Feature",
  "properties": {
    "gn:admin1_code":"25.0",
    "gn:admin2_code":"620.0",
    "gn:asciiname":"Ullur",
    "gn:country_code":"IN",
    "gn:dem":25,
    "gn:feature_class":"P",
    "gn:feature_code":"PPL",
    "gn:name":"Ull\u016br",
    "gn:population":0,
    "gn:timezone":"Asia/Kolkata",
    "iso:country":"IN",
    "name:bpy_x_preferred":[
        "\u0989\u09b2\u09cd\u09b2\u09c1\u09b0"
    ],
    "name:ita_x_preferred":[
        "Ullur"
    ],
    "name:mlg_x_preferred":[
        "Ullur"
    ],
    "name:msa_x_preferred":[
        "Ullur"
    ],
    "name:nld_x_preferred":[
        "Ullur"
    ],
    "name:por_x_preferred":[
        "Ullur"
    ],
    "name:tam_x_preferred":[
        "\u0b89\u0bb3\u0bcd\u0bb3\u0bc2\u0bb0\u0bcd"
    ],
    "name:vie_x_preferred":[
        "Ullur"
    ],
    "name:zho_x_preferred":[
        "\u4e4c\u5362\u5c14"
    ],
    "wof:name":"Ullur",
    "wof:placetype":"locality"
},
  "geometry": {"coordinates":[79.40631999999999,10.97057],"type":"Point"}
}