{
  "type": "Feature",
  "properties": {
    "iso:country":"IN",
    "ks:ks_name":"Mundaguda",
    "ks:ks_pop":125,
    "ks:ks_type":"VILLAGE",
    "name:eng_x_preferred":[
        "Mundaguda"
    ],
    "wof:name":"Mundaguda",
    "wof:placetype":"locality",
    "wof:population":125
},
  "geometry": {"coordinates":[82.27829,19.020978],"type":"Point"}
}