{
  "type": "Feature",
  "properties": {
    "iso:country":"IN",
    "ks:ks_name":"Bandakada Palle",
    "ks:ks_pop":146,
    "ks:ks_type":"HABITATION",
    "name:eng_x_preferred":[
        "Bandakada Palle"
    ],
    "wof:name":"Bandakada Palle",
    "wof:placetype":"locality",
    "wof:population":146
},
  "geometry": {"coordinates":[78.511945,13.872013],"type":"Point"}
}