{
  "type": "Feature",
  "properties": {
    "gn:admin1_code":"35",
    "gn:admin2_code":"461.0",
    "gn:asciiname":"Karondatola",
    "gn:country_code":"IN",
    "gn:dem":774,
    "gn:feature_class":"P",
    "gn:feature_code":"PPL",
    "gn:name":"Karond\u0101tola",
    "gn:population":0,
    "gn:timezone":"Asia/Kolkata",
    "iso:country":"IN",
    "wof:name":"Karondatola",
    "wof:placetype":"locality"
},
  "geometry": {"coordinates":[81.57828000000001,22.76833],"type":"Point"}
}