{
  "type": "Feature",
  "properties": {
    "iso:country":"IN",
    "ks:ks_name":"Gahar",
    "ks:ks_pop":51,
    "ks:ks_type":"VILLAGE",
    "name:eng_x_preferred":[
        "Gahar"
    ],
    "wof:name":"Gahar",
    "wof:placetype":"locality",
    "wof:population":51
},
  "geometry": {"coordinates":[79.62500900000001,30.501148],"type":"Point"}
}