{
  "type": "Feature",
  "properties": {
    "iso:country":"IN",
    "ks:ks_name":"Adiandrawada",
    "ks:ks_pop":323,
    "ks:ks_type":"HABITATION",
    "name:eng_x_preferred":[
        "Adiandrawada"
    ],
    "wof:name":"Adiandrawada",
    "wof:placetype":"locality",
    "wof:population":323
},
  "geometry": {"coordinates":[79.752752,13.747778],"type":"Point"}
}