{
  "type": "Feature",
  "properties": {
    "iso:country":"IN",
    "ks:ks_name":"Barpali",
    "ks:ks_pop":255,
    "ks:ks_type":"VILLAGE",
    "name:eng_x_preferred":[
        "Barpali"
    ],
    "wof:name":"Barpali",
    "wof:placetype":"locality",
    "wof:population":255
},
  "geometry": {"coordinates":[83.41336,22.481156],"type":"Point"}
}