{
  "type": "Feature",
  "properties": {
    "iso:country":"IN",
    "ks:ks_name":"Hemmakki",
    "ks:ks_pop":325,
    "ks:ks_type":"HABITATION",
    "name:eng_x_preferred":[
        "Hemmakki"
    ],
    "wof:name":"Hemmakki",
    "wof:placetype":"locality",
    "wof:population":325
},
  "geometry": {"coordinates":[74.439812,14.343722],"type":"Point"}
}