{
  "type": "Feature",
  "properties": {
    "iso:country":"IN",
    "ks:ks_alt_nam":"Bhawar pada",
    "ks:ks_name":"Bhawar Pada",
    "ks:ks_pop":129,
    "ks:ks_type":"HABITATION",
    "name:eng_x_preferred":[
        "Bhawar Pada"
    ],
    "wof:name":"Bhawar Pada",
    "wof:placetype":"locality",
    "wof:population":129
},
  "geometry": {"coordinates":[73.003666,19.791774],"type":"Point"}
}