{
  "type": "Feature",
  "properties": {
    "gn:admin1_code":"11.0",
    "gn:admin2_code":"026",
    "gn:asciiname":"Dhara",
    "gn:country_code":"IN",
    "gn:dem":1319,
    "gn:feature_class":"P",
    "gn:feature_code":"PPL",
    "gn:name":"Dh\u0101ra",
    "gn:population":0,
    "gn:timezone":"Asia/Kolkata",
    "iso:country":"IN",
    "wof:name":"Dhara",
    "wof:placetype":"locality"
},
  "geometry": {"coordinates":[77.24500999999999,31.84088],"type":"Point"}
}