{
  "type": "Feature",
  "properties": {
    "iso:country":"IN",
    "ks:ks_name":"Dakhin Bakrikuchi",
    "ks:ks_pop":569,
    "ks:ks_type":"HABITATION",
    "name:eng_x_preferred":[
        "Dakhin Bakrikuchi"
    ],
    "wof:name":"Dakhin Bakrikuchi",
    "wof:placetype":"locality",
    "wof:population":569
},
  "geometry": {"coordinates":[91.33691,26.321924],"type":"Point"}
}