{
  "type": "Feature",
  "properties": {
    "gn:admin1_code":"34.0",
    "gn:admin2_code":"218.0",
    "gn:asciiname":"Siuri",
    "gn:country_code":"IN",
    "gn:dem":67,
    "gn:feature_class":"P",
    "gn:feature_code":"PPL",
    "gn:name":"Siuri",
    "gn:population":0,
    "gn:timezone":"Asia/Kolkata",
    "iso:country":"IN",
    "name:ceb_x_preferred":[
        "Siuri"
    ],
    "name:swe_x_preferred":[
        "Siuri"
    ],
    "wof:name":"Siuri",
    "wof:placetype":"locality"
},
  "geometry": {"coordinates":[84.21869000000002,26.06551],"type":"Point"}
}