{
  "type": "Feature",
  "properties": {
    "iso:country":"IN",
    "ks:ks_name":"Savarapeta",
    "ks:ks_pop":69,
    "ks:ks_type":"HABITATION",
    "name:eng_x_preferred":[
        "Savarapeta"
    ],
    "wof:name":"Savarapeta",
    "wof:placetype":"locality",
    "wof:population":69
},
  "geometry": {"coordinates":[84.02244899999999,18.607422],"type":"Point"}
}