{
  "type": "Feature",
  "properties": {
    "iso:country":"IN",
    "ks:ks_name":"Dighagari",
    "ks:ks_pop":312,
    "ks:ks_type":"VILLAGE",
    "name:eng_x_preferred":[
        "Dighagari"
    ],
    "wof:name":"Dighagari",
    "wof:placetype":"locality",
    "wof:population":312
},
  "geometry": {"coordinates":[88.24256699999999,22.966107],"type":"Point"}
}