{
  "type": "Feature",
  "properties": {
    "iso:country":"IN",
    "ks:ks_name":"Bharatewasti",
    "ks:ks_pop":515,
    "ks:ks_type":"HABITATION",
    "name:eng_x_preferred":[
        "Bharatewasti"
    ],
    "wof:name":"Bharatewasti",
    "wof:placetype":"locality",
    "wof:population":515
},
  "geometry": {"coordinates":[74.982342,18.40066],"type":"Point"}
}