{
  "type": "Feature",
  "properties": {
    "iso:country":"IN",
    "ks:ks_alt_nam":"eanithazham",
    "ks:ks_name":"Eanithazham",
    "ks:ks_pop":424,
    "ks:ks_type":"HABITATION",
    "name:eng_x_preferred":[
        "Eanithazham"
    ],
    "wof:name":"Eanithazham",
    "wof:placetype":"locality",
    "wof:population":424
},
  "geometry": {"coordinates":[76.857264,9.997401],"type":"Point"}
}