{
  "type": "Feature",
  "properties": {
    "iso:country":"IN",
    "ks:ks_name":"Sarakanur",
    "ks:ks_pop":264,
    "ks:ks_type":"VILLAGE",
    "name:eng_x_preferred":[
        "Sarakanur"
    ],
    "wof:name":"Sarakanur",
    "wof:placetype":"locality",
    "wof:population":264
},
  "geometry": {"coordinates":[77.931029,13.218851],"type":"Point"}
}