{
  "type": "Feature",
  "properties": {
    "iso:country":"IN",
    "ks:ks_name":"Chanpapurwa",
    "ks:ks_pop":32,
    "ks:ks_type":"HABITATION",
    "ks:ks_uagg_main":0,
    "name:eng_x_preferred":[
        "Chanpapurwa"
    ],
    "wof:name":"Chanpapurwa",
    "wof:placetype":"neighbourhood",
    "wof:population":32
},
  "geometry": {"coordinates":[81.75446599999999,27.166224],"type":"Point"}
}