{
  "type": "Feature",
  "properties": {
    "iso:country":"IN",
    "ks:ks_name":"Bhatipara",
    "ks:ks_pop":204,
    "ks:ks_type":"HABITATION",
    "name:eng_x_preferred":[
        "Bhatipara"
    ],
    "wof:name":"Bhatipara",
    "wof:placetype":"locality",
    "wof:population":204
},
  "geometry": {"coordinates":[91.38480199999999,25.939767],"type":"Point"}
}