{
  "type": "Feature",
  "properties": {
    "iso:country":"IN",
    "ks:ks_name":"Dhanipur Yadav Basti",
    "ks:ks_pop":350,
    "ks:ks_type":"HABITATION",
    "name:eng_x_preferred":[
        "Dhanipur Yadav Basti"
    ],
    "wof:name":"Dhanipur Yadav Basti",
    "wof:placetype":"locality",
    "wof:population":350
},
  "geometry": {"coordinates":[81.94565299999999,25.864295],"type":"Point"}
}