{
  "type": "Feature",
  "properties": {
    "iso:country":"IN",
    "ks:ks_name":"Gona",
    "ks:ks_pop":361,
    "ks:ks_type":"VILLAGE",
    "name:eng_x_preferred":[
        "Gona"
    ],
    "wof:name":"Gona",
    "wof:placetype":"locality",
    "wof:population":361
},
  "geometry": {"coordinates":[78.212763,30.838746],"type":"Point"}
}