{
  "type": "Feature",
  "properties": {
    "iso:country":"IN",
    "ks:ks_name":"Kodal",
    "ks:ks_pop":53,
    "ks:ks_type":"HABITATION",
    "name:eng_x_preferred":[
        "Kodal"
    ],
    "wof:name":"Kodal",
    "wof:placetype":"locality",
    "wof:population":53
},
  "geometry": {"coordinates":[74.619134,14.231172],"type":"Point"}
}