{
  "type": "Feature",
  "properties": {
    "gn:admin1_code":"35",
    "gn:admin2_code":"463.0",
    "gn:asciiname":"Pachwar",
    "gn:country_code":"IN",
    "gn:dem":466,
    "gn:feature_class":"P",
    "gn:feature_code":"PPL",
    "gn:name":"Pachw\u0101r",
    "gn:population":0,
    "gn:timezone":"Asia/Kolkata",
    "iso:country":"IN",
    "ks:ks_name":"Pachuar",
    "ks:ks_pop":1386,
    "ks:ks_type":"VILLAGE",
    "name:eng_x_preferred":[
        "Pachuar"
    ],
    "name:eng_x_variant":[
        "Pachwar"
    ],
    "wof:name":"Pachuar",
    "wof:placetype":"locality",
    "wof:population":1386
},
  "geometry": {"coordinates":[82.489681,24.331696],"type":"Point"}
}