{
  "type": "Feature",
  "properties": {
    "iso:country":"IN",
    "ks:ks_name":"Mumbardewadi",
    "ks:ks_pop":156,
    "ks:ks_type":"HABITATION",
    "name:eng_x_preferred":[
        "Mumbardewadi"
    ],
    "wof:name":"Mumbardewadi",
    "wof:placetype":"locality",
    "wof:population":156
},
  "geometry": {"coordinates":[73.812867,15.745839],"type":"Point"}
}