{
  "type": "Feature",
  "properties": {
    "gn:admin1_code":"36",
    "gn:admin2_code":"143.0",
    "gn:asciiname":"Jareth",
    "gn:country_code":"IN",
    "gn:dem":184,
    "gn:feature_class":"P",
    "gn:feature_code":"PPL",
    "gn:name":"Jareth",
    "gn:population":0,
    "gn:timezone":"Asia/Kolkata",
    "iso:country":"IN",
    "name:rus_x_preferred":[
        "\u0414\u0436\u0430\u0440\u0435\u0442"
    ],
    "wof:name":"Jareth",
    "wof:placetype":"neighbourhood"
},
  "geometry": {"coordinates":[78.49030999999999,27.89102],"type":"Point"}
}