{
  "type": "Feature",
  "properties": {
    "iso:country":"IN",
    "ks:ks_name":"Adiwasi Tola",
    "ks:ks_pop":83,
    "ks:ks_type":"HABITATION",
    "name:eng_x_preferred":[
        "Adiwasi Tola"
    ],
    "wof:name":"Adiwasi Tola",
    "wof:placetype":"locality",
    "wof:population":83
},
  "geometry": {"coordinates":[87.741084,26.288217],"type":"Point"}
}