{
  "type": "Feature",
  "properties": {
    "gn:admin1_code":"24.0",
    "gn:admin2_code":"118.0",
    "gn:asciiname":"Rampura",
    "gn:country_code":"IN",
    "gn:dem":251,
    "gn:feature_class":"P",
    "gn:feature_code":"PPL",
    "gn:name":"R\u0101mpura",
    "gn:population":0,
    "gn:timezone":"Asia/Kolkata",
    "iso:country":"IN",
    "name:cat_x_preferred":[
        "Rampura"
    ],
    "name:pol_x_preferred":[
        "Rampura"
    ],
    "wof:name":"Rampura",
    "wof:placetype":"locality"
},
  "geometry": {"coordinates":[73.49338,25.67591],"type":"Point"}
}