{
  "type": "Feature",
  "properties": {
    "iso:country":"IN",
    "ks:ks_alt_nam":"Panamkutty Rd jun",
    "ks:ks_name":"Panamkutty Rd Jun",
    "ks:ks_pop":636,
    "ks:ks_type":"HABITATION",
    "name:eng_x_preferred":[
        "Panamkutty Rd Jun"
    ],
    "wof:name":"Panamkutty Rd Jun",
    "wof:placetype":"locality",
    "wof:population":636
},
  "geometry": {"coordinates":[76.429569,10.558667],"type":"Point"}
}