{
  "type": "Feature",
  "properties": {
    "iso:country":"IN",
    "ks:ks_name":"Venkannagumpu",
    "ks:ks_pop":106,
    "ks:ks_type":"HABITATION",
    "name:eng_x_preferred":[
        "Venkannagumpu"
    ],
    "wof:name":"Venkannagumpu",
    "wof:placetype":"locality",
    "wof:population":106
},
  "geometry": {"coordinates":[80.15513,17.833661],"type":"Point"}
}