{
  "type": "Feature",
  "properties": {
    "iso:country":"IN",
    "ks:ks_name":"Alampur",
    "ks:ks_pop":3156,
    "ks:ks_type":"VILLAGE",
    "ks:ks_uagg_main":0,
    "name:eng_x_preferred":[
        "Alampur"
    ],
    "wof:name":"Alampur",
    "wof:placetype":"neighbourhood",
    "wof:population":3156
},
  "geometry": {"coordinates":[88.213655,22.583626],"type":"Point"}
}