{
  "type": "Feature",
  "properties": {
    "gn:admin1_code":"23.0",
    "gn:admin2_code":"43.0",
    "gn:asciiname":"Chuhimar",
    "gn:country_code":"IN",
    "gn:dem":201,
    "gn:feature_class":"P",
    "gn:feature_code":"PPL",
    "gn:name":"Ch\u016bh\u012bm\u0101r",
    "gn:population":0,
    "gn:timezone":"Asia/Kolkata",
    "iso:country":"IN",
    "wof:name":"Chuhimar",
    "wof:placetype":"locality"
},
  "geometry": {"coordinates":[74.7123,30.93938],"type":"Point"}
}