{
  "type": "Feature",
  "properties": {
    "iso:country":"IN",
    "ks:ks_name":"Chunukawan Purwa",
    "ks:ks_pop":128,
    "ks:ks_type":"HABITATION",
    "ks:ks_uagg_main":0,
    "name:eng_x_preferred":[
        "Chunukawan Purwa"
    ],
    "wof:name":"Chunukawan Purwa",
    "wof:placetype":"neighbourhood",
    "wof:population":128
},
  "geometry": {"coordinates":[80.962273,25.395888],"type":"Point"}
}