{
  "type": "Feature",
  "properties": {
    "iso:country":"IN",
    "ks:ks_name":"Benupura",
    "ks:ks_pop":877,
    "ks:ks_type":"VILLAGE",
    "ks:ks_uagg_main":0,
    "name:eng_x_preferred":[
        "Benupura"
    ],
    "wof:name":"Benupura",
    "wof:placetype":"neighbourhood",
    "wof:population":877
},
  "geometry": {"coordinates":[86.13588799999999,20.601293],"type":"Point"}
}