{
  "type": "Feature",
  "properties": {
    "iso:country":"IN",
    "ks:ks_name":"Kamarpal",
    "ks:ks_pop":297,
    "ks:ks_type":"VILLAGE",
    "ks:ks_uagg_main":0,
    "name:eng_x_preferred":[
        "Kamarpal"
    ],
    "wof:name":"Kamarpal",
    "wof:placetype":"neighbourhood",
    "wof:population":297
},
  "geometry": {"coordinates":[86.214771,20.829714],"type":"Point"}
}