{
  "type": "Feature",
  "properties": {
    "iso:country":"IN",
    "ks:ks_name":"Malleshwara Temple",
    "ks:ks_pop":342,
    "ks:ks_type":"HABITATION",
    "name:eng_x_preferred":[
        "Malleshwara Temple"
    ],
    "wof:name":"Malleshwara Temple",
    "wof:placetype":"locality",
    "wof:population":342
},
  "geometry": {"coordinates":[75.478137,13.166998],"type":"Point"}
}