{
  "type": "Feature",
  "properties": {
    "iso:country":"IN",
    "ks:ks_name":"Bodrahpara",
    "ks:ks_pop":123,
    "ks:ks_type":"HABITATION",
    "name:eng_x_preferred":[
        "Bodrahpara"
    ],
    "wof:name":"Bodrahpara",
    "wof:placetype":"locality",
    "wof:population":123
},
  "geometry": {"coordinates":[82.327333,22.835542],"type":"Point"}
}