{
  "type": "Feature",
  "properties": {
    "iso:country":"IN",
    "ks:ks_name":"Latatola Buchahu",
    "ks:ks_pop":663,
    "ks:ks_type":"HABITATION",
    "name:eng_x_preferred":[
        "Latatola Buchahu"
    ],
    "wof:name":"Latatola Buchahu",
    "wof:placetype":"locality",
    "wof:population":663
},
  "geometry": {"coordinates":[84.736223,22.065988],"type":"Point"}
}