{
  "type": "Feature",
  "properties": {
    "gn:admin1_code":"19.0",
    "gn:admin2_code":"577.0",
    "gn:asciiname":"Malgankere",
    "gn:country_code":"IN",
    "gn:dem":848,
    "gn:feature_class":"P",
    "gn:feature_code":"PPL",
    "gn:name":"Malgankere",
    "gn:population":0,
    "gn:timezone":"Asia/Kolkata",
    "iso:country":"IN",
    "wof:name":"Malgankere",
    "wof:placetype":"locality"
},
  "geometry": {"coordinates":[76.22303000000002,12.38557],"type":"Point"}
}