{
  "type": "Feature",
  "properties": {
    "gn:admin1_code":"28.0",
    "gn:admin2_code":"337",
    "gn:asciiname":"Bayarmari",
    "gn:country_code":"IN",
    "gn:dem":1,
    "gn:feature_class":"P",
    "gn:feature_code":"PPL",
    "gn:name":"Bay\u0101rm\u0101ri",
    "gn:population":0,
    "gn:timezone":"Asia/Kolkata",
    "iso:country":"IN",
    "name:und_x_variant":[
        "Boyarmari Abad",
        "Bay\u0101rm\u0101ri"
    ],
    "wof:name":"Bayarmari",
    "wof:placetype":"locality"
},
  "geometry": {"coordinates":[88.82973,22.45813],"type":"Point"}
}