{
  "type": "Feature",
  "properties": {
    "iso:country":"IN",
    "ks:ks_alt_nam":"Raung kong",
    "ks:ks_name":"Raung Kong",
    "ks:ks_pop":118,
    "ks:ks_type":"HABITATION",
    "name:eng_x_preferred":[
        "Raung Kong"
    ],
    "wof:name":"Raung Kong",
    "wof:placetype":"locality",
    "wof:population":118
},
  "geometry": {"coordinates":[80.561909,29.892007],"type":"Point"}
}