{
  "type": "Feature",
  "properties": {
    "iso:country":"IN",
    "ks:ks_name":"Kurusbodi",
    "ks:ks_pop":354,
    "ks:ks_type":"HABITATION",
    "name:eng_x_preferred":[
        "Kurusbodi"
    ],
    "wof:name":"Kurusbodi",
    "wof:placetype":"locality",
    "wof:population":354
},
  "geometry": {"coordinates":[80.58562000000001,20.146617],"type":"Point"}
}