{
  "type": "Feature",
  "properties": {
    "gn:admin1_code":"39.0",
    "gn:admin2_code":"57.0",
    "gn:asciiname":"Karchhon",
    "gn:country_code":"IN",
    "gn:dem":2421,
    "gn:feature_class":"P",
    "gn:feature_code":"PPL",
    "gn:name":"Karchhon",
    "gn:population":0,
    "gn:timezone":"Asia/Kolkata",
    "iso:country":"IN",
    "wof:name":"Karchhon",
    "wof:placetype":"locality"
},
  "geometry": {"coordinates":[79.62034,30.47909000000001],"type":"Point"}
}