{
  "type": "Feature",
  "properties": {
    "gn:admin1_code":"11",
    "gn:admin2_code":"24.0",
    "gn:asciiname":"Jhuraru",
    "gn:country_code":"IN",
    "gn:dem":659,
    "gn:feature_class":"P",
    "gn:feature_code":"PPL",
    "gn:name":"Jhuraru",
    "gn:population":0,
    "gn:timezone":"Asia/Kolkata",
    "iso:country":"IN",
    "wof:name":"Jhuraru",
    "wof:placetype":"locality"
},
  "geometry": {"coordinates":[76.21828000000002,32.07714],"type":"Point"}
}