{
  "type": "Feature",
  "properties": {
    "iso:country":"IN",
    "ks:ks_name":"Nawada",
    "ks:ks_pop":0,
    "ks:ks_type":"VILLAGE",
    "name:eng_x_preferred":[
        "Nawada"
    ],
    "wof:name":"Nawada",
    "wof:placetype":"locality",
    "wof:population":0
},
  "geometry": {"coordinates":[83.766914,26.271107],"type":"Point"}
}