{
  "type": "Feature",
  "properties": {
    "gn:admin1_code":"36",
    "gn:admin2_code":"158.0",
    "gn:asciiname":"Baba Khera",
    "gn:country_code":"IN",
    "gn:dem":120,
    "gn:feature_class":"P",
    "gn:feature_code":"PPL",
    "gn:name":"B\u0101ba Khera",
    "gn:population":0,
    "gn:timezone":"Asia/Kolkata",
    "iso:country":"IN",
    "wof:name":"Baba Khera",
    "wof:placetype":"neighbourhood"
},
  "geometry": {"coordinates":[80.85577000000001,26.23663],"type":"Point"}
}