{
  "type": "Feature",
  "properties": {
    "iso:country":"IN",
    "ks:ks_alt_nam":"SURYAWANSHIWASTI",
    "ks:ks_name":"Suryawanshiwasti",
    "ks:ks_pop":125,
    "ks:ks_type":"HABITATION",
    "ks:ks_uagg_main":0,
    "name:eng_x_preferred":[
        "Suryawanshiwasti"
    ],
    "wof:name":"Suryawanshiwasti",
    "wof:placetype":"neighbourhood",
    "wof:population":125
},
  "geometry": {"coordinates":[74.792401,17.064537],"type":"Point"}
}