{
  "type": "Feature",
  "properties": {
    "gn:admin1_code":"36",
    "gn:admin2_code":"147.0",
    "gn:asciiname":"Nagla Budha",
    "gn:country_code":"IN",
    "gn:dem":162,
    "gn:feature_class":"P",
    "gn:feature_code":"PPL",
    "gn:name":"Nagla Budha",
    "gn:population":0,
    "gn:timezone":"Asia/Kolkata",
    "iso:country":"IN",
    "wof:name":"Nagla Budha",
    "wof:placetype":"locality"
},
  "geometry": {"coordinates":[78.73224999999999,27.25708],"type":"Point"}
}