{
  "type": "Feature",
  "properties": {
    "iso:country":"IN",
    "ks:ks_name":"Kishori Falia",
    "ks:ks_pop":601,
    "ks:ks_type":"HABITATION",
    "name:eng_x_preferred":[
        "Kishori Falia"
    ],
    "wof:name":"Kishori Falia",
    "wof:placetype":"locality",
    "wof:population":601
},
  "geometry": {"coordinates":[73.942992,22.915844],"type":"Point"}
}