{
  "type": "Feature",
  "properties": {
    "gn:admin1_code":"2.0",
    "gn:admin2_code":"549.0",
    "gn:asciiname":"Agraharam",
    "gn:country_code":"IN",
    "gn:dem":20,
    "gn:feature_class":"P",
    "gn:feature_code":"PPL",
    "gn:name":"Agrah\u0101ram",
    "gn:population":0,
    "gn:timezone":"Asia/Kolkata",
    "iso:country":"IN",
    "name:deu_x_preferred":[
        "Agraharam"
    ],
    "name:hin_x_preferred":[
        "\u0905\u0917\u094d\u0930\u0939\u093e\u0930\u092e"
    ],
    "name:kan_x_preferred":[
        "\u0c85\u0c97\u0ccd\u0cb0\u0cb9\u0cbe\u0cb0"
    ],
    "name:mal_x_preferred":[
        "\u0d05\u0d17\u0d4d\u0d30\u0d39\u0d3e\u0d30\u0d02"
    ],
    "name:tam_x_preferred":[
        "\u0b85\u0b95\u0bcd\u0bb0\u0b95\u0bbe\u0bb0\u0bae\u0bcd"
    ],
    "name:vie_x_preferred":[
        "Agrahara"
    ],
    "wof:name":"Agraharam",
    "wof:placetype":"locality"
},
  "geometry": {"coordinates":[80.01725999999999,15.27403],"type":"Point"}
}