{
  "type": "Feature",
  "properties": {
    "iso:country":"IN",
    "ks:ks_name":"Pipara",
    "ks:ks_pop":113,
    "ks:ks_type":"HABITATION",
    "name:eng_x_preferred":[
        "Pipara"
    ],
    "wof:name":"Pipara",
    "wof:placetype":"locality",
    "wof:population":113
},
  "geometry": {"coordinates":[86.449851,24.723327],"type":"Point"}
}