{
  "type": "Feature",
  "properties": {
    "iso:country":"IN",
    "ks:ks_name":"Kasiya Mahua",
    "ks:ks_pop":11,
    "ks:ks_type":"HABITATION",
    "name:eng_x_preferred":[
        "Kasiya Mahua"
    ],
    "wof:name":"Kasiya Mahua",
    "wof:placetype":"locality",
    "wof:population":11
},
  "geometry": {"coordinates":[84.702062,24.071271],"type":"Point"}
}