{
  "type": "Feature",
  "properties": {
    "iso:country":"IN",
    "ks:ks_name":"Varchiwadi",
    "ks:ks_pop":92,
    "ks:ks_type":"HABITATION",
    "name:eng_x_preferred":[
        "Varchiwadi"
    ],
    "wof:name":"Varchiwadi",
    "wof:placetype":"locality",
    "wof:population":92
},
  "geometry": {"coordinates":[73.63437500000001,16.653614],"type":"Point"}
}