{
  "type": "Feature",
  "properties": {
    "iso:country":"IN",
    "ks:ks_name":"Burusundiguda",
    "ks:ks_pop":110,
    "ks:ks_type":"HABITATION",
    "name:eng_x_preferred":[
        "Burusundiguda"
    ],
    "wof:name":"Burusundiguda",
    "wof:placetype":"locality",
    "wof:population":110
},
  "geometry": {"coordinates":[82.092983,18.131375],"type":"Point"}
}