{
  "type": "Feature",
  "properties": {
    "iso:country":"IN",
    "ks:ks_name":"Dudhori",
    "ks:ks_pop":331,
    "ks:ks_type":"VILLAGE",
    "name:eng_x_preferred":[
        "Dudhori"
    ],
    "wof:name":"Dudhori",
    "wof:placetype":"locality",
    "wof:population":331
},
  "geometry": {"coordinates":[80.037903,29.210544],"type":"Point"}
}