{
  "type": "Feature",
  "properties": {
    "gn:admin1_code":"35.0",
    "gn:admin2_code":"432.0",
    "gn:asciiname":"Morwan",
    "gn:country_code":"IN",
    "gn:dem":478,
    "gn:feature_class":"P",
    "gn:feature_code":"PPL",
    "gn:name":"Morwan",
    "gn:population":0,
    "gn:timezone":"Asia/Kolkata",
    "iso:country":"IN",
    "wof:name":"Morwan",
    "wof:placetype":"locality"
},
  "geometry": {"coordinates":[74.99478000000001,24.61781],"type":"Point"}
}