{
  "type": "Feature",
  "properties": {
    "iso:country":"IN",
    "ks:ks_name":"Banda Valasa",
    "ks:ks_pop":81,
    "ks:ks_type":"HABITATION",
    "name:eng_x_preferred":[
        "Banda Valasa"
    ],
    "wof:name":"Banda Valasa",
    "wof:placetype":"locality",
    "wof:population":81
},
  "geometry": {"coordinates":[82.935022,17.991319],"type":"Point"}
}