{
  "type": "Feature",
  "properties": {
    "gn:admin1_code":"24",
    "gn:admin2_code":"121.0",
    "gn:asciiname":"Sukpura",
    "gn:country_code":"IN",
    "gn:dem":310,
    "gn:feature_class":"P",
    "gn:feature_code":"PPL",
    "gn:name":"Sukpura",
    "gn:population":0,
    "gn:timezone":"Asia/Kolkata",
    "iso:country":"IN",
    "wof:name":"Sukpura",
    "wof:placetype":"locality"
},
  "geometry": {"coordinates":[75.46664,25.56899],"type":"Point"}
}