{
  "type": "Feature",
  "properties": {
    "iso:country":"IN",
    "ks:ks_name":"Kaloo Gamra",
    "ks:ks_pop":849,
    "ks:ks_type":"VILLAGE",
    "name:eng_x_preferred":[
        "Kaloo Gamra"
    ],
    "wof:name":"Kaloo Gamra",
    "wof:placetype":"locality",
    "wof:population":849
},
  "geometry": {"coordinates":[73.94316000000001,23.881063],"type":"Point"}
}