{
  "type": "Feature",
  "properties": {
    "gn:admin1_code":"39",
    "gn:admin2_code":"67.0",
    "gn:asciiname":"Sheorajpur Patti",
    "gn:country_code":"IN",
    "gn:dem":242,
    "gn:feature_class":"P",
    "gn:feature_code":"PPL",
    "gn:name":"Sheor\u0101jpur Patti",
    "gn:population":0,
    "gn:timezone":"Asia/Kolkata",
    "iso:country":"IN",
    "wof:name":"Sheorajpur Patti",
    "wof:placetype":"locality"
},
  "geometry": {"coordinates":[78.89131999999999,29.26218],"type":"Point"}
}