{
  "type": "Feature",
  "properties": {
    "gn:admin1_code":"19.0",
    "gn:admin2_code":"558.0",
    "gn:asciiname":"Kowtha Buzurg",
    "gn:country_code":"IN",
    "gn:dem":548,
    "gn:feature_class":"P",
    "gn:feature_code":"PPL",
    "gn:name":"Kowtha Buzurg",
    "gn:population":0,
    "gn:timezone":"Asia/Kolkata",
    "iso:country":"IN",
    "wof:name":"Kowtha Buzurg",
    "wof:placetype":"locality"
},
  "geometry": {"coordinates":[77.47499999999999,18.03624],"type":"Point"}
}