{
  "type": "Feature",
  "properties": {
    "gn:admin1_code":"21",
    "gn:admin2_code":"396.0",
    "gn:asciiname":"Kodamaguda",
    "gn:country_code":"IN",
    "gn:dem":373,
    "gn:feature_class":"P",
    "gn:feature_code":"PPL",
    "gn:name":"Kodamaguda",
    "gn:population":0,
    "gn:timezone":"Asia/Kolkata",
    "iso:country":"IN",
    "ks:ks_name":"Kadamaguda",
    "ks:ks_pop":52,
    "ks:ks_type":"VILLAGE",
    "name:eng_x_preferred":[
        "Kadamaguda"
    ],
    "name:eng_x_variant":[
        "Kodamaguda"
    ],
    "wof:name":"Kadamaguda",
    "wof:placetype":"locality",
    "wof:population":52
},
  "geometry": {"coordinates":[83.471411,19.6299],"type":"Point"}
}