{
  "type": "Feature",
  "properties": {
    "iso:country":"IN",
    "ks:ks_name":"Khaigarh",
    "ks:ks_pop":820,
    "ks:ks_type":"VILLAGE",
    "name:eng_x_preferred":[
        "Khaigarh"
    ],
    "wof:name":"Khaigarh",
    "wof:placetype":"locality",
    "wof:population":820
},
  "geometry": {"coordinates":[92.535134,26.241504],"type":"Point"}
}