{
  "type": "Feature",
  "properties": {
    "iso:country":"IN",
    "ks:ks_alt_nam":"Adharkuna pt III",
    "ks:ks_name":"Adharkuna Pt Iii",
    "ks:ks_pop":674,
    "ks:ks_type":"HABITATION",
    "name:eng_x_preferred":[
        "Adharkuna Pt Iii"
    ],
    "wof:name":"Adharkuna Pt Iii",
    "wof:placetype":"locality",
    "wof:population":674
},
  "geometry": {"coordinates":[92.52097500000001,24.760089],"type":"Point"}
}