{
  "type": "Feature",
  "properties": {
    "iso:country":"IN",
    "ks:ks_name":"Bhalukdubi",
    "ks:ks_pop":7008,
    "ks:ks_type":"VILLAGE",
    "ks:ks_uagg_main":0,
    "name:eng_x_preferred":[
        "Bhalukdubi"
    ],
    "wof:name":"Bhalukdubi",
    "wof:placetype":"locality",
    "wof:population":7008
},
  "geometry": {"coordinates":[90.601737,26.152813],"type":"Point"}
}