{
  "type": "Feature",
  "properties": {
    "iso:country":"IN",
    "ks:ks_name":"Sonachora",
    "ks:ks_pop":22,
    "ks:ks_type":"VILLAGE",
    "name:eng_x_preferred":[
        "Sonachora"
    ],
    "wof:name":"Sonachora",
    "wof:placetype":"locality",
    "wof:population":22
},
  "geometry": {"coordinates":[87.153468,23.628212],"type":"Point"}
}