{
  "type": "Feature",
  "properties": {
    "iso:country":"IN",
    "ks:ks_name":"Adiwasipada",
    "ks:ks_pop":236,
    "ks:ks_type":"HABITATION",
    "name:eng_x_preferred":[
        "Adiwasipada"
    ],
    "wof:name":"Adiwasipada",
    "wof:placetype":"locality",
    "wof:population":236
},
  "geometry": {"coordinates":[73.198142,19.346521],"type":"Point"}
}