{
  "type": "Feature",
  "properties": {
    "gn:admin1_code":"39.0",
    "gn:admin2_code":"60.0",
    "gn:asciiname":"Gaski",
    "gn:country_code":"IN",
    "gn:dem":1101,
    "gn:feature_class":"P",
    "gn:feature_code":"PPL",
    "gn:name":"G\u0101ski",
    "gn:population":0,
    "gn:timezone":"Asia/Kolkata",
    "iso:country":"IN",
    "wof:name":"Gaski",
    "wof:placetype":"locality"
},
  "geometry": {"coordinates":[77.91930000000001,30.53411],"type":"Point"}
}