{
  "type": "Feature",
  "properties": {
    "iso:country":"IN",
    "ks:ks_name":"Devarahalli",
    "ks:ks_pop":66,
    "ks:ks_type":"HABITATION",
    "name:eng_x_preferred":[
        "Devarahalli"
    ],
    "wof:name":"Devarahalli",
    "wof:placetype":"locality",
    "wof:population":66
},
  "geometry": {"coordinates":[77.01173,13.287581],"type":"Point"}
}