{
  "type": "Feature",
  "properties": {
    "iso:country":"IN",
    "ks:ks_name":"Tali Gulam",
    "ks:ks_pop":481,
    "ks:ks_type":"VILLAGE",
    "name:eng_x_preferred":[
        "Tali Gulam"
    ],
    "wof:name":"Tali Gulam",
    "wof:placetype":"locality",
    "wof:population":481
},
  "geometry": {"coordinates":[74.759428,31.092915],"type":"Point"}
}