{
  "type": "Feature",
  "properties": {
    "gn:admin1_code":"34.0",
    "gn:admin2_code":"203.0",
    "gn:asciiname":"Jaisinghpur",
    "gn:country_code":"IN",
    "gn:dem":81,
    "gn:feature_class":"P",
    "gn:feature_code":"PPL",
    "gn:name":"Jaisinghpur",
    "gn:population":0,
    "gn:timezone":"Asia/Kolkata",
    "iso:country":"IN",
    "name:urd_x_preferred":[
        "\u062c\u06cc\u0633\u0646\u06af\u06be\u067e\u0648\u0631"
    ],
    "wof:name":"Jaisinghpur",
    "wof:placetype":"locality"
},
  "geometry": {"coordinates":[84.65886999999999,27.0088],"type":"Point"}
}