{
  "type": "Feature",
  "properties": {
    "gn:admin1_code":"17.0",
    "gn:admin2_code":"280",
    "gn:asciiname":"Aihol",
    "gn:country_code":"IN",
    "gn:dem":861,
    "gn:feature_class":"P",
    "gn:feature_code":"PPL",
    "gn:name":"Aihol",
    "gn:population":0,
    "gn:timezone":"Asia/Kolkata",
    "iso:country":"IN",
    "wof:name":"Aihol",
    "wof:placetype":"locality"
},
  "geometry": {"coordinates":[93.98333,23.93333],"type":"Point"}
}