{
  "type": "Feature",
  "properties": {
    "iso:country":"IN",
    "ks:ks_alt_nam":"Mallapur tanda",
    "ks:ks_name":"Mallapur Tanda",
    "ks:ks_pop":193,
    "ks:ks_type":"HABITATION",
    "name:eng_x_preferred":[
        "Mallapur Tanda"
    ],
    "wof:name":"Mallapur Tanda",
    "wof:placetype":"locality",
    "wof:population":193
},
  "geometry": {"coordinates":[76.916714,16.272143],"type":"Point"}
}