{
  "type": "Feature",
  "properties": {
    "iso:country":"IN",
    "ks:ks_name":"Suryapur",
    "ks:ks_pop":0,
    "ks:ks_type":"VILLAGE",
    "name:eng_x_preferred":[
        "Suryapur"
    ],
    "wof:name":"Suryapur",
    "wof:placetype":"locality",
    "wof:population":0
},
  "geometry": {"coordinates":[76.607078,20.103019],"type":"Point"}
}