{
  "type": "Feature",
  "properties": {
    "iso:country":"IN",
    "ks:ks_name":"Kuanrpur",
    "ks:ks_pop":204,
    "ks:ks_type":"VILLAGE",
    "ks:ks_uagg_main":0,
    "name:eng_x_preferred":[
        "Kuanrpur"
    ],
    "wof:name":"Kuanrpur",
    "wof:placetype":"neighbourhood",
    "wof:population":204
},
  "geometry": {"coordinates":[86.14692700000001,20.663316],"type":"Point"}
}