{
  "type": "Feature",
  "properties": {
    "iso:country":"IN",
    "ks:ks_name":"Dinneri Plantation",
    "ks:ks_pop":165,
    "ks:ks_type":"HABITATION",
    "name:eng_x_preferred":[
        "Dinneri Plantation"
    ],
    "wof:name":"Dinneri Plantation",
    "wof:placetype":"locality",
    "wof:population":165
},
  "geometry": {"coordinates":[77.98801400000001,12.934413],"type":"Point"}
}