{
  "type": "Feature",
  "properties": {
    "iso:country":"IN",
    "ks:ks_name":"Raipur Kalan",
    "ks:ks_pop":711,
    "ks:ks_type":"VILLAGE",
    "name:eng_x_preferred":[
        "Raipur Kalan"
    ],
    "wof:name":"Raipur Kalan",
    "wof:placetype":"locality",
    "wof:population":711
},
  "geometry": {"coordinates":[74.67394400000001,31.896658],"type":"Point"}
}