{
  "type": "Feature",
  "properties": {
    "iso:country":"IN",
    "ks:ks_name":"Hatirgool",
    "ks:ks_pop":1402,
    "ks:ks_type":"VILLAGE",
    "name:eng_x_preferred":[
        "Hatirgool"
    ],
    "wof:name":"Hatirgool",
    "wof:placetype":"locality",
    "wof:population":1402
},
  "geometry": {"coordinates":[92.277709,24.654054],"type":"Point"}
}