{
  "type": "Feature",
  "properties": {
    "iso:country":"IN",
    "ks:ks_name":"Jankaravalasa",
    "ks:ks_pop":90,
    "ks:ks_type":"HABITATION",
    "name:eng_x_preferred":[
        "Jankaravalasa"
    ],
    "wof:name":"Jankaravalasa",
    "wof:placetype":"locality",
    "wof:population":90
},
  "geometry": {"coordinates":[82.742795,18.235124],"type":"Point"}
}