{
  "type": "Feature",
  "properties": {
    "iso:country":"IN",
    "ks:ks_name":"Kolavally",
    "ks:ks_pop":260,
    "ks:ks_type":"HABITATION",
    "name:eng_x_preferred":[
        "Kolavally"
    ],
    "wof:name":"Kolavally",
    "wof:placetype":"locality",
    "wof:population":260
},
  "geometry": {"coordinates":[76.197806,11.858333],"type":"Point"}
}