{
  "type": "Feature",
  "properties": {
    "iso:country":"IN",
    "ks:ks_name":"Achandira",
    "ks:ks_pop":29,
    "ks:ks_type":"HABITATION",
    "name:eng_x_preferred":[
        "Achandira"
    ],
    "wof:name":"Achandira",
    "wof:placetype":"locality",
    "wof:population":29
},
  "geometry": {"coordinates":[75.67925200000001,12.294785],"type":"Point"}
}