{
  "type": "Feature",
  "properties": {
    "gn:admin1_code":"13.0",
    "gn:admin2_code":"594.0",
    "gn:asciiname":"Potta",
    "gn:country_code":"IN",
    "gn:dem":27,
    "gn:feature_class":"P",
    "gn:feature_code":"PPL",
    "gn:name":"Potta",
    "gn:population":0,
    "gn:timezone":"Asia/Kolkata",
    "iso:country":"IN",
    "ks:ks_name":"Potta",
    "ks:ks_pop":4315,
    "ks:ks_type":"VILLAGE",
    "name:eng_x_preferred":[
        "Potta"
    ],
    "name:mal_x_preferred":[
        "\u0d2a\u0d4b\u0d1f\u0d4d\u0d1f"
    ],
    "name:msa_x_preferred":[
        "Potta"
    ],
    "wof:name":"Potta",
    "wof:placetype":"locality",
    "wof:population":4315
},
  "geometry": {"coordinates":[76.336766,10.320697],"type":"Point"}
}