{
  "type": "Feature",
  "properties": {
    "iso:country":"IN",
    "ks:ks_name":"Matadakere Inna",
    "ks:ks_pop":126,
    "ks:ks_type":"HABITATION",
    "name:eng_x_preferred":[
        "Matadakere Inna"
    ],
    "wof:name":"Matadakere Inna",
    "wof:placetype":"locality",
    "wof:population":126
},
  "geometry": {"coordinates":[74.83691399999999,13.143901],"type":"Point"}
}