{
  "type": "Feature",
  "properties": {
    "iso:country":"IN",
    "ks:ks_name":"Haikara Tola",
    "ks:ks_pop":484,
    "ks:ks_type":"HABITATION",
    "ks:ks_uagg_main":0,
    "name:eng_x_preferred":[
        "Haikara Tola"
    ],
    "wof:name":"Haikara Tola",
    "wof:placetype":"neighbourhood",
    "wof:population":484
},
  "geometry": {"coordinates":[86.72038999999999,25.139634],"type":"Point"}
}