{
  "type": "Feature",
  "properties": {
    "gn:admin1_code":"34.0",
    "gn:admin2_code":"221.0",
    "gn:asciiname":"Naua Chak",
    "gn:country_code":"IN",
    "gn:dem":54,
    "gn:feature_class":"P",
    "gn:feature_code":"PPL",
    "gn:name":"Naua Chak",
    "gn:population":0,
    "gn:timezone":"Asia/Kolkata",
    "iso:country":"IN",
    "ks:ks_name":"Naua Chak",
    "ks:ks_type":"VILLAGE",
    "name:eng_x_preferred":[
        "Naua Chak"
    ],
    "wof:name":"Naua Chak",
    "wof:placetype":"locality"
},
  "geometry": {"coordinates":[85.664923,25.955585],"type":"Point"}
}