{
  "type": "Feature",
  "properties": {
    "iso:country":"IN",
    "ks:ks_name":"Pakhian Purwa",
    "ks:ks_pop":245,
    "ks:ks_type":"HABITATION",
    "name:eng_x_preferred":[
        "Pakhian Purwa"
    ],
    "wof:name":"Pakhian Purwa",
    "wof:placetype":"locality",
    "wof:population":245
},
  "geometry": {"coordinates":[81.207358,27.018268],"type":"Point"}
}