{
  "type": "Feature",
  "properties": {
    "iso:country":"IN",
    "ks:ks_alt_nam":"Haralal D-Nath para",
    "ks:ks_name":"Haralal D-nath Para",
    "ks:ks_pop":283,
    "ks:ks_type":"HABITATION",
    "name:eng_x_preferred":[
        "Haralal D-nath Para"
    ],
    "wof:name":"Haralal D-nath Para",
    "wof:placetype":"locality",
    "wof:population":283
},
  "geometry": {"coordinates":[91.594284,23.303525],"type":"Point"}
}