{
  "type": "Feature",
  "properties": {
    "iso:country":"IN",
    "ks:ks_name":"Daulat Goga Nagar",
    "ks:ks_pop":131,
    "ks:ks_type":"HABITATION",
    "name:eng_x_preferred":[
        "Daulat Goga Nagar"
    ],
    "wof:name":"Daulat Goga Nagar",
    "wof:placetype":"locality",
    "wof:population":131
},
  "geometry": {"coordinates":[72.34095000000001,26.657311],"type":"Point"}
}