{
  "type": "Feature",
  "properties": {
    "iso:country":"IN",
    "ks:ks_name":"Ghun Ghuta",
    "ks:ks_pop":455,
    "ks:ks_type":"VILLAGE",
    "name:eng_x_preferred":[
        "Ghun Ghuta"
    ],
    "wof:name":"Ghun Ghuta",
    "wof:placetype":"locality",
    "wof:population":455
},
  "geometry": {"coordinates":[81.862199,23.429356],"type":"Point"}
}