{
  "type": "Feature",
  "properties": {
    "iso:country":"IN",
    "ks:ks_alt_nam":"K\u0101let",
    "ks:ks_name":"Kalet",
    "ks:ks_pop":657,
    "ks:ks_type":"VILLAGE",
    "name:eng_x_preferred":[
        "Kalet"
    ],
    "name:eng_x_variant":[
        "K\u0101let"
    ],
    "wof:name":"Kalet",
    "wof:placetype":"locality",
    "wof:population":657
},
  "geometry": {"coordinates":[85.13808,22.867093],"type":"Point"}
}