{
  "type": "Feature",
  "properties": {
    "iso:country":"IN",
    "ks:ks_name":"Majhauli Kalan",
    "ks:ks_pop":584,
    "ks:ks_type":"HABITATION",
    "name:eng_x_preferred":[
        "Majhauli Kalan"
    ],
    "wof:name":"Majhauli Kalan",
    "wof:placetype":"locality",
    "wof:population":584
},
  "geometry": {"coordinates":[80.571355,23.38884],"type":"Point"}
}