{
  "type": "Feature",
  "properties": {
    "gn:admin1_code":"40.0",
    "gn:admin2_code":"534.0",
    "gn:asciiname":"Mallial",
    "gn:country_code":"IN",
    "gn:dem":228,
    "gn:feature_class":"P",
    "gn:feature_code":"PPL",
    "gn:name":"Malli\u0101l",
    "gn:population":0,
    "gn:timezone":"Asia/Kolkata",
    "iso:country":"IN",
    "name:pam_x_preferred":[
        "Mallial"
    ],
    "name:tel_x_preferred":[
        "\u0c2e\u0c32\u0c4d\u0c2f\u0c3e\u0c32"
    ],
    "wof:name":"Mallial",
    "wof:placetype":"locality"
},
  "geometry": {"coordinates":[79.53563,18.25848],"type":"Point"}
}