{
  "type": "Feature",
  "properties": {
    "iso:country":"IN",
    "ks:ks_name":"Hari Harpur",
    "ks:ks_type":"VILLAGE",
    "name:eng_x_preferred":[
        "Hari Harpur"
    ],
    "wof:name":"Hari Harpur",
    "wof:placetype":"locality"
},
  "geometry": {"coordinates":[83.752269,25.606648],"type":"Point"}
}