{
  "type": "Feature",
  "properties": {
    "iso:country":"IN",
    "ks:ks_name":"Buridih",
    "ks:ks_pop":78,
    "ks:ks_type":"VILLAGE",
    "name:eng_x_preferred":[
        "Buridih"
    ],
    "wof:name":"Buridih",
    "wof:placetype":"locality",
    "wof:population":78
},
  "geometry": {"coordinates":[87.589386,24.97059],"type":"Point"}
}