{
  "type": "Feature",
  "properties": {
    "iso:country":"IN",
    "ks:ks_name":"Barikir",
    "ks:ks_pop":197,
    "ks:ks_type":"HABITATION",
    "name:eng_x_preferred":[
        "Barikir"
    ],
    "wof:name":"Barikir",
    "wof:placetype":"locality",
    "wof:population":197
},
  "geometry": {"coordinates":[85.411908,22.875334],"type":"Point"}
}