{
  "type": "Feature",
  "properties": {
    "iso:country":"IN",
    "ks:ks_name":"Gaucharnamuvada",
    "ks:ks_pop":983,
    "ks:ks_type":"HABITATION",
    "name:eng_x_preferred":[
        "Gaucharnamuvada"
    ],
    "wof:name":"Gaucharnamuvada",
    "wof:placetype":"locality",
    "wof:population":983
},
  "geometry": {"coordinates":[73.149528,23.060056],"type":"Point"}
}