{
  "type": "Feature",
  "properties": {
    "iso:country":"IN",
    "ks:ks_name":"Panamthoppu Colony",
    "ks:ks_pop":85,
    "ks:ks_type":"HABITATION",
    "name:eng_x_preferred":[
        "Panamthoppu Colony"
    ],
    "wof:name":"Panamthoppu Colony",
    "wof:placetype":"locality",
    "wof:population":85
},
  "geometry": {"coordinates":[78.77427299999999,12.826619],"type":"Point"}
}