{
  "type": "Feature",
  "properties": {
    "iso:country":"IN",
    "ks:ks_name":"Kajee Khera",
    "ks:ks_pop":743,
    "ks:ks_type":"HABITATION",
    "ks:ks_uagg_main":0,
    "name:eng_x_preferred":[
        "Kajee Khera"
    ],
    "wof:name":"Kajee Khera",
    "wof:placetype":"neighbourhood",
    "wof:population":743
},
  "geometry": {"coordinates":[79.314768,27.969355],"type":"Point"}
}