{
  "type": "Feature",
  "properties": {
    "iso:country":"IN",
    "ks:ks_name":"Shibpur",
    "ks:ks_pop":2289,
    "ks:ks_type":"VILLAGE",
    "ks:ks_uagg_main":0,
    "name:eng_x_preferred":[
        "Shibpur"
    ],
    "wof:name":"Shibpur",
    "wof:placetype":"neighbourhood",
    "wof:population":2289
},
  "geometry": {"coordinates":[87.70519,22.669561],"type":"Point"}
}