{
  "type": "Feature",
  "properties": {
    "iso:country":"IN",
    "ks:ks_name":"Digi",
    "ks:ks_pop":82,
    "ks:ks_type":"VILLAGE",
    "name:eng_x_preferred":[
        "Digi"
    ],
    "wof:name":"Digi",
    "wof:placetype":"locality",
    "wof:population":82
},
  "geometry": {"coordinates":[84.853869,20.088911],"type":"Point"}
}