{
  "type": "Feature",
  "properties": {
    "iso:country":"IN",
    "ks:ks_name":"Sunauli",
    "ks:ks_pop":92,
    "ks:ks_type":"VILLAGE",
    "name:eng_x_preferred":[
        "Sunauli"
    ],
    "wof:name":"Sunauli",
    "wof:placetype":"locality",
    "wof:population":92
},
  "geometry": {"coordinates":[80.057551,29.667639],"type":"Point"}
}