{
  "type": "Feature",
  "properties": {
    "iso:country":"IN",
    "ks:ks_name":"Ulappana Kera",
    "ks:ks_pop":192,
    "ks:ks_type":"HABITATION",
    "name:eng_x_preferred":[
        "Ulappana Kera"
    ],
    "wof:name":"Ulappana Kera",
    "wof:placetype":"locality",
    "wof:population":192
},
  "geometry": {"coordinates":[76.16,15.24],"type":"Point"}
}