{
  "type": "Feature",
  "properties": {
    "gn:admin1_code":"36.0",
    "gn:admin2_code":"157.0",
    "gn:asciiname":"Hanwantpur",
    "gn:country_code":"IN",
    "gn:dem":127,
    "gn:feature_class":"P",
    "gn:feature_code":"PPL",
    "gn:name":"Hanwantpur",
    "gn:population":0,
    "gn:timezone":"Asia/Kolkata",
    "iso:country":"IN",
    "wof:name":"Hanwantpur",
    "wof:placetype":"locality"
},
  "geometry": {"coordinates":[80.94809000000002,27.12577000000001],"type":"Point"}
}