{
  "type": "Feature",
  "properties": {
    "gn:admin1_code":"19.0",
    "gn:admin2_code":"581.0",
    "gn:asciiname":"Naruvalhalli",
    "gn:country_code":"IN",
    "gn:dem":841,
    "gn:feature_class":"P",
    "gn:feature_code":"PPL",
    "gn:name":"Naruvalhalli",
    "gn:population":0,
    "gn:timezone":"Asia/Kolkata",
    "iso:country":"IN",
    "wof:name":"Naruvalhalli",
    "wof:placetype":"locality"
},
  "geometry": {"coordinates":[78.05804999999999,12.85121],"type":"Point"}
}