{
  "type": "Feature",
  "properties": {
    "iso:country":"IN",
    "ks:ks_name":"Marakamallaggakunta",
    "ks:ks_pop":596,
    "ks:ks_type":"HABITATION",
    "name:eng_x_preferred":[
        "Marakamallaggakunta"
    ],
    "wof:name":"Marakamallaggakunta",
    "wof:placetype":"locality",
    "wof:population":596
},
  "geometry": {"coordinates":[78.52752599999999,12.988112],"type":"Point"}
}