{
  "type": "Feature",
  "properties": {
    "iso:country":"IN",
    "ks:ks_alt_nam":"Law\u0101gar\u0101",
    "ks:ks_name":"Lawagara",
    "ks:ks_pop":134,
    "ks:ks_type":"VILLAGE",
    "name:eng_x_preferred":[
        "Lawagara"
    ],
    "name:eng_x_variant":[
        "Law\u0101gar\u0101"
    ],
    "wof:name":"Lawagara",
    "wof:placetype":"locality",
    "wof:population":134
},
  "geometry": {"coordinates":[84.506479,23.78803],"type":"Point"}
}