{
  "type": "Feature",
  "properties": {
    "gn:admin1_code":"21",
    "gn:admin2_code":"396.0",
    "gn:asciiname":"Kaliyaguda",
    "gn:country_code":"IN",
    "gn:dem":427,
    "gn:feature_class":"P",
    "gn:feature_code":"PPL",
    "gn:name":"Kaliyaguda",
    "gn:population":0,
    "gn:timezone":"Asia/Kolkata",
    "iso:country":"IN",
    "wof:name":"Kaliyaguda",
    "wof:placetype":"locality"
},
  "geometry": {"coordinates":[83.27002,19.53164],"type":"Point"}
}