{
  "type": "Feature",
  "properties": {
    "iso:country":"IN",
    "ks:ks_name":"Puthya",
    "ks:ks_pop":75,
    "ks:ks_type":"HABITATION",
    "name:eng_x_preferred":[
        "Puthya"
    ],
    "wof:name":"Puthya",
    "wof:placetype":"locality",
    "wof:population":75
},
  "geometry": {"coordinates":[75.319425,13.022205],"type":"Point"}
}