{
  "type": "Feature",
  "properties": {
    "iso:country":"IN",
    "ks:ks_alt_nam":"paromhatu",
    "ks:ks_name":"Paromhatu",
    "ks:ks_pop":92,
    "ks:ks_type":"HABITATION",
    "name:eng_x_preferred":[
        "Paromhatu"
    ],
    "wof:name":"Paromhatu",
    "wof:placetype":"locality",
    "wof:population":92
},
  "geometry": {"coordinates":[85.26890899999999,22.48298],"type":"Point"}
}