{
  "type": "Feature",
  "properties": {
    "iso:country":"IN",
    "ks:ks_name":"Akhuari",
    "ks:ks_pop":347,
    "ks:ks_type":"VILLAGE",
    "ks:ks_uagg_main":0,
    "name:eng_x_preferred":[
        "Akhuari"
    ],
    "wof:name":"Akhuari",
    "wof:placetype":"neighbourhood",
    "wof:population":347
},
  "geometry": {"coordinates":[87.04148600000001,21.730201],"type":"Point"}
}