{
  "type": "Feature",
  "properties": {
    "gn:admin1_code":"19.0",
    "gn:admin2_code":"571.0",
    "gn:asciiname":"Timmalapura",
    "gn:country_code":"IN",
    "gn:dem":790,
    "gn:feature_class":"P",
    "gn:feature_code":"PPL",
    "gn:name":"Timmal\u0101pura",
    "gn:population":0,
    "gn:timezone":"Asia/Kolkata",
    "iso:country":"IN",
    "wof:name":"Timmalapura",
    "wof:placetype":"locality"
},
  "geometry": {"coordinates":[77.11835000000001,13.64425],"type":"Point"}
}