{
  "type": "Feature",
  "properties": {
    "gn:admin1_code":"16.0",
    "gn:admin2_code":"497.0",
    "gn:asciiname":"Malvan",
    "gn:country_code":"IN",
    "gn:dem":214,
    "gn:feature_class":"P",
    "gn:feature_code":"PPL",
    "gn:name":"Malv\u0101n",
    "gn:population":0,
    "gn:timezone":"Asia/Kolkata",
    "iso:country":"IN",
    "name:ben_x_preferred":[
        "\u09ae\u09be\u09b2\u0993\u09af\u09bc\u09be\u09a8"
    ],
    "name:bpy_x_preferred":[
        "\u09ae\u09be\u09b2\u09f1\u09be\u09a8"
    ],
    "name:ceb_x_preferred":[
        "M\u0101lvan"
    ],
    "name:hin_x_preferred":[
        "\u092e\u093e\u0932\u0935\u0928"
    ],
    "name:ita_x_preferred":[
        "Malwan"
    ],
    "name:mar_x_preferred":[
        "\u092e\u093e\u0932\u0935\u0923"
    ],
    "name:msa_x_preferred":[
        "Malwan"
    ],
    "name:new_x_preferred":[
        "\u092e\u0932\u094d\u0935\u093e\u0928"
    ],
    "name:nld_x_preferred":[
        "Malwan"
    ],
    "name:por_x_preferred":[
        "Malwan"
    ],
    "name:swe_x_preferred":[
        "M\u0101lvan"
    ],
    "name:urd_x_preferred":[
        "\u0645\u0627\u0644\u0648\u0646"
    ],
    "name:vie_x_preferred":[
        "Malwan"
    ],
    "name:zho_x_preferred":[
        "\u9a6c\u5c14\u4e07"
    ],
    "wof:name":"Malvan",
    "wof:placetype":"locality"
},
  "geometry": {"coordinates":[74.05531999999999,21.29073],"type":"Point"}
}