{
  "type": "Feature",
  "properties": {
    "iso:country":"IN",
    "ks:ks_alt_nam":"Biradar tota",
    "ks:ks_name":"Biradar Tota",
    "ks:ks_pop":215,
    "ks:ks_type":"HABITATION",
    "name:eng_x_preferred":[
        "Biradar Tota"
    ],
    "wof:name":"Biradar Tota",
    "wof:placetype":"locality",
    "wof:population":215
},
  "geometry": {"coordinates":[75.011425,16.791835],"type":"Point"}
}