{
  "type": "Feature",
  "properties": {
    "gn:admin1_code":"34.0",
    "gn:asciiname":"Sardawa",
    "gn:country_code":"IN",
    "gn:dem":245,
    "gn:feature_class":"P",
    "gn:feature_code":"PPL",
    "gn:name":"Sard\u0101w\u0101",
    "gn:population":0,
    "gn:timezone":"Asia/Kolkata",
    "iso:country":"IN",
    "ks:ks_name":"Sardama",
    "ks:ks_pop":567,
    "ks:ks_type":"HABITATION",
    "name:eng_x_preferred":[
        "Sardama"
    ],
    "name:eng_x_variant":[
        "Sardawa"
    ],
    "wof:name":"Sardama",
    "wof:placetype":"locality",
    "wof:population":567
},
  "geometry": {"coordinates":[84.48366799999999,24.316159],"type":"Point"}
}