{
  "type": "Feature",
  "properties": {
    "iso:country":"IN",
    "ks:ks_name":"Baloosingh Ki Dhani",
    "ks:ks_pop":760,
    "ks:ks_type":"VILLAGE",
    "name:eng_x_preferred":[
        "Baloosingh Ki Dhani"
    ],
    "wof:name":"Baloosingh Ki Dhani",
    "wof:placetype":"locality",
    "wof:population":760
},
  "geometry": {"coordinates":[71.9332,26.690647],"type":"Point"}
}