{
  "type": "Feature",
  "properties": {
    "gn:admin1_code":"37",
    "gn:admin2_code":"405.0",
    "gn:asciiname":"Parsapali",
    "gn:country_code":"IN",
    "gn:dem":247,
    "gn:feature_class":"P",
    "gn:feature_code":"PPL",
    "gn:name":"Parsap\u0101li",
    "gn:population":0,
    "gn:timezone":"Asia/Kolkata",
    "iso:country":"IN",
    "ks:ks_alt_nam":"Parsap\u0101li",
    "ks:ks_name":"Parsapali",
    "ks:ks_type":"VILLAGE",
    "ks:ks_uagg_main":0,
    "name:eng_x_preferred":[
        "Parsapali"
    ],
    "name:eng_x_variant":[
        "Parsap\u0101li"
    ],
    "wof:name":"Parsapali",
    "wof:placetype":"neighbourhood"
},
  "geometry": {"coordinates":[82.778944,21.927121],"type":"Point"}
}