{
  "type": "Feature",
  "properties": {
    "iso:country":"IN",
    "ks:ks_name":"Somnath Ingalewasti",
    "ks:ks_pop":103,
    "ks:ks_type":"HABITATION",
    "name:eng_x_preferred":[
        "Somnath Ingalewasti"
    ],
    "wof:name":"Somnath Ingalewasti",
    "wof:placetype":"locality",
    "wof:population":103
},
  "geometry": {"coordinates":[75.029094,18.333789],"type":"Point"}
}