{
  "type": "Feature",
  "properties": {
    "gn:admin1_code":"35.0",
    "gn:admin2_code":"451",
    "gn:asciiname":"Gosalpur",
    "gn:country_code":"IN",
    "gn:dem":398,
    "gn:feature_class":"P",
    "gn:feature_code":"PPL",
    "gn:name":"Gosalpur",
    "gn:population":0,
    "gn:timezone":"Asia/Kolkata",
    "iso:country":"IN",
    "wof:name":"Gosalpur",
    "wof:placetype":"neighbourhood"
},
  "geometry": {"coordinates":[80.06046000000001,23.39802],"type":"Point"}
}