{
  "type": "Feature",
  "properties": {
    "gn:admin1_code":"38",
    "gn:admin2_code":"358.0",
    "gn:asciiname":"Bhitihara",
    "gn:country_code":"IN",
    "gn:dem":178,
    "gn:feature_class":"P",
    "gn:feature_code":"PPL",
    "gn:name":"Bhitih\u0101ra",
    "gn:population":0,
    "gn:timezone":"Asia/Kolkata",
    "iso:country":"IN",
    "ks:ks_alt_nam":"Bhitih\u0101ra",
    "ks:ks_name":"Bhitihara",
    "ks:ks_pop":917,
    "ks:ks_type":"VILLAGE",
    "name:eng_x_preferred":[
        "Bhitihara"
    ],
    "name:eng_x_variant":[
        "Bhitih\u0101ra"
    ],
    "wof:name":"Bhitihara",
    "wof:placetype":"locality",
    "wof:population":917
},
  "geometry": {"coordinates":[83.84819299999999,24.264614],"type":"Point"}
}