{
  "type": "Feature",
  "properties": {
    "iso:country":"IN",
    "ks:ks_name":"Triveni Purwa",
    "ks:ks_pop":64,
    "ks:ks_type":"HABITATION",
    "ks:ks_uagg_main":0,
    "name:eng_x_preferred":[
        "Triveni Purwa"
    ],
    "wof:name":"Triveni Purwa",
    "wof:placetype":"neighbourhood",
    "wof:population":64
},
  "geometry": {"coordinates":[82.078417,27.418362],"type":"Point"}
}