{
  "type": "Feature",
  "properties": {
    "iso:country":"IN",
    "ks:ks_name":"Kunuila",
    "ks:ks_pop":432,
    "ks:ks_type":"HABITATION",
    "name:eng_x_preferred":[
        "Kunuila"
    ],
    "wof:name":"Kunuila",
    "wof:placetype":"locality",
    "wof:population":432
},
  "geometry": {"coordinates":[76.800798,8.937305],"type":"Point"}
}