{
  "type": "Feature",
  "properties": {
    "iso:country":"IN",
    "ks:ks_name":"Sangamwadi",
    "ks:ks_pop":375,
    "ks:ks_type":"HABITATION",
    "name:eng_x_preferred":[
        "Sangamwadi"
    ],
    "wof:name":"Sangamwadi",
    "wof:placetype":"locality",
    "wof:population":375
},
  "geometry": {"coordinates":[77.25237,18.5049],"type":"Point"}
}