{
  "type": "Feature",
  "properties": {
    "iso:country":"IN",
    "ks:ks_name":"Dolamba",
    "ks:ks_pop":0,
    "ks:ks_type":"VILLAGE",
    "name:eng_x_preferred":[
        "Dolamba"
    ],
    "wof:name":"Dolamba",
    "wof:placetype":"locality",
    "wof:population":0
},
  "geometry": {"coordinates":[84.375269,19.362197],"type":"Point"}
}