{
  "type": "Feature",
  "properties": {
    "gn:admin1_code":"39.0",
    "gn:asciiname":"Barta",
    "gn:country_code":"IN",
    "gn:dem":913,
    "gn:feature_class":"P",
    "gn:feature_code":"PPL",
    "gn:name":"Barta",
    "gn:population":0,
    "gn:timezone":"Asia/Kolkata",
    "iso:country":"IN",
    "wof:name":"Barta",
    "wof:placetype":"locality"
},
  "geometry": {"coordinates":[77.73016,30.59806],"type":"Point"}
}