{
  "type": "Feature",
  "properties": {
    "iso:country":"IN",
    "ks:ks_name":"Palia Nangal",
    "ks:ks_pop":398,
    "ks:ks_type":"VILLAGE",
    "name:eng_x_preferred":[
        "Palia Nangal"
    ],
    "wof:name":"Palia Nangal",
    "wof:placetype":"locality",
    "wof:population":398
},
  "geometry": {"coordinates":[75.017228,32.03113],"type":"Point"}
}