{
  "type": "Feature",
  "properties": {
    "iso:country":"IN",
    "ks:ks_name":"Gajinkikere",
    "ks:ks_pop":65,
    "ks:ks_type":"HABITATION",
    "name:eng_x_preferred":[
        "Gajinkikere"
    ],
    "wof:name":"Gajinkikere",
    "wof:placetype":"locality",
    "wof:population":65
},
  "geometry": {"coordinates":[74.48618999999999,14.30496],"type":"Point"}
}