{
  "type": "Feature",
  "properties": {
    "iso:country":"IN",
    "ks:ks_name":"Nayagaon Tanka",
    "ks:ks_pop":360,
    "ks:ks_type":"HABITATION",
    "name:eng_x_preferred":[
        "Nayagaon Tanka"
    ],
    "wof:name":"Nayagaon Tanka",
    "wof:placetype":"locality",
    "wof:population":360
},
  "geometry": {"coordinates":[78.014725,25.947079],"type":"Point"}
}