{
  "type": "Feature",
  "properties": {
    "iso:country":"IN",
    "ks:ks_name":"Dakhin Putakallong",
    "ks:ks_pop":2039,
    "ks:ks_type":"HABITATION",
    "name:eng_x_preferred":[
        "Dakhin Putakallong"
    ],
    "wof:name":"Dakhin Putakallong",
    "wof:placetype":"locality",
    "wof:population":2039
},
  "geometry": {"coordinates":[92.868494,26.500231],"type":"Point"}
}