{
  "type": "Feature",
  "properties": {
    "gn:admin1_code":"37",
    "gn:admin2_code":"413.0",
    "gn:asciiname":"Turge",
    "gn:country_code":"IN",
    "gn:dem":353,
    "gn:feature_class":"P",
    "gn:feature_code":"PPL",
    "gn:name":"Turge",
    "gn:population":0,
    "gn:timezone":"Asia/Kolkata",
    "iso:country":"IN",
    "ks:ks_name":"Tudge",
    "ks:ks_pop":560,
    "ks:ks_type":"HABITATION",
    "name:eng_x_preferred":[
        "Tudge"
    ],
    "name:eng_x_variant":[
        "Turge"
    ],
    "wof:name":"Tudge",
    "wof:placetype":"locality",
    "wof:population":560
},
  "geometry": {"coordinates":[80.987917,20.276232],"type":"Point"}
}