{
  "type": "Feature",
  "properties": {
    "iso:country":"IN",
    "ks:ks_alt_nam":"Kramsa gaon",
    "ks:ks_name":"Kramsa Gaon",
    "ks:ks_pop":115,
    "ks:ks_type":"HABITATION",
    "ks:ks_uagg_main":0,
    "name:eng_x_preferred":[
        "Kramsa Gaon"
    ],
    "wof:name":"Kramsa Gaon",
    "wof:placetype":"neighbourhood",
    "wof:population":115
},
  "geometry": {"coordinates":[92.784953,25.900588],"type":"Point"}
}