{
  "type": "Feature",
  "properties": {
    "iso:country":"IN",
    "ks:ks_name":"Tikari",
    "ks:ks_pop":195,
    "ks:ks_type":"VILLAGE",
    "name:eng_x_preferred":[
        "Tikari"
    ],
    "wof:name":"Tikari",
    "wof:placetype":"locality",
    "wof:population":195
},
  "geometry": {"coordinates":[83.98872,25.747619],"type":"Point"}
}