{
  "type": "Feature",
  "properties": {
    "iso:country":"IN",
    "ks:ks_name":"Amani Arasikere",
    "ks:ks_pop":25,
    "ks:ks_type":"HABITATION",
    "name:eng_x_preferred":[
        "Amani Arasikere"
    ],
    "wof:name":"Amani Arasikere",
    "wof:placetype":"locality",
    "wof:population":25
},
  "geometry": {"coordinates":[78.05123399999999,12.938144],"type":"Point"}
}