{
  "type": "Feature",
  "properties": {
    "iso:country":"IN",
    "ks:ks_name":"Patilpada",
    "ks:ks_pop":63,
    "ks:ks_type":"HABITATION",
    "name:eng_x_preferred":[
        "Patilpada"
    ],
    "wof:name":"Patilpada",
    "wof:placetype":"locality",
    "wof:population":63
},
  "geometry": {"coordinates":[73.210556,19.498889],"type":"Point"}
}