{
  "type": "Feature",
  "properties": {
    "iso:country":"IN",
    "ks:ks_name":"Matiyarawa Chota",
    "ks:ks_pop":179,
    "ks:ks_type":"HABITATION",
    "ks:ks_uagg_main":0,
    "name:eng_x_preferred":[
        "Matiyarawa Chota"
    ],
    "wof:name":"Matiyarawa Chota",
    "wof:placetype":"neighbourhood",
    "wof:population":179
},
  "geometry": {"coordinates":[83.509298,27.127003],"type":"Point"}
}