{
  "type": "Feature",
  "properties": {
    "iso:country":"IN",
    "ks:ks_alt_nam":"Rudakhya bam",
    "ks:ks_name":"Rudakhya Bam",
    "ks:ks_pop":319,
    "ks:ks_type":"HABITATION",
    "ks:ks_uagg_main":0,
    "name:eng_x_preferred":[
        "Rudakhya Bam"
    ],
    "wof:name":"Rudakhya Bam",
    "wof:placetype":"neighbourhood",
    "wof:population":319
},
  "geometry": {"coordinates":[94.704576,27.153567],"type":"Point"}
}