{
  "type": "Feature",
  "properties": {
    "iso:country":"IN",
    "ks:ks_name":"Kelagin Khandgar",
    "ks:ks_pop":52,
    "ks:ks_type":"HABITATION",
    "name:eng_x_preferred":[
        "Kelagin Khandgar"
    ],
    "wof:name":"Kelagin Khandgar",
    "wof:placetype":"locality",
    "wof:population":52
},
  "geometry": {"coordinates":[74.427909,14.529903],"type":"Point"}
}