{
  "type": "Feature",
  "properties": {
    "iso:country":"IN",
    "ks:ks_name":"K Padmanavpur",
    "ks:ks_pop":947,
    "ks:ks_type":"HABITATION",
    "name:eng_x_preferred":[
        "K Padmanavpur"
    ],
    "wof:name":"K Padmanavpur",
    "wof:placetype":"locality",
    "wof:population":947
},
  "geometry": {"coordinates":[84.566891,19.351227],"type":"Point"}
}