{
  "type": "Feature",
  "properties": {
    "iso:country":"IN",
    "ks:ks_alt_nam":"BALUMUDIYA",
    "ks:ks_name":"Balumudiya",
    "ks:ks_pop":264,
    "ks:ks_type":"HABITATION",
    "name:eng_x_preferred":[
        "Balumudiya"
    ],
    "wof:name":"Balumudiya",
    "wof:placetype":"locality",
    "wof:population":264
},
  "geometry": {"coordinates":[85.652502,22.56067],"type":"Point"}
}