{
  "type": "Feature",
  "properties": {
    "gn:admin1_code":"36",
    "gn:admin2_code":"198.0",
    "gn:asciiname":"Chandapur",
    "gn:country_code":"IN",
    "gn:dem":90,
    "gn:feature_class":"P",
    "gn:feature_code":"PPL",
    "gn:name":"Chand\u0101pur",
    "gn:population":0,
    "gn:timezone":"Asia/Kolkata",
    "iso:country":"IN",
    "wof:name":"Chandapur",
    "wof:placetype":"locality"
},
  "geometry": {"coordinates":[82.34855,25.29505],"type":"Point"}
}