{
  "type": "Feature",
  "properties": {
    "iso:country":"IN",
    "ks:ks_name":"Vazhichal",
    "ks:ks_pop":156,
    "ks:ks_type":"HABITATION",
    "ks:ks_uagg_main":0,
    "name:eng_x_preferred":[
        "Vazhichal"
    ],
    "wof:name":"Vazhichal",
    "wof:placetype":"neighbourhood",
    "wof:population":156
},
  "geometry": {"coordinates":[76.308487,10.268443],"type":"Point"}
}