{
  "type": "Feature",
  "properties": {
    "iso:country":"IN",
    "ks:ks_name":"Pengawan",
    "ks:ks_pop":147,
    "ks:ks_type":"VILLAGE",
    "name:eng_x_preferred":[
        "Pengawan"
    ],
    "wof:name":"Pengawan",
    "wof:placetype":"locality",
    "wof:population":147
},
  "geometry": {"coordinates":[77.772029,23.250691],"type":"Point"}
}