{
  "type": "Feature",
  "properties": {
    "gn:admin1_code":"35.0",
    "gn:admin2_code":"464.0",
    "gn:asciiname":"Naharpara",
    "gn:country_code":"IN",
    "gn:dem":461,
    "gn:feature_class":"P",
    "gn:feature_code":"PPL",
    "gn:name":"N\u0101harp\u0101ra",
    "gn:population":0,
    "gn:timezone":"Asia/Kolkata",
    "iso:country":"IN",
    "ks:ks_name":"Naharpura",
    "ks:ks_pop":2266,
    "ks:ks_type":"HABITATION",
    "name:eng_x_preferred":[
        "Naharpura"
    ],
    "name:eng_x_variant":[
        "Naharpara"
    ],
    "wof:name":"Naharpura",
    "wof:placetype":"locality",
    "wof:population":2266
},
  "geometry": {"coordinates":[74.96672100000001,23.006123],"type":"Point"}
}