{
  "type": "Feature",
  "properties": {
    "gn:admin1_code":"36",
    "gn:admin2_code":"159.0",
    "gn:asciiname":"Jaitpur",
    "gn:country_code":"IN",
    "gn:dem":154,
    "gn:feature_class":"P",
    "gn:feature_code":"PPL",
    "gn:name":"Ja\u012btpur",
    "gn:population":0,
    "gn:timezone":"Asia/Kolkata",
    "iso:country":"IN",
    "name:fra_x_preferred":[
        "Jaitpur"
    ],
    "name:urd_x_preferred":[
        "\u062c\u06cc\u062a\u067e\u0648\u0631"
    ],
    "wof:name":"Jaitpur",
    "wof:placetype":"locality"
},
  "geometry": {"coordinates":[79.43526,27.26235],"type":"Point"}
}