{
  "type": "Feature",
  "properties": {
    "gn:admin1_code":"38.0",
    "gn:admin2_code":"353.0",
    "gn:asciiname":"Jamchua",
    "gn:country_code":"IN",
    "gn:dem":80,
    "gn:feature_class":"P",
    "gn:feature_code":"PPL",
    "gn:name":"J\u0101mchua",
    "gn:population":0,
    "gn:timezone":"Asia/Kolkata",
    "iso:country":"IN",
    "ks:ks_alt_nam":"J\u0101mchua",
    "ks:ks_name":"Jamchua",
    "ks:ks_pop":143,
    "ks:ks_type":"VILLAGE",
    "name:eng_x_preferred":[
        "Jamchua"
    ],
    "name:eng_x_variant":[
        "J\u0101mchua"
    ],
    "wof:name":"Jamchua",
    "wof:placetype":"locality",
    "wof:population":143
},
  "geometry": {"coordinates":[87.69480799999999,24.404284],"type":"Point"}
}