{
  "type": "Feature",
  "properties": {
    "iso:country":"IN",
    "name:eng_x_preferred":[
        "Adhoiwala"
    ],
    "name:unk_x_variant":[
        "Adhoiwala"
    ],
    "qs:gn_adm0_cc":"IN",
    "qs:gn_local":1273313,
    "qs:gn_nam_loc":"Dehra Dun",
    "qs:gn_namadm1":"39",
    "qs:local_max":215,
    "qs:local_sum":235,
    "qs:localhoods":2,
    "qs:name":"Adhoiwala",
    "qs:name_adm0":"India",
    "qs:name_adm1":"Uttarakhand",
    "qs:name_adm2":"Dehradun",
    "qs:name_local":"Dehradun",
    "qs:photo_max":8,
    "qs:photo_sum":20,
    "qs:placetype":"Suburb",
    "qs:quad_count":7,
    "qs:woe_adm0":23424848,
    "qs:woe_adm1":20070462,
    "qs:woe_adm2":12586735,
    "qs:woe_lau":0,
    "qs:woe_local":2294972,
    "qs:woe_ver":"7.10.0",
    "wof:lang":[
        "eng"
    ],
    "wof:name":"Adhoiwala",
    "wof:placetype":"neighbourhood"
},
  "geometry": {"coordinates":[78.04330400000001,30.337324],"type":"Point"}
}