{
  "type": "Feature",
  "properties": {
    "iso:country":"IN",
    "name:ara_x_preferred":[
        "\u0623\u062f\u0647\u0648\u064a\u0641\u0627\u0644\u0627"
    ],
    "name:ben_bn_x_preferred":[
        "\u0985\u09a7\u09c8\u0993\u09df\u09be\u09b2\u09be"
    ],
    "name:ben_in_x_preferred":[
        "\u0985\u09a7\u09c8\u0993\u09df\u09be\u09b2\u09be"
    ],
    "name:eng_x_preferred":[
        "Adhoiwala"
    ],
    "name:guj_x_preferred":[
        "\u0a85\u0aa7\u0acb\u0a87\u0ab5\u0abe\u0ab2\u0abe"
    ],
    "name:hin_x_preferred":[
        "\u0905\u0927\u094b\u0908\u0935\u093e\u0932\u093e"
    ],
    "name:kan_x_preferred":[
        "\u0c85\u0ca6\u0ccb\u0caf\u0ccd"
    ],
    "name:mal_x_preferred":[
        "\u0d05\u0d27\u0d4b\u0d35\u0d3e\u0d32"
    ],
    "name:mar_x_preferred":[
        "\u0905\u0927\u094b\u0908\u0935\u093e\u0932\u093e"
    ],
    "name:pan_x_preferred":[
        "\u0a05\u0a27\u0a4c\u0a07\u0a35\u0a3e\u0a32\u0a3e"
    ],
    "name:tam_x_preferred":[
        "\u0b85\u0ba4\u0bcd\u0bb9\u0bcb\u0baf\u0bcd\u0bb5\u0bbe\u0bb2\u0bbe"
    ],
    "name:tel_x_preferred":[
        "\u0c05\u0c27\u0c4b\u0c2f\u0c4d"
    ],
    "name:urd_x_preferred":[
        "\u0627\u062f\u06be\u0648\u0626\u06cc \u0648\u0627\u0644\u0627"
    ],
    "qs:gn_adm0_cc":"IN",
    "qs:gn_local":1273313,
    "qs:gn_nam_loc":"Dehra Dun",
    "qs:gn_namadm1":"39",
    "qs:local_max":215,
    "qs:local_sum":235,
    "qs:localhoods":2,
    "qs:name":"Adhoiwala",
    "qs:name_adm0":"India",
    "qs:name_adm1":"Uttarakhand",
    "qs:name_adm2":"Dehradun",
    "qs:name_local":"Dehradun",
    "qs:photo_max":8,
    "qs:photo_sum":20,
    "qs:placetype":"Suburb",
    "qs:quad_count":7,
    "qs:woe_adm0":23424848,
    "qs:woe_adm1":20070462,
    "qs:woe_adm2":12586735,
    "qs:woe_lau":0,
    "qs:woe_local":2294972,
    "qs:woe_ver":"7.10.0",
    "wof:lang":[
        "eng"
    ],
    "wof:name":"Adhoiwala",
    "wof:placetype":"neighbourhood"
},
  "geometry": {"coordinates":[78.04330400000001,30.337324],"type":"Point"}
}