{
  "type": "Feature",
  "properties": {
    "iso:country":"IN",
    "ks:ks_name":"Khankhai",
    "ks:ks_pop":354,
    "ks:ks_type":"VILLAGE",
    "name:eng_x_preferred":[
        "Khankhai"
    ],
    "wof:name":"Khankhai",
    "wof:placetype":"locality",
    "wof:population":354
},
  "geometry": {"coordinates":[74.81724699999999,23.496556],"type":"Point"}
}