{
  "type": "Feature",
  "properties": {
    "gn:admin1_code":"2.0",
    "gn:admin2_code":"550",
    "gn:asciiname":"Kodavaluru",
    "gn:country_code":"IN",
    "gn:dem":19,
    "gn:feature_class":"P",
    "gn:feature_code":"PPL",
    "gn:name":"Kodaval\u016bru",
    "gn:population":0,
    "gn:timezone":"Asia/Kolkata",
    "iso:country":"IN",
    "name:ceb_x_preferred":[
        "Kodaval\u016bru"
    ],
    "name:new_x_preferred":[
        "\u0915\u094b\u0921\u0935\u0932\u0942\u0930\u0941 \u092e\u0923\u094d\u0921\u0932"
    ],
    "name:swe_x_preferred":[
        "Kodaval\u016bru"
    ],
    "name:tel_x_preferred":[
        "\u0c15\u0c4a\u0c21\u0c35\u0c32\u0c42\u0c30\u0c41"
    ],
    "name:und_x_variant":[
        "Kodavalur"
    ],
    "wof:name":"Kodavaluru",
    "wof:placetype":"locality"
},
  "geometry": {"coordinates":[80.00341,14.56689],"type":"Point"}
}