{
  "type": "Feature",
  "properties": {
    "iso:country":"IN",
    "ks:ks_name":"Jambudiya",
    "ks:ks_pop":4209,
    "ks:ks_type":"VILLAGE",
    "ks:ks_uagg_main":0,
    "name:eng_x_preferred":[
        "Jambudiya"
    ],
    "wof:name":"Jambudiya",
    "wof:placetype":"neighbourhood",
    "wof:population":4209
},
  "geometry": {"coordinates":[70.910369,22.785961],"type":"Point"}
}