{
  "type": "Feature",
  "properties": {
    "iso:country":"IN",
    "ks:ks_alt_nam":"Atarokotajhar II",
    "ks:ks_name":"Atarokotajhar Ii",
    "ks:ks_pop":38,
    "ks:ks_type":"HABITATION",
    "name:eng_x_preferred":[
        "Atarokotajhar Ii"
    ],
    "wof:name":"Atarokotajhar Ii",
    "wof:placetype":"locality",
    "wof:population":38
},
  "geometry": {"coordinates":[89.921404,26.135366],"type":"Point"}
}