{
  "type": "Feature",
  "properties": {
    "iso:country":"IN",
    "ks:ks_alt_nam":"Kan\u0101bira",
    "ks:ks_name":"Kanabira",
    "ks:ks_type":"VILLAGE",
    "name:eng_x_preferred":[
        "Kanabira"
    ],
    "name:eng_x_variant":[
        "Kan\u0101bira"
    ],
    "wof:name":"Kanabira",
    "wof:placetype":"locality"
},
  "geometry": {"coordinates":[84.46184599999999,21.849867],"type":"Point"}
}