{
  "type": "Feature",
  "properties": {
    "iso:country":"IN",
    "ks:ks_alt_nam":"dulare purwa",
    "ks:ks_name":"Dulare Purwa",
    "ks:ks_pop":88,
    "ks:ks_type":"HABITATION",
    "ks:ks_uagg_main":0,
    "name:eng_x_preferred":[
        "Dulare Purwa"
    ],
    "wof:name":"Dulare Purwa",
    "wof:placetype":"neighbourhood",
    "wof:population":88
},
  "geometry": {"coordinates":[81.628032,27.370002],"type":"Point"}
}