{
  "type": "Feature",
  "properties": {
    "gn:admin1_code":"19.0",
    "gn:admin2_code":"583.0",
    "gn:asciiname":"Yadehalli",
    "gn:country_code":"IN",
    "gn:dem":925,
    "gn:feature_class":"P",
    "gn:feature_code":"PPL",
    "gn:name":"Yadehalli",
    "gn:population":0,
    "gn:timezone":"Asia/Kolkata",
    "iso:country":"IN",
    "wof:name":"Yadehalli",
    "wof:placetype":"locality"
},
  "geometry": {"coordinates":[77.25424,13.21415],"type":"Point"}
}