{
  "type": "Feature",
  "properties": {
    "iso:country":"IN",
    "ks:ks_name":"Bhatitola",
    "ks:ks_pop":272,
    "ks:ks_type":"HABITATION",
    "name:eng_x_preferred":[
        "Bhatitola"
    ],
    "wof:name":"Bhatitola",
    "wof:placetype":"locality",
    "wof:population":272
},
  "geometry": {"coordinates":[84.7196,22.249408],"type":"Point"}
}