{
  "type": "Feature",
  "properties": {
    "gn:admin1_code":"2.0",
    "gn:admin2_code":"545.0",
    "gn:asciiname":"Nukaletivada",
    "gn:country_code":"IN",
    "gn:dem":510,
    "gn:feature_class":"P",
    "gn:feature_code":"PPL",
    "gn:name":"N\u016bkaletiv\u0101da",
    "gn:population":0,
    "gn:timezone":"Asia/Kolkata",
    "iso:country":"IN",
    "wof:name":"Nukaletivada",
    "wof:placetype":"locality"
},
  "geometry": {"coordinates":[81.72235999999999,17.71844],"type":"Point"}
}