{
  "type": "Feature",
  "properties": {
    "gn:admin1_code":"2.0",
    "gn:admin2_code":"545.0",
    "gn:asciiname":"Nukaletivada",
    "gn:country_code":"IN",
    "gn:dem":510,
    "gn:feature_class":"P",
    "gn:feature_code":"PPL",
    "gn:name":"N\u016bkaletiv\u0101da",
    "gn:population":0,
    "gn:timezone":"Asia/Kolkata",
    "iso:country":"IN",
    "ks:ks_alt_nam":"N\u016bkaletiv\u0101da",
    "ks:ks_name":"Nukaletivada",
    "ks:ks_pop":58,
    "ks:ks_type":"VILLAGE",
    "name:eng_x_preferred":[
        "Nukaletivada"
    ],
    "name:eng_x_variant":[
        "N\u016bkaletiv\u0101da"
    ],
    "wof:name":"Nukaletivada",
    "wof:placetype":"locality",
    "wof:population":58
},
  "geometry": {"coordinates":[81.722433,17.718561],"type":"Point"}
}