{
  "type": "Feature",
  "properties": {
    "gn:admin1_code":"35.0",
    "gn:admin2_code":"423.0",
    "gn:asciiname":"Panchor",
    "gn:country_code":"IN",
    "gn:dem":211,
    "gn:feature_class":"P",
    "gn:feature_code":"PPL",
    "gn:name":"P\u0101nchor",
    "gn:population":0,
    "gn:timezone":"Asia/Kolkata",
    "iso:country":"IN",
    "ks:ks_name":"Pachor",
    "ks:ks_pop":80,
    "ks:ks_type":"HABITATION",
    "name:eng_x_preferred":[
        "Pachor"
    ],
    "name:eng_x_variant":[
        "Panchor"
    ],
    "name:msa_x_preferred":[
        "Panchor"
    ],
    "wof:name":"Pachor",
    "wof:placetype":"locality",
    "wof:population":80
},
  "geometry": {"coordinates":[78.26776599999999,25.779577],"type":"Point"}
}