{
  "type": "Feature",
  "properties": {
    "gn:admin1_code":"2",
    "gn:admin2_code":"544.0",
    "gn:asciiname":"Chinnapalem",
    "gn:country_code":"IN",
    "gn:dem":968,
    "gn:feature_class":"P",
    "gn:feature_code":"PPL",
    "gn:name":"Chinnap\u0101lem",
    "gn:population":0,
    "gn:timezone":"Asia/Kolkata",
    "iso:country":"IN",
    "wof:name":"Chinnapalem",
    "wof:placetype":"locality"
},
  "geometry": {"coordinates":[82.5737,17.87475],"type":"Point"}
}