{
  "type": "Feature",
  "properties": {
    "iso:country":"IN",
    "ks:ks_name":"Singoti",
    "ks:ks_pop":197,
    "ks:ks_type":"VILLAGE",
    "name:eng_x_preferred":[
        "Singoti"
    ],
    "wof:name":"Singoti",
    "wof:placetype":"locality",
    "wof:population":197
},
  "geometry": {"coordinates":[78.355664,30.728381],"type":"Point"}
}