{
  "type": "Feature",
  "properties": {
    "gn:admin1_code":"19",
    "gn:admin2_code":"580.0",
    "gn:asciiname":"Budanur",
    "gn:country_code":"IN",
    "gn:dem":473,
    "gn:feature_class":"P",
    "gn:feature_code":"PPL",
    "gn:name":"Budan\u016br",
    "gn:population":0,
    "gn:timezone":"Asia/Kolkata",
    "iso:country":"IN",
    "name:vie_x_preferred":[
        "Budanur"
    ],
    "wof:name":"Budanur",
    "wof:placetype":"neighbourhood"
},
  "geometry": {"coordinates":[76.65364,16.66466],"type":"Point"}
}