{
  "type": "Feature",
  "properties": {
    "gn:admin1_code":"36",
    "gn:admin2_code":"185.0",
    "gn:asciiname":"Kaithaulia Kunwar",
    "gn:country_code":"IN",
    "gn:dem":103,
    "gn:feature_class":"P",
    "gn:feature_code":"PPL",
    "gn:name":"Kaithaulia Kunwar",
    "gn:population":0,
    "gn:timezone":"Asia/Kolkata",
    "iso:country":"IN",
    "wof:name":"Kaithaulia Kunwar",
    "wof:placetype":"neighbourhood"
},
  "geometry": {"coordinates":[82.31977999999999,26.94369],"type":"Point"}
}