{
  "type": "Feature",
  "properties": {
    "iso:country":"IN",
    "ks:ks_name":"Radhaballavpur",
    "ks:ks_pop":3056,
    "ks:ks_type":"VILLAGE",
    "ks:ks_uagg_main":0,
    "name:eng_x_preferred":[
        "Radhaballavpur"
    ],
    "wof:name":"Radhaballavpur",
    "wof:placetype":"neighbourhood",
    "wof:population":3056
},
  "geometry": {"coordinates":[88.71881399999999,22.194395],"type":"Point"}
}