{
  "type": "Feature",
  "properties": {
    "iso:country":"IN",
    "ks:ks_name":"Melina Kurubarakunte",
    "ks:ks_pop":322,
    "ks:ks_type":"HABITATION",
    "name:eng_x_preferred":[
        "Melina Kurubarakunte"
    ],
    "wof:name":"Melina Kurubarakunte",
    "wof:placetype":"locality",
    "wof:population":322
},
  "geometry": {"coordinates":[77.732406,13.264339],"type":"Point"}
}