{
  "type": "Feature",
  "properties": {
    "iso:country":"IN",
    "ks:ks_name":"Debdaya Kumbharbadi",
    "ks:ks_pop":201,
    "ks:ks_type":"VILLAGE",
    "name:eng_x_preferred":[
        "Debdaya Kumbharbadi"
    ],
    "wof:name":"Debdaya Kumbharbadi",
    "wof:placetype":"locality",
    "wof:population":201
},
  "geometry": {"coordinates":[83.448544,19.476587],"type":"Point"}
}