{
  "type": "Feature",
  "properties": {
    "gn:admin1_code":"16.0",
    "gn:admin2_code":"516",
    "gn:asciiname":"Kolgaon",
    "gn:country_code":"IN",
    "gn:dem":528,
    "gn:feature_class":"P",
    "gn:feature_code":"PPL",
    "gn:name":"Kolgaon",
    "gn:population":0,
    "gn:timezone":"Asia/Kolkata",
    "iso:country":"IN",
    "wof:name":"Kolgaon",
    "wof:placetype":"neighbourhood"
},
  "geometry": {"coordinates":[74.34541,19.855],"type":"Point"}
}