{
  "type": "Feature",
  "properties": {
    "gn:admin1_code":"39.0",
    "gn:admin2_code":"061",
    "gn:asciiname":"Banwar",
    "gn:country_code":"IN",
    "gn:dem":1178,
    "gn:feature_class":"P",
    "gn:feature_code":"PPL",
    "gn:name":"Banw\u0101r",
    "gn:population":0,
    "gn:timezone":"Asia/Kolkata",
    "iso:country":"IN",
    "ks:ks_alt_nam":"Banw\u0101r",
    "ks:ks_name":"Banwar",
    "ks:ks_type":"VILLAGE",
    "name:eng_x_preferred":[
        "Banwar"
    ],
    "name:eng_x_variant":[
        "Banw\u0101r"
    ],
    "wof:name":"Banwar",
    "wof:placetype":"locality"
},
  "geometry": {"coordinates":[78.643939,29.866388],"type":"Point"}
}