{
  "type": "Feature",
  "properties": {
    "gn:admin1_code":"39.0",
    "gn:admin2_code":"061",
    "gn:asciiname":"Banwar",
    "gn:country_code":"IN",
    "gn:dem":1178,
    "gn:feature_class":"P",
    "gn:feature_code":"PPL",
    "gn:name":"Banw\u0101r",
    "gn:population":0,
    "gn:timezone":"Asia/Kolkata",
    "iso:country":"IN",
    "wof:name":"Banwar",
    "wof:placetype":"locality"
},
  "geometry": {"coordinates":[78.64394,29.86639000000001],"type":"Point"}
}