{
  "type": "Feature",
  "properties": {
    "iso:country":"IN",
    "ks:ks_name":"Kadamwadi",
    "ks:ks_pop":160,
    "ks:ks_type":"HABITATION",
    "name:eng_x_preferred":[
        "Kadamwadi"
    ],
    "wof:name":"Kadamwadi",
    "wof:placetype":"locality",
    "wof:population":160
},
  "geometry": {"coordinates":[73.281953,17.868953],"type":"Point"}
}