{
  "type": "Feature",
  "properties": {
    "iso:country":"IN",
    "ks:ks_name":"Fundipara",
    "ks:ks_pop":468,
    "ks:ks_type":"HABITATION",
    "name:eng_x_preferred":[
        "Fundipara"
    ],
    "wof:name":"Fundipara",
    "wof:placetype":"locality",
    "wof:population":468
},
  "geometry": {"coordinates":[90.179591,26.398769],"type":"Point"}
}