{
  "type": "Feature",
  "properties": {
    "iso:country":"IN",
    "ks:ks_name":"Ella Hab",
    "ks:ks_pop":508,
    "ks:ks_type":"HABITATION",
    "name:eng_x_preferred":[
        "Ella Hab"
    ],
    "wof:name":"Ella Hab",
    "wof:placetype":"locality",
    "wof:population":508
},
  "geometry": {"coordinates":[76.851978,9.087542],"type":"Point"}
}