{
  "type": "Feature",
  "properties": {
    "iso:country":"IN",
    "ks:ks_alt_nam":"NAGLA KASOA",
    "ks:ks_name":"Nagla Kasoa",
    "ks:ks_pop":700,
    "ks:ks_type":"HABITATION",
    "name:eng_x_preferred":[
        "Nagla Kasoa"
    ],
    "wof:name":"Nagla Kasoa",
    "wof:placetype":"locality",
    "wof:population":700
},
  "geometry": {"coordinates":[79.00524799999999,26.63684],"type":"Point"}
}