{
  "type": "Feature",
  "properties": {
    "iso:country":"IN",
    "ks:ks_alt_nam":"15 SHPD",
    "ks:ks_name":"15 Shpd",
    "ks:ks_pop":1139,
    "ks:ks_type":"HABITATION",
    "name:eng_x_preferred":[
        "15 Shpd"
    ],
    "wof:name":"15 Shpd",
    "wof:placetype":"locality",
    "wof:population":1139
},
  "geometry": {"coordinates":[73.766908,29.361535],"type":"Point"}
}