{
  "type": "Feature",
  "properties": {
    "iso:country":"IN",
    "ks:ks_alt_nam":"MANYARPADA",
    "ks:ks_name":"Manyarpada",
    "ks:ks_pop":150,
    "ks:ks_type":"HABITATION",
    "name:eng_x_preferred":[
        "Manyarpada"
    ],
    "wof:name":"Manyarpada",
    "wof:placetype":"locality",
    "wof:population":150
},
  "geometry": {"coordinates":[75.45204200000001,21.235559],"type":"Point"}
}