{
  "type": "Feature",
  "properties": {
    "gn:admin1_code":"36.0",
    "gn:admin2_code":"132.0",
    "gn:asciiname":"Mohanpur",
    "gn:country_code":"IN",
    "gn:dem":271,
    "gn:feature_class":"P",
    "gn:feature_code":"PPL",
    "gn:name":"Mohanpur",
    "gn:population":0,
    "gn:timezone":"Asia/Kolkata",
    "iso:country":"IN",
    "name:und_x_variant":[
        "G\u016bjar"
    ],
    "wof:name":"Mohanpur",
    "wof:placetype":"locality"
},
  "geometry": {"coordinates":[77.45814,29.88596],"type":"Point"}
}