{
  "type": "Feature",
  "properties": {
    "gn:admin1_code":"34.0",
    "gn:admin2_code":"213.0",
    "gn:asciiname":"Toka",
    "gn:country_code":"IN",
    "gn:dem":53,
    "gn:feature_class":"P",
    "gn:feature_code":"PPL",
    "gn:name":"Toka",
    "gn:population":0,
    "gn:timezone":"Asia/Kolkata",
    "iso:country":"IN",
    "name:ben_x_preferred":[
        "\u099f\u09cb\u0995\u09be"
    ],
    "name:ceb_x_preferred":[
        "Toka"
    ],
    "name:deu_x_preferred":[
        "Toka"
    ],
    "name:swe_x_preferred":[
        "Toka"
    ],
    "wof:name":"Toka",
    "wof:placetype":"locality"
},
  "geometry": {"coordinates":[86.74825,26.03636],"type":"Point"}
}