{
  "type": "Feature",
  "properties": {
    "iso:country":"IN",
    "ks:ks_name":"Balgarh",
    "ks:ks_pop":210,
    "ks:ks_type":"VILLAGE",
    "name:eng_x_preferred":[
        "Balgarh"
    ],
    "wof:name":"Balgarh",
    "wof:placetype":"locality",
    "wof:population":210
},
  "geometry": {"coordinates":[76.122432,24.595],"type":"Point"}
}