{
  "type": "Feature",
  "properties": {
    "gn:admin1_code":"34.0",
    "gn:admin2_code":"210.0",
    "gn:asciiname":"Dhata",
    "gn:country_code":"IN",
    "gn:dem":70,
    "gn:feature_class":"P",
    "gn:feature_code":"PPL",
    "gn:name":"Dhata",
    "gn:population":0,
    "gn:timezone":"Asia/Kolkata",
    "iso:country":"IN",
    "wof:name":"Dhata",
    "wof:placetype":"locality"
},
  "geometry": {"coordinates":[87.65016999999997,26.3802],"type":"Point"}
}