{
  "type": "Feature",
  "properties": {
    "gn:admin1_code":"17.0",
    "gn:admin2_code":"272",
    "gn:asciiname":"Bongbal Khulen",
    "gn:country_code":"IN",
    "gn:dem":1433,
    "gn:feature_class":"P",
    "gn:feature_code":"PPL",
    "gn:name":"Bongb\u0101l Khulen",
    "gn:population":0,
    "gn:timezone":"Asia/Kolkata",
    "iso:country":"IN",
    "name:und_x_variant":[
        "Bongba Khulen",
        "Bongb\u0101l Khulen"
    ],
    "wof:name":"Bongbal Khulen",
    "wof:placetype":"locality"
},
  "geometry": {"coordinates":[94.16087,24.72003],"type":"Point"}
}