{
  "type": "Feature",
  "properties": {
    "iso:country":"IN",
    "ks:ks_name":"Saki",
    "ks:ks_pop":0,
    "ks:ks_type":"VILLAGE",
    "name:eng_x_preferred":[
        "Saki"
    ],
    "wof:name":"Saki",
    "wof:placetype":"locality",
    "wof:population":0
},
  "geometry": {"coordinates":[73.706333,21.601034],"type":"Point"}
}