{
  "type": "Feature",
  "properties": {
    "iso:country":"IN",
    "ks:ks_name":"Chekkaraibanda",
    "ks:ks_pop":30,
    "ks:ks_type":"HABITATION",
    "name:eng_x_preferred":[
        "Chekkaraibanda"
    ],
    "wof:name":"Chekkaraibanda",
    "wof:placetype":"locality",
    "wof:population":30
},
  "geometry": {"coordinates":[82.573815,17.839589],"type":"Point"}
}