{
  "type": "Feature",
  "properties": {
    "iso:country":"IN",
    "ks:ks_alt_nam":"SATPUTE WASTI",
    "ks:ks_name":"Satpute Wasti",
    "ks:ks_pop":79,
    "ks:ks_type":"HABITATION",
    "name:eng_x_preferred":[
        "Satpute Wasti"
    ],
    "wof:name":"Satpute Wasti",
    "wof:placetype":"locality",
    "wof:population":79
},
  "geometry": {"coordinates":[75.215243,17.165621],"type":"Point"}
}