{
  "type": "Feature",
  "properties": {
    "iso:country":"IN",
    "ks:ks_name":"N. Jai Ram",
    "ks:ks_pop":200,
    "ks:ks_type":"HABITATION",
    "name:eng_x_preferred":[
        "N. Jai Ram"
    ],
    "wof:name":"N. Jai Ram",
    "wof:placetype":"locality",
    "wof:population":200
},
  "geometry": {"coordinates":[78.623242,27.112559],"type":"Point"}
}