{
  "type": "Feature",
  "properties": {
    "iso:country":"IN",
    "ks:ks_name":"Tola Belatanr",
    "ks:ks_pop":25,
    "ks:ks_type":"VILLAGE",
    "name:eng_x_preferred":[
        "Tola Belatanr"
    ],
    "wof:name":"Tola Belatanr",
    "wof:placetype":"locality",
    "wof:population":25
},
  "geometry": {"coordinates":[86.38760499999999,25.076866],"type":"Point"}
}