{
  "type": "Feature",
  "properties": {
    "gn:admin1_code":"2.0",
    "gn:admin2_code":"546.0",
    "gn:asciiname":"Nagalagudem",
    "gn:country_code":"IN",
    "gn:dem":77,
    "gn:feature_class":"P",
    "gn:feature_code":"PPL",
    "gn:name":"N\u0101galag\u016bdem",
    "gn:population":0,
    "gn:timezone":"Asia/Kolkata",
    "iso:country":"IN",
    "wof:name":"Nagalagudem",
    "wof:placetype":"locality"
},
  "geometry": {"coordinates":[81.30486999999999,17.09069],"type":"Point"}
}