{
  "type": "Feature",
  "properties": {
    "iso:country":"IN",
    "ks:ks_name":"Tarra",
    "ks:ks_pop":806,
    "ks:ks_type":"HABITATION",
    "name:eng_x_preferred":[
        "Tarra"
    ],
    "wof:name":"Tarra",
    "wof:placetype":"locality",
    "wof:population":806
},
  "geometry": {"coordinates":[86.929948,23.887111],"type":"Point"}
}