{
  "type": "Feature",
  "properties": {
    "iso:country":"IN",
    "ks:ks_name":"Degolee",
    "ks:ks_pop":126,
    "ks:ks_type":"HABITATION",
    "name:eng_x_preferred":[
        "Degolee"
    ],
    "wof:name":"Degolee",
    "wof:placetype":"locality",
    "wof:population":126
},
  "geometry": {"coordinates":[79.088443,29.840235],"type":"Point"}
}