{
  "type": "Feature",
  "properties": {
    "iso:country":"IN",
    "ks:ks_name":"Devarunda",
    "ks:ks_pop":399,
    "ks:ks_type":"HABITATION",
    "name:eng_x_preferred":[
        "Devarunda"
    ],
    "wof:name":"Devarunda",
    "wof:placetype":"locality",
    "wof:population":399
},
  "geometry": {"coordinates":[75.369889,13.188718],"type":"Point"}
}