{
  "type": "Feature",
  "properties": {
    "iso:country":"IN",
    "ks:ks_name":"Havellian Dhun",
    "ks:ks_pop":1107,
    "ks:ks_type":"HABITATION",
    "name:eng_x_preferred":[
        "Havellian Dhun"
    ],
    "wof:name":"Havellian Dhun",
    "wof:placetype":"locality",
    "wof:population":1107
},
  "geometry": {"coordinates":[75.008922,31.220614],"type":"Point"}
}