{
  "type": "Feature",
  "properties": {
    "iso:country":"IN",
    "ks:ks_name":"Varvand",
    "ks:ks_pop":208,
    "ks:ks_type":"HABITATION",
    "name:eng_x_preferred":[
        "Varvand"
    ],
    "wof:name":"Varvand",
    "wof:placetype":"locality",
    "wof:population":208
},
  "geometry": {"coordinates":[73.65047199999999,18.113456],"type":"Point"}
}