{
  "type": "Feature",
  "properties": {
    "gn:admin1_code":"36",
    "gn:admin2_code":"188.0",
    "gn:asciiname":"Barauli",
    "gn:country_code":"IN",
    "gn:dem":83,
    "gn:feature_class":"P",
    "gn:feature_code":"PPL",
    "gn:name":"Barauli",
    "gn:population":0,
    "gn:timezone":"Asia/Kolkata",
    "iso:country":"IN",
    "name:ara_x_preferred":[
        "\u0628\u0631\u0627\u0648\u0644\u064a"
    ],
    "name:ben_bn_x_preferred":[
        "\u09ac\u09be\u09b0\u09be\u0989\u09b2\u09bf"
    ],
    "name:ben_in_x_preferred":[
        "\u09ac\u09be\u09b0\u09be\u0989\u09b2\u09bf"
    ],
    "name:guj_x_preferred":[
        "\u0aac\u0ab0\u0acc\u0ab2\u0ac0"
    ],
    "name:hin_x_preferred":[
        "\u092c\u0930\u094c\u0932\u0940"
    ],
    "name:kan_x_preferred":[
        "\u0cac\u0cb0\u0ccc\u0cb2\u0cbf"
    ],
    "name:mal_x_preferred":[
        "\u0d2c\u0d31\u0d57\u0d32\u0d3f"
    ],
    "name:mar_x_preferred":[
        "\u092c\u0930\u094c\u0932\u0940"
    ],
    "name:pan_x_preferred":[
        "\u0a2c\u0a30\u0a4c\u0a32\u0a40"
    ],
    "name:tam_x_preferred":[
        "\u0baa\u0bb0\u0bcc\u0bb2\u0bbf"
    ],
    "name:tel_x_preferred":[
        "\u0c2c\u0c30\u0c4c\u0c32\u0c3f"
    ],
    "name:urd_x_preferred":[
        "\u0628\u0631\u0648\u0644\u06cc"
    ],
    "wof:name":"Barauli",
    "wof:placetype":"locality"
},
  "geometry": {"coordinates":[83.21146,26.47862000000001],"type":"Point"}
}