{
  "type": "Feature",
  "properties": {
    "iso:country":"IN",
    "ks:ks_name":"Prasannakati",
    "ks:ks_pop":2463,
    "ks:ks_type":"HABITATION",
    "name:eng_x_preferred":[
        "Prasannakati"
    ],
    "wof:name":"Prasannakati",
    "wof:placetype":"locality",
    "wof:population":2463
},
  "geometry": {"coordinates":[88.92158999999999,22.709117],"type":"Point"}
}