{
  "type": "Feature",
  "properties": {
    "gn:admin1_code":"37",
    "gn:admin2_code":"401.0",
    "gn:asciiname":"Amdanda",
    "gn:country_code":"IN",
    "gn:dem":520,
    "gn:feature_class":"P",
    "gn:feature_code":"PPL",
    "gn:name":"Amdand\u0101",
    "gn:population":0,
    "gn:timezone":"Asia/Kolkata",
    "iso:country":"IN",
    "wof:name":"Amdanda",
    "wof:placetype":"locality"
},
  "geometry": {"coordinates":[83.69674000000001,23.59997000000001],"type":"Point"}
}