{
  "type": "Feature",
  "properties": {
    "gn:admin1_code":"40.0",
    "gn:admin2_code":"534.0",
    "gn:asciiname":"Kottur",
    "gn:country_code":"IN",
    "gn:dem":262,
    "gn:feature_class":"P",
    "gn:feature_code":"PPL",
    "gn:name":"Kott\u016br",
    "gn:population":0,
    "gn:timezone":"Asia/Kolkata",
    "iso:country":"IN",
    "name:bpy_x_preferred":[
        "\u0995\u09cb\u09a4\u09cd\u09a4\u09c1\u09b0"
    ],
    "name:new_x_preferred":[
        "\u0915\u094b\u091f\u094d\u091f\u0941\u0930"
    ],
    "name:vie_x_preferred":[
        "Kottur"
    ],
    "wof:name":"Kottur",
    "wof:placetype":"locality"
},
  "geometry": {"coordinates":[79.23791999999997,18.6574],"type":"Point"}
}