{
  "type": "Feature",
  "properties": {
    "iso:country":"IN",
    "ks:ks_name":"Kubba",
    "ks:ks_pop":517,
    "ks:ks_type":"HABITATION",
    "name:eng_x_preferred":[
        "Kubba"
    ],
    "wof:name":"Kubba",
    "wof:placetype":"locality",
    "wof:population":517
},
  "geometry": {"coordinates":[82.825311,24.369682],"type":"Point"}
}