{
  "type": "Feature",
  "properties": {
    "gn:admin1_code":"11",
    "gn:admin2_code":"23.0",
    "gn:asciiname":"Saran",
    "gn:country_code":"IN",
    "gn:dem":2008,
    "gn:feature_class":"P",
    "gn:feature_code":"PPL",
    "gn:name":"S\u0101ran",
    "gn:population":0,
    "gn:timezone":"Asia/Kolkata",
    "iso:country":"IN",
    "wof:name":"Saran",
    "wof:placetype":"locality"
},
  "geometry": {"coordinates":[76.17140999999999,32.71120999999999],"type":"Point"}
}