{
  "type": "Feature",
  "properties": {
    "iso:country":"IN",
    "ks:ks_name":"Mangta Purwa",
    "ks:ks_pop":25,
    "ks:ks_type":"HABITATION",
    "name:eng_x_preferred":[
        "Mangta Purwa"
    ],
    "wof:name":"Mangta Purwa",
    "wof:placetype":"locality",
    "wof:population":25
},
  "geometry": {"coordinates":[82.69945199999999,26.711359],"type":"Point"}
}