{
  "type": "Feature",
  "properties": {
    "iso:country":"IN",
    "ks:ks_name":"Jakuatoli",
    "ks:ks_pop":251,
    "ks:ks_type":"HABITATION",
    "name:eng_x_preferred":[
        "Jakuatoli"
    ],
    "wof:name":"Jakuatoli",
    "wof:placetype":"locality",
    "wof:population":251
},
  "geometry": {"coordinates":[84.79740700000001,23.084326],"type":"Point"}
}