{
  "type": "Feature",
  "properties": {
    "iso:country":"IN",
    "ks:ks_name":"Aliyarpur Patti",
    "ks:ks_pop":113,
    "ks:ks_type":"VILLAGE",
    "ks:ks_uagg_main":0,
    "name:eng_x_preferred":[
        "Aliyarpur Patti"
    ],
    "wof:name":"Aliyarpur Patti",
    "wof:placetype":"neighbourhood",
    "wof:population":113
},
  "geometry": {"coordinates":[77.623576,29.331096],"type":"Point"}
}