{
  "type": "Feature",
  "properties": {
    "iso:country":"IN",
    "ks:ks_name":"Sengodagoundenpudur",
    "ks:ks_pop":102,
    "ks:ks_type":"HABITATION",
    "name:eng_x_preferred":[
        "Sengodagoundenpudur"
    ],
    "wof:name":"Sengodagoundenpudur",
    "wof:placetype":"locality",
    "wof:population":102
},
  "geometry": {"coordinates":[77.190395,10.732667],"type":"Point"}
}