{
  "type": "Feature",
  "properties": {
    "gn:admin1_code":"34.0",
    "gn:admin2_code":"219.0",
    "gn:asciiname":"Parmanand Chhapra",
    "gn:country_code":"IN",
    "gn:dem":60,
    "gn:feature_class":"P",
    "gn:feature_code":"PPL",
    "gn:name":"Parmanand Chhapra",
    "gn:population":0,
    "gn:timezone":"Asia/Kolkata",
    "iso:country":"IN",
    "ks:ks_name":"Parmanand Chhapra",
    "ks:ks_pop":1101,
    "ks:ks_type":"VILLAGE",
    "ks:ks_uagg_main":0,
    "name:eng_x_preferred":[
        "Parmanand Chhapra"
    ],
    "wof:name":"Parmanand Chhapra",
    "wof:placetype":"neighbourhood",
    "wof:population":1101
},
  "geometry": {"coordinates":[84.98065,25.985535],"type":"Point"}
}