{
  "type": "Feature",
  "properties": {
    "iso:country":"IN",
    "ks:ks_name":"Rajpurhill",
    "ks:ks_pop":0,
    "ks:ks_type":"VILLAGE",
    "name:eng_x_preferred":[
        "Rajpurhill"
    ],
    "wof:name":"Rajpurhill",
    "wof:placetype":"locality",
    "wof:population":0
},
  "geometry": {"coordinates":[84.83807899999999,19.556364],"type":"Point"}
}