{
  "type": "Feature",
  "properties": {
    "iso:country":"IN",
    "ks:ks_alt_nam":"Pachim Lalipathar no 1",
    "ks:ks_name":"Pachim Lalipathar No 1",
    "ks:ks_pop":773,
    "ks:ks_type":"HABITATION",
    "name:eng_x_preferred":[
        "Pachim Lalipathar No 1"
    ],
    "wof:name":"Pachim Lalipathar No 1",
    "wof:placetype":"locality",
    "wof:population":773
},
  "geometry": {"coordinates":[92.43667499999999,26.408813],"type":"Point"}
}