{
  "type": "Feature",
  "properties": {
    "gn:admin1_code":"34.0",
    "gn:admin2_code":"217.0",
    "gn:asciiname":"Barhea",
    "gn:country_code":"IN",
    "gn:dem":68,
    "gn:feature_class":"P",
    "gn:feature_code":"PPL",
    "gn:name":"Barhea",
    "gn:population":0,
    "gn:timezone":"Asia/Kolkata",
    "iso:country":"IN",
    "ks:ks_name":"Barhea",
    "ks:ks_pop":3365,
    "ks:ks_type":"VILLAGE",
    "ks:ks_uagg_main":0,
    "name:eng_x_preferred":[
        "Barhea"
    ],
    "wof:name":"Barhea",
    "wof:placetype":"neighbourhood",
    "wof:population":3365
},
  "geometry": {"coordinates":[84.60927100000001,26.402281],"type":"Point"}
}