{
  "type": "Feature",
  "properties": {
    "iso:country":"IN",
    "ks:ks_name":"Chatlavada",
    "ks:ks_pop":394,
    "ks:ks_type":"VILLAGE",
    "name:eng_x_preferred":[
        "Chatlavada"
    ],
    "wof:name":"Chatlavada",
    "wof:placetype":"locality",
    "wof:population":394
},
  "geometry": {"coordinates":[81.68842100000001,17.699156],"type":"Point"}
}