{
  "type": "Feature",
  "properties": {
    "iso:country":"IN",
    "ks:ks_name":"Kodali",
    "ks:ks_pop":44,
    "ks:ks_type":"HABITATION",
    "name:eng_x_preferred":[
        "Kodali"
    ],
    "wof:name":"Kodali",
    "wof:placetype":"locality",
    "wof:population":44
},
  "geometry": {"coordinates":[76.37502499999999,10.375322],"type":"Point"}
}