{
  "type": "Feature",
  "properties": {
    "iso:country":"IN",
    "ks:ks_alt_nam":"MAGARWASTI",
    "ks:ks_name":"Magarwasti",
    "ks:ks_pop":101,
    "ks:ks_type":"HABITATION",
    "name:eng_x_preferred":[
        "Magarwasti"
    ],
    "wof:name":"Magarwasti",
    "wof:placetype":"locality",
    "wof:population":101
},
  "geometry": {"coordinates":[74.9452,17.465353],"type":"Point"}
}