{
  "type": "Feature",
  "properties": {
    "gn:admin1_code":"23.0",
    "gn:admin2_code":"49.0",
    "gn:asciiname":"Banjarwal",
    "gn:country_code":"IN",
    "gn:dem":236,
    "gn:feature_class":"P",
    "gn:feature_code":"PPL",
    "gn:name":"Banjarw\u0101l",
    "gn:population":0,
    "gn:timezone":"Asia/Kolkata",
    "iso:country":"IN",
    "ks:ks_alt_nam":"Banjarw\u0101l",
    "ks:ks_name":"Banjarwal",
    "ks:ks_pop":97,
    "ks:ks_type":"VILLAGE",
    "name:eng_x_preferred":[
        "Banjarwal"
    ],
    "name:eng_x_variant":[
        "Banjarw\u0101l"
    ],
    "wof:name":"Banjarwal",
    "wof:placetype":"locality",
    "wof:population":97
},
  "geometry": {"coordinates":[75.183784,31.648457],"type":"Point"}
}