{
  "type": "Feature",
  "properties": {
    "iso:country":"IN",
    "ks:ks_name":"Chak Shibpur",
    "ks:ks_pop":681,
    "ks:ks_type":"VILLAGE",
    "ks:ks_uagg_main":0,
    "name:eng_x_preferred":[
        "Chak Shibpur"
    ],
    "wof:name":"Chak Shibpur",
    "wof:placetype":"neighbourhood",
    "wof:population":681
},
  "geometry": {"coordinates":[88.596108,25.48527],"type":"Point"}
}