{
  "type": "Feature",
  "properties": {
    "iso:country":"IN",
    "ks:ks_name":"Khotiakholi No.1",
    "ks:ks_pop":256,
    "ks:ks_type":"HABITATION",
    "name:eng_x_preferred":[
        "Khotiakholi No.1"
    ],
    "wof:name":"Khotiakholi No.1",
    "wof:placetype":"locality",
    "wof:population":256
},
  "geometry": {"coordinates":[93.65117100000001,26.654863],"type":"Point"}
}