{
  "type": "Feature",
  "properties": {
    "iso:country":"IN",
    "ks:ks_name":"Kumaramangalam",
    "ks:ks_pop":225,
    "ks:ks_type":"VILLAGE",
    "ks:ks_uagg_main":0,
    "name:eng_x_preferred":[
        "Kumaramangalam"
    ],
    "wof:name":"Kumaramangalam",
    "wof:placetype":"neighbourhood",
    "wof:population":225
},
  "geometry": {"coordinates":[76.71184,9.938844],"type":"Point"}
}