{
  "type": "Feature",
  "properties": {
    "iso:country":"IN",
    "ks:ks_name":"Mohammadpur",
    "ks:ks_pop":1078,
    "ks:ks_type":"VILLAGE",
    "ks:ks_uagg_main":0,
    "name:eng_x_preferred":[
        "Mohammadpur"
    ],
    "wof:name":"Mohammadpur",
    "wof:placetype":"neighbourhood",
    "wof:population":1078
},
  "geometry": {"coordinates":[85.094368,24.986922],"type":"Point"}
}