{
  "type": "Feature",
  "properties": {
    "iso:country":"IN",
    "ks:ks_name":"Mehekari",
    "ks:ks_pop":803,
    "ks:ks_type":"VILLAGE",
    "name:eng_x_preferred":[
        "Mehekari"
    ],
    "wof:name":"Mehekari",
    "wof:placetype":"locality",
    "wof:population":803
},
  "geometry": {"coordinates":[74.868538,19.101272],"type":"Point"}
}