{
  "type": "Feature",
  "properties": {
    "iso:country":"IN",
    "ks:ks_name":"Banarhotoli",
    "ks:ks_pop":110,
    "ks:ks_type":"HABITATION",
    "name:eng_x_preferred":[
        "Banarhotoli"
    ],
    "wof:name":"Banarhotoli",
    "wof:placetype":"locality",
    "wof:population":110
},
  "geometry": {"coordinates":[84.658576,23.26683],"type":"Point"}
}