{
  "type": "Feature",
  "properties": {
    "gn:admin1_code":"36.0",
    "gn:admin2_code":"157.0",
    "gn:asciiname":"Karaundi",
    "gn:country_code":"IN",
    "gn:dem":133,
    "gn:feature_class":"P",
    "gn:feature_code":"PPL",
    "gn:name":"Karaundi",
    "gn:population":0,
    "gn:timezone":"Asia/Kolkata",
    "iso:country":"IN",
    "ks:ks_name":"Karaundi",
    "ks:ks_pop":810,
    "ks:ks_type":"VILLAGE",
    "ks:ks_uagg_main":0,
    "name:eng_x_preferred":[
        "Karaundi"
    ],
    "wof:name":"Karaundi",
    "wof:placetype":"neighbourhood",
    "wof:population":810
},
  "geometry": {"coordinates":[80.87562800000001,27.105214],"type":"Point"}
}