{
  "type": "Feature",
  "properties": {
    "iso:country":"IN",
    "ks:ks_name":"Siyari",
    "ks:ks_pop":155,
    "ks:ks_type":"HABITATION",
    "name:eng_x_preferred":[
        "Siyari"
    ],
    "wof:name":"Siyari",
    "wof:placetype":"locality",
    "wof:population":155
},
  "geometry": {"coordinates":[74.583172,23.58365],"type":"Point"}
}