{
  "type": "Feature",
  "properties": {
    "iso:country":"IN",
    "ks:ks_name":"Parpancha",
    "ks:ks_pop":603,
    "ks:ks_type":"HABITATION",
    "name:eng_x_preferred":[
        "Parpancha"
    ],
    "wof:name":"Parpancha",
    "wof:placetype":"locality",
    "wof:population":603
},
  "geometry": {"coordinates":[85.50965100000001,23.486894],"type":"Point"}
}