{
  "type": "Feature",
  "properties": {
    "iso:country":"IN",
    "ks:ks_name":"Bir Phillaur",
    "ks:ks_pop":58,
    "ks:ks_type":"VILLAGE",
    "name:eng_x_preferred":[
        "Bir Phillaur"
    ],
    "wof:name":"Bir Phillaur",
    "wof:placetype":"locality",
    "wof:population":58
},
  "geometry": {"coordinates":[75.779681,31.045555],"type":"Point"}
}