{
  "type": "Feature",
  "properties": {
    "iso:country":"IN",
    "ks:ks_name":"Kambavalasa",
    "ks:ks_pop":103,
    "ks:ks_type":"HABITATION",
    "name:eng_x_preferred":[
        "Kambavalasa"
    ],
    "wof:name":"Kambavalasa",
    "wof:placetype":"locality",
    "wof:population":103
},
  "geometry": {"coordinates":[82.798001,18.255702],"type":"Point"}
}