{
  "type": "Feature",
  "properties": {
    "iso:country":"IN",
    "ks:ks_name":"Pipra",
    "ks:ks_pop":208,
    "ks:ks_type":"VILLAGE",
    "name:eng_x_preferred":[
        "Pipra"
    ],
    "wof:name":"Pipra",
    "wof:placetype":"locality",
    "wof:population":208
},
  "geometry": {"coordinates":[87.395475,24.576757],"type":"Point"}
}