{
  "type": "Feature",
  "properties": {
    "gn:admin1_code":"36",
    "gn:admin2_code":"154.0",
    "gn:asciiname":"Tak Purwa",
    "gn:country_code":"IN",
    "gn:dem":140,
    "gn:feature_class":"P",
    "gn:feature_code":"PPL",
    "gn:name":"Tak Purwa",
    "gn:population":0,
    "gn:timezone":"Asia/Kolkata",
    "iso:country":"IN",
    "wof:name":"Tak Purwa",
    "wof:placetype":"locality"
},
  "geometry": {"coordinates":[80.76935999999998,27.51928],"type":"Point"}
}