{
  "type": "Feature",
  "properties": {
    "gn:admin1_code":"11.0",
    "gn:admin2_code":"32.0",
    "gn:asciiname":"Sakanan",
    "gn:country_code":"IN",
    "gn:dem":1885,
    "gn:feature_class":"P",
    "gn:feature_code":"PPL",
    "gn:name":"Sak\u0101nan",
    "gn:population":0,
    "gn:timezone":"Asia/Kolkata",
    "iso:country":"IN",
    "wof:name":"Sakanan",
    "wof:placetype":"locality"
},
  "geometry": {"coordinates":[77.2765,30.90979],"type":"Point"}
}