{
  "type": "Feature",
  "properties": {
    "iso:country":"IN",
    "ks:ks_name":"Mainaguri",
    "ks:ks_pop":97,
    "ks:ks_type":"HABITATION",
    "name:eng_x_preferred":[
        "Mainaguri"
    ],
    "wof:name":"Mainaguri",
    "wof:placetype":"locality",
    "wof:population":97
},
  "geometry": {"coordinates":[87.94959900000001,26.393361],"type":"Point"}
}