{
  "type": "Feature",
  "properties": {
    "iso:country":"IN",
    "ks:ks_name":"Roligaon",
    "ks:ks_pop":1852,
    "ks:ks_type":"VILLAGE",
    "name:eng_x_preferred":[
        "Roligaon"
    ],
    "wof:name":"Roligaon",
    "wof:placetype":"locality",
    "wof:population":1852
},
  "geometry": {"coordinates":[74.30477999999999,22.549249],"type":"Point"}
}