{
  "type": "Feature",
  "properties": {
    "iso:country":"IN",
    "ks:ks_alt_nam":"vaddarhatti",
    "ks:ks_name":"Vaddarhatti",
    "ks:ks_pop":116,
    "ks:ks_type":"HABITATION",
    "name:eng_x_preferred":[
        "Vaddarhatti"
    ],
    "wof:name":"Vaddarhatti",
    "wof:placetype":"locality",
    "wof:population":116
},
  "geometry": {"coordinates":[76.405064,13.354201],"type":"Point"}
}