{
  "type": "Feature",
  "properties": {
    "iso:country":"IN",
    "ks:ks_name":"Upper Mamring",
    "ks:ks_pop":689,
    "ks:ks_type":"HABITATION",
    "name:eng_x_preferred":[
        "Upper Mamring"
    ],
    "wof:name":"Upper Mamring",
    "wof:placetype":"locality",
    "wof:population":689
},
  "geometry": {"coordinates":[88.327567,26.942603],"type":"Point"}
}