{
  "type": "Feature",
  "properties": {
    "gn:admin1_code":"34.0",
    "gn:admin2_code":"212.0",
    "gn:asciiname":"Fatehnagar",
    "gn:country_code":"IN",
    "gn:dem":32,
    "gn:feature_class":"P",
    "gn:feature_code":"PPL",
    "gn:name":"Fatehnagar",
    "gn:population":0,
    "gn:timezone":"Asia/Kolkata",
    "iso:country":"IN",
    "name:ben_x_preferred":[
        "\u09ab\u09a4\u09c7\u09b9\u09a8\u0997\u09b0"
    ],
    "name:bpy_x_preferred":[
        "\u09ab\u09a4\u09c7\u09b9\u09a8\u0997\u09b0"
    ],
    "name:hin_x_preferred":[
        "\u092b\u0924\u0947\u0939\u0928\u0917\u0930"
    ],
    "name:ita_x_preferred":[
        "Fatehnagar"
    ],
    "name:msa_x_preferred":[
        "Fatehnagar"
    ],
    "name:new_x_preferred":[
        "\u092b\u0924\u0947\u0939\u0928\u0917\u0930"
    ],
    "name:por_x_preferred":[
        "Fatehnagar"
    ],
    "name:vie_x_preferred":[
        "Fatehnagar"
    ],
    "name:zho_x_preferred":[
        "\u6cd5\u6cf0\u8d6b\u7eb3\u52a0\u5c14"
    ],
    "wof:name":"Fatehnagar",
    "wof:placetype":"locality"
},
  "geometry": {"coordinates":[87.68531999999998,25.42434],"type":"Point"}
}