{
  "type": "Feature",
  "properties": {
    "gn:admin1_code":"37.0",
    "gn:admin2_code":"410",
    "gn:asciiname":"Indagaon",
    "gn:country_code":"IN",
    "gn:dem":350,
    "gn:feature_class":"P",
    "gn:feature_code":"PPL",
    "gn:name":"Indagaon",
    "gn:population":0,
    "gn:timezone":"Asia/Kolkata",
    "iso:country":"IN",
    "wof:name":"Indagaon",
    "wof:placetype":"locality"
},
  "geometry": {"coordinates":[82.37307,20.07971],"type":"Point"}
}