{
  "type": "Feature",
  "properties": {
    "gn:admin1_code":"35",
    "gn:admin2_code":"443.0",
    "gn:asciiname":"Pachpipra",
    "gn:country_code":"IN",
    "gn:dem":450,
    "gn:feature_class":"P",
    "gn:feature_code":"PPL",
    "gn:name":"Pachpipra",
    "gn:population":0,
    "gn:timezone":"Asia/Kolkata",
    "iso:country":"IN",
    "wof:name":"Pachpipra",
    "wof:placetype":"locality"
},
  "geometry": {"coordinates":[78.25192,23.81294],"type":"Point"}
}