{
  "type": "Feature",
  "properties": {
    "iso:country":"IN",
    "ks:ks_name":"Orengtoli",
    "ks:ks_pop":79,
    "ks:ks_type":"VILLAGE",
    "name:eng_x_preferred":[
        "Orengtoli"
    ],
    "wof:name":"Orengtoli",
    "wof:placetype":"locality",
    "wof:population":79
},
  "geometry": {"coordinates":[85.12414,22.807262],"type":"Point"}
}