{
  "type": "Feature",
  "properties": {
    "iso:country":"IN",
    "ks:ks_name":"Bondena",
    "ks:ks_pop":229,
    "ks:ks_type":"VILLAGE",
    "name:eng_x_preferred":[
        "Bondena"
    ],
    "wof:name":"Bondena",
    "wof:placetype":"locality",
    "wof:population":229
},
  "geometry": {"coordinates":[80.461613,20.75747],"type":"Point"}
}