{
  "type": "Feature",
  "properties": {
    "gn:admin1_code":"36",
    "gn:admin2_code":"137.0",
    "gn:asciiname":"Tur",
    "gn:country_code":"IN",
    "gn:dem":217,
    "gn:feature_class":"P",
    "gn:feature_code":"PPL",
    "gn:name":"Tur",
    "gn:population":0,
    "gn:timezone":"Asia/Kolkata",
    "iso:country":"IN",
    "wof:name":"Tur",
    "wof:placetype":"locality"
},
  "geometry": {"coordinates":[78.52665,29.01708],"type":"Point"}
}