{
  "type": "Feature",
  "properties": {
    "gn:admin1_code":"36.0",
    "gn:admin2_code":"179.0",
    "gn:asciiname":"Khadra",
    "gn:country_code":"IN",
    "gn:dem":106,
    "gn:feature_class":"P",
    "gn:feature_code":"PPL",
    "gn:name":"Khadra",
    "gn:population":0,
    "gn:timezone":"Asia/Kolkata",
    "iso:country":"IN",
    "ks:ks_alt_nam":"KHADARA",
    "ks:ks_name":"Khadara",
    "ks:ks_pop":58,
    "ks:ks_type":"HABITATION",
    "ks:ks_uagg_main":0,
    "name:ara_x_preferred":[
        "\u062e\u0636\u0631\u0629"
    ],
    "name:azb_x_preferred":[
        "\u062e\u0636\u0631\u0647"
    ],
    "name:eng_x_preferred":[
        "Khadara"
    ],
    "name:fas_x_preferred":[
        "\u062e\u0636\u0631\u0647"
    ],
    "name:fra_x_preferred":[
        "Khadra"
    ],
    "name:ita_x_preferred":[
        "Khadra"
    ],
    "name:kab_x_preferred":[
        "Xe\u1e0dra"
    ],
    "name:msa_x_preferred":[
        "Khadra"
    ],
    "name:por_x_preferred":[
        "Khadra"
    ],
    "name:ron_x_preferred":[
        "Khadra"
    ],
    "name:spa_x_preferred":[
        "Khadra"
    ],
    "name:vie_x_preferred":[
        "Khadra"
    ],
    "wof:name":"Khadara",
    "wof:placetype":"neighbourhood",
    "wof:population":58
},
  "geometry": {"coordinates":[81.90363499999999,26.464297],"type":"Point"}
}