{
  "type": "Feature",
  "properties": {
    "iso:country":"IN",
    "ks:ks_alt_nam":"Gunva mulgam",
    "ks:ks_name":"Gunva Mulgam",
    "ks:ks_pop":147,
    "ks:ks_type":"HABITATION",
    "name:eng_x_preferred":[
        "Gunva Mulgam"
    ],
    "wof:name":"Gunva Mulgam",
    "wof:placetype":"locality",
    "wof:population":147
},
  "geometry": {"coordinates":[73.37691700000001,20.561583],"type":"Point"}
}