{
  "type": "Feature",
  "properties": {
    "iso:country":"IN",
    "ks:ks_name":"Salganga Grant",
    "ks:ks_pop":622,
    "ks:ks_type":"VILLAGE",
    "ks:ks_uagg_main":0,
    "name:eng_x_preferred":[
        "Salganga Grant"
    ],
    "wof:name":"Salganga Grant",
    "wof:placetype":"neighbourhood",
    "wof:population":622
},
  "geometry": {"coordinates":[92.955085,24.929264],"type":"Point"}
}