{
  "type": "Feature",
  "properties": {
    "gn:admin1_code":"25.0",
    "gn:asciiname":"Rangarajudukhandigai",
    "gn:country_code":"IN",
    "gn:dem":197,
    "gn:feature_class":"P",
    "gn:feature_code":"PPL",
    "gn:name":"Rangar\u0101judukhandigai",
    "gn:population":0,
    "gn:timezone":"Asia/Kolkata",
    "iso:country":"IN",
    "wof:name":"Rangarajudukhandigai",
    "wof:placetype":"locality"
},
  "geometry": {"coordinates":[79.43755999999998,13.23365],"type":"Point"}
}