{
  "type": "Feature",
  "properties": {
    "gn:admin1_code":"12.0",
    "gn:admin2_code":"8.0",
    "gn:asciiname":"Bon",
    "gn:country_code":"IN",
    "gn:dem":1583,
    "gn:feature_class":"P",
    "gn:feature_code":"PPL",
    "gn:name":"Bon",
    "gn:population":0,
    "gn:timezone":"Asia/Kolkata",
    "iso:country":"IN",
    "name:eng_x_preferred":[
        "Bon"
    ],
    "wof:name":"Bon",
    "wof:placetype":"locality"
},
  "geometry": {"coordinates":[74.57825,34.26926],"type":"Point"}
}