{
  "type": "Feature",
  "properties": {
    "iso:country":"IN",
    "ks:ks_name":"Velvach",
    "ks:ks_pop":3579,
    "ks:ks_type":"VILLAGE",
    "name:eng_x_preferred":[
        "Velvach"
    ],
    "wof:name":"Velvach",
    "wof:placetype":"locality",
    "wof:population":3579
},
  "geometry": {"coordinates":[73.09545199999999,20.484096],"type":"Point"}
}