{
  "type": "Feature",
  "properties": {
    "iso:country":"IN",
    "ks:ks_name":"Machavaram",
    "ks:ks_pop":7165,
    "ks:ks_type":"VILLAGE",
    "ks:ks_uagg_main":0,
    "name:eng_x_preferred":[
        "Machavaram"
    ],
    "wof:name":"Machavaram",
    "wof:placetype":"neighbourhood",
    "wof:population":7165
},
  "geometry": {"coordinates":[81.979787,16.84692],"type":"Point"}
}