{
  "type": "Feature",
  "properties": {
    "iso:country":"IN",
    "ks:ks_name":"Jarwa Bazar",
    "ks:ks_pop":466,
    "ks:ks_type":"HABITATION",
    "name:eng_x_preferred":[
        "Jarwa Bazar"
    ],
    "wof:name":"Jarwa Bazar",
    "wof:placetype":"locality",
    "wof:population":466
},
  "geometry": {"coordinates":[82.524575,27.649543],"type":"Point"}
}