{
  "type": "Feature",
  "properties": {
    "iso:country":"IN",
    "ks:ks_name":"Bhudhipada",
    "ks:ks_pop":491,
    "ks:ks_type":"VILLAGE",
    "name:eng_x_preferred":[
        "Bhudhipada"
    ],
    "wof:name":"Bhudhipada",
    "wof:placetype":"locality",
    "wof:population":491
},
  "geometry": {"coordinates":[85.739598,21.219244],"type":"Point"}
}