{
  "type": "Feature",
  "properties": {
    "iso:country":"IN",
    "ks:ks_name":"Palli",
    "ks:ks_pop":231,
    "ks:ks_type":"HABITATION",
    "name:eng_x_preferred":[
        "Palli"
    ],
    "wof:name":"Palli",
    "wof:placetype":"locality",
    "wof:population":231
},
  "geometry": {"coordinates":[75.11133700000001,13.072203],"type":"Point"}
}