{
  "type": "Feature",
  "properties": {
    "iso:country":"IN",
    "ks:ks_name":"Padmaniya",
    "ks:ks_pop":601,
    "ks:ks_type":"VILLAGE",
    "name:eng_x_preferred":[
        "Padmaniya"
    ],
    "wof:name":"Padmaniya",
    "wof:placetype":"locality",
    "wof:population":601
},
  "geometry": {"coordinates":[81.205602,23.219587],"type":"Point"}
}