{
  "type": "Feature",
  "properties": {
    "iso:country":"IN",
    "ks:ks_name":"Gunangabali",
    "ks:ks_pop":21,
    "ks:ks_type":"VILLAGE",
    "name:eng_x_preferred":[
        "Gunangabali"
    ],
    "wof:name":"Gunangabali",
    "wof:placetype":"locality",
    "wof:population":21
},
  "geometry": {"coordinates":[83.76725399999999,19.437147],"type":"Point"}
}