{
  "type": "Feature",
  "properties": {
    "iso:country":"IN",
    "ks:ks_name":"Hasuadand",
    "ks:ks_pop":100,
    "ks:ks_type":"HABITATION",
    "name:eng_x_preferred":[
        "Hasuadand"
    ],
    "wof:name":"Hasuadand",
    "wof:placetype":"locality",
    "wof:population":100
},
  "geometry": {"coordinates":[83.55978,23.453711],"type":"Point"}
}