{
  "type": "Feature",
  "properties": {
    "iso:country":"IN",
    "ks:ks_name":"Gudurisahi",
    "ks:ks_pop":76,
    "ks:ks_type":"VILLAGE",
    "name:eng_x_preferred":[
        "Gudurisahi"
    ],
    "wof:name":"Gudurisahi",
    "wof:placetype":"locality",
    "wof:population":76
},
  "geometry": {"coordinates":[84.289438,20.455353],"type":"Point"}
}