{
  "type": "Feature",
  "properties": {
    "iso:country":"IN",
    "ks:ks_alt_nam":"KALAI BASTI",
    "ks:ks_name":"Kalai Basti",
    "ks:ks_pop":114,
    "ks:ks_type":"HABITATION",
    "name:eng_x_preferred":[
        "Kalai Basti"
    ],
    "wof:name":"Kalai Basti",
    "wof:placetype":"locality",
    "wof:population":114
},
  "geometry": {"coordinates":[91.738697,23.917606],"type":"Point"}
}