{
  "type": "Feature",
  "properties": {
    "gn:admin1_code":"34.0",
    "gn:admin2_code":"220.0",
    "gn:asciiname":"Ghazipur",
    "gn:country_code":"IN",
    "gn:dem":54,
    "gn:feature_class":"P",
    "gn:feature_code":"PPL",
    "gn:name":"Gh\u0101z\u012bpur",
    "gn:population":0,
    "gn:timezone":"Asia/Kolkata",
    "iso:country":"IN",
    "wof:name":"Ghazipur",
    "wof:placetype":"locality"
},
  "geometry": {"coordinates":[85.4179,25.69296],"type":"Point"}
}