{
  "type": "Feature",
  "properties": {
    "iso:country":"IN",
    "ks:ks_name":"Gurdung",
    "ks:ks_pop":177,
    "ks:ks_type":"HABITATION",
    "name:eng_x_preferred":[
        "Gurdung"
    ],
    "wof:name":"Gurdung",
    "wof:placetype":"locality",
    "wof:population":177
},
  "geometry": {"coordinates":[88.156649,27.086355],"type":"Point"}
}