{
  "type": "Feature",
  "properties": {
    "gn:admin1_code":"36.0",
    "gn:admin2_code":"133.0",
    "gn:asciiname":"Khusropur",
    "gn:country_code":"IN",
    "gn:dem":249,
    "gn:feature_class":"P",
    "gn:feature_code":"PPL",
    "gn:name":"Khusropur",
    "gn:population":0,
    "gn:timezone":"Asia/Kolkata",
    "iso:country":"IN",
    "name:ben_x_preferred":[
        "\u0996\u09c1\u09b8\u09b0\u09cb\u09aa\u09c1\u09b0"
    ],
    "name:ceb_x_preferred":[
        "Khusropur"
    ],
    "name:swe_x_preferred":[
        "Khusropur"
    ],
    "wof:name":"Khusropur",
    "wof:placetype":"neighbourhood"
},
  "geometry": {"coordinates":[77.58046,29.51194],"type":"Point"}
}