{
  "type": "Feature",
  "properties": {
    "iso:country":"IN",
    "ks:ks_name":"Nadi Falia",
    "ks:ks_pop":592,
    "ks:ks_type":"HABITATION",
    "name:eng_x_preferred":[
        "Nadi Falia"
    ],
    "wof:name":"Nadi Falia",
    "wof:placetype":"locality",
    "wof:population":592
},
  "geometry": {"coordinates":[74.01986100000001,22.875028],"type":"Point"}
}