{
  "type": "Feature",
  "properties": {
    "iso:country":"IN",
    "ks:ks_name":"Ati",
    "ks:ks_pop":2795,
    "ks:ks_type":"VILLAGE",
    "name:eng_x_preferred":[
        "Ati"
    ],
    "wof:name":"Ati",
    "wof:placetype":"locality",
    "wof:population":2795
},
  "geometry": {"coordinates":[71.302379,25.697574],"type":"Point"}
}