{
  "type": "Feature",
  "properties": {
    "gn:admin1_code":"21.0",
    "gn:admin2_code":"396.0",
    "gn:asciiname":"Derkapadu",
    "gn:country_code":"IN",
    "gn:dem":401,
    "gn:feature_class":"P",
    "gn:feature_code":"PPL",
    "gn:name":"Derkap\u0101du",
    "gn:population":0,
    "gn:timezone":"Asia/Kolkata",
    "iso:country":"IN",
    "ks:ks_alt_nam":"Derkap\u0101du",
    "ks:ks_name":"Derkapadu",
    "ks:ks_pop":327,
    "ks:ks_type":"VILLAGE",
    "name:eng_x_preferred":[
        "Derkapadu"
    ],
    "name:eng_x_variant":[
        "Derkap\u0101du"
    ],
    "wof:name":"Derkapadu",
    "wof:placetype":"locality",
    "wof:population":327
},
  "geometry": {"coordinates":[83.51660099999999,19.161233],"type":"Point"}
}