{
  "type": "Feature",
  "properties": {
    "gn:admin1_code":"21.0",
    "gn:admin2_code":"396.0",
    "gn:asciiname":"Derkapadu",
    "gn:country_code":"IN",
    "gn:dem":401,
    "gn:feature_class":"P",
    "gn:feature_code":"PPL",
    "gn:name":"Derkap\u0101du",
    "gn:population":0,
    "gn:timezone":"Asia/Kolkata",
    "iso:country":"IN",
    "wof:name":"Derkapadu",
    "wof:placetype":"locality"
},
  "geometry": {"coordinates":[83.51646,19.16092],"type":"Point"}
}