{
  "type": "Feature",
  "properties": {
    "iso:country":"IN",
    "ks:ks_name":"Bir Chandra Para",
    "ks:ks_pop":204,
    "ks:ks_type":"HABITATION",
    "name:eng_x_preferred":[
        "Bir Chandra Para"
    ],
    "wof:name":"Bir Chandra Para",
    "wof:placetype":"locality",
    "wof:population":204
},
  "geometry": {"coordinates":[91.455254,24.000367],"type":"Point"}
}