{
  "type": "Feature",
  "properties": {
    "iso:country":"IN",
    "ks:ks_name":"Lakhibad",
    "ks:ks_pop":99,
    "ks:ks_type":"VILLAGE",
    "name:eng_x_preferred":[
        "Lakhibad"
    ],
    "wof:name":"Lakhibad",
    "wof:placetype":"locality",
    "wof:population":99
},
  "geometry": {"coordinates":[87.070213,24.340335],"type":"Point"}
}