{
  "type": "Feature",
  "properties": {
    "gn:admin1_code":"2.0",
    "gn:admin2_code":"553.0",
    "gn:asciiname":"Ganjikunta",
    "gn:country_code":"IN",
    "gn:dem":294,
    "gn:feature_class":"P",
    "gn:feature_code":"PPL",
    "gn:name":"Ganjikunta",
    "gn:population":0,
    "gn:timezone":"Asia/Kolkata",
    "iso:country":"IN",
    "name:hin_x_preferred":[
        "\u0917\u0902\u091c\u093f\u0915\u0941\u0902\u091f"
    ],
    "name:new_x_preferred":[
        "\u0917\u0902\u091c\u093f\u0915\u0941\u0902\u091f"
    ],
    "name:tel_x_preferred":[
        "\u0c17\u0c02\u0c1c\u0c3f\u0c15\u0c41\u0c02\u0c1f"
    ],
    "wof:name":"Ganjikunta",
    "wof:placetype":"locality"
},
  "geometry": {"coordinates":[77.68955,14.95445],"type":"Point"}
}