{
  "type": "Feature",
  "properties": {
    "iso:country":"IN",
    "ks:ks_name":"Ramama Bada",
    "ks:ks_pop":192,
    "ks:ks_type":"HABITATION",
    "name:eng_x_preferred":[
        "Ramama Bada"
    ],
    "wof:name":"Ramama Bada",
    "wof:placetype":"locality",
    "wof:population":192
},
  "geometry": {"coordinates":[81.94089,27.707676],"type":"Point"}
}