{
  "type": "Feature",
  "properties": {
    "iso:country":"IN",
    "ks:ks_name":"Panchbedi Ryt",
    "ks:ks_pop":567,
    "ks:ks_type":"VILLAGE",
    "name:eng_x_preferred":[
        "Panchbedi Ryt"
    ],
    "wof:name":"Panchbedi Ryt",
    "wof:placetype":"locality",
    "wof:population":567
},
  "geometry": {"coordinates":[76.47993099999999,21.706573],"type":"Point"}
}