{
  "type": "Feature",
  "properties": {
    "gn:admin1_code":"19.0",
    "gn:admin2_code":"581.0",
    "gn:asciiname":"Diguvachintapalli",
    "gn:country_code":"IN",
    "gn:dem":749,
    "gn:feature_class":"P",
    "gn:feature_code":"PPL",
    "gn:name":"Diguvachintapalli",
    "gn:population":0,
    "gn:timezone":"Asia/Kolkata",
    "iso:country":"IN",
    "wof:name":"Diguvachintapalli",
    "wof:placetype":"locality"
},
  "geometry": {"coordinates":[78.27495,13.53008],"type":"Point"}
}