{
  "type": "Feature",
  "properties": {
    "gn:admin1_code":"35",
    "gn:admin2_code":"436.0",
    "gn:asciiname":"Khelagaon",
    "gn:country_code":"IN",
    "gn:dem":412,
    "gn:feature_class":"P",
    "gn:feature_code":"PPL",
    "gn:name":"Khel\u0101gaon",
    "gn:population":0,
    "gn:timezone":"Asia/Kolkata",
    "iso:country":"IN",
    "wof:name":"Khelagaon",
    "wof:placetype":"locality"
},
  "geometry": {"coordinates":[76.15649000000001,23.78571],"type":"Point"}
}