{
  "type": "Feature",
  "properties": {
    "iso:country":"IN",
    "ks:ks_name":"Chak Malyawas",
    "ks:ks_pop":67,
    "ks:ks_type":"HABITATION",
    "name:eng_x_preferred":[
        "Chak Malyawas"
    ],
    "wof:name":"Chak Malyawas",
    "wof:placetype":"locality",
    "wof:population":67
},
  "geometry": {"coordinates":[76.323256,26.727461],"type":"Point"}
}