{
  "type": "Feature",
  "properties": {
    "gn:admin1_code":"36",
    "gn:admin2_code":"158.0",
    "gn:asciiname":"Samsher Bahadur",
    "gn:country_code":"IN",
    "gn:dem":115,
    "gn:feature_class":"P",
    "gn:feature_code":"PPL",
    "gn:name":"Samsher Bah\u0101dur",
    "gn:population":0,
    "gn:timezone":"Asia/Kolkata",
    "iso:country":"IN",
    "wof:name":"Samsher Bahadur",
    "wof:placetype":"locality"
},
  "geometry": {"coordinates":[81.43344999999999,26.53674],"type":"Point"}
}