{
  "type": "Feature",
  "properties": {
    "iso:country":"IN",
    "ks:ks_name":"Chedi Ka Purwa",
    "ks:ks_pop":148,
    "ks:ks_type":"HABITATION",
    "ks:ks_uagg_main":0,
    "name:eng_x_preferred":[
        "Chedi Ka Purwa"
    ],
    "wof:name":"Chedi Ka Purwa",
    "wof:placetype":"neighbourhood",
    "wof:population":148
},
  "geometry": {"coordinates":[82.150001,26.45908],"type":"Point"}
}