{
  "type": "Feature",
  "properties": {
    "iso:country":"IN",
    "ks:ks_name":"Pillumadaikadu",
    "ks:ks_pop":1045,
    "ks:ks_type":"HABITATION",
    "ks:ks_uagg_main":0,
    "name:eng_x_preferred":[
        "Pillumadaikadu"
    ],
    "wof:name":"Pillumadaikadu",
    "wof:placetype":"locality",
    "wof:population":1045
},
  "geometry": {"coordinates":[77.79137,11.365131],"type":"Point"}
}