{
  "type": "Feature",
  "properties": {
    "iso:country":"IN",
    "ks:ks_name":"Uddanmahadlu",
    "ks:ks_pop":8,
    "ks:ks_type":"HABITATION",
    "name:eng_x_preferred":[
        "Uddanmahadlu"
    ],
    "wof:name":"Uddanmahadlu",
    "wof:placetype":"locality",
    "wof:population":8
},
  "geometry": {"coordinates":[75.398498,13.51916],"type":"Point"}
}