{
  "type": "Feature",
  "properties": {
    "gn:admin1_code":"36",
    "gn:admin2_code":"154.0",
    "gn:asciiname":"Pahladpur",
    "gn:country_code":"IN",
    "gn:dem":140,
    "gn:feature_class":"P",
    "gn:feature_code":"PPL",
    "gn:name":"Pahl\u0101dpur",
    "gn:population":0,
    "gn:timezone":"Asia/Kolkata",
    "iso:country":"IN",
    "ks:ks_alt_nam":"Pahl\u0101dpur",
    "ks:ks_name":"Pahladpur",
    "ks:ks_pop":0,
    "ks:ks_type":"VILLAGE",
    "name:eng_x_preferred":[
        "Pahladpur"
    ],
    "name:eng_x_variant":[
        "Pahl\u0101dpur"
    ],
    "wof:name":"Pahladpur",
    "wof:placetype":"locality",
    "wof:population":0
},
  "geometry": {"coordinates":[80.91257899999999,27.723247],"type":"Point"}
}