{
  "type": "Feature",
  "properties": {
    "gn:admin1_code":"21",
    "gn:admin2_code":"394.0",
    "gn:asciiname":"Sarabong",
    "gn:country_code":"IN",
    "gn:dem":336,
    "gn:feature_class":"P",
    "gn:feature_code":"PPL",
    "gn:name":"S\u0101r\u0101bong",
    "gn:population":0,
    "gn:timezone":"Asia/Kolkata",
    "iso:country":"IN",
    "name:und_x_variant":[
        "S\u0101r\u0101bong",
        "Sar\u0101bang"
    ],
    "wof:name":"Sarabong",
    "wof:placetype":"locality"
},
  "geometry": {"coordinates":[82.4633,20.8133],"type":"Point"}
}