{
  "type": "Feature",
  "properties": {
    "iso:country":"IN",
    "ks:ks_name":"Harirampur",
    "ks:ks_pop":2047,
    "ks:ks_type":"VILLAGE",
    "ks:ks_uagg_main":0,
    "name:eng_x_preferred":[
        "Harirampur"
    ],
    "wof:name":"Harirampur",
    "wof:placetype":"neighbourhood",
    "wof:population":2047
},
  "geometry": {"coordinates":[88.42106099999999,24.252096],"type":"Point"}
}