{
  "type": "Feature",
  "properties": {
    "iso:country":"IN",
    "ks:ks_name":"Vallaithadam",
    "ks:ks_pop":1092,
    "ks:ks_type":"HABITATION",
    "name:eng_x_preferred":[
        "Vallaithadam"
    ],
    "wof:name":"Vallaithadam",
    "wof:placetype":"locality",
    "wof:population":1092
},
  "geometry": {"coordinates":[76.135344,10.447324],"type":"Point"}
}