{
  "type": "Feature",
  "properties": {
    "iso:country":"IN",
    "ks:ks_name":"Ambaragodlu",
    "ks:ks_pop":174,
    "ks:ks_type":"VILLAGE",
    "name:eng_x_preferred":[
        "Ambaragodlu"
    ],
    "wof:name":"Ambaragodlu",
    "wof:placetype":"locality",
    "wof:population":174
},
  "geometry": {"coordinates":[74.977886,14.069618],"type":"Point"}
}