{
  "type": "Feature",
  "properties": {
    "gn:admin1_code":"16.0",
    "gn:admin2_code":"521.0",
    "gn:asciiname":"Vishrantwadi",
    "gn:country_code":"IN",
    "gn:dem":556,
    "gn:feature_class":"P",
    "gn:feature_code":"PPL",
    "gn:name":"Vishrantwadi",
    "gn:population":0,
    "gn:timezone":"Asia/Kolkata",
    "iso:country":"IN",
    "name:tam_x_preferred":[
        "\u0bb5\u0bbf\u0bb7\u0bcd\u0bb0\u0ba8\u0bcd\u0ba4\u0bb5\u0bbe\u0b9f\u0bbf"
    ],
    "wof:name":"Vishrantwadi",
    "wof:placetype":"neighbourhood"
},
  "geometry": {"coordinates":[73.87962,18.57217],"type":"Point"}
}