{
  "type": "Feature",
  "properties": {
    "iso:country":"IN",
    "ks:ks_name":"Suri Para",
    "ks:ks_pop":595,
    "ks:ks_type":"HABITATION",
    "name:eng_x_preferred":[
        "Suri Para"
    ],
    "wof:name":"Suri Para",
    "wof:placetype":"locality",
    "wof:population":595
},
  "geometry": {"coordinates":[88.688861,22.264079],"type":"Point"}
}