{
  "type": "Feature",
  "properties": {
    "iso:country":"IN",
    "ks:ks_name":"Dumduntola",
    "ks:ks_pop":67,
    "ks:ks_type":"HABITATION",
    "name:eng_x_preferred":[
        "Dumduntola"
    ],
    "wof:name":"Dumduntola",
    "wof:placetype":"locality",
    "wof:population":67
},
  "geometry": {"coordinates":[80.99813899999999,20.648457],"type":"Point"}
}