{
  "type": "Feature",
  "properties": {
    "gn:admin1_code":"11.0",
    "gn:admin2_code":"31.0",
    "gn:asciiname":"Badhel",
    "gn:country_code":"IN",
    "gn:dem":1224,
    "gn:feature_class":"P",
    "gn:feature_code":"PPL",
    "gn:name":"Badhel",
    "gn:population":0,
    "gn:timezone":"Asia/Kolkata",
    "iso:country":"IN",
    "wof:name":"Badhel",
    "wof:placetype":"locality"
},
  "geometry": {"coordinates":[77.03491,30.9754],"type":"Point"}
}