{
  "type": "Feature",
  "properties": {
    "gn:admin1_code":"25.0",
    "gn:admin2_code":"605.0",
    "gn:asciiname":"Vellanayakkaneri",
    "gn:country_code":"IN",
    "gn:dem":455,
    "gn:feature_class":"P",
    "gn:feature_code":"PPL",
    "gn:name":"Vellan\u0101yakkaneri",
    "gn:population":0,
    "gn:timezone":"Asia/Kolkata",
    "iso:country":"IN",
    "wof:name":"Vellanayakkaneri",
    "wof:placetype":"locality"
},
  "geometry": {"coordinates":[78.49580999999998,12.59936],"type":"Point"}
}