{
  "type": "Feature",
  "properties": {
    "iso:country":"IN",
    "ks:ks_name":"Rathava Faliya",
    "ks:ks_pop":620,
    "ks:ks_type":"HABITATION",
    "name:eng_x_preferred":[
        "Rathava Faliya"
    ],
    "wof:name":"Rathava Faliya",
    "wof:placetype":"locality",
    "wof:population":620
},
  "geometry": {"coordinates":[73.45013899999999,22.885631],"type":"Point"}
}