{
  "type": "Feature",
  "properties": {
    "gn:admin1_code":"23.0",
    "gn:admin2_code":"36.0",
    "gn:asciiname":"Nijran",
    "gn:country_code":"IN",
    "gn:dem":234,
    "gn:feature_class":"P",
    "gn:feature_code":"PPL",
    "gn:name":"Nijr\u0101n",
    "gn:population":0,
    "gn:timezone":"Asia/Kolkata",
    "iso:country":"IN",
    "wof:name":"Nijran",
    "wof:placetype":"locality"
},
  "geometry": {"coordinates":[75.47795000000001,31.26779],"type":"Point"}
}