{
  "type": "Feature",
  "properties": {
    "iso:country":"IN",
    "ks:ks_name":"Jhanpur",
    "ks:ks_pop":259,
    "ks:ks_type":"VILLAGE",
    "name:eng_x_preferred":[
        "Jhanpur"
    ],
    "wof:name":"Jhanpur",
    "wof:placetype":"locality",
    "wof:population":259
},
  "geometry": {"coordinates":[82.323229,23.645643],"type":"Point"}
}