{
  "type": "Feature",
  "properties": {
    "iso:country":"IN",
    "ks:ks_name":"Theelavath Thanda",
    "ks:ks_pop":162,
    "ks:ks_type":"HABITATION",
    "name:eng_x_preferred":[
        "Theelavath Thanda"
    ],
    "wof:name":"Theelavath Thanda",
    "wof:placetype":"locality",
    "wof:population":162
},
  "geometry": {"coordinates":[79.93061400000001,17.387466],"type":"Point"}
}