{
  "type": "Feature",
  "properties": {
    "iso:country":"IN",
    "ks:ks_alt_nam":"nallisara",
    "ks:ks_name":"Nallisara",
    "ks:ks_pop":50,
    "ks:ks_type":"HABITATION",
    "name:eng_x_preferred":[
        "Nallisara"
    ],
    "wof:name":"Nallisara",
    "wof:placetype":"locality",
    "wof:population":50
},
  "geometry": {"coordinates":[75.64887,13.709421],"type":"Point"}
}