{
  "type": "Feature",
  "properties": {
    "gn:admin1_code":"19.0",
    "gn:admin2_code":"563.0",
    "gn:asciiname":"Melin Savle",
    "gn:country_code":"IN",
    "gn:dem":544,
    "gn:feature_class":"P",
    "gn:feature_code":"PPL",
    "gn:name":"Melin Savle",
    "gn:population":0,
    "gn:timezone":"Asia/Kolkata",
    "iso:country":"IN",
    "ks:ks_name":"Melinsavale",
    "ks:ks_pop":72,
    "ks:ks_type":"HABITATION",
    "name:eng_x_preferred":[
        "Melinsavale"
    ],
    "name:eng_x_variant":[
        "Melin Savle"
    ],
    "wof:name":"Melinsavale",
    "wof:placetype":"locality",
    "wof:population":72
},
  "geometry": {"coordinates":[74.634247,14.599405],"type":"Point"}
}