{
  "type": "Feature",
  "properties": {
    "iso:country":"IN",
    "ks:ks_name":"Vaalupana",
    "ks:ks_pop":337,
    "ks:ks_type":"HABITATION",
    "name:eng_x_preferred":[
        "Vaalupana"
    ],
    "wof:name":"Vaalupana",
    "wof:placetype":"locality",
    "wof:population":337
},
  "geometry": {"coordinates":[76.959282,8.896479],"type":"Point"}
}