{
  "type": "Feature",
  "properties": {
    "iso:country":"IN",
    "ks:ks_name":"Hatubhanga",
    "ks:ks_pop":2475,
    "ks:ks_type":"VILLAGE",
    "name:eng_x_preferred":[
        "Hatubhanga"
    ],
    "wof:name":"Hatubhanga",
    "wof:placetype":"locality",
    "wof:population":2475
},
  "geometry": {"coordinates":[88.633405,23.283857],"type":"Point"}
}