{
  "type": "Feature",
  "properties": {
    "gn:admin1_code":"19.0",
    "gn:admin2_code":"582.0",
    "gn:asciiname":"Chinnahalli",
    "gn:country_code":"IN",
    "gn:dem":857,
    "gn:feature_class":"P",
    "gn:feature_code":"PPL",
    "gn:name":"Chinnahalli",
    "gn:population":0,
    "gn:timezone":"Asia/Kolkata",
    "iso:country":"IN",
    "wof:name":"Chinnahalli",
    "wof:placetype":"locality"
},
  "geometry": {"coordinates":[77.68485,13.65696],"type":"Point"}
}