{
  "type": "Feature",
  "properties": {
    "gn:admin1_code":"36",
    "gn:admin2_code":"187.0",
    "gn:asciiname":"Rampur",
    "gn:country_code":"IN",
    "gn:dem":87,
    "gn:feature_class":"P",
    "gn:feature_code":"PPL",
    "gn:name":"R\u0101mpur",
    "gn:population":0,
    "gn:timezone":"Asia/Kolkata",
    "iso:country":"IN",
    "name:ben_x_preferred":[
        "\u09b0\u09be\u09ae\u09aa\u09c1\u09b0"
    ],
    "name:bih_x_preferred":[
        "\u0930\u093e\u092e\u092a\u0941\u0930"
    ],
    "name:bpy_x_preferred":[
        "\u09b0\u09be\u09ae\u09aa\u09c1\u09b0"
    ],
    "name:cat_x_preferred":[
        "Rampur"
    ],
    "name:ceb_x_preferred":[
        "Rampur"
    ],
    "name:deu_x_preferred":[
        "Rampur"
    ],
    "name:fra_x_preferred":[
        "Rampur"
    ],
    "name:ita_x_preferred":[
        "Rampur"
    ],
    "name:new_x_preferred":[
        "\u0930\u093e\u092e\u092a\u0941\u0930"
    ],
    "name:nld_x_preferred":[
        "Rampur"
    ],
    "name:pnb_x_preferred":[
        "\u0631\u0627\u0645 \u067e\u0648\u0631"
    ],
    "name:pol_x_preferred":[
        "Rampur"
    ],
    "name:rus_x_preferred":[
        "\u0420\u0430\u043c\u043f\u0443\u0440"
    ],
    "name:snd_x_preferred":[
        "\u0631\u0627\u0645 \u067e\u0648\u0631"
    ],
    "name:swe_x_preferred":[
        "Rampur"
    ],
    "name:urd_x_preferred":[
        "\u0631\u0627\u0645 \u067e\u0648\u0631"
    ],
    "wof:name":"Rampur",
    "wof:placetype":"locality"
},
  "geometry": {"coordinates":[83.54456999999999,26.99423],"type":"Point"}
}