{
  "type": "Feature",
  "properties": {
    "iso:country":"IN",
    "ks:ks_alt_nam":"Bhakarapet ST Colony",
    "ks:ks_name":"Bhakarapet St Colony",
    "ks:ks_pop":35,
    "ks:ks_type":"HABITATION",
    "name:eng_x_preferred":[
        "Bhakarapet St Colony"
    ],
    "wof:name":"Bhakarapet St Colony",
    "wof:placetype":"locality",
    "wof:population":35
},
  "geometry": {"coordinates":[78.72063300000001,14.007833],"type":"Point"}
}