{
  "type": "Feature",
  "properties": {
    "gn:admin1_code":"11.0",
    "gn:admin2_code":"31.0",
    "gn:asciiname":"Danghari",
    "gn:country_code":"IN",
    "gn:dem":1381,
    "gn:feature_class":"P",
    "gn:feature_code":"PPL",
    "gn:name":"Dangh\u0101ri",
    "gn:population":0,
    "gn:timezone":"Asia/Kolkata",
    "iso:country":"IN",
    "wof:name":"Danghari",
    "wof:placetype":"locality"
},
  "geometry": {"coordinates":[77.02148000000003,30.92395],"type":"Point"}
}