{
  "type": "Feature",
  "properties": {
    "iso:country":"IN",
    "ks:ks_name":"Badho",
    "ks:ks_pop":0,
    "ks:ks_type":"VILLAGE",
    "name:eng_x_preferred":[
        "Badho"
    ],
    "wof:name":"Badho",
    "wof:placetype":"locality",
    "wof:population":0
},
  "geometry": {"coordinates":[83.243847,25.255935],"type":"Point"}
}