{
  "type": "Feature",
  "properties": {
    "iso:country":"IN",
    "ks:ks_name":"Ranpada",
    "ks:ks_pop":500,
    "ks:ks_type":"VILLAGE",
    "name:eng_x_preferred":[
        "Ranpada"
    ],
    "wof:name":"Ranpada",
    "wof:placetype":"locality",
    "wof:population":500
},
  "geometry": {"coordinates":[73.690333,20.609556],"type":"Point"}
}