{
  "type": "Feature",
  "properties": {
    "iso:country":"IN",
    "ks:ks_name":"Asulli",
    "ks:ks_pop":469,
    "ks:ks_type":"VILLAGE",
    "name:eng_x_preferred":[
        "Asulli"
    ],
    "wof:name":"Asulli",
    "wof:placetype":"locality",
    "wof:population":469
},
  "geometry": {"coordinates":[74.356325,15.261657],"type":"Point"}
}