{
  "type": "Feature",
  "properties": {
    "iso:country":"IN",
    "ks:ks_name":"Keherua",
    "ks:ks_pop":766,
    "ks:ks_type":"HABITATION",
    "name:eng_x_preferred":[
        "Keherua"
    ],
    "wof:name":"Keherua",
    "wof:placetype":"locality",
    "wof:population":766
},
  "geometry": {"coordinates":[91.49397500000001,26.541637],"type":"Point"}
}