{
  "type": "Feature",
  "properties": {
    "iso:country":"IN",
    "ks:ks_name":"Chikkaguttahalli",
    "ks:ks_pop":80,
    "ks:ks_type":"HABITATION",
    "name:eng_x_preferred":[
        "Chikkaguttahalli"
    ],
    "wof:name":"Chikkaguttahalli",
    "wof:placetype":"locality",
    "wof:population":80
},
  "geometry": {"coordinates":[77.992638,13.390771],"type":"Point"}
}