{
  "type": "Feature",
  "properties": {
    "iso:country":"IN",
    "ks:ks_name":"Ghadiwadi",
    "ks:ks_pop":158,
    "ks:ks_type":"HABITATION",
    "name:eng_x_preferred":[
        "Ghadiwadi"
    ],
    "wof:name":"Ghadiwadi",
    "wof:placetype":"locality",
    "wof:population":158
},
  "geometry": {"coordinates":[73.46840400000001,16.41],"type":"Point"}
}