{
  "type": "Feature",
  "properties": {
    "iso:country":"IN",
    "ks:ks_name":"Dumaria Alias Dumriatanr",
    "ks:ks_pop":211,
    "ks:ks_type":"VILLAGE",
    "name:eng_x_preferred":[
        "Dumaria Alias Dumriatanr"
    ],
    "wof:name":"Dumaria Alias Dumriatanr",
    "wof:placetype":"locality",
    "wof:population":211
},
  "geometry": {"coordinates":[86.513865,23.874084],"type":"Point"}
}