{
  "type": "Feature",
  "properties": {
    "iso:country":"IN",
    "ks:ks_name":"Dhanwalpada",
    "ks:ks_pop":78,
    "ks:ks_type":"HABITATION",
    "name:eng_x_preferred":[
        "Dhanwalpada"
    ],
    "wof:name":"Dhanwalpada",
    "wof:placetype":"locality",
    "wof:population":78
},
  "geometry": {"coordinates":[73.191086,19.556793],"type":"Point"}
}