{
  "type": "Feature",
  "properties": {
    "gn:admin1_code":"36.0",
    "gn:admin2_code":"182.0",
    "gn:asciiname":"Pura Wazir Nau",
    "gn:country_code":"IN",
    "gn:dem":99,
    "gn:feature_class":"P",
    "gn:feature_code":"PPL",
    "gn:name":"Pura Wazir N\u0101u",
    "gn:population":0,
    "gn:timezone":"Asia/Kolkata",
    "iso:country":"IN",
    "wof:name":"Pura Wazir Nau",
    "wof:placetype":"neighbourhood"
},
  "geometry": {"coordinates":[82.39645,27.19149],"type":"Point"}
}