{
  "type": "Feature",
  "properties": {
    "gn:country":"IN",
    "gn:fcode":"PPL",
    "gn:pop":40214,
    "iso:country":"IN",
    "name:bpy_x_preferred":[
        "\u0997\u09c1\u09b0\u09b8\u09be\u09b9\u09be\u0987\u0997\u099e\u09cd\u099c"
    ],
    "name:ceb_x_preferred":[
        "Gursah\u0101iganj"
    ],
    "name:eng_x_preferred":[
        "Gursahaiganj"
    ],
    "name:ita_x_preferred":[
        "Gursahaiganj"
    ],
    "name:mlg_x_preferred":[
        "Gursahaiganj"
    ],
    "name:msa_x_preferred":[
        "Gursahaiganj"
    ],
    "name:nan_x_preferred":[
        "Gursahaiganj"
    ],
    "name:new_x_preferred":[
        "\u0917\u0941\u0930\u094d\u0938\u0939\u0948\u0917\u091e\u094d\u091c"
    ],
    "name:nld_x_preferred":[
        "Gursahaiganj"
    ],
    "name:pol_x_preferred":[
        "Gursahaiganj"
    ],
    "name:por_x_preferred":[
        "Gursahaiganj"
    ],
    "name:rus_x_preferred":[
        "\u0413\u0443\u0440\u0441\u0430\u0445\u0430\u0438\u0433\u0430\u043d\u0434\u0436"
    ],
    "name:swe_x_preferred":[
        "Gursah\u0101iganj"
    ],
    "name:urd_x_preferred":[
        "\u06af\u0631\u0633\u06c1\u0627\u0626\u06cc \u06af\u0646\u062c"
    ],
    "name:vie_x_preferred":[
        "Gursahaiganj"
    ],
    "name:zho_x_preferred":[
        "\u53e4\u5c14\u8428\u6d77\u7518\u6770"
    ],
    "qs:name":"Gursah\u0101iganj",
    "qs:photos_9r":0,
    "qs:photos_sr":0,
    "qs:pop_sr":"7",
    "wd:wordcount":292,
    "wof:name":"Gursah\u0101iganj",
    "wof:placetype":"locality",
    "wof:population":40214
},
  "geometry": {"coordinates":[79.71666999999999,27.11667],"type":"Point"}
}