{
  "type": "Feature",
  "properties": {
    "iso:country":"IN",
    "ks:ks_name":"Pata Palla",
    "ks:ks_pop":93,
    "ks:ks_type":"HABITATION",
    "name:eng_x_preferred":[
        "Pata Palla"
    ],
    "wof:name":"Pata Palla",
    "wof:placetype":"locality",
    "wof:population":93
},
  "geometry": {"coordinates":[78.555111,30.290384],"type":"Point"}
}