{
  "type": "Feature",
  "properties": {
    "iso:country":"IN",
    "ks:ks_name":"Padasahi",
    "ks:ks_pop":1105,
    "ks:ks_type":"VILLAGE",
    "name:eng_x_preferred":[
        "Padasahi"
    ],
    "wof:name":"Padasahi",
    "wof:placetype":"locality",
    "wof:population":1105
},
  "geometry": {"coordinates":[84.352757,19.405623],"type":"Point"}
}