{
  "type": "Feature",
  "properties": {
    "iso:country":"IN",
    "ks:ks_name":"Makarkol",
    "ks:ks_pop":678,
    "ks:ks_type":"VILLAGE",
    "name:eng_x_preferred":[
        "Makarkol"
    ],
    "wof:name":"Makarkol",
    "wof:placetype":"locality",
    "wof:population":678
},
  "geometry": {"coordinates":[87.01087200000001,22.684288],"type":"Point"}
}