{
  "type": "Feature",
  "properties": {
    "gn:admin1_code":"34.0",
    "gn:admin2_code":"229.0",
    "gn:asciiname":"Padman Bigha",
    "gn:country_code":"IN",
    "gn:dem":63,
    "gn:feature_class":"P",
    "gn:feature_code":"PPL",
    "gn:name":"Padman Bigha",
    "gn:population":0,
    "gn:timezone":"Asia/Kolkata",
    "iso:country":"IN",
    "ks:ks_name":"Praduman Bigha",
    "ks:ks_pop":175,
    "ks:ks_type":"HABITATION",
    "name:eng_x_preferred":[
        "Praduman Bigha"
    ],
    "name:eng_x_variant":[
        "Padman Bigha"
    ],
    "wof:name":"Praduman Bigha",
    "wof:placetype":"locality",
    "wof:population":175
},
  "geometry": {"coordinates":[85.37756899999999,25.155744],"type":"Point"}
}