{
  "type": "Feature",
  "properties": {
    "iso:country":"IN",
    "ks:ks_name":"Brindaban Chak",
    "ks:ks_pop":793,
    "ks:ks_type":"VILLAGE",
    "name:eng_x_preferred":[
        "Brindaban Chak"
    ],
    "wof:name":"Brindaban Chak",
    "wof:placetype":"locality",
    "wof:population":793
},
  "geometry": {"coordinates":[87.837119,22.407412],"type":"Point"}
}