{
  "type": "Feature",
  "properties": {
    "iso:country":"IN",
    "ks:ks_name":"Sapakamba",
    "ks:ks_pop":187,
    "ks:ks_type":"VILLAGE",
    "name:eng_x_preferred":[
        "Sapakamba"
    ],
    "wof:name":"Sapakamba",
    "wof:placetype":"locality",
    "wof:population":187
},
  "geometry": {"coordinates":[83.986628,20.229863],"type":"Point"}
}