{
  "type": "Feature",
  "properties": {
    "iso:country":"IN",
    "ks:ks_name":"Chehla",
    "ks:ks_pop":156,
    "ks:ks_type":"VILLAGE",
    "name:eng_x_preferred":[
        "Chehla"
    ],
    "wof:name":"Chehla",
    "wof:placetype":"locality",
    "wof:population":156
},
  "geometry": {"coordinates":[85.13721700000001,24.665778],"type":"Point"}
}