{
  "type": "Feature",
  "properties": {
    "gn:admin1_code":"24.0",
    "gn:admin2_code":"120",
    "gn:asciiname":"Jaithal",
    "gn:country_code":"IN",
    "gn:dem":291,
    "gn:feature_class":"P",
    "gn:feature_code":"PPL",
    "gn:name":"Jaithal",
    "gn:population":0,
    "gn:timezone":"Asia/Kolkata",
    "iso:country":"IN",
    "wof:name":"Jaithal",
    "wof:placetype":"locality"
},
  "geometry": {"coordinates":[75.60459,25.99059],"type":"Point"}
}