{
  "type": "Feature",
  "properties": {
    "iso:country":"IN",
    "ks:ks_name":"Katunagar",
    "ks:ks_pop":124,
    "ks:ks_type":"VILLAGE",
    "name:eng_x_preferred":[
        "Katunagar"
    ],
    "wof:name":"Katunagar",
    "wof:placetype":"locality",
    "wof:population":124
},
  "geometry": {"coordinates":[84.429315,21.721681],"type":"Point"}
}