{
  "type": "Feature",
  "properties": {
    "iso:country":"IN",
    "ks:ks_name":"Khokharchond Falia",
    "ks:ks_pop":165,
    "ks:ks_type":"HABITATION",
    "name:eng_x_preferred":[
        "Khokharchond Falia"
    ],
    "wof:name":"Khokharchond Falia",
    "wof:placetype":"locality",
    "wof:population":165
},
  "geometry": {"coordinates":[73.78230600000001,20.680694],"type":"Point"}
}