{
  "type": "Feature",
  "properties": {
    "iso:country":"IN",
    "ks:ks_name":"Yatnalli",
    "ks:ks_pop":71,
    "ks:ks_type":"HABITATION",
    "name:eng_x_preferred":[
        "Yatnalli"
    ],
    "wof:name":"Yatnalli",
    "wof:placetype":"locality",
    "wof:population":71
},
  "geometry": {"coordinates":[74.529551,14.195198],"type":"Point"}
}