{
  "type": "Feature",
  "properties": {
    "iso:country":"IN",
    "ks:ks_name":"Arual",
    "ks:ks_pop":2113,
    "ks:ks_type":"VILLAGE",
    "name:eng_x_preferred":[
        "Arual"
    ],
    "wof:name":"Arual",
    "wof:placetype":"neighbourhood",
    "wof:population":2113
},
  "geometry": {"coordinates":[86.339052,20.705798],"type":"Point"}
}