{
  "type": "Feature",
  "properties": {
    "gn:admin1_code":"19",
    "gn:admin2_code":"563.0",
    "gn:asciiname":"Hanajikai",
    "gn:country_code":"IN",
    "gn:dem":584,
    "gn:feature_class":"P",
    "gn:feature_code":"PPL",
    "gn:name":"Hanajikai",
    "gn:population":0,
    "gn:timezone":"Asia/Kolkata",
    "iso:country":"IN",
    "wof:name":"Hanajikai",
    "wof:placetype":"locality"
},
  "geometry": {"coordinates":[74.93741,14.33517],"type":"Point"}
}