{
  "type": "Feature",
  "properties": {
    "iso:country":"IN",
    "ks:ks_alt_nam":"B\u0101dsh\u0101hganj",
    "ks:ks_name":"Badshahganj",
    "ks:ks_type":"VILLAGE",
    "ks:ks_uagg_main":0,
    "name:eng_x_preferred":[
        "Badshahganj"
    ],
    "name:eng_x_variant":[
        "B\u0101dsh\u0101hganj"
    ],
    "wof:name":"Badshahganj",
    "wof:placetype":"neighbourhood"
},
  "geometry": {"coordinates":[85.174812,25.620641],"type":"Point"}
}