{
  "type": "Feature",
  "properties": {
    "iso:country":"IN",
    "ks:ks_name":"Babhnan Purwa",
    "ks:ks_pop":166,
    "ks:ks_type":"HABITATION",
    "ks:ks_uagg_main":0,
    "name:eng_x_preferred":[
        "Babhnan Purwa"
    ],
    "wof:name":"Babhnan Purwa",
    "wof:placetype":"neighbourhood",
    "wof:population":166
},
  "geometry": {"coordinates":[82.148416,27.029957],"type":"Point"}
}