{
  "type": "Feature",
  "properties": {
    "iso:country":"IN",
    "ks:ks_name":"Motipura",
    "ks:ks_pop":954,
    "ks:ks_type":"VILLAGE",
    "name:eng_x_preferred":[
        "Motipura"
    ],
    "wof:name":"Motipura",
    "wof:placetype":"locality",
    "wof:population":954
},
  "geometry": {"coordinates":[75.05193300000001,27.221978],"type":"Point"}
}