{
  "type": "Feature",
  "properties": {
    "gn:admin1_code":"19.0",
    "gn:admin2_code":"568.0",
    "gn:asciiname":"Kerekoppa",
    "gn:country_code":"IN",
    "gn:dem":637,
    "gn:feature_class":"P",
    "gn:feature_code":"PPL",
    "gn:name":"Ker\u0113koppa",
    "gn:population":0,
    "gn:timezone":"Asia/Kolkata",
    "iso:country":"IN",
    "ks:ks_alt_nam":"KEREKOPPA",
    "ks:ks_name":"Kerekoppa",
    "ks:ks_pop":54,
    "ks:ks_type":"HABITATION",
    "name:eng_x_preferred":[
        "Kerekoppa"
    ],
    "wof:name":"Kerekoppa",
    "wof:placetype":"locality",
    "wof:population":54
},
  "geometry": {"coordinates":[75.19229900000001,13.588044],"type":"Point"}
}