{
  "type": "Feature",
  "properties": {
    "gn:admin1_code":"12.0",
    "gn:admin2_code":"6.0",
    "gn:asciiname":"Saj",
    "gn:country_code":"IN",
    "gn:dem":1223,
    "gn:feature_class":"P",
    "gn:feature_code":"PPL",
    "gn:name":"S\u0101j",
    "gn:population":0,
    "gn:timezone":"Asia/Kolkata",
    "iso:country":"IN",
    "name:rus_x_preferred":[
        "\u0421\u0430\u0439"
    ],
    "wof:name":"Saj",
    "wof:placetype":"locality"
},
  "geometry": {"coordinates":[74.33976,33.45905],"type":"Point"}
}