{
  "type": "Feature",
  "properties": {
    "iso:country":"IN",
    "ks:ks_alt_nam":"Dundum mal",
    "ks:ks_name":"Dundum Mal",
    "ks:ks_pop":761,
    "ks:ks_type":"HABITATION",
    "name:eng_x_preferred":[
        "Dundum Mal"
    ],
    "wof:name":"Dundum Mal",
    "wof:placetype":"locality",
    "wof:population":761
},
  "geometry": {"coordinates":[80.234075,22.393635],"type":"Point"}
}