{
  "type": "Feature",
  "properties": {
    "gn:admin1_code":"24.0",
    "gn:admin2_code":"127.0",
    "gn:asciiname":"Hanotiya",
    "gn:country_code":"IN",
    "gn:dem":340,
    "gn:feature_class":"P",
    "gn:feature_code":"PPL",
    "gn:name":"Hanotiya",
    "gn:population":0,
    "gn:timezone":"Asia/Kolkata",
    "iso:country":"IN",
    "wof:name":"Hanotiya",
    "wof:placetype":"locality"
},
  "geometry": {"coordinates":[76.03579000000001,24.56713],"type":"Point"}
}