{
  "type": "Feature",
  "properties": {
    "iso:country":"IN",
    "ks:ks_name":"P Navan",
    "ks:ks_pop":100,
    "ks:ks_type":"HABITATION",
    "ks:ks_uagg_main":0,
    "name:eng_x_preferred":[
        "P Navan"
    ],
    "wof:name":"P Navan",
    "wof:placetype":"neighbourhood",
    "wof:population":100
},
  "geometry": {"coordinates":[81.203059,25.988014],"type":"Point"}
}