{
  "type": "Feature",
  "properties": {
    "iso:country":"IN",
    "ks:ks_name":"Kathihatty",
    "ks:ks_pop":246,
    "ks:ks_type":"HABITATION",
    "name:eng_x_preferred":[
        "Kathihatty"
    ],
    "wof:name":"Kathihatty",
    "wof:placetype":"locality",
    "wof:population":246
},
  "geometry": {"coordinates":[76.26804199999999,14.280446],"type":"Point"}
}