{
  "type": "Feature",
  "properties": {
    "iso:country":"IN",
    "ks:ks_name":"Mahamadpur",
    "ks:ks_pop":1335,
    "ks:ks_type":"VILLAGE",
    "name:eng_x_preferred":[
        "Mahamadpur"
    ],
    "wof:name":"Mahamadpur",
    "wof:placetype":"locality",
    "wof:population":1335
},
  "geometry": {"coordinates":[85.868374,26.057887],"type":"Point"}
}