{
  "type": "Feature",
  "properties": {
    "iso:country":"IN",
    "ks:ks_name":"Barkigarhi Hansagarh",
    "ks:ks_pop":840,
    "ks:ks_type":"HABITATION",
    "name:eng_x_preferred":[
        "Barkigarhi Hansagarh"
    ],
    "wof:name":"Barkigarhi Hansagarh",
    "wof:placetype":"locality",
    "wof:population":840
},
  "geometry": {"coordinates":[77.699726,27.954955],"type":"Point"}
}