{
  "type": "Feature",
  "properties": {
    "gn:admin1_code":"39.0",
    "gn:admin2_code":"66.0",
    "gn:asciiname":"Koidal",
    "gn:country_code":"IN",
    "gn:dem":2041,
    "gn:feature_class":"P",
    "gn:feature_code":"PPL",
    "gn:name":"Koidal",
    "gn:population":0,
    "gn:timezone":"Asia/Kolkata",
    "iso:country":"IN",
    "wof:name":"Koidal",
    "wof:placetype":"locality"
},
  "geometry": {"coordinates":[79.70312,29.37308],"type":"Point"}
}