{
  "type": "Feature",
  "properties": {
    "iso:country":"IN",
    "ks:ks_name":"Padekarpada",
    "ks:ks_pop":40,
    "ks:ks_type":"HABITATION",
    "name:eng_x_preferred":[
        "Padekarpada"
    ],
    "wof:name":"Padekarpada",
    "wof:placetype":"locality",
    "wof:population":40
},
  "geometry": {"coordinates":[73.187639,19.662382],"type":"Point"}
}