{
  "type": "Feature",
  "properties": {
    "iso:country":"IN",
    "ks:ks_name":"Chamrouti m",
    "ks:ks_pop":49,
    "ks:ks_type":"HABITATION",
    "name:eng_x_preferred":[
        "Chamrouti m"
    ],
    "wof:name":"Chamrouti m",
    "wof:placetype":"locality",
    "wof:population":49
},
  "geometry": {"coordinates":[82.94669,26.524118],"type":"Point"}
}