{
  "type": "Feature",
  "properties": {
    "gn:admin1_code":"25.0",
    "gn:admin2_code":"614.0",
    "gn:asciiname":"Balasamudram",
    "gn:country_code":"IN",
    "gn:dem":99,
    "gn:feature_class":"P",
    "gn:feature_code":"PPL",
    "gn:name":"Balasamudram",
    "gn:population":0,
    "gn:timezone":"Asia/Kolkata",
    "iso:country":"IN",
    "wof:name":"Balasamudram",
    "wof:placetype":"locality"
},
  "geometry": {"coordinates":[78.32033,10.9936],"type":"Point"}
}