{
  "type": "Feature",
  "properties": {
    "gn:admin1_code":"25.0",
    "gn:admin2_code":"614.0",
    "gn:asciiname":"Balasamudram",
    "gn:country_code":"IN",
    "gn:dem":99,
    "gn:feature_class":"P",
    "gn:feature_code":"PPL",
    "gn:name":"Balasamudram",
    "gn:population":0,
    "gn:timezone":"Asia/Kolkata",
    "iso:country":"IN",
    "name:bpy_x_preferred":[
        "\u09ac\u09be\u09b2\u09b8\u09ae\u09c1\u09a6\u09cd\u09b0\u09ae"
    ],
    "name:ita_x_preferred":[
        "Balasamudram"
    ],
    "name:msa_x_preferred":[
        "Balasamudram"
    ],
    "name:new_x_preferred":[
        "\u092c\u0932\u0938\u092e\u0941\u0926\u094d\u0930\u093e\u092e"
    ],
    "name:nld_x_preferred":[
        "Balasamudram"
    ],
    "name:por_x_preferred":[
        "Balasamudram"
    ],
    "name:tam_x_preferred":[
        "\u0baa\u0bbe\u0bb2\u0b9a\u0bae\u0bc1\u0ba4\u0bcd\u0ba4\u0bbf\u0bb0\u0bae\u0bcd"
    ],
    "name:vie_x_preferred":[
        "Balasamudram"
    ],
    "name:zho_x_preferred":[
        "\u5df4\u62c9\u8428\u7a46\u5fb7\u62c9\u59c6"
    ],
    "wof:name":"Balasamudram",
    "wof:placetype":"locality"
},
  "geometry": {"coordinates":[78.32033,10.9936],"type":"Point"}
}