{
  "type": "Feature",
  "properties": {
    "gn:admin1_code":"19.0",
    "gn:admin2_code":"566.0",
    "gn:asciiname":"Kittadahal",
    "gn:country_code":"IN",
    "gn:dem":713,
    "gn:feature_class":"P",
    "gn:feature_code":"PPL",
    "gn:name":"Kittadah\u0101l",
    "gn:population":0,
    "gn:timezone":"Asia/Kolkata",
    "iso:country":"IN",
    "wof:name":"Kittadahal",
    "wof:placetype":"locality"
},
  "geometry": {"coordinates":[76.48264,13.73],"type":"Point"}
}