{
  "type": "Feature",
  "properties": {
    "gn:admin1_code":"36",
    "gn:admin2_code":"144.0",
    "gn:asciiname":"Nagla Putha",
    "gn:country_code":"IN",
    "gn:dem":175,
    "gn:feature_class":"P",
    "gn:feature_code":"PPL",
    "gn:name":"Nagla P\u016btha",
    "gn:population":0,
    "gn:timezone":"Asia/Kolkata",
    "iso:country":"IN",
    "ks:ks_alt_nam":"NAGLA  PUTHA",
    "ks:ks_name":"Nagla Putha",
    "ks:ks_pop":30,
    "ks:ks_type":"HABITATION",
    "name:eng_x_preferred":[
        "Nagla Putha"
    ],
    "name:eng_x_variant":[
        "NAGLA  PUTHA"
    ],
    "wof:name":"Nagla Putha",
    "wof:placetype":"locality",
    "wof:population":30
},
  "geometry": {"coordinates":[77.96384399999999,27.494207],"type":"Point"}
}