{
  "type": "Feature",
  "properties": {
    "iso:country":"IN",
    "ks:ks_alt_nam":"T\u016blugonda",
    "ks:ks_name":"Tulugonda",
    "ks:ks_type":"VILLAGE",
    "name:eng_x_preferred":[
        "Tulugonda"
    ],
    "name:eng_x_variant":[
        "T\u016blugonda"
    ],
    "wof:name":"Tulugonda",
    "wof:placetype":"locality"
},
  "geometry": {"coordinates":[81.583196,17.78238],"type":"Point"}
}