{
  "type": "Feature",
  "properties": {
    "gn:admin1_code":"35",
    "gn:admin2_code":"445.0",
    "gn:asciiname":"Ihirnia",
    "gn:country_code":"IN",
    "gn:dem":313,
    "gn:feature_class":"P",
    "gn:feature_code":"PPL",
    "gn:name":"Ihirnia",
    "gn:population":0,
    "gn:timezone":"Asia/Kolkata",
    "iso:country":"IN",
    "wof:name":"Ihirnia",
    "wof:placetype":"locality"
},
  "geometry": {"coordinates":[77.19793,22.76911],"type":"Point"}
}