{
  "type": "Feature",
  "properties": {
    "gn:admin1_code":"36",
    "gn:admin2_code":"200.0",
    "gn:asciiname":"Sarauli",
    "gn:country_code":"IN",
    "gn:dem":291,
    "gn:feature_class":"P",
    "gn:feature_code":"PPL",
    "gn:name":"Sarauli",
    "gn:population":0,
    "gn:timezone":"Asia/Kolkata",
    "iso:country":"IN",
    "ks:ks_name":"Sarauli",
    "ks:ks_pop":1624,
    "ks:ks_type":"VILLAGE",
    "name:eng_x_preferred":[
        "Sarauli"
    ],
    "wof:name":"Sarauli",
    "wof:placetype":"locality",
    "wof:population":1624
},
  "geometry": {"coordinates":[83.008782,24.839778],"type":"Point"}
}