{
  "type": "Feature",
  "properties": {
    "gn:admin1_code":"40",
    "gn:admin2_code":"537.0",
    "gn:asciiname":"Bachpalli",
    "gn:country_code":"IN",
    "gn:dem":668,
    "gn:feature_class":"P",
    "gn:feature_code":"PPL",
    "gn:name":"Bachpalli",
    "gn:population":0,
    "gn:timezone":"Asia/Kolkata",
    "iso:country":"IN",
    "wof:name":"Bachpalli",
    "wof:placetype":"locality"
},
  "geometry": {"coordinates":[78.43783000000001,17.05476],"type":"Point"}
}