{
  "type": "Feature",
  "properties": {
    "iso:country":"IN",
    "ks:ks_name":"Ujgaokarwadi",
    "ks:ks_pop":259,
    "ks:ks_type":"HABITATION",
    "name:eng_x_preferred":[
        "Ujgaokarwadi"
    ],
    "wof:name":"Ujgaokarwadi",
    "wof:placetype":"locality",
    "wof:population":259
},
  "geometry": {"coordinates":[73.558333,17.278056],"type":"Point"}
}