{
  "type": "Feature",
  "properties": {
    "iso:country":"IN",
    "ks:ks_name":"Gopal Chak",
    "ks:ks_pop":493,
    "ks:ks_type":"VILLAGE",
    "name:eng_x_preferred":[
        "Gopal Chak"
    ],
    "wof:name":"Gopal Chak",
    "wof:placetype":"locality",
    "wof:population":493
},
  "geometry": {"coordinates":[87.6271,22.120083],"type":"Point"}
}