{
  "type": "Feature",
  "properties": {
    "iso:country":"IN",
    "ks:ks_name":"Era Camp",
    "ks:ks_pop":10,
    "ks:ks_type":"HABITATION",
    "name:eng_x_preferred":[
        "Era Camp"
    ],
    "wof:name":"Era Camp",
    "wof:placetype":"locality",
    "wof:population":10
},
  "geometry": {"coordinates":[76.84292000000001,15.828195],"type":"Point"}
}