{
  "type": "Feature",
  "properties": {
    "gn:admin1_code":"40",
    "gn:admin2_code":"538.0",
    "gn:asciiname":"Potlapalli Agraharam",
    "gn:country_code":"IN",
    "gn:dem":547,
    "gn:feature_class":"P",
    "gn:feature_code":"PPL",
    "gn:name":"Potlapalli Agrah\u0101ram",
    "gn:population":0,
    "gn:timezone":"Asia/Kolkata",
    "iso:country":"IN",
    "wof:name":"Potlapalli Agraharam",
    "wof:placetype":"locality"
},
  "geometry": {"coordinates":[78.20229999999999,16.89725],"type":"Point"}
}