{
  "type": "Feature",
  "properties": {
    "gn:admin1_code":"16",
    "gn:admin2_code":"504.0",
    "gn:asciiname":"Kamthi",
    "gn:country_code":"IN",
    "gn:dem":260,
    "gn:feature_class":"P",
    "gn:feature_code":"PPL",
    "gn:name":"K\u0101mthi",
    "gn:population":0,
    "gn:timezone":"Asia/Kolkata",
    "iso:country":"IN",
    "wof:name":"Kamthi",
    "wof:placetype":"locality"
},
  "geometry": {"coordinates":[78.65387,20.83617000000001],"type":"Point"}
}