{
  "type": "Feature",
  "properties": {
    "iso:country":"IN",
    "ks:ks_name":"Kankaria",
    "ks:ks_pop":742,
    "ks:ks_type":"HABITATION",
    "name:eng_x_preferred":[
        "Kankaria"
    ],
    "wof:name":"Kankaria",
    "wof:placetype":"locality",
    "wof:population":742
},
  "geometry": {"coordinates":[89.009252,22.314304],"type":"Point"}
}