{
  "type": "Feature",
  "properties": {
    "iso:country":"IN",
    "ks:ks_name":"Thachandi",
    "ks:ks_pop":1645,
    "ks:ks_type":"HABITATION",
    "name:eng_x_preferred":[
        "Thachandi"
    ],
    "wof:name":"Thachandi",
    "wof:placetype":"locality",
    "wof:population":1645
},
  "geometry": {"coordinates":[76.44822499999999,10.63283],"type":"Point"}
}