{
  "type": "Feature",
  "properties": {
    "gn:admin1_code":"24",
    "gn:admin2_code":"101.0",
    "gn:asciiname":"Suin",
    "gn:country_code":"IN",
    "gn:dem":203,
    "gn:feature_class":"P",
    "gn:feature_code":"PPL",
    "gn:name":"Suin",
    "gn:population":0,
    "gn:timezone":"Asia/Kolkata",
    "iso:country":"IN",
    "name:und_x_variant":[
        "Sui",
        "Suin"
    ],
    "wof:name":"Suin",
    "wof:placetype":"locality"
},
  "geometry": {"coordinates":[74.10684999999999,28.7446],"type":"Point"}
}