{
  "type": "Feature",
  "properties": {
    "iso:country":"IN",
    "ks:ks_alt_nam":"Avarekayi guda kaval",
    "ks:ks_name":"Avarekayi Guda Kaval",
    "ks:ks_pop":71,
    "ks:ks_type":"HABITATION",
    "name:eng_x_preferred":[
        "Avarekayi Guda Kaval"
    ],
    "wof:name":"Avarekayi Guda Kaval",
    "wof:placetype":"locality",
    "wof:population":71
},
  "geometry": {"coordinates":[76.105198,12.414601],"type":"Point"}
}