{
  "type": "Feature",
  "properties": {
    "gn:admin1_code":"12.0",
    "gn:asciiname":"Shahdara",
    "gn:country_code":"IN",
    "gn:dem":1401,
    "gn:feature_class":"P",
    "gn:feature_code":"PPL",
    "gn:name":"Sh\u0101hdara",
    "gn:population":0,
    "gn:timezone":"Asia/Kolkata",
    "iso:country":"IN",
    "name:und_x_variant":[
        "Sh\u0101hdara",
        "Shahdara"
    ],
    "wof:name":"Shahdara",
    "wof:placetype":"locality"
},
  "geometry": {"coordinates":[73.96285,34.11283],"type":"Point"}
}