{
  "type": "Feature",
  "properties": {
    "gn:admin1_code":"19.0",
    "gn:admin2_code":"564.0",
    "gn:asciiname":"Galginkatti",
    "gn:country_code":"IN",
    "gn:dem":629,
    "gn:feature_class":"P",
    "gn:feature_code":"PPL",
    "gn:name":"Galg\u012bnkatti",
    "gn:population":0,
    "gn:timezone":"Asia/Kolkata",
    "iso:country":"IN",
    "ks:ks_alt_nam":"Galg\u012bnkatti",
    "ks:ks_name":"Galginkatti",
    "ks:ks_type":"VILLAGE",
    "name:eng_x_preferred":[
        "Galginkatti"
    ],
    "name:eng_x_variant":[
        "Galg\u012bnkatti"
    ],
    "wof:name":"Galginkatti",
    "wof:placetype":"locality"
},
  "geometry": {"coordinates":[75.109167,14.915087],"type":"Point"}
}