{
  "type": "Feature",
  "properties": {
    "iso:country":"IN",
    "ks:ks_name":"Hemtikri",
    "ks:ks_pop":0,
    "ks:ks_type":"VILLAGE",
    "name:eng_x_preferred":[
        "Hemtikri"
    ],
    "wof:name":"Hemtikri",
    "wof:placetype":"locality",
    "wof:population":0
},
  "geometry": {"coordinates":[87.331675,22.24668],"type":"Point"}
}