{
  "type": "Feature",
  "properties": {
    "gn:admin1_code":"2",
    "gn:admin2_code":"544.0",
    "gn:asciiname":"Pulakhandam Ponnavolu",
    "gn:country_code":"IN",
    "gn:dem":109,
    "gn:feature_class":"P",
    "gn:feature_code":"PPL",
    "gn:name":"Pulakhandam Ponnavolu",
    "gn:population":0,
    "gn:timezone":"Asia/Kolkata",
    "iso:country":"IN",
    "wof:name":"Pulakhandam Ponnavolu",
    "wof:placetype":"locality"
},
  "geometry": {"coordinates":[82.76253,17.77234],"type":"Point"}
}