{
  "type": "Feature",
  "properties": {
    "gn:admin1_code":"12.0",
    "gn:admin2_code":"9.0",
    "gn:asciiname":"Pethakut",
    "gn:country_code":"IN",
    "gn:dem":1905,
    "gn:feature_class":"P",
    "gn:feature_code":"PPL",
    "gn:name":"Pethak\u016bt",
    "gn:population":0,
    "gn:timezone":"Asia/Kolkata",
    "iso:country":"IN",
    "name:eng_x_preferred":[
        "Pethak\u016bt"
    ],
    "wof:name":"Pethakut",
    "wof:placetype":"locality"
},
  "geometry": {"coordinates":[74.66109,34.47393],"type":"Point"}
}