{
  "type": "Feature",
  "properties": {
    "iso:country":"IN",
    "ks:ks_name":"Talapewasti",
    "ks:ks_pop":125,
    "ks:ks_type":"HABITATION",
    "name:eng_x_preferred":[
        "Talapewasti"
    ],
    "wof:name":"Talapewasti",
    "wof:placetype":"locality",
    "wof:population":125
},
  "geometry": {"coordinates":[74.13855,19.290149],"type":"Point"}
}