{
  "type": "Feature",
  "properties": {
    "iso:country":"IN",
    "ks:ks_name":"Kilkilla",
    "ks:ks_pop":355,
    "ks:ks_type":"HABITATION",
    "name:eng_x_preferred":[
        "Kilkilla"
    ],
    "wof:name":"Kilkilla",
    "wof:placetype":"locality",
    "wof:population":355
},
  "geometry": {"coordinates":[84.039272,22.488352],"type":"Point"}
}