{
  "type": "Feature",
  "properties": {
    "gn:admin1_code":"35.0",
    "gn:admin2_code":"464.0",
    "gn:asciiname":"Sajidongar",
    "gn:country_code":"IN",
    "gn:dem":294,
    "gn:feature_class":"P",
    "gn:feature_code":"PPL",
    "gn:name":"Sajidongar",
    "gn:population":0,
    "gn:timezone":"Asia/Kolkata",
    "iso:country":"IN",
    "wof:name":"Sajidongar",
    "wof:placetype":"locality"
},
  "geometry": {"coordinates":[74.47968,22.84443],"type":"Point"}
}