{
  "type": "Feature",
  "properties": {
    "iso:country":"IN",
    "ks:ks_alt_nam":"CHAK MANDARANA",
    "ks:ks_name":"Chak Mandarana",
    "ks:ks_pop":257,
    "ks:ks_type":"HABITATION",
    "name:eng_x_preferred":[
        "Chak Mandarana"
    ],
    "wof:name":"Chak Mandarana",
    "wof:placetype":"locality",
    "wof:population":257
},
  "geometry": {"coordinates":[74.470736,28.863481],"type":"Point"}
}