{
  "type": "Feature",
  "properties": {
    "gn:admin1_code":"25.0",
    "gn:admin2_code":"608.0",
    "gn:asciiname":"Tundumaniyam",
    "gn:country_code":"IN",
    "gn:dem":284,
    "gn:feature_class":"P",
    "gn:feature_code":"PPL",
    "gn:name":"Tundum\u0101niyam",
    "gn:population":0,
    "gn:timezone":"Asia/Kolkata",
    "iso:country":"IN",
    "ks:ks_alt_nam":"Tundum\u0101niyam",
    "ks:ks_name":"Tundumaniyam",
    "ks:ks_type":"VILLAGE",
    "ks:ks_uagg_main":0,
    "name:eng_x_preferred":[
        "Tundumaniyam"
    ],
    "name:eng_x_variant":[
        "Tundum\u0101niyam"
    ],
    "wof:name":"Tundumaniyam",
    "wof:placetype":"locality"
},
  "geometry": {"coordinates":[77.97890099999999,11.737321],"type":"Point"}
}