{
  "type": "Feature",
  "properties": {
    "iso:country":"IN",
    "ks:ks_name":"Thachanattukara-II",
    "ks:ks_pop":10523,
    "ks:ks_type":"VILLAGE",
    "name:eng_x_preferred":[
        "Thachanattukara-II"
    ],
    "wof:name":"Thachanattukara-II",
    "wof:placetype":"locality",
    "wof:population":10523
},
  "geometry": {"coordinates":[76.336038,10.93578],"type":"Point"}
}