{
  "type": "Feature",
  "properties": {
    "iso:country":"IN",
    "ks:ks_name":"Dumarsol",
    "ks:ks_pop":126,
    "ks:ks_type":"VILLAGE",
    "name:eng_x_preferred":[
        "Dumarsol"
    ],
    "wof:name":"Dumarsol",
    "wof:placetype":"locality",
    "wof:population":126
},
  "geometry": {"coordinates":[87.345569,24.39412],"type":"Point"}
}