{
  "type": "Feature",
  "properties": {
    "gn:admin1_code":"25.0",
    "gn:admin2_code":"612.0",
    "gn:asciiname":"Lakshmapuram",
    "gn:country_code":"IN",
    "gn:dem":349,
    "gn:feature_class":"P",
    "gn:feature_code":"PPL",
    "gn:name":"Lakshm\u0101puram",
    "gn:population":0,
    "gn:timezone":"Asia/Kolkata",
    "iso:country":"IN",
    "wof:name":"Lakshmapuram",
    "wof:placetype":"locality"
},
  "geometry": {"coordinates":[77.40455,10.43002],"type":"Point"}
}