{
  "type": "Feature",
  "properties": {
    "iso:country":"IN",
    "ks:ks_name":"Roz Falia",
    "ks:ks_pop":455,
    "ks:ks_type":"HABITATION",
    "name:eng_x_preferred":[
        "Roz Falia"
    ],
    "wof:name":"Roz Falia",
    "wof:placetype":"locality",
    "wof:population":455
},
  "geometry": {"coordinates":[74.43575,22.869694],"type":"Point"}
}