{
  "type": "Feature",
  "properties": {
    "iso:country":"IN",
    "ks:ks_alt_nam":"nadhaapurwa",
    "ks:ks_name":"Nadhaapurwa",
    "ks:ks_pop":314,
    "ks:ks_type":"HABITATION",
    "name:eng_x_preferred":[
        "Nadhaapurwa"
    ],
    "wof:name":"Nadhaapurwa",
    "wof:placetype":"locality",
    "wof:population":314
},
  "geometry": {"coordinates":[81.383066,28.120442],"type":"Point"}
}