{
  "type": "Feature",
  "properties": {
    "iso:country":"IN",
    "ks:ks_name":"Kadalibadihill",
    "ks:ks_pop":205,
    "ks:ks_type":"VILLAGE",
    "name:eng_x_preferred":[
        "Kadalibadihill"
    ],
    "wof:name":"Kadalibadihill",
    "wof:placetype":"locality",
    "wof:population":205
},
  "geometry": {"coordinates":[86.116805,21.985979],"type":"Point"}
}