{
  "type": "Feature",
  "properties": {
    "iso:country":"IN",
    "ks:ks_name":"Farm Falia",
    "ks:ks_pop":1316,
    "ks:ks_type":"HABITATION",
    "name:eng_x_preferred":[
        "Farm Falia"
    ],
    "wof:name":"Farm Falia",
    "wof:placetype":"locality",
    "wof:population":1316
},
  "geometry": {"coordinates":[73.87308299999999,22.833722],"type":"Point"}
}