{
  "type": "Feature",
  "properties": {
    "iso:country":"IN",
    "ks:ks_name":"Dhadhauva",
    "ks:ks_pop":2439,
    "ks:ks_type":"VILLAGE",
    "ks:ks_uagg_main":0,
    "name:eng_x_preferred":[
        "Dhadhauva"
    ],
    "wof:name":"Dhadhauva",
    "wof:placetype":"neighbourhood",
    "wof:population":2439
},
  "geometry": {"coordinates":[82.494647,26.925724],"type":"Point"}
}