{
  "type": "Feature",
  "properties": {
    "iso:country":"IN",
    "ks:ks_name":"Krishankebidi",
    "ks:ks_pop":650,
    "ks:ks_type":"VILLAGE",
    "name:eng_x_preferred":[
        "Krishankebidi"
    ],
    "wof:name":"Krishankebidi",
    "wof:placetype":"locality",
    "wof:population":650
},
  "geometry": {"coordinates":[83.007324,19.480553],"type":"Point"}
}