{
  "type": "Feature",
  "properties": {
    "iso:country":"IN",
    "ks:ks_name":"Bheemanakolli",
    "ks:ks_pop":13,
    "ks:ks_type":"HABITATION",
    "name:eng_x_preferred":[
        "Bheemanakolli"
    ],
    "wof:name":"Bheemanakolli",
    "wof:placetype":"locality",
    "wof:population":13
},
  "geometry": {"coordinates":[76.290284,11.963108],"type":"Point"}
}