{
  "type": "Feature",
  "properties": {
    "iso:country":"IN",
    "ks:ks_name":"Mohanpura",
    "ks:ks_pop":96,
    "ks:ks_type":"HABITATION",
    "name:eng_x_preferred":[
        "Mohanpura"
    ],
    "wof:name":"Mohanpura",
    "wof:placetype":"locality",
    "wof:population":96
},
  "geometry": {"coordinates":[73.4636,22.730883],"type":"Point"}
}