{
  "type": "Feature",
  "properties": {
    "iso:country":"IN",
    "ks:ks_alt_nam":"Nallagutla gudem",
    "ks:ks_name":"Nallagutla Gudem",
    "ks:ks_pop":165,
    "ks:ks_type":"HABITATION",
    "name:eng_x_preferred":[
        "Nallagutla Gudem"
    ],
    "wof:name":"Nallagutla Gudem",
    "wof:placetype":"locality",
    "wof:population":165
},
  "geometry": {"coordinates":[78.925673,15.869328],"type":"Point"}
}