{
  "type": "Feature",
  "properties": {
    "iso:country":"IN",
    "ks:ks_name":"Mand Dhaliwal",
    "ks:ks_pop":0,
    "ks:ks_type":"VILLAGE",
    "name:eng_x_preferred":[
        "Mand Dhaliwal"
    ],
    "wof:name":"Mand Dhaliwal",
    "wof:placetype":"locality",
    "wof:population":0
},
  "geometry": {"coordinates":[75.295751,31.479986],"type":"Point"}
}