{
  "type": "Feature",
  "properties": {
    "gn:admin1_code":"35.0",
    "gn:admin2_code":"424",
    "gn:asciiname":"Angara",
    "gn:country_code":"IN",
    "gn:dem":349,
    "gn:feature_class":"P",
    "gn:feature_code":"PPL",
    "gn:name":"Angara",
    "gn:population":0,
    "gn:timezone":"Asia/Kolkata",
    "iso:country":"IN",
    "name:urd_x_preferred":[
        "\u0627\u0646\u06af\u0627\u0631\u0627"
    ],
    "wof:name":"Angara",
    "wof:placetype":"locality"
},
  "geometry": {"coordinates":[78.85556,24.73525],"type":"Point"}
}