{
  "type": "Feature",
  "properties": {
    "gn:admin1_code":"19.0",
    "gn:admin2_code":"574.0",
    "gn:asciiname":"Sirdhalli",
    "gn:country_code":"IN",
    "gn:dem":911,
    "gn:feature_class":"P",
    "gn:feature_code":"PPL",
    "gn:name":"Sirdhalli",
    "gn:population":0,
    "gn:timezone":"Asia/Kolkata",
    "iso:country":"IN",
    "ks:ks_name":"Siradahalli",
    "ks:ks_pop":50,
    "ks:ks_type":"HABITATION",
    "name:eng_x_preferred":[
        "Siradahalli"
    ],
    "name:eng_x_variant":[
        "Sirdhalli"
    ],
    "wof:name":"Siradahalli",
    "wof:placetype":"locality",
    "wof:population":50
},
  "geometry": {"coordinates":[75.725668,12.899182],"type":"Point"}
}