{
  "type": "Feature",
  "properties": {
    "iso:country":"IN",
    "ks:ks_name":"Kattavu",
    "ks:ks_pop":212,
    "ks:ks_type":"HABITATION",
    "name:eng_x_preferred":[
        "Kattavu"
    ],
    "wof:name":"Kattavu",
    "wof:placetype":"locality",
    "wof:population":212
},
  "geometry": {"coordinates":[75.22308700000001,12.632272],"type":"Point"}
}