{
  "type": "Feature",
  "properties": {
    "iso:country":"IN",
    "ks:ks_name":"Barh Chhawa No. 2",
    "ks:ks_pop":22,
    "ks:ks_type":"HABITATION",
    "name:eng_x_preferred":[
        "Barh Chhawa No. 2"
    ],
    "wof:name":"Barh Chhawa No. 2",
    "wof:placetype":"locality",
    "wof:population":22
},
  "geometry": {"coordinates":[76.76384400000001,26.454881],"type":"Point"}
}