{
  "type": "Feature",
  "properties": {
    "iso:country":"IN",
    "ks:ks_name":"Talapanga",
    "ks:ks_pop":402,
    "ks:ks_type":"VILLAGE",
    "name:eng_x_preferred":[
        "Talapanga"
    ],
    "wof:name":"Talapanga",
    "wof:placetype":"locality",
    "wof:population":402
},
  "geometry": {"coordinates":[83.123907,19.386832],"type":"Point"}
}