{
  "type": "Feature",
  "properties": {
    "gn:admin1_code":"36",
    "gn:admin2_code":"195.0",
    "gn:asciiname":"Dharwa",
    "gn:country_code":"IN",
    "gn:dem":78,
    "gn:feature_class":"P",
    "gn:feature_code":"PPL",
    "gn:name":"Dharwa",
    "gn:population":0,
    "gn:timezone":"Asia/Kolkata",
    "iso:country":"IN",
    "ks:ks_name":"Dharwa",
    "ks:ks_pop":1410,
    "ks:ks_type":"VILLAGE",
    "ks:ks_uagg_main":0,
    "name:eng_x_preferred":[
        "Dharwa"
    ],
    "wof:name":"Dharwa",
    "wof:placetype":"neighbourhood",
    "wof:population":1410
},
  "geometry": {"coordinates":[83.314759,25.507876],"type":"Point"}
}