{
  "type": "Feature",
  "properties": {
    "gn:admin1_code":"16",
    "gn:admin2_code":"503.0",
    "gn:asciiname":"Nandur Buzurg",
    "gn:country_code":"IN",
    "gn:dem":323,
    "gn:feature_class":"P",
    "gn:feature_code":"PPL",
    "gn:name":"N\u0101ndur Buzurg",
    "gn:population":0,
    "gn:timezone":"Asia/Kolkata",
    "iso:country":"IN",
    "name:und_x_variant":[
        "N\u0101ndur Buzurg",
        "N\u0101ndura Buzurg"
    ],
    "wof:name":"Nandur Buzurg",
    "wof:placetype":"locality"
},
  "geometry": {"coordinates":[77.74959,21.03826],"type":"Point"}
}