{
  "type": "Feature",
  "properties": {
    "iso:country":"IN",
    "ks:ks_name":"Pusparam Para",
    "ks:ks_pop":324,
    "ks:ks_type":"HABITATION",
    "name:eng_x_preferred":[
        "Pusparam Para"
    ],
    "wof:name":"Pusparam Para",
    "wof:placetype":"locality",
    "wof:population":324
},
  "geometry": {"coordinates":[92.215108,23.730466],"type":"Point"}
}