{
  "type": "Feature",
  "properties": {
    "iso:country":"IN",
    "ks:ks_name":"Rautpara",
    "ks:ks_pop":1824,
    "ks:ks_type":"VILLAGE",
    "name:eng_x_preferred":[
        "Rautpara"
    ],
    "wof:name":"Rautpara",
    "wof:placetype":"locality",
    "wof:population":1824
},
  "geometry": {"coordinates":[85.477845,20.129172],"type":"Point"}
}