{
  "type": "Feature",
  "properties": {
    "iso:country":"IN",
    "ks:ks_name":"Patiyaun",
    "ks:ks_pop":291,
    "ks:ks_type":"HABITATION",
    "name:eng_x_preferred":[
        "Patiyaun"
    ],
    "wof:name":"Patiyaun",
    "wof:placetype":"locality",
    "wof:population":291
},
  "geometry": {"coordinates":[79.03510300000001,30.469216],"type":"Point"}
}