{
  "type": "Feature",
  "properties": {
    "iso:country":"IN",
    "ks:ks_alt_nam":"patel basti",
    "ks:ks_name":"Patel Basti",
    "ks:ks_pop":839,
    "ks:ks_type":"HABITATION",
    "name:eng_x_preferred":[
        "Patel Basti"
    ],
    "wof:name":"Patel Basti",
    "wof:placetype":"locality",
    "wof:population":839
},
  "geometry": {"coordinates":[82.938755,25.448273],"type":"Point"}
}