{
  "type": "Feature",
  "properties": {
    "gn:admin1_code":"9.0",
    "gn:asciiname":"Dores",
    "gn:country_code":"IN",
    "gn:dem":4,
    "gn:feature_class":"P",
    "gn:feature_code":"PPL",
    "gn:name":"Dores",
    "gn:population":0,
    "gn:timezone":"Asia/Kolkata",
    "iso:country":"IN",
    "name:ceb_x_preferred":[
        "Dores"
    ],
    "name:eus_x_preferred":[
        "Dores"
    ],
    "name:gle_x_preferred":[
        "Duras"
    ],
    "name:nld_x_preferred":[
        "Dores"
    ],
    "name:swe_x_preferred":[
        "Dores"
    ],
    "wof:name":"Dores",
    "wof:placetype":"locality"
},
  "geometry": {"coordinates":[70.96666999999999,20.71667],"type":"Point"}
}