{
  "type": "Feature",
  "properties": {
    "iso:country":"IN",
    "ks:ks_name":"Middle Tola",
    "ks:ks_pop":20,
    "ks:ks_type":"HABITATION",
    "name:eng_x_preferred":[
        "Middle Tola"
    ],
    "wof:name":"Middle Tola",
    "wof:placetype":"locality",
    "wof:population":20
},
  "geometry": {"coordinates":[86.35276399999999,24.574009],"type":"Point"}
}