{
  "type": "Feature",
  "properties": {
    "iso:country":"IN",
    "ks:ks_name":"Chainpur",
    "ks:ks_pop":769,
    "ks:ks_type":"VILLAGE",
    "name:eng_x_preferred":[
        "Chainpur"
    ],
    "wof:name":"Chainpur",
    "wof:placetype":"locality",
    "wof:population":769
},
  "geometry": {"coordinates":[86.05260800000001,22.931233],"type":"Point"}
}