{
  "type": "Feature",
  "properties": {
    "iso:country":"IN",
    "ks:ks_name":"Kulpukuria",
    "ks:ks_pop":833,
    "ks:ks_type":"VILLAGE",
    "ks:ks_uagg_main":0,
    "name:eng_x_preferred":[
        "Kulpukuria"
    ],
    "wof:name":"Kulpukuria",
    "wof:placetype":"neighbourhood",
    "wof:population":833
},
  "geometry": {"coordinates":[88.690758,22.995092],"type":"Point"}
}