{
  "type": "Feature",
  "properties": {
    "gn:admin1_code":"36",
    "gn:admin2_code":"156.0",
    "gn:asciiname":"Wadoganj",
    "gn:country_code":"IN",
    "gn:dem":119,
    "gn:feature_class":"P",
    "gn:feature_code":"PPL",
    "gn:name":"Wadoganj",
    "gn:population":0,
    "gn:timezone":"Asia/Kolkata",
    "iso:country":"IN",
    "wof:name":"Wadoganj",
    "wof:placetype":"neighbourhood"
},
  "geometry": {"coordinates":[80.96229,26.48224],"type":"Point"}
}