{
  "type": "Feature",
  "properties": {
    "iso:country":"IN",
    "ks:ks_name":"Nafadewadi",
    "ks:ks_pop":161,
    "ks:ks_type":"HABITATION",
    "name:eng_x_preferred":[
        "Nafadewadi"
    ],
    "wof:name":"Nafadewadi",
    "wof:placetype":"locality",
    "wof:population":161
},
  "geometry": {"coordinates":[73.657331,16.656022],"type":"Point"}
}