{
  "type": "Feature",
  "properties": {
    "iso:country":"IN",
    "ks:ks_name":"Khokha Tola",
    "ks:ks_pop":360,
    "ks:ks_type":"HABITATION",
    "name:eng_x_preferred":[
        "Khokha Tola"
    ],
    "wof:name":"Khokha Tola",
    "wof:placetype":"locality",
    "wof:population":360
},
  "geometry": {"coordinates":[83.422025,24.492168],"type":"Point"}
}