{
  "type": "Feature",
  "properties": {
    "gn:admin1_code":"2.0",
    "gn:admin2_code":"554.0",
    "gn:asciiname":"Gajjalavaripalle",
    "gn:country_code":"IN",
    "gn:dem":854,
    "gn:feature_class":"P",
    "gn:feature_code":"PPL",
    "gn:name":"Gajjalav\u0101ripalle",
    "gn:population":0,
    "gn:timezone":"Asia/Kolkata",
    "iso:country":"IN",
    "wof:name":"Gajjalavaripalle",
    "wof:placetype":"neighbourhood"
},
  "geometry": {"coordinates":[78.41007999999999,13.42901],"type":"Point"}
}