{
  "type": "Feature",
  "properties": {
    "iso:country":"IN",
    "ks:ks_name":"Jata",
    "ks:ks_pop":631,
    "ks:ks_type":"HABITATION",
    "name:eng_x_preferred":[
        "Jata"
    ],
    "wof:name":"Jata",
    "wof:placetype":"locality",
    "wof:population":631
},
  "geometry": {"coordinates":[79.27355900000001,27.682549],"type":"Point"}
}