{
  "type": "Feature",
  "properties": {
    "iso:country":"IN",
    "ks:ks_name":"Burudi",
    "ks:ks_pop":224,
    "ks:ks_type":"VILLAGE",
    "name:eng_x_preferred":[
        "Burudi"
    ],
    "wof:name":"Burudi",
    "wof:placetype":"locality",
    "wof:population":224
},
  "geometry": {"coordinates":[83.89721,19.382359],"type":"Point"}
}