{
  "type": "Feature",
  "properties": {
    "iso:country":"IN",
    "ks:ks_name":"Bengacherra",
    "ks:ks_pop":155,
    "ks:ks_type":"HABITATION",
    "name:eng_x_preferred":[
        "Bengacherra"
    ],
    "wof:name":"Bengacherra",
    "wof:placetype":"locality",
    "wof:population":155
},
  "geometry": {"coordinates":[92.185385,24.128547],"type":"Point"}
}