{
  "type": "Feature",
  "properties": {
    "iso:country":"IN",
    "ks:ks_name":"Takhatgarh",
    "ks:ks_pop":954,
    "ks:ks_type":"VILLAGE",
    "name:eng_x_preferred":[
        "Takhatgarh"
    ],
    "wof:name":"Takhatgarh",
    "wof:placetype":"locality",
    "wof:population":954
},
  "geometry": {"coordinates":[71.41157800000001,24.809075],"type":"Point"}
}