{
  "type": "Feature",
  "properties": {
    "iso:country":"IN",
    "ks:ks_name":"Khaparia",
    "ks:ks_pop":0,
    "ks:ks_type":"VILLAGE",
    "name:eng_x_preferred":[
        "Khaparia"
    ],
    "wof:name":"Khaparia",
    "wof:placetype":"locality",
    "wof:population":0
},
  "geometry": {"coordinates":[85.195049,24.667531],"type":"Point"}
}