{
  "type": "Feature",
  "properties": {
    "gn:admin1_code":"11.0",
    "gn:admin2_code":"26.0",
    "gn:asciiname":"Badgai",
    "gn:country_code":"IN",
    "gn:dem":1517,
    "gn:feature_class":"P",
    "gn:feature_code":"PPL",
    "gn:name":"Badgai",
    "gn:population":0,
    "gn:timezone":"Asia/Kolkata",
    "iso:country":"IN",
    "wof:name":"Badgai",
    "wof:placetype":"locality"
},
  "geometry": {"coordinates":[77.60708000000002,31.4379],"type":"Point"}
}