{
  "type": "Feature",
  "properties": {
    "iso:country":"IN",
    "ks:ks_name":"Chinagantheru",
    "ks:ks_pop":67,
    "ks:ks_type":"HABITATION",
    "name:eng_x_preferred":[
        "Chinagantheru"
    ],
    "wof:name":"Chinagantheru",
    "wof:placetype":"locality",
    "wof:population":67
},
  "geometry": {"coordinates":[84.36291799999999,18.855074],"type":"Point"}
}