{
  "type": "Feature",
  "properties": {
    "iso:country":"IN",
    "ks:ks_name":"Kweralu",
    "ks:ks_pop":107,
    "ks:ks_type":"HABITATION",
    "name:eng_x_preferred":[
        "Kweralu"
    ],
    "wof:name":"Kweralu",
    "wof:placetype":"locality",
    "wof:population":107
},
  "geometry": {"coordinates":[79.304965,30.380733],"type":"Point"}
}