{
  "type": "Feature",
  "properties": {
    "gn:admin1_code":"40.0",
    "gn:admin2_code":"532.0",
    "gn:asciiname":"Venkatapur",
    "gn:country_code":"IN",
    "gn:dem":168,
    "gn:feature_class":"P",
    "gn:feature_code":"PPL",
    "gn:name":"Venkat\u0101pur",
    "gn:population":0,
    "gn:timezone":"Asia/Kolkata",
    "iso:country":"IN",
    "name:fas_x_preferred":[
        "\u0648\u0646\u06a9\u062a\u067e\u0648\u0631"
    ],
    "wof:name":"Venkatapur",
    "wof:placetype":"locality"
},
  "geometry": {"coordinates":[79.63930000000001,19.18097],"type":"Point"}
}