{
  "type": "Feature",
  "properties": {
    "iso:country":"IN",
    "ks:ks_name":"Jonaligaon F V",
    "ks:ks_pop":1999,
    "ks:ks_type":"HABITATION",
    "name:eng_x_preferred":[
        "Jonaligaon F V"
    ],
    "wof:name":"Jonaligaon F V",
    "wof:placetype":"locality",
    "wof:population":1999
},
  "geometry": {"coordinates":[89.959462,26.644295],"type":"Point"}
}