{
  "type": "Feature",
  "properties": {
    "gn:admin1_code":"19.0",
    "gn:admin2_code":"576.0",
    "gn:asciiname":"Gondahalli",
    "gn:country_code":"IN",
    "gn:dem":991,
    "gn:feature_class":"P",
    "gn:feature_code":"PPL",
    "gn:name":"Gondahalli",
    "gn:population":0,
    "gn:timezone":"Asia/Kolkata",
    "iso:country":"IN",
    "wof:name":"Gondahalli",
    "wof:placetype":"locality"
},
  "geometry": {"coordinates":[75.89511999999998,12.67219],"type":"Point"}
}