{
  "type": "Feature",
  "properties": {
    "gn:admin1_code":"39.0",
    "gn:admin2_code":"64.0",
    "gn:asciiname":"Jamania",
    "gn:country_code":"IN",
    "gn:dem":1119,
    "gn:feature_class":"P",
    "gn:feature_code":"PPL",
    "gn:name":"Jamania",
    "gn:population":0,
    "gn:timezone":"Asia/Kolkata",
    "iso:country":"IN",
    "ks:ks_alt_nam":"Jamania",
    "ks:ks_name":"Jamani",
    "ks:ks_type":"VILLAGE",
    "name:eng_x_preferred":[
        "Jamani"
    ],
    "name:eng_x_variant":[
        "Jamania"
    ],
    "wof:name":"Jamani",
    "wof:placetype":"locality"
},
  "geometry": {"coordinates":[79.35402000000001,29.915487],"type":"Point"}
}