{
  "type": "Feature",
  "properties": {
    "iso:country":"IN",
    "ks:ks_name":"Sajan Ki Dhani",
    "ks:ks_pop":578,
    "ks:ks_type":"VILLAGE",
    "name:eng_x_preferred":[
        "Sajan Ki Dhani"
    ],
    "wof:name":"Sajan Ki Dhani",
    "wof:placetype":"locality",
    "wof:population":578
},
  "geometry": {"coordinates":[71.82468900000001,25.738918],"type":"Point"}
}