{
  "type": "Feature",
  "properties": {
    "gn:admin1_code":"33",
    "gn:admin2_code":"585.0",
    "gn:asciiname":"Piligao",
    "gn:country_code":"IN",
    "gn:dem":15,
    "gn:feature_class":"P",
    "gn:feature_code":"PPL",
    "gn:name":"Piligao",
    "gn:population":0,
    "gn:timezone":"Asia/Kolkata",
    "iso:country":"IN",
    "ks:ks_name":"Piligao",
    "ks:ks_pop":2695,
    "ks:ks_type":"VILLAGE",
    "name:eng_x_preferred":[
        "Piligao"
    ],
    "name:und_x_variant":[
        "Pelig\u00e3o",
        "Piligao"
    ],
    "wof:name":"Piligao",
    "wof:placetype":"locality",
    "wof:population":2695
},
  "geometry": {"coordinates":[73.95305399999999,15.551988],"type":"Point"}
}