{
  "type": "Feature",
  "properties": {
    "gn:admin1_code":"33",
    "gn:admin2_code":"585.0",
    "gn:asciiname":"Piligao",
    "gn:country_code":"IN",
    "gn:dem":15,
    "gn:feature_class":"P",
    "gn:feature_code":"PPL",
    "gn:name":"Piligao",
    "gn:population":0,
    "gn:timezone":"Asia/Kolkata",
    "iso:country":"IN",
    "name:und_x_variant":[
        "Pelig\u00e3o",
        "Piligao"
    ],
    "wof:name":"Piligao",
    "wof:placetype":"locality"
},
  "geometry": {"coordinates":[73.95305,15.55199],"type":"Point"}
}