{
  "type": "Feature",
  "properties": {
    "gn:admin1_code":"23.0",
    "gn:admin2_code":"50.0",
    "gn:asciiname":"Bhura Hithar",
    "gn:country_code":"IN",
    "gn:dem":203,
    "gn:feature_class":"P",
    "gn:feature_code":"PPL",
    "gn:name":"Bhura Hith\u0101r",
    "gn:population":0,
    "gn:timezone":"Asia/Kolkata",
    "iso:country":"IN",
    "ks:ks_alt_nam":"Bhura Hith\u0101r",
    "ks:ks_name":"Bhura Hithar",
    "ks:ks_type":"VILLAGE",
    "name:eng_x_preferred":[
        "Bhura Hithar"
    ],
    "name:eng_x_variant":[
        "Bhura Hith\u0101r"
    ],
    "wof:name":"Bhura Hithar",
    "wof:placetype":"locality"
},
  "geometry": {"coordinates":[74.81817100000001,31.154194],"type":"Point"}
}