{
  "type": "Feature",
  "properties": {
    "iso:country":"IN",
    "ks:ks_alt_nam":"BAJAR MURA PARA",
    "ks:ks_name":"Bajar Mura Para",
    "ks:ks_pop":34,
    "ks:ks_type":"HABITATION",
    "ks:ks_uagg_main":0,
    "name:eng_x_preferred":[
        "Bajar Mura Para"
    ],
    "wof:name":"Bajar Mura Para",
    "wof:placetype":"neighbourhood",
    "wof:population":34
},
  "geometry": {"coordinates":[91.37141,23.916864],"type":"Point"}
}