{
  "type": "Feature",
  "properties": {
    "iso:country":"IN",
    "ks:ks_alt_nam":"Kedi pada",
    "ks:ks_name":"Kedi Pada",
    "ks:ks_pop":580,
    "ks:ks_type":"HABITATION",
    "name:eng_x_preferred":[
        "Kedi Pada"
    ],
    "wof:name":"Kedi Pada",
    "wof:placetype":"locality",
    "wof:population":580
},
  "geometry": {"coordinates":[73.34441700000001,20.625778],"type":"Point"}
}