{
  "type": "Feature",
  "properties": {
    "iso:country":"IN",
    "ks:ks_name":"Parabwadi",
    "ks:ks_pop":293,
    "ks:ks_type":"HABITATION",
    "name:eng_x_preferred":[
        "Parabwadi"
    ],
    "wof:name":"Parabwadi",
    "wof:placetype":"locality",
    "wof:population":293
},
  "geometry": {"coordinates":[73.692605,16.204323],"type":"Point"}
}