{
  "type": "Feature",
  "properties": {
    "gn:admin1_code":"35.0",
    "gn:admin2_code":"445.0",
    "gn:asciiname":"Lasuria Bijai Singh",
    "gn:country_code":"IN",
    "gn:dem":524,
    "gn:feature_class":"P",
    "gn:feature_code":"PPL",
    "gn:name":"Las\u016bria Bijai Singh",
    "gn:population":0,
    "gn:timezone":"Asia/Kolkata",
    "iso:country":"IN",
    "wof:name":"Lasuria Bijai Singh",
    "wof:placetype":"locality"
},
  "geometry": {"coordinates":[76.7183,22.94416],"type":"Point"}
}