{
  "type": "Feature",
  "properties": {
    "iso:country":"IN",
    "ks:ks_name":"Karagola",
    "ks:ks_pop":0,
    "ks:ks_type":"VILLAGE",
    "name:eng_x_preferred":[
        "Karagola"
    ],
    "wof:name":"Karagola",
    "wof:placetype":"locality",
    "wof:population":0
},
  "geometry": {"coordinates":[85.833788,20.95433],"type":"Point"}
}