{
  "type": "Feature",
  "properties": {
    "iso:country":"IN",
    "ks:ks_name":"Upperkai Pada",
    "ks:ks_pop":1221,
    "ks:ks_type":"VILLAGE",
    "ks:ks_uagg_main":0,
    "name:eng_x_preferred":[
        "Upperkai Pada"
    ],
    "wof:name":"Upperkai Pada",
    "wof:placetype":"neighbourhood",
    "wof:population":1221
},
  "geometry": {"coordinates":[86.40602199999999,20.633883],"type":"Point"}
}