{
  "type": "Feature",
  "properties": {
    "gn:admin1_code":"34.0",
    "gn:admin2_code":"209.0",
    "gn:asciiname":"Bengbahi",
    "gn:country_code":"IN",
    "gn:dem":56,
    "gn:feature_class":"P",
    "gn:feature_code":"PPL",
    "gn:name":"Bengb\u0101hi",
    "gn:population":0,
    "gn:timezone":"Asia/Kolkata",
    "iso:country":"IN",
    "wof:name":"Bengbahi",
    "wof:placetype":"neighbourhood"
},
  "geometry": {"coordinates":[87.16331,26.03981],"type":"Point"}
}