{
  "type": "Feature",
  "properties": {
    "iso:country":"IN",
    "ks:ks_name":"Heliburia",
    "ks:ks_pop":2045,
    "ks:ks_type":"HABITATION",
    "name:eng_x_preferred":[
        "Heliburia"
    ],
    "wof:name":"Heliburia",
    "wof:placetype":"locality",
    "wof:population":2045
},
  "geometry": {"coordinates":[77.00945299999999,9.64253],"type":"Point"}
}