{
  "type": "Feature",
  "properties": {
    "iso:country":"IN",
    "ks:ks_name":"Valabu",
    "ks:ks_pop":308,
    "ks:ks_type":"VILLAGE",
    "name:eng_x_preferred":[
        "Valabu"
    ],
    "wof:name":"Valabu",
    "wof:placetype":"locality",
    "wof:population":308
},
  "geometry": {"coordinates":[82.894604,18.007897],"type":"Point"}
}