{
  "type": "Feature",
  "properties": {
    "iso:country":"IN",
    "ks:ks_name":"Ladukeswarprasad",
    "ks:ks_pop":385,
    "ks:ks_type":"VILLAGE",
    "name:eng_x_preferred":[
        "Ladukeswarprasad"
    ],
    "wof:name":"Ladukeswarprasad",
    "wof:placetype":"locality",
    "wof:population":385
},
  "geometry": {"coordinates":[85.194096,20.024528],"type":"Point"}
}