{
  "type": "Feature",
  "properties": {
    "gn:admin1_code":"34.0",
    "gn:admin2_code":"239.0",
    "gn:asciiname":"Sukhdeo Bigha",
    "gn:country_code":"IN",
    "gn:dem":67,
    "gn:feature_class":"P",
    "gn:feature_code":"PPL",
    "gn:name":"Sukhdeo Bigha",
    "gn:population":0,
    "gn:timezone":"Asia/Kolkata",
    "iso:country":"IN",
    "wof:name":"Sukhdeo Bigha",
    "wof:placetype":"neighbourhood"
},
  "geometry": {"coordinates":[85.04043,25.22033],"type":"Point"}
}