{
  "type": "Feature",
  "properties": {
    "iso:country":"IN",
    "ks:ks_name":"Kanajar Guddeyangady",
    "ks:ks_pop":181,
    "ks:ks_type":"HABITATION",
    "name:eng_x_preferred":[
        "Kanajar Guddeyangady"
    ],
    "wof:name":"Kanajar Guddeyangady",
    "wof:placetype":"locality",
    "wof:population":181
},
  "geometry": {"coordinates":[74.888879,13.31494],"type":"Point"}
}