{
  "type": "Feature",
  "properties": {
    "iso:country":"IN",
    "ks:ks_alt_nam":"Hoogucha H.C. Road",
    "ks:ks_name":"Hoogucha H.c. Road",
    "ks:ks_pop":98,
    "ks:ks_type":"HABITATION",
    "name:eng_x_preferred":[
        "Hoogucha H.c. Road"
    ],
    "wof:name":"Hoogucha H.c. Road",
    "wof:placetype":"locality",
    "wof:population":98
},
  "geometry": {"coordinates":[75.81222200000001,12.353056],"type":"Point"}
}