{
  "type": "Feature",
  "properties": {
    "iso:country":"IN",
    "ks:ks_name":"Bankhet",
    "ks:ks_pop":571,
    "ks:ks_type":"VILLAGE",
    "name:eng_x_preferred":[
        "Bankhet"
    ],
    "wof:name":"Bankhet",
    "wof:placetype":"locality",
    "wof:population":571
},
  "geometry": {"coordinates":[87.017296,23.858534],"type":"Point"}
}