{
  "type": "Feature",
  "properties": {
    "iso:country":"IN",
    "ks:ks_name":"Chatbud",
    "ks:ks_pop":255,
    "ks:ks_type":"HABITATION",
    "name:eng_x_preferred":[
        "Chatbud"
    ],
    "wof:name":"Chatbud",
    "wof:placetype":"locality",
    "wof:population":255
},
  "geometry": {"coordinates":[84.292368,22.248213],"type":"Point"}
}