{
  "type": "Feature",
  "properties": {
    "iso:country":"IN",
    "ks:ks_alt_nam":"PANRE KE BHUIN",
    "ks:ks_name":"Panre Ke Bhuin",
    "ks:ks_pop":211,
    "ks:ks_type":"HABITATION",
    "name:eng_x_preferred":[
        "Panre Ke Bhuin"
    ],
    "wof:name":"Panre Ke Bhuin",
    "wof:placetype":"locality",
    "wof:population":211
},
  "geometry": {"coordinates":[84.57492999999999,26.02861],"type":"Point"}
}