{
  "type": "Feature",
  "properties": {
    "iso:country":"IN",
    "ks:ks_alt_nam":"Venniyoor GM Upper Primary School Jnc",
    "ks:ks_name":"Venniyoor Gm Upper Primary School Jnc",
    "ks:ks_pop":1641,
    "ks:ks_type":"HABITATION",
    "name:eng_x_preferred":[
        "Venniyoor Gm Upper Primary School Jnc"
    ],
    "wof:name":"Venniyoor Gm Upper Primary School Jnc",
    "wof:placetype":"locality",
    "wof:population":1641
},
  "geometry": {"coordinates":[75.95471999999999,11.013093],"type":"Point"}
}