{
  "type": "Feature",
  "properties": {
    "gn:admin1_code":"35",
    "gn:admin2_code":"447.0",
    "gn:asciiname":"Maudhana",
    "gn:country_code":"IN",
    "gn:dem":519,
    "gn:feature_class":"P",
    "gn:feature_code":"PPL",
    "gn:name":"Ma\u016bdh\u0101na",
    "gn:population":0,
    "gn:timezone":"Asia/Kolkata",
    "iso:country":"IN",
    "wof:name":"Maudhana",
    "wof:placetype":"locality"
},
  "geometry": {"coordinates":[77.68119,21.81618],"type":"Point"}
}