{
  "type": "Feature",
  "properties": {
    "iso:country":"IN",
    "ks:ks_name":"Phalpaju",
    "ks:ks_pop":12,
    "ks:ks_type":"VILLAGE",
    "name:eng_x_preferred":[
        "Phalpaju"
    ],
    "wof:name":"Phalpaju",
    "wof:placetype":"locality",
    "wof:population":12
},
  "geometry": {"coordinates":[84.503619,20.402114],"type":"Point"}
}