{
  "type": "Feature",
  "properties": {
    "iso:country":"IN",
    "ks:ks_name":"Gujjanahalli",
    "ks:ks_pop":200,
    "ks:ks_type":"HABITATION",
    "name:eng_x_preferred":[
        "Gujjanahalli"
    ],
    "wof:name":"Gujjanahalli",
    "wof:placetype":"locality",
    "wof:population":200
},
  "geometry": {"coordinates":[75.77797099999999,13.016193],"type":"Point"}
}