{
  "type": "Feature",
  "properties": {
    "iso:country":"IN",
    "ks:ks_name":"Rehati",
    "ks:ks_pop":0,
    "ks:ks_type":"VILLAGE",
    "name:eng_x_preferred":[
        "Rehati"
    ],
    "wof:name":"Rehati",
    "wof:placetype":"locality",
    "wof:population":0
},
  "geometry": {"coordinates":[83.11481999999999,25.564378],"type":"Point"}
}