{
  "type": "Feature",
  "properties": {
    "iso:country":"IN",
    "ks:ks_name":"Gudri",
    "ks:ks_pop":58,
    "ks:ks_type":"VILLAGE",
    "name:eng_x_preferred":[
        "Gudri"
    ],
    "wof:name":"Gudri",
    "wof:placetype":"locality",
    "wof:population":58
},
  "geometry": {"coordinates":[79.844278,23.889529],"type":"Point"}
}