{
  "type": "Feature",
  "properties": {
    "iso:country":"IN",
    "ks:ks_name":"Kittalebailu",
    "ks:ks_pop":46,
    "ks:ks_type":"HABITATION",
    "name:eng_x_preferred":[
        "Kittalebailu"
    ],
    "wof:name":"Kittalebailu",
    "wof:placetype":"locality",
    "wof:population":46
},
  "geometry": {"coordinates":[75.224895,13.437197],"type":"Point"}
}