{
  "type": "Feature",
  "properties": {
    "iso:country":"IN",
    "ks:ks_name":"Dhobiyan Purwa",
    "ks:ks_pop":54,
    "ks:ks_type":"HABITATION",
    "name:eng_x_preferred":[
        "Dhobiyan Purwa"
    ],
    "wof:name":"Dhobiyan Purwa",
    "wof:placetype":"locality",
    "wof:population":54
},
  "geometry": {"coordinates":[81.322918,27.402677],"type":"Point"}
}