{
  "type": "Feature",
  "properties": {
    "iso:country":"IN",
    "ks:ks_name":"Hikiriguda",
    "ks:ks_pop":21,
    "ks:ks_type":"VILLAGE",
    "name:eng_x_preferred":[
        "Hikiriguda"
    ],
    "wof:name":"Hikiriguda",
    "wof:placetype":"locality",
    "wof:population":21
},
  "geometry": {"coordinates":[83.61850099999999,19.4014],"type":"Point"}
}