{
  "type": "Feature",
  "properties": {
    "gn:admin1_code":"36.0",
    "gn:admin2_code":"137.0",
    "gn:asciiname":"Qasimpur",
    "gn:country_code":"IN",
    "gn:dem":201,
    "gn:feature_class":"P",
    "gn:feature_code":"PPL",
    "gn:name":"Q\u0101simpur",
    "gn:population":0,
    "gn:timezone":"Asia/Kolkata",
    "iso:country":"IN",
    "wof:name":"Qasimpur",
    "wof:placetype":"locality"
},
  "geometry": {"coordinates":[78.35645,28.60655],"type":"Point"}
}