{
  "type": "Feature",
  "properties": {
    "gn:admin1_code":"34",
    "gn:admin2_code":"234.0",
    "gn:asciiname":"Sikandarpur",
    "gn:country_code":"IN",
    "gn:dem":112,
    "gn:feature_class":"P",
    "gn:feature_code":"PPL",
    "gn:name":"Sikandarpur",
    "gn:population":0,
    "gn:timezone":"Asia/Kolkata",
    "iso:country":"IN",
    "ks:ks_name":"Sikandarpur",
    "ks:ks_pop":1350,
    "ks:ks_type":"VILLAGE",
    "name:eng_x_preferred":[
        "Sikandarpur"
    ],
    "wof:name":"Sikandarpur",
    "wof:placetype":"locality",
    "wof:population":1350
},
  "geometry": {"coordinates":[83.900846,24.856322],"type":"Point"}
}