{
  "type": "Feature",
  "properties": {
    "iso:country":"IN",
    "ks:ks_name":"Kharija Kesharibari",
    "ks:ks_pop":500,
    "ks:ks_type":"VILLAGE",
    "name:eng_x_preferred":[
        "Kharija Kesharibari"
    ],
    "wof:name":"Kharija Kesharibari",
    "wof:placetype":"locality",
    "wof:population":500
},
  "geometry": {"coordinates":[89.11215300000001,26.461136],"type":"Point"}
}