{
  "type": "Feature",
  "properties": {
    "gn:admin1_code":"16.0",
    "gn:admin2_code":"523.0",
    "gn:asciiname":"Salimba",
    "gn:country_code":"IN",
    "gn:dem":473,
    "gn:feature_class":"P",
    "gn:feature_code":"PPL",
    "gn:name":"S\u0101l\u012bmba",
    "gn:population":0,
    "gn:timezone":"Asia/Kolkata",
    "iso:country":"IN",
    "wof:name":"Salimba",
    "wof:placetype":"locality"
},
  "geometry": {"coordinates":[76.03537,19.03818],"type":"Point"}
}