{
  "type": "Feature",
  "properties": {
    "iso:country":"IN",
    "ks:ks_alt_nam":"Gar tola",
    "ks:ks_name":"Gar Tola",
    "ks:ks_pop":150,
    "ks:ks_type":"HABITATION",
    "name:eng_x_preferred":[
        "Gar Tola"
    ],
    "wof:name":"Gar Tola",
    "wof:placetype":"locality",
    "wof:population":150
},
  "geometry": {"coordinates":[84.79537500000001,26.241701],"type":"Point"}
}