{
  "type": "Feature",
  "properties": {
    "gn:admin1_code":"2.0",
    "gn:admin2_code":"554.0",
    "gn:asciiname":"Kottapalli",
    "gn:country_code":"IN",
    "gn:dem":593,
    "gn:feature_class":"P",
    "gn:feature_code":"PPL",
    "gn:name":"Kottapalli",
    "gn:population":0,
    "gn:timezone":"Asia/Kolkata",
    "iso:country":"IN",
    "ks:ks_name":"Kothapalle",
    "ks:ks_pop":129,
    "ks:ks_type":"HABITATION",
    "name:eng_x_preferred":[
        "Kothapalle"
    ],
    "name:eng_x_variant":[
        "Kottapalli"
    ],
    "wof:name":"Kothapalle",
    "wof:placetype":"locality",
    "wof:population":129
},
  "geometry": {"coordinates":[79.156217,13.727202],"type":"Point"}
}