{
  "type": "Feature",
  "properties": {
    "gn:admin1_code":"2.0",
    "gn:admin2_code":"554.0",
    "gn:asciiname":"Kottapalli",
    "gn:country_code":"IN",
    "gn:dem":593,
    "gn:feature_class":"P",
    "gn:feature_code":"PPL",
    "gn:name":"Kottapalli",
    "gn:population":0,
    "gn:timezone":"Asia/Kolkata",
    "iso:country":"IN",
    "wof:name":"Kottapalli",
    "wof:placetype":"locality"
},
  "geometry": {"coordinates":[79.15971999999999,13.72506],"type":"Point"}
}