{
  "type": "Feature",
  "properties": {
    "gn:admin1_code":"24",
    "gn:admin2_code":"101.0",
    "gn:asciiname":"Seura",
    "gn:country_code":"IN",
    "gn:dem":180,
    "gn:feature_class":"P",
    "gn:feature_code":"PPL",
    "gn:name":"Seura",
    "gn:population":0,
    "gn:timezone":"Asia/Kolkata",
    "iso:country":"IN",
    "name:fin_x_preferred":[
        "Seura"
    ],
    "name:swe_x_preferred":[
        "Seura"
    ],
    "name:und_x_variant":[
        "Seora",
        "Seura"
    ],
    "wof:name":"Seura",
    "wof:placetype":"locality"
},
  "geometry": {"coordinates":[72.30596,27.53572],"type":"Point"}
}