{
  "type": "Feature",
  "properties": {
    "gn:admin1_code":"11.0",
    "gn:admin2_code":"32.0",
    "gn:asciiname":"Kalari",
    "gn:country_code":"IN",
    "gn:dem":737,
    "gn:feature_class":"P",
    "gn:feature_code":"PPL",
    "gn:name":"Kal\u0101ri",
    "gn:population":0,
    "gn:timezone":"Asia/Kolkata",
    "iso:country":"IN",
    "name:mal_x_preferred":[
        "\u0d15\u0d33\u0d30\u0d3f"
    ],
    "wof:name":"Kalari",
    "wof:placetype":"locality"
},
  "geometry": {"coordinates":[77.43653,30.58867],"type":"Point"}
}