{
  "type": "Feature",
  "properties": {
    "iso:country":"IN",
    "ks:ks_name":"Jaraganda",
    "ks:ks_pop":209,
    "ks:ks_type":"VILLAGE",
    "name:eng_x_preferred":[
        "Jaraganda"
    ],
    "wof:name":"Jaraganda",
    "wof:placetype":"locality",
    "wof:population":209
},
  "geometry": {"coordinates":[84.10592800000001,19.410929],"type":"Point"}
}