{
  "type": "Feature",
  "properties": {
    "gn:admin1_code":"19.0",
    "gn:admin2_code":"577.0",
    "gn:asciiname":"Kaifaspur",
    "gn:country_code":"IN",
    "gn:dem":876,
    "gn:feature_class":"P",
    "gn:feature_code":"PPL",
    "gn:name":"Kaifaspur",
    "gn:population":0,
    "gn:timezone":"Asia/Kolkata",
    "iso:country":"IN",
    "wof:name":"Kaifaspur",
    "wof:placetype":"locality"
},
  "geometry": {"coordinates":[75.97753,12.4102],"type":"Point"}
}