{
  "type": "Feature",
  "properties": {
    "iso:country":"IN",
    "ks:ks_name":"Gaddebailu",
    "ks:ks_pop":40,
    "ks:ks_type":"HABITATION",
    "name:eng_x_preferred":[
        "Gaddebailu"
    ],
    "wof:name":"Gaddebailu",
    "wof:placetype":"locality",
    "wof:population":40
},
  "geometry": {"coordinates":[74.729263,14.730508],"type":"Point"}
}