{
  "type": "Feature",
  "properties": {
    "iso:country":"IN",
    "ks:ks_name":"Khajurichuan",
    "ks:ks_pop":48,
    "ks:ks_type":"HABITATION",
    "name:eng_x_preferred":[
        "Khajurichuan"
    ],
    "wof:name":"Khajurichuan",
    "wof:placetype":"locality",
    "wof:population":48
},
  "geometry": {"coordinates":[84.104494,20.622104],"type":"Point"}
}