{
  "type": "Feature",
  "properties": {
    "gn:admin1_code":"37.0",
    "gn:admin2_code":"411",
    "gn:asciiname":"Garh Phuljhar",
    "gn:country_code":"IN",
    "gn:dem":267,
    "gn:feature_class":"P",
    "gn:feature_code":"PPL",
    "gn:name":"Garh Phuljhar",
    "gn:population":0,
    "gn:timezone":"Asia/Kolkata",
    "iso:country":"IN",
    "wof:name":"Garh Phuljhar",
    "wof:placetype":"locality"
},
  "geometry": {"coordinates":[82.85047,21.21116],"type":"Point"}
}