{
  "type": "Feature",
  "properties": {
    "iso:country":"IN",
    "ks:ks_name":"Gavandarewasti Bhose",
    "ks:ks_pop":101,
    "ks:ks_type":"HABITATION",
    "name:eng_x_preferred":[
        "Gavandarewasti Bhose"
    ],
    "wof:name":"Gavandarewasti Bhose",
    "wof:placetype":"locality",
    "wof:population":101
},
  "geometry": {"coordinates":[75.290848,17.793847],"type":"Point"}
}