{
  "type": "Feature",
  "properties": {
    "iso:country":"IN",
    "ks:ks_name":"Pedavanija",
    "ks:ks_pop":86,
    "ks:ks_type":"HABITATION",
    "name:eng_x_preferred":[
        "Pedavanija"
    ],
    "wof:name":"Pedavanija",
    "wof:placetype":"locality",
    "wof:population":86
},
  "geometry": {"coordinates":[83.645708,18.900983],"type":"Point"}
}