{
  "type": "Feature",
  "properties": {
    "gn:admin1_code":"21",
    "gn:admin2_code":"394.0",
    "gn:asciiname":"Kendumura",
    "gn:country_code":"IN",
    "gn:dem":275,
    "gn:feature_class":"P",
    "gn:feature_code":"PPL",
    "gn:name":"Kendumura",
    "gn:population":0,
    "gn:timezone":"Asia/Kolkata",
    "iso:country":"IN",
    "wof:name":"Kendumura",
    "wof:placetype":"locality"
},
  "geometry": {"coordinates":[82.57236999999998,20.07013],"type":"Point"}
}