{
  "type": "Feature",
  "properties": {
    "gn:admin1_code":"34.0",
    "gn:admin2_code":"221.0",
    "gn:asciiname":"Chak Bheli",
    "gn:country_code":"IN",
    "gn:dem":52,
    "gn:feature_class":"P",
    "gn:feature_code":"PPL",
    "gn:name":"Chak Bheli",
    "gn:population":0,
    "gn:timezone":"Asia/Kolkata",
    "iso:country":"IN",
    "ks:ks_name":"Chakbheli",
    "ks:ks_pop":1375,
    "ks:ks_type":"VILLAGE",
    "name:eng_x_preferred":[
        "Chakbheli"
    ],
    "name:eng_x_variant":[
        "Chak Bheli"
    ],
    "wof:name":"Chakbheli",
    "wof:placetype":"locality",
    "wof:population":1375
},
  "geometry": {"coordinates":[85.625575,25.679562],"type":"Point"}
}