{
  "type": "Feature",
  "properties": {
    "iso:country":"IN",
    "ks:ks_alt_nam":"Pump house",
    "ks:ks_name":"Pump House",
    "ks:ks_pop":373,
    "ks:ks_type":"HABITATION",
    "name:eng_x_preferred":[
        "Pump House"
    ],
    "wof:name":"Pump House",
    "wof:placetype":"locality",
    "wof:population":373
},
  "geometry": {"coordinates":[76.440521,10.693726],"type":"Point"}
}