{
  "type": "Feature",
  "properties": {
    "gn:admin1_code":"19.0",
    "gn:admin2_code":"557",
    "gn:asciiname":"Korhalli",
    "gn:country_code":"IN",
    "gn:dem":450,
    "gn:feature_class":"P",
    "gn:feature_code":"PPL",
    "gn:name":"Korhalli",
    "gn:population":0,
    "gn:timezone":"Asia/Kolkata",
    "iso:country":"IN",
    "wof:name":"Korhalli",
    "wof:placetype":"locality"
},
  "geometry": {"coordinates":[76.22533,17.02953],"type":"Point"}
}