{
  "type": "Feature",
  "properties": {
    "iso:country":"IN",
    "ks:ks_name":"Karandi",
    "ks:ks_pop":1910,
    "ks:ks_type":"VILLAGE",
    "ks:ks_uagg_main":0,
    "name:eng_x_preferred":[
        "Karandi"
    ],
    "wof:name":"Karandi",
    "wof:placetype":"neighbourhood",
    "wof:population":1910
},
  "geometry": {"coordinates":[86.180088,23.323144],"type":"Point"}
}