{
  "type": "Feature",
  "properties": {
    "gn:admin1_code":"36",
    "gn:admin2_code":"191.0",
    "gn:asciiname":"Kolpur",
    "gn:country_code":"IN",
    "gn:dem":84,
    "gn:feature_class":"P",
    "gn:feature_code":"PPL",
    "gn:name":"Kolpur",
    "gn:population":0,
    "gn:timezone":"Asia/Kolkata",
    "iso:country":"IN",
    "name:fas_x_preferred":[
        "\u06a9\u0648\u0644\u067e\u0648\u0631"
    ],
    "name:urd_x_preferred":[
        "\u06a9\u0648\u0644\u067e\u0648\u0631"
    ],
    "wof:name":"Kolpur",
    "wof:placetype":"locality"
},
  "geometry": {"coordinates":[82.96016999999998,26.03055],"type":"Point"}
}