{
  "type": "Feature",
  "properties": {
    "iso:country":"IN",
    "ks:ks_name":"Dakshin Kazirhat",
    "ks:ks_pop":2115,
    "ks:ks_type":"VILLAGE",
    "ks:ks_uagg_main":0,
    "name:eng_x_preferred":[
        "Dakshin Kazirhat"
    ],
    "wof:name":"Dakshin Kazirhat",
    "wof:placetype":"locality",
    "wof:population":2115
},
  "geometry": {"coordinates":[88.268652,22.407166],"type":"Point"}
}