{
  "type": "Feature",
  "properties": {
    "gn:admin1_code":"39.0",
    "gn:admin2_code":"061",
    "gn:asciiname":"Sunkatal",
    "gn:country_code":"IN",
    "gn:dem":866,
    "gn:feature_class":"P",
    "gn:feature_code":"PPL",
    "gn:name":"Sunkatal",
    "gn:population":0,
    "gn:timezone":"Asia/Kolkata",
    "iso:country":"IN",
    "ks:ks_name":"Sunkatla",
    "ks:ks_pop":34,
    "ks:ks_type":"VILLAGE",
    "name:eng_x_preferred":[
        "Sunkatla"
    ],
    "name:eng_x_variant":[
        "Sunkatal"
    ],
    "wof:name":"Sunkatla",
    "wof:placetype":"locality",
    "wof:population":34
},
  "geometry": {"coordinates":[78.728582,29.799551],"type":"Point"}
}