{
  "type": "Feature",
  "properties": {
    "iso:country":"IN",
    "ks:ks_name":"Bara Dopaharu",
    "ks:ks_pop":1291,
    "ks:ks_type":"VILLAGE",
    "name:eng_x_preferred":[
        "Bara Dopaharu"
    ],
    "wof:name":"Bara Dopaharu",
    "wof:placetype":"locality",
    "wof:population":1291
},
  "geometry": {"coordinates":[88.484516,26.377441],"type":"Point"}
}