{
  "type": "Feature",
  "properties": {
    "iso:country":"IN",
    "ks:ks_alt_nam":"nivaiwadi",
    "ks:ks_name":"Nivaiwadi",
    "ks:ks_pop":176,
    "ks:ks_type":"HABITATION",
    "name:eng_x_preferred":[
        "Nivaiwadi"
    ],
    "wof:name":"Nivaiwadi",
    "wof:placetype":"locality",
    "wof:population":176
},
  "geometry": {"coordinates":[73.41870900000001,16.745776],"type":"Point"}
}