{
  "type": "Feature",
  "properties": {
    "gn:admin1_code":"24.0",
    "gn:admin2_code":"130",
    "gn:asciiname":"Chirwa",
    "gn:country_code":"IN",
    "gn:dem":728,
    "gn:feature_class":"P",
    "gn:feature_code":"PPL",
    "gn:name":"Chirwa",
    "gn:population":0,
    "gn:timezone":"Asia/Kolkata",
    "iso:country":"IN",
    "wof:name":"Chirwa",
    "wof:placetype":"locality"
},
  "geometry": {"coordinates":[73.74436999999998,24.70675],"type":"Point"}
}