{
  "type": "Feature",
  "properties": {
    "iso:country":"IN",
    "ks:ks_name":"Narottampur",
    "ks:ks_pop":636,
    "ks:ks_type":"VILLAGE",
    "name:eng_x_preferred":[
        "Narottampur"
    ],
    "wof:name":"Narottampur",
    "wof:placetype":"locality",
    "wof:population":636
},
  "geometry": {"coordinates":[87.916258,24.501064],"type":"Point"}
}