{
  "type": "Feature",
  "properties": {
    "iso:country":"IN",
    "ks:ks_name":"Garadiha",
    "ks:ks_pop":1024,
    "ks:ks_type":"VILLAGE",
    "ks:ks_uagg_main":0,
    "name:eng_x_preferred":[
        "Garadiha"
    ],
    "wof:name":"Garadiha",
    "wof:placetype":"neighbourhood",
    "wof:population":1024
},
  "geometry": {"coordinates":[86.546712,20.826416],"type":"Point"}
}