{
  "type": "Feature",
  "properties": {
    "gn:admin1_code":"34.0",
    "gn:admin2_code":"229.0",
    "gn:asciiname":"Pawai",
    "gn:country_code":"IN",
    "gn:dem":61,
    "gn:feature_class":"P",
    "gn:feature_code":"PPL",
    "gn:name":"Paw\u0101i",
    "gn:population":0,
    "gn:timezone":"Asia/Kolkata",
    "iso:country":"IN",
    "name:ben_x_preferred":[
        "\u09aa\u09be\u0993\u09af\u09bc\u09be\u0987"
    ],
    "name:bpy_x_preferred":[
        "\u09aa\u09be\u09f1\u09be\u0987"
    ],
    "name:ceb_x_preferred":[
        "Pawai"
    ],
    "name:ita_x_preferred":[
        "Pawai"
    ],
    "name:msa_x_preferred":[
        "Pawai"
    ],
    "name:nld_x_preferred":[
        "Pawai"
    ],
    "name:por_x_preferred":[
        "Pawai"
    ],
    "name:swe_x_preferred":[
        "Pawai"
    ],
    "name:vie_x_preferred":[
        "Pawai"
    ],
    "name:zho_x_preferred":[
        "\u5e15\u74e6\u4f0a"
    ],
    "wof:name":"Pawai",
    "wof:placetype":"locality"
},
  "geometry": {"coordinates":[85.32415,25.20041],"type":"Point"}
}