{
  "type": "Feature",
  "properties": {
    "gn:admin1_code":"11.0",
    "gn:admin2_code":"27.0",
    "gn:asciiname":"Dhangthar",
    "gn:country_code":"IN",
    "gn:dem":2566,
    "gn:feature_class":"P",
    "gn:feature_code":"PPL",
    "gn:name":"Dhangthar",
    "gn:population":0,
    "gn:timezone":"Asia/Kolkata",
    "iso:country":"IN",
    "wof:name":"Dhangthar",
    "wof:placetype":"locality"
},
  "geometry": {"coordinates":[77.10781,31.52754],"type":"Point"}
}