{
  "type": "Feature",
  "properties": {
    "iso:country":"IN",
    "ks:ks_name":"Turakorahalli",
    "ks:ks_pop":16,
    "ks:ks_type":"HABITATION",
    "name:eng_x_preferred":[
        "Turakorahalli"
    ],
    "wof:name":"Turakorahalli",
    "wof:placetype":"locality",
    "wof:population":16
},
  "geometry": {"coordinates":[78.397226,13.14265],"type":"Point"}
}