{
  "type": "Feature",
  "properties": {
    "gn:admin1_code":"23.0",
    "gn:admin2_code":"35.0",
    "gn:asciiname":"Hardo Saran",
    "gn:country_code":"IN",
    "gn:dem":519,
    "gn:feature_class":"P",
    "gn:feature_code":"PPL",
    "gn:name":"Hardo Saran",
    "gn:population":0,
    "gn:timezone":"Asia/Kolkata",
    "iso:country":"IN",
    "name:und_x_variant":[
        "Sirni"
    ],
    "wof:name":"Hardo Saran",
    "wof:placetype":"locality"
},
  "geometry": {"coordinates":[75.79549,32.42961],"type":"Point"}
}