{
  "type": "Feature",
  "properties": {
    "iso:country":"IN",
    "ks:ks_name":"Bargadahi Tola",
    "ks:ks_pop":450,
    "ks:ks_type":"HABITATION",
    "ks:ks_uagg_main":0,
    "name:eng_x_preferred":[
        "Bargadahi Tola"
    ],
    "wof:name":"Bargadahi Tola",
    "wof:placetype":"neighbourhood",
    "wof:population":450
},
  "geometry": {"coordinates":[83.80341799999999,26.95326],"type":"Point"}
}