{
  "type": "Feature",
  "properties": {
    "iso:country":"IN",
    "ks:ks_name":"Sisubari No.3",
    "ks:ks_pop":50,
    "ks:ks_type":"VILLAGE",
    "name:eng_x_preferred":[
        "Sisubari No.3"
    ],
    "wof:name":"Sisubari No.3",
    "wof:placetype":"locality",
    "wof:population":50
},
  "geometry": {"coordinates":[90.630211,26.51194],"type":"Point"}
}