{
  "type": "Feature",
  "properties": {
    "iso:country":"IN",
    "ks:ks_name":"Thatimanubanda",
    "ks:ks_pop":225,
    "ks:ks_type":"HABITATION",
    "name:eng_x_preferred":[
        "Thatimanubanda"
    ],
    "wof:name":"Thatimanubanda",
    "wof:placetype":"locality",
    "wof:population":225
},
  "geometry": {"coordinates":[82.33877699999999,17.703189],"type":"Point"}
}