{
  "type": "Feature",
  "properties": {
    "gn:admin1_code":"2.0",
    "gn:admin2_code":"554.0",
    "gn:asciiname":"Madhavaram",
    "gn:country_code":"IN",
    "gn:dem":336,
    "gn:feature_class":"P",
    "gn:feature_code":"PPL",
    "gn:name":"M\u0101dhavaram",
    "gn:population":0,
    "gn:timezone":"Asia/Kolkata",
    "iso:country":"IN",
    "name:bih_x_preferred":[
        "\u092e\u0926\u093e\u0935\u0930\u092e"
    ],
    "name:bpy_x_preferred":[
        "\u09ae\u09be\u09a7\u09ac\u09b0\u09be\u09ae"
    ],
    "name:deu_x_preferred":[
        "Madhavaram"
    ],
    "name:ita_x_preferred":[
        "Madavaram"
    ],
    "name:msa_x_preferred":[
        "Madavaram"
    ],
    "name:new_x_preferred":[
        "\u092e\u093e\u0927\u0935\u0930\u093e\u092e"
    ],
    "name:por_x_preferred":[
        "Madavaram"
    ],
    "name:spa_x_preferred":[
        "Madavaram"
    ],
    "name:tam_x_preferred":[
        "\u0bae\u0bbe\u0ba4\u0bb5\u0bb0\u0bae\u0bcd"
    ],
    "name:urd_x_preferred":[
        "\u0645\u062f\u06be\u0627\u0648\u0627\u0631\u0627\u0645"
    ],
    "name:vie_x_preferred":[
        "Madavaram"
    ],
    "name:zho_x_preferred":[
        "\u9a6c\u8fbe\u74e6\u62c9\u59c6"
    ],
    "wof:name":"Madhavaram",
    "wof:placetype":"locality"
},
  "geometry": {"coordinates":[79.06564,13.17495],"type":"Point"}
}