{
  "type": "Feature",
  "properties": {
    "gn:admin1_code":"19",
    "gn:admin2_code":"579.0",
    "gn:asciiname":"Somanathalli",
    "gn:country_code":"IN",
    "gn:dem":481,
    "gn:feature_class":"P",
    "gn:feature_code":"PPL",
    "gn:name":"Soman\u0101thalli",
    "gn:population":0,
    "gn:timezone":"Asia/Kolkata",
    "iso:country":"IN",
    "wof:name":"Somanathalli",
    "wof:placetype":"locality"
},
  "geometry": {"coordinates":[76.72379000000002,16.88669],"type":"Point"}
}