{
  "type": "Feature",
  "properties": {
    "iso:country":"IN",
    "ks:ks_name":"Chittukadu",
    "ks:ks_pop":210,
    "ks:ks_type":"HABITATION",
    "ks:ks_uagg_main":0,
    "name:eng_x_preferred":[
        "Chittukadu"
    ],
    "wof:name":"Chittukadu",
    "wof:placetype":"neighbourhood",
    "wof:population":210
},
  "geometry": {"coordinates":[80.04871,13.090402],"type":"Point"}
}