{
  "type": "Feature",
  "properties": {
    "iso:country":"IN",
    "ks:ks_name":"Mastikonda",
    "ks:ks_pop":76,
    "ks:ks_type":"HABITATION",
    "name:eng_x_preferred":[
        "Mastikonda"
    ],
    "wof:name":"Mastikonda",
    "wof:placetype":"locality",
    "wof:population":76
},
  "geometry": {"coordinates":[74.73531,14.339028],"type":"Point"}
}