{
  "type": "Feature",
  "properties": {
    "iso:country":"IN",
    "ks:ks_name":"Mullikudi",
    "ks:ks_pop":627,
    "ks:ks_type":"HABITATION",
    "name:eng_x_preferred":[
        "Mullikudi"
    ],
    "wof:name":"Mullikudi",
    "wof:placetype":"locality",
    "wof:population":627
},
  "geometry": {"coordinates":[78.32570200000001,9.594395],"type":"Point"}
}