{
  "type": "Feature",
  "properties": {
    "iso:country":"IN",
    "ks:ks_name":"Giddha",
    "ks:ks_pop":1407,
    "ks:ks_type":"HABITATION",
    "name:eng_x_preferred":[
        "Giddha"
    ],
    "wof:name":"Giddha",
    "wof:placetype":"locality",
    "wof:population":1407
},
  "geometry": {"coordinates":[86.602633,24.880804],"type":"Point"}
}