{
  "type": "Feature",
  "properties": {
    "iso:country":"IN",
    "ks:ks_name":"Gajalamamudi",
    "ks:ks_pop":577,
    "ks:ks_type":"VILLAGE",
    "name:eng_x_preferred":[
        "Gajalamamudi"
    ],
    "wof:name":"Gajalamamudi",
    "wof:placetype":"locality",
    "wof:population":577
},
  "geometry": {"coordinates":[82.20855,18.169022],"type":"Point"}
}