{
  "type": "Feature",
  "properties": {
    "gn:admin1_code":"9.0",
    "gn:admin2_code":"468",
    "gn:asciiname":"Dholovira",
    "gn:country_code":"IN",
    "gn:dem":20,
    "gn:feature_class":"P",
    "gn:feature_code":"PPL",
    "gn:name":"Dholovira",
    "gn:population":0,
    "gn:timezone":"Asia/Kolkata",
    "iso:country":"IN",
    "wof:name":"Dholovira",
    "wof:placetype":"locality"
},
  "geometry": {"coordinates":[70.21715,23.87486],"type":"Point"}
}