{
  "type": "Feature",
  "properties": {
    "gn:admin1_code":"9.0",
    "gn:admin2_code":"468",
    "gn:asciiname":"Dholovira",
    "gn:country_code":"IN",
    "gn:dem":20,
    "gn:feature_class":"P",
    "gn:feature_code":"PPL",
    "gn:name":"Dholovira",
    "gn:population":0,
    "gn:timezone":"Asia/Kolkata",
    "iso:country":"IN",
    "ks:ks_name":"Dholavira",
    "ks:ks_pop":2222,
    "ks:ks_type":"VILLAGE",
    "name:eng_x_preferred":[
        "Dholavira"
    ],
    "name:eng_x_variant":[
        "Dholovira"
    ],
    "wof:name":"Dholavira",
    "wof:placetype":"locality",
    "wof:population":2222
},
  "geometry": {"coordinates":[70.215672,23.883381],"type":"Point"}
}