{
  "type": "Feature",
  "properties": {
    "iso:country":"IN",
    "ks:ks_alt_nam":"NORTH JAM TILLA",
    "ks:ks_name":"North Jam Tilla",
    "ks:ks_pop":217,
    "ks:ks_type":"HABITATION",
    "name:eng_x_preferred":[
        "North Jam Tilla"
    ],
    "wof:name":"North Jam Tilla",
    "wof:placetype":"locality",
    "wof:population":217
},
  "geometry": {"coordinates":[91.661023,24.051474],"type":"Point"}
}