{
  "type": "Feature",
  "properties": {
    "gn:admin1_code":"12.0",
    "gn:admin2_code":"004",
    "gn:asciiname":"Beyama",
    "gn:country_code":"IN",
    "gn:dem":3286,
    "gn:feature_class":"P",
    "gn:feature_code":"PPL",
    "gn:name":"Bey\u0101ma",
    "gn:population":0,
    "gn:timezone":"Asia/Kolkata",
    "iso:country":"IN",
    "wof:name":"Beyama",
    "wof:placetype":"locality"
},
  "geometry": {"coordinates":[76.19159999999999,34.57674],"type":"Point"}
}