{
  "type": "Feature",
  "properties": {
    "gn:admin1_code":"36.0",
    "gn:admin2_code":"150.0",
    "gn:asciiname":"Karpia",
    "gn:country_code":"IN",
    "gn:dem":166,
    "gn:feature_class":"P",
    "gn:feature_code":"PPL",
    "gn:name":"Karpia",
    "gn:population":0,
    "gn:timezone":"Asia/Kolkata",
    "iso:country":"IN",
    "ks:ks_name":"Karpia",
    "ks:ks_pop":459,
    "ks:ks_type":"VILLAGE",
    "name:eng_x_preferred":[
        "Karpia"
    ],
    "name:eng_x_variant":[
        "Kirpia"
    ],
    "wof:name":"Karpia",
    "wof:placetype":"locality",
    "wof:population":459
},
  "geometry": {"coordinates":[79.25382,28.26481],"type":"Point"}
}