{
  "type": "Feature",
  "properties": {
    "gn:admin1_code":"36",
    "gn:admin2_code":"178.0",
    "gn:asciiname":"Hunsepur",
    "gn:country_code":"IN",
    "gn:dem":98,
    "gn:feature_class":"P",
    "gn:feature_code":"PPL",
    "gn:name":"H\u016bnsepur",
    "gn:population":0,
    "gn:timezone":"Asia/Kolkata",
    "iso:country":"IN",
    "ks:ks_alt_nam":"H\u016bnsepur",
    "ks:ks_name":"Hunsepur",
    "ks:ks_type":"VILLAGE",
    "name:eng_x_preferred":[
        "Hunsepur"
    ],
    "name:eng_x_variant":[
        "H\u016bnsepur"
    ],
    "wof:name":"Hunsepur",
    "wof:placetype":"locality"
},
  "geometry": {"coordinates":[82.577775,26.574892],"type":"Point"}
}