{
  "type": "Feature",
  "properties": {
    "iso:country":"IN",
    "ks:ks_name":"Tero Ghar Para",
    "ks:ks_pop":259,
    "ks:ks_type":"HABITATION",
    "ks:ks_uagg_main":0,
    "name:eng_x_preferred":[
        "Tero Ghar Para"
    ],
    "wof:name":"Tero Ghar Para",
    "wof:placetype":"neighbourhood",
    "wof:population":259
},
  "geometry": {"coordinates":[91.99876,24.089957],"type":"Point"}
}