{
  "type": "Feature",
  "properties": {
    "iso:country":"IN",
    "ks:ks_name":"Doddasulikere",
    "ks:ks_pop":135,
    "ks:ks_type":"VILLAGE",
    "name:eng_x_preferred":[
        "Doddasulikere"
    ],
    "wof:name":"Doddasulikere",
    "wof:placetype":"locality",
    "wof:population":135
},
  "geometry": {"coordinates":[77.317177,12.860952],"type":"Point"}
}