{
  "type": "Feature",
  "properties": {
    "iso:country":"IN",
    "ks:ks_name":"Babhandih Wajirganj",
    "ks:ks_pop":2510,
    "ks:ks_type":"VILLAGE",
    "ks:ks_uagg_main":0,
    "name:eng_x_preferred":[
        "Babhandih Wajirganj"
    ],
    "wof:name":"Babhandih Wajirganj",
    "wof:placetype":"neighbourhood",
    "wof:population":2510
},
  "geometry": {"coordinates":[85.23536,24.800964],"type":"Point"}
}