{
  "type": "Feature",
  "properties": {
    "gn:admin1_code":"36.0",
    "gn:admin2_code":"150.0",
    "gn:asciiname":"Udhranpur Ilaka Budhauli",
    "gn:country_code":"IN",
    "gn:dem":167,
    "gn:feature_class":"P",
    "gn:feature_code":"PPL",
    "gn:name":"Udhranpur Il\u0101ka Budhauli",
    "gn:population":0,
    "gn:timezone":"Asia/Kolkata",
    "iso:country":"IN",
    "wof:name":"Udhranpur Ilaka Budhauli",
    "wof:placetype":"locality"
},
  "geometry": {"coordinates":[79.65615,28.2589],"type":"Point"}
}