{
  "type": "Feature",
  "properties": {
    "iso:country":"IN",
    "ks:ks_name":"B Mahulapada",
    "ks:ks_pop":39,
    "ks:ks_type":"VILLAGE",
    "name:eng_x_preferred":[
        "B Mahulapada"
    ],
    "wof:name":"B Mahulapada",
    "wof:placetype":"locality",
    "wof:population":39
},
  "geometry": {"coordinates":[84.37540300000001,19.1649],"type":"Point"}
}