{
  "type": "Feature",
  "properties": {
    "gn:admin1_code":"37",
    "gn:admin2_code":"407.0",
    "gn:asciiname":"Jogipur",
    "gn:country_code":"IN",
    "gn:dem":315,
    "gn:feature_class":"P",
    "gn:feature_code":"PPL",
    "gn:name":"Jog\u012bpur",
    "gn:population":0,
    "gn:timezone":"Asia/Kolkata",
    "iso:country":"IN",
    "ks:ks_alt_nam":"Jog\u012bpur",
    "ks:ks_name":"Jogipur",
    "ks:ks_pop":287,
    "ks:ks_type":"VILLAGE",
    "ks:ks_uagg_main":0,
    "name:eng_x_preferred":[
        "Jogipur"
    ],
    "name:eng_x_variant":[
        "Jog\u012bpur"
    ],
    "wof:name":"Jogipur",
    "wof:placetype":"neighbourhood",
    "wof:population":287
},
  "geometry": {"coordinates":[81.403471,22.035732],"type":"Point"}
}