{
  "type": "Feature",
  "properties": {
    "gn:country":"IN",
    "gn:fcode":"PPL",
    "gn:pop":10536,
    "iso:country":"IN",
    "name:bpy_x_preferred":[
        "\u09ac\u09be\u09b2\u09a6\u09c7\u0993"
    ],
    "name:bul_x_preferred":[
        "\u0411\u0430\u043b\u0434\u0435\u0432"
    ],
    "name:chi_x_preferred":[
        "\u5df4\u5c14\u5fb7\u5965"
    ],
    "name:dut_x_preferred":[
        "Baldeo"
    ],
    "name:eng_x_preferred":[
        "Baldeo"
    ],
    "name:fre_x_preferred":[
        "Baldeo"
    ],
    "name:hin_x_preferred":[
        "\u092c\u0932\u094d\u0926\u0947\u0935"
    ],
    "name:ita_x_preferred":[
        "Baldeo"
    ],
    "name:may_x_preferred":[
        "Baldeo"
    ],
    "name:mlg_x_preferred":[
        "Baldeo"
    ],
    "name:nan_x_preferred":[
        "Baldeo"
    ],
    "name:new_x_preferred":[
        "\u092c\u0932\u0926\u0947\u0935"
    ],
    "name:pol_x_preferred":[
        "Baldeo"
    ],
    "name:por_x_preferred":[
        "Baldeo"
    ],
    "name:rus_x_preferred":[
        "\u0411\u0430\u043b\u0434\u0435\u043e"
    ],
    "name:swe_x_preferred":[
        "Baldev"
    ],
    "name:unk_x_variant":[
        "Baldeo"
    ],
    "name:urd_x_preferred":[
        "\u0628\u0627\u0644 \u062f\u06cc\u0648"
    ],
    "name:vie_x_preferred":[
        "Baldeo"
    ],
    "qs:name":"Baldev",
    "qs:photos_9r":0,
    "qs:photos_sr":0,
    "qs:pop_sr":"6",
    "wof:name":"Baldev",
    "wof:placetype":"locality",
    "wof:population":10536
},
  "geometry": {"coordinates":[77.82382,27.40804],"type":"Point"}
}