{
  "type": "Feature",
  "properties": {
    "gn:admin1_code":"21.0",
    "gn:admin2_code":"388",
    "gn:asciiname":"Kanaipur",
    "gn:country_code":"IN",
    "gn:dem":15,
    "gn:feature_class":"P",
    "gn:feature_code":"PPL",
    "gn:name":"K\u0101n\u0101ipur",
    "gn:population":0,
    "gn:timezone":"Asia/Kolkata",
    "iso:country":"IN",
    "name:und_x_variant":[
        "K\u0101n\u0101ipur"
    ],
    "wof:name":"Kanaipur",
    "wof:placetype":"locality"
},
  "geometry": {"coordinates":[85.13333,19.65],"type":"Point"}
}