{
  "type": "Feature",
  "properties": {
    "iso:country":"IN",
    "ks:ks_name":"Tapanga",
    "ks:ks_pop":418,
    "ks:ks_type":"VILLAGE",
    "name:eng_x_preferred":[
        "Tapanga"
    ],
    "wof:name":"Tapanga",
    "wof:placetype":"locality",
    "wof:population":418
},
  "geometry": {"coordinates":[84.260109,18.932591],"type":"Point"}
}