{
  "type": "Feature",
  "properties": {
    "iso:country":"IN",
    "ks:ks_name":"Kherbahari",
    "ks:ks_pop":114,
    "ks:ks_type":"HABITATION",
    "name:eng_x_preferred":[
        "Kherbahari"
    ],
    "wof:name":"Kherbahari",
    "wof:placetype":"locality",
    "wof:population":114
},
  "geometry": {"coordinates":[82.604468,22.570181],"type":"Point"}
}