{
  "type": "Feature",
  "properties": {
    "gn:admin1_code":"35",
    "gn:admin2_code":"454.0",
    "gn:asciiname":"Khursipar",
    "gn:country_code":"IN",
    "gn:dem":476,
    "gn:feature_class":"P",
    "gn:feature_code":"PPL",
    "gn:name":"Khurs\u012bp\u0101r",
    "gn:population":0,
    "gn:timezone":"Asia/Kolkata",
    "iso:country":"IN",
    "wof:name":"Khursipar",
    "wof:placetype":"locality"
},
  "geometry": {"coordinates":[79.96835,22.55467],"type":"Point"}
}