{
  "type": "Feature",
  "properties": {
    "gn:admin1_code":"24.0",
    "gn:admin2_code":"127.0",
    "gn:asciiname":"Haripura",
    "gn:country_code":"IN",
    "gn:dem":257,
    "gn:feature_class":"P",
    "gn:feature_code":"PPL",
    "gn:name":"Har\u012bpura",
    "gn:population":0,
    "gn:timezone":"Asia/Kolkata",
    "iso:country":"IN",
    "name:guj_x_preferred":[
        "\u0ab9\u0ab0\u0ac0\u0aaa\u0ac1\u0ab0\u0abe"
    ],
    "wof:name":"Haripura",
    "wof:placetype":"locality"
},
  "geometry": {"coordinates":[76.16996999999998,25.07133],"type":"Point"}
}