{
  "type": "Feature",
  "properties": {
    "iso:country":"IN",
    "ks:ks_name":"Mukhawa",
    "ks:ks_pop":1001,
    "ks:ks_type":"VILLAGE",
    "name:eng_x_preferred":[
        "Mukhawa"
    ],
    "qs:name":"Mukhawa",
    "qs:name_adm0":"India",
    "qs:name_adm1":"Uttarakhand",
    "qs:photos":24,
    "qs:photos_1k":5,
    "qs:photos_9k":1,
    "qs:photos_9r":1,
    "qs:photos_all":24,
    "qs:photos_sr":1,
    "qs:placetype":"Town",
    "qs:pop_sr":"0",
    "wof:name":"Mukhawa",
    "wof:placetype":"locality",
    "wof:population":1001
},
  "geometry": {"coordinates":[78.780311,31.04457],"type":"Point"}
}