{
  "type": "Feature",
  "properties": {
    "iso:country":"IN",
    "qs:name":"Mukhawa",
    "qs:name_adm0":"India",
    "qs:name_adm1":"Uttarakhand",
    "qs:photos":24,
    "qs:photos_1k":5,
    "qs:photos_9k":1,
    "qs:photos_9r":1,
    "qs:photos_all":24,
    "qs:photos_sr":1,
    "qs:placetype":"Town",
    "qs:pop_sr":"0",
    "wof:name":"Mukhawa",
    "wof:placetype":"locality"
},
  "geometry": {"coordinates":[78.772659,31.044845],"type":"Point"}
}