{
  "type": "Feature",
  "properties": {
    "gn:admin1_code":"35.0",
    "gn:admin2_code":"455.0",
    "gn:asciiname":"Palaspani",
    "gn:country_code":"IN",
    "gn:dem":484,
    "gn:feature_class":"P",
    "gn:feature_code":"PPL",
    "gn:name":"Pal\u0101sp\u0101ni",
    "gn:population":0,
    "gn:timezone":"Asia/Kolkata",
    "iso:country":"IN",
    "name:und_x_variant":[
        "Pal\u0101sp\u0101ni",
        "Paraspani"
    ],
    "wof:name":"Palaspani",
    "wof:placetype":"locality"
},
  "geometry": {"coordinates":[79.19972,21.72224],"type":"Point"}
}