{
  "type": "Feature",
  "properties": {
    "iso:country":"IN",
    "ks:ks_name":"Guddekeri",
    "ks:ks_pop":66,
    "ks:ks_type":"HABITATION",
    "name:eng_x_preferred":[
        "Guddekeri"
    ],
    "wof:name":"Guddekeri",
    "wof:placetype":"locality",
    "wof:population":66
},
  "geometry": {"coordinates":[74.52812299999999,14.437367],"type":"Point"}
}