{
  "type": "Feature",
  "properties": {
    "iso:country":"IN",
    "ks:ks_name":"Barabila",
    "ks:ks_pop":0,
    "ks:ks_type":"VILLAGE",
    "name:eng_x_preferred":[
        "Barabila"
    ],
    "wof:name":"Barabila",
    "wof:placetype":"locality",
    "wof:population":0
},
  "geometry": {"coordinates":[87.517236,22.795389],"type":"Point"}
}