{
  "type": "Feature",
  "properties": {
    "iso:country":"IN",
    "ks:ks_name":"Balichapari",
    "ks:ks_pop":1760,
    "ks:ks_type":"VILLAGE",
    "ks:ks_uagg_main":0,
    "name:eng_x_preferred":[
        "Balichapari"
    ],
    "wof:name":"Balichapari",
    "wof:placetype":"locality",
    "wof:population":1760
},
  "geometry": {"coordinates":[92.814145,26.629039],"type":"Point"}
}