{
  "type": "Feature",
  "properties": {
    "iso:country":"IN",
    "ks:ks_name":"Nadumogru",
    "ks:ks_pop":194,
    "ks:ks_type":"HABITATION",
    "name:eng_x_preferred":[
        "Nadumogru"
    ],
    "wof:name":"Nadumogru",
    "wof:placetype":"locality",
    "wof:population":194
},
  "geometry": {"coordinates":[75.162015,12.858596],"type":"Point"}
}