{
  "type": "Feature",
  "properties": {
    "iso:country":"IN",
    "ks:ks_name":"Malpewadi",
    "ks:ks_pop":650,
    "ks:ks_type":"VILLAGE",
    "name:eng_x_preferred":[
        "Malpewadi"
    ],
    "wof:name":"Malpewadi",
    "wof:placetype":"locality",
    "wof:population":650
},
  "geometry": {"coordinates":[73.531875,16.515488],"type":"Point"}
}