{
  "type": "Feature",
  "properties": {
    "iso:country":"IN",
    "ks:ks_name":"Sukhwasi Ki Thar",
    "ks:ks_pop":50,
    "ks:ks_type":"HABITATION",
    "name:eng_x_preferred":[
        "Sukhwasi Ki Thar"
    ],
    "wof:name":"Sukhwasi Ki Thar",
    "wof:placetype":"locality",
    "wof:population":50
},
  "geometry": {"coordinates":[78.424502,26.853213],"type":"Point"}
}