{
  "type": "Feature",
  "properties": {
    "iso:country":"IN",
    "ks:ks_name":"Baheriya Ryt. No. 1",
    "ks:ks_pop":23,
    "ks:ks_type":"VILLAGE",
    "name:eng_x_preferred":[
        "Baheriya Ryt. No. 1"
    ],
    "wof:name":"Baheriya Ryt. No. 1",
    "wof:placetype":"locality",
    "wof:population":23
},
  "geometry": {"coordinates":[79.433511,23.350274],"type":"Point"}
}