{
  "type": "Feature",
  "properties": {
    "gn:admin1_code":"23.0",
    "gn:admin2_code":"053",
    "gn:asciiname":"Rurki Kalan",
    "gn:country_code":"IN",
    "gn:dem":257,
    "gn:feature_class":"P",
    "gn:feature_code":"PPL",
    "gn:name":"R\u016brki Kal\u0101n",
    "gn:population":0,
    "gn:timezone":"Asia/Kolkata",
    "iso:country":"IN",
    "wof:name":"Rurki Kalan",
    "wof:placetype":"locality"
},
  "geometry": {"coordinates":[76.01505999999998,30.5642],"type":"Point"}
}