{
  "type": "Feature",
  "properties": {
    "iso:country":"IN",
    "ks:ks_name":"Hibhanapur Ramauli",
    "ks:ks_pop":584,
    "ks:ks_type":"HABITATION",
    "name:eng_x_preferred":[
        "Hibhanapur Ramauli"
    ],
    "wof:name":"Hibhanapur Ramauli",
    "wof:placetype":"locality",
    "wof:population":584
},
  "geometry": {"coordinates":[83.220657,25.416703],"type":"Point"}
}