{
  "type": "Feature",
  "properties": {
    "iso:country":"IN",
    "ks:ks_alt_nam":"Trib\u0101npur",
    "ks:ks_name":"Tribanpur",
    "ks:ks_pop":1318,
    "ks:ks_type":"VILLAGE",
    "name:eng_x_preferred":[
        "Tribanpur"
    ],
    "name:eng_x_variant":[
        "Trib\u0101npur"
    ],
    "wof:name":"Tribanpur",
    "wof:placetype":"locality",
    "wof:population":1318
},
  "geometry": {"coordinates":[84.242052,20.982275],"type":"Point"}
}