{
  "type": "Feature",
  "properties": {
    "gn:admin1_code":"35.0",
    "gn:admin2_code":"435",
    "gn:asciiname":"Bercha",
    "gn:country_code":"IN",
    "gn:dem":469,
    "gn:feature_class":"P",
    "gn:feature_code":"PPL",
    "gn:name":"Bercha",
    "gn:population":0,
    "gn:timezone":"Asia/Kolkata",
    "iso:country":"IN",
    "name:spa_x_preferred":[
        "Bercha"
    ],
    "name:und_x_variant":[
        "Berchha"
    ],
    "wof:name":"Bercha",
    "wof:placetype":"locality"
},
  "geometry": {"coordinates":[75.38938,23.54469],"type":"Point"}
}