{
  "type": "Feature",
  "properties": {
    "iso:country":"IN",
    "ks:ks_alt_nam":"H.Lingapalem",
    "ks:ks_name":"H.lingapalem",
    "ks:ks_pop":312,
    "ks:ks_type":"HABITATION",
    "name:eng_x_preferred":[
        "H.lingapalem"
    ],
    "wof:name":"H.lingapalem",
    "wof:placetype":"locality",
    "wof:population":312
},
  "geometry": {"coordinates":[81.23926899999999,16.883803],"type":"Point"}
}