{
  "type": "Feature",
  "properties": {
    "gn:admin1_code":"36.0",
    "gn:admin2_code":"179.0",
    "gn:asciiname":"Majhgawan",
    "gn:country_code":"IN",
    "gn:dem":106,
    "gn:feature_class":"P",
    "gn:feature_code":"PPL",
    "gn:name":"Majhgaw\u0101n",
    "gn:population":0,
    "gn:timezone":"Asia/Kolkata",
    "iso:country":"IN",
    "name:hin_x_preferred":[
        "\u092e\u091d\u0917\u0935\u093e\u0902"
    ],
    "wof:name":"Majhgawan",
    "wof:placetype":"neighbourhood"
},
  "geometry": {"coordinates":[81.84775999999999,26.35057],"type":"Point"}
}