{
  "type": "Feature",
  "properties": {
    "iso:country":"IN",
    "ks:ks_name":"N. Jawahar",
    "ks:ks_pop":55,
    "ks:ks_type":"HABITATION",
    "name:eng_x_preferred":[
        "N. Jawahar"
    ],
    "wof:name":"N. Jawahar",
    "wof:placetype":"locality",
    "wof:population":55
},
  "geometry": {"coordinates":[79.280807,27.187783],"type":"Point"}
}