{
  "type": "Feature",
  "properties": {
    "iso:country":"IN",
    "ks:ks_name":"Padmapur",
    "ks:ks_pop":295,
    "ks:ks_type":"VILLAGE",
    "name:eng_x_preferred":[
        "Padmapur"
    ],
    "wof:name":"Padmapur",
    "wof:placetype":"locality",
    "wof:population":295
},
  "geometry": {"coordinates":[85.58019400000001,22.790973],"type":"Point"}
}