{
  "type": "Feature",
  "properties": {
    "iso:country":"IN",
    "ks:ks_name":"Sarasom",
    "ks:ks_pop":562,
    "ks:ks_type":"HABITATION",
    "name:eng_x_preferred":[
        "Sarasom"
    ],
    "wof:name":"Sarasom",
    "wof:placetype":"locality",
    "wof:population":562
},
  "geometry": {"coordinates":[85.41133499999999,23.159044],"type":"Point"}
}