{
  "type": "Feature",
  "properties": {
    "iso:country":"IN",
    "ks:ks_name":"Puthu Karuvalli",
    "ks:ks_pop":440,
    "ks:ks_type":"HABITATION",
    "ks:ks_uagg_main":0,
    "name:eng_x_preferred":[
        "Puthu Karuvalli"
    ],
    "wof:name":"Puthu Karuvalli",
    "wof:placetype":"neighbourhood",
    "wof:population":440
},
  "geometry": {"coordinates":[78.03210199999999,11.843893],"type":"Point"}
}