{
  "type": "Feature",
  "properties": {
    "iso:country":"IN",
    "ks:ks_name":"Jawahapura",
    "ks:ks_pop":50,
    "ks:ks_type":"HABITATION",
    "name:eng_x_preferred":[
        "Jawahapura"
    ],
    "wof:name":"Jawahapura",
    "wof:placetype":"locality",
    "wof:population":50
},
  "geometry": {"coordinates":[78.22743199999999,26.912555],"type":"Point"}
}