{
  "type": "Feature",
  "properties": {
    "iso:country":"IN",
    "ks:ks_name":"Sileisinga",
    "ks:ks_pop":103,
    "ks:ks_type":"VILLAGE",
    "name:eng_x_preferred":[
        "Sileisinga"
    ],
    "wof:name":"Sileisinga",
    "wof:placetype":"locality",
    "wof:population":103
},
  "geometry": {"coordinates":[84.435534,19.005005],"type":"Point"}
}