{
  "type": "Feature",
  "properties": {
    "gn:admin1_code":"34.0",
    "gn:admin2_code":"235.0",
    "gn:asciiname":"Amarpur",
    "gn:country_code":"IN",
    "gn:dem":102,
    "gn:feature_class":"P",
    "gn:feature_code":"PPL",
    "gn:name":"Amarpur",
    "gn:population":0,
    "gn:timezone":"Asia/Kolkata",
    "iso:country":"IN",
    "ks:ks_name":"Amarpur",
    "ks:ks_pop":702,
    "ks:ks_type":"HABITATION",
    "ks:ks_uagg_main":0,
    "name:ceb_x_preferred":[
        "Amarpur"
    ],
    "name:eng_x_preferred":[
        "Amarpur"
    ],
    "name:fra_x_preferred":[
        "Amarpur"
    ],
    "name:new_x_preferred":[
        "\u0905\u092e\u0930\u092a\u0941\u0930 \u0917\u093e\u0935\u093f\u0938"
    ],
    "name:nld_x_preferred":[
        "Amarpur"
    ],
    "name:pol_x_preferred":[
        "Amarpur"
    ],
    "name:swe_x_preferred":[
        "Amarpur"
    ],
    "wof:name":"Amarpur",
    "wof:placetype":"neighbourhood",
    "wof:population":702
},
  "geometry": {"coordinates":[84.35495,24.861126],"type":"Point"}
}