{
  "type": "Feature",
  "properties": {
    "iso:country":"IN",
    "ks:ks_name":"Thakurpatana",
    "ks:ks_pop":1221,
    "ks:ks_type":"VILLAGE",
    "ks:ks_uagg_main":0,
    "name:eng_x_preferred":[
        "Thakurpatana"
    ],
    "wof:name":"Thakurpatana",
    "wof:placetype":"neighbourhood",
    "wof:population":1221
},
  "geometry": {"coordinates":[86.141774,20.937955],"type":"Point"}
}