{
  "type": "Feature",
  "properties": {
    "gn:admin1_code":"25.0",
    "gn:admin2_code":"619.0",
    "gn:asciiname":"Govindanattam",
    "gn:country_code":"IN",
    "gn:dem":17,
    "gn:feature_class":"P",
    "gn:feature_code":"PPL",
    "gn:name":"Govindanattam",
    "gn:population":0,
    "gn:timezone":"Asia/Kolkata",
    "iso:country":"IN",
    "ks:ks_name":"Kovindanatham",
    "ks:ks_pop":503,
    "ks:ks_type":"HABITATION",
    "ks:ks_uagg_main":0,
    "name:eng_x_preferred":[
        "Kovindanatham"
    ],
    "wof:name":"Kovindanatham",
    "wof:placetype":"neighbourhood",
    "wof:population":503
},
  "geometry": {"coordinates":[79.469448,10.539569],"type":"Point"}
}