{
  "type": "Feature",
  "properties": {
    "gn:admin1_code":"11",
    "gn:admin2_code":"23.0",
    "gn:asciiname":"Ranch",
    "gn:country_code":"IN",
    "gn:dem":2188,
    "gn:feature_class":"P",
    "gn:feature_code":"PPL",
    "gn:name":"Ranch",
    "gn:population":0,
    "gn:timezone":"Asia/Kolkata",
    "iso:country":"IN",
    "name:ara_x_preferred":[
        "\u0645\u0631\u0628\u0649 \u0645\u0648\u0627\u0634\u064a"
    ],
    "name:bul_x_preferred":[
        "\u0420\u0430\u043d\u0447\u043e"
    ],
    "name:cat_x_preferred":[
        "Ranxo"
    ],
    "name:ces_x_preferred":[
        "Ran\u010d"
    ],
    "name:dan_x_preferred":[
        "Ranch"
    ],
    "name:deu_x_preferred":[
        "Ranching"
    ],
    "name:epo_x_preferred":[
        "Ran\u0109o"
    ],
    "name:eus_x_preferred":[
        "Arrantxo"
    ],
    "name:fas_x_preferred":[
        "\u0645\u0632\u0631\u0639\u0647"
    ],
    "name:fra_x_preferred":[
        "Ranch"
    ],
    "name:gle_x_preferred":[
        "Rainse"
    ],
    "name:grn_x_preferred":[
        "Rr\u00e1ncho"
    ],
    "name:heb_x_preferred":[
        "\u05d7\u05d5\u05d5\u05d4 \u05d7\u05e7\u05dc\u05d0\u05d9\u05ea"
    ],
    "name:ita_x_preferred":[
        "Ranch"
    ],
    "name:nld_x_preferred":[
        "Ranch"
    ],
    "name:pol_x_preferred":[
        "Ranczo"
    ],
    "name:por_x_preferred":[
        "Rancho"
    ],
    "name:rus_x_preferred":[
        "\u0420\u0430\u043d\u0447\u043e"
    ],
    "name:sco_x_preferred":[
        "Ranch"
    ],
    "name:slk_x_preferred":[
        "Ran\u010d"
    ],
    "name:spa_x_preferred":[
        "Rancho"
    ],
    "name:swa_x_preferred":[
        "Ranchi"
    ],
    "name:swe_x_preferred":[
        "Ranch"
    ],
    "name:ukr_x_preferred":[
        "\u0420\u0430\u043d\u0447\u043e"
    ],
    "wof:name":"Ranch",
    "wof:placetype":"locality"
},
  "geometry": {"coordinates":[76.09449000000002,32.39307],"type":"Point"}
}