{
  "type": "Feature",
  "properties": {
    "iso:country":"IN",
    "ks:ks_name":"Gondarakeri",
    "ks:ks_pop":85,
    "ks:ks_type":"HABITATION",
    "name:eng_x_preferred":[
        "Gondarakeri"
    ],
    "wof:name":"Gondarakeri",
    "wof:placetype":"locality",
    "wof:population":85
},
  "geometry": {"coordinates":[74.637641,14.03942],"type":"Point"}
}