{
  "type": "Feature",
  "properties": {
    "gn:admin1_code":"36.0",
    "gn:admin2_code":"193.0",
    "gn:asciiname":"Hansapur",
    "gn:country_code":"IN",
    "gn:dem":68,
    "gn:feature_class":"P",
    "gn:feature_code":"PPL",
    "gn:name":"Hansapur",
    "gn:population":0,
    "gn:timezone":"Asia/Kolkata",
    "iso:country":"IN",
    "name:fra_x_preferred":[
        "Hansapur"
    ],
    "name:new_x_preferred":[
        "\u0939\u0902\u0936\u092a\u0941\u0930"
    ],
    "name:pol_x_preferred":[
        "Hansapur"
    ],
    "wof:name":"Hansapur",
    "wof:placetype":"locality"
},
  "geometry": {"coordinates":[84.00438,25.72428],"type":"Point"}
}