{
  "type": "Feature",
  "properties": {
    "iso:country":"IN",
    "ks:ks_name":"Semaliya Khurd",
    "ks:ks_pop":590,
    "ks:ks_type":"VILLAGE",
    "name:eng_x_preferred":[
        "Semaliya Khurd"
    ],
    "wof:name":"Semaliya Khurd",
    "wof:placetype":"locality",
    "wof:population":590
},
  "geometry": {"coordinates":[74.682041,23.896575],"type":"Point"}
}