{
  "type": "Feature",
  "properties": {
    "gn:admin1_code":"19.0",
    "gn:admin2_code":"567.0",
    "gn:asciiname":"Dagge Basapuram",
    "gn:country_code":"IN",
    "gn:dem":649,
    "gn:feature_class":"P",
    "gn:feature_code":"PPL",
    "gn:name":"Dagge Bas\u0101puram",
    "gn:population":0,
    "gn:timezone":"Asia/Kolkata",
    "iso:country":"IN",
    "wof:name":"Dagge Basapuram",
    "wof:placetype":"locality"
},
  "geometry": {"coordinates":[76.05713,14.60647],"type":"Point"}
}