{
  "type": "Feature",
  "properties": {
    "iso:country":"IN",
    "ks:ks_name":"Chokapara Pt.iii",
    "ks:ks_pop":800,
    "ks:ks_type":"VILLAGE",
    "name:eng_x_preferred":[
        "Chokapara Pt.iii"
    ],
    "wof:name":"Chokapara Pt.iii",
    "wof:placetype":"locality",
    "wof:population":800
},
  "geometry": {"coordinates":[90.22424599999999,26.282212],"type":"Point"}
}