{
  "type": "Feature",
  "properties": {
    "iso:country":"IN",
    "ks:ks_name":"Marjadpur",
    "ks:ks_type":"VILLAGE",
    "name:eng_x_preferred":[
        "Marjadpur"
    ],
    "wof:name":"Marjadpur",
    "wof:placetype":"locality"
},
  "geometry": {"coordinates":[86.773415,23.6513],"type":"Point"}
}