{
  "type": "Feature",
  "properties": {
    "gn:admin1_code":"9.0",
    "gn:admin2_code":"486.0",
    "gn:asciiname":"Tawa",
    "gn:country_code":"IN",
    "gn:dem":179,
    "gn:feature_class":"P",
    "gn:feature_code":"PPL",
    "gn:name":"T\u0101wa",
    "gn:population":0,
    "gn:timezone":"Asia/Kolkata",
    "iso:country":"IN",
    "name:ceb_x_preferred":[
        "Tawa"
    ],
    "name:deu_x_preferred":[
        "Tawa"
    ],
    "name:ita_x_preferred":[
        "Tawa"
    ],
    "name:spa_x_preferred":[
        "Tawa"
    ],
    "name:swe_x_preferred":[
        "Tawa"
    ],
    "name:vie_x_preferred":[
        "Tawa"
    ],
    "wof:name":"Tawa",
    "wof:placetype":"neighbourhood"
},
  "geometry": {"coordinates":[74.06225000000001,22.18785],"type":"Point"}
}