{
  "type": "Feature",
  "properties": {
    "gn:admin1_code":"34",
    "gn:admin2_code":"234.0",
    "gn:asciiname":"Khaira",
    "gn:country_code":"IN",
    "gn:dem":109,
    "gn:feature_class":"P",
    "gn:feature_code":"PPL",
    "gn:name":"Khaira",
    "gn:population":0,
    "gn:timezone":"Asia/Kolkata",
    "iso:country":"IN",
    "ks:ks_name":"Khaira",
    "ks:ks_type":"VILLAGE",
    "ks:ks_uagg_main":0,
    "name:eng_x_preferred":[
        "Khaira"
    ],
    "name:hin_x_preferred":[
        "\u0916\u0948\u0930\u093e"
    ],
    "name:new_x_preferred":[
        "\u0916\u0948\u0930\u093e"
    ],
    "wof:name":"Khaira",
    "wof:placetype":"neighbourhood"
},
  "geometry": {"coordinates":[83.996054,24.941692],"type":"Point"}
}