{
  "type": "Feature",
  "properties": {
    "iso:country":"IN",
    "ks:ks_name":"Kankaliya",
    "ks:ks_pop":849,
    "ks:ks_type":"VILLAGE",
    "name:eng_x_preferred":[
        "Kankaliya"
    ],
    "wof:name":"Kankaliya",
    "wof:placetype":"locality",
    "wof:population":849
},
  "geometry": {"coordinates":[73.545851,22.99637],"type":"Point"}
}