{
  "type": "Feature",
  "properties": {
    "iso:country":"IN",
    "ks:ks_name":"Talla Paya",
    "ks:ks_pop":379,
    "ks:ks_type":"VILLAGE",
    "name:eng_x_preferred":[
        "Talla Paya"
    ],
    "wof:name":"Talla Paya",
    "wof:placetype":"locality",
    "wof:population":379
},
  "geometry": {"coordinates":[79.61537199999999,29.987999],"type":"Point"}
}