{
  "type": "Feature",
  "properties": {
    "gn:admin1_code":"34.0",
    "gn:admin2_code":"230.0",
    "gn:asciiname":"Kansopur",
    "gn:country_code":"IN",
    "gn:dem":75,
    "gn:feature_class":"P",
    "gn:feature_code":"PPL",
    "gn:name":"Kansopur",
    "gn:population":0,
    "gn:timezone":"Asia/Kolkata",
    "iso:country":"IN",
    "wof:name":"Kansopur",
    "wof:placetype":"locality"
},
  "geometry": {"coordinates":[84.73175000000001,25.28003],"type":"Point"}
}