{
  "type": "Feature",
  "properties": {
    "iso:country":"IN",
    "ks:ks_name":"Dinkarpura",
    "ks:ks_pop":44,
    "ks:ks_type":"VILLAGE",
    "name:eng_x_preferred":[
        "Dinkarpura"
    ],
    "wof:name":"Dinkarpura",
    "wof:placetype":"locality",
    "wof:population":44
},
  "geometry": {"coordinates":[77.180914,22.209813],"type":"Point"}
}