{
  "type": "Feature",
  "properties": {
    "gn:admin1_code":"38.0",
    "gn:admin2_code":"360.0",
    "gn:asciiname":"Guri",
    "gn:country_code":"IN",
    "gn:dem":457,
    "gn:feature_class":"P",
    "gn:feature_code":"PPL",
    "gn:name":"Guri",
    "gn:population":0,
    "gn:timezone":"Asia/Kolkata",
    "iso:country":"IN",
    "ks:ks_name":"Guri",
    "ks:ks_pop":279,
    "ks:ks_type":"VILLAGE",
    "name:ara_x_preferred":[
        "\u063a\u0648\u0631\u064a"
    ],
    "name:ces_x_preferred":[
        "Kuri"
    ],
    "name:deu_x_preferred":[
        "Guri"
    ],
    "name:eng_x_preferred":[
        "Guri"
    ],
    "name:epo_x_preferred":[
        "Kuri"
    ],
    "name:fas_x_preferred":[
        "\u06af\u0648\u0631\u06cc"
    ],
    "name:fin_x_preferred":[
        "Guri"
    ],
    "name:fra_x_preferred":[
        "Guri"
    ],
    "name:hak_x_preferred":[
        "Guri S\u1e73"
    ],
    "name:ind_x_preferred":[
        "Guri"
    ],
    "name:ita_x_preferred":[
        "Guri"
    ],
    "name:jav_x_preferred":[
        "Guri"
    ],
    "name:jpn_x_preferred":[
        "\u4e5d\u91cc\u5e02"
    ],
    "name:kor_x_preferred":[
        "\uad6c\ub9ac\uc2dc"
    ],
    "name:mon_x_preferred":[
        "\u041a\u04af\u0440\u0438"
    ],
    "name:nld_x_preferred":[
        "Guri"
    ],
    "name:nor_x_preferred":[
        "Guri"
    ],
    "name:pol_x_preferred":[
        "Guri"
    ],
    "name:por_x_preferred":[
        "Guri"
    ],
    "name:rus_x_preferred":[
        "\u041a\u0443\u0440\u0438"
    ],
    "name:sco_x_preferred":[
        "Guri"
    ],
    "name:spa_x_preferred":[
        "Guri"
    ],
    "name:swe_x_preferred":[
        "Guri"
    ],
    "name:tgl_x_preferred":[
        "Guri"
    ],
    "name:tha_x_preferred":[
        "\u0e04\u0e39\u0e23\u0e35"
    ],
    "name:tur_x_preferred":[
        "Guri"
    ],
    "name:urd_x_preferred":[
        "\u06af\u0648\u0631\u06cc"
    ],
    "name:vie_x_preferred":[
        "Guri"
    ],
    "name:war_x_preferred":[
        "Guri"
    ],
    "name:zho_x_preferred":[
        "\u4e5d\u91cc\u5e02"
    ],
    "wof:name":"Guri",
    "wof:placetype":"locality",
    "wof:population":279
},
  "geometry": {"coordinates":[85.199291,24.182085],"type":"Point"}
}