{
  "type": "Feature",
  "properties": {
    "iso:country":"IN",
    "ks:ks_name":"Puthu Nagar",
    "ks:ks_pop":325,
    "ks:ks_type":"HABITATION",
    "name:eng_x_preferred":[
        "Puthu Nagar"
    ],
    "wof:name":"Puthu Nagar",
    "wof:placetype":"locality",
    "wof:population":325
},
  "geometry": {"coordinates":[77.405154,8.372326],"type":"Point"}
}