{
  "type": "Feature",
  "properties": {
    "gn:admin1_code":"25.0",
    "gn:admin2_code":"630.0",
    "gn:asciiname":"Ariyakavundanhalli",
    "gn:country_code":"IN",
    "gn:dem":477,
    "gn:feature_class":"P",
    "gn:feature_code":"PPL",
    "gn:name":"Ariy\u0101kavundanhalli",
    "gn:population":0,
    "gn:timezone":"Asia/Kolkata",
    "iso:country":"IN",
    "wof:name":"Ariyakavundanhalli",
    "wof:placetype":"locality"
},
  "geometry": {"coordinates":[78.13993000000001,12.08124],"type":"Point"}
}