{
  "type": "Feature",
  "properties": {
    "iso:country":"IN",
    "ks:ks_name":"Paschim Para",
    "ks:ks_pop":576,
    "ks:ks_type":"HABITATION",
    "name:eng_x_preferred":[
        "Paschim Para"
    ],
    "wof:name":"Paschim Para",
    "wof:placetype":"locality",
    "wof:population":576
},
  "geometry": {"coordinates":[89.217933,26.213712],"type":"Point"}
}