{
  "type": "Feature",
  "properties": {
    "iso:country":"IN",
    "ks:ks_name":"Kolapakkam",
    "ks:ks_pop":750,
    "ks:ks_type":"VILLAGE",
    "ks:ks_uagg_main":0,
    "name:eng_x_preferred":[
        "Kolapakkam"
    ],
    "wof:name":"Kolapakkam",
    "wof:placetype":"locality",
    "wof:population":750
},
  "geometry": {"coordinates":[80.149269,13.010688],"type":"Point"}
}