{
  "type": "Feature",
  "properties": {
    "iso:country":"IN",
    "ks:ks_name":"Durgam",
    "ks:ks_pop":326,
    "ks:ks_type":"HABITATION",
    "name:eng_x_preferred":[
        "Durgam"
    ],
    "wof:name":"Durgam",
    "wof:placetype":"locality",
    "wof:population":326
},
  "geometry": {"coordinates":[78.956305,13.020055],"type":"Point"}
}