{
  "type": "Feature",
  "properties": {
    "gn:admin1_code":"36",
    "gn:admin2_code":"185.0",
    "gn:asciiname":"Mahulani Buzurg",
    "gn:country_code":"IN",
    "gn:dem":96,
    "gn:feature_class":"P",
    "gn:feature_code":"PPL",
    "gn:name":"Mahul\u0101ni Buzurg",
    "gn:population":0,
    "gn:timezone":"Asia/Kolkata",
    "iso:country":"IN",
    "ks:ks_name":"Mahulani Bujurg",
    "ks:ks_pop":513,
    "ks:ks_type":"VILLAGE",
    "ks:ks_uagg_main":0,
    "name:eng_x_preferred":[
        "Mahulani Bujurg"
    ],
    "wof:name":"Mahulani Bujurg",
    "wof:placetype":"neighbourhood",
    "wof:population":513
},
  "geometry": {"coordinates":[82.553647,26.724756],"type":"Point"}
}