{
  "type": "Feature",
  "properties": {
    "iso:country":"IN",
    "ks:ks_name":"Gayespur",
    "ks:ks_pop":320,
    "ks:ks_type":"VILLAGE",
    "name:eng_x_preferred":[
        "Gayespur"
    ],
    "name:hin_x_preferred":[
        "\u0917\u093e\u092f\u0938\u092a\u0941\u0930"
    ],
    "wof:name":"Gayespur",
    "wof:placetype":"locality",
    "wof:population":320
},
  "geometry": {"coordinates":[88.77012000000001,25.392321],"type":"Point"}
}