{
  "type": "Feature",
  "properties": {
    "iso:country":"IN",
    "ks:ks_name":"Hudina",
    "ks:ks_pop":1480,
    "ks:ks_type":"VILLAGE",
    "ks:ks_uagg_main":0,
    "name:eng_x_preferred":[
        "Hudina"
    ],
    "wof:name":"Hudina",
    "wof:placetype":"neighbourhood",
    "wof:population":1480
},
  "geometry": {"coordinates":[76.118151,28.137916],"type":"Point"}
}