{
  "type": "Feature",
  "properties": {
    "iso:country":"IN",
    "ks:ks_name":"Sidheswarwadi",
    "ks:ks_pop":26,
    "ks:ks_type":"HABITATION",
    "name:eng_x_preferred":[
        "Sidheswarwadi"
    ],
    "wof:name":"Sidheswarwadi",
    "wof:placetype":"locality",
    "wof:population":26
},
  "geometry": {"coordinates":[73.61702200000001,16.470852],"type":"Point"}
}