{
  "type": "Feature",
  "properties": {
    "iso:country":"IN",
    "ks:ks_name":"Baben",
    "ks:ks_pop":15610,
    "ks:ks_type":"URBAN",
    "ks:ks_uagg_main":0,
    "name:eng_x_preferred":[
        "Baben"
    ],
    "wof:name":"Baben",
    "wof:placetype":"neighbourhood",
    "wof:population":15610
},
  "geometry": {"coordinates":[73.09344400000001,21.142361],"type":"Point"}
}