{
  "type": "Feature",
  "properties": {
    "iso:country":"IN",
    "ks:ks_alt_nam":"Pipr\u0101dih",
    "ks:ks_name":"Pipradih",
    "ks:ks_pop":256,
    "ks:ks_type":"VILLAGE",
    "name:eng_x_preferred":[
        "Pipradih"
    ],
    "name:eng_x_variant":[
        "Pipr\u0101dih"
    ],
    "wof:name":"Pipradih",
    "wof:placetype":"locality",
    "wof:population":256
},
  "geometry": {"coordinates":[86.149666,24.580858],"type":"Point"}
}