{
  "type": "Feature",
  "properties": {
    "iso:country":"IN",
    "ks:ks_name":"Pokanativaripalle",
    "ks:ks_pop":118,
    "ks:ks_type":"HABITATION",
    "name:eng_x_preferred":[
        "Pokanativaripalle"
    ],
    "wof:name":"Pokanativaripalle",
    "wof:placetype":"locality",
    "wof:population":118
},
  "geometry": {"coordinates":[78.249302,13.765342],"type":"Point"}
}