{
  "type": "Feature",
  "properties": {
    "gn:admin1_code":"40.0",
    "gn:admin2_code":"538",
    "gn:asciiname":"Atmakur",
    "gn:country_code":"IN",
    "gn:dem":327,
    "gn:feature_class":"P",
    "gn:feature_code":"PPL",
    "gn:name":"Atm\u0101k\u016br",
    "gn:population":0,
    "gn:timezone":"Asia/Kolkata",
    "iso:country":"IN",
    "name:und_x_variant":[
        "\u0100tamk\u016br",
        "Amatkur",
        "Atm\u0101k\u016br"
    ],
    "wof:name":"Atmakur",
    "wof:placetype":"locality"
},
  "geometry": {"coordinates":[77.80855,16.33802],"type":"Point"}
}