{
  "type": "Feature",
  "properties": {
    "iso:country":"IN",
    "ks:ks_name":"Kakarat Upadhyay",
    "ks:ks_pop":28,
    "ks:ks_type":"VILLAGE",
    "name:eng_x_preferred":[
        "Kakarat Upadhyay"
    ],
    "wof:name":"Kakarat Upadhyay",
    "wof:placetype":"locality",
    "wof:population":28
},
  "geometry": {"coordinates":[79.884604,29.871145],"type":"Point"}
}