{
  "type": "Feature",
  "properties": {
    "iso:country":"IN",
    "ks:ks_name":"Nadiyani",
    "ks:ks_pop":826,
    "ks:ks_type":"VILLAGE",
    "name:eng_x_preferred":[
        "Nadiyani"
    ],
    "wof:name":"Nadiyani",
    "wof:placetype":"locality",
    "wof:population":826
},
  "geometry": {"coordinates":[81.959397,25.571431],"type":"Point"}
}