{
  "type": "Feature",
  "properties": {
    "gn:admin1_code":"25.0",
    "gn:admin2_code":"620.0",
    "gn:asciiname":"Srirangarajapuram",
    "gn:country_code":"IN",
    "gn:dem":30,
    "gn:feature_class":"P",
    "gn:feature_code":"PPL",
    "gn:name":"Sr\u012brangar\u0101japuram",
    "gn:population":0,
    "gn:timezone":"Asia/Kolkata",
    "iso:country":"IN",
    "wof:name":"Srirangarajapuram",
    "wof:placetype":"locality"
},
  "geometry": {"coordinates":[79.41006999999998,10.93821],"type":"Point"}
}