{
  "type": "Feature",
  "properties": {
    "gn:admin1_code":"25.0",
    "gn:admin2_code":"620.0",
    "gn:asciiname":"Srirangarajapuram",
    "gn:country_code":"IN",
    "gn:dem":30,
    "gn:feature_class":"P",
    "gn:feature_code":"PPL",
    "gn:name":"Sr\u012brangar\u0101japuram",
    "gn:population":0,
    "gn:timezone":"Asia/Kolkata",
    "iso:country":"IN",
    "ks:ks_name":"Srirengarajapuram",
    "ks:ks_pop":614,
    "ks:ks_type":"HABITATION",
    "name:eng_x_preferred":[
        "Srirengarajapuram"
    ],
    "name:eng_x_variant":[
        "Srirangarajapuram"
    ],
    "name:new_x_preferred":[
        "\u0936\u094d\u0930\u0940\u0930\u0902\u0917\u0930\u093e\u091c\u092a\u0941\u0930\u0902 \u092e\u0923\u094d\u0921\u0932"
    ],
    "name:pam_x_preferred":[
        "Srirangarajapuram"
    ],
    "name:tam_x_preferred":[
        "\u0bb8\u0bcd\u0bb0\u0bc0\u0bb0\u0b99\u0bcd\u0b95\u0bb0\u0bbe\u0b9c\u0baa\u0bc1\u0bb0\u0bae\u0bcd"
    ],
    "name:tel_x_preferred":[
        "\u0c36\u0c4d\u0c30\u0c40\u0c30\u0c02\u0c17\u0c30\u0c3e\u0c1c\u0c2a\u0c41\u0c30\u0c02"
    ],
    "name:tgl_x_preferred":[
        "Srirangarajapuram"
    ],
    "name:vie_x_preferred":[
        "Srirangarajapuram"
    ],
    "wof:name":"Srirengarajapuram",
    "wof:placetype":"locality",
    "wof:population":614
},
  "geometry": {"coordinates":[79.408912,10.937073],"type":"Point"}
}