{
  "type": "Feature",
  "properties": {
    "gn:country":"IN",
    "gn:fcode":"PPL",
    "gn:pop":41252,
    "iso:country":"IN",
    "name:ben_x_preferred":[
        "\u099a\u09ae\u09cd\u09aa\u09be"
    ],
    "name:bpy_x_preferred":[
        "\u099a\u09ae\u09cd\u09aa\u09be"
    ],
    "name:chi_x_preferred":[
        "\u6070\u59c6\u5e15"
    ],
    "name:dut_x_preferred":[
        "Champa"
    ],
    "name:eng_x_preferred":[
        "Champa"
    ],
    "name:fre_x_preferred":[
        "Champa"
    ],
    "name:ger_x_preferred":[
        "Champa"
    ],
    "name:guj_x_preferred":[
        "\u0a9a\u0a82\u0aaa\u0abe"
    ],
    "name:hin_x_preferred":[
        "\u091a\u092e\u094d\u092a\u093e"
    ],
    "name:ita_x_preferred":[
        "Champa"
    ],
    "name:jpn_x_preferred":[
        "\u30c1\u30e3\u30f3\u30d1"
    ],
    "name:kan_x_preferred":[
        "\u0c9a\u0c82\u0caa\u0cbe"
    ],
    "name:kor_x_preferred":[
        "\ucc38\ud30c"
    ],
    "name:mar_x_preferred":[
        "\u091a\u093e\u0902\u092a\u093e"
    ],
    "name:por_x_preferred":[
        "Champa"
    ],
    "name:rus_x_preferred":[
        "\u0427\u0430\u043c\u043f\u0430"
    ],
    "name:spa_x_preferred":[
        "Champa"
    ],
    "name:tam_x_preferred":[
        "\u0b9a\u0bae\u0bcd\u0baa\u0bbe"
    ],
    "name:tel_x_preferred":[
        "\u0c1a\u0c02\u0c2a\u0c3e"
    ],
    "name:urd_x_preferred":[
        "\u0686\u0645\u067e\u0627\u060c \u0686\u06be\u062a\u06cc\u0633 \u06af\u0691\u06be"
    ],
    "qs:name":"Champa",
    "qs:name_adm0":"India",
    "qs:name_adm1":"Chhattisgarh",
    "qs:photos":21,
    "qs:photos_1k":4,
    "qs:photos_9k":1,
    "qs:photos_9r":1,
    "qs:photos_all":21,
    "qs:photos_sr":1,
    "qs:placetype":"Town",
    "qs:pop_sr":"7",
    "wd:wordcount":2886,
    "wof:name":"Champa",
    "wof:placetype":"locality",
    "wof:population":41252
},
  "geometry": {"coordinates":[82.64248000000001,22.03593],"type":"Point"}
}