{
  "type": "Feature",
  "properties": {
    "iso:country":"IN",
    "ks:ks_alt_nam":"Ankur falia",
    "ks:ks_name":"Ankur Falia",
    "ks:ks_pop":183,
    "ks:ks_type":"HABITATION",
    "name:eng_x_preferred":[
        "Ankur Falia"
    ],
    "wof:name":"Ankur Falia",
    "wof:placetype":"locality",
    "wof:population":183
},
  "geometry": {"coordinates":[73.45955600000001,20.918],"type":"Point"}
}