{
  "type": "Feature",
  "properties": {
    "gn:admin1_code":"25.0",
    "gn:admin2_code":"620.0",
    "gn:asciiname":"Kollukkadu",
    "gn:country_code":"IN",
    "gn:dem":3,
    "gn:feature_class":"P",
    "gn:feature_code":"PPL",
    "gn:name":"Kollukk\u0101du",
    "gn:population":0,
    "gn:timezone":"Asia/Kolkata",
    "iso:country":"IN",
    "name:tam_x_preferred":[
        "\u0b95\u0bca\u0bb3\u0bcd\u0bb3\u0bc1\u0b95\u0bcd\u0b95\u0bbe\u0b9f\u0bc1"
    ],
    "wof:name":"Kollukkadu",
    "wof:placetype":"locality"
},
  "geometry": {"coordinates":[79.33463,10.30322],"type":"Point"}
}