{
  "type": "Feature",
  "properties": {
    "iso:country":"IN",
    "ks:ks_name":"P Godian",
    "ks:ks_pop":222,
    "ks:ks_type":"HABITATION",
    "name:eng_x_preferred":[
        "P Godian"
    ],
    "wof:name":"P Godian",
    "wof:placetype":"locality",
    "wof:population":222
},
  "geometry": {"coordinates":[81.425591,26.3958],"type":"Point"}
}