{
  "type": "Feature",
  "properties": {
    "iso:country":"IN",
    "ks:ks_name":"Taliya Tola",
    "ks:ks_pop":534,
    "ks:ks_type":"HABITATION",
    "ks:ks_uagg_main":0,
    "name:eng_x_preferred":[
        "Taliya Tola"
    ],
    "wof:name":"Taliya Tola",
    "wof:placetype":"neighbourhood",
    "wof:population":534
},
  "geometry": {"coordinates":[83.448133,26.979076],"type":"Point"}
}