{
  "type": "Feature",
  "properties": {
    "iso:country":"IN",
    "ks:ks_name":"Madava",
    "ks:ks_pop":6,
    "ks:ks_type":"HABITATION",
    "name:eng_x_preferred":[
        "Madava"
    ],
    "wof:name":"Madava",
    "wof:placetype":"locality",
    "wof:population":6
},
  "geometry": {"coordinates":[79.01452500000001,15.186179],"type":"Point"}
}