{
  "type": "Feature",
  "properties": {
    "iso:country":"IN",
    "ks:ks_name":"Bazar Para",
    "ks:ks_pop":1076,
    "ks:ks_type":"HABITATION",
    "name:eng_x_preferred":[
        "Bazar Para"
    ],
    "wof:name":"Bazar Para",
    "wof:placetype":"locality",
    "wof:population":1076
},
  "geometry": {"coordinates":[88.90291000000001,22.210383],"type":"Point"}
}