{
  "type": "Feature",
  "properties": {
    "gn:admin1_code":"36",
    "gn:admin2_code":"183.0",
    "gn:asciiname":"Bakhsh Singh",
    "gn:country_code":"IN",
    "gn:dem":114,
    "gn:feature_class":"P",
    "gn:feature_code":"PPL",
    "gn:name":"Bakhsh Singh",
    "gn:population":0,
    "gn:timezone":"Asia/Kolkata",
    "iso:country":"IN",
    "wof:name":"Bakhsh Singh",
    "wof:placetype":"locality"
},
  "geometry": {"coordinates":[81.73645999999999,27.30345],"type":"Point"}
}