{
  "type": "Feature",
  "properties": {
    "gn:admin1_code":"10.0",
    "gn:admin2_code":"80.0",
    "gn:asciiname":"Bobua",
    "gn:country_code":"IN",
    "gn:dem":229,
    "gn:feature_class":"P",
    "gn:feature_code":"PPL",
    "gn:name":"Bobua",
    "gn:population":0,
    "gn:timezone":"Asia/Kolkata",
    "iso:country":"IN",
    "wof:name":"Bobua",
    "wof:placetype":"locality"
},
  "geometry": {"coordinates":[75.95683000000002,29.44101],"type":"Point"}
}