{
  "type": "Feature",
  "properties": {
    "iso:country":"IN",
    "ks:ks_name":"Birwat",
    "ks:ks_pop":242,
    "ks:ks_type":"VILLAGE",
    "ks:ks_uagg_main":0,
    "name:eng_x_preferred":[
        "Birwat"
    ],
    "wof:name":"Birwat",
    "wof:placetype":"neighbourhood",
    "wof:population":242
},
  "geometry": {"coordinates":[82.630754,22.450654],"type":"Point"}
}