{
  "type": "Feature",
  "properties": {
    "iso:country":"IN",
    "ks:ks_name":"Paglijhora",
    "ks:ks_pop":112,
    "ks:ks_type":"HABITATION",
    "name:eng_x_preferred":[
        "Paglijhora"
    ],
    "wof:name":"Paglijhora",
    "wof:placetype":"locality",
    "wof:population":112
},
  "geometry": {"coordinates":[89.815282,26.082244],"type":"Point"}
}