{
  "type": "Feature",
  "properties": {
    "iso:country":"IN",
    "ks:ks_name":"Sonamui",
    "ks:ks_pop":3050,
    "ks:ks_type":"VILLAGE",
    "name:eng_x_preferred":[
        "Sonamui"
    ],
    "wof:name":"Sonamui",
    "wof:placetype":"locality",
    "wof:population":3050
},
  "geometry": {"coordinates":[87.033777,23.325422],"type":"Point"}
}