{
  "type": "Feature",
  "properties": {
    "gn:admin1_code":"13.0",
    "gn:admin2_code":"592.0",
    "gn:asciiname":"Kuttimunda",
    "gn:country_code":"IN",
    "gn:dem":39,
    "gn:feature_class":"P",
    "gn:feature_code":"PPL",
    "gn:name":"Kuttimunda",
    "gn:population":0,
    "gn:timezone":"Asia/Kolkata",
    "iso:country":"IN",
    "wof:name":"Kuttimunda",
    "wof:placetype":"neighbourhood"
},
  "geometry": {"coordinates":[76.26302,11.33896],"type":"Point"}
}