{
  "type": "Feature",
  "properties": {
    "iso:country":"IN",
    "ks:ks_name":"Innoli",
    "ks:ks_pop":1230,
    "ks:ks_type":"HABITATION",
    "name:eng_x_preferred":[
        "Innoli"
    ],
    "wof:name":"Innoli",
    "wof:placetype":"locality",
    "wof:population":1230
},
  "geometry": {"coordinates":[74.95136100000001,12.866865],"type":"Point"}
}