{
  "type": "Feature",
  "properties": {
    "iso:country":"IN",
    "ks:ks_alt_nam":"NAGLA  IMALIYA",
    "ks:ks_name":"Nagla Imaliya",
    "ks:ks_pop":251,
    "ks:ks_type":"HABITATION",
    "name:eng_x_preferred":[
        "Nagla Imaliya"
    ],
    "name:eng_x_variant":[
        "NAGLA  IMALIYA"
    ],
    "wof:name":"Nagla Imaliya",
    "wof:placetype":"locality",
    "wof:population":251
},
  "geometry": {"coordinates":[78.2803,27.532333],"type":"Point"}
}