{
  "type": "Feature",
  "properties": {
    "iso:country":"IN",
    "ks:ks_name":"Bullimalainagar",
    "ks:ks_pop":250,
    "ks:ks_type":"HABITATION",
    "name:eng_x_preferred":[
        "Bullimalainagar"
    ],
    "wof:name":"Bullimalainagar",
    "wof:placetype":"locality",
    "wof:population":250
},
  "geometry": {"coordinates":[79.381193,13.167953],"type":"Point"}
}