{
  "type": "Feature",
  "properties": {
    "iso:country":"IN",
    "ks:ks_name":"Bhawathar",
    "ks:ks_pop":1178,
    "ks:ks_type":"HABITATION",
    "name:eng_x_preferred":[
        "Bhawathar"
    ],
    "wof:name":"Bhawathar",
    "wof:placetype":"locality",
    "wof:population":1178
},
  "geometry": {"coordinates":[82.386917,25.486181],"type":"Point"}
}