{
  "type": "Feature",
  "properties": {
    "iso:country":"IN",
    "ks:ks_name":"Duarasuni",
    "ks:ks_pop":558,
    "ks:ks_type":"VILLAGE",
    "name:eng_x_preferred":[
        "Duarasuni"
    ],
    "wof:name":"Duarasuni",
    "wof:placetype":"locality",
    "wof:population":558
},
  "geometry": {"coordinates":[85.604664,21.496276],"type":"Point"}
}