{
  "type": "Feature",
  "properties": {
    "iso:country":"IN",
    "ks:ks_name":"Maikalong",
    "ks:ks_pop":253,
    "ks:ks_type":"VILLAGE",
    "name:eng_x_preferred":[
        "Maikalong"
    ],
    "wof:name":"Maikalong",
    "wof:placetype":"locality",
    "wof:population":253
},
  "geometry": {"coordinates":[92.599031,26.087298],"type":"Point"}
}