{
  "type": "Feature",
  "properties": {
    "gn:admin1_code":"16",
    "gn:admin2_code":"510.0",
    "gn:asciiname":"Ratnapur",
    "gn:country_code":"IN",
    "gn:dem":352,
    "gn:feature_class":"P",
    "gn:feature_code":"PPL",
    "gn:name":"Ratn\u0101pur",
    "gn:population":0,
    "gn:timezone":"Asia/Kolkata",
    "iso:country":"IN",
    "name:und_x_variant":[
        "Ratn\u0101pur",
        "Dheka"
    ],
    "name:urd_x_preferred":[
        "\u0631\u062a\u0646\u0627\u067e\u0648\u0631"
    ],
    "wof:name":"Ratnapur",
    "wof:placetype":"locality"
},
  "geometry": {"coordinates":[77.80224,20.48436],"type":"Point"}
}