{
  "type": "Feature",
  "properties": {
    "iso:country":"IN",
    "ks:ks_name":"Kalleli",
    "ks:ks_pop":90,
    "ks:ks_type":"HABITATION",
    "name:eng_x_preferred":[
        "Kalleli"
    ],
    "wof:name":"Kalleli",
    "wof:placetype":"locality",
    "wof:population":90
},
  "geometry": {"coordinates":[76.910909,9.181147],"type":"Point"}
}