{
  "type": "Feature",
  "properties": {
    "iso:country":"IN",
    "ks:ks_name":"Satagharia",
    "ks:ks_pop":174,
    "ks:ks_type":"HABITATION",
    "name:eng_x_preferred":[
        "Satagharia"
    ],
    "wof:name":"Satagharia",
    "wof:placetype":"locality",
    "wof:population":174
},
  "geometry": {"coordinates":[84.473742,20.018151],"type":"Point"}
}