{
  "type": "Feature",
  "properties": {
    "iso:country":"IN",
    "ks:ks_name":"Kwite",
    "ks:ks_pop":313,
    "ks:ks_type":"VILLAGE",
    "name:eng_x_preferred":[
        "Kwite"
    ],
    "wof:name":"Kwite",
    "wof:placetype":"locality",
    "wof:population":313
},
  "geometry": {"coordinates":[79.798131,29.621171],"type":"Point"}
}