{
  "type": "Feature",
  "properties": {
    "gn:admin1_code":"36",
    "gn:admin2_code":"175.0",
    "gn:asciiname":"Janwa Dih Khurd",
    "gn:country_code":"IN",
    "gn:dem":95,
    "gn:feature_class":"P",
    "gn:feature_code":"PPL",
    "gn:name":"Janwa D\u012bh Khurd",
    "gn:population":0,
    "gn:timezone":"Asia/Kolkata",
    "iso:country":"IN",
    "wof:name":"Janwa Dih Khurd",
    "wof:placetype":"locality"
},
  "geometry": {"coordinates":[82.16240999999999,25.56409],"type":"Point"}
}