{
  "type": "Feature",
  "properties": {
    "gn:admin1_code":"24.0",
    "gn:admin2_code":"104.0",
    "gn:asciiname":"Khanpurkhera",
    "gn:country_code":"IN",
    "gn:dem":223,
    "gn:feature_class":"P",
    "gn:feature_code":"PPL",
    "gn:name":"Kh\u0101npurkhera",
    "gn:population":0,
    "gn:timezone":"Asia/Kolkata",
    "iso:country":"IN",
    "wof:name":"Khanpurkhera",
    "wof:placetype":"locality"
},
  "geometry": {"coordinates":[76.92416999999998,27.59639],"type":"Point"}
}