{
  "type": "Feature",
  "properties": {
    "gn:admin1_code":"36",
    "gn:admin2_code":"176.0",
    "gn:asciiname":"Baragaon",
    "gn:country_code":"IN",
    "gn:dem":109,
    "gn:feature_class":"P",
    "gn:feature_code":"PPL",
    "gn:name":"Bar\u0101g\u0101on",
    "gn:population":0,
    "gn:timezone":"Asia/Kolkata",
    "iso:country":"IN",
    "ks:ks_alt_nam":"Bar\u0101g\u0101on",
    "ks:ks_name":"Baragaon",
    "ks:ks_pop":0,
    "ks:ks_type":"VILLAGE",
    "name:eng_x_preferred":[
        "Baragaon"
    ],
    "name:eng_x_variant":[
        "Bar\u0101g\u0101on"
    ],
    "name:ita_x_preferred":[
        "Baragaon"
    ],
    "name:nld_x_preferred":[
        "Baragaon"
    ],
    "name:pol_x_preferred":[
        "Baragaon"
    ],
    "wof:name":"Baragaon",
    "wof:placetype":"locality",
    "wof:population":0
},
  "geometry": {"coordinates":[81.433959,27.228279],"type":"Point"}
}