{
  "type": "Feature",
  "properties": {
    "iso:country":"IN",
    "ks:ks_name":"Chikkallalli",
    "ks:ks_pop":348,
    "ks:ks_type":"VILLAGE",
    "name:eng_x_preferred":[
        "Chikkallalli"
    ],
    "wof:name":"Chikkallalli",
    "wof:placetype":"locality",
    "wof:population":348
},
  "geometry": {"coordinates":[75.27010199999999,13.849584],"type":"Point"}
}