{
  "type": "Feature",
  "properties": {
    "gn:admin1_code":"35.0",
    "gn:admin2_code":"437",
    "gn:asciiname":"Kantaphor",
    "gn:country_code":"IN",
    "gn:dem":339,
    "gn:feature_class":"P",
    "gn:feature_code":"PPL",
    "gn:name":"K\u0101nt\u0101phor",
    "gn:population":0,
    "gn:timezone":"Asia/Kolkata",
    "iso:country":"IN",
    "wof:name":"Kantaphor",
    "wof:placetype":"locality"
},
  "geometry": {"coordinates":[76.5596,22.57659],"type":"Point"}
}