{
  "type": "Feature",
  "properties": {
    "iso:country":"IN",
    "ks:ks_name":"Lattipur",
    "ks:ks_pop":16,
    "ks:ks_type":"VILLAGE",
    "name:eng_x_preferred":[
        "Lattipur"
    ],
    "wof:name":"Lattipur",
    "wof:placetype":"locality",
    "wof:population":16
},
  "geometry": {"coordinates":[87.266262,25.301203],"type":"Point"}
}