{
  "type": "Feature",
  "properties": {
    "iso:country":"IN",
    "ks:ks_name":"Mariammalpuram",
    "ks:ks_pop":258,
    "ks:ks_type":"HABITATION",
    "name:eng_x_preferred":[
        "Mariammalpuram"
    ],
    "wof:name":"Mariammalpuram",
    "wof:placetype":"locality",
    "wof:population":258
},
  "geometry": {"coordinates":[77.90022500000001,8.612417],"type":"Point"}
}