{
  "type": "Feature",
  "properties": {
    "gn:admin1_code":"12.0",
    "gn:admin2_code":"1.0",
    "gn:asciiname":"Urniwali",
    "gn:country_code":"IN",
    "gn:dem":1987,
    "gn:feature_class":"P",
    "gn:feature_code":"PPL",
    "gn:name":"\u016arniw\u0101li",
    "gn:population":0,
    "gn:timezone":"Asia/Kolkata",
    "iso:country":"IN",
    "wof:name":"Urniwali",
    "wof:placetype":"locality"
},
  "geometry": {"coordinates":[74.45711999999997,34.56291],"type":"Point"}
}