{
  "type": "Feature",
  "properties": {
    "iso:country":"IN",
    "ks:ks_name":"Bahuroopan Deeh",
    "ks:ks_pop":302,
    "ks:ks_type":"HABITATION",
    "name:eng_x_preferred":[
        "Bahuroopan Deeh"
    ],
    "wof:name":"Bahuroopan Deeh",
    "wof:placetype":"locality",
    "wof:population":302
},
  "geometry": {"coordinates":[82.77912600000001,27.354311],"type":"Point"}
}