{
  "type": "Feature",
  "properties": {
    "iso:country":"IN",
    "ks:ks_name":"Sulunga.",
    "ks:ks_pop":85,
    "ks:ks_type":"HABITATION",
    "name:eng_x_preferred":[
        "Sulunga."
    ],
    "wof:name":"Sulunga.",
    "wof:placetype":"locality",
    "wof:population":85
},
  "geometry": {"coordinates":[87.40758700000001,24.060195],"type":"Point"}
}