{
  "type": "Feature",
  "properties": {
    "gn:admin1_code":"36",
    "gn:admin2_code":"143.0",
    "gn:asciiname":"Naya",
    "gn:country_code":"IN",
    "gn:dem":180,
    "gn:feature_class":"P",
    "gn:feature_code":"PPL",
    "gn:name":"N\u0101ya",
    "gn:population":0,
    "gn:timezone":"Asia/Kolkata",
    "iso:country":"IN",
    "name:ceb_x_preferred":[
        "Naya"
    ],
    "name:deu_x_preferred":[
        "Naya"
    ],
    "name:fra_x_preferred":[
        "Naya"
    ],
    "name:ita_x_preferred":[
        "Naya"
    ],
    "name:rus_x_preferred":[
        "\u041d\u0430\u0439\u044f"
    ],
    "name:spa_x_preferred":[
        "Naya"
    ],
    "name:swe_x_preferred":[
        "Naya"
    ],
    "wof:name":"Naya",
    "wof:placetype":"locality"
},
  "geometry": {"coordinates":[77.92708,27.60986],"type":"Point"}
}