{
  "type": "Feature",
  "properties": {
    "iso:country":"IN",
    "ks:ks_name":"Kadodihi",
    "ks:ks_type":"VILLAGE",
    "name:eng_x_preferred":[
        "Kadodihi"
    ],
    "wof:name":"Kadodihi",
    "wof:placetype":"locality"
},
  "geometry": {"coordinates":[84.74023699999999,21.678746],"type":"Point"}
}