{
  "type": "Feature",
  "properties": {
    "gn:admin1_code":"39.0",
    "gn:admin2_code":"061",
    "gn:asciiname":"Jhatri",
    "gn:country_code":"IN",
    "gn:dem":1116,
    "gn:feature_class":"P",
    "gn:feature_code":"PPL",
    "gn:name":"Jhatri",
    "gn:population":0,
    "gn:timezone":"Asia/Kolkata",
    "iso:country":"IN",
    "wof:name":"Jhatri",
    "wof:placetype":"locality"
},
  "geometry": {"coordinates":[78.59418000000002,29.86271],"type":"Point"}
}