{
  "type": "Feature",
  "properties": {
    "iso:country":"IN",
    "ks:ks_name":"Nalabid",
    "ks:ks_pop":247,
    "ks:ks_type":"HABITATION",
    "name:eng_x_preferred":[
        "Nalabid"
    ],
    "wof:name":"Nalabid",
    "wof:placetype":"locality",
    "wof:population":247
},
  "geometry": {"coordinates":[72.47419499999999,24.671789],"type":"Point"}
}