{
  "type": "Feature",
  "properties": {
    "iso:country":"IN",
    "ks:ks_alt_nam":"Paramanick Baidya and Shaikh Para",
    "ks:ks_name":"Paramanick Baidya And Shaikh Para",
    "ks:ks_pop":669,
    "ks:ks_type":"HABITATION",
    "name:eng_x_preferred":[
        "Paramanick Baidya And Shaikh Para"
    ],
    "wof:name":"Paramanick Baidya And Shaikh Para",
    "wof:placetype":"locality",
    "wof:population":669
},
  "geometry": {"coordinates":[88.41070000000001,22.159668],"type":"Point"}
}