{
  "type": "Feature",
  "properties": {
    "iso:country":"IN",
    "ks:ks_name":"Khaliyapara",
    "ks:ks_pop":342,
    "ks:ks_type":"HABITATION",
    "name:eng_x_preferred":[
        "Khaliyapara"
    ],
    "wof:name":"Khaliyapara",
    "wof:placetype":"locality",
    "wof:population":342
},
  "geometry": {"coordinates":[82.658242,19.988944],"type":"Point"}
}