{
  "type": "Feature",
  "properties": {
    "gn:admin1_code":"19.0",
    "gn:admin2_code":"575.0",
    "gn:asciiname":"Mapale",
    "gn:country_code":"IN",
    "gn:dem":273,
    "gn:feature_class":"P",
    "gn:feature_code":"PPL",
    "gn:name":"Mapale",
    "gn:population":0,
    "gn:timezone":"Asia/Kolkata",
    "iso:country":"IN",
    "ks:ks_name":"Mapalu",
    "ks:ks_pop":100,
    "ks:ks_type":"HABITATION",
    "name:eng_x_preferred":[
        "Mapalu"
    ],
    "name:eng_x_variant":[
        "Mapale"
    ],
    "wof:name":"Mapalu",
    "wof:placetype":"locality",
    "wof:population":100
},
  "geometry": {"coordinates":[75.17419099999999,13.131609],"type":"Point"}
}