{
  "type": "Feature",
  "properties": {
    "iso:country":"IN",
    "ks:ks_name":"Krishnaganj",
    "ks:ks_pop":1166,
    "ks:ks_type":"VILLAGE",
    "ks:ks_uagg_main":0,
    "name:eng_x_preferred":[
        "Krishnaganj"
    ],
    "wof:name":"Krishnaganj",
    "wof:placetype":"neighbourhood",
    "wof:population":1166
},
  "geometry": {"coordinates":[88.02124499999999,25.3419],"type":"Point"}
}