{
  "type": "Feature",
  "properties": {
    "iso:country":"IN",
    "ks:ks_name":"Madurabashanipuram",
    "ks:ks_pop":1036,
    "ks:ks_type":"VILLAGE",
    "ks:ks_uagg_main":0,
    "name:eng_x_preferred":[
        "Madurabashanipuram"
    ],
    "wof:name":"Madurabashanipuram",
    "wof:placetype":"neighbourhood",
    "wof:population":1036
},
  "geometry": {"coordinates":[79.43551600000001,10.468775],"type":"Point"}
}