{
  "type": "Feature",
  "properties": {
    "iso:country":"IN",
    "ks:ks_alt_nam":"TELO TOLI",
    "ks:ks_name":"Telo Toli",
    "ks:ks_pop":376,
    "ks:ks_type":"HABITATION",
    "name:eng_x_preferred":[
        "Telo Toli"
    ],
    "wof:name":"Telo Toli",
    "wof:placetype":"locality",
    "wof:population":376
},
  "geometry": {"coordinates":[85.179714,23.012193],"type":"Point"}
}