{
  "type": "Feature",
  "properties": {
    "iso:country":"IN",
    "ks:ks_name":"Basrehi Mustkil",
    "ks:ks_pop":589,
    "ks:ks_type":"VILLAGE",
    "ks:ks_uagg_main":0,
    "name:eng_x_preferred":[
        "Basrehi Mustkil"
    ],
    "wof:name":"Basrehi Mustkil",
    "wof:placetype":"neighbourhood",
    "wof:population":589
},
  "geometry": {"coordinates":[81.350386,25.337582],"type":"Point"}
}