{
  "type": "Feature",
  "properties": {
    "iso:country":"IN",
    "ks:ks_name":"Kamathgeri",
    "ks:ks_pop":24,
    "ks:ks_type":"HABITATION",
    "name:eng_x_preferred":[
        "Kamathgeri"
    ],
    "wof:name":"Kamathgeri",
    "wof:placetype":"locality",
    "wof:population":24
},
  "geometry": {"coordinates":[74.770293,14.739893],"type":"Point"}
}