{
  "type": "Feature",
  "properties": {
    "iso:country":"IN",
    "ks:ks_name":"Badhunpani",
    "ks:ks_pop":40,
    "ks:ks_type":"VILLAGE",
    "name:eng_x_preferred":[
        "Badhunpani"
    ],
    "wof:name":"Badhunpani",
    "wof:placetype":"locality",
    "wof:population":40
},
  "geometry": {"coordinates":[82.735421,20.033276],"type":"Point"}
}