{
  "type": "Feature",
  "properties": {
    "iso:country":"IN",
    "ks:ks_name":"Sadak Para",
    "ks:ks_pop":591,
    "ks:ks_type":"HABITATION",
    "name:eng_x_preferred":[
        "Sadak Para"
    ],
    "wof:name":"Sadak Para",
    "wof:placetype":"locality",
    "wof:population":591
},
  "geometry": {"coordinates":[81.690808,20.581004],"type":"Point"}
}