{
  "type": "Feature",
  "properties": {
    "iso:country":"IN",
    "ks:ks_alt_nam":"DADHIWAL KA DERA",
    "ks:ks_name":"Dadhiwal Ka Dera",
    "ks:ks_pop":146,
    "ks:ks_type":"HABITATION",
    "name:eng_x_preferred":[
        "Dadhiwal Ka Dera"
    ],
    "wof:name":"Dadhiwal Ka Dera",
    "wof:placetype":"locality",
    "wof:population":146
},
  "geometry": {"coordinates":[84.060681,25.936445],"type":"Point"}
}