{
  "type": "Feature",
  "properties": {
    "gn:admin1_code":"24",
    "gn:admin2_code":"122.0",
    "gn:asciiname":"Matholai",
    "gn:country_code":"IN",
    "gn:dem":336,
    "gn:feature_class":"P",
    "gn:feature_code":"PPL",
    "gn:name":"M\u0101thol\u0101i",
    "gn:population":0,
    "gn:timezone":"Asia/Kolkata",
    "iso:country":"IN",
    "wof:name":"Matholai",
    "wof:placetype":"locality"
},
  "geometry": {"coordinates":[75.27848,25.63399],"type":"Point"}
}