{
  "type": "Feature",
  "properties": {
    "gn:admin1_code":"36",
    "gn:admin2_code":"192.0",
    "gn:asciiname":"Anandjot",
    "gn:country_code":"IN",
    "gn:dem":74,
    "gn:feature_class":"P",
    "gn:feature_code":"PPL",
    "gn:name":"Anandjot",
    "gn:population":0,
    "gn:timezone":"Asia/Kolkata",
    "iso:country":"IN",
    "ks:ks_name":"Anant Jot",
    "ks:ks_pop":360,
    "ks:ks_type":"VILLAGE",
    "ks:ks_uagg_main":0,
    "name:eng_x_preferred":[
        "Anant Jot"
    ],
    "wof:name":"Anant Jot",
    "wof:placetype":"neighbourhood",
    "wof:population":360
},
  "geometry": {"coordinates":[83.64794000000001,25.944939],"type":"Point"}
}