{
  "type": "Feature",
  "properties": {
    "iso:country":"IN",
    "ks:ks_name":"Dom Tola",
    "ks:ks_pop":344,
    "ks:ks_type":"HABITATION",
    "name:eng_x_preferred":[
        "Dom Tola"
    ],
    "wof:name":"Dom Tola",
    "wof:placetype":"locality",
    "wof:population":344
},
  "geometry": {"coordinates":[86.541,25.8844],"type":"Point"}
}