{
  "type": "Feature",
  "properties": {
    "gn:admin1_code":"33",
    "gn:admin2_code":"585.0",
    "gn:asciiname":"Sirangulim",
    "gn:country_code":"IN",
    "gn:dem":56,
    "gn:feature_class":"P",
    "gn:feature_code":"PPL",
    "gn:name":"Sirangulim",
    "gn:population":0,
    "gn:timezone":"Asia/Kolkata",
    "iso:country":"IN",
    "name:und_x_variant":[
        "Siranguli",
        "Sirangulim"
    ],
    "wof:name":"Sirangulim",
    "wof:placetype":"locality"
},
  "geometry": {"coordinates":[74.18096,15.48458],"type":"Point"}
}