{
  "type": "Feature",
  "properties": {
    "gn:admin1_code":"37",
    "gn:admin2_code":"404.0",
    "gn:asciiname":"Bandhapara",
    "gn:country_code":"IN",
    "gn:dem":378,
    "gn:feature_class":"P",
    "gn:feature_code":"PPL",
    "gn:name":"Bandhap\u0101ra",
    "gn:population":0,
    "gn:timezone":"Asia/Kolkata",
    "iso:country":"IN",
    "ks:ks_alt_nam":"Bandhap\u0101ra",
    "ks:ks_name":"Bandhapara",
    "ks:ks_type":"VILLAGE",
    "name:eng_x_preferred":[
        "Bandhapara"
    ],
    "name:eng_x_variant":[
        "Bandhap\u0101ra"
    ],
    "wof:name":"Bandhapara",
    "wof:placetype":"locality"
},
  "geometry": {"coordinates":[82.351229,22.713238],"type":"Point"}
}