{
  "type": "Feature",
  "properties": {
    "iso:country":"IN",
    "ks:ks_alt_nam":"jogwadi",
    "ks:ks_name":"Jogwadi",
    "ks:ks_pop":103,
    "ks:ks_type":"HABITATION",
    "name:eng_x_preferred":[
        "Jogwadi"
    ],
    "wof:name":"Jogwadi",
    "wof:placetype":"locality",
    "wof:population":103
},
  "geometry": {"coordinates":[73.587222,17.354167],"type":"Point"}
}