{
  "type": "Feature",
  "properties": {
    "iso:country":"IN",
    "ks:ks_name":"Mansingh Nagar",
    "ks:ks_pop":505,
    "ks:ks_type":"HABITATION",
    "name:eng_x_preferred":[
        "Mansingh Nagar"
    ],
    "wof:name":"Mansingh Nagar",
    "wof:placetype":"locality",
    "wof:population":505
},
  "geometry": {"coordinates":[72.58663300000001,26.807903],"type":"Point"}
}