{
  "type": "Feature",
  "properties": {
    "gn:admin1_code":"19.0",
    "gn:admin2_code":"559",
    "gn:asciiname":"Jawalgera",
    "gn:country_code":"IN",
    "gn:dem":403,
    "gn:feature_class":"P",
    "gn:feature_code":"PPL",
    "gn:name":"Jawalgera",
    "gn:population":0,
    "gn:timezone":"Asia/Kolkata",
    "iso:country":"IN",
    "wof:name":"Jawalgera",
    "wof:placetype":"locality"
},
  "geometry": {"coordinates":[76.81967,15.8674],"type":"Point"}
}