{
  "type": "Feature",
  "properties": {
    "gn:admin1_code":"16.0",
    "gn:admin2_code":"521",
    "gn:asciiname":"Karhati",
    "gn:country_code":"IN",
    "gn:dem":596,
    "gn:feature_class":"P",
    "gn:feature_code":"PPL",
    "gn:name":"Karhati",
    "gn:population":0,
    "gn:timezone":"Asia/Kolkata",
    "iso:country":"IN",
    "name:mar_x_preferred":[
        "\u0915\u093e\u0931\u094d\u0939\u093e\u091f\u0940"
    ],
    "wof:name":"Karhati",
    "wof:placetype":"locality"
},
  "geometry": {"coordinates":[74.42233,18.26271],"type":"Point"}
}