{
  "type": "Feature",
  "properties": {
    "gn:admin1_code":"16",
    "gn:admin2_code":"516.0",
    "gn:asciiname":"Shegwa",
    "gn:country_code":"IN",
    "gn:dem":313,
    "gn:feature_class":"P",
    "gn:feature_code":"PPL",
    "gn:name":"Shegwa",
    "gn:population":0,
    "gn:timezone":"Asia/Kolkata",
    "iso:country":"IN",
    "wof:name":"Shegwa",
    "wof:placetype":"locality"
},
  "geometry": {"coordinates":[73.34999999999999,20.15],"type":"Point"}
}