{
  "type": "Feature",
  "properties": {
    "iso:country":"IN",
    "ks:ks_alt_nam":"jogindha",
    "ks:ks_name":"Jogindha",
    "ks:ks_pop":231,
    "ks:ks_type":"HABITATION",
    "name:eng_x_preferred":[
        "Jogindha"
    ],
    "wof:name":"Jogindha",
    "wof:placetype":"locality",
    "wof:population":231
},
  "geometry": {"coordinates":[86.780253,24.371043],"type":"Point"}
}