{
  "type": "Feature",
  "properties": {
    "gn:admin1_code":"35.0",
    "gn:admin2_code":"465.0",
    "gn:asciiname":"Maiala",
    "gn:country_code":"IN",
    "gn:dem":238,
    "gn:feature_class":"P",
    "gn:feature_code":"PPL",
    "gn:name":"Mai\u00e1la",
    "gn:population":0,
    "gn:timezone":"Asia/Kolkata",
    "iso:country":"IN",
    "ks:ks_name":"Mayala",
    "ks:ks_pop":1066,
    "ks:ks_type":"VILLAGE",
    "name:eng_x_preferred":[
        "Mayala"
    ],
    "name:eng_x_variant":[
        "Maiala"
    ],
    "wof:name":"Mayala",
    "wof:placetype":"locality",
    "wof:population":1066
},
  "geometry": {"coordinates":[74.457234,22.286889],"type":"Point"}
}