{
  "type": "Feature",
  "properties": {
    "iso:country":"IN",
    "ks:ks_name":"Uchangi",
    "ks:ks_pop":64,
    "ks:ks_type":"VILLAGE",
    "name:eng_x_preferred":[
        "Uchangi"
    ],
    "wof:name":"Uchangi",
    "wof:placetype":"locality",
    "wof:population":64
},
  "geometry": {"coordinates":[83.85950099999999,20.464272],"type":"Point"}
}