{
  "type": "Feature",
  "properties": {
    "iso:country":"IN",
    "ks:ks_alt_nam":"T.M.GARUVU",
    "ks:ks_name":"T.m.garuvu",
    "ks:ks_pop":33,
    "ks:ks_type":"HABITATION",
    "name:eng_x_preferred":[
        "T.m.garuvu"
    ],
    "wof:name":"T.m.garuvu",
    "wof:placetype":"locality",
    "wof:population":33
},
  "geometry": {"coordinates":[82.842902,17.999941],"type":"Point"}
}