{
  "type": "Feature",
  "properties": {
    "gn:admin1_code":"36",
    "gn:admin2_code":"185.0",
    "gn:asciiname":"Narsinghpur",
    "gn:country_code":"IN",
    "gn:dem":94,
    "gn:feature_class":"P",
    "gn:feature_code":"PPL",
    "gn:name":"Narsinghpur",
    "gn:population":0,
    "gn:timezone":"Asia/Kolkata",
    "iso:country":"IN",
    "name:ara_x_preferred":[
        "\u0646\u0627\u0631\u0633\u064a\u0646\u062c\u0628\u0648\u0631"
    ],
    "name:ben_bn_x_preferred":[
        "\u09a8\u09b0\u09b8\u09bf\u0982\u09b9\u09aa\u09c1\u09b0"
    ],
    "name:ben_in_x_preferred":[
        "\u09a8\u09b0\u09b8\u09bf\u0982\u09b9\u09aa\u09c1\u09b0"
    ],
    "name:ben_x_preferred":[
        "\u09a8\u09b0\u09b8\u09bf\u0982\u09b9\u09aa\u09c1\u09b0"
    ],
    "name:bpy_x_preferred":[
        "\u09a8\u09b0\u09b8\u09bf\u0982\u09b9\u09aa\u09c1\u09b0 \u099c\u09bf\u09b2\u09be"
    ],
    "name:cat_x_preferred":[
        "Narsinghpur"
    ],
    "name:ceb_x_preferred":[
        "Narsimhapur"
    ],
    "name:fra_x_preferred":[
        "Narsinghpur"
    ],
    "name:guj_x_preferred":[
        "\u0aa8\u0ab0\u0ab8\u0abf\u0a82\u0a98\u0aaa\u0ac1\u0ab0"
    ],
    "name:guj_x_variant":[
        "\u0aa8\u0ab0\u0ab8\u0abf\u0a82\u0ab9\u0aaa\u0ac1\u0ab0"
    ],
    "name:hin_x_preferred":[
        "\u0928\u0930\u0938\u093f\u0902\u0939\u092a\u0941\u0930"
    ],
    "name:ita_x_preferred":[
        "Narsinghpur"
    ],
    "name:kan_x_preferred":[
        "\u0ca8\u0cb0\u0cb8\u0cbf\u0c82\u0c97\u0ccd"
    ],
    "name:mal_x_preferred":[
        "\u0d28\u0d30\u0d38\u0d3f\u0d19\u0d4d"
    ],
    "name:mar_x_preferred":[
        "\u0928\u0930\u0938\u093f\u0902\u0917\u092a\u0942\u0930"
    ],
    "name:mlg_x_preferred":[
        "Narsinghpur"
    ],
    "name:msa_x_preferred":[
        "Narsimhapur"
    ],
    "name:new_x_preferred":[
        "\u0928\u0930\u094d\u0938\u093f\u0902\u0939\u092a\u0941\u0930"
    ],
    "name:pam_x_preferred":[
        "Narsinghpur"
    ],
    "name:pan_x_preferred":[
        "\u0a28\u0a30\u0a38\u0a3f\u0a70\u0a18\u0a2a\u0a41\u0a30"
    ],
    "name:por_x_preferred":[
        "Narsimhapur"
    ],
    "name:san_x_preferred":[
        "\u0928\u0930\u0938\u093f\u0902\u0939\u092a\u0941\u0930\u092e\u094d"
    ],
    "name:spa_x_preferred":[
        "Narsinghpur"
    ],
    "name:swe_x_preferred":[
        "Narsimhapur"
    ],
    "name:tam_x_preferred":[
        "\u0ba8\u0bb0\u0bcd\u0b9a\u0bbf\u0b99\u0bcd\u0baa\u0bc2\u0bb0\u0bcd"
    ],
    "name:tel_x_preferred":[
        "\u0c28\u0c30\u0c4d\u0c36\u0c3f\u0c02\u0c17\u0c4d"
    ],
    "name:urd_x_preferred":[
        "\u0646\u0631\u0633\u0646\u06af\u06be \u067e\u0648\u0631"
    ],
    "name:vie_x_preferred":[
        "Narsimhapur"
    ],
    "name:zho_x_preferred":[
        "\u7eb3\u5c14\u897f\u59c6\u54c8\u666e\u5c14"
    ],
    "wof:name":"Narsinghpur",
    "wof:placetype":"locality"
},
  "geometry": {"coordinates":[82.43970999999998,26.84469],"type":"Point"}
}