{
  "type": "Feature",
  "properties": {
    "iso:country":"IN",
    "ks:ks_name":"Jaioraidih",
    "ks:ks_pop":102,
    "ks:ks_type":"VILLAGE",
    "ks:ks_uagg_main":0,
    "name:eng_x_preferred":[
        "Jaioraidih"
    ],
    "wof:name":"Jaioraidih",
    "wof:placetype":"neighbourhood",
    "wof:population":102
},
  "geometry": {"coordinates":[85.714499,24.507385],"type":"Point"}
}