{
  "type": "Feature",
  "properties": {
    "gn:admin1_code":"9.0",
    "gn:admin2_code":"469.0",
    "gn:asciiname":"Jaswapur",
    "gn:country_code":"IN",
    "gn:dem":219,
    "gn:feature_class":"P",
    "gn:feature_code":"PPL",
    "gn:name":"Jasw\u0101pur",
    "gn:population":0,
    "gn:timezone":"Asia/Kolkata",
    "iso:country":"IN",
    "ks:ks_name":"Jasvapura",
    "ks:ks_pop":230,
    "ks:ks_type":"VILLAGE",
    "name:eng_x_preferred":[
        "Jasvapura"
    ],
    "name:eng_x_variant":[
        "Jaswapur"
    ],
    "wof:name":"Jasvapura",
    "wof:placetype":"locality",
    "wof:population":230
},
  "geometry": {"coordinates":[72.809054,24.100946],"type":"Point"}
}