{
  "type": "Feature",
  "properties": {
    "iso:country":"IN",
    "ks:ks_name":"Sethunampalayam",
    "ks:ks_pop":892,
    "ks:ks_type":"HABITATION",
    "ks:ks_uagg_main":0,
    "name:eng_x_preferred":[
        "Sethunampalayam"
    ],
    "wof:name":"Sethunampalayam",
    "wof:placetype":"neighbourhood",
    "wof:population":892
},
  "geometry": {"coordinates":[77.60414,11.521128],"type":"Point"}
}