{
  "type": "Feature",
  "properties": {
    "gn:admin1_code":"10",
    "gn:admin2_code":"89.0",
    "gn:asciiname":"Hidayatpur",
    "gn:country_code":"IN",
    "gn:dem":193,
    "gn:feature_class":"P",
    "gn:feature_code":"PPL",
    "gn:name":"Hid\u0101yatpur",
    "gn:population":0,
    "gn:timezone":"Asia/Kolkata",
    "iso:country":"IN",
    "wof:name":"Hidayatpur",
    "wof:placetype":"locality"
},
  "geometry": {"coordinates":[77.39233,28.06933],"type":"Point"}
}