{
  "type": "Feature",
  "properties": {
    "iso:country":"IN",
    "ks:ks_name":"Pichhaldaha",
    "ks:ks_pop":501,
    "ks:ks_type":"VILLAGE",
    "ks:ks_uagg_main":0,
    "name:eng_x_preferred":[
        "Pichhaldaha"
    ],
    "wof:name":"Pichhaldaha",
    "wof:placetype":"neighbourhood",
    "wof:population":501
},
  "geometry": {"coordinates":[88.025862,22.242208],"type":"Point"}
}