{
  "type": "Feature",
  "properties": {
    "gn:admin1_code":"2.0",
    "gn:admin2_code":"543.0",
    "gn:asciiname":"Chilakagedda",
    "gn:country_code":"IN",
    "gn:dem":115,
    "gn:feature_class":"P",
    "gn:feature_code":"PPL",
    "gn:name":"Chilakagedda",
    "gn:population":0,
    "gn:timezone":"Asia/Kolkata",
    "iso:country":"IN",
    "ks:ks_name":"Chilakalagedda",
    "ks:ks_pop":849,
    "ks:ks_type":"VILLAGE",
    "ks:ks_uagg_main":0,
    "name:eng_x_preferred":[
        "Chilakalagedda"
    ],
    "wof:name":"Chilakalagedda",
    "wof:placetype":"neighbourhood",
    "wof:population":849
},
  "geometry": {"coordinates":[83.12757999999999,18.183432],"type":"Point"}
}