{
  "type": "Feature",
  "properties": {
    "iso:country":"IN",
    "ks:ks_name":"Gauniyaraw",
    "ks:ks_pop":1064,
    "ks:ks_type":"VILLAGE",
    "name:eng_x_preferred":[
        "Gauniyaraw"
    ],
    "wof:name":"Gauniyaraw",
    "wof:placetype":"locality",
    "wof:population":1064
},
  "geometry": {"coordinates":[79.820784,29.181142],"type":"Point"}
}