{
  "type": "Feature",
  "properties": {
    "iso:country":"IN",
    "ks:ks_name":"Mandirpada",
    "ks:ks_pop":59,
    "ks:ks_type":"HABITATION",
    "name:eng_x_preferred":[
        "Mandirpada"
    ],
    "wof:name":"Mandirpada",
    "wof:placetype":"locality",
    "wof:population":59
},
  "geometry": {"coordinates":[83.40398999999999,19.928452],"type":"Point"}
}