{
  "type": "Feature",
  "properties": {
    "gn:admin1_code":"25.0",
    "gn:admin2_code":"632.0",
    "gn:asciiname":"Nanjundapuram",
    "gn:country_code":"IN",
    "gn:dem":527,
    "gn:feature_class":"P",
    "gn:feature_code":"PPL",
    "gn:name":"Nanjund\u0101puram",
    "gn:population":0,
    "gn:timezone":"Asia/Kolkata",
    "iso:country":"IN",
    "ks:ks_alt_nam":"Nanjund\u0101puram",
    "ks:ks_name":"Nanjundapuram",
    "ks:ks_pop":980,
    "ks:ks_type":"VILLAGE",
    "ks:ks_uagg_main":0,
    "name:eng_x_preferred":[
        "Nanjundapuram"
    ],
    "name:eng_x_variant":[
        "Nanjund\u0101puram"
    ],
    "wof:name":"Nanjundapuram",
    "wof:placetype":"neighbourhood",
    "wof:population":980
},
  "geometry": {"coordinates":[76.873261,11.085527],"type":"Point"}
}