{
  "type": "Feature",
  "properties": {
    "iso:country":"IN",
    "ks:ks_name":"Bagiya Falia",
    "ks:ks_pop":50,
    "ks:ks_type":"HABITATION",
    "name:eng_x_preferred":[
        "Bagiya Falia"
    ],
    "wof:name":"Bagiya Falia",
    "wof:placetype":"locality",
    "wof:population":50
},
  "geometry": {"coordinates":[73.032419,20.394464],"type":"Point"}
}