{
  "type": "Feature",
  "properties": {
    "gn:admin1_code":"36",
    "gn:admin2_code":"188.0",
    "gn:asciiname":"Amauli",
    "gn:country_code":"IN",
    "gn:dem":83,
    "gn:feature_class":"P",
    "gn:feature_code":"PPL",
    "gn:name":"Amauli",
    "gn:population":0,
    "gn:timezone":"Asia/Kolkata",
    "iso:country":"IN",
    "wof:name":"Amauli",
    "wof:placetype":"neighbourhood"
},
  "geometry": {"coordinates":[83.20438,26.56198],"type":"Point"}
}