{
  "type": "Feature",
  "properties": {
    "iso:country":"IN",
    "ks:ks_name":"Sainda",
    "ks:ks_pop":1510,
    "ks:ks_type":"VILLAGE",
    "ks:ks_uagg_main":0,
    "name:eng_x_preferred":[
        "Sainda"
    ],
    "wof:name":"Sainda",
    "wof:placetype":"neighbourhood",
    "wof:population":1510
},
  "geometry": {"coordinates":[85.901028,20.386074],"type":"Point"}
}