{
  "type": "Feature",
  "properties": {
    "iso:country":"IN",
    "ks:ks_name":"Goudarkeri",
    "ks:ks_pop":398,
    "ks:ks_type":"HABITATION",
    "name:eng_x_preferred":[
        "Goudarkeri"
    ],
    "wof:name":"Goudarkeri",
    "wof:placetype":"locality",
    "wof:population":398
},
  "geometry": {"coordinates":[74.435261,14.316967],"type":"Point"}
}