{
  "type": "Feature",
  "properties": {
    "iso:country":"IN",
    "ks:ks_name":"Rujangi",
    "ks:ks_pop":505,
    "ks:ks_type":"VILLAGE",
    "name:eng_x_preferred":[
        "Rujangi"
    ],
    "wof:name":"Rujangi",
    "wof:placetype":"locality",
    "wof:population":505
},
  "geometry": {"coordinates":[84.342567,19.550442],"type":"Point"}
}