{
  "type": "Feature",
  "properties": {
    "iso:country":"IN",
    "ks:ks_name":"Korgi",
    "ks:ks_pop":483,
    "ks:ks_type":"VILLAGE",
    "name:eng_x_preferred":[
        "Korgi"
    ],
    "wof:name":"Korgi",
    "wof:placetype":"locality",
    "wof:population":483
},
  "geometry": {"coordinates":[84.204526,23.545078],"type":"Point"}
}