{
  "type": "Feature",
  "properties": {
    "gn:admin1_code":"36.0",
    "gn:admin2_code":"190.0",
    "gn:asciiname":"Bagha Chhapar",
    "gn:country_code":"IN",
    "gn:dem":75,
    "gn:feature_class":"P",
    "gn:feature_code":"PPL",
    "gn:name":"B\u0101gha Chh\u0101par",
    "gn:population":0,
    "gn:timezone":"Asia/Kolkata",
    "iso:country":"IN",
    "ks:ks_alt_nam":"B\u0101gha Chh\u0101par",
    "ks:ks_name":"Bagha Chhapar",
    "ks:ks_pop":588,
    "ks:ks_type":"VILLAGE",
    "ks:ks_uagg_main":0,
    "name:eng_x_preferred":[
        "Bagha Chhapar"
    ],
    "name:eng_x_variant":[
        "B\u0101gha Chh\u0101par"
    ],
    "wof:name":"Bagha Chhapar",
    "wof:placetype":"neighbourhood",
    "wof:population":588
},
  "geometry": {"coordinates":[84.15337700000001,26.333398],"type":"Point"}
}