{
  "type": "Feature",
  "properties": {
    "gn:admin1_code":"12.0",
    "gn:admin2_code":"1.0",
    "gn:asciiname":"Dudkull",
    "gn:country_code":"IN",
    "gn:dem":2606,
    "gn:feature_class":"P",
    "gn:feature_code":"PPL",
    "gn:name":"Dudkull",
    "gn:population":0,
    "gn:timezone":"Asia/Kolkata",
    "iso:country":"IN",
    "wof:name":"Dudkull",
    "wof:placetype":"locality"
},
  "geometry": {"coordinates":[74.40429,34.61136],"type":"Point"}
}