{
  "type": "Feature",
  "properties": {
    "gn:admin1_code":"36.0",
    "gn:admin2_code":"190.0",
    "gn:asciiname":"Lohari Bari",
    "gn:country_code":"IN",
    "gn:dem":74,
    "gn:feature_class":"P",
    "gn:feature_code":"PPL",
    "gn:name":"Loh\u0101ri B\u0101ri",
    "gn:population":0,
    "gn:timezone":"Asia/Kolkata",
    "iso:country":"IN",
    "wof:name":"Lohari Bari",
    "wof:placetype":"locality"
},
  "geometry": {"coordinates":[84.10696,26.33898],"type":"Point"}
}