{
  "type": "Feature",
  "properties": {
    "iso:country":"IN",
    "ks:ks_name":"Banakalo",
    "ks:ks_pop":98,
    "ks:ks_type":"HABITATION",
    "name:eng_x_preferred":[
        "Banakalo"
    ],
    "wof:name":"Banakalo",
    "wof:placetype":"locality",
    "wof:population":98
},
  "geometry": {"coordinates":[84.788054,21.471784],"type":"Point"}
}