{
  "type": "Feature",
  "properties": {
    "iso:country":"IN",
    "ks:ks_alt_nam":"SAMLATO",
    "ks:ks_name":"Samlato",
    "ks:ks_pop":206,
    "ks:ks_type":"HABITATION",
    "name:eng_x_preferred":[
        "Samlato"
    ],
    "wof:name":"Samlato",
    "wof:placetype":"locality",
    "wof:population":206
},
  "geometry": {"coordinates":[87.05010900000001,24.313056],"type":"Point"}
}