{
  "type": "Feature",
  "properties": {
    "iso:country":"IN",
    "ks:ks_name":"Bhadia Chuk",
    "ks:ks_pop":382,
    "ks:ks_type":"VILLAGE",
    "ks:ks_uagg_main":0,
    "name:eng_x_preferred":[
        "Bhadia Chuk"
    ],
    "wof:name":"Bhadia Chuk",
    "wof:placetype":"neighbourhood",
    "wof:population":382
},
  "geometry": {"coordinates":[94.675079,27.392203],"type":"Point"}
}