{
  "type": "Feature",
  "properties": {
    "iso:country":"IN",
    "ks:ks_alt_nam":"Chaniya gaon",
    "ks:ks_name":"Chaniya Gaon",
    "ks:ks_pop":21,
    "ks:ks_type":"HABITATION",
    "name:eng_x_preferred":[
        "Chaniya Gaon"
    ],
    "wof:name":"Chaniya Gaon",
    "wof:placetype":"locality",
    "wof:population":21
},
  "geometry": {"coordinates":[80.098947,29.621759],"type":"Point"}
}