{
  "type": "Feature",
  "properties": {
    "gn:admin1_code":"21.0",
    "gn:admin2_code":"389.0",
    "gn:asciiname":"Dangusingi",
    "gn:country_code":"IN",
    "gn:dem":321,
    "gn:feature_class":"P",
    "gn:feature_code":"PPL",
    "gn:name":"Dangusingi",
    "gn:population":0,
    "gn:timezone":"Asia/Kolkata",
    "iso:country":"IN",
    "ks:ks_name":"Dangasing",
    "ks:ks_pop":211,
    "ks:ks_type":"VILLAGE",
    "name:eng_x_preferred":[
        "Dangasing"
    ],
    "name:eng_x_variant":[
        "Dangusingi"
    ],
    "wof:name":"Dangasing",
    "wof:placetype":"locality",
    "wof:population":211
},
  "geometry": {"coordinates":[83.984037,18.990761],"type":"Point"}
}