{
  "type": "Feature",
  "properties": {
    "iso:country":"IN",
    "ks:ks_name":"Ikbalganj",
    "ks:ks_pop":66,
    "ks:ks_type":"VILLAGE",
    "name:eng_x_preferred":[
        "Ikbalganj"
    ],
    "wof:name":"Ikbalganj",
    "wof:placetype":"locality",
    "wof:population":66
},
  "geometry": {"coordinates":[78.16136299999999,23.638945],"type":"Point"}
}