{
  "type": "Feature",
  "properties": {
    "gn:admin1_code":"36",
    "gn:admin2_code":"154.0",
    "gn:asciiname":"Jagdishour",
    "gn:country_code":"IN",
    "gn:dem":136,
    "gn:feature_class":"P",
    "gn:feature_code":"PPL",
    "gn:name":"Jagdishour",
    "gn:population":0,
    "gn:timezone":"Asia/Kolkata",
    "iso:country":"IN",
    "wof:name":"Jagdishour",
    "wof:placetype":"locality"
},
  "geometry": {"coordinates":[80.82195,27.40034],"type":"Point"}
}