{
  "type": "Feature",
  "properties": {
    "gn:admin1_code":"10.0",
    "gn:admin2_code":"75.0",
    "gn:asciiname":"Purbayakhera",
    "gn:country_code":"IN",
    "gn:dem":239,
    "gn:feature_class":"P",
    "gn:feature_code":"PPL",
    "gn:name":"Purbay\u0101khera",
    "gn:population":0,
    "gn:timezone":"Asia/Kolkata",
    "iso:country":"IN",
    "name:und_x_variant":[
        "Purbay\u0101khera",
        "Dharamgarh"
    ],
    "wof:name":"Purbayakhera",
    "wof:placetype":"locality"
},
  "geometry": {"coordinates":[76.80519,29.4678],"type":"Point"}
}