{
  "type": "Feature",
  "properties": {
    "gn:admin1_code":"34.0",
    "gn:admin2_code":"221.0",
    "gn:asciiname":"Mathurapur",
    "gn:country_code":"IN",
    "gn:dem":54,
    "gn:feature_class":"P",
    "gn:feature_code":"PPL",
    "gn:name":"Mathur\u0101pur",
    "gn:population":0,
    "gn:timezone":"Asia/Kolkata",
    "iso:country":"IN",
    "ks:ks_name":"Mathurapur",
    "ks:ks_pop":5574,
    "ks:ks_type":"VILLAGE",
    "name:eng_x_preferred":[
        "Mathurapur"
    ],
    "wof:name":"Mathurapur",
    "wof:placetype":"locality",
    "wof:population":5574
},
  "geometry": {"coordinates":[85.790375,25.877089],"type":"Point"}
}