{
  "type": "Feature",
  "properties": {
    "iso:country":"IN",
    "ks:ks_name":"Rojhad",
    "ks:ks_pop":2436,
    "ks:ks_type":"VILLAGE",
    "ks:ks_uagg_main":0,
    "name:eng_x_preferred":[
        "Rojhad"
    ],
    "wof:name":"Rojhad",
    "wof:placetype":"neighbourhood",
    "wof:population":2436
},
  "geometry": {"coordinates":[73.07852800000001,23.336944],"type":"Point"}
}