{
  "type": "Feature",
  "properties": {
    "gn:admin1_code":"36.0",
    "gn:admin2_code":"149.0",
    "gn:asciiname":"Anandipur",
    "gn:country_code":"IN",
    "gn:dem":172,
    "gn:feature_class":"P",
    "gn:feature_code":"PPL",
    "gn:name":"Anandipur",
    "gn:population":0,
    "gn:timezone":"Asia/Kolkata",
    "iso:country":"IN",
    "ks:ks_name":"Anandi Pur",
    "ks:ks_pop":1224,
    "ks:ks_type":"VILLAGE",
    "ks:ks_uagg_main":0,
    "name:eng_x_preferred":[
        "Anandi Pur"
    ],
    "wof:name":"Anandi Pur",
    "wof:placetype":"locality",
    "wof:population":1224
},
  "geometry": {"coordinates":[78.769777,28.074004],"type":"Point"}
}