{
  "type": "Feature",
  "properties": {
    "gn:admin1_code":"9.0",
    "gn:admin2_code":"477.0",
    "gn:asciiname":"Jamjodhpur",
    "gn:country_code":"IN",
    "gn:dem":97,
    "gn:feature_class":"P",
    "gn:feature_code":"PPL",
    "gn:name":"Jamjodhpur",
    "gn:population":0,
    "gn:timezone":"Asia/Kolkata",
    "iso:country":"IN",
    "wof:name":"Jamjodhpur",
    "wof:placetype":"locality"
},
  "geometry": {"coordinates":[70.03570000000001,21.90219],"type":"Point"}
}