{
  "type": "Feature",
  "properties": {
    "iso:country":"IN",
    "ks:ks_name":"Pipla Falia",
    "ks:ks_pop":218,
    "ks:ks_type":"HABITATION",
    "name:eng_x_preferred":[
        "Pipla Falia"
    ],
    "wof:name":"Pipla Falia",
    "wof:placetype":"locality",
    "wof:population":218
},
  "geometry": {"coordinates":[73.106306,20.916083],"type":"Point"}
}