{
  "type": "Feature",
  "properties": {
    "iso:country":"IN",
    "ks:ks_alt_nam":"galijeddi",
    "ks:ks_name":"Galijeddi",
    "ks:ks_pop":13,
    "ks:ks_type":"HABITATION",
    "name:eng_x_preferred":[
        "Galijeddi"
    ],
    "wof:name":"Galijeddi",
    "wof:placetype":"locality",
    "wof:population":13
},
  "geometry": {"coordinates":[74.712654,14.907404],"type":"Point"}
}