{
  "type": "Feature",
  "properties": {
    "gn:admin1_code":"36.0",
    "gn:admin2_code":"166.0",
    "gn:asciiname":"Garha",
    "gn:country_code":"IN",
    "gn:dem":175,
    "gn:feature_class":"P",
    "gn:feature_code":"PPL",
    "gn:name":"Garh\u0101",
    "gn:population":0,
    "gn:timezone":"Asia/Kolkata",
    "iso:country":"IN",
    "name:cat_x_preferred":[
        "Garha"
    ],
    "name:und_x_variant":[
        "Garh\u0101",
        "Garha"
    ],
    "wof:name":"Garha",
    "wof:placetype":"locality"
},
  "geometry": {"coordinates":[79.18543000000003,25.49893],"type":"Point"}
}