{
  "type": "Feature",
  "properties": {
    "gn:admin1_code":"35",
    "gn:admin2_code":"430.0",
    "gn:asciiname":"Dakwartola",
    "gn:country_code":"IN",
    "gn:dem":309,
    "gn:feature_class":"P",
    "gn:feature_code":"PPL",
    "gn:name":"Dakw\u0101rtola",
    "gn:population":0,
    "gn:timezone":"Asia/Kolkata",
    "iso:country":"IN",
    "ks:ks_alt_nam":"Dakw\u0101rtola",
    "ks:ks_name":"Dakwartola",
    "ks:ks_type":"VILLAGE",
    "ks:ks_uagg_main":0,
    "name:eng_x_preferred":[
        "Dakwartola"
    ],
    "name:eng_x_variant":[
        "Dakw\u0101rtola"
    ],
    "wof:name":"Dakwartola",
    "wof:placetype":"neighbourhood"
},
  "geometry": {"coordinates":[81.306406,24.487487],"type":"Point"}
}