{
  "type": "Feature",
  "properties": {
    "gn:admin1_code":"36",
    "gn:admin2_code":"146.0",
    "gn:asciiname":"Garhwar",
    "gn:country_code":"IN",
    "gn:dem":149,
    "gn:feature_class":"P",
    "gn:feature_code":"PPL",
    "gn:name":"Garhw\u0101r",
    "gn:population":0,
    "gn:timezone":"Asia/Kolkata",
    "iso:country":"IN",
    "ks:ks_name":"Garhwar",
    "ks:ks_pop":1726,
    "ks:ks_type":"VILLAGE",
    "name:eng_x_preferred":[
        "Garhwar"
    ],
    "wof:name":"Garhwar",
    "wof:placetype":"locality",
    "wof:population":1726
},
  "geometry": {"coordinates":[78.692438,26.885497],"type":"Point"}
}