{
  "type": "Feature",
  "properties": {
    "iso:country":"IN",
    "ks:ks_name":"Tarakiya",
    "ks:ks_pop":1077,
    "ks:ks_type":"VILLAGE",
    "name:eng_x_preferred":[
        "Tarakiya"
    ],
    "wof:name":"Tarakiya",
    "wof:placetype":"locality",
    "wof:population":1077
},
  "geometry": {"coordinates":[71.14658300000001,22.49425],"type":"Point"}
}