{
  "type": "Feature",
  "properties": {
    "gn:admin1_code":"37.0",
    "gn:admin2_code":"417.0",
    "gn:asciiname":"Gongla",
    "gn:country_code":"IN",
    "gn:dem":345,
    "gn:feature_class":"P",
    "gn:feature_code":"PPLL",
    "gn:name":"Gongla",
    "gn:population":0,
    "gn:timezone":"Asia/Kolkata",
    "iso:country":"IN",
    "ks:ks_name":"Gongla",
    "ks:ks_pop":125,
    "ks:ks_type":"VILLAGE",
    "name:eng_x_preferred":[
        "Gongla"
    ],
    "wof:name":"Gongla",
    "wof:placetype":"locality",
    "wof:population":125
},
  "geometry": {"coordinates":[81.05426199999999,18.782488],"type":"Point"}
}