{
  "type": "Feature",
  "properties": {
    "iso:country":"IN",
    "ks:ks_name":"Kigglu Kuthodi",
    "ks:ks_pop":149,
    "ks:ks_type":"HABITATION",
    "ks:ks_uagg_main":0,
    "name:eng_x_preferred":[
        "Kigglu Kuthodi"
    ],
    "wof:name":"Kigglu Kuthodi",
    "wof:placetype":"neighbourhood",
    "wof:population":149
},
  "geometry": {"coordinates":[75.750461,12.313507],"type":"Point"}
}