{
  "type": "Feature",
  "properties": {
    "iso:country":"IN",
    "ks:ks_name":"Sendur",
    "ks:ks_pop":326,
    "ks:ks_type":"VILLAGE",
    "name:eng_x_preferred":[
        "Sendur"
    ],
    "wof:name":"Sendur",
    "wof:placetype":"locality",
    "wof:population":326
},
  "geometry": {"coordinates":[84.511555,23.43039],"type":"Point"}
}