{
  "type": "Feature",
  "properties": {
    "gn:admin1_code":"23.0",
    "gn:admin2_code":"44.0",
    "gn:asciiname":"Jandwala Charhat Singh",
    "gn:country_code":"IN",
    "gn:dem":196,
    "gn:feature_class":"P",
    "gn:feature_code":"PPL",
    "gn:name":"Jandw\u0101la Charhat Singh",
    "gn:population":0,
    "gn:timezone":"Asia/Kolkata",
    "iso:country":"IN",
    "wof:name":"Jandwala Charhat Singh",
    "wof:placetype":"neighbourhood"
},
  "geometry": {"coordinates":[74.53261999999999,30.206],"type":"Point"}
}