{
  "type": "Feature",
  "properties": {
    "iso:country":"IN",
    "ks:ks_name":"Velathirankollai",
    "ks:ks_pop":332,
    "ks:ks_type":"HABITATION",
    "name:eng_x_preferred":[
        "Velathirankollai"
    ],
    "wof:name":"Velathirankollai",
    "wof:placetype":"locality",
    "wof:population":332
},
  "geometry": {"coordinates":[79.031891,10.4645],"type":"Point"}
}