{
  "type": "Feature",
  "properties": {
    "iso:country":"IN",
    "ks:ks_name":"Bhagan Ka Tola",
    "ks:ks_pop":158,
    "ks:ks_type":"HABITATION",
    "name:eng_x_preferred":[
        "Bhagan Ka Tola"
    ],
    "wof:name":"Bhagan Ka Tola",
    "wof:placetype":"locality",
    "wof:population":158
},
  "geometry": {"coordinates":[84.28795700000001,26.720261],"type":"Point"}
}