{
  "type": "Feature",
  "properties": {
    "iso:country":"IN",
    "ks:ks_alt_nam":"Bang\u0101li",
    "ks:ks_name":"Bangali",
    "ks:ks_type":"VILLAGE",
    "name:eng_x_preferred":[
        "Bangali"
    ],
    "name:eng_x_variant":[
        "Bang\u0101li"
    ],
    "wof:name":"Bangali",
    "wof:placetype":"locality"
},
  "geometry": {"coordinates":[79.46935000000001,30.193528],"type":"Point"}
}