{
  "type": "Feature",
  "properties": {
    "iso:country":"IN",
    "ks:ks_alt_nam":"JUBLA",
    "ks:ks_name":"Jubla",
    "ks:ks_pop":468,
    "ks:ks_type":"HABITATION",
    "name:eng_x_preferred":[
        "Jubla"
    ],
    "wof:name":"Jubla",
    "wof:placetype":"locality",
    "wof:population":468
},
  "geometry": {"coordinates":[85.305044,23.719189],"type":"Point"}
}