{
  "type": "Feature",
  "properties": {
    "gn:admin1_code":"39.0",
    "gn:admin2_code":"061",
    "gn:asciiname":"Kund",
    "gn:country_code":"IN",
    "gn:dem":834,
    "gn:feature_class":"P",
    "gn:feature_code":"PPL",
    "gn:name":"Kund",
    "gn:population":0,
    "gn:timezone":"Asia/Kolkata",
    "iso:country":"IN",
    "ks:ks_name":"Kund",
    "ks:ks_pop":361,
    "ks:ks_type":"VILLAGE",
    "name:eng_x_preferred":[
        "Kund"
    ],
    "name:fas_x_preferred":[
        "\u06a9\u0646\u062f"
    ],
    "name:urd_x_preferred":[
        "\u06a9\u0646\u0688"
    ],
    "wof:name":"Kund",
    "wof:placetype":"locality",
    "wof:population":361
},
  "geometry": {"coordinates":[78.698944,29.976167],"type":"Point"}
}