{
  "type": "Feature",
  "properties": {
    "iso:country":"IN",
    "ks:ks_name":"Silani Basti",
    "ks:ks_pop":108,
    "ks:ks_type":"HABITATION",
    "ks:ks_uagg_main":0,
    "name:eng_x_preferred":[
        "Silani Basti"
    ],
    "wof:name":"Silani Basti",
    "wof:placetype":"locality",
    "wof:population":108
},
  "geometry": {"coordinates":[91.87937599999999,26.150827],"type":"Point"}
}