{
  "type": "Feature",
  "properties": {
    "gn:admin1_code":"13.0",
    "gn:admin2_code":"593.0",
    "gn:asciiname":"Tottazhiyam",
    "gn:country_code":"IN",
    "gn:dem":20,
    "gn:feature_class":"P",
    "gn:feature_code":"PPL",
    "gn:name":"T\u014dttazhiyam",
    "gn:population":0,
    "gn:timezone":"Asia/Kolkata",
    "iso:country":"IN",
    "ks:ks_alt_nam":"THOTTAZHIYAM",
    "ks:ks_name":"Thottazhiyam",
    "ks:ks_pop":1531,
    "ks:ks_type":"HABITATION",
    "name:eng_x_preferred":[
        "Thottazhiyam"
    ],
    "name:eng_x_variant":[
        "Tottazhiyam"
    ],
    "wof:name":"Thottazhiyam",
    "wof:placetype":"locality",
    "wof:population":1531
},
  "geometry": {"coordinates":[76.03833400000001,10.831049],"type":"Point"}
}