{
  "type": "Feature",
  "properties": {
    "iso:country":"IN",
    "ks:ks_alt_nam":"POSI",
    "ks:ks_name":"Posi",
    "ks:ks_pop":440,
    "ks:ks_type":"HABITATION",
    "ks:ks_uagg_main":0,
    "name:eng_x_preferred":[
        "Posi"
    ],
    "wof:name":"Posi",
    "wof:placetype":"locality",
    "wof:population":440
},
  "geometry": {"coordinates":[82.74811,25.276533],"type":"Point"}
}