{
  "type": "Feature",
  "properties": {
    "gn:admin1_code":"35.0",
    "gn:admin2_code":"457.0",
    "gn:asciiname":"Parrapur",
    "gn:country_code":"IN",
    "gn:dem":540,
    "gn:feature_class":"P",
    "gn:feature_code":"PPL",
    "gn:name":"Parr\u0101pur",
    "gn:population":0,
    "gn:timezone":"Asia/Kolkata",
    "iso:country":"IN",
    "ks:ks_alt_nam":"Parr\u0101pur",
    "ks:ks_name":"Parrapur",
    "ks:ks_pop":463,
    "ks:ks_type":"VILLAGE",
    "name:eng_x_preferred":[
        "Parrapur"
    ],
    "name:eng_x_variant":[
        "Parr\u0101pur"
    ],
    "wof:name":"Parrapur",
    "wof:placetype":"locality",
    "wof:population":463
},
  "geometry": {"coordinates":[80.54479499999999,22.220335],"type":"Point"}
}