{
  "type": "Feature",
  "properties": {
    "iso:country":"IN",
    "ks:ks_name":"Pakartoli",
    "ks:ks_pop":271,
    "ks:ks_type":"HABITATION",
    "name:eng_x_preferred":[
        "Pakartoli"
    ],
    "wof:name":"Pakartoli",
    "wof:placetype":"locality",
    "wof:population":271
},
  "geometry": {"coordinates":[84.07225699999999,22.731915],"type":"Point"}
}