{
  "type": "Feature",
  "properties": {
    "iso:country":"IN",
    "ks:ks_alt_nam":"gondu guda",
    "ks:ks_name":"Gondu Guda",
    "ks:ks_pop":117,
    "ks:ks_type":"HABITATION",
    "name:eng_x_preferred":[
        "Gondu Guda"
    ],
    "wof:name":"Gondu Guda",
    "wof:placetype":"locality",
    "wof:population":117
},
  "geometry": {"coordinates":[78.980946,19.164007],"type":"Point"}
}