{
  "type": "Feature",
  "properties": {
    "iso:country":"IN",
    "ks:ks_name":"Bhar Tola",
    "ks:ks_pop":110,
    "ks:ks_type":"HABITATION",
    "name:eng_x_preferred":[
        "Bhar Tola"
    ],
    "wof:name":"Bhar Tola",
    "wof:placetype":"locality",
    "wof:population":110
},
  "geometry": {"coordinates":[84.144598,26.070054],"type":"Point"}
}