{
  "type": "Feature",
  "properties": {
    "iso:country":"IN",
    "ks:ks_name":"Randhariguda",
    "ks:ks_pop":408,
    "ks:ks_type":"HABITATION",
    "ks:ks_uagg_main":0,
    "name:eng_x_preferred":[
        "Randhariguda"
    ],
    "wof:name":"Randhariguda",
    "wof:placetype":"neighbourhood",
    "wof:population":408
},
  "geometry": {"coordinates":[82.451539,19.163441],"type":"Point"}
}