{
  "type": "Feature",
  "properties": {
    "iso:country":"IN",
    "ks:ks_name":"Manjhipara",
    "ks:ks_pop":107,
    "ks:ks_type":"HABITATION",
    "name:eng_x_preferred":[
        "Manjhipara"
    ],
    "wof:name":"Manjhipara",
    "wof:placetype":"locality",
    "wof:population":107
},
  "geometry": {"coordinates":[80.945193,20.009574],"type":"Point"}
}