{
  "type": "Feature",
  "properties": {
    "iso:country":"IN",
    "ks:ks_name":"Manwan",
    "ks:ks_pop":328,
    "ks:ks_type":"HABITATION",
    "name:eng_x_preferred":[
        "Manwan"
    ],
    "wof:name":"Manwan",
    "wof:placetype":"locality",
    "wof:population":328
},
  "geometry": {"coordinates":[72.760778,22.379028],"type":"Point"}
}