{
  "type": "Feature",
  "properties": {
    "iso:country":"IN",
    "ks:ks_name":"Sathpur",
    "ks:ks_pop":829,
    "ks:ks_type":"VILLAGE",
    "name:eng_x_preferred":[
        "Sathpur"
    ],
    "wof:name":"Sathpur",
    "wof:placetype":"locality",
    "wof:population":829
},
  "geometry": {"coordinates":[74.474531,24.122478],"type":"Point"}
}