{
  "type": "Feature",
  "properties": {
    "iso:country":"IN",
    "ks:ks_name":"Kudahallupete",
    "ks:ks_pop":103,
    "ks:ks_type":"HABITATION",
    "name:eng_x_preferred":[
        "Kudahallupete"
    ],
    "wof:name":"Kudahallupete",
    "wof:placetype":"locality",
    "wof:population":103
},
  "geometry": {"coordinates":[75.54789,13.129485],"type":"Point"}
}