{
  "type": "Feature",
  "properties": {
    "iso:country":"IN",
    "ks:ks_name":"Dubaulia",
    "ks:ks_type":"VILLAGE",
    "name:eng_x_preferred":[
        "Dubaulia"
    ],
    "wof:name":"Dubaulia",
    "wof:placetype":"locality"
},
  "geometry": {"coordinates":[83.33060399999999,25.371825],"type":"Point"}
}