{
  "type": "Feature",
  "properties": {
    "gn:admin1_code":"35",
    "gn:admin2_code":"430.0",
    "gn:asciiname":"Marpha",
    "gn:country_code":"IN",
    "gn:dem":319,
    "gn:feature_class":"P",
    "gn:feature_code":"PPL",
    "gn:name":"Marpha",
    "gn:population":0,
    "gn:timezone":"Asia/Kolkata",
    "iso:country":"IN",
    "name:ceb_x_preferred":[
        "Marpha"
    ],
    "name:deu_x_preferred":[
        "Marpha"
    ],
    "name:dty_x_preferred":[
        "\u092e\u093e\u0930\u094d\u092b\u093e"
    ],
    "name:fra_x_preferred":[
        "Marpha"
    ],
    "name:jpn_x_preferred":[
        "\u30de\u30eb\u30d5\u30a1"
    ],
    "name:msa_x_preferred":[
        "Marpha"
    ],
    "name:nep_x_preferred":[
        "\u092e\u093e\u0930\u094d\u092b\u093e"
    ],
    "name:new_x_preferred":[
        "\u092e\u093e\u0930\u094d\u092b\u093e"
    ],
    "name:pol_x_preferred":[
        "Marpha"
    ],
    "name:por_x_preferred":[
        "Marpha"
    ],
    "wof:name":"Marpha",
    "wof:placetype":"locality"
},
  "geometry": {"coordinates":[81.56570000000001,24.80994],"type":"Point"}
}