{
  "type": "Feature",
  "properties": {
    "gn:admin1_code":"39.0",
    "gn:admin2_code":"64.0",
    "gn:asciiname":"Mehalkhali",
    "gn:country_code":"IN",
    "gn:dem":1940,
    "gn:feature_class":"P",
    "gn:feature_code":"PPL",
    "gn:name":"Mehalkh\u0101li",
    "gn:population":0,
    "gn:timezone":"Asia/Kolkata",
    "iso:country":"IN",
    "wof:name":"Mehalkhali",
    "wof:placetype":"locality"
},
  "geometry": {"coordinates":[79.43243000000002,29.84252],"type":"Point"}
}