{
  "type": "Feature",
  "properties": {
    "iso:country":"IN",
    "ks:ks_name":"Lahar",
    "ks:ks_pop":106,
    "ks:ks_type":"HABITATION",
    "name:eng_x_preferred":[
        "Lahar"
    ],
    "wof:name":"Lahar",
    "wof:placetype":"locality",
    "wof:population":106
},
  "geometry": {"coordinates":[79.06142199999999,24.190668],"type":"Point"}
}