{
  "type": "Feature",
  "properties": {
    "iso:country":"IN",
    "ks:ks_name":"Bhuiya Tola",
    "ks:ks_pop":111,
    "ks:ks_type":"HABITATION",
    "name:eng_x_preferred":[
        "Bhuiya Tola"
    ],
    "wof:name":"Bhuiya Tola",
    "wof:placetype":"locality",
    "wof:population":111
},
  "geometry": {"coordinates":[83.768687,23.975327],"type":"Point"}
}