{
  "type": "Feature",
  "properties": {
    "iso:country":"IN",
    "ks:ks_name":"Bisagnimutt",
    "ks:ks_pop":99,
    "ks:ks_type":"HABITATION",
    "name:eng_x_preferred":[
        "Bisagnimutt"
    ],
    "wof:name":"Bisagnimutt",
    "wof:placetype":"locality",
    "wof:population":99
},
  "geometry": {"coordinates":[75.74762200000001,13.44346],"type":"Point"}
}