{
  "type": "Feature",
  "properties": {
    "iso:country":"IN",
    "ks:ks_name":"Tagotta",
    "ks:ks_pop":278,
    "ks:ks_type":"HABITATION",
    "name:eng_x_preferred":[
        "Tagotta"
    ],
    "wof:name":"Tagotta",
    "wof:placetype":"locality",
    "wof:population":278
},
  "geometry": {"coordinates":[74.423788,14.352513],"type":"Point"}
}