{
  "type": "Feature",
  "properties": {
    "iso:country":"IN",
    "ks:ks_name":"Kodeli",
    "ks:ks_pop":331,
    "ks:ks_type":"VILLAGE",
    "name:eng_x_preferred":[
        "Kodeli"
    ],
    "wof:name":"Kodeli",
    "wof:placetype":"locality",
    "wof:population":331
},
  "geometry": {"coordinates":[82.65137900000001,18.156801],"type":"Point"}
}