{
  "type": "Feature",
  "properties": {
    "iso:country":"IN",
    "ks:ks_name":"Pipali",
    "ks:ks_pop":159,
    "ks:ks_type":"VILLAGE",
    "name:eng_x_preferred":[
        "Pipali"
    ],
    "wof:name":"Pipali",
    "wof:placetype":"locality",
    "wof:population":159
},
  "geometry": {"coordinates":[83.795165,20.289396],"type":"Point"}
}