{
  "type": "Feature",
  "properties": {
    "iso:country":"IN",
    "ks:ks_name":"Isanpur",
    "ks:ks_pop":1468,
    "ks:ks_type":"VILLAGE",
    "name:eng_x_preferred":[
        "Isanpur"
    ],
    "wof:name":"Isanpur",
    "wof:placetype":"locality",
    "wof:population":1468
},
  "geometry": {"coordinates":[88.090518,24.158582],"type":"Point"}
}