{
  "type": "Feature",
  "properties": {
    "iso:country":"IN",
    "ks:ks_name":"Dakshin Para",
    "ks:ks_pop":1410,
    "ks:ks_type":"HABITATION",
    "name:eng_x_preferred":[
        "Dakshin Para"
    ],
    "wof:name":"Dakshin Para",
    "wof:placetype":"locality",
    "wof:population":1410
},
  "geometry": {"coordinates":[88.31217599999999,21.72467],"type":"Point"}
}