{
  "type": "Feature",
  "properties": {
    "gn:admin1_code":"19.0",
    "gn:admin2_code":"569.0",
    "gn:asciiname":"Koralu",
    "gn:country_code":"IN",
    "gn:dem":21,
    "gn:feature_class":"P",
    "gn:feature_code":"PPL",
    "gn:name":"Koralu",
    "gn:population":0,
    "gn:timezone":"Asia/Kolkata",
    "iso:country":"IN",
    "ks:ks_name":"Korala",
    "ks:ks_pop":240,
    "ks:ks_type":"HABITATION",
    "name:eng_x_preferred":[
        "Korala"
    ],
    "name:eng_x_variant":[
        "Koralu"
    ],
    "wof:name":"Korala",
    "wof:placetype":"locality",
    "wof:population":240
},
  "geometry": {"coordinates":[74.801558,13.61692],"type":"Point"}
}