{
  "type": "Feature",
  "properties": {
    "gn:admin1_code":"36",
    "gn:admin2_code":"185.0",
    "gn:asciiname":"Atroh Khas Ramanpur",
    "gn:country_code":"IN",
    "gn:dem":99,
    "gn:feature_class":"P",
    "gn:feature_code":"PPL",
    "gn:name":"Atroh Kh\u0101s R\u0101m\u0101npur",
    "gn:population":0,
    "gn:timezone":"Asia/Kolkata",
    "iso:country":"IN",
    "wof:name":"Atroh Khas Ramanpur",
    "wof:placetype":"neighbourhood"
},
  "geometry": {"coordinates":[82.53804,26.91997],"type":"Point"}
}