{
  "type": "Feature",
  "properties": {
    "iso:country":"IN",
    "ks:ks_name":"Raghoram Patti Mafi",
    "ks:ks_pop":333,
    "ks:ks_type":"VILLAGE",
    "ks:ks_uagg_main":0,
    "name:eng_x_preferred":[
        "Raghoram Patti Mafi"
    ],
    "wof:name":"Raghoram Patti Mafi",
    "wof:placetype":"neighbourhood",
    "wof:population":333
},
  "geometry": {"coordinates":[82.584013,25.487827],"type":"Point"}
}