{
  "type": "Feature",
  "properties": {
    "iso:country":"IN",
    "ks:ks_name":"Basavanahally",
    "ks:ks_pop":641,
    "ks:ks_type":"HABITATION",
    "name:eng_x_preferred":[
        "Basavanahally"
    ],
    "wof:name":"Basavanahally",
    "wof:placetype":"locality",
    "wof:population":641
},
  "geometry": {"coordinates":[76.92671199999999,13.947583],"type":"Point"}
}