{
  "type": "Feature",
  "properties": {
    "iso:country":"IN",
    "ks:ks_name":"Tapon",
    "ks:ks_pop":95,
    "ks:ks_type":"VILLAGE",
    "name:eng_x_preferred":[
        "Tapon"
    ],
    "wof:name":"Tapon",
    "wof:placetype":"locality",
    "wof:population":95
},
  "geometry": {"coordinates":[79.473569,30.494761],"type":"Point"}
}