{
  "type": "Feature",
  "properties": {
    "gn:admin1_code":"24",
    "gn:admin2_code":"105.0",
    "gn:asciiname":"Burana",
    "gn:country_code":"IN",
    "gn:dem":185,
    "gn:feature_class":"P",
    "gn:feature_code":"PPL",
    "gn:name":"Bur\u0101na",
    "gn:population":0,
    "gn:timezone":"Asia/Kolkata",
    "iso:country":"IN",
    "name:ceb_x_preferred":[
        "Burana"
    ],
    "name:deu_x_preferred":[
        "Burana"
    ],
    "name:swe_x_preferred":[
        "Burana"
    ],
    "wof:name":"Burana",
    "wof:placetype":"locality"
},
  "geometry": {"coordinates":[77.5569,27.06828],"type":"Point"}
}