{
  "type": "Feature",
  "properties": {
    "gn:admin1_code":"11.0",
    "gn:admin2_code":"32.0",
    "gn:asciiname":"Dabil",
    "gn:country_code":"IN",
    "gn:dem":1229,
    "gn:feature_class":"P",
    "gn:feature_code":"PPL",
    "gn:name":"D\u0101bil",
    "gn:population":0,
    "gn:timezone":"Asia/Kolkata",
    "iso:country":"IN",
    "name:swa_x_preferred":[
        "Dabil"
    ],
    "wof:name":"Dabil",
    "wof:placetype":"locality"
},
  "geometry": {"coordinates":[77.72994,30.63288],"type":"Point"}
}