{
  "type": "Feature",
  "properties": {
    "iso:country":"IN",
    "ks:ks_alt_nam":"Katattukulam north",
    "ks:ks_name":"Katattukulam North",
    "ks:ks_pop":398,
    "ks:ks_type":"HABITATION",
    "name:eng_x_preferred":[
        "Katattukulam North"
    ],
    "wof:name":"Katattukulam North",
    "wof:placetype":"locality",
    "wof:population":398
},
  "geometry": {"coordinates":[76.67906499999999,10.078214],"type":"Point"}
}