{
  "type": "Feature",
  "properties": {
    "gn:admin1_code":"35",
    "gn:admin2_code":"443.0",
    "gn:asciiname":"Kurwai",
    "gn:country_code":"IN",
    "gn:dem":503,
    "gn:feature_class":"P",
    "gn:feature_code":"PPL",
    "gn:name":"Kurw\u0101i",
    "gn:population":0,
    "gn:timezone":"Asia/Kolkata",
    "iso:country":"IN",
    "name:ben_x_preferred":[
        "\u0995\u09c1\u09b0\u0993\u09af\u09bc\u09be\u0987"
    ],
    "name:bpy_x_preferred":[
        "\u0995\u09c1\u09b0\u09f1\u09be\u0987"
    ],
    "name:cat_x_preferred":[
        "Kurwai"
    ],
    "name:deu_x_preferred":[
        "Kurwai"
    ],
    "name:ita_x_preferred":[
        "Kurwai"
    ],
    "name:mlg_x_preferred":[
        "Kurwai"
    ],
    "name:msa_x_preferred":[
        "Kurwai"
    ],
    "name:new_x_preferred":[
        "\u0915\u0941\u0930\u094d\u0935\u093e\u0908"
    ],
    "name:nld_x_preferred":[
        "Kurwai"
    ],
    "name:pol_x_preferred":[
        "Kurwai"
    ],
    "name:por_x_preferred":[
        "Kurwai"
    ],
    "name:swe_x_preferred":[
        "Kurwai"
    ],
    "name:vie_x_preferred":[
        "Kurwai"
    ],
    "name:zho_x_preferred":[
        "\u5e93\u5c14\u74e6\u4f0a"
    ],
    "wof:name":"Kurwai",
    "wof:placetype":"locality"
},
  "geometry": {"coordinates":[77.50511,24.21609],"type":"Point"}
}