{
  "type": "Feature",
  "properties": {
    "gn:admin1_code":"24",
    "gn:admin2_code":"117.0",
    "gn:asciiname":"Zawal",
    "gn:country_code":"IN",
    "gn:dem":236,
    "gn:feature_class":"P",
    "gn:feature_code":"PPL",
    "gn:name":"Z\u0101wal",
    "gn:population":0,
    "gn:timezone":"Asia/Kolkata",
    "iso:country":"IN",
    "name:und_x_variant":[
        "J\u0101w\u0101l",
        "Z\u0101wal"
    ],
    "wof:name":"Zawal",
    "wof:placetype":"locality"
},
  "geometry": {"coordinates":[72.74858,24.99185],"type":"Point"}
}