{
  "type": "Feature",
  "properties": {
    "iso:country":"IN",
    "ks:ks_name":"Purba Sikta",
    "ks:ks_pop":1030,
    "ks:ks_type":"HABITATION",
    "name:eng_x_preferred":[
        "Purba Sikta"
    ],
    "wof:name":"Purba Sikta",
    "wof:placetype":"locality",
    "wof:population":1030
},
  "geometry": {"coordinates":[88.285281,22.909302],"type":"Point"}
}