{
  "type": "Feature",
  "properties": {
    "iso:country":"IN",
    "ks:ks_name":"Diyra Tola",
    "ks:ks_pop":35,
    "ks:ks_type":"HABITATION",
    "name:eng_x_preferred":[
        "Diyra Tola"
    ],
    "wof:name":"Diyra Tola",
    "wof:placetype":"locality",
    "wof:population":35
},
  "geometry": {"coordinates":[83.189635,26.405043],"type":"Point"}
}