{
  "type": "Feature",
  "properties": {
    "iso:country":"IN",
    "ks:ks_name":"Tukkiyampalayam",
    "ks:ks_pop":4594,
    "ks:ks_type":"VILLAGE",
    "ks:ks_uagg_main":0,
    "name:eng_x_preferred":[
        "Tukkiyampalayam"
    ],
    "wof:name":"Tukkiyampalayam",
    "wof:placetype":"neighbourhood",
    "wof:population":4594
},
  "geometry": {"coordinates":[78.406941,11.690545],"type":"Point"}
}