{
  "type": "Feature",
  "properties": {
    "iso:country":"IN",
    "ks:ks_name":"Hulikatti",
    "ks:ks_pop":737,
    "ks:ks_type":"HABITATION",
    "name:eng_x_preferred":[
        "Hulikatti"
    ],
    "wof:name":"Hulikatti",
    "wof:placetype":"locality",
    "wof:population":737
},
  "geometry": {"coordinates":[74.954722,15.330278],"type":"Point"}
}