{
  "type": "Feature",
  "properties": {
    "gn:admin1_code":"35",
    "gn:admin2_code":"426.0",
    "gn:asciiname":"Baberu",
    "gn:country_code":"IN",
    "gn:dem":175,
    "gn:feature_class":"P",
    "gn:feature_code":"PPL",
    "gn:name":"Baberu",
    "gn:population":0,
    "gn:timezone":"Asia/Kolkata",
    "iso:country":"IN",
    "name:bih_x_preferred":[
        "\u092c\u092c\u0947\u0930\u0942"
    ],
    "name:bpy_x_preferred":[
        "\u09ac\u09be\u09ac\u09c7\u09b0\u09c1"
    ],
    "name:ceb_x_preferred":[
        "Baberu"
    ],
    "name:ita_x_preferred":[
        "Baberu"
    ],
    "name:mlg_x_preferred":[
        "Baberu"
    ],
    "name:msa_x_preferred":[
        "Baberu"
    ],
    "name:new_x_preferred":[
        "\u092c\u093e\u092c\u0947\u0930\u0941"
    ],
    "name:nld_x_preferred":[
        "Baberu"
    ],
    "name:pol_x_preferred":[
        "Baberu"
    ],
    "name:urd_x_preferred":[
        "\u0628\u0627\u0628\u06cc\u0631\u0648"
    ],
    "name:vie_x_preferred":[
        "Baberu"
    ],
    "name:zho_x_preferred":[
        "\u5df4\u8d1d\u9c81"
    ],
    "wof:name":"Baberu",
    "wof:placetype":"locality"
},
  "geometry": {"coordinates":[80.34504,24.91905],"type":"Point"}
}