{
  "type": "Feature",
  "properties": {
    "iso:country":"IN",
    "ks:ks_alt_nam":"PANDAYPATTEE",
    "ks:ks_name":"Pandaypattee",
    "ks:ks_pop":500,
    "ks:ks_type":"HABITATION",
    "ks:ks_uagg_main":0,
    "name:eng_x_preferred":[
        "Pandaypattee"
    ],
    "wof:name":"Pandaypattee",
    "wof:placetype":"neighbourhood",
    "wof:population":500
},
  "geometry": {"coordinates":[86.415458,26.171728],"type":"Point"}
}