{
  "type": "Feature",
  "properties": {
    "iso:country":"IN",
    "ks:ks_name":"Varai",
    "ks:ks_pop":613,
    "ks:ks_type":"VILLAGE",
    "name:eng_x_preferred":[
        "Varai"
    ],
    "wof:name":"Varai",
    "wof:placetype":"locality",
    "wof:population":613
},
  "geometry": {"coordinates":[73.02182000000001,20.462825],"type":"Point"}
}