{
  "type": "Feature",
  "properties": {
    "iso:country":"IN",
    "ks:ks_name":"Harbanspur Jagir",
    "ks:ks_pop":0,
    "ks:ks_type":"VILLAGE",
    "name:eng_x_preferred":[
        "Harbanspur Jagir"
    ],
    "wof:name":"Harbanspur Jagir",
    "wof:placetype":"locality",
    "wof:population":0
},
  "geometry": {"coordinates":[86.71216,25.194405],"type":"Point"}
}