{
  "type": "Feature",
  "properties": {
    "iso:country":"IN",
    "ks:ks_name":"Enayam",
    "ks:ks_pop":499,
    "ks:ks_type":"HABITATION",
    "name:eng_x_preferred":[
        "Enayam"
    ],
    "wof:name":"Enayam",
    "wof:placetype":"locality",
    "wof:population":499
},
  "geometry": {"coordinates":[77.188081,8.217192],"type":"Point"}
}