{
  "type": "Feature",
  "properties": {
    "iso:country":"IN",
    "ks:ks_name":"Nadigara Palya",
    "ks:ks_pop":147,
    "ks:ks_type":"HABITATION",
    "name:eng_x_preferred":[
        "Nadigara Palya"
    ],
    "wof:name":"Nadigara Palya",
    "wof:placetype":"locality",
    "wof:population":147
},
  "geometry": {"coordinates":[76.790556,13.941944],"type":"Point"}
}