{
  "type": "Feature",
  "properties": {
    "iso:country":"IN",
    "ks:ks_name":"Nayak Faliya",
    "ks:ks_pop":1170,
    "ks:ks_type":"HABITATION",
    "name:eng_x_preferred":[
        "Nayak Faliya"
    ],
    "wof:name":"Nayak Faliya",
    "wof:placetype":"locality",
    "wof:population":1170
},
  "geometry": {"coordinates":[73.617867,22.738067],"type":"Point"}
}