{
  "type": "Feature",
  "properties": {
    "iso:country":"IN",
    "ks:ks_alt_nam":"BhadrapurWathar",
    "ks:ks_name":"Bhadrapurwathar",
    "ks:ks_pop":135,
    "ks:ks_type":"HABITATION",
    "name:eng_x_preferred":[
        "Bhadrapurwathar"
    ],
    "wof:name":"Bhadrapurwathar",
    "wof:placetype":"locality",
    "wof:population":135
},
  "geometry": {"coordinates":[73.46984999999999,17.16125],"type":"Point"}
}