{
  "type": "Feature",
  "properties": {
    "gn:admin1_code":"34.0",
    "gn:admin2_code":"207.0",
    "gn:asciiname":"Barhara Dakhli",
    "gn:country_code":"IN",
    "gn:dem":63,
    "gn:feature_class":"P",
    "gn:feature_code":"PPL",
    "gn:name":"Barhara D\u0101khli",
    "gn:population":0,
    "gn:timezone":"Asia/Kolkata",
    "iso:country":"IN",
    "wof:name":"Barhara Dakhli",
    "wof:placetype":"locality"
},
  "geometry": {"coordinates":[86.20206999999998,26.37314000000001],"type":"Point"}
}