{
  "type": "Feature",
  "properties": {
    "gn:admin1_code":"39",
    "gn:admin2_code":"61.0",
    "gn:asciiname":"Kalon",
    "gn:country_code":"IN",
    "gn:dem":1087,
    "gn:feature_class":"P",
    "gn:feature_code":"PPL",
    "gn:name":"Kalon",
    "gn:population":0,
    "gn:timezone":"Asia/Kolkata",
    "iso:country":"IN",
    "name:fas_x_preferred":[
        "\u06a9\u0644\u0627\u0646"
    ],
    "name:ind_x_preferred":[
        "Kalon"
    ],
    "name:msa_x_preferred":[
        "Kalon"
    ],
    "wof:name":"Kalon",
    "wof:placetype":"locality"
},
  "geometry": {"coordinates":[78.81950000000001,30.1924],"type":"Point"}
}