{
  "type": "Feature",
  "properties": {
    "iso:country":"IN",
    "ks:ks_name":"West Bandherpar",
    "ks:ks_pop":412,
    "ks:ks_type":"HABITATION",
    "name:eng_x_preferred":[
        "West Bandherpar"
    ],
    "wof:name":"West Bandherpar",
    "wof:placetype":"locality",
    "wof:population":412
},
  "geometry": {"coordinates":[89.063014,26.66864],"type":"Point"}
}