{
  "type": "Feature",
  "properties": {
    "iso:country":"IN",
    "ks:ks_name":"Kamalpur",
    "ks:ks_pop":462,
    "ks:ks_type":"VILLAGE",
    "name:eng_x_preferred":[
        "Kamalpur"
    ],
    "wof:name":"Kamalpur",
    "wof:placetype":"locality",
    "wof:population":462
},
  "geometry": {"coordinates":[92.38274800000001,24.346557],"type":"Point"}
}