{
  "type": "Feature",
  "properties": {
    "iso:country":"IN",
    "ks:ks_alt_nam":"S.N.Kandriga YC 1",
    "ks:ks_name":"S.n.kandriga Yc 1",
    "ks:ks_pop":172,
    "ks:ks_type":"HABITATION",
    "name:eng_x_preferred":[
        "S.n.kandriga Yc 1"
    ],
    "wof:name":"S.n.kandriga Yc 1",
    "wof:placetype":"locality",
    "wof:population":172
},
  "geometry": {"coordinates":[79.722346,13.790835],"type":"Point"}
}