{
  "type": "Feature",
  "properties": {
    "iso:country":"IN",
    "ks:ks_name":"Baladwip",
    "ks:ks_pop":740,
    "ks:ks_type":"VILLAGE",
    "name:eng_x_preferred":[
        "Baladwip"
    ],
    "wof:name":"Baladwip",
    "wof:placetype":"locality",
    "wof:population":740
},
  "geometry": {"coordinates":[87.612011,22.894471],"type":"Point"}
}