{
  "type": "Feature",
  "properties": {
    "gn:admin1_code":"12.0",
    "gn:admin2_code":"12.0",
    "gn:asciiname":"Rinzpur",
    "gn:country_code":"IN",
    "gn:dem":1601,
    "gn:feature_class":"P",
    "gn:feature_code":"PPL",
    "gn:name":"Rinzpur",
    "gn:population":0,
    "gn:timezone":"Asia/Kolkata",
    "iso:country":"IN",
    "wof:name":"Rinzpur",
    "wof:placetype":"locality"
},
  "geometry": {"coordinates":[74.99735,33.86023],"type":"Point"}
}