{
  "type": "Feature",
  "properties": {
    "iso:country":"IN",
    "ks:ks_alt_nam":"NAGLA LOTE",
    "ks:ks_name":"Nagla Lote",
    "ks:ks_pop":502,
    "ks:ks_type":"HABITATION",
    "ks:ks_uagg_main":0,
    "name:eng_x_preferred":[
        "Nagla Lote"
    ],
    "wof:name":"Nagla Lote",
    "wof:placetype":"neighbourhood",
    "wof:population":502
},
  "geometry": {"coordinates":[79.27213999999999,26.865156],"type":"Point"}
}