{
  "type": "Feature",
  "properties": {
    "gn:admin1_code":"36",
    "gn:admin2_code":"177.0",
    "gn:asciiname":"Kazipur Tappa Biswal",
    "gn:country_code":"IN",
    "gn:dem":98,
    "gn:feature_class":"P",
    "gn:feature_code":"PPL",
    "gn:name":"K\u0101zipur Tappa Biswal",
    "gn:population":0,
    "gn:timezone":"Asia/Kolkata",
    "iso:country":"IN",
    "wof:name":"Kazipur Tappa Biswal",
    "wof:placetype":"locality"
},
  "geometry": {"coordinates":[82.33319,26.68243],"type":"Point"}
}