{
  "type": "Feature",
  "properties": {
    "gn:admin1_code":"37",
    "gn:admin2_code":"404.0",
    "gn:asciiname":"Tendubhata",
    "gn:country_code":"IN",
    "gn:dem":317,
    "gn:feature_class":"P",
    "gn:feature_code":"PPL",
    "gn:name":"Tend\u016bbh\u0101t\u0101",
    "gn:population":0,
    "gn:timezone":"Asia/Kolkata",
    "iso:country":"IN",
    "ks:ks_alt_nam":"Tend\u016bbh\u0101t\u0101",
    "ks:ks_name":"Tendubhata",
    "ks:ks_pop":510,
    "ks:ks_type":"VILLAGE",
    "name:eng_x_preferred":[
        "Tendubhata"
    ],
    "name:eng_x_variant":[
        "Tend\u016bbh\u0101t\u0101"
    ],
    "wof:name":"Tendubhata",
    "wof:placetype":"locality",
    "wof:population":510
},
  "geometry": {"coordinates":[82.351806,22.356314],"type":"Point"}
}