{
  "type": "Feature",
  "properties": {
    "iso:country":"IN",
    "ks:ks_alt_nam":"New colony",
    "ks:ks_name":"New Colony",
    "ks:ks_pop":439,
    "ks:ks_type":"HABITATION",
    "name:eng_x_preferred":[
        "New Colony"
    ],
    "wof:name":"New Colony",
    "wof:placetype":"locality",
    "wof:population":439
},
  "geometry": {"coordinates":[79.09751300000001,12.840961],"type":"Point"}
}