{
  "type": "Feature",
  "properties": {
    "iso:country":"IN",
    "ks:ks_name":"Sivarampuram",
    "ks:ks_pop":137,
    "ks:ks_type":"HABITATION",
    "name:eng_x_preferred":[
        "Sivarampuram"
    ],
    "wof:name":"Sivarampuram",
    "wof:placetype":"locality",
    "wof:population":137
},
  "geometry": {"coordinates":[78.661776,13.541508],"type":"Point"}
}