{
  "type": "Feature",
  "properties": {
    "gn:admin1_code":"23.0",
    "gn:admin2_code":"38.0",
    "gn:asciiname":"Jhang",
    "gn:country_code":"IN",
    "gn:dem":289,
    "gn:feature_class":"P",
    "gn:feature_code":"PPL",
    "gn:name":"Jhang",
    "gn:population":0,
    "gn:timezone":"Asia/Kolkata",
    "iso:country":"IN",
    "name:ara_x_preferred":[
        "\u062c\u0647\u0646\u0643"
    ],
    "name:azb_x_preferred":[
        "\u062c\u0647\u0646\u06af"
    ],
    "name:bel_x_preferred":[
        "\u0414\u0436\u0430\u043d\u0433"
    ],
    "name:cat_x_preferred":[
        "Jhang"
    ],
    "name:dan_x_preferred":[
        "Jhang"
    ],
    "name:deu_x_preferred":[
        "Jhang"
    ],
    "name:eus_x_preferred":[
        "Jhang"
    ],
    "name:fas_x_preferred":[
        "\u062c\u0647\u0646\u06af"
    ],
    "name:fra_x_preferred":[
        "Jhang"
    ],
    "name:hin_x_preferred":[
        "\u091d\u0902\u0917"
    ],
    "name:ind_x_preferred":[
        "Jhang"
    ],
    "name:ita_x_preferred":[
        "Jhang"
    ],
    "name:lit_x_preferred":[
        "D\u017ehangas"
    ],
    "name:mar_x_preferred":[
        "\u091d\u0902\u0917"
    ],
    "name:pan_x_preferred":[
        "\u0a1d\u0a70\u0a17"
    ],
    "name:pnb_x_preferred":[
        "\u0686\u0646\u06af"
    ],
    "name:pol_x_preferred":[
        "Jhang"
    ],
    "name:por_x_preferred":[
        "Jhang"
    ],
    "name:pus_x_preferred":[
        "\u062c\u0647\u0646\u06af"
    ],
    "name:rus_x_preferred":[
        "\u0414\u0436\u0430\u043d\u0433"
    ],
    "name:spa_x_preferred":[
        "Jhang"
    ],
    "name:srp_x_preferred":[
        "\u040f\u0430\u043d\u0433"
    ],
    "name:swe_x_preferred":[
        "Jhang"
    ],
    "name:urd_x_preferred":[
        "\u062c\u06be\u0646\u06af"
    ],
    "name:vie_x_preferred":[
        "Jhang"
    ],
    "name:war_x_preferred":[
        "Jhang"
    ],
    "name:xmf_x_preferred":[
        "\u10ef\u10d0\u10dc\u10d2\u10d8"
    ],
    "wof:name":"Jhang",
    "wof:placetype":"locality"
},
  "geometry": {"coordinates":[75.73076999999998,32.02895],"type":"Point"}
}