{
  "type": "Feature",
  "properties": {
    "gn:admin1_code":"16.0",
    "gn:admin2_code":"508.0",
    "gn:asciiname":"Sida",
    "gn:country_code":"IN",
    "gn:dem":124,
    "gn:feature_class":"P",
    "gn:feature_code":"PPL",
    "gn:name":"Sida",
    "gn:population":0,
    "gn:timezone":"Asia/Kolkata",
    "iso:country":"IN",
    "name:ara_x_preferred":[
        "\u0633\u064a\u062f\u0627"
    ],
    "name:ceb_x_preferred":[
        "Sida"
    ],
    "name:deu_x_preferred":[
        "Sida"
    ],
    "name:fra_x_preferred":[
        "Sida"
    ],
    "name:hrv_x_preferred":[
        "Sida"
    ],
    "name:ita_x_preferred":[
        "Sida"
    ],
    "name:nld_x_preferred":[
        "Sida"
    ],
    "name:pol_x_preferred":[
        "Sida"
    ],
    "name:por_x_preferred":[
        "Sida"
    ],
    "name:spa_x_preferred":[
        "Sida"
    ],
    "name:swe_x_preferred":[
        "Sida"
    ],
    "name:zho_x_preferred":[
        "\u9ec4\u82b1\u7a14\u5c5e"
    ],
    "wof:name":"Sida",
    "wof:placetype":"locality"
},
  "geometry": {"coordinates":[80.23543000000002,19.06352],"type":"Point"}
}