{
  "type": "Feature",
  "properties": {
    "iso:country":"IN",
    "ks:ks_name":"Karimpur",
    "ks:ks_pop":673,
    "ks:ks_type":"VILLAGE",
    "name:eng_x_preferred":[
        "Karimpur"
    ],
    "wof:name":"Karimpur",
    "wof:placetype":"locality",
    "wof:population":673
},
  "geometry": {"coordinates":[87.556309,23.924136],"type":"Point"}
}