{
  "type": "Feature",
  "properties": {
    "iso:country":"IN",
    "ks:ks_name":"Ganto",
    "ks:ks_pop":588,
    "ks:ks_type":"HABITATION",
    "name:eng_x_preferred":[
        "Ganto"
    ],
    "wof:name":"Ganto",
    "wof:placetype":"locality",
    "wof:population":588
},
  "geometry": {"coordinates":[73.51912400000001,23.161358],"type":"Point"}
}