{
  "type": "Feature",
  "properties": {
    "iso:country":"IN",
    "ks:ks_name":"Gunapahari",
    "ks:ks_pop":0,
    "ks:ks_type":"VILLAGE",
    "name:eng_x_preferred":[
        "Gunapahari"
    ],
    "wof:name":"Gunapahari",
    "wof:placetype":"locality",
    "wof:population":0
},
  "geometry": {"coordinates":[85.69738700000001,22.097232],"type":"Point"}
}