{
  "type": "Feature",
  "properties": {
    "iso:country":"IN",
    "ks:ks_alt_nam":"naimpur",
    "ks:ks_name":"Naimpur",
    "ks:ks_pop":448,
    "ks:ks_type":"HABITATION",
    "name:eng_x_preferred":[
        "Naimpur"
    ],
    "wof:name":"Naimpur",
    "wof:placetype":"locality",
    "wof:population":448
},
  "geometry": {"coordinates":[80.712666,26.567552],"type":"Point"}
}