{
  "type": "Feature",
  "properties": {
    "iso:country":"IN",
    "ks:ks_name":"Rajobach Mala",
    "ks:ks_pop":64,
    "ks:ks_type":"HABITATION",
    "name:eng_x_preferred":[
        "Rajobach Mala"
    ],
    "wof:name":"Rajobach Mala",
    "wof:placetype":"locality",
    "wof:population":64
},
  "geometry": {"coordinates":[74.084273,18.396387],"type":"Point"}
}