{
  "type": "Feature",
  "properties": {
    "iso:country":"IN",
    "ks:ks_name":"Bahirwadi",
    "ks:ks_pop":238,
    "ks:ks_type":"HABITATION",
    "name:eng_x_preferred":[
        "Bahirwadi"
    ],
    "wof:name":"Bahirwadi",
    "wof:placetype":"locality",
    "wof:population":238
},
  "geometry": {"coordinates":[74.252343,19.691282],"type":"Point"}
}