{
  "type": "Feature",
  "properties": {
    "gn:admin1_code":"12.0",
    "gn:admin2_code":"004",
    "gn:asciiname":"Garkhun",
    "gn:country_code":"IN",
    "gn:dem":2751,
    "gn:feature_class":"P",
    "gn:feature_code":"PPL",
    "gn:name":"Garkhun",
    "gn:population":0,
    "gn:timezone":"Asia/Kolkata",
    "iso:country":"IN",
    "wof:name":"Garkhun",
    "wof:placetype":"locality"
},
  "geometry": {"coordinates":[76.44696999999999,34.63353],"type":"Point"}
}