{
  "type": "Feature",
  "properties": {
    "iso:country":"IN",
    "ks:ks_name":"Maitha",
    "ks:ks_pop":391,
    "ks:ks_type":"VILLAGE",
    "name:eng_x_preferred":[
        "Maitha"
    ],
    "wof:name":"Maitha",
    "wof:placetype":"locality",
    "wof:population":391
},
  "geometry": {"coordinates":[87.214338,23.195524],"type":"Point"}
}