{
  "type": "Feature",
  "properties": {
    "gn:admin1_code":"13.0",
    "gn:admin2_code":"598.0",
    "gn:asciiname":"Kavaram Vadakku",
    "gn:country_code":"IN",
    "gn:dem":10,
    "gn:feature_class":"P",
    "gn:feature_code":"PPL",
    "gn:name":"K\u0101v\u0101r\u0101m Vadakku",
    "gn:population":0,
    "gn:timezone":"Asia/Kolkata",
    "iso:country":"IN",
    "wof:name":"Kavaram Vadakku",
    "wof:placetype":"locality"
},
  "geometry": {"coordinates":[76.38852,9.30565],"type":"Point"}
}