{
  "type": "Feature",
  "properties": {
    "gn:admin1_code":"36.0",
    "gn:admin2_code":"175.0",
    "gn:asciiname":"Medau ka Pura",
    "gn:country_code":"IN",
    "gn:dem":98,
    "gn:feature_class":"P",
    "gn:feature_code":"PPL",
    "gn:name":"Medau ka Pura",
    "gn:population":0,
    "gn:timezone":"Asia/Kolkata",
    "iso:country":"IN",
    "wof:name":"Medau ka Pura",
    "wof:placetype":"locality"
},
  "geometry": {"coordinates":[81.73326999999998,25.57913],"type":"Point"}
}