{
  "type": "Feature",
  "properties": {
    "iso:country":"IN",
    "ks:ks_name":"Bhanar",
    "ks:ks_pop":1803,
    "ks:ks_type":"VILLAGE",
    "name:eng_x_preferred":[
        "Bhanar"
    ],
    "wof:name":"Bhanar",
    "wof:placetype":"locality",
    "wof:population":1803
},
  "geometry": {"coordinates":[80.025266,29.948058],"type":"Point"}
}