{
  "type": "Feature",
  "properties": {
    "iso:country":"IN",
    "ks:ks_name":"Talakatte",
    "ks:ks_pop":158,
    "ks:ks_type":"HABITATION",
    "name:eng_x_preferred":[
        "Talakatte"
    ],
    "wof:name":"Talakatte",
    "wof:placetype":"locality",
    "wof:population":158
},
  "geometry": {"coordinates":[74.427043,14.365337],"type":"Point"}
}