{
  "type": "Feature",
  "properties": {
    "iso:country":"IN",
    "ks:ks_name":"Kudlum",
    "ks:ks_pop":1459,
    "ks:ks_type":"VILLAGE",
    "ks:ks_uagg_main":0,
    "name:eng_x_preferred":[
        "Kudlum"
    ],
    "wof:name":"Kudlum",
    "wof:placetype":"neighbourhood",
    "wof:population":1459
},
  "geometry": {"coordinates":[85.85500399999999,23.261159],"type":"Point"}
}