{
  "type": "Feature",
  "properties": {
    "iso:country":"IN",
    "ks:ks_name":"Sitarampur",
    "ks:ks_pop":732,
    "ks:ks_type":"VILLAGE",
    "name:eng_x_preferred":[
        "Sitarampur"
    ],
    "wof:name":"Sitarampur",
    "wof:placetype":"locality",
    "wof:population":732
},
  "geometry": {"coordinates":[83.622361,23.48352],"type":"Point"}
}