{
  "type": "Feature",
  "properties": {
    "gn:admin1_code":"35.0",
    "gn:admin2_code":"441.0",
    "gn:asciiname":"Khajpur",
    "gn:country_code":"IN",
    "gn:dem":167,
    "gn:feature_class":"P",
    "gn:feature_code":"PPL",
    "gn:name":"Kh\u0101jpur",
    "gn:population":0,
    "gn:timezone":"Asia/Kolkata",
    "iso:country":"IN",
    "ks:ks_name":"Khajpur",
    "ks:ks_pop":746,
    "ks:ks_type":"HABITATION",
    "name:eng_x_preferred":[
        "Khajpur"
    ],
    "wof:name":"Khajpur",
    "wof:placetype":"locality",
    "wof:population":746
},
  "geometry": {"coordinates":[74.79947,22.013857],"type":"Point"}
}