{
  "type": "Feature",
  "properties": {
    "iso:country":"IN",
    "ks:ks_name":"Baniara",
    "ks:ks_pop":4707,
    "ks:ks_type":"URBAN",
    "ks:ks_uagg_main":0,
    "name:eng_x_preferred":[
        "Baniara"
    ],
    "wof:name":"Baniara",
    "wof:placetype":"neighbourhood",
    "wof:population":4707
},
  "geometry": {"coordinates":[88.21191399999999,22.602507],"type":"Point"}
}