{
  "type": "Feature",
  "properties": {
    "gn:admin1_code":"16",
    "gn:admin2_code":"509.0",
    "gn:asciiname":"Yerkheda",
    "gn:country_code":"IN",
    "gn:dem":249,
    "gn:feature_class":"P",
    "gn:feature_code":"PPL",
    "gn:name":"Yerkheda",
    "gn:population":0,
    "gn:timezone":"Asia/Kolkata",
    "iso:country":"IN",
    "name:ben_x_preferred":[
        "\u09af\u09bc\u09c7\u09b0\u0996\u09c7\u09a6\u09be"
    ],
    "name:bpy_x_preferred":[
        "\u09af\u09bc\u09c7\u09b0\u0996\u09c7\u09a6\u09be"
    ],
    "name:ind_x_preferred":[
        "Yerkheda"
    ],
    "name:ita_x_preferred":[
        "Yerkheda"
    ],
    "name:msa_x_preferred":[
        "Yerkheda"
    ],
    "name:new_x_preferred":[
        "\u092f\u0947\u0930\u094d\u0916\u0947\u0926\u093e"
    ],
    "name:nld_x_preferred":[
        "Yerkheda"
    ],
    "name:por_x_preferred":[
        "Yerkheda"
    ],
    "name:urd_x_preferred":[
        "\u06cc\u0631\u062e\u062f\u06c1"
    ],
    "name:vie_x_preferred":[
        "Yerkheda"
    ],
    "name:zho_x_preferred":[
        "\u8036\u5c14\u51ef\u8fbe"
    ],
    "wof:name":"Yerkheda",
    "wof:placetype":"locality"
},
  "geometry": {"coordinates":[79.14699,20.47115],"type":"Point"}
}