{
  "type": "Feature",
  "properties": {
    "iso:country":"IN",
    "ks:ks_name":"Mundagodu",
    "ks:ks_pop":11,
    "ks:ks_type":"HABITATION",
    "name:eng_x_preferred":[
        "Mundagodu"
    ],
    "wof:name":"Mundagodu",
    "wof:placetype":"locality",
    "wof:population":11
},
  "geometry": {"coordinates":[74.852071,13.946603],"type":"Point"}
}