{
  "type": "Feature",
  "properties": {
    "iso:country":"IN",
    "ks:ks_name":"Majhladih",
    "ks:ks_pop":142,
    "ks:ks_type":"HABITATION",
    "name:eng_x_preferred":[
        "Majhladih"
    ],
    "wof:name":"Majhladih",
    "wof:placetype":"locality",
    "wof:population":142
},
  "geometry": {"coordinates":[86.55255200000001,24.335351],"type":"Point"}
}