{
  "type": "Feature",
  "properties": {
    "iso:country":"IN",
    "ks:ks_alt_nam":"Jahanabad 2nd part",
    "ks:ks_name":"Jahanabad 2nd Part",
    "ks:ks_pop":199,
    "ks:ks_type":"HABITATION",
    "name:eng_x_preferred":[
        "Jahanabad 2nd Part"
    ],
    "wof:name":"Jahanabad 2nd Part",
    "wof:placetype":"locality",
    "wof:population":199
},
  "geometry": {"coordinates":[87.85915,22.152188],"type":"Point"}
}