{
  "type": "Feature",
  "properties": {
    "iso:country":"IN",
    "ks:ks_name":"Jamri",
    "ks:ks_pop":97,
    "ks:ks_type":"VILLAGE",
    "name:eng_x_preferred":[
        "Jamri"
    ],
    "wof:name":"Jamri",
    "wof:placetype":"locality",
    "wof:population":97
},
  "geometry": {"coordinates":[87.406446,24.832799],"type":"Point"}
}