{
  "type": "Feature",
  "properties": {
    "iso:country":"IN",
    "ks:ks_name":"Nai Rajmathai",
    "ks:ks_pop":508,
    "ks:ks_type":"HABITATION",
    "name:eng_x_preferred":[
        "Nai Rajmathai"
    ],
    "wof:name":"Nai Rajmathai",
    "wof:placetype":"locality",
    "wof:population":508
},
  "geometry": {"coordinates":[71.754029,26.549479],"type":"Point"}
}