{
  "type": "Feature",
  "properties": {
    "iso:country":"IN",
    "ks:ks_name":"Gadmiripara",
    "ks:ks_pop":97,
    "ks:ks_type":"HABITATION",
    "name:eng_x_preferred":[
        "Gadmiripara"
    ],
    "wof:name":"Gadmiripara",
    "wof:placetype":"locality",
    "wof:population":97
},
  "geometry": {"coordinates":[80.836865,19.079175],"type":"Point"}
}