{
  "type": "Feature",
  "properties": {
    "iso:country":"IN",
    "ks:ks_name":"Ozhukkupara",
    "ks:ks_pop":520,
    "ks:ks_type":"HABITATION",
    "name:eng_x_preferred":[
        "Ozhukkupara"
    ],
    "wof:name":"Ozhukkupara",
    "wof:placetype":"locality",
    "wof:population":520
},
  "geometry": {"coordinates":[76.947231,8.918657],"type":"Point"}
}