{
  "type": "Feature",
  "properties": {
    "iso:country":"IN",
    "ks:ks_name":"Chhatasarai",
    "ks:ks_pop":594,
    "ks:ks_type":"VILLAGE",
    "name:eng_x_preferred":[
        "Chhatasarai"
    ],
    "wof:name":"Chhatasarai",
    "wof:placetype":"locality",
    "wof:population":594
},
  "geometry": {"coordinates":[83.63395199999999,22.505403],"type":"Point"}
}