{
  "type": "Feature",
  "properties": {
    "iso:country":"IN",
    "ks:ks_name":"Billi",
    "ks:ks_type":"VILLAGE",
    "ks:ks_uagg_main":0,
    "name:eng_x_preferred":[
        "Billi"
    ],
    "wof:name":"Billi",
    "wof:placetype":"neighbourhood"
},
  "geometry": {"coordinates":[82.990914,24.445468],"type":"Point"}
}