{
  "type": "Feature",
  "properties": {
    "iso:country":"IN",
    "ks:ks_name":"Gopalnagar",
    "ks:ks_pop":496,
    "ks:ks_type":"VILLAGE",
    "ks:ks_uagg_main":0,
    "name:eng_x_preferred":[
        "Gopalnagar"
    ],
    "wof:name":"Gopalnagar",
    "wof:placetype":"neighbourhood",
    "wof:population":496
},
  "geometry": {"coordinates":[87.266442,22.846486],"type":"Point"}
}