{
  "type": "Feature",
  "properties": {
    "iso:country":"IN",
    "ks:ks_name":"Kohokwasti",
    "ks:ks_pop":117,
    "ks:ks_type":"HABITATION",
    "name:eng_x_preferred":[
        "Kohokwasti"
    ],
    "wof:name":"Kohokwasti",
    "wof:placetype":"locality",
    "wof:population":117
},
  "geometry": {"coordinates":[74.720697,18.731985],"type":"Point"}
}