{
  "type": "Feature",
  "properties": {
    "iso:country":"IN",
    "ks:ks_alt_nam":"Dhani ka pura",
    "ks:ks_name":"Dhani Ka Pura",
    "ks:ks_pop":431,
    "ks:ks_type":"HABITATION",
    "ks:ks_uagg_main":0,
    "name:eng_x_preferred":[
        "Dhani Ka Pura"
    ],
    "wof:name":"Dhani Ka Pura",
    "wof:placetype":"neighbourhood",
    "wof:population":431
},
  "geometry": {"coordinates":[82.245592,26.211857],"type":"Point"}
}