{
  "type": "Feature",
  "properties": {
    "iso:country":"IN",
    "ks:ks_name":"Bantipur",
    "ks:ks_pop":2105,
    "ks:ks_type":"VILLAGE",
    "name:eng_x_preferred":[
        "Bantipur"
    ],
    "wof:name":"Bantipur",
    "wof:placetype":"locality",
    "wof:population":2105
},
  "geometry": {"coordinates":[91.012123,26.375858],"type":"Point"}
}