{
  "type": "Feature",
  "properties": {
    "iso:country":"IN",
    "ks:ks_name":"Kandalli",
    "ks:ks_pop":335,
    "ks:ks_type":"HABITATION",
    "name:eng_x_preferred":[
        "Kandalli"
    ],
    "wof:name":"Kandalli",
    "wof:placetype":"locality",
    "wof:population":335
},
  "geometry": {"coordinates":[74.540103,14.526059],"type":"Point"}
}