{
  "type": "Feature",
  "properties": {
    "gn:admin1_code":"37",
    "gn:admin2_code":"406.0",
    "gn:asciiname":"Bahra",
    "gn:country_code":"IN",
    "gn:dem":598,
    "gn:feature_class":"P",
    "gn:feature_code":"PPL",
    "gn:name":"B\u0101hra",
    "gn:population":0,
    "gn:timezone":"Asia/Kolkata",
    "iso:country":"IN",
    "name:ceb_x_preferred":[
        "Bahra"
    ],
    "name:deu_x_preferred":[
        "Bahra"
    ],
    "name:swe_x_preferred":[
        "Bahra"
    ],
    "name:und_x_variant":[
        "B\u0101hra",
        "Kurdar"
    ],
    "wof:name":"Bahra",
    "wof:placetype":"locality"
},
  "geometry": {"coordinates":[81.94314,22.44468],"type":"Point"}
}