{
  "type": "Feature",
  "properties": {
    "iso:country":"IN",
    "ks:ks_name":"Kodige",
    "ks:ks_pop":205,
    "ks:ks_type":"HABITATION",
    "name:eng_x_preferred":[
        "Kodige"
    ],
    "wof:name":"Kodige",
    "wof:placetype":"locality",
    "wof:population":205
},
  "geometry": {"coordinates":[75.309258,13.425218],"type":"Point"}
}