{
  "type": "Feature",
  "properties": {
    "iso:country":"IN",
    "ks:ks_name":"Andasar",
    "ks:ks_pop":463,
    "ks:ks_type":"HABITATION",
    "name:eng_x_preferred":[
        "Andasar"
    ],
    "wof:name":"Andasar",
    "wof:placetype":"locality",
    "wof:population":463
},
  "geometry": {"coordinates":[72.37050600000001,27.392244],"type":"Point"}
}