{
  "type": "Feature",
  "properties": {
    "iso:country":"IN",
    "ks:ks_name":"Dhangadmau Khurd",
    "ks:ks_pop":396,
    "ks:ks_type":"VILLAGE",
    "name:eng_x_preferred":[
        "Dhangadmau Khurd"
    ],
    "wof:name":"Dhangadmau Khurd",
    "wof:placetype":"locality",
    "wof:population":396
},
  "geometry": {"coordinates":[75.407882,24.942693],"type":"Point"}
}