{
  "type": "Feature",
  "properties": {
    "iso:country":"IN",
    "ks:ks_name":"Palsandapur",
    "ks:ks_pop":116,
    "ks:ks_type":"VILLAGE",
    "ks:ks_uagg_main":0,
    "name:eng_x_preferred":[
        "Palsandapur"
    ],
    "wof:name":"Palsandapur",
    "wof:placetype":"neighbourhood",
    "wof:population":116
},
  "geometry": {"coordinates":[87.499595,21.623605],"type":"Point"}
}