{
  "type": "Feature",
  "properties": {
    "iso:country":"IN",
    "ks:ks_name":"Arazi Gokarna",
    "ks:ks_pop":0,
    "ks:ks_type":"VILLAGE",
    "name:eng_x_preferred":[
        "Arazi Gokarna"
    ],
    "wof:name":"Arazi Gokarna",
    "wof:placetype":"locality",
    "wof:population":0
},
  "geometry": {"coordinates":[88.08132000000001,24.03688],"type":"Point"}
}