{
  "type": "Feature",
  "properties": {
    "iso:country":"IN",
    "ks:ks_name":"Yadathottilu",
    "ks:ks_pop":49,
    "ks:ks_type":"HABITATION",
    "name:eng_x_preferred":[
        "Yadathottilu"
    ],
    "wof:name":"Yadathottilu",
    "wof:placetype":"locality",
    "wof:population":49
},
  "geometry": {"coordinates":[74.97689699999999,13.793496],"type":"Point"}
}