{
  "type": "Feature",
  "properties": {
    "iso:country":"IN",
    "ks:ks_name":"Paldurema",
    "ks:ks_pop":167,
    "ks:ks_type":"HABITATION",
    "name:eng_x_preferred":[
        "Paldurema"
    ],
    "wof:name":"Paldurema",
    "wof:placetype":"locality",
    "wof:population":167
},
  "geometry": {"coordinates":[82.548136,22.945672],"type":"Point"}
}