{
  "type": "Feature",
  "properties": {
    "iso:country":"IN",
    "ks:ks_name":"Bengapani",
    "ks:ks_pop":10,
    "ks:ks_type":"HABITATION",
    "name:eng_x_preferred":[
        "Bengapani"
    ],
    "wof:name":"Bengapani",
    "wof:placetype":"locality",
    "wof:population":10
},
  "geometry": {"coordinates":[82.253364,18.653332],"type":"Point"}
}