{
  "type": "Feature",
  "properties": {
    "gn:admin1_code":"25",
    "gn:admin2_code":"626.0",
    "gn:asciiname":"Rajasingamangalam",
    "gn:country_code":"IN",
    "gn:dem":17,
    "gn:feature_class":"P",
    "gn:feature_code":"PPL",
    "gn:name":"R\u0101j\u0101singamangalam",
    "gn:population":0,
    "gn:timezone":"Asia/Kolkata",
    "iso:country":"IN",
    "wof:name":"Rajasingamangalam",
    "wof:placetype":"locality"
},
  "geometry": {"coordinates":[78.84613,9.63574],"type":"Point"}
}