{
  "type": "Feature",
  "properties": {
    "iso:country":"IN",
    "ks:ks_name":"Harekrushnapur",
    "ks:ks_pop":253,
    "ks:ks_type":"VILLAGE",
    "name:eng_x_preferred":[
        "Harekrushnapur"
    ],
    "wof:name":"Harekrushnapur",
    "wof:placetype":"locality",
    "wof:population":253
},
  "geometry": {"coordinates":[86.826241,20.807905],"type":"Point"}
}