{
  "type": "Feature",
  "properties": {
    "iso:country":"IN",
    "ks:ks_name":"Hemacharpura",
    "ks:ks_pop":350,
    "ks:ks_type":"HABITATION",
    "name:eng_x_preferred":[
        "Hemacharpura"
    ],
    "wof:name":"Hemacharpura",
    "wof:placetype":"locality",
    "wof:population":350
},
  "geometry": {"coordinates":[71.834857,24.021124],"type":"Point"}
}