{
  "type": "Feature",
  "properties": {
    "gn:admin1_code":"2",
    "gn:admin2_code":"544.0",
    "gn:asciiname":"Dargedda",
    "gn:country_code":"IN",
    "gn:dem":861,
    "gn:feature_class":"P",
    "gn:feature_code":"PPL",
    "gn:name":"Dargedda",
    "gn:population":0,
    "gn:timezone":"Asia/Kolkata",
    "iso:country":"IN",
    "ks:ks_name":"Daragedda",
    "ks:ks_pop":286,
    "ks:ks_type":"VILLAGE",
    "name:eng_x_preferred":[
        "Daragedda"
    ],
    "name:eng_x_variant":[
        "Dargedda"
    ],
    "wof:name":"Daragedda",
    "wof:placetype":"locality",
    "wof:population":286
},
  "geometry": {"coordinates":[82.860001,18.094422],"type":"Point"}
}