{
  "type": "Feature",
  "properties": {
    "iso:country":"IN",
    "ks:ks_name":"Mankisar",
    "ks:ks_pop":1759,
    "ks:ks_type":"HABITATION",
    "name:eng_x_preferred":[
        "Mankisar"
    ],
    "wof:name":"Mankisar",
    "wof:placetype":"locality",
    "wof:population":1759
},
  "geometry": {"coordinates":[81.705682,24.371345],"type":"Point"}
}