{
  "type": "Feature",
  "properties": {
    "iso:country":"IN",
    "ks:ks_name":"Kowadhab",
    "ks:ks_pop":204,
    "ks:ks_type":"VILLAGE",
    "name:eng_x_preferred":[
        "Kowadhab"
    ],
    "wof:name":"Kowadhab",
    "wof:placetype":"locality",
    "wof:population":204
},
  "geometry": {"coordinates":[87.32771200000001,24.41898],"type":"Point"}
}