{
  "type": "Feature",
  "properties": {
    "iso:country":"IN",
    "ks:ks_name":"Vinayaka",
    "ks:ks_pop":0,
    "ks:ks_type":"VILLAGE",
    "name:eng_x_preferred":[
        "Vinayaka"
    ],
    "wof:name":"Vinayaka",
    "wof:placetype":"locality",
    "wof:population":0
},
  "geometry": {"coordinates":[74.986019,24.494809],"type":"Point"}
}