{
  "type": "Feature",
  "properties": {
    "iso:country":"IN",
    "ks:ks_name":"Tikirapada",
    "ks:ks_pop":720,
    "ks:ks_type":"VILLAGE",
    "ks:ks_uagg_main":0,
    "name:eng_x_preferred":[
        "Tikirapada"
    ],
    "wof:name":"Tikirapada",
    "wof:placetype":"neighbourhood",
    "wof:population":720
},
  "geometry": {"coordinates":[87.221833,21.571245],"type":"Point"}
}