{
  "type": "Feature",
  "properties": {
    "iso:country":"IN",
    "ks:ks_name":"Uchiya",
    "ks:ks_pop":1429,
    "ks:ks_type":"VILLAGE",
    "name:eng_x_preferred":[
        "Uchiya"
    ],
    "wof:name":"Uchiya",
    "wof:placetype":"locality",
    "wof:population":1429
},
  "geometry": {"coordinates":[72.129294,25.644217],"type":"Point"}
}