{
  "type": "Feature",
  "properties": {
    "iso:country":"IN",
    "ks:ks_name":"Madhopur Supaul Teria",
    "ks:ks_pop":2650,
    "ks:ks_type":"VILLAGE",
    "name:eng_x_preferred":[
        "Madhopur Supaul Teria"
    ],
    "wof:name":"Madhopur Supaul Teria",
    "wof:placetype":"locality",
    "wof:population":2650
},
  "geometry": {"coordinates":[85.440983,25.849072],"type":"Point"}
}