{
  "type": "Feature",
  "properties": {
    "gn:admin1_code":"30.0",
    "gn:admin2_code":"250",
    "gn:asciiname":"Kombong",
    "gn:country_code":"IN",
    "gn:dem":509,
    "gn:feature_class":"P",
    "gn:feature_code":"PPL",
    "gn:name":"Kombong",
    "gn:population":0,
    "gn:timezone":"Asia/Kolkata",
    "iso:country":"IN",
    "wof:name":"Kombong",
    "wof:placetype":"locality"
},
  "geometry": {"coordinates":[94.83748,28.12285],"type":"Point"}
}