{
  "type": "Feature",
  "properties": {
    "gn:admin1_code":"38.0",
    "gn:admin2_code":"352.0",
    "gn:asciiname":"Shahabad",
    "gn:country_code":"IN",
    "gn:dem":37,
    "gn:feature_class":"P",
    "gn:feature_code":"PPL",
    "gn:name":"Sh\u0101h\u0101b\u0101d",
    "gn:population":0,
    "gn:timezone":"Asia/Kolkata",
    "iso:country":"IN",
    "name:ben_x_preferred":[
        "\u09b6\u09be\u09b9\u09be\u09ac\u09be\u09a6"
    ],
    "name:ceb_x_preferred":[
        "Shahabad"
    ],
    "name:fas_x_preferred":[
        "\u0634\u0627\u0647\u200c\u0622\u0628\u0627\u062f"
    ],
    "name:nld_x_preferred":[
        "Shahabad"
    ],
    "name:pol_x_preferred":[
        "Shahabad"
    ],
    "name:swe_x_preferred":[
        "Shahabad"
    ],
    "wof:name":"Shahabad",
    "wof:placetype":"neighbourhood"
},
  "geometry": {"coordinates":[87.4957,25.26058],"type":"Point"}
}