{
  "type": "Feature",
  "properties": {
    "gn:admin1_code":"35.0",
    "gn:admin2_code":"424",
    "gn:asciiname":"Baldaura",
    "gn:country_code":"IN",
    "gn:dem":338,
    "gn:feature_class":"P",
    "gn:feature_code":"PPL",
    "gn:name":"Baldaura",
    "gn:population":0,
    "gn:timezone":"Asia/Kolkata",
    "iso:country":"IN",
    "name:und_x_variant":[
        "Baidaura"
    ],
    "wof:name":"Baldaura",
    "wof:placetype":"locality"
},
  "geometry": {"coordinates":[78.87661999999997,25.00182],"type":"Point"}
}