{
  "type": "Feature",
  "properties": {
    "iso:country":"IN",
    "ks:ks_name":"Telangjari",
    "ks:ks_pop":522,
    "ks:ks_type":"VILLAGE",
    "name:eng_x_preferred":[
        "Telangjari"
    ],
    "wof:name":"Telangjari",
    "wof:placetype":"locality",
    "wof:population":522
},
  "geometry": {"coordinates":[85.716311,22.694948],"type":"Point"}
}