{
  "type": "Feature",
  "properties": {
    "iso:country":"IN",
    "ks:ks_name":"Nanu Ram Meghwal Ki Dhani",
    "ks:ks_pop":18,
    "ks:ks_type":"HABITATION",
    "name:eng_x_preferred":[
        "Nanu Ram Meghwal Ki Dhani"
    ],
    "wof:name":"Nanu Ram Meghwal Ki Dhani",
    "wof:placetype":"locality",
    "wof:population":18
},
  "geometry": {"coordinates":[74.41104799999999,29.76663],"type":"Point"}
}