{
  "type": "Feature",
  "properties": {
    "gn:admin1_code":"39.0",
    "gn:admin2_code":"060",
    "gn:asciiname":"Khulet",
    "gn:country_code":"IN",
    "gn:dem":1034,
    "gn:feature_class":"P",
    "gn:feature_code":"PPL",
    "gn:name":"Khulet",
    "gn:population":0,
    "gn:timezone":"Asia/Kolkata",
    "iso:country":"IN",
    "wof:name":"Khulet",
    "wof:placetype":"locality"
},
  "geometry": {"coordinates":[77.91083,30.48802],"type":"Point"}
}