{
  "type": "Feature",
  "properties": {
    "gn:admin1_code":"2.0",
    "gn:admin2_code":"549.0",
    "gn:asciiname":"Komatigunta",
    "gn:country_code":"IN",
    "gn:dem":139,
    "gn:feature_class":"P",
    "gn:feature_code":"PPL",
    "gn:name":"Komatigunta",
    "gn:population":0,
    "gn:timezone":"Asia/Kolkata",
    "iso:country":"IN",
    "ks:ks_name":"Komatigunta",
    "ks:ks_pop":440,
    "ks:ks_type":"VILLAGE",
    "name:eng_x_preferred":[
        "Komatigunta"
    ],
    "wof:name":"Komatigunta",
    "wof:placetype":"locality",
    "wof:population":440
},
  "geometry": {"coordinates":[79.338707,15.173895],"type":"Point"}
}