{
  "type": "Feature",
  "properties": {
    "iso:country":"IN",
    "ks:ks_name":"Benda",
    "ks:ks_pop":313,
    "ks:ks_type":"VILLAGE",
    "ks:ks_uagg_main":0,
    "name:eng_x_preferred":[
        "Benda"
    ],
    "wof:name":"Benda",
    "wof:placetype":"neighbourhood",
    "wof:population":313
},
  "geometry": {"coordinates":[87.54894,23.224746],"type":"Point"}
}