{
  "type": "Feature",
  "properties": {
    "gn:admin1_code":"36.0",
    "gn:admin2_code":"171.0",
    "gn:asciiname":"Kapuri",
    "gn:country_code":"IN",
    "gn:dem":119,
    "gn:feature_class":"P",
    "gn:feature_code":"PPL",
    "gn:name":"Kap\u016bri",
    "gn:population":0,
    "gn:timezone":"Asia/Kolkata",
    "iso:country":"IN",
    "ks:ks_alt_nam":"Kap\u016bri",
    "ks:ks_name":"Kapuri",
    "ks:ks_pop":410,
    "ks:ks_type":"VILLAGE",
    "name:eng_x_preferred":[
        "Kapuri"
    ],
    "name:eng_x_variant":[
        "Kap\u016bri"
    ],
    "wof:name":"Kapuri",
    "wof:placetype":"locality",
    "wof:population":410
},
  "geometry": {"coordinates":[81.155764,25.242615],"type":"Point"}
}