{
  "type": "Feature",
  "properties": {
    "gn:admin1_code":"19.0",
    "gn:admin2_code":"582.0",
    "gn:asciiname":"Alumgiri",
    "gn:country_code":"IN",
    "gn:dem":871,
    "gn:feature_class":"P",
    "gn:feature_code":"PPL",
    "gn:name":"\u0100lumgiri",
    "gn:population":0,
    "gn:timezone":"Asia/Kolkata",
    "iso:country":"IN",
    "wof:name":"Alumgiri",
    "wof:placetype":"locality"
},
  "geometry": {"coordinates":[78.05436,13.34241],"type":"Point"}
}