{
  "type": "Feature",
  "properties": {
    "gn:admin1_code":"24.0",
    "gn:admin2_code":"128.0",
    "gn:asciiname":"Acholi",
    "gn:country_code":"IN",
    "gn:dem":337,
    "gn:feature_class":"P",
    "gn:feature_code":"PPL",
    "gn:name":"\u0100choli",
    "gn:population":0,
    "gn:timezone":"Asia/Kolkata",
    "iso:country":"IN",
    "name:deu_x_preferred":[
        "Acholi"
    ],
    "name:fra_x_preferred":[
        "Acholi"
    ],
    "wof:name":"Acholi",
    "wof:placetype":"locality"
},
  "geometry": {"coordinates":[76.85035999999999,24.69936],"type":"Point"}
}