{
  "type": "Feature",
  "properties": {
    "iso:country":"IN",
    "ks:ks_name":"Bhadar",
    "ks:ks_pop":3669,
    "ks:ks_type":"HABITATION",
    "name:eng_x_preferred":[
        "Bhadar"
    ],
    "wof:name":"Bhadar",
    "wof:placetype":"locality",
    "wof:population":3669
},
  "geometry": {"coordinates":[73.813919,23.594407],"type":"Point"}
}