{
  "type": "Feature",
  "properties": {
    "iso:country":"IN",
    "ks:ks_name":"Kanaipur",
    "ks:ks_pop":30,
    "ks:ks_type":"VILLAGE",
    "name:eng_x_preferred":[
        "Kanaipur"
    ],
    "wof:name":"Kanaipur",
    "wof:placetype":"locality",
    "wof:population":30
},
  "geometry": {"coordinates":[88.06374099999999,25.045218],"type":"Point"}
}