{
  "type": "Feature",
  "properties": {
    "iso:country":"IN",
    "qs:name":"Kadapakkam",
    "qs:name_adm0":"India",
    "qs:name_adm1":"Tamil Nadu",
    "qs:photos":3,
    "qs:photos_1k":1,
    "qs:photos_9k":1,
    "qs:photos_9r":1,
    "qs:photos_all":3,
    "qs:photos_sr":1,
    "qs:placetype":"Suburb",
    "qs:pop_sr":"0",
    "wof:name":"Kadapakkam",
    "wof:placetype":"neighbourhood"
},
  "geometry": {"coordinates":[80.213584,13.148358],"type":"Point"}
}