{
  "type": "Feature",
  "properties": {
    "iso:country":"IN",
    "ks:ks_name":"Kukkunja",
    "ks:ks_pop":167,
    "ks:ks_type":"HABITATION",
    "name:eng_x_preferred":[
        "Kukkunja"
    ],
    "wof:name":"Kukkunja",
    "wof:placetype":"locality",
    "wof:population":167
},
  "geometry": {"coordinates":[75.254256,12.715529],"type":"Point"}
}