{
  "type": "Feature",
  "properties": {
    "iso:country":"IN",
    "ks:ks_name":"Pipalyadev",
    "ks:ks_pop":1628,
    "ks:ks_type":"VILLAGE",
    "name:eng_x_preferred":[
        "Pipalyadev"
    ],
    "wof:name":"Pipalyadev",
    "wof:placetype":"locality",
    "wof:population":1628
},
  "geometry": {"coordinates":[75.222607,21.664667],"type":"Point"}
}