{
  "type": "Feature",
  "properties": {
    "iso:country":"IN",
    "ks:ks_name":"Pratap Dighi",
    "ks:ks_pop":2537,
    "ks:ks_type":"VILLAGE",
    "ks:ks_uagg_main":0,
    "name:eng_x_preferred":[
        "Pratap Dighi"
    ],
    "wof:name":"Pratap Dighi",
    "wof:placetype":"neighbourhood",
    "wof:population":2537
},
  "geometry": {"coordinates":[87.60044600000001,21.979781],"type":"Point"}
}