{
  "type": "Feature",
  "properties": {
    "iso:country":"IN",
    "ks:ks_alt_nam":"bhitar rukuba",
    "ks:ks_name":"Bhitar Rukuba",
    "ks:ks_pop":129,
    "ks:ks_type":"HABITATION",
    "name:eng_x_preferred":[
        "Bhitar Rukuba"
    ],
    "wof:name":"Bhitar Rukuba",
    "wof:placetype":"locality",
    "wof:population":129
},
  "geometry": {"coordinates":[82.64456199999999,18.439668],"type":"Point"}
}