{
  "type": "Feature",
  "properties": {
    "iso:country":"IN",
    "ks:ks_name":"Talga Chhari",
    "ks:ks_pop":2973,
    "ks:ks_type":"VILLAGE",
    "ks:ks_uagg_main":0,
    "name:eng_x_preferred":[
        "Talga Chhari"
    ],
    "wof:name":"Talga Chhari",
    "wof:placetype":"neighbourhood",
    "wof:population":2973
},
  "geometry": {"coordinates":[87.56210400000001,21.679781],"type":"Point"}
}