{
  "type": "Feature",
  "properties": {
    "gn:admin1_code":"36.0",
    "gn:admin2_code":"151.0",
    "gn:asciiname":"Ramsala",
    "gn:country_code":"IN",
    "gn:dem":171,
    "gn:feature_class":"P",
    "gn:feature_code":"PPL",
    "gn:name":"R\u0101ms\u0101la",
    "gn:population":0,
    "gn:timezone":"Asia/Kolkata",
    "iso:country":"IN",
    "ks:ks_alt_nam":"R\u0101ms\u0101la",
    "ks:ks_name":"Ramsala",
    "ks:ks_pop":709,
    "ks:ks_type":"VILLAGE",
    "name:eng_x_preferred":[
        "Ramsala"
    ],
    "name:eng_x_variant":[
        "R\u0101ms\u0101la"
    ],
    "name:und_x_variant":[
        "R\u0101ms\u0101la",
        "Mundia"
    ],
    "wof:name":"Ramsala",
    "wof:placetype":"locality",
    "wof:population":709
},
  "geometry": {"coordinates":[79.88245499999999,28.310088],"type":"Point"}
}