{
  "type": "Feature",
  "properties": {
    "gn:admin1_code":"36",
    "gn:admin2_code":"173.0",
    "gn:asciiname":"Dharmpur",
    "gn:country_code":"IN",
    "gn:dem":98,
    "gn:feature_class":"P",
    "gn:feature_code":"PPL",
    "gn:name":"Dharmpur",
    "gn:population":0,
    "gn:timezone":"Asia/Kolkata",
    "iso:country":"IN",
    "name:fra_x_preferred":[
        "Dharampur"
    ],
    "name:new_x_preferred":[
        "\u0927\u0930\u094d\u092e\u092a\u0941\u0930 \u0969"
    ],
    "name:pol_x_preferred":[
        "Dharampur"
    ],
    "wof:name":"Dharmpur",
    "wof:placetype":"locality"
},
  "geometry": {"coordinates":[82.15899999999998,25.89588],"type":"Point"}
}