{
  "type": "Feature",
  "properties": {
    "iso:country":"IN",
    "ks:ks_name":"Vanthala",
    "ks:ks_pop":546,
    "ks:ks_type":"VILLAGE",
    "name:eng_x_preferred":[
        "Vanthala"
    ],
    "wof:name":"Vanthala",
    "wof:placetype":"locality",
    "wof:population":546
},
  "geometry": {"coordinates":[82.616067,18.007885],"type":"Point"}
}