{
  "type": "Feature",
  "properties": {
    "iso:country":"IN",
    "name:eng_x_preferred":[
        "Charni Road"
    ],
    "name:unk_x_variant":[
        "Charni Road"
    ],
    "qs:gn_adm0_cc":"IN",
    "qs:gn_local":1275339,
    "qs:local_max":3819,
    "qs:local_sum":50908,
    "qs:localhoods":70,
    "qs:name":"Charni Road",
    "qs:name_adm0":"India",
    "qs:name_adm1":"Maharashtra",
    "qs:name_adm2":"Mumbai",
    "qs:name_local":"Mumbai",
    "qs:photo_max":152,
    "qs:photo_sum":949,
    "qs:placetype":"Suburb",
    "qs:quad_count":22,
    "qs:woe_adm0":23424848,
    "qs:woe_adm1":2345750,
    "qs:woe_adm2":12586539,
    "qs:woe_lau":0,
    "qs:woe_local":2295411,
    "qs:woe_ver":"7.10.0",
    "wd:wordcount":747,
    "wof:lang":[
        "eng"
    ],
    "wof:name":"Girgaon",
    "wof:placetype":"neighbourhood"
},
  "geometry": {"coordinates":[72.81939800000001,18.952725],"type":"Point"}
}