{
  "type": "Feature",
  "properties": {
    "gn:admin1_code":"10",
    "gn:admin2_code":"82.0",
    "gn:asciiname":"Kishangarh",
    "gn:country_code":"IN",
    "gn:dem":221,
    "gn:feature_class":"P",
    "gn:feature_code":"PPL",
    "gn:name":"Kishangarh",
    "gn:population":0,
    "gn:timezone":"Asia/Kolkata",
    "iso:country":"IN",
    "wof:name":"Kishangarh",
    "wof:placetype":"locality"
},
  "geometry": {"coordinates":[76.29562,28.95641],"type":"Point"}
}