{
  "type": "Feature",
  "properties": {
    "iso:country":"IN",
    "ks:ks_name":"Purabaldahi",
    "ks:ks_pop":1642,
    "ks:ks_type":"VILLAGE",
    "ks:ks_uagg_main":0,
    "name:eng_x_preferred":[
        "Purabaldahi"
    ],
    "wof:name":"Purabaldahi",
    "wof:placetype":"neighbourhood",
    "wof:population":1642
},
  "geometry": {"coordinates":[82.863587,26.22885],"type":"Point"}
}