{
  "type": "Feature",
  "properties": {
    "iso:country":"IN",
    "ks:ks_alt_nam":"Alda  II",
    "ks:ks_name":"Alda Ii",
    "ks:ks_pop":1158,
    "ks:ks_type":"HABITATION",
    "name:eng_x_preferred":[
        "Alda Ii"
    ],
    "name:eng_x_variant":[
        "Alda  II"
    ],
    "wof:name":"Alda Ii",
    "wof:placetype":"locality",
    "wof:population":1158
},
  "geometry": {"coordinates":[86.44365999999999,21.212784],"type":"Point"}
}