{
  "type": "Feature",
  "properties": {
    "gn:admin1_code":"2.0",
    "gn:admin2_code":"554.0",
    "gn:asciiname":"Bangarupalem",
    "gn:country_code":"IN",
    "gn:dem":431,
    "gn:feature_class":"P",
    "gn:feature_code":"PPL",
    "gn:name":"Bang\u0101rup\u0101lem",
    "gn:population":0,
    "gn:timezone":"Asia/Kolkata",
    "iso:country":"IN",
    "name:und_x_variant":[
        "Bang\u0101rup\u0101lem"
    ],
    "wof:name":"Bangarupalem",
    "wof:placetype":"locality"
},
  "geometry": {"coordinates":[78.91283,13.19043],"type":"Point"}
}