{
  "type": "Feature",
  "properties": {
    "iso:country":"IN",
    "ks:ks_alt_nam":"BEL KHORIA KA PURWA",
    "ks:ks_name":"Bel Khoria Ka Purwa",
    "ks:ks_pop":350,
    "ks:ks_type":"HABITATION",
    "name:eng_x_preferred":[
        "Bel Khoria Ka Purwa"
    ],
    "wof:name":"Bel Khoria Ka Purwa",
    "wof:placetype":"locality",
    "wof:population":350
},
  "geometry": {"coordinates":[81.80955,25.59481],"type":"Point"}
}