{
  "type": "Feature",
  "properties": {
    "iso:country":"IN",
    "ks:ks_name":"Bar Phakir",
    "ks:ks_pop":103,
    "ks:ks_type":"VILLAGE",
    "ks:ks_uagg_main":0,
    "name:eng_x_preferred":[
        "Bar Phakir"
    ],
    "wof:name":"Bar Phakir",
    "wof:placetype":"neighbourhood",
    "wof:population":103
},
  "geometry": {"coordinates":[87.41921000000001,22.284674],"type":"Point"}
}