{
  "type": "Feature",
  "properties": {
    "iso:country":"IN",
    "ks:ks_name":"Malaja",
    "ks:ks_pop":1940,
    "ks:ks_type":"VILLAGE",
    "ks:ks_uagg_main":0,
    "name:eng_x_preferred":[
        "Malaja"
    ],
    "wof:name":"Malaja",
    "wof:placetype":"neighbourhood",
    "wof:population":1940
},
  "geometry": {"coordinates":[73.985794,22.349391],"type":"Point"}
}