{
  "type": "Feature",
  "properties": {
    "iso:country":"IN",
    "ks:ks_name":"Daulatpur",
    "ks:ks_pop":64,
    "ks:ks_type":"HABITATION",
    "ks:ks_uagg_main":0,
    "name:eng_x_preferred":[
        "Daulatpur"
    ],
    "wof:name":"Daulatpur",
    "wof:placetype":"neighbourhood",
    "wof:population":64
},
  "geometry": {"coordinates":[80.95667,27.480569],"type":"Point"}
}