{
  "type": "Feature",
  "properties": {
    "gn:admin1_code":"36",
    "gn:admin2_code":"181.0",
    "gn:asciiname":"Haraiya",
    "gn:country_code":"IN",
    "gn:dem":120,
    "gn:feature_class":"P",
    "gn:feature_code":"PPL",
    "gn:name":"Haraiya",
    "gn:population":0,
    "gn:timezone":"Asia/Kolkata",
    "iso:country":"IN",
    "name:ceb_x_preferred":[
        "Haraiya"
    ],
    "name:fra_x_preferred":[
        "Haraiya"
    ],
    "name:hin_x_preferred":[
        "\u0939\u0930\u093f\u092f\u093e"
    ],
    "name:mai_x_preferred":[
        "\u0939\u0930\u0948\u092f\u093e"
    ],
    "name:msa_x_preferred":[
        "Haraiya"
    ],
    "name:nep_x_preferred":[
        "\u0939\u0930\u0948\u092f\u093e"
    ],
    "name:new_x_preferred":[
        "\u0939\u0930\u093f\u092f\u093e"
    ],
    "name:pol_x_preferred":[
        "Haraiya"
    ],
    "wof:name":"Haraiya",
    "wof:placetype":"locality"
},
  "geometry": {"coordinates":[81.71344000000001,27.44948],"type":"Point"}
}