{
  "type": "Feature",
  "properties": {
    "iso:country":"IN",
    "ks:ks_name":"Arakuzha",
    "ks:ks_pop":1200,
    "ks:ks_type":"VILLAGE",
    "name:eng_x_preferred":[
        "Arakuzha"
    ],
    "wof:name":"Arakuzha",
    "wof:placetype":"locality",
    "wof:population":1200
},
  "geometry": {"coordinates":[76.598084,9.934258],"type":"Point"}
}