{
  "type": "Feature",
  "properties": {
    "iso:country":"IN",
    "ks:ks_name":"Chhitapar",
    "ks:ks_pop":493,
    "ks:ks_type":"VILLAGE",
    "name:eng_x_preferred":[
        "Chhitapar"
    ],
    "wof:name":"Chhitapar",
    "wof:placetype":"locality",
    "wof:population":493
},
  "geometry": {"coordinates":[78.28092100000001,23.201253],"type":"Point"}
}