{
  "type": "Feature",
  "properties": {
    "iso:country":"IN",
    "ks:ks_name":"Serithangal",
    "ks:ks_pop":185,
    "ks:ks_type":"HABITATION",
    "name:eng_x_preferred":[
        "Serithangal"
    ],
    "wof:name":"Serithangal",
    "wof:placetype":"locality",
    "wof:population":185
},
  "geometry": {"coordinates":[79.724175,12.900463],"type":"Point"}
}