{
  "type": "Feature",
  "properties": {
    "iso:country":"IN",
    "ks:ks_name":"Asta",
    "ks:ks_pop":242,
    "ks:ks_type":"HABITATION",
    "name:eng_x_preferred":[
        "Asta"
    ],
    "wof:name":"Asta",
    "wof:placetype":"locality",
    "wof:population":242
},
  "geometry": {"coordinates":[83.76442400000001,23.185541],"type":"Point"}
}