{
  "type": "Feature",
  "properties": {
    "gn:admin1_code":"21",
    "gn:admin2_code":"379.0",
    "gn:asciiname":"Righagarh",
    "gn:country_code":"IN",
    "gn:dem":5,
    "gn:feature_class":"P",
    "gn:feature_code":"PPL",
    "gn:name":"Righ\u0101garh",
    "gn:population":0,
    "gn:timezone":"Asia/Kolkata",
    "iso:country":"IN",
    "wof:name":"Righagarh",
    "wof:placetype":"locality"
},
  "geometry": {"coordinates":[86.82145,20.70469],"type":"Point"}
}