{
  "type": "Feature",
  "properties": {
    "iso:country":"IN",
    "ks:ks_alt_nam":"PUNARWASH TOLA",
    "ks:ks_name":"Punarwash Tola",
    "ks:ks_pop":686,
    "ks:ks_type":"HABITATION",
    "ks:ks_uagg_main":0,
    "name:eng_x_preferred":[
        "Punarwash Tola"
    ],
    "wof:name":"Punarwash Tola",
    "wof:placetype":"neighbourhood",
    "wof:population":686
},
  "geometry": {"coordinates":[86.777584,25.535063],"type":"Point"}
}