{
  "type": "Feature",
  "properties": {
    "iso:country":"IN",
    "ks:ks_name":"Imli Ka Pura",
    "ks:ks_pop":129,
    "ks:ks_type":"HABITATION",
    "name:eng_x_preferred":[
        "Imli Ka Pura"
    ],
    "wof:name":"Imli Ka Pura",
    "wof:placetype":"locality",
    "wof:population":129
},
  "geometry": {"coordinates":[78.48329099999999,26.861991],"type":"Point"}
}