{
  "type": "Feature",
  "properties": {
    "iso:country":"IN",
    "ks:ks_name":"Alageshwara Estate",
    "ks:ks_pop":410,
    "ks:ks_type":"HABITATION",
    "name:eng_x_preferred":[
        "Alageshwara Estate"
    ],
    "wof:name":"Alageshwara Estate",
    "wof:placetype":"locality",
    "wof:population":410
},
  "geometry": {"coordinates":[75.38672800000001,13.409144],"type":"Point"}
}