{
  "type": "Feature",
  "properties": {
    "iso:country":"IN",
    "ks:ks_name":"Hazipur",
    "ks:ks_pop":479,
    "ks:ks_type":"VILLAGE",
    "ks:ks_uagg_main":0,
    "name:eng_x_preferred":[
        "Hazipur"
    ],
    "wof:name":"Hazipur",
    "wof:placetype":"neighbourhood",
    "wof:population":479
},
  "geometry": {"coordinates":[75.314111,31.083663],"type":"Point"}
}