{
  "type": "Feature",
  "properties": {
    "gn:admin1_code":"12.0",
    "gn:asciiname":"Urniwali Baihk",
    "gn:country_code":"IN",
    "gn:dem":2650,
    "gn:feature_class":"P",
    "gn:feature_code":"PPL",
    "gn:name":"Urniw\u0101li Baihk",
    "gn:population":0,
    "gn:timezone":"Asia/Kolkata",
    "iso:country":"IN",
    "wof:name":"Urniwali Baihk",
    "wof:placetype":"locality"
},
  "geometry": {"coordinates":[74.09889,34.63374],"type":"Point"}
}