{
  "type": "Feature",
  "properties": {
    "gn:admin1_code":"02",
    "gn:admin2_code":"553.0",
    "gn:asciiname":"Togarakunta",
    "gn:country_code":"IN",
    "gn:dem":444,
    "gn:feature_class":"P",
    "gn:feature_code":"PPL",
    "gn:name":"Togarakunta",
    "gn:population":0,
    "gn:timezone":"Asia/Kolkata",
    "iso:country":"IN",
    "wof:name":"Togarakunta",
    "wof:placetype":"locality"
},
  "geometry": {"coordinates":[77.46007,14.4895],"type":"Point"}
}