{
  "type": "Feature",
  "properties": {
    "gn:admin1_code":"24.0",
    "gn:admin2_code":"101",
    "gn:asciiname":"Bigga",
    "gn:country_code":"IN",
    "gn:dem":297,
    "gn:feature_class":"P",
    "gn:feature_code":"PPL",
    "gn:name":"Bigga",
    "gn:population":0,
    "gn:timezone":"Asia/Kolkata",
    "iso:country":"IN",
    "wof:name":"Bigga",
    "wof:placetype":"locality"
},
  "geometry": {"coordinates":[74.14270999999999,28.06315],"type":"Point"}
}