{
  "type": "Feature",
  "properties": {
    "iso:country":"IN",
    "ks:ks_name":"Lamer",
    "ks:ks_pop":26,
    "ks:ks_type":"VILLAGE",
    "name:eng_x_preferred":[
        "Lamer"
    ],
    "wof:name":"Lamer",
    "wof:placetype":"locality",
    "wof:population":26
},
  "geometry": {"coordinates":[83.4765,20.027294],"type":"Point"}
}