{
  "type": "Feature",
  "properties": {
    "iso:country":"IN",
    "ks:ks_name":"Bulunda",
    "ks:ks_pop":59,
    "ks:ks_type":"VILLAGE",
    "name:eng_x_preferred":[
        "Bulunda"
    ],
    "wof:name":"Bulunda",
    "wof:placetype":"locality",
    "wof:population":59
},
  "geometry": {"coordinates":[84.818645,20.320021],"type":"Point"}
}