{
  "type": "Feature",
  "properties": {
    "gn:admin1_code":"16",
    "gn:admin2_code":"513.0",
    "gn:asciiname":"Borda",
    "gn:country_code":"IN",
    "gn:dem":436,
    "gn:feature_class":"P",
    "gn:feature_code":"PPL",
    "gn:name":"Borda",
    "gn:population":0,
    "gn:timezone":"Asia/Kolkata",
    "iso:country":"IN",
    "wof:name":"Borda",
    "wof:placetype":"locality"
},
  "geometry": {"coordinates":[76.73573,18.82519],"type":"Point"}
}