{
  "type": "Feature",
  "properties": {
    "iso:country":"IN",
    "ks:ks_name":"Kheradewadi",
    "ks:ks_pop":95,
    "ks:ks_type":"HABITATION",
    "name:eng_x_preferred":[
        "Kheradewadi"
    ],
    "wof:name":"Kheradewadi",
    "wof:placetype":"locality",
    "wof:population":95
},
  "geometry": {"coordinates":[73.289067,17.936658],"type":"Point"}
}