{
  "type": "Feature",
  "properties": {
    "iso:country":"IN",
    "ks:ks_name":"Jaltanra",
    "ks:ks_pop":395,
    "ks:ks_type":"VILLAGE",
    "name:eng_x_preferred":[
        "Jaltanra"
    ],
    "wof:name":"Jaltanra",
    "wof:placetype":"locality",
    "wof:population":395
},
  "geometry": {"coordinates":[85.10453699999999,23.086912],"type":"Point"}
}