{
  "type": "Feature",
  "properties": {
    "iso:country":"IN",
    "ks:ks_name":"Sumel",
    "ks:ks_pop":3288,
    "ks:ks_type":"VILLAGE",
    "ks:ks_uagg_main":0,
    "name:eng_x_preferred":[
        "Sumel"
    ],
    "wof:name":"Sumel",
    "wof:placetype":"locality",
    "wof:population":3288
},
  "geometry": {"coordinates":[75.912108,26.91395],"type":"Point"}
}