{
  "type": "Feature",
  "properties": {
    "iso:country":"IN",
    "ks:ks_alt_nam":"Chilawney tar",
    "ks:ks_name":"Chilawney Tar",
    "ks:ks_pop":672,
    "ks:ks_type":"HABITATION",
    "name:eng_x_preferred":[
        "Chilawney Tar"
    ],
    "wof:name":"Chilawney Tar",
    "wof:placetype":"locality",
    "wof:population":672
},
  "geometry": {"coordinates":[88.235119,27.080325],"type":"Point"}
}