{
  "type": "Feature",
  "properties": {
    "gn:admin1_code":"20",
    "gn:admin2_code":"269.0",
    "gn:asciiname":"Lukami",
    "gn:country_code":"IN",
    "gn:dem":1737,
    "gn:feature_class":"P",
    "gn:feature_code":"PPL",
    "gn:name":"Lukami",
    "gn:population":0,
    "gn:timezone":"Asia/Kolkata",
    "iso:country":"IN",
    "wof:name":"Lukami",
    "wof:placetype":"locality"
},
  "geometry": {"coordinates":[94.66667,25.98333],"type":"Point"}
}