{
  "type": "Feature",
  "properties": {
    "iso:country":"IN",
    "ks:ks_name":"Latibpur",
    "ks:ks_pop":80,
    "ks:ks_type":"VILLAGE",
    "ks:ks_uagg_main":0,
    "name:eng_x_preferred":[
        "Latibpur"
    ],
    "wof:name":"Latibpur",
    "wof:placetype":"locality",
    "wof:population":80
},
  "geometry": {"coordinates":[87.28447199999999,22.387712],"type":"Point"}
}