{
  "type": "Feature",
  "properties": {
    "iso:country":"IN",
    "ks:ks_name":"Mirdhapur",
    "ks:ks_pop":368,
    "ks:ks_type":"VILLAGE",
    "name:eng_x_preferred":[
        "Mirdhapur"
    ],
    "wof:name":"Mirdhapur",
    "wof:placetype":"locality",
    "wof:population":368
},
  "geometry": {"coordinates":[87.139314,21.802574],"type":"Point"}
}