{
  "type": "Feature",
  "properties": {
    "iso:country":"IN",
    "ks:ks_alt_nam":"CHARBHAIYA",
    "ks:ks_name":"Charbhaiya",
    "ks:ks_pop":624,
    "ks:ks_type":"HABITATION",
    "name:eng_x_preferred":[
        "Charbhaiya"
    ],
    "wof:name":"Charbhaiya",
    "wof:placetype":"locality",
    "wof:population":624
},
  "geometry": {"coordinates":[83.842598,23.122188],"type":"Point"}
}