{
  "type": "Feature",
  "properties": {
    "iso:country":"IN",
    "ks:ks_name":"Pokhripi",
    "ks:ks_pop":1084,
    "ks:ks_type":"VILLAGE",
    "name:eng_x_preferred":[
        "Pokhripi"
    ],
    "wof:name":"Pokhripi",
    "wof:placetype":"locality",
    "wof:population":1084
},
  "geometry": {"coordinates":[85.60081,22.232801],"type":"Point"}
}