{
  "type": "Feature",
  "properties": {
    "gn:admin1_code":"39.0",
    "gn:admin2_code":"65.0",
    "gn:asciiname":"Bhainsark Khalgada",
    "gn:country_code":"IN",
    "gn:dem":1824,
    "gn:feature_class":"P",
    "gn:feature_code":"PPL",
    "gn:name":"Bhainsark Kh\u0101lgada",
    "gn:population":0,
    "gn:timezone":"Asia/Kolkata",
    "iso:country":"IN",
    "wof:name":"Bhainsark Khalgada",
    "wof:placetype":"locality"
},
  "geometry": {"coordinates":[79.88076,29.40676],"type":"Point"}
}