{
  "type": "Feature",
  "properties": {
    "gn:admin1_code":"24.0",
    "gn:admin2_code":"108.0",
    "gn:asciiname":"Kunchabad Chak Number Three",
    "gn:country_code":"IN",
    "gn:dem":261,
    "gn:feature_class":"P",
    "gn:feature_code":"PPL",
    "gn:name":"K\u016bnch\u0101b\u0101d Chak Number Three",
    "gn:population":0,
    "gn:timezone":"Asia/Kolkata",
    "iso:country":"IN",
    "wof:name":"Kunchabad Chak Number Three",
    "wof:placetype":"neighbourhood"
},
  "geometry": {"coordinates":[76.50479,26.50402],"type":"Point"}
}