{
  "type": "Feature",
  "properties": {
    "gn:admin1_code":"37",
    "gn:admin2_code":"412.0",
    "gn:asciiname":"Patelgura",
    "gn:country_code":"IN",
    "gn:dem":359,
    "gn:feature_class":"P",
    "gn:feature_code":"PPL",
    "gn:name":"Patelgura",
    "gn:population":0,
    "gn:timezone":"Asia/Kolkata",
    "iso:country":"IN",
    "ks:ks_name":"Patelguda",
    "ks:ks_pop":78,
    "ks:ks_type":"VILLAGE",
    "name:eng_x_preferred":[
        "Patelguda"
    ],
    "name:eng_x_variant":[
        "Patelgura"
    ],
    "wof:name":"Patelguda",
    "wof:placetype":"locality",
    "wof:population":78
},
  "geometry": {"coordinates":[81.563473,20.519317],"type":"Point"}
}