{
  "type": "Feature",
  "properties": {
    "iso:country":"IN",
    "ks:ks_name":"Mahuana Dakkihn",
    "ks:ks_pop":138,
    "ks:ks_type":"HABITATION",
    "name:eng_x_preferred":[
        "Mahuana Dakkihn"
    ],
    "wof:name":"Mahuana Dakkihn",
    "wof:placetype":"locality",
    "wof:population":138
},
  "geometry": {"coordinates":[83.198871,27.397178],"type":"Point"}
}