{
  "type": "Feature",
  "properties": {
    "iso:country":"IN",
    "ks:ks_name":"Talojamugura",
    "ks:ks_pop":94,
    "ks:ks_type":"VILLAGE",
    "name:eng_x_preferred":[
        "Talojamugura"
    ],
    "wof:name":"Talojamugura",
    "wof:placetype":"locality",
    "wof:population":94
},
  "geometry": {"coordinates":[83.259715,19.008642],"type":"Point"}
}