{
  "type": "Feature",
  "properties": {
    "iso:country":"IN",
    "ks:ks_name":"Rengabandha",
    "ks:ks_pop":180,
    "ks:ks_type":"HABITATION",
    "name:eng_x_preferred":[
        "Rengabandha"
    ],
    "wof:name":"Rengabandha",
    "wof:placetype":"locality",
    "wof:population":180
},
  "geometry": {"coordinates":[81.802841,18.378147],"type":"Point"}
}