{
  "type": "Feature",
  "properties": {
    "gn:admin1_code":"39",
    "gn:admin2_code":"58.0",
    "gn:asciiname":"Nyalsu",
    "gn:country_code":"IN",
    "gn:dem":1739,
    "gn:feature_class":"P",
    "gn:feature_code":"PPL",
    "gn:name":"Ny\u0101lsu",
    "gn:population":0,
    "gn:timezone":"Asia/Kolkata",
    "iso:country":"IN",
    "wof:name":"Nyalsu",
    "wof:placetype":"locality"
},
  "geometry": {"coordinates":[79.10096,30.61525],"type":"Point"}
}