{
  "type": "Feature",
  "properties": {
    "iso:country":"IN",
    "ks:ks_name":"Jharna Kita",
    "ks:ks_pop":16,
    "ks:ks_type":"VILLAGE",
    "ks:ks_uagg_main":0,
    "name:eng_x_preferred":[
        "Jharna Kita"
    ],
    "wof:name":"Jharna Kita",
    "wof:placetype":"neighbourhood",
    "wof:population":16
},
  "geometry": {"coordinates":[87.332092,25.029658],"type":"Point"}
}