{
  "type": "Feature",
  "properties": {
    "iso:country":"IN",
    "ks:ks_name":"Mambilad",
    "ks:ks_pop":360,
    "ks:ks_type":"HABITATION",
    "name:eng_x_preferred":[
        "Mambilad"
    ],
    "wof:name":"Mambilad",
    "wof:placetype":"locality",
    "wof:population":360
},
  "geometry": {"coordinates":[75.802494,11.666594],"type":"Point"}
}