{
  "type": "Feature",
  "properties": {
    "iso:country":"IN",
    "ks:ks_name":"Diar Syampur",
    "ks:ks_pop":3595,
    "ks:ks_type":"VILLAGE",
    "name:eng_x_preferred":[
        "Diar Syampur"
    ],
    "wof:name":"Diar Syampur",
    "wof:placetype":"locality",
    "wof:population":3595
},
  "geometry": {"coordinates":[88.30039600000001,24.346505],"type":"Point"}
}