{
  "type": "Feature",
  "properties": {
    "iso:country":"IN",
    "ks:ks_name":"Bir Dhandari",
    "ks:ks_pop":875,
    "ks:ks_type":"HABITATION",
    "name:eng_x_preferred":[
        "Bir Dhandari"
    ],
    "wof:name":"Bir Dhandari",
    "wof:placetype":"locality",
    "wof:population":875
},
  "geometry": {"coordinates":[76.83252899999999,29.777461],"type":"Point"}
}