{
  "type": "Feature",
  "properties": {
    "iso:country":"IN",
    "ks:ks_alt_nam":"JAMUNZIRA",
    "ks:ks_name":"Jamunzira",
    "ks:ks_pop":108,
    "ks:ks_type":"HABITATION",
    "name:eng_x_preferred":[
        "Jamunzira"
    ],
    "wof:name":"Jamunzira",
    "wof:placetype":"locality",
    "wof:population":108
},
  "geometry": {"coordinates":[75.65329,21.241717],"type":"Point"}
}