{
  "type": "Feature",
  "properties": {
    "iso:country":"IN",
    "ks:ks_name":"Nikitipadar",
    "ks:ks_pop":221,
    "ks:ks_type":"HABITATION",
    "name:eng_x_preferred":[
        "Nikitipadar"
    ],
    "wof:name":"Nikitipadar",
    "wof:placetype":"locality",
    "wof:population":221
},
  "geometry": {"coordinates":[83.12640500000001,18.805394],"type":"Point"}
}