{
  "type": "Feature",
  "properties": {
    "gn:admin1_code":"23.0",
    "gn:admin2_code":"35.0",
    "gn:asciiname":"Bodhani Talab",
    "gn:country_code":"IN",
    "gn:dem":565,
    "gn:feature_class":"P",
    "gn:feature_code":"PPL",
    "gn:name":"Bodhani Tal\u0101b",
    "gn:population":0,
    "gn:timezone":"Asia/Kolkata",
    "iso:country":"IN",
    "wof:name":"Bodhani Talab",
    "wof:placetype":"locality"
},
  "geometry": {"coordinates":[75.76883000000002,32.33073],"type":"Point"}
}