{
  "type": "Feature",
  "properties": {
    "gn:admin1_code":"19.0",
    "gn:admin2_code":"581.0",
    "gn:asciiname":"Achampalli",
    "gn:country_code":"IN",
    "gn:dem":833,
    "gn:feature_class":"P",
    "gn:feature_code":"PPL",
    "gn:name":"Achampalli",
    "gn:population":0,
    "gn:timezone":"Asia/Kolkata",
    "iso:country":"IN",
    "name:fas_x_preferred":[
        "\u0627\u0686\u0627\u0645\u067e\u0627\u0644\u06cc"
    ],
    "wof:name":"Achampalli",
    "wof:placetype":"locality"
},
  "geometry": {"coordinates":[78.32024,13.29104],"type":"Point"}
}