{
  "type": "Feature",
  "properties": {
    "gn:admin1_code":"36",
    "gn:admin2_code":"201.0",
    "gn:asciiname":"Kharsela",
    "gn:country_code":"IN",
    "gn:dem":160,
    "gn:feature_class":"P",
    "gn:feature_code":"PPL",
    "gn:name":"Kharsela",
    "gn:population":0,
    "gn:timezone":"Asia/Kolkata",
    "iso:country":"IN",
    "name:und_x_variant":[
        "Nagla Painth"
    ],
    "wof:name":"Kharsela",
    "wof:placetype":"neighbourhood"
},
  "geometry": {"coordinates":[79.07733,27.46839],"type":"Point"}
}