{
  "type": "Feature",
  "properties": {
    "gn:admin1_code":"35.0",
    "gn:admin2_code":"454",
    "gn:asciiname":"Baila",
    "gn:country_code":"IN",
    "gn:dem":715,
    "gn:feature_class":"P",
    "gn:feature_code":"PPL",
    "gn:name":"Baila",
    "gn:population":0,
    "gn:timezone":"Asia/Kolkata",
    "iso:country":"IN",
    "name:fra_x_preferred":[
        "Baila"
    ],
    "wof:name":"Baila",
    "wof:placetype":"locality"
},
  "geometry": {"coordinates":[81.04111,22.315],"type":"Point"}
}