{
  "type": "Feature",
  "properties": {
    "gn:admin1_code":"34.0",
    "gn:admin2_code":"222.0",
    "gn:asciiname":"Abhuar",
    "gn:country_code":"IN",
    "gn:dem":43,
    "gn:feature_class":"P",
    "gn:feature_code":"PPL",
    "gn:name":"Abhuar",
    "gn:population":0,
    "gn:timezone":"Asia/Kolkata",
    "iso:country":"IN",
    "wof:name":"Abhuar",
    "wof:placetype":"locality"
},
  "geometry": {"coordinates":[86.22434,25.56789],"type":"Point"}
}