{
  "type": "Feature",
  "properties": {
    "iso:country":"IN",
    "ks:ks_name":"Merha",
    "ks:ks_pop":314,
    "ks:ks_type":"VILLAGE",
    "name:eng_x_preferred":[
        "Merha"
    ],
    "wof:name":"Merha",
    "wof:placetype":"locality",
    "wof:population":314
},
  "geometry": {"coordinates":[85.891744,23.559963],"type":"Point"}
}