{
  "type": "Feature",
  "properties": {
    "iso:country":"IN",
    "ks:ks_name":"Uttar Khatowal",
    "ks:ks_pop":6179,
    "ks:ks_type":"VILLAGE",
    "name:eng_x_preferred":[
        "Uttar Khatowal"
    ],
    "wof:name":"Uttar Khatowal",
    "wof:placetype":"locality",
    "wof:population":6179
},
  "geometry": {"coordinates":[92.696896,26.448223],"type":"Point"}
}