{
  "type": "Feature",
  "properties": {
    "iso:country":"IN",
    "ks:ks_name":"Slari Kheda",
    "ks:ks_pop":330,
    "ks:ks_type":"HABITATION",
    "ks:ks_uagg_main":0,
    "name:eng_x_preferred":[
        "Slari Kheda"
    ],
    "wof:name":"Slari Kheda",
    "wof:placetype":"neighbourhood",
    "wof:population":330
},
  "geometry": {"coordinates":[80.300411,26.851955],"type":"Point"}
}