{
  "type": "Feature",
  "properties": {
    "iso:country":"IN",
    "ks:ks_alt_nam":"NORTH TOLA",
    "ks:ks_name":"North Tola",
    "ks:ks_pop":660,
    "ks:ks_type":"HABITATION",
    "name:eng_x_preferred":[
        "North Tola"
    ],
    "wof:name":"North Tola",
    "wof:placetype":"locality",
    "wof:population":660
},
  "geometry": {"coordinates":[84.944649,25.908114],"type":"Point"}
}