{
  "type": "Feature",
  "properties": {
    "gn:admin1_code":"13.0",
    "gn:admin2_code":"598.0",
    "gn:asciiname":"Triperuntura",
    "gn:country_code":"IN",
    "gn:dem":3,
    "gn:feature_class":"P",
    "gn:feature_code":"PPL",
    "gn:name":"Triperuntura",
    "gn:population":0,
    "gn:timezone":"Asia/Kolkata",
    "iso:country":"IN",
    "wof:name":"Triperuntura",
    "wof:placetype":"locality"
},
  "geometry": {"coordinates":[76.59214,9.2798],"type":"Point"}
}