{
  "type": "Feature",
  "properties": {
    "gn:admin1_code":"19.0",
    "gn:admin2_code":"581.0",
    "gn:asciiname":"Chik Igalur",
    "gn:country_code":"IN",
    "gn:dem":884,
    "gn:feature_class":"P",
    "gn:feature_code":"PPL",
    "gn:name":"Chik Igal\u016br",
    "gn:population":0,
    "gn:timezone":"Asia/Kolkata",
    "iso:country":"IN",
    "wof:name":"Chik Igalur",
    "wof:placetype":"neighbourhood"
},
  "geometry": {"coordinates":[77.97069,12.91467],"type":"Point"}
}