{
  "type": "Feature",
  "properties": {
    "iso:country":"IN",
    "ks:ks_name":"Piproda Khurd",
    "ks:ks_pop":5079,
    "ks:ks_type":"VILLAGE",
    "ks:ks_uagg_main":0,
    "name:eng_x_preferred":[
        "Piproda Khurd"
    ],
    "wof:name":"Piproda Khurd",
    "wof:placetype":"neighbourhood",
    "wof:population":5079
},
  "geometry": {"coordinates":[77.314995,24.663403],"type":"Point"}
}