{
  "type": "Feature",
  "properties": {
    "iso:country":"IN",
    "ks:ks_name":"Pallippattu",
    "ks:ks_pop":1897,
    "ks:ks_type":"VILLAGE",
    "ks:ks_uagg_main":0,
    "name:eng_x_preferred":[
        "Pallippattu"
    ],
    "wof:name":"Pallippattu",
    "wof:placetype":"neighbourhood",
    "wof:population":1897
},
  "geometry": {"coordinates":[79.71134000000001,11.839913],"type":"Point"}
}