{
  "type": "Feature",
  "properties": {
    "iso:country":"IN",
    "ks:ks_name":"Maitala",
    "ks:ks_pop":2219,
    "ks:ks_type":"VILLAGE",
    "ks:ks_uagg_main":0,
    "name:eng_x_preferred":[
        "Maitala"
    ],
    "wof:name":"Maitala",
    "wof:placetype":"neighbourhood",
    "wof:population":2219
},
  "geometry": {"coordinates":[88.372434,22.230757],"type":"Point"}
}