{
  "type": "Feature",
  "properties": {
    "gn:admin1_code":"12.0",
    "gn:admin2_code":"22.0",
    "gn:asciiname":"Naran",
    "gn:country_code":"IN",
    "gn:dem":342,
    "gn:feature_class":"P",
    "gn:feature_code":"PPL",
    "gn:name":"N\u0101ran",
    "gn:population":0,
    "gn:timezone":"Asia/Kolkata",
    "iso:country":"IN",
    "name:ceb_x_preferred":[
        "Naran"
    ],
    "name:fas_x_preferred":[
        "\u0646\u0627\u0631\u0627\u0646"
    ],
    "name:swe_x_preferred":[
        "Naran"
    ],
    "wof:name":"Naran",
    "wof:placetype":"locality"
},
  "geometry": {"coordinates":[75.15764,32.50648],"type":"Point"}
}