{
  "type": "Feature",
  "properties": {
    "iso:country":"IN",
    "ks:ks_name":"Manatari",
    "ks:ks_pop":1148,
    "ks:ks_type":"HABITATION",
    "name:eng_x_preferred":[
        "Manatari"
    ],
    "wof:name":"Manatari",
    "wof:placetype":"locality",
    "wof:population":1148
},
  "geometry": {"coordinates":[89.462738,26.2207],"type":"Point"}
}