{
  "type": "Feature",
  "properties": {
    "iso:country":"IN",
    "ks:ks_name":"Patilpada",
    "ks:ks_pop":270,
    "ks:ks_type":"HABITATION",
    "name:eng_x_preferred":[
        "Patilpada"
    ],
    "wof:name":"Patilpada",
    "wof:placetype":"locality",
    "wof:population":270
},
  "geometry": {"coordinates":[72.91289500000001,19.891486],"type":"Point"}
}