{
  "type": "Feature",
  "properties": {
    "iso:country":"IN",
    "ks:ks_alt_nam":"K.Majhiguda",
    "ks:ks_name":"K.majhiguda",
    "ks:ks_pop":639,
    "ks:ks_type":"HABITATION",
    "name:eng_x_preferred":[
        "K.majhiguda"
    ],
    "wof:name":"K.majhiguda",
    "wof:placetype":"locality",
    "wof:population":639
},
  "geometry": {"coordinates":[82.159013,18.526114],"type":"Point"}
}