{
  "type": "Feature",
  "properties": {
    "iso:country":"IN",
    "ks:ks_name":"Periyaperumalpatty",
    "ks:ks_pop":310,
    "ks:ks_type":"HABITATION",
    "name:eng_x_preferred":[
        "Periyaperumalpatty"
    ],
    "wof:name":"Periyaperumalpatty",
    "wof:placetype":"locality",
    "wof:population":310
},
  "geometry": {"coordinates":[78.492512,9.889237],"type":"Point"}
}