{
  "type": "Feature",
  "properties": {
    "iso:country":"IN",
    "ks:ks_alt_nam":"Komatpally LT",
    "ks:ks_name":"Komatpally Lt",
    "ks:ks_pop":1,
    "ks:ks_type":"HABITATION",
    "name:eng_x_preferred":[
        "Komatpally Lt"
    ],
    "wof:name":"Komatpally Lt",
    "wof:placetype":"locality",
    "wof:population":1
},
  "geometry": {"coordinates":[78.451199,18.090769],"type":"Point"}
}