{
  "type": "Feature",
  "properties": {
    "gn:admin1_code":"39.0",
    "gn:admin2_code":"65.0",
    "gn:asciiname":"Manglalekh",
    "gn:country_code":"IN",
    "gn:dem":1436,
    "gn:feature_class":"P",
    "gn:feature_code":"PPL",
    "gn:name":"Manglalekh",
    "gn:population":0,
    "gn:timezone":"Asia/Kolkata",
    "iso:country":"IN",
    "wof:name":"Manglalekh",
    "wof:placetype":"locality"
},
  "geometry": {"coordinates":[79.89013,29.31696],"type":"Point"}
}