{
  "type": "Feature",
  "properties": {
    "iso:country":"IN",
    "ks:ks_name":"Londhewasti",
    "ks:ks_pop":120,
    "ks:ks_type":"HABITATION",
    "name:eng_x_preferred":[
        "Londhewasti"
    ],
    "wof:name":"Londhewasti",
    "wof:placetype":"locality",
    "wof:population":120
},
  "geometry": {"coordinates":[74.477293,18.799763],"type":"Point"}
}