{
  "type": "Feature",
  "properties": {
    "iso:country":"IN",
    "ks:ks_name":"Pasiyan",
    "ks:ks_pop":160,
    "ks:ks_type":"HABITATION",
    "name:eng_x_preferred":[
        "Pasiyan"
    ],
    "wof:name":"Pasiyan",
    "wof:placetype":"locality",
    "wof:population":160
},
  "geometry": {"coordinates":[82.109908,25.861904],"type":"Point"}
}