{
  "type": "Feature",
  "properties": {
    "iso:country":"IN",
    "ks:ks_name":"Talav Falia",
    "ks:ks_pop":1395,
    "ks:ks_type":"HABITATION",
    "name:eng_x_preferred":[
        "Talav Falia"
    ],
    "wof:name":"Talav Falia",
    "wof:placetype":"locality",
    "wof:population":1395
},
  "geometry": {"coordinates":[74.17063899999999,22.740361],"type":"Point"}
}