{
  "type": "Feature",
  "properties": {
    "gn:admin1_code":"36.0",
    "gn:admin2_code":"158.0",
    "gn:asciiname":"Hakganj",
    "gn:country_code":"IN",
    "gn:dem":109,
    "gn:feature_class":"P",
    "gn:feature_code":"PPL",
    "gn:name":"H\u0101kganj",
    "gn:population":0,
    "gn:timezone":"Asia/Kolkata",
    "iso:country":"IN",
    "ks:ks_alt_nam":"H\u0101kganj",
    "ks:ks_name":"Hakganj",
    "ks:ks_pop":835,
    "ks:ks_type":"VILLAGE",
    "name:eng_x_preferred":[
        "Hakganj"
    ],
    "name:eng_x_variant":[
        "H\u0101kganj"
    ],
    "wof:name":"Hakganj",
    "wof:placetype":"locality",
    "wof:population":835
},
  "geometry": {"coordinates":[81.390562,25.983882],"type":"Point"}
}