{
  "type": "Feature",
  "properties": {
    "iso:country":"IN",
    "ks:ks_name":"Sukanjhora Pt II",
    "ks:ks_pop":175,
    "ks:ks_type":"VILLAGE",
    "name:eng_x_preferred":[
        "Sukanjhora Pt II"
    ],
    "wof:name":"Sukanjhora Pt II",
    "wof:placetype":"locality",
    "wof:population":175
},
  "geometry": {"coordinates":[90.05916999999999,26.208988],"type":"Point"}
}