{
  "type": "Feature",
  "properties": {
    "iso:country":"IN",
    "ks:ks_name":"Baotalai",
    "ks:ks_pop":785,
    "ks:ks_type":"VILLAGE",
    "name:eng_x_preferred":[
        "Baotalai"
    ],
    "wof:name":"Baotalai",
    "wof:placetype":"locality",
    "wof:population":785
},
  "geometry": {"coordinates":[71.411773,24.965099],"type":"Point"}
}