{
  "type": "Feature",
  "properties": {
    "gn:admin1_code":"34.0",
    "gn:admin2_code":"221.0",
    "gn:asciiname":"Narayanpur Darhia",
    "gn:country_code":"IN",
    "gn:dem":54,
    "gn:feature_class":"P",
    "gn:feature_code":"PPL",
    "gn:name":"N\u0101r\u0101yanpur Darhia",
    "gn:population":0,
    "gn:timezone":"Asia/Kolkata",
    "iso:country":"IN",
    "ks:ks_name":"Naraenpur Darhia",
    "ks:ks_pop":319,
    "ks:ks_type":"VILLAGE",
    "name:eng_x_preferred":[
        "Naraenpur Darhia"
    ],
    "name:eng_x_variant":[
        "Narayanpur Darhia"
    ],
    "wof:name":"Naraenpur Darhia",
    "wof:placetype":"locality",
    "wof:population":319
},
  "geometry": {"coordinates":[85.731889,25.870417],"type":"Point"}
}