{
  "type": "Feature",
  "properties": {
    "iso:country":"IN",
    "ks:ks_name":"Purani Kaibatra",
    "ks:ks_pop":564,
    "ks:ks_type":"HABITATION",
    "name:eng_x_preferred":[
        "Purani Kaibatra"
    ],
    "wof:name":"Purani Kaibatra",
    "wof:placetype":"locality",
    "wof:population":564
},
  "geometry": {"coordinates":[95.34302099999999,27.286601],"type":"Point"}
}