{
  "type": "Feature",
  "properties": {
    "iso:country":"IN",
    "ks:ks_name":"Chhotki Banjariya 2",
    "ks:ks_pop":165,
    "ks:ks_type":"HABITATION",
    "name:eng_x_preferred":[
        "Chhotki Banjariya 2"
    ],
    "wof:name":"Chhotki Banjariya 2",
    "wof:placetype":"locality",
    "wof:population":165
},
  "geometry": {"coordinates":[81.82178500000001,27.265819],"type":"Point"}
}