{
  "type": "Feature",
  "properties": {
    "gn:admin1_code":"36.0",
    "gn:admin2_code":"183.0",
    "gn:asciiname":"Ausanpur",
    "gn:country_code":"IN",
    "gn:dem":99,
    "gn:feature_class":"P",
    "gn:feature_code":"PPL",
    "gn:name":"Ausanpur",
    "gn:population":0,
    "gn:timezone":"Asia/Kolkata",
    "iso:country":"IN",
    "name:urd_x_preferred":[
        "\u0627\u0648\u0633\u0627\u0646 \u067e\u0648\u0631"
    ],
    "wof:name":"Ausanpur",
    "wof:placetype":"locality"
},
  "geometry": {"coordinates":[82.20900999999998,26.92201],"type":"Point"}
}