{
  "type": "Feature",
  "properties": {
    "iso:country":"IN",
    "ks:ks_name":"Brundabanpur",
    "ks:ks_pop":427,
    "ks:ks_type":"VILLAGE",
    "ks:ks_uagg_main":0,
    "name:eng_x_preferred":[
        "Brundabanpur"
    ],
    "wof:name":"Brundabanpur",
    "wof:placetype":"neighbourhood",
    "wof:population":427
},
  "geometry": {"coordinates":[87.12159800000001,21.654547],"type":"Point"}
}