{
  "type": "Feature",
  "properties": {
    "iso:country":"IN",
    "ks:ks_name":"Kasimpur",
    "ks:ks_pop":1041,
    "ks:ks_type":"VILLAGE",
    "ks:ks_uagg_main":0,
    "name:eng_x_preferred":[
        "Kasimpur"
    ],
    "wof:name":"Kasimpur",
    "wof:placetype":"neighbourhood",
    "wof:population":1041
},
  "geometry": {"coordinates":[79.26997799999999,26.302994],"type":"Point"}
}