{
  "type": "Feature",
  "properties": {
    "iso:country":"IN",
    "ks:ks_name":"Chokkampatty",
    "ks:ks_pop":127,
    "ks:ks_type":"HABITATION",
    "name:eng_x_preferred":[
        "Chokkampatty"
    ],
    "wof:name":"Chokkampatty",
    "wof:placetype":"locality",
    "wof:population":127
},
  "geometry": {"coordinates":[78.455918,10.661725],"type":"Point"}
}