{
  "type": "Feature",
  "properties": {
    "iso:country":"IN",
    "ks:ks_name":"Warghadpada",
    "ks:ks_pop":269,
    "ks:ks_type":"HABITATION",
    "name:eng_x_preferred":[
        "Warghadpada"
    ],
    "wof:name":"Warghadpada",
    "wof:placetype":"locality",
    "wof:population":269
},
  "geometry": {"coordinates":[73.34473800000001,20.004941],"type":"Point"}
}