{
  "type": "Feature",
  "properties": {
    "iso:country":"IN",
    "ks:ks_name":"Jamuniya Tola",
    "ks:ks_pop":564,
    "ks:ks_type":"HABITATION",
    "name:eng_x_preferred":[
        "Jamuniya Tola"
    ],
    "wof:name":"Jamuniya Tola",
    "wof:placetype":"locality",
    "wof:population":564
},
  "geometry": {"coordinates":[87.26922,25.257312],"type":"Point"}
}