{
  "type": "Feature",
  "properties": {
    "iso:country":"IN",
    "ks:ks_alt_nam":"KOHWA BASA",
    "ks:ks_name":"Kohwa Basa",
    "ks:ks_pop":351,
    "ks:ks_type":"HABITATION",
    "ks:ks_uagg_main":0,
    "name:eng_x_preferred":[
        "Kohwa Basa"
    ],
    "wof:name":"Kohwa Basa",
    "wof:placetype":"neighbourhood",
    "wof:population":351
},
  "geometry": {"coordinates":[86.73078,25.555646],"type":"Point"}
}