{
  "type": "Feature",
  "properties": {
    "iso:country":"IN",
    "ks:ks_name":"Maithalakeri",
    "ks:ks_pop":219,
    "ks:ks_type":"HABITATION",
    "name:eng_x_preferred":[
        "Maithalakeri"
    ],
    "wof:name":"Maithalakeri",
    "wof:placetype":"locality",
    "wof:population":219
},
  "geometry": {"coordinates":[74.621182,14.231527],"type":"Point"}
}