{
  "type": "Feature",
  "properties": {
    "iso:country":"IN",
    "ks:ks_name":"Saliwada Chak",
    "ks:ks_pop":40,
    "ks:ks_type":"HABITATION",
    "name:eng_x_preferred":[
        "Saliwada Chak"
    ],
    "wof:name":"Saliwada Chak",
    "wof:placetype":"locality",
    "wof:population":40
},
  "geometry": {"coordinates":[80.17816500000001,22.52985],"type":"Point"}
}