{
  "type": "Feature",
  "properties": {
    "iso:country":"IN",
    "ks:ks_alt_nam":"DUKHAI JAMADAR PARA",
    "ks:ks_name":"Dukhai Jamadar Para",
    "ks:ks_pop":399,
    "ks:ks_type":"HABITATION",
    "name:eng_x_preferred":[
        "Dukhai Jamadar Para"
    ],
    "wof:name":"Dukhai Jamadar Para",
    "wof:placetype":"locality",
    "wof:population":399
},
  "geometry": {"coordinates":[91.59257700000001,23.866806],"type":"Point"}
}