{
  "type": "Feature",
  "properties": {
    "iso:country":"IN",
    "ks:ks_name":"Manpur North",
    "ks:ks_pop":1973,
    "ks:ks_type":"VILLAGE",
    "ks:ks_uagg_main":0,
    "name:eng_x_preferred":[
        "Manpur North"
    ],
    "wof:name":"Manpur North",
    "wof:placetype":"neighbourhood",
    "wof:population":1973
},
  "geometry": {"coordinates":[79.080573,29.103379],"type":"Point"}
}