{
  "type": "Feature",
  "properties": {
    "iso:country":"IN",
    "ks:ks_name":"Bailur",
    "ks:ks_pop":390,
    "ks:ks_type":"VILLAGE",
    "name:eng_x_preferred":[
        "Bailur"
    ],
    "wof:name":"Bailur",
    "wof:placetype":"locality",
    "wof:population":390
},
  "geometry": {"coordinates":[74.484281,14.13126],"type":"Point"}
}