{
  "type": "Feature",
  "properties": {
    "gn:admin1_code":"16.0",
    "gn:admin2_code":"499.0",
    "gn:asciiname":"Bamrud",
    "gn:country_code":"IN",
    "gn:dem":296,
    "gn:feature_class":"P",
    "gn:feature_code":"PPL",
    "gn:name":"B\u0101mrud",
    "gn:population":0,
    "gn:timezone":"Asia/Kolkata",
    "iso:country":"IN",
    "name:ceb_x_preferred":[
        "Bamr\u016bd"
    ],
    "name:fas_x_preferred":[
        "\u0628\u0645\u0631\u0648\u062f"
    ],
    "name:swe_x_preferred":[
        "Bamr\u016bd"
    ],
    "wof:name":"Bamrud",
    "wof:placetype":"locality"
},
  "geometry": {"coordinates":[75.10298,20.59519],"type":"Point"}
}