{
  "type": "Feature",
  "properties": {
    "iso:country":"IN",
    "ks:ks_name":"Bhitarkanika",
    "ks:ks_pop":0,
    "ks:ks_type":"VILLAGE",
    "name:eng_x_preferred":[
        "Bhitarkanika"
    ],
    "wof:name":"Bhitarkanika",
    "wof:placetype":"locality",
    "wof:population":0
},
  "geometry": {"coordinates":[86.866974,20.719748],"type":"Point"}
}