{
  "type": "Feature",
  "properties": {
    "gn:admin1_code":"34.0",
    "gn:admin2_code":"213.0",
    "gn:asciiname":"Birnagar",
    "gn:country_code":"IN",
    "gn:dem":46,
    "gn:feature_class":"P",
    "gn:feature_code":"PPL",
    "gn:name":"Birnagar",
    "gn:population":0,
    "gn:timezone":"Asia/Kolkata",
    "iso:country":"IN",
    "ks:ks_name":"Pirnagar",
    "ks:ks_pop":664,
    "ks:ks_type":"VILLAGE",
    "ks:ks_uagg_main":0,
    "name:ben_x_preferred":[
        "\u09ac\u09c0\u09b0\u09a8\u0997\u09b0"
    ],
    "name:bpy_x_preferred":[
        "\u09ac\u09c0\u09b0\u09a8\u0997\u09b0"
    ],
    "name:eng_x_preferred":[
        "Pirnagar"
    ],
    "name:ita_x_preferred":[
        "Birnagar"
    ],
    "name:msa_x_preferred":[
        "Birnagar"
    ],
    "name:new_x_preferred":[
        "\u0935\u0940\u0930\u0928\u0917\u0930"
    ],
    "name:por_x_preferred":[
        "Birnagar"
    ],
    "name:spa_x_preferred":[
        "Birnagar"
    ],
    "name:swe_x_preferred":[
        "Birnagar"
    ],
    "name:vie_x_preferred":[
        "Birnagar"
    ],
    "name:zho_x_preferred":[
        "\u6bd4\u5c14\u7eb3\u52a0\u5c14"
    ],
    "wof:name":"Pirnagar",
    "wof:placetype":"neighbourhood",
    "wof:population":664
},
  "geometry": {"coordinates":[86.872058,25.726312],"type":"Point"}
}