{
  "type": "Feature",
  "properties": {
    "iso:country":"IN",
    "ks:ks_name":"Dade Purwa",
    "ks:ks_pop":47,
    "ks:ks_type":"HABITATION",
    "name:eng_x_preferred":[
        "Dade Purwa"
    ],
    "wof:name":"Dade Purwa",
    "wof:placetype":"locality",
    "wof:population":47
},
  "geometry": {"coordinates":[81.312922,27.727362],"type":"Point"}
}