{
  "type": "Feature",
  "properties": {
    "iso:country":"IN",
    "ks:ks_alt_nam":"kandlakunta thanda",
    "ks:ks_name":"Kandlakunta Thanda",
    "ks:ks_pop":187,
    "ks:ks_type":"HABITATION",
    "name:eng_x_preferred":[
        "Kandlakunta Thanda"
    ],
    "wof:name":"Kandlakunta Thanda",
    "wof:placetype":"locality",
    "wof:population":187
},
  "geometry": {"coordinates":[78.899922,17.39408],"type":"Point"}
}