{
  "type": "Feature",
  "properties": {
    "gn:admin1_code":"11",
    "gn:admin2_code":"32.0",
    "gn:asciiname":"Sail",
    "gn:country_code":"IN",
    "gn:dem":1971,
    "gn:feature_class":"P",
    "gn:feature_code":"PPL",
    "gn:name":"Sail",
    "gn:population":0,
    "gn:timezone":"Asia/Kolkata",
    "iso:country":"IN",
    "wof:name":"Sail",
    "wof:placetype":"locality"
},
  "geometry": {"coordinates":[77.51235,30.77637],"type":"Point"}
}