{
  "type": "Feature",
  "properties": {
    "iso:country":"IN",
    "ks:ks_name":"Guphapara",
    "ks:ks_pop":148,
    "ks:ks_type":"HABITATION",
    "name:eng_x_preferred":[
        "Guphapara"
    ],
    "wof:name":"Guphapara",
    "wof:placetype":"locality",
    "wof:population":148
},
  "geometry": {"coordinates":[81.27642899999999,19.13742],"type":"Point"}
}