{
  "type": "Feature",
  "properties": {
    "iso:country":"IN",
    "ks:ks_name":"Chana Ki Umar",
    "ks:ks_pop":422,
    "ks:ks_type":"VILLAGE",
    "name:eng_x_preferred":[
        "Chana Ki Umar"
    ],
    "wof:name":"Chana Ki Umar",
    "wof:placetype":"locality",
    "wof:population":422
},
  "geometry": {"coordinates":[73.261792,24.791189],"type":"Point"}
}