{
  "type": "Feature",
  "properties": {
    "iso:country":"IN",
    "ks:ks_alt_nam":"gurbad",
    "ks:ks_name":"Gurbad",
    "ks:ks_pop":312,
    "ks:ks_type":"HABITATION",
    "name:eng_x_preferred":[
        "Gurbad"
    ],
    "wof:name":"Gurbad",
    "wof:placetype":"locality",
    "wof:population":312
},
  "geometry": {"coordinates":[86.77560699999999,24.086492],"type":"Point"}
}