{
  "type": "Feature",
  "properties": {
    "iso:country":"IN",
    "ks:ks_name":"Neemdih",
    "ks:ks_pop":268,
    "ks:ks_type":"HABITATION",
    "name:eng_x_preferred":[
        "Neemdih"
    ],
    "wof:name":"Neemdih",
    "wof:placetype":"locality",
    "wof:population":268
},
  "geometry": {"coordinates":[82.468394,24.874266],"type":"Point"}
}