{
  "type": "Feature",
  "properties": {
    "iso:country":"IN",
    "ks:ks_name":"Nimha",
    "ks:ks_pop":465,
    "ks:ks_type":"VILLAGE",
    "name:eng_x_preferred":[
        "Nimha"
    ],
    "wof:name":"Nimha",
    "wof:placetype":"locality",
    "wof:population":465
},
  "geometry": {"coordinates":[82.149889,23.339691],"type":"Point"}
}