{
  "type": "Feature",
  "properties": {
    "iso:country":"IN",
    "ks:ks_name":"Borpatoria",
    "ks:ks_pop":740,
    "ks:ks_type":"VILLAGE",
    "ks:ks_uagg_main":0,
    "name:eng_x_preferred":[
        "Borpatoria"
    ],
    "wof:name":"Borpatoria",
    "wof:placetype":"neighbourhood",
    "wof:population":740
},
  "geometry": {"coordinates":[94.571865,27.476712],"type":"Point"}
}