{
  "type": "Feature",
  "properties": {
    "iso:country":"IN",
    "ks:ks_name":"Navedarwadi",
    "ks:ks_pop":27,
    "ks:ks_type":"HABITATION",
    "ks:ks_uagg_main":0,
    "name:eng_x_preferred":[
        "Navedarwadi"
    ],
    "wof:name":"Navedarwadi",
    "wof:placetype":"neighbourhood",
    "wof:population":27
},
  "geometry": {"coordinates":[73.245861,17.197407],"type":"Point"}
}