{
  "type": "Feature",
  "properties": {
    "iso:country":"IN",
    "ks:ks_name":"Musaharan Basti",
    "ks:ks_pop":70,
    "ks:ks_type":"HABITATION",
    "name:eng_x_preferred":[
        "Musaharan Basti"
    ],
    "wof:name":"Musaharan Basti",
    "wof:placetype":"locality",
    "wof:population":70
},
  "geometry": {"coordinates":[82.581937,25.081614],"type":"Point"}
}