{
  "type": "Feature",
  "properties": {
    "iso:country":"IN",
    "ks:ks_alt_nam":"BALTHAR",
    "ks:ks_name":"Balthar",
    "ks:ks_pop":105,
    "ks:ks_type":"HABITATION",
    "name:eng_x_preferred":[
        "Balthar"
    ],
    "wof:name":"Balthar",
    "wof:placetype":"locality",
    "wof:population":105
},
  "geometry": {"coordinates":[84.50557499999999,24.543363],"type":"Point"}
}