{
  "type": "Feature",
  "properties": {
    "gn:admin1_code":"19.0",
    "gn:admin2_code":"569.0",
    "gn:asciiname":"Hebbarabettu",
    "gn:country_code":"IN",
    "gn:dem":47,
    "gn:feature_class":"P",
    "gn:feature_code":"PPL",
    "gn:name":"Hebb\u0101rabettu",
    "gn:population":0,
    "gn:timezone":"Asia/Kolkata",
    "iso:country":"IN",
    "ks:ks_name":"Hebbarabettu",
    "ks:ks_pop":75,
    "ks:ks_type":"HABITATION",
    "name:eng_x_preferred":[
        "Hebbarabettu"
    ],
    "wof:name":"Hebbarabettu",
    "wof:placetype":"locality",
    "wof:population":75
},
  "geometry": {"coordinates":[75.00943599999999,13.278385],"type":"Point"}
}