{
  "type": "Feature",
  "properties": {
    "iso:country":"IN",
    "ks:ks_name":"Divanpada",
    "ks:ks_pop":620,
    "ks:ks_type":"HABITATION",
    "name:eng_x_preferred":[
        "Divanpada"
    ],
    "wof:name":"Divanpada",
    "wof:placetype":"locality",
    "wof:population":620
},
  "geometry": {"coordinates":[72.866444,19.941441],"type":"Point"}
}