{
  "type": "Feature",
  "properties": {
    "gn:admin1_code":"12.0",
    "gn:admin2_code":"16.0",
    "gn:asciiname":"Dugsaran",
    "gn:country_code":"IN",
    "gn:dem":2627,
    "gn:feature_class":"P",
    "gn:feature_code":"PPL",
    "gn:name":"D\u016bgsaran",
    "gn:population":0,
    "gn:timezone":"Asia/Kolkata",
    "iso:country":"IN",
    "wof:name":"Dugsaran",
    "wof:placetype":"locality"
},
  "geometry": {"coordinates":[75.35029,33.25684],"type":"Point"}
}