{
  "type": "Feature",
  "properties": {
    "gn:admin1_code":"12.0",
    "gn:admin2_code":"6.0",
    "gn:asciiname":"Sathla",
    "gn:country_code":"IN",
    "gn:dem":1213,
    "gn:feature_class":"P",
    "gn:feature_code":"PPL",
    "gn:name":"Sathla",
    "gn:population":0,
    "gn:timezone":"Asia/Kolkata",
    "iso:country":"IN",
    "wof:name":"Sathla",
    "wof:placetype":"locality"
},
  "geometry": {"coordinates":[74.38389000000002,33.35623],"type":"Point"}
}