{
  "type": "Feature",
  "properties": {
    "iso:country":"IN",
    "ks:ks_name":"Kachari Para",
    "ks:ks_pop":1246,
    "ks:ks_type":"HABITATION",
    "name:eng_x_preferred":[
        "Kachari Para"
    ],
    "wof:name":"Kachari Para",
    "wof:placetype":"locality",
    "wof:population":1246
},
  "geometry": {"coordinates":[88.804106,22.276195],"type":"Point"}
}