{
  "type": "Feature",
  "properties": {
    "gn:admin1_code":"37",
    "gn:admin2_code":"410.0",
    "gn:asciiname":"Sakri",
    "gn:country_code":"IN",
    "gn:dem":280,
    "gn:feature_class":"P",
    "gn:feature_code":"PPL",
    "gn:name":"Sakri",
    "gn:population":0,
    "gn:timezone":"Asia/Kolkata",
    "iso:country":"IN",
    "wof:name":"Sakri",
    "wof:placetype":"locality"
},
  "geometry": {"coordinates":[81.86703,21.32162000000001],"type":"Point"}
}