{
  "type": "Feature",
  "properties": {
    "iso:country":"IN",
    "ks:ks_alt_nam":"RASUAR NAYA TOLA",
    "ks:ks_name":"Rasuar Naya Tola",
    "ks:ks_pop":271,
    "ks:ks_type":"HABITATION",
    "name:eng_x_preferred":[
        "Rasuar Naya Tola"
    ],
    "wof:name":"Rasuar Naya Tola",
    "wof:placetype":"locality",
    "wof:population":271
},
  "geometry": {"coordinates":[86.602465,26.291546],"type":"Point"}
}