{
  "type": "Feature",
  "properties": {
    "iso:country":"IN",
    "ks:ks_name":"Saparamgutu",
    "ks:ks_pop":315,
    "ks:ks_type":"HABITATION",
    "name:eng_x_preferred":[
        "Saparamgutu"
    ],
    "wof:name":"Saparamgutu",
    "wof:placetype":"locality",
    "wof:population":315
},
  "geometry": {"coordinates":[85.681882,22.227129],"type":"Point"}
}