{
  "type": "Feature",
  "properties": {
    "gn:admin1_code":"34.0",
    "gn:admin2_code":"204.0",
    "gn:asciiname":"Barharwa Mahanand",
    "gn:country_code":"IN",
    "gn:dem":67,
    "gn:feature_class":"P",
    "gn:feature_code":"PPL",
    "gn:name":"Barharw\u0101 Mah\u0101nand",
    "gn:population":0,
    "gn:timezone":"Asia/Kolkata",
    "iso:country":"IN",
    "ks:ks_name":"Barharwa Mahanad",
    "ks:ks_pop":2856,
    "ks:ks_type":"VILLAGE",
    "ks:ks_uagg_main":0,
    "name:eng_x_preferred":[
        "Barharwa Mahanad"
    ],
    "wof:name":"Barharwa Mahanad",
    "wof:placetype":"neighbourhood",
    "wof:population":2856
},
  "geometry": {"coordinates":[84.93154,26.42078],"type":"Point"}
}