{
  "type": "Feature",
  "properties": {
    "iso:country":"IN",
    "ks:ks_name":"Gudara Dhani",
    "ks:ks_pop":2977,
    "ks:ks_type":"HABITATION",
    "name:eng_x_preferred":[
        "Gudara Dhani"
    ],
    "wof:name":"Gudara Dhani",
    "wof:placetype":"locality",
    "wof:population":2977
},
  "geometry": {"coordinates":[74.19070000000001,30.215326],"type":"Point"}
}