{
  "type": "Feature",
  "properties": {
    "gn:admin1_code":"37",
    "gn:admin2_code":"410.0",
    "gn:asciiname":"Phulwari",
    "gn:country_code":"IN",
    "gn:dem":274,
    "gn:feature_class":"P",
    "gn:feature_code":"PPL",
    "gn:name":"Phulw\u0101ri",
    "gn:population":0,
    "gn:timezone":"Asia/Kolkata",
    "iso:country":"IN",
    "wof:name":"Phulwari",
    "wof:placetype":"neighbourhood"
},
  "geometry": {"coordinates":[82.0123,21.54073],"type":"Point"}
}