{
  "type": "Feature",
  "properties": {
    "iso:country":"IN",
    "ks:ks_name":"Pokhra",
    "ks:ks_pop":329,
    "ks:ks_type":"VILLAGE",
    "ks:ks_uagg_main":0,
    "name:eng_x_preferred":[
        "Pokhra"
    ],
    "wof:name":"Pokhra",
    "wof:placetype":"neighbourhood",
    "wof:population":329
},
  "geometry": {"coordinates":[85.56812600000001,24.733479],"type":"Point"}
}