{
  "type": "Feature",
  "properties": {
    "iso:country":"IN",
    "ks:ks_name":"Cheri",
    "ks:ks_pop":1212,
    "ks:ks_type":"VILLAGE",
    "name:eng_x_preferred":[
        "Cheri"
    ],
    "wof:name":"Cheri",
    "wof:placetype":"neighbourhood",
    "wof:population":1212
},
  "geometry": {"coordinates":[85.26408600000001,23.438603],"type":"Point"}
}