{
  "type": "Feature",
  "properties": {
    "gn:admin1_code":"38.0",
    "gn:admin2_code":"358.0",
    "gn:asciiname":"Patariha",
    "gn:country_code":"IN",
    "gn:dem":227,
    "gn:feature_class":"P",
    "gn:feature_code":"PPL",
    "gn:name":"Patarih\u0101",
    "gn:population":0,
    "gn:timezone":"Asia/Kolkata",
    "iso:country":"IN",
    "ks:ks_name":"Pataria",
    "ks:ks_pop":1271,
    "ks:ks_type":"VILLAGE",
    "name:eng_x_preferred":[
        "Pataria"
    ],
    "name:eng_x_variant":[
        "Patariha"
    ],
    "wof:name":"Pataria",
    "wof:placetype":"locality",
    "wof:population":1271
},
  "geometry": {"coordinates":[84.08567600000001,24.208713],"type":"Point"}
}