{
  "type": "Feature",
  "properties": {
    "gn:admin1_code":"19.0",
    "gn:admin2_code":"568.0",
    "gn:asciiname":"Gubbiga",
    "gn:country_code":"IN",
    "gn:dem":707,
    "gn:feature_class":"P",
    "gn:feature_code":"PPL",
    "gn:name":"Gubbiga",
    "gn:population":0,
    "gn:timezone":"Asia/Kolkata",
    "iso:country":"IN",
    "ks:ks_name":"Gubbiga",
    "ks:ks_pop":1099,
    "ks:ks_type":"VILLAGE",
    "name:eng_x_preferred":[
        "Gubbiga"
    ],
    "wof:name":"Gubbiga",
    "wof:placetype":"locality",
    "wof:population":1099
},
  "geometry": {"coordinates":[75.359369,13.93601],"type":"Point"}
}