{
  "type": "Feature",
  "properties": {
    "iso:country":"IN",
    "ks:ks_name":"Waluj Kh.",
    "ks:ks_pop":2676,
    "ks:ks_type":"VILLAGE",
    "ks:ks_uagg_main":0,
    "name:eng_x_preferred":[
        "Waluj Kh."
    ],
    "wof:name":"Waluj Kh.",
    "wof:placetype":"neighbourhood",
    "wof:population":2676
},
  "geometry": {"coordinates":[75.22605900000001,19.801557],"type":"Point"}
}