{
  "type": "Feature",
  "properties": {
    "iso:country":"IN",
    "ks:ks_alt_nam":"Amera khaspara",
    "ks:ks_name":"Amera Khaspara",
    "ks:ks_pop":395,
    "ks:ks_type":"HABITATION",
    "name:eng_x_preferred":[
        "Amera Khaspara"
    ],
    "wof:name":"Amera Khaspara",
    "wof:placetype":"locality",
    "wof:population":395
},
  "geometry": {"coordinates":[83.632994,23.248481],"type":"Point"}
}