{
  "type": "Feature",
  "properties": {
    "gn:admin1_code":"21",
    "gn:admin2_code":"379.0",
    "gn:asciiname":"Satabhaya",
    "gn:country_code":"IN",
    "gn:dem":4,
    "gn:feature_class":"P",
    "gn:feature_code":"PPL",
    "gn:name":"S\u0101tabh\u0101ya",
    "gn:population":0,
    "gn:timezone":"Asia/Kolkata",
    "iso:country":"IN",
    "name:und_x_variant":[
        "Satbaia",
        "S\u0101tbhaya",
        "S\u0101tabh\u0101ya"
    ],
    "wof:name":"Satabhaya",
    "wof:placetype":"locality"
},
  "geometry": {"coordinates":[86.93098000000001,20.63546],"type":"Point"}
}