{
  "type": "Feature",
  "properties": {
    "gn:admin1_code":"21",
    "gn:admin2_code":"379.0",
    "gn:asciiname":"Satabhaya",
    "gn:country_code":"IN",
    "gn:dem":4,
    "gn:feature_class":"P",
    "gn:feature_code":"PPL",
    "gn:name":"S\u0101tabh\u0101ya",
    "gn:population":0,
    "gn:timezone":"Asia/Kolkata",
    "iso:country":"IN",
    "ks:ks_name":"Satavaya",
    "ks:ks_pop":1241,
    "ks:ks_type":"VILLAGE",
    "name:eng_x_preferred":[
        "Satavaya"
    ],
    "name:eng_x_variant":[
        "Satabhaya"
    ],
    "name:und_x_variant":[
        "Satbaia",
        "S\u0101tbhaya",
        "S\u0101tabh\u0101ya"
    ],
    "wof:name":"Satavaya",
    "wof:placetype":"locality",
    "wof:population":1241
},
  "geometry": {"coordinates":[86.94094800000001,20.64108],"type":"Point"}
}