{
  "type": "Feature",
  "properties": {
    "iso:country":"IN",
    "ks:ks_name":"Berunan",
    "ks:ks_pop":948,
    "ks:ks_type":"HABITATION",
    "name:eng_x_preferred":[
        "Berunan"
    ],
    "wof:name":"Berunan",
    "wof:placetype":"locality",
    "wof:population":948
},
  "geometry": {"coordinates":[88.331153,22.265437],"type":"Point"}
}