{
  "type": "Feature",
  "properties": {
    "iso:country":"IN",
    "ks:ks_alt_nam":"PURE GURU",
    "ks:ks_name":"Pure Guru",
    "ks:ks_pop":134,
    "ks:ks_type":"HABITATION",
    "ks:ks_uagg_main":0,
    "name:eng_x_preferred":[
        "Pure Guru"
    ],
    "wof:name":"Pure Guru",
    "wof:placetype":"neighbourhood",
    "wof:population":134
},
  "geometry": {"coordinates":[81.26387699999999,26.101033],"type":"Point"}
}