{
  "type": "Feature",
  "properties": {
    "iso:country":"IN",
    "ks:ks_alt_nam":"parappur palli jn",
    "ks:ks_name":"Parappur Palli Jn",
    "ks:ks_pop":546,
    "ks:ks_type":"HABITATION",
    "ks:ks_uagg_main":0,
    "name:eng_x_preferred":[
        "Parappur Palli Jn"
    ],
    "wof:name":"Parappur Palli Jn",
    "wof:placetype":"locality",
    "wof:population":546
},
  "geometry": {"coordinates":[76.122275,10.564521],"type":"Point"}
}