{
  "type": "Feature",
  "properties": {
    "iso:country":"IN",
    "ks:ks_name":"Ujangaru",
    "ks:ks_pop":187,
    "ks:ks_type":"HABITATION",
    "name:eng_x_preferred":[
        "Ujangaru"
    ],
    "wof:name":"Ujangaru",
    "wof:placetype":"locality",
    "wof:population":187
},
  "geometry": {"coordinates":[74.791526,13.399003],"type":"Point"}
}