{
  "type": "Feature",
  "properties": {
    "iso:country":"IN",
    "ks:ks_name":"Sarfrabad",
    "ks:ks_pop":433,
    "ks:ks_type":"HABITATION",
    "name:eng_x_preferred":[
        "Sarfrabad"
    ],
    "wof:name":"Sarfrabad",
    "wof:placetype":"locality",
    "wof:population":433
},
  "geometry": {"coordinates":[75.32262799999999,22.179648],"type":"Point"}
}