{
  "type": "Feature",
  "properties": {
    "gn:admin1_code":"2.0",
    "gn:admin2_code":"549.0",
    "gn:asciiname":"Balijepalle",
    "gn:country_code":"IN",
    "gn:dem":133,
    "gn:feature_class":"P",
    "gn:feature_code":"PPL",
    "gn:name":"Balijepalle",
    "gn:population":0,
    "gn:timezone":"Asia/Kolkata",
    "iso:country":"IN",
    "ks:ks_name":"Balijipalli",
    "ks:ks_pop":87,
    "ks:ks_type":"HABITATION",
    "name:eng_x_preferred":[
        "Balijipalli"
    ],
    "name:eng_x_variant":[
        "Balijepalle"
    ],
    "wof:name":"Balijipalli",
    "wof:placetype":"locality",
    "wof:population":87
},
  "geometry": {"coordinates":[79.34587999999999,15.885722],"type":"Point"}
}