{
  "type": "Feature",
  "properties": {
    "iso:country":"IN",
    "ks:ks_name":"Asan Bani",
    "ks:ks_pop":372,
    "ks:ks_type":"VILLAGE",
    "name:eng_x_preferred":[
        "Asan Bani"
    ],
    "wof:name":"Asan Bani",
    "wof:placetype":"locality",
    "wof:population":372
},
  "geometry": {"coordinates":[87.24867500000001,23.081121],"type":"Point"}
}