{
  "type": "Feature",
  "properties": {
    "iso:country":"IN",
    "ks:ks_name":"Baldia Gachhi",
    "ks:ks_pop":385,
    "ks:ks_type":"VILLAGE",
    "ks:ks_uagg_main":0,
    "name:eng_x_preferred":[
        "Baldia Gachhi"
    ],
    "wof:name":"Baldia Gachhi",
    "wof:placetype":"neighbourhood",
    "wof:population":385
},
  "geometry": {"coordinates":[87.90916799999999,25.853709],"type":"Point"}
}