{
  "type": "Feature",
  "properties": {
    "iso:country":"IN",
    "ks:ks_name":"Shaidgang",
    "ks:ks_pop":3585,
    "ks:ks_type":"HABITATION",
    "name:eng_x_preferred":[
        "Shaidgang"
    ],
    "wof:name":"Shaidgang",
    "wof:placetype":"locality",
    "wof:population":3585
},
  "geometry": {"coordinates":[87.098169,25.661369],"type":"Point"}
}