{
  "type": "Feature",
  "properties": {
    "iso:country":"IN",
    "ks:ks_alt_nam":"khajoor Tola",
    "ks:ks_name":"Khajoor Tola",
    "ks:ks_pop":345,
    "ks:ks_type":"HABITATION",
    "ks:ks_uagg_main":0,
    "name:eng_x_preferred":[
        "Khajoor Tola"
    ],
    "wof:name":"Khajoor Tola",
    "wof:placetype":"neighbourhood",
    "wof:population":345
},
  "geometry": {"coordinates":[87.38328300000001,25.248808],"type":"Point"}
}