{
  "type": "Feature",
  "properties": {
    "iso:country":"IN",
    "ks:ks_name":"Aditha",
    "ks:ks_pop":168,
    "ks:ks_type":"VILLAGE",
    "name:eng_x_preferred":[
        "Aditha"
    ],
    "wof:name":"Aditha",
    "wof:placetype":"locality",
    "wof:population":168
},
  "geometry": {"coordinates":[79.69005199999999,29.568723],"type":"Point"}
}