{
  "type": "Feature",
  "properties": {
    "iso:country":"IN",
    "ks:ks_name":"Barhi Tola",
    "ks:ks_pop":276,
    "ks:ks_type":"HABITATION",
    "name:eng_x_preferred":[
        "Barhi Tola"
    ],
    "wof:name":"Barhi Tola",
    "wof:placetype":"locality",
    "wof:population":276
},
  "geometry": {"coordinates":[86.845029,25.985744],"type":"Point"}
}