{
  "type": "Feature",
  "properties": {
    "gn:admin1_code":"36",
    "gn:admin2_code":"179.0",
    "gn:asciiname":"Paharpur Bais",
    "gn:country_code":"IN",
    "gn:dem":95,
    "gn:feature_class":"P",
    "gn:feature_code":"PPL",
    "gn:name":"Pah\u0101rpur Bais",
    "gn:population":0,
    "gn:timezone":"Asia/Kolkata",
    "iso:country":"IN",
    "ks:ks_name":"Paharpur Basya",
    "ks:ks_pop":525,
    "ks:ks_type":"VILLAGE",
    "ks:ks_uagg_main":0,
    "name:eng_x_preferred":[
        "Paharpur Basya"
    ],
    "wof:name":"Paharpur Basya",
    "wof:placetype":"neighbourhood",
    "wof:population":525
},
  "geometry": {"coordinates":[82.48676399999999,26.196483],"type":"Point"}
}