{
  "type": "Feature",
  "properties": {
    "iso:country":"IN",
    "ks:ks_name":"Khaladi",
    "ks:ks_pop":0,
    "ks:ks_type":"VILLAGE",
    "name:eng_x_preferred":[
        "Khaladi"
    ],
    "wof:name":"Khaladi",
    "wof:placetype":"locality",
    "wof:population":0
},
  "geometry": {"coordinates":[86.056811,21.96342],"type":"Point"}
}