{
  "type": "Feature",
  "properties": {
    "gn:admin1_code":"36",
    "gn:admin2_code":"187.0",
    "gn:asciiname":"Siglampur Pachchhim",
    "gn:country_code":"IN",
    "gn:dem":87,
    "gn:feature_class":"P",
    "gn:feature_code":"PPL",
    "gn:name":"Sigl\u0101mpur Pachchhim",
    "gn:population":0,
    "gn:timezone":"Asia/Kolkata",
    "iso:country":"IN",
    "wof:name":"Siglampur Pachchhim",
    "wof:placetype":"neighbourhood"
},
  "geometry": {"coordinates":[83.20157,27.16371],"type":"Point"}
}