{
  "type": "Feature",
  "properties": {
    "gn:admin1_code":"3.0",
    "gn:admin2_code":"301.0",
    "gn:asciiname":"Belpara",
    "gn:country_code":"IN",
    "gn:dem":34,
    "gn:feature_class":"P",
    "gn:feature_code":"PPL",
    "gn:name":"Belp\u0101ra",
    "gn:population":0,
    "gn:timezone":"Asia/Kolkata",
    "iso:country":"IN",
    "ks:ks_alt_nam":"Belp\u0101ra",
    "ks:ks_name":"Belpara",
    "ks:ks_type":"VILLAGE",
    "name:eng_x_preferred":[
        "Belpara"
    ],
    "name:eng_x_variant":[
        "Belp\u0101ra"
    ],
    "wof:name":"Belpara",
    "wof:placetype":"locality"
},
  "geometry": {"coordinates":[89.805503,26.323405],"type":"Point"}
}