{
  "type": "Feature",
  "properties": {
    "iso:country":"IN",
    "ks:ks_name":"Hirpur",
    "ks:ks_pop":392,
    "ks:ks_type":"HABITATION",
    "ks:ks_uagg_main":0,
    "name:eng_x_preferred":[
        "Hirpur"
    ],
    "wof:name":"Hirpur",
    "wof:placetype":"neighbourhood",
    "wof:population":392
},
  "geometry": {"coordinates":[84.32001,25.640318],"type":"Point"}
}