{
  "type": "Feature",
  "properties": {
    "iso:country":"IN",
    "ks:ks_name":"Kani Mahuli",
    "ks:ks_pop":282,
    "ks:ks_type":"VILLAGE",
    "ks:ks_uagg_main":0,
    "name:eng_x_preferred":[
        "Kani Mahuli"
    ],
    "wof:name":"Kani Mahuli",
    "wof:placetype":"neighbourhood",
    "wof:population":282
},
  "geometry": {"coordinates":[86.895917,22.382166],"type":"Point"}
}