{
  "type": "Feature",
  "properties": {
    "iso:country":"IN",
    "ks:ks_name":"Badakhowa",
    "ks:ks_pop":258,
    "ks:ks_type":"HABITATION",
    "name:eng_x_preferred":[
        "Badakhowa"
    ],
    "wof:name":"Badakhowa",
    "wof:placetype":"locality",
    "wof:population":258
},
  "geometry": {"coordinates":[90.976477,25.895141],"type":"Point"}
}