{
  "type": "Feature",
  "properties": {
    "gn:admin1_code":"38.0",
    "gn:admin2_code":"353.0",
    "gn:asciiname":"Dumarbhita",
    "gn:country_code":"IN",
    "gn:dem":323,
    "gn:feature_class":"P",
    "gn:feature_code":"PPL",
    "gn:name":"Dumarbhita",
    "gn:population":0,
    "gn:timezone":"Asia/Kolkata",
    "iso:country":"IN",
    "ks:ks_name":"Dumarbhita",
    "ks:ks_pop":151,
    "ks:ks_type":"VILLAGE",
    "name:eng_x_preferred":[
        "Dumarbhita"
    ],
    "wof:name":"Dumarbhita",
    "wof:placetype":"locality",
    "wof:population":151
},
  "geometry": {"coordinates":[87.50498399999999,24.665623],"type":"Point"}
}