{
  "type": "Feature",
  "properties": {
    "iso:country":"IN",
    "ks:ks_name":"Pure Meharbeen",
    "ks:ks_pop":40,
    "ks:ks_type":"HABITATION",
    "name:eng_x_preferred":[
        "Pure Meharbeen"
    ],
    "wof:name":"Pure Meharbeen",
    "wof:placetype":"locality",
    "wof:population":40
},
  "geometry": {"coordinates":[81.829409,26.0729],"type":"Point"}
}