{
  "type": "Feature",
  "properties": {
    "gn:admin1_code":"16.0",
    "gn:admin2_code":"517",
    "gn:asciiname":"Kaman",
    "gn:country_code":"IN",
    "gn:dem":9,
    "gn:feature_class":"P",
    "gn:feature_code":"PPL",
    "gn:name":"Kaman",
    "gn:population":0,
    "gn:timezone":"Asia/Kolkata",
    "iso:country":"IN",
    "wof:name":"Kaman",
    "wof:placetype":"locality"
},
  "geometry": {"coordinates":[72.90940999999999,19.35474],"type":"Point"}
}