{
  "type": "Feature",
  "properties": {
    "gn:admin1_code":"34.0",
    "gn:admin2_code":"219.0",
    "gn:asciiname":"Sendari",
    "gn:country_code":"IN",
    "gn:dem":59,
    "gn:feature_class":"P",
    "gn:feature_code":"PPL",
    "gn:name":"Sendari",
    "gn:population":0,
    "gn:timezone":"Asia/Kolkata",
    "iso:country":"IN",
    "ks:ks_name":"Senduari",
    "ks:ks_pop":1668,
    "ks:ks_type":"VILLAGE",
    "ks:ks_uagg_main":0,
    "name:eng_x_preferred":[
        "Senduari"
    ],
    "wof:name":"Senduari",
    "wof:placetype":"neighbourhood",
    "wof:population":1668
},
  "geometry": {"coordinates":[84.82058499999999,25.900911],"type":"Point"}
}