{
  "type": "Feature",
  "properties": {
    "iso:country":"IN",
    "ks:ks_alt_nam":"savar pada",
    "ks:ks_name":"Savar Pada",
    "ks:ks_pop":240,
    "ks:ks_type":"HABITATION",
    "name:eng_x_preferred":[
        "Savar Pada"
    ],
    "wof:name":"Savar Pada",
    "wof:placetype":"locality",
    "wof:population":240
},
  "geometry": {"coordinates":[73.309895,20.522679],"type":"Point"}
}