{
  "type": "Feature",
  "properties": {
    "gn:admin1_code":"16",
    "gn:admin2_code":"508.0",
    "gn:asciiname":"Pauni",
    "gn:country_code":"IN",
    "gn:dem":243,
    "gn:feature_class":"P",
    "gn:feature_code":"PPL",
    "gn:name":"Pauni",
    "gn:population":0,
    "gn:timezone":"Asia/Kolkata",
    "iso:country":"IN",
    "ks:ks_name":"Paoni",
    "ks:ks_pop":914,
    "ks:ks_type":"HABITATION",
    "name:ben_x_preferred":[
        "\u09aa\u09be\u0993\u09a8\u09bf"
    ],
    "name:bpy_x_preferred":[
        "\u09aa\u09be\u0993\u09a8\u09bf"
    ],
    "name:ceb_x_preferred":[
        "Pauni"
    ],
    "name:eng_x_preferred":[
        "Paoni"
    ],
    "name:eng_x_variant":[
        "Pauni"
    ],
    "name:ita_x_preferred":[
        "Pauni"
    ],
    "name:mar_x_preferred":[
        "\u092a\u0935\u0928\u0940"
    ],
    "name:msa_x_preferred":[
        "Pauni"
    ],
    "name:nld_x_preferred":[
        "Pauni"
    ],
    "name:ori_x_preferred":[
        "\u0b2a\u0b3e\u0b09\u0b28\u0b3f"
    ],
    "name:por_x_preferred":[
        "Pauni"
    ],
    "name:swe_x_preferred":[
        "Pauni"
    ],
    "name:urd_x_preferred":[
        "\u067e\u0648\u0646\u06cc"
    ],
    "name:vie_x_preferred":[
        "Pauni"
    ],
    "wof:name":"Paoni",
    "wof:placetype":"locality",
    "wof:population":914
},
  "geometry": {"coordinates":[80.33443,20.277252],"type":"Point"}
}