{
  "type": "Feature",
  "properties": {
    "iso:country":"IN",
    "ks:ks_name":"Puran Chaprapara",
    "ks:ks_pop":432,
    "ks:ks_type":"HABITATION",
    "name:eng_x_preferred":[
        "Puran Chaprapara"
    ],
    "wof:name":"Puran Chaprapara",
    "wof:placetype":"locality",
    "wof:population":432
},
  "geometry": {"coordinates":[91.345877,26.244538],"type":"Point"}
}