{
  "type": "Feature",
  "properties": {
    "iso:country":"IN",
    "ks:ks_name":"Mannangala",
    "ks:ks_pop":21,
    "ks:ks_type":"HABITATION",
    "name:eng_x_preferred":[
        "Mannangala"
    ],
    "wof:name":"Mannangala",
    "wof:placetype":"locality",
    "wof:population":21
},
  "geometry": {"coordinates":[75.31323399999999,12.842598],"type":"Point"}
}