{
  "type": "Feature",
  "properties": {
    "iso:country":"IN",
    "ks:ks_name":"Madarabadu",
    "ks:ks_pop":338,
    "ks:ks_type":"HABITATION",
    "name:eng_x_preferred":[
        "Madarabadu"
    ],
    "wof:name":"Madarabadu",
    "wof:placetype":"locality",
    "wof:population":338
},
  "geometry": {"coordinates":[79.704024,14.653366],"type":"Point"}
}