{
  "type": "Feature",
  "properties": {
    "iso:country":"IN",
    "ks:ks_name":"Bommarasikoppa",
    "ks:ks_pop":295,
    "ks:ks_type":"HABITATION",
    "name:eng_x_preferred":[
        "Bommarasikoppa"
    ],
    "wof:name":"Bommarasikoppa",
    "wof:placetype":"locality",
    "wof:population":295
},
  "geometry": {"coordinates":[75.143156,14.61454],"type":"Point"}
}