{
  "type": "Feature",
  "properties": {
    "iso:country":"IN",
    "ks:ks_name":"Doonglai",
    "ks:ks_pop":434,
    "ks:ks_type":"VILLAGE",
    "name:eng_x_preferred":[
        "Doonglai"
    ],
    "wof:name":"Doonglai",
    "wof:placetype":"locality",
    "wof:population":434
},
  "geometry": {"coordinates":[74.308508,23.918752],"type":"Point"}
}