{
  "type": "Feature",
  "properties": {
    "gn:admin1_code":"12.0",
    "gn:admin2_code":"7.0",
    "gn:asciiname":"Talin",
    "gn:country_code":"IN",
    "gn:dem":680,
    "gn:feature_class":"P",
    "gn:feature_code":"PPL",
    "gn:name":"Talin",
    "gn:population":0,
    "gn:timezone":"Asia/Kolkata",
    "iso:country":"IN",
    "name:und_x_variant":[
        "Bashrota"
    ],
    "wof:name":"Talin",
    "wof:placetype":"locality"
},
  "geometry": {"coordinates":[75.42935,32.57198],"type":"Point"}
}