{
  "type": "Feature",
  "properties": {
    "gn:admin1_code":"12.0",
    "gn:admin2_code":"7.0",
    "gn:asciiname":"Talin",
    "gn:country_code":"IN",
    "gn:dem":680,
    "gn:feature_class":"P",
    "gn:feature_code":"PPL",
    "gn:name":"Talin",
    "gn:population":0,
    "gn:timezone":"Asia/Kolkata",
    "iso:country":"IN",
    "name:aze_x_preferred":[
        "Talin"
    ],
    "name:ces_x_preferred":[
        "Talin"
    ],
    "name:fas_x_preferred":[
        "\u062a\u0627\u0644\u06cc\u0646"
    ],
    "name:fra_x_preferred":[
        "Talin"
    ],
    "name:hye_x_preferred":[
        "\u0539\u0561\u056c\u056b\u0576"
    ],
    "name:jpn_x_preferred":[
        "\u30bf\u30ea\u30f3"
    ],
    "name:nld_x_preferred":[
        "Talin"
    ],
    "name:sco_x_preferred":[
        "Talin"
    ],
    "name:slv_x_preferred":[
        "Talin"
    ],
    "name:srp_x_preferred":[
        "\u0422\u0430\u043b\u0438\u043d"
    ],
    "name:swe_x_preferred":[
        "Talin"
    ],
    "name:tgl_x_preferred":[
        "Talin"
    ],
    "name:ukr_x_preferred":[
        "\u0422\u0430\u043b\u0456\u043d"
    ],
    "name:und_x_variant":[
        "Bashrota"
    ],
    "wof:name":"Talin",
    "wof:placetype":"locality"
},
  "geometry": {"coordinates":[75.42935,32.57198],"type":"Point"}
}