{
  "type": "Feature",
  "properties": {
    "iso:country":"IN",
    "ks:ks_name":"Duliyahi",
    "ks:ks_pop":455,
    "ks:ks_type":"HABITATION",
    "name:eng_x_preferred":[
        "Duliyahi"
    ],
    "wof:name":"Duliyahi",
    "wof:placetype":"locality",
    "wof:population":455
},
  "geometry": {"coordinates":[86.70380400000001,26.019653],"type":"Point"}
}