{
  "type": "Feature",
  "properties": {
    "gn:admin1_code":"37.0",
    "gn:admin2_code":"414.0",
    "gn:asciiname":"Deipara",
    "gn:country_code":"IN",
    "gn:dem":638,
    "gn:feature_class":"P",
    "gn:feature_code":"PPL",
    "gn:name":"Deip\u0101ra",
    "gn:population":0,
    "gn:timezone":"Asia/Kolkata",
    "iso:country":"IN",
    "wof:name":"Deipara",
    "wof:placetype":"locality"
},
  "geometry": {"coordinates":[81.81381999999998,19.99369],"type":"Point"}
}