{
  "type": "Feature",
  "properties": {
    "iso:country":"IN",
    "ks:ks_name":"Malgalli",
    "ks:ks_pop":120,
    "ks:ks_type":"HABITATION",
    "name:eng_x_preferred":[
        "Malgalli"
    ],
    "wof:name":"Malgalli",
    "wof:placetype":"locality",
    "wof:population":120
},
  "geometry": {"coordinates":[75.818162,12.7595],"type":"Point"}
}