{
  "type": "Feature",
  "properties": {
    "gn:admin1_code":"2.0",
    "gn:admin2_code":"553.0",
    "gn:asciiname":"Golmanhalli",
    "gn:country_code":"IN",
    "gn:dem":614,
    "gn:feature_class":"P",
    "gn:feature_code":"PPL",
    "gn:name":"Golmanhalli",
    "gn:population":0,
    "gn:timezone":"Asia/Kolkata",
    "iso:country":"IN",
    "wof:name":"Golmanhalli",
    "wof:placetype":"locality"
},
  "geometry": {"coordinates":[76.97426,14.01529],"type":"Point"}
}