{
  "type": "Feature",
  "properties": {
    "gn:admin1_code":"34.0",
    "gn:admin2_code":"204.0",
    "gn:asciiname":"Bankat Mafi",
    "gn:country_code":"IN",
    "gn:dem":66,
    "gn:feature_class":"P",
    "gn:feature_code":"PPL",
    "gn:name":"Bankat M\u0101fi",
    "gn:population":0,
    "gn:timezone":"Asia/Kolkata",
    "iso:country":"IN",
    "ks:ks_alt_nam":"Bankat M\u0101fi",
    "ks:ks_name":"Bankat Mafi",
    "ks:ks_type":"VILLAGE",
    "ks:ks_uagg_main":0,
    "name:eng_x_preferred":[
        "Bankat Mafi"
    ],
    "name:eng_x_variant":[
        "Bankat M\u0101fi"
    ],
    "wof:name":"Bankat Mafi",
    "wof:placetype":"neighbourhood"
},
  "geometry": {"coordinates":[84.910267,26.324088],"type":"Point"}
}