{
  "type": "Feature",
  "properties": {
    "iso:country":"IN",
    "ks:ks_name":"Nawabnagar Tah",
    "ks:ks_pop":114,
    "ks:ks_type":"VILLAGE",
    "name:eng_x_preferred":[
        "Nawabnagar Tah"
    ],
    "wof:name":"Nawabnagar Tah",
    "wof:placetype":"locality",
    "wof:population":114
},
  "geometry": {"coordinates":[79.16764499999999,28.971018],"type":"Point"}
}