{
  "type": "Feature",
  "properties": {
    "iso:country":"IN",
    "ks:ks_name":"Antarjal",
    "ks:ks_pop":50,
    "ks:ks_type":"URBAN",
    "ks:ks_uagg_main":0,
    "name:eng_x_preferred":[
        "Antarjal"
    ],
    "wof:name":"Antarjal",
    "wof:placetype":"locality",
    "wof:population":50
},
  "geometry": {"coordinates":[70.084408,23.053825],"type":"Point"}
}