{
  "type": "Feature",
  "properties": {
    "gn:admin1_code":"34.0",
    "gn:admin2_code":"217.0",
    "gn:asciiname":"Majharia",
    "gn:country_code":"IN",
    "gn:dem":78,
    "gn:feature_class":"P",
    "gn:feature_code":"PPL",
    "gn:name":"Majhari\u0101",
    "gn:population":0,
    "gn:timezone":"Asia/Kolkata",
    "iso:country":"IN",
    "name:tam_x_preferred":[
        "\u0bae\u0bbe\u0baf\u0bcd\u0b95\u0bbe\u0bb0\u0bbf\u0baf\u0bbe"
    ],
    "wof:name":"Majharia",
    "wof:placetype":"locality"
},
  "geometry": {"coordinates":[84.08113,26.52907],"type":"Point"}
}