{
  "type": "Feature",
  "properties": {
    "iso:country":"IN",
    "ks:ks_name":"Periyakorungulam",
    "ks:ks_pop":328,
    "ks:ks_type":"HABITATION",
    "name:eng_x_preferred":[
        "Periyakorungulam"
    ],
    "wof:name":"Periyakorungulam",
    "wof:placetype":"locality",
    "wof:population":328
},
  "geometry": {"coordinates":[78.695438,9.900333],"type":"Point"}
}