{
  "type": "Feature",
  "properties": {
    "gn:admin1_code":"36",
    "gn:admin2_code":"195.0",
    "gn:asciiname":"Dhurehra",
    "gn:country_code":"IN",
    "gn:dem":77,
    "gn:feature_class":"P",
    "gn:feature_code":"PPL",
    "gn:name":"Dhurehra",
    "gn:population":0,
    "gn:timezone":"Asia/Kolkata",
    "iso:country":"IN",
    "name:und_x_variant":[
        "Gop\u0101lr\u0101e"
    ],
    "wof:name":"Dhurehra",
    "wof:placetype":"locality"
},
  "geometry": {"coordinates":[83.45825000000001,25.80516],"type":"Point"}
}