{
  "type": "Feature",
  "properties": {
    "iso:country":"IN",
    "ks:ks_name":"Malipara Paharia",
    "ks:ks_pop":65,
    "ks:ks_type":"VILLAGE",
    "name:eng_x_preferred":[
        "Malipara Paharia"
    ],
    "wof:name":"Malipara Paharia",
    "wof:placetype":"locality",
    "wof:population":65
},
  "geometry": {"coordinates":[87.537099,24.61343],"type":"Point"}
}