{
  "type": "Feature",
  "properties": {
    "iso:country":"IN",
    "ks:ks_name":"Male Hitala",
    "ks:ks_pop":80,
    "ks:ks_type":"HABITATION",
    "name:eng_x_preferred":[
        "Male Hitala"
    ],
    "wof:name":"Male Hitala",
    "wof:placetype":"locality",
    "wof:population":80
},
  "geometry": {"coordinates":[74.42261000000001,14.372473],"type":"Point"}
}