{
  "type": "Feature",
  "properties": {
    "iso:country":"IN",
    "ks:ks_name":"Periyavallikulam",
    "ks:ks_pop":727,
    "ks:ks_type":"HABITATION",
    "ks:ks_uagg_main":1,
    "name:eng_x_preferred":[
        "Periyavallikulam"
    ],
    "wof:name":"Periyavallikulam",
    "wof:placetype":"neighbourhood",
    "wof:population":727
},
  "geometry": {"coordinates":[77.978853,9.5665],"type":"Point"}
}