{
  "type": "Feature",
  "properties": {
    "iso:country":"IN",
    "ks:ks_name":"Seerathoppu",
    "ks:ks_pop":978,
    "ks:ks_type":"HABITATION",
    "ks:ks_uagg_main":1,
    "name:eng_x_preferred":[
        "Seerathoppu"
    ],
    "wof:name":"Seerathoppu",
    "wof:placetype":"neighbourhood",
    "wof:population":978
},
  "geometry": {"coordinates":[78.634958,10.835807],"type":"Point"}
}