{
  "type": "Feature",
  "properties": {
    "iso:country":"IN",
    "ks:ks_name":"Niche Tola",
    "ks:ks_pop":201,
    "ks:ks_type":"HABITATION",
    "name:eng_x_preferred":[
        "Niche Tola"
    ],
    "wof:name":"Niche Tola",
    "wof:placetype":"locality",
    "wof:population":201
},
  "geometry": {"coordinates":[86.711169,24.580409],"type":"Point"}
}