{
  "type": "Feature",
  "properties": {
    "iso:country":"IN",
    "ks:ks_name":"Bargo",
    "ks:ks_pop":0,
    "ks:ks_type":"VILLAGE",
    "name:eng_x_preferred":[
        "Bargo"
    ],
    "wof:name":"Bargo",
    "wof:placetype":"locality",
    "wof:population":0
},
  "geometry": {"coordinates":[87.02519700000001,24.423617],"type":"Point"}
}