{
  "type": "Feature",
  "properties": {
    "iso:country":"IN",
    "ks:ks_name":"Maluru",
    "ks:ks_pop":434,
    "ks:ks_type":"HABITATION",
    "name:eng_x_preferred":[
        "Maluru"
    ],
    "wof:name":"Maluru",
    "wof:placetype":"locality",
    "wof:population":434
},
  "geometry": {"coordinates":[75.15315,13.523715],"type":"Point"}
}