{
  "type": "Feature",
  "properties": {
    "gn:admin1_code":"19.0",
    "gn:admin2_code":"570.0",
    "gn:asciiname":"Hosakoppa",
    "gn:country_code":"IN",
    "gn:dem":663,
    "gn:feature_class":"P",
    "gn:feature_code":"PPL",
    "gn:name":"Hosakoppa",
    "gn:population":0,
    "gn:timezone":"Asia/Kolkata",
    "iso:country":"IN",
    "wof:name":"Hosakoppa",
    "wof:placetype":"locality"
},
  "geometry": {"coordinates":[75.26971,13.46664],"type":"Point"}
}