{
  "type": "Feature",
  "properties": {
    "iso:country":"IN",
    "ks:ks_name":"Agarnaral",
    "ks:ks_pop":1189,
    "ks:ks_type":"VILLAGE",
    "name:eng_x_preferred":[
        "Agarnaral"
    ],
    "wof:name":"Agarnaral",
    "wof:placetype":"locality",
    "wof:population":1189
},
  "geometry": {"coordinates":[73.33500100000001,17.219919],"type":"Point"}
}