{
  "type": "Feature",
  "properties": {
    "iso:country":"IN",
    "ks:ks_alt_nam":"Chiuntij\u0101m",
    "ks:ks_name":"Chiuntijam",
    "ks:ks_type":"VILLAGE",
    "name:eng_x_preferred":[
        "Chiuntijam"
    ],
    "name:eng_x_variant":[
        "Chiuntij\u0101m"
    ],
    "wof:name":"Chiuntijam",
    "wof:placetype":"locality"
},
  "geometry": {"coordinates":[83.434713,26.675709],"type":"Point"}
}