{
  "type": "Feature",
  "properties": {
    "iso:country":"IN",
    "ks:ks_name":"Bangalji Ni Muvadi",
    "ks:ks_pop":500,
    "ks:ks_type":"HABITATION",
    "name:eng_x_preferred":[
        "Bangalji Ni Muvadi"
    ],
    "wof:name":"Bangalji Ni Muvadi",
    "wof:placetype":"locality",
    "wof:population":500
},
  "geometry": {"coordinates":[72.83279400000001,22.959969],"type":"Point"}
}