{
  "type": "Feature",
  "properties": {
    "gn:admin1_code":"24.0",
    "gn:admin2_code":"113",
    "gn:asciiname":"Dedasri",
    "gn:country_code":"IN",
    "gn:dem":213,
    "gn:feature_class":"P",
    "gn:feature_code":"PPL",
    "gn:name":"Ded\u0101sri",
    "gn:population":0,
    "gn:timezone":"Asia/Kolkata",
    "iso:country":"IN",
    "wof:name":"Dedasri",
    "wof:placetype":"locality"
},
  "geometry": {"coordinates":[72.01756,27.34948],"type":"Point"}
}