{
  "type": "Feature",
  "properties": {
    "iso:country":"IN",
    "ks:ks_name":"Komurakhati Grazing",
    "ks:ks_pop":109,
    "ks:ks_type":"HABITATION",
    "name:eng_x_preferred":[
        "Komurakhati Grazing"
    ],
    "wof:name":"Komurakhati Grazing",
    "wof:placetype":"locality",
    "wof:population":109
},
  "geometry": {"coordinates":[93.218683,26.770592],"type":"Point"}
}