{
  "type": "Feature",
  "properties": {
    "iso:country":"IN",
    "ks:ks_name":"Bhusarpada",
    "ks:ks_pop":176,
    "ks:ks_type":"HABITATION",
    "name:eng_x_preferred":[
        "Bhusarpada"
    ],
    "wof:name":"Bhusarpada",
    "wof:placetype":"locality",
    "wof:population":176
},
  "geometry": {"coordinates":[73.000604,20.035843],"type":"Point"}
}