{
  "type": "Feature",
  "properties": {
    "iso:country":"IN",
    "ks:ks_alt_nam":"pure Chand Gadh",
    "ks:ks_name":"Pure Chand Gadh",
    "ks:ks_pop":834,
    "ks:ks_type":"HABITATION",
    "name:eng_x_preferred":[
        "Pure Chand Gadh"
    ],
    "wof:name":"Pure Chand Gadh",
    "wof:placetype":"locality",
    "wof:population":834
},
  "geometry": {"coordinates":[81.51819999999999,26.4445],"type":"Point"}
}