{
  "type": "Feature",
  "properties": {
    "gn:admin1_code":"37.0",
    "gn:admin2_code":"416.0",
    "gn:asciiname":"Gudra",
    "gn:country_code":"IN",
    "gn:dem":224,
    "gn:feature_class":"P",
    "gn:feature_code":"PPL",
    "gn:name":"Gudra",
    "gn:population":0,
    "gn:timezone":"Asia/Kolkata",
    "iso:country":"IN",
    "wof:name":"Gudra",
    "wof:placetype":"locality"
},
  "geometry": {"coordinates":[81.82021999999998,18.57576],"type":"Point"}
}