{
  "type": "Feature",
  "properties": {
    "iso:country":"IN",
    "ks:ks_name":"Duddi Reserved Forest",
    "ks:ks_type":"VILLAGE",
    "name:eng_x_preferred":[
        "Duddi Reserved Forest"
    ],
    "wof:name":"Duddi Reserved Forest",
    "wof:placetype":"locality"
},
  "geometry": {"coordinates":[78.843388,22.278312],"type":"Point"}
}