{
  "type": "Feature",
  "properties": {
    "gn:admin1_code":"37",
    "gn:admin2_code":"415.0",
    "gn:asciiname":"Sonpur",
    "gn:country_code":"IN",
    "gn:dem":502,
    "gn:feature_class":"P",
    "gn:feature_code":"PPL",
    "gn:name":"Sonpur",
    "gn:population":0,
    "gn:timezone":"Asia/Kolkata",
    "iso:country":"IN",
    "wof:name":"Sonpur",
    "wof:placetype":"locality"
},
  "geometry": {"coordinates":[81.01236999999998,19.70132000000001],"type":"Point"}
}