{
  "type": "Feature",
  "properties": {
    "iso:country":"IN",
    "ks:ks_name":"Chak Bhati",
    "ks:ks_pop":357,
    "ks:ks_type":"VILLAGE",
    "name:eng_x_preferred":[
        "Chak Bhati"
    ],
    "wof:name":"Chak Bhati",
    "wof:placetype":"locality",
    "wof:population":357
},
  "geometry": {"coordinates":[85.28783900000001,25.951747],"type":"Point"}
}