{
  "type": "Feature",
  "properties": {
    "iso:country":"IN",
    "ks:ks_name":"Latapakur",
    "ks:ks_pop":299,
    "ks:ks_type":"VILLAGE",
    "name:eng_x_preferred":[
        "Latapakur"
    ],
    "wof:name":"Latapakur",
    "wof:placetype":"locality",
    "wof:population":299
},
  "geometry": {"coordinates":[87.467572,23.993324],"type":"Point"}
}