{
  "type": "Feature",
  "properties": {
    "gn:admin1_code":"35",
    "gn:admin2_code":"453.0",
    "gn:asciiname":"Batia",
    "gn:country_code":"IN",
    "gn:dem":764,
    "gn:feature_class":"P",
    "gn:feature_code":"PPL",
    "gn:name":"Batia",
    "gn:population":0,
    "gn:timezone":"Asia/Kolkata",
    "iso:country":"IN",
    "name:ceb_x_preferred":[
        "Batia"
    ],
    "name:fra_x_preferred":[
        "Batia"
    ],
    "name:swe_x_preferred":[
        "Batia"
    ],
    "name:war_x_preferred":[
        "Batia"
    ],
    "wof:name":"Batia",
    "wof:placetype":"locality"
},
  "geometry": {"coordinates":[81.00197,22.73131],"type":"Point"}
}