{
  "type": "Feature",
  "properties": {
    "iso:country":"IN",
    "ks:ks_name":"Kadru Duba",
    "ks:ks_pop":671,
    "ks:ks_type":"HABITATION",
    "name:eng_x_preferred":[
        "Kadru Duba"
    ],
    "wof:name":"Kadru Duba",
    "wof:placetype":"locality",
    "wof:population":671
},
  "geometry": {"coordinates":[85.489351,23.68086],"type":"Point"}
}