{
  "type": "Feature",
  "properties": {
    "iso:country":"IN",
    "ks:ks_name":"Pasi Basti",
    "ks:ks_pop":69,
    "ks:ks_type":"HABITATION",
    "ks:ks_uagg_main":0,
    "name:eng_x_preferred":[
        "Pasi Basti"
    ],
    "wof:name":"Pasi Basti",
    "wof:placetype":"neighbourhood",
    "wof:population":69
},
  "geometry": {"coordinates":[82.06238,25.794357],"type":"Point"}
}