{
  "type": "Feature",
  "properties": {
    "iso:country":"IN",
    "ks:ks_name":"Obridih",
    "ks:ks_pop":65,
    "ks:ks_type":"VILLAGE",
    "name:eng_x_preferred":[
        "Obridih"
    ],
    "wof:name":"Obridih",
    "wof:placetype":"locality",
    "wof:population":65
},
  "geometry": {"coordinates":[85.12888599999999,24.127512],"type":"Point"}
}