{
  "type": "Feature",
  "properties": {
    "iso:country":"IN",
    "ks:ks_alt_nam":"KHUSARSARAI",
    "ks:ks_name":"Khusarsarai",
    "ks:ks_pop":153,
    "ks:ks_type":"HABITATION",
    "name:eng_x_preferred":[
        "Khusarsarai"
    ],
    "wof:name":"Khusarsarai",
    "wof:placetype":"locality",
    "wof:population":153
},
  "geometry": {"coordinates":[85.844585,26.133597],"type":"Point"}
}