{
  "type": "Feature",
  "properties": {
    "gn:admin1_code":"19.0",
    "gn:admin2_code":"574.0",
    "gn:asciiname":"Chennangihalli",
    "gn:country_code":"IN",
    "gn:dem":927,
    "gn:feature_class":"P",
    "gn:feature_code":"PPL",
    "gn:name":"Chennangihalli",
    "gn:population":0,
    "gn:timezone":"Asia/Kolkata",
    "iso:country":"IN",
    "wof:name":"Chennangihalli",
    "wof:placetype":"locality"
},
  "geometry": {"coordinates":[76.10401999999998,12.88111],"type":"Point"}
}