{
  "type": "Feature",
  "properties": {
    "iso:country":"IN",
    "ks:ks_name":"Shobhapur",
    "ks:ks_pop":752,
    "ks:ks_type":"VILLAGE",
    "ks:ks_uagg_main":0,
    "name:eng_x_preferred":[
        "Shobhapur"
    ],
    "wof:name":"Shobhapur",
    "wof:placetype":"neighbourhood",
    "wof:population":752
},
  "geometry": {"coordinates":[87.24785199999999,22.361506],"type":"Point"}
}