{
  "type": "Feature",
  "properties": {
    "iso:country":"IN",
    "ks:ks_name":"Mushari Purb",
    "ks:ks_pop":798,
    "ks:ks_type":"HABITATION",
    "name:eng_x_preferred":[
        "Mushari Purb"
    ],
    "wof:name":"Mushari Purb",
    "wof:placetype":"locality",
    "wof:population":798
},
  "geometry": {"coordinates":[87.262,25.875455],"type":"Point"}
}