{
  "type": "Feature",
  "properties": {
    "iso:country":"IN",
    "ks:ks_name":"Binapani Para",
    "ks:ks_pop":1138,
    "ks:ks_type":"HABITATION",
    "name:eng_x_preferred":[
        "Binapani Para"
    ],
    "wof:name":"Binapani Para",
    "wof:placetype":"locality",
    "wof:population":1138
},
  "geometry": {"coordinates":[88.853059,22.126335],"type":"Point"}
}