{
  "type": "Feature",
  "properties": {
    "iso:country":"IN",
    "ks:ks_name":"Chandipos",
    "ks:ks_pop":379,
    "ks:ks_type":"VILLAGE",
    "name:eng_x_preferred":[
        "Chandipos"
    ],
    "wof:name":"Chandipos",
    "wof:placetype":"locality",
    "wof:population":379
},
  "geometry": {"coordinates":[85.438726,22.588612],"type":"Point"}
}