{
  "type": "Feature",
  "properties": {
    "iso:country":"IN",
    "ks:ks_name":"Bhartapur",
    "ks:ks_pop":987,
    "ks:ks_type":"VILLAGE",
    "name:eng_x_preferred":[
        "Bhartapur"
    ],
    "wof:name":"Bhartapur",
    "wof:placetype":"locality",
    "wof:population":987
},
  "geometry": {"coordinates":[80.105433,28.045788],"type":"Point"}
}