{
  "type": "Feature",
  "properties": {
    "gn:admin1_code":"36",
    "gn:admin2_code":"195.0",
    "gn:asciiname":"Deosiha",
    "gn:country_code":"IN",
    "gn:dem":73,
    "gn:feature_class":"P",
    "gn:feature_code":"PPL",
    "gn:name":"Deosiha",
    "gn:population":0,
    "gn:timezone":"Asia/Kolkata",
    "iso:country":"IN",
    "ks:ks_name":"Deosiha",
    "ks:ks_type":"VILLAGE",
    "name:eng_x_preferred":[
        "Deosiha"
    ],
    "wof:name":"Deosiha",
    "wof:placetype":"locality"
},
  "geometry": {"coordinates":[83.38090800000001,25.56214],"type":"Point"}
}