{
  "type": "Feature",
  "properties": {
    "iso:country":"IN",
    "ks:ks_name":"Kothali Jabgadi",
    "ks:ks_pop":330,
    "ks:ks_type":"HABITATION",
    "name:eng_x_preferred":[
        "Kothali Jabgadi"
    ],
    "wof:name":"Kothali Jabgadi",
    "wof:placetype":"locality",
    "wof:population":330
},
  "geometry": {"coordinates":[83.727385,23.387605],"type":"Point"}
}