{
  "type": "Feature",
  "properties": {
    "iso:country":"IN",
    "ks:ks_alt_nam":"GOPALPUR",
    "ks:ks_name":"Gopalpur",
    "ks:ks_pop":150,
    "ks:ks_type":"HABITATION",
    "name:eng_x_preferred":[
        "Gopalpur"
    ],
    "wof:name":"Gopalpur",
    "wof:placetype":"locality",
    "wof:population":150
},
  "geometry": {"coordinates":[78.334157,27.813639],"type":"Point"}
}