{
  "type": "Feature",
  "properties": {
    "gn:admin1_code":"39.0",
    "gn:admin2_code":"57.0",
    "gn:asciiname":"Barjia Ka Simar",
    "gn:country_code":"IN",
    "gn:dem":1809,
    "gn:feature_class":"P",
    "gn:feature_code":"PPL",
    "gn:name":"Barjia Ka Sim\u0101r",
    "gn:population":0,
    "gn:timezone":"Asia/Kolkata",
    "iso:country":"IN",
    "wof:name":"Barjia Ka Simar",
    "wof:placetype":"locality"
},
  "geometry": {"coordinates":[79.25985,29.99667],"type":"Point"}
}