{
  "type": "Feature",
  "properties": {
    "iso:country":"IN",
    "ks:ks_name":"Paraswar Raja",
    "ks:ks_pop":1421,
    "ks:ks_type":"HABITATION",
    "name:eng_x_preferred":[
        "Paraswar Raja"
    ],
    "wof:name":"Paraswar Raja",
    "wof:placetype":"locality",
    "wof:population":1421
},
  "geometry": {"coordinates":[82.770437,24.173793],"type":"Point"}
}