{
  "type": "Feature",
  "properties": {
    "gn:admin1_code":"25.0",
    "gn:admin2_code":"606.0",
    "gn:asciiname":"Vilvarayanellur",
    "gn:country_code":"IN",
    "gn:dem":135,
    "gn:feature_class":"P",
    "gn:feature_code":"PPL",
    "gn:name":"Vilvar\u0101yanell\u016br",
    "gn:population":0,
    "gn:timezone":"Asia/Kolkata",
    "iso:country":"IN",
    "ks:ks_name":"Vilvarayanallore",
    "ks:ks_pop":633,
    "ks:ks_type":"HABITATION",
    "name:eng_x_preferred":[
        "Vilvarayanallore"
    ],
    "name:eng_x_variant":[
        "Vilvarayanellur"
    ],
    "wof:name":"Vilvarayanallore",
    "wof:placetype":"locality",
    "wof:population":633
},
  "geometry": {"coordinates":[79.335638,12.528457],"type":"Point"}
}