{
  "type": "Feature",
  "properties": {
    "iso:country":"IN",
    "ks:ks_name":"Gorapdu",
    "ks:ks_pop":291,
    "ks:ks_type":"HABITATION",
    "name:eng_x_preferred":[
        "Gorapdu"
    ],
    "wof:name":"Gorapdu",
    "wof:placetype":"locality",
    "wof:population":291
},
  "geometry": {"coordinates":[83.82771700000001,18.766601],"type":"Point"}
}