{
  "type": "Feature",
  "properties": {
    "iso:country":"IN",
    "ks:ks_name":"Burrakayalapally",
    "ks:ks_pop":552,
    "ks:ks_type":"HABITATION",
    "name:eng_x_preferred":[
        "Burrakayalapally"
    ],
    "wof:name":"Burrakayalapally",
    "wof:placetype":"locality",
    "wof:population":552
},
  "geometry": {"coordinates":[79.48617900000001,18.657176],"type":"Point"}
}