{
  "type": "Feature",
  "properties": {
    "iso:country":"IN",
    "ks:ks_name":"Vandanam East",
    "ks:ks_pop":997,
    "ks:ks_type":"HABITATION",
    "name:eng_x_preferred":[
        "Vandanam East"
    ],
    "wof:name":"Vandanam East",
    "wof:placetype":"locality",
    "wof:population":997
},
  "geometry": {"coordinates":[76.371206,9.415141],"type":"Point"}
}