{
  "type": "Feature",
  "properties": {
    "gn:admin1_code":"21.0",
    "gn:admin2_code":"374.0",
    "gn:asciiname":"Kansbahal",
    "gn:country_code":"IN",
    "gn:dem":217,
    "gn:feature_class":"P",
    "gn:feature_code":"PPL",
    "gn:name":"Kansbahal",
    "gn:population":0,
    "gn:timezone":"Asia/Kolkata",
    "iso:country":"IN",
    "name:ori_x_preferred":[
        "\u0b15\u0b3e\u0b02\u0b36\u0b2c\u0b3e\u0b39\u0b3e\u0b32"
    ],
    "wof:name":"Kansbahal",
    "wof:placetype":"locality"
},
  "geometry": {"coordinates":[84.66348000000001,22.21644],"type":"Point"}
}