{
  "type": "Feature",
  "properties": {
    "iso:country":"IN",
    "ks:ks_name":"Mahokiya",
    "ks:ks_pop":131,
    "ks:ks_type":"HABITATION",
    "name:eng_x_preferred":[
        "Mahokiya"
    ],
    "wof:name":"Mahokiya",
    "wof:placetype":"locality",
    "wof:population":131
},
  "geometry": {"coordinates":[79.066377,27.522285],"type":"Point"}
}