{
  "type": "Feature",
  "properties": {
    "iso:country":"IN",
    "ks:ks_name":"Haveli",
    "ks:ks_pop":80,
    "ks:ks_type":"HABITATION",
    "ks:ks_uagg_main":0,
    "name:eng_x_preferred":[
        "Haveli"
    ],
    "wof:name":"Haveli",
    "wof:placetype":"neighbourhood",
    "wof:population":80
},
  "geometry": {"coordinates":[78.09507499999999,26.842228],"type":"Point"}
}