{
  "type": "Feature",
  "properties": {
    "iso:country":"IN",
    "ks:ks_name":"Kalyajhor",
    "ks:ks_pop":752,
    "ks:ks_type":"VILLAGE",
    "name:eng_x_preferred":[
        "Kalyajhor"
    ],
    "wof:name":"Kalyajhor",
    "wof:placetype":"locality",
    "wof:population":752
},
  "geometry": {"coordinates":[86.58712199999999,23.445675],"type":"Point"}
}