{
  "type": "Feature",
  "properties": {
    "iso:country":"IN",
    "ks:ks_name":"Teekhi Ka Khera",
    "ks:ks_pop":369,
    "ks:ks_type":"HABITATION",
    "name:eng_x_preferred":[
        "Teekhi Ka Khera"
    ],
    "wof:name":"Teekhi Ka Khera",
    "wof:placetype":"locality",
    "wof:population":369
},
  "geometry": {"coordinates":[75.093642,25.071969],"type":"Point"}
}