{
  "type": "Feature",
  "properties": {
    "gn:admin1_code":"12.0",
    "gn:admin2_code":"16.0",
    "gn:asciiname":"Maidan",
    "gn:country_code":"IN",
    "gn:dem":2747,
    "gn:feature_class":"P",
    "gn:feature_code":"PPL",
    "gn:name":"Maidan",
    "gn:population":0,
    "gn:timezone":"Asia/Kolkata",
    "iso:country":"IN",
    "wof:name":"Maidan",
    "wof:placetype":"locality"
},
  "geometry": {"coordinates":[75.60420000000001,33.25837],"type":"Point"}
}