{
  "type": "Feature",
  "properties": {
    "iso:country":"IN",
    "ks:ks_name":"Nillur Kanchi Bavi",
    "ks:ks_pop":8,
    "ks:ks_type":"HABITATION",
    "name:eng_x_preferred":[
        "Nillur Kanchi Bavi"
    ],
    "wof:name":"Nillur Kanchi Bavi",
    "wof:placetype":"locality",
    "wof:population":8
},
  "geometry": {"coordinates":[74.32916,14.698037],"type":"Point"}
}