{
  "type": "Feature",
  "properties": {
    "gn:admin1_code":"12.0",
    "gn:admin2_code":"010",
    "gn:asciiname":"Rair Baihk",
    "gn:country_code":"IN",
    "gn:dem":2290,
    "gn:feature_class":"P",
    "gn:feature_code":"PPL",
    "gn:name":"Rair Baihk",
    "gn:population":0,
    "gn:timezone":"Asia/Kolkata",
    "iso:country":"IN",
    "wof:name":"Rair Baihk",
    "wof:placetype":"locality"
},
  "geometry": {"coordinates":[74.85410999999998,34.26423],"type":"Point"}
}