{
  "type": "Feature",
  "properties": {
    "iso:country":"IN",
    "ks:ks_name":"Kherajgarh",
    "ks:ks_pop":462,
    "ks:ks_type":"HABITATION",
    "name:eng_x_preferred":[
        "Kherajgarh"
    ],
    "wof:name":"Kherajgarh",
    "wof:placetype":"locality",
    "wof:population":462
},
  "geometry": {"coordinates":[72.465233,26.323356],"type":"Point"}
}