{
  "type": "Feature",
  "properties": {
    "iso:country":"IN",
    "ks:ks_name":"Puliyampatti",
    "ks:ks_pop":1857,
    "ks:ks_type":"HABITATION",
    "name:eng_x_preferred":[
        "Puliyampatti"
    ],
    "wof:name":"Puliyampatti",
    "wof:placetype":"locality",
    "wof:population":1857
},
  "geometry": {"coordinates":[78.707618,12.155162],"type":"Point"}
}