{
  "type": "Feature",
  "properties": {
    "iso:country":"IN",
    "ks:ks_name":"Samantpura",
    "ks:ks_pop":20,
    "ks:ks_type":"VILLAGE",
    "name:eng_x_preferred":[
        "Samantpura"
    ],
    "wof:name":"Samantpura",
    "wof:placetype":"locality",
    "wof:population":20
},
  "geometry": {"coordinates":[73.270539,22.618258],"type":"Point"}
}