{
  "type": "Feature",
  "properties": {
    "gn:admin1_code":"34.0",
    "gn:admin2_code":"203.0",
    "gn:asciiname":"Pakri",
    "gn:country_code":"IN",
    "gn:dem":83,
    "gn:feature_class":"P",
    "gn:feature_code":"PPL",
    "gn:name":"Pakri",
    "gn:population":0,
    "gn:timezone":"Asia/Kolkata",
    "iso:country":"IN",
    "name:est_x_preferred":[
        "Pakri"
    ],
    "name:lav_x_preferred":[
        "Pakri"
    ],
    "wof:name":"Pakri",
    "wof:placetype":"locality"
},
  "geometry": {"coordinates":[84.26608,26.93845],"type":"Point"}
}