{
  "type": "Feature",
  "properties": {
    "gn:admin1_code":"16",
    "gn:admin2_code":"516.0",
    "gn:asciiname":"Rasegaon",
    "gn:country_code":"IN",
    "gn:dem":705,
    "gn:feature_class":"P",
    "gn:feature_code":"PPL",
    "gn:name":"R\u0101segaon",
    "gn:population":0,
    "gn:timezone":"Asia/Kolkata",
    "iso:country":"IN",
    "name:und_x_variant":[
        "B\u0101s\u0113gaon",
        "R\u0101segaon"
    ],
    "wof:name":"Rasegaon",
    "wof:placetype":"locality"
},
  "geometry": {"coordinates":[73.74821999999998,20.15677],"type":"Point"}
}