{
  "type": "Feature",
  "properties": {
    "iso:country":"IN",
    "ks:ks_name":"Bela",
    "ks:ks_pop":0,
    "ks:ks_type":"VILLAGE",
    "name:eng_x_preferred":[
        "Bela"
    ],
    "wof:name":"Bela",
    "wof:placetype":"locality",
    "wof:population":0
},
  "geometry": {"coordinates":[86.650884,25.002939],"type":"Point"}
}