{
  "type": "Feature",
  "properties": {
    "gn:admin1_code":"11.0",
    "gn:admin2_code":"33.0",
    "gn:asciiname":"Devthi",
    "gn:country_code":"IN",
    "gn:dem":1418,
    "gn:feature_class":"P",
    "gn:feature_code":"PPL",
    "gn:name":"Devthi",
    "gn:population":0,
    "gn:timezone":"Asia/Kolkata",
    "iso:country":"IN",
    "wof:name":"Devthi",
    "wof:placetype":"locality"
},
  "geometry": {"coordinates":[77.27174000000002,31.14676],"type":"Point"}
}