{
  "type": "Feature",
  "properties": {
    "iso:country":"IN",
    "ks:ks_name":"Mahaliya",
    "ks:ks_pop":434,
    "ks:ks_type":"HABITATION",
    "name:eng_x_preferred":[
        "Mahaliya"
    ],
    "wof:name":"Mahaliya",
    "wof:placetype":"locality",
    "wof:population":434
},
  "geometry": {"coordinates":[81.984821,27.370641],"type":"Point"}
}