{
  "type": "Feature",
  "properties": {
    "gn:admin1_code":"24.0",
    "gn:admin2_code":"110",
    "gn:asciiname":"Jamwa Ramgarh",
    "gn:cc2":"IN",
    "gn:country_code":"IN",
    "gn:dem":400,
    "gn:feature_class":"P",
    "gn:feature_code":"PPL",
    "gn:name":"Jamwa R\u0101mgarh",
    "gn:population":0,
    "gn:timezone":"Asia/Kolkata",
    "iso:country":"IN",
    "name:und_x_variant":[
        "R\u0101mgarh Jamwa",
        "Jamwa R\u0101mgarh"
    ],
    "wof:name":"Jamwa Ramgarh",
    "wof:placetype":"locality"
},
  "geometry": {"coordinates":[76.01089,27.02021],"type":"Point"}
}