{
  "type": "Feature",
  "properties": {
    "iso:country":"IN",
    "ks:ks_alt_nam":"Mathi\u0101",
    "ks:ks_name":"Mathia",
    "ks:ks_type":"VILLAGE",
    "name:eng_x_preferred":[
        "Mathia"
    ],
    "name:eng_x_variant":[
        "Mathi\u0101"
    ],
    "wof:name":"Mathia",
    "wof:placetype":"locality"
},
  "geometry": {"coordinates":[84.205969,26.981085],"type":"Point"}
}