{
  "type": "Feature",
  "properties": {
    "gn:admin1_code":"40.0",
    "gn:admin2_code":"537.0",
    "gn:asciiname":"Ganapuram",
    "gn:country_code":"IN",
    "gn:dem":465,
    "gn:feature_class":"P",
    "gn:feature_code":"PPL",
    "gn:name":"Gan\u0101puram",
    "gn:population":0,
    "gn:timezone":"Asia/Kolkata",
    "iso:country":"IN",
    "wof:name":"Ganapuram",
    "wof:placetype":"locality"
},
  "geometry": {"coordinates":[78.68814999999999,17.42973],"type":"Point"}
}