{
  "type": "Feature",
  "properties": {
    "iso:country":"IN",
    "ks:ks_name":"Madaiya Kaharan",
    "ks:ks_pop":86,
    "ks:ks_type":"HABITATION",
    "name:eng_x_preferred":[
        "Madaiya Kaharan"
    ],
    "wof:name":"Madaiya Kaharan",
    "wof:placetype":"locality",
    "wof:population":86
},
  "geometry": {"coordinates":[79.529336,26.773966],"type":"Point"}
}