{
  "type": "Feature",
  "properties": {
    "gn:admin1_code":"25.0",
    "gn:admin2_code":"602.0",
    "gn:asciiname":"Gudem",
    "gn:country_code":"IN",
    "gn:dem":100,
    "gn:feature_class":"P",
    "gn:feature_code":"PPL",
    "gn:name":"Gudem",
    "gn:population":0,
    "gn:timezone":"Asia/Kolkata",
    "iso:country":"IN",
    "name:tel_x_preferred":[
        "\u0c17\u0c42\u0c21\u0c46\u0c2e\u0c41"
    ],
    "wof:name":"Gudem",
    "wof:placetype":"neighbourhood"
},
  "geometry": {"coordinates":[79.82325,13.27143],"type":"Point"}
}