{
  "type": "Feature",
  "properties": {
    "iso:country":"IN",
    "ks:ks_name":"Akkadevanahalli",
    "ks:ks_pop":18,
    "ks:ks_type":"VILLAGE",
    "name:eng_x_preferred":[
        "Akkadevanahalli"
    ],
    "wof:name":"Akkadevanahalli",
    "wof:placetype":"locality",
    "wof:population":18
},
  "geometry": {"coordinates":[76.297228,12.072024],"type":"Point"}
}