{
  "type": "Feature",
  "properties": {
    "gn:admin1_code":"11.0",
    "gn:admin2_code":"33.0",
    "gn:asciiname":"Gahan",
    "gn:country_code":"IN",
    "gn:dem":1835,
    "gn:feature_class":"P",
    "gn:feature_code":"PPL",
    "gn:name":"G\u0101han",
    "gn:population":0,
    "gn:timezone":"Asia/Kolkata",
    "iso:country":"IN",
    "name:deu_x_preferred":[
        "Gahan"
    ],
    "name:fra_x_preferred":[
        "Gahan"
    ],
    "wof:name":"Gahan",
    "wof:placetype":"locality"
},
  "geometry": {"coordinates":[77.3839,31.28451],"type":"Point"}
}