{
  "type": "Feature",
  "properties": {
    "gn:admin1_code":"09",
    "gn:admin2_code":"478.0",
    "gn:asciiname":"Mokal",
    "gn:country_code":"IN",
    "gn:dem":13,
    "gn:feature_class":"P",
    "gn:feature_code":"PPL",
    "gn:name":"Mokal",
    "gn:population":0,
    "gn:timezone":"Asia/Kolkata",
    "iso:country":"IN",
    "wof:name":"Mokal",
    "wof:placetype":"locality"
},
  "geometry": {"coordinates":[69.78713,21.60844],"type":"Point"}
}