{
  "type": "Feature",
  "properties": {
    "iso:country":"IN",
    "ks:ks_name":"Raikera Tokopara",
    "ks:ks_pop":761,
    "ks:ks_type":"HABITATION",
    "name:eng_x_preferred":[
        "Raikera Tokopara"
    ],
    "wof:name":"Raikera Tokopara",
    "wof:placetype":"locality",
    "wof:population":761
},
  "geometry": {"coordinates":[83.503675,22.837618],"type":"Point"}
}