{
  "type": "Feature",
  "properties": {
    "iso:country":"IN",
    "ks:ks_name":"Chhurichukha",
    "ks:ks_pop":192,
    "ks:ks_type":"VILLAGE",
    "name:eng_x_preferred":[
        "Chhurichukha"
    ],
    "wof:name":"Chhurichukha",
    "wof:placetype":"locality",
    "wof:population":192
},
  "geometry": {"coordinates":[84.435901,22.362417],"type":"Point"}
}