{
  "type": "Feature",
  "properties": {
    "iso:country":"IN",
    "ks:ks_name":"Maghnuwa No2",
    "ks:ks_pop":12,
    "ks:ks_type":"HABITATION",
    "name:eng_x_preferred":[
        "Maghnuwa No2"
    ],
    "wof:name":"Maghnuwa No2",
    "wof:placetype":"locality",
    "wof:population":12
},
  "geometry": {"coordinates":[93.78823,26.942333],"type":"Point"}
}