{
  "type": "Feature",
  "properties": {
    "gn:admin1_code":"12.0",
    "gn:admin2_code":"6.0",
    "gn:asciiname":"Saji Bagla",
    "gn:country_code":"IN",
    "gn:dem":2102,
    "gn:feature_class":"P",
    "gn:feature_code":"PPL",
    "gn:name":"Saji Bagla",
    "gn:population":0,
    "gn:timezone":"Asia/Kolkata",
    "iso:country":"IN",
    "wof:name":"Saji Bagla",
    "wof:placetype":"locality"
},
  "geometry": {"coordinates":[74.41365,33.52329],"type":"Point"}
}