{
  "type": "Feature",
  "properties": {
    "iso:country":"IN",
    "ks:ks_name":"Taran",
    "ks:ks_pop":236,
    "ks:ks_type":"HABITATION",
    "name:eng_x_preferred":[
        "Taran"
    ],
    "wof:name":"Taran",
    "wof:placetype":"locality",
    "wof:population":236
},
  "geometry": {"coordinates":[79.828638,26.761599],"type":"Point"}
}