{
  "type": "Feature",
  "properties": {
    "iso:country":"IN",
    "name:eng_x_preferred":[
        "Zoological Garden Area"
    ],
    "qs:gn_adm0_cc":"IN",
    "qs:gn_local":1275004,
    "qs:gn_nam_loc":"Kolkata, Kolkata, West Bengal, IN",
    "qs:gn_namadm1":"28",
    "qs:local_max":2678,
    "qs:local_sum":20035,
    "qs:localhoods":53,
    "qs:name":"Zoological Garden Area",
    "qs:name_adm0":"India",
    "qs:name_adm1":"West Bengal",
    "qs:name_adm2":"Kolkata",
    "qs:name_local":"Kolkata",
    "qs:photo_max":150,
    "qs:photo_sum":631,
    "qs:placetype":"Suburb",
    "qs:quad_count":24,
    "qs:woe_adm0":23424848,
    "qs:woe_adm1":2345761,
    "qs:woe_adm2":12586798,
    "qs:woe_lau":0,
    "qs:woe_local":2295386,
    "qs:woe_ver":"7.10.0",
    "wof:lang":[
        "eng"
    ],
    "wof:name":"Zoological Garden Area",
    "wof:placetype":"neighbourhood"
},
  "geometry": {"coordinates":[88.329245,22.532892],"type":"Point"}
}