{
  "type": "Feature",
  "properties": {
    "gn:admin1_code":"35",
    "gn:admin2_code":"455.0",
    "gn:asciiname":"Mohnighat",
    "gn:country_code":"IN",
    "gn:dem":458,
    "gn:feature_class":"P",
    "gn:feature_code":"PPL",
    "gn:name":"Mohn\u012bgh\u0101t",
    "gn:population":0,
    "gn:timezone":"Asia/Kolkata",
    "iso:country":"IN",
    "wof:name":"Mohnighat",
    "wof:placetype":"locality"
},
  "geometry": {"coordinates":[79.02631,22.67826],"type":"Point"}
}