{
  "type": "Feature",
  "properties": {
    "gn:admin1_code":"36.0",
    "gn:admin2_code":"184.0",
    "gn:asciiname":"Sukrauli",
    "gn:country_code":"IN",
    "gn:dem":93,
    "gn:feature_class":"P",
    "gn:feature_code":"PPL",
    "gn:name":"Sukrauli",
    "gn:population":0,
    "gn:timezone":"Asia/Kolkata",
    "iso:country":"IN",
    "name:ceb_x_preferred":[
        "Sukrauli"
    ],
    "name:fra_x_preferred":[
        "Sukrauli"
    ],
    "name:mai_x_preferred":[
        "\u0938\u0941\u0915\u094d\u0930\u094c\u0932\u0940"
    ],
    "name:msa_x_preferred":[
        "Sukrauli"
    ],
    "name:nep_x_preferred":[
        "\u0938\u0941\u0915\u094d\u0930\u094c\u0932\u0940"
    ],
    "name:new_x_preferred":[
        "\u0936\u0941\u0915\u094d\u0930\u094c\u0932\u0940"
    ],
    "name:pol_x_preferred":[
        "Sukrauli"
    ],
    "wof:name":"Sukrauli",
    "wof:placetype":"locality"
},
  "geometry": {"coordinates":[82.89259,27.22967],"type":"Point"}
}