{
  "type": "Feature",
  "properties": {
    "iso:country":"IN",
    "ks:ks_name":"Jaton Ki Dhani",
    "ks:ks_pop":61,
    "ks:ks_type":"HABITATION",
    "name:eng_x_preferred":[
        "Jaton Ki Dhani"
    ],
    "wof:name":"Jaton Ki Dhani",
    "wof:placetype":"locality",
    "wof:population":61
},
  "geometry": {"coordinates":[74.255219,29.410106],"type":"Point"}
}