{
  "type": "Feature",
  "properties": {
    "gn:admin1_code":"35.0",
    "gn:admin2_code":"447.0",
    "gn:asciiname":"Ghodpend",
    "gn:country_code":"IN",
    "gn:dem":401,
    "gn:feature_class":"P",
    "gn:feature_code":"PPL",
    "gn:name":"Ghodpend",
    "gn:population":0,
    "gn:timezone":"Asia/Kolkata",
    "iso:country":"IN",
    "ks:ks_alt_nam":"GHORPEND",
    "ks:ks_name":"Ghorpend",
    "ks:ks_pop":134,
    "ks:ks_type":"HABITATION",
    "name:eng_x_preferred":[
        "Ghorpend"
    ],
    "name:eng_x_variant":[
        "Ghodpend"
    ],
    "wof:name":"Ghorpend",
    "wof:placetype":"locality",
    "wof:population":134
},
  "geometry": {"coordinates":[78.00232,21.427466],"type":"Point"}
}