{
  "type": "Feature",
  "properties": {
    "iso:country":"IN",
    "ks:ks_name":"Agasthicode",
    "ks:ks_pop":848,
    "ks:ks_type":"HABITATION",
    "name:eng_x_preferred":[
        "Agasthicode"
    ],
    "wof:name":"Agasthicode",
    "wof:placetype":"locality",
    "wof:population":848
},
  "geometry": {"coordinates":[76.913527,8.934995],"type":"Point"}
}