{
  "type": "Feature",
  "properties": {
    "iso:country":"IN",
    "ks:ks_name":"Debattar Khopati Pt I",
    "ks:ks_pop":1217,
    "ks:ks_type":"HABITATION",
    "name:eng_x_preferred":[
        "Debattar Khopati Pt I"
    ],
    "wof:name":"Debattar Khopati Pt I",
    "wof:placetype":"locality",
    "wof:population":1217
},
  "geometry": {"coordinates":[90.005887,26.176944],"type":"Point"}
}