{
  "type": "Feature",
  "properties": {
    "iso:country":"IN",
    "ks:ks_name":"Chhachha",
    "ks:ks_pop":2813,
    "ks:ks_type":"VILLAGE",
    "ks:ks_uagg_main":0,
    "name:eng_x_preferred":[
        "Chhachha"
    ],
    "wof:name":"Chhachha",
    "wof:placetype":"neighbourhood",
    "wof:population":2813
},
  "geometry": {"coordinates":[85.99651799999999,26.276705],"type":"Point"}
}