{
  "type": "Feature",
  "properties": {
    "iso:country":"IN",
    "ks:ks_name":"Taragun",
    "ks:ks_pop":83,
    "ks:ks_type":"HABITATION",
    "name:eng_x_preferred":[
        "Taragun"
    ],
    "wof:name":"Taragun",
    "wof:placetype":"locality",
    "wof:population":83
},
  "geometry": {"coordinates":[80.15576799999999,29.713279],"type":"Point"}
}