{
  "type": "Feature",
  "properties": {
    "gn:admin1_code":"09",
    "gn:admin2_code":"484.0",
    "gn:asciiname":"Muwala",
    "gn:country_code":"IN",
    "gn:dem":89,
    "gn:feature_class":"P",
    "gn:feature_code":"PPL",
    "gn:name":"Muw\u0101la",
    "gn:population":0,
    "gn:timezone":"Asia/Kolkata",
    "iso:country":"IN",
    "wof:name":"Muwala",
    "wof:placetype":"locality"
},
  "geometry": {"coordinates":[73.43080999999999,22.55501],"type":"Point"}
}