{
  "type": "Feature",
  "properties": {
    "iso:country":"IN",
    "ks:ks_alt_nam":"CHARTOLI",
    "ks:ks_name":"Chartoli",
    "ks:ks_pop":256,
    "ks:ks_type":"HABITATION",
    "name:eng_x_preferred":[
        "Chartoli"
    ],
    "wof:name":"Chartoli",
    "wof:placetype":"locality",
    "wof:population":256
},
  "geometry": {"coordinates":[83.82420999999999,22.779284],"type":"Point"}
}