{
  "type": "Feature",
  "properties": {
    "gn:admin1_code":"12.0",
    "gn:admin2_code":"008",
    "gn:asciiname":"Gur Sir",
    "gn:country_code":"IN",
    "gn:dem":1586,
    "gn:feature_class":"P",
    "gn:feature_code":"PPL",
    "gn:name":"Gur S\u012br",
    "gn:population":0,
    "gn:timezone":"Asia/Kolkata",
    "iso:country":"IN",
    "name:und_x_variant":[
        "Gur S\u012br",
        "G\u016br S\u012br"
    ],
    "wof:name":"Gur Sir",
    "wof:placetype":"locality"
},
  "geometry": {"coordinates":[74.42801999999998,34.26032],"type":"Point"}
}