{
  "type": "Feature",
  "properties": {
    "iso:country":"IN",
    "ks:ks_name":"Dungargam",
    "ks:ks_pop":676,
    "ks:ks_type":"VILLAGE",
    "name:eng_x_preferred":[
        "Dungargam"
    ],
    "wof:name":"Dungargam",
    "wof:placetype":"locality",
    "wof:population":676
},
  "geometry": {"coordinates":[73.350444,21.163611],"type":"Point"}
}