{
  "type": "Feature",
  "properties": {
    "gn:admin1_code":"40",
    "gn:admin2_code":"535.0",
    "gn:asciiname":"Darkhaspalli",
    "gn:country_code":"IN",
    "gn:dem":563,
    "gn:feature_class":"P",
    "gn:feature_code":"PPL",
    "gn:name":"Darkh\u0101spalli",
    "gn:population":0,
    "gn:timezone":"Asia/Kolkata",
    "iso:country":"IN",
    "wof:name":"Darkhaspalli",
    "wof:placetype":"neighbourhood"
},
  "geometry": {"coordinates":[77.90474,17.90764],"type":"Point"}
}