{
  "type": "Feature",
  "properties": {
    "iso:country":"IN",
    "ks:ks_name":"Meenakshipuram",
    "ks:ks_pop":250,
    "ks:ks_type":"HABITATION",
    "name:eng_x_preferred":[
        "Meenakshipuram"
    ],
    "wof:name":"Meenakshipuram",
    "wof:placetype":"locality",
    "wof:population":250
},
  "geometry": {"coordinates":[78.369573,9.830911],"type":"Point"}
}