{
  "type": "Feature",
  "properties": {
    "iso:country":"IN",
    "ks:ks_name":"Jadhavwasti",
    "ks:ks_pop":60,
    "ks:ks_type":"HABITATION",
    "name:eng_x_preferred":[
        "Jadhavwasti"
    ],
    "wof:name":"Jadhavwasti",
    "wof:placetype":"locality",
    "wof:population":60
},
  "geometry": {"coordinates":[75.281368,20.096124],"type":"Point"}
}