{
  "type": "Feature",
  "properties": {
    "gn:admin1_code":"11",
    "gn:admin2_code":"27.0",
    "gn:asciiname":"Bahna",
    "gn:country_code":"IN",
    "gn:dem":802,
    "gn:feature_class":"P",
    "gn:feature_code":"PPL",
    "gn:name":"Bahna",
    "gn:population":0,
    "gn:timezone":"Asia/Kolkata",
    "iso:country":"IN",
    "name:ceb_x_preferred":[
        "Comuna Bahna"
    ],
    "name:fra_x_preferred":[
        "Bahna"
    ],
    "name:ita_x_preferred":[
        "Bahna"
    ],
    "name:msa_x_preferred":[
        "Bahna"
    ],
    "name:nld_x_preferred":[
        "Bahna"
    ],
    "name:por_x_preferred":[
        "Bahna"
    ],
    "name:ron_x_preferred":[
        "Comuna Bahna"
    ],
    "name:srp_x_preferred":[
        "\u041e\u043f\u0448\u0442\u0438\u043d\u0430 \u0411\u0430\u0445\u043d\u0430"
    ],
    "name:ukr_x_preferred":[
        "\u0411\u0430\u0445\u043d\u0430"
    ],
    "name:vie_x_preferred":[
        "Bahna"
    ],
    "name:vol_x_preferred":[
        "Bahna"
    ],
    "name:zho_x_preferred":[
        "\u5df4\u8d6b\u7d0d\u9109"
    ],
    "wof:name":"Bahna",
    "wof:placetype":"locality"
},
  "geometry": {"coordinates":[76.80474,31.4727],"type":"Point"}
}