{
  "type": "Feature",
  "properties": {
    "iso:country":"IN",
    "ks:ks_name":"Ojjonigudem",
    "ks:ks_pop":188,
    "ks:ks_type":"HABITATION",
    "name:eng_x_preferred":[
        "Ojjonigudem"
    ],
    "wof:name":"Ojjonigudem",
    "wof:placetype":"locality",
    "wof:population":188
},
  "geometry": {"coordinates":[80.552947,17.646791],"type":"Point"}
}