{
  "type": "Feature",
  "properties": {
    "iso:country":"IN",
    "ks:ks_name":"Garmarahatigar",
    "ks:ks_pop":670,
    "ks:ks_type":"HABITATION",
    "name:eng_x_preferred":[
        "Garmarahatigar"
    ],
    "wof:name":"Garmarahatigar",
    "wof:placetype":"locality",
    "wof:population":670
},
  "geometry": {"coordinates":[94.982651,27.315193],"type":"Point"}
}