{
  "type": "Feature",
  "properties": {
    "iso:country":"IN",
    "ks:ks_name":"Sindikua",
    "ks:ks_pop":623,
    "ks:ks_type":"HABITATION",
    "name:eng_x_preferred":[
        "Sindikua"
    ],
    "wof:name":"Sindikua",
    "wof:placetype":"locality",
    "wof:population":623
},
  "geometry": {"coordinates":[75.157078,22.431545],"type":"Point"}
}