{
  "type": "Feature",
  "properties": {
    "iso:country":"IN",
    "ks:ks_name":"Nallakambireddigaripalle",
    "ks:ks_pop":143,
    "ks:ks_type":"HABITATION",
    "name:eng_x_preferred":[
        "Nallakambireddigaripalle"
    ],
    "wof:name":"Nallakambireddigaripalle",
    "wof:placetype":"locality",
    "wof:population":143
},
  "geometry": {"coordinates":[78.941383,13.833895],"type":"Point"}
}