{
  "type": "Feature",
  "properties": {
    "iso:country":"IN",
    "ks:ks_name":"Phardodon Ka Phanta",
    "ks:ks_pop":562,
    "ks:ks_type":"HABITATION",
    "name:eng_x_preferred":[
        "Phardodon Ka Phanta"
    ],
    "wof:name":"Phardodon Ka Phanta",
    "wof:placetype":"locality",
    "wof:population":562
},
  "geometry": {"coordinates":[71.51893099999999,25.154661],"type":"Point"}
}