{
  "type": "Feature",
  "properties": {
    "gn:admin1_code":"36",
    "gn:admin2_code":"197.0",
    "gn:asciiname":"Ralhupur",
    "gn:country_code":"IN",
    "gn:dem":82,
    "gn:feature_class":"P",
    "gn:feature_code":"PPL",
    "gn:name":"Ralh\u016bpur",
    "gn:population":0,
    "gn:timezone":"Asia/Kolkata",
    "iso:country":"IN",
    "ks:ks_name":"Salhupur",
    "ks:ks_type":"VILLAGE",
    "name:eng_x_preferred":[
        "Salhupur"
    ],
    "name:eng_x_variant":[
        "Ralhupur"
    ],
    "wof:name":"Salhupur",
    "wof:placetype":"locality"
},
  "geometry": {"coordinates":[83.036906,25.253397],"type":"Point"}
}