{
  "type": "Feature",
  "properties": {
    "gn:admin1_code":"16.0",
    "gn:admin2_code":"497.0",
    "gn:asciiname":"Arla",
    "gn:country_code":"IN",
    "gn:dem":129,
    "gn:feature_class":"P",
    "gn:feature_code":"PPL",
    "gn:name":"\u0100rla",
    "gn:population":0,
    "gn:timezone":"Asia/Kolkata",
    "iso:country":"IN",
    "name:ara_x_preferred":[
        "\u0623\u0631\u0644\u0627"
    ],
    "name:deu_x_preferred":[
        "Arla"
    ],
    "name:epo_x_preferred":[
        "Arla"
    ],
    "name:nld_x_preferred":[
        "Arla"
    ],
    "name:swe_x_preferred":[
        "Arla"
    ],
    "wof:name":"Arla",
    "wof:placetype":"neighbourhood"
},
  "geometry": {"coordinates":[74.49424999999999,21.42241],"type":"Point"}
}