{
  "type": "Feature",
  "properties": {
    "gn:admin1_code":"36.0",
    "gn:admin2_code":"149.0",
    "gn:asciiname":"Shikrapur",
    "gn:country_code":"IN",
    "gn:dem":174,
    "gn:feature_class":"P",
    "gn:feature_code":"PPL",
    "gn:name":"Shikr\u0101pur",
    "gn:population":0,
    "gn:timezone":"Asia/Kolkata",
    "iso:country":"IN",
    "name:ceb_x_preferred":[
        "Shikrapur"
    ],
    "name:swe_x_preferred":[
        "Shikrapur"
    ],
    "wof:name":"Shikrapur",
    "wof:placetype":"locality"
},
  "geometry": {"coordinates":[79.12411,28.08427],"type":"Point"}
}