{
  "type": "Feature",
  "properties": {
    "iso:country":"IN",
    "ks:ks_name":"Mukandpur",
    "ks:ks_type":"VILLAGE",
    "ks:ks_uagg_main":0,
    "name:eng_x_preferred":[
        "Mukandpur"
    ],
    "wof:name":"Mukandpur",
    "wof:placetype":"neighbourhood"
},
  "geometry": {"coordinates":[77.183154,28.739436],"type":"Point"}
}