{
  "type": "Feature",
  "properties": {
    "iso:country":"IN",
    "ks:ks_alt_nam":"BAR TILLA",
    "ks:ks_name":"Bar Tilla",
    "ks:ks_pop":139,
    "ks:ks_type":"HABITATION",
    "ks:ks_uagg_main":0,
    "name:eng_x_preferred":[
        "Bar Tilla"
    ],
    "wof:name":"Bar Tilla",
    "wof:placetype":"neighbourhood",
    "wof:population":139
},
  "geometry": {"coordinates":[91.65397,24.124944],"type":"Point"}
}