{
  "type": "Feature",
  "properties": {
    "gn:admin1_code":"36",
    "gn:admin2_code":"193.0",
    "gn:asciiname":"Korahi",
    "gn:country_code":"IN",
    "gn:dem":70,
    "gn:feature_class":"P",
    "gn:feature_code":"PPL",
    "gn:name":"Korah\u012b",
    "gn:population":0,
    "gn:timezone":"Asia/Kolkata",
    "iso:country":"IN",
    "ks:ks_name":"Kurahi",
    "ks:ks_pop":580,
    "ks:ks_type":"HABITATION",
    "ks:ks_uagg_main":0,
    "name:eng_x_preferred":[
        "Kurahi"
    ],
    "wof:name":"Kurahi",
    "wof:placetype":"neighbourhood",
    "wof:population":580
},
  "geometry": {"coordinates":[83.975408,25.972952],"type":"Point"}
}