{
  "type": "Feature",
  "properties": {
    "gn:admin1_code":"19",
    "gn:admin2_code":"558.0",
    "gn:asciiname":"Ujni",
    "gn:country_code":"IN",
    "gn:dem":528,
    "gn:feature_class":"P",
    "gn:feature_code":"PPL",
    "gn:name":"Ujni",
    "gn:population":0,
    "gn:timezone":"Asia/Kolkata",
    "iso:country":"IN",
    "wof:name":"Ujni",
    "wof:placetype":"locality"
},
  "geometry": {"coordinates":[77.54696,18.17402],"type":"Point"}
}