{
  "type": "Feature",
  "properties": {
    "gn:admin1_code":"39.0",
    "gn:admin2_code":"64.0",
    "gn:asciiname":"Jamar",
    "gn:country_code":"IN",
    "gn:dem":1015,
    "gn:feature_class":"P",
    "gn:feature_code":"PPL",
    "gn:name":"Jam\u0101r",
    "gn:population":0,
    "gn:timezone":"Asia/Kolkata",
    "iso:country":"IN",
    "name:deu_x_preferred":[
        "Jamar"
    ],
    "name:fra_x_preferred":[
        "Jamar"
    ],
    "wof:name":"Jamar",
    "wof:placetype":"locality"
},
  "geometry": {"coordinates":[79.88746999999999,29.49018],"type":"Point"}
}