{
  "type": "Feature",
  "properties": {
    "iso:country":"IN",
    "ks:ks_name":"Khaira",
    "ks:ks_pop":1390,
    "ks:ks_type":"VILLAGE",
    "ks:ks_uagg_main":0,
    "name:eng_x_preferred":[
        "Khaira"
    ],
    "wof:name":"Khaira",
    "wof:placetype":"neighbourhood",
    "wof:population":1390
},
  "geometry": {"coordinates":[76.14075200000001,28.264353],"type":"Point"}
}