{
  "type": "Feature",
  "properties": {
    "iso:country":"IN",
    "ks:ks_name":"Bara Daona",
    "ks:ks_pop":164,
    "ks:ks_type":"VILLAGE",
    "name:eng_x_preferred":[
        "Bara Daona"
    ],
    "wof:name":"Bara Daona",
    "wof:placetype":"locality",
    "wof:population":164
},
  "geometry": {"coordinates":[85.97630599999999,22.645492],"type":"Point"}
}