{
  "type": "Feature",
  "properties": {
    "gn:admin1_code":"19.0",
    "gn:admin2_code":"573.0",
    "gn:asciiname":"Karadahalli",
    "gn:country_code":"IN",
    "gn:dem":819,
    "gn:feature_class":"P",
    "gn:feature_code":"PPL",
    "gn:name":"Karadahalli",
    "gn:population":0,
    "gn:timezone":"Asia/Kolkata",
    "iso:country":"IN",
    "wof:name":"Karadahalli",
    "wof:placetype":"locality"
},
  "geometry": {"coordinates":[76.72530999999999,12.91854],"type":"Point"}
}