{
  "type": "Feature",
  "properties": {
    "iso:country":"IN",
    "ks:ks_alt_nam":"Kolur RC",
    "ks:ks_name":"Kolur Rc",
    "ks:ks_pop":1890,
    "ks:ks_type":"HABITATION",
    "name:eng_x_preferred":[
        "Kolur Rc"
    ],
    "wof:name":"Kolur Rc",
    "wof:placetype":"locality",
    "wof:population":1890
},
  "geometry": {"coordinates":[75.424359,16.491749],"type":"Point"}
}