{
  "type": "Feature",
  "properties": {
    "gn:admin1_code":"35",
    "gn:admin2_code":"458.0",
    "gn:asciiname":"Pali",
    "gn:country_code":"IN",
    "gn:dem":492,
    "gn:feature_class":"P",
    "gn:feature_code":"PPL",
    "gn:name":"P\u0101li",
    "gn:population":0,
    "gn:timezone":"Asia/Kolkata",
    "iso:country":"IN",
    "wof:name":"Pali",
    "wof:placetype":"locality"
},
  "geometry": {"coordinates":[77.43473,24.4896],"type":"Point"}
}