{
  "type": "Feature",
  "properties": {
    "gn:admin1_code":"39.0",
    "gn:admin2_code":"64.0",
    "gn:asciiname":"Bhati",
    "gn:country_code":"IN",
    "gn:dem":1425,
    "gn:feature_class":"P",
    "gn:feature_code":"PPL",
    "gn:name":"Bh\u0101ti",
    "gn:population":0,
    "gn:timezone":"Asia/Kolkata",
    "iso:country":"IN",
    "name:ben_x_preferred":[
        "\u09ad\u09be\u099f\u09bf"
    ],
    "name:bpy_x_preferred":[
        "\u09ad\u09be\u099f\u09bf"
    ],
    "name:cat_x_preferred":[
        "Bhatti"
    ],
    "name:guj_x_preferred":[
        "\u0aad\u0abe\u0a9f\u0acd\u0a9f\u0ac0"
    ],
    "name:hin_x_preferred":[
        "\u092d\u093e\u091f\u0940"
    ],
    "name:lit_x_preferred":[
        "Bha\u010diai"
    ],
    "name:msa_x_preferred":[
        "Bhati"
    ],
    "name:new_x_preferred":[
        "\u092d\u0924\u093f"
    ],
    "name:urd_x_preferred":[
        "\u0628\u06be\u0679\u06cc"
    ],
    "name:vie_x_preferred":[
        "Bhati"
    ],
    "wof:name":"Bhati",
    "wof:placetype":"locality"
},
  "geometry": {"coordinates":[79.17834000000001,29.82908],"type":"Point"}
}