{
  "type": "Feature",
  "properties": {
    "iso:country":"IN",
    "ks:ks_name":"Rajit Purwa",
    "ks:ks_pop":64,
    "ks:ks_type":"HABITATION",
    "ks:ks_uagg_main":0,
    "name:eng_x_preferred":[
        "Rajit Purwa"
    ],
    "wof:name":"Rajit Purwa",
    "wof:placetype":"neighbourhood",
    "wof:population":64
},
  "geometry": {"coordinates":[81.90249900000001,27.556194],"type":"Point"}
}