{
  "type": "Feature",
  "properties": {
    "gn:country":"IN",
    "gn:fcode":"PPL",
    "gn:pop":4011,
    "iso:country":"IN",
    "name:bul_x_preferred":[
        "\u041c\u0435\u043b\u0443\u043a\u043e\u0442\u0435"
    ],
    "name:cat_x_preferred":[
        "Melukote"
    ],
    "name:ces_x_preferred":[
        "Melukote"
    ],
    "name:eng_x_preferred":[
        "Melukote"
    ],
    "name:hin_x_preferred":[
        "\u092e\u0947\u0932\u0915\u094b\u091f"
    ],
    "name:kan_x_preferred":[
        "\u0cae\u0cc7\u0cb2\u0cc1\u0c95\u0ccb\u0c9f\u0cc6"
    ],
    "name:nld_x_preferred":[
        "Melukote"
    ],
    "name:rus_x_preferred":[
        "\u041c\u0435\u043b\u0443\u043a\u043e\u0442\u0435"
    ],
    "name:san_x_preferred":[
        "\u092e\u0947\u0932\u0941\u0915\u094b\u091f\u0947"
    ],
    "name:swe_x_preferred":[
        "Melukote"
    ],
    "name:tam_x_preferred":[
        "\u0bae\u0bc7\u0bb2\u0bcd\u0b95\u0bcb\u0b9f\u0bcd\u0b9f\u0bc8"
    ],
    "name:unk_x_variant":[
        "Melkote"
    ],
    "qs:name":"Melukote",
    "qs:name_adm0":"India",
    "qs:name_adm1":"Karnataka",
    "qs:photos":206,
    "qs:photos_1k":42,
    "qs:photos_9k":1,
    "qs:photos_9r":4,
    "qs:photos_all":206,
    "qs:photos_sr":4,
    "qs:placetype":"Town",
    "qs:pop_sr":"4",
    "wd:wordcount":2323,
    "wof:name":"Melukote",
    "wof:placetype":"locality",
    "wof:population":4011
},
  "geometry": {"coordinates":[76.64857000000001,12.66212],"type":"Point"}
}