{
  "type": "Feature",
  "properties": {
    "iso:country":"IN",
    "ks:ks_name":"Khiretirayat",
    "ks:ks_pop":139,
    "ks:ks_type":"HABITATION",
    "name:eng_x_preferred":[
        "Khiretirayat"
    ],
    "wof:name":"Khiretirayat",
    "wof:placetype":"locality",
    "wof:population":139
},
  "geometry": {"coordinates":[78.905719,22.33514],"type":"Point"}
}