{
  "type": "Feature",
  "properties": {
    "iso:country":"IN",
    "ks:ks_name":"Kaimari Pt.V",
    "ks:ks_pop":2458,
    "ks:ks_type":"VILLAGE",
    "name:eng_x_preferred":[
        "Kaimari Pt.V"
    ],
    "wof:name":"Kaimari Pt.V",
    "wof:placetype":"locality",
    "wof:population":2458
},
  "geometry": {"coordinates":[89.835249,26.28312],"type":"Point"}
}