{
  "type": "Feature",
  "properties": {
    "gn:admin1_code":"16",
    "gn:admin2_code":"503.0",
    "gn:asciiname":"Kulangna Khurd",
    "gn:country_code":"IN",
    "gn:dem":616,
    "gn:feature_class":"P",
    "gn:feature_code":"PPL",
    "gn:name":"Kulangna Khurd",
    "gn:population":0,
    "gn:timezone":"Asia/Kolkata",
    "iso:country":"IN",
    "wof:name":"Kulangna Khurd",
    "wof:placetype":"locality"
},
  "geometry": {"coordinates":[77.31609,21.35003],"type":"Point"}
}