{
  "type": "Feature",
  "properties": {
    "iso:country":"IN",
    "ks:ks_name":"Saidol",
    "ks:ks_pop":100,
    "ks:ks_type":"VILLAGE",
    "name:eng_x_preferred":[
        "Saidol"
    ],
    "wof:name":"Saidol",
    "wof:placetype":"locality",
    "wof:population":100
},
  "geometry": {"coordinates":[81.802964,23.852873],"type":"Point"}
}