{
  "type": "Feature",
  "properties": {
    "iso:country":"IN",
    "ks:ks_name":"Kusumdih",
    "ks:ks_pop":105,
    "ks:ks_type":"VILLAGE",
    "name:eng_x_preferred":[
        "Kusumdih"
    ],
    "wof:name":"Kusumdih",
    "wof:placetype":"locality",
    "wof:population":105
},
  "geometry": {"coordinates":[87.05932199999999,24.217034],"type":"Point"}
}