{
  "type": "Feature",
  "properties": {
    "iso:country":"IN",
    "ks:ks_name":"Khajoosar",
    "ks:ks_pop":513,
    "ks:ks_type":"HABITATION",
    "name:eng_x_preferred":[
        "Khajoosar"
    ],
    "wof:name":"Khajoosar",
    "wof:placetype":"locality",
    "wof:population":513
},
  "geometry": {"coordinates":[72.807586,27.369414],"type":"Point"}
}