{
  "type": "Feature",
  "properties": {
    "gn:admin1_code":"36",
    "gn:admin2_code":"179.0",
    "gn:asciiname":"Bihari",
    "gn:country_code":"IN",
    "gn:dem":99,
    "gn:feature_class":"P",
    "gn:feature_code":"PPL",
    "gn:name":"Bih\u0101ri",
    "gn:population":0,
    "gn:timezone":"Asia/Kolkata",
    "iso:country":"IN",
    "name:ben_x_preferred":[
        "\u09ac\u09bf\u09b9\u09be\u09b0\u09c0"
    ],
    "name:deu_x_preferred":[
        "Bihari"
    ],
    "name:fas_x_preferred":[
        "\u0628\u06cc\u0647\u0627\u0631\u06cc"
    ],
    "name:ind_x_preferred":[
        "Bihari"
    ],
    "name:nld_x_preferred":[
        "Bihari"
    ],
    "name:rus_x_preferred":[
        "\u0411\u0438\u0445\u0430\u0440\u0438"
    ],
    "wof:name":"Bihari",
    "wof:placetype":"neighbourhood"
},
  "geometry": {"coordinates":[82.09738,26.08309],"type":"Point"}
}