{
  "type": "Feature",
  "properties": {
    "iso:country":"IN",
    "ks:ks_name":"Khanderi",
    "ks:ks_pop":495,
    "ks:ks_type":"HABITATION",
    "name:eng_x_preferred":[
        "Khanderi"
    ],
    "wof:name":"Khanderi",
    "wof:placetype":"locality",
    "wof:population":495
},
  "geometry": {"coordinates":[72.81291299999999,18.703982],"type":"Point"}
}