{
  "type": "Feature",
  "properties": {
    "iso:country":"IN",
    "ks:ks_name":"Gargari",
    "ks:ks_pop":253,
    "ks:ks_type":"VILLAGE",
    "name:eng_x_preferred":[
        "Gargari"
    ],
    "wof:name":"Gargari",
    "wof:placetype":"locality",
    "wof:population":253
},
  "geometry": {"coordinates":[87.475683,24.997485],"type":"Point"}
}