{
  "type": "Feature",
  "properties": {
    "iso:country":"IN",
    "ks:ks_name":"Chandar",
    "ks:ks_pop":58,
    "ks:ks_type":"VILLAGE",
    "name:eng_x_preferred":[
        "Chandar"
    ],
    "wof:name":"Chandar",
    "wof:placetype":"locality",
    "wof:population":58
},
  "geometry": {"coordinates":[73.518086,18.287686],"type":"Point"}
}