{
  "type": "Feature",
  "properties": {
    "gn:admin1_code":"37",
    "gn:admin2_code":"409.0",
    "gn:asciiname":"Kunjamtola",
    "gn:country_code":"IN",
    "gn:dem":421,
    "gn:feature_class":"P",
    "gn:feature_code":"PPL",
    "gn:name":"Kunj\u0101mtola",
    "gn:population":0,
    "gn:timezone":"Asia/Kolkata",
    "iso:country":"IN",
    "ks:ks_name":"Kunjamtola",
    "ks:ks_pop":257,
    "ks:ks_type":"HABITATION",
    "name:eng_x_preferred":[
        "Kunjamtola"
    ],
    "wof:name":"Kunjamtola",
    "wof:placetype":"locality",
    "wof:population":257
},
  "geometry": {"coordinates":[81.062676,20.599736],"type":"Point"}
}