{
  "type": "Feature",
  "properties": {
    "iso:country":"IN",
    "ks:ks_name":"Arjunpur",
    "ks:ks_pop":1779,
    "ks:ks_type":"VILLAGE",
    "ks:ks_uagg_main":0,
    "name:eng_x_preferred":[
        "Arjunpur"
    ],
    "name:hin_x_preferred":[
        "\u0905\u0930\u094d\u091c\u0941\u0928\u092a\u0941\u0930"
    ],
    "wof:name":"Arjunpur",
    "wof:placetype":"neighbourhood",
    "wof:population":1779
},
  "geometry": {"coordinates":[87.725966,24.7701],"type":"Point"}
}