{
  "type": "Feature",
  "properties": {
    "gn:admin1_code":"40",
    "gn:admin2_code":"535.0",
    "gn:asciiname":"Siwampet",
    "gn:country_code":"IN",
    "gn:dem":572,
    "gn:feature_class":"P",
    "gn:feature_code":"PPL",
    "gn:name":"Siwampet",
    "gn:population":0,
    "gn:timezone":"Asia/Kolkata",
    "iso:country":"IN",
    "name:und_x_variant":[
        "Sivampet",
        "Siwampet"
    ],
    "wof:name":"Siwampet",
    "wof:placetype":"neighbourhood"
},
  "geometry": {"coordinates":[78.37035,17.78848],"type":"Point"}
}