{
  "type": "Feature",
  "properties": {
    "iso:country":"IN",
    "ks:ks_name":"Pathar Amarpur",
    "ks:ks_pop":110,
    "ks:ks_type":"VILLAGE",
    "name:eng_x_preferred":[
        "Pathar Amarpur"
    ],
    "wof:name":"Pathar Amarpur",
    "wof:placetype":"locality",
    "wof:population":110
},
  "geometry": {"coordinates":[88.234739,25.014511],"type":"Point"}
}