{
  "type": "Feature",
  "properties": {
    "gn:admin1_code":"2.0",
    "gn:admin2_code":"550.0",
    "gn:asciiname":"Venkannapalemkhandrika",
    "gn:country_code":"IN",
    "gn:dem":15,
    "gn:feature_class":"P",
    "gn:feature_code":"PPL",
    "gn:name":"Venkann\u0101p\u0101lemkhandrika",
    "gn:population":0,
    "gn:timezone":"Asia/Kolkata",
    "iso:country":"IN",
    "wof:name":"Venkannapalemkhandrika",
    "wof:placetype":"locality"
},
  "geometry": {"coordinates":[80.05195000000001,14.02543],"type":"Point"}
}