{
  "type": "Feature",
  "properties": {
    "gn:country":"IN",
    "gn:fcode":"PPL",
    "gn:pop":76082,
    "iso:country":"IN",
    "name:ben_x_preferred":[
        "\u0995\u09cb\u09a8\u09cd\u09a8\u0997\u09b0"
    ],
    "name:bpy_x_preferred":[
        "\u0995\u09cb\u09a8\u09cd\u09a8\u0997\u09b0"
    ],
    "name:bul_x_preferred":[
        "\u041a\u043e\u043d\u0430\u0433\u0430\u0440"
    ],
    "name:eng_x_preferred":[
        "Konnagar"
    ],
    "name:fra_x_preferred":[
        "Konnagar"
    ],
    "name:hif_x_preferred":[
        "Konnagar"
    ],
    "name:ind_x_preferred":[
        "Konnagar"
    ],
    "name:ita_x_preferred":[
        "Konnagar"
    ],
    "name:msa_x_preferred":[
        "Konnagar"
    ],
    "name:new_x_preferred":[
        "\u0915\u094b\u0928\u094d\u0928\u0917\u0930"
    ],
    "name:nld_x_preferred":[
        "Konnagar"
    ],
    "name:por_x_preferred":[
        "Konnagar"
    ],
    "name:spa_x_preferred":[
        "Konnagar"
    ],
    "name:swe_x_preferred":[
        "Konnagar"
    ],
    "name:unk_x_variant":[
        "Konnagar"
    ],
    "name:vie_x_preferred":[
        "Konnagar"
    ],
    "name:zho_x_preferred":[
        "\u79d1\u7eb3\u52a0\u5c14"
    ],
    "qs:name":"Konanagar",
    "qs:name_adm0":"India",
    "qs:name_adm1":"West Bengal",
    "qs:photos_9r":0,
    "qs:photos_sr":0,
    "qs:placetype":"Town",
    "qs:pop_sr":"8",
    "wof:name":"Konanagar",
    "wof:placetype":"locality",
    "wof:population":76082
},
  "geometry": {"coordinates":[88.34446,22.70508],"type":"Point"}
}