{
  "type": "Feature",
  "properties": {
    "iso:country":"IN",
    "ks:ks_name":"Hospetebail",
    "ks:ks_pop":46,
    "ks:ks_type":"HABITATION",
    "name:eng_x_preferred":[
        "Hospetebail"
    ],
    "wof:name":"Hospetebail",
    "wof:placetype":"locality",
    "wof:population":46
},
  "geometry": {"coordinates":[74.76667500000001,14.469812],"type":"Point"}
}