{
  "type": "Feature",
  "properties": {
    "iso:country":"IN",
    "ks:ks_name":"Dalsalap",
    "ks:ks_pop":1710,
    "ks:ks_type":"VILLAGE",
    "ks:ks_uagg_main":0,
    "name:eng_x_preferred":[
        "Dalsalap"
    ],
    "wof:name":"Dalsalap",
    "wof:placetype":"locality",
    "wof:population":1710
},
  "geometry": {"coordinates":[88.053578,22.449637],"type":"Point"}
}