{
  "type": "Feature",
  "properties": {
    "iso:country":"IN",
    "ks:ks_name":"Gungunpada",
    "ks:ks_pop":276,
    "ks:ks_type":"HABITATION",
    "name:eng_x_preferred":[
        "Gungunpada"
    ],
    "wof:name":"Gungunpada",
    "wof:placetype":"locality",
    "wof:population":276
},
  "geometry": {"coordinates":[73.07865200000001,19.730287],"type":"Point"}
}