{
  "type": "Feature",
  "properties": {
    "iso:country":"IN",
    "ks:ks_name":"Amarpur",
    "ks:ks_pop":370,
    "ks:ks_type":"VILLAGE",
    "ks:ks_uagg_main":0,
    "name:eng_x_preferred":[
        "Amarpur"
    ],
    "wof:name":"Amarpur",
    "wof:placetype":"neighbourhood",
    "wof:population":370
},
  "geometry": {"coordinates":[77.642405,23.834334],"type":"Point"}
}