{
  "type": "Feature",
  "properties": {
    "gn:admin1_code":"36",
    "gn:admin2_code":"180.0",
    "gn:asciiname":"Kothi Jadunath Bakhsh",
    "gn:country_code":"IN",
    "gn:dem":119,
    "gn:feature_class":"P",
    "gn:feature_code":"PPL",
    "gn:name":"Kothi Jadun\u0101th Bakhsh",
    "gn:population":0,
    "gn:timezone":"Asia/Kolkata",
    "iso:country":"IN",
    "wof:name":"Kothi Jadunath Bakhsh",
    "wof:placetype":"locality"
},
  "geometry": {"coordinates":[81.66083,27.46999000000001],"type":"Point"}
}