{
  "type": "Feature",
  "properties": {
    "iso:country":"IN",
    "ks:ks_alt_nam":"Th\u0101pkhera",
    "ks:ks_name":"Thapkhera",
    "ks:ks_pop":1524,
    "ks:ks_type":"VILLAGE",
    "name:eng_x_preferred":[
        "Thapkhera"
    ],
    "name:eng_x_variant":[
        "Th\u0101pkhera"
    ],
    "wof:name":"Thapkhera",
    "wof:placetype":"neighbourhood",
    "wof:population":1524
},
  "geometry": {"coordinates":[77.55363199999999,28.50719],"type":"Point"}
}