{
  "type": "Feature",
  "properties": {
    "iso:country":"IN",
    "ks:ks_name":"Pura Budha",
    "ks:ks_pop":459,
    "ks:ks_type":"HABITATION",
    "name:eng_x_preferred":[
        "Pura Budha"
    ],
    "wof:name":"Pura Budha",
    "wof:placetype":"locality",
    "wof:population":459
},
  "geometry": {"coordinates":[81.635975,26.538509],"type":"Point"}
}