{
  "type": "Feature",
  "properties": {
    "iso:country":"IN",
    "ks:ks_name":"Swaminarayan Patel F",
    "ks:ks_pop":1010,
    "ks:ks_type":"HABITATION",
    "name:eng_x_preferred":[
        "Swaminarayan Patel F"
    ],
    "wof:name":"Swaminarayan Patel F",
    "wof:placetype":"locality",
    "wof:population":1010
},
  "geometry": {"coordinates":[73.7052,22.832167],"type":"Point"}
}