{
  "type": "Feature",
  "properties": {
    "iso:country":"IN",
    "ks:ks_name":"Rajula Pollanki",
    "ks:ks_pop":200,
    "ks:ks_type":"HABITATION",
    "name:eng_x_preferred":[
        "Rajula Pollanki"
    ],
    "wof:name":"Rajula Pollanki",
    "wof:placetype":"locality",
    "wof:population":200
},
  "geometry": {"coordinates":[83.267893,18.130009],"type":"Point"}
}