{
  "type": "Feature",
  "properties": {
    "iso:country":"IN",
    "ks:ks_name":"Beedipalke",
    "ks:ks_pop":137,
    "ks:ks_type":"HABITATION",
    "ks:ks_uagg_main":0,
    "name:eng_x_preferred":[
        "Beedipalke"
    ],
    "wof:name":"Beedipalke",
    "wof:placetype":"neighbourhood",
    "wof:population":137
},
  "geometry": {"coordinates":[75.072821,12.899636],"type":"Point"}
}