{
  "type": "Feature",
  "properties": {
    "gn:admin1_code":"25.0",
    "gn:admin2_code":"611.0",
    "gn:asciiname":"Iruppukallu",
    "gn:country_code":"IN",
    "gn:dem":1756,
    "gn:feature_class":"P",
    "gn:feature_code":"PPL",
    "gn:name":"Iruppukallu",
    "gn:population":0,
    "gn:timezone":"Asia/Kolkata",
    "iso:country":"IN",
    "wof:name":"Iruppukallu",
    "wof:placetype":"locality"
},
  "geometry": {"coordinates":[76.84097,11.41239],"type":"Point"}
}