{
  "type": "Feature",
  "properties": {
    "iso:country":"IN",
    "ks:ks_alt_nam":"\u0100m\u0101n\u0101la",
    "ks:ks_name":"Amanala",
    "ks:ks_type":"VILLAGE",
    "ks:ks_uagg_main":0,
    "name:eng_x_preferred":[
        "Amanala"
    ],
    "name:eng_x_variant":[
        "\u0100m\u0101n\u0101la"
    ],
    "wof:name":"Amanala",
    "wof:placetype":"neighbourhood"
},
  "geometry": {"coordinates":[80.05261900000001,23.166702],"type":"Point"}
}