{
  "type": "Feature",
  "properties": {
    "iso:country":"IN",
    "ks:ks_name":"Rangoli Bon Gaon",
    "ks:ks_pop":352,
    "ks:ks_type":"HABITATION",
    "name:eng_x_preferred":[
        "Rangoli Bon Gaon"
    ],
    "wof:name":"Rangoli Bon Gaon",
    "wof:placetype":"locality",
    "wof:population":352
},
  "geometry": {"coordinates":[94.965819,27.110591],"type":"Point"}
}