{
  "type": "Feature",
  "properties": {
    "gn:admin1_code":"11",
    "gn:admin2_code":"23.0",
    "gn:asciiname":"Dugror",
    "gn:country_code":"IN",
    "gn:dem":1878,
    "gn:feature_class":"P",
    "gn:feature_code":"PPL",
    "gn:name":"Dugror",
    "gn:population":0,
    "gn:timezone":"Asia/Kolkata",
    "iso:country":"IN",
    "wof:name":"Dugror",
    "wof:placetype":"locality"
},
  "geometry": {"coordinates":[76.02474000000002,32.46544],"type":"Point"}
}