{
  "type": "Feature",
  "properties": {
    "gn:admin1_code":"25.0",
    "gn:admin2_code":"607.0",
    "gn:asciiname":"Pallipattu",
    "gn:country_code":"IN",
    "gn:dem":91,
    "gn:feature_class":"P",
    "gn:feature_code":"PPL",
    "gn:name":"Pallipattu",
    "gn:population":0,
    "gn:timezone":"Asia/Kolkata",
    "iso:country":"IN",
    "name:bpy_x_preferred":[
        "\u09aa\u09b2\u09cd\u09b2\u09bf\u09aa\u09be\u09a4\u09cd\u09a4\u09c1"
    ],
    "name:ceb_x_preferred":[
        "Pallipattu"
    ],
    "name:deu_x_preferred":[
        "Pallipattu"
    ],
    "name:ita_x_preferred":[
        "Pallipattu"
    ],
    "name:msa_x_preferred":[
        "Pallipattu"
    ],
    "name:nld_x_preferred":[
        "Pallipattu"
    ],
    "name:por_x_preferred":[
        "Pallipattu"
    ],
    "name:swe_x_preferred":[
        "Pallipattu"
    ],
    "name:tam_x_preferred":[
        "\u0baa\u0bb3\u0bcd\u0bb3\u0bbf\u0baa\u0bcd\u0baa\u0b9f\u0bcd\u0b9f\u0bc1"
    ],
    "name:tel_x_preferred":[
        "\u0c2a\u0c33\u0c4d\u0c33\u0c3f\u0c2a\u0c1f\u0c4d\u0c1f\u0c41"
    ],
    "name:vie_x_preferred":[
        "Pallipattu"
    ],
    "name:zho_x_preferred":[
        "\u5e15\u5229\u5e15\u56fe"
    ],
    "wof:name":"Pallipattu",
    "wof:placetype":"neighbourhood"
},
  "geometry": {"coordinates":[79.42587,12.21628],"type":"Point"}
}