{
  "type": "Feature",
  "properties": {
    "iso:country":"IN",
    "ks:ks_name":"Bakhar Chandiha",
    "ks:ks_pop":5959,
    "ks:ks_type":"VILLAGE",
    "name:eng_x_preferred":[
        "Bakhar Chandiha"
    ],
    "wof:name":"Bakhar Chandiha",
    "wof:placetype":"locality",
    "wof:population":5959
},
  "geometry": {"coordinates":[85.327291,26.654083],"type":"Point"}
}