{
  "type": "Feature",
  "properties": {
    "iso:country":"IN",
    "ks:ks_alt_nam":"Kusumbh\u0101i",
    "ks:ks_name":"Kusumbhai",
    "ks:ks_pop":1072,
    "ks:ks_type":"VILLAGE",
    "ks:ks_uagg_main":0,
    "name:eng_x_preferred":[
        "Kusumbhai"
    ],
    "name:eng_x_variant":[
        "Kusumbh\u0101i"
    ],
    "wof:name":"Kusumbhai",
    "wof:placetype":"neighbourhood",
    "wof:population":1072
},
  "geometry": {"coordinates":[85.875185,24.391793],"type":"Point"}
}