{
  "type": "Feature",
  "properties": {
    "gn:admin1_code":"36",
    "gn:admin2_code":"198.0",
    "gn:asciiname":"Saranwan",
    "gn:country_code":"IN",
    "gn:dem":88,
    "gn:feature_class":"P",
    "gn:feature_code":"PPL",
    "gn:name":"Sar\u0101nw\u0101n",
    "gn:population":0,
    "gn:timezone":"Asia/Kolkata",
    "iso:country":"IN",
    "ks:ks_alt_nam":"Sar\u0101nw\u0101n",
    "ks:ks_name":"Saranwan",
    "ks:ks_type":"VILLAGE",
    "ks:ks_uagg_main":0,
    "name:eng_x_preferred":[
        "Saranwan"
    ],
    "name:eng_x_variant":[
        "Sar\u0101nw\u0101n"
    ],
    "wof:name":"Saranwan",
    "wof:placetype":"neighbourhood"
},
  "geometry": {"coordinates":[82.370938,25.370751],"type":"Point"}
}