{
  "type": "Feature",
  "properties": {
    "iso:country":"IN",
    "ks:ks_name":"Polamguda",
    "ks:ks_pop":44,
    "ks:ks_type":"HABITATION",
    "name:eng_x_preferred":[
        "Polamguda"
    ],
    "wof:name":"Polamguda",
    "wof:placetype":"locality",
    "wof:population":44
},
  "geometry": {"coordinates":[83.85624,18.715679],"type":"Point"}
}