{
  "type": "Feature",
  "properties": {
    "iso:country":"IN",
    "ks:ks_name":"Madhupur",
    "ks:ks_pop":4179,
    "ks:ks_type":"VILLAGE",
    "ks:ks_uagg_main":0,
    "name:eng_x_preferred":[
        "Madhupur"
    ],
    "wof:name":"Madhupur",
    "wof:placetype":"locality",
    "wof:population":4179
},
  "geometry": {"coordinates":[91.260874,23.769161],"type":"Point"}
}