{
  "type": "Feature",
  "properties": {
    "gn:admin1_code":"36",
    "gn:admin2_code":"170.0",
    "gn:asciiname":"Udaipur Bhusasi",
    "gn:country_code":"IN",
    "gn:dem":125,
    "gn:feature_class":"P",
    "gn:feature_code":"PPL",
    "gn:name":"Udaipur Bhus\u0101si",
    "gn:population":0,
    "gn:timezone":"Asia/Kolkata",
    "iso:country":"IN",
    "wof:name":"Udaipur Bhusasi",
    "wof:placetype":"neighbourhood"
},
  "geometry": {"coordinates":[80.67028999999999,25.26237],"type":"Point"}
}