{
  "type": "Feature",
  "properties": {
    "iso:country":"IN",
    "ks:ks_name":"Attukadavu",
    "ks:ks_pop":298,
    "ks:ks_type":"HABITATION",
    "name:eng_x_preferred":[
        "Attukadavu"
    ],
    "wof:name":"Attukadavu",
    "wof:placetype":"neighbourhood",
    "wof:population":298
},
  "geometry": {"coordinates":[76.872207,8.898659],"type":"Point"}
}