{
  "type": "Feature",
  "properties": {
    "iso:country":"IN",
    "ks:ks_name":"Khairipada",
    "ks:ks_pop":159,
    "ks:ks_type":"HABITATION",
    "name:eng_x_preferred":[
        "Khairipada"
    ],
    "wof:name":"Khairipada",
    "wof:placetype":"locality",
    "wof:population":159
},
  "geometry": {"coordinates":[72.99621500000001,19.610412],"type":"Point"}
}