{
  "type": "Feature",
  "properties": {
    "iso:country":"IN",
    "ks:ks_name":"Cheelanahalli",
    "ks:ks_pop":750,
    "ks:ks_type":"HABITATION",
    "name:eng_x_preferred":[
        "Cheelanahalli"
    ],
    "wof:name":"Cheelanahalli",
    "wof:placetype":"locality",
    "wof:population":750
},
  "geometry": {"coordinates":[76.269961,13.200547],"type":"Point"}
}