{
  "type": "Feature",
  "properties": {
    "iso:country":"IN",
    "ks:ks_alt_nam":"channaiahnahatty",
    "ks:ks_name":"Channaiahnahatty",
    "ks:ks_pop":499,
    "ks:ks_type":"HABITATION",
    "name:eng_x_preferred":[
        "Channaiahnahatty"
    ],
    "wof:name":"Channaiahnahatty",
    "wof:placetype":"locality",
    "wof:population":499
},
  "geometry": {"coordinates":[76.336521,14.270543],"type":"Point"}
}