{
  "type": "Feature",
  "properties": {
    "gn:admin1_code":"35.0",
    "gn:admin2_code":"450.0",
    "gn:asciiname":"Nigai",
    "gn:country_code":"IN",
    "gn:dem":435,
    "gn:feature_class":"P",
    "gn:feature_code":"PPL",
    "gn:name":"Nigai",
    "gn:population":0,
    "gn:timezone":"Asia/Kolkata",
    "iso:country":"IN",
    "ks:ks_name":"Naigai",
    "ks:ks_pop":1504,
    "ks:ks_type":"VILLAGE",
    "ks:ks_uagg_main":0,
    "name:eng_x_preferred":[
        "Naigai"
    ],
    "wof:name":"Naigai",
    "wof:placetype":"neighbourhood",
    "wof:population":1504
},
  "geometry": {"coordinates":[80.382561,23.350824],"type":"Point"}
}