{
  "type": "Feature",
  "properties": {
    "iso:country":"IN",
    "ks:ks_name":"Gollalapalem",
    "ks:ks_pop":779,
    "ks:ks_type":"HABITATION",
    "name:eng_x_preferred":[
        "Gollalapalem"
    ],
    "wof:name":"Gollalapalem",
    "wof:placetype":"locality",
    "wof:population":779
},
  "geometry": {"coordinates":[83.29589199999999,17.962991],"type":"Point"}
}