{
  "type": "Feature",
  "properties": {
    "iso:country":"IN",
    "ks:ks_name":"Jaynagar",
    "ks:ks_pop":20,
    "ks:ks_type":"VILLAGE",
    "name:eng_x_preferred":[
        "Jaynagar"
    ],
    "wof:name":"Jaynagar",
    "wof:placetype":"locality",
    "wof:population":20
},
  "geometry": {"coordinates":[87.26266699999999,22.558711],"type":"Point"}
}