{
  "type": "Feature",
  "properties": {
    "gn:admin1_code":"34.0",
    "gn:admin2_code":"215.0",
    "gn:asciiname":"Kharari",
    "gn:country_code":"IN",
    "gn:dem":52,
    "gn:feature_class":"P",
    "gn:feature_code":"PPL",
    "gn:name":"Khar\u0101ri",
    "gn:population":0,
    "gn:timezone":"Asia/Kolkata",
    "iso:country":"IN",
    "ks:ks_alt_nam":"Khar\u0101ri",
    "ks:ks_name":"Kharari",
    "ks:ks_pop":2289,
    "ks:ks_type":"VILLAGE",
    "ks:ks_uagg_main":0,
    "name:eng_x_preferred":[
        "Kharari"
    ],
    "name:eng_x_variant":[
        "Khar\u0101ri"
    ],
    "wof:name":"Kharari",
    "wof:placetype":"neighbourhood",
    "wof:population":2289
},
  "geometry": {"coordinates":[85.99939000000001,25.93826],"type":"Point"}
}