{
  "type": "Feature",
  "properties": {
    "gn:country":"IN",
    "gn:fcode":"PPLX",
    "gn:population":0,
    "iso:country":"IN",
    "name:ara_x_preferred":[
        "\u0645\u0648\u062a\u064a\u0643\u0627\u0646\u062c"
    ],
    "name:ben_bn_x_preferred":[
        "\u09ae\u09c1\u09a0\u09bf\u0997\u099e\u09cd\u099c"
    ],
    "name:ben_in_x_preferred":[
        "\u09ae\u09c1\u09a0\u09bf\u0997\u099e\u09cd\u099c"
    ],
    "name:guj_x_preferred":[
        "\u0aae\u0ac1\u0aa0\u0ac0\u0a97\u0a82\u0a9c"
    ],
    "name:hin_x_preferred":[
        "\u092e\u0941\u0925\u093f\u0917\u0902\u091c"
    ],
    "name:kan_x_preferred":[
        "\u0cae\u0cc1\u0ca4\u0cbf\u0c97\u0c82\u0c9c\u0ccd"
    ],
    "name:mal_x_preferred":[
        "\u0d2e\u0d41\u0d24\u0d4d\u0d24\u0d3f\u0d17\u0d1e\u0d4d\u0d1a\u0d4d"
    ],
    "name:mar_x_preferred":[
        "\u092e\u0941\u0925\u0940\u0917\u0902\u091c"
    ],
    "name:pan_x_preferred":[
        "\u0a2e\u0a41\u0a20\u0a40\u0a17\u0a2e\u0a1c"
    ],
    "name:tam_x_preferred":[
        "\u0bae\u0bc1\u0ba4\u0bbf\u0b95\u0b9e\u0bcd\u0b9a\u0bcd"
    ],
    "name:tel_x_preferred":[
        "\u0c2e\u0c41\u0c25\u0c3f\u0c17\u0c02\u0c1c\u0c4d"
    ],
    "name:und_x_variant":[
        "Mutthiganj"
    ],
    "name:urd_x_preferred":[
        "\u0645\u0679\u06be\u06cc\u0627 \u06af\u0646\u062c"
    ],
    "qs:name":"Muthiganj",
    "qs:name_adm0":"India",
    "qs:name_adm1":"Uttar Pradesh",
    "qs:photos":1,
    "qs:photos_1k":1,
    "qs:photos_9k":1,
    "qs:photos_9r":1,
    "qs:photos_all":1,
    "qs:photos_sr":1,
    "qs:placetype":"Suburb",
    "qs:pop_sr":"0",
    "wof:name":"Muthiganj",
    "wof:placetype":"neighbourhood",
    "wof:population":0
},
  "geometry": {"coordinates":[81.84117999999999,25.43392],"type":"Point"}
}