{
  "type": "Feature",
  "properties": {
    "gn:admin1_code":"36",
    "gn:admin2_code":"201.0",
    "gn:asciiname":"Sadhera",
    "gn:country_code":"IN",
    "gn:dem":159,
    "gn:feature_class":"P",
    "gn:feature_code":"PPL",
    "gn:name":"Sadher\u0101",
    "gn:population":0,
    "gn:timezone":"Asia/Kolkata",
    "iso:country":"IN",
    "ks:ks_name":"Sadhera",
    "ks:ks_pop":463,
    "ks:ks_type":"VILLAGE",
    "name:eng_x_preferred":[
        "Sadhera"
    ],
    "wof:name":"Sadhera",
    "wof:placetype":"locality",
    "wof:population":463
},
  "geometry": {"coordinates":[79.145579,27.47575],"type":"Point"}
}