{
  "type": "Feature",
  "properties": {
    "gn:admin1_code":"24.0",
    "gn:admin2_code":"130.0",
    "gn:asciiname":"Ghagri",
    "gn:country_code":"IN",
    "gn:dem":360,
    "gn:feature_class":"P",
    "gn:feature_code":"PPL",
    "gn:name":"Gh\u0101gri",
    "gn:population":0,
    "gn:timezone":"Asia/Kolkata",
    "iso:country":"IN",
    "ks:ks_name":"Ghaghri",
    "ks:ks_pop":520,
    "ks:ks_type":"VILLAGE",
    "name:eng_x_preferred":[
        "Ghaghri"
    ],
    "name:eng_x_variant":[
        "Ghagri"
    ],
    "wof:name":"Ghaghri",
    "wof:placetype":"locality",
    "wof:population":520
},
  "geometry": {"coordinates":[74.16603600000001,24.163678],"type":"Point"}
}