{
  "type": "Feature",
  "properties": {
    "gn:admin1_code":"19.0",
    "gn:admin2_code":"568.0",
    "gn:asciiname":"Lakkavalli",
    "gn:country_code":"IN",
    "gn:dem":559,
    "gn:feature_class":"P",
    "gn:feature_code":"PPL",
    "gn:name":"Lakkavalli",
    "gn:population":0,
    "gn:timezone":"Asia/Kolkata",
    "iso:country":"IN",
    "name:kan_x_preferred":[
        "\u0cb2\u0c95\u0ccd\u0c95\u0cb5\u0cb3\u0ccd\u0cb3\u0cbf"
    ],
    "name:urd_x_preferred":[
        "\u0644\u0627\u06a9\u0627\u0648\u0627\u0644\u06cc"
    ],
    "wof:name":"Lakkavalli",
    "wof:placetype":"locality"
},
  "geometry": {"coordinates":[75.10793000000002,14.58448],"type":"Point"}
}