{
  "type": "Feature",
  "properties": {
    "gn:admin1_code":"2",
    "gn:admin2_code":"544.0",
    "gn:asciiname":"Tirupatipalem",
    "gn:country_code":"IN",
    "gn:dem":86,
    "gn:feature_class":"P",
    "gn:feature_code":"PPL",
    "gn:name":"Tirupatip\u0101lem",
    "gn:population":0,
    "gn:timezone":"Asia/Kolkata",
    "iso:country":"IN",
    "ks:ks_name":"Tirupathipalem",
    "ks:ks_pop":245,
    "ks:ks_type":"HABITATION",
    "name:eng_x_preferred":[
        "Tirupathipalem"
    ],
    "name:eng_x_variant":[
        "Tirupatipalem"
    ],
    "wof:name":"Tirupathipalem",
    "wof:placetype":"locality",
    "wof:population":245
},
  "geometry": {"coordinates":[82.649844,17.462312],"type":"Point"}
}