{
  "type": "Feature",
  "properties": {
    "iso:country":"IN",
    "ks:ks_name":"Kot",
    "ks:ks_pop":561,
    "ks:ks_type":"VILLAGE",
    "name:eng_x_preferred":[
        "Kot"
    ],
    "wof:name":"Kot",
    "wof:placetype":"locality",
    "wof:population":561
},
  "geometry": {"coordinates":[73.285381,24.258128],"type":"Point"}
}