{
  "type": "Feature",
  "properties": {
    "iso:country":"IN",
    "ks:ks_name":"Udayasahi",
    "ks:ks_pop":123,
    "ks:ks_type":"VILLAGE",
    "name:eng_x_preferred":[
        "Udayasahi"
    ],
    "wof:name":"Udayasahi",
    "wof:placetype":"locality",
    "wof:population":123
},
  "geometry": {"coordinates":[85.966048,22.012792],"type":"Point"}
}