{
  "type": "Feature",
  "properties": {
    "gn:admin1_code":"30.0",
    "gn:admin2_code":"251",
    "gn:asciiname":"Komsing",
    "gn:country_code":"IN",
    "gn:dem":679,
    "gn:feature_class":"P",
    "gn:feature_code":"PPL",
    "gn:name":"Komsing",
    "gn:population":0,
    "gn:timezone":"Asia/Kolkata",
    "iso:country":"IN",
    "wof:name":"Komsing",
    "wof:placetype":"locality"
},
  "geometry": {"coordinates":[95.01595,28.26171],"type":"Point"}
}