{
  "type": "Feature",
  "properties": {
    "gn:admin1_code":"2.0",
    "gn:admin2_code":"553.0",
    "gn:asciiname":"Cheruvuvanipalle",
    "gn:country_code":"IN",
    "gn:dem":643,
    "gn:feature_class":"P",
    "gn:feature_code":"PPL",
    "gn:name":"Cheruvuv\u0101nipalle",
    "gn:population":0,
    "gn:timezone":"Asia/Kolkata",
    "iso:country":"IN",
    "wof:name":"Cheruvuvanipalle",
    "wof:placetype":"neighbourhood"
},
  "geometry": {"coordinates":[77.91818000000001,14.07737],"type":"Point"}
}