{
  "type": "Feature",
  "properties": {
    "iso:country":"IN",
    "ks:ks_name":"Chaq Hafiz Badruddin Urf Konar",
    "ks:ks_pop":1136,
    "ks:ks_type":"VILLAGE",
    "ks:ks_uagg_main":0,
    "name:eng_x_preferred":[
        "Chaq Hafiz Badruddin Urf Konar"
    ],
    "wof:name":"Chaq Hafiz Badruddin Urf Konar",
    "wof:placetype":"neighbourhood",
    "wof:population":1136
},
  "geometry": {"coordinates":[82.12434,25.630761],"type":"Point"}
}