{
  "type": "Feature",
  "properties": {
    "iso:country":"IN",
    "ks:ks_name":"Hatharakandi",
    "ks:ks_pop":87,
    "ks:ks_type":"HABITATION",
    "name:eng_x_preferred":[
        "Hatharakandi"
    ],
    "wof:name":"Hatharakandi",
    "wof:placetype":"locality",
    "wof:population":87
},
  "geometry": {"coordinates":[74.908922,13.752191],"type":"Point"}
}