{
  "type": "Feature",
  "properties": {
    "iso:country":"IN",
    "ks:ks_name":"Baharupara",
    "ks:ks_pop":638,
    "ks:ks_type":"HABITATION",
    "name:eng_x_preferred":[
        "Baharupara"
    ],
    "wof:name":"Baharupara",
    "wof:placetype":"locality",
    "wof:population":638
},
  "geometry": {"coordinates":[81.549694,19.206402],"type":"Point"}
}