{
  "type": "Feature",
  "properties": {
    "iso:country":"IN",
    "ks:ks_name":"Bhavani Falia",
    "ks:ks_pop":525,
    "ks:ks_type":"HABITATION",
    "name:eng_x_preferred":[
        "Bhavani Falia"
    ],
    "wof:name":"Bhavani Falia",
    "wof:placetype":"locality",
    "wof:population":525
},
  "geometry": {"coordinates":[73.068488,20.411692],"type":"Point"}
}