{
  "type": "Feature",
  "properties": {
    "iso:country":"IN",
    "ks:ks_alt_nam":"Bhitah\u0101",
    "ks:ks_name":"Bhitaha",
    "ks:ks_pop":1188,
    "ks:ks_type":"VILLAGE",
    "name:eng_x_preferred":[
        "Bhitaha"
    ],
    "name:eng_x_variant":[
        "Bhitah\u0101"
    ],
    "wof:name":"Bhitaha",
    "wof:placetype":"locality",
    "wof:population":1188
},
  "geometry": {"coordinates":[84.187044,26.891916],"type":"Point"}
}