{
  "type": "Feature",
  "properties": {
    "gn:admin1_code":"16.0",
    "gn:asciiname":"Ukhalshemb",
    "gn:country_code":"IN",
    "gn:dem":201,
    "gn:feature_class":"P",
    "gn:feature_code":"PPL",
    "gn:name":"Ukhalshemb",
    "gn:population":0,
    "gn:timezone":"Asia/Kolkata",
    "iso:country":"IN",
    "ks:ks_name":"Ukhalshem",
    "ks:ks_pop":468,
    "ks:ks_type":"HABITATION",
    "name:eng_x_preferred":[
        "Ukhalshem"
    ],
    "name:eng_x_variant":[
        "Ukhalshemb"
    ],
    "wof:name":"Ukhalshem",
    "wof:placetype":"locality",
    "wof:population":468
},
  "geometry": {"coordinates":[74.61588500000001,21.657125],"type":"Point"}
}