{
  "type": "Feature",
  "properties": {
    "gn:admin1_code":"36",
    "gn:admin2_code":"178.0",
    "gn:asciiname":"Bilari",
    "gn:country_code":"IN",
    "gn:dem":90,
    "gn:feature_class":"P",
    "gn:feature_code":"PPL",
    "gn:name":"Bil\u0101ri",
    "gn:population":0,
    "gn:timezone":"Asia/Kolkata",
    "iso:country":"IN",
    "name:bpy_x_preferred":[
        "\u09ac\u09bf\u09b2\u09be\u09b0\u09bf"
    ],
    "name:ceb_x_preferred":[
        "Bil\u0101ri"
    ],
    "name:hin_x_preferred":[
        "\u092c\u093f\u0932\u093e\u0930\u0940"
    ],
    "name:ita_x_preferred":[
        "Bilari"
    ],
    "name:mlg_x_preferred":[
        "Bilari"
    ],
    "name:msa_x_preferred":[
        "Bilari"
    ],
    "name:new_x_preferred":[
        "\u092c\u093f\u0932\u093e\u0930\u0940"
    ],
    "name:nld_x_preferred":[
        "Bilari"
    ],
    "name:pol_x_preferred":[
        "Bilari"
    ],
    "name:swe_x_preferred":[
        "Bil\u0101ri"
    ],
    "name:urd_x_preferred":[
        "\u0628\u0644\u0627\u0631\u06cc"
    ],
    "name:vie_x_preferred":[
        "Bilari"
    ],
    "name:zho_x_preferred":[
        "\u6bd4\u62c9\u91cc"
    ],
    "wof:name":"Bilari",
    "wof:placetype":"locality"
},
  "geometry": {"coordinates":[82.83439,26.35236],"type":"Point"}
}