{
  "type": "Feature",
  "properties": {
    "iso:country":"IN",
    "ks:ks_name":"Jarekhapur Chauraha",
    "ks:ks_pop":131,
    "ks:ks_type":"HABITATION",
    "name:eng_x_preferred":[
        "Jarekhapur Chauraha"
    ],
    "wof:name":"Jarekhapur Chauraha",
    "wof:placetype":"locality",
    "wof:population":131
},
  "geometry": {"coordinates":[80.831276,27.775094],"type":"Point"}
}