{
  "type": "Feature",
  "properties": {
    "gn:admin1_code":"25.0",
    "gn:admin2_code":"630.0",
    "gn:asciiname":"Ittigenhalli",
    "gn:country_code":"IN",
    "gn:dem":507,
    "gn:feature_class":"P",
    "gn:feature_code":"PPL",
    "gn:name":"Ittigenhalli",
    "gn:population":0,
    "gn:timezone":"Asia/Kolkata",
    "iso:country":"IN",
    "wof:name":"Ittigenhalli",
    "wof:placetype":"locality"
},
  "geometry": {"coordinates":[78.09671999999998,12.26949],"type":"Point"}
}