{
  "type": "Feature",
  "properties": {
    "iso:country":"IN",
    "ks:ks_name":"Dami",
    "ks:ks_pop":121,
    "ks:ks_type":"VILLAGE",
    "name:eng_x_preferred":[
        "Dami"
    ],
    "wof:name":"Dami",
    "wof:placetype":"locality",
    "wof:population":121
},
  "geometry": {"coordinates":[83.944835,20.359171],"type":"Point"}
}