{
  "type": "Feature",
  "properties": {
    "iso:country":"IN",
    "ks:ks_name":"Dadunia Falia",
    "ks:ks_pop":295,
    "ks:ks_type":"HABITATION",
    "name:eng_x_preferred":[
        "Dadunia Falia"
    ],
    "wof:name":"Dadunia Falia",
    "wof:placetype":"locality",
    "wof:population":295
},
  "geometry": {"coordinates":[73.16036099999999,20.355639],"type":"Point"}
}