{
  "type": "Feature",
  "properties": {
    "iso:country":"IN",
    "ks:ks_name":"Mani Falia",
    "ks:ks_pop":290,
    "ks:ks_type":"HABITATION",
    "name:eng_x_preferred":[
        "Mani Falia"
    ],
    "wof:name":"Mani Falia",
    "wof:placetype":"locality",
    "wof:population":290
},
  "geometry": {"coordinates":[73.120722,20.234806],"type":"Point"}
}