{
  "type": "Feature",
  "properties": {
    "gn:admin1_code":"25.0",
    "gn:admin2_code":"619.0",
    "gn:asciiname":"Karugappanattam",
    "gn:country_code":"IN",
    "gn:dem":20,
    "gn:feature_class":"P",
    "gn:feature_code":"PPL",
    "gn:name":"Karugappanattam",
    "gn:population":0,
    "gn:timezone":"Asia/Kolkata",
    "iso:country":"IN",
    "wof:name":"Karugappanattam",
    "wof:placetype":"neighbourhood"
},
  "geometry": {"coordinates":[79.4367,10.57607],"type":"Point"}
}