{
  "type": "Feature",
  "properties": {
    "iso:country":"IN",
    "ks:ks_name":"Bagooranahalli",
    "ks:ks_pop":106,
    "ks:ks_type":"VILLAGE",
    "name:eng_x_preferred":[
        "Bagooranahalli"
    ],
    "wof:name":"Bagooranahalli",
    "wof:placetype":"locality",
    "wof:population":106
},
  "geometry": {"coordinates":[76.338712,13.18266],"type":"Point"}
}