{
  "type": "Feature",
  "properties": {
    "iso:country":"IN",
    "ks:ks_alt_nam":"Maholi\u0101",
    "ks:ks_name":"Maholia",
    "ks:ks_type":"VILLAGE",
    "ks:ks_uagg_main":0,
    "name:eng_x_preferred":[
        "Maholia"
    ],
    "name:eng_x_variant":[
        "Maholi\u0101"
    ],
    "wof:name":"Maholia",
    "wof:placetype":"neighbourhood"
},
  "geometry": {"coordinates":[79.95487199999999,28.923682],"type":"Point"}
}