{
  "type": "Feature",
  "properties": {
    "iso:country":"IN",
    "ks:ks_name":"Kosimanuguda",
    "ks:ks_pop":60,
    "ks:ks_type":"HABITATION",
    "name:eng_x_preferred":[
        "Kosimanuguda"
    ],
    "wof:name":"Kosimanuguda",
    "wof:placetype":"locality",
    "wof:population":60
},
  "geometry": {"coordinates":[83.80638500000001,18.696581],"type":"Point"}
}