{
  "type": "Feature",
  "properties": {
    "gn:admin1_code":"35",
    "gn:admin2_code":"437.0",
    "gn:asciiname":"Sadukheri",
    "gn:country_code":"IN",
    "gn:dem":469,
    "gn:feature_class":"P",
    "gn:feature_code":"PPL",
    "gn:name":"Sadukheri",
    "gn:population":0,
    "gn:timezone":"Asia/Kolkata",
    "iso:country":"IN",
    "wof:name":"Sadukheri",
    "wof:placetype":"locality"
},
  "geometry": {"coordinates":[76.41124000000001,23.0878],"type":"Point"}
}