{
  "type": "Feature",
  "properties": {
    "iso:country":"IN",
    "ks:ks_name":"Sagbehari",
    "ks:ks_pop":577,
    "ks:ks_type":"VILLAGE",
    "name:eng_x_preferred":[
        "Sagbehari"
    ],
    "wof:name":"Sagbehari",
    "wof:placetype":"locality",
    "wof:population":577
},
  "geometry": {"coordinates":[87.31325,24.250652],"type":"Point"}
}