{
  "type": "Feature",
  "properties": {
    "gn:admin1_code":"38.0",
    "gn:admin2_code":"353.0",
    "gn:asciiname":"Borio",
    "gn:country_code":"IN",
    "gn:dem":53,
    "gn:feature_class":"P",
    "gn:feature_code":"PPL",
    "gn:name":"Borio",
    "gn:population":0,
    "gn:timezone":"Asia/Kolkata",
    "iso:country":"IN",
    "name:fra_x_preferred":[
        "Borio"
    ],
    "name:spa_x_preferred":[
        "Borio"
    ],
    "wof:name":"Borio",
    "wof:placetype":"locality"
},
  "geometry": {"coordinates":[87.79101,24.54501],"type":"Point"}
}