{
  "type": "Feature",
  "properties": {
    "gn:admin1_code":"36",
    "gn:admin2_code":"191.0",
    "gn:asciiname":"Ubarpur",
    "gn:country_code":"IN",
    "gn:dem":82,
    "gn:feature_class":"P",
    "gn:feature_code":"PPL",
    "gn:name":"Ub\u0101rpur",
    "gn:population":0,
    "gn:timezone":"Asia/Kolkata",
    "iso:country":"IN",
    "wof:name":"Ubarpur",
    "wof:placetype":"locality"
},
  "geometry": {"coordinates":[82.98725,25.85138],"type":"Point"}
}