{
  "type": "Feature",
  "properties": {
    "iso:country":"IN",
    "ks:ks_name":"Shidurukwadi",
    "ks:ks_pop":118,
    "ks:ks_type":"HABITATION",
    "name:eng_x_preferred":[
        "Shidurukwadi"
    ],
    "wof:name":"Shidurukwadi",
    "wof:placetype":"locality",
    "wof:population":118
},
  "geometry": {"coordinates":[74.003383,17.252546],"type":"Point"}
}