{
  "type": "Feature",
  "properties": {
    "iso:country":"IN",
    "ks:ks_name":"Tholur",
    "ks:ks_pop":6225,
    "ks:ks_type":"VILLAGE",
    "ks:ks_uagg_main":0,
    "name:eng_x_preferred":[
        "Tholur"
    ],
    "wof:name":"Tholur",
    "wof:placetype":"locality",
    "wof:population":6225
},
  "geometry": {"coordinates":[76.125648,10.571106],"type":"Point"}
}