{
  "type": "Feature",
  "properties": {
    "iso:country":"IN",
    "ks:ks_name":"Ambalapura",
    "ks:ks_pop":153,
    "ks:ks_type":"HABITATION",
    "name:eng_x_preferred":[
        "Ambalapura"
    ],
    "wof:name":"Ambalapura",
    "wof:placetype":"locality",
    "wof:population":153
},
  "geometry": {"coordinates":[72.874944,22.795722],"type":"Point"}
}