{
  "type": "Feature",
  "properties": {
    "iso:country":"IN",
    "ks:ks_alt_nam":"PANIKAPARA Sonhat",
    "ks:ks_name":"Panikapara Sonhat",
    "ks:ks_pop":137,
    "ks:ks_type":"HABITATION",
    "name:eng_x_preferred":[
        "Panikapara Sonhat"
    ],
    "wof:name":"Panikapara Sonhat",
    "wof:placetype":"locality",
    "wof:population":137
},
  "geometry": {"coordinates":[82.955501,23.791081],"type":"Point"}
}