{
  "type": "Feature",
  "properties": {
    "iso:country":"IN",
    "ks:ks_name":"Batajhar",
    "ks:ks_pop":388,
    "ks:ks_type":"VILLAGE",
    "name:eng_x_preferred":[
        "Batajhar"
    ],
    "wof:name":"Batajhar",
    "wof:placetype":"locality",
    "wof:population":388
},
  "geometry": {"coordinates":[82.411948,19.840549],"type":"Point"}
}