{
  "type": "Feature",
  "properties": {
    "gn:admin1_code":"37",
    "gn:admin2_code":"412.0",
    "gn:asciiname":"Amabahar",
    "gn:country_code":"IN",
    "gn:dem":494,
    "gn:feature_class":"P",
    "gn:feature_code":"PPL",
    "gn:name":"\u0100m\u0101bah\u0101r",
    "gn:population":0,
    "gn:timezone":"Asia/Kolkata",
    "iso:country":"IN",
    "wof:name":"Amabahar",
    "wof:placetype":"locality"
},
  "geometry": {"coordinates":[82.09605999999999,20.12814],"type":"Point"}
}