{
  "type": "Feature",
  "properties": {
    "gn:admin1_code":"36.0",
    "gn:admin2_code":"162.0",
    "gn:asciiname":"Mishrapur Pratapsingh",
    "gn:country_code":"IN",
    "gn:dem":124,
    "gn:feature_class":"P",
    "gn:feature_code":"PPL",
    "gn:name":"Mishrapur Prat\u0101psingh",
    "gn:population":0,
    "gn:timezone":"Asia/Kolkata",
    "iso:country":"IN",
    "wof:name":"Mishrapur Pratapsingh",
    "wof:placetype":"locality"
},
  "geometry": {"coordinates":[79.3472,26.41028],"type":"Point"}
}