{
  "type": "Feature",
  "properties": {
    "iso:country":"IN",
    "ks:ks_name":"Madapuram",
    "ks:ks_pop":286,
    "ks:ks_type":"HABITATION",
    "name:eng_x_preferred":[
        "Madapuram"
    ],
    "wof:name":"Madapuram",
    "wof:placetype":"locality",
    "wof:population":286
},
  "geometry": {"coordinates":[79.61330599999999,10.64392],"type":"Point"}
}