{
  "type": "Feature",
  "properties": {
    "gn:admin1_code":"36",
    "gn:admin2_code":"144.0",
    "gn:asciiname":"Dadonpur",
    "gn:country_code":"IN",
    "gn:dem":183,
    "gn:feature_class":"P",
    "gn:feature_code":"PPL",
    "gn:name":"D\u0101donpur",
    "gn:population":0,
    "gn:timezone":"Asia/Kolkata",
    "iso:country":"IN",
    "ks:ks_name":"Dadanpur",
    "ks:ks_pop":892,
    "ks:ks_type":"VILLAGE",
    "name:eng_x_preferred":[
        "Dadanpur"
    ],
    "name:eng_x_variant":[
        "Dadonpur"
    ],
    "wof:name":"Dadanpur",
    "wof:placetype":"locality",
    "wof:population":892
},
  "geometry": {"coordinates":[78.07810600000001,27.60106],"type":"Point"}
}