{
  "type": "Feature",
  "properties": {
    "iso:country":"IN",
    "ks:ks_name":"Bramhadevnagar",
    "ks:ks_pop":40,
    "ks:ks_type":"HABITATION",
    "ks:ks_uagg_main":0,
    "name:eng_x_preferred":[
        "Bramhadevnagar"
    ],
    "wof:name":"Bramhadevnagar",
    "wof:placetype":"neighbourhood",
    "wof:population":40
},
  "geometry": {"coordinates":[73.61823699999999,16.539621],"type":"Point"}
}