{
  "type": "Feature",
  "properties": {
    "iso:country":"IN",
    "ks:ks_name":"Seervayal",
    "ks:ks_pop":110,
    "ks:ks_type":"HABITATION",
    "name:eng_x_preferred":[
        "Seervayal"
    ],
    "wof:name":"Seervayal",
    "wof:placetype":"locality",
    "wof:population":110
},
  "geometry": {"coordinates":[78.892124,10.553061],"type":"Point"}
}