{
  "type": "Feature",
  "properties": {
    "iso:country":"IN",
    "ks:ks_name":"Dholidahar",
    "ks:ks_pop":1793,
    "ks:ks_type":"VILLAGE",
    "name:eng_x_preferred":[
        "Dholidahar"
    ],
    "wof:name":"Dholidahar",
    "wof:placetype":"locality",
    "wof:population":1793
},
  "geometry": {"coordinates":[92.592944,24.827883],"type":"Point"}
}