{
  "type": "Feature",
  "properties": {
    "iso:country":"IN",
    "ks:ks_name":"Shanthimudi",
    "ks:ks_pop":16,
    "ks:ks_type":"HABITATION",
    "name:eng_x_preferred":[
        "Shanthimudi"
    ],
    "wof:name":"Shanthimudi",
    "wof:placetype":"locality",
    "wof:population":16
},
  "geometry": {"coordinates":[75.351804,12.804462],"type":"Point"}
}