{
  "type": "Feature",
  "properties": {
    "gn:admin1_code":"19.0",
    "gn:admin2_code":"583.0",
    "gn:asciiname":"Arledibba",
    "gn:country_code":"IN",
    "gn:dem":874,
    "gn:feature_class":"P",
    "gn:feature_code":"PPL",
    "gn:name":"Arledibba",
    "gn:population":0,
    "gn:timezone":"Asia/Kolkata",
    "iso:country":"IN",
    "wof:name":"Arledibba",
    "wof:placetype":"locality"
},
  "geometry": {"coordinates":[77.32876,13.14058],"type":"Point"}
}