{
  "type": "Feature",
  "properties": {
    "iso:country":"IN",
    "ks:ks_name":"Dhaurapath",
    "ks:ks_pop":41,
    "ks:ks_type":"HABITATION",
    "name:eng_x_preferred":[
        "Dhaurapath"
    ],
    "wof:name":"Dhaurapath",
    "wof:placetype":"locality",
    "wof:population":41
},
  "geometry": {"coordinates":[82.616766,22.506456],"type":"Point"}
}