{
  "type": "Feature",
  "properties": {
    "iso:country":"IN",
    "ks:ks_name":"Kisanpur",
    "ks:ks_pop":165,
    "ks:ks_type":"VILLAGE",
    "name:eng_x_preferred":[
        "Kisanpur"
    ],
    "wof:name":"Kisanpur",
    "wof:placetype":"locality",
    "wof:population":165
},
  "geometry": {"coordinates":[86.621773,22.234573],"type":"Point"}
}