{
  "type": "Feature",
  "properties": {
    "iso:country":"IN",
    "ks:ks_name":"Koithan Ka Purwa",
    "ks:ks_pop":428,
    "ks:ks_type":"HABITATION",
    "ks:ks_uagg_main":0,
    "name:eng_x_preferred":[
        "Koithan Ka Purwa"
    ],
    "wof:name":"Koithan Ka Purwa",
    "wof:placetype":"neighbourhood",
    "wof:population":428
},
  "geometry": {"coordinates":[81.77316399999999,25.896355],"type":"Point"}
}