{
  "type": "Feature",
  "properties": {
    "gn:admin1_code":"36.0",
    "gn:admin2_code":"139.0",
    "gn:asciiname":"Hazurabadgarhi",
    "gn:country_code":"IN",
    "gn:dem":227,
    "gn:feature_class":"P",
    "gn:feature_code":"PPL",
    "gn:name":"Haz\u016br\u0101b\u0101dgarhi",
    "gn:population":0,
    "gn:timezone":"Asia/Kolkata",
    "iso:country":"IN",
    "wof:name":"Hazurabadgarhi",
    "wof:placetype":"locality"
},
  "geometry": {"coordinates":[77.40649000000001,29.03198],"type":"Point"}
}