{
  "type": "Feature",
  "properties": {
    "iso:country":"IN",
    "ks:ks_name":"Athiabari",
    "ks:ks_pop":1547,
    "ks:ks_type":"VILLAGE",
    "ks:ks_uagg_main":0,
    "name:eng_x_preferred":[
        "Athiabari"
    ],
    "wof:name":"Athiabari",
    "wof:placetype":"neighbourhood",
    "wof:population":1547
},
  "geometry": {"coordinates":[90.965456,26.512415],"type":"Point"}
}