{
  "type": "Feature",
  "properties": {
    "iso:country":"IN",
    "ks:ks_name":"Rokadewasti",
    "ks:ks_pop":135,
    "ks:ks_type":"HABITATION",
    "name:eng_x_preferred":[
        "Rokadewasti"
    ],
    "wof:name":"Rokadewasti",
    "wof:placetype":"locality",
    "wof:population":135
},
  "geometry": {"coordinates":[75.254024,18.292748],"type":"Point"}
}