{
  "type": "Feature",
  "properties": {
    "iso:country":"IN",
    "ks:ks_name":"Janiguda",
    "ks:ks_pop":216,
    "ks:ks_type":"HABITATION",
    "name:eng_x_preferred":[
        "Janiguda"
    ],
    "wof:name":"Janiguda",
    "wof:placetype":"locality",
    "wof:population":216
},
  "geometry": {"coordinates":[82.186538,19.296936],"type":"Point"}
}