{
  "type": "Feature",
  "properties": {
    "iso:country":"IN",
    "ks:ks_name":"Khalsi",
    "ks:ks_pop":1092,
    "ks:ks_type":"VILLAGE",
    "ks:ks_uagg_main":0,
    "name:eng_x_preferred":[
        "Khalsi"
    ],
    "wof:name":"Khalsi",
    "wof:placetype":"neighbourhood",
    "wof:population":1092
},
  "geometry": {"coordinates":[88.942645,22.795205],"type":"Point"}
}