{
  "type": "Feature",
  "properties": {
    "iso:country":"IN",
    "ks:ks_name":"Pakriwha",
    "ks:ks_pop":335,
    "ks:ks_type":"HABITATION",
    "ks:ks_uagg_main":0,
    "name:eng_x_preferred":[
        "Pakriwha"
    ],
    "wof:name":"Pakriwha",
    "wof:placetype":"neighbourhood",
    "wof:population":335
},
  "geometry": {"coordinates":[83.43589,26.723043],"type":"Point"}
}