{
  "type": "Feature",
  "properties": {
    "gn:admin1_code":"36",
    "gn:admin2_code":"154.0",
    "gn:asciiname":"Allawalpur",
    "gn:country_code":"IN",
    "gn:dem":138,
    "gn:feature_class":"P",
    "gn:feature_code":"PPL",
    "gn:name":"All\u0101walpur",
    "gn:population":0,
    "gn:timezone":"Asia/Kolkata",
    "iso:country":"IN",
    "wof:name":"Allawalpur",
    "wof:placetype":"locality"
},
  "geometry": {"coordinates":[80.7743,27.5561],"type":"Point"}
}