{
  "type": "Feature",
  "properties": {
    "iso:country":"IN",
    "ks:ks_name":"Sankiberia",
    "ks:ks_pop":2383,
    "ks:ks_type":"VILLAGE",
    "name:eng_x_preferred":[
        "Sankiberia"
    ],
    "wof:name":"Sankiberia",
    "wof:placetype":"locality",
    "wof:population":2383
},
  "geometry": {"coordinates":[88.282571,21.963884],"type":"Point"}
}