{
  "type": "Feature",
  "properties": {
    "iso:country":"IN",
    "ks:ks_name":"Kadam Wasti",
    "ks:ks_pop":542,
    "ks:ks_type":"HABITATION",
    "name:eng_x_preferred":[
        "Kadam Wasti"
    ],
    "wof:name":"Kadam Wasti",
    "wof:placetype":"locality",
    "wof:population":542
},
  "geometry": {"coordinates":[75.4128,17.8027],"type":"Point"}
}