{
  "type": "Feature",
  "properties": {
    "gn:admin1_code":"11.0",
    "gn:admin2_code":"33.0",
    "gn:asciiname":"Pajiot",
    "gn:country_code":"IN",
    "gn:dem":1837,
    "gn:feature_class":"P",
    "gn:feature_code":"PPL",
    "gn:name":"Paj\u012bot",
    "gn:population":0,
    "gn:timezone":"Asia/Kolkata",
    "iso:country":"IN",
    "wof:name":"Pajiot",
    "wof:placetype":"locality"
},
  "geometry": {"coordinates":[77.49115,31.14504],"type":"Point"}
}