{
  "type": "Feature",
  "properties": {
    "iso:country":"IN",
    "ks:ks_name":"Hardua",
    "ks:ks_type":"VILLAGE",
    "name:eng_x_preferred":[
        "Hardua"
    ],
    "wof:name":"Hardua",
    "wof:placetype":"locality"
},
  "geometry": {"coordinates":[78.225194,24.487923],"type":"Point"}
}