{
  "type": "Feature",
  "properties": {
    "gn:admin1_code":"36.0",
    "gn:admin2_code":"149",
    "gn:asciiname":"Hasanpur",
    "gn:country_code":"IN",
    "gn:dem":166,
    "gn:feature_class":"P",
    "gn:feature_code":"PPL",
    "gn:name":"Hasanpur",
    "gn:population":0,
    "gn:timezone":"Asia/Kolkata",
    "iso:country":"IN",
    "name:bih_x_preferred":[
        "\u0939\u0938\u0928\u092a\u0941\u0930"
    ],
    "name:bpy_x_preferred":[
        "\u09b9\u09be\u09b8\u09be\u09a8\u09aa\u09c1\u09b0"
    ],
    "name:ceb_x_preferred":[
        "Hasanpur"
    ],
    "name:deu_x_preferred":[
        "Hasanpur"
    ],
    "name:fas_x_preferred":[
        "\u062d\u0633\u0646\u200c\u067e\u0648\u0631"
    ],
    "name:hin_x_preferred":[
        "\u0939\u0938\u0928\u092a\u0941\u0930"
    ],
    "name:ita_x_preferred":[
        "Hasanpur"
    ],
    "name:mlg_x_preferred":[
        "Hasanpur"
    ],
    "name:msa_x_preferred":[
        "Hasanpur"
    ],
    "name:nep_x_preferred":[
        "\u0939\u0938\u0928\u092a\u0941\u0930"
    ],
    "name:new_x_preferred":[
        "\u0939\u0938\u0928\u092a\u0941\u0930"
    ],
    "name:nld_x_preferred":[
        "Hasanpur"
    ],
    "name:pol_x_preferred":[
        "Hasanpur"
    ],
    "name:por_x_preferred":[
        "Hasanpur"
    ],
    "name:urd_x_preferred":[
        "\u062d\u0633\u0646 \u067e\u0648\u0631"
    ],
    "name:vie_x_preferred":[
        "Hasanpur"
    ],
    "name:zho_x_preferred":[
        "\u54c8\u6851\u666e\u5c14"
    ],
    "wof:name":"Hasanpur",
    "wof:placetype":"locality"
},
  "geometry": {"coordinates":[79.20805,27.92393],"type":"Point"}
}