{
  "type": "Feature",
  "properties": {
    "iso:country":"IN",
    "ks:ks_alt_nam":"MANEWASTI",
    "ks:ks_name":"Manewasti",
    "ks:ks_pop":270,
    "ks:ks_type":"HABITATION",
    "name:eng_x_preferred":[
        "Manewasti"
    ],
    "wof:name":"Manewasti",
    "wof:placetype":"locality",
    "wof:population":270
},
  "geometry": {"coordinates":[74.490943,17.127877],"type":"Point"}
}