{
  "type": "Feature",
  "properties": {
    "iso:country":"IN",
    "ks:ks_name":"Tatibahar No3",
    "ks:ks_pop":280,
    "ks:ks_type":"HABITATION",
    "name:eng_x_preferred":[
        "Tatibahar No3"
    ],
    "wof:name":"Tatibahar No3",
    "wof:placetype":"locality",
    "wof:population":280
},
  "geometry": {"coordinates":[93.83526000000001,26.980997],"type":"Point"}
}