{
  "type": "Feature",
  "properties": {
    "iso:country":"IN",
    "ks:ks_name":"Badasal",
    "ks:ks_pop":435,
    "ks:ks_type":"VILLAGE",
    "name:eng_x_preferred":[
        "Badasal"
    ],
    "wof:name":"Badasal",
    "wof:placetype":"locality",
    "wof:population":435
},
  "geometry": {"coordinates":[86.931596,21.684079],"type":"Point"}
}