{
  "type": "Feature",
  "properties": {
    "iso:country":"IN",
    "ks:ks_name":"Nagla Johri",
    "ks:ks_pop":101,
    "ks:ks_type":"HABITATION",
    "name:eng_x_preferred":[
        "Nagla Johri"
    ],
    "wof:name":"Nagla Johri",
    "wof:placetype":"locality",
    "wof:population":101
},
  "geometry": {"coordinates":[78.17134,27.224262],"type":"Point"}
}