{
  "type": "Feature",
  "properties": {
    "iso:country":"IN",
    "ks:ks_name":"Thiyagarajanallur",
    "ks:ks_pop":300,
    "ks:ks_type":"HABITATION",
    "name:eng_x_preferred":[
        "Thiyagarajanallur"
    ],
    "wof:name":"Thiyagarajanallur",
    "wof:placetype":"locality",
    "wof:population":300
},
  "geometry": {"coordinates":[79.749304,11.076988],"type":"Point"}
}