{
  "type": "Feature",
  "properties": {
    "gn:admin1_code":"19.0",
    "gn:admin2_code":"561.0",
    "gn:asciiname":"Gadag-Betageri",
    "gn:country_code":"IN",
    "gn:dem":665,
    "gn:feature_class":"P",
    "gn:feature_code":"PPL",
    "gn:name":"Gadag-Betageri",
    "gn:population":172813,
    "gn:timezone":"Asia/Kolkata",
    "iso:country":"IN",
    "name:bar_x_preferred":[
        "Gadag-Betageri"
    ],
    "name:ben_x_preferred":[
        "\u0997\u09a6\u09be\u0997-\u09ac\u09c7\u09a4\u09bf\u0997\u09c7\u09b0\u09bf"
    ],
    "name:bih_x_preferred":[
        "\u0917\u0921\u0917-\u092c\u0948\u091f\u093e\u0917\u0948\u0930\u0940"
    ],
    "name:bpy_x_preferred":[
        "\u0997\u09a6\u09be\u0997-\u09ac\u09c7\u09a4\u09bf\u0997\u09c7\u09b0\u09bf"
    ],
    "name:deu_x_preferred":[
        "Gadag-Betageri"
    ],
    "name:fra_x_preferred":[
        "Gadag-Betageri"
    ],
    "name:guj_x_preferred":[
        "\u0a97\u0aa1\u0a97"
    ],
    "name:hin_x_preferred":[
        "\u0917\u0926\u0917-\u092c\u0947\u091f\u0917\u0947\u0930\u0940"
    ],
    "name:ita_x_preferred":[
        "Gadag-Betageri"
    ],
    "name:kan_x_preferred":[
        "\u0c97\u0ca6\u0c97"
    ],
    "name:mar_x_preferred":[
        "\u0917\u0926\u0917"
    ],
    "name:mlg_x_preferred":[
        "Gadag-Betageri"
    ],
    "name:msa_x_preferred":[
        "Gadag-Betigeri"
    ],
    "name:new_x_preferred":[
        "\u0917\u0926\u0917"
    ],
    "name:nld_x_preferred":[
        "Gadag-Betigeri"
    ],
    "name:pol_x_preferred":[
        "Gadag-Betigeri"
    ],
    "name:por_x_preferred":[
        "Gadag-Betigeri"
    ],
    "name:rus_x_preferred":[
        "\u0413\u0430\u0434\u0430\u0433-\u0411\u0435\u0442\u0438\u0433\u0435\u0440\u0438"
    ],
    "name:san_x_preferred":[
        "\u0917\u0926\u0917"
    ],
    "name:spa_x_preferred":[
        "Gadag-Betageri"
    ],
    "name:swe_x_preferred":[
        "Gadag-Betigeri"
    ],
    "name:tcy_x_preferred":[
        "\u0c97\u0ca6\u0c97\u0ccd"
    ],
    "name:tel_x_preferred":[
        "\u0c17\u0c26\u0c17\u0c4d"
    ],
    "name:urd_x_preferred":[
        "\u06af\u062f\u06af-\u0628\u06cc\u0679\u06af\u06cc\u0631\u06cc"
    ],
    "name:vie_x_preferred":[
        "Gadag-Betigeri"
    ],
    "name:war_x_preferred":[
        "Gadag-Betgeri"
    ],
    "name:zho_x_preferred":[
        "\u52a0\u8fbe\u683c-\u8d1d\u8482\u76d6\u91cc"
    ],
    "wof:name":"Gadag-Betageri",
    "wof:placetype":"locality",
    "wof:population":172813
},
  "geometry": {"coordinates":[75.61669999999999,15.4167],"type":"Point"}
}