{
  "type": "Feature",
  "properties": {
    "gn:admin1_code":"19.0",
    "gn:admin2_code":"561.0",
    "gn:asciiname":"Gadag-Betageri",
    "gn:country_code":"IN",
    "gn:dem":665,
    "gn:feature_class":"P",
    "gn:feature_code":"PPL",
    "gn:name":"Gadag-Betageri",
    "gn:population":172813,
    "gn:timezone":"Asia/Kolkata",
    "iso:country":"IN",
    "wof:name":"Gadag-Betageri",
    "wof:placetype":"locality",
    "wof:population":172813
},
  "geometry": {"coordinates":[75.61669999999999,15.4167],"type":"Point"}
}