{
  "type": "Feature",
  "properties": {
    "iso:country":"IN",
    "ks:ks_alt_nam":"Bania par",
    "ks:ks_name":"Bania Par",
    "ks:ks_pop":580,
    "ks:ks_type":"HABITATION",
    "ks:ks_uagg_main":0,
    "name:eng_x_preferred":[
        "Bania Par"
    ],
    "wof:name":"Bania Par",
    "wof:placetype":"neighbourhood",
    "wof:population":580
},
  "geometry": {"coordinates":[89.564105,26.292036],"type":"Point"}
}