{
  "type": "Feature",
  "properties": {
    "gn:admin1_code":"02",
    "gn:admin2_code":"551.0",
    "gn:asciiname":"Nandalur",
    "gn:country_code":"IN",
    "gn:dem":144,
    "gn:feature_class":"P",
    "gn:feature_code":"PPL",
    "gn:name":"Nandal\u016br",
    "gn:population":0,
    "gn:timezone":"Asia/Kolkata",
    "iso:country":"IN",
    "ks:ks_alt_nam":"Nandal\u016br",
    "ks:ks_name":"Nandalur",
    "ks:ks_pop":4052,
    "ks:ks_type":"VILLAGE",
    "ks:ks_uagg_main":0,
    "name:eng_x_preferred":[
        "Nandalur"
    ],
    "name:eng_x_variant":[
        "Nandal\u016br"
    ],
    "name:mya_x_preferred":[
        "\u1014\u1014\u103a\u1012\u101c\u102c"
    ],
    "name:new_x_preferred":[
        "\u0928\u0928\u094d\u0926\u0932\u0942\u0930\u0941 \u092e\u0923\u094d\u0921\u0932"
    ],
    "name:pam_x_preferred":[
        "Nandalur"
    ],
    "name:tel_x_preferred":[
        "\u0c28\u0c02\u0c26\u0c32\u0c42\u0c30\u0c41"
    ],
    "name:tgl_x_preferred":[
        "Nandalur"
    ],
    "name:und_x_variant":[
        "Nandal\u016br"
    ],
    "name:urd_x_preferred":[
        "\u0646\u0646\u062f\u0644\u0648\u0631"
    ],
    "wof:name":"Nandalur",
    "wof:placetype":"neighbourhood",
    "wof:population":4052
},
  "geometry": {"coordinates":[79.119519,14.266883],"type":"Point"}
}