{
  "type": "Feature",
  "properties": {
    "iso:country":"IN",
    "ks:ks_name":"Voosakondaguda",
    "ks:ks_pop":169,
    "ks:ks_type":"HABITATION",
    "name:eng_x_preferred":[
        "Voosakondaguda"
    ],
    "wof:name":"Voosakondaguda",
    "wof:placetype":"locality",
    "wof:population":169
},
  "geometry": {"coordinates":[83.69031200000001,18.824764],"type":"Point"}
}