{
  "type": "Feature",
  "properties": {
    "gn:admin1_code":"38.0",
    "gn:admin2_code":"358.0",
    "gn:asciiname":"Mahe",
    "gn:country_code":"IN",
    "gn:dem":325,
    "gn:feature_class":"P",
    "gn:feature_code":"PPL",
    "gn:name":"Mahe",
    "gn:population":0,
    "gn:timezone":"Asia/Kolkata",
    "iso:country":"IN",
    "name:cat_x_preferred":[
        "Mahe"
    ],
    "name:ceb_x_preferred":[
        "Mahe"
    ],
    "name:dan_x_preferred":[
        "Mahe"
    ],
    "name:deu_x_preferred":[
        "Mahe"
    ],
    "name:ita_x_preferred":[
        "Mahe"
    ],
    "name:mal_x_preferred":[
        "\u0d2e\u0d3e\u0d39\u0d3f"
    ],
    "name:rus_x_preferred":[
        "\u041c\u0430\u044d"
    ],
    "name:spa_x_preferred":[
        "Mahe"
    ],
    "name:ukr_x_preferred":[
        "\u041c\u0430\u0435"
    ],
    "wof:name":"Mahe",
    "wof:placetype":"locality"
},
  "geometry": {"coordinates":[84.38435,24.00299],"type":"Point"}
}