{
  "type": "Feature",
  "properties": {
    "gn:admin1_code":"38.0",
    "gn:admin2_code":"358.0",
    "gn:asciiname":"Mahe",
    "gn:country_code":"IN",
    "gn:dem":325,
    "gn:feature_class":"P",
    "gn:feature_code":"PPL",
    "gn:name":"Mahe",
    "gn:population":0,
    "gn:timezone":"Asia/Kolkata",
    "iso:country":"IN",
    "ks:ks_name":"Mahe",
    "ks:ks_pop":73,
    "ks:ks_type":"VILLAGE",
    "name:ara_x_preferred":[
        "\u0645\u0627\u0647\u064a"
    ],
    "name:ben_bn_x_preferred":[
        "\u09ae\u09be\u09b9\u09c7"
    ],
    "name:ben_in_x_preferred":[
        "\u09ae\u09be\u09b9\u09c7"
    ],
    "name:cat_x_preferred":[
        "Mahe"
    ],
    "name:ceb_x_preferred":[
        "Mahe"
    ],
    "name:dan_x_preferred":[
        "Mahe"
    ],
    "name:deu_x_preferred":[
        "Mahe"
    ],
    "name:eng_x_preferred":[
        "Mahe"
    ],
    "name:guj_x_preferred":[
        "\u0aae\u0abe\u0ab9\u0ac7"
    ],
    "name:hin_x_preferred":[
        "\u092e\u093e\u0939\u0947"
    ],
    "name:ita_x_preferred":[
        "Mahe"
    ],
    "name:kan_x_preferred":[
        "\u0cae\u0cbe\u0cb9\u0cc6"
    ],
    "name:mal_x_preferred":[
        "\u0d2e\u0d3e\u0d39\u0d3f"
    ],
    "name:mar_x_preferred":[
        "\u092e\u093e\u0939\u0947"
    ],
    "name:pan_x_preferred":[
        "\u0a2e\u0a3e\u0a39\u0a47"
    ],
    "name:rus_x_preferred":[
        "\u041c\u0430\u044d"
    ],
    "name:spa_x_preferred":[
        "Mahe"
    ],
    "name:tam_x_preferred":[
        "\u0bae\u0bb9\u0bc6"
    ],
    "name:tel_x_preferred":[
        "\u0c2e\u0c39\u0c46"
    ],
    "name:ukr_x_preferred":[
        "\u041c\u0430\u0435"
    ],
    "name:urd_x_preferred":[
        "\u0645\u0627\u06c1\u06cc"
    ],
    "wof:name":"Mahe",
    "wof:placetype":"locality",
    "wof:population":73
},
  "geometry": {"coordinates":[84.38434599999999,24.002987],"type":"Point"}
}