{
  "type": "Feature",
  "properties": {
    "iso:country":"IN",
    "ks:ks_name":"Palasahi",
    "ks:ks_pop":56,
    "ks:ks_type":"VILLAGE",
    "name:eng_x_preferred":[
        "Palasahi"
    ],
    "wof:name":"Palasahi",
    "wof:placetype":"locality",
    "wof:population":56
},
  "geometry": {"coordinates":[86.78178200000001,21.22806],"type":"Point"}
}