{
  "type": "Feature",
  "properties": {
    "iso:country":"IN",
    "ks:ks_name":"Umbarman",
    "ks:ks_pop":400,
    "ks:ks_type":"HABITATION",
    "name:eng_x_preferred":[
        "Umbarman"
    ],
    "wof:name":"Umbarman",
    "wof:placetype":"locality",
    "wof:population":400
},
  "geometry": {"coordinates":[92.33382,25.923765],"type":"Point"}
}