{
  "type": "Feature",
  "properties": {
    "iso:country":"IN",
    "ks:ks_name":"Yeguvaboodi",
    "ks:ks_pop":146,
    "ks:ks_type":"HABITATION",
    "name:eng_x_preferred":[
        "Yeguvaboodi"
    ],
    "wof:name":"Yeguvaboodi",
    "wof:placetype":"locality",
    "wof:population":146
},
  "geometry": {"coordinates":[83.13584400000001,18.237401],"type":"Point"}
}