{
  "type": "Feature",
  "properties": {
    "iso:country":"IN",
    "name:deu_x_preferred":[
        "Chepauk"
    ],
    "name:eng_x_preferred":[
        "Chepauk"
    ],
    "name:fra_x_preferred":[
        "Chepauk"
    ],
    "name:nld_x_preferred":[
        "Chepauk"
    ],
    "name:tam_x_preferred":[
        "\u0b9a\u0bc7\u0baa\u0bcd\u0baa\u0bbe\u0b95\u0bcd\u0b95\u0bae\u0bcd"
    ],
    "name:urd_x_preferred":[
        "\u0686\u06cc\u067e\u0627\u0648\u06a9"
    ],
    "qs:gn_adm0_cc":"IN",
    "qs:gn_fcode":"PPLX",
    "qs:gn_local":1264527,
    "qs:gn_nam_loc":"Chennai, Chennai, Tamil Nadu, IN",
    "qs:gn_namadm1":"25",
    "qs:gn_name":"Chepauk",
    "qs:local_max":2138,
    "qs:local_sum":21081,
    "qs:localhoods":47,
    "qs:name":"Chepauk",
    "qs:name_adm0":"India",
    "qs:name_adm1":"Tamil Nadu",
    "qs:name_adm2":"Chennai",
    "qs:name_local":"Chennai",
    "qs:photo_max":132,
    "qs:photo_sum":695,
    "qs:placetype":"Suburb",
    "qs:quad_count":28,
    "qs:woe_adm0":23424848,
    "qs:woe_adm1":2345758,
    "qs:woe_adm2":12586677,
    "qs:woe_lau":0,
    "qs:woe_local":2295424,
    "qs:woe_ver":"7.10.0",
    "wd:wordcount":305,
    "wof:lang":[
        "eng"
    ],
    "wof:name":"Chepauk",
    "wof:placetype":"neighbourhood"
},
  "geometry": {"coordinates":[80.285111,13.0635],"type":"Point"}
}