{
  "type": "Feature",
  "properties": {
    "iso:country":"IN",
    "ks:ks_name":"Chormanrwa",
    "ks:ks_pop":953,
    "ks:ks_type":"VILLAGE",
    "name:eng_x_preferred":[
        "Chormanrwa"
    ],
    "wof:name":"Chormanrwa",
    "wof:placetype":"locality",
    "wof:population":953
},
  "geometry": {"coordinates":[84.232902,23.355032],"type":"Point"}
}