{
  "type": "Feature",
  "properties": {
    "gn:admin1_code":"28.0",
    "gn:admin2_code":"334",
    "gn:asciiname":"Deocha",
    "gn:country_code":"IN",
    "gn:dem":61,
    "gn:feature_class":"P",
    "gn:feature_code":"PPL",
    "gn:name":"Deocha",
    "gn:population":0,
    "gn:timezone":"Asia/Kolkata",
    "iso:country":"IN",
    "name:und_x_variant":[
        "Deucha",
        "Deocha"
    ],
    "wof:name":"Deocha",
    "wof:placetype":"locality"
},
  "geometry": {"coordinates":[87.58521,24.03996],"type":"Point"}
}