{
  "type": "Feature",
  "properties": {
    "iso:country":"IN",
    "ks:ks_name":"Sikandpur",
    "ks:ks_pop":1,
    "ks:ks_type":"HABITATION",
    "name:eng_x_preferred":[
        "Sikandpur"
    ],
    "wof:name":"Sikandpur",
    "wof:placetype":"locality",
    "wof:population":1
},
  "geometry": {"coordinates":[77.316005,28.852569],"type":"Point"}
}