{
  "type": "Feature",
  "properties": {
    "iso:country":"IN",
    "ks:ks_name":"Korwadih",
    "ks:ks_pop":0,
    "ks:ks_type":"VILLAGE",
    "name:eng_x_preferred":[
        "Korwadih"
    ],
    "wof:name":"Korwadih",
    "wof:placetype":"locality",
    "wof:population":0
},
  "geometry": {"coordinates":[84.01343900000001,23.688363],"type":"Point"}
}