{
  "type": "Feature",
  "properties": {
    "iso:country":"IN",
    "ks:ks_name":"Tetulia",
    "ks:ks_pop":450,
    "ks:ks_type":"VILLAGE",
    "ks:ks_uagg_main":0,
    "name:eng_x_preferred":[
        "Tetulia"
    ],
    "wof:name":"Tetulia",
    "wof:placetype":"neighbourhood",
    "wof:population":450
},
  "geometry": {"coordinates":[87.776869,24.872394],"type":"Point"}
}