{
  "type": "Feature",
  "properties": {
    "iso:country":"IN",
    "ks:ks_name":"Colony",
    "ks:ks_pop":250,
    "ks:ks_type":"HABITATION",
    "name:eng_x_preferred":[
        "Colony"
    ],
    "wof:name":"Colony",
    "wof:placetype":"locality",
    "wof:population":250
},
  "geometry": {"coordinates":[81.54182299999999,26.48011],"type":"Point"}
}