{
  "type": "Feature",
  "properties": {
    "iso:country":"IN",
    "ks:ks_name":"Kolajora",
    "ks:ks_pop":173,
    "ks:ks_type":"HABITATION",
    "name:eng_x_preferred":[
        "Kolajora"
    ],
    "wof:name":"Kolajora",
    "wof:placetype":"locality",
    "wof:population":173
},
  "geometry": {"coordinates":[87.53585099999999,24.428454],"type":"Point"}
}