{
  "type": "Feature",
  "properties": {
    "gn:admin1_code":"25.0",
    "gn:admin2_code":"607.0",
    "gn:asciiname":"Pudunagar",
    "gn:country_code":"IN",
    "gn:dem":17,
    "gn:feature_class":"P",
    "gn:feature_code":"PPL",
    "gn:name":"Pudunagar",
    "gn:population":0,
    "gn:timezone":"Asia/Kolkata",
    "iso:country":"IN",
    "wof:name":"Pudunagar",
    "wof:placetype":"locality"
},
  "geometry": {"coordinates":[79.77345,12.14055],"type":"Point"}
}