{
  "type": "Feature",
  "properties": {
    "gn:admin1_code":"24.0",
    "gn:admin2_code":"124.0",
    "gn:asciiname":"Wasi",
    "gn:country_code":"IN",
    "gn:dem":260,
    "gn:feature_class":"P",
    "gn:feature_code":"PPL",
    "gn:name":"Wasi",
    "gn:population":0,
    "gn:timezone":"Asia/Kolkata",
    "iso:country":"IN",
    "name:ceb_x_preferred":[
        "Wasi"
    ],
    "name:swe_x_preferred":[
        "Wasi"
    ],
    "wof:name":"Wasi",
    "wof:placetype":"locality"
},
  "geometry": {"coordinates":[73.81191,23.9017],"type":"Point"}
}