{
  "type": "Feature",
  "properties": {
    "iso:country":"IN",
    "ks:ks_name":"Nainoorpally",
    "ks:ks_pop":228,
    "ks:ks_type":"HABITATION",
    "name:eng_x_preferred":[
        "Nainoorpally"
    ],
    "wof:name":"Nainoorpally",
    "wof:placetype":"locality",
    "wof:population":228
},
  "geometry": {"coordinates":[78.909295,18.37039],"type":"Point"}
}