{
  "type": "Feature",
  "properties": {
    "iso:country":"IN",
    "ks:ks_name":"Gadahara Kishor Singh",
    "ks:ks_pop":182,
    "ks:ks_type":"HABITATION",
    "name:eng_x_preferred":[
        "Gadahara Kishor Singh"
    ],
    "wof:name":"Gadahara Kishor Singh",
    "wof:placetype":"locality",
    "wof:population":182
},
  "geometry": {"coordinates":[81.384075,24.285541],"type":"Point"}
}