{
  "type": "Feature",
  "properties": {
    "iso:country":"IN",
    "ks:ks_name":"Haluwai Tola",
    "ks:ks_pop":330,
    "ks:ks_type":"HABITATION",
    "ks:ks_uagg_main":0,
    "name:eng_x_preferred":[
        "Haluwai Tola"
    ],
    "wof:name":"Haluwai Tola",
    "wof:placetype":"locality",
    "wof:population":330
},
  "geometry": {"coordinates":[86.53545200000001,25.890989],"type":"Point"}
}