{
  "type": "Feature",
  "properties": {
    "gn:admin1_code":"36",
    "gn:admin2_code":"194.0",
    "gn:asciiname":"Pura Khansa",
    "gn:country_code":"IN",
    "gn:dem":93,
    "gn:feature_class":"P",
    "gn:feature_code":"PPL",
    "gn:name":"Pura Khansa",
    "gn:population":0,
    "gn:timezone":"Asia/Kolkata",
    "iso:country":"IN",
    "wof:name":"Pura Khansa",
    "wof:placetype":"locality"
},
  "geometry": {"coordinates":[82.31381999999998,25.87808],"type":"Point"}
}