{
  "type": "Feature",
  "properties": {
    "gn:admin1_code":"11",
    "gn:admin2_code":"24.0",
    "gn:asciiname":"Nagrota",
    "gn:country_code":"IN",
    "gn:dem":357,
    "gn:feature_class":"P",
    "gn:feature_code":"PPL",
    "gn:name":"Nagrota",
    "gn:population":0,
    "gn:timezone":"Asia/Kolkata",
    "iso:country":"IN",
    "name:hin_x_preferred":[
        "\u0928\u0917\u0930\u094b\u091f\u093e"
    ],
    "name:nld_x_preferred":[
        "Nagrota"
    ],
    "wof:name":"Nagrota",
    "wof:placetype":"locality"
},
  "geometry": {"coordinates":[75.94578,31.94253],"type":"Point"}
}