{
  "type": "Feature",
  "properties": {
    "iso:country":"IN",
    "ks:ks_name":"Baniani",
    "ks:ks_pop":269,
    "ks:ks_type":"HABITATION",
    "ks:ks_uagg_main":0,
    "name:eng_x_preferred":[
        "Baniani"
    ],
    "wof:name":"Baniani",
    "wof:placetype":"neighbourhood",
    "wof:population":269
},
  "geometry": {"coordinates":[88.301436,26.309383],"type":"Point"}
}