{
  "type": "Feature",
  "properties": {
    "gn:admin1_code":"36.0",
    "gn:admin2_code":"175.0",
    "gn:asciiname":"Diha",
    "gn:country_code":"IN",
    "gn:dem":90,
    "gn:feature_class":"P",
    "gn:feature_code":"PPL",
    "gn:name":"D\u012bha",
    "gn:population":0,
    "gn:timezone":"Asia/Kolkata",
    "iso:country":"IN",
    "name:und_x_variant":[
        "D\u012bha",
        "Chuppepur"
    ],
    "wof:name":"Diha",
    "wof:placetype":"locality"
},
  "geometry": {"coordinates":[81.98222,25.29696],"type":"Point"}
}