{
  "type": "Feature",
  "properties": {
    "iso:country":"IN",
    "ks:ks_name":"Vilrampatti",
    "ks:ks_pop":125,
    "ks:ks_type":"HABITATION",
    "name:eng_x_preferred":[
        "Vilrampatti"
    ],
    "wof:name":"Vilrampatti",
    "wof:placetype":"locality",
    "wof:population":125
},
  "geometry": {"coordinates":[78.6915,9.902682],"type":"Point"}
}