{
  "type": "Feature",
  "properties": {
    "iso:country":"IN",
    "ks:ks_name":"Sabalewasti",
    "ks:ks_pop":129,
    "ks:ks_type":"HABITATION",
    "name:eng_x_preferred":[
        "Sabalewasti"
    ],
    "wof:name":"Sabalewasti",
    "wof:placetype":"locality",
    "wof:population":129
},
  "geometry": {"coordinates":[74.58036,18.950969],"type":"Point"}
}