{
  "type": "Feature",
  "properties": {
    "iso:country":"IN",
    "ks:ks_name":"Laseru",
    "ks:ks_pop":38,
    "ks:ks_type":"HABITATION",
    "name:eng_x_preferred":[
        "Laseru"
    ],
    "wof:name":"Laseru",
    "wof:placetype":"locality",
    "wof:population":38
},
  "geometry": {"coordinates":[82.287323,18.023398],"type":"Point"}
}