{
  "type": "Feature",
  "properties": {
    "iso:country":"IN",
    "ks:ks_alt_nam":"32 LNP",
    "ks:ks_name":"32 Lnp",
    "ks:ks_pop":8,
    "ks:ks_type":"HABITATION",
    "name:eng_x_preferred":[
        "32 Lnp"
    ],
    "wof:name":"32 Lnp",
    "wof:placetype":"locality",
    "wof:population":8
},
  "geometry": {"coordinates":[73.886011,29.676803],"type":"Point"}
}