{
  "type": "Feature",
  "properties": {
    "iso:country":"IN",
    "ks:ks_alt_nam":"Babh\u0101ndih",
    "ks:ks_name":"Babhandih",
    "ks:ks_pop":1410,
    "ks:ks_type":"VILLAGE",
    "ks:ks_uagg_main":0,
    "name:eng_x_preferred":[
        "Babhandih"
    ],
    "name:eng_x_variant":[
        "Babh\u0101ndih"
    ],
    "wof:name":"Babhandih",
    "wof:placetype":"neighbourhood",
    "wof:population":1410
},
  "geometry": {"coordinates":[84.108203,23.842285],"type":"Point"}
}