{
  "type": "Feature",
  "properties": {
    "gn:admin1_code":"19.0",
    "gn:admin2_code":"555",
    "gn:asciiname":"Galatge",
    "gn:country_code":"IN",
    "gn:dem":569,
    "gn:feature_class":"P",
    "gn:feature_code":"PPL",
    "gn:name":"Galatge",
    "gn:population":0,
    "gn:timezone":"Asia/Kolkata",
    "iso:country":"IN",
    "name:und_x_variant":[
        "Galatgi",
        "Galatga",
        "Galatge"
    ],
    "wof:name":"Galatge",
    "wof:placetype":"locality"
},
  "geometry": {"coordinates":[74.47131,16.49179],"type":"Point"}
}