{
  "type": "Feature",
  "properties": {
    "iso:country":"IN",
    "ks:ks_name":"Mandal Tola",
    "ks:ks_pop":58,
    "ks:ks_type":"HABITATION",
    "name:eng_x_preferred":[
        "Mandal Tola"
    ],
    "wof:name":"Mandal Tola",
    "wof:placetype":"locality",
    "wof:population":58
},
  "geometry": {"coordinates":[87.118953,25.488999],"type":"Point"}
}