{
  "type": "Feature",
  "properties": {
    "iso:country":"IN",
    "ks:ks_name":"Ghilabari",
    "ks:ks_pop":643,
    "ks:ks_type":"VILLAGE",
    "ks:ks_uagg_main":0,
    "name:eng_x_preferred":[
        "Ghilabari"
    ],
    "wof:name":"Ghilabari",
    "wof:placetype":"neighbourhood",
    "wof:population":643
},
  "geometry": {"coordinates":[91.08247799999999,25.997718],"type":"Point"}
}