{
  "type": "Feature",
  "properties": {
    "iso:country":"IN",
    "ks:ks_name":"Adigadde",
    "ks:ks_pop":38,
    "ks:ks_type":"HABITATION",
    "name:eng_x_preferred":[
        "Adigadde"
    ],
    "wof:name":"Adigadde",
    "wof:placetype":"locality",
    "wof:population":38
},
  "geometry": {"coordinates":[74.648544,14.241379],"type":"Point"}
}