{
  "type": "Feature",
  "properties": {
    "gn:admin1_code":"2.0",
    "gn:admin2_code":"554.0",
    "gn:asciiname":"Gavunivaripalle",
    "gn:country_code":"IN",
    "gn:dem":727,
    "gn:feature_class":"P",
    "gn:feature_code":"PPL",
    "gn:name":"Gavuniv\u0101r\u012bpalle",
    "gn:population":0,
    "gn:timezone":"Asia/Kolkata",
    "iso:country":"IN",
    "wof:name":"Gavunivaripalle",
    "wof:placetype":"locality"
},
  "geometry": {"coordinates":[78.72981,13.33705],"type":"Point"}
}