{
  "type": "Feature",
  "properties": {
    "gn:admin1_code":"2.0",
    "gn:admin2_code":"554.0",
    "gn:asciiname":"Gavunivaripalle",
    "gn:country_code":"IN",
    "gn:dem":727,
    "gn:feature_class":"P",
    "gn:feature_code":"PPL",
    "gn:name":"Gavuniv\u0101r\u012bpalle",
    "gn:population":0,
    "gn:timezone":"Asia/Kolkata",
    "iso:country":"IN",
    "ks:ks_name":"Gownivaripalle",
    "ks:ks_pop":94,
    "ks:ks_type":"HABITATION",
    "name:eng_x_preferred":[
        "Gownivaripalle"
    ],
    "name:eng_x_variant":[
        "Gavunivaripalle"
    ],
    "wof:name":"Gownivaripalle",
    "wof:placetype":"locality",
    "wof:population":94
},
  "geometry": {"coordinates":[78.72921599999999,13.337495],"type":"Point"}
}