{
  "type": "Feature",
  "properties": {
    "gn:admin1_code":"19.0",
    "gn:admin2_code":"555.0",
    "gn:asciiname":"Talavde",
    "gn:country_code":"IN",
    "gn:dem":751,
    "gn:feature_class":"P",
    "gn:feature_code":"PPL",
    "gn:name":"Talavde",
    "gn:population":0,
    "gn:timezone":"Asia/Kolkata",
    "iso:country":"IN",
    "wof:name":"Talavde",
    "wof:placetype":"locality"
},
  "geometry": {"coordinates":[74.26943,15.72126],"type":"Point"}
}