{
  "type": "Feature",
  "properties": {
    "gn:admin1_code":"10",
    "gn:admin2_code":"69.0",
    "gn:asciiname":"Bergati",
    "gn:country_code":"IN",
    "gn:dem":639,
    "gn:feature_class":"P",
    "gn:feature_code":"PPL",
    "gn:name":"Bergati",
    "gn:population":0,
    "gn:timezone":"Asia/Kolkata",
    "iso:country":"IN",
    "ks:ks_name":"Bergati",
    "ks:ks_type":"VILLAGE",
    "name:eng_x_preferred":[
        "Bergati"
    ],
    "wof:name":"Bergati",
    "wof:placetype":"locality"
},
  "geometry": {"coordinates":[76.98848700000001,30.772979],"type":"Point"}
}