{
  "type": "Feature",
  "properties": {
    "gn:admin1_code":"35",
    "gn:admin2_code":"449.0",
    "gn:asciiname":"Malupura",
    "gn:country_code":"IN",
    "gn:dem":362,
    "gn:feature_class":"P",
    "gn:feature_code":"PPL",
    "gn:name":"Malupura",
    "gn:population":0,
    "gn:timezone":"Asia/Kolkata",
    "iso:country":"IN",
    "ks:ks_name":"Mallupura",
    "ks:ks_pop":252,
    "ks:ks_type":"HABITATION",
    "name:eng_x_preferred":[
        "Mallupura"
    ],
    "name:eng_x_variant":[
        "Malupura"
    ],
    "wof:name":"Mallupura",
    "wof:placetype":"locality",
    "wof:population":252
},
  "geometry": {"coordinates":[77.936503,22.425794],"type":"Point"}
}