{
  "type": "Feature",
  "properties": {
    "gn:admin1_code":"19",
    "gn:admin2_code":"568.0",
    "gn:asciiname":"Arodi",
    "gn:country_code":"IN",
    "gn:dem":610,
    "gn:feature_class":"P",
    "gn:feature_code":"PPL",
    "gn:name":"\u0100rodi",
    "gn:population":0,
    "gn:timezone":"Asia/Kolkata",
    "iso:country":"IN",
    "wof:name":"Arodi",
    "wof:placetype":"locality"
},
  "geometry": {"coordinates":[74.81779,14.00771],"type":"Point"}
}