{
  "type": "Feature",
  "properties": {
    "gn:admin1_code":"19",
    "gn:admin2_code":"568.0",
    "gn:asciiname":"Arodi",
    "gn:country_code":"IN",
    "gn:dem":610,
    "gn:feature_class":"P",
    "gn:feature_code":"PPL",
    "gn:name":"\u0100rodi",
    "gn:population":0,
    "gn:timezone":"Asia/Kolkata",
    "iso:country":"IN",
    "ks:ks_name":"Harodi",
    "ks:ks_pop":34,
    "ks:ks_type":"HABITATION",
    "name:eng_x_preferred":[
        "Harodi"
    ],
    "name:eng_x_variant":[
        "Arodi"
    ],
    "wof:name":"Harodi",
    "wof:placetype":"locality",
    "wof:population":34
},
  "geometry": {"coordinates":[74.82754799999999,14.002861],"type":"Point"}
}