{
  "type": "Feature",
  "properties": {
    "iso:country":"IN",
    "name:ara_x_preferred":[
        "\u0633\u0648\u0627\u062a\u064a\u0627 \u0646\u0627\u062c\u0627\u0631"
    ],
    "name:ben_bn_x_preferred":[
        "\u09b8\u09cd\u09ac\u09be\u09a5\u09c0 \u09a8\u0997\u09b0"
    ],
    "name:ben_in_x_preferred":[
        "\u09b8\u09cd\u09ac\u09be\u09a5\u09c0 \u09a8\u0997\u09b0"
    ],
    "name:guj_x_preferred":[
        "\u0ab8\u0acd\u0ab5\u0abe\u0aa4\u0ac0 \u0aa8\u0a97\u0ab0"
    ],
    "name:hin_x_preferred":[
        "\u0938\u094d\u0935\u093e\u0924\u0940 \u0928\u0917\u0930"
    ],
    "name:kan_x_preferred":[
        "\u0cb8\u0ccd\u0cb5\u0cbe\u0ca4\u0cbf \u0ca8\u0c97\u0cb0"
    ],
    "name:mal_x_preferred":[
        "\u0d38\u0d4d\u0d35\u0d3e\u0d24\u0d3f \u0d28\u0d17\u0d7c"
    ],
    "name:mar_x_preferred":[
        "\u0938\u094d\u0935\u093e\u0924\u0940 \u0928\u0917\u0930"
    ],
    "name:pan_x_preferred":[
        "\u0a38\u0a35\u0a3e\u0a24\u0a40 \u0a28\u0a17\u0a30"
    ],
    "name:tam_x_preferred":[
        "\u0bb8\u0bcd\u0bb5\u0bbe\u0ba4\u0bbf \u0ba8\u0b95\u0bb0\u0bcd"
    ],
    "name:tel_x_preferred":[
        "\u0c38\u0c4d\u0c35\u0c3e\u0c24\u0c3f \u0c28\u0c17\u0c30\u0c4d"
    ],
    "name:urd_x_preferred":[
        "\u0633\u0648\u0627\u062a\u06cc \u0646\u06af\u0631"
    ],
    "qs:name":"Swathi Nagar",
    "qs:name_adm0":"India",
    "qs:name_adm1":"Kerala",
    "qs:photos":20,
    "qs:photos_1k":4,
    "qs:photos_9k":1,
    "qs:photos_9r":1,
    "qs:photos_all":20,
    "qs:photos_sr":1,
    "qs:placetype":"Suburb",
    "qs:pop_sr":"0",
    "wof:name":"Swathi Nagar",
    "wof:placetype":"neighbourhood"
},
  "geometry": {"coordinates":[76.94175300000001,8.482933],"type":"Point"}
}