{
  "type": "Feature",
  "properties": {
    "iso:country":"IN",
    "qs:name":"Swathi Nagar",
    "qs:name_adm0":"India",
    "qs:name_adm1":"Kerala",
    "qs:photos":20,
    "qs:photos_1k":4,
    "qs:photos_9k":1,
    "qs:photos_9r":1,
    "qs:photos_all":20,
    "qs:photos_sr":1,
    "qs:placetype":"Suburb",
    "qs:pop_sr":"0",
    "wof:name":"Swathi Nagar",
    "wof:placetype":"neighbourhood"
},
  "geometry": {"coordinates":[76.94175300000001,8.482933],"type":"Point"}
}