{
  "type": "Feature",
  "properties": {
    "iso:country":"IN",
    "ks:ks_name":"Dunatar",
    "ks:ks_pop":7,
    "ks:ks_type":"HABITATION",
    "name:eng_x_preferred":[
        "Dunatar"
    ],
    "wof:name":"Dunatar",
    "wof:placetype":"locality",
    "wof:population":7
},
  "geometry": {"coordinates":[78.036309,24.166132],"type":"Point"}
}