{
  "type": "Feature",
  "properties": {
    "iso:country":"IN",
    "ks:ks_name":"Belne Kh",
    "ks:ks_pop":664,
    "ks:ks_type":"VILLAGE",
    "name:eng_x_preferred":[
        "Belne Kh"
    ],
    "wof:name":"Belne Kh",
    "wof:placetype":"locality",
    "wof:population":664
},
  "geometry": {"coordinates":[73.703895,16.346984],"type":"Point"}
}