{
  "type": "Feature",
  "properties": {
    "gn:admin1_code":"35.0",
    "gn:admin2_code":"431.0",
    "gn:asciiname":"Poria",
    "gn:country_code":"IN",
    "gn:dem":358,
    "gn:feature_class":"P",
    "gn:feature_code":"PPL",
    "gn:name":"Poria",
    "gn:population":0,
    "gn:timezone":"Asia/Kolkata",
    "iso:country":"IN",
    "name:ceb_x_preferred":[
        "Poria"
    ],
    "name:swe_x_preferred":[
        "Poria"
    ],
    "wof:name":"Poria",
    "wof:placetype":"neighbourhood"
},
  "geometry": {"coordinates":[80.95553,24.01375],"type":"Point"}
}