{
  "type": "Feature",
  "properties": {
    "iso:country":"IN",
    "ks:ks_alt_nam":"2 am",
    "ks:ks_name":"2 Am",
    "ks:ks_pop":287,
    "ks:ks_type":"HABITATION",
    "name:eng_x_preferred":[
        "2 Am"
    ],
    "wof:name":"2 Am",
    "wof:placetype":"locality",
    "wof:population":287
},
  "geometry": {"coordinates":[72.640404,28.198153],"type":"Point"}
}