{
  "type": "Feature",
  "properties": {
    "gn:admin1_code":"11",
    "gn:admin2_code":"27.0",
    "gn:asciiname":"Jahmat Nichla",
    "gn:country_code":"IN",
    "gn:dem":1273,
    "gn:feature_class":"P",
    "gn:feature_code":"PPL",
    "gn:name":"Jahmat Nichla",
    "gn:population":0,
    "gn:timezone":"Asia/Kolkata",
    "iso:country":"IN",
    "wof:name":"Jahmat Nichla",
    "wof:placetype":"locality"
},
  "geometry": {"coordinates":[76.7932,31.53043],"type":"Point"}
}