{
  "type": "Feature",
  "properties": {
    "iso:country":"IN",
    "ks:ks_name":"Chak Khidirpur",
    "ks:ks_pop":656,
    "ks:ks_type":"VILLAGE",
    "ks:ks_uagg_main":0,
    "name:eng_x_preferred":[
        "Chak Khidirpur"
    ],
    "wof:name":"Chak Khidirpur",
    "wof:placetype":"neighbourhood",
    "wof:population":656
},
  "geometry": {"coordinates":[88.25633500000001,23.722369],"type":"Point"}
}