{
  "type": "Feature",
  "properties": {
    "iso:country":"IN",
    "ks:ks_name":"Goddemane",
    "ks:ks_pop":25,
    "ks:ks_type":"HABITATION",
    "name:eng_x_preferred":[
        "Goddemane"
    ],
    "wof:name":"Goddemane",
    "wof:placetype":"locality",
    "wof:population":25
},
  "geometry": {"coordinates":[74.651022,14.751969],"type":"Point"}
}