{
  "type": "Feature",
  "properties": {
    "iso:country":"IN",
    "ks:ks_name":"Charanpur",
    "ks:ks_pop":284,
    "ks:ks_type":"HABITATION",
    "ks:ks_uagg_main":0,
    "name:eng_x_preferred":[
        "Charanpur"
    ],
    "wof:name":"Charanpur",
    "wof:placetype":"neighbourhood",
    "wof:population":284
},
  "geometry": {"coordinates":[83.244456,27.225046],"type":"Point"}
}