{
  "type": "Feature",
  "properties": {
    "gn:admin1_code":"25.0",
    "gn:admin2_code":"631.0",
    "gn:asciiname":"Pachchiyur",
    "gn:country_code":"IN",
    "gn:dem":376,
    "gn:feature_class":"P",
    "gn:feature_code":"PPL",
    "gn:name":"Pachchiy\u016br",
    "gn:population":0,
    "gn:timezone":"Asia/Kolkata",
    "iso:country":"IN",
    "wof:name":"Pachchiyur",
    "wof:placetype":"locality"
},
  "geometry": {"coordinates":[78.51645000000001,12.39013],"type":"Point"}
}