{
  "type": "Feature",
  "properties": {
    "gn:admin1_code":"2.0",
    "gn:admin2_code":"554.0",
    "gn:asciiname":"Tirumalrajukhandriga",
    "gn:country_code":"IN",
    "gn:dem":112,
    "gn:feature_class":"P",
    "gn:feature_code":"PPL",
    "gn:name":"Tirumalr\u0101jukhandriga",
    "gn:population":0,
    "gn:timezone":"Asia/Kolkata",
    "iso:country":"IN",
    "wof:name":"Tirumalrajukhandriga",
    "wof:placetype":"neighbourhood"
},
  "geometry": {"coordinates":[79.59704000000001,13.32142],"type":"Point"}
}