{
  "type": "Feature",
  "properties": {
    "iso:country":"IN",
    "ks:ks_name":"Kulinacha",
    "ks:ks_pop":694,
    "ks:ks_type":"HABITATION",
    "name:eng_x_preferred":[
        "Kulinacha"
    ],
    "wof:name":"Kulinacha",
    "wof:placetype":"locality",
    "wof:population":694
},
  "geometry": {"coordinates":[75.536277,11.995252],"type":"Point"}
}