{
  "type": "Feature",
  "properties": {
    "iso:country":"IN",
    "ks:ks_alt_nam":"Ch\u0101prong",
    "ks:ks_name":"Chaprong",
    "ks:ks_pop":294,
    "ks:ks_type":"VILLAGE",
    "name:eng_x_preferred":[
        "Chaprong"
    ],
    "name:eng_x_variant":[
        "Ch\u0101prong"
    ],
    "wof:name":"Chaprong",
    "wof:placetype":"locality",
    "wof:population":294
},
  "geometry": {"coordinates":[84.488333,23.415003],"type":"Point"}
}