{
  "type": "Feature",
  "properties": {
    "iso:country":"IN",
    "ks:ks_name":"Jodha",
    "ks:ks_pop":220,
    "ks:ks_type":"VILLAGE",
    "name:eng_x_preferred":[
        "Jodha"
    ],
    "wof:name":"Jodha",
    "wof:placetype":"locality",
    "wof:population":220
},
  "geometry": {"coordinates":[70.786789,26.458586],"type":"Point"}
}