{
  "type": "Feature",
  "properties": {
    "iso:country":"IN",
    "ks:ks_name":"Kadwajhira",
    "ks:ks_pop":426,
    "ks:ks_type":"HABITATION",
    "name:eng_x_preferred":[
        "Kadwajhira"
    ],
    "wof:name":"Kadwajhira",
    "wof:placetype":"locality",
    "wof:population":426
},
  "geometry": {"coordinates":[75.298205,21.542591],"type":"Point"}
}