{
  "type": "Feature",
  "properties": {
    "iso:country":"IN",
    "ks:ks_name":"Bhojpur Najik",
    "ks:ks_pop":1371,
    "ks:ks_type":"VILLAGE",
    "name:eng_x_preferred":[
        "Bhojpur Najik"
    ],
    "wof:name":"Bhojpur Najik",
    "wof:placetype":"locality",
    "wof:population":1371
},
  "geometry": {"coordinates":[73.349099,21.077415],"type":"Point"}
}