{
  "type": "Feature",
  "properties": {
    "iso:country":"IN",
    "ks:ks_name":"Ala",
    "ks:ks_pop":10391,
    "ks:ks_type":"VILLAGE",
    "name:eng_x_preferred":[
        "Ala"
    ],
    "wof:name":"Ala",
    "wof:placetype":"locality",
    "wof:population":10391
},
  "geometry": {"coordinates":[76.185479,10.25365],"type":"Point"}
}