{
  "type": "Feature",
  "properties": {
    "iso:country":"IN",
    "ks:ks_name":"Shingatageri",
    "ks:ks_pop":609,
    "ks:ks_type":"VILLAGE",
    "ks:ks_uagg_main":0,
    "name:eng_x_preferred":[
        "Shingatageri"
    ],
    "wof:name":"Shingatageri",
    "wof:placetype":"neighbourhood",
    "wof:population":609
},
  "geometry": {"coordinates":[76.97479300000001,12.494724],"type":"Point"}
}