{
  "type": "Feature",
  "properties": {
    "iso:country":"IN",
    "ks:ks_name":"Pahadmadak",
    "ks:ks_pop":715,
    "ks:ks_type":"VILLAGE",
    "name:eng_x_preferred":[
        "Pahadmadak"
    ],
    "wof:name":"Pahadmadak",
    "wof:placetype":"locality",
    "wof:population":715
},
  "geometry": {"coordinates":[86.08537099999999,21.833508],"type":"Point"}
}