{
  "type": "Feature",
  "properties": {
    "iso:country":"IN",
    "ks:ks_name":"Kadari",
    "ks:ks_pop":48,
    "ks:ks_type":"VILLAGE",
    "name:eng_x_preferred":[
        "Kadari"
    ],
    "wof:name":"Kadari",
    "wof:placetype":"locality",
    "wof:population":48
},
  "geometry": {"coordinates":[83.971709,20.521006],"type":"Point"}
}