{
  "type": "Feature",
  "properties": {
    "iso:country":"IN",
    "ks:ks_name":"Goyagoan",
    "ks:ks_pop":150,
    "ks:ks_type":"HABITATION",
    "name:eng_x_preferred":[
        "Goyagoan"
    ],
    "wof:name":"Goyagoan",
    "wof:placetype":"locality",
    "wof:population":150
},
  "geometry": {"coordinates":[73.013873,18.312331],"type":"Point"}
}