{
  "type": "Feature",
  "properties": {
    "gn:admin1_code":"2.0",
    "gn:admin2_code":"549.0",
    "gn:asciiname":"Munangivaripalem",
    "gn:country_code":"IN",
    "gn:dem":28,
    "gn:feature_class":"P",
    "gn:feature_code":"PPL",
    "gn:name":"Munangiv\u0101rip\u0101lem",
    "gn:population":0,
    "gn:timezone":"Asia/Kolkata",
    "iso:country":"IN",
    "ks:ks_name":"Munnangivaripalem",
    "ks:ks_pop":481,
    "ks:ks_type":"HABITATION",
    "ks:ks_uagg_main":0,
    "name:eng_x_preferred":[
        "Munnangivaripalem"
    ],
    "wof:name":"Munnangivaripalem",
    "wof:placetype":"neighbourhood",
    "wof:population":481
},
  "geometry": {"coordinates":[80.20018,15.961094],"type":"Point"}
}