{
  "type": "Feature",
  "properties": {
    "iso:country":"IN",
    "ks:ks_name":"Handiberike",
    "ks:ks_pop":20,
    "ks:ks_type":"HABITATION",
    "name:eng_x_preferred":[
        "Handiberike"
    ],
    "wof:name":"Handiberike",
    "wof:placetype":"locality",
    "wof:population":20
},
  "geometry": {"coordinates":[75.135459,13.331411],"type":"Point"}
}