{
  "type": "Feature",
  "properties": {
    "iso:country":"IN",
    "ks:ks_alt_nam":"P\u0101lmo",
    "ks:ks_name":"Palmo",
    "ks:ks_pop":962,
    "ks:ks_type":"VILLAGE",
    "name:eng_x_preferred":[
        "Palmo"
    ],
    "name:eng_x_variant":[
        "P\u0101lmo"
    ],
    "wof:name":"Palmo",
    "wof:placetype":"locality",
    "wof:population":962
},
  "geometry": {"coordinates":[86.035707,24.599735],"type":"Point"}
}