{
  "type": "Feature",
  "properties": {
    "iso:country":"IN",
    "ks:ks_name":"Kakkemajalu",
    "ks:ks_pop":250,
    "ks:ks_type":"HABITATION",
    "name:eng_x_preferred":[
        "Kakkemajalu"
    ],
    "wof:name":"Kakkemajalu",
    "wof:placetype":"locality",
    "wof:population":250
},
  "geometry": {"coordinates":[74.904775,12.809128],"type":"Point"}
}