{
  "type": "Feature",
  "properties": {
    "gn:admin1_code":"11",
    "gn:admin2_code":"23.0",
    "gn:asciiname":"Dob",
    "gn:country_code":"IN",
    "gn:dem":1712,
    "gn:feature_class":"P",
    "gn:feature_code":"PPL",
    "gn:name":"Dob",
    "gn:population":0,
    "gn:timezone":"Asia/Kolkata",
    "iso:country":"IN",
    "name:bos_x_preferred":[
        "Dob"
    ],
    "name:ceb_x_preferred":[
        "Dob"
    ],
    "name:hun_x_preferred":[
        "Dob"
    ],
    "name:slv_x_preferred":[
        "Dob"
    ],
    "name:swe_x_preferred":[
        "Dob"
    ],
    "wof:name":"Dob",
    "wof:placetype":"locality"
},
  "geometry": {"coordinates":[76.15671999999998,32.83795],"type":"Point"}
}