{
  "type": "Feature",
  "properties": {
    "iso:country":"IN",
    "ks:ks_name":"Bhaisdehi",
    "ks:ks_pop":180,
    "ks:ks_type":"VILLAGE",
    "name:eng_x_preferred":[
        "Bhaisdehi"
    ],
    "wof:name":"Bhaisdehi",
    "wof:placetype":"locality",
    "wof:population":180
},
  "geometry": {"coordinates":[80.019722,23.314179],"type":"Point"}
}