{
  "type": "Feature",
  "properties": {
    "iso:country":"IN",
    "ks:ks_name":"Theekariya Raisinghpura",
    "ks:ks_pop":3483,
    "ks:ks_type":"VILLAGE",
    "name:eng_x_preferred":[
        "Theekariya Raisinghpura"
    ],
    "wof:name":"Theekariya Raisinghpura",
    "wof:placetype":"locality",
    "wof:population":3483
},
  "geometry": {"coordinates":[75.480594,27.441614],"type":"Point"}
}