{
  "type": "Feature",
  "properties": {
    "iso:country":"IN",
    "ks:ks_name":"Kaithakhandi",
    "ks:ks_pop":120,
    "ks:ks_type":"VILLAGE",
    "name:eng_x_preferred":[
        "Kaithakhandi"
    ],
    "wof:name":"Kaithakhandi",
    "wof:placetype":"locality",
    "wof:population":120
},
  "geometry": {"coordinates":[84.767014,19.433062],"type":"Point"}
}