{
  "type": "Feature",
  "properties": {
    "gn:admin1_code":"19.0",
    "gn:admin2_code":"573.0",
    "gn:asciiname":"Jigundipatna",
    "gn:country_code":"IN",
    "gn:dem":706,
    "gn:feature_class":"P",
    "gn:feature_code":"PPL",
    "gn:name":"Jigundipatna",
    "gn:population":0,
    "gn:timezone":"Asia/Kolkata",
    "iso:country":"IN",
    "ks:ks_name":"Jeegundipatna",
    "ks:ks_pop":1173,
    "ks:ks_type":"VILLAGE",
    "name:eng_x_preferred":[
        "Jeegundipatna"
    ],
    "name:eng_x_variant":[
        "Jigundipatna"
    ],
    "wof:name":"Jeegundipatna",
    "wof:placetype":"locality",
    "wof:population":1173
},
  "geometry": {"coordinates":[76.884469,12.592132],"type":"Point"}
}