{
  "type": "Feature",
  "properties": {
    "gn:admin1_code":"37",
    "gn:admin2_code":"403.0",
    "gn:asciiname":"Nawapara",
    "gn:country_code":"IN",
    "gn:dem":217,
    "gn:feature_class":"P",
    "gn:feature_code":"PPL",
    "gn:name":"Naw\u0101p\u0101ra",
    "gn:population":0,
    "gn:timezone":"Asia/Kolkata",
    "iso:country":"IN",
    "wof:name":"Nawapara",
    "wof:placetype":"locality"
},
  "geometry": {"coordinates":[83.35705,21.55931],"type":"Point"}
}