{
  "type": "Feature",
  "properties": {
    "iso:country":"IN",
    "ks:ks_name":"Birewadi",
    "ks:ks_pop":666,
    "ks:ks_type":"HABITATION",
    "name:eng_x_preferred":[
        "Birewadi"
    ],
    "wof:name":"Birewadi",
    "wof:placetype":"locality",
    "wof:population":666
},
  "geometry": {"coordinates":[74.236642,19.68156],"type":"Point"}
}