{
  "type": "Feature",
  "properties": {
    "iso:country":"IN",
    "ks:ks_alt_nam":"Karbali chak Beradhar",
    "ks:ks_name":"Karbali Chak Beradhar",
    "ks:ks_pop":23,
    "ks:ks_type":"HABITATION",
    "name:eng_x_preferred":[
        "Karbali Chak Beradhar"
    ],
    "wof:name":"Karbali Chak Beradhar",
    "wof:placetype":"locality",
    "wof:population":23
},
  "geometry": {"coordinates":[79.560924,30.06104],"type":"Point"}
}