{
  "type": "Feature",
  "properties": {
    "gn:country":"IN",
    "gn:fcode":"PPL",
    "gn:pop":20281,
    "iso:country":"IN",
    "name:bul_x_preferred":[
        "\u041f\u0430\u043b\u0430\u043f\u0430\u0442\u0438"
    ],
    "name:ceb_x_preferred":[
        "Pallappatti"
    ],
    "name:eng_x_preferred":[
        "Pallapatti"
    ],
    "name:fra_x_preferred":[
        "Pallapatti"
    ],
    "name:hif_x_preferred":[
        "Pallapatti"
    ],
    "name:ita_x_preferred":[
        "Pallapatti"
    ],
    "name:msa_x_preferred":[
        "Pallapatti"
    ],
    "name:nan_x_preferred":[
        "Pallapatti"
    ],
    "name:nld_x_preferred":[
        "Pallapatti"
    ],
    "name:swe_x_preferred":[
        "Pallappatti"
    ],
    "name:tam_x_preferred":[
        "pallapatti bazaar"
    ],
    "name:unk_x_variant":[
        "Pallapatti"
    ],
    "name:vie_x_preferred":[
        "Pallapatti"
    ],
    "name:zho_x_preferred":[
        "\u5e15\u62c9\u5e15\u8482"
    ],
    "qs:name":"Palapatti",
    "qs:name_adm0":"India",
    "qs:name_adm1":"Tamil Nadu",
    "qs:photos_9r":0,
    "qs:photos_sr":0,
    "qs:placetype":"Town",
    "qs:pop_sr":"7",
    "wof:name":"Palapatti",
    "wof:placetype":"locality",
    "wof:population":20281
},
  "geometry": {"coordinates":[77.87951,10.72057],"type":"Point"}
}