{
  "type": "Feature",
  "properties": {
    "iso:country":"IN",
    "ks:ks_name":"Kanbha",
    "ks:ks_pop":5109,
    "ks:ks_type":"VILLAGE",
    "ks:ks_uagg_main":0,
    "name:eng_x_preferred":[
        "Kanbha"
    ],
    "wof:name":"Kanbha",
    "wof:placetype":"neighbourhood",
    "wof:population":5109
},
  "geometry": {"coordinates":[72.728987,23.010236],"type":"Point"}
}