{
  "type": "Feature",
  "properties": {
    "iso:country":"IN",
    "ks:ks_name":"Pachhaje",
    "ks:ks_pop":510,
    "ks:ks_type":"HABITATION",
    "name:eng_x_preferred":[
        "Pachhaje"
    ],
    "wof:name":"Pachhaje",
    "wof:placetype":"locality",
    "wof:population":510
},
  "geometry": {"coordinates":[75.107519,12.918395],"type":"Point"}
}