{
  "type": "Feature",
  "properties": {
    "gn:admin1_code":"19",
    "gn:admin2_code":"556.0",
    "gn:asciiname":"Nanmanthnal",
    "gn:country_code":"IN",
    "gn:dem":508,
    "gn:feature_class":"P",
    "gn:feature_code":"PPL",
    "gn:name":"Nanmanthnal",
    "gn:population":0,
    "gn:timezone":"Asia/Kolkata",
    "iso:country":"IN",
    "wof:name":"Nanmanthnal",
    "wof:placetype":"locality"
},
  "geometry": {"coordinates":[76.18590999999998,16.11493],"type":"Point"}
}