{
  "type": "Feature",
  "properties": {
    "iso:country":"IN",
    "ks:ks_alt_nam":"GURLI BARANI",
    "ks:ks_name":"Gurli Barani",
    "ks:ks_pop":13,
    "ks:ks_type":"HABITATION",
    "name:eng_x_preferred":[
        "Gurli Barani"
    ],
    "wof:name":"Gurli Barani",
    "wof:placetype":"locality",
    "wof:population":13
},
  "geometry": {"coordinates":[73.53973499999999,29.038774],"type":"Point"}
}