{
  "type": "Feature",
  "properties": {
    "iso:country":"IN",
    "ks:ks_name":"Adadihi",
    "ks:ks_pop":227,
    "ks:ks_type":"VILLAGE",
    "name:eng_x_preferred":[
        "Adadihi"
    ],
    "wof:name":"Adadihi",
    "wof:placetype":"locality",
    "wof:population":227
},
  "geometry": {"coordinates":[84.864135,21.713885],"type":"Point"}
}