{
  "type": "Feature",
  "properties": {
    "iso:country":"IN",
    "ks:ks_name":"Shashimane",
    "ks:ks_pop":62,
    "ks:ks_type":"HABITATION",
    "name:eng_x_preferred":[
        "Shashimane"
    ],
    "wof:name":"Shashimane",
    "wof:placetype":"locality",
    "wof:population":62
},
  "geometry": {"coordinates":[74.720624,14.625313],"type":"Point"}
}