{
  "type": "Feature",
  "properties": {
    "iso:country":"IN",
    "ks:ks_name":"Gaudadanda",
    "ks:ks_pop":356,
    "ks:ks_type":"VILLAGE",
    "ks:ks_uagg_main":0,
    "name:eng_x_preferred":[
        "Gaudadanda"
    ],
    "wof:name":"Gaudadanda",
    "wof:placetype":"neighbourhood",
    "wof:population":356
},
  "geometry": {"coordinates":[86.877661,21.533645],"type":"Point"}
}