{
  "type": "Feature",
  "properties": {
    "iso:country":"IN",
    "ks:ks_name":"Oupada",
    "ks:ks_pop":167,
    "ks:ks_type":"VILLAGE",
    "name:eng_x_preferred":[
        "Oupada"
    ],
    "wof:name":"Oupada",
    "wof:placetype":"locality",
    "wof:population":167
},
  "geometry": {"coordinates":[86.199865,20.921423],"type":"Point"}
}