{
  "type": "Feature",
  "properties": {
    "iso:country":"IN",
    "ks:ks_alt_nam":"KAYASTH TOLA",
    "ks:ks_name":"Kayasth Tola",
    "ks:ks_pop":114,
    "ks:ks_type":"HABITATION",
    "ks:ks_uagg_main":0,
    "name:eng_x_preferred":[
        "Kayasth Tola"
    ],
    "wof:name":"Kayasth Tola",
    "wof:placetype":"neighbourhood",
    "wof:population":114
},
  "geometry": {"coordinates":[87.32008999999999,25.89098],"type":"Point"}
}