{
  "type": "Feature",
  "properties": {
    "gn:admin1_code":"39.0",
    "gn:admin2_code":"64.0",
    "gn:asciiname":"Jharigaon",
    "gn:country_code":"IN",
    "gn:dem":800,
    "gn:feature_class":"P",
    "gn:feature_code":"PPL",
    "gn:name":"Jhar\u012bgaon",
    "gn:population":0,
    "gn:timezone":"Asia/Kolkata",
    "iso:country":"IN",
    "ks:ks_name":"Jhargaon",
    "ks:ks_pop":504,
    "ks:ks_type":"VILLAGE",
    "name:eng_x_preferred":[
        "Jhargaon"
    ],
    "name:eng_x_variant":[
        "Jharigaon"
    ],
    "wof:name":"Jhargaon",
    "wof:placetype":"locality",
    "wof:population":504
},
  "geometry": {"coordinates":[79.110108,29.611192],"type":"Point"}
}