{
  "type": "Feature",
  "properties": {
    "iso:country":"IN",
    "ks:ks_name":"Mudhapur",
    "ks:ks_pop":0,
    "ks:ks_type":"VILLAGE",
    "name:eng_x_preferred":[
        "Mudhapur"
    ],
    "wof:name":"Mudhapur",
    "wof:placetype":"locality",
    "wof:population":0
},
  "geometry": {"coordinates":[78.537239,20.391043],"type":"Point"}
}