{
  "type": "Feature",
  "properties": {
    "iso:country":"IN",
    "ks:ks_name":"Chamtadih",
    "ks:ks_pop":555,
    "ks:ks_type":"HABITATION",
    "name:eng_x_preferred":[
        "Chamtadih"
    ],
    "wof:name":"Chamtadih",
    "wof:placetype":"locality",
    "wof:population":555
},
  "geometry": {"coordinates":[86.082857,24.441422],"type":"Point"}
}