{
  "type": "Feature",
  "properties": {
    "iso:country":"IN",
    "ks:ks_name":"Ambagadia",
    "ks:ks_pop":66,
    "ks:ks_type":"VILLAGE",
    "name:eng_x_preferred":[
        "Ambagadia"
    ],
    "wof:name":"Ambagadia",
    "wof:placetype":"locality",
    "wof:population":66
},
  "geometry": {"coordinates":[86.993405,21.669016],"type":"Point"}
}