{
  "type": "Feature",
  "properties": {
    "iso:country":"IN",
    "ks:ks_name":"Gadadharpur",
    "ks:ks_pop":425,
    "ks:ks_type":"VILLAGE",
    "ks:ks_uagg_main":0,
    "name:eng_x_preferred":[
        "Gadadharpur"
    ],
    "wof:name":"Gadadharpur",
    "wof:placetype":"neighbourhood",
    "wof:population":425
},
  "geometry": {"coordinates":[87.620015,23.822455],"type":"Point"}
}