{
  "type": "Feature",
  "properties": {
    "iso:country":"IN",
    "ks:ks_alt_nam":"Daspara Guria par",
    "ks:ks_name":"Daspara Guria Par",
    "ks:ks_pop":705,
    "ks:ks_type":"HABITATION",
    "name:eng_x_preferred":[
        "Daspara Guria Par"
    ],
    "wof:name":"Daspara Guria Par",
    "wof:placetype":"locality",
    "wof:population":705
},
  "geometry": {"coordinates":[89.651386,26.358085],"type":"Point"}
}