{
  "type": "Feature",
  "properties": {
    "iso:country":"IN",
    "ks:ks_name":"Old Munnar",
    "ks:ks_pop":1876,
    "ks:ks_type":"HABITATION",
    "name:eng_x_preferred":[
        "Old Munnar"
    ],
    "wof:name":"Old Munnar",
    "wof:placetype":"neighbourhood",
    "wof:population":1876
},
  "geometry": {"coordinates":[77.061961,10.079266],"type":"Point"}
}