{
  "type": "Feature",
  "properties": {
    "iso:country":"IN",
    "ks:ks_name":"Jenukolli Hoskeri Maragodu Road",
    "ks:ks_pop":249,
    "ks:ks_type":"HABITATION",
    "name:eng_x_preferred":[
        "Jenukolli Hoskeri Maragodu Road"
    ],
    "wof:name":"Jenukolli Hoskeri Maragodu Road",
    "wof:placetype":"locality",
    "wof:population":249
},
  "geometry": {"coordinates":[75.822512,12.347561],"type":"Point"}
}