{
  "type": "Feature",
  "properties": {
    "gn:admin1_code":"12",
    "gn:admin2_code":"15.0",
    "gn:asciiname":"Naupur Tsulyand",
    "gn:country_code":"IN",
    "gn:dem":1822,
    "gn:feature_class":"P",
    "gn:feature_code":"PPL",
    "gn:name":"Naup\u016br Tsulyand",
    "gn:population":0,
    "gn:timezone":"Asia/Kolkata",
    "iso:country":"IN",
    "wof:name":"Naupur Tsulyand",
    "wof:placetype":"locality"
},
  "geometry": {"coordinates":[74.96254,33.69078],"type":"Point"}
}