{
  "type": "Feature",
  "properties": {
    "iso:country":"IN",
    "ks:ks_alt_nam":"SUIJORE",
    "ks:ks_name":"Suijore",
    "ks:ks_pop":229,
    "ks:ks_type":"HABITATION",
    "name:eng_x_preferred":[
        "Suijore"
    ],
    "wof:name":"Suijore",
    "wof:placetype":"locality",
    "wof:population":229
},
  "geometry": {"coordinates":[83.75843500000001,22.663086],"type":"Point"}
}