{
  "type": "Feature",
  "properties": {
    "iso:country":"IN",
    "ks:ks_name":"Satyanarayanapuram",
    "ks:ks_pop":477,
    "ks:ks_type":"HABITATION",
    "name:eng_x_preferred":[
        "Satyanarayanapuram"
    ],
    "wof:name":"Satyanarayanapuram",
    "wof:placetype":"locality",
    "wof:population":477
},
  "geometry": {"coordinates":[81.43640499999999,16.485984],"type":"Point"}
}