{
  "type": "Feature",
  "properties": {
    "gn:admin1_code":"11",
    "gn:admin2_code":"24.0",
    "gn:asciiname":"Badehr",
    "gn:country_code":"IN",
    "gn:dem":563,
    "gn:feature_class":"P",
    "gn:feature_code":"PPL",
    "gn:name":"Badehr",
    "gn:population":0,
    "gn:timezone":"Asia/Kolkata",
    "iso:country":"IN",
    "wof:name":"Badehr",
    "wof:placetype":"locality"
},
  "geometry": {"coordinates":[76.03971999999997,32.26441],"type":"Point"}
}