{
  "type": "Feature",
  "properties": {
    "iso:country":"IN",
    "ks:ks_name":"Bamhni",
    "ks:ks_pop":197,
    "ks:ks_type":"VILLAGE",
    "ks:ks_uagg_main":0,
    "name:eng_x_preferred":[
        "Bamhni"
    ],
    "wof:name":"Bamhni",
    "wof:placetype":"neighbourhood",
    "wof:population":197
},
  "geometry": {"coordinates":[85.38655799999999,23.948386],"type":"Point"}
}