{
  "type": "Feature",
  "properties": {
    "iso:country":"IN",
    "ks:ks_name":"Barh Tatarsingh Chak No 1",
    "ks:ks_pop":60,
    "ks:ks_type":"VILLAGE",
    "name:eng_x_preferred":[
        "Barh Tatarsingh Chak No 1"
    ],
    "wof:name":"Barh Tatarsingh Chak No 1",
    "wof:placetype":"locality",
    "wof:population":60
},
  "geometry": {"coordinates":[76.293869,26.537683],"type":"Point"}
}