{
  "type": "Feature",
  "properties": {
    "iso:country":"IN",
    "ks:ks_name":"Dhangergudi",
    "ks:ks_pop":579,
    "ks:ks_type":"VILLAGE",
    "name:eng_x_preferred":[
        "Dhangergudi"
    ],
    "wof:name":"Dhangergudi",
    "wof:placetype":"locality",
    "wof:population":579
},
  "geometry": {"coordinates":[83.77735300000001,22.239256],"type":"Point"}
}