{
  "type": "Feature",
  "properties": {
    "iso:country":"IN",
    "ks:ks_name":"Ousana",
    "ks:ks_pop":102,
    "ks:ks_type":"VILLAGE",
    "name:eng_x_preferred":[
        "Ousana"
    ],
    "wof:name":"Ousana",
    "wof:placetype":"locality",
    "wof:population":102
},
  "geometry": {"coordinates":[75.57388899999999,13.096041],"type":"Point"}
}