{
  "type": "Feature",
  "properties": {
    "gn:admin1_code":"21.0",
    "gn:admin2_code":"396.0",
    "gn:asciiname":"Kumbarisingi",
    "gn:country_code":"IN",
    "gn:dem":373,
    "gn:feature_class":"P",
    "gn:feature_code":"PPL",
    "gn:name":"Kumbarisingi",
    "gn:population":0,
    "gn:timezone":"Asia/Kolkata",
    "iso:country":"IN",
    "wof:name":"Kumbarisingi",
    "wof:placetype":"locality"
},
  "geometry": {"coordinates":[83.93689999999999,19.06492],"type":"Point"}
}