{
  "type": "Feature",
  "properties": {
    "gn:admin1_code":"39.0",
    "gn:admin2_code":"64.0",
    "gn:asciiname":"Kalesim",
    "gn:country_code":"IN",
    "gn:dem":1222,
    "gn:feature_class":"P",
    "gn:feature_code":"PPL",
    "gn:name":"Kalesim",
    "gn:population":0,
    "gn:timezone":"Asia/Kolkata",
    "iso:country":"IN",
    "ks:ks_name":"Kalesim",
    "ks:ks_type":"VILLAGE",
    "name:eng_x_preferred":[
        "Kalesim"
    ],
    "wof:name":"Kalesim",
    "wof:placetype":"locality"
},
  "geometry": {"coordinates":[79.666152,29.530042],"type":"Point"}
}