{
  "type": "Feature",
  "properties": {
    "gn:admin1_code":"36",
    "gn:admin2_code":"194.0",
    "gn:asciiname":"Puralal",
    "gn:country_code":"IN",
    "gn:dem":95,
    "gn:feature_class":"P",
    "gn:feature_code":"PPL",
    "gn:name":"Pur\u0101l\u0101l",
    "gn:population":0,
    "gn:timezone":"Asia/Kolkata",
    "iso:country":"IN",
    "ks:ks_name":"Pure Lal",
    "ks:ks_pop":842,
    "ks:ks_type":"VILLAGE",
    "name:eng_x_preferred":[
        "Pure Lal"
    ],
    "name:eng_x_variant":[
        "Puralal"
    ],
    "wof:name":"Pure Lal",
    "wof:placetype":"locality",
    "wof:population":842
},
  "geometry": {"coordinates":[82.233299,25.606252],"type":"Point"}
}