{
  "type": "Feature",
  "properties": {
    "iso:country":"IN",
    "ks:ks_name":"Kotwal Falia",
    "ks:ks_pop":667,
    "ks:ks_type":"HABITATION",
    "name:eng_x_preferred":[
        "Kotwal Falia"
    ],
    "wof:name":"Kotwal Falia",
    "wof:placetype":"locality",
    "wof:population":667
},
  "geometry": {"coordinates":[74.42533299999999,22.857417],"type":"Point"}
}