{
  "type": "Feature",
  "properties": {
    "iso:country":"IN",
    "ks:ks_name":"Bahadur Bigha",
    "ks:ks_pop":413,
    "ks:ks_type":"HABITATION",
    "ks:ks_uagg_main":0,
    "name:eng_x_preferred":[
        "Bahadur Bigha"
    ],
    "wof:name":"Bahadur Bigha",
    "wof:placetype":"neighbourhood",
    "wof:population":413
},
  "geometry": {"coordinates":[84.77256,24.931759],"type":"Point"}
}