{
  "type": "Feature",
  "properties": {
    "iso:country":"IN",
    "ks:ks_alt_nam":"CHAMAR TOLA",
    "ks:ks_name":"Chamar Tola",
    "ks:ks_pop":38,
    "ks:ks_type":"HABITATION",
    "name:eng_x_preferred":[
        "Chamar Tola"
    ],
    "wof:name":"Chamar Tola",
    "wof:placetype":"locality",
    "wof:population":38
},
  "geometry": {"coordinates":[85.980109,25.484098],"type":"Point"}
}