{
  "type": "Feature",
  "properties": {
    "iso:country":"IN",
    "ks:ks_name":"Kamalapur",
    "ks:ks_pop":4195,
    "ks:ks_type":"VILLAGE",
    "ks:ks_uagg_main":0,
    "name:eng_x_preferred":[
        "Kamalapur"
    ],
    "wof:name":"Kamalapur",
    "wof:placetype":"neighbourhood",
    "wof:population":4195
},
  "geometry": {"coordinates":[88.140372,22.674666],"type":"Point"}
}