{
  "type": "Feature",
  "properties": {
    "iso:country":"IN",
    "ks:ks_name":"Ganeshi Bigha",
    "ks:ks_pop":363,
    "ks:ks_type":"HABITATION",
    "name:eng_x_preferred":[
        "Ganeshi Bigha"
    ],
    "wof:name":"Ganeshi Bigha",
    "wof:placetype":"locality",
    "wof:population":363
},
  "geometry": {"coordinates":[85.01547600000001,24.927876],"type":"Point"}
}