{
  "type": "Feature",
  "properties": {
    "iso:country":"IN",
    "ks:ks_name":"Gori Mati",
    "ks:ks_pop":135,
    "ks:ks_type":"VILLAGE",
    "name:eng_x_preferred":[
        "Gori Mati"
    ],
    "wof:name":"Gori Mati",
    "wof:placetype":"locality",
    "wof:population":135
},
  "geometry": {"coordinates":[80.438126,22.610657],"type":"Point"}
}