{
  "type": "Feature",
  "properties": {
    "iso:country":"IN",
    "ks:ks_alt_nam":"Mulism vattam",
    "ks:ks_name":"Mulism Vattam",
    "ks:ks_pop":263,
    "ks:ks_type":"HABITATION",
    "name:eng_x_preferred":[
        "Mulism Vattam"
    ],
    "wof:name":"Mulism Vattam",
    "wof:placetype":"locality",
    "wof:population":263
},
  "geometry": {"coordinates":[78.455715,12.453442],"type":"Point"}
}