{
  "type": "Feature",
  "properties": {
    "gn:admin1_code":"21",
    "gn:admin2_code":"370.0",
    "gn:asciiname":"Haldipali",
    "gn:country_code":"IN",
    "gn:dem":218,
    "gn:feature_class":"P",
    "gn:feature_code":"PPL",
    "gn:name":"Haldip\u0101li",
    "gn:population":0,
    "gn:timezone":"Asia/Kolkata",
    "iso:country":"IN",
    "wof:name":"Haldipali",
    "wof:placetype":"locality"
},
  "geometry": {"coordinates":[83.4209,21.30319],"type":"Point"}
}