{
  "type": "Feature",
  "properties": {
    "gn:admin1_code":"13.0",
    "gn:asciiname":"Nandangudi",
    "gn:country_code":"IN",
    "gn:dem":930,
    "gn:feature_class":"P",
    "gn:feature_code":"PPL",
    "gn:name":"Nandangudi",
    "gn:population":0,
    "gn:timezone":"Asia/Kolkata",
    "iso:country":"IN",
    "wof:name":"Nandangudi",
    "wof:placetype":"locality"
},
  "geometry": {"coordinates":[76.33929000000001,11.58931],"type":"Point"}
}