{
  "type": "Feature",
  "properties": {
    "gn:admin1_code":"11",
    "gn:admin2_code":"25.0",
    "gn:asciiname":"Salpat",
    "gn:country_code":"IN",
    "gn:dem":2692,
    "gn:feature_class":"P",
    "gn:feature_code":"PPL",
    "gn:name":"Salpat",
    "gn:population":0,
    "gn:timezone":"Asia/Kolkata",
    "iso:country":"IN",
    "wof:name":"Salpat",
    "wof:placetype":"locality"
},
  "geometry": {"coordinates":[76.64360000000001,32.72929],"type":"Point"}
}