{
  "type": "Feature",
  "properties": {
    "iso:country":"IN",
    "ks:ks_name":"Sivalingapuram",
    "ks:ks_pop":107,
    "ks:ks_type":"HABITATION",
    "name:eng_x_preferred":[
        "Sivalingapuram"
    ],
    "wof:name":"Sivalingapuram",
    "wof:placetype":"locality",
    "wof:population":107
},
  "geometry": {"coordinates":[79.53232300000001,14.001815],"type":"Point"}
}