{
  "type": "Feature",
  "properties": {
    "iso:country":"IN",
    "ks:ks_name":"Henne",
    "ks:ks_pop":255,
    "ks:ks_type":"HABITATION",
    "name:eng_x_preferred":[
        "Henne"
    ],
    "wof:name":"Henne",
    "wof:placetype":"locality",
    "wof:population":255
},
  "geometry": {"coordinates":[74.76608899999999,14.224152],"type":"Point"}
}