{
  "type": "Feature",
  "properties": {
    "gn:admin1_code":"38.0",
    "gn:admin2_code":"355.0",
    "gn:asciiname":"Phusro",
    "gn:country_code":"IN",
    "gn:dem":217,
    "gn:feature_class":"P",
    "gn:feature_code":"PPL",
    "gn:name":"Phusro",
    "gn:population":0,
    "gn:timezone":"Asia/Kolkata",
    "iso:country":"IN",
    "name:bih_x_preferred":[
        "\u092b\u0941\u0938\u0930\u094b"
    ],
    "name:bpy_x_preferred":[
        "\u09ab\u09c1\u09b8\u09b0\u09cb"
    ],
    "name:deu_x_preferred":[
        "Phusro"
    ],
    "name:fra_x_preferred":[
        "Phusro"
    ],
    "name:hif_x_preferred":[
        "Phusro"
    ],
    "name:ita_x_preferred":[
        "Phusro"
    ],
    "name:msa_x_preferred":[
        "Phusro"
    ],
    "name:nld_x_preferred":[
        "Phusro"
    ],
    "name:ori_x_preferred":[
        "\u0b2b\u0b41\u0b38\u0b4d\u0b30\u0b4b"
    ],
    "name:pnb_x_preferred":[
        "\u067e\u06be\u064f\u0633\u0631\u0648"
    ],
    "name:por_x_preferred":[
        "Phusro"
    ],
    "name:spa_x_preferred":[
        "Phusro"
    ],
    "name:swe_x_preferred":[
        "Phusro"
    ],
    "name:vie_x_preferred":[
        "Phusro"
    ],
    "name:war_x_preferred":[
        "Phusro"
    ],
    "name:zho_x_preferred":[
        "\u666e\u65af\u7f57"
    ],
    "wof:name":"Phusro",
    "wof:placetype":"locality"
},
  "geometry": {"coordinates":[86.0051,23.75644],"type":"Point"}
}