{
  "type": "Feature",
  "properties": {
    "gn:admin1_code":"38.0",
    "gn:admin2_code":"355.0",
    "gn:asciiname":"Phusro",
    "gn:country_code":"IN",
    "gn:dem":217,
    "gn:feature_class":"P",
    "gn:feature_code":"PPL",
    "gn:name":"Phusro",
    "gn:population":0,
    "gn:timezone":"Asia/Kolkata",
    "iso:country":"IN",
    "wof:name":"Phusro",
    "wof:placetype":"locality"
},
  "geometry": {"coordinates":[86.0051,23.75644],"type":"Point"}
}