{
  "type": "Feature",
  "properties": {
    "iso:country":"IN",
    "ks:ks_alt_nam":"SHINDE WASTI KALAWAL MALA",
    "ks:ks_name":"Shinde Wasti Kalawal Mala",
    "ks:ks_pop":117,
    "ks:ks_type":"HABITATION",
    "name:eng_x_preferred":[
        "Shinde Wasti Kalawal Mala"
    ],
    "wof:name":"Shinde Wasti Kalawal Mala",
    "wof:placetype":"locality",
    "wof:population":117
},
  "geometry": {"coordinates":[75.020071,17.223571],"type":"Point"}
}