{
  "type": "Feature",
  "properties": {
    "gn:admin1_code":"24",
    "gn:admin2_code":"114.0",
    "gn:asciiname":"Tejrawa",
    "gn:country_code":"IN",
    "gn:dem":156,
    "gn:feature_class":"P",
    "gn:feature_code":"PPL",
    "gn:name":"Tejr\u0101wa",
    "gn:population":0,
    "gn:timezone":"Asia/Kolkata",
    "iso:country":"IN",
    "ks:ks_alt_nam":"Tejr\u0101wa",
    "ks:ks_name":"Tejrawa",
    "ks:ks_pop":1006,
    "ks:ks_type":"VILLAGE",
    "name:eng_x_preferred":[
        "Tejrawa"
    ],
    "name:eng_x_variant":[
        "Tejr\u0101wa"
    ],
    "wof:name":"Tejrawa",
    "wof:placetype":"locality",
    "wof:population":1006
},
  "geometry": {"coordinates":[70.64255799999999,26.240444],"type":"Point"}
}