{
  "type": "Feature",
  "properties": {
    "iso:country":"IN",
    "ks:ks_alt_nam":"DHALEHAKE",
    "ks:ks_name":"Dhalehake",
    "ks:ks_pop":125,
    "ks:ks_type":"HABITATION",
    "name:eng_x_preferred":[
        "Dhalehake"
    ],
    "wof:name":"Dhalehake",
    "wof:placetype":"locality",
    "wof:population":125
},
  "geometry": {"coordinates":[74.939854,17.0207],"type":"Point"}
}