{
  "type": "Feature",
  "properties": {
    "iso:country":"IN",
    "ks:ks_name":"Thulluvan Kuppam",
    "ks:ks_pop":215,
    "ks:ks_type":"HABITATION",
    "name:eng_x_preferred":[
        "Thulluvan Kuppam"
    ],
    "wof:name":"Thulluvan Kuppam",
    "wof:placetype":"locality",
    "wof:population":215
},
  "geometry": {"coordinates":[79.64113999999999,11.572741],"type":"Point"}
}