{
  "type": "Feature",
  "properties": {
    "gn:admin1_code":"19.0",
    "gn:admin2_code":"576.0",
    "gn:asciiname":"Mayamudi",
    "gn:country_code":"IN",
    "gn:dem":870,
    "gn:feature_class":"P",
    "gn:feature_code":"PPLL",
    "gn:name":"Mayamudi",
    "gn:population":0,
    "gn:timezone":"Asia/Kolkata",
    "iso:country":"IN",
    "ks:ks_name":"Mayamudi",
    "ks:ks_pop":2474,
    "ks:ks_type":"VILLAGE",
    "name:eng_x_preferred":[
        "Mayamudi"
    ],
    "wof:name":"Mayamudi",
    "wof:placetype":"locality",
    "wof:population":2474
},
  "geometry": {"coordinates":[75.972032,12.184537],"type":"Point"}
}