{
  "type": "Feature",
  "properties": {
    "iso:country":"IN",
    "ks:ks_alt_nam":"CHOPADEWASTI",
    "ks:ks_name":"Chopadewasti",
    "ks:ks_pop":77,
    "ks:ks_type":"HABITATION",
    "name:eng_x_preferred":[
        "Chopadewasti"
    ],
    "wof:name":"Chopadewasti",
    "wof:placetype":"locality",
    "wof:population":77
},
  "geometry": {"coordinates":[74.70079699999999,17.174785],"type":"Point"}
}