{
  "type": "Feature",
  "properties": {
    "iso:country":"IN",
    "ks:ks_name":"Ramapadar",
    "ks:ks_pop":148,
    "ks:ks_type":"VILLAGE",
    "name:eng_x_preferred":[
        "Ramapadar"
    ],
    "wof:name":"Ramapadar",
    "wof:placetype":"locality",
    "wof:population":148
},
  "geometry": {"coordinates":[81.783237,18.335829],"type":"Point"}
}