{
  "type": "Feature",
  "properties": {
    "gn:admin1_code":"36.0",
    "gn:admin2_code":"182.0",
    "gn:asciiname":"Udhauli",
    "gn:country_code":"IN",
    "gn:dem":103,
    "gn:feature_class":"P",
    "gn:feature_code":"PPL",
    "gn:name":"Udhauli",
    "gn:population":0,
    "gn:timezone":"Asia/Kolkata",
    "iso:country":"IN",
    "name:nep_x_preferred":[
        "\u0909\u0927\u094c\u0932\u0940"
    ],
    "wof:name":"Udhauli",
    "wof:placetype":"locality"
},
  "geometry": {"coordinates":[82.38261,27.11147],"type":"Point"}
}