{
  "type": "Feature",
  "properties": {
    "iso:country":"IN",
    "ks:ks_name":"Gardawada",
    "ks:ks_pop":848,
    "ks:ks_type":"HABITATION",
    "name:eng_x_preferred":[
        "Gardawada"
    ],
    "wof:name":"Gardawada",
    "wof:placetype":"locality",
    "wof:population":848
},
  "geometry": {"coordinates":[74.774244,22.503016],"type":"Point"}
}