{
  "type": "Feature",
  "properties": {
    "iso:country":"IN",
    "ks:ks_name":"Bylahalli",
    "ks:ks_pop":36,
    "ks:ks_type":"HABITATION",
    "name:eng_x_preferred":[
        "Bylahalli"
    ],
    "wof:name":"Bylahalli",
    "wof:placetype":"locality",
    "wof:population":36
},
  "geometry": {"coordinates":[77.79797000000001,12.818558],"type":"Point"}
}