{
  "type": "Feature",
  "properties": {
    "iso:country":"IN",
    "ks:ks_name":"Giridhan Para",
    "ks:ks_pop":98,
    "ks:ks_type":"HABITATION",
    "ks:ks_uagg_main":0,
    "name:eng_x_preferred":[
        "Giridhan Para"
    ],
    "wof:name":"Giridhan Para",
    "wof:placetype":"neighbourhood",
    "wof:population":98
},
  "geometry": {"coordinates":[91.912218,23.460031],"type":"Point"}
}