{
  "type": "Feature",
  "properties": {
    "iso:country":"IN",
    "ks:ks_name":"Chiragichak",
    "ks:ks_pop":232,
    "ks:ks_type":"VILLAGE",
    "ks:ks_uagg_main":0,
    "name:eng_x_preferred":[
        "Chiragichak"
    ],
    "wof:name":"Chiragichak",
    "wof:placetype":"neighbourhood",
    "wof:population":232
},
  "geometry": {"coordinates":[87.08852899999999,25.07516],"type":"Point"}
}