{
  "type": "Feature",
  "properties": {
    "gn:admin1_code":"35",
    "gn:admin2_code":"430.0",
    "gn:asciiname":"Amarah",
    "gn:country_code":"IN",
    "gn:dem":419,
    "gn:feature_class":"P",
    "gn:feature_code":"PPL",
    "gn:name":"Amar\u0101h",
    "gn:population":0,
    "gn:timezone":"Asia/Kolkata",
    "iso:country":"IN",
    "name:ara_x_preferred":[
        "\u0627\u0644\u0639\u0645\u0627\u0631\u0629"
    ],
    "name:arz_x_preferred":[
        "\u0627\u0644\u0639\u0645\u0627\u0631\u0647"
    ],
    "name:bel_x_preferred":[
        "\u042d\u043b\u044c-\u0410\u043c\u0430\u0440\u0430"
    ],
    "name:ben_x_preferred":[
        "\u0986\u09ae\u09be\u09b0\u09be\u09b9"
    ],
    "name:cat_x_preferred":[
        "Amara"
    ],
    "name:ceb_x_preferred":[
        "Al \u2018Am\u0101rah"
    ],
    "name:dan_x_preferred":[
        "Amarah"
    ],
    "name:deu_x_preferred":[
        "Amara"
    ],
    "name:epo_x_preferred":[
        "Amara"
    ],
    "name:est_x_preferred":[
        "Al-\u2018Am\u0101rah"
    ],
    "name:eus_x_preferred":[
        "Amara"
    ],
    "name:fas_x_preferred":[
        "\u0639\u0645\u0627\u0631\u0647"
    ],
    "name:fin_x_preferred":[
        "Amara"
    ],
    "name:fra_x_preferred":[
        "Al-Amara"
    ],
    "name:hin_x_preferred":[
        "\u0905\u092e\u093e\u0930\u093e\u0939"
    ],
    "name:hun_x_preferred":[
        "Am\u00e1ra"
    ],
    "name:ind_x_preferred":[
        "Al-'Amarah"
    ],
    "name:ita_x_preferred":[
        "Al-'Amara"
    ],
    "name:kat_x_preferred":[
        "\u10d4\u10da-\u10d0\u10db\u10d0\u10e0\u10d0"
    ],
    "name:kaz_x_preferred":[
        "\u042d\u043b\u044c-\u0410\u043c\u0430\u0440\u0430 \u049b\u0430\u043b\u0430\u0441\u044b"
    ],
    "name:kor_x_preferred":[
        "\uc544\ub9c8\ub77c"
    ],
    "name:lit_x_preferred":[
        "Amara"
    ],
    "name:msa_x_preferred":[
        "Al-'Amarah"
    ],
    "name:mzn_x_preferred":[
        "\u0627\u0644\u0639\u0645\u0627\u0631\u0647"
    ],
    "name:nld_x_preferred":[
        "Amarah"
    ],
    "name:nor_x_preferred":[
        "Al-Amarah"
    ],
    "name:pnb_x_preferred":[
        "\u0639\u0645\u0627\u0631\u0627\u06c1"
    ],
    "name:pol_x_preferred":[
        "Al-Amara"
    ],
    "name:ron_x_preferred":[
        "Amarah"
    ],
    "name:rus_x_preferred":[
        "\u042d\u043b\u044c-\u0410\u043c\u0430\u0440\u0430"
    ],
    "name:spa_x_preferred":[
        "Amara"
    ],
    "name:swe_x_preferred":[
        "Al-Amara"
    ],
    "name:tur_x_preferred":[
        "Amara"
    ],
    "name:ukr_x_preferred":[
        "\u0415\u043b\u044c-\u0410\u043c\u0430\u0440\u0430"
    ],
    "name:urd_x_preferred":[
        "\u0627\u0644\u0639\u0645\u0627\u0631\u06c1"
    ],
    "name:war_x_preferred":[
        "Amarah"
    ],
    "name:zho_x_preferred":[
        "\u963f\u9a6c\u62c9"
    ],
    "wof:name":"Amarah",
    "wof:placetype":"locality"
},
  "geometry": {"coordinates":[81.91726,24.5914],"type":"Point"}
}