{
  "type": "Feature",
  "properties": {
    "gn:admin1_code":"11",
    "gn:admin2_code":"33.0",
    "gn:asciiname":"Badhog",
    "gn:country_code":"IN",
    "gn:dem":1739,
    "gn:feature_class":"P",
    "gn:feature_code":"PPL",
    "gn:name":"Badhog",
    "gn:population":0,
    "gn:timezone":"Asia/Kolkata",
    "iso:country":"IN",
    "wof:name":"Badhog",
    "wof:placetype":"locality"
},
  "geometry": {"coordinates":[77.15269000000001,31.03502000000001],"type":"Point"}
}