{
  "type": "Feature",
  "properties": {
    "gn:admin1_code":"19.0",
    "gn:admin2_code":"583.0",
    "gn:asciiname":"Shettarhalli",
    "gn:country_code":"IN",
    "gn:dem":907,
    "gn:feature_class":"P",
    "gn:feature_code":"PPL",
    "gn:name":"Shettarhalli",
    "gn:population":0,
    "gn:timezone":"Asia/Kolkata",
    "iso:country":"IN",
    "wof:name":"Shettarhalli",
    "wof:placetype":"locality"
},
  "geometry": {"coordinates":[77.67681,13.26243],"type":"Point"}
}