{
  "type": "Feature",
  "properties": {
    "gn:admin1_code":"9.0",
    "gn:admin2_code":"472.0",
    "gn:asciiname":"Bhempur",
    "gn:country_code":"IN",
    "gn:dem":192,
    "gn:feature_class":"P",
    "gn:feature_code":"PPL",
    "gn:name":"Bhempur",
    "gn:population":0,
    "gn:timezone":"Asia/Kolkata",
    "iso:country":"IN",
    "wof:name":"Bhempur",
    "wof:placetype":"locality"
},
  "geometry": {"coordinates":[73.59636,23.57136],"type":"Point"}
}