{
  "type": "Feature",
  "properties": {
    "gn:admin1_code":"19",
    "gn:admin2_code":"579.0",
    "gn:asciiname":"Kansur",
    "gn:country_code":"IN",
    "gn:dem":425,
    "gn:feature_class":"P",
    "gn:feature_code":"PPL",
    "gn:name":"Kans\u016br",
    "gn:population":0,
    "gn:timezone":"Asia/Kolkata",
    "iso:country":"IN",
    "wof:name":"Kansur",
    "wof:placetype":"neighbourhood"
},
  "geometry": {"coordinates":[77.10334,17.35284],"type":"Point"}
}