{
  "type": "Feature",
  "properties": {
    "iso:country":"IN",
    "ks:ks_name":"Chidiyani",
    "ks:ks_pop":84,
    "ks:ks_type":"HABITATION",
    "name:eng_x_preferred":[
        "Chidiyani"
    ],
    "wof:name":"Chidiyani",
    "wof:placetype":"locality",
    "wof:population":84
},
  "geometry": {"coordinates":[78.898366,29.731206],"type":"Point"}
}