{
  "type": "Feature",
  "properties": {
    "iso:country":"IN",
    "ks:ks_alt_nam":"WARNA NADI",
    "ks:ks_name":"Warna Nadi",
    "ks:ks_pop":80,
    "ks:ks_type":"HABITATION",
    "name:eng_x_preferred":[
        "Warna Nadi"
    ],
    "wof:name":"Warna Nadi",
    "wof:placetype":"locality",
    "wof:population":80
},
  "geometry": {"coordinates":[74.08635099999999,16.917965],"type":"Point"}
}