{
  "type": "Feature",
  "properties": {
    "iso:country":"IN",
    "ks:ks_name":"Ghadoi",
    "ks:ks_pop":2263,
    "ks:ks_type":"VILLAGE",
    "name:eng_x_preferred":[
        "Ghadoi"
    ],
    "wof:name":"Ghadoi",
    "wof:placetype":"locality",
    "wof:population":2263
},
  "geometry": {"coordinates":[72.989328,20.607086],"type":"Point"}
}