{
  "type": "Feature",
  "properties": {
    "gn:admin1_code":"12",
    "gn:admin2_code":"21.0",
    "gn:asciiname":"Kirial Jagir",
    "gn:country_code":"IN",
    "gn:dem":274,
    "gn:feature_class":"P",
    "gn:feature_code":"PPL",
    "gn:name":"Kir\u012b\u0101l J\u0101g\u012br",
    "gn:population":0,
    "gn:timezone":"Asia/Kolkata",
    "iso:country":"IN",
    "wof:name":"Kirial Jagir",
    "wof:placetype":"locality"
},
  "geometry": {"coordinates":[74.8386,32.53095],"type":"Point"}
}