{
  "type": "Feature",
  "properties": {
    "iso:country":"IN",
    "ks:ks_name":"Devjeet Ki Thar",
    "ks:ks_pop":89,
    "ks:ks_type":"HABITATION",
    "name:eng_x_preferred":[
        "Devjeet Ki Thar"
    ],
    "wof:name":"Devjeet Ki Thar",
    "wof:placetype":"locality",
    "wof:population":89
},
  "geometry": {"coordinates":[78.335911,27.054813],"type":"Point"}
}