{
  "type": "Feature",
  "properties": {
    "iso:country":"IN",
    "ks:ks_name":"Rameshwar Purwa",
    "ks:ks_pop":95,
    "ks:ks_type":"HABITATION",
    "name:eng_x_preferred":[
        "Rameshwar Purwa"
    ],
    "wof:name":"Rameshwar Purwa",
    "wof:placetype":"locality",
    "wof:population":95
},
  "geometry": {"coordinates":[81.137916,25.189145],"type":"Point"}
}