{
  "type": "Feature",
  "properties": {
    "iso:country":"IN",
    "ks:ks_name":"Simlagaon",
    "ks:ks_pop":567,
    "ks:ks_type":"HABITATION",
    "ks:ks_uagg_main":0,
    "name:eng_x_preferred":[
        "Simlagaon"
    ],
    "wof:name":"Simlagaon",
    "wof:placetype":"neighbourhood",
    "wof:population":567
},
  "geometry": {"coordinates":[90.46572999999999,26.76208],"type":"Point"}
}