{
  "type": "Feature",
  "properties": {
    "iso:country":"IN",
    "ks:ks_name":"Chikkakallalli",
    "ks:ks_pop":8,
    "ks:ks_type":"HABITATION",
    "name:eng_x_preferred":[
        "Chikkakallalli"
    ],
    "wof:name":"Chikkakallalli",
    "wof:placetype":"locality",
    "wof:population":8
},
  "geometry": {"coordinates":[74.638154,14.591758],"type":"Point"}
}