{
  "type": "Feature",
  "properties": {
    "iso:country":"IN",
    "ks:ks_name":"Choti Menhadia",
    "ks:ks_pop":790,
    "ks:ks_type":"HABITATION",
    "name:eng_x_preferred":[
        "Choti Menhadia"
    ],
    "wof:name":"Choti Menhadia",
    "wof:placetype":"locality",
    "wof:population":790
},
  "geometry": {"coordinates":[83.809866,27.051746],"type":"Point"}
}