{
  "type": "Feature",
  "properties": {
    "iso:country":"IN",
    "ks:ks_name":"Sudhiram Para",
    "ks:ks_pop":210,
    "ks:ks_type":"HABITATION",
    "name:eng_x_preferred":[
        "Sudhiram Para"
    ],
    "wof:name":"Sudhiram Para",
    "wof:placetype":"locality",
    "wof:population":210
},
  "geometry": {"coordinates":[91.90642699999999,23.854471],"type":"Point"}
}