{
  "type": "Feature",
  "properties": {
    "iso:country":"IN",
    "ks:ks_name":"Dukalepada",
    "ks:ks_pop":237,
    "ks:ks_type":"HABITATION",
    "name:eng_x_preferred":[
        "Dukalepada"
    ],
    "wof:name":"Dukalepada",
    "wof:placetype":"locality",
    "wof:population":237
},
  "geometry": {"coordinates":[72.987009,19.946595],"type":"Point"}
}