{
  "type": "Feature",
  "properties": {
    "iso:country":"IN",
    "ks:ks_name":"Majhiyawan Bhuiya Toli",
    "ks:ks_pop":325,
    "ks:ks_type":"HABITATION",
    "ks:ks_uagg_main":0,
    "name:eng_x_preferred":[
        "Majhiyawan Bhuiya Toli"
    ],
    "wof:name":"Majhiyawan Bhuiya Toli",
    "wof:placetype":"neighbourhood",
    "wof:population":325
},
  "geometry": {"coordinates":[85.23344299999999,24.592762],"type":"Point"}
}