{
  "type": "Feature",
  "properties": {
    "gn:admin1_code":"23.0",
    "gn:admin2_code":"035",
    "gn:asciiname":"Dhar Khurd",
    "gn:country_code":"IN",
    "gn:dem":641,
    "gn:feature_class":"P",
    "gn:feature_code":"PPL",
    "gn:name":"Dh\u0101r Khurd",
    "gn:population":0,
    "gn:timezone":"Asia/Kolkata",
    "iso:country":"IN",
    "name:und_x_variant":[
        "Dh\u0101r",
        "Dh\u0101r Khurd"
    ],
    "wof:name":"Dhar Khurd",
    "wof:placetype":"locality"
},
  "geometry": {"coordinates":[75.81347,32.39705],"type":"Point"}
}