{
  "type": "Feature",
  "properties": {
    "iso:country":"IN",
    "ks:ks_name":"Phulajhara",
    "ks:ks_pop":288,
    "ks:ks_type":"HABITATION",
    "name:eng_x_preferred":[
        "Phulajhara"
    ],
    "wof:name":"Phulajhara",
    "wof:placetype":"locality",
    "wof:population":288
},
  "geometry": {"coordinates":[85.910578,20.7633],"type":"Point"}
}