{
  "type": "Feature",
  "properties": {
    "gn:admin1_code":"39.0",
    "gn:admin2_code":"60.0",
    "gn:asciiname":"Dhariya Nichla",
    "gn:country_code":"IN",
    "gn:dem":1021,
    "gn:feature_class":"P",
    "gn:feature_code":"PPL",
    "gn:name":"Dh\u0101riya Nichla",
    "gn:population":0,
    "gn:timezone":"Asia/Kolkata",
    "iso:country":"IN",
    "wof:name":"Dhariya Nichla",
    "wof:placetype":"locality"
},
  "geometry": {"coordinates":[77.77866999999998,30.67658],"type":"Point"}
}