{
  "type": "Feature",
  "properties": {
    "gn:admin1_code":"12",
    "gn:admin2_code":"22.0",
    "gn:asciiname":"Ramblu Rajputan",
    "gn:country_code":"IN",
    "gn:dem":303,
    "gn:feature_class":"P",
    "gn:feature_code":"PPL",
    "gn:name":"Ramblu R\u0101jput\u0101n",
    "gn:population":0,
    "gn:timezone":"Asia/Kolkata",
    "iso:country":"IN",
    "wof:name":"Ramblu Rajputan",
    "wof:placetype":"locality"
},
  "geometry": {"coordinates":[74.95238000000001,32.50989000000001],"type":"Point"}
}