{
  "type": "Feature",
  "properties": {
    "iso:country":"IN",
    "ks:ks_alt_nam":"Ich\u0101h\u0101tu",
    "ks:ks_name":"Ichahatu",
    "ks:ks_pop":235,
    "ks:ks_type":"VILLAGE",
    "name:eng_x_preferred":[
        "Ichahatu"
    ],
    "name:eng_x_variant":[
        "Ich\u0101h\u0101tu"
    ],
    "wof:name":"Ichahatu",
    "wof:placetype":"locality",
    "wof:population":235
},
  "geometry": {"coordinates":[85.760639,22.850411],"type":"Point"}
}