{
  "type": "Feature",
  "properties": {
    "iso:country":"IN",
    "ks:ks_name":"Tharupurva",
    "ks:ks_pop":280,
    "ks:ks_type":"HABITATION",
    "ks:ks_uagg_main":0,
    "name:eng_x_preferred":[
        "Tharupurva"
    ],
    "wof:name":"Tharupurva",
    "wof:placetype":"neighbourhood",
    "wof:population":280
},
  "geometry": {"coordinates":[80.601927,28.435797],"type":"Point"}
}