{
  "type": "Feature",
  "properties": {
    "iso:country":"IN",
    "ks:ks_name":"Loharajore",
    "ks:ks_pop":145,
    "ks:ks_type":"VILLAGE",
    "name:eng_x_preferred":[
        "Loharajore"
    ],
    "wof:name":"Loharajore",
    "wof:placetype":"locality",
    "wof:population":145
},
  "geometry": {"coordinates":[82.97913800000001,19.54093],"type":"Point"}
}