{
  "type": "Feature",
  "properties": {
    "iso:country":"IN",
    "ks:ks_name":"Chak Ghachua",
    "ks:ks_pop":508,
    "ks:ks_type":"VILLAGE",
    "ks:ks_uagg_main":0,
    "name:eng_x_preferred":[
        "Chak Ghachua"
    ],
    "wof:name":"Chak Ghachua",
    "wof:placetype":"neighbourhood",
    "wof:population":508
},
  "geometry": {"coordinates":[88.09408000000001,24.311529],"type":"Point"}
}