{
  "type": "Feature",
  "properties": {
    "iso:country":"IN",
    "ks:ks_name":"Mushar Tola",
    "ks:ks_pop":325,
    "ks:ks_type":"HABITATION",
    "ks:ks_uagg_main":0,
    "name:eng_x_preferred":[
        "Mushar Tola"
    ],
    "wof:name":"Mushar Tola",
    "wof:placetype":"neighbourhood",
    "wof:population":325
},
  "geometry": {"coordinates":[84.47985,26.774616],"type":"Point"}
}