{
  "type": "Feature",
  "properties": {
    "gn:admin1_code":"25.0",
    "gn:admin2_code":"606.0",
    "gn:asciiname":"Sananandal",
    "gn:country_code":"IN",
    "gn:dem":169,
    "gn:feature_class":"P",
    "gn:feature_code":"PPL",
    "gn:name":"S\u0101n\u0101nandal",
    "gn:population":0,
    "gn:timezone":"Asia/Kolkata",
    "iso:country":"IN",
    "ks:ks_alt_nam":"S\u0101n\u0101nandal",
    "ks:ks_name":"Sananandal",
    "ks:ks_pop":1303,
    "ks:ks_type":"VILLAGE",
    "name:eng_x_preferred":[
        "Sananandal"
    ],
    "name:eng_x_variant":[
        "S\u0101n\u0101nandal"
    ],
    "wof:name":"Sananandal",
    "wof:placetype":"locality",
    "wof:population":1303
},
  "geometry": {"coordinates":[79.107752,12.285456],"type":"Point"}
}