{
  "type": "Feature",
  "properties": {
    "gn:admin1_code":"36.0",
    "gn:admin2_code":"146",
    "gn:asciiname":"Aharan",
    "gn:country_code":"IN",
    "gn:dem":174,
    "gn:feature_class":"P",
    "gn:feature_code":"PPL",
    "gn:name":"Aharan",
    "gn:population":0,
    "gn:timezone":"Asia/Kolkata",
    "iso:country":"IN",
    "wof:name":"Aharan",
    "wof:placetype":"locality"
},
  "geometry": {"coordinates":[78.23748000000001,27.35782],"type":"Point"}
}