{
  "type": "Feature",
  "properties": {
    "iso:country":"IN",
    "ks:ks_name":"Karikadu",
    "ks:ks_pop":574,
    "ks:ks_type":"VILLAGE",
    "name:eng_x_preferred":[
        "Karikadu"
    ],
    "wof:name":"Karikadu",
    "wof:placetype":"locality",
    "wof:population":574
},
  "geometry": {"coordinates":[80.094402,13.829933],"type":"Point"}
}