{
  "type": "Feature",
  "properties": {
    "iso:country":"IN",
    "ks:ks_name":"Garal",
    "ks:ks_pop":480,
    "ks:ks_type":"VILLAGE",
    "name:eng_x_preferred":[
        "Garal"
    ],
    "wof:name":"Garal",
    "wof:placetype":"locality",
    "wof:population":480
},
  "geometry": {"coordinates":[71.4837,25.582319],"type":"Point"}
}