{
  "type": "Feature",
  "properties": {
    "gn:admin1_code":"2.0",
    "gn:admin2_code":"551.0",
    "gn:asciiname":"Voddapalli",
    "gn:country_code":"IN",
    "gn:dem":137,
    "gn:feature_class":"P",
    "gn:feature_code":"PPL",
    "gn:name":"Voddapalli",
    "gn:population":0,
    "gn:timezone":"Asia/Kolkata",
    "iso:country":"IN",
    "wof:name":"Voddapalli",
    "wof:placetype":"locality"
},
  "geometry": {"coordinates":[79.34578,14.19014],"type":"Point"}
}