{
  "type": "Feature",
  "properties": {
    "iso:country":"IN",
    "ks:ks_name":"Saloipara",
    "ks:ks_pop":2647,
    "ks:ks_type":"VILLAGE",
    "ks:ks_uagg_main":0,
    "name:eng_x_preferred":[
        "Saloipara"
    ],
    "wof:name":"Saloipara",
    "wof:placetype":"neighbourhood",
    "wof:population":2647
},
  "geometry": {"coordinates":[92.033539,26.472325],"type":"Point"}
}