{
  "type": "Feature",
  "properties": {
    "gn:admin1_code":"37.0",
    "gn:admin2_code":"416.0",
    "gn:asciiname":"Lachkipara",
    "gn:country_code":"IN",
    "gn:dem":253,
    "gn:feature_class":"P",
    "gn:feature_code":"PPL",
    "gn:name":"Lachkip\u0101ra",
    "gn:population":0,
    "gn:timezone":"Asia/Kolkata",
    "iso:country":"IN",
    "ks:ks_name":"Lachapara",
    "ks:ks_pop":227,
    "ks:ks_type":"HABITATION",
    "name:eng_x_preferred":[
        "Lachapara"
    ],
    "name:eng_x_variant":[
        "Lachkipara"
    ],
    "wof:name":"Lachapara",
    "wof:placetype":"locality",
    "wof:population":227
},
  "geometry": {"coordinates":[81.721648,18.584352],"type":"Point"}
}