{
  "type": "Feature",
  "properties": {
    "gn:admin1_code":"3.0",
    "gn:admin2_code":"310.0",
    "gn:asciiname":"Amguri Nepali",
    "gn:country_code":"IN",
    "gn:dem":113,
    "gn:feature_class":"P",
    "gn:feature_code":"PPL",
    "gn:name":"Amguri Nepali",
    "gn:population":0,
    "gn:timezone":"Asia/Kolkata",
    "iso:country":"IN",
    "wof:name":"Amguri Nepali",
    "wof:placetype":"locality"
},
  "geometry": {"coordinates":[95.24494,27.33103],"type":"Point"}
}