{
  "type": "Feature",
  "properties": {
    "gn:admin1_code":"3.0",
    "gn:admin2_code":"310.0",
    "gn:asciiname":"Amguri Nepali",
    "gn:country_code":"IN",
    "gn:dem":113,
    "gn:feature_class":"P",
    "gn:feature_code":"PPL",
    "gn:name":"Amguri Nepali",
    "gn:population":0,
    "gn:timezone":"Asia/Kolkata",
    "iso:country":"IN",
    "ks:ks_name":"Amguri Nepali",
    "ks:ks_pop":842,
    "ks:ks_type":"HABITATION",
    "name:eng_x_preferred":[
        "Amguri Nepali"
    ],
    "wof:name":"Amguri Nepali",
    "wof:placetype":"locality",
    "wof:population":842
},
  "geometry": {"coordinates":[95.247944,27.326395],"type":"Point"}
}