{
  "type": "Feature",
  "properties": {
    "iso:country":"IN",
    "ks:ks_alt_nam":"Chak Hum\u0101y\u016bn",
    "ks:ks_name":"Chak Humayun",
    "ks:ks_type":"VILLAGE",
    "name:eng_x_preferred":[
        "Chak Humayun"
    ],
    "name:eng_x_variant":[
        "Chak Hum\u0101y\u016bn"
    ],
    "wof:name":"Chak Humayun",
    "wof:placetype":"locality"
},
  "geometry": {"coordinates":[78.38672,29.299244],"type":"Point"}
}