{
  "type": "Feature",
  "properties": {
    "iso:country":"IN",
    "ks:ks_name":"Karjeepara Chikiguri I",
    "ks:ks_pop":700,
    "ks:ks_type":"HABITATION",
    "name:eng_x_preferred":[
        "Karjeepara Chikiguri I"
    ],
    "wof:name":"Karjeepara Chikiguri I",
    "wof:placetype":"locality",
    "wof:population":700
},
  "geometry": {"coordinates":[89.6691,26.428948],"type":"Point"}
}