{
  "type": "Feature",
  "properties": {
    "iso:country":"IN",
    "ks:ks_name":"Kharuani",
    "ks:ks_pop":119,
    "ks:ks_type":"VILLAGE",
    "name:eng_x_preferred":[
        "Kharuani"
    ],
    "wof:name":"Kharuani",
    "wof:placetype":"locality",
    "wof:population":119
},
  "geometry": {"coordinates":[85.12146799999999,20.595053],"type":"Point"}
}