{
  "type": "Feature",
  "properties": {
    "iso:country":"IN",
    "ks:ks_name":"Kayakuchi Pathar",
    "ks:ks_pop":61,
    "ks:ks_type":"VILLAGE",
    "name:eng_x_preferred":[
        "Kayakuchi Pathar"
    ],
    "wof:name":"Kayakuchi Pathar",
    "wof:placetype":"locality",
    "wof:population":61
},
  "geometry": {"coordinates":[90.774564,26.220378],"type":"Point"}
}