{
  "type": "Feature",
  "properties": {
    "iso:country":"IN",
    "ks:ks_name":"Pub Singimari",
    "ks:ks_pop":245,
    "ks:ks_type":"HABITATION",
    "ks:ks_uagg_main":0,
    "name:eng_x_preferred":[
        "Pub Singimari"
    ],
    "wof:name":"Pub Singimari",
    "wof:placetype":"neighbourhood",
    "wof:population":245
},
  "geometry": {"coordinates":[91.75775299999999,26.546857],"type":"Point"}
}