{
  "type": "Feature",
  "properties": {
    "iso:country":"IN",
    "ks:ks_alt_nam":"Chitkahari para Chaura",
    "ks:ks_name":"Chitkahari Para Chaura",
    "ks:ks_pop":250,
    "ks:ks_type":"HABITATION",
    "name:eng_x_preferred":[
        "Chitkahari Para Chaura"
    ],
    "wof:name":"Chitkahari Para Chaura",
    "wof:placetype":"locality",
    "wof:population":250
},
  "geometry": {"coordinates":[83.211979,23.359555],"type":"Point"}
}