{
  "type": "Feature",
  "properties": {
    "gn:admin1_code":"11.0",
    "gn:admin2_code":"32.0",
    "gn:asciiname":"Kaba",
    "gn:country_code":"IN",
    "gn:dem":1599,
    "gn:feature_class":"P",
    "gn:feature_code":"PPL",
    "gn:name":"K\u0101ba",
    "gn:population":0,
    "gn:timezone":"Asia/Kolkata",
    "iso:country":"IN",
    "name:ceb_x_preferred":[
        "Kaba"
    ],
    "name:deu_x_preferred":[
        "Kaba"
    ],
    "name:fin_x_preferred":[
        "Kaba"
    ],
    "name:fra_x_preferred":[
        "Kaba"
    ],
    "name:hrv_x_preferred":[
        "Kaba"
    ],
    "name:swe_x_preferred":[
        "Kaba"
    ],
    "wof:name":"Kaba",
    "wof:placetype":"locality"
},
  "geometry": {"coordinates":[77.35176,30.66575],"type":"Point"}
}