{
  "type": "Feature",
  "properties": {
    "iso:country":"IN",
    "ks:ks_name":"Kardiyuthu Thanda",
    "ks:ks_pop":510,
    "ks:ks_type":"HABITATION",
    "name:eng_x_preferred":[
        "Kardiyuthu Thanda"
    ],
    "wof:name":"Kardiyuthu Thanda",
    "wof:placetype":"locality",
    "wof:population":510
},
  "geometry": {"coordinates":[78.811168,12.220347],"type":"Point"}
}