{
  "type": "Feature",
  "properties": {
    "iso:country":"IN",
    "ks:ks_name":"Nanda Ka Pura",
    "ks:ks_pop":679,
    "ks:ks_type":"HABITATION",
    "ks:ks_uagg_main":0,
    "name:eng_x_preferred":[
        "Nanda Ka Pura"
    ],
    "wof:name":"Nanda Ka Pura",
    "wof:placetype":"neighbourhood",
    "wof:population":679
},
  "geometry": {"coordinates":[81.782291,25.681285],"type":"Point"}
}