{
  "type": "Feature",
  "properties": {
    "iso:country":"IN",
    "ks:ks_alt_nam":"harijana colony",
    "ks:ks_name":"Harijana Colony",
    "ks:ks_pop":56,
    "ks:ks_type":"HABITATION",
    "name:eng_x_preferred":[
        "Harijana Colony"
    ],
    "wof:name":"Harijana Colony",
    "wof:placetype":"locality",
    "wof:population":56
},
  "geometry": {"coordinates":[74.46011799999999,14.329575],"type":"Point"}
}