{
  "type": "Feature",
  "properties": {
    "iso:country":"IN",
    "ks:ks_name":"Badkher",
    "ks:ks_pop":1781,
    "ks:ks_type":"HABITATION",
    "name:eng_x_preferred":[
        "Badkher"
    ],
    "wof:name":"Badkher",
    "wof:placetype":"locality",
    "wof:population":1781
},
  "geometry": {"coordinates":[80.899967,24.804137],"type":"Point"}
}