{
  "type": "Feature",
  "properties": {
    "gn:admin1_code":"34.0",
    "gn:admin2_code":"229.0",
    "gn:asciiname":"Khanpura",
    "gn:country_code":"IN",
    "gn:dem":54,
    "gn:feature_class":"P",
    "gn:feature_code":"PPL",
    "gn:name":"Kh\u0101npura",
    "gn:population":0,
    "gn:timezone":"Asia/Kolkata",
    "iso:country":"IN",
    "name:ara_x_preferred":[
        "\u062e\u0627\u0646\u0628\u0648\u0631\u0627"
    ],
    "name:ben_bn_x_preferred":[
        "\u0996\u09be\u09a8\u09aa\u09c1\u09b0\u09be"
    ],
    "name:ben_in_x_preferred":[
        "\u0996\u09be\u09a8\u09aa\u09c1\u09b0\u09be"
    ],
    "name:guj_x_preferred":[
        "\u0a96\u0abe\u0aa8\u0aaa\u0ac1\u0ab0\u0abe"
    ],
    "name:hin_x_preferred":[
        "\u0916\u093e\u0928\u092a\u0941\u0930\u093e"
    ],
    "name:kan_x_preferred":[
        "\u0c96\u0cbe\u0ca8\u0ccd"
    ],
    "name:mal_x_preferred":[
        "\u0d16\u0d3e\u0d7b\u0d2a\u0d41\u0d30"
    ],
    "name:mar_x_preferred":[
        "\u0916\u093e\u0928\u092a\u0941\u0930\u093e"
    ],
    "name:pan_x_preferred":[
        "\u0a16\u0a3e\u0a28\u0a2a\u0a41\u0a30\u0a3e"
    ],
    "name:tam_x_preferred":[
        "\u0b95\u0bbe\u0ba9\u0bcd\u0baa\u0bc1\u0bb0\u0bbe"
    ],
    "name:tel_x_preferred":[
        "\u0c16\u0c3e\u0c28\u0c4d"
    ],
    "name:urd_x_preferred":[
        "\u062e\u0627\u0646 \u067e\u0648\u0631\u06c1"
    ],
    "wof:name":"Khanpura",
    "wof:placetype":"locality"
},
  "geometry": {"coordinates":[85.23464,25.37977],"type":"Point"}
}