{
  "type": "Feature",
  "properties": {
    "iso:country":"IN",
    "name:eng_x_preferred":[
        "Perambur"
    ],
    "name:eng_x_variant":[
        "Madras Perambur"
    ],
    "name:por_x_preferred":[
        "Perambur"
    ],
    "name:tam_x_preferred":[
        "\u0baa\u0bc6\u0bb0\u0bae\u0bcd\u0baa\u0bc2\u0bb0\u0bcd"
    ],
    "name:tel_x_preferred":[
        "\u0c2a\u0c46\u0c30\u0c02\u0c2c\u0c42\u0c30\u0c41"
    ],
    "name:und_x_variant":[
        "Peramb\u016br"
    ],
    "qs:gn_adm0_cc":"IN",
    "qs:gn_fcode":"PPLX",
    "qs:gn_local":1264527,
    "qs:gn_nam_loc":"Chennai, Chennai, Tamil Nadu, IN",
    "qs:gn_namadm1":"25",
    "qs:gn_name":"Peramb\u016br",
    "qs:local_max":2138,
    "qs:local_sum":21081,
    "qs:localhoods":47,
    "qs:name":"Perambur",
    "qs:name_adm0":"India",
    "qs:name_adm1":"Tamil Nadu",
    "qs:name_adm2":"Chennai",
    "qs:name_local":"Chennai",
    "qs:photo_max":28,
    "qs:photo_sum":118,
    "qs:placetype":"Suburb",
    "qs:quad_count":15,
    "qs:woe_adm0":23424848,
    "qs:woe_adm1":2345758,
    "qs:woe_adm2":12586677,
    "qs:woe_lau":0,
    "qs:woe_local":2295424,
    "qs:woe_ver":"7.10.0",
    "wd:wordcount":1126,
    "wof:lang":[
        "eng"
    ],
    "wof:name":"Perambur",
    "wof:placetype":"neighbourhood"
},
  "geometry": {"coordinates":[80.256569,13.11371],"type":"Point"}
}