{
  "type": "Feature",
  "properties": {
    "gn:admin1_code":"2.0",
    "gn:admin2_code":"551.0",
    "gn:asciiname":"Balayapalle",
    "gn:country_code":"IN",
    "gn:dem":216,
    "gn:feature_class":"P",
    "gn:feature_code":"PPL",
    "gn:name":"B\u0101l\u0101yapalle",
    "gn:population":0,
    "gn:timezone":"Asia/Kolkata",
    "iso:country":"IN",
    "name:new_x_preferred":[
        "\u092c\u093e\u0932\u093e\u092f\u092a\u0932\u094d\u0932\u0947 \u092e\u0923\u094d\u0921\u0932"
    ],
    "name:tam_x_preferred":[
        "\u0baa\u0bbe\u0bb2\u0bbe\u0baf\u0baa\u0bb2\u0bcd\u0bb2\u0bbf"
    ],
    "name:tel_x_preferred":[
        "\u0c2c\u0c3e\u0c32\u0c3e\u0c2f\u0c2a\u0c32\u0c4d\u0c32\u0c3f"
    ],
    "wof:name":"Balayapalle",
    "wof:placetype":"locality"
},
  "geometry": {"coordinates":[78.89018,15.0675],"type":"Point"}
}