{
  "type": "Feature",
  "properties": {
    "iso:country":"IN",
    "ks:ks_name":"Pase Ka Purwa",
    "ks:ks_pop":687,
    "ks:ks_type":"HABITATION",
    "ks:ks_uagg_main":0,
    "name:eng_x_preferred":[
        "Pase Ka Purwa"
    ],
    "wof:name":"Pase Ka Purwa",
    "wof:placetype":"neighbourhood",
    "wof:population":687
},
  "geometry": {"coordinates":[80.307219,26.281337],"type":"Point"}
}