{
  "type": "Feature",
  "properties": {
    "gn:admin1_code":"19.0",
    "gn:admin2_code":"582.0",
    "gn:asciiname":"Mittapallivandlapalli",
    "gn:country_code":"IN",
    "gn:dem":705,
    "gn:feature_class":"P",
    "gn:feature_code":"PPL",
    "gn:name":"Mittapalliv\u0101ndlapalli",
    "gn:population":0,
    "gn:timezone":"Asia/Kolkata",
    "iso:country":"IN",
    "wof:name":"Mittapallivandlapalli",
    "wof:placetype":"locality"
},
  "geometry": {"coordinates":[77.94615,13.85097],"type":"Point"}
}