{
  "type": "Feature",
  "properties": {
    "gn:admin1_code":"2.0",
    "gn:asciiname":"Ranapur",
    "gn:country_code":"IN",
    "gn:dem":367,
    "gn:feature_class":"P",
    "gn:feature_code":"PPL",
    "gn:name":"R\u0101n\u0101pur",
    "gn:population":0,
    "gn:timezone":"Asia/Kolkata",
    "iso:country":"IN",
    "name:ben_x_preferred":[
        "\u09b0\u09be\u09a8\u09be\u09aa\u09c1\u09b0"
    ],
    "name:bpy_x_preferred":[
        "\u09b0\u09be\u09a8\u09be\u09aa\u09c1\u09b0"
    ],
    "name:ceb_x_preferred":[
        "R\u0101napur"
    ],
    "name:ita_x_preferred":[
        "Ranapur"
    ],
    "name:mlg_x_preferred":[
        "Ranapur"
    ],
    "name:msa_x_preferred":[
        "Ranapur"
    ],
    "name:nld_x_preferred":[
        "Ranapur"
    ],
    "name:por_x_preferred":[
        "Ranapur"
    ],
    "name:swe_x_preferred":[
        "R\u0101napur"
    ],
    "name:vie_x_preferred":[
        "Ranapur"
    ],
    "name:zho_x_preferred":[
        "\u62c9\u7eb3\u666e\u5c14"
    ],
    "wof:name":"Ranapur",
    "wof:placetype":"locality"
},
  "geometry": {"coordinates":[78.3554,19.16953],"type":"Point"}
}