{
  "type": "Feature",
  "properties": {
    "iso:country":"IN",
    "ks:ks_alt_nam":"SCRTOD",
    "ks:ks_name":"Scrtod",
    "ks:ks_pop":15,
    "ks:ks_type":"HABITATION",
    "name:eng_x_preferred":[
        "Scrtod"
    ],
    "wof:name":"Scrtod",
    "wof:placetype":"locality",
    "wof:population":15
},
  "geometry": {"coordinates":[74.062325,29.766258],"type":"Point"}
}