{
  "type": "Feature",
  "properties": {
    "gn:admin1_code":"24.0",
    "gn:admin2_code":"128",
    "gn:asciiname":"Kelwara",
    "gn:country_code":"IN",
    "gn:dem":353,
    "gn:feature_class":"P",
    "gn:feature_code":"PPL",
    "gn:name":"Kelw\u0101ra",
    "gn:population":0,
    "gn:timezone":"Asia/Kolkata",
    "iso:country":"IN",
    "ks:ks_alt_nam":"Kelw\u0101ra",
    "ks:ks_name":"Kelwara",
    "ks:ks_pop":3553,
    "ks:ks_type":"VILLAGE",
    "ks:ks_uagg_main":0,
    "name:eng_x_preferred":[
        "Kelwara"
    ],
    "name:eng_x_variant":[
        "Kelw\u0101ra"
    ],
    "wof:name":"Kelwara",
    "wof:placetype":"neighbourhood",
    "wof:population":3553
},
  "geometry": {"coordinates":[76.88074400000001,25.137342],"type":"Point"}
}