{
  "type": "Feature",
  "properties": {
    "iso:country":"IN",
    "ks:ks_name":"Kudurebena",
    "ks:ks_pop":52,
    "ks:ks_type":"HABITATION",
    "name:eng_x_preferred":[
        "Kudurebena"
    ],
    "wof:name":"Kudurebena",
    "wof:placetype":"locality",
    "wof:population":52
},
  "geometry": {"coordinates":[74.762513,14.952526],"type":"Point"}
}