{
  "type": "Feature",
  "properties": {
    "iso:country":"IN",
    "ks:ks_name":"Rajput Wadi",
    "ks:ks_pop":165,
    "ks:ks_type":"HABITATION",
    "name:eng_x_preferred":[
        "Rajput Wadi"
    ],
    "wof:name":"Rajput Wadi",
    "wof:placetype":"locality",
    "wof:population":165
},
  "geometry": {"coordinates":[75.896992,20.294818],"type":"Point"}
}