{
  "type": "Feature",
  "properties": {
    "gn:admin1_code":"28.0",
    "gn:admin2_code":"328",
    "gn:asciiname":"Buxa Duar",
    "gn:country_code":"IN",
    "gn:dem":642,
    "gn:feature_class":"P",
    "gn:feature_code":"PPL",
    "gn:name":"Buxa Du\u0101r",
    "gn:population":0,
    "gn:timezone":"Asia/Kolkata",
    "iso:country":"IN",
    "name:und_x_variant":[
        "Baksa Duar",
        "Buksa",
        "Buxa Du\u0101r"
    ],
    "wof:name":"Buxa Duar",
    "wof:placetype":"locality"
},
  "geometry": {"coordinates":[89.59398,26.75865],"type":"Point"}
}