{
  "type": "Feature",
  "properties": {
    "gn:admin1_code":"16.0",
    "gn:admin2_code":"526",
    "gn:asciiname":"Gaundre",
    "gn:country_code":"IN",
    "gn:dem":527,
    "gn:feature_class":"P",
    "gn:feature_code":"PPL",
    "gn:name":"Gaundre",
    "gn:population":0,
    "gn:timezone":"Asia/Kolkata",
    "iso:country":"IN",
    "wof:name":"Gaundre",
    "wof:placetype":"locality"
},
  "geometry": {"coordinates":[75.35513,18.31932],"type":"Point"}
}