{
  "type": "Feature",
  "properties": {
    "gn:admin1_code":"24.0",
    "gn:admin2_code":"125.0",
    "gn:asciiname":"Tejpur",
    "gn:country_code":"IN",
    "gn:dem":260,
    "gn:feature_class":"P",
    "gn:feature_code":"PPL",
    "gn:name":"Tejpur",
    "gn:population":0,
    "gn:timezone":"Asia/Kolkata",
    "iso:country":"IN",
    "ks:ks_name":"Tejpura",
    "ks:ks_pop":1763,
    "ks:ks_type":"VILLAGE",
    "name:eng_x_preferred":[
        "Tejpura"
    ],
    "name:eng_x_variant":[
        "Tejpur"
    ],
    "wof:name":"Tejpura",
    "wof:placetype":"locality",
    "wof:population":1763
},
  "geometry": {"coordinates":[74.11814699999999,23.296222],"type":"Point"}
}