{
  "type": "Feature",
  "properties": {
    "gn:admin1_code":"37",
    "gn:admin2_code":"408.0",
    "gn:asciiname":"Ehora",
    "gn:country_code":"IN",
    "gn:dem":384,
    "gn:feature_class":"P",
    "gn:feature_code":"PPL",
    "gn:name":"Ehora",
    "gn:population":0,
    "gn:timezone":"Asia/Kolkata",
    "iso:country":"IN",
    "wof:name":"Ehora",
    "wof:placetype":"locality"
},
  "geometry": {"coordinates":[80.54035999999998,20.64007],"type":"Point"}
}