{
  "type": "Feature",
  "properties": {
    "iso:country":"IN",
    "ks:ks_name":"Dharmatala",
    "ks:ks_pop":3883,
    "ks:ks_type":"VILLAGE",
    "ks:ks_uagg_main":0,
    "name:eng_x_preferred":[
        "Dharmatala"
    ],
    "wof:name":"Dharmatala",
    "wof:placetype":"neighbourhood",
    "wof:population":3883
},
  "geometry": {"coordinates":[88.559932,22.250868],"type":"Point"}
}