{
  "type": "Feature",
  "properties": {
    "iso:country":"IN",
    "ks:ks_alt_nam":"Parekarwadi NV",
    "ks:ks_name":"Parekarwadi Nv",
    "ks:ks_pop":529,
    "ks:ks_type":"HABITATION",
    "name:eng_x_preferred":[
        "Parekarwadi Nv"
    ],
    "wof:name":"Parekarwadi Nv",
    "wof:placetype":"locality",
    "wof:population":529
},
  "geometry": {"coordinates":[74.586277,20.342363],"type":"Point"}
}