{
  "type": "Feature",
  "properties": {
    "iso:country":"IN",
    "ks:ks_name":"Bamanpada",
    "ks:ks_pop":310,
    "ks:ks_type":"HABITATION",
    "name:eng_x_preferred":[
        "Bamanpada"
    ],
    "wof:name":"Bamanpada",
    "wof:placetype":"locality",
    "wof:population":310
},
  "geometry": {"coordinates":[73.07255600000001,20.224222],"type":"Point"}
}