{
  "type": "Feature",
  "properties": {
    "gn:admin1_code":"19.0",
    "gn:admin2_code":"581.0",
    "gn:asciiname":"Karadiguru",
    "gn:country_code":"IN",
    "gn:dem":799,
    "gn:feature_class":"P",
    "gn:feature_code":"PPL",
    "gn:name":"Karadiguru",
    "gn:population":0,
    "gn:timezone":"Asia/Kolkata",
    "iso:country":"IN",
    "wof:name":"Karadiguru",
    "wof:placetype":"locality"
},
  "geometry": {"coordinates":[78.40985999999999,13.0805],"type":"Point"}
}