{
  "type": "Feature",
  "properties": {
    "gn:admin1_code":"34.0",
    "gn:admin2_code":"217.0",
    "gn:asciiname":"Bhangaha",
    "gn:country_code":"IN",
    "gn:dem":81,
    "gn:feature_class":"P",
    "gn:feature_code":"PPL",
    "gn:name":"Bhangaha",
    "gn:population":0,
    "gn:timezone":"Asia/Kolkata",
    "iso:country":"IN",
    "ks:ks_name":"Bhangaha",
    "ks:ks_type":"VILLAGE",
    "name:ara_x_preferred":[
        "\u0641\u0627\u0646\u063a\u0627\u0647\u0627"
    ],
    "name:bih_x_preferred":[
        "\u0938\u093f\u0924\u093e\u092a\u0941\u0930 \u092d\u0919\u094d\u0917\u093e\u0939"
    ],
    "name:eng_x_preferred":[
        "Bhangaha"
    ],
    "name:fas_x_preferred":[
        "\u0648\u0646\u06af\u0647\u0627"
    ],
    "name:mai_x_preferred":[
        "\u0938\u093f\u0924\u093e\u092a\u0941\u0930 \u092d\u0919\u094d\u0917\u093e\u0939"
    ],
    "name:msa_x_preferred":[
        "Vangaha"
    ],
    "name:nep_x_preferred":[
        "\u0938\u093f\u0924\u093e\u092a\u0941\u0930 \u092d\u0919\u094d\u0917\u093e\u0939"
    ],
    "name:pol_x_preferred":[
        "Vagaha"
    ],
    "wof:name":"Bhangaha",
    "wof:placetype":"locality"
},
  "geometry": {"coordinates":[84.171105,26.536143],"type":"Point"}
}