{
  "type": "Feature",
  "properties": {
    "iso:country":"IN",
    "ks:ks_name":"Muralimohani",
    "ks:ks_pop":158,
    "ks:ks_type":"HABITATION",
    "name:eng_x_preferred":[
        "Muralimohani"
    ],
    "wof:name":"Muralimohani",
    "wof:placetype":"locality",
    "wof:population":158
},
  "geometry": {"coordinates":[83.17896500000001,19.444135],"type":"Point"}
}