{
  "type": "Feature",
  "properties": {
    "gn:admin1_code":"40.0",
    "gn:admin2_code":"534.0",
    "gn:asciiname":"Chintalapalli",
    "gn:country_code":"IN",
    "gn:dem":316,
    "gn:feature_class":"P",
    "gn:feature_code":"PPL",
    "gn:name":"Chintalapalli",
    "gn:population":0,
    "gn:timezone":"Asia/Kolkata",
    "iso:country":"IN",
    "wof:name":"Chintalapalli",
    "wof:placetype":"neighbourhood"
},
  "geometry": {"coordinates":[79.13972,18.21801],"type":"Point"}
}