{
  "type": "Feature",
  "properties": {
    "iso:country":"IN",
    "ks:ks_name":"Shivram Ka Purwa",
    "ks:ks_pop":155,
    "ks:ks_type":"HABITATION",
    "name:eng_x_preferred":[
        "Shivram Ka Purwa"
    ],
    "wof:name":"Shivram Ka Purwa",
    "wof:placetype":"locality",
    "wof:population":155
},
  "geometry": {"coordinates":[80.615058,25.365006],"type":"Point"}
}