{
  "type": "Feature",
  "properties": {
    "iso:country":"IN",
    "ks:ks_alt_nam":"CHAVAN WASTI",
    "ks:ks_name":"Chavan Wasti",
    "ks:ks_pop":77,
    "ks:ks_type":"HABITATION",
    "name:eng_x_preferred":[
        "Chavan Wasti"
    ],
    "wof:name":"Chavan Wasti",
    "wof:placetype":"locality",
    "wof:population":77
},
  "geometry": {"coordinates":[74.97720200000001,17.149973],"type":"Point"}
}