{
  "type": "Feature",
  "properties": {
    "iso:country":"IN",
    "ks:ks_name":"Banapatakandha",
    "ks:ks_pop":688,
    "ks:ks_type":"VILLAGE",
    "name:eng_x_preferred":[
        "Banapatakandha"
    ],
    "wof:name":"Banapatakandha",
    "wof:placetype":"locality",
    "wof:population":688
},
  "geometry": {"coordinates":[86.545346,20.244538],"type":"Point"}
}