{
  "type": "Feature",
  "properties": {
    "iso:country":"IN",
    "ks:ks_name":"Kharhi",
    "ks:ks_pop":1186,
    "ks:ks_type":"VILLAGE",
    "name:eng_x_preferred":[
        "Kharhi"
    ],
    "wof:name":"Kharhi",
    "wof:placetype":"locality",
    "wof:population":1186
},
  "geometry": {"coordinates":[79.945498,29.311669],"type":"Point"}
}