{
  "type": "Feature",
  "properties": {
    "iso:country":"IN",
    "ks:ks_name":"Taragabali",
    "ks:ks_pop":185,
    "ks:ks_type":"VILLAGE",
    "name:eng_x_preferred":[
        "Taragabali"
    ],
    "wof:name":"Taragabali",
    "wof:placetype":"locality",
    "wof:population":185
},
  "geometry": {"coordinates":[83.990003,19.648971],"type":"Point"}
}