{
  "type": "Feature",
  "properties": {
    "iso:country":"IN",
    "ks:ks_name":"Kachhawari",
    "ks:ks_pop":110,
    "ks:ks_type":"VILLAGE",
    "name:eng_x_preferred":[
        "Kachhawari"
    ],
    "wof:name":"Kachhawari",
    "wof:placetype":"locality",
    "wof:population":110
},
  "geometry": {"coordinates":[82.638194,23.78402],"type":"Point"}
}