{
  "type": "Feature",
  "properties": {
    "iso:country":"IN",
    "ks:ks_name":"Thar Narain",
    "ks:ks_pop":102,
    "ks:ks_type":"HABITATION",
    "name:eng_x_preferred":[
        "Thar Narain"
    ],
    "wof:name":"Thar Narain",
    "wof:placetype":"locality",
    "wof:population":102
},
  "geometry": {"coordinates":[78.478984,27.066646],"type":"Point"}
}