{
  "type": "Feature",
  "properties": {
    "iso:country":"IN",
    "ks:ks_name":"Ghonapota",
    "ks:ks_pop":329,
    "ks:ks_type":"VILLAGE",
    "name:eng_x_preferred":[
        "Ghonapota"
    ],
    "wof:name":"Ghonapota",
    "wof:placetype":"locality",
    "wof:population":329
},
  "geometry": {"coordinates":[87.52229699999999,22.188151],"type":"Point"}
}