{
  "type": "Feature",
  "properties": {
    "iso:country":"IN",
    "ks:ks_name":"Sitala Pally",
    "ks:ks_pop":1190,
    "ks:ks_type":"HABITATION",
    "name:eng_x_preferred":[
        "Sitala Pally"
    ],
    "wof:name":"Sitala Pally",
    "wof:placetype":"locality",
    "wof:population":1190
},
  "geometry": {"coordinates":[88.43707000000001,21.875466],"type":"Point"}
}