{
  "type": "Feature",
  "properties": {
    "iso:country":"IN",
    "ks:ks_name":"Chinnayyapalem",
    "ks:ks_pop":244,
    "ks:ks_type":"HABITATION",
    "name:eng_x_preferred":[
        "Chinnayyapalem"
    ],
    "wof:name":"Chinnayyapalem",
    "wof:placetype":"locality",
    "wof:population":244
},
  "geometry": {"coordinates":[82.84570600000001,17.64151],"type":"Point"}
}