{
  "type": "Feature",
  "properties": {
    "iso:country":"IN",
    "ks:ks_name":"Kalleri",
    "ks:ks_pop":241,
    "ks:ks_type":"VILLAGE",
    "name:eng_x_preferred":[
        "Kalleri"
    ],
    "wof:name":"Kalleri",
    "wof:placetype":"locality",
    "wof:population":241
},
  "geometry": {"coordinates":[75.75736000000001,13.200127],"type":"Point"}
}