{
  "type": "Feature",
  "properties": {
    "gn:admin1_code":"10",
    "gn:admin2_code":"86.0",
    "gn:asciiname":"Mahaniyawas",
    "gn:country_code":"IN",
    "gn:dem":237,
    "gn:feature_class":"P",
    "gn:feature_code":"PPL",
    "gn:name":"Mahan\u012byaw\u0101s",
    "gn:population":0,
    "gn:timezone":"Asia/Kolkata",
    "iso:country":"IN",
    "wof:name":"Mahaniyawas",
    "wof:placetype":"locality"
},
  "geometry": {"coordinates":[76.69199999999999,28.26791],"type":"Point"}
}