{
  "type": "Feature",
  "properties": {
    "gn:admin1_code":"34.0",
    "gn:admin2_code":"236.0",
    "gn:asciiname":"Baheri",
    "gn:country_code":"IN",
    "gn:dem":136,
    "gn:feature_class":"P",
    "gn:feature_code":"PPL",
    "gn:name":"Baheri",
    "gn:population":0,
    "gn:timezone":"Asia/Kolkata",
    "iso:country":"IN",
    "name:bih_x_preferred":[
        "\u092c\u0939\u0947\u0930\u0940"
    ],
    "name:bpy_x_preferred":[
        "\u09ac\u09be\u09b9\u09c7\u09b0\u09bf"
    ],
    "name:ceb_x_preferred":[
        "Baheri"
    ],
    "name:ita_x_preferred":[
        "Baheri"
    ],
    "name:mlg_x_preferred":[
        "Baheri"
    ],
    "name:msa_x_preferred":[
        "Baheri"
    ],
    "name:new_x_preferred":[
        "\u092c\u0939\u0947\u0930\u0940"
    ],
    "name:nld_x_preferred":[
        "Baheri"
    ],
    "name:pol_x_preferred":[
        "Baheri"
    ],
    "name:por_x_preferred":[
        "Baheri"
    ],
    "name:swe_x_preferred":[
        "Baheri"
    ],
    "name:urd_x_preferred":[
        "\u0628\u06c1\u06cc\u0631\u06cc"
    ],
    "name:vie_x_preferred":[
        "Baheri"
    ],
    "name:zho_x_preferred":[
        "\u5df4\u8d6b\u91cc"
    ],
    "wof:name":"Baheri",
    "wof:placetype":"locality"
},
  "geometry": {"coordinates":[84.67156,24.64387],"type":"Point"}
}