{
  "type": "Feature",
  "properties": {
    "iso:country":"IN",
    "ks:ks_name":"Belatikar",
    "ks:ks_pop":210,
    "ks:ks_type":"HABITATION",
    "name:eng_x_preferred":[
        "Belatikar"
    ],
    "wof:name":"Belatikar",
    "wof:placetype":"locality",
    "wof:population":210
},
  "geometry": {"coordinates":[87.13034500000001,24.925947],"type":"Point"}
}