{
  "type": "Feature",
  "properties": {
    "iso:country":"IN",
    "ks:ks_name":"Ganeshpura With Rundh Kali Ghati",
    "ks:ks_pop":6,
    "ks:ks_type":"HABITATION",
    "name:eng_x_preferred":[
        "Ganeshpura With Rundh Kali Ghati"
    ],
    "wof:name":"Ganeshpura With Rundh Kali Ghati",
    "wof:placetype":"locality",
    "wof:population":6
},
  "geometry": {"coordinates":[76.335683,27.355842],"type":"Point"}
}