{
  "type": "Feature",
  "properties": {
    "iso:country":"IN",
    "ks:ks_name":"Ghogri A",
    "ks:ks_pop":78,
    "ks:ks_type":"HABITATION",
    "name:eng_x_preferred":[
        "Ghogri A"
    ],
    "wof:name":"Ghogri A",
    "wof:placetype":"locality",
    "wof:population":78
},
  "geometry": {"coordinates":[78.496903,22.572713],"type":"Point"}
}