{
  "type": "Feature",
  "properties": {
    "iso:country":"IN",
    "ks:ks_alt_nam":"madhaw purwa",
    "ks:ks_name":"Madhaw Purwa",
    "ks:ks_pop":53,
    "ks:ks_type":"HABITATION",
    "name:eng_x_preferred":[
        "Madhaw Purwa"
    ],
    "wof:name":"Madhaw Purwa",
    "wof:placetype":"locality",
    "wof:population":53
},
  "geometry": {"coordinates":[81.685115,27.373677],"type":"Point"}
}