{
  "type": "Feature",
  "properties": {
    "iso:country":"IN",
    "ks:ks_name":"Kotebylu",
    "ks:ks_pop":70,
    "ks:ks_type":"HABITATION",
    "name:eng_x_preferred":[
        "Kotebylu"
    ],
    "wof:name":"Kotebylu",
    "wof:placetype":"locality",
    "wof:population":70
},
  "geometry": {"coordinates":[75.46832999999999,13.626745],"type":"Point"}
}