{
  "type": "Feature",
  "properties": {
    "iso:country":"IN",
    "ks:ks_name":"Dongarsarwar",
    "ks:ks_pop":582,
    "ks:ks_type":"VILLAGE",
    "name:eng_x_preferred":[
        "Dongarsarwar"
    ],
    "wof:name":"Dongarsarwar",
    "wof:placetype":"locality",
    "wof:population":582
},
  "geometry": {"coordinates":[81.538208,23.763457],"type":"Point"}
}