{
  "type": "Feature",
  "properties": {
    "gn:admin1_code":"38.0",
    "gn:admin2_code":"360",
    "gn:asciiname":"Amnari",
    "gn:country_code":"IN",
    "gn:dem":585,
    "gn:feature_class":"P",
    "gn:feature_code":"PPL",
    "gn:name":"Amn\u0101ri",
    "gn:population":0,
    "gn:timezone":"Asia/Kolkata",
    "iso:country":"IN",
    "wof:name":"Amnari",
    "wof:placetype":"locality"
},
  "geometry": {"coordinates":[85.60451999999999,24.06471],"type":"Point"}
}