{
  "type": "Feature",
  "properties": {
    "gn:admin1_code":"35",
    "gn:admin2_code":"452.0",
    "gn:asciiname":"Gwari Khurd",
    "gn:country_code":"IN",
    "gn:dem":376,
    "gn:feature_class":"P",
    "gn:feature_code":"PPL",
    "gn:name":"Gw\u0101ri Khurd",
    "gn:population":0,
    "gn:timezone":"Asia/Kolkata",
    "iso:country":"IN",
    "ks:ks_alt_nam":"Gw\u0101ri Khurd",
    "ks:ks_name":"Gwari Khurd",
    "ks:ks_pop":111,
    "ks:ks_type":"VILLAGE",
    "name:eng_x_preferred":[
        "Gwari Khurd"
    ],
    "name:eng_x_variant":[
        "Gw\u0101ri Khurd"
    ],
    "wof:name":"Gwari Khurd",
    "wof:placetype":"locality",
    "wof:population":111
},
  "geometry": {"coordinates":[79.155457,22.839084],"type":"Point"}
}