{
  "type": "Feature",
  "properties": {
    "gn:admin1_code":"35",
    "gn:admin2_code":"428.0",
    "gn:asciiname":"Mahuwakhera",
    "gn:country_code":"IN",
    "gn:dem":340,
    "gn:feature_class":"P",
    "gn:feature_code":"PPL",
    "gn:name":"Mahuw\u0101khera",
    "gn:population":0,
    "gn:timezone":"Asia/Kolkata",
    "iso:country":"IN",
    "ks:ks_alt_nam":"Mahuw\u0101khera",
    "ks:ks_name":"Mahuwakhera",
    "ks:ks_type":"VILLAGE",
    "name:eng_x_preferred":[
        "Mahuwakhera"
    ],
    "name:eng_x_variant":[
        "Mahuw\u0101khera"
    ],
    "wof:name":"Mahuwakhera",
    "wof:placetype":"locality"
},
  "geometry": {"coordinates":[79.41618,24.051439],"type":"Point"}
}