{
  "type": "Feature",
  "properties": {
    "iso:country":"IN",
    "ks:ks_name":"Doddadommarapalya",
    "ks:ks_pop":245,
    "ks:ks_type":"HABITATION",
    "name:eng_x_preferred":[
        "Doddadommarapalya"
    ],
    "wof:name":"Doddadommarapalya",
    "wof:placetype":"locality",
    "wof:population":245
},
  "geometry": {"coordinates":[77.92642499999999,12.848614],"type":"Point"}
}