{
  "type": "Feature",
  "properties": {
    "gn:admin1_code":"36.0",
    "gn:admin2_code":"174.0",
    "gn:asciiname":"Sarwaqazi",
    "gn:country_code":"IN",
    "gn:dem":107,
    "gn:feature_class":"P",
    "gn:feature_code":"PPL",
    "gn:name":"Sarw\u0101q\u0101zi",
    "gn:population":0,
    "gn:timezone":"Asia/Kolkata",
    "iso:country":"IN",
    "ks:ks_alt_nam":"Sarw\u0101q\u0101zi",
    "ks:ks_name":"Sarwaqazi",
    "ks:ks_pop":784,
    "ks:ks_type":"VILLAGE",
    "ks:ks_uagg_main":0,
    "name:eng_x_preferred":[
        "Sarwaqazi"
    ],
    "name:eng_x_variant":[
        "Sarw\u0101q\u0101zi"
    ],
    "wof:name":"Sarwaqazi",
    "wof:placetype":"neighbourhood",
    "wof:population":784
},
  "geometry": {"coordinates":[81.558161,25.527603],"type":"Point"}
}