{
  "type": "Feature",
  "properties": {
    "iso:country":"IN",
    "ks:ks_name":"Madhavipada",
    "ks:ks_pop":127,
    "ks:ks_type":"HABITATION",
    "name:eng_x_preferred":[
        "Madhavipada"
    ],
    "wof:name":"Madhavipada",
    "wof:placetype":"locality",
    "wof:population":127
},
  "geometry": {"coordinates":[72.991074,19.381234],"type":"Point"}
}