{
  "type": "Feature",
  "properties": {
    "gn:admin1_code":"02",
    "gn:admin2_code":"549.0",
    "gn:asciiname":"Surareddipalem",
    "gn:country_code":"IN",
    "gn:dem":11,
    "gn:feature_class":"P",
    "gn:feature_code":"PPL",
    "gn:name":"S\u016br\u0101reddip\u0101lem",
    "gn:population":0,
    "gn:timezone":"Asia/Kolkata",
    "iso:country":"IN",
    "name:und_x_variant":[
        "S\u016br\u0101reddip\u0101lem",
        "S\u016brareddip\u0101lem"
    ],
    "wof:name":"Surareddipalem",
    "wof:placetype":"locality"
},
  "geometry": {"coordinates":[80.04943,15.41211],"type":"Point"}
}