{
  "type": "Feature",
  "properties": {
    "iso:country":"IN",
    "ks:ks_alt_nam":"kalyan singh ki  dhani",
    "ks:ks_name":"Kalyan Singh Ki Dhani",
    "ks:ks_pop":1362,
    "ks:ks_type":"HABITATION",
    "name:eng_x_preferred":[
        "Kalyan Singh Ki Dhani"
    ],
    "name:eng_x_variant":[
        "kalyan singh ki  dhani"
    ],
    "wof:name":"Kalyan Singh Ki Dhani",
    "wof:placetype":"locality",
    "wof:population":1362
},
  "geometry": {"coordinates":[72.250664,25.677194],"type":"Point"}
}