{
  "type": "Feature",
  "properties": {
    "iso:country":"IN",
    "ks:ks_alt_nam":"S\u0101mtha",
    "ks:ks_name":"Samtha",
    "ks:ks_pop":1171,
    "ks:ks_type":"VILLAGE",
    "name:eng_x_preferred":[
        "Samtha"
    ],
    "name:eng_x_variant":[
        "S\u0101mtha"
    ],
    "wof:name":"Samtha",
    "wof:placetype":"locality",
    "wof:population":1171
},
  "geometry": {"coordinates":[85.11586200000001,22.267335],"type":"Point"}
}