{
  "type": "Feature",
  "properties": {
    "iso:country":"IN",
    "ks:ks_name":"Anandapur N E",
    "ks:ks_pop":311,
    "ks:ks_type":"HABITATION",
    "name:eng_x_preferred":[
        "Anandapur N E"
    ],
    "wof:name":"Anandapur N E",
    "wof:placetype":"locality",
    "wof:population":311
},
  "geometry": {"coordinates":[91.058308,26.479484],"type":"Point"}
}