{
  "type": "Feature",
  "properties": {
    "gn:admin1_code":"38.0",
    "gn:admin2_code":"353.0",
    "gn:asciiname":"Barkibathan",
    "gn:country_code":"IN",
    "gn:dem":86,
    "gn:feature_class":"P",
    "gn:feature_code":"PPL",
    "gn:name":"B\u0101rkib\u0101th\u0101n",
    "gn:population":0,
    "gn:timezone":"Asia/Kolkata",
    "iso:country":"IN",
    "ks:ks_name":"Birkhibathan",
    "ks:ks_pop":517,
    "ks:ks_type":"VILLAGE",
    "name:eng_x_preferred":[
        "Birkhibathan"
    ],
    "name:eng_x_variant":[
        "Barkibathan"
    ],
    "wof:name":"Birkhibathan",
    "wof:placetype":"locality",
    "wof:population":517
},
  "geometry": {"coordinates":[87.609854,24.459158],"type":"Point"}
}