{
  "type": "Feature",
  "properties": {
    "gn:admin1_code":"36.0",
    "gn:admin2_code":"185.0",
    "gn:asciiname":"Awadh",
    "gn:country_code":"IN",
    "gn:dem":102,
    "gn:feature_class":"P",
    "gn:feature_code":"PPL",
    "gn:name":"Aw\u0101dh",
    "gn:population":0,
    "gn:timezone":"Asia/Kolkata",
    "iso:country":"IN",
    "name:aze_x_preferred":[
        "Aud"
    ],
    "name:bih_x_preferred":[
        "\u0905\u0935\u0927"
    ],
    "name:deu_x_preferred":[
        "Avadh"
    ],
    "name:fas_x_preferred":[
        "\u0627\u0648\u062f\u0647"
    ],
    "name:fra_x_preferred":[
        "Awadh"
    ],
    "name:heb_x_preferred":[
        "\u05d0\u05d5\u05d5\u05d3"
    ],
    "name:hin_x_preferred":[
        "\u0905\u0935\u0927"
    ],
    "name:hun_x_preferred":[
        "Aud \u00e1llam"
    ],
    "name:ita_x_preferred":[
        "Awadh"
    ],
    "name:kan_x_preferred":[
        "\u0c85\u0cb5\u0ca7\u0ccd"
    ],
    "name:kat_x_preferred":[
        "\u10d0\u10e3\u10d3\u10d8"
    ],
    "name:mal_x_preferred":[
        "\u0d05\u0d35\u0d27\u0d4d"
    ],
    "name:mar_x_preferred":[
        "\u0905\u0935\u0927"
    ],
    "name:nep_x_preferred":[
        "\u0905\u0935\u0927"
    ],
    "name:nld_x_preferred":[
        "Avadh"
    ],
    "name:nor_x_preferred":[
        "Oudh"
    ],
    "name:pan_x_preferred":[
        "\u0a05\u0a09\u0a27"
    ],
    "name:pnb_x_preferred":[
        "\u0627\u0648\u062f\u06be"
    ],
    "name:por_x_preferred":[
        "Oude"
    ],
    "name:rus_x_preferred":[
        "\u0410\u0443\u0434"
    ],
    "name:spa_x_preferred":[
        "Oudh"
    ],
    "name:swe_x_preferred":[
        "Awadh"
    ],
    "name:tam_x_preferred":[
        "\u0b85\u0bb5\u0ba4\u0bcd"
    ],
    "name:tgl_x_preferred":[
        "Awadh"
    ],
    "name:tha_x_preferred":[
        "\u0e2d\u0e27\u0e31\u0e18"
    ],
    "name:ukr_x_preferred":[
        "\u0410\u0443\u0434"
    ],
    "name:urd_x_preferred":[
        "\u0627\u0648\u062f\u06be"
    ],
    "wof:name":"Awadh",
    "wof:placetype":"neighbourhood"
},
  "geometry": {"coordinates":[82.24491,26.9266],"type":"Point"}
}