{
  "type": "Feature",
  "properties": {
    "iso:country":"IN",
    "ks:ks_name":"Motia No2",
    "ks:ks_pop":999,
    "ks:ks_type":"HABITATION",
    "name:eng_x_preferred":[
        "Motia No2"
    ],
    "wof:name":"Motia No2",
    "wof:placetype":"locality",
    "wof:population":999
},
  "geometry": {"coordinates":[93.862644,27.05745],"type":"Point"}
}