{
  "type": "Feature",
  "properties": {
    "iso:country":"IN",
    "ks:ks_name":"Madhupur",
    "ks:ks_pop":52,
    "ks:ks_type":"VILLAGE",
    "name:eng_x_preferred":[
        "Madhupur"
    ],
    "wof:name":"Madhupur",
    "wof:placetype":"locality",
    "wof:population":52
},
  "geometry": {"coordinates":[85.24146,20.424106],"type":"Point"}
}