{
  "type": "Feature",
  "properties": {
    "iso:country":"IN",
    "ks:ks_alt_nam":"Konampattiyan vattam",
    "ks:ks_name":"Konampattiyan Vattam",
    "ks:ks_pop":250,
    "ks:ks_type":"HABITATION",
    "ks:ks_uagg_main":0,
    "name:eng_x_preferred":[
        "Konampattiyan Vattam"
    ],
    "wof:name":"Konampattiyan Vattam",
    "wof:placetype":"neighbourhood",
    "wof:population":250
},
  "geometry": {"coordinates":[78.529346,12.572066],"type":"Point"}
}