{
  "type": "Feature",
  "properties": {
    "iso:country":"IN",
    "ks:ks_name":"Bhampuri",
    "ks:ks_pop":28,
    "ks:ks_type":"HABITATION",
    "name:eng_x_preferred":[
        "Bhampuri"
    ],
    "wof:name":"Bhampuri",
    "wof:placetype":"locality",
    "wof:population":28
},
  "geometry": {"coordinates":[78.664998,21.275099],"type":"Point"}
}