{
  "type": "Feature",
  "properties": {
    "iso:country":"IN",
    "ks:ks_name":"Jafrabad",
    "ks:ks_pop":1226,
    "ks:ks_type":"VILLAGE",
    "ks:ks_uagg_main":0,
    "name:eng_x_preferred":[
        "Jafrabad"
    ],
    "wof:name":"Jafrabad",
    "wof:placetype":"neighbourhood",
    "wof:population":1226
},
  "geometry": {"coordinates":[88.31336400000001,24.190408],"type":"Point"}
}