{
  "type": "Feature",
  "properties": {
    "gn:admin1_code":"36",
    "gn:admin2_code":"202.0",
    "gn:asciiname":"Patti East",
    "gn:country_code":"IN",
    "gn:dem":161,
    "gn:feature_class":"P",
    "gn:feature_code":"PPL",
    "gn:name":"Patti East",
    "gn:population":0,
    "gn:timezone":"Asia/Kolkata",
    "iso:country":"IN",
    "wof:name":"Patti East",
    "wof:placetype":"neighbourhood"
},
  "geometry": {"coordinates":[79.14337999999999,27.60069],"type":"Point"}
}