{
  "type": "Feature",
  "properties": {
    "gn:admin1_code":"19",
    "gn:admin2_code":"559.0",
    "gn:asciiname":"Shakodi",
    "gn:country_code":"IN",
    "gn:dem":367,
    "gn:feature_class":"P",
    "gn:feature_code":"PPL",
    "gn:name":"Sh\u0101kodi",
    "gn:population":0,
    "gn:timezone":"Asia/Kolkata",
    "iso:country":"IN",
    "wof:name":"Shakodi",
    "wof:placetype":"neighbourhood"
},
  "geometry": {"coordinates":[77.40857,16.27682],"type":"Point"}
}