{
  "type": "Feature",
  "properties": {
    "iso:country":"IN",
    "ks:ks_name":"Dhummadand",
    "ks:ks_pop":241,
    "ks:ks_type":"VILLAGE",
    "name:eng_x_preferred":[
        "Dhummadand"
    ],
    "wof:name":"Dhummadand",
    "wof:placetype":"locality",
    "wof:population":241
},
  "geometry": {"coordinates":[82.731544,24.015745],"type":"Point"}
}