{
  "type": "Feature",
  "properties": {
    "gn:admin1_code":"25.0",
    "gn:admin2_code":"602.0",
    "gn:asciiname":"Samirajukhandriga",
    "gn:country_code":"IN",
    "gn:dem":170,
    "gn:feature_class":"P",
    "gn:feature_code":"PPL",
    "gn:name":"Samir\u0101jukhandriga",
    "gn:population":0,
    "gn:timezone":"Asia/Kolkata",
    "iso:country":"IN",
    "wof:name":"Samirajukhandriga",
    "wof:placetype":"locality"
},
  "geometry": {"coordinates":[79.44674000000001,13.19829],"type":"Point"}
}