{
  "type": "Feature",
  "properties": {
    "iso:country":"IN",
    "ks:ks_name":"Mundolalu",
    "ks:ks_pop":34,
    "ks:ks_type":"HABITATION",
    "name:eng_x_preferred":[
        "Mundolalu"
    ],
    "wof:name":"Mundolalu",
    "wof:placetype":"locality",
    "wof:population":34
},
  "geometry": {"coordinates":[75.315647,13.40031],"type":"Point"}
}