{
  "type": "Feature",
  "properties": {
    "iso:country":"IN",
    "ks:ks_name":"Ahmed Nagar",
    "ks:ks_pop":275,
    "ks:ks_type":"HABITATION",
    "name:eng_x_preferred":[
        "Ahmed Nagar"
    ],
    "wof:name":"Ahmed Nagar",
    "wof:placetype":"locality",
    "wof:population":275
},
  "geometry": {"coordinates":[91.950197,26.231372],"type":"Point"}
}