{
  "type": "Feature",
  "properties": {
    "gn:admin1_code":"39.0",
    "gn:asciiname":"Manpur",
    "gn:country_code":"IN",
    "gn:dem":425,
    "gn:feature_class":"P",
    "gn:feature_code":"PPL",
    "gn:name":"M\u0101npur",
    "gn:population":0,
    "gn:timezone":"Asia/Kolkata",
    "iso:country":"IN",
    "wof:name":"Manpur",
    "wof:placetype":"locality"
},
  "geometry": {"coordinates":[77.70184999999999,30.46803],"type":"Point"}
}