{
  "type": "Feature",
  "properties": {
    "iso:country":"IN",
    "ks:ks_alt_nam":"HARIZAN",
    "ks:ks_name":"Harizan",
    "ks:ks_pop":400,
    "ks:ks_type":"HABITATION",
    "name:eng_x_preferred":[
        "Harizan"
    ],
    "wof:name":"Harizan",
    "wof:placetype":"locality",
    "wof:population":400
},
  "geometry": {"coordinates":[82.096541,25.616173],"type":"Point"}
}