{
  "type": "Feature",
  "properties": {
    "iso:country":"IN",
    "ks:ks_name":"Kattakindapalem",
    "ks:ks_pop":207,
    "ks:ks_type":"HABITATION",
    "name:eng_x_preferred":[
        "Kattakindapalem"
    ],
    "wof:name":"Kattakindapalem",
    "wof:placetype":"locality",
    "wof:population":207
},
  "geometry": {"coordinates":[78.79190800000001,13.641543],"type":"Point"}
}