{
  "type": "Feature",
  "properties": {
    "iso:country":"IN",
    "ks:ks_name":"Batawali",
    "ks:ks_pop":2684,
    "ks:ks_type":"VILLAGE",
    "ks:ks_uagg_main":0,
    "name:eng_x_preferred":[
        "Batawali"
    ],
    "wof:name":"Batawali",
    "wof:placetype":"neighbourhood",
    "wof:population":2684
},
  "geometry": {"coordinates":[77.947576,29.219646],"type":"Point"}
}