{
  "type": "Feature",
  "properties": {
    "gn:admin1_code":"19.0",
    "gn:admin2_code":"574.0",
    "gn:asciiname":"Mudigere",
    "gn:country_code":"IN",
    "gn:dem":970,
    "gn:feature_class":"P",
    "gn:feature_code":"PPL",
    "gn:name":"Mudigere",
    "gn:population":0,
    "gn:timezone":"Asia/Kolkata",
    "iso:country":"IN",
    "name:ben_x_preferred":[
        "\u09ae\u09c1\u09a6\u09bf\u0997\u09c7\u09b0\u09c7"
    ],
    "name:bpy_x_preferred":[
        "\u09ae\u09c1\u09a6\u09bf\u0997\u09c7\u09b0\u09c7"
    ],
    "name:ceb_x_preferred":[
        "Mudigere"
    ],
    "name:ita_x_preferred":[
        "Mudigere"
    ],
    "name:kan_x_preferred":[
        "\u0cae\u0cc2\u0ca1\u0cbf\u0c97\u0cc6\u0cb0\u0cc6"
    ],
    "name:mlg_x_preferred":[
        "Mudigere"
    ],
    "name:msa_x_preferred":[
        "Mudigere"
    ],
    "name:new_x_preferred":[
        "\u092e\u0941\u0926\u093f\u0917\u0947\u0930\u0940"
    ],
    "name:nld_x_preferred":[
        "Mudigere"
    ],
    "name:por_x_preferred":[
        "Mudigere"
    ],
    "name:vie_x_preferred":[
        "Mudigere"
    ],
    "name:zho_x_preferred":[
        "\u7a46\u8fea\u76d6\u96f7"
    ],
    "wof:name":"Mudigere",
    "wof:placetype":"locality"
},
  "geometry": {"coordinates":[75.89493,13.16978],"type":"Point"}
}