{
  "type": "Feature",
  "properties": {
    "iso:country":"IN",
    "ks:ks_alt_nam":"Bhavani pur Basa",
    "ks:ks_name":"Bhavani Pur Basa",
    "ks:ks_pop":174,
    "ks:ks_type":"HABITATION",
    "name:eng_x_preferred":[
        "Bhavani Pur Basa"
    ],
    "wof:name":"Bhavani Pur Basa",
    "wof:placetype":"locality",
    "wof:population":174
},
  "geometry": {"coordinates":[86.863783,25.511625],"type":"Point"}
}