{
  "type": "Feature",
  "properties": {
    "gn:admin1_code":"34.0",
    "gn:admin2_code":"234.0",
    "gn:asciiname":"Lilkantpur",
    "gn:country_code":"IN",
    "gn:dem":89,
    "gn:feature_class":"P",
    "gn:feature_code":"PPL",
    "gn:name":"Lilkantpur",
    "gn:population":0,
    "gn:timezone":"Asia/Kolkata",
    "iso:country":"IN",
    "ks:ks_name":"Nilkanthpur",
    "ks:ks_pop":555,
    "ks:ks_type":"HABITATION",
    "name:eng_x_preferred":[
        "Nilkanthpur"
    ],
    "name:eng_x_variant":[
        "Lilkantpur"
    ],
    "wof:name":"Nilkanthpur",
    "wof:placetype":"locality",
    "wof:population":555
},
  "geometry": {"coordinates":[84.196265,25.25674],"type":"Point"}
}