{
  "type": "Feature",
  "properties": {
    "iso:country":"IN",
    "ks:ks_name":"Barakhurd",
    "ks:ks_pop":957,
    "ks:ks_type":"HABITATION",
    "name:eng_x_preferred":[
        "Barakhurd"
    ],
    "wof:name":"Barakhurd",
    "wof:placetype":"locality",
    "wof:population":957
},
  "geometry": {"coordinates":[81.76979300000001,24.999037],"type":"Point"}
}