{
  "type": "Feature",
  "properties": {
    "iso:country":"IN",
    "ks:ks_alt_nam":"Gh\u0101ghr\u0101",
    "ks:ks_name":"Ghaghra",
    "ks:ks_pop":908,
    "ks:ks_type":"VILLAGE",
    "name:eng_x_preferred":[
        "Ghaghra"
    ],
    "name:eng_x_variant":[
        "Gh\u0101ghr\u0101"
    ],
    "wof:name":"Ghaghra",
    "wof:placetype":"locality",
    "wof:population":908
},
  "geometry": {"coordinates":[84.41114399999999,23.506742],"type":"Point"}
}