{
  "type": "Feature",
  "properties": {
    "iso:country":"IN",
    "ks:ks_name":"Chak Ramnagar",
    "ks:ks_pop":1959,
    "ks:ks_type":"VILLAGE",
    "ks:ks_uagg_main":0,
    "name:eng_x_preferred":[
        "Chak Ramnagar"
    ],
    "wof:name":"Chak Ramnagar",
    "wof:placetype":"locality",
    "wof:population":1959
},
  "geometry": {"coordinates":[88.332098,22.45117],"type":"Point"}
}