{
  "type": "Feature",
  "properties": {
    "iso:country":"IN",
    "ks:ks_name":"Pattimalan",
    "ks:ks_pop":1040,
    "ks:ks_type":"HABITATION",
    "name:eng_x_preferred":[
        "Pattimalan"
    ],
    "wof:name":"Pattimalan",
    "wof:placetype":"locality",
    "wof:population":1040
},
  "geometry": {"coordinates":[76.66611399999999,11.137814],"type":"Point"}
}