{
  "type": "Feature",
  "properties": {
    "iso:country":"IN",
    "ks:ks_name":"Reabahal Kunjabahal",
    "ks:ks_pop":219,
    "ks:ks_type":"VILLAGE",
    "name:eng_x_preferred":[
        "Reabahal Kunjabahal"
    ],
    "wof:name":"Reabahal Kunjabahal",
    "wof:placetype":"locality",
    "wof:population":219
},
  "geometry": {"coordinates":[84.46396799999999,21.518731],"type":"Point"}
}