{
  "type": "Feature",
  "properties": {
    "iso:country":"IN",
    "ks:ks_alt_nam":"yuva rashmi jn",
    "ks:ks_name":"Yuva Rashmi Jn",
    "ks:ks_pop":458,
    "ks:ks_type":"HABITATION",
    "name:eng_x_preferred":[
        "Yuva Rashmi Jn"
    ],
    "wof:name":"Yuva Rashmi Jn",
    "wof:placetype":"locality",
    "wof:population":458
},
  "geometry": {"coordinates":[76.18925400000001,10.33041],"type":"Point"}
}