{
  "type": "Feature",
  "properties": {
    "gn:admin1_code":"17",
    "gn:admin2_code":"274.0",
    "gn:asciiname":"Thlanship",
    "gn:country_code":"IN",
    "gn:dem":1383,
    "gn:feature_class":"P",
    "gn:feature_code":"PPL",
    "gn:name":"Thlanship",
    "gn:population":0,
    "gn:timezone":"Asia/Kolkata",
    "iso:country":"IN",
    "name:und_x_variant":[
        "Hanship",
        "Thlanship"
    ],
    "wof:name":"Thlanship",
    "wof:placetype":"locality"
},
  "geometry": {"coordinates":[93.20842,24.14403],"type":"Point"}
}