{
  "type": "Feature",
  "properties": {
    "iso:country":"IN",
    "ks:ks_alt_nam":"Satpute wasti",
    "ks:ks_name":"Satpute Wasti",
    "ks:ks_pop":194,
    "ks:ks_type":"HABITATION",
    "name:eng_x_preferred":[
        "Satpute Wasti"
    ],
    "wof:name":"Satpute Wasti",
    "wof:placetype":"locality",
    "wof:population":194
},
  "geometry": {"coordinates":[75.135757,19.323703],"type":"Point"}
}