{
  "type": "Feature",
  "properties": {
    "iso:country":"IN",
    "qs:name":"Dlf City Phase 4",
    "qs:name_adm0":"India",
    "qs:name_adm1":"Haryana",
    "qs:photos":209,
    "qs:photos_1k":42,
    "qs:photos_9k":1,
    "qs:photos_9r":4,
    "qs:photos_all":209,
    "qs:photos_sr":4,
    "qs:placetype":"Suburb",
    "qs:pop_sr":"0",
    "wof:name":"Dlf City Phase 4",
    "wof:placetype":"neighbourhood"
},
  "geometry": {"coordinates":[77.089381,28.476726],"type":"Point"}
}