{
  "type": "Feature",
  "properties": {
    "iso:country":"IN",
    "name:ara_x_preferred":[
        "\u0645\u062f\u064a\u0646\u0629 \u062f\u0644\u0641 \u0627\u0644\u0645\u0631\u062d\u0644\u0629 4"
    ],
    "name:ben_bn_x_preferred":[
        "\u09a1\u09bf\u098f\u09b2\u098f\u09ab \u09b8\u09bf\u099f\u09bf \u09ab\u09c7\u099c 4"
    ],
    "name:ben_in_x_preferred":[
        "\u09a1\u09bf\u098f\u09b2\u098f\u09ab \u09b8\u09bf\u099f\u09bf \u09ab\u09c7\u099c 4"
    ],
    "name:guj_x_preferred":[
        "\u0aa1\u0ac0\u0a8f\u0ab2\u0a8f\u0aab \u0ab8\u0abf\u0a9f\u0ac0 \u0aa4\u0aac\u0a95\u0acd\u0a95\u0acb 4"
    ],
    "name:hin_x_preferred":[
        "\u0921\u0940\u090f\u0932\u090f\u095e \u0938\u093f\u091f\u0940 \u092b\u0947\u091c 4"
    ],
    "name:kan_x_preferred":[
        "\u0ca1\u0cbf\u0c8e\u0cb2\u0ccd"
    ],
    "name:mal_x_preferred":[
        "Dlf \u0d38\u0d3f\u0d31\u0d4d\u0d31\u0d3f \u0d18\u0d1f\u0d4d\u0d1f\u0d02 4"
    ],
    "name:mar_x_preferred":[
        "Dlf \u0938\u093f\u091f\u0940 \u092b\u0947\u091c 4"
    ],
    "name:pan_x_preferred":[
        "\u0a21\u0a40\u0a10\u0a32\u0a10\u0a2b\u0a3c \u0a38\u0a3f\u0a1f\u0a40 \u0a2b\u0a47\u0a1c\u0a3c 4"
    ],
    "name:tam_x_preferred":[
        "\u0b9f\u0bbf\u0b8e\u0bb2\u0bcd\u0b8e\u0b83\u0baa\u0bcd \u0ba8\u0b95\u0bb0\u0bae\u0bcd \u0ba8\u0bbf\u0bb2\u0bc8 4"
    ],
    "name:tel_x_preferred":[
        "\u0c21\u0c3f\u0c0e\u0c32\u0c4d\u0c0e\u0c2b\u0c4d \u0c38\u0c3f\u0c1f\u0c40 \u0c2b\u0c47\u0c1c\u0c4d 4"
    ],
    "name:urd_x_preferred":[
        "\u0688\u06cc \u0627\u06cc\u0644 \u0627\u06cc\u0641 \u0633\u0679\u06cc \u0641\u06cc\u0632 4"
    ],
    "qs:name":"Dlf City Phase 4",
    "qs:name_adm0":"India",
    "qs:name_adm1":"Haryana",
    "qs:photos":209,
    "qs:photos_1k":42,
    "qs:photos_9k":1,
    "qs:photos_9r":4,
    "qs:photos_all":209,
    "qs:photos_sr":4,
    "qs:placetype":"Suburb",
    "qs:pop_sr":"0",
    "wof:name":"Dlf City Phase 4",
    "wof:placetype":"neighbourhood"
},
  "geometry": {"coordinates":[77.089381,28.476726],"type":"Point"}
}