{
  "type": "Feature",
  "properties": {
    "gn:admin1_code":"36",
    "gn:admin2_code":"170.0",
    "gn:asciiname":"Baghonda",
    "gn:country_code":"IN",
    "gn:dem":115,
    "gn:feature_class":"P",
    "gn:feature_code":"PPL",
    "gn:name":"Baghonda",
    "gn:population":0,
    "gn:timezone":"Asia/Kolkata",
    "iso:country":"IN",
    "ks:ks_name":"Baghonda",
    "ks:ks_type":"VILLAGE",
    "name:eng_x_preferred":[
        "Baghonda"
    ],
    "wof:name":"Baghonda",
    "wof:placetype":"locality"
},
  "geometry": {"coordinates":[80.547406,25.552869],"type":"Point"}
}