{
  "type": "Feature",
  "properties": {
    "iso:country":"IN",
    "ks:ks_name":"Buzurg",
    "ks:ks_pop":450,
    "ks:ks_type":"HABITATION",
    "name:eng_x_preferred":[
        "Buzurg"
    ],
    "wof:name":"Buzurg",
    "wof:placetype":"locality",
    "wof:population":450
},
  "geometry": {"coordinates":[78.93789700000001,25.648397],"type":"Point"}
}