{
  "type": "Feature",
  "properties": {
    "iso:country":"IN",
    "ks:ks_name":"Phuljhor",
    "ks:ks_pop":181,
    "ks:ks_type":"VILLAGE",
    "name:eng_x_preferred":[
        "Phuljhor"
    ],
    "wof:name":"Phuljhor",
    "wof:placetype":"locality",
    "wof:population":181
},
  "geometry": {"coordinates":[86.71881399999999,22.752611],"type":"Point"}
}