{
  "type": "Feature",
  "properties": {
    "iso:country":"IN",
    "ks:ks_name":"Kanduan Purwa",
    "ks:ks_pop":133,
    "ks:ks_type":"HABITATION",
    "ks:ks_uagg_main":0,
    "name:eng_x_preferred":[
        "Kanduan Purwa"
    ],
    "wof:name":"Kanduan Purwa",
    "wof:placetype":"neighbourhood",
    "wof:population":133
},
  "geometry": {"coordinates":[81.731573,27.15271],"type":"Point"}
}