{
  "type": "Feature",
  "properties": {
    "gn:admin1_code":"12.0",
    "gn:admin2_code":"6.0",
    "gn:asciiname":"Hasplot",
    "gn:country_code":"IN",
    "gn:dem":1421,
    "gn:feature_class":"P",
    "gn:feature_code":"PPL",
    "gn:name":"Haspl\u014dt",
    "gn:population":0,
    "gn:timezone":"Asia/Kolkata",
    "iso:country":"IN",
    "wof:name":"Hasplot",
    "wof:placetype":"locality"
},
  "geometry": {"coordinates":[74.36188,33.53818],"type":"Point"}
}