{
  "type": "Feature",
  "properties": {
    "iso:country":"IN",
    "ks:ks_name":"Bhamra",
    "ks:ks_pop":44,
    "ks:ks_type":"HABITATION",
    "name:eng_x_preferred":[
        "Bhamra"
    ],
    "wof:name":"Bhamra",
    "wof:placetype":"locality",
    "wof:population":44
},
  "geometry": {"coordinates":[78.555925,23.828395],"type":"Point"}
}