{
  "type": "Feature",
  "properties": {
    "iso:country":"IN",
    "ks:ks_name":"Seri",
    "ks:ks_pop":122,
    "ks:ks_type":"HABITATION",
    "name:eng_x_preferred":[
        "Seri"
    ],
    "wof:name":"Seri",
    "wof:placetype":"locality",
    "wof:population":122
},
  "geometry": {"coordinates":[79.334858,10.875087],"type":"Point"}
}