{
  "type": "Feature",
  "properties": {
    "iso:country":"IN",
    "ks:ks_name":"Laxmijit Kobra Para",
    "ks:ks_pop":165,
    "ks:ks_type":"HABITATION",
    "name:eng_x_preferred":[
        "Laxmijit Kobra Para"
    ],
    "wof:name":"Laxmijit Kobra Para",
    "wof:placetype":"locality",
    "wof:population":165
},
  "geometry": {"coordinates":[92.121621,23.78503],"type":"Point"}
}