{
  "type": "Feature",
  "properties": {
    "iso:country":"IN",
    "ks:ks_name":"Maddiguntacheruvu",
    "ks:ks_pop":370,
    "ks:ks_type":"HABITATION",
    "name:eng_x_preferred":[
        "Maddiguntacheruvu"
    ],
    "wof:name":"Maddiguntacheruvu",
    "wof:placetype":"locality",
    "wof:population":370
},
  "geometry": {"coordinates":[81.809175,16.622945],"type":"Point"}
}