{
  "type": "Feature",
  "properties": {
    "iso:country":"IN",
    "ks:ks_name":"Nagartas",
    "ks:ks_pop":165,
    "ks:ks_type":"VILLAGE",
    "name:eng_x_preferred":[
        "Nagartas"
    ],
    "wof:name":"Nagartas",
    "wof:placetype":"locality",
    "wof:population":165
},
  "geometry": {"coordinates":[76.80250700000001,21.203203],"type":"Point"}
}