{
  "type": "Feature",
  "properties": {
    "iso:country":"IN",
    "ks:ks_name":"Phitkariya",
    "ks:ks_pop":214,
    "ks:ks_type":"VILLAGE",
    "name:eng_x_preferred":[
        "Phitkariya"
    ],
    "wof:name":"Phitkariya",
    "wof:placetype":"locality",
    "wof:population":214
},
  "geometry": {"coordinates":[86.92,24.584011],"type":"Point"}
}