{
  "type": "Feature",
  "properties": {
    "gn:admin1_code":"34",
    "gn:admin2_code":"233.0",
    "gn:asciiname":"Chheria",
    "gn:country_code":"IN",
    "gn:dem":71,
    "gn:feature_class":"P",
    "gn:feature_code":"PPL",
    "gn:name":"Chheria",
    "gn:population":0,
    "gn:timezone":"Asia/Kolkata",
    "iso:country":"IN",
    "wof:name":"Chheria",
    "wof:placetype":"locality"
},
  "geometry": {"coordinates":[83.67284000000002,25.24497],"type":"Point"}
}