{
  "type": "Feature",
  "properties": {
    "iso:country":"IN",
    "ks:ks_name":"Kouthugagudi",
    "ks:ks_pop":252,
    "ks:ks_type":"HABITATION",
    "name:eng_x_preferred":[
        "Kouthugagudi"
    ],
    "wof:name":"Kouthugagudi",
    "wof:placetype":"locality",
    "wof:population":252
},
  "geometry": {"coordinates":[79.64955999999999,10.690725],"type":"Point"}
}