{
  "type": "Feature",
  "properties": {
    "gn:admin1_code":"39",
    "gn:admin2_code":"58.0",
    "gn:asciiname":"Ghatna",
    "gn:country_code":"IN",
    "gn:dem":2704,
    "gn:feature_class":"P",
    "gn:feature_code":"PPL",
    "gn:name":"Ghatna",
    "gn:population":0,
    "gn:timezone":"Asia/Kolkata",
    "iso:country":"IN",
    "wof:name":"Ghatna",
    "wof:placetype":"locality"
},
  "geometry": {"coordinates":[79.16925999999999,30.55542],"type":"Point"}
}