{
  "type": "Feature",
  "properties": {
    "gn:admin1_code":"9.0",
    "gn:admin2_code":"492.0",
    "gn:asciiname":"Zankhvav",
    "gn:country_code":"IN",
    "gn:dem":119,
    "gn:feature_class":"P",
    "gn:feature_code":"PPL",
    "gn:name":"Zankhvav",
    "gn:population":0,
    "gn:timezone":"Asia/Kolkata",
    "iso:country":"IN",
    "name:tam_x_preferred":[
        "\u0b9a\u0bbe\u0b99\u0bcd\u0b95\u0bc1\u0bb5\u0bbe\u0bb5\u0bcd"
    ],
    "name:und_x_variant":[
        "Zankvav",
        "Zankhavav",
        "Zankhvav"
    ],
    "wof:name":"Zankhvav",
    "wof:placetype":"locality"
},
  "geometry": {"coordinates":[73.31919000000001,21.45118],"type":"Point"}
}