{
  "type": "Feature",
  "properties": {
    "iso:country":"IN",
    "ks:ks_name":"Jot Kusahwa",
    "ks:ks_type":"VILLAGE",
    "ks:ks_uagg_main":0,
    "name:eng_x_preferred":[
        "Jot Kusahwa"
    ],
    "wof:name":"Jot Kusahwa",
    "wof:placetype":"neighbourhood"
},
  "geometry": {"coordinates":[83.601187,26.450277],"type":"Point"}
}