{
  "type": "Feature",
  "properties": {
    "iso:country":"IN",
    "ks:ks_name":"Kandike",
    "ks:ks_pop":204,
    "ks:ks_type":"HABITATION",
    "name:eng_x_preferred":[
        "Kandike"
    ],
    "wof:name":"Kandike",
    "wof:placetype":"locality",
    "wof:population":204
},
  "geometry": {"coordinates":[74.79950700000001,13.482487],"type":"Point"}
}