{
  "type": "Feature",
  "properties": {
    "gn:admin1_code":"34.0",
    "gn:admin2_code":"216.0",
    "gn:asciiname":"Ghanipur Bejha",
    "gn:country_code":"IN",
    "gn:dem":51,
    "gn:feature_class":"P",
    "gn:feature_code":"PPL",
    "gn:name":"Ghan\u012bpur Bejha",
    "gn:population":0,
    "gn:timezone":"Asia/Kolkata",
    "iso:country":"IN",
    "ks:ks_alt_nam":"Ghan\u012bpur Bejha",
    "ks:ks_name":"Ghanipur Bejha",
    "ks:ks_pop":7138,
    "ks:ks_type":"VILLAGE",
    "name:eng_x_preferred":[
        "Ghanipur Bejha"
    ],
    "name:eng_x_variant":[
        "Ghan\u012bpur Bejha"
    ],
    "wof:name":"Ghanipur Bejha",
    "wof:placetype":"locality",
    "wof:population":7138
},
  "geometry": {"coordinates":[85.554762,25.928113],"type":"Point"}
}