{
  "type": "Feature",
  "properties": {
    "iso:country":"IN",
    "ks:ks_name":"Deengasi",
    "ks:ks_pop":1366,
    "ks:ks_type":"VILLAGE",
    "ks:ks_uagg_main":0,
    "name:eng_x_preferred":[
        "Deengasi"
    ],
    "wof:name":"Deengasi",
    "wof:placetype":"neighbourhood",
    "wof:population":1366
},
  "geometry": {"coordinates":[76.032028,24.670964],"type":"Point"}
}