{
  "type": "Feature",
  "properties": {
    "gn:admin1_code":"38.0",
    "gn:admin2_code":"353.0",
    "gn:asciiname":"Kanlapahari",
    "gn:country_code":"IN",
    "gn:dem":89,
    "gn:feature_class":"P",
    "gn:feature_code":"PPL",
    "gn:name":"Kanl\u0101pah\u0101ri",
    "gn:population":0,
    "gn:timezone":"Asia/Kolkata",
    "iso:country":"IN",
    "ks:ks_name":"Kangapahari",
    "ks:ks_pop":674,
    "ks:ks_type":"VILLAGE",
    "name:eng_x_preferred":[
        "Kangapahari"
    ],
    "name:eng_x_variant":[
        "Kanlapahari"
    ],
    "wof:name":"Kangapahari",
    "wof:placetype":"locality",
    "wof:population":674
},
  "geometry": {"coordinates":[87.671178,24.397519],"type":"Point"}
}