{
  "type": "Feature",
  "properties": {
    "gn:admin1_code":"38.0",
    "gn:admin2_code":"353.0",
    "gn:asciiname":"Kanlapahari",
    "gn:country_code":"IN",
    "gn:dem":89,
    "gn:feature_class":"P",
    "gn:feature_code":"PPL",
    "gn:name":"Kanl\u0101pah\u0101ri",
    "gn:population":0,
    "gn:timezone":"Asia/Kolkata",
    "iso:country":"IN",
    "wof:name":"Kanlapahari",
    "wof:placetype":"locality"
},
  "geometry": {"coordinates":[87.66969,24.39727],"type":"Point"}
}