{
  "type": "Feature",
  "properties": {
    "iso:country":"IN",
    "ks:ks_name":"Amha",
    "ks:ks_type":"VILLAGE",
    "name:eng_x_preferred":[
        "Amha"
    ],
    "wof:name":"Amha",
    "wof:placetype":"locality"
},
  "geometry": {"coordinates":[83.13429600000001,26.953177],"type":"Point"}
}