{
  "type": "Feature",
  "properties": {
    "iso:country":"IN",
    "ks:ks_name":"Hemlanaik Thanda",
    "ks:ks_pop":65,
    "ks:ks_type":"HABITATION",
    "name:eng_x_preferred":[
        "Hemlanaik Thanda"
    ],
    "wof:name":"Hemlanaik Thanda",
    "wof:placetype":"locality",
    "wof:population":65
},
  "geometry": {"coordinates":[77.849203,18.001747],"type":"Point"}
}