{
  "type": "Feature",
  "properties": {
    "gn:admin1_code":"29",
    "gn:admin2_code":"244.0",
    "gn:asciiname":"Kupup",
    "gn:country_code":"IN",
    "gn:dem":3974,
    "gn:feature_class":"P",
    "gn:feature_code":"PPL",
    "gn:name":"Kupup",
    "gn:population":0,
    "gn:timezone":"Asia/Kolkata",
    "iso:country":"IN",
    "wof:name":"Kupup",
    "wof:placetype":"locality"
},
  "geometry": {"coordinates":[88.84384,27.34243],"type":"Point"}
}