{
  "type": "Feature",
  "properties": {
    "gn:admin1_code":"2.0",
    "gn:admin2_code":"554.0",
    "gn:asciiname":"Mulakalacheruvu",
    "gn:country_code":"IN",
    "gn:dem":598,
    "gn:feature_class":"P",
    "gn:feature_code":"PPL",
    "gn:name":"Mulakalacheruvu",
    "gn:population":0,
    "gn:timezone":"Asia/Kolkata",
    "iso:country":"IN",
    "name:fra_x_preferred":[
        "Mulakalacheruvu"
    ],
    "name:new_x_preferred":[
        "\u092e\u0941\u0932\u0915\u0932\u091a\u0947\u0930\u0941\u0935\u0941 \u092e\u0923\u094d\u0921\u0932"
    ],
    "name:pam_x_preferred":[
        "Mulakalacheruvu"
    ],
    "name:tam_x_preferred":[
        "\u0bae\u0bc1\u0bb2\u0b95\u0bb2\u0b9a\u0bc6\u0bb0\u0bc1\u0bb5\u0bc1"
    ],
    "name:tel_x_preferred":[
        "\u0c2e\u0c41\u0c32\u0c15\u0c32\u0c1a\u0c46\u0c30\u0c41\u0c35\u0c41"
    ],
    "name:tgl_x_preferred":[
        "Mulakalacheruvu"
    ],
    "name:vie_x_preferred":[
        "Mulakalacheruvu"
    ],
    "wof:name":"Mulakalacheruvu",
    "wof:placetype":"locality"
},
  "geometry": {"coordinates":[78.26257,13.80132],"type":"Point"}
}