{
  "type": "Feature",
  "properties": {
    "iso:country":"IN",
    "ks:ks_name":"Udanadaka",
    "ks:ks_pop":9,
    "ks:ks_type":"HABITATION",
    "name:eng_x_preferred":[
        "Udanadaka"
    ],
    "wof:name":"Udanadaka",
    "wof:placetype":"locality",
    "wof:population":9
},
  "geometry": {"coordinates":[75.382525,12.743806],"type":"Point"}
}