{
  "type": "Feature",
  "properties": {
    "iso:country":"IN",
    "ks:ks_alt_nam":"CM Kothaindlu",
    "ks:ks_name":"Cm Kothaindlu",
    "ks:ks_pop":586,
    "ks:ks_type":"HABITATION",
    "name:eng_x_preferred":[
        "Cm Kothaindlu"
    ],
    "wof:name":"Cm Kothaindlu",
    "wof:placetype":"locality",
    "wof:population":586
},
  "geometry": {"coordinates":[79.209234,13.118026],"type":"Point"}
}