{
  "type": "Feature",
  "properties": {
    "gn:admin1_code":"21.0",
    "gn:admin2_code":"385.0",
    "gn:asciiname":"Balisinsa",
    "gn:country_code":"IN",
    "gn:dem":146,
    "gn:feature_class":"P",
    "gn:feature_code":"PPL",
    "gn:name":"Balisinsa",
    "gn:population":0,
    "gn:timezone":"Asia/Kolkata",
    "iso:country":"IN",
    "wof:name":"Balisinsa",
    "wof:placetype":"locality"
},
  "geometry": {"coordinates":[84.87113000000002,20.04083],"type":"Point"}
}