{
  "type": "Feature",
  "properties": {
    "gn:admin1_code":"12.0",
    "gn:admin2_code":"17.0",
    "gn:asciiname":"Suri Kundi",
    "gn:country_code":"IN",
    "gn:dem":1474,
    "gn:feature_class":"P",
    "gn:feature_code":"PPL",
    "gn:name":"S\u016bri Kundi",
    "gn:population":0,
    "gn:timezone":"Asia/Kolkata",
    "iso:country":"IN",
    "wof:name":"Suri Kundi",
    "wof:placetype":"locality"
},
  "geometry": {"coordinates":[75.05923,33.25595],"type":"Point"}
}