{
  "type": "Feature",
  "properties": {
    "iso:country":"IN",
    "ks:ks_name":"Praharajpur",
    "ks:ks_pop":294,
    "ks:ks_type":"VILLAGE",
    "name:eng_x_preferred":[
        "Praharajpur"
    ],
    "wof:name":"Praharajpur",
    "wof:placetype":"locality",
    "wof:population":294
},
  "geometry": {"coordinates":[87.04840900000001,21.70929],"type":"Point"}
}