{
  "type": "Feature",
  "properties": {
    "iso:country":"IN",
    "ks:ks_name":"Pikapar",
    "ks:ks_pop":576,
    "ks:ks_type":"VILLAGE",
    "ks:ks_uagg_main":0,
    "name:eng_x_preferred":[
        "Pikapar"
    ],
    "wof:name":"Pikapar",
    "wof:placetype":"neighbourhood",
    "wof:population":576
},
  "geometry": {"coordinates":[83.215386,27.324548],"type":"Point"}
}