{
  "type": "Feature",
  "properties": {
    "iso:country":"IN",
    "ks:ks_name":"Mandal Para",
    "ks:ks_pop":1021,
    "ks:ks_type":"HABITATION",
    "name:eng_x_preferred":[
        "Mandal Para"
    ],
    "wof:name":"Mandal Para",
    "wof:placetype":"locality",
    "wof:population":1021
},
  "geometry": {"coordinates":[88.84895899999999,22.278542],"type":"Point"}
}