{
  "type": "Feature",
  "properties": {
    "gn:admin1_code":"12.0",
    "gn:admin2_code":"008",
    "gn:asciiname":"Lachhpathar",
    "gn:country_code":"IN",
    "gn:dem":2667,
    "gn:feature_class":"P",
    "gn:feature_code":"PPL",
    "gn:name":"Lachhpathar",
    "gn:population":0,
    "gn:timezone":"Asia/Kolkata",
    "iso:country":"IN",
    "wof:name":"Lachhpathar",
    "wof:placetype":"locality"
},
  "geometry": {"coordinates":[74.12501,34.304],"type":"Point"}
}