{
  "type": "Feature",
  "properties": {
    "iso:country":"IN",
    "ks:ks_name":"Haila Kui",
    "ks:ks_pop":1564,
    "ks:ks_type":"HABITATION",
    "name:eng_x_preferred":[
        "Haila Kui"
    ],
    "wof:name":"Haila Kui",
    "wof:placetype":"locality",
    "wof:population":1564
},
  "geometry": {"coordinates":[73.63712200000001,24.153958],"type":"Point"}
}