{
  "type": "Feature",
  "properties": {
    "gn:admin1_code":"34.0",
    "gn:admin2_code":"220.0",
    "gn:asciiname":"Kaulesar",
    "gn:country_code":"IN",
    "gn:dem":59,
    "gn:feature_class":"P",
    "gn:feature_code":"PPL",
    "gn:name":"Kaulesar",
    "gn:population":0,
    "gn:timezone":"Asia/Kolkata",
    "iso:country":"IN",
    "ks:ks_name":"Kaulesar",
    "ks:ks_pop":643,
    "ks:ks_type":"VILLAGE",
    "name:eng_x_preferred":[
        "Kaulesar"
    ],
    "wof:name":"Kaulesar",
    "wof:placetype":"locality",
    "wof:population":643
},
  "geometry": {"coordinates":[85.214189,25.902227],"type":"Point"}
}