{
  "type": "Feature",
  "properties": {
    "gn:admin1_code":"36.0",
    "gn:admin2_code":"167",
    "gn:asciiname":"Agar",
    "gn:country_code":"IN",
    "gn:dem":334,
    "gn:feature_class":"P",
    "gn:feature_code":"PPL",
    "gn:name":"\u0100gar",
    "gn:population":0,
    "gn:timezone":"Asia/Kolkata",
    "iso:country":"IN",
    "name:und_x_variant":[
        "\u0100gar",
        "Agar"
    ],
    "wof:name":"Agar",
    "wof:placetype":"locality"
},
  "geometry": {"coordinates":[78.28978000000002,24.91261],"type":"Point"}
}