{
  "type": "Feature",
  "properties": {
    "iso:country":"IN",
    "ks:ks_name":"Lutherance",
    "ks:ks_pop":2600,
    "ks:ks_type":"HABITATION",
    "name:eng_x_preferred":[
        "Lutherance"
    ],
    "wof:name":"Lutherance",
    "wof:placetype":"locality",
    "wof:population":2600
},
  "geometry": {"coordinates":[76.34442,9.538008],"type":"Point"}
}