{
  "type": "Feature",
  "properties": {
    "iso:country":"IN",
    "ks:ks_name":"Dansari",
    "ks:ks_pop":1054,
    "ks:ks_type":"VILLAGE",
    "name:eng_x_preferred":[
        "Dansari"
    ],
    "wof:name":"Dansari",
    "wof:placetype":"locality",
    "wof:population":1054
},
  "geometry": {"coordinates":[85.841559,22.143236],"type":"Point"}
}