{
  "type": "Feature",
  "properties": {
    "iso:country":"IN",
    "ks:ks_name":"Daspattar South",
    "ks:ks_pop":1006,
    "ks:ks_type":"HABITATION",
    "name:eng_x_preferred":[
        "Daspattar South"
    ],
    "wof:name":"Daspattar South",
    "wof:placetype":"locality",
    "wof:population":1006
},
  "geometry": {"coordinates":[87.67197,25.77898],"type":"Point"}
}