{
  "type": "Feature",
  "properties": {
    "gn:admin1_code":"34.0",
    "gn:admin2_code":"207.0",
    "gn:asciiname":"Balbhadarpur",
    "gn:country_code":"IN",
    "gn:dem":55,
    "gn:feature_class":"P",
    "gn:feature_code":"PPL",
    "gn:name":"Balbhadarpur",
    "gn:population":0,
    "gn:timezone":"Asia/Kolkata",
    "iso:country":"IN",
    "wof:name":"Balbhadarpur",
    "wof:placetype":"locality"
},
  "geometry": {"coordinates":[86.27157,26.22013],"type":"Point"}
}