{
  "type": "Feature",
  "properties": {
    "iso:country":"IN",
    "ks:ks_name":"Siddharthnagar",
    "ks:ks_pop":42,
    "ks:ks_type":"HABITATION",
    "name:eng_x_preferred":[
        "Siddharthnagar"
    ],
    "wof:name":"Siddharthnagar",
    "wof:placetype":"locality",
    "wof:population":42
},
  "geometry": {"coordinates":[73.78473099999999,16.154089],"type":"Point"}
}