{
  "type": "Feature",
  "properties": {
    "gn:admin1_code":"19.0",
    "gn:admin2_code":"568.0",
    "gn:asciiname":"Siddapur",
    "gn:country_code":"IN",
    "gn:dem":677,
    "gn:feature_class":"P",
    "gn:feature_code":"PPL",
    "gn:name":"Sidd\u0101pur",
    "gn:population":0,
    "gn:timezone":"Asia/Kolkata",
    "iso:country":"IN",
    "ks:ks_name":"Siddapura",
    "ks:ks_pop":4,
    "ks:ks_type":"HABITATION",
    "name:eng_x_preferred":[
        "Siddapura"
    ],
    "name:eng_x_variant":[
        "Siddapur"
    ],
    "wof:name":"Siddapura",
    "wof:placetype":"locality",
    "wof:population":4
},
  "geometry": {"coordinates":[75.31151699999999,13.845465],"type":"Point"}
}