{
  "type": "Feature",
  "properties": {
    "iso:country":"IN",
    "ks:ks_name":"Khap Katahri",
    "ks:ks_pop":0,
    "ks:ks_type":"VILLAGE",
    "name:eng_x_preferred":[
        "Khap Katahri"
    ],
    "wof:name":"Khap Katahri",
    "wof:placetype":"locality",
    "wof:population":0
},
  "geometry": {"coordinates":[84.47514099999999,27.019359],"type":"Point"}
}