{
  "type": "Feature",
  "properties": {
    "iso:country":"IN",
    "ks:ks_name":"Kaikalu",
    "ks:ks_pop":18,
    "ks:ks_type":"HABITATION",
    "name:eng_x_preferred":[
        "Kaikalu"
    ],
    "wof:name":"Kaikalu",
    "wof:placetype":"locality",
    "wof:population":18
},
  "geometry": {"coordinates":[74.925411,13.876843],"type":"Point"}
}