{
  "type": "Feature",
  "properties": {
    "gn:admin1_code":"11.0",
    "gn:admin2_code":"27.0",
    "gn:asciiname":"Nuarh",
    "gn:country_code":"IN",
    "gn:dem":1928,
    "gn:feature_class":"P",
    "gn:feature_code":"PPL",
    "gn:name":"Nu\u0101rh",
    "gn:population":0,
    "gn:timezone":"Asia/Kolkata",
    "iso:country":"IN",
    "wof:name":"Nuarh",
    "wof:placetype":"locality"
},
  "geometry": {"coordinates":[77.12394,31.71844],"type":"Point"}
}