{
  "type": "Feature",
  "properties": {
    "gn:admin1_code":"34.0",
    "gn:admin2_code":"221.0",
    "gn:asciiname":"Bangraha",
    "gn:country_code":"IN",
    "gn:dem":54,
    "gn:feature_class":"P",
    "gn:feature_code":"PPL",
    "gn:name":"Bangr\u0101ha",
    "gn:population":0,
    "gn:timezone":"Asia/Kolkata",
    "iso:country":"IN",
    "ks:ks_alt_nam":"Bangr\u0101ha",
    "ks:ks_name":"Bangraha",
    "ks:ks_pop":112,
    "ks:ks_type":"VILLAGE",
    "name:eng_x_preferred":[
        "Bangraha"
    ],
    "name:eng_x_variant":[
        "Bangr\u0101ha"
    ],
    "wof:name":"Bangraha",
    "wof:placetype":"locality",
    "wof:population":112
},
  "geometry": {"coordinates":[85.744972,25.630728],"type":"Point"}
}