{
  "type": "Feature",
  "properties": {
    "iso:country":"IN",
    "ks:ks_name":"Muthyalamma Colony",
    "ks:ks_pop":92,
    "ks:ks_type":"HABITATION",
    "name:eng_x_preferred":[
        "Muthyalamma Colony"
    ],
    "wof:name":"Muthyalamma Colony",
    "wof:placetype":"locality",
    "wof:population":92
},
  "geometry": {"coordinates":[77.740252,14.449915],"type":"Point"}
}