{
  "type": "Feature",
  "properties": {
    "iso:country":"IN",
    "ks:ks_name":"Dona Gudar Panjgrain",
    "ks:ks_pop":0,
    "ks:ks_type":"VILLAGE",
    "name:eng_x_preferred":[
        "Dona Gudar Panjgrain"
    ],
    "wof:name":"Dona Gudar Panjgrain",
    "wof:placetype":"locality",
    "wof:population":0
},
  "geometry": {"coordinates":[74.269204,30.7237],"type":"Point"}
}