{
  "type": "Feature",
  "properties": {
    "iso:country":"IN",
    "ks:ks_name":"Vettikel",
    "ks:ks_pop":2083,
    "ks:ks_type":"HABITATION",
    "name:eng_x_preferred":[
        "Vettikel"
    ],
    "wof:name":"Vettikel",
    "wof:placetype":"locality",
    "wof:population":2083
},
  "geometry": {"coordinates":[76.45693,10.553994],"type":"Point"}
}