{
  "type": "Feature",
  "properties": {
    "iso:country":"IN",
    "ks:ks_name":"Suryanagar",
    "ks:ks_pop":786,
    "ks:ks_type":"HABITATION",
    "name:eng_x_preferred":[
        "Suryanagar"
    ],
    "wof:name":"Suryanagar",
    "wof:placetype":"locality",
    "wof:population":786
},
  "geometry": {"coordinates":[72.991197,19.912694],"type":"Point"}
}