{
  "type": "Feature",
  "properties": {
    "iso:country":"IN",
    "ks:ks_name":"Pardhi",
    "ks:ks_pop":497,
    "ks:ks_type":"VILLAGE",
    "name:eng_x_preferred":[
        "Pardhi"
    ],
    "wof:name":"Pardhi",
    "wof:placetype":"locality",
    "wof:population":497
},
  "geometry": {"coordinates":[76.311796,19.593532],"type":"Point"}
}