{
  "type": "Feature",
  "properties": {
    "iso:country":"IN",
    "ks:ks_name":"Kagey Khasmahal",
    "ks:ks_pop":1583,
    "ks:ks_type":"VILLAGE",
    "name:eng_x_preferred":[
        "Kagey Khasmahal"
    ],
    "wof:name":"Kagey Khasmahal",
    "wof:placetype":"locality",
    "wof:population":1583
},
  "geometry": {"coordinates":[88.634502,27.137275],"type":"Point"}
}