{
  "type": "Feature",
  "properties": {
    "iso:country":"IN",
    "ks:ks_name":"Chanwar Amaithii",
    "ks:ks_pop":0,
    "ks:ks_type":"VILLAGE",
    "name:eng_x_preferred":[
        "Chanwar Amaithii"
    ],
    "wof:name":"Chanwar Amaithii",
    "wof:placetype":"locality",
    "wof:population":0
},
  "geometry": {"coordinates":[84.443352,26.440759],"type":"Point"}
}