{
  "type": "Feature",
  "properties": {
    "iso:country":"IN",
    "ks:ks_alt_nam":"petthur",
    "ks:ks_name":"Petthur",
    "ks:ks_pop":80,
    "ks:ks_type":"HABITATION",
    "name:eng_x_preferred":[
        "Petthur"
    ],
    "wof:name":"Petthur",
    "wof:placetype":"locality",
    "wof:population":80
},
  "geometry": {"coordinates":[78.401776,10.830421],"type":"Point"}
}