{
  "type": "Feature",
  "properties": {
    "iso:country":"IN",
    "ks:ks_alt_nam":"BELJHIRIYA",
    "ks:ks_name":"Beljhiriya",
    "ks:ks_pop":193,
    "ks:ks_type":"HABITATION",
    "name:eng_x_preferred":[
        "Beljhiriya"
    ],
    "wof:name":"Beljhiriya",
    "wof:placetype":"locality",
    "wof:population":193
},
  "geometry": {"coordinates":[82.13714299999999,23.035022],"type":"Point"}
}