{
  "type": "Feature",
  "properties": {
    "gn:admin1_code":"40.0",
    "gn:admin2_code":"532.0",
    "gn:asciiname":"Samela",
    "gn:country_code":"IN",
    "gn:dem":213,
    "gn:feature_class":"P",
    "gn:feature_code":"PPL",
    "gn:name":"S\u0101mela",
    "gn:population":0,
    "gn:timezone":"Asia/Kolkata",
    "iso:country":"IN",
    "ks:ks_alt_nam":"S\u0101mela",
    "ks:ks_name":"Samela",
    "ks:ks_pop":152,
    "ks:ks_type":"VILLAGE",
    "name:eng_x_preferred":[
        "Samela"
    ],
    "name:eng_x_variant":[
        "S\u0101mela"
    ],
    "wof:name":"Samela",
    "wof:placetype":"locality",
    "wof:population":152
},
  "geometry": {"coordinates":[79.276371,19.346212],"type":"Point"}
}