{
  "type": "Feature",
  "properties": {
    "iso:country":"IN",
    "ks:ks_name":"Rebdabahal",
    "ks:ks_pop":299,
    "ks:ks_type":"HABITATION",
    "name:eng_x_preferred":[
        "Rebdabahal"
    ],
    "wof:name":"Rebdabahal",
    "wof:placetype":"locality",
    "wof:population":299
},
  "geometry": {"coordinates":[84.097925,22.189779],"type":"Point"}
}