{
  "type": "Feature",
  "properties": {
    "gn:admin1_code":"34.0",
    "gn:admin2_code":"232.0",
    "gn:asciiname":"Chhotki Nainijor",
    "gn:country_code":"IN",
    "gn:dem":62,
    "gn:feature_class":"P",
    "gn:feature_code":"PPL",
    "gn:name":"Chhotki Nainijor",
    "gn:population":0,
    "gn:timezone":"Asia/Kolkata",
    "iso:country":"IN",
    "name:und_x_variant":[
        "K\u0101sidera"
    ],
    "wof:name":"Chhotki Nainijor",
    "wof:placetype":"neighbourhood"
},
  "geometry": {"coordinates":[84.35209999999999,25.68358],"type":"Point"}
}