{
  "type": "Feature",
  "properties": {
    "iso:country":"IN",
    "ks:ks_name":"Kakadghat",
    "ks:ks_pop":215,
    "ks:ks_type":"VILLAGE",
    "name:eng_x_preferred":[
        "Kakadghat"
    ],
    "wof:name":"Kakadghat",
    "wof:placetype":"locality",
    "wof:population":215
},
  "geometry": {"coordinates":[79.295646,19.655063],"type":"Point"}
}