{
  "type": "Feature",
  "properties": {
    "gn:admin1_code":"34.0",
    "gn:admin2_code":"208.0",
    "gn:asciiname":"Chuni Milik",
    "gn:country_code":"IN",
    "gn:dem":62,
    "gn:feature_class":"P",
    "gn:feature_code":"PPL",
    "gn:name":"Chuni Milik",
    "gn:population":0,
    "gn:timezone":"Asia/Kolkata",
    "iso:country":"IN",
    "wof:name":"Chuni Milik",
    "wof:placetype":"locality"
},
  "geometry": {"coordinates":[87.04549,26.17714],"type":"Point"}
}