{
  "type": "Feature",
  "properties": {
    "iso:country":"IN",
    "ks:ks_name":"Pohiriya Kash",
    "ks:ks_pop":374,
    "ks:ks_type":"HABITATION",
    "ks:ks_uagg_main":0,
    "name:eng_x_preferred":[
        "Pohiriya Kash"
    ],
    "wof:name":"Pohiriya Kash",
    "wof:placetype":"neighbourhood",
    "wof:population":374
},
  "geometry": {"coordinates":[83.71205,27.065272],"type":"Point"}
}