{
  "type": "Feature",
  "properties": {
    "iso:country":"IN",
    "ks:ks_name":"Udoypur Merapani",
    "ks:ks_pop":506,
    "ks:ks_type":"HABITATION",
    "ks:ks_uagg_main":0,
    "name:eng_x_preferred":[
        "Udoypur Merapani"
    ],
    "wof:name":"Udoypur Merapani",
    "wof:placetype":"neighbourhood",
    "wof:population":506
},
  "geometry": {"coordinates":[94.08506,26.333038],"type":"Point"}
}