{
  "type": "Feature",
  "properties": {
    "iso:country":"IN",
    "ks:ks_name":"Bhandriya",
    "ks:ks_pop":1056,
    "ks:ks_type":"VILLAGE",
    "name:eng_x_preferred":[
        "Bhandriya"
    ],
    "wof:name":"Bhandriya",
    "wof:placetype":"locality",
    "wof:population":1056
},
  "geometry": {"coordinates":[82.539618,27.272756],"type":"Point"}
}