{
  "type": "Feature",
  "properties": {
    "iso:country":"IN",
    "ks:ks_name":"Pacharakarpada",
    "ks:ks_pop":79,
    "ks:ks_type":"HABITATION",
    "name:eng_x_preferred":[
        "Pacharakarpada"
    ],
    "wof:name":"Pacharakarpada",
    "wof:placetype":"locality",
    "wof:population":79
},
  "geometry": {"coordinates":[73.291389,19.484167],"type":"Point"}
}