{
  "type": "Feature",
  "properties": {
    "iso:country":"IN",
    "ks:ks_name":"Daula",
    "ks:ks_pop":260,
    "ks:ks_type":"VILLAGE",
    "name:eng_x_preferred":[
        "Daula"
    ],
    "wof:name":"Daula",
    "wof:placetype":"locality",
    "wof:population":260
},
  "geometry": {"coordinates":[79.096034,30.434297],"type":"Point"}
}