{
  "type": "Feature",
  "properties": {
    "iso:country":"IN",
    "ks:ks_name":"Badnachna",
    "ks:ks_pop":761,
    "ks:ks_type":"VILLAGE",
    "name:eng_x_preferred":[
        "Badnachna"
    ],
    "wof:name":"Badnachna",
    "wof:placetype":"locality",
    "wof:population":761
},
  "geometry": {"coordinates":[86.905199,22.080362],"type":"Point"}
}