{
  "type": "Feature",
  "properties": {
    "iso:country":"IN",
    "ks:ks_name":"Bramhanwadi",
    "ks:ks_pop":26,
    "ks:ks_type":"HABITATION",
    "name:eng_x_preferred":[
        "Bramhanwadi"
    ],
    "wof:name":"Bramhanwadi",
    "wof:placetype":"locality",
    "wof:population":26
},
  "geometry": {"coordinates":[73.668536,16.686835],"type":"Point"}
}