{
  "type": "Feature",
  "properties": {
    "iso:country":"IN",
    "ks:ks_name":"Samarajan N C",
    "ks:ks_pop":134,
    "ks:ks_type":"HABITATION",
    "name:eng_x_preferred":[
        "Samarajan N C"
    ],
    "wof:name":"Samarajan N C",
    "wof:placetype":"locality",
    "wof:population":134
},
  "geometry": {"coordinates":[94.487617,27.4109],"type":"Point"}
}