{
  "type": "Feature",
  "properties": {
    "iso:country":"IN",
    "ks:ks_name":"Gaind",
    "ks:ks_pop":384,
    "ks:ks_type":"VILLAGE",
    "name:eng_x_preferred":[
        "Gaind"
    ],
    "wof:name":"Gaind",
    "wof:placetype":"locality",
    "wof:population":384
},
  "geometry": {"coordinates":[78.094168,30.500554],"type":"Point"}
}