{
  "type": "Feature",
  "properties": {
    "iso:country":"IN",
    "ks:ks_alt_nam":"KHOT VASTI",
    "ks:ks_name":"Khot Vasti",
    "ks:ks_pop":102,
    "ks:ks_type":"HABITATION",
    "name:eng_x_preferred":[
        "Khot Vasti"
    ],
    "wof:name":"Khot Vasti",
    "wof:placetype":"locality",
    "wof:population":102
},
  "geometry": {"coordinates":[74.867205,16.84269],"type":"Point"}
}