{
  "type": "Feature",
  "properties": {
    "gn:admin1_code":"19.0",
    "gn:admin2_code":"563.0",
    "gn:asciiname":"Arsingod",
    "gn:country_code":"IN",
    "gn:dem":521,
    "gn:feature_class":"P",
    "gn:feature_code":"PPL",
    "gn:name":"Arsingod",
    "gn:population":0,
    "gn:timezone":"Asia/Kolkata",
    "iso:country":"IN",
    "ks:ks_name":"Arishingod",
    "ks:ks_pop":80,
    "ks:ks_type":"HABITATION",
    "name:eng_x_preferred":[
        "Arishingod"
    ],
    "name:eng_x_variant":[
        "Arsingod"
    ],
    "wof:name":"Arishingod",
    "wof:placetype":"locality",
    "wof:population":80
},
  "geometry": {"coordinates":[74.734509,14.332463],"type":"Point"}
}