{
  "type": "Feature",
  "properties": {
    "gn:admin1_code":"11.0",
    "gn:admin2_code":"33.0",
    "gn:asciiname":"Hadena",
    "gn:country_code":"IN",
    "gn:dem":1934,
    "gn:feature_class":"P",
    "gn:feature_code":"PPL",
    "gn:name":"Hadena",
    "gn:population":0,
    "gn:timezone":"Asia/Kolkata",
    "iso:country":"IN",
    "name:ara_x_preferred":[
        "\u0647\u0627\u062f\u064a\u0646\u064a\u0629"
    ],
    "name:aze_x_preferred":[
        "Hadena"
    ],
    "name:ceb_x_preferred":[
        "Hadena"
    ],
    "name:fra_x_preferred":[
        "Hadena"
    ],
    "name:lat_x_preferred":[
        "Hadena"
    ],
    "name:nld_x_preferred":[
        "Hadena"
    ],
    "name:nor_x_preferred":[
        "Nellikfly"
    ],
    "name:swe_x_preferred":[
        "Hadena"
    ],
    "name:vie_x_preferred":[
        "Hadena"
    ],
    "name:war_x_preferred":[
        "Hadena"
    ],
    "wof:name":"Hadena",
    "wof:placetype":"locality"
},
  "geometry": {"coordinates":[77.71719,31.11553],"type":"Point"}
}