{
  "type": "Feature",
  "properties": {
    "iso:country":"IN",
    "ks:ks_name":"Lumbarawas",
    "ks:ks_pop":53,
    "ks:ks_type":"VILLAGE",
    "name:eng_x_preferred":[
        "Lumbarawas"
    ],
    "wof:name":"Lumbarawas",
    "wof:placetype":"locality",
    "wof:population":53
},
  "geometry": {"coordinates":[73.876535,26.149417],"type":"Point"}
}