{
  "type": "Feature",
  "properties": {
    "iso:country":"IN",
    "ks:ks_name":"Jeet Pur",
    "ks:ks_pop":85,
    "ks:ks_type":"HABITATION",
    "name:eng_x_preferred":[
        "Jeet Pur"
    ],
    "wof:name":"Jeet Pur",
    "wof:placetype":"locality",
    "wof:population":85
},
  "geometry": {"coordinates":[82.830764,27.386008],"type":"Point"}
}