{
  "type": "Feature",
  "properties": {
    "iso:country":"IN",
    "ks:ks_name":"Khalbajetha",
    "ks:ks_pop":252,
    "ks:ks_type":"VILLAGE",
    "name:eng_x_preferred":[
        "Khalbajetha"
    ],
    "wof:name":"Khalbajetha",
    "wof:placetype":"locality",
    "wof:population":252
},
  "geometry": {"coordinates":[79.21833599999999,30.363784],"type":"Point"}
}