{
  "type": "Feature",
  "properties": {
    "iso:country":"IN",
    "ks:ks_name":"Porda",
    "ks:ks_pop":1265,
    "ks:ks_type":"VILLAGE",
    "ks:ks_uagg_main":0,
    "name:eng_x_preferred":[
        "Porda"
    ],
    "wof:name":"Porda",
    "wof:placetype":"neighbourhood",
    "wof:population":1265
},
  "geometry": {"coordinates":[74.09916699999999,23.503056],"type":"Point"}
}