{
  "type": "Feature",
  "properties": {
    "iso:country":"IN",
    "ks:ks_name":"Diguva Cherlopalle",
    "ks:ks_pop":370,
    "ks:ks_type":"HABITATION",
    "name:eng_x_preferred":[
        "Diguva Cherlopalle"
    ],
    "wof:name":"Diguva Cherlopalle",
    "wof:placetype":"locality",
    "wof:population":370
},
  "geometry": {"coordinates":[77.86582,14.055085],"type":"Point"}
}