{
  "type": "Feature",
  "properties": {
    "iso:country":"IN",
    "ks:ks_name":"Bakra Agraharam",
    "ks:ks_pop":86,
    "ks:ks_type":"HABITATION",
    "name:eng_x_preferred":[
        "Bakra Agraharam"
    ],
    "wof:name":"Bakra Agraharam",
    "wof:placetype":"locality",
    "wof:population":86
},
  "geometry": {"coordinates":[79.333726,13.594454],"type":"Point"}
}