{
  "type": "Feature",
  "properties": {
    "iso:country":"IN",
    "ks:ks_alt_nam":"Chak Sat\u0101wan",
    "ks:ks_name":"Chak Satawan",
    "ks:ks_type":"VILLAGE",
    "name:eng_x_preferred":[
        "Chak Satawan"
    ],
    "name:eng_x_variant":[
        "Chak Sat\u0101wan"
    ],
    "wof:name":"Chak Satawan",
    "wof:placetype":"locality"
},
  "geometry": {"coordinates":[83.114816,25.793118],"type":"Point"}
}