{
  "type": "Feature",
  "properties": {
    "iso:country":"IN",
    "ks:ks_name":"Jirakham Tola",
    "ks:ks_pop":600,
    "ks:ks_type":"HABITATION",
    "name:eng_x_preferred":[
        "Jirakham Tola"
    ],
    "wof:name":"Jirakham Tola",
    "wof:placetype":"locality",
    "wof:population":600
},
  "geometry": {"coordinates":[84.90360699999999,25.654648],"type":"Point"}
}