{
  "type": "Feature",
  "properties": {
    "iso:country":"IN",
    "ks:ks_name":"Jederghutu",
    "ks:ks_pop":120,
    "ks:ks_type":"HABITATION",
    "name:eng_x_preferred":[
        "Jederghutu"
    ],
    "wof:name":"Jederghutu",
    "wof:placetype":"locality",
    "wof:population":120
},
  "geometry": {"coordinates":[86.126625,22.117248],"type":"Point"}
}