{
  "type": "Feature",
  "properties": {
    "iso:country":"IN",
    "ks:ks_name":"Karyambathi",
    "ks:ks_pop":630,
    "ks:ks_type":"HABITATION",
    "name:eng_x_preferred":[
        "Karyambathi"
    ],
    "wof:name":"Karyambathi",
    "wof:placetype":"locality",
    "wof:population":630
},
  "geometry": {"coordinates":[76.167986,11.758909],"type":"Point"}
}