{
  "type": "Feature",
  "properties": {
    "iso:country":"IN",
    "ks:ks_name":"Raitkuchi",
    "ks:ks_pop":250,
    "ks:ks_type":"VILLAGE",
    "ks:ks_uagg_main":0,
    "name:eng_x_preferred":[
        "Raitkuchi"
    ],
    "wof:name":"Raitkuchi",
    "wof:placetype":"neighbourhood",
    "wof:population":250
},
  "geometry": {"coordinates":[91.478516,26.351183],"type":"Point"}
}