{
  "type": "Feature",
  "properties": {
    "iso:country":"IN",
    "ks:ks_name":"Dhanya Khola",
    "ks:ks_pop":1878,
    "ks:ks_type":"VILLAGE",
    "name:eng_x_preferred":[
        "Dhanya Khola"
    ],
    "wof:name":"Dhanya Khola",
    "wof:placetype":"locality",
    "wof:population":1878
},
  "geometry": {"coordinates":[87.968265,21.996592],"type":"Point"}
}