{
  "type": "Feature",
  "properties": {
    "iso:country":"IN",
    "ks:ks_name":"Irkha",
    "ks:ks_pop":1531,
    "ks:ks_type":"VILLAGE",
    "name:eng_x_preferred":[
        "Irkha"
    ],
    "wof:name":"Irkha",
    "wof:placetype":"locality",
    "wof:population":1531
},
  "geometry": {"coordinates":[87.90738,22.2271],"type":"Point"}
}