{
  "type": "Feature",
  "properties": {
    "gn:admin1_code":"40.0",
    "gn:admin2_code":"533",
    "gn:asciiname":"Banjapalli",
    "gn:country_code":"IN",
    "gn:dem":413,
    "gn:feature_class":"P",
    "gn:feature_code":"PPL",
    "gn:name":"Banjapalli",
    "gn:population":0,
    "gn:timezone":"Asia/Kolkata",
    "iso:country":"IN",
    "wof:name":"Banjapalli",
    "wof:placetype":"locality"
},
  "geometry": {"coordinates":[77.93559,18.22973],"type":"Point"}
}