{
  "type": "Feature",
  "properties": {
    "gn:admin1_code":"35",
    "gn:admin2_code":"424.0",
    "gn:asciiname":"Jewar Ka Khirak",
    "gn:country_code":"IN",
    "gn:dem":239,
    "gn:feature_class":"P",
    "gn:feature_code":"PPL",
    "gn:name":"Jewar Ka Khirak",
    "gn:population":0,
    "gn:timezone":"Asia/Kolkata",
    "iso:country":"IN",
    "name:und_x_variant":[
        "Navkua"
    ],
    "wof:name":"Jewar Ka Khirak",
    "wof:placetype":"locality"
},
  "geometry": {"coordinates":[78.99457,25.25336],"type":"Point"}
}