{
  "type": "Feature",
  "properties": {
    "iso:country":"IN",
    "ks:ks_name":"Chamraut",
    "ks:ks_pop":216,
    "ks:ks_type":"HABITATION",
    "name:eng_x_preferred":[
        "Chamraut"
    ],
    "wof:name":"Chamraut",
    "wof:placetype":"locality",
    "wof:population":216
},
  "geometry": {"coordinates":[82.786033,26.32006],"type":"Point"}
}