{
  "type": "Feature",
  "properties": {
    "iso:country":"IN",
    "ks:ks_alt_nam":"delipathar",
    "ks:ks_name":"Delipathar",
    "ks:ks_pop":808,
    "ks:ks_type":"HABITATION",
    "name:eng_x_preferred":[
        "Delipathar"
    ],
    "wof:name":"Delipathar",
    "wof:placetype":"locality",
    "wof:population":808
},
  "geometry": {"coordinates":[86.611109,24.260335],"type":"Point"}
}