{
  "type": "Feature",
  "properties": {
    "iso:country":"IN",
    "ks:ks_name":"Barhoiting Gaon",
    "ks:ks_pop":125,
    "ks:ks_type":"VILLAGE",
    "name:eng_x_preferred":[
        "Barhoiting Gaon"
    ],
    "wof:name":"Barhoiting Gaon",
    "wof:placetype":"locality",
    "wof:population":125
},
  "geometry": {"coordinates":[94.621054,27.575059],"type":"Point"}
}