{
  "type": "Feature",
  "properties": {
    "gn:admin1_code":"19.0",
    "gn:admin2_code":"570.0",
    "gn:asciiname":"Sukaligarahatti",
    "gn:country_code":"IN",
    "gn:dem":794,
    "gn:feature_class":"P",
    "gn:feature_code":"PPL",
    "gn:name":"Suk\u0101ligarahatti",
    "gn:population":0,
    "gn:timezone":"Asia/Kolkata",
    "iso:country":"IN",
    "wof:name":"Sukaligarahatti",
    "wof:placetype":"locality"
},
  "geometry": {"coordinates":[76.03256,13.44382],"type":"Point"}
}