{
  "type": "Feature",
  "properties": {
    "gn:admin1_code":"25.0",
    "gn:admin2_code":"632.0",
    "gn:asciiname":"Segudantali",
    "gn:country_code":"IN",
    "gn:dem":347,
    "gn:feature_class":"P",
    "gn:feature_code":"PPL",
    "gn:name":"Segudant\u0101li",
    "gn:population":0,
    "gn:timezone":"Asia/Kolkata",
    "iso:country":"IN",
    "wof:name":"Segudantali",
    "wof:placetype":"locality"
},
  "geometry": {"coordinates":[77.20939,11.11158],"type":"Point"}
}