{
  "type": "Feature",
  "properties": {
    "iso:country":"IN",
    "ks:ks_name":"Matia Pahar",
    "ks:ks_pop":344,
    "ks:ks_type":"VILLAGE",
    "name:eng_x_preferred":[
        "Matia Pahar"
    ],
    "wof:name":"Matia Pahar",
    "wof:placetype":"locality",
    "wof:population":344
},
  "geometry": {"coordinates":[92.902851,26.327616],"type":"Point"}
}