{
  "type": "Feature",
  "properties": {
    "gn:admin1_code":"34.0",
    "gn:admin2_code":"218.0",
    "gn:asciiname":"Semaria",
    "gn:country_code":"IN",
    "gn:dem":72,
    "gn:feature_class":"P",
    "gn:feature_code":"PPL",
    "gn:name":"Semaria",
    "gn:population":0,
    "gn:timezone":"Asia/Kolkata",
    "iso:country":"IN",
    "wof:name":"Semaria",
    "wof:placetype":"locality"
},
  "geometry": {"coordinates":[84.22091,26.30435],"type":"Point"}
}