{
  "type": "Feature",
  "properties": {
    "iso:country":"IN",
    "ks:ks_alt_nam":"PAWATA FALI",
    "ks:ks_name":"Pawata Fali",
    "ks:ks_pop":250,
    "ks:ks_type":"HABITATION",
    "name:eng_x_preferred":[
        "Pawata Fali"
    ],
    "wof:name":"Pawata Fali",
    "wof:placetype":"locality",
    "wof:population":250
},
  "geometry": {"coordinates":[72.839322,24.507792],"type":"Point"}
}