{
  "type": "Feature",
  "properties": {
    "gn:admin1_code":"24.0",
    "gn:admin2_code":"130.0",
    "gn:asciiname":"Sarmal",
    "gn:country_code":"IN",
    "gn:dem":338,
    "gn:feature_class":"P",
    "gn:feature_code":"PPL",
    "gn:name":"Sarmal",
    "gn:population":0,
    "gn:timezone":"Asia/Kolkata",
    "iso:country":"IN",
    "name:ara_x_preferred":[
        "\u0633\u0631\u0645\u0644"
    ],
    "name:ceb_x_preferred":[
        "Sarmal"
    ],
    "name:fas_x_preferred":[
        "\u0633\u0631\u0645\u0644"
    ],
    "name:msa_x_preferred":[
        "Sarmal"
    ],
    "name:swe_x_preferred":[
        "Sarmal"
    ],
    "wof:name":"Sarmal",
    "wof:placetype":"neighbourhood"
},
  "geometry": {"coordinates":[73.97766,24.39312],"type":"Point"}
}