{
  "type": "Feature",
  "properties": {
    "iso:country":"IN",
    "ks:ks_name":"Sangave",
    "ks:ks_pop":167,
    "ks:ks_type":"VILLAGE",
    "name:eng_x_preferred":[
        "Sangave"
    ],
    "wof:name":"Sangave",
    "wof:placetype":"locality",
    "wof:population":167
},
  "geometry": {"coordinates":[74.546925,15.186072],"type":"Point"}
}