{
  "type": "Feature",
  "properties": {
    "iso:country":"IN",
    "ks:ks_name":"Malaiyandipuram",
    "ks:ks_pop":573,
    "ks:ks_type":"HABITATION",
    "name:eng_x_preferred":[
        "Malaiyandipuram"
    ],
    "wof:name":"Malaiyandipuram",
    "wof:placetype":"locality",
    "wof:population":573
},
  "geometry": {"coordinates":[77.77542,10.337287],"type":"Point"}
}