{
  "type": "Feature",
  "properties": {
    "iso:country":"IN",
    "ks:ks_alt_nam":"pasi tola.",
    "ks:ks_name":"Pasi Tola.",
    "ks:ks_pop":376,
    "ks:ks_type":"HABITATION",
    "name:eng_x_preferred":[
        "Pasi Tola."
    ],
    "wof:name":"Pasi Tola.",
    "wof:placetype":"locality",
    "wof:population":376
},
  "geometry": {"coordinates":[86.59555,25.729321],"type":"Point"}
}