{
  "type": "Feature",
  "properties": {
    "gn:admin1_code":"37",
    "gn:admin2_code":"404.0",
    "gn:asciiname":"Bagdara",
    "gn:country_code":"IN",
    "gn:dem":669,
    "gn:feature_class":"P",
    "gn:feature_code":"PPL",
    "gn:name":"Bagdara",
    "gn:population":0,
    "gn:timezone":"Asia/Kolkata",
    "iso:country":"IN",
    "ks:ks_name":"Bagdara",
    "ks:ks_type":"VILLAGE",
    "name:eng_x_preferred":[
        "Bagdara"
    ],
    "wof:name":"Bagdara",
    "wof:placetype":"locality"
},
  "geometry": {"coordinates":[82.26375,22.524778],"type":"Point"}
}