{
  "type": "Feature",
  "properties": {
    "iso:country":"IN",
    "ks:ks_name":"Pagwara Purabpatti",
    "ks:ks_pop":436,
    "ks:ks_type":"VILLAGE",
    "ks:ks_uagg_main":0,
    "name:eng_x_preferred":[
        "Pagwara Purabpatti"
    ],
    "wof:name":"Pagwara Purabpatti",
    "wof:placetype":"neighbourhood",
    "wof:population":436
},
  "geometry": {"coordinates":[87.073548,24.599902],"type":"Point"}
}