{
  "type": "Feature",
  "properties": {
    "gn:admin1_code":"10.0",
    "gn:admin2_code":"076",
    "gn:asciiname":"Kakroi",
    "gn:country_code":"IN",
    "gn:dem":228,
    "gn:feature_class":"P",
    "gn:feature_code":"PPL",
    "gn:name":"Kakroi",
    "gn:population":0,
    "gn:timezone":"Asia/Kolkata",
    "iso:country":"IN",
    "wof:name":"Kakroi",
    "wof:placetype":"locality"
},
  "geometry": {"coordinates":[76.95854,28.96066],"type":"Point"}
}