{
  "type": "Feature",
  "properties": {
    "iso:country":"IN",
    "ks:ks_name":"Bonrobar",
    "ks:ks_pop":994,
    "ks:ks_type":"VILLAGE",
    "name:eng_x_preferred":[
        "Bonrobar"
    ],
    "wof:name":"Bonrobar",
    "wof:placetype":"locality",
    "wof:population":994
},
  "geometry": {"coordinates":[84.579173,23.577983],"type":"Point"}
}