{
  "type": "Feature",
  "properties": {
    "iso:country":"IN",
    "ks:ks_alt_nam":"dawndpur",
    "ks:ks_name":"Dawndpur",
    "ks:ks_pop":463,
    "ks:ks_type":"HABITATION",
    "name:eng_x_preferred":[
        "Dawndpur"
    ],
    "wof:name":"Dawndpur",
    "wof:placetype":"locality",
    "wof:population":463
},
  "geometry": {"coordinates":[80.10805999999999,26.545928],"type":"Point"}
}