{
  "type": "Feature",
  "properties": {
    "iso:country":"IN",
    "ks:ks_name":"Noniya Tola",
    "ks:ks_pop":448,
    "ks:ks_type":"HABITATION",
    "ks:ks_uagg_main":0,
    "name:eng_x_preferred":[
        "Noniya Tola"
    ],
    "wof:name":"Noniya Tola",
    "wof:placetype":"neighbourhood",
    "wof:population":448
},
  "geometry": {"coordinates":[84.397808,26.389513],"type":"Point"}
}