{
  "type": "Feature",
  "properties": {
    "gn:admin1_code":"24.0",
    "gn:admin2_code":"112",
    "gn:asciiname":"Khinyala",
    "gn:country_code":"IN",
    "gn:dem":305,
    "gn:feature_class":"P",
    "gn:feature_code":"PPL",
    "gn:name":"Khiny\u0101la",
    "gn:population":0,
    "gn:timezone":"Asia/Kolkata",
    "iso:country":"IN",
    "name:und_x_variant":[
        "Khiny\u0101la",
        "Kh\u012bn\u0101la"
    ],
    "wof:name":"Khinyala",
    "wof:placetype":"locality"
},
  "geometry": {"coordinates":[74.20180999999999,27.29401],"type":"Point"}
}