{
  "type": "Feature",
  "properties": {
    "iso:country":"IN",
    "ks:ks_name":"Yerkola",
    "ks:ks_pop":46,
    "ks:ks_type":"HABITATION",
    "name:eng_x_preferred":[
        "Yerkola"
    ],
    "wof:name":"Yerkola",
    "wof:placetype":"locality",
    "wof:population":46
},
  "geometry": {"coordinates":[75.755833,12.563611],"type":"Point"}
}