{
  "type": "Feature",
  "properties": {
    "gn:admin1_code":"13.0",
    "gn:admin2_code":"594.0",
    "gn:asciiname":"Edakalattur",
    "gn:country_code":"IN",
    "gn:dem":21,
    "gn:feature_class":"P",
    "gn:feature_code":"PPL",
    "gn:name":"Edakalatt\u016br",
    "gn:population":0,
    "gn:timezone":"Asia/Kolkata",
    "iso:country":"IN",
    "wof:name":"Edakalattur",
    "wof:placetype":"neighbourhood"
},
  "geometry": {"coordinates":[76.1233,10.59182],"type":"Point"}
}