{
  "type": "Feature",
  "properties": {
    "iso:country":"IN",
    "ks:ks_name":"Vantimane",
    "ks:ks_pop":73,
    "ks:ks_type":"HABITATION",
    "name:eng_x_preferred":[
        "Vantimane"
    ],
    "wof:name":"Vantimane",
    "wof:placetype":"locality",
    "wof:population":73
},
  "geometry": {"coordinates":[74.833358,15.04788],"type":"Point"}
}