{
  "type": "Feature",
  "properties": {
    "gn:admin1_code":"36.0",
    "gn:admin2_code":"142.0",
    "gn:asciiname":"Bhawan Bahadurnagar",
    "gn:country_code":"IN",
    "gn:dem":213,
    "gn:feature_class":"P",
    "gn:feature_code":"PPL",
    "gn:name":"Bhawan Bah\u0101durnagar",
    "gn:population":0,
    "gn:timezone":"Asia/Kolkata",
    "iso:country":"IN",
    "wof:name":"Bhawan Bahadurnagar",
    "wof:placetype":"locality"
},
  "geometry": {"coordinates":[77.95554,28.63983],"type":"Point"}
}