{
  "type": "Feature",
  "properties": {
    "iso:country":"IN",
    "ks:ks_alt_nam":"U.Boddaputtu",
    "ks:ks_name":"U.boddaputtu",
    "ks:ks_pop":227,
    "ks:ks_type":"HABITATION",
    "name:eng_x_preferred":[
        "U.boddaputtu"
    ],
    "wof:name":"U.boddaputtu",
    "wof:placetype":"locality",
    "wof:population":227
},
  "geometry": {"coordinates":[82.730074,18.160711],"type":"Point"}
}