{
  "type": "Feature",
  "properties": {
    "iso:country":"IN",
    "ks:ks_name":"Tola Sivsona",
    "ks:ks_pop":708,
    "ks:ks_type":"VILLAGE",
    "name:eng_x_preferred":[
        "Tola Sivsona"
    ],
    "wof:name":"Tola Sivsona",
    "wof:placetype":"locality",
    "wof:population":708
},
  "geometry": {"coordinates":[86.48445599999999,24.934727],"type":"Point"}
}