{
  "type": "Feature",
  "properties": {
    "gn:admin1_code":"37.0",
    "gn:admin2_code":"407.0",
    "gn:asciiname":"Lokhan",
    "gn:country_code":"IN",
    "gn:dem":427,
    "gn:feature_class":"P",
    "gn:feature_code":"PPL",
    "gn:name":"Lokhan",
    "gn:population":0,
    "gn:timezone":"Asia/Kolkata",
    "iso:country":"IN",
    "wof:name":"Lokhan",
    "wof:placetype":"locality"
},
  "geometry": {"coordinates":[81.38668,22.32799],"type":"Point"}
}