{
  "type": "Feature",
  "properties": {
    "iso:country":"IN",
    "ks:ks_alt_nam":"Andh\u0101ri",
    "ks:ks_name":"Andhari",
    "ks:ks_type":"VILLAGE",
    "name:eng_x_preferred":[
        "Andhari"
    ],
    "name:eng_x_variant":[
        "Andh\u0101ri"
    ],
    "wof:name":"Andhari",
    "wof:placetype":"locality"
},
  "geometry": {"coordinates":[84.60422699999999,21.39697],"type":"Point"}
}