{
  "type": "Feature",
  "properties": {
    "iso:country":"IN",
    "ks:ks_name":"Shaikh Vasti",
    "ks:ks_pop":18,
    "ks:ks_type":"HABITATION",
    "name:eng_x_preferred":[
        "Shaikh Vasti"
    ],
    "wof:name":"Shaikh Vasti",
    "wof:placetype":"locality",
    "wof:population":18
},
  "geometry": {"coordinates":[75.26814899999999,18.758115],"type":"Point"}
}