{
  "type": "Feature",
  "properties": {
    "iso:country":"IN",
    "ks:ks_name":"Ganganagar",
    "ks:ks_pop":870,
    "ks:ks_type":"HABITATION",
    "name:eng_x_preferred":[
        "Ganganagar"
    ],
    "wof:name":"Ganganagar",
    "wof:placetype":"locality",
    "wof:population":870
},
  "geometry": {"coordinates":[73.462217,23.856739],"type":"Point"}
}