{
  "type": "Feature",
  "properties": {
    "iso:country":"IN",
    "ks:ks_name":"Kherdi",
    "ks:ks_type":"VILLAGE",
    "name:eng_x_preferred":[
        "Kherdi"
    ],
    "wof:name":"Kherdi",
    "wof:placetype":"locality"
},
  "geometry": {"coordinates":[79.82445800000001,19.729769],"type":"Point"}
}