{
  "type": "Feature",
  "properties": {
    "iso:country":"IN",
    "ks:ks_name":"Mosam",
    "ks:ks_pop":1136,
    "ks:ks_type":"VILLAGE",
    "name:eng_x_preferred":[
        "Mosam"
    ],
    "wof:name":"Mosam",
    "wof:placetype":"locality",
    "wof:population":1136
},
  "geometry": {"coordinates":[73.633899,16.58046],"type":"Point"}
}