{
  "type": "Feature",
  "properties": {
    "iso:country":"IN",
    "ks:ks_name":"Tellingadde",
    "ks:ks_pop":51,
    "ks:ks_type":"HABITATION",
    "name:eng_x_preferred":[
        "Tellingadde"
    ],
    "wof:name":"Tellingadde",
    "wof:placetype":"locality",
    "wof:population":51
},
  "geometry": {"coordinates":[74.827641,14.81869],"type":"Point"}
}