{
  "type": "Feature",
  "properties": {
    "iso:country":"IN",
    "ks:ks_name":"Jaladihi",
    "ks:ks_pop":440,
    "ks:ks_type":"VILLAGE",
    "name:eng_x_preferred":[
        "Jaladihi"
    ],
    "wof:name":"Jaladihi",
    "wof:placetype":"locality",
    "wof:population":440
},
  "geometry": {"coordinates":[85.420419,21.677478],"type":"Point"}
}