{
  "type": "Feature",
  "properties": {
    "iso:country":"IN",
    "ks:ks_name":"Godagewasti",
    "ks:ks_pop":271,
    "ks:ks_type":"HABITATION",
    "name:eng_x_preferred":[
        "Godagewasti"
    ],
    "wof:name":"Godagewasti",
    "wof:placetype":"locality",
    "wof:population":271
},
  "geometry": {"coordinates":[75.355699,18.229455],"type":"Point"}
}