{
  "type": "Feature",
  "properties": {
    "iso:country":"IN",
    "ks:ks_name":"Kalhajor Khurd",
    "ks:ks_pop":423,
    "ks:ks_type":"VILLAGE",
    "name:eng_x_preferred":[
        "Kalhajor Khurd"
    ],
    "wof:name":"Kalhajor Khurd",
    "wof:placetype":"locality",
    "wof:population":423
},
  "geometry": {"coordinates":[87.306934,24.662154],"type":"Point"}
}