{
  "type": "Feature",
  "properties": {
    "iso:country":"IN",
    "ks:ks_name":"Vattakudi Ukkadai",
    "ks:ks_pop":1072,
    "ks:ks_type":"VILLAGE",
    "name:eng_x_preferred":[
        "Vattakudi Ukkadai"
    ],
    "wof:name":"Vattakudi Ukkadai",
    "wof:placetype":"locality",
    "wof:population":1072
},
  "geometry": {"coordinates":[79.406426,10.436049],"type":"Point"}
}