{
  "type": "Feature",
  "properties": {
    "gn:admin1_code":"36",
    "gn:admin2_code":"179.0",
    "gn:asciiname":"Kumain",
    "gn:country_code":"IN",
    "gn:dem":96,
    "gn:feature_class":"P",
    "gn:feature_code":"PPL",
    "gn:name":"Kum\u0101\u012bn",
    "gn:population":0,
    "gn:timezone":"Asia/Kolkata",
    "iso:country":"IN",
    "name:fas_x_preferred":[
        "\u06a9\u0648\u0645\u0627\u0626\u06cc\u0646"
    ],
    "wof:name":"Kumain",
    "wof:placetype":"neighbourhood"
},
  "geometry": {"coordinates":[82.04772,26.33757],"type":"Point"}
}