{
  "type": "Feature",
  "properties": {
    "iso:country":"IN",
    "ks:ks_alt_nam":"CHANDAGACHI",
    "ks:ks_name":"Chandagachi",
    "ks:ks_pop":1090,
    "ks:ks_type":"HABITATION",
    "ks:ks_uagg_main":0,
    "name:eng_x_preferred":[
        "Chandagachi"
    ],
    "wof:name":"Chandagachi",
    "wof:placetype":"neighbourhood",
    "wof:population":1090
},
  "geometry": {"coordinates":[88.666353,22.892714],"type":"Point"}
}