{
  "type": "Feature",
  "properties": {
    "iso:country":"IN",
    "ks:ks_name":"Gadalaghati",
    "ks:ks_pop":26,
    "ks:ks_type":"VILLAGE",
    "name:eng_x_preferred":[
        "Gadalaghati"
    ],
    "wof:name":"Gadalaghati",
    "wof:placetype":"locality",
    "wof:population":26
},
  "geometry": {"coordinates":[82.99965899999999,19.335805],"type":"Point"}
}