{
  "type": "Feature",
  "properties": {
    "iso:country":"IN",
    "ks:ks_name":"Gudipet",
    "ks:ks_pop":1509,
    "ks:ks_type":"VILLAGE",
    "ks:ks_uagg_main":0,
    "name:eng_x_preferred":[
        "Gudipet"
    ],
    "wof:name":"Gudipet",
    "wof:placetype":"neighbourhood",
    "wof:population":1509
},
  "geometry": {"coordinates":[79.363204,18.874963],"type":"Point"}
}