{
  "type": "Feature",
  "properties": {
    "gn:admin1_code":"12.0",
    "gn:admin2_code":"21.0",
    "gn:asciiname":"Jar",
    "gn:country_code":"IN",
    "gn:dem":346,
    "gn:feature_class":"P",
    "gn:feature_code":"PPL",
    "gn:name":"Jar",
    "gn:population":0,
    "gn:timezone":"Asia/Kolkata",
    "iso:country":"IN",
    "name:ara_x_preferred":[
        "\u062c\u0631\u0629"
    ],
    "name:epo_x_preferred":[
        "Bokalo"
    ],
    "name:fas_x_preferred":[
        "\u0628\u0633\u062a\u0648"
    ],
    "name:fra_x_preferred":[
        "Bocal"
    ],
    "name:hat_x_preferred":[
        "Bokal"
    ],
    "name:heb_x_preferred":[
        "\u05e6\u05e0\u05e6\u05e0\u05ea"
    ],
    "name:hye_x_preferred":[
        "\u0531\u0576\u0578\u0569"
    ],
    "name:ido_x_preferred":[
        "Bokalo"
    ],
    "name:ita_x_preferred":[
        "Barattolo"
    ],
    "name:kan_x_preferred":[
        "\u0c9c\u0cbe\u0ca1\u0cbf"
    ],
    "name:kor_x_preferred":[
        "\ud56d\uc544\ub9ac"
    ],
    "name:mkd_x_preferred":[
        "\u0422\u0435\u0433\u043b\u0430"
    ],
    "name:nno_x_preferred":[
        "Krukke"
    ],
    "name:nor_x_preferred":[
        "Krukke"
    ],
    "name:pnb_x_preferred":[
        "\u0645\u0631\u062a\u0628\u0627\u0646"
    ],
    "name:rus_x_preferred":[
        "\u0411\u0430\u043d\u043a\u0430"
    ],
    "name:srp_x_preferred":[
        "\u0422\u0435\u0433\u043b\u0430"
    ],
    "name:sun_x_preferred":[
        "K\u00e9ler"
    ],
    "name:swe_x_preferred":[
        "Burk"
    ],
    "name:tur_x_preferred":[
        "Kavanoz"
    ],
    "wof:name":"Jar",
    "wof:placetype":"locality"
},
  "geometry": {"coordinates":[74.60775,32.87568],"type":"Point"}
}