{
  "type": "Feature",
  "properties": {
    "gn:admin1_code":"19.0",
    "gn:admin2_code":"582.0",
    "gn:asciiname":"Yerranagenahalli North",
    "gn:country_code":"IN",
    "gn:dem":741,
    "gn:feature_class":"P",
    "gn:feature_code":"PPL",
    "gn:name":"Yerran\u0101genahalli North",
    "gn:population":0,
    "gn:timezone":"Asia/Kolkata",
    "iso:country":"IN",
    "wof:name":"Yerranagenahalli North",
    "wof:placetype":"neighbourhood"
},
  "geometry": {"coordinates":[77.63275,13.62228],"type":"Point"}
}