{
  "type": "Feature",
  "properties": {
    "iso:country":"IN",
    "ks:ks_name":"Patti Sultanpura",
    "ks:ks_pop":47,
    "ks:ks_type":"HABITATION",
    "name:eng_x_preferred":[
        "Patti Sultanpura"
    ],
    "wof:name":"Patti Sultanpura",
    "wof:placetype":"locality",
    "wof:population":47
},
  "geometry": {"coordinates":[76.39572099999999,26.500698],"type":"Point"}
}