{
  "type": "Feature",
  "properties": {
    "iso:country":"IN",
    "ks:ks_alt_nam":"tambadwadi",
    "ks:ks_name":"Tambadwadi",
    "ks:ks_pop":118,
    "ks:ks_type":"HABITATION",
    "name:eng_x_preferred":[
        "Tambadwadi"
    ],
    "wof:name":"Tambadwadi",
    "wof:placetype":"locality",
    "wof:population":118
},
  "geometry": {"coordinates":[73.621786,17.291503],"type":"Point"}
}