{
  "type": "Feature",
  "properties": {
    "iso:country":"IN",
    "ks:ks_name":"Nandhai",
    "ks:ks_pop":1885,
    "ks:ks_type":"VILLAGE",
    "name:eng_x_preferred":[
        "Nandhai"
    ],
    "wof:name":"Nandhai",
    "wof:placetype":"locality",
    "wof:population":1885
},
  "geometry": {"coordinates":[73.091042,20.606821],"type":"Point"}
}