{
  "type": "Feature",
  "properties": {
    "iso:country":"IN",
    "ks:ks_name":"Badanapur",
    "ks:ks_pop":208,
    "ks:ks_type":"HABITATION",
    "name:eng_x_preferred":[
        "Badanapur"
    ],
    "wof:name":"Badanapur",
    "wof:placetype":"locality",
    "wof:population":208
},
  "geometry": {"coordinates":[80.05632900000001,26.438817],"type":"Point"}
}