{
  "type": "Feature",
  "properties": {
    "iso:country":"IN",
    "ks:ks_alt_nam":"Tirath purwa",
    "ks:ks_name":"Tirath Purwa",
    "ks:ks_pop":48,
    "ks:ks_type":"HABITATION",
    "name:eng_x_preferred":[
        "Tirath Purwa"
    ],
    "wof:name":"Tirath Purwa",
    "wof:placetype":"locality",
    "wof:population":48
},
  "geometry": {"coordinates":[81.73063,27.446007],"type":"Point"}
}