{
  "type": "Feature",
  "properties": {
    "iso:country":"IN",
    "ks:ks_name":"Jamripahar",
    "ks:ks_pop":113,
    "ks:ks_type":"VILLAGE",
    "name:eng_x_preferred":[
        "Jamripahar"
    ],
    "wof:name":"Jamripahar",
    "wof:placetype":"locality",
    "wof:population":113
},
  "geometry": {"coordinates":[87.659683,24.854233],"type":"Point"}
}