{
  "type": "Feature",
  "properties": {
    "iso:country":"IN",
    "ks:ks_name":"Kadammaje",
    "ks:ks_pop":100,
    "ks:ks_type":"HABITATION",
    "name:eng_x_preferred":[
        "Kadammaje"
    ],
    "wof:name":"Kadammaje",
    "wof:placetype":"locality",
    "wof:population":100
},
  "geometry": {"coordinates":[75.29145,12.939823],"type":"Point"}
}