{
  "type": "Feature",
  "properties": {
    "iso:country":"IN",
    "ks:ks_name":"Savad",
    "ks:ks_pop":742,
    "ks:ks_type":"HABITATION",
    "name:eng_x_preferred":[
        "Savad"
    ],
    "wof:name":"Savad",
    "wof:placetype":"locality",
    "wof:population":742
},
  "geometry": {"coordinates":[74.4572,22.438032],"type":"Point"}
}