{
  "type": "Feature",
  "properties": {
    "iso:country":"IN",
    "ks:ks_name":"Raikherha",
    "ks:ks_pop":136,
    "ks:ks_type":"HABITATION",
    "name:eng_x_preferred":[
        "Raikherha"
    ],
    "wof:name":"Raikherha",
    "wof:placetype":"locality",
    "wof:population":136
},
  "geometry": {"coordinates":[81.522802,21.822071],"type":"Point"}
}