{
  "type": "Feature",
  "properties": {
    "iso:country":"IN",
    "ks:ks_name":"Ganuadih",
    "ks:ks_pop":261,
    "ks:ks_type":"VILLAGE",
    "name:eng_x_preferred":[
        "Ganuadih"
    ],
    "wof:name":"Ganuadih",
    "wof:placetype":"locality",
    "wof:population":261
},
  "geometry": {"coordinates":[87.104033,24.110426],"type":"Point"}
}