{
  "type": "Feature",
  "properties": {
    "gn:admin1_code":"19.0",
    "gn:admin2_code":"576.0",
    "gn:asciiname":"Kaikeri",
    "gn:country_code":"IN",
    "gn:dem":881,
    "gn:feature_class":"P",
    "gn:feature_code":"PPL",
    "gn:name":"Kaiker\u012b",
    "gn:population":0,
    "gn:timezone":"Asia/Kolkata",
    "iso:country":"IN",
    "wof:name":"Kaikeri",
    "wof:placetype":"locality"
},
  "geometry": {"coordinates":[75.9076,12.17663],"type":"Point"}
}