{
  "type": "Feature",
  "properties": {
    "gn:admin1_code":"19.0",
    "gn:admin2_code":"576.0",
    "gn:asciiname":"Kaikeri",
    "gn:country_code":"IN",
    "gn:dem":881,
    "gn:feature_class":"P",
    "gn:feature_code":"PPL",
    "gn:name":"Kaiker\u012b",
    "gn:population":0,
    "gn:timezone":"Asia/Kolkata",
    "iso:country":"IN",
    "ks:ks_name":"Kaikeri",
    "ks:ks_pop":1890,
    "ks:ks_type":"HABITATION",
    "name:eng_x_preferred":[
        "Kaikeri"
    ],
    "wof:name":"Kaikeri",
    "wof:placetype":"locality",
    "wof:population":1890
},
  "geometry": {"coordinates":[75.901991,12.177246],"type":"Point"}
}