{
  "type": "Feature",
  "properties": {
    "gn:admin1_code":"36",
    "gn:admin2_code":"178.0",
    "gn:asciiname":"Tarka",
    "gn:country_code":"IN",
    "gn:dem":92,
    "gn:feature_class":"P",
    "gn:feature_code":"PPL",
    "gn:name":"Tarka",
    "gn:population":0,
    "gn:timezone":"Asia/Kolkata",
    "iso:country":"IN",
    "name:ceb_x_preferred":[
        "Tarka"
    ],
    "name:deu_x_preferred":[
        "Tarka"
    ],
    "name:ita_x_preferred":[
        "Tarka"
    ],
    "name:pol_x_preferred":[
        "Tarka"
    ],
    "wof:name":"Tarka",
    "wof:placetype":"locality"
},
  "geometry": {"coordinates":[82.84721999999999,26.34937],"type":"Point"}
}