{
  "type": "Feature",
  "properties": {
    "gn:admin1_code":"29.0",
    "gn:admin2_code":"243.0",
    "gn:asciiname":"Nagidanda",
    "gn:country_code":"IN",
    "gn:dem":1463,
    "gn:feature_class":"P",
    "gn:feature_code":"PPL",
    "gn:name":"N\u0101g\u012bd\u0101nda",
    "gn:population":0,
    "gn:timezone":"Asia/Kolkata",
    "iso:country":"IN",
    "wof:name":"Nagidanda",
    "wof:placetype":"locality"
},
  "geometry": {"coordinates":[88.45206999999998,27.16884000000001],"type":"Point"}
}