{
  "type": "Feature",
  "properties": {
    "gn:admin1_code":"2.0",
    "gn:admin2_code":"554.0",
    "gn:asciiname":"Chigaramakulapalli",
    "gn:country_code":"IN",
    "gn:dem":260,
    "gn:feature_class":"P",
    "gn:feature_code":"PPL",
    "gn:name":"Chigaram\u0101kulapalli",
    "gn:population":0,
    "gn:timezone":"Asia/Kolkata",
    "iso:country":"IN",
    "wof:name":"Chigaramakulapalli",
    "wof:placetype":"neighbourhood"
},
  "geometry": {"coordinates":[79.23878999999999,13.54258],"type":"Point"}
}