{
  "type": "Feature",
  "properties": {
    "gn:admin1_code":"37",
    "gn:admin2_code":"407.0",
    "gn:asciiname":"Madanpur",
    "gn:country_code":"IN",
    "gn:dem":354,
    "gn:feature_class":"P",
    "gn:feature_code":"PPL",
    "gn:name":"Madanpur",
    "gn:population":0,
    "gn:timezone":"Asia/Kolkata",
    "iso:country":"IN",
    "name:ara_x_preferred":[
        "\u0645\u0627\u062f\u0646\u0628\u0648\u0631"
    ],
    "name:ben_bn_x_preferred":[
        "\u09ae\u09a6\u09a8\u09aa\u09c1\u09b0"
    ],
    "name:ben_in_x_preferred":[
        "\u09ae\u09a6\u09a8\u09aa\u09c1\u09b0"
    ],
    "name:ceb_x_preferred":[
        "Madanpur"
    ],
    "name:guj_x_preferred":[
        "\u0aae\u0aa6\u0aa8\u0aaa\u0ac1\u0ab0"
    ],
    "name:hin_x_preferred":[
        "\u092e\u0926\u0928\u092a\u0941\u0930"
    ],
    "name:kan_x_preferred":[
        "\u0cae\u0ca6\u0ca8\u0ccd"
    ],
    "name:mal_x_preferred":[
        "\u0d2e\u0d26\u0d7b\u0d2a\u0d42\u0d7c"
    ],
    "name:mar_x_preferred":[
        "\u092e\u0926\u0928\u092a\u0942\u0930"
    ],
    "name:pan_x_preferred":[
        "\u0a2e\u0a26\u0a28\u0a2a\u0a41\u0a30"
    ],
    "name:swe_x_preferred":[
        "Madanpur"
    ],
    "name:tam_x_preferred":[
        "\u0bae\u0ba4\u0ba9\u0bcd\u0baa\u0bc2\u0bb0\u0bcd"
    ],
    "name:tel_x_preferred":[
        "\u0c2e\u0c26\u0c28\u0c4d"
    ],
    "name:urd_x_preferred":[
        "\u0645\u062f\u0646\u067e\u0648\u0631"
    ],
    "wof:name":"Madanpur",
    "wof:placetype":"locality"
},
  "geometry": {"coordinates":[81.52150999999998,22.32223],"type":"Point"}
}