{
  "type": "Feature",
  "properties": {
    "gn:admin1_code":"37",
    "gn:admin2_code":"407.0",
    "gn:asciiname":"Madanpur",
    "gn:country_code":"IN",
    "gn:dem":354,
    "gn:feature_class":"P",
    "gn:feature_code":"PPL",
    "gn:name":"Madanpur",
    "gn:population":0,
    "gn:timezone":"Asia/Kolkata",
    "iso:country":"IN",
    "wof:name":"Madanpur",
    "wof:placetype":"locality"
},
  "geometry": {"coordinates":[81.52150999999998,22.32223],"type":"Point"}
}