{
  "type": "Feature",
  "properties": {
    "gn:admin1_code":"35.0",
    "gn:admin2_code":"454.0",
    "gn:asciiname":"Indri",
    "gn:country_code":"IN",
    "gn:dem":701,
    "gn:feature_class":"P",
    "gn:feature_code":"PPL",
    "gn:name":"Indr\u012b",
    "gn:population":0,
    "gn:timezone":"Asia/Kolkata",
    "iso:country":"IN",
    "name:ara_x_preferred":[
        "\u0625\u0646\u062f\u0631\u064a \u0634\u0627\u0626\u0639"
    ],
    "name:aze_x_preferred":[
        "\u0130ndri"
    ],
    "name:ben_x_preferred":[
        "\u0987\u09a8\u09cd\u09a6\u09cd\u09b0\u09bf"
    ],
    "name:bpy_x_preferred":[
        "\u0987\u09a8\u09cd\u09a6\u09cd\u09b0\u09bf"
    ],
    "name:bre_x_preferred":[
        "Indri"
    ],
    "name:bul_x_preferred":[
        "\u0418\u043d\u0434\u0440\u0438"
    ],
    "name:cat_x_preferred":[
        "Indri"
    ],
    "name:ceb_x_preferred":[
        "Indri indri"
    ],
    "name:ces_x_preferred":[
        "Indri"
    ],
    "name:dan_x_preferred":[
        "Indri"
    ],
    "name:deu_x_preferred":[
        "Indri"
    ],
    "name:ell_x_preferred":[
        "\u038a\u03bd\u03c4\u03c1\u03b9"
    ],
    "name:est_x_preferred":[
        "Indri"
    ],
    "name:eus_x_preferred":[
        "Indri"
    ],
    "name:fas_x_preferred":[
        "\u0627\u06cc\u0646\u062f\u0631\u06cc"
    ],
    "name:fin_x_preferred":[
        "Indri"
    ],
    "name:fra_x_preferred":[
        "Indri indri"
    ],
    "name:gle_x_preferred":[
        "Indr\u00eddigh"
    ],
    "name:heb_x_preferred":[
        "\u05d0\u05d9\u05e0\u05d3\u05e8\u05d9"
    ],
    "name:hun_x_preferred":[
        "Indri"
    ],
    "name:hye_x_preferred":[
        "\u053b\u0576\u0564\u0580\u056b\u0576"
    ],
    "name:ind_x_preferred":[
        "Indri"
    ],
    "name:ita_x_preferred":[
        "Indri indri"
    ],
    "name:jpn_x_preferred":[
        "\u30a4\u30f3\u30c9\u30ea"
    ],
    "name:kat_x_preferred":[
        "\u10d8\u10dc\u10d3\u10e0\u10d8"
    ],
    "name:kor_x_preferred":[
        "\uc778\ub4dc\ub9ac"
    ],
    "name:lit_x_preferred":[
        "Trumpauodegis indris"
    ],
    "name:mlg_x_preferred":[
        "Indri indri"
    ],
    "name:new_x_preferred":[
        "\u0907\u0928\u094d\u0926\u094d\u0930\u0940"
    ],
    "name:nld_x_preferred":[
        "Indri"
    ],
    "name:nor_x_preferred":[
        "Indri"
    ],
    "name:pnb_x_preferred":[
        "\u0627\u0646\u062f\u0631\u06cc"
    ],
    "name:pol_x_preferred":[
        "Indris kr\u00f3tkoogonowy"
    ],
    "name:por_x_preferred":[
        "Indri indri"
    ],
    "name:rus_x_preferred":[
        "\u0418\u043d\u0434\u0440\u0438"
    ],
    "name:slk_x_preferred":[
        "Indri"
    ],
    "name:spa_x_preferred":[
        "Indri indri"
    ],
    "name:srp_x_preferred":[
        "\u0418\u043d\u0434\u0440\u0438"
    ],
    "name:swe_x_preferred":[
        "Indri"
    ],
    "name:tgl_x_preferred":[
        "Indri indri"
    ],
    "name:tha_x_preferred":[
        "\u0e2d\u0e34\u0e19\u0e14\u0e23\u0e35"
    ],
    "name:udm_x_preferred":[
        "\u0418\u043d\u0434\u0440\u0438"
    ],
    "name:ukr_x_preferred":[
        "\u0406\u043d\u0434\u0440\u0456"
    ],
    "name:urd_x_preferred":[
        "\u0627\u0646\u062f\u0631\u06cc"
    ],
    "name:vie_x_preferred":[
        "Indri indri"
    ],
    "name:war_x_preferred":[
        "Indri indri"
    ],
    "name:zho_x_preferred":[
        "\u5927\u72d0\u7334"
    ],
    "wof:name":"Indri",
    "wof:placetype":"neighbourhood"
},
  "geometry": {"coordinates":[80.95577,22.2885],"type":"Point"}
}