{
  "type": "Feature",
  "properties": {
    "iso:country":"IN",
    "ks:ks_name":"Bhurawati",
    "ks:ks_pop":347,
    "ks:ks_type":"HABITATION",
    "name:eng_x_preferred":[
        "Bhurawati"
    ],
    "wof:name":"Bhurawati",
    "wof:placetype":"locality",
    "wof:population":347
},
  "geometry": {"coordinates":[78.974937,28.622545],"type":"Point"}
}