{
  "type": "Feature",
  "properties": {
    "gn:admin1_code":"39.0",
    "gn:admin2_code":"64.0",
    "gn:asciiname":"Airi Khan",
    "gn:country_code":"IN",
    "gn:dem":1725,
    "gn:feature_class":"P",
    "gn:feature_code":"PPL",
    "gn:name":"Airi Kh\u0101n",
    "gn:population":0,
    "gn:timezone":"Asia/Kolkata",
    "iso:country":"IN",
    "wof:name":"Airi Khan",
    "wof:placetype":"locality"
},
  "geometry": {"coordinates":[79.84430999999999,29.68069],"type":"Point"}
}