{
  "type": "Feature",
  "properties": {
    "iso:country":"IN",
    "ks:ks_name":"Chitva",
    "ks:ks_pop":1334,
    "ks:ks_type":"VILLAGE",
    "name:eng_x_preferred":[
        "Chitva"
    ],
    "wof:name":"Chitva",
    "wof:placetype":"locality",
    "wof:population":1334
},
  "geometry": {"coordinates":[73.868222,23.287333],"type":"Point"}
}