{
  "type": "Feature",
  "properties": {
    "iso:country":"IN",
    "ks:ks_name":"Chakloknath",
    "ks:ks_pop":821,
    "ks:ks_type":"VILLAGE",
    "ks:ks_uagg_main":0,
    "name:eng_x_preferred":[
        "Chakloknath"
    ],
    "wof:name":"Chakloknath",
    "wof:placetype":"neighbourhood",
    "wof:population":821
},
  "geometry": {"coordinates":[88.130264,22.222033],"type":"Point"}
}