{
  "type": "Feature",
  "properties": {
    "gn:admin1_code":"34.0",
    "gn:admin2_code":"236.0",
    "gn:asciiname":"Doat",
    "gn:country_code":"IN",
    "gn:dem":202,
    "gn:feature_class":"P",
    "gn:feature_code":"PPL",
    "gn:name":"Do\u0101t",
    "gn:population":0,
    "gn:timezone":"Asia/Kolkata",
    "iso:country":"IN",
    "ks:ks_name":"Deat",
    "ks:ks_pop":425,
    "ks:ks_type":"VILLAGE",
    "name:eng_x_preferred":[
        "Deat"
    ],
    "name:eng_x_variant":[
        "Doat"
    ],
    "wof:name":"Deat",
    "wof:placetype":"locality",
    "wof:population":425
},
  "geometry": {"coordinates":[85.100904,24.447498],"type":"Point"}
}