{
  "type": "Feature",
  "properties": {
    "iso:country":"IN",
    "ks:ks_alt_nam":"BAGAN BARI",
    "ks:ks_name":"Bagan Bari",
    "ks:ks_pop":388,
    "ks:ks_type":"HABITATION",
    "name:eng_x_preferred":[
        "Bagan Bari"
    ],
    "wof:name":"Bagan Bari",
    "wof:placetype":"locality",
    "wof:population":388
},
  "geometry": {"coordinates":[91.36251300000001,23.769374],"type":"Point"}
}