{
  "type": "Feature",
  "properties": {
    "gn:admin1_code":"21.0",
    "gn:admin2_code":"396.0",
    "gn:asciiname":"Karasi",
    "gn:country_code":"IN",
    "gn:dem":207,
    "gn:feature_class":"P",
    "gn:feature_code":"PPL",
    "gn:name":"Karasi",
    "gn:population":0,
    "gn:timezone":"Asia/Kolkata",
    "iso:country":"IN",
    "name:jpn_x_preferred":[
        "\u30ab\u30e9\u30b8"
    ],
    "wof:name":"Karasi",
    "wof:placetype":"locality"
},
  "geometry": {"coordinates":[83.92307,19.05556],"type":"Point"}
}