{
  "type": "Feature",
  "properties": {
    "gn:admin1_code":"21.0",
    "gn:admin2_code":"396.0",
    "gn:asciiname":"Karasi",
    "gn:country_code":"IN",
    "gn:dem":207,
    "gn:feature_class":"P",
    "gn:feature_code":"PPL",
    "gn:name":"Karasi",
    "gn:population":0,
    "gn:timezone":"Asia/Kolkata",
    "iso:country":"IN",
    "ks:ks_name":"Kadasi",
    "ks:ks_pop":1169,
    "ks:ks_type":"VILLAGE",
    "name:eng_x_preferred":[
        "Kadasi"
    ],
    "name:eng_x_variant":[
        "Karasi"
    ],
    "name:jpn_x_preferred":[
        "\u30ab\u30e9\u30b8"
    ],
    "wof:name":"Kadasi",
    "wof:placetype":"locality",
    "wof:population":1169
},
  "geometry": {"coordinates":[83.92331900000001,19.055416],"type":"Point"}
}