{
  "type": "Feature",
  "properties": {
    "gn:country":"IN",
    "gn:fcode":"PPL",
    "gn:pop":29000,
    "iso:country":"IN",
    "name:ben_x_preferred":[
        "\u099a\u09cb\u09a6\u09be\u09ad\u09b0\u09ae"
    ],
    "name:bul_x_preferred":[
        "\u0427\u043e\u0434\u0430\u0432\u0430\u0440\u0430\u043c"
    ],
    "name:ceb_x_preferred":[
        "Chodavaram"
    ],
    "name:deu_x_preferred":[
        "Chodavaram"
    ],
    "name:eng_x_preferred":[
        "Chodavaram"
    ],
    "name:fra_x_preferred":[
        "Chodavaram"
    ],
    "name:guj_x_preferred":[
        "\u0a9a\u0acb\u0aa1\u0abe\u0ab5\u0ab0\u0aae"
    ],
    "name:jpn_x_preferred":[
        "\u30c1\u30e7\u30c0\u30f4\u30a1\u30e9\u30e0"
    ],
    "name:kan_x_preferred":[
        "\u0c9a\u0ccb\u0ca1\u0cb5\u0cb0\u0c82"
    ],
    "name:kor_x_preferred":[
        "\ucd08\ub2f4\ubc14\ub78c"
    ],
    "name:new_x_preferred":[
        "\u091a\u094b\u0921\u0935\u0930\u0902 \u092e\u0923\u094d\u0921\u0932"
    ],
    "name:nld_x_preferred":[
        "Chodavaram"
    ],
    "name:por_x_preferred":[
        "Chodavaram"
    ],
    "name:rus_x_preferred":[
        "\u0427\u043e\u0434\u0430\u0432\u0430\u0440\u0430\u043c"
    ],
    "name:spa_x_preferred":[
        "Chodavaram"
    ],
    "name:swe_x_preferred":[
        "Chodavaram"
    ],
    "name:tam_x_preferred":[
        "\u0b9a\u0bcb\u0b9f\u0bb5\u0bb0\u0bae\u0bcd"
    ],
    "name:tel_x_preferred":[
        "\u0c1a\u0c4b\u0c21\u0c35\u0c30\u0c02"
    ],
    "name:urd_x_preferred":[
        "\u0686\u0648\u0691\u0627\u0648\u0631\u0645\u060c \u0648\u0634\u0627\u06a9\u06be\u0627\u067e\u0679\u0646\u0645"
    ],
    "name:urd_x_variant":[
        "\u0686\u0648\u0691\u0627\u0648\u0631\u0645"
    ],
    "name:vie_x_preferred":[
        "Chodavaram"
    ],
    "qs:name":"Chodavaram",
    "qs:name_adm0":"India",
    "qs:name_adm1":"Andhra Pradesh",
    "qs:photos_9r":0,
    "qs:photos_sr":0,
    "qs:placetype":"Town",
    "qs:pop_sr":"7",
    "wd:wordcount":93,
    "wof:name":"Chodavaram",
    "wof:placetype":"locality",
    "wof:population":29000
},
  "geometry": {"coordinates":[82.93769,17.82974],"type":"Point"}
}