{
  "type": "Feature",
  "properties": {
    "iso:country":"IN",
    "ks:ks_alt_nam":"Nija pipalapadar",
    "ks:ks_name":"Nija Pipalapadar",
    "ks:ks_pop":260,
    "ks:ks_type":"HABITATION",
    "name:eng_x_preferred":[
        "Nija Pipalapadar"
    ],
    "wof:name":"Nija Pipalapadar",
    "wof:placetype":"locality",
    "wof:population":260
},
  "geometry": {"coordinates":[84.76367,20.309026],"type":"Point"}
}