{
  "type": "Feature",
  "properties": {
    "iso:country":"IN",
    "ks:ks_name":"Payarwadi",
    "ks:ks_pop":84,
    "ks:ks_type":"HABITATION",
    "ks:ks_uagg_main":0,
    "name:eng_x_preferred":[
        "Payarwadi"
    ],
    "wof:name":"Payarwadi",
    "wof:placetype":"neighbourhood",
    "wof:population":84
},
  "geometry": {"coordinates":[73.868779,16.202632],"type":"Point"}
}