{
  "type": "Feature",
  "properties": {
    "iso:country":"IN",
    "ks:ks_name":"Bagriyo Ki Khedi",
    "ks:ks_pop":377,
    "ks:ks_type":"URBAN",
    "name:eng_x_preferred":[
        "Bagriyo Ki Khedi"
    ],
    "wof:name":"Bagriyo Ki Khedi",
    "wof:placetype":"locality",
    "wof:population":377
},
  "geometry": {"coordinates":[74.922374,23.455338],"type":"Point"}
}