{
  "type": "Feature",
  "properties": {
    "iso:country":"IN",
    "ks:ks_name":"Sultanpur",
    "ks:ks_pop":0,
    "ks:ks_type":"VILLAGE",
    "ks:ks_uagg_main":0,
    "name:eng_x_preferred":[
        "Sultanpur"
    ],
    "wof:name":"Sultanpur",
    "wof:placetype":"locality",
    "wof:population":0
},
  "geometry": {"coordinates":[81.66188200000001,25.478395],"type":"Point"}
}