{
  "type": "Feature",
  "properties": {
    "iso:country":"IN",
    "ks:ks_name":"Indrapuram",
    "ks:ks_pop":459,
    "ks:ks_type":"HABITATION",
    "name:eng_x_preferred":[
        "Indrapuram"
    ],
    "wof:name":"Indrapuram",
    "wof:placetype":"locality",
    "wof:population":459
},
  "geometry": {"coordinates":[77.901438,10.265194],"type":"Point"}
}