{
  "type": "Feature",
  "properties": {
    "iso:country":"IN",
    "ks:ks_name":"Mithitalavadi",
    "ks:ks_pop":394,
    "ks:ks_type":"HABITATION",
    "name:eng_x_preferred":[
        "Mithitalavadi"
    ],
    "wof:name":"Mithitalavadi",
    "wof:placetype":"locality",
    "wof:population":394
},
  "geometry": {"coordinates":[72.85816699999999,22.602417],"type":"Point"}
}