{
  "type": "Feature",
  "properties": {
    "gn:admin1_code":"36.0",
    "gn:admin2_code":"189.0",
    "gn:asciiname":"Jauhi Harballabh",
    "gn:country_code":"IN",
    "gn:dem":80,
    "gn:feature_class":"P",
    "gn:feature_code":"PPL",
    "gn:name":"Jauhi Harballabh",
    "gn:population":0,
    "gn:timezone":"Asia/Kolkata",
    "iso:country":"IN",
    "ks:ks_name":"Jawahihar Ballabh",
    "ks:ks_pop":1089,
    "ks:ks_type":"VILLAGE",
    "name:eng_x_preferred":[
        "Jawahihar Ballabh"
    ],
    "name:eng_x_variant":[
        "Jauhi Harballabh"
    ],
    "wof:name":"Jawahihar Ballabh",
    "wof:placetype":"locality",
    "wof:population":1089
},
  "geometry": {"coordinates":[84.31009899999999,26.6574],"type":"Point"}
}