{
  "type": "Feature",
  "properties": {
    "gn:admin1_code":"34",
    "gn:admin2_code":"218.0",
    "gn:asciiname":"Rajanpura",
    "gn:country_code":"IN",
    "gn:dem":63,
    "gn:feature_class":"P",
    "gn:feature_code":"PPL",
    "gn:name":"Rajanpura",
    "gn:population":0,
    "gn:timezone":"Asia/Kolkata",
    "iso:country":"IN",
    "wof:name":"Rajanpura",
    "wof:placetype":"locality"
},
  "geometry": {"coordinates":[84.37824999999999,26.04898],"type":"Point"}
}