{
  "type": "Feature",
  "properties": {
    "iso:country":"IN",
    "ks:ks_name":"Asoda",
    "ks:ks_pop":44,
    "ks:ks_type":"VILLAGE",
    "name:eng_x_preferred":[
        "Asoda"
    ],
    "wof:name":"Asoda",
    "wof:placetype":"locality",
    "wof:population":44
},
  "geometry": {"coordinates":[69.815938,26.758644],"type":"Point"}
}