{
  "type": "Feature",
  "properties": {
    "iso:country":"IN",
    "ks:ks_name":"Purba Khalbar",
    "ks:ks_pop":3030,
    "ks:ks_type":"HABITATION",
    "name:eng_x_preferred":[
        "Purba Khalbar"
    ],
    "wof:name":"Purba Khalbar",
    "wof:placetype":"locality",
    "wof:population":3030
},
  "geometry": {"coordinates":[88.60565099999999,22.216604],"type":"Point"}
}