{
  "type": "Feature",
  "properties": {
    "iso:country":"IN",
    "ks:ks_name":"Lewa",
    "ks:ks_pop":1076,
    "ks:ks_type":"VILLAGE",
    "name:eng_x_preferred":[
        "Lewa"
    ],
    "wof:name":"Lewa",
    "wof:placetype":"locality",
    "wof:population":1076
},
  "geometry": {"coordinates":[83.718767,24.931948],"type":"Point"}
}