{
  "type": "Feature",
  "properties": {
    "gn:admin1_code":"19.0",
    "gn:admin2_code":"564.0",
    "gn:asciiname":"Mahur",
    "gn:country_code":"IN",
    "gn:dem":564,
    "gn:feature_class":"P",
    "gn:feature_code":"PPL",
    "gn:name":"M\u0101h\u016br",
    "gn:population":0,
    "gn:timezone":"Asia/Kolkata",
    "iso:country":"IN",
    "name:ceb_x_preferred":[
        "Mahur"
    ],
    "name:swe_x_preferred":[
        "Mahur"
    ],
    "wof:name":"Mahur",
    "wof:placetype":"locality"
},
  "geometry": {"coordinates":[75.31501,14.93127],"type":"Point"}
}