{
  "type": "Feature",
  "properties": {
    "iso:country":"IN",
    "ks:ks_name":"Bagwalikhan",
    "ks:ks_pop":57,
    "ks:ks_type":"HABITATION",
    "name:eng_x_preferred":[
        "Bagwalikhan"
    ],
    "wof:name":"Bagwalikhan",
    "wof:placetype":"locality",
    "wof:population":57
},
  "geometry": {"coordinates":[79.775783,29.761305],"type":"Point"}
}