{
  "type": "Feature",
  "properties": {
    "iso:country":"IN",
    "ks:ks_name":"Bashkaltilla",
    "ks:ks_pop":1435,
    "ks:ks_type":"HABITATION",
    "name:eng_x_preferred":[
        "Bashkaltilla"
    ],
    "wof:name":"Bashkaltilla",
    "wof:placetype":"locality",
    "wof:population":1435
},
  "geometry": {"coordinates":[92.430775,24.570438],"type":"Point"}
}