{
  "type": "Feature",
  "properties": {
    "gn:admin1_code":"16.0",
    "gn:admin2_code":"517.0",
    "gn:asciiname":"Dapivli",
    "gn:country_code":"IN",
    "gn:dem":19,
    "gn:feature_class":"P",
    "gn:feature_code":"PPL",
    "gn:name":"Dapivli",
    "gn:population":0,
    "gn:timezone":"Asia/Kolkata",
    "iso:country":"IN",
    "wof:name":"Dapivli",
    "wof:placetype":"locality"
},
  "geometry": {"coordinates":[72.95896999999999,19.44196],"type":"Point"}
}