{
  "type": "Feature",
  "properties": {
    "iso:country":"IN",
    "ks:ks_name":"Batru",
    "ks:ks_pop":125,
    "ks:ks_type":"VILLAGE",
    "name:eng_x_preferred":[
        "Batru"
    ],
    "wof:name":"Batru",
    "wof:placetype":"locality",
    "wof:population":125
},
  "geometry": {"coordinates":[84.504653,23.469359],"type":"Point"}
}