{
  "type": "Feature",
  "properties": {
    "iso:country":"IN",
    "ks:ks_name":"Rankotha",
    "ks:ks_pop":1889,
    "ks:ks_type":"VILLAGE",
    "ks:ks_uagg_main":0,
    "name:eng_x_preferred":[
        "Rankotha"
    ],
    "wof:name":"Rankotha",
    "wof:placetype":"locality",
    "wof:population":1889
},
  "geometry": {"coordinates":[87.38908499999999,21.603061],"type":"Point"}
}