{
  "type": "Feature",
  "properties": {
    "iso:country":"IN",
    "ks:ks_alt_nam":"R\u0101mpur",
    "ks:ks_name":"Rampur",
    "ks:ks_pop":787,
    "ks:ks_type":"VILLAGE",
    "name:eng_x_preferred":[
        "Rampur"
    ],
    "name:eng_x_variant":[
        "R\u0101mpur"
    ],
    "wof:name":"Rampur",
    "wof:placetype":"locality",
    "wof:population":787
},
  "geometry": {"coordinates":[83.99616,24.79097],"type":"Point"}
}