{
  "type": "Feature",
  "properties": {
    "gn:admin1_code":"11",
    "gn:admin2_code":"23.0",
    "gn:asciiname":"Gara Got",
    "gn:country_code":"IN",
    "gn:dem":2736,
    "gn:feature_class":"P",
    "gn:feature_code":"PPL",
    "gn:name":"Gara Got",
    "gn:population":0,
    "gn:timezone":"Asia/Kolkata",
    "iso:country":"IN",
    "wof:name":"Gara Got",
    "wof:placetype":"locality"
},
  "geometry": {"coordinates":[76.21669,32.81143],"type":"Point"}
}