{
  "type": "Feature",
  "properties": {
    "iso:country":"IN",
    "ks:ks_name":"Urugudde",
    "ks:ks_pop":85,
    "ks:ks_type":"HABITATION",
    "name:eng_x_preferred":[
        "Urugudde"
    ],
    "wof:name":"Urugudde",
    "wof:placetype":"locality",
    "wof:population":85
},
  "geometry": {"coordinates":[75.319648,13.41718],"type":"Point"}
}