{
  "type": "Feature",
  "properties": {
    "iso:country":"IN",
    "ks:ks_alt_nam":"HARRADHODHI",
    "ks:ks_name":"Harradhodhi",
    "ks:ks_pop":150,
    "ks:ks_type":"HABITATION",
    "name:eng_x_preferred":[
        "Harradhodhi"
    ],
    "wof:name":"Harradhodhi",
    "wof:placetype":"locality",
    "wof:population":150
},
  "geometry": {"coordinates":[83.211133,22.857574],"type":"Point"}
}