{
  "type": "Feature",
  "properties": {
    "iso:country":"IN",
    "ks:ks_alt_nam":"K\u0101dakkinaru",
    "ks:ks_name":"Kadakkinaru",
    "ks:ks_type":"VILLAGE",
    "ks:ks_uagg_main":0,
    "name:eng_x_preferred":[
        "Kadakkinaru"
    ],
    "name:eng_x_variant":[
        "K\u0101dakkinaru"
    ],
    "wof:name":"Kadakkinaru",
    "wof:placetype":"locality"
},
  "geometry": {"coordinates":[78.173725,9.985942],"type":"Point"}
}