{
  "type": "Feature",
  "properties": {
    "gn:admin1_code":"35.0",
    "gn:admin2_code":"427",
    "gn:asciiname":"Agasode",
    "gn:country_code":"IN",
    "gn:dem":405,
    "gn:feature_class":"P",
    "gn:feature_code":"PPL",
    "gn:name":"Ag\u0101sode",
    "gn:population":0,
    "gn:timezone":"Asia/Kolkata",
    "iso:country":"IN",
    "name:und_x_variant":[
        "Agasod",
        "Ag\u0101sode"
    ],
    "wof:name":"Agasode",
    "wof:placetype":"locality"
},
  "geometry": {"coordinates":[78.16068,24.27296],"type":"Point"}
}