{
  "type": "Feature",
  "properties": {
    "iso:country":"IN",
    "ks:ks_name":"Dhalagaon Pt I",
    "ks:ks_pop":873,
    "ks:ks_type":"HABITATION",
    "name:eng_x_preferred":[
        "Dhalagaon Pt I"
    ],
    "wof:name":"Dhalagaon Pt I",
    "wof:placetype":"locality",
    "wof:population":873
},
  "geometry": {"coordinates":[90.494407,26.40164],"type":"Point"}
}