{
  "type": "Feature",
  "properties": {
    "iso:country":"IN",
    "ks:ks_name":"Baraigram",
    "ks:ks_pop":556,
    "ks:ks_type":"HABITATION",
    "ks:ks_uagg_main":0,
    "name:eng_x_preferred":[
        "Baraigram"
    ],
    "wof:name":"Baraigram",
    "wof:placetype":"neighbourhood",
    "wof:population":556
},
  "geometry": {"coordinates":[92.33845100000001,24.679919],"type":"Point"}
}