{
  "type": "Feature",
  "properties": {
    "iso:country":"IN",
    "ks:ks_name":"Maleyur Hadi",
    "ks:ks_pop":180,
    "ks:ks_type":"HABITATION",
    "name:eng_x_preferred":[
        "Maleyur Hadi"
    ],
    "wof:name":"Maleyur Hadi",
    "wof:placetype":"locality",
    "wof:population":180
},
  "geometry": {"coordinates":[76.36538400000001,11.860439],"type":"Point"}
}