{
  "type": "Feature",
  "properties": {
    "iso:country":"IN",
    "ks:ks_name":"Dhobin Purwa",
    "ks:ks_pop":59,
    "ks:ks_type":"HABITATION",
    "ks:ks_uagg_main":0,
    "name:eng_x_preferred":[
        "Dhobin Purwa"
    ],
    "wof:name":"Dhobin Purwa",
    "wof:placetype":"neighbourhood",
    "wof:population":59
},
  "geometry": {"coordinates":[81.047692,27.644409],"type":"Point"}
}