{
  "type": "Feature",
  "properties": {
    "iso:country":"IN",
    "ks:ks_name":"Bakeriya",
    "ks:ks_pop":451,
    "ks:ks_type":"HABITATION",
    "name:eng_x_preferred":[
        "Bakeriya"
    ],
    "wof:name":"Bakeriya",
    "wof:placetype":"locality",
    "wof:population":451
},
  "geometry": {"coordinates":[73.45717999999999,23.195633],"type":"Point"}
}