{
  "type": "Feature",
  "properties": {
    "iso:country":"IN",
    "ks:ks_name":"Ragghupur",
    "ks:ks_pop":591,
    "ks:ks_type":"HABITATION",
    "name:eng_x_preferred":[
        "Ragghupur"
    ],
    "wof:name":"Ragghupur",
    "wof:placetype":"locality",
    "wof:population":591
},
  "geometry": {"coordinates":[82.573397,25.364835],"type":"Point"}
}