{
  "type": "Feature",
  "properties": {
    "gn:admin1_code":"24.0",
    "gn:admin2_code":"104.0",
    "gn:asciiname":"Billaora",
    "gn:country_code":"IN",
    "gn:dem":279,
    "gn:feature_class":"P",
    "gn:feature_code":"PPL",
    "gn:name":"Bill\u0101ora",
    "gn:population":0,
    "gn:timezone":"Asia/Kolkata",
    "iso:country":"IN",
    "ks:ks_alt_nam":"Bill\u0101ora",
    "ks:ks_name":"Billaora",
    "ks:ks_type":"VILLAGE",
    "ks:ks_uagg_main":0,
    "wof:name":"Billaora",
    "wof:placetype":"neighbourhood"
},
  "geometry": {"coordinates":[76.60899999999999,27.60396],"type":"Point"}
}