{
  "type": "Feature",
  "properties": {
    "iso:country":"IN",
    "ks:ks_alt_nam":"RABIDAS TOLA",
    "ks:ks_name":"Rabidas Tola",
    "ks:ks_pop":297,
    "ks:ks_type":"HABITATION",
    "ks:ks_uagg_main":0,
    "name:eng_x_preferred":[
        "Rabidas Tola"
    ],
    "wof:name":"Rabidas Tola",
    "wof:placetype":"neighbourhood",
    "wof:population":297
},
  "geometry": {"coordinates":[84.619215,24.629122],"type":"Point"}
}