{
  "type": "Feature",
  "properties": {
    "iso:country":"IN",
    "ks:ks_name":"2 K-A",
    "ks:ks_pop":156,
    "ks:ks_type":"VILLAGE",
    "name:eng_x_preferred":[
        "2 K-A"
    ],
    "wof:name":"2 K-A",
    "wof:placetype":"locality",
    "wof:population":156
},
  "geometry": {"coordinates":[73.225236,29.138546],"type":"Point"}
}