{
  "type": "Feature",
  "properties": {
    "iso:country":"IN",
    "ks:ks_name":"Maa Bhandani Bazar",
    "ks:ks_pop":254,
    "ks:ks_type":"HABITATION",
    "name:eng_x_preferred":[
        "Maa Bhandani Bazar"
    ],
    "wof:name":"Maa Bhandani Bazar",
    "wof:placetype":"locality",
    "wof:population":254
},
  "geometry": {"coordinates":[89.093349,26.625508],"type":"Point"}
}