{
  "type": "Feature",
  "properties": {
    "iso:country":"IN",
    "ks:ks_name":"Vangara",
    "ks:ks_pop":144,
    "ks:ks_type":"HABITATION",
    "name:eng_x_preferred":[
        "Vangara"
    ],
    "wof:name":"Vangara",
    "wof:placetype":"locality",
    "wof:population":144
},
  "geometry": {"coordinates":[84.17374599999999,18.638567],"type":"Point"}
}