{
  "type": "Feature",
  "properties": {
    "gn:admin1_code":"36.0",
    "gn:admin2_code":"177.0",
    "gn:asciiname":"Pura Laukai",
    "gn:country_code":"IN",
    "gn:dem":97,
    "gn:feature_class":"P",
    "gn:feature_code":"PPL",
    "gn:name":"Pura Lauk\u0101i",
    "gn:population":0,
    "gn:timezone":"Asia/Kolkata",
    "iso:country":"IN",
    "wof:name":"Pura Laukai",
    "wof:placetype":"locality"
},
  "geometry": {"coordinates":[81.76224999999999,26.86116],"type":"Point"}
}