{
  "type": "Feature",
  "properties": {
    "iso:country":"IN",
    "ks:ks_name":"Dihipara",
    "ks:ks_pop":600,
    "ks:ks_type":"HABITATION",
    "name:eng_x_preferred":[
        "Dihipara"
    ],
    "wof:name":"Dihipara",
    "wof:placetype":"locality",
    "wof:population":600
},
  "geometry": {"coordinates":[87.334637,23.7914],"type":"Point"}
}