{
  "type": "Feature",
  "properties": {
    "iso:country":"IN",
    "ks:ks_name":"Kothidhura Godamdhura",
    "ks:ks_pop":578,
    "ks:ks_type":"HABITATION",
    "name:eng_x_preferred":[
        "Kothidhura Godamdhura"
    ],
    "wof:name":"Kothidhura Godamdhura",
    "wof:placetype":"locality",
    "wof:population":578
},
  "geometry": {"coordinates":[88.184138,27.042683],"type":"Point"}
}