{
  "type": "Feature",
  "properties": {
    "gn:admin1_code":"19",
    "gn:admin2_code":"568.0",
    "gn:asciiname":"Sasaravalli",
    "gn:country_code":"IN",
    "gn:dem":637,
    "gn:feature_class":"P",
    "gn:feature_code":"PPL",
    "gn:name":"Sasaravalli",
    "gn:population":0,
    "gn:timezone":"Asia/Kolkata",
    "iso:country":"IN",
    "ks:ks_name":"Sasaravalli",
    "ks:ks_pop":103,
    "ks:ks_type":"VILLAGE",
    "name:eng_x_preferred":[
        "Sasaravalli"
    ],
    "wof:name":"Sasaravalli",
    "wof:placetype":"locality",
    "wof:population":103
},
  "geometry": {"coordinates":[74.93829599999999,14.160154],"type":"Point"}
}