{
  "type": "Feature",
  "properties": {
    "iso:country":"IN",
    "ks:ks_name":"Sambrepada",
    "ks:ks_pop":147,
    "ks:ks_type":"HABITATION",
    "name:eng_x_preferred":[
        "Sambrepada"
    ],
    "wof:name":"Sambrepada",
    "wof:placetype":"locality",
    "wof:population":147
},
  "geometry": {"coordinates":[72.964286,19.710615],"type":"Point"}
}