{
  "type": "Feature",
  "properties": {
    "gn:admin1_code":"10",
    "gn:admin2_code":"76.0",
    "gn:asciiname":"Mundlana",
    "gn:country_code":"IN",
    "gn:dem":235,
    "gn:feature_class":"P",
    "gn:feature_code":"PPL",
    "gn:name":"Mundl\u0101na",
    "gn:population":0,
    "gn:timezone":"Asia/Kolkata",
    "iso:country":"IN",
    "wof:name":"Mundlana",
    "wof:placetype":"locality"
},
  "geometry": {"coordinates":[76.76508000000003,29.20422],"type":"Point"}
}