{
  "type": "Feature",
  "properties": {
    "iso:country":"IN",
    "ks:ks_name":"Badabruti",
    "ks:ks_pop":41,
    "ks:ks_type":"VILLAGE",
    "name:eng_x_preferred":[
        "Badabruti"
    ],
    "wof:name":"Badabruti",
    "wof:placetype":"locality",
    "wof:population":41
},
  "geometry": {"coordinates":[85.996208,20.273205],"type":"Point"}
}