{
  "type": "Feature",
  "properties": {
    "iso:country":"IN",
    "ks:ks_name":"Matada Gadde",
    "ks:ks_pop":9,
    "ks:ks_type":"HABITATION",
    "name:eng_x_preferred":[
        "Matada Gadde"
    ],
    "wof:name":"Matada Gadde",
    "wof:placetype":"locality",
    "wof:population":9
},
  "geometry": {"coordinates":[74.71458199999999,14.064451],"type":"Point"}
}