{
  "type": "Feature",
  "properties": {
    "iso:country":"IN",
    "ks:ks_name":"Namte Ka Pura",
    "ks:ks_pop":793,
    "ks:ks_type":"HABITATION",
    "name:eng_x_preferred":[
        "Namte Ka Pura"
    ],
    "wof:name":"Namte Ka Pura",
    "wof:placetype":"locality",
    "wof:population":793
},
  "geometry": {"coordinates":[77.154574,26.306028],"type":"Point"}
}