{
  "type": "Feature",
  "properties": {
    "iso:country":"IN",
    "ks:ks_name":"Janathacolony",
    "ks:ks_pop":164,
    "ks:ks_type":"HABITATION",
    "name:eng_x_preferred":[
        "Janathacolony"
    ],
    "wof:name":"Janathacolony",
    "wof:placetype":"locality",
    "wof:population":164
},
  "geometry": {"coordinates":[74.965109,14.16502],"type":"Point"}
}