{
  "type": "Feature",
  "properties": {
    "iso:country":"IN",
    "ks:ks_name":"Goibandha",
    "ks:ks_pop":236,
    "ks:ks_type":"VILLAGE",
    "name:eng_x_preferred":[
        "Goibandha"
    ],
    "wof:name":"Goibandha",
    "wof:placetype":"locality",
    "wof:population":236
},
  "geometry": {"coordinates":[83.949258,19.333391],"type":"Point"}
}