{
  "type": "Feature",
  "properties": {
    "gn:admin1_code":"25.0",
    "gn:admin2_code":"605.0",
    "gn:asciiname":"Agaramcheri",
    "gn:country_code":"IN",
    "gn:dem":270,
    "gn:feature_class":"P",
    "gn:feature_code":"PPL",
    "gn:name":"Agaramch\u0113ri",
    "gn:population":0,
    "gn:timezone":"Asia/Kolkata",
    "iso:country":"IN",
    "wof:name":"Agaramcheri",
    "wof:placetype":"locality"
},
  "geometry": {"coordinates":[78.89601,12.89486],"type":"Point"}
}