{
  "type": "Feature",
  "properties": {
    "iso:country":"IN",
    "ks:ks_alt_nam":"Hem\u012bpur Kum\u012bpur",
    "ks:ks_name":"Hemipur Kumipur",
    "ks:ks_pop":82,
    "ks:ks_type":"VILLAGE",
    "name:eng_x_preferred":[
        "Hemipur Kumipur"
    ],
    "name:eng_x_variant":[
        "Hem\u012bpur Kum\u012bpur"
    ],
    "wof:name":"Hemipur Kumipur",
    "wof:placetype":"locality",
    "wof:population":82
},
  "geometry": {"coordinates":[79.56235599999999,28.036328],"type":"Point"}
}