{
  "type": "Feature",
  "properties": {
    "gn:admin1_code":"28",
    "gn:admin2_code":"334.0",
    "gn:asciiname":"Ulkanda",
    "gn:country_code":"IN",
    "gn:dem":40,
    "gn:feature_class":"P",
    "gn:feature_code":"PPL",
    "gn:name":"Ulkanda",
    "gn:population":0,
    "gn:timezone":"Asia/Kolkata",
    "iso:country":"IN",
    "wof:name":"Ulkanda",
    "wof:placetype":"locality"
},
  "geometry": {"coordinates":[87.80974000000001,23.89124],"type":"Point"}
}