{
  "type": "Feature",
  "properties": {
    "iso:country":"IN",
    "ks:ks_name":"Bhagorapada",
    "ks:ks_pop":302,
    "ks:ks_type":"VILLAGE",
    "ks:ks_uagg_main":0,
    "name:eng_x_preferred":[
        "Bhagorapada"
    ],
    "wof:name":"Bhagorapada",
    "wof:placetype":"neighbourhood",
    "wof:population":302
},
  "geometry": {"coordinates":[73.326222,23.917389],"type":"Point"}
}