{
  "type": "Feature",
  "properties": {
    "iso:country":"IN",
    "ks:ks_name":"Jadiadarpurwa",
    "ks:ks_pop":52,
    "ks:ks_type":"HABITATION",
    "ks:ks_uagg_main":0,
    "name:eng_x_preferred":[
        "Jadiadarpurwa"
    ],
    "wof:name":"Jadiadarpurwa",
    "wof:placetype":"neighbourhood",
    "wof:population":52
},
  "geometry": {"coordinates":[81.50192300000001,27.57898],"type":"Point"}
}