{
  "type": "Feature",
  "properties": {
    "iso:country":"IN",
    "ks:ks_name":"Bara Dhaidka",
    "ks:ks_pop":488,
    "ks:ks_type":"VILLAGE",
    "ks:ks_uagg_main":0,
    "name:eng_x_preferred":[
        "Bara Dhaidka"
    ],
    "wof:name":"Bara Dhaidka",
    "wof:placetype":"neighbourhood",
    "wof:population":488
},
  "geometry": {"coordinates":[86.593957,22.637869],"type":"Point"}
}