{
  "type": "Feature",
  "properties": {
    "gn:admin1_code":"19.0",
    "gn:admin2_code":"557.0",
    "gn:asciiname":"Narsalgi",
    "gn:country_code":"IN",
    "gn:dem":578,
    "gn:feature_class":"P",
    "gn:feature_code":"PPL",
    "gn:name":"Narsalgi",
    "gn:population":0,
    "gn:timezone":"Asia/Kolkata",
    "iso:country":"IN",
    "wof:name":"Narsalgi",
    "wof:placetype":"locality"
},
  "geometry": {"coordinates":[76.00413,16.50099],"type":"Point"}
}