{
  "type": "Feature",
  "properties": {
    "iso:country":"IN",
    "ks:ks_name":"Lamada",
    "ks:ks_pop":123,
    "ks:ks_type":"HABITATION",
    "name:eng_x_preferred":[
        "Lamada"
    ],
    "wof:name":"Lamada",
    "wof:placetype":"locality",
    "wof:population":123
},
  "geometry": {"coordinates":[82.706357,18.443248],"type":"Point"}
}