{
  "type": "Feature",
  "properties": {
    "gn:admin1_code":"24.0",
    "gn:admin2_code":"119",
    "gn:asciiname":"Deolia",
    "gn:country_code":"IN",
    "gn:dem":389,
    "gn:feature_class":"P",
    "gn:feature_code":"PPL",
    "gn:name":"Deolia",
    "gn:population":0,
    "gn:timezone":"Asia/Kolkata",
    "iso:country":"IN",
    "wof:name":"Deolia",
    "wof:placetype":"neighbourhood"
},
  "geometry": {"coordinates":[74.78489,25.90845],"type":"Point"}
}