{
  "type": "Feature",
  "properties": {
    "gn:admin1_code":"24.0",
    "gn:admin2_code":"108.0",
    "gn:asciiname":"Bandhawara",
    "gn:country_code":"IN",
    "gn:dem":282,
    "gn:feature_class":"P",
    "gn:feature_code":"PPL",
    "gn:name":"Bandh\u0101w\u0101ra",
    "gn:population":0,
    "gn:timezone":"Asia/Kolkata",
    "iso:country":"IN",
    "name:und_x_variant":[
        "Bandh\u0101w\u0101ra",
        "D\u016bngarw\u0101ra"
    ],
    "wof:name":"Bandhawara",
    "wof:placetype":"locality"
},
  "geometry": {"coordinates":[76.54415,26.66718],"type":"Point"}
}