{
  "type": "Feature",
  "properties": {
    "iso:country":"IN",
    "ks:ks_name":"Belguri",
    "ks:ks_pop":38,
    "ks:ks_type":"HABITATION",
    "name:eng_x_preferred":[
        "Belguri"
    ],
    "wof:name":"Belguri",
    "wof:placetype":"locality",
    "wof:population":38
},
  "geometry": {"coordinates":[91.38214499999999,26.011],"type":"Point"}
}