{
  "type": "Feature",
  "properties": {
    "iso:country":"IN",
    "ks:ks_name":"Gudam State",
    "ks:ks_pop":263,
    "ks:ks_type":"VILLAGE",
    "name:eng_x_preferred":[
        "Gudam State"
    ],
    "wof:name":"Gudam State",
    "wof:placetype":"locality",
    "wof:population":263
},
  "geometry": {"coordinates":[79.51479,30.034174],"type":"Point"}
}