{
  "type": "Feature",
  "properties": {
    "iso:country":"IN",
    "ks:ks_name":"Hamaja Pur",
    "ks:ks_pop":907,
    "ks:ks_type":"HABITATION",
    "name:eng_x_preferred":[
        "Hamaja Pur"
    ],
    "wof:name":"Hamaja Pur",
    "wof:placetype":"locality",
    "wof:population":907
},
  "geometry": {"coordinates":[82.297,25.38944],"type":"Point"}
}