{
  "type": "Feature",
  "properties": {
    "iso:country":"IN",
    "ks:ks_name":"Ashrafi Jote",
    "ks:ks_pop":86,
    "ks:ks_type":"HABITATION",
    "name:eng_x_preferred":[
        "Ashrafi Jote"
    ],
    "wof:name":"Ashrafi Jote",
    "wof:placetype":"locality",
    "wof:population":86
},
  "geometry": {"coordinates":[82.645471,27.400475],"type":"Point"}
}