{
  "type": "Feature",
  "properties": {
    "iso:country":"IN",
    "ks:ks_name":"Khemichak",
    "ks:ks_pop":1369,
    "ks:ks_type":"VILLAGE",
    "name:eng_x_preferred":[
        "Khemichak"
    ],
    "wof:name":"Khemichak",
    "wof:placetype":"locality",
    "wof:population":1369
},
  "geometry": {"coordinates":[86.89803000000001,25.026977],"type":"Point"}
}