{
  "type": "Feature",
  "properties": {
    "gn:admin1_code":"36.0",
    "gn:admin2_code":"186.0",
    "gn:asciiname":"Phulwaria",
    "gn:country_code":"IN",
    "gn:dem":90,
    "gn:feature_class":"P",
    "gn:feature_code":"PPL",
    "gn:name":"Phulwaria",
    "gn:population":0,
    "gn:timezone":"Asia/Kolkata",
    "iso:country":"IN",
    "name:bpy_x_preferred":[
        "\u09ab\u09c1\u09b2\u09f1\u09be\u09b0\u09bf\u09af\u09bc\u09be"
    ],
    "name:ita_x_preferred":[
        "Phulwaria"
    ],
    "name:msa_x_preferred":[
        "Phulwaria"
    ],
    "name:nld_x_preferred":[
        "Phulwaria"
    ],
    "name:pol_x_preferred":[
        "Phulwaria"
    ],
    "name:por_x_preferred":[
        "Phulwaria"
    ],
    "name:urd_x_preferred":[
        "\u067e\u06be\u0644\u0648\u0627\u0631\u06cc\u0627"
    ],
    "name:vie_x_preferred":[
        "Phulwaria"
    ],
    "name:zho_x_preferred":[
        "\u666e\u5c14\u74e6\u91cc\u4e9a"
    ],
    "wof:name":"Phulwaria",
    "wof:placetype":"locality"
},
  "geometry": {"coordinates":[82.98215,27.02051],"type":"Point"}
}