{
  "type": "Feature",
  "properties": {
    "gn:admin1_code":"3.0",
    "gn:admin2_code":"312.0",
    "gn:asciiname":"Alengi Gaon",
    "gn:country_code":"IN",
    "gn:dem":91,
    "gn:feature_class":"P",
    "gn:feature_code":"PPL",
    "gn:name":"Alengi Gaon",
    "gn:population":0,
    "gn:timezone":"Asia/Kolkata",
    "iso:country":"IN",
    "ks:ks_name":"Alengi Gaon",
    "ks:ks_pop":552,
    "ks:ks_type":"VILLAGE",
    "ks:ks_uagg_main":0,
    "name:eng_x_preferred":[
        "Alengi Gaon"
    ],
    "wof:name":"Alengi Gaon",
    "wof:placetype":"neighbourhood",
    "wof:population":552
},
  "geometry": {"coordinates":[94.129374,26.586185],"type":"Point"}
}