{
  "type": "Feature",
  "properties": {
    "gn:admin1_code":"34",
    "gn:admin2_code":"218.0",
    "gn:asciiname":"Bariarpur",
    "gn:country_code":"IN",
    "gn:dem":67,
    "gn:feature_class":"P",
    "gn:feature_code":"PPL",
    "gn:name":"Bariarpur",
    "gn:population":0,
    "gn:timezone":"Asia/Kolkata",
    "iso:country":"IN",
    "ks:ks_name":"Baryarpur",
    "ks:ks_pop":2237,
    "ks:ks_type":"VILLAGE",
    "name:eng_x_preferred":[
        "Baryarpur"
    ],
    "name:eng_x_variant":[
        "Bariarpur"
    ],
    "wof:name":"Baryarpur",
    "wof:placetype":"locality",
    "wof:population":2237
},
  "geometry": {"coordinates":[84.427603,26.133732],"type":"Point"}
}