{
  "type": "Feature",
  "properties": {
    "gn:admin1_code":"16.0",
    "gn:admin2_code":"498.0",
    "gn:asciiname":"Jamhan Pada",
    "gn:country_code":"IN",
    "gn:dem":623,
    "gn:feature_class":"P",
    "gn:feature_code":"PPL",
    "gn:name":"J\u0101mhan P\u0101da",
    "gn:population":0,
    "gn:timezone":"Asia/Kolkata",
    "iso:country":"IN",
    "wof:name":"Jamhan Pada",
    "wof:placetype":"locality"
},
  "geometry": {"coordinates":[74.01483,21.05369],"type":"Point"}
}