{
  "type": "Feature",
  "properties": {
    "iso:country":"IN",
    "ks:ks_name":"Tivsadi",
    "ks:ks_pop":0,
    "ks:ks_type":"VILLAGE",
    "name:eng_x_preferred":[
        "Tivsadi"
    ],
    "wof:name":"Tivsadi",
    "wof:placetype":"locality",
    "wof:population":0
},
  "geometry": {"coordinates":[78.731528,20.464103],"type":"Point"}
}