{
  "type": "Feature",
  "properties": {
    "iso:country":"IN",
    "ks:ks_name":"Matkapara",
    "ks:ks_pop":198,
    "ks:ks_type":"HABITATION",
    "name:eng_x_preferred":[
        "Matkapara"
    ],
    "wof:name":"Matkapara",
    "wof:placetype":"locality",
    "wof:population":198
},
  "geometry": {"coordinates":[81.929109,20.337646],"type":"Point"}
}