{
  "type": "Feature",
  "properties": {
    "gn:admin1_code":"3.0",
    "gn:admin2_code":"312",
    "gn:asciiname":"Bhalukmara",
    "gn:country_code":"IN",
    "gn:dem":130,
    "gn:feature_class":"P",
    "gn:feature_code":"PPL",
    "gn:name":"Bhalukmara",
    "gn:population":0,
    "gn:timezone":"Asia/Kolkata",
    "iso:country":"IN",
    "wof:name":"Bhalukmara",
    "wof:placetype":"locality"
},
  "geometry": {"coordinates":[94.46666999999999,26.68333],"type":"Point"}
}