{
  "type": "Feature",
  "properties": {
    "iso:country":"IN",
    "ks:ks_name":"Sajwanichhoti",
    "ks:ks_pop":1016,
    "ks:ks_type":"VILLAGE",
    "name:eng_x_preferred":[
        "Sajwanichhoti"
    ],
    "wof:name":"Sajwanichhoti",
    "wof:placetype":"locality",
    "wof:population":1016
},
  "geometry": {"coordinates":[74.599496,22.681626],"type":"Point"}
}