{
  "type": "Feature",
  "properties": {
    "iso:country":"IN",
    "ks:ks_name":"Tumandi",
    "ks:ks_pop":749,
    "ks:ks_type":"VILLAGE",
    "name:eng_x_preferred":[
        "Tumandi"
    ],
    "wof:name":"Tumandi",
    "wof:placetype":"locality",
    "wof:population":749
},
  "geometry": {"coordinates":[84.774219,20.355867],"type":"Point"}
}