{
  "type": "Feature",
  "properties": {
    "iso:country":"IN",
    "ks:ks_name":"Rampali Purwa",
    "ks:ks_pop":150,
    "ks:ks_type":"HABITATION",
    "name:eng_x_preferred":[
        "Rampali Purwa"
    ],
    "wof:name":"Rampali Purwa",
    "wof:placetype":"locality",
    "wof:population":150
},
  "geometry": {"coordinates":[80.53665599999999,25.129052],"type":"Point"}
}