{
  "type": "Feature",
  "properties": {
    "iso:country":"IN",
    "ks:ks_alt_nam":"KB",
    "ks:ks_name":"Kb",
    "ks:ks_pop":219,
    "ks:ks_type":"HABITATION",
    "name:eng_x_preferred":[
        "Kb"
    ],
    "wof:name":"Kb",
    "wof:placetype":"locality",
    "wof:population":219
},
  "geometry": {"coordinates":[82.822208,25.795613],"type":"Point"}
}