{
  "type": "Feature",
  "properties": {
    "iso:country":"IN",
    "ks:ks_name":"Purab Bakhara",
    "ks:ks_pop":409,
    "ks:ks_type":"HABITATION",
    "name:eng_x_preferred":[
        "Purab Bakhara"
    ],
    "wof:name":"Purab Bakhara",
    "wof:placetype":"locality",
    "wof:population":409
},
  "geometry": {"coordinates":[81.660763,26.573736],"type":"Point"}
}