{
  "type": "Feature",
  "properties": {
    "iso:country":"IN",
    "ks:ks_name":"Chilpahadi",
    "ks:ks_pop":1374,
    "ks:ks_type":"HABITATION",
    "name:eng_x_preferred":[
        "Chilpahadi"
    ],
    "wof:name":"Chilpahadi",
    "wof:placetype":"locality",
    "wof:population":1374
},
  "geometry": {"coordinates":[79.008346,23.999913],"type":"Point"}
}