{
  "type": "Feature",
  "properties": {
    "iso:country":"IN",
    "ks:ks_name":"Mahra Tola",
    "ks:ks_pop":649,
    "ks:ks_type":"HABITATION",
    "name:eng_x_preferred":[
        "Mahra Tola"
    ],
    "wof:name":"Mahra Tola",
    "wof:placetype":"locality",
    "wof:population":649
},
  "geometry": {"coordinates":[83.63015300000001,24.329257],"type":"Point"}
}