{
  "type": "Feature",
  "properties": {
    "iso:country":"IN",
    "ks:ks_name":"Santoshi Nagar",
    "ks:ks_pop":900,
    "ks:ks_type":"VILLAGE",
    "name:eng_x_preferred":[
        "Santoshi Nagar"
    ],
    "wof:name":"Santoshi Nagar",
    "wof:placetype":"locality",
    "wof:population":900
},
  "geometry": {"coordinates":[83.72080800000001,23.625086],"type":"Point"}
}