{
  "type": "Feature",
  "properties": {
    "gn:admin1_code":"23",
    "gn:admin2_code":"39.0",
    "gn:asciiname":"Lal Mazara",
    "gn:country_code":"IN",
    "gn:dem":252,
    "gn:feature_class":"P",
    "gn:feature_code":"PPL",
    "gn:name":"Lal Maz\u0101ra",
    "gn:population":0,
    "gn:timezone":"Asia/Kolkata",
    "iso:country":"IN",
    "wof:name":"Lal Mazara",
    "wof:placetype":"locality"
},
  "geometry": {"coordinates":[75.99438000000001,31.12277000000001],"type":"Point"}
}