{
  "type": "Feature",
  "properties": {
    "gn:admin1_code":"2.0",
    "gn:admin2_code":"550.0",
    "gn:asciiname":"Vaddepalem",
    "gn:country_code":"IN",
    "gn:dem":88,
    "gn:feature_class":"P",
    "gn:feature_code":"PPL",
    "gn:name":"Vaddep\u0101lem",
    "gn:population":0,
    "gn:timezone":"Asia/Kolkata",
    "iso:country":"IN",
    "wof:name":"Vaddepalem",
    "wof:placetype":"locality"
},
  "geometry": {"coordinates":[79.59056,14.82169],"type":"Point"}
}