{
  "type": "Feature",
  "properties": {
    "gn:admin1_code":"19.0",
    "gn:admin2_code":"565.0",
    "gn:asciiname":"Kondinayakanahalli",
    "gn:country_code":"IN",
    "gn:dem":488,
    "gn:feature_class":"P",
    "gn:feature_code":"PPL",
    "gn:name":"Kondin\u0101yakanahalli",
    "gn:population":0,
    "gn:timezone":"Asia/Kolkata",
    "iso:country":"IN",
    "wof:name":"Kondinayakanahalli",
    "wof:placetype":"neighbourhood"
},
  "geometry": {"coordinates":[76.41992,15.28239],"type":"Point"}
}