{
  "type": "Feature",
  "properties": {
    "iso:country":"IN",
    "ks:ks_name":"Uttar Purwa",
    "ks:ks_pop":59,
    "ks:ks_type":"HABITATION",
    "name:eng_x_preferred":[
        "Uttar Purwa"
    ],
    "wof:name":"Uttar Purwa",
    "wof:placetype":"locality",
    "wof:population":59
},
  "geometry": {"coordinates":[82.810034,26.730769],"type":"Point"}
}