{
  "type": "Feature",
  "properties": {
    "gn:admin1_code":"11",
    "gn:admin2_code":"33.0",
    "gn:asciiname":"Shoila",
    "gn:country_code":"IN",
    "gn:dem":1974,
    "gn:feature_class":"P",
    "gn:feature_code":"PPL",
    "gn:name":"Shoila",
    "gn:population":0,
    "gn:timezone":"Asia/Kolkata",
    "iso:country":"IN",
    "wof:name":"Shoila",
    "wof:placetype":"locality"
},
  "geometry": {"coordinates":[77.22638000000001,31.14802],"type":"Point"}
}