{
  "type": "Feature",
  "properties": {
    "gn:admin1_code":"36.0",
    "gn:admin2_code":"163.0",
    "gn:asciiname":"Makrandpur Kainjari",
    "gn:country_code":"IN",
    "gn:dem":140,
    "gn:feature_class":"P",
    "gn:feature_code":"PPL",
    "gn:name":"Makrandpur Kainjari",
    "gn:population":0,
    "gn:timezone":"Asia/Kolkata",
    "iso:country":"IN",
    "ks:ks_name":"Makrandpur Kahinjari",
    "ks:ks_pop":3329,
    "ks:ks_type":"VILLAGE",
    "name:eng_x_preferred":[
        "Makrandpur Kahinjari"
    ],
    "name:eng_x_variant":[
        "Makrandpur Kainjari"
    ],
    "wof:name":"Makrandpur Kahinjari",
    "wof:placetype":"locality",
    "wof:population":3329
},
  "geometry": {"coordinates":[79.91004100000001,26.614099],"type":"Point"}
}