{
  "type": "Feature",
  "properties": {
    "gn:admin1_code":"36.0",
    "gn:admin2_code":"163.0",
    "gn:asciiname":"Makrandpur Kainjari",
    "gn:country_code":"IN",
    "gn:dem":140,
    "gn:feature_class":"P",
    "gn:feature_code":"PPL",
    "gn:name":"Makrandpur Kainjari",
    "gn:population":0,
    "gn:timezone":"Asia/Kolkata",
    "iso:country":"IN",
    "wof:name":"Makrandpur Kainjari",
    "wof:placetype":"locality"
},
  "geometry": {"coordinates":[79.89203000000001,26.61135],"type":"Point"}
}