{
  "type": "Feature",
  "properties": {
    "iso:country":"IN",
    "ks:ks_name":"Marha",
    "ks:ks_pop":2539,
    "ks:ks_type":"VILLAGE",
    "name:eng_x_preferred":[
        "Marha"
    ],
    "wof:name":"Marha",
    "wof:placetype":"locality",
    "wof:population":2539
},
  "geometry": {"coordinates":[79.62597599999999,25.621165],"type":"Point"}
}