{
  "type": "Feature",
  "properties": {
    "gn:admin1_code":"24.0",
    "gn:admin2_code":"122.0",
    "gn:asciiname":"Jaton ka Khera",
    "gn:country_code":"IN",
    "gn:dem":429,
    "gn:feature_class":"P",
    "gn:feature_code":"PPL",
    "gn:name":"J\u0101ton ka Khera",
    "gn:population":0,
    "gn:timezone":"Asia/Kolkata",
    "iso:country":"IN",
    "name:und_x_variant":[
        "J\u0101ton ka Khera",
        "Jodh\u0101khera"
    ],
    "wof:name":"Jaton ka Khera",
    "wof:placetype":"locality"
},
  "geometry": {"coordinates":[74.62676999999999,25.32624],"type":"Point"}
}