{
  "type": "Feature",
  "properties": {
    "iso:country":"IN",
    "ks:ks_name":"Kadamtali",
    "ks:ks_pop":815,
    "ks:ks_type":"VILLAGE",
    "ks:ks_uagg_main":0,
    "name:eng_x_preferred":[
        "Kadamtali"
    ],
    "wof:name":"Kadamtali",
    "wof:placetype":"neighbourhood",
    "wof:population":815
},
  "geometry": {"coordinates":[88.106876,25.264404],"type":"Point"}
}