{
  "type": "Feature",
  "properties": {
    "iso:country":"IN",
    "ks:ks_name":"Khoi",
    "ks:ks_pop":238,
    "ks:ks_type":"VILLAGE",
    "name:eng_x_preferred":[
        "Khoi"
    ],
    "wof:name":"Khoi",
    "wof:placetype":"locality",
    "wof:population":238
},
  "geometry": {"coordinates":[76.987793,30.804354],"type":"Point"}
}