{
  "type": "Feature",
  "properties": {
    "gn:admin1_code":"10.0",
    "gn:admin2_code":"075",
    "gn:asciiname":"Faridpur",
    "gn:country_code":"IN",
    "gn:dem":234,
    "gn:feature_class":"P",
    "gn:feature_code":"PPL",
    "gn:name":"Far\u012bdpur",
    "gn:population":0,
    "gn:timezone":"Asia/Kolkata",
    "iso:country":"IN",
    "ks:ks_alt_nam":"Far\u012bdpur",
    "ks:ks_name":"Faridpur",
    "ks:ks_pop":2237,
    "ks:ks_type":"VILLAGE",
    "ks:ks_uagg_main":0,
    "name:ara_x_preferred":[
        "\u0641\u0631\u064a\u062f\u0628\u0648\u0631"
    ],
    "name:ben_bn_x_preferred":[
        "\u09ab\u09b0\u09bf\u09a6\u09aa\u09c1\u09b0"
    ],
    "name:ben_in_x_preferred":[
        "\u09ab\u09b0\u09bf\u09a6\u09aa\u09c1\u09b0"
    ],
    "name:bpy_x_preferred":[
        "\u09ab\u09b0\u09bf\u09a6\u09aa\u09c1\u09b0"
    ],
    "name:ceb_x_preferred":[
        "Faridpur"
    ],
    "name:eng_x_preferred":[
        "Faridpur"
    ],
    "name:eng_x_variant":[
        "Far\u012bdpur"
    ],
    "name:guj_x_preferred":[
        "\u0aab\u0ab0\u0abf\u0aa6\u0aaa\u0ac1\u0ab0"
    ],
    "name:hin_x_preferred":[
        "\u092b\u0930\u0940\u0926\u092a\u0941\u0930"
    ],
    "name:ita_x_preferred":[
        "Faridpur"
    ],
    "name:kan_x_preferred":[
        "\u0cab\u0cb0\u0cc0\u0ca6\u0ccd"
    ],
    "name:mal_x_preferred":[
        "\u0d2b\u0d30\u0d40\u0d26\u0d4d"
    ],
    "name:mar_x_preferred":[
        "\u092b\u0930\u0940\u0926\u092a\u0941\u0930"
    ],
    "name:nld_x_preferred":[
        "Faridpur"
    ],
    "name:pan_x_preferred":[
        "\u0a2b\u0a30\u0a40\u0a26\u0a2a\u0a41\u0a30"
    ],
    "name:pol_x_preferred":[
        "Faridpur"
    ],
    "name:rus_x_preferred":[
        "\u0424\u0430\u0440\u0438\u0434\u043f\u0443\u0440"
    ],
    "name:swe_x_preferred":[
        "Faridpur"
    ],
    "name:tam_x_preferred":[
        "\u0b83\u0baa\u0bb0\u0bc0\u0ba4\u0bcd\u0baa\u0bc2\u0bb0\u0bcd"
    ],
    "name:tel_x_preferred":[
        "\u0c2b\u0c30\u0c40\u0c26\u0c4d"
    ],
    "name:urd_x_preferred":[
        "\u0641\u0631\u06cc\u062f \u067e\u0648\u0631"
    ],
    "wof:name":"Faridpur",
    "wof:placetype":"locality",
    "wof:population":2237
},
  "geometry": {"coordinates":[76.95410200000001,29.434507],"type":"Point"}
}