{
  "type": "Feature",
  "properties": {
    "iso:country":"IN",
    "ks:ks_name":"Lagabusi",
    "ks:ks_pop":114,
    "ks:ks_type":"HABITATION",
    "name:eng_x_preferred":[
        "Lagabusi"
    ],
    "wof:name":"Lagabusi",
    "wof:placetype":"locality",
    "wof:population":114
},
  "geometry": {"coordinates":[82.537291,18.218976],"type":"Point"}
}