{
  "type": "Feature",
  "properties": {
    "gn:admin1_code":"2.0",
    "gn:admin2_code":"554.0",
    "gn:asciiname":"Kodiganipalli",
    "gn:country_code":"IN",
    "gn:dem":816,
    "gn:feature_class":"P",
    "gn:feature_code":"PPL",
    "gn:name":"Kodig\u0101nipalli",
    "gn:population":0,
    "gn:timezone":"Asia/Kolkata",
    "iso:country":"IN",
    "wof:name":"Kodiganipalli",
    "wof:placetype":"locality"
},
  "geometry": {"coordinates":[78.25331,12.78848],"type":"Point"}
}