{
  "type": "Feature",
  "properties": {
    "iso:country":"IN",
    "ks:ks_name":"Parghat No 2",
    "ks:ks_pop":1056,
    "ks:ks_type":"VILLAGE",
    "ks:ks_uagg_main":0,
    "name:eng_x_preferred":[
        "Parghat No 2"
    ],
    "wof:name":"Parghat No 2",
    "wof:placetype":"neighbourhood",
    "wof:population":1056
},
  "geometry": {"coordinates":[93.855986,26.209816],"type":"Point"}
}