{
  "type": "Feature",
  "properties": {
    "gn:admin1_code":"23",
    "gn:admin2_code":"36.0",
    "gn:asciiname":"Fatehgarh",
    "gn:country_code":"IN",
    "gn:dem":242,
    "gn:feature_class":"P",
    "gn:feature_code":"PPL",
    "gn:name":"Fatehgarh",
    "gn:population":0,
    "gn:timezone":"Asia/Kolkata",
    "iso:country":"IN",
    "wof:name":"Fatehgarh",
    "wof:placetype":"locality"
},
  "geometry": {"coordinates":[75.82512,31.23725],"type":"Point"}
}