{
  "type": "Feature",
  "properties": {
    "iso:country":"IN",
    "ks:ks_name":"Beguniamula",
    "ks:ks_pop":285,
    "ks:ks_type":"VILLAGE",
    "name:eng_x_preferred":[
        "Beguniamula"
    ],
    "wof:name":"Beguniamula",
    "wof:placetype":"locality",
    "wof:population":285
},
  "geometry": {"coordinates":[85.365785,20.221198],"type":"Point"}
}