{
  "type": "Feature",
  "properties": {
    "gn:admin1_code":"34.0",
    "gn:admin2_code":"226.0",
    "gn:asciiname":"Tajpur",
    "gn:country_code":"IN",
    "gn:dem":52,
    "gn:feature_class":"P",
    "gn:feature_code":"PPL",
    "gn:name":"T\u0101jpur",
    "gn:population":0,
    "gn:timezone":"Asia/Kolkata",
    "iso:country":"IN",
    "name:urd_x_preferred":[
        "\u062a\u0627\u062c\u067e\u0648\u0631"
    ],
    "wof:name":"Tajpur",
    "wof:placetype":"locality"
},
  "geometry": {"coordinates":[86.57571999999998,25.1051],"type":"Point"}
}