{
  "type": "Feature",
  "properties": {
    "iso:country":"IN",
    "ks:ks_name":"Kukkar",
    "ks:ks_pop":319,
    "ks:ks_type":"VILLAGE",
    "name:eng_x_preferred":[
        "Kukkar"
    ],
    "wof:name":"Kukkar",
    "wof:placetype":"locality",
    "wof:population":319
},
  "geometry": {"coordinates":[75.21455400000001,32.09516],"type":"Point"}
}