{
  "type": "Feature",
  "properties": {
    "gn:admin1_code":"36",
    "gn:admin2_code":"173.0",
    "gn:asciiname":"Paharpur",
    "gn:country_code":"IN",
    "gn:dem":106,
    "gn:feature_class":"P",
    "gn:feature_code":"PPL",
    "gn:name":"Pah\u0101rpur",
    "gn:population":0,
    "gn:timezone":"Asia/Kolkata",
    "iso:country":"IN",
    "name:ben_x_preferred":[
        "\u09aa\u09be\u09b9\u09be\u09a1\u09bc\u09aa\u09c1\u09b0"
    ],
    "name:ceb_x_preferred":[
        "Paharpur"
    ],
    "name:nld_x_preferred":[
        "Paharpur"
    ],
    "name:und_x_variant":[
        "Pah\u0101rpur",
        "Banohi"
    ],
    "wof:name":"Paharpur",
    "wof:placetype":"locality"
},
  "geometry": {"coordinates":[81.56612,25.70453],"type":"Point"}
}