{
  "type": "Feature",
  "properties": {
    "iso:country":"IN",
    "ks:ks_name":"Halasinkoppa",
    "ks:ks_pop":85,
    "ks:ks_type":"VILLAGE",
    "name:eng_x_preferred":[
        "Halasinkoppa"
    ],
    "wof:name":"Halasinkoppa",
    "wof:placetype":"locality",
    "wof:population":85
},
  "geometry": {"coordinates":[74.852569,14.836016],"type":"Point"}
}