{
  "type": "Feature",
  "properties": {
    "gn:admin1_code":"26",
    "gn:admin2_code":"292.0",
    "gn:asciiname":"Muktasinghpara",
    "gn:country_code":"IN",
    "gn:dem":79,
    "gn:feature_class":"P",
    "gn:feature_code":"PPL",
    "gn:name":"Muktasinghp\u0101ra",
    "gn:population":0,
    "gn:timezone":"Asia/Kolkata",
    "iso:country":"IN",
    "wof:name":"Muktasinghpara",
    "wof:placetype":"locality"
},
  "geometry": {"coordinates":[92.15846000000001,23.96237],"type":"Point"}
}