{
  "type": "Feature",
  "properties": {
    "iso:country":"IN",
    "ks:ks_alt_nam":"Kothe Vire wala",
    "ks:ks_name":"Kothe Vire Wala",
    "ks:ks_pop":907,
    "ks:ks_type":"HABITATION",
    "name:eng_x_preferred":[
        "Kothe Vire Wala"
    ],
    "wof:name":"Kothe Vire Wala",
    "wof:placetype":"locality",
    "wof:population":907
},
  "geometry": {"coordinates":[74.75988599999999,30.63608],"type":"Point"}
}