{
  "type": "Feature",
  "properties": {
    "gn:admin1_code":"19.0",
    "gn:admin2_code":"574.0",
    "gn:asciiname":"Parasanahalli",
    "gn:country_code":"IN",
    "gn:dem":915,
    "gn:feature_class":"P",
    "gn:feature_code":"PPL",
    "gn:name":"Parasanahalli",
    "gn:population":0,
    "gn:timezone":"Asia/Kolkata",
    "iso:country":"IN",
    "wof:name":"Parasanahalli",
    "wof:placetype":"locality"
},
  "geometry": {"coordinates":[76.23841999999998,12.92174],"type":"Point"}
}