{
  "type": "Feature",
  "properties": {
    "iso:country":"IN",
    "ks:ks_name":"Udapuvvudy",
    "ks:ks_pop":768,
    "ks:ks_type":"HABITATION",
    "name:eng_x_preferred":[
        "Udapuvvudy"
    ],
    "wof:name":"Udapuvvudy",
    "wof:placetype":"locality",
    "wof:population":768
},
  "geometry": {"coordinates":[76.725298,9.439555],"type":"Point"}
}