{
  "type": "Feature",
  "properties": {
    "gn:admin1_code":"36",
    "gn:admin2_code":"185.0",
    "gn:asciiname":"Narainpur Kunwar",
    "gn:country_code":"IN",
    "gn:dem":98,
    "gn:feature_class":"P",
    "gn:feature_code":"PPL",
    "gn:name":"Nar\u0101inpur Kunwar",
    "gn:population":0,
    "gn:timezone":"Asia/Kolkata",
    "iso:country":"IN",
    "wof:name":"Narainpur Kunwar",
    "wof:placetype":"locality"
},
  "geometry": {"coordinates":[82.47207,26.8225],"type":"Point"}
}