{
  "type": "Feature",
  "properties": {
    "gn:admin1_code":"24.0",
    "gn:admin2_code":"102",
    "gn:asciiname":"Hardesar",
    "gn:country_code":"IN",
    "gn:dem":223,
    "gn:feature_class":"P",
    "gn:feature_code":"PPL",
    "gn:name":"Hardesar",
    "gn:population":0,
    "gn:timezone":"Asia/Kolkata",
    "iso:country":"IN",
    "wof:name":"Hardesar",
    "wof:placetype":"locality"
},
  "geometry": {"coordinates":[74.37739000000001,28.65303],"type":"Point"}
}