{
  "type": "Feature",
  "properties": {
    "gn:admin1_code":"24.0",
    "gn:admin2_code":"102",
    "gn:asciiname":"Hardesar",
    "gn:country_code":"IN",
    "gn:dem":223,
    "gn:feature_class":"P",
    "gn:feature_code":"PPL",
    "gn:name":"Hardesar",
    "gn:population":0,
    "gn:timezone":"Asia/Kolkata",
    "iso:country":"IN",
    "ks:ks_name":"Hardesar",
    "ks:ks_pop":1953,
    "ks:ks_type":"VILLAGE",
    "name:eng_x_preferred":[
        "Hardesar"
    ],
    "wof:name":"Hardesar",
    "wof:placetype":"locality",
    "wof:population":1953
},
  "geometry": {"coordinates":[74.377394,28.654808],"type":"Point"}
}