{
  "type": "Feature",
  "properties": {
    "gn:admin1_code":"16",
    "gn:admin2_code":"506.0",
    "gn:asciiname":"Chandori",
    "gn:country_code":"IN",
    "gn:dem":264,
    "gn:feature_class":"P",
    "gn:feature_code":"PPL",
    "gn:name":"Ch\u0101ndori",
    "gn:population":0,
    "gn:timezone":"Asia/Kolkata",
    "iso:country":"IN",
    "wof:name":"Chandori",
    "wof:placetype":"locality"
},
  "geometry": {"coordinates":[79.70198000000001,21.10345],"type":"Point"}
}