{
  "type": "Feature",
  "properties": {
    "iso:country":"IN",
    "ks:ks_name":"Deuli",
    "ks:ks_pop":2105,
    "ks:ks_type":"VILLAGE",
    "ks:ks_uagg_main":0,
    "name:eng_x_preferred":[
        "Deuli"
    ],
    "wof:name":"Deuli",
    "wof:placetype":"neighbourhood",
    "wof:population":2105
},
  "geometry": {"coordinates":[87.6309,21.688456],"type":"Point"}
}