{
  "type": "Feature",
  "properties": {
    "iso:country":"IN",
    "ks:ks_name":"Kumbhycha Dand",
    "ks:ks_pop":150,
    "ks:ks_type":"HABITATION",
    "name:eng_x_preferred":[
        "Kumbhycha Dand"
    ],
    "wof:name":"Kumbhycha Dand",
    "wof:placetype":"locality",
    "wof:population":150
},
  "geometry": {"coordinates":[73.64231100000001,17.045672],"type":"Point"}
}