{
  "type": "Feature",
  "properties": {
    "iso:country":"IN",
    "ks:ks_name":"Khanapur",
    "ks:ks_pop":85,
    "ks:ks_type":"HABITATION",
    "name:eng_x_preferred":[
        "Khanapur"
    ],
    "wof:name":"Khanapur",
    "wof:placetype":"locality",
    "wof:population":85
},
  "geometry": {"coordinates":[77.862999,20.731003],"type":"Point"}
}