{
  "type": "Feature",
  "properties": {
    "iso:country":"IN",
    "ks:ks_name":"Chhatra Khanda",
    "ks:ks_pop":645,
    "ks:ks_type":"VILLAGE",
    "name:eng_x_preferred":[
        "Chhatra Khanda"
    ],
    "wof:name":"Chhatra Khanda",
    "wof:placetype":"locality",
    "wof:population":645
},
  "geometry": {"coordinates":[87.73074800000001,23.029833],"type":"Point"}
}