{
  "type": "Feature",
  "properties": {
    "gn:admin1_code":"38.0",
    "gn:admin2_code":"353.0",
    "gn:asciiname":"Simaljori",
    "gn:country_code":"IN",
    "gn:dem":62,
    "gn:feature_class":"P",
    "gn:feature_code":"PPL",
    "gn:name":"Simaljori",
    "gn:population":0,
    "gn:timezone":"Asia/Kolkata",
    "iso:country":"IN",
    "ks:ks_name":"Simlajori",
    "ks:ks_pop":436,
    "ks:ks_type":"VILLAGE",
    "name:eng_x_preferred":[
        "Simlajori"
    ],
    "name:eng_x_variant":[
        "Simaljori"
    ],
    "wof:name":"Simlajori",
    "wof:placetype":"locality",
    "wof:population":436
},
  "geometry": {"coordinates":[87.67946499999999,24.70972],"type":"Point"}
}