{
  "type": "Feature",
  "properties": {
    "iso:country":"IN",
    "ks:ks_name":"Harijanwadi",
    "ks:ks_pop":22,
    "ks:ks_type":"HABITATION",
    "name:eng_x_preferred":[
        "Harijanwadi"
    ],
    "wof:name":"Harijanwadi",
    "wof:placetype":"locality",
    "wof:population":22
},
  "geometry": {"coordinates":[73.73282,15.756958],"type":"Point"}
}