{
  "type": "Feature",
  "properties": {
    "gn:admin1_code":"25.0",
    "gn:admin2_code":"608.0",
    "gn:asciiname":"Sivadanur",
    "gn:country_code":"IN",
    "gn:dem":263,
    "gn:feature_class":"P",
    "gn:feature_code":"PPL",
    "gn:name":"Sivadan\u016br",
    "gn:population":0,
    "gn:timezone":"Asia/Kolkata",
    "iso:country":"IN",
    "ks:ks_name":"Sevadanur",
    "ks:ks_pop":1017,
    "ks:ks_type":"HABITATION",
    "ks:ks_uagg_main":0,
    "name:eng_x_preferred":[
        "Sevadanur"
    ],
    "wof:name":"Sevadanur",
    "wof:placetype":"neighbourhood",
    "wof:population":1017
},
  "geometry": {"coordinates":[77.869595,11.676333],"type":"Point"}
}