{
  "type": "Feature",
  "properties": {
    "iso:country":"IN",
    "ks:ks_name":"Poojarikoppa",
    "ks:ks_pop":66,
    "ks:ks_type":"HABITATION",
    "name:eng_x_preferred":[
        "Poojarikoppa"
    ],
    "wof:name":"Poojarikoppa",
    "wof:placetype":"locality",
    "wof:population":66
},
  "geometry": {"coordinates":[74.822934,14.422845],"type":"Point"}
}