{
  "type": "Feature",
  "properties": {
    "gn:admin1_code":"24.0",
    "gn:admin2_code":"125.0",
    "gn:asciiname":"Balachuna",
    "gn:country_code":"IN",
    "gn:dem":407,
    "gn:feature_class":"P",
    "gn:feature_code":"PPL",
    "gn:name":"B\u0101l\u0101ch\u016bna",
    "gn:population":0,
    "gn:timezone":"Asia/Kolkata",
    "iso:country":"IN",
    "ks:ks_name":"Bala Chuna",
    "ks:ks_pop":631,
    "ks:ks_type":"VILLAGE",
    "name:eng_x_preferred":[
        "Bala Chuna"
    ],
    "name:eng_x_variant":[
        "Balachuna"
    ],
    "wof:name":"Bala Chuna",
    "wof:placetype":"locality",
    "wof:population":631
},
  "geometry": {"coordinates":[74.481031,23.274106],"type":"Point"}
}