{
  "type": "Feature",
  "properties": {
    "gn:admin1_code":"12.0",
    "gn:admin2_code":"7.0",
    "gn:asciiname":"Dhanore di Ban",
    "gn:country_code":"IN",
    "gn:dem":380,
    "gn:feature_class":"P",
    "gn:feature_code":"PPL",
    "gn:name":"Dhanore di Ban",
    "gn:population":0,
    "gn:timezone":"Asia/Kolkata",
    "iso:country":"IN",
    "wof:name":"Dhanore di Ban",
    "wof:placetype":"locality"
},
  "geometry": {"coordinates":[75.61716,32.39202],"type":"Point"}
}