{
  "type": "Feature",
  "properties": {
    "iso:country":"IN",
    "ks:ks_name":"Kalahandi",
    "ks:ks_pop":830,
    "ks:ks_type":"HABITATION",
    "ks:ks_uagg_main":0,
    "name:eng_x_preferred":[
        "Kalahandi"
    ],
    "wof:name":"Kalahandi",
    "wof:placetype":"neighbourhood",
    "wof:population":830
},
  "geometry": {"coordinates":[93.24429000000001,26.770222],"type":"Point"}
}