{
  "type": "Feature",
  "properties": {
    "gn:admin1_code":"37",
    "gn:admin2_code":"404.0",
    "gn:asciiname":"Karranawapara",
    "gn:country_code":"IN",
    "gn:dem":349,
    "gn:feature_class":"P",
    "gn:feature_code":"PPL",
    "gn:name":"Karr\u0101naw\u0101p\u0101ra",
    "gn:population":0,
    "gn:timezone":"Asia/Kolkata",
    "iso:country":"IN",
    "ks:ks_name":"Karranawapara",
    "ks:ks_pop":979,
    "ks:ks_type":"HABITATION",
    "name:eng_x_preferred":[
        "Karranawapara"
    ],
    "wof:name":"Karranawapara",
    "wof:placetype":"locality",
    "wof:population":979
},
  "geometry": {"coordinates":[82.18074300000001,22.435736],"type":"Point"}
}