{
  "type": "Feature",
  "properties": {
    "gn:admin1_code":"16.0",
    "gn:admin2_code":"516",
    "gn:asciiname":"Brahmangaon",
    "gn:country_code":"IN",
    "gn:dem":510,
    "gn:feature_class":"P",
    "gn:feature_code":"PPL",
    "gn:name":"Br\u0101hmangaon",
    "gn:population":0,
    "gn:timezone":"Asia/Kolkata",
    "iso:country":"IN",
    "wof:name":"Brahmangaon",
    "wof:placetype":"locality"
},
  "geometry": {"coordinates":[74.29469,20.55517],"type":"Point"}
}