{
  "type": "Feature",
  "properties": {
    "iso:country":"IN",
    "ks:ks_alt_nam":"BHUIATAND",
    "ks:ks_name":"Bhuiatand",
    "ks:ks_pop":338,
    "ks:ks_type":"HABITATION",
    "name:eng_x_preferred":[
        "Bhuiatand"
    ],
    "wof:name":"Bhuiatand",
    "wof:placetype":"locality",
    "wof:population":338
},
  "geometry": {"coordinates":[85.471952,24.914113],"type":"Point"}
}