{
  "type": "Feature",
  "properties": {
    "iso:country":"IN",
    "ks:ks_name":"Seeranadoddi",
    "ks:ks_pop":430,
    "ks:ks_type":"HABITATION",
    "name:eng_x_preferred":[
        "Seeranadoddi"
    ],
    "wof:name":"Seeranadoddi",
    "wof:placetype":"locality",
    "wof:population":430
},
  "geometry": {"coordinates":[77.07579800000001,12.573231],"type":"Point"}
}