{
  "type": "Feature",
  "properties": {
    "iso:country":"IN",
    "ks:ks_name":"Simulari",
    "ks:ks_pop":0,
    "ks:ks_type":"VILLAGE",
    "name:eng_x_preferred":[
        "Simulari"
    ],
    "wof:name":"Simulari",
    "wof:placetype":"locality",
    "wof:population":0
},
  "geometry": {"coordinates":[87.552369,23.178452],"type":"Point"}
}