{
  "type": "Feature",
  "properties": {
    "iso:country":"IN",
    "ks:ks_name":"Shelwadi",
    "ks:ks_pop":117,
    "ks:ks_type":"HABITATION",
    "name:eng_x_preferred":[
        "Shelwadi"
    ],
    "wof:name":"Shelwadi",
    "wof:placetype":"locality",
    "wof:population":117
},
  "geometry": {"coordinates":[73.646845,16.216601],"type":"Point"}
}