{
  "type": "Feature",
  "properties": {
    "gn:admin1_code":"12.0",
    "gn:admin2_code":"18.0",
    "gn:asciiname":"Dhari",
    "gn:country_code":"IN",
    "gn:dem":2710,
    "gn:feature_class":"P",
    "gn:feature_code":"PPL",
    "gn:name":"Dh\u0101ri",
    "gn:population":0,
    "gn:timezone":"Asia/Kolkata",
    "iso:country":"IN",
    "name:ceb_x_preferred":[
        "Dhari"
    ],
    "name:swe_x_preferred":[
        "Dhari"
    ],
    "wof:name":"Dhari",
    "wof:placetype":"locality"
},
  "geometry": {"coordinates":[75.67655000000001,33.46182],"type":"Point"}
}