{
  "type": "Feature",
  "properties": {
    "gn:admin1_code":"19.0",
    "gn:admin2_code":"562.0",
    "gn:asciiname":"Palikop",
    "gn:country_code":"IN",
    "gn:dem":635,
    "gn:feature_class":"P",
    "gn:feature_code":"PPL",
    "gn:name":"P\u0101likop",
    "gn:population":0,
    "gn:timezone":"Asia/Kolkata",
    "iso:country":"IN",
    "name:nor_x_preferred":[
        "Palikop"
    ],
    "wof:name":"Palikop",
    "wof:placetype":"locality"
},
  "geometry": {"coordinates":[75.12439999999999,15.18245],"type":"Point"}
}