{
  "type": "Feature",
  "properties": {
    "gn:admin1_code":"2.0",
    "gn:admin2_code":"543.0",
    "gn:asciiname":"Sambara",
    "gn:country_code":"IN",
    "gn:dem":156,
    "gn:feature_class":"P",
    "gn:feature_code":"PPL",
    "gn:name":"Sambara",
    "gn:population":0,
    "gn:timezone":"Asia/Kolkata",
    "iso:country":"IN",
    "name:jpn_x_preferred":[
        "\u30b7\u30e3\u30e0\u30d0\u30e9"
    ],
    "wof:name":"Sambara",
    "wof:placetype":"locality"
},
  "geometry": {"coordinates":[83.21195999999998,18.65429],"type":"Point"}
}