{
  "type": "Feature",
  "properties": {
    "iso:country":"IN",
    "ks:ks_alt_nam":"KARANPUR",
    "ks:ks_name":"Karanpur",
    "ks:ks_pop":1500,
    "ks:ks_type":"HABITATION",
    "name:eng_x_preferred":[
        "Karanpur"
    ],
    "wof:name":"Karanpur",
    "wof:placetype":"locality",
    "wof:population":1500
},
  "geometry": {"coordinates":[81.920168,25.945962],"type":"Point"}
}