{
  "type": "Feature",
  "properties": {
    "gn:admin1_code":"36.0",
    "gn:admin2_code":"138.0",
    "gn:asciiname":"Khiwai",
    "gn:country_code":"IN",
    "gn:dem":229,
    "gn:feature_class":"P",
    "gn:feature_code":"PPL",
    "gn:name":"Khiwai",
    "gn:population":0,
    "gn:timezone":"Asia/Kolkata",
    "iso:country":"IN",
    "wof:name":"Khiwai",
    "wof:placetype":"locality"
},
  "geometry": {"coordinates":[77.46101999999998,29.09965],"type":"Point"}
}