{
  "type": "Feature",
  "properties": {
    "iso:country":"IN",
    "ks:ks_name":"Manghatapurva",
    "ks:ks_pop":50,
    "ks:ks_type":"HABITATION",
    "ks:ks_uagg_main":0,
    "name:eng_x_preferred":[
        "Manghatapurva"
    ],
    "wof:name":"Manghatapurva",
    "wof:placetype":"neighbourhood",
    "wof:population":50
},
  "geometry": {"coordinates":[80.97689699999999,27.214155],"type":"Point"}
}