{
  "type": "Feature",
  "properties": {
    "iso:country":"IN",
    "ks:ks_name":"Balipos",
    "ks:ks_pop":6,
    "ks:ks_type":"VILLAGE",
    "ks:ks_uagg_main":0,
    "name:eng_x_preferred":[
        "Balipos"
    ],
    "wof:name":"Balipos",
    "wof:placetype":"neighbourhood",
    "wof:population":6
},
  "geometry": {"coordinates":[85.491269,22.586807],"type":"Point"}
}