{
  "type": "Feature",
  "properties": {
    "iso:country":"IN",
    "ks:ks_name":"Devarakoppa",
    "ks:ks_pop":270,
    "ks:ks_type":"HABITATION",
    "name:eng_x_preferred":[
        "Devarakoppa"
    ],
    "wof:name":"Devarakoppa",
    "wof:placetype":"locality",
    "wof:population":270
},
  "geometry": {"coordinates":[74.801727,14.649545],"type":"Point"}
}