{
  "type": "Feature",
  "properties": {
    "iso:country":"IN",
    "ks:ks_name":"Anantapur",
    "ks:ks_pop":927,
    "ks:ks_type":"VILLAGE",
    "ks:ks_uagg_main":0,
    "name:eng_x_preferred":[
        "Anantapur"
    ],
    "wof:name":"Anantapur",
    "wof:placetype":"neighbourhood",
    "wof:population":927
},
  "geometry": {"coordinates":[85.908807,20.348661],"type":"Point"}
}