{
  "type": "Feature",
  "properties": {
    "iso:country":"IN",
    "ks:ks_name":"Kumar Chuk",
    "ks:ks_pop":927,
    "ks:ks_type":"HABITATION",
    "name:eng_x_preferred":[
        "Kumar Chuk"
    ],
    "wof:name":"Kumar Chuk",
    "wof:placetype":"locality",
    "wof:population":927
},
  "geometry": {"coordinates":[95.07354599999999,27.022945],"type":"Point"}
}