{
  "type": "Feature",
  "properties": {
    "iso:country":"IN",
    "ks:ks_name":"Fatepur",
    "ks:ks_pop":211,
    "ks:ks_type":"VILLAGE",
    "name:eng_x_preferred":[
        "Fatepur"
    ],
    "wof:name":"Fatepur",
    "wof:placetype":"locality",
    "wof:population":211
},
  "geometry": {"coordinates":[87.326402,22.015506],"type":"Point"}
}