{
  "type": "Feature",
  "properties": {
    "iso:country":"IN",
    "ks:ks_name":"Pome Naik Thanda",
    "ks:ks_pop":194,
    "ks:ks_type":"HABITATION",
    "ks:ks_uagg_main":0,
    "name:eng_x_preferred":[
        "Pome Naik Thanda"
    ],
    "wof:name":"Pome Naik Thanda",
    "wof:placetype":"neighbourhood",
    "wof:population":194
},
  "geometry": {"coordinates":[78.187128,13.83693],"type":"Point"}
}