{
  "type": "Feature",
  "properties": {
    "gn:admin1_code":"25.0",
    "gn:admin2_code":"619.0",
    "gn:asciiname":"Pusalangudi",
    "gn:country_code":"IN",
    "gn:dem":11,
    "gn:feature_class":"P",
    "gn:feature_code":"PPL",
    "gn:name":"P\u016bsal\u0101ngudi",
    "gn:population":0,
    "gn:timezone":"Asia/Kolkata",
    "iso:country":"IN",
    "ks:ks_name":"Palangudi",
    "ks:ks_pop":252,
    "ks:ks_type":"HABITATION",
    "name:eng_x_preferred":[
        "Palangudi"
    ],
    "name:eng_x_variant":[
        "Pusalangudi"
    ],
    "wof:name":"Palangudi",
    "wof:placetype":"locality",
    "wof:population":252
},
  "geometry": {"coordinates":[79.638361,10.718299],"type":"Point"}
}