{
  "type": "Feature",
  "properties": {
    "iso:country":"IN",
    "ks:ks_name":"Madkatta",
    "ks:ks_pop":159,
    "ks:ks_type":"HABITATION",
    "name:eng_x_preferred":[
        "Madkatta"
    ],
    "wof:name":"Madkatta",
    "wof:placetype":"locality",
    "wof:population":159
},
  "geometry": {"coordinates":[81.00177600000001,20.093697],"type":"Point"}
}