{
  "type": "Feature",
  "properties": {
    "iso:country":"IN",
    "ks:ks_alt_nam":"UDADAHA TOLA",
    "ks:ks_name":"Udadaha Tola",
    "ks:ks_pop":169,
    "ks:ks_type":"HABITATION",
    "name:eng_x_preferred":[
        "Udadaha Tola"
    ],
    "wof:name":"Udadaha Tola",
    "wof:placetype":"locality",
    "wof:population":169
},
  "geometry": {"coordinates":[83.68666,24.275005],"type":"Point"}
}