{
  "type": "Feature",
  "properties": {
    "gn:admin1_code":"11.0",
    "gn:admin2_code":"33.0",
    "gn:asciiname":"Jalwana",
    "gn:country_code":"IN",
    "gn:dem":2319,
    "gn:feature_class":"P",
    "gn:feature_code":"PPL",
    "gn:name":"Jalwana",
    "gn:population":0,
    "gn:timezone":"Asia/Kolkata",
    "iso:country":"IN",
    "wof:name":"Jalwana",
    "wof:placetype":"locality"
},
  "geometry": {"coordinates":[77.46786,30.92209],"type":"Point"}
}