{
  "type": "Feature",
  "properties": {
    "iso:country":"IN",
    "ks:ks_name":"Khoripada",
    "ks:ks_pop":37,
    "ks:ks_type":"HABITATION",
    "name:eng_x_preferred":[
        "Khoripada"
    ],
    "wof:name":"Khoripada",
    "wof:placetype":"locality",
    "wof:population":37
},
  "geometry": {"coordinates":[72.96785199999999,20.048087],"type":"Point"}
}