{
  "type": "Feature",
  "properties": {
    "gn:admin1_code":"34.0",
    "gn:admin2_code":"230.0",
    "gn:asciiname":"Jafarpur",
    "gn:country_code":"IN",
    "gn:dem":56,
    "gn:feature_class":"P",
    "gn:feature_code":"PPL",
    "gn:name":"Jafarpur",
    "gn:population":0,
    "gn:timezone":"Asia/Kolkata",
    "iso:country":"IN",
    "name:ben_x_preferred":[
        "\u099c\u09be\u09ab\u09b0\u09aa\u09c1\u09b0"
    ],
    "name:bpy_x_preferred":[
        "\u099c\u09be\u09ab\u09b0\u09aa\u09c1\u09b0"
    ],
    "name:ceb_x_preferred":[
        "J\u0101farpur"
    ],
    "name:ita_x_preferred":[
        "Jafarpur"
    ],
    "name:msa_x_preferred":[
        "Jafarpur"
    ],
    "name:new_x_preferred":[
        "\u091c\u092b\u0930\u092a\u0941\u0930"
    ],
    "name:nld_x_preferred":[
        "Jafarpur"
    ],
    "name:por_x_preferred":[
        "Jafarpur"
    ],
    "name:swe_x_preferred":[
        "J\u0101farpur"
    ],
    "name:urd_x_preferred":[
        "\u062c\u0641\u0631\u067e\u0648\u0631"
    ],
    "name:vie_x_preferred":[
        "Jafarpur"
    ],
    "name:zho_x_preferred":[
        "\u8d3e\u6cd5\u5c14\u666e\u5c14"
    ],
    "wof:name":"Jafarpur",
    "wof:placetype":"locality"
},
  "geometry": {"coordinates":[85.03867,25.6855],"type":"Point"}
}