{
  "type": "Feature",
  "properties": {
    "gn:admin1_code":"16.0",
    "gn:admin2_code":"515",
    "gn:asciiname":"Ganori",
    "gn:country_code":"IN",
    "gn:dem":684,
    "gn:feature_class":"P",
    "gn:feature_code":"PPL",
    "gn:name":"Ganori",
    "gn:population":0,
    "gn:timezone":"Asia/Kolkata",
    "iso:country":"IN",
    "name:fas_x_preferred":[
        "\u06af\u0646\u0648\u0631\u06cc"
    ],
    "name:urd_x_preferred":[
        "\u06af\u0646\u0648\u0631\u06cc"
    ],
    "wof:name":"Ganori",
    "wof:placetype":"locality"
},
  "geometry": {"coordinates":[75.34563,20.04472],"type":"Point"}
}