{
  "type": "Feature",
  "properties": {
    "iso:country":"IN",
    "ks:ks_name":"Kotavoru",
    "ks:ks_pop":55,
    "ks:ks_type":"HABITATION",
    "name:eng_x_preferred":[
        "Kotavoru"
    ],
    "wof:name":"Kotavoru",
    "wof:placetype":"locality",
    "wof:population":55
},
  "geometry": {"coordinates":[84.47787700000001,18.797877],"type":"Point"}
}