{
  "type": "Feature",
  "properties": {
    "iso:country":"IN",
    "ks:ks_name":"Kunti Dadargaon",
    "ks:ks_pop":922,
    "ks:ks_type":"VILLAGE",
    "name:eng_x_preferred":[
        "Kunti Dadargaon"
    ],
    "wof:name":"Kunti Dadargaon",
    "wof:placetype":"locality",
    "wof:population":922
},
  "geometry": {"coordinates":[80.841065,22.682644],"type":"Point"}
}