{
  "type": "Feature",
  "properties": {
    "gn:admin1_code":"36.0",
    "gn:admin2_code":"158.0",
    "gn:asciiname":"Shahzadpur",
    "gn:country_code":"IN",
    "gn:dem":118,
    "gn:feature_class":"P",
    "gn:feature_code":"PPL",
    "gn:name":"Sh\u0101hz\u0101dpur",
    "gn:population":0,
    "gn:timezone":"Asia/Kolkata",
    "iso:country":"IN",
    "name:und_x_variant":[
        "Sh\u0101hz\u0101dpur",
        "N\u0101har\u0101pur"
    ],
    "wof:name":"Shahzadpur",
    "wof:placetype":"locality"
},
  "geometry": {"coordinates":[81.05922,26.24612],"type":"Point"}
}