{
  "type": "Feature",
  "properties": {
    "iso:country":"IN",
    "ks:ks_name":"2 Rm(465 Rd)",
    "ks:ks_pop":841,
    "ks:ks_type":"HABITATION",
    "name:eng_x_preferred":[
        "2 Rm(465 Rd)"
    ],
    "wof:name":"2 Rm(465 Rd)",
    "wof:placetype":"locality",
    "wof:population":841
},
  "geometry": {"coordinates":[73.38866400000001,28.875597],"type":"Point"}
}