{
  "type": "Feature",
  "properties": {
    "iso:country":"IN",
    "ks:ks_name":"Sajara Hironoiyo Bharaniyo Ki Dhani",
    "ks:ks_pop":846,
    "ks:ks_type":"HABITATION",
    "name:eng_x_preferred":[
        "Sajara Hironoiyo Bharaniyo Ki Dhani"
    ],
    "wof:name":"Sajara Hironoiyo Bharaniyo Ki Dhani",
    "wof:placetype":"locality",
    "wof:population":846
},
  "geometry": {"coordinates":[72.010589,25.507675],"type":"Point"}
}