{
  "type": "Feature",
  "properties": {
    "gn:admin1_code":"19.0",
    "gn:admin2_code":"570.0",
    "gn:asciiname":"Hosatota",
    "gn:country_code":"IN",
    "gn:dem":757,
    "gn:feature_class":"P",
    "gn:feature_code":"PPL",
    "gn:name":"Hosatota",
    "gn:population":0,
    "gn:timezone":"Asia/Kolkata",
    "iso:country":"IN",
    "ks:ks_name":"Hosathotta",
    "ks:ks_pop":34,
    "ks:ks_type":"HABITATION",
    "name:eng_x_preferred":[
        "Hosathotta"
    ],
    "name:eng_x_variant":[
        "Hosatota"
    ],
    "wof:name":"Hosathotta",
    "wof:placetype":"locality",
    "wof:population":34
},
  "geometry": {"coordinates":[75.317313,13.361134],"type":"Point"}
}