{
  "type": "Feature",
  "properties": {
    "iso:country":"IN",
    "ks:ks_alt_nam":"Maraghmal mandir",
    "ks:ks_name":"Maraghmal Mandir",
    "ks:ks_pop":159,
    "ks:ks_type":"HABITATION",
    "name:eng_x_preferred":[
        "Maraghmal Mandir"
    ],
    "wof:name":"Maraghmal Mandir",
    "wof:placetype":"locality",
    "wof:population":159
},
  "geometry": {"coordinates":[73.138372,20.591928],"type":"Point"}
}