{
  "type": "Feature",
  "properties": {
    "iso:country":"IN",
    "ks:ks_name":"Nirpal Singh Dhani",
    "ks:ks_pop":35,
    "ks:ks_type":"HABITATION",
    "name:eng_x_preferred":[
        "Nirpal Singh Dhani"
    ],
    "wof:name":"Nirpal Singh Dhani",
    "wof:placetype":"locality",
    "wof:population":35
},
  "geometry": {"coordinates":[74.255752,30.337571],"type":"Point"}
}