{
  "type": "Feature",
  "properties": {
    "iso:country":"IN",
    "ks:ks_name":"Rajapur",
    "ks:ks_pop":711,
    "ks:ks_type":"VILLAGE",
    "ks:ks_uagg_main":0,
    "name:eng_x_preferred":[
        "Rajapur"
    ],
    "wof:name":"Rajapur",
    "wof:placetype":"neighbourhood",
    "wof:population":711
},
  "geometry": {"coordinates":[88.413214,23.448272],"type":"Point"}
}