{
  "type": "Feature",
  "properties": {
    "iso:country":"IN",
    "ks:ks_alt_nam":"Chetu\u0101g",
    "ks:ks_name":"Chetuag",
    "ks:ks_pop":626,
    "ks:ks_type":"VILLAGE",
    "name:eng_x_preferred":[
        "Chetuag"
    ],
    "name:eng_x_variant":[
        "Chetu\u0101g"
    ],
    "wof:name":"Chetuag",
    "wof:placetype":"locality",
    "wof:population":626
},
  "geometry": {"coordinates":[84.80752,23.844317],"type":"Point"}
}