{
  "type": "Feature",
  "properties": {
    "iso:country":"IN",
    "ks:ks_name":"Aptyache Galu",
    "ks:ks_pop":169,
    "ks:ks_type":"HABITATION",
    "name:eng_x_preferred":[
        "Aptyache Galu"
    ],
    "wof:name":"Aptyache Galu",
    "wof:placetype":"locality",
    "wof:population":169
},
  "geometry": {"coordinates":[73.874892,15.908707],"type":"Point"}
}