{
  "type": "Feature",
  "properties": {
    "gn:admin1_code":"36",
    "gn:admin2_code":"174.0",
    "gn:asciiname":"Jawai Parri",
    "gn:country_code":"IN",
    "gn:dem":110,
    "gn:feature_class":"P",
    "gn:feature_code":"PPL",
    "gn:name":"Jawai Parri",
    "gn:population":0,
    "gn:timezone":"Asia/Kolkata",
    "iso:country":"IN",
    "wof:name":"Jawai Parri",
    "wof:placetype":"neighbourhood"
},
  "geometry": {"coordinates":[81.26363000000001,25.59733],"type":"Point"}
}