{
  "type": "Feature",
  "properties": {
    "iso:country":"IN",
    "ks:ks_name":"Chellekodla",
    "ks:ks_pop":169,
    "ks:ks_type":"HABITATION",
    "name:eng_x_preferred":[
        "Chellekodla"
    ],
    "wof:name":"Chellekodla",
    "wof:placetype":"locality",
    "wof:population":169
},
  "geometry": {"coordinates":[74.535079,14.295158],"type":"Point"}
}