{
  "type": "Feature",
  "properties": {
    "iso:country":"IN",
    "ks:ks_name":"Modhalpada",
    "ks:ks_pop":580,
    "ks:ks_type":"VILLAGE",
    "name:eng_x_preferred":[
        "Modhalpada"
    ],
    "wof:name":"Modhalpada",
    "wof:placetype":"locality",
    "wof:population":580
},
  "geometry": {"coordinates":[73.49524599999999,20.409853],"type":"Point"}
}