{
  "type": "Feature",
  "properties": {
    "iso:country":"IN",
    "ks:ks_name":"Sivasankarapuram",
    "ks:ks_pop":121,
    "ks:ks_type":"HABITATION",
    "ks:ks_uagg_main":0,
    "name:eng_x_preferred":[
        "Sivasankarapuram"
    ],
    "wof:name":"Sivasankarapuram",
    "wof:placetype":"neighbourhood",
    "wof:population":121
},
  "geometry": {"coordinates":[78.749482,14.294236],"type":"Point"}
}