{
  "type": "Feature",
  "properties": {
    "gn:admin1_code":"2.0",
    "gn:admin2_code":"554.0",
    "gn:asciiname":"Duggandlagundlapalli",
    "gn:country_code":"IN",
    "gn:dem":355,
    "gn:feature_class":"P",
    "gn:feature_code":"PPL",
    "gn:name":"Duggandlagundlapalli",
    "gn:population":0,
    "gn:timezone":"Asia/Kolkata",
    "iso:country":"IN",
    "ks:ks_name":"Duggandlagundlapalle",
    "ks:ks_pop":26,
    "ks:ks_type":"HABITATION",
    "name:eng_x_preferred":[
        "Duggandlagundlapalle"
    ],
    "name:eng_x_variant":[
        "Duggandlagundlapalli"
    ],
    "wof:name":"Duggandlagundlapalle",
    "wof:placetype":"locality",
    "wof:population":26
},
  "geometry": {"coordinates":[79.039052,13.383703],"type":"Point"}
}