{
  "type": "Feature",
  "properties": {
    "gn:admin1_code":"19.0",
    "gn:admin2_code":"565.0",
    "gn:asciiname":"Chellakuriki",
    "gn:country_code":"IN",
    "gn:dem":467,
    "gn:feature_class":"P",
    "gn:feature_code":"PPL",
    "gn:name":"Chellakuriki",
    "gn:population":0,
    "gn:timezone":"Asia/Kolkata",
    "iso:country":"IN",
    "wof:name":"Chellakuriki",
    "wof:placetype":"locality"
},
  "geometry": {"coordinates":[77.13333,15.12158],"type":"Point"}
}