{
  "type": "Feature",
  "properties": {
    "iso:country":"IN",
    "ks:ks_name":"Seeluthukottai",
    "ks:ks_pop":191,
    "ks:ks_type":"HABITATION",
    "name:eng_x_preferred":[
        "Seeluthukottai"
    ],
    "wof:name":"Seeluthukottai",
    "wof:placetype":"locality",
    "wof:population":191
},
  "geometry": {"coordinates":[77.99005200000001,12.245107],"type":"Point"}
}