{
  "type": "Feature",
  "properties": {
    "iso:country":"IN",
    "ks:ks_alt_nam":"bhahariya",
    "ks:ks_name":"Bhahariya",
    "ks:ks_pop":205,
    "ks:ks_type":"HABITATION",
    "name:eng_x_preferred":[
        "Bhahariya"
    ],
    "wof:name":"Bhahariya",
    "wof:placetype":"locality",
    "wof:population":205
},
  "geometry": {"coordinates":[81.90737900000001,26.115329],"type":"Point"}
}