{
  "type": "Feature",
  "properties": {
    "iso:country":"IN",
    "ks:ks_name":"Danseeli",
    "ks:ks_pop":200,
    "ks:ks_type":"VILLAGE",
    "name:eng_x_preferred":[
        "Danseeli"
    ],
    "wof:name":"Danseeli",
    "wof:placetype":"locality",
    "wof:population":200
},
  "geometry": {"coordinates":[79.84577,29.375306],"type":"Point"}
}