{
  "type": "Feature",
  "properties": {
    "gn:admin1_code":"11",
    "gn:admin2_code":"23.0",
    "gn:asciiname":"Chan",
    "gn:country_code":"IN",
    "gn:dem":1030,
    "gn:feature_class":"P",
    "gn:feature_code":"PPL",
    "gn:name":"Chan",
    "gn:population":0,
    "gn:timezone":"Asia/Kolkata",
    "iso:country":"IN",
    "name:ceb_x_preferred":[
        "Chan"
    ],
    "name:ces_x_preferred":[
        "Chan"
    ],
    "name:deu_x_preferred":[
        "Chan"
    ],
    "name:fin_x_preferred":[
        "Chan"
    ],
    "name:fra_x_preferred":[
        "Chan"
    ],
    "name:glg_x_preferred":[
        "Chan"
    ],
    "name:heb_x_preferred":[
        "\u05e6'\u05d0\u05df"
    ],
    "name:ita_x_preferred":[
        "Chan"
    ],
    "name:nld_x_preferred":[
        "Chan"
    ],
    "name:pol_x_preferred":[
        "Chan"
    ],
    "name:por_x_preferred":[
        "Chan"
    ],
    "name:rus_x_preferred":[
        "\u0427\u0436\u0430\u043d\u044c"
    ],
    "name:slk_x_preferred":[
        "Chan"
    ],
    "name:spa_x_preferred":[
        "Chan"
    ],
    "name:swe_x_preferred":[
        "Chan"
    ],
    "wof:name":"Chan",
    "wof:placetype":"locality"
},
  "geometry": {"coordinates":[76.09791,32.31362],"type":"Point"}
}