{
  "type": "Feature",
  "properties": {
    "iso:country":"IN",
    "ks:ks_name":"Ramnagar Parsahi Milik",
    "ks:ks_pop":559,
    "ks:ks_type":"VILLAGE",
    "name:eng_x_preferred":[
        "Ramnagar Parsahi Milik"
    ],
    "wof:name":"Ramnagar Parsahi Milik",
    "wof:placetype":"locality",
    "wof:population":559
},
  "geometry": {"coordinates":[87.15841899999999,25.861865],"type":"Point"}
}