{
  "type": "Feature",
  "properties": {
    "gn:admin1_code":"35",
    "gn:admin2_code":"452.0",
    "gn:asciiname":"Bichua Khurd",
    "gn:country_code":"IN",
    "gn:dem":360,
    "gn:feature_class":"P",
    "gn:feature_code":"PPL",
    "gn:name":"Bichua Khurd",
    "gn:population":0,
    "gn:timezone":"Asia/Kolkata",
    "iso:country":"IN",
    "ks:ks_name":"Bichua Khurd",
    "ks:ks_pop":29,
    "ks:ks_type":"VILLAGE",
    "name:eng_x_preferred":[
        "Bichua Khurd"
    ],
    "wof:name":"Bichua Khurd",
    "wof:placetype":"locality",
    "wof:population":29
},
  "geometry": {"coordinates":[79.166577,22.867618],"type":"Point"}
}