{
  "type": "Feature",
  "properties": {
    "iso:country":"IN",
    "ks:ks_name":"Kach Gerya",
    "ks:ks_pop":0,
    "ks:ks_type":"VILLAGE",
    "name:eng_x_preferred":[
        "Kach Gerya"
    ],
    "wof:name":"Kach Gerya",
    "wof:placetype":"locality",
    "wof:population":0
},
  "geometry": {"coordinates":[87.50191,22.652826],"type":"Point"}
}