{
  "type": "Feature",
  "properties": {
    "gn:admin1_code":"34.0",
    "gn:admin2_code":"207.0",
    "gn:asciiname":"Dunbari",
    "gn:country_code":"IN",
    "gn:dem":78,
    "gn:feature_class":"P",
    "gn:feature_code":"PPL",
    "gn:name":"Dunb\u0101ri",
    "gn:population":0,
    "gn:timezone":"Asia/Kolkata",
    "iso:country":"IN",
    "ks:ks_name":"Donbari",
    "ks:ks_pop":1618,
    "ks:ks_type":"HABITATION",
    "ks:ks_uagg_main":0,
    "name:eng_x_preferred":[
        "Donbari"
    ],
    "wof:name":"Donbari",
    "wof:placetype":"neighbourhood",
    "wof:population":1618
},
  "geometry": {"coordinates":[86.382254,26.493677],"type":"Point"}
}