{
  "type": "Feature",
  "properties": {
    "iso:country":"IN",
    "ks:ks_name":"Mahmood Pur",
    "ks:ks_pop":493,
    "ks:ks_type":"HABITATION",
    "ks:ks_uagg_main":0,
    "name:eng_x_preferred":[
        "Mahmood Pur"
    ],
    "wof:name":"Mahmood Pur",
    "wof:placetype":"neighbourhood",
    "wof:population":493
},
  "geometry": {"coordinates":[80.352245,27.344197],"type":"Point"}
}