{
  "type": "Feature",
  "properties": {
    "iso:country":"IN",
    "ks:ks_name":"40 NGC",
    "ks:ks_pop":15,
    "ks:ks_type":"VILLAGE",
    "name:eng_x_preferred":[
        "40 NGC"
    ],
    "wof:name":"40 NGC",
    "wof:placetype":"locality",
    "wof:population":15
},
  "geometry": {"coordinates":[74.36180299999999,29.622025],"type":"Point"}
}