{
  "type": "Feature",
  "properties": {
    "iso:country":"IN",
    "ks:ks_name":"Gharphaliagaon",
    "ks:ks_pop":381,
    "ks:ks_type":"VILLAGE",
    "ks:ks_uagg_main":0,
    "name:eng_x_preferred":[
        "Gharphaliagaon"
    ],
    "wof:name":"Gharphaliagaon",
    "wof:placetype":"neighbourhood",
    "wof:population":381
},
  "geometry": {"coordinates":[94.297764,26.678246],"type":"Point"}
}