{
  "type": "Feature",
  "properties": {
    "iso:country":"IN",
    "ks:ks_name":"Musaithi",
    "ks:ks_pop":465,
    "ks:ks_type":"VILLAGE",
    "name:eng_x_preferred":[
        "Musaithi"
    ],
    "wof:name":"Musaithi",
    "wof:placetype":"locality",
    "wof:population":465
},
  "geometry": {"coordinates":[79.022543,30.034325],"type":"Point"}
}