{
  "type": "Feature",
  "properties": {
    "iso:country":"IN",
    "ks:ks_name":"Siribala",
    "ks:ks_pop":226,
    "ks:ks_type":"VILLAGE",
    "name:eng_x_preferred":[
        "Siribala"
    ],
    "wof:name":"Siribala",
    "wof:placetype":"locality",
    "wof:population":226
},
  "geometry": {"coordinates":[82.24859600000001,17.914395],"type":"Point"}
}