{
  "type": "Feature",
  "properties": {
    "iso:country":"IN",
    "ks:ks_name":"Sapepar Rayyatwari",
    "ks:ks_pop":67,
    "ks:ks_type":"HABITATION",
    "name:eng_x_preferred":[
        "Sapepar Rayyatwari"
    ],
    "wof:name":"Sapepar Rayyatwari",
    "wof:placetype":"locality",
    "wof:population":67
},
  "geometry": {"coordinates":[79.64766,20.451224],"type":"Point"}
}