{
  "type": "Feature",
  "properties": {
    "gn:admin1_code":"36",
    "gn:admin2_code":"160.0",
    "gn:asciiname":"Rura",
    "gn:country_code":"IN",
    "gn:dem":143,
    "gn:feature_class":"P",
    "gn:feature_code":"PPL",
    "gn:name":"R\u016bra",
    "gn:population":0,
    "gn:timezone":"Asia/Kolkata",
    "iso:country":"IN",
    "name:bpy_x_preferred":[
        "\u09b0\u09c1\u09b0\u09be"
    ],
    "name:ceb_x_preferred":[
        "Rura"
    ],
    "name:hin_x_preferred":[
        "\u0930\u0942\u0930\u093e"
    ],
    "name:ita_x_preferred":[
        "Rura"
    ],
    "name:mlg_x_preferred":[
        "Rura"
    ],
    "name:msa_x_preferred":[
        "Rura"
    ],
    "name:nld_x_preferred":[
        "Rura"
    ],
    "name:pol_x_preferred":[
        "Rura"
    ],
    "name:por_x_preferred":[
        "Rura"
    ],
    "name:urd_x_preferred":[
        "\u0631\u0648\u0631\u0627"
    ],
    "name:vie_x_preferred":[
        "Rura"
    ],
    "wof:name":"Rura",
    "wof:placetype":"locality"
},
  "geometry": {"coordinates":[79.84276,26.90712000000001],"type":"Point"}
}