{
  "type": "Feature",
  "properties": {
    "gn:admin1_code":"25.0",
    "gn:admin2_code":"619.0",
    "gn:asciiname":"Nagar",
    "gn:country_code":"IN",
    "gn:dem":26,
    "gn:feature_class":"P",
    "gn:feature_code":"PPL",
    "gn:name":"Nagar",
    "gn:population":0,
    "gn:timezone":"Asia/Kolkata",
    "iso:country":"IN",
    "name:ben_x_preferred":[
        "\u09a8\u0997\u09b0"
    ],
    "name:bpy_x_preferred":[
        "\u09a8\u0997\u09b0"
    ],
    "name:cat_x_preferred":[
        "Nagar"
    ],
    "name:ceb_x_preferred":[
        "Nagar"
    ],
    "name:deu_x_preferred":[
        "Nagar"
    ],
    "name:heb_x_preferred":[
        "\u05e0\u05d2\u05e8"
    ],
    "name:new_x_preferred":[
        "\u0928\u0917\u0930"
    ],
    "name:nld_x_preferred":[
        "Nagar"
    ],
    "name:swe_x_preferred":[
        "Nagar"
    ],
    "wof:name":"Nagar",
    "wof:placetype":"locality"
},
  "geometry": {"coordinates":[79.37576999999997,10.78702],"type":"Point"}
}