{
  "type": "Feature",
  "properties": {
    "iso:country":"IN",
    "ks:ks_alt_nam":"LOAMDARHA",
    "ks:ks_name":"Loamdarha",
    "ks:ks_pop":197,
    "ks:ks_type":"HABITATION",
    "name:eng_x_preferred":[
        "Loamdarha"
    ],
    "wof:name":"Loamdarha",
    "wof:placetype":"locality",
    "wof:population":197
},
  "geometry": {"coordinates":[83.678652,23.037045],"type":"Point"}
}