{
  "type": "Feature",
  "properties": {
    "iso:country":"IN",
    "ks:ks_alt_nam":"Majhg\u0101w\u0101n",
    "ks:ks_name":"Majhgawan",
    "ks:ks_pop":0,
    "ks:ks_type":"VILLAGE",
    "name:eng_x_preferred":[
        "Majhgawan"
    ],
    "name:eng_x_variant":[
        "Majhg\u0101w\u0101n"
    ],
    "wof:name":"Majhgawan",
    "wof:placetype":"locality",
    "wof:population":0
},
  "geometry": {"coordinates":[83.384837,25.126496],"type":"Point"}
}