{
  "type": "Feature",
  "properties": {
    "iso:country":"IN",
    "ks:ks_name":"Vendar L P S Jn",
    "ks:ks_pop":1915,
    "ks:ks_type":"HABITATION",
    "name:eng_x_preferred":[
        "Vendar L P S Jn"
    ],
    "wof:name":"Vendar L P S Jn",
    "wof:placetype":"locality",
    "wof:population":1915
},
  "geometry": {"coordinates":[76.735401,9.032262],"type":"Point"}
}