{
  "type": "Feature",
  "properties": {
    "iso:country":"IN",
    "ks:ks_alt_nam":"BIGHAPAR",
    "ks:ks_name":"Bighapar",
    "ks:ks_pop":342,
    "ks:ks_type":"HABITATION",
    "name:eng_x_preferred":[
        "Bighapar"
    ],
    "wof:name":"Bighapar",
    "wof:placetype":"locality",
    "wof:population":342
},
  "geometry": {"coordinates":[85.444233,24.911385],"type":"Point"}
}