{
  "type": "Feature",
  "properties": {
    "iso:country":"IN",
    "ks:ks_name":"Dakhin Mahina",
    "ks:ks_pop":300,
    "ks:ks_type":"HABITATION",
    "name:eng_x_preferred":[
        "Dakhin Mahina"
    ],
    "wof:name":"Dakhin Mahina",
    "wof:placetype":"locality",
    "wof:population":300
},
  "geometry": {"coordinates":[91.45327399999999,26.555926],"type":"Point"}
}