{
  "type": "Feature",
  "properties": {
    "iso:country":"IN",
    "ks:ks_alt_nam":"PARDEEP NAGAR",
    "ks:ks_name":"Pardeep Nagar",
    "ks:ks_pop":340,
    "ks:ks_type":"HABITATION",
    "name:eng_x_preferred":[
        "Pardeep Nagar"
    ],
    "wof:name":"Pardeep Nagar",
    "wof:placetype":"locality",
    "wof:population":340
},
  "geometry": {"coordinates":[85.020393,24.687196],"type":"Point"}
}