{
  "type": "Feature",
  "properties": {
    "gn:admin1_code":"35.0",
    "gn:admin2_code":"440.0",
    "gn:asciiname":"Ahilyapura",
    "gn:country_code":"IN",
    "gn:dem":244,
    "gn:feature_class":"P",
    "gn:feature_code":"PPL",
    "gn:name":"Ahily\u0101pura",
    "gn:population":0,
    "gn:timezone":"Asia/Kolkata",
    "iso:country":"IN",
    "ks:ks_alt_nam":"Ahily\u0101pura",
    "ks:ks_name":"Ahilyapura",
    "ks:ks_type":"VILLAGE",
    "name:eng_x_preferred":[
        "Ahilyapura"
    ],
    "name:eng_x_variant":[
        "Ahily\u0101pura"
    ],
    "wof:name":"Ahilyapura",
    "wof:placetype":"locality"
},
  "geometry": {"coordinates":[75.72552,22.308534],"type":"Point"}
}