{
  "type": "Feature",
  "properties": {
    "iso:country":"IN",
    "ks:ks_name":"Magurmari",
    "ks:ks_pop":52,
    "ks:ks_type":"VILLAGE",
    "name:eng_x_preferred":[
        "Magurmari"
    ],
    "wof:name":"Magurmari",
    "wof:placetype":"locality",
    "wof:population":52
},
  "geometry": {"coordinates":[89.083755,26.494421],"type":"Point"}
}