{
  "type": "Feature",
  "properties": {
    "iso:country":"IN",
    "ks:ks_name":"Wayra May Lunthu",
    "ks:ks_pop":575,
    "ks:ks_type":"VILLAGE",
    "name:eng_x_preferred":[
        "Wayra May Lunthu"
    ],
    "wof:name":"Wayra May Lunthu",
    "wof:placetype":"locality",
    "wof:population":575
},
  "geometry": {"coordinates":[78.558848,30.74409],"type":"Point"}
}