{
  "type": "Feature",
  "properties": {
    "iso:country":"IN",
    "ks:ks_name":"Katri Amritpur",
    "ks:ks_type":"VILLAGE",
    "name:eng_x_preferred":[
        "Katri Amritpur"
    ],
    "wof:name":"Katri Amritpur",
    "wof:placetype":"locality"
},
  "geometry": {"coordinates":[79.566976,27.542194],"type":"Point"}
}