{
  "type": "Feature",
  "properties": {
    "iso:country":"IN",
    "ks:ks_name":"Taranga",
    "ks:ks_pop":183,
    "ks:ks_type":"HABITATION",
    "name:eng_x_preferred":[
        "Taranga"
    ],
    "wof:name":"Taranga",
    "wof:placetype":"locality",
    "wof:population":183
},
  "geometry": {"coordinates":[84.47106100000001,21.432814],"type":"Point"}
}