{
  "type": "Feature",
  "properties": {
    "iso:country":"IN",
    "ks:ks_alt_nam":"KOL EAST TOLA",
    "ks:ks_name":"Kol East Tola",
    "ks:ks_pop":366,
    "ks:ks_type":"HABITATION",
    "name:eng_x_preferred":[
        "Kol East Tola"
    ],
    "wof:name":"Kol East Tola",
    "wof:placetype":"locality",
    "wof:population":366
},
  "geometry": {"coordinates":[87.622134,25.883531],"type":"Point"}
}