{
  "type": "Feature",
  "properties": {
    "gn:admin1_code":"34.0",
    "gn:admin2_code":"204.0",
    "gn:asciiname":"Bairiya",
    "gn:country_code":"IN",
    "gn:dem":68,
    "gn:feature_class":"P",
    "gn:feature_code":"PPL",
    "gn:name":"Bairiy\u0101",
    "gn:population":0,
    "gn:timezone":"Asia/Kolkata",
    "iso:country":"IN",
    "name:ceb_x_preferred":[
        "Bairiya"
    ],
    "name:hin_x_preferred":[
        "\u092c\u0948\u0930\u093f\u092f\u093e"
    ],
    "name:mai_x_preferred":[
        "\u092c\u0948\u0930\u093f\u092f\u093e"
    ],
    "name:msa_x_preferred":[
        "Bairiya"
    ],
    "name:new_x_preferred":[
        "\u092c\u0948\u0930\u093f\u092f\u093e"
    ],
    "name:pol_x_preferred":[
        "Bairiya"
    ],
    "wof:name":"Bairiya",
    "wof:placetype":"locality"
},
  "geometry": {"coordinates":[84.87396,26.45263],"type":"Point"}
}