{
  "type": "Feature",
  "properties": {
    "iso:country":"IN",
    "ks:ks_name":"Mukhat",
    "ks:ks_pop":143,
    "ks:ks_type":"VILLAGE",
    "name:eng_x_preferred":[
        "Mukhat"
    ],
    "wof:name":"Mukhat",
    "wof:placetype":"locality",
    "wof:population":143
},
  "geometry": {"coordinates":[81.014494,24.907199],"type":"Point"}
}