{
  "type": "Feature",
  "properties": {
    "iso:country":"IN",
    "ks:ks_name":"22 A-B",
    "ks:ks_pop":98,
    "ks:ks_type":"VILLAGE",
    "name:eng_x_preferred":[
        "22 A-B"
    ],
    "wof:name":"22 A-B",
    "wof:placetype":"locality",
    "wof:population":98
},
  "geometry": {"coordinates":[73.15023100000001,29.182845],"type":"Point"}
}