{
  "type": "Feature",
  "properties": {
    "gn:admin1_code":"2.0",
    "gn:admin2_code":"554.0",
    "gn:asciiname":"Kammavandlapalle",
    "gn:country_code":"IN",
    "gn:dem":626,
    "gn:feature_class":"P",
    "gn:feature_code":"PPL",
    "gn:name":"Kammav\u0101ndlapalle",
    "gn:population":0,
    "gn:timezone":"Asia/Kolkata",
    "iso:country":"IN",
    "wof:name":"Kammavandlapalle",
    "wof:placetype":"locality"
},
  "geometry": {"coordinates":[78.22077,13.76168],"type":"Point"}
}