{
  "type": "Feature",
  "properties": {
    "iso:country":"IN",
    "ks:ks_name":"Kadalibadia",
    "ks:ks_pop":894,
    "ks:ks_type":"VILLAGE",
    "name:eng_x_preferred":[
        "Kadalibadia"
    ],
    "wof:name":"Kadalibadia",
    "wof:placetype":"locality",
    "wof:population":894
},
  "geometry": {"coordinates":[86.696147,21.92386],"type":"Point"}
}