{
  "type": "Feature",
  "properties": {
    "iso:country":"IN",
    "ks:ks_name":"Gelpur",
    "ks:ks_pop":1782,
    "ks:ks_type":"VILLAGE",
    "ks:ks_uagg_main":0,
    "name:eng_x_preferred":[
        "Gelpur"
    ],
    "wof:name":"Gelpur",
    "wof:placetype":"locality",
    "wof:population":1782
},
  "geometry": {"coordinates":[86.480733,21.046267],"type":"Point"}
}