{
  "type": "Feature",
  "properties": {
    "gn:admin1_code":"36",
    "gn:admin2_code":"136.0",
    "gn:asciiname":"Banawala",
    "gn:country_code":"IN",
    "gn:dem":195,
    "gn:feature_class":"P",
    "gn:feature_code":"PPL",
    "gn:name":"Ban\u0101w\u0101la",
    "gn:population":0,
    "gn:timezone":"Asia/Kolkata",
    "iso:country":"IN",
    "ks:ks_name":"Bina Wala",
    "ks:ks_pop":1386,
    "ks:ks_type":"VILLAGE",
    "ks:ks_uagg_main":0,
    "name:eng_x_preferred":[
        "Bina Wala"
    ],
    "wof:name":"Bina Wala",
    "wof:placetype":"neighbourhood",
    "wof:population":1386
},
  "geometry": {"coordinates":[78.959293,28.831685],"type":"Point"}
}