{
  "type": "Feature",
  "properties": {
    "iso:country":"IN",
    "ks:ks_name":"Manni Pur",
    "ks:ks_pop":55,
    "ks:ks_type":"HABITATION",
    "name:eng_x_preferred":[
        "Manni Pur"
    ],
    "wof:name":"Manni Pur",
    "wof:placetype":"locality",
    "wof:population":55
},
  "geometry": {"coordinates":[81.47295699999999,27.495375],"type":"Point"}
}