{
  "type": "Feature",
  "properties": {
    "iso:country":"IN",
    "ks:ks_alt_nam":"Muthur JHC",
    "ks:ks_name":"Muthur Jhc",
    "ks:ks_pop":1005,
    "ks:ks_type":"HABITATION",
    "name:eng_x_preferred":[
        "Muthur Jhc"
    ],
    "wof:name":"Muthur Jhc",
    "wof:placetype":"locality",
    "wof:population":1005
},
  "geometry": {"coordinates":[74.982665,12.957319],"type":"Point"}
}