{
  "type": "Feature",
  "properties": {
    "gn:admin1_code":"13.0",
    "gn:admin2_code":"590.0",
    "gn:asciiname":"Nellivayal",
    "gn:country_code":"IN",
    "gn:dem":878,
    "gn:feature_class":"P",
    "gn:feature_code":"PPL",
    "gn:name":"Nellivayal",
    "gn:population":0,
    "gn:timezone":"Asia/Kolkata",
    "iso:country":"IN",
    "wof:name":"Nellivayal",
    "wof:placetype":"locality"
},
  "geometry": {"coordinates":[76.28813000000002,11.64775],"type":"Point"}
}