{
  "type": "Feature",
  "properties": {
    "iso:country":"IN",
    "ks:ks_name":"West Tola",
    "ks:ks_pop":804,
    "ks:ks_type":"HABITATION",
    "ks:ks_uagg_main":0,
    "name:eng_x_preferred":[
        "West Tola"
    ],
    "wof:name":"West Tola",
    "wof:placetype":"neighbourhood",
    "wof:population":804
},
  "geometry": {"coordinates":[85.985345,25.801877],"type":"Point"}
}