{
  "type": "Feature",
  "properties": {
    "iso:country":"IN",
    "ks:ks_name":"Nimatpur",
    "ks:ks_pop":2005,
    "ks:ks_type":"VILLAGE",
    "name:eng_x_preferred":[
        "Nimatpur"
    ],
    "wof:name":"Nimatpur",
    "wof:placetype":"locality",
    "wof:population":2005
},
  "geometry": {"coordinates":[87.410175,21.641098],"type":"Point"}
}