{
  "type": "Feature",
  "properties": {
    "gn:admin1_code":"17",
    "gn:admin2_code":"272.0",
    "gn:asciiname":"Mao Songsang",
    "gn:country_code":"IN",
    "gn:dem":1712,
    "gn:feature_class":"P",
    "gn:feature_code":"PPL",
    "gn:name":"Mao Songsang",
    "gn:population":0,
    "gn:timezone":"Asia/Kolkata",
    "iso:country":"IN",
    "name:und_x_variant":[
        "Mao",
        "Mao Songsang"
    ],
    "wof:name":"Mao Songsang",
    "wof:placetype":"locality"
},
  "geometry": {"coordinates":[94.1413,25.51339],"type":"Point"}
}