{
  "type": "Feature",
  "properties": {
    "iso:country":"IN",
    "ks:ks_name":"Habi Borangabori",
    "ks:ks_pop":874,
    "ks:ks_type":"HABITATION",
    "name:eng_x_preferred":[
        "Habi Borangabori"
    ],
    "wof:name":"Habi Borangabori",
    "wof:placetype":"locality",
    "wof:population":874
},
  "geometry": {"coordinates":[92.42261499999999,26.370522],"type":"Point"}
}