{
  "type": "Feature",
  "properties": {
    "iso:country":"IN",
    "ks:ks_name":"Narayan Guri",
    "ks:ks_pop":206,
    "ks:ks_type":"VILLAGE",
    "ks:ks_uagg_main":0,
    "name:eng_x_preferred":[
        "Narayan Guri"
    ],
    "wof:name":"Narayan Guri",
    "wof:placetype":"neighbourhood",
    "wof:population":206
},
  "geometry": {"coordinates":[90.98876199999999,26.638841],"type":"Point"}
}