{
  "type": "Feature",
  "properties": {
    "iso:country":"IN",
    "ks:ks_name":"Arazi Chandpara",
    "ks:ks_pop":0,
    "ks:ks_type":"VILLAGE",
    "name:eng_x_preferred":[
        "Arazi Chandpara"
    ],
    "wof:name":"Arazi Chandpara",
    "wof:placetype":"locality",
    "wof:population":0
},
  "geometry": {"coordinates":[88.16256,24.013055],"type":"Point"}
}