{
  "type": "Feature",
  "properties": {
    "iso:country":"IN",
    "ks:ks_name":"Sahan",
    "ks:ks_pop":505,
    "ks:ks_type":"HABITATION",
    "name:eng_x_preferred":[
        "Sahan"
    ],
    "wof:name":"Sahan",
    "wof:placetype":"locality",
    "wof:population":505
},
  "geometry": {"coordinates":[72.924594,18.68442],"type":"Point"}
}