{
  "type": "Feature",
  "properties": {
    "iso:country":"IN",
    "ks:ks_name":"Pathrapani",
    "ks:ks_pop":487,
    "ks:ks_type":"VILLAGE",
    "name:eng_x_preferred":[
        "Pathrapani"
    ],
    "wof:name":"Pathrapani",
    "wof:placetype":"locality",
    "wof:population":487
},
  "geometry": {"coordinates":[81.438953,23.806993],"type":"Point"}
}