{
  "type": "Feature",
  "properties": {
    "gn:admin1_code":"39.0",
    "gn:admin2_code":"63.0",
    "gn:asciiname":"Polin",
    "gn:country_code":"IN",
    "gn:dem":1082,
    "gn:feature_class":"P",
    "gn:feature_code":"PPL",
    "gn:name":"Polin",
    "gn:population":0,
    "gn:timezone":"Asia/Kolkata",
    "iso:country":"IN",
    "ks:ks_name":"Poling",
    "ks:ks_pop":347,
    "ks:ks_type":"HABITATION",
    "name:eng_x_preferred":[
        "Poling"
    ],
    "name:eng_x_variant":[
        "Polin"
    ],
    "name:pol_x_preferred":[
        "Polin"
    ],
    "wof:name":"Poling",
    "wof:placetype":"locality",
    "wof:population":347
},
  "geometry": {"coordinates":[79.86778,29.920668],"type":"Point"}
}