{
  "type": "Feature",
  "properties": {
    "iso:country":"IN",
    "ks:ks_name":"Thelamaruni",
    "ks:ks_pop":67,
    "ks:ks_type":"VILLAGE",
    "name:eng_x_preferred":[
        "Thelamaruni"
    ],
    "wof:name":"Thelamaruni",
    "wof:placetype":"locality",
    "wof:population":67
},
  "geometry": {"coordinates":[84.444311,20.695914],"type":"Point"}
}