{
  "type": "Feature",
  "properties": {
    "iso:country":"IN",
    "name:eng_x_preferred":[
        "Khajwaal"
    ],
    "qs:gn_adm0_cc":"IN",
    "qs:gn_local":1253573,
    "qs:gn_nam_loc":"Vadodara, Vadodara, Gujarat, IN",
    "qs:gn_namadm1":"09",
    "qs:local_max":286,
    "qs:local_sum":573,
    "qs:localhoods":4,
    "qs:name":"Khajwaal",
    "qs:name_adm0":"India",
    "qs:name_adm1":"Gujarat",
    "qs:name_adm2":"Vadodara",
    "qs:name_local":"Vadodara",
    "qs:photo_max":120,
    "qs:photo_sum":125,
    "qs:placetype":"Suburb",
    "qs:quad_count":4,
    "qs:woe_adm0":23424848,
    "qs:woe_adm1":2345743,
    "qs:woe_adm2":12586435,
    "qs:woe_lau":0,
    "qs:woe_local":2295403,
    "qs:woe_ver":"7.10.0",
    "wof:lang":[
        "eng"
    ],
    "wof:name":"Khajwaal",
    "wof:placetype":"neighbourhood"
},
  "geometry": {"coordinates":[73.187061,22.305675],"type":"Point"}
}