{
  "type": "Feature",
  "properties": {
    "iso:country":"IN",
    "name:ara_x_preferred":[
        "\u0643\u0627\u062c\u0648\u0627\u0644"
    ],
    "name:ben_bn_x_preferred":[
        "\u0996\u09be\u099c\u0993\u09df\u09be\u09b2"
    ],
    "name:ben_in_x_preferred":[
        "\u0996\u09be\u099c\u0993\u09df\u09be\u09b2"
    ],
    "name:eng_x_preferred":[
        "Khajwaal"
    ],
    "name:guj_x_preferred":[
        "\u0a96\u0a9c\u0ab5\u0abe\u0ab2"
    ],
    "name:hin_x_preferred":[
        "\u0916\u091c\u0935\u093e\u0932"
    ],
    "name:kan_x_preferred":[
        "\u0c96\u0c9c\u0ccd\u0cb5\u0cbe\u0cb2\u0ccd"
    ],
    "name:mal_x_preferred":[
        "\u0d16\u0d1c\u0d4d"
    ],
    "name:mar_x_preferred":[
        "\u0916\u091c\u0935\u0933"
    ],
    "name:pan_x_preferred":[
        "\u0a16\u0a1c\u0a35\u0a3e\u0a32"
    ],
    "name:tam_x_preferred":[
        "\u0b95\u0b9c\u0bcd\u0bb5\u0bbe\u0bb2\u0bcd"
    ],
    "name:tel_x_preferred":[
        "\u0c16\u0c1c\u0c4d\u0c35\u0c3e\u0c32\u0c4d"
    ],
    "name:urd_x_preferred":[
        "\u06a9\u06be\u0627\u062c\u0648\u0627\u0644"
    ],
    "qs:gn_adm0_cc":"IN",
    "qs:gn_local":1253573,
    "qs:gn_nam_loc":"Vadodara, Vadodara, Gujarat, IN",
    "qs:gn_namadm1":"09",
    "qs:local_max":286,
    "qs:local_sum":573,
    "qs:localhoods":4,
    "qs:name":"Khajwaal",
    "qs:name_adm0":"India",
    "qs:name_adm1":"Gujarat",
    "qs:name_adm2":"Vadodara",
    "qs:name_local":"Vadodara",
    "qs:photo_max":120,
    "qs:photo_sum":125,
    "qs:placetype":"Suburb",
    "qs:quad_count":4,
    "qs:woe_adm0":23424848,
    "qs:woe_adm1":2345743,
    "qs:woe_adm2":12586435,
    "qs:woe_lau":0,
    "qs:woe_local":2295403,
    "qs:woe_ver":"7.10.0",
    "wof:lang":[
        "eng"
    ],
    "wof:name":"Khajwaal",
    "wof:placetype":"neighbourhood"
},
  "geometry": {"coordinates":[73.187061,22.305675],"type":"Point"}
}