{
  "type": "Feature",
  "properties": {
    "gn:admin1_code":"35.0",
    "gn:admin2_code":"439.0",
    "gn:asciiname":"Dhawdiya",
    "gn:country_code":"IN",
    "gn:dem":417,
    "gn:feature_class":"P",
    "gn:feature_code":"PPL",
    "gn:name":"Dh\u0101wdiya",
    "gn:population":0,
    "gn:timezone":"Asia/Kolkata",
    "iso:country":"IN",
    "ks:ks_name":"Dhawadiya",
    "ks:ks_pop":250,
    "ks:ks_type":"VILLAGE",
    "name:eng_x_preferred":[
        "Dhawadiya"
    ],
    "name:eng_x_variant":[
        "Dhawdiya"
    ],
    "wof:name":"Dhawadiya",
    "wof:placetype":"locality",
    "wof:population":250
},
  "geometry": {"coordinates":[75.869647,22.472932],"type":"Point"}
}