{
  "type": "Feature",
  "properties": {
    "gn:admin1_code":"36",
    "gn:admin2_code":"163.0",
    "gn:asciiname":"Aunguri",
    "gn:country_code":"IN",
    "gn:dem":137,
    "gn:feature_class":"P",
    "gn:feature_code":"PPL",
    "gn:name":"Aunguri",
    "gn:population":0,
    "gn:timezone":"Asia/Kolkata",
    "iso:country":"IN",
    "wof:name":"Aunguri",
    "wof:placetype":"locality"
},
  "geometry": {"coordinates":[79.78471,26.26218],"type":"Point"}
}