{
  "type": "Feature",
  "properties": {
    "iso:country":"IN",
    "ks:ks_name":"Kathaun",
    "ks:ks_pop":58,
    "ks:ks_type":"VILLAGE",
    "name:eng_x_preferred":[
        "Kathaun"
    ],
    "wof:name":"Kathaun",
    "wof:placetype":"locality",
    "wof:population":58
},
  "geometry": {"coordinates":[84.787544,24.347865],"type":"Point"}
}