{
  "type": "Feature",
  "properties": {
    "iso:country":"IN",
    "ks:ks_name":"Choolachodu",
    "ks:ks_pop":342,
    "ks:ks_type":"HABITATION",
    "name:eng_x_preferred":[
        "Choolachodu"
    ],
    "wof:name":"Choolachodu",
    "wof:placetype":"locality",
    "wof:population":342
},
  "geometry": {"coordinates":[76.35727199999999,10.652123],"type":"Point"}
}