{
  "type": "Feature",
  "properties": {
    "iso:country":"IN",
    "ks:ks_name":"Singalmunduli",
    "ks:ks_pop":445,
    "ks:ks_type":"VILLAGE",
    "name:eng_x_preferred":[
        "Singalmunduli"
    ],
    "wof:name":"Singalmunduli",
    "wof:placetype":"locality",
    "wof:population":445
},
  "geometry": {"coordinates":[86.836337,21.649441],"type":"Point"}
}