{
  "type": "Feature",
  "properties": {
    "iso:country":"IN",
    "ks:ks_name":"Purushottapuram",
    "ks:ks_pop":641,
    "ks:ks_type":"VILLAGE",
    "ks:ks_uagg_main":0,
    "name:eng_x_preferred":[
        "Purushottapuram"
    ],
    "wof:name":"Purushottapuram",
    "wof:placetype":"neighbourhood",
    "wof:population":641
},
  "geometry": {"coordinates":[84.57968200000001,18.98034],"type":"Point"}
}