{
  "type": "Feature",
  "properties": {
    "iso:country":"IN",
    "ks:ks_name":"Arsel",
    "ks:ks_pop":792,
    "ks:ks_type":"VILLAGE",
    "ks:ks_uagg_main":0,
    "name:eng_x_preferred":[
        "Arsel"
    ],
    "wof:name":"Arsel",
    "wof:placetype":"neighbourhood",
    "wof:population":792
},
  "geometry": {"coordinates":[84.834062,24.008795],"type":"Point"}
}