{
  "type": "Feature",
  "properties": {
    "gn:admin1_code":"34.0",
    "gn:admin2_code":"236.0",
    "gn:asciiname":"Pheru Chak",
    "gn:country_code":"IN",
    "gn:dem":213,
    "gn:feature_class":"P",
    "gn:feature_code":"PPL",
    "gn:name":"Pheru Chak",
    "gn:population":0,
    "gn:timezone":"Asia/Kolkata",
    "iso:country":"IN",
    "ks:ks_name":"Pheru Chak",
    "ks:ks_type":"VILLAGE",
    "name:eng_x_preferred":[
        "Pheru Chak"
    ],
    "wof:name":"Pheru Chak",
    "wof:placetype":"locality"
},
  "geometry": {"coordinates":[84.518137,24.385161],"type":"Point"}
}