{
  "type": "Feature",
  "properties": {
    "iso:country":"IN",
    "ks:ks_name":"Dulum Khutahari",
    "ks:ks_pop":79,
    "ks:ks_type":"VILLAGE",
    "name:eng_x_preferred":[
        "Dulum Khutahari"
    ],
    "wof:name":"Dulum Khutahari",
    "wof:placetype":"locality",
    "wof:population":79
},
  "geometry": {"coordinates":[87.405708,25.190029],"type":"Point"}
}