{
  "type": "Feature",
  "properties": {
    "iso:country":"IN",
    "ks:ks_name":"Sri Rampur",
    "ks:ks_pop":4848,
    "ks:ks_type":"VILLAGE",
    "ks:ks_uagg_main":0,
    "name:eng_x_preferred":[
        "Sri Rampur"
    ],
    "wof:name":"Sri Rampur",
    "wof:placetype":"neighbourhood",
    "wof:population":4848
},
  "geometry": {"coordinates":[87.921205,24.767818],"type":"Point"}
}