{
  "type": "Feature",
  "properties": {
    "iso:country":"IN",
    "ks:ks_name":"Rammanikpur",
    "ks:ks_pop":1743,
    "ks:ks_type":"HABITATION",
    "name:eng_x_preferred":[
        "Rammanikpur"
    ],
    "wof:name":"Rammanikpur",
    "wof:placetype":"locality",
    "wof:population":1743
},
  "geometry": {"coordinates":[92.95801,24.573648],"type":"Point"}
}