{
  "type": "Feature",
  "properties": {
    "iso:country":"IN",
    "ks:ks_name":"Umblebylu Maridibba",
    "ks:ks_pop":263,
    "ks:ks_type":"HABITATION",
    "name:eng_x_preferred":[
        "Umblebylu Maridibba"
    ],
    "wof:name":"Umblebylu Maridibba",
    "wof:placetype":"locality",
    "wof:population":263
},
  "geometry": {"coordinates":[75.559472,13.738775],"type":"Point"}
}