{
  "type": "Feature",
  "properties": {
    "iso:country":"IN",
    "ks:ks_name":"Nagaiah Colony",
    "ks:ks_pop":407,
    "ks:ks_type":"HABITATION",
    "ks:ks_uagg_main":0,
    "name:eng_x_preferred":[
        "Nagaiah Colony"
    ],
    "wof:name":"Nagaiah Colony",
    "wof:placetype":"neighbourhood",
    "wof:population":407
},
  "geometry": {"coordinates":[79.937455,13.598113],"type":"Point"}
}