{
  "type": "Feature",
  "properties": {
    "iso:country":"IN",
    "ks:ks_name":"Dakhin Tola",
    "ks:ks_pop":22,
    "ks:ks_type":"HABITATION",
    "name:eng_x_preferred":[
        "Dakhin Tola"
    ],
    "wof:name":"Dakhin Tola",
    "wof:placetype":"locality",
    "wof:population":22
},
  "geometry": {"coordinates":[84.095416,25.36365],"type":"Point"}
}