{
  "type": "Feature",
  "properties": {
    "gn:admin1_code":"2.0",
    "gn:admin2_code":"554.0",
    "gn:asciiname":"Jalaravanundlu",
    "gn:country_code":"IN",
    "gn:dem":747,
    "gn:feature_class":"P",
    "gn:feature_code":"PPL",
    "gn:name":"Jalaravanundlu",
    "gn:population":0,
    "gn:timezone":"Asia/Kolkata",
    "iso:country":"IN",
    "wof:name":"Jalaravanundlu",
    "wof:placetype":"neighbourhood"
},
  "geometry": {"coordinates":[78.59220999999999,13.16376],"type":"Point"}
}