{
  "type": "Feature",
  "properties": {
    "gn:admin1_code":"24.0",
    "gn:admin2_code":"119.0",
    "gn:asciiname":"Kalikankar",
    "gn:country_code":"IN",
    "gn:dem":474,
    "gn:feature_class":"P",
    "gn:feature_code":"PPL",
    "gn:name":"K\u0101l\u012bk\u0101nkar",
    "gn:population":0,
    "gn:timezone":"Asia/Kolkata",
    "iso:country":"IN",
    "ks:ks_alt_nam":"K\u0101l\u012bk\u0101nkar",
    "ks:ks_name":"Kalikankar",
    "ks:ks_type":"VILLAGE",
    "ks:ks_uagg_main":0,
    "name:eng_x_preferred":[
        "Kalikankar"
    ],
    "name:eng_x_variant":[
        "K\u0101l\u012bk\u0101nkar"
    ],
    "wof:name":"Kalikankar",
    "wof:placetype":"neighbourhood"
},
  "geometry": {"coordinates":[74.24471200000001,26.035406],"type":"Point"}
}