{
  "type": "Feature",
  "properties": {
    "iso:country":"IN",
    "ks:ks_name":"Uttar Banpara",
    "ks:ks_pop":66,
    "ks:ks_type":"VILLAGE",
    "name:eng_x_preferred":[
        "Uttar Banpara"
    ],
    "wof:name":"Uttar Banpara",
    "wof:placetype":"locality",
    "wof:population":66
},
  "geometry": {"coordinates":[87.953469,23.614975],"type":"Point"}
}