{
  "type": "Feature",
  "properties": {
    "gn:admin1_code":"37",
    "gn:admin2_code":"409.0",
    "gn:asciiname":"Deori",
    "gn:country_code":"IN",
    "gn:dem":282,
    "gn:feature_class":"P",
    "gn:feature_code":"PPL",
    "gn:name":"Deori",
    "gn:population":0,
    "gn:timezone":"Asia/Kolkata",
    "iso:country":"IN",
    "ks:ks_name":"Deori",
    "ks:ks_pop":1609,
    "ks:ks_type":"VILLAGE",
    "name:cat_x_preferred":[
        "Deori"
    ],
    "name:ceb_x_preferred":[
        "Deori"
    ],
    "name:eng_x_preferred":[
        "Deori"
    ],
    "name:por_x_preferred":[
        "Deori"
    ],
    "name:swe_x_preferred":[
        "Deori"
    ],
    "wof:name":"Deori",
    "wof:placetype":"locality",
    "wof:population":1609
},
  "geometry": {"coordinates":[81.342844,21.531037],"type":"Point"}
}