{
  "type": "Feature",
  "properties": {
    "iso:country":"IN",
    "ks:ks_name":"Badi Pole",
    "ks:ks_pop":2804,
    "ks:ks_type":"HABITATION",
    "name:eng_x_preferred":[
        "Badi Pole"
    ],
    "wof:name":"Badi Pole",
    "wof:placetype":"locality",
    "wof:population":2804
},
  "geometry": {"coordinates":[74.26074699999999,22.540406],"type":"Point"}
}