{
  "type": "Feature",
  "properties": {
    "gn:admin1_code":"39.0",
    "gn:admin2_code":"64.0",
    "gn:asciiname":"Pandekhola",
    "gn:country_code":"IN",
    "gn:dem":1325,
    "gn:feature_class":"P",
    "gn:feature_code":"PPL",
    "gn:name":"P\u0101ndekhola",
    "gn:population":0,
    "gn:timezone":"Asia/Kolkata",
    "iso:country":"IN",
    "ks:ks_alt_nam":"P\u0101ndekhola",
    "ks:ks_name":"Pandekhola",
    "ks:ks_type":"VILLAGE",
    "name:eng_x_preferred":[
        "Pandekhola"
    ],
    "name:eng_x_variant":[
        "P\u0101ndekhola"
    ],
    "wof:name":"Pandekhola",
    "wof:placetype":"locality"
},
  "geometry": {"coordinates":[79.642672,29.626282],"type":"Point"}
}