{
  "type": "Feature",
  "properties": {
    "gn:admin1_code":"39.0",
    "gn:admin2_code":"64.0",
    "gn:asciiname":"Pandekhola",
    "gn:country_code":"IN",
    "gn:dem":1325,
    "gn:feature_class":"P",
    "gn:feature_code":"PPL",
    "gn:name":"P\u0101ndekhola",
    "gn:population":0,
    "gn:timezone":"Asia/Kolkata",
    "iso:country":"IN",
    "wof:name":"Pandekhola",
    "wof:placetype":"locality"
},
  "geometry": {"coordinates":[79.65376999999999,29.62437000000001],"type":"Point"}
}