{
  "type": "Feature",
  "properties": {
    "iso:country":"IN",
    "ks:ks_name":"Koppadakumeru",
    "ks:ks_pop":250,
    "ks:ks_type":"HABITATION",
    "name:eng_x_preferred":[
        "Koppadakumeru"
    ],
    "wof:name":"Koppadakumeru",
    "wof:placetype":"locality",
    "wof:population":250
},
  "geometry": {"coordinates":[74.95584100000001,13.035681],"type":"Point"}
}