{
  "type": "Feature",
  "properties": {
    "gn:admin1_code":"16",
    "gn:admin2_code":"511.0",
    "gn:asciiname":"Manjri",
    "gn:country_code":"IN",
    "gn:dem":443,
    "gn:feature_class":"P",
    "gn:feature_code":"PPL",
    "gn:name":"M\u0101njri",
    "gn:population":0,
    "gn:timezone":"Asia/Kolkata",
    "iso:country":"IN",
    "name:ukr_x_preferred":[
        "\u041c\u0430\u043d'\u0457\u0440\u0456"
    ],
    "wof:name":"Manjri",
    "wof:placetype":"locality"
},
  "geometry": {"coordinates":[77.30463,18.58695],"type":"Point"}
}