{
  "type": "Feature",
  "properties": {
    "gn:admin1_code":"19.0",
    "gn:admin2_code":"583.0",
    "gn:asciiname":"Kupla",
    "gn:country_code":"IN",
    "gn:dem":941,
    "gn:feature_class":"P",
    "gn:feature_code":"PPL",
    "gn:name":"Kupla",
    "gn:population":0,
    "gn:timezone":"Asia/Kolkata",
    "iso:country":"IN",
    "wof:name":"Kupla",
    "wof:placetype":"locality"
},
  "geometry": {"coordinates":[77.63264000000002,13.25788],"type":"Point"}
}