{
  "type": "Feature",
  "properties": {
    "iso:country":"IN",
    "ks:ks_name":"Baluwa",
    "ks:ks_pop":290,
    "ks:ks_type":"HABITATION",
    "name:eng_x_preferred":[
        "Baluwa"
    ],
    "wof:name":"Baluwa",
    "wof:placetype":"locality",
    "wof:population":290
},
  "geometry": {"coordinates":[82.92394299999999,27.151353],"type":"Point"}
}