{
  "type": "Feature",
  "properties": {
    "iso:country":"IN",
    "ks:ks_name":"Adasahi",
    "ks:ks_pop":322,
    "ks:ks_type":"HABITATION",
    "name:eng_x_preferred":[
        "Adasahi"
    ],
    "wof:name":"Adasahi",
    "wof:placetype":"locality",
    "wof:population":322
},
  "geometry": {"coordinates":[86.10237499999999,21.478155],"type":"Point"}
}