{
  "type": "Feature",
  "properties": {
    "iso:country":"IN",
    "ks:ks_name":"Atwara Chak Kola",
    "ks:ks_pop":1776,
    "ks:ks_type":"VILLAGE",
    "ks:ks_uagg_main":0,
    "name:eng_x_preferred":[
        "Atwara Chak Kola"
    ],
    "wof:name":"Atwara Chak Kola",
    "wof:placetype":"neighbourhood",
    "wof:population":1776
},
  "geometry": {"coordinates":[80.181472,26.962178],"type":"Point"}
}