{
  "type": "Feature",
  "properties": {
    "iso:country":"IN",
    "ks:ks_name":"Noorpur",
    "ks:ks_pop":915,
    "ks:ks_type":"HABITATION",
    "name:eng_x_preferred":[
        "Noorpur"
    ],
    "wof:name":"Noorpur",
    "wof:placetype":"locality",
    "wof:population":915
},
  "geometry": {"coordinates":[76.010087,27.236566],"type":"Point"}
}