{
  "type": "Feature",
  "properties": {
    "gn:admin1_code":"37.0",
    "gn:admin2_code":"416.0",
    "gn:asciiname":"Paila",
    "gn:country_code":"IN",
    "gn:dem":272,
    "gn:feature_class":"P",
    "gn:feature_code":"PPL",
    "gn:name":"Paila",
    "gn:population":0,
    "gn:timezone":"Asia/Kolkata",
    "iso:country":"IN",
    "name:ara_x_preferred":[
        "\u0628\u0627\u064a\u0644\u0627"
    ],
    "name:jpn_x_preferred":[
        "\u30d1\u30a4\u30e9"
    ],
    "name:spa_x_preferred":[
        "Paila"
    ],
    "wof:name":"Paila",
    "wof:placetype":"locality"
},
  "geometry": {"coordinates":[81.52981,18.44726],"type":"Point"}
}