{
  "type": "Feature",
  "properties": {
    "iso:country":"IN",
    "ks:ks_name":"Dondapani",
    "ks:ks_pop":751,
    "ks:ks_type":"VILLAGE",
    "name:eng_x_preferred":[
        "Dondapani"
    ],
    "wof:name":"Dondapani",
    "wof:placetype":"locality",
    "wof:population":751
},
  "geometry": {"coordinates":[83.888609,22.717743],"type":"Point"}
}