{
  "type": "Feature",
  "properties": {
    "iso:country":"IN",
    "ks:ks_name":"Bada",
    "ks:ks_pop":386,
    "ks:ks_type":"VILLAGE",
    "name:eng_x_preferred":[
        "Bada"
    ],
    "wof:name":"Bada",
    "wof:placetype":"locality",
    "wof:population":386
},
  "geometry": {"coordinates":[83.42531,23.584359],"type":"Point"}
}