{
  "type": "Feature",
  "properties": {
    "gn:admin1_code":"35.0",
    "gn:admin2_code":"427.0",
    "gn:asciiname":"Magara",
    "gn:country_code":"IN",
    "gn:dem":458,
    "gn:feature_class":"P",
    "gn:feature_code":"PPL",
    "gn:name":"Magara",
    "gn:population":0,
    "gn:timezone":"Asia/Kolkata",
    "iso:country":"IN",
    "ks:ks_name":"Magra",
    "ks:ks_pop":572,
    "ks:ks_type":"HABITATION",
    "name:eng_x_preferred":[
        "Magra"
    ],
    "name:eng_x_variant":[
        "Magara"
    ],
    "wof:name":"Magra",
    "wof:placetype":"locality",
    "wof:population":572
},
  "geometry": {"coordinates":[79.063175,24.124887],"type":"Point"}
}