{
  "type": "Feature",
  "properties": {
    "gn:admin1_code":"16.0",
    "gn:admin2_code":"521",
    "gn:asciiname":"BioEnable Tech (Office)",
    "gn:country_code":"IN",
    "gn:dem":556,
    "gn:feature_class":"P",
    "gn:feature_code":"PPL",
    "gn:name":"BioEnable Tech (Office)",
    "gn:population":0,
    "gn:timezone":"Asia/Kolkata",
    "iso:country":"IN",
    "wof:name":"BioEnable Tech (Office)",
    "wof:placetype":"locality"
},
  "geometry": {"coordinates":[73.89715,18.53203],"type":"Point"}
}