{
  "type": "Feature",
  "properties": {
    "gn:admin1_code":"39.0",
    "gn:admin2_code":"64.0",
    "gn:asciiname":"Pabhya Chak",
    "gn:country_code":"IN",
    "gn:dem":1224,
    "gn:feature_class":"P",
    "gn:feature_code":"PPL",
    "gn:name":"Pabhya Chak",
    "gn:population":0,
    "gn:timezone":"Asia/Kolkata",
    "iso:country":"IN",
    "wof:name":"Pabhya Chak",
    "wof:placetype":"locality"
},
  "geometry": {"coordinates":[79.89187,29.68966],"type":"Point"}
}