{
  "type": "Feature",
  "properties": {
    "iso:country":"IN",
    "ks:ks_alt_nam":"Teachers colony",
    "ks:ks_name":"Teachers Colony",
    "ks:ks_pop":508,
    "ks:ks_type":"HABITATION",
    "ks:ks_uagg_main":0,
    "name:eng_x_preferred":[
        "Teachers Colony"
    ],
    "wof:name":"Teachers Colony",
    "wof:placetype":"neighbourhood",
    "wof:population":508
},
  "geometry": {"coordinates":[77.47194500000001,8.226335],"type":"Point"}
}