{
  "type": "Feature",
  "properties": {
    "gn:admin1_code":"36.0",
    "gn:admin2_code":"158.0",
    "gn:asciiname":"Chilauli",
    "gn:country_code":"IN",
    "gn:dem":116,
    "gn:feature_class":"P",
    "gn:feature_code":"PPL",
    "gn:name":"Chilauli",
    "gn:population":0,
    "gn:timezone":"Asia/Kolkata",
    "iso:country":"IN",
    "ks:ks_name":"Chiluli",
    "ks:ks_pop":2770,
    "ks:ks_type":"VILLAGE",
    "name:eng_x_preferred":[
        "Chiluli"
    ],
    "name:eng_x_variant":[
        "Chilauli"
    ],
    "wof:name":"Chiluli",
    "wof:placetype":"locality",
    "wof:population":2770
},
  "geometry": {"coordinates":[81.44977400000001,26.414481],"type":"Point"}
}