{
  "type": "Feature",
  "properties": {
    "iso:country":"IN",
    "ks:ks_name":"Gandhia No.2",
    "ks:ks_pop":323,
    "ks:ks_type":"VILLAGE",
    "name:eng_x_preferred":[
        "Gandhia No.2"
    ],
    "wof:name":"Gandhia No.2",
    "wof:placetype":"locality",
    "wof:population":323
},
  "geometry": {"coordinates":[93.96656400000001,27.001629],"type":"Point"}
}