{
  "type": "Feature",
  "properties": {
    "iso:country":"IN",
    "ks:ks_name":"Pyasi Ka Pruwa",
    "ks:ks_pop":209,
    "ks:ks_type":"HABITATION",
    "name:eng_x_preferred":[
        "Pyasi Ka Pruwa"
    ],
    "wof:name":"Pyasi Ka Pruwa",
    "wof:placetype":"locality",
    "wof:population":209
},
  "geometry": {"coordinates":[80.520574,25.858654],"type":"Point"}
}