{
  "type": "Feature",
  "properties": {
    "iso:country":"IN",
    "ks:ks_name":"Krupasingi",
    "ks:ks_pop":18,
    "ks:ks_type":"HABITATION",
    "name:eng_x_preferred":[
        "Krupasingi"
    ],
    "wof:name":"Krupasingi",
    "wof:placetype":"locality",
    "wof:population":18
},
  "geometry": {"coordinates":[84.275048,19.074584],"type":"Point"}
}