{
  "type": "Feature",
  "properties": {
    "iso:country":"IN",
    "ks:ks_name":"Melaputhoor",
    "ks:ks_pop":594,
    "ks:ks_type":"HABITATION",
    "ks:ks_uagg_main":0,
    "name:eng_x_preferred":[
        "Melaputhoor"
    ],
    "wof:name":"Melaputhoor",
    "wof:placetype":"neighbourhood",
    "wof:population":594
},
  "geometry": {"coordinates":[77.39851299999999,8.11442],"type":"Point"}
}