{
  "type": "Feature",
  "properties": {
    "gn:admin1_code":"34.0",
    "gn:admin2_code":"203.0",
    "gn:asciiname":"Belwa",
    "gn:country_code":"IN",
    "gn:dem":96,
    "gn:feature_class":"P",
    "gn:feature_code":"PPL",
    "gn:name":"Belwa",
    "gn:population":0,
    "gn:timezone":"Asia/Kolkata",
    "iso:country":"IN",
    "name:new_x_preferred":[
        "\u092c\u0947\u0932\u0935\u093e"
    ],
    "wof:name":"Belwa",
    "wof:placetype":"locality"
},
  "geometry": {"coordinates":[84.47171,27.19689],"type":"Point"}
}