{
  "type": "Feature",
  "properties": {
    "iso:country":"IN",
    "ks:ks_name":"Kamarpal",
    "ks:ks_pop":526,
    "ks:ks_type":"VILLAGE",
    "name:eng_x_preferred":[
        "Kamarpal"
    ],
    "wof:name":"Kamarpal",
    "wof:placetype":"locality",
    "wof:population":526
},
  "geometry": {"coordinates":[86.630296,22.034222],"type":"Point"}
}