{
  "type": "Feature",
  "properties": {
    "gn:admin1_code":"23.0",
    "gn:admin2_code":"35.0",
    "gn:asciiname":"Tharial",
    "gn:country_code":"IN",
    "gn:dem":360,
    "gn:feature_class":"P",
    "gn:feature_code":"PPL",
    "gn:name":"Thari\u0101l",
    "gn:population":0,
    "gn:timezone":"Asia/Kolkata",
    "iso:country":"IN",
    "name:hin_x_preferred":[
        "\u0925\u0930\u093f\u092f\u093e\u0932"
    ],
    "wof:name":"Tharial",
    "wof:placetype":"locality"
},
  "geometry": {"coordinates":[75.60668000000003,32.3544],"type":"Point"}
}