{
  "type": "Feature",
  "properties": {
    "iso:country":"IN",
    "ks:ks_name":"Bazic Chak",
    "ks:ks_pop":0,
    "ks:ks_type":"VILLAGE",
    "name:eng_x_preferred":[
        "Bazic Chak"
    ],
    "wof:name":"Bazic Chak",
    "wof:placetype":"locality",
    "wof:population":0
},
  "geometry": {"coordinates":[84.045227,25.269123],"type":"Point"}
}