{
  "type": "Feature",
  "properties": {
    "iso:country":"IN",
    "ks:ks_name":"Bhitardarlabeda",
    "ks:ks_pop":46,
    "ks:ks_type":"VILLAGE",
    "name:eng_x_preferred":[
        "Bhitardarlabeda"
    ],
    "wof:name":"Bhitardarlabeda",
    "wof:placetype":"locality",
    "wof:population":46
},
  "geometry": {"coordinates":[82.27042299999999,18.275336],"type":"Point"}
}