{
  "type": "Feature",
  "properties": {
    "gn:admin1_code":"39",
    "gn:admin2_code":"61.0",
    "gn:asciiname":"Khairgaon",
    "gn:country_code":"IN",
    "gn:dem":1313,
    "gn:feature_class":"P",
    "gn:feature_code":"PPL",
    "gn:name":"Khairgaon",
    "gn:population":0,
    "gn:timezone":"Asia/Kolkata",
    "iso:country":"IN",
    "ks:ks_name":"Kher Gaon",
    "ks:ks_pop":212,
    "ks:ks_type":"VILLAGE",
    "name:eng_x_preferred":[
        "Kher Gaon"
    ],
    "name:eng_x_variant":[
        "Khairgaon"
    ],
    "wof:name":"Kher Gaon",
    "wof:placetype":"locality",
    "wof:population":212
},
  "geometry": {"coordinates":[78.859368,29.906766],"type":"Point"}
}