{
  "type": "Feature",
  "properties": {
    "iso:country":"IN",
    "ks:ks_name":"Majan Manikram",
    "ks:ks_pop":454,
    "ks:ks_type":"HABITATION",
    "name:eng_x_preferred":[
        "Majan Manikram"
    ],
    "wof:name":"Majan Manikram",
    "wof:placetype":"locality",
    "wof:population":454
},
  "geometry": {"coordinates":[82.000906,24.707587],"type":"Point"}
}