{
  "type": "Feature",
  "properties": {
    "iso:country":"IN",
    "ks:ks_name":"Padrapani",
    "ks:ks_pop":251,
    "ks:ks_type":"HABITATION",
    "name:eng_x_preferred":[
        "Padrapani"
    ],
    "wof:name":"Padrapani",
    "wof:placetype":"locality",
    "wof:population":251
},
  "geometry": {"coordinates":[84.597296,22.900384],"type":"Point"}
}