{
  "type": "Feature",
  "properties": {
    "gn:admin1_code":"36",
    "gn:admin2_code":"170.0",
    "gn:asciiname":"Modikuan",
    "gn:country_code":"IN",
    "gn:dem":131,
    "gn:feature_class":"P",
    "gn:feature_code":"PPL",
    "gn:name":"Mod\u012bku\u0101n",
    "gn:population":0,
    "gn:timezone":"Asia/Kolkata",
    "iso:country":"IN",
    "name:eng_x_preferred":[
        "Mod\u012bku\u0101n"
    ],
    "wof:name":"Modikuan",
    "wof:placetype":"locality"
},
  "geometry": {"coordinates":[80.22798,25.43422],"type":"Point"}
}