{
  "type": "Feature",
  "properties": {
    "iso:country":"IN",
    "ks:ks_name":"Surendra Nagar",
    "ks:ks_pop":862,
    "ks:ks_type":"HABITATION",
    "name:eng_x_preferred":[
        "Surendra Nagar"
    ],
    "wof:name":"Surendra Nagar",
    "wof:placetype":"locality",
    "wof:population":862
},
  "geometry": {"coordinates":[88.71125499999999,22.240002],"type":"Point"}
}