{
  "type": "Feature",
  "properties": {
    "gn:admin1_code":"11",
    "gn:admin2_code":"28.0",
    "gn:asciiname":"Gariali",
    "gn:country_code":"IN",
    "gn:dem":532,
    "gn:feature_class":"P",
    "gn:feature_code":"PPL",
    "gn:name":"Gari\u0101li",
    "gn:population":0,
    "gn:timezone":"Asia/Kolkata",
    "iso:country":"IN",
    "wof:name":"Gariali",
    "wof:placetype":"locality"
},
  "geometry": {"coordinates":[76.40191999999998,31.75941],"type":"Point"}
}