{
  "type": "Feature",
  "properties": {
    "iso:country":"IN",
    "ks:ks_name":"Kadavathu",
    "ks:ks_pop":812,
    "ks:ks_type":"HABITATION",
    "name:eng_x_preferred":[
        "Kadavathu"
    ],
    "wof:name":"Kadavathu",
    "wof:placetype":"locality",
    "wof:population":812
},
  "geometry": {"coordinates":[75.98695499999999,11.027936],"type":"Point"}
}