{
  "type": "Feature",
  "properties": {
    "gn:admin1_code":"36.0",
    "gn:admin2_code":"175.0",
    "gn:asciiname":"Someshwar Mahadev",
    "gn:country_code":"IN",
    "gn:dem":92,
    "gn:feature_class":"P",
    "gn:feature_code":"PPL",
    "gn:name":"Someshwar Mah\u0101dev",
    "gn:population":0,
    "gn:timezone":"Asia/Kolkata",
    "iso:country":"IN",
    "wof:name":"Someshwar Mahadev",
    "wof:placetype":"locality"
},
  "geometry": {"coordinates":[81.89075,25.40723],"type":"Point"}
}