{
  "type": "Feature",
  "properties": {
    "gn:admin1_code":"25.0",
    "gn:admin2_code":"612.0",
    "gn:asciiname":"Pattiveeranpatti",
    "gn:country_code":"IN",
    "gn:dem":265,
    "gn:feature_class":"P",
    "gn:feature_code":"PPL",
    "gn:name":"Pattiveeranpatti",
    "gn:population":0,
    "gn:timezone":"Asia/Kolkata",
    "iso:country":"IN",
    "name:bpy_x_preferred":[
        "\u09aa\u09be\u09a4\u09cd\u09a4\u09bf\u09ac\u09c0\u09b0\u09a8\u09aa\u09be\u09a4\u09cd\u09a4\u09bf"
    ],
    "name:ceb_x_preferred":[
        "Pattiveeranpatti"
    ],
    "name:ita_x_preferred":[
        "Pattiveeranpatti"
    ],
    "name:msa_x_preferred":[
        "Pattiveeranpatti"
    ],
    "name:nld_x_preferred":[
        "Pattiveeranpatti"
    ],
    "name:por_x_preferred":[
        "Pattiveeranpatti"
    ],
    "name:swe_x_preferred":[
        "Pattiveeranpatti"
    ],
    "name:tam_x_preferred":[
        "\u0baa\u0b9f\u0bcd\u0b9f\u0bbf\u0bb5\u0bc0\u0bb0\u0ba9\u0bcd\u0baa\u0b9f\u0bcd\u0b9f\u0bbf"
    ],
    "name:vie_x_preferred":[
        "Pattiveeranpatti"
    ],
    "name:zho_x_preferred":[
        "\u5e15\u8482\u97e6\u57c3\u5170\u5e15\u8482"
    ],
    "wof:name":"Pattiveeranpatti",
    "wof:placetype":"neighbourhood"
},
  "geometry": {"coordinates":[77.76089,10.21226],"type":"Point"}
}