{
  "type": "Feature",
  "properties": {
    "iso:country":"IN",
    "ks:ks_name":"Chipakur",
    "ks:ks_pop":664,
    "ks:ks_type":"HABITATION",
    "name:eng_x_preferred":[
        "Chipakur"
    ],
    "wof:name":"Chipakur",
    "wof:placetype":"locality",
    "wof:population":664
},
  "geometry": {"coordinates":[82.264931,18.674075],"type":"Point"}
}