{
  "type": "Feature",
  "properties": {
    "iso:country":"IN",
    "ks:ks_name":"Panipat Taraf Afghan",
    "ks:ks_pop":1653,
    "ks:ks_type":"VILLAGE",
    "ks:ks_uagg_main":0,
    "name:eng_x_preferred":[
        "Panipat Taraf Afghan"
    ],
    "wof:name":"Panipat Taraf Afghan",
    "wof:placetype":"neighbourhood",
    "wof:population":1653
},
  "geometry": {"coordinates":[76.98821599999999,29.371972],"type":"Point"}
}