{
  "type": "Feature",
  "properties": {
    "gn:admin1_code":"19.0",
    "gn:admin2_code":"577.0",
    "gn:asciiname":"Kattepur",
    "gn:country_code":"IN",
    "gn:dem":644,
    "gn:feature_class":"P",
    "gn:feature_code":"PPL",
    "gn:name":"Kattep\u016br",
    "gn:population":0,
    "gn:timezone":"Asia/Kolkata",
    "iso:country":"IN",
    "wof:name":"Kattepur",
    "wof:placetype":"locality"
},
  "geometry": {"coordinates":[77.02653000000002,12.22859],"type":"Point"}
}