{
  "type": "Feature",
  "properties": {
    "gn:admin1_code":"16",
    "gn:admin2_code":"511.0",
    "gn:asciiname":"Khurgaon",
    "gn:country_code":"IN",
    "gn:dem":357,
    "gn:feature_class":"P",
    "gn:feature_code":"PPL",
    "gn:name":"Khurgaon",
    "gn:population":0,
    "gn:timezone":"Asia/Kolkata",
    "iso:country":"IN",
    "ks:ks_name":"Khurgaon",
    "ks:ks_pop":1130,
    "ks:ks_type":"VILLAGE",
    "name:eng_x_preferred":[
        "Khurgaon"
    ],
    "wof:name":"Khurgaon",
    "wof:placetype":"locality",
    "wof:population":1130
},
  "geometry": {"coordinates":[77.30175800000001,19.229509],"type":"Point"}
}