{
  "type": "Feature",
  "properties": {
    "gn:admin1_code":"19.0",
    "gn:admin2_code":"571.0",
    "gn:asciiname":"Chikkanahalli",
    "gn:country_code":"IN",
    "gn:dem":718,
    "gn:feature_class":"P",
    "gn:feature_code":"PPL",
    "gn:name":"Chikkanahalli",
    "gn:population":0,
    "gn:timezone":"Asia/Kolkata",
    "iso:country":"IN",
    "wof:name":"Chikkanahalli",
    "wof:placetype":"locality"
},
  "geometry": {"coordinates":[77.32574,13.5682],"type":"Point"}
}