{
  "type": "Feature",
  "properties": {
    "iso:country":"IN",
    "ks:ks_name":"Hirasol",
    "ks:ks_pop":397,
    "ks:ks_type":"HABITATION",
    "name:eng_x_preferred":[
        "Hirasol"
    ],
    "wof:name":"Hirasol",
    "wof:placetype":"locality",
    "wof:population":397
},
  "geometry": {"coordinates":[87.262501,22.631371],"type":"Point"}
}