{
  "type": "Feature",
  "properties": {
    "gn:admin1_code":"35.0",
    "gn:admin2_code":"441.0",
    "gn:asciiname":"Sekat Mohali",
    "gn:country_code":"IN",
    "gn:dem":383,
    "gn:feature_class":"P",
    "gn:feature_code":"PPL",
    "gn:name":"Sekat Moh\u0101li",
    "gn:population":0,
    "gn:timezone":"Asia/Kolkata",
    "iso:country":"IN",
    "ks:ks_name":"Sekatmuhali",
    "ks:ks_pop":988,
    "ks:ks_type":"VILLAGE",
    "name:eng_x_preferred":[
        "Sekatmuhali"
    ],
    "name:eng_x_variant":[
        "Sekat Mohali"
    ],
    "wof:name":"Sekatmuhali",
    "wof:placetype":"locality",
    "wof:population":988
},
  "geometry": {"coordinates":[75.053376,21.737314],"type":"Point"}
}