{
  "type": "Feature",
  "properties": {
    "gn:admin1_code":"2",
    "gn:admin2_code":"545.0",
    "gn:asciiname":"Chilakamamidi",
    "gn:country_code":"IN",
    "gn:dem":244,
    "gn:feature_class":"P",
    "gn:feature_code":"PPL",
    "gn:name":"Chilak\u0101m\u0101midi",
    "gn:population":0,
    "gn:timezone":"Asia/Kolkata",
    "iso:country":"IN",
    "ks:ks_name":"Chilakamamidi",
    "ks:ks_pop":496,
    "ks:ks_type":"HABITATION",
    "name:eng_x_preferred":[
        "Chilakamamidi"
    ],
    "wof:name":"Chilakamamidi",
    "wof:placetype":"locality",
    "wof:population":496
},
  "geometry": {"coordinates":[81.76397299999999,17.483917],"type":"Point"}
}