{
  "type": "Feature",
  "properties": {
    "iso:country":"IN",
    "ks:ks_name":"Borha",
    "ks:ks_pop":510,
    "ks:ks_type":"HABITATION",
    "name:eng_x_preferred":[
        "Borha"
    ],
    "wof:name":"Borha",
    "wof:placetype":"locality",
    "wof:population":510
},
  "geometry": {"coordinates":[84.37854,23.562765],"type":"Point"}
}