{
  "type": "Feature",
  "properties": {
    "gn:admin1_code":"33",
    "gn:asciiname":"Terekhol",
    "gn:country_code":"IN",
    "gn:dem":66,
    "gn:feature_class":"P",
    "gn:feature_code":"PPL",
    "gn:name":"Terekhol",
    "gn:population":0,
    "gn:timezone":"Asia/Kolkata",
    "iso:country":"IN",
    "name:und_x_variant":[
        "Tirakul Fort",
        "Tiracol",
        "Terekhol"
    ],
    "wof:name":"Terekhol",
    "wof:placetype":"locality"
},
  "geometry": {"coordinates":[73.68281,15.73092],"type":"Point"}
}