{
  "type": "Feature",
  "properties": {
    "iso:country":"IN",
    "ks:ks_name":"Malligenahalli",
    "ks:ks_pop":49,
    "ks:ks_type":"HABITATION",
    "name:eng_x_preferred":[
        "Malligenahalli"
    ],
    "wof:name":"Malligenahalli",
    "wof:placetype":"locality",
    "wof:population":49
},
  "geometry": {"coordinates":[76.00165800000001,13.353995],"type":"Point"}
}