{
  "type": "Feature",
  "properties": {
    "gn:admin1_code":"36",
    "gn:admin2_code":"179.0",
    "gn:asciiname":"Bharsare",
    "gn:country_code":"IN",
    "gn:dem":96,
    "gn:feature_class":"P",
    "gn:feature_code":"PPL",
    "gn:name":"Bhars\u0101re",
    "gn:population":0,
    "gn:timezone":"Asia/Kolkata",
    "iso:country":"IN",
    "wof:name":"Bharsare",
    "wof:placetype":"locality"
},
  "geometry": {"coordinates":[82.33935,26.30993],"type":"Point"}
}