{
  "type": "Feature",
  "properties": {
    "gn:admin1_code":"24",
    "gn:admin2_code":"117.0",
    "gn:asciiname":"Mawal",
    "gn:country_code":"IN",
    "gn:dem":239,
    "gn:feature_class":"P",
    "gn:feature_code":"PPL",
    "gn:name":"Maw\u0101l",
    "gn:population":0,
    "gn:timezone":"Asia/Kolkata",
    "iso:country":"IN",
    "name:und_x_variant":[
        "Maw\u0101l",
        "M\u0101w\u0101l"
    ],
    "wof:name":"Mawal",
    "wof:placetype":"locality"
},
  "geometry": {"coordinates":[72.71177,24.43932],"type":"Point"}
}