{
  "type": "Feature",
  "properties": {
    "iso:country":"IN",
    "ks:ks_name":"Sejanya",
    "ks:ks_pop":373,
    "ks:ks_type":"VILLAGE",
    "name:eng_x_preferred":[
        "Sejanya"
    ],
    "wof:name":"Sejanya",
    "wof:placetype":"locality",
    "wof:population":373
},
  "geometry": {"coordinates":[77.07550000000001,24.256247],"type":"Point"}
}