{
  "type": "Feature",
  "properties": {
    "gn:admin1_code":"36",
    "gn:admin2_code":"136.0",
    "gn:asciiname":"Seifni",
    "gn:country_code":"IN",
    "gn:dem":192,
    "gn:feature_class":"P",
    "gn:feature_code":"PPL",
    "gn:name":"Seifni",
    "gn:population":0,
    "gn:timezone":"Asia/Kolkata",
    "iso:country":"IN",
    "wof:name":"Seifni",
    "wof:placetype":"locality"
},
  "geometry": {"coordinates":[78.89109000000001,28.65442],"type":"Point"}
}