{
  "type": "Feature",
  "properties": {
    "iso:country":"IN",
    "ks:ks_name":"Manniladam",
    "ks:ks_pop":715,
    "ks:ks_type":"HABITATION",
    "name:eng_x_preferred":[
        "Manniladam"
    ],
    "wof:name":"Manniladam",
    "wof:placetype":"locality",
    "wof:population":715
},
  "geometry": {"coordinates":[75.91982400000001,11.319477],"type":"Point"}
}