{
  "type": "Feature",
  "properties": {
    "iso:country":"IN",
    "ks:ks_name":"Ramchandarpur",
    "ks:ks_pop":703,
    "ks:ks_type":"VILLAGE",
    "name:eng_x_preferred":[
        "Ramchandarpur"
    ],
    "wof:name":"Ramchandarpur",
    "wof:placetype":"locality",
    "wof:population":703
},
  "geometry": {"coordinates":[85.67895799999999,22.10583],"type":"Point"}
}