{
  "type": "Feature",
  "properties": {
    "gn:admin1_code":"29",
    "gn:admin2_code":"244.0",
    "gn:asciiname":"Lingtam",
    "gn:country_code":"IN",
    "gn:dem":1130,
    "gn:feature_class":"P",
    "gn:feature_code":"PPL",
    "gn:name":"Lingt\u0101m",
    "gn:population":0,
    "gn:timezone":"Asia/Kolkata",
    "iso:country":"IN",
    "wof:name":"Lingtam",
    "wof:placetype":"locality"
},
  "geometry": {"coordinates":[88.71257,27.25457],"type":"Point"}
}