{
  "type": "Feature",
  "properties": {
    "gn:admin1_code":"30.0",
    "gn:admin2_code":"246.0",
    "gn:asciiname":"Sicham",
    "gn:country_code":"IN",
    "gn:dem":1017,
    "gn:feature_class":"P",
    "gn:feature_code":"PPL",
    "gn:name":"Sicham",
    "gn:population":0,
    "gn:timezone":"Asia/Kolkata",
    "iso:country":"IN",
    "wof:name":"Sicham",
    "wof:placetype":"locality"
},
  "geometry": {"coordinates":[92.57671999999999,27.14354],"type":"Point"}
}