{
  "type": "Feature",
  "properties": {
    "iso:country":"IN",
    "ks:ks_name":"Mahulia Tola",
    "ks:ks_pop":360,
    "ks:ks_type":"HABITATION",
    "name:eng_x_preferred":[
        "Mahulia Tola"
    ],
    "wof:name":"Mahulia Tola",
    "wof:placetype":"locality",
    "wof:population":360
},
  "geometry": {"coordinates":[82.961088,24.663084],"type":"Point"}
}