{
  "type": "Feature",
  "properties": {
    "gn:admin1_code":"35.0",
    "gn:admin2_code":"422.0",
    "gn:asciiname":"Ikauna",
    "gn:country_code":"IN",
    "gn:dem":196,
    "gn:feature_class":"P",
    "gn:feature_code":"PPL",
    "gn:name":"Ikauna",
    "gn:population":0,
    "gn:timezone":"Asia/Kolkata",
    "iso:country":"IN",
    "wof:name":"Ikauna",
    "wof:placetype":"locality"
},
  "geometry": {"coordinates":[78.49533000000002,25.81349],"type":"Point"}
}