{
  "type": "Feature",
  "properties": {
    "iso:country":"IN",
    "ks:ks_name":"Simaldi",
    "ks:ks_pop":143,
    "ks:ks_type":"HABITATION",
    "name:eng_x_preferred":[
        "Simaldi"
    ],
    "wof:name":"Simaldi",
    "wof:placetype":"locality",
    "wof:population":143
},
  "geometry": {"coordinates":[87.18805,24.121553],"type":"Point"}
}