{
  "type": "Feature",
  "properties": {
    "gn:admin1_code":"12.0",
    "gn:asciiname":"Sonawa",
    "gn:country_code":"IN",
    "gn:dem":724,
    "gn:feature_class":"P",
    "gn:feature_code":"PPL",
    "gn:name":"Son\u0101wa",
    "gn:population":0,
    "gn:timezone":"Asia/Kolkata",
    "iso:country":"IN",
    "name:und_x_variant":[
        "Son\u0101wa",
        "Soh\u0101wa"
    ],
    "wof:name":"Sonawa",
    "wof:placetype":"locality"
},
  "geometry": {"coordinates":[74.11886,33.19962],"type":"Point"}
}