{
  "type": "Feature",
  "properties": {
    "iso:country":"IN",
    "ks:ks_name":"Maroda",
    "ks:ks_pop":107,
    "ks:ks_type":"VILLAGE",
    "name:eng_x_preferred":[
        "Maroda"
    ],
    "wof:name":"Maroda",
    "wof:placetype":"locality",
    "wof:population":107
},
  "geometry": {"coordinates":[78.55310799999999,30.197472],"type":"Point"}
}