{
  "type": "Feature",
  "properties": {
    "gn:admin1_code":"11",
    "gn:admin2_code":"23.0",
    "gn:asciiname":"Mathi",
    "gn:country_code":"IN",
    "gn:dem":2110,
    "gn:feature_class":"P",
    "gn:feature_code":"PPL",
    "gn:name":"Mathi",
    "gn:population":0,
    "gn:timezone":"Asia/Kolkata",
    "iso:country":"IN",
    "name:azb_x_preferred":[
        "\u0645\u0627\u062a\u06cc"
    ],
    "name:bel_x_preferred":[
        "\u041c\u0430\u0446\u0456"
    ],
    "name:bul_x_preferred":[
        "\u041c\u0430\u0442\u0438"
    ],
    "name:ceb_x_preferred":[
        "Mathi"
    ],
    "name:deu_x_preferred":[
        "Mathi"
    ],
    "name:epo_x_preferred":[
        "Mathi"
    ],
    "name:eus_x_preferred":[
        "Mathi"
    ],
    "name:fas_x_preferred":[
        "\u0645\u0627\u062a\u06cc"
    ],
    "name:fra_x_preferred":[
        "Mathi"
    ],
    "name:hun_x_preferred":[
        "Mathi"
    ],
    "name:hye_x_preferred":[
        "\u0544\u0561\u057f\u056b"
    ],
    "name:ind_x_preferred":[
        "Mathi"
    ],
    "name:ita_x_preferred":[
        "Mathi"
    ],
    "name:jpn_x_preferred":[
        "\u30de\u30fc\u30c6\u30a3"
    ],
    "name:kaz_x_preferred":[
        "\u041c\u0430\u0442\u0438"
    ],
    "name:lat_x_preferred":[
        "Matiga"
    ],
    "name:lmo_x_preferred":[
        "Mathi"
    ],
    "name:msa_x_preferred":[
        "Mathi"
    ],
    "name:nap_x_preferred":[
        "Mathi"
    ],
    "name:nld_x_preferred":[
        "Mathi"
    ],
    "name:pms_x_preferred":[
        "Mati"
    ],
    "name:pol_x_preferred":[
        "Mathi"
    ],
    "name:por_x_preferred":[
        "Mathi"
    ],
    "name:ron_x_preferred":[
        "Mathi"
    ],
    "name:rus_x_preferred":[
        "\u041c\u0430\u0442\u0438"
    ],
    "name:scn_x_preferred":[
        "Mathi"
    ],
    "name:spa_x_preferred":[
        "Mathi"
    ],
    "name:srp_x_preferred":[
        "\u041c\u0430\u0442\u0438"
    ],
    "name:swe_x_preferred":[
        "Mathi"
    ],
    "name:tgl_x_preferred":[
        "Mathi"
    ],
    "name:ukr_x_preferred":[
        "\u041c\u0430\u0442\u0456"
    ],
    "name:uzb_x_preferred":[
        "Mathi"
    ],
    "name:vie_x_preferred":[
        "Mathi"
    ],
    "name:vol_x_preferred":[
        "Mathi"
    ],
    "name:war_x_preferred":[
        "Mathi"
    ],
    "name:zho_x_preferred":[
        "\u9a6c\u7279\u4f0a"
    ],
    "wof:name":"Mathi",
    "wof:placetype":"locality"
},
  "geometry": {"coordinates":[76.10463,32.78902],"type":"Point"}
}