{
  "type": "Feature",
  "properties": {
    "gn:admin1_code":"35.0",
    "gn:admin2_code":"455.0",
    "gn:asciiname":"Ambara",
    "gn:country_code":"IN",
    "gn:dem":821,
    "gn:feature_class":"P",
    "gn:feature_code":"PPL",
    "gn:name":"Ambara",
    "gn:population":0,
    "gn:timezone":"Asia/Kolkata",
    "iso:country":"IN",
    "ks:ks_alt_nam":"Ambara",
    "ks:ks_name":"Ambada",
    "ks:ks_pop":6892,
    "ks:ks_type":"URBAN",
    "ks:ks_uagg_main":0,
    "name:eng_x_preferred":[
        "Ambada"
    ],
    "name:eng_x_variant":[
        "Ambara"
    ],
    "wof:name":"Ambada",
    "wof:placetype":"neighbourhood",
    "wof:population":6892
},
  "geometry": {"coordinates":[78.67079099999999,22.190224],"type":"Point"}
}