{
  "type": "Feature",
  "properties": {
    "iso:country":"IN",
    "ks:ks_name":"Banshakathjuri",
    "ks:ks_pop":0,
    "ks:ks_type":"VILLAGE",
    "name:eng_x_preferred":[
        "Banshakathjuri"
    ],
    "wof:name":"Banshakathjuri",
    "wof:placetype":"locality",
    "wof:population":0
},
  "geometry": {"coordinates":[86.346161,23.999835],"type":"Point"}
}