{
  "type": "Feature",
  "properties": {
    "iso:country":"IN",
    "ks:ks_name":"Rongpur Pt VII",
    "ks:ks_pop":547,
    "ks:ks_type":"VILLAGE",
    "name:eng_x_preferred":[
        "Rongpur Pt VII"
    ],
    "wof:name":"Rongpur Pt VII",
    "wof:placetype":"locality",
    "wof:population":547
},
  "geometry": {"coordinates":[92.576628,24.501951],"type":"Point"}
}