{
  "type": "Feature",
  "properties": {
    "gn:admin1_code":"34.0",
    "gn:admin2_code":"222.0",
    "gn:asciiname":"Karaitanr",
    "gn:country_code":"IN",
    "gn:dem":45,
    "gn:feature_class":"P",
    "gn:feature_code":"PPL",
    "gn:name":"Karait\u0101nr",
    "gn:population":0,
    "gn:timezone":"Asia/Kolkata",
    "iso:country":"IN",
    "ks:ks_name":"Karaitanr",
    "ks:ks_pop":1002,
    "ks:ks_type":"VILLAGE",
    "name:eng_x_preferred":[
        "Karaitanr"
    ],
    "wof:name":"Karaitanr",
    "wof:placetype":"locality",
    "wof:population":1002
},
  "geometry": {"coordinates":[86.248279,25.560972],"type":"Point"}
}