{
  "type": "Feature",
  "properties": {
    "iso:country":"IN",
    "ks:ks_name":"Kattige",
    "ks:ks_pop":61,
    "ks:ks_type":"HABITATION",
    "name:eng_x_preferred":[
        "Kattige"
    ],
    "wof:name":"Kattige",
    "wof:placetype":"locality",
    "wof:population":61
},
  "geometry": {"coordinates":[74.609193,14.969141],"type":"Point"}
}