{
  "type": "Feature",
  "properties": {
    "gn:admin1_code":"39.0",
    "gn:admin2_code":"64.0",
    "gn:asciiname":"Chhatola",
    "gn:country_code":"IN",
    "gn:dem":1695,
    "gn:feature_class":"P",
    "gn:feature_code":"PPL",
    "gn:name":"Chhatola",
    "gn:population":0,
    "gn:timezone":"Asia/Kolkata",
    "iso:country":"IN",
    "ks:ks_name":"Chhatola",
    "ks:ks_type":"VILLAGE",
    "name:eng_x_preferred":[
        "Chhatola"
    ],
    "wof:name":"Chhatola",
    "wof:placetype":"locality"
},
  "geometry": {"coordinates":[79.744658,29.579683],"type":"Point"}
}