{
  "type": "Feature",
  "properties": {
    "iso:country":"IN",
    "ks:ks_name":"Badamara",
    "ks:ks_pop":35,
    "ks:ks_type":"HABITATION",
    "name:eng_x_preferred":[
        "Badamara"
    ],
    "wof:name":"Badamara",
    "wof:placetype":"locality",
    "wof:population":35
},
  "geometry": {"coordinates":[84.705364,21.525793],"type":"Point"}
}