{
  "type": "Feature",
  "properties": {
    "gn:admin1_code":"11",
    "gn:admin2_code":"23.0",
    "gn:asciiname":"Shari",
    "gn:country_code":"IN",
    "gn:dem":1681,
    "gn:feature_class":"P",
    "gn:feature_code":"PPL",
    "gn:name":"Sh\u0101ri",
    "gn:population":0,
    "gn:timezone":"Asia/Kolkata",
    "iso:country":"IN",
    "name:ceb_x_preferred":[
        "Shari"
    ],
    "name:deu_x_preferred":[
        "Shari"
    ],
    "name:fra_x_preferred":[
        "Shari"
    ],
    "name:hrv_x_preferred":[
        "Shari"
    ],
    "name:nld_x_preferred":[
        "Shari"
    ],
    "name:rus_x_preferred":[
        "\u0428\u0430\u0440\u0438"
    ],
    "name:swe_x_preferred":[
        "Shari"
    ],
    "name:ukr_x_preferred":[
        "\u0428\u0430\u0440\u0456"
    ],
    "name:uzb_x_preferred":[
        "Shari"
    ],
    "wof:name":"Shari",
    "wof:placetype":"locality"
},
  "geometry": {"coordinates":[76.23477,32.56857],"type":"Point"}
}