{
  "type": "Feature",
  "properties": {
    "iso:country":"IN",
    "ks:ks_name":"Paratappura",
    "ks:ks_pop":268,
    "ks:ks_type":"VILLAGE",
    "name:eng_x_preferred":[
        "Paratappura"
    ],
    "wof:name":"Paratappura",
    "wof:placetype":"locality",
    "wof:population":268
},
  "geometry": {"coordinates":[78.530523,26.381311],"type":"Point"}
}