{
  "type": "Feature",
  "properties": {
    "iso:country":"IN",
    "ks:ks_alt_nam":"KESARIKHAS",
    "ks:ks_name":"Kesarikhas",
    "ks:ks_pop":1820,
    "ks:ks_type":"HABITATION",
    "name:eng_x_preferred":[
        "Kesarikhas"
    ],
    "wof:name":"Kesarikhas",
    "wof:placetype":"locality",
    "wof:population":1820
},
  "geometry": {"coordinates":[82.97717299999999,23.860818],"type":"Point"}
}