{
  "type": "Feature",
  "properties": {
    "gn:admin1_code":"16.0",
    "gn:admin2_code":"499.0",
    "gn:asciiname":"Adalsa",
    "gn:country_code":"IN",
    "gn:dem":327,
    "gn:feature_class":"P",
    "gn:feature_code":"PPL",
    "gn:name":"\u0100dalsa",
    "gn:population":0,
    "gn:timezone":"Asia/Kolkata",
    "iso:country":"IN",
    "wof:name":"Adalsa",
    "wof:placetype":"locality"
},
  "geometry": {"coordinates":[75.00581,20.65813],"type":"Point"}
}