{
  "type": "Feature",
  "properties": {
    "iso:country":"IN",
    "ks:ks_alt_nam":"Gowder colony",
    "ks:ks_name":"Gowder Colony",
    "ks:ks_pop":200,
    "ks:ks_type":"HABITATION",
    "name:eng_x_preferred":[
        "Gowder Colony"
    ],
    "wof:name":"Gowder Colony",
    "wof:placetype":"locality",
    "wof:population":200
},
  "geometry": {"coordinates":[76.739339,11.447077],"type":"Point"}
}