{
  "type": "Feature",
  "properties": {
    "gn:admin1_code":"37",
    "gn:admin2_code":"409.0",
    "gn:asciiname":"Kutelabhata",
    "gn:country_code":"IN",
    "gn:dem":297,
    "gn:feature_class":"P",
    "gn:feature_code":"PPL",
    "gn:name":"Kutel\u0101bh\u0101ta",
    "gn:population":0,
    "gn:timezone":"Asia/Kolkata",
    "iso:country":"IN",
    "ks:ks_alt_nam":"Kutel\u0101bh\u0101ta",
    "ks:ks_name":"Kutelabhata",
    "ks:ks_pop":1525,
    "ks:ks_type":"VILLAGE",
    "ks:ks_uagg_main":0,
    "name:eng_x_preferred":[
        "Kutelabhata"
    ],
    "name:eng_x_variant":[
        "Kutel\u0101bh\u0101ta"
    ],
    "wof:name":"Kutelabhata",
    "wof:placetype":"neighbourhood",
    "wof:population":1525
},
  "geometry": {"coordinates":[81.316715,21.237659],"type":"Point"}
}