{
  "type": "Feature",
  "properties": {
    "iso:country":"IN",
    "ks:ks_name":"Sidhumar",
    "ks:ks_pop":186,
    "ks:ks_type":"HABITATION",
    "name:eng_x_preferred":[
        "Sidhumar"
    ],
    "wof:name":"Sidhumar",
    "wof:placetype":"locality",
    "wof:population":186
},
  "geometry": {"coordinates":[83.33029399999999,22.47857],"type":"Point"}
}