{
  "type": "Feature",
  "properties": {
    "iso:country":"IN",
    "ks:ks_name":"Chanda Palla",
    "ks:ks_pop":40,
    "ks:ks_type":"HABITATION",
    "name:eng_x_preferred":[
        "Chanda Palla"
    ],
    "wof:name":"Chanda Palla",
    "wof:placetype":"locality",
    "wof:population":40
},
  "geometry": {"coordinates":[78.566362,29.837165],"type":"Point"}
}