{
  "type": "Feature",
  "properties": {
    "gn:admin1_code":"19.0",
    "gn:admin2_code":"570.0",
    "gn:asciiname":"Kumbarakoppa",
    "gn:country_code":"IN",
    "gn:dem":695,
    "gn:feature_class":"P",
    "gn:feature_code":"PPL",
    "gn:name":"Kumb\u0101rakoppa",
    "gn:population":0,
    "gn:timezone":"Asia/Kolkata",
    "iso:country":"IN",
    "ks:ks_alt_nam":"Kumb\u0101rakoppa",
    "ks:ks_name":"Kumbarakoppa",
    "ks:ks_type":"VILLAGE",
    "name:eng_x_preferred":[
        "Kumbarakoppa"
    ],
    "name:eng_x_variant":[
        "Kumb\u0101rakoppa"
    ],
    "wof:name":"Kumbarakoppa",
    "wof:placetype":"locality"
},
  "geometry": {"coordinates":[75.335905,13.565829],"type":"Point"}
}