{
  "type": "Feature",
  "properties": {
    "gn:admin1_code":"12.0",
    "gn:admin2_code":"004",
    "gn:asciiname":"Larchi Masjid",
    "gn:country_code":"IN",
    "gn:dem":2862,
    "gn:feature_class":"P",
    "gn:feature_code":"PPL",
    "gn:name":"Larchi Masjid",
    "gn:population":0,
    "gn:timezone":"Asia/Kolkata",
    "iso:country":"IN",
    "wof:name":"Larchi Masjid",
    "wof:placetype":"locality"
},
  "geometry": {"coordinates":[76.19583,34.50972],"type":"Point"}
}