{
  "type": "Feature",
  "properties": {
    "iso:country":"IN",
    "ks:ks_alt_nam":"SHANKAR BUX",
    "ks:ks_name":"Shankar Bux",
    "ks:ks_pop":109,
    "ks:ks_type":"HABITATION",
    "name:eng_x_preferred":[
        "Shankar Bux"
    ],
    "wof:name":"Shankar Bux",
    "wof:placetype":"locality",
    "wof:population":109
},
  "geometry": {"coordinates":[81.519768,26.286702],"type":"Point"}
}