{
  "type": "Feature",
  "properties": {
    "iso:country":"IN",
    "ks:ks_name":"Gaya Ka Purwa",
    "ks:ks_pop":110,
    "ks:ks_type":"HABITATION",
    "name:eng_x_preferred":[
        "Gaya Ka Purwa"
    ],
    "wof:name":"Gaya Ka Purwa",
    "wof:placetype":"locality",
    "wof:population":110
},
  "geometry": {"coordinates":[80.774278,25.447977],"type":"Point"}
}