{
  "type": "Feature",
  "properties": {
    "iso:country":"IN",
    "ks:ks_name":"Udma Tola",
    "ks:ks_pop":79,
    "ks:ks_type":"HABITATION",
    "name:eng_x_preferred":[
        "Udma Tola"
    ],
    "wof:name":"Udma Tola",
    "wof:placetype":"locality",
    "wof:population":79
},
  "geometry": {"coordinates":[85.797995,23.46237],"type":"Point"}
}