{
  "type": "Feature",
  "properties": {
    "gn:admin1_code":"19.0",
    "gn:admin2_code":"577.0",
    "gn:asciiname":"Banni Mantapam",
    "gn:country_code":"IN",
    "gn:dem":734,
    "gn:feature_class":"P",
    "gn:feature_code":"PPL",
    "gn:name":"Banni Mantapam",
    "gn:population":0,
    "gn:timezone":"Asia/Kolkata",
    "iso:country":"IN",
    "wof:name":"Banni Mantapam",
    "wof:placetype":"locality"
},
  "geometry": {"coordinates":[76.64867,12.33531],"type":"Point"}
}