{
  "type": "Feature",
  "properties": {
    "iso:country":"IN",
    "ks:ks_name":"Sapalipura",
    "ks:ks_pop":245,
    "ks:ks_type":"HABITATION",
    "name:eng_x_preferred":[
        "Sapalipura"
    ],
    "wof:name":"Sapalipura",
    "wof:placetype":"locality",
    "wof:population":245
},
  "geometry": {"coordinates":[72.874222,22.606583],"type":"Point"}
}