{
  "type": "Feature",
  "properties": {
    "gn:admin1_code":"24.0",
    "gn:admin2_code":"114.0",
    "gn:asciiname":"Awal",
    "gn:country_code":"IN",
    "gn:dem":153,
    "gn:feature_class":"P",
    "gn:feature_code":"PPL",
    "gn:name":"Aw\u0101l",
    "gn:population":0,
    "gn:timezone":"Asia/Kolkata",
    "iso:country":"IN",
    "name:ara_x_preferred":[
        "\u0623\u0648\u0627\u0644"
    ],
    "name:ind_x_preferred":[
        "Awal"
    ],
    "wof:name":"Awal",
    "wof:placetype":"locality"
},
  "geometry": {"coordinates":[71.83024,27.51488],"type":"Point"}
}