{
  "type": "Feature",
  "properties": {
    "iso:country":"IN",
    "ks:ks_name":"Miyazal Ki Beri",
    "ks:ks_pop":876,
    "ks:ks_type":"VILLAGE",
    "name:eng_x_preferred":[
        "Miyazal Ki Beri"
    ],
    "wof:name":"Miyazal Ki Beri",
    "wof:placetype":"locality",
    "wof:population":876
},
  "geometry": {"coordinates":[71.301497,25.046867],"type":"Point"}
}