{
  "type": "Feature",
  "properties": {
    "gn:admin1_code":"36",
    "gn:admin2_code":"147.0",
    "gn:asciiname":"Thathi",
    "gn:country_code":"IN",
    "gn:dem":172,
    "gn:feature_class":"P",
    "gn:feature_code":"PPL",
    "gn:name":"Th\u0101thi",
    "gn:population":0,
    "gn:timezone":"Asia/Kolkata",
    "iso:country":"IN",
    "name:fas_x_preferred":[
        "\u062a\u0647\u062a\u06cc"
    ],
    "name:pnb_x_preferred":[
        "\u0679\u06be\u0679\u06be\u06cc"
    ],
    "name:urd_x_preferred":[
        "\u0679\u06be\u0679\u06cc"
    ],
    "wof:name":"Thathi",
    "wof:placetype":"locality"
},
  "geometry": {"coordinates":[78.56066,27.40908],"type":"Point"}
}