{
  "type": "Feature",
  "properties": {
    "iso:country":"IN",
    "ks:ks_name":"Basavanagadde",
    "ks:ks_pop":802,
    "ks:ks_type":"HABITATION",
    "name:eng_x_preferred":[
        "Basavanagadde"
    ],
    "wof:name":"Basavanagadde",
    "wof:placetype":"locality",
    "wof:population":802
},
  "geometry": {"coordinates":[75.390406,13.535832],"type":"Point"}
}