{
  "type": "Feature",
  "properties": {
    "iso:country":"IN",
    "ks:ks_name":"Duhalia pt IV",
    "ks:ks_pop":2009,
    "ks:ks_type":"VILLAGE",
    "ks:ks_uagg_main":0,
    "name:eng_x_preferred":[
        "Duhalia pt IV"
    ],
    "wof:name":"Duhalia pt IV",
    "wof:placetype":"neighbourhood",
    "wof:population":2009
},
  "geometry": {"coordinates":[92.343031,24.588715],"type":"Point"}
}