{
  "type": "Feature",
  "properties": {
    "iso:country":"IN",
    "ks:ks_name":"Bagherka",
    "ks:ks_pop":1,
    "ks:ks_type":"VILLAGE",
    "name:eng_x_preferred":[
        "Bagherka"
    ],
    "wof:name":"Bagherka",
    "wof:placetype":"locality",
    "wof:population":1
},
  "geometry": {"coordinates":[79.930909,25.803659],"type":"Point"}
}