{
  "type": "Feature",
  "properties": {
    "iso:country":"IN",
    "ks:ks_name":"Chibitabichia Pt V",
    "ks:ks_pop":1579,
    "ks:ks_type":"VILLAGE",
    "name:eng_x_preferred":[
        "Chibitabichia Pt V"
    ],
    "wof:name":"Chibitabichia Pt V",
    "wof:placetype":"locality",
    "wof:population":1579
},
  "geometry": {"coordinates":[92.672189,24.728076],"type":"Point"}
}