{
  "type": "Feature",
  "properties": {
    "iso:country":"IN",
    "ks:ks_name":"Navanitgram",
    "ks:ks_pop":9,
    "ks:ks_type":"HABITATION",
    "name:eng_x_preferred":[
        "Navanitgram"
    ],
    "wof:name":"Navanitgram",
    "wof:placetype":"locality",
    "wof:population":9
},
  "geometry": {"coordinates":[80.033168,19.850409],"type":"Point"}
}