{
  "type": "Feature",
  "properties": {
    "gn:admin1_code":"11",
    "gn:admin2_code":"24.0",
    "gn:asciiname":"Khas Nadehr",
    "gn:country_code":"IN",
    "gn:dem":748,
    "gn:feature_class":"P",
    "gn:feature_code":"PPL",
    "gn:name":"Kh\u0101s Nadehr",
    "gn:population":0,
    "gn:timezone":"Asia/Kolkata",
    "iso:country":"IN",
    "wof:name":"Khas Nadehr",
    "wof:placetype":"locality"
},
  "geometry": {"coordinates":[76.28458000000001,32.13174],"type":"Point"}
}