{
  "type": "Feature",
  "properties": {
    "gn:admin1_code":"12.0",
    "gn:admin2_code":"18.0",
    "gn:asciiname":"Takhaigol",
    "gn:country_code":"IN",
    "gn:dem":3158,
    "gn:feature_class":"P",
    "gn:feature_code":"PPL",
    "gn:name":"Takhaig\u014dl",
    "gn:population":0,
    "gn:timezone":"Asia/Kolkata",
    "iso:country":"IN",
    "wof:name":"Takhaigol",
    "wof:placetype":"locality"
},
  "geometry": {"coordinates":[75.51708000000001,33.40227],"type":"Point"}
}