{
  "type": "Feature",
  "properties": {
    "iso:country":"IN",
    "ks:ks_alt_nam":"patla bhash",
    "ks:ks_name":"Patla Bhash",
    "ks:ks_pop":344,
    "ks:ks_type":"HABITATION",
    "name:eng_x_preferred":[
        "Patla Bhash"
    ],
    "wof:name":"Patla Bhash",
    "wof:placetype":"locality",
    "wof:population":344
},
  "geometry": {"coordinates":[88.159216,26.48689],"type":"Point"}
}