{
  "type": "Feature",
  "properties": {
    "gn:admin1_code":"24",
    "gn:admin2_code":"107.0",
    "gn:asciiname":"Nindar ka Pura",
    "gn:country_code":"IN",
    "gn:dem":212,
    "gn:feature_class":"P",
    "gn:feature_code":"PPL",
    "gn:name":"N\u012bndar ka Pura",
    "gn:population":0,
    "gn:timezone":"Asia/Kolkata",
    "iso:country":"IN",
    "wof:name":"Nindar ka Pura",
    "wof:placetype":"locality"
},
  "geometry": {"coordinates":[77.16634999999999,26.31764],"type":"Point"}
}