{
  "type": "Feature",
  "properties": {
    "gn:admin1_code":"36.0",
    "gn:admin2_code":"182.0",
    "gn:asciiname":"Paltipur",
    "gn:country_code":"IN",
    "gn:dem":107,
    "gn:feature_class":"P",
    "gn:feature_code":"PPL",
    "gn:name":"Palt\u012bpur",
    "gn:population":0,
    "gn:timezone":"Asia/Kolkata",
    "iso:country":"IN",
    "ks:ks_name":"Paltipur",
    "ks:ks_pop":134,
    "ks:ks_type":"HABITATION",
    "ks:ks_uagg_main":0,
    "name:eng_x_preferred":[
        "Paltipur"
    ],
    "wof:name":"Paltipur",
    "wof:placetype":"neighbourhood",
    "wof:population":134
},
  "geometry": {"coordinates":[82.20860399999999,27.354384],"type":"Point"}
}