{
  "type": "Feature",
  "properties": {
    "gn:country":"IN",
    "gn:fcode":"PPL",
    "gn:pop":0,
    "iso:country":"IN",
    "name:hin_x_preferred":[
        "\u091a\u0947\u092e\u094d\u092c\u0942\u0930"
    ],
    "name:mar_x_preferred":[
        "\u091a\u0947\u0902\u092c\u0942\u0930"
    ],
    "qs:name":"Chembur",
    "qs:name_adm0":"India",
    "qs:name_adm1":"Maharashtra",
    "qs:photos":1,
    "qs:photos_1k":1,
    "qs:photos_9k":1,
    "qs:photos_9r":1,
    "qs:photos_all":1,
    "qs:photos_sr":1,
    "qs:placetype":"Suburb",
    "qs:pop_sr":"0",
    "wd:wordcount":1599,
    "wof:name":"Chembur",
    "wof:placetype":"neighbourhood",
    "wof:population":0
},
  "geometry": {"coordinates":[72.89291,19.03478],"type":"Point"}
}