{
  "type": "Feature",
  "properties": {
    "gn:country":"IN",
    "gn:fcode":"PPL",
    "gn:population":0,
    "iso:country":"IN",
    "name:ben_x_preferred":[
        "\u099a\u09c7\u09ae\u09cd\u09ac\u09c1\u09b0"
    ],
    "name:cym_x_preferred":[
        "Chembur"
    ],
    "name:deu_x_preferred":[
        "Chembur"
    ],
    "name:eng_x_preferred":[
        "Mangalwar Peth"
    ],
    "name:eng_x_variant":[
        "Chembur"
    ],
    "name:fra_x_preferred":[
        "Chembur"
    ],
    "name:hin_x_preferred":[
        "\u091a\u0947\u092e\u094d\u092c\u0942\u0930"
    ],
    "name:hye_x_preferred":[
        "\u0549\u0565\u0574\u0562\u0578\u0582\u0580"
    ],
    "name:ind_x_preferred":[
        "Chembur"
    ],
    "name:mal_x_preferred":[
        "\u0d1a\u0d46\u0d2e\u0d4d\u0d2a\u0d42\u0d7c"
    ],
    "name:mar_x_preferred":[
        "\u091a\u0947\u0902\u092c\u0942\u0930"
    ],
    "name:ori_x_preferred":[
        "\u0b1a\u0b47\u0b2e\u0b4d\u0b2c\u0b41\u0b30"
    ],
    "name:por_x_preferred":[
        "Chembur"
    ],
    "name:rus_x_preferred":[
        "\u0427\u0435\u043c\u0431\u0443\u0440"
    ],
    "name:ukr_x_preferred":[
        "\u0427\u0435\u043c\u0431\u0443\u0440"
    ],
    "name:urd_x_preferred":[
        "\u0686\u0645\u0628\u0631"
    ],
    "name:zho_x_preferred":[
        "\u5546\u6ce2\u723e"
    ],
    "qs:name":"Chembur",
    "qs:name_adm0":"India",
    "qs:name_adm1":"Maharashtra",
    "qs:photos":1,
    "qs:photos_1k":1,
    "qs:photos_9k":1,
    "qs:photos_9r":1,
    "qs:photos_all":1,
    "qs:photos_sr":1,
    "qs:placetype":"Suburb",
    "qs:pop_sr":"0",
    "wd:wordcount":1599,
    "wof:name":"Chembur",
    "wof:placetype":"neighbourhood",
    "wof:population":0
},
  "geometry": {"coordinates":[72.89291,19.03478],"type":"Point"}
}