{
  "type": "Feature",
  "properties": {
    "gn:admin1_code":"36.0",
    "gn:admin2_code":"182.0",
    "gn:asciiname":"Arazi Bhatta",
    "gn:country_code":"IN",
    "gn:dem":114,
    "gn:feature_class":"P",
    "gn:feature_code":"PPL",
    "gn:name":"\u0100r\u0101zi Bhatta",
    "gn:population":0,
    "gn:timezone":"Asia/Kolkata",
    "iso:country":"IN",
    "wof:name":"Arazi Bhatta",
    "wof:placetype":"neighbourhood"
},
  "geometry": {"coordinates":[82.16172,27.41701],"type":"Point"}
}