{
  "type": "Feature",
  "properties": {
    "iso:country":"IN",
    "ks:ks_name":"Vattulli Rd",
    "ks:ks_pop":444,
    "ks:ks_type":"HABITATION",
    "name:eng_x_preferred":[
        "Vattulli Rd"
    ],
    "wof:name":"Vattulli Rd",
    "wof:placetype":"locality",
    "wof:population":444
},
  "geometry": {"coordinates":[76.341847,10.677452],"type":"Point"}
}