{
  "type": "Feature",
  "properties": {
    "iso:country":"IN",
    "ks:ks_name":"Ghevra",
    "ks:ks_pop":3558,
    "ks:ks_type":"VILLAGE",
    "name:eng_x_preferred":[
        "Ghevra"
    ],
    "wof:name":"Ghevra",
    "wof:placetype":"locality",
    "wof:population":3558
},
  "geometry": {"coordinates":[72.74649700000001,26.607881],"type":"Point"}
}