{
  "type": "Feature",
  "properties": {
    "iso:country":"IN",
    "ks:ks_name":"Manakkalpadi",
    "ks:ks_pop":1778,
    "ks:ks_type":"HABITATION",
    "name:eng_x_preferred":[
        "Manakkalpadi"
    ],
    "wof:name":"Manakkalpadi",
    "wof:placetype":"locality",
    "wof:population":1778
},
  "geometry": {"coordinates":[76.224909,10.844606],"type":"Point"}
}