{
  "type": "Feature",
  "properties": {
    "gn:admin1_code":"11",
    "gn:admin2_code":"23.0",
    "gn:asciiname":"Golu",
    "gn:country_code":"IN",
    "gn:dem":1426,
    "gn:feature_class":"P",
    "gn:feature_code":"PPL",
    "gn:name":"Golu",
    "gn:population":0,
    "gn:timezone":"Asia/Kolkata",
    "iso:country":"IN",
    "name:fra_x_preferred":[
        "Golu"
    ],
    "name:mal_x_preferred":[
        "\u0d2c\u0d4a\u0d2e\u0d4d\u0d2e\u0d15\u0d4d\u0d15\u0d4a\u0d32\u0d41"
    ],
    "name:tam_x_preferred":[
        "\u0b95\u0bca\u0bb2\u0bc1"
    ],
    "wof:name":"Golu",
    "wof:placetype":"locality"
},
  "geometry": {"coordinates":[76.06158000000001,32.38412],"type":"Point"}
}