{
  "type": "Feature",
  "properties": {
    "iso:country":"IN",
    "ks:ks_name":"Patel Para",
    "ks:ks_pop":284,
    "ks:ks_type":"HABITATION",
    "name:eng_x_preferred":[
        "Patel Para"
    ],
    "wof:name":"Patel Para",
    "wof:placetype":"locality",
    "wof:population":284
},
  "geometry": {"coordinates":[81.684679,19.544859],"type":"Point"}
}