{
  "type": "Feature",
  "properties": {
    "iso:country":"IN",
    "ks:ks_alt_nam":"Sri Ram nagar",
    "ks:ks_name":"Sri Ram Nagar",
    "ks:ks_pop":109,
    "ks:ks_type":"HABITATION",
    "ks:ks_uagg_main":0,
    "name:eng_x_preferred":[
        "Sri Ram Nagar"
    ],
    "wof:name":"Sri Ram Nagar",
    "wof:placetype":"neighbourhood",
    "wof:population":109
},
  "geometry": {"coordinates":[78.108518,11.084058],"type":"Point"}
}