{
  "type": "Feature",
  "properties": {
    "iso:country":"IN",
    "ks:ks_name":"Katkariwadi",
    "ks:ks_pop":120,
    "ks:ks_type":"HABITATION",
    "name:eng_x_preferred":[
        "Katkariwadi"
    ],
    "wof:name":"Katkariwadi",
    "wof:placetype":"locality",
    "wof:population":120
},
  "geometry": {"coordinates":[73.17308199999999,19.159718],"type":"Point"}
}