{
  "type": "Feature",
  "properties": {
    "gn:admin1_code":"11.0",
    "gn:admin2_code":"27.0",
    "gn:asciiname":"Jhangru",
    "gn:country_code":"IN",
    "gn:dem":2506,
    "gn:feature_class":"P",
    "gn:feature_code":"PPL",
    "gn:name":"Jh\u0101ngru",
    "gn:population":0,
    "gn:timezone":"Asia/Kolkata",
    "iso:country":"IN",
    "wof:name":"Jhangru",
    "wof:placetype":"locality"
},
  "geometry": {"coordinates":[77.22929000000001,31.47696],"type":"Point"}
}