{
  "type": "Feature",
  "properties": {
    "iso:country":"IN",
    "ks:ks_name":"Pali",
    "ks:ks_pop":581,
    "ks:ks_type":"HABITATION",
    "name:eng_x_preferred":[
        "Pali"
    ],
    "wof:name":"Pali",
    "wof:placetype":"neighbourhood",
    "wof:population":581
},
  "geometry": {"coordinates":[73.167958,19.183099],"type":"Point"}
}