{
  "type": "Feature",
  "properties": {
    "iso:country":"IN",
    "ks:ks_name":"Puthumala",
    "ks:ks_pop":1185,
    "ks:ks_type":"HABITATION",
    "name:eng_x_preferred":[
        "Puthumala"
    ],
    "wof:name":"Puthumala",
    "wof:placetype":"locality",
    "wof:population":1185
},
  "geometry": {"coordinates":[76.14772499999999,11.504352],"type":"Point"}
}