{
  "type": "Feature",
  "properties": {
    "iso:country":"IN",
    "ks:ks_name":"Narsobawadi",
    "ks:ks_pop":250,
    "ks:ks_type":"HABITATION",
    "name:eng_x_preferred":[
        "Narsobawadi"
    ],
    "wof:name":"Narsobawadi",
    "wof:placetype":"locality",
    "wof:population":250
},
  "geometry": {"coordinates":[75.190516,18.172827],"type":"Point"}
}