{
  "type": "Feature",
  "properties": {
    "iso:country":"IN",
    "ks:ks_name":"Nattamaikaranpatti",
    "ks:ks_pop":389,
    "ks:ks_type":"HABITATION",
    "name:eng_x_preferred":[
        "Nattamaikaranpatti"
    ],
    "wof:name":"Nattamaikaranpatti",
    "wof:placetype":"locality",
    "wof:population":389
},
  "geometry": {"coordinates":[78.017737,10.414229],"type":"Point"}
}