{
  "type": "Feature",
  "properties": {
    "gn:admin1_code":"2.0",
    "gn:admin2_code":"544.0",
    "gn:asciiname":"Bardiput",
    "gn:country_code":"IN",
    "gn:dem":1076,
    "gn:feature_class":"P",
    "gn:feature_code":"PPL",
    "gn:name":"Bardiput",
    "gn:population":0,
    "gn:timezone":"Asia/Kolkata",
    "iso:country":"IN",
    "wof:name":"Bardiput",
    "wof:placetype":"locality"
},
  "geometry": {"coordinates":[82.54416999999999,18.12392],"type":"Point"}
}