{
  "type": "Feature",
  "properties": {
    "gn:admin1_code":"34",
    "gn:admin2_code":"234.0",
    "gn:asciiname":"Kekai",
    "gn:country_code":"IN",
    "gn:dem":96,
    "gn:feature_class":"P",
    "gn:feature_code":"PPL",
    "gn:name":"Kekai",
    "gn:population":0,
    "gn:timezone":"Asia/Kolkata",
    "iso:country":"IN",
    "wof:name":"Kekai",
    "wof:placetype":"locality"
},
  "geometry": {"coordinates":[83.86696999999999,24.94763],"type":"Point"}
}