{
  "type": "Feature",
  "properties": {
    "gn:admin1_code":"2.0",
    "gn:admin2_code":"548.0",
    "gn:asciiname":"Peddavaram",
    "gn:country_code":"IN",
    "gn:dem":82,
    "gn:feature_class":"P",
    "gn:feature_code":"PPL",
    "gn:name":"Peddavaram",
    "gn:population":0,
    "gn:timezone":"Asia/Kolkata",
    "iso:country":"IN",
    "ks:ks_name":"Peddavaram",
    "ks:ks_pop":568,
    "ks:ks_type":"VILLAGE",
    "name:eng_x_preferred":[
        "Peddavaram"
    ],
    "wof:name":"Peddavaram",
    "wof:placetype":"locality",
    "wof:population":568
},
  "geometry": {"coordinates":[79.643698,16.003476],"type":"Point"}
}