{
  "type": "Feature",
  "properties": {
    "iso:country":"IN",
    "ks:ks_name":"Rajama",
    "ks:ks_pop":203,
    "ks:ks_type":"VILLAGE",
    "name:eng_x_preferred":[
        "Rajama"
    ],
    "wof:name":"Rajama",
    "wof:placetype":"locality",
    "wof:population":203
},
  "geometry": {"coordinates":[84.22327300000001,19.441512],"type":"Point"}
}