{
  "type": "Feature",
  "properties": {
    "gn:admin1_code":"12.0",
    "gn:admin2_code":"19.0",
    "gn:asciiname":"Busal",
    "gn:country_code":"IN",
    "gn:dem":2033,
    "gn:feature_class":"P",
    "gn:feature_code":"PPL",
    "gn:name":"Busal",
    "gn:population":0,
    "gn:timezone":"Asia/Kolkata",
    "iso:country":"IN",
    "name:fas_x_preferred":[
        "\u0628\u0648\u0633\u0627\u0644"
    ],
    "name:pnb_x_preferred":[
        "\u0628\u0648\u0633\u0627\u0644"
    ],
    "name:urd_x_preferred":[
        "\u0628\u0648\u0633\u0627\u0644"
    ],
    "wof:name":"Busal",
    "wof:placetype":"locality"
},
  "geometry": {"coordinates":[75.17435999999999,33.0329],"type":"Point"}
}