{
  "type": "Feature",
  "properties": {
    "gn:admin1_code":"19.0",
    "gn:admin2_code":"563.0",
    "gn:asciiname":"Negalgona",
    "gn:country_code":"IN",
    "gn:dem":42,
    "gn:feature_class":"P",
    "gn:feature_code":"PPL",
    "gn:name":"Negalgona",
    "gn:population":0,
    "gn:timezone":"Asia/Kolkata",
    "iso:country":"IN",
    "wof:name":"Negalgona",
    "wof:placetype":"locality"
},
  "geometry": {"coordinates":[74.62979,14.44464],"type":"Point"}
}