{
  "type": "Feature",
  "properties": {
    "gn:admin1_code":"19",
    "gn:admin2_code":"563.0",
    "gn:asciiname":"Hakkalmane",
    "gn:country_code":"IN",
    "gn:dem":495,
    "gn:feature_class":"P",
    "gn:feature_code":"PPL",
    "gn:name":"Hakkalmane",
    "gn:population":0,
    "gn:timezone":"Asia/Kolkata",
    "iso:country":"IN",
    "ks:ks_name":"Haklamane",
    "ks:ks_pop":137,
    "ks:ks_type":"HABITATION",
    "name:eng_x_preferred":[
        "Haklamane"
    ],
    "name:eng_x_variant":[
        "Hakkalmane"
    ],
    "wof:name":"Haklamane",
    "wof:placetype":"locality",
    "wof:population":137
},
  "geometry": {"coordinates":[74.83839,14.467476],"type":"Point"}
}