{
  "type": "Feature",
  "properties": {
    "iso:country":"IN",
    "ks:ks_name":"Kosappadi",
    "ks:ks_pop":2290,
    "ks:ks_type":"VILLAGE",
    "ks:ks_uagg_main":0,
    "name:eng_x_preferred":[
        "Kosappadi"
    ],
    "wof:name":"Kosappadi",
    "wof:placetype":"neighbourhood",
    "wof:population":2290
},
  "geometry": {"coordinates":[78.838775,11.893366],"type":"Point"}
}