{
  "type": "Feature",
  "properties": {
    "gn:admin1_code":"37",
    "gn:admin2_code":"406.0",
    "gn:asciiname":"Khairadih",
    "gn:country_code":"IN",
    "gn:dem":267,
    "gn:feature_class":"P",
    "gn:feature_code":"PPL",
    "gn:name":"Khair\u0101d\u012bh",
    "gn:population":0,
    "gn:timezone":"Asia/Kolkata",
    "iso:country":"IN",
    "ks:ks_alt_nam":"KHAIRADIH",
    "ks:ks_name":"Khairadih",
    "ks:ks_pop":502,
    "ks:ks_type":"HABITATION",
    "name:eng_x_preferred":[
        "Khairadih"
    ],
    "wof:name":"Khairadih",
    "wof:placetype":"locality",
    "wof:population":502
},
  "geometry": {"coordinates":[82.05677900000001,22.071352],"type":"Point"}
}