{
  "type": "Feature",
  "properties": {
    "iso:country":"IN",
    "ks:ks_name":"Sarpara",
    "ks:ks_pop":899,
    "ks:ks_type":"URBAN",
    "ks:ks_uagg_main":0,
    "name:eng_x_preferred":[
        "Sarpara"
    ],
    "wof:name":"Sarpara",
    "wof:placetype":"locality",
    "wof:population":899
},
  "geometry": {"coordinates":[91.519498,26.093479],"type":"Point"}
}