{
  "type": "Feature",
  "properties": {
    "iso:country":"IN",
    "ks:ks_name":"Pakir Thota",
    "ks:ks_pop":34,
    "ks:ks_type":"HABITATION",
    "name:eng_x_preferred":[
        "Pakir Thota"
    ],
    "wof:name":"Pakir Thota",
    "wof:placetype":"locality",
    "wof:population":34
},
  "geometry": {"coordinates":[79.26630299999999,13.203507],"type":"Point"}
}