{
  "type": "Feature",
  "properties": {
    "iso:country":"IN",
    "ks:ks_name":"Nutandi",
    "ks:ks_pop":0,
    "ks:ks_type":"VILLAGE",
    "name:eng_x_preferred":[
        "Nutandi"
    ],
    "wof:name":"Nutandi",
    "wof:placetype":"locality",
    "wof:population":0
},
  "geometry": {"coordinates":[86.775397,23.584436],"type":"Point"}
}