{
  "type": "Feature",
  "properties": {
    "iso:country":"IN",
    "ks:ks_name":"Samarpita",
    "ks:ks_pop":327,
    "ks:ks_type":"HABITATION",
    "name:eng_x_preferred":[
        "Samarpita"
    ],
    "wof:name":"Samarpita",
    "wof:placetype":"locality",
    "wof:population":327
},
  "geometry": {"coordinates":[85.94287199999999,21.105511],"type":"Point"}
}