{
  "type": "Feature",
  "properties": {
    "iso:country":"IN",
    "ks:ks_name":"Sangvi",
    "ks:ks_pop":267,
    "ks:ks_type":"VILLAGE",
    "name:eng_x_preferred":[
        "Sangvi"
    ],
    "wof:name":"Sangvi",
    "wof:placetype":"locality",
    "wof:population":267
},
  "geometry": {"coordinates":[73.683937,18.18592],"type":"Point"}
}