{
  "type": "Feature",
  "properties": {
    "iso:country":"IN",
    "ks:ks_name":"Panasa",
    "ks:ks_pop":346,
    "ks:ks_type":"HABITATION",
    "name:eng_x_preferred":[
        "Panasa"
    ],
    "wof:name":"Panasa",
    "wof:placetype":"locality",
    "wof:population":346
},
  "geometry": {"coordinates":[82.596723,18.346453],"type":"Point"}
}