{
  "type": "Feature",
  "properties": {
    "iso:country":"IN",
    "ks:ks_name":"Ahiran Purwa",
    "ks:ks_pop":252,
    "ks:ks_type":"HABITATION",
    "ks:ks_uagg_main":0,
    "name:eng_x_preferred":[
        "Ahiran Purwa"
    ],
    "wof:name":"Ahiran Purwa",
    "wof:placetype":"neighbourhood",
    "wof:population":252
},
  "geometry": {"coordinates":[81.685484,27.037465],"type":"Point"}
}