{
  "type": "Feature",
  "properties": {
    "iso:country":"IN",
    "ks:ks_name":"Badagumuda",
    "ks:ks_pop":68,
    "ks:ks_type":"VILLAGE",
    "name:eng_x_preferred":[
        "Badagumuda"
    ],
    "wof:name":"Badagumuda",
    "wof:placetype":"locality",
    "wof:population":68
},
  "geometry": {"coordinates":[83.520495,19.291986],"type":"Point"}
}