{
  "type": "Feature",
  "properties": {
    "iso:country":"IN",
    "ks:ks_name":"Inderpur Garwal",
    "ks:ks_pop":228,
    "ks:ks_type":"VILLAGE",
    "ks:ks_uagg_main":0,
    "name:eng_x_preferred":[
        "Inderpur Garwal"
    ],
    "wof:name":"Inderpur Garwal",
    "wof:placetype":"neighbourhood",
    "wof:population":228
},
  "geometry": {"coordinates":[79.50309900000001,29.117438],"type":"Point"}
}