{
  "type": "Feature",
  "properties": {
    "gn:admin1_code":"25.0",
    "gn:admin2_code":"604",
    "gn:asciiname":"Vallam",
    "gn:country_code":"IN",
    "gn:dem":48,
    "gn:feature_class":"P",
    "gn:feature_code":"PPL",
    "gn:name":"Vallam",
    "gn:population":0,
    "gn:timezone":"Asia/Kolkata",
    "iso:country":"IN",
    "ks:ks_name":"Vallam",
    "ks:ks_type":"VILLAGE",
    "ks:ks_uagg_main":0,
    "name:bpy_x_preferred":[
        "\u09ac\u09b2\u09b2\u09ae"
    ],
    "name:ceb_x_preferred":[
        "Vallam"
    ],
    "name:eng_x_preferred":[
        "Vallam"
    ],
    "name:ita_x_preferred":[
        "Vallam"
    ],
    "name:msa_x_preferred":[
        "Vallam"
    ],
    "name:nld_x_preferred":[
        "Vallam"
    ],
    "name:por_x_preferred":[
        "Vallam"
    ],
    "name:swe_x_preferred":[
        "Vallam"
    ],
    "name:tam_x_preferred":[
        "\u0bb5\u0bb2\u0bcd\u0bb2\u0bae\u0bcd"
    ],
    "name:vie_x_preferred":[
        "Vallam"
    ],
    "wof:name":"Vallam",
    "wof:placetype":"neighbourhood"
},
  "geometry": {"coordinates":[79.934341,12.894344],"type":"Point"}
}