{
  "type": "Feature",
  "properties": {
    "gn:admin1_code":"34.0",
    "gn:admin2_code":"237.0",
    "gn:asciiname":"Samhri",
    "gn:country_code":"IN",
    "gn:dem":91,
    "gn:feature_class":"P",
    "gn:feature_code":"PPL",
    "gn:name":"Samhri",
    "gn:population":0,
    "gn:timezone":"Asia/Kolkata",
    "iso:country":"IN",
    "wof:name":"Samhri",
    "wof:placetype":"locality"
},
  "geometry": {"coordinates":[85.66443000000002,24.91243],"type":"Point"}
}