{
  "type": "Feature",
  "properties": {
    "iso:country":"IN",
    "ks:ks_name":"H Tola",
    "ks:ks_pop":145,
    "ks:ks_type":"HABITATION",
    "name:eng_x_preferred":[
        "H Tola"
    ],
    "wof:name":"H Tola",
    "wof:placetype":"locality",
    "wof:population":145
},
  "geometry": {"coordinates":[86.11024999999999,24.381487],"type":"Point"}
}