{
  "type": "Feature",
  "properties": {
    "iso:country":"IN",
    "ks:ks_name":"Purbagadia",
    "ks:ks_pop":1175,
    "ks:ks_type":"VILLAGE",
    "name:eng_x_preferred":[
        "Purbagadia"
    ],
    "wof:name":"Purbagadia",
    "wof:placetype":"locality",
    "wof:population":1175
},
  "geometry": {"coordinates":[85.40849900000001,20.281196],"type":"Point"}
}