{
  "type": "Feature",
  "properties": {
    "gn:admin1_code":"10.0",
    "gn:admin2_code":"081",
    "gn:asciiname":"Mandhan",
    "gn:country_code":"IN",
    "gn:dem":219,
    "gn:feature_class":"P",
    "gn:feature_code":"PPL",
    "gn:name":"Mandh\u0101n",
    "gn:population":0,
    "gn:timezone":"Asia/Kolkata",
    "iso:country":"IN",
    "wof:name":"Mandhan",
    "wof:placetype":"locality"
},
  "geometry": {"coordinates":[75.72895,28.79436],"type":"Point"}
}