{
  "type": "Feature",
  "properties": {
    "gn:admin1_code":"2.0",
    "gn:admin2_code":"546.0",
    "gn:asciiname":"Nallagudem",
    "gn:country_code":"IN",
    "gn:dem":154,
    "gn:feature_class":"P",
    "gn:feature_code":"PPL",
    "gn:name":"Nallag\u016bdem",
    "gn:population":0,
    "gn:timezone":"Asia/Kolkata",
    "iso:country":"IN",
    "wof:name":"Nallagudem",
    "wof:placetype":"neighbourhood"
},
  "geometry": {"coordinates":[81.30583,17.24092],"type":"Point"}
}