{
  "type": "Feature",
  "properties": {
    "iso:country":"IN",
    "ks:ks_name":"Pethiya Khas",
    "ks:ks_pop":288,
    "ks:ks_type":"HABITATION",
    "ks:ks_uagg_main":0,
    "name:eng_x_preferred":[
        "Pethiya Khas"
    ],
    "wof:name":"Pethiya Khas",
    "wof:placetype":"neighbourhood",
    "wof:population":288
},
  "geometry": {"coordinates":[82.52031599999999,26.592949],"type":"Point"}
}