{
  "type": "Feature",
  "properties": {
    "iso:country":"IN",
    "ks:ks_name":"Gundlaburju",
    "ks:ks_pop":182,
    "ks:ks_type":"HABITATION",
    "ks:ks_uagg_main":0,
    "name:eng_x_preferred":[
        "Gundlaburju"
    ],
    "wof:name":"Gundlaburju",
    "wof:placetype":"neighbourhood",
    "wof:population":182
},
  "geometry": {"coordinates":[78.580877,13.564719],"type":"Point"}
}