{
  "type": "Feature",
  "properties": {
    "iso:country":"IN",
    "ks:ks_name":"Bendgaon",
    "ks:ks_pop":278,
    "ks:ks_type":"VILLAGE",
    "name:eng_x_preferred":[
        "Bendgaon"
    ],
    "wof:name":"Bendgaon",
    "wof:placetype":"locality",
    "wof:population":278
},
  "geometry": {"coordinates":[73.000382,20.068888],"type":"Point"}
}