{
  "type": "Feature",
  "properties": {
    "gn:admin1_code":"38.0",
    "gn:admin2_code":"347.0",
    "gn:asciiname":"Bhandar",
    "gn:country_code":"IN",
    "gn:dem":264,
    "gn:feature_class":"P",
    "gn:feature_code":"PPL",
    "gn:name":"Bhand\u0101r",
    "gn:population":0,
    "gn:timezone":"Asia/Kolkata",
    "iso:country":"IN",
    "ks:ks_alt_nam":"Bhand\u0101r",
    "ks:ks_name":"Bhandar",
    "ks:ks_pop":58,
    "ks:ks_type":"VILLAGE",
    "name:eng_x_preferred":[
        "Bhandar"
    ],
    "name:eng_x_variant":[
        "Bhand\u0101r"
    ],
    "wof:name":"Bhandar",
    "wof:placetype":"locality",
    "wof:population":58
},
  "geometry": {"coordinates":[84.570104,24.257467],"type":"Point"}
}