{
  "type": "Feature",
  "properties": {
    "iso:country":"IN",
    "ks:ks_name":"Doongra Nada",
    "ks:ks_pop":91,
    "ks:ks_type":"VILLAGE",
    "name:eng_x_preferred":[
        "Doongra Nada"
    ],
    "wof:name":"Doongra Nada",
    "wof:placetype":"locality",
    "wof:population":91
},
  "geometry": {"coordinates":[72.123772,26.133019],"type":"Point"}
}