{
  "type": "Feature",
  "properties": {
    "iso:country":"IN",
    "ks:ks_name":"Tola Marwa",
    "ks:ks_pop":96,
    "ks:ks_type":"VILLAGE",
    "name:eng_x_preferred":[
        "Tola Marwa"
    ],
    "wof:name":"Tola Marwa",
    "wof:placetype":"locality",
    "wof:population":96
},
  "geometry": {"coordinates":[86.234351,24.609735],"type":"Point"}
}