{
  "type": "Feature",
  "properties": {
    "gn:admin1_code":"24.0",
    "gn:admin2_code":"118.0",
    "gn:asciiname":"Piloni",
    "gn:country_code":"IN",
    "gn:dem":297,
    "gn:feature_class":"P",
    "gn:feature_code":"PPL",
    "gn:name":"Piloni",
    "gn:population":0,
    "gn:timezone":"Asia/Kolkata",
    "iso:country":"IN",
    "name:ceb_x_preferred":[
        "Piloni"
    ],
    "name:deu_x_preferred":[
        "Piloni"
    ],
    "name:ita_x_preferred":[
        "Piloni"
    ],
    "name:nld_x_preferred":[
        "Piloni"
    ],
    "name:srp_x_preferred":[
        "\u041f\u0438\u043b\u043e\u043d\u0438"
    ],
    "wof:name":"Piloni",
    "wof:placetype":"locality"
},
  "geometry": {"coordinates":[73.54732,25.48453],"type":"Point"}
}