{
  "type": "Feature",
  "properties": {
    "gn:admin1_code":"36",
    "gn:admin2_code":"185.0",
    "gn:asciiname":"Goria",
    "gn:country_code":"IN",
    "gn:dem":91,
    "gn:feature_class":"P",
    "gn:feature_code":"PPL",
    "gn:name":"Goria",
    "gn:population":0,
    "gn:timezone":"Asia/Kolkata",
    "iso:country":"IN",
    "name:ita_x_preferred":[
        "Goria"
    ],
    "name:srp_x_preferred":[
        "Goria"
    ],
    "wof:name":"Goria",
    "wof:placetype":"locality"
},
  "geometry": {"coordinates":[82.73544,26.82434000000001],"type":"Point"}
}