{
  "type": "Feature",
  "properties": {
    "gn:admin1_code":"02",
    "gn:admin2_code":"552.0",
    "gn:asciiname":"Miduturu",
    "gn:country_code":"IN",
    "gn:dem":311,
    "gn:feature_class":"P",
    "gn:feature_code":"PPL",
    "gn:name":"Midut\u016bru",
    "gn:population":0,
    "gn:timezone":"Asia/Kolkata",
    "iso:country":"IN",
    "name:und_x_variant":[
        "Midutur",
        "Midut\u016bru"
    ],
    "wof:name":"Miduturu",
    "wof:placetype":"neighbourhood"
},
  "geometry": {"coordinates":[78.2895,15.76999],"type":"Point"}
}