{
  "type": "Feature",
  "properties": {
    "gn:admin1_code":"36",
    "gn:admin2_code":"179.0",
    "gn:asciiname":"Asaidapur",
    "gn:country_code":"IN",
    "gn:dem":113,
    "gn:feature_class":"P",
    "gn:feature_code":"PPL",
    "gn:name":"Asaid\u0101pur",
    "gn:population":0,
    "gn:timezone":"Asia/Kolkata",
    "iso:country":"IN",
    "ks:ks_alt_nam":"Asaid\u0101pur",
    "ks:ks_name":"Asaidapur",
    "ks:ks_type":"VILLAGE",
    "ks:ks_uagg_main":0,
    "name:eng_x_preferred":[
        "Asaidapur"
    ],
    "name:eng_x_variant":[
        "Asaid\u0101pur"
    ],
    "wof:name":"Asaidapur",
    "wof:placetype":"neighbourhood"
},
  "geometry": {"coordinates":[81.70228400000001,26.201623],"type":"Point"}
}