{
  "type": "Feature",
  "properties": {
    "iso:country":"IN",
    "ks:ks_name":"Raneji Ki Basti",
    "ks:ks_pop":444,
    "ks:ks_type":"HABITATION",
    "name:eng_x_preferred":[
        "Raneji Ki Basti"
    ],
    "wof:name":"Raneji Ki Basti",
    "wof:placetype":"locality",
    "wof:population":444
},
  "geometry": {"coordinates":[71.257723,26.090583],"type":"Point"}
}