{
  "type": "Feature",
  "properties": {
    "gn:admin1_code":"36",
    "gn:admin2_code":"171.0",
    "gn:asciiname":"Pilkhani",
    "gn:country_code":"IN",
    "gn:dem":115,
    "gn:feature_class":"P",
    "gn:feature_code":"PPL",
    "gn:name":"Pilkhan\u012b",
    "gn:population":0,
    "gn:timezone":"Asia/Kolkata",
    "iso:country":"IN",
    "wof:name":"Pilkhani",
    "wof:placetype":"locality"
},
  "geometry": {"coordinates":[80.93122,25.42959],"type":"Point"}
}