{
  "type": "Feature",
  "properties": {
    "gn:admin1_code":"16",
    "gn:admin2_code":"499.0",
    "gn:asciiname":"Lonja",
    "gn:country_code":"IN",
    "gn:dem":374,
    "gn:feature_class":"P",
    "gn:feature_code":"PPL",
    "gn:name":"Lonja",
    "gn:population":0,
    "gn:timezone":"Asia/Kolkata",
    "iso:country":"IN",
    "name:ces_x_preferred":[
        "Lonja"
    ],
    "name:ell_x_preferred":[
        "\u039b\u03cc\u03bd\u03b9\u03b1"
    ],
    "name:hrv_x_preferred":[
        "Lonja-Trebe\u017e"
    ],
    "name:lit_x_preferred":[
        "Lonia"
    ],
    "name:rus_x_preferred":[
        "\u041b\u043e\u043d\u044c\u044f-\u0422\u0440\u0435\u0431\u0435\u0436"
    ],
    "name:slv_x_preferred":[
        "Lonja"
    ],
    "name:srp_x_preferred":[
        "\u041b\u043e\u045a\u0430"
    ],
    "name:ukr_x_preferred":[
        "\u041b\u043e\u043d\u044c\u044f-\u0422\u0440\u0435\u0431\u0435\u0436"
    ],
    "name:zho_x_preferred":[
        "\u6d1b\u5c3c\u4e9e\u6cb3"
    ],
    "wof:name":"Lonja",
    "wof:placetype":"locality"
},
  "geometry": {"coordinates":[75.09921,20.38651],"type":"Point"}
}