{
  "type": "Feature",
  "properties": {
    "iso:country":"IN",
    "ks:ks_alt_nam":"Devijanaik thanda",
    "ks:ks_name":"Devijanaik Thanda",
    "ks:ks_pop":130,
    "ks:ks_type":"HABITATION",
    "name:eng_x_preferred":[
        "Devijanaik Thanda"
    ],
    "wof:name":"Devijanaik Thanda",
    "wof:placetype":"locality",
    "wof:population":130
},
  "geometry": {"coordinates":[77.96766100000001,16.832055],"type":"Point"}
}