{
  "type": "Feature",
  "properties": {
    "iso:country":"IN",
    "ks:ks_name":"Mora",
    "ks:ks_pop":13924,
    "ks:ks_type":"URBAN",
    "ks:ks_uagg_main":1,
    "name:eng_x_preferred":[
        "Mora"
    ],
    "name:hin_x_preferred":[
        "\u092e\u094b\u0930\u093e"
    ],
    "wof:name":"Mora",
    "wof:placetype":"neighbourhood",
    "wof:population":13924
},
  "geometry": {"coordinates":[72.682304,21.170584],"type":"Point"}
}