{
  "type": "Feature",
  "properties": {
    "iso:country":"IN",
    "ks:ks_name":"Chhatauna",
    "ks:ks_pop":83,
    "ks:ks_type":"HABITATION",
    "ks:ks_uagg_main":0,
    "name:eng_x_preferred":[
        "Chhatauna"
    ],
    "wof:name":"Chhatauna",
    "wof:placetype":"neighbourhood",
    "wof:population":83
},
  "geometry": {"coordinates":[80.271626,27.464023],"type":"Point"}
}