{
  "type": "Feature",
  "properties": {
    "iso:country":"IN",
    "ks:ks_name":"Kalar Para",
    "ks:ks_pop":124,
    "ks:ks_type":"HABITATION",
    "name:eng_x_preferred":[
        "Kalar Para"
    ],
    "wof:name":"Kalar Para",
    "wof:placetype":"locality",
    "wof:population":124
},
  "geometry": {"coordinates":[81.76746799999999,19.218712],"type":"Point"}
}