{
  "type": "Feature",
  "properties": {
    "gn:admin1_code":"11.0",
    "gn:admin2_code":"033",
    "gn:asciiname":"Nehra",
    "gn:country_code":"IN",
    "gn:dem":1136,
    "gn:feature_class":"P",
    "gn:feature_code":"PPL",
    "gn:name":"Nehra",
    "gn:population":0,
    "gn:timezone":"Asia/Kolkata",
    "iso:country":"IN",
    "name:hin_x_preferred":[
        "\u0928\u0947\u0939\u0930\u093e"
    ],
    "wof:name":"Nehra",
    "wof:placetype":"locality"
},
  "geometry": {"coordinates":[77.02083,31.2425],"type":"Point"}
}