{
  "type": "Feature",
  "properties": {
    "gn:admin1_code":"35",
    "gn:admin2_code":"461.0",
    "gn:asciiname":"Garjanbija",
    "gn:country_code":"IN",
    "gn:dem":944,
    "gn:feature_class":"P",
    "gn:feature_code":"PPL",
    "gn:name":"Garjanb\u012bja",
    "gn:population":0,
    "gn:timezone":"Asia/Kolkata",
    "iso:country":"IN",
    "ks:ks_alt_nam":"Garjanb\u012bja",
    "ks:ks_name":"Garjanbija",
    "ks:ks_type":"VILLAGE",
    "name:eng_x_preferred":[
        "Garjanbija"
    ],
    "name:eng_x_variant":[
        "Garjanb\u012bja"
    ],
    "wof:name":"Garjanbija",
    "wof:placetype":"locality"
},
  "geometry": {"coordinates":[81.45660700000001,22.889961],"type":"Point"}
}