{
  "type": "Feature",
  "properties": {
    "gn:admin1_code":"34.0",
    "gn:admin2_code":"218.0",
    "gn:asciiname":"Karanpura",
    "gn:country_code":"IN",
    "gn:dem":66,
    "gn:feature_class":"P",
    "gn:feature_code":"PPL",
    "gn:name":"Karanpura",
    "gn:population":0,
    "gn:timezone":"Asia/Kolkata",
    "iso:country":"IN",
    "ks:ks_name":"Karanpura",
    "ks:ks_pop":1701,
    "ks:ks_type":"VILLAGE",
    "ks:ks_uagg_main":0,
    "name:eng_x_preferred":[
        "Karanpura"
    ],
    "name:msa_x_preferred":[
        "Karanpura"
    ],
    "wof:name":"Karanpura",
    "wof:placetype":"neighbourhood",
    "wof:population":1701
},
  "geometry": {"coordinates":[84.52213500000001,26.193127],"type":"Point"}
}