{
  "type": "Feature",
  "properties": {
    "iso:country":"IN",
    "ks:ks_alt_nam":"Bag\u0101li",
    "ks:ks_name":"Bagali",
    "ks:ks_pop":222,
    "ks:ks_type":"VILLAGE",
    "name:eng_x_preferred":[
        "Bagali"
    ],
    "name:eng_x_variant":[
        "Bag\u0101li"
    ],
    "wof:name":"Bagali",
    "wof:placetype":"locality",
    "wof:population":222
},
  "geometry": {"coordinates":[84.056308,20.361597],"type":"Point"}
}