{
  "type": "Feature",
  "properties": {
    "iso:country":"IN",
    "ks:ks_name":"Donimoduvinadoddi",
    "ks:ks_pop":200,
    "ks:ks_type":"HABITATION",
    "name:eng_x_preferred":[
        "Donimoduvinadoddi"
    ],
    "wof:name":"Donimoduvinadoddi",
    "wof:placetype":"locality",
    "wof:population":200
},
  "geometry": {"coordinates":[77.607327,12.107096],"type":"Point"}
}