{
  "type": "Feature",
  "properties": {
    "iso:country":"IN",
    "ks:ks_name":"Mudiadev",
    "ks:ks_pop":615,
    "ks:ks_type":"VILLAGE",
    "name:eng_x_preferred":[
        "Mudiadev"
    ],
    "wof:name":"Mudiadev",
    "wof:placetype":"locality",
    "wof:population":615
},
  "geometry": {"coordinates":[80.544248,24.993641],"type":"Point"}
}