{
  "type": "Feature",
  "properties": {
    "iso:country":"IN",
    "ks:ks_name":"Mayurjhalia",
    "ks:ks_pop":1853,
    "ks:ks_type":"VILLAGE",
    "name:eng_x_preferred":[
        "Mayurjhalia"
    ],
    "wof:name":"Mayurjhalia",
    "wof:placetype":"locality",
    "wof:population":1853
},
  "geometry": {"coordinates":[85.412768,20.008999],"type":"Point"}
}