{
  "type": "Feature",
  "properties": {
    "iso:country":"IN",
    "ks:ks_name":"Talasahi",
    "ks:ks_pop":87,
    "ks:ks_type":"VILLAGE",
    "name:eng_x_preferred":[
        "Talasahi"
    ],
    "wof:name":"Talasahi",
    "wof:placetype":"locality",
    "wof:population":87
},
  "geometry": {"coordinates":[84.876627,20.392697],"type":"Point"}
}