{
  "type": "Feature",
  "properties": {
    "iso:country":"IN",
    "ks:ks_name":"Bato",
    "ks:ks_pop":1472,
    "ks:ks_type":"VILLAGE",
    "name:eng_x_preferred":[
        "Bato"
    ],
    "wof:name":"Bato",
    "wof:placetype":"locality",
    "wof:population":1472
},
  "geometry": {"coordinates":[86.186385,21.129071],"type":"Point"}
}