{
  "type": "Feature",
  "properties": {
    "iso:country":"IN",
    "ks:ks_name":"Tondhare",
    "ks:ks_pop":2000,
    "ks:ks_type":"VILLAGE",
    "name:eng_x_preferred":[
        "Tondhare"
    ],
    "wof:name":"Tondhare",
    "wof:placetype":"locality",
    "wof:population":2000
},
  "geometry": {"coordinates":[73.130763,19.077996],"type":"Point"}
}