{
  "type": "Feature",
  "properties": {
    "gn:admin1_code":"36",
    "gn:admin2_code":"147.0",
    "gn:asciiname":"Dewa",
    "gn:country_code":"IN",
    "gn:dem":176,
    "gn:feature_class":"P",
    "gn:feature_code":"PPL",
    "gn:name":"Dewa",
    "gn:population":0,
    "gn:timezone":"Asia/Kolkata",
    "iso:country":"IN",
    "name:ceb_x_preferred":[
        "Dewa"
    ],
    "name:deu_x_preferred":[
        "Dewa"
    ],
    "name:nld_x_preferred":[
        "Dewa"
    ],
    "name:pol_x_preferred":[
        "Dewa"
    ],
    "name:rus_x_preferred":[
        "\u0414\u044d\u0432\u0430"
    ],
    "name:swe_x_preferred":[
        "Dewa"
    ],
    "name:ukr_x_preferred":[
        "\u0414\u0435\u0432\u0430"
    ],
    "name:vie_x_preferred":[
        "Dewa"
    ],
    "wof:name":"Dewa",
    "wof:placetype":"neighbourhood"
},
  "geometry": {"coordinates":[78.56476000000001,27.379],"type":"Point"}
}