{
  "type": "Feature",
  "properties": {
    "iso:country":"IN",
    "ks:ks_alt_nam":"Vadv\u0101s",
    "ks:ks_name":"Vadvas",
    "ks:ks_pop":643,
    "ks:ks_type":"VILLAGE",
    "name:eng_x_preferred":[
        "Vadvas"
    ],
    "name:eng_x_variant":[
        "Vadv\u0101s"
    ],
    "wof:name":"Vadvas",
    "wof:placetype":"locality",
    "wof:population":643
},
  "geometry": {"coordinates":[72.358041,24.336612],"type":"Point"}
}