{
  "type": "Feature",
  "properties": {
    "gn:admin1_code":"37",
    "gn:admin2_code":"413.0",
    "gn:asciiname":"Budeli",
    "gn:country_code":"IN",
    "gn:dem":353,
    "gn:feature_class":"P",
    "gn:feature_code":"PPL",
    "gn:name":"Budeli",
    "gn:population":0,
    "gn:timezone":"Asia/Kolkata",
    "iso:country":"IN",
    "ks:ks_name":"Budeli",
    "ks:ks_type":"VILLAGE",
    "name:eng_x_preferred":[
        "Budeli"
    ],
    "wof:name":"Budeli",
    "wof:placetype":"locality"
},
  "geometry": {"coordinates":[80.923958,20.250141],"type":"Point"}
}