{
  "type": "Feature",
  "properties": {
    "iso:country":"IN",
    "ks:ks_alt_nam":"Keel paiyur",
    "ks:ks_name":"Keel Paiyur",
    "ks:ks_pop":700,
    "ks:ks_type":"HABITATION",
    "ks:ks_uagg_main":0,
    "name:eng_x_preferred":[
        "Keel Paiyur"
    ],
    "wof:name":"Keel Paiyur",
    "wof:placetype":"neighbourhood",
    "wof:population":700
},
  "geometry": {"coordinates":[78.218667,12.382631],"type":"Point"}
}