{
  "type": "Feature",
  "properties": {
    "iso:country":"IN",
    "ks:ks_name":"Rawalwadi",
    "ks:ks_pop":144,
    "ks:ks_type":"HABITATION",
    "name:eng_x_preferred":[
        "Rawalwadi"
    ],
    "wof:name":"Rawalwadi",
    "wof:placetype":"locality",
    "wof:population":144
},
  "geometry": {"coordinates":[73.395556,17.440833],"type":"Point"}
}