{
  "type": "Feature",
  "properties": {
    "iso:country":"IN",
    "ks:ks_name":"Kurejhar",
    "ks:ks_type":"VILLAGE",
    "name:eng_x_preferred":[
        "Kurejhar"
    ],
    "wof:name":"Kurejhar",
    "wof:placetype":"locality"
},
  "geometry": {"coordinates":[80.65338199999999,21.239661],"type":"Point"}
}