{
  "type": "Feature",
  "properties": {
    "iso:country":"IN",
    "ks:ks_name":"Karri Bakia",
    "ks:ks_pop":535,
    "ks:ks_type":"HABITATION",
    "name:eng_x_preferred":[
        "Karri Bakia"
    ],
    "wof:name":"Karri Bakia",
    "wof:placetype":"locality",
    "wof:population":535
},
  "geometry": {"coordinates":[82.97155100000001,24.384516],"type":"Point"}
}