{
  "type": "Feature",
  "properties": {
    "gn:admin1_code":"16",
    "gn:admin2_code":"501.0",
    "gn:asciiname":"Devran",
    "gn:country_code":"IN",
    "gn:dem":301,
    "gn:feature_class":"P",
    "gn:feature_code":"PPL",
    "gn:name":"Devran",
    "gn:population":0,
    "gn:timezone":"Asia/Kolkata",
    "iso:country":"IN",
    "ks:ks_alt_nam":"Devran",
    "ks:ks_name":"Deoran",
    "ks:ks_pop":10,
    "ks:ks_type":"VILLAGE",
    "name:eng_x_preferred":[
        "Deoran"
    ],
    "name:eng_x_variant":[
        "Devran"
    ],
    "wof:name":"Deoran",
    "wof:placetype":"locality",
    "wof:population":10
},
  "geometry": {"coordinates":[77.386816,20.745401],"type":"Point"}
}