{
  "type": "Feature",
  "properties": {
    "gn:admin1_code":"19.0",
    "gn:admin2_code":"574.0",
    "gn:asciiname":"Kalhalli",
    "gn:country_code":"IN",
    "gn:dem":946,
    "gn:feature_class":"P",
    "gn:feature_code":"PPL",
    "gn:name":"Kalhalli",
    "gn:population":0,
    "gn:timezone":"Asia/Kolkata",
    "iso:country":"IN",
    "wof:name":"Kalhalli",
    "wof:placetype":"locality"
},
  "geometry": {"coordinates":[75.73869000000001,12.96852],"type":"Point"}
}