{
  "type": "Feature",
  "properties": {
    "gn:admin1_code":"16",
    "gn:admin2_code":"511.0",
    "gn:asciiname":"Mandani",
    "gn:country_code":"IN",
    "gn:dem":362,
    "gn:feature_class":"P",
    "gn:feature_code":"PPL",
    "gn:name":"M\u0101ndani",
    "gn:population":0,
    "gn:timezone":"Asia/Kolkata",
    "iso:country":"IN",
    "name:fas_x_preferred":[
        "\u0645\u0646\u062f\u0646\u06cc"
    ],
    "name:urd_x_preferred":[
        "\u0645\u0646\u062f\u0646\u06cc"
    ],
    "wof:name":"Mandani",
    "wof:placetype":"locality"
},
  "geometry": {"coordinates":[77.43281999999998,18.96252],"type":"Point"}
}