{
  "type": "Feature",
  "properties": {
    "iso:country":"IN",
    "ks:ks_name":"Nagriya",
    "ks:ks_pop":0,
    "ks:ks_type":"VILLAGE",
    "name:eng_x_preferred":[
        "Nagriya"
    ],
    "wof:name":"Nagriya",
    "wof:placetype":"locality",
    "wof:population":0
},
  "geometry": {"coordinates":[78.235884,24.449462],"type":"Point"}
}