{
  "type": "Feature",
  "properties": {
    "iso:country":"IN",
    "ks:ks_name":"Badgaonpara",
    "ks:ks_pop":81,
    "ks:ks_type":"HABITATION",
    "name:eng_x_preferred":[
        "Badgaonpara"
    ],
    "wof:name":"Badgaonpara",
    "wof:placetype":"locality",
    "wof:population":81
},
  "geometry": {"coordinates":[81.07303400000001,19.987044],"type":"Point"}
}