{
  "type": "Feature",
  "properties": {
    "iso:country":"IN",
    "ks:ks_name":"Tukaramnagar",
    "ks:ks_pop":145,
    "ks:ks_type":"HABITATION",
    "name:eng_x_preferred":[
        "Tukaramnagar"
    ],
    "wof:name":"Tukaramnagar",
    "wof:placetype":"locality",
    "wof:population":145
},
  "geometry": {"coordinates":[78.74092400000001,19.366759],"type":"Point"}
}