{
  "type": "Feature",
  "properties": {
    "gn:admin1_code":"36",
    "gn:admin2_code":"201.0",
    "gn:asciiname":"Chathi",
    "gn:country_code":"IN",
    "gn:dem":175,
    "gn:feature_class":"P",
    "gn:feature_code":"PPL",
    "gn:name":"Ch\u0101thi",
    "gn:population":0,
    "gn:timezone":"Asia/Kolkata",
    "iso:country":"IN",
    "name:fas_x_preferred":[
        "\u0686\u062a\u0647\u06cc"
    ],
    "wof:name":"Chathi",
    "wof:placetype":"neighbourhood"
},
  "geometry": {"coordinates":[78.62482,27.69942],"type":"Point"}
}