{
  "type": "Feature",
  "properties": {
    "gn:admin1_code":"2.0",
    "gn:admin2_code":"553.0",
    "gn:asciiname":"Chintarlapalle",
    "gn:country_code":"IN",
    "gn:dem":555,
    "gn:feature_class":"P",
    "gn:feature_code":"PPL",
    "gn:name":"Chintarlapalle",
    "gn:population":0,
    "gn:timezone":"Asia/Kolkata",
    "iso:country":"IN",
    "wof:name":"Chintarlapalle",
    "wof:placetype":"locality"
},
  "geometry": {"coordinates":[76.99764,14.41813],"type":"Point"}
}