{
  "type": "Feature",
  "properties": {
    "iso:country":"IN",
    "ks:ks_name":"Chavandigudde",
    "ks:ks_pop":116,
    "ks:ks_type":"HABITATION",
    "name:eng_x_preferred":[
        "Chavandigudde"
    ],
    "wof:name":"Chavandigudde",
    "wof:placetype":"locality",
    "wof:population":116
},
  "geometry": {"coordinates":[74.903239,13.124323],"type":"Point"}
}