{
  "type": "Feature",
  "properties": {
    "iso:country":"IN",
    "ks:ks_name":"Rao Kalan",
    "ks:ks_pop":992,
    "ks:ks_type":"VILLAGE",
    "name:eng_x_preferred":[
        "Rao Kalan"
    ],
    "wof:name":"Rao Kalan",
    "wof:placetype":"locality",
    "wof:population":992
},
  "geometry": {"coordinates":[78.272916,25.698213],"type":"Point"}
}