{
  "type": "Feature",
  "properties": {
    "iso:country":"IN",
    "ks:ks_name":"Dhobiadih",
    "ks:ks_pop":317,
    "ks:ks_type":"HABITATION",
    "name:eng_x_preferred":[
        "Dhobiadih"
    ],
    "wof:name":"Dhobiadih",
    "wof:placetype":"locality",
    "wof:population":317
},
  "geometry": {"coordinates":[86.319007,24.044336],"type":"Point"}
}