{
  "type": "Feature",
  "properties": {
    "gn:admin1_code":"11.0",
    "gn:admin2_code":"26.0",
    "gn:asciiname":"Gunian",
    "gn:country_code":"IN",
    "gn:dem":1364,
    "gn:feature_class":"P",
    "gn:feature_code":"PPL",
    "gn:name":"Gunian",
    "gn:population":0,
    "gn:timezone":"Asia/Kolkata",
    "iso:country":"IN",
    "name:ara_x_preferred":[
        "\u063a\u0648\u0646\u064a\u0627\u0646"
    ],
    "name:fas_x_preferred":[
        "\u06af\u0648\u0646\u06cc\u0627\u0646"
    ],
    "wof:name":"Gunian",
    "wof:placetype":"locality"
},
  "geometry": {"coordinates":[77.56339,31.43995],"type":"Point"}
}