{
  "type": "Feature",
  "properties": {
    "iso:country":"IN",
    "ks:ks_name":"Dadisahi",
    "ks:ks_pop":325,
    "ks:ks_type":"HABITATION",
    "name:eng_x_preferred":[
        "Dadisahi"
    ],
    "wof:name":"Dadisahi",
    "wof:placetype":"locality",
    "wof:population":325
},
  "geometry": {"coordinates":[84.387624,20.221968],"type":"Point"}
}