{
  "type": "Feature",
  "properties": {
    "iso:country":"IN",
    "ks:ks_name":"B Halwa",
    "ks:ks_pop":379,
    "ks:ks_type":"HABITATION",
    "name:eng_x_preferred":[
        "B Halwa"
    ],
    "wof:name":"B Halwa",
    "wof:placetype":"locality",
    "wof:population":379
},
  "geometry": {"coordinates":[83.439717,19.071793],"type":"Point"}
}