{
  "type": "Feature",
  "properties": {
    "gn:admin1_code":"25.0",
    "gn:admin2_code":"620.0",
    "gn:asciiname":"Arusuttiyarteruvu",
    "gn:country_code":"IN",
    "gn:dem":34,
    "gn:feature_class":"P",
    "gn:feature_code":"PPL",
    "gn:name":"\u0100rusuttiy\u0101rteruvu",
    "gn:population":0,
    "gn:timezone":"Asia/Kolkata",
    "iso:country":"IN",
    "wof:name":"Arusuttiyarteruvu",
    "wof:placetype":"locality"
},
  "geometry": {"coordinates":[79.29819999999999,10.79253],"type":"Point"}
}