{
  "type": "Feature",
  "properties": {
    "iso:country":"IN",
    "ks:ks_name":"Nanda Mohanpur",
    "ks:ks_pop":366,
    "ks:ks_type":"VILLAGE",
    "ks:ks_uagg_main":0,
    "name:eng_x_preferred":[
        "Nanda Mohanpur"
    ],
    "wof:name":"Nanda Mohanpur",
    "wof:placetype":"neighbourhood",
    "wof:population":366
},
  "geometry": {"coordinates":[87.468682,23.31596],"type":"Point"}
}