{
  "type": "Feature",
  "properties": {
    "gn:admin1_code":"23.0",
    "gn:admin2_code":"49.0",
    "gn:asciiname":"Nasir",
    "gn:country_code":"IN",
    "gn:dem":233,
    "gn:feature_class":"P",
    "gn:feature_code":"PPL",
    "gn:name":"Nas\u012br",
    "gn:population":0,
    "gn:timezone":"Asia/Kolkata",
    "iso:country":"IN",
    "name:ell_x_preferred":[
        "\u039d\u03b1\u03c3\u03af\u03c1"
    ],
    "name:fas_x_preferred":[
        "\u0646\u0635\u06cc\u0631"
    ],
    "name:heb_x_preferred":[
        "\u05e0\u05e1\u05d9\u05e8"
    ],
    "name:hin_x_preferred":[
        "\u0928\u093e\u0938\u093f\u0930"
    ],
    "name:hun_x_preferred":[
        "Nasir"
    ],
    "name:ind_x_preferred":[
        "Nasir"
    ],
    "name:ita_x_preferred":[
        "Nasir"
    ],
    "name:kor_x_preferred":[
        "\ub098\uc2dc\ub974"
    ],
    "name:por_x_preferred":[
        "Nasir"
    ],
    "name:spa_x_preferred":[
        "Nasir"
    ],
    "name:swe_x_preferred":[
        "Nasir"
    ],
    "name:tur_x_preferred":[
        "Nasir"
    ],
    "name:ukr_x_preferred":[
        "\u041d\u0430\u0441\u0456\u0440"
    ],
    "name:urd_x_preferred":[
        "\u0646\u0627\u0635\u0631"
    ],
    "name:vie_x_preferred":[
        "Nasir"
    ],
    "wof:name":"Nasir",
    "wof:placetype":"locality"
},
  "geometry": {"coordinates":[74.84408000000001,31.88226],"type":"Point"}
}