{
  "type": "Feature",
  "properties": {
    "iso:country":"IN",
    "ks:ks_name":"Rasanga",
    "ks:ks_pop":988,
    "ks:ks_type":"VILLAGE",
    "name:eng_x_preferred":[
        "Rasanga"
    ],
    "wof:name":"Rasanga",
    "wof:placetype":"locality",
    "wof:population":988
},
  "geometry": {"coordinates":[85.004762,20.425796],"type":"Point"}
}