{
  "type": "Feature",
  "properties": {
    "gn:admin1_code":"36.0",
    "gn:admin2_code":"150.0",
    "gn:asciiname":"Manjha",
    "gn:country_code":"IN",
    "gn:dem":163,
    "gn:feature_class":"P",
    "gn:feature_code":"PPL",
    "gn:name":"Manjha",
    "gn:population":0,
    "gn:timezone":"Asia/Kolkata",
    "iso:country":"IN",
    "name:und_x_variant":[
        "Ar\u0101zi Mutn\u0101za"
    ],
    "wof:name":"Manjha",
    "wof:placetype":"locality"
},
  "geometry": {"coordinates":[79.40553,28.24304],"type":"Point"}
}