{
  "type": "Feature",
  "properties": {
    "gn:country":"IN",
    "gn:fcode":"PPL",
    "gn:pop":12373,
    "iso:country":"IN",
    "name:ben_x_preferred":[
        "\u0993\u09af\u09bc\u09be\u09a6\u0997\u09be\u0981\u0993"
    ],
    "name:bpy_x_preferred":[
        "\u09f1\u09be\u09a6\u0997\u09be\u0981\u0993"
    ],
    "name:ceb_x_preferred":[
        "Wadgaon"
    ],
    "name:eng_x_preferred":[
        "Vadgaon"
    ],
    "name:fra_x_preferred":[
        "Vadgaon"
    ],
    "name:ita_x_preferred":[
        "Vadgaon"
    ],
    "name:mar_x_preferred":[
        "\u0935\u0921\u0917\u093e\u0935"
    ],
    "name:msa_x_preferred":[
        "Vadgaon"
    ],
    "name:nan_x_preferred":[
        "Vadgaon"
    ],
    "name:nld_x_preferred":[
        "Vadgaon"
    ],
    "name:por_x_preferred":[
        "Vadgaon"
    ],
    "name:swe_x_preferred":[
        "Wadgaon"
    ],
    "name:unk_x_variant":[
        "Vadgaon"
    ],
    "name:urd_x_preferred":[
        "\u0648\u0691\u06af\u0627\u0624\u06ba \u0645\u0627\u0648\u0644"
    ],
    "name:vie_x_preferred":[
        "Vadgaon"
    ],
    "name:zho_x_preferred":[
        "\u74e6\u5fb7\u52a0\u5965\u6069"
    ],
    "qs:name":"Wadgaon",
    "qs:photos_9r":0,
    "qs:photos_sr":0,
    "qs:pop_sr":"6",
    "wof:name":"Wadgaon",
    "wof:placetype":"locality",
    "wof:population":12373
},
  "geometry": {"coordinates":[73.63945,18.7392],"type":"Point"}
}