{
  "type": "Feature",
  "properties": {
    "iso:country":"IN",
    "ks:ks_alt_nam":"Chivh pada falia",
    "ks:ks_name":"Chivh Pada Falia",
    "ks:ks_pop":599,
    "ks:ks_type":"HABITATION",
    "name:eng_x_preferred":[
        "Chivh Pada Falia"
    ],
    "wof:name":"Chivh Pada Falia",
    "wof:placetype":"locality",
    "wof:population":599
},
  "geometry": {"coordinates":[73.16369400000001,20.439167],"type":"Point"}
}