{
  "type": "Feature",
  "properties": {
    "iso:country":"IN",
    "ks:ks_name":"Pernodi",
    "ks:ks_pop":358,
    "ks:ks_type":"HABITATION",
    "name:eng_x_preferred":[
        "Pernodi"
    ],
    "wof:name":"Pernodi",
    "wof:placetype":"locality",
    "wof:population":358
},
  "geometry": {"coordinates":[75.10825699999999,13.144688],"type":"Point"}
}