{
  "type": "Feature",
  "properties": {
    "iso:country":"IN",
    "ks:ks_name":"Ponkal",
    "ks:ks_pop":1624,
    "ks:ks_type":"HABITATION",
    "name:eng_x_preferred":[
        "Ponkal"
    ],
    "wof:name":"Ponkal",
    "wof:placetype":"locality",
    "wof:population":1624
},
  "geometry": {"coordinates":[75.36434199999999,12.299437],"type":"Point"}
}