{
  "type": "Feature",
  "properties": {
    "gn:admin1_code":"34",
    "gn:admin2_code":"237.0",
    "gn:asciiname":"Worhanpur",
    "gn:country_code":"IN",
    "gn:dem":82,
    "gn:feature_class":"P",
    "gn:feature_code":"PPL",
    "gn:name":"Worhanpur",
    "gn:population":0,
    "gn:timezone":"Asia/Kolkata",
    "iso:country":"IN",
    "ks:ks_name":"Worhanpur",
    "ks:ks_type":"VILLAGE",
    "ks:ks_uagg_main":0,
    "name:eng_x_preferred":[
        "Worhanpur"
    ],
    "wof:name":"Worhanpur",
    "wof:placetype":"neighbourhood"
},
  "geometry": {"coordinates":[85.530815,24.957147],"type":"Point"}
}