{
  "type": "Feature",
  "properties": {
    "gn:admin1_code":"13.0",
    "gn:admin2_code":"589.0",
    "gn:asciiname":"Sivapuram",
    "gn:country_code":"IN",
    "gn:dem":94,
    "gn:feature_class":"P",
    "gn:feature_code":"PPL",
    "gn:name":"Sivapuram",
    "gn:population":0,
    "gn:timezone":"Asia/Kolkata",
    "iso:country":"IN",
    "ks:ks_name":"Sivapuram",
    "ks:ks_pop":1466,
    "ks:ks_type":"VILLAGE",
    "ks:ks_uagg_main":0,
    "name:eng_x_preferred":[
        "Sivapuram"
    ],
    "wof:name":"Sivapuram",
    "wof:placetype":"neighbourhood",
    "wof:population":1466
},
  "geometry": {"coordinates":[75.604642,11.907267],"type":"Point"}
}