{
  "type": "Feature",
  "properties": {
    "gn:admin1_code":"2.0",
    "gn:admin2_code":"544.0",
    "gn:asciiname":"Nakkagoi",
    "gn:country_code":"IN",
    "gn:dem":998,
    "gn:feature_class":"P",
    "gn:feature_code":"PPL",
    "gn:name":"Nakkagoi",
    "gn:population":0,
    "gn:timezone":"Asia/Kolkata",
    "iso:country":"IN",
    "ks:ks_name":"Nakkagoyyi",
    "ks:ks_pop":73,
    "ks:ks_type":"HABITATION",
    "name:eng_x_preferred":[
        "Nakkagoyyi"
    ],
    "name:eng_x_variant":[
        "Nakkagoi"
    ],
    "wof:name":"Nakkagoyyi",
    "wof:placetype":"locality",
    "wof:population":73
},
  "geometry": {"coordinates":[82.729106,18.102765],"type":"Point"}
}