{
  "type": "Feature",
  "properties": {
    "iso:country":"IN",
    "ks:ks_name":"Badagundurisahi",
    "ks:ks_pop":68,
    "ks:ks_type":"VILLAGE",
    "name:eng_x_preferred":[
        "Badagundurisahi"
    ],
    "wof:name":"Badagundurisahi",
    "wof:placetype":"locality",
    "wof:population":68
},
  "geometry": {"coordinates":[84.618287,20.514601],"type":"Point"}
}