{
  "type": "Feature",
  "properties": {
    "gn:admin1_code":"37.0",
    "gn:admin2_code":"417.0",
    "gn:asciiname":"Kodoli",
    "gn:country_code":"IN",
    "gn:dem":323,
    "gn:feature_class":"P",
    "gn:feature_code":"PPLL",
    "gn:name":"Kodoli",
    "gn:population":0,
    "gn:timezone":"Asia/Kolkata",
    "iso:country":"IN",
    "name:ben_x_preferred":[
        "\u0995\u09cb\u09a6\u09cb\u09b2\u09bf"
    ],
    "name:bpy_x_preferred":[
        "\u0995\u09cb\u09a6\u09cb\u09b2\u09bf"
    ],
    "name:ceb_x_preferred":[
        "Kodoli"
    ],
    "name:ita_x_preferred":[
        "Kodoli"
    ],
    "name:msa_x_preferred":[
        "Kodoli"
    ],
    "name:new_x_preferred":[
        "\u0915\u094b\u0926\u094b\u0932\u0940"
    ],
    "name:nld_x_preferred":[
        "Kodoli"
    ],
    "name:por_x_preferred":[
        "Kodoli"
    ],
    "name:swe_x_preferred":[
        "Kodoli"
    ],
    "name:urd_x_preferred":[
        "\u06a9\u0648\u0688\u0648\u0644\u06cc"
    ],
    "name:vie_x_preferred":[
        "Kodoli"
    ],
    "name:zho_x_preferred":[
        "\u79d1\u591a\u5229"
    ],
    "wof:name":"Kodoli",
    "wof:placetype":"locality"
},
  "geometry": {"coordinates":[81.17523,18.97554],"type":"Point"}
}