{
  "type": "Feature",
  "properties": {
    "gn:admin1_code":"2.0",
    "gn:admin2_code":"552.0",
    "gn:asciiname":"Joharapuram",
    "gn:country_code":"IN",
    "gn:dem":284,
    "gn:feature_class":"P",
    "gn:feature_code":"PPL",
    "gn:name":"Johar\u0101puram",
    "gn:population":0,
    "gn:timezone":"Asia/Kolkata",
    "iso:country":"IN",
    "ks:ks_alt_nam":"Johar\u0101puram",
    "ks:ks_name":"Joharapuram",
    "ks:ks_type":"VILLAGE",
    "ks:ks_uagg_main":0,
    "name:eng_x_preferred":[
        "Joharapuram"
    ],
    "name:eng_x_variant":[
        "Johar\u0101puram"
    ],
    "name:hin_x_preferred":[
        "\u091c\u094a\u0939\u0930\u093e\u092a\u0941\u0930\u0902"
    ],
    "name:new_x_preferred":[
        "\u091c\u094a\u0939\u0930\u093e\u092a\u0941\u0930\u0902"
    ],
    "name:tel_x_preferred":[
        "\u0c1c\u0c4a\u0c39\u0c30\u0c3e\u0c2a\u0c41\u0c30\u0c02"
    ],
    "name:urd_x_preferred":[
        "\u062c\u0648\u06c1\u0631\u0627\u067e\u0648\u0631\u0645"
    ],
    "wof:name":"Joharapuram",
    "wof:placetype":"locality"
},
  "geometry": {"coordinates":[78.060928,15.813956],"type":"Point"}
}