{
  "type": "Feature",
  "properties": {
    "gn:admin1_code":"23.0",
    "gn:admin2_code":"36.0",
    "gn:asciiname":"Nangal Narayan",
    "gn:country_code":"IN",
    "gn:dem":227,
    "gn:feature_class":"P",
    "gn:feature_code":"PPL",
    "gn:name":"Nangal N\u0101r\u0101yan",
    "gn:population":0,
    "gn:timezone":"Asia/Kolkata",
    "iso:country":"IN",
    "ks:ks_alt_nam":"Nangal N\u0101r\u0101yan",
    "ks:ks_name":"Nangal Narayan",
    "ks:ks_pop":104,
    "ks:ks_type":"VILLAGE",
    "name:eng_x_preferred":[
        "Nangal Narayan"
    ],
    "name:eng_x_variant":[
        "Nangal N\u0101r\u0101yan"
    ],
    "wof:name":"Nangal Narayan",
    "wof:placetype":"locality",
    "wof:population":104
},
  "geometry": {"coordinates":[75.406074,31.325221],"type":"Point"}
}