{
  "type": "Feature",
  "properties": {
    "gn:admin1_code":"39",
    "gn:admin2_code":"61.0",
    "gn:asciiname":"Dobela",
    "gn:country_code":"IN",
    "gn:dem":1547,
    "gn:feature_class":"P",
    "gn:feature_code":"PPL",
    "gn:name":"Dobela",
    "gn:population":0,
    "gn:timezone":"Asia/Kolkata",
    "iso:country":"IN",
    "wof:name":"Dobela",
    "wof:placetype":"neighbourhood"
},
  "geometry": {"coordinates":[78.79561,30.09923],"type":"Point"}
}