{
  "type": "Feature",
  "properties": {
    "gn:admin1_code":"13.0",
    "gn:admin2_code":"593.0",
    "gn:asciiname":"Kavandikal",
    "gn:country_code":"IN",
    "gn:dem":704,
    "gn:feature_class":"P",
    "gn:feature_code":"PPL",
    "gn:name":"Kavandikal",
    "gn:population":0,
    "gn:timezone":"Asia/Kolkata",
    "iso:country":"IN",
    "ks:ks_name":"Kavundikkal",
    "ks:ks_pop":694,
    "ks:ks_type":"HABITATION",
    "name:eng_x_preferred":[
        "Kavundikkal"
    ],
    "name:eng_x_variant":[
        "Kavandikal"
    ],
    "wof:name":"Kavundikkal",
    "wof:placetype":"locality",
    "wof:population":694
},
  "geometry": {"coordinates":[76.618629,11.09026],"type":"Point"}
}