{
  "type": "Feature",
  "properties": {
    "iso:country":"IN",
    "ks:ks_name":"Barady Beedu",
    "ks:ks_pop":205,
    "ks:ks_type":"HABITATION",
    "name:eng_x_preferred":[
        "Barady Beedu"
    ],
    "wof:name":"Barady Beedu",
    "wof:placetype":"locality",
    "wof:population":205
},
  "geometry": {"coordinates":[74.975353,13.15545],"type":"Point"}
}