{
  "type": "Feature",
  "properties": {
    "gn:admin1_code":"12",
    "gn:admin2_code":"12.0",
    "gn:asciiname":"Kamla",
    "gn:country_code":"IN",
    "gn:dem":1747,
    "gn:feature_class":"P",
    "gn:feature_code":"PPL",
    "gn:name":"Kamla",
    "gn:population":0,
    "gn:timezone":"Asia/Kolkata",
    "iso:country":"IN",
    "name:ben_x_preferred":[
        "\u0995\u09ae\u09b2\u09be"
    ],
    "name:ceb_x_preferred":[
        "Kamla"
    ],
    "name:swe_x_preferred":[
        "Kamla"
    ],
    "wof:name":"Kamla",
    "wof:placetype":"locality"
},
  "geometry": {"coordinates":[75.10766,33.88373],"type":"Point"}
}