{
  "type": "Feature",
  "properties": {
    "iso:country":"IN",
    "ks:ks_name":"Jawayat",
    "ks:ks_pop":355,
    "ks:ks_type":"HABITATION",
    "ks:ks_uagg_main":0,
    "name:eng_x_preferred":[
        "Jawayat"
    ],
    "wof:name":"Jawayat",
    "wof:placetype":"neighbourhood",
    "wof:population":355
},
  "geometry": {"coordinates":[86.561593,25.247108],"type":"Point"}
}