{
  "type": "Feature",
  "properties": {
    "gn:admin1_code":"38.0",
    "gn:admin2_code":"347.0",
    "gn:asciiname":"Kurkuta",
    "gn:country_code":"IN",
    "gn:dem":433,
    "gn:feature_class":"P",
    "gn:feature_code":"PPL",
    "gn:name":"Kurkut\u0101",
    "gn:population":0,
    "gn:timezone":"Asia/Kolkata",
    "iso:country":"IN",
    "ks:ks_alt_nam":"Kurkut\u0101",
    "ks:ks_name":"Kurkuta",
    "ks:ks_type":"VILLAGE",
    "name:eng_x_preferred":[
        "Kurkuta"
    ],
    "name:eng_x_variant":[
        "Kurkut\u0101"
    ],
    "wof:name":"Kurkuta",
    "wof:placetype":"locality"
},
  "geometry": {"coordinates":[85.009174,24.217861],"type":"Point"}
}