{
  "type": "Feature",
  "properties": {
    "iso:country":"IN",
    "ks:ks_name":"Hathiyani Muvadi",
    "ks:ks_pop":165,
    "ks:ks_type":"VILLAGE",
    "name:eng_x_preferred":[
        "Hathiyani Muvadi"
    ],
    "wof:name":"Hathiyani Muvadi",
    "wof:placetype":"locality",
    "wof:population":165
},
  "geometry": {"coordinates":[72.953812,23.002642],"type":"Point"}
}