{
  "type": "Feature",
  "properties": {
    "gn:admin1_code":"36",
    "gn:admin2_code":"149.0",
    "gn:asciiname":"Jati",
    "gn:country_code":"IN",
    "gn:dem":152,
    "gn:feature_class":"P",
    "gn:feature_code":"PPL",
    "gn:name":"J\u0101ti",
    "gn:population":0,
    "gn:timezone":"Asia/Kolkata",
    "iso:country":"IN",
    "ks:ks_alt_nam":"J\u0101ti",
    "ks:ks_name":"Jati",
    "ks:ks_pop":386,
    "ks:ks_type":"VILLAGE",
    "ks:ks_uagg_main":0,
    "name:bih_x_preferred":[
        "\u091c\u093e\u0924\u093f"
    ],
    "name:ceb_x_preferred":[
        "Jati"
    ],
    "name:eng_x_preferred":[
        "Jati"
    ],
    "name:eng_x_variant":[
        "J\u0101ti"
    ],
    "name:fra_x_preferred":[
        "Jati"
    ],
    "name:ita_x_preferred":[
        "Jati"
    ],
    "name:jav_x_preferred":[
        "Jati"
    ],
    "name:mal_x_preferred":[
        "\u0d1c\u0d3e\u0d24\u0d3f"
    ],
    "name:nld_x_preferred":[
        "Jati"
    ],
    "name:swe_x_preferred":[
        "Jati"
    ],
    "name:vie_x_preferred":[
        "Jati"
    ],
    "wof:name":"Jati",
    "wof:placetype":"neighbourhood",
    "wof:population":386
},
  "geometry": {"coordinates":[79.27910199999999,27.716093],"type":"Point"}
}