{
  "type": "Feature",
  "properties": {
    "gn:admin1_code":"12.0",
    "gn:admin2_code":"005",
    "gn:asciiname":"Waranpathri",
    "gn:country_code":"IN",
    "gn:dem":2740,
    "gn:feature_class":"P",
    "gn:feature_code":"PPL",
    "gn:name":"Waranpathri",
    "gn:population":0,
    "gn:timezone":"Asia/Kolkata",
    "iso:country":"IN",
    "wof:name":"Waranpathri",
    "wof:placetype":"locality"
},
  "geometry": {"coordinates":[74.32361,33.85897],"type":"Point"}
}