{
  "type": "Feature",
  "properties": {
    "iso:country":"IN",
    "ks:ks_name":"Matdjeddu",
    "ks:ks_pop":19,
    "ks:ks_type":"HABITATION",
    "name:eng_x_preferred":[
        "Matdjeddu"
    ],
    "wof:name":"Matdjeddu",
    "wof:placetype":"locality",
    "wof:population":19
},
  "geometry": {"coordinates":[75.021795,13.774081],"type":"Point"}
}