{
  "type": "Feature",
  "properties": {
    "iso:country":"IN",
    "ks:ks_name":"Saregudem",
    "ks:ks_pop":191,
    "ks:ks_type":"HABITATION",
    "name:eng_x_preferred":[
        "Saregudem"
    ],
    "wof:name":"Saregudem",
    "wof:placetype":"locality",
    "wof:population":191
},
  "geometry": {"coordinates":[79.425144,16.634554],"type":"Point"}
}