{
  "type": "Feature",
  "properties": {
    "iso:country":"IN",
    "ks:ks_name":"Takteoa",
    "ks:ks_pop":604,
    "ks:ks_type":"VILLAGE",
    "name:eng_x_preferred":[
        "Takteoa"
    ],
    "wof:name":"Takteoa",
    "wof:placetype":"locality",
    "wof:population":604
},
  "geometry": {"coordinates":[81.47059299999999,22.378857],"type":"Point"}
}