{
  "type": "Feature",
  "properties": {
    "gn:admin1_code":"11.0",
    "gn:admin2_code":"33.0",
    "gn:asciiname":"Nin",
    "gn:country_code":"IN",
    "gn:dem":1929,
    "gn:feature_class":"P",
    "gn:feature_code":"PPL",
    "gn:name":"N\u012bn",
    "gn:population":0,
    "gn:timezone":"Asia/Kolkata",
    "iso:country":"IN",
    "name:bel_x_preferred":[
        "\u041d\u0456\u043d"
    ],
    "name:bos_x_preferred":[
        "Nin"
    ],
    "name:cat_x_preferred":[
        "Nin"
    ],
    "name:ceb_x_preferred":[
        "Nin"
    ],
    "name:ces_x_preferred":[
        "Nin"
    ],
    "name:deu_x_preferred":[
        "Nin"
    ],
    "name:fin_x_preferred":[
        "Nin"
    ],
    "name:fra_x_preferred":[
        "Nin"
    ],
    "name:heb_x_preferred":[
        "\u05e0\u05d9\u05df"
    ],
    "name:slk_x_preferred":[
        "Nin"
    ],
    "name:spa_x_preferred":[
        "Nin"
    ],
    "name:srp_x_preferred":[
        "\u041d\u0438\u043d"
    ],
    "name:swe_x_preferred":[
        "Nin"
    ],
    "name:ukr_x_preferred":[
        "\u041d\u0456\u043d"
    ],
    "wof:name":"Nin",
    "wof:placetype":"locality"
},
  "geometry": {"coordinates":[77.2792,31.00818],"type":"Point"}
}