{
  "type": "Feature",
  "properties": {
    "iso:country":"IN",
    "ks:ks_name":"Rahadigoda",
    "ks:ks_pop":256,
    "ks:ks_type":"HABITATION",
    "name:eng_x_preferred":[
        "Rahadigoda"
    ],
    "wof:name":"Rahadigoda",
    "wof:placetype":"locality",
    "wof:population":256
},
  "geometry": {"coordinates":[86.091157,22.112125],"type":"Point"}
}