{
  "type": "Feature",
  "properties": {
    "gn:admin1_code":"35",
    "gn:admin2_code":"424.0",
    "gn:asciiname":"Ramsagara",
    "gn:country_code":"IN",
    "gn:dem":244,
    "gn:feature_class":"P",
    "gn:feature_code":"PPL",
    "gn:name":"Ramsagara",
    "gn:population":0,
    "gn:timezone":"Asia/Kolkata",
    "iso:country":"IN",
    "name:und_x_variant":[
        "R\u0101ms\u0101gar",
        "Ramsagara"
    ],
    "wof:name":"Ramsagara",
    "wof:placetype":"locality"
},
  "geometry": {"coordinates":[79.30363,24.94072],"type":"Point"}
}