{
  "type": "Feature",
  "properties": {
    "iso:country":"IN",
    "ks:ks_name":"Chakriguda",
    "ks:ks_pop":25,
    "ks:ks_type":"VILLAGE",
    "name:eng_x_preferred":[
        "Chakriguda"
    ],
    "wof:name":"Chakriguda",
    "wof:placetype":"locality",
    "wof:population":25
},
  "geometry": {"coordinates":[83.48409599999999,19.52311],"type":"Point"}
}