{
  "type": "Feature",
  "properties": {
    "iso:country":"IN",
    "ks:ks_alt_nam":"SABLEWADI",
    "ks:ks_name":"Sablewadi",
    "ks:ks_pop":1,
    "ks:ks_type":"HABITATION",
    "name:eng_x_preferred":[
        "Sablewadi"
    ],
    "wof:name":"Sablewadi",
    "wof:placetype":"locality",
    "wof:population":1
},
  "geometry": {"coordinates":[75.71898,17.719543],"type":"Point"}
}