{
  "type": "Feature",
  "properties": {
    "gn:admin1_code":"21.0",
    "gn:admin2_code":"385.0",
    "gn:asciiname":"Sagadabhanga",
    "gn:country_code":"IN",
    "gn:dem":119,
    "gn:feature_class":"P",
    "gn:feature_code":"PPL",
    "gn:name":"Sagadabhanga",
    "gn:population":0,
    "gn:timezone":"Asia/Kolkata",
    "iso:country":"IN",
    "wof:name":"Sagadabhanga",
    "wof:placetype":"locality"
},
  "geometry": {"coordinates":[84.82876999999998,20.46648],"type":"Point"}
}