{
  "type": "Feature",
  "properties": {
    "gn:admin1_code":"21.0",
    "gn:admin2_code":"385.0",
    "gn:asciiname":"Sagadabhanga",
    "gn:country_code":"IN",
    "gn:dem":119,
    "gn:feature_class":"P",
    "gn:feature_code":"PPL",
    "gn:name":"Sagadabhanga",
    "gn:population":0,
    "gn:timezone":"Asia/Kolkata",
    "iso:country":"IN",
    "ks:ks_name":"Sagadabhanga",
    "ks:ks_pop":42,
    "ks:ks_type":"VILLAGE",
    "name:eng_x_preferred":[
        "Sagadabhanga"
    ],
    "wof:name":"Sagadabhanga",
    "wof:placetype":"locality",
    "wof:population":42
},
  "geometry": {"coordinates":[84.820178,20.46216],"type":"Point"}
}