{
  "type": "Feature",
  "properties": {
    "gn:admin1_code":"11.0",
    "gn:admin2_code":"33.0",
    "gn:asciiname":"Bijli",
    "gn:country_code":"IN",
    "gn:dem":2562,
    "gn:feature_class":"P",
    "gn:feature_code":"PPL",
    "gn:name":"Bijli",
    "gn:population":0,
    "gn:timezone":"Asia/Kolkata",
    "iso:country":"IN",
    "wof:name":"Bijli",
    "wof:placetype":"locality"
},
  "geometry": {"coordinates":[77.45678000000002,31.20324],"type":"Point"}
}