{
  "type": "Feature",
  "properties": {
    "iso:country":"IN",
    "ks:ks_name":"Balabhadrapur",
    "ks:ks_pop":1550,
    "ks:ks_type":"VILLAGE",
    "ks:ks_uagg_main":0,
    "name:eng_x_preferred":[
        "Balabhadrapur"
    ],
    "wof:name":"Balabhadrapur",
    "wof:placetype":"neighbourhood",
    "wof:population":1550
},
  "geometry": {"coordinates":[86.294034,20.563151],"type":"Point"}
}