{
  "type": "Feature",
  "properties": {
    "gn:admin1_code":"12.0",
    "gn:admin2_code":"022",
    "gn:asciiname":"Marhajpur",
    "gn:country_code":"IN",
    "gn:dem":297,
    "gn:feature_class":"P",
    "gn:feature_code":"PPL",
    "gn:name":"Marh\u0101jpur",
    "gn:population":0,
    "gn:timezone":"Asia/Kolkata",
    "iso:country":"IN",
    "name:und_x_variant":[
        "Marh\u0101jpur",
        "Mah\u0101r\u0101jpur"
    ],
    "wof:name":"Marhajpur",
    "wof:placetype":"locality"
},
  "geometry": {"coordinates":[74.92271,32.51287],"type":"Point"}
}