{
  "type": "Feature",
  "properties": {
    "gn:admin1_code":"12.0",
    "gn:admin2_code":"2.0",
    "gn:asciiname":"Tsakapur",
    "gn:country_code":"IN",
    "gn:dem":1605,
    "gn:feature_class":"P",
    "gn:feature_code":"PPL",
    "gn:name":"Tsakapur",
    "gn:population":0,
    "gn:timezone":"Asia/Kolkata",
    "iso:country":"IN",
    "wof:name":"Tsakapur",
    "wof:placetype":"locality"
},
  "geometry": {"coordinates":[74.80549999999999,33.95788],"type":"Point"}
}