{
  "type": "Feature",
  "properties": {
    "iso:country":"IN",
    "ks:ks_alt_nam":"PACHVNDE WASTI",
    "ks:ks_name":"Pachvnde Wasti",
    "ks:ks_pop":136,
    "ks:ks_type":"HABITATION",
    "name:eng_x_preferred":[
        "Pachvnde Wasti"
    ],
    "wof:name":"Pachvnde Wasti",
    "wof:placetype":"locality",
    "wof:population":136
},
  "geometry": {"coordinates":[74.795219,16.931072],"type":"Point"}
}