{
  "type": "Feature",
  "properties": {
    "iso:country":"IN",
    "ks:ks_alt_nam":"St coloni jn",
    "ks:ks_name":"St Coloni Jn",
    "ks:ks_pop":519,
    "ks:ks_type":"HABITATION",
    "name:eng_x_preferred":[
        "St Coloni Jn"
    ],
    "wof:name":"St Coloni Jn",
    "wof:placetype":"locality",
    "wof:population":519
},
  "geometry": {"coordinates":[76.269961,11.345841],"type":"Point"}
}