{
  "type": "Feature",
  "properties": {
    "iso:country":"IN",
    "ks:ks_name":"Birwahipara",
    "ks:ks_pop":73,
    "ks:ks_type":"HABITATION",
    "name:eng_x_preferred":[
        "Birwahipara"
    ],
    "wof:name":"Birwahipara",
    "wof:placetype":"locality",
    "wof:population":73
},
  "geometry": {"coordinates":[81.250443,19.166226],"type":"Point"}
}