{
  "type": "Feature",
  "properties": {
    "iso:country":"IN",
    "ks:ks_name":"Jamalpani No.2",
    "ks:ks_pop":348,
    "ks:ks_type":"VILLAGE",
    "name:eng_x_preferred":[
        "Jamalpani No.2"
    ],
    "wof:name":"Jamalpani No.2",
    "wof:placetype":"locality",
    "wof:population":348
},
  "geometry": {"coordinates":[78.79065199999999,21.548044],"type":"Point"}
}