{
  "type": "Feature",
  "properties": {
    "iso:country":"IN",
    "ks:ks_alt_nam":"B\u0101ndarchuwa",
    "ks:ks_name":"Bandarchuwa",
    "ks:ks_type":"VILLAGE",
    "name:eng_x_preferred":[
        "Bandarchuwa"
    ],
    "name:eng_x_variant":[
        "B\u0101ndarchuwa"
    ],
    "wof:name":"Bandarchuwa",
    "wof:placetype":"locality"
},
  "geometry": {"coordinates":[79.58443699999999,21.03685],"type":"Point"}
}