{
  "type": "Feature",
  "properties": {
    "iso:country":"IN",
    "ks:ks_name":"Ghutarapara",
    "ks:ks_pop":238,
    "ks:ks_type":"HABITATION",
    "name:eng_x_preferred":[
        "Ghutarapara"
    ],
    "wof:name":"Ghutarapara",
    "wof:placetype":"locality",
    "wof:population":238
},
  "geometry": {"coordinates":[82.727861,23.42417],"type":"Point"}
}