{
  "type": "Feature",
  "properties": {
    "gn:admin1_code":"25.0",
    "gn:admin2_code":"607",
    "gn:asciiname":"Ulundurpet",
    "gn:cc2":"IN",
    "gn:country_code":"IN",
    "gn:dem":77,
    "gn:feature_class":"P",
    "gn:feature_code":"PPL",
    "gn:name":"Ulundurpet",
    "gn:population":0,
    "gn:timezone":"Asia/Kolkata",
    "iso:country":"IN",
    "name:und_x_variant":[
        "Ulundur",
        "Ulund\u016brpettai",
        "Ulundurpet",
        "K\u012bran\u016br"
    ],
    "wof:name":"Ulundurpet",
    "wof:placetype":"locality"
},
  "geometry": {"coordinates":[79.2873,11.69099],"type":"Point"}
}