{
  "type": "Feature",
  "properties": {
    "iso:country":"IN",
    "ks:ks_name":"Manikpur",
    "ks:ks_pop":267,
    "ks:ks_type":"VILLAGE",
    "name:eng_x_preferred":[
        "Manikpur"
    ],
    "wof:name":"Manikpur",
    "wof:placetype":"locality",
    "wof:population":267
},
  "geometry": {"coordinates":[78.121184,26.041938],"type":"Point"}
}