{
  "type": "Feature",
  "properties": {
    "gn:admin1_code":"19",
    "gn:admin2_code":"558.0",
    "gn:asciiname":"Tuljapur",
    "gn:country_code":"IN",
    "gn:dem":558,
    "gn:feature_class":"P",
    "gn:feature_code":"PPL",
    "gn:name":"Tulj\u0101pur",
    "gn:population":0,
    "gn:timezone":"Asia/Kolkata",
    "iso:country":"IN",
    "name:ben_x_preferred":[
        "\u09a4\u09c1\u09b2\u099c\u09be\u09aa\u09c1\u09b0"
    ],
    "name:bpy_x_preferred":[
        "\u09a4\u09c1\u09b2\u099c\u09be\u09aa\u09c1\u09b0"
    ],
    "name:ceb_x_preferred":[
        "Tulj\u0101pur"
    ],
    "name:deu_x_preferred":[
        "Tuljapur"
    ],
    "name:hif_x_preferred":[
        "Tuljapur"
    ],
    "name:ita_x_preferred":[
        "Tuljapur"
    ],
    "name:jpn_x_preferred":[
        "\u30c8\u30a5\u30eb\u30b8\u30e3\u30fc\u30d7\u30eb"
    ],
    "name:kan_x_preferred":[
        "\u0ca4\u0cc1\u0cb3\u0c9c\u0cbe\u0caa\u0cc1\u0cb0"
    ],
    "name:mar_x_preferred":[
        "\u0924\u0941\u0933\u091c\u093e\u092a\u0942\u0930"
    ],
    "name:mlg_x_preferred":[
        "Tuljapur"
    ],
    "name:msa_x_preferred":[
        "Tuljapur"
    ],
    "name:nld_x_preferred":[
        "Tuljapur"
    ],
    "name:swe_x_preferred":[
        "Tulj\u0101pur"
    ],
    "name:urd_x_preferred":[
        "\u062a\u0644\u062c\u0627\u067e\u0648\u0631"
    ],
    "name:vie_x_preferred":[
        "Tuljapur"
    ],
    "name:zho_x_preferred":[
        "\u56fe\u5c14\u8d3e\u666e\u5c14"
    ],
    "wof:name":"Tuljapur",
    "wof:placetype":"locality"
},
  "geometry": {"coordinates":[77.43233000000002,18.21866],"type":"Point"}
}