{
  "type": "Feature",
  "properties": {
    "iso:country":"IN",
    "ks:ks_name":"Dhulia",
    "ks:ks_pop":389,
    "ks:ks_type":"VILLAGE",
    "name:eng_x_preferred":[
        "Dhulia"
    ],
    "wof:name":"Dhulia",
    "wof:placetype":"locality",
    "wof:population":389
},
  "geometry": {"coordinates":[87.56626900000001,22.319356],"type":"Point"}
}