{
  "type": "Feature",
  "properties": {
    "iso:country":"IN",
    "ks:ks_name":"Uttarpara",
    "ks:ks_pop":2500,
    "ks:ks_type":"HABITATION",
    "ks:ks_uagg_main":0,
    "name:eng_x_preferred":[
        "Uttarpara"
    ],
    "wof:name":"Uttarpara",
    "wof:placetype":"neighbourhood",
    "wof:population":2500
},
  "geometry": {"coordinates":[87.844157,22.673471],"type":"Point"}
}