{
  "type": "Feature",
  "properties": {
    "iso:country":"IN",
    "ks:ks_alt_nam":"Laxmigani tanda",
    "ks:ks_name":"Laxmigani Tanda",
    "ks:ks_pop":150,
    "ks:ks_type":"HABITATION",
    "name:eng_x_preferred":[
        "Laxmigani Tanda"
    ],
    "wof:name":"Laxmigani Tanda",
    "wof:placetype":"locality",
    "wof:population":150
},
  "geometry": {"coordinates":[78.21961,16.249357],"type":"Point"}
}