{
  "type": "Feature",
  "properties": {
    "iso:country":"IN",
    "ks:ks_name":"Baisiya Chhana",
    "ks:ks_pop":980,
    "ks:ks_type":"VILLAGE",
    "name:eng_x_preferred":[
        "Baisiya Chhana"
    ],
    "wof:name":"Baisiya Chhana",
    "wof:placetype":"locality",
    "wof:population":980
},
  "geometry": {"coordinates":[79.87788999999999,29.696168],"type":"Point"}
}