{
  "type": "Feature",
  "properties": {
    "iso:country":"IN",
    "ks:ks_name":"Kallambala",
    "ks:ks_pop":53,
    "ks:ks_type":"HABITATION",
    "name:eng_x_preferred":[
        "Kallambala"
    ],
    "wof:name":"Kallambala",
    "wof:placetype":"locality",
    "wof:population":53
},
  "geometry": {"coordinates":[76.013611,12.0125],"type":"Point"}
}