{
  "type": "Feature",
  "properties": {
    "iso:country":"IN",
    "ks:ks_name":"Duruda",
    "ks:ks_pop":115,
    "ks:ks_type":"VILLAGE",
    "name:eng_x_preferred":[
        "Duruda"
    ],
    "wof:name":"Duruda",
    "wof:placetype":"locality",
    "wof:population":115
},
  "geometry": {"coordinates":[84.95495200000001,19.958666],"type":"Point"}
}