{
  "type": "Feature",
  "properties": {
    "iso:country":"IN",
    "ks:ks_name":"Kuppankottai",
    "ks:ks_pop":517,
    "ks:ks_type":"HABITATION",
    "ks:ks_uagg_main":0,
    "name:eng_x_preferred":[
        "Kuppankottai"
    ],
    "wof:name":"Kuppankottai",
    "wof:placetype":"neighbourhood",
    "wof:population":517
},
  "geometry": {"coordinates":[78.19823700000001,11.957213],"type":"Point"}
}