{
  "type": "Feature",
  "properties": {
    "iso:country":"IN",
    "ks:ks_alt_nam":"NABAB GANJ",
    "ks:ks_name":"Nabab Ganj",
    "ks:ks_pop":875,
    "ks:ks_type":"HABITATION",
    "ks:ks_uagg_main":0,
    "name:eng_x_preferred":[
        "Nabab Ganj"
    ],
    "wof:name":"Nabab Ganj",
    "wof:placetype":"neighbourhood",
    "wof:population":875
},
  "geometry": {"coordinates":[86.17045,25.18918],"type":"Point"}
}