{
  "type": "Feature",
  "properties": {
    "gn:admin1_code":"40.0",
    "gn:admin2_code":"532.0",
    "gn:asciiname":"Niligudem",
    "gn:country_code":"IN",
    "gn:dem":211,
    "gn:feature_class":"P",
    "gn:feature_code":"PPL",
    "gn:name":"N\u012bligudem",
    "gn:population":0,
    "gn:timezone":"Asia/Kolkata",
    "iso:country":"IN",
    "wof:name":"Niligudem",
    "wof:placetype":"locality"
},
  "geometry": {"coordinates":[79.17652,19.03115],"type":"Point"}
}