{
  "type": "Feature",
  "properties": {
    "iso:country":"IN",
    "ks:ks_name":"Sarbaherua",
    "ks:ks_pop":2119,
    "ks:ks_type":"VILLAGE",
    "ks:ks_uagg_main":0,
    "name:eng_x_preferred":[
        "Sarbaherua"
    ],
    "wof:name":"Sarbaherua",
    "wof:placetype":"neighbourhood",
    "wof:population":2119
},
  "geometry": {"coordinates":[92.19129599999999,26.666916],"type":"Point"}
}