{
  "type": "Feature",
  "properties": {
    "iso:country":"IN",
    "ks:ks_name":"Barbaspur",
    "ks:ks_pop":1491,
    "ks:ks_type":"VILLAGE",
    "name:eng_x_preferred":[
        "Barbaspur"
    ],
    "wof:name":"Barbaspur",
    "wof:placetype":"locality",
    "wof:population":1491
},
  "geometry": {"coordinates":[83.32102399999999,23.387603],"type":"Point"}
}