{
  "type": "Feature",
  "properties": {
    "gn:admin1_code":"35",
    "gn:admin2_code":"466.0",
    "gn:asciiname":"Pamakheri",
    "gn:country_code":"IN",
    "gn:dem":267,
    "gn:feature_class":"P",
    "gn:feature_code":"PPL",
    "gn:name":"P\u0101m\u0101kheri",
    "gn:population":0,
    "gn:timezone":"Asia/Kolkata",
    "iso:country":"IN",
    "name:und_x_variant":[
        "P\u0101m\u0101kheri",
        "P\u0101ma Kheri"
    ],
    "wof:name":"Pamakheri",
    "wof:placetype":"locality"
},
  "geometry": {"coordinates":[76.60538000000003,22.33789],"type":"Point"}
}