{
  "type": "Feature",
  "properties": {
    "gn:admin1_code":"16.0",
    "gn:admin2_code":"498.0",
    "gn:asciiname":"Haria Amba Pada",
    "gn:country_code":"IN",
    "gn:dem":640,
    "gn:feature_class":"P",
    "gn:feature_code":"PPL",
    "gn:name":"H\u0101ria Amba P\u0101da",
    "gn:population":0,
    "gn:timezone":"Asia/Kolkata",
    "iso:country":"IN",
    "wof:name":"Haria Amba Pada",
    "wof:placetype":"locality"
},
  "geometry": {"coordinates":[74.03248000000001,21.04354],"type":"Point"}
}