{
  "type": "Feature",
  "properties": {
    "iso:country":"IN",
    "ks:ks_name":"Dharampur",
    "ks:ks_pop":231,
    "ks:ks_type":"VILLAGE",
    "name:eng_x_preferred":[
        "Dharampur"
    ],
    "wof:name":"Dharampur",
    "wof:placetype":"locality",
    "wof:population":231
},
  "geometry": {"coordinates":[83.307531,22.524312],"type":"Point"}
}