{
  "type": "Feature",
  "properties": {
    "iso:country":"IN",
    "ks:ks_name":"Korvai Gamtal",
    "ks:ks_pop":478,
    "ks:ks_type":"HABITATION",
    "name:eng_x_preferred":[
        "Korvai Gamtal"
    ],
    "wof:name":"Korvai Gamtal",
    "wof:placetype":"locality",
    "wof:population":478
},
  "geometry": {"coordinates":[73.66113900000001,23.372528],"type":"Point"}
}