{
  "type": "Feature",
  "properties": {
    "gn:admin1_code":"25.0",
    "gn:admin2_code":"631.0",
    "gn:asciiname":"Kurubarapalli",
    "gn:country_code":"IN",
    "gn:dem":780,
    "gn:feature_class":"P",
    "gn:feature_code":"PPL",
    "gn:name":"Kurubarapalli",
    "gn:population":0,
    "gn:timezone":"Asia/Kolkata",
    "iso:country":"IN",
    "name:tam_x_preferred":[
        "\u0b95\u0bc1\u0bb0\u0bc1\u0baa\u0bb0\u0baa\u0bb3\u0bcd\u0bb3\u0bbf"
    ],
    "wof:name":"Kurubarapalli",
    "wof:placetype":"locality"
},
  "geometry": {"coordinates":[77.94159000000001,12.54611],"type":"Point"}
}