{
  "type": "Feature",
  "properties": {
    "iso:country":"IN",
    "ks:ks_name":"Badi Hirapur",
    "ks:ks_pop":1103,
    "ks:ks_type":"HABITATION",
    "name:eng_x_preferred":[
        "Badi Hirapur"
    ],
    "wof:name":"Badi Hirapur",
    "wof:placetype":"locality",
    "wof:population":1103
},
  "geometry": {"coordinates":[74.474335,22.375633],"type":"Point"}
}