{
  "type": "Feature",
  "properties": {
    "iso:country":"IN",
    "ks:ks_name":"Damelwa",
    "ks:ks_pop":166,
    "ks:ks_type":"VILLAGE",
    "name:eng_x_preferred":[
        "Damelwa"
    ],
    "wof:name":"Damelwa",
    "wof:placetype":"locality",
    "wof:population":166
},
  "geometry": {"coordinates":[86.004975,24.675348],"type":"Point"}
}