{
  "type": "Feature",
  "properties": {
    "iso:country":"IN",
    "ks:ks_name":"Shivasagar",
    "ks:ks_pop":33,
    "ks:ks_type":"HABITATION",
    "name:eng_x_preferred":[
        "Shivasagar"
    ],
    "wof:name":"Shivasagar",
    "wof:placetype":"locality",
    "wof:population":33
},
  "geometry": {"coordinates":[74.80366600000001,14.359004],"type":"Point"}
}