{
  "type": "Feature",
  "properties": {
    "iso:country":"IN",
    "ks:ks_name":"Majhera",
    "ks:ks_pop":314,
    "ks:ks_type":"HABITATION",
    "name:eng_x_preferred":[
        "Majhera"
    ],
    "wof:name":"Majhera",
    "wof:placetype":"locality",
    "wof:population":314
},
  "geometry": {"coordinates":[77.239766,23.977389],"type":"Point"}
}