{
  "type": "Feature",
  "properties": {
    "iso:country":"IN",
    "ks:ks_name":"Kasira",
    "ks:ks_pop":0,
    "ks:ks_type":"VILLAGE",
    "name:eng_x_preferred":[
        "Kasira"
    ],
    "wof:name":"Kasira",
    "wof:placetype":"locality",
    "wof:population":0
},
  "geometry": {"coordinates":[85.541239,21.75714],"type":"Point"}
}