{
  "type": "Feature",
  "properties": {
    "iso:country":"IN",
    "ks:ks_alt_nam":"G.N.Kandriga",
    "ks:ks_name":"G.n.kandriga",
    "ks:ks_pop":16,
    "ks:ks_type":"HABITATION",
    "name:eng_x_preferred":[
        "G.n.kandriga"
    ],
    "wof:name":"G.n.kandriga",
    "wof:placetype":"locality",
    "wof:population":16
},
  "geometry": {"coordinates":[79.64965100000001,13.323212],"type":"Point"}
}