{
  "type": "Feature",
  "properties": {
    "iso:country":"IN",
    "ks:ks_name":"Lakkattoor North",
    "ks:ks_pop":1761,
    "ks:ks_type":"HABITATION",
    "name:eng_x_preferred":[
        "Lakkattoor North"
    ],
    "wof:name":"Lakkattoor North",
    "wof:placetype":"locality",
    "wof:population":1761
},
  "geometry": {"coordinates":[76.64003,9.616804],"type":"Point"}
}