{
  "type": "Feature",
  "properties": {
    "iso:country":"IN",
    "ks:ks_name":"Nagapur",
    "ks:ks_pop":908,
    "ks:ks_type":"VILLAGE",
    "ks:ks_uagg_main":0,
    "name:eng_x_preferred":[
        "Nagapur"
    ],
    "wof:name":"Nagapur",
    "wof:placetype":"neighbourhood",
    "wof:population":908
},
  "geometry": {"coordinates":[78.325647,20.85521],"type":"Point"}
}