{
  "type": "Feature",
  "properties": {
    "iso:country":"IN",
    "ks:ks_name":"Nagari",
    "ks:ks_pop":182,
    "ks:ks_type":"HABITATION",
    "name:eng_x_preferred":[
        "Nagari"
    ],
    "wof:name":"Nagari",
    "wof:placetype":"locality",
    "wof:population":182
},
  "geometry": {"coordinates":[77.946005,10.05994],"type":"Point"}
}