{
  "type": "Feature",
  "properties": {
    "iso:country":"IN",
    "ks:ks_name":"Kuita",
    "ks:ks_pop":1611,
    "ks:ks_type":"VILLAGE",
    "ks:ks_uagg_main":0,
    "name:eng_x_preferred":[
        "Kuita"
    ],
    "wof:name":"Kuita",
    "wof:placetype":"neighbourhood",
    "wof:population":1611
},
  "geometry": {"coordinates":[87.488608,23.782348],"type":"Point"}
}