{
  "type": "Feature",
  "properties": {
    "gn:admin1_code":"34.0",
    "gn:admin2_code":"204.0",
    "gn:asciiname":"Arara",
    "gn:country_code":"IN",
    "gn:dem":81,
    "gn:feature_class":"P",
    "gn:feature_code":"PPL",
    "gn:name":"Arara",
    "gn:population":0,
    "gn:timezone":"Asia/Kolkata",
    "iso:country":"IN",
    "name:ceb_x_preferred":[
        "Arara"
    ],
    "name:ces_x_preferred":[
        "Arara"
    ],
    "name:deu_x_preferred":[
        "Arara"
    ],
    "name:hrv_x_preferred":[
        "Arara"
    ],
    "name:ita_x_preferred":[
        "Arara"
    ],
    "name:kat_x_preferred":[
        "\u10d0\u10e0\u10d0\u10e0\u10d0"
    ],
    "name:por_x_preferred":[
        "Arara"
    ],
    "name:rus_x_preferred":[
        "\u0410\u0440\u0430\u0440\u0430"
    ],
    "name:slk_x_preferred":[
        "Arara"
    ],
    "name:srp_x_preferred":[
        "\u0410\u0440\u0430\u0440\u0430"
    ],
    "name:swe_x_preferred":[
        "Arara"
    ],
    "name:vie_x_preferred":[
        "Arara"
    ],
    "wof:name":"Arara",
    "wof:placetype":"locality"
},
  "geometry": {"coordinates":[84.92404999999999,26.92121],"type":"Point"}
}