{
  "type": "Feature",
  "properties": {
    "iso:country":"IN",
    "ks:ks_name":"Kalyanachowka",
    "ks:ks_pop":62,
    "ks:ks_type":"HABITATION",
    "name:eng_x_preferred":[
        "Kalyanachowka"
    ],
    "wof:name":"Kalyanachowka",
    "wof:placetype":"locality",
    "wof:population":62
},
  "geometry": {"coordinates":[74.900605,13.939234],"type":"Point"}
}