{
  "type": "Feature",
  "properties": {
    "iso:country":"IN",
    "ks:ks_alt_nam":"Karekattu Kadambu palam Road Start",
    "ks:ks_name":"Karekattu Kadambu Palam Road Start",
    "ks:ks_pop":646,
    "ks:ks_type":"HABITATION",
    "name:eng_x_preferred":[
        "Karekattu Kadambu Palam Road Start"
    ],
    "wof:name":"Karekattu Kadambu Palam Road Start",
    "wof:placetype":"locality",
    "wof:population":646
},
  "geometry": {"coordinates":[76.281676,10.387136],"type":"Point"}
}