{
  "type": "Feature",
  "properties": {
    "iso:country":"IN",
    "ks:ks_name":"Kadighat",
    "ks:ks_pop":2529,
    "ks:ks_type":"VILLAGE",
    "name:eng_x_preferred":[
        "Kadighat"
    ],
    "wof:name":"Kadighat",
    "wof:placetype":"neighbourhood",
    "wof:population":2529
},
  "geometry": {"coordinates":[88.508281,25.406143],"type":"Point"}
}