{
  "type": "Feature",
  "properties": {
    "iso:country":"IN",
    "ks:ks_name":"Pantapara",
    "ks:ks_pop":1267,
    "ks:ks_type":"VILLAGE",
    "ks:ks_uagg_main":0,
    "name:eng_x_preferred":[
        "Pantapara"
    ],
    "wof:name":"Pantapara",
    "wof:placetype":"neighbourhood",
    "wof:population":1267
},
  "geometry": {"coordinates":[88.85736300000001,22.860359],"type":"Point"}
}