{
  "type": "Feature",
  "properties": {
    "iso:country":"IN",
    "ks:ks_alt_nam":"BELA TAND",
    "ks:ks_name":"Bela Tand",
    "ks:ks_pop":508,
    "ks:ks_type":"HABITATION",
    "name:eng_x_preferred":[
        "Bela Tand"
    ],
    "wof:name":"Bela Tand",
    "wof:placetype":"locality",
    "wof:population":508
},
  "geometry": {"coordinates":[85.701234,24.231368],"type":"Point"}
}