{
  "type": "Feature",
  "properties": {
    "iso:country":"IN",
    "ks:ks_name":"Dulia Gaon",
    "ks:ks_pop":243,
    "ks:ks_type":"HABITATION",
    "name:eng_x_preferred":[
        "Dulia Gaon"
    ],
    "wof:name":"Dulia Gaon",
    "wof:placetype":"locality",
    "wof:population":243
},
  "geometry": {"coordinates":[91.429064,26.007668],"type":"Point"}
}