{
  "type": "Feature",
  "properties": {
    "iso:country":"IN",
    "ks:ks_alt_nam":"SITALA PARA",
    "ks:ks_name":"Sitala Para",
    "ks:ks_pop":527,
    "ks:ks_type":"HABITATION",
    "name:eng_x_preferred":[
        "Sitala Para"
    ],
    "wof:name":"Sitala Para",
    "wof:placetype":"locality",
    "wof:population":527
},
  "geometry": {"coordinates":[89.356432,26.685443],"type":"Point"}
}