{
  "type": "Feature",
  "properties": {
    "iso:country":"IN",
    "ks:ks_name":"Kali Bari",
    "ks:ks_pop":516,
    "ks:ks_type":"HABITATION",
    "name:eng_x_preferred":[
        "Kali Bari"
    ],
    "wof:name":"Kali Bari",
    "wof:placetype":"locality",
    "wof:population":516
},
  "geometry": {"coordinates":[91.374774,23.130221],"type":"Point"}
}