{
  "type": "Feature",
  "properties": {
    "gn:admin1_code":"34.0",
    "gn:admin2_code":"236.0",
    "gn:asciiname":"Sanwar Chak",
    "gn:country_code":"IN",
    "gn:dem":173,
    "gn:feature_class":"P",
    "gn:feature_code":"PPL",
    "gn:name":"Sanw\u0101r Chak",
    "gn:population":0,
    "gn:timezone":"Asia/Kolkata",
    "iso:country":"IN",
    "ks:ks_name":"Sanwar Chak",
    "ks:ks_pop":1548,
    "ks:ks_type":"VILLAGE",
    "name:eng_x_preferred":[
        "Sanwar Chak"
    ],
    "wof:name":"Sanwar Chak",
    "wof:placetype":"locality",
    "wof:population":1548
},
  "geometry": {"coordinates":[85.21659699999999,24.562489],"type":"Point"}
}