{
  "type": "Feature",
  "properties": {
    "gn:admin1_code":"25.0",
    "gn:admin2_code":"606.0",
    "gn:asciiname":"Muttunattur",
    "gn:country_code":"IN",
    "gn:dem":630,
    "gn:feature_class":"P",
    "gn:feature_code":"PPL",
    "gn:name":"Muttunatt\u016br",
    "gn:population":0,
    "gn:timezone":"Asia/Kolkata",
    "iso:country":"IN",
    "wof:name":"Muttunattur",
    "wof:placetype":"neighbourhood"
},
  "geometry": {"coordinates":[78.99719,12.66193],"type":"Point"}
}