{
  "type": "Feature",
  "properties": {
    "gn:admin1_code":"36",
    "gn:admin2_code":"167.0",
    "gn:asciiname":"Dorna",
    "gn:country_code":"IN",
    "gn:dem":390,
    "gn:feature_class":"P",
    "gn:feature_code":"PPL",
    "gn:name":"Dorna",
    "gn:population":0,
    "gn:timezone":"Asia/Kolkata",
    "iso:country":"IN",
    "name:ceb_x_preferred":[
        "Dorna"
    ],
    "name:deu_x_preferred":[
        "Dorna"
    ],
    "name:glg_x_preferred":[
        "Dorna"
    ],
    "name:ita_x_preferred":[
        "Dorna"
    ],
    "name:nld_x_preferred":[
        "Dorna"
    ],
    "name:ron_x_preferred":[
        "Dorna"
    ],
    "name:srp_x_preferred":[
        "\u0414\u043e\u0440\u043d\u0430"
    ],
    "name:swe_x_preferred":[
        "Dorna"
    ],
    "name:ukr_x_preferred":[
        "\u0414\u043e\u0440\u043d\u0430"
    ],
    "name:vie_x_preferred":[
        "Dorna"
    ],
    "wof:name":"Dorna",
    "wof:placetype":"locality"
},
  "geometry": {"coordinates":[78.51281999999998,24.45382],"type":"Point"}
}