{
  "type": "Feature",
  "properties": {
    "iso:country":"IN",
    "ks:ks_name":"Tilkahna",
    "ks:ks_pop":280,
    "ks:ks_type":"HABITATION",
    "name:eng_x_preferred":[
        "Tilkahna"
    ],
    "wof:name":"Tilkahna",
    "wof:placetype":"locality",
    "wof:population":280
},
  "geometry": {"coordinates":[83.084475,27.313232],"type":"Point"}
}