{
  "type": "Feature",
  "properties": {
    "iso:country":"IN",
    "ks:ks_name":"Baharpur",
    "ks:ks_pop":257,
    "ks:ks_type":"VILLAGE",
    "name:eng_x_preferred":[
        "Baharpur"
    ],
    "wof:name":"Baharpur",
    "wof:placetype":"locality",
    "wof:population":257
},
  "geometry": {"coordinates":[81.30950799999999,27.546328],"type":"Point"}
}