{
  "type": "Feature",
  "properties": {
    "gn:admin1_code":"36",
    "gn:admin2_code":"194.0",
    "gn:asciiname":"Patkhauli",
    "gn:country_code":"IN",
    "gn:dem":83,
    "gn:feature_class":"P",
    "gn:feature_code":"PPL",
    "gn:name":"Patkhaul\u012b",
    "gn:population":0,
    "gn:timezone":"Asia/Kolkata",
    "iso:country":"IN",
    "ks:ks_alt_nam":"Patkhaul\u012b",
    "ks:ks_name":"Patkhauli",
    "ks:ks_type":"VILLAGE",
    "name:eng_x_preferred":[
        "Patkhauli"
    ],
    "name:eng_x_variant":[
        "Patkhaul\u012b"
    ],
    "wof:name":"Patkhauli",
    "wof:placetype":"locality"
},
  "geometry": {"coordinates":[82.989273,25.556995],"type":"Point"}
}