{
  "type": "Feature",
  "properties": {
    "iso:country":"IN",
    "ks:ks_name":"Patel Falia",
    "ks:ks_pop":572,
    "ks:ks_type":"HABITATION",
    "name:eng_x_preferred":[
        "Patel Falia"
    ],
    "wof:name":"Patel Falia",
    "wof:placetype":"locality",
    "wof:population":572
},
  "geometry": {"coordinates":[73.237028,21.020139],"type":"Point"}
}