{
  "type": "Feature",
  "properties": {
    "iso:country":"IN",
    "ks:ks_alt_nam":"peechad",
    "ks:ks_name":"Peechad",
    "ks:ks_pop":1128,
    "ks:ks_type":"HABITATION",
    "name:eng_x_preferred":[
        "Peechad"
    ],
    "wof:name":"Peechad",
    "wof:placetype":"locality",
    "wof:population":1128
},
  "geometry": {"coordinates":[76.95155800000001,10.054101],"type":"Point"}
}