{
  "type": "Feature",
  "properties": {
    "gn:admin1_code":"19.0",
    "gn:admin2_code":"570.0",
    "gn:asciiname":"Kote",
    "gn:country_code":"IN",
    "gn:dem":702,
    "gn:feature_class":"P",
    "gn:feature_code":"PPL",
    "gn:name":"Kote",
    "gn:population":0,
    "gn:timezone":"Asia/Kolkata",
    "iso:country":"IN",
    "name:ceb_x_preferred":[
        "Kote"
    ],
    "name:deu_x_preferred":[
        "Kote"
    ],
    "name:swe_x_preferred":[
        "Kote"
    ],
    "wof:name":"Kote",
    "wof:placetype":"locality"
},
  "geometry": {"coordinates":[75.3142,13.48649],"type":"Point"}
}