{
  "type": "Feature",
  "properties": {
    "iso:country":"IN",
    "ks:ks_name":"Jhadisara",
    "ks:ks_pop":2695,
    "ks:ks_type":"VILLAGE",
    "name:eng_x_preferred":[
        "Jhadisara"
    ],
    "wof:name":"Jhadisara",
    "wof:placetype":"locality",
    "wof:population":2695
},
  "geometry": {"coordinates":[73.812675,27.348528],"type":"Point"}
}