{
  "type": "Feature",
  "properties": {
    "iso:country":"IN",
    "ks:ks_name":"Koothalavadi",
    "ks:ks_pop":1242,
    "ks:ks_type":"VILLAGE",
    "name:eng_x_preferred":[
        "Koothalavadi"
    ],
    "wof:name":"Koothalavadi",
    "wof:placetype":"locality",
    "wof:population":1242
},
  "geometry": {"coordinates":[79.112185,12.330089],"type":"Point"}
}