{
  "type": "Feature",
  "properties": {
    "iso:country":"IN",
    "ks:ks_name":"Yadav Tola",
    "ks:ks_pop":154,
    "ks:ks_type":"HABITATION",
    "name:eng_x_preferred":[
        "Yadav Tola"
    ],
    "wof:name":"Yadav Tola",
    "wof:placetype":"locality",
    "wof:population":154
},
  "geometry": {"coordinates":[86.291631,24.433064],"type":"Point"}
}