{
  "type": "Feature",
  "properties": {
    "iso:country":"IN",
    "ks:ks_name":"Pub Amdah Gaon",
    "ks:ks_pop":486,
    "ks:ks_type":"HABITATION",
    "ks:ks_uagg_main":0,
    "name:eng_x_preferred":[
        "Pub Amdah Gaon"
    ],
    "wof:name":"Pub Amdah Gaon",
    "wof:placetype":"neighbourhood",
    "wof:population":486
},
  "geometry": {"coordinates":[91.147015,26.458948],"type":"Point"}
}