{
  "type": "Feature",
  "properties": {
    "iso:country":"IN",
    "ks:ks_alt_nam":"bazar.",
    "ks:ks_name":"Bazar.",
    "ks:ks_pop":627,
    "ks:ks_type":"HABITATION",
    "ks:ks_uagg_main":0,
    "name:eng_x_preferred":[
        "Bazar."
    ],
    "wof:name":"Bazar.",
    "wof:placetype":"neighbourhood",
    "wof:population":627
},
  "geometry": {"coordinates":[86.59588599999999,25.718217],"type":"Point"}
}