{
  "type": "Feature",
  "properties": {
    "iso:country":"IN",
    "ks:ks_name":"Khakhli",
    "ks:ks_pop":146,
    "ks:ks_type":"VILLAGE",
    "name:eng_x_preferred":[
        "Khakhli"
    ],
    "wof:name":"Khakhli",
    "wof:placetype":"locality",
    "wof:population":146
},
  "geometry": {"coordinates":[75.895549,31.573007],"type":"Point"}
}