{
  "type": "Feature",
  "properties": {
    "iso:country":"IN",
    "ks:ks_name":"Khariapara",
    "ks:ks_pop":70,
    "ks:ks_type":"HABITATION",
    "name:eng_x_preferred":[
        "Khariapara"
    ],
    "wof:name":"Khariapara",
    "wof:placetype":"locality",
    "wof:population":70
},
  "geometry": {"coordinates":[82.328706,22.910953],"type":"Point"}
}