{
  "type": "Feature",
  "properties": {
    "iso:country":"IN",
    "ks:ks_name":"Dandabadu",
    "ks:ks_pop":119,
    "ks:ks_type":"HABITATION",
    "name:eng_x_preferred":[
        "Dandabadu"
    ],
    "wof:name":"Dandabadu",
    "wof:placetype":"locality",
    "wof:population":119
},
  "geometry": {"coordinates":[83.002196,18.234373],"type":"Point"}
}