{
  "type": "Feature",
  "properties": {
    "gn:admin1_code":"25.0",
    "gn:admin2_code":"611.0",
    "gn:asciiname":"Arakkodu",
    "gn:country_code":"IN",
    "gn:dem":1426,
    "gn:feature_class":"P",
    "gn:feature_code":"PPL",
    "gn:name":"Arakk\u014ddu",
    "gn:population":0,
    "gn:timezone":"Asia/Kolkata",
    "iso:country":"IN",
    "wof:name":"Arakkodu",
    "wof:placetype":"locality"
},
  "geometry": {"coordinates":[76.97733000000002,11.45055],"type":"Point"}
}