{
  "type": "Feature",
  "properties": {
    "iso:country":"IN",
    "ks:ks_name":"Thowthoni",
    "ks:ks_pop":1126,
    "ks:ks_type":"VILLAGE",
    "name:eng_x_preferred":[
        "Thowthoni"
    ],
    "wof:name":"Thowthoni",
    "wof:placetype":"locality",
    "wof:population":1126
},
  "geometry": {"coordinates":[94.15781800000001,27.335189],"type":"Point"}
}