{
  "type": "Feature",
  "properties": {
    "gn:admin1_code":"36.0",
    "gn:admin2_code":"150.0",
    "gn:asciiname":"Anandaper Lachhman Narain",
    "gn:country_code":"IN",
    "gn:dem":183,
    "gn:feature_class":"P",
    "gn:feature_code":"PPL",
    "gn:name":"Anand\u0101per Lachhman Nar\u0101in",
    "gn:population":0,
    "gn:timezone":"Asia/Kolkata",
    "iso:country":"IN",
    "wof:name":"Anandaper Lachhman Narain",
    "wof:placetype":"locality"
},
  "geometry": {"coordinates":[79.6657,28.54561],"type":"Point"}
}