{
  "type": "Feature",
  "properties": {
    "iso:country":"IN",
    "ks:ks_name":"Mirtipadu",
    "ks:ks_pop":155,
    "ks:ks_type":"HABITATION",
    "name:eng_x_preferred":[
        "Mirtipadu"
    ],
    "wof:name":"Mirtipadu",
    "wof:placetype":"locality",
    "wof:population":155
},
  "geometry": {"coordinates":[82.936548,18.425285],"type":"Point"}
}