{
  "type": "Feature",
  "properties": {
    "iso:country":"IN",
    "ks:ks_name":"Satyalawadi",
    "ks:ks_pop":34,
    "ks:ks_type":"HABITATION",
    "name:eng_x_preferred":[
        "Satyalawadi"
    ],
    "wof:name":"Satyalawadi",
    "wof:placetype":"locality",
    "wof:population":34
},
  "geometry": {"coordinates":[73.771199,15.799306],"type":"Point"}
}