{
  "type": "Feature",
  "properties": {
    "iso:country":"IN",
    "ks:ks_name":"Kanekuntapalle",
    "ks:ks_pop":86,
    "ks:ks_type":"HABITATION",
    "name:eng_x_preferred":[
        "Kanekuntapalle"
    ],
    "wof:name":"Kanekuntapalle",
    "wof:placetype":"locality",
    "wof:population":86
},
  "geometry": {"coordinates":[78.448093,13.915112],"type":"Point"}
}