{
  "type": "Feature",
  "properties": {
    "gn:admin1_code":"2.0",
    "gn:admin2_code":"554.0",
    "gn:asciiname":"Amidala",
    "gn:country_code":"IN",
    "gn:dem":279,
    "gn:feature_class":"P",
    "gn:feature_code":"PPL",
    "gn:name":"\u0100mid\u0101l\u0101",
    "gn:population":0,
    "gn:timezone":"Asia/Kolkata",
    "iso:country":"IN",
    "wof:name":"Amidala",
    "wof:placetype":"locality"
},
  "geometry": {"coordinates":[79.3087,13.19363],"type":"Point"}
}