{
  "type": "Feature",
  "properties": {
    "iso:country":"IN",
    "ks:ks_name":"Kantharapalke",
    "ks:ks_pop":280,
    "ks:ks_type":"HABITATION",
    "name:eng_x_preferred":[
        "Kantharapalke"
    ],
    "wof:name":"Kantharapalke",
    "wof:placetype":"locality",
    "wof:population":280
},
  "geometry": {"coordinates":[75.11134800000001,13.100029],"type":"Point"}
}