{
  "type": "Feature",
  "properties": {
    "iso:country":"IN",
    "ks:ks_name":"Mahalakshmi Temple Area",
    "ks:ks_pop":202,
    "ks:ks_type":"HABITATION",
    "name:eng_x_preferred":[
        "Mahalakshmi Temple Area"
    ],
    "wof:name":"Mahalakshmi Temple Area",
    "wof:placetype":"locality",
    "wof:population":202
},
  "geometry": {"coordinates":[75.09237400000001,13.159161],"type":"Point"}
}