{
  "type": "Feature",
  "properties": {
    "iso:country":"IN",
    "ks:ks_name":"Jalgorwa",
    "ks:ks_pop":312,
    "ks:ks_type":"HABITATION",
    "name:eng_x_preferred":[
        "Jalgorwa"
    ],
    "wof:name":"Jalgorwa",
    "wof:placetype":"locality",
    "wof:population":312
},
  "geometry": {"coordinates":[86.373913,24.886552],"type":"Point"}
}