{
  "type": "Feature",
  "properties": {
    "iso:country":"IN",
    "ks:ks_name":"Kulgi",
    "ks:ks_pop":440,
    "ks:ks_type":"VILLAGE",
    "name:eng_x_preferred":[
        "Kulgi"
    ],
    "wof:name":"Kulgi",
    "wof:placetype":"locality",
    "wof:population":440
},
  "geometry": {"coordinates":[74.63954099999999,15.167037],"type":"Point"}
}