{
  "type": "Feature",
  "properties": {
    "iso:country":"IN",
    "ks:ks_alt_nam":"Ras\u016bli",
    "ks:ks_name":"Rasuli",
    "ks:ks_pop":104,
    "ks:ks_type":"VILLAGE",
    "name:eng_x_preferred":[
        "Rasuli"
    ],
    "name:eng_x_variant":[
        "Ras\u016bli"
    ],
    "wof:name":"Rasuli",
    "wof:placetype":"locality",
    "wof:population":104
},
  "geometry": {"coordinates":[80.94333399999999,20.420653],"type":"Point"}
}