{
  "type": "Feature",
  "properties": {
    "iso:country":"IN",
    "ks:ks_name":"Mahalat Purwa",
    "ks:ks_pop":120,
    "ks:ks_type":"HABITATION",
    "name:eng_x_preferred":[
        "Mahalat Purwa"
    ],
    "wof:name":"Mahalat Purwa",
    "wof:placetype":"locality",
    "wof:population":120
},
  "geometry": {"coordinates":[81.735716,27.249249],"type":"Point"}
}