{
  "type": "Feature",
  "properties": {
    "gn:admin1_code":"2.0",
    "gn:admin2_code":"553.0",
    "gn:asciiname":"Upparahalli",
    "gn:country_code":"IN",
    "gn:dem":648,
    "gn:feature_class":"P",
    "gn:feature_code":"PPL",
    "gn:name":"Upparahalli",
    "gn:population":0,
    "gn:timezone":"Asia/Kolkata",
    "iso:country":"IN",
    "ks:ks_name":"Upparlahalli",
    "ks:ks_pop":141,
    "ks:ks_type":"HABITATION",
    "name:eng_x_preferred":[
        "Upparlahalli"
    ],
    "name:eng_x_variant":[
        "Upparahalli"
    ],
    "wof:name":"Upparlahalli",
    "wof:placetype":"locality",
    "wof:population":141
},
  "geometry": {"coordinates":[77.05503400000001,13.944435],"type":"Point"}
}