{
  "type": "Feature",
  "properties": {
    "gn:country":"IN",
    "gn:fcode":"PPL",
    "gn:pop":45769,
    "iso:country":"IN",
    "name:unk_x_variant":[
        "N\u0101yudupet"
    ],
    "qs:name":"N\u0101yudupeta",
    "qs:photos_9r":0,
    "qs:photos_sr":0,
    "qs:pop_sr":"7",
    "wd:wordcount":116,
    "wof:name":"N\u0101yudupeta",
    "wof:placetype":"locality",
    "wof:population":45769
},
  "geometry": {"coordinates":[79.89649,13.90777],"type":"Point"}
}