{
  "type": "Feature",
  "properties": {
    "iso:country":"IN",
    "ks:ks_name":"Mukkallil",
    "ks:ks_pop":312,
    "ks:ks_type":"HABITATION",
    "name:eng_x_preferred":[
        "Mukkallil"
    ],
    "wof:name":"Mukkallil",
    "wof:placetype":"locality",
    "wof:population":312
},
  "geometry": {"coordinates":[75.80297899999999,11.560158],"type":"Point"}
}