{
  "type": "Feature",
  "properties": {
    "iso:country":"IN",
    "ks:ks_alt_nam":"M\u0101lupura",
    "ks:ks_name":"Malupura",
    "ks:ks_type":"VILLAGE",
    "name:eng_x_preferred":[
        "Malupura"
    ],
    "name:eng_x_variant":[
        "M\u0101lupura"
    ],
    "wof:name":"Malupura",
    "wof:placetype":"locality"
},
  "geometry": {"coordinates":[79.24177299999999,26.29403],"type":"Point"}
}