{
  "type": "Feature",
  "properties": {
    "iso:country":"IN",
    "ks:ks_name":"Thapal Gaon",
    "ks:ks_pop":613,
    "ks:ks_type":"VILLAGE",
    "name:eng_x_preferred":[
        "Thapal Gaon"
    ],
    "wof:name":"Thapal Gaon",
    "wof:placetype":"locality",
    "wof:population":613
},
  "geometry": {"coordinates":[79.130224,30.332535],"type":"Point"}
}