{
  "type": "Feature",
  "properties": {
    "iso:country":"IN",
    "ks:ks_name":"Anjanpura",
    "ks:ks_pop":128,
    "ks:ks_type":"HABITATION",
    "name:eng_x_preferred":[
        "Anjanpura"
    ],
    "wof:name":"Anjanpura",
    "wof:placetype":"locality",
    "wof:population":128
},
  "geometry": {"coordinates":[77.814582,13.847377],"type":"Point"}
}