{
  "type": "Feature",
  "properties": {
    "iso:country":"IN",
    "ks:ks_name":"Kachla Falia",
    "ks:ks_pop":189,
    "ks:ks_type":"HABITATION",
    "name:eng_x_preferred":[
        "Kachla Falia"
    ],
    "wof:name":"Kachla Falia",
    "wof:placetype":"locality",
    "wof:population":189
},
  "geometry": {"coordinates":[74.18905599999999,23.139417],"type":"Point"}
}