{
  "type": "Feature",
  "properties": {
    "iso:country":"IN",
    "ks:ks_name":"Basuatoli",
    "ks:ks_pop":241,
    "ks:ks_type":"HABITATION",
    "ks:ks_uagg_main":0,
    "name:eng_x_preferred":[
        "Basuatoli"
    ],
    "wof:name":"Basuatoli",
    "wof:placetype":"neighbourhood",
    "wof:population":241
},
  "geometry": {"coordinates":[85.483637,23.460763],"type":"Point"}
}