{
  "type": "Feature",
  "properties": {
    "iso:country":"IN",
    "ks:ks_alt_nam":"3 Lkd(B)",
    "ks:ks_name":"3 Lkd(b)",
    "ks:ks_pop":853,
    "ks:ks_type":"HABITATION",
    "name:eng_x_preferred":[
        "3 Lkd(b)"
    ],
    "wof:name":"3 Lkd(b)",
    "wof:placetype":"locality",
    "wof:population":853
},
  "geometry": {"coordinates":[72.508578,28.643297],"type":"Point"}
}