{
  "type": "Feature",
  "properties": {
    "iso:country":"IN",
    "ks:ks_name":"Thirupathihalli",
    "ks:ks_pop":483,
    "ks:ks_type":"HABITATION",
    "name:eng_x_preferred":[
        "Thirupathihalli"
    ],
    "wof:name":"Thirupathihalli",
    "wof:placetype":"locality",
    "wof:population":483
},
  "geometry": {"coordinates":[76.241169,13.27245],"type":"Point"}
}