{
  "type": "Feature",
  "properties": {
    "gn:admin1_code":"19.0",
    "gn:admin2_code":"583.0",
    "gn:asciiname":"Totlubande",
    "gn:country_code":"IN",
    "gn:dem":840,
    "gn:feature_class":"P",
    "gn:feature_code":"PPL",
    "gn:name":"Totlubande",
    "gn:population":0,
    "gn:timezone":"Asia/Kolkata",
    "iso:country":"IN",
    "wof:name":"Totlubande",
    "wof:placetype":"locality"
},
  "geometry": {"coordinates":[77.38585,13.40239],"type":"Point"}
}