{
  "type": "Feature",
  "properties": {
    "iso:country":"IN",
    "ks:ks_name":"Saikarpara",
    "ks:ks_pop":465,
    "ks:ks_type":"HABITATION",
    "name:eng_x_preferred":[
        "Saikarpara"
    ],
    "wof:name":"Saikarpara",
    "wof:placetype":"locality",
    "wof:population":465
},
  "geometry": {"coordinates":[92.139201,23.896026],"type":"Point"}
}