{
  "type": "Feature",
  "properties": {
    "iso:country":"IN",
    "ks:ks_name":"Radha Damodarpur",
    "ks:ks_pop":331,
    "ks:ks_type":"VILLAGE",
    "name:eng_x_preferred":[
        "Radha Damodarpur"
    ],
    "wof:name":"Radha Damodarpur",
    "wof:placetype":"locality",
    "wof:population":331
},
  "geometry": {"coordinates":[87.36411699999999,23.06885],"type":"Point"}
}