{
  "type": "Feature",
  "properties": {
    "iso:country":"IN",
    "ks:ks_name":"Harijanwadi",
    "ks:ks_pop":369,
    "ks:ks_type":"HABITATION",
    "name:eng_x_preferred":[
        "Harijanwadi"
    ],
    "wof:name":"Harijanwadi",
    "wof:placetype":"locality",
    "wof:population":369
},
  "geometry": {"coordinates":[73.696505,15.974125],"type":"Point"}
}