{
  "type": "Feature",
  "properties": {
    "iso:country":"IN",
    "ks:ks_name":"Tongritoli",
    "ks:ks_pop":107,
    "ks:ks_type":"HABITATION",
    "name:eng_x_preferred":[
        "Tongritoli"
    ],
    "wof:name":"Tongritoli",
    "wof:placetype":"locality",
    "wof:population":107
},
  "geometry": {"coordinates":[84.274378,22.571435],"type":"Point"}
}