{
  "type": "Feature",
  "properties": {
    "iso:country":"IN",
    "ks:ks_name":"Bokial Bagan",
    "ks:ks_pop":2667,
    "ks:ks_type":"HABITATION",
    "name:eng_x_preferred":[
        "Bokial Bagan"
    ],
    "wof:name":"Bokial Bagan",
    "wof:placetype":"locality",
    "wof:population":2667
},
  "geometry": {"coordinates":[93.811775,26.521492],"type":"Point"}
}