{
  "type": "Feature",
  "properties": {
    "iso:country":"IN",
    "ks:ks_name":"Tara",
    "ks:ks_pop":0,
    "ks:ks_type":"VILLAGE",
    "name:eng_x_preferred":[
        "Tara"
    ],
    "wof:name":"Tara",
    "wof:placetype":"locality",
    "wof:population":0
},
  "geometry": {"coordinates":[87.53216999999999,25.080216],"type":"Point"}
}