{
  "type": "Feature",
  "properties": {
    "iso:country":"IN",
    "ks:ks_name":"Kanankulam",
    "ks:ks_pop":2094,
    "ks:ks_type":"HABITATION",
    "ks:ks_uagg_main":0,
    "name:eng_x_preferred":[
        "Kanankulam"
    ],
    "wof:name":"Kanankulam",
    "wof:placetype":"neighbourhood",
    "wof:population":2094
},
  "geometry": {"coordinates":[77.591741,8.14969],"type":"Point"}
}