{
  "type": "Feature",
  "properties": {
    "gn:admin1_code":"35.0",
    "gn:admin2_code":"455.0",
    "gn:asciiname":"Jam",
    "gn:country_code":"IN",
    "gn:dem":667,
    "gn:feature_class":"P",
    "gn:feature_code":"PPL",
    "gn:name":"J\u0101m",
    "gn:population":0,
    "gn:timezone":"Asia/Kolkata",
    "iso:country":"IN",
    "name:tur_x_preferred":[
        "Re\u00e7el"
    ],
    "wof:name":"Jam",
    "wof:placetype":"locality"
},
  "geometry": {"coordinates":[78.86910999999998,21.8995],"type":"Point"}
}