{
  "type": "Feature",
  "properties": {
    "gn:admin1_code":"19.0",
    "gn:admin2_code":"576.0",
    "gn:asciiname":"Ganagur",
    "gn:country_code":"IN",
    "gn:dem":837,
    "gn:feature_class":"P",
    "gn:feature_code":"PPL",
    "gn:name":"Ganagur",
    "gn:population":0,
    "gn:timezone":"Asia/Kolkata",
    "iso:country":"IN",
    "ks:ks_name":"Ganagur",
    "ks:ks_type":"VILLAGE",
    "name:eng_x_preferred":[
        "Ganagur"
    ],
    "wof:name":"Ganagur",
    "wof:placetype":"locality"
},
  "geometry": {"coordinates":[76.073869,12.168701],"type":"Point"}
}