{
  "type": "Feature",
  "properties": {
    "iso:country":"IN",
    "ks:ks_name":"Mundasahi",
    "ks:ks_pop":277,
    "ks:ks_type":"HABITATION",
    "name:eng_x_preferred":[
        "Mundasahi"
    ],
    "wof:name":"Mundasahi",
    "wof:placetype":"locality",
    "wof:population":277
},
  "geometry": {"coordinates":[84.902328,21.779124],"type":"Point"}
}