{
  "type": "Feature",
  "properties": {
    "iso:country":"IN",
    "ks:ks_name":"Dehri",
    "ks:ks_pop":0,
    "ks:ks_type":"VILLAGE",
    "name:eng_x_preferred":[
        "Dehri"
    ],
    "wof:name":"Dehri",
    "wof:placetype":"locality",
    "wof:population":0
},
  "geometry": {"coordinates":[84.08566500000001,24.595736],"type":"Point"}
}