{
  "type": "Feature",
  "properties": {
    "iso:country":"IN",
    "ks:ks_name":"Sariba",
    "ks:ks_pop":254,
    "ks:ks_type":"HABITATION",
    "name:eng_x_preferred":[
        "Sariba"
    ],
    "wof:name":"Sariba",
    "wof:placetype":"locality",
    "wof:population":254
},
  "geometry": {"coordinates":[85.052877,22.566415],"type":"Point"}
}