{
  "type": "Feature",
  "properties": {
    "gn:admin1_code":"36",
    "gn:admin2_code":"135.0",
    "gn:asciiname":"Deolara",
    "gn:country_code":"IN",
    "gn:dem":191,
    "gn:feature_class":"P",
    "gn:feature_code":"PPL",
    "gn:name":"Deol\u0101ra",
    "gn:population":0,
    "gn:timezone":"Asia/Kolkata",
    "iso:country":"IN",
    "wof:name":"Deolara",
    "wof:placetype":"locality"
},
  "geometry": {"coordinates":[78.89757,28.80029],"type":"Point"}
}