{
  "type": "Feature",
  "properties": {
    "iso:country":"IN",
    "ks:ks_name":"Eedulaputtu",
    "ks:ks_pop":127,
    "ks:ks_type":"HABITATION",
    "name:eng_x_preferred":[
        "Eedulaputtu"
    ],
    "wof:name":"Eedulaputtu",
    "wof:placetype":"locality",
    "wof:population":127
},
  "geometry": {"coordinates":[82.862776,18.19094],"type":"Point"}
}