{
  "type": "Feature",
  "properties": {
    "iso:country":"IN",
    "ks:ks_name":"Chichro",
    "ks:ks_pop":254,
    "ks:ks_type":"VILLAGE",
    "name:eng_x_preferred":[
        "Chichro"
    ],
    "wof:name":"Chichro",
    "wof:placetype":"locality",
    "wof:population":254
},
  "geometry": {"coordinates":[87.500916,24.332389],"type":"Point"}
}