{
  "type": "Feature",
  "properties": {
    "iso:country":"IN",
    "name:ceb_x_preferred":[
        "Ramapuram"
    ],
    "name:ita_x_preferred":[
        "Ramapuram"
    ],
    "name:mal_x_preferred":[
        "\u0d30\u0d3e\u0d2e\u0d2a\u0d41\u0d30\u0d02"
    ],
    "name:swe_x_preferred":[
        "Ramapuram"
    ],
    "qs:name":"Ramapuram",
    "qs:name_adm0":"India",
    "qs:name_adm1":"Tamil Nadu",
    "qs:photos":6,
    "qs:photos_1k":1,
    "qs:photos_9k":1,
    "qs:photos_9r":1,
    "qs:photos_all":6,
    "qs:photos_sr":1,
    "qs:placetype":"Suburb",
    "qs:pop_sr":"0",
    "wd:wordcount":130,
    "wof:name":"Ramapuram",
    "wof:placetype":"neighbourhood"
},
  "geometry": {"coordinates":[80.213584,13.148358],"type":"Point"}
}