{
  "type": "Feature",
  "properties": {
    "iso:country":"IN",
    "ks:ks_name":"Prangapada",
    "ks:ks_pop":44,
    "ks:ks_type":"VILLAGE",
    "name:eng_x_preferred":[
        "Prangapada"
    ],
    "wof:name":"Prangapada",
    "wof:placetype":"locality",
    "wof:population":44
},
  "geometry": {"coordinates":[84.263515,20.51288],"type":"Point"}
}