{
  "type": "Feature",
  "properties": {
    "iso:country":"IN",
    "ks:ks_name":"Harijan Falia",
    "ks:ks_pop":275,
    "ks:ks_type":"HABITATION",
    "name:eng_x_preferred":[
        "Harijan Falia"
    ],
    "wof:name":"Harijan Falia",
    "wof:placetype":"locality",
    "wof:population":275
},
  "geometry": {"coordinates":[73.89533299999999,22.83725],"type":"Point"}
}