{
  "type": "Feature",
  "properties": {
    "iso:country":"IN",
    "ks:ks_name":"Pub Safakamar",
    "ks:ks_pop":1277,
    "ks:ks_type":"VILLAGE",
    "ks:ks_uagg_main":0,
    "name:eng_x_preferred":[
        "Pub Safakamar"
    ],
    "wof:name":"Pub Safakamar",
    "wof:placetype":"neighbourhood",
    "wof:population":1277
},
  "geometry": {"coordinates":[90.98347699999999,26.569187],"type":"Point"}
}