{
  "type": "Feature",
  "properties": {
    "gn:admin1_code":"12",
    "gn:admin2_code":"18.0",
    "gn:asciiname":"Kutal",
    "gn:country_code":"IN",
    "gn:dem":2335,
    "gn:feature_class":"P",
    "gn:feature_code":"PPL",
    "gn:name":"Kut\u0101l",
    "gn:population":0,
    "gn:timezone":"Asia/Kolkata",
    "iso:country":"IN",
    "wof:name":"Kutal",
    "wof:placetype":"locality"
},
  "geometry": {"coordinates":[75.75635,33.22932],"type":"Point"}
}