{
  "type": "Feature",
  "properties": {
    "iso:country":"IN",
    "ks:ks_name":"Mosta",
    "ks:ks_pop":252,
    "ks:ks_type":"VILLAGE",
    "name:eng_x_preferred":[
        "Mosta"
    ],
    "wof:name":"Mosta",
    "wof:placetype":"locality",
    "wof:population":252
},
  "geometry": {"coordinates":[80.170635,29.21121],"type":"Point"}
}