{
  "type": "Feature",
  "properties": {
    "iso:country":"IN",
    "ks:ks_name":"Dambale",
    "ks:ks_pop":400,
    "ks:ks_type":"HABITATION",
    "name:eng_x_preferred":[
        "Dambale"
    ],
    "wof:name":"Dambale",
    "wof:placetype":"locality",
    "wof:population":400
},
  "geometry": {"coordinates":[75.283267,12.638898],"type":"Point"}
}