{
  "type": "Feature",
  "properties": {
    "iso:country":"IN",
    "ks:ks_name":"Punipada",
    "ks:ks_pop":25,
    "ks:ks_type":"VILLAGE",
    "name:eng_x_preferred":[
        "Punipada"
    ],
    "wof:name":"Punipada",
    "wof:placetype":"locality",
    "wof:population":25
},
  "geometry": {"coordinates":[85.11234899999999,19.972252],"type":"Point"}
}