{
  "type": "Feature",
  "properties": {
    "gn:admin1_code":"11.0",
    "gn:admin2_code":"33.0",
    "gn:asciiname":"Barog",
    "gn:country_code":"IN",
    "gn:dem":1741,
    "gn:feature_class":"P",
    "gn:feature_code":"PPL",
    "gn:name":"Barog",
    "gn:population":0,
    "gn:timezone":"Asia/Kolkata",
    "iso:country":"IN",
    "name:mal_x_preferred":[
        "\u0d2c\u0d3e\u0d31\u0d4b\u0d17\u0d4d"
    ],
    "name:pol_x_preferred":[
        "Barog"
    ],
    "name:san_x_preferred":[
        "\u092c\u093e\u0930\u094b\u0917\u094d \u0938\u0941\u0930\u0919\u094d\u0917\u092e\u093e\u0930\u094d\u0917\u0903"
    ],
    "wof:name":"Barog",
    "wof:placetype":"locality"
},
  "geometry": {"coordinates":[77.37891999999999,31.32243],"type":"Point"}
}