{
  "type": "Feature",
  "properties": {
    "iso:country":"IN",
    "ks:ks_name":"Palayavalam",
    "ks:ks_pop":1105,
    "ks:ks_type":"VILLAGE",
    "name:eng_x_preferred":[
        "Palayavalam"
    ],
    "wof:name":"Palayavalam",
    "wof:placetype":"locality",
    "wof:population":1105
},
  "geometry": {"coordinates":[79.69028900000001,10.791154],"type":"Point"}
}