{
  "type": "Feature",
  "properties": {
    "gn:admin1_code":"10.0",
    "gn:admin2_code":"75.0",
    "gn:asciiname":"Etaola",
    "gn:country_code":"IN",
    "gn:dem":236,
    "gn:feature_class":"P",
    "gn:feature_code":"PPL",
    "gn:name":"Et\u0101ola",
    "gn:population":0,
    "gn:timezone":"Asia/Kolkata",
    "iso:country":"IN",
    "wof:name":"Etaola",
    "wof:placetype":"locality"
},
  "geometry": {"coordinates":[76.74219000000002,29.33165],"type":"Point"}
}