{
  "type": "Feature",
  "properties": {
    "iso:country":"IN",
    "ks:ks_name":"Santhal Tola",
    "ks:ks_pop":1310,
    "ks:ks_type":"HABITATION",
    "name:eng_x_preferred":[
        "Santhal Tola"
    ],
    "wof:name":"Santhal Tola",
    "wof:placetype":"locality",
    "wof:population":1310
},
  "geometry": {"coordinates":[87.057964,25.815147],"type":"Point"}
}