{
  "type": "Feature",
  "properties": {
    "iso:country":"IN",
    "ks:ks_name":"Chota Chandana",
    "ks:ks_pop":77,
    "ks:ks_type":"VILLAGE",
    "name:eng_x_preferred":[
        "Chota Chandana"
    ],
    "wof:name":"Chota Chandana",
    "wof:placetype":"locality",
    "wof:population":77
},
  "geometry": {"coordinates":[87.024945,24.177979],"type":"Point"}
}