{
  "type": "Feature",
  "properties": {
    "gn:admin1_code":"19.0",
    "gn:admin2_code":"567.0",
    "gn:asciiname":"Akkanuru",
    "gn:country_code":"IN",
    "gn:dem":641,
    "gn:feature_class":"P",
    "gn:feature_code":"PPL",
    "gn:name":"Akkan\u016bru",
    "gn:population":0,
    "gn:timezone":"Asia/Kolkata",
    "iso:country":"IN",
    "wof:name":"Akkanuru",
    "wof:placetype":"locality"
},
  "geometry": {"coordinates":[76.39494000000001,14.47934],"type":"Point"}
}