{
  "type": "Feature",
  "properties": {
    "gn:admin1_code":"36",
    "gn:admin2_code":"143.0",
    "gn:asciiname":"Jhujharka",
    "gn:country_code":"IN",
    "gn:dem":190,
    "gn:feature_class":"P",
    "gn:feature_code":"PPL",
    "gn:name":"Jhujharka",
    "gn:population":0,
    "gn:timezone":"Asia/Kolkata",
    "iso:country":"IN",
    "wof:name":"Jhujharka",
    "wof:placetype":"locality"
},
  "geometry": {"coordinates":[78.25216999999998,27.98228],"type":"Point"}
}