{
  "type": "Feature",
  "properties": {
    "iso:country":"IN",
    "ks:ks_name":"Sohakha",
    "ks:ks_pop":35,
    "ks:ks_type":"HABITATION",
    "name:eng_x_preferred":[
        "Sohakha"
    ],
    "wof:name":"Sohakha",
    "wof:placetype":"locality",
    "wof:population":35
},
  "geometry": {"coordinates":[80.985224,27.063963],"type":"Point"}
}