{
  "type": "Feature",
  "properties": {
    "iso:country":"IN",
    "ks:ks_name":"Kanduguda Para",
    "ks:ks_pop":27,
    "ks:ks_type":"HABITATION",
    "name:eng_x_preferred":[
        "Kanduguda Para"
    ],
    "wof:name":"Kanduguda Para",
    "wof:placetype":"locality",
    "wof:population":27
},
  "geometry": {"coordinates":[81.970806,19.39484],"type":"Point"}
}