{
  "type": "Feature",
  "properties": {
    "gn:admin1_code":"38.0",
    "gn:admin2_code":"360.0",
    "gn:asciiname":"Pundri",
    "gn:country_code":"IN",
    "gn:dem":566,
    "gn:feature_class":"P",
    "gn:feature_code":"PPL",
    "gn:name":"Pundri",
    "gn:population":0,
    "gn:timezone":"Asia/Kolkata",
    "iso:country":"IN",
    "wof:name":"Pundri",
    "wof:placetype":"locality"
},
  "geometry": {"coordinates":[85.46583000000003,24.03017],"type":"Point"}
}