{
  "type": "Feature",
  "properties": {
    "gn:admin1_code":"38.0",
    "gn:admin2_code":"360.0",
    "gn:asciiname":"Pundri",
    "gn:country_code":"IN",
    "gn:dem":566,
    "gn:feature_class":"P",
    "gn:feature_code":"PPL",
    "gn:name":"Pundri",
    "gn:population":0,
    "gn:timezone":"Asia/Kolkata",
    "iso:country":"IN",
    "name:ben_x_preferred":[
        "\u09aa\u09c1\u09a8\u09cd\u09a1\u09b0\u09c0"
    ],
    "name:bpy_x_preferred":[
        "\u09aa\u09c1\u09a8\u09cd\u09a1\u09b0\u09c0"
    ],
    "name:ceb_x_preferred":[
        "P\u016bndri"
    ],
    "name:hin_x_preferred":[
        "\u092a\u0942\u0923\u094d\u0921\u0930\u0940"
    ],
    "name:ita_x_preferred":[
        "Pundri"
    ],
    "name:mlg_x_preferred":[
        "Pundri"
    ],
    "name:msa_x_preferred":[
        "Pundri"
    ],
    "name:nld_x_preferred":[
        "Pundri"
    ],
    "name:pan_x_preferred":[
        "\u0a2a\u0a42\u0a70\u0a21\u0a30\u0a40"
    ],
    "name:spa_x_preferred":[
        "Pundri"
    ],
    "name:swe_x_preferred":[
        "P\u016bndri"
    ],
    "name:vie_x_preferred":[
        "Pundri"
    ],
    "name:zho_x_preferred":[
        "\u666e\u6069\u5fb7\u91cc"
    ],
    "wof:name":"Pundri",
    "wof:placetype":"locality"
},
  "geometry": {"coordinates":[85.46583000000003,24.03017],"type":"Point"}
}