{
  "type": "Feature",
  "properties": {
    "gn:admin1_code":"39.0",
    "gn:admin2_code":"66.0",
    "gn:asciiname":"Jaleni",
    "gn:country_code":"IN",
    "gn:dem":1369,
    "gn:feature_class":"P",
    "gn:feature_code":"PPL",
    "gn:name":"Jaleni",
    "gn:population":0,
    "gn:timezone":"Asia/Kolkata",
    "iso:country":"IN",
    "wof:name":"Jaleni",
    "wof:placetype":"locality"
},
  "geometry": {"coordinates":[79.90158000000002,29.2353],"type":"Point"}
}