{
  "type": "Feature",
  "properties": {
    "gn:admin1_code":"24.0",
    "gn:admin2_code":"103",
    "gn:asciiname":"Dhandar Bas",
    "gn:country_code":"IN",
    "gn:dem":294,
    "gn:feature_class":"P",
    "gn:feature_code":"PPL",
    "gn:name":"Dhand\u0101r B\u0101s",
    "gn:population":0,
    "gn:timezone":"Asia/Kolkata",
    "iso:country":"IN",
    "wof:name":"Dhandar Bas",
    "wof:placetype":"neighbourhood"
},
  "geometry": {"coordinates":[75.5264,28.35394],"type":"Point"}
}