{
  "type": "Feature",
  "properties": {
    "gn:admin1_code":"21",
    "gn:admin2_code":"374.0",
    "gn:asciiname":"Sagarpali",
    "gn:country_code":"IN",
    "gn:dem":238,
    "gn:feature_class":"P",
    "gn:feature_code":"PPL",
    "gn:name":"S\u0101garp\u0101li",
    "gn:population":0,
    "gn:timezone":"Asia/Kolkata",
    "iso:country":"IN",
    "wof:name":"Sagarpali",
    "wof:placetype":"locality"
},
  "geometry": {"coordinates":[83.96016999999998,21.97019],"type":"Point"}
}