{
  "type": "Feature",
  "properties": {
    "iso:country":"IN",
    "ks:ks_name":"Bilaibeda",
    "ks:ks_pop":48,
    "ks:ks_type":"HABITATION",
    "name:eng_x_preferred":[
        "Bilaibeda"
    ],
    "wof:name":"Bilaibeda",
    "wof:placetype":"locality",
    "wof:population":48
},
  "geometry": {"coordinates":[81.027832,20.051251],"type":"Point"}
}