{
  "type": "Feature",
  "properties": {
    "iso:country":"IN",
    "ks:ks_name":"Bukhariya",
    "ks:ks_pop":58,
    "ks:ks_type":"HABITATION",
    "name:eng_x_preferred":[
        "Bukhariya"
    ],
    "wof:name":"Bukhariya",
    "wof:placetype":"locality",
    "wof:population":58
},
  "geometry": {"coordinates":[76.77546599999999,24.352345],"type":"Point"}
}