{
  "type": "Feature",
  "properties": {
    "iso:country":"IN",
    "ks:ks_name":"Abasingi",
    "ks:ks_pop":1028,
    "ks:ks_type":"VILLAGE",
    "name:eng_x_preferred":[
        "Abasingi"
    ],
    "wof:name":"Abasingi",
    "wof:placetype":"locality",
    "wof:population":1028
},
  "geometry": {"coordinates":[84.190243,18.959989],"type":"Point"}
}