{
  "type": "Feature",
  "properties": {
    "gn:admin1_code":"19.0",
    "gn:admin2_code":"567.0",
    "gn:asciiname":"Chittanhalli",
    "gn:country_code":"IN",
    "gn:dem":576,
    "gn:feature_class":"P",
    "gn:feature_code":"PPL",
    "gn:name":"Chittanhalli",
    "gn:population":0,
    "gn:timezone":"Asia/Kolkata",
    "iso:country":"IN",
    "ks:ks_name":"B Chittanahalli",
    "ks:ks_pop":910,
    "ks:ks_type":"HABITATION",
    "ks:ks_uagg_main":0,
    "name:eng_x_preferred":[
        "B Chittanahalli"
    ],
    "wof:name":"B Chittanahalli",
    "wof:placetype":"neighbourhood",
    "wof:population":910
},
  "geometry": {"coordinates":[75.9285,14.507044],"type":"Point"}
}