{
  "type": "Feature",
  "properties": {
    "gn:admin1_code":"36",
    "gn:admin2_code":"202.0",
    "gn:asciiname":"Jalilpur",
    "gn:country_code":"IN",
    "gn:dem":170,
    "gn:feature_class":"P",
    "gn:feature_code":"PPL",
    "gn:name":"Jal\u012blpur",
    "gn:population":0,
    "gn:timezone":"Asia/Kolkata",
    "iso:country":"IN",
    "name:und_x_variant":[
        "Jal\u012blpur",
        "Kutera"
    ],
    "wof:name":"Jalilpur",
    "wof:placetype":"locality"
},
  "geometry": {"coordinates":[78.82163,27.61447],"type":"Point"}
}