{
  "type": "Feature",
  "properties": {
    "iso:country":"IN",
    "ks:ks_name":"Dewal Bichharal",
    "ks:ks_pop":362,
    "ks:ks_type":"VILLAGE",
    "name:eng_x_preferred":[
        "Dewal Bichharal"
    ],
    "wof:name":"Dewal Bichharal",
    "wof:placetype":"locality",
    "wof:population":362
},
  "geometry": {"coordinates":[79.94603600000001,29.784026],"type":"Point"}
}