{
  "type": "Feature",
  "properties": {
    "iso:country":"IN",
    "ks:ks_name":"Ghatiaguda",
    "ks:ks_pop":115,
    "ks:ks_type":"HABITATION",
    "name:eng_x_preferred":[
        "Ghatiaguda"
    ],
    "wof:name":"Ghatiaguda",
    "wof:placetype":"locality",
    "wof:population":115
},
  "geometry": {"coordinates":[82.74427799999999,18.508038],"type":"Point"}
}