{
  "type": "Feature",
  "properties": {
    "iso:country":"IN",
    "ks:ks_name":"Asinpurwa",
    "ks:ks_pop":379,
    "ks:ks_type":"HABITATION",
    "name:eng_x_preferred":[
        "Asinpurwa"
    ],
    "wof:name":"Asinpurwa",
    "wof:placetype":"locality",
    "wof:population":379
},
  "geometry": {"coordinates":[81.045404,27.393469],"type":"Point"}
}