{
  "type": "Feature",
  "properties": {
    "iso:country":"IN",
    "ks:ks_name":"Harijan Pada",
    "ks:ks_pop":85,
    "ks:ks_type":"HABITATION",
    "name:eng_x_preferred":[
        "Harijan Pada"
    ],
    "wof:name":"Harijan Pada",
    "wof:placetype":"locality",
    "wof:population":85
},
  "geometry": {"coordinates":[83.4464,20.753166],"type":"Point"}
}