{
  "type": "Feature",
  "properties": {
    "iso:country":"IN",
    "ks:ks_name":"Deulgerya",
    "ks:ks_pop":0,
    "ks:ks_type":"VILLAGE",
    "name:eng_x_preferred":[
        "Deulgerya"
    ],
    "wof:name":"Deulgerya",
    "wof:placetype":"locality",
    "wof:population":0
},
  "geometry": {"coordinates":[87.46058600000001,22.673236],"type":"Point"}
}