{
  "type": "Feature",
  "properties": {
    "iso:country":"IN",
    "ks:ks_name":"Dhantali",
    "ks:ks_pop":710,
    "ks:ks_type":"VILLAGE",
    "name:eng_x_preferred":[
        "Dhantali"
    ],
    "wof:name":"Dhantali",
    "wof:placetype":"locality",
    "wof:population":710
},
  "geometry": {"coordinates":[89.795042,26.604168],"type":"Point"}
}