{
  "type": "Feature",
  "properties": {
    "iso:country":"IN",
    "ks:ks_name":"Nilambarapur",
    "ks:ks_pop":0,
    "ks:ks_type":"VILLAGE",
    "name:eng_x_preferred":[
        "Nilambarapur"
    ],
    "wof:name":"Nilambarapur",
    "wof:placetype":"locality",
    "wof:population":0
},
  "geometry": {"coordinates":[86.185889,20.691698],"type":"Point"}
}