{
  "type": "Feature",
  "properties": {
    "iso:country":"IN",
    "ks:ks_name":"Chotehiroli",
    "ks:ks_pop":71,
    "ks:ks_type":"HABITATION",
    "name:eng_x_preferred":[
        "Chotehiroli"
    ],
    "wof:name":"Chotehiroli",
    "wof:placetype":"locality",
    "wof:population":71
},
  "geometry": {"coordinates":[81.11575000000001,18.748454],"type":"Point"}
}