{
  "type": "Feature",
  "properties": {
    "iso:country":"IN",
    "ks:ks_name":"Jagroop Ka Dera",
    "ks:ks_pop":170,
    "ks:ks_type":"HABITATION",
    "name:eng_x_preferred":[
        "Jagroop Ka Dera"
    ],
    "wof:name":"Jagroop Ka Dera",
    "wof:placetype":"locality",
    "wof:population":170
},
  "geometry": {"coordinates":[80.929802,25.729543],"type":"Point"}
}