{
  "type": "Feature",
  "properties": {
    "gn:admin1_code":"16",
    "gn:admin2_code":"509.0",
    "gn:asciiname":"Kem",
    "gn:country_code":"IN",
    "gn:dem":251,
    "gn:feature_class":"P",
    "gn:feature_code":"PPL",
    "gn:name":"Kem",
    "gn:population":0,
    "gn:timezone":"Asia/Kolkata",
    "iso:country":"IN",
    "name:bel_x_preferred":[
        "\u041a\u0435\u043c"
    ],
    "name:ces_x_preferred":[
        "Kem"
    ],
    "name:fin_x_preferred":[
        "Kem"
    ],
    "name:fra_x_preferred":[
        "Kem"
    ],
    "name:hsb_x_preferred":[
        "Kem"
    ],
    "name:ita_x_preferred":[
        "Kem'"
    ],
    "name:nld_x_preferred":[
        "Kem"
    ],
    "name:nor_x_preferred":[
        "KEM"
    ],
    "name:pol_x_preferred":[
        "Kem"
    ],
    "name:rus_x_preferred":[
        "\u041a\u0435\u043c\u044c"
    ],
    "name:sco_x_preferred":[
        "Kem"
    ],
    "name:spa_x_preferred":[
        "Kem"
    ],
    "name:tur_x_preferred":[
        "Kem"
    ],
    "name:vep_x_preferred":[
        "Kem'"
    ],
    "name:vie_x_preferred":[
        "Kem"
    ],
    "wof:name":"Kem",
    "wof:placetype":"locality"
},
  "geometry": {"coordinates":[79.08171999999998,20.39565],"type":"Point"}
}