{
  "type": "Feature",
  "properties": {
    "iso:country":"IN",
    "ks:ks_name":"Doddabailu",
    "ks:ks_pop":57,
    "ks:ks_type":"HABITATION",
    "name:eng_x_preferred":[
        "Doddabailu"
    ],
    "wof:name":"Doddabailu",
    "wof:placetype":"locality",
    "wof:population":57
},
  "geometry": {"coordinates":[74.830275,14.838714],"type":"Point"}
}