{
  "type": "Feature",
  "properties": {
    "iso:country":"IN",
    "ks:ks_name":"Kumbhirmundi",
    "ks:ks_pop":150,
    "ks:ks_type":"VILLAGE",
    "name:eng_x_preferred":[
        "Kumbhirmundi"
    ],
    "wof:name":"Kumbhirmundi",
    "wof:placetype":"locality",
    "wof:population":150
},
  "geometry": {"coordinates":[86.416597,22.07017],"type":"Point"}
}