{
  "type": "Feature",
  "properties": {
    "gn:admin1_code":"19",
    "gn:admin2_code":"563.0",
    "gn:asciiname":"Amatgar",
    "gn:country_code":"IN",
    "gn:dem":561,
    "gn:feature_class":"P",
    "gn:feature_code":"PPL",
    "gn:name":"Amatg\u0101r",
    "gn:population":0,
    "gn:timezone":"Asia/Kolkata",
    "iso:country":"IN",
    "ks:ks_name":"Ammatgar",
    "ks:ks_pop":20,
    "ks:ks_type":"VILLAGE",
    "name:eng_x_preferred":[
        "Ammatgar"
    ],
    "name:eng_x_variant":[
        "Amatgar"
    ],
    "wof:name":"Ammatgar",
    "wof:placetype":"locality",
    "wof:population":20
},
  "geometry": {"coordinates":[74.948776,14.820961],"type":"Point"}
}