{
  "type": "Feature",
  "properties": {
    "gn:admin1_code":"19",
    "gn:admin2_code":"563.0",
    "gn:asciiname":"Amatgar",
    "gn:country_code":"IN",
    "gn:dem":561,
    "gn:feature_class":"P",
    "gn:feature_code":"PPL",
    "gn:name":"Amatg\u0101r",
    "gn:population":0,
    "gn:timezone":"Asia/Kolkata",
    "iso:country":"IN",
    "wof:name":"Amatgar",
    "wof:placetype":"locality"
},
  "geometry": {"coordinates":[74.96709,14.82745],"type":"Point"}
}