{
  "type": "Feature",
  "properties": {
    "gn:admin1_code":"2.0",
    "gn:admin2_code":"544.0",
    "gn:asciiname":"Gomangi",
    "gn:country_code":"IN",
    "gn:dem":973,
    "gn:feature_class":"P",
    "gn:feature_code":"PPL",
    "gn:name":"Gomangi",
    "gn:population":0,
    "gn:timezone":"Asia/Kolkata",
    "iso:country":"IN",
    "ks:ks_name":"Gomangi",
    "ks:ks_pop":27,
    "ks:ks_type":"HABITATION",
    "name:eng_x_preferred":[
        "Gomangi"
    ],
    "wof:name":"Gomangi",
    "wof:placetype":"locality",
    "wof:population":27
},
  "geometry": {"coordinates":[82.652956,18.104256],"type":"Point"}
}