{
  "type": "Feature",
  "properties": {
    "gn:admin1_code":"16",
    "gn:admin2_code":"517.0",
    "gn:asciiname":"Mathana",
    "gn:country_code":"IN",
    "gn:dem":13,
    "gn:feature_class":"P",
    "gn:feature_code":"PPL",
    "gn:name":"Math\u0101na",
    "gn:population":0,
    "gn:timezone":"Asia/Kolkata",
    "iso:country":"IN",
    "wof:name":"Mathana",
    "wof:placetype":"locality"
},
  "geometry": {"coordinates":[72.72464000000002,19.54893],"type":"Point"}
}