{
  "type": "Feature",
  "properties": {
    "iso:country":"IN",
    "ks:ks_name":"Kanagodu",
    "ks:ks_pop":7,
    "ks:ks_type":"HABITATION",
    "name:eng_x_preferred":[
        "Kanagodu"
    ],
    "wof:name":"Kanagodu",
    "wof:placetype":"locality",
    "wof:population":7
},
  "geometry": {"coordinates":[75.089223,13.985712],"type":"Point"}
}