{
  "type": "Feature",
  "properties": {
    "iso:country":"IN",
    "ks:ks_name":"Dhhavalewai",
    "ks:ks_pop":369,
    "ks:ks_type":"HABITATION",
    "name:eng_x_preferred":[
        "Dhhavalewai"
    ],
    "wof:name":"Dhhavalewai",
    "wof:placetype":"locality",
    "wof:population":369
},
  "geometry": {"coordinates":[73.889224,17.09288],"type":"Point"}
}