{
  "type": "Feature",
  "properties": {
    "iso:country":"IN",
    "ks:ks_name":"Rikhar Gaon",
    "ks:ks_pop":234,
    "ks:ks_type":"VILLAGE",
    "name:eng_x_preferred":[
        "Rikhar Gaon"
    ],
    "wof:name":"Rikhar Gaon",
    "wof:placetype":"locality",
    "wof:population":234
},
  "geometry": {"coordinates":[78.20062900000001,30.658163],"type":"Point"}
}