{
  "type": "Feature",
  "properties": {
    "gn:admin1_code":"34.0",
    "gn:admin2_code":"235.0",
    "gn:asciiname":"Bandhi",
    "gn:country_code":"IN",
    "gn:dem":330,
    "gn:feature_class":"P",
    "gn:feature_code":"PPL",
    "gn:name":"Bandhi",
    "gn:population":0,
    "gn:timezone":"Asia/Kolkata",
    "iso:country":"IN",
    "name:ceb_x_preferred":[
        "B\u0101ndhi"
    ],
    "name:fas_x_preferred":[
        "\u0628\u0627\u0646\u062f\u0647\u06cc"
    ],
    "name:fra_x_preferred":[
        "Bandhi"
    ],
    "name:snd_x_preferred":[
        "\u067b\u0627\u0646\u068c\u064a"
    ],
    "name:urd_x_preferred":[
        "\u0628\u0627\u0646\u062f\u06be\u06cc"
    ],
    "wof:name":"Bandhi",
    "wof:placetype":"locality"
},
  "geometry": {"coordinates":[84.53782,24.54529],"type":"Point"}
}