{
  "type": "Feature",
  "properties": {
    "iso:country":"IN",
    "ks:ks_name":"Rajmao Na Paglam",
    "ks:ks_pop":349,
    "ks:ks_type":"VILLAGE",
    "name:eng_x_preferred":[
        "Rajmao Na Paglam"
    ],
    "wof:name":"Rajmao Na Paglam",
    "wof:placetype":"locality",
    "wof:population":349
},
  "geometry": {"coordinates":[95.758162,27.873713],"type":"Point"}
}