{
  "type": "Feature",
  "properties": {
    "iso:country":"IN",
    "ks:ks_name":"Kadvimane",
    "ks:ks_pop":11,
    "ks:ks_type":"HABITATION",
    "name:eng_x_preferred":[
        "Kadvimane"
    ],
    "wof:name":"Kadvimane",
    "wof:placetype":"locality",
    "wof:population":11
},
  "geometry": {"coordinates":[74.86949199999999,14.206678],"type":"Point"}
}