{
  "type": "Feature",
  "properties": {
    "gn:admin1_code":"19.0",
    "gn:admin2_code":"570.0",
    "gn:asciiname":"Hangalu",
    "gn:country_code":"IN",
    "gn:dem":689,
    "gn:feature_class":"P",
    "gn:feature_code":"PPL",
    "gn:name":"Hang\u0101lu",
    "gn:population":0,
    "gn:timezone":"Asia/Kolkata",
    "iso:country":"IN",
    "ks:ks_name":"Hanngalu",
    "ks:ks_pop":78,
    "ks:ks_type":"HABITATION",
    "name:eng_x_preferred":[
        "Hanngalu"
    ],
    "name:eng_x_variant":[
        "Hangalu"
    ],
    "wof:name":"Hanngalu",
    "wof:placetype":"locality",
    "wof:population":78
},
  "geometry": {"coordinates":[75.291585,13.497095],"type":"Point"}
}