{
  "type": "Feature",
  "properties": {
    "iso:country":"IN",
    "ks:ks_name":"Moagram",
    "ks:ks_pop":336,
    "ks:ks_type":"HABITATION",
    "name:eng_x_preferred":[
        "Moagram"
    ],
    "wof:name":"Moagram",
    "wof:placetype":"locality",
    "wof:population":336
},
  "geometry": {"coordinates":[92.54496899999999,24.983058],"type":"Point"}
}