{
  "type": "Feature",
  "properties": {
    "gn:admin1_code":"36",
    "gn:admin2_code":"154.0",
    "gn:asciiname":"Paintepur",
    "gn:country_code":"IN",
    "gn:dem":125,
    "gn:feature_class":"P",
    "gn:feature_code":"PPL",
    "gn:name":"Paintepur",
    "gn:population":0,
    "gn:timezone":"Asia/Kolkata",
    "iso:country":"IN",
    "name:bpy_x_preferred":[
        "\u09aa\u09be\u0987\u09a8\u09cd\u09a4\u09c7\u09aa\u09c1\u09b0"
    ],
    "name:ita_x_preferred":[
        "Paintepur"
    ],
    "name:msa_x_preferred":[
        "Paintepur"
    ],
    "name:nld_x_preferred":[
        "Paintepur"
    ],
    "name:pol_x_preferred":[
        "Paintepur"
    ],
    "name:por_x_preferred":[
        "Paintepur"
    ],
    "name:urd_x_preferred":[
        "\u067e\u06cc\u0646\u062a\u06d2 \u067e\u0648\u0631"
    ],
    "name:vie_x_preferred":[
        "Paintepur"
    ],
    "name:zho_x_preferred":[
        "\u6d3e\u6069\u6cf0\u666e\u5c14"
    ],
    "wof:name":"Paintepur",
    "wof:placetype":"locality"
},
  "geometry": {"coordinates":[81.18213,27.27801],"type":"Point"}
}