{
  "type": "Feature",
  "properties": {
    "iso:country":"IN",
    "ks:ks_name":"Gulamapalli",
    "ks:ks_pop":102,
    "ks:ks_type":"HABITATION",
    "name:eng_x_preferred":[
        "Gulamapalli"
    ],
    "wof:name":"Gulamapalli",
    "wof:placetype":"locality",
    "wof:population":102
},
  "geometry": {"coordinates":[82.89555300000001,18.160798],"type":"Point"}
}