{
  "type": "Feature",
  "properties": {
    "iso:country":"IN",
    "ks:ks_name":"Lutua",
    "ks:ks_pop":0,
    "ks:ks_type":"VILLAGE",
    "name:eng_x_preferred":[
        "Lutua"
    ],
    "wof:name":"Lutua",
    "wof:placetype":"locality",
    "wof:population":0
},
  "geometry": {"coordinates":[84.91389599999999,24.278297],"type":"Point"}
}