{
  "type": "Feature",
  "properties": {
    "iso:country":"IN",
    "ks:ks_name":"Geraja",
    "ks:ks_pop":220,
    "ks:ks_type":"VILLAGE",
    "name:eng_x_preferred":[
        "Geraja"
    ],
    "wof:name":"Geraja",
    "wof:placetype":"locality",
    "wof:population":220
},
  "geometry": {"coordinates":[70.834278,26.542213],"type":"Point"}
}