{
  "type": "Feature",
  "properties": {
    "gn:admin1_code":"37",
    "gn:admin2_code":"404.0",
    "gn:asciiname":"Kolga",
    "gn:country_code":"IN",
    "gn:dem":328,
    "gn:feature_class":"P",
    "gn:feature_code":"PPL",
    "gn:name":"Kolga",
    "gn:population":0,
    "gn:timezone":"Asia/Kolkata",
    "iso:country":"IN",
    "name:ceb_x_preferred":[
        "Kolga"
    ],
    "name:deu_x_preferred":[
        "Kolga"
    ],
    "name:est_x_preferred":[
        "Kolga"
    ],
    "name:fra_x_preferred":[
        "Kolga"
    ],
    "name:hye_x_preferred":[
        "\u053f\u0578\u056c\u0563\u0561"
    ],
    "name:nld_x_preferred":[
        "Kolga"
    ],
    "name:pol_x_preferred":[
        "Kolga"
    ],
    "name:rus_x_preferred":[
        "\u041a\u043e\u043b\u0433\u0430"
    ],
    "name:sco_x_preferred":[
        "Kolga"
    ],
    "name:spa_x_preferred":[
        "Kolga"
    ],
    "name:swe_x_preferred":[
        "Kolga"
    ],
    "name:ukr_x_preferred":[
        "\u041a\u043e\u043b\u0433\u0430"
    ],
    "name:vol_x_preferred":[
        "Kolga"
    ],
    "wof:name":"Kolga",
    "wof:placetype":"locality"
},
  "geometry": {"coordinates":[82.9909,22.39783],"type":"Point"}
}