{
  "type": "Feature",
  "properties": {
    "iso:country":"IN",
    "ks:ks_name":"Nagra",
    "ks:ks_type":"VILLAGE",
    "ks:ks_uagg_main":0,
    "name:eng_x_preferred":[
        "Nagra"
    ],
    "wof:name":"Nagra",
    "wof:placetype":"neighbourhood"
},
  "geometry": {"coordinates":[85.239812,25.582923],"type":"Point"}
}