{
  "type": "Feature",
  "properties": {
    "gn:admin1_code":"40.0",
    "gn:admin2_code":"537.0",
    "gn:asciiname":"Masjidpur",
    "gn:country_code":"IN",
    "gn:dem":573,
    "gn:feature_class":"P",
    "gn:feature_code":"PPL",
    "gn:name":"Masjidpur",
    "gn:population":0,
    "gn:timezone":"Asia/Kolkata",
    "iso:country":"IN",
    "wof:name":"Masjidpur",
    "wof:placetype":"locality"
},
  "geometry": {"coordinates":[78.56809,17.62388],"type":"Point"}
}