{
  "type": "Feature",
  "properties": {
    "iso:country":"IN",
    "ks:ks_name":"Elashijhar",
    "ks:ks_pop":207,
    "ks:ks_type":"HABITATION",
    "name:eng_x_preferred":[
        "Elashijhar"
    ],
    "wof:name":"Elashijhar",
    "wof:placetype":"locality",
    "wof:population":207
},
  "geometry": {"coordinates":[90.23758599999999,26.418843],"type":"Point"}
}