{
  "type": "Feature",
  "properties": {
    "gn:admin1_code":"35",
    "gn:admin2_code":"427.0",
    "gn:asciiname":"Naindhara",
    "gn:country_code":"IN",
    "gn:dem":416,
    "gn:feature_class":"P",
    "gn:feature_code":"PPL",
    "gn:name":"Naindhara",
    "gn:population":0,
    "gn:timezone":"Asia/Kolkata",
    "iso:country":"IN",
    "name:und_x_variant":[
        "Naindara",
        "Naindhara"
    ],
    "wof:name":"Naindhara",
    "wof:placetype":"neighbourhood"
},
  "geometry": {"coordinates":[79.09023000000001,24.0146],"type":"Point"}
}