{
  "type": "Feature",
  "properties": {
    "gn:admin1_code":"21.0",
    "gn:admin2_code":"377.0",
    "gn:asciiname":"Sardang",
    "gn:country_code":"IN",
    "gn:dem":19,
    "gn:feature_class":"P",
    "gn:feature_code":"PPL",
    "gn:name":"Sardang",
    "gn:population":0,
    "gn:timezone":"Asia/Kolkata",
    "iso:country":"IN",
    "ks:ks_name":"Sardang",
    "ks:ks_pop":3730,
    "ks:ks_type":"VILLAGE",
    "name:eng_x_preferred":[
        "Sardang"
    ],
    "wof:name":"Sardang",
    "wof:placetype":"locality",
    "wof:population":3730
},
  "geometry": {"coordinates":[86.525148,21.238939],"type":"Point"}
}