{
  "type": "Feature",
  "properties": {
    "iso:country":"IN",
    "ks:ks_name":"Bazar Tola",
    "ks:ks_pop":333,
    "ks:ks_type":"HABITATION",
    "ks:ks_uagg_main":0,
    "name:eng_x_preferred":[
        "Bazar Tola"
    ],
    "wof:name":"Bazar Tola",
    "wof:placetype":"neighbourhood",
    "wof:population":333
},
  "geometry": {"coordinates":[84.09053900000001,26.139297],"type":"Point"}
}