{
  "type": "Feature",
  "properties": {
    "iso:country":"IN",
    "ks:ks_name":"Buidhew Khurd",
    "ks:ks_pop":4285,
    "ks:ks_type":"HABITATION",
    "name:eng_x_preferred":[
        "Buidhew Khurd"
    ],
    "wof:name":"Buidhew Khurd",
    "wof:placetype":"locality",
    "wof:population":4285
},
  "geometry": {"coordinates":[79.042912,28.406192],"type":"Point"}
}