{
  "type": "Feature",
  "properties": {
    "gn:admin1_code":"38.0",
    "gn:admin2_code":"352.0",
    "gn:asciiname":"Gauripur",
    "gn:country_code":"IN",
    "gn:dem":90,
    "gn:feature_class":"P",
    "gn:feature_code":"PPL",
    "gn:name":"Gaur\u012bpur",
    "gn:population":0,
    "gn:timezone":"Asia/Kolkata",
    "iso:country":"IN",
    "ks:ks_name":"Gauripur",
    "ks:ks_pop":982,
    "ks:ks_type":"VILLAGE",
    "ks:ks_uagg_main":0,
    "name:ceb_x_preferred":[
        "Gauripur"
    ],
    "name:eng_x_preferred":[
        "Gauripur"
    ],
    "name:sco_x_preferred":[
        "Gauripur"
    ],
    "name:swe_x_preferred":[
        "Gauripur"
    ],
    "wof:name":"Gauripur",
    "wof:placetype":"neighbourhood",
    "wof:population":982
},
  "geometry": {"coordinates":[87.586913,25.039271],"type":"Point"}
}