{
  "type": "Feature",
  "properties": {
    "iso:country":"IN",
    "ks:ks_name":"Akajan Bangali",
    "ks:ks_pop":336,
    "ks:ks_type":"VILLAGE",
    "ks:ks_uagg_main":0,
    "name:eng_x_preferred":[
        "Akajan Bangali"
    ],
    "wof:name":"Akajan Bangali",
    "wof:placetype":"neighbourhood",
    "wof:population":336
},
  "geometry": {"coordinates":[94.743439,27.567398],"type":"Point"}
}