{
  "type": "Feature",
  "properties": {
    "gn:admin1_code":"19.0",
    "gn:admin2_code":"578.0",
    "gn:asciiname":"Kavudavadi",
    "gn:country_code":"IN",
    "gn:dem":681,
    "gn:feature_class":"P",
    "gn:feature_code":"PPL",
    "gn:name":"K\u0101vudav\u0101di",
    "gn:population":0,
    "gn:timezone":"Asia/Kolkata",
    "iso:country":"IN",
    "wof:name":"Kavudavadi",
    "wof:placetype":"locality"
},
  "geometry": {"coordinates":[76.98553000000003,12.06214],"type":"Point"}
}