{
  "type": "Feature",
  "properties": {
    "gn:admin1_code":"12.0",
    "gn:admin2_code":"17.0",
    "gn:asciiname":"Tharan",
    "gn:country_code":"IN",
    "gn:dem":2657,
    "gn:feature_class":"P",
    "gn:feature_code":"PPL",
    "gn:name":"Tharan",
    "gn:population":0,
    "gn:timezone":"Asia/Kolkata",
    "iso:country":"IN",
    "wof:name":"Tharan",
    "wof:placetype":"locality"
},
  "geometry": {"coordinates":[75.23068000000001,33.1541],"type":"Point"}
}