{
  "type": "Feature",
  "properties": {
    "gn:admin1_code":"24.0",
    "gn:admin2_code":"100.0",
    "gn:asciiname":"Chak Sardarpura",
    "gn:country_code":"IN",
    "gn:dem":194,
    "gn:feature_class":"P",
    "gn:feature_code":"PPL",
    "gn:name":"Chak Sard\u0101rpura",
    "gn:population":0,
    "gn:timezone":"Asia/Kolkata",
    "iso:country":"IN",
    "wof:name":"Chak Sardarpura",
    "wof:placetype":"neighbourhood"
},
  "geometry": {"coordinates":[74.79652,29.16489],"type":"Point"}
}