{
  "type": "Feature",
  "properties": {
    "iso:country":"IN",
    "ks:ks_name":"Ambangndili",
    "ks:ks_pop":70,
    "ks:ks_type":"HABITATION",
    "name:eng_x_preferred":[
        "Ambangndili"
    ],
    "wof:name":"Ambangndili",
    "wof:placetype":"locality",
    "wof:population":70
},
  "geometry": {"coordinates":[82.196772,18.794235],"type":"Point"}
}