{
  "type": "Feature",
  "properties": {
    "gn:admin1_code":"35.0",
    "gn:admin2_code":"454.0",
    "gn:asciiname":"Isharpur",
    "gn:country_code":"IN",
    "gn:dem":584,
    "gn:feature_class":"P",
    "gn:feature_code":"PPL",
    "gn:name":"\u012asharpur",
    "gn:population":0,
    "gn:timezone":"Asia/Kolkata",
    "iso:country":"IN",
    "wof:name":"Isharpur",
    "wof:placetype":"locality"
},
  "geometry": {"coordinates":[80.74614,22.57873],"type":"Point"}
}