{
  "type": "Feature",
  "properties": {
    "gn:admin1_code":"35.0",
    "gn:admin2_code":"454.0",
    "gn:asciiname":"Isharpur",
    "gn:country_code":"IN",
    "gn:dem":584,
    "gn:feature_class":"P",
    "gn:feature_code":"PPL",
    "gn:name":"\u012asharpur",
    "gn:population":0,
    "gn:timezone":"Asia/Kolkata",
    "iso:country":"IN",
    "ks:ks_name":"Ishwarpur",
    "ks:ks_pop":750,
    "ks:ks_type":"VILLAGE",
    "name:eng_x_preferred":[
        "Ishwarpur"
    ],
    "name:eng_x_variant":[
        "Isharpur"
    ],
    "wof:name":"Ishwarpur",
    "wof:placetype":"locality",
    "wof:population":750
},
  "geometry": {"coordinates":[80.742257,22.574197],"type":"Point"}
}