{
  "type": "Feature",
  "properties": {
    "iso:country":"IN",
    "ks:ks_name":"Barh Radho Das Pura",
    "ks:ks_pop":14,
    "ks:ks_type":"HABITATION",
    "name:eng_x_preferred":[
        "Barh Radho Das Pura"
    ],
    "wof:name":"Barh Radho Das Pura",
    "wof:placetype":"locality",
    "wof:population":14
},
  "geometry": {"coordinates":[75.967944,26.923877],"type":"Point"}
}