{
  "type": "Feature",
  "properties": {
    "iso:country":"IN",
    "ks:ks_name":"Baleswar",
    "ks:ks_pop":228,
    "ks:ks_type":"VILLAGE",
    "name:eng_x_preferred":[
        "Baleswar"
    ],
    "wof:name":"Baleswar",
    "wof:placetype":"locality",
    "wof:population":228
},
  "geometry": {"coordinates":[85.10409199999999,21.001737],"type":"Point"}
}