{
  "type": "Feature",
  "properties": {
    "gn:admin1_code":"25.0",
    "gn:admin2_code":"632.0",
    "gn:asciiname":"Pannimadai",
    "gn:country_code":"IN",
    "gn:dem":478,
    "gn:feature_class":"P",
    "gn:feature_code":"PPL",
    "gn:name":"Pannimadai",
    "gn:population":0,
    "gn:timezone":"Asia/Kolkata",
    "iso:country":"IN",
    "ks:ks_name":"Pannimadai",
    "ks:ks_pop":4908,
    "ks:ks_type":"VILLAGE",
    "ks:ks_uagg_main":0,
    "name:eng_x_preferred":[
        "Pannimadai"
    ],
    "wof:name":"Pannimadai",
    "wof:placetype":"locality",
    "wof:population":4908
},
  "geometry": {"coordinates":[76.917553,11.08499],"type":"Point"}
}