{
  "type": "Feature",
  "properties": {
    "iso:country":"IN",
    "ks:ks_name":"Tembi",
    "ks:ks_pop":8,
    "ks:ks_type":"VILLAGE",
    "name:eng_x_preferred":[
        "Tembi"
    ],
    "wof:name":"Tembi",
    "wof:placetype":"locality",
    "wof:population":8
},
  "geometry": {"coordinates":[77.98051,20.55998],"type":"Point"}
}