{
  "type": "Feature",
  "properties": {
    "iso:country":"IN",
    "ks:ks_name":"Jhau",
    "ks:ks_pop":0,
    "ks:ks_type":"VILLAGE",
    "name:eng_x_preferred":[
        "Jhau"
    ],
    "wof:name":"Jhau",
    "wof:placetype":"locality",
    "wof:population":0
},
  "geometry": {"coordinates":[86.979258,25.311399],"type":"Point"}
}