{
  "type": "Feature",
  "properties": {
    "iso:country":"IN",
    "ks:ks_name":"Ramnaresh Tola",
    "ks:ks_pop":35,
    "ks:ks_type":"HABITATION",
    "ks:ks_uagg_main":0,
    "name:eng_x_preferred":[
        "Ramnaresh Tola"
    ],
    "wof:name":"Ramnaresh Tola",
    "wof:placetype":"neighbourhood",
    "wof:population":35
},
  "geometry": {"coordinates":[83.716922,26.953742],"type":"Point"}
}