{
  "type": "Feature",
  "properties": {
    "iso:country":"IN",
    "ks:ks_name":"Takimari",
    "ks:ks_pop":305,
    "ks:ks_type":"VILLAGE",
    "name:eng_x_preferred":[
        "Takimari"
    ],
    "wof:name":"Takimari",
    "wof:placetype":"locality",
    "wof:population":305
},
  "geometry": {"coordinates":[89.330617,26.131548],"type":"Point"}
}