{
  "type": "Feature",
  "properties": {
    "iso:country":"IN",
    "ks:ks_alt_nam":"mavinakatte",
    "ks:ks_name":"Mavinakatte",
    "ks:ks_pop":209,
    "ks:ks_type":"HABITATION",
    "name:eng_x_preferred":[
        "Mavinakatte"
    ],
    "wof:name":"Mavinakatte",
    "wof:placetype":"locality",
    "wof:population":209
},
  "geometry": {"coordinates":[75.23053400000001,13.506817],"type":"Point"}
}