{
  "type": "Feature",
  "properties": {
    "iso:country":"IN",
    "ks:ks_alt_nam":"BARHI TOLA",
    "ks:ks_name":"Barhi Tola",
    "ks:ks_pop":194,
    "ks:ks_type":"HABITATION",
    "name:eng_x_preferred":[
        "Barhi Tola"
    ],
    "wof:name":"Barhi Tola",
    "wof:placetype":"locality",
    "wof:population":194
},
  "geometry": {"coordinates":[86.04518,25.2418],"type":"Point"}
}