{
  "type": "Feature",
  "properties": {
    "gn:admin1_code":"19.0",
    "gn:admin2_code":"574.0",
    "gn:asciiname":"Haralahalli",
    "gn:country_code":"IN",
    "gn:dem":948,
    "gn:feature_class":"P",
    "gn:feature_code":"PPL",
    "gn:name":"Haralahalli",
    "gn:population":0,
    "gn:timezone":"Asia/Kolkata",
    "iso:country":"IN",
    "wof:name":"Haralahalli",
    "wof:placetype":"locality"
},
  "geometry": {"coordinates":[76.05549999999999,13.02291],"type":"Point"}
}