{
  "type": "Feature",
  "properties": {
    "gn:admin1_code":"36.0",
    "gn:admin2_code":"184.0",
    "gn:asciiname":"Chandapur",
    "gn:country_code":"IN",
    "gn:dem":91,
    "gn:feature_class":"P",
    "gn:feature_code":"PPL",
    "gn:name":"Ch\u0101ndapur",
    "gn:population":0,
    "gn:timezone":"Asia/Kolkata",
    "iso:country":"IN",
    "ks:ks_alt_nam":"Ch\u0101ndapur",
    "ks:ks_name":"Chandapur",
    "ks:ks_type":"VILLAGE",
    "ks:ks_uagg_main":0,
    "name:ben_x_preferred":[
        "\u099a\u09be\u09a8\u09cd\u09a6\u09be\u09aa\u09c1\u09b0"
    ],
    "name:bpy_x_preferred":[
        "\u099a\u09be\u09a8\u09cd\u09a6\u09be\u09aa\u09c1\u09b0"
    ],
    "name:eng_x_preferred":[
        "Chandapur"
    ],
    "name:eng_x_variant":[
        "Ch\u0101ndapur"
    ],
    "name:ita_x_preferred":[
        "Chandapur"
    ],
    "name:msa_x_preferred":[
        "Chandapur"
    ],
    "name:new_x_preferred":[
        "\u091a\u0928\u094d\u0926\u093e\u092a\u0941\u0930"
    ],
    "name:nld_x_preferred":[
        "Chandapur"
    ],
    "name:por_x_preferred":[
        "Chandapur"
    ],
    "name:vie_x_preferred":[
        "Chandapur"
    ],
    "name:zho_x_preferred":[
        "\u94b1\u8fbe\u666e\u5c14"
    ],
    "wof:name":"Chandapur",
    "wof:placetype":"neighbourhood"
},
  "geometry": {"coordinates":[82.906491,27.063937],"type":"Point"}
}