{
  "type": "Feature",
  "properties": {
    "iso:country":"IN",
    "ks:ks_name":"Kori Purwa",
    "ks:ks_pop":124,
    "ks:ks_type":"HABITATION",
    "name:eng_x_preferred":[
        "Kori Purwa"
    ],
    "wof:name":"Kori Purwa",
    "wof:placetype":"locality",
    "wof:population":124
},
  "geometry": {"coordinates":[82.05815200000001,27.018564],"type":"Point"}
}