{
  "type": "Feature",
  "properties": {
    "iso:country":"IN",
    "ks:ks_name":"Mahishdubi",
    "ks:ks_pop":0,
    "ks:ks_type":"VILLAGE",
    "name:eng_x_preferred":[
        "Mahishdubi"
    ],
    "wof:name":"Mahishdubi",
    "wof:placetype":"locality",
    "wof:population":0
},
  "geometry": {"coordinates":[87.354969,22.666654],"type":"Point"}
}