{
  "type": "Feature",
  "properties": {
    "iso:country":"IN",
    "ks:ks_name":"Chota Hatta",
    "ks:ks_pop":105,
    "ks:ks_type":"HABITATION",
    "name:eng_x_preferred":[
        "Chota Hatta"
    ],
    "wof:name":"Chota Hatta",
    "wof:placetype":"locality",
    "wof:population":105
},
  "geometry": {"coordinates":[88.093396,27.075297],"type":"Point"}
}