{
  "type": "Feature",
  "properties": {
    "iso:country":"IN",
    "ks:ks_name":"Eerlapenta",
    "ks:ks_pop":65,
    "ks:ks_type":"HABITATION",
    "name:eng_x_preferred":[
        "Eerlapenta"
    ],
    "wof:name":"Eerlapenta",
    "wof:placetype":"locality",
    "wof:population":65
},
  "geometry": {"coordinates":[78.57821,16.238639],"type":"Point"}
}