{
  "type": "Feature",
  "properties": {
    "gn:admin1_code":"36.0",
    "gn:admin2_code":"195.0",
    "gn:asciiname":"Badhu Sarai",
    "gn:country_code":"IN",
    "gn:dem":73,
    "gn:feature_class":"P",
    "gn:feature_code":"PPL",
    "gn:name":"Badhu Sarai",
    "gn:population":0,
    "gn:timezone":"Asia/Kolkata",
    "iso:country":"IN",
    "wof:name":"Badhu Sarai",
    "wof:placetype":"locality"
},
  "geometry": {"coordinates":[83.58105999999999,25.65864],"type":"Point"}
}