{
  "type": "Feature",
  "properties": {
    "gn:admin1_code":"37",
    "gn:asciiname":"Farfod",
    "gn:country_code":"IN",
    "gn:dem":385,
    "gn:feature_class":"P",
    "gn:feature_code":"PPL",
    "gn:name":"Farfod",
    "gn:population":0,
    "gn:timezone":"Asia/Kolkata",
    "iso:country":"IN",
    "wof:name":"Farfod",
    "wof:placetype":"locality"
},
  "geometry": {"coordinates":[82.35807,20.88013],"type":"Point"}
}