{
  "type": "Feature",
  "properties": {
    "iso:country":"IN",
    "ks:ks_name":"Konnasedu",
    "ks:ks_pop":88,
    "ks:ks_type":"HABITATION",
    "name:eng_x_preferred":[
        "Konnasedu"
    ],
    "wof:name":"Konnasedu",
    "wof:placetype":"locality",
    "wof:population":88
},
  "geometry": {"coordinates":[78.51867300000001,11.836915],"type":"Point"}
}