{
  "type": "Feature",
  "properties": {
    "iso:country":"IN",
    "ks:ks_name":"Jadudih",
    "ks:ks_pop":359,
    "ks:ks_type":"VILLAGE",
    "ks:ks_uagg_main":0,
    "name:eng_x_preferred":[
        "Jadudih"
    ],
    "wof:name":"Jadudih",
    "wof:placetype":"neighbourhood",
    "wof:population":359
},
  "geometry": {"coordinates":[86.56812499999999,24.086043],"type":"Point"}
}