{
  "type": "Feature",
  "properties": {
    "iso:country":"IN",
    "ks:ks_name":"Gollarahatti",
    "ks:ks_pop":144,
    "ks:ks_type":"HABITATION",
    "name:eng_x_preferred":[
        "Gollarahatti"
    ],
    "wof:name":"Gollarahatti",
    "wof:placetype":"locality",
    "wof:population":144
},
  "geometry": {"coordinates":[76.749714,13.361522],"type":"Point"}
}