{
  "type": "Feature",
  "properties": {
    "iso:country":"IN",
    "ks:ks_name":"Jilleduvalasa",
    "ks:ks_pop":280,
    "ks:ks_type":"HABITATION",
    "name:eng_x_preferred":[
        "Jilleduvalasa"
    ],
    "wof:name":"Jilleduvalasa",
    "wof:placetype":"locality",
    "wof:population":280
},
  "geometry": {"coordinates":[83.22559099999999,18.738447],"type":"Point"}
}