{
  "type": "Feature",
  "properties": {
    "iso:country":"IN",
    "ks:ks_name":"Sonapur Salani Gaon",
    "ks:ks_pop":71,
    "ks:ks_type":"HABITATION",
    "name:eng_x_preferred":[
        "Sonapur Salani Gaon"
    ],
    "wof:name":"Sonapur Salani Gaon",
    "wof:placetype":"locality",
    "wof:population":71
},
  "geometry": {"coordinates":[93.12243700000001,26.259165],"type":"Point"}
}