{
  "type": "Feature",
  "properties": {
    "iso:country":"IN",
    "ks:ks_name":"Udayagiri",
    "ks:ks_pop":233,
    "ks:ks_type":"HABITATION",
    "name:eng_x_preferred":[
        "Udayagiri"
    ],
    "wof:name":"Udayagiri",
    "wof:placetype":"locality",
    "wof:population":233
},
  "geometry": {"coordinates":[86.142195,20.654073],"type":"Point"}
}