{
  "type": "Feature",
  "properties": {
    "iso:country":"IN",
    "ks:ks_name":"Chichorguda",
    "ks:ks_pop":215,
    "ks:ks_type":"VILLAGE",
    "name:eng_x_preferred":[
        "Chichorguda"
    ],
    "wof:name":"Chichorguda",
    "wof:placetype":"locality",
    "wof:population":215
},
  "geometry": {"coordinates":[81.570779,18.417988],"type":"Point"}
}