{
  "type": "Feature",
  "properties": {
    "iso:country":"IN",
    "ks:ks_alt_nam":"Pudiyotil kadav",
    "ks:ks_name":"Pudiyotil Kadav",
    "ks:ks_pop":971,
    "ks:ks_type":"HABITATION",
    "name:eng_x_preferred":[
        "Pudiyotil Kadav"
    ],
    "wof:name":"Pudiyotil Kadav",
    "wof:placetype":"locality",
    "wof:population":971
},
  "geometry": {"coordinates":[75.74678400000001,11.350505],"type":"Point"}
}