{
  "type": "Feature",
  "properties": {
    "iso:country":"IN",
    "ks:ks_name":"Rasal",
    "ks:ks_pop":1193,
    "ks:ks_type":"VILLAGE",
    "name:eng_x_preferred":[
        "Rasal"
    ],
    "wof:name":"Rasal",
    "wof:placetype":"locality",
    "wof:population":1193
},
  "geometry": {"coordinates":[73.24588199999999,18.558357],"type":"Point"}
}