{
  "type": "Feature",
  "properties": {
    "iso:country":"IN",
    "ks:ks_name":"Bhair Gaon",
    "ks:ks_pop":28,
    "ks:ks_type":"VILLAGE",
    "name:eng_x_preferred":[
        "Bhair Gaon"
    ],
    "wof:name":"Bhair Gaon",
    "wof:placetype":"locality",
    "wof:population":28
},
  "geometry": {"coordinates":[78.718282,30.008625],"type":"Point"}
}