{
  "type": "Feature",
  "properties": {
    "iso:country":"IN",
    "ks:ks_alt_nam":"JHAKARA",
    "ks:ks_name":"Jhakara",
    "ks:ks_pop":23,
    "ks:ks_type":"HABITATION",
    "name:eng_x_preferred":[
        "Jhakara"
    ],
    "wof:name":"Jhakara",
    "wof:placetype":"locality",
    "wof:population":23
},
  "geometry": {"coordinates":[85.168075,24.313634],"type":"Point"}
}