{
  "type": "Feature",
  "properties": {
    "iso:country":"IN",
    "ks:ks_alt_nam":"S\u0101h\u0101rpur",
    "ks:ks_name":"Saharpur",
    "ks:ks_pop":1001,
    "ks:ks_type":"VILLAGE",
    "name:eng_x_preferred":[
        "Saharpur"
    ],
    "name:eng_x_variant":[
        "S\u0101h\u0101rpur"
    ],
    "wof:name":"Saharpur",
    "wof:placetype":"locality",
    "wof:population":1001
},
  "geometry": {"coordinates":[85.416443,21.594579],"type":"Point"}
}