{
  "type": "Feature",
  "properties": {
    "gn:country":"IN",
    "gn:fcode":"PPL",
    "gn:pop":28208,
    "iso:country":"IN",
    "name:ben_x_preferred":[
        "\u09b6\u09cd\u09b0\u09c0\u0997\u09cb\u09a8\u09cd\u09a6\u09be"
    ],
    "name:bpy_x_preferred":[
        "\u09b6\u09cd\u09b0\u09c0\u0997\u09cb\u09a8\u09cd\u09a6\u09be"
    ],
    "name:deu_x_preferred":[
        "Shrigonda"
    ],
    "name:eng_x_preferred":[
        "Shrigonda"
    ],
    "name:fra_x_preferred":[
        "Shrigonda"
    ],
    "name:guj_x_preferred":[
        "\u0ab6\u0acd\u0ab0\u0ac0\u0a97\u0acb\u0a82\u0aa1\u0abe"
    ],
    "name:ita_x_preferred":[
        "Shrigonda"
    ],
    "name:jpn_x_preferred":[
        "\u30b7\u30e5\u30ea\u30b4\u30f3\u30c0"
    ],
    "name:kan_x_preferred":[
        "\u0cb6\u0cb0\u0cbf\u0c97\u0cca\u0c82\u0ca1\u0cbe"
    ],
    "name:kor_x_preferred":[
        "\uc2dc\ub9ac\ub2f9\ub2e4"
    ],
    "name:mar_x_preferred":[
        "\u0936\u094d\u0930\u0940\u0917\u094b\u0902\u0926\u093e"
    ],
    "name:mlg_x_preferred":[
        "Shrigonda"
    ],
    "name:msa_x_preferred":[
        "Shrigonda"
    ],
    "name:nan_x_preferred":[
        "Shrigonda"
    ],
    "name:nld_x_preferred":[
        "Shrigonda"
    ],
    "name:ori_x_preferred":[
        "\u0b36\u0b4d\u0b30\u0b40\u0b17\u0b4b\u0b28\u0b4d\u0b26\u0b3e"
    ],
    "name:pam_x_preferred":[
        "Shrigonda"
    ],
    "name:por_x_preferred":[
        "Shrigonda"
    ],
    "name:rus_x_preferred":[
        "\u0428\u0440\u0438\u0433\u043e\u043d\u0434\u0430"
    ],
    "name:spa_x_preferred":[
        "Shrigonda"
    ],
    "name:swe_x_preferred":[
        "Shr\u012bgonda"
    ],
    "name:tam_x_preferred":[
        "\u0bb8\u0bcd\u0bb0\u0bc0\u0b95\u0bcb\u0ba9\u0bcd\u0b9f\u0bbe"
    ],
    "name:tel_x_preferred":[
        "\u0c36\u0c4d\u0c30\u0c40\u0c17\u0c4b\u0c02\u0c21\u0c3e"
    ],
    "name:unk_x_variant":[
        "Shr\u012bgonda"
    ],
    "name:urd_x_preferred":[
        "\u0634\u0631\u06cc \u06af\u0648\u0646\u0688\u0627"
    ],
    "name:vie_x_preferred":[
        "Shrigonda"
    ],
    "name:zho_x_preferred":[
        "\u65af\u8d6b\u91cc\u8d21\u8fbe"
    ],
    "qs:name":"Shrigonda",
    "qs:name_adm0":"India",
    "qs:name_adm1":"Maharashtra",
    "qs:photos_9k":1,
    "qs:photos_9r":1,
    "qs:photos_all":1,
    "qs:photos_sr":0,
    "qs:placetype":"Town",
    "qs:pop_sr":"7",
    "wd:wordcount":1826,
    "wof:name":"Shrigonda",
    "wof:placetype":"locality",
    "wof:population":28208
},
  "geometry": {"coordinates":[74.69895,18.61527],"type":"Point"}
}