{
  "type": "Feature",
  "properties": {
    "gn:admin1_code":"24.0",
    "gn:admin2_code":"123.0",
    "gn:asciiname":"Umarwas",
    "gn:country_code":"IN",
    "gn:dem":765,
    "gn:feature_class":"P",
    "gn:feature_code":"PPL",
    "gn:name":"Umarw\u0101s",
    "gn:population":0,
    "gn:timezone":"Asia/Kolkata",
    "iso:country":"IN",
    "name:tat_x_preferred":[
        "\u0423\u043c\u0430\u0440\u0432\u0430\u0441"
    ],
    "wof:name":"Umarwas",
    "wof:placetype":"locality"
},
  "geometry": {"coordinates":[73.71673,25.34156],"type":"Point"}
}