{
  "type": "Feature",
  "properties": {
    "iso:country":"IN",
    "ks:ks_name":"Kattehole",
    "ks:ks_pop":107,
    "ks:ks_type":"VILLAGE",
    "name:eng_x_preferred":[
        "Kattehole"
    ],
    "wof:name":"Kattehole",
    "wof:placetype":"locality",
    "wof:population":107
},
  "geometry": {"coordinates":[76.515716,13.872131],"type":"Point"}
}