{
  "type": "Feature",
  "properties": {
    "gn:admin1_code":"12.0",
    "gn:admin2_code":"005",
    "gn:asciiname":"Salamabad",
    "gn:country_code":"IN",
    "gn:dem":1710,
    "gn:feature_class":"P",
    "gn:feature_code":"PPL",
    "gn:name":"Sal\u0101m\u0101b\u0101d",
    "gn:population":0,
    "gn:timezone":"Asia/Kolkata",
    "iso:country":"IN",
    "name:und_x_variant":[
        "Sal\u0101m\u0101b\u0101d",
        "Isl\u0101m\u0101b\u0101d"
    ],
    "wof:name":"Salamabad",
    "wof:placetype":"locality"
},
  "geometry": {"coordinates":[74.18248,33.80915],"type":"Point"}
}