{
  "type": "Feature",
  "properties": {
    "iso:country":"IN",
    "ks:ks_name":"Vikrampur",
    "ks:ks_pop":0,
    "ks:ks_type":"VILLAGE",
    "name:eng_x_preferred":[
        "Vikrampur"
    ],
    "wof:name":"Vikrampur",
    "wof:placetype":"locality",
    "wof:population":0
},
  "geometry": {"coordinates":[77.210756,23.652874],"type":"Point"}
}