{
  "type": "Feature",
  "properties": {
    "iso:country":"IN",
    "ks:ks_name":"Shekhpuro",
    "ks:ks_pop":325,
    "ks:ks_type":"VILLAGE",
    "ks:ks_uagg_main":0,
    "name:eng_x_preferred":[
        "Shekhpuro"
    ],
    "wof:name":"Shekhpuro",
    "wof:placetype":"neighbourhood",
    "wof:population":325
},
  "geometry": {"coordinates":[82.389764,26.743774],"type":"Point"}
}