{
  "type": "Feature",
  "properties": {
    "gn:admin1_code":"36",
    "gn:admin2_code":"199.0",
    "gn:asciiname":"Sabri",
    "gn:country_code":"IN",
    "gn:dem":90,
    "gn:feature_class":"P",
    "gn:feature_code":"PPL",
    "gn:name":"Sabri",
    "gn:population":0,
    "gn:timezone":"Asia/Kolkata",
    "iso:country":"IN",
    "ks:ks_name":"Sabri",
    "ks:ks_type":"VILLAGE",
    "ks:ks_uagg_main":0,
    "name:deu_x_preferred":[
        "Sabri"
    ],
    "name:fra_x_preferred":[
        "Sabri"
    ],
    "name:por_x_preferred":[
        "Sabri"
    ],
    "name:rus_x_preferred":[
        "\u0421\u0430\u0431\u0440\u0438"
    ],
    "wof:name":"Sabri",
    "wof:placetype":"neighbourhood"
},
  "geometry": {"coordinates":[82.55978,25.14128],"type":"Point"}
}