{
  "type": "Feature",
  "properties": {
    "iso:country":"IN",
    "ks:ks_name":"Gajron",
    "ks:ks_pop":207,
    "ks:ks_type":"VILLAGE",
    "name:eng_x_preferred":[
        "Gajron"
    ],
    "wof:name":"Gajron",
    "wof:placetype":"locality",
    "wof:population":207
},
  "geometry": {"coordinates":[76.81576800000001,25.042211],"type":"Point"}
}