{
  "type": "Feature",
  "properties": {
    "iso:country":"IN",
    "ks:ks_name":"Bounsiapali",
    "ks:ks_pop":3004,
    "ks:ks_type":"HABITATION",
    "name:eng_x_preferred":[
        "Bounsiapali"
    ],
    "wof:name":"Bounsiapali",
    "wof:placetype":"locality",
    "wof:population":3004
},
  "geometry": {"coordinates":[84.67522599999999,19.35899],"type":"Point"}
}