{
  "type": "Feature",
  "properties": {
    "gn:admin1_code":"35",
    "gn:admin2_code":"452.0",
    "gn:asciiname":"Padaria",
    "gn:country_code":"IN",
    "gn:dem":369,
    "gn:feature_class":"P",
    "gn:feature_code":"PPL",
    "gn:name":"Padaria",
    "gn:population":0,
    "gn:timezone":"Asia/Kolkata",
    "iso:country":"IN",
    "ks:ks_name":"Padariya",
    "ks:ks_pop":473,
    "ks:ks_type":"VILLAGE",
    "ks:ks_uagg_main":0,
    "name:eng_x_preferred":[
        "Padariya"
    ],
    "wof:name":"Padariya",
    "wof:placetype":"neighbourhood",
    "wof:population":473
},
  "geometry": {"coordinates":[79.48001600000001,23.082073],"type":"Point"}
}