{
  "type": "Feature",
  "properties": {
    "iso:country":"IN",
    "ks:ks_name":"Chakmatmur",
    "ks:ks_pop":143,
    "ks:ks_type":"HABITATION",
    "name:eng_x_preferred":[
        "Chakmatmur"
    ],
    "wof:name":"Chakmatmur",
    "wof:placetype":"locality",
    "wof:population":143
},
  "geometry": {"coordinates":[75.575766,22.218104],"type":"Point"}
}