{
  "type": "Feature",
  "properties": {
    "gn:admin1_code":"36",
    "gn:admin2_code":"147.0",
    "gn:asciiname":"Baltigarh",
    "gn:country_code":"IN",
    "gn:dem":165,
    "gn:feature_class":"P",
    "gn:feature_code":"PPL",
    "gn:name":"Baltigarh",
    "gn:population":0,
    "gn:timezone":"Asia/Kolkata",
    "iso:country":"IN",
    "name:und_x_variant":[
        "Raghaul"
    ],
    "wof:name":"Baltigarh",
    "wof:placetype":"locality"
},
  "geometry": {"coordinates":[78.47856999999998,27.14378],"type":"Point"}
}