{
  "type": "Feature",
  "properties": {
    "iso:country":"IN",
    "ks:ks_alt_nam":"Koamali pudhur",
    "ks:ks_name":"Koamali Pudhur",
    "ks:ks_pop":122,
    "ks:ks_type":"HABITATION",
    "ks:ks_uagg_main":0,
    "name:eng_x_preferred":[
        "Koamali Pudhur"
    ],
    "wof:name":"Koamali Pudhur",
    "wof:placetype":"neighbourhood",
    "wof:population":122
},
  "geometry": {"coordinates":[77.447557,10.499502],"type":"Point"}
}