{
  "type": "Feature",
  "properties": {
    "gn:admin1_code":"35.0",
    "gn:admin2_code":"454.0",
    "gn:asciiname":"Dilwara",
    "gn:country_code":"IN",
    "gn:dem":606,
    "gn:feature_class":"P",
    "gn:feature_code":"PPL",
    "gn:name":"Dilw\u0101ra",
    "gn:population":0,
    "gn:timezone":"Asia/Kolkata",
    "iso:country":"IN",
    "ks:ks_alt_nam":"Dilw\u0101ra",
    "ks:ks_name":"Dilwara",
    "ks:ks_pop":233,
    "ks:ks_type":"VILLAGE",
    "name:eng_x_preferred":[
        "Dilwara"
    ],
    "name:eng_x_variant":[
        "Dilw\u0101ra"
    ],
    "wof:name":"Dilwara",
    "wof:placetype":"locality",
    "wof:population":233
},
  "geometry": {"coordinates":[80.638243,22.441793],"type":"Point"}
}