{
  "type": "Feature",
  "properties": {
    "iso:country":"IN",
    "ks:ks_name":"Jadopur Nankar",
    "ks:ks_pop":984,
    "ks:ks_type":"VILLAGE",
    "ks:ks_uagg_main":0,
    "name:eng_x_preferred":[
        "Jadopur Nankar"
    ],
    "wof:name":"Jadopur Nankar",
    "wof:placetype":"neighbourhood",
    "wof:population":984
},
  "geometry": {"coordinates":[85.19150500000001,26.702565],"type":"Point"}
}