{
  "type": "Feature",
  "properties": {
    "iso:country":"IN",
    "ks:ks_alt_nam":"25 RJD",
    "ks:ks_name":"25 Rjd",
    "ks:ks_pop":141,
    "ks:ks_type":"HABITATION",
    "name:eng_x_preferred":[
        "25 Rjd"
    ],
    "wof:name":"25 Rjd",
    "wof:placetype":"locality",
    "wof:population":141
},
  "geometry": {"coordinates":[72.963132,28.776409],"type":"Point"}
}