{
  "type": "Feature",
  "properties": {
    "gn:admin1_code":"13.0",
    "gn:admin2_code":"593.0",
    "gn:asciiname":"Perengod",
    "gn:country_code":"IN",
    "gn:dem":89,
    "gn:feature_class":"P",
    "gn:feature_code":"PPL",
    "gn:name":"Per\u0113ng\u014dd",
    "gn:population":0,
    "gn:timezone":"Asia/Kolkata",
    "iso:country":"IN",
    "ks:ks_name":"Peringode",
    "ks:ks_pop":1903,
    "ks:ks_type":"HABITATION",
    "ks:ks_uagg_main":0,
    "name:eng_x_preferred":[
        "Peringode"
    ],
    "wof:name":"Peringode",
    "wof:placetype":"neighbourhood",
    "wof:population":1903
},
  "geometry": {"coordinates":[76.476198,10.867104],"type":"Point"}
}