{
  "type": "Feature",
  "properties": {
    "gn:admin1_code":"19.0",
    "gn:admin2_code":"574.0",
    "gn:asciiname":"Yarekoppal",
    "gn:country_code":"IN",
    "gn:dem":856,
    "gn:feature_class":"P",
    "gn:feature_code":"PPL",
    "gn:name":"Yarekoppal",
    "gn:population":0,
    "gn:timezone":"Asia/Kolkata",
    "iso:country":"IN",
    "ks:ks_name":"Yarekoppalu",
    "ks:ks_pop":84,
    "ks:ks_type":"HABITATION",
    "name:eng_x_preferred":[
        "Yarekoppalu"
    ],
    "name:eng_x_variant":[
        "Yarekoppal"
    ],
    "wof:name":"Yarekoppalu",
    "wof:placetype":"locality",
    "wof:population":84
},
  "geometry": {"coordinates":[76.48662299999999,12.800367],"type":"Point"}
}