{
  "type": "Feature",
  "properties": {
    "gn:admin1_code":"35",
    "gn:admin2_code":"427.0",
    "gn:asciiname":"Khand",
    "gn:country_code":"IN",
    "gn:dem":497,
    "gn:feature_class":"P",
    "gn:feature_code":"PPL",
    "gn:name":"Khand",
    "gn:population":0,
    "gn:timezone":"Asia/Kolkata",
    "iso:country":"IN",
    "name:fra_x_preferred":[
        "Khand"
    ],
    "name:nld_x_preferred":[
        "Khand"
    ],
    "wof:name":"Khand",
    "wof:placetype":"locality"
},
  "geometry": {"coordinates":[78.90716,23.75117],"type":"Point"}
}