{
  "type": "Feature",
  "properties": {
    "gn:admin1_code":"34.0",
    "gn:admin2_code":"203.0",
    "gn:asciiname":"Barharwa",
    "gn:country_code":"IN",
    "gn:dem":80,
    "gn:feature_class":"P",
    "gn:feature_code":"PPL",
    "gn:name":"Barharwa",
    "gn:population":0,
    "gn:timezone":"Asia/Kolkata",
    "iso:country":"IN",
    "name:bih_x_preferred":[
        "\u092c\u0930\u0939\u0930\u0935\u093e"
    ],
    "name:ceb_x_preferred":[
        "Barharw\u0101"
    ],
    "name:swe_x_preferred":[
        "Barharw\u0101"
    ],
    "wof:name":"Barharwa",
    "wof:placetype":"neighbourhood"
},
  "geometry": {"coordinates":[84.45634,26.85377],"type":"Point"}
}