{
  "type": "Feature",
  "properties": {
    "iso:country":"IN",
    "ks:ks_name":"Amapada",
    "ks:ks_pop":132,
    "ks:ks_type":"HABITATION",
    "name:eng_x_preferred":[
        "Amapada"
    ],
    "wof:name":"Amapada",
    "wof:placetype":"locality",
    "wof:population":132
},
  "geometry": {"coordinates":[84.173428,22.291139],"type":"Point"}
}