{
  "type": "Feature",
  "properties": {
    "gn:admin1_code":"36.0",
    "gn:admin2_code":"189.0",
    "gn:asciiname":"Phulwaria Mashriq",
    "gn:country_code":"IN",
    "gn:dem":89,
    "gn:feature_class":"P",
    "gn:feature_code":"PPL",
    "gn:name":"Phulwaria Mashriq",
    "gn:population":0,
    "gn:timezone":"Asia/Kolkata",
    "iso:country":"IN",
    "ks:ks_name":"Phulwaria Masriq",
    "ks:ks_pop":874,
    "ks:ks_type":"VILLAGE",
    "ks:ks_uagg_main":0,
    "name:eng_x_preferred":[
        "Phulwaria Masriq"
    ],
    "wof:name":"Phulwaria Masriq",
    "wof:placetype":"neighbourhood",
    "wof:population":874
},
  "geometry": {"coordinates":[83.77279900000001,26.959117],"type":"Point"}
}