{
  "type": "Feature",
  "properties": {
    "iso:country":"IN",
    "ks:ks_name":"Sikari Deeh",
    "ks:ks_pop":126,
    "ks:ks_type":"HABITATION",
    "name:eng_x_preferred":[
        "Sikari Deeh"
    ],
    "wof:name":"Sikari Deeh",
    "wof:placetype":"locality",
    "wof:population":126
},
  "geometry": {"coordinates":[82.879474,27.31738],"type":"Point"}
}