{
  "type": "Feature",
  "properties": {
    "iso:country":"IN",
    "ks:ks_name":"Lachhmipur",
    "ks:ks_type":"VILLAGE",
    "ks:ks_uagg_main":0,
    "name:eng_x_preferred":[
        "Lachhmipur"
    ],
    "wof:name":"Lachhmipur",
    "wof:placetype":"neighbourhood"
},
  "geometry": {"coordinates":[85.768742,24.888307],"type":"Point"}
}