{
  "type": "Feature",
  "properties": {
    "gn:country":"IN",
    "gn:fcode":"PPL",
    "gn:population":17661,
    "iso:country":"IN",
    "name:ben_x_preferred":[
        "\u0997\u0999\u09cd\u0997\u09be\u09aa\u09c1\u09b0"
    ],
    "name:bpy_x_preferred":[
        "\u0997\u0999\u09cd\u0997\u09be\u09aa\u09c1\u09b0"
    ],
    "name:cat_x_preferred":[
        "Gangapur"
    ],
    "name:ceb_x_preferred":[
        "Gang\u0101pur"
    ],
    "name:eng_x_preferred":[
        "Gangapur"
    ],
    "name:fra_x_preferred":[
        "Gangapur"
    ],
    "name:hin_x_preferred":[
        "\u0917\u0902\u0917\u093e\u092a\u0941\u0930"
    ],
    "name:ita_x_preferred":[
        "Gangapur"
    ],
    "name:msa_x_preferred":[
        "Gangapur"
    ],
    "name:nld_x_preferred":[
        "Gangapur"
    ],
    "name:swe_x_preferred":[
        "Gang\u0101pur"
    ],
    "qs:name":"Gangapur",
    "qs:name_adm0":"India",
    "qs:name_adm1":"Rajasthan",
    "qs:photos_9r":0,
    "qs:photos_sr":0,
    "qs:placetype":"Town",
    "qs:pop_sr":"6",
    "wd:wordcount":49,
    "wof:name":"Gangapur",
    "wof:placetype":"locality",
    "wof:population":17661
},
  "geometry": {"coordinates":[74.26027999999999,25.21954],"type":"Point"}
}