{
  "type": "Feature",
  "properties": {
    "iso:country":"IN",
    "ks:ks_name":"Golaperalga",
    "ks:ks_pop":627,
    "ks:ks_type":"VILLAGE",
    "name:eng_x_preferred":[
        "Golaperalga"
    ],
    "wof:name":"Golaperalga",
    "wof:placetype":"locality",
    "wof:population":627
},
  "geometry": {"coordinates":[90.026954,25.983166],"type":"Point"}
}