{
  "type": "Feature",
  "properties": {
    "gn:admin1_code":"24.0",
    "gn:admin2_code":"102",
    "gn:asciiname":"Pithisar",
    "gn:country_code":"IN",
    "gn:dem":283,
    "gn:feature_class":"P",
    "gn:feature_code":"PPL",
    "gn:name":"Pith\u012bsar",
    "gn:population":0,
    "gn:timezone":"Asia/Kolkata",
    "iso:country":"IN",
    "name:und_x_variant":[
        "Pith\u012bsar",
        "Pithisar"
    ],
    "wof:name":"Pithisar",
    "wof:placetype":"neighbourhood"
},
  "geometry": {"coordinates":[74.81269,28.38159],"type":"Point"}
}