{
  "type": "Feature",
  "properties": {
    "iso:country":"IN",
    "ks:ks_name":"Ramdevpura",
    "ks:ks_pop":808,
    "ks:ks_type":"VILLAGE",
    "name:eng_x_preferred":[
        "Ramdevpura"
    ],
    "wof:name":"Ramdevpura",
    "wof:placetype":"locality",
    "wof:population":808
},
  "geometry": {"coordinates":[73.001811,27.183939],"type":"Point"}
}