{
  "type": "Feature",
  "properties": {
    "gn:admin1_code":"19.0",
    "gn:admin2_code":"575",
    "gn:asciiname":"Kateel",
    "gn:country_code":"IN",
    "gn:dem":26,
    "gn:feature_class":"P",
    "gn:feature_code":"PPLR",
    "gn:name":"Kateel",
    "gn:population":0,
    "gn:timezone":"Asia/Kolkata",
    "iso:country":"IN",
    "wof:name":"Kateel",
    "wof:placetype":"locality"
},
  "geometry": {"coordinates":[74.86946999999998,13.04725],"type":"Point"}
}