{
  "type": "Feature",
  "properties": {
    "iso:country":"IN",
    "ks:ks_name":"Tapariyan",
    "ks:ks_pop":125,
    "ks:ks_type":"HABITATION",
    "name:eng_x_preferred":[
        "Tapariyan"
    ],
    "wof:name":"Tapariyan",
    "wof:placetype":"locality",
    "wof:population":125
},
  "geometry": {"coordinates":[79.10722,25.352022],"type":"Point"}
}