{
  "type": "Feature",
  "properties": {
    "gn:admin1_code":"34.0",
    "gn:admin2_code":"218.0",
    "gn:asciiname":"Dalai",
    "gn:country_code":"IN",
    "gn:dem":70,
    "gn:feature_class":"P",
    "gn:feature_code":"PPL",
    "gn:name":"Dalai",
    "gn:population":0,
    "gn:timezone":"Asia/Kolkata",
    "iso:country":"IN",
    "name:ceb_x_preferred":[
        "Dalai"
    ],
    "name:deu_x_preferred":[
        "Dalai"
    ],
    "name:fra_x_preferred":[
        "Dala\u00ef"
    ],
    "name:mlg_x_preferred":[
        "Dalai"
    ],
    "name:swe_x_preferred":[
        "Dalai"
    ],
    "wof:name":"Dalai",
    "wof:placetype":"neighbourhood"
},
  "geometry": {"coordinates":[84.5611,26.26949],"type":"Point"}
}