{
  "type": "Feature",
  "properties": {
    "gn:admin1_code":"34.0",
    "gn:admin2_code":"216.0",
    "gn:asciiname":"Parsauni Patti Gulab",
    "gn:country_code":"IN",
    "gn:dem":65,
    "gn:feature_class":"P",
    "gn:feature_code":"PPL",
    "gn:name":"Parsauni Patti Gul\u0101b",
    "gn:population":0,
    "gn:timezone":"Asia/Kolkata",
    "iso:country":"IN",
    "ks:ks_name":"Parsauni Patti Gulab",
    "ks:ks_pop":2156,
    "ks:ks_type":"VILLAGE",
    "ks:ks_uagg_main":0,
    "name:eng_x_preferred":[
        "Parsauni Patti Gulab"
    ],
    "wof:name":"Parsauni Patti Gulab",
    "wof:placetype":"neighbourhood",
    "wof:population":2156
},
  "geometry": {"coordinates":[84.916635,26.320576],"type":"Point"}
}