{
  "type": "Feature",
  "properties": {
    "iso:country":"IN",
    "ks:ks_name":"Budhabhuin",
    "ks:ks_pop":116,
    "ks:ks_type":"VILLAGE",
    "name:eng_x_preferred":[
        "Budhabhuin"
    ],
    "wof:name":"Budhabhuin",
    "wof:placetype":"locality",
    "wof:population":116
},
  "geometry": {"coordinates":[85.12576900000001,21.597483],"type":"Point"}
}