{
  "type": "Feature",
  "properties": {
    "gn:admin1_code":"35.0",
    "gn:admin2_code":"427.0",
    "gn:asciiname":"Khairana",
    "gn:country_code":"IN",
    "gn:dem":426,
    "gn:feature_class":"P",
    "gn:feature_code":"PPL",
    "gn:name":"Khair\u0101na",
    "gn:population":0,
    "gn:timezone":"Asia/Kolkata",
    "iso:country":"IN",
    "wof:name":"Khairana",
    "wof:placetype":"locality"
},
  "geometry": {"coordinates":[78.98616,23.56862000000001],"type":"Point"}
}