{
  "type": "Feature",
  "properties": {
    "gn:admin1_code":"36",
    "gn:admin2_code":"178.0",
    "gn:asciiname":"Gobardhanpur Nurullahpur",
    "gn:country_code":"IN",
    "gn:dem":87,
    "gn:feature_class":"P",
    "gn:feature_code":"PPL",
    "gn:name":"Gobardhanpur Nurullahpur",
    "gn:population":0,
    "gn:timezone":"Asia/Kolkata",
    "iso:country":"IN",
    "wof:name":"Gobardhanpur Nurullahpur",
    "wof:placetype":"neighbourhood"
},
  "geometry": {"coordinates":[82.9431,26.49075],"type":"Point"}
}