{
  "type": "Feature",
  "properties": {
    "iso:country":"IN",
    "ks:ks_name":"Honnemaradu",
    "ks:ks_pop":68,
    "ks:ks_type":"VILLAGE",
    "name:eng_x_preferred":[
        "Honnemaradu"
    ],
    "wof:name":"Honnemaradu",
    "wof:placetype":"locality",
    "wof:population":68
},
  "geometry": {"coordinates":[74.86852,14.185226],"type":"Point"}
}