{
  "type": "Feature",
  "properties": {
    "iso:country":"IN",
    "ks:ks_alt_nam":"NAWLE WASTI",
    "ks:ks_name":"Nawle Wasti",
    "ks:ks_pop":174,
    "ks:ks_type":"HABITATION",
    "name:eng_x_preferred":[
        "Nawle Wasti"
    ],
    "wof:name":"Nawle Wasti",
    "wof:placetype":"locality",
    "wof:population":174
},
  "geometry": {"coordinates":[74.74386199999999,19.534369],"type":"Point"}
}