{
  "type": "Feature",
  "properties": {
    "gn:admin1_code":"19.0",
    "gn:admin2_code":"563.0",
    "gn:asciiname":"Kalche",
    "gn:country_code":"IN",
    "gn:dem":261,
    "gn:feature_class":"P",
    "gn:feature_code":"PPL",
    "gn:name":"Kalche",
    "gn:population":0,
    "gn:timezone":"Asia/Kolkata",
    "iso:country":"IN",
    "ks:ks_name":"Kalache",
    "ks:ks_pop":490,
    "ks:ks_type":"VILLAGE",
    "name:eng_x_preferred":[
        "Kalache"
    ],
    "name:eng_x_variant":[
        "Kalche"
    ],
    "wof:name":"Kalache",
    "wof:placetype":"locality",
    "wof:population":490
},
  "geometry": {"coordinates":[74.56211399999999,14.918407],"type":"Point"}
}