{
  "type": "Feature",
  "properties": {
    "gn:admin1_code":"24.0",
    "gn:admin2_code":"127.0",
    "gn:asciiname":"Katun",
    "gn:country_code":"IN",
    "gn:dem":255,
    "gn:feature_class":"P",
    "gn:feature_code":"PPL",
    "gn:name":"K\u0101t\u016bn",
    "gn:population":0,
    "gn:timezone":"Asia/Kolkata",
    "iso:country":"IN",
    "name:bos_x_preferred":[
        "Katun"
    ],
    "name:bul_x_preferred":[
        "\u041a\u0430\u0442\u0443\u043d"
    ],
    "name:deu_x_preferred":[
        "Katun"
    ],
    "name:fra_x_preferred":[
        "Katun"
    ],
    "name:hrv_x_preferred":[
        "Katun"
    ],
    "name:hun_x_preferred":[
        "Katun"
    ],
    "name:hye_x_preferred":[
        "\u053f\u0561\u057f\u0578\u0582\u0576"
    ],
    "name:ita_x_preferred":[
        "Katun"
    ],
    "name:nld_x_preferred":[
        "Katun"
    ],
    "name:rus_x_preferred":[
        "\u041a\u0430\u0442\u0443\u043d\u044c"
    ],
    "name:sco_x_preferred":[
        "Katun"
    ],
    "name:slv_x_preferred":[
        "Katun"
    ],
    "name:srp_x_preferred":[
        "\u041a\u0430\u0442\u0443\u043d"
    ],
    "wof:name":"Katun",
    "wof:placetype":"locality"
},
  "geometry": {"coordinates":[76.16986,25.0531],"type":"Point"}
}