{
  "type": "Feature",
  "properties": {
    "iso:country":"IN",
    "ks:ks_name":"Dhanbad",
    "ks:ks_pop":439,
    "ks:ks_type":"VILLAGE",
    "name:eng_x_preferred":[
        "Dhanbad"
    ],
    "wof:name":"Dhanbad",
    "wof:placetype":"locality",
    "wof:population":439
},
  "geometry": {"coordinates":[87.379015,24.236361],"type":"Point"}
}