{
  "type": "Feature",
  "properties": {
    "iso:country":"IN",
    "ks:ks_name":"Gharpathar",
    "ks:ks_pop":1301,
    "ks:ks_type":"VILLAGE",
    "name:eng_x_preferred":[
        "Gharpathar"
    ],
    "wof:name":"Gharpathar",
    "wof:placetype":"locality",
    "wof:population":1301
},
  "geometry": {"coordinates":[86.985991,23.113443],"type":"Point"}
}