{
  "type": "Feature",
  "properties": {
    "gn:admin1_code":"19.0",
    "gn:admin2_code":"570.0",
    "gn:asciiname":"Kademane",
    "gn:country_code":"IN",
    "gn:dem":653,
    "gn:feature_class":"P",
    "gn:feature_code":"PPL",
    "gn:name":"Kademane",
    "gn:population":0,
    "gn:timezone":"Asia/Kolkata",
    "iso:country":"IN",
    "ks:ks_name":"Kademane",
    "ks:ks_pop":21,
    "ks:ks_type":"HABITATION",
    "name:eng_x_preferred":[
        "Kademane"
    ],
    "wof:name":"Kademane",
    "wof:placetype":"locality",
    "wof:population":21
},
  "geometry": {"coordinates":[75.262163,13.442509],"type":"Point"}
}