{
  "type": "Feature",
  "properties": {
    "gn:admin1_code":"34.0",
    "gn:admin2_code":"220.0",
    "gn:asciiname":"Sahdai Buzurg",
    "gn:country_code":"IN",
    "gn:dem":52,
    "gn:feature_class":"P",
    "gn:feature_code":"PPL",
    "gn:name":"Sahdai Buzurg",
    "gn:population":0,
    "gn:timezone":"Asia/Kolkata",
    "iso:country":"IN",
    "ks:ks_name":"Sahdai Buzurg",
    "ks:ks_pop":5169,
    "ks:ks_type":"VILLAGE",
    "name:eng_x_preferred":[
        "Sahdai Buzurg"
    ],
    "wof:name":"Sahdai Buzurg",
    "wof:placetype":"locality",
    "wof:population":5169
},
  "geometry": {"coordinates":[85.459693,25.662214],"type":"Point"}
}