{
  "type": "Feature",
  "properties": {
    "gn:country":"IN",
    "gn:fcode":"PPL",
    "gn:pop":27874,
    "iso:country":"IN",
    "name:bpy_x_preferred":[
        "\u0987\u09af\u09bc\u09c7\u09b0\u09be\u0997\u09c1\u09a8\u09a4\u09b2\u09be"
    ],
    "name:bul_x_preferred":[
        "\u0415\u0440\u0430\u0433\u0443\u043d\u0442\u043b\u0430"
    ],
    "name:chi_x_preferred":[
        "\u8036\u5c14\u62c9\u8d21\u7279\u62c9"
    ],
    "name:dut_x_preferred":[
        "Yerraguntla"
    ],
    "name:eng_x_preferred":[
        "Yerraguntla"
    ],
    "name:fre_x_preferred":[
        "Yerraguntla"
    ],
    "name:ita_x_preferred":[
        "Yerraguntla"
    ],
    "name:may_x_preferred":[
        "Yerraguntla"
    ],
    "name:nan_x_preferred":[
        "Yerraguntla"
    ],
    "name:new_x_preferred":[
        "\u092f\u0947\u0930\u094d\u0930\u093e\u0917\u0941\u0928\u094d\u0924\u094d\u0932"
    ],
    "name:pam_x_preferred":[
        "Yerraguntla"
    ],
    "name:por_x_preferred":[
        "Yerraguntla"
    ],
    "name:swe_x_preferred":[
        "Erraguntla"
    ],
    "name:tel_x_preferred":[
        "\u0c2f\u0c30\u0c4d\u0c30\u0c17\u0c41\u0c02\u0c1f\u0c4d\u0c32"
    ],
    "name:unk_x_variant":[
        "Erraguntla"
    ],
    "name:urd_x_preferred":[
        "\u06cc\u0631\u0631\u0627\u06af\u0646\u062a\u0644\u0627"
    ],
    "name:vie_x_preferred":[
        "Yerraguntla"
    ],
    "qs:name":"Yerraguntla",
    "qs:name_adm0":"India",
    "qs:name_adm1":"Andhra Pradesh",
    "qs:photos_9r":0,
    "qs:photos_sr":0,
    "qs:placetype":"Town",
    "qs:pop_sr":"7",
    "wd:wordcount":357,
    "wof:name":"Yerraguntla",
    "wof:placetype":"locality",
    "wof:population":27874
},
  "geometry": {"coordinates":[78.53973999999999,14.63853],"type":"Point"}
}