{
  "type": "Feature",
  "properties": {
    "iso:country":"IN",
    "ks:ks_name":"Sadulpura",
    "ks:ks_pop":990,
    "ks:ks_type":"HABITATION",
    "name:eng_x_preferred":[
        "Sadulpura"
    ],
    "wof:name":"Sadulpura",
    "wof:placetype":"locality",
    "wof:population":990
},
  "geometry": {"coordinates":[72.17289700000001,26.785892],"type":"Point"}
}