{
  "type": "Feature",
  "properties": {
    "iso:country":"IN",
    "ks:ks_name":"Bentapada",
    "ks:ks_pop":389,
    "ks:ks_type":"VILLAGE",
    "name:eng_x_preferred":[
        "Bentapada"
    ],
    "wof:name":"Bentapada",
    "wof:placetype":"locality",
    "wof:population":389
},
  "geometry": {"coordinates":[84.96275,20.464327],"type":"Point"}
}