{
  "type": "Feature",
  "properties": {
    "iso:country":"IN",
    "ks:ks_name":"Zadani",
    "ks:ks_pop":12,
    "ks:ks_type":"VILLAGE",
    "name:eng_x_preferred":[
        "Zadani"
    ],
    "wof:name":"Zadani",
    "wof:placetype":"locality",
    "wof:population":12
},
  "geometry": {"coordinates":[73.622119,17.79596],"type":"Point"}
}