{
  "type": "Feature",
  "properties": {
    "iso:country":"IN",
    "ks:ks_name":"Chinthavalasa",
    "ks:ks_pop":40,
    "ks:ks_type":"HABITATION",
    "name:eng_x_preferred":[
        "Chinthavalasa"
    ],
    "wof:name":"Chinthavalasa",
    "wof:placetype":"locality",
    "wof:population":40
},
  "geometry": {"coordinates":[81.855829,17.740815],"type":"Point"}
}