{
  "type": "Feature",
  "properties": {
    "iso:country":"IN",
    "ks:ks_name":"Ghurhu Chak",
    "ks:ks_type":"VILLAGE",
    "name:eng_x_preferred":[
        "Ghurhu Chak"
    ],
    "wof:name":"Ghurhu Chak",
    "wof:placetype":"locality"
},
  "geometry": {"coordinates":[83.743381,25.00012],"type":"Point"}
}