{
  "type": "Feature",
  "properties": {
    "gn:admin1_code":"2.0",
    "gn:admin2_code":"542.0",
    "gn:asciiname":"Kottakarra",
    "gn:country_code":"IN",
    "gn:dem":126,
    "gn:feature_class":"P",
    "gn:feature_code":"PPL",
    "gn:name":"Kottakarra",
    "gn:population":0,
    "gn:timezone":"Asia/Kolkata",
    "iso:country":"IN",
    "wof:name":"Kottakarra",
    "wof:placetype":"locality"
},
  "geometry": {"coordinates":[83.47763,18.37889],"type":"Point"}
}