{
  "type": "Feature",
  "properties": {
    "iso:country":"IN",
    "ks:ks_name":"Parasia Dewar",
    "ks:ks_pop":4811,
    "ks:ks_type":"VILLAGE",
    "name:eng_x_preferred":[
        "Parasia Dewar"
    ],
    "wof:name":"Parasia Dewar",
    "wof:placetype":"locality",
    "wof:population":4811
},
  "geometry": {"coordinates":[83.701008,26.261809],"type":"Point"}
}