{
  "type": "Feature",
  "properties": {
    "iso:country":"IN",
    "ks:ks_name":"Kauwadanr",
    "ks:ks_pop":829,
    "ks:ks_type":"VILLAGE",
    "name:eng_x_preferred":[
        "Kauwadanr"
    ],
    "wof:name":"Kauwadanr",
    "wof:placetype":"locality",
    "wof:population":829
},
  "geometry": {"coordinates":[84.508002,23.543174],"type":"Point"}
}