{
  "type": "Feature",
  "properties": {
    "iso:country":"IN",
    "ks:ks_name":"Sahapur",
    "ks:ks_pop":7581,
    "ks:ks_type":"VILLAGE",
    "ks:ks_uagg_main":0,
    "name:eng_x_preferred":[
        "Sahapur"
    ],
    "wof:name":"Sahapur",
    "wof:placetype":"neighbourhood",
    "wof:population":7581
},
  "geometry": {"coordinates":[88.154793,24.988078],"type":"Point"}
}