{
  "type": "Feature",
  "properties": {
    "gn:admin1_code":"21.0",
    "gn:admin2_code":"381.0",
    "gn:asciiname":"Fulara",
    "gn:country_code":"IN",
    "gn:dem":15,
    "gn:feature_class":"P",
    "gn:feature_code":"PPL",
    "gn:name":"Fulara",
    "gn:population":0,
    "gn:timezone":"Asia/Kolkata",
    "iso:country":"IN",
    "wof:name":"Fulara",
    "wof:placetype":"locality"
},
  "geometry": {"coordinates":[86.12535,20.37661],"type":"Point"}
}