{
  "type": "Feature",
  "properties": {
    "iso:country":"IN",
    "ks:ks_alt_nam":"JHC Vaddarse",
    "ks:ks_name":"Jhc Vaddarse",
    "ks:ks_pop":132,
    "ks:ks_type":"HABITATION",
    "name:eng_x_preferred":[
        "Jhc Vaddarse"
    ],
    "wof:name":"Jhc Vaddarse",
    "wof:placetype":"locality",
    "wof:population":132
},
  "geometry": {"coordinates":[74.743335,13.510209],"type":"Point"}
}