{
  "type": "Feature",
  "properties": {
    "iso:country":"IN",
    "ks:ks_alt_nam":"Muppidathiamman Kovil street",
    "ks:ks_name":"Muppidathiamman Kovil Street",
    "ks:ks_pop":123,
    "ks:ks_type":"HABITATION",
    "name:eng_x_preferred":[
        "Muppidathiamman Kovil Street"
    ],
    "wof:name":"Muppidathiamman Kovil Street",
    "wof:placetype":"locality",
    "wof:population":123
},
  "geometry": {"coordinates":[77.587903,8.710491],"type":"Point"}
}