{
  "type": "Feature",
  "properties": {
    "iso:country":"IN",
    "ks:ks_name":"Kopenkonadi",
    "ks:ks_pop":161,
    "ks:ks_type":"HABITATION",
    "name:eng_x_preferred":[
        "Kopenkonadi"
    ],
    "wof:name":"Kopenkonadi",
    "wof:placetype":"locality",
    "wof:population":161
},
  "geometry": {"coordinates":[81.70219299999999,20.074358],"type":"Point"}
}