{
  "type": "Feature",
  "properties": {
    "iso:country":"IN",
    "ks:ks_name":"Sewaniya Parihar",
    "ks:ks_pop":635,
    "ks:ks_type":"VILLAGE",
    "name:eng_x_preferred":[
        "Sewaniya Parihar"
    ],
    "wof:name":"Sewaniya Parihar",
    "wof:placetype":"locality",
    "wof:population":635
},
  "geometry": {"coordinates":[77.333066,23.019834],"type":"Point"}
}