{
  "type": "Feature",
  "properties": {
    "iso:country":"IN",
    "ks:ks_name":"Bahupathar No1",
    "ks:ks_pop":393,
    "ks:ks_type":"HABITATION",
    "name:eng_x_preferred":[
        "Bahupathar No1"
    ],
    "wof:name":"Bahupathar No1",
    "wof:placetype":"locality",
    "wof:population":393
},
  "geometry": {"coordinates":[93.84138900000001,26.914842],"type":"Point"}
}