{
  "type": "Feature",
  "properties": {
    "iso:country":"IN",
    "ks:ks_name":"Sevathankottai",
    "ks:ks_pop":475,
    "ks:ks_type":"HABITATION",
    "ks:ks_uagg_main":0,
    "name:eng_x_preferred":[
        "Sevathankottai"
    ],
    "wof:name":"Sevathankottai",
    "wof:placetype":"neighbourhood",
    "wof:population":475
},
  "geometry": {"coordinates":[78.14557499999999,12.296563],"type":"Point"}
}