{
  "type": "Feature",
  "properties": {
    "iso:country":"IN",
    "ks:ks_name":"Atharnala",
    "ks:ks_pop":1117,
    "ks:ks_type":"VILLAGE",
    "ks:ks_uagg_main":0,
    "name:eng_x_preferred":[
        "Atharnala"
    ],
    "wof:name":"Atharnala",
    "wof:placetype":"neighbourhood",
    "wof:population":1117
},
  "geometry": {"coordinates":[85.836517,19.820537],"type":"Point"}
}