{
  "type": "Feature",
  "properties": {
    "iso:country":"IN",
    "ks:ks_name":"Dhodh Fa",
    "ks:ks_pop":1034,
    "ks:ks_type":"HABITATION",
    "ks:ks_uagg_main":0,
    "name:eng_x_preferred":[
        "Dhodh Fa"
    ],
    "wof:name":"Dhodh Fa",
    "wof:placetype":"neighbourhood",
    "wof:population":1034
},
  "geometry": {"coordinates":[72.972917,20.510194],"type":"Point"}
}