{
  "type": "Feature",
  "properties": {
    "iso:country":"IN",
    "ks:ks_name":"Hegadetota",
    "ks:ks_pop":22,
    "ks:ks_type":"HABITATION",
    "name:eng_x_preferred":[
        "Hegadetota"
    ],
    "wof:name":"Hegadetota",
    "wof:placetype":"locality",
    "wof:population":22
},
  "geometry": {"coordinates":[74.694194,14.877994],"type":"Point"}
}