{
  "type": "Feature",
  "properties": {
    "iso:country":"IN",
    "ks:ks_name":"Khurimal",
    "ks:ks_pop":122,
    "ks:ks_type":"HABITATION",
    "name:eng_x_preferred":[
        "Khurimal"
    ],
    "wof:name":"Khurimal",
    "wof:placetype":"locality",
    "wof:population":122
},
  "geometry": {"coordinates":[82.23202499999999,18.146154],"type":"Point"}
}