{
  "type": "Feature",
  "properties": {
    "gn:admin1_code":"25.0",
    "gn:admin2_code":"632.0",
    "gn:asciiname":"Kummalkambe",
    "gn:country_code":"IN",
    "gn:dem":979,
    "gn:feature_class":"P",
    "gn:feature_code":"PPL",
    "gn:name":"Kummalkambe",
    "gn:population":0,
    "gn:timezone":"Asia/Kolkata",
    "iso:country":"IN",
    "wof:name":"Kummalkambe",
    "wof:placetype":"locality"
},
  "geometry": {"coordinates":[76.81076,11.29089],"type":"Point"}
}