{
  "type": "Feature",
  "properties": {
    "iso:country":"IN",
    "ks:ks_name":"Dewal Gaon",
    "ks:ks_pop":62,
    "ks:ks_type":"VILLAGE",
    "name:eng_x_preferred":[
        "Dewal Gaon"
    ],
    "wof:name":"Dewal Gaon",
    "wof:placetype":"locality",
    "wof:population":62
},
  "geometry": {"coordinates":[78.65251000000001,30.189697],"type":"Point"}
}