{
  "type": "Feature",
  "properties": {
    "gn:admin1_code":"12.0",
    "gn:admin2_code":"16.0",
    "gn:asciiname":"Kalinag",
    "gn:country_code":"IN",
    "gn:dem":2901,
    "gn:feature_class":"P",
    "gn:feature_code":"PPL",
    "gn:name":"Kalin\u0101g",
    "gn:population":0,
    "gn:timezone":"Asia/Kolkata",
    "iso:country":"IN",
    "wof:name":"Kalinag",
    "wof:placetype":"locality"
},
  "geometry": {"coordinates":[75.43871999999998,33.31089],"type":"Point"}
}