{
  "type": "Feature",
  "properties": {
    "iso:country":"IN",
    "ks:ks_name":"Dundukachar",
    "ks:ks_pop":103,
    "ks:ks_type":"HABITATION",
    "name:eng_x_preferred":[
        "Dundukachar"
    ],
    "wof:name":"Dundukachar",
    "wof:placetype":"locality",
    "wof:population":103
},
  "geometry": {"coordinates":[84.33741000000001,22.650987],"type":"Point"}
}