{
  "type": "Feature",
  "properties": {
    "iso:country":"IN",
    "ks:ks_name":"Adivarpet",
    "ks:ks_pop":110,
    "ks:ks_type":"HABITATION",
    "name:eng_x_preferred":[
        "Adivarpet"
    ],
    "wof:name":"Adivarpet",
    "wof:placetype":"locality",
    "wof:population":110
},
  "geometry": {"coordinates":[79.78681400000001,18.902786],"type":"Point"}
}