{
  "type": "Feature",
  "properties": {
    "iso:country":"IN",
    "ks:ks_name":"Gopirampura",
    "ks:ks_pop":379,
    "ks:ks_type":"VILLAGE",
    "name:eng_x_preferred":[
        "Gopirampura"
    ],
    "wof:name":"Gopirampura",
    "wof:placetype":"locality",
    "wof:population":379
},
  "geometry": {"coordinates":[75.92274399999999,26.679075],"type":"Point"}
}