{
  "type": "Feature",
  "properties": {
    "gn:admin1_code":"2.0",
    "gn:admin2_code":"553.0",
    "gn:asciiname":"Mudupulazuvvi",
    "gn:country_code":"IN",
    "gn:dem":599,
    "gn:feature_class":"P",
    "gn:feature_code":"PPL",
    "gn:name":"Mudupulazuvvi",
    "gn:population":0,
    "gn:timezone":"Asia/Kolkata",
    "iso:country":"IN",
    "wof:name":"Mudupulazuvvi",
    "wof:placetype":"locality"
},
  "geometry": {"coordinates":[78.2801,14.04733],"type":"Point"}
}