{
  "type": "Feature",
  "properties": {
    "iso:country":"IN",
    "ks:ks_name":"Saranbi",
    "ks:ks_pop":92,
    "ks:ks_type":"HABITATION",
    "name:eng_x_preferred":[
        "Saranbi"
    ],
    "wof:name":"Saranbi",
    "wof:placetype":"locality",
    "wof:population":92
},
  "geometry": {"coordinates":[83.519295,19.632517],"type":"Point"}
}