{
  "type": "Feature",
  "properties": {
    "iso:country":"IN",
    "ks:ks_name":"Hanchikadu 1",
    "ks:ks_pop":79,
    "ks:ks_type":"HABITATION",
    "name:eng_x_preferred":[
        "Hanchikadu 1"
    ],
    "wof:name":"Hanchikadu 1",
    "wof:placetype":"locality",
    "wof:population":79
},
  "geometry": {"coordinates":[75.886354,12.245546],"type":"Point"}
}