{
  "type": "Feature",
  "properties": {
    "iso:country":"IN",
    "ks:ks_name":"Ramanagar Colony",
    "ks:ks_pop":170,
    "ks:ks_type":"HABITATION",
    "name:eng_x_preferred":[
        "Ramanagar Colony"
    ],
    "wof:name":"Ramanagar Colony",
    "wof:placetype":"locality",
    "wof:population":170
},
  "geometry": {"coordinates":[82.432779,17.862796],"type":"Point"}
}