{
  "type": "Feature",
  "properties": {
    "iso:country":"IN",
    "ks:ks_name":"Belana",
    "ks:ks_pop":10,
    "ks:ks_type":"HABITATION",
    "name:eng_x_preferred":[
        "Belana"
    ],
    "wof:name":"Belana",
    "wof:placetype":"locality",
    "wof:population":10
},
  "geometry": {"coordinates":[79.059782,23.139947],"type":"Point"}
}