{
  "type": "Feature",
  "properties": {
    "iso:country":"IN",
    "ks:ks_name":"Hale Unchalli",
    "ks:ks_pop":115,
    "ks:ks_type":"HABITATION",
    "name:eng_x_preferred":[
        "Hale Unchalli"
    ],
    "wof:name":"Hale Unchalli",
    "wof:placetype":"locality",
    "wof:population":115
},
  "geometry": {"coordinates":[74.902497,14.586128],"type":"Point"}
}