{
  "type": "Feature",
  "properties": {
    "iso:country":"IN",
    "ks:ks_name":"Jajneswarpur",
    "ks:ks_pop":2075,
    "ks:ks_type":"VILLAGE",
    "ks:ks_uagg_main":0,
    "name:eng_x_preferred":[
        "Jajneswarpur"
    ],
    "wof:name":"Jajneswarpur",
    "wof:placetype":"neighbourhood",
    "wof:population":2075
},
  "geometry": {"coordinates":[88.27978,23.522998],"type":"Point"}
}