{
  "type": "Feature",
  "properties": {
    "iso:country":"IN",
    "ks:ks_name":"20 GG",
    "ks:ks_pop":726,
    "ks:ks_type":"VILLAGE",
    "ks:ks_uagg_main":0,
    "name:eng_x_preferred":[
        "20 GG"
    ],
    "wof:name":"20 GG",
    "wof:placetype":"neighbourhood",
    "wof:population":726
},
  "geometry": {"coordinates":[73.80882200000001,29.834069],"type":"Point"}
}