{
  "type": "Feature",
  "properties": {
    "iso:country":"IN",
    "ks:ks_name":"Rohila Bhandoo",
    "ks:ks_pop":29,
    "ks:ks_type":"VILLAGE",
    "name:eng_x_preferred":[
        "Rohila Bhandoo"
    ],
    "wof:name":"Rohila Bhandoo",
    "wof:placetype":"locality",
    "wof:population":29
},
  "geometry": {"coordinates":[72.866317,26.10535],"type":"Point"}
}