{
  "type": "Feature",
  "properties": {
    "iso:country":"IN",
    "ks:ks_name":"Purbbahari",
    "ks:ks_pop":678,
    "ks:ks_type":"VILLAGE",
    "name:eng_x_preferred":[
        "Purbbahari"
    ],
    "wof:name":"Purbbahari",
    "wof:placetype":"locality",
    "wof:population":678
},
  "geometry": {"coordinates":[87.688823,22.054432],"type":"Point"}
}