{
  "type": "Feature",
  "properties": {
    "gn:admin1_code":"40.0",
    "gn:admin2_code":"541",
    "gn:asciiname":"Ashwaraopet",
    "gn:country_code":"IN",
    "gn:dem":172,
    "gn:feature_class":"P",
    "gn:feature_code":"PPL",
    "gn:name":"Ashwaraopet",
    "gn:population":0,
    "gn:timezone":"Asia/Kolkata",
    "iso:country":"IN",
    "wof:name":"Ashwaraopet",
    "wof:placetype":"locality"
},
  "geometry": {"coordinates":[81.13395,17.24711],"type":"Point"}
}