{
  "type": "Feature",
  "properties": {
    "iso:country":"IN",
    "ks:ks_name":"Bhimjipura",
    "ks:ks_pop":351,
    "ks:ks_type":"HABITATION",
    "name:eng_x_preferred":[
        "Bhimjipura"
    ],
    "wof:name":"Bhimjipura",
    "wof:placetype":"locality",
    "wof:population":351
},
  "geometry": {"coordinates":[72.70789000000001,23.928738],"type":"Point"}
}