{
  "type": "Feature",
  "properties": {
    "iso:country":"IN",
    "ks:ks_name":"Satgawa Tola",
    "ks:ks_pop":6,
    "ks:ks_type":"HABITATION",
    "name:eng_x_preferred":[
        "Satgawa Tola"
    ],
    "wof:name":"Satgawa Tola",
    "wof:placetype":"locality",
    "wof:population":6
},
  "geometry": {"coordinates":[86.23402,24.737602],"type":"Point"}
}