{
  "type": "Feature",
  "properties": {
    "iso:country":"IN",
    "ks:ks_name":"Daludih",
    "ks:ks_pop":1582,
    "ks:ks_type":"VILLAGE",
    "ks:ks_uagg_main":0,
    "name:eng_x_preferred":[
        "Daludih"
    ],
    "wof:name":"Daludih",
    "wof:placetype":"neighbourhood",
    "wof:population":1582
},
  "geometry": {"coordinates":[86.328272,23.877098],"type":"Point"}
}