{
  "type": "Feature",
  "properties": {
    "iso:country":"IN",
    "ks:ks_name":"Sathalpur",
    "ks:ks_pop":1391,
    "ks:ks_type":"HABITATION",
    "name:eng_x_preferred":[
        "Sathalpur"
    ],
    "wof:name":"Sathalpur",
    "wof:placetype":"locality",
    "wof:population":1391
},
  "geometry": {"coordinates":[77.17959500000001,26.28982],"type":"Point"}
}