{
  "type": "Feature",
  "properties": {
    "iso:country":"IN",
    "ks:ks_name":"Chandi Khera",
    "ks:ks_pop":423,
    "ks:ks_type":"HABITATION",
    "name:eng_x_preferred":[
        "Chandi Khera"
    ],
    "wof:name":"Chandi Khera",
    "wof:placetype":"locality",
    "wof:population":423
},
  "geometry": {"coordinates":[81.07501600000001,26.584662],"type":"Point"}
}