{
  "type": "Feature",
  "properties": {
    "iso:country":"IN",
    "ks:ks_name":"Bharad",
    "ks:ks_pop":261,
    "ks:ks_type":"HABITATION",
    "name:eng_x_preferred":[
        "Bharad"
    ],
    "wof:name":"Bharad",
    "wof:placetype":"locality",
    "wof:population":261
},
  "geometry": {"coordinates":[74.162222,21.927436],"type":"Point"}
}