{
  "type": "Feature",
  "properties": {
    "gn:admin1_code":"35",
    "gn:admin2_code":"466.0",
    "gn:asciiname":"Pabai Kalan",
    "gn:country_code":"IN",
    "gn:dem":353,
    "gn:feature_class":"P",
    "gn:feature_code":"PPL",
    "gn:name":"P\u0101bai Kalan",
    "gn:population":0,
    "gn:timezone":"Asia/Kolkata",
    "iso:country":"IN",
    "wof:name":"Pabai Kalan",
    "wof:placetype":"locality"
},
  "geometry": {"coordinates":[76.33246,21.6779],"type":"Point"}
}