{
  "type": "Feature",
  "properties": {
    "iso:country":"IN",
    "ks:ks_name":"Majra Chmaro Wala",
    "ks:ks_pop":52,
    "ks:ks_type":"HABITATION",
    "name:eng_x_preferred":[
        "Majra Chmaro Wala"
    ],
    "wof:name":"Majra Chmaro Wala",
    "wof:placetype":"locality",
    "wof:population":52
},
  "geometry": {"coordinates":[78.981537,28.981187],"type":"Point"}
}