{
  "type": "Feature",
  "properties": {
    "iso:country":"IN",
    "ks:ks_name":"Bano Ka Tala",
    "ks:ks_pop":417,
    "ks:ks_type":"HABITATION",
    "name:eng_x_preferred":[
        "Bano Ka Tala"
    ],
    "wof:name":"Bano Ka Tala",
    "wof:placetype":"locality",
    "wof:population":417
},
  "geometry": {"coordinates":[71.173858,25.760558],"type":"Point"}
}