{
  "type": "Feature",
  "properties": {
    "iso:country":"IN",
    "ks:ks_name":"Gobra",
    "ks:ks_pop":1419,
    "ks:ks_type":"VILLAGE",
    "ks:ks_uagg_main":0,
    "name:eng_x_preferred":[
        "Gobra"
    ],
    "wof:name":"Gobra",
    "wof:placetype":"neighbourhood",
    "wof:population":1419
},
  "geometry": {"coordinates":[88.896289,22.890156],"type":"Point"}
}