{
  "type": "Feature",
  "properties": {
    "iso:country":"IN",
    "ks:ks_name":"Tenuahi Tola",
    "ks:ks_pop":550,
    "ks:ks_type":"HABITATION",
    "name:eng_x_preferred":[
        "Tenuahi Tola"
    ],
    "wof:name":"Tenuahi Tola",
    "wof:placetype":"locality",
    "wof:population":550
},
  "geometry": {"coordinates":[83.43610200000001,24.134893],"type":"Point"}
}