{
  "type": "Feature",
  "properties": {
    "iso:country":"IN",
    "ks:ks_alt_nam":"Yaxi bindumakki",
    "ks:ks_name":"Yaxi Bindumakki",
    "ks:ks_pop":12,
    "ks:ks_type":"HABITATION",
    "name:eng_x_preferred":[
        "Yaxi Bindumakki"
    ],
    "wof:name":"Yaxi Bindumakki",
    "wof:placetype":"locality",
    "wof:population":12
},
  "geometry": {"coordinates":[74.776904,14.013359],"type":"Point"}
}