{
  "type": "Feature",
  "properties": {
    "iso:country":"IN",
    "ks:ks_name":"Lower Pubung",
    "ks:ks_pop":696,
    "ks:ks_type":"HABITATION",
    "name:eng_x_preferred":[
        "Lower Pubung"
    ],
    "wof:name":"Lower Pubung",
    "wof:placetype":"locality",
    "wof:population":696
},
  "geometry": {"coordinates":[88.345409,27.024513],"type":"Point"}
}