{
  "type": "Feature",
  "properties": {
    "gn:admin1_code":"9",
    "gn:admin2_code":"485.0",
    "gn:asciiname":"Timi",
    "gn:country_code":"IN",
    "gn:dem":249,
    "gn:feature_class":"P",
    "gn:feature_code":"PPL",
    "gn:name":"Timi",
    "gn:population":0,
    "gn:timezone":"Asia/Kolkata",
    "iso:country":"IN",
    "name:bul_x_preferred":[
        "\u0422\u0438\u043c\u0438"
    ],
    "name:ceb_x_preferred":[
        "T\u00edmi"
    ],
    "name:ell_x_preferred":[
        "\u03a4\u03af\u03bc\u03b7"
    ],
    "name:fin_x_preferred":[
        "T\u00edmi"
    ],
    "name:hye_x_preferred":[
        "\u054f\u056b\u0574\u056b"
    ],
    "name:pol_x_preferred":[
        "Timi"
    ],
    "name:swe_x_preferred":[
        "T\u00edmi"
    ],
    "name:urd_x_preferred":[
        "\u062a\u06cc\u0645\u06cc"
    ],
    "wof:name":"Timi",
    "wof:placetype":"locality"
},
  "geometry": {"coordinates":[74.28678000000002,23.08282],"type":"Point"}
}