{
  "type": "Feature",
  "properties": {
    "iso:country":"IN",
    "ks:ks_name":"Handh Para",
    "ks:ks_pop":606,
    "ks:ks_type":"HABITATION",
    "ks:ks_uagg_main":0,
    "name:eng_x_preferred":[
        "Handh Para"
    ],
    "wof:name":"Handh Para",
    "wof:placetype":"neighbourhood",
    "wof:population":606
},
  "geometry": {"coordinates":[88.540728,22.045685],"type":"Point"}
}