{
  "type": "Feature",
  "properties": {
    "iso:country":"IN",
    "ks:ks_name":"Pachgaon Patti Amar Singh",
    "ks:ks_pop":2897,
    "ks:ks_type":"VILLAGE",
    "name:eng_x_preferred":[
        "Pachgaon Patti Amar Singh"
    ],
    "wof:name":"Pachgaon Patti Amar Singh",
    "wof:placetype":"locality",
    "wof:population":2897
},
  "geometry": {"coordinates":[77.82838099999999,28.926535],"type":"Point"}
}