{
  "type": "Feature",
  "properties": {
    "iso:country":"IN",
    "ks:ks_alt_nam":"KHADRA FALI",
    "ks:ks_name":"Khadra Fali",
    "ks:ks_pop":400,
    "ks:ks_type":"HABITATION",
    "name:eng_x_preferred":[
        "Khadra Fali"
    ],
    "wof:name":"Khadra Fali",
    "wof:placetype":"locality",
    "wof:population":400
},
  "geometry": {"coordinates":[72.75809700000001,24.413806],"type":"Point"}
}