{
  "type": "Feature",
  "properties": {
    "gn:admin1_code":"12.0",
    "gn:admin2_code":"18.0",
    "gn:asciiname":"Jushane",
    "gn:country_code":"IN",
    "gn:dem":1509,
    "gn:feature_class":"P",
    "gn:feature_code":"PPL",
    "gn:name":"Jush\u0101n\u0113",
    "gn:population":0,
    "gn:timezone":"Asia/Kolkata",
    "iso:country":"IN",
    "wof:name":"Jushane",
    "wof:placetype":"locality"
},
  "geometry": {"coordinates":[75.81839000000002,33.19078],"type":"Point"}
}