{
  "type": "Feature",
  "properties": {
    "iso:country":"IN",
    "ks:ks_name":"Janguo Nagar",
    "ks:ks_pop":364,
    "ks:ks_type":"HABITATION",
    "name:eng_x_preferred":[
        "Janguo Nagar"
    ],
    "wof:name":"Janguo Nagar",
    "wof:placetype":"locality",
    "wof:population":364
},
  "geometry": {"coordinates":[71.736103,24.909569],"type":"Point"}
}