{
  "type": "Feature",
  "properties": {
    "iso:country":"IN",
    "ks:ks_name":"G Kanchili",
    "ks:ks_pop":810,
    "ks:ks_type":"HABITATION",
    "name:eng_x_preferred":[
        "G Kanchili"
    ],
    "wof:name":"G Kanchili",
    "wof:placetype":"locality",
    "wof:population":810
},
  "geometry": {"coordinates":[84.56885200000001,18.979548],"type":"Point"}
}