{
  "type": "Feature",
  "properties": {
    "iso:country":"IN",
    "ks:ks_name":"Girjatola",
    "ks:ks_pop":15,
    "ks:ks_type":"HABITATION",
    "name:eng_x_preferred":[
        "Girjatola"
    ],
    "wof:name":"Girjatola",
    "wof:placetype":"locality",
    "wof:population":15
},
  "geometry": {"coordinates":[85.433463,22.965259],"type":"Point"}
}