{
  "type": "Feature",
  "properties": {
    "gn:admin1_code":"19.0",
    "gn:admin2_code":"574.0",
    "gn:asciiname":"Madranahalli",
    "gn:country_code":"IN",
    "gn:dem":933,
    "gn:feature_class":"P",
    "gn:feature_code":"PPL",
    "gn:name":"Madranahalli",
    "gn:population":0,
    "gn:timezone":"Asia/Kolkata",
    "iso:country":"IN",
    "wof:name":"Madranahalli",
    "wof:placetype":"locality"
},
  "geometry": {"coordinates":[76.01855999999999,12.9867],"type":"Point"}
}