{
  "type": "Feature",
  "properties": {
    "gn:admin1_code":"36",
    "gn:admin2_code":"155.0",
    "gn:asciiname":"Sonepur",
    "gn:country_code":"IN",
    "gn:dem":140,
    "gn:feature_class":"P",
    "gn:feature_code":"PPL",
    "gn:name":"Sonepur",
    "gn:population":0,
    "gn:timezone":"Asia/Kolkata",
    "iso:country":"IN",
    "name:deu_x_preferred":[
        "Sonepur"
    ],
    "name:fra_x_preferred":[
        "Sonepur"
    ],
    "name:msa_x_preferred":[
        "Sonapur"
    ],
    "name:nld_x_preferred":[
        "Sonepur"
    ],
    "wof:name":"Sonepur",
    "wof:placetype":"locality"
},
  "geometry": {"coordinates":[79.88150999999998,27.35711],"type":"Point"}
}