{
  "type": "Feature",
  "properties": {
    "iso:country":"IN",
    "ks:ks_alt_nam":"kasakadi",
    "ks:ks_name":"Kasakadi",
    "ks:ks_pop":41,
    "ks:ks_type":"HABITATION",
    "name:eng_x_preferred":[
        "Kasakadi"
    ],
    "wof:name":"Kasakadi",
    "wof:placetype":"locality",
    "wof:population":41
},
  "geometry": {"coordinates":[83.97541,20.498255],"type":"Point"}
}