{
  "type": "Feature",
  "properties": {
    "iso:country":"IN",
    "ks:ks_name":"Talenji",
    "ks:ks_pop":585,
    "ks:ks_type":"HABITATION",
    "name:eng_x_preferred":[
        "Talenji"
    ],
    "wof:name":"Talenji",
    "wof:placetype":"locality",
    "wof:population":585
},
  "geometry": {"coordinates":[75.225407,12.643176],"type":"Point"}
}