{
  "type": "Feature",
  "properties": {
    "gn:admin1_code":"29.0",
    "gn:admin2_code":"243.0",
    "gn:asciiname":"Papung",
    "gn:country_code":"IN",
    "gn:dem":1159,
    "gn:feature_class":"P",
    "gn:feature_code":"PPL",
    "gn:name":"P\u0101pung",
    "gn:population":0,
    "gn:timezone":"Asia/Kolkata",
    "iso:country":"IN",
    "wof:name":"Papung",
    "wof:placetype":"locality"
},
  "geometry": {"coordinates":[88.44580000000001,27.22938],"type":"Point"}
}