{
  "type": "Feature",
  "properties": {
    "gn:admin1_code":"29.0",
    "gn:admin2_code":"243.0",
    "gn:asciiname":"Papung",
    "gn:country_code":"IN",
    "gn:dem":1159,
    "gn:feature_class":"P",
    "gn:feature_code":"PPL",
    "gn:name":"P\u0101pung",
    "gn:population":0,
    "gn:timezone":"Asia/Kolkata",
    "iso:country":"IN",
    "name:ceb_x_preferred":[
        "Papung"
    ],
    "name:fra_x_preferred":[
        "Papung"
    ],
    "name:mai_x_preferred":[
        "\u092a\u093e\u092a\u0941\u0919\u094d\u0917"
    ],
    "name:msa_x_preferred":[
        "Papung"
    ],
    "name:nep_x_preferred":[
        "\u092a\u093e\u092a\u0941\u0919"
    ],
    "name:new_x_preferred":[
        "\u092a\u093e\u092a\u0941\u0919"
    ],
    "name:pol_x_preferred":[
        "Papung"
    ],
    "wof:name":"Papung",
    "wof:placetype":"locality"
},
  "geometry": {"coordinates":[88.44580000000001,27.22938],"type":"Point"}
}