{
  "type": "Feature",
  "properties": {
    "gn:admin1_code":"36",
    "gn:admin2_code":"185.0",
    "gn:asciiname":"Dharamnagar",
    "gn:country_code":"IN",
    "gn:dem":93,
    "gn:feature_class":"P",
    "gn:feature_code":"PPL",
    "gn:name":"Dharamnagar",
    "gn:population":0,
    "gn:timezone":"Asia/Kolkata",
    "iso:country":"IN",
    "ks:ks_name":"Dharm Nagar",
    "ks:ks_pop":321,
    "ks:ks_type":"VILLAGE",
    "ks:ks_uagg_main":0,
    "name:eng_x_preferred":[
        "Dharm Nagar"
    ],
    "wof:name":"Dharm Nagar",
    "wof:placetype":"neighbourhood",
    "wof:population":321
},
  "geometry": {"coordinates":[82.442922,26.728634],"type":"Point"}
}