{
  "type": "Feature",
  "properties": {
    "iso:country":"IN",
    "ks:ks_alt_nam":"D\u012bgha",
    "ks:ks_name":"Digha",
    "ks:ks_pop":27,
    "ks:ks_type":"VILLAGE",
    "ks:ks_uagg_main":0,
    "name:eng_x_preferred":[
        "Digha"
    ],
    "name:eng_x_variant":[
        "D\u012bgha"
    ],
    "wof:name":"Digha",
    "wof:placetype":"neighbourhood",
    "wof:population":27
},
  "geometry": {"coordinates":[85.08740299999999,25.648118],"type":"Point"}
}