{
  "type": "Feature",
  "properties": {
    "iso:country":"IN",
    "ks:ks_name":"Nagpur",
    "ks:ks_pop":358,
    "ks:ks_type":"VILLAGE",
    "name:eng_x_preferred":[
        "Nagpur"
    ],
    "wof:name":"Nagpur",
    "wof:placetype":"locality",
    "wof:population":358
},
  "geometry": {"coordinates":[86.912927,24.518699],"type":"Point"}
}