{
  "type": "Feature",
  "properties": {
    "iso:country":"IN",
    "ks:ks_name":"Udaiyar Street",
    "ks:ks_pop":102,
    "ks:ks_type":"HABITATION",
    "name:eng_x_preferred":[
        "Udaiyar Street"
    ],
    "wof:name":"Udaiyar Street",
    "wof:placetype":"locality",
    "wof:population":102
},
  "geometry": {"coordinates":[79.17916200000001,10.039206],"type":"Point"}
}