{
  "type": "Feature",
  "properties": {
    "iso:country":"IN",
    "ks:ks_alt_nam":"Meyy\u016br",
    "ks:ks_alt_nam_2":"Meyyur",
    "ks:ks_name":"C. Meyyur",
    "ks:ks_pop":3084,
    "ks:ks_type":"VILLAGE",
    "ks:ks_uagg_main":0,
    "name:eng_x_preferred":[
        "C. Meyyur"
    ],
    "name:eng_x_variant":[
        "Meyy\u016br",
        "Meyyur"
    ],
    "wof:name":"C. Meyyur",
    "wof:placetype":"neighbourhood",
    "wof:population":3084
},
  "geometry": {"coordinates":[79.291465,11.93119],"type":"Point"}
}