{
  "type": "Feature",
  "properties": {
    "iso:country":"IN",
    "ks:ks_name":"Mandeshetwadi",
    "ks:ks_pop":279,
    "ks:ks_type":"HABITATION",
    "name:eng_x_preferred":[
        "Mandeshetwadi"
    ],
    "wof:name":"Mandeshetwadi",
    "wof:placetype":"locality",
    "wof:population":279
},
  "geometry": {"coordinates":[73.82643400000001,16.04289],"type":"Point"}
}