{
  "type": "Feature",
  "properties": {
    "iso:country":"IN",
    "ks:ks_name":"Shivrajpur",
    "ks:ks_pop":806,
    "ks:ks_type":"VILLAGE",
    "name:eng_x_preferred":[
        "Shivrajpur"
    ],
    "wof:name":"Shivrajpur",
    "wof:placetype":"locality",
    "wof:population":806
},
  "geometry": {"coordinates":[80.36134699999999,27.870356],"type":"Point"}
}