{
  "type": "Feature",
  "properties": {
    "gn:admin1_code":"16",
    "gn:admin2_code":"502.0",
    "gn:asciiname":"Shelu",
    "gn:country_code":"IN",
    "gn:dem":433,
    "gn:feature_class":"P",
    "gn:feature_code":"PPL",
    "gn:name":"Shelu",
    "gn:population":0,
    "gn:timezone":"Asia/Kolkata",
    "iso:country":"IN",
    "name:mar_x_preferred":[
        "\u0936\u0947\u0932\u0942"
    ],
    "name:urd_x_preferred":[
        "\u0634\u06cc\u0644\u0648"
    ],
    "wof:name":"Shelu",
    "wof:placetype":"locality"
},
  "geometry": {"coordinates":[77.40405,20.44122],"type":"Point"}
}