{
  "type": "Feature",
  "properties": {
    "iso:country":"IN",
    "ks:ks_alt_nam":"GOSAINDH",
    "ks:ks_name":"Gosaindh",
    "ks:ks_pop":1521,
    "ks:ks_type":"HABITATION",
    "name:eng_x_preferred":[
        "Gosaindh"
    ],
    "wof:name":"Gosaindh",
    "wof:placetype":"locality",
    "wof:population":1521
},
  "geometry": {"coordinates":[84.78114100000001,24.388865],"type":"Point"}
}