{
  "type": "Feature",
  "properties": {
    "iso:country":"IN",
    "ks:ks_name":"Kalanda",
    "ks:ks_pop":775,
    "ks:ks_type":"VILLAGE",
    "name:eng_x_preferred":[
        "Kalanda"
    ],
    "wof:name":"Kalanda",
    "wof:placetype":"locality",
    "wof:population":775
},
  "geometry": {"coordinates":[85.816354,21.938985],"type":"Point"}
}