{
  "type": "Feature",
  "properties": {
    "iso:country":"IN",
    "ks:ks_name":"Bhotaha Kewathi",
    "ks:ks_pop":125,
    "ks:ks_type":"HABITATION",
    "ks:ks_uagg_main":0,
    "name:eng_x_preferred":[
        "Bhotaha Kewathi"
    ],
    "wof:name":"Bhotaha Kewathi",
    "wof:placetype":"neighbourhood",
    "wof:population":125
},
  "geometry": {"coordinates":[82.89518700000001,26.555695],"type":"Point"}
}