{
  "type": "Feature",
  "properties": {
    "gn:admin1_code":"19.0",
    "gn:admin2_code":"583.0",
    "gn:asciiname":"Banasvadi",
    "gn:country_code":"IN",
    "gn:dem":836,
    "gn:feature_class":"P",
    "gn:feature_code":"PPL",
    "gn:name":"B\u0101nasv\u0101di",
    "gn:population":0,
    "gn:timezone":"Asia/Kolkata",
    "iso:country":"IN",
    "wof:name":"Banasvadi",
    "wof:placetype":"locality"
},
  "geometry": {"coordinates":[77.36502,13.01474],"type":"Point"}
}