{
  "type": "Feature",
  "properties": {
    "iso:country":"IN",
    "ks:ks_name":"Aawadhani",
    "ks:ks_pop":1418,
    "ks:ks_type":"HABITATION",
    "name:eng_x_preferred":[
        "Aawadhani"
    ],
    "wof:name":"Aawadhani",
    "wof:placetype":"locality",
    "wof:population":1418
},
  "geometry": {"coordinates":[72.91481400000001,19.754249],"type":"Point"}
}