{
  "type": "Feature",
  "properties": {
    "gn:admin1_code":"36",
    "gn:asciiname":"Subhan Khera",
    "gn:country_code":"IN",
    "gn:dem":150,
    "gn:feature_class":"P",
    "gn:feature_code":"PPL",
    "gn:name":"Subh\u0101n Khera",
    "gn:population":0,
    "gn:timezone":"Asia/Kolkata",
    "iso:country":"IN",
    "wof:name":"Subhan Khera",
    "wof:placetype":"locality"
},
  "geometry": {"coordinates":[80.34180000000001,25.06217],"type":"Point"}
}