{
  "type": "Feature",
  "properties": {
    "gn:admin1_code":"36.0",
    "gn:admin2_code":"132.0",
    "gn:asciiname":"Latifpur",
    "gn:country_code":"IN",
    "gn:dem":264,
    "gn:feature_class":"P",
    "gn:feature_code":"PPL",
    "gn:name":"Lat\u012bfpur",
    "gn:population":0,
    "gn:timezone":"Asia/Kolkata",
    "iso:country":"IN",
    "name:urd_x_preferred":[
        "\u0644\u0637\u06cc\u0641\u067e\u0648\u0631"
    ],
    "wof:name":"Latifpur",
    "wof:placetype":"locality"
},
  "geometry": {"coordinates":[77.29989,29.96443],"type":"Point"}
}