{
  "type": "Feature",
  "properties": {
    "iso:country":"IN",
    "ks:ks_name":"Dhekani",
    "ks:ks_pop":125,
    "ks:ks_type":"HABITATION",
    "name:eng_x_preferred":[
        "Dhekani"
    ],
    "wof:name":"Dhekani",
    "wof:placetype":"locality",
    "wof:population":125
},
  "geometry": {"coordinates":[80.097037,19.931241],"type":"Point"}
}