{
  "type": "Feature",
  "properties": {
    "iso:country":"IN",
    "ks:ks_name":"Yadavtola",
    "ks:ks_pop":103,
    "ks:ks_type":"HABITATION",
    "name:eng_x_preferred":[
        "Yadavtola"
    ],
    "wof:name":"Yadavtola",
    "wof:placetype":"locality",
    "wof:population":103
},
  "geometry": {"coordinates":[86.102582,24.310137],"type":"Point"}
}