{
  "type": "Feature",
  "properties": {
    "iso:country":"IN",
    "ks:ks_name":"Linganapura",
    "ks:ks_pop":810,
    "ks:ks_type":"VILLAGE",
    "ks:ks_uagg_main":0,
    "name:eng_x_preferred":[
        "Linganapura"
    ],
    "wof:name":"Linganapura",
    "wof:placetype":"neighbourhood",
    "wof:population":810
},
  "geometry": {"coordinates":[77.124357,12.149314],"type":"Point"}
}