{
  "type": "Feature",
  "properties": {
    "iso:country":"IN",
    "ks:ks_name":"Desh Bandh",
    "ks:ks_pop":32,
    "ks:ks_type":"VILLAGE",
    "name:eng_x_preferred":[
        "Desh Bandh"
    ],
    "wof:name":"Desh Bandh",
    "wof:placetype":"locality",
    "wof:population":32
},
  "geometry": {"coordinates":[87.423636,22.776262],"type":"Point"}
}