{
  "type": "Feature",
  "properties": {
    "iso:country":"IN",
    "ks:ks_name":"Taljhari",
    "ks:ks_pop":320,
    "ks:ks_type":"HABITATION",
    "ks:ks_uagg_main":0,
    "name:eng_x_preferred":[
        "Taljhari"
    ],
    "wof:name":"Taljhari",
    "wof:placetype":"neighbourhood",
    "wof:population":320
},
  "geometry": {"coordinates":[86.354145,24.953558],"type":"Point"}
}