{
  "type": "Feature",
  "properties": {
    "iso:country":"IN",
    "ks:ks_name":"Nagla Bari",
    "ks:ks_pop":600,
    "ks:ks_type":"HABITATION",
    "name:eng_x_preferred":[
        "Nagla Bari"
    ],
    "wof:name":"Nagla Bari",
    "wof:placetype":"locality",
    "wof:population":600
},
  "geometry": {"coordinates":[78.509671,26.986679],"type":"Point"}
}