{
  "type": "Feature",
  "properties": {
    "iso:country":"IN",
    "ks:ks_name":"Chakjodhi",
    "ks:ks_pop":662,
    "ks:ks_type":"VILLAGE",
    "name:eng_x_preferred":[
        "Chakjodhi"
    ],
    "wof:name":"Chakjodhi",
    "wof:placetype":"locality",
    "wof:population":662
},
  "geometry": {"coordinates":[82.571162,25.260374],"type":"Point"}
}