{
  "type": "Feature",
  "properties": {
    "iso:country":"IN",
    "ks:ks_alt_nam":"Ekt\u0101",
    "ks:ks_name":"Ekta",
    "ks:ks_type":"VILLAGE",
    "name:eng_x_preferred":[
        "Ekta"
    ],
    "name:eng_x_variant":[
        "Ekt\u0101"
    ],
    "wof:name":"Ekta",
    "wof:placetype":"locality"
},
  "geometry": {"coordinates":[84.323837,23.931647],"type":"Point"}
}