{
  "type": "Feature",
  "properties": {
    "gn:admin1_code":"35.0",
    "gn:admin2_code":"454.0",
    "gn:asciiname":"Kudopani",
    "gn:country_code":"IN",
    "gn:dem":591,
    "gn:feature_class":"P",
    "gn:feature_code":"PPL",
    "gn:name":"Kudop\u0101ni",
    "gn:population":0,
    "gn:timezone":"Asia/Kolkata",
    "iso:country":"IN",
    "ks:ks_alt_nam":"Kudop\u0101ni",
    "ks:ks_name":"Kudopani",
    "ks:ks_type":"VILLAGE",
    "name:eng_x_preferred":[
        "Kudopani"
    ],
    "name:eng_x_variant":[
        "Kudop\u0101ni"
    ],
    "wof:name":"Kudopani",
    "wof:placetype":"locality"
},
  "geometry": {"coordinates":[80.44546,22.779394],"type":"Point"}
}