{
  "type": "Feature",
  "properties": {
    "gn:admin1_code":"25.0",
    "gn:admin2_code":"602",
    "gn:asciiname":"Kilachcheri",
    "gn:country_code":"IN",
    "gn:dem":64,
    "gn:feature_class":"P",
    "gn:feature_code":"PPL",
    "gn:name":"K\u012blachcheri",
    "gn:population":0,
    "gn:timezone":"Asia/Kolkata",
    "iso:country":"IN",
    "name:und_x_variant":[
        "Kilacheri",
        "K\u012blachcheri",
        "K\u012blcheri"
    ],
    "wof:name":"Kilachcheri",
    "wof:placetype":"locality"
},
  "geometry": {"coordinates":[79.84621,13.02553],"type":"Point"}
}