{
  "type": "Feature",
  "properties": {
    "iso:country":"IN",
    "ks:ks_name":"Mankarpada",
    "ks:ks_pop":136,
    "ks:ks_type":"HABITATION",
    "name:eng_x_preferred":[
        "Mankarpada"
    ],
    "wof:name":"Mankarpada",
    "wof:placetype":"locality",
    "wof:population":136
},
  "geometry": {"coordinates":[72.941064,19.984431],"type":"Point"}
}