{
  "type": "Feature",
  "properties": {
    "iso:country":"IN",
    "ks:ks_name":"Basantapur",
    "ks:ks_pop":1062,
    "ks:ks_type":"HABITATION",
    "name:eng_x_preferred":[
        "Basantapur"
    ],
    "wof:name":"Basantapur",
    "wof:placetype":"locality",
    "wof:population":1062
},
  "geometry": {"coordinates":[88.12054500000001,21.636747],"type":"Point"}
}