{
  "type": "Feature",
  "properties": {
    "gn:admin1_code":"40",
    "gn:admin2_code":"537.0",
    "gn:asciiname":"Asnathpalle",
    "gn:country_code":"IN",
    "gn:dem":462,
    "gn:feature_class":"P",
    "gn:feature_code":"PPL",
    "gn:name":"Asn\u0101thpalle",
    "gn:population":0,
    "gn:timezone":"Asia/Kolkata",
    "iso:country":"IN",
    "wof:name":"Asnathpalle",
    "wof:placetype":"neighbourhood"
},
  "geometry": {"coordinates":[77.65448000000001,17.22136],"type":"Point"}
}