{
  "type": "Feature",
  "properties": {
    "iso:country":"IN",
    "ks:ks_name":"Bholwat",
    "ks:ks_pop":626,
    "ks:ks_type":"VILLAGE",
    "name:eng_x_preferred":[
        "Bholwat"
    ],
    "wof:name":"Bholwat",
    "wof:placetype":"locality",
    "wof:population":626
},
  "geometry": {"coordinates":[74.181969,22.449629],"type":"Point"}
}