{
  "type": "Feature",
  "properties": {
    "iso:country":"IN",
    "ks:ks_alt_nam":"Pura bhagraj",
    "ks:ks_name":"Pura Bhagraj",
    "ks:ks_pop":400,
    "ks:ks_type":"HABITATION",
    "ks:ks_uagg_main":0,
    "name:eng_x_preferred":[
        "Pura Bhagraj"
    ],
    "wof:name":"Pura Bhagraj",
    "wof:placetype":"neighbourhood",
    "wof:population":400
},
  "geometry": {"coordinates":[78.53607100000001,26.802005],"type":"Point"}
}