{
  "type": "Feature",
  "properties": {
    "iso:country":"IN",
    "ks:ks_name":"Balijan",
    "ks:ks_pop":305,
    "ks:ks_type":"VILLAGE",
    "name:eng_x_preferred":[
        "Balijan"
    ],
    "wof:name":"Balijan",
    "wof:placetype":"locality",
    "wof:population":305
},
  "geometry": {"coordinates":[93.03838500000001,26.798339],"type":"Point"}
}