{
  "type": "Feature",
  "properties": {
    "iso:country":"IN",
    "ks:ks_alt_nam":"chavanwadi",
    "ks:ks_name":"Chavanwadi",
    "ks:ks_pop":29,
    "ks:ks_type":"HABITATION",
    "name:eng_x_preferred":[
        "Chavanwadi"
    ],
    "wof:name":"Chavanwadi",
    "wof:placetype":"locality",
    "wof:population":29
},
  "geometry": {"coordinates":[73.144306,17.652939],"type":"Point"}
}