{
  "type": "Feature",
  "properties": {
    "iso:country":"IN",
    "ks:ks_name":"Mustafa Bad",
    "ks:ks_pop":176,
    "ks:ks_type":"HABITATION",
    "name:eng_x_preferred":[
        "Mustafa Bad"
    ],
    "wof:name":"Mustafa Bad",
    "wof:placetype":"locality",
    "wof:population":176
},
  "geometry": {"coordinates":[83.045934,26.030543],"type":"Point"}
}