{
  "type": "Feature",
  "properties": {
    "iso:country":"IN",
    "ks:ks_name":"Khojn Pur",
    "ks:ks_pop":7032,
    "ks:ks_type":"VILLAGE",
    "ks:ks_uagg_main":0,
    "name:eng_x_preferred":[
        "Khojn Pur"
    ],
    "wof:name":"Khojn Pur",
    "wof:placetype":"neighbourhood",
    "wof:population":7032
},
  "geometry": {"coordinates":[82.125518,26.769163],"type":"Point"}
}