{
  "type": "Feature",
  "properties": {
    "gn:admin1_code":"11",
    "gn:admin2_code":"23.0",
    "gn:asciiname":"Sarg Adwar",
    "gn:country_code":"IN",
    "gn:dem":3215,
    "gn:feature_class":"P",
    "gn:feature_code":"PPL",
    "gn:name":"Sarg Adw\u0101r",
    "gn:population":0,
    "gn:timezone":"Asia/Kolkata",
    "iso:country":"IN",
    "wof:name":"Sarg Adwar",
    "wof:placetype":"locality"
},
  "geometry": {"coordinates":[76.50764000000002,32.993],"type":"Point"}
}