{
  "type": "Feature",
  "properties": {
    "iso:country":"IN",
    "ks:ks_alt_nam":"Bongshijhora Pt.II",
    "ks:ks_name":"Bongshijhora Pt.ii",
    "ks:ks_pop":34,
    "ks:ks_type":"HABITATION",
    "name:eng_x_preferred":[
        "Bongshijhora Pt.ii"
    ],
    "wof:name":"Bongshijhora Pt.ii",
    "wof:placetype":"locality",
    "wof:population":34
},
  "geometry": {"coordinates":[90.010805,26.237272],"type":"Point"}
}