{
  "type": "Feature",
  "properties": {
    "iso:country":"IN",
    "ks:ks_name":"Karkain",
    "ks:ks_pop":2585,
    "ks:ks_type":"HABITATION",
    "name:eng_x_preferred":[
        "Karkain"
    ],
    "wof:name":"Karkain",
    "wof:placetype":"locality",
    "wof:population":2585
},
  "geometry": {"coordinates":[85.822778,25.301971],"type":"Point"}
}