{
  "type": "Feature",
  "properties": {
    "iso:country":"IN",
    "ks:ks_name":"Saidpur Hafizpur",
    "ks:ks_pop":1075,
    "ks:ks_type":"HABITATION",
    "name:eng_x_preferred":[
        "Saidpur Hafizpur"
    ],
    "wof:name":"Saidpur Hafizpur",
    "wof:placetype":"locality",
    "wof:population":1075
},
  "geometry": {"coordinates":[81.37073599999999,25.632267],"type":"Point"}
}