{
  "type": "Feature",
  "properties": {
    "iso:country":"IN",
    "ks:ks_name":"Tola Alagjara",
    "ks:ks_pop":132,
    "ks:ks_type":"VILLAGE",
    "name:eng_x_preferred":[
        "Tola Alagjara"
    ],
    "wof:name":"Tola Alagjara",
    "wof:placetype":"locality",
    "wof:population":132
},
  "geometry": {"coordinates":[86.451836,24.971895],"type":"Point"}
}