{
  "type": "Feature",
  "properties": {
    "gn:admin1_code":"35.0",
    "gn:admin2_code":"439.0",
    "gn:asciiname":"Gwaltoli",
    "gn:country_code":"IN",
    "gn:dem":559,
    "gn:feature_class":"P",
    "gn:feature_code":"PPL",
    "gn:name":"Gw\u0101ltoli",
    "gn:population":0,
    "gn:timezone":"Asia/Kolkata",
    "iso:country":"IN",
    "wof:name":"Gwaltoli",
    "wof:placetype":"neighbourhood"
},
  "geometry": {"coordinates":[75.89183,22.71821],"type":"Point"}
}