{
  "type": "Feature",
  "properties": {
    "gn:admin1_code":"37.0",
    "gn:admin2_code":"403",
    "gn:asciiname":"Chhal",
    "gn:country_code":"IN",
    "gn:dem":239,
    "gn:feature_class":"P",
    "gn:feature_code":"PPL",
    "gn:name":"Chh\u0101l",
    "gn:population":0,
    "gn:timezone":"Asia/Kolkata",
    "iso:country":"IN",
    "name:und_x_variant":[
        "Chal",
        "Chh\u0101l"
    ],
    "wof:name":"Chhal",
    "wof:placetype":"locality"
},
  "geometry": {"coordinates":[83.11623,22.12832],"type":"Point"}
}