{
  "type": "Feature",
  "properties": {
    "iso:country":"IN",
    "ks:ks_name":"Bharatpara",
    "ks:ks_pop":190,
    "ks:ks_type":"HABITATION",
    "name:eng_x_preferred":[
        "Bharatpara"
    ],
    "wof:name":"Bharatpara",
    "wof:placetype":"locality",
    "wof:population":190
},
  "geometry": {"coordinates":[84.235951,22.373016],"type":"Point"}
}