{
  "type": "Feature",
  "properties": {
    "gn:admin1_code":"19.0",
    "gn:admin2_code":"563.0",
    "gn:asciiname":"Kudargod",
    "gn:country_code":"IN",
    "gn:dem":566,
    "gn:feature_class":"P",
    "gn:feature_code":"PPL",
    "gn:name":"Kudargod",
    "gn:population":0,
    "gn:timezone":"Asia/Kolkata",
    "iso:country":"IN",
    "ks:ks_name":"Kudragod",
    "ks:ks_pop":119,
    "ks:ks_type":"HABITATION",
    "name:eng_x_preferred":[
        "Kudragod"
    ],
    "name:eng_x_variant":[
        "Kudargod"
    ],
    "wof:name":"Kudragod",
    "wof:placetype":"locality",
    "wof:population":119
},
  "geometry": {"coordinates":[74.661269,14.655395],"type":"Point"}
}