{
  "type": "Feature",
  "properties": {
    "gn:admin1_code":"19.0",
    "gn:admin2_code":"563.0",
    "gn:asciiname":"Kudargod",
    "gn:country_code":"IN",
    "gn:dem":566,
    "gn:feature_class":"P",
    "gn:feature_code":"PPL",
    "gn:name":"Kudargod",
    "gn:population":0,
    "gn:timezone":"Asia/Kolkata",
    "iso:country":"IN",
    "wof:name":"Kudargod",
    "wof:placetype":"locality"
},
  "geometry": {"coordinates":[74.65952,14.6547],"type":"Point"}
}