{
  "type": "Feature",
  "properties": {
    "gn:admin1_code":"3.0",
    "gn:admin2_code":"306",
    "gn:asciiname":"Gangmohthan",
    "gn:country_code":"IN",
    "gn:dem":85,
    "gn:feature_class":"P",
    "gn:feature_code":"PPL",
    "gn:name":"G\u0101ngmohth\u0101n",
    "gn:population":0,
    "gn:timezone":"Asia/Kolkata",
    "iso:country":"IN",
    "ks:ks_name":"Gang Mouthan",
    "ks:ks_pop":1245,
    "ks:ks_type":"VILLAGE",
    "ks:ks_uagg_main":0,
    "name:eng_x_preferred":[
        "Gang Mouthan"
    ],
    "wof:name":"Gang Mouthan",
    "wof:placetype":"neighbourhood",
    "wof:population":1245
},
  "geometry": {"coordinates":[93.311795,26.776363],"type":"Point"}
}