{
  "type": "Feature",
  "properties": {
    "iso:country":"IN",
    "ks:ks_alt_nam":"Alm\u0101spur",
    "ks:ks_name":"Almaspur",
    "ks:ks_type":"VILLAGE",
    "name:eng_x_preferred":[
        "Almaspur"
    ],
    "name:eng_x_variant":[
        "Alm\u0101spur"
    ],
    "wof:name":"Almaspur",
    "wof:placetype":"locality"
},
  "geometry": {"coordinates":[77.890546,29.894375],"type":"Point"}
}