{
  "type": "Feature",
  "properties": {
    "gn:admin1_code":"25.0",
    "gn:admin2_code":"632.0",
    "gn:asciiname":"Nilampatti",
    "gn:country_code":"IN",
    "gn:dem":558,
    "gn:feature_class":"P",
    "gn:feature_code":"PPL",
    "gn:name":"Nilampatti",
    "gn:population":0,
    "gn:timezone":"Asia/Kolkata",
    "iso:country":"IN",
    "wof:name":"Nilampatti",
    "wof:placetype":"locality"
},
  "geometry": {"coordinates":[76.83414999999999,11.13876],"type":"Point"}
}