{
  "type": "Feature",
  "properties": {
    "iso:country":"IN",
    "ks:ks_name":"Banjarapatti",
    "ks:ks_pop":525,
    "ks:ks_type":"VILLAGE",
    "name:eng_x_preferred":[
        "Banjarapatti"
    ],
    "wof:name":"Banjarapatti",
    "wof:placetype":"locality",
    "wof:population":525
},
  "geometry": {"coordinates":[84.115083,26.75795],"type":"Point"}
}