{
  "type": "Feature",
  "properties": {
    "gn:admin1_code":"2.0",
    "gn:admin2_code":"554.0",
    "gn:asciiname":"Errasanipalle",
    "gn:country_code":"IN",
    "gn:dem":579,
    "gn:feature_class":"P",
    "gn:feature_code":"PPL",
    "gn:name":"Erras\u0101nipalle",
    "gn:population":0,
    "gn:timezone":"Asia/Kolkata",
    "iso:country":"IN",
    "wof:name":"Errasanipalle",
    "wof:placetype":"locality"
},
  "geometry": {"coordinates":[78.46254999999999,13.79019],"type":"Point"}
}