{
  "type": "Feature",
  "properties": {
    "iso:country":"IN",
    "ks:ks_name":"Nalkeri Forest",
    "ks:ks_pop":233,
    "ks:ks_type":"VILLAGE",
    "name:eng_x_preferred":[
        "Nalkeri Forest"
    ],
    "wof:name":"Nalkeri Forest",
    "wof:placetype":"locality",
    "wof:population":233
},
  "geometry": {"coordinates":[76.066391,11.991746],"type":"Point"}
}