{
  "type": "Feature",
  "properties": {
    "iso:country":"IN",
    "ks:ks_name":"Kuppedada",
    "ks:ks_pop":436,
    "ks:ks_type":"VILLAGE",
    "name:eng_x_preferred":[
        "Kuppedada"
    ],
    "wof:name":"Kuppedada",
    "wof:placetype":"locality",
    "wof:population":436
},
  "geometry": {"coordinates":[76.58918,12.382374],"type":"Point"}
}