{
  "type": "Feature",
  "properties": {
    "iso:country":"IN",
    "ks:ks_name":"Choraikhola Jangal Block",
    "ks:ks_pop":365,
    "ks:ks_type":"VILLAGE",
    "name:eng_x_preferred":[
        "Choraikhola Jangal Block"
    ],
    "wof:name":"Choraikhola Jangal Block",
    "wof:placetype":"locality",
    "wof:population":365
},
  "geometry": {"coordinates":[90.324119,26.396337],"type":"Point"}
}