{
  "type": "Feature",
  "properties": {
    "iso:country":"IN",
    "ks:ks_name":"Vasvani",
    "ks:ks_pop":819,
    "ks:ks_type":"VILLAGE",
    "name:eng_x_preferred":[
        "Vasvani"
    ],
    "wof:name":"Vasvani",
    "wof:placetype":"locality",
    "wof:population":819
},
  "geometry": {"coordinates":[73.91116700000001,22.009083],"type":"Point"}
}