{
  "type": "Feature",
  "properties": {
    "iso:country":"IN",
    "ks:ks_name":"Thinklkkadu",
    "ks:ks_pop":1200,
    "ks:ks_type":"HABITATION",
    "name:eng_x_preferred":[
        "Thinklkkadu"
    ],
    "wof:name":"Thinklkkadu",
    "wof:placetype":"locality",
    "wof:population":1200
},
  "geometry": {"coordinates":[77.11800599999999,9.909143],"type":"Point"}
}