{
  "type": "Feature",
  "properties": {
    "iso:country":"IN",
    "ks:ks_name":"Datina",
    "ks:ks_pop":585,
    "ks:ks_type":"VILLAGE",
    "ks:ks_uagg_main":0,
    "name:eng_x_preferred":[
        "Datina"
    ],
    "wof:name":"Datina",
    "wof:placetype":"neighbourhood",
    "wof:population":585
},
  "geometry": {"coordinates":[87.80390199999999,23.693511],"type":"Point"}
}