{
  "type": "Feature",
  "properties": {
    "gn:admin1_code":"25.0",
    "gn:admin2_code":"608.0",
    "gn:asciiname":"Ayittasanur",
    "gn:country_code":"IN",
    "gn:dem":367,
    "gn:feature_class":"P",
    "gn:feature_code":"PPL",
    "gn:name":"Ayitt\u0101san\u016br",
    "gn:population":0,
    "gn:timezone":"Asia/Kolkata",
    "iso:country":"IN",
    "wof:name":"Ayittasanur",
    "wof:placetype":"locality"
},
  "geometry": {"coordinates":[77.85942,11.75089],"type":"Point"}
}