{
  "type": "Feature",
  "properties": {
    "gn:admin1_code":"37",
    "gn:admin2_code":"413.0",
    "gn:asciiname":"Karegaon",
    "gn:country_code":"IN",
    "gn:dem":374,
    "gn:feature_class":"P",
    "gn:feature_code":"PPL",
    "gn:name":"Karegaon",
    "gn:population":0,
    "gn:timezone":"Asia/Kolkata",
    "iso:country":"IN",
    "ks:ks_name":"Karregaon",
    "ks:ks_pop":406,
    "ks:ks_type":"VILLAGE",
    "name:eng_x_preferred":[
        "Karregaon"
    ],
    "name:eng_x_variant":[
        "Karegaon"
    ],
    "wof:name":"Karregaon",
    "wof:placetype":"locality",
    "wof:population":406
},
  "geometry": {"coordinates":[81.040918,20.144737],"type":"Point"}
}