{
  "type": "Feature",
  "properties": {
    "gn:admin1_code":"19",
    "gn:admin2_code":"563.0",
    "gn:asciiname":"Urmunde",
    "gn:country_code":"IN",
    "gn:dem":531,
    "gn:feature_class":"P",
    "gn:feature_code":"PPL",
    "gn:name":"Urmunde",
    "gn:population":0,
    "gn:timezone":"Asia/Kolkata",
    "iso:country":"IN",
    "wof:name":"Urmunde",
    "wof:placetype":"locality"
},
  "geometry": {"coordinates":[74.80570999999998,14.80235],"type":"Point"}
}