{
  "type": "Feature",
  "properties": {
    "iso:country":"IN",
    "ks:ks_name":"Isakagaruvu",
    "ks:ks_pop":134,
    "ks:ks_type":"VILLAGE",
    "name:eng_x_preferred":[
        "Isakagaruvu"
    ],
    "wof:name":"Isakagaruvu",
    "wof:placetype":"locality",
    "wof:population":134
},
  "geometry": {"coordinates":[82.575731,18.074375],"type":"Point"}
}