{
  "type": "Feature",
  "properties": {
    "iso:country":"IN",
    "ks:ks_name":"Poridiamba",
    "ks:ks_pop":14,
    "ks:ks_type":"HABITATION",
    "name:eng_x_preferred":[
        "Poridiamba"
    ],
    "wof:name":"Poridiamba",
    "wof:placetype":"locality",
    "wof:population":14
},
  "geometry": {"coordinates":[83.091475,18.894109],"type":"Point"}
}