{
  "type": "Feature",
  "properties": {
    "gn:admin1_code":"36",
    "gn:admin2_code":"135.0",
    "gn:asciiname":"Basantpur Shahpur",
    "gn:country_code":"IN",
    "gn:dem":192,
    "gn:feature_class":"P",
    "gn:feature_code":"PPL",
    "gn:name":"Basantpur Sh\u0101hpur",
    "gn:population":0,
    "gn:timezone":"Asia/Kolkata",
    "iso:country":"IN",
    "wof:name":"Basantpur Shahpur",
    "wof:placetype":"locality"
},
  "geometry": {"coordinates":[78.84864,28.85236],"type":"Point"}
}