{
  "type": "Feature",
  "properties": {
    "gn:admin1_code":"37",
    "gn:admin2_code":"413.0",
    "gn:asciiname":"Narharpur",
    "gn:country_code":"IN",
    "gn:dem":402,
    "gn:feature_class":"P",
    "gn:feature_code":"PPL",
    "gn:name":"Narharpur",
    "gn:population":6500,
    "gn:timezone":"Asia/Kolkata",
    "iso:country":"IN",
    "wof:name":"Narharpur",
    "wof:placetype":"locality",
    "wof:population":6500
},
  "geometry": {"coordinates":[81.62004,20.44892],"type":"Point"}
}