{
  "type": "Feature",
  "properties": {
    "gn:admin1_code":"37.0",
    "gn:admin2_code":"416.0",
    "gn:asciiname":"Kundeli",
    "gn:country_code":"IN",
    "gn:dem":388,
    "gn:feature_class":"P",
    "gn:feature_code":"PPL",
    "gn:name":"Kundeli",
    "gn:population":0,
    "gn:timezone":"Asia/Kolkata",
    "iso:country":"IN",
    "ks:ks_name":"Kundeli",
    "ks:ks_pop":317,
    "ks:ks_type":"VILLAGE",
    "name:eng_x_preferred":[
        "Kundeli"
    ],
    "wof:name":"Kundeli",
    "wof:placetype":"locality",
    "wof:population":317
},
  "geometry": {"coordinates":[81.32479499999999,18.845373],"type":"Point"}
}