{
  "type": "Feature",
  "properties": {
    "gn:admin1_code":"36",
    "gn:admin2_code":"200.0",
    "gn:asciiname":"Pandar",
    "gn:country_code":"IN",
    "gn:dem":312,
    "gn:feature_class":"P",
    "gn:feature_code":"PPL",
    "gn:name":"P\u0101ndar",
    "gn:population":0,
    "gn:timezone":"Asia/Kolkata",
    "iso:country":"IN",
    "name:ceb_x_preferred":[
        "Pandar"
    ],
    "name:fas_x_preferred":[
        "\u067e\u0646\u062f\u0631"
    ],
    "name:swe_x_preferred":[
        "Pandar"
    ],
    "wof:name":"Pandar",
    "wof:placetype":"locality"
},
  "geometry": {"coordinates":[83.02802,24.79245],"type":"Point"}
}