{
  "type": "Feature",
  "properties": {
    "iso:country":"IN",
    "ks:ks_name":"Suriyavalavu",
    "ks:ks_pop":75,
    "ks:ks_type":"HABITATION",
    "name:eng_x_preferred":[
        "Suriyavalavu"
    ],
    "wof:name":"Suriyavalavu",
    "wof:placetype":"locality",
    "wof:population":75
},
  "geometry": {"coordinates":[78.343307,11.370447],"type":"Point"}
}