{
  "type": "Feature",
  "properties": {
    "iso:country":"IN",
    "ks:ks_name":"Dewardand",
    "ks:ks_pop":703,
    "ks:ks_type":"VILLAGE",
    "name:eng_x_preferred":[
        "Dewardand"
    ],
    "wof:name":"Dewardand",
    "wof:placetype":"locality",
    "wof:population":703
},
  "geometry": {"coordinates":[81.94682,24.43887],"type":"Point"}
}