{
  "type": "Feature",
  "properties": {
    "iso:country":"IN",
    "ks:ks_name":"Rampatti North",
    "ks:ks_pop":371,
    "ks:ks_type":"HABITATION",
    "name:eng_x_preferred":[
        "Rampatti North"
    ],
    "wof:name":"Rampatti North",
    "wof:placetype":"locality",
    "wof:population":371
},
  "geometry": {"coordinates":[86.152552,26.317563],"type":"Point"}
}