{
  "type": "Feature",
  "properties": {
    "gn:admin1_code":"35",
    "gn:admin2_code":"462.0",
    "gn:asciiname":"Saro",
    "gn:country_code":"IN",
    "gn:dem":309,
    "gn:feature_class":"P",
    "gn:feature_code":"PPL",
    "gn:name":"S\u0101ro",
    "gn:population":0,
    "gn:timezone":"Asia/Kolkata",
    "iso:country":"IN",
    "name:ceb_x_preferred":[
        "Saro"
    ],
    "name:deu_x_preferred":[
        "Saro"
    ],
    "name:fra_x_preferred":[
        "Saro"
    ],
    "name:ita_x_preferred":[
        "Saro"
    ],
    "name:nld_x_preferred":[
        "Saro"
    ],
    "name:spa_x_preferred":[
        "Saro"
    ],
    "name:swe_x_preferred":[
        "Saro"
    ],
    "wof:name":"Saro",
    "wof:placetype":"locality"
},
  "geometry": {"coordinates":[82.03858000000002,24.35841],"type":"Point"}
}