{
  "type": "Feature",
  "properties": {
    "gn:admin1_code":"28.0",
    "gn:admin2_code":"338",
    "gn:asciiname":"Gopinagar",
    "gn:country_code":"IN",
    "gn:dem":19,
    "gn:feature_class":"P",
    "gn:feature_code":"PPL",
    "gn:name":"Gopinagar",
    "gn:population":0,
    "gn:timezone":"Asia/Kolkata",
    "iso:country":"IN",
    "ks:ks_name":"Gopinagar",
    "ks:ks_pop":3733,
    "ks:ks_type":"VILLAGE",
    "name:eng_x_preferred":[
        "Gopinagar"
    ],
    "wof:name":"Gopinagar",
    "wof:placetype":"locality",
    "wof:population":3733
},
  "geometry": {"coordinates":[88.115008,22.84147],"type":"Point"}
}