{
  "type": "Feature",
  "properties": {
    "iso:country":"IN",
    "ks:ks_name":"Nishal",
    "ks:ks_pop":300,
    "ks:ks_type":"HABITATION",
    "name:eng_x_preferred":[
        "Nishal"
    ],
    "wof:name":"Nishal",
    "wof:placetype":"locality",
    "wof:population":300
},
  "geometry": {"coordinates":[73.30204999999999,21.209633],"type":"Point"}
}