{
  "type": "Feature",
  "properties": {
    "gn:admin1_code":"21.0",
    "gn:admin2_code":"376",
    "gn:asciiname":"Bangriposi",
    "gn:country_code":"IN",
    "gn:dem":115,
    "gn:feature_class":"P",
    "gn:feature_code":"PPL",
    "gn:name":"B\u0101ngriposi",
    "gn:population":0,
    "gn:timezone":"Asia/Kolkata",
    "iso:country":"IN",
    "name:ori_x_preferred":[
        "\u0b2c\u0b3e\u0b19\u0b4d\u0b17\u0b3f\u0b30\u0b3f\u0b2a\u0b4b\u0b37\u0b3f"
    ],
    "name:und_x_variant":[
        "B\u0101ngriposi"
    ],
    "wof:name":"Bangriposi",
    "wof:placetype":"locality"
},
  "geometry": {"coordinates":[86.54160999999998,22.15286],"type":"Point"}
}