{
  "type": "Feature",
  "properties": {
    "iso:country":"IN",
    "ks:ks_name":"Gangadharpur",
    "ks:ks_pop":945,
    "ks:ks_type":"VILLAGE",
    "ks:ks_uagg_main":0,
    "name:eng_x_preferred":[
        "Gangadharpur"
    ],
    "wof:name":"Gangadharpur",
    "wof:placetype":"neighbourhood",
    "wof:population":945
},
  "geometry": {"coordinates":[88.397075,23.142416],"type":"Point"}
}