{
  "type": "Feature",
  "properties": {
    "gn:admin1_code":"19",
    "gn:admin2_code":"563.0",
    "gn:asciiname":"Bamankop",
    "gn:country_code":"IN",
    "gn:dem":482,
    "gn:feature_class":"P",
    "gn:feature_code":"PPL",
    "gn:name":"B\u0101mankop",
    "gn:population":0,
    "gn:timezone":"Asia/Kolkata",
    "iso:country":"IN",
    "ks:ks_name":"Bamankoppa",
    "ks:ks_pop":30,
    "ks:ks_type":"HABITATION",
    "name:eng_x_preferred":[
        "Bamankoppa"
    ],
    "name:eng_x_variant":[
        "Bamankop"
    ],
    "wof:name":"Bamankoppa",
    "wof:placetype":"locality",
    "wof:population":30
},
  "geometry": {"coordinates":[74.82205999999999,14.895007],"type":"Point"}
}