{
  "type": "Feature",
  "properties": {
    "gn:admin1_code":"24.0",
    "gn:admin2_code":"125.0",
    "gn:asciiname":"Lokia",
    "gn:country_code":"IN",
    "gn:dem":157,
    "gn:feature_class":"P",
    "gn:feature_code":"PPL",
    "gn:name":"Lokia",
    "gn:population":0,
    "gn:timezone":"Asia/Kolkata",
    "iso:country":"IN",
    "ks:ks_name":"Lokiya",
    "ks:ks_pop":541,
    "ks:ks_type":"VILLAGE",
    "ks:ks_uagg_main":0,
    "name:ceb_x_preferred":[
        "Lokia"
    ],
    "name:cym_x_preferred":[
        "Lokia"
    ],
    "name:eng_x_preferred":[
        "Lokiya"
    ],
    "name:fra_x_preferred":[
        "Lokia"
    ],
    "name:nld_x_preferred":[
        "Lokia"
    ],
    "name:por_x_preferred":[
        "Lokia"
    ],
    "name:swe_x_preferred":[
        "Lokia"
    ],
    "name:vie_x_preferred":[
        "Lokia"
    ],
    "name:war_x_preferred":[
        "Lokia"
    ],
    "wof:name":"Lokiya",
    "wof:placetype":"neighbourhood",
    "wof:population":541
},
  "geometry": {"coordinates":[74.09777800000001,23.490556],"type":"Point"}
}