{
  "type": "Feature",
  "properties": {
    "iso:country":"IN",
    "qs:name":"Moodabettu",
    "qs:name_adm0":"India",
    "qs:name_adm1":"Karnataka",
    "qs:photos":4,
    "qs:photos_1k":1,
    "qs:photos_9k":1,
    "qs:photos_9r":1,
    "qs:photos_all":4,
    "qs:photos_sr":1,
    "qs:placetype":"Town",
    "qs:pop_sr":"0",
    "wof:name":"Moodabettu",
    "wof:placetype":"locality"
},
  "geometry": {"coordinates":[74.75077,13.290414],"type":"Point"}
}