{
  "type": "Feature",
  "properties": {
    "gn:admin1_code":"19.0",
    "gn:admin2_code":"569.0",
    "gn:asciiname":"Mudabettu",
    "gn:country_code":"IN",
    "gn:dem":14,
    "gn:feature_class":"P",
    "gn:feature_code":"PPL",
    "gn:name":"M\u016bdabettu",
    "gn:population":0,
    "gn:timezone":"Asia/Kolkata",
    "iso:country":"IN",
    "ks:ks_name":"Moodabettu",
    "ks:ks_pop":4738,
    "ks:ks_type":"URBAN",
    "ks:ks_uagg_main":1,
    "name:eng_x_preferred":[
        "Moodabettu"
    ],
    "name:eng_x_variant":[
        "Mudabettu"
    ],
    "qs:name":"Moodabettu",
    "qs:name_adm0":"India",
    "qs:name_adm1":"Karnataka",
    "qs:photos":4,
    "qs:photos_1k":1,
    "qs:photos_9k":1,
    "qs:photos_9r":1,
    "qs:photos_all":4,
    "qs:photos_sr":1,
    "qs:placetype":"Town",
    "qs:pop_sr":"0",
    "wof:name":"Moodabettu",
    "wof:placetype":"locality",
    "wof:population":4738
},
  "geometry": {"coordinates":[74.75077,13.290414],"type":"Point"}
}