{
  "type": "Feature",
  "properties": {
    "gn:admin1_code":"34.0",
    "gn:admin2_code":"220.0",
    "gn:asciiname":"Narsinghpur Bagahi",
    "gn:country_code":"IN",
    "gn:dem":55,
    "gn:feature_class":"P",
    "gn:feature_code":"PPL",
    "gn:name":"Narsinghpur Bagahi",
    "gn:population":0,
    "gn:timezone":"Asia/Kolkata",
    "iso:country":"IN",
    "ks:ks_name":"Narsinghpur Bagahi",
    "ks:ks_pop":646,
    "ks:ks_type":"VILLAGE",
    "name:eng_x_preferred":[
        "Narsinghpur Bagahi"
    ],
    "wof:name":"Narsinghpur Bagahi",
    "wof:placetype":"locality",
    "wof:population":646
},
  "geometry": {"coordinates":[85.43128299999999,25.793565],"type":"Point"}
}