{
  "type": "Feature",
  "properties": {
    "gn:admin1_code":"34.0",
    "gn:admin2_code":"220.0",
    "gn:asciiname":"Narsinghpur Bagahi",
    "gn:country_code":"IN",
    "gn:dem":55,
    "gn:feature_class":"P",
    "gn:feature_code":"PPL",
    "gn:name":"Narsinghpur Bagahi",
    "gn:population":0,
    "gn:timezone":"Asia/Kolkata",
    "iso:country":"IN",
    "wof:name":"Narsinghpur Bagahi",
    "wof:placetype":"locality"
},
  "geometry": {"coordinates":[85.43128,25.79357000000001],"type":"Point"}
}