{
  "type": "Feature",
  "properties": {
    "iso:country":"IN",
    "ks:ks_name":"Gurandar",
    "ks:ks_pop":0,
    "ks:ks_type":"VILLAGE",
    "name:eng_x_preferred":[
        "Gurandar"
    ],
    "wof:name":"Gurandar",
    "wof:placetype":"locality",
    "wof:population":0
},
  "geometry": {"coordinates":[88.296081,25.268578],"type":"Point"}
}