{
  "type": "Feature",
  "properties": {
    "gn:admin1_code":"36",
    "gn:admin2_code":"180.0",
    "gn:asciiname":"Bulaki Purwa",
    "gn:country_code":"IN",
    "gn:dem":120,
    "gn:feature_class":"P",
    "gn:feature_code":"PPL",
    "gn:name":"Bul\u0101ki Purwa",
    "gn:population":0,
    "gn:timezone":"Asia/Kolkata",
    "iso:country":"IN",
    "wof:name":"Bulaki Purwa",
    "wof:placetype":"locality"
},
  "geometry": {"coordinates":[81.58379000000002,27.64196],"type":"Point"}
}