{
  "type": "Feature",
  "properties": {
    "iso:country":"IN",
    "ks:ks_name":"Mahua Kheda",
    "ks:ks_pop":115,
    "ks:ks_type":"HABITATION",
    "name:eng_x_preferred":[
        "Mahua Kheda"
    ],
    "wof:name":"Mahua Kheda",
    "wof:placetype":"locality",
    "wof:population":115
},
  "geometry": {"coordinates":[77.37036000000001,23.757856],"type":"Point"}
}