{
  "type": "Feature",
  "properties": {
    "gn:admin1_code":"11",
    "gn:admin2_code":"33.0",
    "gn:asciiname":"Sanjauli",
    "gn:country_code":"IN",
    "gn:dem":2092,
    "gn:feature_class":"P",
    "gn:feature_code":"PPL",
    "gn:name":"Sanjauli",
    "gn:population":0,
    "gn:timezone":"Asia/Kolkata",
    "iso:country":"IN",
    "name:pan_x_preferred":[
        "\u0a38\u0a70\u0a1c\u0a4c\u0a32\u0a40"
    ],
    "wof:name":"Sanjauli",
    "wof:placetype":"locality"
},
  "geometry": {"coordinates":[77.20108,31.10036],"type":"Point"}
}