{
  "type": "Feature",
  "properties": {
    "iso:country":"IN",
    "ks:ks_name":"Jiraulia",
    "ks:ks_pop":87,
    "ks:ks_type":"VILLAGE",
    "name:eng_x_preferred":[
        "Jiraulia"
    ],
    "wof:name":"Jiraulia",
    "wof:placetype":"locality",
    "wof:population":87
},
  "geometry": {"coordinates":[87.313087,24.504838],"type":"Point"}
}