{
  "type": "Feature",
  "properties": {
    "gn:admin1_code":"19.0",
    "gn:admin2_code":"571.0",
    "gn:asciiname":"Hanumantageri",
    "gn:country_code":"IN",
    "gn:dem":807,
    "gn:feature_class":"P",
    "gn:feature_code":"PPL",
    "gn:name":"Hanumantageri",
    "gn:population":0,
    "gn:timezone":"Asia/Kolkata",
    "iso:country":"IN",
    "wof:name":"Hanumantageri",
    "wof:placetype":"locality"
},
  "geometry": {"coordinates":[77.17928000000001,13.46958],"type":"Point"}
}