{
  "type": "Feature",
  "properties": {
    "iso:country":"IN",
    "ks:ks_name":"Sindurapur",
    "ks:ks_pop":68,
    "ks:ks_type":"VILLAGE",
    "name:eng_x_preferred":[
        "Sindurapur"
    ],
    "wof:name":"Sindurapur",
    "wof:placetype":"locality",
    "wof:population":68
},
  "geometry": {"coordinates":[84.64179900000001,19.223883],"type":"Point"}
}