{
  "type": "Feature",
  "properties": {
    "iso:country":"IN",
    "ks:ks_name":"Senkattur",
    "ks:ks_pop":262,
    "ks:ks_type":"HABITATION",
    "name:eng_x_preferred":[
        "Senkattur"
    ],
    "wof:name":"Senkattur",
    "wof:placetype":"locality",
    "wof:population":262
},
  "geometry": {"coordinates":[77.945335,11.789758],"type":"Point"}
}