{
  "type": "Feature",
  "properties": {
    "iso:country":"IN",
    "name:ara_x_preferred":[
        "\u062b\u064a\u0631\u063a\u0648\u0646"
    ],
    "name:ast_x_preferred":[
        "Thergaon"
    ],
    "name:ben_bn_x_preferred":[
        "\u09a5\u09c7\u09b0\u0997\u09be\u0981\u0993"
    ],
    "name:ben_in_x_preferred":[
        "\u09a5\u09c7\u09b0\u0997\u09be\u0981\u0993"
    ],
    "name:eng_x_preferred":[
        "Thergaon"
    ],
    "name:guj_x_preferred":[
        "\u0aa5\u0ac7\u0ab0\u0a97\u0abe\u0a82\u0ab5"
    ],
    "name:hin_x_preferred":[
        "\u0925\u0947\u0930\u0917\u093e\u0902\u0935"
    ],
    "name:kan_x_preferred":[
        "\u0ca5\u0cc7\u0cb0\u0ccd"
    ],
    "name:mal_x_preferred":[
        "\u0d24\u0d46\u0d7c\u0d17\u0d3e\u0d35\u0d4d"
    ],
    "name:mar_x_preferred":[
        "\u0925\u0947\u0930\u0917\u093e\u0935"
    ],
    "name:nld_x_preferred":[
        "Thergaon"
    ],
    "name:pan_x_preferred":[
        "\u0a25\u0a30\u0a17\u0a3e\u0a13\u0a02"
    ],
    "name:tam_x_preferred":[
        "\u0ba4\u0bc6\u0bb0\u0bcd\u0b95\u0bbe\u0bb5\u0bcd\u0ba9\u0bcd"
    ],
    "name:tel_x_preferred":[
        "\u0c25\u0c46\u0c30\u0c4d"
    ],
    "name:urd_x_preferred":[
        "\u062a\u06be\u06cc\u0631 \u06af\u0627\u0624\u06ba"
    ],
    "qs:name":"Thergaon",
    "qs:name_adm0":"India",
    "qs:name_adm1":"Maharashtra",
    "qs:photos":8,
    "qs:photos_1k":2,
    "qs:photos_9k":1,
    "qs:photos_9r":1,
    "qs:photos_all":8,
    "qs:photos_sr":1,
    "qs:placetype":"Suburb",
    "qs:pop_sr":"0",
    "wd:wordcount":420,
    "wof:name":"Thergaon",
    "wof:placetype":"neighbourhood"
},
  "geometry": {"coordinates":[73.7692455,18.6099075],"type":"Point"}
}