{
  "type": "Feature",
  "properties": {
    "iso:country":"IN",
    "name:ast_x_preferred":[
        "Thergaon"
    ],
    "name:eng_x_preferred":[
        "Thergaon"
    ],
    "name:nld_x_preferred":[
        "Thergaon"
    ],
    "qs:name":"Thergaon",
    "qs:name_adm0":"India",
    "qs:name_adm1":"Maharashtra",
    "qs:photos":8,
    "qs:photos_1k":2,
    "qs:photos_9k":1,
    "qs:photos_9r":1,
    "qs:photos_all":8,
    "qs:photos_sr":1,
    "qs:placetype":"Suburb",
    "qs:pop_sr":"0",
    "wd:wordcount":420,
    "wof:name":"Thergaon",
    "wof:placetype":"neighbourhood"
},
  "geometry": {"coordinates":[73.7692455,18.6099075],"type":"Point"}
}