{
  "type": "Feature",
  "properties": {
    "gn:admin1_code":"38.0",
    "gn:admin2_code":"358.0",
    "gn:asciiname":"Chapi",
    "gn:country_code":"IN",
    "gn:dem":272,
    "gn:feature_class":"P",
    "gn:feature_code":"PPL",
    "gn:name":"Ch\u0101p\u012b",
    "gn:population":0,
    "gn:timezone":"Asia/Kolkata",
    "iso:country":"IN",
    "ks:ks_name":"Chanpi",
    "ks:ks_pop":397,
    "ks:ks_type":"VILLAGE",
    "name:eng_x_preferred":[
        "Chanpi"
    ],
    "name:eng_x_variant":[
        "Chapi"
    ],
    "wof:name":"Chanpi",
    "wof:placetype":"locality",
    "wof:population":397
},
  "geometry": {"coordinates":[84.450085,24.286991],"type":"Point"}
}