{
  "type": "Feature",
  "properties": {
    "iso:country":"IN",
    "ks:ks_name":"Pipariya Luhar",
    "ks:ks_pop":111,
    "ks:ks_type":"URBAN",
    "name:eng_x_preferred":[
        "Pipariya Luhar"
    ],
    "wof:name":"Pipariya Luhar",
    "wof:placetype":"locality",
    "wof:population":111
},
  "geometry": {"coordinates":[79.252568,23.893343],"type":"Point"}
}