{
  "type": "Feature",
  "properties": {
    "gn:admin1_code":"7.0",
    "gn:admin2_code":"97.0",
    "gn:asciiname":"Nangli Sakraoti",
    "gn:country_code":"IN",
    "gn:dem":214,
    "gn:feature_class":"P",
    "gn:feature_code":"PPL",
    "gn:name":"N\u0101ngli Sakr\u0101oti",
    "gn:population":0,
    "gn:timezone":"Asia/Kolkata",
    "iso:country":"IN",
    "wof:name":"Nangli Sakraoti",
    "wof:placetype":"neighbourhood"
},
  "geometry": {"coordinates":[77.01823,28.62425],"type":"Point"}
}