{
  "type": "Feature",
  "properties": {
    "iso:country":"IN",
    "ks:ks_name":"Baraghata",
    "ks:ks_pop":284,
    "ks:ks_type":"VILLAGE",
    "name:eng_x_preferred":[
        "Baraghata"
    ],
    "wof:name":"Baraghata",
    "wof:placetype":"locality",
    "wof:population":284
},
  "geometry": {"coordinates":[87.475155,24.064436],"type":"Point"}
}