{
  "type": "Feature",
  "properties": {
    "gn:admin1_code":"36",
    "gn:admin2_code":"158.0",
    "gn:asciiname":"Sumeri Khera",
    "gn:country_code":"IN",
    "gn:dem":117,
    "gn:feature_class":"P",
    "gn:feature_code":"PPL",
    "gn:name":"Sumeri Khera",
    "gn:population":0,
    "gn:timezone":"Asia/Kolkata",
    "iso:country":"IN",
    "ks:ks_name":"Sumeri Khera",
    "ks:ks_pop":115,
    "ks:ks_type":"HABITATION",
    "ks:ks_uagg_main":0,
    "name:eng_x_preferred":[
        "Sumeri Khera"
    ],
    "wof:name":"Sumeri Khera",
    "wof:placetype":"neighbourhood",
    "wof:population":115
},
  "geometry": {"coordinates":[81.15324,26.510812],"type":"Point"}
}