{
  "type": "Feature",
  "properties": {
    "gn:admin1_code":"10.0",
    "gn:admin2_code":"88.0",
    "gn:asciiname":"Madalpur",
    "gn:country_code":"IN",
    "gn:dem":202,
    "gn:feature_class":"P",
    "gn:feature_code":"PPL",
    "gn:name":"M\u0101dalpur",
    "gn:population":0,
    "gn:timezone":"Asia/Kolkata",
    "iso:country":"IN",
    "wof:name":"Madalpur",
    "wof:placetype":"locality"
},
  "geometry": {"coordinates":[77.2576,28.32484],"type":"Point"}
}