{
  "type": "Feature",
  "properties": {
    "gn:admin1_code":"19.0",
    "gn:admin2_code":"573.0",
    "gn:asciiname":"Arenahalli",
    "gn:country_code":"IN",
    "gn:dem":815,
    "gn:feature_class":"P",
    "gn:feature_code":"PPL",
    "gn:name":"Arenahalli",
    "gn:population":0,
    "gn:timezone":"Asia/Kolkata",
    "iso:country":"IN",
    "wof:name":"Arenahalli",
    "wof:placetype":"locality"
},
  "geometry": {"coordinates":[76.36993000000002,12.66226],"type":"Point"}
}