{
  "type": "Feature",
  "properties": {
    "gn:admin1_code":"39.0",
    "gn:admin2_code":"60.0",
    "gn:asciiname":"Kotla",
    "gn:country_code":"IN",
    "gn:dem":1243,
    "gn:feature_class":"P",
    "gn:feature_code":"PPL",
    "gn:name":"Kotla",
    "gn:population":0,
    "gn:timezone":"Asia/Kolkata",
    "iso:country":"IN",
    "ks:ks_name":"Kotala",
    "ks:ks_pop":47,
    "ks:ks_type":"VILLAGE",
    "name:eng_x_preferred":[
        "Kotala"
    ],
    "name:eng_x_variant":[
        "Kotla"
    ],
    "wof:name":"Kotala",
    "wof:placetype":"locality",
    "wof:population":47
},
  "geometry": {"coordinates":[78.23334,30.267401],"type":"Point"}
}