{
  "type": "Feature",
  "properties": {
    "iso:country":"IN",
    "ks:ks_name":"Udlakone",
    "ks:ks_pop":43,
    "ks:ks_type":"HABITATION",
    "name:eng_x_preferred":[
        "Udlakone"
    ],
    "wof:name":"Udlakone",
    "wof:placetype":"locality",
    "wof:population":43
},
  "geometry": {"coordinates":[74.73738899999999,14.309711],"type":"Point"}
}