{
  "type": "Feature",
  "properties": {
    "gn:admin1_code":"35.0",
    "gn:admin2_code":"467",
    "gn:asciiname":"Dhertalai",
    "gn:country_code":"IN",
    "gn:dem":306,
    "gn:feature_class":"P",
    "gn:feature_code":"PPL",
    "gn:name":"Dhertalai",
    "gn:population":0,
    "gn:timezone":"Asia/Kolkata",
    "iso:country":"IN",
    "wof:name":"Dhertalai",
    "wof:placetype":"neighbourhood"
},
  "geometry": {"coordinates":[76.76178,21.49527],"type":"Point"}
}