{
  "type": "Feature",
  "properties": {
    "iso:country":"IN",
    "ks:ks_name":"Hariram Purwa",
    "ks:ks_pop":120,
    "ks:ks_type":"HABITATION",
    "name:eng_x_preferred":[
        "Hariram Purwa"
    ],
    "wof:name":"Hariram Purwa",
    "wof:placetype":"locality",
    "wof:population":120
},
  "geometry": {"coordinates":[79.997939,26.814787],"type":"Point"}
}