{
  "type": "Feature",
  "properties": {
    "iso:country":"IN",
    "ks:ks_name":"Pura Jhoriyan",
    "ks:ks_pop":232,
    "ks:ks_type":"HABITATION",
    "name:eng_x_preferred":[
        "Pura Jhoriyan"
    ],
    "wof:name":"Pura Jhoriyan",
    "wof:placetype":"locality",
    "wof:population":232
},
  "geometry": {"coordinates":[78.345341,26.927521],"type":"Point"}
}