{
  "type": "Feature",
  "properties": {
    "iso:country":"IN",
    "ks:ks_name":"Rawatsar",
    "ks:ks_pop":1071,
    "ks:ks_type":"HABITATION",
    "name:eng_x_preferred":[
        "Rawatsar"
    ],
    "wof:name":"Rawatsar",
    "wof:placetype":"locality",
    "wof:population":1071
},
  "geometry": {"coordinates":[70.30035599999999,25.828578],"type":"Point"}
}