{
  "type": "Feature",
  "properties": {
    "iso:country":"IN",
    "ks:ks_name":"Luhakhamba",
    "ks:ks_pop":0,
    "ks:ks_type":"VILLAGE",
    "name:eng_x_preferred":[
        "Luhakhamba"
    ],
    "wof:name":"Luhakhamba",
    "wof:placetype":"locality",
    "wof:population":0
},
  "geometry": {"coordinates":[83.70420799999999,19.496858],"type":"Point"}
}