{
  "type": "Feature",
  "properties": {
    "iso:country":"IN",
    "ks:ks_name":"Manikpur",
    "ks:ks_pop":240,
    "ks:ks_type":"VILLAGE",
    "ks:ks_uagg_main":0,
    "name:eng_x_preferred":[
        "Manikpur"
    ],
    "wof:name":"Manikpur",
    "wof:placetype":"neighbourhood",
    "wof:population":240
},
  "geometry": {"coordinates":[86.02617600000001,20.180136],"type":"Point"}
}