{
  "type": "Feature",
  "properties": {
    "iso:country":"IN",
    "ks:ks_name":"Shakuntaleshwar",
    "ks:ks_pop":340,
    "ks:ks_type":"HABITATION",
    "name:eng_x_preferred":[
        "Shakuntaleshwar"
    ],
    "wof:name":"Shakuntaleshwar",
    "wof:placetype":"locality",
    "wof:population":340
},
  "geometry": {"coordinates":[74.051528,17.752708],"type":"Point"}
}