{
  "type": "Feature",
  "properties": {
    "iso:country":"IN",
    "ks:ks_name":"Khidkia Khurd",
    "ks:ks_pop":217,
    "ks:ks_type":"HABITATION",
    "name:eng_x_preferred":[
        "Khidkia Khurd"
    ],
    "wof:name":"Khidkia Khurd",
    "wof:placetype":"locality",
    "wof:population":217
},
  "geometry": {"coordinates":[75.187504,22.45666],"type":"Point"}
}