{
  "type": "Feature",
  "properties": {
    "iso:country":"IN",
    "ks:ks_name":"Tendudand",
    "ks:ks_pop":353,
    "ks:ks_type":"HABITATION",
    "name:eng_x_preferred":[
        "Tendudand"
    ],
    "wof:name":"Tendudand",
    "wof:placetype":"locality",
    "wof:population":353
},
  "geometry": {"coordinates":[83.55582,22.816623],"type":"Point"}
}