{
  "type": "Feature",
  "properties": {
    "iso:country":"IN",
    "ks:ks_alt_nam":"Vishaka Harijana wada",
    "ks:ks_name":"Vishaka Harijana Wada",
    "ks:ks_pop":129,
    "ks:ks_type":"HABITATION",
    "name:eng_x_preferred":[
        "Vishaka Harijana Wada"
    ],
    "wof:name":"Vishaka Harijana Wada",
    "wof:placetype":"locality",
    "wof:population":129
},
  "geometry": {"coordinates":[80.15674199999999,14.507708],"type":"Point"}
}