{
  "type": "Feature",
  "properties": {
    "iso:country":"IN",
    "ks:ks_alt_nam":"Saletola-Gondpara",
    "ks:ks_name":"Saletola-gondpara",
    "ks:ks_pop":865,
    "ks:ks_type":"HABITATION",
    "name:eng_x_preferred":[
        "Saletola-gondpara"
    ],
    "wof:name":"Saletola-gondpara",
    "wof:placetype":"locality",
    "wof:population":865
},
  "geometry": {"coordinates":[80.817032,20.063814],"type":"Point"}
}