{
  "type": "Feature",
  "properties": {
    "gn:admin1_code":"16",
    "gn:admin2_code":"504.0",
    "gn:asciiname":"Girgaon",
    "gn:country_code":"IN",
    "gn:dem":236,
    "gn:feature_class":"P",
    "gn:feature_code":"PPL",
    "gn:name":"Girgaon",
    "gn:population":0,
    "gn:timezone":"Asia/Kolkata",
    "iso:country":"IN",
    "name:fra_x_preferred":[
        "Girgaon"
    ],
    "name:kan_x_preferred":[
        "\u0c97\u0cbf\u0cb0\u0ccd\u200d\u0c97\u0cbe\u0c82\u0cb5\u0ccd"
    ],
    "name:mar_x_preferred":[
        "\u0917\u093f\u0930\u0917\u093e\u0935"
    ],
    "wof:name":"Girgaon",
    "wof:placetype":"locality"
},
  "geometry": {"coordinates":[79.09423000000002,20.47666],"type":"Point"}
}