{
  "type": "Feature",
  "properties": {
    "iso:country":"IN",
    "ks:ks_name":"Chakasridharpur",
    "ks:ks_pop":789,
    "ks:ks_type":"VILLAGE",
    "name:eng_x_preferred":[
        "Chakasridharpur"
    ],
    "wof:name":"Chakasridharpur",
    "wof:placetype":"locality",
    "wof:population":789
},
  "geometry": {"coordinates":[86.56121400000001,21.011304],"type":"Point"}
}