{
  "type": "Feature",
  "properties": {
    "iso:country":"IN",
    "ks:ks_alt_nam":"Poosaruthasan valavu",
    "ks:ks_name":"Poosaruthasan Valavu",
    "ks:ks_pop":665,
    "ks:ks_type":"HABITATION",
    "name:eng_x_preferred":[
        "Poosaruthasan Valavu"
    ],
    "wof:name":"Poosaruthasan Valavu",
    "wof:placetype":"locality",
    "wof:population":665
},
  "geometry": {"coordinates":[77.881874,11.72266],"type":"Point"}
}