{
  "type": "Feature",
  "properties": {
    "iso:country":"IN",
    "ks:ks_name":"Mahulaiya",
    "ks:ks_pop":355,
    "ks:ks_type":"VILLAGE",
    "ks:ks_uagg_main":0,
    "name:eng_x_preferred":[
        "Mahulaiya"
    ],
    "wof:name":"Mahulaiya",
    "wof:placetype":"neighbourhood",
    "wof:population":355
},
  "geometry": {"coordinates":[83.647251,26.78435],"type":"Point"}
}