{
  "type": "Feature",
  "properties": {
    "gn:admin1_code":"40.0",
    "gn:admin2_code":"539",
    "gn:asciiname":"Jangaon",
    "gn:country_code":"IN",
    "gn:dem":341,
    "gn:feature_class":"P",
    "gn:feature_code":"PPL",
    "gn:name":"Jangaon",
    "gn:population":0,
    "gn:timezone":"Asia/Kolkata",
    "iso:country":"IN",
    "name:bpy_x_preferred":[
        "\u099c\u09be\u09a8\u0997\u09be\u0981\u0993"
    ],
    "name:ceb_x_preferred":[
        "Jangaon"
    ],
    "name:hif_x_preferred":[
        "Jangaon"
    ],
    "name:hin_x_preferred":[
        "\u091c\u0928\u0917\u093e\u0901\u0935"
    ],
    "name:ita_x_preferred":[
        "Jangaon"
    ],
    "name:msa_x_preferred":[
        "Jangaon"
    ],
    "name:new_x_preferred":[
        "\u091c\u0919\u094d\u0917\u093e\u0902\u0935"
    ],
    "name:nld_x_preferred":[
        "Jangaon"
    ],
    "name:ori_x_preferred":[
        "\u0b1c\u0b28\u0b17\u0b3e\u0b01"
    ],
    "name:por_x_preferred":[
        "Jangaon"
    ],
    "name:tel_x_preferred":[
        "\u0c1c\u0c28\u0c17\u0c3e\u0c02"
    ],
    "name:urd_x_preferred":[
        "\u062c\u0646\u06af\u0627\u0648\u06ba"
    ],
    "name:vie_x_preferred":[
        "Jangaon"
    ],
    "name:zho_x_preferred":[
        "\u59dc\u683c\u963f\u5965\u6069"
    ],
    "wof:name":"Jangaon",
    "wof:placetype":"neighbourhood"
},
  "geometry": {"coordinates":[78.89870999999999,17.11213],"type":"Point"}
}