{
  "type": "Feature",
  "properties": {
    "gn:admin1_code":"39.0",
    "gn:admin2_code":"57.0",
    "gn:asciiname":"Singdhar",
    "gn:country_code":"IN",
    "gn:dem":1733,
    "gn:feature_class":"P",
    "gn:feature_code":"PPL",
    "gn:name":"Singdh\u0101r",
    "gn:population":0,
    "gn:timezone":"Asia/Kolkata",
    "iso:country":"IN",
    "wof:name":"Singdhar",
    "wof:placetype":"locality"
},
  "geometry": {"coordinates":[79.55214000000002,30.55921],"type":"Point"}
}