{
  "type": "Feature",
  "properties": {
    "iso:country":"IN",
    "ks:ks_name":"Sahapur",
    "ks:ks_pop":2679,
    "ks:ks_type":"VILLAGE",
    "name:eng_x_preferred":[
        "Sahapur"
    ],
    "wof:name":"Sahapur",
    "wof:placetype":"locality",
    "wof:population":2679
},
  "geometry": {"coordinates":[87.63303999999999,22.0756],"type":"Point"}
}