{
  "type": "Feature",
  "properties": {
    "iso:country":"IN",
    "ks:ks_name":"Nawada Majra",
    "ks:ks_pop":59,
    "ks:ks_type":"HABITATION",
    "name:eng_x_preferred":[
        "Nawada Majra"
    ],
    "wof:name":"Nawada Majra",
    "wof:placetype":"locality",
    "wof:population":59
},
  "geometry": {"coordinates":[77.412066,29.747857],"type":"Point"}
}