{
  "type": "Feature",
  "properties": {
    "gn:admin1_code":"36",
    "gn:admin2_code":"167.0",
    "gn:asciiname":"Baroda Dang",
    "gn:country_code":"IN",
    "gn:dem":321,
    "gn:feature_class":"P",
    "gn:feature_code":"PPL",
    "gn:name":"Baroda D\u0101ng",
    "gn:population":0,
    "gn:timezone":"Asia/Kolkata",
    "iso:country":"IN",
    "ks:ks_name":"Barauda Dang",
    "ks:ks_pop":4079,
    "ks:ks_type":"VILLAGE",
    "name:eng_x_preferred":[
        "Barauda Dang"
    ],
    "name:eng_x_variant":[
        "Baroda Dang"
    ],
    "wof:name":"Barauda Dang",
    "wof:placetype":"locality",
    "wof:population":4079
},
  "geometry": {"coordinates":[78.54039,24.933207],"type":"Point"}
}