{
  "type": "Feature",
  "properties": {
    "gn:admin1_code":"35.0",
    "gn:admin2_code":"439.0",
    "gn:asciiname":"Bargaunda",
    "gn:country_code":"IN",
    "gn:dem":629,
    "gn:feature_class":"P",
    "gn:feature_code":"PPL",
    "gn:name":"Bargaunda",
    "gn:population":0,
    "gn:timezone":"Asia/Kolkata",
    "iso:country":"IN",
    "wof:name":"Bargaunda",
    "wof:placetype":"locality"
},
  "geometry": {"coordinates":[75.73818,22.46962000000001],"type":"Point"}
}