{
  "type": "Feature",
  "properties": {
    "iso:country":"IN",
    "ks:ks_name":"Chiraijharia",
    "ks:ks_pop":200,
    "ks:ks_type":"HABITATION",
    "name:eng_x_preferred":[
        "Chiraijharia"
    ],
    "wof:name":"Chiraijharia",
    "wof:placetype":"locality",
    "wof:population":200
},
  "geometry": {"coordinates":[82.993135,22.205172],"type":"Point"}
}