{
  "type": "Feature",
  "properties": {
    "iso:country":"IN",
    "ks:ks_name":"Bilagodi",
    "ks:ks_pop":321,
    "ks:ks_type":"HABITATION",
    "name:eng_x_preferred":[
        "Bilagodi"
    ],
    "wof:name":"Bilagodi",
    "wof:placetype":"locality",
    "wof:population":321
},
  "geometry": {"coordinates":[74.73397799999999,14.038776],"type":"Point"}
}