{
  "type": "Feature",
  "properties": {
    "gn:admin1_code":"11",
    "gn:admin2_code":"33.0",
    "gn:asciiname":"Shaliawol",
    "gn:country_code":"IN",
    "gn:dem":1929,
    "gn:feature_class":"P",
    "gn:feature_code":"PPL",
    "gn:name":"Shali\u0101wol",
    "gn:population":0,
    "gn:timezone":"Asia/Kolkata",
    "iso:country":"IN",
    "wof:name":"Shaliawol",
    "wof:placetype":"locality"
},
  "geometry": {"coordinates":[77.22196,31.16143],"type":"Point"}
}