{
  "type": "Feature",
  "properties": {
    "iso:country":"IN",
    "ks:ks_alt_nam":"Kakkan colony",
    "ks:ks_name":"Kakkan Colony",
    "ks:ks_pop":7660,
    "ks:ks_type":"HABITATION",
    "name:eng_x_preferred":[
        "Kakkan Colony"
    ],
    "wof:name":"Kakkan Colony",
    "wof:placetype":"locality",
    "wof:population":7660
},
  "geometry": {"coordinates":[78.258363,9.895902],"type":"Point"}
}