{
  "type": "Feature",
  "properties": {
    "iso:country":"IN",
    "ks:ks_name":"Talkola",
    "ks:ks_pop":671,
    "ks:ks_type":"VILLAGE",
    "name:eng_x_preferred":[
        "Talkola"
    ],
    "wof:name":"Talkola",
    "wof:placetype":"locality",
    "wof:population":671
},
  "geometry": {"coordinates":[88.746636,23.005075],"type":"Point"}
}