{
  "type": "Feature",
  "properties": {
    "iso:country":"IN",
    "ks:ks_name":"Yadava Basti",
    "ks:ks_pop":202,
    "ks:ks_type":"HABITATION",
    "name:eng_x_preferred":[
        "Yadava Basti"
    ],
    "wof:name":"Yadava Basti",
    "wof:placetype":"locality",
    "wof:population":202
},
  "geometry": {"coordinates":[82.16402600000001,25.501091],"type":"Point"}
}