{
  "type": "Feature",
  "properties": {
    "gn:admin1_code":"36",
    "gn:admin2_code":"198.0",
    "gn:asciiname":"Karigaon",
    "gn:country_code":"IN",
    "gn:dem":89,
    "gn:feature_class":"P",
    "gn:feature_code":"PPL",
    "gn:name":"K\u0101r\u012bgaon",
    "gn:population":0,
    "gn:timezone":"Asia/Kolkata",
    "iso:country":"IN",
    "ks:ks_alt_nam":"K\u0101r\u012bgaon",
    "ks:ks_name":"Karigaon",
    "ks:ks_pop":3727,
    "ks:ks_type":"VILLAGE",
    "name:eng_x_preferred":[
        "Karigaon"
    ],
    "name:eng_x_variant":[
        "K\u0101r\u012bgaon"
    ],
    "wof:name":"Karigaon",
    "wof:placetype":"locality",
    "wof:population":3727
},
  "geometry": {"coordinates":[82.38196499999999,25.365078],"type":"Point"}
}