{
  "type": "Feature",
  "properties": {
    "gn:admin1_code":"36",
    "gn:admin2_code":"199.0",
    "gn:asciiname":"Tendui",
    "gn:country_code":"IN",
    "gn:dem":96,
    "gn:feature_class":"P",
    "gn:feature_code":"PPL",
    "gn:name":"Tendui",
    "gn:population":0,
    "gn:timezone":"Asia/Kolkata",
    "iso:country":"IN",
    "ks:ks_name":"Tendui",
    "ks:ks_type":"VILLAGE",
    "name:eng_x_preferred":[
        "Tendui"
    ],
    "wof:name":"Tendui",
    "wof:placetype":"locality"
},
  "geometry": {"coordinates":[83.05573800000001,25.006834],"type":"Point"}
}