{
  "type": "Feature",
  "properties": {
    "iso:country":"IN",
    "ks:ks_name":"Dandiposi",
    "ks:ks_pop":503,
    "ks:ks_type":"HABITATION",
    "name:eng_x_preferred":[
        "Dandiposi"
    ],
    "wof:name":"Dandiposi",
    "wof:placetype":"locality",
    "wof:population":503
},
  "geometry": {"coordinates":[85.74302,21.588377],"type":"Point"}
}