{
  "type": "Feature",
  "properties": {
    "iso:country":"IN",
    "ks:ks_name":"Gadharia Pathar",
    "ks:ks_pop":661,
    "ks:ks_type":"VILLAGE",
    "ks:ks_uagg_main":0,
    "name:eng_x_preferred":[
        "Gadharia Pathar"
    ],
    "wof:name":"Gadharia Pathar",
    "wof:placetype":"neighbourhood",
    "wof:population":661
},
  "geometry": {"coordinates":[93.466032,26.814904],"type":"Point"}
}