{
  "type": "Feature",
  "properties": {
    "iso:country":"IN",
    "ks:ks_name":"Miya Tola",
    "ks:ks_pop":309,
    "ks:ks_type":"HABITATION",
    "name:eng_x_preferred":[
        "Miya Tola"
    ],
    "wof:name":"Miya Tola",
    "wof:placetype":"locality",
    "wof:population":309
},
  "geometry": {"coordinates":[84.656198,27.085853],"type":"Point"}
}