{
  "type": "Feature",
  "properties": {
    "iso:country":"IN",
    "ks:ks_name":"Amanat Manullah Subedar",
    "ks:ks_pop":0,
    "ks:ks_type":"VILLAGE",
    "name:eng_x_preferred":[
        "Amanat Manullah Subedar"
    ],
    "wof:name":"Amanat Manullah Subedar",
    "wof:placetype":"locality",
    "wof:population":0
},
  "geometry": {"coordinates":[86.979527,25.524387],"type":"Point"}
}