{
  "type": "Feature",
  "properties": {
    "gn:admin1_code":"36",
    "gn:admin2_code":"196.0",
    "gn:asciiname":"Majhgawan",
    "gn:country_code":"IN",
    "gn:dem":300,
    "gn:feature_class":"P",
    "gn:feature_code":"PPL",
    "gn:name":"Majhg\u0101w\u0101n",
    "gn:population":0,
    "gn:timezone":"Asia/Kolkata",
    "iso:country":"IN",
    "wof:name":"Majhgawan",
    "wof:placetype":"locality"
},
  "geometry": {"coordinates":[83.17341999999999,24.77462],"type":"Point"}
}