{
  "type": "Feature",
  "properties": {
    "gn:admin1_code":"36",
    "gn:admin2_code":"196.0",
    "gn:asciiname":"Majhgawan",
    "gn:country_code":"IN",
    "gn:dem":300,
    "gn:feature_class":"P",
    "gn:feature_code":"PPL",
    "gn:name":"Majhg\u0101w\u0101n",
    "gn:population":0,
    "gn:timezone":"Asia/Kolkata",
    "iso:country":"IN",
    "ks:ks_alt_nam":"Majhg\u0101w\u0101n",
    "ks:ks_name":"Majhgawan",
    "ks:ks_pop":150,
    "ks:ks_type":"VILLAGE",
    "name:eng_x_preferred":[
        "Majhgawan"
    ],
    "name:eng_x_variant":[
        "Majhg\u0101w\u0101n"
    ],
    "name:hin_x_preferred":[
        "\u092e\u091d\u0917\u0935\u093e\u0902"
    ],
    "wof:name":"Majhgawan",
    "wof:placetype":"locality",
    "wof:population":150
},
  "geometry": {"coordinates":[83.174049,24.775791],"type":"Point"}
}