{
  "type": "Feature",
  "properties": {
    "iso:country":"IN",
    "ks:ks_name":"Lakrapahari",
    "ks:ks_pop":26,
    "ks:ks_type":"VILLAGE",
    "ks:ks_uagg_main":0,
    "name:eng_x_preferred":[
        "Lakrapahari"
    ],
    "wof:name":"Lakrapahari",
    "wof:placetype":"neighbourhood",
    "wof:population":26
},
  "geometry": {"coordinates":[85.90043799999999,22.686508],"type":"Point"}
}