{
  "type": "Feature",
  "properties": {
    "gn:admin1_code":"19.0",
    "gn:admin2_code":"577.0",
    "gn:asciiname":"Jalhalli",
    "gn:country_code":"IN",
    "gn:dem":709,
    "gn:feature_class":"P",
    "gn:feature_code":"PPL",
    "gn:name":"Jalhalli",
    "gn:population":0,
    "gn:timezone":"Asia/Kolkata",
    "iso:country":"IN",
    "ks:ks_name":"Jalahalli",
    "ks:ks_pop":221,
    "ks:ks_type":"VILLAGE",
    "name:eng_x_preferred":[
        "Jalahalli"
    ],
    "name:eng_x_variant":[
        "Jalhalli"
    ],
    "name:urd_x_preferred":[
        "\u062c\u0644\u06be\u0644\u0644\u06cc"
    ],
    "wof:name":"Jalahalli",
    "wof:placetype":"locality",
    "wof:population":221
},
  "geometry": {"coordinates":[76.49068800000001,11.996567],"type":"Point"}
}