{
  "type": "Feature",
  "properties": {
    "gn:admin1_code":"10.0",
    "gn:admin2_code":"074",
    "gn:asciiname":"Jhinwar Heri",
    "gn:country_code":"IN",
    "gn:dem":244,
    "gn:feature_class":"P",
    "gn:feature_code":"PPL",
    "gn:name":"Jhinwar Heri",
    "gn:population":0,
    "gn:timezone":"Asia/Kolkata",
    "iso:country":"IN",
    "name:und_x_variant":[
        "Jh\u012bnwarheri"
    ],
    "wof:name":"Jhinwar Heri",
    "wof:placetype":"locality"
},
  "geometry": {"coordinates":[76.96429999999999,29.59152000000001],"type":"Point"}
}