{
  "type": "Feature",
  "properties": {
    "iso:country":"IN",
    "ks:ks_name":"Taisar",
    "ks:ks_pop":7117,
    "ks:ks_type":"VILLAGE",
    "name:eng_x_preferred":[
        "Taisar"
    ],
    "wof:name":"Taisar",
    "wof:placetype":"locality",
    "wof:population":7117
},
  "geometry": {"coordinates":[84.180358,22.486701],"type":"Point"}
}