{
  "type": "Feature",
  "properties": {
    "gn:admin1_code":"23.0",
    "gn:admin2_code":"36.0",
    "gn:asciiname":"Sial",
    "gn:country_code":"IN",
    "gn:dem":222,
    "gn:feature_class":"P",
    "gn:feature_code":"PPL",
    "gn:name":"Si\u0101l",
    "gn:population":0,
    "gn:timezone":"Asia/Kolkata",
    "iso:country":"IN",
    "name:ara_x_preferred":[
        "\u0635\u062e\u0648\u0631 \u0627\u0644\u0633\u064a\u0627\u0644"
    ],
    "name:est_x_preferred":[
        "Graniidikiht"
    ],
    "name:fas_x_preferred":[
        "\u0633\u06cc\u0627\u0644"
    ],
    "name:fin_x_preferred":[
        "Sial"
    ],
    "name:fra_x_preferred":[
        "Sial"
    ],
    "name:gle_x_preferred":[
        "Sial"
    ],
    "name:heb_x_preferred":[
        "\u05e1\u05d9\u05d0\u05dc"
    ],
    "name:ita_x_preferred":[
        "Sial"
    ],
    "name:jpn_x_preferred":[
        "\u30b7\u30a2\u30eb"
    ],
    "name:nno_x_preferred":[
        "Sial"
    ],
    "name:pol_x_preferred":[
        "Sial"
    ],
    "name:slk_x_preferred":[
        "Sial"
    ],
    "name:spa_x_preferred":[
        "Sial"
    ],
    "name:tha_x_preferred":[
        "\u0e2b\u0e34\u0e19\u0e44\u0e0b\u0e2d\u0e31\u0e25"
    ],
    "name:zho_x_preferred":[
        "\u7845\u94dd\u5c42"
    ],
    "wof:name":"Sial",
    "wof:placetype":"locality"
},
  "geometry": {"coordinates":[75.33818000000002,31.27414000000001],"type":"Point"}
}