{
  "type": "Feature",
  "properties": {
    "iso:country":"IN",
    "ks:ks_name":"Shukulpura",
    "ks:ks_pop":25,
    "ks:ks_type":"VILLAGE",
    "ks:ks_uagg_main":0,
    "name:eng_x_preferred":[
        "Shukulpura"
    ],
    "wof:name":"Shukulpura",
    "wof:placetype":"locality",
    "wof:population":25
},
  "geometry": {"coordinates":[84.809802,25.762963],"type":"Point"}
}