{
  "type": "Feature",
  "properties": {
    "iso:country":"IN",
    "ks:ks_name":"Mayanewadi",
    "ks:ks_pop":27,
    "ks:ks_type":"HABITATION",
    "name:eng_x_preferred":[
        "Mayanewadi"
    ],
    "wof:name":"Mayanewadi",
    "wof:placetype":"locality",
    "wof:population":27
},
  "geometry": {"coordinates":[73.487551,16.149154],"type":"Point"}
}