{
  "type": "Feature",
  "properties": {
    "gn:admin1_code":"38",
    "gn:admin2_code":"350.0",
    "gn:asciiname":"Thari Sonarai",
    "gn:country_code":"IN",
    "gn:dem":263,
    "gn:feature_class":"P",
    "gn:feature_code":"PPL",
    "gn:name":"Thari Sonarai",
    "gn:population":0,
    "gn:timezone":"Asia/Kolkata",
    "iso:country":"IN",
    "wof:name":"Thari Sonarai",
    "wof:placetype":"locality"
},
  "geometry": {"coordinates":[86.89742,24.36305],"type":"Point"}
}