{
  "type": "Feature",
  "properties": {
    "gn:admin1_code":"36.0",
    "gn:admin2_code":"175.0",
    "gn:asciiname":"Kuria",
    "gn:country_code":"IN",
    "gn:dem":98,
    "gn:feature_class":"P",
    "gn:feature_code":"PPL",
    "gn:name":"Kuria",
    "gn:population":0,
    "gn:timezone":"Asia/Kolkata",
    "iso:country":"IN",
    "name:ceb_x_preferred":[
        "Kuria"
    ],
    "name:deu_x_preferred":[
        "Kuria"
    ],
    "name:fra_x_preferred":[
        "Kuria"
    ],
    "name:nld_x_preferred":[
        "Kuria"
    ],
    "name:pol_x_preferred":[
        "Kuria"
    ],
    "name:por_x_preferred":[
        "Kuria"
    ],
    "name:swe_x_preferred":[
        "Kuria"
    ],
    "wof:name":"Kuria",
    "wof:placetype":"locality"
},
  "geometry": {"coordinates":[81.90716,25.35413],"type":"Point"}
}