{
  "type": "Feature",
  "properties": {
    "iso:country":"IN",
    "ks:ks_name":"Melanapathukudusu",
    "ks:ks_pop":88,
    "ks:ks_type":"HABITATION",
    "name:eng_x_preferred":[
        "Melanapathukudusu"
    ],
    "wof:name":"Melanapathukudusu",
    "wof:placetype":"locality",
    "wof:population":88
},
  "geometry": {"coordinates":[77.475938,9.749399],"type":"Point"}
}