{
  "type": "Feature",
  "properties": {
    "iso:country":"IN",
    "ks:ks_alt_nam":"Dhatha west",
    "ks:ks_name":"Dhatha West",
    "ks:ks_pop":1403,
    "ks:ks_type":"HABITATION",
    "ks:ks_uagg_main":0,
    "name:eng_x_preferred":[
        "Dhatha West"
    ],
    "wof:name":"Dhatha West",
    "wof:placetype":"neighbourhood",
    "wof:population":1403
},
  "geometry": {"coordinates":[86.05144799999999,25.781859],"type":"Point"}
}