{
  "type": "Feature",
  "properties": {
    "iso:country":"IN",
    "ks:ks_name":"Battanjaddi",
    "ks:ks_pop":19,
    "ks:ks_type":"HABITATION",
    "name:eng_x_preferred":[
        "Battanjaddi"
    ],
    "wof:name":"Battanjaddi",
    "wof:placetype":"locality",
    "wof:population":19
},
  "geometry": {"coordinates":[74.732468,14.426919],"type":"Point"}
}