{
  "type": "Feature",
  "properties": {
    "iso:country":"IN",
    "ks:ks_name":"Dhudhmaniya",
    "ks:ks_pop":362,
    "ks:ks_type":"HABITATION",
    "name:eng_x_preferred":[
        "Dhudhmaniya"
    ],
    "wof:name":"Dhudhmaniya",
    "wof:placetype":"locality",
    "wof:population":362
},
  "geometry": {"coordinates":[81.63408800000001,24.347833],"type":"Point"}
}