{
  "type": "Feature",
  "properties": {
    "iso:country":"IN",
    "ks:ks_name":"Hanuman Nagar",
    "ks:ks_pop":126,
    "ks:ks_type":"HABITATION",
    "name:eng_x_preferred":[
        "Hanuman Nagar"
    ],
    "wof:name":"Hanuman Nagar",
    "wof:placetype":"locality",
    "wof:population":126
},
  "geometry": {"coordinates":[74.175631,19.053512],"type":"Point"}
}