{
  "type": "Feature",
  "properties": {
    "iso:country":"IN",
    "ks:ks_alt_nam":"All\u0101laperi",
    "ks:ks_name":"Allalaperi",
    "ks:ks_pop":690,
    "ks:ks_type":"VILLAGE",
    "name:eng_x_preferred":[
        "Allalaperi"
    ],
    "name:eng_x_variant":[
        "All\u0101laperi"
    ],
    "wof:name":"Allalaperi",
    "wof:placetype":"locality",
    "wof:population":690
},
  "geometry": {"coordinates":[78.180902,9.642508],"type":"Point"}
}