{
  "type": "Feature",
  "properties": {
    "gn:admin1_code":"12.0",
    "gn:admin2_code":"16.0",
    "gn:asciiname":"Kundabaggi",
    "gn:country_code":"IN",
    "gn:dem":2781,
    "gn:feature_class":"P",
    "gn:feature_code":"PPL",
    "gn:name":"Kundabaggi",
    "gn:population":0,
    "gn:timezone":"Asia/Kolkata",
    "iso:country":"IN",
    "wof:name":"Kundabaggi",
    "wof:placetype":"locality"
},
  "geometry": {"coordinates":[75.40394999999999,33.27318],"type":"Point"}
}