{
  "type": "Feature",
  "properties": {
    "iso:country":"IN",
    "ks:ks_name":"Fanasinamal",
    "ks:ks_pop":74,
    "ks:ks_type":"HABITATION",
    "name:eng_x_preferred":[
        "Fanasinamal"
    ],
    "wof:name":"Fanasinamal",
    "wof:placetype":"locality",
    "wof:population":74
},
  "geometry": {"coordinates":[73.298444,20.643917],"type":"Point"}
}