{
  "type": "Feature",
  "properties": {
    "iso:country":"IN",
    "ks:ks_name":"Dahisar T Tarapur",
    "ks:ks_pop":339,
    "ks:ks_type":"HABITATION",
    "ks:ks_uagg_main":0,
    "name:eng_x_preferred":[
        "Dahisar T Tarapur"
    ],
    "wof:name":"Dahisar T Tarapur",
    "wof:placetype":"neighbourhood",
    "wof:population":339
},
  "geometry": {"coordinates":[72.72535999999999,19.849506],"type":"Point"}
}