{
  "type": "Feature",
  "properties": {
    "iso:country":"IN",
    "ks:ks_name":"Teemulabanda",
    "ks:ks_pop":216,
    "ks:ks_type":"HABITATION",
    "name:eng_x_preferred":[
        "Teemulabanda"
    ],
    "wof:name":"Teemulabanda",
    "wof:placetype":"locality",
    "wof:population":216
},
  "geometry": {"coordinates":[82.255201,17.786495],"type":"Point"}
}