{
  "type": "Feature",
  "properties": {
    "iso:country":"IN",
    "ks:ks_name":"Kachari Para",
    "ks:ks_pop":2077,
    "ks:ks_type":"HABITATION",
    "name:eng_x_preferred":[
        "Kachari Para"
    ],
    "wof:name":"Kachari Para",
    "wof:placetype":"locality",
    "wof:population":2077
},
  "geometry": {"coordinates":[88.173613,21.958944],"type":"Point"}
}