{
  "type": "Feature",
  "properties": {
    "iso:country":"IN",
    "ks:ks_alt_nam":"GUDLIGUTU",
    "ks:ks_name":"Gudligutu",
    "ks:ks_pop":76,
    "ks:ks_type":"HABITATION",
    "name:eng_x_preferred":[
        "Gudligutu"
    ],
    "wof:name":"Gudligutu",
    "wof:placetype":"locality",
    "wof:population":76
},
  "geometry": {"coordinates":[85.69864200000001,22.343177],"type":"Point"}
}