{
  "type": "Feature",
  "properties": {
    "iso:country":"IN",
    "ks:ks_name":"Devpura",
    "ks:ks_type":"VILLAGE",
    "name:eng_x_preferred":[
        "Devpura"
    ],
    "wof:name":"Devpura",
    "wof:placetype":"locality"
},
  "geometry": {"coordinates":[78.56826700000001,29.233754],"type":"Point"}
}