{
  "type": "Feature",
  "properties": {
    "gn:admin1_code":"25.0",
    "gn:admin2_code":"619.0",
    "gn:asciiname":"Elanagar",
    "gn:country_code":"IN",
    "gn:dem":7,
    "gn:feature_class":"P",
    "gn:feature_code":"PPL",
    "gn:name":"Elanagar",
    "gn:population":0,
    "gn:timezone":"Asia/Kolkata",
    "iso:country":"IN",
    "ks:ks_name":"Elanagar",
    "ks:ks_pop":328,
    "ks:ks_type":"HABITATION",
    "name:eng_x_preferred":[
        "Elanagar"
    ],
    "wof:name":"Elanagar",
    "wof:placetype":"locality",
    "wof:population":328
},
  "geometry": {"coordinates":[79.59626400000001,10.5286],"type":"Point"}
}