{
  "type": "Feature",
  "properties": {
    "iso:country":"IN",
    "ks:ks_name":"Nagalur",
    "ks:ks_pop":108,
    "ks:ks_type":"HABITATION",
    "ks:ks_uagg_main":0,
    "name:eng_x_preferred":[
        "Nagalur"
    ],
    "wof:name":"Nagalur",
    "wof:placetype":"neighbourhood",
    "wof:population":108
},
  "geometry": {"coordinates":[78.041427,10.785515],"type":"Point"}
}