{
  "type": "Feature",
  "properties": {
    "iso:country":"IN",
    "ks:ks_alt_nam":"PINJAREBEDAGEMALA",
    "ks:ks_name":"Pinjarebedagemala",
    "ks:ks_pop":76,
    "ks:ks_type":"HABITATION",
    "name:eng_x_preferred":[
        "Pinjarebedagemala"
    ],
    "wof:name":"Pinjarebedagemala",
    "wof:placetype":"locality",
    "wof:population":76
},
  "geometry": {"coordinates":[74.652593,16.973364],"type":"Point"}
}