{
  "type": "Feature",
  "properties": {
    "iso:country":"IN",
    "ks:ks_name":"Pavarwadi",
    "ks:ks_pop":94,
    "ks:ks_type":"HABITATION",
    "ks:ks_uagg_main":0,
    "name:eng_x_preferred":[
        "Pavarwadi"
    ],
    "wof:name":"Pavarwadi",
    "wof:placetype":"neighbourhood",
    "wof:population":94
},
  "geometry": {"coordinates":[73.492576,16.946837],"type":"Point"}
}