{
  "type": "Feature",
  "properties": {
    "iso:country":"IN",
    "ks:ks_name":"Rahim Kita",
    "ks:ks_pop":73,
    "ks:ks_type":"VILLAGE",
    "ks:ks_uagg_main":0,
    "name:eng_x_preferred":[
        "Rahim Kita"
    ],
    "wof:name":"Rahim Kita",
    "wof:placetype":"neighbourhood",
    "wof:population":73
},
  "geometry": {"coordinates":[87.303703,25.037854],"type":"Point"}
}