{
  "type": "Feature",
  "properties": {
    "gn:admin1_code":"35",
    "gn:admin2_code":"459.0",
    "gn:asciiname":"Fatehabad",
    "gn:country_code":"IN",
    "gn:dem":436,
    "gn:feature_class":"P",
    "gn:feature_code":"PPL",
    "gn:name":"Fateh\u0101b\u0101d",
    "gn:population":0,
    "gn:timezone":"Asia/Kolkata",
    "iso:country":"IN",
    "name:ara_x_preferred":[
        "\u0641\u0627\u062a\u062d \u0623\u0628\u0627\u062f"
    ],
    "name:ben_bn_x_preferred":[
        "\u09ab\u09a4\u09c7\u09b9\u09be\u09ac\u09be\u09a6"
    ],
    "name:ben_in_x_preferred":[
        "\u09ab\u09a4\u09c7\u09b9\u09be\u09ac\u09be\u09a6"
    ],
    "name:ben_x_preferred":[
        "\u09ab\u09a4\u09c7\u09b9\u09be\u09ac\u09be\u09a6"
    ],
    "name:deu_x_preferred":[
        "Fatehabad"
    ],
    "name:guj_x_preferred":[
        "\u0aab\u0aa4\u0ac7\u0ab9\u0aac\u0abe\u0aa6"
    ],
    "name:hin_x_preferred":[
        "\u092b\u0924\u0947\u0939\u093e\u092c\u093e\u0926"
    ],
    "name:ita_x_preferred":[
        "Fatehabad"
    ],
    "name:kan_x_preferred":[
        "\u0cab\u0ca4\u0cc7\u0cb9\u0cbe\u0cac\u0cbe\u0ca6\u0ccd"
    ],
    "name:mal_x_preferred":[
        "\u0d2b\u0d24\u0d4d\u0d24\u0d47\u0d39\u0d3e\u0d2c\u0d3e\u0d26\u0d4d"
    ],
    "name:mar_x_preferred":[
        "\u092b\u0924\u0947\u0939\u093e\u092c\u093e\u0926"
    ],
    "name:msa_x_preferred":[
        "Fatehabad"
    ],
    "name:nld_x_preferred":[
        "Fatehabad"
    ],
    "name:pan_x_preferred":[
        "\u0a2b\u0a24\u0a47\u0a39\u0a3e\u0a2c\u0a3e\u0a26"
    ],
    "name:pol_x_preferred":[
        "Fatehabad"
    ],
    "name:tam_x_preferred":[
        "\u0b83\u0baa\u0ba4\u0bc7\u0bb9\u0bbe\u0baa\u0bbe\u0ba4\u0bcd"
    ],
    "name:tel_x_preferred":[
        "\u0c2a\u0c24\u0c47\u0c39\u0c3e\u0c2c\u0c3e\u0c26\u0c4d"
    ],
    "name:urd_x_preferred":[
        "\u0641\u062a\u062d \u0622\u0628\u0627\u062f"
    ],
    "wof:name":"Fatehabad",
    "wof:placetype":"neighbourhood"
},
  "geometry": {"coordinates":[78.11545,24.70302],"type":"Point"}
}