{
  "type": "Feature",
  "properties": {
    "iso:country":"IN",
    "ks:ks_name":"Tuligarmath",
    "ks:ks_pop":30,
    "ks:ks_type":"HABITATION",
    "name:eng_x_preferred":[
        "Tuligarmath"
    ],
    "wof:name":"Tuligarmath",
    "wof:placetype":"locality",
    "wof:population":30
},
  "geometry": {"coordinates":[74.694649,14.757811],"type":"Point"}
}