{
  "type": "Feature",
  "properties": {
    "iso:country":"IN",
    "ks:ks_name":"27 LNP",
    "ks:ks_pop":98,
    "ks:ks_type":"VILLAGE",
    "name:eng_x_preferred":[
        "27 LNP"
    ],
    "wof:name":"27 LNP",
    "wof:placetype":"locality",
    "wof:population":98
},
  "geometry": {"coordinates":[73.91330499999999,29.753071],"type":"Point"}
}