{
  "type": "Feature",
  "properties": {
    "gn:admin1_code":"34.0",
    "gn:admin2_code":"214.0",
    "gn:asciiname":"Lagma",
    "gn:country_code":"IN",
    "gn:dem":41,
    "gn:feature_class":"P",
    "gn:feature_code":"PPL",
    "gn:name":"Lagma",
    "gn:population":0,
    "gn:timezone":"Asia/Kolkata",
    "iso:country":"IN",
    "name:urd_x_preferred":[
        "\u0644\u0627\u06af\u0645\u0627"
    ],
    "wof:name":"Lagma",
    "wof:placetype":"locality"
},
  "geometry": {"coordinates":[86.67431999999999,25.74862000000001],"type":"Point"}
}