{
  "type": "Feature",
  "properties": {
    "gn:admin1_code":"24",
    "gn:admin2_code":"110.0",
    "gn:asciiname":"Sonpri",
    "gn:country_code":"IN",
    "gn:dem":373,
    "gn:feature_class":"P",
    "gn:feature_code":"PPL",
    "gn:name":"Sonpri",
    "gn:population":0,
    "gn:timezone":"Asia/Kolkata",
    "iso:country":"IN",
    "wof:name":"Sonpri",
    "wof:placetype":"locality"
},
  "geometry": {"coordinates":[75.81905999999999,26.8084],"type":"Point"}
}