{
  "type": "Feature",
  "properties": {
    "gn:admin1_code":"23",
    "gn:admin2_code":"39.0",
    "gn:asciiname":"Bhano Mazara",
    "gn:country_code":"IN",
    "gn:dem":262,
    "gn:feature_class":"P",
    "gn:feature_code":"PPL",
    "gn:name":"Bhano Maz\u0101ra",
    "gn:population":0,
    "gn:timezone":"Asia/Kolkata",
    "iso:country":"IN",
    "wof:name":"Bhano Mazara",
    "wof:placetype":"locality"
},
  "geometry": {"coordinates":[76.19416,31.11336],"type":"Point"}
}