{
  "type": "Feature",
  "properties": {
    "iso:country":"IN",
    "ks:ks_name":"Balwariya",
    "ks:ks_pop":216,
    "ks:ks_type":"HABITATION",
    "name:eng_x_preferred":[
        "Balwariya"
    ],
    "wof:name":"Balwariya",
    "wof:placetype":"locality",
    "wof:population":216
},
  "geometry": {"coordinates":[82.651397,26.905085],"type":"Point"}
}