{
  "type": "Feature",
  "properties": {
    "iso:country":"IN",
    "ks:ks_name":"Buruguveedhi",
    "ks:ks_pop":102,
    "ks:ks_type":"HABITATION",
    "name:eng_x_preferred":[
        "Buruguveedhi"
    ],
    "wof:name":"Buruguveedhi",
    "wof:placetype":"locality",
    "wof:population":102
},
  "geometry": {"coordinates":[82.44416,18.207074],"type":"Point"}
}