{
  "type": "Feature",
  "properties": {
    "gn:admin1_code":"11",
    "gn:admin2_code":"33.0",
    "gn:asciiname":"Chanal",
    "gn:country_code":"IN",
    "gn:dem":1874,
    "gn:feature_class":"P",
    "gn:feature_code":"PPL",
    "gn:name":"Chan\u0101l",
    "gn:population":0,
    "gn:timezone":"Asia/Kolkata",
    "iso:country":"IN",
    "name:ceb_x_preferred":[
        "Chanal"
    ],
    "name:deu_x_preferred":[
        "Chanal"
    ],
    "name:fra_x_preferred":[
        "Chanal"
    ],
    "name:swe_x_preferred":[
        "Chanal"
    ],
    "wof:name":"Chanal",
    "wof:placetype":"locality"
},
  "geometry": {"coordinates":[77.19355,31.1608],"type":"Point"}
}