{
  "type": "Feature",
  "properties": {
    "iso:country":"IN",
    "ks:ks_alt_nam":"ANDHARIYA BADLA",
    "ks:ks_name":"Andhariya Badla",
    "ks:ks_pop":200,
    "ks:ks_type":"HABITATION",
    "name:eng_x_preferred":[
        "Andhariya Badla"
    ],
    "wof:name":"Andhariya Badla",
    "wof:placetype":"locality",
    "wof:population":200
},
  "geometry": {"coordinates":[74.81831099999999,23.570573],"type":"Point"}
}