{
  "type": "Feature",
  "properties": {
    "iso:country":"IN",
    "ks:ks_name":"Suddavaguthanda",
    "ks:ks_pop":373,
    "ks:ks_type":"HABITATION",
    "name:eng_x_preferred":[
        "Suddavaguthanda"
    ],
    "wof:name":"Suddavaguthanda",
    "wof:placetype":"locality",
    "wof:population":373
},
  "geometry": {"coordinates":[79.804835,17.319878],"type":"Point"}
}