{
  "type": "Feature",
  "properties": {
    "iso:country":"IN",
    "ks:ks_name":"Sindhiguda",
    "ks:ks_pop":120,
    "ks:ks_type":"HABITATION",
    "name:eng_x_preferred":[
        "Sindhiguda"
    ],
    "wof:name":"Sindhiguda",
    "wof:placetype":"locality",
    "wof:population":120
},
  "geometry": {"coordinates":[82.089961,18.420501],"type":"Point"}
}