{
  "type": "Feature",
  "properties": {
    "gn:admin1_code":"38.0",
    "gn:admin2_code":"348.0",
    "gn:asciiname":"Dhobiadih",
    "gn:country_code":"IN",
    "gn:dem":372,
    "gn:feature_class":"P",
    "gn:feature_code":"PPL",
    "gn:name":"Dhobi\u0101dih",
    "gn:population":0,
    "gn:timezone":"Asia/Kolkata",
    "iso:country":"IN",
    "ks:ks_name":"Dhobiadih",
    "ks:ks_pop":96,
    "ks:ks_type":"VILLAGE",
    "name:eng_x_preferred":[
        "Dhobiadih"
    ],
    "wof:name":"Dhobiadih",
    "wof:placetype":"locality",
    "wof:population":96
},
  "geometry": {"coordinates":[85.69543,24.255632],"type":"Point"}
}