{
  "type": "Feature",
  "properties": {
    "iso:country":"IN",
    "ks:ks_name":"Kalsara",
    "ks:ks_pop":392,
    "ks:ks_type":"VILLAGE",
    "ks:ks_uagg_main":0,
    "name:eng_x_preferred":[
        "Kalsara"
    ],
    "wof:name":"Kalsara",
    "wof:placetype":"neighbourhood",
    "wof:population":392
},
  "geometry": {"coordinates":[87.704848,25.56418],"type":"Point"}
}