{
  "type": "Feature",
  "properties": {
    "gn:admin1_code":"24",
    "gn:admin2_code":"114.0",
    "gn:asciiname":"Shahgarh",
    "gn:country_code":"IN",
    "gn:dem":86,
    "gn:feature_class":"P",
    "gn:feature_code":"PPL",
    "gn:name":"Sh\u0101hgarh",
    "gn:population":0,
    "gn:timezone":"Asia/Kolkata",
    "iso:country":"IN",
    "name:ben_x_preferred":[
        "\u09b6\u09be\u09b9\u0997\u09a1\u09bc"
    ],
    "name:bpy_x_preferred":[
        "\u09b6\u09be\u09b9\u0997\u09a1\u09bc"
    ],
    "name:ceb_x_preferred":[
        "Sh\u0101hgarh"
    ],
    "name:guj_x_preferred":[
        "\u0ab6\u0abe\u0ab9\u0a97\u0aa2"
    ],
    "name:ita_x_preferred":[
        "Shahgarh"
    ],
    "name:msa_x_preferred":[
        "Shahgarh"
    ],
    "name:nld_x_preferred":[
        "Shahgarh"
    ],
    "name:por_x_preferred":[
        "Shahgarh"
    ],
    "name:swe_x_preferred":[
        "Sh\u0101hgarh"
    ],
    "name:vie_x_preferred":[
        "Shahgarh"
    ],
    "name:zho_x_preferred":[
        "\u65af\u54c8\u8d6b\u52a0\u5c14"
    ],
    "wof:name":"Shahgarh",
    "wof:placetype":"locality"
},
  "geometry": {"coordinates":[69.89771,27.12059],"type":"Point"}
}