{
  "type": "Feature",
  "properties": {
    "iso:country":"IN",
    "ks:ks_name":"Madhubati",
    "ks:ks_pop":1369,
    "ks:ks_type":"HABITATION",
    "ks:ks_uagg_main":0,
    "name:eng_x_preferred":[
        "Madhubati"
    ],
    "wof:name":"Madhubati",
    "wof:placetype":"locality",
    "wof:population":1369
},
  "geometry": {"coordinates":[88.209464,22.786471],"type":"Point"}
}