{
  "type": "Feature",
  "properties": {
    "gn:admin1_code":"2",
    "gn:admin2_code":"544.0",
    "gn:asciiname":"Tallapalem",
    "gn:country_code":"IN",
    "gn:dem":215,
    "gn:feature_class":"P",
    "gn:feature_code":"PPL",
    "gn:name":"Tallap\u0101lem",
    "gn:population":0,
    "gn:timezone":"Asia/Kolkata",
    "iso:country":"IN",
    "ks:ks_name":"Tallapalem",
    "ks:ks_pop":153,
    "ks:ks_type":"HABITATION",
    "name:eng_x_preferred":[
        "Tallapalem"
    ],
    "wof:name":"Tallapalem",
    "wof:placetype":"locality",
    "wof:population":153
},
  "geometry": {"coordinates":[82.335509,17.613407],"type":"Point"}
}