{
  "type": "Feature",
  "properties": {
    "iso:country":"IN",
    "ks:ks_name":"Bahattara",
    "ks:ks_pop":529,
    "ks:ks_type":"HABITATION",
    "name:eng_x_preferred":[
        "Bahattara"
    ],
    "wof:name":"Bahattara",
    "wof:placetype":"locality",
    "wof:population":529
},
  "geometry": {"coordinates":[79.716694,30.141757],"type":"Point"}
}