{
  "type": "Feature",
  "properties": {
    "iso:country":"IN",
    "ks:ks_name":"Sirauli",
    "ks:ks_pop":50,
    "ks:ks_type":"HABITATION",
    "name:eng_x_preferred":[
        "Sirauli"
    ],
    "wof:name":"Sirauli",
    "wof:placetype":"locality",
    "wof:population":50
},
  "geometry": {"coordinates":[80.23745,29.342152],"type":"Point"}
}