{
  "type": "Feature",
  "properties": {
    "iso:country":"IN",
    "ks:ks_name":"Simhat",
    "ks:ks_pop":4964,
    "ks:ks_type":"URBAN",
    "ks:ks_uagg_main":0,
    "name:eng_x_preferred":[
        "Simhat"
    ],
    "wof:name":"Simhat",
    "wof:placetype":"locality",
    "wof:population":4964
},
  "geometry": {"coordinates":[88.549004,22.954599],"type":"Point"}
}