{
  "type": "Feature",
  "properties": {
    "gn:admin1_code":"12.0",
    "gn:admin2_code":"19.0",
    "gn:asciiname":"Daman",
    "gn:country_code":"IN",
    "gn:dem":1769,
    "gn:feature_class":"P",
    "gn:feature_code":"PPL",
    "gn:name":"Dam\u0101n",
    "gn:population":0,
    "gn:timezone":"Asia/Kolkata",
    "iso:country":"IN",
    "name:ben_x_preferred":[
        "\u09a6\u09ae\u09a8"
    ],
    "name:bpy_x_preferred":[
        "\u09a6\u09ae\u09a8"
    ],
    "name:cat_x_preferred":[
        "Daman"
    ],
    "name:ceb_x_preferred":[
        "Daman"
    ],
    "name:deu_x_preferred":[
        "Daman"
    ],
    "name:fra_x_preferred":[
        "Daman"
    ],
    "name:nld_x_preferred":[
        "Daman"
    ],
    "name:sat_x_preferred":[
        "\u1c70\u1c5f\u1c62\u1c5a\u1c71"
    ],
    "name:slk_x_preferred":[
        "Daman"
    ],
    "name:swe_x_preferred":[
        "Daman"
    ],
    "name:tur_x_preferred":[
        "Daman"
    ],
    "wof:name":"Daman",
    "wof:placetype":"locality"
},
  "geometry": {"coordinates":[75.39488,32.72827],"type":"Point"}
}