{
  "type": "Feature",
  "properties": {
    "gn:admin1_code":"12.0",
    "gn:admin2_code":"19.0",
    "gn:asciiname":"Daman",
    "gn:country_code":"IN",
    "gn:dem":1769,
    "gn:feature_class":"P",
    "gn:feature_code":"PPL",
    "gn:name":"Dam\u0101n",
    "gn:population":0,
    "gn:timezone":"Asia/Kolkata",
    "iso:country":"IN",
    "name:ara_x_preferred":[
        "\u062f\u0627\u0645\u0627\u0646"
    ],
    "name:ben_bn_x_preferred":[
        "\u09a6\u09ae\u09a8"
    ],
    "name:ben_in_x_preferred":[
        "\u09a6\u09ae\u09a8"
    ],
    "name:ben_x_preferred":[
        "\u09a6\u09ae\u09a8"
    ],
    "name:bpy_x_preferred":[
        "\u09a6\u09ae\u09a8"
    ],
    "name:cat_x_preferred":[
        "Daman"
    ],
    "name:ceb_x_preferred":[
        "Daman"
    ],
    "name:deu_x_preferred":[
        "Daman"
    ],
    "name:ell_x_preferred":[
        "\u039d\u03c4\u03b1\u03bc\u03ac\u03bd"
    ],
    "name:fra_x_preferred":[
        "Daman"
    ],
    "name:guj_x_preferred":[
        "\u0aa6\u0aae\u0aa3"
    ],
    "name:heb_x_preferred":[
        "\u05d3\u05d0\u05de\u05d0\u05df"
    ],
    "name:hin_x_preferred":[
        "\u0926\u092e\u0928"
    ],
    "name:kan_x_preferred":[
        "\u0ca6\u0cae\u0ca8\u0ccd"
    ],
    "name:mal_x_preferred":[
        "\u0d26\u0d3e\u0d2e\u0d7b"
    ],
    "name:mar_x_preferred":[
        "\u0926\u092e\u0923"
    ],
    "name:nld_x_preferred":[
        "Daman"
    ],
    "name:pan_x_preferred":[
        "\u0a26\u0a2e\u0a28"
    ],
    "name:sat_x_preferred":[
        "\u1c70\u1c5f\u1c62\u1c5a\u1c71"
    ],
    "name:slk_x_preferred":[
        "Daman"
    ],
    "name:swe_x_preferred":[
        "Daman"
    ],
    "name:tam_x_preferred":[
        "\u0b9f\u0bbe\u0bae\u0ba9\u0bcd"
    ],
    "name:tel_x_preferred":[
        "\u0c21\u0c2e\u0c28\u0c4d"
    ],
    "name:tur_x_preferred":[
        "Daman"
    ],
    "name:urd_x_preferred":[
        "\u062f\u0645\u0646"
    ],
    "wof:name":"Daman",
    "wof:placetype":"locality"
},
  "geometry": {"coordinates":[75.39488,32.72827],"type":"Point"}
}