{
  "type": "Feature",
  "properties": {
    "gn:admin1_code":"16.0",
    "gn:admin2_code":"529.0",
    "gn:asciiname":"Kendre-khurd",
    "gn:country_code":"IN",
    "gn:dem":163,
    "gn:feature_class":"P",
    "gn:feature_code":"PPL",
    "gn:name":"Kendre-khurd",
    "gn:population":0,
    "gn:timezone":"Asia/Kolkata",
    "iso:country":"IN",
    "wof:name":"Kendre-khurd",
    "wof:placetype":"locality"
},
  "geometry": {"coordinates":[74.17494000000001,15.75903],"type":"Point"}
}