{
  "type": "Feature",
  "properties": {
    "gn:admin1_code":"19.0",
    "gn:admin2_code":"568.0",
    "gn:asciiname":"Dapadamane",
    "gn:country_code":"IN",
    "gn:dem":655,
    "gn:feature_class":"P",
    "gn:feature_code":"PPL",
    "gn:name":"Dapadamane",
    "gn:population":0,
    "gn:timezone":"Asia/Kolkata",
    "iso:country":"IN",
    "wof:name":"Dapadamane",
    "wof:placetype":"locality"
},
  "geometry": {"coordinates":[75.22721999999997,13.76423],"type":"Point"}
}