{
  "type": "Feature",
  "properties": {
    "iso:country":"IN",
    "ks:ks_name":"Bantrabettu",
    "ks:ks_pop":56,
    "ks:ks_type":"HABITATION",
    "name:eng_x_preferred":[
        "Bantrabettu"
    ],
    "wof:name":"Bantrabettu",
    "wof:placetype":"locality",
    "wof:population":56
},
  "geometry": {"coordinates":[75.024686,13.276821],"type":"Point"}
}