{
  "type": "Feature",
  "properties": {
    "iso:country":"IN",
    "ks:ks_alt_nam":"Hokaldanga Dakshin Para and Hat Para",
    "ks:ks_name":"Hokaldanga Dakshin Para And Hat Para",
    "ks:ks_pop":1440,
    "ks:ks_type":"HABITATION",
    "name:eng_x_preferred":[
        "Hokaldanga Dakshin Para And Hat Para"
    ],
    "wof:name":"Hokaldanga Dakshin Para And Hat Para",
    "wof:placetype":"locality",
    "wof:population":1440
},
  "geometry": {"coordinates":[88.466567,22.097681],"type":"Point"}
}