{
  "type": "Feature",
  "properties": {
    "iso:country":"IN",
    "ks:ks_name":"Bhaturpasi",
    "ks:ks_pop":165,
    "ks:ks_type":"VILLAGE",
    "name:eng_x_preferred":[
        "Bhaturpasi"
    ],
    "wof:name":"Bhaturpasi",
    "wof:placetype":"locality",
    "wof:population":165
},
  "geometry": {"coordinates":[86.13269099999999,20.744505],"type":"Point"}
}