{
  "type": "Feature",
  "properties": {
    "iso:country":"IN",
    "ks:ks_name":"Bakratpur",
    "ks:ks_pop":63,
    "ks:ks_type":"VILLAGE",
    "ks:ks_uagg_main":0,
    "name:eng_x_preferred":[
        "Bakratpur"
    ],
    "wof:name":"Bakratpur",
    "wof:placetype":"locality",
    "wof:population":63
},
  "geometry": {"coordinates":[72.10026499999999,23.845125],"type":"Point"}
}