{
  "type": "Feature",
  "properties": {
    "iso:country":"IN",
    "ks:ks_name":"Maarakutti",
    "ks:ks_pop":32,
    "ks:ks_type":"HABITATION",
    "name:eng_x_preferred":[
        "Maarakutti"
    ],
    "wof:name":"Maarakutti",
    "wof:placetype":"locality",
    "wof:population":32
},
  "geometry": {"coordinates":[74.897009,13.906263],"type":"Point"}
}