{
  "type": "Feature",
  "properties": {
    "gn:admin1_code":"36.0",
    "gn:admin2_code":"174.0",
    "gn:asciiname":"Faridpur",
    "gn:country_code":"IN",
    "gn:dem":103,
    "gn:feature_class":"P",
    "gn:feature_code":"PPL",
    "gn:name":"Far\u012bdpur",
    "gn:population":0,
    "gn:timezone":"Asia/Kolkata",
    "iso:country":"IN",
    "name:und_x_variant":[
        "Far\u012bdpur",
        "Salempur"
    ],
    "wof:name":"Faridpur",
    "wof:placetype":"locality"
},
  "geometry": {"coordinates":[81.60464,25.4411],"type":"Point"}
}