{
  "type": "Feature",
  "properties": {
    "iso:country":"IN",
    "ks:ks_alt_nam":"Dirid\u0101g",
    "ks:ks_name":"Diridag",
    "ks:ks_pop":568,
    "ks:ks_type":"VILLAGE",
    "name:eng_x_preferred":[
        "Diridag"
    ],
    "name:eng_x_variant":[
        "Dirid\u0101g"
    ],
    "wof:name":"Diridag",
    "wof:placetype":"locality",
    "wof:population":568
},
  "geometry": {"coordinates":[84.712417,23.832908],"type":"Point"}
}