{
  "type": "Feature",
  "properties": {
    "gn:admin1_code":"25.0",
    "gn:admin2_code":"604",
    "gn:asciiname":"Pillappakkam",
    "gn:country_code":"IN",
    "gn:dem":41,
    "gn:feature_class":"P",
    "gn:feature_code":"PPL",
    "gn:name":"Pillapp\u0101kkam",
    "gn:population":0,
    "gn:timezone":"Asia/Kolkata",
    "iso:country":"IN",
    "ks:ks_alt_nam":"Pillapp\u0101kkam",
    "ks:ks_name":"Pillappakkam",
    "ks:ks_type":"VILLAGE",
    "name:eng_x_preferred":[
        "Pillappakkam"
    ],
    "name:eng_x_variant":[
        "Pillapp\u0101kkam"
    ],
    "wof:name":"Pillappakkam",
    "wof:placetype":"locality"
},
  "geometry": {"coordinates":[79.971389,12.955118],"type":"Point"}
}