{
  "type": "Feature",
  "properties": {
    "gn:admin1_code":"38.0",
    "gn:admin2_code":"347.0",
    "gn:asciiname":"Meramgara",
    "gn:country_code":"IN",
    "gn:dem":499,
    "gn:feature_class":"P",
    "gn:feature_code":"PPL",
    "gn:name":"Meramgar\u0101",
    "gn:population":0,
    "gn:timezone":"Asia/Kolkata",
    "iso:country":"IN",
    "ks:ks_alt_nam":"Meramgar\u0101",
    "ks:ks_name":"Meramgara",
    "ks:ks_pop":394,
    "ks:ks_type":"VILLAGE",
    "name:eng_x_preferred":[
        "Meramgara"
    ],
    "name:eng_x_variant":[
        "Meramgar\u0101"
    ],
    "wof:name":"Meramgara",
    "wof:placetype":"locality",
    "wof:population":394
},
  "geometry": {"coordinates":[85.133926,24.071993],"type":"Point"}
}