{
  "type": "Feature",
  "properties": {
    "iso:country":"IN",
    "ks:ks_name":"Chakurbera",
    "ks:ks_pop":382,
    "ks:ks_type":"HABITATION",
    "name:eng_x_preferred":[
        "Chakurbera"
    ],
    "wof:name":"Chakurbera",
    "wof:placetype":"locality",
    "wof:population":382
},
  "geometry": {"coordinates":[84.596098,22.472451],"type":"Point"}
}