{
  "type": "Feature",
  "properties": {
    "gn:admin1_code":"11.0",
    "gn:admin2_code":"32.0",
    "gn:asciiname":"Kuphta",
    "gn:country_code":"IN",
    "gn:dem":1135,
    "gn:feature_class":"P",
    "gn:feature_code":"PPL",
    "gn:name":"Kuphta",
    "gn:population":0,
    "gn:timezone":"Asia/Kolkata",
    "iso:country":"IN",
    "wof:name":"Kuphta",
    "wof:placetype":"locality"
},
  "geometry": {"coordinates":[77.23596999999999,30.89891],"type":"Point"}
}