{
  "type": "Feature",
  "properties": {
    "iso:country":"IN",
    "ks:ks_name":"Ingavalewadi",
    "ks:ks_pop":221,
    "ks:ks_type":"HABITATION",
    "ks:ks_uagg_main":0,
    "name:eng_x_preferred":[
        "Ingavalewadi"
    ],
    "wof:name":"Ingavalewadi",
    "wof:placetype":"neighbourhood",
    "wof:population":221
},
  "geometry": {"coordinates":[73.963397,16.981428],"type":"Point"}
}