{
  "type": "Feature",
  "properties": {
    "gn:admin1_code":"24",
    "gn:admin2_code":"118.0",
    "gn:asciiname":"Bhopaji ka Gudha",
    "gn:country_code":"IN",
    "gn:dem":337,
    "gn:feature_class":"P",
    "gn:feature_code":"PPL",
    "gn:name":"Bhop\u0101ji ka G\u016bdha",
    "gn:population":0,
    "gn:timezone":"Asia/Kolkata",
    "iso:country":"IN",
    "wof:name":"Bhopaji ka Gudha",
    "wof:placetype":"locality"
},
  "geometry": {"coordinates":[73.76789000000002,25.58158],"type":"Point"}
}