{
  "type": "Feature",
  "properties": {
    "iso:country":"IN",
    "ks:ks_alt_nam":"PURE BHAGWANDEEN",
    "ks:ks_name":"Pure Bhagwandeen",
    "ks:ks_pop":74,
    "ks:ks_type":"HABITATION",
    "name:eng_x_preferred":[
        "Pure Bhagwandeen"
    ],
    "wof:name":"Pure Bhagwandeen",
    "wof:placetype":"locality",
    "wof:population":74
},
  "geometry": {"coordinates":[81.76664,26.110005],"type":"Point"}
}