{
  "type": "Feature",
  "properties": {
    "iso:country":"IN",
    "ks:ks_name":"Gera Garh Gaon",
    "ks:ks_pop":200,
    "ks:ks_type":"VILLAGE",
    "ks:ks_uagg_main":0,
    "name:eng_x_preferred":[
        "Gera Garh Gaon"
    ],
    "wof:name":"Gera Garh Gaon",
    "wof:placetype":"neighbourhood",
    "wof:population":200
},
  "geometry": {"coordinates":[92.423579,26.133296],"type":"Point"}
}