{
  "type": "Feature",
  "properties": {
    "iso:country":"IN",
    "ks:ks_name":"Khaspara",
    "ks:ks_pop":197,
    "ks:ks_type":"HABITATION",
    "name:eng_x_preferred":[
        "Khaspara"
    ],
    "wof:name":"Khaspara",
    "wof:placetype":"locality",
    "wof:population":197
},
  "geometry": {"coordinates":[82.11710600000001,19.385476],"type":"Point"}
}