{
  "type": "Feature",
  "properties": {
    "iso:country":"IN",
    "ks:ks_alt_nam":"Chikan khill",
    "ks:ks_name":"Chikan Khill",
    "ks:ks_pop":751,
    "ks:ks_type":"HABITATION",
    "name:eng_x_preferred":[
        "Chikan Khill"
    ],
    "wof:name":"Chikan Khill",
    "wof:placetype":"locality",
    "wof:population":751
},
  "geometry": {"coordinates":[91.343962,23.174972],"type":"Point"}
}