{
  "type": "Feature",
  "properties": {
    "iso:country":"IN",
    "ks:ks_name":"Sekupur",
    "ks:ks_pop":101,
    "ks:ks_type":"VILLAGE",
    "name:eng_x_preferred":[
        "Sekupur"
    ],
    "wof:name":"Sekupur",
    "wof:placetype":"locality",
    "wof:population":101
},
  "geometry": {"coordinates":[87.368279,23.768246],"type":"Point"}
}