{
  "type": "Feature",
  "properties": {
    "iso:country":"IN",
    "ks:ks_name":"Rayani",
    "ks:ks_pop":0,
    "ks:ks_type":"VILLAGE",
    "name:eng_x_preferred":[
        "Rayani"
    ],
    "wof:name":"Rayani",
    "wof:placetype":"locality",
    "wof:population":0
},
  "geometry": {"coordinates":[77.400875,21.21629],"type":"Point"}
}