{
  "type": "Feature",
  "properties": {
    "gn:admin1_code":"21.0",
    "gn:admin2_code":"396.0",
    "gn:asciiname":"Gundiripadar",
    "gn:country_code":"IN",
    "gn:dem":408,
    "gn:feature_class":"P",
    "gn:feature_code":"PPL",
    "gn:name":"Gundiripadar",
    "gn:population":0,
    "gn:timezone":"Asia/Kolkata",
    "iso:country":"IN",
    "ks:ks_name":"Gundripadar",
    "ks:ks_pop":44,
    "ks:ks_type":"VILLAGE",
    "name:eng_x_preferred":[
        "Gundripadar"
    ],
    "name:eng_x_variant":[
        "Gundiripadar"
    ],
    "wof:name":"Gundripadar",
    "wof:placetype":"locality",
    "wof:population":44
},
  "geometry": {"coordinates":[83.9729,19.371129],"type":"Point"}
}