{
  "type": "Feature",
  "properties": {
    "gn:admin1_code":"36",
    "gn:admin2_code":"134.0",
    "gn:asciiname":"Satarwala",
    "gn:country_code":"IN",
    "gn:dem":252,
    "gn:feature_class":"P",
    "gn:feature_code":"PPL",
    "gn:name":"Sat\u0101rw\u0101la",
    "gn:population":0,
    "gn:timezone":"Asia/Kolkata",
    "iso:country":"IN",
    "ks:ks_alt_nam":"Sat\u0101rw\u0101la",
    "ks:ks_name":"Satarwala",
    "ks:ks_type":"VILLAGE",
    "name:eng_x_preferred":[
        "Satarwala"
    ],
    "name:eng_x_variant":[
        "Sat\u0101rw\u0101la"
    ],
    "name:und_x_variant":[
        "Sat\u0101rw\u0101la",
        "H\u012bmpur Makhd\u016bra Jah\u0101n"
    ],
    "wof:name":"Satarwala",
    "wof:placetype":"locality"
},
  "geometry": {"coordinates":[78.407067,29.497123],"type":"Point"}
}