{
  "type": "Feature",
  "properties": {
    "gn:admin1_code":"34.0",
    "gn:admin2_code":"219.0",
    "gn:asciiname":"Siuri",
    "gn:country_code":"IN",
    "gn:dem":61,
    "gn:feature_class":"P",
    "gn:feature_code":"PPL",
    "gn:name":"Siuri",
    "gn:population":0,
    "gn:timezone":"Asia/Kolkata",
    "iso:country":"IN",
    "ks:ks_name":"Siuri",
    "ks:ks_pop":542,
    "ks:ks_type":"VILLAGE",
    "ks:ks_uagg_main":0,
    "name:ben_x_preferred":[
        "\u09b8\u09bf\u0989\u09b0\u09bf"
    ],
    "name:ceb_x_preferred":[
        "Siuri"
    ],
    "name:eng_x_preferred":[
        "Siuri"
    ],
    "name:hin_x_preferred":[
        "\u0938\u093f\u0909\u0930\u0940"
    ],
    "name:swe_x_preferred":[
        "Siuri"
    ],
    "wof:name":"Siuri",
    "wof:placetype":"neighbourhood",
    "wof:population":542
},
  "geometry": {"coordinates":[84.76678200000001,26.040144],"type":"Point"}
}