{
  "type": "Feature",
  "properties": {
    "iso:country":"IN",
    "ks:ks_name":"Dhangarwadi",
    "ks:ks_pop":163,
    "ks:ks_type":"HABITATION",
    "name:eng_x_preferred":[
        "Dhangarwadi"
    ],
    "wof:name":"Dhangarwadi",
    "wof:placetype":"locality",
    "wof:population":163
},
  "geometry": {"coordinates":[73.33671099999999,16.881392],"type":"Point"}
}