{
  "type": "Feature",
  "properties": {
    "iso:country":"IN",
    "ks:ks_name":"Kudradka1",
    "ks:ks_pop":280,
    "ks:ks_type":"HABITATION",
    "name:eng_x_preferred":[
        "Kudradka1"
    ],
    "wof:name":"Kudradka1",
    "wof:placetype":"locality",
    "wof:population":280
},
  "geometry": {"coordinates":[75.284437,13.018651],"type":"Point"}
}