{
  "type": "Feature",
  "properties": {
    "iso:country":"IN",
    "ks:ks_name":"Noga Gaon Chuk",
    "ks:ks_pop":325,
    "ks:ks_type":"HABITATION",
    "name:eng_x_preferred":[
        "Noga Gaon Chuk"
    ],
    "wof:name":"Noga Gaon Chuk",
    "wof:placetype":"locality",
    "wof:population":325
},
  "geometry": {"coordinates":[95.312443,27.117113],"type":"Point"}
}