{
  "type": "Feature",
  "properties": {
    "iso:country":"IN",
    "ks:ks_alt_nam":"T\u012bpra",
    "ks:ks_name":"Tipra",
    "ks:ks_pop":2074,
    "ks:ks_type":"VILLAGE",
    "ks:ks_uagg_main":0,
    "name:eng_x_preferred":[
        "Tipra"
    ],
    "name:eng_x_variant":[
        "T\u012bpra"
    ],
    "wof:name":"Tipra",
    "wof:placetype":"neighbourhood",
    "wof:population":2074
},
  "geometry": {"coordinates":[76.94608700000001,30.827314],"type":"Point"}
}