{
  "type": "Feature",
  "properties": {
    "gn:admin1_code":"23.0",
    "gn:admin2_code":"040",
    "gn:asciiname":"Majri",
    "gn:country_code":"IN",
    "gn:dem":265,
    "gn:feature_class":"P",
    "gn:feature_code":"PPL",
    "gn:name":"M\u0101jri",
    "gn:population":0,
    "gn:timezone":"Asia/Kolkata",
    "iso:country":"IN",
    "name:und_x_variant":[
        "R\u0101i\u0101n",
        "M\u0101jri"
    ],
    "wof:name":"Majri",
    "wof:placetype":"locality"
},
  "geometry": {"coordinates":[76.22577,30.62296],"type":"Point"}
}