{
  "type": "Feature",
  "properties": {
    "iso:country":"IN",
    "ks:ks_name":"Maniarpur Kita Urf Rauri",
    "ks:ks_pop":0,
    "ks:ks_type":"VILLAGE",
    "name:eng_x_preferred":[
        "Maniarpur Kita Urf Rauri"
    ],
    "wof:name":"Maniarpur Kita Urf Rauri",
    "wof:placetype":"locality",
    "wof:population":0
},
  "geometry": {"coordinates":[86.87995100000001,25.187317],"type":"Point"}
}