{
  "type": "Feature",
  "properties": {
    "iso:country":"IN",
    "ks:ks_alt_nam":"Basanth",
    "ks:ks_name":"Basant",
    "ks:ks_pop":0,
    "ks:ks_type":"VILLAGE",
    "name:eng_x_preferred":[
        "Basant"
    ],
    "name:eng_x_variant":[
        "Basanth"
    ],
    "wof:name":"Basant",
    "wof:placetype":"locality",
    "wof:population":0
},
  "geometry": {"coordinates":[81.599518,20.603238],"type":"Point"}
}