{
  "type": "Feature",
  "properties": {
    "iso:country":"IN",
    "ks:ks_name":"28 SSW",
    "ks:ks_pop":129,
    "ks:ks_type":"VILLAGE",
    "name:eng_x_preferred":[
        "28 SSW"
    ],
    "wof:name":"28 SSW",
    "wof:placetype":"locality",
    "wof:population":129
},
  "geometry": {"coordinates":[74.257616,29.48041],"type":"Point"}
}