{
  "type": "Feature",
  "properties": {
    "iso:country":"IN",
    "ks:ks_name":"Niraballi",
    "ks:ks_pop":25,
    "ks:ks_type":"HABITATION",
    "name:eng_x_preferred":[
        "Niraballi"
    ],
    "wof:name":"Niraballi",
    "wof:placetype":"locality",
    "wof:population":25
},
  "geometry": {"coordinates":[74.99715500000001,13.828317],"type":"Point"}
}