{
  "type": "Feature",
  "properties": {
    "gn:admin1_code":"39.0",
    "gn:admin2_code":"64.0",
    "gn:asciiname":"Kapchaun",
    "gn:country_code":"IN",
    "gn:dem":1401,
    "gn:feature_class":"P",
    "gn:feature_code":"PPL",
    "gn:name":"Kapchaun",
    "gn:population":0,
    "gn:timezone":"Asia/Kolkata",
    "iso:country":"IN",
    "ks:ks_name":"Kafchaun",
    "ks:ks_pop":19,
    "ks:ks_type":"VILLAGE",
    "name:eng_x_preferred":[
        "Kafchaun"
    ],
    "name:eng_x_variant":[
        "Kapchaun"
    ],
    "wof:name":"Kafchaun",
    "wof:placetype":"locality",
    "wof:population":19
},
  "geometry": {"coordinates":[79.55126799999999,29.615394],"type":"Point"}
}