{
  "type": "Feature",
  "properties": {
    "gn:admin1_code":"39.0",
    "gn:admin2_code":"64.0",
    "gn:asciiname":"Kapchaun",
    "gn:country_code":"IN",
    "gn:dem":1401,
    "gn:feature_class":"P",
    "gn:feature_code":"PPL",
    "gn:name":"Kapchaun",
    "gn:population":0,
    "gn:timezone":"Asia/Kolkata",
    "iso:country":"IN",
    "wof:name":"Kapchaun",
    "wof:placetype":"locality"
},
  "geometry": {"coordinates":[79.55566,29.61627],"type":"Point"}
}