{
  "type": "Feature",
  "properties": {
    "iso:country":"IN",
    "ks:ks_name":"Madatumpurampadam",
    "ks:ks_pop":582,
    "ks:ks_type":"HABITATION",
    "name:eng_x_preferred":[
        "Madatumpurampadam"
    ],
    "wof:name":"Madatumpurampadam",
    "wof:placetype":"locality",
    "wof:population":582
},
  "geometry": {"coordinates":[76.06882299999999,10.733558],"type":"Point"}
}