{
  "type": "Feature",
  "properties": {
    "gn:admin1_code":"36.0",
    "gn:admin2_code":"179.0",
    "gn:asciiname":"Bhatwa",
    "gn:country_code":"IN",
    "gn:dem":112,
    "gn:feature_class":"P",
    "gn:feature_code":"PPL",
    "gn:name":"Bhatwa",
    "gn:population":0,
    "gn:timezone":"Asia/Kolkata",
    "iso:country":"IN",
    "name:und_x_variant":[
        "Bagh M\u012bran"
    ],
    "wof:name":"Bhatwa",
    "wof:placetype":"locality"
},
  "geometry": {"coordinates":[81.65425999999999,26.50916],"type":"Point"}
}