{
  "type": "Feature",
  "properties": {
    "gn:admin1_code":"16.0",
    "gn:admin2_code":"505.0",
    "gn:asciiname":"Pathar",
    "gn:country_code":"IN",
    "gn:dem":493,
    "gn:feature_class":"P",
    "gn:feature_code":"PPL",
    "gn:name":"Path\u0101r",
    "gn:population":0,
    "gn:timezone":"Asia/Kolkata",
    "iso:country":"IN",
    "wof:name":"Pathar",
    "wof:placetype":"locality"
},
  "geometry": {"coordinates":[78.62028000000002,21.29393],"type":"Point"}
}