{
  "type": "Feature",
  "properties": {
    "gn:admin1_code":"39.0",
    "gn:admin2_code":"61.0",
    "gn:asciiname":"Thanga Talla",
    "gn:country_code":"IN",
    "gn:dem":1575,
    "gn:feature_class":"P",
    "gn:feature_code":"PPL",
    "gn:name":"Thanga Talla",
    "gn:population":0,
    "gn:timezone":"Asia/Kolkata",
    "iso:country":"IN",
    "name:und_x_variant":[
        "Sungargairi"
    ],
    "wof:name":"Thanga Talla",
    "wof:placetype":"locality"
},
  "geometry": {"coordinates":[79.00700999999999,29.91068],"type":"Point"}
}