{
  "type": "Feature",
  "properties": {
    "gn:admin1_code":"39.0",
    "gn:admin2_code":"61.0",
    "gn:asciiname":"Thanga Talla",
    "gn:country_code":"IN",
    "gn:dem":1575,
    "gn:feature_class":"P",
    "gn:feature_code":"PPL",
    "gn:name":"Thanga Talla",
    "gn:population":0,
    "gn:timezone":"Asia/Kolkata",
    "iso:country":"IN",
    "ks:ks_name":"Thanga Malla",
    "ks:ks_type":"VILLAGE",
    "name:eng_x_preferred":[
        "Thanga Malla"
    ],
    "name:eng_x_variant":[
        "Thanga Talla"
    ],
    "name:und_x_variant":[
        "Sungargairi"
    ],
    "wof:name":"Thanga Malla",
    "wof:placetype":"locality"
},
  "geometry": {"coordinates":[79.001902,29.902662],"type":"Point"}
}