{
  "type": "Feature",
  "properties": {
    "gn:admin1_code":"16.0",
    "gn:admin2_code":"503.0",
    "gn:asciiname":"Thuni",
    "gn:country_code":"IN",
    "gn:dem":335,
    "gn:feature_class":"P",
    "gn:feature_code":"PPL",
    "gn:name":"Th\u016bni",
    "gn:population":0,
    "gn:timezone":"Asia/Kolkata",
    "iso:country":"IN",
    "ks:ks_name":"Thani",
    "ks:ks_pop":14,
    "ks:ks_type":"VILLAGE",
    "name:eng_x_preferred":[
        "Thani"
    ],
    "name:eng_x_variant":[
        "Thuni"
    ],
    "wof:name":"Thani",
    "wof:placetype":"locality",
    "wof:population":14
},
  "geometry": {"coordinates":[78.061283,21.35687],"type":"Point"}
}