{
  "type": "Feature",
  "properties": {
    "gn:admin1_code":"37.0",
    "gn:admin2_code":"417.0",
    "gn:asciiname":"Gundapuri",
    "gn:country_code":"IN",
    "gn:dem":196,
    "gn:feature_class":"P",
    "gn:feature_code":"PPL",
    "gn:name":"Gund\u0101puri",
    "gn:population":0,
    "gn:timezone":"Asia/Kolkata",
    "iso:country":"IN",
    "ks:ks_alt_nam":"Gund\u0101puri",
    "ks:ks_name":"Gundapuri",
    "ks:ks_pop":122,
    "ks:ks_type":"VILLAGE",
    "name:eng_x_preferred":[
        "Gundapuri"
    ],
    "name:eng_x_variant":[
        "Gund\u0101puri"
    ],
    "wof:name":"Gundapuri",
    "wof:placetype":"locality",
    "wof:population":122
},
  "geometry": {"coordinates":[80.536135,19.180021],"type":"Point"}
}