{
  "type": "Feature",
  "properties": {
    "iso:country":"IN",
    "ks:ks_name":"Khairi Purwa",
    "ks:ks_pop":635,
    "ks:ks_type":"HABITATION",
    "name:eng_x_preferred":[
        "Khairi Purwa"
    ],
    "wof:name":"Khairi Purwa",
    "wof:placetype":"locality",
    "wof:population":635
},
  "geometry": {"coordinates":[81.245052,28.158175],"type":"Point"}
}