{
  "type": "Feature",
  "properties": {
    "iso:country":"IN",
    "ks:ks_name":"Barikhal",
    "ks:ks_pop":173,
    "ks:ks_type":"VILLAGE",
    "name:eng_x_preferred":[
        "Barikhal"
    ],
    "wof:name":"Barikhal",
    "wof:placetype":"locality",
    "wof:population":173
},
  "geometry": {"coordinates":[83.61174699999999,19.657344],"type":"Point"}
}