{
  "type": "Feature",
  "properties": {
    "gn:admin1_code":"19.0",
    "gn:admin2_code":"574.0",
    "gn:asciiname":"Kogarhalli",
    "gn:country_code":"IN",
    "gn:dem":975,
    "gn:feature_class":"P",
    "gn:feature_code":"PPL",
    "gn:name":"Kogarhalli",
    "gn:population":0,
    "gn:timezone":"Asia/Kolkata",
    "iso:country":"IN",
    "ks:ks_name":"Kogaravalli",
    "ks:ks_pop":723,
    "ks:ks_type":"VILLAGE",
    "name:eng_x_preferred":[
        "Kogaravalli"
    ],
    "name:eng_x_variant":[
        "Kogarhalli"
    ],
    "wof:name":"Kogaravalli",
    "wof:placetype":"locality",
    "wof:population":723
},
  "geometry": {"coordinates":[75.659054,13.021256],"type":"Point"}
}