{
  "type": "Feature",
  "properties": {
    "iso:country":"IN",
    "qs:name":"Sanwal Nagar",
    "qs:name_adm0":"India",
    "qs:name_adm1":"Delhi",
    "qs:photos":3,
    "qs:photos_1k":1,
    "qs:photos_9k":1,
    "qs:photos_9r":1,
    "qs:photos_all":3,
    "qs:photos_sr":1,
    "qs:placetype":"Suburb",
    "qs:pop_sr":"0",
    "wof:name":"Sanwal Nagar",
    "wof:placetype":"neighbourhood"
},
  "geometry": {"coordinates":[77.23212700000001,28.558666],"type":"Point"}
}