{
  "type": "Feature",
  "properties": {
    "iso:country":"IN",
    "ks:ks_name":"Kumhar Tola",
    "ks:ks_pop":55,
    "ks:ks_type":"HABITATION",
    "name:eng_x_preferred":[
        "Kumhar Tola"
    ],
    "wof:name":"Kumhar Tola",
    "wof:placetype":"locality",
    "wof:population":55
},
  "geometry": {"coordinates":[84.101249,26.204784],"type":"Point"}
}