{
  "type": "Feature",
  "properties": {
    "gn:admin1_code":"36",
    "gn:admin2_code":"197.0",
    "gn:asciiname":"Maniaripur",
    "gn:country_code":"IN",
    "gn:dem":84,
    "gn:feature_class":"P",
    "gn:feature_code":"PPL",
    "gn:name":"Mani\u0101r\u012bpur",
    "gn:population":0,
    "gn:timezone":"Asia/Kolkata",
    "iso:country":"IN",
    "ks:ks_name":"Maniyaripur",
    "ks:ks_pop":1265,
    "ks:ks_type":"HABITATION",
    "name:eng_x_preferred":[
        "Maniyaripur"
    ],
    "name:eng_x_variant":[
        "Maniaripur"
    ],
    "wof:name":"Maniyaripur",
    "wof:placetype":"locality",
    "wof:population":1265
},
  "geometry": {"coordinates":[82.820955,25.349117],"type":"Point"}
}