{
  "type": "Feature",
  "properties": {
    "gn:admin1_code":"35.0",
    "gn:admin2_code":"454",
    "gn:asciiname":"Karanjia",
    "gn:country_code":"IN",
    "gn:dem":634,
    "gn:feature_class":"P",
    "gn:feature_code":"PPL",
    "gn:name":"Karanji\u0101",
    "gn:population":0,
    "gn:timezone":"Asia/Kolkata",
    "iso:country":"IN",
    "name:und_x_variant":[
        "Karanji\u0101",
        "Karanjia"
    ],
    "wof:name":"Karanjia",
    "wof:placetype":"locality"
},
  "geometry": {"coordinates":[80.77701,22.38022],"type":"Point"}
}