{
  "type": "Feature",
  "properties": {
    "iso:country":"IN",
    "ks:ks_name":"Souralugurumundi",
    "ks:ks_pop":16,
    "ks:ks_type":"VILLAGE",
    "name:eng_x_preferred":[
        "Souralugurumundi"
    ],
    "wof:name":"Souralugurumundi",
    "wof:placetype":"locality",
    "wof:population":16
},
  "geometry": {"coordinates":[84.002717,19.318423],"type":"Point"}
}