{
  "type": "Feature",
  "properties": {
    "iso:country":"IN",
    "ks:ks_alt_nam":"BABUTOLI",
    "ks:ks_name":"Babutoli",
    "ks:ks_pop":265,
    "ks:ks_type":"HABITATION",
    "name:eng_x_preferred":[
        "Babutoli"
    ],
    "wof:name":"Babutoli",
    "wof:placetype":"locality",
    "wof:population":265
},
  "geometry": {"coordinates":[83.700468,23.195595],"type":"Point"}
}