{
  "type": "Feature",
  "properties": {
    "gn:admin1_code":"25.0",
    "gn:admin2_code":"630.0",
    "gn:asciiname":"Tattinaiyakkanhalli",
    "gn:country_code":"IN",
    "gn:dem":492,
    "gn:feature_class":"P",
    "gn:feature_code":"PPL",
    "gn:name":"Tattin\u0101iyakkanhalli",
    "gn:population":0,
    "gn:timezone":"Asia/Kolkata",
    "iso:country":"IN",
    "wof:name":"Tattinaiyakkanhalli",
    "wof:placetype":"neighbourhood"
},
  "geometry": {"coordinates":[78.08244999999999,12.02049],"type":"Point"}
}