{
  "type": "Feature",
  "properties": {
    "iso:country":"IN",
    "name:ara_x_preferred":[
        "\u0633\u064a\u0645\u0627\u0643\u0627\u0644"
    ],
    "name:ben_bn_x_preferred":[
        "\u09b8\u09bf\u09ae\u09cd\u09ae\u09be\u0995\u09cd\u0995\u09be\u09b2"
    ],
    "name:ben_in_x_preferred":[
        "\u09b8\u09bf\u09ae\u09cd\u09ae\u09be\u0995\u09cd\u0995\u09be\u09b2"
    ],
    "name:eng_x_preferred":[
        "Simmakkal"
    ],
    "name:guj_x_preferred":[
        "\u0ab8\u0abf\u0aae\u0acd\u0aae\u0abe\u0a95\u0acd\u0a95\u0ab2"
    ],
    "name:hin_x_preferred":[
        "\u0938\u093f\u092e\u0915\u094d\u0915\u0932"
    ],
    "name:kan_x_preferred":[
        "\u0cb8\u0cbf\u0cae\u0ccd\u0cae\u0c95\u0ccd\u0c95\u0cb2\u0ccd"
    ],
    "name:mal_x_preferred":[
        "\u0d38\u0d3f\u0d2e\u0d4d\u0d2e\u0d15\u0d4d\u0d15\u0d7d"
    ],
    "name:mar_x_preferred":[
        "\u0938\u093f\u092e\u0915\u0915\u094d\u0915\u0932"
    ],
    "name:pan_x_preferred":[
        "\u0a38\u0a3f\u0a71\u0a2e\u0a3e\u0a15\u0a32"
    ],
    "name:tam_x_preferred":[
        "\u0b9a\u0bbf\u0bae\u0bcd\u0bae\u0b95\u0bcd\u0b95\u0bb2\u0bcd"
    ],
    "name:tel_x_preferred":[
        "\u0c38\u0c3f\u0c2e\u0c4d\u0c2e\u0c15\u0c4d\u0c15\u0c32\u0c4d"
    ],
    "name:urd_x_preferred":[
        "\u0633\u06cc\u0645\u0627\u06a9\u0651\u0644"
    ],
    "qs:gn_adm0_cc":"IN",
    "qs:gn_local":1264521,
    "qs:gn_nam_loc":"Madurai, Madurai, Tamil Nadu, IN",
    "qs:gn_namadm1":"25",
    "qs:local_max":1568,
    "qs:local_sum":2851,
    "qs:localhoods":8,
    "qs:name":"Simmakkal",
    "qs:name_adm0":"India",
    "qs:name_adm1":"Tamil Nadu",
    "qs:name_adm2":"Madurai",
    "qs:name_local":"Madurai",
    "qs:photo_max":170,
    "qs:photo_sum":653,
    "qs:placetype":"Suburb",
    "qs:quad_count":18,
    "qs:woe_adm0":23424848,
    "qs:woe_adm1":2345758,
    "qs:woe_adm2":12586687,
    "qs:woe_lau":0,
    "qs:woe_local":2295425,
    "qs:woe_ver":"7.10.0",
    "wof:lang":[
        "eng"
    ],
    "wof:name":"Simmakkal",
    "wof:placetype":"neighbourhood"
},
  "geometry": {"coordinates":[78.116951,9.919944],"type":"Point"}
}