{
  "type": "Feature",
  "properties": {
    "iso:country":"IN",
    "name:eng_x_preferred":[
        "Simmakkal"
    ],
    "qs:gn_adm0_cc":"IN",
    "qs:gn_local":1264521,
    "qs:gn_nam_loc":"Madurai, Madurai, Tamil Nadu, IN",
    "qs:gn_namadm1":"25",
    "qs:local_max":1568,
    "qs:local_sum":2851,
    "qs:localhoods":8,
    "qs:name":"Simmakkal",
    "qs:name_adm0":"India",
    "qs:name_adm1":"Tamil Nadu",
    "qs:name_adm2":"Madurai",
    "qs:name_local":"Madurai",
    "qs:photo_max":170,
    "qs:photo_sum":653,
    "qs:placetype":"Suburb",
    "qs:quad_count":18,
    "qs:woe_adm0":23424848,
    "qs:woe_adm1":2345758,
    "qs:woe_adm2":12586687,
    "qs:woe_lau":0,
    "qs:woe_local":2295425,
    "qs:woe_ver":"7.10.0",
    "wof:lang":[
        "eng"
    ],
    "wof:name":"Simmakkal",
    "wof:placetype":"neighbourhood"
},
  "geometry": {"coordinates":[78.116951,9.919944],"type":"Point"}
}