{
  "type": "Feature",
  "properties": {
    "gn:admin1_code":"39.0",
    "gn:admin2_code":"66.0",
    "gn:asciiname":"Danda Tok",
    "gn:country_code":"IN",
    "gn:dem":1286,
    "gn:feature_class":"P",
    "gn:feature_code":"PPL",
    "gn:name":"D\u0101nda Tok",
    "gn:population":0,
    "gn:timezone":"Asia/Kolkata",
    "iso:country":"IN",
    "wof:name":"Danda Tok",
    "wof:placetype":"locality"
},
  "geometry": {"coordinates":[79.69462,29.30002],"type":"Point"}
}