{
  "type": "Feature",
  "properties": {
    "gn:admin1_code":"36",
    "gn:admin2_code":"154.0",
    "gn:asciiname":"Lachhmanpur",
    "gn:country_code":"IN",
    "gn:dem":130,
    "gn:feature_class":"P",
    "gn:feature_code":"PPL",
    "gn:name":"Lachhmanpur",
    "gn:population":0,
    "gn:timezone":"Asia/Kolkata",
    "iso:country":"IN",
    "wof:name":"Lachhmanpur",
    "wof:placetype":"locality"
},
  "geometry": {"coordinates":[81.05568000000002,27.39147],"type":"Point"}
}