{
  "type": "Feature",
  "properties": {
    "iso:country":"IN",
    "ks:ks_alt_nam":"P.N.Palayam Colony",
    "ks:ks_name":"P.n.palayam Colony",
    "ks:ks_pop":4649,
    "ks:ks_type":"HABITATION",
    "name:eng_x_preferred":[
        "P.n.palayam Colony"
    ],
    "wof:name":"P.n.palayam Colony",
    "wof:placetype":"locality",
    "wof:population":4649
},
  "geometry": {"coordinates":[79.62622399999999,11.783075],"type":"Point"}
}