{
  "type": "Feature",
  "properties": {
    "gn:admin1_code":"19.0",
    "gn:admin2_code":"573.0",
    "gn:asciiname":"Yadavanahalli",
    "gn:country_code":"IN",
    "gn:dem":675,
    "gn:feature_class":"P",
    "gn:feature_code":"PPL",
    "gn:name":"Yadavanahalli",
    "gn:population":0,
    "gn:timezone":"Asia/Kolkata",
    "iso:country":"IN",
    "wof:name":"Yadavanahalli",
    "wof:placetype":"locality"
},
  "geometry": {"coordinates":[76.95336999999998,12.79064],"type":"Point"}
}