{
  "type": "Feature",
  "properties": {
    "iso:country":"IN",
    "ks:ks_name":"Sukriora",
    "ks:ks_pop":79,
    "ks:ks_type":"HABITATION",
    "name:eng_x_preferred":[
        "Sukriora"
    ],
    "wof:name":"Sukriora",
    "wof:placetype":"locality",
    "wof:population":79
},
  "geometry": {"coordinates":[85.496118,23.062454],"type":"Point"}
}