{
  "type": "Feature",
  "properties": {
    "gn:admin1_code":"34.0",
    "gn:admin2_code":"230.0",
    "gn:asciiname":"Malpur",
    "gn:country_code":"IN",
    "gn:dem":52,
    "gn:feature_class":"P",
    "gn:feature_code":"PPL",
    "gn:name":"M\u0101lpur",
    "gn:population":0,
    "gn:timezone":"Asia/Kolkata",
    "iso:country":"IN",
    "name:ara_x_preferred":[
        "\u0645\u0627\u0644\u0628\u0648\u0631"
    ],
    "name:ben_bn_x_preferred":[
        "\u09ae\u09be\u09b2\u09aa\u09c1\u09b0"
    ],
    "name:ben_in_x_preferred":[
        "\u09ae\u09be\u09b2\u09aa\u09c1\u09b0"
    ],
    "name:bpy_x_preferred":[
        "\u09ae\u09be\u09b2\u09aa\u09c1\u09b0"
    ],
    "name:ceb_x_preferred":[
        "M\u0101lpur"
    ],
    "name:guj_x_preferred":[
        "\u0aae\u0abe\u0ab2\u0aaa\u0ac1\u0ab0"
    ],
    "name:hin_x_preferred":[
        "\u092e\u093e\u0932\u092a\u0941\u0930"
    ],
    "name:ita_x_preferred":[
        "Malpur"
    ],
    "name:kan_x_preferred":[
        "\u0cae\u0cb2\u0ccd\u0caa\u0cc1\u0cb0\u0ccd"
    ],
    "name:mal_x_preferred":[
        "\u0d2e\u0d3e\u0d7d\u0d2a\u0d42\u0d7c"
    ],
    "name:mar_x_preferred":[
        "\u092e\u093e\u0932\u092a\u0942\u0930"
    ],
    "name:mlg_x_preferred":[
        "Malpur"
    ],
    "name:msa_x_preferred":[
        "Malpur"
    ],
    "name:new_x_preferred":[
        "\u092e\u0932\u094d\u092a\u0941\u0930"
    ],
    "name:nld_x_preferred":[
        "Malpur"
    ],
    "name:pan_x_preferred":[
        "\u0a2e\u0a32\u0a2a\u0a41\u0a30"
    ],
    "name:swe_x_preferred":[
        "M\u0101lpur"
    ],
    "name:tam_x_preferred":[
        "\u0bae\u0bbe\u0bb2\u0bcd\u0baa\u0bc2\u0bb0\u0bcd"
    ],
    "name:tel_x_preferred":[
        "\u0c2e\u0c3e\u0c32\u0c4d\u0c2a\u0c42\u0c30\u0c4d"
    ],
    "name:urd_x_preferred":[
        "\u0645\u0644\u067e\u0648\u0631"
    ],
    "name:vie_x_preferred":[
        "Malpur"
    ],
    "name:zho_x_preferred":[
        "\u9a6c\u5c14\u666e\u5c14"
    ],
    "wof:name":"Malpur",
    "wof:placetype":"locality"
},
  "geometry": {"coordinates":[85.37014000000001,25.45979],"type":"Point"}
}