{
  "type": "Feature",
  "properties": {
    "iso:country":"IN",
    "ks:ks_alt_nam":"N\u0101gal\u0101puram Reserved Forest",
    "ks:ks_name":"Nagalapuram Reserved Forest",
    "ks:ks_type":"VILLAGE",
    "name:eng_x_preferred":[
        "Nagalapuram Reserved Forest"
    ],
    "name:eng_x_variant":[
        "N\u0101gal\u0101puram Reserved Forest"
    ],
    "wof:name":"Nagalapuram Reserved Forest",
    "wof:placetype":"locality"
},
  "geometry": {"coordinates":[79.769355,13.430051],"type":"Point"}
}