{
  "type": "Feature",
  "properties": {
    "gn:admin1_code":"24.0",
    "gn:admin2_code":"126.0",
    "gn:asciiname":"Chauganwri",
    "gn:country_code":"IN",
    "gn:dem":410,
    "gn:feature_class":"P",
    "gn:feature_code":"PPL",
    "gn:name":"Chaug\u0101nwri",
    "gn:population":0,
    "gn:timezone":"Asia/Kolkata",
    "iso:country":"IN",
    "wof:name":"Chauganwri",
    "wof:placetype":"neighbourhood"
},
  "geometry": {"coordinates":[74.66731,25.02114],"type":"Point"}
}