{
  "type": "Feature",
  "properties": {
    "iso:country":"IN",
    "ks:ks_alt_nam":"kicharan",
    "ks:ks_name":"Kicharan",
    "ks:ks_pop":228,
    "ks:ks_type":"HABITATION",
    "name:eng_x_preferred":[
        "Kicharan"
    ],
    "wof:name":"Kicharan",
    "wof:placetype":"locality",
    "wof:population":228
},
  "geometry": {"coordinates":[82.119281,25.360756],"type":"Point"}
}