{
  "type": "Feature",
  "properties": {
    "iso:country":"IN",
    "ks:ks_name":"Sakariya",
    "ks:ks_pop":413,
    "ks:ks_type":"HABITATION",
    "name:eng_x_preferred":[
        "Sakariya"
    ],
    "wof:name":"Sakariya",
    "wof:placetype":"locality",
    "wof:population":413
},
  "geometry": {"coordinates":[81.67039699999999,23.085087],"type":"Point"}
}