{
  "type": "Feature",
  "properties": {
    "gn:admin1_code":"16.0",
    "gn:admin2_code":"498.0",
    "gn:asciiname":"Darana",
    "gn:country_code":"IN",
    "gn:dem":225,
    "gn:feature_class":"P",
    "gn:feature_code":"PPL",
    "gn:name":"Dar\u0101na",
    "gn:population":0,
    "gn:timezone":"Asia/Kolkata",
    "iso:country":"IN",
    "wof:name":"Darana",
    "wof:placetype":"locality"
},
  "geometry": {"coordinates":[74.68799,21.14004],"type":"Point"}
}