{
  "type": "Feature",
  "properties": {
    "gn:admin1_code":"37",
    "gn:admin2_code":"405.0",
    "gn:asciiname":"Siriagarh",
    "gn:country_code":"IN",
    "gn:dem":212,
    "gn:feature_class":"P",
    "gn:feature_code":"PPL",
    "gn:name":"Siriagarh",
    "gn:population":0,
    "gn:timezone":"Asia/Kolkata",
    "iso:country":"IN",
    "wof:name":"Siriagarh",
    "wof:placetype":"locality"
},
  "geometry": {"coordinates":[83.03426,21.76234],"type":"Point"}
}