{
  "type": "Feature",
  "properties": {
    "iso:country":"IN",
    "ks:ks_name":"Gosaintola",
    "ks:ks_pop":0,
    "ks:ks_type":"VILLAGE",
    "name:eng_x_preferred":[
        "Gosaintola"
    ],
    "wof:name":"Gosaintola",
    "wof:placetype":"locality",
    "wof:population":0
},
  "geometry": {"coordinates":[87.74258399999999,25.069091],"type":"Point"}
}