{
  "type": "Feature",
  "properties": {
    "iso:country":"IN",
    "ks:ks_name":"Cheedipalem Rf",
    "ks:ks_pop":59,
    "ks:ks_type":"HABITATION",
    "name:eng_x_preferred":[
        "Cheedipalem Rf"
    ],
    "wof:name":"Cheedipalem Rf",
    "wof:placetype":"locality",
    "wof:population":59
},
  "geometry": {"coordinates":[82.673175,18.021173],"type":"Point"}
}