{
  "type": "Feature",
  "properties": {
    "iso:country":"IN",
    "ks:ks_alt_nam":"Basant pur",
    "ks:ks_name":"Basant Pur",
    "ks:ks_pop":143,
    "ks:ks_type":"HABITATION",
    "name:eng_x_preferred":[
        "Basant Pur"
    ],
    "wof:name":"Basant Pur",
    "wof:placetype":"locality",
    "wof:population":143
},
  "geometry": {"coordinates":[83.877043,26.08747],"type":"Point"}
}