{
  "type": "Feature",
  "properties": {
    "gn:admin1_code":"36.0",
    "gn:admin2_code":"151.0",
    "gn:asciiname":"Lodhpura",
    "gn:country_code":"IN",
    "gn:dem":186,
    "gn:feature_class":"P",
    "gn:feature_code":"PPL",
    "gn:name":"Lodhpura",
    "gn:population":0,
    "gn:timezone":"Asia/Kolkata",
    "iso:country":"IN",
    "wof:name":"Lodhpura",
    "wof:placetype":"locality"
},
  "geometry": {"coordinates":[79.84733,28.61279],"type":"Point"}
}