{
  "type": "Feature",
  "properties": {
    "iso:country":"IN",
    "ks:ks_name":"Chamaraut",
    "ks:ks_pop":100,
    "ks:ks_type":"HABITATION",
    "name:eng_x_preferred":[
        "Chamaraut"
    ],
    "wof:name":"Chamaraut",
    "wof:placetype":"locality",
    "wof:population":100
},
  "geometry": {"coordinates":[82.44548500000001,24.945518],"type":"Point"}
}