{
  "type": "Feature",
  "properties": {
    "gn:admin1_code":"13.0",
    "gn:admin2_code":"601.0",
    "gn:asciiname":"Kolluvila",
    "gn:country_code":"IN",
    "gn:dem":113,
    "gn:feature_class":"P",
    "gn:feature_code":"PPL",
    "gn:name":"Kolluvila",
    "gn:population":0,
    "gn:timezone":"Asia/Kolkata",
    "iso:country":"IN",
    "ks:ks_name":"Kolluvila",
    "ks:ks_pop":3069,
    "ks:ks_type":"HABITATION",
    "name:eng_x_preferred":[
        "Kolluvila"
    ],
    "wof:name":"Kolluvila",
    "wof:placetype":"locality",
    "wof:population":3069
},
  "geometry": {"coordinates":[76.925977,8.751119],"type":"Point"}
}