{
  "type": "Feature",
  "properties": {
    "gn:admin1_code":"19.0",
    "gn:admin2_code":"582.0",
    "gn:asciiname":"Babenahalli",
    "gn:country_code":"IN",
    "gn:dem":667,
    "gn:feature_class":"P",
    "gn:feature_code":"PPL",
    "gn:name":"B\u0101benahalli",
    "gn:population":0,
    "gn:timezone":"Asia/Kolkata",
    "iso:country":"IN",
    "ks:ks_alt_nam":"B\u0101benahalli",
    "ks:ks_name":"Babenahalli",
    "ks:ks_type":"VILLAGE",
    "name:eng_x_preferred":[
        "Babenahalli"
    ],
    "name:eng_x_variant":[
        "B\u0101benahalli"
    ],
    "wof:name":"Babenahalli",
    "wof:placetype":"locality"
},
  "geometry": {"coordinates":[77.49036,13.683257],"type":"Point"}
}