{
  "type": "Feature",
  "properties": {
    "iso:country":"IN",
    "ks:ks_name":"Mahijipura",
    "ks:ks_pop":710,
    "ks:ks_type":"HABITATION",
    "name:eng_x_preferred":[
        "Mahijipura"
    ],
    "wof:name":"Mahijipura",
    "wof:placetype":"locality",
    "wof:population":710
},
  "geometry": {"coordinates":[72.797222,22.503111],"type":"Point"}
}