{
  "type": "Feature",
  "properties": {
    "iso:country":"IN",
    "ks:ks_name":"Godar Par",
    "ks:ks_pop":775,
    "ks:ks_type":"HABITATION",
    "name:eng_x_preferred":[
        "Godar Par"
    ],
    "wof:name":"Godar Par",
    "wof:placetype":"locality",
    "wof:population":775
},
  "geometry": {"coordinates":[89.275373,26.197834],"type":"Point"}
}