{
  "type": "Feature",
  "properties": {
    "iso:country":"IN",
    "ks:ks_name":"Pura Sukhlan",
    "ks:ks_pop":350,
    "ks:ks_type":"HABITATION",
    "name:eng_x_preferred":[
        "Pura Sukhlan"
    ],
    "wof:name":"Pura Sukhlan",
    "wof:placetype":"locality",
    "wof:population":350
},
  "geometry": {"coordinates":[81.638628,26.556683],"type":"Point"}
}