{
  "type": "Feature",
  "properties": {
    "iso:country":"IN",
    "ks:ks_name":"Ghola",
    "ks:ks_pop":774,
    "ks:ks_type":"VILLAGE",
    "name:eng_x_preferred":[
        "Ghola"
    ],
    "wof:name":"Ghola",
    "wof:placetype":"locality",
    "wof:population":774
},
  "geometry": {"coordinates":[87.839083,22.413405],"type":"Point"}
}