{
  "type": "Feature",
  "properties": {
    "iso:country":"IN",
    "ks:ks_name":"S Jerribadra",
    "ks:ks_pop":122,
    "ks:ks_type":"HABITATION",
    "name:eng_x_preferred":[
        "S Jerribadra"
    ],
    "wof:name":"S Jerribadra",
    "wof:placetype":"locality",
    "wof:population":122
},
  "geometry": {"coordinates":[84.322013,18.765679],"type":"Point"}
}