{
  "type": "Feature",
  "properties": {
    "gn:admin1_code":"36",
    "gn:admin2_code":"176.0",
    "gn:asciiname":"Paradepao",
    "gn:country_code":"IN",
    "gn:dem":122,
    "gn:feature_class":"P",
    "gn:feature_code":"PPL",
    "gn:name":"Paradepao",
    "gn:population":0,
    "gn:timezone":"Asia/Kolkata",
    "iso:country":"IN",
    "wof:name":"Paradepao",
    "wof:placetype":"neighbourhood"
},
  "geometry": {"coordinates":[81.2449,26.87149],"type":"Point"}
}