{
  "type": "Feature",
  "properties": {
    "iso:country":"IN",
    "ks:ks_alt_nam":"Bhagw\u0101n Jot",
    "ks:ks_name":"Bhagwan Jot",
    "ks:ks_type":"VILLAGE",
    "name:eng_x_preferred":[
        "Bhagwan Jot"
    ],
    "name:eng_x_variant":[
        "Bhagw\u0101n Jot"
    ],
    "wof:name":"Bhagwan Jot",
    "wof:placetype":"locality"
},
  "geometry": {"coordinates":[82.37209300000001,26.72249],"type":"Point"}
}