{
  "type": "Feature",
  "properties": {
    "iso:country":"IN",
    "ks:ks_name":"Chunkudar",
    "ks:ks_pop":389,
    "ks:ks_type":"VILLAGE",
    "name:eng_x_preferred":[
        "Chunkudar"
    ],
    "wof:name":"Chunkudar",
    "wof:placetype":"locality",
    "wof:population":389
},
  "geometry": {"coordinates":[87.082542,23.995728],"type":"Point"}
}