{
  "type": "Feature",
  "properties": {
    "gn:admin1_code":"36",
    "gn:admin2_code":"191.0",
    "gn:asciiname":"Bisani",
    "gn:country_code":"IN",
    "gn:dem":81,
    "gn:feature_class":"P",
    "gn:feature_code":"PPL",
    "gn:name":"Bis\u0101ni",
    "gn:population":0,
    "gn:timezone":"Asia/Kolkata",
    "iso:country":"IN",
    "ks:ks_alt_nam":"Bis\u0101ni",
    "ks:ks_name":"Bisani",
    "ks:ks_type":"VILLAGE",
    "ks:ks_uagg_main":0,
    "name:eng_x_preferred":[
        "Bisani"
    ],
    "name:eng_x_variant":[
        "Bis\u0101ni"
    ],
    "wof:name":"Bisani",
    "wof:placetype":"neighbourhood"
},
  "geometry": {"coordinates":[83.215155,25.795864],"type":"Point"}
}