{
  "type": "Feature",
  "properties": {
    "iso:country":"IN",
    "ks:ks_name":"Melnemmar",
    "ks:ks_pop":10,
    "ks:ks_type":"HABITATION",
    "name:eng_x_preferred":[
        "Melnemmar"
    ],
    "wof:name":"Melnemmar",
    "wof:placetype":"locality",
    "wof:population":10
},
  "geometry": {"coordinates":[75.225859,13.376934],"type":"Point"}
}