{
  "type": "Feature",
  "properties": {
    "gn:admin1_code":"36.0",
    "gn:admin2_code":"173.0",
    "gn:asciiname":"Teunga",
    "gn:country_code":"IN",
    "gn:dem":102,
    "gn:feature_class":"P",
    "gn:feature_code":"PPL",
    "gn:name":"Te\u016bnga",
    "gn:population":0,
    "gn:timezone":"Asia/Kolkata",
    "iso:country":"IN",
    "name:hin_x_preferred":[
        "\u091f\u0947\u090a\u0902\u0917\u093e"
    ],
    "name:urd_x_preferred":[
        "\u0679\u06cc\u0648\u0646\u06af\u0627"
    ],
    "wof:name":"Teunga",
    "wof:placetype":"locality"
},
  "geometry": {"coordinates":[81.96069,25.89855],"type":"Point"}
}