{
  "type": "Feature",
  "properties": {
    "iso:country":"IN",
    "ks:ks_name":"Nayanivaripalle",
    "ks:ks_pop":45,
    "ks:ks_type":"HABITATION",
    "name:eng_x_preferred":[
        "Nayanivaripalle"
    ],
    "wof:name":"Nayanivaripalle",
    "wof:placetype":"locality",
    "wof:population":45
},
  "geometry": {"coordinates":[78.951093,13.89308],"type":"Point"}
}