{
  "type": "Feature",
  "properties": {
    "iso:country":"IN",
    "ks:ks_name":"Kotravalli",
    "ks:ks_pop":32,
    "ks:ks_type":"HABITATION",
    "name:eng_x_preferred":[
        "Kotravalli"
    ],
    "wof:name":"Kotravalli",
    "wof:placetype":"locality",
    "wof:population":32
},
  "geometry": {"coordinates":[75.265642,13.527773],"type":"Point"}
}