{
  "type": "Feature",
  "properties": {
    "iso:country":"IN",
    "ks:ks_name":"Guduripanka",
    "ks:ks_pop":64,
    "ks:ks_type":"HABITATION",
    "name:eng_x_preferred":[
        "Guduripanka"
    ],
    "wof:name":"Guduripanka",
    "wof:placetype":"locality",
    "wof:population":64
},
  "geometry": {"coordinates":[84.15334799999999,19.492579],"type":"Point"}
}