{
  "type": "Feature",
  "properties": {
    "iso:country":"IN",
    "ks:ks_name":"Modenga",
    "ks:ks_pop":396,
    "ks:ks_type":"VILLAGE",
    "name:eng_x_preferred":[
        "Modenga"
    ],
    "wof:name":"Modenga",
    "wof:placetype":"locality",
    "wof:population":396
},
  "geometry": {"coordinates":[81.447417,19.717117],"type":"Point"}
}