{
  "type": "Feature",
  "properties": {
    "iso:country":"IN",
    "ks:ks_name":"Barkur",
    "ks:ks_pop":470,
    "ks:ks_type":"VILLAGE",
    "name:eng_x_preferred":[
        "Barkur"
    ],
    "wof:name":"Barkur",
    "wof:placetype":"locality",
    "wof:population":470
},
  "geometry": {"coordinates":[91.13739200000001,26.508078],"type":"Point"}
}