{
  "type": "Feature",
  "properties": {
    "iso:country":"IN",
    "ks:ks_alt_nam":"Thirupathi koil vattam",
    "ks:ks_name":"Thirupathi Koil Vattam",
    "ks:ks_pop":206,
    "ks:ks_type":"HABITATION",
    "ks:ks_uagg_main":0,
    "name:eng_x_preferred":[
        "Thirupathi Koil Vattam"
    ],
    "wof:name":"Thirupathi Koil Vattam",
    "wof:placetype":"neighbourhood",
    "wof:population":206
},
  "geometry": {"coordinates":[78.648771,12.421439],"type":"Point"}
}