{
  "type": "Feature",
  "properties": {
    "iso:country":"IN",
    "ks:ks_name":"Bichitra Chow Para",
    "ks:ks_pop":66,
    "ks:ks_type":"HABITATION",
    "name:eng_x_preferred":[
        "Bichitra Chow Para"
    ],
    "wof:name":"Bichitra Chow Para",
    "wof:placetype":"locality",
    "wof:population":66
},
  "geometry": {"coordinates":[91.808982,24.037538],"type":"Point"}
}