{
  "type": "Feature",
  "properties": {
    "iso:country":"IN",
    "ks:ks_name":"Ganesh Mandal Basa",
    "ks:ks_pop":419,
    "ks:ks_type":"HABITATION",
    "ks:ks_uagg_main":0,
    "name:eng_x_preferred":[
        "Ganesh Mandal Basa"
    ],
    "wof:name":"Ganesh Mandal Basa",
    "wof:placetype":"neighbourhood",
    "wof:population":419
},
  "geometry": {"coordinates":[86.84365,25.58368],"type":"Point"}
}