{
  "type": "Feature",
  "properties": {
    "iso:country":"IN",
    "ks:ks_name":"Chopdi",
    "ks:ks_pop":519,
    "ks:ks_type":"VILLAGE",
    "name:eng_x_preferred":[
        "Chopdi"
    ],
    "wof:name":"Chopdi",
    "wof:placetype":"locality",
    "wof:population":519
},
  "geometry": {"coordinates":[73.669664,21.763516],"type":"Point"}
}