{
  "type": "Feature",
  "properties": {
    "iso:country":"IN",
    "ks:ks_name":"Ghagrapar Pt I",
    "ks:ks_pop":1388,
    "ks:ks_type":"VILLAGE",
    "ks:ks_uagg_main":0,
    "name:eng_x_preferred":[
        "Ghagrapar Pt I"
    ],
    "wof:name":"Ghagrapar Pt I",
    "wof:placetype":"neighbourhood",
    "wof:population":1388
},
  "geometry": {"coordinates":[92.664502,24.832438],"type":"Point"}
}