{
  "type": "Feature",
  "properties": {
    "iso:country":"IN",
    "name:dut_x_preferred":[
        "Ettumanoor"
    ],
    "name:eng_x_preferred":[
        "Ettumanoor"
    ],
    "name:mal_x_preferred":[
        "\u0d0f\u0d31\u0d4d\u0d31\u0d41\u0d2e\u0d3e\u0d28\u0d42\u0d7c"
    ],
    "name:tam_x_preferred":[
        "\u0b8e\u0b9f\u0bcd\u0b9f\u0bc1\u0bae\u0ba9\u0bc2\u0bb0\u0bcd"
    ],
    "name:urd_x_preferred":[
        "\u0627\u06cc\u0679\u0648\u0645\u0627\u0646\u0648\u0631"
    ],
    "qs:name":"Ettumanoor",
    "qs:name_adm0":"India",
    "qs:name_adm1":"Kerala",
    "qs:photos":29,
    "qs:photos_1k":6,
    "qs:photos_9k":1,
    "qs:photos_9r":2,
    "qs:photos_all":29,
    "qs:photos_sr":2,
    "qs:placetype":"Town",
    "qs:pop_sr":"0",
    "wd:wordcount":1715,
    "wof:name":"Ettumanoor",
    "wof:placetype":"locality"
},
  "geometry": {"coordinates":[76.558052,9.673564],"type":"Point"}
}