{
  "type": "Feature",
  "properties": {
    "gn:admin1_code":"34.0",
    "gn:admin2_code":"239.0",
    "gn:asciiname":"Lodipur",
    "gn:country_code":"IN",
    "gn:dem":78,
    "gn:feature_class":"P",
    "gn:feature_code":"PPL",
    "gn:name":"Lodipur",
    "gn:population":0,
    "gn:timezone":"Asia/Kolkata",
    "iso:country":"IN",
    "ks:ks_name":"Lodipur",
    "ks:ks_type":"VILLAGE",
    "ks:ks_uagg_main":0,
    "name:eng_x_preferred":[
        "Lodipur"
    ],
    "name:hif_x_preferred":[
        "Lodipur"
    ],
    "wof:name":"Lodipur",
    "wof:placetype":"neighbourhood"
},
  "geometry": {"coordinates":[85.15430000000001,25.077413],"type":"Point"}
}