{
  "type": "Feature",
  "properties": {
    "gn:admin1_code":"35.0",
    "gn:admin2_code":"439.0",
    "gn:asciiname":"Nachanbor",
    "gn:country_code":"IN",
    "gn:dem":632,
    "gn:feature_class":"P",
    "gn:feature_code":"PPL",
    "gn:name":"N\u0101chanbor",
    "gn:population":0,
    "gn:timezone":"Asia/Kolkata",
    "iso:country":"IN",
    "ks:ks_alt_nam":"N\u0101chanbor",
    "ks:ks_name":"Nachanbor",
    "ks:ks_type":"VILLAGE",
    "name:eng_x_preferred":[
        "Nachanbor"
    ],
    "name:eng_x_variant":[
        "N\u0101chanbor"
    ],
    "wof:name":"Nachanbor",
    "wof:placetype":"locality"
},
  "geometry": {"coordinates":[75.758562,22.391984],"type":"Point"}
}