{
  "type": "Feature",
  "properties": {
    "iso:country":"IN",
    "ks:ks_name":"Tidhara",
    "ks:ks_pop":2541,
    "ks:ks_type":"VILLAGE",
    "name:eng_x_preferred":[
        "Tidhara"
    ],
    "wof:name":"Tidhara",
    "wof:placetype":"locality",
    "wof:population":2541
},
  "geometry": {"coordinates":[72.919877,20.435602],"type":"Point"}
}