{
  "type": "Feature",
  "properties": {
    "iso:country":"IN",
    "ks:ks_name":"Luduriput",
    "ks:ks_pop":45,
    "ks:ks_type":"VILLAGE",
    "name:eng_x_preferred":[
        "Luduriput"
    ],
    "wof:name":"Luduriput",
    "wof:placetype":"locality",
    "wof:population":45
},
  "geometry": {"coordinates":[83.130212,19.049073],"type":"Point"}
}