{
  "type": "Feature",
  "properties": {
    "iso:country":"IN",
    "ks:ks_name":"Khodar Bazar",
    "ks:ks_pop":4997,
    "ks:ks_type":"VILLAGE",
    "ks:ks_uagg_main":0,
    "name:eng_x_preferred":[
        "Khodar Bazar"
    ],
    "wof:name":"Khodar Bazar",
    "wof:placetype":"locality",
    "wof:population":4997
},
  "geometry": {"coordinates":[88.42516000000001,22.36124],"type":"Point"}
}