{
  "type": "Feature",
  "properties": {
    "iso:country":"IN",
    "ks:ks_name":"Marasettihalli",
    "ks:ks_pop":809,
    "ks:ks_type":"HABITATION",
    "name:eng_x_preferred":[
        "Marasettihalli"
    ],
    "wof:name":"Marasettihalli",
    "wof:placetype":"locality",
    "wof:population":809
},
  "geometry": {"coordinates":[76.353171,13.175136],"type":"Point"}
}