{
  "type": "Feature",
  "properties": {
    "iso:country":"IN",
    "ks:ks_name":"Jabaguda",
    "ks:ks_pop":166,
    "ks:ks_type":"HABITATION",
    "name:eng_x_preferred":[
        "Jabaguda"
    ],
    "wof:name":"Jabaguda",
    "wof:placetype":"locality",
    "wof:population":166
},
  "geometry": {"coordinates":[82.598902,19.470993],"type":"Point"}
}