{
  "type": "Feature",
  "properties": {
    "iso:country":"IN",
    "ks:ks_name":"Umchetri",
    "ks:ks_pop":228,
    "ks:ks_type":"HABITATION",
    "name:eng_x_preferred":[
        "Umchetri"
    ],
    "wof:name":"Umchetri",
    "wof:placetype":"locality",
    "wof:population":228
},
  "geometry": {"coordinates":[92.21032599999999,25.933493],"type":"Point"}
}