{
  "type": "Feature",
  "properties": {
    "gn:admin1_code":"36.0",
    "gn:admin2_code":"136.0",
    "gn:asciiname":"Milak Ahladpur Karar",
    "gn:country_code":"IN",
    "gn:dem":188,
    "gn:feature_class":"P",
    "gn:feature_code":"PPL",
    "gn:name":"Milak Ahl\u0101dpur Kar\u0101r",
    "gn:population":0,
    "gn:timezone":"Asia/Kolkata",
    "iso:country":"IN",
    "wof:name":"Milak Ahladpur Karar",
    "wof:placetype":"locality"
},
  "geometry": {"coordinates":[78.93616999999998,28.5661],"type":"Point"}
}