{
  "type": "Feature",
  "properties": {
    "gn:admin1_code":"13.0",
    "gn:admin2_code":"593.0",
    "gn:asciiname":"Panniyur",
    "gn:country_code":"IN",
    "gn:dem":11,
    "gn:feature_class":"P",
    "gn:feature_code":"PPL",
    "gn:name":"Panniy\u016br",
    "gn:population":0,
    "gn:timezone":"Asia/Kolkata",
    "iso:country":"IN",
    "ks:ks_name":"Panniyoor",
    "ks:ks_pop":3475,
    "ks:ks_type":"HABITATION",
    "name:eng_x_preferred":[
        "Panniyoor"
    ],
    "name:eng_x_variant":[
        "Panniyur"
    ],
    "wof:name":"Panniyoor",
    "wof:placetype":"locality",
    "wof:population":3475
},
  "geometry": {"coordinates":[76.05911500000001,10.83207],"type":"Point"}
}