{
  "type": "Feature",
  "properties": {
    "iso:country":"IN",
    "ks:ks_name":"Mailoo Teron Gaon",
    "ks:ks_pop":120,
    "ks:ks_type":"HABITATION",
    "name:eng_x_preferred":[
        "Mailoo Teron Gaon"
    ],
    "wof:name":"Mailoo Teron Gaon",
    "wof:placetype":"locality",
    "wof:population":120
},
  "geometry": {"coordinates":[92.998548,25.837652],"type":"Point"}
}