{
  "type": "Feature",
  "properties": {
    "iso:country":"IN",
    "qs:name":"Rundh",
    "qs:name_adm0":"India",
    "qs:name_adm1":"Gujarat",
    "qs:photos":225,
    "qs:photos_1k":46,
    "qs:photos_9k":1,
    "qs:photos_9r":4,
    "qs:photos_all":225,
    "qs:photos_sr":4,
    "qs:placetype":"Town",
    "qs:pop_sr":"0",
    "wof:name":"Rundh",
    "wof:placetype":"neighbourhood"
},
  "geometry": {"coordinates":[72.778919,21.163532],"type":"Point"}
}