{
  "type": "Feature",
  "properties": {
    "iso:country":"IN",
    "ks:ks_name":"Karalakadu",
    "ks:ks_pop":544,
    "ks:ks_type":"HABITATION",
    "name:eng_x_preferred":[
        "Karalakadu"
    ],
    "wof:name":"Karalakadu",
    "wof:placetype":"locality",
    "wof:population":544
},
  "geometry": {"coordinates":[78.347049,11.522552],"type":"Point"}
}