{
  "type": "Feature",
  "properties": {
    "iso:country":"IN",
    "ks:ks_name":"Naseerpur Annant Singh",
    "ks:ks_pop":332,
    "ks:ks_type":"HABITATION",
    "name:eng_x_preferred":[
        "Naseerpur Annant Singh"
    ],
    "wof:name":"Naseerpur Annant Singh",
    "wof:placetype":"locality",
    "wof:population":332
},
  "geometry": {"coordinates":[81.008257,27.483747],"type":"Point"}
}