{
  "type": "Feature",
  "properties": {
    "iso:country":"IN",
    "ks:ks_name":"Nasirapur",
    "ks:ks_pop":372,
    "ks:ks_type":"HABITATION",
    "ks:ks_uagg_main":0,
    "name:eng_x_preferred":[
        "Nasirapur"
    ],
    "wof:name":"Nasirapur",
    "wof:placetype":"neighbourhood",
    "wof:population":372
},
  "geometry": {"coordinates":[80.71616,27.602705],"type":"Point"}
}