{
  "type": "Feature",
  "properties": {
    "iso:country":"IN",
    "ks:ks_name":"Muturmunda",
    "ks:ks_pop":159,
    "ks:ks_type":"HABITATION",
    "name:eng_x_preferred":[
        "Muturmunda"
    ],
    "wof:name":"Muturmunda",
    "wof:placetype":"locality",
    "wof:population":159
},
  "geometry": {"coordinates":[84.39957699999999,21.136502],"type":"Point"}
}