{
  "type": "Feature",
  "properties": {
    "iso:country":"IN",
    "ks:ks_name":"Dakshin Talbari",
    "ks:ks_pop":709,
    "ks:ks_type":"VILLAGE",
    "name:eng_x_preferred":[
        "Dakshin Talbari"
    ],
    "wof:name":"Dakshin Talbari",
    "wof:placetype":"locality",
    "wof:population":709
},
  "geometry": {"coordinates":[88.02731900000001,25.927535],"type":"Point"}
}