{
  "type": "Feature",
  "properties": {
    "iso:country":"IN",
    "ks:ks_name":"Saleri",
    "ks:ks_pop":34,
    "ks:ks_type":"VILLAGE",
    "name:eng_x_preferred":[
        "Saleri"
    ],
    "wof:name":"Saleri",
    "wof:placetype":"locality",
    "wof:population":34
},
  "geometry": {"coordinates":[83.99605699999999,20.541319],"type":"Point"}
}