{
  "type": "Feature",
  "properties": {
    "iso:country":"IN",
    "ks:ks_name":"Kari Chak",
    "ks:ks_pop":642,
    "ks:ks_type":"VILLAGE",
    "name:eng_x_preferred":[
        "Kari Chak"
    ],
    "wof:name":"Kari Chak",
    "wof:placetype":"locality",
    "wof:population":642
},
  "geometry": {"coordinates":[86.115903,25.467266],"type":"Point"}
}