{
  "type": "Feature",
  "properties": {
    "gn:admin1_code":"19.0",
    "gn:admin2_code":"567.0",
    "gn:asciiname":"Yeraganahalu",
    "gn:country_code":"IN",
    "gn:dem":631,
    "gn:feature_class":"P",
    "gn:feature_code":"PPL",
    "gn:name":"Yeraganah\u0101lu",
    "gn:population":0,
    "gn:timezone":"Asia/Kolkata",
    "iso:country":"IN",
    "wof:name":"Yeraganahalu",
    "wof:placetype":"locality"
},
  "geometry": {"coordinates":[75.53532,14.16754],"type":"Point"}
}