{
  "type": "Feature",
  "properties": {
    "gn:admin1_code":"2.0",
    "gn:admin2_code":"553.0",
    "gn:asciiname":"Pottuvandlapalle",
    "gn:country_code":"IN",
    "gn:dem":560,
    "gn:feature_class":"P",
    "gn:feature_code":"PPL",
    "gn:name":"Pottuv\u0101ndlapalle",
    "gn:population":0,
    "gn:timezone":"Asia/Kolkata",
    "iso:country":"IN",
    "wof:name":"Pottuvandlapalle",
    "wof:placetype":"locality"
},
  "geometry": {"coordinates":[78.27619,14.12155],"type":"Point"}
}