{
  "type": "Feature",
  "properties": {
    "iso:country":"IN",
    "name:ben_x_preferred":[
        "\u09b6\u09cd\u09b0\u09c0\u0995\u09be\u09b2\u09be\u09b9\u09b8\u09cd\u09a4\u09c0"
    ],
    "name:bpy_x_preferred":[
        "\u09b6\u09cd\u09b0\u09c0\u0995\u09be\u09b2\u09b9\u09b8\u09cd\u09a4\u09bf"
    ],
    "name:cat_x_preferred":[
        "Srikalahasti"
    ],
    "name:deu_x_preferred":[
        "Srikalahasti"
    ],
    "name:eng_x_preferred":[
        "Srikalahasti"
    ],
    "name:fra_x_preferred":[
        "Srikalahasti"
    ],
    "name:guj_x_preferred":[
        "\u0a95\u0abe\u0ab3\u0ab9\u0ab8\u0acd\u0aa4\u0ac0 \u0aae\u0a82\u0aa6\u0abf\u0ab0"
    ],
    "name:hin_x_preferred":[
        "\u0915\u093e\u0932\u093e\u0939\u0938\u094d\u0924\u0940 \u092e\u0902\u0926\u093f\u0930"
    ],
    "name:ita_x_preferred":[
        "Srikalahasti"
    ],
    "name:jpn_x_preferred":[
        "\u30b7\u30e5\u30ea\u30fc\u30ab\u30fc\u30e9\u30cf\u30b9\u30c6\u30a3"
    ],
    "name:kan_x_preferred":[
        "\u0cb6\u0ccd\u0cb0\u0cc0\u0c95\u0cbe\u0cb3\u0cb9\u0cb8\u0ccd\u0ca4\u0cbf"
    ],
    "name:kor_x_preferred":[
        "\uc2a4\ub9ac \uce7c\ub77c\ud558\uc2a4\ud2f0"
    ],
    "name:msa_x_preferred":[
        "Srikalahasti"
    ],
    "name:new_x_preferred":[
        "\u0936\u094d\u0930\u0940\u0915\u093e\u0932\u0939\u0938\u094d\u0924\u093f"
    ],
    "name:nld_x_preferred":[
        "Srikalahasti"
    ],
    "name:ori_x_preferred":[
        "\u0b36\u0b4d\u0b30\u0b40\u0b15\u0b33\u0b3e\u0b39\u0b38\u0b4d\u0b24\u0b40"
    ],
    "name:pam_x_preferred":[
        "Srikalahasti"
    ],
    "name:por_x_preferred":[
        "Srikalahasti"
    ],
    "name:rus_x_preferred":[
        "\u0428\u0440\u0438\u043a\u0430\u043b\u0430\u0445\u0430\u0441\u0442\u0438"
    ],
    "name:spa_x_preferred":[
        "Srikalahasti"
    ],
    "name:swe_x_preferred":[
        "Kalahasti"
    ],
    "name:tam_x_preferred":[
        "\u0ba4\u0bbf\u0bb0\u0bc1\u0b95\u0bcd\u0b95\u0bbe\u0bb3\u0ba4\u0bcd\u0ba4\u0bbf"
    ],
    "name:tat_x_preferred":[
        "\u041a\u0430\u043b\u0430\u0445\u0430\u0441\u0442\u0438"
    ],
    "name:tel_x_preferred":[
        "\u0c36\u0c4d\u0c30\u0c40\u0c15\u0c3e\u0c33\u0c39\u0c38\u0c4d\u0c24\u0c3f"
    ],
    "name:tgl_x_preferred":[
        "Srikalahasti"
    ],
    "name:urd_x_preferred":[
        "\u0634\u0631\u06cc \u06a9\u0627\u0644\u0627\u06c1\u0633\u062a\u06cc"
    ],
    "name:vie_x_preferred":[
        "Srikalahasti"
    ],
    "name:zho_x_preferred":[
        "\u65af\u91cc\u5361\u62c9\u54c8\u65af\u8482"
    ],
    "qs:name":"Srikalahasti",
    "qs:name_adm0":"India",
    "qs:name_adm1":"Andhra Pradesh",
    "qs:photos":41,
    "qs:photos_1k":8,
    "qs:photos_9k":1,
    "qs:photos_9r":2,
    "qs:photos_all":41,
    "qs:photos_sr":2,
    "qs:placetype":"Town",
    "qs:pop_sr":"0",
    "wd:wordcount":547,
    "wof:name":"Srikalahasti",
    "wof:placetype":"locality"
},
  "geometry": {"coordinates":[79.699265,13.766861],"type":"Point"}
}