{
  "type": "Feature",
  "properties": {
    "iso:country":"IN",
    "ks:ks_name":"Dulha Bigha",
    "ks:ks_pop":165,
    "ks:ks_type":"HABITATION",
    "name:eng_x_preferred":[
        "Dulha Bigha"
    ],
    "wof:name":"Dulha Bigha",
    "wof:placetype":"locality",
    "wof:population":165
},
  "geometry": {"coordinates":[84.884838,24.953547],"type":"Point"}
}