{
  "type": "Feature",
  "properties": {
    "gn:admin1_code":"35",
    "gn:admin2_code":"425.0",
    "gn:asciiname":"Paira",
    "gn:country_code":"IN",
    "gn:dem":159,
    "gn:feature_class":"P",
    "gn:feature_code":"PPL",
    "gn:name":"Paira",
    "gn:population":0,
    "gn:timezone":"Asia/Kolkata",
    "iso:country":"IN",
    "name:fas_x_preferred":[
        "\u067e\u06cc\u0631\u0627"
    ],
    "name:urd_x_preferred":[
        "\u067e\u06cc\u0631\u0627"
    ],
    "wof:name":"Paira",
    "wof:placetype":"locality"
},
  "geometry": {"coordinates":[80.29553,25.11308],"type":"Point"}
}