{
  "type": "Feature",
  "properties": {
    "iso:country":"IN",
    "ks:ks_alt_nam":"Mangi Lal Jyani ki Dhani",
    "ks:ks_name":"Mangi Lal Jyani Ki Dhani",
    "ks:ks_pop":50,
    "ks:ks_type":"HABITATION",
    "name:eng_x_preferred":[
        "Mangi Lal Jyani Ki Dhani"
    ],
    "wof:name":"Mangi Lal Jyani Ki Dhani",
    "wof:placetype":"locality",
    "wof:population":50
},
  "geometry": {"coordinates":[74.364593,29.843698],"type":"Point"}
}