{
  "type": "Feature",
  "properties": {
    "iso:country":"IN",
    "ks:ks_name":"Tulsiguda",
    "ks:ks_pop":162,
    "ks:ks_type":"HABITATION",
    "name:eng_x_preferred":[
        "Tulsiguda"
    ],
    "wof:name":"Tulsiguda",
    "wof:placetype":"locality",
    "wof:population":162
},
  "geometry": {"coordinates":[82.131102,18.433359],"type":"Point"}
}