{
  "type": "Feature",
  "properties": {
    "gn:admin1_code":"36",
    "gn:admin2_code":"134.0",
    "gn:asciiname":"Banwaripur",
    "gn:country_code":"IN",
    "gn:dem":276,
    "gn:feature_class":"P",
    "gn:feature_code":"PPL",
    "gn:name":"Banw\u0101r\u012bpur",
    "gn:population":0,
    "gn:timezone":"Asia/Kolkata",
    "iso:country":"IN",
    "name:und_x_variant":[
        "Banw\u0101r\u012bpur",
        "R\u0101mpur Mangal"
    ],
    "wof:name":"Banwaripur",
    "wof:placetype":"locality"
},
  "geometry": {"coordinates":[78.3463,29.65106],"type":"Point"}
}