{
  "type": "Feature",
  "properties": {
    "iso:country":"IN",
    "ks:ks_name":"Orvad",
    "ks:ks_pop":4207,
    "ks:ks_type":"URBAN",
    "name:eng_x_preferred":[
        "Orvad"
    ],
    "wof:name":"Orvad",
    "wof:placetype":"locality",
    "wof:population":4207
},
  "geometry": {"coordinates":[72.920249,20.451284],"type":"Point"}
}