{
  "type": "Feature",
  "properties": {
    "gn:admin1_code":"24.0",
    "gn:admin2_code":"129.0",
    "gn:asciiname":"Bakshpura",
    "gn:country_code":"IN",
    "gn:dem":317,
    "gn:feature_class":"P",
    "gn:feature_code":"PPL",
    "gn:name":"Bakshpura",
    "gn:population":0,
    "gn:timezone":"Asia/Kolkata",
    "iso:country":"IN",
    "ks:ks_name":"Bakshpura",
    "ks:ks_pop":491,
    "ks:ks_type":"VILLAGE",
    "ks:ks_uagg_main":0,
    "name:eng_x_preferred":[
        "Bakshpura"
    ],
    "wof:name":"Bakshpura",
    "wof:placetype":"neighbourhood",
    "wof:population":491
},
  "geometry": {"coordinates":[76.192719,24.533589],"type":"Point"}
}