{
  "type": "Feature",
  "properties": {
    "iso:country":"IN",
    "ks:ks_name":"Dharmu",
    "ks:ks_pop":1492,
    "ks:ks_type":"VILLAGE",
    "ks:ks_uagg_main":0,
    "name:eng_x_preferred":[
        "Dharmu"
    ],
    "wof:name":"Dharmu",
    "wof:placetype":"neighbourhood",
    "wof:population":1492
},
  "geometry": {"coordinates":[85.421953,24.089493],"type":"Point"}
}