{
  "type": "Feature",
  "properties": {
    "iso:country":"IN",
    "ks:ks_name":"Nal",
    "ks:ks_pop":838,
    "ks:ks_type":"VILLAGE",
    "name:eng_x_preferred":[
        "Nal"
    ],
    "wof:name":"Nal",
    "wof:placetype":"locality",
    "wof:population":838
},
  "geometry": {"coordinates":[73.176286,24.254769],"type":"Point"}
}