{
  "type": "Feature",
  "properties": {
    "gn:admin1_code":"10.0",
    "gn:admin2_code":"85.0",
    "gn:asciiname":"Jaliawas",
    "gn:country_code":"IN",
    "gn:dem":260,
    "gn:feature_class":"P",
    "gn:feature_code":"PPL",
    "gn:name":"Jali\u0101w\u0101s",
    "gn:population":0,
    "gn:timezone":"Asia/Kolkata",
    "iso:country":"IN",
    "name:und_x_variant":[
        "Jali\u0101w\u0101s"
    ],
    "wof:name":"Jaliawas",
    "wof:placetype":"locality"
},
  "geometry": {"coordinates":[76.5966,28.1029],"type":"Point"}
}