{
  "type": "Feature",
  "properties": {
    "iso:country":"IN",
    "ks:ks_name":"Jamra Laxmangarh",
    "ks:ks_pop":224,
    "ks:ks_type":"HABITATION",
    "name:eng_x_preferred":[
        "Jamra Laxmangarh"
    ],
    "wof:name":"Jamra Laxmangarh",
    "wof:placetype":"locality",
    "wof:population":224
},
  "geometry": {"coordinates":[72.129864,26.36135],"type":"Point"}
}