{
  "type": "Feature",
  "properties": {
    "iso:country":"IN",
    "ks:ks_name":"Umali Rampur",
    "ks:ks_pop":422,
    "ks:ks_type":"HABITATION",
    "name:eng_x_preferred":[
        "Umali Rampur"
    ],
    "wof:name":"Umali Rampur",
    "wof:placetype":"locality",
    "wof:population":422
},
  "geometry": {"coordinates":[76.403756,15.801992],"type":"Point"}
}