{
  "type": "Feature",
  "properties": {
    "iso:country":"IN",
    "ks:ks_alt_nam":"Gararia purwa",
    "ks:ks_name":"Gararia Purwa",
    "ks:ks_pop":208,
    "ks:ks_type":"HABITATION",
    "ks:ks_uagg_main":0,
    "name:eng_x_preferred":[
        "Gararia Purwa"
    ],
    "wof:name":"Gararia Purwa",
    "wof:placetype":"neighbourhood",
    "wof:population":208
},
  "geometry": {"coordinates":[81.517066,27.267709],"type":"Point"}
}