{
  "type": "Feature",
  "properties": {
    "gn:admin1_code":"25.0",
    "gn:admin2_code":"616.0",
    "gn:asciiname":"Pudukkottai",
    "gn:country_code":"IN",
    "gn:dem":53,
    "gn:feature_class":"P",
    "gn:feature_code":"PPL",
    "gn:name":"Pudukkottai",
    "gn:population":0,
    "gn:timezone":"Asia/Kolkata",
    "iso:country":"IN",
    "name:ara_x_preferred":[
        "\u0628\u0648\u062f\u0648\u0643\u0648\u062a\u062a\u064a"
    ],
    "name:ben_bn_x_preferred":[
        "\u09aa\u09c1\u09a6\u09c1\u0995\u09cd\u0995\u099f\u09cd\u099f\u09be\u0987"
    ],
    "name:ben_in_x_preferred":[
        "\u09aa\u09c1\u09a6\u09c1\u0995\u09cd\u0995\u099f\u09cd\u099f\u09be\u0987"
    ],
    "name:bih_x_preferred":[
        "\u092a\u0941\u0926\u0941\u0915\u094d\u0915\u094b\u091f\u094d\u091f\u0908"
    ],
    "name:bpy_x_preferred":[
        "\u09aa\u09c1\u09a1\u09bc\u09c1\u0995\u09cd\u0995\u09cb\u09a4\u09cd\u09a4\u09be\u0987"
    ],
    "name:cat_x_preferred":[
        "Pudukkottai"
    ],
    "name:ceb_x_preferred":[
        "Pudukkottai"
    ],
    "name:deu_x_preferred":[
        "Pudukkottai"
    ],
    "name:fra_x_preferred":[
        "Pudukkottai"
    ],
    "name:guj_x_preferred":[
        "\u0aaa\u0ac1\u0aa6\u0ac1\u0a95\u0acd\u0a95\u0acb\u0a9f\u0abe\u0a87"
    ],
    "name:hin_x_preferred":[
        "\u092a\u0941\u0926\u0941\u0915\u094b\u091f\u094d\u091f\u0908"
    ],
    "name:ita_x_preferred":[
        "Pudukkottai"
    ],
    "name:jpn_x_preferred":[
        "\u30d7\u30c9\u30a5\u30b3\u30fc\u30c3\u30bf\u30a4"
    ],
    "name:kan_x_preferred":[
        "\u0caa\u0ca6\u0cc1\u0c95\u0ccd\u0c95\u0cca\u0c9f\u0ccd\u0c9f\u0cc8"
    ],
    "name:mal_x_preferred":[
        "\u0d2a\u0d41\u0d24\u0d41\u0d15\u0d4d\u0d15\u0d4b\u0d1f\u0d4d\u0d1f"
    ],
    "name:mar_x_preferred":[
        "\u092a\u0941\u0921\u0941\u0915\u094b\u091f\u094d\u091f\u093e\u0908"
    ],
    "name:mlg_x_preferred":[
        "Pudukkottai"
    ],
    "name:msa_x_preferred":[
        "Pudukkottai"
    ],
    "name:nld_x_preferred":[
        "Pudukkottai"
    ],
    "name:ori_x_preferred":[
        "\u0b2a\u0b41\u0b21\u0b41\u0b15\u0b4d\u0b15\u0b4b\u0b1f\u0b4d\u0b1f\u0b3e\u0b07"
    ],
    "name:pan_x_preferred":[
        "\u0a2a\u0a41\u0a21\u0a42\u0a15\u0a4b\u0a1f\u0a3e\u0a08"
    ],
    "name:por_x_preferred":[
        "Puducotai"
    ],
    "name:rus_x_preferred":[
        "\u041f\u0443\u0434\u0443\u043a\u043a\u043e\u0442\u0442\u0430\u0439"
    ],
    "name:spa_x_preferred":[
        "Pudukkottai"
    ],
    "name:swe_x_preferred":[
        "Pudukkottai"
    ],
    "name:tam_x_preferred":[
        "\u0baa\u0bc1\u0ba4\u0bc1\u0b95\u0bcd\u0b95\u0bcb\u0b9f\u0bcd\u0b9f\u0bc8"
    ],
    "name:tel_x_preferred":[
        "\u0c2a\u0c41\u0c21\u0c41\u0c15\u0c4d\u0c15\u0c4a\u0c1f\u0c4d\u0c1f\u0c48"
    ],
    "name:tur_x_preferred":[
        "Pudukottai"
    ],
    "name:urd_x_preferred":[
        "\u067e\u0688\u0648\u06a9\u0651\u0648\u0679\u0627\u0626\u06cc"
    ],
    "name:urd_x_variant":[
        "\u067e\u0648\u062f\u0648\u06a9\u0648\u0679\u0627\u0626\u06cc"
    ],
    "name:vie_x_preferred":[
        "Pudukkottai"
    ],
    "name:zho_x_preferred":[
        "\u666e\u675c\u79d1\u6cf0"
    ],
    "wof:name":"Pudukkottai",
    "wof:placetype":"locality"
},
  "geometry": {"coordinates":[79.03691999999999,10.89541],"type":"Point"}
}