{
  "type": "Feature",
  "properties": {
    "iso:country":"IN",
    "ks:ks_name":"Kathipada",
    "ks:ks_pop":166,
    "ks:ks_type":"HABITATION",
    "name:eng_x_preferred":[
        "Kathipada"
    ],
    "wof:name":"Kathipada",
    "wof:placetype":"locality",
    "wof:population":166
},
  "geometry": {"coordinates":[72.80556199999999,19.86823],"type":"Point"}
}