{
  "type": "Feature",
  "properties": {
    "gn:admin1_code":"23",
    "gn:admin2_code":"38.0",
    "gn:asciiname":"Barar",
    "gn:country_code":"IN",
    "gn:dem":567,
    "gn:feature_class":"P",
    "gn:feature_code":"PPL",
    "gn:name":"Barar",
    "gn:population":0,
    "gn:timezone":"Asia/Kolkata",
    "iso:country":"IN",
    "name:ara_x_preferred":[
        "\u0628\u0631\u0627\u0631"
    ],
    "name:fas_x_preferred":[
        "\u0628\u0631\u0627\u0631"
    ],
    "wof:name":"Barar",
    "wof:placetype":"neighbourhood"
},
  "geometry": {"coordinates":[75.9115,31.83864],"type":"Point"}
}