{
  "type": "Feature",
  "properties": {
    "iso:country":"IN",
    "ks:ks_name":"Bhadkura",
    "ks:ks_pop":4,
    "ks:ks_type":"VILLAGE",
    "name:eng_x_preferred":[
        "Bhadkura"
    ],
    "wof:name":"Bhadkura",
    "wof:placetype":"locality",
    "wof:population":4
},
  "geometry": {"coordinates":[79.884322,23.502374],"type":"Point"}
}