{
  "type": "Feature",
  "properties": {
    "gn:admin1_code":"37",
    "gn:admin2_code":"411.0",
    "gn:asciiname":"Daijbandha",
    "gn:country_code":"IN",
    "gn:dem":319,
    "gn:feature_class":"P",
    "gn:feature_code":"PPL",
    "gn:name":"Daijb\u0101ndha",
    "gn:population":0,
    "gn:timezone":"Asia/Kolkata",
    "iso:country":"IN",
    "wof:name":"Daijbandha",
    "wof:placetype":"locality"
},
  "geometry": {"coordinates":[82.54085000000001,20.9506],"type":"Point"}
}