{
  "type": "Feature",
  "properties": {
    "iso:country":"IN",
    "ks:ks_name":"Kherani Umbari",
    "ks:ks_pop":640,
    "ks:ks_type":"VILLAGE",
    "name:eng_x_preferred":[
        "Kherani Umbari"
    ],
    "wof:name":"Kherani Umbari",
    "wof:placetype":"locality",
    "wof:population":640
},
  "geometry": {"coordinates":[72.92775899999999,24.237781],"type":"Point"}
}