{
  "type": "Feature",
  "properties": {
    "gn:admin1_code":"2.0",
    "gn:admin2_code":"544.0",
    "gn:asciiname":"Kottauru",
    "gn:country_code":"IN",
    "gn:dem":1064,
    "gn:feature_class":"P",
    "gn:feature_code":"PPL",
    "gn:name":"Kotta\u016bru",
    "gn:population":0,
    "gn:timezone":"Asia/Kolkata",
    "iso:country":"IN",
    "ks:ks_name":"Kothuru",
    "ks:ks_pop":57,
    "ks:ks_type":"VILLAGE",
    "name:eng_x_preferred":[
        "Kothuru"
    ],
    "name:eng_x_variant":[
        "Kottauru"
    ],
    "wof:name":"Kothuru",
    "wof:placetype":"locality",
    "wof:population":57
},
  "geometry": {"coordinates":[82.63043,18.100282],"type":"Point"}
}