{
  "type": "Feature",
  "properties": {
    "gn:admin1_code":"25.0",
    "gn:admin2_code":"610.0",
    "gn:asciiname":"Brahmana Periya Agraharam",
    "gn:country_code":"IN",
    "gn:dem":169,
    "gn:feature_class":"P",
    "gn:feature_code":"PPL",
    "gn:name":"Br\u0101hmana Periya Agrah\u0101ram",
    "gn:population":0,
    "gn:timezone":"Asia/Kolkata",
    "iso:country":"IN",
    "ks:ks_alt_nam":"Br\u0101hmana Periya Agrah\u0101ram",
    "ks:ks_name":"Brahmana Periya Agraharam",
    "ks:ks_type":"VILLAGE",
    "ks:ks_uagg_main":0,
    "wof:name":"Brahmana Periya Agraharam",
    "wof:placetype":"neighbourhood"
},
  "geometry": {"coordinates":[77.70632999999999,11.36904],"type":"Point"}
}