{
  "type": "Feature",
  "properties": {
    "gn:admin1_code":"36",
    "gn:admin2_code":"199.0",
    "gn:asciiname":"Sirsi",
    "gn:country_code":"IN",
    "gn:dem":217,
    "gn:feature_class":"P",
    "gn:feature_code":"PPL",
    "gn:name":"Sirsi",
    "gn:population":0,
    "gn:timezone":"Asia/Kolkata",
    "iso:country":"IN",
    "name:und_x_variant":[
        "Sirsee",
        "Sirsi"
    ],
    "wof:name":"Sirsi",
    "wof:placetype":"locality"
},
  "geometry": {"coordinates":[82.49184,24.84481],"type":"Point"}
}