{
  "type": "Feature",
  "properties": {
    "iso:country":"IN",
    "ks:ks_name":"Missamari No.1",
    "ks:ks_pop":1297,
    "ks:ks_type":"VILLAGE",
    "name:eng_x_preferred":[
        "Missamari No.1"
    ],
    "wof:name":"Missamari No.1",
    "wof:placetype":"locality",
    "wof:population":1297
},
  "geometry": {"coordinates":[92.577961,26.147178],"type":"Point"}
}