{
  "type": "Feature",
  "properties": {
    "gn:admin1_code":"11",
    "gn:admin2_code":"23.0",
    "gn:asciiname":"Silpiri",
    "gn:country_code":"IN",
    "gn:dem":2088,
    "gn:feature_class":"P",
    "gn:feature_code":"PPL",
    "gn:name":"Silpiri",
    "gn:population":0,
    "gn:timezone":"Asia/Kolkata",
    "iso:country":"IN",
    "wof:name":"Silpiri",
    "wof:placetype":"locality"
},
  "geometry": {"coordinates":[76.45711,32.52925],"type":"Point"}
}