{
  "type": "Feature",
  "properties": {
    "iso:country":"IN",
    "ks:ks_name":"Devara Gollahalli",
    "ks:ks_pop":45,
    "ks:ks_type":"VILLAGE",
    "name:eng_x_preferred":[
        "Devara Gollahalli"
    ],
    "wof:name":"Devara Gollahalli",
    "wof:placetype":"locality",
    "wof:population":45
},
  "geometry": {"coordinates":[77.88459,13.011541],"type":"Point"}
}