{
  "type": "Feature",
  "properties": {
    "iso:country":"IN",
    "ks:ks_name":"Zalaki",
    "ks:ks_pop":2376,
    "ks:ks_type":"HABITATION",
    "name:eng_x_preferred":[
        "Zalaki"
    ],
    "wof:name":"Zalaki",
    "wof:placetype":"locality",
    "wof:population":2376
},
  "geometry": {"coordinates":[75.76931500000001,17.243084],"type":"Point"}
}