{
  "type": "Feature",
  "properties": {
    "iso:country":"IN",
    "ks:ks_name":"Jalipente",
    "ks:ks_type":"VILLAGE",
    "name:eng_x_preferred":[
        "Jalipente"
    ],
    "wof:name":"Jalipente",
    "wof:placetype":"locality"
},
  "geometry": {"coordinates":[76.676258,14.925495],"type":"Point"}
}