{
  "type": "Feature",
  "properties": {
    "iso:country":"IN",
    "ks:ks_name":"Garasiapura",
    "ks:ks_pop":200,
    "ks:ks_type":"HABITATION",
    "name:eng_x_preferred":[
        "Garasiapura"
    ],
    "wof:name":"Garasiapura",
    "wof:placetype":"locality",
    "wof:population":200
},
  "geometry": {"coordinates":[72.67068500000001,24.458624],"type":"Point"}
}