{
  "type": "Feature",
  "properties": {
    "iso:country":"IN",
    "ks:ks_name":"Pampanagar",
    "ks:ks_pop":1353,
    "ks:ks_type":"VILLAGE",
    "name:eng_x_preferred":[
        "Pampanagar"
    ],
    "wof:name":"Pampanagar",
    "wof:placetype":"locality",
    "wof:population":1353
},
  "geometry": {"coordinates":[82.733678,23.117954],"type":"Point"}
}