{
  "type": "Feature",
  "properties": {
    "iso:country":"IN",
    "ks:ks_name":"Asia",
    "ks:ks_pop":625,
    "ks:ks_type":"VILLAGE",
    "name:eng_x_preferred":[
        "Asia"
    ],
    "wof:name":"Asia",
    "wof:placetype":"locality",
    "wof:population":625
},
  "geometry": {"coordinates":[86.232173,21.198674],"type":"Point"}
}