{
  "type": "Feature",
  "properties": {
    "iso:country":"IN",
    "ks:ks_name":"Melekkaru",
    "ks:ks_pop":1092,
    "ks:ks_type":"HABITATION",
    "name:eng_x_preferred":[
        "Melekkaru"
    ],
    "wof:name":"Melekkaru",
    "wof:placetype":"locality",
    "wof:population":1092
},
  "geometry": {"coordinates":[74.89000799999999,13.019571],"type":"Point"}
}