{
  "type": "Feature",
  "properties": {
    "iso:country":"IN",
    "ks:ks_name":"Barai",
    "ks:ks_pop":1517,
    "ks:ks_type":"VILLAGE",
    "name:eng_x_preferred":[
        "Barai"
    ],
    "wof:name":"Barai",
    "wof:placetype":"locality",
    "wof:population":1517
},
  "geometry": {"coordinates":[73.02276500000001,20.427399],"type":"Point"}
}