{
  "type": "Feature",
  "properties": {
    "iso:country":"IN",
    "ks:ks_name":"Baladka",
    "ks:ks_pop":36,
    "ks:ks_type":"HABITATION",
    "name:eng_x_preferred":[
        "Baladka"
    ],
    "wof:name":"Baladka",
    "wof:placetype":"locality",
    "wof:population":36
},
  "geometry": {"coordinates":[75.101428,13.214097],"type":"Point"}
}