{
  "type": "Feature",
  "properties": {
    "iso:country":"IN",
    "ks:ks_name":"Dhawa Tanr",
    "ks:ks_pop":212,
    "ks:ks_type":"HABITATION",
    "name:eng_x_preferred":[
        "Dhawa Tanr"
    ],
    "wof:name":"Dhawa Tanr",
    "wof:placetype":"locality",
    "wof:population":212
},
  "geometry": {"coordinates":[86.571625,24.836868],"type":"Point"}
}