{
  "type": "Feature",
  "properties": {
    "iso:country":"IN",
    "ks:ks_alt_nam":"MALIBHAG",
    "ks:ks_name":"Malibhag",
    "ks:ks_pop":160,
    "ks:ks_type":"HABITATION",
    "ks:ks_uagg_main":0,
    "name:eng_x_preferred":[
        "Malibhag"
    ],
    "wof:name":"Malibhag",
    "wof:placetype":"neighbourhood",
    "wof:population":160
},
  "geometry": {"coordinates":[74.425259,17.038752],"type":"Point"}
}