{
  "type": "Feature",
  "properties": {
    "gn:admin1_code":"16.0",
    "gn:admin2_code":"497.0",
    "gn:asciiname":"Ranipur",
    "gn:country_code":"IN",
    "gn:dem":217,
    "gn:feature_class":"P",
    "gn:feature_code":"PPL",
    "gn:name":"R\u0101nipur",
    "gn:population":0,
    "gn:timezone":"Asia/Kolkata",
    "iso:country":"IN",
    "name:pol_x_preferred":[
        "Ranipur"
    ],
    "name:snd_x_preferred":[
        "\u0631\u0627\u06bb\u064a \u067e\u0648\u0631"
    ],
    "name:urd_x_preferred":[
        "\u0631\u0627\u0646\u06cc \u067e\u0648\u0631"
    ],
    "wof:name":"Ranipur",
    "wof:placetype":"locality"
},
  "geometry": {"coordinates":[74.26528,21.65086],"type":"Point"}
}