{
  "type": "Feature",
  "properties": {
    "gn:admin1_code":"35.0",
    "gn:admin2_code":"447.0",
    "gn:asciiname":"Maholi",
    "gn:country_code":"IN",
    "gn:dem":736,
    "gn:feature_class":"P",
    "gn:feature_code":"PPL",
    "gn:name":"Maholi",
    "gn:population":0,
    "gn:timezone":"Asia/Kolkata",
    "iso:country":"IN",
    "name:bpy_x_preferred":[
        "\u09ae\u09be\u09b9\u09cb\u09b2\u09bf"
    ],
    "name:ceb_x_preferred":[
        "Maholi"
    ],
    "name:hin_x_preferred":[
        "\u092e\u0939\u094b\u0932\u0940"
    ],
    "name:ita_x_preferred":[
        "Maholi"
    ],
    "name:mlg_x_preferred":[
        "Maholi"
    ],
    "name:msa_x_preferred":[
        "Maholi"
    ],
    "name:new_x_preferred":[
        "\u092e\u093e\u0939\u094b\u0932\u0940"
    ],
    "name:nld_x_preferred":[
        "Maholi"
    ],
    "name:pol_x_preferred":[
        "Maholi"
    ],
    "name:por_x_preferred":[
        "Maholi"
    ],
    "name:swe_x_preferred":[
        "Maholi"
    ],
    "name:urd_x_preferred":[
        "\u0645\u0627\u06c1\u0648\u0644\u06cc"
    ],
    "name:vie_x_preferred":[
        "Maholi"
    ],
    "name:zho_x_preferred":[
        "\u9a6c\u970d\u5229"
    ],
    "wof:name":"Maholi",
    "wof:placetype":"locality"
},
  "geometry": {"coordinates":[78.223,21.97667],"type":"Point"}
}