{
  "type": "Feature",
  "properties": {
    "iso:country":"IN",
    "ks:ks_name":"Rongchomang Sevar",
    "ks:ks_pop":47,
    "ks:ks_type":"HABITATION",
    "name:eng_x_preferred":[
        "Rongchomang Sevar"
    ],
    "wof:name":"Rongchomang Sevar",
    "wof:placetype":"locality",
    "wof:population":47
},
  "geometry": {"coordinates":[92.483531,25.957223],"type":"Point"}
}