{
  "type": "Feature",
  "properties": {
    "iso:country":"IN",
    "ks:ks_name":"Satnapur",
    "ks:ks_pop":112,
    "ks:ks_type":"HABITATION",
    "name:eng_x_preferred":[
        "Satnapur"
    ],
    "wof:name":"Satnapur",
    "wof:placetype":"locality",
    "wof:population":112
},
  "geometry": {"coordinates":[81.81531200000001,25.906325],"type":"Point"}
}