{
  "type": "Feature",
  "properties": {
    "iso:country":"IN",
    "ks:ks_name":"Nerlamakki",
    "ks:ks_pop":171,
    "ks:ks_type":"HABITATION",
    "name:eng_x_preferred":[
        "Nerlamakki"
    ],
    "wof:name":"Nerlamakki",
    "wof:placetype":"locality",
    "wof:population":171
},
  "geometry": {"coordinates":[75.75662,13.08471],"type":"Point"}
}