{
  "type": "Feature",
  "properties": {
    "gn:admin1_code":"10.0",
    "gn:admin2_code":"071",
    "gn:asciiname":"Khurdban",
    "gn:country_code":"IN",
    "gn:dem":260,
    "gn:feature_class":"P",
    "gn:feature_code":"PPL",
    "gn:name":"Khurdban",
    "gn:population":0,
    "gn:timezone":"Asia/Kolkata",
    "iso:country":"IN",
    "wof:name":"Khurdban",
    "wof:placetype":"locality"
},
  "geometry": {"coordinates":[77.14138,29.984],"type":"Point"}
}