{
  "type": "Feature",
  "properties": {
    "iso:country":"IN",
    "ks:ks_name":"Kuppaguttapalle",
    "ks:ks_pop":155,
    "ks:ks_type":"HABITATION",
    "name:eng_x_preferred":[
        "Kuppaguttapalle"
    ],
    "wof:name":"Kuppaguttapalle",
    "wof:placetype":"locality",
    "wof:population":155
},
  "geometry": {"coordinates":[78.88036200000001,13.937578],"type":"Point"}
}