{
  "type": "Feature",
  "properties": {
    "iso:country":"IN",
    "ks:ks_name":"Chiguruwada South",
    "ks:ks_pop":360,
    "ks:ks_type":"VILLAGE",
    "ks:ks_uagg_main":0,
    "name:eng_x_preferred":[
        "Chiguruwada South"
    ],
    "wof:name":"Chiguruwada South",
    "wof:placetype":"locality",
    "wof:population":360
},
  "geometry": {"coordinates":[79.399525,13.586679],"type":"Point"}
}