{
  "type": "Feature",
  "properties": {
    "iso:country":"IN",
    "ks:ks_name":"Jhari",
    "ks:ks_pop":162,
    "ks:ks_type":"HABITATION",
    "name:eng_x_preferred":[
        "Jhari"
    ],
    "wof:name":"Jhari",
    "wof:placetype":"locality",
    "wof:population":162
},
  "geometry": {"coordinates":[71.111403,26.029647],"type":"Point"}
}