{
  "type": "Feature",
  "properties": {
    "iso:country":"IN",
    "ks:ks_name":"Vairampatti",
    "ks:ks_pop":245,
    "ks:ks_type":"HABITATION",
    "name:eng_x_preferred":[
        "Vairampatti"
    ],
    "wof:name":"Vairampatti",
    "wof:placetype":"locality",
    "wof:population":245
},
  "geometry": {"coordinates":[78.656063,10.285957],"type":"Point"}
}