{
  "type": "Feature",
  "properties": {
    "gn:admin1_code":"36",
    "gn:admin2_code":"199.0",
    "gn:asciiname":"Simra Partabsingh",
    "gn:country_code":"IN",
    "gn:dem":132,
    "gn:feature_class":"P",
    "gn:feature_code":"PPL",
    "gn:name":"Simra Part\u0101bsingh",
    "gn:population":0,
    "gn:timezone":"Asia/Kolkata",
    "iso:country":"IN",
    "wof:name":"Simra Partabsingh",
    "wof:placetype":"neighbourhood"
},
  "geometry": {"coordinates":[82.39373999999999,25.03967],"type":"Point"}
}