{
  "type": "Feature",
  "properties": {
    "iso:country":"IN",
    "ks:ks_name":"Karadka",
    "ks:ks_pop":1598,
    "ks:ks_type":"HABITATION",
    "name:eng_x_preferred":[
        "Karadka"
    ],
    "wof:name":"Karadka",
    "wof:placetype":"locality",
    "wof:population":1598
},
  "geometry": {"coordinates":[75.128649,12.531548],"type":"Point"}
}