{
  "type": "Feature",
  "properties": {
    "iso:country":"IN",
    "ks:ks_name":"Telipara",
    "ks:ks_pop":220,
    "ks:ks_type":"HABITATION",
    "name:eng_x_preferred":[
        "Telipara"
    ],
    "wof:name":"Telipara",
    "wof:placetype":"locality",
    "wof:population":220
},
  "geometry": {"coordinates":[80.809358,18.888019],"type":"Point"}
}