{
  "type": "Feature",
  "properties": {
    "iso:country":"IN",
    "ks:ks_alt_nam":"Harishchand  safi purwa",
    "ks:ks_name":"Harishchand Safi Purwa",
    "ks:ks_pop":80,
    "ks:ks_type":"HABITATION",
    "ks:ks_uagg_main":0,
    "name:eng_x_preferred":[
        "Harishchand Safi Purwa"
    ],
    "name:eng_x_variant":[
        "Harishchand  safi purwa"
    ],
    "wof:name":"Harishchand Safi Purwa",
    "wof:placetype":"neighbourhood",
    "wof:population":80
},
  "geometry": {"coordinates":[81.79246500000001,27.303035],"type":"Point"}
}