{
  "type": "Feature",
  "properties": {
    "gn:country":"IN",
    "gn:fcode":"PPL",
    "gn:population":25074,
    "iso:country":"IN",
    "name:ast_x_preferred":[
        "Rampachodavaram"
    ],
    "name:ben_x_preferred":[
        "\u09b0\u09be\u09ae\u09cd\u09aa\u09be\u099a\u09cb\u09a6\u09be\u09ad\u09b0\u09ae"
    ],
    "name:bpy_x_preferred":[
        "\u09b0\u09ae\u09cd\u09aa\u099a\u09cb\u09a6\u09f1\u09b0\u09ae"
    ],
    "name:bul_x_preferred":[
        "\u0420\u0430\u043c\u043f\u0430\u0447\u043e\u0434\u0430\u0432\u0430\u0440\u0430\u043c"
    ],
    "name:ceb_x_preferred":[
        "Rampachodavaram"
    ],
    "name:deu_x_preferred":[
        "Rampachodavaram"
    ],
    "name:eng_x_preferred":[
        "Rampachodavaram"
    ],
    "name:fra_x_preferred":[
        "Rampachodavaram"
    ],
    "name:guj_x_preferred":[
        "\u0ab0\u0abe\u0aae\u0acd\u0aaa\u0abe\u0a9a\u0acb\u0aa1\u0abe\u0ab5\u0ab0\u0aae"
    ],
    "name:hin_x_preferred":[
        "\u0930\u092e\u094d\u092a\u091a\u094b\u0921\u093c\u0935\u0930\u092e"
    ],
    "name:ita_x_preferred":[
        "Rampachodavaram"
    ],
    "name:jpn_x_preferred":[
        "\u30e9\u30e0\u30d1\u30c1\u30e7\u30c0\u30f4\u30a1\u30e9\u30e0"
    ],
    "name:kan_x_preferred":[
        "\u0cb0\u0cbe\u0c82\u0caa\u0c9a\u0ccb\u0ca6\u0cbe\u0cb5\u0cb0\u0cae\u0ccd"
    ],
    "name:kor_x_preferred":[
        "\ub78c\ud30c\ucd08\ub2e4\ubc14\ub78c"
    ],
    "name:lld_x_preferred":[
        "Rampachodavaram"
    ],
    "name:msa_x_preferred":[
        "Rampachodavaram"
    ],
    "name:nan_x_preferred":[
        "Rampachodavaram"
    ],
    "name:new_x_preferred":[
        "\u0930\u0902\u092a\u091a\u094b\u0921\u0935\u0930\u0902 \u092e\u0923\u094d\u0921\u0932"
    ],
    "name:nld_x_preferred":[
        "Rampachodavaram"
    ],
    "name:por_x_preferred":[
        "Rampachodavaram"
    ],
    "name:rus_x_preferred":[
        "\u0420\u0430\u043c\u043f\u0430\u0447\u043e\u0434\u0430\u0432\u0430\u0440\u0430\u043c"
    ],
    "name:spa_x_preferred":[
        "Rampachodavaram"
    ],
    "name:swe_x_preferred":[
        "Rampachodavaram"
    ],
    "name:tam_x_preferred":[
        "\u0bb0\u0bae\u0bcd\u0baa\u0b9a\u0bcd\u0b9a\u0bcb\u0ba4\u0bb5\u0bb0\u0bae\u0bcd"
    ],
    "name:tel_x_preferred":[
        "\u0c30\u0c02\u0c2a\u0c1a\u0c4b\u0c21\u0c35\u0c30\u0c02"
    ],
    "name:tel_x_variant":[
        "\u0c30\u0c02\u0c2a\u0c1a\u0c4b\u0c21\u0c35\u0c30\u0c02 \u0c2e\u0c02\u0c21\u0c32\u0c02"
    ],
    "name:tgl_x_preferred":[
        "Rampachodavaram"
    ],
    "name:urd_x_preferred":[
        "\u0631\u0645\u067e\u0627\u0686\u0648\u0691\u0627\u0648\u0631\u0645"
    ],
    "name:vie_x_preferred":[
        "Rampachodavaram"
    ],
    "name:zho_x_preferred":[
        "\u62c9\u59c6\u5e15\u4e54\u8fbe\u74e6\u62c9\u59c6"
    ],
    "qs:name":"Boddavaram",
    "qs:name_adm0":"India",
    "qs:name_adm1":"Andhra Pradesh",
    "qs:photos_9r":0,
    "qs:photos_sr":0,
    "qs:placetype":"Town",
    "qs:pop_sr":"7",
    "wof:name":"Boddavaram",
    "wof:placetype":"locality",
    "wof:population":25074
},
  "geometry": {"coordinates":[81.77558000000001,17.44088],"type":"Point"}
}