{
  "type": "Feature",
  "properties": {
    "gn:admin1_code":"35",
    "gn:admin2_code":"456.0",
    "gn:asciiname":"Satikachhar",
    "gn:country_code":"IN",
    "gn:dem":536,
    "gn:feature_class":"P",
    "gn:feature_code":"PPL",
    "gn:name":"Satikachh\u0101r",
    "gn:population":0,
    "gn:timezone":"Asia/Kolkata",
    "iso:country":"IN",
    "wof:name":"Satikachhar",
    "wof:placetype":"locality"
},
  "geometry": {"coordinates":[79.46526999999998,22.66256],"type":"Point"}
}