{
  "type": "Feature",
  "properties": {
    "gn:admin1_code":"12.0",
    "gn:admin2_code":"8.0",
    "gn:asciiname":"Zinipur",
    "gn:country_code":"IN",
    "gn:dem":1583,
    "gn:feature_class":"P",
    "gn:feature_code":"PPL",
    "gn:name":"Zin\u012bpur",
    "gn:population":0,
    "gn:timezone":"Asia/Kolkata",
    "iso:country":"IN",
    "name:eng_x_preferred":[
        "Zin\u012bpur"
    ],
    "wof:name":"Zinipur",
    "wof:placetype":"locality"
},
  "geometry": {"coordinates":[74.63684000000001,34.26428],"type":"Point"}
}