{
  "type": "Feature",
  "properties": {
    "iso:country":"IN",
    "ks:ks_name":"Dhula Bari",
    "ks:ks_pop":520,
    "ks:ks_type":"HABITATION",
    "name:eng_x_preferred":[
        "Dhula Bari"
    ],
    "wof:name":"Dhula Bari",
    "wof:placetype":"locality",
    "wof:population":520
},
  "geometry": {"coordinates":[88.04504,26.232847],"type":"Point"}
}