{
  "type": "Feature",
  "properties": {
    "gn:admin1_code":"36.0",
    "gn:admin2_code":"165",
    "gn:asciiname":"Jajipura",
    "gn:country_code":"IN",
    "gn:dem":148,
    "gn:feature_class":"P",
    "gn:feature_code":"PPL",
    "gn:name":"J\u0101jipura",
    "gn:population":0,
    "gn:timezone":"Asia/Kolkata",
    "iso:country":"IN",
    "name:und_x_variant":[
        "J\u0101jipura",
        "J\u0101j\u012bpura"
    ],
    "wof:name":"Jajipura",
    "wof:placetype":"locality"
},
  "geometry": {"coordinates":[79.23218,26.31681],"type":"Point"}
}