{
  "type": "Feature",
  "properties": {
    "iso:country":"IN",
    "ks:ks_name":"Harijanwasti",
    "ks:ks_pop":69,
    "ks:ks_type":"HABITATION",
    "ks:ks_uagg_main":0,
    "name:eng_x_preferred":[
        "Harijanwasti"
    ],
    "wof:name":"Harijanwasti",
    "wof:placetype":"neighbourhood",
    "wof:population":69
},
  "geometry": {"coordinates":[73.90152500000001,17.312545],"type":"Point"}
}