{
  "type": "Feature",
  "properties": {
    "iso:country":"IN",
    "ks:ks_name":"Sonauli",
    "ks:ks_pop":285,
    "ks:ks_type":"HABITATION",
    "name:eng_x_preferred":[
        "Sonauli"
    ],
    "wof:name":"Sonauli",
    "wof:placetype":"locality",
    "wof:population":285
},
  "geometry": {"coordinates":[83.30099199999999,27.216417],"type":"Point"}
}