{
  "type": "Feature",
  "properties": {
    "gn:admin1_code":"2",
    "gn:admin2_code":"545.0",
    "gn:asciiname":"Ramavaram",
    "gn:country_code":"IN",
    "gn:dem":283,
    "gn:feature_class":"P",
    "gn:feature_code":"PPL",
    "gn:name":"R\u0101mavaram",
    "gn:population":0,
    "gn:timezone":"Asia/Kolkata",
    "iso:country":"IN",
    "wof:name":"Ramavaram",
    "wof:placetype":"locality"
},
  "geometry": {"coordinates":[82.05566999999998,17.56812],"type":"Point"}
}