{
  "type": "Feature",
  "properties": {
    "iso:country":"IN",
    "ks:ks_name":"Jaitapkarwadi",
    "ks:ks_pop":22,
    "ks:ks_type":"HABITATION",
    "name:eng_x_preferred":[
        "Jaitapkarwadi"
    ],
    "wof:name":"Jaitapkarwadi",
    "wof:placetype":"locality",
    "wof:population":22
},
  "geometry": {"coordinates":[73.36397599999999,16.627677],"type":"Point"}
}