{
  "type": "Feature",
  "properties": {
    "iso:country":"IN",
    "ks:ks_name":"Chhoteemarnee",
    "ks:ks_pop":340,
    "ks:ks_type":"HABITATION",
    "name:eng_x_preferred":[
        "Chhoteemarnee"
    ],
    "wof:name":"Chhoteemarnee",
    "wof:placetype":"locality",
    "wof:population":340
},
  "geometry": {"coordinates":[81.77068199999999,25.718548],"type":"Point"}
}