{
  "type": "Feature",
  "properties": {
    "gn:admin1_code":"37",
    "gn:admin2_code":"408.0",
    "gn:asciiname":"Thailitola",
    "gn:country_code":"IN",
    "gn:dem":332,
    "gn:feature_class":"P",
    "gn:feature_code":"PPL",
    "gn:name":"Thail\u012btola",
    "gn:population":0,
    "gn:timezone":"Asia/Kolkata",
    "iso:country":"IN",
    "ks:ks_alt_nam":"Thail\u012btola",
    "ks:ks_name":"Thailitola",
    "ks:ks_pop":415,
    "ks:ks_type":"VILLAGE",
    "name:eng_x_preferred":[
        "Thailitola"
    ],
    "name:eng_x_variant":[
        "Thail\u012btola"
    ],
    "wof:name":"Thailitola",
    "wof:placetype":"locality",
    "wof:population":415
},
  "geometry": {"coordinates":[80.70586299999999,20.90954],"type":"Point"}
}