{
  "type": "Feature",
  "properties": {
    "gn:admin1_code":"19.0",
    "gn:admin2_code":"582.0",
    "gn:asciiname":"Rayappanahalli",
    "gn:country_code":"IN",
    "gn:dem":803,
    "gn:feature_class":"P",
    "gn:feature_code":"PPL",
    "gn:name":"Rayappanahalli",
    "gn:population":0,
    "gn:timezone":"Asia/Kolkata",
    "iso:country":"IN",
    "wof:name":"Rayappanahalli",
    "wof:placetype":"locality"
},
  "geometry": {"coordinates":[77.91804999999999,13.54846],"type":"Point"}
}