{
  "type": "Feature",
  "properties": {
    "iso:country":"IN",
    "ks:ks_name":"Javale Honda",
    "ks:ks_pop":22,
    "ks:ks_type":"HABITATION",
    "name:eng_x_preferred":[
        "Javale Honda"
    ],
    "wof:name":"Javale Honda",
    "wof:placetype":"locality",
    "wof:population":22
},
  "geometry": {"coordinates":[74.953366,14.807651],"type":"Point"}
}