{
  "type": "Feature",
  "properties": {
    "gn:admin1_code":"19.0",
    "gn:admin2_code":"555",
    "gn:asciiname":"Avarkhod",
    "gn:country_code":"IN",
    "gn:dem":538,
    "gn:feature_class":"P",
    "gn:feature_code":"PPL",
    "gn:name":"Avarkhod",
    "gn:population":0,
    "gn:timezone":"Asia/Kolkata",
    "iso:country":"IN",
    "wof:name":"Avarkhod",
    "wof:placetype":"locality"
},
  "geometry": {"coordinates":[75.03192,16.62829],"type":"Point"}
}