{
  "type": "Feature",
  "properties": {
    "iso:country":"IN",
    "ks:ks_name":"Kottamedu",
    "ks:ks_pop":584,
    "ks:ks_type":"HABITATION",
    "name:eng_x_preferred":[
        "Kottamedu"
    ],
    "wof:name":"Kottamedu",
    "wof:placetype":"locality",
    "wof:population":584
},
  "geometry": {"coordinates":[79.19945199999999,11.89289],"type":"Point"}
}