{
  "type": "Feature",
  "properties": {
    "iso:country":"IN",
    "ks:ks_name":"Barabangachar Pt. I",
    "ks:ks_pop":328,
    "ks:ks_type":"VILLAGE",
    "name:eng_x_preferred":[
        "Barabangachar Pt. I"
    ],
    "wof:name":"Barabangachar Pt. I",
    "wof:placetype":"locality",
    "wof:population":328
},
  "geometry": {"coordinates":[89.897766,25.842296],"type":"Point"}
}