{
  "type": "Feature",
  "properties": {
    "iso:country":"IN",
    "ks:ks_name":"Balua Ghat",
    "ks:ks_pop":991,
    "ks:ks_type":"HABITATION",
    "ks:ks_uagg_main":0,
    "name:eng_x_preferred":[
        "Balua Ghat"
    ],
    "wof:name":"Balua Ghat",
    "wof:placetype":"neighbourhood",
    "wof:population":991
},
  "geometry": {"coordinates":[84.960155,26.559728],"type":"Point"}
}