{
  "type": "Feature",
  "properties": {
    "iso:country":"IN",
    "ks:ks_name":"Devagaru",
    "ks:ks_pop":300,
    "ks:ks_type":"HABITATION",
    "name:eng_x_preferred":[
        "Devagaru"
    ],
    "wof:name":"Devagaru",
    "wof:placetype":"locality",
    "wof:population":300
},
  "geometry": {"coordinates":[74.68681599999999,14.107429],"type":"Point"}
}