{
  "type": "Feature",
  "properties": {
    "iso:country":"IN",
    "ks:ks_alt_nam":"PURE BACHA MISHRA",
    "ks:ks_name":"Pure Bacha Mishra",
    "ks:ks_pop":196,
    "ks:ks_type":"HABITATION",
    "ks:ks_uagg_main":0,
    "name:eng_x_preferred":[
        "Pure Bacha Mishra"
    ],
    "wof:name":"Pure Bacha Mishra",
    "wof:placetype":"neighbourhood",
    "wof:population":196
},
  "geometry": {"coordinates":[81.94786000000001,26.322335],"type":"Point"}
}