{
  "type": "Feature",
  "properties": {
    "iso:country":"IN",
    "ks:ks_alt_nam":"PINDARKON",
    "ks:ks_name":"Pindarkon",
    "ks:ks_pop":2009,
    "ks:ks_type":"HABITATION",
    "name:eng_x_preferred":[
        "Pindarkon"
    ],
    "wof:name":"Pindarkon",
    "wof:placetype":"locality",
    "wof:population":2009
},
  "geometry": {"coordinates":[85.325399,24.235263],"type":"Point"}
}