{
  "type": "Feature",
  "properties": {
    "gn:admin1_code":"2.0",
    "gn:admin2_code":"543.0",
    "gn:asciiname":"Adarupadu",
    "gn:country_code":"IN",
    "gn:dem":293,
    "gn:feature_class":"P",
    "gn:feature_code":"PPL",
    "gn:name":"Ad\u0101rup\u0101du",
    "gn:population":0,
    "gn:timezone":"Asia/Kolkata",
    "iso:country":"IN",
    "ks:ks_name":"Adaripadu",
    "ks:ks_pop":65,
    "ks:ks_type":"VILLAGE",
    "name:eng_x_preferred":[
        "Adaripadu"
    ],
    "name:eng_x_variant":[
        "Adarupadu"
    ],
    "wof:name":"Adaripadu",
    "wof:placetype":"locality",
    "wof:population":65
},
  "geometry": {"coordinates":[83.051669,18.435663],"type":"Point"}
}