{
  "type": "Feature",
  "properties": {
    "iso:country":"IN",
    "ks:ks_name":"Dargarbond Pt I",
    "ks:ks_pop":954,
    "ks:ks_type":"HABITATION",
    "name:eng_x_preferred":[
        "Dargarbond Pt I"
    ],
    "wof:name":"Dargarbond Pt I",
    "wof:placetype":"locality",
    "wof:population":954
},
  "geometry": {"coordinates":[92.479857,24.662727],"type":"Point"}
}