{
  "type": "Feature",
  "properties": {
    "iso:country":"IN",
    "ks:ks_name":"Gambhiraghat Pt.I",
    "ks:ks_pop":205,
    "ks:ks_type":"VILLAGE",
    "name:eng_x_preferred":[
        "Gambhiraghat Pt.I"
    ],
    "wof:name":"Gambhiraghat Pt.I",
    "wof:placetype":"locality",
    "wof:population":205
},
  "geometry": {"coordinates":[89.99158,26.223825],"type":"Point"}
}