{
  "type": "Feature",
  "properties": {
    "iso:country":"IN",
    "ks:ks_name":"Mahto Tola",
    "ks:ks_pop":102,
    "ks:ks_type":"HABITATION",
    "name:eng_x_preferred":[
        "Mahto Tola"
    ],
    "wof:name":"Mahto Tola",
    "wof:placetype":"locality",
    "wof:population":102
},
  "geometry": {"coordinates":[83.429469,24.141808],"type":"Point"}
}