{
  "type": "Feature",
  "properties": {
    "gn:admin1_code":"37",
    "gn:admin2_code":"404.0",
    "gn:asciiname":"Chandroti",
    "gn:country_code":"IN",
    "gn:dem":553,
    "gn:feature_class":"P",
    "gn:feature_code":"PPL",
    "gn:name":"Chandroti",
    "gn:population":0,
    "gn:timezone":"Asia/Kolkata",
    "iso:country":"IN",
    "ks:ks_name":"Chandroti",
    "ks:ks_pop":1221,
    "ks:ks_type":"VILLAGE",
    "name:eng_x_preferred":[
        "Chandroti"
    ],
    "wof:name":"Chandroti",
    "wof:placetype":"locality",
    "wof:population":1221
},
  "geometry": {"coordinates":[82.17415800000001,22.799003],"type":"Point"}
}