{
  "type": "Feature",
  "properties": {
    "gn:admin1_code":"2.0",
    "gn:admin2_code":"553.0",
    "gn:asciiname":"Subbarayanipalle",
    "gn:country_code":"IN",
    "gn:dem":549,
    "gn:feature_class":"P",
    "gn:feature_code":"PPL",
    "gn:name":"Subbar\u0101yanipalle",
    "gn:population":0,
    "gn:timezone":"Asia/Kolkata",
    "iso:country":"IN",
    "ks:ks_name":"Subbarayuni Palli",
    "ks:ks_pop":274,
    "ks:ks_type":"HABITATION",
    "name:eng_x_preferred":[
        "Subbarayuni Palli"
    ],
    "name:eng_x_variant":[
        "Subbarayanipalle"
    ],
    "wof:name":"Subbarayuni Palli",
    "wof:placetype":"locality",
    "wof:population":274
},
  "geometry": {"coordinates":[78.074578,14.101788],"type":"Point"}
}