{
  "type": "Feature",
  "properties": {
    "iso:country":"IN",
    "ks:ks_name":"Kamalpur Rani",
    "ks:ks_pop":0,
    "ks:ks_type":"VILLAGE",
    "name:eng_x_preferred":[
        "Kamalpur Rani"
    ],
    "wof:name":"Kamalpur Rani",
    "wof:placetype":"locality",
    "wof:population":0
},
  "geometry": {"coordinates":[78.39966699999999,28.527657],"type":"Point"}
}