{
  "type": "Feature",
  "properties": {
    "iso:country":"IN",
    "ks:ks_name":"Manibhai Kampa",
    "ks:ks_pop":96,
    "ks:ks_type":"HABITATION",
    "name:eng_x_preferred":[
        "Manibhai Kampa"
    ],
    "wof:name":"Manibhai Kampa",
    "wof:placetype":"locality",
    "wof:population":96
},
  "geometry": {"coordinates":[73.354,23.592583],"type":"Point"}
}