{
  "type": "Feature",
  "properties": {
    "iso:country":"IN",
    "ks:ks_name":"Palandiguda",
    "ks:ks_pop":72,
    "ks:ks_type":"HABITATION",
    "name:eng_x_preferred":[
        "Palandiguda"
    ],
    "wof:name":"Palandiguda",
    "wof:placetype":"locality",
    "wof:population":72
},
  "geometry": {"coordinates":[78.62848200000001,19.537722],"type":"Point"}
}