{
  "type": "Feature",
  "properties": {
    "iso:country":"IN",
    "ks:ks_name":"Magurmari",
    "ks:ks_pop":638,
    "ks:ks_type":"VILLAGE",
    "name:eng_x_preferred":[
        "Magurmari"
    ],
    "wof:name":"Magurmari",
    "wof:placetype":"locality",
    "wof:population":638
},
  "geometry": {"coordinates":[92.48943,26.488599],"type":"Point"}
}