{
  "type": "Feature",
  "properties": {
    "iso:country":"IN",
    "ks:ks_name":"Chamrahia",
    "ks:ks_pop":32,
    "ks:ks_type":"HABITATION",
    "name:eng_x_preferred":[
        "Chamrahia"
    ],
    "wof:name":"Chamrahia",
    "wof:placetype":"locality",
    "wof:population":32
},
  "geometry": {"coordinates":[82.50966,26.812202],"type":"Point"}
}