{
  "type": "Feature",
  "properties": {
    "iso:country":"IN",
    "ks:ks_alt_nam":"NONA GATI",
    "ks:ks_name":"Nona Gati",
    "ks:ks_pop":1515,
    "ks:ks_type":"HABITATION",
    "name:eng_x_preferred":[
        "Nona Gati"
    ],
    "wof:name":"Nona Gati",
    "wof:placetype":"locality",
    "wof:population":1515
},
  "geometry": {"coordinates":[88.948517,26.893916],"type":"Point"}
}