{
  "type": "Feature",
  "properties": {
    "iso:country":"IN",
    "ks:ks_alt_nam":"PASWAN TOLI HT",
    "ks:ks_name":"Paswan Toli Ht",
    "ks:ks_pop":186,
    "ks:ks_type":"HABITATION",
    "name:eng_x_preferred":[
        "Paswan Toli Ht"
    ],
    "wof:name":"Paswan Toli Ht",
    "wof:placetype":"locality",
    "wof:population":186
},
  "geometry": {"coordinates":[87.90307300000001,26.098486],"type":"Point"}
}