{
  "type": "Feature",
  "properties": {
    "gn:admin1_code":"36",
    "gn:admin2_code":"173.0",
    "gn:asciiname":"Nakai Purwa",
    "gn:country_code":"IN",
    "gn:dem":97,
    "gn:feature_class":"P",
    "gn:feature_code":"PPL",
    "gn:name":"Nakai Purwa",
    "gn:population":0,
    "gn:timezone":"Asia/Kolkata",
    "iso:country":"IN",
    "wof:name":"Nakai Purwa",
    "wof:placetype":"neighbourhood"
},
  "geometry": {"coordinates":[82.01384,26.03645],"type":"Point"}
}