{
  "type": "Feature",
  "properties": {
    "iso:country":"IN",
    "ks:ks_name":"Udayabhanu Rd Jun",
    "ks:ks_pop":591,
    "ks:ks_type":"HABITATION",
    "name:eng_x_preferred":[
        "Udayabhanu Rd Jun"
    ],
    "wof:name":"Udayabhanu Rd Jun",
    "wof:placetype":"locality",
    "wof:population":591
},
  "geometry": {"coordinates":[76.12801899999999,10.374838],"type":"Point"}
}