{
  "type": "Feature",
  "properties": {
    "gn:admin1_code":"34.0",
    "gn:admin2_code":"217.0",
    "gn:asciiname":"Sitaram",
    "gn:country_code":"IN",
    "gn:dem":74,
    "gn:feature_class":"P",
    "gn:feature_code":"PPL",
    "gn:name":"Sit\u0101r\u0101m",
    "gn:population":0,
    "gn:timezone":"Asia/Kolkata",
    "iso:country":"IN",
    "name:tel_x_preferred":[
        "\u0c38\u0c40\u0c24\u0c3e\u0c30\u0c3e\u0c02"
    ],
    "wof:name":"Sitaram",
    "wof:placetype":"locality"
},
  "geometry": {"coordinates":[84.03746,26.41804],"type":"Point"}
}