{
  "type": "Feature",
  "properties": {
    "gn:admin1_code":"19.0",
    "gn:admin2_code":"581.0",
    "gn:asciiname":"Magondi",
    "gn:country_code":"IN",
    "gn:dem":810,
    "gn:feature_class":"P",
    "gn:feature_code":"PPL",
    "gn:name":"Magondi",
    "gn:population":0,
    "gn:timezone":"Asia/Kolkata",
    "iso:country":"IN",
    "wof:name":"Magondi",
    "wof:placetype":"locality"
},
  "geometry": {"coordinates":[78.17239000000002,12.94071],"type":"Point"}
}