{
  "type": "Feature",
  "properties": {
    "iso:country":"IN",
    "ks:ks_name":"Daryab Singh Patti",
    "ks:ks_pop":637,
    "ks:ks_type":"HABITATION",
    "ks:ks_uagg_main":0,
    "name:eng_x_preferred":[
        "Daryab Singh Patti"
    ],
    "wof:name":"Daryab Singh Patti",
    "wof:placetype":"neighbourhood",
    "wof:population":637
},
  "geometry": {"coordinates":[83.903356,26.792629],"type":"Point"}
}