{
  "type": "Feature",
  "properties": {
    "iso:country":"IN",
    "ks:ks_name":"5 KWD",
    "ks:ks_pop":189,
    "ks:ks_type":"VILLAGE",
    "name:eng_x_preferred":[
        "5 KWD"
    ],
    "wof:name":"5 KWD",
    "wof:placetype":"locality",
    "wof:population":189
},
  "geometry": {"coordinates":[74.387512,29.296731],"type":"Point"}
}