{
  "type": "Feature",
  "properties": {
    "iso:country":"IN",
    "ks:ks_name":"Edathara",
    "ks:ks_pop":420,
    "ks:ks_type":"HABITATION",
    "ks:ks_uagg_main":0,
    "name:eng_x_preferred":[
        "Edathara"
    ],
    "wof:name":"Edathara",
    "wof:placetype":"neighbourhood",
    "wof:population":420
},
  "geometry": {"coordinates":[76.821709,9.329606],"type":"Point"}
}