{
  "type": "Feature",
  "properties": {
    "iso:country":"IN",
    "ks:ks_name":"Paraikalam",
    "ks:ks_pop":100,
    "ks:ks_type":"HABITATION",
    "name:eng_x_preferred":[
        "Paraikalam"
    ],
    "wof:name":"Paraikalam",
    "wof:placetype":"locality",
    "wof:population":100
},
  "geometry": {"coordinates":[78.55662700000001,10.374612],"type":"Point"}
}