{
  "type": "Feature",
  "properties": {
    "gn:admin1_code":"12.0",
    "gn:admin2_code":"010",
    "gn:asciiname":"Wandahom",
    "gn:country_code":"IN",
    "gn:dem":1626,
    "gn:feature_class":"P",
    "gn:feature_code":"PPL",
    "gn:name":"Wandahom",
    "gn:population":0,
    "gn:timezone":"Asia/Kolkata",
    "iso:country":"IN",
    "wof:name":"Wandahom",
    "wof:placetype":"locality"
},
  "geometry": {"coordinates":[74.72469,34.24707],"type":"Point"}
}