{
  "type": "Feature",
  "properties": {
    "iso:country":"IN",
    "ks:ks_alt_nam":"GIRGAON",
    "ks:ks_name":"Girgaon",
    "ks:ks_pop":2375,
    "ks:ks_type":"HABITATION",
    "name:eng_x_preferred":[
        "Girgaon"
    ],
    "wof:name":"Girgaon",
    "wof:placetype":"locality",
    "wof:population":2375
},
  "geometry": {"coordinates":[75.642534,17.058065],"type":"Point"}
}