{
  "type": "Feature",
  "properties": {
    "gn:admin1_code":"39.0",
    "gn:admin2_code":"63.0",
    "gn:asciiname":"Mallades",
    "gn:country_code":"IN",
    "gn:dem":1390,
    "gn:feature_class":"P",
    "gn:feature_code":"PPL",
    "gn:name":"Mallades",
    "gn:population":0,
    "gn:timezone":"Asia/Kolkata",
    "iso:country":"IN",
    "wof:name":"Mallades",
    "wof:placetype":"locality"
},
  "geometry": {"coordinates":[79.94419000000001,29.95913],"type":"Point"}
}