{
  "type": "Feature",
  "properties": {
    "gn:admin1_code":"39.0",
    "gn:admin2_code":"63.0",
    "gn:asciiname":"Mallades",
    "gn:country_code":"IN",
    "gn:dem":1390,
    "gn:feature_class":"P",
    "gn:feature_code":"PPL",
    "gn:name":"Mallades",
    "gn:population":0,
    "gn:timezone":"Asia/Kolkata",
    "iso:country":"IN",
    "ks:ks_name":"Malladesh",
    "ks:ks_pop":618,
    "ks:ks_type":"VILLAGE",
    "name:eng_x_preferred":[
        "Malladesh"
    ],
    "name:eng_x_variant":[
        "Mallades"
    ],
    "wof:name":"Malladesh",
    "wof:placetype":"locality",
    "wof:population":618
},
  "geometry": {"coordinates":[79.93863,29.965577],"type":"Point"}
}