{
  "type": "Feature",
  "properties": {
    "iso:country":"IN",
    "ks:ks_name":"Bramhan Basti",
    "ks:ks_pop":124,
    "ks:ks_type":"HABITATION",
    "name:eng_x_preferred":[
        "Bramhan Basti"
    ],
    "wof:name":"Bramhan Basti",
    "wof:placetype":"locality",
    "wof:population":124
},
  "geometry": {"coordinates":[82.743562,25.347839],"type":"Point"}
}