{
  "type": "Feature",
  "properties": {
    "iso:country":"IN",
    "ks:ks_name":"Brajerkuthi",
    "ks:ks_pop":1924,
    "ks:ks_type":"VILLAGE",
    "name:eng_x_preferred":[
        "Brajerkuthi"
    ],
    "wof:name":"Brajerkuthi",
    "wof:placetype":"locality",
    "wof:population":1924
},
  "geometry": {"coordinates":[89.7097,26.433814],"type":"Point"}
}