{
  "type": "Feature",
  "properties": {
    "gn:admin1_code":"35",
    "gn:admin2_code":"426.0",
    "gn:asciiname":"Marainya",
    "gn:country_code":"IN",
    "gn:dem":402,
    "gn:feature_class":"P",
    "gn:feature_code":"PPL",
    "gn:name":"Mara\u012bnya",
    "gn:population":0,
    "gn:timezone":"Asia/Kolkata",
    "iso:country":"IN",
    "wof:name":"Marainya",
    "wof:placetype":"locality"
},
  "geometry": {"coordinates":[80.09218,24.70099],"type":"Point"}
}