{
  "type": "Feature",
  "properties": {
    "iso:country":"IN",
    "ks:ks_name":"Tikariya",
    "ks:ks_pop":119,
    "ks:ks_type":"VILLAGE",
    "ks:ks_uagg_main":0,
    "name:eng_x_preferred":[
        "Tikariya"
    ],
    "wof:name":"Tikariya",
    "wof:placetype":"neighbourhood",
    "wof:population":119
},
  "geometry": {"coordinates":[83.283254,26.550019],"type":"Point"}
}