{
  "type": "Feature",
  "properties": {
    "gn:admin1_code":"23",
    "gn:admin2_code":"35.0",
    "gn:asciiname":"Pherochechi",
    "gn:country_code":"IN",
    "gn:dem":237,
    "gn:feature_class":"P",
    "gn:feature_code":"PPL",
    "gn:name":"Pherochechi",
    "gn:population":0,
    "gn:timezone":"Asia/Kolkata",
    "iso:country":"IN",
    "ks:ks_name":"Pherochechi",
    "ks:ks_pop":1045,
    "ks:ks_type":"VILLAGE",
    "ks:ks_uagg_main":0,
    "name:eng_x_preferred":[
        "Pherochechi"
    ],
    "wof:name":"Pherochechi",
    "wof:placetype":"neighbourhood",
    "wof:population":1045
},
  "geometry": {"coordinates":[75.501881,31.840685],"type":"Point"}
}