{
  "type": "Feature",
  "properties": {
    "iso:country":"IN",
    "ks:ks_name":"Gothapatna",
    "ks:ks_pop":1641,
    "ks:ks_type":"VILLAGE",
    "ks:ks_uagg_main":0,
    "name:eng_x_preferred":[
        "Gothapatna"
    ],
    "wof:name":"Gothapatna",
    "wof:placetype":"neighbourhood",
    "wof:population":1641
},
  "geometry": {"coordinates":[85.741033,20.294197],"type":"Point"}
}