{
  "type": "Feature",
  "properties": {
    "iso:country":"IN",
    "ks:ks_alt_nam":"Edaiyur colony",
    "ks:ks_name":"Edaiyur Colony",
    "ks:ks_pop":934,
    "ks:ks_type":"HABITATION",
    "name:eng_x_preferred":[
        "Edaiyur Colony"
    ],
    "wof:name":"Edaiyur Colony",
    "wof:placetype":"locality",
    "wof:population":934
},
  "geometry": {"coordinates":[79.235556,11.49362],"type":"Point"}
}