{
  "type": "Feature",
  "properties": {
    "iso:country":"IN",
    "ks:ks_name":"Cholikere Estate",
    "ks:ks_pop":168,
    "ks:ks_type":"HABITATION",
    "ks:ks_uagg_main":0,
    "name:eng_x_preferred":[
        "Cholikere Estate"
    ],
    "wof:name":"Cholikere Estate",
    "wof:placetype":"neighbourhood",
    "wof:population":168
},
  "geometry": {"coordinates":[75.609706,13.122198],"type":"Point"}
}