{
  "type": "Feature",
  "properties": {
    "iso:country":"IN",
    "ks:ks_name":"Garhi Sona",
    "ks:ks_pop":998,
    "ks:ks_type":"HABITATION",
    "ks:ks_uagg_main":1,
    "name:eng_x_preferred":[
        "Garhi Sona"
    ],
    "wof:name":"Garhi Sona",
    "wof:placetype":"neighbourhood",
    "wof:population":998
},
  "geometry": {"coordinates":[78.07792499999999,27.108669],"type":"Point"}
}