{
  "type": "Feature",
  "properties": {
    "gn:admin1_code":"39",
    "gn:admin2_code":"61.0",
    "gn:asciiname":"Bamsu",
    "gn:country_code":"IN",
    "gn:dem":1066,
    "gn:feature_class":"P",
    "gn:feature_code":"PPL",
    "gn:name":"B\u0101msu",
    "gn:population":0,
    "gn:timezone":"Asia/Kolkata",
    "iso:country":"IN",
    "ks:ks_alt_nam":"B\u0101msu",
    "ks:ks_name":"Bamsu",
    "ks:ks_pop":136,
    "ks:ks_type":"VILLAGE",
    "name:eng_x_preferred":[
        "Bamsu"
    ],
    "name:eng_x_variant":[
        "B\u0101msu"
    ],
    "wof:name":"Bamsu",
    "wof:placetype":"locality",
    "wof:population":136
},
  "geometry": {"coordinates":[78.849054,29.761924],"type":"Point"}
}