{
  "type": "Feature",
  "properties": {
    "iso:country":"IN",
    "ks:ks_name":"Shakari Pur",
    "ks:ks_pop":364,
    "ks:ks_type":"VILLAGE",
    "name:eng_x_preferred":[
        "Shakari Pur"
    ],
    "wof:name":"Shakari Pur",
    "wof:placetype":"locality",
    "wof:population":364
},
  "geometry": {"coordinates":[83.16148200000001,24.674997],"type":"Point"}
}