{
  "type": "Feature",
  "properties": {
    "iso:country":"IN",
    "ks:ks_name":"Kashidih",
    "ks:ks_pop":648,
    "ks:ks_type":"VILLAGE",
    "name:eng_x_preferred":[
        "Kashidih"
    ],
    "wof:name":"Kashidih",
    "wof:placetype":"locality",
    "wof:population":648
},
  "geometry": {"coordinates":[85.64881200000001,23.360835],"type":"Point"}
}