{
  "type": "Feature",
  "properties": {
    "iso:country":"IN",
    "ks:ks_name":"Makkaltaimane",
    "ks:ks_pop":40,
    "ks:ks_type":"HABITATION",
    "name:eng_x_preferred":[
        "Makkaltaimane"
    ],
    "wof:name":"Makkaltaimane",
    "wof:placetype":"locality",
    "wof:population":40
},
  "geometry": {"coordinates":[74.71374299999999,14.598551],"type":"Point"}
}