{
  "type": "Feature",
  "properties": {
    "iso:country":"IN",
    "ks:ks_name":"Karheri",
    "ks:ks_pop":657,
    "ks:ks_type":"VILLAGE",
    "ks:ks_uagg_main":0,
    "name:eng_x_preferred":[
        "Karheri"
    ],
    "wof:name":"Karheri",
    "wof:placetype":"locality",
    "wof:population":657
},
  "geometry": {"coordinates":[76.452032,30.350043],"type":"Point"}
}