{
  "type": "Feature",
  "properties": {
    "iso:country":"IN",
    "ks:ks_name":"Badapadiaposi",
    "ks:ks_pop":116,
    "ks:ks_type":"VILLAGE",
    "name:eng_x_preferred":[
        "Badapadiaposi"
    ],
    "wof:name":"Badapadiaposi",
    "wof:placetype":"locality",
    "wof:population":116
},
  "geometry": {"coordinates":[85.88394700000001,21.589269],"type":"Point"}
}