{
  "type": "Feature",
  "properties": {
    "gn:admin1_code":"36",
    "gn:admin2_code":"194.0",
    "gn:asciiname":"Hardasipur",
    "gn:country_code":"IN",
    "gn:dem":82,
    "gn:feature_class":"P",
    "gn:feature_code":"PPL",
    "gn:name":"Hard\u0101s\u012bpur",
    "gn:population":0,
    "gn:timezone":"Asia/Kolkata",
    "iso:country":"IN",
    "ks:ks_alt_nam":"Hard\u0101s\u012bpur",
    "ks:ks_name":"Hardasipur",
    "ks:ks_type":"VILLAGE",
    "ks:ks_uagg_main":0,
    "name:eng_x_preferred":[
        "Hardasipur"
    ],
    "name:eng_x_variant":[
        "Hard\u0101s\u012bpur"
    ],
    "wof:name":"Hardasipur",
    "wof:placetype":"neighbourhood"
},
  "geometry": {"coordinates":[82.99275799999999,25.611444],"type":"Point"}
}