{
  "type": "Feature",
  "properties": {
    "gn:admin1_code":"19",
    "gn:admin2_code":"569.0",
    "gn:asciiname":"Kalavara",
    "gn:country_code":"IN",
    "gn:dem":11,
    "gn:feature_class":"P",
    "gn:feature_code":"PPLL",
    "gn:name":"K\u0101l\u0101vara",
    "gn:population":0,
    "gn:timezone":"Asia/Kolkata",
    "iso:country":"IN",
    "ks:ks_alt_nam":"K\u0101l\u0101vara",
    "ks:ks_name":"Kalavara",
    "ks:ks_pop":2838,
    "ks:ks_type":"VILLAGE",
    "name:eng_x_preferred":[
        "Kalavara"
    ],
    "name:eng_x_variant":[
        "K\u0101l\u0101vara"
    ],
    "wof:name":"Kalavara",
    "wof:placetype":"locality",
    "wof:population":2838
},
  "geometry": {"coordinates":[74.738145,13.596323],"type":"Point"}
}