{
  "type": "Feature",
  "properties": {
    "gn:admin1_code":"19",
    "gn:admin2_code":"569.0",
    "gn:asciiname":"Kalavara",
    "gn:country_code":"IN",
    "gn:dem":11,
    "gn:feature_class":"P",
    "gn:feature_code":"PPLL",
    "gn:name":"K\u0101l\u0101vara",
    "gn:population":0,
    "gn:timezone":"Asia/Kolkata",
    "iso:country":"IN",
    "wof:name":"Kalavara",
    "wof:placetype":"locality"
},
  "geometry": {"coordinates":[74.73815,13.59632],"type":"Point"}
}