{
  "type": "Feature",
  "properties": {
    "iso:country":"IN",
    "ks:ks_name":"Gudan Gaon",
    "ks:ks_pop":37,
    "ks:ks_type":"VILLAGE",
    "name:eng_x_preferred":[
        "Gudan Gaon"
    ],
    "wof:name":"Gudan Gaon",
    "wof:placetype":"locality",
    "wof:population":37
},
  "geometry": {"coordinates":[78.54819500000001,30.222994],"type":"Point"}
}