{
  "type": "Feature",
  "properties": {
    "iso:country":"IN",
    "ks:ks_name":"South East Gopalpur",
    "ks:ks_pop":1661,
    "ks:ks_type":"HABITATION",
    "name:eng_x_preferred":[
        "South East Gopalpur"
    ],
    "wof:name":"South East Gopalpur",
    "wof:placetype":"locality",
    "wof:population":1661
},
  "geometry": {"coordinates":[89.492317,26.460603],"type":"Point"}
}