{
  "type": "Feature",
  "properties": {
    "iso:country":"IN",
    "ks:ks_name":"Pradhan Ka Dera",
    "ks:ks_pop":50,
    "ks:ks_type":"HABITATION",
    "name:eng_x_preferred":[
        "Pradhan Ka Dera"
    ],
    "wof:name":"Pradhan Ka Dera",
    "wof:placetype":"locality",
    "wof:population":50
},
  "geometry": {"coordinates":[81.108496,25.139149],"type":"Point"}
}