{
  "type": "Feature",
  "properties": {
    "iso:country":"IN",
    "ks:ks_name":"Atareya",
    "ks:ks_pop":1175,
    "ks:ks_type":"VILLAGE",
    "ks:ks_uagg_main":0,
    "name:eng_x_preferred":[
        "Atareya"
    ],
    "wof:name":"Atareya",
    "wof:placetype":"neighbourhood",
    "wof:population":1175
},
  "geometry": {"coordinates":[80.56499100000001,28.408076],"type":"Point"}
}