{
  "type": "Feature",
  "properties": {
    "iso:country":"IN",
    "ks:ks_alt_nam":"gondalipada",
    "ks:ks_name":"Gondalipada",
    "ks:ks_pop":95,
    "ks:ks_type":"HABITATION",
    "ks:ks_uagg_main":0,
    "name:eng_x_preferred":[
        "Gondalipada"
    ],
    "wof:name":"Gondalipada",
    "wof:placetype":"neighbourhood",
    "wof:population":95
},
  "geometry": {"coordinates":[72.711506,19.666117],"type":"Point"}
}