{
  "type": "Feature",
  "properties": {
    "gn:admin1_code":"35.0",
    "gn:admin2_code":"442.0",
    "gn:asciiname":"Birgari",
    "gn:country_code":"IN",
    "gn:dem":474,
    "gn:feature_class":"P",
    "gn:feature_code":"PPL",
    "gn:name":"Birgari",
    "gn:population":0,
    "gn:timezone":"Asia/Kolkata",
    "iso:country":"IN",
    "wof:name":"Birgari",
    "wof:placetype":"locality"
},
  "geometry": {"coordinates":[76.91025999999999,23.5237],"type":"Point"}
}