{
  "type": "Feature",
  "properties": {
    "iso:country":"IN",
    "ks:ks_name":"Bahlarke",
    "ks:ks_pop":54,
    "ks:ks_type":"VILLAGE",
    "name:eng_x_preferred":[
        "Bahlarke"
    ],
    "wof:name":"Bahlarke",
    "wof:placetype":"locality",
    "wof:population":54
},
  "geometry": {"coordinates":[74.770364,31.134473],"type":"Point"}
}