{
  "type": "Feature",
  "properties": {
    "gn:admin1_code":"36.0",
    "gn:admin2_code":"186.0",
    "gn:asciiname":"Ninbha",
    "gn:country_code":"IN",
    "gn:dem":83,
    "gn:feature_class":"P",
    "gn:feature_code":"PPL",
    "gn:name":"Ninbha",
    "gn:population":0,
    "gn:timezone":"Asia/Kolkata",
    "iso:country":"IN",
    "wof:name":"Ninbha",
    "wof:placetype":"locality"
},
  "geometry": {"coordinates":[82.96351,27.00671],"type":"Point"}
}