{
  "type": "Feature",
  "properties": {
    "iso:country":"IN",
    "ks:ks_name":"N.C. Kurua Chapari",
    "ks:ks_pop":0,
    "ks:ks_type":"VILLAGE",
    "name:eng_x_preferred":[
        "N.C. Kurua Chapari"
    ],
    "wof:name":"N.C. Kurua Chapari",
    "wof:placetype":"locality",
    "wof:population":0
},
  "geometry": {"coordinates":[91.771297,26.24221],"type":"Point"}
}