{
  "type": "Feature",
  "properties": {
    "iso:country":"IN",
    "ks:ks_name":"Chitta Para",
    "ks:ks_pop":118,
    "ks:ks_type":"HABITATION",
    "name:eng_x_preferred":[
        "Chitta Para"
    ],
    "wof:name":"Chitta Para",
    "wof:placetype":"locality",
    "wof:population":118
},
  "geometry": {"coordinates":[91.991359,24.087727],"type":"Point"}
}