{
  "type": "Feature",
  "properties": {
    "iso:country":"IN",
    "ks:ks_alt_nam":"Suripara II",
    "ks:ks_name":"Suripara Ii",
    "ks:ks_pop":153,
    "ks:ks_type":"HABITATION",
    "name:eng_x_preferred":[
        "Suripara Ii"
    ],
    "wof:name":"Suripara Ii",
    "wof:placetype":"locality",
    "wof:population":153
},
  "geometry": {"coordinates":[90.14452300000001,26.318782],"type":"Point"}
}