{
  "type": "Feature",
  "properties": {
    "iso:country":"IN",
    "ks:ks_name":"Ramachandrapur",
    "ks:ks_pop":823,
    "ks:ks_type":"VILLAGE",
    "ks:ks_uagg_main":0,
    "name:eng_x_preferred":[
        "Ramachandrapur"
    ],
    "wof:name":"Ramachandrapur",
    "wof:placetype":"neighbourhood",
    "wof:population":823
},
  "geometry": {"coordinates":[86.077327,20.422885],"type":"Point"}
}