{
  "type": "Feature",
  "properties": {
    "iso:country":"IN",
    "ks:ks_alt_nam":"SURVE MALA",
    "ks:ks_name":"Surve Mala",
    "ks:ks_pop":85,
    "ks:ks_type":"HABITATION",
    "name:eng_x_preferred":[
        "Surve Mala"
    ],
    "wof:name":"Surve Mala",
    "wof:placetype":"locality",
    "wof:population":85
},
  "geometry": {"coordinates":[74.400175,17.193781],"type":"Point"}
}