{
  "type": "Feature",
  "properties": {
    "iso:country":"IN",
    "ks:ks_name":"Jakhol",
    "ks:ks_pop":275,
    "ks:ks_type":"VILLAGE",
    "name:eng_x_preferred":[
        "Jakhol"
    ],
    "wof:name":"Jakhol",
    "wof:placetype":"locality",
    "wof:population":275
},
  "geometry": {"coordinates":[78.57550000000001,30.770338],"type":"Point"}
}