{
  "type": "Feature",
  "properties": {
    "iso:country":"IN",
    "ks:ks_name":"Nepal Purwa",
    "ks:ks_pop":186,
    "ks:ks_type":"HABITATION",
    "name:eng_x_preferred":[
        "Nepal Purwa"
    ],
    "wof:name":"Nepal Purwa",
    "wof:placetype":"locality",
    "wof:population":186
},
  "geometry": {"coordinates":[81.37455799999999,27.589516],"type":"Point"}
}