{
  "type": "Feature",
  "properties": {
    "gn:admin1_code":"35.0",
    "gn:admin2_code":"442.0",
    "gn:asciiname":"Gager",
    "gn:country_code":"IN",
    "gn:dem":449,
    "gn:feature_class":"P",
    "gn:feature_code":"PPL",
    "gn:name":"G\u0101ger",
    "gn:population":0,
    "gn:timezone":"Asia/Kolkata",
    "iso:country":"IN",
    "name:ceb_x_preferred":[
        "Gager"
    ],
    "name:deu_x_preferred":[
        "Gager"
    ],
    "name:swe_x_preferred":[
        "Gager"
    ],
    "wof:name":"Gager",
    "wof:placetype":"locality"
},
  "geometry": {"coordinates":[76.80516,23.62472],"type":"Point"}
}