{
  "type": "Feature",
  "properties": {
    "iso:country":"IN",
    "ks:ks_name":"Dhumalwadi",
    "ks:ks_pop":205,
    "ks:ks_type":"HABITATION",
    "name:eng_x_preferred":[
        "Dhumalwadi"
    ],
    "wof:name":"Dhumalwadi",
    "wof:placetype":"locality",
    "wof:population":205
},
  "geometry": {"coordinates":[73.50407199999999,16.524711],"type":"Point"}
}