{
  "type": "Feature",
  "properties": {
    "iso:country":"IN",
    "ks:ks_alt_nam":"Men\u0101dh\u0101na",
    "ks:ks_name":"Menadhana",
    "ks:ks_type":"VILLAGE",
    "name:eng_x_preferred":[
        "Menadhana"
    ],
    "name:eng_x_variant":[
        "Men\u0101dh\u0101na"
    ],
    "wof:name":"Menadhana",
    "wof:placetype":"locality"
},
  "geometry": {"coordinates":[79.182125,23.515356],"type":"Point"}
}