{
  "type": "Feature",
  "properties": {
    "iso:country":"IN",
    "ks:ks_alt_nam":"TAJANI MANDO KI DHANI",
    "ks:ks_name":"Tajani Mando Ki Dhani",
    "ks:ks_pop":265,
    "ks:ks_type":"HABITATION",
    "name:eng_x_preferred":[
        "Tajani Mando Ki Dhani"
    ],
    "wof:name":"Tajani Mando Ki Dhani",
    "wof:placetype":"locality",
    "wof:population":265
},
  "geometry": {"coordinates":[71.338442,25.445708],"type":"Point"}
}