{
  "type": "Feature",
  "properties": {
    "iso:country":"IN",
    "ks:ks_name":"Barh Jagner",
    "ks:ks_pop":188,
    "ks:ks_type":"VILLAGE",
    "name:eng_x_preferred":[
        "Barh Jagner"
    ],
    "wof:name":"Barh Jagner",
    "wof:placetype":"locality",
    "wof:population":188
},
  "geometry": {"coordinates":[76.310103,26.674519],"type":"Point"}
}