{
  "type": "Feature",
  "properties": {
    "iso:country":"IN",
    "ks:ks_name":"Karmipur",
    "ks:ks_pop":340,
    "ks:ks_type":"HABITATION",
    "ks:ks_uagg_main":0,
    "name:eng_x_preferred":[
        "Karmipur"
    ],
    "wof:name":"Karmipur",
    "wof:placetype":"neighbourhood",
    "wof:population":340
},
  "geometry": {"coordinates":[81.215791,25.723705],"type":"Point"}
}