{
  "type": "Feature",
  "properties": {
    "iso:country":"IN",
    "ks:ks_name":"Sarwai",
    "ks:ks_pop":1119,
    "ks:ks_type":"VILLAGE",
    "name:eng_x_preferred":[
        "Sarwai"
    ],
    "wof:name":"Sarwai",
    "wof:placetype":"locality",
    "wof:population":1119
},
  "geometry": {"coordinates":[74.01063600000001,23.359294],"type":"Point"}
}