{
  "type": "Feature",
  "properties": {
    "gn:admin1_code":"25.0",
    "gn:admin2_code":"620.0",
    "gn:asciiname":"Vanduvancheri",
    "gn:country_code":"IN",
    "gn:dem":25,
    "gn:feature_class":"P",
    "gn:feature_code":"PPL",
    "gn:name":"Vanduv\u0101ncheri",
    "gn:population":0,
    "gn:timezone":"Asia/Kolkata",
    "iso:country":"IN",
    "name:ara_x_preferred":[
        "\u0641\u0627\u0646\u062f\u0648\u0641\u0627\u0646\u062a\u0634\u0631\u064a"
    ],
    "name:fas_x_preferred":[
        "\u0648\u0646\u062f\u0648\u0648\u0646\u0686\u0631\u06cc"
    ],
    "name:tam_x_preferred":[
        "\u0bb5\u0b9f\u0bc1\u0bb5\u0b9e\u0bcd\u0b9a\u0bc7\u0bb0\u0bbf"
    ],
    "wof:name":"Vanduvancheri",
    "wof:placetype":"locality"
},
  "geometry": {"coordinates":[79.44928,10.89714],"type":"Point"}
}