{
  "type": "Feature",
  "properties": {
    "iso:country":"IN",
    "ks:ks_alt_nam":"KATHULIA PURBATARI",
    "ks:ks_name":"Kathulia Purbatari",
    "ks:ks_pop":973,
    "ks:ks_type":"HABITATION",
    "name:eng_x_preferred":[
        "Kathulia Purbatari"
    ],
    "wof:name":"Kathulia Purbatari",
    "wof:placetype":"locality",
    "wof:population":973
},
  "geometry": {"coordinates":[88.973868,26.640512],"type":"Point"}
}