{
  "type": "Feature",
  "properties": {
    "iso:country":"IN",
    "ks:ks_name":"P Pasin",
    "ks:ks_pop":112,
    "ks:ks_type":"HABITATION",
    "name:eng_x_preferred":[
        "P Pasin"
    ],
    "wof:name":"P Pasin",
    "wof:placetype":"locality",
    "wof:population":112
},
  "geometry": {"coordinates":[81.253995,25.871388],"type":"Point"}
}