{
  "type": "Feature",
  "properties": {
    "gn:admin1_code":"19.0",
    "gn:admin2_code":"565",
    "gn:asciiname":"Hagari",
    "gn:country_code":"IN",
    "gn:dem":415,
    "gn:feature_class":"P",
    "gn:feature_code":"PPL",
    "gn:name":"Hagari",
    "gn:population":0,
    "gn:timezone":"Asia/Kolkata",
    "iso:country":"IN",
    "wof:name":"Hagari",
    "wof:placetype":"neighbourhood"
},
  "geometry": {"coordinates":[77.05006,15.15126],"type":"Point"}
}