{
  "type": "Feature",
  "properties": {
    "gn:admin1_code":"19.0",
    "gn:admin2_code":"575",
    "gn:asciiname":"Charmadi",
    "gn:country_code":"IN",
    "gn:dem":141,
    "gn:feature_class":"P",
    "gn:feature_code":"PPL",
    "gn:name":"Ch\u0101rm\u0101di",
    "gn:population":0,
    "gn:timezone":"Asia/Kolkata",
    "iso:country":"IN",
    "name:kan_x_preferred":[
        "\u0c9a\u0cbe\u0cb0\u0ccd\u0cae\u0cbe\u0ca1\u0cbf \u0c98\u0cbe\u0c9f\u0cbf"
    ],
    "name:und_x_variant":[
        "Ch\u0101rm\u0101di"
    ],
    "wof:name":"Charmadi",
    "wof:placetype":"locality"
},
  "geometry": {"coordinates":[75.42296999999998,13.05186],"type":"Point"}
}