{
  "type": "Feature",
  "properties": {
    "gn:admin1_code":"34.0",
    "gn:admin2_code":"236.0",
    "gn:asciiname":"Murgawan",
    "gn:country_code":"IN",
    "gn:dem":103,
    "gn:feature_class":"P",
    "gn:feature_code":"PPL",
    "gn:name":"Murg\u0101w\u0101n",
    "gn:population":0,
    "gn:timezone":"Asia/Kolkata",
    "iso:country":"IN",
    "ks:ks_alt_nam":"Murg\u0101w\u0101n",
    "ks:ks_name":"Murgawan",
    "ks:ks_pop":655,
    "ks:ks_type":"VILLAGE",
    "name:eng_x_preferred":[
        "Murgawan"
    ],
    "name:eng_x_variant":[
        "Murg\u0101w\u0101n"
    ],
    "wof:name":"Murgawan",
    "wof:placetype":"locality",
    "wof:population":655
},
  "geometry": {"coordinates":[84.996939,24.92446],"type":"Point"}
}