{
  "type": "Feature",
  "properties": {
    "gn:admin1_code":"36.0",
    "gn:admin2_code":"136.0",
    "gn:asciiname":"Maswasi",
    "gn:country_code":"IN",
    "gn:dem":218,
    "gn:feature_class":"P",
    "gn:feature_code":"PPL",
    "gn:name":"Masw\u0101si",
    "gn:population":0,
    "gn:timezone":"Asia/Kolkata",
    "iso:country":"IN",
    "name:bpy_x_preferred":[
        "\u09ae\u09be\u09b8\u09f1\u09be\u09b8\u09bf"
    ],
    "name:ita_x_preferred":[
        "Maswasi"
    ],
    "name:mlg_x_preferred":[
        "Maswasi"
    ],
    "name:msa_x_preferred":[
        "Maswasi"
    ],
    "name:new_x_preferred":[
        "\u092e\u0938\u094d\u0935\u093e\u0938\u0940"
    ],
    "name:nld_x_preferred":[
        "Maswasi"
    ],
    "name:pol_x_preferred":[
        "Maswasi"
    ],
    "name:por_x_preferred":[
        "Maswasi"
    ],
    "name:urd_x_preferred":[
        "\u0645\u0633\u0648\u0627\u0633\u06cc"
    ],
    "name:vie_x_preferred":[
        "Maswasi"
    ],
    "name:zho_x_preferred":[
        "\u9a6c\u65af\u74e6\u897f"
    ],
    "wof:name":"Maswasi",
    "wof:placetype":"locality"
},
  "geometry": {"coordinates":[79.06614999999999,29.10068],"type":"Point"}
}