{
  "type": "Feature",
  "properties": {
    "iso:country":"IN",
    "ks:ks_name":"Swargamvaripalle",
    "ks:ks_pop":15,
    "ks:ks_type":"HABITATION",
    "name:eng_x_preferred":[
        "Swargamvaripalle"
    ],
    "wof:name":"Swargamvaripalle",
    "wof:placetype":"locality",
    "wof:population":15
},
  "geometry": {"coordinates":[78.93329,13.815559],"type":"Point"}
}