{
  "type": "Feature",
  "properties": {
    "iso:country":"IN",
    "ks:ks_name":"Diwari",
    "ks:ks_pop":686,
    "ks:ks_type":"VILLAGE",
    "ks:ks_uagg_main":0,
    "name:eng_x_preferred":[
        "Diwari"
    ],
    "wof:name":"Diwari",
    "wof:placetype":"neighbourhood",
    "wof:population":686
},
  "geometry": {"coordinates":[80.36461,23.68291],"type":"Point"}
}