{
  "type": "Feature",
  "properties": {
    "iso:country":"IN",
    "ks:ks_name":"Wadageri",
    "ks:ks_pop":33,
    "ks:ks_type":"HABITATION",
    "name:eng_x_preferred":[
        "Wadageri"
    ],
    "wof:name":"Wadageri",
    "wof:placetype":"locality",
    "wof:population":33
},
  "geometry": {"coordinates":[74.807821,14.593592],"type":"Point"}
}