{
  "type": "Feature",
  "properties": {
    "iso:country":"IN",
    "ks:ks_name":"Gadariyawas",
    "ks:ks_pop":136,
    "ks:ks_type":"HABITATION",
    "name:eng_x_preferred":[
        "Gadariyawas"
    ],
    "wof:name":"Gadariyawas",
    "wof:placetype":"locality",
    "wof:population":136
},
  "geometry": {"coordinates":[73.372353,24.548931],"type":"Point"}
}