{
  "type": "Feature",
  "properties": {
    "iso:country":"IN",
    "ks:ks_name":"Dom Tola",
    "ks:ks_pop":873,
    "ks:ks_type":"HABITATION",
    "name:eng_x_preferred":[
        "Dom Tola"
    ],
    "wof:name":"Dom Tola",
    "wof:placetype":"locality",
    "wof:population":873
},
  "geometry": {"coordinates":[87.01160400000001,26.171172],"type":"Point"}
}