{
  "type": "Feature",
  "properties": {
    "iso:country":"IN",
    "ks:ks_name":"Umbla Makki",
    "ks:ks_pop":35,
    "ks:ks_type":"HABITATION",
    "name:eng_x_preferred":[
        "Umbla Makki"
    ],
    "wof:name":"Umbla Makki",
    "wof:placetype":"locality",
    "wof:population":35
},
  "geometry": {"coordinates":[74.50563099999999,14.23161],"type":"Point"}
}