{
  "type": "Feature",
  "properties": {
    "gn:admin1_code":"39.0",
    "gn:admin2_code":"59.0",
    "gn:asciiname":"Rangaon",
    "gn:country_code":"IN",
    "gn:dem":1184,
    "gn:feature_class":"P",
    "gn:feature_code":"PPL",
    "gn:name":"Rangaon",
    "gn:population":0,
    "gn:timezone":"Asia/Kolkata",
    "iso:country":"IN",
    "ks:ks_name":"Rangaon",
    "ks:ks_type":"VILLAGE",
    "name:eng_x_preferred":[
        "Rangaon"
    ],
    "wof:name":"Rangaon",
    "wof:placetype":"locality"
},
  "geometry": {"coordinates":[78.05789300000001,30.492124],"type":"Point"}
}