{
  "type": "Feature",
  "properties": {
    "iso:country":"IN",
    "ks:ks_name":"Abdullahpur",
    "ks:ks_type":"VILLAGE",
    "name:eng_x_preferred":[
        "Abdullahpur"
    ],
    "wof:name":"Abdullahpur",
    "wof:placetype":"locality"
},
  "geometry": {"coordinates":[83.736594,25.55006],"type":"Point"}
}