{
  "type": "Feature",
  "properties": {
    "iso:country":"IN",
    "ks:ks_name":"Khurd",
    "ks:ks_pop":46,
    "ks:ks_type":"VILLAGE",
    "name:eng_x_preferred":[
        "Khurd"
    ],
    "wof:name":"Khurd",
    "wof:placetype":"locality",
    "wof:population":46
},
  "geometry": {"coordinates":[87.264505,24.972978],"type":"Point"}
}