{
  "type": "Feature",
  "properties": {
    "iso:country":"IN",
    "ks:ks_alt_nam":"Bhadw\u0101dih",
    "ks:ks_name":"Bhadwadih",
    "ks:ks_pop":121,
    "ks:ks_type":"VILLAGE",
    "name:eng_x_preferred":[
        "Bhadwadih"
    ],
    "name:eng_x_variant":[
        "Bhadw\u0101dih"
    ],
    "wof:name":"Bhadwadih",
    "wof:placetype":"locality",
    "wof:population":121
},
  "geometry": {"coordinates":[86.066084,24.137265],"type":"Point"}
}