{
  "type": "Feature",
  "properties": {
    "gn:admin1_code":"24.0",
    "gn:admin2_code":"102",
    "gn:asciiname":"Meghsar",
    "gn:country_code":"IN",
    "gn:dem":221,
    "gn:feature_class":"P",
    "gn:feature_code":"PPL",
    "gn:name":"Meghsar",
    "gn:population":0,
    "gn:timezone":"Asia/Kolkata",
    "iso:country":"IN",
    "name:und_x_variant":[
        "Megsar"
    ],
    "wof:name":"Meghsar",
    "wof:placetype":"locality"
},
  "geometry": {"coordinates":[74.94126999999997,28.79649],"type":"Point"}
}