{
  "type": "Feature",
  "properties": {
    "iso:country":"IN",
    "ks:ks_alt_nam":"Kandulavaripalli A.Wada",
    "ks:ks_name":"Kandulavaripalli A.wada",
    "ks:ks_pop":129,
    "ks:ks_type":"HABITATION",
    "name:eng_x_preferred":[
        "Kandulavaripalli A.wada"
    ],
    "wof:name":"Kandulavaripalli A.wada",
    "wof:placetype":"locality",
    "wof:population":129
},
  "geometry": {"coordinates":[79.33987,14.136569],"type":"Point"}
}