{
  "type": "Feature",
  "properties": {
    "iso:country":"IN",
    "ks:ks_name":"Abra Dihi",
    "ks:ks_pop":999,
    "ks:ks_type":"VILLAGE",
    "ks:ks_uagg_main":0,
    "name:eng_x_preferred":[
        "Abra Dihi"
    ],
    "wof:name":"Abra Dihi",
    "wof:placetype":"neighbourhood",
    "wof:population":999
},
  "geometry": {"coordinates":[87.180655,22.565563],"type":"Point"}
}