{
  "type": "Feature",
  "properties": {
    "gn:admin1_code":"24",
    "gn:admin2_code":"109.0",
    "gn:asciiname":"Rahuwas",
    "gn:country_code":"IN",
    "gn:dem":345,
    "gn:feature_class":"P",
    "gn:feature_code":"PPL",
    "gn:name":"R\u0101h\u016bw\u0101s",
    "gn:population":0,
    "gn:timezone":"Asia/Kolkata",
    "iso:country":"IN",
    "name:und_x_variant":[
        "R\u0101h\u016bw\u0101s",
        "R\u0101haw\u0101s"
    ],
    "wof:name":"Rahuwas",
    "wof:placetype":"locality"
},
  "geometry": {"coordinates":[76.33495000000001,26.70002],"type":"Point"}
}