{
  "type": "Feature",
  "properties": {
    "iso:country":"IN",
    "ks:ks_alt_nam":"hulas khera",
    "ks:ks_name":"Hulas Khera",
    "ks:ks_pop":350,
    "ks:ks_type":"HABITATION",
    "ks:ks_uagg_main":0,
    "name:eng_x_preferred":[
        "Hulas Khera"
    ],
    "wof:name":"Hulas Khera",
    "wof:placetype":"neighbourhood",
    "wof:population":350
},
  "geometry": {"coordinates":[80.50602499999999,26.62122],"type":"Point"}
}