{
  "type": "Feature",
  "properties": {
    "iso:country":"IN",
    "ks:ks_name":"Aram Kallu Bus Stop",
    "ks:ks_pop":627,
    "ks:ks_type":"HABITATION",
    "ks:ks_uagg_main":0,
    "name:eng_x_preferred":[
        "Aram Kallu Bus Stop"
    ],
    "wof:name":"Aram Kallu Bus Stop",
    "wof:placetype":"neighbourhood",
    "wof:population":627
},
  "geometry": {"coordinates":[76.227137,10.462791],"type":"Point"}
}