{
  "type": "Feature",
  "properties": {
    "iso:country":"IN",
    "ks:ks_name":"Bhandewali",
    "ks:ks_pop":0,
    "ks:ks_type":"VILLAGE",
    "name:eng_x_preferred":[
        "Bhandewali"
    ],
    "wof:name":"Bhandewali",
    "wof:placetype":"locality",
    "wof:population":0
},
  "geometry": {"coordinates":[74.922431,31.777383],"type":"Point"}
}