{
  "type": "Feature",
  "properties": {
    "gn:admin1_code":"12.0",
    "gn:admin2_code":"2.0",
    "gn:asciiname":"Khaigom",
    "gn:country_code":"IN",
    "gn:dem":2083,
    "gn:feature_class":"P",
    "gn:feature_code":"PPL",
    "gn:name":"Khaigom",
    "gn:population":0,
    "gn:timezone":"Asia/Kolkata",
    "iso:country":"IN",
    "wof:name":"Khaigom",
    "wof:placetype":"locality"
},
  "geometry": {"coordinates":[74.75391999999999,33.81382],"type":"Point"}
}