{
  "type": "Feature",
  "properties": {
    "iso:country":"IN",
    "ks:ks_name":"Khandila",
    "ks:ks_pop":23,
    "ks:ks_type":"VILLAGE",
    "name:eng_x_preferred":[
        "Khandila"
    ],
    "wof:name":"Khandila",
    "wof:placetype":"locality",
    "wof:population":23
},
  "geometry": {"coordinates":[78.995988,29.631908],"type":"Point"}
}