{
  "type": "Feature",
  "properties": {
    "iso:country":"IN",
    "ks:ks_name":"Diapathar",
    "ks:ks_pop":230,
    "ks:ks_type":"VILLAGE",
    "name:eng_x_preferred":[
        "Diapathar"
    ],
    "wof:name":"Diapathar",
    "wof:placetype":"locality",
    "wof:population":230
},
  "geometry": {"coordinates":[84.10823499999999,22.446759],"type":"Point"}
}