{
  "type": "Feature",
  "properties": {
    "iso:country":"IN",
    "ks:ks_name":"Neeraje",
    "ks:ks_pop":50,
    "ks:ks_type":"HABITATION",
    "name:eng_x_preferred":[
        "Neeraje"
    ],
    "wof:name":"Neeraje",
    "wof:placetype":"locality",
    "wof:population":50
},
  "geometry": {"coordinates":[75.492818,12.747557],"type":"Point"}
}