{
  "type": "Feature",
  "properties": {
    "gn:admin1_code":"25.0",
    "gn:admin2_code":"631.0",
    "gn:asciiname":"Attur",
    "gn:country_code":"IN",
    "gn:dem":837,
    "gn:feature_class":"P",
    "gn:feature_code":"PPL",
    "gn:name":"Att\u016br",
    "gn:population":0,
    "gn:timezone":"Asia/Kolkata",
    "iso:country":"IN",
    "name:bpy_x_preferred":[
        "\u0986\u09a4\u09cd\u09a4\u09c1\u09b0"
    ],
    "name:ceb_x_preferred":[
        "Attur"
    ],
    "name:hin_x_preferred":[
        "\u0905\u0924\u094d\u0924\u0941\u0930"
    ],
    "name:ita_x_preferred":[
        "Attur"
    ],
    "name:mlg_x_preferred":[
        "Attur"
    ],
    "name:msa_x_preferred":[
        "Attur"
    ],
    "name:new_x_preferred":[
        "\u0905\u0924\u094d\u0924\u0941\u0930"
    ],
    "name:spa_x_preferred":[
        "Attur"
    ],
    "name:swe_x_preferred":[
        "Attur"
    ],
    "name:tam_x_preferred":[
        "\u0b86\u0ba4\u0bcd\u0ba4\u0bc2\u0bb0\u0bcd"
    ],
    "name:vie_x_preferred":[
        "Attur"
    ],
    "wof:name":"Attur",
    "wof:placetype":"locality"
},
  "geometry": {"coordinates":[77.91314,12.74671],"type":"Point"}
}