{
  "type": "Feature",
  "properties": {
    "iso:country":"IN",
    "ks:ks_name":"Jodhpuriya",
    "ks:ks_pop":613,
    "ks:ks_type":"VILLAGE",
    "name:eng_x_preferred":[
        "Jodhpuriya"
    ],
    "wof:name":"Jodhpuriya",
    "wof:placetype":"locality",
    "wof:population":613
},
  "geometry": {"coordinates":[73.834203,24.423694],"type":"Point"}
}