{
  "type": "Feature",
  "properties": {
    "gn:admin1_code":"19.0",
    "gn:admin2_code":"583.0",
    "gn:asciiname":"Kurubarhalli",
    "gn:country_code":"IN",
    "gn:dem":902,
    "gn:feature_class":"P",
    "gn:feature_code":"PPL",
    "gn:name":"Kurubarhalli",
    "gn:population":0,
    "gn:timezone":"Asia/Kolkata",
    "iso:country":"IN",
    "ks:ks_name":"Kurubarahally",
    "ks:ks_pop":158,
    "ks:ks_type":"VILLAGE",
    "ks:ks_uagg_main":0,
    "name:eng_x_preferred":[
        "Kurubarahally"
    ],
    "wof:name":"Kurubarahally",
    "wof:placetype":"locality",
    "wof:population":158
},
  "geometry": {"coordinates":[77.523166,13.306841],"type":"Point"}
}