{
  "type": "Feature",
  "properties": {
    "iso:country":"IN",
    "ks:ks_name":"Tilopad",
    "ks:ks_pop":132,
    "ks:ks_type":"HABITATION",
    "name:eng_x_preferred":[
        "Tilopad"
    ],
    "wof:name":"Tilopad",
    "wof:placetype":"locality",
    "wof:population":132
},
  "geometry": {"coordinates":[86.061212,22.889124],"type":"Point"}
}