{
  "type": "Feature",
  "properties": {
    "gn:admin1_code":"23.0",
    "gn:admin2_code":"35.0",
    "gn:asciiname":"Talwandi",
    "gn:country_code":"IN",
    "gn:dem":262,
    "gn:feature_class":"P",
    "gn:feature_code":"PPL",
    "gn:name":"Talwandi",
    "gn:population":0,
    "gn:timezone":"Asia/Kolkata",
    "iso:country":"IN",
    "name:fas_x_preferred":[
        "\u062a\u0644\u0648\u0646\u062f\u06cc"
    ],
    "name:hin_x_preferred":[
        "\u0924\u0932\u0935\u0902\u0921\u0940"
    ],
    "name:urd_x_preferred":[
        "\u062a\u0644\u0648\u0646\u0688\u0649"
    ],
    "wof:name":"Talwandi",
    "wof:placetype":"locality"
},
  "geometry": {"coordinates":[75.38042,31.97112000000001],"type":"Point"}
}