{
  "type": "Feature",
  "properties": {
    "gn:country":"IN",
    "gn:fcode":"PPL",
    "gn:population":28978,
    "iso:country":"IN",
    "name:ara_x_preferred":[
        "\u0628\u0627\u0646\u062f\u0627"
    ],
    "name:ast_x_preferred":[
        "Banda"
    ],
    "name:bel_x_preferred":[
        "\u0411\u0430\u043d\u0434\u0430"
    ],
    "name:ben_bn_x_preferred":[
        "\u09ac\u09be\u09a8\u09cd\u09a6\u09be"
    ],
    "name:ben_in_x_preferred":[
        "\u09ac\u09be\u09a8\u09cd\u09a6\u09be"
    ],
    "name:ben_x_preferred":[
        "\u09ac\u09be\u09a8\u09cd\u09a6\u09be"
    ],
    "name:bih_x_preferred":[
        "\u092c\u093e\u0901\u0926\u093e"
    ],
    "name:bos_x_preferred":[
        "Banda"
    ],
    "name:bpy_x_preferred":[
        "\u09ac\u09be\u09a8\u09cd\u09a6\u09be"
    ],
    "name:bul_x_preferred":[
        "\u0411\u0430\u043d\u0434\u0430"
    ],
    "name:cat_x_preferred":[
        "Banda"
    ],
    "name:ceb_x_preferred":[
        "Banda"
    ],
    "name:deu_x_preferred":[
        "Banda"
    ],
    "name:fra_x_preferred":[
        "Banda"
    ],
    "name:glg_x_preferred":[
        "Banda"
    ],
    "name:guj_x_preferred":[
        "\u0aac\u0abe\u0a82\u0aa1\u0abe"
    ],
    "name:heb_x_preferred":[
        "\u05d1\u05d0\u05e0\u05d3\u05d4"
    ],
    "name:hin_x_preferred":[
        "\u092c\u093e\u0902\u0926\u093e"
    ],
    "name:hrv_x_preferred":[
        "Banda"
    ],
    "name:ind_x_preferred":[
        "Banda"
    ],
    "name:ita_x_preferred":[
        "Banda"
    ],
    "name:jpn_x_preferred":[
        "\u30d0\u30f3\u30c0"
    ],
    "name:kan_x_preferred":[
        "\u0cac\u0c82\u0ca6"
    ],
    "name:kat_x_preferred":[
        "\u10d1\u10d0\u10dc\u10d3\u10d0"
    ],
    "name:kaz_x_preferred":[
        "\u0411\u0430\u043d\u0434\u0430"
    ],
    "name:lit_x_preferred":[
        "Banda"
    ],
    "name:mal_x_preferred":[
        "\u0d2c\u0d28\u0d4d\u0d26"
    ],
    "name:mar_x_preferred":[
        "\u092c\u0902\u0921\u093e"
    ],
    "name:new_x_preferred":[
        "\u092c\u093e\u0928\u094d\u0926\u093e"
    ],
    "name:nld_x_preferred":[
        "Banda"
    ],
    "name:pan_x_preferred":[
        "\u0a2c\u0a3e\u0a02\u0a26\u0a3e"
    ],
    "name:pnb_x_preferred":[
        "\u0628\u0646\u062f\u06c1"
    ],
    "name:pol_x_preferred":[
        "Banda"
    ],
    "name:por_x_preferred":[
        "Banda"
    ],
    "name:rus_x_preferred":[
        "\u0411\u0430\u043d\u0434\u0430"
    ],
    "name:slk_x_preferred":[
        "Banda"
    ],
    "name:spa_x_preferred":[
        "Banda"
    ],
    "name:swe_x_preferred":[
        "Banda"
    ],
    "name:tam_x_preferred":[
        "\u0baa\u0ba9\u0bcd\u0b9f\u0bbe"
    ],
    "name:tel_x_preferred":[
        "\u0c2c\u0c02\u0c21"
    ],
    "name:ukr_x_preferred":[
        "\u0411\u0430\u043d\u0434\u0430"
    ],
    "name:urd_x_preferred":[
        "\u0628\u0627\u0646\u062f\u06c1"
    ],
    "qs:name":"Banda",
    "qs:name_adm0":"India",
    "qs:name_adm1":"Madhya Pradesh",
    "qs:photos_9k":1,
    "qs:photos_9r":1,
    "qs:photos_all":1,
    "qs:photos_sr":0,
    "qs:placetype":"Town",
    "qs:pop_sr":"7",
    "wd:wordcount":262,
    "wof:name":"Banda",
    "wof:placetype":"locality",
    "wof:population":28978
},
  "geometry": {"coordinates":[78.96163,24.04449],"type":"Point"}
}