{
  "type": "Feature",
  "properties": {
    "gn:country":"IN",
    "gn:fcode":"PPL",
    "gn:pop":28978,
    "iso:country":"IN",
    "qs:name":"Banda",
    "qs:name_adm0":"India",
    "qs:name_adm1":"Madhya Pradesh",
    "qs:photos_9k":1,
    "qs:photos_9r":1,
    "qs:photos_all":1,
    "qs:photos_sr":0,
    "qs:placetype":"Town",
    "qs:pop_sr":"7",
    "wd:wordcount":262,
    "wof:name":"Banda",
    "wof:placetype":"locality",
    "wof:population":28978
},
  "geometry": {"coordinates":[78.96163,24.04449],"type":"Point"}
}