{
  "type": "Feature",
  "properties": {
    "iso:country":"IN",
    "ks:ks_name":"Mardihi",
    "ks:ks_pop":270,
    "ks:ks_type":"HABITATION",
    "name:eng_x_preferred":[
        "Mardihi"
    ],
    "wof:name":"Mardihi",
    "wof:placetype":"locality",
    "wof:population":270
},
  "geometry": {"coordinates":[84.84566100000001,21.673977],"type":"Point"}
}