{
  "type": "Feature",
  "properties": {
    "gn:admin1_code":"40",
    "gn:admin2_code":"537.0",
    "gn:asciiname":"Rangareddipalli",
    "gn:country_code":"IN",
    "gn:dem":501,
    "gn:feature_class":"P",
    "gn:feature_code":"PPL",
    "gn:name":"Rang\u0101reddipalli",
    "gn:population":0,
    "gn:timezone":"Asia/Kolkata",
    "iso:country":"IN",
    "wof:name":"Rangareddipalli",
    "wof:placetype":"locality"
},
  "geometry": {"coordinates":[77.77873000000002,16.93411],"type":"Point"}
}