{
  "type": "Feature",
  "properties": {
    "iso:country":"IN",
    "ks:ks_name":"Bagaiara",
    "ks:ks_pop":315,
    "ks:ks_type":"VILLAGE",
    "name:eng_x_preferred":[
        "Bagaiara"
    ],
    "wof:name":"Bagaiara",
    "wof:placetype":"locality",
    "wof:population":315
},
  "geometry": {"coordinates":[87.12161999999999,24.031292],"type":"Point"}
}