{
  "type": "Feature",
  "properties": {
    "iso:country":"IN",
    "ks:ks_name":"Jagtapwasti",
    "ks:ks_pop":250,
    "ks:ks_type":"HABITATION",
    "name:eng_x_preferred":[
        "Jagtapwasti"
    ],
    "wof:name":"Jagtapwasti",
    "wof:placetype":"locality",
    "wof:population":250
},
  "geometry": {"coordinates":[75.473838,18.126392],"type":"Point"}
}