{
  "type": "Feature",
  "properties": {
    "gn:admin1_code":"17.0",
    "gn:admin2_code":"273.0",
    "gn:asciiname":"Kadi",
    "gn:country_code":"IN",
    "gn:dem":1668,
    "gn:feature_class":"P",
    "gn:feature_code":"PPL",
    "gn:name":"Kadi",
    "gn:population":0,
    "gn:timezone":"Asia/Kolkata",
    "iso:country":"IN",
    "name:ceb_x_preferred":[
        "Kadi"
    ],
    "name:ces_x_preferred":[
        "Kadi"
    ],
    "name:deu_x_preferred":[
        "Kadi"
    ],
    "name:fas_x_preferred":[
        "\u0642\u0627\u0636\u06cc"
    ],
    "name:fra_x_preferred":[
        "Kadi"
    ],
    "name:ita_x_preferred":[
        "Kadi"
    ],
    "name:nld_x_preferred":[
        "Kadi"
    ],
    "name:rus_x_preferred":[
        "\u041a\u0430\u0434\u0438"
    ],
    "name:swe_x_preferred":[
        "Kadi"
    ],
    "wof:name":"Kadi",
    "wof:placetype":"locality"
},
  "geometry": {"coordinates":[93.77334999999999,25.30275],"type":"Point"}
}