{
  "type": "Feature",
  "properties": {
    "gn:admin1_code":"35.0",
    "gn:admin2_code":"451.0",
    "gn:asciiname":"Salaia Tola",
    "gn:country_code":"IN",
    "gn:dem":588,
    "gn:feature_class":"P",
    "gn:feature_code":"PPL",
    "gn:name":"Sal\u0101ia Tola",
    "gn:population":0,
    "gn:timezone":"Asia/Kolkata",
    "iso:country":"IN",
    "wof:name":"Salaia Tola",
    "wof:placetype":"neighbourhood"
},
  "geometry": {"coordinates":[80.39516,23.24591],"type":"Point"}
}