{
  "type": "Feature",
  "properties": {
    "gn:admin1_code":"23.0",
    "gn:admin2_code":"044",
    "gn:asciiname":"Fakarsar",
    "gn:country_code":"IN",
    "gn:dem":196,
    "gn:feature_class":"P",
    "gn:feature_code":"PPL",
    "gn:name":"Fakarsar",
    "gn:population":0,
    "gn:timezone":"Asia/Kolkata",
    "iso:country":"IN",
    "wof:name":"Fakarsar",
    "wof:placetype":"locality"
},
  "geometry": {"coordinates":[74.57458000000003,30.20016],"type":"Point"}
}