{
  "type": "Feature",
  "properties": {
    "gn:admin1_code":"23.0",
    "gn:admin2_code":"041",
    "gn:asciiname":"Hariawan Kalan",
    "gn:country_code":"IN",
    "gn:dem":266,
    "gn:feature_class":"P",
    "gn:feature_code":"PPL",
    "gn:name":"Hari\u0101w\u0101n Kal\u0101n",
    "gn:population":0,
    "gn:timezone":"Asia/Kolkata",
    "iso:country":"IN",
    "wof:name":"Hariawan Kalan",
    "wof:placetype":"locality"
},
  "geometry": {"coordinates":[76.24679999999999,30.73593],"type":"Point"}
}