{
  "type": "Feature",
  "properties": {
    "iso:country":"IN",
    "ks:ks_name":"Takewadi",
    "ks:ks_pop":178,
    "ks:ks_type":"HABITATION",
    "name:eng_x_preferred":[
        "Takewadi"
    ],
    "wof:name":"Takewadi",
    "wof:placetype":"locality",
    "wof:population":178
},
  "geometry": {"coordinates":[73.300967,17.372353],"type":"Point"}
}