{
  "type": "Feature",
  "properties": {
    "iso:country":"IN",
    "ks:ks_name":"Markhola",
    "ks:ks_pop":93,
    "ks:ks_type":"VILLAGE",
    "ks:ks_uagg_main":0,
    "name:eng_x_preferred":[
        "Markhola"
    ],
    "wof:name":"Markhola",
    "wof:placetype":"neighbourhood",
    "wof:population":93
},
  "geometry": {"coordinates":[78.896964,30.063118],"type":"Point"}
}