{
  "type": "Feature",
  "properties": {
    "iso:country":"IN",
    "ks:ks_name":"Shamsa",
    "ks:ks_pop":5622,
    "ks:ks_type":"VILLAGE",
    "name:eng_x_preferred":[
        "Shamsa"
    ],
    "wof:name":"Shamsa",
    "wof:placetype":"locality",
    "wof:population":5622
},
  "geometry": {"coordinates":[85.966678,25.631004],"type":"Point"}
}