{
  "type": "Feature",
  "properties": {
    "iso:country":"IN",
    "ks:ks_alt_nam":"Parai kollai vattam",
    "ks:ks_name":"Parai Kollai Vattam",
    "ks:ks_pop":400,
    "ks:ks_type":"HABITATION",
    "ks:ks_uagg_main":0,
    "name:eng_x_preferred":[
        "Parai Kollai Vattam"
    ],
    "wof:name":"Parai Kollai Vattam",
    "wof:placetype":"neighbourhood",
    "wof:population":400
},
  "geometry": {"coordinates":[78.58461699999999,12.703814],"type":"Point"}
}