{
  "type": "Feature",
  "properties": {
    "iso:country":"IN",
    "ks:ks_alt_nam":"Chakmi mal",
    "ks:ks_name":"Chakmi Mal",
    "ks:ks_pop":325,
    "ks:ks_type":"HABITATION",
    "name:eng_x_preferred":[
        "Chakmi Mal"
    ],
    "wof:name":"Chakmi Mal",
    "wof:placetype":"locality",
    "wof:population":325
},
  "geometry": {"coordinates":[81.51389,22.56541],"type":"Point"}
}