{
  "type": "Feature",
  "properties": {
    "gn:admin1_code":"21.0",
    "gn:admin2_code":"396.0",
    "gn:asciiname":"Charani Maribhata",
    "gn:country_code":"IN",
    "gn:dem":900,
    "gn:feature_class":"P",
    "gn:feature_code":"PPL",
    "gn:name":"Charani M\u0101ribhata",
    "gn:population":0,
    "gn:timezone":"Asia/Kolkata",
    "iso:country":"IN",
    "ks:ks_name":"Choranimaribhata",
    "ks:ks_pop":295,
    "ks:ks_type":"VILLAGE",
    "name:eng_x_preferred":[
        "Choranimaribhata"
    ],
    "name:eng_x_variant":[
        "Charani Maribhata"
    ],
    "wof:name":"Choranimaribhata",
    "wof:placetype":"locality",
    "wof:population":295
},
  "geometry": {"coordinates":[83.125257,19.233906],"type":"Point"}
}