{
  "type": "Feature",
  "properties": {
    "iso:country":"IN",
    "ks:ks_name":"Bholu Purwa",
    "ks:ks_pop":360,
    "ks:ks_type":"HABITATION",
    "name:eng_x_preferred":[
        "Bholu Purwa"
    ],
    "wof:name":"Bholu Purwa",
    "wof:placetype":"locality",
    "wof:population":360
},
  "geometry": {"coordinates":[81.925066,27.288754],"type":"Point"}
}