{
  "type": "Feature",
  "properties": {
    "iso:country":"IN",
    "ks:ks_name":"Kudlu",
    "ks:ks_type":"VILLAGE",
    "name:eng_x_preferred":[
        "Kudlu"
    ],
    "wof:name":"Kudlu",
    "wof:placetype":"locality"
},
  "geometry": {"coordinates":[77.327223,12.972935],"type":"Point"}
}