{
  "type": "Feature",
  "properties": {
    "iso:country":"IN",
    "ks:ks_name":"Devara Uliya",
    "ks:ks_pop":7,
    "ks:ks_type":"HABITATION",
    "name:eng_x_preferred":[
        "Devara Uliya"
    ],
    "wof:name":"Devara Uliya",
    "wof:placetype":"locality",
    "wof:population":7
},
  "geometry": {"coordinates":[75.61894100000001,12.607079],"type":"Point"}
}