{
  "type": "Feature",
  "properties": {
    "gn:admin1_code":"12",
    "gn:admin2_code":"15.0",
    "gn:asciiname":"Batapur",
    "gn:country_code":"IN",
    "gn:dem":1762,
    "gn:feature_class":"P",
    "gn:feature_code":"PPL",
    "gn:name":"Batapur",
    "gn:population":0,
    "gn:timezone":"Asia/Kolkata",
    "iso:country":"IN",
    "name:fas_x_preferred":[
        "\u0628\u0627\u062a\u0627\u067e\u0648\u0631"
    ],
    "name:urd_x_preferred":[
        "\u0628\u0627\u0679\u0627\u067e\u0648\u0631"
    ],
    "wof:name":"Batapur",
    "wof:placetype":"locality"
},
  "geometry": {"coordinates":[74.98786,33.67332],"type":"Point"}
}