{
  "type": "Feature",
  "properties": {
    "iso:country":"IN",
    "ks:ks_name":"Raghunathapur Sasan",
    "ks:ks_pop":144,
    "ks:ks_type":"VILLAGE",
    "name:eng_x_preferred":[
        "Raghunathapur Sasan"
    ],
    "wof:name":"Raghunathapur Sasan",
    "wof:placetype":"locality",
    "wof:population":144
},
  "geometry": {"coordinates":[86.120589,20.784087],"type":"Point"}
}