{
  "type": "Feature",
  "properties": {
    "iso:country":"IN",
    "ks:ks_name":"Panchayat Falia",
    "ks:ks_pop":165,
    "ks:ks_type":"HABITATION",
    "name:eng_x_preferred":[
        "Panchayat Falia"
    ],
    "wof:name":"Panchayat Falia",
    "wof:placetype":"locality",
    "wof:population":165
},
  "geometry": {"coordinates":[73.43216700000001,23.445083],"type":"Point"}
}