{
  "type": "Feature",
  "properties": {
    "iso:country":"IN",
    "ks:ks_name":"Dhanipal",
    "ks:ks_pop":2140,
    "ks:ks_type":"HABITATION",
    "name:eng_x_preferred":[
        "Dhanipal"
    ],
    "wof:name":"Dhanipal",
    "wof:placetype":"locality",
    "wof:population":2140
},
  "geometry": {"coordinates":[75.97506300000001,29.155329],"type":"Point"}
}