{
  "type": "Feature",
  "properties": {
    "gn:admin1_code":"37.0",
    "gn:admin2_code":"412",
    "gn:asciiname":"Batrel",
    "gn:country_code":"IN",
    "gn:dem":347,
    "gn:feature_class":"P",
    "gn:feature_code":"PPL",
    "gn:name":"Batrel",
    "gn:population":0,
    "gn:timezone":"Asia/Kolkata",
    "iso:country":"IN",
    "ks:ks_name":"Batrel",
    "ks:ks_pop":0,
    "ks:ks_type":"VILLAGE",
    "name:eng_x_preferred":[
        "Batrel"
    ],
    "wof:name":"Batrel",
    "wof:placetype":"locality",
    "wof:population":0
},
  "geometry": {"coordinates":[81.540871,20.571486],"type":"Point"}
}