{
  "type": "Feature",
  "properties": {
    "gn:admin1_code":"9.0",
    "gn:admin2_code":"475",
    "gn:asciiname":"Dhandhalpur",
    "gn:country_code":"IN",
    "gn:dem":172,
    "gn:feature_class":"P",
    "gn:feature_code":"PPL",
    "gn:name":"Dhandhalpur",
    "gn:population":0,
    "gn:timezone":"Asia/Kolkata",
    "iso:country":"IN",
    "wof:name":"Dhandhalpur",
    "wof:placetype":"locality"
},
  "geometry": {"coordinates":[71.3623,22.39251],"type":"Point"}
}