{
  "type": "Feature",
  "properties": {
    "gn:admin1_code":"11",
    "gn:admin2_code":"23.0",
    "gn:asciiname":"Amrota Got",
    "gn:country_code":"IN",
    "gn:dem":2909,
    "gn:feature_class":"P",
    "gn:feature_code":"PPL",
    "gn:name":"Amrota Got",
    "gn:population":0,
    "gn:timezone":"Asia/Kolkata",
    "iso:country":"IN",
    "wof:name":"Amrota Got",
    "wof:placetype":"locality"
},
  "geometry": {"coordinates":[76.29579,32.7748],"type":"Point"}
}