{
  "type": "Feature",
  "properties": {
    "iso:country":"IN",
    "ks:ks_name":"Kusumkot",
    "ks:ks_pop":2061,
    "ks:ks_type":"VILLAGE",
    "name:eng_x_preferred":[
        "Kusumkot"
    ],
    "wof:name":"Kusumkot",
    "wof:placetype":"locality",
    "wof:population":2061
},
  "geometry": {"coordinates":[76.866831,21.530843],"type":"Point"}
}