{
  "type": "Feature",
  "properties": {
    "iso:country":"IN",
    "ks:ks_name":"Chhichudih",
    "ks:ks_pop":353,
    "ks:ks_type":"HABITATION",
    "name:eng_x_preferred":[
        "Chhichudih"
    ],
    "wof:name":"Chhichudih",
    "wof:placetype":"locality",
    "wof:population":353
},
  "geometry": {"coordinates":[86.37404100000001,24.5476],"type":"Point"}
}