{
  "type": "Feature",
  "properties": {
    "gn:admin1_code":"11.0",
    "gn:admin2_code":"27.0",
    "gn:asciiname":"Katahach",
    "gn:country_code":"IN",
    "gn:dem":1616,
    "gn:feature_class":"P",
    "gn:feature_code":"PPL",
    "gn:name":"Kat\u0101hach",
    "gn:population":0,
    "gn:timezone":"Asia/Kolkata",
    "iso:country":"IN",
    "wof:name":"Katahach",
    "wof:placetype":"locality"
},
  "geometry": {"coordinates":[77.30616999999999,31.45431],"type":"Point"}
}