{
  "type": "Feature",
  "properties": {
    "iso:country":"IN",
    "ks:ks_name":"Kalathurpadi",
    "ks:ks_pop":231,
    "ks:ks_type":"HABITATION",
    "name:eng_x_preferred":[
        "Kalathurpadi"
    ],
    "wof:name":"Kalathurpadi",
    "wof:placetype":"locality",
    "wof:population":231
},
  "geometry": {"coordinates":[76.029737,11.406431],"type":"Point"}
}