{
  "type": "Feature",
  "properties": {
    "iso:country":"IN",
    "ks:ks_name":"Ram Kumar Ki Dhani",
    "ks:ks_pop":20,
    "ks:ks_type":"HABITATION",
    "name:eng_x_preferred":[
        "Ram Kumar Ki Dhani"
    ],
    "wof:name":"Ram Kumar Ki Dhani",
    "wof:placetype":"locality",
    "wof:population":20
},
  "geometry": {"coordinates":[75.280795,28.246951],"type":"Point"}
}