{
  "type": "Feature",
  "properties": {
    "gn:admin1_code":"39",
    "gn:admin2_code":"56.0",
    "gn:asciiname":"Madheso",
    "gn:country_code":"IN",
    "gn:dem":2242,
    "gn:feature_class":"P",
    "gn:feature_code":"PPL",
    "gn:name":"Madheso",
    "gn:population":0,
    "gn:timezone":"Asia/Kolkata",
    "iso:country":"IN",
    "name:und_x_variant":[
        "Madhes",
        "Madheso"
    ],
    "wof:name":"Madheso",
    "wof:placetype":"locality"
},
  "geometry": {"coordinates":[78.40748000000001,30.92459],"type":"Point"}
}