{
  "type": "Feature",
  "properties": {
    "gn:admin1_code":"35.0",
    "gn:admin2_code":"442.0",
    "gn:asciiname":"Chhibar",
    "gn:country_code":"IN",
    "gn:dem":415,
    "gn:feature_class":"P",
    "gn:feature_code":"PPL",
    "gn:name":"Chh\u012bbar",
    "gn:population":0,
    "gn:timezone":"Asia/Kolkata",
    "iso:country":"IN",
    "wof:name":"Chhibar",
    "wof:placetype":"locality"
},
  "geometry": {"coordinates":[76.49509999999999,24.1235],"type":"Point"}
}