{
  "type": "Feature",
  "properties": {
    "gn:admin1_code":"34.0",
    "gn:admin2_code":"229.0",
    "gn:asciiname":"Renri",
    "gn:country_code":"IN",
    "gn:dem":59,
    "gn:feature_class":"P",
    "gn:feature_code":"PPL",
    "gn:name":"Renri",
    "gn:population":0,
    "gn:timezone":"Asia/Kolkata",
    "iso:country":"IN",
    "name:ara_x_preferred":[
        "\u0631\u064a\u0646\u0631\u064a"
    ],
    "name:fas_x_preferred":[
        "\u0631\u06cc\u0646\u0631\u06cc"
    ],
    "name:ita_x_preferred":[
        "Renri"
    ],
    "name:nor_x_preferred":[
        "Renri"
    ],
    "name:rus_x_preferred":[
        "\u0414\u0437\u0438\u043d\u0434\u0437\u0438\u0446\u0443"
    ],
    "wof:name":"Renri",
    "wof:placetype":"locality"
},
  "geometry": {"coordinates":[85.23560999999999,25.3222],"type":"Point"}
}