{
  "type": "Feature",
  "properties": {
    "gn:admin1_code":"25.0",
    "gn:admin2_code":"631.0",
    "gn:asciiname":"Mallepalli",
    "gn:country_code":"IN",
    "gn:dem":721,
    "gn:feature_class":"P",
    "gn:feature_code":"PPL",
    "gn:name":"Mallepalli",
    "gn:population":0,
    "gn:timezone":"Asia/Kolkata",
    "iso:country":"IN",
    "name:hin_x_preferred":[
        "\u092e\u0932\u094d\u0932\u0947\u092a\u0932\u094d\u0932\u0946"
    ],
    "name:new_x_preferred":[
        "\u092e\u0932\u094d\u0932\u0947\u092a\u0932\u094d\u0932\u0946"
    ],
    "name:tel_x_preferred":[
        "\u0c2e\u0c32\u0c4d\u0c32\u0c47\u0c2a\u0c32\u0c4d\u0c32\u0c46"
    ],
    "name:urd_x_preferred":[
        "\u0645\u0644\u06d2 \u067e\u0644\u06cc"
    ],
    "wof:name":"Mallepalli",
    "wof:placetype":"locality"
},
  "geometry": {"coordinates":[78.02927,12.71691],"type":"Point"}
}