{
  "type": "Feature",
  "properties": {
    "gn:admin1_code":"10.0",
    "gn:admin2_code":"080",
    "gn:asciiname":"Ranjitkakar ki Dhani",
    "gn:country_code":"IN",
    "gn:dem":210,
    "gn:feature_class":"P",
    "gn:feature_code":"PPL",
    "gn:name":"Ranj\u012btkakar ki Dh\u0101ni",
    "gn:population":0,
    "gn:timezone":"Asia/Kolkata",
    "iso:country":"IN",
    "wof:name":"Ranjitkakar ki Dhani",
    "wof:placetype":"locality"
},
  "geometry": {"coordinates":[75.64542,28.96251],"type":"Point"}
}