{
  "type": "Feature",
  "properties": {
    "iso:country":"IN",
    "ks:ks_name":"Banglabari",
    "ks:ks_pop":221,
    "ks:ks_type":"VILLAGE",
    "name:eng_x_preferred":[
        "Banglabari"
    ],
    "wof:name":"Banglabari",
    "wof:placetype":"locality",
    "wof:population":221
},
  "geometry": {"coordinates":[92.26008899999999,23.928936],"type":"Point"}
}