{
  "type": "Feature",
  "properties": {
    "gn:admin1_code":"11",
    "gn:admin2_code":"27.0",
    "gn:asciiname":"Khiur",
    "gn:country_code":"IN",
    "gn:dem":852,
    "gn:feature_class":"P",
    "gn:feature_code":"PPL",
    "gn:name":"Kh\u012b\u016br",
    "gn:population":0,
    "gn:timezone":"Asia/Kolkata",
    "iso:country":"IN",
    "wof:name":"Khiur",
    "wof:placetype":"locality"
},
  "geometry": {"coordinates":[76.97049,31.58594],"type":"Point"}
}