{
  "type": "Feature",
  "properties": {
    "iso:country":"IN",
    "ks:ks_alt_nam":"SUKHI BIGHA",
    "ks:ks_name":"Sukhi Bigha",
    "ks:ks_pop":831,
    "ks:ks_type":"HABITATION",
    "name:eng_x_preferred":[
        "Sukhi Bigha"
    ],
    "wof:name":"Sukhi Bigha",
    "wof:placetype":"locality",
    "wof:population":831
},
  "geometry": {"coordinates":[84.64431399999999,25.202422],"type":"Point"}
}