{
  "type": "Feature",
  "properties": {
    "gn:admin1_code":"24.0",
    "gn:admin2_code":"105.0",
    "gn:asciiname":"Bholapura",
    "gn:country_code":"IN",
    "gn:dem":218,
    "gn:feature_class":"P",
    "gn:feature_code":"PPL",
    "gn:name":"Bhol\u0101pura",
    "gn:population":0,
    "gn:timezone":"Asia/Kolkata",
    "iso:country":"IN",
    "wof:name":"Bholapura",
    "wof:placetype":"locality"
},
  "geometry": {"coordinates":[77.34899999999998,26.8714],"type":"Point"}
}