{
  "type": "Feature",
  "properties": {
    "iso:country":"IN",
    "ks:ks_alt_nam":"DHARHI TOLA",
    "ks:ks_name":"Dharhi Tola",
    "ks:ks_pop":978,
    "ks:ks_type":"HABITATION",
    "name:eng_x_preferred":[
        "Dharhi Tola"
    ],
    "wof:name":"Dharhi Tola",
    "wof:placetype":"locality",
    "wof:population":978
},
  "geometry": {"coordinates":[85.927183,25.241709],"type":"Point"}
}