{
  "type": "Feature",
  "properties": {
    "gn:admin1_code":"34.0",
    "gn:admin2_code":"218.0",
    "gn:asciiname":"Nagai",
    "gn:country_code":"IN",
    "gn:dem":60,
    "gn:feature_class":"P",
    "gn:feature_code":"PPL",
    "gn:name":"Nagai",
    "gn:population":0,
    "gn:timezone":"Asia/Kolkata",
    "iso:country":"IN",
    "ks:ks_name":"Nagai",
    "ks:ks_pop":503,
    "ks:ks_type":"VILLAGE",
    "ks:ks_uagg_main":0,
    "name:deu_x_preferred":[
        "Nagai"
    ],
    "name:eng_x_preferred":[
        "Nagai"
    ],
    "name:ita_x_preferred":[
        "Nagai"
    ],
    "name:kor_x_preferred":[
        "\ub098\uac00\uc774"
    ],
    "name:lit_x_preferred":[
        "Nagai"
    ],
    "name:mlg_x_preferred":[
        "Nagai"
    ],
    "name:nld_x_preferred":[
        "Nagai"
    ],
    "name:rus_x_preferred":[
        "\u041d\u0430\u0433\u0430\u0438"
    ],
    "wof:name":"Nagai",
    "wof:placetype":"neighbourhood",
    "wof:population":503
},
  "geometry": {"coordinates":[84.41699199999999,25.978156],"type":"Point"}
}