{
  "type": "Feature",
  "properties": {
    "gn:admin1_code":"12.0",
    "gn:admin2_code":"10.0",
    "gn:asciiname":"Krunts",
    "gn:country_code":"IN",
    "gn:dem":1616,
    "gn:feature_class":"P",
    "gn:feature_code":"PPL",
    "gn:name":"Kr\u016bnts",
    "gn:population":0,
    "gn:timezone":"Asia/Kolkata",
    "iso:country":"IN",
    "wof:name":"Krunts",
    "wof:placetype":"locality"
},
  "geometry": {"coordinates":[74.94893,33.99869],"type":"Point"}
}