{
  "type": "Feature",
  "properties": {
    "gn:admin1_code":"36.0",
    "gn:admin2_code":"132",
    "gn:asciiname":"Dhunda Majra",
    "gn:country_code":"IN",
    "gn:dem":258,
    "gn:feature_class":"P",
    "gn:feature_code":"PPL",
    "gn:name":"Dhunda M\u0101jra",
    "gn:population":0,
    "gn:timezone":"Asia/Kolkata",
    "iso:country":"IN",
    "wof:name":"Dhunda Majra",
    "wof:placetype":"locality"
},
  "geometry": {"coordinates":[77.2165,29.87246],"type":"Point"}
}