{
  "type": "Feature",
  "properties": {
    "gn:admin1_code":"19",
    "gn:admin2_code":"579.0",
    "gn:asciiname":"Shikar Mothakpalli",
    "gn:country_code":"IN",
    "gn:dem":492,
    "gn:feature_class":"P",
    "gn:feature_code":"PPL",
    "gn:name":"Shik\u0101r Mothakpalli",
    "gn:population":0,
    "gn:timezone":"Asia/Kolkata",
    "iso:country":"IN",
    "wof:name":"Shikar Mothakpalli",
    "wof:placetype":"locality"
},
  "geometry": {"coordinates":[77.38367,17.54011],"type":"Point"}
}