{
  "type": "Feature",
  "properties": {
    "iso:country":"IN",
    "ks:ks_name":"Haludbani",
    "ks:ks_pop":352,
    "ks:ks_type":"VILLAGE",
    "name:eng_x_preferred":[
        "Haludbani"
    ],
    "wof:name":"Haludbani",
    "wof:placetype":"locality",
    "wof:population":352
},
  "geometry": {"coordinates":[86.40354499999999,22.369504],"type":"Point"}
}