{
  "type": "Feature",
  "properties": {
    "iso:country":"IN",
    "ks:ks_name":"Kumaramudi",
    "ks:ks_pop":18,
    "ks:ks_type":"HABITATION",
    "name:eng_x_preferred":[
        "Kumaramudi"
    ],
    "wof:name":"Kumaramudi",
    "wof:placetype":"locality",
    "wof:population":18
},
  "geometry": {"coordinates":[76.986648,11.446748],"type":"Point"}
}