{
  "type": "Feature",
  "properties": {
    "iso:country":"IN",
    "ks:ks_name":"Rangametya",
    "ks:ks_pop":178,
    "ks:ks_type":"VILLAGE",
    "name:eng_x_preferred":[
        "Rangametya"
    ],
    "wof:name":"Rangametya",
    "wof:placetype":"locality",
    "wof:population":178
},
  "geometry": {"coordinates":[86.75273,23.702757],"type":"Point"}
}