{
  "type": "Feature",
  "properties": {
    "gn:admin1_code":"36",
    "gn:admin2_code":"199.0",
    "gn:asciiname":"Nahian",
    "gn:country_code":"IN",
    "gn:dem":81,
    "gn:feature_class":"P",
    "gn:feature_code":"PPL",
    "gn:name":"Nah\u012b\u0101n",
    "gn:population":0,
    "gn:timezone":"Asia/Kolkata",
    "iso:country":"IN",
    "ks:ks_alt_nam":"Nah\u012b\u0101n",
    "ks:ks_name":"Nahian",
    "ks:ks_type":"VILLAGE",
    "ks:ks_uagg_main":0,
    "name:eng_x_preferred":[
        "Nahian"
    ],
    "name:eng_x_variant":[
        "Nah\u012b\u0101n"
    ],
    "wof:name":"Nahian",
    "wof:placetype":"neighbourhood"
},
  "geometry": {"coordinates":[82.77574,25.122876],"type":"Point"}
}