{
  "type": "Feature",
  "properties": {
    "gn:admin1_code":"36.0",
    "gn:admin2_code":"174.0",
    "gn:asciiname":"Jawai",
    "gn:country_code":"IN",
    "gn:dem":100,
    "gn:feature_class":"P",
    "gn:feature_code":"PPL",
    "gn:name":"Jawai",
    "gn:population":0,
    "gn:timezone":"Asia/Kolkata",
    "iso:country":"IN",
    "name:ben_x_preferred":[
        "\u099c\u09be\u0993\u09af\u09bc\u09be\u0987"
    ],
    "name:bpy_x_preferred":[
        "\u099c\u09be\u0993\u09af\u09bc\u09be\u0987"
    ],
    "name:new_x_preferred":[
        "\u091c\u0935\u093e\u0908"
    ],
    "name:por_x_preferred":[
        "Jawai"
    ],
    "name:vie_x_preferred":[
        "Jawai"
    ],
    "wof:name":"Jawai",
    "wof:placetype":"locality"
},
  "geometry": {"coordinates":[81.56128000000002,25.32509],"type":"Point"}
}