{
  "type": "Feature",
  "properties": {
    "iso:country":"IN",
    "ks:ks_name":"Purunapani",
    "ks:ks_pop":327,
    "ks:ks_type":"VILLAGE",
    "name:eng_x_preferred":[
        "Purunapani"
    ],
    "wof:name":"Purunapani",
    "wof:placetype":"locality",
    "wof:population":327
},
  "geometry": {"coordinates":[86.84567699999999,21.706531],"type":"Point"}
}