{
  "type": "Feature",
  "properties": {
    "iso:country":"IN",
    "ks:ks_name":"Ranginiguda",
    "ks:ks_pop":156,
    "ks:ks_type":"VILLAGE",
    "name:eng_x_preferred":[
        "Ranginiguda"
    ],
    "wof:name":"Ranginiguda",
    "wof:placetype":"locality",
    "wof:population":156
},
  "geometry": {"coordinates":[82.12538600000001,18.354654],"type":"Point"}
}