{
  "type": "Feature",
  "properties": {
    "gn:admin1_code":"37.0",
    "gn:admin2_code":"402.0",
    "gn:asciiname":"Talasily",
    "gn:country_code":"IN",
    "gn:dem":851,
    "gn:feature_class":"P",
    "gn:feature_code":"PPL",
    "gn:name":"Talasily",
    "gn:population":0,
    "gn:timezone":"Asia/Kolkata",
    "iso:country":"IN",
    "ks:ks_name":"Talasili",
    "ks:ks_pop":484,
    "ks:ks_type":"VILLAGE",
    "name:eng_x_preferred":[
        "Talasili"
    ],
    "name:eng_x_variant":[
        "Talasily"
    ],
    "wof:name":"Talasili",
    "wof:placetype":"locality",
    "wof:population":484
},
  "geometry": {"coordinates":[83.96807699999999,23.033111],"type":"Point"}
}