{
  "type": "Feature",
  "properties": {
    "iso:country":"IN",
    "ks:ks_name":"Dedrani",
    "ks:ks_pop":42,
    "ks:ks_type":"VILLAGE",
    "name:eng_x_preferred":[
        "Dedrani"
    ],
    "wof:name":"Dedrani",
    "wof:placetype":"locality",
    "wof:population":42
},
  "geometry": {"coordinates":[68.965366,23.48607],"type":"Point"}
}