{
  "type": "Feature",
  "properties": {
    "iso:country":"IN",
    "ks:ks_name":"Mandadijaddu",
    "ks:ks_pop":33,
    "ks:ks_type":"HABITATION",
    "name:eng_x_preferred":[
        "Mandadijaddu"
    ],
    "wof:name":"Mandadijaddu",
    "wof:placetype":"locality",
    "wof:population":33
},
  "geometry": {"coordinates":[74.957694,13.457637],"type":"Point"}
}