{
  "type": "Feature",
  "properties": {
    "gn:admin1_code":"11.0",
    "gn:asciiname":"Khawa",
    "gn:country_code":"IN",
    "gn:dem":1061,
    "gn:feature_class":"P",
    "gn:feature_code":"PPL",
    "gn:name":"Kh\u0101wa",
    "gn:population":0,
    "gn:timezone":"Asia/Kolkata",
    "iso:country":"IN",
    "name:bih_x_preferred":[
        "\u0916\u093e\u0935\u093e"
    ],
    "name:ceb_x_preferred":[
        "Khawa"
    ],
    "name:mai_x_preferred":[
        "\u0916\u093e\u0935\u093e"
    ],
    "name:msa_x_preferred":[
        "Khawa"
    ],
    "name:nep_x_preferred":[
        "\u0916\u093e\u0935\u093e"
    ],
    "name:new_x_preferred":[
        "\u0916\u0935\u093e"
    ],
    "name:pol_x_preferred":[
        "Khawa"
    ],
    "wof:name":"Khawa",
    "wof:placetype":"locality"
},
  "geometry": {"coordinates":[77.13932,30.69933],"type":"Point"}
}