{
  "type": "Feature",
  "properties": {
    "gn:admin1_code":"28.0",
    "gn:admin2_code":"336",
    "gn:asciiname":"Badkulla",
    "gn:country_code":"IN",
    "gn:dem":20,
    "gn:feature_class":"P",
    "gn:feature_code":"PPL",
    "gn:name":"B\u0101dkulla",
    "gn:population":0,
    "gn:timezone":"Asia/Kolkata",
    "iso:country":"IN",
    "ks:ks_name":"Badkulla",
    "ks:ks_pop":15788,
    "ks:ks_type":"VILLAGE",
    "ks:ks_uagg_main":0,
    "name:ceb_x_preferred":[
        "B\u0101dkulla"
    ],
    "name:eng_x_preferred":[
        "Badkulla"
    ],
    "name:swe_x_preferred":[
        "B\u0101dkulla"
    ],
    "wof:name":"Badkulla",
    "wof:placetype":"locality",
    "wof:population":15788
},
  "geometry": {"coordinates":[88.531105,23.301465],"type":"Point"}
}