{
  "type": "Feature",
  "properties": {
    "iso:country":"IN",
    "ks:ks_alt_nam":"MILL KA WEST",
    "ks:ks_name":"Mill Ka West",
    "ks:ks_pop":408,
    "ks:ks_type":"HABITATION",
    "ks:ks_uagg_main":0,
    "name:eng_x_preferred":[
        "Mill Ka West"
    ],
    "wof:name":"Mill Ka West",
    "wof:placetype":"neighbourhood",
    "wof:population":408
},
  "geometry": {"coordinates":[84.662036,26.336863],"type":"Point"}
}