{
  "type": "Feature",
  "properties": {
    "gn:admin1_code":"12.0",
    "gn:admin2_code":"001",
    "gn:asciiname":"Nagar Malpur",
    "gn:country_code":"IN",
    "gn:dem":1610,
    "gn:feature_class":"P",
    "gn:feature_code":"PPL",
    "gn:name":"Nagar Malpur",
    "gn:population":0,
    "gn:timezone":"Asia/Kolkata",
    "iso:country":"IN",
    "wof:name":"Nagar Malpur",
    "wof:placetype":"locality"
},
  "geometry": {"coordinates":[74.26928000000002,34.4741],"type":"Point"}
}