{
  "type": "Feature",
  "properties": {
    "iso:country":"IN",
    "ks:ks_name":"Diguvathurakapalle",
    "ks:ks_pop":67,
    "ks:ks_type":"HABITATION",
    "ks:ks_uagg_main":0,
    "name:eng_x_preferred":[
        "Diguvathurakapalle"
    ],
    "wof:name":"Diguvathurakapalle",
    "wof:placetype":"neighbourhood",
    "wof:population":67
},
  "geometry": {"coordinates":[78.73464800000001,14.425603],"type":"Point"}
}