{
  "type": "Feature",
  "properties": {
    "gn:admin1_code":"37.0",
    "gn:admin2_code":"417.0",
    "gn:asciiname":"Korlapalli",
    "gn:country_code":"IN",
    "gn:dem":305,
    "gn:feature_class":"P",
    "gn:feature_code":"PPL",
    "gn:name":"Korl\u0101palli",
    "gn:population":0,
    "gn:timezone":"Asia/Kolkata",
    "iso:country":"IN",
    "ks:ks_alt_nam":"Korl\u0101palli",
    "ks:ks_name":"Korlapalli",
    "ks:ks_type":"VILLAGE",
    "name:eng_x_preferred":[
        "Korlapalli"
    ],
    "name:eng_x_variant":[
        "Korl\u0101palli"
    ],
    "wof:name":"Korlapalli",
    "wof:placetype":"locality"
},
  "geometry": {"coordinates":[80.66290600000001,18.992696],"type":"Point"}
}