{
  "type": "Feature",
  "properties": {
    "gn:admin1_code":"21.0",
    "gn:admin2_code":"395.0",
    "gn:asciiname":"Maligaon",
    "gn:country_code":"IN",
    "gn:dem":691,
    "gn:feature_class":"P",
    "gn:feature_code":"PPL",
    "gn:name":"Maligaon",
    "gn:population":0,
    "gn:timezone":"Asia/Kolkata",
    "iso:country":"IN",
    "wof:name":"Maligaon",
    "wof:placetype":"locality"
},
  "geometry": {"coordinates":[82.90578000000002,19.29856],"type":"Point"}
}