{
  "type": "Feature",
  "properties": {
    "iso:country":"IN",
    "ks:ks_alt_nam":"SURYAWANSHIWASTI",
    "ks:ks_name":"Suryawanshiwasti",
    "ks:ks_pop":33,
    "ks:ks_type":"HABITATION",
    "name:eng_x_preferred":[
        "Suryawanshiwasti"
    ],
    "wof:name":"Suryawanshiwasti",
    "wof:placetype":"locality",
    "wof:population":33
},
  "geometry": {"coordinates":[74.950867,17.097418],"type":"Point"}
}