{
  "type": "Feature",
  "properties": {
    "iso:country":"IN",
    "ks:ks_name":"Kilthampalem",
    "ks:ks_pop":17,
    "ks:ks_type":"HABITATION",
    "name:eng_x_preferred":[
        "Kilthampalem"
    ],
    "wof:name":"Kilthampalem",
    "wof:placetype":"locality",
    "wof:population":17
},
  "geometry": {"coordinates":[83.15749,18.157343],"type":"Point"}
}