{
  "type": "Feature",
  "properties": {
    "iso:country":"IN",
    "ks:ks_name":"Chintalapalem",
    "ks:ks_pop":291,
    "ks:ks_type":"HABITATION",
    "ks:ks_uagg_main":0,
    "name:eng_x_preferred":[
        "Chintalapalem"
    ],
    "wof:name":"Chintalapalem",
    "wof:placetype":"neighbourhood",
    "wof:population":291
},
  "geometry": {"coordinates":[80.778265,16.267717],"type":"Point"}
}