{
  "type": "Feature",
  "properties": {
    "iso:country":"IN",
    "ks:ks_name":"Aunajuli Dafalapota",
    "ks:ks_pop":133,
    "ks:ks_type":"HABITATION",
    "ks:ks_uagg_main":0,
    "name:eng_x_preferred":[
        "Aunajuli Dafalapota"
    ],
    "wof:name":"Aunajuli Dafalapota",
    "wof:placetype":"neighbourhood",
    "wof:population":133
},
  "geometry": {"coordinates":[92.293036,26.745004],"type":"Point"}
}