{
  "type": "Feature",
  "properties": {
    "gn:admin1_code":"35",
    "gn:admin2_code":"459.0",
    "gn:asciiname":"Richha",
    "gn:country_code":"IN",
    "gn:dem":402,
    "gn:feature_class":"P",
    "gn:feature_code":"PPL",
    "gn:name":"Richha",
    "gn:population":0,
    "gn:timezone":"Asia/Kolkata",
    "iso:country":"IN",
    "name:bpy_x_preferred":[
        "\u09b0\u09bf\u099b\u09be"
    ],
    "name:ceb_x_preferred":[
        "Richha"
    ],
    "name:ita_x_preferred":[
        "Richha"
    ],
    "name:mlg_x_preferred":[
        "Richha"
    ],
    "name:msa_x_preferred":[
        "Richha"
    ],
    "name:nld_x_preferred":[
        "Richha"
    ],
    "name:pol_x_preferred":[
        "Richha"
    ],
    "name:por_x_preferred":[
        "Richha"
    ],
    "name:spa_x_preferred":[
        "Richha"
    ],
    "name:urd_x_preferred":[
        "\u0631\u06cc\u0686\u06be\u0627"
    ],
    "name:vie_x_preferred":[
        "Richha"
    ],
    "wof:name":"Richha",
    "wof:placetype":"locality"
},
  "geometry": {"coordinates":[78.14827,24.45499],"type":"Point"}
}