{
  "type": "Feature",
  "properties": {
    "iso:country":"IN",
    "ks:ks_alt_nam":"TAWADEWADI",
    "ks:ks_name":"Tawadewadi",
    "ks:ks_pop":45,
    "ks:ks_type":"HABITATION",
    "name:eng_x_preferred":[
        "Tawadewadi"
    ],
    "wof:name":"Tawadewadi",
    "wof:placetype":"locality",
    "wof:population":45
},
  "geometry": {"coordinates":[73.68482400000001,16.719814],"type":"Point"}
}