{
  "type": "Feature",
  "properties": {
    "iso:country":"IN",
    "ks:ks_name":"Kurupuzha",
    "ks:ks_pop":1010,
    "ks:ks_type":"VILLAGE",
    "name:eng_x_preferred":[
        "Kurupuzha"
    ],
    "wof:name":"Kurupuzha",
    "wof:placetype":"locality",
    "wof:population":1010
},
  "geometry": {"coordinates":[77.026737,8.65948],"type":"Point"}
}