{
  "type": "Feature",
  "properties": {
    "iso:country":"IN",
    "ks:ks_name":"Depot",
    "ks:ks_pop":1208,
    "ks:ks_type":"HABITATION",
    "name:eng_x_preferred":[
        "Depot"
    ],
    "wof:name":"Depot",
    "wof:placetype":"locality",
    "wof:population":1208
},
  "geometry": {"coordinates":[76.965855,29.705764],"type":"Point"}
}