{
  "type": "Feature",
  "properties": {
    "iso:country":"IN",
    "ks:ks_alt_nam":"BANGHATI",
    "ks:ks_name":"Banghati",
    "ks:ks_pop":1401,
    "ks:ks_type":"HABITATION",
    "name:eng_x_preferred":[
        "Banghati"
    ],
    "wof:name":"Banghati",
    "wof:placetype":"locality",
    "wof:population":1401
},
  "geometry": {"coordinates":[74.742746,23.797593],"type":"Point"}
}