{
  "type": "Feature",
  "properties": {
    "iso:country":"IN",
    "ks:ks_name":"Barajibanpur",
    "ks:ks_pop":272,
    "ks:ks_type":"HABITATION",
    "name:eng_x_preferred":[
        "Barajibanpur"
    ],
    "wof:name":"Barajibanpur",
    "wof:placetype":"locality",
    "wof:population":272
},
  "geometry": {"coordinates":[86.959411,22.550987],"type":"Point"}
}