{
  "type": "Feature",
  "properties": {
    "gn:admin1_code":"23",
    "gn:admin2_code":"38.0",
    "gn:asciiname":"Alaman",
    "gn:country_code":"IN",
    "gn:dem":240,
    "gn:feature_class":"P",
    "gn:feature_code":"PPL",
    "gn:name":"Al\u0101m\u0101n",
    "gn:population":0,
    "gn:timezone":"Asia/Kolkata",
    "iso:country":"IN",
    "ks:ks_name":"Alman",
    "ks:ks_pop":865,
    "ks:ks_type":"VILLAGE",
    "name:ara_x_preferred":[
        "\u0627\u0644\u0627\u0645\u0627\u0646"
    ],
    "name:ceb_x_preferred":[
        "Al\u0101man"
    ],
    "name:eng_x_preferred":[
        "Alman"
    ],
    "name:eng_x_variant":[
        "Alaman"
    ],
    "name:fas_x_preferred":[
        "\u0627\u0644\u0627\u0645\u0646"
    ],
    "name:msa_x_preferred":[
        "Alaman"
    ],
    "name:swe_x_preferred":[
        "Al\u0101man"
    ],
    "wof:name":"Alman",
    "wof:placetype":"locality",
    "wof:population":865
},
  "geometry": {"coordinates":[75.54722599999999,31.871705],"type":"Point"}
}