{
  "type": "Feature",
  "properties": {
    "iso:country":"IN",
    "ks:ks_alt_nam":"Kinh\u0101la",
    "ks:ks_name":"Kinhala",
    "ks:ks_type":"VILLAGE",
    "name:eng_x_preferred":[
        "Kinhala"
    ],
    "name:eng_x_variant":[
        "Kinh\u0101la"
    ],
    "wof:name":"Kinhala",
    "wof:placetype":"locality"
},
  "geometry": {"coordinates":[79.150109,20.712944],"type":"Point"}
}