{
  "type": "Feature",
  "properties": {
    "iso:country":"IN",
    "ks:ks_alt_nam":"Ch\u0101kund\u0101p\u0101l",
    "ks:ks_name":"Chakundapal",
    "ks:ks_type":"VILLAGE",
    "name:eng_x_preferred":[
        "Chakundapal"
    ],
    "name:eng_x_variant":[
        "Ch\u0101kund\u0101p\u0101l"
    ],
    "wof:name":"Chakundapal",
    "wof:placetype":"locality"
},
  "geometry": {"coordinates":[84.903254,20.997876],"type":"Point"}
}