{
  "type": "Feature",
  "properties": {
    "gn:admin1_code":"25.0",
    "gn:admin2_code":"607.0",
    "gn:asciiname":"Pasar",
    "gn:country_code":"IN",
    "gn:dem":33,
    "gn:feature_class":"P",
    "gn:feature_code":"PPL",
    "gn:name":"Pas\u0101r",
    "gn:population":0,
    "gn:timezone":"Asia/Kolkata",
    "iso:country":"IN",
    "name:ceb_x_preferred":[
        "P\u0101s\u0101r"
    ],
    "name:fas_x_preferred":[
        "\u067e\u0627\u0633\u0627\u0631"
    ],
    "wof:name":"Pasar",
    "wof:placetype":"locality"
},
  "geometry": {"coordinates":[79.77623,12.27008],"type":"Point"}
}