{
  "type": "Feature",
  "properties": {
    "iso:country":"IN",
    "ks:ks_name":"Kirwai Purwa",
    "ks:ks_pop":64,
    "ks:ks_type":"HABITATION",
    "name:eng_x_preferred":[
        "Kirwai Purwa"
    ],
    "wof:name":"Kirwai Purwa",
    "wof:placetype":"locality",
    "wof:population":64
},
  "geometry": {"coordinates":[81.915549,27.733217],"type":"Point"}
}