{
  "type": "Feature",
  "properties": {
    "gn:admin1_code":"23.0",
    "gn:admin2_code":"51.0",
    "gn:asciiname":"Kotla",
    "gn:country_code":"IN",
    "gn:dem":284,
    "gn:feature_class":"P",
    "gn:feature_code":"PPL",
    "gn:name":"Kotla",
    "gn:population":0,
    "gn:timezone":"Asia/Kolkata",
    "iso:country":"IN",
    "wof:name":"Kotla",
    "wof:placetype":"locality"
},
  "geometry": {"coordinates":[76.4987,30.82679000000001],"type":"Point"}
}