{
  "type": "Feature",
  "properties": {
    "iso:country":"IN",
    "ks:ks_name":"Jhupulia",
    "ks:ks_pop":0,
    "ks:ks_type":"VILLAGE",
    "name:eng_x_preferred":[
        "Jhupulia"
    ],
    "wof:name":"Jhupulia",
    "wof:placetype":"locality",
    "wof:population":0
},
  "geometry": {"coordinates":[87.010194,23.628491],"type":"Point"}
}