{
  "type": "Feature",
  "properties": {
    "iso:country":"IN",
    "ks:ks_name":"Pancho",
    "ks:ks_pop":3731,
    "ks:ks_type":"VILLAGE",
    "name:eng_x_preferred":[
        "Pancho"
    ],
    "wof:name":"Pancho",
    "wof:placetype":"locality",
    "wof:population":3731
},
  "geometry": {"coordinates":[77.111598,26.157228],"type":"Point"}
}