{
  "type": "Feature",
  "properties": {
    "gn:admin1_code":"34.0",
    "gn:admin2_code":"216.0",
    "gn:asciiname":"Itha Rasulnagar",
    "gn:country_code":"IN",
    "gn:dem":57,
    "gn:feature_class":"P",
    "gn:feature_code":"PPL",
    "gn:name":"Itha Ras\u016blnagar",
    "gn:population":0,
    "gn:timezone":"Asia/Kolkata",
    "iso:country":"IN",
    "ks:ks_alt_nam":"Itha Ras\u016blnagar",
    "ks:ks_name":"Itha Rasulnagar",
    "ks:ks_pop":4539,
    "ks:ks_type":"VILLAGE",
    "name:eng_x_preferred":[
        "Itha Rasulnagar"
    ],
    "name:eng_x_variant":[
        "Itha Ras\u016blnagar"
    ],
    "wof:name":"Itha Rasulnagar",
    "wof:placetype":"locality",
    "wof:population":4539
},
  "geometry": {"coordinates":[85.60115500000001,25.978712],"type":"Point"}
}