{
  "type": "Feature",
  "properties": {
    "iso:country":"IN",
    "ks:ks_name":"Pilliputtu",
    "ks:ks_pop":99,
    "ks:ks_type":"HABITATION",
    "name:eng_x_preferred":[
        "Pilliputtu"
    ],
    "wof:name":"Pilliputtu",
    "wof:placetype":"locality",
    "wof:population":99
},
  "geometry": {"coordinates":[82.600677,18.110726],"type":"Point"}
}