{
  "type": "Feature",
  "properties": {
    "gn:admin1_code":"35",
    "gn:admin2_code":"457.0",
    "gn:asciiname":"Thema",
    "gn:country_code":"IN",
    "gn:dem":317,
    "gn:feature_class":"P",
    "gn:feature_code":"PPL",
    "gn:name":"Thema",
    "gn:population":0,
    "gn:timezone":"Asia/Kolkata",
    "iso:country":"IN",
    "name:als_x_preferred":[
        "Thema"
    ],
    "name:deu_x_preferred":[
        "Thema"
    ],
    "name:ell_x_preferred":[
        "\u0398\u03ad\u03bc\u03b1"
    ],
    "name:fry_x_preferred":[
        "Tema"
    ],
    "name:ita_x_preferred":[
        "Thema"
    ],
    "name:jpn_x_preferred":[
        "\u30c6\u30fc\u30de"
    ],
    "name:nld_x_preferred":[
        "Thema"
    ],
    "wof:name":"Thema",
    "wof:placetype":"locality"
},
  "geometry": {"coordinates":[80.53889000000002,21.38793],"type":"Point"}
}