{
  "type": "Feature",
  "properties": {
    "iso:country":"IN",
    "ks:ks_name":"Khakhri Khara No.1",
    "ks:ks_pop":2,
    "ks:ks_type":"HABITATION",
    "name:eng_x_preferred":[
        "Khakhri Khara No.1"
    ],
    "wof:name":"Khakhri Khara No.1",
    "wof:placetype":"locality",
    "wof:population":2
},
  "geometry": {"coordinates":[74.613703,24.061633],"type":"Point"}
}