{
  "type": "Feature",
  "properties": {
    "iso:country":"IN",
    "ks:ks_name":"Panch Gere",
    "ks:ks_pop":265,
    "ks:ks_type":"VILLAGE",
    "name:eng_x_preferred":[
        "Panch Gere"
    ],
    "wof:name":"Panch Gere",
    "wof:placetype":"locality",
    "wof:population":265
},
  "geometry": {"coordinates":[87.60128899999999,22.34229],"type":"Point"}
}