{
  "type": "Feature",
  "properties": {
    "iso:country":"IN",
    "ks:ks_name":"Tase",
    "ks:ks_pop":491,
    "ks:ks_type":"HABITATION",
    "name:eng_x_preferred":[
        "Tase"
    ],
    "wof:name":"Tase",
    "wof:placetype":"locality",
    "wof:population":491
},
  "geometry": {"coordinates":[84.419414,27.244155],"type":"Point"}
}