{
  "type": "Feature",
  "properties": {
    "iso:country":"IN",
    "ks:ks_alt_nam":"HARIJAN TOLA",
    "ks:ks_name":"Harijan Tola",
    "ks:ks_pop":162,
    "ks:ks_type":"HABITATION",
    "ks:ks_uagg_main":0,
    "name:eng_x_preferred":[
        "Harijan Tola"
    ],
    "wof:name":"Harijan Tola",
    "wof:placetype":"neighbourhood",
    "wof:population":162
},
  "geometry": {"coordinates":[83.34472599999999,25.026573],"type":"Point"}
}