{
  "type": "Feature",
  "properties": {
    "iso:country":"IN",
    "ks:ks_alt_nam":"Gala falia",
    "ks:ks_name":"Gala Falia",
    "ks:ks_pop":374,
    "ks:ks_type":"HABITATION",
    "name:eng_x_preferred":[
        "Gala Falia"
    ],
    "wof:name":"Gala Falia",
    "wof:placetype":"locality",
    "wof:population":374
},
  "geometry": {"coordinates":[74.302583,22.758944],"type":"Point"}
}