{
  "type": "Feature",
  "properties": {
    "gn:admin1_code":"37",
    "gn:admin2_code":"412.0",
    "gn:asciiname":"Mujgahan",
    "gn:country_code":"IN",
    "gn:dem":324,
    "gn:feature_class":"P",
    "gn:feature_code":"PPL",
    "gn:name":"Mujgahan",
    "gn:population":0,
    "gn:timezone":"Asia/Kolkata",
    "iso:country":"IN",
    "ks:ks_name":"Mujgahan",
    "ks:ks_pop":3178,
    "ks:ks_type":"VILLAGE",
    "ks:ks_uagg_main":0,
    "name:eng_x_preferred":[
        "Mujgahan"
    ],
    "wof:name":"Mujgahan",
    "wof:placetype":"locality",
    "wof:population":3178
},
  "geometry": {"coordinates":[81.51957400000001,20.724236],"type":"Point"}
}