{
  "type": "Feature",
  "properties": {
    "iso:country":"IN",
    "ks:ks_name":"Katalachakond",
    "ks:ks_pop":120,
    "ks:ks_type":"HABITATION",
    "name:eng_x_preferred":[
        "Katalachakond"
    ],
    "wof:name":"Katalachakond",
    "wof:placetype":"locality",
    "wof:population":120
},
  "geometry": {"coordinates":[73.35891700000001,18.158726],"type":"Point"}
}