{
  "type": "Feature",
  "properties": {
    "gn:admin1_code":"12.0",
    "gn:admin2_code":"18.0",
    "gn:asciiname":"Waithane",
    "gn:country_code":"IN",
    "gn:dem":1782,
    "gn:feature_class":"P",
    "gn:feature_code":"PPL",
    "gn:name":"Waith\u0101n\u0113",
    "gn:population":0,
    "gn:timezone":"Asia/Kolkata",
    "iso:country":"IN",
    "wof:name":"Waithane",
    "wof:placetype":"locality"
},
  "geometry": {"coordinates":[75.68686,33.40517],"type":"Point"}
}