{
  "type": "Feature",
  "properties": {
    "iso:country":"IN",
    "ks:ks_name":"Khalachiwadi",
    "ks:ks_pop":101,
    "ks:ks_type":"HABITATION",
    "name:eng_x_preferred":[
        "Khalachiwadi"
    ],
    "wof:name":"Khalachiwadi",
    "wof:placetype":"locality",
    "wof:population":101
},
  "geometry": {"coordinates":[73.924092,16.05108],"type":"Point"}
}