{
  "type": "Feature",
  "properties": {
    "iso:country":"IN",
    "ks:ks_name":"Vaderhalli",
    "ks:ks_type":"VILLAGE",
    "name:eng_x_preferred":[
        "Vaderhalli"
    ],
    "wof:name":"Vaderhalli",
    "wof:placetype":"locality"
},
  "geometry": {"coordinates":[75.859983,14.55547],"type":"Point"}
}