{
  "type": "Feature",
  "properties": {
    "iso:country":"IN",
    "ks:ks_name":"Patelpara",
    "ks:ks_pop":90,
    "ks:ks_type":"HABITATION",
    "name:eng_x_preferred":[
        "Patelpara"
    ],
    "wof:name":"Patelpara",
    "wof:placetype":"locality",
    "wof:population":90
},
  "geometry": {"coordinates":[81.795615,19.746322],"type":"Point"}
}