{
  "type": "Feature",
  "properties": {
    "iso:country":"IN",
    "ks:ks_name":"Tola Malaipur",
    "ks:ks_pop":87,
    "ks:ks_type":"VILLAGE",
    "name:eng_x_preferred":[
        "Tola Malaipur"
    ],
    "wof:name":"Tola Malaipur",
    "wof:placetype":"locality",
    "wof:population":87
},
  "geometry": {"coordinates":[87.853388,24.712203],"type":"Point"}
}