{
  "type": "Feature",
  "properties": {
    "iso:country":"IN",
    "ks:ks_name":"Kanhayni Talli",
    "ks:ks_pop":48,
    "ks:ks_type":"VILLAGE",
    "name:eng_x_preferred":[
        "Kanhayni Talli"
    ],
    "wof:name":"Kanhayni Talli",
    "wof:placetype":"locality",
    "wof:population":48
},
  "geometry": {"coordinates":[79.176008,29.834475],"type":"Point"}
}