{
  "type": "Feature",
  "properties": {
    "gn:admin1_code":"9.0",
    "gn:admin2_code":"468.0",
    "gn:asciiname":"Naga Walaria",
    "gn:country_code":"IN",
    "gn:dem":18,
    "gn:feature_class":"P",
    "gn:feature_code":"PPL",
    "gn:name":"Naga Wal\u0101ria",
    "gn:population":0,
    "gn:timezone":"Asia/Kolkata",
    "iso:country":"IN",
    "wof:name":"Naga Walaria",
    "wof:placetype":"neighbourhood"
},
  "geometry": {"coordinates":[69.98723,22.93715],"type":"Point"}
}