{
  "type": "Feature",
  "properties": {
    "iso:country":"IN",
    "ks:ks_name":"Laxman Pur",
    "ks:ks_pop":109,
    "ks:ks_type":"HABITATION",
    "name:eng_x_preferred":[
        "Laxman Pur"
    ],
    "wof:name":"Laxman Pur",
    "wof:placetype":"locality",
    "wof:population":109
},
  "geometry": {"coordinates":[82.206712,26.465367],"type":"Point"}
}