{
  "type": "Feature",
  "properties": {
    "iso:country":"IN",
    "ks:ks_name":"Dimia Chhatarjan",
    "ks:ks_pop":932,
    "ks:ks_type":"HABITATION",
    "name:eng_x_preferred":[
        "Dimia Chhatarjan"
    ],
    "wof:name":"Dimia Chhatarjan",
    "wof:placetype":"locality",
    "wof:population":932
},
  "geometry": {"coordinates":[87.536888,25.692146],"type":"Point"}
}