{
  "type": "Feature",
  "properties": {
    "iso:country":"IN",
    "ks:ks_name":"Kukkavaripalem",
    "ks:ks_pop":609,
    "ks:ks_type":"HABITATION",
    "ks:ks_uagg_main":0,
    "name:eng_x_preferred":[
        "Kukkavaripalem"
    ],
    "wof:name":"Kukkavaripalem",
    "wof:placetype":"neighbourhood",
    "wof:population":609
},
  "geometry": {"coordinates":[80.44398200000001,15.89393],"type":"Point"}
}