{
  "type": "Feature",
  "properties": {
    "gn:admin1_code":"35",
    "gn:admin2_code":"459.0",
    "gn:asciiname":"Panauwa",
    "gn:country_code":"IN",
    "gn:dem":479,
    "gn:feature_class":"P",
    "gn:feature_code":"PPL",
    "gn:name":"Panauwa",
    "gn:population":0,
    "gn:timezone":"Asia/Kolkata",
    "iso:country":"IN",
    "wof:name":"Panauwa",
    "wof:placetype":"locality"
},
  "geometry": {"coordinates":[77.62966999999998,24.75818],"type":"Point"}
}