{
  "type": "Feature",
  "properties": {
    "gn:admin1_code":"35.0",
    "gn:admin2_code":"424",
    "gn:asciiname":"Sukwaha",
    "gn:country_code":"IN",
    "gn:dem":375,
    "gn:feature_class":"P",
    "gn:feature_code":"PPL",
    "gn:name":"Sukw\u0101ha",
    "gn:population":0,
    "gn:timezone":"Asia/Kolkata",
    "iso:country":"IN",
    "wof:name":"Sukwaha",
    "wof:placetype":"locality"
},
  "geometry": {"coordinates":[78.90254,24.63258],"type":"Point"}
}