{
  "type": "Feature",
  "properties": {
    "gn:admin1_code":"37",
    "gn:admin2_code":"404.0",
    "gn:asciiname":"Diluatendu",
    "gn:country_code":"IN",
    "gn:dem":325,
    "gn:feature_class":"P",
    "gn:feature_code":"PPL",
    "gn:name":"Dilu\u0101tend\u016b",
    "gn:population":0,
    "gn:timezone":"Asia/Kolkata",
    "iso:country":"IN",
    "wof:name":"Diluatendu",
    "wof:placetype":"locality"
},
  "geometry": {"coordinates":[82.81004,22.23368],"type":"Point"}
}