{
  "type": "Feature",
  "properties": {
    "gn:admin1_code":"19",
    "gn:admin2_code":"557.0",
    "gn:asciiname":"Jainapur",
    "gn:country_code":"IN",
    "gn:dem":532,
    "gn:feature_class":"P",
    "gn:feature_code":"PPL",
    "gn:name":"Jain\u0101pur",
    "gn:population":0,
    "gn:timezone":"Asia/Kolkata",
    "iso:country":"IN",
    "name:urd_x_preferred":[
        "\u062c\u06cc\u0646\u067e\u0631"
    ],
    "wof:name":"Jainapur",
    "wof:placetype":"locality"
},
  "geometry": {"coordinates":[76.28076999999998,16.29235],"type":"Point"}
}