{
  "type": "Feature",
  "properties": {
    "gn:admin1_code":"16",
    "gn:admin2_code":"505.0",
    "gn:asciiname":"Bahadur",
    "gn:country_code":"IN",
    "gn:dem":285,
    "gn:feature_class":"P",
    "gn:feature_code":"PPL",
    "gn:name":"Bah\u0101dur",
    "gn:population":0,
    "gn:timezone":"Asia/Kolkata",
    "iso:country":"IN",
    "name:aze_x_preferred":[
        "Bahadur"
    ],
    "name:hin_x_preferred":[
        "\u092c\u0939\u093e\u0926\u0941\u0930"
    ],
    "name:ita_x_preferred":[
        "Bahadur"
    ],
    "name:jpn_x_preferred":[
        "\u30d0\u30cf\u30fc\u30c9\u30a5\u30eb"
    ],
    "name:rus_x_preferred":[
        "\u0411\u0430\u0445\u0430\u0434\u0443\u0440"
    ],
    "name:uzb_x_preferred":[
        "Bahodir"
    ],
    "wof:name":"Bahadur",
    "wof:placetype":"locality"
},
  "geometry": {"coordinates":[79.16513,21.09854],"type":"Point"}
}