{
  "type": "Feature",
  "properties": {
    "iso:country":"IN",
    "name:eng_x_preferred":[
        "Adimali"
    ],
    "name:fas_x_preferred":[
        "\u0627\u062f\u06cc\u0645\u0627\u0644\u06cc"
    ],
    "name:mal_x_preferred":[
        "\u0d05\u0d1f\u0d3f\u0d2e\u0d3e\u0d32\u0d3f"
    ],
    "name:nld_x_preferred":[
        "Adimali"
    ],
    "name:tam_x_preferred":[
        "\u0b85\u0b9f\u0bbf\u0bae\u0bbe\u0bb2\u0bbf"
    ],
    "qs:name":"Adimali",
    "qs:name_adm0":"India",
    "qs:name_adm1":"Kerala",
    "qs:photos":33,
    "qs:photos_1k":7,
    "qs:photos_9k":1,
    "qs:photos_9r":2,
    "qs:photos_all":33,
    "qs:photos_sr":2,
    "qs:placetype":"Town",
    "qs:pop_sr":"0",
    "wd:wordcount":1052,
    "wof:name":"Adimali",
    "wof:placetype":"locality"
},
  "geometry": {"coordinates":[76.956138,10.01476],"type":"Point"}
}