{
  "type": "Feature",
  "properties": {
    "iso:country":"IN",
    "ks:ks_name":"Arwapur",
    "ks:ks_pop":1067,
    "ks:ks_type":"HABITATION",
    "name:eng_x_preferred":[
        "Arwapur"
    ],
    "wof:name":"Arwapur",
    "wof:placetype":"locality",
    "wof:population":1067
},
  "geometry": {"coordinates":[80.25117,27.490918],"type":"Point"}
}