{
  "type": "Feature",
  "properties": {
    "iso:country":"IN",
    "ks:ks_name":"Chhiri",
    "ks:ks_pop":10490,
    "ks:ks_type":"URBAN",
    "ks:ks_uagg_main":0,
    "name:eng_x_preferred":[
        "Chhiri"
    ],
    "wof:name":"Chhiri",
    "wof:placetype":"neighbourhood",
    "wof:population":10490
},
  "geometry": {"coordinates":[72.942808,20.371176],"type":"Point"}
}