{
  "type": "Feature",
  "properties": {
    "iso:country":"IN",
    "ks:ks_name":"Kumbharwadi",
    "ks:ks_pop":505,
    "ks:ks_type":"HABITATION",
    "name:eng_x_preferred":[
        "Kumbharwadi"
    ],
    "wof:name":"Kumbharwadi",
    "wof:placetype":"locality",
    "wof:population":505
},
  "geometry": {"coordinates":[73.51829499999999,17.483503],"type":"Point"}
}