{
  "type": "Feature",
  "properties": {
    "iso:country":"IN",
    "ks:ks_alt_nam":"GINABAHAR",
    "ks:ks_name":"Ginabahar",
    "ks:ks_pop":428,
    "ks:ks_type":"HABITATION",
    "name:eng_x_preferred":[
        "Ginabahar"
    ],
    "wof:name":"Ginabahar",
    "wof:placetype":"locality",
    "wof:population":428
},
  "geometry": {"coordinates":[83.940864,22.760785],"type":"Point"}
}