{
  "type": "Feature",
  "properties": {
    "gn:admin1_code":"24.0",
    "gn:admin2_code":"113.0",
    "gn:asciiname":"Sangaria",
    "gn:country_code":"IN",
    "gn:dem":202,
    "gn:feature_class":"P",
    "gn:feature_code":"PPL",
    "gn:name":"S\u0101ngaria",
    "gn:population":0,
    "gn:timezone":"Asia/Kolkata",
    "iso:country":"IN",
    "wof:name":"Sangaria",
    "wof:placetype":"neighbourhood"
},
  "geometry": {"coordinates":[73.02649,26.18872],"type":"Point"}
}