{
  "type": "Feature",
  "properties": {
    "iso:country":"IN",
    "ks:ks_name":"Khediyaboop",
    "ks:ks_pop":684,
    "ks:ks_type":"VILLAGE",
    "name:eng_x_preferred":[
        "Khediyaboop"
    ],
    "wof:name":"Khediyaboop",
    "wof:placetype":"locality",
    "wof:population":684
},
  "geometry": {"coordinates":[75.740515,23.996351],"type":"Point"}
}