{
  "type": "Feature",
  "properties": {
    "iso:country":"IN",
    "ks:ks_name":"Muchane",
    "ks:ks_pop":743,
    "ks:ks_type":"VILLAGE",
    "name:eng_x_preferred":[
        "Muchane"
    ],
    "wof:name":"Muchane",
    "wof:placetype":"locality",
    "wof:population":743
},
  "geometry": {"coordinates":[73.079576,18.351366],"type":"Point"}
}