{
  "type": "Feature",
  "properties": {
    "gn:admin1_code":"36",
    "gn:admin2_code":"163.0",
    "gn:asciiname":"Shivlal Ki Marhaiyan",
    "gn:country_code":"IN",
    "gn:dem":142,
    "gn:feature_class":"P",
    "gn:feature_code":"PPL",
    "gn:name":"Shivl\u0101l Ki Marhaiy\u0101n",
    "gn:population":0,
    "gn:timezone":"Asia/Kolkata",
    "iso:country":"IN",
    "wof:name":"Shivlal Ki Marhaiyan",
    "wof:placetype":"neighbourhood"
},
  "geometry": {"coordinates":[79.57832999999999,26.41749],"type":"Point"}
}