{
  "type": "Feature",
  "properties": {
    "iso:country":"IN",
    "ks:ks_name":"Jakedevi",
    "ks:ks_pop":34,
    "ks:ks_type":"HABITATION",
    "name:eng_x_preferred":[
        "Jakedevi"
    ],
    "wof:name":"Jakedevi",
    "wof:placetype":"locality",
    "wof:population":34
},
  "geometry": {"coordinates":[73.496775,16.940031],"type":"Point"}
}