{
  "type": "Feature",
  "properties": {
    "iso:country":"IN",
    "ks:ks_name":"Gadapasi",
    "ks:ks_pop":268,
    "ks:ks_type":"VILLAGE",
    "name:eng_x_preferred":[
        "Gadapasi"
    ],
    "wof:name":"Gadapasi",
    "wof:placetype":"locality",
    "wof:population":268
},
  "geometry": {"coordinates":[84.86477600000001,21.093299],"type":"Point"}
}