{
  "type": "Feature",
  "properties": {
    "iso:country":"IN",
    "ks:ks_name":"Dikruit Killing",
    "ks:ks_pop":126,
    "ks:ks_type":"HABITATION",
    "name:eng_x_preferred":[
        "Dikruit Killing"
    ],
    "wof:name":"Dikruit Killing",
    "wof:placetype":"locality",
    "wof:population":126
},
  "geometry": {"coordinates":[93.46821300000001,25.894101],"type":"Point"}
}