{
  "type": "Feature",
  "properties": {
    "gn:admin1_code":"36",
    "gn:admin2_code":"194.0",
    "gn:asciiname":"Salempur",
    "gn:country_code":"IN",
    "gn:dem":89,
    "gn:feature_class":"P",
    "gn:feature_code":"PPL",
    "gn:name":"Salempur",
    "gn:population":0,
    "gn:timezone":"Asia/Kolkata",
    "iso:country":"IN",
    "name:ceb_x_preferred":[
        "Salempur"
    ],
    "name:pol_x_preferred":[
        "Salempur"
    ],
    "name:swe_x_preferred":[
        "Salempur"
    ],
    "wof:name":"Salempur",
    "wof:placetype":"locality"
},
  "geometry": {"coordinates":[82.56253000000002,25.58672],"type":"Point"}
}