{
  "type": "Feature",
  "properties": {
    "gn:admin1_code":"36",
    "gn:admin2_code":"194.0",
    "gn:asciiname":"Salempur",
    "gn:country_code":"IN",
    "gn:dem":89,
    "gn:feature_class":"P",
    "gn:feature_code":"PPL",
    "gn:name":"Salempur",
    "gn:population":0,
    "gn:timezone":"Asia/Kolkata",
    "iso:country":"IN",
    "ks:ks_name":"Salampur",
    "ks:ks_pop":730,
    "ks:ks_type":"VILLAGE",
    "name:ceb_x_preferred":[
        "Salempur"
    ],
    "name:eng_x_preferred":[
        "Salampur"
    ],
    "name:eng_x_variant":[
        "Salempur"
    ],
    "name:pol_x_preferred":[
        "Salempur"
    ],
    "name:swe_x_preferred":[
        "Salempur"
    ],
    "wof:name":"Salampur",
    "wof:placetype":"locality",
    "wof:population":730
},
  "geometry": {"coordinates":[82.55977300000001,25.586874],"type":"Point"}
}