{
  "type": "Feature",
  "properties": {
    "iso:country":"IN",
    "ks:ks_alt_nam":"mudikkanam",
    "ks:ks_name":"Mudikkanam",
    "ks:ks_pop":2827,
    "ks:ks_type":"HABITATION",
    "name:eng_x_preferred":[
        "Mudikkanam"
    ],
    "wof:name":"Mudikkanam",
    "wof:placetype":"locality",
    "wof:population":2827
},
  "geometry": {"coordinates":[75.315776,12.087941],"type":"Point"}
}