{
  "type": "Feature",
  "properties": {
    "iso:country":"IN",
    "ks:ks_name":"Parm Nagar",
    "ks:ks_pop":584,
    "ks:ks_type":"HABITATION",
    "name:eng_x_preferred":[
        "Parm Nagar"
    ],
    "wof:name":"Parm Nagar",
    "wof:placetype":"locality",
    "wof:population":584
},
  "geometry": {"coordinates":[84.36304,27.283031],"type":"Point"}
}