{
  "type": "Feature",
  "properties": {
    "iso:country":"IN",
    "ks:ks_name":"Kahiyapur",
    "ks:ks_pop":824,
    "ks:ks_type":"HABITATION",
    "name:eng_x_preferred":[
        "Kahiyapur"
    ],
    "wof:name":"Kahiyapur",
    "wof:placetype":"locality",
    "wof:population":824
},
  "geometry": {"coordinates":[81.792337,27.58255],"type":"Point"}
}