{
  "type": "Feature",
  "properties": {
    "iso:country":"IN",
    "ks:ks_name":"Khadpewadi",
    "ks:ks_pop":307,
    "ks:ks_type":"HABITATION",
    "name:eng_x_preferred":[
        "Khadpewadi"
    ],
    "wof:name":"Khadpewadi",
    "wof:placetype":"locality",
    "wof:population":307
},
  "geometry": {"coordinates":[73.556562,15.948225],"type":"Point"}
}