{
  "type": "Feature",
  "properties": {
    "iso:country":"IN",
    "ks:ks_alt_nam":"JADHAV WASTI",
    "ks:ks_name":"Jadhav Wasti",
    "ks:ks_pop":468,
    "ks:ks_type":"HABITATION",
    "name:eng_x_preferred":[
        "Jadhav Wasti"
    ],
    "wof:name":"Jadhav Wasti",
    "wof:placetype":"locality",
    "wof:population":468
},
  "geometry": {"coordinates":[74.534543,19.800292],"type":"Point"}
}