{
  "type": "Feature",
  "properties": {
    "gn:admin1_code":"9",
    "gn:admin2_code":"485.0",
    "gn:asciiname":"Ambajharan",
    "gn:country_code":"IN",
    "gn:dem":233,
    "gn:feature_class":"P",
    "gn:feature_code":"PPL",
    "gn:name":"\u0100mb\u0101jharan",
    "gn:population":0,
    "gn:timezone":"Asia/Kolkata",
    "iso:country":"IN",
    "wof:name":"Ambajharan",
    "wof:placetype":"locality"
},
  "geometry": {"coordinates":[74.21947,23.17781],"type":"Point"}
}