{
  "type": "Feature",
  "properties": {
    "gn:admin1_code":"9",
    "gn:admin2_code":"485.0",
    "gn:asciiname":"Ambajharan",
    "gn:country_code":"IN",
    "gn:dem":233,
    "gn:feature_class":"P",
    "gn:feature_code":"PPL",
    "gn:name":"\u0100mb\u0101jharan",
    "gn:population":0,
    "gn:timezone":"Asia/Kolkata",
    "iso:country":"IN",
    "ks:ks_name":"Amba Jharan",
    "ks:ks_pop":414,
    "ks:ks_type":"VILLAGE",
    "name:eng_x_preferred":[
        "Amba Jharan"
    ],
    "name:eng_x_variant":[
        "Ambajharan"
    ],
    "wof:name":"Amba Jharan",
    "wof:placetype":"locality",
    "wof:population":414
},
  "geometry": {"coordinates":[74.22190999999999,23.178315],"type":"Point"}
}