{
  "type": "Feature",
  "properties": {
    "gn:admin1_code":"35.0",
    "gn:admin2_code":"446.0",
    "gn:asciiname":"Dholpur",
    "gn:country_code":"IN",
    "gn:dem":576,
    "gn:feature_class":"P",
    "gn:feature_code":"PPL",
    "gn:name":"Dholpur",
    "gn:population":0,
    "gn:timezone":"Asia/Kolkata",
    "iso:country":"IN",
    "name:ben_x_preferred":[
        "\u09a2\u09cb\u09b2\u09aa\u09c1\u09b0"
    ],
    "name:bih_x_preferred":[
        "\u0927\u094c\u0932\u092a\u0941\u0930"
    ],
    "name:bpy_x_preferred":[
        "\u09a7\u09cc\u09b2\u09aa\u09c1\u09b0"
    ],
    "name:cat_x_preferred":[
        "Dholpur"
    ],
    "name:ceb_x_preferred":[
        "Dhaulpur"
    ],
    "name:deu_x_preferred":[
        "Dholpur"
    ],
    "name:fra_x_preferred":[
        "Dholpur"
    ],
    "name:guj_x_preferred":[
        "\u0aa7\u0acb\u0ab2\u0aaa\u0ac1\u0ab0"
    ],
    "name:hin_x_preferred":[
        "\u0927\u094c\u0932\u092a\u0941\u0930"
    ],
    "name:ita_x_preferred":[
        "Dholpur"
    ],
    "name:jpn_x_preferred":[
        "\u30c9\u30fc\u30eb\u30d7\u30eb"
    ],
    "name:mal_x_preferred":[
        "\u0d27\u0d4b\u0d7d\u0d2a\u0d42\u0d7c"
    ],
    "name:mar_x_preferred":[
        "\u0927\u094b\u0932\u092a\u0942\u0930"
    ],
    "name:mlg_x_preferred":[
        "Dholpur"
    ],
    "name:msa_x_preferred":[
        "Dholpur"
    ],
    "name:new_x_preferred":[
        "\u0927\u094c\u0932\u092a\u0941\u0930"
    ],
    "name:rus_x_preferred":[
        "\u0414\u0445\u043e\u043b\u043f\u0443\u0440"
    ],
    "name:san_x_preferred":[
        "\u0927\u094c\u0932\u092a\u0941\u0930\u092e\u094d"
    ],
    "name:swe_x_preferred":[
        "Dhaulpur"
    ],
    "name:tam_x_preferred":[
        "\u0ba4\u0bcb\u0bb2\u0bcd\u0baa\u0bc2\u0bb0\u0bcd"
    ],
    "name:urd_x_preferred":[
        "\u062f\u06be\u0648\u0644 \u067e\u0648\u0631"
    ],
    "name:vie_x_preferred":[
        "Dhaulpur"
    ],
    "name:xmf_x_preferred":[
        "\u10d3\u10f0\u10dd\u10da\u10de\u10e3\u10e0\u10d8"
    ],
    "name:zho_x_preferred":[
        "\u9053\u5c14\u666e\u5c14"
    ],
    "wof:name":"Dholpur",
    "wof:placetype":"locality"
},
  "geometry": {"coordinates":[78.40821,23.37298],"type":"Point"}
}