{
  "type": "Feature",
  "properties": {
    "iso:country":"IN",
    "ks:ks_name":"Nandaha",
    "ks:ks_pop":284,
    "ks:ks_type":"VILLAGE",
    "ks:ks_uagg_main":0,
    "name:eng_x_preferred":[
        "Nandaha"
    ],
    "wof:name":"Nandaha",
    "wof:placetype":"neighbourhood",
    "wof:population":284
},
  "geometry": {"coordinates":[86.651264,23.553659],"type":"Point"}
}