{
  "type": "Feature",
  "properties": {
    "gn:admin1_code":"40.0",
    "gn:admin2_code":"533.0",
    "gn:asciiname":"Nagapuram",
    "gn:country_code":"IN",
    "gn:dem":351,
    "gn:feature_class":"P",
    "gn:feature_code":"PPL",
    "gn:name":"N\u0101g\u0101puram",
    "gn:population":0,
    "gn:timezone":"Asia/Kolkata",
    "iso:country":"IN",
    "wof:name":"Nagapuram",
    "wof:placetype":"locality"
},
  "geometry": {"coordinates":[78.32724,18.89879],"type":"Point"}
}