{
  "type": "Feature",
  "properties": {
    "iso:country":"IN",
    "ks:ks_name":"Mudkheda Karsena",
    "ks:ks_pop":425,
    "ks:ks_type":"VILLAGE",
    "name:eng_x_preferred":[
        "Mudkheda Karsena"
    ],
    "wof:name":"Mudkheda Karsena",
    "wof:placetype":"locality",
    "wof:population":425
},
  "geometry": {"coordinates":[77.742548,25.843037],"type":"Point"}
}