{
  "type": "Feature",
  "properties": {
    "iso:country":"IN",
    "ks:ks_name":"Labadewasti",
    "ks:ks_pop":116,
    "ks:ks_type":"HABITATION",
    "name:eng_x_preferred":[
        "Labadewasti"
    ],
    "wof:name":"Labadewasti",
    "wof:placetype":"locality",
    "wof:population":116
},
  "geometry": {"coordinates":[75.121076,18.245228],"type":"Point"}
}