{
  "type": "Feature",
  "properties": {
    "iso:country":"IN",
    "ks:ks_name":"Lakadbandi",
    "ks:ks_pop":332,
    "ks:ks_type":"VILLAGE",
    "name:eng_x_preferred":[
        "Lakadbandi"
    ],
    "wof:name":"Lakadbandi",
    "wof:placetype":"locality",
    "wof:population":332
},
  "geometry": {"coordinates":[78.327854,22.135929],"type":"Point"}
}