{
  "type": "Feature",
  "properties": {
    "iso:country":"IN",
    "ks:ks_name":"Lengarkhole",
    "ks:ks_pop":105,
    "ks:ks_type":"VILLAGE",
    "name:eng_x_preferred":[
        "Lengarkhole"
    ],
    "wof:name":"Lengarkhole",
    "wof:placetype":"locality",
    "wof:population":105
},
  "geometry": {"coordinates":[84.273584,20.306979],"type":"Point"}
}