{
  "type": "Feature",
  "properties": {
    "iso:country":"IN",
    "ks:ks_name":"Borbhadri",
    "ks:ks_pop":516,
    "ks:ks_type":"HABITATION",
    "name:eng_x_preferred":[
        "Borbhadri"
    ],
    "wof:name":"Borbhadri",
    "wof:placetype":"locality",
    "wof:population":516
},
  "geometry": {"coordinates":[92.289512,24.862284],"type":"Point"}
}