{
  "type": "Feature",
  "properties": {
    "iso:country":"IN",
    "ks:ks_name":"Rampur Chack",
    "ks:ks_pop":31,
    "ks:ks_type":"HABITATION",
    "name:eng_x_preferred":[
        "Rampur Chack"
    ],
    "wof:name":"Rampur Chack",
    "wof:placetype":"locality",
    "wof:population":31
},
  "geometry": {"coordinates":[77.97938499999999,23.619437],"type":"Point"}
}