{
  "type": "Feature",
  "properties": {
    "gn:admin1_code":"2.0",
    "gn:admin2_code":"554",
    "gn:asciiname":"Kalakada",
    "gn:country_code":"IN",
    "gn:dem":447,
    "gn:feature_class":"P",
    "gn:feature_code":"PPL",
    "gn:name":"Kalakada",
    "gn:population":0,
    "gn:timezone":"Asia/Kolkata",
    "iso:country":"IN",
    "name:new_x_preferred":[
        "\u0915\u0932\u0915\u0921 \u092e\u0923\u094d\u0921\u0932"
    ],
    "name:pam_x_preferred":[
        "Kalakada"
    ],
    "name:tam_x_preferred":[
        "\u0b95\u0bb2\u0b95\u0b9f\u0bbe"
    ],
    "name:tel_x_preferred":[
        "\u0c15\u0c32\u0c15\u0c21"
    ],
    "name:tgl_x_preferred":[
        "Kalakada"
    ],
    "name:urd_x_preferred":[
        "\u06a9\u0644\u06a9\u0691\u0627"
    ],
    "name:vie_x_preferred":[
        "Kalakada"
    ],
    "wof:name":"Kalakada",
    "wof:placetype":"locality"
},
  "geometry": {"coordinates":[78.78931,13.827],"type":"Point"}
}