{
  "type": "Feature",
  "properties": {
    "gn:admin1_code":"28.0",
    "gn:admin2_code":"338",
    "gn:asciiname":"Ayan",
    "gn:country_code":"IN",
    "gn:dem":9,
    "gn:feature_class":"P",
    "gn:feature_code":"PPL",
    "gn:name":"\u0100y\u0101n",
    "gn:population":0,
    "gn:timezone":"Asia/Kolkata",
    "iso:country":"IN",
    "name:aze_x_preferred":[
        "Ayan"
    ],
    "name:ben_x_preferred":[
        "\u0986\u09df\u09be\u09a8"
    ],
    "name:ceb_x_preferred":[
        "Ayan"
    ],
    "name:deu_x_preferred":[
        "Ayan"
    ],
    "name:ell_x_preferred":[
        "\u0391\u03ca\u03ac\u03bd"
    ],
    "name:fas_x_preferred":[
        "\u0622\u06cc\u0627\u0646"
    ],
    "name:heb_x_preferred":[
        "\u05d0\u05d9\u05d9\u05d0\u05df"
    ],
    "name:hin_x_preferred":[
        "\u0905\u092f\u093e\u0928"
    ],
    "name:ind_x_preferred":[
        "Ayan"
    ],
    "name:ita_x_preferred":[
        "Ayan"
    ],
    "name:kor_x_preferred":[
        "\uc544\uc580"
    ],
    "name:pol_x_preferred":[
        "Ayan"
    ],
    "name:rus_x_preferred":[
        "\u0410\u044f\u043d"
    ],
    "name:swe_x_preferred":[
        "Ayan"
    ],
    "name:tur_x_preferred":[
        "Ayan"
    ],
    "name:ukr_x_preferred":[
        "\u0410\u044f\u043d"
    ],
    "name:urd_x_preferred":[
        "\u0622\u06cc\u0627\u0646"
    ],
    "name:vie_x_preferred":[
        "Ayan"
    ],
    "wof:name":"Ayan",
    "wof:placetype":"locality"
},
  "geometry": {"coordinates":[88.14194000000001,22.72639],"type":"Point"}
}