{
  "type": "Feature",
  "properties": {
    "gn:admin1_code":"28.0",
    "gn:admin2_code":"338",
    "gn:asciiname":"Ayan",
    "gn:country_code":"IN",
    "gn:dem":9,
    "gn:feature_class":"P",
    "gn:feature_code":"PPL",
    "gn:name":"\u0100y\u0101n",
    "gn:population":0,
    "gn:timezone":"Asia/Kolkata",
    "iso:country":"IN",
    "name:aze_x_preferred":[
        "Ayan"
    ],
    "name:ceb_x_preferred":[
        "Ayan"
    ],
    "name:deu_x_preferred":[
        "Ayan"
    ],
    "name:rus_x_preferred":[
        "\u0410\u044f\u043d"
    ],
    "name:swe_x_preferred":[
        "Ayan"
    ],
    "name:ukr_x_preferred":[
        "\u0410\u044f\u043d"
    ],
    "wof:name":"Ayan",
    "wof:placetype":"locality"
},
  "geometry": {"coordinates":[88.14194000000001,22.72639],"type":"Point"}
}