{
  "type": "Feature",
  "properties": {
    "gn:admin1_code":"36.0",
    "gn:admin2_code":"183.0",
    "gn:asciiname":"Purwa Jamadar",
    "gn:country_code":"IN",
    "gn:dem":104,
    "gn:feature_class":"P",
    "gn:feature_code":"PPL",
    "gn:name":"Purwa Jam\u0101d\u0101r",
    "gn:population":0,
    "gn:timezone":"Asia/Kolkata",
    "iso:country":"IN",
    "wof:name":"Purwa Jamadar",
    "wof:placetype":"neighbourhood"
},
  "geometry": {"coordinates":[81.84113000000001,26.94713],"type":"Point"}
}