{
  "type": "Feature",
  "properties": {
    "iso:country":"IN",
    "ks:ks_alt_nam":"Dakhin digheli",
    "ks:ks_name":"Dakhin Digheli",
    "ks:ks_pop":378,
    "ks:ks_type":"HABITATION",
    "name:eng_x_preferred":[
        "Dakhin Digheli"
    ],
    "wof:name":"Dakhin Digheli",
    "wof:placetype":"locality",
    "wof:population":378
},
  "geometry": {"coordinates":[91.311468,26.493013],"type":"Point"}
}