{
  "type": "Feature",
  "properties": {
    "gn:admin1_code":"36.0",
    "gn:admin2_code":"154.0",
    "gn:asciiname":"Kasauli",
    "gn:country_code":"IN",
    "gn:dem":139,
    "gn:feature_class":"P",
    "gn:feature_code":"PPL",
    "gn:name":"Kasauli",
    "gn:population":0,
    "gn:timezone":"Asia/Kolkata",
    "iso:country":"IN",
    "name:ben_x_preferred":[
        "\u0995\u09b8\u09cc\u09b2\u09c0"
    ],
    "name:bpy_x_preferred":[
        "\u0995\u09be\u09b8\u09be\u0989\u09b2\u09bf"
    ],
    "name:ceb_x_preferred":[
        "Kasauli"
    ],
    "name:fra_x_preferred":[
        "Kasauli"
    ],
    "name:hin_x_preferred":[
        "\u0915\u0938\u094c\u0932\u0940"
    ],
    "name:ita_x_preferred":[
        "Kasauli"
    ],
    "name:mal_x_preferred":[
        "\u0d15\u0d38\u0d4b\u0d33\u0d3f"
    ],
    "name:msa_x_preferred":[
        "Kasauli"
    ],
    "name:nep_x_preferred":[
        "\u0915\u0938\u094c\u0932\u0940"
    ],
    "name:new_x_preferred":[
        "\u0915\u0938\u094c\u0932\u0940"
    ],
    "name:nld_x_preferred":[
        "Kasauli"
    ],
    "name:ori_x_preferred":[
        "\u0b15\u0b38\u0b4c\u0b32\u0b3f"
    ],
    "name:pan_x_preferred":[
        "\u0a15\u0a38\u0a4c\u0a32\u0a40"
    ],
    "name:pol_x_preferred":[
        "Kasauli"
    ],
    "name:swe_x_preferred":[
        "Kasauli"
    ],
    "name:tam_x_preferred":[
        "\u0b95\u0b9a\u0bcc\u0bb2\u0bbf"
    ],
    "name:urd_x_preferred":[
        "\u06a9\u0633\u0648\u0644\u06cc"
    ],
    "name:vie_x_preferred":[
        "Kasauli"
    ],
    "name:zho_x_preferred":[
        "\u5361\u7ecd\u5229"
    ],
    "wof:name":"Kasauli",
    "wof:placetype":"locality"
},
  "geometry": {"coordinates":[80.67106,27.34411],"type":"Point"}
}