{
  "type": "Feature",
  "properties": {
    "gn:admin1_code":"23",
    "gn:admin2_code":"37.0",
    "gn:asciiname":"Aliwal",
    "gn:country_code":"IN",
    "gn:dem":218,
    "gn:feature_class":"P",
    "gn:feature_code":"PPL",
    "gn:name":"Al\u012bw\u0101l",
    "gn:population":0,
    "gn:timezone":"Asia/Kolkata",
    "iso:country":"IN",
    "ks:ks_alt_nam":"Al\u012bw\u0101l",
    "ks:ks_name":"Aliwal",
    "ks:ks_type":"VILLAGE",
    "name:eng_x_preferred":[
        "Aliwal"
    ],
    "name:eng_x_variant":[
        "Al\u012bw\u0101l"
    ],
    "wof:name":"Aliwal",
    "wof:placetype":"locality"
},
  "geometry": {"coordinates":[75.269293,31.138823],"type":"Point"}
}