{
  "type": "Feature",
  "properties": {
    "iso:country":"IN",
    "ks:ks_name":"Moroshi",
    "ks:ks_pop":150,
    "ks:ks_type":"VILLAGE",
    "name:eng_x_preferred":[
        "Moroshi"
    ],
    "wof:name":"Moroshi",
    "wof:placetype":"locality",
    "wof:population":150
},
  "geometry": {"coordinates":[73.690482,19.34348],"type":"Point"}
}