{
  "type": "Feature",
  "properties": {
    "iso:country":"IN",
    "ks:ks_alt_nam":"Jakhal\u0101b\u0101ndha",
    "ks:ks_name":"Jakhalabandha",
    "ks:ks_type":"VILLAGE",
    "ks:ks_uagg_main":0,
    "name:eng_x_preferred":[
        "Jakhalabandha"
    ],
    "name:eng_x_variant":[
        "Jakhal\u0101b\u0101ndha"
    ],
    "wof:name":"Jakhalabandha",
    "wof:placetype":"neighbourhood"
},
  "geometry": {"coordinates":[92.970044,26.585548],"type":"Point"}
}