{
  "type": "Feature",
  "properties": {
    "iso:country":"IN",
    "ks:ks_name":"Labana Plot",
    "ks:ks_pop":243,
    "ks:ks_type":"HABITATION",
    "name:eng_x_preferred":[
        "Labana Plot"
    ],
    "wof:name":"Labana Plot",
    "wof:placetype":"locality",
    "wof:population":243
},
  "geometry": {"coordinates":[76.419094,30.187727],"type":"Point"}
}