{
  "type": "Feature",
  "properties": {
    "gn:admin1_code":"2.0",
    "gn:admin2_code":"550.0",
    "gn:asciiname":"Balasamudram",
    "gn:country_code":"IN",
    "gn:dem":76,
    "gn:feature_class":"P",
    "gn:feature_code":"PPL",
    "gn:name":"B\u0101lasamudram",
    "gn:population":0,
    "gn:timezone":"Asia/Kolkata",
    "iso:country":"IN",
    "ks:ks_alt_nam":"B\u0101lasamudram",
    "ks:ks_name":"Balasamudram",
    "ks:ks_pop":286,
    "ks:ks_type":"VILLAGE",
    "name:bpy_x_preferred":[
        "\u09ac\u09be\u09b2\u09b8\u09ae\u09c1\u09a6\u09cd\u09b0\u09ae"
    ],
    "name:eng_x_preferred":[
        "Balasamudram"
    ],
    "name:eng_x_variant":[
        "B\u0101lasamudram"
    ],
    "name:ita_x_preferred":[
        "Balasamudram"
    ],
    "name:msa_x_preferred":[
        "Balasamudram"
    ],
    "name:new_x_preferred":[
        "\u092c\u0932\u0938\u092e\u0941\u0926\u094d\u0930\u093e\u092e"
    ],
    "name:nld_x_preferred":[
        "Balasamudram"
    ],
    "name:por_x_preferred":[
        "Balasamudram"
    ],
    "name:tam_x_preferred":[
        "\u0baa\u0bbe\u0bb2\u0b9a\u0bae\u0bc1\u0ba4\u0bcd\u0ba4\u0bbf\u0bb0\u0bae\u0bcd"
    ],
    "name:vie_x_preferred":[
        "Balasamudram"
    ],
    "name:zho_x_preferred":[
        "\u5df4\u62c9\u8428\u7a46\u5fb7\u62c9\u59c6"
    ],
    "wof:name":"Balasamudram",
    "wof:placetype":"locality",
    "wof:population":286
},
  "geometry": {"coordinates":[79.557017,13.990503],"type":"Point"}
}