{
  "type": "Feature",
  "properties": {
    "iso:country":"IN",
    "ks:ks_name":"Tokiguda",
    "ks:ks_pop":17,
    "ks:ks_type":"HABITATION",
    "name:eng_x_preferred":[
        "Tokiguda"
    ],
    "wof:name":"Tokiguda",
    "wof:placetype":"locality",
    "wof:population":17
},
  "geometry": {"coordinates":[79.10363,19.3246],"type":"Point"}
}