{
  "type": "Feature",
  "properties": {
    "gn:admin1_code":"39.0",
    "gn:admin2_code":"66.0",
    "gn:asciiname":"Padampur",
    "gn:country_code":"IN",
    "gn:dem":333,
    "gn:feature_class":"P",
    "gn:feature_code":"PPL",
    "gn:name":"Padampur",
    "gn:population":0,
    "gn:timezone":"Asia/Kolkata",
    "iso:country":"IN",
    "name:ceb_x_preferred":[
        "Padampur"
    ],
    "name:swe_x_preferred":[
        "Padampur"
    ],
    "wof:name":"Padampur",
    "wof:placetype":"locality"
},
  "geometry": {"coordinates":[79.60064,29.15823],"type":"Point"}
}