{
  "type": "Feature",
  "properties": {
    "iso:country":"IN",
    "ks:ks_name":"Bhariyas",
    "ks:ks_pop":85,
    "ks:ks_type":"HABITATION",
    "name:eng_x_preferred":[
        "Bhariyas"
    ],
    "wof:name":"Bhariyas",
    "wof:placetype":"locality",
    "wof:population":85
},
  "geometry": {"coordinates":[80.15027000000001,29.218683],"type":"Point"}
}