{
  "type": "Feature",
  "properties": {
    "gn:admin1_code":"19",
    "gn:admin2_code":"559.0",
    "gn:asciiname":"Nawalkal",
    "gn:country_code":"IN",
    "gn:dem":435,
    "gn:feature_class":"P",
    "gn:feature_code":"PPL",
    "gn:name":"Nawalkal",
    "gn:population":0,
    "gn:timezone":"Asia/Kolkata",
    "iso:country":"IN",
    "name:und_x_variant":[
        "N\u0101walkal"
    ],
    "wof:name":"Nawalkal",
    "wof:placetype":"locality"
},
  "geometry": {"coordinates":[76.96873000000002,16.16393],"type":"Point"}
}