{
  "type": "Feature",
  "properties": {
    "iso:country":"IN",
    "ks:ks_alt_nam":"1 SAD",
    "ks:ks_name":"1 Sad",
    "ks:ks_pop":8,
    "ks:ks_type":"HABITATION",
    "name:eng_x_preferred":[
        "1 Sad"
    ],
    "wof:name":"1 Sad",
    "wof:placetype":"locality",
    "wof:population":8
},
  "geometry": {"coordinates":[73.60333300000001,29.381944],"type":"Point"}
}