{
  "type": "Feature",
  "properties": {
    "gn:admin1_code":"16",
    "gn:admin2_code":"531.0",
    "gn:asciiname":"Marabgi",
    "gn:country_code":"IN",
    "gn:dem":526,
    "gn:feature_class":"P",
    "gn:feature_code":"PPL",
    "gn:name":"Marabgi",
    "gn:population":0,
    "gn:timezone":"Asia/Kolkata",
    "iso:country":"IN",
    "name:und_x_variant":[
        "Morabgi",
        "Marabgi"
    ],
    "wof:name":"Marabgi",
    "wof:placetype":"locality"
},
  "geometry": {"coordinates":[75.60816,17.09437],"type":"Point"}
}