{
  "type": "Feature",
  "properties": {
    "iso:country":"IN",
    "name:cat_x_preferred":[
        "Por"
    ],
    "name:ceb_x_preferred":[
        "Por"
    ],
    "name:eng_x_preferred":[
        "Por"
    ],
    "name:fin_x_preferred":[
        "Por"
    ],
    "name:frr_x_preferred":[
        "Por"
    ],
    "name:glg_x_preferred":[
        "Por"
    ],
    "name:hun_x_preferred":[
        "Por"
    ],
    "name:hye_x_preferred":[
        "\u0553\u0578\u057c"
    ],
    "name:ita_x_preferred":[
        "Por"
    ],
    "name:kur_x_preferred":[
        "Por"
    ],
    "name:ltz_x_preferred":[
        "Por"
    ],
    "name:nld_x_preferred":[
        "Por"
    ],
    "name:pol_x_preferred":[
        "Por"
    ],
    "name:rus_x_preferred":[
        "\u041f\u043e\u0440"
    ],
    "name:slv_x_preferred":[
        "Por"
    ],
    "name:spa_x_preferred":[
        "Por"
    ],
    "name:swe_x_preferred":[
        "Por"
    ],
    "name:ukr_x_preferred":[
        "\u041f\u043e\u0440"
    ],
    "qs:name":"Por",
    "qs:name_adm0":"India",
    "qs:name_adm1":"Gujarat",
    "qs:photos":4,
    "qs:photos_1k":1,
    "qs:photos_9k":1,
    "qs:photos_9r":1,
    "qs:photos_all":4,
    "qs:photos_sr":1,
    "qs:placetype":"Town",
    "qs:pop_sr":"0",
    "wd:wordcount":156,
    "wof:name":"Por",
    "wof:placetype":"locality"
},
  "geometry": {"coordinates":[73.18288699999999,22.1430325],"type":"Point"}
}