{
  "type": "Feature",
  "properties": {
    "iso:country":"IN",
    "ks:ks_name":"Barbocha",
    "ks:ks_pop":309,
    "ks:ks_type":"VILLAGE",
    "ks:ks_uagg_main":0,
    "name:eng_x_preferred":[
        "Barbocha"
    ],
    "wof:name":"Barbocha",
    "wof:placetype":"locality",
    "wof:population":309
},
  "geometry": {"coordinates":[94.113986,27.269374],"type":"Point"}
}