{
  "type": "Feature",
  "properties": {
    "gn:admin1_code":"39.0",
    "gn:admin2_code":"66.0",
    "gn:asciiname":"Gajojali Dakhhan",
    "gn:country_code":"IN",
    "gn:dem":379,
    "gn:feature_class":"P",
    "gn:feature_code":"PPL",
    "gn:name":"Gajoj\u0101li Dakhhan",
    "gn:population":0,
    "gn:timezone":"Asia/Kolkata",
    "iso:country":"IN",
    "wof:name":"Gajojali Dakhhan",
    "wof:placetype":"locality"
},
  "geometry": {"coordinates":[79.52986999999997,29.17357],"type":"Point"}
}