{
  "type": "Feature",
  "properties": {
    "iso:country":"IN",
    "ks:ks_alt_nam":"TANGERPANI",
    "ks:ks_name":"Tangerpani",
    "ks:ks_pop":286,
    "ks:ks_type":"HABITATION",
    "name:eng_x_preferred":[
        "Tangerpani"
    ],
    "wof:name":"Tangerpani",
    "wof:placetype":"locality",
    "wof:population":286
},
  "geometry": {"coordinates":[83.659353,22.487677],"type":"Point"}
}