{
  "type": "Feature",
  "properties": {
    "gn:admin1_code":"36",
    "gn:admin2_code":"175.0",
    "gn:asciiname":"Chakia",
    "gn:country_code":"IN",
    "gn:dem":95,
    "gn:feature_class":"P",
    "gn:feature_code":"PPL",
    "gn:name":"Chakia",
    "gn:population":0,
    "gn:timezone":"Asia/Kolkata",
    "iso:country":"IN",
    "name:ben_x_preferred":[
        "\u099a\u09be\u0995\u09bf\u09af\u09bc\u09be"
    ],
    "name:bpy_x_preferred":[
        "\u099a\u09be\u0995\u09bf\u09af\u09bc\u09be"
    ],
    "name:ceb_x_preferred":[
        "Chakia"
    ],
    "name:new_x_preferred":[
        "\u091a\u0915\u093f\u092f\u093e"
    ],
    "name:nld_x_preferred":[
        "Chakia"
    ],
    "name:pol_x_preferred":[
        "Chakia"
    ],
    "name:swe_x_preferred":[
        "Chakia"
    ],
    "wof:name":"Chakia",
    "wof:placetype":"neighbourhood"
},
  "geometry": {"coordinates":[82.27486,25.47406],"type":"Point"}
}