{
  "type": "Feature",
  "properties": {
    "iso:country":"IN",
    "ks:ks_name":"Nattani",
    "ks:ks_pop":251,
    "ks:ks_type":"HABITATION",
    "name:eng_x_preferred":[
        "Nattani"
    ],
    "wof:name":"Nattani",
    "wof:placetype":"locality",
    "wof:population":251
},
  "geometry": {"coordinates":[79.427713,10.532763],"type":"Point"}
}