{
  "type": "Feature",
  "properties": {
    "iso:country":"IN",
    "ks:ks_alt_nam":"ADAKEWASTI",
    "ks:ks_name":"Adakewasti",
    "ks:ks_pop":125,
    "ks:ks_type":"HABITATION",
    "name:eng_x_preferred":[
        "Adakewasti"
    ],
    "wof:name":"Adakewasti",
    "wof:placetype":"locality",
    "wof:population":125
},
  "geometry": {"coordinates":[74.722382,17.049102],"type":"Point"}
}