{
  "type": "Feature",
  "properties": {
    "iso:country":"IN",
    "ks:ks_name":"Hari Nagar Pt II",
    "ks:ks_pop":1124,
    "ks:ks_type":"VILLAGE",
    "ks:ks_uagg_main":0,
    "name:eng_x_preferred":[
        "Hari Nagar Pt II"
    ],
    "wof:name":"Hari Nagar Pt II",
    "wof:placetype":"neighbourhood",
    "wof:population":1124
},
  "geometry": {"coordinates":[92.50296899999999,24.884364],"type":"Point"}
}