{
  "type": "Feature",
  "properties": {
    "iso:country":"IN",
    "ks:ks_alt_nam":"Bar\u0101padar",
    "ks:ks_name":"Barapadar",
    "ks:ks_type":"VILLAGE",
    "name:eng_x_preferred":[
        "Barapadar"
    ],
    "name:eng_x_variant":[
        "Bar\u0101padar"
    ],
    "wof:name":"Barapadar",
    "wof:placetype":"locality"
},
  "geometry": {"coordinates":[84.216081,20.623688],"type":"Point"}
}