{
  "type": "Feature",
  "properties": {
    "iso:country":"IN",
    "ks:ks_name":"Dilawarpur",
    "ks:ks_pop":2747,
    "ks:ks_type":"VILLAGE",
    "ks:ks_uagg_main":0,
    "name:eng_x_preferred":[
        "Dilawarpur"
    ],
    "wof:name":"Dilawarpur",
    "wof:placetype":"neighbourhood",
    "wof:population":2747
},
  "geometry": {"coordinates":[85.97581599999999,26.027976],"type":"Point"}
}