{
  "type": "Feature",
  "properties": {
    "gn:admin1_code":"36",
    "gn:admin2_code":"134.0",
    "gn:asciiname":"Abdulpur",
    "gn:country_code":"IN",
    "gn:dem":253,
    "gn:feature_class":"P",
    "gn:feature_code":"PPL",
    "gn:name":"Abdulpur",
    "gn:population":0,
    "gn:timezone":"Asia/Kolkata",
    "iso:country":"IN",
    "name:und_x_variant":[
        "Shekhpur N\u0101w\u0101b\u0101d"
    ],
    "wof:name":"Abdulpur",
    "wof:placetype":"locality"
},
  "geometry": {"coordinates":[78.43316999999998,29.5079],"type":"Point"}
}