{
  "type": "Feature",
  "properties": {
    "iso:country":"IN",
    "ks:ks_name":"Chalunebar",
    "ks:ks_pop":0,
    "ks:ks_type":"VILLAGE",
    "name:eng_x_preferred":[
        "Chalunebar"
    ],
    "wof:name":"Chalunebar",
    "wof:placetype":"locality",
    "wof:population":0
},
  "geometry": {"coordinates":[87.265792,23.824387],"type":"Point"}
}