{
  "type": "Feature",
  "properties": {
    "iso:country":"IN",
    "ks:ks_name":"Hanga",
    "ks:ks_pop":3800,
    "ks:ks_type":"VILLAGE",
    "name:eng_x_preferred":[
        "Hanga"
    ],
    "wof:name":"Hanga",
    "wof:placetype":"neighbourhood",
    "wof:population":3800
},
  "geometry": {"coordinates":[74.51664599999999,18.961614],"type":"Point"}
}