{
  "type": "Feature",
  "properties": {
    "gn:admin1_code":"35",
    "gn:admin2_code":"420.0",
    "gn:asciiname":"Aimanpura",
    "gn:country_code":"IN",
    "gn:dem":164,
    "gn:feature_class":"P",
    "gn:feature_code":"PPL",
    "gn:name":"Aimanpura",
    "gn:population":0,
    "gn:timezone":"Asia/Kolkata",
    "iso:country":"IN",
    "ks:ks_name":"Amanpura",
    "ks:ks_pop":260,
    "ks:ks_type":"VILLAGE",
    "name:eng_x_preferred":[
        "Amanpura"
    ],
    "name:eng_x_variant":[
        "Aimanpura"
    ],
    "wof:name":"Amanpura",
    "wof:placetype":"locality",
    "wof:population":260
},
  "geometry": {"coordinates":[78.27855700000001,26.541882],"type":"Point"}
}