{
  "type": "Feature",
  "properties": {
    "iso:country":"IN",
    "ks:ks_alt_nam":"Hasapur panchalinga",
    "ks:ks_name":"Hasapur Panchalinga",
    "ks:ks_pop":32,
    "ks:ks_type":"HABITATION",
    "name:eng_x_preferred":[
        "Hasapur Panchalinga"
    ],
    "wof:name":"Hasapur Panchalinga",
    "wof:placetype":"locality",
    "wof:population":32
},
  "geometry": {"coordinates":[74.81429199999999,14.755611],"type":"Point"}
}