{
  "type": "Feature",
  "properties": {
    "iso:country":"IN",
    "ks:ks_name":"Tharu Ekwad",
    "ks:ks_pop":373,
    "ks:ks_type":"HABITATION",
    "name:eng_x_preferred":[
        "Tharu Ekwad"
    ],
    "wof:name":"Tharu Ekwad",
    "wof:placetype":"locality",
    "wof:population":373
},
  "geometry": {"coordinates":[84.576165,27.287552],"type":"Point"}
}