{
  "type": "Feature",
  "properties": {
    "iso:country":"IN",
    "ks:ks_name":"Barha Khurd",
    "ks:ks_pop":91,
    "ks:ks_type":"VILLAGE",
    "ks:ks_uagg_main":0,
    "name:eng_x_preferred":[
        "Barha Khurd"
    ],
    "wof:name":"Barha Khurd",
    "wof:placetype":"neighbourhood",
    "wof:population":91
},
  "geometry": {"coordinates":[78.435317,23.151469],"type":"Point"}
}