{
  "type": "Feature",
  "properties": {
    "gn:admin1_code":"25.0",
    "gn:admin2_code":"611.0",
    "gn:asciiname":"Maditerai",
    "gn:country_code":"IN",
    "gn:dem":2149,
    "gn:feature_class":"P",
    "gn:feature_code":"PPL",
    "gn:name":"Maditerai",
    "gn:population":0,
    "gn:timezone":"Asia/Kolkata",
    "iso:country":"IN",
    "wof:name":"Maditerai",
    "wof:placetype":"locality"
},
  "geometry": {"coordinates":[76.77181999999998,11.41147],"type":"Point"}
}