{
  "type": "Feature",
  "properties": {
    "iso:country":"IN",
    "ks:ks_name":"Upalewadi",
    "ks:ks_pop":58,
    "ks:ks_type":"HABITATION",
    "name:eng_x_preferred":[
        "Upalewadi"
    ],
    "wof:name":"Upalewadi",
    "wof:placetype":"locality",
    "wof:population":58
},
  "geometry": {"coordinates":[73.80947500000001,16.64173],"type":"Point"}
}