{
  "type": "Feature",
  "properties": {
    "iso:country":"IN",
    "ks:ks_name":"Rampur Chauthar",
    "ks:ks_pop":1128,
    "ks:ks_type":"HABITATION",
    "name:eng_x_preferred":[
        "Rampur Chauthar"
    ],
    "wof:name":"Rampur Chauthar",
    "wof:placetype":"locality",
    "wof:population":1128
},
  "geometry": {"coordinates":[82.44705999999999,25.344334],"type":"Point"}
}