{
  "type": "Feature",
  "properties": {
    "iso:country":"IN",
    "ks:ks_name":"Hemmane",
    "ks:ks_pop":30,
    "ks:ks_type":"HABITATION",
    "name:eng_x_preferred":[
        "Hemmane"
    ],
    "wof:name":"Hemmane",
    "wof:placetype":"locality",
    "wof:population":30
},
  "geometry": {"coordinates":[75.247056,13.405346],"type":"Point"}
}