{
  "type": "Feature",
  "properties": {
    "iso:country":"IN",
    "ks:ks_alt_nam":"Etape wasti",
    "ks:ks_name":"Etape Wasti",
    "ks:ks_pop":38,
    "ks:ks_type":"HABITATION",
    "name:eng_x_preferred":[
        "Etape Wasti"
    ],
    "wof:name":"Etape Wasti",
    "wof:placetype":"locality",
    "wof:population":38
},
  "geometry": {"coordinates":[75.95049,18.724767],"type":"Point"}
}