{
  "type": "Feature",
  "properties": {
    "gn:admin1_code":"39.0",
    "gn:admin2_code":"60.0",
    "gn:asciiname":"Chunhau",
    "gn:country_code":"IN",
    "gn:dem":1126,
    "gn:feature_class":"P",
    "gn:feature_code":"PPL",
    "gn:name":"Chunhau",
    "gn:population":0,
    "gn:timezone":"Asia/Kolkata",
    "iso:country":"IN",
    "ks:ks_name":"Chunhau",
    "ks:ks_type":"VILLAGE",
    "name:eng_x_preferred":[
        "Chunhau"
    ],
    "wof:name":"Chunhau",
    "wof:placetype":"locality"
},
  "geometry": {"coordinates":[77.95011700000001,30.528048],"type":"Point"}
}