{
  "type": "Feature",
  "properties": {
    "gn:admin1_code":"23.0",
    "gn:admin2_code":"45.0",
    "gn:asciiname":"Ramgarh",
    "gn:country_code":"IN",
    "gn:dem":211,
    "gn:feature_class":"P",
    "gn:feature_code":"PPL",
    "gn:name":"R\u0101mgarh",
    "gn:population":0,
    "gn:timezone":"Asia/Kolkata",
    "iso:country":"IN",
    "name:cat_x_preferred":[
        "Ramgarh"
    ],
    "name:ceb_x_preferred":[
        "Ramgarh"
    ],
    "name:deu_x_preferred":[
        "Ramgarh"
    ],
    "name:ita_x_preferred":[
        "Ramgarh"
    ],
    "name:pol_x_preferred":[
        "Ramgarh"
    ],
    "name:rus_x_preferred":[
        "\u0420\u0430\u043c\u0433\u0430\u0440\u0445"
    ],
    "name:swe_x_preferred":[
        "Ramgarh"
    ],
    "name:und_x_variant":[
        "R\u0101mgarh",
        "Bhagtu\u0101na"
    ],
    "wof:name":"Ramgarh",
    "wof:placetype":"locality"
},
  "geometry": {"coordinates":[74.86328,30.41776],"type":"Point"}
}