{
  "type": "Feature",
  "properties": {
    "iso:country":"IN",
    "ks:ks_name":"Poduchenu",
    "ks:ks_pop":234,
    "ks:ks_type":"HABITATION",
    "name:eng_x_preferred":[
        "Poduchenu"
    ],
    "wof:name":"Poduchenu",
    "wof:placetype":"locality",
    "wof:population":234
},
  "geometry": {"coordinates":[78.388814,12.823512],"type":"Point"}
}