{
  "type": "Feature",
  "properties": {
    "iso:country":"IN",
    "ks:ks_name":"Aunlaput",
    "ks:ks_pop":26,
    "ks:ks_type":"HABITATION",
    "name:eng_x_preferred":[
        "Aunlaput"
    ],
    "wof:name":"Aunlaput",
    "wof:placetype":"locality",
    "wof:population":26
},
  "geometry": {"coordinates":[82.46641099999999,18.585124],"type":"Point"}
}