{
  "type": "Feature",
  "properties": {
    "iso:country":"IN",
    "ks:ks_alt_nam":"Mukanaik tanda",
    "ks:ks_name":"Mukanaik Tanda",
    "ks:ks_pop":63,
    "ks:ks_type":"HABITATION",
    "name:eng_x_preferred":[
        "Mukanaik Tanda"
    ],
    "wof:name":"Mukanaik Tanda",
    "wof:placetype":"locality",
    "wof:population":63
},
  "geometry": {"coordinates":[76.909549,16.298281],"type":"Point"}
}