{
  "type": "Feature",
  "properties": {
    "iso:country":"IN",
    "ks:ks_name":"Sansari",
    "ks:ks_pop":152,
    "ks:ks_type":"VILLAGE",
    "name:eng_x_preferred":[
        "Sansari"
    ],
    "wof:name":"Sansari",
    "wof:placetype":"locality",
    "wof:population":152
},
  "geometry": {"coordinates":[79.087833,30.514001],"type":"Point"}
}