{
  "type": "Feature",
  "properties": {
    "iso:country":"IN",
    "ks:ks_alt_nam":"SHAMRAO PATIL VASTI",
    "ks:ks_name":"Shamrao Patil Vasti",
    "ks:ks_pop":98,
    "ks:ks_type":"HABITATION",
    "name:eng_x_preferred":[
        "Shamrao Patil Vasti"
    ],
    "wof:name":"Shamrao Patil Vasti",
    "wof:placetype":"locality",
    "wof:population":98
},
  "geometry": {"coordinates":[74.67805,16.893585],"type":"Point"}
}