{
  "type": "Feature",
  "properties": {
    "iso:country":"IN",
    "ks:ks_name":"Sobari",
    "ks:ks_pop":640,
    "ks:ks_type":"HABITATION",
    "name:eng_x_preferred":[
        "Sobari"
    ],
    "wof:name":"Sobari",
    "wof:placetype":"locality",
    "wof:population":640
},
  "geometry": {"coordinates":[82.32992900000001,25.362682],"type":"Point"}
}