{
  "type": "Feature",
  "properties": {
    "iso:country":"IN",
    "ks:ks_name":"Kethuabad",
    "ks:ks_pop":0,
    "ks:ks_type":"VILLAGE",
    "name:eng_x_preferred":[
        "Kethuabad"
    ],
    "wof:name":"Kethuabad",
    "wof:placetype":"locality",
    "wof:population":0
},
  "geometry": {"coordinates":[87.14363,22.849492],"type":"Point"}
}