{
  "type": "Feature",
  "properties": {
    "iso:country":"IN",
    "ks:ks_name":"Biradisahi",
    "ks:ks_pop":222,
    "ks:ks_type":"VILLAGE",
    "name:eng_x_preferred":[
        "Biradisahi"
    ],
    "wof:name":"Biradisahi",
    "wof:placetype":"locality",
    "wof:population":222
},
  "geometry": {"coordinates":[85.054681,20.119005],"type":"Point"}
}