{
  "type": "Feature",
  "properties": {
    "iso:country":"IN",
    "ks:ks_alt_nam":"Padariya ryt",
    "ks:ks_name":"Padariya Ryt",
    "ks:ks_pop":206,
    "ks:ks_type":"HABITATION",
    "name:eng_x_preferred":[
        "Padariya Ryt"
    ],
    "wof:name":"Padariya Ryt",
    "wof:placetype":"locality",
    "wof:population":206
},
  "geometry": {"coordinates":[81.005787,22.836425],"type":"Point"}
}