{
  "type": "Feature",
  "properties": {
    "gn:admin1_code":"36",
    "gn:admin2_code":"173.0",
    "gn:asciiname":"Bhawanigarh",
    "gn:country_code":"IN",
    "gn:dem":99,
    "gn:feature_class":"P",
    "gn:feature_code":"PPL",
    "gn:name":"Bhawan\u012bgarh",
    "gn:population":0,
    "gn:timezone":"Asia/Kolkata",
    "iso:country":"IN",
    "name:ben_x_preferred":[
        "\u09ad\u0993\u09af\u09bc\u09be\u09a8\u09bf\u0997\u09a1\u09bc"
    ],
    "name:bpy_x_preferred":[
        "\u09ad\u09f1\u09be\u09a8\u09bf\u0997\u09a1\u09bc"
    ],
    "name:ceb_x_preferred":[
        "Bhaw\u0101n\u012bgarh"
    ],
    "name:ita_x_preferred":[
        "Bhawanigarh"
    ],
    "name:msa_x_preferred":[
        "Bhawanigarh"
    ],
    "name:new_x_preferred":[
        "\u092d\u0935\u093e\u0928\u0940\u0917\u0922"
    ],
    "name:nld_x_preferred":[
        "Bhawanigarh"
    ],
    "name:pan_x_preferred":[
        "\u0a2d\u0a35\u0a3e\u0a28\u0a40\u0a17\u0a5c\u0a4d\u0a39"
    ],
    "name:por_x_preferred":[
        "Bhawanigarh"
    ],
    "name:swe_x_preferred":[
        "Bhaw\u0101n\u012bgarh"
    ],
    "name:vie_x_preferred":[
        "Bhawanigarh"
    ],
    "name:zho_x_preferred":[
        "\u5df4\u74e6\u5c3c\u52a0\u5c14"
    ],
    "wof:name":"Bhawanigarh",
    "wof:placetype":"locality"
},
  "geometry": {"coordinates":[81.72955,25.8746],"type":"Point"}
}