{
  "type": "Feature",
  "properties": {
    "iso:country":"IN",
    "ks:ks_name":"Patalwas",
    "ks:ks_pop":1358,
    "ks:ks_type":"VILLAGE",
    "name:eng_x_preferred":[
        "Patalwas"
    ],
    "wof:name":"Patalwas",
    "wof:placetype":"locality",
    "wof:population":1358
},
  "geometry": {"coordinates":[76.146547,27.089719],"type":"Point"}
}