{
  "type": "Feature",
  "properties": {
    "iso:country":"IN",
    "ks:ks_name":"Khudoli",
    "ks:ks_pop":114,
    "ks:ks_type":"VILLAGE",
    "name:eng_x_preferred":[
        "Khudoli"
    ],
    "wof:name":"Khudoli",
    "wof:placetype":"locality",
    "wof:population":114
},
  "geometry": {"coordinates":[79.49229699999999,29.553014],"type":"Point"}
}