{
  "type": "Feature",
  "properties": {
    "iso:country":"IN",
    "name:eng_x_preferred":[
        "Tolichowki"
    ],
    "name:unk_x_variant":[
        "Tolichowki"
    ],
    "qs:gn_adm0_cc":"IN",
    "qs:gn_local":1269843,
    "qs:local_max":1198,
    "qs:local_sum":10545,
    "qs:localhoods":56,
    "qs:name":"Tolichowki",
    "qs:name_adm0":"India",
    "qs:name_adm1":"Andhra Pradesh",
    "qs:name_adm2":"Hyderabad",
    "qs:name_local":"Hyderabad",
    "qs:photo_max":9,
    "qs:photo_sum":19,
    "qs:placetype":"Suburb",
    "qs:quad_count":5,
    "qs:woe_adm0":23424848,
    "qs:woe_adm1":2345740,
    "qs:woe_adm2":24527543,
    "qs:woe_lau":0,
    "qs:woe_local":2295414,
    "qs:woe_ver":"7.10.0",
    "wd:wordcount":407,
    "wof:lang":[
        "eng"
    ],
    "wof:name":"Tolichowki",
    "wof:placetype":"neighbourhood"
},
  "geometry": {"coordinates":[78.40898799999999,17.403753],"type":"Point"}
}