{
  "type": "Feature",
  "properties": {
    "iso:country":"IN",
    "ks:ks_name":"Pukhuria",
    "ks:ks_pop":2552,
    "ks:ks_type":"VILLAGE",
    "ks:ks_uagg_main":0,
    "name:eng_x_preferred":[
        "Pukhuria"
    ],
    "wof:name":"Pukhuria",
    "wof:placetype":"neighbourhood",
    "wof:population":2552
},
  "geometry": {"coordinates":[88.762641,22.614148],"type":"Point"}
}