{
  "type": "Feature",
  "properties": {
    "iso:country":"IN",
    "ks:ks_alt_nam":"Naikasahi silipada",
    "ks:ks_name":"Naikasahi Silipada",
    "ks:ks_pop":260,
    "ks:ks_type":"HABITATION",
    "name:eng_x_preferred":[
        "Naikasahi Silipada"
    ],
    "wof:name":"Naikasahi Silipada",
    "wof:placetype":"locality",
    "wof:population":260
},
  "geometry": {"coordinates":[85.877331,21.68312],"type":"Point"}
}