{
  "type": "Feature",
  "properties": {
    "gn:admin1_code":"23.0",
    "gn:admin2_code":"35.0",
    "gn:asciiname":"Kila Darshan Singh",
    "gn:country_code":"IN",
    "gn:dem":250,
    "gn:feature_class":"P",
    "gn:feature_code":"PPL",
    "gn:name":"Kila Darshan Singh",
    "gn:population":0,
    "gn:timezone":"Asia/Kolkata",
    "iso:country":"IN",
    "ks:ks_name":"Qila Darshan Singh",
    "ks:ks_pop":973,
    "ks:ks_type":"VILLAGE",
    "name:eng_x_preferred":[
        "Qila Darshan Singh"
    ],
    "name:eng_x_variant":[
        "Kila Darshan Singh"
    ],
    "wof:name":"Qila Darshan Singh",
    "wof:placetype":"locality",
    "wof:population":973
},
  "geometry": {"coordinates":[75.239626,31.865594],"type":"Point"}
}