{
  "type": "Feature",
  "properties": {
    "iso:country":"IN",
    "ks:ks_name":"Reesupeta",
    "ks:ks_pop":74,
    "ks:ks_type":"HABITATION",
    "name:eng_x_preferred":[
        "Reesupeta"
    ],
    "wof:name":"Reesupeta",
    "wof:placetype":"locality",
    "wof:population":74
},
  "geometry": {"coordinates":[83.641825,18.095835],"type":"Point"}
}