{
  "type": "Feature",
  "properties": {
    "iso:country":"IN",
    "ks:ks_name":"Madaripur Karan",
    "ks:ks_pop":3805,
    "ks:ks_type":"VILLAGE",
    "ks:ks_uagg_main":0,
    "name:eng_x_preferred":[
        "Madaripur Karan"
    ],
    "wof:name":"Madaripur Karan",
    "wof:placetype":"neighbourhood",
    "wof:population":3805
},
  "geometry": {"coordinates":[85.448367,26.270066],"type":"Point"}
}