{
  "type": "Feature",
  "properties": {
    "iso:country":"IN",
    "ks:ks_name":"Bhelwatoli",
    "ks:ks_pop":185,
    "ks:ks_type":"HABITATION",
    "name:eng_x_preferred":[
        "Bhelwatoli"
    ],
    "wof:name":"Bhelwatoli",
    "wof:placetype":"locality",
    "wof:population":185
},
  "geometry": {"coordinates":[84.810959,22.956977],"type":"Point"}
}