{
  "type": "Feature",
  "properties": {
    "iso:country":"IN",
    "ks:ks_name":"Totasingha",
    "ks:ks_pop":229,
    "ks:ks_type":"VILLAGE",
    "ks:ks_uagg_main":0,
    "name:eng_x_preferred":[
        "Totasingha"
    ],
    "wof:name":"Totasingha",
    "wof:placetype":"neighbourhood",
    "wof:population":229
},
  "geometry": {"coordinates":[86.04812800000001,20.756573],"type":"Point"}
}