{
  "type": "Feature",
  "properties": {
    "iso:country":"IN",
    "ks:ks_name":"Juna Muvada",
    "ks:ks_pop":178,
    "ks:ks_type":"VILLAGE",
    "name:eng_x_preferred":[
        "Juna Muvada"
    ],
    "wof:name":"Juna Muvada",
    "wof:placetype":"locality",
    "wof:population":178
},
  "geometry": {"coordinates":[73.639608,23.079819],"type":"Point"}
}