{
  "type": "Feature",
  "properties": {
    "iso:country":"IN",
    "ks:ks_name":"Pasi Basti",
    "ks:ks_pop":300,
    "ks:ks_type":"HABITATION",
    "name:eng_x_preferred":[
        "Pasi Basti"
    ],
    "wof:name":"Pasi Basti",
    "wof:placetype":"locality",
    "wof:population":300
},
  "geometry": {"coordinates":[82.70965700000001,25.406613],"type":"Point"}
}