{
  "type": "Feature",
  "properties": {
    "gn:admin1_code":"35.0",
    "gn:admin2_code":"448",
    "gn:asciiname":"Bhunnas",
    "gn:country_code":"IN",
    "gn:dem":292,
    "gn:feature_class":"P",
    "gn:feature_code":"PPL",
    "gn:name":"Bhunn\u0101s",
    "gn:population":0,
    "gn:timezone":"Asia/Kolkata",
    "iso:country":"IN",
    "name:und_x_variant":[
        "Bhunn\u0101s",
        "Bhun\u0101s"
    ],
    "wof:name":"Bhunnas",
    "wof:placetype":"locality"
},
  "geometry": {"coordinates":[77.10104,22.43477],"type":"Point"}
}