{
  "type": "Feature",
  "properties": {
    "iso:country":"IN",
    "ks:ks_name":"Ganeshwadi",
    "ks:ks_pop":82,
    "ks:ks_type":"HABITATION",
    "name:eng_x_preferred":[
        "Ganeshwadi"
    ],
    "wof:name":"Ganeshwadi",
    "wof:placetype":"locality",
    "wof:population":82
},
  "geometry": {"coordinates":[73.396816,19.810199],"type":"Point"}
}