{
  "type": "Feature",
  "properties": {
    "iso:country":"IN",
    "ks:ks_name":"Lepeta Para",
    "ks:ks_pop":463,
    "ks:ks_type":"VILLAGE",
    "ks:ks_uagg_main":0,
    "name:eng_x_preferred":[
        "Lepeta Para"
    ],
    "wof:name":"Lepeta Para",
    "wof:placetype":"neighbourhood",
    "wof:population":463
},
  "geometry": {"coordinates":[93.457418,26.822711],"type":"Point"}
}