{
  "type": "Feature",
  "properties": {
    "gn:admin1_code":"20",
    "gn:admin2_code":"267.0",
    "gn:asciiname":"Thonokhyu",
    "gn:country_code":"IN",
    "gn:dem":1556,
    "gn:feature_class":"P",
    "gn:feature_code":"PPL",
    "gn:name":"Thonokhyu",
    "gn:population":0,
    "gn:timezone":"Asia/Kolkata",
    "iso:country":"IN",
    "wof:name":"Thonokhyu",
    "wof:placetype":"locality"
},
  "geometry": {"coordinates":[94.90595999999999,25.96897],"type":"Point"}
}