{
  "type": "Feature",
  "properties": {
    "iso:country":"IN",
    "ks:ks_name":"Dongarfali",
    "ks:ks_pop":430,
    "ks:ks_type":"HABITATION",
    "name:eng_x_preferred":[
        "Dongarfali"
    ],
    "wof:name":"Dongarfali",
    "wof:placetype":"locality",
    "wof:population":430
},
  "geometry": {"coordinates":[73.9662,21.8052],"type":"Point"}
}