{
  "type": "Feature",
  "properties": {
    "gn:admin1_code":"36",
    "gn:admin2_code":"159.0",
    "gn:asciiname":"Rukhia Khalikdadpur",
    "gn:country_code":"IN",
    "gn:dem":160,
    "gn:feature_class":"P",
    "gn:feature_code":"PPL",
    "gn:name":"R\u016bkhia Kh\u0101likd\u0101dpur",
    "gn:population":0,
    "gn:timezone":"Asia/Kolkata",
    "iso:country":"IN",
    "wof:name":"Rukhia Khalikdadpur",
    "wof:placetype":"locality"
},
  "geometry": {"coordinates":[79.27670999999999,27.45659],"type":"Point"}
}