{
  "type": "Feature",
  "properties": {
    "gn:admin1_code":"35.0",
    "gn:admin2_code":"427",
    "gn:asciiname":"Bharrana",
    "gn:country_code":"IN",
    "gn:dem":482,
    "gn:feature_class":"P",
    "gn:feature_code":"PPL",
    "gn:name":"Bharr\u0101na",
    "gn:population":0,
    "gn:timezone":"Asia/Kolkata",
    "iso:country":"IN",
    "name:und_x_variant":[
        "Bharr\u0101na",
        "Bhadrana"
    ],
    "wof:name":"Bharrana",
    "wof:placetype":"locality"
},
  "geometry": {"coordinates":[79.00329000000001,23.96509],"type":"Point"}
}