{
  "type": "Feature",
  "properties": {
    "iso:country":"IN",
    "ks:ks_name":"Kamalpur",
    "ks:ks_pop":1059,
    "ks:ks_type":"VILLAGE",
    "name:eng_x_preferred":[
        "Kamalpur"
    ],
    "wof:name":"Kamalpur",
    "wof:placetype":"locality",
    "wof:population":1059
},
  "geometry": {"coordinates":[82.830889,23.845836],"type":"Point"}
}