{
  "type": "Feature",
  "properties": {
    "iso:country":"IN",
    "ks:ks_name":"Kaithala",
    "ks:ks_pop":1212,
    "ks:ks_type":"HABITATION",
    "name:eng_x_preferred":[
        "Kaithala"
    ],
    "wof:name":"Kaithala",
    "wof:placetype":"locality",
    "wof:population":1212
},
  "geometry": {"coordinates":[77.773646,28.377412],"type":"Point"}
}