{
  "type": "Feature",
  "properties": {
    "iso:country":"IN",
    "ks:ks_name":"Mokasa Chinna Pedda Kotturu",
    "ks:ks_pop":86,
    "ks:ks_type":"HABITATION",
    "name:eng_x_preferred":[
        "Mokasa Chinna Pedda Kotturu"
    ],
    "wof:name":"Mokasa Chinna Pedda Kotturu",
    "wof:placetype":"locality",
    "wof:population":86
},
  "geometry": {"coordinates":[84.19676800000001,18.751034],"type":"Point"}
}