{
  "type": "Feature",
  "properties": {
    "gn:admin1_code":"03",
    "gn:admin2_code":"305.0",
    "gn:asciiname":"Misa",
    "gn:country_code":"IN",
    "gn:dem":73,
    "gn:feature_class":"P",
    "gn:feature_code":"PPL",
    "gn:name":"Mis\u0101",
    "gn:population":0,
    "gn:timezone":"Asia/Kolkata",
    "iso:country":"IN",
    "name:ceb_x_preferred":[
        "Misa"
    ],
    "name:deu_x_preferred":[
        "Misa"
    ],
    "name:fra_x_preferred":[
        "Misa"
    ],
    "name:glg_x_preferred":[
        "Misa"
    ],
    "name:hun_x_preferred":[
        "Misa"
    ],
    "name:ita_x_preferred":[
        "Misa"
    ],
    "name:lav_x_preferred":[
        "Misa"
    ],
    "name:lit_x_preferred":[
        "Misa"
    ],
    "name:por_x_preferred":[
        "Misa"
    ],
    "name:ron_x_preferred":[
        "Misa"
    ],
    "name:spa_x_preferred":[
        "Misa"
    ],
    "name:swe_x_preferred":[
        "Misa"
    ],
    "name:tha_x_preferred":[
        "\u0e21\u0e34\u0e2a\u0e30"
    ],
    "wof:name":"Misa",
    "wof:placetype":"locality"
},
  "geometry": {"coordinates":[92.93333,26.48333],"type":"Point"}
}