{
  "type": "Feature",
  "properties": {
    "iso:country":"IN",
    "ks:ks_name":"Kothankudi",
    "ks:ks_pop":281,
    "ks:ks_type":"HABITATION",
    "name:eng_x_preferred":[
        "Kothankudi"
    ],
    "wof:name":"Kothankudi",
    "wof:placetype":"locality",
    "wof:population":281
},
  "geometry": {"coordinates":[79.723274,10.672193],"type":"Point"}
}