{
  "type": "Feature",
  "properties": {
    "iso:country":"IN",
    "ks:ks_name":"Nitaipur",
    "ks:ks_pop":8,
    "ks:ks_type":"VILLAGE",
    "name:eng_x_preferred":[
        "Nitaipur"
    ],
    "wof:name":"Nitaipur",
    "wof:placetype":"locality",
    "wof:population":8
},
  "geometry": {"coordinates":[87.272767,22.587546],"type":"Point"}
}