{
  "type": "Feature",
  "properties": {
    "gn:admin1_code":"16",
    "gn:admin2_code":"501.0",
    "gn:asciiname":"Jamti Khurd",
    "gn:country_code":"IN",
    "gn:dem":311,
    "gn:feature_class":"P",
    "gn:feature_code":"PPL",
    "gn:name":"Jamti Khurd",
    "gn:population":0,
    "gn:timezone":"Asia/Kolkata",
    "iso:country":"IN",
    "wof:name":"Jamti Khurd",
    "wof:placetype":"locality"
},
  "geometry": {"coordinates":[77.39502,20.69507],"type":"Point"}
}