{
  "type": "Feature",
  "properties": {
    "iso:country":"IN",
    "ks:ks_name":"Bhandripada",
    "ks:ks_pop":148,
    "ks:ks_type":"HABITATION",
    "name:eng_x_preferred":[
        "Bhandripada"
    ],
    "wof:name":"Bhandripada",
    "wof:placetype":"locality",
    "wof:population":148
},
  "geometry": {"coordinates":[72.95258200000001,19.930115],"type":"Point"}
}