{
  "type": "Feature",
  "properties": {
    "iso:country":"IN",
    "ks:ks_name":"Shakarpally",
    "ks:ks_pop":314,
    "ks:ks_type":"HABITATION",
    "name:eng_x_preferred":[
        "Shakarpally"
    ],
    "wof:name":"Shakarpally",
    "wof:placetype":"locality",
    "wof:population":314
},
  "geometry": {"coordinates":[79.51591500000001,18.977548],"type":"Point"}
}