{
  "type": "Feature",
  "properties": {
    "iso:country":"IN",
    "ks:ks_name":"Naguesiyan Dhoondha",
    "ks:ks_type":"VILLAGE",
    "name:eng_x_preferred":[
        "Naguesiyan Dhoondha"
    ],
    "wof:name":"Naguesiyan Dhoondha",
    "wof:placetype":"locality"
},
  "geometry": {"coordinates":[71.536169,25.830651],"type":"Point"}
}