{
  "type": "Feature",
  "properties": {
    "iso:country":"IN",
    "ks:ks_name":"Mundarithanda",
    "ks:ks_pop":124,
    "ks:ks_type":"HABITATION",
    "name:eng_x_preferred":[
        "Mundarithanda"
    ],
    "wof:name":"Mundarithanda",
    "wof:placetype":"locality",
    "wof:population":124
},
  "geometry": {"coordinates":[78.11978999999999,16.401303],"type":"Point"}
}