{
  "type": "Feature",
  "properties": {
    "iso:country":"IN",
    "ks:ks_name":"Kaval Kinaru Vilakku",
    "ks:ks_pop":445,
    "ks:ks_type":"HABITATION",
    "ks:ks_uagg_main":0,
    "name:eng_x_preferred":[
        "Kaval Kinaru Vilakku"
    ],
    "wof:name":"Kaval Kinaru Vilakku",
    "wof:placetype":"neighbourhood",
    "wof:population":445
},
  "geometry": {"coordinates":[77.56788899999999,8.277565],"type":"Point"}
}