{
  "type": "Feature",
  "properties": {
    "iso:country":"IN",
    "ks:ks_name":"Dasbaria",
    "ks:ks_pop":1565,
    "ks:ks_type":"VILLAGE",
    "ks:ks_uagg_main":0,
    "name:eng_x_preferred":[
        "Dasbaria"
    ],
    "wof:name":"Dasbaria",
    "wof:placetype":"neighbourhood",
    "wof:population":1565
},
  "geometry": {"coordinates":[88.65694000000001,22.926479],"type":"Point"}
}