{
  "type": "Feature",
  "properties": {
    "iso:country":"IN",
    "ks:ks_name":"Fatehpur",
    "ks:ks_pop":465,
    "ks:ks_type":"VILLAGE",
    "ks:ks_uagg_main":0,
    "name:eng_x_preferred":[
        "Fatehpur"
    ],
    "name:hin_x_preferred":[
        "\u095e\u0924\u0947\u0939\u092a\u0941\u0930"
    ],
    "wof:name":"Fatehpur",
    "wof:placetype":"neighbourhood",
    "wof:population":465
},
  "geometry": {"coordinates":[80.617566,26.244123],"type":"Point"}
}