{
  "type": "Feature",
  "properties": {
    "iso:country":"IN",
    "ks:ks_name":"Gadadharpur",
    "ks:ks_pop":268,
    "ks:ks_type":"VILLAGE",
    "name:eng_x_preferred":[
        "Gadadharpur"
    ],
    "wof:name":"Gadadharpur",
    "wof:placetype":"locality",
    "wof:population":268
},
  "geometry": {"coordinates":[84.46524100000001,21.62861],"type":"Point"}
}