{
  "type": "Feature",
  "properties": {
    "iso:country":"IN",
    "ks:ks_name":"Hulimanejeddi",
    "ks:ks_pop":54,
    "ks:ks_type":"HABITATION",
    "name:eng_x_preferred":[
        "Hulimanejeddi"
    ],
    "wof:name":"Hulimanejeddi",
    "wof:placetype":"locality",
    "wof:population":54
},
  "geometry": {"coordinates":[74.817857,14.788711],"type":"Point"}
}