{
  "type": "Feature",
  "properties": {
    "iso:country":"IN",
    "ks:ks_name":"Dumatandi",
    "ks:ks_pop":185,
    "ks:ks_type":"VILLAGE",
    "name:eng_x_preferred":[
        "Dumatandi"
    ],
    "wof:name":"Dumatandi",
    "wof:placetype":"locality",
    "wof:population":185
},
  "geometry": {"coordinates":[86.134382,22.48517],"type":"Point"}
}