{
  "type": "Feature",
  "properties": {
    "iso:country":"IN",
    "ks:ks_name":"Kanjileru",
    "ks:ks_pop":1802,
    "ks:ks_type":"HABITATION",
    "name:eng_x_preferred":[
        "Kanjileru"
    ],
    "wof:name":"Kanjileru",
    "wof:placetype":"locality",
    "wof:population":1802
},
  "geometry": {"coordinates":[75.567761,12.040148],"type":"Point"}
}