{
  "type": "Feature",
  "properties": {
    "iso:country":"IN",
    "ks:ks_name":"Materjhar",
    "ks:ks_pop":563,
    "ks:ks_type":"HABITATION",
    "name:eng_x_preferred":[
        "Materjhar"
    ],
    "wof:name":"Materjhar",
    "wof:placetype":"locality",
    "wof:population":563
},
  "geometry": {"coordinates":[89.920973,26.244167],"type":"Point"}
}