{
  "type": "Feature",
  "properties": {
    "gn:admin1_code":"25.0",
    "gn:admin2_code":"604",
    "gn:asciiname":"Valarpuram",
    "gn:country_code":"IN",
    "gn:dem":42,
    "gn:feature_class":"P",
    "gn:feature_code":"PPL",
    "gn:name":"Valarpuram",
    "gn:population":0,
    "gn:timezone":"Asia/Kolkata",
    "iso:country":"IN",
    "name:und_x_variant":[
        "Valapuram",
        "Valarpuram"
    ],
    "wof:name":"Valarpuram",
    "wof:placetype":"locality"
},
  "geometry": {"coordinates":[79.97412,13.02134],"type":"Point"}
}