{
  "type": "Feature",
  "properties": {
    "iso:country":"IN",
    "ks:ks_name":"Gawarwadi",
    "ks:ks_pop":150,
    "ks:ks_type":"HABITATION",
    "name:eng_x_preferred":[
        "Gawarwadi"
    ],
    "wof:name":"Gawarwadi",
    "wof:placetype":"locality",
    "wof:population":150
},
  "geometry": {"coordinates":[73.655866,18.562673],"type":"Point"}
}