{
  "type": "Feature",
  "properties": {
    "gn:admin1_code":"35.0",
    "gn:admin2_code":"457.0",
    "gn:asciiname":"Sihora",
    "gn:country_code":"IN",
    "gn:dem":297,
    "gn:feature_class":"P",
    "gn:feature_code":"PPL",
    "gn:name":"Sihor\u0101",
    "gn:population":0,
    "gn:timezone":"Asia/Kolkata",
    "iso:country":"IN",
    "name:ben_x_preferred":[
        "\u09b8\u09bf\u09b9\u09cb\u09b0\u09be"
    ],
    "name:bpy_x_preferred":[
        "\u09b8\u09bf\u09b9\u09cb\u09b0\u09be"
    ],
    "name:ceb_x_preferred":[
        "Sihor\u0101"
    ],
    "name:ita_x_preferred":[
        "Sihora"
    ],
    "name:msa_x_preferred":[
        "Sihora"
    ],
    "name:ori_x_preferred":[
        "\u0b38\u0b3f\u0b39\u0b4b\u0b30\u0b3e"
    ],
    "name:por_x_preferred":[
        "Sihora"
    ],
    "name:spa_x_preferred":[
        "Sihora"
    ],
    "name:swe_x_preferred":[
        "Sihor\u0101"
    ],
    "name:vie_x_preferred":[
        "Sihora"
    ],
    "name:zho_x_preferred":[
        "\u897f\u970d\u62c9"
    ],
    "wof:name":"Sihora",
    "wof:placetype":"locality"
},
  "geometry": {"coordinates":[80.23524999999999,21.73195],"type":"Point"}
}