{
  "type": "Feature",
  "properties": {
    "iso:country":"IN",
    "ks:ks_name":"Ganthiya",
    "ks:ks_pop":480,
    "ks:ks_type":"HABITATION",
    "name:eng_x_preferred":[
        "Ganthiya"
    ],
    "wof:name":"Ganthiya",
    "wof:placetype":"locality",
    "wof:population":480
},
  "geometry": {"coordinates":[73.457978,24.071858],"type":"Point"}
}