{
  "type": "Feature",
  "properties": {
    "iso:country":"IN",
    "ks:ks_name":"Jonadu",
    "ks:ks_pop":275,
    "ks:ks_type":"HABITATION",
    "name:eng_x_preferred":[
        "Jonadu"
    ],
    "wof:name":"Jonadu",
    "wof:placetype":"locality",
    "wof:population":275
},
  "geometry": {"coordinates":[74.692924,14.097019],"type":"Point"}
}