{
  "type": "Feature",
  "properties": {
    "gn:country":"IN",
    "gn:fcode":"PPL",
    "gn:population":22779,
    "iso:country":"IN",
    "name:ben_x_preferred":[
        "\u09b9\u09bf\u09a8\u09cd\u099c\u09bf\u09b2\u09bf\u0995\u09be\u099f"
    ],
    "name:bpy_x_preferred":[
        "\u09b9\u09bf\u09a8\u09cd\u099c\u09bf\u09b2\u09bf\u0995\u09be\u099f"
    ],
    "name:ceb_x_preferred":[
        "Hinjilikatu"
    ],
    "name:eng_x_preferred":[
        "Hinjilicut"
    ],
    "name:hin_x_preferred":[
        "\u0939\u093f\u0902\u091c\u093f\u0932\u093f\u0915\u091f"
    ],
    "name:ita_x_preferred":[
        "Hinjilicut"
    ],
    "name:msa_x_preferred":[
        "Hinjilicut"
    ],
    "name:nan_x_preferred":[
        "Hinjilicut"
    ],
    "name:nld_x_preferred":[
        "Hinjilicut"
    ],
    "name:ori_x_preferred":[
        "\u0b39\u0b3f\u0b1e\u0b4d\u0b1c\u0b3f\u0b33\u0b3f\u0b15\u0b3e\u0b1f\u0b41"
    ],
    "name:por_x_preferred":[
        "Hinjilicut"
    ],
    "name:spa_x_preferred":[
        "Hinjilicut"
    ],
    "name:swe_x_preferred":[
        "Hinjilikatu"
    ],
    "name:vie_x_preferred":[
        "Hinjilicut"
    ],
    "name:zho_x_preferred":[
        "\u6b23\u5409\u5229\u4e18\u7279"
    ],
    "qs:name":"Hinjilikatu",
    "qs:photos_9r":0,
    "qs:photos_sr":0,
    "qs:pop_sr":"7",
    "wd:wordcount":1445,
    "wof:name":"Hinjilikatu",
    "wof:placetype":"locality",
    "wof:population":22779
},
  "geometry": {"coordinates":[84.74489,19.48166],"type":"Point"}
}