{
  "type": "Feature",
  "properties": {
    "gn:admin1_code":"37.0",
    "gn:admin2_code":"416.0",
    "gn:asciiname":"Keratong",
    "gn:country_code":"IN",
    "gn:dem":265,
    "gn:feature_class":"P",
    "gn:feature_code":"PPL",
    "gn:name":"Keratong",
    "gn:population":0,
    "gn:timezone":"Asia/Kolkata",
    "iso:country":"IN",
    "ks:ks_name":"Keratong",
    "ks:ks_type":"VILLAGE",
    "name:eng_x_preferred":[
        "Keratong"
    ],
    "wof:name":"Keratong",
    "wof:placetype":"locality"
},
  "geometry": {"coordinates":[81.69531600000001,18.601662],"type":"Point"}
}