{
  "type": "Feature",
  "properties": {
    "iso:country":"IN",
    "ks:ks_name":"Beldari Tola Chhotaki",
    "ks:ks_pop":345,
    "ks:ks_type":"HABITATION",
    "ks:ks_uagg_main":0,
    "name:eng_x_preferred":[
        "Beldari Tola Chhotaki"
    ],
    "wof:name":"Beldari Tola Chhotaki",
    "wof:placetype":"neighbourhood",
    "wof:population":345
},
  "geometry": {"coordinates":[83.234199,26.558142],"type":"Point"}
}