{
  "type": "Feature",
  "properties": {
    "iso:country":"IN",
    "ks:ks_name":"Konwarijan",
    "ks:ks_pop":351,
    "ks:ks_type":"VILLAGE",
    "ks:ks_uagg_main":0,
    "name:eng_x_preferred":[
        "Konwarijan"
    ],
    "wof:name":"Konwarijan",
    "wof:placetype":"locality",
    "wof:population":351
},
  "geometry": {"coordinates":[95.28750100000001,27.296443],"type":"Point"}
}