{
  "type": "Feature",
  "properties": {
    "iso:country":"IN",
    "ks:ks_name":"Melapoigainallur",
    "ks:ks_pop":218,
    "ks:ks_type":"HABITATION",
    "name:eng_x_preferred":[
        "Melapoigainallur"
    ],
    "wof:name":"Melapoigainallur",
    "wof:placetype":"locality",
    "wof:population":218
},
  "geometry": {"coordinates":[79.61568699999999,10.674634],"type":"Point"}
}