{
  "type": "Feature",
  "properties": {
    "gn:admin1_code":"16.0",
    "gn:admin2_code":"513",
    "gn:asciiname":"Babulgaon",
    "gn:country_code":"IN",
    "gn:dem":415,
    "gn:feature_class":"P",
    "gn:feature_code":"PPL",
    "gn:name":"B\u0101bulgaon",
    "gn:population":0,
    "gn:timezone":"Asia/Kolkata",
    "iso:country":"IN",
    "name:und_x_variant":[
        "B\u0101bulgaon",
        "Bab\u016blgaon"
    ],
    "wof:name":"Babulgaon",
    "wof:placetype":"locality"
},
  "geometry": {"coordinates":[76.42731999999999,19.16889],"type":"Point"}
}