{
  "type": "Feature",
  "properties": {
    "iso:country":"IN",
    "ks:ks_name":"Pusugondi",
    "ks:ks_pop":92,
    "ks:ks_type":"HABITATION",
    "name:eng_x_preferred":[
        "Pusugondi"
    ],
    "wof:name":"Pusugondi",
    "wof:placetype":"locality",
    "wof:population":92
},
  "geometry": {"coordinates":[81.375434,17.474135],"type":"Point"}
}