{
  "type": "Feature",
  "properties": {
    "iso:country":"IN",
    "ks:ks_name":"Rengalbeda",
    "ks:ks_pop":164,
    "ks:ks_type":"VILLAGE",
    "name:eng_x_preferred":[
        "Rengalbeda"
    ],
    "wof:name":"Rengalbeda",
    "wof:placetype":"locality",
    "wof:population":164
},
  "geometry": {"coordinates":[84.686306,22.114712],"type":"Point"}
}