{
  "type": "Feature",
  "properties": {
    "iso:country":"IN",
    "ks:ks_name":"Konarpur",
    "ks:ks_pop":176,
    "ks:ks_type":"VILLAGE",
    "ks:ks_uagg_main":0,
    "name:eng_x_preferred":[
        "Konarpur"
    ],
    "wof:name":"Konarpur",
    "wof:placetype":"neighbourhood",
    "wof:population":176
},
  "geometry": {"coordinates":[87.368448,22.897063],"type":"Point"}
}