{
  "type": "Feature",
  "properties": {
    "gn:admin1_code":"36.0",
    "gn:admin2_code":"141.0",
    "gn:asciiname":"Muqimpur",
    "gn:country_code":"IN",
    "gn:dem":201,
    "gn:feature_class":"P",
    "gn:feature_code":"PPL",
    "gn:name":"Muq\u012bmpur",
    "gn:population":0,
    "gn:timezone":"Asia/Kolkata",
    "iso:country":"IN",
    "name:und_x_variant":[
        "Muq\u012bmpur",
        "Siw\u0101ra"
    ],
    "wof:name":"Muqimpur",
    "wof:placetype":"locality"
},
  "geometry": {"coordinates":[77.57966999999999,28.16305],"type":"Point"}
}