{
  "type": "Feature",
  "properties": {
    "iso:country":"IN",
    "ks:ks_name":"Jojogoda",
    "ks:ks_pop":62,
    "ks:ks_type":"HABITATION",
    "name:eng_x_preferred":[
        "Jojogoda"
    ],
    "wof:name":"Jojogoda",
    "wof:placetype":"locality",
    "wof:population":62
},
  "geometry": {"coordinates":[86.254687,22.420611],"type":"Point"}
}