{
  "type": "Feature",
  "properties": {
    "gn:admin1_code":"28.0",
    "gn:admin2_code":"335",
    "gn:asciiname":"Ausgram",
    "gn:country_code":"IN",
    "gn:dem":45,
    "gn:feature_class":"P",
    "gn:feature_code":"PPL",
    "gn:name":"\u0100usgr\u0101m",
    "gn:population":0,
    "gn:timezone":"Asia/Kolkata",
    "iso:country":"IN",
    "name:und_x_variant":[
        "\u0100usgr\u0101m"
    ],
    "wof:name":"Ausgram",
    "wof:placetype":"locality"
},
  "geometry": {"coordinates":[87.66611999999998,23.51762],"type":"Point"}
}