{
  "type": "Feature",
  "properties": {
    "iso:country":"IN",
    "ks:ks_name":"Thalancheri",
    "ks:ks_pop":722,
    "ks:ks_type":"VILLAGE",
    "name:eng_x_preferred":[
        "Thalancheri"
    ],
    "wof:name":"Thalancheri",
    "wof:placetype":"locality",
    "wof:population":722
},
  "geometry": {"coordinates":[79.61034600000001,11.162078],"type":"Point"}
}