{
  "type": "Feature",
  "properties": {
    "iso:country":"IN",
    "ks:ks_alt_nam":"Balan vattam",
    "ks:ks_name":"Balan Vattam",
    "ks:ks_pop":200,
    "ks:ks_type":"HABITATION",
    "ks:ks_uagg_main":0,
    "name:eng_x_preferred":[
        "Balan Vattam"
    ],
    "wof:name":"Balan Vattam",
    "wof:placetype":"neighbourhood",
    "wof:population":200
},
  "geometry": {"coordinates":[78.55948600000001,12.629501],"type":"Point"}
}