{
  "type": "Feature",
  "properties": {
    "iso:country":"IN",
    "ks:ks_name":"Pusuguppa Patch 3",
    "ks:ks_pop":202,
    "ks:ks_type":"HABITATION",
    "name:eng_x_preferred":[
        "Pusuguppa Patch 3"
    ],
    "wof:name":"Pusuguppa Patch 3",
    "wof:placetype":"locality",
    "wof:population":202
},
  "geometry": {"coordinates":[80.834862,18.22338],"type":"Point"}
}