{
  "type": "Feature",
  "properties": {
    "iso:country":"IN",
    "ks:ks_name":"Moolakkari",
    "ks:ks_pop":1861,
    "ks:ks_type":"HABITATION",
    "name:eng_x_preferred":[
        "Moolakkari"
    ],
    "wof:name":"Moolakkari",
    "wof:placetype":"locality",
    "wof:population":1861
},
  "geometry": {"coordinates":[75.50035800000001,11.933426],"type":"Point"}
}