{
  "type": "Feature",
  "properties": {
    "iso:country":"IN",
    "ks:ks_name":"Sirtola",
    "ks:ks_pop":128,
    "ks:ks_type":"VILLAGE",
    "name:eng_x_preferred":[
        "Sirtola"
    ],
    "wof:name":"Sirtola",
    "wof:placetype":"locality",
    "wof:population":128
},
  "geometry": {"coordinates":[80.323559,29.999116],"type":"Point"}
}