{
  "type": "Feature",
  "properties": {
    "iso:country":"IN",
    "ks:ks_name":"Sampala",
    "ks:ks_pop":227,
    "ks:ks_type":"VILLAGE",
    "name:eng_x_preferred":[
        "Sampala"
    ],
    "wof:name":"Sampala",
    "wof:placetype":"locality",
    "wof:population":227
},
  "geometry": {"coordinates":[82.97207400000001,19.664386],"type":"Point"}
}