{
  "type": "Feature",
  "properties": {
    "iso:country":"IN",
    "ks:ks_alt_nam":"TANRWA",
    "ks:ks_name":"Tanrwa",
    "ks:ks_pop":3702,
    "ks:ks_type":"HABITATION",
    "name:eng_x_preferred":[
        "Tanrwa"
    ],
    "wof:name":"Tanrwa",
    "wof:placetype":"locality",
    "wof:population":3702
},
  "geometry": {"coordinates":[84.726495,24.326764],"type":"Point"}
}