{
  "type": "Feature",
  "properties": {
    "iso:country":"IN",
    "ks:ks_name":"Dewoolwadi",
    "ks:ks_pop":61,
    "ks:ks_type":"HABITATION",
    "name:eng_x_preferred":[
        "Dewoolwadi"
    ],
    "wof:name":"Dewoolwadi",
    "wof:placetype":"locality",
    "wof:population":61
},
  "geometry": {"coordinates":[73.90370799999999,15.857038],"type":"Point"}
}