{
  "type": "Feature",
  "properties": {
    "gn:admin1_code":"35.0",
    "gn:admin2_code":"446.0",
    "gn:asciiname":"Rahman",
    "gn:country_code":"IN",
    "gn:dem":330,
    "gn:feature_class":"P",
    "gn:feature_code":"PPL",
    "gn:name":"Rahm\u0101n",
    "gn:population":0,
    "gn:timezone":"Asia/Kolkata",
    "iso:country":"IN",
    "name:ara_x_preferred":[
        "\u0627\u0644\u0631\u062d\u0645\u0646"
    ],
    "name:fra_x_preferred":[
        "Rahman"
    ],
    "name:heb_x_preferred":[
        "\u05e8\u05d7\u05de\u05df"
    ],
    "name:lav_x_preferred":[
        "Rahmans"
    ],
    "name:pol_x_preferred":[
        "Rahman"
    ],
    "name:rus_x_preferred":[
        "\u0420\u0430\u0445\u043c\u0430\u043d"
    ],
    "name:tur_x_preferred":[
        "Rahman"
    ],
    "wof:name":"Rahman",
    "wof:placetype":"locality"
},
  "geometry": {"coordinates":[78.47708,23.10216],"type":"Point"}
}