{
  "type": "Feature",
  "properties": {
    "gn:admin1_code":"13",
    "gn:admin2_code":"597.0",
    "gn:asciiname":"Kuravalangad",
    "gn:country_code":"IN",
    "gn:dem":86,
    "gn:feature_class":"P",
    "gn:feature_code":"PPL",
    "gn:name":"Kuravalang\u0101d",
    "gn:population":0,
    "gn:timezone":"Asia/Kolkata",
    "iso:country":"IN",
    "ks:ks_name":"Kuravilangad",
    "ks:ks_pop":18242,
    "ks:ks_type":"VILLAGE",
    "name:eng_x_preferred":[
        "Kuravilangad"
    ],
    "name:eng_x_variant":[
        "Kuravalangad"
    ],
    "wof:name":"Kuravilangad",
    "wof:placetype":"locality",
    "wof:population":18242
},
  "geometry": {"coordinates":[76.56478199999999,9.752979],"type":"Point"}
}