{
  "type": "Feature",
  "properties": {
    "gn:admin1_code":"13",
    "gn:admin2_code":"597.0",
    "gn:asciiname":"Kuravalangad",
    "gn:country_code":"IN",
    "gn:dem":86,
    "gn:feature_class":"P",
    "gn:feature_code":"PPL",
    "gn:name":"Kuravalang\u0101d",
    "gn:population":0,
    "gn:timezone":"Asia/Kolkata",
    "iso:country":"IN",
    "wof:name":"Kuravalangad",
    "wof:placetype":"locality"
},
  "geometry": {"coordinates":[76.56667,9.75],"type":"Point"}
}