{
  "type": "Feature",
  "properties": {
    "iso:country":"IN",
    "ks:ks_name":"Nagla Lachhi",
    "ks:ks_pop":0,
    "ks:ks_type":"VILLAGE",
    "name:eng_x_preferred":[
        "Nagla Lachhi"
    ],
    "wof:name":"Nagla Lachhi",
    "wof:placetype":"locality",
    "wof:population":0
},
  "geometry": {"coordinates":[79.366134,26.671793],"type":"Point"}
}