{
  "type": "Feature",
  "properties": {
    "iso:country":"IN",
    "ks:ks_name":"Turka",
    "ks:ks_pop":189,
    "ks:ks_type":"VILLAGE",
    "name:eng_x_preferred":[
        "Turka"
    ],
    "wof:name":"Turka",
    "wof:placetype":"locality",
    "wof:population":189
},
  "geometry": {"coordinates":[86.763565,24.579382],"type":"Point"}
}