{
  "type": "Feature",
  "properties": {
    "iso:country":"IN",
    "ks:ks_alt_nam":"J\u0101mp\u0101ni",
    "ks:ks_name":"Jampani",
    "ks:ks_pop":117,
    "ks:ks_type":"VILLAGE",
    "name:eng_x_preferred":[
        "Jampani"
    ],
    "name:eng_x_variant":[
        "J\u0101mp\u0101ni"
    ],
    "wof:name":"Jampani",
    "wof:placetype":"locality",
    "wof:population":117
},
  "geometry": {"coordinates":[84.53746700000001,22.472603],"type":"Point"}
}