{
  "type": "Feature",
  "properties": {
    "iso:country":"IN",
    "ks:ks_name":"Balibhata",
    "ks:ks_pop":53,
    "ks:ks_type":"HABITATION",
    "name:eng_x_preferred":[
        "Balibhata"
    ],
    "wof:name":"Balibhata",
    "wof:placetype":"locality",
    "wof:population":53
},
  "geometry": {"coordinates":[83.429563,19.776716],"type":"Point"}
}