{
  "type": "Feature",
  "properties": {
    "iso:country":"IN",
    "ks:ks_name":"Puttaganasara",
    "ks:ks_pop":64,
    "ks:ks_type":"HABITATION",
    "name:eng_x_preferred":[
        "Puttaganasara"
    ],
    "wof:name":"Puttaganasara",
    "wof:placetype":"locality",
    "wof:population":64
},
  "geometry": {"coordinates":[75.292748,13.434726],"type":"Point"}
}