{
  "type": "Feature",
  "properties": {
    "gn:admin1_code":"34.0",
    "gn:admin2_code":"234.0",
    "gn:asciiname":"Barana",
    "gn:country_code":"IN",
    "gn:dem":97,
    "gn:feature_class":"P",
    "gn:feature_code":"PPL",
    "gn:name":"Barana",
    "gn:population":0,
    "gn:timezone":"Asia/Kolkata",
    "iso:country":"IN",
    "name:fas_x_preferred":[
        "\u0628\u0631\u0627\u0646\u0627"
    ],
    "name:urd_x_preferred":[
        "\u0628\u0631\u0627\u0646\u0627"
    ],
    "wof:name":"Barana",
    "wof:placetype":"locality"
},
  "geometry": {"coordinates":[84.23196999999998,25.1175],"type":"Point"}
}