{
  "type": "Feature",
  "properties": {
    "iso:country":"IN",
    "ks:ks_name":"Hapaiya Bari",
    "ks:ks_pop":212,
    "ks:ks_type":"HABITATION",
    "name:eng_x_preferred":[
        "Hapaiya Bari"
    ],
    "wof:name":"Hapaiya Bari",
    "wof:placetype":"locality",
    "wof:population":212
},
  "geometry": {"coordinates":[91.707297,23.483328],"type":"Point"}
}