{
  "type": "Feature",
  "properties": {
    "iso:country":"IN",
    "ks:ks_name":"Padasahi",
    "ks:ks_pop":377,
    "ks:ks_type":"VILLAGE",
    "ks:ks_uagg_main":0,
    "name:eng_x_preferred":[
        "Padasahi"
    ],
    "wof:name":"Padasahi",
    "wof:placetype":"neighbourhood",
    "wof:population":377
},
  "geometry": {"coordinates":[86.08681900000001,20.342371],"type":"Point"}
}