{
  "type": "Feature",
  "properties": {
    "iso:country":"IN",
    "ks:ks_name":"Mathauni Grazing",
    "ks:ks_pop":58,
    "ks:ks_type":"HABITATION",
    "name:eng_x_preferred":[
        "Mathauni Grazing"
    ],
    "wof:name":"Mathauni Grazing",
    "wof:placetype":"locality",
    "wof:population":58
},
  "geometry": {"coordinates":[95.15402400000001,27.318338],"type":"Point"}
}