{
  "type": "Feature",
  "properties": {
    "gn:admin1_code":"11.0",
    "gn:admin2_code":"23.0",
    "gn:asciiname":"Naghiar",
    "gn:country_code":"IN",
    "gn:dem":1452,
    "gn:feature_class":"P",
    "gn:feature_code":"PPL",
    "gn:name":"Naghi\u0101r",
    "gn:population":0,
    "gn:timezone":"Asia/Kolkata",
    "iso:country":"IN",
    "wof:name":"Naghiar",
    "wof:placetype":"locality"
},
  "geometry": {"coordinates":[75.99075000000001,32.47608],"type":"Point"}
}