{
  "type": "Feature",
  "properties": {
    "gn:admin1_code":"12",
    "gn:asciiname":"Jawand",
    "gn:country_code":"IN",
    "gn:dem":1633,
    "gn:feature_class":"P",
    "gn:feature_code":"PPL",
    "gn:name":"J\u0101wand",
    "gn:population":0,
    "gn:timezone":"Asia/Kolkata",
    "iso:country":"IN",
    "name:urd_x_preferred":[
        "\u062c\u0648\u0646\u062f"
    ],
    "wof:name":"Jawand",
    "wof:placetype":"locality"
},
  "geometry": {"coordinates":[74.22164000000002,34.1514],"type":"Point"}
}