{
  "type": "Feature",
  "properties": {
    "iso:country":"IN",
    "ks:ks_name":"Churahi",
    "ks:ks_pop":0,
    "ks:ks_type":"VILLAGE",
    "name:eng_x_preferred":[
        "Churahi"
    ],
    "wof:name":"Churahi",
    "wof:placetype":"locality",
    "wof:population":0
},
  "geometry": {"coordinates":[84.14634100000001,26.99638],"type":"Point"}
}