{
  "type": "Feature",
  "properties": {
    "iso:country":"IN",
    "ks:ks_name":"Kulpat",
    "ks:ks_pop":266,
    "ks:ks_type":"VILLAGE",
    "name:eng_x_preferred":[
        "Kulpat"
    ],
    "wof:name":"Kulpat",
    "wof:placetype":"locality",
    "wof:population":266
},
  "geometry": {"coordinates":[84.07176200000001,18.978473],"type":"Point"}
}