{
  "type": "Feature",
  "properties": {
    "gn:admin1_code":"19.0",
    "gn:admin2_code":"575.0",
    "gn:asciiname":"Munnuru",
    "gn:country_code":"IN",
    "gn:dem":59,
    "gn:feature_class":"P",
    "gn:feature_code":"PPLL",
    "gn:name":"Munn\u016bru",
    "gn:population":0,
    "gn:timezone":"Asia/Kolkata",
    "iso:country":"IN",
    "name:vie_x_preferred":[
        "Munnuru"
    ],
    "wof:name":"Munnuru",
    "wof:placetype":"locality"
},
  "geometry": {"coordinates":[74.88025999999998,12.8283],"type":"Point"}
}