{
  "type": "Feature",
  "properties": {
    "gn:admin1_code":"16",
    "gn:admin2_code":"500.0",
    "gn:asciiname":"Takarkhed",
    "gn:country_code":"IN",
    "gn:dem":308,
    "gn:feature_class":"P",
    "gn:feature_code":"PPL",
    "gn:name":"T\u0101karkhed",
    "gn:population":0,
    "gn:timezone":"Asia/Kolkata",
    "iso:country":"IN",
    "wof:name":"Takarkhed",
    "wof:placetype":"locality"
},
  "geometry": {"coordinates":[76.28121,20.73211],"type":"Point"}
}