{
  "type": "Feature",
  "properties": {
    "gn:admin1_code":"10.0",
    "gn:admin2_code":"076",
    "gn:asciiname":"Farmana",
    "gn:country_code":"IN",
    "gn:dem":229,
    "gn:feature_class":"P",
    "gn:feature_code":"PPL",
    "gn:name":"Farm\u0101na",
    "gn:population":0,
    "gn:timezone":"Asia/Kolkata",
    "iso:country":"IN",
    "name:und_x_variant":[
        "Farm\u0101nah",
        "Farm\u0101na"
    ],
    "wof:name":"Farmana",
    "wof:placetype":"locality"
},
  "geometry": {"coordinates":[76.81223,28.98387],"type":"Point"}
}