{
  "type": "Feature",
  "properties": {
    "iso:country":"IN",
    "ks:ks_alt_nam":"sevalal nagar",
    "ks:ks_name":"Sevalal Nagar",
    "ks:ks_pop":566,
    "ks:ks_type":"HABITATION",
    "name:eng_x_preferred":[
        "Sevalal Nagar"
    ],
    "wof:name":"Sevalal Nagar",
    "wof:placetype":"locality",
    "wof:population":566
},
  "geometry": {"coordinates":[76.17429199999999,17.450849],"type":"Point"}
}