{
  "type": "Feature",
  "properties": {
    "gn:admin1_code":"19.0",
    "gn:admin2_code":"573.0",
    "gn:asciiname":"Machalagatta",
    "gn:country_code":"IN",
    "gn:dem":862,
    "gn:feature_class":"P",
    "gn:feature_code":"PPL",
    "gn:name":"M\u0101chalagatta",
    "gn:population":0,
    "gn:timezone":"Asia/Kolkata",
    "iso:country":"IN",
    "wof:name":"Machalagatta",
    "wof:placetype":"locality"
},
  "geometry": {"coordinates":[76.70241999999998,12.68509],"type":"Point"}
}