{
  "type": "Feature",
  "properties": {
    "gn:admin1_code":"34.0",
    "gn:admin2_code":"209.0",
    "gn:asciiname":"Pokharia",
    "gn:country_code":"IN",
    "gn:dem":64,
    "gn:feature_class":"P",
    "gn:feature_code":"PPL",
    "gn:name":"Pokharia",
    "gn:population":0,
    "gn:timezone":"Asia/Kathmandu",
    "iso:country":"IN",
    "name:hif_x_preferred":[
        "Pokharia"
    ],
    "wof:name":"Pokharia",
    "wof:placetype":"locality"
},
  "geometry": {"coordinates":[87.31663,26.36468],"type":"Point"}
}