{
  "type": "Feature",
  "properties": {
    "iso:country":"IN",
    "ks:ks_alt_nam":"Chit\u0101ri",
    "ks:ks_name":"Chitari",
    "ks:ks_pop":28,
    "ks:ks_type":"VILLAGE",
    "ks:ks_uagg_main":0,
    "name:eng_x_preferred":[
        "Chitari"
    ],
    "name:eng_x_variant":[
        "Chit\u0101ri"
    ],
    "wof:name":"Chitari",
    "wof:placetype":"neighbourhood",
    "wof:population":28
},
  "geometry": {"coordinates":[82.100521,26.112342],"type":"Point"}
}