{
  "type": "Feature",
  "properties": {
    "iso:country":"IN",
    "ks:ks_name":"Ammachi",
    "ks:ks_pop":30,
    "ks:ks_type":"HABITATION",
    "name:eng_x_preferred":[
        "Ammachi"
    ],
    "wof:name":"Ammachi",
    "wof:placetype":"locality",
    "wof:population":30
},
  "geometry": {"coordinates":[74.785661,14.545852],"type":"Point"}
}