{
  "type": "Feature",
  "properties": {
    "iso:country":"IN",
    "ks:ks_name":"Bramhinwadi",
    "ks:ks_pop":62,
    "ks:ks_type":"HABITATION",
    "name:eng_x_preferred":[
        "Bramhinwadi"
    ],
    "wof:name":"Bramhinwadi",
    "wof:placetype":"locality",
    "wof:population":62
},
  "geometry": {"coordinates":[73.422775,17.254397],"type":"Point"}
}