{
  "type": "Feature",
  "properties": {
    "iso:country":"IN",
    "ks:ks_name":"Deonagar",
    "ks:ks_pop":275,
    "ks:ks_type":"HABITATION",
    "name:eng_x_preferred":[
        "Deonagar"
    ],
    "wof:name":"Deonagar",
    "wof:placetype":"locality",
    "wof:population":275
},
  "geometry": {"coordinates":[72.54995599999999,26.311981],"type":"Point"}
}