{
  "type": "Feature",
  "properties": {
    "gn:admin1_code":"10",
    "gn:admin2_code":"85.0",
    "gn:asciiname":"Kanhauri",
    "gn:country_code":"IN",
    "gn:dem":223,
    "gn:feature_class":"P",
    "gn:feature_code":"PPL",
    "gn:name":"Kanhauri",
    "gn:population":0,
    "gn:timezone":"Asia/Kolkata",
    "iso:country":"IN",
    "wof:name":"Kanhauri",
    "wof:placetype":"locality"
},
  "geometry": {"coordinates":[76.61359,28.41282],"type":"Point"}
}