{
  "type": "Feature",
  "properties": {
    "gn:admin1_code":"37.0",
    "gn:admin2_code":"413.0",
    "gn:asciiname":"Nawapara",
    "gn:country_code":"IN",
    "gn:dem":373,
    "gn:feature_class":"P",
    "gn:feature_code":"PPL",
    "gn:name":"Naw\u0101p\u0101ra",
    "gn:population":0,
    "gn:timezone":"Asia/Kolkata",
    "iso:country":"IN",
    "name:und_x_variant":[
        "Naw\u0101p\u0101ra",
        "B\u0101rgari"
    ],
    "wof:name":"Nawapara",
    "wof:placetype":"neighbourhood"
},
  "geometry": {"coordinates":[81.34815999999999,20.47508],"type":"Point"}
}