{
  "type": "Feature",
  "properties": {
    "iso:country":"IN",
    "ks:ks_name":"Lolki",
    "ks:ks_pop":1113,
    "ks:ks_type":"VILLAGE",
    "name:eng_x_preferred":[
        "Lolki"
    ],
    "wof:name":"Lolki",
    "wof:placetype":"locality",
    "wof:population":1113
},
  "geometry": {"coordinates":[83.245606,23.550363],"type":"Point"}
}