{
  "type": "Feature",
  "properties": {
    "gn:admin1_code":"16.0",
    "gn:admin2_code":"525",
    "gn:asciiname":"Khamaswari",
    "gn:country_code":"IN",
    "gn:dem":680,
    "gn:feature_class":"P",
    "gn:feature_code":"PPL",
    "gn:name":"Kh\u0101masw\u0101ri",
    "gn:population":0,
    "gn:timezone":"Asia/Kolkata",
    "iso:country":"IN",
    "name:und_x_variant":[
        "Khamswadi",
        "Kh\u0101masw\u0101ri"
    ],
    "wof:name":"Khamaswari",
    "wof:placetype":"locality"
},
  "geometry": {"coordinates":[76.04465,18.45672],"type":"Point"}
}