{
  "type": "Feature",
  "properties": {
    "gn:admin1_code":"11.0",
    "gn:admin2_code":"32.0",
    "gn:asciiname":"Chuli",
    "gn:country_code":"IN",
    "gn:dem":958,
    "gn:feature_class":"P",
    "gn:feature_code":"PPL",
    "gn:name":"Ch\u016bli",
    "gn:population":0,
    "gn:timezone":"Asia/Kolkata",
    "iso:country":"IN",
    "name:fin_x_preferred":[
        "Chuli"
    ],
    "name:glg_x_preferred":[
        "Chuli"
    ],
    "name:ita_x_preferred":[
        "Chuli"
    ],
    "name:pol_x_preferred":[
        "Manuel V\u00e1zquez"
    ],
    "name:spa_x_preferred":[
        "Chuli"
    ],
    "name:tgk_x_preferred":[
        "\u041a\u0443\u043b\u0438"
    ],
    "wof:name":"Chuli",
    "wof:placetype":"locality"
},
  "geometry": {"coordinates":[77.42675,30.60327],"type":"Point"}
}