{
  "type": "Feature",
  "properties": {
    "iso:country":"IN",
    "ks:ks_alt_nam":"Maremma camp",
    "ks:ks_name":"Maremma Camp",
    "ks:ks_pop":55,
    "ks:ks_type":"HABITATION",
    "name:eng_x_preferred":[
        "Maremma Camp"
    ],
    "wof:name":"Maremma Camp",
    "wof:placetype":"locality",
    "wof:population":55
},
  "geometry": {"coordinates":[76.65618000000001,15.447438],"type":"Point"}
}