{
  "type": "Feature",
  "properties": {
    "iso:country":"IN",
    "ks:ks_name":"Kotrapara",
    "ks:ks_pop":133,
    "ks:ks_type":"HABITATION",
    "name:eng_x_preferred":[
        "Kotrapara"
    ],
    "wof:name":"Kotrapara",
    "wof:placetype":"locality",
    "wof:population":133
},
  "geometry": {"coordinates":[83.52585000000001,22.357015],"type":"Point"}
}