{
  "type": "Feature",
  "properties": {
    "gn:admin1_code":"36",
    "gn:admin2_code":"144.0",
    "gn:asciiname":"Tarphara",
    "gn:country_code":"IN",
    "gn:dem":179,
    "gn:feature_class":"P",
    "gn:feature_code":"PPL",
    "gn:name":"Tarphara",
    "gn:population":0,
    "gn:timezone":"Asia/Kolkata",
    "iso:country":"IN",
    "wof:name":"Tarphara",
    "wof:placetype":"locality"
},
  "geometry": {"coordinates":[78.06795,27.57758],"type":"Point"}
}