{
  "type": "Feature",
  "properties": {
    "iso:country":"IN",
    "ks:ks_alt_nam":"MARWA KHAS",
    "ks:ks_name":"Marwa Khas",
    "ks:ks_pop":70,
    "ks:ks_type":"HABITATION",
    "name:eng_x_preferred":[
        "Marwa Khas"
    ],
    "wof:name":"Marwa Khas",
    "wof:placetype":"locality",
    "wof:population":70
},
  "geometry": {"coordinates":[84.874916,26.114701],"type":"Point"}
}