{
  "type": "Feature",
  "properties": {
    "iso:country":"IN",
    "ks:ks_name":"Patkhauli",
    "ks:ks_pop":277,
    "ks:ks_type":"HABITATION",
    "ks:ks_uagg_main":0,
    "name:eng_x_preferred":[
        "Patkhauli"
    ],
    "wof:name":"Patkhauli",
    "wof:placetype":"neighbourhood",
    "wof:population":277
},
  "geometry": {"coordinates":[84.342977,25.860868],"type":"Point"}
}