{
  "type": "Feature",
  "properties": {
    "iso:country":"IN",
    "ks:ks_name":"Karapalapampudur",
    "ks:ks_pop":202,
    "ks:ks_type":"HABITATION",
    "ks:ks_uagg_main":0,
    "name:eng_x_preferred":[
        "Karapalapampudur"
    ],
    "wof:name":"Karapalapampudur",
    "wof:placetype":"neighbourhood",
    "wof:population":202
},
  "geometry": {"coordinates":[77.113882,11.267137],"type":"Point"}
}