{
  "type": "Feature",
  "properties": {
    "gn:admin1_code":"36",
    "gn:admin2_code":"172.0",
    "gn:asciiname":"Baragaon",
    "gn:country_code":"IN",
    "gn:dem":122,
    "gn:feature_class":"P",
    "gn:feature_code":"PPL",
    "gn:name":"Bar\u0101g\u0101on",
    "gn:population":0,
    "gn:timezone":"Asia/Kolkata",
    "iso:country":"IN",
    "name:ita_x_preferred":[
        "Baragaon"
    ],
    "name:nld_x_preferred":[
        "Baragaon"
    ],
    "name:pol_x_preferred":[
        "Baragaon"
    ],
    "wof:name":"Baragaon",
    "wof:placetype":"locality"
},
  "geometry": {"coordinates":[80.88986,26.02179],"type":"Point"}
}