{
  "type": "Feature",
  "properties": {
    "iso:country":"IN",
    "ks:ks_name":"Bhattikhora",
    "ks:ks_pop":22,
    "ks:ks_type":"VILLAGE",
    "name:eng_x_preferred":[
        "Bhattikhora"
    ],
    "wof:name":"Bhattikhora",
    "wof:placetype":"locality",
    "wof:population":22
},
  "geometry": {"coordinates":[78.607286,30.001091],"type":"Point"}
}