{
  "type": "Feature",
  "properties": {
    "iso:country":"IN",
    "ks:ks_name":"K G Hatti",
    "ks:ks_pop":105,
    "ks:ks_type":"HABITATION",
    "name:eng_x_preferred":[
        "K G Hatti"
    ],
    "wof:name":"K G Hatti",
    "wof:placetype":"locality",
    "wof:population":105
},
  "geometry": {"coordinates":[76.795185,13.07521],"type":"Point"}
}