{
  "type": "Feature",
  "properties": {
    "gn:admin1_code":"16.0",
    "gn:admin2_code":"499.0",
    "gn:asciiname":"Maskavad Sim",
    "gn:country_code":"IN",
    "gn:dem":225,
    "gn:feature_class":"P",
    "gn:feature_code":"PPL",
    "gn:name":"Mask\u0101vad Sim",
    "gn:population":0,
    "gn:timezone":"Asia/Kolkata",
    "iso:country":"IN",
    "ks:ks_name":"Maskawad Sim",
    "ks:ks_pop":1998,
    "ks:ks_type":"VILLAGE",
    "ks:ks_uagg_main":0,
    "name:eng_x_preferred":[
        "Maskawad Sim"
    ],
    "wof:name":"Maskawad Sim",
    "wof:placetype":"neighbourhood",
    "wof:population":1998
},
  "geometry": {"coordinates":[75.909447,21.139022],"type":"Point"}
}