{
  "type": "Feature",
  "properties": {
    "iso:country":"IN",
    "ks:ks_name":"Kurrapalem",
    "ks:ks_pop":511,
    "ks:ks_type":"HABITATION",
    "ks:ks_uagg_main":0,
    "name:eng_x_preferred":[
        "Kurrapalem"
    ],
    "wof:name":"Kurrapalem",
    "wof:placetype":"neighbourhood",
    "wof:population":511
},
  "geometry": {"coordinates":[80.24351,15.922425],"type":"Point"}
}