{
  "type": "Feature",
  "properties": {
    "iso:country":"IN",
    "ks:ks_name":"Gilalgundi",
    "ks:ks_pop":19,
    "ks:ks_type":"HABITATION",
    "name:eng_x_preferred":[
        "Gilalgundi"
    ],
    "wof:name":"Gilalgundi",
    "wof:placetype":"locality",
    "wof:population":19
},
  "geometry": {"coordinates":[74.83267600000001,14.206446],"type":"Point"}
}