{
  "type": "Feature",
  "properties": {
    "iso:country":"IN",
    "ks:ks_name":"Harijanpada",
    "ks:ks_pop":174,
    "ks:ks_type":"HABITATION",
    "name:eng_x_preferred":[
        "Harijanpada"
    ],
    "wof:name":"Harijanpada",
    "wof:placetype":"locality",
    "wof:population":174
},
  "geometry": {"coordinates":[82.94483,19.608956],"type":"Point"}
}