{
  "type": "Feature",
  "properties": {
    "iso:country":"IN",
    "ks:ks_name":"Hanumanpura",
    "ks:ks_pop":166,
    "ks:ks_type":"HABITATION",
    "name:eng_x_preferred":[
        "Hanumanpura"
    ],
    "wof:name":"Hanumanpura",
    "wof:placetype":"locality",
    "wof:population":166
},
  "geometry": {"coordinates":[73.189722,23.147111],"type":"Point"}
}