{
  "type": "Feature",
  "properties": {
    "gn:admin1_code":"36.0",
    "gn:admin2_code":"134.0",
    "gn:asciiname":"Asafabad Chaman",
    "gn:country_code":"IN",
    "gn:dem":229,
    "gn:feature_class":"P",
    "gn:feature_code":"PPL",
    "gn:name":"Asaf\u0101b\u0101d Chaman",
    "gn:population":0,
    "gn:timezone":"Asia/Kolkata",
    "iso:country":"IN",
    "wof:name":"Asafabad Chaman",
    "wof:placetype":"locality"
},
  "geometry": {"coordinates":[78.67014,29.35183],"type":"Point"}
}