{
  "type": "Feature",
  "properties": {
    "gn:admin1_code":"19.0",
    "gn:admin2_code":"573.0",
    "gn:asciiname":"Gangadihalli",
    "gn:country_code":"IN",
    "gn:dem":904,
    "gn:feature_class":"P",
    "gn:feature_code":"PPL",
    "gn:name":"Gangadihalli",
    "gn:population":0,
    "gn:timezone":"Asia/Kolkata",
    "iso:country":"IN",
    "wof:name":"Gangadihalli",
    "wof:placetype":"locality"
},
  "geometry": {"coordinates":[76.68378,12.85315],"type":"Point"}
}