{
  "type": "Feature",
  "properties": {
    "iso:country":"IN",
    "ks:ks_name":"Periyadka",
    "ks:ks_pop":440,
    "ks:ks_type":"HABITATION",
    "name:eng_x_preferred":[
        "Periyadka"
    ],
    "wof:name":"Periyadka",
    "wof:placetype":"locality",
    "wof:population":440
},
  "geometry": {"coordinates":[75.305483,12.747068],"type":"Point"}
}