{
  "type": "Feature",
  "properties": {
    "gn:admin1_code":"11",
    "gn:admin2_code":"23.0",
    "gn:asciiname":"Phultwas",
    "gn:country_code":"IN",
    "gn:dem":2113,
    "gn:feature_class":"P",
    "gn:feature_code":"PPL",
    "gn:name":"Phultw\u0101s",
    "gn:population":0,
    "gn:timezone":"Asia/Kolkata",
    "iso:country":"IN",
    "wof:name":"Phultwas",
    "wof:placetype":"locality"
},
  "geometry": {"coordinates":[76.16981,32.85019],"type":"Point"}
}