{
  "type": "Feature",
  "properties": {
    "iso:country":"IN",
    "ks:ks_name":"8 AMP",
    "ks:ks_pop":34,
    "ks:ks_type":"VILLAGE",
    "name:eng_x_preferred":[
        "8 AMP"
    ],
    "wof:name":"8 AMP",
    "wof:placetype":"locality",
    "wof:population":34
},
  "geometry": {"coordinates":[74.38578800000001,29.844323],"type":"Point"}
}