{
  "type": "Feature",
  "properties": {
    "iso:country":"IN",
    "ks:ks_name":"Bogulakeravadi",
    "ks:ks_pop":328,
    "ks:ks_type":"HABITATION",
    "name:eng_x_preferred":[
        "Bogulakeravadi"
    ],
    "wof:name":"Bogulakeravadi",
    "wof:placetype":"locality",
    "wof:population":328
},
  "geometry": {"coordinates":[74.27240399999999,14.889003],"type":"Point"}
}