{
  "type": "Feature",
  "properties": {
    "gn:admin1_code":"19.0",
    "gn:admin2_code":"568.0",
    "gn:asciiname":"Kottekoppa",
    "gn:country_code":"IN",
    "gn:dem":617,
    "gn:feature_class":"P",
    "gn:feature_code":"PPL",
    "gn:name":"Kottekoppa",
    "gn:population":0,
    "gn:timezone":"Asia/Kolkata",
    "iso:country":"IN",
    "ks:ks_alt_nam":"kotekoppa",
    "ks:ks_name":"Kotekoppa",
    "ks:ks_pop":174,
    "ks:ks_type":"HABITATION",
    "name:eng_x_preferred":[
        "Kotekoppa"
    ],
    "name:eng_x_variant":[
        "Kottekoppa"
    ],
    "wof:name":"Kotekoppa",
    "wof:placetype":"locality",
    "wof:population":174
},
  "geometry": {"coordinates":[75.31726500000001,13.679671],"type":"Point"}
}