{
  "type": "Feature",
  "properties": {
    "iso:country":"IN",
    "ks:ks_name":"Bidrupane",
    "ks:ks_pop":76,
    "ks:ks_type":"HABITATION",
    "name:eng_x_preferred":[
        "Bidrupane"
    ],
    "wof:name":"Bidrupane",
    "wof:placetype":"locality",
    "wof:population":76
},
  "geometry": {"coordinates":[75.813056,12.314167],"type":"Point"}
}