{
  "type": "Feature",
  "properties": {
    "gn:admin1_code":"24.0",
    "gn:admin2_code":"124.0",
    "gn:asciiname":"Ramsor",
    "gn:country_code":"IN",
    "gn:dem":192,
    "gn:feature_class":"P",
    "gn:feature_code":"PPL",
    "gn:name":"R\u0101msor",
    "gn:population":0,
    "gn:timezone":"Asia/Kolkata",
    "iso:country":"IN",
    "wof:name":"Ramsor",
    "wof:placetype":"locality"
},
  "geometry": {"coordinates":[73.78876,23.47962],"type":"Point"}
}