{
  "type": "Feature",
  "properties": {
    "iso:country":"IN",
    "ks:ks_name":"Tamboli Hagarewasti",
    "ks:ks_pop":228,
    "ks:ks_type":"HABITATION",
    "name:eng_x_preferred":[
        "Tamboli Hagarewasti"
    ],
    "wof:name":"Tamboli Hagarewasti",
    "wof:placetype":"locality",
    "wof:population":228
},
  "geometry": {"coordinates":[74.86799999999999,18.08],"type":"Point"}
}