{
  "type": "Feature",
  "properties": {
    "iso:country":"IN",
    "ks:ks_name":"Road Purva",
    "ks:ks_pop":27,
    "ks:ks_type":"HABITATION",
    "name:eng_x_preferred":[
        "Road Purva"
    ],
    "wof:name":"Road Purva",
    "wof:placetype":"locality",
    "wof:population":27
},
  "geometry": {"coordinates":[83.393339,26.3813],"type":"Point"}
}