{
  "type": "Feature",
  "properties": {
    "iso:country":"IN",
    "ks:ks_name":"Tola Kadmatanr",
    "ks:ks_pop":113,
    "ks:ks_type":"VILLAGE",
    "name:eng_x_preferred":[
        "Tola Kadmatanr"
    ],
    "wof:name":"Tola Kadmatanr",
    "wof:placetype":"locality",
    "wof:population":113
},
  "geometry": {"coordinates":[86.83185,24.610242],"type":"Point"}
}