{
  "type": "Feature",
  "properties": {
    "gn:admin1_code":"16",
    "gn:admin2_code":"507.0",
    "gn:asciiname":"Pujaritola",
    "gn:country_code":"IN",
    "gn:dem":286,
    "gn:feature_class":"P",
    "gn:feature_code":"PPL",
    "gn:name":"Puj\u0101ritola",
    "gn:population":0,
    "gn:timezone":"Asia/Kolkata",
    "iso:country":"IN",
    "wof:name":"Pujaritola",
    "wof:placetype":"locality"
},
  "geometry": {"coordinates":[80.14398,20.93742],"type":"Point"}
}