{
  "type": "Feature",
  "properties": {
    "iso:country":"IN",
    "ks:ks_name":"Qasampur",
    "ks:ks_pop":3,
    "ks:ks_type":"HABITATION",
    "name:eng_x_preferred":[
        "Qasampur"
    ],
    "wof:name":"Qasampur",
    "wof:placetype":"locality",
    "wof:population":3
},
  "geometry": {"coordinates":[77.056228,30.543444],"type":"Point"}
}