{
  "type": "Feature",
  "properties": {
    "gn:admin1_code":"35.0",
    "gn:admin2_code":"454.0",
    "gn:asciiname":"Bhikampur",
    "gn:country_code":"IN",
    "gn:dem":650,
    "gn:feature_class":"P",
    "gn:feature_code":"PPL",
    "gn:name":"Bh\u012bkampur",
    "gn:population":0,
    "gn:timezone":"Asia/Kolkata",
    "iso:country":"IN",
    "name:ara_x_preferred":[
        "\u0628\u064a\u0643\u0627\u0645\u0628\u0648\u0631"
    ],
    "name:ben_bn_x_preferred":[
        "\u09ad\u09bf\u0995\u09ae\u09aa\u09c1\u09b0"
    ],
    "name:ben_in_x_preferred":[
        "\u09ad\u09bf\u0995\u09ae\u09aa\u09c1\u09b0"
    ],
    "name:guj_x_preferred":[
        "\u0aad\u0abf\u0a95\u0aae\u0aaa\u0ac1\u0ab0"
    ],
    "name:hin_x_preferred":[
        "\u092d\u0940\u0915\u092e\u092a\u0941\u0930"
    ],
    "name:kan_x_preferred":[
        "\u0cad\u0cbf\u0c95\u0cbe\u0cae\u0ccd"
    ],
    "name:mal_x_preferred":[
        "\u0d2d\u0d3f\u0d15\u0d3e\u0d02\u0d2a\u0d42\u0d7c"
    ],
    "name:mar_x_preferred":[
        "\u092d\u093f\u0915\u092e\u092a\u0942\u0930"
    ],
    "name:pan_x_preferred":[
        "\u0a2d\u0a40\u0a16\u0a2e\u0a2a\u0a41\u0a30"
    ],
    "name:tam_x_preferred":[
        "\u0baa\u0bbf\u0b95\u0bbe\u0bae\u0bcd\u0baa\u0bc2\u0bb0\u0bcd"
    ],
    "name:tel_x_preferred":[
        "\u0c2d\u0c3f\u0c15\u0c3e\u0c2e\u0c4d"
    ],
    "name:urd_x_preferred":[
        "\u0628\u06be\u06cc\u06a9\u0645 \u067e\u0648\u0631"
    ],
    "wof:name":"Bhikampur",
    "wof:placetype":"locality"
},
  "geometry": {"coordinates":[80.43424,23.08442],"type":"Point"}
}