{
  "type": "Feature",
  "properties": {
    "iso:country":"IN",
    "ks:ks_name":"Bibipur",
    "ks:ks_pop":612,
    "ks:ks_type":"HABITATION",
    "name:eng_x_preferred":[
        "Bibipur"
    ],
    "wof:name":"Bibipur",
    "wof:placetype":"locality",
    "wof:population":612
},
  "geometry": {"coordinates":[85.520037,25.325136],"type":"Point"}
}