{
  "type": "Feature",
  "properties": {
    "iso:country":"IN",
    "ks:ks_name":"Yegaon",
    "ks:ks_pop":1720,
    "ks:ks_type":"VILLAGE",
    "name:eng_x_preferred":[
        "Yegaon"
    ],
    "wof:name":"Yegaon",
    "wof:placetype":"locality",
    "wof:population":1720
},
  "geometry": {"coordinates":[73.581788,17.330037],"type":"Point"}
}