{
  "type": "Feature",
  "properties": {
    "gn:admin1_code":"19.0",
    "gn:admin2_code":"577.0",
    "gn:asciiname":"Asvala",
    "gn:country_code":"IN",
    "gn:dem":746,
    "gn:feature_class":"P",
    "gn:feature_code":"PPL",
    "gn:name":"Asv\u0101la",
    "gn:population":0,
    "gn:timezone":"Asia/Kolkata",
    "iso:country":"IN",
    "wof:name":"Asvala",
    "wof:placetype":"neighbourhood"
},
  "geometry": {"coordinates":[76.41164999999999,12.22258],"type":"Point"}
}