{
  "type": "Feature",
  "properties": {
    "gn:admin1_code":"36.0",
    "gn:admin2_code":"150.0",
    "gn:asciiname":"Aspur Dariao Singh",
    "gn:country_code":"IN",
    "gn:dem":179,
    "gn:feature_class":"P",
    "gn:feature_code":"PPL",
    "gn:name":"\u0100spur Dari\u0101o Singh",
    "gn:population":0,
    "gn:timezone":"Asia/Kolkata",
    "iso:country":"IN",
    "wof:name":"Aspur Dariao Singh",
    "wof:placetype":"locality"
},
  "geometry": {"coordinates":[79.72920999999999,28.50828],"type":"Point"}
}