{
  "type": "Feature",
  "properties": {
    "gn:admin1_code":"36.0",
    "gn:admin2_code":"150.0",
    "gn:asciiname":"Aspur Dariao Singh",
    "gn:country_code":"IN",
    "gn:dem":179,
    "gn:feature_class":"P",
    "gn:feature_code":"PPL",
    "gn:name":"\u0100spur Dari\u0101o Singh",
    "gn:population":0,
    "gn:timezone":"Asia/Kolkata",
    "iso:country":"IN",
    "ks:ks_alt_nam":"\u0100spur Dari\u0101o Singh",
    "ks:ks_name":"Aspur Dariao Singh",
    "ks:ks_type":"VILLAGE",
    "name:eng_x_preferred":[
        "Aspur Dariao Singh"
    ],
    "name:eng_x_variant":[
        "\u0100spur Dari\u0101o Singh"
    ],
    "wof:name":"Aspur Dariao Singh",
    "wof:placetype":"locality"
},
  "geometry": {"coordinates":[79.729213,28.508281],"type":"Point"}
}