{
  "type": "Feature",
  "properties": {
    "gn:admin1_code":"12.0",
    "gn:admin2_code":"16.0",
    "gn:asciiname":"Diron Kiran",
    "gn:country_code":"IN",
    "gn:dem":1139,
    "gn:feature_class":"P",
    "gn:feature_code":"PPL",
    "gn:name":"Diron Kir\u0101n",
    "gn:population":0,
    "gn:timezone":"Asia/Kolkata",
    "iso:country":"IN",
    "wof:name":"Diron Kiran",
    "wof:placetype":"locality"
},
  "geometry": {"coordinates":[75.68589,33.14807],"type":"Point"}
}