{
  "type": "Feature",
  "properties": {
    "iso:country":"IN",
    "ks:ks_name":"Nazat Gazikhali",
    "ks:ks_pop":1243,
    "ks:ks_type":"HABITATION",
    "name:eng_x_preferred":[
        "Nazat Gazikhali"
    ],
    "wof:name":"Nazat Gazikhali",
    "wof:placetype":"locality",
    "wof:population":1243
},
  "geometry": {"coordinates":[88.840879,22.431786],"type":"Point"}
}