{
  "type": "Feature",
  "properties": {
    "gn:admin1_code":"11",
    "gn:admin2_code":"23.0",
    "gn:asciiname":"Satun",
    "gn:country_code":"IN",
    "gn:dem":1974,
    "gn:feature_class":"P",
    "gn:feature_code":"PPL",
    "gn:name":"Sat\u016bn",
    "gn:population":0,
    "gn:timezone":"Asia/Kolkata",
    "iso:country":"IN",
    "name:ben_x_preferred":[
        "\u09b8\u09be\u09a4\u09c1\u09a8"
    ],
    "name:bod_x_preferred":[
        "\u0f66\u0f0b\u0f4a\u0f74\u0f53\u0f0d"
    ],
    "name:ceb_x_preferred":[
        "Satun"
    ],
    "name:deu_x_preferred":[
        "Satun"
    ],
    "name:ell_x_preferred":[
        "\u03a3\u03b1\u03c4\u03bf\u03cd\u03bd"
    ],
    "name:fas_x_preferred":[
        "\u0633\u0627\u062a\u0648\u0646"
    ],
    "name:fra_x_preferred":[
        "Satun"
    ],
    "name:heb_x_preferred":[
        "\u05e1\u05d0\u05d8\u05d5\u05df"
    ],
    "name:hin_x_preferred":[
        "\u0938\u0948\u091f\u0928"
    ],
    "name:hun_x_preferred":[
        "Satun"
    ],
    "name:ind_x_preferred":[
        "Satun"
    ],
    "name:ita_x_preferred":[
        "Satun"
    ],
    "name:nld_x_preferred":[
        "Satun"
    ],
    "name:pnb_x_preferred":[
        "\u0633\u0627\u0679\u0646"
    ],
    "name:pol_x_preferred":[
        "Satun"
    ],
    "name:por_x_preferred":[
        "Satun"
    ],
    "name:rus_x_preferred":[
        "\u0421\u0430\u0442\u0443\u043d"
    ],
    "name:spa_x_preferred":[
        "Satun"
    ],
    "name:swe_x_preferred":[
        "Satun"
    ],
    "name:tur_x_preferred":[
        "Satun"
    ],
    "name:ukr_x_preferred":[
        "\u0421\u0430\u0442\u0443\u043d"
    ],
    "name:urd_x_preferred":[
        "\u0633\u0627\u062a\u0648\u0646"
    ],
    "name:vie_x_preferred":[
        "Satun"
    ],
    "name:war_x_preferred":[
        "Satun"
    ],
    "name:zho_cn_x_preferred":[
        "\u6c99\u6566"
    ],
    "name:zho_tw_x_preferred":[
        "\u6c99\u6566"
    ],
    "wof:name":"Satun",
    "wof:placetype":"locality"
},
  "geometry": {"coordinates":[76.17089,32.45911],"type":"Point"}
}