{
  "type": "Feature",
  "properties": {
    "iso:country":"IN",
    "qs:name":"Shah Ganj",
    "qs:name_adm0":"India",
    "qs:name_adm1":"Delhi",
    "qs:photos":27,
    "qs:photos_1k":5,
    "qs:photos_9k":1,
    "qs:photos_9r":2,
    "qs:photos_all":27,
    "qs:photos_sr":2,
    "qs:placetype":"Suburb",
    "qs:pop_sr":"0",
    "wof:name":"Shah Ganj",
    "wof:placetype":"neighbourhood"
},
  "geometry": {"coordinates":[77.221695,28.649796],"type":"Point"}
}
},
  "geometry": {"coordinates":[77.221695,28.649796],"type":"Point"}
}