{
  "type": "Feature",
  "properties": {
    "iso:country":"IN",
    "ks:ks_name":"Saraiha Ryt.",
    "ks:ks_pop":372,
    "ks:ks_type":"VILLAGE",
    "name:eng_x_preferred":[
        "Saraiha Ryt."
    ],
    "wof:name":"Saraiha Ryt.",
    "wof:placetype":"locality",
    "wof:population":372
},
  "geometry": {"coordinates":[81.551751,22.652816],"type":"Point"}
}