{
  "type": "Feature",
  "properties": {
    "gn:admin1_code":"35",
    "gn:admin2_code":"450.0",
    "gn:asciiname":"Kusma",
    "gn:country_code":"IN",
    "gn:dem":384,
    "gn:feature_class":"P",
    "gn:feature_code":"PPL",
    "gn:name":"Kusma",
    "gn:population":0,
    "gn:timezone":"Asia/Kolkata",
    "iso:country":"IN",
    "name:ceb_x_preferred":[
        "Kusma"
    ],
    "name:est_x_preferred":[
        "Kusma"
    ],
    "name:pol_x_preferred":[
        "Kusma"
    ],
    "name:vol_x_preferred":[
        "Kusma"
    ],
    "wof:name":"Kusma",
    "wof:placetype":"locality"
},
  "geometry": {"coordinates":[80.72150000000001,24.04808],"type":"Point"}
}