{
  "type": "Feature",
  "properties": {
    "iso:country":"IN",
    "ks:ks_name":"Pusparam Para",
    "ks:ks_pop":260,
    "ks:ks_type":"HABITATION",
    "name:eng_x_preferred":[
        "Pusparam Para"
    ],
    "wof:name":"Pusparam Para",
    "wof:placetype":"locality",
    "wof:population":260
},
  "geometry": {"coordinates":[91.818658,23.838744],"type":"Point"}
}