{
  "type": "Feature",
  "properties": {
    "iso:country":"IN",
    "ks:ks_name":"Uttar Kalinagar",
    "ks:ks_pop":734,
    "ks:ks_type":"VILLAGE",
    "name:eng_x_preferred":[
        "Uttar Kalinagar"
    ],
    "wof:name":"Uttar Kalinagar",
    "wof:placetype":"locality",
    "wof:population":734
},
  "geometry": {"coordinates":[88.086333,22.134732],"type":"Point"}
}