{
  "type": "Feature",
  "properties": {
    "gn:admin1_code":"34.0",
    "gn:admin2_code":"233",
    "gn:asciiname":"Kudra",
    "gn:country_code":"IN",
    "gn:dem":93,
    "gn:feature_class":"P",
    "gn:feature_code":"PPL",
    "gn:name":"Kudra",
    "gn:population":0,
    "gn:timezone":"Asia/Kolkata",
    "iso:country":"IN",
    "name:und_x_variant":[
        "Jah\u0101n\u0101b\u0101d",
        "Jahan\u0101b\u0101d"
    ],
    "name:urd_x_preferred":[
        "\u06a9\u062f\u0631\u0627"
    ],
    "wof:name":"Kudra",
    "wof:placetype":"neighbourhood"
},
  "geometry": {"coordinates":[83.79261,25.04628],"type":"Point"}
}