{
  "type": "Feature",
  "properties": {
    "iso:country":"IN",
    "ks:ks_name":"Magarwadi",
    "ks:ks_pop":647,
    "ks:ks_type":"VILLAGE",
    "name:eng_x_preferred":[
        "Magarwadi"
    ],
    "wof:name":"Magarwadi",
    "wof:placetype":"locality",
    "wof:population":647
},
  "geometry": {"coordinates":[74.30119999999999,18.1544],"type":"Point"}
}