{
  "type": "Feature",
  "properties": {
    "iso:country":"IN",
    "ks:ks_name":"Darjipada",
    "ks:ks_pop":349,
    "ks:ks_type":"HABITATION",
    "name:eng_x_preferred":[
        "Darjipada"
    ],
    "wof:name":"Darjipada",
    "wof:placetype":"locality",
    "wof:population":349
},
  "geometry": {"coordinates":[72.753,20.121417],"type":"Point"}
}