{
  "type": "Feature",
  "properties": {
    "iso:country":"IN",
    "ks:ks_name":"Kusumpura",
    "ks:ks_pop":530,
    "ks:ks_type":"VILLAGE",
    "name:eng_x_preferred":[
        "Kusumpura"
    ],
    "wof:name":"Kusumpura",
    "wof:placetype":"locality",
    "wof:population":530
},
  "geometry": {"coordinates":[75.55945699999999,21.980192],"type":"Point"}
}