{
  "type": "Feature",
  "properties": {
    "gn:admin1_code":"35.0",
    "gn:asciiname":"Anturli",
    "gn:country_code":"IN",
    "gn:dem":235,
    "gn:feature_class":"P",
    "gn:feature_code":"PPL",
    "gn:name":"Anturli",
    "gn:population":0,
    "gn:timezone":"Asia/Kolkata",
    "iso:country":"IN",
    "wof:name":"Anturli",
    "wof:placetype":"locality"
},
  "geometry": {"coordinates":[76.13694,21.19667],"type":"Point"}
}