{
  "type": "Feature",
  "properties": {
    "gn:admin1_code":"12.0",
    "gn:admin2_code":"16.0",
    "gn:asciiname":"Dhadkai",
    "gn:country_code":"IN",
    "gn:dem":2222,
    "gn:feature_class":"P",
    "gn:feature_code":"PPL",
    "gn:name":"Dhadkai",
    "gn:population":0,
    "gn:timezone":"Asia/Kolkata",
    "iso:country":"IN",
    "wof:name":"Dhadkai",
    "wof:placetype":"locality"
},
  "geometry": {"coordinates":[75.90087,33.06215],"type":"Point"}
}