{
  "type": "Feature",
  "properties": {
    "gn:admin1_code":"36",
    "gn:admin2_code":"188.0",
    "gn:asciiname":"Lakhan Khurd",
    "gn:country_code":"IN",
    "gn:dem":84,
    "gn:feature_class":"P",
    "gn:feature_code":"PPL",
    "gn:name":"L\u0101khan Khurd",
    "gn:population":0,
    "gn:timezone":"Asia/Kolkata",
    "iso:country":"IN",
    "ks:ks_alt_nam":"L\u0101khan Khurd",
    "ks:ks_name":"Lakhan Khurd",
    "ks:ks_type":"VILLAGE",
    "ks:ks_uagg_main":0,
    "name:eng_x_preferred":[
        "Lakhan Khurd"
    ],
    "name:eng_x_variant":[
        "L\u0101khan Khurd"
    ],
    "wof:name":"Lakhan Khurd",
    "wof:placetype":"neighbourhood"
},
  "geometry": {"coordinates":[83.244294,26.518742],"type":"Point"}
}