{
  "type": "Feature",
  "properties": {
    "iso:country":"IN",
    "ks:ks_name":"Dhobadiha",
    "ks:ks_pop":182,
    "ks:ks_type":"VILLAGE",
    "name:eng_x_preferred":[
        "Dhobadiha"
    ],
    "wof:name":"Dhobadiha",
    "wof:placetype":"locality",
    "wof:population":182
},
  "geometry": {"coordinates":[86.259747,22.273017],"type":"Point"}
}