{
  "type": "Feature",
  "properties": {
    "gn:admin1_code":"36",
    "gn:admin2_code":"157.0",
    "gn:asciiname":"Miraknagar",
    "gn:country_code":"IN",
    "gn:dem":126,
    "gn:feature_class":"P",
    "gn:feature_code":"PPL",
    "gn:name":"Miraknagar",
    "gn:population":0,
    "gn:timezone":"Asia/Kolkata",
    "iso:country":"IN",
    "ks:ks_name":"Miraknagar",
    "ks:ks_type":"VILLAGE",
    "ks:ks_uagg_main":0,
    "name:eng_x_preferred":[
        "Miraknagar"
    ],
    "wof:name":"Miraknagar",
    "wof:placetype":"neighbourhood"
},
  "geometry": {"coordinates":[81.077646,26.576181],"type":"Point"}
}