{
  "type": "Feature",
  "properties": {
    "iso:country":"IN",
    "ks:ks_name":"Modakpara Sahapara",
    "ks:ks_pop":232,
    "ks:ks_type":"HABITATION",
    "ks:ks_uagg_main":0,
    "name:eng_x_preferred":[
        "Modakpara Sahapara"
    ],
    "wof:name":"Modakpara Sahapara",
    "wof:placetype":"neighbourhood",
    "wof:population":232
},
  "geometry": {"coordinates":[88.08755499999999,26.120531],"type":"Point"}
}