{
  "type": "Feature",
  "properties": {
    "iso:country":"IN",
    "ks:ks_name":"Kodhgeed",
    "ks:ks_pop":7,
    "ks:ks_type":"HABITATION",
    "name:eng_x_preferred":[
        "Kodhgeed"
    ],
    "wof:name":"Kodhgeed",
    "wof:placetype":"locality",
    "wof:population":7
},
  "geometry": {"coordinates":[79.179438,30.338852],"type":"Point"}
}