{
  "type": "Feature",
  "properties": {
    "iso:country":"IN",
    "ks:ks_name":"Baghnari",
    "ks:ks_pop":4,
    "ks:ks_type":"HABITATION",
    "name:eng_x_preferred":[
        "Baghnari"
    ],
    "wof:name":"Baghnari",
    "wof:placetype":"locality",
    "wof:population":4
},
  "geometry": {"coordinates":[81.457566,24.507235],"type":"Point"}
}