{
  "type": "Feature",
  "properties": {
    "gn:admin1_code":"34.0",
    "gn:admin2_code":"221.0",
    "gn:asciiname":"Baha",
    "gn:country_code":"IN",
    "gn:dem":42,
    "gn:feature_class":"P",
    "gn:feature_code":"PPL",
    "gn:name":"B\u0101ha",
    "gn:population":0,
    "gn:timezone":"Asia/Kolkata",
    "iso:country":"IN",
    "name:ceb_x_preferred":[
        "Baha"
    ],
    "name:deu_x_preferred":[
        "Baha"
    ],
    "name:msa_x_preferred":[
        "Baha"
    ],
    "name:pol_x_preferred":[
        "Baha"
    ],
    "name:rus_x_preferred":[
        "\u0411\u0430\u0445\u0430"
    ],
    "name:swe_x_preferred":[
        "Baha"
    ],
    "wof:name":"Baha",
    "wof:placetype":"locality"
},
  "geometry": {"coordinates":[86.36757,25.7306],"type":"Point"}
}