{
  "type": "Feature",
  "properties": {
    "iso:country":"IN",
    "ks:ks_name":"Charuyapara",
    "ks:ks_pop":22,
    "ks:ks_type":"HABITATION",
    "name:eng_x_preferred":[
        "Charuyapara"
    ],
    "wof:name":"Charuyapara",
    "wof:placetype":"locality",
    "wof:population":22
},
  "geometry": {"coordinates":[82.015652,19.892011],"type":"Point"}
}