{
  "type": "Feature",
  "properties": {
    "iso:country":"IN",
    "ks:ks_name":"Vadi Falia",
    "ks:ks_pop":133,
    "ks:ks_type":"HABITATION",
    "name:eng_x_preferred":[
        "Vadi Falia"
    ],
    "wof:name":"Vadi Falia",
    "wof:placetype":"locality",
    "wof:population":133
},
  "geometry": {"coordinates":[73.79594400000001,20.9415],"type":"Point"}
}