{
  "type": "Feature",
  "properties": {
    "gn:admin1_code":"38.0",
    "gn:admin2_code":"360.0",
    "gn:asciiname":"Bandua",
    "gn:country_code":"IN",
    "gn:dem":596,
    "gn:feature_class":"P",
    "gn:feature_code":"PPL",
    "gn:name":"Bandu\u0101",
    "gn:population":0,
    "gn:timezone":"Asia/Kolkata",
    "iso:country":"IN",
    "ks:ks_name":"Bandua",
    "ks:ks_pop":208,
    "ks:ks_type":"VILLAGE",
    "ks:ks_uagg_main":0,
    "name:cat_x_preferred":[
        "Bandua"
    ],
    "name:deu_x_preferred":[
        "Bandua"
    ],
    "name:eng_x_preferred":[
        "Bandua"
    ],
    "name:glg_x_preferred":[
        "Bandua"
    ],
    "name:por_x_preferred":[
        "Bandua"
    ],
    "name:zho_x_preferred":[
        "\u73ed\u8fbe"
    ],
    "wof:name":"Bandua",
    "wof:placetype":"neighbourhood",
    "wof:population":208
},
  "geometry": {"coordinates":[85.442972,24.094218],"type":"Point"}
}