{
  "type": "Feature",
  "properties": {
    "iso:country":"IN",
    "ks:ks_name":"Lalasar",
    "ks:ks_pop":637,
    "ks:ks_type":"HABITATION",
    "name:eng_x_preferred":[
        "Lalasar"
    ],
    "wof:name":"Lalasar",
    "wof:placetype":"locality",
    "wof:population":637
},
  "geometry": {"coordinates":[71.408053,24.802972],"type":"Point"}
}