{
  "type": "Feature",
  "properties": {
    "iso:country":"IN",
    "ks:ks_alt_nam":"chakalakunni SC colony",
    "ks:ks_name":"Chakalakunni Sc Colony",
    "ks:ks_pop":330,
    "ks:ks_type":"HABITATION",
    "name:eng_x_preferred":[
        "Chakalakunni Sc Colony"
    ],
    "wof:name":"Chakalakunni Sc Colony",
    "wof:placetype":"locality",
    "wof:population":330
},
  "geometry": {"coordinates":[75.699099,11.593165],"type":"Point"}
}