{
  "type": "Feature",
  "properties": {
    "gn:admin1_code":"24.0",
    "gn:admin2_code":"114.0",
    "gn:asciiname":"Khawai",
    "gn:country_code":"IN",
    "gn:dem":107,
    "gn:feature_class":"P",
    "gn:feature_code":"PPL",
    "gn:name":"Khaw\u0101i",
    "gn:population":0,
    "gn:timezone":"Asia/Kolkata",
    "iso:country":"IN",
    "name:und_x_variant":[
        "Khaw\u0101i",
        "Khew\u0101i"
    ],
    "wof:name":"Khawai",
    "wof:placetype":"locality"
},
  "geometry": {"coordinates":[71.44870999999998,27.82795],"type":"Point"}
}