{
  "type": "Feature",
  "properties": {
    "iso:country":"IN",
    "ks:ks_name":"Danya Lagga Dhura",
    "ks:ks_pop":63,
    "ks:ks_type":"VILLAGE",
    "ks:ks_uagg_main":0,
    "name:eng_x_preferred":[
        "Danya Lagga Dhura"
    ],
    "wof:name":"Danya Lagga Dhura",
    "wof:placetype":"neighbourhood",
    "wof:population":63
},
  "geometry": {"coordinates":[79.90713,29.572591],"type":"Point"}
}