{
  "type": "Feature",
  "properties": {
    "gn:admin1_code":"28.0",
    "gn:admin2_code":"337",
    "gn:asciiname":"Islampur",
    "gn:country_code":"IN",
    "gn:dem":14,
    "gn:feature_class":"P",
    "gn:feature_code":"PPL",
    "gn:name":"Isl\u0101mpur",
    "gn:population":0,
    "gn:timezone":"Asia/Kolkata",
    "iso:country":"IN",
    "ks:ks_name":"Isllampur",
    "ks:ks_pop":7146,
    "ks:ks_type":"HABITATION",
    "ks:ks_uagg_main":0,
    "name:ben_x_preferred":[
        "\u0987\u09b8\u09b2\u09be\u09ae\u09aa\u09c1\u09b0"
    ],
    "name:ceb_x_preferred":[
        "Islampur"
    ],
    "name:deu_x_preferred":[
        "Islampur"
    ],
    "name:eng_x_preferred":[
        "Isllampur"
    ],
    "name:new_x_preferred":[
        "\u0907\u0938\u094d\u0932\u093e\u092e\u092a\u0941\u0930"
    ],
    "name:ori_x_preferred":[
        "\u0b07\u0b38\u0b32\u0b3e\u0b2e\u0b2a\u0b41\u0b30"
    ],
    "name:swe_x_preferred":[
        "Islampur"
    ],
    "name:vie_x_preferred":[
        "Islampur"
    ],
    "wof:name":"Isllampur",
    "wof:placetype":"neighbourhood",
    "wof:population":7146
},
  "geometry": {"coordinates":[88.706461,22.99468],"type":"Point"}
}