{
  "type": "Feature",
  "properties": {
    "iso:country":"IN",
    "ks:ks_alt_nam":"panabandaru",
    "ks:ks_name":"Panabandaru",
    "ks:ks_pop":31,
    "ks:ks_type":"HABITATION",
    "name:eng_x_preferred":[
        "Panabandaru"
    ],
    "wof:name":"Panabandaru",
    "wof:placetype":"locality",
    "wof:population":31
},
  "geometry": {"coordinates":[84.533103,20.259265],"type":"Point"}
}