{
  "type": "Feature",
  "properties": {
    "iso:country":"IN",
    "ks:ks_name":"Gangadeigarh",
    "ks:ks_pop":666,
    "ks:ks_type":"HABITATION",
    "name:eng_x_preferred":[
        "Gangadeigarh"
    ],
    "wof:name":"Gangadeigarh",
    "wof:placetype":"locality",
    "wof:population":666
},
  "geometry": {"coordinates":[82.360659,20.740333],"type":"Point"}
}