{
  "type": "Feature",
  "properties": {
    "iso:country":"IN",
    "ks:ks_name":"Kuttithazham Padam",
    "ks:ks_pop":251,
    "ks:ks_type":"HABITATION",
    "name:eng_x_preferred":[
        "Kuttithazham Padam"
    ],
    "wof:name":"Kuttithazham Padam",
    "wof:placetype":"locality",
    "wof:population":251
},
  "geometry": {"coordinates":[76.03884100000001,10.703646],"type":"Point"}
}