{
  "type": "Feature",
  "properties": {
    "iso:country":"IN",
    "ks:ks_alt_nam":"AWATI HATTLI WASTI",
    "ks:ks_name":"Awati Hattli Wasti",
    "ks:ks_pop":176,
    "ks:ks_type":"HABITATION",
    "name:eng_x_preferred":[
        "Awati Hattli Wasti"
    ],
    "wof:name":"Awati Hattli Wasti",
    "wof:placetype":"locality",
    "wof:population":176
},
  "geometry": {"coordinates":[75.441599,17.232626],"type":"Point"}
}