{
  "type": "Feature",
  "properties": {
    "iso:country":"IN",
    "ks:ks_name":"Pansut",
    "ks:ks_pop":250,
    "ks:ks_type":"VILLAGE",
    "name:eng_x_preferred":[
        "Pansut"
    ],
    "wof:name":"Pansut",
    "wof:placetype":"locality",
    "wof:population":250
},
  "geometry": {"coordinates":[78.525791,30.480889],"type":"Point"}
}