{
  "type": "Feature",
  "properties": {
    "iso:country":"IN",
    "ks:ks_name":"Hosa Goddanakoppa",
    "ks:ks_pop":1172,
    "ks:ks_type":"HABITATION",
    "name:eng_x_preferred":[
        "Hosa Goddanakoppa"
    ],
    "wof:name":"Hosa Goddanakoppa",
    "wof:placetype":"locality",
    "wof:population":1172
},
  "geometry": {"coordinates":[75.38,14.31],"type":"Point"}
}