{
  "type": "Feature",
  "properties": {
    "gn:admin1_code":"34.0",
    "gn:admin2_code":"227.0",
    "gn:asciiname":"Manikpur",
    "gn:country_code":"IN",
    "gn:dem":60,
    "gn:feature_class":"P",
    "gn:feature_code":"PPL",
    "gn:name":"M\u0101nikpur",
    "gn:population":0,
    "gn:timezone":"Asia/Kolkata",
    "iso:country":"IN",
    "ks:ks_alt_nam":"M\u0101nikpur",
    "ks:ks_name":"Manikpur",
    "ks:ks_type":"VILLAGE",
    "name:eng_x_preferred":[
        "Manikpur"
    ],
    "name:eng_x_variant":[
        "M\u0101nikpur"
    ],
    "name:nld_x_preferred":[
        "Manikpur"
    ],
    "name:pol_x_preferred":[
        "Manikpur"
    ],
    "wof:name":"Manikpur",
    "wof:placetype":"locality"
},
  "geometry": {"coordinates":[86.048193,24.983109],"type":"Point"}
}