{
  "type": "Feature",
  "properties": {
    "iso:country":"IN",
    "ks:ks_name":"Khargaon",
    "ks:ks_type":"VILLAGE",
    "name:eng_x_preferred":[
        "Khargaon"
    ],
    "wof:name":"Khargaon",
    "wof:placetype":"locality"
},
  "geometry": {"coordinates":[81.182844,20.140906],"type":"Point"}
}