{
  "type": "Feature",
  "properties": {
    "gn:admin1_code":"9.0",
    "gn:admin2_code":"471.0",
    "gn:asciiname":"Rabarivas",
    "gn:country_code":"IN",
    "gn:dem":202,
    "gn:feature_class":"P",
    "gn:feature_code":"PPL",
    "gn:name":"Rabariv\u0101s",
    "gn:population":0,
    "gn:timezone":"Asia/Kolkata",
    "iso:country":"IN",
    "wof:name":"Rabarivas",
    "wof:placetype":"locality"
},
  "geometry": {"coordinates":[72.79470000000001,24.06327000000001],"type":"Point"}
}