{
  "type": "Feature",
  "properties": {
    "gn:admin1_code":"9.0",
    "gn:admin2_code":"471.0",
    "gn:asciiname":"Rabarivas",
    "gn:country_code":"IN",
    "gn:dem":202,
    "gn:feature_class":"P",
    "gn:feature_code":"PPL",
    "gn:name":"Rabariv\u0101s",
    "gn:population":0,
    "gn:timezone":"Asia/Kolkata",
    "iso:country":"IN",
    "ks:ks_alt_nam":"Rabariv\u0101s",
    "ks:ks_name":"Rabarivas",
    "ks:ks_type":"VILLAGE",
    "name:eng_x_preferred":[
        "Rabarivas"
    ],
    "name:eng_x_variant":[
        "Rabariv\u0101s"
    ],
    "wof:name":"Rabarivas",
    "wof:placetype":"locality"
},
  "geometry": {"coordinates":[72.794703,24.063268],"type":"Point"}
}