{
  "type": "Feature",
  "properties": {
    "iso:country":"IN",
    "ks:ks_name":"Matikhula Gaon",
    "ks:ks_pop":628,
    "ks:ks_type":"VILLAGE",
    "name:eng_x_preferred":[
        "Matikhula Gaon"
    ],
    "wof:name":"Matikhula Gaon",
    "wof:placetype":"locality",
    "wof:population":628
},
  "geometry": {"coordinates":[94.12984899999999,26.3875],"type":"Point"}
}