{
  "type": "Feature",
  "properties": {
    "iso:country":"IN",
    "ks:ks_name":"Nayatareta",
    "ks:ks_pop":142,
    "ks:ks_type":"HABITATION",
    "name:eng_x_preferred":[
        "Nayatareta"
    ],
    "wof:name":"Nayatareta",
    "wof:placetype":"locality",
    "wof:population":142
},
  "geometry": {"coordinates":[78.62110800000001,24.967247],"type":"Point"}
}