{
  "type": "Feature",
  "properties": {
    "iso:country":"IN",
    "ks:ks_name":"Bhawanipur",
    "ks:ks_pop":475,
    "ks:ks_type":"VILLAGE",
    "name:eng_x_preferred":[
        "Bhawanipur"
    ],
    "wof:name":"Bhawanipur",
    "wof:placetype":"locality",
    "wof:population":475
},
  "geometry": {"coordinates":[86.397794,25.246576],"type":"Point"}
}