{
  "type": "Feature",
  "properties": {
    "gn:admin1_code":"34.0",
    "gn:admin2_code":"224.0",
    "gn:asciiname":"Raipura",
    "gn:country_code":"IN",
    "gn:dem":38,
    "gn:feature_class":"P",
    "gn:feature_code":"PPL",
    "gn:name":"Raipura",
    "gn:population":0,
    "gn:timezone":"Asia/Kolkata",
    "iso:country":"IN",
    "wof:name":"Raipura",
    "wof:placetype":"locality"
},
  "geometry": {"coordinates":[87.11312,25.16543],"type":"Point"}
}