{
  "type": "Feature",
  "properties": {
    "gn:admin1_code":"36.0",
    "gn:admin2_code":"183.0",
    "gn:asciiname":"Jhala",
    "gn:country_code":"IN",
    "gn:dem":110,
    "gn:feature_class":"P",
    "gn:feature_code":"PPL",
    "gn:name":"Jh\u0101la",
    "gn:population":0,
    "gn:timezone":"Asia/Kolkata",
    "iso:country":"IN",
    "ks:ks_alt_nam":"Jh\u0101la",
    "ks:ks_name":"Jhala",
    "ks:ks_type":"VILLAGE",
    "name:eng_x_preferred":[
        "Jhala"
    ],
    "name:eng_x_variant":[
        "Jh\u0101la"
    ],
    "name:nld_x_preferred":[
        "Jhala"
    ],
    "name:spa_x_preferred":[
        "Jhala"
    ],
    "wof:name":"Jhala",
    "wof:placetype":"locality"
},
  "geometry": {"coordinates":[81.764509,27.304976],"type":"Point"}
}