{
  "type": "Feature",
  "properties": {
    "iso:country":"IN",
    "ks:ks_name":"Bankapur",
    "ks:ks_pop":344,
    "ks:ks_type":"VILLAGE",
    "name:eng_x_preferred":[
        "Bankapur"
    ],
    "wof:name":"Bankapur",
    "wof:placetype":"locality",
    "wof:population":344
},
  "geometry": {"coordinates":[85.872106,25.945707],"type":"Point"}
}