{
  "type": "Feature",
  "properties": {
    "gn:admin1_code":"36.0",
    "gn:admin2_code":"141.0",
    "gn:asciiname":"Kureb",
    "gn:country_code":"IN",
    "gn:dem":200,
    "gn:feature_class":"P",
    "gn:feature_code":"PPL",
    "gn:name":"Kureb",
    "gn:population":0,
    "gn:timezone":"Asia/Kolkata",
    "iso:country":"IN",
    "wof:name":"Kureb",
    "wof:placetype":"locality"
},
  "geometry": {"coordinates":[77.60414,28.19413],"type":"Point"}
}