{
  "type": "Feature",
  "properties": {
    "iso:country":"IN",
    "ks:ks_name":"Manjar Chak",
    "ks:ks_pop":0,
    "ks:ks_type":"VILLAGE",
    "name:eng_x_preferred":[
        "Manjar Chak"
    ],
    "wof:name":"Manjar Chak",
    "wof:placetype":"locality",
    "wof:population":0
},
  "geometry": {"coordinates":[86.82230199999999,25.168179],"type":"Point"}
}