{
  "type": "Feature",
  "properties": {
    "gn:admin1_code":"37",
    "gn:admin2_code":"403.0",
    "gn:asciiname":"Kargipali",
    "gn:country_code":"IN",
    "gn:dem":241,
    "gn:feature_class":"P",
    "gn:feature_code":"PPL",
    "gn:name":"Kargip\u0101li",
    "gn:population":0,
    "gn:timezone":"Asia/Kolkata",
    "iso:country":"IN",
    "ks:ks_alt_nam":"Kargip\u0101li",
    "ks:ks_name":"Kargipali",
    "ks:ks_type":"VILLAGE",
    "name:eng_x_preferred":[
        "Kargipali"
    ],
    "name:eng_x_variant":[
        "Kargip\u0101li"
    ],
    "wof:name":"Kargipali",
    "wof:placetype":"locality"
},
  "geometry": {"coordinates":[83.10696900000001,21.437234],"type":"Point"}
}