{
  "type": "Feature",
  "properties": {
    "iso:country":"IN",
    "ks:ks_name":"Kadapanage Palle",
    "ks:ks_pop":554,
    "ks:ks_type":"HABITATION",
    "ks:ks_uagg_main":0,
    "name:eng_x_preferred":[
        "Kadapanage Palle"
    ],
    "wof:name":"Kadapanage Palle",
    "wof:placetype":"neighbourhood",
    "wof:population":554
},
  "geometry": {"coordinates":[77.81300899999999,14.21836],"type":"Point"}
}