{
  "type": "Feature",
  "properties": {
    "iso:country":"IN",
    "ks:ks_name":"Arasa",
    "ks:ks_pop":792,
    "ks:ks_type":"VILLAGE",
    "ks:ks_uagg_main":0,
    "name:eng_x_preferred":[
        "Arasa"
    ],
    "wof:name":"Arasa",
    "wof:placetype":"neighbourhood",
    "wof:population":792
},
  "geometry": {"coordinates":[86.712124,20.74352],"type":"Point"}
}