{
  "type": "Feature",
  "properties": {
    "gn:admin1_code":"24",
    "gn:admin2_code":"113.0",
    "gn:asciiname":"Mogra Khurd",
    "gn:country_code":"IN",
    "gn:dem":197,
    "gn:feature_class":"P",
    "gn:feature_code":"PPL",
    "gn:name":"Mogra Khurd",
    "gn:population":0,
    "gn:timezone":"Asia/Kolkata",
    "iso:country":"IN",
    "ks:ks_name":"Mogra Khurd",
    "ks:ks_pop":851,
    "ks:ks_type":"VILLAGE",
    "ks:ks_uagg_main":0,
    "name:eng_x_preferred":[
        "Mogra Khurd"
    ],
    "wof:name":"Mogra Khurd",
    "wof:placetype":"neighbourhood",
    "wof:population":851
},
  "geometry": {"coordinates":[73.058739,26.126303],"type":"Point"}
}