{
  "type": "Feature",
  "properties": {
    "iso:country":"IN",
    "ks:ks_name":"Madha Nirbhainath",
    "ks:ks_pop":46,
    "ks:ks_type":"HABITATION",
    "name:eng_x_preferred":[
        "Madha Nirbhainath"
    ],
    "wof:name":"Madha Nirbhainath",
    "wof:placetype":"locality",
    "wof:population":46
},
  "geometry": {"coordinates":[82.031584,24.726424],"type":"Point"}
}