{
  "type": "Feature",
  "properties": {
    "iso:country":"IN",
    "ks:ks_name":"Muhiuddinpur",
    "ks:ks_pop":582,
    "ks:ks_type":"VILLAGE",
    "ks:ks_uagg_main":0,
    "name:eng_x_preferred":[
        "Muhiuddinpur"
    ],
    "wof:name":"Muhiuddinpur",
    "wof:placetype":"neighbourhood",
    "wof:population":582
},
  "geometry": {"coordinates":[80.933908,26.944795],"type":"Point"}
}