{
  "type": "Feature",
  "properties": {
    "gn:admin1_code":"36",
    "gn:admin2_code":"178.0",
    "gn:asciiname":"Kataria",
    "gn:country_code":"IN",
    "gn:dem":95,
    "gn:feature_class":"P",
    "gn:feature_code":"PPL",
    "gn:name":"Kataria",
    "gn:population":0,
    "gn:timezone":"Asia/Kolkata",
    "iso:country":"IN",
    "ks:ks_name":"Kataria",
    "ks:ks_pop":4091,
    "ks:ks_type":"VILLAGE",
    "name:eng_x_preferred":[
        "Kataria"
    ],
    "wof:name":"Kataria",
    "wof:placetype":"locality",
    "wof:population":4091
},
  "geometry": {"coordinates":[82.584856,26.602337],"type":"Point"}
}