{
  "type": "Feature",
  "properties": {
    "iso:country":"IN",
    "ks:ks_name":"Junia Gadhi",
    "ks:ks_pop":177,
    "ks:ks_type":"HABITATION",
    "name:eng_x_preferred":[
        "Junia Gadhi"
    ],
    "wof:name":"Junia Gadhi",
    "wof:placetype":"locality",
    "wof:population":177
},
  "geometry": {"coordinates":[79.125581,29.870295],"type":"Point"}
}