{
  "type": "Feature",
  "properties": {
    "iso:country":"IN",
    "ks:ks_name":"Sankundeikela",
    "ks:ks_pop":4,
    "ks:ks_type":"VILLAGE",
    "name:eng_x_preferred":[
        "Sankundeikela"
    ],
    "wof:name":"Sankundeikela",
    "wof:placetype":"locality",
    "wof:population":4
},
  "geometry": {"coordinates":[84.99961500000001,21.850176],"type":"Point"}
}