{
  "type": "Feature",
  "properties": {
    "iso:country":"IN",
    "ks:ks_alt_nam":"ratevara",
    "ks:ks_name":"Ratevara",
    "ks:ks_pop":832,
    "ks:ks_type":"HABITATION",
    "name:eng_x_preferred":[
        "Ratevara"
    ],
    "wof:name":"Ratevara",
    "wof:placetype":"locality",
    "wof:population":832
},
  "geometry": {"coordinates":[81.989914,24.990746],"type":"Point"}
}