{
  "type": "Feature",
  "properties": {
    "iso:country":"IN",
    "ks:ks_name":"Rohiamba",
    "ks:ks_pop":76,
    "ks:ks_type":"HABITATION",
    "name:eng_x_preferred":[
        "Rohiamba"
    ],
    "wof:name":"Rohiamba",
    "wof:placetype":"locality",
    "wof:population":76
},
  "geometry": {"coordinates":[82.90167,19.149215],"type":"Point"}
}