{
  "type": "Feature",
  "properties": {
    "gn:admin1_code":"19.0",
    "gn:admin2_code":"574.0",
    "gn:asciiname":"Madanhalli",
    "gn:country_code":"IN",
    "gn:dem":962,
    "gn:feature_class":"P",
    "gn:feature_code":"PPL",
    "gn:name":"Madanhalli",
    "gn:population":0,
    "gn:timezone":"Asia/Kolkata",
    "iso:country":"IN",
    "wof:name":"Madanhalli",
    "wof:placetype":"locality"
},
  "geometry": {"coordinates":[75.91498,12.99247],"type":"Point"}
}