{
  "type": "Feature",
  "properties": {
    "gn:admin1_code":"19.0",
    "gn:admin2_code":"577.0",
    "gn:asciiname":"Tammadahalli",
    "gn:country_code":"IN",
    "gn:dem":818,
    "gn:feature_class":"P",
    "gn:feature_code":"PPL",
    "gn:name":"Tammadahalli",
    "gn:population":0,
    "gn:timezone":"Asia/Kolkata",
    "iso:country":"IN",
    "ks:ks_name":"Tammadahalli",
    "ks:ks_pop":1148,
    "ks:ks_type":"VILLAGE",
    "name:eng_x_preferred":[
        "Tammadahalli"
    ],
    "wof:name":"Tammadahalli",
    "wof:placetype":"locality",
    "wof:population":1148
},
  "geometry": {"coordinates":[76.252374,12.326913],"type":"Point"}
}