{
  "type": "Feature",
  "properties": {
    "iso:country":"IN",
    "ks:ks_name":"Thangai Para",
    "ks:ks_pop":165,
    "ks:ks_type":"HABITATION",
    "name:eng_x_preferred":[
        "Thangai Para"
    ],
    "wof:name":"Thangai Para",
    "wof:placetype":"locality",
    "wof:population":165
},
  "geometry": {"coordinates":[92.320031,24.08421],"type":"Point"}
}