{
  "type": "Feature",
  "properties": {
    "iso:country":"IN",
    "ks:ks_name":"Kolamuru",
    "ks:ks_pop":15642,
    "ks:ks_type":"VILLAGE",
    "ks:ks_uagg_main":0,
    "name:eng_x_preferred":[
        "Kolamuru"
    ],
    "wof:name":"Kolamuru",
    "wof:placetype":"locality",
    "wof:population":15642
},
  "geometry": {"coordinates":[81.81265500000001,17.069741],"type":"Point"}
}