{
  "type": "Feature",
  "properties": {
    "gn:admin1_code":"35",
    "gn:admin2_code":"420.0",
    "gn:asciiname":"Bade ka Pura",
    "gn:country_code":"IN",
    "gn:dem":161,
    "gn:feature_class":"P",
    "gn:feature_code":"PPL",
    "gn:name":"Bade ka Pura",
    "gn:population":0,
    "gn:timezone":"Asia/Kolkata",
    "iso:country":"IN",
    "wof:name":"Bade ka Pura",
    "wof:placetype":"locality"
},
  "geometry": {"coordinates":[78.49250000000001,26.63113],"type":"Point"}
}