{
  "type": "Feature",
  "properties": {
    "iso:country":"IN",
    "ks:ks_name":"Tilhera",
    "ks:ks_pop":364,
    "ks:ks_type":"VILLAGE",
    "ks:ks_uagg_main":0,
    "name:eng_x_preferred":[
        "Tilhera"
    ],
    "wof:name":"Tilhera",
    "wof:placetype":"neighbourhood",
    "wof:population":364
},
  "geometry": {"coordinates":[78.76217200000001,25.849871],"type":"Point"}
}