{
  "type": "Feature",
  "properties": {
    "iso:country":"IN",
    "ks:ks_name":"Koparguda",
    "ks:ks_pop":51,
    "ks:ks_type":"HABITATION",
    "name:eng_x_preferred":[
        "Koparguda"
    ],
    "wof:name":"Koparguda",
    "wof:placetype":"locality",
    "wof:population":51
},
  "geometry": {"coordinates":[79.069789,19.420452],"type":"Point"}
}