{
  "type": "Feature",
  "properties": {
    "iso:country":"IN",
    "ks:ks_name":"Ankarantipur",
    "ks:ks_pop":1935,
    "ks:ks_type":"VILLAGE",
    "ks:ks_uagg_main":0,
    "name:eng_x_preferred":[
        "Ankarantipur"
    ],
    "wof:name":"Ankarantipur",
    "wof:placetype":"neighbourhood",
    "wof:population":1935
},
  "geometry": {"coordinates":[85.52970500000001,20.696837],"type":"Point"}
}