{
  "type": "Feature",
  "properties": {
    "gn:admin1_code":"21.0",
    "gn:admin2_code":"393",
    "gn:asciiname":"Domkipali",
    "gn:country_code":"IN",
    "gn:dem":219,
    "gn:feature_class":"P",
    "gn:feature_code":"PPL",
    "gn:name":"Domkip\u0101li",
    "gn:population":0,
    "gn:timezone":"Asia/Kolkata",
    "iso:country":"IN",
    "ks:ks_name":"Damkipali",
    "ks:ks_pop":1904,
    "ks:ks_type":"VILLAGE",
    "name:eng_x_preferred":[
        "Damkipali"
    ],
    "name:eng_x_variant":[
        "Domkipali"
    ],
    "wof:name":"Damkipali",
    "wof:placetype":"locality",
    "wof:population":1904
},
  "geometry": {"coordinates":[83.23259299999999,20.907427],"type":"Point"}
}