{
  "type": "Feature",
  "properties": {
    "gn:admin1_code":"21.0",
    "gn:admin2_code":"393",
    "gn:asciiname":"Domkipali",
    "gn:country_code":"IN",
    "gn:dem":219,
    "gn:feature_class":"P",
    "gn:feature_code":"PPL",
    "gn:name":"Domkip\u0101li",
    "gn:population":0,
    "gn:timezone":"Asia/Kolkata",
    "iso:country":"IN",
    "wof:name":"Domkipali",
    "wof:placetype":"locality"
},
  "geometry": {"coordinates":[83.21666999999999,20.91667],"type":"Point"}
}