{
  "type": "Feature",
  "properties": {
    "iso:country":"IN",
    "ks:ks_name":"Santipur No 2",
    "ks:ks_pop":463,
    "ks:ks_type":"HABITATION",
    "ks:ks_uagg_main":0,
    "name:eng_x_preferred":[
        "Santipur No 2"
    ],
    "wof:name":"Santipur No 2",
    "wof:placetype":"neighbourhood",
    "wof:population":463
},
  "geometry": {"coordinates":[93.80086300000001,26.010525],"type":"Point"}
}