{
  "type": "Feature",
  "properties": {
    "iso:country":"IN",
    "ks:ks_name":"Kheriyado",
    "ks:ks_pop":544,
    "ks:ks_type":"VILLAGE",
    "name:eng_x_preferred":[
        "Kheriyado"
    ],
    "wof:name":"Kheriyado",
    "wof:placetype":"locality",
    "wof:population":544
},
  "geometry": {"coordinates":[74.73773300000001,24.151683],"type":"Point"}
}