{
  "type": "Feature",
  "properties": {
    "gn:admin1_code":"34.0",
    "gn:admin2_code":"224.0",
    "gn:asciiname":"Rasulpur Kasim",
    "gn:country_code":"IN",
    "gn:dem":37,
    "gn:feature_class":"P",
    "gn:feature_code":"PPL",
    "gn:name":"Rasulpur K\u0101sim",
    "gn:population":0,
    "gn:timezone":"Asia/Kolkata",
    "iso:country":"IN",
    "wof:name":"Rasulpur Kasim",
    "wof:placetype":"locality"
},
  "geometry": {"coordinates":[87.08163,25.3872],"type":"Point"}
}