{
  "type": "Feature",
  "properties": {
    "gn:admin1_code":"11.0",
    "gn:admin2_code":"26.0",
    "gn:asciiname":"Dasholi",
    "gn:country_code":"IN",
    "gn:dem":1477,
    "gn:feature_class":"P",
    "gn:feature_code":"PPL",
    "gn:name":"Dasholi",
    "gn:population":0,
    "gn:timezone":"Asia/Kolkata",
    "iso:country":"IN",
    "wof:name":"Dasholi",
    "wof:placetype":"locality"
},
  "geometry": {"coordinates":[77.57068000000002,31.46745],"type":"Point"}
}