{
  "type": "Feature",
  "properties": {
    "iso:country":"IN",
    "ks:ks_name":"Guttala Bhavi",
    "ks:ks_pop":12,
    "ks:ks_type":"HABITATION",
    "name:eng_x_preferred":[
        "Guttala Bhavi"
    ],
    "wof:name":"Guttala Bhavi",
    "wof:placetype":"locality",
    "wof:population":12
},
  "geometry": {"coordinates":[79.013493,17.491951],"type":"Point"}
}