{
  "type": "Feature",
  "properties": {
    "iso:country":"IN",
    "ks:ks_name":"Bisarpur",
    "ks:ks_pop":262,
    "ks:ks_type":"HABITATION",
    "name:eng_x_preferred":[
        "Bisarpur"
    ],
    "wof:name":"Bisarpur",
    "wof:placetype":"locality",
    "wof:population":262
},
  "geometry": {"coordinates":[87.38163900000001,22.109574],"type":"Point"}
}