{
  "type": "Feature",
  "properties": {
    "iso:country":"IN",
    "name:eng_x_preferred":[
        "Pattanpalli"
    ],
    "name:unk_x_variant":[
        "Pattanpalli"
    ],
    "qs:gn_local":0,
    "qs:local_max":594,
    "qs:local_sum":650,
    "qs:localhoods":3,
    "qs:name":"Pattanpalli",
    "qs:name_adm0":"India",
    "qs:name_adm1":"Kerala",
    "qs:name_adm2":"Thrissur",
    "qs:name_local":"Thrissur",
    "qs:photo_max":305,
    "qs:photo_sum":594,
    "qs:placetype":"Suburb",
    "qs:quad_count":20,
    "qs:woe_adm0":23424848,
    "qs:woe_adm1":2345747,
    "qs:woe_adm2":12586477,
    "qs:woe_lau":0,
    "qs:woe_local":2295334,
    "qs:woe_ver":"7.10.0",
    "wof:lang":[
        "eng"
    ],
    "wof:name":"Pattanpalli",
    "wof:placetype":"neighbourhood"
},
  "geometry": {"coordinates":[76.21718,10.529344],"type":"Point"}
}