{
  "type": "Feature",
  "properties": {
    "iso:country":"IN",
    "name:ara_x_preferred":[
        "\u0628\u0627\u062a\u0646\u0628\u0627\u0644\u064a"
    ],
    "name:ben_bn_x_preferred":[
        "\u09aa\u09a4\u09cd\u09a4\u09a8\u09aa\u09be\u09b2\u09cd\u09b2\u09bf"
    ],
    "name:ben_in_x_preferred":[
        "\u09aa\u09a4\u09cd\u09a4\u09a8\u09aa\u09be\u09b2\u09cd\u09b2\u09bf"
    ],
    "name:eng_x_preferred":[
        "Pattanpalli"
    ],
    "name:guj_x_preferred":[
        "\u0aaa\u0a9f\u0acd\u0a9f\u0abe\u0a82\u0aaa\u0ab2\u0acd\u0ab2\u0ac0"
    ],
    "name:hin_x_preferred":[
        "\u092a\u0924\u094d\u0924\u0928\u092a\u0932\u094d\u0932\u0940"
    ],
    "name:kan_x_preferred":[
        "\u0caa\u0c9f\u0ccd\u0c9f\u0ca8\u0caa\u0cb2\u0ccd\u0cb2\u0cbf"
    ],
    "name:mal_x_preferred":[
        "\u0d2a\u0d1f\u0d4d\u0d1f\u0d7b\u0d2a\u0d33\u0d4d\u0d33\u0d3f"
    ],
    "name:mar_x_preferred":[
        "\u092a\u091f\u094d\u091f\u0928\u092a\u0932\u094d\u0932\u0940"
    ],
    "name:pan_x_preferred":[
        "\u0a2a\u0a71\u0a1f\u0a28\u0a2a\u0a71\u0a32\u0a40"
    ],
    "name:tam_x_preferred":[
        "\u0baa\u0b9f\u0bcd\u0b9f\u0ba9\u0bcd\u0baa\u0bb3\u0bcd\u0bb3\u0bbf"
    ],
    "name:tel_x_preferred":[
        "\u0c2a\u0c1f\u0c4d\u0c1f\u0c28\u0c4d"
    ],
    "name:urd_x_preferred":[
        "\u067e\u0679\u0651\u0646 \u067e\u0644\u0651\u06cc"
    ],
    "qs:gn_local":0,
    "qs:local_max":594,
    "qs:local_sum":650,
    "qs:localhoods":3,
    "qs:name":"Pattanpalli",
    "qs:name_adm0":"India",
    "qs:name_adm1":"Kerala",
    "qs:name_adm2":"Thrissur",
    "qs:name_local":"Thrissur",
    "qs:photo_max":305,
    "qs:photo_sum":594,
    "qs:placetype":"Suburb",
    "qs:quad_count":20,
    "qs:woe_adm0":23424848,
    "qs:woe_adm1":2345747,
    "qs:woe_adm2":12586477,
    "qs:woe_lau":0,
    "qs:woe_local":2295334,
    "qs:woe_ver":"7.10.0",
    "wof:lang":[
        "eng"
    ],
    "wof:name":"Pattanpalli",
    "wof:placetype":"neighbourhood"
},
  "geometry": {"coordinates":[76.21718,10.529344],"type":"Point"}
}