{
  "type": "Feature",
  "properties": {
    "iso:country":"IN",
    "ks:ks_alt_nam":"Ras\u016blpur Shekh",
    "ks:ks_name":"Rasulpur Shekh",
    "ks:ks_type":"VILLAGE",
    "name:eng_x_preferred":[
        "Rasulpur Shekh"
    ],
    "name:eng_x_variant":[
        "Ras\u016blpur Shekh"
    ],
    "wof:name":"Rasulpur Shekh",
    "wof:placetype":"locality"
},
  "geometry": {"coordinates":[78.410321,29.319563],"type":"Point"}
}