{
  "type": "Feature",
  "properties": {
    "gn:admin1_code":"35.0",
    "gn:admin2_code":"455.0",
    "gn:asciiname":"Shankarpur",
    "gn:country_code":"IN",
    "gn:dem":748,
    "gn:feature_class":"P",
    "gn:feature_code":"PPL",
    "gn:name":"Shankarpur",
    "gn:population":0,
    "gn:timezone":"Asia/Kolkata",
    "iso:country":"IN",
    "ks:ks_name":"Shankarpur",
    "ks:ks_pop":558,
    "ks:ks_type":"HABITATION",
    "name:eng_x_preferred":[
        "Shankarpur"
    ],
    "wof:name":"Shankarpur",
    "wof:placetype":"locality",
    "wof:population":558
},
  "geometry": {"coordinates":[78.74135800000001,21.931304],"type":"Point"}
}