{
  "type": "Feature",
  "properties": {
    "gn:admin1_code":"36.0",
    "gn:admin2_code":"195.0",
    "gn:asciiname":"Piarepur",
    "gn:country_code":"IN",
    "gn:dem":72,
    "gn:feature_class":"P",
    "gn:feature_code":"PPL",
    "gn:name":"Pi\u0101repur",
    "gn:population":0,
    "gn:timezone":"Asia/Kolkata",
    "iso:country":"IN",
    "ks:ks_name":"Pyarepur",
    "ks:ks_pop":596,
    "ks:ks_type":"VILLAGE",
    "ks:ks_uagg_main":0,
    "name:eng_x_preferred":[
        "Pyarepur"
    ],
    "wof:name":"Pyarepur",
    "wof:placetype":"neighbourhood",
    "wof:population":596
},
  "geometry": {"coordinates":[83.643289,25.659554],"type":"Point"}
}