{
  "type": "Feature",
  "properties": {
    "iso:country":"IN",
    "ks:ks_name":"Tikarpada",
    "ks:ks_pop":359,
    "ks:ks_type":"VILLAGE",
    "name:eng_x_preferred":[
        "Tikarpada"
    ],
    "wof:name":"Tikarpada",
    "wof:placetype":"locality",
    "wof:population":359
},
  "geometry": {"coordinates":[83.506663,19.946148],"type":"Point"}
}