{
  "type": "Feature",
  "properties": {
    "iso:country":"IN",
    "ks:ks_alt_nam":"Laxman tanda",
    "ks:ks_name":"Laxman Tanda",
    "ks:ks_pop":34,
    "ks:ks_type":"HABITATION",
    "name:eng_x_preferred":[
        "Laxman Tanda"
    ],
    "wof:name":"Laxman Tanda",
    "wof:placetype":"locality",
    "wof:population":34
},
  "geometry": {"coordinates":[78.44017100000001,16.906397],"type":"Point"}
}