{
  "type": "Feature",
  "properties": {
    "iso:country":"IN",
    "ks:ks_name":"More Patuyri",
    "ks:ks_pop":273,
    "ks:ks_type":"HABITATION",
    "name:eng_x_preferred":[
        "More Patuyri"
    ],
    "wof:name":"More Patuyri",
    "wof:placetype":"locality",
    "wof:population":273
},
  "geometry": {"coordinates":[79.70474299999999,29.46739],"type":"Point"}
}