{
  "type": "Feature",
  "properties": {
    "gn:admin1_code":"39.0",
    "gn:admin2_code":"65.0",
    "gn:asciiname":"Kalkphar",
    "gn:country_code":"IN",
    "gn:dem":425,
    "gn:feature_class":"P",
    "gn:feature_code":"PPL",
    "gn:name":"Kalkph\u0101r",
    "gn:population":0,
    "gn:timezone":"Asia/Kolkata",
    "iso:country":"IN",
    "wof:name":"Kalkphar",
    "wof:placetype":"locality"
},
  "geometry": {"coordinates":[80.19808,29.2125],"type":"Point"}
}