{
  "type": "Feature",
  "properties": {
    "iso:country":"IN",
    "ks:ks_name":"Madhubanwa",
    "ks:ks_pop":198,
    "ks:ks_type":"HABITATION",
    "name:eng_x_preferred":[
        "Madhubanwa"
    ],
    "wof:name":"Madhubanwa",
    "wof:placetype":"locality",
    "wof:population":198
},
  "geometry": {"coordinates":[83.11399900000001,24.509205],"type":"Point"}
}