{
  "type": "Feature",
  "properties": {
    "iso:country":"IN",
    "ks:ks_alt_nam":"7 No. Pub odali",
    "ks:ks_name":"7 No. Pub Odali",
    "ks:ks_pop":569,
    "ks:ks_type":"HABITATION",
    "name:eng_x_preferred":[
        "7 No. Pub Odali"
    ],
    "wof:name":"7 No. Pub Odali",
    "wof:placetype":"locality",
    "wof:population":569
},
  "geometry": {"coordinates":[93.05701000000001,25.913972],"type":"Point"}
}