{
  "type": "Feature",
  "properties": {
    "gn:admin1_code":"36.0",
    "gn:admin2_code":"150.0",
    "gn:asciiname":"Kachahri",
    "gn:country_code":"IN",
    "gn:dem":174,
    "gn:feature_class":"P",
    "gn:feature_code":"PPL",
    "gn:name":"Kachahri",
    "gn:population":0,
    "gn:timezone":"Asia/Kolkata",
    "iso:country":"IN",
    "name:ara_x_preferred":[
        "\u0643\u0627\u0634\u0627\u0647\u0631\u064a"
    ],
    "name:ben_bn_x_preferred":[
        "\u0995\u09be\u099b\u09be\u09b0\u09bf"
    ],
    "name:ben_in_x_preferred":[
        "\u0995\u09be\u099b\u09be\u09b0\u09bf"
    ],
    "name:guj_x_preferred":[
        "\u0a95\u0a9a\u0acd\u0a9b\u0ab0\u0ac0"
    ],
    "name:hin_x_preferred":[
        "\u0915\u091a\u0939\u0930\u0940"
    ],
    "name:kan_x_preferred":[
        "\u0c95\u0c9a\u0cb9\u0ccd\u0cb0\u0cbf"
    ],
    "name:mal_x_preferred":[
        "\u0d15\u0d1a\u0d4d\u0d1a\u0d39\u0d4d\u0d30\u0d3f"
    ],
    "name:mar_x_preferred":[
        "\u0915\u091a\u0939\u0930\u0940"
    ],
    "name:pan_x_preferred":[
        "\u0a15\u0a1a\u0a3e\u0a39\u0a30\u0a40"
    ],
    "name:tam_x_preferred":[
        "\u0b95\u0b9a\u0bbe\u0bb9\u0bcd\u0bb0\u0bbf"
    ],
    "name:tel_x_preferred":[
        "\u0c15\u0c1b\u0c3e\u0c39\u0c4d\u0c30\u0c3f"
    ],
    "name:urd_x_preferred":[
        "\u06a9\u0686\u06c1\u0631\u06cc"
    ],
    "wof:name":"Kachahri",
    "wof:placetype":"locality"
},
  "geometry": {"coordinates":[79.41797,28.34061],"type":"Point"}
}