{
  "type": "Feature",
  "properties": {
    "iso:country":"IN",
    "ks:ks_name":"Tumritola",
    "ks:ks_pop":103,
    "ks:ks_type":"HABITATION",
    "name:eng_x_preferred":[
        "Tumritola"
    ],
    "wof:name":"Tumritola",
    "wof:placetype":"locality",
    "wof:population":103
},
  "geometry": {"coordinates":[80.576742,19.800605],"type":"Point"}
}