{
  "type": "Feature",
  "properties": {
    "iso:country":"IN",
    "ks:ks_name":"Silauta",
    "ks:ks_pop":48,
    "ks:ks_type":"VILLAGE",
    "ks:ks_uagg_main":0,
    "name:eng_x_preferred":[
        "Silauta"
    ],
    "wof:name":"Silauta",
    "wof:placetype":"neighbourhood",
    "wof:population":48
},
  "geometry": {"coordinates":[84.27224,25.229693],"type":"Point"}
}