{
  "type": "Feature",
  "properties": {
    "gn:admin1_code":"25.0",
    "gn:admin2_code":"631.0",
    "gn:asciiname":"Oddappatti",
    "gn:country_code":"IN",
    "gn:dem":368,
    "gn:feature_class":"P",
    "gn:feature_code":"PPL",
    "gn:name":"Oddappatti",
    "gn:population":0,
    "gn:timezone":"Asia/Kolkata",
    "iso:country":"IN",
    "ks:ks_name":"Oddapatti",
    "ks:ks_pop":345,
    "ks:ks_type":"VILLAGE",
    "ks:ks_uagg_main":0,
    "name:eng_x_preferred":[
        "Oddapatti"
    ],
    "wof:name":"Oddapatti",
    "wof:placetype":"neighbourhood",
    "wof:population":345
},
  "geometry": {"coordinates":[78.50184400000001,12.302854],"type":"Point"}
}