{
  "type": "Feature",
  "properties": {
    "iso:country":"IN",
    "ks:ks_name":"Kuhimari No.1",
    "ks:ks_pop":829,
    "ks:ks_type":"VILLAGE",
    "name:eng_x_preferred":[
        "Kuhimari No.1"
    ],
    "wof:name":"Kuhimari No.1",
    "wof:placetype":"locality",
    "wof:population":829
},
  "geometry": {"coordinates":[92.70016099999999,26.10041],"type":"Point"}
}