{
  "type": "Feature",
  "properties": {
    "iso:country":"IN",
    "ks:ks_name":"Madha Khurd Kalan",
    "ks:ks_pop":1061,
    "ks:ks_type":"HABITATION",
    "name:eng_x_preferred":[
        "Madha Khurd Kalan"
    ],
    "wof:name":"Madha Khurd Kalan",
    "wof:placetype":"locality",
    "wof:population":1061
},
  "geometry": {"coordinates":[80.257532,28.29806],"type":"Point"}
}