{
  "type": "Feature",
  "properties": {
    "gn:admin1_code":"16",
    "gn:admin2_code":"509.0",
    "gn:asciiname":"Pahmi",
    "gn:country_code":"IN",
    "gn:dem":212,
    "gn:feature_class":"P",
    "gn:feature_code":"PPL",
    "gn:name":"P\u0101hmi",
    "gn:population":0,
    "gn:timezone":"Asia/Kolkata",
    "iso:country":"IN",
    "ks:ks_name":"Pahami",
    "ks:ks_pop":70,
    "ks:ks_type":"VILLAGE",
    "name:eng_x_preferred":[
        "Pahami"
    ],
    "name:eng_x_variant":[
        "Pahmi"
    ],
    "wof:name":"Pahami",
    "wof:placetype":"locality",
    "wof:population":70
},
  "geometry": {"coordinates":[79.467068,20.092783],"type":"Point"}
}