{
  "type": "Feature",
  "properties": {
    "iso:country":"IN",
    "ks:ks_name":"Baddemetta",
    "ks:ks_pop":59,
    "ks:ks_type":"HABITATION",
    "name:eng_x_preferred":[
        "Baddemetta"
    ],
    "wof:name":"Baddemetta",
    "wof:placetype":"locality",
    "wof:population":59
},
  "geometry": {"coordinates":[82.50921700000001,17.881408],"type":"Point"}
}