{
  "type": "Feature",
  "properties": {
    "iso:country":"IN",
    "ks:ks_name":"Tatipara",
    "ks:ks_pop":903,
    "ks:ks_type":"HABITATION",
    "name:eng_x_preferred":[
        "Tatipara"
    ],
    "wof:name":"Tatipara",
    "wof:placetype":"locality",
    "wof:population":903
},
  "geometry": {"coordinates":[89.437433,26.286759],"type":"Point"}
}