{
  "type": "Feature",
  "properties": {
    "iso:country":"IN",
    "ks:ks_name":"Sammanenthal",
    "ks:ks_pop":23,
    "ks:ks_type":"HABITATION",
    "name:eng_x_preferred":[
        "Sammanenthal"
    ],
    "wof:name":"Sammanenthal",
    "wof:placetype":"locality",
    "wof:population":23
},
  "geometry": {"coordinates":[78.353257,9.562875],"type":"Point"}
}