{
  "type": "Feature",
  "properties": {
    "iso:country":"IN",
    "ks:ks_alt_nam":"AHER WASTI KHOKAR ROD",
    "ks:ks_name":"Aher Wasti Khokar Rod",
    "ks:ks_pop":110,
    "ks:ks_type":"HABITATION",
    "name:eng_x_preferred":[
        "Aher Wasti Khokar Rod"
    ],
    "wof:name":"Aher Wasti Khokar Rod",
    "wof:placetype":"locality",
    "wof:population":110
},
  "geometry": {"coordinates":[74.77753300000001,19.610167],"type":"Point"}
}