{
  "type": "Feature",
  "properties": {
    "gn:admin1_code":"35",
    "gn:admin2_code":"429.0",
    "gn:asciiname":"Delaora",
    "gn:country_code":"IN",
    "gn:dem":333,
    "gn:feature_class":"P",
    "gn:feature_code":"PPL",
    "gn:name":"Delaora",
    "gn:population":0,
    "gn:timezone":"Asia/Kolkata",
    "iso:country":"IN",
    "wof:name":"Delaora",
    "wof:placetype":"locality"
},
  "geometry": {"coordinates":[80.73145,24.67445],"type":"Point"}
}