{
  "type": "Feature",
  "properties": {
    "iso:country":"IN",
    "ks:ks_name":"Khedikhurd",
    "ks:ks_pop":6,
    "ks:ks_type":"VILLAGE",
    "name:eng_x_preferred":[
        "Khedikhurd"
    ],
    "wof:name":"Khedikhurd",
    "wof:placetype":"locality",
    "wof:population":6
},
  "geometry": {"coordinates":[78.115514,21.701638],"type":"Point"}
}