{
  "type": "Feature",
  "properties": {
    "iso:country":"IN",
    "ks:ks_name":"Bocharpada",
    "ks:ks_pop":110,
    "ks:ks_type":"HABITATION",
    "name:eng_x_preferred":[
        "Bocharpada"
    ],
    "wof:name":"Bocharpada",
    "wof:placetype":"locality",
    "wof:population":110
},
  "geometry": {"coordinates":[72.87890899999999,19.773734],"type":"Point"}
}