{
  "type": "Feature",
  "properties": {
    "iso:country":"IN",
    "ks:ks_name":"Bhatgudi",
    "ks:ks_pop":8,
    "ks:ks_type":"HABITATION",
    "name:eng_x_preferred":[
        "Bhatgudi"
    ],
    "wof:name":"Bhatgudi",
    "wof:placetype":"locality",
    "wof:population":8
},
  "geometry": {"coordinates":[74.711656,14.626279],"type":"Point"}
}