{
  "type": "Feature",
  "properties": {
    "iso:country":"IN",
    "ks:ks_name":"Gariyari",
    "ks:ks_pop":332,
    "ks:ks_type":"HABITATION",
    "name:eng_x_preferred":[
        "Gariyari"
    ],
    "wof:name":"Gariyari",
    "wof:placetype":"locality",
    "wof:population":332
},
  "geometry": {"coordinates":[86.960565,24.384891],"type":"Point"}
}