{
  "type": "Feature",
  "properties": {
    "iso:country":"IN",
    "ks:ks_name":"Uttar Maju",
    "ks:ks_pop":3309,
    "ks:ks_type":"VILLAGE",
    "ks:ks_uagg_main":0,
    "name:eng_x_preferred":[
        "Uttar Maju"
    ],
    "wof:name":"Uttar Maju",
    "wof:placetype":"neighbourhood",
    "wof:population":3309
},
  "geometry": {"coordinates":[88.082612,22.618471],"type":"Point"}
}