{
  "type": "Feature",
  "properties": {
    "iso:country":"IN",
    "ks:ks_name":"Haranda Bk",
    "ks:ks_pop":290,
    "ks:ks_type":"HABITATION",
    "name:eng_x_preferred":[
        "Haranda Bk"
    ],
    "wof:name":"Haranda Bk",
    "wof:placetype":"locality",
    "wof:population":290
},
  "geometry": {"coordinates":[80.33677400000001,19.995601],"type":"Point"}
}