{
  "type": "Feature",
  "properties": {
    "gn:admin1_code":"1.0",
    "gn:admin2_code":"640",
    "gn:asciiname":"Aberdeen",
    "gn:country_code":"IN",
    "gn:dem":15,
    "gn:feature_class":"P",
    "gn:feature_code":"PPL",
    "gn:name":"Aberdeen",
    "gn:population":0,
    "gn:timezone":"Asia/Kolkata",
    "iso:country":"IN",
    "wof:name":"Aberdeen",
    "wof:placetype":"locality"
},
  "geometry": {"coordinates":[92.73997,11.6677],"type":"Point"}
}