{
  "type": "Feature",
  "properties": {
    "iso:country":"IN",
    "ks:ks_name":"Ismailpur",
    "ks:ks_pop":84,
    "ks:ks_type":"VILLAGE",
    "name:eng_x_preferred":[
        "Ismailpur"
    ],
    "wof:name":"Ismailpur",
    "wof:placetype":"locality",
    "wof:population":84
},
  "geometry": {"coordinates":[75.35636100000001,32.207376],"type":"Point"}
}