{
  "type": "Feature",
  "properties": {
    "gn:admin1_code":"34",
    "gn:admin2_code":"233.0",
    "gn:asciiname":"Dumaria",
    "gn:country_code":"IN",
    "gn:dem":102,
    "gn:feature_class":"P",
    "gn:feature_code":"PPL",
    "gn:name":"Dumaria",
    "gn:population":0,
    "gn:timezone":"Asia/Kolkata",
    "iso:country":"IN",
    "name:cat_x_preferred":[
        "Dumaria"
    ],
    "name:tam_x_preferred":[
        "\u0ba4\u0bc1\u0bae\u0bbe\u0bb0\u0bbf\u0baf\u0bbe"
    ],
    "wof:name":"Dumaria",
    "wof:placetype":"locality"
},
  "geometry": {"coordinates":[83.42638000000002,25.0408],"type":"Point"}
}