{
  "type": "Feature",
  "properties": {
    "iso:country":"IN",
    "ks:ks_name":"Malibarahi",
    "ks:ks_pop":539,
    "ks:ks_type":"VILLAGE",
    "ks:ks_uagg_main":0,
    "name:eng_x_preferred":[
        "Malibarahi"
    ],
    "wof:name":"Malibarahi",
    "wof:placetype":"neighbourhood",
    "wof:population":539
},
  "geometry": {"coordinates":[85.834337,20.067626],"type":"Point"}
}