{
  "type": "Feature",
  "properties": {
    "iso:country":"IN",
    "ks:ks_alt_nam":"siddar        koppalu",
    "ks:ks_name":"Siddar Koppalu",
    "ks:ks_pop":223,
    "ks:ks_type":"HABITATION",
    "name:eng_x_preferred":[
        "Siddar Koppalu"
    ],
    "name:eng_x_variant":[
        "siddar        koppalu"
    ],
    "wof:name":"Siddar Koppalu",
    "wof:placetype":"locality",
    "wof:population":223
},
  "geometry": {"coordinates":[76.143064,12.786638],"type":"Point"}
}