{
  "type": "Feature",
  "properties": {
    "iso:country":"IN",
    "ks:ks_name":"Chak Raypur",
    "ks:ks_pop":0,
    "ks:ks_type":"VILLAGE",
    "name:eng_x_preferred":[
        "Chak Raypur"
    ],
    "wof:name":"Chak Raypur",
    "wof:placetype":"locality",
    "wof:population":0
},
  "geometry": {"coordinates":[88.25388100000001,22.110353],"type":"Point"}
}