{
  "type": "Feature",
  "properties": {
    "iso:country":"IN",
    "ks:ks_alt_nam":"damgarha",
    "ks:ks_name":"Damgarha",
    "ks:ks_pop":877,
    "ks:ks_type":"HABITATION",
    "name:eng_x_preferred":[
        "Damgarha"
    ],
    "wof:name":"Damgarha",
    "wof:placetype":"locality",
    "wof:population":877
},
  "geometry": {"coordinates":[86.85797100000001,24.112463],"type":"Point"}
}