{
  "type": "Feature",
  "properties": {
    "iso:country":"IN",
    "ks:ks_name":"Banamalipur",
    "ks:ks_pop":568,
    "ks:ks_type":"VILLAGE",
    "ks:ks_uagg_main":0,
    "name:eng_x_preferred":[
        "Banamalipur"
    ],
    "wof:name":"Banamalipur",
    "wof:placetype":"neighbourhood",
    "wof:population":568
},
  "geometry": {"coordinates":[87.67945400000001,23.231248],"type":"Point"}
}