{
  "type": "Feature",
  "properties": {
    "iso:country":"IN",
    "ks:ks_alt_nam":"Marupayikkara road",
    "ks:ks_name":"Marupayikkara Road",
    "ks:ks_pop":740,
    "ks:ks_type":"HABITATION",
    "name:eng_x_preferred":[
        "Marupayikkara Road"
    ],
    "wof:name":"Marupayikkara Road",
    "wof:placetype":"locality",
    "wof:population":740
},
  "geometry": {"coordinates":[76.528245,9.243717],"type":"Point"}
}