{
  "type": "Feature",
  "properties": {
    "gn:admin1_code":"19.0",
    "gn:admin2_code":"571.0",
    "gn:asciiname":"Kembalhalli",
    "gn:country_code":"IN",
    "gn:dem":802,
    "gn:feature_class":"P",
    "gn:feature_code":"PPL",
    "gn:name":"Kembalhalli",
    "gn:population":0,
    "gn:timezone":"Asia/Kolkata",
    "iso:country":"IN",
    "wof:name":"Kembalhalli",
    "wof:placetype":"locality"
},
  "geometry": {"coordinates":[77.02476,13.19038],"type":"Point"}
}