{
  "type": "Feature",
  "properties": {
    "iso:country":"IN",
    "ks:ks_alt_nam":"KOHAHA BASA",
    "ks:ks_name":"Kohaha Basa",
    "ks:ks_pop":145,
    "ks:ks_type":"HABITATION",
    "ks:ks_uagg_main":0,
    "name:eng_x_preferred":[
        "Kohaha Basa"
    ],
    "wof:name":"Kohaha Basa",
    "wof:placetype":"neighbourhood",
    "wof:population":145
},
  "geometry": {"coordinates":[86.711065,25.564267],"type":"Point"}
}