{
  "type": "Feature",
  "properties": {
    "gn:admin1_code":"24.0",
    "gn:admin2_code":"124",
    "gn:asciiname":"Kodariya",
    "gn:country_code":"IN",
    "gn:dem":218,
    "gn:feature_class":"P",
    "gn:feature_code":"PPL",
    "gn:name":"Kod\u0101riya",
    "gn:population":0,
    "gn:timezone":"Asia/Kolkata",
    "iso:country":"IN",
    "ks:ks_alt_nam":"Kod\u0101riya",
    "ks:ks_name":"Kodariya",
    "ks:ks_type":"VILLAGE",
    "name:eng_x_preferred":[
        "Kodariya"
    ],
    "name:eng_x_variant":[
        "Kod\u0101riya"
    ],
    "name:und_x_variant":[
        "Kod\u0101riya",
        "Kodaria"
    ],
    "wof:name":"Kodariya",
    "wof:placetype":"locality"
},
  "geometry": {"coordinates":[73.848681,23.566047],"type":"Point"}
}