{
  "type": "Feature",
  "properties": {
    "gn:admin1_code":"39.0",
    "gn:admin2_code":"66.0",
    "gn:asciiname":"Seti",
    "gn:country_code":"IN",
    "gn:dem":672,
    "gn:feature_class":"P",
    "gn:feature_code":"PPL",
    "gn:name":"Seti",
    "gn:population":0,
    "gn:timezone":"Asia/Kolkata",
    "iso:country":"IN",
    "name:fas_x_preferred":[
        "\u0633\u062a\u06cc"
    ],
    "name:heb_x_preferred":[
        "\u05e1\u05b6\u05d8\u05d9"
    ],
    "name:hun_x_preferred":[
        "Seti"
    ],
    "wof:name":"Seti",
    "wof:placetype":"locality"
},
  "geometry": {"coordinates":[79.25654,29.54808],"type":"Point"}
}