{
  "type": "Feature",
  "properties": {
    "iso:country":"IN",
    "ks:ks_name":"Siswa",
    "ks:ks_pop":962,
    "ks:ks_type":"HABITATION",
    "name:eng_x_preferred":[
        "Siswa"
    ],
    "wof:name":"Siswa",
    "wof:placetype":"locality",
    "wof:population":962
},
  "geometry": {"coordinates":[82.31225499999999,27.486668],"type":"Point"}
}