{
  "type": "Feature",
  "properties": {
    "iso:country":"IN",
    "ks:ks_name":"Bamnichhara",
    "ks:ks_pop":580,
    "ks:ks_type":"VILLAGE",
    "name:eng_x_preferred":[
        "Bamnichhara"
    ],
    "wof:name":"Bamnichhara",
    "wof:placetype":"locality",
    "wof:population":580
},
  "geometry": {"coordinates":[91.38164,23.713787],"type":"Point"}
}