{
  "type": "Feature",
  "properties": {
    "iso:country":"IN",
    "ks:ks_alt_nam":"Ponniamman vattam",
    "ks:ks_name":"Ponniamman Vattam",
    "ks:ks_pop":300,
    "ks:ks_type":"HABITATION",
    "name:eng_x_preferred":[
        "Ponniamman Vattam"
    ],
    "wof:name":"Ponniamman Vattam",
    "wof:placetype":"locality",
    "wof:population":300
},
  "geometry": {"coordinates":[78.65066899999999,12.687942],"type":"Point"}
}