{
  "type": "Feature",
  "properties": {
    "iso:country":"IN",
    "ks:ks_name":"Manjarekarwadi",
    "ks:ks_pop":96,
    "ks:ks_type":"HABITATION",
    "name:eng_x_preferred":[
        "Manjarekarwadi"
    ],
    "wof:name":"Manjarekarwadi",
    "wof:placetype":"locality",
    "wof:population":96
},
  "geometry": {"coordinates":[73.58459999999999,16.276563],"type":"Point"}
}