{
  "type": "Feature",
  "properties": {
    "iso:country":"IN",
    "ks:ks_name":"Jakhni Tola",
    "ks:ks_pop":413,
    "ks:ks_type":"HABITATION",
    "ks:ks_uagg_main":0,
    "name:eng_x_preferred":[
        "Jakhni Tola"
    ],
    "wof:name":"Jakhni Tola",
    "wof:placetype":"neighbourhood",
    "wof:population":413
},
  "geometry": {"coordinates":[83.97605299999999,26.707412],"type":"Point"}
}