{
  "type": "Feature",
  "properties": {
    "iso:country":"IN",
    "ks:ks_name":"Kedila",
    "ks:ks_pop":139,
    "ks:ks_type":"HABITATION",
    "name:eng_x_preferred":[
        "Kedila"
    ],
    "wof:name":"Kedila",
    "wof:placetype":"locality",
    "wof:population":139
},
  "geometry": {"coordinates":[75.35731699999999,12.773673],"type":"Point"}
}