{
  "type": "Feature",
  "properties": {
    "gn:admin1_code":"9.0",
    "gn:admin2_code":"484.0",
    "gn:asciiname":"Nasirpur",
    "gn:country_code":"IN",
    "gn:dem":123,
    "gn:feature_class":"P",
    "gn:feature_code":"PPL",
    "gn:name":"Nasirpur",
    "gn:population":0,
    "gn:timezone":"Asia/Kolkata",
    "iso:country":"IN",
    "ks:ks_name":"Nasirpur",
    "ks:ks_pop":252,
    "ks:ks_type":"VILLAGE",
    "name:ara_x_preferred":[
        "\u0646\u0627\u0635\u0631 \u0628\u0648\u0631"
    ],
    "name:ben_bn_x_preferred":[
        "\u09a8\u09be\u09b8\u09bf\u09b0\u09aa\u09c1\u09b0"
    ],
    "name:ben_in_x_preferred":[
        "\u09a8\u09be\u09b8\u09bf\u09b0\u09aa\u09c1\u09b0"
    ],
    "name:eng_x_preferred":[
        "Nasirpur"
    ],
    "name:fas_x_preferred":[
        "\u0646\u0635\u06cc\u0631\u067e\u0648\u0631"
    ],
    "name:fra_x_preferred":[
        "Nasirpur"
    ],
    "name:guj_x_preferred":[
        "\u0aa8\u0abe\u0ab8\u0abf\u0ab0\u0aaa\u0ac1\u0ab0"
    ],
    "name:hin_x_preferred":[
        "\u0928\u093e\u0938\u093f\u0930\u092a\u0941\u0930"
    ],
    "name:kan_x_preferred":[
        "\u0ca8\u0cb8\u0cc0\u0cb0\u0ccd"
    ],
    "name:mal_x_preferred":[
        "\u0d28\u0d3e\u0d38\u0d3f\u0d7c\u0d2a\u0d42\u0d7c"
    ],
    "name:mar_x_preferred":[
        "\u0928\u093e\u0938\u093f\u0930\u092a\u0942\u0930"
    ],
    "name:pan_x_preferred":[
        "\u0a28\u0a38\u0a40\u0a30\u0a2a\u0a41\u0a30"
    ],
    "name:pan_x_variant":[
        "\u0a28\u0a38\u0a30\u0a2a\u0a41\u0a30"
    ],
    "name:snd_x_preferred":[
        "\u0646\u0635\u0631 \u067e\u0648\u0631"
    ],
    "name:tam_x_preferred":[
        "\u0ba8\u0b9a\u0bbf\u0bb0\u0bcd\u0baa\u0bc2\u0bb0\u0bcd"
    ],
    "name:tel_x_preferred":[
        "\u0c28\u0c3e\u0c38\u0c3f\u0c30\u0c4d"
    ],
    "name:urd_x_preferred":[
        "\u0646\u0627\u0635\u0631 \u067e\u0648\u0631"
    ],
    "wof:name":"Nasirpur",
    "wof:placetype":"locality",
    "wof:population":252
},
  "geometry": {"coordinates":[73.788922,23.01385],"type":"Point"}
}