{
  "type": "Feature",
  "properties": {
    "iso:country":"IN",
    "ks:ks_name":"Ernoor",
    "ks:ks_pop":987,
    "ks:ks_type":"HABITATION",
    "name:eng_x_preferred":[
        "Ernoor"
    ],
    "wof:name":"Ernoor",
    "wof:placetype":"locality",
    "wof:population":987
},
  "geometry": {"coordinates":[76.812636,8.971975],"type":"Point"}
}