{
  "type": "Feature",
  "properties": {
    "iso:country":"IN",
    "ks:ks_name":"Jamunapur",
    "ks:ks_pop":654,
    "ks:ks_type":"VILLAGE",
    "name:eng_x_preferred":[
        "Jamunapur"
    ],
    "wof:name":"Jamunapur",
    "wof:placetype":"locality",
    "wof:population":654
},
  "geometry": {"coordinates":[84.06336,27.195064],"type":"Point"}
}