{
  "type": "Feature",
  "properties": {
    "iso:country":"IN",
    "ks:ks_name":"Mathada Keri",
    "ks:ks_pop":467,
    "ks:ks_type":"HABITATION",
    "ks:ks_uagg_main":0,
    "name:eng_x_preferred":[
        "Mathada Keri"
    ],
    "wof:name":"Mathada Keri",
    "wof:placetype":"neighbourhood",
    "wof:population":467
},
  "geometry": {"coordinates":[74.439435,14.301173],"type":"Point"}
}