{
  "type": "Feature",
  "properties": {
    "iso:country":"IN",
    "ks:ks_name":"Dumli",
    "ks:ks_pop":118,
    "ks:ks_type":"VILLAGE",
    "name:eng_x_preferred":[
        "Dumli"
    ],
    "wof:name":"Dumli",
    "wof:placetype":"locality",
    "wof:population":118
},
  "geometry": {"coordinates":[87.436442,24.648192],"type":"Point"}
}