{
  "type": "Feature",
  "properties": {
    "iso:country":"IN",
    "ks:ks_alt_nam":"pure Pandey",
    "ks:ks_name":"Pure Pandey",
    "ks:ks_pop":45,
    "ks:ks_type":"HABITATION",
    "name:eng_x_preferred":[
        "Pure Pandey"
    ],
    "wof:name":"Pure Pandey",
    "wof:placetype":"locality",
    "wof:population":45
},
  "geometry": {"coordinates":[81.52719999999999,26.356],"type":"Point"}
}