{
  "type": "Feature",
  "properties": {
    "gn:admin1_code":"19.0",
    "gn:admin2_code":"582.0",
    "gn:asciiname":"Neradaguttahalli",
    "gn:country_code":"IN",
    "gn:dem":788,
    "gn:feature_class":"P",
    "gn:feature_code":"PPL",
    "gn:name":"Neradaguttahalli",
    "gn:population":0,
    "gn:timezone":"Asia/Kolkata",
    "iso:country":"IN",
    "wof:name":"Neradaguttahalli",
    "wof:placetype":"locality"
},
  "geometry": {"coordinates":[77.98265000000001,13.54721],"type":"Point"}
}