{
  "type": "Feature",
  "properties": {
    "gn:admin1_code":"36.0",
    "gn:admin2_code":"193.0",
    "gn:asciiname":"Patnari Kirtpur",
    "gn:country_code":"IN",
    "gn:dem":72,
    "gn:feature_class":"P",
    "gn:feature_code":"PPL",
    "gn:name":"Patn\u0101ri Kirtpur",
    "gn:population":0,
    "gn:timezone":"Asia/Kolkata",
    "iso:country":"IN",
    "wof:name":"Patnari Kirtpur",
    "wof:placetype":"locality"
},
  "geometry": {"coordinates":[83.81501999999998,26.12714],"type":"Point"}
}