{
  "type": "Feature",
  "properties": {
    "iso:country":"IN",
    "ks:ks_name":"Jhilimili",
    "ks:ks_pop":2239,
    "ks:ks_type":"VILLAGE",
    "ks:ks_uagg_main":0,
    "name:eng_x_preferred":[
        "Jhilimili"
    ],
    "wof:name":"Jhilimili",
    "wof:placetype":"neighbourhood",
    "wof:population":2239
},
  "geometry": {"coordinates":[82.539562,19.056629],"type":"Point"}
}