{
  "type": "Feature",
  "properties": {
    "gn:admin1_code":"28.0",
    "gn:admin2_code":"329.0",
    "gn:asciiname":"Takwamari",
    "gn:country_code":"IN",
    "gn:dem":47,
    "gn:feature_class":"P",
    "gn:feature_code":"PPL",
    "gn:name":"Takwam\u0101ri",
    "gn:population":0,
    "gn:timezone":"Asia/Kolkata",
    "iso:country":"IN",
    "wof:name":"Takwamari",
    "wof:placetype":"locality"
},
  "geometry": {"coordinates":[89.75294,26.42101],"type":"Point"}
}