{
  "type": "Feature",
  "properties": {
    "iso:country":"IN",
    "ks:ks_name":"Similia",
    "ks:ks_pop":0,
    "ks:ks_type":"VILLAGE",
    "name:eng_x_preferred":[
        "Similia"
    ],
    "wof:name":"Similia",
    "wof:placetype":"locality",
    "wof:population":0
},
  "geometry": {"coordinates":[85.466846,20.34736],"type":"Point"}
}