{
  "type": "Feature",
  "properties": {
    "gn:admin1_code":"34.0",
    "gn:admin2_code":"219.0",
    "gn:asciiname":"Bhuwalpur",
    "gn:country_code":"IN",
    "gn:dem":59,
    "gn:feature_class":"P",
    "gn:feature_code":"PPL",
    "gn:name":"Bhuw\u0101lpur",
    "gn:population":0,
    "gn:timezone":"Asia/Kolkata",
    "iso:country":"IN",
    "ks:ks_alt_nam":"Bhuw\u0101lpur",
    "ks:ks_name":"Bhuwalpur",
    "ks:ks_pop":3603,
    "ks:ks_type":"VILLAGE",
    "ks:ks_uagg_main":0,
    "name:eng_x_preferred":[
        "Bhuwalpur"
    ],
    "name:eng_x_variant":[
        "Bhuw\u0101lpur"
    ],
    "wof:name":"Bhuwalpur",
    "wof:placetype":"neighbourhood",
    "wof:population":3603
},
  "geometry": {"coordinates":[84.841174,25.868676],"type":"Point"}
}