{
  "type": "Feature",
  "properties": {
    "iso:country":"IN",
    "ks:ks_name":"Pinajageeru",
    "ks:ks_pop":176,
    "ks:ks_type":"VILLAGE",
    "name:eng_x_preferred":[
        "Pinajageeru"
    ],
    "wof:name":"Pinajageeru",
    "wof:placetype":"locality",
    "wof:population":176
},
  "geometry": {"coordinates":[82.458169,18.069571],"type":"Point"}
}