{
  "type": "Feature",
  "properties": {
    "iso:country":"IN",
    "ks:ks_name":"Asarifali",
    "ks:ks_pop":216,
    "ks:ks_type":"HABITATION",
    "name:eng_x_preferred":[
        "Asarifali"
    ],
    "wof:name":"Asarifali",
    "wof:placetype":"locality",
    "wof:population":216
},
  "geometry": {"coordinates":[73.49730599999999,23.550917],"type":"Point"}
}