{
  "type": "Feature",
  "properties": {
    "gn:admin1_code":"36",
    "gn:admin2_code":"188.0",
    "gn:asciiname":"Unchgaon",
    "gn:country_code":"IN",
    "gn:dem":81,
    "gn:feature_class":"P",
    "gn:feature_code":"PPL",
    "gn:name":"Unchg\u0101on",
    "gn:population":0,
    "gn:timezone":"Asia/Kolkata",
    "iso:country":"IN",
    "name:und_x_variant":[
        "Unchg\u0101on",
        "Semra M\u0101nik Chak"
    ],
    "wof:name":"Unchgaon",
    "wof:placetype":"locality"
},
  "geometry": {"coordinates":[83.44886,26.60726],"type":"Point"}
}