{
  "type": "Feature",
  "properties": {
    "gn:admin1_code":"23.0",
    "gn:admin2_code":"036",
    "gn:asciiname":"Kala Sanghian",
    "gn:country_code":"IN",
    "gn:dem":240,
    "gn:feature_class":"P",
    "gn:feature_code":"PPL",
    "gn:name":"K\u0101la Sanghi\u0101n",
    "gn:population":0,
    "gn:timezone":"Asia/Kolkata",
    "iso:country":"IN",
    "name:pan_x_preferred":[
        "\u0a15\u0a3e\u0a32\u0a3e \u0a38\u0a70\u0a18\u0a3f\u0a06\u0a02"
    ],
    "name:und_x_variant":[
        "K\u0101la Sanghi\u0101n",
        "K\u0101la"
    ],
    "wof:name":"Kala Sanghian",
    "wof:placetype":"locality"
},
  "geometry": {"coordinates":[75.44412,31.26278],"type":"Point"}
}