{
  "type": "Feature",
  "properties": {
    "gn:admin1_code":"19.0",
    "gn:admin2_code":"563.0",
    "gn:asciiname":"Holigadde",
    "gn:country_code":"IN",
    "gn:dem":20,
    "gn:feature_class":"P",
    "gn:feature_code":"PPL",
    "gn:name":"Holigadde",
    "gn:population":0,
    "gn:timezone":"Asia/Kolkata",
    "iso:country":"IN",
    "ks:ks_alt_nam":"holegadde",
    "ks:ks_name":"Holegadde",
    "ks:ks_pop":193,
    "ks:ks_type":"HABITATION",
    "name:eng_x_preferred":[
        "Holegadde"
    ],
    "name:eng_x_variant":[
        "Holigadde"
    ],
    "wof:name":"Holegadde",
    "wof:placetype":"locality",
    "wof:population":193
},
  "geometry": {"coordinates":[74.59880800000001,13.94829],"type":"Point"}
}