{
  "type": "Feature",
  "properties": {
    "iso:country":"IN",
    "ks:ks_name":"Hangarakanda",
    "ks:ks_pop":71,
    "ks:ks_type":"HABITATION",
    "name:eng_x_preferred":[
        "Hangarakanda"
    ],
    "wof:name":"Hangarakanda",
    "wof:placetype":"locality",
    "wof:population":71
},
  "geometry": {"coordinates":[74.85685100000001,14.487906],"type":"Point"}
}