{
  "type": "Feature",
  "properties": {
    "iso:country":"IN",
    "ks:ks_name":"Purnima",
    "ks:ks_pop":40,
    "ks:ks_type":"VILLAGE",
    "name:eng_x_preferred":[
        "Purnima"
    ],
    "wof:name":"Purnima",
    "wof:placetype":"locality",
    "wof:population":40
},
  "geometry": {"coordinates":[83.65203700000001,19.2525],"type":"Point"}
}