{
  "type": "Feature",
  "properties": {
    "iso:country":"IN",
    "ks:ks_name":"Khulet",
    "ks:ks_pop":260,
    "ks:ks_type":"VILLAGE",
    "name:eng_x_preferred":[
        "Khulet"
    ],
    "wof:name":"Khulet",
    "wof:placetype":"locality",
    "wof:population":260
},
  "geometry": {"coordinates":[80.11775900000001,29.65431],"type":"Point"}
}