{
  "type": "Feature",
  "properties": {
    "iso:country":"IN",
    "ks:ks_alt_nam":"MASALWASTI",
    "ks:ks_name":"Masalwasti",
    "ks:ks_pop":113,
    "ks:ks_type":"HABITATION",
    "name:eng_x_preferred":[
        "Masalwasti"
    ],
    "wof:name":"Masalwasti",
    "wof:placetype":"locality",
    "wof:population":113
},
  "geometry": {"coordinates":[75.01393,16.963561],"type":"Point"}
}