{
  "type": "Feature",
  "properties": {
    "gn:admin1_code":"19.0",
    "gn:admin2_code":"570.0",
    "gn:asciiname":"Kalakodagi",
    "gn:country_code":"IN",
    "gn:dem":842,
    "gn:feature_class":"P",
    "gn:feature_code":"PPL",
    "gn:name":"Kalakodagi",
    "gn:population":0,
    "gn:timezone":"Asia/Kolkata",
    "iso:country":"IN",
    "wof:name":"Kalakodagi",
    "wof:placetype":"locality"
},
  "geometry": {"coordinates":[75.42981,13.36567],"type":"Point"}
}