{
  "type": "Feature",
  "properties": {
    "iso:country":"IN",
    "ks:ks_name":"Alipur",
    "ks:ks_pop":12864,
    "ks:ks_type":"VILLAGE",
    "ks:ks_uagg_main":0,
    "name:eng_x_preferred":[
        "Alipur"
    ],
    "wof:name":"Alipur",
    "wof:placetype":"neighbourhood",
    "wof:population":12864
},
  "geometry": {"coordinates":[88.033046,24.853831],"type":"Point"}
}