{
  "type": "Feature",
  "properties": {
    "iso:country":"IN",
    "ks:ks_name":"Gompam",
    "ks:ks_pop":173,
    "ks:ks_type":"VILLAGE",
    "name:eng_x_preferred":[
        "Gompam"
    ],
    "wof:name":"Gompam",
    "wof:placetype":"locality",
    "wof:population":173
},
  "geometry": {"coordinates":[82.55497,17.925585],"type":"Point"}
}