{
  "type": "Feature",
  "properties": {
    "iso:country":"IN",
    "ks:ks_name":"Bhaloo Jogsar",
    "ks:ks_pop":651,
    "ks:ks_type":"VILLAGE",
    "name:eng_x_preferred":[
        "Bhaloo Jogsar"
    ],
    "wof:name":"Bhaloo Jogsar",
    "wof:placetype":"locality",
    "wof:population":651
},
  "geometry": {"coordinates":[72.53870000000001,26.619194],"type":"Point"}
}