{
  "type": "Feature",
  "properties": {
    "gn:admin1_code":"12.0",
    "gn:admin2_code":"009",
    "gn:asciiname":"Logirpur",
    "gn:country_code":"IN",
    "gn:dem":1592,
    "gn:feature_class":"P",
    "gn:feature_code":"PPL",
    "gn:name":"Logirpur",
    "gn:population":0,
    "gn:timezone":"Asia/Kolkata",
    "iso:country":"IN",
    "wof:name":"Logirpur",
    "wof:placetype":"locality"
},
  "geometry": {"coordinates":[74.40803000000002,34.3599],"type":"Point"}
}