{
  "type": "Feature",
  "properties": {
    "iso:country":"IN",
    "ks:ks_name":"Donigoda",
    "ks:ks_pop":0,
    "ks:ks_type":"VILLAGE",
    "name:eng_x_preferred":[
        "Donigoda"
    ],
    "wof:name":"Donigoda",
    "wof:placetype":"locality",
    "wof:population":0
},
  "geometry": {"coordinates":[87.469955,24.830108],"type":"Point"}
}