{
  "type": "Feature",
  "properties": {
    "iso:country":"IN",
    "ks:ks_name":"Nandpura",
    "ks:ks_pop":1301,
    "ks:ks_type":"VILLAGE",
    "ks:ks_uagg_main":0,
    "name:eng_x_preferred":[
        "Nandpura"
    ],
    "wof:name":"Nandpura",
    "wof:placetype":"locality",
    "wof:population":1301
},
  "geometry": {"coordinates":[76.171525,24.350289],"type":"Point"}
}