{
  "type": "Feature",
  "properties": {
    "gn:admin1_code":"34.0",
    "gn:admin2_code":"230.0",
    "gn:asciiname":"Chak Rahim",
    "gn:country_code":"IN",
    "gn:dem":58,
    "gn:feature_class":"P",
    "gn:feature_code":"PPL",
    "gn:name":"Chak Rah\u012bm",
    "gn:population":0,
    "gn:timezone":"Asia/Kolkata",
    "iso:country":"IN",
    "wof:name":"Chak Rahim",
    "wof:placetype":"locality"
},
  "geometry": {"coordinates":[85.17801,25.41754],"type":"Point"}
}