{
  "type": "Feature",
  "properties": {
    "gn:admin1_code":"22.0",
    "gn:admin2_code":"635.0",
    "gn:asciiname":"Singareddippalaiyam",
    "gn:country_code":"IN",
    "gn:dem":35,
    "gn:feature_class":"P",
    "gn:feature_code":"PPL",
    "gn:name":"Sing\u0101reddippalaiyam",
    "gn:population":0,
    "gn:timezone":"Asia/Kolkata",
    "iso:country":"IN",
    "wof:name":"Singareddippalaiyam",
    "wof:placetype":"locality"
},
  "geometry": {"coordinates":[79.70049,12.0183],"type":"Point"}
}