{
  "type": "Feature",
  "properties": {
    "gn:admin1_code":"25.0",
    "gn:admin2_code":"632.0",
    "gn:asciiname":"Kalampalaiyam",
    "gn:country_code":"IN",
    "gn:dem":379,
    "gn:feature_class":"P",
    "gn:feature_code":"PPL",
    "gn:name":"K\u0101lamp\u0101laiyam",
    "gn:population":0,
    "gn:timezone":"Asia/Kolkata",
    "iso:country":"IN",
    "ks:ks_name":"Kalampalayam",
    "ks:ks_pop":5432,
    "ks:ks_type":"VILLAGE",
    "ks:ks_uagg_main":0,
    "name:eng_x_preferred":[
        "Kalampalayam"
    ],
    "wof:name":"Kalampalayam",
    "wof:placetype":"neighbourhood",
    "wof:population":5432
},
  "geometry": {"coordinates":[76.87097199999999,11.206628],"type":"Point"}
}