{
  "type": "Feature",
  "properties": {
    "iso:country":"IN",
    "ks:ks_name":"Dakshin Maligram",
    "ks:ks_pop":174,
    "ks:ks_type":"VILLAGE",
    "ks:ks_uagg_main":0,
    "name:eng_x_preferred":[
        "Dakshin Maligram"
    ],
    "wof:name":"Dakshin Maligram",
    "wof:placetype":"neighbourhood",
    "wof:population":174
},
  "geometry": {"coordinates":[87.825675,23.902676],"type":"Point"}
}