{
  "type": "Feature",
  "properties": {
    "iso:country":"IN",
    "ks:ks_alt_nam":"RAM KRISHNA PARA",
    "ks:ks_name":"Ram Krishna Para",
    "ks:ks_pop":14,
    "ks:ks_type":"HABITATION",
    "ks:ks_uagg_main":0,
    "name:eng_x_preferred":[
        "Ram Krishna Para"
    ],
    "wof:name":"Ram Krishna Para",
    "wof:placetype":"neighbourhood",
    "wof:population":14
},
  "geometry": {"coordinates":[91.445217,23.923173],"type":"Point"}
}