{
  "type": "Feature",
  "properties": {
    "gn:admin1_code":"35",
    "gn:admin2_code":"419.0",
    "gn:asciiname":"Gulabpura",
    "gn:country_code":"IN",
    "gn:dem":191,
    "gn:feature_class":"P",
    "gn:feature_code":"PPL",
    "gn:name":"Gul\u0101bpura",
    "gn:population":0,
    "gn:timezone":"Asia/Kolkata",
    "iso:country":"IN",
    "name:ben_x_preferred":[
        "\u0997\u09c1\u09b2\u09be\u09ac\u09aa\u09c1\u09b0\u09be"
    ],
    "name:bpy_x_preferred":[
        "\u0997\u09c1\u09b2\u09be\u09ac\u09aa\u09c1\u09b0\u09be"
    ],
    "name:ceb_x_preferred":[
        "Gul\u0101bpura"
    ],
    "name:hin_x_preferred":[
        "\u0917\u0941\u0932\u093e\u092c\u092a\u0941\u0930\u093e"
    ],
    "name:ita_x_preferred":[
        "Gulabpura"
    ],
    "name:mlg_x_preferred":[
        "Gulabpura"
    ],
    "name:msa_x_preferred":[
        "Gulabpura"
    ],
    "name:new_x_preferred":[
        "\u0917\u0941\u0932\u093e\u092c\u092a\u0941\u0930\u093e"
    ],
    "name:por_x_preferred":[
        "Gulabpura"
    ],
    "name:swe_x_preferred":[
        "Gul\u0101bpura"
    ],
    "name:und_x_variant":[
        "Gul\u0101bpura",
        "Pachpent ka Pura"
    ],
    "name:vie_x_preferred":[
        "Gulabpura"
    ],
    "name:zho_x_preferred":[
        "\u53e4\u62c9\u5e03\u666e\u62c9"
    ],
    "wof:name":"Gulabpura",
    "wof:placetype":"locality"
},
  "geometry": {"coordinates":[77.58246,26.39443],"type":"Point"}
}