{
  "type": "Feature",
  "properties": {
    "iso:country":"IN",
    "ks:ks_name":"Nahala",
    "ks:ks_pop":1580,
    "ks:ks_type":"VILLAGE",
    "ks:ks_uagg_main":0,
    "name:eng_x_preferred":[
        "Nahala"
    ],
    "wof:name":"Nahala",
    "wof:placetype":"locality",
    "wof:population":1580
},
  "geometry": {"coordinates":[87.994209,22.487123],"type":"Point"}
}