{
  "type": "Feature",
  "properties": {
    "iso:country":"IN",
    "ks:ks_name":"Channarayanahalli",
    "ks:ks_type":"VILLAGE",
    "name:eng_x_preferred":[
        "Channarayanahalli"
    ],
    "wof:name":"Channarayanahalli",
    "wof:placetype":"locality"
},
  "geometry": {"coordinates":[77.762412,13.74165],"type":"Point"}
}