{
  "type": "Feature",
  "properties": {
    "iso:country":"IN",
    "ks:ks_name":"Chamariya Khamariya",
    "ks:ks_pop":472,
    "ks:ks_type":"VILLAGE",
    "name:eng_x_preferred":[
        "Chamariya Khamariya"
    ],
    "wof:name":"Chamariya Khamariya",
    "wof:placetype":"locality",
    "wof:population":472
},
  "geometry": {"coordinates":[77.697754,23.153081],"type":"Point"}
}