{
  "type": "Feature",
  "properties": {
    "gn:admin1_code":"36.0",
    "gn:admin2_code":"154.0",
    "gn:asciiname":"Gangupur",
    "gn:country_code":"IN",
    "gn:dem":128,
    "gn:feature_class":"P",
    "gn:feature_code":"PPL",
    "gn:name":"G\u0101ngupur",
    "gn:population":0,
    "gn:timezone":"Asia/Kolkata",
    "iso:country":"IN",
    "wof:name":"Gangupur",
    "wof:placetype":"locality"
},
  "geometry": {"coordinates":[80.64814,27.26625],"type":"Point"}
}