{
  "type": "Feature",
  "properties": {
    "gn:admin1_code":"35",
    "gn:admin2_code":"447.0",
    "gn:asciiname":"Baretha",
    "gn:country_code":"IN",
    "gn:dem":466,
    "gn:feature_class":"P",
    "gn:feature_code":"PPL",
    "gn:name":"Baretha",
    "gn:population":0,
    "gn:timezone":"Asia/Kolkata",
    "iso:country":"IN",
    "wof:name":"Baretha",
    "wof:placetype":"locality"
},
  "geometry": {"coordinates":[77.89516,22.13715],"type":"Point"}
}