{
  "type": "Feature",
  "properties": {
    "iso:country":"IN",
    "ks:ks_alt_nam":"LACHUMAN BIGHA",
    "ks:ks_name":"Lachuman Bigha",
    "ks:ks_pop":260,
    "ks:ks_type":"HABITATION",
    "name:eng_x_preferred":[
        "Lachuman Bigha"
    ],
    "wof:name":"Lachuman Bigha",
    "wof:placetype":"locality",
    "wof:population":260
},
  "geometry": {"coordinates":[84.85333900000001,25.015375],"type":"Point"}
}