{
  "type": "Feature",
  "properties": {
    "gn:admin1_code":"19.0",
    "gn:admin2_code":"572.0",
    "gn:asciiname":"Gudimau",
    "gn:country_code":"IN",
    "gn:dem":767,
    "gn:feature_class":"P",
    "gn:feature_code":"PPL",
    "gn:name":"Gudimau",
    "gn:population":0,
    "gn:timezone":"Asia/Kolkata",
    "iso:country":"IN",
    "ks:ks_name":"Gudimavu",
    "ks:ks_pop":196,
    "ks:ks_type":"VILLAGE",
    "ks:ks_uagg_main":0,
    "name:eng_x_preferred":[
        "Gudimavu"
    ],
    "wof:name":"Gudimavu",
    "wof:placetype":"locality",
    "wof:population":196
},
  "geometry": {"coordinates":[77.46275,12.867215],"type":"Point"}
}