{
  "type": "Feature",
  "properties": {
    "gn:admin1_code":"13.0",
    "gn:admin2_code":"595.0",
    "gn:asciiname":"Padinjare Kadungalur",
    "gn:country_code":"IN",
    "gn:dem":12,
    "gn:feature_class":"P",
    "gn:feature_code":"PPL",
    "gn:name":"Padinj\u0101re Kadungal\u016br",
    "gn:population":0,
    "gn:timezone":"Asia/Kolkata",
    "iso:country":"IN",
    "wof:name":"Padinjare Kadungalur",
    "wof:placetype":"locality"
},
  "geometry": {"coordinates":[76.32247,10.10732],"type":"Point"}
}