{
  "type": "Feature",
  "properties": {
    "iso:country":"IN",
    "ks:ks_name":"Hanagod",
    "ks:ks_pop":13,
    "ks:ks_type":"HABITATION",
    "name:eng_x_preferred":[
        "Hanagod"
    ],
    "wof:name":"Hanagod",
    "wof:placetype":"locality",
    "wof:population":13
},
  "geometry": {"coordinates":[74.78688099999999,14.248048],"type":"Point"}
}