{
  "type": "Feature",
  "properties": {
    "gn:admin1_code":"35",
    "gn:admin2_code":"419.0",
    "gn:asciiname":"Bastauli",
    "gn:country_code":"IN",
    "gn:dem":190,
    "gn:feature_class":"P",
    "gn:feature_code":"PPL",
    "gn:name":"Bastauli",
    "gn:population":0,
    "gn:timezone":"Asia/Kolkata",
    "iso:country":"IN",
    "name:ara_x_preferred":[
        "\u0628\u0627\u0633\u062a\u0648\u0644\u064a"
    ],
    "name:ben_bn_x_preferred":[
        "\u09ac\u09be\u09b8\u09a4\u09be\u0989\u09b2\u09bf"
    ],
    "name:ben_in_x_preferred":[
        "\u09ac\u09be\u09b8\u09a4\u09be\u0989\u09b2\u09bf"
    ],
    "name:guj_x_preferred":[
        "\u0aac\u0ab8\u0acd\u0aa4\u0acc\u0ab2\u0ac0"
    ],
    "name:hin_x_preferred":[
        "\u092c\u0938\u094d\u0924\u094c\u0932\u0940"
    ],
    "name:kan_x_preferred":[
        "\u0cac\u0cb8\u0ccd\u0ca4\u0ccc\u0cb2\u0cbf"
    ],
    "name:mal_x_preferred":[
        "\u0d2c\u0d38\u0d4d\u0d24\u0d57\u0d32\u0d3f"
    ],
    "name:mar_x_preferred":[
        "\u092c\u0938\u094d\u0924\u094c\u0932\u0940"
    ],
    "name:pan_x_preferred":[
        "\u0a2c\u0a38\u0a24\u0a4c\u0a32\u0a40"
    ],
    "name:tam_x_preferred":[
        "\u0baa\u0b9a\u0b9f\u0bcc\u0bb2\u0bbf"
    ],
    "name:tel_x_preferred":[
        "\u0c2c\u0c38\u0c4d\u0c1f\u0c4c\u0c32\u0c3f"
    ],
    "name:urd_x_preferred":[
        "\u0628\u0633\u062a\u0648\u0644\u06cc"
    ],
    "wof:name":"Bastauli",
    "wof:placetype":"locality"
},
  "geometry": {"coordinates":[77.66767,26.29757],"type":"Point"}
}