{
  "type": "Feature",
  "properties": {
    "iso:country":"IN",
    "ks:ks_name":"Bishunpur",
    "ks:ks_pop":75,
    "ks:ks_type":"VILLAGE",
    "ks:ks_uagg_main":0,
    "name:eng_x_preferred":[
        "Bishunpur"
    ],
    "wof:name":"Bishunpur",
    "wof:placetype":"neighbourhood",
    "wof:population":75
},
  "geometry": {"coordinates":[83.44428000000001,25.894804],"type":"Point"}
}