{
  "type": "Feature",
  "properties": {
    "iso:country":"IN",
    "ks:ks_name":"Burugulanka",
    "ks:ks_pop":236,
    "ks:ks_type":"HABITATION",
    "name:eng_x_preferred":[
        "Burugulanka"
    ],
    "wof:name":"Burugulanka",
    "wof:placetype":"locality",
    "wof:population":236
},
  "geometry": {"coordinates":[82.12566200000001,16.66685],"type":"Point"}
}