{
  "type": "Feature",
  "properties": {
    "iso:country":"IN",
    "ks:ks_name":"Islampur No.2",
    "ks:ks_pop":2131,
    "ks:ks_type":"VILLAGE",
    "ks:ks_uagg_main":0,
    "name:eng_x_preferred":[
        "Islampur No.2"
    ],
    "wof:name":"Islampur No.2",
    "wof:placetype":"neighbourhood",
    "wof:population":2131
},
  "geometry": {"coordinates":[93.96381100000001,27.092877],"type":"Point"}
}