{
  "type": "Feature",
  "properties": {
    "gn:admin1_code":"19.0",
    "gn:admin2_code":"567.0",
    "gn:asciiname":"Gode",
    "gn:country_code":"IN",
    "gn:dem":690,
    "gn:feature_class":"P",
    "gn:feature_code":"PPL",
    "gn:name":"Gode",
    "gn:population":0,
    "gn:timezone":"Asia/Kolkata",
    "iso:country":"IN",
    "name:deu_x_preferred":[
        "Gode"
    ],
    "name:fas_x_preferred":[
        "\u06af\u0648\u062f\u0647"
    ],
    "name:fra_x_preferred":[
        "Gode"
    ],
    "name:heb_x_preferred":[
        "\u05d2\u05d5\u05d3\u05d4"
    ],
    "name:hrv_x_preferred":[
        "Gode"
    ],
    "name:hun_x_preferred":[
        "Gode"
    ],
    "name:ita_x_preferred":[
        "Gode"
    ],
    "name:nld_x_preferred":[
        "Gode"
    ],
    "name:pol_x_preferred":[
        "Gode"
    ],
    "name:por_x_preferred":[
        "Gode"
    ],
    "name:ron_x_preferred":[
        "Gode"
    ],
    "name:rus_x_preferred":[
        "\u0413\u043e\u0434\u0435"
    ],
    "name:som_x_preferred":[
        "Godeey"
    ],
    "name:ukr_x_preferred":[
        "\u0413\u043e\u0434\u0435"
    ],
    "name:vie_x_preferred":[
        "Gode"
    ],
    "wof:name":"Gode",
    "wof:placetype":"locality"
},
  "geometry": {"coordinates":[76.22257,14.57398],"type":"Point"}
}