{
  "type": "Feature",
  "properties": {
    "iso:country":"IN",
    "ks:ks_name":"Chaipara",
    "ks:ks_pop":2343,
    "ks:ks_type":"VILLAGE",
    "ks:ks_uagg_main":0,
    "name:eng_x_preferred":[
        "Chaipara"
    ],
    "wof:name":"Chaipara",
    "wof:placetype":"neighbourhood",
    "wof:population":2343
},
  "geometry": {"coordinates":[88.26785599999999,24.25661],"type":"Point"}
}