{
  "type": "Feature",
  "properties": {
    "gn:admin1_code":"16.0",
    "gn:admin2_code":"498.0",
    "gn:asciiname":"Mukti",
    "gn:country_code":"IN",
    "gn:dem":253,
    "gn:feature_class":"P",
    "gn:feature_code":"PPL",
    "gn:name":"Mukti",
    "gn:population":0,
    "gn:timezone":"Asia/Kolkata",
    "iso:country":"IN",
    "wof:name":"Mukti",
    "wof:placetype":"locality"
},
  "geometry": {"coordinates":[74.68222,21.1012],"type":"Point"}
}