{
  "type": "Feature",
  "properties": {
    "iso:country":"IN",
    "ks:ks_name":"Paschimpara",
    "ks:ks_pop":740,
    "ks:ks_type":"HABITATION",
    "ks:ks_uagg_main":0,
    "name:eng_x_preferred":[
        "Paschimpara"
    ],
    "wof:name":"Paschimpara",
    "wof:placetype":"neighbourhood",
    "wof:population":740
},
  "geometry": {"coordinates":[88.29491299999999,22.990552],"type":"Point"}
}