{
  "type": "Feature",
  "properties": {
    "iso:country":"IN",
    "ks:ks_name":"Bakapur",
    "ks:ks_pop":625,
    "ks:ks_type":"VILLAGE",
    "ks:ks_uagg_main":0,
    "name:eng_x_preferred":[
        "Bakapur"
    ],
    "wof:name":"Bakapur",
    "wof:placetype":"neighbourhood",
    "wof:population":625
},
  "geometry": {"coordinates":[75.420528,19.933518],"type":"Point"}
}