{
  "type": "Feature",
  "properties": {
    "iso:country":"IN",
    "ks:ks_name":"Paharidih",
    "ks:ks_pop":389,
    "ks:ks_type":"HABITATION",
    "name:eng_x_preferred":[
        "Paharidih"
    ],
    "wof:name":"Paharidih",
    "wof:placetype":"locality",
    "wof:population":389
},
  "geometry": {"coordinates":[86.799796,24.799576],"type":"Point"}
}