{
  "type": "Feature",
  "properties": {
    "iso:country":"IN",
    "ks:ks_name":"Mohaniya Falia",
    "ks:ks_pop":716,
    "ks:ks_type":"HABITATION",
    "ks:ks_uagg_main":0,
    "name:eng_x_preferred":[
        "Mohaniya Falia"
    ],
    "wof:name":"Mohaniya Falia",
    "wof:placetype":"neighbourhood",
    "wof:population":716
},
  "geometry": {"coordinates":[74.352833,22.779361],"type":"Point"}
}