{
  "type": "Feature",
  "properties": {
    "iso:country":"IN",
    "ks:ks_name":"Karungalpatti",
    "ks:ks_pop":401,
    "ks:ks_type":"VILLAGE",
    "ks:ks_uagg_main":0,
    "name:eng_x_preferred":[
        "Karungalpatti"
    ],
    "wof:name":"Karungalpatti",
    "wof:placetype":"neighbourhood",
    "wof:population":401
},
  "geometry": {"coordinates":[78.341741,11.542469],"type":"Point"}
}