{
  "type": "Feature",
  "properties": {
    "iso:country":"IN",
    "ks:ks_name":"Devari Tola",
    "ks:ks_pop":576,
    "ks:ks_type":"HABITATION",
    "name:eng_x_preferred":[
        "Devari Tola"
    ],
    "wof:name":"Devari Tola",
    "wof:placetype":"locality",
    "wof:population":576
},
  "geometry": {"coordinates":[83.057531,24.079105],"type":"Point"}
}