{
  "type": "Feature",
  "properties": {
    "iso:country":"IN",
    "ks:ks_name":"Dyurari",
    "ks:ks_pop":161,
    "ks:ks_type":"VILLAGE",
    "name:eng_x_preferred":[
        "Dyurari"
    ],
    "wof:name":"Dyurari",
    "wof:placetype":"locality",
    "wof:population":161
},
  "geometry": {"coordinates":[79.22926200000001,29.659848],"type":"Point"}
}