{
  "type": "Feature",
  "properties": {
    "iso:country":"IN",
    "ks:ks_name":"Gobinda Para",
    "ks:ks_pop":116,
    "ks:ks_type":"HABITATION",
    "name:eng_x_preferred":[
        "Gobinda Para"
    ],
    "wof:name":"Gobinda Para",
    "wof:placetype":"locality",
    "wof:population":116
},
  "geometry": {"coordinates":[91.700112,23.168354],"type":"Point"}
}