{
  "type": "Feature",
  "properties": {
    "iso:country":"IN",
    "ks:ks_name":"Dakshin Para",
    "ks:ks_pop":1396,
    "ks:ks_type":"HABITATION",
    "name:eng_x_preferred":[
        "Dakshin Para"
    ],
    "wof:name":"Dakshin Para",
    "wof:placetype":"locality",
    "wof:population":1396
},
  "geometry": {"coordinates":[88.534521,22.103196],"type":"Point"}
}