{
  "type": "Feature",
  "properties": {
    "gn:admin1_code":"36.0",
    "gn:admin2_code":"141.0",
    "gn:asciiname":"Makrandpur",
    "gn:country_code":"IN",
    "gn:dem":206,
    "gn:feature_class":"P",
    "gn:feature_code":"PPL",
    "gn:name":"Makrandpur",
    "gn:population":0,
    "gn:timezone":"Asia/Kolkata",
    "iso:country":"IN",
    "name:und_x_variant":[
        "Fatehpur"
    ],
    "wof:name":"Makrandpur",
    "wof:placetype":"locality"
},
  "geometry": {"coordinates":[77.67471,28.37588],"type":"Point"}
}