{
  "type": "Feature",
  "properties": {
    "gn:admin1_code":"12.0",
    "gn:admin2_code":"005",
    "gn:asciiname":"Fakir Dorax",
    "gn:country_code":"IN",
    "gn:dem":943,
    "gn:feature_class":"P",
    "gn:feature_code":"PPL",
    "gn:name":"Fak\u012br Dorax",
    "gn:population":0,
    "gn:timezone":"Asia/Kolkata",
    "iso:country":"IN",
    "name:und_x_variant":[
        "Fak\u012br Dorax",
        "Fak\u012br D\u0101ra",
        "Fak\u012br Dara"
    ],
    "wof:name":"Fakir Dorax",
    "wof:placetype":"locality"
},
  "geometry": {"coordinates":[74.02994,33.76006],"type":"Point"}
}