{
  "type": "Feature",
  "properties": {
    "gn:admin1_code":"36.0",
    "gn:admin2_code":"138.0",
    "gn:asciiname":"Qamruddinnagar Mandyai",
    "gn:country_code":"IN",
    "gn:dem":229,
    "gn:feature_class":"P",
    "gn:feature_code":"PPL",
    "gn:name":"Qamrudd\u012bnnagar Mandy\u0101i",
    "gn:population":0,
    "gn:timezone":"Asia/Kolkata",
    "iso:country":"IN",
    "wof:name":"Qamruddinnagar Mandyai",
    "wof:placetype":"locality"
},
  "geometry": {"coordinates":[77.62141,29.11322],"type":"Point"}
}