{
  "type": "Feature",
  "properties": {
    "gn:admin1_code":"39",
    "gn:admin2_code":"60.0",
    "gn:asciiname":"Gomaniwala",
    "gn:country_code":"IN",
    "gn:dem":346,
    "gn:feature_class":"P",
    "gn:feature_code":"PPL",
    "gn:name":"Gomaniw\u0101la",
    "gn:population":0,
    "gn:timezone":"Asia/Kolkata",
    "iso:country":"IN",
    "ks:ks_alt_nam":"Gomaniw\u0101la",
    "ks:ks_alt_nam_2":"Gomaniwala",
    "ks:ks_name":"Gumaniwala",
    "ks:ks_pop":5450,
    "ks:ks_type":"VILLAGE",
    "ks:ks_uagg_main":1,
    "name:eng_x_preferred":[
        "Gumaniwala"
    ],
    "name:eng_x_variant":[
        "Gomaniwala",
        "Gomaniw\u0101la"
    ],
    "wof:name":"Gumaniwala",
    "wof:placetype":"locality",
    "wof:population":5450
},
  "geometry": {"coordinates":[78.237965,30.064975],"type":"Point"}
}