{
  "type": "Feature",
  "properties": {
    "iso:country":"IN",
    "ks:ks_name":"Dhaka Chora",
    "ks:ks_pop":188,
    "ks:ks_type":"VILLAGE",
    "ks:ks_uagg_main":0,
    "name:eng_x_preferred":[
        "Dhaka Chora"
    ],
    "wof:name":"Dhaka Chora",
    "wof:placetype":"neighbourhood",
    "wof:population":188
},
  "geometry": {"coordinates":[87.792288,22.108631],"type":"Point"}
}