{
  "type": "Feature",
  "properties": {
    "iso:country":"IN",
    "ks:ks_alt_nam":"East Bhanukumari III No Ward",
    "ks:ks_name":"East Bhanukumari Iii No Ward",
    "ks:ks_pop":2000,
    "ks:ks_type":"HABITATION",
    "name:eng_x_preferred":[
        "East Bhanukumari Iii No Ward"
    ],
    "wof:name":"East Bhanukumari Iii No Ward",
    "wof:placetype":"locality",
    "wof:population":2000
},
  "geometry": {"coordinates":[89.75414499999999,26.426162],"type":"Point"}
}