{
  "type": "Feature",
  "properties": {
    "iso:country":"IN",
    "qs:name":"Majarekashi",
    "qs:name_adm0":"India",
    "qs:name_adm1":"Maharashtra",
    "qs:photos":15,
    "qs:photos_1k":3,
    "qs:photos_9k":1,
    "qs:photos_9r":1,
    "qs:photos_all":15,
    "qs:photos_sr":1,
    "qs:placetype":"Town",
    "qs:pop_sr":"0",
    "wof:name":"Majarekashi",
    "wof:placetype":"locality"
},
  "geometry": {"coordinates":[73.496983,17.55732],"type":"Point"}
}