{
  "type": "Feature",
  "properties": {
    "iso:country":"IN",
    "ks:ks_name":"Maliwasti",
    "ks:ks_pop":115,
    "ks:ks_type":"HABITATION",
    "name:eng_x_preferred":[
        "Maliwasti"
    ],
    "wof:name":"Maliwasti",
    "wof:placetype":"locality",
    "wof:population":115
},
  "geometry": {"coordinates":[74.17976299999999,17.31467],"type":"Point"}
}