{
  "type": "Feature",
  "properties": {
    "iso:country":"IN",
    "ks:ks_name":"Fatullapur",
    "ks:ks_pop":2866,
    "ks:ks_type":"VILLAGE",
    "ks:ks_uagg_main":0,
    "name:eng_x_preferred":[
        "Fatullapur"
    ],
    "wof:name":"Fatullapur",
    "wof:placetype":"neighbourhood",
    "wof:population":2866
},
  "geometry": {"coordinates":[88.073463,24.537966],"type":"Point"}
}