{
  "type": "Feature",
  "properties": {
    "iso:country":"IN",
    "ks:ks_name":"Kitumulu",
    "ks:ks_pop":221,
    "ks:ks_type":"VILLAGE",
    "name:eng_x_preferred":[
        "Kitumulu"
    ],
    "wof:name":"Kitumulu",
    "wof:placetype":"locality",
    "wof:population":221
},
  "geometry": {"coordinates":[82.409549,18.052117],"type":"Point"}
}