{
  "type": "Feature",
  "properties": {
    "gn:admin1_code":"12.0",
    "gn:admin2_code":"16.0",
    "gn:asciiname":"Lakhan",
    "gn:country_code":"IN",
    "gn:dem":2855,
    "gn:feature_class":"P",
    "gn:feature_code":"PPL",
    "gn:name":"L\u0101khan",
    "gn:population":0,
    "gn:timezone":"Asia/Kolkata",
    "iso:country":"IN",
    "wof:name":"Lakhan",
    "wof:placetype":"locality"
},
  "geometry": {"coordinates":[76.01625,33.06204],"type":"Point"}
}