{
  "type": "Feature",
  "properties": {
    "gn:admin1_code":"40.0",
    "gn:admin2_code":"534.0",
    "gn:asciiname":"Mallapalli",
    "gn:country_code":"IN",
    "gn:dem":227,
    "gn:feature_class":"P",
    "gn:feature_code":"PPL",
    "gn:name":"Mallapalli",
    "gn:population":0,
    "gn:timezone":"Asia/Kolkata",
    "iso:country":"IN",
    "wof:name":"Mallapalli",
    "wof:placetype":"locality"
},
  "geometry": {"coordinates":[79.48541999999998,18.34325],"type":"Point"}
}