{
  "type": "Feature",
  "properties": {
    "iso:country":"IN",
    "ks:ks_alt_nam":"kudichapada",
    "ks:ks_name":"Kudichapada",
    "ks:ks_pop":70,
    "ks:ks_type":"HABITATION",
    "name:eng_x_preferred":[
        "Kudichapada"
    ],
    "wof:name":"Kudichapada",
    "wof:placetype":"locality",
    "wof:population":70
},
  "geometry": {"coordinates":[72.89995500000001,19.688933],"type":"Point"}
}