{
  "type": "Feature",
  "properties": {
    "iso:country":"IN",
    "ks:ks_name":"Tan",
    "ks:ks_pop":40,
    "ks:ks_type":"HABITATION",
    "name:eng_x_preferred":[
        "Tan"
    ],
    "wof:name":"Tan",
    "wof:placetype":"locality",
    "wof:population":40
},
  "geometry": {"coordinates":[73.251147,19.120141],"type":"Point"}
}