{
  "type": "Feature",
  "properties": {
    "iso:country":"IN",
    "ks:ks_name":"Bellipal",
    "ks:ks_pop":82,
    "ks:ks_type":"HABITATION",
    "name:eng_x_preferred":[
        "Bellipal"
    ],
    "wof:name":"Bellipal",
    "wof:placetype":"locality",
    "wof:population":82
},
  "geometry": {"coordinates":[74.56705599999999,14.861224],"type":"Point"}
}