{
  "type": "Feature",
  "properties": {
    "iso:country":"IN",
    "name:ben_x_preferred":[
        "\u09a4\u09bf\u09b0\u09c1\u09ac\u09b2\u09cd\u09b2\u09c0\u0995\u09c7\u09a3\u09bf"
    ],
    "name:cat_x_preferred":[
        "Triplicane"
    ],
    "name:deu_x_preferred":[
        "Triplicane"
    ],
    "name:eng_x_preferred":[
        "Triplicane"
    ],
    "name:eng_x_variant":[
        "Madras Triplicane"
    ],
    "name:fra_x_preferred":[
        "Triplicane"
    ],
    "name:nld_x_preferred":[
        "Triplicane"
    ],
    "name:tam_x_preferred":[
        "\u0ba4\u0bbf\u0bb0\u0bc1\u0bb5\u0bb2\u0bcd\u0bb2\u0bbf\u0b95\u0bcd\u0b95\u0bc7\u0ba3\u0bbf"
    ],
    "qs:gn_adm0_cc":"IN",
    "qs:gn_fcode":"PPLX",
    "qs:gn_local":1264527,
    "qs:gn_nam_loc":"Chennai, Chennai, Tamil Nadu, IN",
    "qs:gn_namadm1":"25",
    "qs:gn_name":"Triplicane",
    "qs:local_max":2138,
    "qs:local_sum":21081,
    "qs:localhoods":47,
    "qs:name":"Triplicane",
    "qs:name_adm0":"India",
    "qs:name_adm1":"Tamil Nadu",
    "qs:name_adm2":"Chennai",
    "qs:name_local":"Chennai",
    "qs:photo_max":165,
    "qs:photo_sum":901,
    "qs:placetype":"Suburb",
    "qs:quad_count":50,
    "qs:woe_adm0":23424848,
    "qs:woe_adm1":2345758,
    "qs:woe_adm2":12586677,
    "qs:woe_lau":0,
    "qs:woe_local":2295424,
    "qs:woe_ver":"7.10.0",
    "wd:wordcount":4140,
    "wof:lang":[
        "eng"
    ],
    "wof:name":"Triplicane",
    "wof:placetype":"neighbourhood"
},
  "geometry": {"coordinates":[80.26756899999999,13.053618],"type":"Point"}
}