{
  "type": "Feature",
  "properties": {
    "gn:admin1_code":"36.0",
    "gn:admin2_code":"183.0",
    "gn:asciiname":"Pura Gajraj Singh",
    "gn:country_code":"IN",
    "gn:dem":101,
    "gn:feature_class":"P",
    "gn:feature_code":"PPL",
    "gn:name":"Pura Gajr\u0101j Singh",
    "gn:population":0,
    "gn:timezone":"Asia/Kolkata",
    "iso:country":"IN",
    "wof:name":"Pura Gajraj Singh",
    "wof:placetype":"neighbourhood"
},
  "geometry": {"coordinates":[81.87705,26.94822],"type":"Point"}
}