{
  "type": "Feature",
  "properties": {
    "iso:country":"IN",
    "name:cat_x_preferred":[
        "Jal Mahal"
    ],
    "name:eng_x_preferred":[
        "Jal Mahal"
    ],
    "name:fas_x_preferred":[
        "\u062c\u0627\u0644 \u0645\u062d\u0644"
    ],
    "name:fra_x_preferred":[
        "Jal Mahal"
    ],
    "name:guj_x_preferred":[
        "\u0a9c\u0ab2 \u0aae\u0ab9\u0ac7\u0ab2"
    ],
    "name:hin_x_preferred":[
        "\u091c\u0932 \u092e\u0939\u0932"
    ],
    "name:kas_x_preferred":[
        "\u062c\u064e\u0644 \u0645\u064e\u062d\u0644"
    ],
    "name:mal_x_preferred":[
        "\u0d1c\u0d7d \u0d2e\u0d39\u0d7d"
    ],
    "name:msa_x_preferred":[
        "Jal Mahal"
    ],
    "name:pan_x_preferred":[
        "\u0a1c\u0a32 \u0a2e\u0a39\u0a3f\u0a32"
    ],
    "name:tha_x_preferred":[
        "\u0e0a\u0e31\u0e25 \u0e21\u0e2b\u0e31\u0e25"
    ],
    "name:unk_x_variant":[
        "Jal Mahal"
    ],
    "name:vie_x_preferred":[
        "Jal Mahal"
    ],
    "name:zho_x_preferred":[
        "\u6c34\u4e4b\u5bab\u6bbf"
    ],
    "qs:gn_local":0,
    "qs:local_max":159,
    "qs:local_sum":159,
    "qs:localhoods":1,
    "qs:name":"Jal Mahal",
    "qs:name_adm0":"India",
    "qs:name_adm1":"Rajasthan",
    "qs:name_adm2":"Jaipur",
    "qs:name_local":"Jal Mahal",
    "qs:photo_max":87,
    "qs:photo_sum":159,
    "qs:placetype":"POI",
    "qs:quad_count":5,
    "qs:woe_adm0":23424848,
    "qs:woe_adm1":2345757,
    "qs:woe_adm2":12586662,
    "qs:woe_funk":"Changed from suburb in 7.3.1",
    "qs:woe_lau":0,
    "qs:woe_local":55959567,
    "qs:woe_ver":"7.10.0",
    "wd:wordcount":3891,
    "wof:lang":[
        "eng"
    ],
    "wof:name":"Jal Mahal",
    "wof:placetype":"neighbourhood"
},
  "geometry": {"coordinates":[75.848328,26.954291],"type":"Point"}
}