{
  "type": "Feature",
  "properties": {
    "iso:country":"IN",
    "ks:ks_name":"Mittapalem",
    "ks:ks_pop":65,
    "ks:ks_type":"HABITATION",
    "name:eng_x_preferred":[
        "Mittapalem"
    ],
    "wof:name":"Mittapalem",
    "wof:placetype":"locality",
    "wof:population":65
},
  "geometry": {"coordinates":[80.10733999999999,14.084441],"type":"Point"}
}