{
  "type": "Feature",
  "properties": {
    "iso:country":"IN",
    "ks:ks_name":"Yelemala",
    "ks:ks_pop":57,
    "ks:ks_type":"HABITATION",
    "name:eng_x_preferred":[
        "Yelemala"
    ],
    "wof:name":"Yelemala",
    "wof:placetype":"locality",
    "wof:population":57
},
  "geometry": {"coordinates":[74.512332,14.281814],"type":"Point"}
}