{
  "type": "Feature",
  "properties": {
    "gn:admin1_code":"25.0",
    "gn:admin2_code":"629.0",
    "gn:asciiname":"Marthandam",
    "gn:country_code":"IN",
    "gn:dem":62,
    "gn:feature_class":"P",
    "gn:feature_code":"PPL",
    "gn:name":"Marthandam",
    "gn:population":0,
    "gn:timezone":"Asia/Kolkata",
    "iso:country":"IN",
    "name:tam_x_preferred":[
        "\u0bae\u0bbe\u0bb0\u0bcd\u0ba4\u0bcd\u0ba4\u0bbe\u0ba3\u0bcd\u0b9f\u0bae\u0bcd"
    ],
    "wof:name":"Marthandam",
    "wof:placetype":"neighbourhood"
},
  "geometry": {"coordinates":[77.22144,8.30812],"type":"Point"}
}