{
  "type": "Feature",
  "properties": {
    "iso:country":"IN",
    "ks:ks_name":"Ezhumuttom",
    "ks:ks_pop":745,
    "ks:ks_type":"HABITATION",
    "ks:ks_uagg_main":0,
    "name:eng_x_preferred":[
        "Ezhumuttom"
    ],
    "wof:name":"Ezhumuttom",
    "wof:placetype":"neighbourhood",
    "wof:population":745
},
  "geometry": {"coordinates":[76.75733200000001,9.921243],"type":"Point"}
}