{
  "type": "Feature",
  "properties": {
    "iso:country":"IN",
    "ks:ks_name":"Gadragan-ii",
    "ks:ks_pop":289,
    "ks:ks_type":"VILLAGE",
    "name:eng_x_preferred":[
        "Gadragan-ii"
    ],
    "wof:name":"Gadragan-ii",
    "wof:placetype":"locality",
    "wof:population":289
},
  "geometry": {"coordinates":[84.48708000000001,20.233534],"type":"Point"}
}