{
  "type": "Feature",
  "properties": {
    "iso:country":"IN",
    "ks:ks_name":"Bara",
    "ks:ks_pop":996,
    "ks:ks_type":"HABITATION",
    "name:eng_x_preferred":[
        "Bara"
    ],
    "wof:name":"Bara",
    "wof:placetype":"locality",
    "wof:population":996
},
  "geometry": {"coordinates":[74.16528599999999,24.121569],"type":"Point"}
}