{
  "type": "Feature",
  "properties": {
    "gn:admin1_code":"13.0",
    "gn:admin2_code":"601.0",
    "gn:asciiname":"Bhadrakali Chetram",
    "gn:country_code":"IN",
    "gn:dem":14,
    "gn:feature_class":"P",
    "gn:feature_code":"PPL",
    "gn:name":"Bhadrak\u0101li Chetram",
    "gn:population":0,
    "gn:timezone":"Asia/Kolkata",
    "iso:country":"IN",
    "wof:name":"Bhadrakali Chetram",
    "wof:placetype":"neighbourhood"
},
  "geometry": {"coordinates":[76.90483999999999,8.51005],"type":"Point"}
}