{
  "type": "Feature",
  "properties": {
    "iso:country":"IN",
    "ks:ks_name":"Mangudi",
    "ks:ks_pop":185,
    "ks:ks_type":"HABITATION",
    "name:eng_x_preferred":[
        "Mangudi"
    ],
    "wof:name":"Mangudi",
    "wof:placetype":"locality",
    "wof:population":185
},
  "geometry": {"coordinates":[78.899142,9.77861],"type":"Point"}
}