{
  "type": "Feature",
  "properties": {
    "iso:country":"IN",
    "ks:ks_name":"Balmoti",
    "ks:ks_pop":163,
    "ks:ks_type":"VILLAGE",
    "name:eng_x_preferred":[
        "Balmoti"
    ],
    "wof:name":"Balmoti",
    "wof:placetype":"locality",
    "wof:population":163
},
  "geometry": {"coordinates":[83.467158,19.101031],"type":"Point"}
}