{
  "type": "Feature",
  "properties": {
    "iso:country":"IN",
    "ks:ks_name":"Hosur",
    "ks:ks_pop":30,
    "ks:ks_type":"HABITATION",
    "name:eng_x_preferred":[
        "Hosur"
    ],
    "wof:name":"Hosur",
    "wof:placetype":"locality",
    "wof:population":30
},
  "geometry": {"coordinates":[75.817656,13.43495],"type":"Point"}
}