{
  "type": "Feature",
  "properties": {
    "iso:country":"IN",
    "ks:ks_name":"Hulagod",
    "ks:ks_pop":228,
    "ks:ks_type":"HABITATION",
    "name:eng_x_preferred":[
        "Hulagod"
    ],
    "wof:name":"Hulagod",
    "wof:placetype":"locality",
    "wof:population":228
},
  "geometry": {"coordinates":[74.820122,14.868587],"type":"Point"}
}