{
  "type": "Feature",
  "properties": {
    "iso:country":"IN",
    "ks:ks_name":"Mal",
    "ks:ks_pop":1551,
    "ks:ks_type":"HABITATION",
    "name:eng_x_preferred":[
        "Mal"
    ],
    "wof:name":"Mal",
    "wof:placetype":"locality",
    "wof:population":1551
},
  "geometry": {"coordinates":[74.119212,21.717572],"type":"Point"}
}