{
  "type": "Feature",
  "properties": {
    "iso:country":"IN",
    "ks:ks_name":"1 PGM",
    "ks:ks_pop":410,
    "ks:ks_type":"VILLAGE",
    "name:eng_x_preferred":[
        "1 PGM"
    ],
    "wof:name":"1 PGM",
    "wof:placetype":"locality",
    "wof:population":410
},
  "geometry": {"coordinates":[73.286733,29.163053],"type":"Point"}
}