{
  "type": "Feature",
  "properties": {
    "iso:country":"IN",
    "ks:ks_name":"Sawantwadi",
    "ks:ks_pop":254,
    "ks:ks_type":"HABITATION",
    "name:eng_x_preferred":[
        "Sawantwadi"
    ],
    "wof:name":"Sawantwadi",
    "wof:placetype":"locality",
    "wof:population":254
},
  "geometry": {"coordinates":[73.720737,16.331165],"type":"Point"}
}