{
  "type": "Feature",
  "properties": {
    "iso:country":"IN",
    "ks:ks_name":"Kherivav",
    "ks:ks_pop":508,
    "ks:ks_type":"VILLAGE",
    "name:eng_x_preferred":[
        "Kherivav"
    ],
    "wof:name":"Kherivav",
    "wof:placetype":"locality",
    "wof:population":508
},
  "geometry": {"coordinates":[73.148557,24.0464],"type":"Point"}
}