{
  "type": "Feature",
  "properties": {
    "gn:admin1_code":"36",
    "gn:admin2_code":"143.0",
    "gn:asciiname":"Hetampur",
    "gn:country_code":"IN",
    "gn:dem":188,
    "gn:feature_class":"P",
    "gn:feature_code":"PPL",
    "gn:name":"Hetampur",
    "gn:population":0,
    "gn:timezone":"Asia/Kolkata",
    "iso:country":"IN",
    "ks:ks_name":"Hetampur",
    "ks:ks_pop":240,
    "ks:ks_type":"VILLAGE",
    "name:ben_x_preferred":[
        "\u09b9\u09c7\u09a4\u09ae\u09aa\u09c1\u09b0"
    ],
    "wof:name":"Hetampur",
    "wof:placetype":"neighbourhood"
},
  "geometry": {"coordinates":[78.11335,27.94772],"type":"Point"}
}