{
  "type": "Feature",
  "properties": {
    "gn:admin1_code":"19.0",
    "gn:admin2_code":"568.0",
    "gn:asciiname":"Ambatirtha",
    "gn:country_code":"IN",
    "gn:dem":683,
    "gn:feature_class":"P",
    "gn:feature_code":"PPL",
    "gn:name":"Ambat\u012brtha",
    "gn:population":0,
    "gn:timezone":"Asia/Kolkata",
    "iso:country":"IN",
    "ks:ks_alt_nam":"AMBUTHIRTHA",
    "ks:ks_name":"Ambuthirtha",
    "ks:ks_pop":291,
    "ks:ks_type":"HABITATION",
    "name:eng_x_preferred":[
        "Ambuthirtha"
    ],
    "name:eng_x_variant":[
        "Ambatirtha"
    ],
    "wof:name":"Ambuthirtha",
    "wof:placetype":"locality",
    "wof:population":291
},
  "geometry": {"coordinates":[75.176835,13.79185],"type":"Point"}
}