{
  "type": "Feature",
  "properties": {
    "gn:admin1_code":"40.0",
    "gn:admin2_code":"541.0",
    "gn:asciiname":"Totapalle",
    "gn:country_code":"IN",
    "gn:dem":51,
    "gn:feature_class":"P",
    "gn:feature_code":"PPL",
    "gn:name":"Totapalle",
    "gn:population":0,
    "gn:timezone":"Asia/Kolkata",
    "iso:country":"IN",
    "ks:ks_name":"Thotapalle",
    "ks:ks_pop":632,
    "ks:ks_type":"VILLAGE",
    "ks:ks_uagg_main":0,
    "name:eng_x_preferred":[
        "Thotapalle"
    ],
    "wof:name":"Thotapalle",
    "wof:placetype":"neighbourhood",
    "wof:population":632
},
  "geometry": {"coordinates":[81.056189,17.627453],"type":"Point"}
}