{
  "type": "Feature",
  "properties": {
    "iso:country":"IN",
    "ks:ks_name":"Jhmpa",
    "ks:ks_pop":737,
    "ks:ks_type":"HABITATION",
    "name:eng_x_preferred":[
        "Jhmpa"
    ],
    "wof:name":"Jhmpa",
    "wof:placetype":"locality",
    "wof:population":737
},
  "geometry": {"coordinates":[88.243712,22.892369],"type":"Point"}
}