{
  "type": "Feature",
  "properties": {
    "gn:admin1_code":"34.0",
    "gn:admin2_code":"207.0",
    "gn:asciiname":"Kaurna",
    "gn:country_code":"IN",
    "gn:dem":75,
    "gn:feature_class":"P",
    "gn:feature_code":"PPL",
    "gn:name":"Kaurna",
    "gn:population":0,
    "gn:timezone":"Asia/Kolkata",
    "iso:country":"IN",
    "name:deu_x_preferred":[
        "Kaurna"
    ],
    "name:fra_x_preferred":[
        "Kaurna"
    ],
    "wof:name":"Kaurna",
    "wof:placetype":"locality"
},
  "geometry": {"coordinates":[86.01640999999999,26.63328],"type":"Point"}
}