{
  "type": "Feature",
  "properties": {
    "iso:country":"IN",
    "ks:ks_name":"Aunachudam",
    "ks:ks_pop":395,
    "ks:ks_type":"HABITATION",
    "name:eng_x_preferred":[
        "Aunachudam"
    ],
    "wof:name":"Aunachudam",
    "wof:placetype":"locality",
    "wof:population":395
},
  "geometry": {"coordinates":[76.383166,10.699021],"type":"Point"}
}