{
  "type": "Feature",
  "properties": {
    "iso:country":"IN",
    "ks:ks_name":"Scatted Hub",
    "ks:ks_pop":210,
    "ks:ks_type":"HABITATION",
    "name:eng_x_preferred":[
        "Scatted Hub"
    ],
    "wof:name":"Scatted Hub",
    "wof:placetype":"locality",
    "wof:population":210
},
  "geometry": {"coordinates":[73.733075,29.725314],"type":"Point"}
}