{
  "type": "Feature",
  "properties": {
    "iso:country":"IN",
    "ks:ks_name":"Bari Tola",
    "ks:ks_pop":336,
    "ks:ks_type":"HABITATION",
    "ks:ks_uagg_main":0,
    "name:eng_x_preferred":[
        "Bari Tola"
    ],
    "wof:name":"Bari Tola",
    "wof:placetype":"neighbourhood",
    "wof:population":336
},
  "geometry": {"coordinates":[83.472827,26.686758],"type":"Point"}
}