{
  "type": "Feature",
  "properties": {
    "iso:country":"IN",
    "ks:ks_name":"Sakabaripur Uprhar",
    "ks:ks_pop":1646,
    "ks:ks_type":"VILLAGE",
    "name:eng_x_preferred":[
        "Sakabaripur Uprhar"
    ],
    "wof:name":"Sakabaripur Uprhar",
    "wof:placetype":"locality",
    "wof:population":1646
},
  "geometry": {"coordinates":[81.531633,25.586376],"type":"Point"}
}