{
  "type": "Feature",
  "properties": {
    "gn:admin1_code":"16.0",
    "gn:admin2_code":"511",
    "gn:asciiname":"Kandahar",
    "gn:country_code":"IN",
    "gn:dem":432,
    "gn:feature_class":"P",
    "gn:feature_code":"PPL",
    "gn:name":"Kandah\u0101r",
    "gn:population":0,
    "gn:timezone":"Asia/Kolkata",
    "iso:country":"IN",
    "wof:name":"Kandahar",
    "wof:placetype":"locality"
},
  "geometry": {"coordinates":[77.19230999999998,18.87312],"type":"Point"}
}