{
  "type": "Feature",
  "properties": {
    "iso:country":"IN",
    "ks:ks_name":"Kumbrigadde",
    "ks:ks_pop":12,
    "ks:ks_type":"HABITATION",
    "name:eng_x_preferred":[
        "Kumbrigadde"
    ],
    "wof:name":"Kumbrigadde",
    "wof:placetype":"locality",
    "wof:population":12
},
  "geometry": {"coordinates":[74.718903,14.47929],"type":"Point"}
}