{
  "type": "Feature",
  "properties": {
    "iso:country":"IN",
    "ks:ks_alt_nam":"Makalathu KonalethuKulangara",
    "ks:ks_name":"Makalathu Konalethukulangara",
    "ks:ks_pop":1257,
    "ks:ks_type":"HABITATION",
    "name:eng_x_preferred":[
        "Makalathu Konalethukulangara"
    ],
    "wof:name":"Makalathu Konalethukulangara",
    "wof:placetype":"neighbourhood",
    "wof:population":1257
},
  "geometry": {"coordinates":[76.453406,9.28961],"type":"Point"}
}