{
  "type": "Feature",
  "properties": {
    "iso:country":"IN",
    "ks:ks_name":"Gowdanakere",
    "ks:ks_pop":644,
    "ks:ks_type":"HABITATION",
    "name:eng_x_preferred":[
        "Gowdanakere"
    ],
    "wof:name":"Gowdanakere",
    "wof:placetype":"locality",
    "wof:population":644
},
  "geometry": {"coordinates":[75.664901,13.042843],"type":"Point"}
}