{
  "type": "Feature",
  "properties": {
    "iso:country":"IN",
    "ks:ks_name":"Velangudy",
    "ks:ks_pop":562,
    "ks:ks_type":"HABITATION",
    "name:eng_x_preferred":[
        "Velangudy"
    ],
    "wof:name":"Velangudy",
    "wof:placetype":"locality",
    "wof:population":562
},
  "geometry": {"coordinates":[79.62548,11.000107],"type":"Point"}
}