{
  "type": "Feature",
  "properties": {
    "iso:country":"IN",
    "ks:ks_name":"Aamarpura",
    "ks:ks_pop":719,
    "ks:ks_type":"HABITATION",
    "name:eng_x_preferred":[
        "Aamarpura"
    ],
    "wof:name":"Aamarpura",
    "wof:placetype":"locality",
    "wof:population":719
},
  "geometry": {"coordinates":[72.380906,26.252156],"type":"Point"}
}