{
  "type": "Feature",
  "properties": {
    "iso:country":"IN",
    "ks:ks_name":"Jaipur",
    "ks:ks_pop":270,
    "ks:ks_type":"VILLAGE",
    "name:eng_x_preferred":[
        "Jaipur"
    ],
    "wof:name":"Jaipur",
    "wof:placetype":"locality",
    "wof:population":270
},
  "geometry": {"coordinates":[87.088813,24.485835],"type":"Point"}
}