{
  "type": "Feature",
  "properties": {
    "gn:admin1_code":"35",
    "gn:admin2_code":"458.0",
    "gn:asciiname":"Jesalmer",
    "gn:country_code":"IN",
    "gn:dem":420,
    "gn:feature_class":"P",
    "gn:feature_code":"PPL",
    "gn:name":"Jesalmer",
    "gn:population":0,
    "gn:timezone":"Asia/Kolkata",
    "iso:country":"IN",
    "wof:name":"Jesalmer",
    "wof:placetype":"locality"
},
  "geometry": {"coordinates":[77.20094,24.32475],"type":"Point"}
}