{
  "type": "Feature",
  "properties": {
    "iso:country":"IN",
    "ks:ks_name":"Sani Tapu",
    "ks:ks_pop":7,
    "ks:ks_type":"HABITATION",
    "name:eng_x_preferred":[
        "Sani Tapu"
    ],
    "wof:name":"Sani Tapu",
    "wof:placetype":"locality",
    "wof:population":7
},
  "geometry": {"coordinates":[92.467213,26.531005],"type":"Point"}
}