{
  "type": "Feature",
  "properties": {
    "iso:country":"IN",
    "ks:ks_name":"Timil Gair",
    "ks:ks_pop":37,
    "ks:ks_type":"HABITATION",
    "name:eng_x_preferred":[
        "Timil Gair"
    ],
    "wof:name":"Timil Gair",
    "wof:placetype":"locality",
    "wof:population":37
},
  "geometry": {"coordinates":[79.29912400000001,29.959988],"type":"Point"}
}