{
  "type": "Feature",
  "properties": {
    "iso:country":"IN",
    "ks:ks_name":"Kakkaveri",
    "ks:ks_pop":5851,
    "ks:ks_type":"VILLAGE",
    "ks:ks_uagg_main":0,
    "name:eng_x_preferred":[
        "Kakkaveri"
    ],
    "wof:name":"Kakkaveri",
    "wof:placetype":"neighbourhood",
    "wof:population":5851
},
  "geometry": {"coordinates":[78.218355,11.452712],"type":"Point"}
}