{
  "type": "Feature",
  "properties": {
    "iso:country":"IN",
    "ks:ks_name":"Kalliadippu",
    "ks:ks_pop":311,
    "ks:ks_type":"HABITATION",
    "ks:ks_uagg_main":0,
    "name:eng_x_preferred":[
        "Kalliadippu"
    ],
    "wof:name":"Kalliadippu",
    "wof:placetype":"neighbourhood",
    "wof:population":311
},
  "geometry": {"coordinates":[77.859673,8.518532],"type":"Point"}
}