{
  "type": "Feature",
  "properties": {
    "iso:country":"IN",
    "ks:ks_name":"Bakongbari",
    "ks:ks_pop":421,
    "ks:ks_type":"HABITATION",
    "name:eng_x_preferred":[
        "Bakongbari"
    ],
    "wof:name":"Bakongbari",
    "wof:placetype":"locality",
    "wof:population":421
},
  "geometry": {"coordinates":[91.938559,26.115918],"type":"Point"}
}