{
  "type": "Feature",
  "properties": {
    "iso:country":"IN",
    "ks:ks_name":"Jhuntiasahi",
    "ks:ks_pop":145,
    "ks:ks_type":"VILLAGE",
    "name:eng_x_preferred":[
        "Jhuntiasahi"
    ],
    "wof:name":"Jhuntiasahi",
    "wof:placetype":"locality",
    "wof:population":145
},
  "geometry": {"coordinates":[84.18072100000001,19.085257],"type":"Point"}
}