{
  "type": "Feature",
  "properties": {
    "iso:country":"IN",
    "ks:ks_alt_nam":"Sengmari Boro supa",
    "ks:ks_name":"Sengmari Boro Supa",
    "ks:ks_pop":346,
    "ks:ks_type":"HABITATION",
    "ks:ks_uagg_main":0,
    "name:eng_x_preferred":[
        "Sengmari Boro Supa"
    ],
    "wof:name":"Sengmari Boro Supa",
    "wof:placetype":"neighbourhood",
    "wof:population":346
},
  "geometry": {"coordinates":[91.64470900000001,26.62174],"type":"Point"}
}