{
  "type": "Feature",
  "properties": {
    "iso:country":"IN",
    "ks:ks_name":"Damodarpur",
    "ks:ks_pop":1053,
    "ks:ks_type":"VILLAGE",
    "name:eng_x_preferred":[
        "Damodarpur"
    ],
    "wof:name":"Damodarpur",
    "wof:placetype":"locality",
    "wof:population":1053
},
  "geometry": {"coordinates":[85.095653,26.076188],"type":"Point"}
}