{
  "type": "Feature",
  "properties": {
    "gn:admin1_code":"2",
    "gn:admin2_code":"544.0",
    "gn:asciiname":"Malinguda",
    "gn:country_code":"IN",
    "gn:dem":1045,
    "gn:feature_class":"P",
    "gn:feature_code":"PPL",
    "gn:name":"Maling\u016bda",
    "gn:population":0,
    "gn:timezone":"Asia/Kolkata",
    "iso:country":"IN",
    "wof:name":"Malinguda",
    "wof:placetype":"locality"
},
  "geometry": {"coordinates":[82.81676999999998,18.4314],"type":"Point"}
}