{
  "type": "Feature",
  "properties": {
    "iso:country":"IN",
    "ks:ks_name":"Khurhari",
    "ks:ks_pop":738,
    "ks:ks_type":"VILLAGE",
    "ks:ks_uagg_main":0,
    "name:eng_x_preferred":[
        "Khurhari"
    ],
    "wof:name":"Khurhari",
    "wof:placetype":"neighbourhood",
    "wof:population":738
},
  "geometry": {"coordinates":[83.568319,26.513224],"type":"Point"}
}