{
  "type": "Feature",
  "properties": {
    "gn:admin1_code":"39.0",
    "gn:admin2_code":"061",
    "gn:asciiname":"Chamoligaon",
    "gn:country_code":"IN",
    "gn:dem":811,
    "gn:feature_class":"P",
    "gn:feature_code":"PPL",
    "gn:name":"Chamoligaon",
    "gn:population":0,
    "gn:timezone":"Asia/Kolkata",
    "iso:country":"IN",
    "ks:ks_name":"Chamoli Gaon",
    "ks:ks_pop":108,
    "ks:ks_type":"VILLAGE",
    "name:eng_x_preferred":[
        "Chamoli Gaon"
    ],
    "name:eng_x_variant":[
        "Chamoligaon"
    ],
    "wof:name":"Chamoli Gaon",
    "wof:placetype":"locality",
    "wof:population":108
},
  "geometry": {"coordinates":[78.68603899999999,29.943459],"type":"Point"}
}