{
  "type": "Feature",
  "properties": {
    "gn:admin1_code":"39.0",
    "gn:admin2_code":"061",
    "gn:asciiname":"Chamoligaon",
    "gn:country_code":"IN",
    "gn:dem":811,
    "gn:feature_class":"P",
    "gn:feature_code":"PPL",
    "gn:name":"Chamoligaon",
    "gn:population":0,
    "gn:timezone":"Asia/Kolkata",
    "iso:country":"IN",
    "wof:name":"Chamoligaon",
    "wof:placetype":"locality"
},
  "geometry": {"coordinates":[78.68701999999998,29.94393],"type":"Point"}
}