{
  "type": "Feature",
  "properties": {
    "iso:country":"IN",
    "ks:ks_alt_nam":"Kamlakund tola",
    "ks:ks_name":"Kamlakund Tola",
    "ks:ks_pop":182,
    "ks:ks_type":"HABITATION",
    "ks:ks_uagg_main":0,
    "name:eng_x_preferred":[
        "Kamlakund Tola"
    ],
    "wof:name":"Kamlakund Tola",
    "wof:placetype":"neighbourhood",
    "wof:population":182
},
  "geometry": {"coordinates":[87.19374500000001,25.327366],"type":"Point"}
}