{
  "type": "Feature",
  "properties": {
    "gn:admin1_code":"35",
    "gn:admin2_code":"422.0",
    "gn:asciiname":"Merpura",
    "gn:country_code":"IN",
    "gn:dem":161,
    "gn:feature_class":"P",
    "gn:feature_code":"PPL",
    "gn:name":"Merpura",
    "gn:population":0,
    "gn:timezone":"Asia/Kolkata",
    "iso:country":"IN",
    "ks:ks_name":"Medpura",
    "ks:ks_pop":14,
    "ks:ks_type":"VILLAGE",
    "name:eng_x_preferred":[
        "Medpura"
    ],
    "name:eng_x_variant":[
        "Merpura"
    ],
    "wof:name":"Medpura",
    "wof:placetype":"locality",
    "wof:population":14
},
  "geometry": {"coordinates":[78.637787,26.086295],"type":"Point"}
}