{
  "type": "Feature",
  "properties": {
    "iso:country":"IN",
    "ks:ks_name":"Itavati",
    "ks:ks_pop":1200,
    "ks:ks_type":"HABITATION",
    "name:eng_x_preferred":[
        "Itavati"
    ],
    "wof:name":"Itavati",
    "wof:placetype":"locality",
    "wof:population":1200
},
  "geometry": {"coordinates":[88.73428699999999,22.212114],"type":"Point"}
}