{
  "type": "Feature",
  "properties": {
    "iso:country":"IN",
    "ks:ks_name":"Vemuguntapalem",
    "ks:ks_pop":472,
    "ks:ks_type":"HABITATION",
    "name:eng_x_preferred":[
        "Vemuguntapalem"
    ],
    "wof:name":"Vemuguntapalem",
    "wof:placetype":"locality",
    "wof:population":472
},
  "geometry": {"coordinates":[80.06675300000001,13.921],"type":"Point"}
}