{
  "type": "Feature",
  "properties": {
    "iso:country":"IN",
    "ks:ks_name":"Uman",
    "ks:ks_pop":123,
    "ks:ks_type":"VILLAGE",
    "name:eng_x_preferred":[
        "Uman"
    ],
    "wof:name":"Uman",
    "wof:placetype":"locality",
    "wof:population":123
},
  "geometry": {"coordinates":[78.60208900000001,30.02774],"type":"Point"}
}