{
  "type": "Feature",
  "properties": {
    "iso:country":"IN",
    "ks:ks_name":"Aurangpur Nandlal",
    "ks:ks_pop":549,
    "ks:ks_type":"VILLAGE",
    "name:eng_x_preferred":[
        "Aurangpur Nandlal"
    ],
    "wof:name":"Aurangpur Nandlal",
    "wof:placetype":"locality",
    "wof:population":549
},
  "geometry": {"coordinates":[78.267219,29.43879],"type":"Point"}
}