{
  "type": "Feature",
  "properties": {
    "iso:country":"IN",
    "ks:ks_alt_nam":"kamerkarwadi",
    "ks:ks_name":"Kamerkarwadi",
    "ks:ks_pop":146,
    "ks:ks_type":"HABITATION",
    "name:eng_x_preferred":[
        "Kamerkarwadi"
    ],
    "wof:name":"Kamerkarwadi",
    "wof:placetype":"locality",
    "wof:population":146
},
  "geometry": {"coordinates":[73.553056,16.959167],"type":"Point"}
}