{
  "type": "Feature",
  "properties": {
    "iso:country":"IN",
    "ks:ks_alt_nam":"Amm\u0101p\u0101laiyam Reserved Forest",
    "ks:ks_name":"Ammapalaiyam Reserved Forest",
    "ks:ks_type":"VILLAGE",
    "name:eng_x_preferred":[
        "Ammapalaiyam Reserved Forest"
    ],
    "name:eng_x_variant":[
        "Amm\u0101p\u0101laiyam Reserved Forest"
    ],
    "wof:name":"Ammapalaiyam Reserved Forest",
    "wof:placetype":"locality"
},
  "geometry": {"coordinates":[78.57555600000001,11.843785],"type":"Point"}
}