{
  "type": "Feature",
  "properties": {
    "iso:country":"IN",
    "ks:ks_alt_nam":"baisath",
    "ks:ks_name":"Baisath",
    "ks:ks_pop":120,
    "ks:ks_type":"HABITATION",
    "name:eng_x_preferred":[
        "Baisath"
    ],
    "wof:name":"Baisath",
    "wof:placetype":"locality",
    "wof:population":120
},
  "geometry": {"coordinates":[82.837509,27.189411],"type":"Point"}
}