{
  "type": "Feature",
  "properties": {
    "iso:country":"IN",
    "ks:ks_name":"Sonekodi",
    "ks:ks_pop":150,
    "ks:ks_type":"HABITATION",
    "name:eng_x_preferred":[
        "Sonekodi"
    ],
    "wof:name":"Sonekodi",
    "wof:placetype":"locality",
    "wof:population":150
},
  "geometry": {"coordinates":[74.810515,13.433573],"type":"Point"}
}