{
  "type": "Feature",
  "properties": {
    "iso:country":"IN",
    "ks:ks_name":"Noda",
    "ks:ks_pop":110,
    "ks:ks_type":"VILLAGE",
    "name:eng_x_preferred":[
        "Noda"
    ],
    "wof:name":"Noda",
    "wof:placetype":"locality",
    "wof:population":110
},
  "geometry": {"coordinates":[78.433308,30.057378],"type":"Point"}
}