{
  "type": "Feature",
  "properties": {
    "gn:admin1_code":"12.0",
    "gn:admin2_code":"7.0",
    "gn:asciiname":"Thakurdwara",
    "gn:country_code":"IN",
    "gn:dem":848,
    "gn:feature_class":"P",
    "gn:feature_code":"PPL",
    "gn:name":"Thakurdw\u0101ra",
    "gn:population":0,
    "gn:timezone":"Asia/Kolkata",
    "iso:country":"IN",
    "wof:name":"Thakurdwara",
    "wof:placetype":"locality"
},
  "geometry": {"coordinates":[75.52311999999998,32.63834],"type":"Point"}
}