{
  "type": "Feature",
  "properties": {
    "gn:admin1_code":"12.0",
    "gn:admin2_code":"7.0",
    "gn:asciiname":"Thakurdwara",
    "gn:country_code":"IN",
    "gn:dem":848,
    "gn:feature_class":"P",
    "gn:feature_code":"PPL",
    "gn:name":"Thakurdw\u0101ra",
    "gn:population":0,
    "gn:timezone":"Asia/Kolkata",
    "iso:country":"IN",
    "name:bpy_x_preferred":[
        "\u09a0\u09be\u0995\u09c1\u09b0\u09a6\u09f1\u09be\u09b0\u09be"
    ],
    "name:ceb_x_preferred":[
        "Thakurdwara"
    ],
    "name:ita_x_preferred":[
        "Thakurdwara"
    ],
    "name:mlg_x_preferred":[
        "Thakurdwara"
    ],
    "name:msa_x_preferred":[
        "Thakurdwara"
    ],
    "name:nld_x_preferred":[
        "Thakurdwara"
    ],
    "name:ori_x_preferred":[
        "\u0b20\u0b3e\u0b15\u0b41\u0b30\u0b26\u0b4d\u0b71\u0b3e\u0b30"
    ],
    "name:pnb_x_preferred":[
        "\u0679\u06be\u0627\u06a9\u0631\u062f\u0648\u0627\u0691\u06c1"
    ],
    "name:pol_x_preferred":[
        "Thakurdwara"
    ],
    "name:por_x_preferred":[
        "Thakurdwara"
    ],
    "name:swe_x_preferred":[
        "Thakurdwara"
    ],
    "name:urd_x_preferred":[
        "\u0679\u06be\u0627\u06a9\u0631\u062f\u0648\u0627\u0691\u06c1"
    ],
    "name:vie_x_preferred":[
        "Thakurdwara"
    ],
    "name:zho_x_preferred":[
        "\u5854\u5e93\u5c14\u5fb7\u74e6\u62c9"
    ],
    "wof:name":"Thakurdwara",
    "wof:placetype":"locality"
},
  "geometry": {"coordinates":[75.52311999999998,32.63834],"type":"Point"}
}