{
  "type": "Feature",
  "properties": {
    "iso:country":"IN",
    "ks:ks_name":"Bhagwanpur Simra",
    "ks:ks_pop":2424,
    "ks:ks_type":"VILLAGE",
    "name:eng_x_preferred":[
        "Bhagwanpur Simra"
    ],
    "wof:name":"Bhagwanpur Simra",
    "wof:placetype":"locality",
    "wof:population":2424
},
  "geometry": {"coordinates":[85.100075,26.070975],"type":"Point"}
}