{
  "type": "Feature",
  "properties": {
    "iso:country":"IN",
    "ks:ks_alt_nam":"Murbhat faliya",
    "ks:ks_name":"Murbhat Faliya",
    "ks:ks_pop":355,
    "ks:ks_type":"HABITATION",
    "name:eng_x_preferred":[
        "Murbhat Faliya"
    ],
    "wof:name":"Murbhat Faliya",
    "wof:placetype":"locality",
    "wof:population":355
},
  "geometry": {"coordinates":[73.458181,20.52813],"type":"Point"}
}