{
  "type": "Feature",
  "properties": {
    "iso:country":"IN",
    "ks:ks_name":"Dihatelasara",
    "ks:ks_pop":848,
    "ks:ks_type":"VILLAGE",
    "ks:ks_uagg_main":0,
    "name:eng_x_preferred":[
        "Dihatelasara"
    ],
    "wof:name":"Dihatelasara",
    "wof:placetype":"neighbourhood",
    "wof:population":848
},
  "geometry": {"coordinates":[86.246888,20.059564],"type":"Point"}
}