{
  "type": "Feature",
  "properties": {
    "gn:admin1_code":"11",
    "gn:admin2_code":"23.0",
    "gn:asciiname":"Chawa",
    "gn:country_code":"IN",
    "gn:dem":1466,
    "gn:feature_class":"P",
    "gn:feature_code":"PPL",
    "gn:name":"Chawa",
    "gn:population":0,
    "gn:timezone":"Asia/Kolkata",
    "iso:country":"IN",
    "name:fas_x_preferred":[
        "\u0686\u0627\u0648\u0627"
    ],
    "name:und_x_variant":[
        "Choh"
    ],
    "name:urd_x_preferred":[
        "\u0686\u0627\u0648\u0627"
    ],
    "wof:name":"Chawa",
    "wof:placetype":"locality"
},
  "geometry": {"coordinates":[76.03519,32.40862],"type":"Point"}
}