{
  "type": "Feature",
  "properties": {
    "gn:admin1_code":"34.0",
    "gn:admin2_code":"230.0",
    "gn:asciiname":"Kishanpur",
    "gn:country_code":"IN",
    "gn:dem":50,
    "gn:feature_class":"P",
    "gn:feature_code":"PPL",
    "gn:name":"Kishanpur",
    "gn:population":0,
    "gn:timezone":"Asia/Kolkata",
    "iso:country":"IN",
    "ks:ks_name":"Kisunpur",
    "ks:ks_pop":1325,
    "ks:ks_type":"VILLAGE",
    "name:eng_x_preferred":[
        "Kisunpur"
    ],
    "name:eng_x_variant":[
        "Kishanpur"
    ],
    "wof:name":"Kisunpur",
    "wof:placetype":"locality",
    "wof:population":1325
},
  "geometry": {"coordinates":[85.67482699999999,25.376426],"type":"Point"}
}