{
  "type": "Feature",
  "properties": {
    "gn:admin1_code":"16.0",
    "gn:admin2_code":"499.0",
    "gn:asciiname":"Gata",
    "gn:country_code":"IN",
    "gn:dem":221,
    "gn:feature_class":"P",
    "gn:feature_code":"PPL",
    "gn:name":"G\u0101ta",
    "gn:population":0,
    "gn:timezone":"Asia/Kolkata",
    "iso:country":"IN",
    "name:bos_x_preferred":[
        "Gata"
    ],
    "name:cat_x_preferred":[
        "Gata"
    ],
    "name:ceb_x_preferred":[
        "Gata"
    ],
    "name:deu_x_preferred":[
        "Perreo#Wortherkunft"
    ],
    "name:fra_x_preferred":[
        "Gata"
    ],
    "name:glg_x_preferred":[
        "Gata"
    ],
    "name:nld_x_preferred":[
        "Gata"
    ],
    "name:por_x_preferred":[
        "Gata"
    ],
    "name:slv_x_preferred":[
        "Gata"
    ],
    "name:spa_x_preferred":[
        "Gata"
    ],
    "name:srp_x_preferred":[
        "\u0413\u0430\u0442\u0430"
    ],
    "name:swe_x_preferred":[
        "Gata"
    ],
    "name:tur_x_preferred":[
        "Gata"
    ],
    "wof:name":"Gata",
    "wof:placetype":"locality"
},
  "geometry": {"coordinates":[75.91141,21.1073],"type":"Point"}
}