{
  "type": "Feature",
  "properties": {
    "gn:admin1_code":"23.0",
    "gn:admin2_code":"44.0",
    "gn:asciiname":"Sammewali",
    "gn:country_code":"IN",
    "gn:dem":194,
    "gn:feature_class":"P",
    "gn:feature_code":"PPL",
    "gn:name":"Sammew\u0101li",
    "gn:population":0,
    "gn:timezone":"Asia/Kolkata",
    "iso:country":"IN",
    "wof:name":"Sammewali",
    "wof:placetype":"locality"
},
  "geometry": {"coordinates":[74.29278000000002,30.41669000000001],"type":"Point"}
}