{
  "type": "Feature",
  "properties": {
    "gn:admin1_code":"35.0",
    "gn:admin2_code":"442.0",
    "gn:asciiname":"Aluni",
    "gn:country_code":"IN",
    "gn:dem":434,
    "gn:feature_class":"P",
    "gn:feature_code":"PPL",
    "gn:name":"Al\u016bni",
    "gn:population":0,
    "gn:timezone":"Asia/Kolkata",
    "iso:country":"IN",
    "name:ara_x_preferred":[
        "\u0623\u0644\u0648\u0646\u064a"
    ],
    "name:aze_x_preferred":[
        "Aluni"
    ],
    "name:ceb_x_preferred":[
        "\u0100l\u016bn\u012b"
    ],
    "name:fas_x_preferred":[
        "\u0622\u0644\u0648\u0646\u06cc"
    ],
    "name:mlg_x_preferred":[
        "Aluni"
    ],
    "name:msa_x_preferred":[
        "Aluni"
    ],
    "name:swe_x_preferred":[
        "\u0100l\u016bn\u012b"
    ],
    "name:tur_x_preferred":[
        "Aluni"
    ],
    "name:urd_x_preferred":[
        "\u0622\u0644\u0648\u0646\u06cc"
    ],
    "wof:name":"Aluni",
    "wof:placetype":"locality"
},
  "geometry": {"coordinates":[76.66160000000001,23.5944],"type":"Point"}
}