{
  "type": "Feature",
  "properties": {
    "gn:admin1_code":"37",
    "gn:admin2_code":"406.0",
    "gn:asciiname":"Saket",
    "gn:country_code":"IN",
    "gn:dem":256,
    "gn:feature_class":"P",
    "gn:feature_code":"PPL",
    "gn:name":"Saket",
    "gn:population":0,
    "gn:timezone":"Asia/Kolkata",
    "iso:country":"IN",
    "name:ara_x_preferred":[
        "\u0633\u0627\u0643\u064a\u062a"
    ],
    "name:ben_bn_x_preferred":[
        "\u09b8\u09be\u0995\u09c7\u09a4"
    ],
    "name:ben_in_x_preferred":[
        "\u09b8\u09be\u0995\u09c7\u09a4"
    ],
    "name:guj_x_preferred":[
        "\u0ab8\u0abe\u0a95\u0ac7\u0a9f"
    ],
    "name:hin_x_preferred":[
        "\u0938\u093e\u0915\u0947\u0924"
    ],
    "name:kan_x_preferred":[
        "\u0cb8\u0cbe\u0c95\u0cc7\u0ca4\u0ccd"
    ],
    "name:mal_x_preferred":[
        "\u0d38\u0d3e\u0d15\u0d47\u0d24\u0d4d"
    ],
    "name:mar_x_preferred":[
        "\u0938\u093e\u0915\u0947\u0924"
    ],
    "name:pan_x_preferred":[
        "\u0a38\u0a3e\u0a15\u0a47\u0a24"
    ],
    "name:spa_x_preferred":[
        "Saketa"
    ],
    "name:tam_x_preferred":[
        "\u0b9a\u0bbe\u0b95\u0bc7\u0ba4\u0bcd"
    ],
    "name:tam_x_variant":[
        "\u0b9a\u0b95\u0bc7\u0ba4\u0bae\u0bcd"
    ],
    "name:tel_x_preferred":[
        "\u0c38\u0c3e\u0c15\u0c47\u0c24\u0c4d"
    ],
    "name:urd_x_preferred":[
        "\u0633\u0627\u06a9\u06cc\u062a"
    ],
    "wof:name":"Saket",
    "wof:placetype":"locality"
},
  "geometry": {"coordinates":[81.97291,22.00075],"type":"Point"}
}