{
  "type": "Feature",
  "properties": {
    "gn:admin1_code":"37",
    "gn:admin2_code":"406.0",
    "gn:asciiname":"Saket",
    "gn:country_code":"IN",
    "gn:dem":256,
    "gn:feature_class":"P",
    "gn:feature_code":"PPL",
    "gn:name":"Saket",
    "gn:population":0,
    "gn:timezone":"Asia/Kolkata",
    "iso:country":"IN",
    "name:spa_x_preferred":[
        "Saketa"
    ],
    "name:tam_x_preferred":[
        "\u0b9a\u0b95\u0bc7\u0ba4\u0bae\u0bcd"
    ],
    "wof:name":"Saket",
    "wof:placetype":"locality"
},
  "geometry": {"coordinates":[81.97291,22.00075],"type":"Point"}
}