{
  "type": "Feature",
  "properties": {
    "iso:country":"IN",
    "ks:ks_name":"Shyamlipura",
    "ks:ks_pop":2,
    "ks:ks_type":"HABITATION",
    "name:eng_x_preferred":[
        "Shyamlipura"
    ],
    "wof:name":"Shyamlipura",
    "wof:placetype":"locality",
    "wof:population":2
},
  "geometry": {"coordinates":[75.86216,21.804375],"type":"Point"}
}