{
  "type": "Feature",
  "properties": {
    "iso:country":"IN",
    "ks:ks_name":"Gwatoli",
    "ks:ks_pop":81,
    "ks:ks_type":"HABITATION",
    "name:eng_x_preferred":[
        "Gwatoli"
    ],
    "wof:name":"Gwatoli",
    "wof:placetype":"locality",
    "wof:population":81
},
  "geometry": {"coordinates":[79.882485,29.888437],"type":"Point"}
}