{
  "type": "Feature",
  "properties": {
    "gn:admin1_code":"36",
    "gn:admin2_code":"158.0",
    "gn:asciiname":"Karhiya Bazar",
    "gn:country_code":"IN",
    "gn:dem":109,
    "gn:feature_class":"P",
    "gn:feature_code":"PPL",
    "gn:name":"Karhiya B\u0101z\u0101r",
    "gn:population":0,
    "gn:timezone":"Asia/Kolkata",
    "iso:country":"IN",
    "wof:name":"Karhiya Bazar",
    "wof:placetype":"locality"
},
  "geometry": {"coordinates":[81.54257,25.99268],"type":"Point"}
}