{
  "type": "Feature",
  "properties": {
    "iso:country":"IN",
    "ks:ks_alt_nam":"NAIBASTI",
    "ks:ks_name":"Naibasti",
    "ks:ks_pop":106,
    "ks:ks_type":"HABITATION",
    "name:eng_x_preferred":[
        "Naibasti"
    ],
    "wof:name":"Naibasti",
    "wof:placetype":"locality",
    "wof:population":106
},
  "geometry": {"coordinates":[82.71931499999999,25.426989],"type":"Point"}
}