{
  "type": "Feature",
  "properties": {
    "iso:country":"IN",
    "ks:ks_name":"Thanikodu",
    "ks:ks_pop":42,
    "ks:ks_type":"HABITATION",
    "name:eng_x_preferred":[
        "Thanikodu"
    ],
    "wof:name":"Thanikodu",
    "wof:placetype":"locality",
    "wof:population":42
},
  "geometry": {"coordinates":[75.256862,13.398508],"type":"Point"}
}