{
  "type": "Feature",
  "properties": {
    "iso:country":"IN",
    "ks:ks_name":"Harpur",
    "ks:ks_pop":794,
    "ks:ks_type":"VILLAGE",
    "name:eng_x_preferred":[
        "Harpur"
    ],
    "wof:name":"Harpur",
    "wof:placetype":"locality",
    "wof:population":794
},
  "geometry": {"coordinates":[85.205466,26.048179],"type":"Point"}
}