{
  "type": "Feature",
  "properties": {
    "iso:country":"IN",
    "ks:ks_name":"Darkhad",
    "ks:ks_pop":1749,
    "ks:ks_type":"VILLAGE",
    "name:eng_x_preferred":[
        "Darkhad"
    ],
    "wof:name":"Darkhad",
    "wof:placetype":"locality",
    "wof:population":1749
},
  "geometry": {"coordinates":[74.26918000000001,22.251129],"type":"Point"}
}