{
  "type": "Feature",
  "properties": {
    "iso:country":"IN",
    "ks:ks_name":"Ramgobindapur",
    "ks:ks_pop":1812,
    "ks:ks_type":"VILLAGE",
    "ks:ks_uagg_main":0,
    "name:eng_x_preferred":[
        "Ramgobindapur"
    ],
    "wof:name":"Ramgobindapur",
    "wof:placetype":"neighbourhood",
    "wof:population":1812
},
  "geometry": {"coordinates":[88.19129,22.213955],"type":"Point"}
}