{
  "type": "Feature",
  "properties": {
    "gn:admin1_code":"36",
    "gn:admin2_code":"192.0",
    "gn:asciiname":"Dandi",
    "gn:country_code":"IN",
    "gn:dem":75,
    "gn:feature_class":"P",
    "gn:feature_code":"PPL",
    "gn:name":"D\u0101ndi",
    "gn:population":0,
    "gn:timezone":"Asia/Kolkata",
    "iso:country":"IN",
    "name:ceb_x_preferred":[
        "Dandi"
    ],
    "name:deu_x_preferred":[
        "Dandi"
    ],
    "name:ita_x_preferred":[
        "Dandi"
    ],
    "name:por_x_preferred":[
        "Dandi"
    ],
    "name:swe_x_preferred":[
        "Dandi"
    ],
    "name:tam_x_preferred":[
        "\u0ba4\u0ba3\u0bcd\u0b9f\u0bbf"
    ],
    "wof:name":"Dandi",
    "wof:placetype":"locality"
},
  "geometry": {"coordinates":[83.58013000000003,25.99601],"type":"Point"}
}