{
  "type": "Feature",
  "properties": {
    "iso:country":"IN",
    "ks:ks_name":"Kusumjhari",
    "ks:ks_pop":263,
    "ks:ks_type":"HABITATION",
    "name:eng_x_preferred":[
        "Kusumjhari"
    ],
    "wof:name":"Kusumjhari",
    "wof:placetype":"locality",
    "wof:population":263
},
  "geometry": {"coordinates":[86.0102,21.080018],"type":"Point"}
}