{
  "type": "Feature",
  "properties": {
    "iso:country":"IN",
    "ks:ks_name":"Barigaon",
    "ks:ks_pop":1124,
    "ks:ks_type":"VILLAGE",
    "name:eng_x_preferred":[
        "Barigaon"
    ],
    "wof:name":"Barigaon",
    "wof:placetype":"locality",
    "wof:population":1124
},
  "geometry": {"coordinates":[91.931681,26.485426],"type":"Point"}
}