{
  "type": "Feature",
  "properties": {
    "iso:country":"IN",
    "ks:ks_name":"1 KPD-A",
    "ks:ks_pop":238,
    "ks:ks_type":"VILLAGE",
    "name:eng_x_preferred":[
        "1 KPD-A"
    ],
    "wof:name":"1 KPD-A",
    "wof:placetype":"locality",
    "wof:population":238
},
  "geometry": {"coordinates":[72.892759,28.82648],"type":"Point"}
}