{
  "type": "Feature",
  "properties": {
    "gn:admin1_code":"13.0",
    "gn:admin2_code":"598.0",
    "gn:asciiname":"Komana",
    "gn:country_code":"IN",
    "gn:dem":7,
    "gn:feature_class":"P",
    "gn:feature_code":"PPL",
    "gn:name":"Komana",
    "gn:population":0,
    "gn:timezone":"Asia/Kolkata",
    "iso:country":"IN",
    "name:ita_x_preferred":[
        "Komana"
    ],
    "name:mlg_x_preferred":[
        "Komana"
    ],
    "name:nld_x_preferred":[
        "Komana"
    ],
    "name:pol_x_preferred":[
        "Komana"
    ],
    "name:swa_x_preferred":[
        "Komana"
    ],
    "wof:name":"Komana",
    "wof:placetype":"locality"
},
  "geometry": {"coordinates":[76.36433000000002,9.38744],"type":"Point"}
}