{
  "type": "Feature",
  "properties": {
    "iso:country":"IN",
    "ks:ks_name":"Nirabavi Jada",
    "ks:ks_pop":84,
    "ks:ks_type":"HABITATION",
    "name:eng_x_preferred":[
        "Nirabavi Jada"
    ],
    "wof:name":"Nirabavi Jada",
    "wof:placetype":"locality",
    "wof:population":84
},
  "geometry": {"coordinates":[75.405427,13.476462],"type":"Point"}
}