{
  "type": "Feature",
  "properties": {
    "gn:admin1_code":"21.0",
    "gn:admin2_code":"372.0",
    "gn:asciiname":"Katupali",
    "gn:country_code":"IN",
    "gn:dem":256,
    "gn:feature_class":"P",
    "gn:feature_code":"PPL",
    "gn:name":"Katupali",
    "gn:population":0,
    "gn:timezone":"Asia/Kolkata",
    "iso:country":"IN",
    "wof:name":"Katupali",
    "wof:placetype":"locality"
},
  "geometry": {"coordinates":[84.47764000000002,21.83325],"type":"Point"}
}