{
  "type": "Feature",
  "properties": {
    "iso:country":"IN",
    "ks:ks_name":"Siwani Khurd",
    "ks:ks_pop":1008,
    "ks:ks_type":"VILLAGE",
    "name:eng_x_preferred":[
        "Siwani Khurd"
    ],
    "wof:name":"Siwani Khurd",
    "wof:placetype":"locality",
    "wof:population":1008
},
  "geometry": {"coordinates":[78.411866,24.72018],"type":"Point"}
}