{
  "type": "Feature",
  "properties": {
    "gn:admin1_code":"16.0",
    "gn:admin2_code":"502",
    "gn:asciiname":"Chakoli",
    "gn:country_code":"IN",
    "gn:dem":553,
    "gn:feature_class":"P",
    "gn:feature_code":"PPL",
    "gn:name":"Ch\u0101koli",
    "gn:population":0,
    "gn:timezone":"Asia/Kolkata",
    "iso:country":"IN",
    "name:und_x_variant":[
        "Ch\u0101koli",
        "Ghakoli"
    ],
    "wof:name":"Chakoli",
    "wof:placetype":"locality"
},
  "geometry": {"coordinates":[76.68136,19.95284],"type":"Point"}
}