{
  "type": "Feature",
  "properties": {
    "iso:country":"IN",
    "ks:ks_name":"Vettaikaranpalayam",
    "ks:ks_pop":100,
    "ks:ks_type":"HABITATION",
    "name:eng_x_preferred":[
        "Vettaikaranpalayam"
    ],
    "wof:name":"Vettaikaranpalayam",
    "wof:placetype":"locality",
    "wof:population":100
},
  "geometry": {"coordinates":[79.95544099999999,13.203932],"type":"Point"}
}