{
  "type": "Feature",
  "properties": {
    "iso:country":"IN",
    "ks:ks_name":"Choti Yadav Basti",
    "ks:ks_pop":569,
    "ks:ks_type":"HABITATION",
    "name:eng_x_preferred":[
        "Choti Yadav Basti"
    ],
    "wof:name":"Choti Yadav Basti",
    "wof:placetype":"locality",
    "wof:population":569
},
  "geometry": {"coordinates":[82.715254,25.337824],"type":"Point"}
}