{
  "type": "Feature",
  "properties": {
    "gn:admin1_code":"35",
    "gn:admin2_code":"457.0",
    "gn:asciiname":"Paraswaraghattola",
    "gn:country_code":"IN",
    "gn:dem":332,
    "gn:feature_class":"P",
    "gn:feature_code":"PPL",
    "gn:name":"Parasw\u0101r\u0101gh\u0101ttola",
    "gn:population":0,
    "gn:timezone":"Asia/Kolkata",
    "iso:country":"IN",
    "wof:name":"Paraswaraghattola",
    "wof:placetype":"locality"
},
  "geometry": {"coordinates":[79.82311999999997,21.66258],"type":"Point"}
}