{
  "type": "Feature",
  "properties": {
    "iso:country":"IN",
    "ks:ks_name":"Alsunde",
    "ks:ks_pop":2920,
    "ks:ks_type":"VILLAGE",
    "name:eng_x_preferred":[
        "Alsunde"
    ],
    "wof:name":"Alsunde",
    "wof:placetype":"locality",
    "wof:population":2920
},
  "geometry": {"coordinates":[75.03670099999999,18.473886],"type":"Point"}
}