{
  "type": "Feature",
  "properties": {
    "iso:country":"IN",
    "ks:ks_name":"Tola Sukhasan",
    "ks:ks_pop":474,
    "ks:ks_type":"VILLAGE",
    "ks:ks_uagg_main":0,
    "name:eng_x_preferred":[
        "Tola Sukhasan"
    ],
    "wof:name":"Tola Sukhasan",
    "wof:placetype":"neighbourhood",
    "wof:population":474
},
  "geometry": {"coordinates":[86.469854,24.943081],"type":"Point"}
}