{
  "type": "Feature",
  "properties": {
    "iso:country":"IN",
    "ks:ks_name":"Palliveerankadu",
    "ks:ks_pop":690,
    "ks:ks_type":"HABITATION",
    "ks:ks_uagg_main":1,
    "name:eng_x_preferred":[
        "Palliveerankadu"
    ],
    "wof:name":"Palliveerankadu",
    "wof:placetype":"neighbourhood",
    "wof:population":690
},
  "geometry": {"coordinates":[78.078439,11.77448],"type":"Point"}
}