{
  "type": "Feature",
  "properties": {
    "gn:admin1_code":"11.0",
    "gn:admin2_code":"32.0",
    "gn:asciiname":"Jagaji",
    "gn:country_code":"IN",
    "gn:dem":1284,
    "gn:feature_class":"P",
    "gn:feature_code":"PPL",
    "gn:name":"Jag\u0101ji",
    "gn:population":0,
    "gn:timezone":"Asia/Kolkata",
    "iso:country":"IN",
    "wof:name":"Jagaji",
    "wof:placetype":"locality"
},
  "geometry": {"coordinates":[77.13383,30.80895],"type":"Point"}
}