{
  "type": "Feature",
  "properties": {
    "iso:country":"IN",
    "ks:ks_name":"Dhapatepada",
    "ks:ks_pop":70,
    "ks:ks_type":"HABITATION",
    "name:eng_x_preferred":[
        "Dhapatepada"
    ],
    "wof:name":"Dhapatepada",
    "wof:placetype":"locality",
    "wof:population":70
},
  "geometry": {"coordinates":[73.401494,19.648758],"type":"Point"}
}