{
  "type": "Feature",
  "properties": {
    "iso:country":"IN",
    "ks:ks_name":"Agrai",
    "ks:ks_pop":677,
    "ks:ks_type":"VILLAGE",
    "name:eng_x_preferred":[
        "Agrai"
    ],
    "wof:name":"Agrai",
    "wof:placetype":"locality",
    "wof:population":677
},
  "geometry": {"coordinates":[77.993556,24.955499],"type":"Point"}
}