{
  "type": "Feature",
  "properties": {
    "gn:admin1_code":"24.0",
    "gn:admin2_code":"99.0",
    "gn:asciiname":"Goindsar",
    "gn:country_code":"IN",
    "gn:dem":172,
    "gn:feature_class":"P",
    "gn:feature_code":"PPL",
    "gn:name":"Goindsar",
    "gn:population":0,
    "gn:timezone":"Asia/Kolkata",
    "iso:country":"IN",
    "wof:name":"Goindsar",
    "wof:placetype":"locality"
},
  "geometry": {"coordinates":[73.5539,29.07718],"type":"Point"}
}