{
  "type": "Feature",
  "properties": {
    "iso:country":"IN",
    "ks:ks_name":"Veeravaram",
    "ks:ks_pop":382,
    "ks:ks_type":"VILLAGE",
    "name:eng_x_preferred":[
        "Veeravaram"
    ],
    "wof:name":"Veeravaram",
    "wof:placetype":"locality",
    "wof:population":382
},
  "geometry": {"coordinates":[82.093129,17.627166],"type":"Point"}
}