{
  "type": "Feature",
  "properties": {
    "gn:admin1_code":"11",
    "gn:admin2_code":"31.0",
    "gn:asciiname":"Sori",
    "gn:country_code":"IN",
    "gn:dem":347,
    "gn:feature_class":"P",
    "gn:feature_code":"PPL",
    "gn:name":"Sori",
    "gn:population":0,
    "gn:timezone":"Asia/Kolkata",
    "iso:country":"IN",
    "name:ceb_x_preferred":[
        "Sori"
    ],
    "name:dan_x_preferred":[
        "Sori"
    ],
    "name:deu_x_preferred":[
        "Sori"
    ],
    "name:fra_x_preferred":[
        "Sori"
    ],
    "name:hye_x_preferred":[
        "\u054d\u0578\u0580\u056b"
    ],
    "name:ita_x_preferred":[
        "Sori"
    ],
    "name:kaz_x_preferred":[
        "\u0421\u043e\u0440\u0438"
    ],
    "name:kor_x_preferred":[
        "\uc18c\ub9ac"
    ],
    "name:rus_x_preferred":[
        "\u0421\u043e\u0440\u0438"
    ],
    "name:swe_x_preferred":[
        "Sori"
    ],
    "name:ukr_x_preferred":[
        "\u0421\u043e\u0440\u0456"
    ],
    "name:wln_x_preferred":[
        "Sori"
    ],
    "wof:name":"Sori",
    "wof:placetype":"locality"
},
  "geometry": {"coordinates":[76.7093,31.06063],"type":"Point"}
}