{
  "type": "Feature",
  "properties": {
    "iso:country":"IN",
    "ks:ks_name":"Hosatota",
    "ks:ks_pop":176,
    "ks:ks_type":"HABITATION",
    "name:eng_x_preferred":[
        "Hosatota"
    ],
    "wof:name":"Hosatota",
    "wof:placetype":"locality",
    "wof:population":176
},
  "geometry": {"coordinates":[74.582477,14.249586],"type":"Point"}
}