{
  "type": "Feature",
  "properties": {
    "iso:country":"IN",
    "ks:ks_name":"Sc Housing Colony",
    "ks:ks_pop":211,
    "ks:ks_type":"HABITATION",
    "name:eng_x_preferred":[
        "Sc Housing Colony"
    ],
    "wof:name":"Sc Housing Colony",
    "wof:placetype":"locality",
    "wof:population":211
},
  "geometry": {"coordinates":[79.547611,19.062531],"type":"Point"}
}