{
  "type": "Feature",
  "properties": {
    "iso:country":"IN",
    "ks:ks_name":"Byas Para Part 2",
    "ks:ks_pop":268,
    "ks:ks_type":"HABITATION",
    "ks:ks_uagg_main":0,
    "name:eng_x_preferred":[
        "Byas Para Part 2"
    ],
    "wof:name":"Byas Para Part 2",
    "wof:placetype":"neighbourhood",
    "wof:population":268
},
  "geometry": {"coordinates":[91.879698,26.415801],"type":"Point"}
}