{
  "type": "Feature",
  "properties": {
    "gn:admin1_code":"2",
    "gn:admin2_code":"544.0",
    "gn:asciiname":"Gujjumanpakalu",
    "gn:country_code":"IN",
    "gn:dem":143,
    "gn:feature_class":"P",
    "gn:feature_code":"PPL",
    "gn:name":"Gujjumanp\u0101kalu",
    "gn:population":0,
    "gn:timezone":"Asia/Kolkata",
    "iso:country":"IN",
    "wof:name":"Gujjumanpakalu",
    "wof:placetype":"locality"
},
  "geometry": {"coordinates":[82.40600999999999,17.66427999999999],"type":"Point"}
}