{
  "type": "Feature",
  "properties": {
    "gn:admin1_code":"2",
    "gn:admin2_code":"544.0",
    "gn:asciiname":"Gujjumanpakalu",
    "gn:country_code":"IN",
    "gn:dem":143,
    "gn:feature_class":"P",
    "gn:feature_code":"PPL",
    "gn:name":"Gujjumanp\u0101kalu",
    "gn:population":0,
    "gn:timezone":"Asia/Kolkata",
    "iso:country":"IN",
    "ks:ks_name":"Gujjumanupakalu",
    "ks:ks_pop":148,
    "ks:ks_type":"HABITATION",
    "name:eng_x_preferred":[
        "Gujjumanupakalu"
    ],
    "name:eng_x_variant":[
        "Gujjumanpakalu"
    ],
    "wof:name":"Gujjumanupakalu",
    "wof:placetype":"locality",
    "wof:population":148
},
  "geometry": {"coordinates":[82.406069,17.664903],"type":"Point"}
}