{
  "type": "Feature",
  "properties": {
    "gn:admin1_code":"35.0",
    "gn:admin2_code":"420.0",
    "gn:asciiname":"Basahra",
    "gn:country_code":"IN",
    "gn:dem":163,
    "gn:feature_class":"P",
    "gn:feature_code":"PPL",
    "gn:name":"Bas\u0101hra",
    "gn:population":0,
    "gn:timezone":"Asia/Kolkata",
    "iso:country":"IN",
    "wof:name":"Basahra",
    "wof:placetype":"locality"
},
  "geometry": {"coordinates":[78.42294,26.4387],"type":"Point"}
}