{
  "type": "Feature",
  "properties": {
    "iso:country":"IN",
    "ks:ks_name":"Dupeli",
    "ks:ks_pop":211,
    "ks:ks_type":"VILLAGE",
    "name:eng_x_preferred":[
        "Dupeli"
    ],
    "wof:name":"Dupeli",
    "wof:placetype":"locality",
    "wof:population":211
},
  "geometry": {"coordinates":[80.756118,18.923698],"type":"Point"}
}