{
  "type": "Feature",
  "properties": {
    "gn:admin1_code":"16.0",
    "gn:admin2_code":"503",
    "gn:asciiname":"Kaundanpur",
    "gn:country_code":"IN",
    "gn:dem":296,
    "gn:feature_class":"P",
    "gn:feature_code":"PPL",
    "gn:name":"Kaundanpur",
    "gn:population":0,
    "gn:timezone":"Asia/Kolkata",
    "iso:country":"IN",
    "wof:name":"Kaundanpur",
    "wof:placetype":"neighbourhood"
},
  "geometry": {"coordinates":[78.14527,20.98076],"type":"Point"}
}