{
  "type": "Feature",
  "properties": {
    "iso:country":"IN",
    "ks:ks_name":"Sarpanchguda",
    "ks:ks_pop":260,
    "ks:ks_type":"HABITATION",
    "name:eng_x_preferred":[
        "Sarpanchguda"
    ],
    "wof:name":"Sarpanchguda",
    "wof:placetype":"locality",
    "wof:population":260
},
  "geometry": {"coordinates":[78.80283900000001,19.690811],"type":"Point"}
}