{
  "type": "Feature",
  "properties": {
    "gn:admin1_code":"11.0",
    "gn:admin2_code":"32.0",
    "gn:asciiname":"Didu",
    "gn:country_code":"IN",
    "gn:dem":1243,
    "gn:feature_class":"P",
    "gn:feature_code":"PPL",
    "gn:name":"Didu",
    "gn:population":0,
    "gn:timezone":"Asia/Kolkata",
    "iso:country":"IN",
    "name:ceb_x_preferred":[
        "Didu"
    ],
    "name:swe_x_preferred":[
        "Didu"
    ],
    "wof:name":"Didu",
    "wof:placetype":"locality"
},
  "geometry": {"coordinates":[77.16928,30.80909],"type":"Point"}
}