{
  "type": "Feature",
  "properties": {
    "iso:country":"IN",
    "ks:ks_alt_nam":"PURE AWATARI",
    "ks:ks_name":"Pure Awatari",
    "ks:ks_pop":143,
    "ks:ks_type":"HABITATION",
    "ks:ks_uagg_main":0,
    "name:eng_x_preferred":[
        "Pure Awatari"
    ],
    "wof:name":"Pure Awatari",
    "wof:placetype":"neighbourhood",
    "wof:population":143
},
  "geometry": {"coordinates":[82.229382,26.350244],"type":"Point"}
}