{
  "type": "Feature",
  "properties": {
    "iso:country":"IN",
    "qs:name":"Nagoriwad",
    "qs:name_adm0":"India",
    "qs:name_adm1":"Gujarat",
    "qs:photos":34,
    "qs:photos_1k":7,
    "qs:photos_9k":1,
    "qs:photos_9r":2,
    "qs:photos_all":34,
    "qs:photos_sr":2,
    "qs:placetype":"Suburb",
    "qs:pop_sr":"0",
    "wof:name":"Nagoriwad",
    "wof:placetype":"neighbourhood"
},
  "geometry": {"coordinates":[72.587834,23.038098],"type":"Point"}
}