{
  "type": "Feature",
  "properties": {
    "iso:country":"IN",
    "ks:ks_name":"Bardadda",
    "ks:ks_pop":162,
    "ks:ks_type":"HABITATION",
    "name:eng_x_preferred":[
        "Bardadda"
    ],
    "wof:name":"Bardadda",
    "wof:placetype":"locality",
    "wof:population":162
},
  "geometry": {"coordinates":[75.178602,12.882467],"type":"Point"}
}