{
  "type": "Feature",
  "properties": {
    "iso:country":"IN",
    "ks:ks_name":"Telem Ukha Chapori",
    "ks:ks_pop":122,
    "ks:ks_type":"HABITATION",
    "name:eng_x_preferred":[
        "Telem Ukha Chapori"
    ],
    "wof:name":"Telem Ukha Chapori",
    "wof:placetype":"locality",
    "wof:population":122
},
  "geometry": {"coordinates":[95.012119,27.756443],"type":"Point"}
}