{
  "type": "Feature",
  "properties": {
    "iso:country":"IN",
    "ks:ks_name":"Kwarana",
    "ks:ks_pop":251,
    "ks:ks_type":"VILLAGE",
    "name:eng_x_preferred":[
        "Kwarana"
    ],
    "wof:name":"Kwarana",
    "wof:placetype":"locality",
    "wof:population":251
},
  "geometry": {"coordinates":[77.85549399999999,30.680448],"type":"Point"}
}