{
  "type": "Feature",
  "properties": {
    "iso:country":"IN",
    "ks:ks_name":"Nec Para",
    "ks:ks_pop":127,
    "ks:ks_type":"HABITATION",
    "name:eng_x_preferred":[
        "Nec Para"
    ],
    "wof:name":"Nec Para",
    "wof:placetype":"locality",
    "wof:population":127
},
  "geometry": {"coordinates":[91.454252,23.746279],"type":"Point"}
}