{
  "type": "Feature",
  "properties": {
    "gn:admin1_code":"21",
    "gn:admin2_code":"371.0",
    "gn:asciiname":"Dudolsingha",
    "gn:country_code":"IN",
    "gn:dem":197,
    "gn:feature_class":"P",
    "gn:feature_code":"PPL",
    "gn:name":"Dudolsingha",
    "gn:population":0,
    "gn:timezone":"Asia/Kolkata",
    "iso:country":"IN",
    "ks:ks_name":"Dudulsingha",
    "ks:ks_pop":864,
    "ks:ks_type":"VILLAGE",
    "name:eng_x_preferred":[
        "Dudulsingha"
    ],
    "name:eng_x_variant":[
        "Dudolsingha"
    ],
    "wof:name":"Dudulsingha",
    "wof:placetype":"locality",
    "wof:population":864
},
  "geometry": {"coordinates":[83.92616700000001,21.763359],"type":"Point"}
}