{
  "type": "Feature",
  "properties": {
    "iso:country":"IN",
    "ks:ks_alt_nam":"tenginakere",
    "ks:ks_name":"Tenginakere",
    "ks:ks_pop":82,
    "ks:ks_type":"HABITATION",
    "name:eng_x_preferred":[
        "Tenginakere"
    ],
    "wof:name":"Tenginakere",
    "wof:placetype":"locality",
    "wof:population":82
},
  "geometry": {"coordinates":[75.396367,13.742801],"type":"Point"}
}