{
  "type": "Feature",
  "properties": {
    "gn:admin1_code":"36",
    "gn:admin2_code":"174.0",
    "gn:asciiname":"Faridpur Parsakhi",
    "gn:country_code":"IN",
    "gn:dem":103,
    "gn:feature_class":"P",
    "gn:feature_code":"PPL",
    "gn:name":"Far\u012bdpur Parsakhi",
    "gn:population":0,
    "gn:timezone":"Asia/Kolkata",
    "iso:country":"IN",
    "wof:name":"Faridpur Parsakhi",
    "wof:placetype":"locality"
},
  "geometry": {"coordinates":[81.43155,25.64291],"type":"Point"}
}