{
  "type": "Feature",
  "properties": {
    "gn:admin1_code":"36.0",
    "gn:admin2_code":"134.0",
    "gn:asciiname":"Gokalpur",
    "gn:country_code":"IN",
    "gn:dem":228,
    "gn:feature_class":"P",
    "gn:feature_code":"PPL",
    "gn:name":"Gokalpur",
    "gn:population":0,
    "gn:timezone":"Asia/Kolkata",
    "iso:country":"IN",
    "wof:name":"Gokalpur",
    "wof:placetype":"neighbourhood"
},
  "geometry": {"coordinates":[78.10274,29.364],"type":"Point"}
}