{
  "type": "Feature",
  "properties": {
    "iso:country":"IN",
    "ks:ks_alt_nam":"Jurr\u0101npur",
    "ks:ks_name":"Jurranpur",
    "ks:ks_pop":961,
    "ks:ks_type":"VILLAGE",
    "name:eng_x_preferred":[
        "Jurranpur"
    ],
    "name:eng_x_variant":[
        "Jurr\u0101npur"
    ],
    "wof:name":"Jurranpur",
    "wof:placetype":"neighbourhood",
    "wof:population":961
},
  "geometry": {"coordinates":[77.713849,28.921742],"type":"Point"}
}