{
  "type": "Feature",
  "properties": {
    "iso:country":"IN",
    "ks:ks_name":"Rasa",
    "ks:ks_pop":1321,
    "ks:ks_type":"VILLAGE",
    "name:eng_x_preferred":[
        "Rasa"
    ],
    "wof:name":"Rasa",
    "wof:placetype":"locality",
    "wof:population":1321
},
  "geometry": {"coordinates":[88.277742,22.260612],"type":"Point"}
}