{
  "type": "Feature",
  "properties": {
    "iso:country":"IN",
    "ks:ks_name":"Olodithazha",
    "ks:ks_pop":1728,
    "ks:ks_type":"HABITATION",
    "name:eng_x_preferred":[
        "Olodithazha"
    ],
    "wof:name":"Olodithazha",
    "wof:placetype":"locality",
    "wof:population":1728
},
  "geometry": {"coordinates":[75.72056000000001,11.626345],"type":"Point"}
}