{
  "type": "Feature",
  "properties": {
    "iso:country":"IN",
    "ks:ks_name":"Vadakattalai",
    "ks:ks_pop":89,
    "ks:ks_type":"HABITATION",
    "name:eng_x_preferred":[
        "Vadakattalai"
    ],
    "wof:name":"Vadakattalai",
    "wof:placetype":"locality",
    "wof:population":89
},
  "geometry": {"coordinates":[79.80000699999999,11.1202],"type":"Point"}
}