{
  "type": "Feature",
  "properties": {
    "gn:admin1_code":"11.0",
    "gn:admin2_code":"33.0",
    "gn:asciiname":"Ghasgari",
    "gn:country_code":"IN",
    "gn:dem":2805,
    "gn:feature_class":"P",
    "gn:feature_code":"PPL",
    "gn:name":"Ghasgari",
    "gn:population":0,
    "gn:timezone":"Asia/Kolkata",
    "iso:country":"IN",
    "wof:name":"Ghasgari",
    "wof:placetype":"locality"
},
  "geometry": {"coordinates":[77.66848,31.30383],"type":"Point"}
}