{
  "type": "Feature",
  "properties": {
    "gn:admin1_code":"36.0",
    "gn:admin2_code":"184.0",
    "gn:asciiname":"Gahirwala",
    "gn:country_code":"IN",
    "gn:dem":99,
    "gn:feature_class":"P",
    "gn:feature_code":"PPL",
    "gn:name":"Gahirw\u0101la",
    "gn:population":0,
    "gn:timezone":"Asia/Kolkata",
    "iso:country":"IN",
    "ks:ks_alt_nam":"Gahirw\u0101la",
    "ks:ks_name":"Gahirwala",
    "ks:ks_type":"VILLAGE",
    "ks:ks_uagg_main":0,
    "name:eng_x_preferred":[
        "Gahirwala"
    ],
    "name:eng_x_variant":[
        "Gahirw\u0101la"
    ],
    "wof:name":"Gahirwala",
    "wof:placetype":"neighbourhood"
},
  "geometry": {"coordinates":[82.525488,27.164936],"type":"Point"}
}