{
  "type": "Feature",
  "properties": {
    "gn:admin1_code":"35",
    "gn:admin2_code":"452.0",
    "gn:asciiname":"Paharikhera",
    "gn:country_code":"IN",
    "gn:dem":444,
    "gn:feature_class":"P",
    "gn:feature_code":"PPL",
    "gn:name":"Pah\u0101r\u012bkhera",
    "gn:population":0,
    "gn:timezone":"Asia/Kolkata",
    "iso:country":"IN",
    "wof:name":"Paharikhera",
    "wof:placetype":"locality"
},
  "geometry": {"coordinates":[79.61808000000001,22.9026],"type":"Point"}
}