{
  "type": "Feature",
  "properties": {
    "gn:admin1_code":"23.0",
    "gn:asciiname":"Mianwala Uttar",
    "gn:country_code":"IN",
    "gn:dem":206,
    "gn:feature_class":"P",
    "gn:feature_code":"PPL",
    "gn:name":"Mi\u0101nw\u0101la Utt\u0101r",
    "gn:population":0,
    "gn:timezone":"Asia/Karachi",
    "iso:country":"IN",
    "wof:name":"Mianwala Uttar",
    "wof:placetype":"locality"
},
  "geometry": {"coordinates":[74.55216999999998,31.12062],"type":"Point"}
}