{
  "type": "Feature",
  "properties": {
    "iso:country":"IN",
    "ks:ks_name":"Sakharoli",
    "ks:ks_pop":0,
    "ks:ks_type":"VILLAGE",
    "name:eng_x_preferred":[
        "Sakharoli"
    ],
    "wof:name":"Sakharoli",
    "wof:placetype":"locality",
    "wof:population":0
},
  "geometry": {"coordinates":[73.14965100000001,19.138946],"type":"Point"}
}