{
  "type": "Feature",
  "properties": {
    "iso:country":"IN",
    "ks:ks_name":"Koya Dhariya",
    "ks:ks_pop":969,
    "ks:ks_type":"VILLAGE",
    "name:eng_x_preferred":[
        "Koya Dhariya"
    ],
    "wof:name":"Koya Dhariya",
    "wof:placetype":"locality",
    "wof:population":969
},
  "geometry": {"coordinates":[74.479714,22.82506],"type":"Point"}
}