{
  "type": "Feature",
  "properties": {
    "iso:country":"IN",
    "ks:ks_name":"Bandarkhanda",
    "ks:ks_pop":0,
    "ks:ks_type":"VILLAGE",
    "name:eng_x_preferred":[
        "Bandarkhanda"
    ],
    "wof:name":"Bandarkhanda",
    "wof:placetype":"locality",
    "wof:population":0
},
  "geometry": {"coordinates":[87.228003,22.554171],"type":"Point"}
}