{
  "type": "Feature",
  "properties": {
    "gn:admin1_code":"36",
    "gn:admin2_code":"158.0",
    "gn:asciiname":"Gonda",
    "gn:country_code":"IN",
    "gn:dem":112,
    "gn:feature_class":"P",
    "gn:feature_code":"PPL",
    "gn:name":"Gonda",
    "gn:population":0,
    "gn:timezone":"Asia/Kolkata",
    "iso:country":"IN",
    "name:bih_x_preferred":[
        "\u0917\u094b\u0902\u0921\u093e"
    ],
    "name:bpy_x_preferred":[
        "\u0997\u09cb\u09a8\u09cd\u09a6\u09be"
    ],
    "name:ceb_x_preferred":[
        "Gonda"
    ],
    "name:deu_x_preferred":[
        "Gonda"
    ],
    "name:new_x_preferred":[
        "\u0917\u094b\u0902\u0921\u093e"
    ],
    "name:nld_x_preferred":[
        "Gonda"
    ],
    "name:pnb_x_preferred":[
        "\u06af\u0648\u0646\u0688\u06c1"
    ],
    "name:pol_x_preferred":[
        "Gonda"
    ],
    "name:por_x_preferred":[
        "Gonda"
    ],
    "name:swe_x_preferred":[
        "Gonda"
    ],
    "wof:name":"Gonda",
    "wof:placetype":"locality"
},
  "geometry": {"coordinates":[80.79928000000002,26.07452],"type":"Point"}
}