{
  "type": "Feature",
  "properties": {
    "iso:country":"IN",
    "ks:ks_name":"Hedateri",
    "ks:ks_pop":82,
    "ks:ks_type":"HABITATION",
    "name:eng_x_preferred":[
        "Hedateri"
    ],
    "wof:name":"Hedateri",
    "wof:placetype":"locality",
    "wof:population":82
},
  "geometry": {"coordinates":[74.981718,14.144908],"type":"Point"}
}