{
  "type": "Feature",
  "properties": {
    "gn:admin1_code":"12.0",
    "gn:admin2_code":"012",
    "gn:asciiname":"Jewan Sahib",
    "gn:country_code":"IN",
    "gn:dem":1629,
    "gn:feature_class":"P",
    "gn:feature_code":"PPL",
    "gn:name":"Jewan S\u0101hib",
    "gn:population":0,
    "gn:timezone":"Asia/Kolkata",
    "iso:country":"IN",
    "wof:name":"Jewan Sahib",
    "wof:placetype":"locality"
},
  "geometry": {"coordinates":[74.99637,34.00265],"type":"Point"}
}