{
  "type": "Feature",
  "properties": {
    "iso:country":"IN",
    "ks:ks_alt_nam":"Cheripadi jn",
    "ks:ks_name":"Cheripadi Jn",
    "ks:ks_pop":512,
    "ks:ks_type":"HABITATION",
    "name:eng_x_preferred":[
        "Cheripadi Jn"
    ],
    "wof:name":"Cheripadi Jn",
    "wof:placetype":"locality",
    "wof:population":512
},
  "geometry": {"coordinates":[76.010138,11.106876],"type":"Point"}
}