{
  "type": "Feature",
  "properties": {
    "iso:country":"IN",
    "ks:ks_name":"Kolra",
    "ks:ks_pop":1224,
    "ks:ks_type":"HABITATION",
    "name:eng_x_preferred":[
        "Kolra"
    ],
    "wof:name":"Kolra",
    "wof:placetype":"locality",
    "wof:population":1224
},
  "geometry": {"coordinates":[73.661535,23.941374],"type":"Point"}
}