{
  "type": "Feature",
  "properties": {
    "iso:country":"IN",
    "ks:ks_name":"Dudekulapalem",
    "ks:ks_pop":144,
    "ks:ks_type":"HABITATION",
    "name:eng_x_preferred":[
        "Dudekulapalem"
    ],
    "wof:name":"Dudekulapalem",
    "wof:placetype":"locality",
    "wof:population":144
},
  "geometry": {"coordinates":[80.015787,14.888022],"type":"Point"}
}