{
  "type": "Feature",
  "properties": {
    "gn:admin1_code":"37.0",
    "gn:admin2_code":"416.0",
    "gn:asciiname":"Pariya",
    "gn:country_code":"IN",
    "gn:dem":268,
    "gn:feature_class":"P",
    "gn:feature_code":"PPL",
    "gn:name":"Pariya",
    "gn:population":0,
    "gn:timezone":"Asia/Kolkata",
    "iso:country":"IN",
    "ks:ks_name":"Pariya",
    "ks:ks_pop":354,
    "ks:ks_type":"VILLAGE",
    "name:eng_x_preferred":[
        "Pariya"
    ],
    "wof:name":"Pariya",
    "wof:placetype":"locality",
    "wof:population":354
},
  "geometry": {"coordinates":[81.431663,18.319051],"type":"Point"}
}