{
  "type": "Feature",
  "properties": {
    "gn:admin1_code":"36",
    "gn:admin2_code":"176.0",
    "gn:asciiname":"Purwa Subadar",
    "gn:country_code":"IN",
    "gn:dem":117,
    "gn:feature_class":"P",
    "gn:feature_code":"PPL",
    "gn:name":"Purwa Subadar",
    "gn:population":0,
    "gn:timezone":"Asia/Kolkata",
    "iso:country":"IN",
    "wof:name":"Purwa Subadar",
    "wof:placetype":"neighbourhood"
},
  "geometry": {"coordinates":[81.37393,26.57868],"type":"Point"}
}