{
  "type": "Feature",
  "properties": {
    "iso:country":"IN",
    "ks:ks_name":"Krishnagoundanur",
    "ks:ks_pop":260,
    "ks:ks_type":"HABITATION",
    "ks:ks_uagg_main":0,
    "name:eng_x_preferred":[
        "Krishnagoundanur"
    ],
    "wof:name":"Krishnagoundanur",
    "wof:placetype":"neighbourhood",
    "wof:population":260
},
  "geometry": {"coordinates":[78.162318,11.972781],"type":"Point"}
}