{
  "type": "Feature",
  "properties": {
    "gn:admin1_code":"35.0",
    "gn:admin2_code":"457.0",
    "gn:asciiname":"Chandia",
    "gn:country_code":"IN",
    "gn:dem":528,
    "gn:feature_class":"P",
    "gn:feature_code":"PPL",
    "gn:name":"Chandi\u0101",
    "gn:population":0,
    "gn:timezone":"Asia/Kolkata",
    "iso:country":"IN",
    "ks:ks_name":"Chandiya",
    "ks:ks_pop":550,
    "ks:ks_type":"VILLAGE",
    "name:eng_x_preferred":[
        "Chandiya"
    ],
    "name:eng_x_variant":[
        "Chandia"
    ],
    "wof:name":"Chandiya",
    "wof:placetype":"locality",
    "wof:population":550
},
  "geometry": {"coordinates":[80.436404,22.237002],"type":"Point"}
}