{
  "type": "Feature",
  "properties": {
    "gn:admin1_code":"40.0",
    "gn:admin2_code":"532.0",
    "gn:asciiname":"Kosara",
    "gn:country_code":"IN",
    "gn:dem":224,
    "gn:feature_class":"P",
    "gn:feature_code":"PPL",
    "gn:name":"Kos\u0101ra",
    "gn:population":0,
    "gn:timezone":"Asia/Kolkata",
    "iso:country":"IN",
    "wof:name":"Kosara",
    "wof:placetype":"locality"
},
  "geometry": {"coordinates":[79.23909,19.3431],"type":"Point"}
}