{
  "type": "Feature",
  "properties": {
    "gn:admin1_code":"40.0",
    "gn:admin2_code":"532.0",
    "gn:asciiname":"Kosara",
    "gn:country_code":"IN",
    "gn:dem":224,
    "gn:feature_class":"P",
    "gn:feature_code":"PPL",
    "gn:name":"Kos\u0101ra",
    "gn:population":0,
    "gn:timezone":"Asia/Kolkata",
    "iso:country":"IN",
    "name:bul_x_preferred":[
        "\u0422\u0435\u043e\u0434\u043e\u0440\u0430 \u041a\u043e\u0441\u0430\u0440\u0430"
    ],
    "name:hrv_x_preferred":[
        "Kosara"
    ],
    "name:pol_x_preferred":[
        "Teodora Kosara"
    ],
    "name:por_x_preferred":[
        "Cossara"
    ],
    "name:srp_x_preferred":[
        "\u0422\u0435\u043e\u0434\u043e\u0440\u0430 \u041a\u043e\u0441\u0430\u0440\u0430"
    ],
    "wof:name":"Kosara",
    "wof:placetype":"locality"
},
  "geometry": {"coordinates":[79.23909,19.3431],"type":"Point"}
}