{
  "type": "Feature",
  "properties": {
    "iso:country":"IN",
    "ks:ks_name":"Nagla Bahelyan Purwa",
    "ks:ks_pop":187,
    "ks:ks_type":"HABITATION",
    "name:eng_x_preferred":[
        "Nagla Bahelyan Purwa"
    ],
    "wof:name":"Nagla Bahelyan Purwa",
    "wof:placetype":"locality",
    "wof:population":187
},
  "geometry": {"coordinates":[79.405506,26.643062],"type":"Point"}
}