{
  "type": "Feature",
  "properties": {
    "iso:country":"IN",
    "ks:ks_name":"Basha",
    "ks:ks_pop":1214,
    "ks:ks_type":"VILLAGE",
    "ks:ks_uagg_main":0,
    "name:eng_x_preferred":[
        "Basha"
    ],
    "wof:name":"Basha",
    "wof:placetype":"neighbourhood",
    "wof:population":1214
},
  "geometry": {"coordinates":[80.99454,26.952931],"type":"Point"}
}