{
  "type": "Feature",
  "properties": {
    "iso:country":"IN",
    "ks:ks_alt_nam":"RAYAVARAM",
    "ks:ks_name":"Rayavaram",
    "ks:ks_pop":291,
    "ks:ks_type":"HABITATION",
    "ks:ks_uagg_main":0,
    "name:eng_x_preferred":[
        "Rayavaram"
    ],
    "wof:name":"Rayavaram",
    "wof:placetype":"locality",
    "wof:population":291
},
  "geometry": {"coordinates":[78.592769,14.735502],"type":"Point"}
}