{
  "type": "Feature",
  "properties": {
    "iso:country":"IN",
    "ks:ks_name":"No 7 Kumrakhali",
    "ks:ks_pop":4161,
    "ks:ks_type":"HABITATION",
    "name:eng_x_preferred":[
        "No 7 Kumrakhali"
    ],
    "wof:name":"No 7 Kumrakhali",
    "wof:placetype":"locality",
    "wof:population":4161
},
  "geometry": {"coordinates":[88.810339,22.348738],"type":"Point"}
}