{
  "type": "Feature",
  "properties": {
    "iso:country":"IN",
    "ks:ks_name":"Arekatta",
    "ks:ks_pop":84,
    "ks:ks_type":"HABITATION",
    "name:eng_x_preferred":[
        "Arekatta"
    ],
    "wof:name":"Arekatta",
    "wof:placetype":"locality",
    "wof:population":84
},
  "geometry": {"coordinates":[74.611165,14.671718],"type":"Point"}
}