{
  "type": "Feature",
  "properties": {
    "gn:admin1_code":"33.0",
    "gn:admin2_code":"585.0",
    "gn:asciiname":"Dongarvada",
    "gn:country_code":"IN",
    "gn:dem":133,
    "gn:feature_class":"P",
    "gn:feature_code":"PPL",
    "gn:name":"Dongarv\u0101da",
    "gn:population":0,
    "gn:timezone":"Asia/Kolkata",
    "iso:country":"IN",
    "wof:name":"Dongarvada",
    "wof:placetype":"locality"
},
  "geometry": {"coordinates":[74.17296999999998,15.59281],"type":"Point"}
}