{
  "type": "Feature",
  "properties": {
    "iso:country":"IN",
    "ks:ks_name":"Melapiranthiyankarai",
    "ks:ks_pop":264,
    "ks:ks_type":"HABITATION",
    "name:eng_x_preferred":[
        "Melapiranthiyankarai"
    ],
    "wof:name":"Melapiranthiyankarai",
    "wof:placetype":"locality",
    "wof:population":264
},
  "geometry": {"coordinates":[79.69195999999999,10.473559],"type":"Point"}
}