{
  "type": "Feature",
  "properties": {
    "iso:country":"IN",
    "ks:ks_name":"Nokh",
    "ks:ks_pop":526,
    "ks:ks_type":"VILLAGE",
    "name:eng_x_preferred":[
        "Nokh"
    ],
    "wof:name":"Nokh",
    "wof:placetype":"locality",
    "wof:population":526
},
  "geometry": {"coordinates":[73.891931,26.094517],"type":"Point"}
}