{
  "type": "Feature",
  "properties": {
    "gn:admin1_code":"24.0",
    "gn:admin2_code":"117",
    "gn:asciiname":"Goyali",
    "gn:country_code":"IN",
    "gn:dem":284,
    "gn:feature_class":"P",
    "gn:feature_code":"PPL",
    "gn:name":"Goyali",
    "gn:population":0,
    "gn:timezone":"Asia/Kolkata",
    "iso:country":"IN",
    "name:und_x_variant":[
        "Goelli"
    ],
    "wof:name":"Goyali",
    "wof:placetype":"neighbourhood"
},
  "geometry": {"coordinates":[72.83042,24.89947],"type":"Point"}
}