{
  "type": "Feature",
  "properties": {
    "gn:admin1_code":"23.0",
    "gn:admin2_code":"40.0",
    "gn:asciiname":"Bathli",
    "gn:country_code":"IN",
    "gn:dem":263,
    "gn:feature_class":"P",
    "gn:feature_code":"PPL",
    "gn:name":"Bathli",
    "gn:population":0,
    "gn:timezone":"Asia/Kolkata",
    "iso:country":"IN",
    "wof:name":"Bathli",
    "wof:placetype":"locality"
},
  "geometry": {"coordinates":[76.47620999999999,30.43683],"type":"Point"}
}