{
  "type": "Feature",
  "properties": {
    "gn:admin1_code":"16.0",
    "gn:admin2_code":"521.0",
    "gn:asciiname":"Bhiuri",
    "gn:country_code":"IN",
    "gn:dem":875,
    "gn:feature_class":"P",
    "gn:feature_code":"PPL",
    "gn:name":"Bhiuri",
    "gn:population":0,
    "gn:timezone":"Asia/Kolkata",
    "iso:country":"IN",
    "wof:name":"Bhiuri",
    "wof:placetype":"locality"
},
  "geometry": {"coordinates":[73.93370999999998,18.39055],"type":"Point"}
}