{
  "type": "Feature",
  "properties": {
    "gn:admin1_code":"1.0",
    "gn:admin2_code":"638",
    "gn:asciiname":"Dakoank",
    "gn:country_code":"IN",
    "gn:dem":28,
    "gn:feature_class":"P",
    "gn:feature_code":"PPL",
    "gn:name":"D\u0101ko\u0101nk",
    "gn:population":0,
    "gn:timezone":"Asia/Kolkata",
    "iso:country":"IN",
    "wof:name":"Dakoank",
    "wof:placetype":"locality"
},
  "geometry": {"coordinates":[93.71666999999999,7.03333],"type":"Point"}
}