{
  "type": "Feature",
  "properties": {
    "iso:country":"IN",
    "ks:ks_name":"Kheragopiwala",
    "ks:ks_pop":332,
    "ks:ks_type":"VILLAGE",
    "name:eng_x_preferred":[
        "Kheragopiwala"
    ],
    "wof:name":"Kheragopiwala",
    "wof:placetype":"locality",
    "wof:population":332
},
  "geometry": {"coordinates":[78.054993,30.410673],"type":"Point"}
}