{
  "type": "Feature",
  "properties": {
    "iso:country":"IN",
    "ks:ks_name":"Bhairopur",
    "ks:ks_pop":8,
    "ks:ks_type":"HABITATION",
    "name:eng_x_preferred":[
        "Bhairopur"
    ],
    "wof:name":"Bhairopur",
    "wof:placetype":"locality",
    "wof:population":8
},
  "geometry": {"coordinates":[82.335178,26.71461],"type":"Point"}
}