{
  "type": "Feature",
  "properties": {
    "gn:admin1_code":"34",
    "gn:asciiname":"Dhanaitpur",
    "gn:country_code":"IN",
    "gn:dem":75,
    "gn:feature_class":"P",
    "gn:feature_code":"PPL",
    "gn:name":"Dhan\u0101itpur",
    "gn:population":0,
    "gn:timezone":"Asia/Kolkata",
    "iso:country":"IN",
    "wof:name":"Dhanaitpur",
    "wof:placetype":"locality"
},
  "geometry": {"coordinates":[83.47655999999998,25.27288],"type":"Point"}
}