{
  "type": "Feature",
  "properties": {
    "iso:country":"IN",
    "ks:ks_alt_nam":"Sukale wasti",
    "ks:ks_name":"Sukale Wasti",
    "ks:ks_pop":100,
    "ks:ks_type":"HABITATION",
    "name:eng_x_preferred":[
        "Sukale Wasti"
    ],
    "wof:name":"Sukale Wasti",
    "wof:placetype":"locality",
    "wof:population":100
},
  "geometry": {"coordinates":[75.837508,18.573697],"type":"Point"}
}