{
  "type": "Feature",
  "properties": {
    "iso:country":"IN",
    "ks:ks_name":"Ramtekari",
    "ks:ks_pop":439,
    "ks:ks_type":"HABITATION",
    "name:eng_x_preferred":[
        "Ramtekari"
    ],
    "wof:name":"Ramtekari",
    "wof:placetype":"locality",
    "wof:population":439
},
  "geometry": {"coordinates":[70.97794399999999,22.622944],"type":"Point"}
}