{
  "type": "Feature",
  "properties": {
    "iso:country":"IN",
    "ks:ks_alt_nam":"piprachouki",
    "ks:ks_name":"Piprachouki",
    "ks:ks_pop":100,
    "ks:ks_type":"HABITATION",
    "name:eng_x_preferred":[
        "Piprachouki"
    ],
    "wof:name":"Piprachouki",
    "wof:placetype":"locality",
    "wof:population":100
},
  "geometry": {"coordinates":[81.93471,27.494003],"type":"Point"}
}