{
  "type": "Feature",
  "properties": {
    "iso:country":"IN",
    "ks:ks_name":"Niz Khowang Betoni",
    "ks:ks_pop":526,
    "ks:ks_type":"VILLAGE",
    "ks:ks_uagg_main":0,
    "name:eng_x_preferred":[
        "Niz Khowang Betoni"
    ],
    "wof:name":"Niz Khowang Betoni",
    "wof:placetype":"locality",
    "wof:population":526
},
  "geometry": {"coordinates":[94.89558599999999,27.282553],"type":"Point"}
}