{
  "type": "Feature",
  "properties": {
    "iso:country":"IN",
    "ks:ks_alt_nam":"cheekkuli",
    "ks:ks_name":"Cheekkuli",
    "ks:ks_pop":1839,
    "ks:ks_type":"HABITATION",
    "name:eng_x_preferred":[
        "Cheekkuli"
    ],
    "wof:name":"Cheekkuli",
    "wof:placetype":"locality",
    "wof:population":1839
},
  "geometry": {"coordinates":[76.65057899999999,10.833931],"type":"Point"}
}