{
  "type": "Feature",
  "properties": {
    "iso:country":"IN",
    "ks:ks_name":"Toota Ambalam Kunnu",
    "ks:ks_pop":349,
    "ks:ks_type":"HABITATION",
    "name:eng_x_preferred":[
        "Toota Ambalam Kunnu"
    ],
    "wof:name":"Toota Ambalam Kunnu",
    "wof:placetype":"locality",
    "wof:population":349
},
  "geometry": {"coordinates":[76.290892,10.927294],"type":"Point"}
}