{
  "type": "Feature",
  "properties": {
    "iso:country":"IN",
    "ks:ks_name":"Daiya",
    "ks:ks_pop":881,
    "ks:ks_type":"VILLAGE",
    "name:eng_x_preferred":[
        "Daiya"
    ],
    "wof:name":"Daiya",
    "wof:placetype":"locality",
    "wof:population":881
},
  "geometry": {"coordinates":[73.119404,28.069698],"type":"Point"}
}