{
  "type": "Feature",
  "properties": {
    "gn:admin1_code":"36",
    "gn:admin2_code":"137.0",
    "gn:asciiname":"Bastaura Rani",
    "gn:country_code":"IN",
    "gn:dem":207,
    "gn:feature_class":"P",
    "gn:feature_code":"PPL",
    "gn:name":"Bastaura R\u0101n\u012b",
    "gn:population":0,
    "gn:timezone":"Asia/Kolkata",
    "iso:country":"IN",
    "ks:ks_name":"Bastora Rani",
    "ks:ks_pop":52,
    "ks:ks_type":"VILLAGE",
    "name:eng_x_preferred":[
        "Bastora Rani"
    ],
    "name:eng_x_variant":[
        "Bastaura Rani"
    ],
    "wof:name":"Bastora Rani",
    "wof:placetype":"locality",
    "wof:population":52
},
  "geometry": {"coordinates":[78.092842,28.971649],"type":"Point"}
}