{
  "type": "Feature",
  "properties": {
    "iso:country":"IN",
    "ks:ks_name":"Tengani P",
    "ks:ks_pop":358,
    "ks:ks_type":"HABITATION",
    "name:eng_x_preferred":[
        "Tengani P"
    ],
    "wof:name":"Tengani P",
    "wof:placetype":"locality",
    "wof:population":358
},
  "geometry": {"coordinates":[82.432483,23.230072],"type":"Point"}
}