{
  "type": "Feature",
  "properties": {
    "iso:country":"IN",
    "ks:ks_alt_nam":"Arekaduvina doddi",
    "ks:ks_name":"Arekaduvina Doddi",
    "ks:ks_pop":244,
    "ks:ks_type":"HABITATION",
    "name:eng_x_preferred":[
        "Arekaduvina Doddi"
    ],
    "wof:name":"Arekaduvina Doddi",
    "wof:placetype":"locality",
    "wof:population":244
},
  "geometry": {"coordinates":[77.233616,11.932173],"type":"Point"}
}