{
  "type": "Feature",
  "properties": {
    "gn:admin1_code":"35.0",
    "gn:admin2_code":"447.0",
    "gn:asciiname":"Kohpani",
    "gn:country_code":"IN",
    "gn:dem":711,
    "gn:feature_class":"P",
    "gn:feature_code":"PPL",
    "gn:name":"Kohp\u0101ni",
    "gn:population":0,
    "gn:timezone":"Asia/Kolkata",
    "iso:country":"IN",
    "ks:ks_name":"Kohapani",
    "ks:ks_pop":312,
    "ks:ks_type":"VILLAGE",
    "name:eng_x_preferred":[
        "Kohapani"
    ],
    "name:eng_x_variant":[
        "Kohpani"
    ],
    "wof:name":"Kohapani",
    "wof:placetype":"locality",
    "wof:population":312
},
  "geometry": {"coordinates":[78.366681,21.911363],"type":"Point"}
}