{
  "type": "Feature",
  "properties": {
    "iso:country":"IN",
    "ks:ks_name":"Sanjeev Nagar",
    "ks:ks_pop":311,
    "ks:ks_type":"HABITATION",
    "ks:ks_uagg_main":0,
    "name:eng_x_preferred":[
        "Sanjeev Nagar"
    ],
    "wof:name":"Sanjeev Nagar",
    "wof:placetype":"neighbourhood",
    "wof:population":311
},
  "geometry": {"coordinates":[78.49758799999999,14.401988],"type":"Point"}
}