{
  "type": "Feature",
  "properties": {
    "gn:admin1_code":"25.0",
    "gn:admin2_code":"630.0",
    "gn:asciiname":"Nakkalahalli",
    "gn:country_code":"IN",
    "gn:dem":477,
    "gn:feature_class":"P",
    "gn:feature_code":"PPL",
    "gn:name":"Nakkalahalli",
    "gn:population":0,
    "gn:timezone":"Asia/Kolkata",
    "iso:country":"IN",
    "wof:name":"Nakkalahalli",
    "wof:placetype":"neighbourhood"
},
  "geometry": {"coordinates":[78.10065,12.21077],"type":"Point"}
}