{
  "type": "Feature",
  "properties": {
    "iso:country":"IN",
    "ks:ks_alt_nam":"AnnaNagar",
    "ks:ks_name":"Annanagar",
    "ks:ks_pop":330,
    "ks:ks_type":"HABITATION",
    "ks:ks_uagg_main":0,
    "name:eng_x_preferred":[
        "Annanagar"
    ],
    "wof:name":"Annanagar",
    "wof:placetype":"neighbourhood",
    "wof:population":330
},
  "geometry": {"coordinates":[78.459913,12.483744],"type":"Point"}
}