{
  "type": "Feature",
  "properties": {
    "gn:admin1_code":"12.0",
    "gn:admin2_code":"18.0",
    "gn:asciiname":"Margan",
    "gn:country_code":"IN",
    "gn:dem":2696,
    "gn:feature_class":"P",
    "gn:feature_code":"PPL",
    "gn:name":"Margan",
    "gn:population":0,
    "gn:timezone":"Asia/Kolkata",
    "iso:country":"IN",
    "name:ceb_x_preferred":[
        "Margan"
    ],
    "name:fas_x_preferred":[
        "\u0645\u0627\u0631\u06af\u0627\u0646"
    ],
    "name:msa_x_preferred":[
        "Margan"
    ],
    "name:pnb_x_preferred":[
        "\u062f\u06c1\u0633\u062a\u0627\u0646 \u0645\u0627\u0631\u06af\u0627\u0646"
    ],
    "name:swe_x_preferred":[
        "Margan"
    ],
    "wof:name":"Margan",
    "wof:placetype":"locality"
},
  "geometry": {"coordinates":[75.61223000000003,33.48996],"type":"Point"}
}