{
  "type": "Feature",
  "properties": {
    "iso:country":"IN",
    "ks:ks_name":"Subrayakodlu",
    "ks:ks_pop":45,
    "ks:ks_type":"HABITATION",
    "name:eng_x_preferred":[
        "Subrayakodlu"
    ],
    "wof:name":"Subrayakodlu",
    "wof:placetype":"locality",
    "wof:population":45
},
  "geometry": {"coordinates":[74.844899,14.638456],"type":"Point"}
}