{
  "type": "Feature",
  "properties": {
    "gn:admin1_code":"24",
    "gn:admin2_code":"126.0",
    "gn:asciiname":"Matasara",
    "gn:country_code":"IN",
    "gn:dem":346,
    "gn:feature_class":"P",
    "gn:feature_code":"PPL",
    "gn:name":"M\u0101t\u0101sara",
    "gn:population":0,
    "gn:timezone":"Asia/Kolkata",
    "iso:country":"IN",
    "wof:name":"Matasara",
    "wof:placetype":"locality"
},
  "geometry": {"coordinates":[75.58333,24.78333],"type":"Point"}
}