{
  "type": "Feature",
  "properties": {
    "iso:country":"IN",
    "ks:ks_name":"Thakurpada",
    "ks:ks_pop":147,
    "ks:ks_type":"HABITATION",
    "name:eng_x_preferred":[
        "Thakurpada"
    ],
    "wof:name":"Thakurpada",
    "wof:placetype":"locality",
    "wof:population":147
},
  "geometry": {"coordinates":[73.04475499999999,19.813327],"type":"Point"}
}