{
  "type": "Feature",
  "properties": {
    "iso:country":"IN",
    "ks:ks_name":"Girijapada",
    "ks:ks_pop":117,
    "ks:ks_type":"HABITATION",
    "name:eng_x_preferred":[
        "Girijapada"
    ],
    "wof:name":"Girijapada",
    "wof:placetype":"locality",
    "wof:population":117
},
  "geometry": {"coordinates":[84.744271,22.346867],"type":"Point"}
}