{
  "type": "Feature",
  "properties": {
    "iso:country":"IN",
    "ks:ks_name":"Kuttapali",
    "ks:ks_pop":113,
    "ks:ks_type":"HABITATION",
    "name:eng_x_preferred":[
        "Kuttapali"
    ],
    "wof:name":"Kuttapali",
    "wof:placetype":"locality",
    "wof:population":113
},
  "geometry": {"coordinates":[77.98847499999999,11.852991],"type":"Point"}
}