{
  "type": "Feature",
  "properties": {
    "iso:country":"IN",
    "ks:ks_alt_nam":"PURE BRAMGHARA",
    "ks:ks_name":"Pure Bramghara",
    "ks:ks_pop":220,
    "ks:ks_type":"HABITATION",
    "ks:ks_uagg_main":0,
    "name:eng_x_preferred":[
        "Pure Bramghara"
    ],
    "wof:name":"Pure Bramghara",
    "wof:placetype":"neighbourhood",
    "wof:population":220
},
  "geometry": {"coordinates":[81.983834,26.477152],"type":"Point"}
}