{
  "type": "Feature",
  "properties": {
    "gn:admin1_code":"13.0",
    "gn:admin2_code":"594.0",
    "gn:asciiname":"Pukkod",
    "gn:country_code":"IN",
    "gn:dem":13,
    "gn:feature_class":"P",
    "gn:feature_code":"PPL",
    "gn:name":"P\u016bkk\u014dd",
    "gn:population":0,
    "gn:timezone":"Asia/Kolkata",
    "iso:country":"IN",
    "ks:ks_alt_nam":"P\u016bkk\u014dd",
    "ks:ks_name":"Pukkod",
    "ks:ks_type":"VILLAGE",
    "name:eng_x_preferred":[
        "Pukkod"
    ],
    "name:eng_x_variant":[
        "P\u016bkk\u014dd"
    ],
    "wof:name":"Pukkod",
    "wof:placetype":"locality"
},
  "geometry": {"coordinates":[76.042624,10.623629],"type":"Point"}
}