{
  "type": "Feature",
  "properties": {
    "iso:country":"IN",
    "ks:ks_name":"Kotara",
    "ks:ks_pop":391,
    "ks:ks_type":"HABITATION",
    "name:eng_x_preferred":[
        "Kotara"
    ],
    "wof:name":"Kotara",
    "wof:placetype":"locality",
    "wof:population":391
},
  "geometry": {"coordinates":[75.421594,12.69478],"type":"Point"}
}