{
  "type": "Feature",
  "properties": {
    "gn:admin1_code":"19.0",
    "gn:admin2_code":"556.0",
    "gn:asciiname":"Hire Muchalgud",
    "gn:country_code":"IN",
    "gn:dem":596,
    "gn:feature_class":"P",
    "gn:feature_code":"PPL",
    "gn:name":"Hire Muchalgud",
    "gn:population":0,
    "gn:timezone":"Asia/Kolkata",
    "iso:country":"IN",
    "wof:name":"Hire Muchalgud",
    "wof:placetype":"locality"
},
  "geometry": {"coordinates":[75.65980999999999,15.99168],"type":"Point"}
}