{
  "type": "Feature",
  "properties": {
    "iso:country":"IN",
    "ks:ks_name":"Madpada",
    "ks:ks_pop":140,
    "ks:ks_type":"HABITATION",
    "name:eng_x_preferred":[
        "Madpada"
    ],
    "wof:name":"Madpada",
    "wof:placetype":"locality",
    "wof:population":140
},
  "geometry": {"coordinates":[73.03309400000001,20.007676],"type":"Point"}
}