{
  "type": "Feature",
  "properties": {
    "gn:admin1_code":"40",
    "gn:admin2_code":"541.0",
    "gn:asciiname":"Edira",
    "gn:country_code":"IN",
    "gn:dem":82,
    "gn:feature_class":"P",
    "gn:feature_code":"PPL",
    "gn:name":"Edira",
    "gn:population":0,
    "gn:timezone":"Asia/Kolkata",
    "iso:country":"IN",
    "ks:ks_name":"Edhira",
    "ks:ks_pop":1146,
    "ks:ks_type":"VILLAGE",
    "name:eng_x_preferred":[
        "Edhira"
    ],
    "name:eng_x_variant":[
        "Edira"
    ],
    "wof:name":"Edhira",
    "wof:placetype":"locality",
    "wof:population":1146
},
  "geometry": {"coordinates":[80.72728600000001,18.144357],"type":"Point"}
}