{
  "type": "Feature",
  "properties": {
    "iso:country":"IN",
    "ks:ks_name":"Bapeli",
    "ks:ks_pop":323,
    "ks:ks_type":"VILLAGE",
    "name:eng_x_preferred":[
        "Bapeli"
    ],
    "wof:name":"Bapeli",
    "wof:placetype":"locality",
    "wof:population":323
},
  "geometry": {"coordinates":[74.509569,15.184374],"type":"Point"}
}