{
  "type": "Feature",
  "properties": {
    "iso:country":"IN",
    "ks:ks_name":"Kotda",
    "ks:ks_pop":1443,
    "ks:ks_type":"VILLAGE",
    "name:eng_x_preferred":[
        "Kotda"
    ],
    "wof:name":"Kotda",
    "wof:placetype":"locality",
    "wof:population":1443
},
  "geometry": {"coordinates":[74.82455299999999,23.142885],"type":"Point"}
}