{
  "type": "Feature",
  "properties": {
    "iso:country":"IN",
    "ks:ks_name":"Mahudipada",
    "ks:ks_pop":236,
    "ks:ks_type":"HABITATION",
    "name:eng_x_preferred":[
        "Mahudipada"
    ],
    "wof:name":"Mahudipada",
    "wof:placetype":"locality",
    "wof:population":236
},
  "geometry": {"coordinates":[74.89181499999999,23.290126],"type":"Point"}
}