{
  "type": "Feature",
  "properties": {
    "iso:country":"IN",
    "ks:ks_name":"Jeera",
    "ks:ks_pop":709,
    "ks:ks_type":"VILLAGE",
    "name:eng_x_preferred":[
        "Jeera"
    ],
    "wof:name":"Jeera",
    "wof:placetype":"locality",
    "wof:population":709
},
  "geometry": {"coordinates":[82.788234,18.409515],"type":"Point"}
}