{
  "type": "Feature",
  "properties": {
    "iso:country":"IN",
    "ks:ks_name":"Pub Chiling",
    "ks:ks_pop":500,
    "ks:ks_type":"HABITATION",
    "name:eng_x_preferred":[
        "Pub Chiling"
    ],
    "wof:name":"Pub Chiling",
    "wof:placetype":"locality",
    "wof:population":500
},
  "geometry": {"coordinates":[91.547144,26.424323],"type":"Point"}
}