{
  "type": "Feature",
  "properties": {
    "iso:country":"IN",
    "ks:ks_name":"Manjhwarpara",
    "ks:ks_pop":98,
    "ks:ks_type":"HABITATION",
    "name:eng_x_preferred":[
        "Manjhwarpara"
    ],
    "wof:name":"Manjhwarpara",
    "wof:placetype":"locality",
    "wof:population":98
},
  "geometry": {"coordinates":[82.355322,22.797999],"type":"Point"}
}