{
  "type": "Feature",
  "properties": {
    "iso:country":"IN",
    "ks:ks_name":"Akanwali",
    "ks:ks_pop":0,
    "ks:ks_type":"VILLAGE",
    "name:eng_x_preferred":[
        "Akanwali"
    ],
    "wof:name":"Akanwali",
    "wof:placetype":"locality",
    "wof:population":0
},
  "geometry": {"coordinates":[69.798648,26.601888],"type":"Point"}
}