{
  "type": "Feature",
  "properties": {
    "iso:country":"IN",
    "ks:ks_name":"Uttar S Pur Madhyam",
    "ks:ks_pop":832,
    "ks:ks_type":"HABITATION",
    "name:eng_x_preferred":[
        "Uttar S Pur Madhyam"
    ],
    "wof:name":"Uttar S Pur Madhyam",
    "wof:placetype":"locality",
    "wof:population":832
},
  "geometry": {"coordinates":[88.26555999999999,21.675957],"type":"Point"}
}