{
  "type": "Feature",
  "properties": {
    "iso:country":"IN",
    "ks:ks_name":"Dubikhal",
    "ks:ks_pop":46,
    "ks:ks_type":"HABITATION",
    "name:eng_x_preferred":[
        "Dubikhal"
    ],
    "wof:name":"Dubikhal",
    "wof:placetype":"locality",
    "wof:population":46
},
  "geometry": {"coordinates":[85.937888,21.035283],"type":"Point"}
}