{
  "type": "Feature",
  "properties": {
    "gn:admin1_code":"36.0",
    "gn:admin2_code":"182.0",
    "gn:asciiname":"Kohraura",
    "gn:country_code":"IN",
    "gn:dem":153,
    "gn:feature_class":"P",
    "gn:feature_code":"PPL",
    "gn:name":"Kohraura",
    "gn:population":0,
    "gn:timezone":"Asia/Kolkata",
    "iso:country":"IN",
    "wof:name":"Kohraura",
    "wof:placetype":"locality"
},
  "geometry": {"coordinates":[82.24665,27.71321],"type":"Point"}
}