{
  "type": "Feature",
  "properties": {
    "iso:country":"IN",
    "ks:ks_name":"Kaliyanda Family",
    "ks:ks_pop":78,
    "ks:ks_type":"HABITATION",
    "name:eng_x_preferred":[
        "Kaliyanda Family"
    ],
    "wof:name":"Kaliyanda Family",
    "wof:placetype":"locality",
    "wof:population":78
},
  "geometry": {"coordinates":[75.65352,12.286447],"type":"Point"}
}