{
  "type": "Feature",
  "properties": {
    "iso:country":"IN",
    "ks:ks_alt_nam":"Khajura Ar\u0101zi",
    "ks:ks_name":"Khajura Arazi",
    "ks:ks_type":"VILLAGE",
    "name:eng_x_preferred":[
        "Khajura Arazi"
    ],
    "name:eng_x_variant":[
        "Khajura Ar\u0101zi"
    ],
    "wof:name":"Khajura Arazi",
    "wof:placetype":"locality"
},
  "geometry": {"coordinates":[83.421036,25.230717],"type":"Point"}
}