{
  "type": "Feature",
  "properties": {
    "iso:country":"IN",
    "ks:ks_alt_nam":"SODHAKALA",
    "ks:ks_name":"Sodhakala",
    "ks:ks_pop":242,
    "ks:ks_type":"HABITATION",
    "name:eng_x_preferred":[
        "Sodhakala"
    ],
    "wof:name":"Sodhakala",
    "wof:placetype":"locality",
    "wof:population":242
},
  "geometry": {"coordinates":[82.02200499999999,22.472128],"type":"Point"}
}