{
  "type": "Feature",
  "properties": {
    "iso:country":"IN",
    "ks:ks_name":"Malipada",
    "ks:ks_pop":28,
    "ks:ks_type":"VILLAGE",
    "name:eng_x_preferred":[
        "Malipada"
    ],
    "wof:name":"Malipada",
    "wof:placetype":"locality",
    "wof:population":28
},
  "geometry": {"coordinates":[83.207095,19.663226],"type":"Point"}
}