{
  "type": "Feature",
  "properties": {
    "iso:country":"IN",
    "ks:ks_name":"Arjungawan Kalan",
    "ks:ks_pop":473,
    "ks:ks_type":"VILLAGE",
    "name:eng_x_preferred":[
        "Arjungawan Kalan"
    ],
    "wof:name":"Arjungawan Kalan",
    "wof:placetype":"locality",
    "wof:population":473
},
  "geometry": {"coordinates":[77.759389,25.286997],"type":"Point"}
}