{
  "type": "Feature",
  "properties": {
    "gn:admin1_code":"35",
    "gn:admin2_code":"427.0",
    "gn:asciiname":"Manegaon",
    "gn:country_code":"IN",
    "gn:dem":368,
    "gn:feature_class":"P",
    "gn:feature_code":"PPL",
    "gn:name":"M\u0101negaon",
    "gn:population":0,
    "gn:timezone":"Asia/Kolkata",
    "iso:country":"IN",
    "ks:ks_alt_nam":"M\u0101negaon",
    "ks:ks_name":"Manegaon",
    "ks:ks_type":"VILLAGE",
    "name:eng_x_preferred":[
        "Manegaon"
    ],
    "name:eng_x_variant":[
        "M\u0101negaon"
    ],
    "wof:name":"Manegaon",
    "wof:placetype":"locality"
},
  "geometry": {"coordinates":[79.308432,23.59222],"type":"Point"}
}