{
  "type": "Feature",
  "properties": {
    "iso:country":"IN",
    "ks:ks_name":"Tarunnagar",
    "ks:ks_pop":368,
    "ks:ks_type":"HABITATION",
    "name:eng_x_preferred":[
        "Tarunnagar"
    ],
    "wof:name":"Tarunnagar",
    "wof:placetype":"locality",
    "wof:population":368
},
  "geometry": {"coordinates":[80.037797,19.637228],"type":"Point"}
}