{
  "type": "Feature",
  "properties": {
    "gn:admin1_code":"38",
    "gn:admin2_code":"365.0",
    "gn:asciiname":"Murhu",
    "gn:country_code":"IN",
    "gn:dem":593,
    "gn:feature_class":"P",
    "gn:feature_code":"PPL",
    "gn:name":"Murhu",
    "gn:population":0,
    "gn:timezone":"Asia/Kolkata",
    "iso:country":"IN",
    "wof:name":"Murhu",
    "wof:placetype":"locality"
},
  "geometry": {"coordinates":[85.28099,22.97266],"type":"Point"}
}