{
  "type": "Feature",
  "properties": {
    "iso:country":"IN",
    "ks:ks_alt_nam":"Rayapalli & B.Palli",
    "ks:ks_name":"Rayapalli & B.palli",
    "ks:ks_pop":239,
    "ks:ks_type":"HABITATION",
    "name:eng_x_preferred":[
        "Rayapalli & B.palli"
    ],
    "wof:name":"Rayapalli & B.palli",
    "wof:placetype":"locality",
    "wof:population":239
},
  "geometry": {"coordinates":[78.655005,14.022041],"type":"Point"}
}