{
  "type": "Feature",
  "properties": {
    "iso:country":"IN",
    "ks:ks_name":"Ferkuwa Faliya",
    "ks:ks_pop":1050,
    "ks:ks_type":"HABITATION",
    "name:eng_x_preferred":[
        "Ferkuwa Faliya"
    ],
    "wof:name":"Ferkuwa Faliya",
    "wof:placetype":"locality",
    "wof:population":1050
},
  "geometry": {"coordinates":[73.718433,22.75355],"type":"Point"}
}