{
  "type": "Feature",
  "properties": {
    "gn:admin1_code":"38.0",
    "gn:admin2_code":"364",
    "gn:asciiname":"Angara",
    "gn:country_code":"IN",
    "gn:dem":620,
    "gn:feature_class":"P",
    "gn:feature_code":"PPL",
    "gn:name":"Angar\u0101",
    "gn:population":0,
    "gn:timezone":"Asia/Kolkata",
    "iso:country":"IN",
    "ks:ks_name":"Angara",
    "ks:ks_pop":2302,
    "ks:ks_type":"VILLAGE",
    "ks:ks_uagg_main":0,
    "name:eng_x_preferred":[
        "Angara"
    ],
    "name:urd_x_preferred":[
        "\u0627\u0646\u06af\u0627\u0631\u0627"
    ],
    "wof:name":"Angara",
    "wof:placetype":"neighbourhood",
    "wof:population":2302
},
  "geometry": {"coordinates":[85.511438,23.401969],"type":"Point"}
}