{
  "type": "Feature",
  "properties": {
    "gn:admin1_code":"11",
    "gn:admin2_code":"33.0",
    "gn:asciiname":"Baglan",
    "gn:country_code":"IN",
    "gn:dem":1916,
    "gn:feature_class":"P",
    "gn:feature_code":"PPL",
    "gn:name":"Baglan",
    "gn:population":0,
    "gn:timezone":"Asia/Kolkata",
    "iso:country":"IN",
    "name:bre_x_preferred":[
        "Baglan"
    ],
    "name:ceb_x_preferred":[
        "Baglan"
    ],
    "name:cor_x_preferred":[
        "Baglan"
    ],
    "name:cym_x_preferred":[
        "Baglan"
    ],
    "name:deu_x_preferred":[
        "Baglan"
    ],
    "name:est_x_preferred":[
        "Baglan"
    ],
    "name:fra_x_preferred":[
        "Baglan"
    ],
    "name:gla_x_preferred":[
        "Baglan"
    ],
    "name:nld_x_preferred":[
        "Baghlan"
    ],
    "name:rus_x_preferred":[
        "\u0411\u0430\u0433\u043b\u0430\u043d"
    ],
    "name:swe_x_preferred":[
        "Baglan"
    ],
    "name:uzb_x_preferred":[
        "Bag\u02bblon"
    ],
    "wof:name":"Baglan",
    "wof:placetype":"locality"
},
  "geometry": {"coordinates":[77.57746,30.97129],"type":"Point"}
}