{
  "type": "Feature",
  "properties": {
    "iso:country":"IN",
    "ks:ks_alt_nam":"Banp\u0101s Reserved Forest",
    "ks:ks_alt_nam_2":"Banpas Reserved Forest",
    "ks:ks_name":"Banpas",
    "ks:ks_type":"VILLAGE",
    "name:eng_x_preferred":[
        "Banpas"
    ],
    "name:eng_x_variant":[
        "Banp\u0101s Reserved Forest",
        "Banpas Reserved Forest"
    ],
    "wof:name":"Banpas",
    "wof:placetype":"locality"
},
  "geometry": {"coordinates":[79.99732899999999,29.307609],"type":"Point"}
}