{
  "type": "Feature",
  "properties": {
    "gn:admin1_code":"35",
    "gn:admin2_code":"452.0",
    "gn:asciiname":"Pala",
    "gn:country_code":"IN",
    "gn:dem":381,
    "gn:feature_class":"P",
    "gn:feature_code":"PPL",
    "gn:name":"P\u0101la",
    "gn:population":0,
    "gn:timezone":"Asia/Kolkata",
    "iso:country":"IN",
    "name:ben_x_preferred":[
        "\u09aa\u09be\u09b2\u09be"
    ],
    "name:cat_x_preferred":[
        "Pala"
    ],
    "name:ceb_x_preferred":[
        "Pala"
    ],
    "name:ces_x_preferred":[
        "Pala"
    ],
    "name:deu_x_preferred":[
        "Pala"
    ],
    "name:ell_x_preferred":[
        "\u03a0\u03ac\u03bb\u03b1"
    ],
    "name:est_x_preferred":[
        "Pala"
    ],
    "name:eus_x_preferred":[
        "Pala"
    ],
    "name:fra_x_preferred":[
        "Pala"
    ],
    "name:glg_x_preferred":[
        "Pala"
    ],
    "name:heb_x_preferred":[
        "\u05e4\u05dc\u05d4"
    ],
    "name:hrv_x_preferred":[
        "Pala"
    ],
    "name:hun_x_preferred":[
        "Pala"
    ],
    "name:ita_x_preferred":[
        "Pala"
    ],
    "name:kor_x_preferred":[
        "\ud314\ub77c"
    ],
    "name:lit_x_preferred":[
        "Pala"
    ],
    "name:mal_x_preferred":[
        "\u0d2a\u0d3e\u0d32"
    ],
    "name:nld_x_preferred":[
        "Pala"
    ],
    "name:pol_x_preferred":[
        "Pala"
    ],
    "name:por_x_preferred":[
        "Pala"
    ],
    "name:ron_x_preferred":[
        "Pala"
    ],
    "name:rus_x_preferred":[
        "\u041f\u0430\u043b\u0430"
    ],
    "name:slk_x_preferred":[
        "Pala"
    ],
    "name:spa_x_preferred":[
        "Pala"
    ],
    "name:srp_x_preferred":[
        "\u041f\u0430\u043b\u0430"
    ],
    "name:swe_x_preferred":[
        "Pala"
    ],
    "name:tgl_x_preferred":[
        "Pala"
    ],
    "name:tur_x_preferred":[
        "Pala"
    ],
    "name:ukr_x_preferred":[
        "\u041f\u0430\u043b\u0430"
    ],
    "name:vie_x_preferred":[
        "Pala"
    ],
    "name:vol_x_preferred":[
        "Pala"
    ],
    "wof:name":"Pala",
    "wof:placetype":"locality"
},
  "geometry": {"coordinates":[79.22047000000001,22.84513],"type":"Point"}
}