{
  "type": "Feature",
  "properties": {
    "iso:country":"IN",
    "ks:ks_name":"Madhaiyan Khagwavas",
    "ks:ks_pop":285,
    "ks:ks_type":"HABITATION",
    "name:eng_x_preferred":[
        "Madhaiyan Khagwavas"
    ],
    "wof:name":"Madhaiyan Khagwavas",
    "wof:placetype":"locality",
    "wof:population":285
},
  "geometry": {"coordinates":[77.72632900000001,28.498801],"type":"Point"}
}