{
  "type": "Feature",
  "properties": {
    "iso:country":"IN",
    "ks:ks_name":"Nagla Ninnu",
    "ks:ks_pop":109,
    "ks:ks_type":"HABITATION",
    "ks:ks_uagg_main":0,
    "name:eng_x_preferred":[
        "Nagla Ninnu"
    ],
    "wof:name":"Nagla Ninnu",
    "wof:placetype":"neighbourhood",
    "wof:population":109
},
  "geometry": {"coordinates":[78.131303,27.261362],"type":"Point"}
}