{
  "type": "Feature",
  "properties": {
    "iso:country":"IN",
    "ks:ks_alt_nam":"ragihakkalu",
    "ks:ks_name":"Ragihakkalu",
    "ks:ks_pop":43,
    "ks:ks_type":"HABITATION",
    "name:eng_x_preferred":[
        "Ragihakkalu"
    ],
    "wof:name":"Ragihakkalu",
    "wof:placetype":"locality",
    "wof:population":43
},
  "geometry": {"coordinates":[75.821934,13.874177],"type":"Point"}
}