{
  "type": "Feature",
  "properties": {
    "iso:country":"IN",
    "ks:ks_name":"Loharadebri",
    "ks:ks_pop":569,
    "ks:ks_type":"VILLAGE",
    "ks:ks_uagg_main":0,
    "name:eng_x_preferred":[
        "Loharadebri"
    ],
    "wof:name":"Loharadebri",
    "wof:placetype":"neighbourhood",
    "wof:population":569
},
  "geometry": {"coordinates":[83.090805,20.189567],"type":"Point"}
}