{
  "type": "Feature",
  "properties": {
    "iso:country":"IN",
    "ks:ks_name":"Ghilazar",
    "ks:ks_pop":335,
    "ks:ks_type":"HABITATION",
    "name:eng_x_preferred":[
        "Ghilazar"
    ],
    "wof:name":"Ghilazar",
    "wof:placetype":"locality",
    "wof:population":335
},
  "geometry": {"coordinates":[91.65126100000001,26.677746],"type":"Point"}
}