{
  "type": "Feature",
  "properties": {
    "iso:country":"IN",
    "ks:ks_name":"Dholi Doob",
    "ks:ks_pop":1758,
    "ks:ks_type":"VILLAGE",
    "ks:ks_uagg_main":0,
    "name:eng_x_preferred":[
        "Dholi Doob"
    ],
    "wof:name":"Dholi Doob",
    "wof:placetype":"neighbourhood",
    "wof:population":1758
},
  "geometry": {"coordinates":[76.60994700000001,27.614994],"type":"Point"}
}