{
  "type": "Feature",
  "properties": {
    "iso:country":"IN",
    "ks:ks_name":"Gosaipura",
    "ks:ks_pop":721,
    "ks:ks_type":"HABITATION",
    "name:eng_x_preferred":[
        "Gosaipura"
    ],
    "wof:name":"Gosaipura",
    "wof:placetype":"locality",
    "wof:population":721
},
  "geometry": {"coordinates":[73.005978,27.152092],"type":"Point"}
}