{
  "type": "Feature",
  "properties": {
    "gn:country":"IN",
    "gn:fcode":"PPL",
    "gn:pop":57170,
    "iso:country":"IN",
    "name:bpy_x_preferred":[
        "\u09aa\u09cb\u09a8\u09cd\u09a8\u09c1\u09b0"
    ],
    "name:bul_x_preferred":[
        "\u041f\u043e\u043d\u0443\u0440"
    ],
    "name:eng_x_preferred":[
        "Ponnur"
    ],
    "name:fra_x_preferred":[
        "Ponnur"
    ],
    "name:ita_x_preferred":[
        "Ponnur"
    ],
    "name:msa_x_preferred":[
        "Ponnur"
    ],
    "name:new_x_preferred":[
        "\u092a\u094a\u0928\u094d\u0928\u0942\u0930\u0941 \u092e\u0923\u094d\u0921\u0932"
    ],
    "name:nld_x_preferred":[
        "Ponnur"
    ],
    "name:ori_x_preferred":[
        "\u0b2a\u0b4b\u0b28\u0b4d\u0b28\u0b41\u0b30"
    ],
    "name:pam_x_preferred":[
        "Ponnur"
    ],
    "name:por_x_preferred":[
        "Ponnur"
    ],
    "name:swe_x_preferred":[
        "Ponnur"
    ],
    "name:tel_x_preferred":[
        "\u0c2a\u0c4a\u0c28\u0c4d\u0c28\u0c42\u0c30\u0c41"
    ],
    "name:vie_x_preferred":[
        "Ponnur"
    ],
    "name:zho_x_preferred":[
        "\u84ec\u52aa\u5c14"
    ],
    "qs:name":"Ponn\u016bru",
    "qs:photos_9r":0,
    "qs:photos_sr":0,
    "qs:pop_sr":"8",
    "wof:name":"Ponn\u016bru",
    "wof:placetype":"locality",
    "wof:population":57170
},
  "geometry": {"coordinates":[80.55203,16.06547],"type":"Point"}
}