{
  "type": "Feature",
  "properties": {
    "iso:country":"IN",
    "ks:ks_name":"Dheluaha",
    "ks:ks_pop":1130,
    "ks:ks_type":"VILLAGE",
    "name:eng_x_preferred":[
        "Dheluaha"
    ],
    "wof:name":"Dheluaha",
    "wof:placetype":"locality",
    "wof:population":1130
},
  "geometry": {"coordinates":[85.234352,26.335034],"type":"Point"}
}