{
  "type": "Feature",
  "properties": {
    "iso:country":"IN",
    "ks:ks_name":"Gura",
    "ks:ks_pop":933,
    "ks:ks_type":"HABITATION",
    "name:eng_x_preferred":[
        "Gura"
    ],
    "wof:name":"Gura",
    "wof:placetype":"locality",
    "wof:population":933
},
  "geometry": {"coordinates":[73.232303,24.361636],"type":"Point"}
}