{
  "type": "Feature",
  "properties": {
    "iso:country":"IN",
    "ks:ks_name":"Jammichinnaipeta",
    "ks:ks_pop":54,
    "ks:ks_type":"HABITATION",
    "name:eng_x_preferred":[
        "Jammichinnaipeta"
    ],
    "wof:name":"Jammichinnaipeta",
    "wof:placetype":"locality",
    "wof:population":54
},
  "geometry": {"coordinates":[84.105614,18.673706],"type":"Point"}
}