{
  "type": "Feature",
  "properties": {
    "gn:admin1_code":"37",
    "gn:admin2_code":"405.0",
    "gn:asciiname":"Rainkhol",
    "gn:country_code":"IN",
    "gn:dem":409,
    "gn:feature_class":"P",
    "gn:feature_code":"PPL",
    "gn:name":"Rainkhol",
    "gn:population":0,
    "gn:timezone":"Asia/Kolkata",
    "iso:country":"IN",
    "wof:name":"Rainkhol",
    "wof:placetype":"locality"
},
  "geometry": {"coordinates":[82.86395999999998,22.15363],"type":"Point"}
}