{
  "type": "Feature",
  "properties": {
    "iso:country":"IN",
    "ks:ks_alt_nam":"SANKAR PARA",
    "ks:ks_name":"Sankar Para",
    "ks:ks_pop":53,
    "ks:ks_type":"HABITATION",
    "ks:ks_uagg_main":0,
    "name:eng_x_preferred":[
        "Sankar Para"
    ],
    "wof:name":"Sankar Para",
    "wof:placetype":"neighbourhood",
    "wof:population":53
},
  "geometry": {"coordinates":[88.70819299999999,26.653325],"type":"Point"}
}