{
  "type": "Feature",
  "properties": {
    "gn:admin1_code":"19.0",
    "gn:admin2_code":"563",
    "gn:asciiname":"Harkantarkeri",
    "gn:country_code":"IN",
    "gn:dem":9,
    "gn:feature_class":"P",
    "gn:feature_code":"PPL",
    "gn:name":"Harkantarkeri",
    "gn:population":0,
    "gn:timezone":"Asia/Kolkata",
    "iso:country":"IN",
    "ks:ks_name":"Harikantra Keri",
    "ks:ks_pop":177,
    "ks:ks_type":"HABITATION",
    "name:eng_x_preferred":[
        "Harikantra Keri"
    ],
    "name:eng_x_variant":[
        "Harkantarkeri"
    ],
    "wof:name":"Harikantra Keri",
    "wof:placetype":"locality",
    "wof:population":177
},
  "geometry": {"coordinates":[74.411928,14.346517],"type":"Point"}
}