{
  "type": "Feature",
  "properties": {
    "iso:country":"IN",
    "ks:ks_name":"Shyamraypur",
    "ks:ks_pop":94,
    "ks:ks_type":"VILLAGE",
    "name:eng_x_preferred":[
        "Shyamraypur"
    ],
    "wof:name":"Shyamraypur",
    "wof:placetype":"locality",
    "wof:population":94
},
  "geometry": {"coordinates":[87.334743,22.277266],"type":"Point"}
}