{
  "type": "Feature",
  "properties": {
    "iso:country":"IN",
    "ks:ks_name":"Kalakha",
    "ks:ks_pop":558,
    "ks:ks_type":"VILLAGE",
    "name:eng_x_preferred":[
        "Kalakha"
    ],
    "wof:name":"Kalakha",
    "wof:placetype":"locality",
    "wof:population":558
},
  "geometry": {"coordinates":[86.13434100000001,20.175219],"type":"Point"}
}