{
  "type": "Feature",
  "properties": {
    "gn:admin1_code":"36.0",
    "gn:admin2_code":"193.0",
    "gn:asciiname":"Beur",
    "gn:country_code":"IN",
    "gn:dem":65,
    "gn:feature_class":"P",
    "gn:feature_code":"PPL",
    "gn:name":"Beur",
    "gn:population":0,
    "gn:timezone":"Asia/Kolkata",
    "iso:country":"IN",
    "ks:ks_name":"Beur",
    "ks:ks_type":"VILLAGE",
    "name:ara_x_preferred":[
        "\u0628\u0648\u0631"
    ],
    "name:deu_x_preferred":[
        "Beur"
    ],
    "name:eng_x_preferred":[
        "Beur"
    ],
    "name:fra_x_preferred":[
        "Beur"
    ],
    "name:hin_x_preferred":[
        "\u092c\u0947\u090a\u0930"
    ],
    "name:tur_x_preferred":[
        "Beur"
    ],
    "wof:name":"Beur",
    "wof:placetype":"locality"
},
  "geometry": {"coordinates":[84.28518,25.867499],"type":"Point"}
}