{
  "type": "Feature",
  "properties": {
    "gn:admin1_code":"10.0",
    "gn:admin2_code":"69.0",
    "gn:asciiname":"Bhori",
    "gn:country_code":"IN",
    "gn:dem":994,
    "gn:feature_class":"P",
    "gn:feature_code":"PPL",
    "gn:name":"Bhori",
    "gn:population":0,
    "gn:timezone":"Asia/Kolkata",
    "iso:country":"IN",
    "wof:name":"Bhori",
    "wof:placetype":"locality"
},
  "geometry": {"coordinates":[77.04288000000003,30.71377],"type":"Point"}
}