{
  "type": "Feature",
  "properties": {
    "gn:admin1_code":"36",
    "gn:admin2_code":"154.0",
    "gn:asciiname":"Lalapur",
    "gn:country_code":"IN",
    "gn:dem":136,
    "gn:feature_class":"P",
    "gn:feature_code":"PPL",
    "gn:name":"Lal\u0101pur",
    "gn:population":0,
    "gn:timezone":"Asia/Kolkata",
    "iso:country":"IN",
    "wof:name":"Lalapur",
    "wof:placetype":"neighbourhood"
},
  "geometry": {"coordinates":[81.03157,27.30723],"type":"Point"}
}