{
  "type": "Feature",
  "properties": {
    "gn:admin1_code":"16",
    "gn:admin2_code":"522.0",
    "gn:asciiname":"Takli",
    "gn:country_code":"IN",
    "gn:dem":513,
    "gn:feature_class":"P",
    "gn:feature_code":"PPL",
    "gn:name":"T\u0101kli",
    "gn:population":0,
    "gn:timezone":"Asia/Kolkata",
    "iso:country":"IN",
    "wof:name":"Takli",
    "wof:placetype":"neighbourhood"
},
  "geometry": {"coordinates":[74.66777999999999,19.45325],"type":"Point"}
}