{
  "type": "Feature",
  "properties": {
    "iso:country":"IN",
    "ks:ks_name":"Bachkande",
    "ks:ks_pop":289,
    "ks:ks_type":"VILLAGE",
    "name:eng_x_preferred":[
        "Bachkande"
    ],
    "wof:name":"Bachkande",
    "wof:placetype":"locality",
    "wof:population":289
},
  "geometry": {"coordinates":[79.792703,29.500223],"type":"Point"}
}