{
  "type": "Feature",
  "properties": {
    "iso:country":"IN",
    "ks:ks_name":"Harerkhola",
    "ks:ks_pop":3965,
    "ks:ks_type":"VILLAGE",
    "ks:ks_uagg_main":0,
    "name:eng_x_preferred":[
        "Harerkhola"
    ],
    "wof:name":"Harerkhola",
    "wof:placetype":"neighbourhood",
    "wof:population":3965
},
  "geometry": {"coordinates":[91.81204700000001,24.182731],"type":"Point"}
}