{
  "type": "Feature",
  "properties": {
    "iso:country":"IN",
    "ks:ks_name":"Dighra",
    "ks:ks_pop":3724,
    "ks:ks_type":"VILLAGE",
    "ks:ks_uagg_main":0,
    "name:eng_x_preferred":[
        "Dighra"
    ],
    "wof:name":"Dighra",
    "wof:placetype":"locality",
    "wof:population":3724
},
  "geometry": {"coordinates":[88.52973,22.783423],"type":"Point"}
}