{
  "type": "Feature",
  "properties": {
    "iso:country":"IN",
    "ks:ks_name":"Saladasingi",
    "ks:ks_pop":204,
    "ks:ks_type":"VILLAGE",
    "name:eng_x_preferred":[
        "Saladasingi"
    ],
    "wof:name":"Saladasingi",
    "wof:placetype":"locality",
    "wof:population":204
},
  "geometry": {"coordinates":[84.07541500000001,19.116179],"type":"Point"}
}