{
  "type": "Feature",
  "properties": {
    "iso:country":"IN",
    "ks:ks_name":"Kallagudee",
    "ks:ks_pop":18,
    "ks:ks_type":"HABITATION",
    "name:eng_x_preferred":[
        "Kallagudee"
    ],
    "wof:name":"Kallagudee",
    "wof:placetype":"locality",
    "wof:population":18
},
  "geometry": {"coordinates":[75.365657,12.561753],"type":"Point"}
}