{
  "type": "Feature",
  "properties": {
    "iso:country":"IN",
    "ks:ks_alt_nam":"sekhalpur",
    "ks:ks_name":"Sekhalpur",
    "ks:ks_pop":225,
    "ks:ks_type":"HABITATION",
    "name:eng_x_preferred":[
        "Sekhalpur"
    ],
    "wof:name":"Sekhalpur",
    "wof:placetype":"locality",
    "wof:population":225
},
  "geometry": {"coordinates":[81.77118,25.52105],"type":"Point"}
}