{
  "type": "Feature",
  "properties": {
    "iso:country":"IN",
    "ks:ks_name":"Kurubarakoppalu",
    "ks:ks_pop":136,
    "ks:ks_type":"HABITATION",
    "name:eng_x_preferred":[
        "Kurubarakoppalu"
    ],
    "wof:name":"Kurubarakoppalu",
    "wof:placetype":"locality",
    "wof:population":136
},
  "geometry": {"coordinates":[75.978539,13.198522],"type":"Point"}
}