{
  "type": "Feature",
  "properties": {
    "gn:admin1_code":"39.0",
    "gn:admin2_code":"66.0",
    "gn:asciiname":"Kamalwaganja Kabdal",
    "gn:country_code":"IN",
    "gn:dem":385,
    "gn:feature_class":"P",
    "gn:feature_code":"PPL",
    "gn:name":"Kamalwag\u0101nja Kabd\u0101l",
    "gn:population":0,
    "gn:timezone":"Asia/Kolkata",
    "iso:country":"IN",
    "ks:ks_name":"Kamaluwa Ghaja Kabdal",
    "ks:ks_pop":193,
    "ks:ks_type":"VILLAGE",
    "ks:ks_uagg_main":0,
    "name:eng_x_preferred":[
        "Kamaluwa Ghaja Kabdal"
    ],
    "wof:name":"Kamaluwa Ghaja Kabdal",
    "wof:placetype":"neighbourhood",
    "wof:population":193
},
  "geometry": {"coordinates":[79.463899,29.215826],"type":"Point"}
}