{
  "type": "Feature",
  "properties": {
    "iso:country":"IN",
    "ks:ks_name":"Banskunri",
    "ks:ks_pop":57,
    "ks:ks_type":"VILLAGE",
    "name:eng_x_preferred":[
        "Banskunri"
    ],
    "wof:name":"Banskunri",
    "wof:placetype":"locality",
    "wof:population":57
},
  "geometry": {"coordinates":[87.06101700000001,23.587658],"type":"Point"}
}