{
  "type": "Feature",
  "properties": {
    "iso:country":"IN",
    "ks:ks_alt_nam":"jhorkipara",
    "ks:ks_name":"Jhorkipara",
    "ks:ks_pop":958,
    "ks:ks_type":"HABITATION",
    "name:eng_x_preferred":[
        "Jhorkipara"
    ],
    "wof:name":"Jhorkipara",
    "wof:placetype":"locality",
    "wof:population":958
},
  "geometry": {"coordinates":[82.373165,22.333513],"type":"Point"}
}