{
  "type": "Feature",
  "properties": {
    "iso:country":"IN",
    "ks:ks_alt_nam":"paavara",
    "ks:ks_name":"Paavara",
    "ks:ks_pop":562,
    "ks:ks_type":"HABITATION",
    "name:eng_x_preferred":[
        "Paavara"
    ],
    "wof:name":"Paavara",
    "wof:placetype":"locality",
    "wof:population":562
},
  "geometry": {"coordinates":[77.114285,8.308939],"type":"Point"}
}