{
  "type": "Feature",
  "properties": {
    "iso:country":"IN",
    "ks:ks_name":"Gome",
    "ks:ks_pop":244,
    "ks:ks_type":"HABITATION",
    "name:eng_x_preferred":[
        "Gome"
    ],
    "wof:name":"Gome",
    "wof:placetype":"locality",
    "wof:population":244
},
  "geometry": {"coordinates":[81.059657,19.34594],"type":"Point"}
}