{
  "type": "Feature",
  "properties": {
    "iso:country":"IN",
    "ks:ks_name":"Monadih",
    "ks:ks_pop":126,
    "ks:ks_type":"VILLAGE",
    "name:eng_x_preferred":[
        "Monadih"
    ],
    "wof:name":"Monadih",
    "wof:placetype":"locality",
    "wof:population":126
},
  "geometry": {"coordinates":[87.39271599999999,24.684644],"type":"Point"}
}