{
  "type": "Feature",
  "properties": {
    "iso:country":"IN",
    "ks:ks_name":"Harijanwadi",
    "ks:ks_pop":113,
    "ks:ks_type":"HABITATION",
    "ks:ks_uagg_main":0,
    "name:eng_x_preferred":[
        "Harijanwadi"
    ],
    "wof:name":"Harijanwadi",
    "wof:placetype":"neighbourhood",
    "wof:population":113
},
  "geometry": {"coordinates":[73.759711,16.1117],"type":"Point"}
}