{
  "type": "Feature",
  "properties": {
    "gn:admin1_code":"16.0",
    "gn:admin2_code":"505.0",
    "gn:asciiname":"Bopapur",
    "gn:country_code":"IN",
    "gn:dem":499,
    "gn:feature_class":"P",
    "gn:feature_code":"PPL",
    "gn:name":"Bop\u0101pur",
    "gn:population":0,
    "gn:timezone":"Asia/Kolkata",
    "iso:country":"IN",
    "ks:ks_alt_nam":"Bop\u0101pur",
    "ks:ks_name":"Bopapur",
    "ks:ks_pop":30,
    "ks:ks_type":"VILLAGE",
    "name:eng_x_preferred":[
        "Bopapur"
    ],
    "name:eng_x_variant":[
        "Bop\u0101pur"
    ],
    "wof:name":"Bopapur",
    "wof:placetype":"locality",
    "wof:population":30
},
  "geometry": {"coordinates":[78.63185900000001,21.078434],"type":"Point"}
}