{
  "type": "Feature",
  "properties": {
    "gn:admin1_code":"2.0",
    "gn:admin2_code":"544.0",
    "gn:asciiname":"Serbaram",
    "gn:country_code":"IN",
    "gn:dem":715,
    "gn:feature_class":"P",
    "gn:feature_code":"PPL",
    "gn:name":"Serbaram",
    "gn:population":0,
    "gn:timezone":"Asia/Kolkata",
    "iso:country":"IN",
    "wof:name":"Serbaram",
    "wof:placetype":"locality"
},
  "geometry": {"coordinates":[82.36294000000002,18.08617000000001],"type":"Point"}
}