{
  "type": "Feature",
  "properties": {
    "iso:country":"IN",
    "ks:ks_name":"Kataki Bari",
    "ks:ks_pop":1555,
    "ks:ks_type":"VILLAGE",
    "ks:ks_uagg_main":0,
    "name:eng_x_preferred":[
        "Kataki Bari"
    ],
    "wof:name":"Kataki Bari",
    "wof:placetype":"neighbourhood",
    "wof:population":1555
},
  "geometry": {"coordinates":[94.67032,26.896938],"type":"Point"}
}