{
  "type": "Feature",
  "properties": {
    "iso:country":"IN",
    "ks:ks_alt_nam":"JAIPRAKASH NAGAR",
    "ks:ks_name":"Jaiprakash Nagar",
    "ks:ks_pop":731,
    "ks:ks_type":"HABITATION",
    "name:eng_x_preferred":[
        "Jaiprakash Nagar"
    ],
    "wof:name":"Jaiprakash Nagar",
    "wof:placetype":"locality",
    "wof:population":731
},
  "geometry": {"coordinates":[85.45763599999999,24.868089],"type":"Point"}
}