{
  "type": "Feature",
  "properties": {
    "gn:admin1_code":"34.0",
    "gn:admin2_code":"224.0",
    "gn:asciiname":"Bhanpur",
    "gn:country_code":"IN",
    "gn:dem":41,
    "gn:feature_class":"P",
    "gn:feature_code":"PPL",
    "gn:name":"Bh\u0101npur",
    "gn:population":0,
    "gn:timezone":"Asia/Kolkata",
    "iso:country":"IN",
    "wof:name":"Bhanpur",
    "wof:placetype":"locality"
},
  "geometry": {"coordinates":[86.99923000000003,25.42622],"type":"Point"}
}