{
  "type": "Feature",
  "properties": {
    "gn:admin1_code":"39.0",
    "gn:admin2_code":"64.0",
    "gn:asciiname":"Danda Koliyan",
    "gn:country_code":"IN",
    "gn:dem":1700,
    "gn:feature_class":"P",
    "gn:feature_code":"PPL",
    "gn:name":"D\u0101nda Koliyan",
    "gn:population":0,
    "gn:timezone":"Asia/Kolkata",
    "iso:country":"IN",
    "wof:name":"Danda Koliyan",
    "wof:placetype":"locality"
},
  "geometry": {"coordinates":[79.15777,29.72996],"type":"Point"}
}