{
  "type": "Feature",
  "properties": {
    "gn:admin1_code":"21.0",
    "gn:admin2_code":"396",
    "gn:asciiname":"Komatlapeta",
    "gn:country_code":"IN",
    "gn:dem":232,
    "gn:feature_class":"P",
    "gn:feature_code":"PPL",
    "gn:name":"Komatlapeta",
    "gn:population":0,
    "gn:timezone":"Asia/Kolkata",
    "iso:country":"IN",
    "wof:name":"Komatlapeta",
    "wof:placetype":"locality"
},
  "geometry": {"coordinates":[83.42361,19.23782000000001],"type":"Point"}
}