{
  "type": "Feature",
  "properties": {
    "iso:country":"IN",
    "ks:ks_name":"Bargoor",
    "ks:ks_pop":28,
    "ks:ks_type":"HABITATION",
    "name:eng_x_preferred":[
        "Bargoor"
    ],
    "wof:name":"Bargoor",
    "wof:placetype":"locality",
    "wof:population":28
},
  "geometry": {"coordinates":[76.99914200000001,11.452423],"type":"Point"}
}