{
  "type": "Feature",
  "properties": {
    "gn:admin1_code":"36",
    "gn:admin2_code":"132.0",
    "gn:asciiname":"Chak Dewali",
    "gn:country_code":"IN",
    "gn:dem":281,
    "gn:feature_class":"P",
    "gn:feature_code":"PPL",
    "gn:name":"Chak Dew\u0101li",
    "gn:population":0,
    "gn:timezone":"Asia/Kolkata",
    "iso:country":"IN",
    "ks:ks_alt_nam":"Chak Dew\u0101li",
    "ks:ks_name":"Chak Dewali",
    "ks:ks_type":"VILLAGE",
    "ks:ks_uagg_main":0,
    "name:eng_x_preferred":[
        "Chak Dewali"
    ],
    "name:eng_x_variant":[
        "Chak Dew\u0101li"
    ],
    "wof:name":"Chak Dewali",
    "wof:placetype":"locality"
},
  "geometry": {"coordinates":[77.568427,30.00777],"type":"Point"}
}