{
  "type": "Feature",
  "properties": {
    "gn:admin1_code":"11",
    "gn:admin2_code":"30.0",
    "gn:asciiname":"Mohlaer",
    "gn:country_code":"IN",
    "gn:dem":1497,
    "gn:feature_class":"P",
    "gn:feature_code":"PPL",
    "gn:name":"Mohl\u00e4r",
    "gn:population":0,
    "gn:timezone":"Asia/Kolkata",
    "iso:country":"IN",
    "wof:name":"Mohlaer",
    "wof:placetype":"locality"
},
  "geometry": {"coordinates":[76.88459,31.32223],"type":"Point"}
}