{
  "type": "Feature",
  "properties": {
    "gn:admin1_code":"19.0",
    "gn:admin2_code":"584.0",
    "gn:asciiname":"Iralpodu",
    "gn:country_code":"IN",
    "gn:dem":622,
    "gn:feature_class":"P",
    "gn:feature_code":"PPL",
    "gn:name":"Iralpodu",
    "gn:population":0,
    "gn:timezone":"Asia/Kolkata",
    "iso:country":"IN",
    "wof:name":"Iralpodu",
    "wof:placetype":"locality"
},
  "geometry": {"coordinates":[77.53383000000002,12.35689],"type":"Point"}
}