{
  "type": "Feature",
  "properties": {
    "gn:admin1_code":"35.0",
    "gn:admin2_code":"440.0",
    "gn:asciiname":"Raigarh",
    "gn:country_code":"IN",
    "gn:dem":203,
    "gn:feature_class":"P",
    "gn:feature_code":"PPL",
    "gn:name":"R\u0101igarh",
    "gn:population":0,
    "gn:timezone":"Asia/Kolkata",
    "iso:country":"IN",
    "name:ara_x_preferred":[
        "\u0631\u0627\u064a\u062c\u0627\u0631\u0647"
    ],
    "name:ben_bn_x_preferred":[
        "\u09b0\u09be\u099c\u0997\u09dc"
    ],
    "name:ben_in_x_preferred":[
        "\u09b0\u09be\u099c\u0997\u09dc"
    ],
    "name:ben_x_preferred":[
        "\u09b0\u09be\u09af\u09bc\u0997\u09a1\u09bc"
    ],
    "name:bih_x_preferred":[
        "\u0930\u093e\u092f\u0917\u0922\u093c"
    ],
    "name:bpy_x_preferred":[
        "\u09b0\u09be\u09af\u09bc\u0997\u09a1\u09bc"
    ],
    "name:cat_x_preferred":[
        "Raigarh"
    ],
    "name:ceb_x_preferred":[
        "Raigarh"
    ],
    "name:deu_x_preferred":[
        "Raigarh"
    ],
    "name:fra_x_preferred":[
        "Raig\u00e2rh"
    ],
    "name:guj_x_preferred":[
        "\u0ab0\u0abe\u0aaf\u0a97\u0aa2"
    ],
    "name:hin_x_preferred":[
        "\u0930\u093e\u092f\u0917\u0922\u093c"
    ],
    "name:hin_x_variant":[
        "\u0930\u093e\u092f\u0917\u095d"
    ],
    "name:ita_x_preferred":[
        "Raigarh"
    ],
    "name:kan_x_preferred":[
        "\u0cb0\u0cbe\u0caf\u0c97\u0ca1"
    ],
    "name:mal_x_preferred":[
        "\u0d31\u0d3e\u0d2f\u0d4d\u0d17\u0d21\u0d4d"
    ],
    "name:mar_x_preferred":[
        "\u0930\u093e\u092f\u0917\u0921"
    ],
    "name:mar_x_variant":[
        "\u0930\u093e\u092f\u0917\u0922",
        "\u0930\u093e\u092f\u0917\u095d"
    ],
    "name:mlg_x_preferred":[
        "Raigarh"
    ],
    "name:msa_x_preferred":[
        "Raigarh"
    ],
    "name:ori_x_preferred":[
        "\u0b30\u0b3e\u0b5f\u0b17\u0b22"
    ],
    "name:pam_x_preferred":[
        "Raigarh"
    ],
    "name:pan_x_preferred":[
        "\u0a30\u0a3e\u0a07\u0a17\u0a5c\u0a4d\u0a39"
    ],
    "name:pol_x_preferred":[
        "Rajgarh"
    ],
    "name:rus_x_preferred":[
        "\u0420\u0430\u0439\u0433\u0430\u0440\u0445"
    ],
    "name:san_x_preferred":[
        "\u0930\u093e\u092f\u0917\u0922"
    ],
    "name:spa_x_preferred":[
        "Raigarh"
    ],
    "name:swe_x_preferred":[
        "Raigarh"
    ],
    "name:tam_x_preferred":[
        "\u0bb0\u0bbe\u0baf\u0bcd\u0b95\u0bb0\u0bcd"
    ],
    "name:tel_x_preferred":[
        "\u0c30\u0c3e\u0c2f\u0c4d"
    ],
    "name:tgl_x_preferred":[
        "Raigarh"
    ],
    "name:urd_x_preferred":[
        "\u0631\u0627\u062c\u06af\u06cc\u0631"
    ],
    "name:urd_x_variant":[
        "\u0631\u0627\u0626\u06d2 \u06af\u0691\u06be"
    ],
    "name:vie_x_preferred":[
        "Raigarh"
    ],
    "name:war_x_preferred":[
        "Raigarh"
    ],
    "name:zho_x_preferred":[
        "\u8d56\u52a0\u5c14"
    ],
    "wof:name":"Raigarh",
    "wof:placetype":"neighbourhood"
},
  "geometry": {"coordinates":[76.01645000000001,22.13167],"type":"Point"}
}