{
  "type": "Feature",
  "properties": {
    "iso:country":"IN",
    "ks:ks_name":"Chanduria",
    "ks:ks_pop":11040,
    "ks:ks_type":"URBAN",
    "ks:ks_uagg_main":0,
    "name:eng_x_preferred":[
        "Chanduria"
    ],
    "wof:name":"Chanduria",
    "wof:placetype":"locality",
    "wof:population":11040
},
  "geometry": {"coordinates":[88.50619500000001,23.045661],"type":"Point"}
}