{
  "type": "Feature",
  "properties": {
    "iso:country":"IN",
    "ks:ks_name":"Uddole",
    "ks:ks_pop":186,
    "ks:ks_type":"HABITATION",
    "name:eng_x_preferred":[
        "Uddole"
    ],
    "wof:name":"Uddole",
    "wof:placetype":"locality",
    "wof:population":186
},
  "geometry": {"coordinates":[75.203508,12.837877],"type":"Point"}
}