{
  "type": "Feature",
  "properties": {
    "iso:country":"IN",
    "ks:ks_alt_nam":"MADHYA KHATTIMARI KHALBARI",
    "ks:ks_name":"Madhya Khattimari Khalbari",
    "ks:ks_pop":1205,
    "ks:ks_type":"HABITATION",
    "name:eng_x_preferred":[
        "Madhya Khattimari Khalbari"
    ],
    "wof:name":"Madhya Khattimari Khalbari",
    "wof:placetype":"locality",
    "wof:population":1205
},
  "geometry": {"coordinates":[88.968703,26.682075],"type":"Point"}
}