{
  "type": "Feature",
  "properties": {
    "iso:country":"IN",
    "ks:ks_alt_nam":"DUSADH TOLA",
    "ks:ks_name":"Dusadh Tola",
    "ks:ks_pop":189,
    "ks:ks_type":"HABITATION",
    "ks:ks_uagg_main":0,
    "name:eng_x_preferred":[
        "Dusadh Tola"
    ],
    "wof:name":"Dusadh Tola",
    "wof:placetype":"neighbourhood",
    "wof:population":189
},
  "geometry": {"coordinates":[84.682625,26.400086],"type":"Point"}
}