{
  "type": "Feature",
  "properties": {
    "iso:country":"IN",
    "ks:ks_alt_nam":"MANE WASTI",
    "ks:ks_name":"Mane Wasti",
    "ks:ks_pop":75,
    "ks:ks_type":"HABITATION",
    "name:eng_x_preferred":[
        "Mane Wasti"
    ],
    "wof:name":"Mane Wasti",
    "wof:placetype":"locality",
    "wof:population":75
},
  "geometry": {"coordinates":[75.217056,17.013724],"type":"Point"}
}