{
  "type": "Feature",
  "properties": {
    "gn:admin1_code":"39.0",
    "gn:admin2_code":"66.0",
    "gn:asciiname":"Pokhria Thok",
    "gn:country_code":"IN",
    "gn:dem":1364,
    "gn:feature_class":"P",
    "gn:feature_code":"PPL",
    "gn:name":"Pokhr\u012ba Thok",
    "gn:population":0,
    "gn:timezone":"Asia/Kolkata",
    "iso:country":"IN",
    "wof:name":"Pokhria Thok",
    "wof:placetype":"locality"
},
  "geometry": {"coordinates":[79.48419,29.30413],"type":"Point"}
}