{
  "type": "Feature",
  "properties": {
    "gn:admin1_code":"21.0",
    "gn:admin2_code":"398.0",
    "gn:asciiname":"Rangupani",
    "gn:country_code":"IN",
    "gn:dem":872,
    "gn:feature_class":"P",
    "gn:feature_code":"PPL",
    "gn:name":"Rangup\u0101ni",
    "gn:population":0,
    "gn:timezone":"Asia/Kolkata",
    "iso:country":"IN",
    "ks:ks_name":"Rangapani",
    "ks:ks_pop":228,
    "ks:ks_type":"VILLAGE",
    "name:eng_x_preferred":[
        "Rangapani"
    ],
    "name:eng_x_variant":[
        "Rangupani"
    ],
    "wof:name":"Rangapani",
    "wof:placetype":"locality",
    "wof:population":228
},
  "geometry": {"coordinates":[83.052211,18.868174],"type":"Point"}
}