{
  "type": "Feature",
  "properties": {
    "iso:country":"IN",
    "ks:ks_name":"Bairuguda",
    "ks:ks_pop":58,
    "ks:ks_type":"HABITATION",
    "name:eng_x_preferred":[
        "Bairuguda"
    ],
    "wof:name":"Bairuguda",
    "wof:placetype":"locality",
    "wof:population":58
},
  "geometry": {"coordinates":[82.835165,18.237469],"type":"Point"}
}