{
  "type": "Feature",
  "properties": {
    "gn:admin1_code":"35",
    "gn:admin2_code":"445.0",
    "gn:asciiname":"Salikhera",
    "gn:country_code":"IN",
    "gn:dem":457,
    "gn:feature_class":"P",
    "gn:feature_code":"PPL",
    "gn:name":"S\u0101likhera",
    "gn:population":0,
    "gn:timezone":"Asia/Kolkata",
    "iso:country":"IN",
    "ks:ks_name":"Sali Kheda",
    "ks:ks_pop":79,
    "ks:ks_type":"VILLAGE",
    "name:eng_x_preferred":[
        "Sali Kheda"
    ],
    "name:eng_x_variant":[
        "Salikhera"
    ],
    "wof:name":"Sali Kheda",
    "wof:placetype":"locality",
    "wof:population":79
},
  "geometry": {"coordinates":[77.291849,22.96799],"type":"Point"}
}