{
  "type": "Feature",
  "properties": {
    "iso:country":"IN",
    "ks:ks_name":"Bhoerpada",
    "ks:ks_pop":125,
    "ks:ks_type":"HABITATION",
    "name:eng_x_preferred":[
        "Bhoerpada"
    ],
    "wof:name":"Bhoerpada",
    "wof:placetype":"locality",
    "wof:population":125
},
  "geometry": {"coordinates":[72.868334,19.900023],"type":"Point"}
}