{
  "type": "Feature",
  "properties": {
    "gn:admin1_code":"24",
    "gn:admin2_code":"102.0",
    "gn:asciiname":"Lohsana Bara",
    "gn:country_code":"IN",
    "gn:dem":267,
    "gn:feature_class":"P",
    "gn:feature_code":"PPL",
    "gn:name":"Lohsana Bara",
    "gn:population":0,
    "gn:timezone":"Asia/Kolkata",
    "iso:country":"IN",
    "name:und_x_variant":[
        "Lohsna",
        "Lohsana Bara"
    ],
    "wof:name":"Lohsana Bara",
    "wof:placetype":"locality"
},
  "geometry": {"coordinates":[75.19145999999998,28.42824],"type":"Point"}
}