{
  "type": "Feature",
  "properties": {
    "gn:admin1_code":"13.0",
    "gn:admin2_code":"589.0",
    "gn:asciiname":"Elayavur",
    "gn:country_code":"IN",
    "gn:dem":32,
    "gn:feature_class":"P",
    "gn:feature_code":"PPL",
    "gn:name":"Elayavur",
    "gn:population":0,
    "gn:timezone":"Asia/Kolkata",
    "iso:country":"IN",
    "ks:ks_name":"Elayavoor",
    "ks:ks_pop":31537,
    "ks:ks_type":"VILLAGE",
    "name:eng_x_preferred":[
        "Elayavoor"
    ],
    "name:eng_x_variant":[
        "Elayavur"
    ],
    "wof:name":"Elayavoor",
    "wof:placetype":"locality",
    "wof:population":31537
},
  "geometry": {"coordinates":[75.405344,11.880381],"type":"Point"}
}