{
  "type": "Feature",
  "properties": {
    "iso:country":"IN",
    "ks:ks_name":"Kothapalle Mala Palli",
    "ks:ks_pop":11,
    "ks:ks_type":"HABITATION",
    "name:eng_x_preferred":[
        "Kothapalle Mala Palli"
    ],
    "wof:name":"Kothapalle Mala Palli",
    "wof:placetype":"locality",
    "wof:population":11
},
  "geometry": {"coordinates":[78.97966700000001,13.962712],"type":"Point"}
}