{
  "type": "Feature",
  "properties": {
    "iso:country":"IN",
    "ks:ks_name":"Narabari No 2",
    "ks:ks_pop":150,
    "ks:ks_type":"HABITATION",
    "name:eng_x_preferred":[
        "Narabari No 2"
    ],
    "wof:name":"Narabari No 2",
    "wof:placetype":"locality",
    "wof:population":150
},
  "geometry": {"coordinates":[90.136987,26.563288],"type":"Point"}
}