{
  "type": "Feature",
  "properties": {
    "iso:country":"IN",
    "ks:ks_name":"Bhaidel",
    "ks:ks_pop":280,
    "ks:ks_type":"HABITATION",
    "name:eng_x_preferred":[
        "Bhaidel"
    ],
    "wof:name":"Bhaidel",
    "wof:placetype":"locality",
    "wof:population":280
},
  "geometry": {"coordinates":[72.869056,22.837611],"type":"Point"}
}