{
  "type": "Feature",
  "properties": {
    "iso:country":"IN",
    "ks:ks_name":"Nemmale E W",
    "ks:ks_pop":1633,
    "ks:ks_type":"HABITATION",
    "name:eng_x_preferred":[
        "Nemmale E W"
    ],
    "wof:name":"Nemmale E W",
    "wof:placetype":"locality",
    "wof:population":1633
},
  "geometry": {"coordinates":[75.971491,12.021446],"type":"Point"}
}