{
  "type": "Feature",
  "properties": {
    "iso:country":"IN",
    "ks:ks_name":"Daboli",
    "ks:ks_pop":187,
    "ks:ks_type":"VILLAGE",
    "name:eng_x_preferred":[
        "Daboli"
    ],
    "wof:name":"Daboli",
    "wof:placetype":"locality",
    "wof:population":187
},
  "geometry": {"coordinates":[78.533008,29.932413],"type":"Point"}
}