{
  "type": "Feature",
  "properties": {
    "gn:admin1_code":"10.0",
    "gn:admin2_code":"082",
    "gn:asciiname":"Bhalaut",
    "gn:country_code":"IN",
    "gn:dem":225,
    "gn:feature_class":"P",
    "gn:feature_code":"PPL",
    "gn:name":"Bh\u0101laut",
    "gn:population":0,
    "gn:timezone":"Asia/Kolkata",
    "iso:country":"IN",
    "wof:name":"Bhalaut",
    "wof:placetype":"locality"
},
  "geometry": {"coordinates":[76.70588000000002,28.90447],"type":"Point"}
}