{
  "type": "Feature",
  "properties": {
    "iso:country":"IN",
    "ks:ks_alt_nam":"MAN CHARAN PARA",
    "ks:ks_name":"Man Charan Para",
    "ks:ks_pop":863,
    "ks:ks_type":"HABITATION",
    "name:eng_x_preferred":[
        "Man Charan Para"
    ],
    "wof:name":"Man Charan Para",
    "wof:placetype":"locality",
    "wof:population":863
},
  "geometry": {"coordinates":[91.35890999999999,23.762133],"type":"Point"}
}