{
  "type": "Feature",
  "properties": {
    "iso:country":"IN",
    "ks:ks_name":"Jugania Ati",
    "ks:ks_pop":512,
    "ks:ks_type":"VILLAGE",
    "name:eng_x_preferred":[
        "Jugania Ati"
    ],
    "wof:name":"Jugania Ati",
    "wof:placetype":"locality",
    "wof:population":512
},
  "geometry": {"coordinates":[93.651602,26.675707],"type":"Point"}
}