{
  "type": "Feature",
  "properties": {
    "iso:country":"IN",
    "ks:ks_name":"Pernadka",
    "ks:ks_pop":134,
    "ks:ks_type":"HABITATION",
    "name:eng_x_preferred":[
        "Pernadka"
    ],
    "wof:name":"Pernadka",
    "wof:placetype":"locality",
    "wof:population":134
},
  "geometry": {"coordinates":[75.15559,12.692411],"type":"Point"}
}