{
  "type": "Feature",
  "properties": {
    "gn:admin1_code":"28.0",
    "gn:admin2_code":"338",
    "gn:asciiname":"Devanandapur",
    "gn:cc2":"IN",
    "gn:country_code":"IN",
    "gn:dem":15,
    "gn:feature_class":"P",
    "gn:feature_code":"PPL",
    "gn:name":"Devanandapur",
    "gn:population":0,
    "gn:timezone":"Asia/Kolkata",
    "iso:country":"IN",
    "ks:ks_name":"Debanandapur",
    "ks:ks_pop":2633,
    "ks:ks_type":"VILLAGE",
    "ks:ks_uagg_main":0,
    "name:eng_x_preferred":[
        "Debanandapur"
    ],
    "name:und_x_variant":[
        "Dabnundpoor",
        "Debanandapur",
        "Devanandapur"
    ],
    "wof:name":"Debanandapur",
    "wof:placetype":"locality",
    "wof:population":2633
},
  "geometry": {"coordinates":[88.368943,22.935567],"type":"Point"}
}