{
  "type": "Feature",
  "properties": {
    "iso:country":"IN",
    "ks:ks_name":"Shiwara",
    "ks:ks_pop":440,
    "ks:ks_type":"HABITATION",
    "name:eng_x_preferred":[
        "Shiwara"
    ],
    "wof:name":"Shiwara",
    "wof:placetype":"locality",
    "wof:population":440
},
  "geometry": {"coordinates":[78.46296700000001,20.404468],"type":"Point"}
}