{
  "type": "Feature",
  "properties": {
    "gn:admin1_code":"36",
    "gn:admin2_code":"158.0",
    "gn:asciiname":"Ashrafabad",
    "gn:country_code":"IN",
    "gn:dem":116,
    "gn:feature_class":"P",
    "gn:feature_code":"PPL",
    "gn:name":"Ashraf\u0101b\u0101d",
    "gn:population":0,
    "gn:timezone":"Asia/Kolkata",
    "iso:country":"IN",
    "name:fas_x_preferred":[
        "\u0627\u0634\u0631\u0641\u200c\u0622\u0628\u0627\u062f"
    ],
    "wof:name":"Ashrafabad",
    "wof:placetype":"locality"
},
  "geometry": {"coordinates":[81.4911,26.53148],"type":"Point"}
}