{
  "type": "Feature",
  "properties": {
    "gn:admin1_code":"28.0",
    "gn:admin2_code":"333.0",
    "gn:asciiname":"Bahutal",
    "gn:country_code":"IN",
    "gn:dem":30,
    "gn:feature_class":"P",
    "gn:feature_code":"PPL",
    "gn:name":"Bahut\u0101l",
    "gn:population":0,
    "gn:timezone":"Asia/Kolkata",
    "iso:country":"IN",
    "wof:name":"Bahutal",
    "wof:placetype":"neighbourhood"
},
  "geometry": {"coordinates":[87.9027,24.55723],"type":"Point"}
}