{
  "type": "Feature",
  "properties": {
    "iso:country":"IN",
    "ks:ks_alt_nam":"Er\u0101ndip\u0101thar",
    "ks:ks_name":"Erandipathar",
    "ks:ks_type":"VILLAGE",
    "name:eng_x_preferred":[
        "Erandipathar"
    ],
    "name:eng_x_variant":[
        "Er\u0101ndip\u0101thar"
    ],
    "wof:name":"Erandipathar",
    "wof:placetype":"locality"
},
  "geometry": {"coordinates":[85.038155,20.389382],"type":"Point"}
}