{
  "type": "Feature",
  "properties": {
    "iso:country":"IN",
    "ks:ks_name":"Vachali Muvadi",
    "ks:ks_pop":330,
    "ks:ks_type":"HABITATION",
    "name:eng_x_preferred":[
        "Vachali Muvadi"
    ],
    "wof:name":"Vachali Muvadi",
    "wof:placetype":"locality",
    "wof:population":330
},
  "geometry": {"coordinates":[72.950861,23.084667],"type":"Point"}
}