{
  "type": "Feature",
  "properties": {
    "iso:country":"IN",
    "ks:ks_alt_nam":"103 RDL",
    "ks:ks_name":"103 Rdl",
    "ks:ks_pop":240,
    "ks:ks_type":"HABITATION",
    "name:eng_x_preferred":[
        "103 Rdl"
    ],
    "wof:name":"103 Rdl",
    "wof:placetype":"locality",
    "wof:population":240
},
  "geometry": {"coordinates":[73.903649,29.170724],"type":"Point"}
}