{
  "type": "Feature",
  "properties": {
    "gn:admin1_code":"21.0",
    "gn:admin2_code":"398.0",
    "gn:asciiname":"Ponjelu",
    "gn:country_code":"IN",
    "gn:dem":906,
    "gn:feature_class":"P",
    "gn:feature_code":"PPL",
    "gn:name":"Ponjelu",
    "gn:population":0,
    "gn:timezone":"Asia/Kolkata",
    "iso:country":"IN",
    "wof:name":"Ponjelu",
    "wof:placetype":"locality"
},
  "geometry": {"coordinates":[82.67267,18.63731],"type":"Point"}
}