{
  "type": "Feature",
  "properties": {
    "gn:admin1_code":"2.0",
    "gn:asciiname":"Murchikona",
    "gn:country_code":"IN",
    "gn:dem":721,
    "gn:feature_class":"P",
    "gn:feature_code":"PPL",
    "gn:name":"Murchikona",
    "gn:population":0,
    "gn:timezone":"Asia/Kolkata",
    "iso:country":"IN",
    "wof:name":"Murchikona",
    "wof:placetype":"locality"
},
  "geometry": {"coordinates":[83.60061999999998,19.1035],"type":"Point"}
}