{
  "type": "Feature",
  "properties": {
    "gn:admin1_code":"11",
    "gn:admin2_code":"33.0",
    "gn:asciiname":"Paienighat",
    "gn:country_code":"IN",
    "gn:dem":1998,
    "gn:feature_class":"P",
    "gn:feature_code":"PPL",
    "gn:name":"Paien\u012bgh\u0101t",
    "gn:population":0,
    "gn:timezone":"Asia/Kolkata",
    "iso:country":"IN",
    "wof:name":"Paienighat",
    "wof:placetype":"locality"
},
  "geometry": {"coordinates":[77.176,31.18625],"type":"Point"}
}