{
  "type": "Feature",
  "properties": {
    "gn:admin1_code":"40",
    "gn:admin2_code":"532.0",
    "gn:asciiname":"Bijjur",
    "gn:country_code":"IN",
    "gn:dem":361,
    "gn:feature_class":"P",
    "gn:feature_code":"PPL",
    "gn:name":"Bijjur",
    "gn:population":0,
    "gn:timezone":"Asia/Kolkata",
    "iso:country":"IN",
    "name:vie_x_preferred":[
        "Bijjur"
    ],
    "wof:name":"Bijjur",
    "wof:placetype":"locality"
},
  "geometry": {"coordinates":[78.01094000000001,19.13738],"type":"Point"}
}