{
  "type": "Feature",
  "properties": {
    "iso:country":"IN",
    "name:ara_x_preferred":[
        "\u0643\u0631\u064a\u0634\u0627\u0646\u0628\u0648\u0631"
    ],
    "name:ben_bn_x_preferred":[
        "\u0995\u09c3\u09b7\u09cd\u09a3\u09aa\u09c1\u09b0"
    ],
    "name:ben_in_x_preferred":[
        "\u0995\u09c3\u09b7\u09cd\u09a3\u09aa\u09c1\u09b0"
    ],
    "name:guj_x_preferred":[
        "\u0a95\u0acd\u0ab0\u0abf\u0ab7\u0acd\u0aa8\u0abe\u0aaa\u0ac1\u0ab0"
    ],
    "name:hin_x_preferred":[
        "\u0915\u093f\u0936\u0928\u092a\u0941\u0930"
    ],
    "name:kan_x_preferred":[
        "\u0c95\u0cc3\u0cb7\u0ccd\u0ca3\u0caa\u0cc1\u0cb0"
    ],
    "name:mal_x_preferred":[
        "\u0d15\u0d43\u0d37\u0d7a\u0d2a\u0d42\u0d7c"
    ],
    "name:mar_x_preferred":[
        "\u0915\u094d\u0930\u093f\u0936\u0928\u092a\u0942\u0930"
    ],
    "name:pan_x_preferred":[
        "\u0a15\u0a30\u0a3f\u0a36\u0a28\u0a2a\u0a41\u0a30"
    ],
    "name:tam_x_preferred":[
        "\u0b95\u0bbf\u0bb0\u0bc1\u0bb7\u0ba9\u0bcd\u0baa\u0bc2\u0bb0\u0bcd"
    ],
    "name:tel_x_preferred":[
        "\u0c15\u0c4d\u0c30\u0c3f\u0c37\u0c28\u0c4d"
    ],
    "name:urd_x_preferred":[
        "\u06a9\u0631\u0634\u0646 \u067e\u0648\u0631"
    ],
    "qs:name":"Krishanpur",
    "qs:name_adm0":"India",
    "qs:name_adm1":"West Bengal",
    "qs:photos":21,
    "qs:photos_1k":4,
    "qs:photos_9k":1,
    "qs:photos_9r":1,
    "qs:photos_all":21,
    "qs:photos_sr":1,
    "qs:placetype":"Suburb",
    "qs:pop_sr":"0",
    "wof:name":"Krishanpur",
    "wof:placetype":"neighbourhood"
},
  "geometry": {"coordinates":[88.41366600000001,22.585999],"type":"Point"}
}