{
  "type": "Feature",
  "properties": {
    "iso:country":"IN",
    "qs:name":"Krishanpur",
    "qs:name_adm0":"India",
    "qs:name_adm1":"West Bengal",
    "qs:photos":21,
    "qs:photos_1k":4,
    "qs:photos_9k":1,
    "qs:photos_9r":1,
    "qs:photos_all":21,
    "qs:photos_sr":1,
    "qs:placetype":"Suburb",
    "qs:pop_sr":"0",
    "wof:name":"Krishanpur",
    "wof:placetype":"neighbourhood"
},
  "geometry": {"coordinates":[88.41366600000001,22.585999],"type":"Point"}
}