{
  "type": "Feature",
  "properties": {
    "iso:country":"IN",
    "ks:ks_name":"Gochamundri",
    "ks:ks_pop":14,
    "ks:ks_type":"VILLAGE",
    "name:eng_x_preferred":[
        "Gochamundri"
    ],
    "wof:name":"Gochamundri",
    "wof:placetype":"locality",
    "wof:population":14
},
  "geometry": {"coordinates":[83.885469,20.465617],"type":"Point"}
}