{
  "type": "Feature",
  "properties": {
    "iso:country":"IN",
    "ks:ks_name":"Kundi",
    "ks:ks_pop":703,
    "ks:ks_type":"VILLAGE",
    "ks:ks_uagg_main":0,
    "name:eng_x_preferred":[
        "Kundi"
    ],
    "wof:name":"Kundi",
    "wof:placetype":"neighbourhood",
    "wof:population":703
},
  "geometry": {"coordinates":[86.370529,21.216333],"type":"Point"}
}