{
  "type": "Feature",
  "properties": {
    "iso:country":"IN",
    "ks:ks_name":"Endri",
    "ks:ks_pop":149,
    "ks:ks_type":"VILLAGE",
    "name:eng_x_preferred":[
        "Endri"
    ],
    "wof:name":"Endri",
    "wof:placetype":"locality",
    "wof:population":149
},
  "geometry": {"coordinates":[84.247159,18.90572],"type":"Point"}
}