{
  "type": "Feature",
  "properties": {
    "gn:admin1_code":"24",
    "gn:admin2_code":"113.0",
    "gn:asciiname":"Ramrawas Kalan",
    "gn:country_code":"IN",
    "gn:dem":247,
    "gn:feature_class":"P",
    "gn:feature_code":"PPL",
    "gn:name":"R\u0101mr\u0101w\u0101s Kal\u0101n",
    "gn:population":0,
    "gn:timezone":"Asia/Kolkata",
    "iso:country":"IN",
    "name:und_x_variant":[
        "R\u0101mr\u0101w\u0101s",
        "R\u0101mr\u0101w\u0101s Kal\u0101n"
    ],
    "wof:name":"Ramrawas Kalan",
    "wof:placetype":"locality"
},
  "geometry": {"coordinates":[73.38871,26.36981],"type":"Point"}
}