{
  "type": "Feature",
  "properties": {
    "iso:country":"IN",
    "ks:ks_name":"Dhobiguda Para",
    "ks:ks_pop":56,
    "ks:ks_type":"HABITATION",
    "name:eng_x_preferred":[
        "Dhobiguda Para"
    ],
    "wof:name":"Dhobiguda Para",
    "wof:placetype":"locality",
    "wof:population":56
},
  "geometry": {"coordinates":[81.96578599999999,19.494738],"type":"Point"}
}