{
  "type": "Feature",
  "properties": {
    "iso:country":"IN",
    "ks:ks_name":"Nichala F",
    "ks:ks_pop":339,
    "ks:ks_type":"HABITATION",
    "ks:ks_uagg_main":0,
    "name:eng_x_preferred":[
        "Nichala F"
    ],
    "wof:name":"Nichala F",
    "wof:placetype":"neighbourhood",
    "wof:population":339
},
  "geometry": {"coordinates":[73.266389,20.615056],"type":"Point"}
}