{
  "type": "Feature",
  "properties": {
    "iso:country":"IN",
    "ks:ks_name":"Mundagar",
    "ks:ks_pop":55,
    "ks:ks_type":"HABITATION",
    "name:eng_x_preferred":[
        "Mundagar"
    ],
    "wof:name":"Mundagar",
    "wof:placetype":"locality",
    "wof:population":55
},
  "geometry": {"coordinates":[74.702037,14.620533],"type":"Point"}
}