{
  "type": "Feature",
  "properties": {
    "gn:admin1_code":"25.0",
    "gn:admin2_code":"611.0",
    "gn:asciiname":"Bombalakambe",
    "gn:country_code":"IN",
    "gn:dem":1545,
    "gn:feature_class":"P",
    "gn:feature_code":"PPL",
    "gn:name":"Bombalakambe",
    "gn:population":0,
    "gn:timezone":"Asia/Kolkata",
    "iso:country":"IN",
    "wof:name":"Bombalakambe",
    "wof:placetype":"locality"
},
  "geometry": {"coordinates":[76.78553000000002,11.30001],"type":"Point"}
}