{
  "type": "Feature",
  "properties": {
    "gn:admin1_code":"39.0",
    "gn:admin2_code":"061",
    "gn:asciiname":"Siraun",
    "gn:country_code":"IN",
    "gn:dem":1277,
    "gn:feature_class":"P",
    "gn:feature_code":"PPL",
    "gn:name":"S\u012braun",
    "gn:population":0,
    "gn:timezone":"Asia/Kolkata",
    "iso:country":"IN",
    "wof:name":"Siraun",
    "wof:placetype":"locality"
},
  "geometry": {"coordinates":[78.73734,29.96031],"type":"Point"}
}