{
  "type": "Feature",
  "properties": {
    "gn:admin1_code":"39.0",
    "gn:admin2_code":"061",
    "gn:asciiname":"Siraun",
    "gn:country_code":"IN",
    "gn:dem":1277,
    "gn:feature_class":"P",
    "gn:feature_code":"PPL",
    "gn:name":"S\u012braun",
    "gn:population":0,
    "gn:timezone":"Asia/Kolkata",
    "iso:country":"IN",
    "ks:ks_alt_nam":"S\u012braun",
    "ks:ks_name":"Siraun",
    "ks:ks_type":"VILLAGE",
    "name:eng_x_preferred":[
        "Siraun"
    ],
    "name:eng_x_variant":[
        "S\u012braun"
    ],
    "wof:name":"Siraun",
    "wof:placetype":"locality"
},
  "geometry": {"coordinates":[78.73733900000001,29.960309],"type":"Point"}
}