{
  "type": "Feature",
  "properties": {
    "gn:admin1_code":"36.0",
    "gn:admin2_code":"150.0",
    "gn:asciiname":"Anandpur",
    "gn:country_code":"IN",
    "gn:dem":164,
    "gn:feature_class":"P",
    "gn:feature_code":"PPL",
    "gn:name":"Anandpur",
    "gn:population":0,
    "gn:timezone":"Asia/Kolkata",
    "iso:country":"IN",
    "ks:ks_name":"Anandpur",
    "ks:ks_pop":203,
    "ks:ks_type":"VILLAGE",
    "ks:ks_uagg_main":0,
    "name:eng_x_preferred":[
        "Anandpur"
    ],
    "wof:name":"Anandpur",
    "wof:placetype":"neighbourhood",
    "wof:population":203
},
  "geometry": {"coordinates":[79.269704,28.249779],"type":"Point"}
}