{
  "type": "Feature",
  "properties": {
    "iso:country":"IN",
    "ks:ks_name":"Siddapurhatti",
    "ks:ks_pop":249,
    "ks:ks_type":"HABITATION",
    "name:eng_x_preferred":[
        "Siddapurhatti"
    ],
    "wof:name":"Siddapurhatti",
    "wof:placetype":"locality",
    "wof:population":249
},
  "geometry": {"coordinates":[74.988079,16.220788],"type":"Point"}
}