{
  "type": "Feature",
  "properties": {
    "gn:admin1_code":"34.0",
    "gn:admin2_code":"235.0",
    "gn:asciiname":"Shivpur",
    "gn:country_code":"IN",
    "gn:dem":172,
    "gn:feature_class":"P",
    "gn:feature_code":"PPL",
    "gn:name":"Shivpur",
    "gn:population":0,
    "gn:timezone":"Asia/Kolkata",
    "iso:country":"IN",
    "ks:ks_alt_nam":"SHIVPUR",
    "ks:ks_name":"Shivpur",
    "ks:ks_pop":291,
    "ks:ks_type":"HABITATION",
    "name:eng_x_preferred":[
        "Shivpur"
    ],
    "wof:name":"Shivpur",
    "wof:placetype":"locality",
    "wof:population":291
},
  "geometry": {"coordinates":[84.10921,24.49572],"type":"Point"}
}