{
  "type": "Feature",
  "properties": {
    "gn:admin1_code":"36.0",
    "gn:admin2_code":"164.0",
    "gn:asciiname":"Alawa Khera",
    "gn:country_code":"IN",
    "gn:dem":127,
    "gn:feature_class":"P",
    "gn:feature_code":"PPL",
    "gn:name":"Al\u0101wa Khera",
    "gn:population":0,
    "gn:timezone":"Asia/Kolkata",
    "iso:country":"IN",
    "wof:name":"Alawa Khera",
    "wof:placetype":"locality"
},
  "geometry": {"coordinates":[80.4106,26.35333],"type":"Point"}
}