{
  "type": "Feature",
  "properties": {
    "gn:admin1_code":"35",
    "gn:admin2_code":"458.0",
    "gn:asciiname":"Kumrai",
    "gn:country_code":"IN",
    "gn:dem":524,
    "gn:feature_class":"P",
    "gn:feature_code":"PPL",
    "gn:name":"Kumr\u0101i",
    "gn:population":0,
    "gn:timezone":"Asia/Kolkata",
    "iso:country":"IN",
    "wof:name":"Kumrai",
    "wof:placetype":"neighbourhood"
},
  "geometry": {"coordinates":[77.36196,24.34963],"type":"Point"}
}