{
  "type": "Feature",
  "properties": {
    "iso:country":"IN",
    "ks:ks_name":"Kalyan Singh Ki Sid",
    "ks:ks_pop":524,
    "ks:ks_type":"VILLAGE",
    "ks:ks_uagg_main":0,
    "name:eng_x_preferred":[
        "Kalyan Singh Ki Sid"
    ],
    "wof:name":"Kalyan Singh Ki Sid",
    "wof:placetype":"neighbourhood",
    "wof:population":524
},
  "geometry": {"coordinates":[72.495858,27.462217],"type":"Point"}
}