{
  "type": "Feature",
  "properties": {
    "iso:country":"IN",
    "ks:ks_name":"Tejalpatti No2",
    "ks:ks_pop":649,
    "ks:ks_type":"HABITATION",
    "ks:ks_uagg_main":0,
    "name:eng_x_preferred":[
        "Tejalpatti No2"
    ],
    "wof:name":"Tejalpatti No2",
    "wof:placetype":"neighbourhood",
    "wof:population":649
},
  "geometry": {"coordinates":[92.987903,26.838734],"type":"Point"}
}