{
  "type": "Feature",
  "properties": {
    "iso:country":"IN",
    "ks:ks_name":"Umarsar",
    "ks:ks_pop":117,
    "ks:ks_type":"VILLAGE",
    "name:eng_x_preferred":[
        "Umarsar"
    ],
    "wof:name":"Umarsar",
    "wof:placetype":"locality",
    "wof:population":117
},
  "geometry": {"coordinates":[68.819315,23.745249],"type":"Point"}
}