{
  "type": "Feature",
  "properties": {
    "gn:admin1_code":"37",
    "gn:admin2_code":"403.0",
    "gn:asciiname":"Kakaimuhan",
    "gn:country_code":"IN",
    "gn:dem":201,
    "gn:feature_class":"P",
    "gn:feature_code":"PPL",
    "gn:name":"Kakaimuh\u0101n",
    "gn:population":0,
    "gn:timezone":"Asia/Kolkata",
    "iso:country":"IN",
    "ks:ks_name":"Kakaimohan",
    "ks:ks_pop":184,
    "ks:ks_type":"HABITATION",
    "name:eng_x_preferred":[
        "Kakaimohan"
    ],
    "name:eng_x_variant":[
        "Kakaimuhan"
    ],
    "wof:name":"Kakaimohan",
    "wof:placetype":"locality",
    "wof:population":184
},
  "geometry": {"coordinates":[83.420269,21.693414],"type":"Point"}
}