{
  "type": "Feature",
  "properties": {
    "gn:admin1_code":"36.0",
    "gn:admin2_code":"158",
    "gn:asciiname":"Khajurgaon",
    "gn:country_code":"IN",
    "gn:dem":115,
    "gn:feature_class":"P",
    "gn:feature_code":"PPL",
    "gn:name":"Khajurg\u0101on",
    "gn:population":0,
    "gn:timezone":"Asia/Kolkata",
    "iso:country":"IN",
    "name:und_x_variant":[
        "Khajurg\u0101on",
        "Khajurgaon"
    ],
    "wof:name":"Khajurgaon",
    "wof:placetype":"locality"
},
  "geometry": {"coordinates":[80.93243000000002,26.07198],"type":"Point"}
}