{
  "type": "Feature",
  "properties": {
    "iso:country":"IN",
    "ks:ks_name":"Lodta Achlawata",
    "ks:ks_pop":1743,
    "ks:ks_type":"HABITATION",
    "name:eng_x_preferred":[
        "Lodta Achlawata"
    ],
    "wof:name":"Lodta Achlawata",
    "wof:placetype":"locality",
    "wof:population":1743
},
  "geometry": {"coordinates":[72.44244399999999,26.719083],"type":"Point"}
}