{
  "type": "Feature",
  "properties": {
    "iso:country":"IN",
    "ks:ks_name":"Jhuntamara",
    "ks:ks_pop":107,
    "ks:ks_type":"VILLAGE",
    "name:eng_x_preferred":[
        "Jhuntamara"
    ],
    "wof:name":"Jhuntamara",
    "wof:placetype":"locality",
    "wof:population":107
},
  "geometry": {"coordinates":[84.90439600000001,20.386137],"type":"Point"}
}