{
  "type": "Feature",
  "properties": {
    "iso:country":"IN",
    "ks:ks_name":"Sukansuti Miri",
    "ks:ks_pop":615,
    "ks:ks_type":"HABITATION",
    "name:eng_x_preferred":[
        "Sukansuti Miri"
    ],
    "wof:name":"Sukansuti Miri",
    "wof:placetype":"locality",
    "wof:population":615
},
  "geometry": {"coordinates":[94.299257,26.96455],"type":"Point"}
}