{
  "type": "Feature",
  "properties": {
    "iso:country":"IN",
    "ks:ks_name":"Gopalpada Para",
    "ks:ks_pop":98,
    "ks:ks_type":"HABITATION",
    "name:eng_x_preferred":[
        "Gopalpada Para"
    ],
    "wof:name":"Gopalpada Para",
    "wof:placetype":"locality",
    "wof:population":98
},
  "geometry": {"coordinates":[91.738935,23.453365],"type":"Point"}
}