{
  "type": "Feature",
  "properties": {
    "iso:country":"IN",
    "ks:ks_name":"Chembakkad",
    "ks:ks_pop":1253,
    "ks:ks_type":"HABITATION",
    "name:eng_x_preferred":[
        "Chembakkad"
    ],
    "wof:name":"Chembakkad",
    "wof:placetype":"locality",
    "wof:population":1253
},
  "geometry": {"coordinates":[75.16847,12.469401],"type":"Point"}
}