{
  "type": "Feature",
  "properties": {
    "gn:admin1_code":"28.0",
    "gn:admin2_code":"328.0",
    "gn:asciiname":"Telipara Choupathi",
    "gn:country_code":"IN",
    "gn:dem":53,
    "gn:feature_class":"P",
    "gn:feature_code":"PPL",
    "gn:name":"Telipara Choupathi",
    "gn:population":0,
    "gn:timezone":"Asia/Kolkata",
    "iso:country":"IN",
    "wof:name":"Telipara Choupathi",
    "wof:placetype":"locality"
},
  "geometry": {"coordinates":[89.76297,26.47616],"type":"Point"}
}