{
  "type": "Feature",
  "properties": {
    "iso:country":"IN",
    "ks:ks_name":"Sainjjogiyana",
    "ks:ks_pop":47,
    "ks:ks_type":"HABITATION",
    "name:eng_x_preferred":[
        "Sainjjogiyana"
    ],
    "wof:name":"Sainjjogiyana",
    "wof:placetype":"locality",
    "wof:population":47
},
  "geometry": {"coordinates":[78.66261900000001,30.171132],"type":"Point"}
}