{
  "type": "Feature",
  "properties": {
    "iso:country":"IN",
    "ks:ks_name":"Khinwali Sara",
    "ks:ks_pop":120,
    "ks:ks_type":"VILLAGE",
    "name:eng_x_preferred":[
        "Khinwali Sara"
    ],
    "wof:name":"Khinwali Sara",
    "wof:placetype":"locality",
    "wof:population":120
},
  "geometry": {"coordinates":[71.84843100000001,25.871706],"type":"Point"}
}