{
  "type": "Feature",
  "properties": {
    "iso:country":"IN",
    "ks:ks_name":"Jorakusumi",
    "ks:ks_pop":11,
    "ks:ks_type":"VILLAGE",
    "name:eng_x_preferred":[
        "Jorakusumi"
    ],
    "wof:name":"Jorakusumi",
    "wof:placetype":"locality",
    "wof:population":11
},
  "geometry": {"coordinates":[87.23019499999999,22.628533],"type":"Point"}
}