{
  "type": "Feature",
  "properties": {
    "iso:country":"IN",
    "ks:ks_name":"Niduniya",
    "ks:ks_pop":130,
    "ks:ks_type":"HABITATION",
    "name:eng_x_preferred":[
        "Niduniya"
    ],
    "wof:name":"Niduniya",
    "wof:placetype":"locality",
    "wof:population":130
},
  "geometry": {"coordinates":[73.31697200000001,20.369806],"type":"Point"}
}