{
  "type": "Feature",
  "properties": {
    "iso:country":"IN",
    "name:ara_x_preferred":[
        "\u0628\u064a\u0644\u0627\u0645\u064a\u062f\u0648"
    ],
    "name:ben_bn_x_preferred":[
        "\u09aa\u09c0\u09b2\u09be\u09ae\u09c7\u09a6\u09c1"
    ],
    "name:ben_in_x_preferred":[
        "\u09aa\u09c0\u09b2\u09be\u09ae\u09c7\u09a6\u09c1"
    ],
    "name:ben_x_preferred":[
        "\u09aa\u09bf\u09b2\u09be\u09ae\u09c7\u09a6\u09c1"
    ],
    "name:ben_x_variant":[
        "\u09aa\u09c0\u09b2\u09ae\u09c7\u09a1\u09bc\u09c1"
    ],
    "name:eng_x_preferred":[
        "Peelamedu"
    ],
    "name:guj_x_preferred":[
        "\u0aaa\u0ac0\u0ab2\u0abe\u0aae\u0ac7\u0aa1\u0ac1"
    ],
    "name:hin_x_preferred":[
        "\u092a\u0940\u0932\u093e\u092e\u0947\u0926\u0942"
    ],
    "name:hin_x_variant":[
        "\u092a\u0940\u0932\u092e\u0947\u0921\u0942"
    ],
    "name:kan_x_preferred":[
        "\u0caa\u0cc0\u0cb2\u0cae\u0cc6\u0ca1\u0cc1"
    ],
    "name:mal_x_preferred":[
        "\u0d2a\u0d40\u0d32\u0d2e\u0d47\u0d21\u0d41"
    ],
    "name:mar_x_preferred":[
        "\u092a\u0947\u0932\u0947\u092e\u0947\u0921\u0942"
    ],
    "name:mar_x_variant":[
        "\u092a\u0940\u0933\u092e\u0947\u0921\u0942"
    ],
    "name:pan_x_preferred":[
        "\u0a2a\u0a40\u0a32\u0a3e\u0a2e\u0a47\u0a21\u0a42"
    ],
    "name:tam_x_preferred":[
        "\u0baa\u0bc0\u0bb3\u0bae\u0bc7\u0b9f\u0bc1"
    ],
    "name:tel_x_preferred":[
        "\u0c2a\u0c40\u0c32\u0c2e\u0c47\u0c21\u0c41"
    ],
    "name:urd_x_preferred":[
        "\u067e\u06cc\u0644\u0627 \u0645\u06cc\u0688\u0648"
    ],
    "qs:name":"Peelamedu",
    "qs:name_adm0":"India",
    "qs:name_adm1":"Tamil Nadu",
    "qs:photos":10,
    "qs:photos_1k":2,
    "qs:photos_9k":1,
    "qs:photos_9r":1,
    "qs:photos_all":10,
    "qs:photos_sr":1,
    "qs:placetype":"Suburb",
    "qs:pop_sr":"0",
    "wd:wordcount":406,
    "wof:name":"Peelamedu",
    "wof:placetype":"neighbourhood"
},
  "geometry": {"coordinates":[76.965665,11.007589],"type":"Point"}
}