{
  "type": "Feature",
  "properties": {
    "iso:country":"IN",
    "qs:name":"Peelamedu",
    "qs:name_adm0":"India",
    "qs:name_adm1":"Tamil Nadu",
    "qs:photos":10,
    "qs:photos_1k":2,
    "qs:photos_9k":1,
    "qs:photos_9r":1,
    "qs:photos_all":10,
    "qs:photos_sr":1,
    "qs:placetype":"Suburb",
    "qs:pop_sr":"0",
    "wd:wordcount":406,
    "wof:name":"Peelamedu",
    "wof:placetype":"neighbourhood"
},
  "geometry": {"coordinates":[76.965665,11.007589],"type":"Point"}
}