{
  "type": "Feature",
  "properties": {
    "iso:country":"IN",
    "name:ben_x_preferred":[
        "\u09aa\u09bf\u09b2\u09be\u09ae\u09c7\u09a6\u09c1"
    ],
    "name:eng_x_preferred":[
        "Peelamedu"
    ],
    "name:hin_x_preferred":[
        "\u092a\u0940\u0932\u092e\u0947\u0921\u0942"
    ],
    "name:mar_x_preferred":[
        "\u092a\u0940\u0933\u092e\u0947\u0921\u0942"
    ],
    "name:tam_x_preferred":[
        "\u0baa\u0bc0\u0bb3\u0bae\u0bc7\u0b9f\u0bc1"
    ],
    "qs:name":"Peelamedu",
    "qs:name_adm0":"India",
    "qs:name_adm1":"Tamil Nadu",
    "qs:photos":10,
    "qs:photos_1k":2,
    "qs:photos_9k":1,
    "qs:photos_9r":1,
    "qs:photos_all":10,
    "qs:photos_sr":1,
    "qs:placetype":"Suburb",
    "qs:pop_sr":"0",
    "wd:wordcount":406,
    "wof:name":"Peelamedu",
    "wof:placetype":"neighbourhood"
},
  "geometry": {"coordinates":[76.965665,11.007589],"type":"Point"}
}