{
  "type": "Feature",
  "properties": {
    "iso:country":"IN",
    "ks:ks_name":"Amjora",
    "ks:ks_pop":259,
    "ks:ks_type":"VILLAGE",
    "ks:ks_uagg_main":0,
    "name:eng_x_preferred":[
        "Amjora"
    ],
    "wof:name":"Amjora",
    "wof:placetype":"neighbourhood",
    "wof:population":259
},
  "geometry": {"coordinates":[86.952353,24.532985],"type":"Point"}
}