{
  "type": "Feature",
  "properties": {
    "iso:country":"IN",
    "ks:ks_name":"Ganganaikanahalli",
    "ks:ks_pop":63,
    "ks:ks_type":"VILLAGE",
    "name:eng_x_preferred":[
        "Ganganaikanahalli"
    ],
    "wof:name":"Ganganaikanahalli",
    "wof:placetype":"locality",
    "wof:population":63
},
  "geometry": {"coordinates":[76.62750699999999,13.522514],"type":"Point"}
}