{
  "type": "Feature",
  "properties": {
    "iso:country":"IN",
    "ks:ks_name":"Hulimundgi",
    "ks:ks_pop":29,
    "ks:ks_type":"HABITATION",
    "name:eng_x_preferred":[
        "Hulimundgi"
    ],
    "wof:name":"Hulimundgi",
    "wof:placetype":"locality",
    "wof:population":29
},
  "geometry": {"coordinates":[74.87812599999999,14.882616],"type":"Point"}
}