{
  "type": "Feature",
  "properties": {
    "gn:admin1_code":"24.0",
    "gn:admin2_code":"110",
    "gn:asciiname":"Khejroli",
    "gn:country_code":"IN",
    "gn:dem":494,
    "gn:feature_class":"P",
    "gn:feature_code":"PPL",
    "gn:name":"Khejroli",
    "gn:population":0,
    "gn:timezone":"Asia/Kolkata",
    "iso:country":"IN",
    "name:und_x_variant":[
        "Khejrauli"
    ],
    "wof:name":"Khejroli",
    "wof:placetype":"locality"
},
  "geometry": {"coordinates":[75.69580000000001,27.33231],"type":"Point"}
}