{
  "type": "Feature",
  "properties": {
    "iso:country":"IN",
    "ks:ks_name":"Sirajpur",
    "ks:ks_pop":760,
    "ks:ks_type":"VILLAGE",
    "ks:ks_uagg_main":0,
    "name:eng_x_preferred":[
        "Sirajpur"
    ],
    "wof:name":"Sirajpur",
    "wof:placetype":"neighbourhood",
    "wof:population":760
},
  "geometry": {"coordinates":[88.884018,22.590213],"type":"Point"}
}