{
  "type": "Feature",
  "properties": {
    "iso:country":"IN",
    "ks:ks_name":"Sarubelbari",
    "ks:ks_pop":256,
    "ks:ks_type":"HABITATION",
    "name:eng_x_preferred":[
        "Sarubelbari"
    ],
    "wof:name":"Sarubelbari",
    "wof:placetype":"locality",
    "wof:population":256
},
  "geometry": {"coordinates":[91.617639,26.585664],"type":"Point"}
}