{
  "type": "Feature",
  "properties": {
    "gn:admin1_code":"36",
    "gn:admin2_code":"185.0",
    "gn:asciiname":"Kuti Baba Gharib Das",
    "gn:country_code":"IN",
    "gn:dem":96,
    "gn:feature_class":"P",
    "gn:feature_code":"PPL",
    "gn:name":"Kuti B\u0101b\u0101 Ghar\u012bb D\u0101s",
    "gn:population":0,
    "gn:timezone":"Asia/Kolkata",
    "iso:country":"IN",
    "wof:name":"Kuti Baba Gharib Das",
    "wof:placetype":"locality"
},
  "geometry": {"coordinates":[82.64068,26.86873],"type":"Point"}
}