{
  "type": "Feature",
  "properties": {
    "iso:country":"IN",
    "ks:ks_name":"Pitambarpur",
    "ks:ks_pop":438,
    "ks:ks_type":"VILLAGE",
    "name:eng_x_preferred":[
        "Pitambarpur"
    ],
    "wof:name":"Pitambarpur",
    "wof:placetype":"locality",
    "wof:population":438
},
  "geometry": {"coordinates":[87.605774,22.054207],"type":"Point"}
}