{
  "type": "Feature",
  "properties": {
    "iso:country":"IN",
    "ks:ks_name":"Sarulachi Suba",
    "ks:ks_pop":200,
    "ks:ks_type":"HABITATION",
    "name:eng_x_preferred":[
        "Sarulachi Suba"
    ],
    "wof:name":"Sarulachi Suba",
    "wof:placetype":"locality",
    "wof:population":200
},
  "geometry": {"coordinates":[91.577799,26.387673],"type":"Point"}
}