{
  "type": "Feature",
  "properties": {
    "iso:country":"IN",
    "ks:ks_name":"Jungle Khorma",
    "ks:ks_pop":12,
    "ks:ks_type":"VILLAGE",
    "name:eng_x_preferred":[
        "Jungle Khorma"
    ],
    "wof:name":"Jungle Khorma",
    "wof:placetype":"locality",
    "wof:population":12
},
  "geometry": {"coordinates":[83.594891,26.50315],"type":"Point"}
}