{
  "type": "Feature",
  "properties": {
    "iso:country":"IN",
    "ks:ks_name":"Nawale Wasti",
    "ks:ks_pop":127,
    "ks:ks_type":"HABITATION",
    "name:eng_x_preferred":[
        "Nawale Wasti"
    ],
    "wof:name":"Nawale Wasti",
    "wof:placetype":"locality",
    "wof:population":127
},
  "geometry": {"coordinates":[75.634916,18.259476],"type":"Point"}
}