{
  "type": "Feature",
  "properties": {
    "iso:country":"IN",
    "ks:ks_name":"Saralikud",
    "ks:ks_pop":259,
    "ks:ks_type":"VILLAGE",
    "name:eng_x_preferred":[
        "Saralikud"
    ],
    "wof:name":"Saralikud",
    "wof:placetype":"locality",
    "wof:population":259
},
  "geometry": {"coordinates":[86.712935,20.305923],"type":"Point"}
}