{
  "type": "Feature",
  "properties": {
    "iso:country":"IN",
    "ks:ks_alt_nam":"Bah\u0101durpur Khurd",
    "ks:ks_name":"Bahadurpur Khurd",
    "ks:ks_type":"VILLAGE",
    "ks:ks_uagg_main":0,
    "name:eng_x_preferred":[
        "Bahadurpur Khurd"
    ],
    "name:eng_x_variant":[
        "Bah\u0101durpur Khurd"
    ],
    "wof:name":"Bahadurpur Khurd",
    "wof:placetype":"neighbourhood"
},
  "geometry": {"coordinates":[83.141497,26.448679],"type":"Point"}
}