{
  "type": "Feature",
  "properties": {
    "gn:admin1_code":"35.0",
    "gn:admin2_code":"457.0",
    "gn:asciiname":"Bothli",
    "gn:country_code":"IN",
    "gn:dem":308,
    "gn:feature_class":"P",
    "gn:feature_code":"PPL",
    "gn:name":"Bothl\u012b",
    "gn:population":0,
    "gn:timezone":"Asia/Kolkata",
    "iso:country":"IN",
    "ks:ks_name":"Bothali",
    "ks:ks_pop":1312,
    "ks:ks_type":"VILLAGE",
    "name:eng_x_preferred":[
        "Bothali"
    ],
    "name:eng_x_variant":[
        "Bothli"
    ],
    "wof:name":"Bothali",
    "wof:placetype":"locality",
    "wof:population":1312
},
  "geometry": {"coordinates":[80.492243,21.415647],"type":"Point"}
}