{
  "type": "Feature",
  "properties": {
    "iso:country":"IN",
    "ks:ks_name":"Singari Bil",
    "ks:ks_pop":98,
    "ks:ks_type":"VILLAGE",
    "name:eng_x_preferred":[
        "Singari Bil"
    ],
    "wof:name":"Singari Bil",
    "wof:placetype":"locality",
    "wof:population":98
},
  "geometry": {"coordinates":[94.601506,27.497421],"type":"Point"}
}