{
  "type": "Feature",
  "properties": {
    "iso:country":"IN",
    "ks:ks_name":"Biswamoni Para",
    "ks:ks_pop":454,
    "ks:ks_type":"HABITATION",
    "name:eng_x_preferred":[
        "Biswamoni Para"
    ],
    "wof:name":"Biswamoni Para",
    "wof:placetype":"locality",
    "wof:population":454
},
  "geometry": {"coordinates":[92.191537,23.737367],"type":"Point"}
}