{
  "type": "Feature",
  "properties": {
    "iso:country":"IN",
    "ks:ks_name":"Vav Faliya",
    "ks:ks_pop":250,
    "ks:ks_type":"HABITATION",
    "name:eng_x_preferred":[
        "Vav Faliya"
    ],
    "wof:name":"Vav Faliya",
    "wof:placetype":"locality",
    "wof:population":250
},
  "geometry": {"coordinates":[74.264528,22.974],"type":"Point"}
}