{
  "type": "Feature",
  "properties": {
    "gn:admin1_code":"12.0",
    "gn:asciiname":"Bandho Kaian",
    "gn:country_code":"IN",
    "gn:dem":903,
    "gn:feature_class":"P",
    "gn:feature_code":"PPL",
    "gn:name":"Bandho Kai\u0101n",
    "gn:population":0,
    "gn:timezone":"Asia/Kolkata",
    "iso:country":"IN",
    "wof:name":"Bandho Kaian",
    "wof:placetype":"locality"
},
  "geometry": {"coordinates":[74.43986,32.9871],"type":"Point"}
}