{
  "type": "Feature",
  "properties": {
    "gn:admin1_code":"36.0",
    "gn:admin2_code":"155.0",
    "gn:asciiname":"Peng",
    "gn:country_code":"IN",
    "gn:dem":150,
    "gn:feature_class":"P",
    "gn:feature_code":"PPL",
    "gn:name":"Peng",
    "gn:population":0,
    "gn:timezone":"Asia/Kolkata",
    "iso:country":"IN",
    "name:deu_x_preferred":[
        "Peng"
    ],
    "name:por_x_preferred":[
        "Peng"
    ],
    "name:swe_x_preferred":[
        "Peng"
    ],
    "wof:name":"Peng",
    "wof:placetype":"locality"
},
  "geometry": {"coordinates":[80.04890999999998,27.31965],"type":"Point"}
}