{
  "type": "Feature",
  "properties": {
    "iso:country":"IN",
    "ks:ks_alt_nam":"Rangoyi UI",
    "ks:ks_name":"Rangoyi Ui",
    "ks:ks_pop":61,
    "ks:ks_type":"HABITATION",
    "name:eng_x_preferred":[
        "Rangoyi Ui"
    ],
    "wof:name":"Rangoyi Ui",
    "wof:placetype":"locality",
    "wof:population":61
},
  "geometry": {"coordinates":[84.526878,19.03168],"type":"Point"}
}