{
  "type": "Feature",
  "properties": {
    "iso:country":"IN",
    "ks:ks_name":"Taddalase",
    "ks:ks_pop":20,
    "ks:ks_type":"HABITATION",
    "name:eng_x_preferred":[
        "Taddalase"
    ],
    "wof:name":"Taddalase",
    "wof:placetype":"locality",
    "wof:population":20
},
  "geometry": {"coordinates":[74.72606399999999,14.812677],"type":"Point"}
}