{
  "type": "Feature",
  "properties": {
    "iso:country":"IN",
    "ks:ks_name":"Badia Para",
    "ks:ks_pop":45,
    "ks:ks_type":"HABITATION",
    "name:eng_x_preferred":[
        "Badia Para"
    ],
    "wof:name":"Badia Para",
    "wof:placetype":"locality",
    "wof:population":45
},
  "geometry": {"coordinates":[91.44378500000001,23.772546],"type":"Point"}
}