{
  "type": "Feature",
  "properties": {
    "gn:admin1_code":"34.0",
    "gn:admin2_code":"234.0",
    "gn:asciiname":"Milki",
    "gn:country_code":"IN",
    "gn:dem":100,
    "gn:feature_class":"P",
    "gn:feature_code":"PPL",
    "gn:name":"Milki",
    "gn:population":0,
    "gn:timezone":"Asia/Kolkata",
    "iso:country":"IN",
    "ks:ks_name":"Milki",
    "ks:ks_type":"VILLAGE",
    "name:eng_x_preferred":[
        "Milki"
    ],
    "wof:name":"Milki",
    "wof:placetype":"locality"
},
  "geometry": {"coordinates":[84.14592500000001,25.062389],"type":"Point"}
}