{
  "type": "Feature",
  "properties": {
    "iso:country":"IN",
    "ks:ks_name":"Suagard",
    "ks:ks_pop":143,
    "ks:ks_type":"HABITATION",
    "name:eng_x_preferred":[
        "Suagard"
    ],
    "wof:name":"Suagard",
    "wof:placetype":"locality",
    "wof:population":143
},
  "geometry": {"coordinates":[78.312091,23.322675],"type":"Point"}
}