{
  "type": "Feature",
  "properties": {
    "iso:country":"IN",
    "ks:ks_name":"Ghotulpara",
    "ks:ks_pop":72,
    "ks:ks_type":"HABITATION",
    "name:eng_x_preferred":[
        "Ghotulpara"
    ],
    "wof:name":"Ghotulpara",
    "wof:placetype":"locality",
    "wof:population":72
},
  "geometry": {"coordinates":[81.398211,20.119539],"type":"Point"}
}