{
  "type": "Feature",
  "properties": {
    "iso:country":"IN",
    "ks:ks_name":"Batwadiya Khurd",
    "ks:ks_pop":130,
    "ks:ks_type":"VILLAGE",
    "name:eng_x_preferred":[
        "Batwadiya Khurd"
    ],
    "wof:name":"Batwadiya Khurd",
    "wof:placetype":"locality",
    "wof:population":130
},
  "geometry": {"coordinates":[75.206176,22.981046],"type":"Point"}
}