{
  "type": "Feature",
  "properties": {
    "gn:admin1_code":"2.0",
    "gn:admin2_code":"554.0",
    "gn:asciiname":"Vankamadivandlapalli",
    "gn:country_code":"IN",
    "gn:dem":532,
    "gn:feature_class":"P",
    "gn:feature_code":"PPL",
    "gn:name":"Vankamadiv\u0101ndlapalli",
    "gn:population":0,
    "gn:timezone":"Asia/Kolkata",
    "iso:country":"IN",
    "wof:name":"Vankamadivandlapalli",
    "wof:placetype":"locality"
},
  "geometry": {"coordinates":[79.07304000000001,13.76014],"type":"Point"}
}