{
  "type": "Feature",
  "properties": {
    "gn:admin1_code":"35.0",
    "gn:admin2_code":"454.0",
    "gn:asciiname":"Samnapur",
    "gn:country_code":"IN",
    "gn:dem":538,
    "gn:feature_class":"P",
    "gn:feature_code":"PPL",
    "gn:name":"Samn\u0101p\u016br",
    "gn:population":0,
    "gn:timezone":"Asia/Kolkata",
    "iso:country":"IN",
    "wof:name":"Samnapur",
    "wof:placetype":"locality"
},
  "geometry": {"coordinates":[80.09787,23.02616],"type":"Point"}
}