{
  "type": "Feature",
  "properties": {
    "iso:country":"IN",
    "ks:ks_name":"Nayadayapara",
    "ks:ks_pop":557,
    "ks:ks_type":"HABITATION",
    "name:eng_x_preferred":[
        "Nayadayapara"
    ],
    "wof:name":"Nayadayapara",
    "wof:placetype":"locality",
    "wof:population":557
},
  "geometry": {"coordinates":[70.214,22.443147],"type":"Point"}
}