{
  "type": "Feature",
  "properties": {
    "gn:admin1_code":"36",
    "gn:admin2_code":"184.0",
    "gn:asciiname":"Pat-hara",
    "gn:country_code":"IN",
    "gn:dem":91,
    "gn:feature_class":"P",
    "gn:feature_code":"PPL",
    "gn:name":"Pat-hara",
    "gn:population":0,
    "gn:timezone":"Asia/Kolkata",
    "iso:country":"IN",
    "wof:name":"Pat-hara",
    "wof:placetype":"locality"
},
  "geometry": {"coordinates":[83.04996,27.10303],"type":"Point"}
}