{
  "type": "Feature",
  "properties": {
    "iso:country":"IN",
    "name:eng_x_preferred":[
        "Vanayak Nagar"
    ],
    "wof:name":"Vanayak Nagar",
    "wof:placetype":"neighbourhood"
},
  "geometry": {"coordinates":[73.81564161243074,18.58163235794044],"type":"Point"}
}