{
  "type": "Feature",
  "properties": {
    "iso:country":"IN",
    "name:ara_x_preferred":[
        "\u0641\u0627\u0646\u0627\u064a\u0643\u0627 \u0646\u0627\u062c\u0627\u0631"
    ],
    "name:ben_bn_x_preferred":[
        "\u09ac\u09bf\u09a8\u09be\u09df\u0995 \u09a8\u0997\u09b0"
    ],
    "name:ben_in_x_preferred":[
        "\u09ac\u09bf\u09a8\u09be\u09df\u0995 \u09a8\u0997\u09b0"
    ],
    "name:eng_x_preferred":[
        "Vanayak Nagar"
    ],
    "name:guj_x_preferred":[
        "\u0ab5\u0aa8\u0abe\u0aaf\u0a95 \u0aa8\u0a97\u0ab0"
    ],
    "name:hin_x_preferred":[
        "\u0935\u0928\u093e\u092f\u0915 \u0928\u0917\u0930"
    ],
    "name:kan_x_preferred":[
        "\u0cb5\u0ca8\u0cbe\u0caf\u0c95\u0ccd"
    ],
    "name:mal_x_preferred":[
        "\u0d35\u0d28\u0d3e\u0d2f\u0d15\u0d4d \u0d28\u0d17\u0d7c"
    ],
    "name:mar_x_preferred":[
        "\u0935\u0928\u093e\u092f\u0915 \u0928\u0917\u0930"
    ],
    "name:pan_x_preferred":[
        "\u0a35\u0a3e\u0a28\u0a3e\u0a07\u0a15 \u0a28\u0a17\u0a30"
    ],
    "name:tam_x_preferred":[
        "\u0bb5\u0bbf\u0ba9\u0bbe\u0baf\u0b95\u0bcd \u0ba8\u0b95\u0bb0\u0bcd"
    ],
    "name:tel_x_preferred":[
        "\u0c35\u0c3f\u0c28\u0c3e\u0c2f\u0c15\u0c4d \u0c28\u0c17\u0c30\u0c4d"
    ],
    "name:urd_x_preferred":[
        "\u0648\u0646\u0627\u06cc\u06a9 \u0646\u06af\u0631"
    ],
    "wof:name":"Vanayak Nagar",
    "wof:placetype":"neighbourhood"
},
  "geometry": {"coordinates":[73.81564161243074,18.58163235794044],"type":"Point"}
}