{
  "type": "Feature",
  "properties": {
    "iso:country":"IN",
    "ks:ks_name":"Bilandi",
    "ks:ks_pop":115,
    "ks:ks_type":"VILLAGE",
    "name:eng_x_preferred":[
        "Bilandi"
    ],
    "wof:name":"Bilandi",
    "wof:placetype":"locality",
    "wof:population":115
},
  "geometry": {"coordinates":[86.805328,26.438868],"type":"Point"}
}