{
  "type": "Feature",
  "properties": {
    "iso:country":"IN",
    "ks:ks_alt_nam":"Mathia tola",
    "ks:ks_name":"Mathia Tola",
    "ks:ks_pop":123,
    "ks:ks_type":"HABITATION",
    "ks:ks_uagg_main":0,
    "name:eng_x_preferred":[
        "Mathia Tola"
    ],
    "wof:name":"Mathia Tola",
    "wof:placetype":"neighbourhood",
    "wof:population":123
},
  "geometry": {"coordinates":[84.544935,26.706102],"type":"Point"}
}