{
  "type": "Feature",
  "properties": {
    "iso:country":"IN",
    "ks:ks_name":"Vazeer Nagar",
    "ks:ks_pop":439,
    "ks:ks_type":"HABITATION",
    "ks:ks_uagg_main":0,
    "name:eng_x_preferred":[
        "Vazeer Nagar"
    ],
    "wof:name":"Vazeer Nagar",
    "wof:placetype":"neighbourhood",
    "wof:population":439
},
  "geometry": {"coordinates":[79.008257,28.744237],"type":"Point"}
}