{
  "type": "Feature",
  "properties": {
    "iso:country":"IN",
    "ks:ks_name":"Kanapur",
    "ks:ks_pop":178,
    "ks:ks_type":"HABITATION",
    "name:eng_x_preferred":[
        "Kanapur"
    ],
    "wof:name":"Kanapur",
    "wof:placetype":"locality",
    "wof:population":178
},
  "geometry": {"coordinates":[78.73825100000001,19.328278],"type":"Point"}
}