{
  "type": "Feature",
  "properties": {
    "iso:country":"IN",
    "ks:ks_name":"Badarodanga",
    "ks:ks_pop":1031,
    "ks:ks_type":"VILLAGE",
    "name:eng_x_preferred":[
        "Badarodanga"
    ],
    "wof:name":"Badarodanga",
    "wof:placetype":"locality",
    "wof:population":1031
},
  "geometry": {"coordinates":[86.31250799999999,20.114152],"type":"Point"}
}