{
  "type": "Feature",
  "properties": {
    "iso:country":"IN",
    "ks:ks_name":"Melmanavur",
    "ks:ks_pop":3751,
    "ks:ks_type":"VILLAGE",
    "name:eng_x_preferred":[
        "Melmanavur"
    ],
    "wof:name":"Melmanavur",
    "wof:placetype":"locality",
    "wof:population":3751
},
  "geometry": {"coordinates":[79.07697400000001,12.916345],"type":"Point"}
}