{
  "type": "Feature",
  "properties": {
    "iso:country":"IN",
    "ks:ks_name":"Babhan Gaon",
    "ks:ks_pop":0,
    "ks:ks_type":"VILLAGE",
    "name:eng_x_preferred":[
        "Babhan Gaon"
    ],
    "wof:name":"Babhan Gaon",
    "wof:placetype":"locality",
    "wof:population":0
},
  "geometry": {"coordinates":[88.043487,26.131764],"type":"Point"}
}