{
  "type": "Feature",
  "properties": {
    "iso:country":"IN",
    "ks:ks_name":"Amratanr",
    "ks:ks_pop":430,
    "ks:ks_type":"VILLAGE",
    "name:eng_x_preferred":[
        "Amratanr"
    ],
    "wof:name":"Amratanr",
    "wof:placetype":"locality",
    "wof:population":430
},
  "geometry": {"coordinates":[86.718045,23.963893],"type":"Point"}
}