{
  "type": "Feature",
  "properties": {
    "gn:admin1_code":"36",
    "gn:admin2_code":"199.0",
    "gn:asciiname":"Manjhara",
    "gn:country_code":"IN",
    "gn:dem":76,
    "gn:feature_class":"P",
    "gn:feature_code":"PPL",
    "gn:name":"Manjhara",
    "gn:population":0,
    "gn:timezone":"Asia/Kolkata",
    "iso:country":"IN",
    "ks:ks_name":"Manjhara",
    "ks:ks_type":"VILLAGE",
    "name:eng_x_preferred":[
        "Manjhara"
    ],
    "wof:name":"Manjhara",
    "wof:placetype":"locality"
},
  "geometry": {"coordinates":[82.489445,25.20665],"type":"Point"}
}