{
  "type": "Feature",
  "properties": {
    "gn:admin1_code":"16.0",
    "gn:admin2_code":"516.0",
    "gn:asciiname":"Parsul",
    "gn:country_code":"IN",
    "gn:dem":651,
    "gn:feature_class":"P",
    "gn:feature_code":"PPL",
    "gn:name":"Parsul",
    "gn:population":0,
    "gn:timezone":"Asia/Kolkata",
    "iso:country":"IN",
    "wof:name":"Parsul",
    "wof:placetype":"locality"
},
  "geometry": {"coordinates":[74.1846,20.26473],"type":"Point"}
}