{
  "type": "Feature",
  "properties": {
    "gn:admin1_code":"12.0",
    "gn:admin2_code":"16.0",
    "gn:asciiname":"Dadi",
    "gn:country_code":"IN",
    "gn:dem":2011,
    "gn:feature_class":"P",
    "gn:feature_code":"PPL",
    "gn:name":"Dad\u012b",
    "gn:population":0,
    "gn:timezone":"Asia/Kolkata",
    "iso:country":"IN",
    "name:ceb_x_preferred":[
        "Dadi"
    ],
    "name:deu_x_preferred":[
        "Dadi"
    ],
    "name:ita_x_preferred":[
        "Dadi"
    ],
    "name:pol_x_preferred":[
        "Dadi"
    ],
    "name:rus_x_preferred":[
        "Dadi"
    ],
    "name:swe_x_preferred":[
        "Dadi"
    ],
    "wof:name":"Dadi",
    "wof:placetype":"locality"
},
  "geometry": {"coordinates":[75.7565,33.11640999999999],"type":"Point"}
}