{
  "type": "Feature",
  "properties": {
    "iso:country":"IN",
    "ks:ks_name":"Kalacherra",
    "ks:ks_pop":743,
    "ks:ks_type":"HABITATION",
    "name:eng_x_preferred":[
        "Kalacherra"
    ],
    "wof:name":"Kalacherra",
    "wof:placetype":"locality",
    "wof:population":743
},
  "geometry": {"coordinates":[92.049435,24.316403],"type":"Point"}
}