{
  "type": "Feature",
  "properties": {
    "iso:country":"IN",
    "ks:ks_name":"Pimpalwadi",
    "ks:ks_pop":57,
    "ks:ks_type":"HABITATION",
    "name:eng_x_preferred":[
        "Pimpalwadi"
    ],
    "wof:name":"Pimpalwadi",
    "wof:placetype":"locality",
    "wof:population":57
},
  "geometry": {"coordinates":[73.55591099999999,17.827011],"type":"Point"}
}