{
  "type": "Feature",
  "properties": {
    "gn:admin1_code":"2.0",
    "gn:admin2_code":"543.0",
    "gn:asciiname":"Lova Lakshmipuram",
    "gn:country_code":"IN",
    "gn:dem":215,
    "gn:feature_class":"P",
    "gn:feature_code":"PPL",
    "gn:name":"Lova Lakshm\u012bpuram",
    "gn:population":0,
    "gn:timezone":"Asia/Kolkata",
    "iso:country":"IN",
    "wof:name":"Lova Lakshmipuram",
    "wof:placetype":"locality"
},
  "geometry": {"coordinates":[83.56969000000002,18.93775],"type":"Point"}
}