{
  "type": "Feature",
  "properties": {
    "gn:admin1_code":"36",
    "gn:admin2_code":"144.0",
    "gn:asciiname":"Gabrari",
    "gn:country_code":"IN",
    "gn:dem":180,
    "gn:feature_class":"P",
    "gn:feature_code":"PPL",
    "gn:name":"Gabr\u0101ri",
    "gn:population":0,
    "gn:timezone":"Asia/Kolkata",
    "iso:country":"IN",
    "wof:name":"Gabrari",
    "wof:placetype":"locality"
},
  "geometry": {"coordinates":[77.91354,27.52186],"type":"Point"}
}