{
  "type": "Feature",
  "properties": {
    "gn:admin1_code":"36.0",
    "gn:admin2_code":"185",
    "gn:asciiname":"Ama",
    "gn:country_code":"IN",
    "gn:dem":94,
    "gn:feature_class":"P",
    "gn:feature_code":"PPL",
    "gn:name":"Ama",
    "gn:population":0,
    "gn:timezone":"Asia/Kolkata",
    "iso:country":"IN",
    "wof:name":"Ama",
    "wof:placetype":"locality"
},
  "geometry": {"coordinates":[82.65080999999998,26.87999000000001],"type":"Point"}
}