{
  "type": "Feature",
  "properties": {
    "gn:admin1_code":"39",
    "gn:admin2_code":"61.0",
    "gn:asciiname":"Margaon",
    "gn:country_code":"IN",
    "gn:dem":1179,
    "gn:feature_class":"P",
    "gn:feature_code":"PPL",
    "gn:name":"Margaon",
    "gn:population":0,
    "gn:timezone":"Asia/Kolkata",
    "iso:country":"IN",
    "ks:ks_name":"Mar Gaon",
    "ks:ks_pop":48,
    "ks:ks_type":"VILLAGE",
    "name:eng_x_preferred":[
        "Mar Gaon"
    ],
    "name:eng_x_variant":[
        "Margaon"
    ],
    "wof:name":"Mar Gaon",
    "wof:placetype":"locality",
    "wof:population":48
},
  "geometry": {"coordinates":[78.950081,30.199209],"type":"Point"}
}