{
  "type": "Feature",
  "properties": {
    "gn:admin1_code":"36",
    "gn:admin2_code":"199.0",
    "gn:asciiname":"Madanpatti",
    "gn:country_code":"IN",
    "gn:dem":86,
    "gn:feature_class":"P",
    "gn:feature_code":"PPL",
    "gn:name":"Madanpatti",
    "gn:population":0,
    "gn:timezone":"Asia/Kolkata",
    "iso:country":"IN",
    "ks:ks_name":"Madan Patti",
    "ks:ks_pop":1054,
    "ks:ks_type":"VILLAGE",
    "ks:ks_uagg_main":0,
    "name:eng_x_preferred":[
        "Madan Patti"
    ],
    "wof:name":"Madan Patti",
    "wof:placetype":"locality",
    "wof:population":1054
},
  "geometry": {"coordinates":[82.57348500000001,25.165],"type":"Point"}
}