{
  "type": "Feature",
  "properties": {
    "iso:country":"IN",
    "ks:ks_name":"Paira Chali",
    "ks:ks_pop":325,
    "ks:ks_type":"VILLAGE",
    "name:eng_x_preferred":[
        "Paira Chali"
    ],
    "wof:name":"Paira Chali",
    "wof:placetype":"locality",
    "wof:population":325
},
  "geometry": {"coordinates":[87.17667299999999,22.185361],"type":"Point"}
}