{
  "type": "Feature",
  "properties": {
    "iso:country":"IN",
    "ks:ks_name":"Alagoor",
    "ks:ks_pop":335,
    "ks:ks_type":"HABITATION",
    "name:eng_x_preferred":[
        "Alagoor"
    ],
    "wof:name":"Alagoor",
    "wof:placetype":"locality",
    "wof:population":335
},
  "geometry": {"coordinates":[78.48146300000001,11.884715],"type":"Point"}
}