{
  "type": "Feature",
  "properties": {
    "gn:admin1_code":"10",
    "gn:admin2_code":"70.0",
    "gn:asciiname":"Jamiatgarh",
    "gn:country_code":"IN",
    "gn:dem":268,
    "gn:feature_class":"P",
    "gn:feature_code":"PPL",
    "gn:name":"Jam\u012batgarh",
    "gn:population":0,
    "gn:timezone":"Asia/Kolkata",
    "iso:country":"IN",
    "wof:name":"Jamiatgarh",
    "wof:placetype":"locality"
},
  "geometry": {"coordinates":[76.7389,30.3631],"type":"Point"}
}