{
  "type": "Feature",
  "properties": {
    "gn:admin1_code":"38.0",
    "gn:admin2_code":"352.0",
    "gn:asciiname":"Ladonri",
    "gn:country_code":"IN",
    "gn:dem":243,
    "gn:feature_class":"P",
    "gn:feature_code":"PPL",
    "gn:name":"Ladonri",
    "gn:population":0,
    "gn:timezone":"Asia/Kolkata",
    "iso:country":"IN",
    "ks:ks_name":"Ladonri",
    "ks:ks_pop":73,
    "ks:ks_type":"VILLAGE",
    "name:eng_x_preferred":[
        "Ladonri"
    ],
    "wof:name":"Ladonri",
    "wof:placetype":"locality",
    "wof:population":73
},
  "geometry": {"coordinates":[87.63165100000001,25.215101],"type":"Point"}
}