{
  "type": "Feature",
  "properties": {
    "gn:admin1_code":"34",
    "gn:admin2_code":"219.0",
    "gn:asciiname":"Chapraithi",
    "gn:country_code":"IN",
    "gn:dem":65,
    "gn:feature_class":"P",
    "gn:feature_code":"PPL",
    "gn:name":"Ch\u0101praithi",
    "gn:population":0,
    "gn:timezone":"Asia/Kolkata",
    "iso:country":"IN",
    "wof:name":"Chapraithi",
    "wof:placetype":"locality"
},
  "geometry": {"coordinates":[84.47811,26.02813],"type":"Point"}
}