{
  "type": "Feature",
  "properties": {
    "iso:country":"IN",
    "ks:ks_name":"Ramunipalem",
    "ks:ks_pop":279,
    "ks:ks_type":"HABITATION",
    "name:eng_x_preferred":[
        "Ramunipalem"
    ],
    "wof:name":"Ramunipalem",
    "wof:placetype":"locality",
    "wof:population":279
},
  "geometry": {"coordinates":[83.68091,18.258154],"type":"Point"}
}