{
  "type": "Feature",
  "properties": {
    "iso:country":"IN",
    "ks:ks_name":"Dumaguda",
    "ks:ks_pop":251,
    "ks:ks_type":"HABITATION",
    "name:eng_x_preferred":[
        "Dumaguda"
    ],
    "wof:name":"Dumaguda",
    "wof:placetype":"locality",
    "wof:population":251
},
  "geometry": {"coordinates":[82.298244,19.756053],"type":"Point"}
}