{
  "type": "Feature",
  "properties": {
    "gn:admin1_code":"19.0",
    "gn:admin2_code":"570.0",
    "gn:asciiname":"Kuppur",
    "gn:country_code":"IN",
    "gn:dem":655,
    "gn:feature_class":"P",
    "gn:feature_code":"PPL",
    "gn:name":"Kupp\u016br",
    "gn:population":0,
    "gn:timezone":"Asia/Kolkata",
    "iso:country":"IN",
    "ks:ks_name":"Kuppuru",
    "ks:ks_pop":214,
    "ks:ks_type":"HABITATION",
    "name:eng_x_preferred":[
        "Kuppuru"
    ],
    "name:eng_x_variant":[
        "Kuppur"
    ],
    "wof:name":"Kuppuru",
    "wof:placetype":"locality",
    "wof:population":214
},
  "geometry": {"coordinates":[75.465683,13.703768],"type":"Point"}
}