{
  "type": "Feature",
  "properties": {
    "iso:country":"IN",
    "ks:ks_name":"Bishunpur Dharam",
    "ks:ks_pop":118,
    "ks:ks_type":"VILLAGE",
    "ks:ks_uagg_main":0,
    "name:eng_x_preferred":[
        "Bishunpur Dharam"
    ],
    "wof:name":"Bishunpur Dharam",
    "wof:placetype":"neighbourhood",
    "wof:population":118
},
  "geometry": {"coordinates":[85.057249,26.301632],"type":"Point"}
}