{
  "type": "Feature",
  "properties": {
    "gn:admin1_code":"21",
    "gn:admin2_code":"372.0",
    "gn:asciiname":"Bhardol",
    "gn:country_code":"IN",
    "gn:dem":155,
    "gn:feature_class":"P",
    "gn:feature_code":"PPL",
    "gn:name":"Bhardol",
    "gn:population":0,
    "gn:timezone":"Asia/Kolkata",
    "iso:country":"IN",
    "wof:name":"Bhardol",
    "wof:placetype":"locality"
},
  "geometry": {"coordinates":[83.95544,21.31418],"type":"Point"}
}