{
  "type": "Feature",
  "properties": {
    "iso:country":"IN",
    "ks:ks_name":"Boppagondanakoppa",
    "ks:ks_pop":254,
    "ks:ks_type":"VILLAGE",
    "name:eng_x_preferred":[
        "Boppagondanakoppa"
    ],
    "wof:name":"Boppagondanakoppa",
    "wof:placetype":"locality",
    "wof:population":254
},
  "geometry": {"coordinates":[75.205237,14.394347],"type":"Point"}
}