{
  "type": "Feature",
  "properties": {
    "iso:country":"IN",
    "ks:ks_name":"Kojappady",
    "ks:ks_pop":120,
    "ks:ks_type":"HABITATION",
    "name:eng_x_preferred":[
        "Kojappady"
    ],
    "wof:name":"Kojappady",
    "wof:placetype":"locality",
    "wof:population":120
},
  "geometry": {"coordinates":[75.43593799999999,12.937271],"type":"Point"}
}