{
  "type": "Feature",
  "properties": {
    "iso:country":"IN",
    "ks:ks_alt_nam":"BARASAI GANTISAI",
    "ks:ks_name":"Barasai Gantisai",
    "ks:ks_pop":83,
    "ks:ks_type":"HABITATION",
    "name:eng_x_preferred":[
        "Barasai Gantisai"
    ],
    "wof:name":"Barasai Gantisai",
    "wof:placetype":"locality",
    "wof:population":83
},
  "geometry": {"coordinates":[85.88842200000001,22.057045],"type":"Point"}
}