{
  "type": "Feature",
  "properties": {
    "gn:admin1_code":"36",
    "gn:admin2_code":"196.0",
    "gn:asciiname":"Imliadih",
    "gn:country_code":"IN",
    "gn:dem":309,
    "gn:feature_class":"P",
    "gn:feature_code":"PPL",
    "gn:name":"Imli\u0101d\u012bh",
    "gn:population":0,
    "gn:timezone":"Asia/Kolkata",
    "iso:country":"IN",
    "ks:ks_name":"Imaliadih",
    "ks:ks_pop":349,
    "ks:ks_type":"VILLAGE",
    "name:eng_x_preferred":[
        "Imaliadih"
    ],
    "name:eng_x_variant":[
        "Imliadih"
    ],
    "wof:name":"Imaliadih",
    "wof:placetype":"locality",
    "wof:population":349
},
  "geometry": {"coordinates":[83.15378,24.750727],"type":"Point"}
}