{
  "type": "Feature",
  "properties": {
    "iso:country":"IN",
    "ks:ks_name":"Mahuwatoli",
    "ks:ks_pop":307,
    "ks:ks_type":"HABITATION",
    "name:eng_x_preferred":[
        "Mahuwatoli"
    ],
    "wof:name":"Mahuwatoli",
    "wof:placetype":"locality",
    "wof:population":307
},
  "geometry": {"coordinates":[85.57534200000001,23.26768],"type":"Point"}
}