{
  "type": "Feature",
  "properties": {
    "gn:admin1_code":"16",
    "gn:admin2_code":"528.0",
    "gn:asciiname":"Purangad",
    "gn:country_code":"IN",
    "gn:dem":50,
    "gn:feature_class":"P",
    "gn:feature_code":"PPL",
    "gn:name":"P\u016brangad",
    "gn:population":0,
    "gn:timezone":"Asia/Kolkata",
    "iso:country":"IN",
    "name:und_x_variant":[
        "P\u016brangarh",
        "Purngad",
        "P\u016brangad"
    ],
    "wof:name":"Purangad",
    "wof:placetype":"locality"
},
  "geometry": {"coordinates":[73.32026999999999,16.81415],"type":"Point"}
}