{
  "type": "Feature",
  "properties": {
    "iso:country":"IN",
    "ks:ks_name":"Kelagina Malali",
    "ks:ks_pop":55,
    "ks:ks_type":"HABITATION",
    "name:eng_x_preferred":[
        "Kelagina Malali"
    ],
    "wof:name":"Kelagina Malali",
    "wof:placetype":"locality",
    "wof:population":55
},
  "geometry": {"coordinates":[74.77506200000001,14.570397],"type":"Point"}
}