{
  "type": "Feature",
  "properties": {
    "gn:admin1_code":"24.0",
    "gn:admin2_code":"100.0",
    "gn:asciiname":"Shirasar",
    "gn:country_code":"IN",
    "gn:dem":194,
    "gn:feature_class":"P",
    "gn:feature_code":"PPL",
    "gn:name":"Shir\u0101sar",
    "gn:population":0,
    "gn:timezone":"Asia/Kolkata",
    "iso:country":"IN",
    "name:hin_x_preferred":[
        "Shir\u0101sar"
    ],
    "wof:name":"Shirasar",
    "wof:placetype":"locality"
},
  "geometry": {"coordinates":[74.10961,28.96845],"type":"Point"}
}