{
  "type": "Feature",
  "properties": {
    "gn:admin1_code":"19.0",
    "gn:admin2_code":"566.0",
    "gn:asciiname":"Galirangayyanahatti",
    "gn:country_code":"IN",
    "gn:dem":756,
    "gn:feature_class":"P",
    "gn:feature_code":"PPL",
    "gn:name":"G\u0101lirangayyanahatti",
    "gn:population":0,
    "gn:timezone":"Asia/Kolkata",
    "iso:country":"IN",
    "ks:ks_name":"Galirangaianahatty",
    "ks:ks_pop":530,
    "ks:ks_type":"HABITATION",
    "name:eng_x_preferred":[
        "Galirangaianahatty"
    ],
    "name:eng_x_variant":[
        "Galirangayyanahatti"
    ],
    "wof:name":"Galirangaianahatty",
    "wof:placetype":"locality",
    "wof:population":530
},
  "geometry": {"coordinates":[76.23721500000001,13.888957],"type":"Point"}
}