{
  "type": "Feature",
  "properties": {
    "gn:admin1_code":"36",
    "gn:admin2_code":"178.0",
    "gn:asciiname":"Maganpur",
    "gn:country_code":"IN",
    "gn:dem":97,
    "gn:feature_class":"P",
    "gn:feature_code":"PPL",
    "gn:name":"Maganpur",
    "gn:population":0,
    "gn:timezone":"Asia/Kolkata",
    "iso:country":"IN",
    "wof:name":"Maganpur",
    "wof:placetype":"locality"
},
  "geometry": {"coordinates":[82.3908,26.38827],"type":"Point"}
}