{
  "type": "Feature",
  "properties": {
    "iso:country":"IN",
    "ks:ks_name":"Jaunlipokhari",
    "ks:ks_pop":289,
    "ks:ks_type":"VILLAGE",
    "name:eng_x_preferred":[
        "Jaunlipokhari"
    ],
    "wof:name":"Jaunlipokhari",
    "wof:placetype":"locality",
    "wof:population":289
},
  "geometry": {"coordinates":[85.797921,21.330343],"type":"Point"}
}