{
  "type": "Feature",
  "properties": {
    "iso:country":"IN",
    "ks:ks_name":"Rasikpur",
    "ks:ks_pop":1383,
    "ks:ks_type":"VILLAGE",
    "name:eng_x_preferred":[
        "Rasikpur"
    ],
    "wof:name":"Rasikpur",
    "wof:placetype":"locality",
    "wof:population":1383
},
  "geometry": {"coordinates":[87.728735,22.271454],"type":"Point"}
}