{
  "type": "Feature",
  "properties": {
    "iso:country":"IN",
    "ks:ks_name":"Juni Bordi",
    "ks:ks_pop":630,
    "ks:ks_type":"VILLAGE",
    "name:eng_x_preferred":[
        "Juni Bordi"
    ],
    "wof:name":"Juni Bordi",
    "wof:placetype":"locality",
    "wof:population":630
},
  "geometry": {"coordinates":[74.64491099999999,23.084191],"type":"Point"}
}