{
  "type": "Feature",
  "properties": {
    "gn:admin1_code":"16",
    "gn:admin2_code":"505.0",
    "gn:asciiname":"Manegaon",
    "gn:country_code":"IN",
    "gn:dem":335,
    "gn:feature_class":"P",
    "gn:feature_code":"PPL",
    "gn:name":"M\u0101negaon",
    "gn:population":0,
    "gn:timezone":"Asia/Kolkata",
    "iso:country":"IN",
    "ks:ks_alt_nam":"M\u0101negaon",
    "ks:ks_name":"Manegaon",
    "ks:ks_pop":20,
    "ks:ks_type":"VILLAGE",
    "name:eng_x_preferred":[
        "Manegaon"
    ],
    "name:eng_x_variant":[
        "M\u0101negaon"
    ],
    "wof:name":"Manegaon",
    "wof:placetype":"locality",
    "wof:population":20
},
  "geometry": {"coordinates":[79.40852599999999,21.428298],"type":"Point"}
}