{
  "type": "Feature",
  "properties": {
    "iso:country":"IN",
    "ks:ks_name":"Meru",
    "ks:ks_pop":120,
    "ks:ks_type":"VILLAGE",
    "name:eng_x_preferred":[
        "Meru"
    ],
    "wof:name":"Meru",
    "wof:placetype":"locality",
    "wof:population":120
},
  "geometry": {"coordinates":[84.441436,20.356673],"type":"Point"}
}