{
  "type": "Feature",
  "properties": {
    "iso:country":"IN",
    "ks:ks_name":"Bela Chand Sukhia",
    "ks:ks_pop":2768,
    "ks:ks_type":"VILLAGE",
    "ks:ks_uagg_main":0,
    "name:eng_x_preferred":[
        "Bela Chand Sukhia"
    ],
    "wof:name":"Bela Chand Sukhia",
    "wof:placetype":"neighbourhood",
    "wof:population":2768
},
  "geometry": {"coordinates":[87.121483,25.911949],"type":"Point"}
}