{
  "type": "Feature",
  "properties": {
    "gn:admin1_code":"19.0",
    "gn:admin2_code":"574.0",
    "gn:asciiname":"Devara Betta",
    "gn:country_code":"IN",
    "gn:dem":1228,
    "gn:feature_class":"P",
    "gn:feature_code":"PPL",
    "gn:name":"Devara Betta",
    "gn:population":0,
    "gn:timezone":"Asia/Kolkata",
    "iso:country":"IN",
    "wof:name":"Devara Betta",
    "wof:placetype":"locality"
},
  "geometry": {"coordinates":[75.60692,12.87318],"type":"Point"}
}