{
  "type": "Feature",
  "properties": {
    "iso:country":"IN",
    "ks:ks_name":"Kanker Beda",
    "ks:ks_pop":660,
    "ks:ks_type":"HABITATION",
    "name:eng_x_preferred":[
        "Kanker Beda"
    ],
    "wof:name":"Kanker Beda",
    "wof:placetype":"locality",
    "wof:population":660
},
  "geometry": {"coordinates":[81.354899,19.459256],"type":"Point"}
}