{
  "type": "Feature",
  "properties": {
    "gn:admin1_code":"37",
    "gn:admin2_code":"410.0",
    "gn:asciiname":"Gurra",
    "gn:country_code":"IN",
    "gn:dem":255,
    "gn:feature_class":"P",
    "gn:feature_code":"PPL",
    "gn:name":"Gurra",
    "gn:population":0,
    "gn:timezone":"Asia/Kolkata",
    "iso:country":"IN",
    "ks:ks_name":"Gurra",
    "ks:ks_pop":1223,
    "ks:ks_type":"VILLAGE",
    "name:eng_x_preferred":[
        "Gurra"
    ],
    "wof:name":"Gurra",
    "wof:placetype":"locality",
    "wof:population":1223
},
  "geometry": {"coordinates":[82.015117,21.712382],"type":"Point"}
}