{
  "type": "Feature",
  "properties": {
    "gn:admin1_code":"37",
    "gn:admin2_code":"407.0",
    "gn:asciiname":"Kuba",
    "gn:country_code":"IN",
    "gn:dem":351,
    "gn:feature_class":"P",
    "gn:feature_code":"PPL",
    "gn:name":"K\u016bba",
    "gn:population":0,
    "gn:timezone":"Asia/Kolkata",
    "iso:country":"IN",
    "name:bel_x_preferred":[
        "\u041a\u0443\u0431\u0430"
    ],
    "name:bul_x_preferred":[
        "\u041a\u0443\u0431\u0430"
    ],
    "name:cat_x_preferred":[
        "Kuba"
    ],
    "name:ceb_x_preferred":[
        "Kuba"
    ],
    "name:ces_x_preferred":[
        "Kuba"
    ],
    "name:deu_x_preferred":[
        "Kuba"
    ],
    "name:fra_x_preferred":[
        "Kuba"
    ],
    "name:hrv_x_preferred":[
        "Kuba"
    ],
    "name:kor_x_preferred":[
        "\ucfe0\ubc14"
    ],
    "name:lit_x_preferred":[
        "Kuba"
    ],
    "name:nor_x_preferred":[
        "Kuba"
    ],
    "name:pol_x_preferred":[
        "Kuba"
    ],
    "name:rus_x_preferred":[
        "\u041a\u0443\u0431\u0430"
    ],
    "name:slk_x_preferred":[
        "Kuba"
    ],
    "name:srp_x_preferred":[
        "\u041a\u0443\u0431\u0430"
    ],
    "name:swe_x_preferred":[
        "Kuba"
    ],
    "name:tur_x_preferred":[
        "Kuba"
    ],
    "name:ukr_x_preferred":[
        "\u041a\u0443\u0431\u0430"
    ],
    "name:uzb_x_preferred":[
        "Kuba"
    ],
    "wof:name":"Kuba",
    "wof:placetype":"locality"
},
  "geometry": {"coordinates":[81.38878000000003,22.22323],"type":"Point"}
}