{
  "type": "Feature",
  "properties": {
    "iso:country":"IN",
    "ks:ks_alt_nam":"tarepada",
    "ks:ks_name":"Tarepada",
    "ks:ks_pop":25,
    "ks:ks_type":"HABITATION",
    "name:eng_x_preferred":[
        "Tarepada"
    ],
    "wof:name":"Tarepada",
    "wof:placetype":"locality",
    "wof:population":25
},
  "geometry": {"coordinates":[73.152547,19.708914],"type":"Point"}
}