{
  "type": "Feature",
  "properties": {
    "gn:admin1_code":"36.0",
    "gn:admin2_code":"181.0",
    "gn:asciiname":"Chaipurwa",
    "gn:country_code":"IN",
    "gn:dem":126,
    "gn:feature_class":"P",
    "gn:feature_code":"PPL",
    "gn:name":"Chaipurwa",
    "gn:population":0,
    "gn:timezone":"Asia/Kolkata",
    "iso:country":"IN",
    "ks:ks_name":"Chai Purwa",
    "ks:ks_pop":436,
    "ks:ks_type":"VILLAGE",
    "name:eng_x_preferred":[
        "Chai Purwa"
    ],
    "name:eng_x_variant":[
        "Chaipurwa"
    ],
    "wof:name":"Chai Purwa",
    "wof:placetype":"locality",
    "wof:population":436
},
  "geometry": {"coordinates":[82.018137,27.733681],"type":"Point"}
}