{
  "type": "Feature",
  "properties": {
    "iso:country":"IN",
    "ks:ks_name":"Tangarmunda",
    "ks:ks_pop":247,
    "ks:ks_type":"HABITATION",
    "name:eng_x_preferred":[
        "Tangarmunda"
    ],
    "wof:name":"Tangarmunda",
    "wof:placetype":"locality",
    "wof:population":247
},
  "geometry": {"coordinates":[84.143975,21.854667],"type":"Point"}
}