{
  "type": "Feature",
  "properties": {
    "gn:admin1_code":"21",
    "gn:admin2_code":"398.0",
    "gn:asciiname":"Bejjaguda",
    "gn:country_code":"IN",
    "gn:dem":1030,
    "gn:feature_class":"P",
    "gn:feature_code":"PPL",
    "gn:name":"Bejjag\u016bda",
    "gn:population":0,
    "gn:timezone":"Asia/Kolkata",
    "iso:country":"IN",
    "ks:ks_name":"Bhejaguda",
    "ks:ks_pop":354,
    "ks:ks_type":"HABITATION",
    "name:eng_x_preferred":[
        "Bhejaguda"
    ],
    "name:eng_x_variant":[
        "Bejjaguda"
    ],
    "wof:name":"Bhejaguda",
    "wof:placetype":"locality",
    "wof:population":354
},
  "geometry": {"coordinates":[82.817505,18.48307],"type":"Point"}
}