{
  "type": "Feature",
  "properties": {
    "iso:country":"IN",
    "ks:ks_name":"Samda",
    "ks:ks_pop":183,
    "ks:ks_type":"HABITATION",
    "name:eng_x_preferred":[
        "Samda"
    ],
    "wof:name":"Samda",
    "wof:placetype":"locality",
    "wof:population":183
},
  "geometry": {"coordinates":[82.026917,24.48251],"type":"Point"}
}