{
  "type": "Feature",
  "properties": {
    "gn:admin1_code":"24",
    "gn:admin2_code":"123.0",
    "gn:asciiname":"Nichli Miyari",
    "gn:country_code":"IN",
    "gn:dem":606,
    "gn:feature_class":"P",
    "gn:feature_code":"PPL",
    "gn:name":"Nichli Miy\u0101ri",
    "gn:population":0,
    "gn:timezone":"Asia/Kolkata",
    "iso:country":"IN",
    "wof:name":"Nichli Miyari",
    "wof:placetype":"locality"
},
  "geometry": {"coordinates":[73.84248000000002,25.18174],"type":"Point"}
}