{
  "type": "Feature",
  "properties": {
    "iso:country":"IN",
    "ks:ks_name":"Badiyargaon Talla",
    "ks:ks_pop":92,
    "ks:ks_type":"VILLAGE",
    "name:eng_x_preferred":[
        "Badiyargaon Talla"
    ],
    "wof:name":"Badiyargaon Talla",
    "wof:placetype":"locality",
    "wof:population":92
},
  "geometry": {"coordinates":[78.879711,29.723629],"type":"Point"}
}