{
  "type": "Feature",
  "properties": {
    "gn:admin1_code":"11",
    "gn:admin2_code":"23.0",
    "gn:asciiname":"Gond",
    "gn:country_code":"IN",
    "gn:dem":1452,
    "gn:feature_class":"P",
    "gn:feature_code":"PPL",
    "gn:name":"Gond",
    "gn:population":0,
    "gn:timezone":"Asia/Kolkata",
    "iso:country":"IN",
    "name:cat_x_preferred":[
        "Gond"
    ],
    "name:fra_x_preferred":[
        "Gond"
    ],
    "name:hin_x_preferred":[
        "\u0917\u094b\u0902\u0921"
    ],
    "wof:name":"Gond",
    "wof:placetype":"locality"
},
  "geometry": {"coordinates":[76.17903000000003,32.63233],"type":"Point"}
}