{
  "type": "Feature",
  "properties": {
    "iso:country":"IN",
    "ks:ks_name":"Devi Nagar",
    "ks:ks_pop":40,
    "ks:ks_type":"VILLAGE",
    "ks:ks_uagg_main":0,
    "name:eng_x_preferred":[
        "Devi Nagar"
    ],
    "wof:name":"Devi Nagar",
    "wof:placetype":"neighbourhood",
    "wof:population":40
},
  "geometry": {"coordinates":[76.72967800000001,30.807554],"type":"Point"}
}