{
  "type": "Feature",
  "properties": {
    "iso:country":"IN",
    "ks:ks_name":"Bagdharash",
    "ks:ks_pop":0,
    "ks:ks_type":"VILLAGE",
    "name:eng_x_preferred":[
        "Bagdharash"
    ],
    "wof:name":"Bagdharash",
    "wof:placetype":"locality",
    "wof:population":0
},
  "geometry": {"coordinates":[87.464246,21.719991],"type":"Point"}
}