{
  "type": "Feature",
  "properties": {
    "iso:country":"IN",
    "ks:ks_name":"Patel Falia",
    "ks:ks_pop":200,
    "ks:ks_type":"HABITATION",
    "ks:ks_uagg_main":0,
    "name:eng_x_preferred":[
        "Patel Falia"
    ],
    "wof:name":"Patel Falia",
    "wof:placetype":"neighbourhood",
    "wof:population":200
},
  "geometry": {"coordinates":[73.19030600000001,20.439472],"type":"Point"}
}