{
  "type": "Feature",
  "properties": {
    "iso:country":"IN",
    "ks:ks_name":"Harijan Faliya",
    "ks:ks_pop":810,
    "ks:ks_type":"HABITATION",
    "name:eng_x_preferred":[
        "Harijan Faliya"
    ],
    "wof:name":"Harijan Faliya",
    "wof:placetype":"locality",
    "wof:population":810
},
  "geometry": {"coordinates":[73.85427799999999,22.924556],"type":"Point"}
}