{
  "type": "Feature",
  "properties": {
    "iso:country":"IN",
    "ks:ks_alt_nam":"Kuledu STC",
    "ks:ks_name":"Kuledu Stc",
    "ks:ks_pop":157,
    "ks:ks_type":"HABITATION",
    "name:eng_x_preferred":[
        "Kuledu Stc"
    ],
    "wof:name":"Kuledu Stc",
    "wof:placetype":"locality",
    "wof:population":157
},
  "geometry": {"coordinates":[74.97080699999999,13.271017],"type":"Point"}
}