{
  "type": "Feature",
  "properties": {
    "iso:country":"IN",
    "ks:ks_name":"Beedamajalu",
    "ks:ks_pop":15,
    "ks:ks_type":"HABITATION",
    "name:eng_x_preferred":[
        "Beedamajalu"
    ],
    "wof:name":"Beedamajalu",
    "wof:placetype":"locality",
    "wof:population":15
},
  "geometry": {"coordinates":[75.268022,12.705978],"type":"Point"}
}