{
  "type": "Feature",
  "properties": {
    "iso:country":"IN",
    "ks:ks_name":"3 KM",
    "ks:ks_pop":37,
    "ks:ks_type":"VILLAGE",
    "name:eng_x_preferred":[
        "3 KM"
    ],
    "wof:name":"3 KM",
    "wof:placetype":"locality",
    "wof:population":37
},
  "geometry": {"coordinates":[73.20058899999999,28.995919],"type":"Point"}
}