{
  "type": "Feature",
  "properties": {
    "iso:country":"IN",
    "ks:ks_name":"Uttar Debipur Gurguria",
    "ks:ks_pop":3618,
    "ks:ks_type":"HABITATION",
    "name:eng_x_preferred":[
        "Uttar Debipur Gurguria"
    ],
    "wof:name":"Uttar Debipur Gurguria",
    "wof:placetype":"locality",
    "wof:population":3618
},
  "geometry": {"coordinates":[88.515519,21.971469],"type":"Point"}
}