{
  "type": "Feature",
  "properties": {
    "iso:country":"IN",
    "ks:ks_name":"Balluguda",
    "ks:ks_pop":67,
    "ks:ks_type":"HABITATION",
    "name:eng_x_preferred":[
        "Balluguda"
    ],
    "wof:name":"Balluguda",
    "wof:placetype":"locality",
    "wof:population":67
},
  "geometry": {"coordinates":[82.922391,17.995283],"type":"Point"}
}