{
  "type": "Feature",
  "properties": {
    "iso:country":"IN",
    "ks:ks_name":"Shitolewasti",
    "ks:ks_pop":130,
    "ks:ks_type":"HABITATION",
    "name:eng_x_preferred":[
        "Shitolewasti"
    ],
    "wof:name":"Shitolewasti",
    "wof:placetype":"locality",
    "wof:population":130
},
  "geometry": {"coordinates":[74.43408700000001,18.37351],"type":"Point"}
}