{
  "type": "Feature",
  "properties": {
    "iso:country":"IN",
    "ks:ks_alt_nam":"Gutguti Pakuwa FV",
    "ks:ks_name":"Gutguti Pakuwa Fv",
    "ks:ks_pop":1469,
    "ks:ks_type":"HABITATION",
    "name:eng_x_preferred":[
        "Gutguti Pakuwa Fv"
    ],
    "wof:name":"Gutguti Pakuwa Fv",
    "wof:placetype":"locality",
    "wof:population":1469
},
  "geometry": {"coordinates":[92.492795,24.189097],"type":"Point"}
}