{
  "type": "Feature",
  "properties": {
    "gn:admin1_code":"25.0",
    "gn:admin2_code":"611.0",
    "gn:asciiname":"Pirgatvayal",
    "gn:country_code":"IN",
    "gn:dem":961,
    "gn:feature_class":"P",
    "gn:feature_code":"PPL",
    "gn:name":"Pirgatvayal",
    "gn:population":0,
    "gn:timezone":"Asia/Kolkata",
    "iso:country":"IN",
    "wof:name":"Pirgatvayal",
    "wof:placetype":"neighbourhood"
},
  "geometry": {"coordinates":[76.36172000000001,11.57499],"type":"Point"}
}