{
  "type": "Feature",
  "properties": {
    "gn:admin1_code":"35",
    "gn:admin2_code":"447.0",
    "gn:asciiname":"Dhanori",
    "gn:country_code":"IN",
    "gn:dem":648,
    "gn:feature_class":"P",
    "gn:feature_code":"PPL",
    "gn:name":"Dhanori",
    "gn:population":0,
    "gn:timezone":"Asia/Kolkata",
    "iso:country":"IN",
    "wof:name":"Dhanori",
    "wof:placetype":"locality"
},
  "geometry": {"coordinates":[77.95196999999997,21.67766],"type":"Point"}
}