{
  "type": "Feature",
  "properties": {
    "gn:admin1_code":"35",
    "gn:admin2_code":"447.0",
    "gn:asciiname":"Dhanori",
    "gn:country_code":"IN",
    "gn:dem":648,
    "gn:feature_class":"P",
    "gn:feature_code":"PPL",
    "gn:name":"Dhanori",
    "gn:population":0,
    "gn:timezone":"Asia/Kolkata",
    "iso:country":"IN",
    "name:ara_x_preferred":[
        "\u062f\u0627\u0646\u0648\u0631\u064a"
    ],
    "name:ben_bn_x_preferred":[
        "\u09a7\u09be\u09a8\u09cb\u09b0\u09bf"
    ],
    "name:ben_in_x_preferred":[
        "\u09a7\u09be\u09a8\u09cb\u09b0\u09bf"
    ],
    "name:guj_x_preferred":[
        "\u0aa7\u0aa8\u0acb\u0ab0\u0ac0"
    ],
    "name:hin_x_preferred":[
        "\u0927\u0928\u094b\u0930\u0940"
    ],
    "name:kan_x_preferred":[
        "\u0ca7\u0ca8\u0ccb\u0cb0\u0cbf"
    ],
    "name:mal_x_preferred":[
        "\u0d27\u0d28\u0d4b\u0d30\u0d3f"
    ],
    "name:mar_x_preferred":[
        "\u0927\u093e\u0928\u094b\u0930\u0940"
    ],
    "name:pan_x_preferred":[
        "\u0a27\u0a28\u0a4c\u0a30\u0a40"
    ],
    "name:tam_x_preferred":[
        "\u0ba4\u0ba9\u0bcb\u0bb0\u0bbf"
    ],
    "name:tel_x_preferred":[
        "\u0c27\u0c28\u0c4b\u0c30\u0c3f"
    ],
    "name:urd_x_preferred":[
        "\u062f\u06be\u0646\u0648\u0631\u06cc"
    ],
    "wof:name":"Dhanori",
    "wof:placetype":"locality"
},
  "geometry": {"coordinates":[77.95196999999997,21.67766],"type":"Point"}
}