{
  "type": "Feature",
  "properties": {
    "iso:country":"IN",
    "ks:ks_name":"Tendera",
    "ks:ks_pop":1309,
    "ks:ks_type":"VILLAGE",
    "name:eng_x_preferred":[
        "Tendera"
    ],
    "wof:name":"Tendera",
    "wof:placetype":"locality",
    "wof:population":1309
},
  "geometry": {"coordinates":[86.037188,22.215082],"type":"Point"}
}