{
  "type": "Feature",
  "properties": {
    "iso:country":"IN",
    "ks:ks_name":"Ukharia",
    "ks:ks_pop":40,
    "ks:ks_type":"VILLAGE",
    "name:eng_x_preferred":[
        "Ukharia"
    ],
    "wof:name":"Ukharia",
    "wof:placetype":"locality",
    "wof:population":40
},
  "geometry": {"coordinates":[86.45902,24.721855],"type":"Point"}
}