{
  "type": "Feature",
  "properties": {
    "gn:admin1_code":"35",
    "gn:admin2_code":"443.0",
    "gn:asciiname":"Mahuwakhera Bilochi",
    "gn:country_code":"IN",
    "gn:dem":445,
    "gn:feature_class":"P",
    "gn:feature_code":"PPL",
    "gn:name":"Mahuw\u0101khera Bilochi",
    "gn:population":0,
    "gn:timezone":"Asia/Kolkata",
    "iso:country":"IN",
    "wof:name":"Mahuwakhera Bilochi",
    "wof:placetype":"locality"
},
  "geometry": {"coordinates":[77.76129,24.18478],"type":"Point"}
}