{
  "type": "Feature",
  "properties": {
    "gn:admin1_code":"25.0",
    "gn:admin2_code":"602.0",
    "gn:asciiname":"Siyenjeri",
    "gn:country_code":"IN",
    "gn:dem":24,
    "gn:feature_class":"P",
    "gn:feature_code":"PPL",
    "gn:name":"Siyenjeri",
    "gn:population":0,
    "gn:timezone":"Asia/Kolkata",
    "iso:country":"IN",
    "wof:name":"Siyenjeri",
    "wof:placetype":"locality"
},
  "geometry": {"coordinates":[80.07913000000001,13.3137],"type":"Point"}
}