{
  "type": "Feature",
  "properties": {
    "iso:country":"IN",
    "ks:ks_name":"Partihan Purwa",
    "ks:ks_pop":192,
    "ks:ks_type":"HABITATION",
    "ks:ks_uagg_main":0,
    "name:eng_x_preferred":[
        "Partihan Purwa"
    ],
    "wof:name":"Partihan Purwa",
    "wof:placetype":"neighbourhood",
    "wof:population":192
},
  "geometry": {"coordinates":[82.171457,27.10868],"type":"Point"}
}