{
  "type": "Feature",
  "properties": {
    "gn:admin1_code":"23",
    "gn:admin2_code":"38.0",
    "gn:asciiname":"Umrpur",
    "gn:country_code":"IN",
    "gn:dem":251,
    "gn:feature_class":"P",
    "gn:feature_code":"PPL",
    "gn:name":"Umrpur",
    "gn:population":0,
    "gn:timezone":"Asia/Kolkata",
    "iso:country":"IN",
    "ks:ks_name":"Umrpur",
    "ks:ks_pop":310,
    "ks:ks_type":"VILLAGE",
    "name:eng_x_preferred":[
        "Umrpur"
    ],
    "wof:name":"Umrpur",
    "wof:placetype":"locality",
    "wof:population":310
},
  "geometry": {"coordinates":[75.611164,31.89931],"type":"Point"}
}