{
  "type": "Feature",
  "properties": {
    "gn:admin1_code":"36.0",
    "gn:admin2_code":"152.0",
    "gn:asciiname":"Indarpur Zamima Sutha",
    "gn:country_code":"IN",
    "gn:dem":162,
    "gn:feature_class":"P",
    "gn:feature_code":"PPL",
    "gn:name":"Indarpur Zam\u012bma S\u016btha",
    "gn:population":0,
    "gn:timezone":"Asia/Kolkata",
    "iso:country":"IN",
    "wof:name":"Indarpur Zamima Sutha",
    "wof:placetype":"locality"
},
  "geometry": {"coordinates":[79.77343,28.11372],"type":"Point"}
}