{
  "type": "Feature",
  "properties": {
    "iso:country":"IN",
    "ks:ks_name":"Simariya Multani",
    "ks:ks_pop":617,
    "ks:ks_type":"VILLAGE",
    "name:eng_x_preferred":[
        "Simariya Multani"
    ],
    "wof:name":"Simariya Multani",
    "wof:placetype":"locality",
    "wof:population":617
},
  "geometry": {"coordinates":[79.127043,22.396267],"type":"Point"}
}