{
  "type": "Feature",
  "properties": {
    "gn:admin1_code":"16",
    "gn:admin2_code":"507.0",
    "gn:asciiname":"Korambi",
    "gn:country_code":"IN",
    "gn:dem":238,
    "gn:feature_class":"P",
    "gn:feature_code":"PPL",
    "gn:name":"Korambi",
    "gn:population":0,
    "gn:timezone":"Asia/Kolkata",
    "iso:country":"IN",
    "wof:name":"Korambi",
    "wof:placetype":"locality"
},
  "geometry": {"coordinates":[80.00981999999998,20.72503],"type":"Point"}
}