{
  "type": "Feature",
  "properties": {
    "iso:country":"IN",
    "ks:ks_name":"Gandabaju",
    "ks:ks_pop":202,
    "ks:ks_type":"VILLAGE",
    "name:eng_x_preferred":[
        "Gandabaju"
    ],
    "wof:name":"Gandabaju",
    "wof:placetype":"locality",
    "wof:population":202
},
  "geometry": {"coordinates":[83.626865,19.562785],"type":"Point"}
}