{
  "type": "Feature",
  "properties": {
    "gn:admin1_code":"35",
    "gn:admin2_code":"443.0",
    "gn:asciiname":"Kanjela",
    "gn:country_code":"IN",
    "gn:dem":450,
    "gn:feature_class":"P",
    "gn:feature_code":"PPL",
    "gn:name":"Kanjela",
    "gn:population":0,
    "gn:timezone":"Asia/Kolkata",
    "iso:country":"IN",
    "wof:name":"Kanjela",
    "wof:placetype":"locality"
},
  "geometry": {"coordinates":[78.05479,23.58048],"type":"Point"}
}