{
  "type": "Feature",
  "properties": {
    "gn:admin1_code":"34.0",
    "gn:admin2_code":"222.0",
    "gn:asciiname":"Chalhaki",
    "gn:country_code":"IN",
    "gn:dem":45,
    "gn:feature_class":"P",
    "gn:feature_code":"PPL",
    "gn:name":"Chalh\u0101ki",
    "gn:population":0,
    "gn:timezone":"Asia/Kolkata",
    "iso:country":"IN",
    "wof:name":"Chalhaki",
    "wof:placetype":"neighbourhood"
},
  "geometry": {"coordinates":[86.05051,25.71116],"type":"Point"}
}