{
  "type": "Feature",
  "properties": {
    "iso:country":"IN",
    "ks:ks_name":"Geddavari Group",
    "ks:ks_pop":555,
    "ks:ks_type":"HABITATION",
    "name:eng_x_preferred":[
        "Geddavari Group"
    ],
    "wof:name":"Geddavari Group",
    "wof:placetype":"locality",
    "wof:population":555
},
  "geometry": {"coordinates":[81.91460600000001,16.428359],"type":"Point"}
}