{
  "type": "Feature",
  "properties": {
    "iso:country":"IN",
    "ks:ks_alt_nam":"PURA KURMI",
    "ks:ks_name":"Pura Kurmi",
    "ks:ks_pop":104,
    "ks:ks_type":"HABITATION",
    "name:eng_x_preferred":[
        "Pura Kurmi"
    ],
    "wof:name":"Pura Kurmi",
    "wof:placetype":"locality",
    "wof:population":104
},
  "geometry": {"coordinates":[81.63805000000001,26.63803],"type":"Point"}
}