{
  "type": "Feature",
  "properties": {
    "iso:country":"IN",
    "ks:ks_name":"12 AS",
    "ks:ks_pop":113,
    "ks:ks_type":"VILLAGE",
    "name:eng_x_preferred":[
        "12 AS"
    ],
    "wof:name":"12 AS",
    "wof:placetype":"locality",
    "wof:population":113
},
  "geometry": {"coordinates":[73.43121499999999,29.124488],"type":"Point"}
}