{
  "type": "Feature",
  "properties": {
    "gn:admin1_code":"10.0",
    "gn:admin2_code":"072",
    "gn:asciiname":"Narayangarh",
    "gn:country_code":"IN",
    "gn:dem":263,
    "gn:feature_class":"P",
    "gn:feature_code":"PPL",
    "gn:name":"N\u0101r\u0101yangarh",
    "gn:population":0,
    "gn:timezone":"Asia/Kolkata",
    "iso:country":"IN",
    "name:rus_x_preferred":[
        "\u041d\u0430\u0440\u0430\u044f\u043d\u0433\u0430\u0440\u0445"
    ],
    "wof:name":"Narayangarh",
    "wof:placetype":"locality"
},
  "geometry": {"coordinates":[76.94955999999998,30.10801],"type":"Point"}
}