{
  "type": "Feature",
  "properties": {
    "iso:country":"IN",
    "ks:ks_alt_nam":"Bandh\u0101niya",
    "ks:ks_name":"Bandhaniya",
    "ks:ks_type":"VILLAGE",
    "name:eng_x_preferred":[
        "Bandhaniya"
    ],
    "name:eng_x_variant":[
        "Bandh\u0101niya"
    ],
    "wof:name":"Bandhaniya",
    "wof:placetype":"locality"
},
  "geometry": {"coordinates":[76.642184,22.222601],"type":"Point"}
}