{
  "type": "Feature",
  "properties": {
    "iso:country":"IN",
    "ks:ks_name":"Baddevelly",
    "ks:ks_pop":20,
    "ks:ks_type":"VILLAGE",
    "name:eng_x_preferred":[
        "Baddevelly"
    ],
    "wof:name":"Baddevelly",
    "wof:placetype":"locality",
    "wof:population":20
},
  "geometry": {"coordinates":[79.835035,19.028],"type":"Point"}
}