{
  "type": "Feature",
  "properties": {
    "iso:country":"IN",
    "ks:ks_name":"Konwar Chuk",
    "ks:ks_pop":416,
    "ks:ks_type":"HABITATION",
    "name:eng_x_preferred":[
        "Konwar Chuk"
    ],
    "wof:name":"Konwar Chuk",
    "wof:placetype":"locality",
    "wof:population":416
},
  "geometry": {"coordinates":[95.15357299999999,27.059904],"type":"Point"}
}