{
  "type": "Feature",
  "properties": {
    "gn:admin1_code":"2",
    "gn:admin2_code":"549.0",
    "gn:asciiname":"Chintapallipadu",
    "gn:country_code":"IN",
    "gn:dem":26,
    "gn:feature_class":"P",
    "gn:feature_code":"PPL",
    "gn:name":"Chintapallip\u0101du",
    "gn:population":0,
    "gn:timezone":"Asia/Kolkata",
    "iso:country":"IN",
    "wof:name":"Chintapallipadu",
    "wof:placetype":"locality"
},
  "geometry": {"coordinates":[80.14354,16.00436],"type":"Point"}
}