{
  "type": "Feature",
  "properties": {
    "iso:country":"IN",
    "ks:ks_name":"Khaspara 2",
    "ks:ks_pop":271,
    "ks:ks_type":"HABITATION",
    "name:eng_x_preferred":[
        "Khaspara 2"
    ],
    "wof:name":"Khaspara 2",
    "wof:placetype":"locality",
    "wof:population":271
},
  "geometry": {"coordinates":[82.137998,19.40515],"type":"Point"}
}