{
  "type": "Feature",
  "properties": {
    "gn:admin1_code":"16",
    "gn:admin2_code":"503.0",
    "gn:asciiname":"Mhasona",
    "gn:country_code":"IN",
    "gn:dem":463,
    "gn:feature_class":"P",
    "gn:feature_code":"PPL",
    "gn:name":"Mhasona",
    "gn:population":0,
    "gn:timezone":"Asia/Kolkata",
    "iso:country":"IN",
    "ks:ks_name":"Masona",
    "ks:ks_pop":1072,
    "ks:ks_type":"HABITATION",
    "name:eng_x_preferred":[
        "Masona"
    ],
    "name:eng_x_variant":[
        "Mhasona"
    ],
    "wof:name":"Masona",
    "wof:placetype":"locality",
    "wof:population":1072
},
  "geometry": {"coordinates":[77.50730299999999,21.3551],"type":"Point"}
}