{
  "type": "Feature",
  "properties": {
    "iso:country":"IN",
    "ks:ks_alt_nam":"Alwar ayyar kottai",
    "ks:ks_name":"Alwar Ayyar Kottai",
    "ks:ks_pop":176,
    "ks:ks_type":"HABITATION",
    "name:eng_x_preferred":[
        "Alwar Ayyar Kottai"
    ],
    "wof:name":"Alwar Ayyar Kottai",
    "wof:placetype":"locality",
    "wof:population":176
},
  "geometry": {"coordinates":[78.228233,12.381474],"type":"Point"}
}