{
  "type": "Feature",
  "properties": {
    "gn:admin1_code":"37",
    "gn:admin2_code":"406.0",
    "gn:asciiname":"Kosabari",
    "gn:country_code":"IN",
    "gn:dem":339,
    "gn:feature_class":"P",
    "gn:feature_code":"PPL",
    "gn:name":"Kos\u0101b\u0101ri",
    "gn:population":0,
    "gn:timezone":"Asia/Kolkata",
    "iso:country":"IN",
    "name:und_x_variant":[
        "Kos\u0101b\u0101ri",
        "Chand\u016btola"
    ],
    "wof:name":"Kosabari",
    "wof:placetype":"locality"
},
  "geometry": {"coordinates":[81.67071,22.34474],"type":"Point"}
}