{
  "type": "Feature",
  "properties": {
    "gn:admin1_code":"36",
    "gn:admin2_code":"195.0",
    "gn:asciiname":"Pattigarh",
    "gn:country_code":"IN",
    "gn:dem":72,
    "gn:feature_class":"P",
    "gn:feature_code":"PPL",
    "gn:name":"Patt\u012bgarh",
    "gn:population":0,
    "gn:timezone":"Asia/Kolkata",
    "iso:country":"IN",
    "name:und_x_variant":[
        "Patt\u012bgarh",
        "Abdulpur"
    ],
    "wof:name":"Pattigarh",
    "wof:placetype":"locality"
},
  "geometry": {"coordinates":[83.64851,25.87398],"type":"Point"}
}