{
  "type": "Feature",
  "properties": {
    "iso:country":"IN",
    "ks:ks_name":"Mangal Sardar Para",
    "ks:ks_pop":103,
    "ks:ks_type":"HABITATION",
    "name:eng_x_preferred":[
        "Mangal Sardar Para"
    ],
    "wof:name":"Mangal Sardar Para",
    "wof:placetype":"locality",
    "wof:population":103
},
  "geometry": {"coordinates":[91.502793,23.921494],"type":"Point"}
}