{
  "type": "Feature",
  "properties": {
    "iso:country":"IN",
    "ks:ks_name":"Dyavatapura",
    "ks:ks_pop":180,
    "ks:ks_type":"HABITATION",
    "name:eng_x_preferred":[
        "Dyavatapura"
    ],
    "wof:name":"Dyavatapura",
    "wof:placetype":"locality",
    "wof:population":180
},
  "geometry": {"coordinates":[76.46746899999999,13.065492],"type":"Point"}
}