{
  "type": "Feature",
  "properties": {
    "gn:admin1_code":"36",
    "gn:admin2_code":"176.0",
    "gn:asciiname":"Dulaipur",
    "gn:country_code":"IN",
    "gn:dem":125,
    "gn:feature_class":"P",
    "gn:feature_code":"PPL",
    "gn:name":"Dulaipur",
    "gn:population":0,
    "gn:timezone":"Asia/Kolkata",
    "iso:country":"IN",
    "wof:name":"Dulaipur",
    "wof:placetype":"locality"
},
  "geometry": {"coordinates":[81.24229,27.00618],"type":"Point"}
}