{
  "type": "Feature",
  "properties": {
    "iso:country":"IN",
    "ks:ks_name":"Saradka Gate",
    "ks:ks_pop":380,
    "ks:ks_type":"HABITATION",
    "name:eng_x_preferred":[
        "Saradka Gate"
    ],
    "wof:name":"Saradka Gate",
    "wof:placetype":"locality",
    "wof:population":380
},
  "geometry": {"coordinates":[75.113214,12.685314],"type":"Point"}
}