{
  "type": "Feature",
  "properties": {
    "gn:admin1_code":"11",
    "gn:admin2_code":"23.0",
    "gn:asciiname":"Thared",
    "gn:country_code":"IN",
    "gn:dem":1403,
    "gn:feature_class":"P",
    "gn:feature_code":"PPL",
    "gn:name":"Thared",
    "gn:population":0,
    "gn:timezone":"Asia/Kolkata",
    "iso:country":"IN",
    "wof:name":"Thared",
    "wof:placetype":"locality"
},
  "geometry": {"coordinates":[76.18623000000002,32.50537],"type":"Point"}
}