{
  "type": "Feature",
  "properties": {
    "iso:country":"IN",
    "ks:ks_alt_nam":"Z.Jogampeta",
    "ks:ks_name":"Z.jogampeta",
    "ks:ks_pop":308,
    "ks:ks_type":"HABITATION",
    "name:eng_x_preferred":[
        "Z.jogampeta"
    ],
    "wof:name":"Z.jogampeta",
    "wof:placetype":"locality",
    "wof:population":308
},
  "geometry": {"coordinates":[82.65421499999999,17.832404],"type":"Point"}
}