{
  "type": "Feature",
  "properties": {
    "iso:country":"IN",
    "ks:ks_alt_nam":"LAXMIMALA",
    "ks:ks_name":"Laxmimala",
    "ks:ks_pop":80,
    "ks:ks_type":"HABITATION",
    "name:eng_x_preferred":[
        "Laxmimala"
    ],
    "wof:name":"Laxmimala",
    "wof:placetype":"locality",
    "wof:population":80
},
  "geometry": {"coordinates":[74.206118,16.931978],"type":"Point"}
}