{
  "type": "Feature",
  "properties": {
    "iso:country":"IN",
    "ks:ks_name":"Idukai",
    "ks:ks_pop":62,
    "ks:ks_type":"HABITATION",
    "name:eng_x_preferred":[
        "Idukai"
    ],
    "wof:name":"Idukai",
    "wof:placetype":"locality",
    "wof:population":62
},
  "geometry": {"coordinates":[74.85199299999999,14.48355],"type":"Point"}
}