{
  "type": "Feature",
  "properties": {
    "iso:country":"IN",
    "ks:ks_name":"Kokalunadaaje",
    "ks:ks_pop":304,
    "ks:ks_type":"HABITATION",
    "name:eng_x_preferred":[
        "Kokalunadaaje"
    ],
    "wof:name":"Kokalunadaaje",
    "wof:placetype":"locality",
    "wof:population":304
},
  "geometry": {"coordinates":[75.021185,12.814643],"type":"Point"}
}