{
  "type": "Feature",
  "properties": {
    "gn:admin1_code":"39.0",
    "gn:admin2_code":"62.0",
    "gn:asciiname":"Sartola",
    "gn:country_code":"IN",
    "gn:dem":811,
    "gn:feature_class":"P",
    "gn:feature_code":"PPL",
    "gn:name":"Sartola",
    "gn:population":0,
    "gn:timezone":"Asia/Kolkata",
    "iso:country":"IN",
    "ks:ks_name":"Sartola",
    "ks:ks_type":"VILLAGE",
    "name:eng_x_preferred":[
        "Sartola"
    ],
    "wof:name":"Sartola",
    "wof:placetype":"locality"
},
  "geometry": {"coordinates":[79.93109800000001,29.697265],"type":"Point"}
}