{
  "type": "Feature",
  "properties": {
    "iso:country":"IN",
    "ks:ks_name":"Eattickalpadi",
    "ks:ks_pop":688,
    "ks:ks_type":"HABITATION",
    "name:eng_x_preferred":[
        "Eattickalpadi"
    ],
    "wof:name":"Eattickalpadi",
    "wof:placetype":"locality",
    "wof:population":688
},
  "geometry": {"coordinates":[76.65537999999999,9.481191],"type":"Point"}
}