{
  "type": "Feature",
  "properties": {
    "gn:admin1_code":"36",
    "gn:admin2_code":"145.0",
    "gn:asciiname":"Am Ka Nagla",
    "gn:country_code":"IN",
    "gn:dem":178,
    "gn:feature_class":"P",
    "gn:feature_code":"PPL",
    "gn:name":"\u0100m Ka Nagla",
    "gn:population":0,
    "gn:timezone":"Asia/Kolkata",
    "iso:country":"IN",
    "wof:name":"Am Ka Nagla",
    "wof:placetype":"locality"
},
  "geometry": {"coordinates":[77.74153000000003,27.4548],"type":"Point"}
}