{
  "type": "Feature",
  "properties": {
    "iso:country":"IN",
    "ks:ks_name":"Kola",
    "ks:ks_pop":232,
    "ks:ks_type":"VILLAGE",
    "name:eng_x_preferred":[
        "Kola"
    ],
    "wof:name":"Kola",
    "wof:placetype":"locality",
    "wof:population":232
},
  "geometry": {"coordinates":[79.963751,29.639007],"type":"Point"}
}