{
  "type": "Feature",
  "properties": {
    "iso:country":"IN",
    "ks:ks_name":"Chak Dabwala",
    "ks:ks_pop":1596,
    "ks:ks_type":"VILLAGE",
    "name:eng_x_preferred":[
        "Chak Dabwala"
    ],
    "wof:name":"Chak Dabwala",
    "wof:placetype":"locality",
    "wof:population":1596
},
  "geometry": {"coordinates":[74.145532,30.401096],"type":"Point"}
}