{
  "type": "Feature",
  "properties": {
    "iso:country":"IN",
    "ks:ks_name":"Bela Sariana",
    "ks:ks_pop":1283,
    "ks:ks_type":"VILLAGE",
    "name:eng_x_preferred":[
        "Bela Sariana"
    ],
    "wof:name":"Bela Sariana",
    "wof:placetype":"locality",
    "wof:population":1283
},
  "geometry": {"coordinates":[75.767021,32.007762],"type":"Point"}
}