{
  "type": "Feature",
  "properties": {
    "gn:admin1_code":"12",
    "gn:admin2_code":"4.0",
    "gn:asciiname":"Pachari",
    "gn:country_code":"IN",
    "gn:dem":3689,
    "gn:feature_class":"P",
    "gn:feature_code":"PPL",
    "gn:name":"Pachari",
    "gn:population":0,
    "gn:timezone":"Asia/Kolkata",
    "iso:country":"IN",
    "wof:name":"Pachari",
    "wof:placetype":"locality"
},
  "geometry": {"coordinates":[76.64662,34.4087],"type":"Point"}
}