{
  "type": "Feature",
  "properties": {
    "iso:country":"IN",
    "ks:ks_name":"Chapakandar",
    "ks:ks_pop":400,
    "ks:ks_type":"HABITATION",
    "name:eng_x_preferred":[
        "Chapakandar"
    ],
    "wof:name":"Chapakandar",
    "wof:placetype":"locality",
    "wof:population":400
},
  "geometry": {"coordinates":[87.34329099999999,24.359264],"type":"Point"}
}