{
  "type": "Feature",
  "properties": {
    "gn:admin1_code":"39",
    "gn:admin2_code":"61.0",
    "gn:asciiname":"Pansikhal",
    "gn:country_code":"IN",
    "gn:dem":1521,
    "gn:feature_class":"P",
    "gn:feature_code":"PPL",
    "gn:name":"P\u0101ns\u012bkh\u0101l",
    "gn:population":0,
    "gn:timezone":"Asia/Kolkata",
    "iso:country":"IN",
    "wof:name":"Pansikhal",
    "wof:placetype":"locality"
},
  "geometry": {"coordinates":[78.95235,29.71944],"type":"Point"}
}