{
  "type": "Feature",
  "properties": {
    "gn:admin1_code":"9.0",
    "gn:admin2_code":"485.0",
    "gn:asciiname":"Tanda",
    "gn:country_code":"IN",
    "gn:dem":290,
    "gn:feature_class":"P",
    "gn:feature_code":"PPL",
    "gn:name":"T\u0101nda",
    "gn:population":0,
    "gn:timezone":"Asia/Kolkata",
    "iso:country":"IN",
    "name:bpy_x_preferred":[
        "\u09a4\u09be\u09a8\u09cd\u09a6\u09be"
    ],
    "name:ceb_x_preferred":[
        "Tanda"
    ],
    "name:deu_x_preferred":[
        "Tanda"
    ],
    "name:fra_x_preferred":[
        "Tanda"
    ],
    "name:ita_x_preferred":[
        "Tanda"
    ],
    "name:nld_x_preferred":[
        "Tanda"
    ],
    "name:pol_x_preferred":[
        "Tanda"
    ],
    "name:swa_x_preferred":[
        "Tanda"
    ],
    "name:swe_x_preferred":[
        "Tanda"
    ],
    "wof:name":"Tanda",
    "wof:placetype":"locality"
},
  "geometry": {"coordinates":[74.43897,22.88982],"type":"Point"}
}