{
  "type": "Feature",
  "properties": {
    "iso:country":"IN",
    "ks:ks_name":"Laxmipura Ojariya",
    "ks:ks_pop":150,
    "ks:ks_type":"HABITATION",
    "ks:ks_uagg_main":0,
    "name:eng_x_preferred":[
        "Laxmipura Ojariya"
    ],
    "wof:name":"Laxmipura Ojariya",
    "wof:placetype":"neighbourhood",
    "wof:population":150
},
  "geometry": {"coordinates":[74.186944,23.699722],"type":"Point"}
}