{
  "type": "Feature",
  "properties": {
    "gn:admin1_code":"34.0",
    "gn:admin2_code":"220.0",
    "gn:asciiname":"Gopalpur Mircha",
    "gn:country_code":"IN",
    "gn:dem":55,
    "gn:feature_class":"P",
    "gn:feature_code":"PPL",
    "gn:name":"Gop\u0101lpur Mircha",
    "gn:population":0,
    "gn:timezone":"Asia/Kolkata",
    "iso:country":"IN",
    "ks:ks_alt_nam":"Gop\u0101lpur Mircha",
    "ks:ks_name":"Gopalpur Mircha",
    "ks:ks_pop":1162,
    "ks:ks_type":"VILLAGE",
    "name:eng_x_preferred":[
        "Gopalpur Mircha"
    ],
    "name:eng_x_variant":[
        "Gop\u0101lpur Mircha"
    ],
    "wof:name":"Gopalpur Mircha",
    "wof:placetype":"locality",
    "wof:population":1162
},
  "geometry": {"coordinates":[85.434459,25.83268],"type":"Point"}
}