{
  "type": "Feature",
  "properties": {
    "iso:country":"IN",
    "ks:ks_name":"Bhaiswada",
    "ks:ks_pop":354,
    "ks:ks_type":"HABITATION",
    "name:eng_x_preferred":[
        "Bhaiswada"
    ],
    "wof:name":"Bhaiswada",
    "wof:placetype":"locality",
    "wof:population":354
},
  "geometry": {"coordinates":[79.03717399999999,30.204327],"type":"Point"}
}