{
  "type": "Feature",
  "properties": {
    "iso:country":"IN",
    "ks:ks_name":"Etar Bhata Suba",
    "ks:ks_pop":498,
    "ks:ks_type":"HABITATION",
    "name:eng_x_preferred":[
        "Etar Bhata Suba"
    ],
    "wof:name":"Etar Bhata Suba",
    "wof:placetype":"locality",
    "wof:population":498
},
  "geometry": {"coordinates":[91.753096,26.414077],"type":"Point"}
}