{
  "type": "Feature",
  "properties": {
    "iso:country":"IN",
    "ks:ks_name":"Gopapur",
    "ks:ks_pop":1800,
    "ks:ks_type":"VILLAGE",
    "ks:ks_uagg_main":0,
    "name:eng_x_preferred":[
        "Gopapur"
    ],
    "wof:name":"Gopapur",
    "wof:placetype":"neighbourhood",
    "wof:population":1800
},
  "geometry": {"coordinates":[85.022516,19.573819],"type":"Point"}
}