{
  "type": "Feature",
  "properties": {
    "iso:country":"IN",
    "ks:ks_name":"Kalwadi",
    "ks:ks_pop":192,
    "ks:ks_type":"HABITATION",
    "name:eng_x_preferred":[
        "Kalwadi"
    ],
    "wof:name":"Kalwadi",
    "wof:placetype":"locality",
    "wof:population":192
},
  "geometry": {"coordinates":[73.746219,19.161719],"type":"Point"}
}