{
  "type": "Feature",
  "properties": {
    "iso:country":"IN",
    "ks:ks_name":"Bhalunka",
    "ks:ks_pop":213,
    "ks:ks_type":"VILLAGE",
    "name:eng_x_preferred":[
        "Bhalunka"
    ],
    "wof:name":"Bhalunka",
    "wof:placetype":"locality",
    "wof:population":213
},
  "geometry": {"coordinates":[85.79089500000001,20.418308],"type":"Point"}
}