{
  "type": "Feature",
  "properties": {
    "iso:country":"IN",
    "ks:ks_name":"Mohanpur",
    "ks:ks_pop":2,
    "ks:ks_type":"VILLAGE",
    "ks:ks_uagg_main":0,
    "name:eng_x_preferred":[
        "Mohanpur"
    ],
    "wof:name":"Mohanpur",
    "wof:placetype":"neighbourhood",
    "wof:population":2
},
  "geometry": {"coordinates":[86.579629,24.107634],"type":"Point"}
}