{
  "type": "Feature",
  "properties": {
    "iso:country":"IN",
    "ks:ks_name":"Birai",
    "ks:ks_pop":617,
    "ks:ks_type":"HABITATION",
    "name:eng_x_preferred":[
        "Birai"
    ],
    "wof:name":"Birai",
    "wof:placetype":"locality",
    "wof:population":617
},
  "geometry": {"coordinates":[78.689679,26.971596],"type":"Point"}
}