{
  "type": "Feature",
  "properties": {
    "gn:admin1_code":"21.0",
    "gn:admin2_code":"377.0",
    "gn:asciiname":"Samia",
    "gn:country_code":"IN",
    "gn:dem":4,
    "gn:feature_class":"P",
    "gn:feature_code":"PPL",
    "gn:name":"Samia",
    "gn:population":0,
    "gn:timezone":"Asia/Kolkata",
    "iso:country":"IN",
    "wof:name":"Samia",
    "wof:placetype":"locality"
},
  "geometry": {"coordinates":[86.64220999999998,21.07111],"type":"Point"}
}