{
  "type": "Feature",
  "properties": {
    "iso:country":"IN",
    "ks:ks_name":"Chhenakhia",
    "ks:ks_pop":280,
    "ks:ks_type":"VILLAGE",
    "ks:ks_uagg_main":0,
    "name:eng_x_preferred":[
        "Chhenakhia"
    ],
    "wof:name":"Chhenakhia",
    "wof:placetype":"neighbourhood",
    "wof:population":280
},
  "geometry": {"coordinates":[86.85041099999999,20.982248],"type":"Point"}
}