{
  "type": "Feature",
  "properties": {
    "iso:country":"IN",
    "ks:ks_name":"Poojarivandlapalle",
    "ks:ks_pop":59,
    "ks:ks_type":"HABITATION",
    "name:eng_x_preferred":[
        "Poojarivandlapalle"
    ],
    "wof:name":"Poojarivandlapalle",
    "wof:placetype":"locality",
    "wof:population":59
},
  "geometry": {"coordinates":[78.7179,13.649816],"type":"Point"}
}