{
  "type": "Feature",
  "properties": {
    "gn:admin1_code":"21.0",
    "gn:admin2_code":"377.0",
    "gn:asciiname":"Srikanthapur",
    "gn:country_code":"IN",
    "gn:dem":12,
    "gn:feature_class":"P",
    "gn:feature_code":"PPL",
    "gn:name":"Srikanthapur",
    "gn:population":0,
    "gn:timezone":"Asia/Kolkata",
    "iso:country":"IN",
    "ks:ks_name":"Srikanthapur",
    "ks:ks_pop":160,
    "ks:ks_type":"VILLAGE",
    "ks:ks_uagg_main":0,
    "name:eng_x_preferred":[
        "Srikanthapur"
    ],
    "wof:name":"Srikanthapur",
    "wof:placetype":"neighbourhood",
    "wof:population":160
},
  "geometry": {"coordinates":[87.39312200000001,21.714759],"type":"Point"}
}