{
  "type": "Feature",
  "properties": {
    "gn:admin1_code":"35.0",
    "gn:admin2_code":"451.0",
    "gn:asciiname":"Batai",
    "gn:country_code":"IN",
    "gn:dem":434,
    "gn:feature_class":"P",
    "gn:feature_code":"PPL",
    "gn:name":"Batai",
    "gn:population":0,
    "gn:timezone":"Asia/Kolkata",
    "iso:country":"IN",
    "wof:name":"Batai",
    "wof:placetype":"locality"
},
  "geometry": {"coordinates":[80.16226,23.16063],"type":"Point"}
}