{
  "type": "Feature",
  "properties": {
    "gn:admin1_code":"35",
    "gn:admin2_code":"445.0",
    "gn:asciiname":"Bisakheri",
    "gn:country_code":"IN",
    "gn:dem":307,
    "gn:feature_class":"P",
    "gn:feature_code":"PPL",
    "gn:name":"Bisakheri",
    "gn:population":0,
    "gn:timezone":"Asia/Kolkata",
    "iso:country":"IN",
    "wof:name":"Bisakheri",
    "wof:placetype":"locality"
},
  "geometry": {"coordinates":[77.9333,22.83065],"type":"Point"}
}