{
  "type": "Feature",
  "properties": {
    "iso:country":"IN",
    "ks:ks_name":"Lemra",
    "ks:ks_pop":287,
    "ks:ks_type":"VILLAGE",
    "name:eng_x_preferred":[
        "Lemra"
    ],
    "wof:name":"Lemra",
    "wof:placetype":"locality",
    "wof:population":287
},
  "geometry": {"coordinates":[85.335671,22.28781],"type":"Point"}
}