{
  "type": "Feature",
  "properties": {
    "gn:admin1_code":"36.0",
    "gn:admin2_code":"176.0",
    "gn:asciiname":"Nirban Chak",
    "gn:country_code":"IN",
    "gn:dem":118,
    "gn:feature_class":"P",
    "gn:feature_code":"PPL",
    "gn:name":"Nirban Chak",
    "gn:population":0,
    "gn:timezone":"Asia/Kolkata",
    "iso:country":"IN",
    "wof:name":"Nirban Chak",
    "wof:placetype":"neighbourhood"
},
  "geometry": {"coordinates":[81.51819999999999,26.58004],"type":"Point"}
}