{
  "type": "Feature",
  "properties": {
    "iso:country":"IN",
    "ks:ks_name":"Amalpur Urf Gpganpahari",
    "ks:ks_pop":1569,
    "ks:ks_type":"VILLAGE",
    "name:eng_x_preferred":[
        "Amalpur Urf Gpganpahari"
    ],
    "wof:name":"Amalpur Urf Gpganpahari",
    "wof:placetype":"locality",
    "wof:population":1569
},
  "geometry": {"coordinates":[87.89597500000001,24.714991],"type":"Point"}
}