{
  "type": "Feature",
  "properties": {
    "iso:country":"IN",
    "ks:ks_name":"South Button Island",
    "ks:ks_type":"VILLAGE",
    "name:eng_x_preferred":[
        "South Button Island"
    ],
    "wof:name":"South Button Island",
    "wof:placetype":"locality"
},
  "geometry": {"coordinates":[93.020522,12.22395],"type":"Point"}
}