{
  "type": "Feature",
  "properties": {
    "iso:country":"IN",
    "ks:ks_alt_nam":"KUMHAR TOLA",
    "ks:ks_name":"Kumhar Tola",
    "ks:ks_pop":190,
    "ks:ks_type":"HABITATION",
    "name:eng_x_preferred":[
        "Kumhar Tola"
    ],
    "wof:name":"Kumhar Tola",
    "wof:placetype":"locality",
    "wof:population":190
},
  "geometry": {"coordinates":[84.20263799999999,25.537245],"type":"Point"}
}