{
  "type": "Feature",
  "properties": {
    "iso:country":"IN",
    "ks:ks_name":"Asurhaddi",
    "ks:ks_pop":170,
    "ks:ks_type":"VILLAGE",
    "name:eng_x_preferred":[
        "Asurhaddi"
    ],
    "wof:name":"Asurhaddi",
    "wof:placetype":"locality",
    "wof:population":170
},
  "geometry": {"coordinates":[85.952845,24.710067],"type":"Point"}
}