{
  "type": "Feature",
  "properties": {
    "gn:admin1_code":"36",
    "gn:admin2_code":"191.0",
    "gn:asciiname":"Azampur",
    "gn:country_code":"IN",
    "gn:dem":82,
    "gn:feature_class":"P",
    "gn:feature_code":"PPL",
    "gn:name":"Azampur",
    "gn:population":0,
    "gn:timezone":"Asia/Kolkata",
    "iso:country":"IN",
    "name:ben_x_preferred":[
        "\u0986\u099c\u09ae\u09aa\u09c1\u09b0"
    ],
    "wof:name":"Azampur",
    "wof:placetype":"locality"
},
  "geometry": {"coordinates":[83.19596999999997,26.12107],"type":"Point"}
}