{
  "type": "Feature",
  "properties": {
    "gn:admin1_code":"36",
    "gn:admin2_code":"168.0",
    "gn:asciiname":"Amund",
    "gn:country_code":"IN",
    "gn:dem":142,
    "gn:feature_class":"P",
    "gn:feature_code":"PPL",
    "gn:name":"Am\u016bnd",
    "gn:population":0,
    "gn:timezone":"Asia/Kolkata",
    "iso:country":"IN",
    "name:nno_x_preferred":[
        "Amund"
    ],
    "name:nor_x_preferred":[
        "Amund"
    ],
    "name:por_x_preferred":[
        "Amundo"
    ],
    "wof:name":"Amund",
    "wof:placetype":"locality"
},
  "geometry": {"coordinates":[79.67312,25.71922],"type":"Point"}
}