{
  "type": "Feature",
  "properties": {
    "iso:country":"IN",
    "ks:ks_name":"Gavhanwadi",
    "ks:ks_pop":585,
    "ks:ks_type":"HABITATION",
    "ks:ks_uagg_main":0,
    "name:eng_x_preferred":[
        "Gavhanwadi"
    ],
    "wof:name":"Gavhanwadi",
    "wof:placetype":"neighbourhood",
    "wof:population":585
},
  "geometry": {"coordinates":[73.955242,17.322252],"type":"Point"}
}