{
  "type": "Feature",
  "properties": {
    "iso:country":"IN",
    "ks:ks_alt_nam":"T\u0101ndiyon",
    "ks:ks_name":"Tandiyon",
    "ks:ks_type":"VILLAGE",
    "name:eng_x_preferred":[
        "Tandiyon"
    ],
    "name:eng_x_variant":[
        "T\u0101ndiyon"
    ],
    "wof:name":"Tandiyon",
    "wof:placetype":"locality"
},
  "geometry": {"coordinates":[79.029202,29.728583],"type":"Point"}
}