{
  "type": "Feature",
  "properties": {
    "iso:country":"IN",
    "ks:ks_name":"Dharampur",
    "ks:ks_pop":1248,
    "ks:ks_type":"VILLAGE",
    "name:eng_x_preferred":[
        "Dharampur"
    ],
    "wof:name":"Dharampur",
    "wof:placetype":"locality",
    "wof:population":1248
},
  "geometry": {"coordinates":[86.94607499999999,22.795877],"type":"Point"}
}