{
  "type": "Feature",
  "properties": {
    "iso:country":"IN",
    "ks:ks_name":"Bhikhapura",
    "ks:ks_pop":104,
    "ks:ks_type":"HABITATION",
    "name:eng_x_preferred":[
        "Bhikhapura"
    ],
    "wof:name":"Bhikhapura",
    "wof:placetype":"locality",
    "wof:population":104
},
  "geometry": {"coordinates":[73.274861,22.519472],"type":"Point"}
}