{
  "type": "Feature",
  "properties": {
    "gn:admin1_code":"36.0",
    "gn:admin2_code":"161.0",
    "gn:asciiname":"Badnapur",
    "gn:country_code":"IN",
    "gn:dem":151,
    "gn:feature_class":"P",
    "gn:feature_code":"PPL",
    "gn:name":"Badn\u0101pur",
    "gn:population":0,
    "gn:timezone":"Asia/Kolkata",
    "iso:country":"IN",
    "name:fra_x_preferred":[
        "Badnapur"
    ],
    "name:urd_x_preferred":[
        "\u0628\u062f\u0646\u0627\u067e\u0648\u0631"
    ],
    "wof:name":"Badnapur",
    "wof:placetype":"neighbourhood"
},
  "geometry": {"coordinates":[79.25226000000001,26.91289],"type":"Point"}
}