{
  "type": "Feature",
  "properties": {
    "iso:country":"IN",
    "ks:ks_name":"Attakandam",
    "ks:ks_pop":1837,
    "ks:ks_type":"HABITATION",
    "name:eng_x_preferred":[
        "Attakandam"
    ],
    "wof:name":"Attakandam",
    "wof:placetype":"locality",
    "wof:population":1837
},
  "geometry": {"coordinates":[75.22399,12.364605],"type":"Point"}
}