{
  "type": "Feature",
  "properties": {
    "iso:country":"IN",
    "ks:ks_name":"Herike",
    "ks:ks_pop":102,
    "ks:ks_type":"HABITATION",
    "name:eng_x_preferred":[
        "Herike"
    ],
    "wof:name":"Herike",
    "wof:placetype":"locality",
    "wof:population":102
},
  "geometry": {"coordinates":[75.598854,12.98601],"type":"Point"}
}