{
  "type": "Feature",
  "properties": {
    "gn:admin1_code":"10.0",
    "gn:admin2_code":"080",
    "gn:asciiname":"Khot Khurd",
    "gn:country_code":"IN",
    "gn:dem":227,
    "gn:feature_class":"P",
    "gn:feature_code":"PPL",
    "gn:name":"Khot Khurd",
    "gn:population":0,
    "gn:timezone":"Asia/Kolkata",
    "iso:country":"IN",
    "wof:name":"Khot Khurd",
    "wof:placetype":"locality"
},
  "geometry": {"coordinates":[76.17301999999999,29.37276],"type":"Point"}
}