{
  "type": "Feature",
  "properties": {
    "gn:admin1_code":"16",
    "gn:admin2_code":"506.0",
    "gn:asciiname":"Ronga",
    "gn:country_code":"IN",
    "gn:dem":376,
    "gn:feature_class":"P",
    "gn:feature_code":"PPL",
    "gn:name":"Ronga",
    "gn:population":0,
    "gn:timezone":"Asia/Kolkata",
    "iso:country":"IN",
    "wof:name":"Ronga",
    "wof:placetype":"locality"
},
  "geometry": {"coordinates":[79.53723000000002,21.47386],"type":"Point"}
}