{
  "type": "Feature",
  "properties": {
    "iso:country":"IN",
    "ks:ks_name":"Gulab Tola",
    "ks:ks_pop":69,
    "ks:ks_type":"HABITATION",
    "ks:ks_uagg_main":0,
    "name:eng_x_preferred":[
        "Gulab Tola"
    ],
    "wof:name":"Gulab Tola",
    "wof:placetype":"neighbourhood",
    "wof:population":69
},
  "geometry": {"coordinates":[83.49942900000001,27.152538],"type":"Point"}
}