{
  "type": "Feature",
  "properties": {
    "iso:country":"IN",
    "ks:ks_alt_nam":"Naw\u0101d\u012bh",
    "ks:ks_name":"Nawadih",
    "ks:ks_pop":272,
    "ks:ks_type":"VILLAGE",
    "name:eng_x_preferred":[
        "Nawadih"
    ],
    "name:eng_x_variant":[
        "Naw\u0101d\u012bh"
    ],
    "wof:name":"Nawadih",
    "wof:placetype":"locality",
    "wof:population":272
},
  "geometry": {"coordinates":[85.64793400000001,23.38704],"type":"Point"}
}