{
  "type": "Feature",
  "properties": {
    "iso:country":"IN",
    "ks:ks_name":"Mantiguni",
    "ks:ks_pop":36,
    "ks:ks_type":"HABITATION",
    "name:eng_x_preferred":[
        "Mantiguni"
    ],
    "wof:name":"Mantiguni",
    "wof:placetype":"locality",
    "wof:population":36
},
  "geometry": {"coordinates":[74.84857599999999,14.722201],"type":"Point"}
}