{
  "type": "Feature",
  "properties": {
    "iso:country":"IN",
    "ks:ks_name":"Paharpur Mafi",
    "ks:ks_pop":462,
    "ks:ks_type":"VILLAGE",
    "ks:ks_uagg_main":0,
    "name:eng_x_preferred":[
        "Paharpur Mafi"
    ],
    "wof:name":"Paharpur Mafi",
    "wof:placetype":"locality",
    "wof:population":462
},
  "geometry": {"coordinates":[78.664292,27.809149],"type":"Point"}
}