{
  "type": "Feature",
  "properties": {
    "iso:country":"IN",
    "ks:ks_name":"Dhaurahara Khas",
    "ks:ks_pop":1248,
    "ks:ks_type":"HABITATION",
    "ks:ks_uagg_main":0,
    "name:eng_x_preferred":[
        "Dhaurahara Khas"
    ],
    "wof:name":"Dhaurahara Khas",
    "wof:placetype":"neighbourhood",
    "wof:population":1248
},
  "geometry": {"coordinates":[84.052654,26.687599],"type":"Point"}
}