{
  "type": "Feature",
  "properties": {
    "gn:admin1_code":"29",
    "gn:admin2_code":"244.0",
    "gn:asciiname":"Padamchen",
    "gn:country_code":"IN",
    "gn:dem":2118,
    "gn:feature_class":"P",
    "gn:feature_code":"PPL",
    "gn:name":"Padamchen",
    "gn:population":0,
    "gn:timezone":"Asia/Kolkata",
    "iso:country":"IN",
    "wof:name":"Padamchen",
    "wof:placetype":"locality"
},
  "geometry": {"coordinates":[88.76626999999998,27.237],"type":"Point"}
}