{
  "type": "Feature",
  "properties": {
    "gn:admin1_code":"34.0",
    "gn:admin2_code":"220.0",
    "gn:asciiname":"Lodipur Phatikwara",
    "gn:country_code":"IN",
    "gn:dem":54,
    "gn:feature_class":"P",
    "gn:feature_code":"PPL",
    "gn:name":"Lodipur Phatikw\u0101ra",
    "gn:population":0,
    "gn:timezone":"Asia/Kolkata",
    "iso:country":"IN",
    "name:eng_x_preferred":[
        "Lodipur Phatikw\u0101ra"
    ],
    "wof:name":"Lodipur Phatikwara",
    "wof:placetype":"locality"
},
  "geometry": {"coordinates":[85.54524000000001,25.64473],"type":"Point"}
}