{
  "type": "Feature",
  "properties": {
    "gn:admin1_code":"34.0",
    "gn:admin2_code":"220.0",
    "gn:asciiname":"Lodipur Phatikwara",
    "gn:country_code":"IN",
    "gn:dem":54,
    "gn:feature_class":"P",
    "gn:feature_code":"PPL",
    "gn:name":"Lodipur Phatikw\u0101ra",
    "gn:population":0,
    "gn:timezone":"Asia/Kolkata",
    "iso:country":"IN",
    "ks:ks_name":"Lodipur Phatikwara",
    "ks:ks_pop":1603,
    "ks:ks_type":"VILLAGE",
    "name:eng_x_preferred":[
        "Lodipur Phatikwara"
    ],
    "wof:name":"Lodipur Phatikwara",
    "wof:placetype":"locality",
    "wof:population":1603
},
  "geometry": {"coordinates":[85.552751,25.645041],"type":"Point"}
}