{
  "type": "Feature",
  "properties": {
    "iso:country":"IN",
    "ks:ks_name":"Hukkalkai",
    "ks:ks_pop":20,
    "ks:ks_type":"HABITATION",
    "name:eng_x_preferred":[
        "Hukkalkai"
    ],
    "wof:name":"Hukkalkai",
    "wof:placetype":"locality",
    "wof:population":20
},
  "geometry": {"coordinates":[74.80625999999999,14.512398],"type":"Point"}
}