{
  "type": "Feature",
  "properties": {
    "iso:country":"IN",
    "ks:ks_name":"Toralpur",
    "ks:ks_pop":1551,
    "ks:ks_type":"VILLAGE",
    "ks:ks_uagg_main":0,
    "name:eng_x_preferred":[
        "Toralpur"
    ],
    "wof:name":"Toralpur",
    "wof:placetype":"neighbourhood",
    "wof:population":1551
},
  "geometry": {"coordinates":[88.120024,22.731593],"type":"Point"}
}