{
  "type": "Feature",
  "properties": {
    "gn:admin1_code":"11",
    "gn:admin2_code":"27.0",
    "gn:asciiname":"Sapreti",
    "gn:country_code":"IN",
    "gn:dem":965,
    "gn:feature_class":"P",
    "gn:feature_code":"PPL",
    "gn:name":"Sapreti",
    "gn:population":0,
    "gn:timezone":"Asia/Kolkata",
    "iso:country":"IN",
    "wof:name":"Sapreti",
    "wof:placetype":"locality"
},
  "geometry": {"coordinates":[76.91448000000003,31.83006],"type":"Point"}
}