{
  "type": "Feature",
  "properties": {
    "iso:country":"IN",
    "ks:ks_name":"Mansinhapur",
    "ks:ks_pop":5401,
    "ks:ks_type":"URBAN",
    "ks:ks_uagg_main":0,
    "name:eng_x_preferred":[
        "Mansinhapur"
    ],
    "wof:name":"Mansinhapur",
    "wof:placetype":"neighbourhood",
    "wof:population":5401
},
  "geometry": {"coordinates":[88.145169,22.651646],"type":"Point"}
}