{
  "type": "Feature",
  "properties": {
    "gn:admin1_code":"16",
    "gn:admin2_code":"509.0",
    "gn:asciiname":"Wisapur",
    "gn:country_code":"IN",
    "gn:dem":216,
    "gn:feature_class":"P",
    "gn:feature_code":"PPL",
    "gn:name":"W\u012bs\u0101pur",
    "gn:population":0,
    "gn:timezone":"Asia/Kolkata",
    "iso:country":"IN",
    "wof:name":"Wisapur",
    "wof:placetype":"locality"
},
  "geometry": {"coordinates":[79.2723,20.22372],"type":"Point"}
}