{
  "type": "Feature",
  "properties": {
    "iso:country":"IN",
    "ks:ks_name":"Umarpur Khurd Diyara Khas",
    "ks:ks_pop":0,
    "ks:ks_type":"VILLAGE",
    "name:eng_x_preferred":[
        "Umarpur Khurd Diyara Khas"
    ],
    "wof:name":"Umarpur Khurd Diyara Khas",
    "wof:placetype":"locality",
    "wof:population":0
},
  "geometry": {"coordinates":[84.04473299999999,25.648561],"type":"Point"}
}