{
  "type": "Feature",
  "properties": {
    "gn:admin1_code":"10.0",
    "gn:admin2_code":"072",
    "gn:asciiname":"Baraunda",
    "gn:country_code":"IN",
    "gn:dem":264,
    "gn:feature_class":"P",
    "gn:feature_code":"PPL",
    "gn:name":"Baraunda",
    "gn:population":0,
    "gn:timezone":"Asia/Kolkata",
    "iso:country":"IN",
    "wof:name":"Baraunda",
    "wof:placetype":"locality"
},
  "geometry": {"coordinates":[77.05933,29.95746],"type":"Point"}
}