{
  "type": "Feature",
  "properties": {
    "gn:admin1_code":"37.0",
    "gn:admin2_code":"409.0",
    "gn:asciiname":"Patharri Khurd",
    "gn:country_code":"IN",
    "gn:dem":305,
    "gn:feature_class":"P",
    "gn:feature_code":"PPL",
    "gn:name":"Patharri Khurd",
    "gn:population":0,
    "gn:timezone":"Asia/Kolkata",
    "iso:country":"IN",
    "name:eng_x_preferred":[
        "Patharri Khurd"
    ],
    "wof:name":"Patharri Khurd",
    "wof:placetype":"locality"
},
  "geometry": {"coordinates":[81.18046,21.5931],"type":"Point"}
}