{
  "type": "Feature",
  "properties": {
    "iso:country":"IN",
    "ks:ks_name":"Kudkulli",
    "ks:ks_pop":94,
    "ks:ks_type":"HABITATION",
    "name:eng_x_preferred":[
        "Kudkulli"
    ],
    "wof:name":"Kudkulli",
    "wof:placetype":"locality",
    "wof:population":94
},
  "geometry": {"coordinates":[75.530556,12.396944],"type":"Point"}
}