{
  "type": "Feature",
  "properties": {
    "iso:country":"IN",
    "ks:ks_name":"Asanbani",
    "ks:ks_pop":248,
    "ks:ks_type":"HABITATION",
    "name:eng_x_preferred":[
        "Asanbani"
    ],
    "wof:name":"Asanbani",
    "wof:placetype":"locality",
    "wof:population":248
},
  "geometry": {"coordinates":[86.82107999999999,22.597088],"type":"Point"}
}