{
  "type": "Feature",
  "properties": {
    "iso:country":"IN",
    "ks:ks_name":"Muslimwadi",
    "ks:ks_pop":155,
    "ks:ks_type":"HABITATION",
    "name:eng_x_preferred":[
        "Muslimwadi"
    ],
    "wof:name":"Muslimwadi",
    "wof:placetype":"locality",
    "wof:population":155
},
  "geometry": {"coordinates":[73.329882,16.813096],"type":"Point"}
}