{
  "type": "Feature",
  "properties": {
    "iso:country":"IN",
    "ks:ks_name":"Horeag",
    "ks:ks_pop":1101,
    "ks:ks_type":"HABITATION",
    "name:eng_x_preferred":[
        "Horeag"
    ],
    "wof:name":"Horeag",
    "wof:placetype":"locality",
    "wof:population":1101
},
  "geometry": {"coordinates":[85.34887000000001,23.55386],"type":"Point"}
}