{
  "type": "Feature",
  "properties": {
    "gn:admin1_code":"19.0",
    "gn:admin2_code":"568.0",
    "gn:asciiname":"Muttavalli",
    "gn:country_code":"IN",
    "gn:dem":645,
    "gn:feature_class":"P",
    "gn:feature_code":"PPL",
    "gn:name":"Muttavalli",
    "gn:population":0,
    "gn:timezone":"Asia/Kolkata",
    "iso:country":"IN",
    "ks:ks_name":"Muttavalli",
    "ks:ks_type":"VILLAGE",
    "name:eng_x_preferred":[
        "Muttavalli"
    ],
    "wof:name":"Muttavalli",
    "wof:placetype":"locality"
},
  "geometry": {"coordinates":[75.20725899999999,13.615005],"type":"Point"}
}