{
  "type": "Feature",
  "properties": {
    "gn:admin1_code":"19.0",
    "gn:admin2_code":"568.0",
    "gn:asciiname":"Muttavalli",
    "gn:country_code":"IN",
    "gn:dem":645,
    "gn:feature_class":"P",
    "gn:feature_code":"PPL",
    "gn:name":"Muttavalli",
    "gn:population":0,
    "gn:timezone":"Asia/Kolkata",
    "iso:country":"IN",
    "wof:name":"Muttavalli",
    "wof:placetype":"locality"
},
  "geometry": {"coordinates":[75.20725999999998,13.61501],"type":"Point"}
}