{
  "type": "Feature",
  "properties": {
    "iso:country":"IN",
    "ks:ks_name":"Mukunda",
    "ks:ks_pop":552,
    "ks:ks_type":"HABITATION",
    "name:eng_x_preferred":[
        "Mukunda"
    ],
    "wof:name":"Mukunda",
    "wof:placetype":"locality",
    "wof:population":552
},
  "geometry": {"coordinates":[86.889049,24.5807],"type":"Point"}
}