{
  "type": "Feature",
  "properties": {
    "gn:admin1_code":"12.0",
    "gn:admin2_code":"6.0",
    "gn:asciiname":"Kunala",
    "gn:country_code":"IN",
    "gn:dem":1458,
    "gn:feature_class":"P",
    "gn:feature_code":"PPL",
    "gn:name":"K\u016bn\u0101la",
    "gn:population":0,
    "gn:timezone":"Asia/Kolkata",
    "iso:country":"IN",
    "name:hin_x_preferred":[
        "\u0915\u0941\u0923\u093e\u0932"
    ],
    "name:ind_x_preferred":[
        "Kunala"
    ],
    "name:kor_x_preferred":[
        "\ucfe0\ub0a0\ub77c"
    ],
    "name:mal_x_preferred":[
        "\u0d15\u0d41\u0d23\u0d3e\u0d7d"
    ],
    "name:mar_x_preferred":[
        "\u0915\u0941\u0923\u093e\u0932"
    ],
    "name:tam_x_preferred":[
        "\u0b95\u0bc1\u0ba3\u0bbe\u0bb3\u0ba9\u0bcd"
    ],
    "name:tha_x_preferred":[
        "\u0e40\u0e08\u0e49\u0e32\u0e0a\u0e32\u0e22\u0e01\u0e38\u0e13\u0e32\u0e25\u0e30"
    ],
    "wof:name":"Kunala",
    "wof:placetype":"locality"
},
  "geometry": {"coordinates":[74.59144999999999,33.30754],"type":"Point"}
}