{
  "type": "Feature",
  "properties": {
    "iso:country":"IN",
    "ks:ks_name":"Karoli",
    "ks:ks_pop":560,
    "ks:ks_type":"VILLAGE",
    "name:eng_x_preferred":[
        "Karoli"
    ],
    "wof:name":"Karoli",
    "wof:placetype":"locality",
    "wof:population":560
},
  "geometry": {"coordinates":[74.691147,23.984692],"type":"Point"}
}