{
  "type": "Feature",
  "properties": {
    "iso:country":"IN",
    "ks:ks_name":"Nagpara",
    "ks:ks_pop":2983,
    "ks:ks_type":"VILLAGE",
    "ks:ks_uagg_main":0,
    "name:eng_x_preferred":[
        "Nagpara"
    ],
    "wof:name":"Nagpara",
    "wof:placetype":"neighbourhood",
    "wof:population":2983
},
  "geometry": {"coordinates":[88.29053999999999,24.115804],"type":"Point"}
}