{
  "type": "Feature",
  "properties": {
    "gn:admin1_code":"09",
    "gn:admin2_code":"471.0",
    "gn:asciiname":"Sipor",
    "gn:country_code":"IN",
    "gn:dem":178,
    "gn:feature_class":"P",
    "gn:feature_code":"PPL",
    "gn:name":"S\u012bpor",
    "gn:population":0,
    "gn:timezone":"Asia/Kolkata",
    "iso:country":"IN",
    "name:und_x_variant":[
        "S\u012bpor",
        "Sipur"
    ],
    "wof:name":"Sipor",
    "wof:placetype":"locality"
},
  "geometry": {"coordinates":[72.66795999999999,23.84676],"type":"Point"}
}