{
  "type": "Feature",
  "properties": {
    "gn:admin1_code":"12.0",
    "gn:admin2_code":"002",
    "gn:asciiname":"Bopat",
    "gn:country_code":"IN",
    "gn:dem":1835,
    "gn:feature_class":"P",
    "gn:feature_code":"PPL",
    "gn:name":"Bopat",
    "gn:population":0,
    "gn:timezone":"Asia/Kolkata",
    "iso:country":"IN",
    "wof:name":"Bopat",
    "wof:placetype":"locality"
},
  "geometry": {"coordinates":[74.64171999999998,34.00594],"type":"Point"}
}