{
  "type": "Feature",
  "properties": {
    "iso:country":"IN",
    "ks:ks_name":"Charandas Chak",
    "ks:ks_pop":1041,
    "ks:ks_type":"VILLAGE",
    "name:eng_x_preferred":[
        "Charandas Chak"
    ],
    "wof:name":"Charandas Chak",
    "wof:placetype":"locality",
    "wof:population":1041
},
  "geometry": {"coordinates":[87.749971,22.244205],"type":"Point"}
}