{
  "type": "Feature",
  "properties": {
    "iso:country":"IN",
    "ks:ks_name":"Dabhadi",
    "ks:ks_pop":273,
    "ks:ks_type":"HABITATION",
    "name:eng_x_preferred":[
        "Dabhadi"
    ],
    "wof:name":"Dabhadi",
    "wof:placetype":"locality",
    "wof:population":273
},
  "geometry": {"coordinates":[73.68440200000001,15.914899],"type":"Point"}
}