{
  "type": "Feature",
  "properties": {
    "iso:country":"IN",
    "ks:ks_name":"Bhramarajod",
    "ks:ks_pop":135,
    "ks:ks_type":"VILLAGE",
    "name:eng_x_preferred":[
        "Bhramarajod"
    ],
    "wof:name":"Bhramarajod",
    "wof:placetype":"locality",
    "wof:population":135
},
  "geometry": {"coordinates":[82.96205999999999,19.39993],"type":"Point"}
}