{
  "type": "Feature",
  "properties": {
    "gn:admin1_code":"36.0",
    "gn:admin2_code":"175.0",
    "gn:asciiname":"Chak Pura Khurd",
    "gn:country_code":"IN",
    "gn:dem":98,
    "gn:feature_class":"P",
    "gn:feature_code":"PPL",
    "gn:name":"Chak Pura Khurd",
    "gn:population":0,
    "gn:timezone":"Asia/Kolkata",
    "iso:country":"IN",
    "name:und_x_variant":[
        "Miy\u0101n ka Pura"
    ],
    "wof:name":"Chak Pura Khurd",
    "wof:placetype":"neighbourhood"
},
  "geometry": {"coordinates":[81.88113,25.34102],"type":"Point"}
}