{
  "type": "Feature",
  "properties": {
    "iso:country":"IN",
    "ks:ks_alt_nam":"GHRIT KUNDALI",
    "ks:ks_name":"Ghrit Kundali",
    "ks:ks_pop":899,
    "ks:ks_type":"HABITATION",
    "name:eng_x_preferred":[
        "Ghrit Kundali"
    ],
    "wof:name":"Ghrit Kundali",
    "wof:placetype":"locality",
    "wof:population":899
},
  "geometry": {"coordinates":[86.097087,26.27512],"type":"Point"}
}