{
  "type": "Feature",
  "properties": {
    "iso:country":"IN",
    "ks:ks_name":"Majhapada",
    "ks:ks_pop":95,
    "ks:ks_type":"HABITATION",
    "name:eng_x_preferred":[
        "Majhapada"
    ],
    "wof:name":"Majhapada",
    "wof:placetype":"locality",
    "wof:population":95
},
  "geometry": {"coordinates":[84.594556,22.138581],"type":"Point"}
}