{
  "type": "Feature",
  "properties": {
    "gn:admin1_code":"25.0",
    "gn:admin2_code":"621.0",
    "gn:asciiname":"Kovilpatti",
    "gn:country_code":"IN",
    "gn:dem":57,
    "gn:feature_class":"P",
    "gn:feature_code":"PPL",
    "gn:name":"Kovilpatti",
    "gn:population":0,
    "gn:timezone":"Asia/Kolkata",
    "iso:country":"IN",
    "name:bpy_x_preferred":[
        "\u0995\u09cb\u09ac\u09bf\u09b2\u09aa\u09be\u09a4\u09cd\u09a4\u09bf"
    ],
    "name:ceb_x_preferred":[
        "Kovilpatti"
    ],
    "name:ita_x_preferred":[
        "Kovilpatti"
    ],
    "name:mlg_x_preferred":[
        "Kovilpatti"
    ],
    "name:msa_x_preferred":[
        "Kovilpatti"
    ],
    "name:new_x_preferred":[
        "\u0915\u094b\u092d\u093f\u0932\u092a\u091f\u094d\u091f\u0940"
    ],
    "name:pam_x_preferred":[
        "Kovilpatti"
    ],
    "name:spa_x_preferred":[
        "Kovilpatti"
    ],
    "name:swe_x_preferred":[
        "Kovilpatti"
    ],
    "name:tam_x_preferred":[
        "\u0b95\u0bcb\u0bb5\u0bbf\u0bb2\u0bcd\u0baa\u0b9f\u0bcd\u0b9f\u0bbf"
    ],
    "name:vie_x_preferred":[
        "Kovilpatti"
    ],
    "name:zho_x_preferred":[
        "\u79d1\u7ef4\u5c14\u5e15\u8482"
    ],
    "wof:name":"Kovilpatti",
    "wof:placetype":"locality"
},
  "geometry": {"coordinates":[79.12668000000002,10.60636],"type":"Point"}
}