{
  "type": "Feature",
  "properties": {
    "gn:admin1_code":"25.0",
    "gn:admin2_code":"621.0",
    "gn:asciiname":"Kovilpatti",
    "gn:country_code":"IN",
    "gn:dem":57,
    "gn:feature_class":"P",
    "gn:feature_code":"PPL",
    "gn:name":"Kovilpatti",
    "gn:population":0,
    "gn:timezone":"Asia/Kolkata",
    "iso:country":"IN",
    "wof:name":"Kovilpatti",
    "wof:placetype":"locality"
},
  "geometry": {"coordinates":[79.12668000000002,10.60636],"type":"Point"}
}