{
  "type": "Feature",
  "properties": {
    "iso:country":"IN",
    "ks:ks_name":"Bangalbigha",
    "ks:ks_pop":426,
    "ks:ks_type":"HABITATION",
    "name:eng_x_preferred":[
        "Bangalbigha"
    ],
    "wof:name":"Bangalbigha",
    "wof:placetype":"locality",
    "wof:population":426
},
  "geometry": {"coordinates":[85.033817,24.728168],"type":"Point"}
}