{
  "type": "Feature",
  "properties": {
    "gn:admin1_code":"39",
    "gn:admin2_code":"61.0",
    "gn:asciiname":"Kota",
    "gn:country_code":"IN",
    "gn:dem":1313,
    "gn:feature_class":"P",
    "gn:feature_code":"PPL",
    "gn:name":"Kota",
    "gn:population":0,
    "gn:timezone":"Asia/Kolkata",
    "iso:country":"IN",
    "wof:name":"Kota",
    "wof:placetype":"locality"
},
  "geometry": {"coordinates":[78.86593000000001,30.01674],"type":"Point"}
}