{
  "type": "Feature",
  "properties": {
    "iso:country":"IN",
    "ks:ks_name":"Rambakkam",
    "ks:ks_pop":1245,
    "ks:ks_type":"HABITATION",
    "name:eng_x_preferred":[
        "Rambakkam"
    ],
    "wof:name":"Rambakkam",
    "wof:placetype":"locality",
    "wof:population":1245
},
  "geometry": {"coordinates":[79.610052,11.829572],"type":"Point"}
}