{
  "type": "Feature",
  "properties": {
    "iso:country":"IN",
    "ks:ks_name":"Amaravathi",
    "ks:ks_pop":98,
    "ks:ks_type":"HABITATION",
    "name:eng_x_preferred":[
        "Amaravathi"
    ],
    "wof:name":"Amaravathi",
    "wof:placetype":"locality",
    "wof:population":98
},
  "geometry": {"coordinates":[75.59821100000001,13.12351],"type":"Point"}
}