{
  "type": "Feature",
  "properties": {
    "iso:country":"IN",
    "ks:ks_alt_nam":"khon pur wa",
    "ks:ks_name":"Khon Pur Wa",
    "ks:ks_pop":80,
    "ks:ks_type":"HABITATION",
    "name:eng_x_preferred":[
        "Khon Pur Wa"
    ],
    "wof:name":"Khon Pur Wa",
    "wof:placetype":"locality",
    "wof:population":80
},
  "geometry": {"coordinates":[81.64476999999999,27.37265],"type":"Point"}
}