{
  "type": "Feature",
  "properties": {
    "gn:admin1_code":"10.0",
    "gn:admin2_code":"085",
    "gn:asciiname":"Bikaner",
    "gn:country_code":"IN",
    "gn:dem":238,
    "gn:feature_class":"P",
    "gn:feature_code":"PPL",
    "gn:name":"B\u012bkaner",
    "gn:population":0,
    "gn:timezone":"Asia/Kolkata",
    "iso:country":"IN",
    "name:und_x_variant":[
        "B\u012bkaner",
        "Bik\u0101ner"
    ],
    "wof:name":"Bikaner",
    "wof:placetype":"locality"
},
  "geometry": {"coordinates":[76.61005,28.2555],"type":"Point"}
}