{
  "type": "Feature",
  "properties": {
    "gn:admin1_code":"19.0",
    "gn:admin2_code":"583.0",
    "gn:asciiname":"Bolamaranhalli",
    "gn:country_code":"IN",
    "gn:dem":913,
    "gn:feature_class":"P",
    "gn:feature_code":"PPL",
    "gn:name":"Bolam\u0101ranhalli",
    "gn:population":0,
    "gn:timezone":"Asia/Kolkata",
    "iso:country":"IN",
    "wof:name":"Bolamaranhalli",
    "wof:placetype":"locality"
},
  "geometry": {"coordinates":[77.39754000000001,13.16056],"type":"Point"}
}