{
  "type": "Feature",
  "properties": {
    "iso:country":"IN",
    "ks:ks_name":"Sonbarsa",
    "ks:ks_pop":43,
    "ks:ks_type":"VILLAGE",
    "ks:ks_uagg_main":0,
    "name:eng_x_preferred":[
        "Sonbarsa"
    ],
    "wof:name":"Sonbarsa",
    "wof:placetype":"locality",
    "wof:population":43
},
  "geometry": {"coordinates":[82.549218,25.180239],"type":"Point"}
}