{
  "type": "Feature",
  "properties": {
    "iso:country":"IN",
    "ks:ks_alt_nam":"Katirail TE",
    "ks:ks_name":"Katirail Te",
    "ks:ks_pop":1254,
    "ks:ks_type":"HABITATION",
    "name:eng_x_preferred":[
        "Katirail Te"
    ],
    "wof:name":"Katirail Te",
    "wof:placetype":"locality",
    "wof:population":1254
},
  "geometry": {"coordinates":[92.588808,24.931736],"type":"Point"}
}