{
  "type": "Feature",
  "properties": {
    "gn:admin1_code":"35",
    "gn:admin2_code":"455.0",
    "gn:asciiname":"Piparpani",
    "gn:country_code":"IN",
    "gn:dem":929,
    "gn:feature_class":"P",
    "gn:feature_code":"PPL",
    "gn:name":"P\u012bparp\u0101ni",
    "gn:population":0,
    "gn:timezone":"Asia/Kolkata",
    "iso:country":"IN",
    "wof:name":"Piparpani",
    "wof:placetype":"locality"
},
  "geometry": {"coordinates":[78.9984,22.36814],"type":"Point"}
}