{
  "type": "Feature",
  "properties": {
    "gn:admin1_code":"35.0",
    "gn:admin2_code":"450.0",
    "gn:asciiname":"Marwa",
    "gn:country_code":"IN",
    "gn:dem":344,
    "gn:feature_class":"P",
    "gn:feature_code":"PPL",
    "gn:name":"Marwa",
    "gn:population":0,
    "gn:timezone":"Asia/Kolkata",
    "iso:country":"IN",
    "name:ara_x_preferred":[
        "\u0645\u0631\u0648\u0649"
    ],
    "name:ceb_x_preferred":[
        "Marwa"
    ],
    "name:deu_x_preferred":[
        "Marwa"
    ],
    "name:rus_x_preferred":[
        "\u041c\u0430\u0440\u0432\u0430"
    ],
    "name:swe_x_preferred":[
        "Marwa"
    ],
    "wof:name":"Marwa",
    "wof:placetype":"locality"
},
  "geometry": {"coordinates":[80.83543,23.98305],"type":"Point"}
}