{
  "type": "Feature",
  "properties": {
    "iso:country":"IN",
    "ks:ks_name":"Lama Gumba Forest",
    "ks:ks_pop":9,
    "ks:ks_type":"VILLAGE",
    "name:eng_x_preferred":[
        "Lama Gumba Forest"
    ],
    "wof:name":"Lama Gumba Forest",
    "wof:placetype":"locality",
    "wof:population":9
},
  "geometry": {"coordinates":[88.310975,26.821481],"type":"Point"}
}