{
  "type": "Feature",
  "properties": {
    "gn:admin1_code":"35",
    "gn:admin2_code":"451.0",
    "gn:asciiname":"Gangajali",
    "gn:country_code":"IN",
    "gn:dem":378,
    "gn:feature_class":"P",
    "gn:feature_code":"PPL",
    "gn:name":"Gang\u0101jali",
    "gn:population":0,
    "gn:timezone":"Asia/Kolkata",
    "iso:country":"IN",
    "ks:ks_alt_nam":"Gang\u0101jali",
    "ks:ks_name":"Gangajali",
    "ks:ks_pop":41,
    "ks:ks_type":"VILLAGE",
    "name:eng_x_preferred":[
        "Gangajali"
    ],
    "name:eng_x_variant":[
        "Gang\u0101jali"
    ],
    "wof:name":"Gangajali",
    "wof:placetype":"locality",
    "wof:population":41
},
  "geometry": {"coordinates":[79.865286,23.301509],"type":"Point"}
}