{
  "type": "Feature",
  "properties": {
    "gn:admin1_code":"23.0",
    "gn:admin2_code":"43.0",
    "gn:asciiname":"Sharf Ali Shahwala",
    "gn:country_code":"IN",
    "gn:dem":214,
    "gn:feature_class":"P",
    "gn:feature_code":"PPL",
    "gn:name":"Sharf Ali Sh\u0101hw\u0101la",
    "gn:population":0,
    "gn:timezone":"Asia/Kolkata",
    "iso:country":"IN",
    "wof:name":"Sharf Ali Shahwala",
    "wof:placetype":"locality"
},
  "geometry": {"coordinates":[75.10484,31.08211],"type":"Point"}
}