{
  "type": "Feature",
  "properties": {
    "iso:country":"IN",
    "ks:ks_alt_nam":"chacherwa",
    "ks:ks_name":"Chacherwa",
    "ks:ks_pop":215,
    "ks:ks_type":"HABITATION",
    "name:eng_x_preferred":[
        "Chacherwa"
    ],
    "wof:name":"Chacherwa",
    "wof:placetype":"locality",
    "wof:population":215
},
  "geometry": {"coordinates":[81.407735,27.446107],"type":"Point"}
}