{
  "type": "Feature",
  "properties": {
    "iso:country":"IN",
    "ks:ks_name":"Igalamakki",
    "ks:ks_pop":17,
    "ks:ks_type":"HABITATION",
    "name:eng_x_preferred":[
        "Igalamakki"
    ],
    "wof:name":"Igalamakki",
    "wof:placetype":"locality",
    "wof:population":17
},
  "geometry": {"coordinates":[75.372586,12.67162],"type":"Point"}
}