{
  "type": "Feature",
  "properties": {
    "gn:admin1_code":"30",
    "gn:admin2_code":"247.0",
    "gn:asciiname":"Tangmaolia",
    "gn:country_code":"IN",
    "gn:dem":1278,
    "gn:feature_class":"P",
    "gn:feature_code":"PPL",
    "gn:name":"Tangmaolia",
    "gn:population":0,
    "gn:timezone":"Asia/Kolkata",
    "iso:country":"IN",
    "wof:name":"Tangmaolia",
    "wof:placetype":"locality"
},
  "geometry": {"coordinates":[93.03333000000001,27.28333],"type":"Point"}
}