{
  "type": "Feature",
  "properties": {
    "iso:country":"IN",
    "ks:ks_name":"Palahipur",
    "ks:ks_pop":65,
    "ks:ks_type":"VILLAGE",
    "name:eng_x_preferred":[
        "Palahipur"
    ],
    "wof:name":"Palahipur",
    "wof:placetype":"locality",
    "wof:population":65
},
  "geometry": {"coordinates":[82.691867,25.028956],"type":"Point"}
}