{
  "type": "Feature",
  "properties": {
    "iso:country":"IN",
    "ks:ks_name":"Indaun",
    "ks:ks_pop":693,
    "ks:ks_type":"VILLAGE",
    "name:eng_x_preferred":[
        "Indaun"
    ],
    "wof:name":"Indaun",
    "wof:placetype":"locality",
    "wof:population":693
},
  "geometry": {"coordinates":[77.50317800000001,26.791747],"type":"Point"}
}