{
  "type": "Feature",
  "properties": {
    "iso:country":"IN",
    "ks:ks_name":"Salguri",
    "ks:ks_pop":503,
    "ks:ks_type":"HABITATION",
    "name:eng_x_preferred":[
        "Salguri"
    ],
    "wof:name":"Salguri",
    "wof:placetype":"locality",
    "wof:population":503
},
  "geometry": {"coordinates":[90.418587,26.759159],"type":"Point"}
}