{
  "type": "Feature",
  "properties": {
    "gn:admin1_code":"36",
    "gn:admin2_code":"179.0",
    "gn:asciiname":"Udharanpur",
    "gn:country_code":"IN",
    "gn:dem":95,
    "gn:feature_class":"P",
    "gn:feature_code":"PPL",
    "gn:name":"Udharanpur",
    "gn:population":0,
    "gn:timezone":"Asia/Kolkata",
    "iso:country":"IN",
    "ks:ks_name":"Udharan Pur",
    "ks:ks_pop":484,
    "ks:ks_type":"VILLAGE",
    "ks:ks_uagg_main":0,
    "name:eng_x_preferred":[
        "Udharan Pur"
    ],
    "wof:name":"Udharan Pur",
    "wof:placetype":"neighbourhood",
    "wof:population":484
},
  "geometry": {"coordinates":[82.240015,26.061139],"type":"Point"}
}