{
  "type": "Feature",
  "properties": {
    "gn:admin1_code":"11",
    "gn:admin2_code":"23.0",
    "gn:asciiname":"Chachal Adwar",
    "gn:country_code":"IN",
    "gn:dem":2484,
    "gn:feature_class":"P",
    "gn:feature_code":"PPL",
    "gn:name":"Chachal Adw\u0101r",
    "gn:population":0,
    "gn:timezone":"Asia/Kolkata",
    "iso:country":"IN",
    "wof:name":"Chachal Adwar",
    "wof:placetype":"locality"
},
  "geometry": {"coordinates":[76.08698000000003,32.85921],"type":"Point"}
}