{
  "type": "Feature",
  "properties": {
    "iso:country":"IN",
    "ks:ks_alt_nam":"PATHARKAT PURWA",
    "ks:ks_name":"Patharkat Purwa",
    "ks:ks_pop":80,
    "ks:ks_type":"HABITATION",
    "ks:ks_uagg_main":0,
    "name:eng_x_preferred":[
        "Patharkat Purwa"
    ],
    "wof:name":"Patharkat Purwa",
    "wof:placetype":"neighbourhood",
    "wof:population":80
},
  "geometry": {"coordinates":[81.610388,27.350562],"type":"Point"}
}