{
  "type": "Feature",
  "properties": {
    "iso:country":"IN",
    "ks:ks_name":"Agaljaddi",
    "ks:ks_pop":24,
    "ks:ks_type":"HABITATION",
    "name:eng_x_preferred":[
        "Agaljaddi"
    ],
    "wof:name":"Agaljaddi",
    "wof:placetype":"locality",
    "wof:population":24
},
  "geometry": {"coordinates":[74.773596,14.895145],"type":"Point"}
}