{
  "type": "Feature",
  "properties": {
    "iso:country":"IN",
    "ks:ks_name":"Harijan Basti",
    "ks:ks_pop":67,
    "ks:ks_type":"HABITATION",
    "name:eng_x_preferred":[
        "Harijan Basti"
    ],
    "wof:name":"Harijan Basti",
    "wof:placetype":"locality",
    "wof:population":67
},
  "geometry": {"coordinates":[83.06440000000001,25.0436],"type":"Point"}
}