{
  "type": "Feature",
  "properties": {
    "iso:country":"IN",
    "ks:ks_name":"Palsankarwadi",
    "ks:ks_pop":659,
    "ks:ks_type":"HABITATION",
    "name:eng_x_preferred":[
        "Palsankarwadi"
    ],
    "wof:name":"Palsankarwadi",
    "wof:placetype":"locality",
    "wof:population":659
},
  "geometry": {"coordinates":[73.502792,16.757717],"type":"Point"}
}