{
  "type": "Feature",
  "properties": {
    "iso:country":"IN",
    "ks:ks_name":"Maheshpur",
    "ks:ks_pop":3234,
    "ks:ks_type":"HABITATION",
    "name:eng_x_preferred":[
        "Maheshpur"
    ],
    "wof:name":"Maheshpur",
    "wof:placetype":"locality",
    "wof:population":3234
},
  "geometry": {"coordinates":[86.245482,23.781171],"type":"Point"}
}