{
  "type": "Feature",
  "properties": {
    "iso:country":"IN",
    "ks:ks_name":"Subrao Jadhav Wasti",
    "ks:ks_pop":120,
    "ks:ks_type":"HABITATION",
    "name:eng_x_preferred":[
        "Subrao Jadhav Wasti"
    ],
    "wof:name":"Subrao Jadhav Wasti",
    "wof:placetype":"locality",
    "wof:population":120
},
  "geometry": {"coordinates":[74.418582,17.130054],"type":"Point"}
}