{
  "type": "Feature",
  "properties": {
    "iso:country":"IN",
    "ks:ks_name":"Taklana",
    "ks:ks_pop":22,
    "ks:ks_type":"VILLAGE",
    "name:eng_x_preferred":[
        "Taklana"
    ],
    "wof:name":"Taklana",
    "wof:placetype":"locality",
    "wof:population":22
},
  "geometry": {"coordinates":[78.673537,30.017581],"type":"Point"}
}