{
  "type": "Feature",
  "properties": {
    "iso:country":"IN",
    "ks:ks_name":"Upper Goke",
    "ks:ks_pop":1241,
    "ks:ks_type":"HABITATION",
    "name:eng_x_preferred":[
        "Upper Goke"
    ],
    "wof:name":"Upper Goke",
    "wof:placetype":"locality",
    "wof:population":1241
},
  "geometry": {"coordinates":[88.22996500000001,27.105141],"type":"Point"}
}