{
  "type": "Feature",
  "properties": {
    "gn:admin1_code":"23.0",
    "gn:admin2_code":"49.0",
    "gn:asciiname":"Khasa",
    "gn:country_code":"IN",
    "gn:dem":220,
    "gn:feature_class":"P",
    "gn:feature_code":"PPL",
    "gn:name":"Kh\u0101sa",
    "gn:population":0,
    "gn:timezone":"Asia/Kolkata",
    "iso:country":"IN",
    "name:swe_x_preferred":[
        "Khasa"
    ],
    "wof:name":"Khasa",
    "wof:placetype":"locality"
},
  "geometry": {"coordinates":[74.71285999999998,31.61588],"type":"Point"}
}