{
  "type": "Feature",
  "properties": {
    "iso:country":"IN",
    "ks:ks_name":"Budhawadi",
    "ks:ks_pop":150,
    "ks:ks_type":"HABITATION",
    "name:eng_x_preferred":[
        "Budhawadi"
    ],
    "wof:name":"Budhawadi",
    "wof:placetype":"locality",
    "wof:population":150
},
  "geometry": {"coordinates":[73.210048,18.108981],"type":"Point"}
}