{
  "type": "Feature",
  "properties": {
    "gn:admin1_code":"35.0",
    "gn:admin2_code":"452.0",
    "gn:asciiname":"Sangai",
    "gn:country_code":"IN",
    "gn:dem":331,
    "gn:feature_class":"P",
    "gn:feature_code":"PPL",
    "gn:name":"S\u0101ngai",
    "gn:population":0,
    "gn:timezone":"Asia/Kolkata",
    "iso:country":"IN",
    "name:hin_x_preferred":[
        "\u0938\u0902\u0917\u0948"
    ],
    "name:mal_x_preferred":[
        "\u0d38\u0d3e\u0d02\u0d17\u0d3e\u0d2f\u0d4d"
    ],
    "name:tam_x_preferred":[
        "\u0b9a\u0b99\u0bcd\u0b95\u0bbe\u0baf\u0bcd \u0bae\u0bbe\u0ba9\u0bcd"
    ],
    "name:tha_x_preferred":[
        "\u0e0b\u0e31\u0e19\u0e44\u0e01"
    ],
    "wof:name":"Sangai",
    "wof:placetype":"locality"
},
  "geometry": {"coordinates":[78.76564999999999,22.9489],"type":"Point"}
}