{
  "type": "Feature",
  "properties": {
    "iso:country":"IN",
    "ks:ks_name":"Butchampadu",
    "ks:ks_pop":55,
    "ks:ks_type":"HABITATION",
    "name:eng_x_preferred":[
        "Butchampadu"
    ],
    "wof:name":"Butchampadu",
    "wof:placetype":"locality",
    "wof:population":55
},
  "geometry": {"coordinates":[83.057712,18.438893],"type":"Point"}
}