{
  "type": "Feature",
  "properties": {
    "iso:country":"IN",
    "ks:ks_name":"Tolsandi",
    "ks:ks_pop":170,
    "ks:ks_type":"HABITATION",
    "name:eng_x_preferred":[
        "Tolsandi"
    ],
    "wof:name":"Tolsandi",
    "wof:placetype":"locality",
    "wof:population":170
},
  "geometry": {"coordinates":[85.51611200000001,23.159733],"type":"Point"}
}