{
  "type": "Feature",
  "properties": {
    "gn:admin1_code":"11",
    "gn:admin2_code":"23.0",
    "gn:asciiname":"Palahka Dramman",
    "gn:country_code":"IN",
    "gn:dem":1245,
    "gn:feature_class":"P",
    "gn:feature_code":"PPL",
    "gn:name":"Palahka Dramman",
    "gn:population":0,
    "gn:timezone":"Asia/Kolkata",
    "iso:country":"IN",
    "wof:name":"Palahka Dramman",
    "wof:placetype":"locality"
},
  "geometry": {"coordinates":[76.15323000000002,32.29028],"type":"Point"}
}