{
  "type": "Feature",
  "properties": {
    "iso:country":"IN",
    "ks:ks_alt_nam":"SHIVANAND WASTI",
    "ks:ks_name":"Shivanand Wasti",
    "ks:ks_pop":117,
    "ks:ks_type":"HABITATION",
    "name:eng_x_preferred":[
        "Shivanand Wasti"
    ],
    "wof:name":"Shivanand Wasti",
    "wof:placetype":"locality",
    "wof:population":117
},
  "geometry": {"coordinates":[75.477408,17.063875],"type":"Point"}
}