{
  "type": "Feature",
  "properties": {
    "iso:country":"IN",
    "ks:ks_name":"Nana Kantva",
    "ks:ks_pop":694,
    "ks:ks_type":"VILLAGE",
    "name:eng_x_preferred":[
        "Nana Kantva"
    ],
    "wof:name":"Nana Kantva",
    "wof:placetype":"locality",
    "wof:population":694
},
  "geometry": {"coordinates":[73.771134,22.398371],"type":"Point"}
}