{
  "type": "Feature",
  "properties": {
    "gn:admin1_code":"21.0",
    "gn:admin2_code":"396.0",
    "gn:asciiname":"Chekka",
    "gn:country_code":"IN",
    "gn:dem":834,
    "gn:feature_class":"P",
    "gn:feature_code":"PPL",
    "gn:name":"Chekka",
    "gn:population":0,
    "gn:timezone":"Asia/Kolkata",
    "iso:country":"IN",
    "name:ara_x_preferred":[
        "\u0634\u0643\u0627"
    ],
    "name:fas_x_preferred":[
        "\u0634\u06a9\u0627"
    ],
    "name:fra_x_preferred":[
        "Chekka"
    ],
    "name:heb_x_preferred":[
        "\u05e9\u05db\u05d0"
    ],
    "name:ita_x_preferred":[
        "Chekka"
    ],
    "name:nno_x_preferred":[
        "Chekka"
    ],
    "name:nor_x_preferred":[
        "Chekka"
    ],
    "name:pol_x_preferred":[
        "Szikka"
    ],
    "wof:name":"Chekka",
    "wof:placetype":"locality"
},
  "geometry": {"coordinates":[83.21758,19.04442],"type":"Point"}
}