{
  "type": "Feature",
  "properties": {
    "gn:admin1_code":"19.0",
    "gn:admin2_code":"568.0",
    "gn:asciiname":"Nandikale",
    "gn:country_code":"IN",
    "gn:dem":642,
    "gn:feature_class":"P",
    "gn:feature_code":"PPL",
    "gn:name":"Nandikale",
    "gn:population":0,
    "gn:timezone":"Asia/Kolkata",
    "iso:country":"IN",
    "ks:ks_name":"Nanditale",
    "ks:ks_pop":269,
    "ks:ks_type":"VILLAGE",
    "name:eng_x_preferred":[
        "Nanditale"
    ],
    "name:eng_x_variant":[
        "Nandikale"
    ],
    "wof:name":"Nanditale",
    "wof:placetype":"locality",
    "wof:population":269
},
  "geometry": {"coordinates":[75.13094700000001,14.112418],"type":"Point"}
}