{
  "type": "Feature",
  "properties": {
    "gn:admin1_code":"35",
    "gn:admin2_code":"452.0",
    "gn:asciiname":"Jharkhurpa",
    "gn:country_code":"IN",
    "gn:dem":382,
    "gn:feature_class":"P",
    "gn:feature_code":"PPL",
    "gn:name":"Jh\u0101rkhurpa",
    "gn:population":0,
    "gn:timezone":"Asia/Kolkata",
    "iso:country":"IN",
    "wof:name":"Jharkhurpa",
    "wof:placetype":"locality"
},
  "geometry": {"coordinates":[79.25264,22.87127000000001],"type":"Point"}
}