{
  "type": "Feature",
  "properties": {
    "iso:country":"IN",
    "ks:ks_alt_nam":"Shiv Charan ka Dera",
    "ks:ks_name":"Shiv Charan Ka Dera",
    "ks:ks_pop":113,
    "ks:ks_type":"HABITATION",
    "ks:ks_uagg_main":0,
    "name:eng_x_preferred":[
        "Shiv Charan Ka Dera"
    ],
    "wof:name":"Shiv Charan Ka Dera",
    "wof:placetype":"neighbourhood",
    "wof:population":113
},
  "geometry": {"coordinates":[80.611375,25.664022],"type":"Point"}
}