{
  "type": "Feature",
  "properties": {
    "iso:country":"IN",
    "ks:ks_name":"Pakariya",
    "ks:ks_pop":129,
    "ks:ks_type":"HABITATION",
    "ks:ks_uagg_main":0,
    "name:eng_x_preferred":[
        "Pakariya"
    ],
    "wof:name":"Pakariya",
    "wof:placetype":"neighbourhood",
    "wof:population":129
},
  "geometry": {"coordinates":[80.070274,27.420114],"type":"Point"}
}