{
  "type": "Feature",
  "properties": {
    "gn:admin1_code":"36",
    "gn:admin2_code":"188.0",
    "gn:asciiname":"Jadu Patti",
    "gn:country_code":"IN",
    "gn:dem":86,
    "gn:feature_class":"P",
    "gn:feature_code":"PPL",
    "gn:name":"J\u0101du Patti",
    "gn:population":0,
    "gn:timezone":"Asia/Kolkata",
    "iso:country":"IN",
    "ks:ks_alt_nam":"J\u0101du Patti",
    "ks:ks_name":"Jadu Patti",
    "ks:ks_type":"VILLAGE",
    "ks:ks_uagg_main":0,
    "name:eng_x_preferred":[
        "Jadu Patti"
    ],
    "name:eng_x_variant":[
        "J\u0101du Patti"
    ],
    "wof:name":"Jadu Patti",
    "wof:placetype":"neighbourhood"
},
  "geometry": {"coordinates":[83.201447,26.513584],"type":"Point"}
}