{
  "type": "Feature",
  "properties": {
    "gn:admin1_code":"36",
    "gn:admin2_code":"175.0",
    "gn:asciiname":"Chamrupur",
    "gn:country_code":"IN",
    "gn:dem":98,
    "gn:feature_class":"P",
    "gn:feature_code":"PPL",
    "gn:name":"Chamr\u016bpur",
    "gn:population":0,
    "gn:timezone":"Asia/Kolkata",
    "iso:country":"IN",
    "ks:ks_name":"Chamarupur",
    "ks:ks_pop":679,
    "ks:ks_type":"VILLAGE",
    "ks:ks_uagg_main":0,
    "name:eng_x_preferred":[
        "Chamarupur"
    ],
    "wof:name":"Chamarupur",
    "wof:placetype":"neighbourhood",
    "wof:population":679
},
  "geometry": {"coordinates":[82.003677,25.689933],"type":"Point"}
}