{
  "type": "Feature",
  "properties": {
    "iso:country":"IN",
    "ks:ks_alt_nam":"Oddi indulu",
    "ks:ks_name":"Oddi Indulu",
    "ks:ks_pop":97,
    "ks:ks_type":"HABITATION",
    "name:eng_x_preferred":[
        "Oddi Indulu"
    ],
    "wof:name":"Oddi Indulu",
    "wof:placetype":"locality",
    "wof:population":97
},
  "geometry": {"coordinates":[79.652075,13.293597],"type":"Point"}
}