{
  "type": "Feature",
  "properties": {
    "gn:admin1_code":"25.0",
    "gn:admin2_code":"611.0",
    "gn:asciiname":"Karakkalmund",
    "gn:country_code":"IN",
    "gn:dem":2036,
    "gn:feature_class":"P",
    "gn:feature_code":"PPL",
    "gn:name":"Karakkalmund",
    "gn:population":0,
    "gn:timezone":"Asia/Kolkata",
    "iso:country":"IN",
    "wof:name":"Karakkalmund",
    "wof:placetype":"locality"
},
  "geometry": {"coordinates":[76.55185,11.45191],"type":"Point"}
}