{
  "type": "Feature",
  "properties": {
    "gn:admin1_code":"34.0",
    "gn:admin2_code":"231.0",
    "gn:asciiname":"Sardha Singhtola",
    "gn:country_code":"IN",
    "gn:dem":64,
    "gn:feature_class":"P",
    "gn:feature_code":"PPL",
    "gn:name":"Sardha Singhtola",
    "gn:population":0,
    "gn:timezone":"Asia/Kolkata",
    "iso:country":"IN",
    "ks:ks_name":"Sardar Singh Tola",
    "ks:ks_pop":742,
    "ks:ks_type":"HABITATION",
    "name:eng_x_preferred":[
        "Sardar Singh Tola"
    ],
    "name:eng_x_variant":[
        "Sardha Singhtola"
    ],
    "wof:name":"Sardar Singh Tola",
    "wof:placetype":"locality",
    "wof:population":742
},
  "geometry": {"coordinates":[84.62576,25.656523],"type":"Point"}
}