{
  "type": "Feature",
  "properties": {
    "iso:country":"IN",
    "ks:ks_name":"Kodamalai Hosatty",
    "ks:ks_pop":204,
    "ks:ks_type":"HABITATION",
    "ks:ks_uagg_main":0,
    "name:eng_x_preferred":[
        "Kodamalai Hosatty"
    ],
    "wof:name":"Kodamalai Hosatty",
    "wof:placetype":"neighbourhood",
    "wof:population":204
},
  "geometry": {"coordinates":[76.82888199999999,11.370077],"type":"Point"}
}