{
  "type": "Feature",
  "properties": {
    "gn:admin1_code":"35",
    "gn:admin2_code":"462.0",
    "gn:asciiname":"Banjari",
    "gn:country_code":"IN",
    "gn:dem":359,
    "gn:feature_class":"P",
    "gn:feature_code":"PPL",
    "gn:name":"Banj\u0101ri",
    "gn:population":0,
    "gn:timezone":"Asia/Kolkata",
    "iso:country":"IN",
    "name:tat_x_preferred":[
        "\u0411\u0430\u043d\u0434\u0436\u0430\u0440\u0438"
    ],
    "wof:name":"Banjari",
    "wof:placetype":"locality"
},
  "geometry": {"coordinates":[81.64976999999998,24.14329],"type":"Point"}
}