{
  "type": "Feature",
  "properties": {
    "iso:country":"IN",
    "ks:ks_name":"Nawapara",
    "ks:ks_pop":479,
    "ks:ks_type":"HABITATION",
    "name:eng_x_preferred":[
        "Nawapara"
    ],
    "wof:name":"Nawapara",
    "wof:placetype":"locality",
    "wof:population":479
},
  "geometry": {"coordinates":[82.410618,22.482238],"type":"Point"}
}