{
  "type": "Feature",
  "properties": {
    "iso:country":"IN",
    "ks:ks_name":"Mal Itadi Baraiya Bhag",
    "ks:ks_pop":2937,
    "ks:ks_type":"VILLAGE",
    "ks:ks_uagg_main":0,
    "name:eng_x_preferred":[
        "Mal Itadi Baraiya Bhag"
    ],
    "wof:name":"Mal Itadi Baraiya Bhag",
    "wof:placetype":"neighbourhood",
    "wof:population":2937
},
  "geometry": {"coordinates":[73.23214,22.977645],"type":"Point"}
}