{
  "type": "Feature",
  "properties": {
    "iso:country":"IN",
    "ks:ks_name":"Sarjamdih",
    "ks:ks_pop":152,
    "ks:ks_type":"VILLAGE",
    "name:eng_x_preferred":[
        "Sarjamdih"
    ],
    "wof:name":"Sarjamdih",
    "wof:placetype":"locality",
    "wof:population":152
},
  "geometry": {"coordinates":[85.52970000000001,22.64506],"type":"Point"}
}