{
  "type": "Feature",
  "properties": {
    "gn:admin1_code":"25",
    "gn:admin2_code":"618.0",
    "gn:asciiname":"Tiruppundi",
    "gn:country_code":"IN",
    "gn:dem":7,
    "gn:feature_class":"P",
    "gn:feature_code":"PPL",
    "gn:name":"Tirupp\u016bndi",
    "gn:population":0,
    "gn:timezone":"Asia/Kolkata",
    "iso:country":"IN",
    "name:und_x_variant":[
        "Tirupundi",
        "Tirupp\u016bndi"
    ],
    "wof:name":"Tiruppundi",
    "wof:placetype":"neighbourhood"
},
  "geometry": {"coordinates":[79.81183,10.62647],"type":"Point"}
}