{
  "type": "Feature",
  "properties": {
    "iso:country":"IN",
    "ks:ks_name":"Pub Dimla Supa",
    "ks:ks_pop":302,
    "ks:ks_type":"HABITATION",
    "name:eng_x_preferred":[
        "Pub Dimla Supa"
    ],
    "wof:name":"Pub Dimla Supa",
    "wof:placetype":"locality",
    "wof:population":302
},
  "geometry": {"coordinates":[91.55270899999999,26.618439],"type":"Point"}
}