{
  "type": "Feature",
  "properties": {
    "gn:admin1_code":"36",
    "gn:admin2_code":"200.0",
    "gn:asciiname":"Hathiari",
    "gn:country_code":"IN",
    "gn:dem":376,
    "gn:feature_class":"P",
    "gn:feature_code":"PPL",
    "gn:name":"Hathi\u0101ri",
    "gn:population":0,
    "gn:timezone":"Asia/Kolkata",
    "iso:country":"IN",
    "ks:ks_name":"Hathiyar",
    "ks:ks_pop":923,
    "ks:ks_type":"VILLAGE",
    "name:eng_x_preferred":[
        "Hathiyar"
    ],
    "name:eng_x_variant":[
        "Hathiari"
    ],
    "wof:name":"Hathiyar",
    "wof:placetype":"locality",
    "wof:population":923
},
  "geometry": {"coordinates":[83.002787,23.985763],"type":"Point"}
}