{
  "type": "Feature",
  "properties": {
    "gn:admin1_code":"34.0",
    "gn:admin2_code":"216.0",
    "gn:asciiname":"Ratwara Hathu",
    "gn:country_code":"IN",
    "gn:dem":62,
    "gn:feature_class":"P",
    "gn:feature_code":"PPL",
    "gn:name":"Ratw\u0101ra H\u0101thu",
    "gn:population":0,
    "gn:timezone":"Asia/Kolkata",
    "iso:country":"IN",
    "wof:name":"Ratwara Hathu",
    "wof:placetype":"locality"
},
  "geometry": {"coordinates":[84.98855999999998,26.11961],"type":"Point"}
}