{
  "type": "Feature",
  "properties": {
    "iso:country":"IN",
    "ks:ks_name":"Periyakorukkai",
    "ks:ks_pop":1818,
    "ks:ks_type":"HABITATION",
    "name:eng_x_preferred":[
        "Periyakorukkai"
    ],
    "wof:name":"Periyakorukkai",
    "wof:placetype":"locality",
    "wof:population":1818
},
  "geometry": {"coordinates":[79.702853,10.524966],"type":"Point"}
}