{
  "type": "Feature",
  "properties": {
    "iso:country":"IN",
    "ks:ks_name":"Devlaswadi",
    "ks:ks_pop":129,
    "ks:ks_type":"HABITATION",
    "name:eng_x_preferred":[
        "Devlaswadi"
    ],
    "wof:name":"Devlaswadi",
    "wof:placetype":"locality",
    "wof:population":129
},
  "geometry": {"coordinates":[73.78451,15.766283],"type":"Point"}
}