{
  "type": "Feature",
  "properties": {
    "iso:country":"IN",
    "ks:ks_name":"Devigiri",
    "ks:ks_pop":16,
    "ks:ks_type":"HABITATION",
    "name:eng_x_preferred":[
        "Devigiri"
    ],
    "wof:name":"Devigiri",
    "wof:placetype":"locality",
    "wof:population":16
},
  "geometry": {"coordinates":[74.826976,14.342612],"type":"Point"}
}