{
  "type": "Feature",
  "properties": {
    "iso:country":"IN",
    "ks:ks_name":"Kariyanapalya",
    "ks:ks_pop":61,
    "ks:ks_type":"HABITATION",
    "name:eng_x_preferred":[
        "Kariyanapalya"
    ],
    "wof:name":"Kariyanapalya",
    "wof:placetype":"locality",
    "wof:population":61
},
  "geometry": {"coordinates":[77.262272,12.904162],"type":"Point"}
}