{
  "type": "Feature",
  "properties": {
    "iso:country":"IN",
    "ks:ks_name":"Kuntrikeri",
    "ks:ks_pop":60,
    "ks:ks_type":"HABITATION",
    "name:eng_x_preferred":[
        "Kuntrikeri"
    ],
    "wof:name":"Kuntrikeri",
    "wof:placetype":"locality",
    "wof:population":60
},
  "geometry": {"coordinates":[74.954814,14.688199],"type":"Point"}
}