{
  "type": "Feature",
  "properties": {
    "gn:admin1_code":"40",
    "gn:admin2_code":"537.0",
    "gn:asciiname":"Mankammaguda",
    "gn:country_code":"IN",
    "gn:dem":599,
    "gn:feature_class":"P",
    "gn:feature_code":"PPL",
    "gn:name":"M\u0101nkammaguda",
    "gn:population":0,
    "gn:timezone":"Asia/Kolkata",
    "iso:country":"IN",
    "wof:name":"Mankammaguda",
    "wof:placetype":"locality"
},
  "geometry": {"coordinates":[78.33244999999999,17.1359],"type":"Point"}
}