{
  "type": "Feature",
  "properties": {
    "iso:country":"IN",
    "ks:ks_name":"Sadeksarai",
    "ks:ks_pop":805,
    "ks:ks_type":"VILLAGE",
    "ks:ks_uagg_main":0,
    "name:eng_x_preferred":[
        "Sadeksarai"
    ],
    "wof:name":"Sadeksarai",
    "wof:placetype":"neighbourhood",
    "wof:population":805
},
  "geometry": {"coordinates":[88.271276,24.266677],"type":"Point"}
}