{
  "type": "Feature",
  "properties": {
    "iso:country":"IN",
    "ks:ks_alt_nam":"Mall\u0101pura",
    "ks:ks_alt_nam_2":"Mallapura",
    "ks:ks_name":"Mallapur",
    "ks:ks_type":"VILLAGE",
    "name:eng_x_preferred":[
        "Mallapur"
    ],
    "name:eng_x_variant":[
        "Mall\u0101pura",
        "Mallapura"
    ],
    "wof:name":"Mallapur",
    "wof:placetype":"locality"
},
  "geometry": {"coordinates":[76.09678,14.027129],"type":"Point"}
}