{
  "type": "Feature",
  "properties": {
    "iso:country":"IN",
    "ks:ks_alt_nam":"jagraj thakur tola",
    "ks:ks_name":"Jagraj Thakur Tola",
    "ks:ks_pop":837,
    "ks:ks_type":"HABITATION",
    "ks:ks_uagg_main":0,
    "name:eng_x_preferred":[
        "Jagraj Thakur Tola"
    ],
    "wof:name":"Jagraj Thakur Tola",
    "wof:placetype":"neighbourhood",
    "wof:population":837
},
  "geometry": {"coordinates":[86.988316,25.618811],"type":"Point"}
}