{
  "type": "Feature",
  "properties": {
    "iso:country":"IN",
    "ks:ks_name":"Neggubail",
    "ks:ks_pop":41,
    "ks:ks_type":"HABITATION",
    "name:eng_x_preferred":[
        "Neggubail"
    ],
    "wof:name":"Neggubail",
    "wof:placetype":"locality",
    "wof:population":41
},
  "geometry": {"coordinates":[74.72345300000001,14.33599],"type":"Point"}
}