{
  "type": "Feature",
  "properties": {
    "iso:country":"IN",
    "ks:ks_name":"Matambaru",
    "ks:ks_pop":39,
    "ks:ks_type":"VILLAGE",
    "name:eng_x_preferred":[
        "Matambaru"
    ],
    "wof:name":"Matambaru",
    "wof:placetype":"locality",
    "wof:population":39
},
  "geometry": {"coordinates":[83.452918,19.934748],"type":"Point"}
}