{
  "type": "Feature",
  "properties": {
    "iso:country":"IN",
    "ks:ks_name":"Patakumundajungle",
    "ks:ks_pop":297,
    "ks:ks_type":"VILLAGE",
    "name:eng_x_preferred":[
        "Patakumundajungle"
    ],
    "wof:name":"Patakumundajungle",
    "wof:placetype":"locality",
    "wof:population":297
},
  "geometry": {"coordinates":[84.82083799999999,21.162924],"type":"Point"}
}