{
  "type": "Feature",
  "properties": {
    "gn:admin1_code":"39",
    "gn:admin2_code":"61.0",
    "gn:asciiname":"Kisandar",
    "gn:country_code":"IN",
    "gn:dem":1169,
    "gn:feature_class":"P",
    "gn:feature_code":"PPL",
    "gn:name":"Kisandar",
    "gn:population":0,
    "gn:timezone":"Asia/Kolkata",
    "iso:country":"IN",
    "wof:name":"Kisandar",
    "wof:placetype":"locality"
},
  "geometry": {"coordinates":[78.75803000000001,30.19062000000001],"type":"Point"}
}