{
  "type": "Feature",
  "properties": {
    "gn:admin1_code":"36.0",
    "gn:admin2_code":"175.0",
    "gn:asciiname":"Pura Gangachh",
    "gn:country_code":"IN",
    "gn:dem":117,
    "gn:feature_class":"P",
    "gn:feature_code":"PPL",
    "gn:name":"Pura Gang\u0101chh",
    "gn:population":0,
    "gn:timezone":"Asia/Kolkata",
    "iso:country":"IN",
    "ks:ks_alt_nam":"Pura Gang\u0101chh",
    "ks:ks_name":"Pura Gangachh",
    "ks:ks_pop":481,
    "ks:ks_type":"VILLAGE",
    "ks:ks_uagg_main":0,
    "name:eng_x_preferred":[
        "Pura Gangachh"
    ],
    "name:eng_x_variant":[
        "Pura Gang\u0101chh"
    ],
    "wof:name":"Pura Gangachh",
    "wof:placetype":"neighbourhood",
    "wof:population":481
},
  "geometry": {"coordinates":[81.68860599999999,25.143313],"type":"Point"}
}