{
  "type": "Feature",
  "properties": {
    "gn:admin1_code":"23.0",
    "gn:admin2_code":"53.0",
    "gn:asciiname":"Lakhmirwala",
    "gn:country_code":"IN",
    "gn:dem":234,
    "gn:feature_class":"P",
    "gn:feature_code":"PPL",
    "gn:name":"Lakhm\u012brw\u0101la",
    "gn:population":0,
    "gn:timezone":"Asia/Kolkata",
    "iso:country":"IN",
    "name:und_x_variant":[
        "Lakhm\u012brw\u0101la",
        "Sh\u014dhpur Khurd"
    ],
    "wof:name":"Lakhmirwala",
    "wof:placetype":"locality"
},
  "geometry": {"coordinates":[75.81189000000001,30.15932],"type":"Point"}
}