{
  "type": "Feature",
  "properties": {
    "gn:admin1_code":"12.0",
    "gn:admin2_code":"1.0",
    "gn:asciiname":"Dumalar Forest",
    "gn:country_code":"IN",
    "gn:dem":1772,
    "gn:feature_class":"P",
    "gn:feature_code":"PPL",
    "gn:name":"Dumal\u0101r Forest",
    "gn:population":0,
    "gn:timezone":"Asia/Kolkata",
    "iso:country":"IN",
    "wof:name":"Dumalar Forest",
    "wof:placetype":"locality"
},
  "geometry": {"coordinates":[74.40810999999999,34.54132],"type":"Point"}
}