{
  "type": "Feature",
  "properties": {
    "iso:country":"IN",
    "ks:ks_name":"Kayam Ka Tala",
    "ks:ks_pop":75,
    "ks:ks_type":"VILLAGE",
    "name:eng_x_preferred":[
        "Kayam Ka Tala"
    ],
    "wof:name":"Kayam Ka Tala",
    "wof:placetype":"locality",
    "wof:population":75
},
  "geometry": {"coordinates":[71.21743600000001,25.187794],"type":"Point"}
}