{
  "type": "Feature",
  "properties": {
    "iso:country":"IN",
    "ks:ks_name":"Lingaraja Nagar",
    "ks:ks_pop":415,
    "ks:ks_type":"HABITATION",
    "name:eng_x_preferred":[
        "Lingaraja Nagar"
    ],
    "wof:name":"Lingaraja Nagar",
    "wof:placetype":"locality",
    "wof:population":415
},
  "geometry": {"coordinates":[75.26565600000001,15.888536],"type":"Point"}
}