{
  "type": "Feature",
  "properties": {
    "gn:admin1_code":"37",
    "gn:admin2_code":"414.0",
    "gn:asciiname":"Pujariguda",
    "gn:country_code":"IN",
    "gn:dem":550,
    "gn:feature_class":"P",
    "gn:feature_code":"PPL",
    "gn:name":"P\u016bj\u0101riguda",
    "gn:population":0,
    "gn:timezone":"Asia/Kolkata",
    "iso:country":"IN",
    "wof:name":"Pujariguda",
    "wof:placetype":"locality"
},
  "geometry": {"coordinates":[82.06545,19.10452],"type":"Point"}
}