{
  "type": "Feature",
  "properties": {
    "iso:country":"IN",
    "ks:ks_name":"Pattaje",
    "ks:ks_pop":602,
    "ks:ks_type":"HABITATION",
    "name:eng_x_preferred":[
        "Pattaje"
    ],
    "wof:name":"Pattaje",
    "wof:placetype":"locality",
    "wof:population":602
},
  "geometry": {"coordinates":[75.359619,12.656313],"type":"Point"}
}