{
  "type": "Feature",
  "properties": {
    "gn:admin1_code":"11",
    "gn:admin2_code":"23.0",
    "gn:asciiname":"Panela",
    "gn:country_code":"IN",
    "gn:dem":2238,
    "gn:feature_class":"P",
    "gn:feature_code":"PPL",
    "gn:name":"Panela",
    "gn:population":0,
    "gn:timezone":"Asia/Kolkata",
    "iso:country":"IN",
    "name:cat_x_preferred":[
        "Panela"
    ],
    "name:deu_x_preferred":[
        "Panela"
    ],
    "name:fra_x_preferred":[
        "Panela"
    ],
    "name:glg_x_preferred":[
        "Panela"
    ],
    "name:ita_x_preferred":[
        "Panela"
    ],
    "name:mwl_x_preferred":[
        "Rapadura"
    ],
    "name:nld_x_preferred":[
        "Oersuiker"
    ],
    "name:por_x_preferred":[
        "Rapadura"
    ],
    "name:scn_x_preferred":[
        "Arraspata"
    ],
    "name:spa_x_preferred":[
        "Panela"
    ],
    "wof:name":"Panela",
    "wof:placetype":"locality"
},
  "geometry": {"coordinates":[76.2166,32.90049],"type":"Point"}
}