{
  "type": "Feature",
  "properties": {
    "gn:admin1_code":"36",
    "gn:admin2_code":"172.0",
    "gn:asciiname":"Sainbasi",
    "gn:country_code":"IN",
    "gn:dem":120,
    "gn:feature_class":"P",
    "gn:feature_code":"PPL",
    "gn:name":"Sa\u012bnbas\u012b",
    "gn:population":0,
    "gn:timezone":"Asia/Kolkata",
    "iso:country":"IN",
    "ks:ks_name":"Saibasi",
    "ks:ks_pop":748,
    "ks:ks_type":"HABITATION",
    "ks:ks_uagg_main":0,
    "name:eng_x_preferred":[
        "Saibasi"
    ],
    "wof:name":"Saibasi",
    "wof:placetype":"neighbourhood",
    "wof:population":748
},
  "geometry": {"coordinates":[80.911207,25.967421],"type":"Point"}
}