{
  "type": "Feature",
  "properties": {
    "iso:country":"IN",
    "ks:ks_name":"Rajput Nagar",
    "ks:ks_pop":753,
    "ks:ks_type":"HABITATION",
    "name:eng_x_preferred":[
        "Rajput Nagar"
    ],
    "wof:name":"Rajput Nagar",
    "wof:placetype":"locality",
    "wof:population":753
},
  "geometry": {"coordinates":[81.267732,25.810188],"type":"Point"}
}