{
  "type": "Feature",
  "properties": {
    "iso:country":"IN",
    "ks:ks_name":"Patkhaulia",
    "ks:ks_pop":529,
    "ks:ks_type":"VILLAGE",
    "name:eng_x_preferred":[
        "Patkhaulia"
    ],
    "wof:name":"Patkhaulia",
    "wof:placetype":"locality",
    "wof:population":529
},
  "geometry": {"coordinates":[84.216106,27.011939],"type":"Point"}
}