{
  "type": "Feature",
  "properties": {
    "iso:country":"IN",
    "ks:ks_name":"Hiluvalli",
    "ks:ks_pop":999,
    "ks:ks_type":"VILLAGE",
    "name:eng_x_preferred":[
        "Hiluvalli"
    ],
    "wof:name":"Hiluvalli",
    "wof:placetype":"locality",
    "wof:population":999
},
  "geometry": {"coordinates":[75.52359300000001,13.618896],"type":"Point"}
}