{
  "type": "Feature",
  "properties": {
    "iso:country":"IN",
    "ks:ks_name":"Barodih Mubarakpur",
    "ks:ks_pop":959,
    "ks:ks_type":"VILLAGE",
    "name:eng_x_preferred":[
        "Barodih Mubarakpur"
    ],
    "wof:name":"Barodih Mubarakpur",
    "wof:placetype":"locality",
    "wof:population":959
},
  "geometry": {"coordinates":[83.329115,25.787695],"type":"Point"}
}