{
  "type": "Feature",
  "properties": {
    "iso:country":"IN",
    "ks:ks_name":"Karmahi",
    "ks:ks_pop":127,
    "ks:ks_type":"HABITATION",
    "name:eng_x_preferred":[
        "Karmahi"
    ],
    "wof:name":"Karmahi",
    "wof:placetype":"locality",
    "wof:population":127
},
  "geometry": {"coordinates":[84.410945,23.836908],"type":"Point"}
}