{
  "type": "Feature",
  "properties": {
    "gn:admin1_code":"3.0",
    "gn:admin2_code":"317.0",
    "gn:asciiname":"Mugrapur",
    "gn:country_code":"IN",
    "gn:dem":27,
    "gn:feature_class":"P",
    "gn:feature_code":"PPL",
    "gn:name":"Mugrapur",
    "gn:population":0,
    "gn:timezone":"Asia/Kolkata",
    "iso:country":"IN",
    "wof:name":"Mugrapur",
    "wof:placetype":"locality"
},
  "geometry": {"coordinates":[92.49628,24.78707],"type":"Point"}
}