{
  "type": "Feature",
  "properties": {
    "iso:country":"IN",
    "ks:ks_name":"Guldhar",
    "ks:ks_type":"VILLAGE",
    "ks:ks_uagg_main":0,
    "name:eng_x_preferred":[
        "Guldhar"
    ],
    "wof:name":"Guldhar",
    "wof:placetype":"neighbourhood"
},
  "geometry": {"coordinates":[77.45330800000001,28.700719],"type":"Point"}
}