{
  "type": "Feature",
  "properties": {
    "gn:admin1_code":"36",
    "gn:admin2_code":"177.0",
    "gn:asciiname":"Musahar",
    "gn:country_code":"IN",
    "gn:dem":104,
    "gn:feature_class":"P",
    "gn:feature_code":"PPL",
    "gn:name":"Musahar",
    "gn:population":0,
    "gn:timezone":"Asia/Kolkata",
    "iso:country":"IN",
    "name:hin_x_preferred":[
        "\u092e\u0941\u0938\u0939\u0930 \u091c\u093e\u0924\u093f"
    ],
    "name:zho_x_preferred":[
        "\u7a46\u85a9\u54c8\u723e"
    ],
    "wof:name":"Musahar",
    "wof:placetype":"locality"
},
  "geometry": {"coordinates":[82.16545000000001,26.42584],"type":"Point"}
}