{
  "type": "Feature",
  "properties": {
    "gn:admin1_code":"35.0",
    "gn:admin2_code":"466.0",
    "gn:asciiname":"Khamkhera",
    "gn:country_code":"IN",
    "gn:dem":262,
    "gn:feature_class":"P",
    "gn:feature_code":"PPL",
    "gn:name":"Kh\u0101mkhera",
    "gn:population":0,
    "gn:timezone":"Asia/Kolkata",
    "iso:country":"IN",
    "ks:ks_alt_nam":"Kh\u0101mkhera",
    "ks:ks_name":"Khamkhera",
    "ks:ks_type":"VILLAGE",
    "name:eng_x_preferred":[
        "Khamkhera"
    ],
    "name:eng_x_variant":[
        "Kh\u0101mkhera"
    ],
    "wof:name":"Khamkhera",
    "wof:placetype":"locality"
},
  "geometry": {"coordinates":[76.48283499999999,22.165465],"type":"Point"}
}