{
  "type": "Feature",
  "properties": {
    "iso:country":"IN",
    "ks:ks_name":"Majhipatna",
    "ks:ks_pop":913,
    "ks:ks_type":"VILLAGE",
    "ks:ks_uagg_main":0,
    "name:eng_x_preferred":[
        "Majhipatna"
    ],
    "wof:name":"Majhipatna",
    "wof:placetype":"neighbourhood",
    "wof:population":913
},
  "geometry": {"coordinates":[85.294004,20.415609],"type":"Point"}
}