{
  "type": "Feature",
  "properties": {
    "iso:country":"IN",
    "ks:ks_name":"Machapur",
    "ks:ks_pop":332,
    "ks:ks_type":"VILLAGE",
    "ks:ks_uagg_main":0,
    "name:eng_x_preferred":[
        "Machapur"
    ],
    "wof:name":"Machapur",
    "wof:placetype":"neighbourhood",
    "wof:population":332
},
  "geometry": {"coordinates":[78.47485500000001,18.981384],"type":"Point"}
}