{
  "type": "Feature",
  "properties": {
    "gn:admin1_code":"11",
    "gn:admin2_code":"30.0",
    "gn:asciiname":"Retho",
    "gn:country_code":"IN",
    "gn:dem":1059,
    "gn:feature_class":"P",
    "gn:feature_code":"PPL",
    "gn:name":"Retho",
    "gn:population":0,
    "gn:timezone":"Asia/Kolkata",
    "iso:country":"IN",
    "wof:name":"Retho",
    "wof:placetype":"locality"
},
  "geometry": {"coordinates":[76.85973,31.29807000000001],"type":"Point"}
}