{
  "type": "Feature",
  "properties": {
    "gn:admin1_code":"19",
    "gn:admin2_code":"563.0",
    "gn:asciiname":"Bandisera",
    "gn:country_code":"IN",
    "gn:dem":488,
    "gn:feature_class":"P",
    "gn:feature_code":"PPL",
    "gn:name":"Bandisera",
    "gn:population":0,
    "gn:timezone":"Asia/Kolkata",
    "iso:country":"IN",
    "wof:name":"Bandisera",
    "wof:placetype":"locality"
},
  "geometry": {"coordinates":[74.79727,14.70327],"type":"Point"}
}