{
  "type": "Feature",
  "properties": {
    "gn:admin1_code":"2.0",
    "gn:admin2_code":"551",
    "gn:asciiname":"Kodur",
    "gn:country_code":"IN",
    "gn:dem":189,
    "gn:feature_class":"P",
    "gn:feature_code":"PPL",
    "gn:name":"Kod\u016br",
    "gn:population":0,
    "gn:timezone":"Asia/Kolkata",
    "iso:country":"IN",
    "name:und_x_variant":[
        "Kod\u016bru",
        "Kod\u016br"
    ],
    "wof:name":"Kodur",
    "wof:placetype":"locality"
},
  "geometry": {"coordinates":[79.35132,13.95771],"type":"Point"}
}