{
  "type": "Feature",
  "properties": {
    "iso:country":"IN",
    "ks:ks_name":"Pagi",
    "ks:ks_pop":252,
    "ks:ks_type":"HABITATION",
    "name:eng_x_preferred":[
        "Pagi"
    ],
    "wof:name":"Pagi",
    "wof:placetype":"locality",
    "wof:population":252
},
  "geometry": {"coordinates":[73.815111,23.372611],"type":"Point"}
}