{
  "type": "Feature",
  "properties": {
    "gn:admin1_code":"39.0",
    "gn:admin2_code":"61.0",
    "gn:asciiname":"Sinduri Talli",
    "gn:country_code":"IN",
    "gn:dem":1461,
    "gn:feature_class":"P",
    "gn:feature_code":"PPL",
    "gn:name":"Sinduri Talli",
    "gn:population":0,
    "gn:timezone":"Asia/Kolkata",
    "iso:country":"IN",
    "ks:ks_name":"Sinduni Talli",
    "ks:ks_pop":113,
    "ks:ks_type":"VILLAGE",
    "name:eng_x_preferred":[
        "Sinduni Talli"
    ],
    "name:eng_x_variant":[
        "Sinduri Talli"
    ],
    "wof:name":"Sinduni Talli",
    "wof:placetype":"locality",
    "wof:population":113
},
  "geometry": {"coordinates":[79.058897,29.831059],"type":"Point"}
}