{
  "type": "Feature",
  "properties": {
    "gn:admin1_code":"39.0",
    "gn:admin2_code":"61.0",
    "gn:asciiname":"Sinduri Talli",
    "gn:country_code":"IN",
    "gn:dem":1461,
    "gn:feature_class":"P",
    "gn:feature_code":"PPL",
    "gn:name":"Sinduri Talli",
    "gn:population":0,
    "gn:timezone":"Asia/Kolkata",
    "iso:country":"IN",
    "wof:name":"Sinduri Talli",
    "wof:placetype":"locality"
},
  "geometry": {"coordinates":[79.06014999999999,29.83214000000001],"type":"Point"}
}