{
  "type": "Feature",
  "properties": {
    "iso:country":"IN",
    "ks:ks_name":"Dalwade",
    "ks:ks_pop":214,
    "ks:ks_type":"VILLAGE",
    "name:eng_x_preferred":[
        "Dalwade"
    ],
    "wof:name":"Dalwade",
    "wof:placetype":"locality",
    "wof:population":214
},
  "geometry": {"coordinates":[75.108242,20.618025],"type":"Point"}
}