{
  "type": "Feature",
  "properties": {
    "gn:admin1_code":"9.0",
    "gn:admin2_code":"473",
    "gn:asciiname":"Bilodra",
    "gn:country_code":"IN",
    "gn:dem":121,
    "gn:feature_class":"P",
    "gn:feature_code":"PPL",
    "gn:name":"Bilodra",
    "gn:population":0,
    "gn:timezone":"Asia/Kolkata",
    "iso:country":"IN",
    "wof:name":"Bilodra",
    "wof:placetype":"locality"
},
  "geometry": {"coordinates":[72.65221,23.52472],"type":"Point"}
}