{
  "type": "Feature",
  "properties": {
    "iso:country":"IN",
    "ks:ks_alt_nam":"Vazhakkulam east",
    "ks:ks_name":"Vazhakkulam East",
    "ks:ks_pop":1615,
    "ks:ks_type":"HABITATION",
    "name:eng_x_preferred":[
        "Vazhakkulam East"
    ],
    "wof:name":"Vazhakkulam East",
    "wof:placetype":"neighbourhood",
    "wof:population":1615
},
  "geometry": {"coordinates":[76.616191,9.949989],"type":"Point"}
}