{
  "type": "Feature",
  "properties": {
    "gn:admin1_code":"36",
    "gn:admin2_code":"166.0",
    "gn:asciiname":"Pratappura",
    "gn:country_code":"IN",
    "gn:dem":142,
    "gn:feature_class":"P",
    "gn:feature_code":"PPL",
    "gn:name":"Prat\u0101ppura",
    "gn:population":0,
    "gn:timezone":"Asia/Kolkata",
    "iso:country":"IN",
    "ks:ks_alt_nam":"Prat\u0101ppura",
    "ks:ks_name":"Pratappura",
    "ks:ks_pop":310,
    "ks:ks_type":"VILLAGE",
    "name:eng_x_preferred":[
        "Pratappura"
    ],
    "name:eng_x_variant":[
        "Prat\u0101ppura"
    ],
    "wof:name":"Pratappura",
    "wof:placetype":"locality",
    "wof:population":310
},
  "geometry": {"coordinates":[79.345974,25.775107],"type":"Point"}
}