{
  "type": "Feature",
  "properties": {
    "iso:country":"IN",
    "ks:ks_name":"Karma",
    "ks:ks_pop":628,
    "ks:ks_type":"VILLAGE",
    "name:eng_x_preferred":[
        "Karma"
    ],
    "wof:name":"Karma",
    "wof:placetype":"locality",
    "wof:population":628
},
  "geometry": {"coordinates":[84.198227,25.138312],"type":"Point"}
}