{
  "type": "Feature",
  "properties": {
    "iso:country":"IN",
    "ks:ks_name":"Pazhanji Road",
    "ks:ks_pop":163,
    "ks:ks_type":"HABITATION",
    "name:eng_x_preferred":[
        "Pazhanji Road"
    ],
    "wof:name":"Pazhanji Road",
    "wof:placetype":"locality",
    "wof:population":163
},
  "geometry": {"coordinates":[76.09083200000001,10.695303],"type":"Point"}
}