{
  "type": "Feature",
  "properties": {
    "iso:country":"IN",
    "ks:ks_name":"Thummha",
    "ks:ks_pop":1270,
    "ks:ks_type":"VILLAGE",
    "ks:ks_uagg_main":0,
    "name:eng_x_preferred":[
        "Thummha"
    ],
    "wof:name":"Thummha",
    "wof:placetype":"neighbourhood",
    "wof:population":1270
},
  "geometry": {"coordinates":[83.94119999999999,24.593215],"type":"Point"}
}