{
  "type": "Feature",
  "properties": {
    "iso:country":"IN",
    "ks:ks_alt_nam":"Tb.Road Kothamalapall",
    "ks:ks_name":"Tb.road Kothamalapall",
    "ks:ks_pop":211,
    "ks:ks_type":"HABITATION",
    "name:eng_x_preferred":[
        "Tb.road Kothamalapall"
    ],
    "wof:name":"Tb.road Kothamalapall",
    "wof:placetype":"locality",
    "wof:population":211
},
  "geometry": {"coordinates":[78.787824,13.650667],"type":"Point"}
}