{
  "type": "Feature",
  "properties": {
    "iso:country":"IN",
    "ks:ks_name":"Kombo",
    "ks:ks_pop":528,
    "ks:ks_type":"VILLAGE",
    "name:eng_x_preferred":[
        "Kombo"
    ],
    "wof:name":"Kombo",
    "wof:placetype":"locality",
    "wof:population":528
},
  "geometry": {"coordinates":[85.61595699999999,23.299525],"type":"Point"}
}