{
  "type": "Feature",
  "properties": {
    "iso:country":"IN",
    "ks:ks_name":"Jagdishpur",
    "ks:ks_pop":946,
    "ks:ks_type":"HABITATION",
    "name:eng_x_preferred":[
        "Jagdishpur"
    ],
    "wof:name":"Jagdishpur",
    "wof:placetype":"locality",
    "wof:population":946
},
  "geometry": {"coordinates":[85.033282,24.789264],"type":"Point"}
}