{
  "type": "Feature",
  "properties": {
    "iso:country":"IN",
    "ks:ks_alt_nam":"BASARE JADHAVWASTI",
    "ks:ks_name":"Basare Jadhavwasti",
    "ks:ks_pop":150,
    "ks:ks_type":"HABITATION",
    "name:eng_x_preferred":[
        "Basare Jadhavwasti"
    ],
    "wof:name":"Basare Jadhavwasti",
    "wof:placetype":"locality",
    "wof:population":150
},
  "geometry": {"coordinates":[74.36734300000001,16.872868],"type":"Point"}
}