{
  "type": "Feature",
  "properties": {
    "iso:country":"IN",
    "ks:ks_alt_nam":"CHAMBHAR WASTI",
    "ks:ks_name":"Chambhar Wasti",
    "ks:ks_pop":45,
    "ks:ks_type":"HABITATION",
    "name:eng_x_preferred":[
        "Chambhar Wasti"
    ],
    "wof:name":"Chambhar Wasti",
    "wof:placetype":"locality",
    "wof:population":45
},
  "geometry": {"coordinates":[74.946716,17.088399],"type":"Point"}
}