{
  "type": "Feature",
  "properties": {
    "gn:admin1_code":"35",
    "gn:admin2_code":"440.0",
    "gn:asciiname":"Nawalpura",
    "gn:country_code":"IN",
    "gn:dem":271,
    "gn:feature_class":"P",
    "gn:feature_code":"PPL",
    "gn:name":"Nawalpura",
    "gn:population":0,
    "gn:timezone":"Asia/Kolkata",
    "iso:country":"IN",
    "wof:name":"Nawalpura",
    "wof:placetype":"locality"
},
  "geometry": {"coordinates":[76.07708000000002,21.95086],"type":"Point"}
}