{
  "type": "Feature",
  "properties": {
    "iso:country":"IN",
    "ks:ks_name":"Harijanawada",
    "ks:ks_pop":341,
    "ks:ks_type":"HABITATION",
    "name:eng_x_preferred":[
        "Harijanawada"
    ],
    "wof:name":"Harijanawada",
    "wof:placetype":"locality",
    "wof:population":341
},
  "geometry": {"coordinates":[77.934016,13.944069],"type":"Point"}
}