{
  "type": "Feature",
  "properties": {
    "iso:country":"IN",
    "ks:ks_name":"Thakuron Ki Madhiyan",
    "ks:ks_pop":330,
    "ks:ks_type":"HABITATION",
    "name:eng_x_preferred":[
        "Thakuron Ki Madhiyan"
    ],
    "wof:name":"Thakuron Ki Madhiyan",
    "wof:placetype":"locality",
    "wof:population":330
},
  "geometry": {"coordinates":[77.781679,28.486841],"type":"Point"}
}