{
  "type": "Feature",
  "properties": {
    "iso:country":"IN",
    "ks:ks_name":"Pipalput",
    "ks:ks_pop":189,
    "ks:ks_type":"HABITATION",
    "name:eng_x_preferred":[
        "Pipalput"
    ],
    "wof:name":"Pipalput",
    "wof:placetype":"locality",
    "wof:population":189
},
  "geometry": {"coordinates":[82.751627,18.571843],"type":"Point"}
}