{
  "type": "Feature",
  "properties": {
    "iso:country":"IN",
    "ks:ks_name":"Bhorgarh",
    "ks:ks_type":"VILLAGE",
    "ks:ks_uagg_main":0,
    "name:eng_x_preferred":[
        "Bhorgarh"
    ],
    "wof:name":"Bhorgarh",
    "wof:placetype":"neighbourhood"
},
  "geometry": {"coordinates":[77.095209,28.829264],"type":"Point"}
}