{
  "type": "Feature",
  "properties": {
    "iso:country":"IN",
    "ks:ks_name":"Block Colony",
    "ks:ks_pop":217,
    "ks:ks_type":"HABITATION",
    "name:eng_x_preferred":[
        "Block Colony"
    ],
    "wof:name":"Block Colony",
    "wof:placetype":"locality",
    "wof:population":217
},
  "geometry": {"coordinates":[86.22272599999999,24.381093],"type":"Point"}
}