{
  "type": "Feature",
  "properties": {
    "iso:country":"IN",
    "ks:ks_alt_nam":"1 LGM",
    "ks:ks_name":"1 Lgm",
    "ks:ks_pop":209,
    "ks:ks_type":"HABITATION",
    "name:eng_x_preferred":[
        "1 Lgm"
    ],
    "wof:name":"1 Lgm",
    "wof:placetype":"locality",
    "wof:population":209
},
  "geometry": {"coordinates":[73.76543700000001,29.094289],"type":"Point"}
}