{
  "type": "Feature",
  "properties": {
    "iso:country":"IN",
    "ks:ks_name":"Lachhiwar Ka Goliya",
    "ks:ks_pop":2378,
    "ks:ks_type":"HABITATION",
    "name:eng_x_preferred":[
        "Lachhiwar Ka Goliya"
    ],
    "wof:name":"Lachhiwar Ka Goliya",
    "wof:placetype":"locality",
    "wof:population":2378
},
  "geometry": {"coordinates":[72.01420899999999,24.70057],"type":"Point"}
}