{
  "type": "Feature",
  "properties": {
    "iso:country":"IN",
    "ks:ks_name":"Pure Baaz",
    "ks:ks_pop":758,
    "ks:ks_type":"HABITATION",
    "ks:ks_uagg_main":0,
    "name:eng_x_preferred":[
        "Pure Baaz"
    ],
    "wof:name":"Pure Baaz",
    "wof:placetype":"neighbourhood",
    "wof:population":758
},
  "geometry": {"coordinates":[81.365066,26.707608],"type":"Point"}
}