{
  "type": "Feature",
  "properties": {
    "iso:country":"IN",
    "ks:ks_name":"Indira Nagar",
    "ks:ks_pop":176,
    "ks:ks_type":"HABITATION",
    "name:eng_x_preferred":[
        "Indira Nagar"
    ],
    "wof:name":"Indira Nagar",
    "wof:placetype":"locality",
    "wof:population":176
},
  "geometry": {"coordinates":[76.031374,17.688682],"type":"Point"}
}