{
  "type": "Feature",
  "properties": {
    "iso:country":"IN",
    "ks:ks_name":"Vilangupara",
    "ks:ks_pop":2155,
    "ks:ks_type":"HABITATION",
    "name:eng_x_preferred":[
        "Vilangupara"
    ],
    "wof:name":"Vilangupara",
    "wof:placetype":"locality",
    "wof:population":2155
},
  "geometry": {"coordinates":[76.530107,9.939712],"type":"Point"}
}