{
  "type": "Feature",
  "properties": {
    "iso:country":"IN",
    "ks:ks_name":"Sarkari Grant",
    "ks:ks_pop":318,
    "ks:ks_type":"HABITATION",
    "name:eng_x_preferred":[
        "Sarkari Grant"
    ],
    "wof:name":"Sarkari Grant",
    "wof:placetype":"locality",
    "wof:population":318
},
  "geometry": {"coordinates":[82.183217,27.299828],"type":"Point"}
}