{
  "type": "Feature",
  "properties": {
    "iso:country":"IN",
    "ks:ks_name":"Narikhet",
    "ks:ks_pop":300,
    "ks:ks_type":"HABITATION",
    "name:eng_x_preferred":[
        "Narikhet"
    ],
    "wof:name":"Narikhet",
    "wof:placetype":"locality",
    "wof:population":300
},
  "geometry": {"coordinates":[80.060231,26.42908],"type":"Point"}
}