{
  "type": "Feature",
  "properties": {
    "iso:country":"IN",
    "ks:ks_name":"Devpura",
    "ks:ks_type":"VILLAGE",
    "ks:ks_uagg_main":0,
    "name:eng_x_preferred":[
        "Devpura"
    ],
    "wof:name":"Devpura",
    "wof:placetype":"neighbourhood"
},
  "geometry": {"coordinates":[78.15080500000001,29.939587],"type":"Point"}
}