{
  "type": "Feature",
  "properties": {
    "gn:admin1_code":"36.0",
    "gn:admin2_code":"183.0",
    "gn:asciiname":"Harchandpur",
    "gn:country_code":"IN",
    "gn:dem":115,
    "gn:feature_class":"P",
    "gn:feature_code":"PPL",
    "gn:name":"Harchandpur",
    "gn:population":0,
    "gn:timezone":"Asia/Kolkata",
    "iso:country":"IN",
    "name:hin_x_preferred":[
        "\u0939\u0930\u091a\u0902\u0926\u092a\u0941\u0930"
    ],
    "wof:name":"Harchandpur",
    "wof:placetype":"locality"
},
  "geometry": {"coordinates":[81.97100999999998,27.39787],"type":"Point"}
}