{
  "type": "Feature",
  "properties": {
    "iso:country":"IN",
    "ks:ks_name":"Kupada",
    "ks:ks_pop":352,
    "ks:ks_type":"VILLAGE",
    "name:eng_x_preferred":[
        "Kupada"
    ],
    "wof:name":"Kupada",
    "wof:placetype":"locality",
    "wof:population":352
},
  "geometry": {"coordinates":[74.78182099999999,23.439632],"type":"Point"}
}