{
  "type": "Feature",
  "properties": {
    "gn:admin1_code":"2",
    "gn:admin2_code":"544.0",
    "gn:asciiname":"Yadagiripalem",
    "gn:country_code":"IN",
    "gn:dem":18,
    "gn:feature_class":"P",
    "gn:feature_code":"PPL",
    "gn:name":"Y\u0101dagirip\u0101lem",
    "gn:population":0,
    "gn:timezone":"Asia/Kolkata",
    "iso:country":"IN",
    "wof:name":"Yadagiripalem",
    "wof:placetype":"locality"
},
  "geometry": {"coordinates":[82.89713,17.57844],"type":"Point"}
}