{
  "type": "Feature",
  "properties": {
    "iso:country":"IN",
    "ks:ks_name":"Lalpura",
    "ks:ks_pop":221,
    "ks:ks_type":"HABITATION",
    "name:eng_x_preferred":[
        "Lalpura"
    ],
    "wof:name":"Lalpura",
    "wof:placetype":"locality",
    "wof:population":221
},
  "geometry": {"coordinates":[72.39019,24.713251],"type":"Point"}
}