{
  "type": "Feature",
  "properties": {
    "iso:country":"IN",
    "ks:ks_alt_nam":"GOPALGANJ",
    "ks:ks_name":"Gopalganj",
    "ks:ks_pop":522,
    "ks:ks_type":"HABITATION",
    "name:eng_x_preferred":[
        "Gopalganj"
    ],
    "wof:name":"Gopalganj",
    "wof:placetype":"locality",
    "wof:population":522
},
  "geometry": {"coordinates":[88.768826,26.516178],"type":"Point"}
}