{
  "type": "Feature",
  "properties": {
    "gn:admin1_code":"34.0",
    "gn:admin2_code":"235.0",
    "gn:asciiname":"Gamharia",
    "gn:country_code":"IN",
    "gn:dem":167,
    "gn:feature_class":"P",
    "gn:feature_code":"PPL",
    "gn:name":"Gamhari\u0101",
    "gn:population":0,
    "gn:timezone":"Asia/Kolkata",
    "iso:country":"IN",
    "ks:ks_name":"Gamhariya",
    "ks:ks_pop":680,
    "ks:ks_type":"VILLAGE",
    "ks:ks_uagg_main":0,
    "name:eng_x_preferred":[
        "Gamhariya"
    ],
    "name:hif_x_preferred":[
        "Gamhari"
    ],
    "name:hin_x_preferred":[
        "\u0917\u092e\u094d\u0939\u0930\u093f\u092f\u093e"
    ],
    "wof:name":"Gamhariya",
    "wof:placetype":"neighbourhood",
    "wof:population":680
},
  "geometry": {"coordinates":[84.18167099999999,24.553944],"type":"Point"}
}