{
  "type": "Feature",
  "properties": {
    "iso:country":"IN",
    "ks:ks_name":"Mathwadi",
    "ks:ks_pop":189,
    "ks:ks_type":"HABITATION",
    "name:eng_x_preferred":[
        "Mathwadi"
    ],
    "wof:name":"Mathwadi",
    "wof:placetype":"locality",
    "wof:population":189
},
  "geometry": {"coordinates":[73.554382,15.958052],"type":"Point"}
}