{
  "type": "Feature",
  "properties": {
    "iso:country":"IN",
    "ks:ks_name":"Basantpur",
    "ks:ks_pop":449,
    "ks:ks_type":"VILLAGE",
    "name:eng_x_preferred":[
        "Basantpur"
    ],
    "wof:name":"Basantpur",
    "wof:placetype":"locality",
    "wof:population":449
},
  "geometry": {"coordinates":[83.677817,22.263844],"type":"Point"}
}