{
  "type": "Feature",
  "properties": {
    "gn:country":"IN",
    "gn:fcode":"PPL",
    "gn:population":15007,
    "iso:country":"IN",
    "qs:name":"Misrikh",
    "qs:photos_9r":0,
    "qs:photos_sr":0,
    "qs:pop_sr":"6",
    "wof:name":"Misrikh",
    "wof:placetype":"locality",
    "wof:population":15007
},
  "geometry": {"coordinates":[80.53135,27.43201],"type":"Point"}
}