{
  "type": "Feature",
  "properties": {
    "iso:country":"IN",
    "name:deu_x_preferred":[
        "Thiruvanmiyur"
    ],
    "name:eng_x_preferred":[
        "Tiruvanmiyur"
    ],
    "name:eng_x_variant":[
        "Tiruvamiyur",
        "Tiruvanimayur",
        "Tiruv\u0101nmiy\u016br",
        "Thiruvanmiyur"
    ],
    "name:hin_x_preferred":[
        "\u0924\u093f\u0930\u0941\u0935\u093e\u0928\u092e\u093f\u092f\u0942\u0930"
    ],
    "name:rus_x_preferred":[
        "\u0422\u0438\u0440\u0443\u0432\u0430\u043d\u043c\u0438\u044e\u0440"
    ],
    "name:tam_x_preferred":[
        "\u0ba4\u0bbf\u0bb0\u0bc1\u0bb5\u0bbe\u0ba9\u0bcd\u0bae\u0bbf\u0baf\u0bc2\u0bb0\u0bcd"
    ],
    "name:und_x_variant":[
        "Tiruv\u0101miy\u016br",
        "Tiruyamiyur"
    ],
    "qs:gn_adm0_cc":"IN",
    "qs:gn_fcode":"PPL",
    "qs:gn_local":1264527,
    "qs:gn_nam_loc":"Chennai, Chennai, Tamil Nadu, IN",
    "qs:gn_namadm1":"25",
    "qs:gn_name":"Tiruv\u0101nmiy\u016br",
    "qs:local_max":2138,
    "qs:local_sum":21081,
    "qs:localhoods":47,
    "qs:name":"Tiruvanmiyur",
    "qs:name_adm0":"India",
    "qs:name_adm1":"Tamil Nadu",
    "qs:name_adm2":"Chennai",
    "qs:name_local":"Chennai",
    "qs:photo_max":140,
    "qs:photo_sum":398,
    "qs:placetype":"Suburb",
    "qs:quad_count":26,
    "qs:woe_adm0":23424848,
    "qs:woe_adm1":2345758,
    "qs:woe_adm2":12586677,
    "qs:woe_lau":0,
    "qs:woe_local":2295424,
    "qs:woe_ver":"7.10.0",
    "wd:wordcount":419,
    "wof:lang":[
        "eng"
    ],
    "wof:name":"Tiruvanmiyur",
    "wof:placetype":"neighbourhood"
},
  "geometry": {"coordinates":[80.263278,12.988901],"type":"Point"}
}