{
  "type": "Feature",
  "properties": {
    "gn:admin1_code":"34",
    "gn:admin2_code":"237.0",
    "gn:asciiname":"Pichhli",
    "gn:country_code":"IN",
    "gn:dem":264,
    "gn:feature_class":"P",
    "gn:feature_code":"PPL",
    "gn:name":"Pichhli",
    "gn:population":0,
    "gn:timezone":"Asia/Kolkata",
    "iso:country":"IN",
    "wof:name":"Pichhli",
    "wof:placetype":"locality"
},
  "geometry": {"coordinates":[85.48333000000002,24.55],"type":"Point"}
}