{
  "type": "Feature",
  "properties": {
    "gn:admin1_code":"36.0",
    "gn:admin2_code":"170.0",
    "gn:asciiname":"Ahiran ka Purwa",
    "gn:country_code":"IN",
    "gn:dem":143,
    "gn:feature_class":"P",
    "gn:feature_code":"PPL",
    "gn:name":"Ah\u012bran ka Purwa",
    "gn:population":0,
    "gn:timezone":"Asia/Kolkata",
    "iso:country":"IN",
    "wof:name":"Ahiran ka Purwa",
    "wof:placetype":"locality"
},
  "geometry": {"coordinates":[80.58908000000002,25.14229],"type":"Point"}
}