{
  "type": "Feature",
  "properties": {
    "gn:admin1_code":"11",
    "gn:admin2_code":"27.0",
    "gn:asciiname":"Gard Khol",
    "gn:country_code":"IN",
    "gn:dem":1151,
    "gn:feature_class":"P",
    "gn:feature_code":"PPL",
    "gn:name":"Gard Khol",
    "gn:population":0,
    "gn:timezone":"Asia/Kolkata",
    "iso:country":"IN",
    "wof:name":"Gard Khol",
    "wof:placetype":"locality"
},
  "geometry": {"coordinates":[76.90233000000001,31.86907],"type":"Point"}
}