{
  "type": "Feature",
  "properties": {
    "iso:country":"IN",
    "ks:ks_name":"Tanmura",
    "ks:ks_pop":312,
    "ks:ks_type":"VILLAGE",
    "name:eng_x_preferred":[
        "Tanmura"
    ],
    "wof:name":"Tanmura",
    "wof:placetype":"locality",
    "wof:population":312
},
  "geometry": {"coordinates":[84.54841,21.756122],"type":"Point"}
}