{
  "type": "Feature",
  "properties": {
    "iso:country":"IN",
    "ks:ks_name":"Rangamatiya",
    "ks:ks_pop":413,
    "ks:ks_type":"VILLAGE",
    "name:eng_x_preferred":[
        "Rangamatiya"
    ],
    "wof:name":"Rangamatiya",
    "wof:placetype":"locality",
    "wof:population":413
},
  "geometry": {"coordinates":[86.325245,22.601107],"type":"Point"}
}