{
  "type": "Feature",
  "properties": {
    "gn:admin1_code":"16.0",
    "gn:admin2_code":"503.0",
    "gn:asciiname":"Jamthi Ganeshpur",
    "gn:country_code":"IN",
    "gn:dem":419,
    "gn:feature_class":"P",
    "gn:feature_code":"PPL",
    "gn:name":"J\u0101mthi Ganeshpur",
    "gn:population":0,
    "gn:timezone":"Asia/Kolkata",
    "iso:country":"IN",
    "wof:name":"Jamthi Ganeshpur",
    "wof:placetype":"locality"
},
  "geometry": {"coordinates":[78.42851,21.46653],"type":"Point"}
}