{
  "type": "Feature",
  "properties": {
    "iso:country":"IN",
    "ks:ks_alt_nam":"Mandadi doddamane",
    "ks:ks_name":"Mandadi Doddamane",
    "ks:ks_pop":90,
    "ks:ks_type":"HABITATION",
    "name:eng_x_preferred":[
        "Mandadi Doddamane"
    ],
    "wof:name":"Mandadi Doddamane",
    "wof:placetype":"locality",
    "wof:population":90
},
  "geometry": {"coordinates":[74.778431,13.592288],"type":"Point"}
}