{
  "type": "Feature",
  "properties": {
    "iso:country":"IN",
    "ks:ks_name":"Parathakkadu",
    "ks:ks_pop":950,
    "ks:ks_type":"HABITATION",
    "name:eng_x_preferred":[
        "Parathakkadu"
    ],
    "wof:name":"Parathakkadu",
    "wof:placetype":"locality",
    "wof:population":950
},
  "geometry": {"coordinates":[75.96702399999999,11.201968],"type":"Point"}
}