{
  "type": "Feature",
  "properties": {
    "gn:admin1_code":"37.0",
    "gn:admin2_code":"409.0",
    "gn:asciiname":"Gabradih",
    "gn:country_code":"IN",
    "gn:dem":305,
    "gn:feature_class":"P",
    "gn:feature_code":"PPL",
    "gn:name":"Gabr\u0101dih",
    "gn:population":0,
    "gn:timezone":"Asia/Kolkata",
    "iso:country":"IN",
    "name:eng_x_preferred":[
        "Gabr\u0101dih"
    ],
    "wof:name":"Gabradih",
    "wof:placetype":"locality"
},
  "geometry": {"coordinates":[81.21316999999998,21.5522],"type":"Point"}
}