{
  "type": "Feature",
  "properties": {
    "gn:admin1_code":"39.0",
    "gn:admin2_code":"61.0",
    "gn:asciiname":"Bhairgaon",
    "gn:country_code":"IN",
    "gn:dem":1504,
    "gn:feature_class":"P",
    "gn:feature_code":"PPL",
    "gn:name":"Bhairgaon",
    "gn:population":0,
    "gn:timezone":"Asia/Kolkata",
    "iso:country":"IN",
    "wof:name":"Bhairgaon",
    "wof:placetype":"locality"
},
  "geometry": {"coordinates":[79.13794,29.91968],"type":"Point"}
}