{
  "type": "Feature",
  "properties": {
    "iso:country":"IN",
    "ks:ks_name":"Guhipur",
    "ks:ks_pop":262,
    "ks:ks_type":"VILLAGE",
    "name:eng_x_preferred":[
        "Guhipur"
    ],
    "wof:name":"Guhipur",
    "wof:placetype":"locality",
    "wof:population":262
},
  "geometry": {"coordinates":[86.986966,21.583834],"type":"Point"}
}