{
  "type": "Feature",
  "properties": {
    "iso:country":"IN",
    "ks:ks_name":"Bhogadipada",
    "ks:ks_pop":114,
    "ks:ks_type":"HABITATION",
    "name:eng_x_preferred":[
        "Bhogadipada"
    ],
    "wof:name":"Bhogadipada",
    "wof:placetype":"locality",
    "wof:population":114
},
  "geometry": {"coordinates":[72.848997,19.562301],"type":"Point"}
}