{
  "type": "Feature",
  "properties": {
    "iso:country":"IN",
    "ks:ks_name":"Teja Tola",
    "ks:ks_pop":181,
    "ks:ks_type":"HABITATION",
    "ks:ks_uagg_main":0,
    "name:eng_x_preferred":[
        "Teja Tola"
    ],
    "wof:name":"Teja Tola",
    "wof:placetype":"neighbourhood",
    "wof:population":181
},
  "geometry": {"coordinates":[83.95056,27.34814],"type":"Point"}
}