{
  "type": "Feature",
  "properties": {
    "iso:country":"IN",
    "ks:ks_name":"Laldhipa",
    "ks:ks_pop":97,
    "ks:ks_type":"HABITATION",
    "name:eng_x_preferred":[
        "Laldhipa"
    ],
    "wof:name":"Laldhipa",
    "wof:placetype":"locality",
    "wof:population":97
},
  "geometry": {"coordinates":[84.680037,22.173531],"type":"Point"}
}