{
  "type": "Feature",
  "properties": {
    "gn:admin1_code":"16",
    "gn:admin2_code":"510.0",
    "gn:asciiname":"Ralegaon",
    "gn:country_code":"IN",
    "gn:dem":251,
    "gn:feature_class":"P",
    "gn:feature_code":"PPL",
    "gn:name":"R\u0101legaon",
    "gn:population":0,
    "gn:timezone":"Asia/Kolkata",
    "iso:country":"IN",
    "name:mar_x_preferred":[
        "\u0930\u093e\u0933\u0947\u0917\u093e\u0902\u0935"
    ],
    "name:und_x_variant":[
        "R\u0101legaon"
    ],
    "name:urd_x_preferred":[
        "\u0631\u0627\u0644\u06d2 \u06af\u0627\u0624\u06ba"
    ],
    "wof:name":"Ralegaon",
    "wof:placetype":"locality"
},
  "geometry": {"coordinates":[78.52110999999999,20.42389],"type":"Point"}
}