{
  "type": "Feature",
  "properties": {
    "gn:admin1_code":"36.0",
    "gn:admin2_code":"156",
    "gn:asciiname":"Bithar",
    "gn:country_code":"IN",
    "gn:dem":128,
    "gn:feature_class":"P",
    "gn:feature_code":"PPL",
    "gn:name":"Bithar",
    "gn:population":0,
    "gn:timezone":"Asia/Kolkata",
    "iso:country":"IN",
    "wof:name":"Bithar",
    "wof:placetype":"locality"
},
  "geometry": {"coordinates":[80.56458000000001,26.42267],"type":"Point"}
}