{
  "type": "Feature",
  "properties": {
    "gn:admin1_code":"23.0",
    "gn:admin2_code":"41.0",
    "gn:asciiname":"Nurwala",
    "gn:country_code":"IN",
    "gn:dem":238,
    "gn:feature_class":"P",
    "gn:feature_code":"PPL",
    "gn:name":"N\u016brw\u0101la",
    "gn:population":0,
    "gn:timezone":"Asia/Kolkata",
    "iso:country":"IN",
    "ks:ks_alt_nam":"N\u016brw\u0101la",
    "ks:ks_name":"Nurwala",
    "ks:ks_type":"VILLAGE",
    "name:eng_x_preferred":[
        "Nurwala"
    ],
    "name:eng_x_variant":[
        "N\u016brw\u0101la"
    ],
    "wof:name":"Nurwala",
    "wof:placetype":"locality"
},
  "geometry": {"coordinates":[75.866213,30.961312],"type":"Point"}
}