{
  "type": "Feature",
  "properties": {
    "iso:country":"IN",
    "ks:ks_name":"Mahulapada",
    "ks:ks_pop":208,
    "ks:ks_type":"VILLAGE",
    "name:eng_x_preferred":[
        "Mahulapada"
    ],
    "wof:name":"Mahulapada",
    "wof:placetype":"locality",
    "wof:population":208
},
  "geometry": {"coordinates":[84.63063200000001,19.305286],"type":"Point"}
}