{
  "type": "Feature",
  "properties": {
    "iso:country":"IN",
    "ks:ks_name":"Hegadekumbri",
    "ks:ks_pop":25,
    "ks:ks_type":"HABITATION",
    "name:eng_x_preferred":[
        "Hegadekumbri"
    ],
    "wof:name":"Hegadekumbri",
    "wof:placetype":"locality",
    "wof:population":25
},
  "geometry": {"coordinates":[74.650109,14.91299],"type":"Point"}
}