{
  "type": "Feature",
  "properties": {
    "iso:country":"IN",
    "ks:ks_name":"Bhadel",
    "ks:ks_pop":1481,
    "ks:ks_type":"VILLAGE",
    "name:eng_x_preferred":[
        "Bhadel"
    ],
    "wof:name":"Bhadel",
    "wof:placetype":"locality",
    "wof:population":1481
},
  "geometry": {"coordinates":[85.216154,24.388338],"type":"Point"}
}