{
  "type": "Feature",
  "properties": {
    "iso:country":"IN",
    "ks:ks_name":"Bamhni Khurd",
    "ks:ks_pop":0,
    "ks:ks_type":"VILLAGE",
    "name:eng_x_preferred":[
        "Bamhni Khurd"
    ],
    "wof:name":"Bamhni Khurd",
    "wof:placetype":"locality",
    "wof:population":0
},
  "geometry": {"coordinates":[79.198527,22.776289],"type":"Point"}
}