{
  "type": "Feature",
  "properties": {
    "iso:country":"IN",
    "ks:ks_name":"Bayardengi",
    "ks:ks_pop":4202,
    "ks:ks_type":"VILLAGE",
    "name:eng_x_preferred":[
        "Bayardengi"
    ],
    "wof:name":"Bayardengi",
    "wof:placetype":"locality",
    "wof:population":4202
},
  "geometry": {"coordinates":[88.66731900000001,23.293659],"type":"Point"}
}