{
  "type": "Feature",
  "properties": {
    "iso:country":"IN",
    "ks:ks_name":"Bariya Falia",
    "ks:ks_pop":219,
    "ks:ks_type":"HABITATION",
    "name:eng_x_preferred":[
        "Bariya Falia"
    ],
    "wof:name":"Bariya Falia",
    "wof:placetype":"locality",
    "wof:population":219
},
  "geometry": {"coordinates":[73.736333,23.289028],"type":"Point"}
}