{
  "type": "Feature",
  "properties": {
    "iso:country":"IN",
    "ks:ks_name":"Papuje",
    "ks:ks_pop":287,
    "ks:ks_type":"HABITATION",
    "name:eng_x_preferred":[
        "Papuje"
    ],
    "wof:name":"Papuje",
    "wof:placetype":"locality",
    "wof:population":287
},
  "geometry": {"coordinates":[74.86854700000001,13.361101],"type":"Point"}
}