{
  "type": "Feature",
  "properties": {
    "gn:admin1_code":"36.0",
    "gn:admin2_code":"132",
    "gn:asciiname":"Bhojpur",
    "gn:country_code":"IN",
    "gn:dem":256,
    "gn:feature_class":"P",
    "gn:feature_code":"PPL",
    "gn:name":"Bhojpur",
    "gn:population":0,
    "gn:timezone":"Asia/Kolkata",
    "iso:country":"IN",
    "name:ara_x_preferred":[
        "\u0628\u0647\u0648\u062c\u0628\u0648\u0631"
    ],
    "name:ara_x_variant":[
        "\u0628\u0648\u062c \u0628\u0648\u0631"
    ],
    "name:ben_bn_x_preferred":[
        "\u09ad\u09cb\u099c\u09aa\u09c1\u09b0"
    ],
    "name:ben_in_x_preferred":[
        "\u09ad\u09cb\u099c\u09aa\u09c1\u09b0"
    ],
    "name:ceb_x_preferred":[
        "Bhojpur"
    ],
    "name:deu_x_preferred":[
        "Bhojpur"
    ],
    "name:fra_x_preferred":[
        "Bhojpur"
    ],
    "name:guj_x_preferred":[
        "\u0aad\u0acb\u0a9c\u0aaa\u0ac1\u0ab0"
    ],
    "name:hin_x_preferred":[
        "\u092d\u094b\u091c\u092a\u0941\u0930"
    ],
    "name:kan_x_preferred":[
        "\u0cad\u0ccb\u0c9c\u0ccd"
    ],
    "name:mal_x_preferred":[
        "\u0d2d\u0d4b\u0d1c\u0d4d\u0d2a\u0d42\u0d7c"
    ],
    "name:mar_x_preferred":[
        "\u092d\u094b\u091c\u092a\u0942\u0930"
    ],
    "name:nld_x_preferred":[
        "Bhojpur"
    ],
    "name:pan_x_preferred":[
        "\u0a2d\u0a4b\u0a1c\u0a2a\u0a41\u0a30"
    ],
    "name:swe_x_preferred":[
        "Bhojpur"
    ],
    "name:tam_x_preferred":[
        "\u0baa\u0bcb\u0b9c\u0bcd\u0baa\u0bc2\u0bb0\u0bcd"
    ],
    "name:tel_x_preferred":[
        "\u0c2d\u0c4b\u0c1c\u0c4d"
    ],
    "name:urd_x_preferred":[
        "\u0628\u06be\u0648\u062c\u067e\u0648\u0631"
    ],
    "name:vie_x_preferred":[
        "Bhojpur"
    ],
    "wof:name":"Bhojpur",
    "wof:placetype":"locality"
},
  "geometry": {"coordinates":[77.46626999999999,29.68598],"type":"Point"}
}