{
  "type": "Feature",
  "properties": {
    "iso:country":"IN",
    "ks:ks_name":"25 PS-A",
    "ks:ks_pop":23,
    "ks:ks_type":"VILLAGE",
    "ks:ks_uagg_main":0,
    "name:eng_x_preferred":[
        "25 PS-A"
    ],
    "wof:name":"25 PS-A",
    "wof:placetype":"neighbourhood",
    "wof:population":23
},
  "geometry": {"coordinates":[73.445818,29.543189],"type":"Point"}
}