{
  "type": "Feature",
  "properties": {
    "iso:country":"IN",
    "ks:ks_name":"Brahaman Tola",
    "ks:ks_pop":623,
    "ks:ks_type":"HABITATION",
    "ks:ks_uagg_main":0,
    "name:eng_x_preferred":[
        "Brahaman Tola"
    ],
    "wof:name":"Brahaman Tola",
    "wof:placetype":"neighbourhood",
    "wof:population":623
},
  "geometry": {"coordinates":[84.89675699999999,26.549047],"type":"Point"}
}