{
  "type": "Feature",
  "properties": {
    "iso:country":"IN",
    "ks:ks_name":"Kethavaripalem",
    "ks:ks_pop":126,
    "ks:ks_type":"HABITATION",
    "name:eng_x_preferred":[
        "Kethavaripalem"
    ],
    "wof:name":"Kethavaripalem",
    "wof:placetype":"locality",
    "wof:population":126
},
  "geometry": {"coordinates":[81.66800000000001,16.702355],"type":"Point"}
}