{
  "type": "Feature",
  "properties": {
    "iso:country":"IN",
    "ks:ks_alt_nam":"HRMBOROM BASA",
    "ks:ks_name":"Hrmborom Basa",
    "ks:ks_pop":317,
    "ks:ks_type":"HABITATION",
    "name:eng_x_preferred":[
        "Hrmborom Basa"
    ],
    "wof:name":"Hrmborom Basa",
    "wof:placetype":"locality",
    "wof:population":317
},
  "geometry": {"coordinates":[85.60643,22.318145],"type":"Point"}
}