{
  "type": "Feature",
  "properties": {
    "iso:country":"IN",
    "ks:ks_name":"Lachhamakana",
    "ks:ks_pop":340,
    "ks:ks_type":"VILLAGE",
    "name:eng_x_preferred":[
        "Lachhamakana"
    ],
    "wof:name":"Lachhamakana",
    "wof:placetype":"locality",
    "wof:population":340
},
  "geometry": {"coordinates":[86.38745299999999,20.126856],"type":"Point"}
}