{
  "type": "Feature",
  "properties": {
    "iso:country":"IN",
    "ks:ks_name":"Sardardin Wala",
    "ks:ks_pop":625,
    "ks:ks_type":"HABITATION",
    "name:eng_x_preferred":[
        "Sardardin Wala"
    ],
    "wof:name":"Sardardin Wala",
    "wof:placetype":"locality",
    "wof:population":625
},
  "geometry": {"coordinates":[74.513299,30.873001],"type":"Point"}
}