{
  "type": "Feature",
  "properties": {
    "gn:admin1_code":"35.0",
    "gn:admin2_code":"438.0",
    "gn:asciiname":"Dasana",
    "gn:country_code":"IN",
    "gn:dem":262,
    "gn:feature_class":"P",
    "gn:feature_code":"PPL",
    "gn:name":"Das\u0101na",
    "gn:population":0,
    "gn:timezone":"Asia/Kolkata",
    "iso:country":"IN",
    "ks:ks_alt_nam":"Das\u0101na",
    "ks:ks_name":"Dasana",
    "ks:ks_pop":1209,
    "ks:ks_type":"VILLAGE",
    "name:eng_x_preferred":[
        "Dasana"
    ],
    "name:eng_x_variant":[
        "Das\u0101na"
    ],
    "wof:name":"Dasana",
    "wof:placetype":"locality",
    "wof:population":1209
},
  "geometry": {"coordinates":[74.589947,22.05574],"type":"Point"}
}