{
  "type": "Feature",
  "properties": {
    "gn:admin1_code":"36",
    "gn:admin2_code":"179.0",
    "gn:asciiname":"Bajaipur",
    "gn:country_code":"IN",
    "gn:dem":103,
    "gn:feature_class":"P",
    "gn:feature_code":"PPL",
    "gn:name":"Bajaipur",
    "gn:population":0,
    "gn:timezone":"Asia/Kolkata",
    "iso:country":"IN",
    "ks:ks_name":"Bajipur",
    "ks:ks_pop":339,
    "ks:ks_type":"VILLAGE",
    "ks:ks_uagg_main":0,
    "name:eng_x_preferred":[
        "Bajipur"
    ],
    "wof:name":"Bajipur",
    "wof:placetype":"neighbourhood",
    "wof:population":339
},
  "geometry": {"coordinates":[82.08842799999999,26.10256],"type":"Point"}
}