{
  "type": "Feature",
  "properties": {
    "gn:admin1_code":"16.0",
    "gn:admin2_code":"499.0",
    "gn:asciiname":"Sunasgaon Budrukh",
    "gn:country_code":"IN",
    "gn:dem":262,
    "gn:feature_class":"P",
    "gn:feature_code":"PPL",
    "gn:name":"Sunasgaon Budrukh",
    "gn:population":0,
    "gn:timezone":"Asia/Kolkata",
    "iso:country":"IN",
    "wof:name":"Sunasgaon Budrukh",
    "wof:placetype":"locality"
},
  "geometry": {"coordinates":[75.63252,20.79926],"type":"Point"}
}