{
  "type": "Feature",
  "properties": {
    "iso:country":"IN",
    "ks:ks_name":"Umling",
    "ks:ks_pop":155,
    "ks:ks_type":"HABITATION",
    "name:eng_x_preferred":[
        "Umling"
    ],
    "wof:name":"Umling",
    "wof:placetype":"locality",
    "wof:population":155
},
  "geometry": {"coordinates":[91.274175,25.857756],"type":"Point"}
}