{
  "type": "Feature",
  "properties": {
    "iso:country":"IN",
    "ks:ks_name":"Banupada",
    "ks:ks_pop":120,
    "ks:ks_type":"HABITATION",
    "name:eng_x_preferred":[
        "Banupada"
    ],
    "wof:name":"Banupada",
    "wof:placetype":"locality",
    "wof:population":120
},
  "geometry": {"coordinates":[82.761183,20.017387],"type":"Point"}
}