{
  "type": "Feature",
  "properties": {
    "iso:country":"IN",
    "ks:ks_name":"Debendra Para",
    "ks:ks_pop":116,
    "ks:ks_type":"HABITATION",
    "name:eng_x_preferred":[
        "Debendra Para"
    ],
    "wof:name":"Debendra Para",
    "wof:placetype":"locality",
    "wof:population":116
},
  "geometry": {"coordinates":[91.623666,23.034495],"type":"Point"}
}