{
  "type": "Feature",
  "properties": {
    "gn:admin1_code":"21.0",
    "gn:admin2_code":"376.0",
    "gn:asciiname":"Badbilla",
    "gn:country_code":"IN",
    "gn:dem":82,
    "gn:feature_class":"P",
    "gn:feature_code":"PPL",
    "gn:name":"Badbilla",
    "gn:population":0,
    "gn:timezone":"Asia/Kolkata",
    "iso:country":"IN",
    "wof:name":"Badbilla",
    "wof:placetype":"locality"
},
  "geometry": {"coordinates":[86.77934,21.97744],"type":"Point"}
}