{
  "type": "Feature",
  "properties": {
    "iso:country":"IN",
    "ks:ks_name":"Makavaram",
    "ks:ks_pop":120,
    "ks:ks_type":"HABITATION",
    "name:eng_x_preferred":[
        "Makavaram"
    ],
    "wof:name":"Makavaram",
    "wof:placetype":"locality",
    "wof:population":120
},
  "geometry": {"coordinates":[84.25852999999999,18.629282],"type":"Point"}
}