{
  "type": "Feature",
  "properties": {
    "iso:country":"IN",
    "ks:ks_name":"Alipir Gamdi",
    "ks:ks_pop":252,
    "ks:ks_type":"HABITATION",
    "name:eng_x_preferred":[
        "Alipir Gamdi"
    ],
    "wof:name":"Alipir Gamdi",
    "wof:placetype":"locality",
    "wof:population":252
},
  "geometry": {"coordinates":[71.37536,23.829465],"type":"Point"}
}