{
  "type": "Feature",
  "properties": {
    "iso:country":"IN",
    "ks:ks_name":"Brikharam Pur",
    "ks:ks_pop":184,
    "ks:ks_type":"HABITATION",
    "name:eng_x_preferred":[
        "Brikharam Pur"
    ],
    "wof:name":"Brikharam Pur",
    "wof:placetype":"locality",
    "wof:population":184
},
  "geometry": {"coordinates":[92.158456,24.028423],"type":"Point"}
}