{
  "type": "Feature",
  "properties": {
    "gn:admin1_code":"39.0",
    "gn:admin2_code":"061",
    "gn:asciiname":"Suraikhet",
    "gn:country_code":"IN",
    "gn:dem":849,
    "gn:feature_class":"P",
    "gn:feature_code":"PPL",
    "gn:name":"Sura\u012bkhet",
    "gn:population":0,
    "gn:timezone":"Asia/Kolkata",
    "iso:country":"IN",
    "wof:name":"Suraikhet",
    "wof:placetype":"locality"
},
  "geometry": {"coordinates":[78.74066999999999,29.77107],"type":"Point"}
}