{
  "type": "Feature",
  "properties": {
    "gn:admin1_code":"39.0",
    "gn:admin2_code":"061",
    "gn:asciiname":"Suraikhet",
    "gn:country_code":"IN",
    "gn:dem":849,
    "gn:feature_class":"P",
    "gn:feature_code":"PPL",
    "gn:name":"Sura\u012bkhet",
    "gn:population":0,
    "gn:timezone":"Asia/Kolkata",
    "iso:country":"IN",
    "ks:ks_name":"Suraikhat",
    "ks:ks_pop":97,
    "ks:ks_type":"VILLAGE",
    "name:eng_x_preferred":[
        "Suraikhat"
    ],
    "name:eng_x_variant":[
        "Suraikhet"
    ],
    "wof:name":"Suraikhat",
    "wof:placetype":"locality",
    "wof:population":97
},
  "geometry": {"coordinates":[78.743272,29.770298],"type":"Point"}
}