{
  "type": "Feature",
  "properties": {
    "iso:country":"IN",
    "ks:ks_name":"Newalgaon",
    "ks:ks_pop":16,
    "ks:ks_type":"VILLAGE",
    "name:eng_x_preferred":[
        "Newalgaon"
    ],
    "wof:name":"Newalgaon",
    "wof:placetype":"locality",
    "wof:population":16
},
  "geometry": {"coordinates":[79.219758,29.807675],"type":"Point"}
}