{
  "type": "Feature",
  "properties": {
    "iso:country":"IN",
    "ks:ks_name":"Dewoolwadi",
    "ks:ks_pop":104,
    "ks:ks_type":"HABITATION",
    "name:eng_x_preferred":[
        "Dewoolwadi"
    ],
    "wof:name":"Dewoolwadi",
    "wof:placetype":"locality",
    "wof:population":104
},
  "geometry": {"coordinates":[73.849317,16.033207],"type":"Point"}
}