{
  "type": "Feature",
  "properties": {
    "gn:admin1_code":"36.0",
    "gn:admin2_code":"146.0",
    "gn:asciiname":"Basai Jagner",
    "gn:country_code":"IN",
    "gn:dem":233,
    "gn:feature_class":"P",
    "gn:feature_code":"PPL",
    "gn:name":"Basai Jagner",
    "gn:population":0,
    "gn:timezone":"Asia/Kolkata",
    "iso:country":"IN",
    "wof:name":"Basai Jagner",
    "wof:placetype":"locality"
},
  "geometry": {"coordinates":[77.47197,26.80644],"type":"Point"}
}