{
  "type": "Feature",
  "properties": {
    "iso:country":"IN",
    "ks:ks_name":"Paikajodi",
    "ks:ks_pop":72,
    "ks:ks_type":"VILLAGE",
    "name:eng_x_preferred":[
        "Paikajodi"
    ],
    "wof:name":"Paikajodi",
    "wof:placetype":"locality",
    "wof:population":72
},
  "geometry": {"coordinates":[83.419562,19.38302],"type":"Point"}
}