{
  "type": "Feature",
  "properties": {
    "iso:country":"IN",
    "ks:ks_alt_nam":"KEERIPATHY",
    "ks:ks_name":"Keeripathy",
    "ks:ks_pop":100,
    "ks:ks_type":"HABITATION",
    "name:eng_x_preferred":[
        "Keeripathy"
    ],
    "wof:name":"Keeripathy",
    "wof:placetype":"locality",
    "wof:population":100
},
  "geometry": {"coordinates":[76.69640699999999,11.088267],"type":"Point"}
}