{
  "type": "Feature",
  "properties": {
    "iso:country":"IN",
    "ks:ks_name":"Selvapuram",
    "ks:ks_pop":103,
    "ks:ks_type":"HABITATION",
    "name:eng_x_preferred":[
        "Selvapuram"
    ],
    "wof:name":"Selvapuram",
    "wof:placetype":"locality",
    "wof:population":103
},
  "geometry": {"coordinates":[77.263093,9.696378],"type":"Point"}
}