{
  "type": "Feature",
  "properties": {
    "gn:admin1_code":"13.0",
    "gn:admin2_code":"595.0",
    "gn:asciiname":"Onakkoor",
    "gn:country_code":"IN",
    "gn:dem":55,
    "gn:feature_class":"P",
    "gn:feature_code":"PPL",
    "gn:name":"Onakkoor",
    "gn:population":0,
    "gn:timezone":"Asia/Kolkata",
    "iso:country":"IN",
    "name:mal_x_preferred":[
        "\u0d13\u0d23\u0d15\u0d4d\u0d15\u0d42\u0d7c"
    ],
    "wof:name":"Onakkoor",
    "wof:placetype":"locality"
},
  "geometry": {"coordinates":[76.50544000000002,9.89246],"type":"Point"}
}