{
  "type": "Feature",
  "properties": {
    "gn:admin1_code":"36.0",
    "gn:admin2_code":"186",
    "gn:asciiname":"Dhanghata",
    "gn:country_code":"IN",
    "gn:dem":84,
    "gn:feature_class":"P",
    "gn:feature_code":"PPL",
    "gn:name":"Dhanghata",
    "gn:population":0,
    "gn:timezone":"Asia/Kolkata",
    "iso:country":"IN",
    "ks:ks_name":"Dhanghata",
    "ks:ks_pop":612,
    "ks:ks_type":"VILLAGE",
    "ks:ks_uagg_main":0,
    "name:eng_x_preferred":[
        "Dhanghata"
    ],
    "wof:name":"Dhanghata",
    "wof:placetype":"neighbourhood",
    "wof:population":612
},
  "geometry": {"coordinates":[83.004901,26.554651],"type":"Point"}
}