{
  "type": "Feature",
  "properties": {
    "iso:country":"IN",
    "ks:ks_name":"Madanmohanpur",
    "ks:ks_pop":402,
    "ks:ks_type":"VILLAGE",
    "name:eng_x_preferred":[
        "Madanmohanpur"
    ],
    "wof:name":"Madanmohanpur",
    "wof:placetype":"locality",
    "wof:population":402
},
  "geometry": {"coordinates":[85.188665,20.967599],"type":"Point"}
}