{
  "type": "Feature",
  "properties": {
    "gn:admin1_code":"36.0",
    "gn:admin2_code":"163.0",
    "gn:asciiname":"Purwa Kashiran",
    "gn:country_code":"IN",
    "gn:dem":137,
    "gn:feature_class":"P",
    "gn:feature_code":"PPL",
    "gn:name":"Purwa Kashir\u0101n",
    "gn:population":0,
    "gn:timezone":"Asia/Kolkata",
    "iso:country":"IN",
    "wof:name":"Purwa Kashiran",
    "wof:placetype":"locality"
},
  "geometry": {"coordinates":[79.99759,26.57691],"type":"Point"}
}