{
  "type": "Feature",
  "properties": {
    "gn:admin1_code":"21",
    "gn:admin2_code":"375.0",
    "gn:asciiname":"Rajnagar",
    "gn:country_code":"IN",
    "gn:dem":353,
    "gn:feature_class":"P",
    "gn:feature_code":"PPL",
    "gn:name":"R\u0101jnagar",
    "gn:population":0,
    "gn:timezone":"Asia/Kolkata",
    "iso:country":"IN",
    "name:ceb_x_preferred":[
        "Rajnagar"
    ],
    "name:swe_x_preferred":[
        "Rajnagar"
    ],
    "wof:name":"Rajnagar",
    "wof:placetype":"locality"
},
  "geometry": {"coordinates":[85.81454000000002,21.76277],"type":"Point"}
}