{
  "type": "Feature",
  "properties": {
    "iso:country":"IN",
    "ks:ks_name":"Basmata",
    "ks:ks_pop":328,
    "ks:ks_type":"VILLAGE",
    "name:eng_x_preferred":[
        "Basmata"
    ],
    "wof:name":"Basmata",
    "wof:placetype":"locality",
    "wof:population":328
},
  "geometry": {"coordinates":[87.34436700000001,24.144896],"type":"Point"}
}