{
  "type": "Feature",
  "properties": {
    "gn:admin1_code":"2.0",
    "gn:admin2_code":"554.0",
    "gn:asciiname":"Gollavaripalaiyam",
    "gn:country_code":"IN",
    "gn:dem":25,
    "gn:feature_class":"P",
    "gn:feature_code":"PPL",
    "gn:name":"Gollav\u0101rip\u0101laiyam",
    "gn:population":0,
    "gn:timezone":"Asia/Kolkata",
    "iso:country":"IN",
    "ks:ks_name":"Gollavaripalem",
    "ks:ks_pop":215,
    "ks:ks_type":"VILLAGE",
    "ks:ks_uagg_main":0,
    "name:eng_x_preferred":[
        "Gollavaripalem"
    ],
    "wof:name":"Gollavaripalem",
    "wof:placetype":"neighbourhood",
    "wof:population":215
},
  "geometry": {"coordinates":[79.992812,13.533346],"type":"Point"}
}