{
  "type": "Feature",
  "properties": {
    "gn:admin1_code":"35.0",
    "gn:admin2_code":"450.0",
    "gn:asciiname":"Chikhla",
    "gn:country_code":"IN",
    "gn:dem":415,
    "gn:feature_class":"P",
    "gn:feature_code":"PPL",
    "gn:name":"Chikhla",
    "gn:population":0,
    "gn:timezone":"Asia/Kolkata",
    "iso:country":"IN",
    "ks:ks_name":"Chikhala",
    "ks:ks_pop":172,
    "ks:ks_type":"VILLAGE",
    "name:eng_x_preferred":[
        "Chikhala"
    ],
    "name:eng_x_variant":[
        "Chikhla"
    ],
    "wof:name":"Chikhala",
    "wof:placetype":"locality",
    "wof:population":172
},
  "geometry": {"coordinates":[80.211485,23.910581],"type":"Point"}
}