{
  "type": "Feature",
  "properties": {
    "iso:country":"IN",
    "ks:ks_name":"Rajderwa",
    "ks:ks_pop":84,
    "ks:ks_type":"VILLAGE",
    "name:eng_x_preferred":[
        "Rajderwa"
    ],
    "wof:name":"Rajderwa",
    "wof:placetype":"locality",
    "wof:population":84
},
  "geometry": {"coordinates":[84.23944899999999,24.265645],"type":"Point"}
}