{
  "type": "Feature",
  "properties": {
    "iso:country":"IN",
    "ks:ks_name":"Ghatti Nagjiri - Marghatti",
    "ks:ks_pop":1060,
    "ks:ks_type":"HABITATION",
    "name:eng_x_preferred":[
        "Ghatti Nagjiri - Marghatti"
    ],
    "wof:name":"Ghatti Nagjiri - Marghatti",
    "wof:placetype":"locality",
    "wof:population":1060
},
  "geometry": {"coordinates":[75.719708,21.764849],"type":"Point"}
}