{
  "type": "Feature",
  "properties": {
    "gn:admin1_code":"24.0",
    "gn:admin2_code":"129.0",
    "gn:asciiname":"Barapati",
    "gn:country_code":"IN",
    "gn:dem":368,
    "gn:feature_class":"P",
    "gn:feature_code":"PPL",
    "gn:name":"B\u0101r\u0101p\u0101ti",
    "gn:population":0,
    "gn:timezone":"Asia/Kolkata",
    "iso:country":"IN",
    "ks:ks_alt_nam":"B\u0101r\u0101p\u0101ti",
    "ks:ks_name":"Barapati",
    "ks:ks_type":"VILLAGE",
    "name:eng_x_preferred":[
        "Barapati"
    ],
    "name:eng_x_variant":[
        "B\u0101r\u0101p\u0101ti"
    ],
    "wof:name":"Barapati",
    "wof:placetype":"locality"
},
  "geometry": {"coordinates":[76.446423,24.745274],"type":"Point"}
}