{
  "type": "Feature",
  "properties": {
    "iso:country":"IN",
    "ks:ks_name":"Muchikkad",
    "ks:ks_pop":276,
    "ks:ks_type":"HABITATION",
    "name:eng_x_preferred":[
        "Muchikkad"
    ],
    "wof:name":"Muchikkad",
    "wof:placetype":"locality",
    "wof:population":276
},
  "geometry": {"coordinates":[76.655137,11.07248],"type":"Point"}
}