{
  "type": "Feature",
  "properties": {
    "iso:country":"IN",
    "ks:ks_name":"Pandigummipadu",
    "ks:ks_pop":58,
    "ks:ks_type":"HABITATION",
    "name:eng_x_preferred":[
        "Pandigummipadu"
    ],
    "wof:name":"Pandigummipadu",
    "wof:placetype":"locality",
    "wof:population":58
},
  "geometry": {"coordinates":[83.094472,18.592512],"type":"Point"}
}