{
  "type": "Feature",
  "properties": {
    "iso:country":"IN",
    "ks:ks_name":"Bhadakoti",
    "ks:ks_pop":240,
    "ks:ks_type":"HABITATION",
    "name:eng_x_preferred":[
        "Bhadakoti"
    ],
    "wof:name":"Bhadakoti",
    "wof:placetype":"locality",
    "wof:population":240
},
  "geometry": {"coordinates":[79.293373,30.438238],"type":"Point"}
}