{
  "type": "Feature",
  "properties": {
    "gn:admin1_code":"28.0",
    "gn:admin2_code":"332",
    "gn:asciiname":"Kaliachak",
    "gn:country_code":"IN",
    "gn:dem":29,
    "gn:feature_class":"P",
    "gn:feature_code":"PPL",
    "gn:name":"K\u0101li\u0101chak",
    "gn:population":0,
    "gn:timezone":"Asia/Kolkata",
    "iso:country":"IN",
    "name:und_x_variant":[
        "Kalichak",
        "K\u0101li\u0101chak"
    ],
    "wof:name":"Kaliachak",
    "wof:placetype":"locality"
},
  "geometry": {"coordinates":[88.02207,24.86371],"type":"Point"}
}