{
  "type": "Feature",
  "properties": {
    "gn:admin1_code":"28.0",
    "gn:admin2_code":"332",
    "gn:asciiname":"Kaliachak",
    "gn:country_code":"IN",
    "gn:dem":29,
    "gn:feature_class":"P",
    "gn:feature_code":"PPL",
    "gn:name":"K\u0101li\u0101chak",
    "gn:population":0,
    "gn:timezone":"Asia/Kolkata",
    "iso:country":"IN",
    "ks:ks_name":"Kaliachak",
    "ks:ks_pop":3075,
    "ks:ks_type":"VILLAGE",
    "name:eng_x_preferred":[
        "Kaliachak"
    ],
    "name:und_x_variant":[
        "Kalichak",
        "K\u0101li\u0101chak"
    ],
    "wof:name":"Kaliachak",
    "wof:placetype":"locality",
    "wof:population":3075
},
  "geometry": {"coordinates":[88.009186,24.861732],"type":"Point"}
}