{
  "type": "Feature",
  "properties": {
    "iso:country":"IN",
    "ks:ks_name":"Dronacharjya Para",
    "ks:ks_pop":201,
    "ks:ks_type":"HABITATION",
    "name:eng_x_preferred":[
        "Dronacharjya Para"
    ],
    "wof:name":"Dronacharjya Para",
    "wof:placetype":"locality",
    "wof:population":201
},
  "geometry": {"coordinates":[91.53107900000001,23.214345],"type":"Point"}
}