{
  "type": "Feature",
  "properties": {
    "iso:country":"IN",
    "ks:ks_name":"Rin",
    "ks:ks_pop":193,
    "ks:ks_type":"HABITATION",
    "name:eng_x_preferred":[
        "Rin"
    ],
    "wof:name":"Rin",
    "wof:placetype":"locality",
    "wof:population":193
},
  "geometry": {"coordinates":[80.23312799999999,29.667557],"type":"Point"}
}