{
  "type": "Feature",
  "properties": {
    "iso:country":"IN",
    "ks:ks_name":"Wagholi N V",
    "ks:ks_pop":844,
    "ks:ks_type":"HABITATION",
    "name:eng_x_preferred":[
        "Wagholi N V"
    ],
    "wof:name":"Wagholi N V",
    "wof:placetype":"locality",
    "wof:population":844
},
  "geometry": {"coordinates":[73.053269,18.533313],"type":"Point"}
}