{
  "type": "Feature",
  "properties": {
    "gn:admin1_code":"2",
    "gn:admin2_code":"546.0",
    "gn:asciiname":"Devara Gopavaram",
    "gn:country_code":"IN",
    "gn:dem":9,
    "gn:feature_class":"P",
    "gn:feature_code":"PPL",
    "gn:name":"Devara Gopavaram",
    "gn:population":0,
    "gn:timezone":"Asia/Kolkata",
    "iso:country":"IN",
    "ks:ks_name":"Devaragopavaram",
    "ks:ks_pop":1212,
    "ks:ks_type":"VILLAGE",
    "ks:ks_uagg_main":0,
    "name:eng_x_preferred":[
        "Devaragopavaram"
    ],
    "wof:name":"Devaragopavaram",
    "wof:placetype":"neighbourhood",
    "wof:population":1212
},
  "geometry": {"coordinates":[81.38556699999999,16.743062],"type":"Point"}
}