{
  "type": "Feature",
  "properties": {
    "iso:country":"IN",
    "ks:ks_name":"Kodulolangipadu",
    "ks:ks_pop":51,
    "ks:ks_type":"HABITATION",
    "name:eng_x_preferred":[
        "Kodulolangipadu"
    ],
    "wof:name":"Kodulolangipadu",
    "wof:placetype":"locality",
    "wof:population":51
},
  "geometry": {"coordinates":[82.78509200000001,18.019921],"type":"Point"}
}