{
  "type": "Feature",
  "properties": {
    "iso:country":"IN",
    "ks:ks_name":"Dangini",
    "ks:ks_pop":404,
    "ks:ks_type":"VILLAGE",
    "name:eng_x_preferred":[
        "Dangini"
    ],
    "wof:name":"Dangini",
    "wof:placetype":"locality",
    "wof:population":404
},
  "geometry": {"coordinates":[83.412165,19.593634],"type":"Point"}
}