{
  "type": "Feature",
  "properties": {
    "iso:country":"IN",
    "ks:ks_name":"Dasauha468",
    "ks:ks_pop":318,
    "ks:ks_type":"HABITATION",
    "name:eng_x_preferred":[
        "Dasauha468"
    ],
    "wof:name":"Dasauha468",
    "wof:placetype":"locality",
    "wof:population":318
},
  "geometry": {"coordinates":[81.841663,24.733694],"type":"Point"}
}