{
  "type": "Feature",
  "properties": {
    "iso:country":"IN",
    "ks:ks_name":"Nagla Vishnu",
    "ks:ks_pop":246,
    "ks:ks_type":"HABITATION",
    "ks:ks_uagg_main":0,
    "name:eng_x_preferred":[
        "Nagla Vishnu"
    ],
    "wof:name":"Nagla Vishnu",
    "wof:placetype":"neighbourhood",
    "wof:population":246
},
  "geometry": {"coordinates":[78.796521,26.972255],"type":"Point"}
}