{
  "type": "Feature",
  "properties": {
    "iso:country":"IN",
    "ks:ks_name":"Haibatpur",
    "ks:ks_pop":302,
    "ks:ks_type":"HABITATION",
    "name:eng_x_preferred":[
        "Haibatpur"
    ],
    "wof:name":"Haibatpur",
    "wof:placetype":"locality",
    "wof:population":302
},
  "geometry": {"coordinates":[88.171882,22.286775],"type":"Point"}
}