{
  "type": "Feature",
  "properties": {
    "iso:country":"IN",
    "ks:ks_name":"Muradpur Urf Belar",
    "ks:ks_pop":435,
    "ks:ks_type":"HABITATION",
    "name:eng_x_preferred":[
        "Muradpur Urf Belar"
    ],
    "wof:name":"Muradpur Urf Belar",
    "wof:placetype":"locality",
    "wof:population":435
},
  "geometry": {"coordinates":[82.927837,26.696397],"type":"Point"}
}