{
  "type": "Feature",
  "properties": {
    "iso:country":"IN",
    "ks:ks_name":"Bilkod",
    "ks:ks_pop":19,
    "ks:ks_type":"HABITATION",
    "name:eng_x_preferred":[
        "Bilkod"
    ],
    "wof:name":"Bilkod",
    "wof:placetype":"locality",
    "wof:population":19
},
  "geometry": {"coordinates":[74.74373,14.411027],"type":"Point"}
}