{
  "type": "Feature",
  "properties": {
    "gn:admin1_code":"19",
    "gn:admin2_code":"568.0",
    "gn:asciiname":"Hagalpura",
    "gn:country_code":"IN",
    "gn:dem":591,
    "gn:feature_class":"P",
    "gn:feature_code":"PPL",
    "gn:name":"Hagalpura",
    "gn:population":0,
    "gn:timezone":"Asia/Kolkata",
    "iso:country":"IN",
    "ks:ks_name":"Hagalapura",
    "ks:ks_pop":150,
    "ks:ks_type":"HABITATION",
    "name:eng_x_preferred":[
        "Hagalapura"
    ],
    "name:eng_x_variant":[
        "Hagalpura"
    ],
    "wof:name":"Hagalapura",
    "wof:placetype":"locality",
    "wof:population":150
},
  "geometry": {"coordinates":[74.999269,14.263138],"type":"Point"}
}