{
  "type": "Feature",
  "properties": {
    "iso:country":"IN",
    "ks:ks_name":"Chinakapavaram",
    "ks:ks_pop":22,
    "ks:ks_type":"HABITATION",
    "name:eng_x_preferred":[
        "Chinakapavaram"
    ],
    "wof:name":"Chinakapavaram",
    "wof:placetype":"locality",
    "wof:population":22
},
  "geometry": {"coordinates":[81.359058,17.212065],"type":"Point"}
}