{
  "type": "Feature",
  "properties": {
    "gn:country":"IN",
    "gn:fcode":"PPL",
    "gn:population":0,
    "iso:country":"IN",
    "name:ara_x_preferred":[
        "\u0623\u0631\u0627\u0645\u0641\u0627\u0631\u064a"
    ],
    "name:ben_bn_x_preferred":[
        "\u0986\u09b0\u09be\u09ae\u0993\u09df\u09be\u09dc\u09bf"
    ],
    "name:ben_in_x_preferred":[
        "\u0986\u09b0\u09be\u09ae\u0993\u09df\u09be\u09dc\u09bf"
    ],
    "name:guj_x_preferred":[
        "\u0a86\u0ab0\u0abe\u0aae\u0ab5\u0abe\u0ab0\u0ac0"
    ],
    "name:hin_x_preferred":[
        "\u0906\u0930\u093e\u092e\u0935\u093e\u095c\u0940"
    ],
    "name:kan_x_preferred":[
        "\u0c85\u0cb0\u0cae\u0ccd"
    ],
    "name:mal_x_preferred":[
        "\u0d05\u0d30\u0d3e\u0d02\u0d35\u0d3e\u0d30\u0d3f"
    ],
    "name:mar_x_preferred":[
        "\u0905\u0930\u093e\u092e\u0935\u093e\u0930\u0940"
    ],
    "name:pan_x_preferred":[
        "\u0a05\u0a30\u0a3e\u0a2e\u0a35\u0a3e\u0a30\u0a40"
    ],
    "name:tam_x_preferred":[
        "\u0b85\u0bb0\u0bae\u0bcd\u0bb5\u0bbe\u0bb0\u0bbf"
    ],
    "name:tel_x_preferred":[
        "\u0c06\u0c30\u0c3e\u0c02\u0c35\u0c3e\u0c30\u0c3f"
    ],
    "name:urd_x_preferred":[
        "\u0622\u0631\u0627\u0645 \u0648\u0627\u0691\u06cc"
    ],
    "qs:name":"Aramwari",
    "qs:name_adm0":"India",
    "qs:name_adm1":"Jammu and Kashmir",
    "qs:photos":1,
    "qs:photos_1k":1,
    "qs:photos_9k":1,
    "qs:photos_9r":1,
    "qs:photos_all":1,
    "qs:photos_sr":1,
    "qs:placetype":"Suburb",
    "qs:pop_sr":"0",
    "wof:name":"Aramwari",
    "wof:placetype":"neighbourhood",
    "wof:population":0
},
  "geometry": {"coordinates":[74.84166999999999,34.06806],"type":"Point"}
}