{
  "type": "Feature",
  "properties": {
    "gn:admin1_code":"24.0",
    "gn:admin2_code":"102.0",
    "gn:asciiname":"Bhojusar Upadhiyan",
    "gn:country_code":"IN",
    "gn:dem":264,
    "gn:feature_class":"P",
    "gn:feature_code":"PPL",
    "gn:name":"Bhoj\u016bsar Up\u0101dhiy\u0101n",
    "gn:population":0,
    "gn:timezone":"Asia/Kolkata",
    "iso:country":"IN",
    "wof:name":"Bhojusar Upadhiyan",
    "wof:placetype":"locality"
},
  "geometry": {"coordinates":[74.36331,28.30478],"type":"Point"}
}