{
  "type": "Feature",
  "properties": {
    "gn:admin1_code":"28.0",
    "gn:asciiname":"Mahalwari",
    "gn:country_code":"IN",
    "gn:dem":48,
    "gn:feature_class":"P",
    "gn:feature_code":"PPL",
    "gn:name":"Mahalw\u0101ri",
    "gn:population":0,
    "gn:timezone":"Asia/Kolkata",
    "iso:country":"IN",
    "name:pol_x_preferred":[
        "Mahalwari"
    ],
    "wof:name":"Mahalwari",
    "wof:placetype":"neighbourhood"
},
  "geometry": {"coordinates":[87.82823,25.93963],"type":"Point"}
}