{
  "type": "Feature",
  "properties": {
    "iso:country":"IN",
    "ks:ks_name":"Besalbhadi",
    "ks:ks_pop":456,
    "ks:ks_type":"VILLAGE",
    "name:eng_x_preferred":[
        "Besalbhadi"
    ],
    "wof:name":"Besalbhadi",
    "wof:placetype":"locality",
    "wof:population":456
},
  "geometry": {"coordinates":[84.494165,22.376745],"type":"Point"}
}