{
  "type": "Feature",
  "properties": {
    "gn:admin1_code":"39.0",
    "gn:admin2_code":"64.0",
    "gn:asciiname":"Chaurgair",
    "gn:country_code":"IN",
    "gn:dem":1073,
    "gn:feature_class":"P",
    "gn:feature_code":"PPL",
    "gn:name":"Chaurgair",
    "gn:population":0,
    "gn:timezone":"Asia/Kolkata",
    "iso:country":"IN",
    "wof:name":"Chaurgair",
    "wof:placetype":"locality"
},
  "geometry": {"coordinates":[79.90025,29.69212000000001],"type":"Point"}
}