{
  "type": "Feature",
  "properties": {
    "iso:country":"IN",
    "ks:ks_name":"Marrimula",
    "ks:ks_pop":605,
    "ks:ks_type":"HABITATION",
    "name:eng_x_preferred":[
        "Marrimula"
    ],
    "wof:name":"Marrimula",
    "wof:placetype":"locality",
    "wof:population":605
},
  "geometry": {"coordinates":[81.866955,16.570595],"type":"Point"}
}