{
  "type": "Feature",
  "properties": {
    "iso:country":"IN",
    "ks:ks_name":"Goaridih",
    "ks:ks_pop":246,
    "ks:ks_type":"VILLAGE",
    "name:eng_x_preferred":[
        "Goaridih"
    ],
    "wof:name":"Goaridih",
    "wof:placetype":"locality",
    "wof:population":246
},
  "geometry": {"coordinates":[87.14727999999999,24.714175],"type":"Point"}
}