{
  "type": "Feature",
  "properties": {
    "iso:country":"IN",
    "ks:ks_name":"Mugali",
    "ks:ks_pop":292,
    "ks:ks_type":"HABITATION",
    "name:eng_x_preferred":[
        "Mugali"
    ],
    "wof:name":"Mugali",
    "wof:placetype":"locality",
    "wof:population":292
},
  "geometry": {"coordinates":[74.458484,14.220845],"type":"Point"}
}