{
  "type": "Feature",
  "properties": {
    "iso:country":"IN",
    "name:ara_x_preferred":[
        "\u0636\u0627\u062d\u064a\u0629 \u062a\u0634\u064a\u0646\u0627\u064a"
    ],
    "name:ast_x_preferred":[
        "Chennai"
    ],
    "name:ben_x_preferred":[
        "\u099a\u09c7\u09a8\u09cd\u09a8\u09be\u0987 \u099c\u09c7\u09b2\u09be"
    ],
    "name:bho_x_preferred":[
        "\u091a\u0947\u0928\u094d\u0928\u0908 \u091c\u093f\u0932\u093e"
    ],
    "name:deu_x_preferred":[
        "Chennai"
    ],
    "name:eng_x_preferred":[
        "Chennai district"
    ],
    "name:fin_x_preferred":[
        "Chennain piirikunta"
    ],
    "name:guj_x_preferred":[
        "\u0a9a\u0ac7\u0aa8\u0acd\u0aa8\u0a88 \u0a9c\u0abf\u0ab2\u0acd\u0ab2\u0acb"
    ],
    "name:hin_x_preferred":[
        "\u091a\u0947\u0928\u094d\u0928\u0908 \u091c\u093f\u0932\u093e"
    ],
    "name:jpn_x_preferred":[
        "\u30c1\u30a7\u30f3\u30ca\u30a4\u770c"
    ],
    "name:kor_x_preferred":[
        "\uccb8\ub098\uc774 \uad6c"
    ],
    "name:mal_x_preferred":[
        "\u0d1a\u0d46\u0d28\u0d4d\u0d28\u0d48 \u0d1c\u0d3f\u0d32\u0d4d\u0d32"
    ],
    "name:mar_x_preferred":[
        "\u091a\u0947\u0928\u094d\u0928\u0908 \u091c\u093f\u0932\u094d\u0939\u093e"
    ],
    "name:nep_x_preferred":[
        "\u091a\u0947\u0928\u094d\u0928\u0908 \u091c\u093f\u0932\u094d\u0932\u093e"
    ],
    "name:new_x_preferred":[
        "\u091a\u0947\u0928\u094d\u0928\u0908 \u091c\u093f\u0932\u094d\u0932\u093e"
    ],
    "name:nld_x_preferred":[
        "Chennai district"
    ],
    "name:nob_x_preferred":[
        "Chennai"
    ],
    "name:ori_x_preferred":[
        "\u0b1a\u0b47\u0b28\u0b4d\u0b28\u0b3e\u0b07 \u0b1c\u0b3f\u0b32\u0b4d\u0b32\u0b3e"
    ],
    "name:pnb_x_preferred":[
        "\u0636\u0644\u0639 \u0686\u06cc\u0646\u0627\u0626"
    ],
    "name:rus_x_preferred":[
        "\u0427\u0435\u043d\u043d\u0430\u0438"
    ],
    "name:san_x_preferred":[
        "\u091a\u0947\u0928\u094d\u0928\u0948\u092e\u0923\u094d\u0921\u0932\u092e\u094d"
    ],
    "name:sat_x_preferred":[
        "\u1c6a\u1c6e\u1c71\u1c71\u1c5f\u1c6d \u1c66\u1c5a\u1c71\u1c5a\u1c5b"
    ],
    "name:spa_x_preferred":[
        "Chennai"
    ],
    "name:tam_x_preferred":[
        "\u0b9a\u0bc6\u0ba9\u0bcd\u0ba9\u0bc8 \u0bae\u0bbe\u0bb5\u0b9f\u0bcd\u0b9f\u0bae\u0bcd"
    ],
    "name:tel_x_preferred":[
        "\u0c1a\u0c46\u0c28\u0c4d\u0c28\u0c48 \u0c1c\u0c3f\u0c32\u0c4d\u0c32\u0c3e"
    ],
    "name:vie_x_preferred":[
        "Chennai"
    ],
    "name:zho_x_preferred":[
        "\u91d1\u5948\u7e23"
    ],
    "qs:name":"Sembarambakkam",
    "qs:name_adm0":"India",
    "qs:name_adm1":"Tamil Nadu",
    "qs:photos":43,
    "qs:photos_1k":9,
    "qs:photos_9k":1,
    "qs:photos_9r":2,
    "qs:photos_all":43,
    "qs:photos_sr":2,
    "qs:placetype":"Suburb",
    "qs:pop_sr":"0",
    "wd:wordcount":1405,
    "wof:name":"Sembarambakkam",
    "wof:placetype":"neighbourhood"
},
  "geometry": {"coordinates":[80.213584,13.148358],"type":"Point"}
}