{
  "type": "Feature",
  "properties": {
    "iso:country":"IN",
    "qs:name":"Sembarambakkam",
    "qs:name_adm0":"India",
    "qs:name_adm1":"Tamil Nadu",
    "qs:photos":43,
    "qs:photos_1k":9,
    "qs:photos_9k":1,
    "qs:photos_9r":2,
    "qs:photos_all":43,
    "qs:photos_sr":2,
    "qs:placetype":"Suburb",
    "qs:pop_sr":"0",
    "wd:wordcount":1405,
    "wof:name":"Sembarambakkam",
    "wof:placetype":"neighbourhood"
},
  "geometry": {"coordinates":[80.213584,13.148358],"type":"Point"}
}