{
  "type": "Feature",
  "properties": {
    "iso:country":"IN",
    "ks:ks_name":"Yadapalem",
    "ks:ks_pop":427,
    "ks:ks_type":"HABITATION",
    "name:eng_x_preferred":[
        "Yadapalem"
    ],
    "wof:name":"Yadapalem",
    "wof:placetype":"locality",
    "wof:population":427
},
  "geometry": {"coordinates":[80.0307,13.723783],"type":"Point"}
}