{
  "type": "Feature",
  "properties": {
    "iso:country":"IN",
    "ks:ks_alt_nam":"MATA MATI",
    "ks:ks_name":"Mata Mati",
    "ks:ks_pop":200,
    "ks:ks_type":"HABITATION",
    "name:eng_x_preferred":[
        "Mata Mati"
    ],
    "wof:name":"Mata Mati",
    "wof:placetype":"locality",
    "wof:population":200
},
  "geometry": {"coordinates":[72.74225300000001,24.433656],"type":"Point"}
}