{
  "type": "Feature",
  "properties": {
    "iso:country":"IN",
    "ks:ks_name":"Burlagutta Palli",
    "ks:ks_pop":125,
    "ks:ks_type":"HABITATION",
    "name:eng_x_preferred":[
        "Burlagutta Palli"
    ],
    "wof:name":"Burlagutta Palli",
    "wof:placetype":"locality",
    "wof:population":125
},
  "geometry": {"coordinates":[78.415898,14.144888],"type":"Point"}
}