{
  "type": "Feature",
  "properties": {
    "iso:country":"IN",
    "ks:ks_name":"Tichakpura",
    "ks:ks_pop":235,
    "ks:ks_type":"VILLAGE",
    "name:eng_x_preferred":[
        "Tichakpura"
    ],
    "wof:name":"Tichakpura",
    "wof:placetype":"locality",
    "wof:population":235
},
  "geometry": {"coordinates":[73.33888899999999,21.101361],"type":"Point"}
}