{
  "type": "Feature",
  "properties": {
    "iso:country":"IN",
    "ks:ks_name":"Urma",
    "ks:ks_pop":312,
    "ks:ks_type":"VILLAGE",
    "name:eng_x_preferred":[
        "Urma"
    ],
    "wof:name":"Urma",
    "wof:placetype":"locality",
    "wof:population":312
},
  "geometry": {"coordinates":[80.29982699999999,29.734257],"type":"Point"}
}