{
  "type": "Feature",
  "properties": {
    "gn:admin1_code":"34.0",
    "gn:admin2_code":"222.0",
    "gn:asciiname":"Pansalla",
    "gn:country_code":"IN",
    "gn:dem":47,
    "gn:feature_class":"P",
    "gn:feature_code":"PPL",
    "gn:name":"Pansalla",
    "gn:population":0,
    "gn:timezone":"Asia/Kolkata",
    "iso:country":"IN",
    "ks:ks_name":"Pansalla",
    "ks:ks_pop":2991,
    "ks:ks_type":"VILLAGE",
    "ks:ks_uagg_main":0,
    "name:eng_x_preferred":[
        "Pansalla"
    ],
    "wof:name":"Pansalla",
    "wof:placetype":"neighbourhood",
    "wof:population":2991
},
  "geometry": {"coordinates":[86.098603,25.676227],"type":"Point"}
}