{
  "type": "Feature",
  "properties": {
    "iso:country":"IN",
    "ks:ks_name":"Saru Mechai No 3",
    "ks:ks_pop":420,
    "ks:ks_type":"HABITATION",
    "name:eng_x_preferred":[
        "Saru Mechai No 3"
    ],
    "wof:name":"Saru Mechai No 3",
    "wof:placetype":"locality",
    "wof:population":420
},
  "geometry": {"coordinates":[95.73045399999999,27.664306],"type":"Point"}
}