{
  "type": "Feature",
  "properties": {
    "gn:admin1_code":"35",
    "gn:admin2_code":"447.0",
    "gn:asciiname":"Devthan",
    "gn:country_code":"IN",
    "gn:dem":442,
    "gn:feature_class":"P",
    "gn:feature_code":"PPL",
    "gn:name":"Devth\u0101n",
    "gn:population":0,
    "gn:timezone":"Asia/Kolkata",
    "iso:country":"IN",
    "ks:ks_alt_nam":"DEOTHAN",
    "ks:ks_name":"Deothan",
    "ks:ks_pop":271,
    "ks:ks_type":"HABITATION",
    "name:eng_x_preferred":[
        "Deothan"
    ],
    "name:eng_x_variant":[
        "Devthan"
    ],
    "wof:name":"Deothan",
    "wof:placetype":"locality",
    "wof:population":271
},
  "geometry": {"coordinates":[77.57316299999999,22.326042],"type":"Point"}
}