{
  "type": "Feature",
  "properties": {
    "iso:country":"IN",
    "ks:ks_name":"Njellorapalli",
    "ks:ks_pop":900,
    "ks:ks_type":"HABITATION",
    "name:eng_x_preferred":[
        "Njellorapalli"
    ],
    "wof:name":"Njellorapalli",
    "wof:placetype":"locality",
    "wof:population":900
},
  "geometry": {"coordinates":[75.71036700000001,11.658734],"type":"Point"}
}