{
  "type": "Feature",
  "properties": {
    "iso:country":"IN",
    "ks:ks_name":"Malvan",
    "ks:ks_pop":5019,
    "ks:ks_type":"VILLAGE",
    "name:eng_x_preferred":[
        "Malvan"
    ],
    "wof:name":"Malvan",
    "wof:placetype":"locality",
    "wof:population":5019
},
  "geometry": {"coordinates":[72.911832,20.717229],"type":"Point"}
}