{
  "type": "Feature",
  "properties": {
    "iso:country":"IN",
    "ks:ks_name":"Tinjhari",
    "ks:ks_pop":116,
    "ks:ks_type":"HABITATION",
    "name:eng_x_preferred":[
        "Tinjhari"
    ],
    "wof:name":"Tinjhari",
    "wof:placetype":"locality",
    "wof:population":116
},
  "geometry": {"coordinates":[85.573802,23.155911],"type":"Point"}
}