{
  "type": "Feature",
  "properties": {
    "iso:country":"IN",
    "ks:ks_name":"Malpara Kutubpur",
    "ks:ks_pop":523,
    "ks:ks_type":"HABITATION",
    "name:eng_x_preferred":[
        "Malpara Kutubpur"
    ],
    "wof:name":"Malpara Kutubpur",
    "wof:placetype":"locality",
    "wof:population":523
},
  "geometry": {"coordinates":[88.19320999999999,25.073723],"type":"Point"}
}