{
  "type": "Feature",
  "properties": {
    "iso:country":"IN",
    "ks:ks_name":"Kodi",
    "ks:ks_pop":178,
    "ks:ks_type":"HABITATION",
    "name:eng_x_preferred":[
        "Kodi"
    ],
    "wof:name":"Kodi",
    "wof:placetype":"locality",
    "wof:population":178
},
  "geometry": {"coordinates":[74.87746300000001,12.831796],"type":"Point"}
}