{
  "type": "Feature",
  "properties": {
    "iso:country":"IN",
    "ks:ks_name":"Powarti",
    "ks:ks_pop":466,
    "ks:ks_type":"HABITATION",
    "name:eng_x_preferred":[
        "Powarti"
    ],
    "wof:name":"Powarti",
    "wof:placetype":"locality",
    "wof:population":466
},
  "geometry": {"coordinates":[81.012378,18.413912],"type":"Point"}
}