{
  "type": "Feature",
  "properties": {
    "iso:country":"IN",
    "ks:ks_name":"Bharwadi Ryt",
    "ks:ks_pop":331,
    "ks:ks_type":"VILLAGE",
    "ks:ks_uagg_main":0,
    "name:eng_x_preferred":[
        "Bharwadi Ryt"
    ],
    "wof:name":"Bharwadi Ryt",
    "wof:placetype":"neighbourhood",
    "wof:population":331
},
  "geometry": {"coordinates":[76.911168,22.019871],"type":"Point"}
}