{
  "type": "Feature",
  "properties": {
    "gn:admin1_code":"21.0",
    "gn:admin2_code":"393",
    "gn:asciiname":"Gumsar",
    "gn:country_code":"IN",
    "gn:dem":177,
    "gn:feature_class":"P",
    "gn:feature_code":"PPL",
    "gn:name":"Gumsar",
    "gn:population":0,
    "gn:timezone":"Asia/Kolkata",
    "iso:country":"IN",
    "name:und_x_variant":[
        "Gumsa",
        "Gumsar"
    ],
    "wof:name":"Gumsar",
    "wof:placetype":"locality"
},
  "geometry": {"coordinates":[83.37411999999998,20.36554],"type":"Point"}
}