{
  "type": "Feature",
  "properties": {
    "iso:country":"IN",
    "ks:ks_name":"Joynagar-Punjee N.C.",
    "ks:ks_pop":101,
    "ks:ks_type":"VILLAGE",
    "name:eng_x_preferred":[
        "Joynagar-Punjee N.C."
    ],
    "wof:name":"Joynagar-Punjee N.C.",
    "wof:placetype":"locality",
    "wof:population":101
},
  "geometry": {"coordinates":[92.514036,24.552238],"type":"Point"}
}