{
  "type": "Feature",
  "properties": {
    "iso:country":"IN",
    "ks:ks_name":"Thoppukkad",
    "ks:ks_pop":267,
    "ks:ks_type":"HABITATION",
    "name:eng_x_preferred":[
        "Thoppukkad"
    ],
    "wof:name":"Thoppukkad",
    "wof:placetype":"locality",
    "wof:population":267
},
  "geometry": {"coordinates":[76.644976,11.149309],"type":"Point"}
}