{
  "type": "Feature",
  "properties": {
    "iso:country":"IN",
    "ks:ks_name":"Purbba Sahapur",
    "ks:ks_pop":1924,
    "ks:ks_type":"VILLAGE",
    "ks:ks_uagg_main":0,
    "name:eng_x_preferred":[
        "Purbba Sahapur"
    ],
    "wof:name":"Purbba Sahapur",
    "wof:placetype":"neighbourhood",
    "wof:population":1924
},
  "geometry": {"coordinates":[88.380881,23.202009],"type":"Point"}
}