{
  "type": "Feature",
  "properties": {
    "iso:country":"IN",
    "ks:ks_name":"Kondavalsa",
    "ks:ks_pop":324,
    "ks:ks_type":"HABITATION",
    "name:eng_x_preferred":[
        "Kondavalsa"
    ],
    "wof:name":"Kondavalsa",
    "wof:placetype":"locality",
    "wof:population":324
},
  "geometry": {"coordinates":[82.97682399999999,18.50626],"type":"Point"}
}