{
  "type": "Feature",
  "properties": {
    "iso:country":"IN",
    "ks:ks_name":"6 JSL",
    "ks:ks_pop":8,
    "ks:ks_type":"VILLAGE",
    "name:eng_x_preferred":[
        "6 JSL"
    ],
    "wof:name":"6 JSL",
    "wof:placetype":"locality",
    "wof:population":8
},
  "geometry": {"coordinates":[75.356233,29.148531],"type":"Point"}
}