{
  "type": "Feature",
  "properties": {
    "gn:admin1_code":"11.0",
    "gn:admin2_code":"26.0",
    "gn:asciiname":"Bajauri",
    "gn:country_code":"IN",
    "gn:dem":1040,
    "gn:feature_class":"P",
    "gn:feature_code":"PPL",
    "gn:name":"Bajauri",
    "gn:population":0,
    "gn:timezone":"Asia/Kolkata",
    "iso:country":"IN",
    "wof:name":"Bajauri",
    "wof:placetype":"locality"
},
  "geometry": {"coordinates":[77.53627,31.38205],"type":"Point"}
}