{
  "type": "Feature",
  "properties": {
    "iso:country":"IN",
    "ks:ks_name":"Haritola",
    "ks:ks_pop":272,
    "ks:ks_type":"HABITATION",
    "name:eng_x_preferred":[
        "Haritola"
    ],
    "wof:name":"Haritola",
    "wof:placetype":"locality",
    "wof:population":272
},
  "geometry": {"coordinates":[86.19599599999999,24.057482],"type":"Point"}
}