{
  "type": "Feature",
  "properties": {
    "iso:country":"IN",
    "ks:ks_alt_nam":"KOWRI",
    "ks:ks_name":"Kowri",
    "ks:ks_pop":114,
    "ks:ks_type":"HABITATION",
    "name:eng_x_preferred":[
        "Kowri"
    ],
    "wof:name":"Kowri",
    "wof:placetype":"locality",
    "wof:population":114
},
  "geometry": {"coordinates":[75.381787,13.633971],"type":"Point"}
}