{
  "type": "Feature",
  "properties": {
    "iso:country":"IN",
    "ks:ks_alt_nam":"SALAIA",
    "ks:ks_name":"Salaia",
    "ks:ks_pop":838,
    "ks:ks_type":"HABITATION",
    "name:eng_x_preferred":[
        "Salaia"
    ],
    "wof:name":"Salaia",
    "wof:placetype":"locality",
    "wof:population":838
},
  "geometry": {"coordinates":[84.19114999999999,24.321932],"type":"Point"}
}