{
  "type": "Feature",
  "properties": {
    "iso:country":"IN",
    "ks:ks_name":"Dhandanga",
    "ks:ks_pop":385,
    "ks:ks_type":"HABITATION",
    "name:eng_x_preferred":[
        "Dhandanga"
    ],
    "wof:name":"Dhandanga",
    "wof:placetype":"locality",
    "wof:population":385
},
  "geometry": {"coordinates":[87.746054,23.866014],"type":"Point"}
}