{
  "type": "Feature",
  "properties": {
    "iso:country":"IN",
    "ks:ks_alt_nam":"FAKIRA PUR",
    "ks:ks_name":"Fakira Pur",
    "ks:ks_pop":435,
    "ks:ks_type":"HABITATION",
    "name:eng_x_preferred":[
        "Fakira Pur"
    ],
    "wof:name":"Fakira Pur",
    "wof:placetype":"locality",
    "wof:population":435
},
  "geometry": {"coordinates":[82.214603,27.587675],"type":"Point"}
}