{
  "type": "Feature",
  "properties": {
    "iso:country":"IN",
    "ks:ks_name":"Sabajpur South",
    "ks:ks_pop":789,
    "ks:ks_type":"HABITATION",
    "name:eng_x_preferred":[
        "Sabajpur South"
    ],
    "wof:name":"Sabajpur South",
    "wof:placetype":"locality",
    "wof:population":789
},
  "geometry": {"coordinates":[92.187709,24.361231],"type":"Point"}
}