{
  "type": "Feature",
  "properties": {
    "iso:country":"IN",
    "ks:ks_alt_nam":"Lingyanaik tanda",
    "ks:ks_name":"Lingyanaik Tanda",
    "ks:ks_pop":80,
    "ks:ks_type":"HABITATION",
    "name:eng_x_preferred":[
        "Lingyanaik Tanda"
    ],
    "wof:name":"Lingyanaik Tanda",
    "wof:placetype":"locality",
    "wof:population":80
},
  "geometry": {"coordinates":[77.69238799999999,17.136992],"type":"Point"}
}