{
  "type": "Feature",
  "properties": {
    "iso:country":"IN",
    "ks:ks_name":"Bhirkapada",
    "ks:ks_pop":80,
    "ks:ks_type":"HABITATION",
    "name:eng_x_preferred":[
        "Bhirkapada"
    ],
    "wof:name":"Bhirkapada",
    "wof:placetype":"locality",
    "wof:population":80
},
  "geometry": {"coordinates":[82.93209,20.517912],"type":"Point"}
}