{
  "type": "Feature",
  "properties": {
    "iso:country":"IN",
    "ks:ks_name":"Baghar",
    "ks:ks_pop":1673,
    "ks:ks_type":"VILLAGE",
    "name:eng_x_preferred":[
        "Baghar"
    ],
    "wof:name":"Baghar",
    "wof:placetype":"locality",
    "wof:population":1673
},
  "geometry": {"coordinates":[79.844549,30.038726],"type":"Point"}
}