{
  "type": "Feature",
  "properties": {
    "gn:admin1_code":"19.0",
    "gn:admin2_code":"570.0",
    "gn:asciiname":"Dinnekere",
    "gn:country_code":"IN",
    "gn:dem":1110,
    "gn:feature_class":"P",
    "gn:feature_code":"PPL",
    "gn:name":"Dinnekere",
    "gn:population":0,
    "gn:timezone":"Asia/Kolkata",
    "iso:country":"IN",
    "ks:ks_name":"Dinnekere",
    "ks:ks_pop":53,
    "ks:ks_type":"HABITATION",
    "name:eng_x_preferred":[
        "Dinnekere"
    ],
    "wof:name":"Dinnekere",
    "wof:placetype":"locality",
    "wof:population":53
},
  "geometry": {"coordinates":[75.685153,13.27382],"type":"Point"}
}