{
  "type": "Feature",
  "properties": {
    "iso:country":"IN",
    "ks:ks_name":"Vellanchattukal Jn",
    "ks:ks_pop":559,
    "ks:ks_type":"HABITATION",
    "name:eng_x_preferred":[
        "Vellanchattukal Jn"
    ],
    "wof:name":"Vellanchattukal Jn",
    "wof:placetype":"locality",
    "wof:population":559
},
  "geometry": {"coordinates":[76.29506499999999,11.154205],"type":"Point"}
}