{
  "type": "Feature",
  "properties": {
    "iso:country":"IN",
    "ks:ks_name":"Mahulbana",
    "ks:ks_pop":190,
    "ks:ks_type":"VILLAGE",
    "name:eng_x_preferred":[
        "Mahulbana"
    ],
    "wof:name":"Mahulbana",
    "wof:placetype":"locality",
    "wof:population":190
},
  "geometry": {"coordinates":[87.72381799999999,24.959504],"type":"Point"}
}