{
  "type": "Feature",
  "properties": {
    "iso:country":"IN",
    "ks:ks_name":"Kalipur",
    "ks:ks_pop":812,
    "ks:ks_type":"VILLAGE",
    "name:eng_x_preferred":[
        "Kalipur"
    ],
    "wof:name":"Kalipur",
    "wof:placetype":"locality",
    "wof:population":812
},
  "geometry": {"coordinates":[86.952399,23.350681],"type":"Point"}
}