{
  "type": "Feature",
  "properties": {
    "iso:country":"IN",
    "ks:ks_name":"Kandhulimari",
    "ks:ks_pop":1224,
    "ks:ks_type":"VILLAGE",
    "ks:ks_uagg_main":0,
    "name:eng_x_preferred":[
        "Kandhulimari"
    ],
    "wof:name":"Kandhulimari",
    "wof:placetype":"neighbourhood",
    "wof:population":1224
},
  "geometry": {"coordinates":[92.60803300000001,26.462455],"type":"Point"}
}