{
  "type": "Feature",
  "properties": {
    "iso:country":"IN",
    "ks:ks_name":"Bhadua",
    "ks:ks_pop":1992,
    "ks:ks_type":"VILLAGE",
    "ks:ks_uagg_main":0,
    "name:eng_x_preferred":[
        "Bhadua"
    ],
    "wof:name":"Bhadua",
    "wof:placetype":"locality",
    "wof:population":1992
},
  "geometry": {"coordinates":[88.304377,22.713582],"type":"Point"}
}