{
  "type": "Feature",
  "properties": {
    "gn:admin1_code":"34.0",
    "gn:admin2_code":"239.0",
    "gn:asciiname":"Lachhmi Bigha",
    "gn:country_code":"IN",
    "gn:dem":71,
    "gn:feature_class":"P",
    "gn:feature_code":"PPL",
    "gn:name":"Lachhmi Bigha",
    "gn:population":0,
    "gn:timezone":"Asia/Kolkata",
    "iso:country":"IN",
    "wof:name":"Lachhmi Bigha",
    "wof:placetype":"locality"
},
  "geometry": {"coordinates":[84.99603,25.16766],"type":"Point"}
}