{
  "type": "Feature",
  "properties": {
    "gn:admin1_code":"16.0",
    "gn:admin2_code":"500",
    "gn:asciiname":"Kingaon Raja",
    "gn:country_code":"IN",
    "gn:dem":512,
    "gn:feature_class":"P",
    "gn:feature_code":"PPL",
    "gn:name":"Kingaon R\u0101ja",
    "gn:population":0,
    "gn:timezone":"Asia/Kolkata",
    "iso:country":"IN",
    "wof:name":"Kingaon Raja",
    "wof:placetype":"locality"
},
  "geometry": {"coordinates":[76.24446,19.98916],"type":"Point"}
}