{
  "type": "Feature",
  "properties": {
    "iso:country":"IN",
    "ks:ks_alt_nam":"MAHUATAR RANA TOLA",
    "ks:ks_name":"Mahuatar Rana Tola",
    "ks:ks_pop":229,
    "ks:ks_type":"HABITATION",
    "name:eng_x_preferred":[
        "Mahuatar Rana Tola"
    ],
    "wof:name":"Mahuatar Rana Tola",
    "wof:placetype":"locality",
    "wof:population":229
},
  "geometry": {"coordinates":[85.07649499999999,24.185947],"type":"Point"}
}