{
  "type": "Feature",
  "properties": {
    "iso:country":"IN",
    "ks:ks_name":"Majha Hakumpur Khurd",
    "ks:ks_pop":459,
    "ks:ks_type":"HABITATION",
    "name:eng_x_preferred":[
        "Majha Hakumpur Khurd"
    ],
    "wof:name":"Majha Hakumpur Khurd",
    "wof:placetype":"locality",
    "wof:population":459
},
  "geometry": {"coordinates":[82.91074500000001,26.476992],"type":"Point"}
}