{
  "type": "Feature",
  "properties": {
    "iso:country":"IN",
    "ks:ks_name":"Umblehadd",
    "ks:ks_pop":35,
    "ks:ks_type":"HABITATION",
    "name:eng_x_preferred":[
        "Umblehadd"
    ],
    "wof:name":"Umblehadd",
    "wof:placetype":"locality",
    "wof:population":35
},
  "geometry": {"coordinates":[74.866243,14.850495],"type":"Point"}
}