{
  "type": "Feature",
  "properties": {
    "iso:country":"IN",
    "ks:ks_name":"Suara",
    "ks:ks_pop":0,
    "ks:ks_type":"VILLAGE",
    "name:eng_x_preferred":[
        "Suara"
    ],
    "wof:name":"Suara",
    "wof:placetype":"locality",
    "wof:population":0
},
  "geometry": {"coordinates":[83.694948,25.199506],"type":"Point"}
}