{
  "type": "Feature",
  "properties": {
    "iso:country":"IN",
    "ks:ks_alt_nam":"6 no dhura Burmeik",
    "ks:ks_name":"6 No Dhura Burmeik",
    "ks:ks_pop":597,
    "ks:ks_type":"HABITATION",
    "name:eng_x_preferred":[
        "6 No Dhura Burmeik"
    ],
    "wof:name":"6 No Dhura Burmeik",
    "wof:placetype":"locality",
    "wof:population":597
},
  "geometry": {"coordinates":[88.566608,27.137626],"type":"Point"}
}