{
  "type": "Feature",
  "properties": {
    "iso:country":"IN",
    "ks:ks_name":"Seajuli Grant 170 173",
    "ks:ks_pop":267,
    "ks:ks_type":"HABITATION",
    "name:eng_x_preferred":[
        "Seajuli Grant 170 173"
    ],
    "wof:name":"Seajuli Grant 170 173",
    "wof:placetype":"locality",
    "wof:population":267
},
  "geometry": {"coordinates":[94.10881999999999,27.353488],"type":"Point"}
}