{
  "type": "Feature",
  "properties": {
    "iso:country":"IN",
    "ks:ks_name":"Ganesh Yadav Ka Tola",
    "ks:ks_pop":276,
    "ks:ks_type":"HABITATION",
    "name:eng_x_preferred":[
        "Ganesh Yadav Ka Tola"
    ],
    "wof:name":"Ganesh Yadav Ka Tola",
    "wof:placetype":"locality",
    "wof:population":276
},
  "geometry": {"coordinates":[84.31677500000001,26.662355],"type":"Point"}
}