{
  "type": "Feature",
  "properties": {
    "gn:admin1_code":"25.0",
    "gn:admin2_code":"605.0",
    "gn:asciiname":"Tappur",
    "gn:country_code":"IN",
    "gn:dem":131,
    "gn:feature_class":"P",
    "gn:feature_code":"PPL",
    "gn:name":"Tapp\u016br",
    "gn:population":0,
    "gn:timezone":"Asia/Kolkata",
    "iso:country":"IN",
    "wof:name":"Tappur",
    "wof:placetype":"locality"
},
  "geometry": {"coordinates":[79.49703000000002,13.06238],"type":"Point"}
}