{
  "type": "Feature",
  "properties": {
    "gn:admin1_code":"36",
    "gn:admin2_code":"189.0",
    "gn:asciiname":"Bairia",
    "gn:country_code":"IN",
    "gn:dem":88,
    "gn:feature_class":"P",
    "gn:feature_code":"PPL",
    "gn:name":"Bairia",
    "gn:population":0,
    "gn:timezone":"Asia/Kolkata",
    "iso:country":"IN",
    "name:bih_x_preferred":[
        "\u092c\u0948\u0930\u093f\u092f\u093e"
    ],
    "name:hin_x_preferred":[
        "\u092c\u0948\u0930\u093f\u092f\u093e"
    ],
    "wof:name":"Bairia",
    "wof:placetype":"locality"
},
  "geometry": {"coordinates":[83.61835000000001,26.79395],"type":"Point"}
}