{
  "type": "Feature",
  "properties": {
    "iso:country":"IN",
    "ks:ks_name":"Naladiasasan",
    "ks:ks_pop":648,
    "ks:ks_type":"VILLAGE",
    "ks:ks_uagg_main":0,
    "name:eng_x_preferred":[
        "Naladiasasan"
    ],
    "wof:name":"Naladiasasan",
    "wof:placetype":"neighbourhood",
    "wof:population":648
},
  "geometry": {"coordinates":[86.540327,20.363886],"type":"Point"}
}