{
  "type": "Feature",
  "properties": {
    "gn:admin1_code":"25.0",
    "gn:admin2_code":"605.0",
    "gn:asciiname":"Vinnamangalam",
    "gn:country_code":"IN",
    "gn:dem":334,
    "gn:feature_class":"P",
    "gn:feature_code":"PPL",
    "gn:name":"Vinnamangalam",
    "gn:population":0,
    "gn:timezone":"Asia/Kolkata",
    "iso:country":"IN",
    "ks:ks_name":"Vinnamangalam",
    "ks:ks_type":"VILLAGE",
    "ks:ks_uagg_main":0,
    "name:eng_x_preferred":[
        "Vinnamangalam"
    ],
    "name:tam_x_preferred":[
        "\u0bb5\u0bbf\u0ba3\u0bcd\u0ba3\u0bae\u0b99\u0bcd\u0b95\u0bb2\u0bae\u0bcd"
    ],
    "wof:name":"Vinnamangalam",
    "wof:placetype":"locality"
},
  "geometry": {"coordinates":[78.692633,12.742266],"type":"Point"}
}