{
  "type": "Feature",
  "properties": {
    "iso:country":"IN",
    "ks:ks_alt_nam":"Musalman wasti",
    "ks:ks_name":"Musalman Wasti",
    "ks:ks_pop":149,
    "ks:ks_type":"HABITATION",
    "name:eng_x_preferred":[
        "Musalman Wasti"
    ],
    "wof:name":"Musalman Wasti",
    "wof:placetype":"locality",
    "wof:population":149
},
  "geometry": {"coordinates":[75.27014800000001,18.69548],"type":"Point"}
}