{
  "type": "Feature",
  "properties": {
    "gn:admin1_code":"16.0",
    "gn:admin2_code":"516.0",
    "gn:asciiname":"Bhor",
    "gn:country_code":"IN",
    "gn:dem":555,
    "gn:feature_class":"P",
    "gn:feature_code":"PPL",
    "gn:name":"Bhor",
    "gn:population":0,
    "gn:timezone":"Asia/Kolkata",
    "iso:country":"IN",
    "name:ben_x_preferred":[
        "\u09ad\u09cb\u09b0"
    ],
    "name:bpy_x_preferred":[
        "\u09ad\u09cb\u09b0"
    ],
    "name:cat_x_preferred":[
        "Bhor"
    ],
    "name:ceb_x_preferred":[
        "Bhor"
    ],
    "name:deu_x_preferred":[
        "Bhor"
    ],
    "name:fra_x_preferred":[
        "Bhor"
    ],
    "name:hin_x_preferred":[
        "\u092d\u094b\u0930"
    ],
    "name:ita_x_preferred":[
        "Bhor"
    ],
    "name:mar_x_preferred":[
        "\u092d\u094b\u0930"
    ],
    "name:mlg_x_preferred":[
        "Bhor"
    ],
    "name:msa_x_preferred":[
        "Bhor"
    ],
    "name:new_x_preferred":[
        "\u092d\u094b\u0930"
    ],
    "name:nld_x_preferred":[
        "Bhor"
    ],
    "name:swe_x_preferred":[
        "Bhor"
    ],
    "name:ukr_x_preferred":[
        "\u0411\u0445\u043e\u0440"
    ],
    "name:urd_x_preferred":[
        "\u0628\u06be\u0648\u0631"
    ],
    "name:vie_x_preferred":[
        "Bhor"
    ],
    "name:zho_x_preferred":[
        "\u535a\u5c14"
    ],
    "wof:name":"Bhor",
    "wof:placetype":"locality"
},
  "geometry": {"coordinates":[74.12373000000002,20.51715],"type":"Point"}
}