{
  "type": "Feature",
  "properties": {
    "gn:admin1_code":"34.0",
    "gn:admin2_code":"204.0",
    "gn:asciiname":"Phanghata",
    "gn:country_code":"IN",
    "gn:dem":74,
    "gn:feature_class":"P",
    "gn:feature_code":"PPL",
    "gn:name":"Phangh\u0101ta",
    "gn:population":0,
    "gn:timezone":"Asia/Kolkata",
    "iso:country":"IN",
    "wof:name":"Phanghata",
    "wof:placetype":"neighbourhood"
},
  "geometry": {"coordinates":[84.70398,26.67066],"type":"Point"}
}