{
  "type": "Feature",
  "properties": {
    "gn:admin1_code":"25.0",
    "gn:admin2_code":"610.0",
    "gn:asciiname":"Elandakkadusakkilivalasu",
    "gn:country_code":"IN",
    "gn:dem":265,
    "gn:feature_class":"P",
    "gn:feature_code":"PPL",
    "gn:name":"Elandakk\u0101dusakkilivalasu",
    "gn:population":0,
    "gn:timezone":"Asia/Kolkata",
    "iso:country":"IN",
    "wof:name":"Elandakkadusakkilivalasu",
    "wof:placetype":"neighbourhood"
},
  "geometry": {"coordinates":[77.47,11.36928],"type":"Point"}
}