{
  "type": "Feature",
  "properties": {
    "iso:country":"IN",
    "ks:ks_name":"8 DWM",
    "ks:ks_pop":212,
    "ks:ks_type":"VILLAGE",
    "name:eng_x_preferred":[
        "8 DWM"
    ],
    "wof:name":"8 DWM",
    "wof:placetype":"locality",
    "wof:population":212
},
  "geometry": {"coordinates":[74.39671300000001,29.214617],"type":"Point"}
}