{
  "type": "Feature",
  "properties": {
    "iso:country":"IN",
    "ks:ks_alt_nam":"JAMBALSAI",
    "ks:ks_name":"Jambalsai",
    "ks:ks_pop":446,
    "ks:ks_type":"HABITATION",
    "name:eng_x_preferred":[
        "Jambalsai"
    ],
    "wof:name":"Jambalsai",
    "wof:placetype":"locality",
    "wof:population":446
},
  "geometry": {"coordinates":[85.731199,22.565916],"type":"Point"}
}