{
  "type": "Feature",
  "properties": {
    "gn:admin1_code":"35.0",
    "gn:admin2_code":"454.0",
    "gn:asciiname":"Madhogarh",
    "gn:country_code":"IN",
    "gn:dem":465,
    "gn:feature_class":"P",
    "gn:feature_code":"PPL",
    "gn:name":"M\u0101dhogarh",
    "gn:population":0,
    "gn:timezone":"Asia/Kolkata",
    "iso:country":"IN",
    "name:bpy_x_preferred":[
        "\u09ae\u09be\u09a7\u09cb\u0997\u09a1\u09bc"
    ],
    "name:ceb_x_preferred":[
        "M\u0101dhogarh"
    ],
    "name:hin_x_preferred":[
        "\u092e\u093e\u0927\u094b\u0917\u0922\u093c"
    ],
    "name:ita_x_preferred":[
        "Madhogarh"
    ],
    "name:msa_x_preferred":[
        "Madhogarh"
    ],
    "name:new_x_preferred":[
        "\u092e\u093e\u0927\u094b\u0917\u0922"
    ],
    "name:nld_x_preferred":[
        "Madhogarh"
    ],
    "name:pol_x_preferred":[
        "Madhogarh"
    ],
    "name:por_x_preferred":[
        "Madhogarh"
    ],
    "name:urd_x_preferred":[
        "\u0645\u0627\u0688\u06be\u0648\u06af\u0691\u06be"
    ],
    "name:vie_x_preferred":[
        "Madhogarh"
    ],
    "name:zho_x_preferred":[
        "\u9a6c\u591a\u52a0\u5c14"
    ],
    "wof:name":"Madhogarh",
    "wof:placetype":"locality"
},
  "geometry": {"coordinates":[80.25490000000001,22.90805],"type":"Point"}
}