{
  "type": "Feature",
  "properties": {
    "iso:country":"IN",
    "ks:ks_name":"Maniram Para",
    "ks:ks_pop":91,
    "ks:ks_type":"HABITATION",
    "name:eng_x_preferred":[
        "Maniram Para"
    ],
    "wof:name":"Maniram Para",
    "wof:placetype":"locality",
    "wof:population":91
},
  "geometry": {"coordinates":[91.421182,24.044875],"type":"Point"}
}