{
  "type": "Feature",
  "properties": {
    "iso:country":"IN",
    "ks:ks_alt_nam":"Khanpara Mondalpara and Khanpara BaurparaPara",
    "ks:ks_name":"Khanpara Mondalpara And Khanpara Baurparapara",
    "ks:ks_pop":1536,
    "ks:ks_type":"HABITATION",
    "name:eng_x_preferred":[
        "Khanpara Mondalpara And Khanpara Baurparapara"
    ],
    "wof:name":"Khanpara Mondalpara And Khanpara Baurparapara",
    "wof:placetype":"locality",
    "wof:population":1536
},
  "geometry": {"coordinates":[88.41437999999999,22.05402],"type":"Point"}
}