{
  "type": "Feature",
  "properties": {
    "gn:admin1_code":"24",
    "gn:admin2_code":"106.0",
    "gn:asciiname":"Indrapura",
    "gn:country_code":"IN",
    "gn:dem":245,
    "gn:feature_class":"P",
    "gn:feature_code":"PPL",
    "gn:name":"Indrapura",
    "gn:population":0,
    "gn:timezone":"Asia/Kolkata",
    "iso:country":"IN",
    "name:ind_x_preferred":[
        "Indrapura"
    ],
    "name:ita_x_preferred":[
        "Indrapura"
    ],
    "name:nld_x_preferred":[
        "Indrapura"
    ],
    "name:zho_x_preferred":[
        "\u56e0\u9640\u7f85\u88dc\u7f85"
    ],
    "wof:name":"Indrapura",
    "wof:placetype":"locality"
},
  "geometry": {"coordinates":[77.33402,26.52486],"type":"Point"}
}