{
  "type": "Feature",
  "properties": {
    "gn:admin1_code":"19.0",
    "gn:admin2_code":"572.0",
    "gn:asciiname":"Kaval Bhairsandra",
    "gn:country_code":"IN",
    "gn:dem":898,
    "gn:feature_class":"P",
    "gn:feature_code":"PPL",
    "gn:name":"K\u0101val Bhairsandra",
    "gn:population":0,
    "gn:timezone":"Asia/Kolkata",
    "iso:country":"IN",
    "wof:name":"Kaval Bhairsandra",
    "wof:placetype":"locality"
},
  "geometry": {"coordinates":[77.60911999999998,13.01913],"type":"Point"}
}