{
  "type": "Feature",
  "properties": {
    "gn:admin1_code":"03",
    "gn:admin2_code":"320.0",
    "gn:asciiname":"Manakasha",
    "gn:country_code":"IN",
    "gn:dem":53,
    "gn:feature_class":"P",
    "gn:feature_code":"PPL",
    "gn:name":"M\u0101nak\u0101sha",
    "gn:population":0,
    "gn:timezone":"Asia/Kolkata",
    "iso:country":"IN",
    "wof:name":"Manakasha",
    "wof:placetype":"locality"
},
  "geometry": {"coordinates":[90.83398,26.52992],"type":"Point"}
}