{
  "type": "Feature",
  "properties": {
    "iso:country":"IN",
    "ks:ks_name":"Kudriba",
    "ks:ks_pop":266,
    "ks:ks_type":"HABITATION",
    "name:eng_x_preferred":[
        "Kudriba"
    ],
    "wof:name":"Kudriba",
    "wof:placetype":"locality",
    "wof:population":266
},
  "geometry": {"coordinates":[85.289868,22.225028],"type":"Point"}
}