{
  "type": "Feature",
  "properties": {
    "iso:country":"IN",
    "ks:ks_name":"Jitiyatoli",
    "ks:ks_pop":220,
    "ks:ks_type":"HABITATION",
    "ks:ks_uagg_main":0,
    "name:eng_x_preferred":[
        "Jitiyatoli"
    ],
    "wof:name":"Jitiyatoli",
    "wof:placetype":"neighbourhood",
    "wof:population":220
},
  "geometry": {"coordinates":[84.136099,23.163475],"type":"Point"}
}