{
  "type": "Feature",
  "properties": {
    "iso:country":"IN",
    "ks:ks_alt_nam":"DUGUR BASA",
    "ks:ks_name":"Dugur Basa",
    "ks:ks_pop":276,
    "ks:ks_type":"HABITATION",
    "name:eng_x_preferred":[
        "Dugur Basa"
    ],
    "wof:name":"Dugur Basa",
    "wof:placetype":"locality",
    "wof:population":276
},
  "geometry": {"coordinates":[85.526549,22.281658],"type":"Point"}
}