{
  "type": "Feature",
  "properties": {
    "iso:country":"IN",
    "ks:ks_alt_nam":"P. MALAWADA",
    "ks:ks_name":"P. Malawada",
    "ks:ks_pop":306,
    "ks:ks_type":"HABITATION",
    "name:eng_x_preferred":[
        "P. Malawada"
    ],
    "wof:name":"P. Malawada",
    "wof:placetype":"locality",
    "wof:population":306
},
  "geometry": {"coordinates":[79.275475,14.098444],"type":"Point"}
}