{
  "type": "Feature",
  "properties": {
    "gn:admin1_code":"39.0",
    "gn:admin2_code":"64.0",
    "gn:asciiname":"Kankot",
    "gn:country_code":"IN",
    "gn:dem":1432,
    "gn:feature_class":"P",
    "gn:feature_code":"PPL",
    "gn:name":"Kankot",
    "gn:population":0,
    "gn:timezone":"Asia/Kolkata",
    "iso:country":"IN",
    "ks:ks_name":"Kankote",
    "ks:ks_pop":155,
    "ks:ks_type":"VILLAGE",
    "name:eng_x_preferred":[
        "Kankote"
    ],
    "name:eng_x_variant":[
        "Kankot"
    ],
    "wof:name":"Kankote",
    "wof:placetype":"locality",
    "wof:population":155
},
  "geometry": {"coordinates":[79.203261,29.771099],"type":"Point"}
}