{
  "type": "Feature",
  "properties": {
    "iso:country":"IN",
    "ks:ks_name":"Sendkhera",
    "ks:ks_pop":99,
    "ks:ks_type":"HABITATION",
    "name:eng_x_preferred":[
        "Sendkhera"
    ],
    "wof:name":"Sendkhera",
    "wof:placetype":"locality",
    "wof:population":99
},
  "geometry": {"coordinates":[73.993286,25.543297],"type":"Point"}
}