{
  "type": "Feature",
  "properties": {
    "gn:admin1_code":"24.0",
    "gn:admin2_code":"103",
    "gn:asciiname":"Kulriyon ka Bas",
    "gn:country_code":"IN",
    "gn:dem":357,
    "gn:feature_class":"P",
    "gn:feature_code":"PPL",
    "gn:name":"Kulriyon ka B\u0101s",
    "gn:population":0,
    "gn:timezone":"Asia/Kolkata",
    "iso:country":"IN",
    "name:und_x_variant":[
        "Kulriyon ka B\u0101s",
        "Kulriyan ka B\u0101s"
    ],
    "wof:name":"Kulriyon ka Bas",
    "wof:placetype":"locality"
},
  "geometry": {"coordinates":[75.37520000000001,28.02002],"type":"Point"}
}