{
  "type": "Feature",
  "properties": {
    "iso:country":"IN",
    "ks:ks_name":"Khajuria",
    "ks:ks_pop":405,
    "ks:ks_type":"VILLAGE",
    "name:eng_x_preferred":[
        "Khajuria"
    ],
    "wof:name":"Khajuria",
    "wof:placetype":"locality",
    "wof:population":405
},
  "geometry": {"coordinates":[85.34504,22.427132],"type":"Point"}
}