{
  "type": "Feature",
  "properties": {
    "gn:admin1_code":"36",
    "gn:admin2_code":"181.0",
    "gn:asciiname":"Ahiran Purwa",
    "gn:country_code":"IN",
    "gn:dem":116,
    "gn:feature_class":"P",
    "gn:feature_code":"PPL",
    "gn:name":"Ah\u012br\u0101n Purwa",
    "gn:population":0,
    "gn:timezone":"Asia/Kolkata",
    "iso:country":"IN",
    "ks:ks_name":"Ahiran Purwa",
    "ks:ks_pop":148,
    "ks:ks_type":"HABITATION",
    "ks:ks_uagg_main":0,
    "name:eng_x_preferred":[
        "Ahiran Purwa"
    ],
    "wof:name":"Ahiran Purwa",
    "wof:placetype":"neighbourhood",
    "wof:population":148
},
  "geometry": {"coordinates":[81.92157,27.535188],"type":"Point"}
}