{
  "type": "Feature",
  "properties": {
    "iso:country":"IN",
    "ks:ks_name":"Tenuhwa",
    "ks:ks_pop":118,
    "ks:ks_type":"HABITATION",
    "name:eng_x_preferred":[
        "Tenuhwa"
    ],
    "wof:name":"Tenuhwa",
    "wof:placetype":"locality",
    "wof:population":118
},
  "geometry": {"coordinates":[83.02361000000001,27.321463],"type":"Point"}
}