{
  "type": "Feature",
  "properties": {
    "gn:admin1_code":"34.0",
    "gn:admin2_code":"229.0",
    "gn:asciiname":"Mandachh Khurd",
    "gn:country_code":"IN",
    "gn:dem":63,
    "gn:feature_class":"P",
    "gn:feature_code":"PPL",
    "gn:name":"Mand\u0101chh Khurd",
    "gn:population":0,
    "gn:timezone":"Asia/Kolkata",
    "iso:country":"IN",
    "ks:ks_alt_nam":"Mand\u0101chh Khurd",
    "ks:ks_name":"Mandachh Khurd",
    "ks:ks_pop":3461,
    "ks:ks_type":"VILLAGE",
    "ks:ks_uagg_main":0,
    "name:eng_x_preferred":[
        "Mandachh Khurd"
    ],
    "name:eng_x_variant":[
        "Mand\u0101chh Khurd"
    ],
    "wof:name":"Mandachh Khurd",
    "wof:placetype":"neighbourhood",
    "wof:population":3461
},
  "geometry": {"coordinates":[85.46603500000001,25.187651],"type":"Point"}
}