{
  "type": "Feature",
  "properties": {
    "gn:admin1_code":"36",
    "gn:admin2_code":"143.0",
    "gn:asciiname":"Kamsai",
    "gn:country_code":"IN",
    "gn:dem":188,
    "gn:feature_class":"P",
    "gn:feature_code":"PPL",
    "gn:name":"Kamsai",
    "gn:population":0,
    "gn:timezone":"Asia/Kolkata",
    "iso:country":"IN",
    "wof:name":"Kamsai",
    "wof:placetype":"neighbourhood"
},
  "geometry": {"coordinates":[78.49417,28.03326],"type":"Point"}
}