{
  "type": "Feature",
  "properties": {
    "gn:admin1_code":"33",
    "gn:admin2_code":"586.0",
    "gn:asciiname":"Sancordem",
    "gn:cc2":"IN",
    "gn:country_code":"IN",
    "gn:dem":39,
    "gn:feature_class":"P",
    "gn:feature_code":"PPL",
    "gn:name":"Sancordem",
    "gn:population":0,
    "gn:timezone":"Asia/Kolkata",
    "iso:country":"IN",
    "name:und_x_variant":[
        "Sancord\u00e1m",
        "Sancordem"
    ],
    "wof:name":"Sancordem",
    "wof:placetype":"locality"
},
  "geometry": {"coordinates":[74.16235,15.41057],"type":"Point"}
}