{
  "type": "Feature",
  "properties": {
    "gn:admin1_code":"33",
    "gn:admin2_code":"586.0",
    "gn:asciiname":"Sancordem",
    "gn:cc2":"IN",
    "gn:country_code":"IN",
    "gn:dem":39,
    "gn:feature_class":"P",
    "gn:feature_code":"PPL",
    "gn:name":"Sancordem",
    "gn:population":0,
    "gn:timezone":"Asia/Kolkata",
    "iso:country":"IN",
    "ks:ks_name":"Sancordem",
    "ks:ks_pop":1252,
    "ks:ks_type":"VILLAGE",
    "name:eng_x_preferred":[
        "Sancordem"
    ],
    "name:und_x_variant":[
        "Sancord\u00e1m",
        "Sancordem"
    ],
    "wof:name":"Sancordem",
    "wof:placetype":"locality",
    "wof:population":1252
},
  "geometry": {"coordinates":[74.180852,15.403937],"type":"Point"}
}