{
  "type": "Feature",
  "properties": {
    "iso:country":"IN",
    "ks:ks_name":"Rautdih",
    "ks:ks_pop":311,
    "ks:ks_type":"VILLAGE",
    "name:eng_x_preferred":[
        "Rautdih"
    ],
    "wof:name":"Rautdih",
    "wof:placetype":"locality",
    "wof:population":311
},
  "geometry": {"coordinates":[86.767713,24.385945],"type":"Point"}
}