{
  "type": "Feature",
  "properties": {
    "iso:country":"IN",
    "ks:ks_name":"Gangaiah Naidu Puram",
    "ks:ks_pop":25,
    "ks:ks_type":"HABITATION",
    "name:eng_x_preferred":[
        "Gangaiah Naidu Puram"
    ],
    "wof:name":"Gangaiah Naidu Puram",
    "wof:placetype":"locality",
    "wof:population":25
},
  "geometry": {"coordinates":[78.97250699999999,13.301949],"type":"Point"}
}