{
  "type": "Feature",
  "properties": {
    "iso:country":"IN",
    "ks:ks_name":"Hanumanwadi",
    "ks:ks_pop":780,
    "ks:ks_type":"VILLAGE",
    "name:eng_x_preferred":[
        "Hanumanwadi"
    ],
    "wof:name":"Hanumanwadi",
    "wof:placetype":"locality",
    "wof:population":780
},
  "geometry": {"coordinates":[75.282245,20.609443],"type":"Point"}
}