{
  "type": "Feature",
  "properties": {
    "gn:admin1_code":"21.0",
    "gn:admin2_code":"399.0",
    "gn:asciiname":"Pasuvulabanda",
    "gn:country_code":"IN",
    "gn:dem":640,
    "gn:feature_class":"P",
    "gn:feature_code":"PPL",
    "gn:name":"Pasuvulabanda",
    "gn:population":0,
    "gn:timezone":"Asia/Kolkata",
    "iso:country":"IN",
    "wof:name":"Pasuvulabanda",
    "wof:placetype":"locality"
},
  "geometry": {"coordinates":[82.32153000000002,18.05583],"type":"Point"}
}