{
  "type": "Feature",
  "properties": {
    "gn:admin1_code":"24.0",
    "gn:admin2_code":"102",
    "gn:asciiname":"Bhamran",
    "gn:country_code":"IN",
    "gn:dem":232,
    "gn:feature_class":"P",
    "gn:feature_code":"PPL",
    "gn:name":"Bh\u0101mr\u0101n",
    "gn:population":0,
    "gn:timezone":"Asia/Kolkata",
    "iso:country":"IN",
    "name:und_x_variant":[
        "Bh\u0101mran",
        "Bhamra",
        "Bh\u0101mr\u0101n"
    ],
    "wof:name":"Bhamran",
    "wof:placetype":"locality"
},
  "geometry": {"coordinates":[74.91454,28.72769000000001],"type":"Point"}
}