{
  "type": "Feature",
  "properties": {
    "iso:country":"IN",
    "ks:ks_name":"Bachalmeta",
    "ks:ks_pop":127,
    "ks:ks_type":"HABITATION",
    "ks:ks_uagg_main":0,
    "name:eng_x_preferred":[
        "Bachalmeta"
    ],
    "wof:name":"Bachalmeta",
    "wof:placetype":"neighbourhood",
    "wof:population":127
},
  "geometry": {"coordinates":[82.249725,18.545336],"type":"Point"}
}