{
  "type": "Feature",
  "properties": {
    "iso:country":"IN",
    "ks:ks_name":"Kalam Punjee",
    "ks:ks_pop":873,
    "ks:ks_type":"HABITATION",
    "name:eng_x_preferred":[
        "Kalam Punjee"
    ],
    "wof:name":"Kalam Punjee",
    "wof:placetype":"locality",
    "wof:population":873
},
  "geometry": {"coordinates":[93.110417,24.864408],"type":"Point"}
}