{
  "type": "Feature",
  "properties": {
    "iso:country":"IN",
    "ks:ks_name":"Regumanuguda",
    "ks:ks_pop":202,
    "ks:ks_type":"HABITATION",
    "name:eng_x_preferred":[
        "Regumanuguda"
    ],
    "wof:name":"Regumanuguda",
    "wof:placetype":"locality",
    "wof:population":202
},
  "geometry": {"coordinates":[83.828039,18.728604],"type":"Point"}
}