{
  "type": "Feature",
  "properties": {
    "iso:country":"IN",
    "ks:ks_name":"Santhaiyur",
    "ks:ks_pop":208,
    "ks:ks_type":"HABITATION",
    "ks:ks_uagg_main":0,
    "name:eng_x_preferred":[
        "Santhaiyur"
    ],
    "wof:name":"Santhaiyur",
    "wof:placetype":"neighbourhood",
    "wof:population":208
},
  "geometry": {"coordinates":[78.32560700000001,10.740432],"type":"Point"}
}