{
  "type": "Feature",
  "properties": {
    "iso:country":"IN",
    "ks:ks_name":"Kolha",
    "ks:ks_pop":267,
    "ks:ks_type":"VILLAGE",
    "name:eng_x_preferred":[
        "Kolha"
    ],
    "wof:name":"Kolha",
    "wof:placetype":"locality",
    "wof:population":267
},
  "geometry": {"coordinates":[87.39252,24.497192],"type":"Point"}
}