{
  "type": "Feature",
  "properties": {
    "iso:country":"IN",
    "ks:ks_name":"Chhota Bathanpahari",
    "ks:ks_pop":103,
    "ks:ks_type":"VILLAGE",
    "name:eng_x_preferred":[
        "Chhota Bathanpahari"
    ],
    "wof:name":"Chhota Bathanpahari",
    "wof:placetype":"locality",
    "wof:population":103
},
  "geometry": {"coordinates":[87.548776,24.409753],"type":"Point"}
}