{
  "type": "Feature",
  "properties": {
    "gn:admin1_code":"39",
    "gn:admin2_code":"61.0",
    "gn:asciiname":"Bandhni",
    "gn:country_code":"IN",
    "gn:dem":684,
    "gn:feature_class":"P",
    "gn:feature_code":"PPL",
    "gn:name":"B\u0101ndhni",
    "gn:population":0,
    "gn:timezone":"Asia/Kolkata",
    "iso:country":"IN",
    "wof:name":"Bandhni",
    "wof:placetype":"locality"
},
  "geometry": {"coordinates":[78.35784,29.9819],"type":"Point"}
}