{
  "type": "Feature",
  "properties": {
    "iso:country":"IN",
    "ks:ks_alt_nam":"HARIJAN WASTI",
    "ks:ks_name":"Harijan Wasti",
    "ks:ks_pop":90,
    "ks:ks_type":"HABITATION",
    "name:eng_x_preferred":[
        "Harijan Wasti"
    ],
    "wof:name":"Harijan Wasti",
    "wof:placetype":"locality",
    "wof:population":90
},
  "geometry": {"coordinates":[74.089811,16.925459],"type":"Point"}
}