{
  "type": "Feature",
  "properties": {
    "iso:country":"IN",
    "ks:ks_name":"Bhataura",
    "ks:ks_pop":4,
    "ks:ks_type":"HABITATION",
    "name:eng_x_preferred":[
        "Bhataura"
    ],
    "wof:name":"Bhataura",
    "wof:placetype":"locality",
    "wof:population":4
},
  "geometry": {"coordinates":[80.717915,25.258435],"type":"Point"}
}