{
  "type": "Feature",
  "properties": {
    "iso:country":"IN",
    "ks:ks_name":"Bamani Rith",
    "ks:ks_pop":100,
    "ks:ks_type":"HABITATION",
    "name:eng_x_preferred":[
        "Bamani Rith"
    ],
    "wof:name":"Bamani Rith",
    "wof:placetype":"locality",
    "wof:population":100
},
  "geometry": {"coordinates":[79.638947,20.200231],"type":"Point"}
}