{
  "type": "Feature",
  "properties": {
    "gn:admin1_code":"36.0",
    "gn:admin2_code":"160.0",
    "gn:asciiname":"Nagla Madari",
    "gn:country_code":"IN",
    "gn:dem":151,
    "gn:feature_class":"P",
    "gn:feature_code":"PPL",
    "gn:name":"Nagla Mad\u0101ri",
    "gn:population":0,
    "gn:timezone":"Asia/Kolkata",
    "iso:country":"IN",
    "wof:name":"Nagla Madari",
    "wof:placetype":"locality"
},
  "geometry": {"coordinates":[79.3754,26.97374000000001],"type":"Point"}
}