{
  "type": "Feature",
  "properties": {
    "iso:country":"IN",
    "ks:ks_alt_nam":"hagaganji",
    "ks:ks_name":"Hagaganji",
    "ks:ks_pop":90,
    "ks:ks_type":"HABITATION",
    "name:eng_x_preferred":[
        "Hagaganji"
    ],
    "wof:name":"Hagaganji",
    "wof:placetype":"locality",
    "wof:population":90
},
  "geometry": {"coordinates":[75.294102,13.384705],"type":"Point"}
}