{
  "type": "Feature",
  "properties": {
    "gn:admin1_code":"28.0",
    "gn:admin2_code":"328",
    "gn:asciiname":"Belakoba",
    "gn:country_code":"IN",
    "gn:dem":99,
    "gn:feature_class":"P",
    "gn:feature_code":"PPL",
    "gn:name":"Bel\u0101koba",
    "gn:population":0,
    "gn:timezone":"Asia/Kolkata",
    "iso:country":"IN",
    "ks:ks_alt_nam":"BELACOBA",
    "ks:ks_name":"Belacoba",
    "ks:ks_pop":550,
    "ks:ks_type":"HABITATION",
    "ks:ks_uagg_main":0,
    "name:ceb_x_preferred":[
        "Bel\u0101koba"
    ],
    "name:eng_x_preferred":[
        "Belacoba"
    ],
    "name:swe_x_preferred":[
        "Bel\u0101koba"
    ],
    "wof:name":"Belacoba",
    "wof:placetype":"neighbourhood",
    "wof:population":550
},
  "geometry": {"coordinates":[88.584833,26.589779],"type":"Point"}
}