{
  "type": "Feature",
  "properties": {
    "gn:admin1_code":"36.0",
    "gn:admin2_code":"183.0",
    "gn:asciiname":"Chakpan",
    "gn:country_code":"IN",
    "gn:dem":99,
    "gn:feature_class":"P",
    "gn:feature_code":"PPL",
    "gn:name":"Chakp\u0101n",
    "gn:population":0,
    "gn:timezone":"Asia/Kolkata",
    "iso:country":"IN",
    "ks:ks_alt_nam":"Chakp\u0101n",
    "ks:ks_name":"Chakpan",
    "ks:ks_type":"VILLAGE",
    "name:eng_x_preferred":[
        "Chakpan"
    ],
    "name:eng_x_variant":[
        "Chakp\u0101n"
    ],
    "wof:name":"Chakpan",
    "wof:placetype":"locality"
},
  "geometry": {"coordinates":[82.15272299999999,26.895524],"type":"Point"}
}