{
  "type": "Feature",
  "properties": {
    "iso:country":"IN",
    "ks:ks_name":"Vadavali",
    "ks:ks_pop":4602,
    "ks:ks_type":"VILLAGE",
    "name:eng_x_preferred":[
        "Vadavali"
    ],
    "wof:name":"Vadavali",
    "wof:placetype":"locality",
    "wof:population":4602
},
  "geometry": {"coordinates":[72.916984,20.100269],"type":"Point"}
}