{
  "type": "Feature",
  "properties": {
    "iso:country":"IN",
    "ks:ks_name":"Koovaikinaru",
    "ks:ks_pop":293,
    "ks:ks_type":"HABITATION",
    "ks:ks_uagg_main":0,
    "name:eng_x_preferred":[
        "Koovaikinaru"
    ],
    "wof:name":"Koovaikinaru",
    "wof:placetype":"neighbourhood",
    "wof:population":293
},
  "geometry": {"coordinates":[77.852177,8.473359],"type":"Point"}
}