{
  "type": "Feature",
  "properties": {
    "gn:admin1_code":"37",
    "gn:admin2_code":"409.0",
    "gn:asciiname":"Dhaurabhata Kalan",
    "gn:country_code":"IN",
    "gn:dem":293,
    "gn:feature_class":"P",
    "gn:feature_code":"PPL",
    "gn:name":"Dhaur\u0101bh\u0101ta Kal\u0101n",
    "gn:population":0,
    "gn:timezone":"Asia/Kolkata",
    "iso:country":"IN",
    "wof:name":"Dhaurabhata Kalan",
    "wof:placetype":"locality"
},
  "geometry": {"coordinates":[81.56265999999999,21.98827],"type":"Point"}
}