{
  "type": "Feature",
  "properties": {
    "iso:country":"IN",
    "ks:ks_name":"Ambachak",
    "ks:ks_pop":156,
    "ks:ks_type":"VILLAGE",
    "name:eng_x_preferred":[
        "Ambachak"
    ],
    "wof:name":"Ambachak",
    "wof:placetype":"locality",
    "wof:population":156
},
  "geometry": {"coordinates":[83.21827,25.354272],"type":"Point"}
}