{
  "type": "Feature",
  "properties": {
    "iso:country":"IN",
    "ks:ks_name":"Madlu",
    "ks:ks_pop":27,
    "ks:ks_type":"HABITATION",
    "name:eng_x_preferred":[
        "Madlu"
    ],
    "wof:name":"Madlu",
    "wof:placetype":"locality",
    "wof:population":27
},
  "geometry": {"coordinates":[75.35800399999999,13.582076],"type":"Point"}
}