{
  "type": "Feature",
  "properties": {
    "gn:admin1_code":"2.0",
    "gn:admin2_code":"550.0",
    "gn:asciiname":"Mittapalem",
    "gn:country_code":"IN",
    "gn:dem":26,
    "gn:feature_class":"P",
    "gn:feature_code":"PPL",
    "gn:name":"Mittap\u0101lem",
    "gn:population":0,
    "gn:timezone":"Asia/Kolkata",
    "iso:country":"IN",
    "ks:ks_name":"Mitta Palem",
    "ks:ks_pop":69,
    "ks:ks_type":"HABITATION",
    "name:eng_x_preferred":[
        "Mitta Palem"
    ],
    "name:eng_x_variant":[
        "Mittapalem"
    ],
    "wof:name":"Mitta Palem",
    "wof:placetype":"locality",
    "wof:population":69
},
  "geometry": {"coordinates":[79.90857800000001,13.957147],"type":"Point"}
}