{
  "type": "Feature",
  "properties": {
    "iso:country":"IN",
    "ks:ks_name":"Thakra",
    "ks:ks_pop":530,
    "ks:ks_type":"VILLAGE",
    "name:eng_x_preferred":[
        "Thakra"
    ],
    "wof:name":"Thakra",
    "wof:placetype":"locality",
    "wof:population":530
},
  "geometry": {"coordinates":[74.620643,23.665965],"type":"Point"}
}