{
  "type": "Feature",
  "properties": {
    "iso:country":"IN",
    "ks:ks_name":"Manaru Tola",
    "ks:ks_pop":906,
    "ks:ks_type":"HABITATION",
    "name:eng_x_preferred":[
        "Manaru Tola"
    ],
    "wof:name":"Manaru Tola",
    "wof:placetype":"locality",
    "wof:population":906
},
  "geometry": {"coordinates":[83.28385299999999,24.030036],"type":"Point"}
}