{
  "type": "Feature",
  "properties": {
    "gn:admin1_code":"37",
    "gn:admin2_code":"407.0",
    "gn:asciiname":"Rengabor",
    "gn:country_code":"IN",
    "gn:dem":332,
    "gn:feature_class":"P",
    "gn:feature_code":"PPL",
    "gn:name":"Reng\u0101bor",
    "gn:population":0,
    "gn:timezone":"Asia/Kolkata",
    "iso:country":"IN",
    "wof:name":"Rengabor",
    "wof:placetype":"neighbourhood"
},
  "geometry": {"coordinates":[81.45935,22.15538],"type":"Point"}
}