{
  "type": "Feature",
  "properties": {
    "iso:country":"IN",
    "ks:ks_name":"Belshula",
    "ks:ks_pop":976,
    "ks:ks_type":"VILLAGE",
    "name:eng_x_preferred":[
        "Belshula"
    ],
    "wof:name":"Belshula",
    "wof:placetype":"locality",
    "wof:population":976
},
  "geometry": {"coordinates":[87.411067,23.027114],"type":"Point"}
}