{
  "type": "Feature",
  "properties": {
    "iso:country":"IN",
    "ks:ks_name":"Kashiganja",
    "ks:ks_pop":394,
    "ks:ks_type":"VILLAGE",
    "ks:ks_uagg_main":0,
    "name:eng_x_preferred":[
        "Kashiganja"
    ],
    "wof:name":"Kashiganja",
    "wof:placetype":"neighbourhood",
    "wof:population":394
},
  "geometry": {"coordinates":[87.611932,22.702382],"type":"Point"}
}