{
  "type": "Feature",
  "properties": {
    "iso:country":"IN",
    "ks:ks_name":"Rambardi",
    "ks:ks_pop":110,
    "ks:ks_type":"HABITATION",
    "name:eng_x_preferred":[
        "Rambardi"
    ],
    "wof:name":"Rambardi",
    "wof:placetype":"locality",
    "wof:population":110
},
  "geometry": {"coordinates":[75.18926500000001,21.414284],"type":"Point"}
}