{
  "type": "Feature",
  "properties": {
    "iso:country":"IN",
    "ks:ks_alt_nam":"BAGAI JHARIYA",
    "ks:ks_name":"Bagai Jhariya",
    "ks:ks_pop":283,
    "ks:ks_type":"HABITATION",
    "name:eng_x_preferred":[
        "Bagai Jhariya"
    ],
    "wof:name":"Bagai Jhariya",
    "wof:placetype":"locality",
    "wof:population":283
},
  "geometry": {"coordinates":[83.644564,22.644156],"type":"Point"}
}