{
  "type": "Feature",
  "properties": {
    "iso:country":"IN",
    "ks:ks_alt_nam":"Paran\u0101tt\u0101rmangalam",
    "ks:ks_name":"Paranattarmangalam",
    "ks:ks_type":"VILLAGE",
    "ks:ks_uagg_main":0,
    "name:eng_x_preferred":[
        "Paranattarmangalam"
    ],
    "name:eng_x_variant":[
        "Paran\u0101tt\u0101rmangalam"
    ],
    "wof:name":"Paranattarmangalam",
    "wof:placetype":"neighbourhood"
},
  "geometry": {"coordinates":[78.12719300000001,11.622147],"type":"Point"}
}