{
  "type": "Feature",
  "properties": {
    "gn:admin1_code":"38.0",
    "gn:admin2_code":"352.0",
    "gn:asciiname":"Salmandra",
    "gn:country_code":"IN",
    "gn:dem":40,
    "gn:feature_class":"P",
    "gn:feature_code":"PPL",
    "gn:name":"S\u0101lmandra",
    "gn:population":0,
    "gn:timezone":"Asia/Kolkata",
    "iso:country":"IN",
    "wof:name":"Salmandra",
    "wof:placetype":"locality"
},
  "geometry": {"coordinates":[87.72774,25.01581],"type":"Point"}
}