{
  "type": "Feature",
  "properties": {
    "iso:country":"IN",
    "ks:ks_name":"Nabasan",
    "ks:ks_pop":891,
    "ks:ks_type":"VILLAGE",
    "name:eng_x_preferred":[
        "Nabasan"
    ],
    "wof:name":"Nabasan",
    "wof:placetype":"locality",
    "wof:population":891
},
  "geometry": {"coordinates":[87.493077,23.03068],"type":"Point"}
}