{
  "type": "Feature",
  "properties": {
    "gn:admin1_code":"23",
    "gn:admin2_code":"37.0",
    "gn:asciiname":"Mawai",
    "gn:country_code":"IN",
    "gn:dem":239,
    "gn:feature_class":"P",
    "gn:feature_code":"PPL",
    "gn:name":"Maw\u0101i",
    "gn:population":0,
    "gn:timezone":"Asia/Kolkata",
    "iso:country":"IN",
    "name:msa_x_preferred":[
        "Mawai"
    ],
    "wof:name":"Mawai",
    "wof:placetype":"locality"
},
  "geometry": {"coordinates":[75.67898000000002,31.06572],"type":"Point"}
}