{
  "type": "Feature",
  "properties": {
    "iso:country":"IN",
    "ks:ks_name":"Sadaram",
    "ks:ks_pop":73,
    "ks:ks_type":"VILLAGE",
    "name:eng_x_preferred":[
        "Sadaram"
    ],
    "wof:name":"Sadaram",
    "wof:placetype":"locality",
    "wof:population":73
},
  "geometry": {"coordinates":[82.33040200000001,18.353411],"type":"Point"}
}