{
  "type": "Feature",
  "properties": {
    "iso:country":"IN",
    "ks:ks_name":"12 BGP",
    "ks:ks_pop":5,
    "ks:ks_type":"VILLAGE",
    "name:eng_x_preferred":[
        "12 BGP"
    ],
    "wof:name":"12 BGP",
    "wof:placetype":"locality",
    "wof:population":5
},
  "geometry": {"coordinates":[74.471613,29.842894],"type":"Point"}
}