{
  "type": "Feature",
  "properties": {
    "iso:country":"IN",
    "ks:ks_name":"Gopinathapur",
    "ks:ks_pop":634,
    "ks:ks_type":"VILLAGE",
    "ks:ks_uagg_main":0,
    "name:eng_x_preferred":[
        "Gopinathapur"
    ],
    "wof:name":"Gopinathapur",
    "wof:placetype":"neighbourhood",
    "wof:population":634
},
  "geometry": {"coordinates":[85.660331,20.538886],"type":"Point"}
}