{
  "type": "Feature",
  "properties": {
    "iso:country":"IN",
    "ks:ks_name":"Juibra",
    "ks:ks_pop":250,
    "ks:ks_type":"HABITATION",
    "name:eng_x_preferred":[
        "Juibra"
    ],
    "wof:name":"Juibra",
    "wof:placetype":"locality",
    "wof:population":250
},
  "geometry": {"coordinates":[93.298051,25.297735],"type":"Point"}
}