{
  "type": "Feature",
  "properties": {
    "iso:country":"IN",
    "ks:ks_name":"Alakocha",
    "ks:ks_pop":33,
    "ks:ks_type":"VILLAGE",
    "name:eng_x_preferred":[
        "Alakocha"
    ],
    "wof:name":"Alakocha",
    "wof:placetype":"locality",
    "wof:population":33
},
  "geometry": {"coordinates":[87.501784,24.874671],"type":"Point"}
}