{
  "type": "Feature",
  "properties": {
    "gn:admin1_code":"2.0",
    "gn:admin2_code":"553.0",
    "gn:asciiname":"Duminahalli",
    "gn:country_code":"IN",
    "gn:dem":682,
    "gn:feature_class":"P",
    "gn:feature_code":"PPL",
    "gn:name":"Duminahalli",
    "gn:population":0,
    "gn:timezone":"Asia/Kolkata",
    "iso:country":"IN",
    "wof:name":"Duminahalli",
    "wof:placetype":"neighbourhood"
},
  "geometry": {"coordinates":[77.10587,13.94254],"type":"Point"}
}