{
  "type": "Feature",
  "properties": {
    "gn:admin1_code":"40.0",
    "gn:admin2_code":"532.0",
    "gn:asciiname":"Sudal",
    "gn:country_code":"IN",
    "gn:dem":128,
    "gn:feature_class":"P",
    "gn:feature_code":"PPL",
    "gn:name":"Sud\u0101l",
    "gn:population":0,
    "gn:timezone":"Asia/Kolkata",
    "iso:country":"IN",
    "name:bih_x_preferred":[
        "\u0938\u0941\u0921\u093e\u0932"
    ],
    "name:ceb_x_preferred":[
        "Sudal"
    ],
    "name:msa_x_preferred":[
        "Sudal"
    ],
    "name:nep_x_preferred":[
        "\u0938\u0941\u0921\u093e\u0932"
    ],
    "name:new_x_preferred":[
        "\u0938\u0941\u0926\u093e\u0932"
    ],
    "name:pol_x_preferred":[
        "Sudal"
    ],
    "wof:name":"Sudal",
    "wof:placetype":"locality"
},
  "geometry": {"coordinates":[79.74485,18.82516],"type":"Point"}
}