{
  "type": "Feature",
  "properties": {
    "iso:country":"IN",
    "ks:ks_name":"Manjoli Talli",
    "ks:ks_pop":40,
    "ks:ks_type":"VILLAGE",
    "name:eng_x_preferred":[
        "Manjoli Talli"
    ],
    "wof:name":"Manjoli Talli",
    "wof:placetype":"locality",
    "wof:population":40
},
  "geometry": {"coordinates":[78.820137,29.812419],"type":"Point"}
}