{
  "type": "Feature",
  "properties": {
    "iso:country":"IN",
    "ks:ks_name":"Mathabari",
    "ks:ks_pop":8284,
    "ks:ks_type":"VILLAGE",
    "ks:ks_uagg_main":0,
    "name:eng_x_preferred":[
        "Mathabari"
    ],
    "wof:name":"Mathabari",
    "wof:placetype":"neighbourhood",
    "wof:population":8284
},
  "geometry": {"coordinates":[88.040098,24.927401],"type":"Point"}
}