{
  "type": "Feature",
  "properties": {
    "iso:country":"IN",
    "ks:ks_name":"Bura Gaon",
    "ks:ks_pop":927,
    "ks:ks_type":"VILLAGE",
    "ks:ks_uagg_main":0,
    "name:eng_x_preferred":[
        "Bura Gaon"
    ],
    "wof:name":"Bura Gaon",
    "wof:placetype":"neighbourhood",
    "wof:population":927
},
  "geometry": {"coordinates":[92.803523,26.847267],"type":"Point"}
}