{
  "type": "Feature",
  "properties": {
    "iso:country":"IN",
    "ks:ks_name":"Jharakata",
    "ks:ks_pop":1894,
    "ks:ks_type":"VILLAGE",
    "name:eng_x_preferred":[
        "Jharakata"
    ],
    "wof:name":"Jharakata",
    "wof:placetype":"locality",
    "wof:population":1894
},
  "geometry": {"coordinates":[86.88279,20.804692],"type":"Point"}
}