{
  "type": "Feature",
  "properties": {
    "gn:admin1_code":"34.0",
    "gn:admin2_code":"220.0",
    "gn:asciiname":"Chak Shakur",
    "gn:country_code":"IN",
    "gn:dem":63,
    "gn:feature_class":"P",
    "gn:feature_code":"PPL",
    "gn:name":"Chak Shakur",
    "gn:population":0,
    "gn:timezone":"Asia/Kolkata",
    "iso:country":"IN",
    "ks:ks_name":"Chak Shakur",
    "ks:ks_pop":364,
    "ks:ks_type":"VILLAGE",
    "name:eng_x_preferred":[
        "Chak Shakur"
    ],
    "wof:name":"Chak Shakur",
    "wof:placetype":"locality",
    "wof:population":364
},
  "geometry": {"coordinates":[85.110963,25.965222],"type":"Point"}
}