{
  "type": "Feature",
  "properties": {
    "gn:admin1_code":"31",
    "gn:admin2_code":"281.0",
    "gn:asciiname":"Sabual",
    "gn:country_code":"IN",
    "gn:dem":855,
    "gn:feature_class":"P",
    "gn:feature_code":"PPL",
    "gn:name":"Sabual",
    "gn:population":0,
    "gn:timezone":"Asia/Kolkata",
    "iso:country":"IN",
    "wof:name":"Sabual",
    "wof:placetype":"locality"
},
  "geometry": {"coordinates":[92.59403,23.44238],"type":"Point"}
}