{
  "type": "Feature",
  "properties": {
    "iso:country":"IN",
    "ks:ks_name":"Karremarka",
    "ks:ks_pop":84,
    "ks:ks_type":"HABITATION",
    "name:eng_x_preferred":[
        "Karremarka"
    ],
    "wof:name":"Karremarka",
    "wof:placetype":"locality",
    "wof:population":84
},
  "geometry": {"coordinates":[80.650778,19.030745],"type":"Point"}
}