{
  "type": "Feature",
  "properties": {
    "iso:country":"IN",
    "ks:ks_name":"Kakarahi",
    "ks:ks_pop":1030,
    "ks:ks_type":"HABITATION",
    "name:eng_x_preferred":[
        "Kakarahi"
    ],
    "wof:name":"Kakarahi",
    "wof:placetype":"locality",
    "wof:population":1030
},
  "geometry": {"coordinates":[83.023203,27.273021],"type":"Point"}
}