{
  "type": "Feature",
  "properties": {
    "iso:country":"IN",
    "ks:ks_name":"Kajri Kunj",
    "ks:ks_pop":163,
    "ks:ks_type":"VILLAGE",
    "name:eng_x_preferred":[
        "Kajri Kunj"
    ],
    "wof:name":"Kajri Kunj",
    "wof:placetype":"locality",
    "wof:population":163
},
  "geometry": {"coordinates":[82.60678,26.808791],"type":"Point"}
}