{
  "type": "Feature",
  "properties": {
    "iso:country":"IN",
    "ks:ks_name":"Kaldi",
    "ks:ks_pop":1334,
    "ks:ks_type":"VILLAGE",
    "name:eng_x_preferred":[
        "Kaldi"
    ],
    "wof:name":"Kaldi",
    "wof:placetype":"locality",
    "wof:population":1334
},
  "geometry": {"coordinates":[91.30685800000001,26.280025],"type":"Point"}
}