{
  "type": "Feature",
  "properties": {
    "iso:country":"IN",
    "ks:ks_name":"Gobindapur W-1",
    "ks:ks_pop":805,
    "ks:ks_type":"HABITATION",
    "name:eng_x_preferred":[
        "Gobindapur W-1"
    ],
    "wof:name":"Gobindapur W-1",
    "wof:placetype":"locality",
    "wof:population":805
},
  "geometry": {"coordinates":[92.203898,24.407956],"type":"Point"}
}