{
  "type": "Feature",
  "properties": {
    "iso:country":"IN",
    "ks:ks_name":"Hinautiya",
    "ks:ks_pop":35,
    "ks:ks_type":"HABITATION",
    "name:eng_x_preferred":[
        "Hinautiya"
    ],
    "wof:name":"Hinautiya",
    "wof:placetype":"locality",
    "wof:population":35
},
  "geometry": {"coordinates":[80.087411,23.39249],"type":"Point"}
}