{
  "type": "Feature",
  "properties": {
    "iso:country":"IN",
    "ks:ks_name":"Titidanga",
    "ks:ks_pop":0,
    "ks:ks_type":"VILLAGE",
    "name:eng_x_preferred":[
        "Titidanga"
    ],
    "wof:name":"Titidanga",
    "wof:placetype":"locality",
    "wof:population":0
},
  "geometry": {"coordinates":[88.21205500000001,25.431256],"type":"Point"}
}