{
  "type": "Feature",
  "properties": {
    "gn:admin1_code":"02",
    "gn:admin2_code":"549.0",
    "gn:asciiname":"Nandanavanam",
    "gn:country_code":"IN",
    "gn:dem":155,
    "gn:feature_class":"P",
    "gn:feature_code":"PPL",
    "gn:name":"Nandanavanam",
    "gn:population":0,
    "gn:timezone":"Asia/Kolkata",
    "iso:country":"IN",
    "name:und_x_variant":[
        "Nandavanam"
    ],
    "wof:name":"Nandanavanam",
    "wof:placetype":"locality"
},
  "geometry": {"coordinates":[79.27434000000002,15.47054],"type":"Point"}
}