{
  "type": "Feature",
  "properties": {
    "iso:country":"IN",
    "ks:ks_name":"Vaddha",
    "ks:ks_pop":940,
    "ks:ks_type":"VILLAGE",
    "name:eng_x_preferred":[
        "Vaddha"
    ],
    "wof:name":"Vaddha",
    "wof:placetype":"locality",
    "wof:population":940
},
  "geometry": {"coordinates":[73.16699300000001,20.316099],"type":"Point"}
}