{
  "type": "Feature",
  "properties": {
    "gn:admin1_code":"10.0",
    "gn:admin2_code":"73.0",
    "gn:asciiname":"Hansu Majra",
    "gn:country_code":"IN",
    "gn:dem":238,
    "gn:feature_class":"P",
    "gn:feature_code":"PPL",
    "gn:name":"H\u0101nsu M\u0101jra",
    "gn:population":0,
    "gn:timezone":"Asia/Kolkata",
    "iso:country":"IN",
    "wof:name":"Hansu Majra",
    "wof:placetype":"locality"
},
  "geometry": {"coordinates":[76.22450000000001,30.00091],"type":"Point"}
}