{
  "type": "Feature",
  "properties": {
    "gn:admin1_code":"23.0",
    "gn:admin2_code":"35.0",
    "gn:asciiname":"Bhatoia",
    "gn:country_code":"IN",
    "gn:dem":266,
    "gn:feature_class":"P",
    "gn:feature_code":"PPL",
    "gn:name":"Bhatoia",
    "gn:population":0,
    "gn:timezone":"Asia/Kolkata",
    "iso:country":"IN",
    "ks:ks_name":"Bhatoia",
    "ks:ks_pop":929,
    "ks:ks_type":"VILLAGE",
    "ks:ks_uagg_main":0,
    "name:eng_x_preferred":[
        "Bhatoia"
    ],
    "wof:name":"Bhatoia",
    "wof:placetype":"neighbourhood",
    "wof:population":929
},
  "geometry": {"coordinates":[75.46713200000001,32.198775],"type":"Point"}
}