{
  "type": "Feature",
  "properties": {
    "iso:country":"IN",
    "ks:ks_name":"Sannuagaon",
    "ks:ks_pop":0,
    "ks:ks_type":"VILLAGE",
    "name:eng_x_preferred":[
        "Sannuagaon"
    ],
    "wof:name":"Sannuagaon",
    "wof:placetype":"locality",
    "wof:population":0
},
  "geometry": {"coordinates":[85.635479,21.503075],"type":"Point"}
}