{
  "type": "Feature",
  "properties": {
    "iso:country":"IN",
    "ks:ks_name":"Tianimamudi",
    "ks:ks_pop":78,
    "ks:ks_type":"HABITATION",
    "name:eng_x_preferred":[
        "Tianimamudi"
    ],
    "wof:name":"Tianimamudi",
    "wof:placetype":"locality",
    "wof:population":78
},
  "geometry": {"coordinates":[81.982451,18.093709],"type":"Point"}
}