{
  "type": "Feature",
  "properties": {
    "iso:country":"IN",
    "ks:ks_name":"Swetpur",
    "ks:ks_pop":1952,
    "ks:ks_type":"VILLAGE",
    "ks:ks_uagg_main":0,
    "name:eng_x_preferred":[
        "Swetpur"
    ],
    "wof:name":"Swetpur",
    "wof:placetype":"neighbourhood",
    "wof:population":1952
},
  "geometry": {"coordinates":[88.838722,22.61065],"type":"Point"}
}