{
  "type": "Feature",
  "properties": {
    "iso:country":"IN",
    "ks:ks_name":"Ramchandarpur",
    "ks:ks_pop":928,
    "ks:ks_type":"VILLAGE",
    "ks:ks_uagg_main":0,
    "name:eng_x_preferred":[
        "Ramchandarpur"
    ],
    "wof:name":"Ramchandarpur",
    "wof:placetype":"neighbourhood",
    "wof:population":928
},
  "geometry": {"coordinates":[86.073244,22.836815],"type":"Point"}
}