{
  "type": "Feature",
  "properties": {
    "gn:admin1_code":"22.0",
    "gn:admin2_code":"635.0",
    "gn:asciiname":"Kakkalippattu",
    "gn:country_code":"IN",
    "gn:dem":26,
    "gn:feature_class":"P",
    "gn:feature_code":"PPL",
    "gn:name":"Kakkalippattu",
    "gn:population":0,
    "gn:timezone":"Asia/Kolkata",
    "iso:country":"IN",
    "wof:name":"Kakkalippattu",
    "wof:placetype":"locality"
},
  "geometry": {"coordinates":[79.67025,12.00598],"type":"Point"}
}