{
  "type": "Feature",
  "properties": {
    "gn:admin1_code":"35",
    "gn:admin2_code":"421.0",
    "gn:asciiname":"Chandni",
    "gn:country_code":"IN",
    "gn:dem":173,
    "gn:feature_class":"P",
    "gn:feature_code":"PPL",
    "gn:name":"Ch\u0101ndni",
    "gn:population":0,
    "gn:timezone":"Asia/Kolkata",
    "iso:country":"IN",
    "name:deu_x_preferred":[
        "Chandni"
    ],
    "name:fas_x_preferred":[
        "\u0645\u0647\u062a\u0627\u0628"
    ],
    "name:fin_x_preferred":[
        "Chandni"
    ],
    "name:ita_x_preferred":[
        "Chandni"
    ],
    "name:mar_x_preferred":[
        "\u091a\u093e\u0902\u0926\u0928\u0940"
    ],
    "name:new_x_preferred":[
        "\u091a\u093e\u0901\u0926\u0928\u0940"
    ],
    "name:pol_x_preferred":[
        "Chandni"
    ],
    "name:rus_x_preferred":[
        "\u0427\u0430\u043d\u0434\u043d\u0438"
    ],
    "wof:name":"Chandni",
    "wof:placetype":"locality"
},
  "geometry": {"coordinates":[78.81461999999998,25.93604],"type":"Point"}
}