{
  "type": "Feature",
  "properties": {
    "iso:country":"IN",
    "ks:ks_alt_nam":"Baraip\u0101r",
    "ks:ks_name":"Baraipar",
    "ks:ks_type":"VILLAGE",
    "name:eng_x_preferred":[
        "Baraipar"
    ],
    "name:eng_x_variant":[
        "Baraip\u0101r"
    ],
    "wof:name":"Baraipar",
    "wof:placetype":"locality"
},
  "geometry": {"coordinates":[83.309963,26.812009],"type":"Point"}
}