{
  "type": "Feature",
  "properties": {
    "gn:admin1_code":"40.0",
    "gn:admin2_code":"534.0",
    "gn:asciiname":"Bhimrazpalli",
    "gn:country_code":"IN",
    "gn:dem":211,
    "gn:feature_class":"P",
    "gn:feature_code":"PPL",
    "gn:name":"Bh\u012bmr\u0101zpalli",
    "gn:population":0,
    "gn:timezone":"Asia/Kolkata",
    "iso:country":"IN",
    "wof:name":"Bhimrazpalli",
    "wof:placetype":"locality"
},
  "geometry": {"coordinates":[79.10655,18.7818],"type":"Point"}
}