{
  "type": "Feature",
  "properties": {
    "iso:country":"IN",
    "ks:ks_name":"Kahikuchi",
    "ks:ks_pop":1129,
    "ks:ks_type":"VILLAGE",
    "ks:ks_uagg_main":0,
    "name:eng_x_preferred":[
        "Kahikuchi"
    ],
    "wof:name":"Kahikuchi",
    "wof:placetype":"neighbourhood",
    "wof:population":1129
},
  "geometry": {"coordinates":[91.59866,26.102094],"type":"Point"}
}