{
  "type": "Feature",
  "properties": {
    "iso:country":"IN",
    "ks:ks_alt_nam":"SANKARPUR",
    "ks:ks_name":"Sankarpur",
    "ks:ks_pop":670,
    "ks:ks_type":"HABITATION",
    "ks:ks_uagg_main":0,
    "name:eng_x_preferred":[
        "Sankarpur"
    ],
    "wof:name":"Sankarpur",
    "wof:placetype":"neighbourhood",
    "wof:population":670
},
  "geometry": {"coordinates":[89.265529,26.661191],"type":"Point"}
}