{
  "type": "Feature",
  "properties": {
    "gn:admin1_code":"16.0",
    "gn:admin2_code":"499.0",
    "gn:asciiname":"Kanashi",
    "gn:country_code":"IN",
    "gn:dem":287,
    "gn:feature_class":"P",
    "gn:feature_code":"PPL",
    "gn:name":"Kan\u0101shi",
    "gn:population":0,
    "gn:timezone":"Asia/Kolkata",
    "iso:country":"IN",
    "name:und_x_variant":[
        "Kan\u0101shi",
        "Kanashi"
    ],
    "wof:name":"Kanashi",
    "wof:placetype":"locality"
},
  "geometry": {"coordinates":[75.15658000000001,20.61699],"type":"Point"}
}