{
  "type": "Feature",
  "properties": {
    "gn:admin1_code":"10.0",
    "gn:admin2_code":"85.0",
    "gn:asciiname":"Ramgarh",
    "gn:country_code":"IN",
    "gn:dem":240,
    "gn:feature_class":"P",
    "gn:feature_code":"PPL",
    "gn:name":"R\u0101mgarh",
    "gn:population":0,
    "gn:timezone":"Asia/Kolkata",
    "iso:country":"IN",
    "wof:name":"Ramgarh",
    "wof:placetype":"locality"
},
  "geometry": {"coordinates":[76.67024000000001,28.22772],"type":"Point"}
}