{
  "type": "Feature",
  "properties": {
    "iso:country":"IN",
    "ks:ks_name":"Rajanpal",
    "ks:ks_pop":177,
    "ks:ks_type":"VILLAGE",
    "name:eng_x_preferred":[
        "Rajanpal"
    ],
    "wof:name":"Rajanpal",
    "wof:placetype":"locality",
    "wof:population":177
},
  "geometry": {"coordinates":[84.747353,21.036134],"type":"Point"}
}