{
  "type": "Feature",
  "properties": {
    "iso:country":"IN",
    "ks:ks_name":"Jerrigedda",
    "ks:ks_pop":68,
    "ks:ks_type":"HABITATION",
    "name:eng_x_preferred":[
        "Jerrigedda"
    ],
    "wof:name":"Jerrigedda",
    "wof:placetype":"locality",
    "wof:population":68
},
  "geometry": {"coordinates":[82.409002,17.801678],"type":"Point"}
}