{
  "type": "Feature",
  "properties": {
    "iso:country":"IN",
    "ks:ks_name":"Dasha Gram",
    "ks:ks_pop":4581,
    "ks:ks_type":"VILLAGE",
    "name:eng_x_preferred":[
        "Dasha Gram"
    ],
    "wof:name":"Dasha Gram",
    "wof:placetype":"locality",
    "wof:population":4581
},
  "geometry": {"coordinates":[87.507374,22.110646],"type":"Point"}
}