{
  "type": "Feature",
  "properties": {
    "iso:country":"IN",
    "ks:ks_name":"Sindhiyon Ki Dhani",
    "ks:ks_pop":960,
    "ks:ks_type":"VILLAGE",
    "name:eng_x_preferred":[
        "Sindhiyon Ki Dhani"
    ],
    "wof:name":"Sindhiyon Ki Dhani",
    "wof:placetype":"locality",
    "wof:population":960
},
  "geometry": {"coordinates":[71.687769,25.597306],"type":"Point"}
}