{
  "type": "Feature",
  "properties": {
    "iso:country":"IN",
    "ks:ks_name":"Bachhi Ka Dera",
    "ks:ks_pop":105,
    "ks:ks_type":"HABITATION",
    "name:eng_x_preferred":[
        "Bachhi Ka Dera"
    ],
    "wof:name":"Bachhi Ka Dera",
    "wof:placetype":"locality",
    "wof:population":105
},
  "geometry": {"coordinates":[80.961876,25.739989],"type":"Point"}
}