{
  "type": "Feature",
  "properties": {
    "gn:admin1_code":"36.0",
    "gn:admin2_code":"167",
    "gn:asciiname":"Amarpur",
    "gn:country_code":"IN",
    "gn:dem":351,
    "gn:feature_class":"P",
    "gn:feature_code":"PPL",
    "gn:name":"Amarpur",
    "gn:population":0,
    "gn:timezone":"Asia/Kolkata",
    "iso:country":"IN",
    "wof:name":"Amarpur",
    "wof:placetype":"locality"
},
  "geometry": {"coordinates":[78.41967,24.75994],"type":"Point"}
}