{
  "type": "Feature",
  "properties": {
    "gn:admin1_code":"36",
    "gn:admin2_code":"196.0",
    "gn:asciiname":"Indarpura",
    "gn:country_code":"IN",
    "gn:dem":86,
    "gn:feature_class":"P",
    "gn:feature_code":"PPL",
    "gn:name":"Indarpura",
    "gn:population":0,
    "gn:timezone":"Asia/Kolkata",
    "iso:country":"IN",
    "ks:ks_name":"Inderpurwa",
    "ks:ks_pop":302,
    "ks:ks_type":"HABITATION",
    "name:eng_x_preferred":[
        "Inderpurwa"
    ],
    "name:eng_x_variant":[
        "Indarpura"
    ],
    "wof:name":"Inderpurwa",
    "wof:placetype":"locality",
    "wof:population":302
},
  "geometry": {"coordinates":[83.217234,25.083178],"type":"Point"}
}