{
  "type": "Feature",
  "properties": {
    "gn:admin1_code":"35.0",
    "gn:admin2_code":"440.0",
    "gn:asciiname":"Motapura",
    "gn:country_code":"IN",
    "gn:dem":232,
    "gn:feature_class":"P",
    "gn:feature_code":"PPL",
    "gn:name":"Mot\u0101pura",
    "gn:population":0,
    "gn:timezone":"Asia/Kolkata",
    "iso:country":"IN",
    "wof:name":"Motapura",
    "wof:placetype":"locality"
},
  "geometry": {"coordinates":[75.45086999999999,21.94026],"type":"Point"}
}