{
  "type": "Feature",
  "properties": {
    "iso:country":"IN",
    "ks:ks_name":"Hunyanaik Thanda",
    "ks:ks_pop":40,
    "ks:ks_type":"HABITATION",
    "name:eng_x_preferred":[
        "Hunyanaik Thanda"
    ],
    "wof:name":"Hunyanaik Thanda",
    "wof:placetype":"locality",
    "wof:population":40
},
  "geometry": {"coordinates":[78.103793,18.54796],"type":"Point"}
}