{
  "type": "Feature",
  "properties": {
    "iso:country":"IN",
    "ks:ks_name":"Dharanwadi",
    "ks:ks_pop":251,
    "ks:ks_type":"HABITATION",
    "name:eng_x_preferred":[
        "Dharanwadi"
    ],
    "wof:name":"Dharanwadi",
    "wof:placetype":"locality",
    "wof:population":251
},
  "geometry": {"coordinates":[73.414025,17.554486],"type":"Point"}
}