{
  "type": "Feature",
  "properties": {
    "gn:admin1_code":"38.0",
    "gn:admin2_code":"358.0",
    "gn:asciiname":"Nima Chak",
    "gn:country_code":"IN",
    "gn:dem":285,
    "gn:feature_class":"P",
    "gn:feature_code":"PPL",
    "gn:name":"Nima Chak",
    "gn:population":0,
    "gn:timezone":"Asia/Kolkata",
    "iso:country":"IN",
    "ks:ks_name":"Nima Chak",
    "ks:ks_pop":503,
    "ks:ks_type":"VILLAGE",
    "ks:ks_uagg_main":0,
    "name:eng_x_preferred":[
        "Nima Chak"
    ],
    "wof:name":"Nima Chak",
    "wof:placetype":"neighbourhood",
    "wof:population":503
},
  "geometry": {"coordinates":[84.457668,24.048768],"type":"Point"}
}