{
  "type": "Feature",
  "properties": {
    "iso:country":"IN",
    "name:ara_x_preferred":[
        "\u0628\u0627\u0641\u062f\u0627\u0646 \u0628\u0648\u062f\u0631\u0643"
    ],
    "name:ben_bn_x_preferred":[
        "\u09ac\u09be\u09ad\u09a7\u09be\u09a8 \u09ac\u09c1\u09a6\u09b0\u09c1\u0995"
    ],
    "name:ben_in_x_preferred":[
        "\u09ac\u09be\u09ad\u09a7\u09be\u09a8 \u09ac\u09c1\u09a6\u09b0\u09c1\u0995"
    ],
    "name:eng_x_preferred":[
        "Bavdhan Budruk"
    ],
    "name:guj_x_preferred":[
        "\u0aac\u0abe\u0ab5\u0aa7\u0abe\u0aa8 \u0aac\u0ac1\u0aa6\u0acd\u0ab0\u0ac1\u0a95"
    ],
    "name:hin_x_preferred":[
        "\u092c\u093e\u0935\u0927\u0928 \u092c\u0941\u0926\u094d\u0930\u0941\u0915"
    ],
    "name:kan_x_preferred":[
        "\u0cac\u0cbe\u0cb5\u0ca7\u0cbe\u0ca8\u0ccd"
    ],
    "name:mal_x_preferred":[
        "\u0d2c\u0d35\u0d4d\u0d26\u0d3e\u0d7b \u0d2c\u0d41\u0d26\u0d4d\u0d30\u0d41\u0d15\u0d4d\u0d15\u0d4d"
    ],
    "name:mar_x_preferred":[
        "\u092c\u093e\u0935\u0927\u0928 \u092c\u0941\u0926\u094d\u0930\u0941\u0915"
    ],
    "name:pan_x_preferred":[
        "\u0a2c\u0a35\u0a27\u0a3e\u0a28 \u0a2c\u0a41\u0a21\u0a30\u0a41\u0a15"
    ],
    "name:tam_x_preferred":[
        "\u0baa\u0bb5\u0bcd\u0ba4\u0bbe\u0ba9\u0bcd \u0baa\u0bc1\u0ba4\u0bcd\u0bb0\u0bc1\u0b95\u0bcd"
    ],
    "name:tel_x_preferred":[
        "\u0c2c\u0c35\u0c4d"
    ],
    "name:urd_x_preferred":[
        "\u0628\u0624\u062f\u06be\u0627\u0646 \u0628\u062f\u0631\u06a9"
    ],
    "wof:name":"Bavdhan Budruk",
    "wof:placetype":"neighbourhood"
},
  "geometry": {"coordinates":[73.77773765827402,18.52839139944613],"type":"Point"}
}