{
  "type": "Feature",
  "properties": {
    "iso:country":"IN",
    "name:eng_x_preferred":[
        "Bavdhan Budruk"
    ],
    "wof:name":"Bavdhan Budruk",
    "wof:placetype":"neighbourhood"
},
  "geometry": {"coordinates":[73.77773765827402,18.52839139944613],"type":"Point"}
}