{
  "type": "Feature",
  "properties": {
    "gn:admin1_code":"19.0",
    "gn:admin2_code":"575.0",
    "gn:asciiname":"Barya",
    "gn:country_code":"IN",
    "gn:dem":68,
    "gn:feature_class":"P",
    "gn:feature_code":"PPLL",
    "gn:name":"B\u0101rya",
    "gn:population":0,
    "gn:timezone":"Asia/Kolkata",
    "iso:country":"IN",
    "ks:ks_alt_nam":"B\u0101rya",
    "ks:ks_name":"Barya",
    "ks:ks_type":"VILLAGE",
    "name:eng_x_preferred":[
        "Barya"
    ],
    "name:eng_x_variant":[
        "B\u0101rya"
    ],
    "wof:name":"Barya",
    "wof:placetype":"locality"
},
  "geometry": {"coordinates":[75.210932,12.855083],"type":"Point"}
}