{
  "type": "Feature",
  "properties": {
    "iso:country":"IN",
    "ks:ks_name":"Radhanagar",
    "ks:ks_pop":221,
    "ks:ks_type":"HABITATION",
    "name:eng_x_preferred":[
        "Radhanagar"
    ],
    "wof:name":"Radhanagar",
    "wof:placetype":"locality",
    "wof:population":221
},
  "geometry": {"coordinates":[87.374157,23.835907],"type":"Point"}
}