{
  "type": "Feature",
  "properties": {
    "iso:country":"IN",
    "ks:ks_alt_nam":"pasiyan",
    "ks:ks_name":"Pasiyan",
    "ks:ks_pop":175,
    "ks:ks_type":"HABITATION",
    "name:eng_x_preferred":[
        "Pasiyan"
    ],
    "wof:name":"Pasiyan",
    "wof:placetype":"locality",
    "wof:population":175
},
  "geometry": {"coordinates":[81.66304,25.55567],"type":"Point"}
}