{
  "type": "Feature",
  "properties": {
    "iso:country":"IN",
    "ks:ks_name":"Barkheda Khurd",
    "ks:ks_pop":561,
    "ks:ks_type":"HABITATION",
    "name:eng_x_preferred":[
        "Barkheda Khurd"
    ],
    "wof:name":"Barkheda Khurd",
    "wof:placetype":"locality",
    "wof:population":561
},
  "geometry": {"coordinates":[75.61351999999999,23.585829],"type":"Point"}
}