{
  "type": "Feature",
  "properties": {
    "gn:admin1_code":"19.0",
    "gn:admin2_code":"568.0",
    "gn:asciiname":"Bilaki",
    "gn:country_code":"IN",
    "gn:dem":649,
    "gn:feature_class":"P",
    "gn:feature_code":"PPL",
    "gn:name":"B\u012blaki",
    "gn:population":0,
    "gn:timezone":"Asia/Kolkata",
    "iso:country":"IN",
    "wof:name":"Bilaki",
    "wof:placetype":"locality"
},
  "geometry": {"coordinates":[75.26416999999999,14.45018],"type":"Point"}
}