{
  "type": "Feature",
  "properties": {
    "gn:country":"IN",
    "gn:fcode":"PPL",
    "gn:population":21327,
    "iso:country":"IN",
    "ks:ks_name":"Bedi",
    "ks:ks_type":"VILLAGE",
    "ks:ks_uagg_main":0,
    "name:bpy_x_preferred":[
        "\u09ac\u09c7\u09a6\u09c0"
    ],
    "name:ceb_x_preferred":[
        "Bedi"
    ],
    "name:eng_x_preferred":[
        "Bedi"
    ],
    "name:guj_x_preferred":[
        "\u0aac\u0ac7\u0aa1\u0ac0 \u0aac\u0a82\u0aa6\u0ab0"
    ],
    "name:hin_x_preferred":[
        "\u092c\u0947\u0921\u0940"
    ],
    "name:ita_x_preferred":[
        "Bedi"
    ],
    "name:nan_x_preferred":[
        "Bedi"
    ],
    "name:new_x_preferred":[
        "\u092c\u0947\u0926\u0940"
    ],
    "name:nld_x_preferred":[
        "Bedi"
    ],
    "name:rus_x_preferred":[
        "\u0411\u0435\u0434\u0430"
    ],
    "name:spa_x_preferred":[
        "Bedi"
    ],
    "name:swe_x_preferred":[
        "Bedi"
    ],
    "name:und_x_variant":[
        "Bedi Bandar"
    ],
    "name:vie_x_preferred":[
        "Bedi"
    ],
    "name:zho_x_preferred":[
        "\u8d1d\u8fea"
    ],
    "name:zho_x_variant":[
        "\u5361\u7eb3\u666e\u5c14"
    ],
    "qs:name":"Bedi",
    "qs:name_adm0":"India",
    "qs:name_adm1":"Gujarat",
    "qs:photos":55,
    "qs:photos_1k":11,
    "qs:photos_9k":1,
    "qs:photos_9r":2,
    "qs:photos_all":55,
    "qs:photos_sr":2,
    "qs:placetype":"Town",
    "qs:pop_sr":"7",
    "wd:wordcount":462,
    "wof:name":"Bedi",
    "wof:placetype":"neighbourhood",
    "wof:population":21327
},
  "geometry": {"coordinates":[70.04362999999999,22.50143],"type":"Point"}
}