{
  "type": "Feature",
  "properties": {
    "iso:country":"IN",
    "ks:ks_name":"Narsali Nadi",
    "ks:ks_pop":1500,
    "ks:ks_type":"HABITATION",
    "name:eng_x_preferred":[
        "Narsali Nadi"
    ],
    "wof:name":"Narsali Nadi",
    "wof:placetype":"locality",
    "wof:population":1500
},
  "geometry": {"coordinates":[71.729072,25.989111],"type":"Point"}
}