{
  "type": "Feature",
  "properties": {
    "iso:country":"IN",
    "ks:ks_name":"Tembahaka",
    "ks:ks_pop":144,
    "ks:ks_type":"VILLAGE",
    "name:eng_x_preferred":[
        "Tembahaka"
    ],
    "wof:name":"Tembahaka",
    "wof:placetype":"locality",
    "wof:population":144
},
  "geometry": {"coordinates":[85.56099500000001,22.469486],"type":"Point"}
}