{
  "type": "Feature",
  "properties": {
    "gn:admin1_code":"36",
    "gn:admin2_code":"152.0",
    "gn:asciiname":"Dabhaura",
    "gn:country_code":"IN",
    "gn:dem":161,
    "gn:feature_class":"P",
    "gn:feature_code":"PPL",
    "gn:name":"Dabhaura",
    "gn:population":0,
    "gn:timezone":"Asia/Kolkata",
    "iso:country":"IN",
    "ks:ks_name":"Dabhaura",
    "ks:ks_pop":5755,
    "ks:ks_type":"VILLAGE",
    "ks:ks_uagg_main":0,
    "name:eng_x_preferred":[
        "Dabhaura"
    ],
    "wof:name":"Dabhaura",
    "wof:placetype":"locality",
    "wof:population":5755
},
  "geometry": {"coordinates":[79.741607,27.975251],"type":"Point"}
}