{
  "type": "Feature",
  "properties": {
    "iso:country":"IN",
    "ks:ks_alt_nam":"Hes\u0101tu",
    "ks:ks_name":"Hesatu",
    "ks:ks_pop":670,
    "ks:ks_type":"VILLAGE",
    "name:eng_x_preferred":[
        "Hesatu"
    ],
    "name:eng_x_variant":[
        "Hes\u0101tu"
    ],
    "wof:name":"Hesatu",
    "wof:placetype":"locality",
    "wof:population":670
},
  "geometry": {"coordinates":[84.54965900000001,23.923218],"type":"Point"}
}