{
  "type": "Feature",
  "properties": {
    "gn:admin1_code":"39.0",
    "gn:admin2_code":"64.0",
    "gn:asciiname":"Magraunkhal",
    "gn:country_code":"IN",
    "gn:dem":1737,
    "gn:feature_class":"P",
    "gn:feature_code":"PPL",
    "gn:name":"Magraunkh\u0101l",
    "gn:population":0,
    "gn:timezone":"Asia/Kolkata",
    "iso:country":"IN",
    "wof:name":"Magraunkhal",
    "wof:placetype":"locality"
},
  "geometry": {"coordinates":[79.12900999999999,29.83251],"type":"Point"}
}