{
  "type": "Feature",
  "properties": {
    "gn:admin1_code":"19.0",
    "gn:admin2_code":"564.0",
    "gn:asciiname":"Kittur",
    "gn:country_code":"IN",
    "gn:dem":526,
    "gn:feature_class":"P",
    "gn:feature_code":"PPL",
    "gn:name":"Kitt\u016br",
    "gn:population":0,
    "gn:timezone":"Asia/Kolkata",
    "iso:country":"IN",
    "name:cat_x_preferred":[
        "Kittur"
    ],
    "name:hin_x_preferred":[
        "\u0915\u093f\u0924\u094d\u0924\u0942\u0930"
    ],
    "name:kan_x_preferred":[
        "\u0c95\u0cbf\u0ca4\u0ccd\u0ca4\u0cc2\u0cb0\u0cc1"
    ],
    "wof:name":"Kittur",
    "wof:placetype":"locality"
},
  "geometry": {"coordinates":[75.57165000000001,14.92561],"type":"Point"}
}