{
  "type": "Feature",
  "properties": {
    "iso:country":"IN",
    "ks:ks_name":"Koniwadi",
    "ks:ks_pop":155,
    "ks:ks_type":"HABITATION",
    "name:eng_x_preferred":[
        "Koniwadi"
    ],
    "wof:name":"Koniwadi",
    "wof:placetype":"locality",
    "wof:population":155
},
  "geometry": {"coordinates":[73.52408800000001,16.122826],"type":"Point"}
}