{
  "type": "Feature",
  "properties": {
    "iso:country":"IN",
    "ks:ks_name":"Meda",
    "ks:ks_pop":144,
    "ks:ks_type":"HABITATION",
    "name:eng_x_preferred":[
        "Meda"
    ],
    "wof:name":"Meda",
    "wof:placetype":"locality",
    "wof:population":144
},
  "geometry": {"coordinates":[74.321918,15.471771],"type":"Point"}
}