{
  "type": "Feature",
  "properties": {
    "iso:country":"IN",
    "ks:ks_name":"Mathari",
    "ks:ks_pop":163,
    "ks:ks_type":"VILLAGE",
    "name:eng_x_preferred":[
        "Mathari"
    ],
    "wof:name":"Mathari",
    "wof:placetype":"locality",
    "wof:population":163
},
  "geometry": {"coordinates":[80.68321899999999,21.814897],"type":"Point"}
}