{
  "type": "Feature",
  "properties": {
    "gn:admin1_code":"23.0",
    "gn:admin2_code":"35.0",
    "gn:asciiname":"Kauntarpur",
    "gn:country_code":"IN",
    "gn:dem":292,
    "gn:feature_class":"P",
    "gn:feature_code":"PPL",
    "gn:name":"Kauntarpur",
    "gn:population":0,
    "gn:timezone":"Asia/Kolkata",
    "iso:country":"IN",
    "ks:ks_name":"Kauntarpur",
    "ks:ks_pop":1708,
    "ks:ks_type":"VILLAGE",
    "ks:ks_uagg_main":0,
    "name:eng_x_preferred":[
        "Kauntarpur"
    ],
    "wof:name":"Kauntarpur",
    "wof:placetype":"neighbourhood",
    "wof:population":1708
},
  "geometry": {"coordinates":[75.614519,32.160906],"type":"Point"}
}