{
  "type": "Feature",
  "properties": {
    "iso:country":"IN",
    "ks:ks_name":"Vrita Tola",
    "ks:ks_pop":480,
    "ks:ks_type":"HABITATION",
    "name:eng_x_preferred":[
        "Vrita Tola"
    ],
    "wof:name":"Vrita Tola",
    "wof:placetype":"locality",
    "wof:population":480
},
  "geometry": {"coordinates":[84.42123100000001,26.722752],"type":"Point"}
}