{
  "type": "Feature",
  "properties": {
    "iso:country":"IN",
    "ks:ks_name":"Majhipali",
    "ks:ks_pop":96,
    "ks:ks_type":"VILLAGE",
    "name:eng_x_preferred":[
        "Majhipali"
    ],
    "wof:name":"Majhipali",
    "wof:placetype":"locality",
    "wof:population":96
},
  "geometry": {"coordinates":[83.72170699999999,20.799031],"type":"Point"}
}