{
  "type": "Feature",
  "properties": {
    "iso:country":"IN",
    "ks:ks_alt_nam":"9KHR",
    "ks:ks_name":"9khr",
    "ks:ks_pop":275,
    "ks:ks_type":"HABITATION",
    "name:eng_x_preferred":[
        "9khr"
    ],
    "wof:name":"9khr",
    "wof:placetype":"locality",
    "wof:population":275
},
  "geometry": {"coordinates":[74.55403099999999,29.677595],"type":"Point"}
}