{
  "type": "Feature",
  "properties": {
    "iso:country":"IN",
    "ks:ks_name":"Ramkrishanapur",
    "ks:ks_pop":580,
    "ks:ks_type":"VILLAGE",
    "ks:ks_uagg_main":0,
    "name:eng_x_preferred":[
        "Ramkrishanapur"
    ],
    "wof:name":"Ramkrishanapur",
    "wof:placetype":"neighbourhood",
    "wof:population":580
},
  "geometry": {"coordinates":[87.535084,21.863553],"type":"Point"}
}