{
  "type": "Feature",
  "properties": {
    "iso:country":"IN",
    "ks:ks_name":"Vagal Vasti",
    "ks:ks_pop":176,
    "ks:ks_type":"HABITATION",
    "name:eng_x_preferred":[
        "Vagal Vasti"
    ],
    "wof:name":"Vagal Vasti",
    "wof:placetype":"locality",
    "wof:population":176
},
  "geometry": {"coordinates":[75.233998,16.871262],"type":"Point"}
}