{
  "type": "Feature",
  "properties": {
    "gn:admin1_code":"21.0",
    "gn:admin2_code":"396.0",
    "gn:asciiname":"Bada Maturu",
    "gn:country_code":"IN",
    "gn:dem":521,
    "gn:feature_class":"P",
    "gn:feature_code":"PPL",
    "gn:name":"Bada Mat\u016bru",
    "gn:population":0,
    "gn:timezone":"Asia/Kolkata",
    "iso:country":"IN",
    "wof:name":"Bada Maturu",
    "wof:placetype":"locality"
},
  "geometry": {"coordinates":[83.24203,19.33766],"type":"Point"}
}