{
  "type": "Feature",
  "properties": {
    "gn:admin1_code":"21.0",
    "gn:admin2_code":"396.0",
    "gn:asciiname":"Bada Maturu",
    "gn:country_code":"IN",
    "gn:dem":521,
    "gn:feature_class":"P",
    "gn:feature_code":"PPL",
    "gn:name":"Bada Mat\u016bru",
    "gn:population":0,
    "gn:timezone":"Asia/Kolkata",
    "iso:country":"IN",
    "ks:ks_name":"Badamatru",
    "ks:ks_pop":273,
    "ks:ks_type":"VILLAGE",
    "name:eng_x_preferred":[
        "Badamatru"
    ],
    "name:eng_x_variant":[
        "Bada Maturu"
    ],
    "wof:name":"Badamatru",
    "wof:placetype":"locality",
    "wof:population":273
},
  "geometry": {"coordinates":[83.23450099999999,19.342691],"type":"Point"}
}