{
  "type": "Feature",
  "properties": {
    "iso:country":"IN",
    "ks:ks_name":"Rampur 33",
    "ks:ks_pop":674,
    "ks:ks_type":"HABITATION",
    "name:eng_x_preferred":[
        "Rampur 33"
    ],
    "wof:name":"Rampur 33",
    "wof:placetype":"locality",
    "wof:population":674
},
  "geometry": {"coordinates":[82.890232,24.894678],"type":"Point"}
}