{
  "type": "Feature",
  "properties": {
    "iso:country":"IN",
    "ks:ks_name":"Kaltahar Kalibari",
    "ks:ks_pop":693,
    "ks:ks_type":"HABITATION",
    "name:eng_x_preferred":[
        "Kaltahar Kalibari"
    ],
    "wof:name":"Kaltahar Kalibari",
    "wof:placetype":"locality",
    "wof:population":693
},
  "geometry": {"coordinates":[88.139599,26.156165],"type":"Point"}
}