{
  "type": "Feature",
  "properties": {
    "gn:country":"IN",
    "gn:fcode":"PPL",
    "gn:population":24906,
    "iso:country":"IN",
    "name:ben_x_preferred":[
        "\u09ac\u09be\u0993\u09af\u09bc\u09be\u09a8\u09be"
    ],
    "name:bpy_x_preferred":[
        "\u09ac\u09be\u09f1\u09be\u09a8\u09be"
    ],
    "name:ceb_x_preferred":[
        "Baw\u0101na"
    ],
    "name:eng_x_preferred":[
        "Bawana"
    ],
    "name:fra_x_preferred":[
        "Bawana"
    ],
    "name:hin_x_preferred":[
        "\u092c\u0935\u093e\u0928\u093e"
    ],
    "name:ita_x_preferred":[
        "Bawana"
    ],
    "name:mlg_x_preferred":[
        "Bawana"
    ],
    "name:msa_x_preferred":[
        "Bawana"
    ],
    "name:nan_x_preferred":[
        "Bawana"
    ],
    "name:new_x_preferred":[
        "\u092c\u0935\u093e\u0928\u093e"
    ],
    "name:nld_x_preferred":[
        "Bawana"
    ],
    "name:por_x_preferred":[
        "Bawana"
    ],
    "name:rus_x_preferred":[
        "\u0411\u0430\u0432\u0430\u043d\u0430"
    ],
    "name:swe_x_preferred":[
        "Baw\u0101na"
    ],
    "name:und_x_variant":[
        "Bawana Delhi"
    ],
    "name:urd_x_preferred":[
        "\u0628\u06cc\u0648\u0627\u0646\u0627"
    ],
    "name:vie_x_preferred":[
        "Bawana"
    ],
    "name:zho_x_preferred":[
        "\u5df4\u74e6\u7eb3"
    ],
    "qs:name":"Bawana",
    "qs:name_adm0":"India",
    "qs:name_adm1":"Uttar Pradesh",
    "qs:photos_9r":0,
    "qs:photos_sr":0,
    "qs:placetype":"Town",
    "qs:pop_sr":"7",
    "wd:wordcount":638,
    "wof:name":"Bawana",
    "wof:placetype":"neighbourhood",
    "wof:population":24906
},
  "geometry": {"coordinates":[77.03473,28.80059],"type":"Point"}
}