{
  "type": "Feature",
  "properties": {
    "iso:country":"IN",
    "ks:ks_name":"Perungudi",
    "ks:ks_pop":17863,
    "ks:ks_type":"VILLAGE",
    "ks:ks_uagg_main":0,
    "name:eng_x_preferred":[
        "Perungudi"
    ],
    "wof:name":"Perungudi",
    "wof:placetype":"neighbourhood",
    "wof:population":17863
},
  "geometry": {"coordinates":[77.58057100000001,8.314244],"type":"Point"}
}