{
  "type": "Feature",
  "properties": {
    "iso:country":"IN",
    "ks:ks_name":"Maddimanuguda",
    "ks:ks_pop":2,
    "ks:ks_type":"HABITATION",
    "name:eng_x_preferred":[
        "Maddimanuguda"
    ],
    "wof:name":"Maddimanuguda",
    "wof:placetype":"locality",
    "wof:population":2
},
  "geometry": {"coordinates":[83.71905599999999,18.768189],"type":"Point"}
}