{
  "type": "Feature",
  "properties": {
    "iso:country":"IN",
    "ks:ks_name":"Badka Deeh",
    "ks:ks_pop":150,
    "ks:ks_type":"HABITATION",
    "name:eng_x_preferred":[
        "Badka Deeh"
    ],
    "wof:name":"Badka Deeh",
    "wof:placetype":"locality",
    "wof:population":150
},
  "geometry": {"coordinates":[83.08567600000001,27.242854],"type":"Point"}
}