{
  "type": "Feature",
  "properties": {
    "iso:country":"IN",
    "ks:ks_alt_nam":"Dihur phonglo",
    "ks:ks_name":"Dihur Phonglo",
    "ks:ks_pop":688,
    "ks:ks_type":"HABITATION",
    "ks:ks_uagg_main":0,
    "name:eng_x_preferred":[
        "Dihur Phonglo"
    ],
    "wof:name":"Dihur Phonglo",
    "wof:placetype":"neighbourhood",
    "wof:population":688
},
  "geometry": {"coordinates":[93.136453,25.296617],"type":"Point"}
}