{
  "type": "Feature",
  "properties": {
    "gn:admin1_code":"12.0",
    "gn:admin2_code":"7.0",
    "gn:asciiname":"Kalah",
    "gn:country_code":"IN",
    "gn:dem":1529,
    "gn:feature_class":"P",
    "gn:feature_code":"PPL",
    "gn:name":"Kal\u0101h",
    "gn:population":0,
    "gn:timezone":"Asia/Kolkata",
    "iso:country":"IN",
    "name:ast_x_preferred":[
        "Kalah"
    ],
    "name:bul_x_preferred":[
        "\u041a\u0430\u043b\u0430\u0445\u0430"
    ],
    "name:dan_x_preferred":[
        "Kalaha"
    ],
    "name:deu_x_preferred":[
        "Kalaha"
    ],
    "name:epo_x_preferred":[
        "Kalaho"
    ],
    "name:est_x_preferred":[
        "Kalah"
    ],
    "name:ita_x_preferred":[
        "Kalah"
    ],
    "name:nor_x_preferred":[
        "Kalaha"
    ],
    "name:pol_x_preferred":[
        "Kalaha"
    ],
    "name:rus_x_preferred":[
        "\u041a\u0430\u043b\u0430\u0445"
    ],
    "name:spa_x_preferred":[
        "Kalah"
    ],
    "name:swe_x_preferred":[
        "Kalah"
    ],
    "name:zho_x_preferred":[
        "\u7f8e\u570b\u64ad\u68cb"
    ],
    "wof:name":"Kalah",
    "wof:placetype":"locality"
},
  "geometry": {"coordinates":[75.74594,32.63091],"type":"Point"}
}