{
  "type": "Feature",
  "properties": {
    "gn:admin1_code":"18.0",
    "gn:admin2_code":"297",
    "gn:asciiname":"Ksehkma Bazar",
    "gn:country_code":"IN",
    "gn:dem":799,
    "gn:feature_class":"P",
    "gn:feature_code":"PPL",
    "gn:name":"Ksehkma B\u0101z\u0101r",
    "gn:population":0,
    "gn:timezone":"Asia/Kolkata",
    "iso:country":"IN",
    "wof:name":"Ksehkma Bazar",
    "wof:placetype":"locality"
},
  "geometry": {"coordinates":[92.12347,25.88973],"type":"Point"}
}