{
  "type": "Feature",
  "properties": {
    "iso:country":"IN",
    "ks:ks_name":"Dumeniheju",
    "ks:ks_pop":258,
    "ks:ks_type":"VILLAGE",
    "name:eng_x_preferred":[
        "Dumeniheju"
    ],
    "wof:name":"Dumeniheju",
    "wof:placetype":"locality",
    "wof:population":258
},
  "geometry": {"coordinates":[83.433549,19.843064],"type":"Point"}
}