{
  "type": "Feature",
  "properties": {
    "iso:country":"IN",
    "ks:ks_name":"Waund",
    "ks:ks_pop":294,
    "ks:ks_type":"HABITATION",
    "name:eng_x_preferred":[
        "Waund"
    ],
    "wof:name":"Waund",
    "wof:placetype":"locality",
    "wof:population":294
},
  "geometry": {"coordinates":[73.563951,18.82157],"type":"Point"}
}