{
  "type": "Feature",
  "properties": {
    "iso:country":"IN",
    "ks:ks_name":"Pattewadi",
    "ks:ks_pop":160,
    "ks:ks_type":"HABITATION",
    "name:eng_x_preferred":[
        "Pattewadi"
    ],
    "wof:name":"Pattewadi",
    "wof:placetype":"locality",
    "wof:population":160
},
  "geometry": {"coordinates":[73.863207,19.71748],"type":"Point"}
}