{
  "type": "Feature",
  "properties": {
    "iso:country":"IN",
    "ks:ks_name":"Haridaspur",
    "ks:ks_pop":649,
    "ks:ks_type":"VILLAGE",
    "name:eng_x_preferred":[
        "Haridaspur"
    ],
    "wof:name":"Haridaspur",
    "wof:placetype":"locality",
    "wof:population":649
},
  "geometry": {"coordinates":[87.81518800000001,22.317684],"type":"Point"}
}