{
  "type": "Feature",
  "properties": {
    "iso:country":"IN",
    "ks:ks_name":"Champadih Budhtoli",
    "ks:ks_pop":132,
    "ks:ks_type":"HABITATION",
    "name:eng_x_preferred":[
        "Champadih Budhtoli"
    ],
    "wof:name":"Champadih Budhtoli",
    "wof:placetype":"locality",
    "wof:population":132
},
  "geometry": {"coordinates":[85.05738599999999,23.152154],"type":"Point"}
}