{
  "type": "Feature",
  "properties": {
    "iso:country":"IN",
    "ks:ks_name":"Kanakpar",
    "ks:ks_pop":1960,
    "ks:ks_type":"VILLAGE",
    "name:eng_x_preferred":[
        "Kanakpar"
    ],
    "wof:name":"Kanakpar",
    "wof:placetype":"locality",
    "wof:population":1960
},
  "geometry": {"coordinates":[69.51820600000001,22.100895],"type":"Point"}
}