{
  "type": "Feature",
  "properties": {
    "iso:country":"IN",
    "ks:ks_name":"Bamdeopur",
    "ks:ks_pop":55,
    "ks:ks_type":"VILLAGE",
    "ks:ks_uagg_main":0,
    "name:eng_x_preferred":[
        "Bamdeopur"
    ],
    "wof:name":"Bamdeopur",
    "wof:placetype":"neighbourhood",
    "wof:population":55
},
  "geometry": {"coordinates":[79.270194,29.281309],"type":"Point"}
}