{
  "type": "Feature",
  "properties": {
    "gn:admin1_code":"34.0",
    "gn:admin2_code":"220.0",
    "gn:asciiname":"Pakri Kanth",
    "gn:country_code":"IN",
    "gn:dem":56,
    "gn:feature_class":"P",
    "gn:feature_code":"PPL",
    "gn:name":"Pakri Kanth",
    "gn:population":0,
    "gn:timezone":"Asia/Kolkata",
    "iso:country":"IN",
    "ks:ks_name":"Pakri Kanth",
    "ks:ks_pop":1460,
    "ks:ks_type":"VILLAGE",
    "name:eng_x_preferred":[
        "Pakri Kanth"
    ],
    "wof:name":"Pakri Kanth",
    "wof:placetype":"locality",
    "wof:population":1460
},
  "geometry": {"coordinates":[85.189168,25.866937],"type":"Point"}
}