{
  "type": "Feature",
  "properties": {
    "iso:country":"IN",
    "ks:ks_name":"Paret Falia",
    "ks:ks_pop":124,
    "ks:ks_type":"HABITATION",
    "name:eng_x_preferred":[
        "Paret Falia"
    ],
    "wof:name":"Paret Falia",
    "wof:placetype":"locality",
    "wof:population":124
},
  "geometry": {"coordinates":[73.11575000000001,20.215944],"type":"Point"}
}