{
  "type": "Feature",
  "properties": {
    "iso:country":"IN",
    "ks:ks_name":"Kawkata",
    "ks:ks_pop":609,
    "ks:ks_type":"HABITATION",
    "name:eng_x_preferred":[
        "Kawkata"
    ],
    "wof:name":"Kawkata",
    "wof:placetype":"locality",
    "wof:population":609
},
  "geometry": {"coordinates":[86.982952,23.110862],"type":"Point"}
}