{
  "type": "Feature",
  "properties": {
    "iso:country":"IN",
    "ks:ks_name":"Nagar Cholia",
    "ks:ks_pop":0,
    "ks:ks_type":"VILLAGE",
    "name:eng_x_preferred":[
        "Nagar Cholia"
    ],
    "wof:name":"Nagar Cholia",
    "wof:placetype":"locality",
    "wof:population":0
},
  "geometry": {"coordinates":[85.13264599999999,24.426104],"type":"Point"}
}