{
  "type": "Feature",
  "properties": {
    "iso:country":"IN",
    "ks:ks_name":"Dhanuadi",
    "ks:ks_pop":217,
    "ks:ks_type":"VILLAGE",
    "name:eng_x_preferred":[
        "Dhanuadi"
    ],
    "wof:name":"Dhanuadi",
    "wof:placetype":"locality",
    "wof:population":217
},
  "geometry": {"coordinates":[86.386889,23.934978],"type":"Point"}
}