{
  "type": "Feature",
  "properties": {
    "iso:country":"IN",
    "ks:ks_name":"Madka Madai",
    "ks:ks_pop":164,
    "ks:ks_type":"HABITATION",
    "name:eng_x_preferred":[
        "Madka Madai"
    ],
    "wof:name":"Madka Madai",
    "wof:placetype":"locality",
    "wof:population":164
},
  "geometry": {"coordinates":[80.374392,21.775681],"type":"Point"}
}