{
  "type": "Feature",
  "properties": {
    "iso:country":"IN",
    "ks:ks_name":"Shaksahar",
    "ks:ks_pop":3209,
    "ks:ks_type":"VILLAGE",
    "ks:ks_uagg_main":0,
    "name:eng_x_preferred":[
        "Shaksahar"
    ],
    "wof:name":"Shaksahar",
    "wof:placetype":"neighbourhood",
    "wof:population":3209
},
  "geometry": {"coordinates":[88.58901299999999,22.467634],"type":"Point"}
}