{
  "type": "Feature",
  "properties": {
    "iso:country":"IN",
    "ks:ks_name":"Mohandi",
    "ks:ks_pop":108,
    "ks:ks_type":"VILLAGE",
    "name:eng_x_preferred":[
        "Mohandi"
    ],
    "wof:name":"Mohandi",
    "wof:placetype":"locality",
    "wof:population":108
},
  "geometry": {"coordinates":[80.562314,19.605114],"type":"Point"}
}