{
  "type": "Feature",
  "properties": {
    "gn:admin1_code":"11",
    "gn:admin2_code":"29.0",
    "gn:asciiname":"Dour",
    "gn:country_code":"IN",
    "gn:dem":558,
    "gn:feature_class":"P",
    "gn:feature_code":"PPL",
    "gn:name":"Dour",
    "gn:population":0,
    "gn:timezone":"Asia/Kolkata",
    "iso:country":"IN",
    "name:bre_x_preferred":[
        "Dour"
    ],
    "name:bul_x_preferred":[
        "\u0414\u0443\u0440"
    ],
    "name:cat_x_preferred":[
        "Dour"
    ],
    "name:ceb_x_preferred":[
        "Dour"
    ],
    "name:deu_x_preferred":[
        "Dour"
    ],
    "name:epo_x_preferred":[
        "Dour"
    ],
    "name:eus_x_preferred":[
        "Dour"
    ],
    "name:fas_x_preferred":[
        "\u062f\u0648\u0631"
    ],
    "name:fra_x_preferred":[
        "Dour"
    ],
    "name:ita_x_preferred":[
        "Dour"
    ],
    "name:lim_x_preferred":[
        "Dour"
    ],
    "name:nld_x_preferred":[
        "Dour"
    ],
    "name:nor_x_preferred":[
        "Dour"
    ],
    "name:oci_x_preferred":[
        "Dour"
    ],
    "name:pcd_x_preferred":[
        "Do\u00fb"
    ],
    "name:pol_x_preferred":[
        "Dour"
    ],
    "name:por_x_preferred":[
        "Dour"
    ],
    "name:ron_x_preferred":[
        "Dour"
    ],
    "name:rus_x_preferred":[
        "\u0414\u0443\u0440"
    ],
    "name:slk_x_preferred":[
        "Dour"
    ],
    "name:spa_x_preferred":[
        "Dour"
    ],
    "name:swe_x_preferred":[
        "Dour"
    ],
    "name:vie_x_preferred":[
        "Dour"
    ],
    "name:vol_x_preferred":[
        "Dour"
    ],
    "name:war_x_preferred":[
        "Dour"
    ],
    "name:wln_x_preferred":[
        "Do\u00fb"
    ],
    "name:zho_x_preferred":[
        "\u675c\u5c14"
    ],
    "wof:name":"Dour",
    "wof:placetype":"locality"
},
  "geometry": {"coordinates":[75.98980999999998,31.83136],"type":"Point"}
}