{
  "type": "Feature",
  "properties": {
    "iso:country":"IN",
    "ks:ks_name":"Tari Adong",
    "ks:ks_pop":179,
    "ks:ks_type":"HABITATION",
    "name:eng_x_preferred":[
        "Tari Adong"
    ],
    "wof:name":"Tari Adong",
    "wof:placetype":"locality",
    "wof:population":179
},
  "geometry": {"coordinates":[93.319041,25.839145],"type":"Point"}
}