{
  "type": "Feature",
  "properties": {
    "gn:admin1_code":"34.0",
    "gn:admin2_code":"220.0",
    "gn:asciiname":"Jalalpur",
    "gn:country_code":"IN",
    "gn:dem":54,
    "gn:feature_class":"P",
    "gn:feature_code":"PPL",
    "gn:name":"Jal\u0101lpur",
    "gn:population":0,
    "gn:timezone":"Asia/Kolkata",
    "iso:country":"IN",
    "ks:ks_alt_nam":"Jal\u0101lpur",
    "ks:ks_name":"Jalalpur",
    "ks:ks_pop":505,
    "ks:ks_type":"VILLAGE",
    "name:bpy_x_preferred":[
        "\u099c\u09be\u09b2\u09be\u09b2\u09aa\u09c1\u09b0"
    ],
    "name:cat_x_preferred":[
        "Jalalpur"
    ],
    "name:ceb_x_preferred":[
        "Jal\u0101lpur"
    ],
    "name:eng_x_preferred":[
        "Jalalpur"
    ],
    "name:eng_x_variant":[
        "Jal\u0101lpur"
    ],
    "name:fas_x_preferred":[
        "\u062c\u0644\u0627\u0644\u200c\u067e\u0648\u0631"
    ],
    "name:hin_x_preferred":[
        "\u091c\u0932\u093e\u0932\u092a\u0941\u0930"
    ],
    "name:ita_x_preferred":[
        "Jalalpur"
    ],
    "name:mlg_x_preferred":[
        "Jalalpur"
    ],
    "name:msa_x_preferred":[
        "Jalalpur"
    ],
    "name:new_x_preferred":[
        "\u091c\u0932\u093e\u0932\u092a\u0941\u0930"
    ],
    "name:nld_x_preferred":[
        "Jalalpur"
    ],
    "name:pol_x_preferred":[
        "Jalalpur"
    ],
    "name:por_x_preferred":[
        "Jalalpur"
    ],
    "name:tam_x_preferred":[
        "\u0b9c\u0bb2\u0bbe\u0bb2\u0bcd\u0baa\u0bc2\u0bb0\u0bcd"
    ],
    "name:urd_x_preferred":[
        "\u062c\u0644\u0627\u0644\u067e\u0648\u0631"
    ],
    "name:vie_x_preferred":[
        "Jalalpur"
    ],
    "name:zho_x_preferred":[
        "\u8d3e\u62c9\u5c14\u666e\u5c14"
    ],
    "wof:name":"Jalalpur",
    "wof:placetype":"locality",
    "wof:population":505
},
  "geometry": {"coordinates":[85.44808500000001,25.757451],"type":"Point"}
}