{
  "type": "Feature",
  "properties": {
    "iso:country":"IN",
    "ks:ks_name":"Kajekadu",
    "ks:ks_pop":224,
    "ks:ks_type":"HABITATION",
    "name:eng_x_preferred":[
        "Kajekadu"
    ],
    "wof:name":"Kajekadu",
    "wof:placetype":"locality",
    "wof:population":224
},
  "geometry": {"coordinates":[75.07826300000001,13.058407],"type":"Point"}
}