{
  "type": "Feature",
  "properties": {
    "gn:admin1_code":"2.0",
    "gn:admin2_code":"546.0",
    "gn:asciiname":"Gauravaram",
    "gn:country_code":"IN",
    "gn:dem":89,
    "gn:feature_class":"P",
    "gn:feature_code":"PPL",
    "gn:name":"Gauravaram",
    "gn:population":0,
    "gn:timezone":"Asia/Kolkata",
    "iso:country":"IN",
    "ks:ks_name":"Gavaravaram",
    "ks:ks_pop":2328,
    "ks:ks_type":"VILLAGE",
    "ks:ks_uagg_main":0,
    "name:eng_x_preferred":[
        "Gavaravaram"
    ],
    "wof:name":"Gavaravaram",
    "wof:placetype":"neighbourhood",
    "wof:population":2328
},
  "geometry": {"coordinates":[81.423951,17.113794],"type":"Point"}
}