{
  "type": "Feature",
  "properties": {
    "gn:admin1_code":"35.0",
    "gn:admin2_code":"454.0",
    "gn:asciiname":"Sarangwani",
    "gn:country_code":"IN",
    "gn:dem":473,
    "gn:feature_class":"P",
    "gn:feature_code":"PPL",
    "gn:name":"S\u0101rangw\u0101ni",
    "gn:population":0,
    "gn:timezone":"Asia/Kolkata",
    "iso:country":"IN",
    "ks:ks_name":"Surangwani",
    "ks:ks_pop":474,
    "ks:ks_type":"HABITATION",
    "name:eng_x_preferred":[
        "Surangwani"
    ],
    "name:eng_x_variant":[
        "Sarangwani"
    ],
    "wof:name":"Surangwani",
    "wof:placetype":"locality",
    "wof:population":474
},
  "geometry": {"coordinates":[80.17173200000001,22.850447],"type":"Point"}
}