{
  "type": "Feature",
  "properties": {
    "gn:admin1_code":"34.0",
    "gn:admin2_code":"214.0",
    "gn:asciiname":"Goalpara",
    "gn:country_code":"IN",
    "gn:dem":43,
    "gn:feature_class":"P",
    "gn:feature_code":"PPL",
    "gn:name":"Go\u0101lp\u0101ra",
    "gn:population":0,
    "gn:timezone":"Asia/Kolkata",
    "iso:country":"IN",
    "name:ara_x_preferred":[
        "\u062c\u0648\u0644\u0628\u0627\u0631\u0627"
    ],
    "name:asm_x_preferred":[
        "\u0997\u09cb\u09f1\u09be\u09b2\u09aa\u09be\u09f0\u09be"
    ],
    "name:bpy_x_preferred":[
        "\u0997\u09cb\u09f1\u09be\u09b2\u09aa\u09be\u09a1\u09bc\u09be"
    ],
    "name:cat_x_preferred":[
        "Goalpara"
    ],
    "name:ceb_x_preferred":[
        "Go\u0101lp\u0101ra"
    ],
    "name:fra_x_preferred":[
        "Goalpara"
    ],
    "name:guj_x_preferred":[
        "\u0a97\u0acb\u0ab2\u0aaa\u0abe\u0ab0\u0abe"
    ],
    "name:hin_x_preferred":[
        "\u0917\u094b\u0935\u093e\u0932\u092a\u093e\u0930\u093e"
    ],
    "name:ita_x_preferred":[
        "Goalpara"
    ],
    "name:kan_x_preferred":[
        "\u0c97\u0ccb\u0cb2\u0ccd\u0caa\u0cbe\u0cb0\u0cbe"
    ],
    "name:mar_x_preferred":[
        "\u0917\u094b\u0935\u093e\u0932\u092a\u093e\u0930\u093e"
    ],
    "name:mlg_x_preferred":[
        "Goalpara"
    ],
    "name:msa_x_preferred":[
        "Goalpara"
    ],
    "name:new_x_preferred":[
        "\u0917\u094b\u0935\u093e\u0932\u092a\u093e\u0930\u093e"
    ],
    "name:oci_x_preferred":[
        "Goalpara"
    ],
    "name:ori_x_preferred":[
        "\u0b17\u0b4b\u0b32\u0b2a\u0b21\u0b3c\u0b3e"
    ],
    "name:pol_x_preferred":[
        "Goalpara"
    ],
    "name:por_x_preferred":[
        "Goalpara"
    ],
    "name:rus_x_preferred":[
        "\u0413\u043e\u0430\u043b\u043f\u0430\u0440\u0430"
    ],
    "name:san_x_preferred":[
        "\u0917\u093e\u0935\u0932\u094d\u092a\u093e\u0930\u093e-\u0928\u0917\u0930\u092e\u094d"
    ],
    "name:spa_x_preferred":[
        "Goalpara"
    ],
    "name:swe_x_preferred":[
        "Goalpara"
    ],
    "name:urd_x_preferred":[
        "\u06af\u0648\u0627\u0644\u067e\u0627\u0631\u0627"
    ],
    "name:vie_x_preferred":[
        "Goalpara"
    ],
    "name:war_x_preferred":[
        "Goalpara"
    ],
    "name:zho_x_preferred":[
        "\u6208\u963f\u5c14\u5e15\u62c9"
    ],
    "wof:name":"Goalpara",
    "wof:placetype":"locality"
},
  "geometry": {"coordinates":[86.73612,25.72993],"type":"Point"}
}