{
  "type": "Feature",
  "properties": {
    "gn:admin1_code":"36.0",
    "gn:admin2_code":"161",
    "gn:asciiname":"Lodhpura Muhabbatpur",
    "gn:country_code":"IN",
    "gn:dem":152,
    "gn:feature_class":"P",
    "gn:feature_code":"PPL",
    "gn:name":"Lodhpura Muhabbatpur",
    "gn:population":0,
    "gn:timezone":"Asia/Kolkata",
    "iso:country":"IN",
    "name:und_x_variant":[
        "Lodhpura"
    ],
    "wof:name":"Lodhpura Muhabbatpur",
    "wof:placetype":"locality"
},
  "geometry": {"coordinates":[79.09604,26.84271],"type":"Point"}
}