{
  "type": "Feature",
  "properties": {
    "iso:country":"IN",
    "ks:ks_name":"Naduvinamadkal",
    "ks:ks_pop":103,
    "ks:ks_type":"VILLAGE",
    "name:eng_x_preferred":[
        "Naduvinamadkal"
    ],
    "wof:name":"Naduvinamadkal",
    "wof:placetype":"locality",
    "wof:population":103
},
  "geometry": {"coordinates":[75.667895,13.157403],"type":"Point"}
}