{
  "type": "Feature",
  "properties": {
    "gn:admin1_code":"19.0",
    "gn:admin2_code":"568.0",
    "gn:asciiname":"Jambekallur",
    "gn:country_code":"IN",
    "gn:dem":674,
    "gn:feature_class":"P",
    "gn:feature_code":"PPL",
    "gn:name":"Jambekall\u016br",
    "gn:population":0,
    "gn:timezone":"Asia/Kolkata",
    "iso:country":"IN",
    "wof:name":"Jambekallur",
    "wof:placetype":"locality"
},
  "geometry": {"coordinates":[75.23919000000002,13.7818],"type":"Point"}
}