{
  "type": "Feature",
  "properties": {
    "iso:country":"IN",
    "ks:ks_name":"Chigauna",
    "ks:ks_pop":349,
    "ks:ks_type":"VILLAGE",
    "ks:ks_uagg_main":0,
    "name:eng_x_preferred":[
        "Chigauna"
    ],
    "wof:name":"Chigauna",
    "wof:placetype":"neighbourhood",
    "wof:population":349
},
  "geometry": {"coordinates":[83.135745,26.818266],"type":"Point"}
}