{
  "type": "Feature",
  "properties": {
    "iso:country":"IN",
    "ks:ks_name":"Devigarh",
    "ks:ks_pop":103,
    "ks:ks_type":"VILLAGE",
    "name:eng_x_preferred":[
        "Devigarh"
    ],
    "wof:name":"Devigarh",
    "wof:placetype":"locality",
    "wof:population":103
},
  "geometry": {"coordinates":[72.322639,26.264808],"type":"Point"}
}