{
  "type": "Feature",
  "properties": {
    "iso:country":"IN",
    "ks:ks_alt_nam":"POKHAR MUSHAHARI",
    "ks:ks_name":"Pokhar Mushahari",
    "ks:ks_pop":109,
    "ks:ks_type":"HABITATION",
    "name:eng_x_preferred":[
        "Pokhar Mushahari"
    ],
    "wof:name":"Pokhar Mushahari",
    "wof:placetype":"locality",
    "wof:population":109
},
  "geometry": {"coordinates":[87.4479,25.86504],"type":"Point"}
}