{
  "type": "Feature",
  "properties": {
    "iso:country":"IN",
    "ks:ks_name":"Panikondanviduthi",
    "ks:ks_pop":1592,
    "ks:ks_type":"HABITATION",
    "name:eng_x_preferred":[
        "Panikondanviduthi"
    ],
    "wof:name":"Panikondanviduthi",
    "wof:placetype":"locality",
    "wof:population":1592
},
  "geometry": {"coordinates":[79.140294,10.499109],"type":"Point"}
}