{
  "type": "Feature",
  "properties": {
    "iso:country":"IN",
    "ks:ks_name":"Schoolpara",
    "ks:ks_pop":309,
    "ks:ks_type":"HABITATION",
    "name:eng_x_preferred":[
        "Schoolpara"
    ],
    "wof:name":"Schoolpara",
    "wof:placetype":"locality",
    "wof:population":309
},
  "geometry": {"coordinates":[81.48257099999999,19.37528],"type":"Point"}
}