{
  "type": "Feature",
  "properties": {
    "iso:country":"IN",
    "ks:ks_name":"Muttugadani",
    "ks:ks_pop":97,
    "ks:ks_type":"HABITATION",
    "name:eng_x_preferred":[
        "Muttugadani"
    ],
    "wof:name":"Muttugadani",
    "wof:placetype":"locality",
    "wof:population":97
},
  "geometry": {"coordinates":[75.396489,13.541592],"type":"Point"}
}