{
  "type": "Feature",
  "properties": {
    "iso:country":"IN",
    "ks:ks_name":"Poovanallur",
    "ks:ks_pop":152,
    "ks:ks_type":"HABITATION",
    "name:eng_x_preferred":[
        "Poovanallur"
    ],
    "wof:name":"Poovanallur",
    "wof:placetype":"locality",
    "wof:population":152
},
  "geometry": {"coordinates":[77.60024199999999,10.947573],"type":"Point"}
}