{
  "type": "Feature",
  "properties": {
    "gn:admin1_code":"36.0",
    "gn:admin2_code":"182.0",
    "gn:asciiname":"Nachaura",
    "gn:country_code":"IN",
    "gn:dem":106,
    "gn:feature_class":"P",
    "gn:feature_code":"PPL",
    "gn:name":"Nachaura",
    "gn:population":0,
    "gn:timezone":"Asia/Kolkata",
    "iso:country":"IN",
    "ks:ks_name":"Nachaura",
    "ks:ks_pop":1270,
    "ks:ks_type":"VILLAGE",
    "name:eng_x_preferred":[
        "Nachaura"
    ],
    "wof:name":"Nachaura",
    "wof:placetype":"locality",
    "wof:population":1270
},
  "geometry": {"coordinates":[82.44007499999999,27.467667],"type":"Point"}
}