{
  "type": "Feature",
  "properties": {
    "iso:country":"IN",
    "ks:ks_name":"Kawadewasti",
    "ks:ks_pop":61,
    "ks:ks_type":"HABITATION",
    "name:eng_x_preferred":[
        "Kawadewasti"
    ],
    "wof:name":"Kawadewasti",
    "wof:placetype":"locality",
    "wof:population":61
},
  "geometry": {"coordinates":[73.96457100000001,19.189453],"type":"Point"}
}