{
  "type": "Feature",
  "properties": {
    "iso:country":"IN",
    "ks:ks_name":"Siroi Aima",
    "ks:ks_pop":2001,
    "ks:ks_type":"VILLAGE",
    "name:eng_x_preferred":[
        "Siroi Aima"
    ],
    "wof:name":"Siroi Aima",
    "wof:placetype":"locality",
    "wof:population":2001
},
  "geometry": {"coordinates":[85.20650000000001,26.042204],"type":"Point"}
}