{
  "type": "Feature",
  "properties": {
    "gn:admin1_code":"40.0",
    "gn:admin2_code":"541.0",
    "gn:asciiname":"Kadekai",
    "gn:country_code":"IN",
    "gn:dem":93,
    "gn:feature_class":"P",
    "gn:feature_code":"PPL",
    "gn:name":"Kadekai",
    "gn:population":0,
    "gn:timezone":"Asia/Kolkata",
    "iso:country":"IN",
    "ks:ks_name":"Kadekal",
    "ks:ks_type":"VILLAGE",
    "name:eng_x_preferred":[
        "Kadekal"
    ],
    "name:eng_x_variant":[
        "Kadekai"
    ],
    "wof:name":"Kadekal",
    "wof:placetype":"locality"
},
  "geometry": {"coordinates":[80.431611,18.537331],"type":"Point"}
}