{
  "type": "Feature",
  "properties": {
    "gn:admin1_code":"12.0",
    "gn:admin2_code":"6.0",
    "gn:asciiname":"Pir Bhera",
    "gn:country_code":"IN",
    "gn:dem":991,
    "gn:feature_class":"P",
    "gn:feature_code":"PPL",
    "gn:name":"P\u012br Bhera",
    "gn:population":0,
    "gn:timezone":"Asia/Kolkata",
    "iso:country":"IN",
    "wof:name":"Pir Bhera",
    "wof:placetype":"locality"
},
  "geometry": {"coordinates":[74.25270999999999,33.28279000000001],"type":"Point"}
}