{
  "type": "Feature",
  "properties": {
    "gn:admin1_code":"2.0",
    "gn:admin2_code":"554.0",
    "gn:asciiname":"Govindappanayudukhandriga",
    "gn:country_code":"IN",
    "gn:dem":156,
    "gn:feature_class":"P",
    "gn:feature_code":"PPL",
    "gn:name":"Govindappan\u0101yudukhandriga",
    "gn:population":0,
    "gn:timezone":"Asia/Kolkata",
    "iso:country":"IN",
    "wof:name":"Govindappanayudukhandriga",
    "wof:placetype":"locality"
},
  "geometry": {"coordinates":[79.5508,13.4057],"type":"Point"}
}