{
  "type": "Feature",
  "properties": {
    "gn:admin1_code":"36.0",
    "gn:admin2_code":"135.0",
    "gn:asciiname":"Akbarpur",
    "gn:country_code":"IN",
    "gn:dem":191,
    "gn:feature_class":"P",
    "gn:feature_code":"PPL",
    "gn:name":"Akbarpur",
    "gn:population":0,
    "gn:timezone":"Asia/Kolkata",
    "iso:country":"IN",
    "name:und_x_variant":[
        "Jam\u012bma J\u0101rai"
    ],
    "wof:name":"Akbarpur",
    "wof:placetype":"locality"
},
  "geometry": {"coordinates":[78.79004,28.47888],"type":"Point"}
}