{
  "type": "Feature",
  "properties": {
    "iso:country":"IN",
    "ks:ks_name":"Yallareddiguntalu",
    "ks:ks_pop":137,
    "ks:ks_type":"HABITATION",
    "name:eng_x_preferred":[
        "Yallareddiguntalu"
    ],
    "wof:name":"Yallareddiguntalu",
    "wof:placetype":"locality",
    "wof:population":137
},
  "geometry": {"coordinates":[79.329269,13.423999],"type":"Point"}
}