{
  "type": "Feature",
  "properties": {
    "iso:country":"IN",
    "ks:ks_name":"Jungle Block No-1",
    "ks:ks_pop":5,
    "ks:ks_type":"VILLAGE",
    "name:eng_x_preferred":[
        "Jungle Block No-1"
    ],
    "wof:name":"Jungle Block No-1",
    "wof:placetype":"locality",
    "wof:population":5
},
  "geometry": {"coordinates":[84.141459,19.135686],"type":"Point"}
}