{
  "type": "Feature",
  "properties": {
    "gn:country":"IN",
    "gn:fcode":"PPL",
    "gn:population":10891,
    "iso:country":"IN",
    "name:ben_x_preferred":[
        "\u0996\u09c7\u09a4\u09cd\u09b0\u09bf"
    ],
    "name:bpy_x_preferred":[
        "\u0996\u09c7\u09a4\u09cd\u09b0\u09bf"
    ],
    "name:hin_x_preferred":[
        "\u0916\u0947\u0924\u0921\u093c\u0940"
    ],
    "name:new_x_preferred":[
        "\u0916\u0947\u0930\u094d\u0924\u0940"
    ],
    "name:und_x_variant":[
        "Khetri"
    ],
    "name:zho_x_preferred":[
        "\u51ef\u7279\u91cc"
    ],
    "qs:name":"Kheri Sampla",
    "qs:name_adm0":"India",
    "qs:name_adm1":"Haryana",
    "qs:photos_9r":0,
    "qs:photos_sr":0,
    "qs:placetype":"Town",
    "qs:pop_sr":"6",
    "wof:name":"Kheri Sampla",
    "wof:placetype":"locality",
    "wof:population":10891
},
  "geometry": {"coordinates":[76.77406999999999,28.77768],"type":"Point"}
}