{
  "type": "Feature",
  "properties": {
    "iso:country":"IN",
    "ks:ks_name":"Matarvadi",
    "ks:ks_pop":497,
    "ks:ks_type":"VILLAGE",
    "name:eng_x_preferred":[
        "Matarvadi"
    ],
    "wof:name":"Matarvadi",
    "wof:placetype":"locality",
    "wof:population":497
},
  "geometry": {"coordinates":[72.149299,23.868021],"type":"Point"}
}