{
  "type": "Feature",
  "properties": {
    "iso:country":"IN",
    "ks:ks_name":"Ambepada",
    "ks:ks_pop":181,
    "ks:ks_type":"HABITATION",
    "name:eng_x_preferred":[
        "Ambepada"
    ],
    "wof:name":"Ambepada",
    "wof:placetype":"locality",
    "wof:population":181
},
  "geometry": {"coordinates":[73.36617099999999,20.004181],"type":"Point"}
}