{
  "type": "Feature",
  "properties": {
    "gn:admin1_code":"36",
    "gn:admin2_code":"180.0",
    "gn:asciiname":"Muria",
    "gn:country_code":"IN",
    "gn:dem":115,
    "gn:feature_class":"P",
    "gn:feature_code":"PPL",
    "gn:name":"Muria",
    "gn:population":0,
    "gn:timezone":"Asia/Kolkata",
    "iso:country":"IN",
    "name:ceb_x_preferred":[
        "Muria"
    ],
    "name:deu_x_preferred":[
        "Muria"
    ],
    "name:fra_x_preferred":[
        "Muria"
    ],
    "name:swe_x_preferred":[
        "Muria"
    ],
    "wof:name":"Muria",
    "wof:placetype":"neighbourhood"
},
  "geometry": {"coordinates":[81.57644999999999,27.40215],"type":"Point"}
}