{
  "type": "Feature",
  "properties": {
    "gn:admin1_code":"25.0",
    "gn:admin2_code":"619.0",
    "gn:asciiname":"Vaduvur Vadakkuttoppu",
    "gn:country_code":"IN",
    "gn:dem":36,
    "gn:feature_class":"P",
    "gn:feature_code":"PPL",
    "gn:name":"Vaduv\u016br Vadakkuttoppu",
    "gn:population":0,
    "gn:timezone":"Asia/Kolkata",
    "iso:country":"IN",
    "wof:name":"Vaduvur Vadakkuttoppu",
    "wof:placetype":"locality"
},
  "geometry": {"coordinates":[79.33018,10.72359],"type":"Point"}
}