{
  "type": "Feature",
  "properties": {
    "iso:country":"IN",
    "ks:ks_name":"Gullekar Wada",
    "ks:ks_pop":188,
    "ks:ks_type":"HABITATION",
    "name:eng_x_preferred":[
        "Gullekar Wada"
    ],
    "wof:name":"Gullekar Wada",
    "wof:placetype":"locality",
    "wof:population":188
},
  "geometry": {"coordinates":[74.54248,15.398352],"type":"Point"}
}