{
  "type": "Feature",
  "properties": {
    "iso:country":"IN",
    "ks:ks_alt_nam":"P\u0101ndukeshwar Reserved Forest",
    "ks:ks_name":"Pandukeshwar Reserved Forest",
    "ks:ks_type":"VILLAGE",
    "name:eng_x_preferred":[
        "Pandukeshwar Reserved Forest"
    ],
    "name:eng_x_variant":[
        "P\u0101ndukeshwar Reserved Forest"
    ],
    "wof:name":"Pandukeshwar Reserved Forest",
    "wof:placetype":"locality"
},
  "geometry": {"coordinates":[79.599298,30.671494],"type":"Point"}
}