{
  "type": "Feature",
  "properties": {
    "iso:country":"IN",
    "ks:ks_name":"Kumbalakode",
    "ks:ks_pop":365,
    "ks:ks_type":"HABITATION",
    "name:eng_x_preferred":[
        "Kumbalakode"
    ],
    "wof:name":"Kumbalakode",
    "wof:placetype":"locality",
    "wof:population":365
},
  "geometry": {"coordinates":[76.39451800000001,10.66324],"type":"Point"}
}