{
  "type": "Feature",
  "properties": {
    "iso:country":"IN",
    "ks:ks_name":"Gattumpakalu",
    "ks:ks_pop":190,
    "ks:ks_type":"VILLAGE",
    "name:eng_x_preferred":[
        "Gattumpakalu"
    ],
    "wof:name":"Gattumpakalu",
    "wof:placetype":"locality",
    "wof:population":190
},
  "geometry": {"coordinates":[82.51682599999999,17.831866],"type":"Point"}
}