{
  "type": "Feature",
  "properties": {
    "gn:admin1_code":"1.0",
    "gn:admin2_code":"640",
    "gn:asciiname":"Bindraban",
    "gn:country_code":"IN",
    "gn:dem":6,
    "gn:feature_class":"P",
    "gn:feature_code":"PPL",
    "gn:name":"Bindr\u0101ban",
    "gn:population":0,
    "gn:timezone":"Asia/Kolkata",
    "iso:country":"IN",
    "wof:name":"Bindraban",
    "wof:placetype":"locality"
},
  "geometry": {"coordinates":[92.66667,11.71667],"type":"Point"}
}