{
  "type": "Feature",
  "properties": {
    "iso:country":"IN",
    "ks:ks_name":"Maglo Pukhuri",
    "ks:ks_pop":791,
    "ks:ks_type":"VILLAGE",
    "name:eng_x_preferred":[
        "Maglo Pukhuri"
    ],
    "wof:name":"Maglo Pukhuri",
    "wof:placetype":"locality",
    "wof:population":791
},
  "geometry": {"coordinates":[94.480131,26.968048],"type":"Point"}
}