{
  "type": "Feature",
  "properties": {
    "iso:country":"IN",
    "ks:ks_alt_nam":"N\u0101ikaneri Reserved Forest",
    "ks:ks_name":"Naikaneri Reserved Forest",
    "ks:ks_type":"VILLAGE",
    "name:eng_x_preferred":[
        "Naikaneri Reserved Forest"
    ],
    "name:eng_x_variant":[
        "N\u0101ikaneri Reserved Forest"
    ],
    "wof:name":"Naikaneri Reserved Forest",
    "wof:placetype":"locality"
},
  "geometry": {"coordinates":[78.62821,13.019752],"type":"Point"}
}