{
  "type": "Feature",
  "properties": {
    "iso:country":"IN",
    "ks:ks_name":"Chak Asrasar",
    "ks:ks_pop":425,
    "ks:ks_type":"VILLAGE",
    "name:eng_x_preferred":[
        "Chak Asrasar"
    ],
    "wof:name":"Chak Asrasar",
    "wof:placetype":"locality",
    "wof:population":425
},
  "geometry": {"coordinates":[73.830011,28.93125],"type":"Point"}
}