{
  "type": "Feature",
  "properties": {
    "iso:country":"IN",
    "ks:ks_name":"Maharajapuram",
    "ks:ks_pop":362,
    "ks:ks_type":"HABITATION",
    "ks:ks_uagg_main":0,
    "name:eng_x_preferred":[
        "Maharajapuram"
    ],
    "wof:name":"Maharajapuram",
    "wof:placetype":"neighbourhood",
    "wof:population":362
},
  "geometry": {"coordinates":[77.45108399999999,8.663581],"type":"Point"}
}