{
  "type": "Feature",
  "properties": {
    "gn:admin1_code":"16",
    "gn:admin2_code":"517.0",
    "gn:asciiname":"Parali",
    "gn:country_code":"IN",
    "gn:dem":115,
    "gn:feature_class":"P",
    "gn:feature_code":"PPL",
    "gn:name":"Parali",
    "gn:population":0,
    "gn:timezone":"Asia/Kolkata",
    "iso:country":"IN",
    "wof:name":"Parali",
    "wof:placetype":"locality"
},
  "geometry": {"coordinates":[73.26045999999999,19.71015],"type":"Point"}
}