{
  "type": "Feature",
  "properties": {
    "gn:admin1_code":"12.0",
    "gn:admin2_code":"022",
    "gn:asciiname":"Jogpura",
    "gn:country_code":"IN",
    "gn:dem":314,
    "gn:feature_class":"P",
    "gn:feature_code":"PPL",
    "gn:name":"Jogpura",
    "gn:population":0,
    "gn:timezone":"Asia/Kolkata",
    "iso:country":"IN",
    "name:und_x_variant":[
        "Yogpur"
    ],
    "wof:name":"Jogpura",
    "wof:placetype":"locality"
},
  "geometry": {"coordinates":[74.97193,32.58324],"type":"Point"}
}