{
  "type": "Feature",
  "properties": {
    "iso:country":"IN",
    "ks:ks_name":"Mohalla",
    "ks:ks_pop":85,
    "ks:ks_type":"HABITATION",
    "ks:ks_uagg_main":0,
    "name:eng_x_preferred":[
        "Mohalla"
    ],
    "wof:name":"Mohalla",
    "wof:placetype":"neighbourhood",
    "wof:population":85
},
  "geometry": {"coordinates":[73.512703,17.483908],"type":"Point"}
}