{
  "type": "Feature",
  "properties": {
    "gn:admin1_code":"34.0",
    "gn:admin2_code":"212.0",
    "gn:asciiname":"Kusaha",
    "gn:country_code":"IN",
    "gn:dem":32,
    "gn:feature_class":"P",
    "gn:feature_code":"PPL",
    "gn:name":"Kus\u0101ha",
    "gn:population":0,
    "gn:timezone":"Asia/Kolkata",
    "iso:country":"IN",
    "ks:ks_alt_nam":"KUSAHA",
    "ks:ks_name":"Kusaha",
    "ks:ks_pop":973,
    "ks:ks_type":"HABITATION",
    "ks:ks_uagg_main":0,
    "name:eng_x_preferred":[
        "Kusaha"
    ],
    "wof:name":"Kusaha",
    "wof:placetype":"neighbourhood",
    "wof:population":973
},
  "geometry": {"coordinates":[87.669747,25.432809],"type":"Point"}
}