{
  "type": "Feature",
  "properties": {
    "iso:country":"IN",
    "ks:ks_name":"Golikatta Hitlakai",
    "ks:ks_pop":68,
    "ks:ks_type":"HABITATION",
    "name:eng_x_preferred":[
        "Golikatta Hitlakai"
    ],
    "wof:name":"Golikatta Hitlakai",
    "wof:placetype":"locality",
    "wof:population":68
},
  "geometry": {"coordinates":[74.792941,14.512576],"type":"Point"}
}