{
  "type": "Feature",
  "properties": {
    "iso:country":"IN",
    "ks:ks_alt_nam":"GUDDITOLA",
    "ks:ks_name":"Gudditola",
    "ks:ks_pop":186,
    "ks:ks_type":"HABITATION",
    "name:eng_x_preferred":[
        "Gudditola"
    ],
    "wof:name":"Gudditola",
    "wof:placetype":"locality",
    "wof:population":186
},
  "geometry": {"coordinates":[82.078971,22.987597],"type":"Point"}
}