{
  "type": "Feature",
  "properties": {
    "gn:admin1_code":"16",
    "gn:admin2_code":"524.0",
    "gn:asciiname":"Pardhiwadi",
    "gn:country_code":"IN",
    "gn:dem":612,
    "gn:feature_class":"P",
    "gn:feature_code":"PPL",
    "gn:name":"P\u0101rdh\u012bw\u0101di",
    "gn:population":0,
    "gn:timezone":"Asia/Kolkata",
    "iso:country":"IN",
    "wof:name":"Pardhiwadi",
    "wof:placetype":"locality"
},
  "geometry": {"coordinates":[76.60574,18.09156],"type":"Point"}
}