{
  "type": "Feature",
  "properties": {
    "gn:admin1_code":"24.0",
    "gn:admin2_code":"130.0",
    "gn:asciiname":"Ghoramari",
    "gn:country_code":"IN",
    "gn:dem":311,
    "gn:feature_class":"P",
    "gn:feature_code":"PPL",
    "gn:name":"Ghor\u0101m\u0101ri",
    "gn:population":0,
    "gn:timezone":"Asia/Kolkata",
    "iso:country":"IN",
    "ks:ks_alt_nam":"Ghor\u0101m\u0101ri",
    "ks:ks_name":"Ghoramari",
    "ks:ks_pop":695,
    "ks:ks_type":"VILLAGE",
    "name:eng_x_preferred":[
        "Ghoramari"
    ],
    "name:eng_x_variant":[
        "Ghor\u0101m\u0101ri"
    ],
    "wof:name":"Ghoramari",
    "wof:placetype":"locality",
    "wof:population":695
},
  "geometry": {"coordinates":[73.149714,24.213997],"type":"Point"}
}