{
  "type": "Feature",
  "properties": {
    "gn:admin1_code":"9.0",
    "gn:admin2_code":"474.0",
    "gn:asciiname":"Gangad",
    "gn:country_code":"IN",
    "gn:dem":20,
    "gn:feature_class":"P",
    "gn:feature_code":"PPL",
    "gn:name":"Gangad",
    "gn:population":0,
    "gn:timezone":"Asia/Kolkata",
    "iso:country":"IN",
    "wof:name":"Gangad",
    "wof:placetype":"locality"
},
  "geometry": {"coordinates":[72.27845000000001,22.67809],"type":"Point"}
}