{
  "type": "Feature",
  "properties": {
    "iso:country":"IN",
    "ks:ks_name":"3 Km Sukhdeopura",
    "ks:ks_pop":611,
    "ks:ks_type":"HABITATION",
    "name:eng_x_preferred":[
        "3 Km Sukhdeopura"
    ],
    "wof:name":"3 Km Sukhdeopura",
    "wof:placetype":"locality",
    "wof:population":611
},
  "geometry": {"coordinates":[72.908541,28.492442],"type":"Point"}
}