{
  "type": "Feature",
  "properties": {
    "iso:country":"IN",
    "ks:ks_name":"Raybar Uttar",
    "ks:ks_pop":2452,
    "ks:ks_type":"VILLAGE",
    "name:eng_x_preferred":[
        "Raybar Uttar"
    ],
    "wof:name":"Raybar Uttar",
    "wof:placetype":"locality",
    "wof:population":2452
},
  "geometry": {"coordinates":[87.295766,21.949883],"type":"Point"}
}