{
  "type": "Feature",
  "properties": {
    "gn:admin1_code":"39.0",
    "gn:admin2_code":"68.0",
    "gn:asciiname":"Ibrahimpur",
    "gn:country_code":"IN",
    "gn:dem":267,
    "gn:feature_class":"P",
    "gn:feature_code":"PPL",
    "gn:name":"Ibr\u0101h\u012bmpur",
    "gn:population":0,
    "gn:timezone":"Asia/Kolkata",
    "iso:country":"IN",
    "ks:ks_alt_nam":"Ibr\u0101h\u012bmpur",
    "ks:ks_name":"Ibrahimpur",
    "ks:ks_pop":5993,
    "ks:ks_type":"VILLAGE",
    "ks:ks_uagg_main":0,
    "name:ara_x_preferred":[
        "\u0625\u0628\u0631\u0627\u0647\u064a\u0645 \u0628\u0648\u0631"
    ],
    "name:ben_bn_x_preferred":[
        "\u0987\u09ac\u09cd\u09b0\u09be\u09b9\u09bf\u09ae\u09aa\u09c1\u09b0"
    ],
    "name:ben_in_x_preferred":[
        "\u0987\u09ac\u09cd\u09b0\u09be\u09b9\u09bf\u09ae\u09aa\u09c1\u09b0"
    ],
    "name:eng_x_preferred":[
        "Ibrahimpur"
    ],
    "name:eng_x_variant":[
        "Ibr\u0101h\u012bmpur"
    ],
    "name:guj_x_preferred":[
        "\u0a87\u0aac\u0acd\u0ab0\u0abe\u0ab9\u0ac0\u0aae\u0aaa\u0ac1\u0ab0"
    ],
    "name:hin_x_preferred":[
        "\u0907\u092c\u094d\u0930\u093e\u0939\u093f\u092e\u092a\u0941\u0930"
    ],
    "name:kan_x_preferred":[
        "\u0c87\u0cac\u0ccd\u0cb0\u0cbe\u0cb9\u0cbf\u0cae\u0ccd"
    ],
    "name:mal_x_preferred":[
        "\u0d07\u0d2c\u0d4d\u0d30\u0d3e\u0d39\u0d3f\u0d02\u0d2a\u0d42\u0d7c"
    ],
    "name:mar_x_preferred":[
        "\u0907\u092c\u094d\u0930\u093e\u0939\u093f\u092e\u092a\u0942\u0930"
    ],
    "name:pan_x_preferred":[
        "\u0a07\u0a2c\u0a30\u0a3e\u0a39\u0a3f\u0a2e\u0a2a\u0a41\u0a30"
    ],
    "name:tam_x_preferred":[
        "\u0b87\u0baa\u0bcd\u0bb0\u0bbe\u0bb9\u0bbf\u0bae\u0bcd\u0baa\u0bc2\u0bb0\u0bcd"
    ],
    "name:tel_x_preferred":[
        "\u0c07\u0c2c\u0c4d\u0c30\u0c39\u0c3f\u0c02\u0c2a\u0c42\u0c30\u0c4d"
    ],
    "name:urd_x_preferred":[
        "\u0627\u0628\u0631\u0627\u06c1\u06cc\u0645 \u067e\u0648\u0631"
    ],
    "wof:name":"Ibrahimpur",
    "wof:placetype":"neighbourhood",
    "wof:population":5993
},
  "geometry": {"coordinates":[77.86936900000001,29.895136],"type":"Point"}
}