{
  "type": "Feature",
  "properties": {
    "iso:country":"IN",
    "ks:ks_name":"Mittapalli",
    "ks:ks_pop":26,
    "ks:ks_type":"HABITATION",
    "name:eng_x_preferred":[
        "Mittapalli"
    ],
    "wof:name":"Mittapalli",
    "wof:placetype":"locality",
    "wof:population":26
},
  "geometry": {"coordinates":[80.540148,17.702187],"type":"Point"}
}