{
  "type": "Feature",
  "properties": {
    "iso:country":"IN",
    "ks:ks_name":"Kalta",
    "ks:ks_type":"VILLAGE",
    "name:eng_x_preferred":[
        "Kalta"
    ],
    "wof:name":"Kalta",
    "wof:placetype":"locality"
},
  "geometry": {"coordinates":[85.225072,21.974293],"type":"Point"}
}