{
  "type": "Feature",
  "properties": {
    "iso:country":"IN",
    "ks:ks_name":"Makhi",
    "ks:ks_pop":363,
    "ks:ks_type":"VILLAGE",
    "ks:ks_uagg_main":0,
    "name:eng_x_preferred":[
        "Makhi"
    ],
    "wof:name":"Makhi",
    "wof:placetype":"neighbourhood",
    "wof:population":363
},
  "geometry": {"coordinates":[86.224232,20.270995],"type":"Point"}
}