{
  "type": "Feature",
  "properties": {
    "gn:admin1_code":"36",
    "gn:admin2_code":"180.0",
    "gn:asciiname":"P Mahabir Kahar",
    "gn:country_code":"IN",
    "gn:dem":115,
    "gn:feature_class":"P",
    "gn:feature_code":"PPL",
    "gn:name":"P Mah\u0101b\u012br Kah\u0101r",
    "gn:population":0,
    "gn:timezone":"Asia/Kolkata",
    "iso:country":"IN",
    "wof:name":"P Mahabir Kahar",
    "wof:placetype":"locality"
},
  "geometry": {"coordinates":[81.56491,27.39267000000001],"type":"Point"}
}