{
  "type": "Feature",
  "properties": {
    "iso:country":"IN",
    "ks:ks_name":"Vanchipetti",
    "ks:ks_pop":120,
    "ks:ks_type":"HABITATION",
    "name:eng_x_preferred":[
        "Vanchipetti"
    ],
    "wof:name":"Vanchipetti",
    "wof:placetype":"locality",
    "wof:population":120
},
  "geometry": {"coordinates":[76.855256,8.919176],"type":"Point"}
}