{
  "type": "Feature",
  "properties": {
    "iso:country":"IN",
    "ks:ks_name":"Basuli",
    "ks:ks_pop":189,
    "ks:ks_type":"VILLAGE",
    "name:eng_x_preferred":[
        "Basuli"
    ],
    "wof:name":"Basuli",
    "wof:placetype":"locality",
    "wof:population":189
},
  "geometry": {"coordinates":[82.15140599999999,24.566071],"type":"Point"}
}