{
  "type": "Feature",
  "properties": {
    "iso:country":"IN",
    "ks:ks_alt_nam":"GOSIANPURWA",
    "ks:ks_name":"Gosianpurwa",
    "ks:ks_pop":851,
    "ks:ks_type":"HABITATION",
    "name:eng_x_preferred":[
        "Gosianpurwa"
    ],
    "wof:name":"Gosianpurwa",
    "wof:placetype":"locality",
    "wof:population":851
},
  "geometry": {"coordinates":[81.471245,27.972915],"type":"Point"}
}