{
  "type": "Feature",
  "properties": {
    "iso:country":"IN",
    "ks:ks_name":"Thannerpandhal",
    "ks:ks_pop":327,
    "ks:ks_type":"HABITATION",
    "ks:ks_uagg_main":0,
    "name:eng_x_preferred":[
        "Thannerpandhal"
    ],
    "wof:name":"Thannerpandhal",
    "wof:placetype":"neighbourhood",
    "wof:population":327
},
  "geometry": {"coordinates":[79.67010999999999,10.818636],"type":"Point"}
}