{
  "type": "Feature",
  "properties": {
    "gn:admin1_code":"36.0",
    "gn:admin2_code":"173.0",
    "gn:asciiname":"Hariharpur Kailah",
    "gn:country_code":"IN",
    "gn:dem":102,
    "gn:feature_class":"P",
    "gn:feature_code":"PPL",
    "gn:name":"Hariharpur Kail\u0101h",
    "gn:population":0,
    "gn:timezone":"Asia/Kolkata",
    "iso:country":"IN",
    "wof:name":"Hariharpur Kailah",
    "wof:placetype":"locality"
},
  "geometry": {"coordinates":[81.84299,25.90573],"type":"Point"}
}