{
  "type": "Feature",
  "properties": {
    "iso:country":"IN",
    "ks:ks_name":"Quitol",
    "ks:ks_pop":1393,
    "ks:ks_type":"VILLAGE",
    "name:eng_x_preferred":[
        "Quitol"
    ],
    "wof:name":"Quitol",
    "wof:placetype":"locality",
    "wof:population":1393
},
  "geometry": {"coordinates":[73.986486,15.119823],"type":"Point"}
}