{
  "type": "Feature",
  "properties": {
    "iso:country":"IN",
    "ks:ks_name":"Taliwadi",
    "ks:ks_pop":208,
    "ks:ks_type":"HABITATION",
    "name:eng_x_preferred":[
        "Taliwadi"
    ],
    "wof:name":"Taliwadi",
    "wof:placetype":"locality",
    "wof:population":208
},
  "geometry": {"coordinates":[73.53818099999999,16.971167],"type":"Point"}
}