{
  "type": "Feature",
  "properties": {
    "gn:admin1_code":"28.0",
    "gn:admin2_code":"334.0",
    "gn:asciiname":"Hararampur",
    "gn:country_code":"IN",
    "gn:dem":45,
    "gn:feature_class":"P",
    "gn:feature_code":"PPL",
    "gn:name":"Harar\u0101mpur",
    "gn:population":0,
    "gn:timezone":"Asia/Kolkata",
    "iso:country":"IN",
    "ks:ks_name":"Harirampur",
    "ks:ks_pop":1088,
    "ks:ks_type":"VILLAGE",
    "ks:ks_uagg_main":0,
    "name:eng_x_preferred":[
        "Harirampur"
    ],
    "wof:name":"Harirampur",
    "wof:placetype":"neighbourhood",
    "wof:population":1088
},
  "geometry": {"coordinates":[87.844024,24.370097],"type":"Point"}
}