{
  "type": "Feature",
  "properties": {
    "gn:admin1_code":"33",
    "gn:admin2_code":"585.0",
    "gn:asciiname":"Malvona",
    "gn:cc2":"IN",
    "gn:country_code":"IN",
    "gn:dem":99,
    "gn:feature_class":"P",
    "gn:feature_code":"PPL",
    "gn:name":"Malvona",
    "gn:population":0,
    "gn:timezone":"Asia/Kolkata",
    "iso:country":"IN",
    "ks:ks_name":"Malpona",
    "ks:ks_pop":293,
    "ks:ks_type":"VILLAGE",
    "name:eng_x_preferred":[
        "Malpona"
    ],
    "name:eng_x_variant":[
        "Malvona"
    ],
    "name:und_x_variant":[
        "Malbona",
        "Malvona"
    ],
    "wof:name":"Malpona",
    "wof:placetype":"locality",
    "wof:population":293
},
  "geometry": {"coordinates":[74.176344,15.44575],"type":"Point"}
}