{
  "type": "Feature",
  "properties": {
    "gn:admin1_code":"33",
    "gn:admin2_code":"585.0",
    "gn:asciiname":"Malvona",
    "gn:cc2":"IN",
    "gn:country_code":"IN",
    "gn:dem":99,
    "gn:feature_class":"P",
    "gn:feature_code":"PPL",
    "gn:name":"Malvona",
    "gn:population":0,
    "gn:timezone":"Asia/Kolkata",
    "iso:country":"IN",
    "name:und_x_variant":[
        "Malbona",
        "Malvona"
    ],
    "wof:name":"Malvona",
    "wof:placetype":"locality"
},
  "geometry": {"coordinates":[74.16667,15.45],"type":"Point"}
}