{
  "type": "Feature",
  "properties": {
    "gn:admin1_code":"36.0",
    "gn:admin2_code":"193.0",
    "gn:asciiname":"Umti",
    "gn:country_code":"IN",
    "gn:dem":61,
    "gn:feature_class":"P",
    "gn:feature_code":"PPL",
    "gn:name":"Umti",
    "gn:population":0,
    "gn:timezone":"Asia/Kolkata",
    "iso:country":"IN",
    "wof:name":"Umti",
    "wof:placetype":"locality"
},
  "geometry": {"coordinates":[84.37170999999999,25.86879],"type":"Point"}
}