{
  "type": "Feature",
  "properties": {
    "iso:country":"IN",
    "ks:ks_alt_nam":"South tola",
    "ks:ks_name":"South Tola",
    "ks:ks_pop":376,
    "ks:ks_type":"HABITATION",
    "ks:ks_uagg_main":0,
    "name:eng_x_preferred":[
        "South Tola"
    ],
    "wof:name":"South Tola",
    "wof:placetype":"neighbourhood",
    "wof:population":376
},
  "geometry": {"coordinates":[86.740111,24.739153],"type":"Point"}
}