{
  "type": "Feature",
  "properties": {
    "iso:country":"IN",
    "ks:ks_name":"Kaminuaguda",
    "ks:ks_pop":110,
    "ks:ks_type":"HABITATION",
    "name:eng_x_preferred":[
        "Kaminuaguda"
    ],
    "wof:name":"Kaminuaguda",
    "wof:placetype":"locality",
    "wof:population":110
},
  "geometry": {"coordinates":[82.832975,18.932571],"type":"Point"}
}