{
  "type": "Feature",
  "properties": {
    "iso:country":"IN",
    "ks:ks_name":"Ambarde",
    "ks:ks_pop":70,
    "ks:ks_type":"HABITATION",
    "name:eng_x_preferred":[
        "Ambarde"
    ],
    "wof:name":"Ambarde",
    "wof:placetype":"locality",
    "wof:population":70
},
  "geometry": {"coordinates":[74.45252499999999,15.138509],"type":"Point"}
}