{
  "type": "Feature",
  "properties": {
    "gn:admin1_code":"21.0",
    "gn:admin2_code":"387.0",
    "gn:asciiname":"Tinikudi",
    "gn:country_code":"IN",
    "gn:dem":12,
    "gn:feature_class":"P",
    "gn:feature_code":"PPL",
    "gn:name":"Tinikudi",
    "gn:population":0,
    "gn:timezone":"Asia/Kolkata",
    "iso:country":"IN",
    "wof:name":"Tinikudi",
    "wof:placetype":"locality"
},
  "geometry": {"coordinates":[85.69709,19.82992],"type":"Point"}
}