{
  "type": "Feature",
  "properties": {
    "gn:admin1_code":"34.0",
    "gn:admin2_code":"220.0",
    "gn:asciiname":"Parsidhnagar",
    "gn:country_code":"IN",
    "gn:dem":61,
    "gn:feature_class":"P",
    "gn:feature_code":"PPL",
    "gn:name":"Parsidhnagar",
    "gn:population":0,
    "gn:timezone":"Asia/Kolkata",
    "iso:country":"IN",
    "ks:ks_name":"Prasidh Nagar",
    "ks:ks_pop":789,
    "ks:ks_type":"VILLAGE",
    "name:eng_x_preferred":[
        "Prasidh Nagar"
    ],
    "name:eng_x_variant":[
        "Parsidhnagar"
    ],
    "wof:name":"Prasidh Nagar",
    "wof:placetype":"locality",
    "wof:population":789
},
  "geometry": {"coordinates":[85.146618,25.919617],"type":"Point"}
}