{
  "type": "Feature",
  "properties": {
    "gn:admin1_code":"35",
    "gn:admin2_code":"423.0",
    "gn:asciiname":"Bhangarh",
    "gn:country_code":"IN",
    "gn:dem":322,
    "gn:feature_class":"P",
    "gn:feature_code":"PPL",
    "gn:name":"Bh\u0101ngarh",
    "gn:population":0,
    "gn:timezone":"Asia/Kolkata",
    "iso:country":"IN",
    "name:aze_x_preferred":[
        "Bhangarh Rajasthan"
    ],
    "name:ckb_x_preferred":[
        "\u0628\u06d5\u06be\u0627\u0646\u06af\u0627\u0631\u06d5"
    ],
    "name:hin_x_preferred":[
        "\u092d\u093e\u0928\u0917\u0922\u093c"
    ],
    "name:kor_x_preferred":[
        "\ubc18\uac00\ub77c"
    ],
    "name:mal_x_preferred":[
        "\u0d2d\u0d3e\u0d7b\u0d17\u0d7c"
    ],
    "name:pan_x_preferred":[
        "\u0a2d\u0a3e\u0a28\u0a17\u0a5c\u0a4d\u0a39"
    ],
    "name:srp_x_preferred":[
        "\u0411\u0430\u043d\u0433\u0430\u0440"
    ],
    "wof:name":"Bhangarh",
    "wof:placetype":"locality"
},
  "geometry": {"coordinates":[77.75673,25.81945],"type":"Point"}
}