{
  "type": "Feature",
  "properties": {
    "iso:country":"IN",
    "ks:ks_name":"Gadheli",
    "ks:ks_pop":50,
    "ks:ks_type":"VILLAGE",
    "name:eng_x_preferred":[
        "Gadheli"
    ],
    "wof:name":"Gadheli",
    "wof:placetype":"locality",
    "wof:population":50
},
  "geometry": {"coordinates":[80.44913200000001,20.660662],"type":"Point"}
}