{
  "type": "Feature",
  "properties": {
    "iso:country":"IN",
    "ks:ks_name":"Gotgerya",
    "ks:ks_pop":90,
    "ks:ks_type":"VILLAGE",
    "name:eng_x_preferred":[
        "Gotgerya"
    ],
    "wof:name":"Gotgerya",
    "wof:placetype":"locality",
    "wof:population":90
},
  "geometry": {"coordinates":[87.3904,22.197545],"type":"Point"}
}