{
  "type": "Feature",
  "properties": {
    "iso:country":"IN",
    "ks:ks_name":"Sorbatara",
    "ks:ks_pop":0,
    "ks:ks_type":"VILLAGE",
    "name:eng_x_preferred":[
        "Sorbatara"
    ],
    "wof:name":"Sorbatara",
    "wof:placetype":"locality",
    "wof:population":0
},
  "geometry": {"coordinates":[84.16259100000001,25.665641],"type":"Point"}
}