{
  "type": "Feature",
  "properties": {
    "iso:country":"IN",
    "ks:ks_name":"Borhayak Pt I",
    "ks:ks_pop":333,
    "ks:ks_type":"HABITATION",
    "name:eng_x_preferred":[
        "Borhayak Pt I"
    ],
    "wof:name":"Borhayak Pt I",
    "wof:placetype":"locality",
    "wof:population":333
},
  "geometry": {"coordinates":[94.583792,26.835547],"type":"Point"}
}