{
  "type": "Feature",
  "properties": {
    "iso:country":"IN",
    "ks:ks_name":"Kaptanpur Pt IX",
    "ks:ks_pop":948,
    "ks:ks_type":"VILLAGE",
    "name:eng_x_preferred":[
        "Kaptanpur Pt IX"
    ],
    "wof:name":"Kaptanpur Pt IX",
    "wof:placetype":"locality",
    "wof:population":948
},
  "geometry": {"coordinates":[93.001925,24.754272],"type":"Point"}
}