{
  "type": "Feature",
  "properties": {
    "gn:admin1_code":"16.0",
    "gn:admin2_code":"522",
    "gn:asciiname":"Chapadgaon",
    "gn:country_code":"IN",
    "gn:dem":549,
    "gn:feature_class":"P",
    "gn:feature_code":"PPL",
    "gn:name":"Chapadgaon",
    "gn:population":0,
    "gn:timezone":"Asia/Kolkata",
    "iso:country":"IN",
    "wof:name":"Chapadgaon",
    "wof:placetype":"locality"
},
  "geometry": {"coordinates":[75.16138000000002,18.54622],"type":"Point"}
}