{
  "type": "Feature",
  "properties": {
    "gn:admin1_code":"11",
    "gn:admin2_code":"27.0",
    "gn:asciiname":"Chahnoi",
    "gn:country_code":"IN",
    "gn:dem":1047,
    "gn:feature_class":"P",
    "gn:feature_code":"PPL",
    "gn:name":"Ch\u0101hnoi",
    "gn:population":0,
    "gn:timezone":"Asia/Kolkata",
    "iso:country":"IN",
    "wof:name":"Chahnoi",
    "wof:placetype":"locality"
},
  "geometry": {"coordinates":[76.92534000000001,31.5204],"type":"Point"}
}