{
  "type": "Feature",
  "properties": {
    "iso:country":"IN",
    "ks:ks_alt_nam":"WEST KATHE KURHA",
    "ks:ks_name":"West Kathe Kurha",
    "ks:ks_pop":119,
    "ks:ks_type":"HABITATION",
    "name:eng_x_preferred":[
        "West Kathe Kurha"
    ],
    "wof:name":"West Kathe Kurha",
    "wof:placetype":"locality",
    "wof:population":119
},
  "geometry": {"coordinates":[84.80838,25.25276],"type":"Point"}
}