{
  "type": "Feature",
  "properties": {
    "iso:country":"IN",
    "ks:ks_name":"Kadambakudi",
    "ks:ks_pop":95,
    "ks:ks_type":"HABITATION",
    "name:eng_x_preferred":[
        "Kadambakudi"
    ],
    "wof:name":"Kadambakudi",
    "wof:placetype":"locality",
    "wof:population":95
},
  "geometry": {"coordinates":[78.77227600000001,9.792633],"type":"Point"}
}