{
  "type": "Feature",
  "properties": {
    "iso:country":"IN",
    "ks:ks_name":"Rasalpur Bijaygopal",
    "ks:ks_pop":2215,
    "ks:ks_type":"HABITATION",
    "name:eng_x_preferred":[
        "Rasalpur Bijaygopal"
    ],
    "wof:name":"Rasalpur Bijaygopal",
    "wof:placetype":"locality",
    "wof:population":2215
},
  "geometry": {"coordinates":[84.95297600000001,25.608477],"type":"Point"}
}