{
  "type": "Feature",
  "properties": {
    "iso:country":"IN",
    "ks:ks_name":"Balmikpur",
    "ks:ks_pop":41,
    "ks:ks_type":"VILLAGE",
    "name:eng_x_preferred":[
        "Balmikpur"
    ],
    "wof:name":"Balmikpur",
    "wof:placetype":"locality",
    "wof:population":41
},
  "geometry": {"coordinates":[83.96243699999999,25.312679],"type":"Point"}
}