{
  "type": "Feature",
  "properties": {
    "iso:country":"IN",
    "ks:ks_name":"Pallepalem",
    "ks:ks_pop":588,
    "ks:ks_type":"HABITATION",
    "ks:ks_uagg_main":0,
    "name:eng_x_preferred":[
        "Pallepalem"
    ],
    "wof:name":"Pallepalem",
    "wof:placetype":"neighbourhood",
    "wof:population":588
},
  "geometry": {"coordinates":[80.212935,15.583709],"type":"Point"}
}