{
  "type": "Feature",
  "properties": {
    "gn:admin1_code":"2.0",
    "gn:admin2_code":"554.0",
    "gn:asciiname":"Pichikuntlavandlapalli",
    "gn:country_code":"IN",
    "gn:dem":525,
    "gn:feature_class":"P",
    "gn:feature_code":"PPL",
    "gn:name":"Pichikuntlav\u0101ndlapalli",
    "gn:population":0,
    "gn:timezone":"Asia/Kolkata",
    "iso:country":"IN",
    "wof:name":"Pichikuntlavandlapalli",
    "wof:placetype":"neighbourhood"
},
  "geometry": {"coordinates":[79.02804999999999,13.66981],"type":"Point"}
}