{
  "type": "Feature",
  "properties": {
    "iso:country":"IN",
    "ks:ks_name":"Chakmeera",
    "ks:ks_pop":189,
    "ks:ks_type":"HABITATION",
    "name:eng_x_preferred":[
        "Chakmeera"
    ],
    "wof:name":"Chakmeera",
    "wof:placetype":"locality",
    "wof:population":189
},
  "geometry": {"coordinates":[83.50824799999999,25.366294],"type":"Point"}
}