{
  "type": "Feature",
  "properties": {
    "iso:country":"IN",
    "ks:ks_alt_nam":"SENDRIBAHAR",
    "ks:ks_name":"Sendribahar",
    "ks:ks_pop":736,
    "ks:ks_type":"HABITATION",
    "name:eng_x_preferred":[
        "Sendribahar"
    ],
    "wof:name":"Sendribahar",
    "wof:placetype":"locality",
    "wof:population":736
},
  "geometry": {"coordinates":[83.586934,22.563629],"type":"Point"}
}