{
  "type": "Feature",
  "properties": {
    "gn:admin1_code":"16",
    "gn:admin2_code":"510.0",
    "gn:asciiname":"Durgada",
    "gn:country_code":"IN",
    "gn:dem":307,
    "gn:feature_class":"P",
    "gn:feature_code":"PPL",
    "gn:name":"Durg\u0101da",
    "gn:population":0,
    "gn:timezone":"Asia/Kolkata",
    "iso:country":"IN",
    "ks:ks_alt_nam":"Durg\u0101da",
    "ks:ks_name":"Durgada",
    "ks:ks_pop":51,
    "ks:ks_type":"VILLAGE",
    "name:eng_x_preferred":[
        "Durgada"
    ],
    "name:eng_x_variant":[
        "Durg\u0101da"
    ],
    "name:tel_x_preferred":[
        "\u0c26\u0c41\u0c30\u0c4d\u0c17\u0c3e\u0c21"
    ],
    "wof:name":"Durgada",
    "wof:placetype":"locality",
    "wof:population":51
},
  "geometry": {"coordinates":[78.634432,20.067887],"type":"Point"}
}