{
  "type": "Feature",
  "properties": {
    "gn:admin1_code":"16",
    "gn:admin2_code":"510.0",
    "gn:asciiname":"Durgada",
    "gn:country_code":"IN",
    "gn:dem":307,
    "gn:feature_class":"P",
    "gn:feature_code":"PPL",
    "gn:name":"Durg\u0101da",
    "gn:population":0,
    "gn:timezone":"Asia/Kolkata",
    "iso:country":"IN",
    "name:tel_x_preferred":[
        "\u0c26\u0c41\u0c30\u0c4d\u0c17\u0c3e\u0c21"
    ],
    "wof:name":"Durgada",
    "wof:placetype":"locality"
},
  "geometry": {"coordinates":[78.63398000000002,20.06852],"type":"Point"}
}