{
  "type": "Feature",
  "properties": {
    "iso:country":"IN",
    "ks:ks_name":"Badaipara",
    "ks:ks_pop":317,
    "ks:ks_type":"HABITATION",
    "ks:ks_uagg_main":0,
    "name:eng_x_preferred":[
        "Badaipara"
    ],
    "wof:name":"Badaipara",
    "wof:placetype":"neighbourhood",
    "wof:population":317
},
  "geometry": {"coordinates":[81.88247699999999,19.217452],"type":"Point"}
}