{
  "type": "Feature",
  "properties": {
    "iso:country":"IN",
    "ks:ks_name":"Putrabettu",
    "ks:ks_pop":228,
    "ks:ks_type":"HABITATION",
    "name:eng_x_preferred":[
        "Putrabettu"
    ],
    "wof:name":"Putrabettu",
    "wof:placetype":"locality",
    "wof:population":228
},
  "geometry": {"coordinates":[74.82026399999999,13.288055],"type":"Point"}
}