{
  "type": "Feature",
  "properties": {
    "gn:admin1_code":"23",
    "gn:admin2_code":"51.0",
    "gn:asciiname":"Pirthipur",
    "gn:country_code":"IN",
    "gn:dem":284,
    "gn:feature_class":"P",
    "gn:feature_code":"PPL",
    "gn:name":"Pirthipur",
    "gn:population":0,
    "gn:timezone":"Asia/Kolkata",
    "iso:country":"IN",
    "wof:name":"Pirthipur",
    "wof:placetype":"locality"
},
  "geometry": {"coordinates":[76.58103,31.14125],"type":"Point"}
}