{
  "type": "Feature",
  "properties": {
    "gn:admin1_code":"38.0",
    "gn:admin2_code":"347.0",
    "gn:asciiname":"Bamandih",
    "gn:country_code":"IN",
    "gn:dem":423,
    "gn:feature_class":"P",
    "gn:feature_code":"PPL",
    "gn:name":"B\u0101mandih",
    "gn:population":0,
    "gn:timezone":"Asia/Kolkata",
    "iso:country":"IN",
    "ks:ks_name":"Bamandiha",
    "ks:ks_pop":249,
    "ks:ks_type":"VILLAGE",
    "name:eng_x_preferred":[
        "Bamandiha"
    ],
    "name:eng_x_variant":[
        "Bamandih"
    ],
    "wof:name":"Bamandiha",
    "wof:placetype":"locality",
    "wof:population":249
},
  "geometry": {"coordinates":[85.19576000000001,24.278478],"type":"Point"}
}