{
  "type": "Feature",
  "properties": {
    "iso:country":"IN",
    "ks:ks_name":"Darghai",
    "ks:ks_pop":35,
    "ks:ks_type":"HABITATION",
    "name:eng_x_preferred":[
        "Darghai"
    ],
    "wof:name":"Darghai",
    "wof:placetype":"locality",
    "wof:population":35
},
  "geometry": {"coordinates":[86.613303,22.199406],"type":"Point"}
}