{
  "type": "Feature",
  "properties": {
    "gn:admin1_code":"13.0",
    "gn:admin2_code":"595.0",
    "gn:asciiname":"Moothakunnam",
    "gn:country_code":"IN",
    "gn:dem":12,
    "gn:feature_class":"P",
    "gn:feature_code":"PPL",
    "gn:name":"Moothakunnam",
    "gn:population":0,
    "gn:timezone":"Asia/Kolkata",
    "iso:country":"IN",
    "name:mal_x_preferred":[
        "\u0d2e\u0d42\u0d24\u0d4d\u0d24\u0d15\u0d41\u0d28\u0d4d\u0d28\u0d02"
    ],
    "wof:name":"Moothakunnam",
    "wof:placetype":"locality"
},
  "geometry": {"coordinates":[76.20079,10.18995],"type":"Point"}
}