{
  "type": "Feature",
  "properties": {
    "gn:admin1_code":"35.0",
    "gn:admin2_code":"442.0",
    "gn:asciiname":"Jharkariakheri",
    "gn:country_code":"IN",
    "gn:dem":415,
    "gn:feature_class":"P",
    "gn:feature_code":"PPL",
    "gn:name":"Jhark\u0101ri\u0101kheri",
    "gn:population":0,
    "gn:timezone":"Asia/Kolkata",
    "iso:country":"IN",
    "wof:name":"Jharkariakheri",
    "wof:placetype":"neighbourhood"
},
  "geometry": {"coordinates":[76.87693,23.81426],"type":"Point"}
}