{
  "type": "Feature",
  "properties": {
    "iso:country":"IN",
    "ks:ks_name":"Lohasihana",
    "ks:ks_pop":87,
    "ks:ks_type":"HABITATION",
    "name:eng_x_preferred":[
        "Lohasihana"
    ],
    "wof:name":"Lohasihana",
    "wof:placetype":"locality",
    "wof:population":87
},
  "geometry": {"coordinates":[84.48122499999999,24.316217],"type":"Point"}
}