{
  "type": "Feature",
  "properties": {
    "gn:admin1_code":"34.0",
    "gn:admin2_code":"238.0",
    "gn:asciiname":"Khojdih",
    "gn:country_code":"IN",
    "gn:dem":70,
    "gn:feature_class":"P",
    "gn:feature_code":"PPL",
    "gn:name":"Khojdih",
    "gn:population":0,
    "gn:timezone":"Asia/Kolkata",
    "iso:country":"IN",
    "wof:name":"Khojdih",
    "wof:placetype":"locality"
},
  "geometry": {"coordinates":[86.10148000000002,24.95991],"type":"Point"}
}