{
  "type": "Feature",
  "properties": {
    "gn:admin1_code":"2.0",
    "gn:asciiname":"Panasagadda",
    "gn:country_code":"IN",
    "gn:dem":328,
    "gn:feature_class":"P",
    "gn:feature_code":"PPL",
    "gn:name":"Panasagadda",
    "gn:population":0,
    "gn:timezone":"Asia/Kolkata",
    "iso:country":"IN",
    "ks:ks_name":"Panasagedda",
    "ks:ks_pop":61,
    "ks:ks_type":"HABITATION",
    "name:eng_x_preferred":[
        "Panasagedda"
    ],
    "name:eng_x_variant":[
        "Panasagadda"
    ],
    "wof:name":"Panasagedda",
    "wof:placetype":"locality",
    "wof:population":61
},
  "geometry": {"coordinates":[83.141903,18.680319],"type":"Point"}
}