{
  "type": "Feature",
  "properties": {
    "iso:country":"IN",
    "ks:ks_name":"Gurramvandlapalli",
    "ks:ks_pop":56,
    "ks:ks_type":"HABITATION",
    "name:eng_x_preferred":[
        "Gurramvandlapalli"
    ],
    "wof:name":"Gurramvandlapalli",
    "wof:placetype":"locality",
    "wof:population":56
},
  "geometry": {"coordinates":[78.531193,14.075007],"type":"Point"}
}