{
  "type": "Feature",
  "properties": {
    "iso:country":"IN",
    "ks:ks_name":"Bera",
    "ks:ks_pop":0,
    "ks:ks_type":"VILLAGE",
    "name:eng_x_preferred":[
        "Bera"
    ],
    "wof:name":"Bera",
    "wof:placetype":"locality",
    "wof:population":0
},
  "geometry": {"coordinates":[88.150206,23.612124],"type":"Point"}
}