{
  "type": "Feature",
  "properties": {
    "iso:country":"IN",
    "ks:ks_name":"Chauinnriguda",
    "ks:ks_pop":253,
    "ks:ks_type":"HABITATION",
    "name:eng_x_preferred":[
        "Chauinnriguda"
    ],
    "wof:name":"Chauinnriguda",
    "wof:placetype":"locality",
    "wof:population":253
},
  "geometry": {"coordinates":[82.35901800000001,19.778801],"type":"Point"}
}