{
  "type": "Feature",
  "properties": {
    "iso:country":"IN",
    "ks:ks_name":"Borthva",
    "ks:ks_pop":609,
    "ks:ks_type":"HABITATION",
    "name:eng_x_preferred":[
        "Borthva"
    ],
    "wof:name":"Borthva",
    "wof:placetype":"locality",
    "wof:population":609
},
  "geometry": {"coordinates":[73.88038899999999,20.964972],"type":"Point"}
}