{
  "type": "Feature",
  "properties": {
    "iso:country":"IN",
    "ks:ks_name":"Dolabari No 1 Gha",
    "ks:ks_pop":1525,
    "ks:ks_type":"HABITATION",
    "ks:ks_uagg_main":0,
    "name:eng_x_preferred":[
        "Dolabari No 1 Gha"
    ],
    "wof:name":"Dolabari No 1 Gha",
    "wof:placetype":"locality",
    "wof:population":1525
},
  "geometry": {"coordinates":[92.81192799999999,26.641821],"type":"Point"}
}