{
  "type": "Feature",
  "properties": {
    "gn:admin1_code":"36.0",
    "gn:admin2_code":"134.0",
    "gn:asciiname":"Nawagaon",
    "gn:country_code":"IN",
    "gn:dem":246,
    "gn:feature_class":"P",
    "gn:feature_code":"PPL",
    "gn:name":"Naw\u0101gaon",
    "gn:population":0,
    "gn:timezone":"Asia/Kolkata",
    "iso:country":"IN",
    "ks:ks_alt_nam":"Naw\u0101gaon",
    "ks:ks_name":"Nawagaon",
    "ks:ks_type":"VILLAGE",
    "name:eng_x_preferred":[
        "Nawagaon"
    ],
    "name:eng_x_variant":[
        "Naw\u0101gaon"
    ],
    "wof:name":"Nawagaon",
    "wof:placetype":"locality"
},
  "geometry": {"coordinates":[78.205823,29.557447],"type":"Point"}
}