{
  "type": "Feature",
  "properties": {
    "iso:country":"IN",
    "ks:ks_name":"Bhangamunda",
    "ks:ks_pop":405,
    "ks:ks_type":"VILLAGE",
    "name:eng_x_preferred":[
        "Bhangamunda"
    ],
    "wof:name":"Bhangamunda",
    "wof:placetype":"locality",
    "wof:population":405
},
  "geometry": {"coordinates":[84.472804,21.023646],"type":"Point"}
}