{
  "type": "Feature",
  "properties": {
    "iso:country":"IN",
    "ks:ks_name":"Kothaguda",
    "ks:ks_pop":109,
    "ks:ks_type":"HABITATION",
    "name:eng_x_preferred":[
        "Kothaguda"
    ],
    "wof:name":"Kothaguda",
    "wof:placetype":"locality",
    "wof:population":109
},
  "geometry": {"coordinates":[78.823663,19.287062],"type":"Point"}
}