{
  "type": "Feature",
  "properties": {
    "gn:admin1_code":"21.0",
    "gn:admin2_code":"389.0",
    "gn:asciiname":"Mariguda",
    "gn:country_code":"IN",
    "gn:dem":129,
    "gn:feature_class":"P",
    "gn:feature_code":"PPL",
    "gn:name":"Marig\u016bda",
    "gn:population":0,
    "gn:timezone":"Asia/Kolkata",
    "iso:country":"IN",
    "wof:name":"Mariguda",
    "wof:placetype":"locality"
},
  "geometry": {"coordinates":[83.88453,18.89799],"type":"Point"}
}