{
  "type": "Feature",
  "properties": {
    "iso:country":"IN",
    "ks:ks_name":"Kondru",
    "ks:ks_pop":211,
    "ks:ks_type":"HABITATION",
    "name:eng_x_preferred":[
        "Kondru"
    ],
    "wof:name":"Kondru",
    "wof:placetype":"locality",
    "wof:population":211
},
  "geometry": {"coordinates":[82.366173,18.166582],"type":"Point"}
}