{
  "type": "Feature",
  "properties": {
    "iso:country":"IN",
    "ks:ks_name":"Shrinagar",
    "ks:ks_pop":368,
    "ks:ks_type":"VILLAGE",
    "name:eng_x_preferred":[
        "Shrinagar"
    ],
    "wof:name":"Shrinagar",
    "wof:placetype":"locality",
    "wof:population":368
},
  "geometry": {"coordinates":[80.525593,28.400534],"type":"Point"}
}