{
  "type": "Feature",
  "properties": {
    "iso:country":"IN",
    "ks:ks_name":"Deuli",
    "ks:ks_pop":768,
    "ks:ks_type":"VILLAGE",
    "name:eng_x_preferred":[
        "Deuli"
    ],
    "wof:name":"Deuli",
    "wof:placetype":"locality",
    "wof:population":768
},
  "geometry": {"coordinates":[87.389832,22.880333],"type":"Point"}
}