{
  "type": "Feature",
  "properties": {
    "iso:country":"IN",
    "ks:ks_alt_nam":"CHABANIA",
    "ks:ks_name":"Chabania",
    "ks:ks_pop":761,
    "ks:ks_type":"HABITATION",
    "name:eng_x_preferred":[
        "Chabania"
    ],
    "wof:name":"Chabania",
    "wof:placetype":"locality",
    "wof:population":761
},
  "geometry": {"coordinates":[85.23679,23.933445],"type":"Point"}
}