{
  "type": "Feature",
  "properties": {
    "gn:admin1_code":"36.0",
    "gn:admin2_code":"182.0",
    "gn:asciiname":"Chai Dih",
    "gn:country_code":"IN",
    "gn:dem":100,
    "gn:feature_class":"P",
    "gn:feature_code":"PPL",
    "gn:name":"Ch\u0101i D\u012bh",
    "gn:population":0,
    "gn:timezone":"Asia/Kolkata",
    "iso:country":"IN",
    "ks:ks_alt_nam":"Ch\u0101i D\u012bh",
    "ks:ks_name":"Chai Dih",
    "ks:ks_type":"VILLAGE",
    "ks:ks_uagg_main":0,
    "name:eng_x_preferred":[
        "Chai Dih"
    ],
    "name:eng_x_variant":[
        "Ch\u0101i D\u012bh"
    ],
    "wof:name":"Chai Dih",
    "wof:placetype":"neighbourhood"
},
  "geometry": {"coordinates":[82.481871,27.30369],"type":"Point"}
}