{
  "type": "Feature",
  "properties": {
    "iso:country":"IN",
    "ks:ks_name":"Tandola",
    "ks:ks_type":"VILLAGE",
    "name:eng_x_preferred":[
        "Tandola"
    ],
    "wof:name":"Tandola",
    "wof:placetype":"locality"
},
  "geometry": {"coordinates":[78.99645,29.969981],"type":"Point"}
}