{
  "type": "Feature",
  "properties": {
    "iso:country":"IN",
    "ks:ks_name":"Kharadipada",
    "ks:ks_pop":235,
    "ks:ks_type":"HABITATION",
    "ks:ks_uagg_main":0,
    "name:eng_x_preferred":[
        "Kharadipada"
    ],
    "wof:name":"Kharadipada",
    "wof:placetype":"neighbourhood",
    "wof:population":235
},
  "geometry": {"coordinates":[73.547235,20.141568],"type":"Point"}
}