{
  "type": "Feature",
  "properties": {
    "gn:admin1_code":"25.0",
    "gn:admin2_code":"620.0",
    "gn:asciiname":"Vadakku Mulangudi",
    "gn:country_code":"IN",
    "gn:dem":27,
    "gn:feature_class":"P",
    "gn:feature_code":"PPL",
    "gn:name":"Vadakku M\u016blangudi",
    "gn:population":0,
    "gn:timezone":"Asia/Kolkata",
    "iso:country":"IN",
    "wof:name":"Vadakku Mulangudi",
    "wof:placetype":"neighbourhood"
},
  "geometry": {"coordinates":[79.47286,10.97707],"type":"Point"}
}