{
  "type": "Feature",
  "properties": {
    "iso:country":"IN",
    "ks:ks_name":"Pallakollai",
    "ks:ks_pop":468,
    "ks:ks_type":"HABITATION",
    "name:eng_x_preferred":[
        "Pallakollai"
    ],
    "wof:name":"Pallakollai",
    "wof:placetype":"locality",
    "wof:population":468
},
  "geometry": {"coordinates":[79.024006,13.035277],"type":"Point"}
}