{
  "type": "Feature",
  "properties": {
    "iso:country":"IN",
    "ks:ks_name":"Paschim Godkhali",
    "ks:ks_pop":952,
    "ks:ks_type":"HABITATION",
    "name:eng_x_preferred":[
        "Paschim Godkhali"
    ],
    "wof:name":"Paschim Godkhali",
    "wof:placetype":"locality",
    "wof:population":952
},
  "geometry": {"coordinates":[88.764168,22.16171],"type":"Point"}
}