{
  "type": "Feature",
  "properties": {
    "iso:country":"IN",
    "ks:ks_name":"Moti Sheri",
    "ks:ks_pop":165,
    "ks:ks_type":"HABITATION",
    "name:eng_x_preferred":[
        "Moti Sheri"
    ],
    "wof:name":"Moti Sheri",
    "wof:placetype":"locality",
    "wof:population":165
},
  "geometry": {"coordinates":[73.3655,20.313111],"type":"Point"}
}