{
  "type": "Feature",
  "properties": {
    "gn:admin1_code":"2",
    "gn:admin2_code":"545.0",
    "gn:asciiname":"Bhupatipalem",
    "gn:country_code":"IN",
    "gn:dem":186,
    "gn:feature_class":"P",
    "gn:feature_code":"PPL",
    "gn:name":"Bh\u016bpatip\u0101lem",
    "gn:population":0,
    "gn:timezone":"Asia/Kolkata",
    "iso:country":"IN",
    "ks:ks_name":"Bhupathipalem",
    "ks:ks_pop":46,
    "ks:ks_type":"HABITATION",
    "name:eng_x_preferred":[
        "Bhupathipalem"
    ],
    "name:eng_x_variant":[
        "Bhupatipalem"
    ],
    "wof:name":"Bhupathipalem",
    "wof:placetype":"locality",
    "wof:population":46
},
  "geometry": {"coordinates":[81.76316300000001,17.448332],"type":"Point"}
}