{
  "type": "Feature",
  "properties": {
    "gn:admin1_code":"11",
    "gn:admin2_code":"32.0",
    "gn:asciiname":"Nanwa Khil",
    "gn:country_code":"IN",
    "gn:dem":2211,
    "gn:feature_class":"P",
    "gn:feature_code":"PPL",
    "gn:name":"Nanwa Khil",
    "gn:population":0,
    "gn:timezone":"Asia/Kolkata",
    "iso:country":"IN",
    "wof:name":"Nanwa Khil",
    "wof:placetype":"locality"
},
  "geometry": {"coordinates":[77.50650999999998,30.78227],"type":"Point"}
}