{
  "type": "Feature",
  "properties": {
    "gn:admin1_code":"36.0",
    "gn:admin2_code":"176.0",
    "gn:asciiname":"Bhulbhuliapur",
    "gn:country_code":"IN",
    "gn:dem":107,
    "gn:feature_class":"P",
    "gn:feature_code":"PPL",
    "gn:name":"Bhulbhuli\u0101pur",
    "gn:population":0,
    "gn:timezone":"Asia/Kolkata",
    "iso:country":"IN",
    "wof:name":"Bhulbhuliapur",
    "wof:placetype":"locality"
},
  "geometry": {"coordinates":[81.50423000000001,27.03344],"type":"Point"}
}