{
  "type": "Feature",
  "properties": {
    "iso:country":"IN",
    "ks:ks_name":"Tedhera Pathar",
    "ks:ks_pop":1088,
    "ks:ks_type":"VILLAGE",
    "ks:ks_uagg_main":0,
    "name:eng_x_preferred":[
        "Tedhera Pathar"
    ],
    "wof:name":"Tedhera Pathar",
    "wof:placetype":"neighbourhood",
    "wof:population":1088
},
  "geometry": {"coordinates":[90.947253,26.244055],"type":"Point"}
}