{
  "type": "Feature",
  "properties": {
    "gn:admin1_code":"35",
    "gn:admin2_code":"460.0",
    "gn:asciiname":"Chintimar",
    "gn:country_code":"IN",
    "gn:dem":355,
    "gn:feature_class":"P",
    "gn:feature_code":"PPL",
    "gn:name":"Ch\u012bnt\u012bm\u0101r",
    "gn:population":0,
    "gn:timezone":"Asia/Kolkata",
    "iso:country":"IN",
    "wof:name":"Chintimar",
    "wof:placetype":"locality"
},
  "geometry": {"coordinates":[81.51170999999999,24.05648],"type":"Point"}
}