{
  "type": "Feature",
  "properties": {
    "iso:country":"IN",
    "ks:ks_name":"Salempur",
    "ks:ks_pop":418,
    "ks:ks_type":"HABITATION",
    "ks:ks_uagg_main":0,
    "name:eng_x_preferred":[
        "Salempur"
    ],
    "wof:name":"Salempur",
    "wof:placetype":"neighbourhood",
    "wof:population":418
},
  "geometry": {"coordinates":[78.14993800000001,29.57506],"type":"Point"}
}