{
  "type": "Feature",
  "properties": {
    "iso:country":"IN",
    "ks:ks_name":"Pipri",
    "ks:ks_pop":365,
    "ks:ks_type":"VILLAGE",
    "name:eng_x_preferred":[
        "Pipri"
    ],
    "wof:name":"Pipri",
    "wof:placetype":"locality",
    "wof:population":365
},
  "geometry": {"coordinates":[82.944593,27.34952],"type":"Point"}
}