{
  "type": "Feature",
  "properties": {
    "iso:country":"IN",
    "ks:ks_name":"Konemane",
    "ks:ks_pop":13,
    "ks:ks_type":"HABITATION",
    "name:eng_x_preferred":[
        "Konemane"
    ],
    "wof:name":"Konemane",
    "wof:placetype":"locality",
    "wof:population":13
},
  "geometry": {"coordinates":[74.601997,14.927279],"type":"Point"}
}