{
  "type": "Feature",
  "properties": {
    "iso:country":"IN",
    "ks:ks_alt_nam":"BAMNIA",
    "ks:ks_name":"Bamnia",
    "ks:ks_pop":1022,
    "ks:ks_type":"HABITATION",
    "name:eng_x_preferred":[
        "Bamnia"
    ],
    "wof:name":"Bamnia",
    "wof:placetype":"locality",
    "wof:population":1022
},
  "geometry": {"coordinates":[89.748865,26.482443],"type":"Point"}
}