{
  "type": "Feature",
  "properties": {
    "iso:country":"IN",
    "ks:ks_name":"Panva",
    "ks:ks_pop":1255,
    "ks:ks_type":"VILLAGE",
    "name:eng_x_preferred":[
        "Panva"
    ],
    "wof:name":"Panva",
    "wof:placetype":"locality",
    "wof:population":1255
},
  "geometry": {"coordinates":[73.270326,20.474874],"type":"Point"}
}