{
  "type": "Feature",
  "properties": {
    "gn:admin1_code":"19.0",
    "gn:admin2_code":"574.0",
    "gn:asciiname":"Dindagur",
    "gn:country_code":"IN",
    "gn:dem":857,
    "gn:feature_class":"P",
    "gn:feature_code":"PPL",
    "gn:name":"Dindag\u016br",
    "gn:population":0,
    "gn:timezone":"Asia/Kolkata",
    "iso:country":"IN",
    "wof:name":"Dindagur",
    "wof:placetype":"locality"
},
  "geometry": {"coordinates":[76.42440999999999,12.9323],"type":"Point"}
}