{
  "type": "Feature",
  "properties": {
    "iso:country":"IN",
    "ks:ks_name":"Palchha",
    "ks:ks_pop":93,
    "ks:ks_type":"VILLAGE",
    "name:eng_x_preferred":[
        "Palchha"
    ],
    "wof:name":"Palchha",
    "wof:placetype":"locality",
    "wof:population":93
},
  "geometry": {"coordinates":[75.049644,24.818967],"type":"Point"}
}