{
  "type": "Feature",
  "properties": {
    "iso:country":"IN",
    "ks:ks_alt_nam":"WEST SUPAULY",
    "ks:ks_name":"West Supauly",
    "ks:ks_pop":229,
    "ks:ks_type":"HABITATION",
    "name:eng_x_preferred":[
        "West Supauly"
    ],
    "wof:name":"West Supauly",
    "wof:placetype":"locality",
    "wof:population":229
},
  "geometry": {"coordinates":[84.662942,26.389399],"type":"Point"}
}