{
  "type": "Feature",
  "properties": {
    "gn:admin1_code":"11",
    "gn:admin2_code":"27.0",
    "gn:asciiname":"Ghagtian",
    "gn:country_code":"IN",
    "gn:dem":1628,
    "gn:feature_class":"P",
    "gn:feature_code":"PPL",
    "gn:name":"Ghagti\u0101n",
    "gn:population":0,
    "gn:timezone":"Asia/Kolkata",
    "iso:country":"IN",
    "wof:name":"Ghagtian",
    "wof:placetype":"locality"
},
  "geometry": {"coordinates":[76.9282,31.93618],"type":"Point"}
}