{
  "type": "Feature",
  "properties": {
    "iso:country":"IN",
    "ks:ks_name":"Bhaluksoth",
    "ks:ks_pop":77,
    "ks:ks_type":"HABITATION",
    "name:eng_x_preferred":[
        "Bhaluksoth"
    ],
    "wof:name":"Bhaluksoth",
    "wof:placetype":"locality",
    "wof:population":77
},
  "geometry": {"coordinates":[86.997681,22.597123],"type":"Point"}
}