{
  "type": "Feature",
  "properties": {
    "gn:admin1_code":"36.0",
    "gn:admin2_code":"202",
    "gn:asciiname":"Jijaul",
    "gn:country_code":"IN",
    "gn:dem":157,
    "gn:feature_class":"P",
    "gn:feature_code":"PPL",
    "gn:name":"Jijaul",
    "gn:population":0,
    "gn:timezone":"Asia/Kolkata",
    "iso:country":"IN",
    "wof:name":"Jijaul",
    "wof:placetype":"locality"
},
  "geometry": {"coordinates":[79.12307,27.81382],"type":"Point"}
}