{
  "type": "Feature",
  "properties": {
    "iso:country":"IN",
    "ks:ks_name":"Nani Jaduli",
    "ks:ks_pop":369,
    "ks:ks_type":"VILLAGE",
    "name:eng_x_preferred":[
        "Nani Jaduli"
    ],
    "wof:name":"Nani Jaduli",
    "wof:placetype":"locality",
    "wof:population":369
},
  "geometry": {"coordinates":[73.958243,21.990451],"type":"Point"}
}