{
  "type": "Feature",
  "properties": {
    "gn:admin1_code":"11",
    "gn:admin2_code":"23.0",
    "gn:asciiname":"Salga",
    "gn:country_code":"IN",
    "gn:dem":920,
    "gn:feature_class":"P",
    "gn:feature_code":"PPL",
    "gn:name":"S\u0101lga",
    "gn:population":0,
    "gn:timezone":"Asia/Kolkata",
    "iso:country":"IN",
    "name:ceb_x_preferred":[
        "Salga"
    ],
    "name:deu_x_preferred":[
        "Salga"
    ],
    "name:msa_x_preferred":[
        "Salga"
    ],
    "name:por_x_preferred":[
        "Salga"
    ],
    "name:rus_x_preferred":[
        "\u0421\u0430\u043b\u0433\u0430"
    ],
    "name:spa_x_preferred":[
        "Salga"
    ],
    "wof:name":"Salga",
    "wof:placetype":"locality"
},
  "geometry": {"coordinates":[76.07217,32.60479],"type":"Point"}
}