{
  "type": "Feature",
  "properties": {
    "iso:country":"IN",
    "ks:ks_name":"Kamarajapuram",
    "ks:ks_pop":280,
    "ks:ks_type":"HABITATION",
    "name:eng_x_preferred":[
        "Kamarajapuram"
    ],
    "wof:name":"Kamarajapuram",
    "wof:placetype":"locality",
    "wof:population":280
},
  "geometry": {"coordinates":[78.770805,10.875933],"type":"Point"}
}