{
  "type": "Feature",
  "properties": {
    "gn:admin1_code":"37",
    "gn:admin2_code":"404.0",
    "gn:asciiname":"Chatuabhauna",
    "gn:country_code":"IN",
    "gn:dem":356,
    "gn:feature_class":"P",
    "gn:feature_code":"PPL",
    "gn:name":"Chatu\u0101bhaun\u0101",
    "gn:population":0,
    "gn:timezone":"Asia/Kolkata",
    "iso:country":"IN",
    "ks:ks_name":"Chatuabhawana",
    "ks:ks_pop":567,
    "ks:ks_type":"HABITATION",
    "name:eng_x_preferred":[
        "Chatuabhawana"
    ],
    "name:eng_x_variant":[
        "Chatuabhauna"
    ],
    "wof:name":"Chatuabhawana",
    "wof:placetype":"locality",
    "wof:population":567
},
  "geometry": {"coordinates":[82.392437,22.408383],"type":"Point"}
}