{
  "type": "Feature",
  "properties": {
    "iso:country":"IN",
    "ks:ks_name":"Bandagal",
    "ks:ks_pop":0,
    "ks:ks_type":"VILLAGE",
    "name:eng_x_preferred":[
        "Bandagal"
    ],
    "wof:name":"Bandagal",
    "wof:placetype":"locality",
    "wof:population":0
},
  "geometry": {"coordinates":[87.250157,23.858668],"type":"Point"}
}