{
  "type": "Feature",
  "properties": {
    "iso:country":"IN",
    "ks:ks_alt_nam":"Valluvar theru",
    "ks:ks_name":"Valluvar Theru",
    "ks:ks_pop":250,
    "ks:ks_type":"HABITATION",
    "name:eng_x_preferred":[
        "Valluvar Theru"
    ],
    "wof:name":"Valluvar Theru",
    "wof:placetype":"locality",
    "wof:population":250
},
  "geometry": {"coordinates":[77.866691,11.423992],"type":"Point"}
}