{
  "type": "Feature",
  "properties": {
    "iso:country":"IN",
    "ks:ks_name":"Thannimani",
    "ks:ks_pop":945,
    "ks:ks_type":"VILLAGE",
    "name:eng_x_preferred":[
        "Thannimani"
    ],
    "wof:name":"Thannimani",
    "wof:placetype":"locality",
    "wof:population":945
},
  "geometry": {"coordinates":[75.519412,12.395661],"type":"Point"}
}