{
  "type": "Feature",
  "properties": {
    "iso:country":"IN",
    "ks:ks_name":"Chawa",
    "ks:ks_pop":14,
    "ks:ks_type":"VILLAGE",
    "name:eng_x_preferred":[
        "Chawa"
    ],
    "wof:name":"Chawa",
    "wof:placetype":"locality",
    "wof:population":14
},
  "geometry": {"coordinates":[70.98808,25.827805],"type":"Point"}
}