{
  "type": "Feature",
  "properties": {
    "iso:country":"IN",
    "ks:ks_name":"Khairi Tola",
    "ks:ks_pop":332,
    "ks:ks_type":"HABITATION",
    "name:eng_x_preferred":[
        "Khairi Tola"
    ],
    "wof:name":"Khairi Tola",
    "wof:placetype":"locality",
    "wof:population":332
},
  "geometry": {"coordinates":[82.905337,24.287028],"type":"Point"}
}