{
  "type": "Feature",
  "properties": {
    "iso:country":"IN",
    "ks:ks_name":"Kaily Khurd",
    "ks:ks_pop":399,
    "ks:ks_type":"VILLAGE",
    "ks:ks_uagg_main":0,
    "name:eng_x_preferred":[
        "Kaily Khurd"
    ],
    "wof:name":"Kaily Khurd",
    "wof:placetype":"neighbourhood",
    "wof:population":399
},
  "geometry": {"coordinates":[75.299498,31.9931],"type":"Point"}
}