{
  "type": "Feature",
  "properties": {
    "iso:country":"IN",
    "ks:ks_name":"Kaaranji",
    "ks:ks_pop":37,
    "ks:ks_type":"HABITATION",
    "name:eng_x_preferred":[
        "Kaaranji"
    ],
    "wof:name":"Kaaranji",
    "wof:placetype":"locality",
    "wof:population":37
},
  "geometry": {"coordinates":[75.271879,13.576325],"type":"Point"}
}