{
  "type": "Feature",
  "properties": {
    "iso:country":"IN",
    "ks:ks_alt_nam":"KAMAT TOLA",
    "ks:ks_name":"Kamat Tola",
    "ks:ks_pop":236,
    "ks:ks_type":"HABITATION",
    "ks:ks_uagg_main":0,
    "name:eng_x_preferred":[
        "Kamat Tola"
    ],
    "wof:name":"Kamat Tola",
    "wof:placetype":"neighbourhood",
    "wof:population":236
},
  "geometry": {"coordinates":[87.571056,25.695177],"type":"Point"}
}