{
  "type": "Feature",
  "properties": {
    "iso:country":"IN",
    "ks:ks_name":"Alampur Chak Sultan",
    "ks:ks_pop":0,
    "ks:ks_type":"VILLAGE",
    "name:eng_x_preferred":[
        "Alampur Chak Sultan"
    ],
    "wof:name":"Alampur Chak Sultan",
    "wof:placetype":"locality",
    "wof:population":0
},
  "geometry": {"coordinates":[85.798051,25.63055],"type":"Point"}
}