{
  "type": "Feature",
  "properties": {
    "iso:country":"IN",
    "ks:ks_name":"Maripur Mal",
    "ks:ks_pop":2656,
    "ks:ks_type":"VILLAGE",
    "ks:ks_uagg_main":0,
    "name:eng_x_preferred":[
        "Maripur Mal"
    ],
    "wof:name":"Maripur Mal",
    "wof:placetype":"neighbourhood",
    "wof:population":2656
},
  "geometry": {"coordinates":[85.085004,26.407968],"type":"Point"}
}