{
  "type": "Feature",
  "properties": {
    "gn:admin1_code":"35",
    "gn:admin2_code":"458.0",
    "gn:asciiname":"Mahuakhera",
    "gn:country_code":"IN",
    "gn:dem":530,
    "gn:feature_class":"P",
    "gn:feature_code":"PPL",
    "gn:name":"Mahu\u0101khera",
    "gn:population":0,
    "gn:timezone":"Asia/Kolkata",
    "iso:country":"IN",
    "wof:name":"Mahuakhera",
    "wof:placetype":"locality"
},
  "geometry": {"coordinates":[77.60639,24.30566],"type":"Point"}
}