{
  "type": "Feature",
  "properties": {
    "iso:country":"IN",
    "ks:ks_alt_nam":"Panchavadi pachakadu",
    "ks:ks_name":"Panchavadi Pachakadu",
    "ks:ks_pop":880,
    "ks:ks_type":"HABITATION",
    "name:eng_x_preferred":[
        "Panchavadi Pachakadu"
    ],
    "wof:name":"Panchavadi Pachakadu",
    "wof:placetype":"locality",
    "wof:population":880
},
  "geometry": {"coordinates":[76.04522299999999,11.311284],"type":"Point"}
}