{
  "type": "Feature",
  "properties": {
    "gn:admin1_code":"11",
    "gn:admin2_code":"23.0",
    "gn:asciiname":"Manjoi",
    "gn:country_code":"IN",
    "gn:dem":2256,
    "gn:feature_class":"P",
    "gn:feature_code":"PPL",
    "gn:name":"Manjoi",
    "gn:population":0,
    "gn:timezone":"Asia/Kolkata",
    "iso:country":"IN",
    "wof:name":"Manjoi",
    "wof:placetype":"locality"
},
  "geometry": {"coordinates":[76.21465999999999,32.84689],"type":"Point"}
}