{
  "type": "Feature",
  "properties": {
    "iso:country":"IN",
    "ks:ks_name":"Deoriya Iema",
    "ks:ks_pop":206,
    "ks:ks_type":"VILLAGE",
    "name:eng_x_preferred":[
        "Deoriya Iema"
    ],
    "wof:name":"Deoriya Iema",
    "wof:placetype":"locality",
    "wof:population":206
},
  "geometry": {"coordinates":[83.298299,26.021085],"type":"Point"}
}