{
  "type": "Feature",
  "properties": {
    "iso:country":"IN",
    "ks:ks_name":"Chintapentagudem",
    "ks:ks_pop":107,
    "ks:ks_type":"HABITATION",
    "name:eng_x_preferred":[
        "Chintapentagudem"
    ],
    "wof:name":"Chintapentagudem",
    "wof:placetype":"locality",
    "wof:population":107
},
  "geometry": {"coordinates":[80.60235400000001,17.773369],"type":"Point"}
}