{
  "type": "Feature",
  "properties": {
    "gn:admin1_code":"40",
    "gn:admin2_code":"533.0",
    "gn:asciiname":"Awalgaon",
    "gn:country_code":"IN",
    "gn:dem":399,
    "gn:feature_class":"P",
    "gn:feature_code":"PPL",
    "gn:name":"\u0100walgaon",
    "gn:population":0,
    "gn:timezone":"Asia/Kolkata",
    "iso:country":"IN",
    "wof:name":"Awalgaon",
    "wof:placetype":"locality"
},
  "geometry": {"coordinates":[77.62014000000001,18.47826],"type":"Point"}
}