{
  "type": "Feature",
  "properties": {
    "gn:admin1_code":"19.0",
    "gn:admin2_code":"566.0",
    "gn:asciiname":"Matada Jogihalli",
    "gn:country_code":"IN",
    "gn:dem":559,
    "gn:feature_class":"P",
    "gn:feature_code":"PPL",
    "gn:name":"Matada Jogihalli",
    "gn:population":0,
    "gn:timezone":"Asia/Kolkata",
    "iso:country":"IN",
    "wof:name":"Matada Jogihalli",
    "wof:placetype":"locality"
},
  "geometry": {"coordinates":[76.65286,14.73468],"type":"Point"}
}