{
  "type": "Feature",
  "properties": {
    "gn:admin1_code":"19.0",
    "gn:admin2_code":"566.0",
    "gn:asciiname":"Matada Jogihalli",
    "gn:country_code":"IN",
    "gn:dem":559,
    "gn:feature_class":"P",
    "gn:feature_code":"PPL",
    "gn:name":"Matada Jogihalli",
    "gn:population":0,
    "gn:timezone":"Asia/Kolkata",
    "iso:country":"IN",
    "ks:ks_name":"Matadajogihalli",
    "ks:ks_pop":34,
    "ks:ks_type":"VILLAGE",
    "name:eng_x_preferred":[
        "Matadajogihalli"
    ],
    "name:eng_x_variant":[
        "Matada Jogihalli"
    ],
    "wof:name":"Matadajogihalli",
    "wof:placetype":"locality",
    "wof:population":34
},
  "geometry": {"coordinates":[76.65682099999999,14.742131],"type":"Point"}
}