{
  "type": "Feature",
  "properties": {
    "iso:country":"IN",
    "ks:ks_name":"Tokelguda.",
    "ks:ks_pop":309,
    "ks:ks_type":"HABITATION",
    "name:eng_x_preferred":[
        "Tokelguda."
    ],
    "wof:name":"Tokelguda.",
    "wof:placetype":"locality",
    "wof:population":309
},
  "geometry": {"coordinates":[81.584374,18.273833],"type":"Point"}
}