{
  "type": "Feature",
  "properties": {
    "iso:country":"IN",
    "ks:ks_name":"Darkhola",
    "ks:ks_pop":18,
    "ks:ks_type":"VILLAGE",
    "name:eng_x_preferred":[
        "Darkhola"
    ],
    "wof:name":"Darkhola",
    "wof:placetype":"locality",
    "wof:population":18
},
  "geometry": {"coordinates":[87.401332,22.892586],"type":"Point"}
}