{
  "type": "Feature",
  "properties": {
    "iso:country":"IN",
    "ks:ks_name":"Jurripadu",
    "ks:ks_pop":259,
    "ks:ks_type":"HABITATION",
    "name:eng_x_preferred":[
        "Jurripadu"
    ],
    "wof:name":"Jurripadu",
    "wof:placetype":"locality",
    "wof:population":259
},
  "geometry": {"coordinates":[82.745574,18.222575],"type":"Point"}
}