{
  "type": "Feature",
  "properties": {
    "gn:admin1_code":"23",
    "gn:admin2_code":"52.0",
    "gn:asciiname":"Makran",
    "gn:country_code":"IN",
    "gn:dem":292,
    "gn:feature_class":"P",
    "gn:feature_code":"PPL",
    "gn:name":"Makr\u0101n",
    "gn:population":0,
    "gn:timezone":"Asia/Kolkata",
    "iso:country":"IN",
    "name:ara_x_preferred":[
        "\u0645\u0643\u0631\u0627\u0646"
    ],
    "name:bel_x_preferred":[
        "\u041c\u0435\u043a\u0440\u0430\u043d"
    ],
    "name:ces_x_preferred":[
        "Makr\u00e1n"
    ],
    "name:cym_x_preferred":[
        "Makran"
    ],
    "name:deu_x_preferred":[
        "Makran"
    ],
    "name:ell_x_preferred":[
        "\u039c\u03b1\u03ba\u03c1\u03b1\u03bd\u03af\u03b1"
    ],
    "name:epo_x_preferred":[
        "Makran"
    ],
    "name:eus_x_preferred":[
        "Makran"
    ],
    "name:fas_x_preferred":[
        "\u0645\u06a9\u0631\u0627\u0646"
    ],
    "name:fra_x_preferred":[
        "Makran"
    ],
    "name:hin_x_preferred":[
        "\u092e\u0915\u0930\u093e\u0928"
    ],
    "name:hrv_x_preferred":[
        "Makran"
    ],
    "name:hun_x_preferred":[
        "Makr\u00e1n"
    ],
    "name:ind_x_preferred":[
        "Makran"
    ],
    "name:ita_x_preferred":[
        "Makran"
    ],
    "name:lit_x_preferred":[
        "Makranas"
    ],
    "name:mar_x_preferred":[
        "\u092e\u0916\u0930\u093e\u0923\u093e"
    ],
    "name:nno_x_preferred":[
        "Makran"
    ],
    "name:pan_x_preferred":[
        "\u0a2e\u0a15\u0a30\u0a3e\u0a28"
    ],
    "name:pnb_x_preferred":[
        "\u0645\u06a9\u0631\u0627\u0646"
    ],
    "name:pol_x_preferred":[
        "Mekran"
    ],
    "name:por_x_preferred":[
        "Macr\u00e3o"
    ],
    "name:rus_x_preferred":[
        "\u041c\u0435\u043a\u0440\u0430\u043d"
    ],
    "name:snd_x_preferred":[
        "\u0645\u06aa\u0631\u0627\u0646"
    ],
    "name:spa_x_preferred":[
        "Makr\u00e1n"
    ],
    "name:srp_x_preferred":[
        "\u041c\u0430\u043a\u0440\u0430\u043d"
    ],
    "name:tur_x_preferred":[
        "Mekran"
    ],
    "name:ukr_x_preferred":[
        "\u041c\u0435\u043a\u0440\u0430\u043d"
    ],
    "name:urd_x_preferred":[
        "\u0645\u06a9\u0631\u0627\u0646"
    ],
    "name:uzb_x_preferred":[
        "Makron"
    ],
    "name:zho_x_preferred":[
        "\u83ab\u514b\u5170"
    ],
    "wof:name":"Makran",
    "wof:placetype":"locality"
},
  "geometry": {"coordinates":[76.60183000000001,30.676],"type":"Point"}
}