{
  "type": "Feature",
  "properties": {
    "iso:country":"IN",
    "ks:ks_name":"Awarijor",
    "ks:ks_pop":74,
    "ks:ks_type":"HABITATION",
    "name:eng_x_preferred":[
        "Awarijor"
    ],
    "wof:name":"Awarijor",
    "wof:placetype":"locality",
    "wof:population":74
},
  "geometry": {"coordinates":[84.15652300000001,22.504787],"type":"Point"}
}