{
  "type": "Feature",
  "properties": {
    "iso:country":"IN",
    "ks:ks_alt_nam":"JADHAVAVASTI",
    "ks:ks_name":"Jadhavavasti",
    "ks:ks_pop":100,
    "ks:ks_type":"HABITATION",
    "name:eng_x_preferred":[
        "Jadhavavasti"
    ],
    "wof:name":"Jadhavavasti",
    "wof:placetype":"locality",
    "wof:population":100
},
  "geometry": {"coordinates":[74.835768,17.173127],"type":"Point"}
}