{
  "type": "Feature",
  "properties": {
    "iso:country":"IN",
    "ks:ks_name":"Naikpada",
    "ks:ks_pop":152,
    "ks:ks_type":"HABITATION",
    "name:eng_x_preferred":[
        "Naikpada"
    ],
    "wof:name":"Naikpada",
    "wof:placetype":"locality",
    "wof:population":152
},
  "geometry": {"coordinates":[73.428906,20.616037],"type":"Point"}
}