{
  "type": "Feature",
  "properties": {
    "iso:country":"IN",
    "ks:ks_name":"Honniganahalli",
    "ks:ks_pop":1219,
    "ks:ks_type":"VILLAGE",
    "ks:ks_uagg_main":0,
    "name:eng_x_preferred":[
        "Honniganahalli"
    ],
    "wof:name":"Honniganahalli",
    "wof:placetype":"locality",
    "wof:population":1219
},
  "geometry": {"coordinates":[77.228069,12.678145],"type":"Point"}
}