{
  "type": "Feature",
  "properties": {
    "iso:country":"IN",
    "ks:ks_name":"Saliki Nc",
    "ks:ks_pop":1196,
    "ks:ks_type":"VILLAGE",
    "ks:ks_uagg_main":0,
    "name:eng_x_preferred":[
        "Saliki Nc"
    ],
    "wof:name":"Saliki Nc",
    "wof:placetype":"neighbourhood",
    "wof:population":1196
},
  "geometry": {"coordinates":[95.817778,27.311473],"type":"Point"}
}