{
  "type": "Feature",
  "properties": {
    "iso:country":"IN",
    "ks:ks_alt_nam":"KhairaKhaspara",
    "ks:ks_name":"Khairakhaspara",
    "ks:ks_pop":243,
    "ks:ks_type":"HABITATION",
    "name:eng_x_preferred":[
        "Khairakhaspara"
    ],
    "wof:name":"Khairakhaspara",
    "wof:placetype":"locality",
    "wof:population":243
},
  "geometry": {"coordinates":[82.710632,23.792279],"type":"Point"}
}