{
  "type": "Feature",
  "properties": {
    "iso:country":"IN",
    "ks:ks_name":"Koilahra",
    "ks:ks_pop":228,
    "ks:ks_type":"HABITATION",
    "name:eng_x_preferred":[
        "Koilahra"
    ],
    "wof:name":"Koilahra",
    "wof:placetype":"locality",
    "wof:population":228
},
  "geometry": {"coordinates":[83.028479,27.315857],"type":"Point"}
}