{
  "type": "Feature",
  "properties": {
    "gn:admin1_code":"19.0",
    "gn:admin2_code":"574.0",
    "gn:asciiname":"Rajendrapur",
    "gn:country_code":"IN",
    "gn:dem":1020,
    "gn:feature_class":"P",
    "gn:feature_code":"PPL",
    "gn:name":"Rajendrapur",
    "gn:population":0,
    "gn:timezone":"Asia/Kolkata",
    "iso:country":"IN",
    "wof:name":"Rajendrapur",
    "wof:placetype":"locality"
},
  "geometry": {"coordinates":[75.8879,12.9278],"type":"Point"}
}