{
  "type": "Feature",
  "properties": {
    "iso:country":"IN",
    "ks:ks_name":"Koili",
    "ks:ks_pop":224,
    "ks:ks_type":"VILLAGE",
    "name:eng_x_preferred":[
        "Koili"
    ],
    "wof:name":"Koili",
    "wof:placetype":"locality",
    "wof:population":224
},
  "geometry": {"coordinates":[84.291095,23.845645],"type":"Point"}
}