{
  "type": "Feature",
  "properties": {
    "iso:country":"IN",
    "ks:ks_name":"Suttalmane",
    "ks:ks_pop":96,
    "ks:ks_type":"HABITATION",
    "name:eng_x_preferred":[
        "Suttalmane"
    ],
    "wof:name":"Suttalmane",
    "wof:placetype":"locality",
    "wof:population":96
},
  "geometry": {"coordinates":[74.789474,14.30137],"type":"Point"}
}