{
  "type": "Feature",
  "properties": {
    "iso:country":"IN",
    "ks:ks_name":"Sajapur",
    "ks:ks_pop":961,
    "ks:ks_type":"VILLAGE",
    "ks:ks_uagg_main":0,
    "name:eng_x_preferred":[
        "Sajapur"
    ],
    "wof:name":"Sajapur",
    "wof:placetype":"locality",
    "wof:population":961
},
  "geometry": {"coordinates":[84.485533,26.34189],"type":"Point"}
}