{
  "type": "Feature",
  "properties": {
    "gn:admin1_code":"40.0",
    "gn:admin2_code":"540.0",
    "gn:asciiname":"Kottapet",
    "gn:country_code":"IN",
    "gn:dem":266,
    "gn:feature_class":"P",
    "gn:feature_code":"PPL",
    "gn:name":"Kottapet",
    "gn:population":0,
    "gn:timezone":"Asia/Kolkata",
    "iso:country":"IN",
    "wof:name":"Kottapet",
    "wof:placetype":"locality"
},
  "geometry": {"coordinates":[79.65308,18.02712],"type":"Point"}
}