{
  "type": "Feature",
  "properties": {
    "gn:admin1_code":"36",
    "gn:admin2_code":"197.0",
    "gn:asciiname":"Taraon",
    "gn:country_code":"IN",
    "gn:dem":82,
    "gn:feature_class":"P",
    "gn:feature_code":"PPL",
    "gn:name":"Tar\u0101on",
    "gn:population":0,
    "gn:timezone":"Asia/Kolkata",
    "iso:country":"IN",
    "ks:ks_alt_nam":"Tar\u0101on",
    "ks:ks_name":"Taraon",
    "ks:ks_pop":734,
    "ks:ks_type":"VILLAGE",
    "ks:ks_uagg_main":0,
    "name:eng_x_preferred":[
        "Taraon"
    ],
    "name:eng_x_variant":[
        "Tar\u0101on"
    ],
    "wof:name":"Taraon",
    "wof:placetype":"neighbourhood",
    "wof:population":734
},
  "geometry": {"coordinates":[82.999228,25.53159],"type":"Point"}
}