{
  "type": "Feature",
  "properties": {
    "iso:country":"IN",
    "ks:ks_name":"Bahata Khadar",
    "ks:ks_pop":118,
    "ks:ks_type":"VILLAGE",
    "name:eng_x_preferred":[
        "Bahata Khadar"
    ],
    "wof:name":"Bahata Khadar",
    "wof:placetype":"locality",
    "wof:population":118
},
  "geometry": {"coordinates":[77.67334700000001,27.786918],"type":"Point"}
}