{
  "type": "Feature",
  "properties": {
    "gn:admin1_code":"2.0",
    "gn:admin2_code":"549.0",
    "gn:asciiname":"Koniki",
    "gn:country_code":"IN",
    "gn:dem":15,
    "gn:feature_class":"P",
    "gn:feature_code":"PPL",
    "gn:name":"Koniki",
    "gn:population":0,
    "gn:timezone":"Asia/Kolkata",
    "iso:country":"IN",
    "name:tel_x_preferred":[
        "\u0c15\u0c4a\u0c23\u0c3f\u0c15\u0c3f"
    ],
    "wof:name":"Koniki",
    "wof:placetype":"locality"
},
  "geometry": {"coordinates":[80.17541999999997,15.78173],"type":"Point"}
}