{
  "type": "Feature",
  "properties": {
    "gn:admin1_code":"12",
    "gn:admin2_code":"2.0",
    "gn:asciiname":"Qasba Nagum",
    "gn:country_code":"IN",
    "gn:dem":1669,
    "gn:feature_class":"P",
    "gn:feature_code":"PPL",
    "gn:name":"Qasba Nagum",
    "gn:population":0,
    "gn:timezone":"Asia/Kolkata",
    "iso:country":"IN",
    "name:und_x_variant":[
        "Kasba Nagum",
        "Qasba Nagum"
    ],
    "wof:name":"Qasba Nagum",
    "wof:placetype":"locality"
},
  "geometry": {"coordinates":[74.79245,33.92594],"type":"Point"}
}