{
  "type": "Feature",
  "properties": {
    "iso:country":"IN",
    "ks:ks_alt_nam":"Burli tota",
    "ks:ks_name":"Burli Tota",
    "ks:ks_pop":255,
    "ks:ks_type":"HABITATION",
    "name:eng_x_preferred":[
        "Burli Tota"
    ],
    "wof:name":"Burli Tota",
    "wof:placetype":"locality",
    "wof:population":255
},
  "geometry": {"coordinates":[75.04321,16.787996],"type":"Point"}
}