{
  "type": "Feature",
  "properties": {
    "iso:country":"IN",
    "ks:ks_name":"Madhaliwadi",
    "ks:ks_pop":163,
    "ks:ks_type":"HABITATION",
    "name:eng_x_preferred":[
        "Madhaliwadi"
    ],
    "wof:name":"Madhaliwadi",
    "wof:placetype":"locality",
    "wof:population":163
},
  "geometry": {"coordinates":[73.36335,17.363922],"type":"Point"}
}