{
  "type": "Feature",
  "properties": {
    "iso:country":"IN",
    "ks:ks_alt_nam":"RAMUNAGAR",
    "ks:ks_name":"Ramunagar",
    "ks:ks_pop":710,
    "ks:ks_type":"HABITATION",
    "name:eng_x_preferred":[
        "Ramunagar"
    ],
    "wof:name":"Ramunagar",
    "wof:placetype":"locality",
    "wof:population":710
},
  "geometry": {"coordinates":[81.599734,22.33504],"type":"Point"}
}