{
  "type": "Feature",
  "properties": {
    "iso:country":"IN",
    "ks:ks_name":"Guner",
    "ks:ks_pop":19,
    "ks:ks_type":"HABITATION",
    "name:eng_x_preferred":[
        "Guner"
    ],
    "wof:name":"Guner",
    "wof:placetype":"locality",
    "wof:population":19
},
  "geometry": {"coordinates":[81.040665,19.336],"type":"Point"}
}