{
  "type": "Feature",
  "properties": {
    "iso:country":"IN",
    "ks:ks_name":"Chhota Baghlata",
    "ks:ks_pop":439,
    "ks:ks_type":"VILLAGE",
    "name:eng_x_preferred":[
        "Chhota Baghlata"
    ],
    "wof:name":"Chhota Baghlata",
    "wof:placetype":"locality",
    "wof:population":439
},
  "geometry": {"coordinates":[86.117813,22.538031],"type":"Point"}
}