{
  "type": "Feature",
  "properties": {
    "iso:country":"IN",
    "ks:ks_name":"Dhansiri Bagaribari No 3",
    "ks:ks_pop":180,
    "ks:ks_type":"HABITATION",
    "name:eng_x_preferred":[
        "Dhansiri Bagaribari No 3"
    ],
    "wof:name":"Dhansiri Bagaribari No 3",
    "wof:placetype":"locality",
    "wof:population":180
},
  "geometry": {"coordinates":[92.31884700000001,26.703514],"type":"Point"}
}