{
  "type": "Feature",
  "properties": {
    "iso:country":"IN",
    "ks:ks_name":"Tildangra",
    "ks:ks_pop":0,
    "ks:ks_type":"VILLAGE",
    "name:eng_x_preferred":[
        "Tildangra"
    ],
    "wof:name":"Tildangra",
    "wof:placetype":"locality",
    "wof:population":0
},
  "geometry": {"coordinates":[87.342961,22.871199],"type":"Point"}
}