{
  "type": "Feature",
  "properties": {
    "gn:admin1_code":"11",
    "gn:admin2_code":"33.0",
    "gn:asciiname":"Bei",
    "gn:country_code":"IN",
    "gn:dem":1336,
    "gn:feature_class":"P",
    "gn:feature_code":"PPL",
    "gn:name":"Bei",
    "gn:population":0,
    "gn:timezone":"Asia/Kolkata",
    "iso:country":"IN",
    "name:ara_x_preferred":[
        "\u0628\u0627\u064a"
    ],
    "name:ben_x_preferred":[
        "\u09ac\u09c7\u0987"
    ],
    "name:ell_x_preferred":[
        "\u039c\u03c0\u03ad\u03b9"
    ],
    "name:fas_x_preferred":[
        "\u0628\u06cc"
    ],
    "name:heb_x_preferred":[
        "\u05d1\u05b6\u05bc\u05d9\u05d9"
    ],
    "name:hun_x_preferred":[
        "Bei"
    ],
    "name:ind_x_preferred":[
        "Bei"
    ],
    "name:ita_x_preferred":[
        "Bei"
    ],
    "name:nld_x_preferred":[
        "Bei"
    ],
    "name:por_x_preferred":[
        "Bei"
    ],
    "name:ukr_x_preferred":[
        "\u0411\u0435\u0439"
    ],
    "name:urd_x_preferred":[
        "\u0628\u06cc"
    ],
    "wof:name":"Bei",
    "wof:placetype":"locality"
},
  "geometry": {"coordinates":[77.14677,31.1828],"type":"Point"}
}