{
  "type": "Feature",
  "properties": {
    "iso:country":"IN",
    "ks:ks_alt_nam":"NICHA TOLA",
    "ks:ks_name":"Nicha Tola",
    "ks:ks_pop":233,
    "ks:ks_type":"HABITATION",
    "name:eng_x_preferred":[
        "Nicha Tola"
    ],
    "wof:name":"Nicha Tola",
    "wof:placetype":"locality",
    "wof:population":233
},
  "geometry": {"coordinates":[84.799693,24.19346],"type":"Point"}
}