{
  "type": "Feature",
  "properties": {
    "iso:country":"IN",
    "ks:ks_name":"Mehamanpur",
    "ks:ks_pop":225,
    "ks:ks_type":"VILLAGE",
    "name:eng_x_preferred":[
        "Mehamanpur"
    ],
    "wof:name":"Mehamanpur",
    "wof:placetype":"locality",
    "wof:population":225
},
  "geometry": {"coordinates":[88.16227000000001,25.065105],"type":"Point"}
}