{
  "type": "Feature",
  "properties": {
    "iso:country":"IN",
    "ks:ks_name":"Kakad Toli",
    "ks:ks_pop":3,
    "ks:ks_type":"VILLAGE",
    "name:eng_x_preferred":[
        "Kakad Toli"
    ],
    "wof:name":"Kakad Toli",
    "wof:placetype":"locality",
    "wof:population":3
},
  "geometry": {"coordinates":[79.443775,30.091897],"type":"Point"}
}