{
  "type": "Feature",
  "properties": {
    "gn:admin1_code":"25.0",
    "gn:admin2_code":"631",
    "gn:asciiname":"Dasampatti",
    "gn:country_code":"IN",
    "gn:dem":405,
    "gn:feature_class":"P",
    "gn:feature_code":"PPL",
    "gn:name":"D\u0101sampatti",
    "gn:population":0,
    "gn:timezone":"Asia/Kolkata",
    "iso:country":"IN",
    "name:und_x_variant":[
        "D\u0101sampatti"
    ],
    "wof:name":"Dasampatti",
    "wof:placetype":"locality"
},
  "geometry": {"coordinates":[78.44033,12.24937],"type":"Point"}
}