{
  "type": "Feature",
  "properties": {
    "iso:country":"IN",
    "ks:ks_name":"Kaithakkad",
    "ks:ks_pop":3056,
    "ks:ks_type":"HABITATION",
    "name:eng_x_preferred":[
        "Kaithakkad"
    ],
    "wof:name":"Kaithakkad",
    "wof:placetype":"locality",
    "wof:population":3056
},
  "geometry": {"coordinates":[75.13638899999999,12.200588],"type":"Point"}
}