{
  "type": "Feature",
  "properties": {
    "iso:country":"IN",
    "ks:ks_name":"Srichandanpur",
    "ks:ks_pop":0,
    "ks:ks_type":"VILLAGE",
    "name:eng_x_preferred":[
        "Srichandanpur"
    ],
    "wof:name":"Srichandanpur",
    "wof:placetype":"locality",
    "wof:population":0
},
  "geometry": {"coordinates":[86.175414,20.707271],"type":"Point"}
}