{
  "type": "Feature",
  "properties": {
    "gn:admin1_code":"16",
    "gn:admin2_code":"513.0",
    "gn:asciiname":"Chukar Pimpri Tanda",
    "gn:country_code":"IN",
    "gn:dem":410,
    "gn:feature_class":"P",
    "gn:feature_code":"PPL",
    "gn:name":"Chuk\u0101r Pimpri T\u0101nda",
    "gn:population":0,
    "gn:timezone":"Asia/Kolkata",
    "iso:country":"IN",
    "wof:name":"Chukar Pimpri Tanda",
    "wof:placetype":"locality"
},
  "geometry": {"coordinates":[76.57902,18.98979],"type":"Point"}
}