{
  "type": "Feature",
  "properties": {
    "iso:country":"IN",
    "ks:ks_name":"Mayagondanhalli",
    "ks:ks_type":"VILLAGE",
    "name:eng_x_preferred":[
        "Mayagondanhalli"
    ],
    "wof:name":"Mayagondanhalli",
    "wof:placetype":"locality"
},
  "geometry": {"coordinates":[77.31619499999999,13.342534],"type":"Point"}
}