{
  "type": "Feature",
  "properties": {
    "iso:country":"IN",
    "ks:ks_name":"Mullagere",
    "ks:ks_pop":93,
    "ks:ks_type":"HABITATION",
    "name:eng_x_preferred":[
        "Mullagere"
    ],
    "wof:name":"Mullagere",
    "wof:placetype":"locality",
    "wof:population":93
},
  "geometry": {"coordinates":[75.015884,13.897698],"type":"Point"}
}