{
  "type": "Feature",
  "properties": {
    "gn:admin1_code":"36",
    "gn:admin2_code":"191.0",
    "gn:asciiname":"Khairuddinpur Ali Azim",
    "gn:country_code":"IN",
    "gn:dem":89,
    "gn:feature_class":"P",
    "gn:feature_code":"PPL",
    "gn:name":"Khairudd\u012bnpur Ali Az\u012bm",
    "gn:population":0,
    "gn:timezone":"Asia/Kolkata",
    "iso:country":"IN",
    "wof:name":"Khairuddinpur Ali Azim",
    "wof:placetype":"locality"
},
  "geometry": {"coordinates":[82.72277,26.0909],"type":"Point"}
}