{
  "type": "Feature",
  "properties": {
    "gn:admin1_code":"11.0",
    "gn:admin2_code":"33.0",
    "gn:asciiname":"Ketu",
    "gn:country_code":"IN",
    "gn:dem":1746,
    "gn:feature_class":"P",
    "gn:feature_code":"PPL",
    "gn:name":"Ketu",
    "gn:population":0,
    "gn:timezone":"Asia/Kolkata",
    "iso:country":"IN",
    "name:ben_x_preferred":[
        "\u0995\u09c7\u09a4\u09c1"
    ],
    "name:cat_x_preferred":[
        "Ketu"
    ],
    "name:ceb_x_preferred":[
        "Ketu"
    ],
    "name:est_x_preferred":[
        "Ketu"
    ],
    "name:fra_x_preferred":[
        "Ketu"
    ],
    "name:por_x_preferred":[
        "Ketu"
    ],
    "name:san_x_preferred":[
        "\u0915\u0947\u0924\u0941\u0903"
    ],
    "name:swe_x_preferred":[
        "Ketu"
    ],
    "wof:name":"Ketu",
    "wof:placetype":"locality"
},
  "geometry": {"coordinates":[77.73676,31.37303],"type":"Point"}
}