{
  "type": "Feature",
  "properties": {
    "iso:country":"IN",
    "ks:ks_name":"Jambudi Faliya",
    "ks:ks_pop":510,
    "ks:ks_type":"HABITATION",
    "name:eng_x_preferred":[
        "Jambudi Faliya"
    ],
    "wof:name":"Jambudi Faliya",
    "wof:placetype":"locality",
    "wof:population":510
},
  "geometry": {"coordinates":[73.709733,22.75805],"type":"Point"}
}