{
  "type": "Feature",
  "properties": {
    "gn:country":"IN",
    "gn:fcode":"PPL",
    "gn:population":9332,
    "iso:country":"IN",
    "name:ara_x_preferred":[
        "\u0628\u0627\u062a\u0627\u0646"
    ],
    "name:ben_bn_x_preferred":[
        "\u09aa\u09a4\u09a8"
    ],
    "name:ben_in_x_preferred":[
        "\u09aa\u09a4\u09a8"
    ],
    "name:ceb_x_preferred":[
        "P\u0101tan"
    ],
    "name:eng_x_preferred":[
        "Patan"
    ],
    "name:fra_x_preferred":[
        "Patan"
    ],
    "name:guj_x_preferred":[
        "\u0aaa\u0abe\u0a9f\u0aa3"
    ],
    "name:hin_x_preferred":[
        "\u092a\u093e\u091f\u0928"
    ],
    "name:ita_x_preferred":[
        "Patan"
    ],
    "name:kan_x_preferred":[
        "\u0caa\u0c9f\u0ca8\u0ccd"
    ],
    "name:mal_x_preferred":[
        "\u0d2a\u0d24\u0d4d\u0d24\u0d3e\u0d7b"
    ],
    "name:mar_x_preferred":[
        "\u092a\u093e\u091f\u0928"
    ],
    "name:msa_x_preferred":[
        "Patan"
    ],
    "name:nan_x_preferred":[
        "Patan"
    ],
    "name:nld_x_preferred":[
        "Patan"
    ],
    "name:pan_x_preferred":[
        "\u0a2a\u0a24\u0a23"
    ],
    "name:rus_x_preferred":[
        "\u041f\u0430\u0442\u0430\u043d"
    ],
    "name:spa_x_preferred":[
        "Patan"
    ],
    "name:swe_x_preferred":[
        "P\u0101tan"
    ],
    "name:tam_x_preferred":[
        "\u0baa\u0b9f\u0bbe\u0ba9\u0bcd"
    ],
    "name:tel_x_preferred":[
        "\u0c2a\u0c3e\u0c1f\u0c28\u0c4d"
    ],
    "name:urd_x_preferred":[
        "\u067e\u0679\u0646"
    ],
    "name:urd_x_variant":[
        "\u067e\u0627\u0679\u0646\u060c \u0686\u06be\u062a\u06cc\u0633 \u06af\u0691\u06be",
        "\u067e\u0627\u0679\u0646"
    ],
    "qs:name":"Patan",
    "qs:name_adm0":"India",
    "qs:name_adm1":"Chhattisgarh",
    "qs:photos_9r":0,
    "qs:photos_sr":0,
    "qs:placetype":"Town",
    "qs:pop_sr":"5",
    "wd:wordcount":110,
    "wof:name":"Patan",
    "wof:placetype":"locality",
    "wof:population":9332
},
  "geometry": {"coordinates":[81.53333000000001,21.03333],"type":"Point"}
}