{
  "type": "Feature",
  "properties": {
    "gn:country":"IN",
    "gn:fcode":"PPL",
    "gn:pop":9332,
    "iso:country":"IN",
    "name:dut_x_preferred":[
        "Patan"
    ],
    "name:eng_x_preferred":[
        "Patan"
    ],
    "name:fre_x_preferred":[
        "Patan"
    ],
    "name:ita_x_preferred":[
        "Patan"
    ],
    "name:may_x_preferred":[
        "Patan"
    ],
    "name:nan_x_preferred":[
        "Patan"
    ],
    "name:rus_x_preferred":[
        "\u041f\u0430\u0442\u0430\u043d"
    ],
    "name:spa_x_preferred":[
        "Patan"
    ],
    "name:swe_x_preferred":[
        "P\u0101tan"
    ],
    "name:unk_x_variant":[
        "P\u0101tan"
    ],
    "name:urd_x_preferred":[
        "\u067e\u0627\u0679\u0646\u060c \u0686\u06be\u062a\u06cc\u0633 \u06af\u0691\u06be"
    ],
    "qs:name":"Patan",
    "qs:name_adm0":"India",
    "qs:name_adm1":"Chhattisgarh",
    "qs:photos_9r":0,
    "qs:photos_sr":0,
    "qs:placetype":"Town",
    "qs:pop_sr":"5",
    "wd:wordcount":110,
    "wof:name":"Patan",
    "wof:placetype":"locality",
    "wof:population":9332
},
  "geometry": {"coordinates":[81.53333000000001,21.03333],"type":"Point"}
}