{
  "type": "Feature",
  "properties": {
    "iso:country":"IN",
    "ks:ks_alt_nam":"Pandu gaon",
    "ks:ks_name":"Pandu Gaon",
    "ks:ks_pop":539,
    "ks:ks_type":"HABITATION",
    "ks:ks_uagg_main":0,
    "name:eng_x_preferred":[
        "Pandu Gaon"
    ],
    "wof:name":"Pandu Gaon",
    "wof:placetype":"neighbourhood",
    "wof:population":539
},
  "geometry": {"coordinates":[93.127219,26.203615],"type":"Point"}
}