{
  "type": "Feature",
  "properties": {
    "iso:country":"IN",
    "ks:ks_name":"Purnaki Dabri",
    "ks:ks_pop":368,
    "ks:ks_type":"VILLAGE",
    "name:eng_x_preferred":[
        "Purnaki Dabri"
    ],
    "wof:name":"Purnaki Dabri",
    "wof:placetype":"locality",
    "wof:population":368
},
  "geometry": {"coordinates":[84.328007,23.637968],"type":"Point"}
}