{
  "type": "Feature",
  "properties": {
    "gn:admin1_code":"40",
    "gn:admin2_code":"540.0",
    "gn:asciiname":"Parked",
    "gn:country_code":"IN",
    "gn:dem":233,
    "gn:feature_class":"P",
    "gn:feature_code":"PPL",
    "gn:name":"Parked",
    "gn:population":0,
    "gn:timezone":"Asia/Kolkata",
    "iso:country":"IN",
    "name:fin_x_preferred":[
        "Jumissa"
    ],
    "name:ita_x_preferred":[
        "Parked"
    ],
    "name:spa_x_preferred":[
        "Parked"
    ],
    "wof:name":"Parked",
    "wof:placetype":"locality"
},
  "geometry": {"coordinates":[79.6592,17.7025],"type":"Point"}
}