{
  "type": "Feature",
  "properties": {
    "iso:country":"IN",
    "ks:ks_alt_nam":"BICH TOLA",
    "ks:ks_name":"Bich Tola",
    "ks:ks_pop":106,
    "ks:ks_type":"HABITATION",
    "name:eng_x_preferred":[
        "Bich Tola"
    ],
    "wof:name":"Bich Tola",
    "wof:placetype":"locality",
    "wof:population":106
},
  "geometry": {"coordinates":[83.593374,24.585674],"type":"Point"}
}