{
  "type": "Feature",
  "properties": {
    "gn:admin1_code":"23",
    "gn:admin2_code":"38.0",
    "gn:asciiname":"Jaja",
    "gn:country_code":"IN",
    "gn:dem":248,
    "gn:feature_class":"P",
    "gn:feature_code":"PPL",
    "gn:name":"Jaja",
    "gn:population":0,
    "gn:timezone":"Asia/Kolkata",
    "iso:country":"IN",
    "name:ces_x_preferred":[
        "Jaja"
    ],
    "name:deu_x_preferred":[
        "Jaja"
    ],
    "name:fas_x_preferred":[
        "\u062c\u0627\u062c\u0627"
    ],
    "name:ita_x_preferred":[
        "Jaja"
    ],
    "name:jpn_x_preferred":[
        "\u30b8\u30e3\u30b8\u30e3"
    ],
    "name:nor_x_preferred":[
        "Jaja"
    ],
    "name:por_x_preferred":[
        "Jaj\u00e1"
    ],
    "name:swe_x_preferred":[
        "Jaja"
    ],
    "wof:name":"Jaja",
    "wof:placetype":"locality"
},
  "geometry": {"coordinates":[75.66134,31.67746],"type":"Point"}
}