{
  "type": "Feature",
  "properties": {
    "iso:country":"IN",
    "ks:ks_name":"Asrey Dih",
    "ks:ks_pop":172,
    "ks:ks_type":"HABITATION",
    "name:eng_x_preferred":[
        "Asrey Dih"
    ],
    "wof:name":"Asrey Dih",
    "wof:placetype":"locality",
    "wof:population":172
},
  "geometry": {"coordinates":[82.52922700000001,27.01561],"type":"Point"}
}