{
  "type": "Feature",
  "properties": {
    "iso:country":"IN",
    "ks:ks_name":"Magodu",
    "ks:ks_pop":225,
    "ks:ks_type":"VILLAGE",
    "name:eng_x_preferred":[
        "Magodu"
    ],
    "wof:name":"Magodu",
    "wof:placetype":"locality",
    "wof:population":225
},
  "geometry": {"coordinates":[74.986283,13.918111],"type":"Point"}
}