{
  "type": "Feature",
  "properties": {
    "iso:country":"IN",
    "ks:ks_alt_nam":"Muthuraja colony",
    "ks:ks_name":"Muthuraja Colony",
    "ks:ks_pop":36,
    "ks:ks_type":"HABITATION",
    "name:eng_x_preferred":[
        "Muthuraja Colony"
    ],
    "wof:name":"Muthuraja Colony",
    "wof:placetype":"locality",
    "wof:population":36
},
  "geometry": {"coordinates":[76.846374,13.507886],"type":"Point"}
}