{
  "type": "Feature",
  "properties": {
    "iso:country":"IN",
    "ks:ks_name":"Gardih",
    "ks:ks_pop":598,
    "ks:ks_type":"VILLAGE",
    "name:eng_x_preferred":[
        "Gardih"
    ],
    "wof:name":"Gardih",
    "wof:placetype":"locality",
    "wof:population":598
},
  "geometry": {"coordinates":[82.73310600000001,21.49974],"type":"Point"}
}