{
  "type": "Feature",
  "properties": {
    "iso:country":"IN",
    "ks:ks_name":"Kusum Barhenda",
    "ks:ks_pop":342,
    "ks:ks_type":"VILLAGE",
    "name:eng_x_preferred":[
        "Kusum Barhenda"
    ],
    "wof:name":"Kusum Barhenda",
    "wof:placetype":"locality",
    "wof:population":342
},
  "geometry": {"coordinates":[85.772418,25.678874],"type":"Point"}
}