{
  "type": "Feature",
  "properties": {
    "gn:admin1_code":"35",
    "gn:admin2_code":"453.0",
    "gn:asciiname":"Chapwar",
    "gn:country_code":"IN",
    "gn:dem":799,
    "gn:feature_class":"P",
    "gn:feature_code":"PPL",
    "gn:name":"Chapw\u0101r",
    "gn:population":0,
    "gn:timezone":"Asia/Kolkata",
    "iso:country":"IN",
    "ks:ks_alt_nam":"Chapw\u0101r",
    "ks:ks_name":"Chapwar",
    "ks:ks_type":"VILLAGE",
    "name:eng_x_preferred":[
        "Chapwar"
    ],
    "name:eng_x_variant":[
        "Chapw\u0101r"
    ],
    "wof:name":"Chapwar",
    "wof:placetype":"locality"
},
  "geometry": {"coordinates":[81.16214600000001,22.617285],"type":"Point"}
}