{
  "type": "Feature",
  "properties": {
    "gn:admin1_code":"38",
    "gn:admin2_code":"346.0",
    "gn:asciiname":"Majhganwan",
    "gn:country_code":"IN",
    "gn:dem":246,
    "gn:feature_class":"P",
    "gn:feature_code":"PPL",
    "gn:name":"Majhg\u0101nw\u0101n",
    "gn:population":0,
    "gn:timezone":"Asia/Kolkata",
    "iso:country":"IN",
    "ks:ks_alt_nam":"Majhg\u0101nw\u0101n",
    "ks:ks_name":"Majhganwan",
    "ks:ks_pop":2452,
    "ks:ks_type":"VILLAGE",
    "name:eng_x_preferred":[
        "Majhganwan"
    ],
    "name:eng_x_variant":[
        "Majhg\u0101nw\u0101n"
    ],
    "wof:name":"Majhganwan",
    "wof:placetype":"locality",
    "wof:population":2452
},
  "geometry": {"coordinates":[83.475177,24.397604],"type":"Point"}
}