{
  "type": "Feature",
  "properties": {
    "iso:country":"IN",
    "ks:ks_name":"Bankasemal",
    "ks:ks_pop":41,
    "ks:ks_type":"VILLAGE",
    "name:eng_x_preferred":[
        "Bankasemal"
    ],
    "wof:name":"Bankasemal",
    "wof:placetype":"locality",
    "wof:population":41
},
  "geometry": {"coordinates":[86.963706,23.898742],"type":"Point"}
}