{
  "type": "Feature",
  "properties": {
    "iso:country":"IN",
    "ks:ks_alt_nam":"Bheelya thanda",
    "ks:ks_name":"Bheelya Thanda",
    "ks:ks_pop":47,
    "ks:ks_type":"HABITATION",
    "name:eng_x_preferred":[
        "Bheelya Thanda"
    ],
    "wof:name":"Bheelya Thanda",
    "wof:placetype":"locality",
    "wof:population":47
},
  "geometry": {"coordinates":[79.311148,17.967208],"type":"Point"}
}