{
  "type": "Feature",
  "properties": {
    "iso:country":"IN",
    "ks:ks_alt_nam":"HARIZON TOLA.",
    "ks:ks_name":"Harizon Tola.",
    "ks:ks_pop":132,
    "ks:ks_type":"HABITATION",
    "name:eng_x_preferred":[
        "Harizon Tola."
    ],
    "wof:name":"Harizon Tola.",
    "wof:placetype":"locality",
    "wof:population":132
},
  "geometry": {"coordinates":[86.866798,26.308316],"type":"Point"}
}