{
  "type": "Feature",
  "properties": {
    "iso:country":"IN",
    "ks:ks_name":"Kalur Mandala Patti",
    "ks:ks_pop":95,
    "ks:ks_type":"HABITATION",
    "name:eng_x_preferred":[
        "Kalur Mandala Patti"
    ],
    "wof:name":"Kalur Mandala Patti",
    "wof:placetype":"locality",
    "wof:population":95
},
  "geometry": {"coordinates":[75.703333,12.541667],"type":"Point"}
}