{
  "type": "Feature",
  "properties": {
    "iso:country":"IN",
    "ks:ks_name":"Pachim Tola",
    "ks:ks_pop":790,
    "ks:ks_type":"HABITATION",
    "name:eng_x_preferred":[
        "Pachim Tola"
    ],
    "wof:name":"Pachim Tola",
    "wof:placetype":"locality",
    "wof:population":790
},
  "geometry": {"coordinates":[84.099531,26.67166],"type":"Point"}
}