{
  "type": "Feature",
  "properties": {
    "iso:country":"IN",
    "ks:ks_name":"Thotavalasa",
    "ks:ks_pop":69,
    "ks:ks_type":"HABITATION",
    "name:eng_x_preferred":[
        "Thotavalasa"
    ],
    "wof:name":"Thotavalasa",
    "wof:placetype":"locality",
    "wof:population":69
},
  "geometry": {"coordinates":[82.94741399999999,18.265829],"type":"Point"}
}