{
  "type": "Feature",
  "properties": {
    "iso:country":"IN",
    "ks:ks_name":"Lalnagar",
    "ks:ks_pop":257,
    "ks:ks_type":"HABITATION",
    "name:eng_x_preferred":[
        "Lalnagar"
    ],
    "wof:name":"Lalnagar",
    "wof:placetype":"locality",
    "wof:population":257
},
  "geometry": {"coordinates":[72.541861,26.68645],"type":"Point"}
}