{
  "type": "Feature",
  "properties": {
    "gn:admin1_code":"21.0",
    "gn:admin2_code":"396.0",
    "gn:asciiname":"Darukona",
    "gn:country_code":"IN",
    "gn:dem":547,
    "gn:feature_class":"P",
    "gn:feature_code":"PPL",
    "gn:name":"D\u0101rukona",
    "gn:population":0,
    "gn:timezone":"Asia/Kolkata",
    "iso:country":"IN",
    "ks:ks_alt_nam":"D\u0101rukona",
    "ks:ks_name":"Darukona",
    "ks:ks_pop":406,
    "ks:ks_type":"VILLAGE",
    "name:eng_x_preferred":[
        "Darukona"
    ],
    "name:eng_x_variant":[
        "D\u0101rukona"
    ],
    "wof:name":"Darukona",
    "wof:placetype":"locality",
    "wof:population":406
},
  "geometry": {"coordinates":[83.574556,19.434463],"type":"Point"}
}