{
  "type": "Feature",
  "properties": {
    "gn:country":"IN",
    "gn:fcode":"PPL",
    "gn:pop":23984,
    "iso:country":"IN",
    "name:ben_x_preferred":[
        "\u09ae\u09c2\u09b2"
    ],
    "name:cat_x_preferred":[
        "Mul"
    ],
    "name:deu_x_preferred":[
        "Mul"
    ],
    "name:eng_x_preferred":[
        "Mul"
    ],
    "name:fra_x_preferred":[
        "Mul"
    ],
    "name:guj_x_preferred":[
        "\u0aae\u0ac2\u0ab2"
    ],
    "name:ita_x_preferred":[
        "Mul"
    ],
    "name:jpn_x_preferred":[
        "\u30e0\u30a4"
    ],
    "name:kan_x_preferred":[
        "\u0cae\u0cb2\u0ccd"
    ],
    "name:kor_x_preferred":[
        "\ubb3c"
    ],
    "name:nan_x_preferred":[
        "Mul"
    ],
    "name:nld_x_preferred":[
        "Mul"
    ],
    "name:ori_x_preferred":[
        "\u0b2e\u0b41\u0b32\u0b4d"
    ],
    "name:por_x_preferred":[
        "Mul"
    ],
    "name:rus_x_preferred":[
        "\u041c\u0443\u043b"
    ],
    "name:spa_x_preferred":[
        "Mul"
    ],
    "name:swe_x_preferred":[
        "M\u016bl"
    ],
    "name:tam_x_preferred":[
        "\u0bae\u0bc1\u0bb3\u0bcd"
    ],
    "name:tel_x_preferred":[
        "\u0c2e\u0c32\u0c4d"
    ],
    "name:urd_x_preferred":[
        "\u0645\u0648\u0644\u060c \u0628\u06be\u0627\u0631\u062a"
    ],
    "qs:name":"M\u016bl",
    "qs:photos_9r":0,
    "qs:photos_sr":0,
    "qs:pop_sr":"7",
    "wof:name":"M\u016bl",
    "wof:placetype":"locality",
    "wof:population":23984
},
  "geometry": {"coordinates":[79.67812000000001,20.0684],"type":"Point"}
}