{
  "type": "Feature",
  "properties": {
    "iso:country":"IN",
    "ks:ks_name":"Manglasai",
    "ks:ks_pop":265,
    "ks:ks_type":"VILLAGE",
    "name:eng_x_preferred":[
        "Manglasai"
    ],
    "wof:name":"Manglasai",
    "wof:placetype":"locality",
    "wof:population":265
},
  "geometry": {"coordinates":[86.155073,22.564911],"type":"Point"}
}