{
  "type": "Feature",
  "properties": {
    "gn:admin1_code":"23.0",
    "gn:admin2_code":"35.0",
    "gn:asciiname":"Gande Pindi",
    "gn:country_code":"IN",
    "gn:dem":261,
    "gn:feature_class":"P",
    "gn:feature_code":"PPL",
    "gn:name":"Gande Pindi",
    "gn:population":0,
    "gn:timezone":"Asia/Kolkata",
    "iso:country":"IN",
    "ks:ks_name":"Gande Pindi",
    "ks:ks_pop":332,
    "ks:ks_type":"VILLAGE",
    "ks:ks_uagg_main":0,
    "name:eng_x_preferred":[
        "Gande Pindi"
    ],
    "wof:name":"Gande Pindi",
    "wof:placetype":"neighbourhood",
    "wof:population":332
},
  "geometry": {"coordinates":[75.427088,32.191363],"type":"Point"}
}