{
  "type": "Feature",
  "properties": {
    "iso:country":"IN",
    "ks:ks_name":"Perungiraipatti",
    "ks:ks_pop":92,
    "ks:ks_type":"HABITATION",
    "name:eng_x_preferred":[
        "Perungiraipatti"
    ],
    "wof:name":"Perungiraipatti",
    "wof:placetype":"locality",
    "wof:population":92
},
  "geometry": {"coordinates":[78.381254,11.365386],"type":"Point"}
}