{
  "type": "Feature",
  "properties": {
    "iso:country":"IN",
    "ks:ks_name":"Habipur",
    "ks:ks_pop":374,
    "ks:ks_type":"VILLAGE",
    "name:eng_x_preferred":[
        "Habipur"
    ],
    "wof:name":"Habipur",
    "wof:placetype":"locality",
    "wof:population":374
},
  "geometry": {"coordinates":[88.425909,24.136915],"type":"Point"}
}