{
  "type": "Feature",
  "properties": {
    "iso:country":"IN",
    "ks:ks_alt_nam":"P\u0113r\u0101mbra",
    "ks:ks_name":"Perambra",
    "ks:ks_pop":10507,
    "ks:ks_type":"VILLAGE",
    "name:eng_x_preferred":[
        "Perambra"
    ],
    "name:eng_x_variant":[
        "P\u0113r\u0101mbra"
    ],
    "wof:name":"Perambra",
    "wof:placetype":"locality",
    "wof:population":10507
},
  "geometry": {"coordinates":[75.8018,11.577691],"type":"Point"}
}