{
  "type": "Feature",
  "properties": {
    "iso:country":"IN",
    "ks:ks_name":"Pura",
    "ks:ks_pop":100,
    "ks:ks_type":"VILLAGE",
    "name:eng_x_preferred":[
        "Pura"
    ],
    "wof:name":"Pura",
    "wof:placetype":"locality",
    "wof:population":100
},
  "geometry": {"coordinates":[82.214434,23.834764],"type":"Point"}
}