{
  "type": "Feature",
  "properties": {
    "gn:admin1_code":"37",
    "gn:admin2_code":"406.0",
    "gn:asciiname":"Bhanwar",
    "gn:country_code":"IN",
    "gn:dem":423,
    "gn:feature_class":"P",
    "gn:feature_code":"PPL",
    "gn:name":"Bh\u0101nwar",
    "gn:population":0,
    "gn:timezone":"Asia/Kolkata",
    "iso:country":"IN",
    "name:new_x_preferred":[
        "\u092d\u0901\u0935\u0930"
    ],
    "wof:name":"Bhanwar",
    "wof:placetype":"locality"
},
  "geometry": {"coordinates":[81.80025999999999,22.44197],"type":"Point"}
}