{
  "type": "Feature",
  "properties": {
    "iso:country":"IN",
    "ks:ks_name":"South Harijanawada",
    "ks:ks_pop":308,
    "ks:ks_type":"HABITATION",
    "name:eng_x_preferred":[
        "South Harijanawada"
    ],
    "wof:name":"South Harijanawada",
    "wof:placetype":"locality",
    "wof:population":308
},
  "geometry": {"coordinates":[79.582838,14.823891],"type":"Point"}
}