{
  "type": "Feature",
  "properties": {
    "iso:country":"IN",
    "ks:ks_alt_nam":"CHANGONDA WASTI",
    "ks:ks_name":"Changonda Wasti",
    "ks:ks_pop":117,
    "ks:ks_type":"HABITATION",
    "name:eng_x_preferred":[
        "Changonda Wasti"
    ],
    "wof:name":"Changonda Wasti",
    "wof:placetype":"locality",
    "wof:population":117
},
  "geometry": {"coordinates":[75.505422,17.146395],"type":"Point"}
}