{
  "type": "Feature",
  "properties": {
    "iso:country":"IN",
    "ks:ks_name":"Maldongri",
    "ks:ks_pop":58,
    "ks:ks_type":"HABITATION",
    "name:eng_x_preferred":[
        "Maldongri"
    ],
    "wof:name":"Maldongri",
    "wof:placetype":"locality",
    "wof:population":58
},
  "geometry": {"coordinates":[80.937591,20.554599],"type":"Point"}
}