{
  "type": "Feature",
  "properties": {
    "iso:country":"IN",
    "ks:ks_name":"Vadakkumuri",
    "ks:ks_pop":1951,
    "ks:ks_type":"HABITATION",
    "ks:ks_uagg_main":0,
    "name:eng_x_preferred":[
        "Vadakkumuri"
    ],
    "wof:name":"Vadakkumuri",
    "wof:placetype":"neighbourhood",
    "wof:population":1951
},
  "geometry": {"coordinates":[76.052333,11.252355],"type":"Point"}
}