{
  "type": "Feature",
  "properties": {
    "iso:country":"IN",
    "ks:ks_name":"Arjundoddi",
    "ks:ks_pop":371,
    "ks:ks_type":"HABITATION",
    "name:eng_x_preferred":[
        "Arjundoddi"
    ],
    "wof:name":"Arjundoddi",
    "wof:placetype":"locality",
    "wof:population":371
},
  "geometry": {"coordinates":[77.344031,11.908322],"type":"Point"}
}