{
  "type": "Feature",
  "properties": {
    "iso:country":"IN",
    "ks:ks_name":"Ruparel Falia",
    "ks:ks_pop":1278,
    "ks:ks_type":"HABITATION",
    "name:eng_x_preferred":[
        "Ruparel Falia"
    ],
    "wof:name":"Ruparel Falia",
    "wof:placetype":"locality",
    "wof:population":1278
},
  "geometry": {"coordinates":[73.984083,22.579],"type":"Point"}
}