{
  "type": "Feature",
  "properties": {
    "iso:country":"IN",
    "ks:ks_alt_nam":"parabwadi",
    "ks:ks_name":"Parabwadi",
    "ks:ks_pop":71,
    "ks:ks_type":"HABITATION",
    "name:eng_x_preferred":[
        "Parabwadi"
    ],
    "wof:name":"Parabwadi",
    "wof:placetype":"locality",
    "wof:population":71
},
  "geometry": {"coordinates":[73.687793,15.835717],"type":"Point"}
}