{
  "type": "Feature",
  "properties": {
    "iso:country":"IN",
    "ks:ks_alt_nam":"kalsusar ka pura",
    "ks:ks_name":"Kalsusar Ka Pura",
    "ks:ks_pop":235,
    "ks:ks_type":"HABITATION",
    "name:eng_x_preferred":[
        "Kalsusar Ka Pura"
    ],
    "wof:name":"Kalsusar Ka Pura",
    "wof:placetype":"locality",
    "wof:population":235
},
  "geometry": {"coordinates":[83.805808,26.016223],"type":"Point"}
}