{
  "type": "Feature",
  "properties": {
    "gn:admin1_code":"19.0",
    "gn:admin2_code":"574.0",
    "gn:asciiname":"Bindenahalli",
    "gn:country_code":"IN",
    "gn:dem":1026,
    "gn:feature_class":"P",
    "gn:feature_code":"PPL",
    "gn:name":"Bindenahalli",
    "gn:population":0,
    "gn:timezone":"Asia/Kolkata",
    "iso:country":"IN",
    "ks:ks_name":"Bendenahalli",
    "ks:ks_pop":70,
    "ks:ks_type":"HABITATION",
    "name:eng_x_preferred":[
        "Bendenahalli"
    ],
    "name:eng_x_variant":[
        "Bindenahalli"
    ],
    "wof:name":"Bendenahalli",
    "wof:placetype":"locality",
    "wof:population":70
},
  "geometry": {"coordinates":[75.749921,13.175591],"type":"Point"}
}