{
  "type": "Feature",
  "properties": {
    "gn:admin1_code":"19.0",
    "gn:admin2_code":"574.0",
    "gn:asciiname":"Bindenahalli",
    "gn:country_code":"IN",
    "gn:dem":1026,
    "gn:feature_class":"P",
    "gn:feature_code":"PPL",
    "gn:name":"Bindenahalli",
    "gn:population":0,
    "gn:timezone":"Asia/Kolkata",
    "iso:country":"IN",
    "wof:name":"Bindenahalli",
    "wof:placetype":"locality"
},
  "geometry": {"coordinates":[75.75609,13.17116],"type":"Point"}
}