{
  "type": "Feature",
  "properties": {
    "gn:admin1_code":"34.0",
    "gn:admin2_code":"236.0",
    "gn:asciiname":"Lutitanr",
    "gn:country_code":"IN",
    "gn:dem":339,
    "gn:feature_class":"P",
    "gn:feature_code":"PPL",
    "gn:name":"Lut\u012bt\u0101nr",
    "gn:population":0,
    "gn:timezone":"Asia/Kolkata",
    "iso:country":"IN",
    "wof:name":"Lutitanr",
    "wof:placetype":"locality"
},
  "geometry": {"coordinates":[84.54446999999998,24.50529],"type":"Point"}
}