{
  "type": "Feature",
  "properties": {
    "gn:admin1_code":"36",
    "gn:admin2_code":"158.0",
    "gn:asciiname":"Itaura Ruzuro",
    "gn:country_code":"IN",
    "gn:dem":119,
    "gn:feature_class":"P",
    "gn:feature_code":"PPL",
    "gn:name":"Itaura Ruzuro",
    "gn:population":0,
    "gn:timezone":"Asia/Kolkata",
    "iso:country":"IN",
    "wof:name":"Itaura Ruzuro",
    "wof:placetype":"locality"
},
  "geometry": {"coordinates":[81.30133000000002,26.00295],"type":"Point"}
}