{
  "type": "Feature",
  "properties": {
    "gn:admin1_code":"23.0",
    "gn:admin2_code":"38.0",
    "gn:asciiname":"Mustapur",
    "gn:country_code":"IN",
    "gn:dem":389,
    "gn:feature_class":"P",
    "gn:feature_code":"PPL",
    "gn:name":"Mustapur",
    "gn:population":0,
    "gn:timezone":"Asia/Kolkata",
    "iso:country":"IN",
    "ks:ks_name":"Mustapur",
    "ks:ks_type":"VILLAGE",
    "name:eng_x_preferred":[
        "Mustapur"
    ],
    "wof:name":"Mustapur",
    "wof:placetype":"locality"
},
  "geometry": {"coordinates":[75.947304,31.628545],"type":"Point"}
}