{
  "type": "Feature",
  "properties": {
    "iso:country":"IN",
    "ks:ks_alt_nam":"DOHARAM PARA",
    "ks:ks_name":"Doharam Para",
    "ks:ks_pop":616,
    "ks:ks_type":"HABITATION",
    "name:eng_x_preferred":[
        "Doharam Para"
    ],
    "wof:name":"Doharam Para",
    "wof:placetype":"locality",
    "wof:population":616
},
  "geometry": {"coordinates":[91.415092,23.64647],"type":"Point"}
}