{
  "type": "Feature",
  "properties": {
    "gn:admin1_code":"35.0",
    "gn:admin2_code":"455.0",
    "gn:asciiname":"Pathrakhokar",
    "gn:country_code":"IN",
    "gn:dem":748,
    "gn:feature_class":"P",
    "gn:feature_code":"PPL",
    "gn:name":"Pathr\u0101khokar",
    "gn:population":0,
    "gn:timezone":"Asia/Kolkata",
    "iso:country":"IN",
    "ks:ks_name":"Pathra Khokar",
    "ks:ks_pop":566,
    "ks:ks_type":"VILLAGE",
    "name:eng_x_preferred":[
        "Pathra Khokar"
    ],
    "name:eng_x_variant":[
        "Pathrakhokar"
    ],
    "wof:name":"Pathra Khokar",
    "wof:placetype":"locality",
    "wof:population":566
},
  "geometry": {"coordinates":[78.74084000000001,21.93875],"type":"Point"}
}