{
  "type": "Feature",
  "properties": {
    "iso:country":"IN",
    "ks:ks_name":"Kumbhirgadi",
    "ks:ks_pop":1497,
    "ks:ks_type":"VILLAGE",
    "name:eng_x_preferred":[
        "Kumbhirgadi"
    ],
    "wof:name":"Kumbhirgadi",
    "wof:placetype":"locality",
    "wof:population":1497
},
  "geometry": {"coordinates":[87.325575,21.597948],"type":"Point"}
}