{
  "type": "Feature",
  "properties": {
    "gn:admin1_code":"23.0",
    "gn:admin2_code":"045",
    "gn:asciiname":"Chand Bhan",
    "gn:country_code":"IN",
    "gn:dem":208,
    "gn:feature_class":"P",
    "gn:feature_code":"PPL",
    "gn:name":"Chand Bh\u0101n",
    "gn:population":0,
    "gn:timezone":"Asia/Kolkata",
    "iso:country":"IN",
    "wof:name":"Chand Bhan",
    "wof:placetype":"locality"
},
  "geometry": {"coordinates":[74.89829,30.38469000000001],"type":"Point"}
}