{
  "type": "Feature",
  "properties": {
    "iso:country":"IN",
    "ks:ks_name":"Chhota Salunchi",
    "ks:ks_pop":452,
    "ks:ks_type":"VILLAGE",
    "name:eng_x_preferred":[
        "Chhota Salunchi"
    ],
    "wof:name":"Chhota Salunchi",
    "wof:placetype":"locality",
    "wof:population":452
},
  "geometry": {"coordinates":[87.468191,23.775741],"type":"Point"}
}