{
  "type": "Feature",
  "properties": {
    "gn:admin1_code":"39.0",
    "gn:admin2_code":"61.0",
    "gn:asciiname":"Matela",
    "gn:country_code":"IN",
    "gn:dem":1403,
    "gn:feature_class":"P",
    "gn:feature_code":"PPL",
    "gn:name":"Matela",
    "gn:population":0,
    "gn:timezone":"Asia/Kolkata",
    "iso:country":"IN",
    "name:ceb_x_preferred":[
        "Matela"
    ],
    "name:deu_x_preferred":[
        "Matela"
    ],
    "name:fra_x_preferred":[
        "Matela"
    ],
    "name:new_x_preferred":[
        "\u092e\u0924\u0947\u0932\u093e"
    ],
    "name:nld_x_preferred":[
        "Matela"
    ],
    "name:pol_x_preferred":[
        "Matela"
    ],
    "name:por_x_preferred":[
        "Matela"
    ],
    "name:rus_x_preferred":[
        "\u041c\u0430\u0442\u0435\u043b\u0430"
    ],
    "name:ukr_x_preferred":[
        "\u041c\u0430\u0442\u0435\u043b\u0430"
    ],
    "wof:name":"Matela",
    "wof:placetype":"locality"
},
  "geometry": {"coordinates":[79.03475,29.9093],"type":"Point"}
}