{
  "type": "Feature",
  "properties": {
    "iso:country":"IN",
    "ks:ks_name":"Jamuniha Khurd",
    "ks:ks_pop":282,
    "ks:ks_type":"HABITATION",
    "name:eng_x_preferred":[
        "Jamuniha Khurd"
    ],
    "wof:name":"Jamuniha Khurd",
    "wof:placetype":"locality",
    "wof:population":282
},
  "geometry": {"coordinates":[81.966551,24.378067],"type":"Point"}
}