{
  "type": "Feature",
  "properties": {
    "gn:country":"IN",
    "gn:fcode":"PPL",
    "gn:population":0,
    "iso:country":"IN",
    "qs:name":"Rajaji Nagar",
    "qs:name_adm0":"India",
    "qs:name_adm1":"Karnataka",
    "qs:photos_9r":0,
    "qs:photos_sr":0,
    "qs:placetype":"Suburb",
    "qs:pop_sr":"0",
    "wof:name":"Rajaji Nagar",
    "wof:placetype":"neighbourhood",
    "wof:population":0
},
  "geometry": {"coordinates":[77.54906,12.98474],"type":"Point"}
}