{
  "type": "Feature",
  "properties": {
    "gn:country":"IN",
    "gn:fcode":"PPL",
    "gn:population":0,
    "iso:country":"IN",
    "name:ara_x_preferred":[
        "\u0631\u0627\u062c\u0627\u062c\u064a \u0646\u0627\u062c\u0627\u0631"
    ],
    "name:ben_bn_x_preferred":[
        "\u09b0\u09be\u099c\u09be\u099c\u09bf \u09a8\u0997\u09b0"
    ],
    "name:ben_in_x_preferred":[
        "\u09b0\u09be\u099c\u09be\u099c\u09bf \u09a8\u0997\u09b0"
    ],
    "name:guj_x_preferred":[
        "\u0ab0\u0abe\u0a9c\u0abe\u0a9c\u0ac0 \u0aa8\u0a97\u0ab0"
    ],
    "name:hin_x_preferred":[
        "\u0930\u093e\u091c\u093e\u091c\u0940 \u0928\u0917\u0930"
    ],
    "name:kan_x_preferred":[
        "\u0cb0\u0cbe\u0c9c\u0cbe\u0c9c\u0cbf \u0ca8\u0c97\u0cb0"
    ],
    "name:mal_x_preferred":[
        "\u0d30\u0d3e\u0d1c\u0d3e\u0d1c\u0d3f \u0d28\u0d17\u0d7c"
    ],
    "name:mar_x_preferred":[
        "\u0930\u093e\u091c\u093e\u091c\u0940 \u0928\u0917\u0930"
    ],
    "name:pan_x_preferred":[
        "\u0a30\u0a3e\u0a1c\u0a3e\u0a1c\u0a40 \u0a28\u0a17\u0a30"
    ],
    "name:tam_x_preferred":[
        "\u0bb0\u0bbe\u0b9c\u0bbe\u0b9c\u0bbf \u0ba8\u0b95\u0bb0\u0bcd"
    ],
    "name:tel_x_preferred":[
        "\u0c30\u0c3e\u0c1c\u0c3e\u0c1c\u0c3f \u0c28\u0c17\u0c30\u0c4d"
    ],
    "name:urd_x_preferred":[
        "\u0631\u0627\u062c\u0627 \u062c\u06cc \u0646\u06af\u0631"
    ],
    "qs:name":"Rajaji Nagar",
    "qs:name_adm0":"India",
    "qs:name_adm1":"Karnataka",
    "qs:photos_9r":0,
    "qs:photos_sr":0,
    "qs:placetype":"Suburb",
    "qs:pop_sr":"0",
    "wof:name":"Rajaji Nagar",
    "wof:placetype":"neighbourhood",
    "wof:population":0
},
  "geometry": {"coordinates":[77.54906,12.98474],"type":"Point"}
}