{
  "type": "Feature",
  "properties": {
    "iso:country":"IN",
    "ks:ks_name":"Narayan Paul Para",
    "ks:ks_pop":332,
    "ks:ks_type":"HABITATION",
    "name:eng_x_preferred":[
        "Narayan Paul Para"
    ],
    "wof:name":"Narayan Paul Para",
    "wof:placetype":"locality",
    "wof:population":332
},
  "geometry": {"coordinates":[91.61739900000001,23.209986],"type":"Point"}
}