{
  "type": "Feature",
  "properties": {
    "gn:admin1_code":"24.0",
    "gn:admin2_code":"103.0",
    "gn:asciiname":"Raipur",
    "gn:country_code":"IN",
    "gn:dem":301,
    "gn:feature_class":"P",
    "gn:feature_code":"PPL",
    "gn:name":"R\u0101ipur",
    "gn:population":0,
    "gn:timezone":"Asia/Kolkata",
    "iso:country":"IN",
    "wof:name":"Raipur",
    "wof:placetype":"locality"
},
  "geometry": {"coordinates":[75.98578000000001,28.16576],"type":"Point"}
}