{
  "type": "Feature",
  "properties": {
    "iso:country":"IN",
    "ks:ks_name":"Pala",
    "ks:ks_pop":492,
    "ks:ks_type":"VILLAGE",
    "ks:ks_uagg_main":0,
    "name:eng_x_preferred":[
        "Pala"
    ],
    "wof:name":"Pala",
    "wof:placetype":"neighbourhood",
    "wof:population":492
},
  "geometry": {"coordinates":[76.64572200000001,27.347447],"type":"Point"}
}