{
  "type": "Feature",
  "properties": {
    "iso:country":"IN",
    "ks:ks_alt_nam":"KUSHA SARDAR PARA",
    "ks:ks_name":"Kusha Sardar Para",
    "ks:ks_pop":104,
    "ks:ks_type":"HABITATION",
    "name:eng_x_preferred":[
        "Kusha Sardar Para"
    ],
    "wof:name":"Kusha Sardar Para",
    "wof:placetype":"locality",
    "wof:population":104
},
  "geometry": {"coordinates":[91.48863299999999,23.873725],"type":"Point"}
}