{
  "type": "Feature",
  "properties": {
    "iso:country":"IN",
    "ks:ks_name":"P Kuti",
    "ks:ks_pop":250,
    "ks:ks_type":"HABITATION",
    "name:eng_x_preferred":[
        "P Kuti"
    ],
    "wof:name":"P Kuti",
    "wof:placetype":"locality",
    "wof:population":250
},
  "geometry": {"coordinates":[81.532,26.3612],"type":"Point"}
}