{
  "type": "Feature",
  "properties": {
    "iso:country":"IN",
    "ks:ks_name":"Kadalimunda",
    "ks:ks_pop":75,
    "ks:ks_type":"HABITATION",
    "name:eng_x_preferred":[
        "Kadalimunda"
    ],
    "wof:name":"Kadalimunda",
    "wof:placetype":"locality",
    "wof:population":75
},
  "geometry": {"coordinates":[82.800815,20.045311],"type":"Point"}
}