{
  "type": "Feature",
  "properties": {
    "gn:admin1_code":"34.0",
    "gn:admin2_code":"226.0",
    "gn:asciiname":"Dasauni",
    "gn:country_code":"IN",
    "gn:dem":64,
    "gn:feature_class":"P",
    "gn:feature_code":"PPL",
    "gn:name":"Dasauni",
    "gn:population":0,
    "gn:timezone":"Asia/Kolkata",
    "iso:country":"IN",
    "wof:name":"Dasauni",
    "wof:placetype":"locality"
},
  "geometry": {"coordinates":[86.51918000000001,25.07702],"type":"Point"}
}