{
  "type": "Feature",
  "properties": {
    "iso:country":"IN",
    "ks:ks_name":"Subhaindih",
    "ks:ks_pop":80,
    "ks:ks_type":"HABITATION",
    "name:eng_x_preferred":[
        "Subhaindih"
    ],
    "wof:name":"Subhaindih",
    "wof:placetype":"locality",
    "wof:population":80
},
  "geometry": {"coordinates":[83.407432,27.395798],"type":"Point"}
}