{
  "type": "Feature",
  "properties": {
    "gn:admin1_code":"35.0",
    "gn:admin2_code":"442.0",
    "gn:asciiname":"Moi",
    "gn:country_code":"IN",
    "gn:dem":430,
    "gn:feature_class":"P",
    "gn:feature_code":"PPL",
    "gn:name":"Moi",
    "gn:population":0,
    "gn:timezone":"Asia/Kolkata",
    "iso:country":"IN",
    "name:ceb_x_preferred":[
        "Moi"
    ],
    "name:deu_x_preferred":[
        "Moi"
    ],
    "name:fin_x_preferred":[
        "Moi"
    ],
    "name:fra_x_preferred":[
        "Moi"
    ],
    "name:nld_x_preferred":[
        "Moi"
    ],
    "name:por_x_preferred":[
        "Moi"
    ],
    "name:swa_x_preferred":[
        "Moi"
    ],
    "name:swe_x_preferred":[
        "Moi"
    ],
    "name:ukr_x_preferred":[
        "\u041c\u043e\u0457"
    ],
    "name:vie_x_preferred":[
        "Moi"
    ],
    "wof:name":"Moi",
    "wof:placetype":"locality"
},
  "geometry": {"coordinates":[76.93491999999998,23.95058],"type":"Point"}
}