{
  "type": "Feature",
  "properties": {
    "gn:admin1_code":"2",
    "gn:admin2_code":"548.0",
    "gn:asciiname":"Tummalapalem",
    "gn:country_code":"IN",
    "gn:dem":51,
    "gn:feature_class":"P",
    "gn:feature_code":"PPL",
    "gn:name":"Tummalap\u0101lem",
    "gn:population":0,
    "gn:timezone":"Asia/Kolkata",
    "iso:country":"IN",
    "name:hin_x_preferred":[
        "\u0924\u0941\u092e\u094d\u092e\u0932\u092a\u093e\u0932\u0946\u0902"
    ],
    "name:new_x_preferred":[
        "\u0924\u0941\u092e\u094d\u092e\u0932\u092a\u093e\u0932\u0946\u0902"
    ],
    "name:tel_x_preferred":[
        "\u0c24\u0c41\u0c2e\u0c4d\u0c2e\u0c32\u0c2a\u0c3e\u0c32\u0c46\u0c02"
    ],
    "wof:name":"Tummalapalem",
    "wof:placetype":"locality"
},
  "geometry": {"coordinates":[80.28390999999998,16.19896],"type":"Point"}
}