{
  "type": "Feature",
  "properties": {
    "iso:country":"IN",
    "ks:ks_name":"Nallikudi",
    "ks:ks_pop":110,
    "ks:ks_type":"HABITATION",
    "name:eng_x_preferred":[
        "Nallikudi"
    ],
    "wof:name":"Nallikudi",
    "wof:placetype":"locality",
    "wof:population":110
},
  "geometry": {"coordinates":[78.98056699999999,10.033563],"type":"Point"}
}