{
  "type": "Feature",
  "properties": {
    "gn:admin1_code":"36",
    "gn:admin2_code":"195.0",
    "gn:asciiname":"Horilpur",
    "gn:country_code":"IN",
    "gn:dem":76,
    "gn:feature_class":"P",
    "gn:feature_code":"PPL",
    "gn:name":"Horilpur",
    "gn:population":0,
    "gn:timezone":"Asia/Kolkata",
    "iso:country":"IN",
    "name:und_x_variant":[
        "Bhaw\u0101n\u012bpur"
    ],
    "wof:name":"Horilpur",
    "wof:placetype":"locality"
},
  "geometry": {"coordinates":[83.32784000000002,25.51333],"type":"Point"}
}