{
  "type": "Feature",
  "properties": {
    "gn:admin1_code":"24.0",
    "gn:admin2_code":"119.0",
    "gn:asciiname":"Bargaon",
    "gn:country_code":"IN",
    "gn:dem":476,
    "gn:feature_class":"P",
    "gn:feature_code":"PPL",
    "gn:name":"Bargaon",
    "gn:population":0,
    "gn:timezone":"Asia/Kolkata",
    "iso:country":"IN",
    "ks:ks_name":"Bargaon",
    "ks:ks_pop":3888,
    "ks:ks_type":"VILLAGE",
    "ks:ks_uagg_main":0,
    "name:eng_x_preferred":[
        "Bargaon"
    ],
    "wof:name":"Bargaon",
    "wof:placetype":"neighbourhood",
    "wof:population":3888
},
  "geometry": {"coordinates":[74.650642,26.396439],"type":"Point"}
}