{
  "type": "Feature",
  "properties": {
    "iso:country":"IN",
    "ks:ks_name":"Uttar Joykrishnapur",
    "ks:ks_pop":124,
    "ks:ks_type":"VILLAGE",
    "name:eng_x_preferred":[
        "Uttar Joykrishnapur"
    ],
    "wof:name":"Uttar Joykrishnapur",
    "wof:placetype":"locality",
    "wof:population":124
},
  "geometry": {"coordinates":[88.416096,22.098537],"type":"Point"}
}