{
  "type": "Feature",
  "properties": {
    "gn:admin1_code":"39.0",
    "gn:admin2_code":"64.0",
    "gn:asciiname":"Jaurasi",
    "gn:country_code":"IN",
    "gn:dem":1772,
    "gn:feature_class":"P",
    "gn:feature_code":"PPL",
    "gn:name":"Jaur\u0101si",
    "gn:population":0,
    "gn:timezone":"Asia/Kolkata",
    "iso:country":"IN",
    "name:hin_x_preferred":[
        "\u091c\u094c\u0930\u093e\u0938\u0940"
    ],
    "wof:name":"Jaurasi",
    "wof:placetype":"locality"
},
  "geometry": {"coordinates":[79.27849000000001,29.88141],"type":"Point"}
}