{
  "type": "Feature",
  "properties": {
    "iso:country":"IN",
    "ks:ks_alt_nam":"gopibandh",
    "ks:ks_name":"Gopibandh",
    "ks:ks_pop":620,
    "ks:ks_type":"HABITATION",
    "name:eng_x_preferred":[
        "Gopibandh"
    ],
    "wof:name":"Gopibandh",
    "wof:placetype":"locality",
    "wof:population":620
},
  "geometry": {"coordinates":[86.88258500000001,24.259949],"type":"Point"}
}