{
  "type": "Feature",
  "properties": {
    "gn:admin1_code":"2",
    "gn:admin2_code":"544.0",
    "gn:asciiname":"Dummagudri",
    "gn:country_code":"IN",
    "gn:dem":973,
    "gn:feature_class":"P",
    "gn:feature_code":"PPL",
    "gn:name":"Dummagudri",
    "gn:population":0,
    "gn:timezone":"Asia/Kolkata",
    "iso:country":"IN",
    "ks:ks_name":"Dummaguda",
    "ks:ks_pop":312,
    "ks:ks_type":"HABITATION",
    "name:eng_x_preferred":[
        "Dummaguda"
    ],
    "name:eng_x_variant":[
        "Dummagudri"
    ],
    "wof:name":"Dummaguda",
    "wof:placetype":"locality",
    "wof:population":312
},
  "geometry": {"coordinates":[82.868196,18.369657],"type":"Point"}
}