{
  "type": "Feature",
  "properties": {
    "iso:country":"IN",
    "name:eng_x_preferred":[
        "Bhairaun Ghat"
    ],
    "name:und_x_preferred":[
        "Bhairaun Gh\u0101t"
    ],
    "name:unk_x_variant":[
        "Bhairaun Ghat"
    ],
    "qs:gn_adm0_cc":"IN",
    "qs:gn_fcode":"PPLX",
    "qs:gn_local":1267995,
    "qs:gn_nam_loc":"kanpur",
    "qs:gn_namadm1":"36",
    "qs:gn_name":"Bhairaun Gh\u0101t",
    "qs:local_max":351,
    "qs:local_sum":546,
    "qs:localhoods":4,
    "qs:name":"Bhairaun Ghat",
    "qs:name_adm0":"India",
    "qs:name_adm1":"Uttar Pradesh",
    "qs:name_adm2":"Kanpur Nagar",
    "qs:name_local":"Kanpur",
    "qs:photo_max":8,
    "qs:photo_sum":16,
    "qs:placetype":"Suburb",
    "qs:quad_count":6,
    "qs:woe_adm0":23424848,
    "qs:woe_adm1":2345760,
    "qs:woe_adm2":12586757,
    "qs:woe_lau":0,
    "qs:woe_local":2295378,
    "qs:woe_ver":"7.10.0",
    "wof:lang":[
        "eng"
    ],
    "wof:name":"Bhairaun Ghat",
    "wof:placetype":"neighbourhood"
},
  "geometry": {"coordinates":[80.317612,26.473032],"type":"Point"}
}