{
  "type": "Feature",
  "properties": {
    "iso:country":"IN",
    "name:ara_x_preferred":[
        "\u0628\u0647\u064a\u0631\u0648\u0646 \u063a\u0627\u062a"
    ],
    "name:ben_bn_x_preferred":[
        "\u09ad\u09c8\u09b0\u09cb \u0998\u09be\u099f"
    ],
    "name:ben_in_x_preferred":[
        "\u09ad\u09c8\u09b0\u09cb \u0998\u09be\u099f"
    ],
    "name:eng_x_preferred":[
        "Bhairaun Ghat"
    ],
    "name:guj_x_preferred":[
        "\u0aad\u0ac8\u0ab0\u0ab5 \u0a98\u0abe\u0a9f"
    ],
    "name:hin_x_preferred":[
        "\u092d\u0948\u0930\u094b\u0902 \u0918\u093e\u091f"
    ],
    "name:kan_x_preferred":[
        "\u0cad\u0cc8\u0cb0\u0ccb\u0c82 \u0c98\u0cbe\u0c9f\u0ccd"
    ],
    "name:mal_x_preferred":[
        "\u0d2d\u0d48\u0d31\u0d57\u0d7b \u0d18\u0d1f\u0d4d\u0d1f\u0d4d"
    ],
    "name:mar_x_preferred":[
        "\u092d\u0948\u0930\u094c\u0928 \u0918\u093e\u091f"
    ],
    "name:pan_x_preferred":[
        "\u0a2d\u0a48\u0a30\u0a4b\u0a02 \u0a18\u0a3e\u0a1f"
    ],
    "name:tam_x_preferred":[
        "\u0baa\u0bc8\u0bb0\u0bcc\u0ba9\u0bcd \u0b95\u0bbe\u0b9f\u0bcd"
    ],
    "name:tel_x_preferred":[
        "\u0c2d\u0c3e\u0c2f\u0c3f\u0c30\u0c35\u0c41\u0c28\u0c4d \u0c18\u0c3e\u0c1f\u0c4d"
    ],
    "name:und_x_variant":[
        "Bhairaun Gh\u0101t"
    ],
    "name:urd_x_preferred":[
        "\u0628\u06be\u06cc\u0631\u0648\u06ba \u06af\u06be\u0627\u0679"
    ],
    "qs:gn_adm0_cc":"IN",
    "qs:gn_fcode":"PPLX",
    "qs:gn_local":1267995,
    "qs:gn_nam_loc":"kanpur",
    "qs:gn_namadm1":"36",
    "qs:gn_name":"Bhairaun Gh\u0101t",
    "qs:local_max":351,
    "qs:local_sum":546,
    "qs:localhoods":4,
    "qs:name":"Bhairaun Ghat",
    "qs:name_adm0":"India",
    "qs:name_adm1":"Uttar Pradesh",
    "qs:name_adm2":"Kanpur Nagar",
    "qs:name_local":"Kanpur",
    "qs:photo_max":8,
    "qs:photo_sum":16,
    "qs:placetype":"Suburb",
    "qs:quad_count":6,
    "qs:woe_adm0":23424848,
    "qs:woe_adm1":2345760,
    "qs:woe_adm2":12586757,
    "qs:woe_lau":0,
    "qs:woe_local":2295378,
    "qs:woe_ver":"7.10.0",
    "wof:lang":[
        "eng"
    ],
    "wof:name":"Bhairaun Ghat",
    "wof:placetype":"neighbourhood"
},
  "geometry": {"coordinates":[80.317612,26.473032],"type":"Point"}
}