{
  "type": "Feature",
  "properties": {
    "iso:country":"IN",
    "ks:ks_name":"Jor Ingti",
    "ks:ks_pop":88,
    "ks:ks_type":"HABITATION",
    "name:eng_x_preferred":[
        "Jor Ingti"
    ],
    "wof:name":"Jor Ingti",
    "wof:placetype":"locality",
    "wof:population":88
},
  "geometry": {"coordinates":[93.78210799999999,26.120557],"type":"Point"}
}