{
  "type": "Feature",
  "properties": {
    "iso:country":"IN",
    "ks:ks_name":"Doraga",
    "ks:ks_pop":443,
    "ks:ks_type":"VILLAGE",
    "name:eng_x_preferred":[
        "Doraga"
    ],
    "wof:name":"Doraga",
    "wof:placetype":"locality",
    "wof:population":443
},
  "geometry": {"coordinates":[80.17009899999999,29.386356],"type":"Point"}
}