{
  "type": "Feature",
  "properties": {
    "iso:country":"IN",
    "ks:ks_name":"Baulabeni",
    "ks:ks_pop":249,
    "ks:ks_type":"HABITATION",
    "name:eng_x_preferred":[
        "Baulabeni"
    ],
    "wof:name":"Baulabeni",
    "wof:placetype":"locality",
    "wof:population":249
},
  "geometry": {"coordinates":[87.03314899999999,21.482826],"type":"Point"}
}