{
  "type": "Feature",
  "properties": {
    "iso:country":"IN",
    "ks:ks_alt_nam":"Panitola Te.No 66 Fs.Gt.",
    "ks:ks_name":"Panitola Te.no 66 Fs.gt.",
    "ks:ks_pop":1752,
    "ks:ks_type":"HABITATION",
    "name:eng_x_preferred":[
        "Panitola Te.no 66 Fs.gt."
    ],
    "wof:name":"Panitola Te.no 66 Fs.gt.",
    "wof:placetype":"locality",
    "wof:population":1752
},
  "geometry": {"coordinates":[95.23894,27.476816],"type":"Point"}
}