{
  "type": "Feature",
  "properties": {
    "gn:admin1_code":"36",
    "gn:admin2_code":"136.0",
    "gn:asciiname":"Khushalpur",
    "gn:country_code":"IN",
    "gn:dem":201,
    "gn:feature_class":"P",
    "gn:feature_code":"PPL",
    "gn:name":"Khush\u0101lpur",
    "gn:population":0,
    "gn:timezone":"Asia/Kolkata",
    "iso:country":"IN",
    "wof:name":"Khushalpur",
    "wof:placetype":"locality"
},
  "geometry": {"coordinates":[78.94877,28.92026],"type":"Point"}
}