{
  "type": "Feature",
  "properties": {
    "iso:country":"IN",
    "ks:ks_alt_nam":"DUNGARSINGHPURA",
    "ks:ks_name":"Dungarsinghpura",
    "ks:ks_pop":4015,
    "ks:ks_type":"HABITATION",
    "name:eng_x_preferred":[
        "Dungarsinghpura"
    ],
    "wof:name":"Dungarsinghpura",
    "wof:placetype":"locality",
    "wof:population":4015
},
  "geometry": {"coordinates":[73.927164,29.743917],"type":"Point"}
}