{
  "type": "Feature",
  "properties": {
    "gn:admin1_code":"16.0",
    "gn:admin2_code":"509.0",
    "gn:asciiname":"Manoli",
    "gn:country_code":"IN",
    "gn:dem":259,
    "gn:feature_class":"P",
    "gn:feature_code":"PPL",
    "gn:name":"Manoli",
    "gn:population":0,
    "gn:timezone":"Asia/Kolkata",
    "iso:country":"IN",
    "wof:name":"Manoli",
    "wof:placetype":"locality"
},
  "geometry": {"coordinates":[79.16104,19.70383],"type":"Point"}
}