{
  "type": "Feature",
  "properties": {
    "iso:country":"IN",
    "ks:ks_name":"Anagalapura",
    "ks:ks_pop":392,
    "ks:ks_type":"VILLAGE",
    "ks:ks_uagg_main":0,
    "name:eng_x_preferred":[
        "Anagalapura"
    ],
    "wof:name":"Anagalapura",
    "wof:placetype":"locality",
    "wof:population":392
},
  "geometry": {"coordinates":[77.68209,13.064141],"type":"Point"}
}