{
  "type": "Feature",
  "properties": {
    "gn:admin1_code":"35.0",
    "gn:admin2_code":"444.0",
    "gn:asciiname":"Pipaliya Kadim",
    "gn:country_code":"IN",
    "gn:dem":467,
    "gn:feature_class":"P",
    "gn:feature_code":"PPL",
    "gn:name":"Pipaliya Kadim",
    "gn:population":0,
    "gn:timezone":"Asia/Kolkata",
    "iso:country":"IN",
    "wof:name":"Pipaliya Kadim",
    "wof:placetype":"locality"
},
  "geometry": {"coordinates":[77.44438000000002,23.48714],"type":"Point"}
}