{
  "type": "Feature",
  "properties": {
    "gn:admin1_code":"19",
    "gn:admin2_code":"563.0",
    "gn:asciiname":"Adkhalli",
    "gn:country_code":"IN",
    "gn:dem":532,
    "gn:feature_class":"P",
    "gn:feature_code":"PPL",
    "gn:name":"Adkhalli",
    "gn:population":0,
    "gn:timezone":"Asia/Kolkata",
    "iso:country":"IN",
    "ks:ks_name":"Adkalli",
    "ks:ks_pop":59,
    "ks:ks_type":"VILLAGE",
    "name:eng_x_preferred":[
        "Adkalli"
    ],
    "name:eng_x_variant":[
        "Adkhalli"
    ],
    "wof:name":"Adkalli",
    "wof:placetype":"locality",
    "wof:population":59
},
  "geometry": {"coordinates":[74.817363,14.519423],"type":"Point"}
}