{
  "type": "Feature",
  "properties": {
    "iso:country":"IN",
    "ks:ks_name":"Narayanpur",
    "ks:ks_pop":477,
    "ks:ks_type":"VILLAGE",
    "name:eng_x_preferred":[
        "Narayanpur"
    ],
    "name:hin_x_preferred":[
        "\u0928\u093e\u0930\u093e\u092f\u0923\u092a\u0941\u0930"
    ],
    "wof:name":"Narayanpur",
    "wof:placetype":"locality",
    "wof:population":477
},
  "geometry": {"coordinates":[85.25827700000001,26.184799],"type":"Point"}
}