{
  "type": "Feature",
  "properties": {
    "gn:admin1_code":"11.0",
    "gn:admin2_code":"27.0",
    "gn:asciiname":"Jurn Thach",
    "gn:country_code":"IN",
    "gn:dem":2183,
    "gn:feature_class":"P",
    "gn:feature_code":"PPL",
    "gn:name":"Jurn Th\u0101ch",
    "gn:population":0,
    "gn:timezone":"Asia/Kolkata",
    "iso:country":"IN",
    "wof:name":"Jurn Thach",
    "wof:placetype":"locality"
},
  "geometry": {"coordinates":[77.16686,31.62746],"type":"Point"}
}