{
  "type": "Feature",
  "properties": {
    "iso:country":"IN",
    "qs:name":"Khapari",
    "qs:name_adm0":"India",
    "qs:name_adm1":"Maharashtra",
    "qs:photos":42,
    "qs:photos_1k":9,
    "qs:photos_9k":1,
    "qs:photos_9r":2,
    "qs:photos_all":42,
    "qs:photos_sr":2,
    "qs:placetype":"Town",
    "qs:pop_sr":"0",
    "wof:name":"Khapari",
    "wof:placetype":"locality"
},
  "geometry": {"coordinates":[79.05256300000001,21.0521535],"type":"Point"}
}