{
  "type": "Feature",
  "properties": {
    "iso:country":"IN",
    "ks:ks_name":"Manpita",
    "ks:ks_pop":1415,
    "ks:ks_type":"VILLAGE",
    "name:eng_x_preferred":[
        "Manpita"
    ],
    "wof:name":"Manpita",
    "wof:placetype":"neighbourhood",
    "wof:population":1415
},
  "geometry": {"coordinates":[86.28759100000001,22.776944],"type":"Point"}
}