{
  "type": "Feature",
  "properties": {
    "iso:country":"IN",
    "ks:ks_name":"Bhabala",
    "ks:ks_pop":398,
    "ks:ks_type":"HABITATION",
    "name:eng_x_preferred":[
        "Bhabala"
    ],
    "wof:name":"Bhabala",
    "wof:placetype":"locality",
    "wof:population":398
},
  "geometry": {"coordinates":[95.802419,27.834813],"type":"Point"}
}