{
  "type": "Feature",
  "properties": {
    "iso:country":"IN",
    "ks:ks_alt_nam":"Pundurl\u0101wa",
    "ks:ks_name":"Pundurlawa",
    "ks:ks_pop":74,
    "ks:ks_type":"VILLAGE",
    "name:eng_x_preferred":[
        "Pundurlawa"
    ],
    "name:eng_x_variant":[
        "Pundurl\u0101wa"
    ],
    "wof:name":"Pundurlawa",
    "wof:placetype":"locality",
    "wof:population":74
},
  "geometry": {"coordinates":[84.856127,23.830949],"type":"Point"}
}