{
  "type": "Feature",
  "properties": {
    "iso:country":"IN",
    "ks:ks_name":"Hemmannu",
    "ks:ks_pop":328,
    "ks:ks_type":"HABITATION",
    "name:eng_x_preferred":[
        "Hemmannu"
    ],
    "wof:name":"Hemmannu",
    "wof:placetype":"locality",
    "wof:population":328
},
  "geometry": {"coordinates":[75.019293,13.425502],"type":"Point"}
}