{
  "type": "Feature",
  "properties": {
    "iso:country":"IN",
    "ks:ks_name":"Kummaripeta",
    "ks:ks_pop":512,
    "ks:ks_type":"HABITATION",
    "name:eng_x_preferred":[
        "Kummaripeta"
    ],
    "wof:name":"Kummaripeta",
    "wof:placetype":"locality",
    "wof:population":512
},
  "geometry": {"coordinates":[83.99029400000001,18.42116],"type":"Point"}
}