{
  "type": "Feature",
  "properties": {
    "iso:country":"IN",
    "ks:ks_name":"Manikpur",
    "ks:ks_pop":928,
    "ks:ks_type":"VILLAGE",
    "ks:ks_uagg_main":0,
    "name:eng_x_preferred":[
        "Manikpur"
    ],
    "wof:name":"Manikpur",
    "wof:placetype":"neighbourhood",
    "wof:population":928
},
  "geometry": {"coordinates":[87.76033,25.005004],"type":"Point"}
}