{
  "type": "Feature",
  "properties": {
    "gn:admin1_code":"11",
    "gn:admin2_code":"23.0",
    "gn:asciiname":"Duga Badhrua",
    "gn:country_code":"IN",
    "gn:dem":3815,
    "gn:feature_class":"P",
    "gn:feature_code":"PPL",
    "gn:name":"Duga Badhrua",
    "gn:population":0,
    "gn:timezone":"Asia/Kolkata",
    "iso:country":"IN",
    "wof:name":"Duga Badhrua",
    "wof:placetype":"locality"
},
  "geometry": {"coordinates":[76.34586999999998,32.62995],"type":"Point"}
}