{
  "type": "Feature",
  "properties": {
    "iso:country":"IN",
    "ks:ks_name":"Barmer Gadan",
    "ks:ks_pop":1606,
    "ks:ks_type":"HABITATION",
    "name:eng_x_preferred":[
        "Barmer Gadan"
    ],
    "wof:name":"Barmer Gadan",
    "wof:placetype":"locality",
    "wof:population":1606
},
  "geometry": {"coordinates":[71.36465,25.692686],"type":"Point"}
}