{
  "type": "Feature",
  "properties": {
    "iso:country":"IN",
    "ks:ks_alt_nam":"Chambatu mukku",
    "ks:ks_name":"Chambatu Mukku",
    "ks:ks_pop":412,
    "ks:ks_type":"HABITATION",
    "ks:ks_uagg_main":0,
    "name:eng_x_preferred":[
        "Chambatu Mukku"
    ],
    "wof:name":"Chambatu Mukku",
    "wof:placetype":"neighbourhood",
    "wof:population":412
},
  "geometry": {"coordinates":[75.870598,11.369615],"type":"Point"}
}