{
  "type": "Feature",
  "properties": {
    "iso:country":"IN",
    "ks:ks_name":"Moyyalla Mamidi",
    "ks:ks_pop":15,
    "ks:ks_type":"HABITATION",
    "name:eng_x_preferred":[
        "Moyyalla Mamidi"
    ],
    "wof:name":"Moyyalla Mamidi",
    "wof:placetype":"locality",
    "wof:population":15
},
  "geometry": {"coordinates":[82.45292999999999,18.268012],"type":"Point"}
}