{
  "type": "Feature",
  "properties": {
    "gn:admin1_code":"19.0",
    "gn:admin2_code":"574.0",
    "gn:asciiname":"Mattigodu",
    "gn:country_code":"IN",
    "gn:dem":823,
    "gn:feature_class":"P",
    "gn:feature_code":"PPL",
    "gn:name":"Mattigodu",
    "gn:population":0,
    "gn:timezone":"Asia/Kolkata",
    "iso:country":"IN",
    "wof:name":"Mattigodu",
    "wof:placetype":"locality"
},
  "geometry": {"coordinates":[76.10689000000001,12.59331],"type":"Point"}
}