{
  "type": "Feature",
  "properties": {
    "gn:admin1_code":"39.0",
    "gn:admin2_code":"66.0",
    "gn:asciiname":"Tulsipur Dani",
    "gn:country_code":"IN",
    "gn:dem":292,
    "gn:feature_class":"P",
    "gn:feature_code":"PPL",
    "gn:name":"Tuls\u012bpur Dani",
    "gn:population":0,
    "gn:timezone":"Asia/Kolkata",
    "iso:country":"IN",
    "ks:ks_alt_nam":"Tuls\u012bpur Dani",
    "ks:ks_name":"Tulsipur Dani",
    "ks:ks_type":"VILLAGE",
    "ks:ks_uagg_main":0,
    "name:eng_x_preferred":[
        "Tulsipur Dani"
    ],
    "name:eng_x_variant":[
        "Tuls\u012bpur Dani"
    ],
    "wof:name":"Tulsipur Dani",
    "wof:placetype":"neighbourhood"
},
  "geometry": {"coordinates":[79.07473400000001,29.332291],"type":"Point"}
}