{
  "type": "Feature",
  "properties": {
    "iso:country":"IN",
    "ks:ks_name":"Baddadka",
    "ks:ks_pop":554,
    "ks:ks_type":"HABITATION",
    "name:eng_x_preferred":[
        "Baddadka"
    ],
    "wof:name":"Baddadka",
    "wof:placetype":"locality",
    "wof:population":554
},
  "geometry": {"coordinates":[75.393961,12.509673],"type":"Point"}
}