{
  "type": "Feature",
  "properties": {
    "gn:admin1_code":"21",
    "gn:admin2_code":"388.0",
    "gn:asciiname":"Nuapalli",
    "gn:country_code":"IN",
    "gn:dem":170,
    "gn:feature_class":"P",
    "gn:feature_code":"PPL",
    "gn:name":"Nu\u0101palli",
    "gn:population":0,
    "gn:timezone":"Asia/Kolkata",
    "iso:country":"IN",
    "wof:name":"Nuapalli",
    "wof:placetype":"locality"
},
  "geometry": {"coordinates":[84.92697,19.85425],"type":"Point"}
}