{
  "type": "Feature",
  "properties": {
    "gn:admin1_code":"36.0",
    "gn:admin2_code":"154.0",
    "gn:asciiname":"Beni Madho",
    "gn:country_code":"IN",
    "gn:dem":123,
    "gn:feature_class":"P",
    "gn:feature_code":"PPL",
    "gn:name":"Beni M\u0101dho",
    "gn:population":0,
    "gn:timezone":"Asia/Kolkata",
    "iso:country":"IN",
    "wof:name":"Beni Madho",
    "wof:placetype":"locality"
},
  "geometry": {"coordinates":[80.80062,27.19645],"type":"Point"}
}