{
  "type": "Feature",
  "properties": {
    "gn:admin1_code":"24.0",
    "gn:admin2_code":"101",
    "gn:asciiname":"Hadda",
    "gn:country_code":"IN",
    "gn:dem":275,
    "gn:feature_class":"P",
    "gn:feature_code":"PPL",
    "gn:name":"Hadda",
    "gn:population":0,
    "gn:timezone":"Asia/Kolkata",
    "iso:country":"IN",
    "name:deu_x_preferred":[
        "Hadda"
    ],
    "name:nld_x_preferred":[
        "Hadda"
    ],
    "name:slk_x_preferred":[
        "Hadda"
    ],
    "wof:name":"Hadda",
    "wof:placetype":"locality"
},
  "geometry": {"coordinates":[72.88064,27.63818],"type":"Point"}
}