{
  "type": "Feature",
  "properties": {
    "iso:country":"IN",
    "ks:ks_name":"Gopinathpur",
    "ks:ks_pop":655,
    "ks:ks_type":"VILLAGE",
    "name:eng_x_preferred":[
        "Gopinathpur"
    ],
    "wof:name":"Gopinathpur",
    "wof:placetype":"locality",
    "wof:population":655
},
  "geometry": {"coordinates":[87.221324,23.058036],"type":"Point"}
}