{
  "type": "Feature",
  "properties": {
    "iso:country":"IN",
    "ks:ks_name":"Bashbari Grant",
    "ks:ks_pop":1253,
    "ks:ks_type":"HABITATION",
    "name:eng_x_preferred":[
        "Bashbari Grant"
    ],
    "wof:name":"Bashbari Grant",
    "wof:placetype":"locality",
    "wof:population":1253
},
  "geometry": {"coordinates":[92.54145800000001,24.735806],"type":"Point"}
}