{
  "type": "Feature",
  "properties": {
    "gn:admin1_code":"25.0",
    "gn:admin2_code":"605.0",
    "gn:asciiname":"Sengalnatham",
    "gn:country_code":"IN",
    "gn:dem":198,
    "gn:feature_class":"P",
    "gn:feature_code":"PPL",
    "gn:name":"Sengalnatham",
    "gn:population":0,
    "gn:timezone":"Asia/Kolkata",
    "iso:country":"IN",
    "wof:name":"Sengalnatham",
    "wof:placetype":"locality"
},
  "geometry": {"coordinates":[79.33219,13.05498],"type":"Point"}
}