{
  "type": "Feature",
  "properties": {
    "gn:admin1_code":"2.0",
    "gn:admin2_code":"553.0",
    "gn:asciiname":"Brahmanapalle",
    "gn:country_code":"IN",
    "gn:dem":504,
    "gn:feature_class":"P",
    "gn:feature_code":"PPL",
    "gn:name":"Br\u0101hmanapalle",
    "gn:population":0,
    "gn:timezone":"Asia/Kolkata",
    "iso:country":"IN",
    "ks:ks_alt_nam":"BRAMHANAPALLE",
    "ks:ks_name":"Bramhanapalle",
    "ks:ks_pop":258,
    "ks:ks_type":"HABITATION",
    "name:eng_x_preferred":[
        "Bramhanapalle"
    ],
    "name:eng_x_variant":[
        "Brahmanapalle"
    ],
    "wof:name":"Bramhanapalle",
    "wof:placetype":"locality",
    "wof:population":258
},
  "geometry": {"coordinates":[77.83214700000001,14.266975],"type":"Point"}
}