{
  "type": "Feature",
  "properties": {
    "gn:admin1_code":"28.0",
    "gn:admin2_code":"334.0",
    "gn:asciiname":"Bahutal",
    "gn:country_code":"IN",
    "gn:dem":29,
    "gn:feature_class":"P",
    "gn:feature_code":"PPL",
    "gn:name":"Bahut\u0101l",
    "gn:population":0,
    "gn:timezone":"Asia/Kolkata",
    "iso:country":"IN",
    "ks:ks_name":"Bahutali",
    "ks:ks_pop":7095,
    "ks:ks_type":"VILLAGE",
    "ks:ks_uagg_main":0,
    "name:eng_x_preferred":[
        "Bahutali"
    ],
    "wof:name":"Bahutali",
    "wof:placetype":"neighbourhood",
    "wof:population":7095
},
  "geometry": {"coordinates":[87.893647,24.561805],"type":"Point"}
}