{
  "type": "Feature",
  "properties": {
    "iso:country":"IN",
    "ks:ks_alt_nam":"NAV TOLA",
    "ks:ks_name":"Nav Tola",
    "ks:ks_pop":454,
    "ks:ks_type":"HABITATION",
    "name:eng_x_preferred":[
        "Nav Tola"
    ],
    "wof:name":"Nav Tola",
    "wof:placetype":"locality",
    "wof:population":454
},
  "geometry": {"coordinates":[86.42252999999999,26.263862],"type":"Point"}
}