{
  "type": "Feature",
  "properties": {
    "gn:admin1_code":"39",
    "gn:admin2_code":"61.0",
    "gn:asciiname":"Painwalgaon",
    "gn:country_code":"IN",
    "gn:dem":1153,
    "gn:feature_class":"P",
    "gn:feature_code":"PPL",
    "gn:name":"Painw\u0101lgaon",
    "gn:population":0,
    "gn:timezone":"Asia/Kolkata",
    "iso:country":"IN",
    "ks:ks_name":"Painul Gaon",
    "ks:ks_pop":290,
    "ks:ks_type":"VILLAGE",
    "name:eng_x_preferred":[
        "Painul Gaon"
    ],
    "name:eng_x_variant":[
        "Painwalgaon"
    ],
    "wof:name":"Painul Gaon",
    "wof:placetype":"locality",
    "wof:population":290
},
  "geometry": {"coordinates":[78.803957,29.764145],"type":"Point"}
}