{
  "type": "Feature",
  "properties": {
    "gn:admin1_code":"39",
    "gn:admin2_code":"61.0",
    "gn:asciiname":"Painwalgaon",
    "gn:country_code":"IN",
    "gn:dem":1153,
    "gn:feature_class":"P",
    "gn:feature_code":"PPL",
    "gn:name":"Painw\u0101lgaon",
    "gn:population":0,
    "gn:timezone":"Asia/Kolkata",
    "iso:country":"IN",
    "wof:name":"Painwalgaon",
    "wof:placetype":"locality"
},
  "geometry": {"coordinates":[78.80569,29.76493],"type":"Point"}
}