{
  "type": "Feature",
  "properties": {
    "iso:country":"IN",
    "ks:ks_name":"Kamalabandha",
    "ks:ks_pop":16,
    "ks:ks_type":"HABITATION",
    "name:eng_x_preferred":[
        "Kamalabandha"
    ],
    "wof:name":"Kamalabandha",
    "wof:placetype":"locality",
    "wof:population":16
},
  "geometry": {"coordinates":[82.74722300000001,18.420351],"type":"Point"}
}