{
  "type": "Feature",
  "properties": {
    "iso:country":"IN",
    "ks:ks_name":"Gamharo",
    "ks:ks_pop":369,
    "ks:ks_type":"HABITATION",
    "name:eng_x_preferred":[
        "Gamharo"
    ],
    "wof:name":"Gamharo",
    "wof:placetype":"locality",
    "wof:population":369
},
  "geometry": {"coordinates":[87.418948,25.142098],"type":"Point"}
}