{
  "type": "Feature",
  "properties": {
    "iso:country":"IN",
    "ks:ks_alt_nam":"BELTAN KA PURA",
    "ks:ks_name":"Beltan Ka Pura",
    "ks:ks_pop":229,
    "ks:ks_type":"HABITATION",
    "ks:ks_uagg_main":0,
    "name:eng_x_preferred":[
        "Beltan Ka Pura"
    ],
    "wof:name":"Beltan Ka Pura",
    "wof:placetype":"neighbourhood",
    "wof:population":229
},
  "geometry": {"coordinates":[81.42688,25.33338],"type":"Point"}
}