{
  "type": "Feature",
  "properties": {
    "iso:country":"IN",
    "ks:ks_name":"Sreepuria",
    "ks:ks_pop":206,
    "ks:ks_type":"HABITATION",
    "name:eng_x_preferred":[
        "Sreepuria"
    ],
    "wof:name":"Sreepuria",
    "wof:placetype":"locality",
    "wof:population":206
},
  "geometry": {"coordinates":[95.195201,27.204539],"type":"Point"}
}