{
  "type": "Feature",
  "properties": {
    "iso:country":"IN",
    "ks:ks_name":"Keragadde",
    "ks:ks_pop":19,
    "ks:ks_type":"HABITATION",
    "name:eng_x_preferred":[
        "Keragadde"
    ],
    "wof:name":"Keragadde",
    "wof:placetype":"locality",
    "wof:population":19
},
  "geometry": {"coordinates":[74.962458,14.626163],"type":"Point"}
}