{
  "type": "Feature",
  "properties": {
    "iso:country":"IN",
    "ks:ks_name":"Badhurnagar",
    "ks:ks_pop":134,
    "ks:ks_type":"HABITATION",
    "name:eng_x_preferred":[
        "Badhurnagar"
    ],
    "wof:name":"Badhurnagar",
    "wof:placetype":"locality",
    "wof:population":134
},
  "geometry": {"coordinates":[80.280556,26.366111],"type":"Point"}
}