{
  "type": "Feature",
  "properties": {
    "iso:country":"IN",
    "ks:ks_name":"Bandarpahari",
    "ks:ks_pop":75,
    "ks:ks_type":"VILLAGE",
    "name:eng_x_preferred":[
        "Bandarpahari"
    ],
    "wof:name":"Bandarpahari",
    "wof:placetype":"locality",
    "wof:population":75
},
  "geometry": {"coordinates":[86.84799,24.387593],"type":"Point"}
}