{
  "type": "Feature",
  "properties": {
    "iso:country":"IN",
    "ks:ks_name":"Muraurf Matra",
    "ks:ks_pop":126,
    "ks:ks_type":"VILLAGE",
    "ks:ks_uagg_main":0,
    "name:eng_x_preferred":[
        "Muraurf Matra"
    ],
    "wof:name":"Muraurf Matra",
    "wof:placetype":"neighbourhood",
    "wof:population":126
},
  "geometry": {"coordinates":[88.030276,25.661325],"type":"Point"}
}