{
  "type": "Feature",
  "properties": {
    "gn:admin1_code":"37.0",
    "gn:admin2_code":"410.0",
    "gn:asciiname":"Shuklabhata",
    "gn:country_code":"IN",
    "gn:dem":248,
    "gn:feature_class":"P",
    "gn:feature_code":"PPL",
    "gn:name":"Shuklabhata",
    "gn:population":0,
    "gn:timezone":"Asia/Kolkata",
    "iso:country":"IN",
    "wof:name":"Shuklabhata",
    "wof:placetype":"locality"
},
  "geometry": {"coordinates":[82.15926,21.69292],"type":"Point"}
}