{
  "type": "Feature",
  "properties": {
    "iso:country":"IN",
    "ks:ks_alt_nam":"Mijika TE 135 243",
    "ks:ks_name":"Mijika Te 135 243",
    "ks:ks_pop":179,
    "ks:ks_type":"HABITATION",
    "name:eng_x_preferred":[
        "Mijika Te 135 243"
    ],
    "wof:name":"Mijika Te 135 243",
    "wof:placetype":"locality",
    "wof:population":179
},
  "geometry": {"coordinates":[93.17571,26.84665],"type":"Point"}
}