{
  "type": "Feature",
  "properties": {
    "iso:country":"IN",
    "ks:ks_name":"Kodelguda",
    "ks:ks_pop":105,
    "ks:ks_type":"HABITATION",
    "name:eng_x_preferred":[
        "Kodelguda"
    ],
    "wof:name":"Kodelguda",
    "wof:placetype":"locality",
    "wof:population":105
},
  "geometry": {"coordinates":[81.600222,18.050802],"type":"Point"}
}