{
  "type": "Feature",
  "properties": {
    "gn:admin1_code":"35",
    "gn:admin2_code":"428.0",
    "gn:asciiname":"Silgi",
    "gn:country_code":"IN",
    "gn:dem":497,
    "gn:feature_class":"P",
    "gn:feature_code":"PPL",
    "gn:name":"Silgi",
    "gn:population":0,
    "gn:timezone":"Asia/Kolkata",
    "iso:country":"IN",
    "wof:name":"Silgi",
    "wof:placetype":"locality"
},
  "geometry": {"coordinates":[79.47481999999999,23.28211],"type":"Point"}
}