{
  "type": "Feature",
  "properties": {
    "gn:admin1_code":"25",
    "gn:admin2_code":"604.0",
    "gn:asciiname":"Chettipattu Ramayankuppam",
    "gn:country_code":"IN",
    "gn:dem":19,
    "gn:feature_class":"P",
    "gn:feature_code":"PPL",
    "gn:name":"Chettipattu R\u0101mayankuppam",
    "gn:population":0,
    "gn:timezone":"Asia/Kolkata",
    "iso:country":"IN",
    "wof:name":"Chettipattu Ramayankuppam",
    "wof:placetype":"neighbourhood"
},
  "geometry": {"coordinates":[80.14375,12.70447],"type":"Point"}
}