{
  "type": "Feature",
  "properties": {
    "iso:country":"IN",
    "ks:ks_name":"Holegadde",
    "ks:ks_pop":152,
    "ks:ks_type":"HABITATION",
    "name:eng_x_preferred":[
        "Holegadde"
    ],
    "wof:name":"Holegadde",
    "wof:placetype":"locality",
    "wof:population":152
},
  "geometry": {"coordinates":[75.226665,13.526254],"type":"Point"}
}