{
  "type": "Feature",
  "properties": {
    "iso:country":"IN",
    "ks:ks_name":"Bagrakonda",
    "ks:ks_pop":35,
    "ks:ks_type":"VILLAGE",
    "name:eng_x_preferred":[
        "Bagrakonda"
    ],
    "wof:name":"Bagrakonda",
    "wof:placetype":"locality",
    "wof:population":35
},
  "geometry": {"coordinates":[87.105273,23.306112],"type":"Point"}
}