{
  "type": "Feature",
  "properties": {
    "gn:admin1_code":"35",
    "gn:admin2_code":"418.0",
    "gn:asciiname":"Baroda Khurd",
    "gn:country_code":"IN",
    "gn:dem":407,
    "gn:feature_class":"P",
    "gn:feature_code":"PPL",
    "gn:name":"Baroda Khurd",
    "gn:population":0,
    "gn:timezone":"Asia/Kolkata",
    "iso:country":"IN",
    "wof:name":"Baroda Khurd",
    "wof:placetype":"locality"
},
  "geometry": {"coordinates":[77.49449,25.87995],"type":"Point"}
}