{
  "type": "Feature",
  "properties": {
    "gn:admin1_code":"35.0",
    "gn:admin2_code":"421.0",
    "gn:asciiname":"Fatehpur",
    "gn:country_code":"IN",
    "gn:dem":239,
    "gn:feature_class":"P",
    "gn:feature_code":"PPL",
    "gn:name":"Fatehpur",
    "gn:population":0,
    "gn:timezone":"Asia/Kolkata",
    "iso:country":"IN",
    "wof:name":"Fatehpur",
    "wof:placetype":"locality"
},
  "geometry": {"coordinates":[78.2217,25.96954],"type":"Point"}
}