{
  "type": "Feature",
  "properties": {
    "iso:country":"IN",
    "ks:ks_name":"Bayasi",
    "ks:ks_pop":385,
    "ks:ks_type":"HABITATION",
    "name:eng_x_preferred":[
        "Bayasi"
    ],
    "wof:name":"Bayasi",
    "wof:placetype":"locality",
    "wof:population":385
},
  "geometry": {"coordinates":[83.205862,26.009866],"type":"Point"}
}