{
  "type": "Feature",
  "properties": {
    "gn:admin1_code":"37",
    "gn:admin2_code":"404.0",
    "gn:asciiname":"Maheshpur",
    "gn:country_code":"IN",
    "gn:dem":335,
    "gn:feature_class":"P",
    "gn:feature_code":"PPL",
    "gn:name":"Maheshpur",
    "gn:population":0,
    "gn:timezone":"Asia/Kolkata",
    "iso:country":"IN",
    "name:ceb_x_preferred":[
        "Maheshpur"
    ],
    "name:fra_x_preferred":[
        "Maheshpur"
    ],
    "name:hin_x_preferred":[
        "\u092e\u0939\u0947\u0936\u092a\u0941\u0930 \u0968"
    ],
    "name:new_x_preferred":[
        "\u092e\u0939\u0947\u0936\u092a\u0941\u0930 \u0917\u093e\u0935\u093f\u0938"
    ],
    "name:pol_x_preferred":[
        "Maheshpur"
    ],
    "name:swe_x_preferred":[
        "Maheshpur"
    ],
    "wof:name":"Maheshpur",
    "wof:placetype":"locality"
},
  "geometry": {"coordinates":[82.55813000000001,22.52166],"type":"Point"}
}