{
  "type": "Feature",
  "properties": {
    "iso:country":"IN",
    "ks:ks_name":"N. Banjara",
    "ks:ks_pop":118,
    "ks:ks_type":"HABITATION",
    "name:eng_x_preferred":[
        "N. Banjara"
    ],
    "wof:name":"N. Banjara",
    "wof:placetype":"locality",
    "wof:population":118
},
  "geometry": {"coordinates":[78.73049,26.952073],"type":"Point"}
}