{
  "type": "Feature",
  "properties": {
    "iso:country":"IN",
    "ks:ks_name":"Chaurasipur",
    "ks:ks_pop":54,
    "ks:ks_type":"VILLAGE",
    "name:eng_x_preferred":[
        "Chaurasipur"
    ],
    "wof:name":"Chaurasipur",
    "wof:placetype":"locality",
    "wof:population":54
},
  "geometry": {"coordinates":[83.677544,20.907785],"type":"Point"}
}