{
  "type": "Feature",
  "properties": {
    "iso:country":"IN",
    "ks:ks_name":"Morliken",
    "ks:ks_pop":393,
    "ks:ks_type":"HABITATION",
    "name:eng_x_preferred":[
        "Morliken"
    ],
    "wof:name":"Morliken",
    "wof:placetype":"locality",
    "wof:population":393
},
  "geometry": {"coordinates":[86.852878,24.656732],"type":"Point"}
}