{
  "type": "Feature",
  "properties": {
    "gn:admin1_code":"25.0",
    "gn:admin2_code":"626.0",
    "gn:asciiname":"Panaikulam",
    "gn:country_code":"IN",
    "gn:dem":5,
    "gn:feature_class":"P",
    "gn:feature_code":"PPL",
    "gn:name":"Panaikulam",
    "gn:population":0,
    "gn:timezone":"Asia/Kolkata",
    "iso:country":"IN",
    "wof:name":"Panaikulam",
    "wof:placetype":"neighbourhood"
},
  "geometry": {"coordinates":[78.95402,9.37565],"type":"Point"}
}