{
  "type": "Feature",
  "properties": {
    "iso:country":"IN",
    "ks:ks_name":"Keshapura Juna",
    "ks:ks_pop":56,
    "ks:ks_type":"HABITATION",
    "name:eng_x_preferred":[
        "Keshapura Juna"
    ],
    "wof:name":"Keshapura Juna",
    "wof:placetype":"locality",
    "wof:population":56
},
  "geometry": {"coordinates":[73.190944,23.60475],"type":"Point"}
}