{
  "type": "Feature",
  "properties": {
    "iso:country":"IN",
    "ks:ks_name":"Piperadih",
    "ks:ks_pop":357,
    "ks:ks_type":"HABITATION",
    "name:eng_x_preferred":[
        "Piperadih"
    ],
    "wof:name":"Piperadih",
    "wof:placetype":"locality",
    "wof:population":357
},
  "geometry": {"coordinates":[86.75639,24.624667],"type":"Point"}
}