{
  "type": "Feature",
  "properties": {
    "iso:country":"IN",
    "ks:ks_name":"Ekanathwadi",
    "ks:ks_pop":332,
    "ks:ks_type":"HABITATION",
    "name:eng_x_preferred":[
        "Ekanathwadi"
    ],
    "wof:name":"Ekanathwadi",
    "wof:placetype":"locality",
    "wof:population":332
},
  "geometry": {"coordinates":[73.861296,19.237491],"type":"Point"}
}