{
  "type": "Feature",
  "properties": {
    "iso:country":"IN",
    "ks:ks_name":"Kallahalli",
    "ks:ks_pop":50,
    "ks:ks_type":"HABITATION",
    "name:eng_x_preferred":[
        "Kallahalli"
    ],
    "wof:name":"Kallahalli",
    "wof:placetype":"locality",
    "wof:population":50
},
  "geometry": {"coordinates":[74.97832,14.1561],"type":"Point"}
}