{
  "type": "Feature",
  "properties": {
    "iso:country":"IN",
    "ks:ks_name":"Muddingadde",
    "ks:ks_pop":64,
    "ks:ks_type":"HABITATION",
    "name:eng_x_preferred":[
        "Muddingadde"
    ],
    "wof:name":"Muddingadde",
    "wof:placetype":"locality",
    "wof:population":64
},
  "geometry": {"coordinates":[74.82025299999999,14.906524],"type":"Point"}
}