{
  "type": "Feature",
  "properties": {
    "iso:country":"IN",
    "ks:ks_name":"Jatradih",
    "ks:ks_pop":111,
    "ks:ks_type":"HABITATION",
    "name:eng_x_preferred":[
        "Jatradih"
    ],
    "wof:name":"Jatradih",
    "wof:placetype":"locality",
    "wof:population":111
},
  "geometry": {"coordinates":[86.33130199999999,24.054398],"type":"Point"}
}