{
  "type": "Feature",
  "properties": {
    "iso:country":"IN",
    "ks:ks_name":"Nava Gamthan",
    "ks:ks_pop":188,
    "ks:ks_type":"HABITATION",
    "ks:ks_uagg_main":0,
    "name:eng_x_preferred":[
        "Nava Gamthan"
    ],
    "wof:name":"Nava Gamthan",
    "wof:placetype":"neighbourhood",
    "wof:population":188
},
  "geometry": {"coordinates":[73.419222,21.083556],"type":"Point"}
}