{
  "type": "Feature",
  "properties": {
    "gn:admin1_code":"11.0",
    "gn:admin2_code":"33.0",
    "gn:asciiname":"Bhatirsar",
    "gn:country_code":"IN",
    "gn:dem":2964,
    "gn:feature_class":"P",
    "gn:feature_code":"PPL",
    "gn:name":"Bhatirs\u0101r",
    "gn:population":0,
    "gn:timezone":"Asia/Kolkata",
    "iso:country":"IN",
    "wof:name":"Bhatirsar",
    "wof:placetype":"locality"
},
  "geometry": {"coordinates":[78.0819,31.27024],"type":"Point"}
}