{
  "type": "Feature",
  "properties": {
    "iso:country":"IN",
    "ks:ks_name":"Bodikonda",
    "ks:ks_pop":31,
    "ks:ks_type":"HABITATION",
    "name:eng_x_preferred":[
        "Bodikonda"
    ],
    "wof:name":"Bodikonda",
    "wof:placetype":"locality",
    "wof:population":31
},
  "geometry": {"coordinates":[83.07719400000001,18.422961],"type":"Point"}
}