{
  "type": "Feature",
  "properties": {
    "gn:admin1_code":"2",
    "gn:admin2_code":"544.0",
    "gn:asciiname":"Geddavalasa",
    "gn:country_code":"IN",
    "gn:dem":1078,
    "gn:feature_class":"P",
    "gn:feature_code":"PPL",
    "gn:name":"Geddavalasa",
    "gn:population":0,
    "gn:timezone":"Asia/Kolkata",
    "iso:country":"IN",
    "ks:ks_name":"Gaddavalasa",
    "ks:ks_pop":133,
    "ks:ks_type":"HABITATION",
    "name:eng_x_preferred":[
        "Gaddavalasa"
    ],
    "name:eng_x_variant":[
        "Geddavalasa"
    ],
    "wof:name":"Gaddavalasa",
    "wof:placetype":"locality",
    "wof:population":133
},
  "geometry": {"coordinates":[82.78974700000001,18.091006],"type":"Point"}
}