{
  "type": "Feature",
  "properties": {
    "iso:country":"IN",
    "ks:ks_name":"Cherimthepi",
    "ks:ks_pop":343,
    "ks:ks_type":"HABITATION",
    "name:eng_x_preferred":[
        "Cherimthepi"
    ],
    "wof:name":"Cherimthepi",
    "wof:placetype":"locality",
    "wof:population":343
},
  "geometry": {"coordinates":[92.747068,25.67775],"type":"Point"}
}