{
  "type": "Feature",
  "properties": {
    "iso:country":"IN",
    "ks:ks_alt_nam":"Nandi vattam",
    "ks:ks_name":"Nandi Vattam",
    "ks:ks_pop":167,
    "ks:ks_type":"HABITATION",
    "ks:ks_uagg_main":0,
    "name:eng_x_preferred":[
        "Nandi Vattam"
    ],
    "wof:name":"Nandi Vattam",
    "wof:placetype":"neighbourhood",
    "wof:population":167
},
  "geometry": {"coordinates":[78.589986,12.601431],"type":"Point"}
}