{
  "type": "Feature",
  "properties": {
    "iso:country":"IN",
    "ks:ks_name":"Jambakhal",
    "ks:ks_pop":284,
    "ks:ks_type":"VILLAGE",
    "name:eng_x_preferred":[
        "Jambakhal"
    ],
    "wof:name":"Jambakhal",
    "wof:placetype":"locality",
    "wof:population":284
},
  "geometry": {"coordinates":[83.719711,19.567644],"type":"Point"}
}