{
  "type": "Feature",
  "properties": {
    "gn:admin1_code":"26.0",
    "gn:admin2_code":"292.0",
    "gn:asciiname":"Kumarghat",
    "gn:country_code":"IN",
    "gn:dem":36,
    "gn:feature_class":"P",
    "gn:feature_code":"PPL",
    "gn:name":"Kumarghat",
    "gn:population":0,
    "gn:timezone":"Asia/Kolkata",
    "iso:country":"IN",
    "wof:name":"Kumarghat",
    "wof:placetype":"locality"
},
  "geometry": {"coordinates":[92.0329,24.15974],"type":"Point"}
}