{
  "type": "Feature",
  "properties": {
    "gn:admin1_code":"26.0",
    "gn:admin2_code":"292.0",
    "gn:asciiname":"Kumarghat",
    "gn:country_code":"IN",
    "gn:dem":36,
    "gn:feature_class":"P",
    "gn:feature_code":"PPL",
    "gn:name":"Kumarghat",
    "gn:population":0,
    "gn:timezone":"Asia/Kolkata",
    "iso:country":"IN",
    "name:ben_x_preferred":[
        "\u0995\u09c1\u09ae\u09be\u09b0\u0998\u09be\u099f"
    ],
    "name:bpy_x_preferred":[
        "\u0995\u09c1\u09ae\u09be\u09b0\u0998\u09be\u099f"
    ],
    "name:ita_x_preferred":[
        "Kumarghat"
    ],
    "name:mlg_x_preferred":[
        "Kumarghat"
    ],
    "name:msa_x_preferred":[
        "Kumarghat"
    ],
    "name:new_x_preferred":[
        "\u0915\u0941\u092e\u093e\u0930\u0918\u093e\u091f"
    ],
    "name:nld_x_preferred":[
        "Kumarghat"
    ],
    "name:ori_x_preferred":[
        "\u0b15\u0b41\u0b2e\u0b3e\u0b30\u0b18\u0b3e\u0b1f"
    ],
    "name:por_x_preferred":[
        "Kumarghat"
    ],
    "name:vie_x_preferred":[
        "Kumarghat"
    ],
    "name:zho_x_preferred":[
        "\u5e93\u9a6c\u5c14\u52a0\u7279"
    ],
    "wof:name":"Kumarghat",
    "wof:placetype":"locality"
},
  "geometry": {"coordinates":[92.0329,24.15974],"type":"Point"}
}