{
  "type": "Feature",
  "properties": {
    "gn:admin1_code":"36.0",
    "gn:admin2_code":"158.0",
    "gn:asciiname":"Bibipur Mutfarkat",
    "gn:country_code":"IN",
    "gn:dem":112,
    "gn:feature_class":"P",
    "gn:feature_code":"PPL",
    "gn:name":"Bibipur Mutfark\u0101t",
    "gn:population":0,
    "gn:timezone":"Asia/Kolkata",
    "iso:country":"IN",
    "wof:name":"Bibipur Mutfarkat",
    "wof:placetype":"locality"
},
  "geometry": {"coordinates":[81.24070999999998,26.20287],"type":"Point"}
}