{
  "type": "Feature",
  "properties": {
    "iso:country":"IN",
    "ks:ks_name":"Odamaru",
    "ks:ks_pop":44,
    "ks:ks_type":"HABITATION",
    "name:eng_x_preferred":[
        "Odamaru"
    ],
    "wof:name":"Odamaru",
    "wof:placetype":"locality",
    "wof:population":44
},
  "geometry": {"coordinates":[74.87583600000001,13.201281],"type":"Point"}
}