{
  "type": "Feature",
  "properties": {
    "iso:country":"IN",
    "ks:ks_name":"Kerekoppa",
    "ks:ks_pop":250,
    "ks:ks_type":"HABITATION",
    "name:eng_x_preferred":[
        "Kerekoppa"
    ],
    "wof:name":"Kerekoppa",
    "wof:placetype":"locality",
    "wof:population":250
},
  "geometry": {"coordinates":[74.81683099999999,14.724519],"type":"Point"}
}