{
  "type": "Feature",
  "properties": {
    "iso:country":"IN",
    "ks:ks_alt_nam":"gahalapada",
    "ks:ks_name":"Gahalapada",
    "ks:ks_pop":371,
    "ks:ks_type":"HABITATION",
    "name:eng_x_preferred":[
        "Gahalapada"
    ],
    "wof:name":"Gahalapada",
    "wof:placetype":"locality",
    "wof:population":371
},
  "geometry": {"coordinates":[72.772774,19.889159],"type":"Point"}
}