{
  "type": "Feature",
  "properties": {
    "gn:admin1_code":"38.0",
    "gn:admin2_code":"352.0",
    "gn:asciiname":"Boga",
    "gn:country_code":"IN",
    "gn:dem":246,
    "gn:feature_class":"P",
    "gn:feature_code":"PPL",
    "gn:name":"Boga",
    "gn:population":0,
    "gn:timezone":"Asia/Kolkata",
    "iso:country":"IN",
    "ks:ks_name":"Boga",
    "ks:ks_pop":112,
    "ks:ks_type":"VILLAGE",
    "name:cat_x_preferred":[
        "Boga"
    ],
    "name:ceb_x_preferred":[
        "Boga"
    ],
    "name:deu_x_preferred":[
        "Boga"
    ],
    "name:eng_x_preferred":[
        "Boga"
    ],
    "name:fra_x_preferred":[
        "Boga"
    ],
    "name:glg_x_preferred":[
        "Boga"
    ],
    "name:ita_x_preferred":[
        "Boga"
    ],
    "name:spa_x_preferred":[
        "Boga"
    ],
    "name:swe_x_preferred":[
        "Boga"
    ],
    "name:tur_x_preferred":[
        "Bo\u011fa"
    ],
    "wof:name":"Boga",
    "wof:placetype":"locality",
    "wof:population":112
},
  "geometry": {"coordinates":[87.687943,25.077565],"type":"Point"}
}