{
  "type": "Feature",
  "properties": {
    "gn:admin1_code":"19.0",
    "gn:admin2_code":"571.0",
    "gn:asciiname":"Kempanhalli",
    "gn:country_code":"IN",
    "gn:dem":818,
    "gn:feature_class":"P",
    "gn:feature_code":"PPL",
    "gn:name":"Kempanhalli",
    "gn:population":0,
    "gn:timezone":"Asia/Kolkata",
    "iso:country":"IN",
    "wof:name":"Kempanhalli",
    "wof:placetype":"locality"
},
  "geometry": {"coordinates":[77.10240999999998,12.95532],"type":"Point"}
}