{
  "type": "Feature",
  "properties": {
    "iso:country":"IN",
    "ks:ks_name":"Dambarewadi",
    "ks:ks_pop":107,
    "ks:ks_type":"HABITATION",
    "name:eng_x_preferred":[
        "Dambarewadi"
    ],
    "wof:name":"Dambarewadi",
    "wof:placetype":"locality",
    "wof:population":107
},
  "geometry": {"coordinates":[73.662413,16.388562],"type":"Point"}
}