{
  "type": "Feature",
  "properties": {
    "iso:country":"IN",
    "ks:ks_alt_nam":"BELTOLI",
    "ks:ks_name":"Beltoli",
    "ks:ks_pop":142,
    "ks:ks_type":"HABITATION",
    "name:eng_x_preferred":[
        "Beltoli"
    ],
    "wof:name":"Beltoli",
    "wof:placetype":"locality",
    "wof:population":142
},
  "geometry": {"coordinates":[83.811823,22.60449],"type":"Point"}
}