{
  "type": "Feature",
  "properties": {
    "iso:country":"IN",
    "ks:ks_name":"2 DOL",
    "ks:ks_pop":439,
    "ks:ks_type":"VILLAGE",
    "name:eng_x_preferred":[
        "2 DOL"
    ],
    "wof:name":"2 DOL",
    "wof:placetype":"locality",
    "wof:population":439
},
  "geometry": {"coordinates":[72.864496,28.833317],"type":"Point"}
}