{
  "type": "Feature",
  "properties": {
    "iso:country":"IN",
    "ks:ks_name":"Tilawali",
    "ks:ks_pop":113,
    "ks:ks_type":"VILLAGE",
    "name:eng_x_preferred":[
        "Tilawali"
    ],
    "wof:name":"Tilawali",
    "wof:placetype":"locality",
    "wof:population":113
},
  "geometry": {"coordinates":[73.965371,29.23203],"type":"Point"}
}