{
  "type": "Feature",
  "properties": {
    "gn:admin1_code":"36",
    "gn:admin2_code":"173.0",
    "gn:asciiname":"Lohartara",
    "gn:country_code":"IN",
    "gn:dem":96,
    "gn:feature_class":"P",
    "gn:feature_code":"PPL",
    "gn:name":"Loh\u0101rt\u0101ra",
    "gn:population":0,
    "gn:timezone":"Asia/Kolkata",
    "iso:country":"IN",
    "ks:ks_name":"Lohar Tara",
    "ks:ks_pop":387,
    "ks:ks_type":"VILLAGE",
    "name:eng_x_preferred":[
        "Lohar Tara"
    ],
    "name:eng_x_variant":[
        "Lohartara"
    ],
    "wof:name":"Lohar Tara",
    "wof:placetype":"locality",
    "wof:population":387
},
  "geometry": {"coordinates":[82.100098,25.834872],"type":"Point"}
}