{
  "type": "Feature",
  "properties": {
    "iso:country":"IN",
    "ks:ks_alt_nam":"RAMLAUT PURWA",
    "ks:ks_name":"Ramlaut Purwa",
    "ks:ks_pop":69,
    "ks:ks_type":"HABITATION",
    "name:eng_x_preferred":[
        "Ramlaut Purwa"
    ],
    "wof:name":"Ramlaut Purwa",
    "wof:placetype":"locality",
    "wof:population":69
},
  "geometry": {"coordinates":[81.18405199999999,28.243433],"type":"Point"}
}