{
  "type": "Feature",
  "properties": {
    "gn:admin1_code":"36",
    "gn:admin2_code":"180.0",
    "gn:asciiname":"Umaria",
    "gn:country_code":"IN",
    "gn:dem":118,
    "gn:feature_class":"P",
    "gn:feature_code":"PPL",
    "gn:name":"Umaria",
    "gn:population":0,
    "gn:timezone":"Asia/Kolkata",
    "iso:country":"IN",
    "name:ben_x_preferred":[
        "\u0989\u09ae\u09be\u09b0\u09bf\u09af\u09bc\u09be"
    ],
    "name:bpy_x_preferred":[
        "\u0989\u09ae\u09be\u09b0\u09bf\u09af\u09bc\u09be"
    ],
    "name:fra_x_preferred":[
        "Umaria"
    ],
    "name:guj_x_preferred":[
        "\u0a89\u0aae\u0ab0\u0abf\u0aaf\u0abe"
    ],
    "name:hif_x_preferred":[
        "Umaria"
    ],
    "name:hin_x_preferred":[
        "\u0909\u092e\u0930\u093f\u092f\u093e"
    ],
    "name:ita_x_preferred":[
        "Umaria"
    ],
    "name:mar_x_preferred":[
        "\u0909\u092e\u0930\u093f\u092f\u093e"
    ],
    "name:mlg_x_preferred":[
        "Umaria"
    ],
    "name:msa_x_preferred":[
        "Umaria"
    ],
    "name:por_x_preferred":[
        "Umaria"
    ],
    "name:san_x_preferred":[
        "\u0909\u092e\u0930\u093f\u092f\u093e"
    ],
    "name:spa_x_preferred":[
        "Umaria"
    ],
    "name:swe_x_preferred":[
        "Umaria"
    ],
    "name:urd_x_preferred":[
        "\u0627\u0648\u0645\u0627\u0631\u06cc\u0627"
    ],
    "name:vie_x_preferred":[
        "Umaria"
    ],
    "name:zho_x_preferred":[
        "\u4e4c\u9a6c\u91cc\u4e9a"
    ],
    "wof:name":"Umaria",
    "wof:placetype":"locality"
},
  "geometry": {"coordinates":[81.44348000000002,27.46336],"type":"Point"}
}