{
  "type": "Feature",
  "properties": {
    "iso:country":"IN",
    "ks:ks_name":"Pal Basti",
    "ks:ks_pop":350,
    "ks:ks_type":"HABITATION",
    "ks:ks_uagg_main":0,
    "name:eng_x_preferred":[
        "Pal Basti"
    ],
    "wof:name":"Pal Basti",
    "wof:placetype":"neighbourhood",
    "wof:population":350
},
  "geometry": {"coordinates":[82.94257399999999,24.87522],"type":"Point"}
}