{
  "type": "Feature",
  "properties": {
    "iso:country":"IN",
    "ks:ks_name":"Suklai",
    "ks:ks_pop":1356,
    "ks:ks_type":"VILLAGE",
    "ks:ks_uagg_main":0,
    "name:eng_x_preferred":[
        "Suklai"
    ],
    "wof:name":"Suklai",
    "wof:placetype":"neighbourhood",
    "wof:population":1356
},
  "geometry": {"coordinates":[87.223006,23.16929],"type":"Point"}
}