{
  "type": "Feature",
  "properties": {
    "gn:admin1_code":"37.0",
    "gn:admin2_code":"416.0",
    "gn:asciiname":"Tadmetla",
    "gn:country_code":"IN",
    "gn:dem":165,
    "gn:feature_class":"P",
    "gn:feature_code":"PPL",
    "gn:name":"T\u0101dmetla",
    "gn:population":0,
    "gn:timezone":"Asia/Kolkata",
    "iso:country":"IN",
    "ks:ks_alt_nam":"T\u0101dmetla",
    "ks:ks_name":"Tadmetla",
    "ks:ks_type":"VILLAGE",
    "name:eng_x_preferred":[
        "Tadmetla"
    ],
    "name:eng_x_variant":[
        "T\u0101dmetla"
    ],
    "wof:name":"Tadmetla",
    "wof:placetype":"locality"
},
  "geometry": {"coordinates":[81.149691,18.288415],"type":"Point"}
}