{
  "type": "Feature",
  "properties": {
    "gn:admin1_code":"36.0",
    "gn:admin2_code":"155",
    "gn:asciiname":"Daghela",
    "gn:country_code":"IN",
    "gn:dem":142,
    "gn:feature_class":"P",
    "gn:feature_code":"PPL",
    "gn:name":"Daghela",
    "gn:population":0,
    "gn:timezone":"Asia/Kolkata",
    "iso:country":"IN",
    "wof:name":"Daghela",
    "wof:placetype":"locality"
},
  "geometry": {"coordinates":[79.74683,27.53926],"type":"Point"}
}