{
  "type": "Feature",
  "properties": {
    "iso:country":"IN",
    "ks:ks_name":"Kamhai",
    "ks:ks_pop":100,
    "ks:ks_type":"HABITATION",
    "name:eng_x_preferred":[
        "Kamhai"
    ],
    "wof:name":"Kamhai",
    "wof:placetype":"locality",
    "wof:population":100
},
  "geometry": {"coordinates":[81.490579,25.121201],"type":"Point"}
}