{
  "type": "Feature",
  "properties": {
    "iso:country":"IN",
    "ks:ks_name":"Vettikal",
    "ks:ks_pop":400,
    "ks:ks_type":"HABITATION",
    "name:eng_x_preferred":[
        "Vettikal"
    ],
    "wof:name":"Vettikal",
    "wof:placetype":"locality",
    "wof:population":400
},
  "geometry": {"coordinates":[76.49214000000001,10.68432],"type":"Point"}
}