{
  "type": "Feature",
  "properties": {
    "gn:admin1_code":"35.0",
    "gn:admin2_code":"441.0",
    "gn:asciiname":"Umar Pani",
    "gn:country_code":"IN",
    "gn:dem":588,
    "gn:feature_class":"P",
    "gn:feature_code":"PPL",
    "gn:name":"Umar Pani",
    "gn:population":0,
    "gn:timezone":"Asia/Kolkata",
    "iso:country":"IN",
    "wof:name":"Umar Pani",
    "wof:placetype":"locality"
},
  "geometry": {"coordinates":[75.02753,21.59401],"type":"Point"}
}