{
  "type": "Feature",
  "properties": {
    "iso:country":"IN",
    "ks:ks_name":"Mohane",
    "ks:ks_pop":549,
    "ks:ks_type":"VILLAGE",
    "name:eng_x_preferred":[
        "Mohane"
    ],
    "wof:name":"Mohane",
    "wof:placetype":"locality",
    "wof:population":549
},
  "geometry": {"coordinates":[73.484275,17.729478],"type":"Point"}
}