{
  "type": "Feature",
  "properties": {
    "iso:country":"IN",
    "ks:ks_name":"Aklasarai",
    "ks:ks_pop":787,
    "ks:ks_type":"VILLAGE",
    "name:eng_x_preferred":[
        "Aklasarai"
    ],
    "wof:name":"Aklasarai",
    "wof:placetype":"locality",
    "wof:population":787
},
  "geometry": {"coordinates":[82.383289,23.429383],"type":"Point"}
}