{
  "type": "Feature",
  "properties": {
    "gn:admin1_code":"37",
    "gn:admin2_code":"406.0",
    "gn:asciiname":"Anda",
    "gn:country_code":"IN",
    "gn:dem":254,
    "gn:feature_class":"P",
    "gn:feature_code":"PPL",
    "gn:name":"Anda",
    "gn:population":0,
    "gn:timezone":"Asia/Kolkata",
    "iso:country":"IN",
    "name:ceb_x_preferred":[
        "Anda"
    ],
    "name:dan_x_preferred":[
        "Anda"
    ],
    "name:deu_x_preferred":[
        "Anda"
    ],
    "name:ell_x_preferred":[
        "\u0391\u03bd\u03c4\u03ac"
    ],
    "name:eus_x_preferred":[
        "Anda"
    ],
    "name:fra_x_preferred":[
        "Anda"
    ],
    "name:heb_x_preferred":[
        "\u05d0\u05e0\u05d3\u05d4"
    ],
    "name:hin_x_preferred":[
        "\u0910\u0902\u0921\u093e"
    ],
    "name:hun_x_preferred":[
        "Anda"
    ],
    "name:ind_x_preferred":[
        "Anda"
    ],
    "name:ita_x_preferred":[
        "Anda"
    ],
    "name:mlg_x_preferred":[
        "Anda"
    ],
    "name:nld_x_preferred":[
        "Anda"
    ],
    "name:nno_x_preferred":[
        "Anda"
    ],
    "name:nor_x_preferred":[
        "Anda"
    ],
    "name:pol_x_preferred":[
        "Anda"
    ],
    "name:slv_x_preferred":[
        "Anda"
    ],
    "name:spa_x_preferred":[
        "Anda"
    ],
    "name:swe_x_preferred":[
        "Anda"
    ],
    "name:ukr_x_preferred":[
        "\u0410\u043d\u0434\u0430"
    ],
    "name:war_x_preferred":[
        "Anda"
    ],
    "wof:name":"Anda",
    "wof:placetype":"locality"
},
  "geometry": {"coordinates":[81.97569,21.95968],"type":"Point"}
}