{
  "type": "Feature",
  "properties": {
    "iso:country":"IN",
    "ks:ks_name":"Settibettu",
    "ks:ks_pop":213,
    "ks:ks_type":"HABITATION",
    "name:eng_x_preferred":[
        "Settibettu"
    ],
    "wof:name":"Settibettu",
    "wof:placetype":"locality",
    "wof:population":213
},
  "geometry": {"coordinates":[74.936064,13.126174],"type":"Point"}
}