{
  "type": "Feature",
  "properties": {
    "iso:country":"IN",
    "ks:ks_alt_nam":"LONIYAN PURWA",
    "ks:ks_name":"Loniyan Purwa",
    "ks:ks_pop":82,
    "ks:ks_type":"HABITATION",
    "ks:ks_uagg_main":0,
    "name:eng_x_preferred":[
        "Loniyan Purwa"
    ],
    "wof:name":"Loniyan Purwa",
    "wof:placetype":"neighbourhood",
    "wof:population":82
},
  "geometry": {"coordinates":[81.469973,27.430568],"type":"Point"}
}