{
  "type": "Feature",
  "properties": {
    "iso:country":"IN",
    "ks:ks_name":"Brahman Toli",
    "ks:ks_pop":233,
    "ks:ks_type":"HABITATION",
    "name:eng_x_preferred":[
        "Brahman Toli"
    ],
    "wof:name":"Brahman Toli",
    "wof:placetype":"locality",
    "wof:population":233
},
  "geometry": {"coordinates":[85.516885,25.651679],"type":"Point"}
}