{
  "type": "Feature",
  "properties": {
    "gn:admin1_code":"35.0",
    "gn:admin2_code":"457.0",
    "gn:asciiname":"Barbaspur",
    "gn:country_code":"IN",
    "gn:dem":326,
    "gn:feature_class":"P",
    "gn:feature_code":"PPL",
    "gn:name":"Barbaspur",
    "gn:population":0,
    "gn:timezone":"Asia/Kolkata",
    "iso:country":"IN",
    "wof:name":"Barbaspur",
    "wof:placetype":"locality"
},
  "geometry": {"coordinates":[80.10643,21.80647],"type":"Point"}
}