{
  "type": "Feature",
  "properties": {
    "iso:country":"IN",
    "ks:ks_alt_nam":"Chinnagamanibenda colony",
    "ks:ks_name":"Chinnagamanibenda Colony",
    "ks:ks_pop":69,
    "ks:ks_type":"HABITATION",
    "name:eng_x_preferred":[
        "Chinnagamanibenda Colony"
    ],
    "wof:name":"Chinnagamanibenda Colony",
    "wof:placetype":"locality",
    "wof:population":69
},
  "geometry": {"coordinates":[78.561505,12.757661],"type":"Point"}
}