{
  "type": "Feature",
  "properties": {
    "gn:admin1_code":"39.0",
    "gn:admin2_code":"64.0",
    "gn:asciiname":"Malyalgaon",
    "gn:country_code":"IN",
    "gn:dem":1566,
    "gn:feature_class":"P",
    "gn:feature_code":"PPL",
    "gn:name":"Maly\u0101lgaon",
    "gn:population":0,
    "gn:timezone":"Asia/Kolkata",
    "iso:country":"IN",
    "wof:name":"Malyalgaon",
    "wof:placetype":"locality"
},
  "geometry": {"coordinates":[79.54789,29.72187000000001],"type":"Point"}
}