{
  "type": "Feature",
  "properties": {
    "iso:country":"IN",
    "ks:ks_name":"Kariganahalli",
    "ks:ks_pop":78,
    "ks:ks_type":"HABITATION",
    "name:eng_x_preferred":[
        "Kariganahalli"
    ],
    "wof:name":"Kariganahalli",
    "wof:placetype":"locality",
    "wof:population":78
},
  "geometry": {"coordinates":[77.443033,13.65681],"type":"Point"}
}