{
  "type": "Feature",
  "properties": {
    "iso:country":"IN",
    "ks:ks_name":"Chandaniya Koylwadi",
    "ks:ks_pop":622,
    "ks:ks_type":"HABITATION",
    "name:eng_x_preferred":[
        "Chandaniya Koylwadi"
    ],
    "wof:name":"Chandaniya Koylwadi",
    "wof:placetype":"locality",
    "wof:population":622
},
  "geometry": {"coordinates":[78.371495,22.214013],"type":"Point"}
}