{
  "type": "Feature",
  "properties": {
    "iso:country":"IN",
    "ks:ks_name":"Kishorpura",
    "ks:ks_pop":558,
    "ks:ks_type":"HABITATION",
    "name:eng_x_preferred":[
        "Kishorpura"
    ],
    "wof:name":"Kishorpura",
    "wof:placetype":"locality",
    "wof:population":558
},
  "geometry": {"coordinates":[76.70515399999999,26.342381],"type":"Point"}
}