{
  "type": "Feature",
  "properties": {
    "gn:admin1_code":"34.0",
    "gn:admin2_code":"203.0",
    "gn:asciiname":"Dhangar",
    "gn:country_code":"IN",
    "gn:dem":82,
    "gn:feature_class":"P",
    "gn:feature_code":"PPL",
    "gn:name":"Dh\u0101ngar",
    "gn:population":0,
    "gn:timezone":"Asia/Kolkata",
    "iso:country":"IN",
    "name:gom_x_preferred":[
        "Dhongor"
    ],
    "name:hin_x_preferred":[
        "\u0927\u0928\u0917\u0930"
    ],
    "name:mar_x_preferred":[
        "\u0927\u0928\u0917\u0930"
    ],
    "name:new_x_preferred":[
        "\u0917\u0926\u0930\u093f\u092f\u093e"
    ],
    "wof:name":"Dhangar",
    "wof:placetype":"neighbourhood"
},
  "geometry": {"coordinates":[84.44305,26.8491],"type":"Point"}
}