{
  "type": "Feature",
  "properties": {
    "iso:country":"IN",
    "ks:ks_name":"Beghima",
    "ks:ks_pop":511,
    "ks:ks_type":"VILLAGE",
    "name:eng_x_preferred":[
        "Beghima"
    ],
    "wof:name":"Beghima",
    "wof:placetype":"locality",
    "wof:population":511
},
  "geometry": {"coordinates":[85.10705400000001,22.680493],"type":"Point"}
}