{
  "type": "Feature",
  "properties": {
    "iso:country":"IN",
    "ks:ks_name":"Rupsinghgachh",
    "ks:ks_pop":706,
    "ks:ks_type":"HABITATION",
    "name:eng_x_preferred":[
        "Rupsinghgachh"
    ],
    "wof:name":"Rupsinghgachh",
    "wof:placetype":"locality",
    "wof:population":706
},
  "geometry": {"coordinates":[88.250636,26.556985],"type":"Point"}
}