{
  "type": "Feature",
  "properties": {
    "gn:admin1_code":"12.0",
    "gn:asciiname":"Jabrian",
    "gn:country_code":"IN",
    "gn:dem":881,
    "gn:feature_class":"P",
    "gn:feature_code":"PPL",
    "gn:name":"Jabri\u0101n",
    "gn:population":0,
    "gn:timezone":"Asia/Kolkata",
    "iso:country":"IN",
    "name:fas_x_preferred":[
        "\u062c\u0628\u0631\u0627\u0646"
    ],
    "name:urd_x_preferred":[
        "\u062c\u0628\u0631\u0627\u0646"
    ],
    "wof:name":"Jabrian",
    "wof:placetype":"locality"
},
  "geometry": {"coordinates":[74.13271999999998,33.15813],"type":"Point"}
}