{
  "type": "Feature",
  "properties": {
    "gn:admin1_code":"36",
    "gn:admin2_code":"199.0",
    "gn:asciiname":"Nawagaon",
    "gn:country_code":"IN",
    "gn:dem":187,
    "gn:feature_class":"P",
    "gn:feature_code":"PPL",
    "gn:name":"Naw\u0101gaon",
    "gn:population":0,
    "gn:timezone":"Asia/Kolkata",
    "iso:country":"IN",
    "ks:ks_name":"Nava Gaon",
    "ks:ks_pop":313,
    "ks:ks_type":"VILLAGE",
    "name:eng_x_preferred":[
        "Nava Gaon"
    ],
    "name:eng_x_variant":[
        "Nawagaon"
    ],
    "wof:name":"Nava Gaon",
    "wof:placetype":"locality",
    "wof:population":313
},
  "geometry": {"coordinates":[82.443287,24.943915],"type":"Point"}
}