{
  "type": "Feature",
  "properties": {
    "iso:country":"IN",
    "ks:ks_name":"Didisa Bazar",
    "ks:ks_pop":420,
    "ks:ks_type":"HABITATION",
    "ks:ks_uagg_main":0,
    "name:eng_x_preferred":[
        "Didisa Bazar"
    ],
    "wof:name":"Didisa Bazar",
    "wof:placetype":"neighbourhood",
    "wof:population":420
},
  "geometry": {"coordinates":[81.919757,27.011664],"type":"Point"}
}