{
  "type": "Feature",
  "properties": {
    "gn:admin1_code":"36.0",
    "gn:admin2_code":"151.0",
    "gn:asciiname":"Mohammadpur",
    "gn:country_code":"IN",
    "gn:dem":190,
    "gn:feature_class":"P",
    "gn:feature_code":"PPL",
    "gn:name":"Mohammadpur",
    "gn:population":0,
    "gn:timezone":"Asia/Kolkata",
    "iso:country":"IN",
    "name:ara_x_preferred":[
        "\u0645\u062d\u0645\u062f \u0628\u0648\u0631"
    ],
    "name:ben_bn_x_preferred":[
        "\u09ae\u09cb\u09b9\u09ae\u09cd\u09ae\u09a6\u09aa\u09c1\u09b0"
    ],
    "name:ben_in_x_preferred":[
        "\u09ae\u09cb\u09b9\u09ae\u09cd\u09ae\u09a6\u09aa\u09c1\u09b0"
    ],
    "name:guj_x_preferred":[
        "\u0aae\u0ab9\u0aae\u0acd\u0aae\u0aa6\u0aaa\u0ac1\u0ab0"
    ],
    "name:hin_x_preferred":[
        "\u092e\u094b\u0939\u092e\u094d\u092e\u0926\u092a\u0941\u0930"
    ],
    "name:kan_x_preferred":[
        "\u0cae\u0cca\u0cb9\u0cae\u0ccd\u0cae\u0ca6\u0ccd"
    ],
    "name:mal_x_preferred":[
        "\u0d2e\u0d41\u0d39\u0d2e\u0d4d\u0d2e\u0d26\u0d4d"
    ],
    "name:mar_x_preferred":[
        "\u092e\u094b\u0939\u092e\u094d\u092e\u0926\u092a\u0942\u0930"
    ],
    "name:pan_x_preferred":[
        "\u0a2e\u0a4b\u0a39\u0a70\u0a2e\u0a26\u0a2a\u0a41\u0a30"
    ],
    "name:tam_x_preferred":[
        "\u0bae\u0bca\u0bb9\u0bae\u0bcd\u0bae\u0ba4\u0bcd\u0baa\u0bc2\u0bb0\u0bcd"
    ],
    "name:tel_x_preferred":[
        "\u0c2e\u0c4a\u0c39\u0c2e\u0c4d\u0c2e\u0c26\u0c4d"
    ],
    "name:urd_x_preferred":[
        "\u0645\u062d\u0645\u062f \u067e\u0648\u0631"
    ],
    "wof:name":"Mohammadpur",
    "wof:placetype":"locality"
},
  "geometry": {"coordinates":[79.62090000000001,28.68609],"type":"Point"}
}