{
  "type": "Feature",
  "properties": {
    "gn:admin1_code":"19.0",
    "gn:admin2_code":"569.0",
    "gn:asciiname":"Nilavara Ammanoru",
    "gn:country_code":"IN",
    "gn:dem":18,
    "gn:feature_class":"P",
    "gn:feature_code":"PPL",
    "gn:name":"Nil\u0101vara Ammanoru",
    "gn:population":0,
    "gn:timezone":"Asia/Kolkata",
    "iso:country":"IN",
    "wof:name":"Nilavara Ammanoru",
    "wof:placetype":"locality"
},
  "geometry": {"coordinates":[74.77972,13.45442],"type":"Point"}
}