{
  "type": "Feature",
  "properties": {
    "iso:country":"IN",
    "ks:ks_name":"Sc Colony",
    "ks:ks_pop":210,
    "ks:ks_type":"HABITATION",
    "name:eng_x_preferred":[
        "Sc Colony"
    ],
    "wof:name":"Sc Colony",
    "wof:placetype":"locality",
    "wof:population":210
},
  "geometry": {"coordinates":[74.46897199999999,14.397016],"type":"Point"}
}