{
  "type": "Feature",
  "properties": {
    "gn:admin1_code":"25.0",
    "gn:admin2_code":"620.0",
    "gn:asciiname":"Serumanallur",
    "gn:country_code":"IN",
    "gn:dem":30,
    "gn:feature_class":"P",
    "gn:feature_code":"PPL",
    "gn:name":"Serum\u0101nall\u016br",
    "gn:population":0,
    "gn:timezone":"Asia/Kolkata",
    "iso:country":"IN",
    "name:und_x_variant":[
        "Serum\u0101nall\u016br",
        "Ukkadai"
    ],
    "wof:name":"Serumanallur",
    "wof:placetype":"locality"
},
  "geometry": {"coordinates":[79.35821,10.80104],"type":"Point"}
}