{
  "type": "Feature",
  "properties": {
    "iso:country":"IN",
    "ks:ks_name":"Dehvant",
    "ks:ks_pop":367,
    "ks:ks_type":"HABITATION",
    "name:eng_x_preferred":[
        "Dehvant"
    ],
    "wof:name":"Dehvant",
    "wof:placetype":"locality",
    "wof:population":367
},
  "geometry": {"coordinates":[74.07466700000001,22.361694],"type":"Point"}
}