{
  "type": "Feature",
  "properties": {
    "iso:country":"IN",
    "ks:ks_name":"Bodiganapalya",
    "ks:ks_pop":67,
    "ks:ks_type":"HABITATION",
    "name:eng_x_preferred":[
        "Bodiganapalya"
    ],
    "wof:name":"Bodiganapalya",
    "wof:placetype":"locality",
    "wof:population":67
},
  "geometry": {"coordinates":[77.26813799999999,13.012963],"type":"Point"}
}