{
  "type": "Feature",
  "properties": {
    "iso:country":"IN",
    "ks:ks_name":"Devarkoppa",
    "ks:ks_pop":70,
    "ks:ks_type":"VILLAGE",
    "name:eng_x_preferred":[
        "Devarkoppa"
    ],
    "wof:name":"Devarkoppa",
    "wof:placetype":"locality",
    "wof:population":70
},
  "geometry": {"coordinates":[74.82556,14.679266],"type":"Point"}
}