{
  "type": "Feature",
  "properties": {
    "gn:admin1_code":"2.0",
    "gn:admin2_code":"554.0",
    "gn:asciiname":"Kurappalle",
    "gn:country_code":"IN",
    "gn:dem":721,
    "gn:feature_class":"P",
    "gn:feature_code":"PPL",
    "gn:name":"Kurappalle",
    "gn:population":0,
    "gn:timezone":"Asia/Kolkata",
    "iso:country":"IN",
    "wof:name":"Kurappalle",
    "wof:placetype":"locality"
},
  "geometry": {"coordinates":[78.62846999999999,13.39785],"type":"Point"}
}