{
  "type": "Feature",
  "properties": {
    "iso:country":"IN",
    "ks:ks_name":"4 B",
    "ks:ks_pop":2524,
    "ks:ks_type":"VILLAGE",
    "name:eng_x_preferred":[
        "4 B"
    ],
    "wof:name":"4 B",
    "wof:placetype":"locality",
    "wof:population":2524
},
  "geometry": {"coordinates":[73.93937,30.128789],"type":"Point"}
}