{
  "type": "Feature",
  "properties": {
    "gn:admin1_code":"35",
    "gn:admin2_code":"433.0",
    "gn:asciiname":"Sunara",
    "gn:country_code":"IN",
    "gn:dem":365,
    "gn:feature_class":"P",
    "gn:feature_code":"PPL",
    "gn:name":"Sun\u0101ra",
    "gn:population":0,
    "gn:timezone":"Asia/Kolkata",
    "iso:country":"IN",
    "wof:name":"Sunara",
    "wof:placetype":"locality"
},
  "geometry": {"coordinates":[75.86853000000001,24.56465],"type":"Point"}
}