{
  "type": "Feature",
  "properties": {
    "gn:admin1_code":"36",
    "gn:admin2_code":"194.0",
    "gn:asciiname":"Kashiapur",
    "gn:country_code":"IN",
    "gn:dem":96,
    "gn:feature_class":"P",
    "gn:feature_code":"PPL",
    "gn:name":"Kashi\u0101pur",
    "gn:population":0,
    "gn:timezone":"Asia/Kolkata",
    "iso:country":"IN",
    "ks:ks_alt_nam":"Kashi\u0101pur",
    "ks:ks_name":"Kashiapur",
    "ks:ks_type":"VILLAGE",
    "name:eng_x_preferred":[
        "Kashiapur"
    ],
    "name:eng_x_variant":[
        "Kashi\u0101pur"
    ],
    "wof:name":"Kashiapur",
    "wof:placetype":"locality"
},
  "geometry": {"coordinates":[82.52836600000001,26.053143],"type":"Point"}
}