{
  "type": "Feature",
  "properties": {
    "iso:country":"IN",
    "ks:ks_name":"Bilipada",
    "ks:ks_pop":278,
    "ks:ks_type":"VILLAGE",
    "name:eng_x_preferred":[
        "Bilipada"
    ],
    "wof:name":"Bilipada",
    "wof:placetype":"locality",
    "wof:population":278
},
  "geometry": {"coordinates":[86.221284,20.572175],"type":"Point"}
}