{
  "type": "Feature",
  "properties": {
    "iso:country":"IN",
    "ks:ks_name":"Tendarangi",
    "ks:ks_pop":201,
    "ks:ks_type":"VILLAGE",
    "name:eng_x_preferred":[
        "Tendarangi"
    ],
    "wof:name":"Tendarangi",
    "wof:placetype":"locality",
    "wof:population":201
},
  "geometry": {"coordinates":[83.752267,20.088548],"type":"Point"}
}