{
  "type": "Feature",
  "properties": {
    "gn:admin1_code":"35",
    "gn:admin2_code":"463.0",
    "gn:asciiname":"Parihasi",
    "gn:country_code":"IN",
    "gn:dem":428,
    "gn:feature_class":"P",
    "gn:feature_code":"PPL",
    "gn:name":"Parih\u0101si",
    "gn:population":0,
    "gn:timezone":"Asia/Kolkata",
    "iso:country":"IN",
    "ks:ks_alt_nam":"Parih\u0101si",
    "ks:ks_name":"Parihasi",
    "ks:ks_pop":1055,
    "ks:ks_type":"VILLAGE",
    "name:eng_x_preferred":[
        "Parihasi"
    ],
    "name:eng_x_variant":[
        "Parih\u0101si"
    ],
    "wof:name":"Parihasi",
    "wof:placetype":"locality",
    "wof:population":1055
},
  "geometry": {"coordinates":[82.482786,24.293183],"type":"Point"}
}