{
  "type": "Feature",
  "properties": {
    "iso:country":"IN",
    "ks:ks_name":"3 GM",
    "ks:ks_pop":175,
    "ks:ks_type":"VILLAGE",
    "name:eng_x_preferred":[
        "3 GM"
    ],
    "wof:name":"3 GM",
    "wof:placetype":"locality",
    "wof:population":175
},
  "geometry": {"coordinates":[73.462845,29.009129],"type":"Point"}
}