{
  "type": "Feature",
  "properties": {
    "iso:country":"IN",
    "ks:ks_name":"Jaidwar Malla",
    "ks:ks_pop":256,
    "ks:ks_type":"VILLAGE",
    "name:eng_x_preferred":[
        "Jaidwar Malla"
    ],
    "wof:name":"Jaidwar Malla",
    "wof:placetype":"locality",
    "wof:population":256
},
  "geometry": {"coordinates":[78.036647,30.549328],"type":"Point"}
}