{
  "type": "Feature",
  "properties": {
    "iso:country":"IN",
    "ks:ks_name":"Makangadde",
    "ks:ks_type":"VILLAGE",
    "name:eng_x_preferred":[
        "Makangadde"
    ],
    "wof:name":"Makangadde",
    "wof:placetype":"locality"
},
  "geometry": {"coordinates":[75.61534899999999,12.994234],"type":"Point"}
}