{
  "type": "Feature",
  "properties": {
    "iso:country":"IN",
    "ks:ks_name":"Godarasta",
    "ks:ks_pop":195,
    "ks:ks_type":"VILLAGE",
    "name:eng_x_preferred":[
        "Godarasta"
    ],
    "wof:name":"Godarasta",
    "wof:placetype":"locality",
    "wof:population":195
},
  "geometry": {"coordinates":[87.09057799999999,22.388245],"type":"Point"}
}