{
  "type": "Feature",
  "properties": {
    "iso:country":"IN",
    "ks:ks_alt_nam":"ARAZI BASAULI",
    "ks:ks_name":"Arazi Basauli",
    "ks:ks_pop":5162,
    "ks:ks_type":"HABITATION",
    "ks:ks_uagg_main":0,
    "name:eng_x_preferred":[
        "Arazi Basauli"
    ],
    "wof:name":"Arazi Basauli",
    "wof:placetype":"neighbourhood",
    "wof:population":5162
},
  "geometry": {"coordinates":[85.968206,26.327563],"type":"Point"}
}