{
  "type": "Feature",
  "properties": {
    "gn:admin1_code":"12.0",
    "gn:admin2_code":"010",
    "gn:asciiname":"Tsinar",
    "gn:country_code":"IN",
    "gn:dem":1785,
    "gn:feature_class":"P",
    "gn:feature_code":"PPL",
    "gn:name":"Ts\u012bnar",
    "gn:population":0,
    "gn:timezone":"Asia/Kolkata",
    "iso:country":"IN",
    "name:und_x_variant":[
        "Ts\u012bnar",
        "Chinar"
    ],
    "wof:name":"Tsinar",
    "wof:placetype":"locality"
},
  "geometry": {"coordinates":[74.8616,34.29026],"type":"Point"}
}