{
  "type": "Feature",
  "properties": {
    "iso:country":"IN",
    "ks:ks_name":"Navileedigarahalli",
    "ks:ks_pop":80,
    "ks:ks_type":"HABITATION",
    "name:eng_x_preferred":[
        "Navileedigarahalli"
    ],
    "wof:name":"Navileedigarahalli",
    "wof:placetype":"locality",
    "wof:population":80
},
  "geometry": {"coordinates":[76.455958,13.091735],"type":"Point"}
}