{
  "type": "Feature",
  "properties": {
    "gn:admin1_code":"11.0",
    "gn:admin2_code":"27.0",
    "gn:asciiname":"Kushla",
    "gn:country_code":"IN",
    "gn:dem":1756,
    "gn:feature_class":"P",
    "gn:feature_code":"PPL",
    "gn:name":"Kushla",
    "gn:population":0,
    "gn:timezone":"Asia/Kolkata",
    "iso:country":"IN",
    "name:bul_x_preferred":[
        "\u041a\u0443\u0448\u043b\u0430"
    ],
    "name:kat_x_preferred":[
        "\u10d9\u10e3\u10e8\u10da\u10d0"
    ],
    "name:kaz_x_preferred":[
        "\u041a\u0443\u0448\u043b\u0430"
    ],
    "name:msa_x_preferred":[
        "Kushla"
    ],
    "name:ron_x_preferred":[
        "Ku\u0219la"
    ],
    "name:rus_x_preferred":[
        "\u041a\u0443\u0448\u043b\u0430"
    ],
    "name:ukr_x_preferred":[
        "\u041a\u0443\u0448\u043b\u0430"
    ],
    "wof:name":"Kushla",
    "wof:placetype":"locality"
},
  "geometry": {"coordinates":[77.00189,31.4899],"type":"Point"}
}