{
  "type": "Feature",
  "properties": {
    "iso:country":"IN",
    "ks:ks_name":"Damdongri",
    "ks:ks_pop":223,
    "ks:ks_type":"HABITATION",
    "name:eng_x_preferred":[
        "Damdongri"
    ],
    "wof:name":"Damdongri",
    "wof:placetype":"locality",
    "wof:population":223
},
  "geometry": {"coordinates":[77.97653,23.251848],"type":"Point"}
}