{
  "type": "Feature",
  "properties": {
    "gn:admin1_code":"36.0",
    "gn:admin2_code":"150.0",
    "gn:asciiname":"Bari Nagla",
    "gn:country_code":"IN",
    "gn:dem":166,
    "gn:feature_class":"P",
    "gn:feature_code":"PPL",
    "gn:name":"B\u0101ri Nagla",
    "gn:population":0,
    "gn:timezone":"Asia/Kolkata",
    "iso:country":"IN",
    "ks:ks_alt_nam":"B\u0101ri Nagla",
    "ks:ks_name":"Bari Nagla",
    "ks:ks_pop":1343,
    "ks:ks_type":"VILLAGE",
    "ks:ks_uagg_main":0,
    "name:eng_x_preferred":[
        "Bari Nagla"
    ],
    "name:eng_x_variant":[
        "B\u0101ri Nagla"
    ],
    "wof:name":"Bari Nagla",
    "wof:placetype":"locality",
    "wof:population":1343
},
  "geometry": {"coordinates":[79.411615,28.295842],"type":"Point"}
}