{
  "type": "Feature",
  "properties": {
    "iso:country":"IN",
    "ks:ks_alt_nam":"Khemanar wasti",
    "ks:ks_name":"Khemanar Wasti",
    "ks:ks_pop":100,
    "ks:ks_type":"HABITATION",
    "name:eng_x_preferred":[
        "Khemanar Wasti"
    ],
    "wof:name":"Khemanar Wasti",
    "wof:placetype":"locality",
    "wof:population":100
},
  "geometry": {"coordinates":[74.591853,19.516522],"type":"Point"}
}