{
  "type": "Feature",
  "properties": {
    "gn:admin1_code":"19.0",
    "gn:admin2_code":"569",
    "gn:asciiname":"Golikatte",
    "gn:country_code":"IN",
    "gn:dem":67,
    "gn:feature_class":"P",
    "gn:feature_code":"PPL",
    "gn:name":"Golikatte",
    "gn:population":0,
    "gn:timezone":"Asia/Kolkata",
    "iso:country":"IN",
    "wof:name":"Golikatte",
    "wof:placetype":"locality"
},
  "geometry": {"coordinates":[74.86123000000001,13.60582],"type":"Point"}
}