{
  "type": "Feature",
  "properties": {
    "iso:country":"IN",
    "ks:ks_name":"Gerupalya",
    "ks:ks_pop":138,
    "ks:ks_type":"HABITATION",
    "ks:ks_uagg_main":0,
    "name:eng_x_preferred":[
        "Gerupalya"
    ],
    "wof:name":"Gerupalya",
    "wof:placetype":"neighbourhood",
    "wof:population":138
},
  "geometry": {"coordinates":[77.287689,13.012252],"type":"Point"}
}