{
  "type": "Feature",
  "properties": {
    "iso:country":"IN",
    "ks:ks_name":"Mooruguttapalle",
    "ks:ks_pop":18,
    "ks:ks_type":"HABITATION",
    "name:eng_x_preferred":[
        "Mooruguttapalle"
    ],
    "wof:name":"Mooruguttapalle",
    "wof:placetype":"locality",
    "wof:population":18
},
  "geometry": {"coordinates":[78.95578399999999,13.51545],"type":"Point"}
}