{
  "type": "Feature",
  "properties": {
    "iso:country":"IN",
    "ks:ks_name":"Badjharan",
    "ks:ks_pop":66,
    "ks:ks_type":"VILLAGE",
    "name:eng_x_preferred":[
        "Badjharan"
    ],
    "wof:name":"Badjharan",
    "wof:placetype":"locality",
    "wof:population":66
},
  "geometry": {"coordinates":[84.847179,21.666464],"type":"Point"}
}