{
  "type": "Feature",
  "properties": {
    "gn:admin1_code":"12.0",
    "gn:asciiname":"Gali",
    "gn:country_code":"IN",
    "gn:dem":3023,
    "gn:feature_class":"P",
    "gn:feature_code":"PPL",
    "gn:name":"Gali",
    "gn:population":0,
    "gn:timezone":"Asia/Kolkata",
    "iso:country":"IN",
    "name:ceb_x_preferred":[
        "Gali"
    ],
    "name:heb_x_preferred":[
        "\u05d2\u05d0\u05dc\u05d9"
    ],
    "name:kat_x_preferred":[
        "\u10d2\u10d0\u10da\u10d8"
    ],
    "name:nld_x_preferred":[
        "Gali"
    ],
    "name:sco_x_preferred":[
        "Gali"
    ],
    "name:swe_x_preferred":[
        "Gali"
    ],
    "wof:name":"Gali",
    "wof:placetype":"locality"
},
  "geometry": {"coordinates":[73.89981,34.43496],"type":"Point"}
}