{
  "type": "Feature",
  "properties": {
    "gn:admin1_code":"12.0",
    "gn:asciiname":"Gali",
    "gn:country_code":"IN",
    "gn:dem":3023,
    "gn:feature_class":"P",
    "gn:feature_code":"PPL",
    "gn:name":"Gali",
    "gn:population":0,
    "gn:timezone":"Asia/Kolkata",
    "iso:country":"IN",
    "wof:name":"Gali",
    "wof:placetype":"locality"
},
  "geometry": {"coordinates":[73.89981,34.43496],"type":"Point"}
}