{
  "type": "Feature",
  "properties": {
    "gn:admin1_code":"16",
    "gn:admin2_code":"525.0",
    "gn:asciiname":"Mankeshwar",
    "gn:country_code":"IN",
    "gn:dem":545,
    "gn:feature_class":"P",
    "gn:feature_code":"PPL",
    "gn:name":"M\u0101nkeshwar",
    "gn:population":0,
    "gn:timezone":"Asia/Kolkata",
    "iso:country":"IN",
    "name:ceb_x_preferred":[
        "M\u0101nkeshwar"
    ],
    "name:swe_x_preferred":[
        "M\u0101nkeshwar"
    ],
    "name:und_x_variant":[
        "Menkaiser"
    ],
    "wof:name":"Mankeshwar",
    "wof:placetype":"locality"
},
  "geometry": {"coordinates":[75.63918000000002,18.35367],"type":"Point"}
}