{
  "type": "Feature",
  "properties": {
    "iso:country":"IN",
    "ks:ks_name":"Rambal Deeh",
    "ks:ks_pop":255,
    "ks:ks_type":"HABITATION",
    "name:eng_x_preferred":[
        "Rambal Deeh"
    ],
    "wof:name":"Rambal Deeh",
    "wof:placetype":"locality",
    "wof:population":255
},
  "geometry": {"coordinates":[82.893674,27.095164],"type":"Point"}
}