{
  "type": "Feature",
  "properties": {
    "gn:admin1_code":"21.0",
    "gn:admin2_code":"396.0",
    "gn:asciiname":"Pusubadi",
    "gn:country_code":"IN",
    "gn:dem":487,
    "gn:feature_class":"P",
    "gn:feature_code":"PPL",
    "gn:name":"P\u016bsub\u0101di",
    "gn:population":0,
    "gn:timezone":"Asia/Kolkata",
    "iso:country":"IN",
    "ks:ks_name":"Pushabadi",
    "ks:ks_pop":79,
    "ks:ks_type":"VILLAGE",
    "name:eng_x_preferred":[
        "Pushabadi"
    ],
    "name:eng_x_variant":[
        "Pusubadi"
    ],
    "wof:name":"Pushabadi",
    "wof:placetype":"locality",
    "wof:population":79
},
  "geometry": {"coordinates":[83.305558,19.228186],"type":"Point"}
}