{
  "type": "Feature",
  "properties": {
    "gn:admin1_code":"24.0",
    "gn:admin2_code":"103.0",
    "gn:asciiname":"Ramsar",
    "gn:country_code":"IN",
    "gn:dem":314,
    "gn:feature_class":"P",
    "gn:feature_code":"PPL",
    "gn:name":"R\u0101msar",
    "gn:population":0,
    "gn:timezone":"Asia/Kolkata",
    "iso:country":"IN",
    "name:ceb_x_preferred":[
        "Ramsar"
    ],
    "name:fas_x_preferred":[
        "\u0631\u0627\u0645\u0633\u0631"
    ],
    "name:fra_x_preferred":[
        "Ramsar"
    ],
    "name:pnb_x_preferred":[
        "\u0631\u0627\u0645\u0633\u0631"
    ],
    "name:spa_x_preferred":[
        "Ramsar"
    ],
    "name:swe_x_preferred":[
        "Ramsar"
    ],
    "wof:name":"Ramsar",
    "wof:placetype":"locality"
},
  "geometry": {"coordinates":[75.93467,28.13076],"type":"Point"}
}