{
  "type": "Feature",
  "properties": {
    "gn:admin1_code":"36.0",
    "gn:admin2_code":"151.0",
    "gn:asciiname":"Dhakia",
    "gn:country_code":"IN",
    "gn:dem":196,
    "gn:feature_class":"P",
    "gn:feature_code":"PPL",
    "gn:name":"Dhaki\u0101",
    "gn:population":0,
    "gn:timezone":"Asia/Kolkata",
    "iso:country":"IN",
    "wof:name":"Dhakia",
    "wof:placetype":"locality"
},
  "geometry": {"coordinates":[79.87161999999999,28.77991],"type":"Point"}
}