{
  "type": "Feature",
  "properties": {
    "iso:country":"IN",
    "ks:ks_name":"Mohanpur",
    "ks:ks_pop":331,
    "ks:ks_type":"VILLAGE",
    "name:eng_x_preferred":[
        "Mohanpur"
    ],
    "wof:name":"Mohanpur",
    "wof:placetype":"locality",
    "wof:population":331
},
  "geometry": {"coordinates":[87.42097800000001,24.330557],"type":"Point"}
}