{
  "type": "Feature",
  "properties": {
    "iso:country":"IN",
    "ks:ks_name":"Saimali",
    "ks:ks_pop":196,
    "ks:ks_type":"HABITATION",
    "name:eng_x_preferred":[
        "Saimali"
    ],
    "wof:name":"Saimali",
    "wof:placetype":"locality",
    "wof:population":196
},
  "geometry": {"coordinates":[80.31398799999999,29.972542],"type":"Point"}
}