{
  "type": "Feature",
  "properties": {
    "gn:admin1_code":"24.0",
    "gn:admin2_code":"102",
    "gn:asciiname":"Sarayanwas",
    "gn:country_code":"IN",
    "gn:dem":231,
    "gn:feature_class":"P",
    "gn:feature_code":"PPL",
    "gn:name":"S\u0101r\u0101yanw\u0101s",
    "gn:population":0,
    "gn:timezone":"Asia/Kolkata",
    "iso:country":"IN",
    "name:und_x_variant":[
        "S\u0101r\u0101yanw\u0101s",
        "Sarahbas"
    ],
    "wof:name":"Sarayanwas",
    "wof:placetype":"locality"
},
  "geometry": {"coordinates":[74.76743,28.68363],"type":"Point"}
}