{
  "type": "Feature",
  "properties": {
    "iso:country":"IN",
    "ks:ks_alt_nam":"SURESH DAS PARA",
    "ks:ks_name":"Suresh Das Para",
    "ks:ks_pop":200,
    "ks:ks_type":"HABITATION",
    "name:eng_x_preferred":[
        "Suresh Das Para"
    ],
    "wof:name":"Suresh Das Para",
    "wof:placetype":"locality",
    "wof:population":200
},
  "geometry": {"coordinates":[91.247345,23.693028],"type":"Point"}
}