{
  "type": "Feature",
  "properties": {
    "gn:admin1_code":"36",
    "gn:admin2_code":"163.0",
    "gn:asciiname":"Thanwanpur",
    "gn:country_code":"IN",
    "gn:dem":137,
    "gn:feature_class":"P",
    "gn:feature_code":"PPL",
    "gn:name":"Thanw\u0101npur",
    "gn:population":0,
    "gn:timezone":"Asia/Kolkata",
    "iso:country":"IN",
    "ks:ks_name":"Thanwapur",
    "ks:ks_pop":1178,
    "ks:ks_type":"VILLAGE",
    "ks:ks_uagg_main":0,
    "name:eng_x_preferred":[
        "Thanwapur"
    ],
    "wof:name":"Thanwapur",
    "wof:placetype":"neighbourhood",
    "wof:population":1178
},
  "geometry": {"coordinates":[79.829593,26.354497],"type":"Point"}
}