{
  "type": "Feature",
  "properties": {
    "gn:admin1_code":"36.0",
    "gn:admin2_code":"149.0",
    "gn:asciiname":"Nawabganj",
    "gn:country_code":"IN",
    "gn:dem":163,
    "gn:feature_class":"P",
    "gn:feature_code":"PPL",
    "gn:name":"Naw\u0101bganj",
    "gn:population":0,
    "gn:timezone":"Asia/Kolkata",
    "iso:country":"IN",
    "name:ara_x_preferred":[
        "\u0646\u0648\u0627\u0628\u063a\u0627\u0646\u062c"
    ],
    "name:ara_x_variant":[
        "\u0646\u0641\u0627\u0628\u062c\u0627\u0646\u0634"
    ],
    "name:ben_bn_x_preferred":[
        "\u09a8\u09ac\u09be\u09ac\u0997\u099e\u09cd\u099c"
    ],
    "name:ben_in_x_preferred":[
        "\u09a8\u09ac\u09be\u09ac\u0997\u099e\u09cd\u099c"
    ],
    "name:bpy_x_preferred":[
        "\u09a8\u09f1\u09be\u09ac\u0997\u099e\u09cd\u099c"
    ],
    "name:cat_x_preferred":[
        "Nawabganj"
    ],
    "name:ceb_x_preferred":[
        "Nawabganj"
    ],
    "name:deu_x_preferred":[
        "Nawabganj"
    ],
    "name:fas_x_preferred":[
        "\u0646\u0648\u0627\u0628 \u06af\u0646\u062c"
    ],
    "name:guj_x_preferred":[
        "\u0aa8\u0ab5\u0abe\u0aac\u0a97\u0a82\u0a9c"
    ],
    "name:heb_x_preferred":[
        "\u05e0\u05d5\u05d5\u05d1\u05d2\u05e0\u05d2'"
    ],
    "name:hin_x_preferred":[
        "\u0928\u0935\u093e\u092c\u0917\u0902\u091c"
    ],
    "name:hun_x_preferred":[
        "Nawabganj"
    ],
    "name:ind_x_preferred":[
        "Nawabganj"
    ],
    "name:ita_x_preferred":[
        "Nawabganj"
    ],
    "name:jpn_x_preferred":[
        "\u30ca\u30ef\u30d6\u30ac\u30f3\u30b8"
    ],
    "name:kan_x_preferred":[
        "\u0ca8\u0cb5\u0cbe\u0cac\u0ccd"
    ],
    "name:kor_x_preferred":[
        "\ub098\uc640\ube0c\uac04\uc988"
    ],
    "name:mal_x_preferred":[
        "\u0d28\u0d35\u0d3e\u0d2c\u0d4d\u0d17\u0d1e\u0d4d\u0d1a\u0d4d"
    ],
    "name:mar_x_preferred":[
        "\u0928\u0935\u093e\u092c\u0917\u0902\u091c"
    ],
    "name:new_x_preferred":[
        "\u0928\u0935\u093e\u092c\u0917\u091e\u094d\u091c"
    ],
    "name:nld_x_preferred":[
        "Nawabganj"
    ],
    "name:pan_x_preferred":[
        "\u0a28\u0a35\u0a3e\u0a2c\u0a17\u0a70\u0a1c"
    ],
    "name:pol_x_preferred":[
        "Nawabganj"
    ],
    "name:por_x_preferred":[
        "Nawabganj"
    ],
    "name:rus_x_preferred":[
        "\u041d\u0430\u0432\u0430\u0431\u0433\u0430\u043d\u0434\u0436"
    ],
    "name:spa_x_preferred":[
        "Nawabganj"
    ],
    "name:swe_x_preferred":[
        "Nawabganj"
    ],
    "name:tam_x_preferred":[
        "\u0ba8\u0bb5\u0bbe\u0baa\u0bcd\u0b95\u0b9e\u0bcd\u0b9a\u0bcd"
    ],
    "name:tel_x_preferred":[
        "\u0c28\u0c35\u0c3e\u0c2c\u0c4d"
    ],
    "name:tur_x_preferred":[
        "Nawabganj"
    ],
    "name:ukr_x_preferred":[
        "\u041d\u0430\u0432\u0430\u0431\u0433\u0430\u043d\u0434\u0436"
    ],
    "name:urd_x_preferred":[
        "\u0646\u0648\u0627\u0628 \u06af\u0646\u062c"
    ],
    "name:vie_x_preferred":[
        "Nawabganj"
    ],
    "name:zho_cn_x_preferred":[
        "\u7eb3\u74e6\u7518\u6770"
    ],
    "name:zho_tw_x_preferred":[
        "\u7d0d\u74e6\u5e03\u6839\u5091"
    ],
    "wof:name":"Nawabganj",
    "wof:placetype":"locality"
},
  "geometry": {"coordinates":[79.21183000000001,28.1779],"type":"Point"}
}