{
  "type": "Feature",
  "properties": {
    "iso:country":"IN",
    "ks:ks_name":"Jaura Narwar",
    "ks:ks_pop":759,
    "ks:ks_type":"HABITATION",
    "name:eng_x_preferred":[
        "Jaura Narwar"
    ],
    "wof:name":"Jaura Narwar",
    "wof:placetype":"locality",
    "wof:population":759
},
  "geometry": {"coordinates":[80.91745,24.23798],"type":"Point"}
}