{
  "type": "Feature",
  "properties": {
    "iso:country":"IN",
    "ks:ks_name":"Radabali",
    "ks:ks_pop":90,
    "ks:ks_type":"VILLAGE",
    "name:eng_x_preferred":[
        "Radabali"
    ],
    "wof:name":"Radabali",
    "wof:placetype":"locality",
    "wof:population":90
},
  "geometry": {"coordinates":[84.201258,20.010108],"type":"Point"}
}