{
  "type": "Feature",
  "properties": {
    "iso:country":"IN",
    "name:ara_x_preferred":[
        "\u062a\u0634\u064a\u0644\u0628\u0627\u0643\u0627\u0645"
    ],
    "name:ben_bn_x_preferred":[
        "\u099a\u09bf\u09a4\u09cd\u09b2\u09be\u09aa\u0995\u09cd\u0995\u09ae"
    ],
    "name:ben_in_x_preferred":[
        "\u099a\u09bf\u09a4\u09cd\u09b2\u09be\u09aa\u0995\u09cd\u0995\u09ae"
    ],
    "name:bpy_x_preferred":[
        "\u099a\u09bf\u09a4\u09b2\u09aa\u0995\u09cd\u0995\u09ae"
    ],
    "name:eng_x_preferred":[
        "Chitlapakkam"
    ],
    "name:eng_x_variant":[
        "Chithalapakkam"
    ],
    "name:fra_x_preferred":[
        "Chitlapakkam"
    ],
    "name:guj_x_preferred":[
        "\u0a9a\u0abf\u0aa4\u0ab2\u0aaa\u0a95\u0acd\u0a95\u0aae\u0acd"
    ],
    "name:hin_x_preferred":[
        "\u091a\u093f\u0924\u0932\u093e\u092a\u0915\u094d\u0915\u092e"
    ],
    "name:ita_x_preferred":[
        "Chitlapakkam"
    ],
    "name:kan_x_preferred":[
        "\u0c9a\u0cbf\u0ca4\u0ccd\u0cb2\u0caa\u0c95\u0ccd\u0c95\u0cae\u0ccd"
    ],
    "name:mal_x_preferred":[
        "\u0d1a\u0d3f\u0d24\u0d4d\u0d32\u0d2a\u0d3e\u0d15\u0d4d\u0d15\u0d02"
    ],
    "name:mar_x_preferred":[
        "\u091a\u093f\u0924\u0932\u092a\u0915\u094d\u0915\u092e"
    ],
    "name:mlg_x_preferred":[
        "Chitlapakkam"
    ],
    "name:msa_x_preferred":[
        "Chitlapakkam"
    ],
    "name:nan_x_preferred":[
        "Chitlapakkam"
    ],
    "name:new_x_preferred":[
        "\u091a\u093f\u0924\u094d\u0932\u092a\u0915\u094d\u0915\u092e"
    ],
    "name:nld_x_preferred":[
        "Chitlapakkam"
    ],
    "name:pan_x_preferred":[
        "\u0a1a\u0a3f\u0a71\u0a1f\u0a32\u0a3e\u0a2a\u0a71\u0a15\u0a2e"
    ],
    "name:tam_x_preferred":[
        "\u0b9a\u0bbf\u0b9f\u0bcd\u0bb2\u0baa\u0bcd\u0baa\u0bbe\u0b95\u0bcd\u0b95\u0bae\u0bcd"
    ],
    "name:tel_x_preferred":[
        "\u0c1a\u0c3f\u0c1f\u0c4d\u0c32\u0c2a\u0c15\u0c4d\u0c15\u0c2e\u0c4d"
    ],
    "name:urd_x_preferred":[
        "\u0686\u062a\u0644\u0627 \u067e\u0627\u06a9\u0651\u0645"
    ],
    "name:vie_x_preferred":[
        "Chitlapakkam"
    ],
    "name:zho_min_nan_x_preferred":[
        "Chitlapakkam"
    ],
    "name:zho_x_preferred":[
        "\u5947\u7279\u62c9\u5e15\u5361\u59c6"
    ],
    "qs:gn_adm0_cc":"IN",
    "qs:gn_local":1268159,
    "qs:gn_nam_loc":"Kancheepuram, Kanchipuram, Tamil Nadu, IN",
    "qs:gn_namadm1":"25",
    "qs:local_max":274,
    "qs:local_sum":2276,
    "qs:localhoods":28,
    "qs:name":"Chitlapakkam",
    "qs:name_adm0":"India",
    "qs:name_adm1":"Tamil Nadu",
    "qs:name_adm2":"Kancheepuram",
    "qs:name_local":"Kanchipuram",
    "qs:photo_max":20,
    "qs:photo_sum":29,
    "qs:placetype":"Suburb",
    "qs:quad_count":3,
    "qs:woe_adm0":23424848,
    "qs:woe_adm1":2345758,
    "qs:woe_adm2":12586683,
    "qs:woe_lau":0,
    "qs:woe_local":55924325,
    "qs:woe_ver":"7.10.0",
    "wd:wordcount":2220,
    "wof:lang":[
        "eng"
    ],
    "wof:name":"Chitlapakkam",
    "wof:placetype":"neighbourhood"
},
  "geometry": {"coordinates":[80.146495,12.937461],"type":"Point"}
}