{
  "type": "Feature",
  "properties": {
    "iso:country":"IN",
    "name:bpy_x_preferred":[
        "\u099a\u09bf\u09a4\u09b2\u09aa\u0995\u09cd\u0995\u09ae"
    ],
    "name:eng_x_preferred":[
        "Chitlapakkam"
    ],
    "name:eng_x_variant":[
        "Chithalapakkam"
    ],
    "name:ita_x_preferred":[
        "Chitlapakkam"
    ],
    "name:mlg_x_preferred":[
        "Chitlapakkam"
    ],
    "name:msa_x_preferred":[
        "Chitlapakkam"
    ],
    "name:new_x_preferred":[
        "\u091a\u093f\u0924\u094d\u0932\u092a\u0915\u094d\u0915\u092e"
    ],
    "name:nld_x_preferred":[
        "Chitlapakkam"
    ],
    "name:tam_x_preferred":[
        "\u0b9a\u0bbf\u0b9f\u0bcd\u0bb2\u0baa\u0bcd\u0baa\u0bbe\u0b95\u0bcd\u0b95\u0bae\u0bcd"
    ],
    "name:unk_x_variant":[
        "Chitlapakkam"
    ],
    "name:vie_x_preferred":[
        "Chitlapakkam"
    ],
    "name:zho_min_nan_x_preferred":[
        "Chitlapakkam"
    ],
    "name:zho_x_preferred":[
        "\u5947\u7279\u62c9\u5e15\u5361\u59c6"
    ],
    "qs:gn_adm0_cc":"IN",
    "qs:gn_local":1268159,
    "qs:gn_nam_loc":"Kancheepuram, Kanchipuram, Tamil Nadu, IN",
    "qs:gn_namadm1":"25",
    "qs:local_max":274,
    "qs:local_sum":2276,
    "qs:localhoods":28,
    "qs:name":"Chitlapakkam",
    "qs:name_adm0":"India",
    "qs:name_adm1":"Tamil Nadu",
    "qs:name_adm2":"Kancheepuram",
    "qs:name_local":"Kanchipuram",
    "qs:photo_max":20,
    "qs:photo_sum":29,
    "qs:placetype":"Suburb",
    "qs:quad_count":3,
    "qs:woe_adm0":23424848,
    "qs:woe_adm1":2345758,
    "qs:woe_adm2":12586683,
    "qs:woe_lau":0,
    "qs:woe_local":55924325,
    "qs:woe_ver":"7.10.0",
    "wd:wordcount":2220,
    "wof:lang":[
        "eng"
    ],
    "wof:name":"Chitlapakkam",
    "wof:placetype":"neighbourhood"
},
  "geometry": {"coordinates":[80.146495,12.937461],"type":"Point"}
}