{
  "type": "Feature",
  "properties": {
    "iso:country":"IN",
    "ks:ks_name":"Nani Tambadi",
    "ks:ks_pop":3209,
    "ks:ks_type":"VILLAGE",
    "name:eng_x_preferred":[
        "Nani Tambadi"
    ],
    "wof:name":"Nani Tambadi",
    "wof:placetype":"locality",
    "wof:population":3209
},
  "geometry": {"coordinates":[72.993764,20.32419],"type":"Point"}
}