{
  "type": "Feature",
  "properties": {
    "iso:country":"IN",
    "name:ara_x_preferred":[
        "\u0645\u0627\u0644\u064a \u0648\u0645\u0648\u0646\u062c\u064a\u0631\u0627"
    ],
    "name:ben_bn_x_preferred":[
        "\u09ae\u09be\u09b2\u09bf \u0993 \u09ae\u09c1\u099e\u09cd\u099c\u09c7\u09b0\u09bf"
    ],
    "name:ben_in_x_preferred":[
        "\u09ae\u09be\u09b2\u09bf \u0993 \u09ae\u09c1\u099e\u09cd\u099c\u09c7\u09b0\u09bf"
    ],
    "name:eng_x_preferred":[
        "Mali and Munjeri"
    ],
    "name:guj_x_preferred":[
        "\u0aae\u0abe\u0ab2\u0ac0 \u0a85\u0aa8\u0ac7 \u0aae\u0ac1\u0a82\u0a9c\u0ac7\u0ab0\u0ac0"
    ],
    "name:hin_x_preferred":[
        "\u092e\u093e\u0932\u0940 \u0935 \u092e\u0941\u0902\u091c\u0947\u0930\u0940"
    ],
    "name:kan_x_preferred":[
        "\u0cae\u0cbe\u0cb2\u0cbf \u0cae\u0ca4\u0ccd\u0ca4\u0cc1 \u0cae\u0cc1\u0c82\u0c9c\u0cc7\u0cb0\u0cbf"
    ],
    "name:mal_x_preferred":[
        "\u0d2e\u0d3e\u0d32\u0d3f \u0d2e\u0d41\u0d1e\u0d4d\u0d1c\u0d47\u0d30\u0d3f"
    ],
    "name:mar_x_preferred":[
        "\u092e\u093e\u0932\u0940 \u0906\u0923\u093f \u092e\u0941\u0902\u091c\u0947\u0930\u0940"
    ],
    "name:pan_x_preferred":[
        "\u0a2e\u0a3e\u0a32\u0a40 \u0a05\u0a24\u0a47 \u0a2e\u0a41\u0a70\u0a1c\u0a48\u0a30\u0a40"
    ],
    "name:tam_x_preferred":[
        "\u0bae\u0bbe\u0bb2\u0bbf \u0bae\u0bb1\u0bcd\u0bb1\u0bc1\u0bae\u0bcd \u0bae\u0bc1\u0b9e\u0bcd\u0b9a\u0bc6\u0bb0\u0bbf"
    ],
    "name:tel_x_preferred":[
        "\u0c2e\u0c3e\u0c32\u0c3f \u0c2e\u0c30\u0c3f\u0c2f\u0c41 \u0c2e\u0c02\u0c1c\u0c47\u0c30\u0c40"
    ],
    "name:urd_x_preferred":[
        "\u0645\u0627\u0644\u06cc \u0627\u0648\u0631 \u0645\u0646\u062c\u06cc\u0631\u06cc"
    ],
    "qs:gn_adm0_cc":"IN",
    "qs:gn_fcode":"PPLX",
    "qs:gn_local":1259229,
    "qs:gn_nam_loc":"Pune, Pune, Maharashtra, IN",
    "qs:gn_namadm1":"16",
    "qs:gn_name":"Mali and Munjeri",
    "qs:local_max":2969,
    "qs:local_sum":13446,
    "qs:localhoods":37,
    "qs:name":"Mali and Munjeri",
    "qs:name_adm0":"India",
    "qs:name_adm1":"Maharashtra",
    "qs:name_adm2":"Pune",
    "qs:name_local":"Pune",
    "qs:photo_max":305,
    "qs:photo_sum":1712,
    "qs:placetype":"Suburb",
    "qs:quad_count":78,
    "qs:woe_adm0":23424848,
    "qs:woe_adm1":2345750,
    "qs:woe_adm2":12586544,
    "qs:woe_lau":0,
    "qs:woe_local":2295412,
    "qs:woe_ver":"7.10.0",
    "wof:lang":[
        "eng"
    ],
    "wof:name":"Mali and Munjeri",
    "wof:placetype":"neighbourhood"
},
  "geometry": {"coordinates":[73.869873,18.528067],"type":"Point"}
}