{
  "type": "Feature",
  "properties": {
    "iso:country":"IN",
    "ks:ks_name":"Goudaguda",
    "ks:ks_pop":1093,
    "ks:ks_type":"HABITATION",
    "name:eng_x_preferred":[
        "Goudaguda"
    ],
    "wof:name":"Goudaguda",
    "wof:placetype":"locality",
    "wof:population":1093
},
  "geometry": {"coordinates":[81.976645,18.492136],"type":"Point"}
}