{
  "type": "Feature",
  "properties": {
    "gn:admin1_code":"34.0",
    "gn:admin2_code":"206.0",
    "gn:asciiname":"Sirkhandi Bhitha",
    "gn:country_code":"IN",
    "gn:dem":68,
    "gn:feature_class":"P",
    "gn:feature_code":"PPL",
    "gn:name":"Sirkhandi Bhitha",
    "gn:population":0,
    "gn:timezone":"Asia/Kolkata",
    "iso:country":"IN",
    "wof:name":"Sirkhandi Bhitha",
    "wof:placetype":"locality"
},
  "geometry": {"coordinates":[85.77871,26.62439],"type":"Point"}
}