{
  "type": "Feature",
  "properties": {
    "iso:country":"IN",
    "ks:ks_name":"Padubar",
    "ks:ks_pop":1340,
    "ks:ks_type":"VILLAGE",
    "name:eng_x_preferred":[
        "Padubar"
    ],
    "wof:name":"Padubar",
    "wof:placetype":"locality",
    "wof:population":1340
},
  "geometry": {"coordinates":[87.49227999999999,21.7226],"type":"Point"}
}