{
  "type": "Feature",
  "properties": {
    "gn:admin1_code":"11",
    "gn:admin2_code":"33.0",
    "gn:asciiname":"Kandhar",
    "gn:country_code":"IN",
    "gn:dem":1464,
    "gn:feature_class":"P",
    "gn:feature_code":"PPL",
    "gn:name":"Kandh\u0101r",
    "gn:population":0,
    "gn:timezone":"Asia/Kolkata",
    "iso:country":"IN",
    "name:ben_x_preferred":[
        "\u0995\u09be\u09a8\u09a7\u09be\u09b0"
    ],
    "name:bpy_x_preferred":[
        "\u0995\u09be\u09a8\u09a7\u09be\u09b0"
    ],
    "name:hin_x_preferred":[
        "\u0915\u0902\u0927\u093e\u0930"
    ],
    "name:ita_x_preferred":[
        "Kandhar"
    ],
    "name:mar_x_preferred":[
        "\u0915\u0902\u0927\u093e\u0930"
    ],
    "name:msa_x_preferred":[
        "Kandhar"
    ],
    "name:new_x_preferred":[
        "\u0915\u0928\u094d\u0927\u0930"
    ],
    "name:nld_x_preferred":[
        "Kandhar"
    ],
    "name:por_x_preferred":[
        "Kandhar"
    ],
    "name:urd_x_preferred":[
        "\u06a9\u0646\u062f\u06be\u0627\u0631"
    ],
    "name:vie_x_preferred":[
        "Kandhar"
    ],
    "name:zho_x_preferred":[
        "\u574e\u8fbe\u5c14"
    ],
    "wof:name":"Kandhar",
    "wof:placetype":"locality"
},
  "geometry": {"coordinates":[77.19943000000001,31.22142],"type":"Point"}
}