{
  "type": "Feature",
  "properties": {
    "iso:country":"IN",
    "ks:ks_name":"Hawal Bagh Farm",
    "ks:ks_pop":71,
    "ks:ks_type":"HABITATION",
    "name:eng_x_preferred":[
        "Hawal Bagh Farm"
    ],
    "wof:name":"Hawal Bagh Farm",
    "wof:placetype":"locality",
    "wof:population":71
},
  "geometry": {"coordinates":[79.646152,29.633803],"type":"Point"}
}