{
  "type": "Feature",
  "properties": {
    "gn:gn_country":"IN",
    "gn:gn_fcode":"PPLX",
    "gn:gn_pop":0,
    "iso:country":"IN",
    "name:ben_x_preferred":[
        "\u09ac\u09c7\u09b9\u09be\u09b2\u09be"
    ],
    "name:eng_x_preferred":[
        "Behala"
    ],
    "name:eng_x_variant":[
        "South Suburban",
        "S Suburban"
    ],
    "name:hin_x_preferred":[
        "\u092c\u0947\u0939\u093e\u0932\u093e"
    ],
    "name:mar_x_preferred":[
        "\u092c\u0947\u0939\u093e\u0932\u093e"
    ],
    "name:und_x_preferred":[
        "Beh\u0101la"
    ],
    "name:unk_x_variant":[
        "South Suburban",
        "Behala"
    ],
    "qs_pg:aaroncc":"IN",
    "qs_pg:gn_country":"IN",
    "qs_pg:gn_fcode":"PPLX",
    "qs_pg:gn_pop":0,
    "qs_pg:name":"Behala",
    "qs_pg:name_adm0":"India",
    "qs_pg:name_adm1":"West Bengal",
    "qs_pg:photos":135,
    "qs_pg:photos_1k":27,
    "qs_pg:photos_9k":1,
    "qs_pg:photos_9r":3,
    "qs_pg:photos_all":135,
    "qs_pg:photos_sr":3,
    "qs_pg:pop_sr":0,
    "qs_pg:qs_pg_placetype":"neighbourhood",
    "qs_pg:qs_pg_placetype_gp":"Suburb",
    "qs_pg:woe_adm0":23424848,
    "woe:adm0_id":23424848,
    "woe:name_adm0":"India",
    "woe:name_adm1":"West Bengal",
    "woe:placetype":"Suburb",
    "wof:name":"Behala",
    "wof:placetype":"neighbourhood"
},
  "geometry": {"coordinates":[88.27884,22.50147],"type":"Point"}
}