{
  "type": "Feature",
  "properties": {
    "gn:country":"IN",
    "gn:fcode":"PPLX",
    "gn:population":0,
    "iso:country":"IN",
    "name:ara_x_preferred":[
        "\u0628\u0647\u0627\u0644\u0627"
    ],
    "name:ben_bn_x_preferred":[
        "\u09ac\u09c7\u09b9\u09be\u09b2\u09be"
    ],
    "name:ben_in_x_preferred":[
        "\u09ac\u09c7\u09b9\u09be\u09b2\u09be"
    ],
    "name:ben_x_preferred":[
        "\u09ac\u09c7\u09b9\u09be\u09b2\u09be"
    ],
    "name:eng_x_preferred":[
        "Behala"
    ],
    "name:eng_x_variant":[
        "South Suburban",
        "S Suburban"
    ],
    "name:guj_x_preferred":[
        "\u0aac\u0ac7\u0ab9\u0abe\u0ab2\u0abe"
    ],
    "name:hin_x_preferred":[
        "\u092c\u0947\u0939\u093e\u0932\u093e"
    ],
    "name:kan_x_preferred":[
        "\u0cac\u0cc6\u0cb9\u0cbe\u0cb2"
    ],
    "name:mal_x_preferred":[
        "\u0d2c\u0d46\u0d39\u0d3e\u0d32"
    ],
    "name:mar_x_preferred":[
        "\u092c\u0947\u0939\u0932\u093e"
    ],
    "name:mar_x_variant":[
        "\u092c\u0947\u0939\u093e\u0932\u093e"
    ],
    "name:nld_x_preferred":[
        "Behala"
    ],
    "name:pan_x_preferred":[
        "\u0a2c\u0a47\u0a39\u0a3e\u0a32\u0a3e"
    ],
    "name:rus_x_preferred":[
        "\u0411\u0435\u0445\u0430\u043b\u0430"
    ],
    "name:tam_x_preferred":[
        "\u0baa\u0bc6\u0bb9\u0bbe\u0bb2\u0bbe"
    ],
    "name:tel_x_preferred":[
        "\u0c2c\u0c46\u0c39\u0c3e\u0c32\u0c3e"
    ],
    "name:und_x_variant":[
        "Beh\u0101la"
    ],
    "name:urd_x_preferred":[
        "\u0628\u06cc\u06c1\u0627\u0644\u0627"
    ],
    "qs_pg:aaroncc":"IN",
    "qs_pg:gn_country":"IN",
    "qs_pg:gn_fcode":"PPLX",
    "qs_pg:gn_pop":0,
    "qs_pg:name":"Behala",
    "qs_pg:name_adm0":"India",
    "qs_pg:name_adm1":"West Bengal",
    "qs_pg:photos":135,
    "qs_pg:photos_1k":27,
    "qs_pg:photos_9k":1,
    "qs_pg:photos_9r":3,
    "qs_pg:photos_all":135,
    "qs_pg:photos_sr":3,
    "qs_pg:pop_sr":0,
    "qs_pg:qs_pg_placetype":"neighbourhood",
    "qs_pg:qs_pg_placetype_gp":"Suburb",
    "qs_pg:woe_adm0":23424848,
    "woe:adm0_id":23424848,
    "woe:name_adm0":"India",
    "woe:name_adm1":"West Bengal",
    "woe:placetype":"Suburb",
    "wof:name":"Behala",
    "wof:placetype":"neighbourhood"
},
  "geometry": {"coordinates":[88.27884,22.50147],"type":"Point"}
}