{
  "type": "Feature",
  "properties": {
    "iso:country":"IN",
    "ks:ks_name":"Langalkata",
    "ks:ks_pop":432,
    "ks:ks_type":"VILLAGE",
    "name:eng_x_preferred":[
        "Langalkata"
    ],
    "wof:name":"Langalkata",
    "wof:placetype":"locality",
    "wof:population":432
},
  "geometry": {"coordinates":[85.084431,22.079172],"type":"Point"}
}