{
  "type": "Feature",
  "properties": {
    "gn:admin1_code":"21.0",
    "gn:admin2_code":"398.0",
    "gn:asciiname":"Tikarapadu",
    "gn:country_code":"IN",
    "gn:dem":238,
    "gn:feature_class":"P",
    "gn:feature_code":"PPL",
    "gn:name":"Tikarap\u0101du",
    "gn:population":0,
    "gn:timezone":"Asia/Kolkata",
    "iso:country":"IN",
    "ks:ks_name":"Tikaraparu",
    "ks:ks_pop":217,
    "ks:ks_type":"VILLAGE",
    "name:eng_x_preferred":[
        "Tikaraparu"
    ],
    "name:eng_x_variant":[
        "Tikarapadu"
    ],
    "wof:name":"Tikaraparu",
    "wof:placetype":"locality",
    "wof:population":217
},
  "geometry": {"coordinates":[83.25586300000001,18.884457],"type":"Point"}
}