{
  "type": "Feature",
  "properties": {
    "gn:admin1_code":"39.0",
    "gn:admin2_code":"64.0",
    "gn:asciiname":"Badarua Tila",
    "gn:country_code":"IN",
    "gn:dem":1383,
    "gn:feature_class":"P",
    "gn:feature_code":"PPL",
    "gn:name":"Badarua T\u012bla",
    "gn:population":0,
    "gn:timezone":"Asia/Kolkata",
    "iso:country":"IN",
    "ks:ks_name":"Badaruwa Tila",
    "ks:ks_pop":30,
    "ks:ks_type":"HABITATION",
    "name:eng_x_preferred":[
        "Badaruwa Tila"
    ],
    "name:eng_x_variant":[
        "Badarua Tila"
    ],
    "wof:name":"Badaruwa Tila",
    "wof:placetype":"locality",
    "wof:population":30
},
  "geometry": {"coordinates":[79.17823,29.73245],"type":"Point"}
}