{
  "type": "Feature",
  "properties": {
    "iso:country":"IN",
    "ks:ks_name":"Banjarutandya",
    "ks:ks_pop":1519,
    "ks:ks_type":"HABITATION",
    "name:eng_x_preferred":[
        "Banjarutandya"
    ],
    "wof:name":"Banjarutandya",
    "wof:placetype":"locality",
    "wof:population":1519
},
  "geometry": {"coordinates":[75.940478,13.507016],"type":"Point"}
}