{
  "type": "Feature",
  "properties": {
    "gn:admin1_code":"25.0",
    "gn:admin2_code":"606.0",
    "gn:asciiname":"Narasingapuram",
    "gn:country_code":"IN",
    "gn:dem":158,
    "gn:feature_class":"P",
    "gn:feature_code":"PPL",
    "gn:name":"Narasingapuram",
    "gn:population":0,
    "gn:timezone":"Asia/Kolkata",
    "iso:country":"IN",
    "ks:ks_name":"Narasingapuram",
    "ks:ks_pop":1413,
    "ks:ks_type":"VILLAGE",
    "name:eng_x_preferred":[
        "Narasingapuram"
    ],
    "name:ita_x_preferred":[
        "Narasingapuram"
    ],
    "name:nld_x_preferred":[
        "Narasingapuram"
    ],
    "name:tam_x_preferred":[
        "\u0ba8\u0bb0\u0b9a\u0bbf\u0b99\u0bcd\u0b95\u0baa\u0bc1\u0bb0\u0bae\u0bcd"
    ],
    "wof:name":"Narasingapuram",
    "wof:placetype":"locality",
    "wof:population":1413
},
  "geometry": {"coordinates":[79.262846,12.527991],"type":"Point"}
}