{
  "type": "Feature",
  "properties": {
    "gn:admin1_code":"36.0",
    "gn:admin2_code":"172.0",
    "gn:asciiname":"Maikuwapur",
    "gn:country_code":"IN",
    "gn:dem":112,
    "gn:feature_class":"P",
    "gn:feature_code":"PPL",
    "gn:name":"Maikuw\u0101pur",
    "gn:population":0,
    "gn:timezone":"Asia/Kolkata",
    "iso:country":"IN",
    "name:und_x_variant":[
        "Maikuw\u0101pur",
        "Khobhra"
    ],
    "wof:name":"Maikuwapur",
    "wof:placetype":"locality"
},
  "geometry": {"coordinates":[80.89811999999998,25.70717],"type":"Point"}
}