{
  "type": "Feature",
  "properties": {
    "gn:admin1_code":"19.0",
    "gn:admin2_code":"566.0",
    "gn:asciiname":"Siddavvanadurga",
    "gn:country_code":"IN",
    "gn:dem":699,
    "gn:feature_class":"P",
    "gn:feature_code":"PPL",
    "gn:name":"Siddavvanadurga",
    "gn:population":0,
    "gn:timezone":"Asia/Kolkata",
    "iso:country":"IN",
    "wof:name":"Siddavvanadurga",
    "wof:placetype":"locality"
},
  "geometry": {"coordinates":[76.32160999999998,14.32527],"type":"Point"}
}