{
  "type": "Feature",
  "properties": {
    "gn:admin1_code":"36",
    "gn:admin2_code":"195.0",
    "gn:asciiname":"Shaikhpur",
    "gn:country_code":"IN",
    "gn:dem":78,
    "gn:feature_class":"P",
    "gn:feature_code":"PPL",
    "gn:name":"Shaikhpur",
    "gn:population":0,
    "gn:timezone":"Asia/Kolkata",
    "iso:country":"IN",
    "name:und_x_variant":[
        "Singhpur"
    ],
    "wof:name":"Shaikhpur",
    "wof:placetype":"neighbourhood"
},
  "geometry": {"coordinates":[83.23954999999999,25.57174],"type":"Point"}
}