{
  "type": "Feature",
  "properties": {
    "iso:country":"IN",
    "ks:ks_name":"Amirthi",
    "ks:ks_pop":122,
    "ks:ks_type":"HABITATION",
    "name:eng_x_preferred":[
        "Amirthi"
    ],
    "wof:name":"Amirthi",
    "wof:placetype":"locality",
    "wof:population":122
},
  "geometry": {"coordinates":[79.058941,12.725967],"type":"Point"}
}