{
  "type": "Feature",
  "properties": {
    "iso:country":"IN",
    "ks:ks_name":"Rautpada",
    "ks:ks_pop":189,
    "ks:ks_type":"HABITATION",
    "name:eng_x_preferred":[
        "Rautpada"
    ],
    "wof:name":"Rautpada",
    "wof:placetype":"locality",
    "wof:population":189
},
  "geometry": {"coordinates":[73.19342,19.660004],"type":"Point"}
}