{
  "type": "Feature",
  "properties": {
    "iso:country":"IN",
    "ks:ks_name":"Dikoli Khurd",
    "ks:ks_pop":579,
    "ks:ks_type":"HABITATION",
    "name:eng_x_preferred":[
        "Dikoli Khurd"
    ],
    "wof:name":"Dikoli Khurd",
    "wof:placetype":"locality",
    "wof:population":579
},
  "geometry": {"coordinates":[76.726026,26.289323],"type":"Point"}
}