{
  "type": "Feature",
  "properties": {
    "iso:country":"IN",
    "ks:ks_name":"Bhagnewadi",
    "ks:ks_pop":531,
    "ks:ks_type":"HABITATION",
    "name:eng_x_preferred":[
        "Bhagnewadi"
    ],
    "wof:name":"Bhagnewadi",
    "wof:placetype":"locality",
    "wof:population":531
},
  "geometry": {"coordinates":[73.325486,17.590333],"type":"Point"}
}