{
  "type": "Feature",
  "properties": {
    "iso:country":"IN",
    "ks:ks_name":"Dhangharwadi",
    "ks:ks_pop":94,
    "ks:ks_type":"HABITATION",
    "name:eng_x_preferred":[
        "Dhangharwadi"
    ],
    "wof:name":"Dhangharwadi",
    "wof:placetype":"locality",
    "wof:population":94
},
  "geometry": {"coordinates":[73.472752,17.87376],"type":"Point"}
}