{
  "type": "Feature",
  "properties": {
    "iso:country":"IN",
    "ks:ks_name":"Harnagar Jangalia Gaon",
    "ks:ks_pop":300,
    "ks:ks_type":"HABITATION",
    "ks:ks_uagg_main":0,
    "name:eng_x_preferred":[
        "Harnagar Jangalia Gaon"
    ],
    "wof:name":"Harnagar Jangalia Gaon",
    "wof:placetype":"neighbourhood",
    "wof:population":300
},
  "geometry": {"coordinates":[79.604527,29.33423],"type":"Point"}
}