{
  "type": "Feature",
  "properties": {
    "iso:country":"IN",
    "ks:ks_name":"Parampasi",
    "ks:ks_pop":16,
    "ks:ks_type":"HABITATION",
    "name:eng_x_preferred":[
        "Parampasi"
    ],
    "wof:name":"Parampasi",
    "wof:placetype":"locality",
    "wof:population":16
},
  "geometry": {"coordinates":[85.08457900000001,21.237193],"type":"Point"}
}