{
  "type": "Feature",
  "properties": {
    "gn:admin1_code":"34.0",
    "gn:admin2_code":"230.0",
    "gn:asciiname":"Sattar",
    "gn:country_code":"IN",
    "gn:dem":59,
    "gn:feature_class":"P",
    "gn:feature_code":"PPL",
    "gn:name":"Sattar",
    "gn:population":0,
    "gn:timezone":"Asia/Kolkata",
    "iso:country":"IN",
    "ks:ks_name":"Sattar",
    "ks:ks_pop":3558,
    "ks:ks_type":"VILLAGE",
    "ks:ks_uagg_main":0,
    "name:eng_x_preferred":[
        "Sattar"
    ],
    "wof:name":"Sattar",
    "wof:placetype":"neighbourhood",
    "wof:population":3558
},
  "geometry": {"coordinates":[84.983468,25.604205],"type":"Point"}
}