{
  "type": "Feature",
  "properties": {
    "gn:admin1_code":"11.0",
    "gn:admin2_code":"32.0",
    "gn:asciiname":"Rau",
    "gn:country_code":"IN",
    "gn:dem":1780,
    "gn:feature_class":"P",
    "gn:feature_code":"PPL",
    "gn:name":"Rau",
    "gn:population":0,
    "gn:timezone":"Asia/Kolkata",
    "iso:country":"IN",
    "name:ita_x_preferred":[
        "Rau"
    ],
    "name:msa_x_preferred":[
        "Rau"
    ],
    "name:nld_x_preferred":[
        "Rau"
    ],
    "name:ori_x_preferred":[
        "\u0b30\u0b3e\u0b09"
    ],
    "name:por_x_preferred":[
        "Rau"
    ],
    "name:spa_x_preferred":[
        "Rau"
    ],
    "wof:name":"Rau",
    "wof:placetype":"locality"
},
  "geometry": {"coordinates":[77.64435,30.69585],"type":"Point"}
}