{
  "type": "Feature",
  "properties": {
    "iso:country":"IN",
    "ks:ks_name":"Suwakhedi",
    "ks:ks_pop":1034,
    "ks:ks_type":"VILLAGE",
    "ks:ks_uagg_main":0,
    "name:eng_x_preferred":[
        "Suwakhedi"
    ],
    "wof:name":"Suwakhedi",
    "wof:placetype":"neighbourhood",
    "wof:population":1034
},
  "geometry": {"coordinates":[77.86582199999999,22.705129],"type":"Point"}
}