{
  "type": "Feature",
  "properties": {
    "iso:country":"IN",
    "ks:ks_name":"Baragram",
    "ks:ks_pop":2142,
    "ks:ks_type":"VILLAGE",
    "ks:ks_uagg_main":0,
    "name:eng_x_preferred":[
        "Baragram"
    ],
    "wof:name":"Baragram",
    "wof:placetype":"neighbourhood",
    "wof:population":2142
},
  "geometry": {"coordinates":[88.05737499999999,22.514821],"type":"Point"}
}