{
  "type": "Feature",
  "properties": {
    "iso:country":"IN",
    "ks:ks_name":"Duwarmara Pathar",
    "ks:ks_pop":577,
    "ks:ks_type":"VILLAGE",
    "name:eng_x_preferred":[
        "Duwarmara Pathar"
    ],
    "wof:name":"Duwarmara Pathar",
    "wof:placetype":"locality",
    "wof:population":577
},
  "geometry": {"coordinates":[95.72544600000001,27.497863],"type":"Point"}
}