{
  "type": "Feature",
  "properties": {
    "gn:admin1_code":"35",
    "gn:admin2_code":"423.0",
    "gn:asciiname":"Sular Khurd",
    "gn:country_code":"IN",
    "gn:dem":362,
    "gn:feature_class":"P",
    "gn:feature_code":"PPL",
    "gn:name":"Sul\u0101r Khurd",
    "gn:population":0,
    "gn:timezone":"Asia/Kolkata",
    "iso:country":"IN",
    "wof:name":"Sular Khurd",
    "wof:placetype":"locality"
},
  "geometry": {"coordinates":[78.07678,24.88475],"type":"Point"}
}