{
  "type": "Feature",
  "properties": {
    "gn:admin1_code":"35.0",
    "gn:admin2_code":"447.0",
    "gn:asciiname":"Paradsinga",
    "gn:country_code":"IN",
    "gn:dem":759,
    "gn:feature_class":"P",
    "gn:feature_code":"PPL",
    "gn:name":"P\u0101radsinga",
    "gn:population":0,
    "gn:timezone":"Asia/Kolkata",
    "iso:country":"IN",
    "wof:name":"Paradsinga",
    "wof:placetype":"locality"
},
  "geometry": {"coordinates":[78.31081999999998,21.78467],"type":"Point"}
}