{
  "type": "Feature",
  "properties": {
    "gn:admin1_code":"35.0",
    "gn:admin2_code":"455.0",
    "gn:asciiname":"Kothidev",
    "gn:country_code":"IN",
    "gn:dem":936,
    "gn:feature_class":"P",
    "gn:feature_code":"PPL",
    "gn:name":"Kothidev",
    "gn:population":0,
    "gn:timezone":"Asia/Kolkata",
    "iso:country":"IN",
    "wof:name":"Kothidev",
    "wof:placetype":"locality"
},
  "geometry": {"coordinates":[78.52691999999998,22.20831],"type":"Point"}
}