{
  "type": "Feature",
  "properties": {
    "iso:country":"IN",
    "ks:ks_name":"Ramulaputtu",
    "ks:ks_pop":226,
    "ks:ks_type":"HABITATION",
    "name:eng_x_preferred":[
        "Ramulaputtu"
    ],
    "wof:name":"Ramulaputtu",
    "wof:placetype":"locality",
    "wof:population":226
},
  "geometry": {"coordinates":[82.69102700000001,18.094807],"type":"Point"}
}