{
  "type": "Feature",
  "properties": {
    "iso:country":"IN",
    "ks:ks_name":"Morewadi",
    "ks:ks_pop":147,
    "ks:ks_type":"HABITATION",
    "name:eng_x_preferred":[
        "Morewadi"
    ],
    "wof:name":"Morewadi",
    "wof:placetype":"locality",
    "wof:population":147
},
  "geometry": {"coordinates":[73.265736,17.832753],"type":"Point"}
}