{
  "type": "Feature",
  "properties": {
    "iso:country":"IN",
    "ks:ks_name":"Shivnara",
    "ks:ks_pop":105,
    "ks:ks_type":"HABITATION",
    "name:eng_x_preferred":[
        "Shivnara"
    ],
    "wof:name":"Shivnara",
    "wof:placetype":"locality",
    "wof:population":105
},
  "geometry": {"coordinates":[78.913528,19.625006],"type":"Point"}
}