{
  "type": "Feature",
  "properties": {
    "iso:country":"IN",
    "ks:ks_name":"Kunda Rai",
    "ks:ks_pop":287,
    "ks:ks_type":"VILLAGE",
    "name:eng_x_preferred":[
        "Kunda Rai"
    ],
    "wof:name":"Kunda Rai",
    "wof:placetype":"locality",
    "wof:population":287
},
  "geometry": {"coordinates":[77.50217600000001,25.246505],"type":"Point"}
}