{
  "type": "Feature",
  "properties": {
    "gn:admin1_code":"37",
    "gn:admin2_code":"414.0",
    "gn:asciiname":"Kokhapal",
    "gn:country_code":"IN",
    "gn:dem":557,
    "gn:feature_class":"P",
    "gn:feature_code":"PPL",
    "gn:name":"Kokhap\u0101l",
    "gn:population":0,
    "gn:timezone":"Asia/Kolkata",
    "iso:country":"IN",
    "wof:name":"Kokhapal",
    "wof:placetype":"locality"
},
  "geometry": {"coordinates":[82.0996,19.12851],"type":"Point"}
}