{
  "type": "Feature",
  "properties": {
    "iso:country":"IN",
    "ks:ks_name":"Borraponukuvalasa",
    "ks:ks_pop":16,
    "ks:ks_type":"HABITATION",
    "name:eng_x_preferred":[
        "Borraponukuvalasa"
    ],
    "wof:name":"Borraponukuvalasa",
    "wof:placetype":"locality",
    "wof:population":16
},
  "geometry": {"coordinates":[83.255135,18.600133],"type":"Point"}
}