{
  "type": "Feature",
  "properties": {
    "iso:country":"IN",
    "ks:ks_name":"Galdhar",
    "ks:ks_pop":772,
    "ks:ks_type":"VILLAGE",
    "name:eng_x_preferred":[
        "Galdhar"
    ],
    "wof:name":"Galdhar",
    "wof:placetype":"locality",
    "wof:population":772
},
  "geometry": {"coordinates":[74.52051400000001,23.228432],"type":"Point"}
}