{
  "type": "Feature",
  "properties": {
    "gn:admin1_code":"11.0",
    "gn:admin2_code":"27.0",
    "gn:asciiname":"Ser Kalan",
    "gn:country_code":"IN",
    "gn:dem":1942,
    "gn:feature_class":"P",
    "gn:feature_code":"PPL",
    "gn:name":"Ser Kal\u0101n",
    "gn:population":0,
    "gn:timezone":"Asia/Kolkata",
    "iso:country":"IN",
    "wof:name":"Ser Kalan",
    "wof:placetype":"locality"
},
  "geometry": {"coordinates":[77.14431999999999,31.4264],"type":"Point"}
}