{
  "type": "Feature",
  "properties": {
    "gn:admin1_code":"25.0",
    "gn:admin2_code":"604.0",
    "gn:asciiname":"Melamayyur",
    "gn:country_code":"IN",
    "gn:dem":49,
    "gn:feature_class":"P",
    "gn:feature_code":"PPL",
    "gn:name":"Melamayy\u016br",
    "gn:population":0,
    "gn:timezone":"Asia/Kolkata",
    "iso:country":"IN",
    "ks:ks_alt_nam":"Melamayy\u016br",
    "ks:ks_name":"Melamayyur",
    "ks:ks_type":"VILLAGE",
    "ks:ks_uagg_main":0,
    "name:eng_x_preferred":[
        "Melamayyur"
    ],
    "name:eng_x_variant":[
        "Melamayy\u016br"
    ],
    "wof:name":"Melamayyur",
    "wof:placetype":"locality"
},
  "geometry": {"coordinates":[79.989051,12.672898],"type":"Point"}
}