{
  "type": "Feature",
  "properties": {
    "iso:country":"IN",
    "ks:ks_name":"Hannagadde",
    "ks:ks_pop":7,
    "ks:ks_type":"HABITATION",
    "name:eng_x_preferred":[
        "Hannagadde"
    ],
    "wof:name":"Hannagadde",
    "wof:placetype":"locality",
    "wof:population":7
},
  "geometry": {"coordinates":[74.672358,14.715219],"type":"Point"}
}