{
  "type": "Feature",
  "properties": {
    "iso:country":"IN",
    "ks:ks_alt_nam":"Arkara Major supa",
    "ks:ks_name":"Arkara Major Supa",
    "ks:ks_pop":289,
    "ks:ks_type":"HABITATION",
    "ks:ks_uagg_main":0,
    "name:eng_x_preferred":[
        "Arkara Major Supa"
    ],
    "wof:name":"Arkara Major Supa",
    "wof:placetype":"neighbourhood",
    "wof:population":289
},
  "geometry": {"coordinates":[91.251448,26.697811],"type":"Point"}
}