{
  "type": "Feature",
  "properties": {
    "gn:admin1_code":"16.0",
    "gn:admin2_code":"514.0",
    "gn:asciiname":"Rajur",
    "gn:country_code":"IN",
    "gn:dem":626,
    "gn:feature_class":"P",
    "gn:feature_code":"PPL",
    "gn:name":"R\u0101j\u016br",
    "gn:population":0,
    "gn:timezone":"Asia/Kolkata",
    "iso:country":"IN",
    "name:ben_x_preferred":[
        "\u09b0\u09be\u099c\u09c1\u09b0"
    ],
    "name:bpy_x_preferred":[
        "\u09b0\u09be\u099c\u09c1\u09b0"
    ],
    "name:ceb_x_preferred":[
        "R\u0101jur"
    ],
    "name:ita_x_preferred":[
        "Rajur"
    ],
    "name:msa_x_preferred":[
        "Rajur"
    ],
    "name:nld_x_preferred":[
        "Rajur"
    ],
    "name:por_x_preferred":[
        "Rajur"
    ],
    "name:swe_x_preferred":[
        "R\u0101jur"
    ],
    "name:urd_x_preferred":[
        "\u0631\u0627\u062c\u0648\u0631"
    ],
    "name:vie_x_preferred":[
        "Rajur"
    ],
    "name:zho_x_preferred":[
        "\u62c9\u4e45\u5c14"
    ],
    "wof:name":"Rajur",
    "wof:placetype":"locality"
},
  "geometry": {"coordinates":[75.85149,20.05931],"type":"Point"}
}