{
  "type": "Feature",
  "properties": {
    "gn:admin1_code":"12.0",
    "gn:admin2_code":"21.0",
    "gn:asciiname":"Pindi Charkan",
    "gn:country_code":"IN",
    "gn:dem":270,
    "gn:feature_class":"P",
    "gn:feature_code":"PPL",
    "gn:name":"Pindi Charkan",
    "gn:population":0,
    "gn:timezone":"Asia/Kolkata",
    "iso:country":"IN",
    "name:und_x_variant":[
        "Pindi Ch\u0101rk\u0101n",
        "Pindi Charkan"
    ],
    "wof:name":"Pindi Charkan",
    "wof:placetype":"locality"
},
  "geometry": {"coordinates":[74.80634999999999,32.4958],"type":"Point"}
}