{
  "type": "Feature",
  "properties": {
    "iso:country":"IN",
    "ks:ks_name":"Thippapuram",
    "ks:ks_pop":2616,
    "ks:ks_type":"VILLAGE",
    "ks:ks_uagg_main":0,
    "name:eng_x_preferred":[
        "Thippapuram"
    ],
    "wof:name":"Thippapuram",
    "wof:placetype":"locality",
    "wof:population":2616
},
  "geometry": {"coordinates":[78.868287,18.460315],"type":"Point"}
}