{
  "type": "Feature",
  "properties": {
    "iso:country":"IN",
    "ks:ks_name":"Ambatola",
    "ks:ks_pop":322,
    "ks:ks_type":"VILLAGE",
    "ks:ks_uagg_main":0,
    "name:eng_x_preferred":[
        "Ambatola"
    ],
    "wof:name":"Ambatola",
    "wof:placetype":"neighbourhood",
    "wof:population":322
},
  "geometry": {"coordinates":[86.185406,20.879223],"type":"Point"}
}