{
  "type": "Feature",
  "properties": {
    "iso:country":"IN",
    "ks:ks_name":"Jasra",
    "ks:ks_pop":680,
    "ks:ks_type":"VILLAGE",
    "ks:ks_uagg_main":0,
    "name:eng_x_preferred":[
        "Jasra"
    ],
    "wof:name":"Jasra",
    "wof:placetype":"neighbourhood",
    "wof:population":680
},
  "geometry": {"coordinates":[80.316357,26.783238],"type":"Point"}
}