{
  "type": "Feature",
  "properties": {
    "gn:admin1_code":"25.0",
    "gn:admin2_code":"619.0",
    "gn:asciiname":"Melakottagam",
    "gn:country_code":"IN",
    "gn:dem":7,
    "gn:feature_class":"P",
    "gn:feature_code":"PPL",
    "gn:name":"Melakottagam",
    "gn:population":0,
    "gn:timezone":"Asia/Kolkata",
    "iso:country":"IN",
    "ks:ks_name":"Moolagottagam",
    "ks:ks_pop":133,
    "ks:ks_type":"HABITATION",
    "name:eng_x_preferred":[
        "Moolagottagam"
    ],
    "name:eng_x_variant":[
        "Melakottagam"
    ],
    "wof:name":"Moolagottagam",
    "wof:placetype":"locality",
    "wof:population":133
},
  "geometry": {"coordinates":[79.55830899999999,10.55246],"type":"Point"}
}