{
  "type": "Feature",
  "properties": {
    "iso:country":"IN",
    "ks:ks_name":"Atuon Simal",
    "ks:ks_pop":171,
    "ks:ks_type":"HABITATION",
    "name:eng_x_preferred":[
        "Atuon Simal"
    ],
    "wof:name":"Atuon Simal",
    "wof:placetype":"locality",
    "wof:population":171
},
  "geometry": {"coordinates":[86.148318,22.951792],"type":"Point"}
}