{
  "type": "Feature",
  "properties": {
    "gn:admin1_code":"40",
    "gn:admin2_code":"540.0",
    "gn:asciiname":"Gabbeta",
    "gn:country_code":"IN",
    "gn:dem":323,
    "gn:feature_class":"P",
    "gn:feature_code":"PPL",
    "gn:name":"Gabbeta",
    "gn:population":0,
    "gn:timezone":"Asia/Kolkata",
    "iso:country":"IN",
    "ks:ks_name":"Gabbeta",
    "ks:ks_pop":1902,
    "ks:ks_type":"VILLAGE",
    "name:eng_x_preferred":[
        "Gabbeta"
    ],
    "wof:name":"Gabbeta",
    "wof:placetype":"locality",
    "wof:population":1902
},
  "geometry": {"coordinates":[79.323292,17.70706],"type":"Point"}
}