{
  "type": "Feature",
  "properties": {
    "gn:admin1_code":"19.0",
    "gn:admin2_code":"570.0",
    "gn:asciiname":"Hosanhalli",
    "gn:country_code":"IN",
    "gn:dem":765,
    "gn:feature_class":"P",
    "gn:feature_code":"PPL",
    "gn:name":"Hosanhalli",
    "gn:population":0,
    "gn:timezone":"Asia/Kolkata",
    "iso:country":"IN",
    "wof:name":"Hosanhalli",
    "wof:placetype":"locality"
},
  "geometry": {"coordinates":[75.9187,13.74919],"type":"Point"}
}