{
  "type": "Feature",
  "properties": {
    "gn:admin1_code":"19.0",
    "gn:admin2_code":"578.0",
    "gn:asciiname":"Bokkepur",
    "gn:country_code":"IN",
    "gn:dem":821,
    "gn:feature_class":"P",
    "gn:feature_code":"PPL",
    "gn:name":"Bokkep\u016br",
    "gn:population":0,
    "gn:timezone":"Asia/Kolkata",
    "iso:country":"IN",
    "ks:ks_name":"Bokkepura",
    "ks:ks_pop":633,
    "ks:ks_type":"VILLAGE",
    "name:eng_x_preferred":[
        "Bokkepura"
    ],
    "name:eng_x_variant":[
        "Bokkepur"
    ],
    "wof:name":"Bokkepura",
    "wof:placetype":"locality",
    "wof:population":633
},
  "geometry": {"coordinates":[76.868998,11.819485],"type":"Point"}
}