{
  "type": "Feature",
  "properties": {
    "gn:admin1_code":"36",
    "gn:admin2_code":"168.0",
    "gn:asciiname":"Ghanduwa",
    "gn:country_code":"IN",
    "gn:dem":138,
    "gn:feature_class":"P",
    "gn:feature_code":"PPL",
    "gn:name":"Ghanduwa",
    "gn:population":0,
    "gn:timezone":"Asia/Kolkata",
    "iso:country":"IN",
    "name:eng_x_preferred":[
        "Ghanduwa"
    ],
    "wof:name":"Ghanduwa",
    "wof:placetype":"locality"
},
  "geometry": {"coordinates":[80.13785,25.45689],"type":"Point"}
}