{
  "type": "Feature",
  "properties": {
    "iso:country":"IN",
    "ks:ks_alt_nam":"ADAKE VASTI",
    "ks:ks_name":"Adake Vasti",
    "ks:ks_pop":110,
    "ks:ks_type":"HABITATION",
    "name:eng_x_preferred":[
        "Adake Vasti"
    ],
    "wof:name":"Adake Vasti",
    "wof:placetype":"locality",
    "wof:population":110
},
  "geometry": {"coordinates":[74.734893,16.951932],"type":"Point"}
}