{
  "type": "Feature",
  "properties": {
    "iso:country":"IN",
    "ks:ks_alt_nam":"Malshikare wasti",
    "ks:ks_name":"Malshikare Wasti",
    "ks:ks_pop":156,
    "ks:ks_type":"HABITATION",
    "name:eng_x_preferred":[
        "Malshikare Wasti"
    ],
    "wof:name":"Malshikare Wasti",
    "wof:placetype":"locality",
    "wof:population":156
},
  "geometry": {"coordinates":[74.943133,18.692871],"type":"Point"}
}