{
  "type": "Feature",
  "properties": {
    "iso:country":"IN",
    "ks:ks_name":"Maikpur Khurd",
    "ks:ks_type":"VILLAGE",
    "name:eng_x_preferred":[
        "Maikpur Khurd"
    ],
    "wof:name":"Maikpur Khurd",
    "wof:placetype":"locality"
},
  "geometry": {"coordinates":[79.592119,28.293707],"type":"Point"}
}