{
  "type": "Feature",
  "properties": {
    "iso:country":"IN",
    "ks:ks_name":"Jaunpuri",
    "ks:ks_pop":108,
    "ks:ks_type":"VILLAGE",
    "name:eng_x_preferred":[
        "Jaunpuri"
    ],
    "wof:name":"Jaunpuri",
    "wof:placetype":"locality",
    "wof:population":108
},
  "geometry": {"coordinates":[85.03833299999999,25.438967],"type":"Point"}
}