{
  "type": "Feature",
  "properties": {
    "iso:country":"IN",
    "ks:ks_name":"Hope Island",
    "ks:ks_pop":327,
    "ks:ks_type":"HABITATION",
    "name:eng_x_preferred":[
        "Hope Island"
    ],
    "wof:name":"Hope Island",
    "wof:placetype":"locality",
    "wof:population":327
},
  "geometry": {"coordinates":[82.23418100000001,16.802168],"type":"Point"}
}