{
  "type": "Feature",
  "properties": {
    "iso:country":"IN",
    "ks:ks_alt_nam":"GURAVWADI",
    "ks:ks_name":"Guravwadi",
    "ks:ks_pop":37,
    "ks:ks_type":"HABITATION",
    "name:eng_x_preferred":[
        "Guravwadi"
    ],
    "wof:name":"Guravwadi",
    "wof:placetype":"locality",
    "wof:population":37
},
  "geometry": {"coordinates":[73.71159900000001,16.725389],"type":"Point"}
}