{
  "type": "Feature",
  "properties": {
    "iso:country":"IN",
    "ks:ks_alt_nam":"NAGLA KISHOR",
    "ks:ks_name":"Nagla Kishor",
    "ks:ks_pop":120,
    "ks:ks_type":"HABITATION",
    "name:eng_x_preferred":[
        "Nagla Kishor"
    ],
    "wof:name":"Nagla Kishor",
    "wof:placetype":"locality",
    "wof:population":120
},
  "geometry": {"coordinates":[79.052859,26.548069],"type":"Point"}
}