{
  "type": "Feature",
  "properties": {
    "iso:country":"IN",
    "ks:ks_name":"Kajraut Khadar",
    "ks:ks_pop":17,
    "ks:ks_type":"VILLAGE",
    "name:eng_x_preferred":[
        "Kajraut Khadar"
    ],
    "wof:name":"Kajraut Khadar",
    "wof:placetype":"locality",
    "wof:population":17
},
  "geometry": {"coordinates":[77.667303,27.762549],"type":"Point"}
}