{
  "type": "Feature",
  "properties": {
    "iso:country":"IN",
    "ks:ks_name":"Bodang",
    "ks:ks_pop":534,
    "ks:ks_type":"VILLAGE",
    "ks:ks_uagg_main":0,
    "name:eng_x_preferred":[
        "Bodang"
    ],
    "wof:name":"Bodang",
    "wof:placetype":"neighbourhood",
    "wof:population":534
},
  "geometry": {"coordinates":[86.596962,21.017172],"type":"Point"}
}