{
  "type": "Feature",
  "properties": {
    "iso:country":"IN",
    "ks:ks_name":"Lariatanr",
    "ks:ks_pop":355,
    "ks:ks_type":"VILLAGE",
    "ks:ks_uagg_main":0,
    "name:eng_x_preferred":[
        "Lariatanr"
    ],
    "wof:name":"Lariatanr",
    "wof:placetype":"neighbourhood",
    "wof:population":355
},
  "geometry": {"coordinates":[86.147909,24.473864],"type":"Point"}
}