{
  "type": "Feature",
  "properties": {
    "iso:country":"IN",
    "ks:ks_name":"Sila Malla",
    "ks:ks_pop":120,
    "ks:ks_type":"VILLAGE",
    "name:eng_x_preferred":[
        "Sila Malla"
    ],
    "wof:name":"Sila Malla",
    "wof:placetype":"locality",
    "wof:population":120
},
  "geometry": {"coordinates":[79.020173,29.69046],"type":"Point"}
}