{
  "type": "Feature",
  "properties": {
    "iso:country":"IN",
    "ks:ks_name":"Badong",
    "ks:ks_pop":400,
    "ks:ks_type":"HABITATION",
    "name:eng_x_preferred":[
        "Badong"
    ],
    "wof:name":"Badong",
    "wof:placetype":"locality",
    "wof:population":400
},
  "geometry": {"coordinates":[92.550577,25.788881],"type":"Point"}
}