{
  "type": "Feature",
  "properties": {
    "gn:admin1_code":"13.0",
    "gn:admin2_code":"592.0",
    "gn:asciiname":"Irimbiliyam",
    "gn:country_code":"IN",
    "gn:dem":20,
    "gn:feature_class":"P",
    "gn:feature_code":"PPL",
    "gn:name":"Irimbiliyam",
    "gn:population":0,
    "gn:timezone":"Asia/Kolkata",
    "iso:country":"IN",
    "ks:ks_name":"Irimbiliyam",
    "ks:ks_pop":27075,
    "ks:ks_type":"VILLAGE",
    "name:eng_x_preferred":[
        "Irimbiliyam"
    ],
    "wof:name":"Irimbiliyam",
    "wof:placetype":"locality",
    "wof:population":27075
},
  "geometry": {"coordinates":[76.092181,10.862424],"type":"Point"}
}