{
  "type": "Feature",
  "properties": {
    "gn:admin1_code":"36.0",
    "gn:admin2_code":"162.0",
    "gn:asciiname":"Hira Purwa",
    "gn:country_code":"IN",
    "gn:dem":146,
    "gn:feature_class":"P",
    "gn:feature_code":"PPL",
    "gn:name":"H\u012bra Purwa",
    "gn:population":0,
    "gn:timezone":"Asia/Kolkata",
    "iso:country":"IN",
    "wof:name":"Hira Purwa",
    "wof:placetype":"locality"
},
  "geometry": {"coordinates":[79.58299,26.80839000000001],"type":"Point"}
}