{
  "type": "Feature",
  "properties": {
    "iso:country":"IN",
    "ks:ks_name":"Keshabpur",
    "ks:ks_pop":469,
    "ks:ks_type":"VILLAGE",
    "ks:ks_uagg_main":0,
    "name:eng_x_preferred":[
        "Keshabpur"
    ],
    "wof:name":"Keshabpur",
    "wof:placetype":"locality",
    "wof:population":469
},
  "geometry": {"coordinates":[87.353679,22.408218],"type":"Point"}
}