{
  "type": "Feature",
  "properties": {
    "iso:country":"IN",
    "ks:ks_alt_nam":"Midal tola",
    "ks:ks_name":"Midal Tola",
    "ks:ks_pop":90,
    "ks:ks_type":"HABITATION",
    "name:eng_x_preferred":[
        "Midal Tola"
    ],
    "wof:name":"Midal Tola",
    "wof:placetype":"locality",
    "wof:population":90
},
  "geometry": {"coordinates":[86.47111200000001,24.589138],"type":"Point"}
}