{
  "type": "Feature",
  "properties": {
    "iso:country":"IN",
    "ks:ks_name":"Biralsa",
    "ks:ks_pop":521,
    "ks:ks_type":"VILLAGE",
    "name:eng_x_preferred":[
        "Biralsa"
    ],
    "wof:name":"Biralsa",
    "wof:placetype":"locality",
    "wof:population":521
},
  "geometry": {"coordinates":[77.512379,29.561018],"type":"Point"}
}