{
  "type": "Feature",
  "properties": {
    "gn:admin1_code":"39",
    "gn:admin2_code":"61.0",
    "gn:asciiname":"Upgaon Malla",
    "gn:country_code":"IN",
    "gn:dem":1081,
    "gn:feature_class":"P",
    "gn:feature_code":"PPL",
    "gn:name":"Upgaon Malla",
    "gn:population":0,
    "gn:timezone":"Asia/Kolkata",
    "iso:country":"IN",
    "ks:ks_name":"Upgaon Malla",
    "ks:ks_pop":78,
    "ks:ks_type":"VILLAGE",
    "name:eng_x_preferred":[
        "Upgaon Malla"
    ],
    "wof:name":"Upgaon Malla",
    "wof:placetype":"locality",
    "wof:population":78
},
  "geometry": {"coordinates":[78.94329399999999,29.659042],"type":"Point"}
}