{
  "type": "Feature",
  "properties": {
    "gn:admin1_code":"39",
    "gn:admin2_code":"61.0",
    "gn:asciiname":"Upgaon Malla",
    "gn:country_code":"IN",
    "gn:dem":1081,
    "gn:feature_class":"P",
    "gn:feature_code":"PPL",
    "gn:name":"Upgaon Malla",
    "gn:population":0,
    "gn:timezone":"Asia/Kolkata",
    "iso:country":"IN",
    "wof:name":"Upgaon Malla",
    "wof:placetype":"locality"
},
  "geometry": {"coordinates":[78.94561,29.65879],"type":"Point"}
}