{
  "type": "Feature",
  "properties": {
    "iso:country":"IN",
    "ks:ks_name":"Atikabad",
    "ks:ks_pop":783,
    "ks:ks_type":"HABITATION",
    "name:eng_x_preferred":[
        "Atikabad"
    ],
    "wof:name":"Atikabad",
    "wof:placetype":"locality",
    "wof:population":783
},
  "geometry": {"coordinates":[78.78457,26.977632],"type":"Point"}
}