{
  "type": "Feature",
  "properties": {
    "iso:country":"IN",
    "ks:ks_alt_nam":"mahurwapu",
    "ks:ks_name":"Mahurwapu",
    "ks:ks_pop":85,
    "ks:ks_type":"HABITATION",
    "ks:ks_uagg_main":0,
    "name:eng_x_preferred":[
        "Mahurwapu"
    ],
    "wof:name":"Mahurwapu",
    "wof:placetype":"neighbourhood",
    "wof:population":85
},
  "geometry": {"coordinates":[93.109301,25.336829],"type":"Point"}
}