{
  "type": "Feature",
  "properties": {
    "gn:admin1_code":"39.0",
    "gn:admin2_code":"61.0",
    "gn:asciiname":"Saingaon",
    "gn:country_code":"IN",
    "gn:dem":1372,
    "gn:feature_class":"P",
    "gn:feature_code":"PPL",
    "gn:name":"Saingaon",
    "gn:population":0,
    "gn:timezone":"Asia/Kolkata",
    "iso:country":"IN",
    "wof:name":"Saingaon",
    "wof:placetype":"locality"
},
  "geometry": {"coordinates":[79.03901999999999,29.90368],"type":"Point"}
}