{
  "type": "Feature",
  "properties": {
    "iso:country":"IN",
    "ks:ks_name":"Molia",
    "ks:ks_pop":3801,
    "ks:ks_type":"VILLAGE",
    "name:eng_x_preferred":[
        "Molia"
    ],
    "wof:name":"Molia",
    "wof:placetype":"locality",
    "wof:population":3801
},
  "geometry": {"coordinates":[86.67788,25.413717],"type":"Point"}
}