{
  "type": "Feature",
  "properties": {
    "gn:admin1_code":"19.0",
    "gn:admin2_code":"574.0",
    "gn:asciiname":"Kattehosur",
    "gn:country_code":"IN",
    "gn:dem":893,
    "gn:feature_class":"P",
    "gn:feature_code":"PPL",
    "gn:name":"Kattehosur",
    "gn:population":0,
    "gn:timezone":"Asia/Kolkata",
    "iso:country":"IN",
    "ks:ks_name":"Kattehosur",
    "ks:ks_type":"VILLAGE",
    "name:eng_x_preferred":[
        "Kattehosur"
    ],
    "wof:name":"Kattehosur",
    "wof:placetype":"locality"
},
  "geometry": {"coordinates":[75.954249,12.807089],"type":"Point"}
}