{
  "type": "Feature",
  "properties": {
    "gn:admin1_code":"21",
    "gn:admin2_code":"395.0",
    "gn:asciiname":"Dhaurabhata",
    "gn:country_code":"IN",
    "gn:dem":697,
    "gn:feature_class":"P",
    "gn:feature_code":"PPL",
    "gn:name":"Dhaurabhata",
    "gn:population":0,
    "gn:timezone":"Asia/Kolkata",
    "iso:country":"IN",
    "ks:ks_name":"Dhaunrabhata",
    "ks:ks_pop":36,
    "ks:ks_type":"VILLAGE",
    "name:eng_x_preferred":[
        "Dhaunrabhata"
    ],
    "name:eng_x_variant":[
        "Dhaurabhata"
    ],
    "wof:name":"Dhaunrabhata",
    "wof:placetype":"locality",
    "wof:population":36
},
  "geometry": {"coordinates":[83.306635,19.686868],"type":"Point"}
}