{
  "type": "Feature",
  "properties": {
    "iso:country":"IN",
    "ks:ks_alt_nam":"pothapatti",
    "ks:ks_name":"Pothapatti",
    "ks:ks_pop":61,
    "ks:ks_type":"HABITATION",
    "ks:ks_uagg_main":0,
    "name:eng_x_preferred":[
        "Pothapatti"
    ],
    "wof:name":"Pothapatti",
    "wof:placetype":"neighbourhood",
    "wof:population":61
},
  "geometry": {"coordinates":[78.348461,10.424199],"type":"Point"}
}