{
  "type": "Feature",
  "properties": {
    "iso:country":"IN",
    "ks:ks_name":"Shindewadi",
    "ks:ks_pop":220,
    "ks:ks_type":"HABITATION",
    "name:eng_x_preferred":[
        "Shindewadi"
    ],
    "wof:name":"Shindewadi",
    "wof:placetype":"locality",
    "wof:population":220
},
  "geometry": {"coordinates":[73.435028,17.054181],"type":"Point"}
}