{
  "type": "Feature",
  "properties": {
    "iso:country":"IN",
    "ks:ks_alt_nam":"khant Faliya",
    "ks:ks_name":"Khant Faliya",
    "ks:ks_pop":399,
    "ks:ks_type":"HABITATION",
    "name:eng_x_preferred":[
        "Khant Faliya"
    ],
    "wof:name":"Khant Faliya",
    "wof:placetype":"locality",
    "wof:population":399
},
  "geometry": {"coordinates":[73.645889,23.179056],"type":"Point"}
}