{
  "type": "Feature",
  "properties": {
    "iso:country":"IN",
    "ks:ks_name":"Vepamanikothur",
    "ks:ks_pop":121,
    "ks:ks_type":"HABITATION",
    "ks:ks_uagg_main":0,
    "name:eng_x_preferred":[
        "Vepamanikothur"
    ],
    "wof:name":"Vepamanikothur",
    "wof:placetype":"neighbourhood",
    "wof:population":121
},
  "geometry": {"coordinates":[78.347582,12.79458],"type":"Point"}
}