{
  "type": "Feature",
  "properties": {
    "iso:country":"IN",
    "ks:ks_name":"Bagalmannu",
    "ks:ks_pop":102,
    "ks:ks_type":"HABITATION",
    "name:eng_x_preferred":[
        "Bagalmannu"
    ],
    "wof:name":"Bagalmannu",
    "wof:placetype":"locality",
    "wof:population":102
},
  "geometry": {"coordinates":[74.75035800000001,13.687793],"type":"Point"}
}