{
  "type": "Feature",
  "properties": {
    "gn:admin1_code":"19.0",
    "gn:admin2_code":"570.0",
    "gn:asciiname":"Harkodu",
    "gn:country_code":"IN",
    "gn:dem":827,
    "gn:feature_class":"P",
    "gn:feature_code":"PPL",
    "gn:name":"Harkodu",
    "gn:population":0,
    "gn:timezone":"Asia/Kolkata",
    "iso:country":"IN",
    "wof:name":"Harkodu",
    "wof:placetype":"locality"
},
  "geometry": {"coordinates":[75.33969,13.37088],"type":"Point"}
}