{
  "type": "Feature",
  "properties": {
    "gn:admin1_code":"19.0",
    "gn:admin2_code":"570.0",
    "gn:asciiname":"Harkodu",
    "gn:country_code":"IN",
    "gn:dem":827,
    "gn:feature_class":"P",
    "gn:feature_code":"PPL",
    "gn:name":"Harkodu",
    "gn:population":0,
    "gn:timezone":"Asia/Kolkata",
    "iso:country":"IN",
    "ks:ks_name":"Harakodu",
    "ks:ks_pop":28,
    "ks:ks_type":"HABITATION",
    "name:eng_x_preferred":[
        "Harakodu"
    ],
    "name:eng_x_variant":[
        "Harkodu"
    ],
    "wof:name":"Harakodu",
    "wof:placetype":"locality",
    "wof:population":28
},
  "geometry": {"coordinates":[75.33300699999999,13.368426],"type":"Point"}
}