{
  "type": "Feature",
  "properties": {
    "iso:country":"IN",
    "ks:ks_name":"Koppala",
    "ks:ks_pop":102,
    "ks:ks_type":"HABITATION",
    "name:eng_x_preferred":[
        "Koppala"
    ],
    "wof:name":"Koppala",
    "wof:placetype":"locality",
    "wof:population":102
},
  "geometry": {"coordinates":[74.72345,13.278946],"type":"Point"}
}