{
  "type": "Feature",
  "properties": {
    "iso:country":"IN",
    "ks:ks_name":"Choorani",
    "ks:ks_pop":433,
    "ks:ks_type":"HABITATION",
    "name:eng_x_preferred":[
        "Choorani"
    ],
    "wof:name":"Choorani",
    "wof:placetype":"locality",
    "wof:population":433
},
  "geometry": {"coordinates":[75.80386900000001,11.732741],"type":"Point"}
}