{
  "type": "Feature",
  "properties": {
    "iso:country":"IN",
    "ks:ks_name":"Gumanpur Markahar",
    "ks:ks_pop":64,
    "ks:ks_type":"VILLAGE",
    "name:eng_x_preferred":[
        "Gumanpur Markahar"
    ],
    "wof:name":"Gumanpur Markahar",
    "wof:placetype":"locality",
    "wof:population":64
},
  "geometry": {"coordinates":[80.408107,25.215152],"type":"Point"}
}