{
  "type": "Feature",
  "properties": {
    "gn:admin1_code":"19.0",
    "gn:admin2_code":"570.0",
    "gn:asciiname":"Kerodi",
    "gn:country_code":"IN",
    "gn:dem":648,
    "gn:feature_class":"P",
    "gn:feature_code":"PPL",
    "gn:name":"Kerodi",
    "gn:population":0,
    "gn:timezone":"Asia/Kolkata",
    "iso:country":"IN",
    "ks:ks_name":"Kerodi",
    "ks:ks_pop":57,
    "ks:ks_type":"HABITATION",
    "name:eng_x_preferred":[
        "Kerodi"
    ],
    "wof:name":"Kerodi",
    "wof:placetype":"locality",
    "wof:population":57
},
  "geometry": {"coordinates":[75.307661,13.464139],"type":"Point"}
}