{
  "type": "Feature",
  "properties": {
    "iso:country":"IN",
    "ks:ks_alt_nam":"Aparia N.C.",
    "ks:ks_name":"Aparia N.c.",
    "ks:ks_pop":39,
    "ks:ks_type":"HABITATION",
    "name:eng_x_preferred":[
        "Aparia N.c."
    ],
    "wof:name":"Aparia N.c.",
    "wof:placetype":"locality",
    "wof:population":39
},
  "geometry": {"coordinates":[92.11921100000001,26.392545],"type":"Point"}
}