{
  "type": "Feature",
  "properties": {
    "gn:admin1_code":"40.0",
    "gn:admin2_code":"533.0",
    "gn:asciiname":"Medaram",
    "gn:country_code":"IN",
    "gn:dem":315,
    "gn:feature_class":"P",
    "gn:feature_code":"PPL",
    "gn:name":"Med\u0101ram",
    "gn:population":0,
    "gn:timezone":"Asia/Kolkata",
    "iso:country":"IN",
    "name:tel_x_preferred":[
        "\u0c2e\u0c47\u0c21\u0c3e\u0c30\u0c02"
    ],
    "wof:name":"Medaram",
    "wof:placetype":"locality"
},
  "geometry": {"coordinates":[78.40246999999999,18.95175],"type":"Point"}
}