{
  "type": "Feature",
  "properties": {
    "iso:country":"IN",
    "ks:ks_name":"Nesada",
    "ks:ks_pop":937,
    "ks:ks_type":"HABITATION",
    "name:eng_x_preferred":[
        "Nesada"
    ],
    "wof:name":"Nesada",
    "wof:placetype":"locality",
    "wof:population":937
},
  "geometry": {"coordinates":[73.54436099999999,23.381056],"type":"Point"}
}