{
  "type": "Feature",
  "properties": {
    "iso:country":"IN",
    "ks:ks_name":"Ayur Bethaniya Herbal Gardan Road Jn",
    "ks:ks_pop":763,
    "ks:ks_type":"HABITATION",
    "name:eng_x_preferred":[
        "Ayur Bethaniya Herbal Gardan Road Jn"
    ],
    "wof:name":"Ayur Bethaniya Herbal Gardan Road Jn",
    "wof:placetype":"locality",
    "wof:population":763
},
  "geometry": {"coordinates":[76.207295,10.618254],"type":"Point"}
}