{
  "type": "Feature",
  "properties": {
    "iso:country":"IN",
    "ks:ks_name":"Sanaroutapati",
    "ks:ks_pop":136,
    "ks:ks_type":"VILLAGE",
    "name:eng_x_preferred":[
        "Sanaroutapati"
    ],
    "wof:name":"Sanaroutapati",
    "wof:placetype":"locality",
    "wof:population":136
},
  "geometry": {"coordinates":[86.135988,20.461944],"type":"Point"}
}