{
  "type": "Feature",
  "properties": {
    "gn:admin1_code":"36.0",
    "gn:admin2_code":"134.0",
    "gn:asciiname":"Khwajgipur",
    "gn:country_code":"IN",
    "gn:dem":236,
    "gn:feature_class":"P",
    "gn:feature_code":"PPL",
    "gn:name":"Khw\u0101jg\u012bpur",
    "gn:population":0,
    "gn:timezone":"Asia/Kolkata",
    "iso:country":"IN",
    "name:und_x_variant":[
        "Khw\u0101jg\u012bpur"
    ],
    "wof:name":"Khwajgipur",
    "wof:placetype":"locality"
},
  "geometry": {"coordinates":[78.10384999999999,29.57014],"type":"Point"}
}