{
  "type": "Feature",
  "properties": {
    "iso:country":"IN",
    "ks:ks_alt_nam":"mudakirai",
    "ks:ks_name":"Mudakirai",
    "ks:ks_pop":1200,
    "ks:ks_type":"HABITATION",
    "name:eng_x_preferred":[
        "Mudakirai"
    ],
    "wof:name":"Mudakirai",
    "wof:placetype":"locality",
    "wof:population":1200
},
  "geometry": {"coordinates":[76.519503,10.111681],"type":"Point"}
}