{
  "type": "Feature",
  "properties": {
    "iso:country":"IN",
    "ks:ks_name":"Kundhuroor",
    "ks:ks_pop":12,
    "ks:ks_type":"HABITATION",
    "name:eng_x_preferred":[
        "Kundhuroor"
    ],
    "wof:name":"Kundhuroor",
    "wof:placetype":"locality",
    "wof:population":12
},
  "geometry": {"coordinates":[75.26936600000001,13.393812],"type":"Point"}
}