{
  "type": "Feature",
  "properties": {
    "iso:country":"IN",
    "ks:ks_name":"Hosakadu",
    "ks:ks_pop":650,
    "ks:ks_type":"HABITATION",
    "ks:ks_uagg_main":0,
    "name:eng_x_preferred":[
        "Hosakadu"
    ],
    "wof:name":"Hosakadu",
    "wof:placetype":"locality",
    "wof:population":650
},
  "geometry": {"coordinates":[74.82849400000001,13.055061],"type":"Point"}
}