{
  "type": "Feature",
  "properties": {
    "gn:admin1_code":"36.0",
    "gn:admin2_code":"134.0",
    "gn:asciiname":"Sadikpur",
    "gn:country_code":"IN",
    "gn:dem":233,
    "gn:feature_class":"P",
    "gn:feature_code":"PPL",
    "gn:name":"Sad\u012bkpur",
    "gn:population":0,
    "gn:timezone":"Asia/Kolkata",
    "iso:country":"IN",
    "name:und_x_variant":[
        "Sad\u012bkpur",
        "Sult\u0101nnagar"
    ],
    "wof:name":"Sadikpur",
    "wof:placetype":"locality"
},
  "geometry": {"coordinates":[78.70696,29.33956],"type":"Point"}
}