{
  "type": "Feature",
  "properties": {
    "iso:country":"IN",
    "ks:ks_name":"D B Halli",
    "ks:ks_pop":549,
    "ks:ks_type":"HABITATION",
    "name:eng_x_preferred":[
        "D B Halli"
    ],
    "wof:name":"D B Halli",
    "wof:placetype":"locality",
    "wof:population":549
},
  "geometry": {"coordinates":[76.576454,14.912494],"type":"Point"}
}