{
  "type": "Feature",
  "properties": {
    "gn:admin1_code":"36.0",
    "gn:admin2_code":"135.0",
    "gn:asciiname":"Mangupura",
    "gn:country_code":"IN",
    "gn:dem":190,
    "gn:feature_class":"P",
    "gn:feature_code":"PPL",
    "gn:name":"Mangupura",
    "gn:population":0,
    "gn:timezone":"Asia/Kolkata",
    "iso:country":"IN",
    "name:ara_x_preferred":[
        "\u0645\u0627\u0646\u063a\u0648\u0628\u0648\u0631\u0627"
    ],
    "name:ind_x_preferred":[
        "Mangupura"
    ],
    "wof:name":"Mangupura",
    "wof:placetype":"locality"
},
  "geometry": {"coordinates":[78.90994000000001,28.5687],"type":"Point"}
}