{
  "type": "Feature",
  "properties": {
    "iso:country":"IN",
    "ks:ks_name":"Bagkhal Manipuri Basti",
    "ks:ks_pop":100,
    "ks:ks_type":"HABITATION",
    "name:eng_x_preferred":[
        "Bagkhal Manipuri Basti"
    ],
    "wof:name":"Bagkhal Manipuri Basti",
    "wof:placetype":"locality",
    "wof:population":100
},
  "geometry": {"coordinates":[93.094021,24.774455],"type":"Point"}
}