{
  "type": "Feature",
  "properties": {
    "gn:admin1_code":"19.0",
    "gn:admin2_code":"563.0",
    "gn:asciiname":"Indur",
    "gn:country_code":"IN",
    "gn:dem":556,
    "gn:feature_class":"P",
    "gn:feature_code":"PPL",
    "gn:name":"Ind\u016br",
    "gn:population":0,
    "gn:timezone":"Asia/Kolkata",
    "iso:country":"IN",
    "name:ara_x_preferred":[
        "\u0625\u0646\u062f\u0648\u0631"
    ],
    "name:cat_x_preferred":[
        "Indur"
    ],
    "name:pol_x_preferred":[
        "Indur"
    ],
    "wof:name":"Indur",
    "wof:placetype":"neighbourhood"
},
  "geometry": {"coordinates":[75.01913999999999,15.02424],"type":"Point"}
}