{
  "type": "Feature",
  "properties": {
    "iso:country":"IN",
    "ks:ks_name":"Thirumalayapalli",
    "ks:ks_pop":289,
    "ks:ks_type":"HABITATION",
    "name:eng_x_preferred":[
        "Thirumalayapalli"
    ],
    "wof:name":"Thirumalayapalli",
    "wof:placetype":"locality",
    "wof:population":289
},
  "geometry": {"coordinates":[78.182,14.891431],"type":"Point"}
}