{
  "type": "Feature",
  "properties": {
    "iso:country":"IN",
    "ks:ks_name":"Harigan Pada",
    "ks:ks_pop":30,
    "ks:ks_type":"HABITATION",
    "name:eng_x_preferred":[
        "Harigan Pada"
    ],
    "wof:name":"Harigan Pada",
    "wof:placetype":"locality",
    "wof:population":30
},
  "geometry": {"coordinates":[72.842845,19.619532],"type":"Point"}
}