{
  "type": "Feature",
  "properties": {
    "iso:country":"IN",
    "ks:ks_alt_nam":"LONARWADI",
    "ks:ks_name":"Lonarwadi",
    "ks:ks_pop":81,
    "ks:ks_type":"HABITATION",
    "name:eng_x_preferred":[
        "Lonarwadi"
    ],
    "wof:name":"Lonarwadi",
    "wof:placetype":"locality",
    "wof:population":81
},
  "geometry": {"coordinates":[75.004696,17.418635],"type":"Point"}
}