{
  "type": "Feature",
  "properties": {
    "gn:admin1_code":"25.0",
    "gn:admin2_code":"631.0",
    "gn:asciiname":"Maragutta",
    "gn:country_code":"IN",
    "gn:dem":934,
    "gn:feature_class":"P",
    "gn:feature_code":"PPL",
    "gn:name":"Maragutta",
    "gn:population":0,
    "gn:timezone":"Asia/Kolkata",
    "iso:country":"IN",
    "wof:name":"Maragutta",
    "wof:placetype":"locality"
},
  "geometry": {"coordinates":[77.77693000000002,12.48813],"type":"Point"}
}