{
  "type": "Feature",
  "properties": {
    "iso:country":"IN",
    "ks:ks_name":"Elayapadam",
    "ks:ks_pop":655,
    "ks:ks_type":"HABITATION",
    "name:eng_x_preferred":[
        "Elayapadam"
    ],
    "wof:name":"Elayapadam",
    "wof:placetype":"locality",
    "wof:population":655
},
  "geometry": {"coordinates":[76.284774,9.776921],"type":"Point"}
}