{
  "type": "Feature",
  "properties": {
    "iso:country":"IN",
    "ks:ks_name":"Taradwasti",
    "ks:ks_pop":234,
    "ks:ks_type":"HABITATION",
    "name:eng_x_preferred":[
        "Taradwasti"
    ],
    "wof:name":"Taradwasti",
    "wof:placetype":"locality",
    "wof:population":234
},
  "geometry": {"coordinates":[74.353477,19.048537],"type":"Point"}
}