{
  "type": "Feature",
  "properties": {
    "iso:country":"IN",
    "ks:ks_name":"Masudan Dehri",
    "ks:ks_pop":0,
    "ks:ks_type":"VILLAGE",
    "name:eng_x_preferred":[
        "Masudan Dehri"
    ],
    "wof:name":"Masudan Dehri",
    "wof:placetype":"locality",
    "wof:population":0
},
  "geometry": {"coordinates":[84.139449,25.307676],"type":"Point"}
}