{
  "type": "Feature",
  "properties": {
    "iso:country":"IN",
    "ks:ks_name":"Dumurbera",
    "ks:ks_pop":0,
    "ks:ks_type":"VILLAGE",
    "name:eng_x_preferred":[
        "Dumurbera"
    ],
    "wof:name":"Dumurbera",
    "wof:placetype":"locality",
    "wof:population":0
},
  "geometry": {"coordinates":[86.16743200000001,22.566494],"type":"Point"}
}