{
  "type": "Feature",
  "properties": {
    "gn:admin1_code":"35",
    "gn:admin2_code":"418.0",
    "gn:asciiname":"Agra",
    "gn:country_code":"IN",
    "gn:dem":253,
    "gn:feature_class":"P",
    "gn:feature_code":"PPL",
    "gn:name":"Agra",
    "gn:population":0,
    "gn:timezone":"Asia/Kolkata",
    "iso:country":"IN",
    "wof:name":"Agra",
    "wof:placetype":"locality"
},
  "geometry": {"coordinates":[77.25766999999998,25.92978],"type":"Point"}
}