{
  "type": "Feature",
  "properties": {
    "iso:country":"IN",
    "ks:ks_name":"Japihojia",
    "ks:ks_pop":931,
    "ks:ks_type":"HABITATION",
    "name:eng_x_preferred":[
        "Japihojia"
    ],
    "wof:name":"Japihojia",
    "wof:placetype":"locality",
    "wof:population":931
},
  "geometry": {"coordinates":[93.961527,26.547122],"type":"Point"}
}