{
  "type": "Feature",
  "properties": {
    "gn:admin1_code":"03",
    "gn:admin2_code":"317.0",
    "gn:asciiname":"Sonakhira",
    "gn:country_code":"IN",
    "gn:dem":36,
    "gn:feature_class":"P",
    "gn:feature_code":"PPL",
    "gn:name":"Son\u0101khira",
    "gn:population":0,
    "gn:timezone":"Asia/Kolkata",
    "iso:country":"IN",
    "wof:name":"Sonakhira",
    "wof:placetype":"locality"
},
  "geometry": {"coordinates":[92.28842,24.57064],"type":"Point"}
}