{
  "type": "Feature",
  "properties": {
    "iso:country":"IN",
    "ks:ks_name":"Jamuda",
    "ks:ks_pop":1671,
    "ks:ks_type":"VILLAGE",
    "name:eng_x_preferred":[
        "Jamuda"
    ],
    "wof:name":"Jamuda",
    "wof:placetype":"locality",
    "wof:population":1671
},
  "geometry": {"coordinates":[85.842803,21.330348],"type":"Point"}
}