{
  "type": "Feature",
  "properties": {
    "gn:admin1_code":"19.0",
    "gn:admin2_code":"565.0",
    "gn:asciiname":"Bommenahalli",
    "gn:country_code":"IN",
    "gn:dem":696,
    "gn:feature_class":"P",
    "gn:feature_code":"PPL",
    "gn:name":"Bommenahalli",
    "gn:population":0,
    "gn:timezone":"Asia/Kolkata",
    "iso:country":"IN",
    "wof:name":"Bommenahalli",
    "wof:placetype":"locality"
},
  "geometry": {"coordinates":[76.61235000000001,14.93843],"type":"Point"}
}