{
  "type": "Feature",
  "properties": {
    "gn:admin1_code":"12",
    "gn:admin2_code":"15.0",
    "gn:asciiname":"Mahi Nag",
    "gn:country_code":"IN",
    "gn:dem":3034,
    "gn:feature_class":"P",
    "gn:feature_code":"PPL",
    "gn:name":"Mahi Nag",
    "gn:population":0,
    "gn:timezone":"Asia/Kolkata",
    "iso:country":"IN",
    "name:und_x_variant":[
        "Mahi N\u0101g"
    ],
    "wof:name":"Mahi Nag",
    "wof:placetype":"locality"
},
  "geometry": {"coordinates":[74.75576,33.55838],"type":"Point"}
}