{
  "type": "Feature",
  "properties": {
    "gn:admin1_code":"39.0",
    "gn:admin2_code":"64.0",
    "gn:asciiname":"Motiapathar",
    "gn:country_code":"IN",
    "gn:dem":2132,
    "gn:feature_class":"P",
    "gn:feature_code":"PPL",
    "gn:name":"Moti\u0101p\u0101thar",
    "gn:population":0,
    "gn:timezone":"Asia/Kolkata",
    "iso:country":"IN",
    "wof:name":"Motiapathar",
    "wof:placetype":"neighbourhood"
},
  "geometry": {"coordinates":[79.72445,29.45982],"type":"Point"}
}