{
  "type": "Feature",
  "properties": {
    "iso:country":"IN",
    "ks:ks_name":"4 SJM",
    "ks:ks_pop":511,
    "ks:ks_type":"VILLAGE",
    "name:eng_x_preferred":[
        "4 SJM"
    ],
    "wof:name":"4 SJM",
    "wof:placetype":"locality",
    "wof:population":511
},
  "geometry": {"coordinates":[72.804095,28.783602],"type":"Point"}
}