{
  "type": "Feature",
  "properties": {
    "gn:admin1_code":"12.0",
    "gn:admin2_code":"008",
    "gn:asciiname":"Ningarpur",
    "gn:country_code":"IN",
    "gn:dem":1738,
    "gn:feature_class":"P",
    "gn:feature_code":"PPL",
    "gn:name":"Ningarpur",
    "gn:population":0,
    "gn:timezone":"Asia/Kolkata",
    "iso:country":"IN",
    "name:und_x_variant":[
        "Ningapur"
    ],
    "wof:name":"Ningarpur",
    "wof:placetype":"locality"
},
  "geometry": {"coordinates":[74.5025,34.11246],"type":"Point"}
}