{
  "type": "Feature",
  "properties": {
    "gn:admin1_code":"36",
    "gn:admin2_code":"172.0",
    "gn:asciiname":"Unnaur",
    "gn:country_code":"IN",
    "gn:dem":117,
    "gn:feature_class":"P",
    "gn:feature_code":"PPL",
    "gn:name":"Unnaur",
    "gn:population":0,
    "gn:timezone":"Asia/Kolkata",
    "iso:country":"IN",
    "ks:ks_name":"Unnaur",
    "ks:ks_pop":410,
    "ks:ks_type":"VILLAGE",
    "name:eng_x_preferred":[
        "Unnaur"
    ],
    "wof:name":"Unnaur",
    "wof:placetype":"locality",
    "wof:population":410
},
  "geometry": {"coordinates":[80.841866,26.019376],"type":"Point"}
}