{
  "type": "Feature",
  "properties": {
    "gn:admin1_code":"34.0",
    "gn:admin2_code":"237.0",
    "gn:asciiname":"Parbati",
    "gn:country_code":"IN",
    "gn:dem":66,
    "gn:feature_class":"P",
    "gn:feature_code":"PPL",
    "gn:name":"P\u0101rbati",
    "gn:population":0,
    "gn:timezone":"Asia/Kolkata",
    "iso:country":"IN",
    "name:ara_x_preferred":[
        "\u0628\u0627\u0631\u0628\u0627\u062a\u064a"
    ],
    "name:ben_x_preferred":[
        "\u09aa\u09be\u09b0\u09ac\u09be\u09a4\u09bf"
    ],
    "name:ell_x_preferred":[
        "\u03a0\u03b1\u03c1\u03bc\u03c0\u03ac\u03c4\u03b9"
    ],
    "name:fas_x_preferred":[
        "\u067e\u0627\u0631\u0628\u0627\u062a\u06cc"
    ],
    "name:heb_x_preferred":[
        "\u05e4\u05e8\u05d1\u05bc\u05d0\u05d8\u05d9"
    ],
    "name:hin_x_preferred":[
        "\u092a\u093e\u0930\u094d\u092c\u0924\u0940"
    ],
    "name:hun_x_preferred":[
        "Parbati"
    ],
    "name:ind_x_preferred":[
        "Parbati"
    ],
    "name:ita_x_preferred":[
        "Parbati"
    ],
    "name:kor_x_preferred":[
        "\ud30c\ub974\ubc14\ud2f0"
    ],
    "name:pol_x_preferred":[
        "Parbati"
    ],
    "name:por_x_preferred":[
        "Parbati"
    ],
    "name:rus_x_preferred":[
        "\u0440\u0435\u043a\u0430 \u041f\u0430\u0440\u0431\u0430\u0442\u0438"
    ],
    "name:spa_x_preferred":[
        "Parbati"
    ],
    "name:swe_x_preferred":[
        "Parbati"
    ],
    "name:tur_x_preferred":[
        "Parbati"
    ],
    "name:ukr_x_preferred":[
        "\u041f\u0430\u0440\u0431\u0430\u0442\u0456"
    ],
    "name:urd_x_preferred":[
        "\u067e\u0631\u0628\u0627\u062a\u06cc"
    ],
    "name:vie_x_preferred":[
        "S\u00f4ng Parbati"
    ],
    "name:zho_cn_x_preferred":[
        "\u5e15\u5c14\u5df4\u8482\u6cb3"
    ],
    "name:zho_tw_x_preferred":[
        "\u5e15\u5df4\u63d0\u6cb3"
    ],
    "wof:name":"Parbati",
    "wof:placetype":"locality"
},
  "geometry": {"coordinates":[85.65298,25.08754],"type":"Point"}
}