{
  "type": "Feature",
  "properties": {
    "gn:admin1_code":"21",
    "gn:admin2_code":"397.0",
    "gn:asciiname":"Kariki",
    "gn:country_code":"IN",
    "gn:dem":661,
    "gn:feature_class":"P",
    "gn:feature_code":"PPL",
    "gn:name":"Kariki",
    "gn:population":0,
    "gn:timezone":"Asia/Kolkata",
    "iso:country":"IN",
    "wof:name":"Kariki",
    "wof:placetype":"neighbourhood"
},
  "geometry": {"coordinates":[81.95856999999999,20.02532],"type":"Point"}
}