{
  "type": "Feature",
  "properties": {
    "iso:country":"IN",
    "ks:ks_name":"8 MJD",
    "ks:ks_pop":55,
    "ks:ks_type":"VILLAGE",
    "name:eng_x_preferred":[
        "8 MJD"
    ],
    "wof:name":"8 MJD",
    "wof:placetype":"locality",
    "wof:population":55
},
  "geometry": {"coordinates":[74.375152,29.780162],"type":"Point"}
}