{
  "type": "Feature",
  "properties": {
    "iso:country":"IN",
    "ks:ks_name":"Purusharakodi",
    "ks:ks_pop":1255,
    "ks:ks_type":"HABITATION",
    "name:eng_x_preferred":[
        "Purusharakodi"
    ],
    "wof:name":"Purusharakodi",
    "wof:placetype":"locality",
    "wof:population":1255
},
  "geometry": {"coordinates":[74.918638,12.822761],"type":"Point"}
}