{
  "type": "Feature",
  "properties": {
    "iso:country":"IN",
    "name:ara_x_preferred":[
        "\u0628\u0627\u0631\u0627\u0645\u0648\u0646\u062f\u0627"
    ],
    "name:ben_bn_x_preferred":[
        "\u09ac\u09be\u09b0\u09be\u09ae\u09c1\u09a8\u09cd\u09a1\u09be"
    ],
    "name:ben_in_x_preferred":[
        "\u09ac\u09be\u09b0\u09be\u09ae\u09c1\u09a8\u09cd\u09a1\u09be"
    ],
    "name:eng_x_preferred":[
        "Baramunda"
    ],
    "name:guj_x_preferred":[
        "\u0aac\u0abe\u0ab0\u0abe\u0aae\u0ac1\u0a82\u0aa1\u0abe\u0ac1"
    ],
    "name:hin_x_preferred":[
        "\u092c\u093e\u0930\u093e\u092e\u0941\u0902\u0921\u093e"
    ],
    "name:kan_x_preferred":[
        "\u0cac\u0cb0\u0cae\u0cc1\u0c82\u0ca1\u0cbe"
    ],
    "name:mal_x_preferred":[
        "\u0d2c\u0d3e\u0d30\u0d3e\u0d2e\u0d41\u0d23\u0d4d\u0d1f"
    ],
    "name:mar_x_preferred":[
        "\u092c\u093e\u0930\u093e\u092e\u0941\u0902\u0921\u093e"
    ],
    "name:pan_x_preferred":[
        "\u0a2c\u0a3e\u0a30\u0a3e\u0a2e\u0a41\u0a70\u0a21\u0a3e"
    ],
    "name:tam_x_preferred":[
        "\u0baa\u0bb0\u0bae\u0bc1\u0ba9\u0bcd\u0b9f\u0bbe"
    ],
    "name:tel_x_preferred":[
        "\u0c2c\u0c3e\u0c30\u0c3e\u0c2e\u0c41\u0c02\u0c21\u0c3e"
    ],
    "name:urd_x_preferred":[
        "\u0628\u0627\u0631\u0627\u0645\u0646\u0688\u0627"
    ],
    "qs:gn_adm0_cc":"IN",
    "qs:gn_local":1275817,
    "qs:local_max":122,
    "qs:local_sum":302,
    "qs:localhoods":5,
    "qs:name":"Baramunda",
    "qs:name_adm0":"India",
    "qs:name_adm1":"Orissa",
    "qs:name_adm2":"Khurda",
    "qs:name_local":"Bhubaneswar",
    "qs:photo_max":27,
    "qs:photo_sum":65,
    "qs:placetype":"Suburb",
    "qs:quad_count":7,
    "qs:woe_adm0":23424848,
    "qs:woe_adm1":2345755,
    "qs:woe_adm2":12586615,
    "qs:woe_lau":0,
    "qs:woe_local":2294941,
    "qs:woe_ver":"7.10.0",
    "wof:lang":[
        "eng"
    ],
    "wof:name":"Baramunda",
    "wof:placetype":"neighbourhood"
},
  "geometry": {"coordinates":[85.785411,20.263683],"type":"Point"}
}