{
  "type": "Feature",
  "properties": {
    "iso:country":"IN",
    "name:eng_x_preferred":[
        "Baramunda"
    ],
    "qs:gn_adm0_cc":"IN",
    "qs:gn_local":1275817,
    "qs:local_max":122,
    "qs:local_sum":302,
    "qs:localhoods":5,
    "qs:name":"Baramunda",
    "qs:name_adm0":"India",
    "qs:name_adm1":"Orissa",
    "qs:name_adm2":"Khurda",
    "qs:name_local":"Bhubaneswar",
    "qs:photo_max":27,
    "qs:photo_sum":65,
    "qs:placetype":"Suburb",
    "qs:quad_count":7,
    "qs:woe_adm0":23424848,
    "qs:woe_adm1":2345755,
    "qs:woe_adm2":12586615,
    "qs:woe_lau":0,
    "qs:woe_local":2294941,
    "qs:woe_ver":"7.10.0",
    "wof:lang":[
        "eng"
    ],
    "wof:name":"Baramunda",
    "wof:placetype":"neighbourhood"
},
  "geometry": {"coordinates":[85.785411,20.263683],"type":"Point"}
}