{
  "type": "Feature",
  "properties": {
    "iso:country":"IN",
    "ks:ks_name":"Mahathpur",
    "ks:ks_type":"VILLAGE",
    "ks:ks_uagg_main":0,
    "name:eng_x_preferred":[
        "Mahathpur"
    ],
    "wof:name":"Mahathpur",
    "wof:placetype":"neighbourhood"
},
  "geometry": {"coordinates":[85.856674,24.95931],"type":"Point"}
}