{
  "type": "Feature",
  "properties": {
    "iso:country":"IN",
    "ks:ks_name":"Mulhe Singh Ka Purwa",
    "ks:ks_pop":112,
    "ks:ks_type":"HABITATION",
    "ks:ks_uagg_main":0,
    "name:eng_x_preferred":[
        "Mulhe Singh Ka Purwa"
    ],
    "wof:name":"Mulhe Singh Ka Purwa",
    "wof:placetype":"neighbourhood",
    "wof:population":112
},
  "geometry": {"coordinates":[81.379969,27.197365],"type":"Point"}
}