{
  "type": "Feature",
  "properties": {
    "iso:country":"IN",
    "ks:ks_alt_nam":"Noopura Residency beside rd",
    "ks:ks_name":"Noopura Residency Beside Rd",
    "ks:ks_pop":372,
    "ks:ks_type":"HABITATION",
    "name:eng_x_preferred":[
        "Noopura Residency Beside Rd"
    ],
    "wof:name":"Noopura Residency Beside Rd",
    "wof:placetype":"locality",
    "wof:population":372
},
  "geometry": {"coordinates":[76.416526,10.678191],"type":"Point"}
}