{
  "type": "Feature",
  "properties": {
    "iso:country":"IN",
    "ks:ks_name":"Singlakundi",
    "ks:ks_pop":301,
    "ks:ks_type":"HABITATION",
    "name:eng_x_preferred":[
        "Singlakundi"
    ],
    "wof:name":"Singlakundi",
    "wof:placetype":"locality",
    "wof:population":301
},
  "geometry": {"coordinates":[74.663675,23.204769],"type":"Point"}
}