{
  "type": "Feature",
  "properties": {
    "iso:country":"IN",
    "ks:ks_name":"Rongpur Pt V",
    "ks:ks_pop":1533,
    "ks:ks_type":"VILLAGE",
    "name:eng_x_preferred":[
        "Rongpur Pt V"
    ],
    "wof:name":"Rongpur Pt V",
    "wof:placetype":"locality",
    "wof:population":1533
},
  "geometry": {"coordinates":[92.57730599999999,24.524023],"type":"Point"}
}