{
  "type": "Feature",
  "properties": {
    "iso:country":"IN",
    "ks:ks_name":"Valipara",
    "ks:ks_pop":765,
    "ks:ks_type":"HABITATION",
    "name:eng_x_preferred":[
        "Valipara"
    ],
    "wof:name":"Valipara",
    "wof:placetype":"locality",
    "wof:population":765
},
  "geometry": {"coordinates":[76.85283800000001,8.851603],"type":"Point"}
}