{
  "type": "Feature",
  "properties": {
    "iso:country":"IN",
    "ks:ks_name":"Amadongari",
    "ks:ks_pop":156,
    "ks:ks_type":"HABITATION",
    "name:eng_x_preferred":[
        "Amadongari"
    ],
    "wof:name":"Amadongari",
    "wof:placetype":"locality",
    "wof:population":156
},
  "geometry": {"coordinates":[81.982039,19.002093],"type":"Point"}
}