{
  "type": "Feature",
  "properties": {
    "iso:country":"IN",
    "ks:ks_name":"Munundpara",
    "ks:ks_pop":247,
    "ks:ks_type":"HABITATION",
    "name:eng_x_preferred":[
        "Munundpara"
    ],
    "wof:name":"Munundpara",
    "wof:placetype":"locality",
    "wof:population":247
},
  "geometry": {"coordinates":[83.111349,22.215563],"type":"Point"}
}