{
  "type": "Feature",
  "properties": {
    "gn:admin1_code":"35",
    "gn:admin2_code":"456.0",
    "gn:asciiname":"Begarwani Buzurg",
    "gn:country_code":"IN",
    "gn:dem":517,
    "gn:feature_class":"P",
    "gn:feature_code":"PPL",
    "gn:name":"Begarw\u0101ni Buzurg",
    "gn:population":0,
    "gn:timezone":"Asia/Kolkata",
    "iso:country":"IN",
    "wof:name":"Begarwani Buzurg",
    "wof:placetype":"neighbourhood"
},
  "geometry": {"coordinates":[79.94070000000001,22.51498],"type":"Point"}
}