{
  "type": "Feature",
  "properties": {
    "iso:country":"IN",
    "ks:ks_name":"Dattabag",
    "ks:ks_pop":120,
    "ks:ks_type":"HABITATION",
    "name:eng_x_preferred":[
        "Dattabag"
    ],
    "wof:name":"Dattabag",
    "wof:placetype":"locality",
    "wof:population":120
},
  "geometry": {"coordinates":[74.133661,19.584353],"type":"Point"}
}