{
  "type": "Feature",
  "properties": {
    "gn:country":"IN",
    "gn:fcode":"PPL",
    "gn:pop":23810,
    "iso:country":"IN",
    "qs:name":"Fatehganj West",
    "qs:photos_9r":0,
    "qs:photos_sr":0,
    "qs:pop_sr":"7",
    "wof:name":"Fatehganj West",
    "wof:placetype":"locality",
    "wof:population":23810
},
  "geometry": {"coordinates":[79.30418,28.46125],"type":"Point"}
}