{
  "type": "Feature",
  "properties": {
    "iso:country":"IN",
    "ks:ks_name":"Dhusai",
    "ks:ks_pop":516,
    "ks:ks_type":"VILLAGE",
    "name:eng_x_preferred":[
        "Dhusai"
    ],
    "wof:name":"Dhusai",
    "wof:placetype":"locality",
    "wof:population":516
},
  "geometry": {"coordinates":[76.999156,26.164153],"type":"Point"}
}