{
  "type": "Feature",
  "properties": {
    "gn:admin1_code":"37",
    "gn:admin2_code":"408.0",
    "gn:asciiname":"Munjal",
    "gn:country_code":"IN",
    "gn:dem":357,
    "gn:feature_class":"P",
    "gn:feature_code":"PPL",
    "gn:name":"Munj\u0101l",
    "gn:population":0,
    "gn:timezone":"Asia/Kolkata",
    "iso:country":"IN",
    "ks:ks_name":"Munjal",
    "ks:ks_pop":371,
    "ks:ks_type":"VILLAGE",
    "name:eng_x_preferred":[
        "Munjal"
    ],
    "wof:name":"Munjal",
    "wof:placetype":"locality",
    "wof:population":371
},
  "geometry": {"coordinates":[80.651824,20.777664],"type":"Point"}
}