{
  "type": "Feature",
  "properties": {
    "iso:country":"IN",
    "ks:ks_name":"Chiramarni Urf Chorajor",
    "ks:ks_pop":199,
    "ks:ks_type":"VILLAGE",
    "name:eng_x_preferred":[
        "Chiramarni Urf Chorajor"
    ],
    "wof:name":"Chiramarni Urf Chorajor",
    "wof:placetype":"locality",
    "wof:population":199
},
  "geometry": {"coordinates":[86.84156900000001,24.371982],"type":"Point"}
}