{
  "type": "Feature",
  "properties": {
    "gn:admin1_code":"39.0",
    "gn:admin2_code":"132",
    "gn:asciiname":"Thapal",
    "gn:country_code":"IN",
    "gn:dem":313,
    "gn:feature_class":"P",
    "gn:feature_code":"PPL",
    "gn:name":"Th\u0101pal",
    "gn:population":0,
    "gn:timezone":"Asia/Kolkata",
    "iso:country":"IN",
    "wof:name":"Thapal",
    "wof:placetype":"locality"
},
  "geometry": {"coordinates":[77.83289000000001,30.09513],"type":"Point"}
}