{
  "type": "Feature",
  "properties": {
    "gn:admin1_code":"36",
    "gn:admin2_code":"172.0",
    "gn:asciiname":"Kakraiha",
    "gn:country_code":"IN",
    "gn:dem":118,
    "gn:feature_class":"P",
    "gn:feature_code":"PPL",
    "gn:name":"Kakraiha",
    "gn:population":0,
    "gn:timezone":"Asia/Kolkata",
    "iso:country":"IN",
    "wof:name":"Kakraiha",
    "wof:placetype":"neighbourhood"
},
  "geometry": {"coordinates":[80.7167,25.86408],"type":"Point"}
}