{
  "type": "Feature",
  "properties": {
    "gn:admin1_code":"11.0",
    "gn:admin2_code":"27.0",
    "gn:asciiname":"Kanda",
    "gn:country_code":"IN",
    "gn:dem":2026,
    "gn:feature_class":"P",
    "gn:feature_code":"PPL",
    "gn:name":"K\u0101nda",
    "gn:population":0,
    "gn:timezone":"Asia/Kolkata",
    "iso:country":"IN",
    "wof:name":"Kanda",
    "wof:placetype":"locality"
},
  "geometry": {"coordinates":[77.10446,31.55929],"type":"Point"}
}