{
  "type": "Feature",
  "properties": {
    "gn:admin1_code":"16",
    "gn:admin2_code":"503.0",
    "gn:asciiname":"Shendurjana",
    "gn:country_code":"IN",
    "gn:dem":434,
    "gn:feature_class":"P",
    "gn:feature_code":"PPL",
    "gn:name":"Shendurjana",
    "gn:population":0,
    "gn:timezone":"Asia/Kolkata",
    "iso:country":"IN",
    "name:ben_x_preferred":[
        "\u09b6\u09c7\u09a8\u09a6\u09c1\u09b0\u099c\u09a8\u09be"
    ],
    "name:bpy_x_preferred":[
        "\u09b6\u09c7\u09a8\u09a6\u09c1\u09b0\u099c\u09a8\u09be"
    ],
    "name:hif_x_preferred":[
        "Shendurjana"
    ],
    "name:ind_x_preferred":[
        "Shendurjana"
    ],
    "name:ita_x_preferred":[
        "Shendurjana"
    ],
    "name:msa_x_preferred":[
        "Shendurjana"
    ],
    "name:nld_x_preferred":[
        "Shendurjana"
    ],
    "name:ori_x_preferred":[
        "\u0b36\u0b47\u0b28\u0b4d\u0b26\u0b41\u0b30\u0b4d\u0b1c\u0b3e\u0b28\u0b3e"
    ],
    "name:por_x_preferred":[
        "Shendurjana"
    ],
    "name:und_x_variant":[
        "Sendurjana"
    ],
    "name:urd_x_preferred":[
        "\u0634\u06cc\u0646\u062f\u0648\u0631\u062c\u0627\u0646\u0627 \u06af\u06be\u0627\u0679"
    ],
    "name:vie_x_preferred":[
        "Shendurjana"
    ],
    "name:zho_x_preferred":[
        "\u65af\u4ea8\u675c\u5c14\u8d3e\u7eb3"
    ],
    "wof:name":"Shendurjana",
    "wof:placetype":"locality"
},
  "geometry": {"coordinates":[78.2835,21.52488],"type":"Point"}
}