{
  "type": "Feature",
  "properties": {
    "gn:admin1_code":"16",
    "gn:admin2_code":"503.0",
    "gn:asciiname":"Shendurjana",
    "gn:country_code":"IN",
    "gn:dem":434,
    "gn:feature_class":"P",
    "gn:feature_code":"PPL",
    "gn:name":"Shendurjana",
    "gn:population":0,
    "gn:timezone":"Asia/Kolkata",
    "iso:country":"IN",
    "name:und_x_variant":[
        "Sendurjana"
    ],
    "wof:name":"Shendurjana",
    "wof:placetype":"locality"
},
  "geometry": {"coordinates":[78.2835,21.52488],"type":"Point"}
}