{
  "type": "Feature",
  "properties": {
    "iso:country":"IN",
    "ks:ks_name":"Kalajan No2",
    "ks:ks_pop":793,
    "ks:ks_type":"HABITATION",
    "ks:ks_uagg_main":0,
    "name:eng_x_preferred":[
        "Kalajan No2"
    ],
    "wof:name":"Kalajan No2",
    "wof:placetype":"neighbourhood",
    "wof:population":793
},
  "geometry": {"coordinates":[94.09779,26.339716],"type":"Point"}
}