{
  "type": "Feature",
  "properties": {
    "gn:admin1_code":"37.0",
    "gn:admin2_code":"414",
    "gn:asciiname":"Keskal",
    "gn:country_code":"IN",
    "gn:dem":668,
    "gn:feature_class":"P",
    "gn:feature_code":"PPL",
    "gn:name":"Kesk\u0101l",
    "gn:population":0,
    "gn:timezone":"Asia/Kolkata",
    "iso:country":"IN",
    "name:und_x_variant":[
        "Kesk\u0101l"
    ],
    "wof:name":"Keskal",
    "wof:placetype":"locality"
},
  "geometry": {"coordinates":[81.58674999999999,20.0836],"type":"Point"}
}