{
  "type": "Feature",
  "properties": {
    "iso:country":"IN",
    "ks:ks_name":"Sangitapatti",
    "ks:ks_pop":2335,
    "ks:ks_type":"VILLAGE",
    "ks:ks_uagg_main":0,
    "name:eng_x_preferred":[
        "Sangitapatti"
    ],
    "wof:name":"Sangitapatti",
    "wof:placetype":"neighbourhood",
    "wof:population":2335
},
  "geometry": {"coordinates":[78.080986,11.729105],"type":"Point"}
}