{
  "type": "Feature",
  "properties": {
    "iso:country":"IN",
    "ks:ks_name":"42 NDR",
    "ks:ks_pop":89,
    "ks:ks_type":"VILLAGE",
    "name:eng_x_preferred":[
        "42 NDR"
    ],
    "wof:name":"42 NDR",
    "wof:placetype":"locality",
    "wof:population":89
},
  "geometry": {"coordinates":[74.169461,29.416833],"type":"Point"}
}