{
  "type": "Feature",
  "properties": {
    "gn:admin1_code":"16",
    "gn:admin2_code":"502.0",
    "gn:asciiname":"Nagalvadi",
    "gn:country_code":"IN",
    "gn:dem":338,
    "gn:feature_class":"P",
    "gn:feature_code":"PPL",
    "gn:name":"N\u0101galv\u0101di",
    "gn:population":0,
    "gn:timezone":"Asia/Kolkata",
    "iso:country":"IN",
    "wof:name":"Nagalvadi",
    "wof:placetype":"locality"
},
  "geometry": {"coordinates":[77.62269999999999,20.6465],"type":"Point"}
}