{
  "type": "Feature",
  "properties": {
    "iso:country":"IN",
    "ks:ks_alt_nam":"Lingdh\u0101l",
    "ks:ks_name":"Lingdhal",
    "ks:ks_type":"VILLAGE",
    "name:eng_x_preferred":[
        "Lingdhal"
    ],
    "name:eng_x_variant":[
        "Lingdh\u0101l"
    ],
    "wof:name":"Lingdhal",
    "wof:placetype":"locality"
},
  "geometry": {"coordinates":[75.50520299999999,15.859268],"type":"Point"}
}