{
  "type": "Feature",
  "properties": {
    "iso:country":"IN",
    "ks:ks_name":"Salawali",
    "ks:ks_pop":1074,
    "ks:ks_type":"VILLAGE",
    "name:eng_x_preferred":[
        "Salawali"
    ],
    "wof:name":"Salawali",
    "wof:placetype":"locality",
    "wof:population":1074
},
  "geometry": {"coordinates":[75.822743,27.644332],"type":"Point"}
}