{
  "type": "Feature",
  "properties": {
    "gn:admin1_code":"12.0",
    "gn:admin2_code":"008",
    "gn:asciiname":"Nadihal",
    "gn:country_code":"IN",
    "gn:dem":1598,
    "gn:feature_class":"P",
    "gn:feature_code":"PPL",
    "gn:name":"N\u0101dihal",
    "gn:population":0,
    "gn:timezone":"Asia/Kolkata",
    "iso:country":"IN",
    "name:und_x_variant":[
        "N\u0101dihal",
        "N\u0101dibal"
    ],
    "wof:name":"Nadihal",
    "wof:placetype":"locality"
},
  "geometry": {"coordinates":[74.36913,34.25783],"type":"Point"}
}