{
  "type": "Feature",
  "properties": {
    "gn:admin1_code":"9.0",
    "gn:admin2_code":"491",
    "gn:asciiname":"Kolak",
    "gn:country_code":"IN",
    "gn:dem":10,
    "gn:feature_class":"P",
    "gn:feature_code":"PPL",
    "gn:name":"Kolak",
    "gn:population":0,
    "gn:timezone":"Asia/Kolkata",
    "iso:country":"IN",
    "ks:ks_name":"Kolak",
    "ks:ks_pop":4503,
    "ks:ks_type":"VILLAGE",
    "ks:ks_uagg_main":0,
    "name:bjn_x_preferred":[
        "Sarawa"
    ],
    "name:eng_x_preferred":[
        "Kolak"
    ],
    "name:fra_x_preferred":[
        "Kolak"
    ],
    "name:ind_x_preferred":[
        "Kolak"
    ],
    "name:jav_x_preferred":[
        "Kolak"
    ],
    "name:sun_x_preferred":[
        "Kolek"
    ],
    "wof:name":"Kolak",
    "wof:placetype":"neighbourhood",
    "wof:population":4503
},
  "geometry": {"coordinates":[72.861437,20.468833],"type":"Point"}
}