{
  "type": "Feature",
  "properties": {
    "gn:admin1_code":"11.0",
    "gn:admin2_code":"27.0",
    "gn:asciiname":"Mathunu",
    "gn:country_code":"IN",
    "gn:dem":1820,
    "gn:feature_class":"P",
    "gn:feature_code":"PPL",
    "gn:name":"Math\u016bnu",
    "gn:population":0,
    "gn:timezone":"Asia/Kolkata",
    "iso:country":"IN",
    "wof:name":"Mathunu",
    "wof:placetype":"locality"
},
  "geometry": {"coordinates":[77.22943000000002,31.70364],"type":"Point"}
}