{
  "type": "Feature",
  "properties": {
    "iso:country":"IN",
    "ks:ks_name":"Pure Meharbaan",
    "ks:ks_pop":34,
    "ks:ks_type":"HABITATION",
    "ks:ks_uagg_main":0,
    "name:eng_x_preferred":[
        "Pure Meharbaan"
    ],
    "wof:name":"Pure Meharbaan",
    "wof:placetype":"neighbourhood",
    "wof:population":34
},
  "geometry": {"coordinates":[81.930274,26.061141],"type":"Point"}
}