{
  "type": "Feature",
  "properties": {
    "iso:country":"IN",
    "ks:ks_name":"Chillevaripalem",
    "ks:ks_pop":172,
    "ks:ks_type":"HABITATION",
    "name:eng_x_preferred":[
        "Chillevaripalem"
    ],
    "wof:name":"Chillevaripalem",
    "wof:placetype":"locality",
    "wof:population":172
},
  "geometry": {"coordinates":[81.844712,16.545377],"type":"Point"}
}