{
  "type": "Feature",
  "properties": {
    "gn:admin1_code":"35",
    "gn:asciiname":"Purwa Sargaiyan",
    "gn:country_code":"IN",
    "gn:dem":168,
    "gn:feature_class":"P",
    "gn:feature_code":"PPL",
    "gn:name":"Purwa Sargaiyan",
    "gn:population":0,
    "gn:timezone":"Asia/Kolkata",
    "iso:country":"IN",
    "name:eng_x_preferred":[
        "Purwa Sargaiyan"
    ],
    "wof:name":"Purwa Sargaiyan",
    "wof:placetype":"neighbourhood"
},
  "geometry": {"coordinates":[80.01805,25.31713],"type":"Point"}
}