{
  "type": "Feature",
  "properties": {
    "gn:admin1_code":"13.0",
    "gn:admin2_code":"596.0",
    "gn:asciiname":"Karumutti",
    "gn:country_code":"IN",
    "gn:dem":988,
    "gn:feature_class":"P",
    "gn:feature_code":"PPL",
    "gn:name":"Karumutti",
    "gn:population":0,
    "gn:timezone":"Asia/Kolkata",
    "iso:country":"IN",
    "wof:name":"Karumutti",
    "wof:placetype":"neighbourhood"
},
  "geometry": {"coordinates":[77.16651,10.2866],"type":"Point"}
}