{
  "type": "Feature",
  "properties": {
    "iso:country":"IN",
    "ks:ks_name":"Naya Purwa",
    "ks:ks_pop":17,
    "ks:ks_type":"HABITATION",
    "name:eng_x_preferred":[
        "Naya Purwa"
    ],
    "wof:name":"Naya Purwa",
    "wof:placetype":"locality",
    "wof:population":17
},
  "geometry": {"coordinates":[81.747407,26.401882],"type":"Point"}
}