{
  "type": "Feature",
  "properties": {
    "gn:admin1_code":"36.0",
    "gn:admin2_code":"163.0",
    "gn:asciiname":"Mau",
    "gn:country_code":"IN",
    "gn:dem":138,
    "gn:feature_class":"P",
    "gn:feature_code":"PPL",
    "gn:name":"Mau",
    "gn:population":0,
    "gn:timezone":"Asia/Kolkata",
    "iso:country":"IN",
    "ks:ks_name":"Mau",
    "ks:ks_pop":685,
    "ks:ks_type":"VILLAGE",
    "name:ara_x_preferred":[
        "\u0645\u0627\u0648"
    ],
    "name:azb_x_preferred":[
        "\u0645\u0627\u0648"
    ],
    "name:ben_bn_x_preferred":[
        "\u09ae\u09be\u0989"
    ],
    "name:ben_in_x_preferred":[
        "\u09ae\u09be\u0989"
    ],
    "name:cat_x_preferred":[
        "Mau"
    ],
    "name:ceb_x_preferred":[
        "Mau"
    ],
    "name:deu_x_preferred":[
        "Mau"
    ],
    "name:eng_x_preferred":[
        "Mau"
    ],
    "name:fas_x_preferred":[
        "\u0645\u0627\u0648"
    ],
    "name:fra_x_preferred":[
        "Mau"
    ],
    "name:guj_x_preferred":[
        "\u0aae\u0abe\u0a89"
    ],
    "name:hin_x_preferred":[
        "\u092e\u090a"
    ],
    "name:ita_x_preferred":[
        "Mau"
    ],
    "name:kan_x_preferred":[
        "\u0cae\u0cbe\u0cb5\u0ccd"
    ],
    "name:mal_x_preferred":[
        "\u0d2e\u0d57"
    ],
    "name:mar_x_preferred":[
        "\u092e\u093e\u090a"
    ],
    "name:msa_x_preferred":[
        "Mau"
    ],
    "name:nld_x_preferred":[
        "Mau"
    ],
    "name:pan_x_preferred":[
        "\u0a2e\u0a3e\u0a13"
    ],
    "name:pnb_x_preferred":[
        "\u0645\u0626\u0648"
    ],
    "name:pol_x_preferred":[
        "Mau"
    ],
    "name:por_x_preferred":[
        "Maunath Bhanjan"
    ],
    "name:rus_x_preferred":[
        "\u041c\u0430\u0443"
    ],
    "name:san_x_preferred":[
        "\u092e\u0935\u0941"
    ],
    "name:srp_x_preferred":[
        "\u041c\u0430\u0443"
    ],
    "name:swe_x_preferred":[
        "Maunath Bhanjan"
    ],
    "name:tam_x_preferred":[
        "\u0bae\u0bcc"
    ],
    "name:tel_x_preferred":[
        "\u0c2e\u0c4c"
    ],
    "name:urd_x_preferred":[
        "\u0645\u0626\u0648"
    ],
    "name:vie_x_preferred":[
        "Maunath Bhanjan"
    ],
    "name:war_x_preferred":[
        "Mau"
    ],
    "name:zho_x_preferred":[
        "\u6bdb\u7eb3\u7279\u73ed\u8a79"
    ],
    "wof:name":"Mau",
    "wof:placetype":"locality",
    "wof:population":685
},
  "geometry": {"coordinates":[79.88393499999999,26.672058],"type":"Point"}
}