{
  "type": "Feature",
  "properties": {
    "iso:country":"IN",
    "ks:ks_name":"Appapurpenta",
    "ks:ks_pop":84,
    "ks:ks_type":"HABITATION",
    "name:eng_x_preferred":[
        "Appapurpenta"
    ],
    "wof:name":"Appapurpenta",
    "wof:placetype":"locality",
    "wof:population":84
},
  "geometry": {"coordinates":[78.670067,16.181269],"type":"Point"}
}