{
  "type": "Feature",
  "properties": {
    "iso:country":"IN",
    "ks:ks_name":"Manik Bill",
    "ks:ks_pop":25,
    "ks:ks_type":"HABITATION",
    "ks:ks_uagg_main":0,
    "name:eng_x_preferred":[
        "Manik Bill"
    ],
    "wof:name":"Manik Bill",
    "wof:placetype":"neighbourhood",
    "wof:population":25
},
  "geometry": {"coordinates":[94.302689,26.93958],"type":"Point"}
}