{
  "type": "Feature",
  "properties": {
    "iso:country":"IN",
    "ks:ks_name":"Dongarewasti",
    "ks:ks_pop":679,
    "ks:ks_type":"HABITATION",
    "name:eng_x_preferred":[
        "Dongarewasti"
    ],
    "wof:name":"Dongarewasti",
    "wof:placetype":"locality",
    "wof:population":679
},
  "geometry": {"coordinates":[74.71369300000001,19.176598],"type":"Point"}
}