{
  "type": "Feature",
  "properties": {
    "gn:admin1_code":"39.0",
    "gn:admin2_code":"66.0",
    "gn:asciiname":"Kaulgaon",
    "gn:country_code":"IN",
    "gn:dem":1933,
    "gn:feature_class":"P",
    "gn:feature_code":"PPL",
    "gn:name":"Kaulgaon",
    "gn:population":0,
    "gn:timezone":"Asia/Kolkata",
    "iso:country":"IN",
    "wof:name":"Kaulgaon",
    "wof:placetype":"locality"
},
  "geometry": {"coordinates":[79.64461999999997,29.4042],"type":"Point"}
}