{
  "type": "Feature",
  "properties": {
    "iso:country":"IN",
    "ks:ks_name":"East Babura",
    "ks:ks_pop":2931,
    "ks:ks_type":"HABITATION",
    "name:eng_x_preferred":[
        "East Babura"
    ],
    "wof:name":"East Babura",
    "wof:placetype":"locality",
    "wof:population":2931
},
  "geometry": {"coordinates":[84.793933,25.682795],"type":"Point"}
}