{
  "type": "Feature",
  "properties": {
    "iso:country":"IN",
    "ks:ks_alt_nam":"Embannavalasa Agrah\u0101ram",
    "ks:ks_alt_nam_2":"Embannavalasa Agraharam",
    "ks:ks_name":"Embannavalasa",
    "ks:ks_pop":0,
    "ks:ks_type":"VILLAGE",
    "name:eng_x_preferred":[
        "Embannavalasa"
    ],
    "name:eng_x_variant":[
        "Embannavalasa Agrah\u0101ram",
        "Embannavalasa Agraharam"
    ],
    "wof:name":"Embannavalasa",
    "wof:placetype":"locality",
    "wof:population":0
},
  "geometry": {"coordinates":[83.40797999999999,18.557939],"type":"Point"}
}