{
  "type": "Feature",
  "properties": {
    "iso:country":"IN",
    "ks:ks_name":"Tetariyatanr",
    "ks:ks_pop":102,
    "ks:ks_type":"HABITATION",
    "name:eng_x_preferred":[
        "Tetariyatanr"
    ],
    "wof:name":"Tetariyatanr",
    "wof:placetype":"locality",
    "wof:population":102
},
  "geometry": {"coordinates":[86.8612,24.218223],"type":"Point"}
}