{
  "type": "Feature",
  "properties": {
    "gn:admin1_code":"12",
    "gn:asciiname":"Bharan Paihri",
    "gn:country_code":"IN",
    "gn:dem":2715,
    "gn:feature_class":"P",
    "gn:feature_code":"PPL",
    "gn:name":"Bharan Paihri",
    "gn:population":0,
    "gn:timezone":"Asia/Kolkata",
    "iso:country":"IN",
    "wof:name":"Bharan Paihri",
    "wof:placetype":"locality"
},
  "geometry": {"coordinates":[74.05929999999999,34.19417],"type":"Point"}
}