{
  "type": "Feature",
  "properties": {
    "iso:country":"IN",
    "ks:ks_alt_nam":"Monabari TE 153 269",
    "ks:ks_name":"Monabari Te 153 269",
    "ks:ks_pop":1912,
    "ks:ks_type":"HABITATION",
    "ks:ks_uagg_main":0,
    "name:eng_x_preferred":[
        "Monabari Te 153 269"
    ],
    "wof:name":"Monabari Te 153 269",
    "wof:placetype":"neighbourhood",
    "wof:population":1912
},
  "geometry": {"coordinates":[93.24867399999999,26.748228],"type":"Point"}
}