{
  "type": "Feature",
  "properties": {
    "iso:country":"IN",
    "ks:ks_name":"Somjidhana",
    "ks:ks_pop":21,
    "ks:ks_type":"HABITATION",
    "name:eng_x_preferred":[
        "Somjidhana"
    ],
    "wof:name":"Somjidhana",
    "wof:placetype":"locality",
    "wof:population":21
},
  "geometry": {"coordinates":[77.827376,22.586801],"type":"Point"}
}