{
  "type": "Feature",
  "properties": {
    "gn:admin1_code":"2.0",
    "gn:admin2_code":"550.0",
    "gn:asciiname":"Kondavallipadu",
    "gn:country_code":"IN",
    "gn:dem":26,
    "gn:feature_class":"P",
    "gn:feature_code":"PPL",
    "gn:name":"Kondavallip\u0101du",
    "gn:population":0,
    "gn:timezone":"Asia/Kolkata",
    "iso:country":"IN",
    "wof:name":"Kondavallipadu",
    "wof:placetype":"locality"
},
  "geometry": {"coordinates":[79.93281,14.02322],"type":"Point"}
}