{
  "type": "Feature",
  "properties": {
    "iso:country":"IN",
    "ks:ks_name":"Tikirigam",
    "ks:ks_pop":255,
    "ks:ks_type":"HABITATION",
    "name:eng_x_preferred":[
        "Tikirigam"
    ],
    "wof:name":"Tikirigam",
    "wof:placetype":"locality",
    "wof:population":255
},
  "geometry": {"coordinates":[82.89227,18.929594],"type":"Point"}
}