{
  "type": "Feature",
  "properties": {
    "iso:country":"IN",
    "ks:ks_name":"Kathara",
    "ks:ks_pop":213,
    "ks:ks_type":"VILLAGE",
    "name:eng_x_preferred":[
        "Kathara"
    ],
    "wof:name":"Kathara",
    "wof:placetype":"locality",
    "wof:population":213
},
  "geometry": {"coordinates":[86.605198,25.018166],"type":"Point"}
}