{
  "type": "Feature",
  "properties": {
    "iso:country":"IN",
    "ks:ks_name":"Barsila",
    "ks:ks_pop":60,
    "ks:ks_type":"VILLAGE",
    "name:eng_x_preferred":[
        "Barsila"
    ],
    "wof:name":"Barsila",
    "wof:placetype":"locality",
    "wof:population":60
},
  "geometry": {"coordinates":[78.962632,30.125104],"type":"Point"}
}