{
  "type": "Feature",
  "properties": {
    "gn:admin1_code":"39",
    "gn:asciiname":"Nadal Dogri",
    "gn:country_code":"IN",
    "gn:dem":1626,
    "gn:feature_class":"P",
    "gn:feature_code":"PPL",
    "gn:name":"N\u0101dal Dogri",
    "gn:population":0,
    "gn:timezone":"Asia/Kolkata",
    "iso:country":"IN",
    "wof:name":"Nadal Dogri",
    "wof:placetype":"locality"
},
  "geometry": {"coordinates":[77.81612,31.05544],"type":"Point"}
}