{
  "type": "Feature",
  "properties": {
    "gn:admin1_code":"19.0",
    "gn:admin2_code":"584.0",
    "gn:asciiname":"Nagarsankote",
    "gn:country_code":"IN",
    "gn:dem":664,
    "gn:feature_class":"P",
    "gn:feature_code":"PPL",
    "gn:name":"N\u0101garsankote",
    "gn:population":0,
    "gn:timezone":"Asia/Kolkata",
    "iso:country":"IN",
    "ks:ks_name":"Nagarasanakote",
    "ks:ks_pop":1045,
    "ks:ks_type":"VILLAGE",
    "ks:ks_uagg_main":0,
    "name:eng_x_preferred":[
        "Nagarasanakote"
    ],
    "wof:name":"Nagarasanakote",
    "wof:placetype":"neighbourhood",
    "wof:population":1045
},
  "geometry": {"coordinates":[77.338724,12.438535],"type":"Point"}
}