{
  "type": "Feature",
  "properties": {
    "gn:admin1_code":"36",
    "gn:admin2_code":"188.0",
    "gn:asciiname":"Nawa Chak",
    "gn:country_code":"IN",
    "gn:dem":75,
    "gn:feature_class":"P",
    "gn:feature_code":"PPL",
    "gn:name":"Nawa Chak",
    "gn:population":0,
    "gn:timezone":"Asia/Kolkata",
    "iso:country":"IN",
    "ks:ks_name":"Nawachak",
    "ks:ks_pop":836,
    "ks:ks_type":"VILLAGE",
    "ks:ks_uagg_main":0,
    "name:eng_x_preferred":[
        "Nawachak"
    ],
    "wof:name":"Nawachak",
    "wof:placetype":"neighbourhood",
    "wof:population":836
},
  "geometry": {"coordinates":[83.482326,26.406588],"type":"Point"}
}