{
  "type": "Feature",
  "properties": {
    "gn:admin1_code":"36",
    "gn:admin2_code":"188.0",
    "gn:asciiname":"Sarsara Buzurg",
    "gn:country_code":"IN",
    "gn:dem":85,
    "gn:feature_class":"P",
    "gn:feature_code":"PPL",
    "gn:name":"Sarsara Buzurg",
    "gn:population":0,
    "gn:timezone":"Asia/Kolkata",
    "iso:country":"IN",
    "ks:ks_name":"Sarsara Bujurg",
    "ks:ks_pop":505,
    "ks:ks_type":"VILLAGE",
    "ks:ks_uagg_main":0,
    "name:eng_x_preferred":[
        "Sarsara Bujurg"
    ],
    "wof:name":"Sarsara Bujurg",
    "wof:placetype":"neighbourhood",
    "wof:population":505
},
  "geometry": {"coordinates":[83.304438,26.381937],"type":"Point"}
}