{
  "type": "Feature",
  "properties": {
    "iso:country":"IN",
    "ks:ks_name":"Khalchiwadi",
    "ks:ks_pop":284,
    "ks:ks_type":"HABITATION",
    "name:eng_x_preferred":[
        "Khalchiwadi"
    ],
    "wof:name":"Khalchiwadi",
    "wof:placetype":"locality",
    "wof:population":284
},
  "geometry": {"coordinates":[73.67561000000001,16.049448],"type":"Point"}
}