{
  "type": "Feature",
  "properties": {
    "iso:country":"IN",
    "ks:ks_name":"Dhanpur",
    "ks:ks_pop":636,
    "ks:ks_type":"VILLAGE",
    "name:eng_x_preferred":[
        "Dhanpur"
    ],
    "wof:name":"Dhanpur",
    "wof:placetype":"locality",
    "wof:population":636
},
  "geometry": {"coordinates":[82.41181400000001,22.998032],"type":"Point"}
}