{
  "type": "Feature",
  "properties": {
    "iso:country":"IN",
    "ks:ks_name":"Majhapada",
    "ks:ks_pop":50,
    "ks:ks_type":"HABITATION",
    "name:eng_x_preferred":[
        "Majhapada"
    ],
    "wof:name":"Majhapada",
    "wof:placetype":"locality",
    "wof:population":50
},
  "geometry": {"coordinates":[84.705145,22.181431],"type":"Point"}
}