{
  "type": "Feature",
  "properties": {
    "gn:admin1_code":"39.0",
    "gn:admin2_code":"061",
    "gn:asciiname":"Satpuli Malli",
    "gn:country_code":"IN",
    "gn:dem":926,
    "gn:feature_class":"P",
    "gn:feature_code":"PPL",
    "gn:name":"Satpuli Malli",
    "gn:population":0,
    "gn:timezone":"Asia/Kolkata",
    "iso:country":"IN",
    "wof:name":"Satpuli Malli",
    "wof:placetype":"locality"
},
  "geometry": {"coordinates":[78.70474,29.91069],"type":"Point"}
}