{
  "type": "Feature",
  "properties": {
    "iso:country":"IN",
    "ks:ks_name":"Bagdarh",
    "ks:ks_pop":236,
    "ks:ks_type":"HABITATION",
    "name:eng_x_preferred":[
        "Bagdarh"
    ],
    "wof:name":"Bagdarh",
    "wof:placetype":"locality",
    "wof:population":236
},
  "geometry": {"coordinates":[84.690292,22.893767],"type":"Point"}
}