{
  "type": "Feature",
  "properties": {
    "gn:admin1_code":"34.0",
    "gn:admin2_code":"232.0",
    "gn:asciiname":"Nikhura",
    "gn:country_code":"IN",
    "gn:dem":77,
    "gn:feature_class":"P",
    "gn:feature_code":"PPL",
    "gn:name":"Nikhura",
    "gn:population":0,
    "gn:timezone":"Asia/Kolkata",
    "iso:country":"IN",
    "wof:name":"Nikhura",
    "wof:placetype":"locality"
},
  "geometry": {"coordinates":[84.15649000000001,25.51693],"type":"Point"}
}