{
  "type": "Feature",
  "properties": {
    "gn:admin1_code":"9.0",
    "gn:admin2_code":"485.0",
    "gn:asciiname":"Wankia",
    "gn:country_code":"IN",
    "gn:dem":342,
    "gn:feature_class":"P",
    "gn:feature_code":"PPL",
    "gn:name":"W\u0101nkia",
    "gn:population":0,
    "gn:timezone":"Asia/Kolkata",
    "iso:country":"IN",
    "wof:name":"Wankia",
    "wof:placetype":"neighbourhood"
},
  "geometry": {"coordinates":[74.36703,22.74876],"type":"Point"}
}