{
  "type": "Feature",
  "properties": {
    "gn:admin1_code":"24",
    "gn:admin2_code":"104.0",
    "gn:asciiname":"Madhan",
    "gn:country_code":"IN",
    "gn:dem":295,
    "gn:feature_class":"P",
    "gn:feature_code":"PPL",
    "gn:name":"M\u0101dhan",
    "gn:population":0,
    "gn:timezone":"Asia/Kolkata",
    "iso:country":"IN",
    "name:und_x_variant":[
        "M\u0101dhan",
        "M\u0101ndhan"
    ],
    "wof:name":"Madhan",
    "wof:placetype":"locality"
},
  "geometry": {"coordinates":[76.37808000000003,28.10847],"type":"Point"}
}