{
  "type": "Feature",
  "properties": {
    "iso:country":"IN",
    "ks:ks_name":"Mahato Tola",
    "ks:ks_pop":79,
    "ks:ks_type":"HABITATION",
    "name:eng_x_preferred":[
        "Mahato Tola"
    ],
    "wof:name":"Mahato Tola",
    "wof:placetype":"locality",
    "wof:population":79
},
  "geometry": {"coordinates":[86.183336,24.026518],"type":"Point"}
}