{
  "type": "Feature",
  "properties": {
    "gn:admin1_code":"35",
    "gn:admin2_code":"428.0",
    "gn:asciiname":"Jamunia",
    "gn:country_code":"IN",
    "gn:dem":596,
    "gn:feature_class":"P",
    "gn:feature_code":"PPL",
    "gn:name":"Jamunia",
    "gn:population":0,
    "gn:timezone":"Asia/Kolkata",
    "iso:country":"IN",
    "ks:ks_name":"Jamuniya",
    "ks:ks_pop":293,
    "ks:ks_type":"VILLAGE",
    "name:eng_x_preferred":[
        "Jamuniya"
    ],
    "name:eng_x_variant":[
        "Jamunia"
    ],
    "wof:name":"Jamuniya",
    "wof:placetype":"locality",
    "wof:population":293
},
  "geometry": {"coordinates":[79.78590800000001,23.480954],"type":"Point"}
}