{
  "type": "Feature",
  "properties": {
    "gn:admin1_code":"36",
    "gn:admin2_code":"194.0",
    "gn:asciiname":"Khajura",
    "gn:country_code":"IN",
    "gn:dem":89,
    "gn:feature_class":"P",
    "gn:feature_code":"PPL",
    "gn:name":"Khaj\u016bra",
    "gn:population":0,
    "gn:timezone":"Asia/Kolkata",
    "iso:country":"IN",
    "ks:ks_alt_nam":"Khaj\u016bra",
    "ks:ks_name":"Khajura",
    "ks:ks_pop":1631,
    "ks:ks_type":"VILLAGE",
    "ks:ks_uagg_main":0,
    "name:eng_x_preferred":[
        "Khajura"
    ],
    "name:eng_x_variant":[
        "Khaj\u016bra"
    ],
    "wof:name":"Khajura",
    "wof:placetype":"neighbourhood",
    "wof:population":1631
},
  "geometry": {"coordinates":[82.625483,25.875124],"type":"Point"}
}