{
  "type": "Feature",
  "properties": {
    "gn:admin1_code":"11.0",
    "gn:admin2_code":"27.0",
    "gn:asciiname":"Manola",
    "gn:country_code":"IN",
    "gn:dem":1858,
    "gn:feature_class":"P",
    "gn:feature_code":"PPL",
    "gn:name":"Manola",
    "gn:population":0,
    "gn:timezone":"Asia/Kolkata",
    "iso:country":"IN",
    "name:ceb_x_preferred":[
        "Manola"
    ],
    "wof:name":"Manola",
    "wof:placetype":"locality"
},
  "geometry": {"coordinates":[77.15982,31.7353],"type":"Point"}
}