{
  "type": "Feature",
  "properties": {
    "iso:country":"IN",
    "ks:ks_name":"Gorwa",
    "ks:ks_pop":619,
    "ks:ks_type":"VILLAGE",
    "ks:ks_uagg_main":0,
    "name:eng_x_preferred":[
        "Gorwa"
    ],
    "wof:name":"Gorwa",
    "wof:placetype":"neighbourhood",
    "wof:population":619
},
  "geometry": {"coordinates":[80.554585,26.987194],"type":"Point"}
}