{
  "type": "Feature",
  "properties": {
    "iso:country":"IN",
    "ks:ks_name":"Durgam",
    "ks:ks_pop":55,
    "ks:ks_type":"HABITATION",
    "name:eng_x_preferred":[
        "Durgam"
    ],
    "wof:name":"Durgam",
    "wof:placetype":"locality",
    "wof:population":55
},
  "geometry": {"coordinates":[82.878107,18.191203],"type":"Point"}
}