{
  "type": "Feature",
  "properties": {
    "iso:country":"IN",
    "ks:ks_name":"Doraguda",
    "ks:ks_pop":51,
    "ks:ks_type":"HABITATION",
    "name:eng_x_preferred":[
        "Doraguda"
    ],
    "wof:name":"Doraguda",
    "wof:placetype":"locality",
    "wof:population":51
},
  "geometry": {"coordinates":[82.743656,18.320471],"type":"Point"}
}