{
  "type": "Feature",
  "properties": {
    "iso:country":"IN",
    "ks:ks_name":"Pachora",
    "ks:ks_pop":811,
    "ks:ks_type":"VILLAGE",
    "name:eng_x_preferred":[
        "Pachora"
    ],
    "wof:name":"Pachora",
    "wof:placetype":"locality",
    "wof:population":811
},
  "geometry": {"coordinates":[77.227688,27.295116],"type":"Point"}
}