{
  "type": "Feature",
  "properties": {
    "gn:admin1_code":"37.0",
    "gn:admin2_code":"416.0",
    "gn:asciiname":"Kamaram",
    "gn:country_code":"IN",
    "gn:dem":200,
    "gn:feature_class":"P",
    "gn:feature_code":"PPL",
    "gn:name":"K\u0101m\u0101ram",
    "gn:population":0,
    "gn:timezone":"Asia/Kolkata",
    "iso:country":"IN",
    "ks:ks_alt_nam":"K\u0101m\u0101ram",
    "ks:ks_name":"Kamaram",
    "ks:ks_pop":270,
    "ks:ks_type":"VILLAGE",
    "name:eng_x_preferred":[
        "Kamaram"
    ],
    "name:eng_x_variant":[
        "K\u0101m\u0101ram"
    ],
    "wof:name":"Kamaram",
    "wof:placetype":"locality",
    "wof:population":270
},
  "geometry": {"coordinates":[81.203879,18.411764],"type":"Point"}
}