{
  "type": "Feature",
  "properties": {
    "iso:country":"IN",
    "ks:ks_name":"Badripar",
    "ks:ks_pop":1891,
    "ks:ks_type":"HABITATION",
    "name:eng_x_preferred":[
        "Badripar"
    ],
    "wof:name":"Badripar",
    "wof:placetype":"locality",
    "wof:population":1891
},
  "geometry": {"coordinates":[92.899204,24.832611],"type":"Point"}
}