{
  "type": "Feature",
  "properties": {
    "gn:admin1_code":"19.0",
    "gn:admin2_code":"563.0",
    "gn:asciiname":"Shambhumane",
    "gn:country_code":"IN",
    "gn:dem":532,
    "gn:feature_class":"P",
    "gn:feature_code":"PPL",
    "gn:name":"Shambhumane",
    "gn:population":0,
    "gn:timezone":"Asia/Kolkata",
    "iso:country":"IN",
    "wof:name":"Shambhumane",
    "wof:placetype":"locality"
},
  "geometry": {"coordinates":[74.67409000000001,14.98574],"type":"Point"}
}