{
  "type": "Feature",
  "properties": {
    "iso:country":"IN",
    "ks:ks_name":"Haridagotha",
    "ks:ks_pop":0,
    "ks:ks_type":"VILLAGE",
    "name:eng_x_preferred":[
        "Haridagotha"
    ],
    "wof:name":"Haridagotha",
    "wof:placetype":"locality",
    "wof:population":0
},
  "geometry": {"coordinates":[85.819422,21.33585],"type":"Point"}
}