{
  "type": "Feature",
  "properties": {
    "iso:country":"IN",
    "ks:ks_name":"Tulajwadi",
    "ks:ks_pop":268,
    "ks:ks_type":"HABITATION",
    "name:eng_x_preferred":[
        "Tulajwadi"
    ],
    "wof:name":"Tulajwadi",
    "wof:placetype":"locality",
    "wof:population":268
},
  "geometry": {"coordinates":[75.35158,19.17763],"type":"Point"}
}