{
  "type": "Feature",
  "properties": {
    "iso:country":"IN",
    "ks:ks_name":"Pana Chhapra Urf Sanrha Sumar",
    "ks:ks_pop":3210,
    "ks:ks_type":"VILLAGE",
    "name:eng_x_preferred":[
        "Pana Chhapra Urf Sanrha Sumar"
    ],
    "wof:name":"Pana Chhapra Urf Sanrha Sumar",
    "wof:placetype":"locality",
    "wof:population":3210
},
  "geometry": {"coordinates":[85.170751,26.230191],"type":"Point"}
}