{
  "type": "Feature",
  "properties": {
    "iso:country":"IN",
    "ks:ks_name":"B B Palayam",
    "ks:ks_pop":510,
    "ks:ks_type":"HABITATION",
    "name:eng_x_preferred":[
        "B B Palayam"
    ],
    "wof:name":"B B Palayam",
    "wof:placetype":"locality",
    "wof:population":510
},
  "geometry": {"coordinates":[77.68746899999999,12.559803],"type":"Point"}
}