{
  "type": "Feature",
  "properties": {
    "iso:country":"IN",
    "ks:ks_name":"Punade",
    "ks:ks_pop":623,
    "ks:ks_type":"VILLAGE",
    "ks:ks_uagg_main":0,
    "name:eng_x_preferred":[
        "Punade"
    ],
    "wof:name":"Punade",
    "wof:placetype":"neighbourhood",
    "wof:population":623
},
  "geometry": {"coordinates":[73.028688,18.824837],"type":"Point"}
}