{
  "type": "Feature",
  "properties": {
    "iso:country":"IN",
    "ks:ks_name":"Bogribari",
    "ks:ks_pop":253,
    "ks:ks_type":"HABITATION",
    "ks:ks_uagg_main":0,
    "name:eng_x_preferred":[
        "Bogribari"
    ],
    "wof:name":"Bogribari",
    "wof:placetype":"neighbourhood",
    "wof:population":253
},
  "geometry": {"coordinates":[91.37843700000001,26.713541],"type":"Point"}
}