{
  "type": "Feature",
  "properties": {
    "gn:admin1_code":"16.0",
    "gn:admin2_code":"514.0",
    "gn:asciiname":"Jalgaon",
    "gn:country_code":"IN",
    "gn:dem":484,
    "gn:feature_class":"P",
    "gn:feature_code":"PPL",
    "gn:name":"Jalgaon",
    "gn:population":0,
    "gn:timezone":"Asia/Kolkata",
    "iso:country":"IN",
    "name:ara_x_preferred":[
        "\u062c\u0627\u0644\u062c\u0627\u0648\u0646"
    ],
    "name:azb_x_preferred":[
        "\u062c\u0627\u0644\u0642\u0627\u0648\u0646"
    ],
    "name:ben_x_preferred":[
        "\u099c\u09b2\u0997\u09be\u0981\u0993"
    ],
    "name:bih_x_preferred":[
        "\u091c\u0932\u0917\u093e\u0901\u0935"
    ],
    "name:bpy_x_preferred":[
        "\u099c\u09be\u09b2\u0997\u09be\u0981\u0993"
    ],
    "name:ceb_x_preferred":[
        "J\u0101lgaon"
    ],
    "name:deu_x_preferred":[
        "Jalgaon"
    ],
    "name:epo_x_preferred":[
        "\u011calgaon"
    ],
    "name:fas_x_preferred":[
        "\u062c\u0627\u0644\u06af\u0627\u0648\u0646"
    ],
    "name:fra_x_preferred":[
        "Jalgaon"
    ],
    "name:guj_x_preferred":[
        "\u0a9c\u0ab2\u0a97\u0abe\u0a82\u0ab5"
    ],
    "name:hin_x_preferred":[
        "\u091c\u0932\u0917\u093e\u0901\u0935"
    ],
    "name:ita_x_preferred":[
        "Jalgaon"
    ],
    "name:lit_x_preferred":[
        "D\u017ealgaonas"
    ],
    "name:mar_x_preferred":[
        "\u091c\u0933\u0917\u093e\u0935"
    ],
    "name:mlg_x_preferred":[
        "Jalgaon"
    ],
    "name:msa_x_preferred":[
        "Jalgaon"
    ],
    "name:new_x_preferred":[
        "\u091c\u0932\u0917\u093e\u0935"
    ],
    "name:nld_x_preferred":[
        "Jalgaon"
    ],
    "name:nor_x_preferred":[
        "Jalgaon"
    ],
    "name:pam_x_preferred":[
        "Jalgaon"
    ],
    "name:pnb_x_preferred":[
        "\u062c\u0644\u06af\u0627\u0624\u0646"
    ],
    "name:pol_x_preferred":[
        "Jalgaon"
    ],
    "name:por_x_preferred":[
        "Jalgaon"
    ],
    "name:pus_x_preferred":[
        "\u062c\u0627\u0644\u06af\u0627\u0648"
    ],
    "name:ron_x_preferred":[
        "Jalgaon"
    ],
    "name:rus_x_preferred":[
        "\u0414\u0436\u0430\u043b\u0433\u0430\u043e\u043d"
    ],
    "name:san_x_preferred":[
        "\u091c\u0933\u0917\u093e\u0935"
    ],
    "name:srp_x_preferred":[
        "\u040f\u0430\u043b\u0433\u0430\u043e\u043d"
    ],
    "name:swe_x_preferred":[
        "Jalgaon"
    ],
    "name:tam_x_preferred":[
        "\u0b9c\u0bb3\u0bcd\u0b95\u0bbe\u0bb5\u0bcd"
    ],
    "name:ukr_x_preferred":[
        "\u0414\u0436\u0430\u043b\u0433\u0430\u043e\u043d"
    ],
    "name:urd_x_preferred":[
        "\u062c\u0644\u06af\u0627\u0624\u06ba"
    ],
    "name:vie_x_preferred":[
        "Jalgaon"
    ],
    "name:war_x_preferred":[
        "Jalgaon"
    ],
    "name:zho_x_preferred":[
        "\u52a0\u723e\u5ca1"
    ],
    "wof:name":"Jalgaon",
    "wof:placetype":"locality"
},
  "geometry": {"coordinates":[76.05133000000002,19.83529],"type":"Point"}
}