{
  "type": "Feature",
  "properties": {
    "iso:country":"IN",
    "ks:ks_name":"Paramananadapur",
    "ks:ks_pop":229,
    "ks:ks_type":"VILLAGE",
    "name:eng_x_preferred":[
        "Paramananadapur"
    ],
    "wof:name":"Paramananadapur",
    "wof:placetype":"locality",
    "wof:population":229
},
  "geometry": {"coordinates":[86.888986,20.610917],"type":"Point"}
}