{
  "type": "Feature",
  "properties": {
    "gn:admin1_code":"39.0",
    "gn:admin2_code":"63.0",
    "gn:asciiname":"Sumti",
    "gn:country_code":"IN",
    "gn:dem":1459,
    "gn:feature_class":"P",
    "gn:feature_code":"PPL",
    "gn:name":"Sumti",
    "gn:population":0,
    "gn:timezone":"Asia/Kolkata",
    "iso:country":"IN",
    "ks:ks_name":"Sumti",
    "ks:ks_pop":511,
    "ks:ks_type":"VILLAGE",
    "name:eng_x_preferred":[
        "Sumti"
    ],
    "wof:name":"Sumti",
    "wof:placetype":"locality",
    "wof:population":511
},
  "geometry": {"coordinates":[79.75909900000001,29.980884],"type":"Point"}
}