{
  "type": "Feature",
  "properties": {
    "iso:country":"IN",
    "ks:ks_name":"Kharkana Toli",
    "ks:ks_pop":779,
    "ks:ks_type":"VILLAGE",
    "name:eng_x_preferred":[
        "Kharkana Toli"
    ],
    "wof:name":"Kharkana Toli",
    "wof:placetype":"locality",
    "wof:population":779
},
  "geometry": {"coordinates":[79.976519,29.936971],"type":"Point"}
}