{
  "type": "Feature",
  "properties": {
    "iso:country":"IN",
    "ks:ks_name":"Dhung",
    "ks:ks_pop":161,
    "ks:ks_type":"VILLAGE",
    "name:eng_x_preferred":[
        "Dhung"
    ],
    "wof:name":"Dhung",
    "wof:placetype":"locality",
    "wof:population":161
},
  "geometry": {"coordinates":[79.122176,30.33683],"type":"Point"}
}