{
  "type": "Feature",
  "properties": {
    "iso:country":"IN",
    "ks:ks_name":"Gilgodi",
    "ks:ks_pop":199,
    "ks:ks_type":"HABITATION",
    "name:eng_x_preferred":[
        "Gilgodi"
    ],
    "wof:name":"Gilgodi",
    "wof:placetype":"locality",
    "wof:population":199
},
  "geometry": {"coordinates":[72.716891,19.652325],"type":"Point"}
}