{
  "type": "Feature",
  "properties": {
    "gn:admin1_code":"36.0",
    "gn:admin2_code":"160",
    "gn:asciiname":"Mehdipur",
    "gn:country_code":"IN",
    "gn:dem":139,
    "gn:feature_class":"P",
    "gn:feature_code":"PPL",
    "gn:name":"Mehd\u012bpur",
    "gn:population":0,
    "gn:timezone":"Asia/Kolkata",
    "iso:country":"IN",
    "ks:ks_alt_nam":"Mehd\u012bpur",
    "ks:ks_name":"Mehdipur",
    "ks:ks_pop":1113,
    "ks:ks_type":"VILLAGE",
    "name:eng_x_preferred":[
        "Mehdipur"
    ],
    "name:eng_x_variant":[
        "Mehd\u012bpur"
    ],
    "wof:name":"Mehdipur",
    "wof:placetype":"locality",
    "wof:population":1113
},
  "geometry": {"coordinates":[79.977549,27.012295],"type":"Point"}
}