{
  "type": "Feature",
  "properties": {
    "iso:country":"IN",
    "ks:ks_name":"Ughati Pattisarki",
    "ks:ks_pop":2775,
    "ks:ks_type":"VILLAGE",
    "ks:ks_uagg_main":0,
    "name:eng_x_preferred":[
        "Ughati Pattisarki"
    ],
    "wof:name":"Ughati Pattisarki",
    "wof:placetype":"neighbourhood",
    "wof:population":2775
},
  "geometry": {"coordinates":[78.809663,28.228598],"type":"Point"}
}