{
  "type": "Feature",
  "properties": {
    "iso:country":"IN",
    "ks:ks_name":"Haripur Thathola",
    "ks:ks_pop":44,
    "ks:ks_type":"VILLAGE",
    "name:eng_x_preferred":[
        "Haripur Thathola"
    ],
    "wof:name":"Haripur Thathola",
    "wof:placetype":"locality",
    "wof:population":44
},
  "geometry": {"coordinates":[79.590733,29.129457],"type":"Point"}
}