{
  "type": "Feature",
  "properties": {
    "iso:country":"IN",
    "ks:ks_name":"Ugavali",
    "ks:ks_pop":0,
    "ks:ks_type":"VILLAGE",
    "name:eng_x_preferred":[
        "Ugavali"
    ],
    "wof:name":"Ugavali",
    "wof:placetype":"locality",
    "wof:population":0
},
  "geometry": {"coordinates":[73.462101,18.38373],"type":"Point"}
}