{
  "type": "Feature",
  "properties": {
    "iso:country":"IN",
    "ks:ks_alt_nam":"3 DNG",
    "ks:ks_name":"3 Dng",
    "ks:ks_pop":49,
    "ks:ks_type":"HABITATION",
    "name:eng_x_preferred":[
        "3 Dng"
    ],
    "wof:name":"3 Dng",
    "wof:placetype":"locality",
    "wof:population":49
},
  "geometry": {"coordinates":[74.471031,29.910354],"type":"Point"}
}