{
  "type": "Feature",
  "properties": {
    "gn:admin1_code":"21",
    "gn:admin2_code":"395.0",
    "gn:asciiname":"Asergam",
    "gn:country_code":"IN",
    "gn:dem":383,
    "gn:feature_class":"P",
    "gn:feature_code":"PPL",
    "gn:name":"Aserg\u0101m",
    "gn:population":0,
    "gn:timezone":"Asia/Kolkata",
    "iso:country":"IN",
    "wof:name":"Asergam",
    "wof:placetype":"locality"
},
  "geometry": {"coordinates":[83.45258000000003,19.75701],"type":"Point"}
}