{
  "type": "Feature",
  "properties": {
    "iso:country":"IN",
    "ks:ks_name":"Shambhoopura",
    "ks:ks_pop":96,
    "ks:ks_type":"HABITATION",
    "name:eng_x_preferred":[
        "Shambhoopura"
    ],
    "wof:name":"Shambhoopura",
    "wof:placetype":"locality",
    "wof:population":96
},
  "geometry": {"coordinates":[75.30300699999999,27.010425],"type":"Point"}
}