{
  "type": "Feature",
  "properties": {
    "gn:admin1_code":"35",
    "gn:admin2_code":"463.0",
    "gn:asciiname":"Rajdaha",
    "gn:country_code":"IN",
    "gn:dem":269,
    "gn:feature_class":"P",
    "gn:feature_code":"PPL",
    "gn:name":"Rajdaha",
    "gn:population":0,
    "gn:timezone":"Asia/Kolkata",
    "iso:country":"IN",
    "wof:name":"Rajdaha",
    "wof:placetype":"locality"
},
  "geometry": {"coordinates":[82.41449,24.47486],"type":"Point"}
}