{
  "type": "Feature",
  "properties": {
    "iso:country":"IN",
    "ks:ks_name":"Mahulaguda",
    "ks:ks_pop":122,
    "ks:ks_type":"HABITATION",
    "name:eng_x_preferred":[
        "Mahulaguda"
    ],
    "wof:name":"Mahulaguda",
    "wof:placetype":"locality",
    "wof:population":122
},
  "geometry": {"coordinates":[82.729669,19.129916],"type":"Point"}
}