{
  "type": "Feature",
  "properties": {
    "iso:country":"IN",
    "ks:ks_alt_nam":"motebag",
    "ks:ks_name":"Motebag",
    "ks:ks_pop":767,
    "ks:ks_type":"HABITATION",
    "name:eng_x_preferred":[
        "Motebag"
    ],
    "wof:name":"Motebag",
    "wof:placetype":"locality",
    "wof:population":767
},
  "geometry": {"coordinates":[74.5947,18.1511],"type":"Point"}
}