{
  "type": "Feature",
  "properties": {
    "iso:country":"IN",
    "ks:ks_alt_nam":"JAGGA KUBRA PARA",
    "ks:ks_name":"Jagga Kubra Para",
    "ks:ks_pop":202,
    "ks:ks_type":"HABITATION",
    "ks:ks_uagg_main":0,
    "name:eng_x_preferred":[
        "Jagga Kubra Para"
    ],
    "wof:name":"Jagga Kubra Para",
    "wof:placetype":"neighbourhood",
    "wof:population":202
},
  "geometry": {"coordinates":[91.70924100000001,23.978063],"type":"Point"}
}