{
  "type": "Feature",
  "properties": {
    "gn:admin1_code":"24.0",
    "gn:admin2_code":"105",
    "gn:asciiname":"Dhurairi",
    "gn:country_code":"IN",
    "gn:dem":210,
    "gn:feature_class":"P",
    "gn:feature_code":"PPL",
    "gn:name":"Dhurair\u012b",
    "gn:population":0,
    "gn:timezone":"Asia/Kolkata",
    "iso:country":"IN",
    "ks:ks_name":"Dhurairi",
    "ks:ks_pop":637,
    "ks:ks_type":"VILLAGE",
    "ks:ks_uagg_main":0,
    "name:eng_x_preferred":[
        "Dhurairi"
    ],
    "wof:name":"Dhurairi",
    "wof:placetype":"neighbourhood",
    "wof:population":637
},
  "geometry": {"coordinates":[77.23981499999999,26.842771],"type":"Point"}
}