{
  "type": "Feature",
  "properties": {
    "iso:country":"IN",
    "ks:ks_name":"Tatri",
    "ks:ks_pop":178,
    "ks:ks_type":"HABITATION",
    "name:eng_x_preferred":[
        "Tatri"
    ],
    "wof:name":"Tatri",
    "wof:placetype":"locality",
    "wof:population":178
},
  "geometry": {"coordinates":[81.580224,19.434539],"type":"Point"}
}