{
  "type": "Feature",
  "properties": {
    "iso:country":"IN",
    "ks:ks_name":"Manchekarwadi",
    "ks:ks_pop":27,
    "ks:ks_type":"HABITATION",
    "name:eng_x_preferred":[
        "Manchekarwadi"
    ],
    "wof:name":"Manchekarwadi",
    "wof:placetype":"locality",
    "wof:population":27
},
  "geometry": {"coordinates":[73.734844,16.590442],"type":"Point"}
}