{
  "type": "Feature",
  "properties": {
    "iso:country":"IN",
    "ks:ks_name":"Ummat",
    "ks:ks_pop":278,
    "ks:ks_type":"HABITATION",
    "name:eng_x_preferred":[
        "Ummat"
    ],
    "wof:name":"Ummat",
    "wof:placetype":"locality",
    "wof:population":278
},
  "geometry": {"coordinates":[92.21741299999999,25.814874],"type":"Point"}
}