{
  "type": "Feature",
  "properties": {
    "iso:country":"IN",
    "ks:ks_name":"Bhalupadar",
    "ks:ks_pop":22,
    "ks:ks_type":"VILLAGE",
    "name:eng_x_preferred":[
        "Bhalupadar"
    ],
    "wof:name":"Bhalupadar",
    "wof:placetype":"locality",
    "wof:population":22
},
  "geometry": {"coordinates":[83.038062,18.80043],"type":"Point"}
}