{
  "type": "Feature",
  "properties": {
    "iso:country":"IN",
    "ks:ks_name":"Boudhawadi",
    "ks:ks_pop":239,
    "ks:ks_type":"HABITATION",
    "name:eng_x_preferred":[
        "Boudhawadi"
    ],
    "wof:name":"Boudhawadi",
    "wof:placetype":"locality",
    "wof:population":239
},
  "geometry": {"coordinates":[73.5475,17.467222],"type":"Point"}
}