{
  "type": "Feature",
  "properties": {
    "gn:admin1_code":"25.0",
    "gn:admin2_code":"621.0",
    "gn:asciiname":"Rajappatti",
    "gn:country_code":"IN",
    "gn:dem":78,
    "gn:feature_class":"P",
    "gn:feature_code":"PPL",
    "gn:name":"R\u0101j\u0101ppatti",
    "gn:population":0,
    "gn:timezone":"Asia/Kolkata",
    "iso:country":"IN",
    "wof:name":"Rajappatti",
    "wof:placetype":"locality"
},
  "geometry": {"coordinates":[79.02951,10.53291],"type":"Point"}
}