{
  "type": "Feature",
  "properties": {
    "iso:country":"IN",
    "ks:ks_name":"Harijan Colony",
    "ks:ks_pop":626,
    "ks:ks_type":"HABITATION",
    "name:eng_x_preferred":[
        "Harijan Colony"
    ],
    "wof:name":"Harijan Colony",
    "wof:placetype":"locality",
    "wof:population":626
},
  "geometry": {"coordinates":[88.03233899999999,26.340754],"type":"Point"}
}