{
  "type": "Feature",
  "properties": {
    "gn:admin1_code":"38.0",
    "gn:admin2_code":"353.0",
    "gn:asciiname":"Siulidanga",
    "gn:country_code":"IN",
    "gn:dem":66,
    "gn:feature_class":"P",
    "gn:feature_code":"PPL",
    "gn:name":"Siulid\u0101nga",
    "gn:population":0,
    "gn:timezone":"Asia/Kolkata",
    "iso:country":"IN",
    "ks:ks_name":"Siwlidanga",
    "ks:ks_pop":183,
    "ks:ks_type":"VILLAGE",
    "name:eng_x_preferred":[
        "Siwlidanga"
    ],
    "name:eng_x_variant":[
        "Siulidanga"
    ],
    "wof:name":"Siwlidanga",
    "wof:placetype":"locality",
    "wof:population":183
},
  "geometry": {"coordinates":[87.756882,24.695988],"type":"Point"}
}