{
  "type": "Feature",
  "properties": {
    "iso:country":"IN",
    "ks:ks_name":"Nagla Sembhal",
    "ks:ks_pop":0,
    "ks:ks_type":"VILLAGE",
    "name:eng_x_preferred":[
        "Nagla Sembhal"
    ],
    "wof:name":"Nagla Sembhal",
    "wof:placetype":"locality",
    "wof:population":0
},
  "geometry": {"coordinates":[78.28266000000001,29.633348],"type":"Point"}
}