{
  "type": "Feature",
  "properties": {
    "iso:country":"IN",
    "ks:ks_name":"Bordooba Toop",
    "ks:ks_pop":2800,
    "ks:ks_type":"VILLAGE",
    "ks:ks_uagg_main":0,
    "name:eng_x_preferred":[
        "Bordooba Toop"
    ],
    "wof:name":"Bordooba Toop",
    "wof:placetype":"neighbourhood",
    "wof:population":2800
},
  "geometry": {"coordinates":[92.227282,26.388317],"type":"Point"}
}