{
  "type": "Feature",
  "properties": {
    "iso:country":"IN",
    "ks:ks_name":"Somdhara",
    "ks:ks_pop":568,
    "ks:ks_type":"HABITATION",
    "name:eng_x_preferred":[
        "Somdhara"
    ],
    "wof:name":"Somdhara",
    "wof:placetype":"locality",
    "wof:population":568
},
  "geometry": {"coordinates":[93.804658,26.947094],"type":"Point"}
}