{
  "type": "Feature",
  "properties": {
    "iso:country":"IN",
    "ks:ks_name":"Malladevanahalli",
    "ks:ks_pop":405,
    "ks:ks_type":"HABITATION",
    "name:eng_x_preferred":[
        "Malladevanahalli"
    ],
    "wof:name":"Malladevanahalli",
    "wof:placetype":"locality",
    "wof:population":405
},
  "geometry": {"coordinates":[76.896587,13.085214],"type":"Point"}
}