{
  "type": "Feature",
  "properties": {
    "iso:country":"IN",
    "ks:ks_alt_nam":"jarpula Thanda",
    "ks:ks_name":"Jarpula Thanda",
    "ks:ks_pop":86,
    "ks:ks_type":"HABITATION",
    "name:eng_x_preferred":[
        "Jarpula Thanda"
    ],
    "wof:name":"Jarpula Thanda",
    "wof:placetype":"locality",
    "wof:population":86
},
  "geometry": {"coordinates":[78.83776,16.730997],"type":"Point"}
}