{
  "type": "Feature",
  "properties": {
    "iso:country":"IN",
    "ks:ks_name":"Devpura",
    "ks:ks_pop":519,
    "ks:ks_type":"HABITATION",
    "name:eng_x_preferred":[
        "Devpura"
    ],
    "wof:name":"Devpura",
    "wof:placetype":"locality",
    "wof:population":519
},
  "geometry": {"coordinates":[71.61283899999999,24.782519],"type":"Point"}
}