{
  "type": "Feature",
  "properties": {
    "iso:country":"IN",
    "ks:ks_name":"Vedulacheruvu",
    "ks:ks_pop":530,
    "ks:ks_type":"HABITATION",
    "name:eng_x_preferred":[
        "Vedulacheruvu"
    ],
    "wof:name":"Vedulacheruvu",
    "wof:placetype":"locality",
    "wof:population":530
},
  "geometry": {"coordinates":[82.15482299999999,16.614863],"type":"Point"}
}