{
  "type": "Feature",
  "properties": {
    "iso:country":"IN",
    "ks:ks_name":"Landibeda",
    "ks:ks_pop":30,
    "ks:ks_type":"HABITATION",
    "name:eng_x_preferred":[
        "Landibeda"
    ],
    "wof:name":"Landibeda",
    "wof:placetype":"locality",
    "wof:population":30
},
  "geometry": {"coordinates":[82.00991399999999,19.979873],"type":"Point"}
}