{
  "type": "Feature",
  "properties": {
    "iso:country":"IN",
    "ks:ks_name":"Saraia Urf Pirapur",
    "ks:ks_pop":501,
    "ks:ks_type":"VILLAGE",
    "name:eng_x_preferred":[
        "Saraia Urf Pirapur"
    ],
    "wof:name":"Saraia Urf Pirapur",
    "wof:placetype":"locality",
    "wof:population":501
},
  "geometry": {"coordinates":[85.529633,25.717036],"type":"Point"}
}