{
  "type": "Feature",
  "properties": {
    "gn:admin1_code":"40.0",
    "gn:admin2_code":"532.0",
    "gn:asciiname":"Kagaznagar",
    "gn:country_code":"IN",
    "gn:dem":176,
    "gn:feature_class":"P",
    "gn:feature_code":"PPLA3",
    "gn:name":"Kagazn\u0101g\u0101r",
    "gn:population":0,
    "gn:timezone":"Asia/Kolkata",
    "iso:country":"IN",
    "name:bpy_x_preferred":[
        "\u0995\u09be\u0997\u099c\u09a8\u0997\u09b0"
    ],
    "name:ceb_x_preferred":[
        "Kagazn\u0101g\u0101r"
    ],
    "name:fas_x_preferred":[
        "\u06a9\u0627\u063a\u0630\u0646\u06af\u0631"
    ],
    "name:hif_x_preferred":[
        "Kagaznagar"
    ],
    "name:ind_x_preferred":[
        "Kaghaznagar"
    ],
    "name:ita_x_preferred":[
        "Kagaznagar"
    ],
    "name:msa_x_preferred":[
        "Kaghaznagar"
    ],
    "name:new_x_preferred":[
        "\u0915\u0918\u091c\u0928\u0917\u0930"
    ],
    "name:ori_x_preferred":[
        "\u0b15\u0b3e\u0b18\u0b1c\u0b4d\u200c\u200c\u0b28\u0b17\u0b30"
    ],
    "name:pam_x_preferred":[
        "Kaghaznagar"
    ],
    "name:por_x_preferred":[
        "Kaghaznagar"
    ],
    "name:spa_x_preferred":[
        "Kaghaznagar"
    ],
    "name:swe_x_preferred":[
        "Kagazn\u0101g\u0101r"
    ],
    "name:tel_x_preferred":[
        "\u0c15\u0c3e\u0c17\u0c1c\u0c4d\u200c\u0c28\u0c17\u0c30\u0c4d\u200c"
    ],
    "name:urd_x_preferred":[
        "\u06a9\u0627\u063a\u0630\u0646\u06af\u0631"
    ],
    "name:vie_x_preferred":[
        "Kaghaznagar"
    ],
    "name:zho_x_preferred":[
        "\u5361\u52a0\u5179\u7eb3\u52a0\u5c14"
    ],
    "wof:name":"Kagaznagar",
    "wof:placetype":"locality"
},
  "geometry": {"coordinates":[79.46605,19.33159],"type":"Point"}
}