{
  "type": "Feature",
  "properties": {
    "gn:admin1_code":"40.0",
    "gn:admin2_code":"532.0",
    "gn:asciiname":"Kagaznagar",
    "gn:country_code":"IN",
    "gn:dem":176,
    "gn:feature_class":"P",
    "gn:feature_code":"PPLA3",
    "gn:name":"Kagazn\u0101g\u0101r",
    "gn:population":0,
    "gn:timezone":"Asia/Kolkata",
    "iso:country":"IN",
    "name:und_x_variant":[
        "Kagazn\u0101g\u0101r"
    ],
    "wof:name":"Kagaznagar",
    "wof:placetype":"locality"
},
  "geometry": {"coordinates":[79.46605,19.33159],"type":"Point"}
}