{
  "type": "Feature",
  "properties": {
    "iso:country":"IN",
    "ks:ks_name":"Karchhuna Talla",
    "ks:ks_pop":104,
    "ks:ks_type":"VILLAGE",
    "name:eng_x_preferred":[
        "Karchhuna Talla"
    ],
    "wof:name":"Karchhuna Talla",
    "wof:placetype":"locality",
    "wof:population":104
},
  "geometry": {"coordinates":[79.184741,30.298097],"type":"Point"}
}