{
  "type": "Feature",
  "properties": {
    "iso:country":"IN",
    "ks:ks_name":"Chhandoli",
    "ks:ks_pop":39,
    "ks:ks_type":"HABITATION",
    "name:eng_x_preferred":[
        "Chhandoli"
    ],
    "wof:name":"Chhandoli",
    "wof:placetype":"locality",
    "wof:population":39
},
  "geometry": {"coordinates":[79.183076,30.29395],"type":"Point"}
}