{
  "type": "Feature",
  "properties": {
    "iso:country":"IN",
    "ks:ks_name":"3 ARW",
    "ks:ks_pop":61,
    "ks:ks_type":"VILLAGE",
    "name:eng_x_preferred":[
        "3 ARW"
    ],
    "wof:name":"3 ARW",
    "wof:placetype":"locality",
    "wof:population":61
},
  "geometry": {"coordinates":[74.249689,29.432856],"type":"Point"}
}