{
  "type": "Feature",
  "properties": {
    "iso:country":"IN",
    "ks:ks_name":"Navtoliya",
    "ks:ks_pop":315,
    "ks:ks_type":"HABITATION",
    "name:eng_x_preferred":[
        "Navtoliya"
    ],
    "wof:name":"Navtoliya",
    "wof:placetype":"locality",
    "wof:population":315
},
  "geometry": {"coordinates":[86.89121299999999,25.235155],"type":"Point"}
}