{
  "type": "Feature",
  "properties": {
    "iso:country":"IN",
    "ks:ks_name":"Kailashpur",
    "ks:ks_pop":1276,
    "ks:ks_type":"VILLAGE",
    "name:eng_x_preferred":[
        "Kailashpur"
    ],
    "wof:name":"Kailashpur",
    "wof:placetype":"locality",
    "wof:population":1276
},
  "geometry": {"coordinates":[95.777106,27.620382],"type":"Point"}
}