{
  "type": "Feature",
  "properties": {
    "gn:admin1_code":"36",
    "gn:admin2_code":"165.0",
    "gn:asciiname":"Barhar",
    "gn:country_code":"IN",
    "gn:dem":133,
    "gn:feature_class":"P",
    "gn:feature_code":"PPL",
    "gn:name":"Barhar",
    "gn:population":0,
    "gn:timezone":"Asia/Kolkata",
    "iso:country":"IN",
    "wof:name":"Barhar",
    "wof:placetype":"locality"
},
  "geometry": {"coordinates":[79.77373,26.0573],"type":"Point"}
}