{
  "type": "Feature",
  "properties": {
    "gn:admin1_code":"19.0",
    "gn:admin2_code":"584.0",
    "gn:asciiname":"Virapura",
    "gn:country_code":"IN",
    "gn:dem":924,
    "gn:feature_class":"P",
    "gn:feature_code":"PPL",
    "gn:name":"Vir\u0101pura",
    "gn:population":0,
    "gn:timezone":"Asia/Kolkata",
    "iso:country":"IN",
    "wof:name":"Virapura",
    "wof:placetype":"locality"
},
  "geometry": {"coordinates":[77.22570999999998,13.11562],"type":"Point"}
}