{
  "type": "Feature",
  "properties": {
    "iso:country":"IN",
    "ks:ks_name":"Chinthagunnela",
    "ks:ks_pop":216,
    "ks:ks_type":"HABITATION",
    "name:eng_x_preferred":[
        "Chinthagunnela"
    ],
    "wof:name":"Chinthagunnela",
    "wof:placetype":"locality",
    "wof:population":216
},
  "geometry": {"coordinates":[82.668717,18.001842],"type":"Point"}
}