{
  "type": "Feature",
  "properties": {
    "gn:admin1_code":"11.0",
    "gn:admin2_code":"24.0",
    "gn:asciiname":"Haler",
    "gn:country_code":"IN",
    "gn:dem":314,
    "gn:feature_class":"P",
    "gn:feature_code":"PPL",
    "gn:name":"Haler",
    "gn:population":0,
    "gn:timezone":"Asia/Kolkata",
    "iso:country":"IN",
    "name:ceb_x_preferred":[
        "Haler"
    ],
    "name:fra_x_preferred":[
        "Haler"
    ],
    "name:lim_x_preferred":[
        "Haalder"
    ],
    "name:nld_x_preferred":[
        "Haler"
    ],
    "wof:name":"Haler",
    "wof:placetype":"locality"
},
  "geometry": {"coordinates":[75.69458,32.17585],"type":"Point"}
}