{
  "type": "Feature",
  "properties": {
    "gn:admin1_code":"21.0",
    "gn:admin2_code":"399.0",
    "gn:asciiname":"Cheruguda",
    "gn:country_code":"IN",
    "gn:dem":185,
    "gn:feature_class":"P",
    "gn:feature_code":"PPL",
    "gn:name":"Cherug\u016bda",
    "gn:population":0,
    "gn:timezone":"Asia/Kolkata",
    "iso:country":"IN",
    "ks:ks_alt_nam":"Cherug\u016bda",
    "ks:ks_name":"Cheruguda",
    "ks:ks_type":"VILLAGE",
    "name:eng_x_preferred":[
        "Cheruguda"
    ],
    "name:eng_x_variant":[
        "Cherug\u016bda"
    ],
    "wof:name":"Cheruguda",
    "wof:placetype":"locality"
},
  "geometry": {"coordinates":[81.61498400000001,18.297339],"type":"Point"}
}