{
  "type": "Feature",
  "properties": {
    "iso:country":"IN",
    "ks:ks_name":"Jora",
    "ks:ks_pop":3968,
    "ks:ks_type":"VILLAGE",
    "ks:ks_uagg_main":0,
    "name:eng_x_preferred":[
        "Jora"
    ],
    "wof:name":"Jora",
    "wof:placetype":"locality",
    "wof:population":3968
},
  "geometry": {"coordinates":[81.711288,21.242309],"type":"Point"}
}