{
  "type": "Feature",
  "properties": {
    "iso:country":"IN",
    "qs:name":"Sanapur",
    "qs:name_adm0":"India",
    "qs:name_adm1":"Karnataka",
    "qs:photos":162,
    "qs:photos_1k":33,
    "qs:photos_9k":1,
    "qs:photos_9r":4,
    "qs:photos_all":162,
    "qs:photos_sr":4,
    "qs:placetype":"Town",
    "qs:pop_sr":"0",
    "wd:wordcount":78,
    "wof:name":"Sanapur",
    "wof:placetype":"locality"
},
  "geometry": {"coordinates":[76.4445015,15.348722],"type":"Point"}
}