{
  "type": "Feature",
  "properties": {
    "iso:country":"IN",
    "name:ara_x_preferred":[
        "\u062c\u0648\u0627\u0647\u0631 \u0646\u0627\u062c\u0627\u0631"
    ],
    "name:ben_bn_x_preferred":[
        "\u099c\u0993\u09b9\u09b0 \u09a8\u0997\u09b0"
    ],
    "name:ben_in_x_preferred":[
        "\u099c\u0993\u09b9\u09b0 \u09a8\u0997\u09b0"
    ],
    "name:eng_x_preferred":[
        "Jawahar Nagar"
    ],
    "name:guj_x_preferred":[
        "\u0a9c\u0ab5\u0abe\u0ab9\u0ab0 \u0aa8\u0a97\u0ab0"
    ],
    "name:hin_x_preferred":[
        "\u091c\u0935\u093e\u0939\u0930 \u0928\u0917\u0930"
    ],
    "name:kan_x_preferred":[
        "\u0c9c\u0cb5\u0cbe\u0cb9\u0cb0\u0ccd \u0ca8\u0c97\u0cb0"
    ],
    "name:mal_x_preferred":[
        "\u0d1c\u0d35\u0d39\u0d7c \u0d28\u0d17\u0d7c"
    ],
    "name:mar_x_preferred":[
        "\u091c\u0935\u093e\u0939\u0930 \u0928\u0917\u0930"
    ],
    "name:pan_x_preferred":[
        "\u0a1c\u0a35\u0a3e\u0a39\u0a30 \u0a28\u0a17\u0a30"
    ],
    "name:tam_x_preferred":[
        "\u0b9c\u0bb5\u0bb9\u0bb0\u0bcd \u0ba8\u0b95\u0bb0\u0bcd"
    ],
    "name:tel_x_preferred":[
        "\u0c1c\u0c35\u0c3e\u0c39\u0c30\u0c4d \u0c28\u0c17\u0c30\u0c4d"
    ],
    "name:urd_x_preferred":[
        "\u062c\u0648\u0627\u06c1\u0631 \u0646\u06af\u0631"
    ],
    "name:urd_x_variant":[
        "\u062c\u0648\u0627\u06c1\u0631 \u0646\u06af\u0627\u0631"
    ],
    "qs:gn_adm0_cc":"IN",
    "qs:gn_local":1253405,
    "qs:gn_nam_loc":"Varanasi, Varanasi, Uttar Pradesh, IN",
    "qs:gn_namadm1":"36",
    "qs:local_max":11649,
    "qs:local_sum":17228,
    "qs:localhoods":15,
    "qs:name":"Jawahar Nagar",
    "qs:name_adm0":"India",
    "qs:name_adm1":"Uttar Pradesh",
    "qs:name_adm2":"Varanasi",
    "qs:name_local":"Varanasi",
    "qs:photo_max":391,
    "qs:photo_sum":1002,
    "qs:placetype":"Suburb",
    "qs:quad_count":14,
    "qs:woe_adm0":23424848,
    "qs:woe_adm1":2345760,
    "qs:woe_adm2":12586794,
    "qs:woe_lau":0,
    "qs:woe_local":2295380,
    "qs:woe_ver":"7.10.0",
    "wd:wordcount":37,
    "wof:lang":[
        "eng"
    ],
    "wof:name":"Jawahar Nagar",
    "wof:placetype":"neighbourhood"
},
  "geometry": {"coordinates":[83.005512,25.296273],"type":"Point"}
}