{
  "type": "Feature",
  "properties": {
    "iso:country":"IN",
    "ks:ks_alt_nam":"kunnumal thazha",
    "ks:ks_name":"Kunnumal Thazha",
    "ks:ks_pop":600,
    "ks:ks_type":"HABITATION",
    "name:eng_x_preferred":[
        "Kunnumal Thazha"
    ],
    "wof:name":"Kunnumal Thazha",
    "wof:placetype":"locality",
    "wof:population":600
},
  "geometry": {"coordinates":[75.739605,11.577531],"type":"Point"}
}