{
  "type": "Feature",
  "properties": {
    "iso:country":"IN",
    "ks:ks_name":"Nattappara",
    "ks:ks_pop":969,
    "ks:ks_type":"HABITATION",
    "name:eng_x_preferred":[
        "Nattappara"
    ],
    "wof:name":"Nattappara",
    "wof:placetype":"locality",
    "wof:population":969
},
  "geometry": {"coordinates":[77.194469,8.496853],"type":"Point"}
}