{
  "type": "Feature",
  "properties": {
    "iso:country":"IN",
    "ks:ks_name":"Nekkere",
    "ks:ks_pop":159,
    "ks:ks_type":"HABITATION",
    "name:eng_x_preferred":[
        "Nekkere"
    ],
    "wof:name":"Nekkere",
    "wof:placetype":"locality",
    "wof:population":159
},
  "geometry": {"coordinates":[75.376701,13.056487],"type":"Point"}
}