{
  "type": "Feature",
  "properties": {
    "iso:country":"IN",
    "ks:ks_name":"Kadagere",
    "ks:ks_pop":117,
    "ks:ks_type":"HABITATION",
    "name:eng_x_preferred":[
        "Kadagere"
    ],
    "wof:name":"Kadagere",
    "wof:placetype":"locality",
    "wof:population":117
},
  "geometry": {"coordinates":[76.438339,11.847999],"type":"Point"}
}