{
  "type": "Feature",
  "properties": {
    "gn:admin1_code":"34.0",
    "gn:admin2_code":"223.0",
    "gn:asciiname":"Chhota Bahorwa",
    "gn:country_code":"IN",
    "gn:dem":42,
    "gn:feature_class":"P",
    "gn:feature_code":"PPL",
    "gn:name":"Chhota Bahorwa",
    "gn:population":0,
    "gn:timezone":"Asia/Kolkata",
    "iso:country":"IN",
    "wof:name":"Chhota Bahorwa",
    "wof:placetype":"locality"
},
  "geometry": {"coordinates":[86.40965,25.69534],"type":"Point"}
}