{
  "type": "Feature",
  "properties": {
    "iso:country":"IN",
    "ks:ks_name":"Belabahali",
    "ks:ks_pop":280,
    "ks:ks_type":"HABITATION",
    "name:eng_x_preferred":[
        "Belabahali"
    ],
    "wof:name":"Belabahali",
    "wof:placetype":"locality",
    "wof:population":280
},
  "geometry": {"coordinates":[85.940871,21.105311],"type":"Point"}
}