{
  "type": "Feature",
  "properties": {
    "gn:admin1_code":"11.0",
    "gn:admin2_code":"24.0",
    "gn:asciiname":"Kharod",
    "gn:country_code":"IN",
    "gn:dem":459,
    "gn:feature_class":"P",
    "gn:feature_code":"PPL",
    "gn:name":"Kharod",
    "gn:population":0,
    "gn:timezone":"Asia/Kolkata",
    "iso:country":"IN",
    "name:ben_x_preferred":[
        "\u0996\u09be\u09b0\u09cb\u09a6"
    ],
    "name:bpy_x_preferred":[
        "\u0996\u09be\u09b0\u09cb\u09a6"
    ],
    "name:ceb_x_preferred":[
        "Kharod"
    ],
    "name:ita_x_preferred":[
        "Kharod"
    ],
    "name:msa_x_preferred":[
        "Kharod"
    ],
    "name:new_x_preferred":[
        "\u0916\u0930\u094b\u0926"
    ],
    "name:nld_x_preferred":[
        "Kharod"
    ],
    "name:por_x_preferred":[
        "Kharod"
    ],
    "name:swe_x_preferred":[
        "Kharod"
    ],
    "name:tgl_x_preferred":[
        "Kharod"
    ],
    "name:urd_x_preferred":[
        "\u06a9\u06be\u0631\u0648\u0691"
    ],
    "name:vie_x_preferred":[
        "Kharod"
    ],
    "name:zho_x_preferred":[
        "\u5361\u7f57\u5fb7"
    ],
    "wof:name":"Kharod",
    "wof:placetype":"locality"
},
  "geometry": {"coordinates":[75.83424000000002,32.32485],"type":"Point"}
}