{
  "type": "Feature",
  "properties": {
    "iso:country":"IN",
    "ks:ks_name":"Banigiri",
    "ks:ks_pop":216,
    "ks:ks_type":"HABITATION",
    "name:eng_x_preferred":[
        "Banigiri"
    ],
    "wof:name":"Banigiri",
    "wof:placetype":"locality",
    "wof:population":216
},
  "geometry": {"coordinates":[86.272876,21.11747],"type":"Point"}
}