{
  "type": "Feature",
  "properties": {
    "iso:country":"IN",
    "ks:ks_name":"Thekkanamnirappu",
    "ks:ks_pop":563,
    "ks:ks_type":"HABITATION",
    "name:eng_x_preferred":[
        "Thekkanamnirappu"
    ],
    "wof:name":"Thekkanamnirappu",
    "wof:placetype":"locality",
    "wof:population":563
},
  "geometry": {"coordinates":[76.653068,9.859538],"type":"Point"}
}