{
  "type": "Feature",
  "properties": {
    "gn:admin1_code":"36",
    "gn:admin2_code":"179.0",
    "gn:asciiname":"Saraiya Ambar Singh",
    "gn:country_code":"IN",
    "gn:dem":103,
    "gn:feature_class":"P",
    "gn:feature_code":"PPL",
    "gn:name":"Saraiya Ambar Singh",
    "gn:population":0,
    "gn:timezone":"Asia/Kolkata",
    "iso:country":"IN",
    "ks:ks_name":"Saraiya Ambar Singh",
    "ks:ks_type":"VILLAGE",
    "ks:ks_uagg_main":0,
    "name:eng_x_preferred":[
        "Saraiya Ambar Singh"
    ],
    "wof:name":"Saraiya Ambar Singh",
    "wof:placetype":"neighbourhood"
},
  "geometry": {"coordinates":[82.152835,26.177925],"type":"Point"}
}