{
  "type": "Feature",
  "properties": {
    "iso:country":"IN",
    "ks:ks_alt_nam":"MURUMBURA",
    "ks:ks_name":"Murumbura",
    "ks:ks_pop":842,
    "ks:ks_type":"HABITATION",
    "name:eng_x_preferred":[
        "Murumbura"
    ],
    "wof:name":"Murumbura",
    "wof:placetype":"locality",
    "wof:population":842
},
  "geometry": {"coordinates":[85.531734,22.37053],"type":"Point"}
}