{
  "type": "Feature",
  "properties": {
    "iso:country":"IN",
    "ks:ks_name":"Nedgaon",
    "ks:ks_pop":103,
    "ks:ks_type":"VILLAGE",
    "name:eng_x_preferred":[
        "Nedgaon"
    ],
    "wof:name":"Nedgaon",
    "wof:placetype":"locality",
    "wof:population":103
},
  "geometry": {"coordinates":[80.730783,20.065061],"type":"Point"}
}