{
  "type": "Feature",
  "properties": {
    "iso:country":"IN",
    "ks:ks_alt_nam":"CHIGARE VASAHAT",
    "ks:ks_name":"Chigare Vasahat",
    "ks:ks_pop":463,
    "ks:ks_type":"HABITATION",
    "ks:ks_uagg_main":0,
    "name:eng_x_preferred":[
        "Chigare Vasahat"
    ],
    "wof:name":"Chigare Vasahat",
    "wof:placetype":"neighbourhood",
    "wof:population":463
},
  "geometry": {"coordinates":[74.588831,16.617719],"type":"Point"}
}