{
  "type": "Feature",
  "properties": {
    "iso:country":"IN",
    "ks:ks_name":"Rajput Tola",
    "ks:ks_pop":192,
    "ks:ks_type":"HABITATION",
    "name:eng_x_preferred":[
        "Rajput Tola"
    ],
    "wof:name":"Rajput Tola",
    "wof:placetype":"locality",
    "wof:population":192
},
  "geometry": {"coordinates":[83.456664,24.23729],"type":"Point"}
}