{
  "type": "Feature",
  "properties": {
    "gn:admin1_code":"39.0",
    "gn:admin2_code":"59.0",
    "gn:asciiname":"Saur",
    "gn:country_code":"IN",
    "gn:dem":1412,
    "gn:feature_class":"P",
    "gn:feature_code":"PPL",
    "gn:name":"Saur",
    "gn:population":0,
    "gn:timezone":"Asia/Kolkata",
    "iso:country":"IN",
    "name:deu_x_preferred":[
        "Saur"
    ],
    "wof:name":"Saur",
    "wof:placetype":"locality"
},
  "geometry": {"coordinates":[78.2306,30.4878],"type":"Point"}
}