{
  "type": "Feature",
  "properties": {
    "iso:country":"IN",
    "ks:ks_name":"Ranjeet Nagar",
    "ks:ks_pop":182,
    "ks:ks_type":"HABITATION",
    "name:eng_x_preferred":[
        "Ranjeet Nagar"
    ],
    "wof:name":"Ranjeet Nagar",
    "wof:placetype":"locality",
    "wof:population":182
},
  "geometry": {"coordinates":[72.428269,27.512331],"type":"Point"}
}