{
  "type": "Feature",
  "properties": {
    "gn:admin1_code":"39.0",
    "gn:admin2_code":"57.0",
    "gn:asciiname":"Authgaon",
    "gn:country_code":"IN",
    "gn:dem":2571,
    "gn:feature_class":"P",
    "gn:feature_code":"PPL",
    "gn:name":"Authgaon",
    "gn:population":0,
    "gn:timezone":"Asia/Kolkata",
    "iso:country":"IN",
    "wof:name":"Authgaon",
    "wof:placetype":"locality"
},
  "geometry": {"coordinates":[79.51603,30.69432],"type":"Point"}
}