{
  "type": "Feature",
  "properties": {
    "iso:country":"IN",
    "ks:ks_name":"Podakeri",
    "ks:ks_pop":47,
    "ks:ks_type":"HABITATION",
    "name:eng_x_preferred":[
        "Podakeri"
    ],
    "wof:name":"Podakeri",
    "wof:placetype":"locality",
    "wof:population":47
},
  "geometry": {"coordinates":[75.8425,12.126389],"type":"Point"}
}