{
  "type": "Feature",
  "properties": {
    "gn:admin1_code":"23.0",
    "gn:admin2_code":"37.0",
    "gn:asciiname":"Patra Kalan",
    "gn:country_code":"IN",
    "gn:dem":230,
    "gn:feature_class":"P",
    "gn:feature_code":"PPL",
    "gn:name":"Patra Kal\u0101n",
    "gn:population":0,
    "gn:timezone":"Asia/Kolkata",
    "iso:country":"IN",
    "wof:name":"Patra Kalan",
    "wof:placetype":"locality"
},
  "geometry": {"coordinates":[75.45692,31.39727],"type":"Point"}
}