{
  "type": "Feature",
  "properties": {
    "gn:admin1_code":"2.0",
    "gn:admin2_code":"553.0",
    "gn:asciiname":"Peddireddipalle",
    "gn:country_code":"IN",
    "gn:dem":625,
    "gn:feature_class":"P",
    "gn:feature_code":"PPL",
    "gn:name":"Peddireddipalle",
    "gn:population":0,
    "gn:timezone":"Asia/Kolkata",
    "iso:country":"IN",
    "wof:name":"Peddireddipalle",
    "wof:placetype":"locality"
},
  "geometry": {"coordinates":[77.47103,13.84095],"type":"Point"}
}