{
  "type": "Feature",
  "properties": {
    "iso:country":"IN",
    "ks:ks_alt_nam":"Bari faliya",
    "ks:ks_name":"Bari Faliya",
    "ks:ks_pop":389,
    "ks:ks_type":"HABITATION",
    "name:eng_x_preferred":[
        "Bari Faliya"
    ],
    "wof:name":"Bari Faliya",
    "wof:placetype":"locality",
    "wof:population":389
},
  "geometry": {"coordinates":[73.24461100000001,20.489861],"type":"Point"}
}