{
  "type": "Feature",
  "properties": {
    "iso:country":"IN",
    "ks:ks_alt_nam":"Yadav tola",
    "ks:ks_name":"Yadav Tola",
    "ks:ks_pop":107,
    "ks:ks_type":"HABITATION",
    "name:eng_x_preferred":[
        "Yadav Tola"
    ],
    "wof:name":"Yadav Tola",
    "wof:placetype":"locality",
    "wof:population":107
},
  "geometry": {"coordinates":[86.474062,25.990057],"type":"Point"}
}