{
  "type": "Feature",
  "properties": {
    "iso:country":"IN",
    "ks:ks_name":"Thenpathi",
    "ks:ks_pop":730,
    "ks:ks_type":"HABITATION",
    "name:eng_x_preferred":[
        "Thenpathi"
    ],
    "wof:name":"Thenpathi",
    "wof:placetype":"locality",
    "wof:population":730
},
  "geometry": {"coordinates":[79.731121,10.565298],"type":"Point"}
}