{
  "type": "Feature",
  "properties": {
    "iso:country":"IN",
    "ks:ks_name":"Pooja Khulari",
    "ks:ks_pop":875,
    "ks:ks_type":"HABITATION",
    "name:eng_x_preferred":[
        "Pooja Khulari"
    ],
    "wof:name":"Pooja Khulari",
    "wof:placetype":"locality",
    "wof:population":875
},
  "geometry": {"coordinates":[74.082381,23.378339],"type":"Point"}
}