{
  "type": "Feature",
  "properties": {
    "iso:country":"IN",
    "ks:ks_name":"Singodiya",
    "ks:ks_pop":212,
    "ks:ks_type":"HABITATION",
    "name:eng_x_preferred":[
        "Singodiya"
    ],
    "wof:name":"Singodiya",
    "wof:placetype":"locality",
    "wof:population":212
},
  "geometry": {"coordinates":[74.819812,22.618584],"type":"Point"}
}