{
  "type": "Feature",
  "properties": {
    "gn:admin1_code":"24.0",
    "gn:admin2_code":"126.0",
    "gn:asciiname":"Rajgarh",
    "gn:country_code":"IN",
    "gn:dem":397,
    "gn:feature_class":"P",
    "gn:feature_code":"PPL",
    "gn:name":"R\u0101jgarh",
    "gn:population":0,
    "gn:timezone":"Asia/Kolkata",
    "iso:country":"IN",
    "name:und_x_variant":[
        "R\u0101jgarh",
        "Sing\u0101ri"
    ],
    "wof:name":"Rajgarh",
    "wof:placetype":"locality"
},
  "geometry": {"coordinates":[74.84950000000001,25.08814],"type":"Point"}
}