{
  "type": "Feature",
  "properties": {
    "gn:admin1_code":"38",
    "gn:admin2_code":"346.0",
    "gn:asciiname":"Phulwar",
    "gn:country_code":"IN",
    "gn:dem":319,
    "gn:feature_class":"P",
    "gn:feature_code":"PPL",
    "gn:name":"Phulw\u0101r",
    "gn:population":0,
    "gn:timezone":"Asia/Kolkata",
    "iso:country":"IN",
    "name:und_x_variant":[
        "Phulw\u0101r",
        "Low\u0101donar"
    ],
    "wof:name":"Phulwar",
    "wof:placetype":"locality"
},
  "geometry": {"coordinates":[83.56254,24.09454],"type":"Point"}
}