{
  "type": "Feature",
  "properties": {
    "iso:country":"IN",
    "ks:ks_name":"Ranmochan",
    "ks:ks_pop":0,
    "ks:ks_type":"VILLAGE",
    "name:eng_x_preferred":[
        "Ranmochan"
    ],
    "wof:name":"Ranmochan",
    "wof:placetype":"locality",
    "wof:population":0
},
  "geometry": {"coordinates":[78.210948,21.735769],"type":"Point"}
}