{
  "type": "Feature",
  "properties": {
    "gn:admin1_code":"19.0",
    "gn:admin2_code":"574.0",
    "gn:asciiname":"Bendekere",
    "gn:country_code":"IN",
    "gn:dem":798,
    "gn:feature_class":"P",
    "gn:feature_code":"PPL",
    "gn:name":"Bendekere",
    "gn:population":0,
    "gn:timezone":"Asia/Kolkata",
    "iso:country":"IN",
    "name:vie_x_preferred":[
        "Bendekere"
    ],
    "wof:name":"Bendekere",
    "wof:placetype":"locality"
},
  "geometry": {"coordinates":[76.2129,13.36172],"type":"Point"}
}