{
  "type": "Feature",
  "properties": {
    "iso:country":"IN",
    "ks:ks_alt_nam":"Bhoere wasti 2",
    "ks:ks_name":"Bhoere Wasti 2",
    "ks:ks_pop":286,
    "ks:ks_type":"HABITATION",
    "name:eng_x_preferred":[
        "Bhoere Wasti 2"
    ],
    "wof:name":"Bhoere Wasti 2",
    "wof:placetype":"locality",
    "wof:population":286
},
  "geometry": {"coordinates":[75.43584300000001,18.738853],"type":"Point"}
}