{
  "type": "Feature",
  "properties": {
    "iso:country":"IN",
    "ks:ks_name":"Mettuperumalkoil",
    "ks:ks_pop":300,
    "ks:ks_type":"HABITATION",
    "name:eng_x_preferred":[
        "Mettuperumalkoil"
    ],
    "wof:name":"Mettuperumalkoil",
    "wof:placetype":"locality",
    "wof:population":300
},
  "geometry": {"coordinates":[77.856031,11.45043],"type":"Point"}
}