{
  "type": "Feature",
  "properties": {
    "gn:admin1_code":"23.0",
    "gn:admin2_code":"48.0",
    "gn:asciiname":"Rajgarh",
    "gn:country_code":"IN",
    "gn:dem":241,
    "gn:feature_class":"P",
    "gn:feature_code":"PPL",
    "gn:name":"R\u0101jgarh",
    "gn:population":0,
    "gn:timezone":"Asia/Kolkata",
    "iso:country":"IN",
    "name:und_x_variant":[
        "R\u0101jgarh",
        "Sonda M\u0101jro"
    ],
    "wof:name":"Rajgarh",
    "wof:placetype":"locality"
},
  "geometry": {"coordinates":[76.21486999999998,30.08629],"type":"Point"}
}