{
  "type": "Feature",
  "properties": {
    "iso:country":"IN",
    "ks:ks_name":"Bhatwadi",
    "ks:ks_pop":139,
    "ks:ks_type":"HABITATION",
    "name:eng_x_preferred":[
        "Bhatwadi"
    ],
    "wof:name":"Bhatwadi",
    "wof:placetype":"locality",
    "wof:population":139
},
  "geometry": {"coordinates":[73.866224,16.186104],"type":"Point"}
}