{
  "type": "Feature",
  "properties": {
    "iso:country":"IN",
    "ks:ks_alt_nam":"Hes\u0101lo",
    "ks:ks_name":"Hesalo",
    "ks:ks_pop":184,
    "ks:ks_type":"VILLAGE",
    "name:eng_x_preferred":[
        "Hesalo"
    ],
    "name:eng_x_variant":[
        "Hes\u0101lo"
    ],
    "wof:name":"Hesalo",
    "wof:placetype":"locality",
    "wof:population":184
},
  "geometry": {"coordinates":[86.188727,24.062968],"type":"Point"}
}