{
  "type": "Feature",
  "properties": {
    "gn:admin1_code":"28.0",
    "gn:admin2_code":"335",
    "gn:asciiname":"Baidyapur",
    "gn:country_code":"IN",
    "gn:dem":17,
    "gn:feature_class":"P",
    "gn:feature_code":"PPL",
    "gn:name":"Baidyapur",
    "gn:population":0,
    "gn:timezone":"Asia/Kolkata",
    "iso:country":"IN",
    "wof:name":"Baidyapur",
    "wof:placetype":"locality"
},
  "geometry": {"coordinates":[88.25140999999998,23.1669],"type":"Point"}
}