{
  "type": "Feature",
  "properties": {
    "gn:admin1_code":"02",
    "gn:admin2_code":"554.0",
    "gn:asciiname":"Ramasamudram",
    "gn:country_code":"IN",
    "gn:dem":804,
    "gn:feature_class":"P",
    "gn:feature_code":"PPL",
    "gn:name":"R\u0101masamudram",
    "gn:population":0,
    "gn:timezone":"Asia/Kolkata",
    "iso:country":"IN",
    "name:und_x_variant":[
        "R\u0101masamudram"
    ],
    "wof:name":"Ramasamudram",
    "wof:placetype":"locality"
},
  "geometry": {"coordinates":[78.42438,13.36664],"type":"Point"}
}