{
  "type": "Feature",
  "properties": {
    "iso:country":"IN",
    "ks:ks_name":"Dhakkan Deeh",
    "ks:ks_pop":232,
    "ks:ks_type":"HABITATION",
    "name:eng_x_preferred":[
        "Dhakkan Deeh"
    ],
    "wof:name":"Dhakkan Deeh",
    "wof:placetype":"locality",
    "wof:population":232
},
  "geometry": {"coordinates":[82.47605799999999,27.258403],"type":"Point"}
}