{
  "type": "Feature",
  "properties": {
    "iso:country":"IN",
    "ks:ks_name":"Godlitanr",
    "ks:ks_pop":503,
    "ks:ks_type":"HABITATION",
    "name:eng_x_preferred":[
        "Godlitanr"
    ],
    "wof:name":"Godlitanr",
    "wof:placetype":"locality",
    "wof:population":503
},
  "geometry": {"coordinates":[86.145116,24.018329],"type":"Point"}
}