{
  "type": "Feature",
  "properties": {
    "gn:admin1_code":"25.0",
    "gn:admin2_code":"605.0",
    "gn:asciiname":"Kottanur",
    "gn:country_code":"IN",
    "gn:dem":868,
    "gn:feature_class":"P",
    "gn:feature_code":"PPL",
    "gn:name":"Kott\u0101n\u016br",
    "gn:population":0,
    "gn:timezone":"Asia/Kolkata",
    "iso:country":"IN",
    "ks:ks_name":"Kothanur",
    "ks:ks_pop":420,
    "ks:ks_type":"HABITATION",
    "name:eng_x_preferred":[
        "Kothanur"
    ],
    "name:eng_x_variant":[
        "Kottanur"
    ],
    "wof:name":"Kothanur",
    "wof:placetype":"locality",
    "wof:population":420
},
  "geometry": {"coordinates":[78.702398,12.428569],"type":"Point"}
}