{
  "type": "Feature",
  "properties": {
    "iso:country":"IN",
    "ks:ks_name":"Kangapada",
    "ks:ks_pop":141,
    "ks:ks_type":"VILLAGE",
    "name:eng_x_preferred":[
        "Kangapada"
    ],
    "wof:name":"Kangapada",
    "wof:placetype":"locality",
    "wof:population":141
},
  "geometry": {"coordinates":[83.954297,20.455081],"type":"Point"}
}