{
  "type": "Feature",
  "properties": {
    "gn:admin1_code":"37.0",
    "gn:admin2_code":"416.0",
    "gn:asciiname":"Taneli",
    "gn:country_code":"IN",
    "gn:dem":591,
    "gn:feature_class":"P",
    "gn:feature_code":"PPL",
    "gn:name":"Taneli",
    "gn:population":0,
    "gn:timezone":"Asia/Kolkata",
    "iso:country":"IN",
    "ks:ks_name":"Taneli",
    "ks:ks_pop":238,
    "ks:ks_type":"VILLAGE",
    "name:eng_x_preferred":[
        "Taneli"
    ],
    "name:fin_x_preferred":[
        "Taneli"
    ],
    "wof:name":"Taneli",
    "wof:placetype":"locality",
    "wof:population":238
},
  "geometry": {"coordinates":[81.283884,18.533974],"type":"Point"}
}