{
  "type": "Feature",
  "properties": {
    "gn:admin1_code":"34.0",
    "gn:admin2_code":"216.0",
    "gn:asciiname":"Bhalui Rasul",
    "gn:country_code":"IN",
    "gn:dem":61,
    "gn:feature_class":"P",
    "gn:feature_code":"PPL",
    "gn:name":"Bhalui Ras\u016bl",
    "gn:population":0,
    "gn:timezone":"Asia/Kolkata",
    "iso:country":"IN",
    "ks:ks_alt_nam":"Bhalui Ras\u016bl",
    "ks:ks_name":"Bhalui Rasul",
    "ks:ks_pop":1048,
    "ks:ks_type":"VILLAGE",
    "ks:ks_uagg_main":0,
    "name:eng_x_preferred":[
        "Bhalui Rasul"
    ],
    "name:eng_x_variant":[
        "Bhalui Ras\u016bl"
    ],
    "wof:name":"Bhalui Rasul",
    "wof:placetype":"neighbourhood",
    "wof:population":1048
},
  "geometry": {"coordinates":[84.95540800000001,26.262535],"type":"Point"}
}