{
  "type": "Feature",
  "properties": {
    "gn:admin1_code":"35.0",
    "gn:admin2_code":"454.0",
    "gn:asciiname":"Bahar",
    "gn:country_code":"IN",
    "gn:dem":652,
    "gn:feature_class":"P",
    "gn:feature_code":"PPL",
    "gn:name":"Bah\u0101r",
    "gn:population":0,
    "gn:timezone":"Asia/Kolkata",
    "iso:country":"IN",
    "name:aze_x_preferred":[
        "Bahar"
    ],
    "name:bel_x_preferred":[
        "\u0411\u0430\u0445\u0430\u0440"
    ],
    "name:cat_x_preferred":[
        "Bahar"
    ],
    "name:ceb_x_preferred":[
        "Bahar"
    ],
    "name:deu_x_preferred":[
        "Bahar"
    ],
    "name:fas_x_preferred":[
        "\u0628\u0647\u0627\u0631"
    ],
    "name:fra_x_preferred":[
        "Bahar"
    ],
    "name:kat_x_preferred":[
        "\u10d1\u10d0\u10f0\u10d0\u10e0\u10d8"
    ],
    "name:pnb_x_preferred":[
        "\u0628\u06c1\u0627\u0631"
    ],
    "name:rus_x_preferred":[
        "\u0411\u0430\u0445\u0430\u0440"
    ],
    "name:swe_x_preferred":[
        "Bahar"
    ],
    "name:tur_x_preferred":[
        "Bahar"
    ],
    "wof:name":"Bahar",
    "wof:placetype":"locality"
},
  "geometry": {"coordinates":[80.41311999999998,23.01827],"type":"Point"}
}