{
  "type": "Feature",
  "properties": {
    "gn:admin1_code":"35.0",
    "gn:admin2_code":"454.0",
    "gn:asciiname":"Bahar",
    "gn:country_code":"IN",
    "gn:dem":652,
    "gn:feature_class":"P",
    "gn:feature_code":"PPL",
    "gn:name":"Bah\u0101r",
    "gn:population":0,
    "gn:timezone":"Asia/Kolkata",
    "iso:country":"IN",
    "wof:name":"Bahar",
    "wof:placetype":"locality"
},
  "geometry": {"coordinates":[80.41311999999998,23.01827],"type":"Point"}
}