{
  "type": "Feature",
  "properties": {
    "iso:country":"IN",
    "ks:ks_alt_nam":"SOUTH TOLA",
    "ks:ks_name":"South Tola",
    "ks:ks_pop":1312,
    "ks:ks_type":"HABITATION",
    "ks:ks_uagg_main":0,
    "name:eng_x_preferred":[
        "South Tola"
    ],
    "wof:name":"South Tola",
    "wof:placetype":"neighbourhood",
    "wof:population":1312
},
  "geometry": {"coordinates":[86.14704,25.18354],"type":"Point"}
}