{
  "type": "Feature",
  "properties": {
    "iso:country":"IN",
    "ks:ks_name":"Udyagiri",
    "ks:ks_pop":16,
    "ks:ks_type":"VILLAGE",
    "name:eng_x_preferred":[
        "Udyagiri"
    ],
    "wof:name":"Udyagiri",
    "wof:placetype":"locality",
    "wof:population":16
},
  "geometry": {"coordinates":[84.094077,20.420692],"type":"Point"}
}