{
  "type": "Feature",
  "properties": {
    "iso:country":"IN",
    "ks:ks_name":"Paruthiyoor",
    "ks:ks_pop":181,
    "ks:ks_type":"HABITATION",
    "name:eng_x_preferred":[
        "Paruthiyoor"
    ],
    "wof:name":"Paruthiyoor",
    "wof:placetype":"locality",
    "wof:population":181
},
  "geometry": {"coordinates":[78.859021,9.784086],"type":"Point"}
}