{
  "type": "Feature",
  "properties": {
    "iso:country":"IN",
    "ks:ks_name":"Kokera",
    "ks:ks_pop":28,
    "ks:ks_type":"HABITATION",
    "name:eng_x_preferred":[
        "Kokera"
    ],
    "wof:name":"Kokera",
    "wof:placetype":"locality",
    "wof:population":28
},
  "geometry": {"coordinates":[80.470083,19.172257],"type":"Point"}
}