{
  "type": "Feature",
  "properties": {
    "iso:country":"IN",
    "ks:ks_name":"Sanju Tilla",
    "ks:ks_pop":290,
    "ks:ks_type":"HABITATION",
    "ks:ks_uagg_main":0,
    "name:eng_x_preferred":[
        "Sanju Tilla"
    ],
    "wof:name":"Sanju Tilla",
    "wof:placetype":"neighbourhood",
    "wof:population":290
},
  "geometry": {"coordinates":[91.949872,24.328761],"type":"Point"}
}