{
  "type": "Feature",
  "properties": {
    "gn:admin1_code":"35.0",
    "gn:admin2_code":"457.0",
    "gn:asciiname":"Mendhra",
    "gn:country_code":"IN",
    "gn:dem":339,
    "gn:feature_class":"P",
    "gn:feature_code":"PPL",
    "gn:name":"Mendhra",
    "gn:population":0,
    "gn:timezone":"Asia/Kolkata",
    "iso:country":"IN",
    "ks:ks_name":"Menthra",
    "ks:ks_pop":134,
    "ks:ks_type":"VILLAGE",
    "name:eng_x_preferred":[
        "Menthra"
    ],
    "name:eng_x_variant":[
        "Mendhra"
    ],
    "wof:name":"Menthra",
    "wof:placetype":"locality",
    "wof:population":134
},
  "geometry": {"coordinates":[80.517061,21.612428],"type":"Point"}
}