{
  "type": "Feature",
  "properties": {
    "iso:country":"IN",
    "ks:ks_alt_nam":"\u0100dh\u012b T\u012blw\u0101",
    "ks:ks_name":"Adhi Tilwa",
    "ks:ks_type":"VILLAGE",
    "name:eng_x_preferred":[
        "Adhi Tilwa"
    ],
    "name:eng_x_variant":[
        "\u0100dh\u012b T\u012blw\u0101"
    ],
    "wof:name":"Adhi Tilwa",
    "wof:placetype":"locality"
},
  "geometry": {"coordinates":[83.72450600000001,25.573451],"type":"Point"}
}