{
  "type": "Feature",
  "properties": {
    "gn:admin1_code":"35.0",
    "gn:admin2_code":"420.0",
    "gn:asciiname":"Lehchura",
    "gn:country_code":"IN",
    "gn:dem":168,
    "gn:feature_class":"P",
    "gn:feature_code":"PPL",
    "gn:name":"Lehch\u016bra",
    "gn:population":0,
    "gn:timezone":"Asia/Kolkata",
    "iso:country":"IN",
    "wof:name":"Lehchura",
    "wof:placetype":"locality"
},
  "geometry": {"coordinates":[78.32388,26.36372],"type":"Point"}
}