{
  "type": "Feature",
  "properties": {
    "gn:admin1_code":"19.0",
    "gn:admin2_code":"576.0",
    "gn:asciiname":"Kelakodli",
    "gn:country_code":"IN",
    "gn:dem":933,
    "gn:feature_class":"P",
    "gn:feature_code":"PPL",
    "gn:name":"Kelakodli",
    "gn:population":0,
    "gn:timezone":"Asia/Kolkata",
    "iso:country":"IN",
    "wof:name":"Kelakodli",
    "wof:placetype":"locality"
},
  "geometry": {"coordinates":[75.88713,12.82035],"type":"Point"}
}