{
  "type": "Feature",
  "properties": {
    "iso:country":"IN",
    "ks:ks_name":"Beltali Para",
    "ks:ks_pop":220,
    "ks:ks_type":"HABITATION",
    "name:eng_x_preferred":[
        "Beltali Para"
    ],
    "wof:name":"Beltali Para",
    "wof:placetype":"locality",
    "wof:population":220
},
  "geometry": {"coordinates":[91.823257,23.09502],"type":"Point"}
}