{
  "type": "Feature",
  "properties": {
    "iso:country":"IN",
    "ks:ks_name":"Wanneri",
    "ks:ks_pop":0,
    "ks:ks_type":"VILLAGE",
    "name:eng_x_preferred":[
        "Wanneri"
    ],
    "wof:name":"Wanneri",
    "wof:placetype":"locality",
    "wof:population":0
},
  "geometry": {"coordinates":[78.856336,20.317775],"type":"Point"}
}