{
  "type": "Feature",
  "properties": {
    "iso:country":"IN",
    "ks:ks_name":"Gadil May Gahar",
    "ks:ks_pop":174,
    "ks:ks_type":"VILLAGE",
    "name:eng_x_preferred":[
        "Gadil May Gahar"
    ],
    "wof:name":"Gadil May Gahar",
    "wof:placetype":"locality",
    "wof:population":174
},
  "geometry": {"coordinates":[78.539502,30.210342],"type":"Point"}
}