{
  "type": "Feature",
  "properties": {
    "iso:country":"IN",
    "ks:ks_name":"Angaragudde",
    "ks:ks_pop":531,
    "ks:ks_type":"HABITATION",
    "name:eng_x_preferred":[
        "Angaragudde"
    ],
    "wof:name":"Angaragudde",
    "wof:placetype":"locality",
    "wof:population":531
},
  "geometry": {"coordinates":[74.814052,13.077567],"type":"Point"}
}