{
  "type": "Feature",
  "properties": {
    "iso:country":"IN",
    "ks:ks_name":"Dulari",
    "ks:ks_pop":350,
    "ks:ks_type":"HABITATION",
    "name:eng_x_preferred":[
        "Dulari"
    ],
    "wof:name":"Dulari",
    "wof:placetype":"locality",
    "wof:population":350
},
  "geometry": {"coordinates":[84.20773800000001,26.937057],"type":"Point"}
}