{
  "type": "Feature",
  "properties": {
    "iso:country":"IN",
    "ks:ks_name":"Dubauli Mahesh",
    "ks:ks_pop":1248,
    "ks:ks_type":"VILLAGE",
    "name:eng_x_preferred":[
        "Dubauli Mahesh"
    ],
    "wof:name":"Dubauli Mahesh",
    "wof:placetype":"locality",
    "wof:population":1248
},
  "geometry": {"coordinates":[84.16722300000001,25.631389],"type":"Point"}
}