{
  "type": "Feature",
  "properties": {
    "iso:country":"IN",
    "ks:ks_name":"Dolyapur",
    "ks:ks_pop":170,
    "ks:ks_type":"HABITATION",
    "name:eng_x_preferred":[
        "Dolyapur"
    ],
    "wof:name":"Dolyapur",
    "wof:placetype":"locality",
    "wof:population":170
},
  "geometry": {"coordinates":[76.074414,27.480295],"type":"Point"}
}