{
  "type": "Feature",
  "properties": {
    "iso:country":"IN",
    "ks:ks_name":"Sangolkarwasti",
    "ks:ks_pop":80,
    "ks:ks_type":"HABITATION",
    "name:eng_x_preferred":[
        "Sangolkarwasti"
    ],
    "wof:name":"Sangolkarwasti",
    "wof:placetype":"locality",
    "wof:population":80
},
  "geometry": {"coordinates":[75.59599900000001,17.401112],"type":"Point"}
}