{
  "type": "Feature",
  "properties": {
    "gn:admin1_code":"34.0",
    "gn:admin2_code":"222.0",
    "gn:asciiname":"Bind",
    "gn:country_code":"IN",
    "gn:dem":48,
    "gn:feature_class":"P",
    "gn:feature_code":"PPL",
    "gn:name":"Bind",
    "gn:population":0,
    "gn:timezone":"Asia/Kolkata",
    "iso:country":"IN",
    "name:deu_x_preferred":[
        "Bind"
    ],
    "name:kor_x_preferred":[
        "\ubc14\uc778\ub4dc"
    ],
    "name:rus_x_preferred":[
        "Bind"
    ],
    "wof:name":"Bind",
    "wof:placetype":"neighbourhood"
},
  "geometry": {"coordinates":[86.07095,25.39548],"type":"Point"}
}