{
  "type": "Feature",
  "properties": {
    "gn:admin1_code":"12.0",
    "gn:admin2_code":"008",
    "gn:asciiname":"Gund-i-Mulraj",
    "gn:country_code":"IN",
    "gn:dem":1589,
    "gn:feature_class":"P",
    "gn:feature_code":"PPL",
    "gn:name":"Gund-i-Mulr\u0101j",
    "gn:population":0,
    "gn:timezone":"Asia/Kolkata",
    "iso:country":"IN",
    "wof:name":"Gund-i-Mulraj",
    "wof:placetype":"locality"
},
  "geometry": {"coordinates":[74.39544000000002,34.31343],"type":"Point"}
}