{
  "type": "Feature",
  "properties": {
    "gn:admin1_code":"16.0",
    "gn:admin2_code":"503.0",
    "gn:asciiname":"Jalka",
    "gn:country_code":"IN",
    "gn:dem":322,
    "gn:feature_class":"P",
    "gn:feature_code":"PPL",
    "gn:name":"Jalka",
    "gn:population":0,
    "gn:timezone":"Asia/Kolkata",
    "iso:country":"IN",
    "name:und_x_variant":[
        "Jagt\u0101p"
    ],
    "wof:name":"Jalka",
    "wof:placetype":"neighbourhood"
},
  "geometry": {"coordinates":[78.06189999999999,20.87967],"type":"Point"}
}