{
  "type": "Feature",
  "properties": {
    "gn:admin1_code":"35",
    "gn:admin2_code":"455.0",
    "gn:asciiname":"Churi Kalan",
    "gn:country_code":"IN",
    "gn:dem":629,
    "gn:feature_class":"P",
    "gn:feature_code":"PPL",
    "gn:name":"Churi Kal\u0101n",
    "gn:population":0,
    "gn:timezone":"Asia/Kolkata",
    "iso:country":"IN",
    "ks:ks_alt_nam":"Churi Kal\u0101n",
    "ks:ks_name":"Churi Kalan",
    "ks:ks_pop":247,
    "ks:ks_type":"VILLAGE",
    "name:eng_x_preferred":[
        "Churi Kalan"
    ],
    "name:eng_x_variant":[
        "Churi Kal\u0101n"
    ],
    "wof:name":"Churi Kalan",
    "wof:placetype":"locality",
    "wof:population":247
},
  "geometry": {"coordinates":[79.03268300000001,22.605776],"type":"Point"}
}