{
  "type": "Feature",
  "properties": {
    "iso:country":"IN",
    "ks:ks_name":"Banjeng",
    "ks:ks_pop":211,
    "ks:ks_type":"HABITATION",
    "name:eng_x_preferred":[
        "Banjeng"
    ],
    "wof:name":"Banjeng",
    "wof:placetype":"locality",
    "wof:population":211
},
  "geometry": {"coordinates":[91.197463,25.811064],"type":"Point"}
}