{
  "type": "Feature",
  "properties": {
    "iso:country":"IN",
    "ks:ks_name":"Anukuru",
    "ks:ks_pop":74,
    "ks:ks_type":"HABITATION",
    "name:eng_x_preferred":[
        "Anukuru"
    ],
    "wof:name":"Anukuru",
    "wof:placetype":"locality",
    "wof:population":74
},
  "geometry": {"coordinates":[82.70660100000001,17.853928],"type":"Point"}
}