{
  "type": "Feature",
  "properties": {
    "gn:admin1_code":"3.0",
    "gn:admin2_code":"318.0",
    "gn:asciiname":"Panchgram",
    "gn:country_code":"IN",
    "gn:dem":32,
    "gn:feature_class":"P",
    "gn:feature_code":"PPL",
    "gn:name":"Panchgram",
    "gn:population":0,
    "gn:timezone":"Asia/Kolkata",
    "iso:country":"IN",
    "wof:name":"Panchgram",
    "wof:placetype":"locality"
},
  "geometry": {"coordinates":[92.59631,24.86144],"type":"Point"}
}