{
  "type": "Feature",
  "properties": {
    "iso:country":"IN",
    "ks:ks_name":"Kedarwadi",
    "ks:ks_pop":1372,
    "ks:ks_type":"HABITATION",
    "name:eng_x_preferred":[
        "Kedarwadi"
    ],
    "wof:name":"Kedarwadi",
    "wof:placetype":"locality",
    "wof:population":1372
},
  "geometry": {"coordinates":[75.178544,17.412785],"type":"Point"}
}