{
  "type": "Feature",
  "properties": {
    "iso:country":"IN",
    "ks:ks_name":"Udhampur",
    "ks:ks_pop":457,
    "ks:ks_type":"HABITATION",
    "name:eng_x_preferred":[
        "Udhampur"
    ],
    "wof:name":"Udhampur",
    "wof:placetype":"locality",
    "wof:population":457
},
  "geometry": {"coordinates":[78.662992,27.692379],"type":"Point"}
}