{
  "type": "Feature",
  "properties": {
    "iso:country":"IN",
    "ks:ks_name":"Mhasapada",
    "ks:ks_pop":148,
    "ks:ks_type":"HABITATION",
    "name:eng_x_preferred":[
        "Mhasapada"
    ],
    "wof:name":"Mhasapada",
    "wof:placetype":"locality",
    "wof:population":148
},
  "geometry": {"coordinates":[72.933171,20.099358],"type":"Point"}
}