{
  "type": "Feature",
  "properties": {
    "iso:country":"IN",
    "ks:ks_name":"Salipeta",
    "ks:ks_pop":138,
    "ks:ks_type":"HABITATION",
    "name:eng_x_preferred":[
        "Salipeta"
    ],
    "wof:name":"Salipeta",
    "wof:placetype":"locality",
    "wof:population":138
},
  "geometry": {"coordinates":[83.963897,18.465769],"type":"Point"}
}