{
  "type": "Feature",
  "properties": {
    "iso:country":"IN",
    "ks:ks_name":"Balekoppa",
    "ks:ks_pop":52,
    "ks:ks_type":"HABITATION",
    "name:eng_x_preferred":[
        "Balekoppa"
    ],
    "wof:name":"Balekoppa",
    "wof:placetype":"locality",
    "wof:population":52
},
  "geometry": {"coordinates":[74.90335,14.459755],"type":"Point"}
}