{
  "type": "Feature",
  "properties": {
    "iso:country":"IN",
    "ks:ks_name":"Kumbaraguli",
    "ks:ks_pop":129,
    "ks:ks_type":"HABITATION",
    "name:eng_x_preferred":[
        "Kumbaraguli"
    ],
    "wof:name":"Kumbaraguli",
    "wof:placetype":"locality",
    "wof:population":129
},
  "geometry": {"coordinates":[75.09156900000001,14.120187],"type":"Point"}
}