{
  "type": "Feature",
  "properties": {
    "iso:country":"IN",
    "ks:ks_name":"Sawnga",
    "ks:ks_pop":1207,
    "ks:ks_type":"HABITATION",
    "name:eng_x_preferred":[
        "Sawnga"
    ],
    "wof:name":"Sawnga",
    "wof:placetype":"locality",
    "wof:population":1207
},
  "geometry": {"coordinates":[80.452589,20.117156],"type":"Point"}
}