{
  "type": "Feature",
  "properties": {
    "iso:country":"IN",
    "ks:ks_alt_nam":"KUMBHARWAGHMODE",
    "ks:ks_name":"Kumbharwaghmode",
    "ks:ks_pop":113,
    "ks:ks_type":"HABITATION",
    "name:eng_x_preferred":[
        "Kumbharwaghmode"
    ],
    "wof:name":"Kumbharwaghmode",
    "wof:placetype":"locality",
    "wof:population":113
},
  "geometry": {"coordinates":[74.938231,17.036921],"type":"Point"}
}