{
  "type": "Feature",
  "properties": {
    "iso:country":"IN",
    "ks:ks_name":"Khaspara Gudabeda",
    "ks:ks_pop":692,
    "ks:ks_type":"HABITATION",
    "name:eng_x_preferred":[
        "Khaspara Gudabeda"
    ],
    "wof:name":"Khaspara Gudabeda",
    "wof:placetype":"locality",
    "wof:population":692
},
  "geometry": {"coordinates":[81.008844,19.918708],"type":"Point"}
}