{
  "type": "Feature",
  "properties": {
    "iso:country":"IN",
    "ks:ks_name":"Kondapara",
    "ks:ks_pop":179,
    "ks:ks_type":"HABITATION",
    "name:eng_x_preferred":[
        "Kondapara"
    ],
    "wof:name":"Kondapara",
    "wof:placetype":"locality",
    "wof:population":179
},
  "geometry": {"coordinates":[81.759019,20.002255],"type":"Point"}
}