{
  "type": "Feature",
  "properties": {
    "iso:country":"IN",
    "ks:ks_name":"Rawat Gaon",
    "ks:ks_pop":33,
    "ks:ks_type":"VILLAGE",
    "name:eng_x_preferred":[
        "Rawat Gaon"
    ],
    "wof:name":"Rawat Gaon",
    "wof:placetype":"locality",
    "wof:population":33
},
  "geometry": {"coordinates":[78.801164,30.136747],"type":"Point"}
}