{
  "type": "Feature",
  "properties": {
    "iso:country":"IN",
    "ks:ks_name":"Belabhaur Mustqil",
    "ks:ks_pop":48,
    "ks:ks_type":"HABITATION",
    "name:eng_x_preferred":[
        "Belabhaur Mustqil"
    ],
    "wof:name":"Belabhaur Mustqil",
    "wof:placetype":"locality",
    "wof:population":48
},
  "geometry": {"coordinates":[79.806217,28.719774],"type":"Point"}
}