{
  "type": "Feature",
  "properties": {
    "gn:admin1_code":"34",
    "gn:admin2_code":"234.0",
    "gn:asciiname":"Ghanpura",
    "gn:country_code":"IN",
    "gn:dem":102,
    "gn:feature_class":"P",
    "gn:feature_code":"PPL",
    "gn:name":"Ghanpura",
    "gn:population":0,
    "gn:timezone":"Asia/Kolkata",
    "iso:country":"IN",
    "wof:name":"Ghanpura",
    "wof:placetype":"locality"
},
  "geometry": {"coordinates":[83.81854,24.90951],"type":"Point"}
}