{
  "type": "Feature",
  "properties": {
    "gn:admin1_code":"19.0",
    "gn:admin2_code":"568.0",
    "gn:asciiname":"Kademakki",
    "gn:country_code":"IN",
    "gn:dem":690,
    "gn:feature_class":"P",
    "gn:feature_code":"PPL",
    "gn:name":"Kademakki",
    "gn:population":0,
    "gn:timezone":"Asia/Kolkata",
    "iso:country":"IN",
    "ks:ks_name":"Kademakki",
    "ks:ks_pop":121,
    "ks:ks_type":"HABITATION",
    "name:eng_x_preferred":[
        "Kademakki"
    ],
    "wof:name":"Kademakki",
    "wof:placetype":"locality",
    "wof:population":121
},
  "geometry": {"coordinates":[75.323992,13.592736],"type":"Point"}
}