{
  "type": "Feature",
  "properties": {
    "gn:admin1_code":"37",
    "gn:admin2_code":"407.0",
    "gn:asciiname":"Piparkhunta",
    "gn:country_code":"IN",
    "gn:dem":718,
    "gn:feature_class":"P",
    "gn:feature_code":"PPL",
    "gn:name":"P\u012bparkh\u016bnta",
    "gn:population":0,
    "gn:timezone":"Asia/Kolkata",
    "iso:country":"IN",
    "ks:ks_name":"Piparkhunta",
    "ks:ks_pop":348,
    "ks:ks_type":"HABITATION",
    "name:eng_x_preferred":[
        "Piparkhunta"
    ],
    "wof:name":"Piparkhunta",
    "wof:placetype":"locality",
    "wof:population":348
},
  "geometry": {"coordinates":[81.118556,22.420241],"type":"Point"}
}