{
  "type": "Feature",
  "properties": {
    "iso:country":"IN",
    "ks:ks_name":"Matsajibi Para",
    "ks:ks_pop":1418,
    "ks:ks_type":"HABITATION",
    "name:eng_x_preferred":[
        "Matsajibi Para"
    ],
    "wof:name":"Matsajibi Para",
    "wof:placetype":"locality",
    "wof:population":1418
},
  "geometry": {"coordinates":[89.739251,26.322722],"type":"Point"}
}