{
  "type": "Feature",
  "properties": {
    "gn:country":"IN",
    "gn:fcode":"PPL",
    "gn:population":0,
    "iso:country":"IN",
    "qs_pg:aaroncc":"IN",
    "qs_pg:gn_country":"IN",
    "qs_pg:gn_fcode":"PPL",
    "qs_pg:gn_pop":0,
    "qs_pg:name":"Shindewadi",
    "qs_pg:name_adm0":"India",
    "qs_pg:name_adm1":"Maharashtra",
    "qs_pg:photos_9r":0,
    "qs_pg:photos_sr":0,
    "qs_pg:pop_sr":0,
    "qs_pg:qs_pg_placetype":"locality",
    "qs_pg:qs_pg_placetype_gp":"Town",
    "qs_pg:woe_adm0":23424848,
    "woe:adm0_id":23424848,
    "woe:name_adm0":"India",
    "woe:name_adm1":"Maharashtra",
    "woe:placetype":"Town",
    "wof:name":"Shindewadi",
    "wof:placetype":"neighbourhood"
},
  "geometry": {"coordinates":[73.72985,18.59342],"type":"Point"}
}