{
  "type": "Feature",
  "properties": {
    "iso:country":"IN",
    "ks:ks_name":"Duarparom",
    "ks:ks_pop":476,
    "ks:ks_type":"VILLAGE",
    "name:eng_x_preferred":[
        "Duarparom"
    ],
    "wof:name":"Duarparom",
    "wof:placetype":"locality",
    "wof:population":476
},
  "geometry": {"coordinates":[85.564239,22.757882],"type":"Point"}
}