{
  "type": "Feature",
  "properties": {
    "iso:country":"IN",
    "ks:ks_name":"2 BGM",
    "ks:ks_pop":78,
    "ks:ks_type":"VILLAGE",
    "ks:ks_uagg_main":0,
    "name:eng_x_preferred":[
        "2 BGM"
    ],
    "wof:name":"2 BGM",
    "wof:placetype":"neighbourhood",
    "wof:population":78
},
  "geometry": {"coordinates":[73.656389,29.349167],"type":"Point"}
}