{
  "type": "Feature",
  "properties": {
    "iso:country":"IN",
    "ks:ks_alt_nam":"NIRANJA NARAYAN PARA",
    "ks:ks_name":"Niranja Narayan Para",
    "ks:ks_pop":101,
    "ks:ks_type":"HABITATION",
    "name:eng_x_preferred":[
        "Niranja Narayan Para"
    ],
    "wof:name":"Niranja Narayan Para",
    "wof:placetype":"locality",
    "wof:population":101
},
  "geometry": {"coordinates":[91.403487,23.883796],"type":"Point"}
}