{
  "type": "Feature",
  "properties": {
    "iso:country":"IN",
    "ks:ks_alt_nam":"Koipady-Kadapuram",
    "ks:ks_name":"Koipady-kadapuram",
    "ks:ks_pop":1788,
    "ks:ks_type":"HABITATION",
    "name:eng_x_preferred":[
        "Koipady-kadapuram"
    ],
    "wof:name":"Koipady-kadapuram",
    "wof:placetype":"locality",
    "wof:population":1788
},
  "geometry": {"coordinates":[74.941772,12.586136],"type":"Point"}
}