{
  "type": "Feature",
  "properties": {
    "iso:country":"IN",
    "ks:ks_name":"Chemmalapadi Jn",
    "ks:ks_pop":801,
    "ks:ks_type":"HABITATION",
    "name:eng_x_preferred":[
        "Chemmalapadi Jn"
    ],
    "wof:name":"Chemmalapadi Jn",
    "wof:placetype":"locality",
    "wof:population":801
},
  "geometry": {"coordinates":[76.335193,11.143758],"type":"Point"}
}