{
  "type": "Feature",
  "properties": {
    "iso:country":"IN",
    "ks:ks_alt_nam":"Lal thanda",
    "ks:ks_name":"Lal Thanda",
    "ks:ks_pop":200,
    "ks:ks_type":"HABITATION",
    "name:eng_x_preferred":[
        "Lal Thanda"
    ],
    "wof:name":"Lal Thanda",
    "wof:placetype":"locality",
    "wof:population":200
},
  "geometry": {"coordinates":[79.75979599999999,17.825948],"type":"Point"}
}