{
  "type": "Feature",
  "properties": {
    "iso:country":"IN",
    "ks:ks_name":"Muthanoor",
    "ks:ks_pop":221,
    "ks:ks_type":"HABITATION",
    "ks:ks_uagg_main":0,
    "name:eng_x_preferred":[
        "Muthanoor"
    ],
    "wof:name":"Muthanoor",
    "wof:placetype":"neighbourhood",
    "wof:population":221
},
  "geometry": {"coordinates":[78.21484,12.223008],"type":"Point"}
}