{
  "type": "Feature",
  "properties": {
    "iso:country":"IN",
    "ks:ks_name":"Sasansima",
    "ks:ks_pop":2015,
    "ks:ks_type":"VILLAGE",
    "ks:ks_uagg_main":0,
    "name:eng_x_preferred":[
        "Sasansima"
    ],
    "wof:name":"Sasansima",
    "wof:placetype":"neighbourhood",
    "wof:population":2015
},
  "geometry": {"coordinates":[86.12238499999999,20.685799],"type":"Point"}
}