{
  "type": "Feature",
  "properties": {
    "iso:country":"IN",
    "ks:ks_name":"Achpalgarhi",
    "ks:ks_type":"VILLAGE",
    "ks:ks_uagg_main":0,
    "name:eng_x_preferred":[
        "Achpalgarhi"
    ],
    "wof:name":"Achpalgarhi",
    "wof:placetype":"neighbourhood"
},
  "geometry": {"coordinates":[77.670079,28.70439],"type":"Point"}
}