{
  "type": "Feature",
  "properties": {
    "iso:country":"IN",
    "ks:ks_name":"Tikopara",
    "ks:ks_pop":0,
    "ks:ks_type":"VILLAGE",
    "name:eng_x_preferred":[
        "Tikopara"
    ],
    "wof:name":"Tikopara",
    "wof:placetype":"locality",
    "wof:population":0
},
  "geometry": {"coordinates":[85.748002,24.390638],"type":"Point"}
}