{
  "type": "Feature",
  "properties": {
    "iso:country":"IN",
    "ks:ks_name":"Duliapara",
    "ks:ks_pop":423,
    "ks:ks_type":"VILLAGE",
    "ks:ks_uagg_main":0,
    "name:eng_x_preferred":[
        "Duliapara"
    ],
    "wof:name":"Duliapara",
    "wof:placetype":"neighbourhood",
    "wof:population":423
},
  "geometry": {"coordinates":[91.878409,26.675942],"type":"Point"}
}