{
  "type": "Feature",
  "properties": {
    "gn:admin1_code":"12.0",
    "gn:admin2_code":"021",
    "gn:asciiname":"Swamibagh",
    "gn:country_code":"IN",
    "gn:dem":314,
    "gn:feature_class":"P",
    "gn:feature_code":"PPL",
    "gn:name":"Sw\u0101mib\u0101gh",
    "gn:population":0,
    "gn:timezone":"Asia/Kolkata",
    "iso:country":"IN",
    "name:und_x_variant":[
        "Sw\u0101mib\u0101gh"
    ],
    "wof:name":"Swamibagh",
    "wof:placetype":"locality"
},
  "geometry": {"coordinates":[74.88472,32.74444],"type":"Point"}
}