{
  "type": "Feature",
  "properties": {
    "gn:admin1_code":"12.0",
    "gn:admin2_code":"021",
    "gn:asciiname":"Swamibagh",
    "gn:country_code":"IN",
    "gn:dem":314,
    "gn:feature_class":"P",
    "gn:feature_code":"PPL",
    "gn:name":"Sw\u0101mib\u0101gh",
    "gn:population":0,
    "gn:timezone":"Asia/Kolkata",
    "iso:country":"IN",
    "name:bpy_x_preferred":[
        "\u09b8\u09cd\u09ac\u09be\u09ae\u09bf\u09ac\u09be\u0997"
    ],
    "name:ita_x_preferred":[
        "Swamibagh"
    ],
    "name:msa_x_preferred":[
        "Swamibagh"
    ],
    "name:nld_x_preferred":[
        "Swamibagh"
    ],
    "name:pol_x_preferred":[
        "Swamibagh"
    ],
    "name:por_x_preferred":[
        "Swamibagh"
    ],
    "name:und_x_variant":[
        "Sw\u0101mib\u0101gh"
    ],
    "name:urd_x_preferred":[
        "\u0633\u0648\u0627\u0645\u06cc \u0628\u0627\u063a"
    ],
    "name:vie_x_preferred":[
        "Swamibagh"
    ],
    "name:zho_x_preferred":[
        "\u65af\u74e6\u7c73\u5df4\u683c"
    ],
    "wof:name":"Swamibagh",
    "wof:placetype":"locality"
},
  "geometry": {"coordinates":[74.88472,32.74444],"type":"Point"}
}