{
  "type": "Feature",
  "properties": {
    "iso:country":"IN",
    "ks:ks_name":"Pakhor",
    "ks:ks_pop":0,
    "ks:ks_type":"VILLAGE",
    "name:eng_x_preferred":[
        "Pakhor"
    ],
    "wof:name":"Pakhor",
    "wof:placetype":"locality",
    "wof:population":0
},
  "geometry": {"coordinates":[77.498267,30.155395],"type":"Point"}
}