{
  "type": "Feature",
  "properties": {
    "iso:country":"IN",
    "ks:ks_alt_nam":"Kare mane",
    "ks:ks_name":"Kare Mane",
    "ks:ks_pop":71,
    "ks:ks_type":"HABITATION",
    "name:eng_x_preferred":[
        "Kare Mane"
    ],
    "wof:name":"Kare Mane",
    "wof:placetype":"locality",
    "wof:population":71
},
  "geometry": {"coordinates":[74.55564099999999,15.037276],"type":"Point"}
}