{
  "type": "Feature",
  "properties": {
    "iso:country":"IN",
    "ks:ks_name":"Kondupara",
    "ks:ks_pop":109,
    "ks:ks_type":"HABITATION",
    "name:eng_x_preferred":[
        "Kondupara"
    ],
    "wof:name":"Kondupara",
    "wof:placetype":"locality",
    "wof:population":109
},
  "geometry": {"coordinates":[81.438534,19.607915],"type":"Point"}
}