{
  "type": "Feature",
  "properties": {
    "gn:admin1_code":"35",
    "gn:admin2_code":"466.0",
    "gn:asciiname":"Siwana",
    "gn:country_code":"IN",
    "gn:dem":290,
    "gn:feature_class":"P",
    "gn:feature_code":"PPL",
    "gn:name":"Siwana",
    "gn:population":0,
    "gn:timezone":"Asia/Kolkata",
    "iso:country":"IN",
    "name:ceb_x_preferred":[
        "Siw\u0101na"
    ],
    "name:swe_x_preferred":[
        "Siw\u0101na"
    ],
    "wof:name":"Siwana",
    "wof:placetype":"locality"
},
  "geometry": {"coordinates":[76.48425,21.86946],"type":"Point"}
}