{
  "type": "Feature",
  "properties": {
    "iso:country":"IN",
    "ks:ks_name":"Vrindhavannam",
    "ks:ks_pop":325,
    "ks:ks_type":"HABITATION",
    "name:eng_x_preferred":[
        "Vrindhavannam"
    ],
    "wof:name":"Vrindhavannam",
    "wof:placetype":"neighbourhood",
    "wof:population":325
},
  "geometry": {"coordinates":[76.894526,8.929271],"type":"Point"}
}