{
  "type": "Feature",
  "properties": {
    "gn:admin1_code":"36",
    "gn:admin2_code":"188.0",
    "gn:asciiname":"Balua",
    "gn:country_code":"IN",
    "gn:dem":85,
    "gn:feature_class":"P",
    "gn:feature_code":"PPL",
    "gn:name":"Balua",
    "gn:population":0,
    "gn:timezone":"Asia/Kolkata",
    "iso:country":"IN",
    "ks:ks_name":"Balua",
    "ks:ks_type":"VILLAGE",
    "name:eng_x_preferred":[
        "Balua"
    ],
    "wof:name":"Balua",
    "wof:placetype":"locality"
},
  "geometry": {"coordinates":[83.259315,26.513911],"type":"Point"}
}