{
  "type": "Feature",
  "properties": {
    "iso:country":"IN",
    "ks:ks_name":"Khojalvasa",
    "ks:ks_pop":4239,
    "ks:ks_type":"VILLAGE",
    "name:eng_x_preferred":[
        "Khojalvasa"
    ],
    "wof:name":"Khojalvasa",
    "wof:placetype":"locality",
    "wof:population":4239
},
  "geometry": {"coordinates":[73.74518500000001,22.957596],"type":"Point"}
}