{
  "type": "Feature",
  "properties": {
    "gn:admin1_code":"35",
    "gn:admin2_code":"460.0",
    "gn:asciiname":"Gopaipur",
    "gn:country_code":"IN",
    "gn:dem":296,
    "gn:feature_class":"P",
    "gn:feature_code":"PPL",
    "gn:name":"Gop\u0101ipur",
    "gn:population":0,
    "gn:timezone":"Asia/Kolkata",
    "iso:country":"IN",
    "wof:name":"Gopaipur",
    "wof:placetype":"locality"
},
  "geometry": {"coordinates":[81.39424,24.24654],"type":"Point"}
}