{
  "type": "Feature",
  "properties": {
    "gn:admin1_code":"35",
    "gn:admin2_code":"460.0",
    "gn:asciiname":"Gopaipur",
    "gn:country_code":"IN",
    "gn:dem":296,
    "gn:feature_class":"P",
    "gn:feature_code":"PPL",
    "gn:name":"Gop\u0101ipur",
    "gn:population":0,
    "gn:timezone":"Asia/Kolkata",
    "iso:country":"IN",
    "ks:ks_name":"Gopalpur",
    "ks:ks_pop":1786,
    "ks:ks_type":"VILLAGE",
    "name:eng_x_preferred":[
        "Gopalpur"
    ],
    "name:eng_x_variant":[
        "Gopaipur"
    ],
    "wof:name":"Gopalpur",
    "wof:placetype":"locality",
    "wof:population":1786
},
  "geometry": {"coordinates":[81.396186,24.246163],"type":"Point"}
}