{
  "type": "Feature",
  "properties": {
    "iso:country":"IN",
    "ks:ks_name":"Mitumamudi",
    "ks:ks_pop":120,
    "ks:ks_type":"HABITATION",
    "name:eng_x_preferred":[
        "Mitumamudi"
    ],
    "wof:name":"Mitumamudi",
    "wof:placetype":"locality",
    "wof:population":120
},
  "geometry": {"coordinates":[82.026185,18.101238],"type":"Point"}
}