{
  "type": "Feature",
  "properties": {
    "iso:country":"IN",
    "ks:ks_alt_nam":"RAM LAKHAN SINGH TOLA",
    "ks:ks_name":"Ram Lakhan Singh Tola",
    "ks:ks_pop":270,
    "ks:ks_type":"HABITATION",
    "name:eng_x_preferred":[
        "Ram Lakhan Singh Tola"
    ],
    "wof:name":"Ram Lakhan Singh Tola",
    "wof:placetype":"locality",
    "wof:population":270
},
  "geometry": {"coordinates":[84.91804399999999,25.856623],"type":"Point"}
}