{
  "type": "Feature",
  "properties": {
    "gn:admin1_code":"25.0",
    "gn:admin2_code":"620.0",
    "gn:asciiname":"Seturayan Kudikkadu",
    "gn:country_code":"IN",
    "gn:dem":46,
    "gn:feature_class":"P",
    "gn:feature_code":"PPL",
    "gn:name":"Setur\u0101yan Kudikk\u0101du",
    "gn:population":0,
    "gn:timezone":"Asia/Kolkata",
    "iso:country":"IN",
    "wof:name":"Seturayan Kudikkadu",
    "wof:placetype":"locality"
},
  "geometry": {"coordinates":[79.20331999999998,10.63622],"type":"Point"}
}