{
  "type": "Feature",
  "properties": {
    "gn:admin1_code":"25.0",
    "gn:admin2_code":"620.0",
    "gn:asciiname":"Seturayan Kudikkadu",
    "gn:country_code":"IN",
    "gn:dem":46,
    "gn:feature_class":"P",
    "gn:feature_code":"PPL",
    "gn:name":"Setur\u0101yan Kudikk\u0101du",
    "gn:population":0,
    "gn:timezone":"Asia/Kolkata",
    "iso:country":"IN",
    "ks:ks_name":"Sethurayankudikadu",
    "ks:ks_pop":895,
    "ks:ks_type":"HABITATION",
    "name:eng_x_preferred":[
        "Sethurayankudikadu"
    ],
    "name:eng_x_variant":[
        "Seturayan Kudikkadu"
    ],
    "wof:name":"Sethurayankudikadu",
    "wof:placetype":"locality",
    "wof:population":895
},
  "geometry": {"coordinates":[79.217286,10.644272],"type":"Point"}
}