{
  "type": "Feature",
  "properties": {
    "iso:country":"IN",
    "name:bos_x_preferred":[
        "Mala"
    ],
    "name:deu_x_preferred":[
        "Mala"
    ],
    "name:eng_x_preferred":[
        "Mala"
    ],
    "name:fra_x_preferred":[
        "Mala"
    ],
    "name:hun_x_preferred":[
        "Mala"
    ],
    "name:ita_x_preferred":[
        "Mala"
    ],
    "name:nld_x_preferred":[
        "Mala"
    ],
    "name:nor_x_preferred":[
        "Mala"
    ],
    "name:pol_x_preferred":[
        "Mala"
    ],
    "name:por_x_preferred":[
        "Mala"
    ],
    "name:spa_x_preferred":[
        "Mala"
    ],
    "name:unk_x_variant":[
        "Mala"
    ],
    "qs:gn_fcode":"PPL",
    "qs:gn_local":0,
    "qs:gn_namadm1":"33",
    "qs:gn_name":"Malar",
    "qs:local_max":1483,
    "qs:local_sum":2422,
    "qs:localhoods":5,
    "qs:name":"Mala",
    "qs:name_adm0":"India",
    "qs:name_adm1":"Goa",
    "qs:name_adm2":"North Goa",
    "qs:name_local":"Panaji",
    "qs:photo_max":23,
    "qs:photo_sum":23,
    "qs:placetype":"Suburb",
    "qs:quad_count":1,
    "qs:woe_adm0":23424848,
    "qs:woe_adm1":2345764,
    "qs:woe_adm2":12586827,
    "qs:woe_lau":0,
    "qs:woe_local":2295173,
    "qs:woe_ver":"7.10.0",
    "wof:lang":[
        "eng"
    ],
    "wof:name":"Mala",
    "wof:placetype":"neighbourhood"
},
  "geometry": {"coordinates":[73.825378,15.488092],"type":"Point"}
}