{
  "type": "Feature",
  "properties": {
    "iso:country":"IN",
    "name:ara_x_preferred":[
        "\u0645\u0627\u0644\u0627"
    ],
    "name:ben_bn_x_preferred":[
        "\u09ae\u09be\u09b2\u09be"
    ],
    "name:ben_in_x_preferred":[
        "\u09ae\u09be\u09b2\u09be"
    ],
    "name:bos_x_preferred":[
        "Mala"
    ],
    "name:ceb_x_preferred":[
        "Mala"
    ],
    "name:deu_x_preferred":[
        "Mala"
    ],
    "name:eng_x_preferred":[
        "Mala"
    ],
    "name:fra_x_preferred":[
        "Mala"
    ],
    "name:guj_x_preferred":[
        "\u0aae\u0abe\u0ab2\u0abe"
    ],
    "name:hin_x_preferred":[
        "\u092e\u093e\u0932\u093e"
    ],
    "name:hun_x_preferred":[
        "Mala"
    ],
    "name:ita_x_preferred":[
        "Mala"
    ],
    "name:kan_x_preferred":[
        "\u0cae\u0cbe\u0cb2\u0cbe"
    ],
    "name:mal_x_preferred":[
        "\u0d2e\u0d3e\u0d33"
    ],
    "name:mar_x_preferred":[
        "\u092e\u093e\u0932\u093e"
    ],
    "name:nld_x_preferred":[
        "Mala"
    ],
    "name:nor_x_preferred":[
        "Mala"
    ],
    "name:pan_x_preferred":[
        "\u0a2e\u0a3e\u0a32\u0a3e"
    ],
    "name:pol_x_preferred":[
        "Mala"
    ],
    "name:por_x_preferred":[
        "Mala"
    ],
    "name:spa_x_preferred":[
        "Mala"
    ],
    "name:srp_x_preferred":[
        "Mala"
    ],
    "name:swe_x_preferred":[
        "Mala"
    ],
    "name:tam_x_preferred":[
        "\u0bae\u0bb2\u0bbe"
    ],
    "name:tel_x_preferred":[
        "\u0c2e\u0c3e\u0c32\u0c3e"
    ],
    "name:urd_x_preferred":[
        "\u0645\u0627\u0644\u0627"
    ],
    "name:uzb_x_preferred":[
        "Male"
    ],
    "qs:gn_fcode":"PPL",
    "qs:gn_local":0,
    "qs:gn_namadm1":"33",
    "qs:gn_name":"Malar",
    "qs:local_max":1483,
    "qs:local_sum":2422,
    "qs:localhoods":5,
    "qs:name":"Mala",
    "qs:name_adm0":"India",
    "qs:name_adm1":"Goa",
    "qs:name_adm2":"North Goa",
    "qs:name_local":"Panaji",
    "qs:photo_max":23,
    "qs:photo_sum":23,
    "qs:placetype":"Suburb",
    "qs:quad_count":1,
    "qs:woe_adm0":23424848,
    "qs:woe_adm1":2345764,
    "qs:woe_adm2":12586827,
    "qs:woe_lau":0,
    "qs:woe_local":2295173,
    "qs:woe_ver":"7.10.0",
    "wof:lang":[
        "eng"
    ],
    "wof:name":"Mala",
    "wof:placetype":"neighbourhood"
},
  "geometry": {"coordinates":[73.825378,15.488092],"type":"Point"}
}