{
  "type": "Feature",
  "properties": {
    "gn:admin1_code":"10.0",
    "gn:admin2_code":"71.0",
    "gn:asciiname":"Satahari",
    "gn:country_code":"IN",
    "gn:dem":288,
    "gn:feature_class":"P",
    "gn:feature_code":"PPL",
    "gn:name":"Sat\u0101hari",
    "gn:population":0,
    "gn:timezone":"Asia/Kolkata",
    "iso:country":"IN",
    "wof:name":"Satahari",
    "wof:placetype":"locality"
},
  "geometry": {"coordinates":[77.18994000000001,30.27661],"type":"Point"}
}