{
  "type": "Feature",
  "properties": {
    "iso:country":"IN",
    "ks:ks_name":"Balipatana",
    "ks:ks_pop":734,
    "ks:ks_type":"VILLAGE",
    "name:eng_x_preferred":[
        "Balipatana"
    ],
    "wof:name":"Balipatana",
    "wof:placetype":"locality",
    "wof:population":734
},
  "geometry": {"coordinates":[86.51185700000001,20.871006],"type":"Point"}
}