{
  "type": "Feature",
  "properties": {
    "iso:country":"IN",
    "ks:ks_name":"Magdiya Chak Koti Madhe",
    "ks:ks_pop":67,
    "ks:ks_type":"HABITATION",
    "name:eng_x_preferred":[
        "Magdiya Chak Koti Madhe"
    ],
    "wof:name":"Magdiya Chak Koti Madhe",
    "wof:placetype":"locality",
    "wof:population":67
},
  "geometry": {"coordinates":[78.037623,30.564618],"type":"Point"}
}