{
  "type": "Feature",
  "properties": {
    "iso:country":"IN",
    "ks:ks_alt_nam":"DEWRISAI",
    "ks:ks_name":"Dewrisai",
    "ks:ks_pop":617,
    "ks:ks_type":"HABITATION",
    "name:eng_x_preferred":[
        "Dewrisai"
    ],
    "wof:name":"Dewrisai",
    "wof:placetype":"locality",
    "wof:population":617
},
  "geometry": {"coordinates":[85.891715,22.048813],"type":"Point"}
}