{
  "type": "Feature",
  "properties": {
    "gn:admin1_code":"2",
    "gn:admin2_code":"544.0",
    "gn:asciiname":"Jangamput",
    "gn:country_code":"IN",
    "gn:dem":1226,
    "gn:feature_class":"P",
    "gn:feature_code":"PPL",
    "gn:name":"Jangamput",
    "gn:population":0,
    "gn:timezone":"Asia/Kolkata",
    "iso:country":"IN",
    "ks:ks_name":"Jangamputtu",
    "ks:ks_pop":99,
    "ks:ks_type":"VILLAGE",
    "name:eng_x_preferred":[
        "Jangamputtu"
    ],
    "name:eng_x_variant":[
        "Jangamput"
    ],
    "wof:name":"Jangamputtu",
    "wof:placetype":"locality",
    "wof:population":99
},
  "geometry": {"coordinates":[82.831402,18.173536],"type":"Point"}
}