{
  "type": "Feature",
  "properties": {
    "gn:admin1_code":"35.0",
    "gn:admin2_code":"452.0",
    "gn:asciiname":"Khairi",
    "gn:country_code":"IN",
    "gn:dem":380,
    "gn:feature_class":"P",
    "gn:feature_code":"PPL",
    "gn:name":"Khairi",
    "gn:population":0,
    "gn:timezone":"Asia/Kolkata",
    "iso:country":"IN",
    "wof:name":"Khairi",
    "wof:placetype":"locality"
},
  "geometry": {"coordinates":[78.73425999999998,22.7393],"type":"Point"}
}