{
  "type": "Feature",
  "properties": {
    "gn:admin1_code":"34.0",
    "gn:admin2_code":"237.0",
    "gn:asciiname":"Adampur",
    "gn:country_code":"IN",
    "gn:dem":93,
    "gn:feature_class":"P",
    "gn:feature_code":"PPL",
    "gn:name":"Adampur",
    "gn:population":0,
    "gn:timezone":"Asia/Kolkata",
    "iso:country":"IN",
    "wof:name":"Adampur",
    "wof:placetype":"locality"
},
  "geometry": {"coordinates":[85.66808,24.90787000000001],"type":"Point"}
}