{
  "type": "Feature",
  "properties": {
    "iso:country":"IN",
    "ks:ks_name":"Telem Gamchuk",
    "ks:ks_pop":810,
    "ks:ks_type":"HABITATION",
    "ks:ks_uagg_main":0,
    "name:eng_x_preferred":[
        "Telem Gamchuk"
    ],
    "wof:name":"Telem Gamchuk",
    "wof:placetype":"neighbourhood",
    "wof:population":810
},
  "geometry": {"coordinates":[95.004763,27.761955],"type":"Point"}
}