{
  "type": "Feature",
  "properties": {
    "gn:admin1_code":"11.0",
    "gn:admin2_code":"27.0",
    "gn:asciiname":"Bahn",
    "gn:country_code":"IN",
    "gn:dem":1915,
    "gn:feature_class":"P",
    "gn:feature_code":"PPL",
    "gn:name":"B\u0101hn",
    "gn:population":0,
    "gn:timezone":"Asia/Kolkata",
    "iso:country":"IN",
    "name:deu_x_preferred":[
        "Bahn"
    ],
    "name:fra_x_preferred":[
        "Bahn"
    ],
    "name:nld_x_preferred":[
        "Bahn"
    ],
    "wof:name":"Bahn",
    "wof:placetype":"locality"
},
  "geometry": {"coordinates":[77.29365,31.39298],"type":"Point"}
}