{
  "type": "Feature",
  "properties": {
    "gn:admin1_code":"36",
    "gn:admin2_code":"185.0",
    "gn:asciiname":"Mahulani",
    "gn:country_code":"IN",
    "gn:dem":97,
    "gn:feature_class":"P",
    "gn:feature_code":"PPL",
    "gn:name":"Mahul\u0101ni",
    "gn:population":0,
    "gn:timezone":"Asia/Kolkata",
    "iso:country":"IN",
    "wof:name":"Mahulani",
    "wof:placetype":"locality"
},
  "geometry": {"coordinates":[82.46214999999999,26.85241],"type":"Point"}
}