{
  "type": "Feature",
  "properties": {
    "iso:country":"IN",
    "ks:ks_name":"Chomakunda Area",
    "ks:ks_pop":94,
    "ks:ks_type":"HABITATION",
    "name:eng_x_preferred":[
        "Chomakunda Area"
    ],
    "wof:name":"Chomakunda Area",
    "wof:placetype":"locality",
    "wof:population":94
},
  "geometry": {"coordinates":[75.690556,12.214444],"type":"Point"}
}