{
  "type": "Feature",
  "properties": {
    "iso:country":"IN",
    "ks:ks_alt_nam":"ghungha jila par",
    "ks:ks_name":"Ghungha Jila Par",
    "ks:ks_pop":591,
    "ks:ks_type":"HABITATION",
    "name:eng_x_preferred":[
        "Ghungha Jila Par"
    ],
    "wof:name":"Ghungha Jila Par",
    "wof:placetype":"locality",
    "wof:population":591
},
  "geometry": {"coordinates":[82.20129,25.25672],"type":"Point"}
}