{
  "type": "Feature",
  "properties": {
    "iso:country":"IN",
    "ks:ks_alt_nam":"modi tola",
    "ks:ks_name":"Modi Tola",
    "ks:ks_pop":42,
    "ks:ks_type":"HABITATION",
    "ks:ks_uagg_main":0,
    "name:eng_x_preferred":[
        "Modi Tola"
    ],
    "wof:name":"Modi Tola",
    "wof:placetype":"neighbourhood",
    "wof:population":42
},
  "geometry": {"coordinates":[86.35392899999999,24.64351],"type":"Point"}
}