{
  "type": "Feature",
  "properties": {
    "iso:country":"IN",
    "ks:ks_name":"Karundia",
    "ks:ks_pop":2202,
    "ks:ks_type":"HABITATION",
    "name:eng_x_preferred":[
        "Karundia"
    ],
    "wof:name":"Karundia",
    "wof:placetype":"locality",
    "wof:population":2202
},
  "geometry": {"coordinates":[88.82697899999999,22.526521],"type":"Point"}
}