{
  "type": "Feature",
  "properties": {
    "iso:country":"IN",
    "ks:ks_name":"Kunreddygudem",
    "ks:ks_pop":35,
    "ks:ks_type":"HABITATION",
    "name:eng_x_preferred":[
        "Kunreddygudem"
    ],
    "wof:name":"Kunreddygudem",
    "wof:placetype":"locality",
    "wof:population":35
},
  "geometry": {"coordinates":[79.086963,16.778217],"type":"Point"}
}