{
  "type": "Feature",
  "properties": {
    "iso:country":"IN",
    "ks:ks_name":"Gadavewasti",
    "ks:ks_pop":117,
    "ks:ks_type":"HABITATION",
    "name:eng_x_preferred":[
        "Gadavewasti"
    ],
    "wof:name":"Gadavewasti",
    "wof:placetype":"locality",
    "wof:population":117
},
  "geometry": {"coordinates":[75.241724,18.31463],"type":"Point"}
}