{
  "type": "Feature",
  "properties": {
    "iso:country":"IN",
    "ks:ks_name":"Uparpatama",
    "ks:ks_pop":33,
    "ks:ks_type":"VILLAGE",
    "name:eng_x_preferred":[
        "Uparpatama"
    ],
    "wof:name":"Uparpatama",
    "wof:placetype":"locality",
    "wof:population":33
},
  "geometry": {"coordinates":[84.295327,19.628383],"type":"Point"}
}