{
  "type": "Feature",
  "properties": {
    "iso:country":"IN",
    "ks:ks_name":"Hatiberya",
    "ks:ks_pop":973,
    "ks:ks_type":"VILLAGE",
    "name:eng_x_preferred":[
        "Hatiberya"
    ],
    "wof:name":"Hatiberya",
    "wof:placetype":"locality",
    "wof:population":973
},
  "geometry": {"coordinates":[87.629575,22.341994],"type":"Point"}
}