{
  "type": "Feature",
  "properties": {
    "iso:country":"IN",
    "ks:ks_name":"Khamra",
    "ks:ks_pop":0,
    "ks:ks_type":"VILLAGE",
    "name:eng_x_preferred":[
        "Khamra"
    ],
    "wof:name":"Khamra",
    "wof:placetype":"locality",
    "wof:population":0
},
  "geometry": {"coordinates":[88.15230099999999,24.494893],"type":"Point"}
}