{
  "type": "Feature",
  "properties": {
    "iso:country":"IN",
    "ks:ks_name":"Gorawa Ka Purwa",
    "ks:ks_pop":377,
    "ks:ks_type":"HABITATION",
    "name:eng_x_preferred":[
        "Gorawa Ka Purwa"
    ],
    "wof:name":"Gorawa Ka Purwa",
    "wof:placetype":"locality",
    "wof:population":377
},
  "geometry": {"coordinates":[81.20926,27.869733],"type":"Point"}
}