{
  "type": "Feature",
  "properties": {
    "iso:country":"IN",
    "ks:ks_name":"Komadavolu",
    "ks:ks_pop":2779,
    "ks:ks_type":"VILLAGE",
    "ks:ks_uagg_main":0,
    "name:eng_x_preferred":[
        "Komadavolu"
    ],
    "wof:name":"Komadavolu",
    "wof:placetype":"locality",
    "wof:population":2779
},
  "geometry": {"coordinates":[81.125828,16.7108],"type":"Point"}
}