{
  "type": "Feature",
  "properties": {
    "iso:country":"IN",
    "ks:ks_name":"Kudapalewadi",
    "ks:ks_pop":223,
    "ks:ks_type":"HABITATION",
    "name:eng_x_preferred":[
        "Kudapalewadi"
    ],
    "wof:name":"Kudapalewadi",
    "wof:placetype":"locality",
    "wof:population":223
},
  "geometry": {"coordinates":[73.800359,17.449339],"type":"Point"}
}