{
  "type": "Feature",
  "properties": {
    "iso:country":"IN",
    "ks:ks_name":"Kainad",
    "ks:ks_pop":5390,
    "ks:ks_type":"VILLAGE",
    "name:eng_x_preferred":[
        "Kainad"
    ],
    "wof:name":"Kainad",
    "wof:placetype":"locality",
    "wof:population":5390
},
  "geometry": {"coordinates":[72.78561000000001,20.034972],"type":"Point"}
}