{
  "type": "Feature",
  "properties": {
    "gn:admin1_code":"12",
    "gn:admin2_code":"7.0",
    "gn:asciiname":"Loang",
    "gn:country_code":"IN",
    "gn:dem":1864,
    "gn:feature_class":"P",
    "gn:feature_code":"PPL",
    "gn:name":"Lo\u0101ng",
    "gn:population":0,
    "gn:timezone":"Asia/Kolkata",
    "iso:country":"IN",
    "wof:name":"Loang",
    "wof:placetype":"locality"
},
  "geometry": {"coordinates":[75.79609000000001,32.77638],"type":"Point"}
}