{
  "type": "Feature",
  "properties": {
    "iso:country":"IN",
    "ks:ks_name":"Kantijhari",
    "ks:ks_pop":603,
    "ks:ks_type":"VILLAGE",
    "name:eng_x_preferred":[
        "Kantijhari"
    ],
    "wof:name":"Kantijhari",
    "wof:placetype":"locality",
    "wof:population":603
},
  "geometry": {"coordinates":[86.099531,19.91254],"type":"Point"}
}