{
  "type": "Feature",
  "properties": {
    "iso:country":"IN",
    "ks:ks_name":"Gamhariya Khairwaripara",
    "ks:ks_pop":629,
    "ks:ks_type":"HABITATION",
    "name:eng_x_preferred":[
        "Gamhariya Khairwaripara"
    ],
    "wof:name":"Gamhariya Khairwaripara",
    "wof:placetype":"locality",
    "wof:population":629
},
  "geometry": {"coordinates":[83.554356,23.818942],"type":"Point"}
}