{
  "type": "Feature",
  "properties": {
    "gn:admin1_code":"23.0",
    "gn:admin2_code":"35.0",
    "gn:asciiname":"Japuwal",
    "gn:country_code":"IN",
    "gn:dem":261,
    "gn:feature_class":"P",
    "gn:feature_code":"PPL",
    "gn:name":"Japuw\u0101l",
    "gn:population":0,
    "gn:timezone":"Asia/Kolkata",
    "iso:country":"IN",
    "ks:ks_alt_nam":"Japuw\u0101l",
    "ks:ks_name":"Japuwal",
    "ks:ks_pop":593,
    "ks:ks_type":"VILLAGE",
    "ks:ks_uagg_main":0,
    "name:eng_x_preferred":[
        "Japuwal"
    ],
    "name:eng_x_variant":[
        "Japuw\u0101l"
    ],
    "wof:name":"Japuwal",
    "wof:placetype":"locality",
    "wof:population":593
},
  "geometry": {"coordinates":[75.362803,32.001151],"type":"Point"}
}