{
  "type": "Feature",
  "properties": {
    "iso:country":"IN",
    "ks:ks_name":"Arlahonda",
    "ks:ks_pop":85,
    "ks:ks_type":"HABITATION",
    "name:eng_x_preferred":[
        "Arlahonda"
    ],
    "wof:name":"Arlahonda",
    "wof:placetype":"locality",
    "wof:population":85
},
  "geometry": {"coordinates":[74.91045800000001,14.602641],"type":"Point"}
}