{
  "type": "Feature",
  "properties": {
    "gn:admin1_code":"24",
    "gn:admin2_code":"123.0",
    "gn:asciiname":"Mandawar",
    "gn:country_code":"IN",
    "gn:dem":629,
    "gn:feature_class":"P",
    "gn:feature_code":"PPL",
    "gn:name":"Mand\u0101war",
    "gn:population":0,
    "gn:timezone":"Asia/Kolkata",
    "iso:country":"IN",
    "name:ita_x_preferred":[
        "Mandawar"
    ],
    "name:nld_x_preferred":[
        "Mandawar"
    ],
    "wof:name":"Mandawar",
    "wof:placetype":"locality"
},
  "geometry": {"coordinates":[73.81085,25.202],"type":"Point"}
}