{
  "type": "Feature",
  "properties": {
    "iso:country":"IN",
    "ks:ks_name":"Belwani Tola",
    "ks:ks_pop":415,
    "ks:ks_type":"HABITATION",
    "ks:ks_uagg_main":0,
    "name:eng_x_preferred":[
        "Belwani Tola"
    ],
    "wof:name":"Belwani Tola",
    "wof:placetype":"neighbourhood",
    "wof:population":415
},
  "geometry": {"coordinates":[83.980655,27.064107],"type":"Point"}
}