{
  "type": "Feature",
  "properties": {
    "gn:admin1_code":"2.0",
    "gn:admin2_code":"544.0",
    "gn:asciiname":"Kuncharpanaku",
    "gn:country_code":"IN",
    "gn:dem":1034,
    "gn:feature_class":"P",
    "gn:feature_code":"PPL",
    "gn:name":"Kuncharpanaku",
    "gn:population":0,
    "gn:timezone":"Asia/Kolkata",
    "iso:country":"IN",
    "wof:name":"Kuncharpanaku",
    "wof:placetype":"locality"
},
  "geometry": {"coordinates":[82.57370999999998,18.00781],"type":"Point"}
}