{
  "type": "Feature",
  "properties": {
    "gn:admin1_code":"2.0",
    "gn:admin2_code":"544.0",
    "gn:asciiname":"Kuncharpanaku",
    "gn:country_code":"IN",
    "gn:dem":1034,
    "gn:feature_class":"P",
    "gn:feature_code":"PPL",
    "gn:name":"Kuncharpanaku",
    "gn:population":0,
    "gn:timezone":"Asia/Kolkata",
    "iso:country":"IN",
    "ks:ks_name":"Kancharapanuku",
    "ks:ks_pop":51,
    "ks:ks_type":"HABITATION",
    "name:eng_x_preferred":[
        "Kancharapanuku"
    ],
    "name:eng_x_variant":[
        "Kuncharpanaku"
    ],
    "wof:name":"Kancharapanuku",
    "wof:placetype":"locality",
    "wof:population":51
},
  "geometry": {"coordinates":[82.57332700000001,18.009438],"type":"Point"}
}