{
  "type": "Feature",
  "properties": {
    "gn:admin1_code":"10",
    "gn:admin2_code":"69.0",
    "gn:asciiname":"Kakrali",
    "gn:country_code":"IN",
    "gn:dem":302,
    "gn:feature_class":"P",
    "gn:feature_code":"PPL",
    "gn:name":"Kakr\u0101li",
    "gn:population":0,
    "gn:timezone":"Asia/Kolkata",
    "iso:country":"IN",
    "wof:name":"Kakrali",
    "wof:placetype":"locality"
},
  "geometry": {"coordinates":[76.96556,30.49329],"type":"Point"}
}