{
  "type": "Feature",
  "properties": {
    "gn:admin1_code":"34.0",
    "gn:admin2_code":"210.0",
    "gn:asciiname":"Panchgachhi",
    "gn:country_code":"IN",
    "gn:dem":65,
    "gn:feature_class":"P",
    "gn:feature_code":"PPL",
    "gn:name":"P\u0101nchg\u0101chhi",
    "gn:population":0,
    "gn:timezone":"Asia/Kolkata",
    "iso:country":"IN",
    "name:bih_x_preferred":[
        "\u092a\u093e\u0901\u091a\u0917\u093e\u091b\u0940"
    ],
    "name:dty_x_preferred":[
        "\u092a\u093e\u0901\u091a\u0917\u093e\u091b\u0940"
    ],
    "name:fra_x_preferred":[
        "Panchgachhi"
    ],
    "name:hin_x_preferred":[
        "\u092a\u093e\u0901\u091a\u0917\u093e\u091b\u0940"
    ],
    "name:mai_x_preferred":[
        "\u092a\u093e\u0901\u091a\u0917\u093e\u091b\u0940"
    ],
    "name:msa_x_preferred":[
        "Panchganchi"
    ],
    "name:nep_x_preferred":[
        "\u092a\u093e\u0901\u091a\u0917\u093e\u091b\u0940"
    ],
    "name:pol_x_preferred":[
        "Panchgachhi"
    ],
    "wof:name":"Panchgachhi",
    "wof:placetype":"locality"
},
  "geometry": {"coordinates":[87.70031999999998,26.33711],"type":"Point"}
}