{
  "type": "Feature",
  "properties": {
    "iso:country":"IN",
    "ks:ks_alt_nam":"K\u0101sh\u012br\u0101mpur",
    "ks:ks_name":"Kashirampur",
    "ks:ks_type":"VILLAGE",
    "ks:ks_uagg_main":0,
    "name:eng_x_preferred":[
        "Kashirampur"
    ],
    "name:eng_x_variant":[
        "K\u0101sh\u012br\u0101mpur"
    ],
    "wof:name":"Kashirampur",
    "wof:placetype":"neighbourhood"
},
  "geometry": {"coordinates":[78.521974,29.737535],"type":"Point"}
}