{
  "type": "Feature",
  "properties": {
    "gn:admin1_code":"39",
    "gn:admin2_code":"61.0",
    "gn:asciiname":"Kande Talla",
    "gn:country_code":"IN",
    "gn:dem":1463,
    "gn:feature_class":"P",
    "gn:feature_code":"PPL",
    "gn:name":"K\u0101nde Talla",
    "gn:population":0,
    "gn:timezone":"Asia/Kolkata",
    "iso:country":"IN",
    "wof:name":"Kande Talla",
    "wof:placetype":"locality"
},
  "geometry": {"coordinates":[78.76493000000001,30.095],"type":"Point"}
}