{
  "type": "Feature",
  "properties": {
    "iso:country":"IN",
    "ks:ks_name":"Khalsa Bamanpur",
    "ks:ks_pop":600,
    "ks:ks_type":"VILLAGE",
    "name:eng_x_preferred":[
        "Khalsa Bamanpur"
    ],
    "wof:name":"Khalsa Bamanpur",
    "wof:placetype":"locality",
    "wof:population":600
},
  "geometry": {"coordinates":[87.959479,22.210054],"type":"Point"}
}