{
  "type": "Feature",
  "properties": {
    "gn:admin1_code":"16",
    "gn:admin2_code":"502.0",
    "gn:asciiname":"Babapur",
    "gn:country_code":"IN",
    "gn:dem":346,
    "gn:feature_class":"P",
    "gn:feature_code":"PPL",
    "gn:name":"B\u0101b\u0101pur",
    "gn:population":0,
    "gn:timezone":"Asia/Kolkata",
    "iso:country":"IN",
    "wof:name":"Babapur",
    "wof:placetype":"locality"
},
  "geometry": {"coordinates":[77.49200999999999,20.63223],"type":"Point"}
}