{
  "type": "Feature",
  "properties": {
    "iso:country":"IN",
    "qs:name":"Dwarka Sector 12",
    "qs:name_adm0":"India",
    "qs:name_adm1":"Delhi",
    "qs:photos":5,
    "qs:photos_1k":1,
    "qs:photos_9k":1,
    "qs:photos_9r":1,
    "qs:photos_all":5,
    "qs:photos_sr":1,
    "qs:placetype":"Suburb",
    "qs:pop_sr":"0",
    "wof:name":"Dwarka Sector 12",
    "wof:placetype":"neighbourhood"
},
  "geometry": {"coordinates":[77.041797,28.594658],"type":"Point"}
}