{
  "type": "Feature",
  "properties": {
    "iso:country":"IN",
    "ks:ks_name":"Barrikheda",
    "ks:ks_pop":0,
    "ks:ks_type":"VILLAGE",
    "name:eng_x_preferred":[
        "Barrikheda"
    ],
    "wof:name":"Barrikheda",
    "wof:placetype":"locality",
    "wof:population":0
},
  "geometry": {"coordinates":[77.573407,24.231276],"type":"Point"}
}