{
  "type": "Feature",
  "properties": {
    "gn:admin1_code":"11.0",
    "gn:admin2_code":"33.0",
    "gn:asciiname":"Mond",
    "gn:country_code":"IN",
    "gn:dem":1424,
    "gn:feature_class":"P",
    "gn:feature_code":"PPL",
    "gn:name":"Mond",
    "gn:population":0,
    "gn:timezone":"Asia/Kolkata",
    "iso:country":"IN",
    "name:als_x_preferred":[
        "Mond"
    ],
    "name:deu_x_preferred":[
        "Mond"
    ],
    "name:heb_x_preferred":[
        "\u05de\u05d5\u05e0\u05d3"
    ],
    "name:ita_x_preferred":[
        "Mond"
    ],
    "name:lim_x_preferred":[
        "Mond"
    ],
    "name:nld_x_preferred":[
        "Mond"
    ],
    "name:urd_x_preferred":[
        "\u0645\u0646\u062f"
    ],
    "wof:name":"Mond",
    "wof:placetype":"locality"
},
  "geometry": {"coordinates":[77.43438,30.98352],"type":"Point"}
}