{
  "type": "Feature",
  "properties": {
    "iso:country":"IN",
    "ks:ks_name":"Makrandpur Manak",
    "ks:ks_pop":627,
    "ks:ks_type":"VILLAGE",
    "ks:ks_uagg_main":0,
    "name:eng_x_preferred":[
        "Makrandpur Manak"
    ],
    "wof:name":"Makrandpur Manak",
    "wof:placetype":"neighbourhood",
    "wof:population":627
},
  "geometry": {"coordinates":[78.43698999999999,29.283453],"type":"Point"}
}