{
  "type": "Feature",
  "properties": {
    "iso:country":"IN",
    "ks:ks_name":"S Annavaram",
    "ks:ks_pop":11058,
    "ks:ks_type":"VILLAGE",
    "ks:ks_uagg_main":0,
    "name:eng_x_preferred":[
        "S Annavaram"
    ],
    "wof:name":"S Annavaram",
    "wof:placetype":"neighbourhood",
    "wof:population":11058
},
  "geometry": {"coordinates":[82.542044,17.344533],"type":"Point"}
}