{
  "type": "Feature",
  "properties": {
    "gn:admin1_code":"24",
    "gn:admin2_code":"106.0",
    "gn:asciiname":"Chandpura",
    "gn:country_code":"IN",
    "gn:dem":259,
    "gn:feature_class":"P",
    "gn:feature_code":"PPL",
    "gn:name":"Ch\u0101ndpura",
    "gn:population":0,
    "gn:timezone":"Asia/Kolkata",
    "iso:country":"IN",
    "ks:ks_alt_nam":"Ch\u0101ndpura",
    "ks:ks_name":"Chandpura",
    "ks:ks_pop":966,
    "ks:ks_type":"VILLAGE",
    "name:eng_x_preferred":[
        "Chandpura"
    ],
    "name:eng_x_variant":[
        "Ch\u0101ndpura"
    ],
    "wof:name":"Chandpura",
    "wof:placetype":"locality",
    "wof:population":966
},
  "geometry": {"coordinates":[77.270731,26.52237],"type":"Point"}
}