{
  "type": "Feature",
  "properties": {
    "iso:country":"IN",
    "ks:ks_name":"Bara Chaparia",
    "ks:ks_pop":272,
    "ks:ks_type":"VILLAGE",
    "name:eng_x_preferred":[
        "Bara Chaparia"
    ],
    "wof:name":"Bara Chaparia",
    "wof:placetype":"locality",
    "wof:population":272
},
  "geometry": {"coordinates":[87.39374100000001,24.459947],"type":"Point"}
}