{
  "type": "Feature",
  "properties": {
    "iso:country":"IN",
    "ks:ks_name":"Ozarwadi",
    "ks:ks_pop":130,
    "ks:ks_type":"HABITATION",
    "name:eng_x_preferred":[
        "Ozarwadi"
    ],
    "wof:name":"Ozarwadi",
    "wof:placetype":"locality",
    "wof:population":130
},
  "geometry": {"coordinates":[73.68000000000001,16.98],"type":"Point"}
}