{
  "type": "Feature",
  "properties": {
    "gn:admin1_code":"12.0",
    "gn:admin2_code":"19.0",
    "gn:asciiname":"Dingi Dhar",
    "gn:country_code":"IN",
    "gn:dem":1290,
    "gn:feature_class":"P",
    "gn:feature_code":"PPL",
    "gn:name":"Ding\u012b Dhar",
    "gn:population":0,
    "gn:timezone":"Asia/Kolkata",
    "iso:country":"IN",
    "wof:name":"Dingi Dhar",
    "wof:placetype":"locality"
},
  "geometry": {"coordinates":[75.01867,33.10149000000001],"type":"Point"}
}