{
  "type": "Feature",
  "properties": {
    "gn:admin1_code":"10",
    "gn:admin2_code":"73.0",
    "gn:asciiname":"Titram",
    "gn:country_code":"IN",
    "gn:dem":236,
    "gn:feature_class":"P",
    "gn:feature_code":"PPL",
    "gn:name":"T\u012btram",
    "gn:population":0,
    "gn:timezone":"Asia/Kolkata",
    "iso:country":"IN",
    "name:hin_x_preferred":[
        "\u0924\u093f\u0924\u0930\u092e"
    ],
    "wof:name":"Titram",
    "wof:placetype":"locality"
},
  "geometry": {"coordinates":[76.40389,29.71808],"type":"Point"}
}