{
  "type": "Feature",
  "properties": {
    "iso:country":"IN",
    "ks:ks_name":"Chandiapipal",
    "ks:ks_pop":633,
    "ks:ks_type":"HABITATION",
    "name:eng_x_preferred":[
        "Chandiapipal"
    ],
    "wof:name":"Chandiapipal",
    "wof:placetype":"locality",
    "wof:population":633
},
  "geometry": {"coordinates":[74.59384799999999,22.12829],"type":"Point"}
}