{
  "type": "Feature",
  "properties": {
    "iso:country":"IN",
    "ks:ks_name":"Chavanwadi",
    "ks:ks_pop":162,
    "ks:ks_type":"HABITATION",
    "name:eng_x_preferred":[
        "Chavanwadi"
    ],
    "wof:name":"Chavanwadi",
    "wof:placetype":"locality",
    "wof:population":162
},
  "geometry": {"coordinates":[73.566041,15.955875],"type":"Point"}
}