{
  "type": "Feature",
  "properties": {
    "gn:admin1_code":"19.0",
    "gn:admin2_code":"578.0",
    "gn:asciiname":"Kirigotara",
    "gn:country_code":"IN",
    "gn:dem":757,
    "gn:feature_class":"P",
    "gn:feature_code":"PPL",
    "gn:name":"Kirigotara",
    "gn:population":0,
    "gn:timezone":"Asia/Kolkata",
    "iso:country":"IN",
    "wof:name":"Kirigotara",
    "wof:placetype":"locality"
},
  "geometry": {"coordinates":[76.84774,11.97349],"type":"Point"}
}