{
  "type": "Feature",
  "properties": {
    "iso:country":"IN",
    "ks:ks_alt_nam":"ROKHRE TOLA",
    "ks:ks_name":"Rokhre Tola",
    "ks:ks_pop":239,
    "ks:ks_type":"HABITATION",
    "name:eng_x_preferred":[
        "Rokhre Tola"
    ],
    "wof:name":"Rokhre Tola",
    "wof:placetype":"locality",
    "wof:population":239
},
  "geometry": {"coordinates":[84.23322899999999,25.415586],"type":"Point"}
}