{
  "type": "Feature",
  "properties": {
    "iso:country":"IN",
    "ks:ks_name":"Nama Bhandertikur",
    "ks:ks_pop":363,
    "ks:ks_type":"HABITATION",
    "name:eng_x_preferred":[
        "Nama Bhandertikur"
    ],
    "wof:name":"Nama Bhandertikur",
    "wof:placetype":"locality",
    "wof:population":363
},
  "geometry": {"coordinates":[88.33093100000001,23.435863],"type":"Point"}
}