{
  "type": "Feature",
  "properties": {
    "iso:country":"IN",
    "ks:ks_name":"Tadupara",
    "ks:ks_pop":543,
    "ks:ks_type":"HABITATION",
    "name:eng_x_preferred":[
        "Tadupara"
    ],
    "wof:name":"Tadupara",
    "wof:placetype":"locality",
    "wof:population":543
},
  "geometry": {"coordinates":[82.71861199999999,21.626899],"type":"Point"}
}