{
  "type": "Feature",
  "properties": {
    "iso:country":"IN",
    "ks:ks_name":"Paschim Singhichhara",
    "ks:ks_pop":7894,
    "ks:ks_type":"VILLAGE",
    "name:eng_x_preferred":[
        "Paschim Singhichhara"
    ],
    "wof:name":"Paschim Singhichhara",
    "wof:placetype":"locality",
    "wof:population":7894
},
  "geometry": {"coordinates":[91.620132,24.082889],"type":"Point"}
}