{
  "type": "Feature",
  "properties": {
    "gn:admin1_code":"28.0",
    "gn:admin2_code":"344",
    "gn:asciiname":"Godapiasal",
    "gn:country_code":"IN",
    "gn:dem":46,
    "gn:feature_class":"P",
    "gn:feature_code":"PPL",
    "gn:name":"God\u0101pi\u0101s\u0101l",
    "gn:population":0,
    "gn:timezone":"Asia/Kolkata",
    "iso:country":"IN",
    "wof:name":"Godapiasal",
    "wof:placetype":"locality"
},
  "geometry": {"coordinates":[87.32783000000001,22.53641],"type":"Point"}
}