{
  "type": "Feature",
  "properties": {
    "gn:admin1_code":"23.0",
    "gn:admin2_code":"49.0",
    "gn:asciiname":"Chawinda",
    "gn:country_code":"IN",
    "gn:dem":238,
    "gn:feature_class":"P",
    "gn:feature_code":"PPL",
    "gn:name":"Chawinda",
    "gn:population":0,
    "gn:timezone":"Asia/Kolkata",
    "iso:country":"IN",
    "name:ceb_x_preferred":[
        "Chawinda"
    ],
    "name:fas_x_preferred":[
        "\u0686\u0648\u0646\u062f\u0647"
    ],
    "name:fra_x_preferred":[
        "Chawinda"
    ],
    "name:hin_x_preferred":[
        "\u091a\u0935\u093f\u0902\u0921\u0939"
    ],
    "name:pan_x_preferred":[
        "\u0a1a\u0a35\u0a3f\u0a70\u0a21\u0a3e"
    ],
    "name:pnb_x_preferred":[
        "\u0686\u0648\u0646\u0688\u06c1"
    ],
    "name:por_x_preferred":[
        "Chawinda"
    ],
    "name:urd_x_preferred":[
        "\u0686\u0648\u0646\u0688\u06c1"
    ],
    "wof:name":"Chawinda",
    "wof:placetype":"locality"
},
  "geometry": {"coordinates":[75.05882,31.72138],"type":"Point"}
}