{
  "type": "Feature",
  "properties": {
    "gn:admin1_code":"19.0",
    "gn:admin2_code":"581.0",
    "gn:asciiname":"Bestarahalli",
    "gn:country_code":"IN",
    "gn:dem":822,
    "gn:feature_class":"P",
    "gn:feature_code":"PPL",
    "gn:name":"Bestarahalli",
    "gn:population":0,
    "gn:timezone":"Asia/Kolkata",
    "iso:country":"IN",
    "wof:name":"Bestarahalli",
    "wof:placetype":"locality"
},
  "geometry": {"coordinates":[78.32106999999998,13.21655],"type":"Point"}
}