{
  "type": "Feature",
  "properties": {
    "gn:admin1_code":"16.0",
    "gn:admin2_code":"511",
    "gn:asciiname":"Digras Khurd",
    "gn:country_code":"IN",
    "gn:dem":494,
    "gn:feature_class":"P",
    "gn:feature_code":"PPL",
    "gn:name":"Digras Khurd",
    "gn:population":0,
    "gn:timezone":"Asia/Kolkata",
    "iso:country":"IN",
    "wof:name":"Digras Khurd",
    "wof:placetype":"neighbourhood"
},
  "geometry": {"coordinates":[77.22399,18.73246],"type":"Point"}
}