{
  "type": "Feature",
  "properties": {
    "iso:country":"IN",
    "ks:ks_alt_nam":"WadeVathar",
    "ks:ks_name":"Wadevathar",
    "ks:ks_pop":218,
    "ks:ks_type":"HABITATION",
    "ks:ks_uagg_main":0,
    "name:eng_x_preferred":[
        "Wadevathar"
    ],
    "wof:name":"Wadevathar",
    "wof:placetype":"neighbourhood",
    "wof:population":218
},
  "geometry": {"coordinates":[73.335703,16.552287],"type":"Point"}
}