{
  "type": "Feature",
  "properties": {
    "iso:country":"IN",
    "ks:ks_name":"Waghdongari",
    "ks:ks_pop":154,
    "ks:ks_type":"VILLAGE",
    "name:eng_x_preferred":[
        "Waghdongari"
    ],
    "wof:name":"Waghdongari",
    "wof:placetype":"locality",
    "wof:population":154
},
  "geometry": {"coordinates":[80.370225,21.308903],"type":"Point"}
}