{
  "type": "Feature",
  "properties": {
    "iso:country":"IN",
    "ks:ks_name":"Mananda",
    "ks:ks_pop":974,
    "ks:ks_type":"VILLAGE",
    "name:eng_x_preferred":[
        "Mananda"
    ],
    "wof:name":"Mananda",
    "wof:placetype":"locality",
    "wof:population":974
},
  "geometry": {"coordinates":[85.62779999999999,21.935689],"type":"Point"}
}