{
  "type": "Feature",
  "properties": {
    "gn:admin1_code":"12.0",
    "gn:admin2_code":"18.0",
    "gn:asciiname":"Nalan",
    "gn:country_code":"IN",
    "gn:dem":2461,
    "gn:feature_class":"P",
    "gn:feature_code":"PPL",
    "gn:name":"Nalan",
    "gn:population":0,
    "gn:timezone":"Asia/Kolkata",
    "iso:country":"IN",
    "name:tur_x_preferred":[
        "Nalan"
    ],
    "wof:name":"Nalan",
    "wof:placetype":"locality"
},
  "geometry": {"coordinates":[75.71043,33.71069],"type":"Point"}
}