{
  "type": "Feature",
  "properties": {
    "iso:country":"IN",
    "ks:ks_alt_nam":"Sadhu para",
    "ks:ks_name":"Sadhu Para",
    "ks:ks_pop":878,
    "ks:ks_type":"HABITATION",
    "name:eng_x_preferred":[
        "Sadhu Para"
    ],
    "wof:name":"Sadhu Para",
    "wof:placetype":"locality",
    "wof:population":878
},
  "geometry": {"coordinates":[91.405205,23.310347],"type":"Point"}
}