{
  "type": "Feature",
  "properties": {
    "iso:country":"IN",
    "ks:ks_name":"Ungamaha",
    "ks:ks_pop":626,
    "ks:ks_type":"VILLAGE",
    "name:eng_x_preferred":[
        "Ungamaha"
    ],
    "wof:name":"Ungamaha",
    "wof:placetype":"locality",
    "wof:population":626
},
  "geometry": {"coordinates":[83.744983,20.061164],"type":"Point"}
}