{
  "type": "Feature",
  "properties": {
    "gn:admin1_code":"9.0",
    "gn:admin2_code":"480",
    "gn:asciiname":"Chhara",
    "gn:country_code":"IN",
    "gn:dem":16,
    "gn:feature_class":"P",
    "gn:feature_code":"PPL",
    "gn:name":"Chh\u0101ra",
    "gn:population":0,
    "gn:timezone":"Asia/Kolkata",
    "iso:country":"IN",
    "name:ceb_x_preferred":[
        "Chh\u0101ra"
    ],
    "name:spa_x_preferred":[
        "Chhara"
    ],
    "name:swe_x_preferred":[
        "Chh\u0101ra"
    ],
    "wof:name":"Chhara",
    "wof:placetype":"locality"
},
  "geometry": {"coordinates":[70.71581999999999,20.74245],"type":"Point"}
}