{
  "type": "Feature",
  "properties": {
    "iso:country":"IN",
    "ks:ks_name":"Tola Butatari",
    "ks:ks_pop":0,
    "ks:ks_type":"VILLAGE",
    "name:eng_x_preferred":[
        "Tola Butatari"
    ],
    "wof:name":"Tola Butatari",
    "wof:placetype":"locality",
    "wof:population":0
},
  "geometry": {"coordinates":[86.860052,24.561187],"type":"Point"}
}