{
  "type": "Feature",
  "properties": {
    "gn:admin1_code":"35.0",
    "gn:admin2_code":"442.0",
    "gn:asciiname":"Chainpura",
    "gn:country_code":"IN",
    "gn:dem":405,
    "gn:feature_class":"P",
    "gn:feature_code":"PPL",
    "gn:name":"Chainpura",
    "gn:population":0,
    "gn:timezone":"Asia/Kolkata",
    "iso:country":"IN",
    "wof:name":"Chainpura",
    "wof:placetype":"locality"
},
  "geometry": {"coordinates":[76.43339,24.03068],"type":"Point"}
}