{
  "type": "Feature",
  "properties": {
    "gn:admin1_code":"36",
    "gn:admin2_code":"138.0",
    "gn:asciiname":"Gesupur Shimali",
    "gn:country_code":"IN",
    "gn:dem":223,
    "gn:feature_class":"P",
    "gn:feature_code":"PPL",
    "gn:name":"Gesupur Shim\u0101l\u012b",
    "gn:population":0,
    "gn:timezone":"Asia/Kolkata",
    "iso:country":"IN",
    "ks:ks_name":"Gesupur Shumali",
    "ks:ks_pop":1784,
    "ks:ks_type":"VILLAGE",
    "ks:ks_uagg_main":0,
    "name:eng_x_preferred":[
        "Gesupur Shumali"
    ],
    "wof:name":"Gesupur Shumali",
    "wof:placetype":"neighbourhood",
    "wof:population":1784
},
  "geometry": {"coordinates":[78.015649,28.939567],"type":"Point"}
}