{
  "type": "Feature",
  "properties": {
    "iso:country":"IN",
    "ks:ks_alt_nam":"HIDAYETPUR",
    "ks:ks_name":"Hidayetpur",
    "ks:ks_pop":1121,
    "ks:ks_type":"HABITATION",
    "name:eng_x_preferred":[
        "Hidayetpur"
    ],
    "wof:name":"Hidayetpur",
    "wof:placetype":"locality",
    "wof:population":1121
},
  "geometry": {"coordinates":[89.22373899999999,26.676864],"type":"Point"}
}