{
  "type": "Feature",
  "properties": {
    "gn:admin1_code":"13.0",
    "gn:admin2_code":"600.0",
    "gn:asciiname":"Mannur",
    "gn:country_code":"IN",
    "gn:dem":83,
    "gn:feature_class":"P",
    "gn:feature_code":"PPL",
    "gn:name":"Mann\u016br",
    "gn:population":0,
    "gn:timezone":"Asia/Kolkata",
    "iso:country":"IN",
    "name:ceb_x_preferred":[
        "Mann\u016br"
    ],
    "name:swe_x_preferred":[
        "Mann\u016br"
    ],
    "wof:name":"Mannur",
    "wof:placetype":"neighbourhood"
},
  "geometry": {"coordinates":[76.94248,8.87879],"type":"Point"}
}