{
  "type": "Feature",
  "properties": {
    "gn:admin1_code":"25.0",
    "gn:admin2_code":"605.0",
    "gn:asciiname":"Yalavandapudur",
    "gn:country_code":"IN",
    "gn:dem":655,
    "gn:feature_class":"P",
    "gn:feature_code":"PPL",
    "gn:name":"Yalavandapud\u016br",
    "gn:population":0,
    "gn:timezone":"Asia/Kolkata",
    "iso:country":"IN",
    "wof:name":"Yalavandapudur",
    "wof:placetype":"locality"
},
  "geometry": {"coordinates":[78.9966,12.75184],"type":"Point"}
}