{
  "type": "Feature",
  "properties": {
    "iso:country":"IN",
    "ks:ks_name":"Kinnir Keri",
    "ks:ks_pop":124,
    "ks:ks_type":"HABITATION",
    "name:eng_x_preferred":[
        "Kinnir Keri"
    ],
    "wof:name":"Kinnir Keri",
    "wof:placetype":"locality",
    "wof:population":124
},
  "geometry": {"coordinates":[74.485028,14.246774],"type":"Point"}
}