{
  "type": "Feature",
  "properties": {
    "gn:admin1_code":"36",
    "gn:admin2_code":"188.0",
    "gn:asciiname":"Aunratari",
    "gn:country_code":"IN",
    "gn:dem":79,
    "gn:feature_class":"P",
    "gn:feature_code":"PPL",
    "gn:name":"Aunr\u0101t\u0101ri",
    "gn:population":0,
    "gn:timezone":"Asia/Kolkata",
    "iso:country":"IN",
    "ks:ks_name":"Aura Tari",
    "ks:ks_pop":7,
    "ks:ks_type":"VILLAGE",
    "ks:ks_uagg_main":0,
    "name:eng_x_preferred":[
        "Aura Tari"
    ],
    "wof:name":"Aura Tari",
    "wof:placetype":"neighbourhood",
    "wof:population":7
},
  "geometry": {"coordinates":[83.349765,26.650297],"type":"Point"}
}