{
  "type": "Feature",
  "properties": {
    "iso:country":"IN",
    "ks:ks_name":"Gujottu",
    "ks:ks_pop":260,
    "ks:ks_type":"HABITATION",
    "name:eng_x_preferred":[
        "Gujottu"
    ],
    "wof:name":"Gujottu",
    "wof:placetype":"locality",
    "wof:population":260
},
  "geometry": {"coordinates":[75.146959,13.080122],"type":"Point"}
}