{
  "type": "Feature",
  "properties": {
    "iso:country":"IN",
    "ks:ks_name":"Harijana Collony",
    "ks:ks_pop":108,
    "ks:ks_type":"HABITATION",
    "name:eng_x_preferred":[
        "Harijana Collony"
    ],
    "wof:name":"Harijana Collony",
    "wof:placetype":"locality",
    "wof:population":108
},
  "geometry": {"coordinates":[75.858611,12.494167],"type":"Point"}
}