{
  "type": "Feature",
  "properties": {
    "iso:country":"IN",
    "ks:ks_name":"China Gumuda",
    "ks:ks_pop":63,
    "ks:ks_type":"HABITATION",
    "name:eng_x_preferred":[
        "China Gumuda"
    ],
    "wof:name":"China Gumuda",
    "wof:placetype":"locality",
    "wof:population":63
},
  "geometry": {"coordinates":[84.25491599999999,18.78478],"type":"Point"}
}