{
  "type": "Feature",
  "properties": {
    "iso:country":"IN",
    "ks:ks_name":"Palluparamb",
    "ks:ks_pop":406,
    "ks:ks_type":"HABITATION",
    "name:eng_x_preferred":[
        "Palluparamb"
    ],
    "wof:name":"Palluparamb",
    "wof:placetype":"locality",
    "wof:population":406
},
  "geometry": {"coordinates":[76.45475999999999,10.603927],"type":"Point"}
}