{
  "type": "Feature",
  "properties": {
    "iso:country":"IN",
    "ks:ks_name":"Geramari",
    "ks:ks_pop":141,
    "ks:ks_type":"HABITATION",
    "name:eng_x_preferred":[
        "Geramari"
    ],
    "wof:name":"Geramari",
    "wof:placetype":"locality",
    "wof:population":141
},
  "geometry": {"coordinates":[90.282864,26.167516],"type":"Point"}
}