{
  "type": "Feature",
  "properties": {
    "iso:country":"IN",
    "ks:ks_name":"Khaddhuwa",
    "ks:ks_pop":1135,
    "ks:ks_type":"VILLAGE",
    "ks:ks_uagg_main":0,
    "name:eng_x_preferred":[
        "Khaddhuwa"
    ],
    "wof:name":"Khaddhuwa",
    "wof:placetype":"neighbourhood",
    "wof:population":1135
},
  "geometry": {"coordinates":[83.406679,22.972619],"type":"Point"}
}