{
  "type": "Feature",
  "properties": {
    "iso:country":"IN",
    "ks:ks_name":"Simana",
    "ks:ks_pop":152,
    "ks:ks_type":"VILLAGE",
    "name:eng_x_preferred":[
        "Simana"
    ],
    "wof:name":"Simana",
    "wof:placetype":"locality",
    "wof:population":152
},
  "geometry": {"coordinates":[87.52256300000001,22.412308],"type":"Point"}
}