{
  "type": "Feature",
  "properties": {
    "iso:country":"IN",
    "ks:ks_alt_nam":"paswan tola",
    "ks:ks_name":"Paswan Tola",
    "ks:ks_pop":950,
    "ks:ks_type":"HABITATION",
    "ks:ks_uagg_main":0,
    "name:eng_x_preferred":[
        "Paswan Tola"
    ],
    "wof:name":"Paswan Tola",
    "wof:placetype":"neighbourhood",
    "wof:population":950
},
  "geometry": {"coordinates":[86.470449,25.704972],"type":"Point"}
}