{
  "type": "Feature",
  "properties": {
    "gn:admin1_code":"36.0",
    "gn:admin2_code":"171.0",
    "gn:asciiname":"Barhaiya",
    "gn:country_code":"IN",
    "gn:dem":235,
    "gn:feature_class":"P",
    "gn:feature_code":"PPL",
    "gn:name":"Barhaiya",
    "gn:population":0,
    "gn:timezone":"Asia/Kolkata",
    "iso:country":"IN",
    "wof:name":"Barhaiya",
    "wof:placetype":"locality"
},
  "geometry": {"coordinates":[81.12787,25.06169],"type":"Point"}
}