{
  "type": "Feature",
  "properties": {
    "iso:country":"IN",
    "ks:ks_name":"Sunyura Talla",
    "ks:ks_pop":100,
    "ks:ks_type":"HABITATION",
    "name:eng_x_preferred":[
        "Sunyura Talla"
    ],
    "wof:name":"Sunyura Talla",
    "wof:placetype":"locality",
    "wof:population":100
},
  "geometry": {"coordinates":[79.935909,29.832737],"type":"Point"}
}