{
  "type": "Feature",
  "properties": {
    "iso:country":"IN",
    "ks:ks_name":"Barsara",
    "ks:ks_pop":1389,
    "ks:ks_type":"VILLAGE",
    "ks:ks_uagg_main":0,
    "name:eng_x_preferred":[
        "Barsara"
    ],
    "wof:name":"Barsara",
    "wof:placetype":"locality",
    "wof:population":1389
},
  "geometry": {"coordinates":[84.447839,26.330455],"type":"Point"}
}