{
  "type": "Feature",
  "properties": {
    "iso:country":"IN",
    "ks:ks_name":"Shalkota",
    "ks:ks_pop":374,
    "ks:ks_type":"VILLAGE",
    "name:eng_x_preferred":[
        "Shalkota"
    ],
    "wof:name":"Shalkota",
    "wof:placetype":"locality",
    "wof:population":374
},
  "geometry": {"coordinates":[87.462424,23.131804],"type":"Point"}
}