{
  "type": "Feature",
  "properties": {
    "iso:country":"IN",
    "ks:ks_name":"Malaguda",
    "ks:ks_pop":58,
    "ks:ks_type":"HABITATION",
    "name:eng_x_preferred":[
        "Malaguda"
    ],
    "wof:name":"Malaguda",
    "wof:placetype":"locality",
    "wof:population":58
},
  "geometry": {"coordinates":[79.291177,19.174012],"type":"Point"}
}