{
  "type": "Feature",
  "properties": {
    "iso:country":"IN",
    "ks:ks_name":"Milkiyan",
    "ks:ks_pop":103,
    "ks:ks_type":"HABITATION",
    "ks:ks_uagg_main":0,
    "name:eng_x_preferred":[
        "Milkiyan"
    ],
    "wof:name":"Milkiyan",
    "wof:placetype":"neighbourhood",
    "wof:population":103
},
  "geometry": {"coordinates":[82.581605,25.968511],"type":"Point"}
}