{
  "type": "Feature",
  "properties": {
    "gn:admin1_code":"12.0",
    "gn:asciiname":"Girinar",
    "gn:country_code":"IN",
    "gn:dem":2071,
    "gn:feature_class":"P",
    "gn:feature_code":"PPL",
    "gn:name":"Girin\u0101r",
    "gn:population":0,
    "gn:timezone":"Asia/Kolkata",
    "iso:country":"IN",
    "name:und_x_variant":[
        "Girin\u0101r",
        "Girlo\u0101r",
        "Glrin\u0101r"
    ],
    "wof:name":"Girinar",
    "wof:placetype":"locality"
},
  "geometry": {"coordinates":[73.93956999999997,34.0685],"type":"Point"}
}