{
  "type": "Feature",
  "properties": {
    "iso:country":"IN",
    "ks:ks_name":"Argari",
    "ks:ks_pop":9522,
    "ks:ks_type":"VILLAGE",
    "ks:ks_uagg_main":0,
    "name:eng_x_preferred":[
        "Argari"
    ],
    "wof:name":"Argari",
    "wof:placetype":"neighbourhood",
    "wof:population":9522
},
  "geometry": {"coordinates":[88.22610400000001,22.590876],"type":"Point"}
}