{
  "type": "Feature",
  "properties": {
    "gn:admin1_code":"36",
    "gn:admin2_code":"155.0",
    "gn:asciiname":"Ramapur Bich",
    "gn:country_code":"IN",
    "gn:dem":135,
    "gn:feature_class":"P",
    "gn:feature_code":"PPL",
    "gn:name":"R\u0101m\u0101pur B\u012bch",
    "gn:population":0,
    "gn:timezone":"Asia/Kolkata",
    "iso:country":"IN",
    "wof:name":"Ramapur Bich",
    "wof:placetype":"neighbourhood"
},
  "geometry": {"coordinates":[79.91070000000001,27.36404],"type":"Point"}
}