{
  "type": "Feature",
  "properties": {
    "iso:country":"IN",
    "ks:ks_alt_nam":"Saberajina muwada",
    "ks:ks_name":"Saberajina Muwada",
    "ks:ks_pop":490,
    "ks:ks_type":"HABITATION",
    "name:eng_x_preferred":[
        "Saberajina Muwada"
    ],
    "wof:name":"Saberajina Muwada",
    "wof:placetype":"locality",
    "wof:population":490
},
  "geometry": {"coordinates":[72.946472,23.281556],"type":"Point"}
}