{
  "type": "Feature",
  "properties": {
    "iso:country":"IN",
    "ks:ks_name":"Malwadi",
    "ks:ks_pop":150,
    "ks:ks_type":"HABITATION",
    "name:eng_x_preferred":[
        "Malwadi"
    ],
    "wof:name":"Malwadi",
    "wof:placetype":"locality",
    "wof:population":150
},
  "geometry": {"coordinates":[74.360721,19.492187],"type":"Point"}
}