{
  "type": "Feature",
  "properties": {
    "gn:admin1_code":"36.0",
    "gn:admin2_code":"148",
    "gn:asciiname":"Joga Khurd",
    "gn:country_code":"IN",
    "gn:dem":154,
    "gn:feature_class":"P",
    "gn:feature_code":"PPL",
    "gn:name":"Joga Khurd",
    "gn:population":0,
    "gn:timezone":"Asia/Kolkata",
    "iso:country":"IN",
    "wof:name":"Joga Khurd",
    "wof:placetype":"neighbourhood"
},
  "geometry": {"coordinates":[79.32901,27.19825],"type":"Point"}
}