{
  "type": "Feature",
  "properties": {
    "gn:admin1_code":"34.0",
    "gn:admin2_code":"236.0",
    "gn:asciiname":"Salaitanr",
    "gn:country_code":"IN",
    "gn:dem":225,
    "gn:feature_class":"P",
    "gn:feature_code":"PPL",
    "gn:name":"Salait\u0101nr",
    "gn:population":0,
    "gn:timezone":"Asia/Kolkata",
    "iso:country":"IN",
    "wof:name":"Salaitanr",
    "wof:placetype":"locality"
},
  "geometry": {"coordinates":[84.46626999999999,24.39601],"type":"Point"}
}