{
  "type": "Feature",
  "properties": {
    "iso:country":"IN",
    "ks:ks_name":"Lokeisuni",
    "ks:ks_pop":98,
    "ks:ks_type":"HABITATION",
    "name:eng_x_preferred":[
        "Lokeisuni"
    ],
    "wof:name":"Lokeisuni",
    "wof:placetype":"locality",
    "wof:population":98
},
  "geometry": {"coordinates":[84.40131700000001,19.139534],"type":"Point"}
}