{
  "type": "Feature",
  "properties": {
    "iso:country":"IN",
    "ks:ks_name":"Nagal Durgasi",
    "ks:ks_pop":913,
    "ks:ks_type":"HABITATION",
    "name:eng_x_preferred":[
        "Nagal Durgasi"
    ],
    "wof:name":"Nagal Durgasi",
    "wof:placetype":"locality",
    "wof:population":913
},
  "geometry": {"coordinates":[77.192511,26.772061],"type":"Point"}
}