{
  "type": "Feature",
  "properties": {
    "iso:country":"IN",
    "ks:ks_name":"Panchmani",
    "ks:ks_pop":53,
    "ks:ks_type":"VILLAGE",
    "name:eng_x_preferred":[
        "Panchmani"
    ],
    "wof:name":"Panchmani",
    "wof:placetype":"locality",
    "wof:population":53
},
  "geometry": {"coordinates":[78.758385,29.933409],"type":"Point"}
}