{
  "type": "Feature",
  "properties": {
    "gn:admin1_code":"39",
    "gn:admin2_code":"60.0",
    "gn:asciiname":"Sarni",
    "gn:country_code":"IN",
    "gn:dem":2102,
    "gn:feature_class":"P",
    "gn:feature_code":"PPL",
    "gn:name":"S\u0101rni",
    "gn:population":0,
    "gn:timezone":"Asia/Kolkata",
    "iso:country":"IN",
    "ks:ks_alt_nam":"S\u0101rni",
    "ks:ks_name":"Sarni",
    "ks:ks_pop":230,
    "ks:ks_type":"VILLAGE",
    "name:eng_x_preferred":[
        "Sarni"
    ],
    "name:eng_x_variant":[
        "S\u0101rni"
    ],
    "wof:name":"Sarni",
    "wof:placetype":"locality",
    "wof:population":230
},
  "geometry": {"coordinates":[77.91701500000001,30.839231],"type":"Point"}
}