{
  "type": "Feature",
  "properties": {
    "iso:country":"IN",
    "ks:ks_name":"Mudariya Ramnaval",
    "ks:ks_pop":29,
    "ks:ks_type":"HABITATION",
    "name:eng_x_preferred":[
        "Mudariya Ramnaval"
    ],
    "wof:name":"Mudariya Ramnaval",
    "wof:placetype":"locality",
    "wof:population":29
},
  "geometry": {"coordinates":[81.858102,24.682536],"type":"Point"}
}