{
  "type": "Feature",
  "properties": {
    "iso:country":"IN",
    "ks:ks_name":"Sainti Gunth",
    "ks:ks_pop":291,
    "ks:ks_type":"HABITATION",
    "name:eng_x_preferred":[
        "Sainti Gunth"
    ],
    "wof:name":"Sainti Gunth",
    "wof:placetype":"locality",
    "wof:population":291
},
  "geometry": {"coordinates":[79.448098,30.236551],"type":"Point"}
}