{
  "type": "Feature",
  "properties": {
    "gn:admin1_code":"35",
    "gn:admin2_code":"447.0",
    "gn:asciiname":"Chhipnia",
    "gn:country_code":"IN",
    "gn:dem":743,
    "gn:feature_class":"P",
    "gn:feature_code":"PPL",
    "gn:name":"Chhipnia",
    "gn:population":0,
    "gn:timezone":"Asia/Kolkata",
    "iso:country":"IN",
    "wof:name":"Chhipnia",
    "wof:placetype":"locality"
},
  "geometry": {"coordinates":[78.29465999999999,22.01183],"type":"Point"}
}