{
  "type": "Feature",
  "properties": {
    "iso:country":"IN",
    "ks:ks_name":"Sorekaipura",
    "ks:ks_pop":180,
    "ks:ks_type":"HABITATION",
    "name:eng_x_preferred":[
        "Sorekaipura"
    ],
    "wof:name":"Sorekaipura",
    "wof:placetype":"locality",
    "wof:population":180
},
  "geometry": {"coordinates":[76.51069,12.883282],"type":"Point"}
}