{
  "type": "Feature",
  "properties": {
    "iso:country":"IN",
    "ks:ks_name":"Kandhahiriba",
    "ks:ks_pop":105,
    "ks:ks_type":"VILLAGE",
    "name:eng_x_preferred":[
        "Kandhahiriba"
    ],
    "wof:name":"Kandhahiriba",
    "wof:placetype":"locality",
    "wof:population":105
},
  "geometry": {"coordinates":[83.640383,19.53648],"type":"Point"}
}