{
  "type": "Feature",
  "properties": {
    "gn:admin1_code":"12.0",
    "gn:admin2_code":"009",
    "gn:asciiname":"Guripur",
    "gn:country_code":"IN",
    "gn:dem":1593,
    "gn:feature_class":"P",
    "gn:feature_code":"PPL",
    "gn:name":"G\u016bripur",
    "gn:population":0,
    "gn:timezone":"Asia/Kolkata",
    "iso:country":"IN",
    "name:und_x_variant":[
        "G\u016bripur",
        "Guripur"
    ],
    "wof:name":"Guripur",
    "wof:placetype":"locality"
},
  "geometry": {"coordinates":[74.43331999999999,34.36212],"type":"Point"}
}