{
  "type": "Feature",
  "properties": {
    "gn:admin1_code":"36.0",
    "gn:admin2_code":"193.0",
    "gn:asciiname":"Sahatwar",
    "gn:country_code":"IN",
    "gn:dem":65,
    "gn:feature_class":"P",
    "gn:feature_code":"PPL",
    "gn:name":"Sahatw\u0101r",
    "gn:population":0,
    "gn:timezone":"Asia/Kolkata",
    "iso:country":"IN",
    "name:bih_x_preferred":[
        "\u0938\u0939\u0924\u0935\u093e\u0930"
    ],
    "name:bpy_x_preferred":[
        "\u09b8\u09be\u09b9\u09be\u09a4\u09f1\u09be\u09b0"
    ],
    "name:hin_x_preferred":[
        "\u0938\u0939\u0924\u0935\u093e\u0930"
    ],
    "name:ita_x_preferred":[
        "Sahatwar"
    ],
    "name:msa_x_preferred":[
        "Sahatwar"
    ],
    "name:nld_x_preferred":[
        "Sahatwar"
    ],
    "name:pol_x_preferred":[
        "Sahatwar"
    ],
    "name:por_x_preferred":[
        "Sahatwar"
    ],
    "name:urd_x_preferred":[
        "\u0635\u062d\u062a\u0648\u0631"
    ],
    "name:vie_x_preferred":[
        "Sahatwar"
    ],
    "name:zho_x_preferred":[
        "\u8428\u54c8\u7279\u74e6\u5c14"
    ],
    "wof:name":"Sahatwar",
    "wof:placetype":"locality"
},
  "geometry": {"coordinates":[84.30441999999999,25.83434],"type":"Point"}
}