{
  "type": "Feature",
  "properties": {
    "iso:country":"IN",
    "ks:ks_alt_nam":"UHARIA KALYANPUR MATHIYA",
    "ks:ks_name":"Uharia Kalyanpur Mathiya",
    "ks:ks_pop":163,
    "ks:ks_type":"HABITATION",
    "name:eng_x_preferred":[
        "Uharia Kalyanpur Mathiya"
    ],
    "wof:name":"Uharia Kalyanpur Mathiya",
    "wof:placetype":"locality",
    "wof:population":163
},
  "geometry": {"coordinates":[84.66624,26.40779],"type":"Point"}
}