{
  "type": "Feature",
  "properties": {
    "gn:admin1_code":"19.0",
    "gn:admin2_code":"569.0",
    "gn:asciiname":"Kamalashile",
    "gn:country_code":"IN",
    "gn:dem":78,
    "gn:feature_class":"P",
    "gn:feature_code":"PPL",
    "gn:name":"Kamalashile",
    "gn:population":0,
    "gn:timezone":"Asia/Kolkata",
    "iso:country":"IN",
    "ks:ks_name":"Kamalashile",
    "ks:ks_pop":1392,
    "ks:ks_type":"VILLAGE",
    "name:eng_x_preferred":[
        "Kamalashile"
    ],
    "wof:name":"Kamalashile",
    "wof:placetype":"locality",
    "wof:population":1392
},
  "geometry": {"coordinates":[74.899175,13.736854],"type":"Point"}
}