{
  "type": "Feature",
  "properties": {
    "iso:country":"IN",
    "ks:ks_name":"Sadholi Kadim",
    "ks:ks_pop":3096,
    "ks:ks_type":"VILLAGE",
    "ks:ks_uagg_main":0,
    "name:eng_x_preferred":[
        "Sadholi Kadim"
    ],
    "wof:name":"Sadholi Kadim",
    "wof:placetype":"neighbourhood",
    "wof:population":3096
},
  "geometry": {"coordinates":[77.57265200000001,30.200966],"type":"Point"}
}