{
  "type": "Feature",
  "properties": {
    "gn:admin1_code":"39",
    "gn:admin2_code":"61.0",
    "gn:asciiname":"Bali",
    "gn:country_code":"IN",
    "gn:dem":1511,
    "gn:feature_class":"P",
    "gn:feature_code":"PPL",
    "gn:name":"B\u0101li",
    "gn:population":0,
    "gn:timezone":"Asia/Kolkata",
    "iso:country":"IN",
    "name:ace_x_preferred":[
        "Bali"
    ],
    "name:ara_x_preferred":[
        "\u0628\u0627\u0644\u064a"
    ],
    "name:ben_bn_x_preferred":[
        "\u09ac\u09be\u09b2\u09bf"
    ],
    "name:ben_in_x_preferred":[
        "\u09ac\u09be\u09b2\u09bf"
    ],
    "name:ceb_x_preferred":[
        "Provinsi Bali"
    ],
    "name:est_x_preferred":[
        "Bali provints"
    ],
    "name:fra_x_preferred":[
        "Bali"
    ],
    "name:gor_x_preferred":[
        "Bali"
    ],
    "name:guj_x_preferred":[
        "\u0aac\u0ab2\u0ac0"
    ],
    "name:hin_x_preferred":[
        "\u092c\u093e\u0932\u0940"
    ],
    "name:ind_x_preferred":[
        "Bali"
    ],
    "name:jav_x_preferred":[
        "Bali"
    ],
    "name:jpn_x_preferred":[
        "\u30d0\u30ea\u5dde"
    ],
    "name:kan_x_preferred":[
        "\u0cac\u0cbe\u0cb2\u0cbf"
    ],
    "name:kor_x_preferred":[
        "\ubc1c\ub9ac\uc8fc"
    ],
    "name:lav_x_preferred":[
        "Bali"
    ],
    "name:mal_x_preferred":[
        "\u0d2c\u0d3e\u0d32\u0d3f"
    ],
    "name:mar_x_preferred":[
        "\u092c\u093e\u0932\u0940"
    ],
    "name:pan_x_preferred":[
        "\u0a2c\u0a3e\u0a32\u0a40"
    ],
    "name:pol_x_preferred":[
        "Bali"
    ],
    "name:rus_x_preferred":[
        "\u0411\u0430\u043b\u0438"
    ],
    "name:swe_x_preferred":[
        "Bali"
    ],
    "name:tam_x_preferred":[
        "\u0baa\u0bb2\u0bbf"
    ],
    "name:tel_x_preferred":[
        "\u0c2c\u0c3e\u0c32\u0c3f"
    ],
    "name:tur_x_preferred":[
        "Bali"
    ],
    "name:urd_x_preferred":[
        "\u0628\u0627\u0644\u06cc"
    ],
    "name:war_x_preferred":[
        "Bali"
    ],
    "name:zho_x_preferred":[
        "\u5df4\u5398\u5c9b"
    ],
    "wof:name":"Bali",
    "wof:placetype":"locality"
},
  "geometry": {"coordinates":[78.8798,29.76854],"type":"Point"}
}