{
  "type": "Feature",
  "properties": {
    "iso:country":"IN",
    "ks:ks_alt_nam":"HUNATPURA",
    "ks:ks_name":"Hunatpura",
    "ks:ks_pop":815,
    "ks:ks_type":"HABITATION",
    "name:eng_x_preferred":[
        "Hunatpura"
    ],
    "wof:name":"Hunatpura",
    "wof:placetype":"locality",
    "wof:population":815
},
  "geometry": {"coordinates":[73.796322,29.644489],"type":"Point"}
}