{
  "type": "Feature",
  "properties": {
    "gn:admin1_code":"21.0",
    "gn:admin2_code":"396.0",
    "gn:asciiname":"Kodiguda",
    "gn:country_code":"IN",
    "gn:dem":779,
    "gn:feature_class":"P",
    "gn:feature_code":"PPL",
    "gn:name":"Kodiguda",
    "gn:population":0,
    "gn:timezone":"Asia/Kolkata",
    "iso:country":"IN",
    "ks:ks_name":"Kodiguda",
    "ks:ks_pop":221,
    "ks:ks_type":"VILLAGE",
    "name:eng_x_preferred":[
        "Kodiguda"
    ],
    "wof:name":"Kodiguda",
    "wof:placetype":"locality",
    "wof:population":221
},
  "geometry": {"coordinates":[83.04819999999999,19.4426],"type":"Point"}
}