{
  "type": "Feature",
  "properties": {
    "gn:admin1_code":"38.0",
    "gn:admin2_code":"362.0",
    "gn:asciiname":"Bhalsumia",
    "gn:country_code":"IN",
    "gn:dem":122,
    "gn:feature_class":"P",
    "gn:feature_code":"PPL",
    "gn:name":"Bh\u0101lsumia",
    "gn:population":0,
    "gn:timezone":"Asia/Kolkata",
    "iso:country":"IN",
    "ks:ks_alt_nam":"Bh\u0101lsumia",
    "ks:ks_name":"Bhalsumia",
    "ks:ks_pop":403,
    "ks:ks_type":"VILLAGE",
    "name:eng_x_preferred":[
        "Bhalsumia"
    ],
    "name:eng_x_variant":[
        "Bh\u0101lsumia"
    ],
    "wof:name":"Bhalsumia",
    "wof:placetype":"locality",
    "wof:population":403
},
  "geometry": {"coordinates":[87.565191,24.321023],"type":"Point"}
}