{
  "type": "Feature",
  "properties": {
    "iso:country":"IN",
    "ks:ks_name":"Targari",
    "ks:ks_pop":3000,
    "ks:ks_type":"VILLAGE",
    "ks:ks_uagg_main":0,
    "name:eng_x_preferred":[
        "Targari"
    ],
    "wof:name":"Targari",
    "wof:placetype":"neighbourhood",
    "wof:population":3000
},
  "geometry": {"coordinates":[85.10978799999999,23.327643],"type":"Point"}
}