{
  "type": "Feature",
  "properties": {
    "iso:country":"IN",
    "ks:ks_name":"Ringewadi",
    "ks:ks_pop":281,
    "ks:ks_type":"HABITATION",
    "name:eng_x_preferred":[
        "Ringewadi"
    ],
    "wof:name":"Ringewadi",
    "wof:placetype":"locality",
    "wof:population":281
},
  "geometry": {"coordinates":[73.816427,16.563342],"type":"Point"}
}