{
  "type": "Feature",
  "properties": {
    "iso:country":"IN",
    "ks:ks_name":"Manguvai",
    "ks:ks_pop":155,
    "ks:ks_type":"HABITATION",
    "name:eng_x_preferred":[
        "Manguvai"
    ],
    "wof:name":"Manguvai",
    "wof:placetype":"locality",
    "wof:population":155
},
  "geometry": {"coordinates":[80.95737,17.666522],"type":"Point"}
}