{
  "type": "Feature",
  "properties": {
    "iso:country":"IN",
    "ks:ks_alt_nam":"Sydari jamin",
    "ks:ks_name":"Sydari Jamin",
    "ks:ks_pop":58,
    "ks:ks_type":"HABITATION",
    "name:eng_x_preferred":[
        "Sydari Jamin"
    ],
    "wof:name":"Sydari Jamin",
    "wof:placetype":"locality",
    "wof:population":58
},
  "geometry": {"coordinates":[79.09082100000001,29.744789],"type":"Point"}
}