{
  "type": "Feature",
  "properties": {
    "iso:country":"IN",
    "ks:ks_name":"Gaothanwadi",
    "ks:ks_pop":15,
    "ks:ks_type":"HABITATION",
    "name:eng_x_preferred":[
        "Gaothanwadi"
    ],
    "wof:name":"Gaothanwadi",
    "wof:placetype":"locality",
    "wof:population":15
},
  "geometry": {"coordinates":[73.379786,17.443611],"type":"Point"}
}