{
  "type": "Feature",
  "properties": {
    "iso:country":"IN",
    "ks:ks_name":"Muduba Coffee Estate",
    "ks:ks_pop":116,
    "ks:ks_type":"HABITATION",
    "name:eng_x_preferred":[
        "Muduba Coffee Estate"
    ],
    "wof:name":"Muduba Coffee Estate",
    "wof:placetype":"locality",
    "wof:population":116
},
  "geometry": {"coordinates":[75.448108,13.715037],"type":"Point"}
}