{
  "type": "Feature",
  "properties": {
    "gn:admin1_code":"10.0",
    "gn:admin2_code":"81.0",
    "gn:asciiname":"Dohki",
    "gn:country_code":"IN",
    "gn:dem":219,
    "gn:feature_class":"P",
    "gn:feature_code":"PPL",
    "gn:name":"Dohki",
    "gn:population":0,
    "gn:timezone":"Asia/Kolkata",
    "iso:country":"IN",
    "wof:name":"Dohki",
    "wof:placetype":"locality"
},
  "geometry": {"coordinates":[76.16416,28.66377],"type":"Point"}
}