{
  "type": "Feature",
  "properties": {
    "iso:country":"IN",
    "ks:ks_name":"Dindwad",
    "ks:ks_pop":210,
    "ks:ks_type":"VILLAGE",
    "name:eng_x_preferred":[
        "Dindwad"
    ],
    "wof:name":"Dindwad",
    "wof:placetype":"locality",
    "wof:population":210
},
  "geometry": {"coordinates":[74.13065,22.216167],"type":"Point"}
}