{
  "type": "Feature",
  "properties": {
    "gn:admin1_code":"25.0",
    "gn:admin2_code":"633.0",
    "gn:asciiname":"Palaiyur",
    "gn:country_code":"IN",
    "gn:dem":415,
    "gn:feature_class":"P",
    "gn:feature_code":"PPL",
    "gn:name":"Palaiy\u016br",
    "gn:population":0,
    "gn:timezone":"Asia/Kolkata",
    "iso:country":"IN",
    "name:tam_x_preferred":[
        "\u0baa\u0bbe\u0bb2\u0bc8\u0baf\u0bc2\u0bb0\u0bcd"
    ],
    "wof:name":"Palaiyur",
    "wof:placetype":"locality"
},
  "geometry": {"coordinates":[77.24205000000001,10.95883],"type":"Point"}
}