{
  "type": "Feature",
  "properties": {
    "gn:admin1_code":"39.0",
    "gn:admin2_code":"64.0",
    "gn:asciiname":"Sialkhet",
    "gn:country_code":"IN",
    "gn:dem":1210,
    "gn:feature_class":"P",
    "gn:feature_code":"PPL",
    "gn:name":"Si\u0101lkhet",
    "gn:population":0,
    "gn:timezone":"Asia/Kolkata",
    "iso:country":"IN",
    "ks:ks_name":"Syali Khet",
    "ks:ks_pop":125,
    "ks:ks_type":"VILLAGE",
    "name:eng_x_preferred":[
        "Syali Khet"
    ],
    "name:eng_x_variant":[
        "Sialkhet"
    ],
    "wof:name":"Syali Khet",
    "wof:placetype":"locality",
    "wof:population":125
},
  "geometry": {"coordinates":[79.46316899999999,29.548877],"type":"Point"}
}