{
  "type": "Feature",
  "properties": {
    "gn:admin1_code":"36",
    "gn:admin2_code":"153.0",
    "gn:asciiname":"Nizampur",
    "gn:country_code":"IN",
    "gn:dem":149,
    "gn:feature_class":"P",
    "gn:feature_code":"PPL",
    "gn:name":"Niz\u0101mpur",
    "gn:population":0,
    "gn:timezone":"Asia/Kolkata",
    "iso:country":"IN",
    "wof:name":"Nizampur",
    "wof:placetype":"locality"
},
  "geometry": {"coordinates":[80.81636999999998,27.91586],"type":"Point"}
}