{
  "type": "Feature",
  "properties": {
    "iso:country":"IN",
    "ks:ks_name":"Sonarhat",
    "ks:ks_pop":343,
    "ks:ks_type":"VILLAGE",
    "name:eng_x_preferred":[
        "Sonarhat"
    ],
    "wof:name":"Sonarhat",
    "wof:placetype":"locality",
    "wof:population":343
},
  "geometry": {"coordinates":[89.364211,26.050622],"type":"Point"}
}