{
  "type": "Feature",
  "properties": {
    "iso:country":"IN",
    "ks:ks_name":"Gudarimamidi",
    "ks:ks_pop":108,
    "ks:ks_type":"HABITATION",
    "name:eng_x_preferred":[
        "Gudarimamidi"
    ],
    "wof:name":"Gudarimamidi",
    "wof:placetype":"locality",
    "wof:population":108
},
  "geometry": {"coordinates":[82.152637,18.021153],"type":"Point"}
}