{
  "type": "Feature",
  "properties": {
    "gn:admin1_code":"36.0",
    "gn:admin2_code":"149.0",
    "gn:asciiname":"Azamganj Mudia",
    "gn:country_code":"IN",
    "gn:dem":172,
    "gn:feature_class":"P",
    "gn:feature_code":"PPL",
    "gn:name":"\u0100zamganj M\u016bdia",
    "gn:population":0,
    "gn:timezone":"Asia/Kolkata",
    "iso:country":"IN",
    "ks:ks_alt_nam":"\u0100zamganj M\u016bdia",
    "ks:ks_name":"Azamganj Mudia",
    "ks:ks_type":"VILLAGE",
    "ks:ks_uagg_main":0,
    "name:eng_x_preferred":[
        "Azamganj Mudia"
    ],
    "name:eng_x_variant":[
        "\u0100zamganj M\u016bdia"
    ],
    "wof:name":"Azamganj Mudia",
    "wof:placetype":"neighbourhood"
},
  "geometry": {"coordinates":[79.16098,28.163149],"type":"Point"}
}