{
  "type": "Feature",
  "properties": {
    "gn:admin1_code":"36",
    "gn:admin2_code":"180.0",
    "gn:asciiname":"Hisampur",
    "gn:country_code":"IN",
    "gn:dem":112,
    "gn:feature_class":"P",
    "gn:feature_code":"PPL",
    "gn:name":"His\u0101mpur",
    "gn:population":0,
    "gn:timezone":"Asia/Kolkata",
    "iso:country":"IN",
    "ks:ks_alt_nam":"His\u0101mpur",
    "ks:ks_name":"Hisampur",
    "ks:ks_type":"VILLAGE",
    "ks:ks_uagg_main":0,
    "name:eng_x_preferred":[
        "Hisampur"
    ],
    "name:eng_x_variant":[
        "His\u0101mpur"
    ],
    "wof:name":"Hisampur",
    "wof:placetype":"neighbourhood"
},
  "geometry": {"coordinates":[81.59712,27.253178],"type":"Point"}
}