{
  "type": "Feature",
  "properties": {
    "iso:country":"IN",
    "ks:ks_name":"Parbatipur",
    "ks:ks_pop":31,
    "ks:ks_type":"VILLAGE",
    "name:eng_x_preferred":[
        "Parbatipur"
    ],
    "wof:name":"Parbatipur",
    "wof:placetype":"locality",
    "wof:population":31
},
  "geometry": {"coordinates":[87.432576,22.853472],"type":"Point"}
}