{
  "type": "Feature",
  "properties": {
    "gn:admin1_code":"36.0",
    "gn:admin2_code":"152",
    "gn:asciiname":"Kania Khurd",
    "gn:country_code":"IN",
    "gn:dem":147,
    "gn:feature_class":"P",
    "gn:feature_code":"PPL",
    "gn:name":"Kania Khurd",
    "gn:population":0,
    "gn:timezone":"Asia/Kolkata",
    "iso:country":"IN",
    "wof:name":"Kania Khurd",
    "wof:placetype":"neighbourhood"
},
  "geometry": {"coordinates":[79.55951,27.68807],"type":"Point"}
}