{
  "type": "Feature",
  "properties": {
    "iso:country":"IN",
    "ks:ks_name":"Sekhuwaniya",
    "ks:ks_pop":702,
    "ks:ks_type":"HABITATION",
    "name:eng_x_preferred":[
        "Sekhuwaniya"
    ],
    "wof:name":"Sekhuwaniya",
    "wof:placetype":"locality",
    "wof:population":702
},
  "geometry": {"coordinates":[81.95826,27.818887],"type":"Point"}
}