{
  "type": "Feature",
  "properties": {
    "gn:admin1_code":"24",
    "gn:admin2_code":"106.0",
    "gn:asciiname":"Bajargarh",
    "gn:country_code":"IN",
    "gn:dem":171,
    "gn:feature_class":"P",
    "gn:feature_code":"PPL",
    "gn:name":"Bajargarh",
    "gn:population":0,
    "gn:timezone":"Asia/Kolkata",
    "iso:country":"IN",
    "ks:ks_name":"Bajjar Garh",
    "ks:ks_pop":642,
    "ks:ks_type":"HABITATION",
    "name:eng_x_preferred":[
        "Bajjar Garh"
    ],
    "name:eng_x_variant":[
        "Bajargarh"
    ],
    "wof:name":"Bajjar Garh",
    "wof:placetype":"locality",
    "wof:population":642
},
  "geometry": {"coordinates":[77.812972,26.922372],"type":"Point"}
}