{
  "type": "Feature",
  "properties": {
    "iso:country":"IN",
    "ks:ks_name":"Karthibailu",
    "ks:ks_pop":140,
    "ks:ks_type":"HABITATION",
    "name:eng_x_preferred":[
        "Karthibailu"
    ],
    "wof:name":"Karthibailu",
    "wof:placetype":"locality",
    "wof:population":140
},
  "geometry": {"coordinates":[74.783356,13.399781],"type":"Point"}
}