{
  "type": "Feature",
  "properties": {
    "iso:country":"IN",
    "ks:ks_alt_nam":"Muchch\u012bler",
    "ks:ks_name":"Muchchiler",
    "ks:ks_type":"VILLAGE",
    "name:eng_x_preferred":[
        "Muchchiler"
    ],
    "name:eng_x_variant":[
        "Muchch\u012bler"
    ],
    "wof:name":"Muchchiler",
    "wof:placetype":"locality"
},
  "geometry": {"coordinates":[80.720501,19.033199],"type":"Point"}
}