{
  "type": "Feature",
  "properties": {
    "gn:admin1_code":"24",
    "gn:admin2_code":"122.0",
    "gn:asciiname":"Chandadhand-ki-Jhonpria",
    "gn:country_code":"IN",
    "gn:dem":346,
    "gn:feature_class":"P",
    "gn:feature_code":"PPL",
    "gn:name":"Chandadhand-ki-Jhonpria",
    "gn:population":0,
    "gn:timezone":"Asia/Kolkata",
    "iso:country":"IN",
    "wof:name":"Chandadhand-ki-Jhonpria",
    "wof:placetype":"locality"
},
  "geometry": {"coordinates":[75.41755999999999,25.63181],"type":"Point"}
}