{
  "type": "Feature",
  "properties": {
    "gn:admin1_code":"11.0",
    "gn:admin2_code":"24.0",
    "gn:asciiname":"Maheti",
    "gn:country_code":"IN",
    "gn:dem":684,
    "gn:feature_class":"P",
    "gn:feature_code":"PPL",
    "gn:name":"Maheti",
    "gn:population":0,
    "gn:timezone":"Asia/Kolkata",
    "iso:country":"IN",
    "wof:name":"Maheti",
    "wof:placetype":"locality"
},
  "geometry": {"coordinates":[75.87170999999999,32.31468],"type":"Point"}
}