{
  "type": "Feature",
  "properties": {
    "gn:admin1_code":"19.0",
    "gn:admin2_code":"570.0",
    "gn:asciiname":"Megaramakki",
    "gn:country_code":"IN",
    "gn:dem":717,
    "gn:feature_class":"P",
    "gn:feature_code":"PPL",
    "gn:name":"Megaramakki",
    "gn:population":0,
    "gn:timezone":"Asia/Kolkata",
    "iso:country":"IN",
    "wof:name":"Megaramakki",
    "wof:placetype":"locality"
},
  "geometry": {"coordinates":[75.47475,13.42472],"type":"Point"}
}