{
  "type": "Feature",
  "properties": {
    "iso:country":"IN",
    "ks:ks_alt_nam":"HARRAPATH",
    "ks:ks_name":"Harrapath",
    "ks:ks_pop":118,
    "ks:ks_type":"HABITATION",
    "name:eng_x_preferred":[
        "Harrapath"
    ],
    "wof:name":"Harrapath",
    "wof:placetype":"locality",
    "wof:population":118
},
  "geometry": {"coordinates":[83.98509300000001,23.001191],"type":"Point"}
}