{
  "type": "Feature",
  "properties": {
    "iso:country":"IN",
    "ks:ks_name":"Jambavanipeta",
    "ks:ks_pop":569,
    "ks:ks_type":"HABITATION",
    "name:eng_x_preferred":[
        "Jambavanipeta"
    ],
    "wof:name":"Jambavanipeta",
    "wof:placetype":"locality",
    "wof:population":569
},
  "geometry": {"coordinates":[81.796722,16.828334],"type":"Point"}
}