{
  "type": "Feature",
  "properties": {
    "iso:country":"IN",
    "ks:ks_name":"Malchiwadi",
    "ks:ks_pop":230,
    "ks:ks_type":"HABITATION",
    "name:eng_x_preferred":[
        "Malchiwadi"
    ],
    "wof:name":"Malchiwadi",
    "wof:placetype":"locality",
    "wof:population":230
},
  "geometry": {"coordinates":[73.55194400000001,16.972222],"type":"Point"}
}