{
  "type": "Feature",
  "properties": {
    "iso:country":"IN",
    "ks:ks_name":"Barwadih",
    "ks:ks_pop":200,
    "ks:ks_type":"HABITATION",
    "name:eng_x_preferred":[
        "Barwadih"
    ],
    "wof:name":"Barwadih",
    "wof:placetype":"locality",
    "wof:population":200
},
  "geometry": {"coordinates":[83.402402,24.59008],"type":"Point"}
}