{
  "type": "Feature",
  "properties": {
    "iso:country":"IN",
    "ks:ks_name":"Narayanpur No 2",
    "ks:ks_pop":294,
    "ks:ks_type":"HABITATION",
    "name:eng_x_preferred":[
        "Narayanpur No 2"
    ],
    "wof:name":"Narayanpur No 2",
    "wof:placetype":"locality",
    "wof:population":294
},
  "geometry": {"coordinates":[94.87569499999999,27.661209],"type":"Point"}
}