{
  "type": "Feature",
  "properties": {
    "gn:admin1_code":"35",
    "gn:admin2_code":"457.0",
    "gn:asciiname":"Dhimrurith",
    "gn:country_code":"IN",
    "gn:dem":359,
    "gn:feature_class":"P",
    "gn:feature_code":"PPL",
    "gn:name":"Dh\u012bmr\u016br\u012bth",
    "gn:population":0,
    "gn:timezone":"Asia/Kolkata",
    "iso:country":"IN",
    "ks:ks_name":"Dhimru Reeth",
    "ks:ks_pop":239,
    "ks:ks_type":"VILLAGE",
    "name:eng_x_preferred":[
        "Dhimru Reeth"
    ],
    "name:eng_x_variant":[
        "Dhimrurith"
    ],
    "name:und_x_variant":[
        "Dh\u012bmr\u016br\u012bth",
        "Rayatw\u0101ri"
    ],
    "wof:name":"Dhimru Reeth",
    "wof:placetype":"locality",
    "wof:population":239
},
  "geometry": {"coordinates":[79.838385,21.834463],"type":"Point"}
}