{
  "type": "Feature",
  "properties": {
    "gn:admin1_code":"35",
    "gn:admin2_code":"457.0",
    "gn:asciiname":"Dhimrurith",
    "gn:country_code":"IN",
    "gn:dem":359,
    "gn:feature_class":"P",
    "gn:feature_code":"PPL",
    "gn:name":"Dh\u012bmr\u016br\u012bth",
    "gn:population":0,
    "gn:timezone":"Asia/Kolkata",
    "iso:country":"IN",
    "name:und_x_variant":[
        "Dh\u012bmr\u016br\u012bth",
        "Rayatw\u0101ri"
    ],
    "wof:name":"Dhimrurith",
    "wof:placetype":"locality"
},
  "geometry": {"coordinates":[79.83939000000002,21.83459],"type":"Point"}
}