{
  "type": "Feature",
  "properties": {
    "iso:country":"IN",
    "ks:ks_name":"Sooriyapillaiyarkuppam",
    "ks:ks_pop":170,
    "ks:ks_type":"HABITATION",
    "name:eng_x_preferred":[
        "Sooriyapillaiyarkuppam"
    ],
    "wof:name":"Sooriyapillaiyarkuppam",
    "wof:placetype":"locality",
    "wof:population":170
},
  "geometry": {"coordinates":[80.056196,12.475352],"type":"Point"}
}