{
  "type": "Feature",
  "properties": {
    "iso:country":"IN",
    "ks:ks_name":"Harekrishnapur",
    "ks:ks_pop":667,
    "ks:ks_type":"VILLAGE",
    "name:eng_x_preferred":[
        "Harekrishnapur"
    ],
    "wof:name":"Harekrishnapur",
    "wof:placetype":"locality",
    "wof:population":667
},
  "geometry": {"coordinates":[84.39079599999999,20.680874],"type":"Point"}
}