{
  "type": "Feature",
  "properties": {
    "gn:admin1_code":"19.0",
    "gn:admin2_code":"568.0",
    "gn:asciiname":"Chimatgundi",
    "gn:country_code":"IN",
    "gn:dem":641,
    "gn:feature_class":"P",
    "gn:feature_code":"PPL",
    "gn:name":"Chimatgundi",
    "gn:population":0,
    "gn:timezone":"Asia/Kolkata",
    "iso:country":"IN",
    "ks:ks_name":"Chimtagundi",
    "ks:ks_pop":6,
    "ks:ks_type":"HABITATION",
    "name:eng_x_preferred":[
        "Chimtagundi"
    ],
    "name:eng_x_variant":[
        "Chimatgundi"
    ],
    "wof:name":"Chimtagundi",
    "wof:placetype":"locality",
    "wof:population":6
},
  "geometry": {"coordinates":[75.17709499999999,13.504495],"type":"Point"}
}