{
  "type": "Feature",
  "properties": {
    "gn:admin1_code":"13.0",
    "gn:admin2_code":"589.0",
    "gn:asciiname":"Perumparamba",
    "gn:country_code":"IN",
    "gn:dem":42,
    "gn:feature_class":"P",
    "gn:feature_code":"PPL",
    "gn:name":"Perumparamba",
    "gn:population":0,
    "gn:timezone":"Asia/Kolkata",
    "iso:country":"IN",
    "ks:ks_name":"Perumparamba",
    "ks:ks_pop":1614,
    "ks:ks_type":"HABITATION",
    "name:eng_x_preferred":[
        "Perumparamba"
    ],
    "wof:name":"Perumparamba",
    "wof:placetype":"locality",
    "wof:population":1614
},
  "geometry": {"coordinates":[75.652625,11.988829],"type":"Point"}
}