{
  "type": "Feature",
  "properties": {
    "iso:country":"IN",
    "ks:ks_name":"Thethakudi North",
    "ks:ks_pop":3588,
    "ks:ks_type":"VILLAGE",
    "ks:ks_uagg_main":0,
    "name:eng_x_preferred":[
        "Thethakudi North"
    ],
    "wof:name":"Thethakudi North",
    "wof:placetype":"neighbourhood",
    "wof:population":3588
},
  "geometry": {"coordinates":[79.83034600000001,10.434421],"type":"Point"}
}