{
  "type": "Feature",
  "properties": {
    "iso:country":"IN",
    "ks:ks_alt_nam":"Th\u0101nw\u0101r",
    "ks:ks_name":"Thanwar",
    "ks:ks_pop":571,
    "ks:ks_type":"VILLAGE",
    "ks:ks_uagg_main":0,
    "name:eng_x_preferred":[
        "Thanwar"
    ],
    "name:eng_x_variant":[
        "Th\u0101nw\u0101r"
    ],
    "wof:name":"Thanwar",
    "wof:placetype":"neighbourhood",
    "wof:population":571
},
  "geometry": {"coordinates":[86.403373,25.894336],"type":"Point"}
}