{
  "type": "Feature",
  "properties": {
    "iso:country":"IN",
    "ks:ks_name":"Narasaiana Palya",
    "ks:ks_pop":207,
    "ks:ks_type":"HABITATION",
    "name:eng_x_preferred":[
        "Narasaiana Palya"
    ],
    "wof:name":"Narasaiana Palya",
    "wof:placetype":"locality",
    "wof:population":207
},
  "geometry": {"coordinates":[77.244123,13.349079],"type":"Point"}
}