{
  "type": "Feature",
  "properties": {
    "iso:country":"IN",
    "ks:ks_name":"Kishanpura",
    "ks:ks_pop":375,
    "ks:ks_type":"HABITATION",
    "name:eng_x_preferred":[
        "Kishanpura"
    ],
    "wof:name":"Kishanpura",
    "wof:placetype":"locality",
    "wof:population":375
},
  "geometry": {"coordinates":[75.736423,23.347338],"type":"Point"}
}