{
  "type": "Feature",
  "properties": {
    "iso:country":"IN",
    "ks:ks_name":"Majhauwa Purwa",
    "ks:ks_pop":240,
    "ks:ks_type":"HABITATION",
    "name:eng_x_preferred":[
        "Majhauwa Purwa"
    ],
    "wof:name":"Majhauwa Purwa",
    "wof:placetype":"locality",
    "wof:population":240
},
  "geometry": {"coordinates":[82.67788899999999,26.759599],"type":"Point"}
}