{
  "type": "Feature",
  "properties": {
    "iso:country":"IN",
    "ks:ks_name":"Killamamidivalasa",
    "ks:ks_pop":67,
    "ks:ks_type":"HABITATION",
    "name:eng_x_preferred":[
        "Killamamidivalasa"
    ],
    "wof:name":"Killamamidivalasa",
    "wof:placetype":"locality",
    "wof:population":67
},
  "geometry": {"coordinates":[82.94841700000001,18.274989],"type":"Point"}
}