{
  "type": "Feature",
  "properties": {
    "iso:country":"IN",
    "ks:ks_name":"Bottolekatte",
    "ks:ks_pop":32,
    "ks:ks_type":"HABITATION",
    "name:eng_x_preferred":[
        "Bottolekatte"
    ],
    "wof:name":"Bottolekatte",
    "wof:placetype":"locality",
    "wof:population":32
},
  "geometry": {"coordinates":[75.115008,14.270209],"type":"Point"}
}