{
  "type": "Feature",
  "properties": {
    "iso:country":"IN",
    "ks:ks_name":"Bangurkela",
    "ks:ks_pop":475,
    "ks:ks_type":"VILLAGE",
    "ks:ks_uagg_main":0,
    "name:eng_x_preferred":[
        "Bangurkela"
    ],
    "wof:name":"Bangurkela",
    "wof:placetype":"neighbourhood",
    "wof:population":475
},
  "geometry": {"coordinates":[83.733519,21.995874],"type":"Point"}
}