{
  "type": "Feature",
  "properties": {
    "iso:country":"IN",
    "ks:ks_name":"Kwarali",
    "ks:ks_pop":249,
    "ks:ks_type":"VILLAGE",
    "name:eng_x_preferred":[
        "Kwarali"
    ],
    "wof:name":"Kwarali",
    "wof:placetype":"locality",
    "wof:population":249
},
  "geometry": {"coordinates":[79.567627,29.788186],"type":"Point"}
}