{
  "type": "Feature",
  "properties": {
    "iso:country":"IN",
    "ks:ks_name":"Salmara",
    "ks:ks_pop":200,
    "ks:ks_type":"HABITATION",
    "name:eng_x_preferred":[
        "Salmara"
    ],
    "wof:name":"Salmara",
    "wof:placetype":"locality",
    "wof:population":200
},
  "geometry": {"coordinates":[75.19269,12.936747],"type":"Point"}
}