{
  "type": "Feature",
  "properties": {
    "iso:country":"IN",
    "ks:ks_alt_nam":"kondesaval",
    "ks:ks_name":"Kondesaval",
    "ks:ks_pop":124,
    "ks:ks_type":"HABITATION",
    "name:eng_x_preferred":[
        "Kondesaval"
    ],
    "wof:name":"Kondesaval",
    "wof:placetype":"locality",
    "wof:population":124
},
  "geometry": {"coordinates":[74.717055,14.656486],"type":"Point"}
}