{
  "type": "Feature",
  "properties": {
    "iso:country":"IN",
    "ks:ks_name":"Sukh Nandan Tola",
    "ks:ks_pop":20,
    "ks:ks_type":"HABITATION",
    "ks:ks_uagg_main":0,
    "name:eng_x_preferred":[
        "Sukh Nandan Tola"
    ],
    "wof:name":"Sukh Nandan Tola",
    "wof:placetype":"neighbourhood",
    "wof:population":20
},
  "geometry": {"coordinates":[83.410861,26.866053],"type":"Point"}
}