{
  "type": "Feature",
  "properties": {
    "iso:country":"IN",
    "ks:ks_name":"Bheludihi",
    "ks:ks_pop":256,
    "ks:ks_type":"VILLAGE",
    "name:eng_x_preferred":[
        "Bheludihi"
    ],
    "wof:name":"Bheludihi",
    "wof:placetype":"locality",
    "wof:population":256
},
  "geometry": {"coordinates":[86.254772,22.379785],"type":"Point"}
}