{
  "type": "Feature",
  "properties": {
    "gn:admin1_code":"21.0",
    "gn:admin2_code":"397.0",
    "gn:asciiname":"Hirripara",
    "gn:country_code":"IN",
    "gn:dem":659,
    "gn:feature_class":"P",
    "gn:feature_code":"PPL",
    "gn:name":"Hirrip\u0101ra",
    "gn:population":0,
    "gn:timezone":"Asia/Kolkata",
    "iso:country":"IN",
    "ks:ks_name":"Hirapara",
    "ks:ks_pop":316,
    "ks:ks_type":"VILLAGE",
    "name:eng_x_preferred":[
        "Hirapara"
    ],
    "name:eng_x_variant":[
        "Hirripara"
    ],
    "wof:name":"Hirapara",
    "wof:placetype":"locality",
    "wof:population":316
},
  "geometry": {"coordinates":[81.96534200000001,19.945737],"type":"Point"}
}