{
  "type": "Feature",
  "properties": {
    "iso:country":"IN",
    "ks:ks_name":"Jhar Gangapur",
    "ks:ks_pop":335,
    "ks:ks_type":"HABITATION",
    "name:eng_x_preferred":[
        "Jhar Gangapur"
    ],
    "wof:name":"Jhar Gangapur",
    "wof:placetype":"locality",
    "wof:population":335
},
  "geometry": {"coordinates":[93.09769300000001,26.079527],"type":"Point"}
}