{
  "type": "Feature",
  "properties": {
    "gn:admin1_code":"25.0",
    "gn:admin2_code":"633.0",
    "gn:asciiname":"Anaikkalpalaiyam",
    "gn:country_code":"IN",
    "gn:dem":339,
    "gn:feature_class":"P",
    "gn:feature_code":"PPL",
    "gn:name":"\u0100naikkalp\u0101laiyam",
    "gn:population":0,
    "gn:timezone":"Asia/Kolkata",
    "iso:country":"IN",
    "ks:ks_name":"Anaikkalpalayam",
    "ks:ks_pop":269,
    "ks:ks_type":"HABITATION",
    "name:eng_x_preferred":[
        "Anaikkalpalayam"
    ],
    "name:eng_x_variant":[
        "Anaikkalpalaiyam"
    ],
    "wof:name":"Anaikkalpalayam",
    "wof:placetype":"locality",
    "wof:population":269
},
  "geometry": {"coordinates":[77.278896,11.306674],"type":"Point"}
}