{
  "type": "Feature",
  "properties": {
    "iso:country":"IN",
    "ks:ks_name":"Korwadih",
    "ks:ks_pop":28,
    "ks:ks_type":"VILLAGE",
    "name:eng_x_preferred":[
        "Korwadih"
    ],
    "wof:name":"Korwadih",
    "wof:placetype":"locality",
    "wof:population":28
},
  "geometry": {"coordinates":[83.963005,23.645155],"type":"Point"}
}