{
  "type": "Feature",
  "properties": {
    "iso:country":"IN",
    "ks:ks_alt_nam":"M\u014ddalli",
    "ks:ks_name":"Modalli",
    "ks:ks_pop":494,
    "ks:ks_type":"VILLAGE",
    "name:eng_x_preferred":[
        "Modalli"
    ],
    "name:eng_x_variant":[
        "M\u014ddalli"
    ],
    "wof:name":"Modalli",
    "wof:placetype":"locality",
    "wof:population":494
},
  "geometry": {"coordinates":[77.202921,12.103291],"type":"Point"}
}