{
  "type": "Feature",
  "properties": {
    "iso:country":"IN",
    "ks:ks_name":"Asanbani",
    "ks:ks_pop":320,
    "ks:ks_type":"VILLAGE",
    "name:eng_x_preferred":[
        "Asanbani"
    ],
    "wof:name":"Asanbani",
    "wof:placetype":"locality",
    "wof:population":320
},
  "geometry": {"coordinates":[87.180629,24.31667],"type":"Point"}
}