{
  "type": "Feature",
  "properties": {
    "gn:admin1_code":"35",
    "gn:admin2_code":"425.0",
    "gn:asciiname":"Jamra",
    "gn:country_code":"IN",
    "gn:dem":184,
    "gn:feature_class":"P",
    "gn:feature_code":"PPL",
    "gn:name":"Jamra",
    "gn:population":0,
    "gn:timezone":"Asia/Kolkata",
    "iso:country":"IN",
    "name:snd_x_preferred":[
        "\u0684\u0627\u0645\u0699\u0648"
    ],
    "wof:name":"Jamra",
    "wof:placetype":"locality"
},
  "geometry": {"coordinates":[80.13975000000001,25.07149],"type":"Point"}
}