{
  "type": "Feature",
  "properties": {
    "gn:admin1_code":"19.0",
    "gn:admin2_code":"573.0",
    "gn:asciiname":"Doddanakatte",
    "gn:country_code":"IN",
    "gn:dem":778,
    "gn:feature_class":"P",
    "gn:feature_code":"PPL",
    "gn:name":"Doddanakatte",
    "gn:population":0,
    "gn:timezone":"Asia/Kolkata",
    "iso:country":"IN",
    "wof:name":"Doddanakatte",
    "wof:placetype":"neighbourhood"
},
  "geometry": {"coordinates":[76.47345,12.58992],"type":"Point"}
}