{
  "type": "Feature",
  "properties": {
    "iso:country":"IN",
    "ks:ks_name":"Shahjahanpur",
    "ks:ks_pop":1368,
    "ks:ks_type":"VILLAGE",
    "name:eng_x_preferred":[
        "Shahjahanpur"
    ],
    "wof:name":"Shahjahanpur",
    "wof:placetype":"locality",
    "wof:population":1368
},
  "geometry": {"coordinates":[77.67775,29.659887],"type":"Point"}
}