{
  "type": "Feature",
  "properties": {
    "iso:country":"IN",
    "ks:ks_alt_nam":"RSC 3",
    "ks:ks_name":"Rsc 3",
    "ks:ks_pop":107,
    "ks:ks_type":"HABITATION",
    "name:eng_x_preferred":[
        "Rsc 3"
    ],
    "wof:name":"Rsc 3",
    "wof:placetype":"locality",
    "wof:population":107
},
  "geometry": {"coordinates":[82.096243,18.127825],"type":"Point"}
}