{
  "type": "Feature",
  "properties": {
    "iso:country":"IN",
    "ks:ks_name":"Kuthiraikuthi",
    "ks:ks_pop":690,
    "ks:ks_type":"HABITATION",
    "name:eng_x_preferred":[
        "Kuthiraikuthi"
    ],
    "wof:name":"Kuthiraikuthi",
    "wof:placetype":"locality",
    "wof:population":690
},
  "geometry": {"coordinates":[79.76702299999999,11.3256],"type":"Point"}
}