{
  "type": "Feature",
  "properties": {
    "iso:country":"IN",
    "ks:ks_name":"Rampura Bhagali",
    "ks:ks_pop":50,
    "ks:ks_type":"HABITATION",
    "name:eng_x_preferred":[
        "Rampura Bhagali"
    ],
    "wof:name":"Rampura Bhagali",
    "wof:placetype":"locality",
    "wof:population":50
},
  "geometry": {"coordinates":[72.840569,24.778268],"type":"Point"}
}