{
  "type": "Feature",
  "properties": {
    "iso:country":"IN",
    "ks:ks_name":"Jayanagar",
    "ks:ks_pop":2252,
    "ks:ks_type":"HABITATION",
    "name:eng_x_preferred":[
        "Jayanagar"
    ],
    "wof:name":"Jayanagar",
    "wof:placetype":"locality",
    "wof:population":2252
},
  "geometry": {"coordinates":[75.11877699999999,12.577231],"type":"Point"}
}