{
  "type": "Feature",
  "properties": {
    "iso:country":"IN",
    "ks:ks_name":"Dongripada",
    "ks:ks_pop":264,
    "ks:ks_type":"HABITATION",
    "name:eng_x_preferred":[
        "Dongripada"
    ],
    "wof:name":"Dongripada",
    "wof:placetype":"locality",
    "wof:population":264
},
  "geometry": {"coordinates":[72.880354,20.201841],"type":"Point"}
}