{
  "type": "Feature",
  "properties": {
    "iso:country":"IN",
    "ks:ks_name":"Jayamangalam",
    "ks:ks_pop":280,
    "ks:ks_type":"HABITATION",
    "name:eng_x_preferred":[
        "Jayamangalam"
    ],
    "wof:name":"Jayamangalam",
    "wof:placetype":"locality",
    "wof:population":280
},
  "geometry": {"coordinates":[78.497713,10.628633],"type":"Point"}
}