{
  "type": "Feature",
  "properties": {
    "iso:country":"IN",
    "ks:ks_name":"Tetariatanr",
    "ks:ks_pop":0,
    "ks:ks_type":"VILLAGE",
    "name:eng_x_preferred":[
        "Tetariatanr"
    ],
    "wof:name":"Tetariatanr",
    "wof:placetype":"locality",
    "wof:population":0
},
  "geometry": {"coordinates":[86.345275,24.391087],"type":"Point"}
}