{
  "type": "Feature",
  "properties": {
    "gn:admin1_code":"25.0",
    "gn:admin2_code":"618.0",
    "gn:asciiname":"Sembiyavilagam",
    "gn:country_code":"IN",
    "gn:dem":4,
    "gn:feature_class":"P",
    "gn:feature_code":"PPL",
    "gn:name":"Sembiyavil\u0101gam",
    "gn:population":0,
    "gn:timezone":"Asia/Kolkata",
    "iso:country":"IN",
    "wof:name":"Sembiyavilagam",
    "wof:placetype":"neighbourhood"
},
  "geometry": {"coordinates":[79.70661,10.55815],"type":"Point"}
}