{
  "type": "Feature",
  "properties": {
    "iso:country":"IN",
    "ks:ks_alt_nam":"Temr\u016bpura",
    "ks:ks_name":"Temrupura",
    "ks:ks_type":"VILLAGE",
    "name:eng_x_preferred":[
        "Temrupura"
    ],
    "name:eng_x_variant":[
        "Temr\u016bpura"
    ],
    "wof:name":"Temrupura",
    "wof:placetype":"locality"
},
  "geometry": {"coordinates":[77.756466,22.308708],"type":"Point"}
}