{
  "type": "Feature",
  "properties": {
    "iso:country":"IN",
    "ks:ks_name":"Bahera Dol",
    "ks:ks_pop":604,
    "ks:ks_type":"VILLAGE",
    "name:eng_x_preferred":[
        "Bahera Dol"
    ],
    "wof:name":"Bahera Dol",
    "wof:placetype":"locality",
    "wof:population":604
},
  "geometry": {"coordinates":[81.770025,23.349563],"type":"Point"}
}