{
  "type": "Feature",
  "properties": {
    "gn:admin1_code":"35",
    "gn:admin2_code":"421.0",
    "gn:asciiname":"Gajna",
    "gn:country_code":"IN",
    "gn:dem":262,
    "gn:feature_class":"P",
    "gn:feature_code":"PPL",
    "gn:name":"G\u0101jna",
    "gn:population":0,
    "gn:timezone":"Asia/Kolkata",
    "iso:country":"IN",
    "ks:ks_alt_nam":"G\u0101jna",
    "ks:ks_name":"Gajna",
    "ks:ks_pop":626,
    "ks:ks_type":"VILLAGE",
    "ks:ks_uagg_main":0,
    "name:eng_x_preferred":[
        "Gajna"
    ],
    "name:eng_x_variant":[
        "G\u0101jna"
    ],
    "name:hif_x_preferred":[
        "Gajna"
    ],
    "wof:name":"Gajna",
    "wof:placetype":"neighbourhood",
    "wof:population":626
},
  "geometry": {"coordinates":[77.959919,25.836565],"type":"Point"}
}