{
  "type": "Feature",
  "properties": {
    "iso:country":"IN",
    "ks:ks_alt_nam":"shirani",
    "ks:ks_name":"Shirani",
    "ks:ks_pop":841,
    "ks:ks_type":"HABITATION",
    "name:eng_x_preferred":[
        "Shirani"
    ],
    "wof:name":"Shirani",
    "wof:placetype":"locality",
    "wof:population":841
},
  "geometry": {"coordinates":[74.530728,14.088722],"type":"Point"}
}