{
  "type": "Feature",
  "properties": {
    "iso:country":"IN",
    "ks:ks_name":"Pothenchira",
    "ks:ks_pop":480,
    "ks:ks_type":"HABITATION",
    "name:eng_x_preferred":[
        "Pothenchira"
    ],
    "wof:name":"Pothenchira",
    "wof:placetype":"locality",
    "wof:population":480
},
  "geometry": {"coordinates":[76.408017,10.378947],"type":"Point"}
}