{
  "type": "Feature",
  "properties": {
    "iso:country":"IN",
    "ks:ks_name":"Tola Bhalua",
    "ks:ks_pop":139,
    "ks:ks_type":"VILLAGE",
    "name:eng_x_preferred":[
        "Tola Bhalua"
    ],
    "wof:name":"Tola Bhalua",
    "wof:placetype":"locality",
    "wof:population":139
},
  "geometry": {"coordinates":[86.48048900000001,24.462154],"type":"Point"}
}