{
  "type": "Feature",
  "properties": {
    "iso:country":"IN",
    "ks:ks_name":"Gavliwadi",
    "ks:ks_pop":363,
    "ks:ks_type":"HABITATION",
    "name:eng_x_preferred":[
        "Gavliwadi"
    ],
    "wof:name":"Gavliwadi",
    "wof:placetype":"locality",
    "wof:population":363
},
  "geometry": {"coordinates":[73.868424,15.92517],"type":"Point"}
}