{
  "type": "Feature",
  "properties": {
    "iso:country":"IN",
    "ks:ks_name":"Sanyasikodi",
    "ks:ks_pop":211,
    "ks:ks_type":"HABITATION",
    "name:eng_x_preferred":[
        "Sanyasikodi"
    ],
    "wof:name":"Sanyasikodi",
    "wof:placetype":"locality",
    "wof:population":211
},
  "geometry": {"coordinates":[75.120554,12.827809],"type":"Point"}
}