{
  "type": "Feature",
  "properties": {
    "gn:admin1_code":"40",
    "gn:admin2_code":"532.0",
    "gn:asciiname":"Linga",
    "gn:country_code":"IN",
    "gn:dem":363,
    "gn:feature_class":"P",
    "gn:feature_code":"PPL",
    "gn:name":"Linga",
    "gn:population":0,
    "gn:timezone":"Asia/Kolkata",
    "iso:country":"IN",
    "ks:ks_name":"Linga",
    "ks:ks_pop":308,
    "ks:ks_type":"VILLAGE",
    "name:eng_x_preferred":[
        "Linga"
    ],
    "wof:name":"Linga",
    "wof:placetype":"locality",
    "wof:population":308
},
  "geometry": {"coordinates":[77.94270899999999,19.137925],"type":"Point"}
}