{
  "type": "Feature",
  "properties": {
    "gn:admin1_code":"25",
    "gn:admin2_code":"607.0",
    "gn:asciiname":"Ongur",
    "gn:country_code":"IN",
    "gn:dem":30,
    "gn:feature_class":"P",
    "gn:feature_code":"PPL",
    "gn:name":"Ong\u016br",
    "gn:population":0,
    "gn:timezone":"Asia/Kolkata",
    "iso:country":"IN",
    "wof:name":"Ongur",
    "wof:placetype":"locality"
},
  "geometry": {"coordinates":[79.77977,12.32738],"type":"Point"}
}