{
  "type": "Feature",
  "properties": {
    "gn:admin1_code":"35",
    "gn:admin2_code":"442.0",
    "gn:asciiname":"Kundiye",
    "gn:country_code":"IN",
    "gn:dem":431,
    "gn:feature_class":"P",
    "gn:feature_code":"PPL",
    "gn:name":"Kund\u012bye",
    "gn:population":0,
    "gn:timezone":"Asia/Kolkata",
    "iso:country":"IN",
    "wof:name":"Kundiye",
    "wof:placetype":"neighbourhood"
},
  "geometry": {"coordinates":[76.68264000000001,23.94188],"type":"Point"}
}