{
  "type": "Feature",
  "properties": {
    "gn:admin1_code":"35.0",
    "gn:admin2_code":"458.0",
    "gn:asciiname":"Jhitiya",
    "gn:country_code":"IN",
    "gn:dem":514,
    "gn:feature_class":"P",
    "gn:feature_code":"PPL",
    "gn:name":"Jhitiya",
    "gn:population":0,
    "gn:timezone":"Asia/Kolkata",
    "iso:country":"IN",
    "wof:name":"Jhitiya",
    "wof:placetype":"locality"
},
  "geometry": {"coordinates":[77.63364,24.40399],"type":"Point"}
}