{
  "type": "Feature",
  "properties": {
    "iso:country":"IN",
    "ks:ks_name":"Varabnath",
    "ks:ks_pop":750,
    "ks:ks_type":"HABITATION",
    "name:eng_x_preferred":[
        "Varabnath"
    ],
    "wof:name":"Varabnath",
    "wof:placetype":"locality",
    "wof:population":750
},
  "geometry": {"coordinates":[76.52462199999999,9.367892],"type":"Point"}
}