{
  "type": "Feature",
  "properties": {
    "iso:country":"IN",
    "ks:ks_alt_nam":"Lodha purwa",
    "ks:ks_name":"Lodha Purwa",
    "ks:ks_pop":125,
    "ks:ks_type":"HABITATION",
    "name:eng_x_preferred":[
        "Lodha Purwa"
    ],
    "wof:name":"Lodha Purwa",
    "wof:placetype":"locality",
    "wof:population":125
},
  "geometry": {"coordinates":[80.806116,27.558338],"type":"Point"}
}