{
  "type": "Feature",
  "properties": {
    "iso:country":"IN",
    "ks:ks_name":"Pawarwasti",
    "ks:ks_pop":100,
    "ks:ks_type":"HABITATION",
    "name:eng_x_preferred":[
        "Pawarwasti"
    ],
    "wof:name":"Pawarwasti",
    "wof:placetype":"locality",
    "wof:population":100
},
  "geometry": {"coordinates":[74.871928,17.805989],"type":"Point"}
}