{
  "type": "Feature",
  "properties": {
    "iso:country":"IN",
    "ks:ks_name":"Bada Murra",
    "ks:ks_pop":39,
    "ks:ks_type":"HABITATION",
    "name:eng_x_preferred":[
        "Bada Murra"
    ],
    "wof:name":"Bada Murra",
    "wof:placetype":"locality",
    "wof:population":39
},
  "geometry": {"coordinates":[78.95885699999999,23.409985],"type":"Point"}
}