{
  "type": "Feature",
  "properties": {
    "iso:country":"IN",
    "ks:ks_name":"Choudhuri Pam",
    "ks:ks_pop":1135,
    "ks:ks_type":"VILLAGE",
    "ks:ks_uagg_main":0,
    "name:eng_x_preferred":[
        "Choudhuri Pam"
    ],
    "wof:name":"Choudhuri Pam",
    "wof:placetype":"neighbourhood",
    "wof:population":1135
},
  "geometry": {"coordinates":[91.11284999999999,26.123793],"type":"Point"}
}