{
  "type": "Feature",
  "properties": {
    "iso:country":"IN",
    "ks:ks_name":"Lingareddipalle",
    "ks:ks_pop":157,
    "ks:ks_type":"VILLAGE",
    "ks:ks_uagg_main":0,
    "name:eng_x_preferred":[
        "Lingareddipalle"
    ],
    "wof:name":"Lingareddipalle",
    "wof:placetype":"neighbourhood",
    "wof:population":157
},
  "geometry": {"coordinates":[78.457666,17.93163],"type":"Point"}
}