{
  "type": "Feature",
  "properties": {
    "iso:country":"IN",
    "ks:ks_name":"Munni Purwa",
    "ks:ks_pop":290,
    "ks:ks_type":"HABITATION",
    "name:eng_x_preferred":[
        "Munni Purwa"
    ],
    "wof:name":"Munni Purwa",
    "wof:placetype":"locality",
    "wof:population":290
},
  "geometry": {"coordinates":[82.28321800000001,27.329998],"type":"Point"}
}