{
  "type": "Feature",
  "properties": {
    "iso:country":"IN",
    "ks:ks_name":"Brundaban",
    "ks:ks_pop":36,
    "ks:ks_type":"HABITATION",
    "name:eng_x_preferred":[
        "Brundaban"
    ],
    "wof:name":"Brundaban",
    "wof:placetype":"locality",
    "wof:population":36
},
  "geometry": {"coordinates":[86.29689999999999,21.975386],"type":"Point"}
}