{
  "type": "Feature",
  "properties": {
    "gn:country":"IN",
    "gn:fcode":"PPL",
    "gn:population":0,
    "iso:country":"IN",
    "name:ara_x_preferred":[
        "\u0625\u064a\u062a\u0648\u0627\u0631\u064a"
    ],
    "name:ben_bn_x_preferred":[
        "\u0987\u09a4\u0993\u09df\u09be\u09b0\u09bf"
    ],
    "name:ben_in_x_preferred":[
        "\u0987\u09a4\u0993\u09df\u09be\u09b0\u09bf"
    ],
    "name:guj_x_preferred":[
        "\u0a87\u0a9f\u0ab5\u0abe\u0ab0\u0ac0"
    ],
    "name:hin_x_preferred":[
        "\u0907\u0924\u0935\u093e\u0930\u0940"
    ],
    "name:kan_x_preferred":[
        "\u0c87\u0c9f\u0ccd\u0cb5\u0cbe\u0cb0\u0cbf"
    ],
    "name:mal_x_preferred":[
        "\u0d07\u0d24\u0d4d\u0d35\u0d3e\u0d30\u0d3f"
    ],
    "name:mar_x_preferred":[
        "\u0907\u0924\u0935\u093e\u0930\u0940"
    ],
    "name:pan_x_preferred":[
        "\u0a07\u0a1f\u0a35\u0a3e\u0a30\u0a40"
    ],
    "name:tam_x_preferred":[
        "\u0b87\u0b9f\u0bcd\u0bb5\u0bbe\u0bb0\u0bbf"
    ],
    "name:tel_x_preferred":[
        "\u0c07\u0c1f\u0c4d"
    ],
    "name:und_x_variant":[
        "Itw\u0101ri"
    ],
    "name:urd_x_preferred":[
        "\u0627\u062a\u0648\u0627\u0631\u06cc"
    ],
    "qs:name":"Itwari",
    "qs:name_adm0":"India",
    "qs:name_adm1":"Maharashtra",
    "qs:photos":1,
    "qs:photos_1k":1,
    "qs:photos_9k":1,
    "qs:photos_9r":1,
    "qs:photos_all":1,
    "qs:photos_sr":1,
    "qs:placetype":"Suburb",
    "qs:pop_sr":"0",
    "wof:name":"Itwari",
    "wof:placetype":"neighbourhood",
    "wof:population":0
},
  "geometry": {"coordinates":[79.12023000000001,21.15521],"type":"Point"}
}