{
  "type": "Feature",
  "properties": {
    "gn:admin1_code":"16",
    "gn:admin2_code":"499.0",
    "gn:asciiname":"Taroda",
    "gn:country_code":"IN",
    "gn:dem":239,
    "gn:feature_class":"P",
    "gn:feature_code":"PPL",
    "gn:name":"Taroda",
    "gn:population":0,
    "gn:timezone":"Asia/Kolkata",
    "iso:country":"IN",
    "name:afr_x_preferred":[
        "Taroda"
    ],
    "name:ang_x_preferred":[
        "Taroda"
    ],
    "name:ara_x_preferred":[
        "\u062a\u0627\u0631\u0648\u062f\u0627"
    ],
    "name:arg_x_preferred":[
        "Taroda"
    ],
    "name:ast_x_preferred":[
        "Taroda"
    ],
    "name:azb_x_preferred":[
        "\u062a\u0627\u0631\u062f\u0627"
    ],
    "name:cat_x_preferred":[
        "Taroda"
    ],
    "name:ceb_x_preferred":[
        "Taroda"
    ],
    "name:cha_x_preferred":[
        "Taroda"
    ],
    "name:cos_x_preferred":[
        "Taroda"
    ],
    "name:epo_x_preferred":[
        "Taroda"
    ],
    "name:eus_x_preferred":[
        "Taroda"
    ],
    "name:fas_x_preferred":[
        "\u062a\u0627\u0631\u062f\u0627"
    ],
    "name:fra_x_preferred":[
        "Taroda"
    ],
    "name:hak_x_preferred":[
        "Taroda"
    ],
    "name:hat_x_preferred":[
        "Taroda"
    ],
    "name:haw_x_preferred":[
        "Taroda"
    ],
    "name:hun_x_preferred":[
        "Taroda"
    ],
    "name:ido_x_preferred":[
        "Taroda"
    ],
    "name:ile_x_preferred":[
        "Taroda"
    ],
    "name:ina_x_preferred":[
        "Taroda"
    ],
    "name:ita_x_preferred":[
        "Taroda"
    ],
    "name:jam_x_preferred":[
        "Taroda"
    ],
    "name:kaz_x_preferred":[
        "\u0422\u0430\u0440\u043e\u0434\u0430"
    ],
    "name:lij_x_preferred":[
        "Taroda"
    ],
    "name:mlg_x_preferred":[
        "Taroda"
    ],
    "name:msa_x_preferred":[
        "Taroda"
    ],
    "name:nld_x_preferred":[
        "Taroda"
    ],
    "name:nno_x_preferred":[
        "Taroda"
    ],
    "name:nrm_x_preferred":[
        "Taroda"
    ],
    "name:oci_x_preferred":[
        "Taroda"
    ],
    "name:pap_x_preferred":[
        "Taroda"
    ],
    "name:pdc_x_preferred":[
        "Taroda"
    ],
    "name:pol_x_preferred":[
        "Taroda"
    ],
    "name:por_x_preferred":[
        "Taroda"
    ],
    "name:rmy_x_preferred":[
        "Taroda"
    ],
    "name:rus_x_preferred":[
        "\u0422\u0430\u0440\u043e\u0434\u0430"
    ],
    "name:scn_x_preferred":[
        "Taroda"
    ],
    "name:spa_x_preferred":[
        "Taroda"
    ],
    "name:sqi_x_preferred":[
        "Taroda"
    ],
    "name:tah_x_preferred":[
        "Taroda"
    ],
    "name:tpi_x_preferred":[
        "Taroda"
    ],
    "name:tso_x_preferred":[
        "Taroda"
    ],
    "name:ukr_x_preferred":[
        "\u0422\u0430\u0440\u043e\u0434\u0430"
    ],
    "name:uzb_x_preferred":[
        "Taroda"
    ],
    "name:vie_x_preferred":[
        "Taroda"
    ],
    "name:war_x_preferred":[
        "Taroda"
    ],
    "name:wln_x_preferred":[
        "Taroda"
    ],
    "name:zho_x_preferred":[
        "\u5854\u7f57\u8fbe"
    ],
    "wof:name":"Taroda",
    "wof:placetype":"locality"
},
  "geometry": {"coordinates":[76.11959,20.99789],"type":"Point"}
}