{
  "type": "Feature",
  "properties": {
    "iso:country":"IN",
    "ks:ks_name":"Kural Bari",
    "ks:ks_pop":76,
    "ks:ks_type":"VILLAGE",
    "name:eng_x_preferred":[
        "Kural Bari"
    ],
    "wof:name":"Kural Bari",
    "wof:placetype":"locality",
    "wof:population":76
},
  "geometry": {"coordinates":[87.333972,23.039085],"type":"Point"}
}