{
  "type": "Feature",
  "properties": {
    "iso:country":"IN",
    "name:eng_x_preferred":[
        "Sector 21C"
    ],
    "qs:gn_adm0_cc":"IN",
    "qs:gn_local":1271951,
    "qs:gn_nam_loc":"faridabad",
    "qs:gn_namadm1":"10",
    "qs:local_max":355,
    "qs:local_sum":583,
    "qs:localhoods":8,
    "qs:name":"Sector 21C",
    "qs:name_adm0":"India",
    "qs:name_adm1":"Haryana",
    "qs:name_adm2":"Faridabad",
    "qs:name_local":"Faridabad",
    "qs:photo_max":24,
    "qs:photo_sum":33,
    "qs:placetype":"Suburb",
    "qs:quad_count":3,
    "qs:woe_adm0":23424848,
    "qs:woe_adm1":2345744,
    "qs:woe_adm2":12586440,
    "qs:woe_lau":0,
    "qs:woe_local":2295396,
    "qs:woe_ver":"7.10.0",
    "wof:lang":[
        "eng"
    ],
    "wof:name":"Sector 21C",
    "wof:placetype":"neighbourhood"
},
  "geometry": {"coordinates":[77.29789,28.430575],"type":"Point"}
}