{
  "type": "Feature",
  "properties": {
    "iso:country":"IN",
    "name:ara_x_preferred":[
        "\u0627\u0644\u0642\u0637\u0627\u0639 21C"
    ],
    "name:ben_bn_x_preferred":[
        "\u09b8\u09c7\u0995\u09cd\u099f\u09b0 21\u09b8\u09bf"
    ],
    "name:ben_in_x_preferred":[
        "\u09b8\u09c7\u0995\u09cd\u099f\u09b0 21\u09b8\u09bf"
    ],
    "name:eng_x_preferred":[
        "Sector 21C"
    ],
    "name:guj_x_preferred":[
        "\u0ab8\u0ac7\u0a95\u0acd\u0a9f\u0ab0 21\u0ab8\u0ac0"
    ],
    "name:hin_x_preferred":[
        "\u0938\u0947\u0915\u094d\u091f\u0930 21\u0938\u0940"
    ],
    "name:kan_x_preferred":[
        "\u0cb8\u0cc6\u0c95\u0ccd\u0c9f\u0cb0\u0ccd"
    ],
    "name:mal_x_preferred":[
        "\u0d38\u0d46\u0d15\u0d4d\u0d1f\u0d30\u0d4d"
    ],
    "name:mar_x_preferred":[
        "\u0938\u0947\u0915\u094d\u091f\u0930 21C"
    ],
    "name:pan_x_preferred":[
        "\u0a38\u0a48\u0a15\u0a1f\u0a30 21\u0a38\u0a40"
    ],
    "name:tam_x_preferred":[
        "\u0baa\u0bbf\u0bb0\u0bbf\u0bb5\u0bc1 21C"
    ],
    "name:tel_x_preferred":[
        "\u0c38\u0c46\u0c15\u0c4d\u0c1f\u0c30\u0c4d"
    ],
    "name:urd_x_preferred":[
        "\u0633\u06cc\u06a9\u0679\u0631 21C"
    ],
    "qs:gn_adm0_cc":"IN",
    "qs:gn_local":1271951,
    "qs:gn_nam_loc":"faridabad",
    "qs:gn_namadm1":"10",
    "qs:local_max":355,
    "qs:local_sum":583,
    "qs:localhoods":8,
    "qs:name":"Sector 21C",
    "qs:name_adm0":"India",
    "qs:name_adm1":"Haryana",
    "qs:name_adm2":"Faridabad",
    "qs:name_local":"Faridabad",
    "qs:photo_max":24,
    "qs:photo_sum":33,
    "qs:placetype":"Suburb",
    "qs:quad_count":3,
    "qs:woe_adm0":23424848,
    "qs:woe_adm1":2345744,
    "qs:woe_adm2":12586440,
    "qs:woe_lau":0,
    "qs:woe_local":2295396,
    "qs:woe_ver":"7.10.0",
    "wof:lang":[
        "eng"
    ],
    "wof:name":"Sector 21C",
    "wof:placetype":"neighbourhood"
},
  "geometry": {"coordinates":[77.29789,28.430575],"type":"Point"}
}