{
  "type": "Feature",
  "properties": {
    "gn:admin1_code":"36",
    "gn:admin2_code":"132.0",
    "gn:asciiname":"Hasanpur",
    "gn:country_code":"IN",
    "gn:dem":324,
    "gn:feature_class":"P",
    "gn:feature_code":"PPL",
    "gn:name":"Hasanpur",
    "gn:population":0,
    "gn:timezone":"Asia/Kolkata",
    "iso:country":"IN",
    "ks:ks_name":"Hasunpur",
    "ks:ks_pop":1014,
    "ks:ks_type":"VILLAGE",
    "ks:ks_uagg_main":0,
    "name:ara_x_preferred":[
        "\u062d\u0633\u0646 \u0628\u0648\u0631"
    ],
    "name:ben_bn_x_preferred":[
        "\u09b9\u09be\u09b8\u09be\u09a8\u09aa\u09c1\u09b0"
    ],
    "name:ben_in_x_preferred":[
        "\u09b9\u09be\u09b8\u09be\u09a8\u09aa\u09c1\u09b0"
    ],
    "name:bih_x_preferred":[
        "\u0939\u0938\u0928\u092a\u0941\u0930"
    ],
    "name:bpy_x_preferred":[
        "\u09b9\u09be\u09b8\u09be\u09a8\u09aa\u09c1\u09b0"
    ],
    "name:ceb_x_preferred":[
        "Hasanpur"
    ],
    "name:deu_x_preferred":[
        "Hasanpur"
    ],
    "name:eng_x_preferred":[
        "Hasunpur"
    ],
    "name:fas_x_preferred":[
        "\u062d\u0633\u0646\u200c\u067e\u0648\u0631"
    ],
    "name:guj_x_preferred":[
        "\u0ab9\u0ab8\u0aa8\u0aaa\u0ac1\u0ab0"
    ],
    "name:hin_x_preferred":[
        "\u0939\u0938\u0928\u092a\u0941\u0930"
    ],
    "name:ita_x_preferred":[
        "Hasanpur"
    ],
    "name:kan_x_preferred":[
        "\u0cb9\u0cb8\u0ca8\u0ccd"
    ],
    "name:mal_x_preferred":[
        "\u0d39\u0d38\u0d7b\u0d2a\u0d42\u0d7c"
    ],
    "name:mar_x_preferred":[
        "\u0939\u0938\u0928\u092a\u0941\u0930"
    ],
    "name:mlg_x_preferred":[
        "Hasanpur"
    ],
    "name:msa_x_preferred":[
        "Hasanpur"
    ],
    "name:nep_x_preferred":[
        "\u0939\u0938\u0928\u092a\u0941\u0930"
    ],
    "name:new_x_preferred":[
        "\u0939\u0938\u0928\u092a\u0941\u0930"
    ],
    "name:nld_x_preferred":[
        "Hasanpur"
    ],
    "name:pan_x_preferred":[
        "\u0a39\u0a38\u0a28\u0a2a\u0a41\u0a30"
    ],
    "name:pol_x_preferred":[
        "Hasanpur"
    ],
    "name:por_x_preferred":[
        "Hasanpur"
    ],
    "name:tam_x_preferred":[
        "\u0bb9\u0b9a\u0ba9\u0bcd\u0baa\u0bc2\u0bb0\u0bcd"
    ],
    "name:tel_x_preferred":[
        "\u0c39\u0c38\u0c28\u0c4d"
    ],
    "name:urd_x_preferred":[
        "\u062d\u0633\u0646 \u067e\u0648\u0631"
    ],
    "name:vie_x_preferred":[
        "Hasanpur"
    ],
    "name:zho_x_preferred":[
        "\u54c8\u6851\u666e\u5c14"
    ],
    "wof:name":"Hasunpur",
    "wof:placetype":"neighbourhood",
    "wof:population":1014
},
  "geometry": {"coordinates":[77.658518,30.205422],"type":"Point"}
}