{
  "type": "Feature",
  "properties": {
    "gn:admin1_code":"24.0",
    "gn:admin2_code":"122.0",
    "gn:asciiname":"Rampuriya",
    "gn:country_code":"IN",
    "gn:dem":449,
    "gn:feature_class":"P",
    "gn:feature_code":"PPL",
    "gn:name":"R\u0101mpur\u012bya",
    "gn:population":0,
    "gn:timezone":"Asia/Kolkata",
    "iso:country":"IN",
    "wof:name":"Rampuriya",
    "wof:placetype":"locality"
},
  "geometry": {"coordinates":[74.45033000000002,25.28382],"type":"Point"}
}