{
  "type": "Feature",
  "properties": {
    "iso:country":"IN",
    "ks:ks_name":"Dhomdhari",
    "ks:ks_pop":242,
    "ks:ks_type":"VILLAGE",
    "name:eng_x_preferred":[
        "Dhomdhari"
    ],
    "wof:name":"Dhomdhari",
    "wof:placetype":"locality",
    "wof:population":242
},
  "geometry": {"coordinates":[78.710671,19.283896],"type":"Point"}
}