{
  "type": "Feature",
  "properties": {
    "gn:admin1_code":"19.0",
    "gn:admin2_code":"555.0",
    "gn:asciiname":"Ghodedurg",
    "gn:country_code":"IN",
    "gn:dem":744,
    "gn:feature_class":"P",
    "gn:feature_code":"PPL",
    "gn:name":"Ghodedurg",
    "gn:population":0,
    "gn:timezone":"Asia/Kolkata",
    "iso:country":"IN",
    "ks:ks_name":"Ghodedurg",
    "ks:ks_pop":135,
    "ks:ks_type":"HABITATION",
    "name:eng_x_preferred":[
        "Ghodedurg"
    ],
    "wof:name":"Ghodedurg",
    "wof:placetype":"locality",
    "wof:population":135
},
  "geometry": {"coordinates":[74.44022200000001,15.696804],"type":"Point"}
}