{
  "type": "Feature",
  "properties": {
    "gn:country":"IN",
    "gn:fcode":"PPL",
    "gn:pop":53468,
    "iso:country":"IN",
    "name:ben_x_preferred":[
        "\u09b0\u09be\u09ae\u09aa\u09c1\u09b0\u09b9\u09be\u099f"
    ],
    "name:bpy_x_preferred":[
        "\u09b0\u09be\u09ae\u09aa\u09c1\u09b0\u09b9\u09be\u099f"
    ],
    "name:deu_x_preferred":[
        "Rampurhat"
    ],
    "name:eng_x_preferred":[
        "Rampurhat"
    ],
    "name:fra_x_preferred":[
        "Rampurhat"
    ],
    "name:guj_x_preferred":[
        "\u0ab0\u0abe\u0aae\u0aaa\u0ac1\u0ab0\u0ab9\u0a9f"
    ],
    "name:ita_x_preferred":[
        "Rampurhat"
    ],
    "name:jpn_x_preferred":[
        "\u30e9\u30e0\u30d1\u30eb\u30cf\u30c3\u30c8"
    ],
    "name:kan_x_preferred":[
        "\u0cb0\u0cbe\u0c82\u0caa\u0cc1\u0cb0\u0ccd\u0cb9\u0cbe\u0ca4\u0ccd"
    ],
    "name:kor_x_preferred":[
        "\ub78c\ud478\ub78f"
    ],
    "name:mlg_x_preferred":[
        "Rampurhat"
    ],
    "name:msa_x_preferred":[
        "Rampurhat"
    ],
    "name:nld_x_preferred":[
        "Rampurhat"
    ],
    "name:ori_x_preferred":[
        "\u0b30\u0b3e\u0b2e\u0b2a\u0b41\u0b30\u0b39\u0b3e\u0b1f"
    ],
    "name:por_x_preferred":[
        "Rampurhat"
    ],
    "name:rus_x_preferred":[
        "\u0420\u0430\u043c\u043f\u0443\u0440\u0445\u0430\u0442"
    ],
    "name:spa_x_preferred":[
        "Rampurhat"
    ],
    "name:tam_x_preferred":[
        "\u0bb0\u0bbe\u0bae\u0baa\u0bc1\u0bb0\u0bcd\u0bb9\u0bbe\u0b9f\u0bcd"
    ],
    "name:tel_x_preferred":[
        "\u0c30\u0c3e\u0c02\u0c2a\u0c41\u0c30\u0c4d\u0c39\u0c1f\u0c4d"
    ],
    "name:urd_x_preferred":[
        "\u0631\u0627\u0645\u067e\u0648\u0631\u06c1\u0627\u062a"
    ],
    "name:vie_x_preferred":[
        "Rampurhat"
    ],
    "name:zho_x_preferred":[
        "\u62c9\u59c6\u666e\u5c14\u54c8\u7279"
    ],
    "qs:name":"R\u0101mpur H\u0101t",
    "qs:photos_9r":0,
    "qs:photos_sr":0,
    "qs:pop_sr":"8",
    "wof:name":"R\u0101mpur H\u0101t",
    "wof:placetype":"locality",
    "wof:population":53468
},
  "geometry": {"coordinates":[87.78274999999999,24.17737],"type":"Point"}
}