{
  "type": "Feature",
  "properties": {
    "gn:admin1_code":"36",
    "gn:admin2_code":"152.0",
    "gn:asciiname":"Adampur",
    "gn:country_code":"IN",
    "gn:dem":161,
    "gn:feature_class":"P",
    "gn:feature_code":"PPL",
    "gn:name":"Adampur",
    "gn:population":0,
    "gn:timezone":"Asia/Kolkata",
    "iso:country":"IN",
    "name:ben_x_preferred":[
        "\u0986\u09a6\u09ae\u09aa\u09c1\u09b0"
    ],
    "name:bpy_x_preferred":[
        "\u0986\u09a6\u09ae\u09aa\u09c1\u09b0"
    ],
    "name:fas_x_preferred":[
        "\u0627\u062f\u0627\u0645\u067e\u0648\u0631"
    ],
    "name:hin_x_preferred":[
        "\u0906\u0926\u092e\u092a\u0941\u0930"
    ],
    "name:ita_x_preferred":[
        "Adampur"
    ],
    "name:min_x_preferred":[
        "Adampur"
    ],
    "name:mlg_x_preferred":[
        "Adampur"
    ],
    "name:msa_x_preferred":[
        "Adampur"
    ],
    "name:new_x_preferred":[
        "\u0906\u0926\u092e\u092a\u0941\u0930"
    ],
    "name:nld_x_preferred":[
        "Adampur"
    ],
    "name:pan_x_preferred":[
        "\u0a06\u0a26\u0a2e\u0a2a\u0a41\u0a30"
    ],
    "name:por_x_preferred":[
        "Adampur"
    ],
    "name:spa_x_preferred":[
        "Adampur"
    ],
    "name:tam_x_preferred":[
        "\u0b86\u0ba4\u0bae\u0bcd\u0baa\u0bc2\u0bb0\u0bcd"
    ],
    "name:vie_x_preferred":[
        "Adampur"
    ],
    "name:zho_x_preferred":[
        "\u963f\u8fbe\u59c6\u666e\u5c14"
    ],
    "wof:name":"Adampur",
    "wof:placetype":"locality"
},
  "geometry": {"coordinates":[79.9884,28.00009],"type":"Point"}
}