{
  "type": "Feature",
  "properties": {
    "iso:country":"IN",
    "ks:ks_name":"Chandangundo",
    "ks:ks_pop":84,
    "ks:ks_type":"VILLAGE",
    "name:eng_x_preferred":[
        "Chandangundo"
    ],
    "wof:name":"Chandangundo",
    "wof:placetype":"locality",
    "wof:population":84
},
  "geometry": {"coordinates":[85.77697000000001,24.236645],"type":"Point"}
}