{
  "type": "Feature",
  "properties": {
    "iso:country":"IN",
    "ks:ks_name":"Bakrapara",
    "ks:ks_pop":583,
    "ks:ks_type":"HABITATION",
    "name:eng_x_preferred":[
        "Bakrapara"
    ],
    "wof:name":"Bakrapara",
    "wof:placetype":"locality",
    "wof:population":583
},
  "geometry": {"coordinates":[91.267455,25.896939],"type":"Point"}
}