{
  "type": "Feature",
  "properties": {
    "gn:admin1_code":"19.0",
    "gn:admin2_code":"562",
    "gn:asciiname":"Amargol",
    "gn:country_code":"IN",
    "gn:dem":648,
    "gn:feature_class":"P",
    "gn:feature_code":"PPL",
    "gn:name":"Amargol",
    "gn:population":0,
    "gn:timezone":"Asia/Kolkata",
    "iso:country":"IN",
    "wof:name":"Amargol",
    "wof:placetype":"locality"
},
  "geometry": {"coordinates":[75.09792,15.3979],"type":"Point"}
}