{
  "type": "Feature",
  "properties": {
    "gn:admin1_code":"12.0",
    "gn:admin2_code":"008",
    "gn:asciiname":"Nawa Behk",
    "gn:country_code":"IN",
    "gn:dem":2750,
    "gn:feature_class":"P",
    "gn:feature_code":"PPL",
    "gn:name":"N\u0101wa Behk",
    "gn:population":0,
    "gn:timezone":"Asia/Kolkata",
    "iso:country":"IN",
    "name:und_x_variant":[
        "N\u0101wa Behk",
        "N\u0101wa Baihk"
    ],
    "wof:name":"Nawa Behk",
    "wof:placetype":"locality"
},
  "geometry": {"coordinates":[74.13928,34.28213],"type":"Point"}
}