{
  "type": "Feature",
  "properties": {
    "iso:country":"IN",
    "ks:ks_name":"Hemrajpur",
    "ks:ks_pop":618,
    "ks:ks_type":"VILLAGE",
    "ks:ks_uagg_main":0,
    "name:eng_x_preferred":[
        "Hemrajpur"
    ],
    "wof:name":"Hemrajpur",
    "wof:placetype":"neighbourhood",
    "wof:population":618
},
  "geometry": {"coordinates":[82.97349800000001,26.415729],"type":"Point"}
}