{
  "type": "Feature",
  "properties": {
    "iso:country":"IN",
    "ks:ks_name":"Rawal Gaon",
    "ks:ks_pop":339,
    "ks:ks_type":"VILLAGE",
    "ks:ks_uagg_main":0,
    "name:eng_x_preferred":[
        "Rawal Gaon"
    ],
    "wof:name":"Rawal Gaon",
    "wof:placetype":"neighbourhood",
    "wof:population":339
},
  "geometry": {"coordinates":[80.046333,29.656758],"type":"Point"}
}