{
  "type": "Feature",
  "properties": {
    "iso:country":"IN",
    "ks:ks_alt_nam":"UTTAR MARAKHATA",
    "ks:ks_name":"Uttar Marakhata",
    "ks:ks_pop":920,
    "ks:ks_type":"HABITATION",
    "name:eng_x_preferred":[
        "Uttar Marakhata"
    ],
    "wof:name":"Uttar Marakhata",
    "wof:placetype":"locality",
    "wof:population":920
},
  "geometry": {"coordinates":[89.795897,26.579283],"type":"Point"}
}