{
  "type": "Feature",
  "properties": {
    "iso:country":"IN",
    "ks:ks_name":"Buruda",
    "ks:ks_pop":513,
    "ks:ks_type":"VILLAGE",
    "name:eng_x_preferred":[
        "Buruda"
    ],
    "wof:name":"Buruda",
    "wof:placetype":"locality",
    "wof:population":513
},
  "geometry": {"coordinates":[84.014117,18.880954],"type":"Point"}
}