{
  "type": "Feature",
  "properties": {
    "iso:country":"IN",
    "ks:ks_name":"Antrasingi",
    "ks:ks_pop":786,
    "ks:ks_type":"VILLAGE",
    "name:eng_x_preferred":[
        "Antrasingi"
    ],
    "wof:name":"Antrasingi",
    "wof:placetype":"locality",
    "wof:population":786
},
  "geometry": {"coordinates":[84.583185,19.081524],"type":"Point"}
}