{
  "type": "Feature",
  "properties": {
    "gn:admin1_code":"35",
    "gn:admin2_code":"430.0",
    "gn:asciiname":"Paipkhara",
    "gn:country_code":"IN",
    "gn:dem":321,
    "gn:feature_class":"P",
    "gn:feature_code":"PPL",
    "gn:name":"Paipkhara",
    "gn:population":0,
    "gn:timezone":"Asia/Kolkata",
    "iso:country":"IN",
    "ks:ks_name":"Paipakhara",
    "ks:ks_pop":398,
    "ks:ks_type":"VILLAGE",
    "ks:ks_uagg_main":0,
    "name:eng_x_preferred":[
        "Paipakhara"
    ],
    "wof:name":"Paipakhara",
    "wof:placetype":"neighbourhood",
    "wof:population":398
},
  "geometry": {"coordinates":[81.22905299999999,24.597894],"type":"Point"}
}