{
  "type": "Feature",
  "properties": {
    "gn:admin1_code":"35.0",
    "gn:admin2_code":"455.0",
    "gn:asciiname":"Mankadei",
    "gn:country_code":"IN",
    "gn:dem":961,
    "gn:feature_class":"P",
    "gn:feature_code":"PPL",
    "gn:name":"M\u0101nk\u0101dei",
    "gn:population":0,
    "gn:timezone":"Asia/Kolkata",
    "iso:country":"IN",
    "ks:ks_alt_nam":"M\u0101nk\u0101dei",
    "ks:ks_name":"Mankadei",
    "ks:ks_pop":721,
    "ks:ks_type":"VILLAGE",
    "name:eng_x_preferred":[
        "Mankadei"
    ],
    "name:eng_x_variant":[
        "M\u0101nk\u0101dei"
    ],
    "wof:name":"Mankadei",
    "wof:placetype":"locality",
    "wof:population":721
},
  "geometry": {"coordinates":[78.654785,22.266624],"type":"Point"}
}