{
  "type": "Feature",
  "properties": {
    "gn:admin1_code":"35.0",
    "gn:admin2_code":"455.0",
    "gn:asciiname":"Mankadei",
    "gn:country_code":"IN",
    "gn:dem":961,
    "gn:feature_class":"P",
    "gn:feature_code":"PPL",
    "gn:name":"M\u0101nk\u0101dei",
    "gn:population":0,
    "gn:timezone":"Asia/Kolkata",
    "iso:country":"IN",
    "wof:name":"Mankadei",
    "wof:placetype":"locality"
},
  "geometry": {"coordinates":[78.65479999999999,22.26583],"type":"Point"}
}