{
  "type": "Feature",
  "properties": {
    "gn:country":"IN",
    "gn:fcode":"PPL",
    "gn:pop":56497,
    "iso:country":"IN",
    "name:ben_x_preferred":[
        "\u0995\u09cb\u09b2\u09cd\u09b2\u09c7\u0997\u09be\u09b2"
    ],
    "name:bpy_x_preferred":[
        "\u0995\u09cb\u09b2\u09cd\u09b2\u09c7\u0997\u09be\u09b2"
    ],
    "name:chi_x_preferred":[
        "\u79d1\u5c14\u83b1\u52a0\u5c14"
    ],
    "name:dut_x_preferred":[
        "Kollegal"
    ],
    "name:eng_x_preferred":[
        "Kollegal"
    ],
    "name:fre_x_preferred":[
        "Kollegal"
    ],
    "name:ger_x_preferred":[
        "Kollegal"
    ],
    "name:guj_x_preferred":[
        "\u0a95\u0acb\u0ab2\u0ac7\u0a97\u0ab2"
    ],
    "name:ita_x_preferred":[
        "Kollegal"
    ],
    "name:jpn_x_preferred":[
        "\u30b3\u30ec\u30ac\u30eb"
    ],
    "name:kan_x_preferred":[
        "\u0c95\u0cca\u0cb3\u0ccd\u0cb3\u0cc7\u0c97\u0cbe\u0cb2"
    ],
    "name:kor_x_preferred":[
        "\ucf5c\ub808\uac08"
    ],
    "name:may_x_preferred":[
        "Kollegal"
    ],
    "name:mlg_x_preferred":[
        "Kollegal"
    ],
    "name:nan_x_preferred":[
        "Kollegal"
    ],
    "name:new_x_preferred":[
        "\u0915\u094b\u0932\u094d\u0932\u0947\u0917\u0932"
    ],
    "name:por_x_preferred":[
        "Kollegal"
    ],
    "name:rus_x_preferred":[
        "\u041a\u043e\u043b\u043b\u0435\u0433\u0430\u043b"
    ],
    "name:san_x_preferred":[
        "\u0915\u094b\u0933\u094d\u0933\u0947\u0917\u093e\u0932\u0903"
    ],
    "name:spa_x_preferred":[
        "Kollegal"
    ],
    "name:swe_x_preferred":[
        "Kolleg\u0101l"
    ],
    "name:tam_x_preferred":[
        "\u0b95\u0bca\u0bb2\u0bcd\u0bb2\u0bc7\u0b95\u0bb2\u0bcd"
    ],
    "name:tel_x_preferred":[
        "\u0c15\u0c4a\u0c32\u0c4d\u0c32\u0c47\u0c17\u0c32\u0c4d"
    ],
    "name:unk_x_variant":[
        "Collegal"
    ],
    "name:urd_x_preferred":[
        "\u06a9\u0648\u0644\u06cc\u062c\u0627\u0644"
    ],
    "name:vie_x_preferred":[
        "Kollegal"
    ],
    "qs:name":"Kollegal",
    "qs:name_adm0":"India",
    "qs:name_adm1":"Karnataka",
    "qs:photos_9k":1,
    "qs:photos_9r":1,
    "qs:photos_all":1,
    "qs:photos_sr":0,
    "qs:placetype":"Town",
    "qs:pop_sr":"8",
    "wd:wordcount":831,
    "wof:name":"Kollegal",
    "wof:placetype":"locality",
    "wof:population":56497
},
  "geometry": {"coordinates":[77.10693999999999,12.1569],"type":"Point"}
}