{
  "type": "Feature",
  "properties": {
    "iso:country":"IN",
    "ks:ks_name":"Honnenahalli G Hatti",
    "ks:ks_pop":248,
    "ks:ks_type":"HABITATION",
    "name:eng_x_preferred":[
        "Honnenahalli G Hatti"
    ],
    "wof:name":"Honnenahalli G Hatti",
    "wof:placetype":"locality",
    "wof:population":248
},
  "geometry": {"coordinates":[76.83707,13.856379],"type":"Point"}
}