{
  "type": "Feature",
  "properties": {
    "iso:country":"IN",
    "ks:ks_name":"Thanda Korangrapady",
    "ks:ks_pop":231,
    "ks:ks_type":"HABITATION",
    "name:eng_x_preferred":[
        "Thanda Korangrapady"
    ],
    "wof:name":"Thanda Korangrapady",
    "wof:placetype":"locality",
    "wof:population":231
},
  "geometry": {"coordinates":[74.761764,13.298455],"type":"Point"}
}