{
  "type": "Feature",
  "properties": {
    "iso:country":"IN",
    "ks:ks_alt_nam":"BAGHMARWA",
    "ks:ks_name":"Baghmarwa",
    "ks:ks_pop":165,
    "ks:ks_type":"HABITATION",
    "name:eng_x_preferred":[
        "Baghmarwa"
    ],
    "wof:name":"Baghmarwa",
    "wof:placetype":"locality",
    "wof:population":165
},
  "geometry": {"coordinates":[84.635627,24.598486],"type":"Point"}
}