{
  "type": "Feature",
  "properties": {
    "iso:country":"IN",
    "ks:ks_name":"Jiya Pur",
    "ks:ks_pop":230,
    "ks:ks_type":"HABITATION",
    "ks:ks_uagg_main":0,
    "name:eng_x_preferred":[
        "Jiya Pur"
    ],
    "wof:name":"Jiya Pur",
    "wof:placetype":"neighbourhood",
    "wof:population":230
},
  "geometry": {"coordinates":[81.458023,26.515425],"type":"Point"}
}