{
  "type": "Feature",
  "properties": {
    "iso:country":"IN",
    "ks:ks_alt_nam":"Singimari part 1",
    "ks:ks_name":"Singimari Part 1",
    "ks:ks_pop":1056,
    "ks:ks_type":"HABITATION",
    "name:eng_x_preferred":[
        "Singimari Part 1"
    ],
    "wof:name":"Singimari Part 1",
    "wof:placetype":"locality",
    "wof:population":1056
},
  "geometry": {"coordinates":[91.842741,26.348902],"type":"Point"}
}