{
  "type": "Feature",
  "properties": {
    "gn:admin1_code":"34.0",
    "gn:admin2_code":"219.0",
    "gn:asciiname":"Lohchha",
    "gn:country_code":"IN",
    "gn:dem":57,
    "gn:feature_class":"P",
    "gn:feature_code":"PPL",
    "gn:name":"Lohchha",
    "gn:population":0,
    "gn:timezone":"Asia/Kolkata",
    "iso:country":"IN",
    "ks:ks_name":"Lohchha",
    "ks:ks_pop":1253,
    "ks:ks_type":"VILLAGE",
    "ks:ks_uagg_main":0,
    "name:eng_x_preferred":[
        "Lohchha"
    ],
    "wof:name":"Lohchha",
    "wof:placetype":"neighbourhood",
    "wof:population":1253
},
  "geometry": {"coordinates":[84.978846,25.827321],"type":"Point"}
}