{
  "type": "Feature",
  "properties": {
    "iso:country":"IN",
    "ks:ks_name":"Muthawali Trf Tala",
    "ks:ks_pop":675,
    "ks:ks_type":"VILLAGE",
    "name:eng_x_preferred":[
        "Muthawali Trf Tala"
    ],
    "wof:name":"Muthawali Trf Tala",
    "wof:placetype":"locality",
    "wof:population":675
},
  "geometry": {"coordinates":[73.213688,18.304412],"type":"Point"}
}