{
  "type": "Feature",
  "properties": {
    "iso:country":"IN",
    "ks:ks_name":"Paikbar",
    "ks:ks_pop":278,
    "ks:ks_type":"VILLAGE",
    "ks:ks_uagg_main":0,
    "name:eng_x_preferred":[
        "Paikbar"
    ],
    "wof:name":"Paikbar",
    "wof:placetype":"neighbourhood",
    "wof:population":278
},
  "geometry": {"coordinates":[87.28959999999999,21.943574],"type":"Point"}
}