{
  "type": "Feature",
  "properties": {
    "iso:country":"IN",
    "ks:ks_name":"Bethasaravu",
    "ks:ks_pop":365,
    "ks:ks_type":"HABITATION",
    "name:eng_x_preferred":[
        "Bethasaravu"
    ],
    "wof:name":"Bethasaravu",
    "wof:placetype":"locality",
    "wof:population":365
},
  "geometry": {"coordinates":[75.08130199999999,12.81464],"type":"Point"}
}