{
  "type": "Feature",
  "properties": {
    "iso:country":"IN",
    "ks:ks_name":"Mundia Ahmed Nagar",
    "ks:ks_pop":3548,
    "ks:ks_type":"VILLAGE",
    "name:eng_x_preferred":[
        "Mundia Ahmed Nagar"
    ],
    "wof:name":"Mundia Ahmed Nagar",
    "wof:placetype":"neighbourhood",
    "wof:population":3548
},
  "geometry": {"coordinates":[79.472977,28.426045],"type":"Point"}
}