{
  "type": "Feature",
  "properties": {
    "gn:country":"IN",
    "gn:fcode":"PPL",
    "gn:population":76973,
    "iso:country":"IN",
    "name:ben_x_preferred":[
        "\u09ae\u09be\u0993\u09a8\u09be"
    ],
    "name:bpy_x_preferred":[
        "\u09ae\u09be\u09f1\u09be\u09a8\u09be"
    ],
    "name:ceb_x_preferred":[
        "Maw\u0101na"
    ],
    "name:deu_x_preferred":[
        "Mawana"
    ],
    "name:eng_x_preferred":[
        "Mawana"
    ],
    "name:fra_x_preferred":[
        "Mawana"
    ],
    "name:guj_x_preferred":[
        "\u0aae\u0abe\u0ab5\u0abe\u0aa8\u0abe"
    ],
    "name:hin_x_preferred":[
        "\u092e\u0935\u093e\u0928\u093e"
    ],
    "name:ita_x_preferred":[
        "Mawana"
    ],
    "name:jpn_x_preferred":[
        "\u30de\u30ef\u30ca"
    ],
    "name:kan_x_preferred":[
        "\u0cae\u0cb5\u0cbe\u0ca8\u0cbe"
    ],
    "name:kor_x_preferred":[
        "\ub9c8\uc640\ub098"
    ],
    "name:mlg_x_preferred":[
        "Mawana"
    ],
    "name:msa_x_preferred":[
        "Mawana"
    ],
    "name:nan_x_preferred":[
        "Mawana"
    ],
    "name:new_x_preferred":[
        "\u092e\u0935\u0928\u093e"
    ],
    "name:nld_x_preferred":[
        "Mawana"
    ],
    "name:pol_x_preferred":[
        "Mawana"
    ],
    "name:por_x_preferred":[
        "Mawana"
    ],
    "name:rus_x_preferred":[
        "\u041c\u0430\u0432\u0430\u043d\u0430"
    ],
    "name:spa_x_preferred":[
        "Mawana"
    ],
    "name:swe_x_preferred":[
        "Mawana"
    ],
    "name:tam_x_preferred":[
        "\u0bae\u0bbe\u0bb5\u0bbe\u0ba9\u0bbe"
    ],
    "name:tel_x_preferred":[
        "\u0c2e\u0c35\u0c3e\u0c28"
    ],
    "name:urd_x_preferred":[
        "\u0645\u0648\u0627\u0646\u0627"
    ],
    "name:vie_x_preferred":[
        "Mawana"
    ],
    "name:zho_x_preferred":[
        "\u9a6c\u74e6\u7eb3"
    ],
    "qs:name":"Mawana",
    "qs:name_adm0":"India",
    "qs:name_adm1":"Uttar Pradesh",
    "qs:photos_9k":1,
    "qs:photos_9r":1,
    "qs:photos_all":1,
    "qs:photos_sr":0,
    "qs:placetype":"Town",
    "qs:pop_sr":"8",
    "wd:wordcount":300,
    "wof:name":"Mawana",
    "wof:placetype":"locality",
    "wof:population":76973
},
  "geometry": {"coordinates":[77.92134,29.10436],"type":"Point"}
}