{
  "type": "Feature",
  "properties": {
    "iso:country":"IN",
    "ks:ks_name":"Kandraker Baripara",
    "ks:ks_pop":200,
    "ks:ks_type":"HABITATION",
    "name:eng_x_preferred":[
        "Kandraker Baripara"
    ],
    "wof:name":"Kandraker Baripara",
    "wof:placetype":"locality",
    "wof:population":200
},
  "geometry": {"coordinates":[92.18939,24.135179],"type":"Point"}
}