{
  "type": "Feature",
  "properties": {
    "gn:admin1_code":"36",
    "gn:admin2_code":"197.0",
    "gn:asciiname":"Murdi",
    "gn:country_code":"IN",
    "gn:dem":83,
    "gn:feature_class":"P",
    "gn:feature_code":"PPL",
    "gn:name":"Murdi",
    "gn:population":0,
    "gn:timezone":"Asia/Kolkata",
    "iso:country":"IN",
    "ks:ks_name":"Murdi",
    "ks:ks_pop":1294,
    "ks:ks_type":"VILLAGE",
    "ks:ks_uagg_main":0,
    "name:eng_x_preferred":[
        "Murdi"
    ],
    "wof:name":"Murdi",
    "wof:placetype":"neighbourhood",
    "wof:population":1294
},
  "geometry": {"coordinates":[82.92931299999999,25.486852],"type":"Point"}
}