{
  "type": "Feature",
  "properties": {
    "iso:country":"IN",
    "ks:ks_alt_nam":"Tokrapara Gaon Pt III",
    "ks:ks_name":"Tokrapara Gaon Pt Iii",
    "ks:ks_pop":105,
    "ks:ks_type":"HABITATION",
    "name:eng_x_preferred":[
        "Tokrapara Gaon Pt Iii"
    ],
    "wof:name":"Tokrapara Gaon Pt Iii",
    "wof:placetype":"locality",
    "wof:population":105
},
  "geometry": {"coordinates":[89.989756,26.308],"type":"Point"}
}