{
  "type": "Feature",
  "properties": {
    "gn:admin1_code":"11",
    "gn:admin2_code":"27.0",
    "gn:asciiname":"Jandroh",
    "gn:country_code":"IN",
    "gn:dem":1605,
    "gn:feature_class":"P",
    "gn:feature_code":"PPL",
    "gn:name":"Jandroh",
    "gn:population":0,
    "gn:timezone":"Asia/Kolkata",
    "iso:country":"IN",
    "wof:name":"Jandroh",
    "wof:placetype":"locality"
},
  "geometry": {"coordinates":[76.98065,31.47815],"type":"Point"}
}