{
  "type": "Feature",
  "properties": {
    "gn:admin1_code":"25.0",
    "gn:admin2_code":"620.0",
    "gn:asciiname":"Jambugambalpuram",
    "gn:country_code":"IN",
    "gn:dem":42,
    "gn:feature_class":"P",
    "gn:feature_code":"PPL",
    "gn:name":"Jambugamb\u0101lpuram",
    "gn:population":0,
    "gn:timezone":"Asia/Kolkata",
    "iso:country":"IN",
    "wof:name":"Jambugambalpuram",
    "wof:placetype":"neighbourhood"
},
  "geometry": {"coordinates":[79.2398,10.74229],"type":"Point"}
}