{
  "type": "Feature",
  "properties": {
    "gn:admin1_code":"34.0",
    "gn:admin2_code":"213.0",
    "gn:asciiname":"Nandana",
    "gn:country_code":"IN",
    "gn:dem":57,
    "gn:feature_class":"P",
    "gn:feature_code":"PPL",
    "gn:name":"Nand\u0101na",
    "gn:population":0,
    "gn:timezone":"Asia/Kolkata",
    "iso:country":"IN",
    "name:urd_x_preferred":[
        "\u0642\u0644\u0639\u06c1 \u0646\u0646\u062f\u0646\u06c1"
    ],
    "wof:name":"Nandana",
    "wof:placetype":"locality"
},
  "geometry": {"coordinates":[87.08338000000001,26.05466],"type":"Point"}
}