{
  "type": "Feature",
  "properties": {
    "iso:country":"IN",
    "ks:ks_name":"Coffee Thotta",
    "ks:ks_pop":196,
    "ks:ks_type":"HABITATION",
    "name:eng_x_preferred":[
        "Coffee Thotta"
    ],
    "wof:name":"Coffee Thotta",
    "wof:placetype":"locality",
    "wof:population":196
},
  "geometry": {"coordinates":[75.30888299999999,13.33085],"type":"Point"}
}