{
  "type": "Feature",
  "properties": {
    "gn:admin1_code":"35",
    "gn:admin2_code":"445.0",
    "gn:asciiname":"Murari",
    "gn:country_code":"IN",
    "gn:dem":319,
    "gn:feature_class":"P",
    "gn:feature_code":"PPL",
    "gn:name":"Mur\u0101ri",
    "gn:population":0,
    "gn:timezone":"Asia/Kolkata",
    "iso:country":"IN",
    "name:ceb_x_preferred":[
        "Murari"
    ],
    "name:tel_x_preferred":[
        "\u0c2e\u0c41\u0c30\u0c3e\u0c30\u0c3f"
    ],
    "wof:name":"Murari",
    "wof:placetype":"locality"
},
  "geometry": {"coordinates":[77.90798000000002,22.93318],"type":"Point"}
}