{
  "type": "Feature",
  "properties": {
    "gn:admin1_code":"39.0",
    "gn:admin2_code":"65.0",
    "gn:asciiname":"Borabagar",
    "gn:country_code":"IN",
    "gn:dem":1006,
    "gn:feature_class":"P",
    "gn:feature_code":"PPL",
    "gn:name":"Borabagar",
    "gn:population":0,
    "gn:timezone":"Asia/Kolkata",
    "iso:country":"IN",
    "wof:name":"Borabagar",
    "wof:placetype":"locality"
},
  "geometry": {"coordinates":[79.86703,29.31449000000001],"type":"Point"}
}