{
  "type": "Feature",
  "properties": {
    "gn:admin1_code":"36",
    "gn:admin2_code":"177.0",
    "gn:asciiname":"Rampur Baihari",
    "gn:country_code":"IN",
    "gn:dem":99,
    "gn:feature_class":"P",
    "gn:feature_code":"PPL",
    "gn:name":"R\u0101mpur Baih\u0101ri",
    "gn:population":0,
    "gn:timezone":"Asia/Kolkata",
    "iso:country":"IN",
    "ks:ks_name":"Rampur Baihari",
    "ks:ks_pop":539,
    "ks:ks_type":"VILLAGE",
    "name:eng_x_preferred":[
        "Rampur Baihari"
    ],
    "wof:name":"Rampur Baihari",
    "wof:placetype":"locality",
    "wof:population":539
},
  "geometry": {"coordinates":[82.369528,26.637764],"type":"Point"}
}