{
  "type": "Feature",
  "properties": {
    "iso:country":"IN",
    "ks:ks_name":"Pisadewadi",
    "ks:ks_pop":306,
    "ks:ks_type":"HABITATION",
    "name:eng_x_preferred":[
        "Pisadewadi"
    ],
    "wof:name":"Pisadewadi",
    "wof:placetype":"locality",
    "wof:population":306
},
  "geometry": {"coordinates":[73.770499,17.666283],"type":"Point"}
}