{
  "type": "Feature",
  "properties": {
    "iso:country":"IN",
    "ks:ks_name":"Udyavad",
    "ks:ks_pop":252,
    "ks:ks_type":"HABITATION",
    "name:eng_x_preferred":[
        "Udyavad"
    ],
    "wof:name":"Udyavad",
    "wof:placetype":"locality",
    "wof:population":252
},
  "geometry": {"coordinates":[73.936635,21.01293],"type":"Point"}
}