{
  "type": "Feature",
  "properties": {
    "gn:admin1_code":"19.0",
    "gn:admin2_code":"583.0",
    "gn:asciiname":"Gundappanayakanpalya",
    "gn:country_code":"IN",
    "gn:dem":786,
    "gn:feature_class":"P",
    "gn:feature_code":"PPL",
    "gn:name":"Gundappan\u0101yakanp\u0101lya",
    "gn:population":0,
    "gn:timezone":"Asia/Kolkata",
    "iso:country":"IN",
    "wof:name":"Gundappanayakanpalya",
    "wof:placetype":"locality"
},
  "geometry": {"coordinates":[77.39945999999998,13.46022],"type":"Point"}
}