{
  "type": "Feature",
  "properties": {
    "iso:country":"IN",
    "ks:ks_name":"Aawali",
    "ks:ks_pop":1206,
    "ks:ks_type":"HABITATION",
    "name:eng_x_preferred":[
        "Aawali"
    ],
    "wof:name":"Aawali",
    "wof:placetype":"locality",
    "wof:population":1206
},
  "geometry": {"coordinates":[75.015809,22.083808],"type":"Point"}
}