{
  "type": "Feature",
  "properties": {
    "gn:admin1_code":"34.0",
    "gn:admin2_code":"220.0",
    "gn:asciiname":"Rupnarayanpur",
    "gn:country_code":"IN",
    "gn:dem":50,
    "gn:feature_class":"P",
    "gn:feature_code":"PPL",
    "gn:name":"Rupn\u0101r\u0101yanpur",
    "gn:population":0,
    "gn:timezone":"Asia/Kolkata",
    "iso:country":"IN",
    "name:ceb_x_preferred":[
        "Rupn\u0101r\u0101yanpur"
    ],
    "name:eng_x_preferred":[
        "Rupn\u0101r\u0101yanpur"
    ],
    "name:swe_x_preferred":[
        "Rupn\u0101r\u0101yanpur"
    ],
    "name:zho_x_preferred":[
        "\u6b23\u675c\u65af\u5766\u6070\u5e03\u83b1\u9547"
    ],
    "wof:name":"Rupnarayanpur",
    "wof:placetype":"locality"
},
  "geometry": {"coordinates":[85.56881,25.67745],"type":"Point"}
}