{
  "type": "Feature",
  "properties": {
    "iso:country":"IN",
    "ks:ks_name":"Theakin Chvudu Jn",
    "ks:ks_pop":784,
    "ks:ks_type":"HABITATION",
    "ks:ks_uagg_main":0,
    "name:eng_x_preferred":[
        "Theakin Chvudu Jn"
    ],
    "wof:name":"Theakin Chvudu Jn",
    "wof:placetype":"neighbourhood",
    "wof:population":784
},
  "geometry": {"coordinates":[76.043854,11.253865],"type":"Point"}
}