{
  "type": "Feature",
  "properties": {
    "gn:admin1_code":"2.0",
    "gn:admin2_code":"543.0",
    "gn:asciiname":"Chinna Dodija",
    "gn:country_code":"IN",
    "gn:dem":399,
    "gn:feature_class":"P",
    "gn:feature_code":"PPL",
    "gn:name":"Chinna Dodija",
    "gn:population":0,
    "gn:timezone":"Asia/Kolkata",
    "iso:country":"IN",
    "ks:ks_name":"Chinadodija",
    "ks:ks_pop":306,
    "ks:ks_type":"HABITATION",
    "name:eng_x_preferred":[
        "Chinadodija"
    ],
    "name:eng_x_variant":[
        "Chinna Dodija"
    ],
    "wof:name":"Chinadodija",
    "wof:placetype":"locality",
    "wof:population":306
},
  "geometry": {"coordinates":[83.640788,18.849695],"type":"Point"}
}