{
  "type": "Feature",
  "properties": {
    "iso:country":"IN",
    "ks:ks_name":"Chandandih",
    "ks:ks_pop":904,
    "ks:ks_type":"VILLAGE",
    "ks:ks_uagg_main":0,
    "name:eng_x_preferred":[
        "Chandandih"
    ],
    "wof:name":"Chandandih",
    "wof:placetype":"neighbourhood",
    "wof:population":904
},
  "geometry": {"coordinates":[86.273325,24.218375],"type":"Point"}
}