{
  "type": "Feature",
  "properties": {
    "gn:admin1_code":"2.0",
    "gn:admin2_code":"553.0",
    "gn:asciiname":"Byadarahalli",
    "gn:country_code":"IN",
    "gn:dem":573,
    "gn:feature_class":"P",
    "gn:feature_code":"PPL",
    "gn:name":"By\u0101darahalli",
    "gn:population":0,
    "gn:timezone":"Asia/Kolkata",
    "iso:country":"IN",
    "wof:name":"Byadarahalli",
    "wof:placetype":"locality"
},
  "geometry": {"coordinates":[77.15624,14.45694],"type":"Point"}
}