{
  "type": "Feature",
  "properties": {
    "gn:admin1_code":"36",
    "gn:admin2_code":"154.0",
    "gn:asciiname":"Purwa Khushhal Tewari",
    "gn:country_code":"IN",
    "gn:dem":140,
    "gn:feature_class":"P",
    "gn:feature_code":"PPL",
    "gn:name":"Purwa Khushh\u0101l Tew\u0101ri",
    "gn:population":0,
    "gn:timezone":"Asia/Kolkata",
    "iso:country":"IN",
    "wof:name":"Purwa Khushhal Tewari",
    "wof:placetype":"locality"
},
  "geometry": {"coordinates":[80.88325999999998,27.46757],"type":"Point"}
}