{
  "type": "Feature",
  "properties": {
    "iso:country":"IN",
    "ks:ks_name":"Gauranga Chak",
    "ks:ks_pop":1313,
    "ks:ks_type":"VILLAGE",
    "name:eng_x_preferred":[
        "Gauranga Chak"
    ],
    "wof:name":"Gauranga Chak",
    "wof:placetype":"locality",
    "wof:population":1313
},
  "geometry": {"coordinates":[88.00523,22.676862],"type":"Point"}
}