{
  "type": "Feature",
  "properties": {
    "iso:country":"IN",
    "ks:ks_name":"Karadakal",
    "ks:ks_pop":124,
    "ks:ks_type":"VILLAGE",
    "name:eng_x_preferred":[
        "Karadakal"
    ],
    "wof:name":"Karadakal",
    "wof:placetype":"locality",
    "wof:population":124
},
  "geometry": {"coordinates":[76.50048200000001,16.15865],"type":"Point"}
}