{
  "type": "Feature",
  "properties": {
    "gn:admin1_code":"16",
    "gn:admin2_code":"508.0",
    "gn:asciiname":"Phokur",
    "gn:country_code":"IN",
    "gn:dem":263,
    "gn:feature_class":"P",
    "gn:feature_code":"PPL",
    "gn:name":"Phokur",
    "gn:population":0,
    "gn:timezone":"Asia/Kolkata",
    "iso:country":"IN",
    "ks:ks_name":"Pokur",
    "ks:ks_pop":94,
    "ks:ks_type":"HABITATION",
    "name:eng_x_preferred":[
        "Pokur"
    ],
    "name:eng_x_variant":[
        "Phokur"
    ],
    "name:und_x_variant":[
        "Purkahur"
    ],
    "wof:name":"Pokur",
    "wof:placetype":"locality",
    "wof:population":94
},
  "geometry": {"coordinates":[80.448763,19.485023],"type":"Point"}
}