{
  "type": "Feature",
  "properties": {
    "iso:country":"IN",
    "ks:ks_name":"Sanabankasahi",
    "ks:ks_pop":515,
    "ks:ks_type":"VILLAGE",
    "name:eng_x_preferred":[
        "Sanabankasahi"
    ],
    "wof:name":"Sanabankasahi",
    "wof:placetype":"locality",
    "wof:population":515
},
  "geometry": {"coordinates":[86.24626600000001,20.878629],"type":"Point"}
}