{
  "type": "Feature",
  "properties": {
    "gn:admin1_code":"36",
    "gn:admin2_code":"191.0",
    "gn:asciiname":"Bhukhli",
    "gn:country_code":"IN",
    "gn:dem":88,
    "gn:feature_class":"P",
    "gn:feature_code":"PPL",
    "gn:name":"Bh\u016bkhli",
    "gn:population":0,
    "gn:timezone":"Asia/Kolkata",
    "iso:country":"IN",
    "ks:ks_name":"Bhukh Ali",
    "ks:ks_pop":653,
    "ks:ks_type":"VILLAGE",
    "ks:ks_uagg_main":0,
    "name:eng_x_preferred":[
        "Bhukh Ali"
    ],
    "wof:name":"Bhukh Ali",
    "wof:placetype":"neighbourhood",
    "wof:population":653
},
  "geometry": {"coordinates":[82.73250400000001,26.136334],"type":"Point"}
}