{
  "type": "Feature",
  "properties": {
    "iso:country":"IN",
    "ks:ks_name":"Moti Bedwan",
    "ks:ks_pop":762,
    "ks:ks_type":"VILLAGE",
    "name:eng_x_preferred":[
        "Moti Bedwan"
    ],
    "wof:name":"Moti Bedwan",
    "wof:placetype":"locality",
    "wof:population":762
},
  "geometry": {"coordinates":[73.622231,21.480097],"type":"Point"}
}