{
  "type": "Feature",
  "properties": {
    "gn:admin1_code":"12",
    "gn:admin2_code":"20.0",
    "gn:asciiname":"Lhad",
    "gn:country_code":"IN",
    "gn:dem":1738,
    "gn:feature_class":"P",
    "gn:feature_code":"PPL",
    "gn:name":"Lhad",
    "gn:population":0,
    "gn:timezone":"Asia/Kolkata",
    "iso:country":"IN",
    "wof:name":"Lhad",
    "wof:placetype":"locality"
},
  "geometry": {"coordinates":[74.91578,33.39854],"type":"Point"}
}