{
  "type": "Feature",
  "properties": {
    "iso:country":"IN",
    "ks:ks_name":"Dolpady",
    "ks:ks_pop":2183,
    "ks:ks_type":"VILLAGE",
    "name:eng_x_preferred":[
        "Dolpady"
    ],
    "wof:name":"Dolpady",
    "wof:placetype":"locality",
    "wof:population":2183
},
  "geometry": {"coordinates":[75.40034900000001,12.739896],"type":"Point"}
}