{
  "type": "Feature",
  "properties": {
    "iso:country":"IN",
    "ks:ks_alt_nam":"bhidewadi",
    "ks:ks_name":"Bhidewadi",
    "ks:ks_pop":28,
    "ks:ks_type":"HABITATION",
    "name:eng_x_preferred":[
        "Bhidewadi"
    ],
    "wof:name":"Bhidewadi",
    "wof:placetype":"locality",
    "wof:population":28
},
  "geometry": {"coordinates":[73.95372399999999,15.839156],"type":"Point"}
}