{
  "type": "Feature",
  "properties": {
    "iso:country":"IN",
    "ks:ks_name":"Kanasale",
    "ks:ks_pop":8,
    "ks:ks_type":"HABITATION",
    "name:eng_x_preferred":[
        "Kanasale"
    ],
    "wof:name":"Kanasale",
    "wof:placetype":"locality",
    "wof:population":8
},
  "geometry": {"coordinates":[74.97669500000001,14.110547],"type":"Point"}
}