{
  "type": "Feature",
  "properties": {
    "iso:country":"IN",
    "ks:ks_name":"Kaniasupa",
    "ks:ks_pop":545,
    "ks:ks_type":"HABITATION",
    "ks:ks_uagg_main":0,
    "name:eng_x_preferred":[
        "Kaniasupa"
    ],
    "wof:name":"Kaniasupa",
    "wof:placetype":"neighbourhood",
    "wof:population":545
},
  "geometry": {"coordinates":[91.741614,26.3407],"type":"Point"}
}