{
  "type": "Feature",
  "properties": {
    "iso:country":"IN",
    "ks:ks_name":"Thana Gudi Para",
    "ks:ks_pop":62,
    "ks:ks_type":"HABITATION",
    "name:eng_x_preferred":[
        "Thana Gudi Para"
    ],
    "wof:name":"Thana Gudi Para",
    "wof:placetype":"locality",
    "wof:population":62
},
  "geometry": {"coordinates":[81.85001200000001,19.187235],"type":"Point"}
}