{
  "type": "Feature",
  "properties": {
    "gn:admin1_code":"37",
    "gn:admin2_code":"408.0",
    "gn:asciiname":"Salhe",
    "gn:country_code":"IN",
    "gn:dem":379,
    "gn:feature_class":"P",
    "gn:feature_code":"PPL",
    "gn:name":"S\u0101lhe",
    "gn:population":0,
    "gn:timezone":"Asia/Kolkata",
    "iso:country":"IN",
    "ks:ks_alt_nam":"S\u0101lhe",
    "ks:ks_name":"Salhe",
    "ks:ks_pop":80,
    "ks:ks_type":"VILLAGE",
    "name:eng_x_preferred":[
        "Salhe"
    ],
    "name:eng_x_variant":[
        "S\u0101lhe"
    ],
    "wof:name":"Salhe",
    "wof:placetype":"locality",
    "wof:population":80
},
  "geometry": {"coordinates":[80.549571,20.629192],"type":"Point"}
}