{
  "type": "Feature",
  "properties": {
    "gn:admin1_code":"35.0",
    "gn:admin2_code":"442.0",
    "gn:asciiname":"Shivpura",
    "gn:country_code":"IN",
    "gn:dem":424,
    "gn:feature_class":"P",
    "gn:feature_code":"PPL",
    "gn:name":"Shivpura",
    "gn:population":0,
    "gn:timezone":"Asia/Kolkata",
    "iso:country":"IN",
    "wof:name":"Shivpura",
    "wof:placetype":"locality"
},
  "geometry": {"coordinates":[76.84713000000001,23.95082],"type":"Point"}
}