{
  "type": "Feature",
  "properties": {
    "iso:country":"IN",
    "ks:ks_name":"Nandeni",
    "ks:ks_pop":50,
    "ks:ks_type":"VILLAGE",
    "name:eng_x_preferred":[
        "Nandeni"
    ],
    "wof:name":"Nandeni",
    "wof:placetype":"locality",
    "wof:population":50
},
  "geometry": {"coordinates":[83.924285,20.447106],"type":"Point"}
}