{
  "type": "Feature",
  "properties": {
    "iso:country":"IN",
    "ks:ks_name":"Pholiamari Pathar",
    "ks:ks_pop":1737,
    "ks:ks_type":"VILLAGE",
    "ks:ks_uagg_main":0,
    "name:eng_x_preferred":[
        "Pholiamari Pathar"
    ],
    "wof:name":"Pholiamari Pathar",
    "wof:placetype":"neighbourhood",
    "wof:population":1737
},
  "geometry": {"coordinates":[92.268181,26.395997],"type":"Point"}
}