{
  "type": "Feature",
  "properties": {
    "iso:country":"IN",
    "ks:ks_name":"Huluk Reserved Forest",
    "ks:ks_type":"VILLAGE",
    "name:eng_x_preferred":[
        "Huluk Reserved Forest"
    ],
    "wof:name":"Huluk Reserved Forest",
    "wof:placetype":"locality"
},
  "geometry": {"coordinates":[84.259681,23.621213],"type":"Point"}
}