{
  "type": "Feature",
  "properties": {
    "gn:admin1_code":"12.0",
    "gn:admin2_code":"16.0",
    "gn:asciiname":"Kothi",
    "gn:country_code":"IN",
    "gn:dem":2290,
    "gn:feature_class":"P",
    "gn:feature_code":"PPL",
    "gn:name":"Kothi",
    "gn:population":0,
    "gn:timezone":"Asia/Kolkata",
    "iso:country":"IN",
    "name:ceb_x_preferred":[
        "Kothi"
    ],
    "name:swe_x_preferred":[
        "Kothi"
    ],
    "wof:name":"Kothi",
    "wof:placetype":"locality"
},
  "geometry": {"coordinates":[75.5453,33.19260999999999],"type":"Point"}
}