{
  "type": "Feature",
  "properties": {
    "iso:country":"IN",
    "ks:ks_name":"Eettpara",
    "ks:ks_pop":438,
    "ks:ks_type":"HABITATION",
    "name:eng_x_preferred":[
        "Eettpara"
    ],
    "wof:name":"Eettpara",
    "wof:placetype":"locality",
    "wof:population":438
},
  "geometry": {"coordinates":[76.048288,11.342603],"type":"Point"}
}