{
  "type": "Feature",
  "properties": {
    "iso:country":"IN",
    "ks:ks_alt_nam":"Gang\u0101pur",
    "ks:ks_name":"Gangapur",
    "ks:ks_type":"VILLAGE",
    "name:eng_x_preferred":[
        "Gangapur"
    ],
    "name:eng_x_variant":[
        "Gang\u0101pur"
    ],
    "wof:name":"Gangapur",
    "wof:placetype":"locality"
},
  "geometry": {"coordinates":[79.880291,28.834358],"type":"Point"}
}