{
  "type": "Feature",
  "properties": {
    "iso:country":"IN",
    "ks:ks_name":"Anuppur",
    "ks:ks_pop":572,
    "ks:ks_type":"VILLAGE",
    "ks:ks_uagg_main":0,
    "name:eng_x_preferred":[
        "Anuppur"
    ],
    "name:hin_x_preferred":[
        "\u0905\u0928\u0942\u092a\u092a\u0941\u0930"
    ],
    "wof:name":"Anuppur",
    "wof:placetype":"neighbourhood",
    "wof:population":572
},
  "geometry": {"coordinates":[87.906521,24.725351],"type":"Point"}
}