{
  "type": "Feature",
  "properties": {
    "iso:country":"IN",
    "ks:ks_name":"Khaspara 8",
    "ks:ks_pop":266,
    "ks:ks_type":"HABITATION",
    "name:eng_x_preferred":[
        "Khaspara 8"
    ],
    "wof:name":"Khaspara 8",
    "wof:placetype":"locality",
    "wof:population":266
},
  "geometry": {"coordinates":[81.866119,19.854709],"type":"Point"}
}