{
  "type": "Feature",
  "properties": {
    "iso:country":"IN",
    "ks:ks_name":"7 PSD-A",
    "ks:ks_pop":146,
    "ks:ks_type":"VILLAGE",
    "name:eng_x_preferred":[
        "7 PSD-A"
    ],
    "wof:name":"7 PSD-A",
    "wof:placetype":"locality",
    "wof:population":146
},
  "geometry": {"coordinates":[72.932502,28.853873],"type":"Point"}
}