{
  "type": "Feature",
  "properties": {
    "gn:admin1_code":"2.0",
    "gn:admin2_code":"544.0",
    "gn:asciiname":"Kondemulu",
    "gn:country_code":"IN",
    "gn:dem":929,
    "gn:feature_class":"P",
    "gn:feature_code":"PPL",
    "gn:name":"Kondem\u016blu",
    "gn:population":0,
    "gn:timezone":"Asia/Kolkata",
    "iso:country":"IN",
    "ks:ks_name":"Kondemulu",
    "ks:ks_pop":75,
    "ks:ks_type":"HABITATION",
    "name:eng_x_preferred":[
        "Kondemulu"
    ],
    "wof:name":"Kondemulu",
    "wof:placetype":"locality",
    "wof:population":75
},
  "geometry": {"coordinates":[82.469962,18.13073],"type":"Point"}
}