{
  "type": "Feature",
  "properties": {
    "iso:country":"IN",
    "ks:ks_name":"Lao Gaon",
    "ks:ks_pop":5334,
    "ks:ks_type":"VILLAGE",
    "name:eng_x_preferred":[
        "Lao Gaon"
    ],
    "wof:name":"Lao Gaon",
    "wof:placetype":"locality",
    "wof:population":5334
},
  "geometry": {"coordinates":[92.699197,26.38779],"type":"Point"}
}