{
  "type": "Feature",
  "properties": {
    "gn:admin1_code":"37",
    "gn:admin2_code":"409.0",
    "gn:asciiname":"Dhumadah",
    "gn:country_code":"IN",
    "gn:dem":328,
    "gn:feature_class":"P",
    "gn:feature_code":"PPL",
    "gn:name":"Dh\u016bm\u0101dah",
    "gn:population":0,
    "gn:timezone":"Asia/Kolkata",
    "iso:country":"IN",
    "ks:ks_alt_nam":"Dh\u016bm\u0101dah",
    "ks:ks_name":"Dhumadah",
    "ks:ks_type":"VILLAGE",
    "name:eng_x_preferred":[
        "Dhumadah"
    ],
    "name:eng_x_variant":[
        "Dh\u016bm\u0101dah"
    ],
    "wof:name":"Dhumadah",
    "wof:placetype":"locality"
},
  "geometry": {"coordinates":[80.994327,20.838622],"type":"Point"}
}