{
  "type": "Feature",
  "properties": {
    "gn:admin1_code":"12.0",
    "gn:admin2_code":"2.0",
    "gn:asciiname":"Chak-i-Sirijmut",
    "gn:country_code":"IN",
    "gn:dem":1586,
    "gn:feature_class":"P",
    "gn:feature_code":"PPL",
    "gn:name":"Chak-i-Sirijmut",
    "gn:population":0,
    "gn:timezone":"Asia/Kolkata",
    "iso:country":"IN",
    "wof:name":"Chak-i-Sirijmut",
    "wof:placetype":"locality"
},
  "geometry": {"coordinates":[74.88944000000002,33.99233],"type":"Point"}
}