{
  "type": "Feature",
  "properties": {
    "iso:country":"IN",
    "ks:ks_name":"Kolila Rawad",
    "ks:ks_pop":758,
    "ks:ks_type":"VILLAGE",
    "ks:ks_uagg_main":0,
    "name:eng_x_preferred":[
        "Kolila Rawad"
    ],
    "wof:name":"Kolila Rawad",
    "wof:placetype":"neighbourhood",
    "wof:population":758
},
  "geometry": {"coordinates":[76.373811,27.933561],"type":"Point"}
}