{
  "type": "Feature",
  "properties": {
    "iso:country":"IN",
    "ks:ks_name":"Tikrapada I",
    "ks:ks_pop":37,
    "ks:ks_type":"HABITATION",
    "name:eng_x_preferred":[
        "Tikrapada I"
    ],
    "wof:name":"Tikrapada I",
    "wof:placetype":"locality",
    "wof:population":37
},
  "geometry": {"coordinates":[82.748516,19.743236],"type":"Point"}
}