{
  "type": "Feature",
  "properties": {
    "gn:admin1_code":"19.0",
    "gn:admin2_code":"582.0",
    "gn:asciiname":"Bommasandra",
    "gn:country_code":"IN",
    "gn:dem":731,
    "gn:feature_class":"P",
    "gn:feature_code":"PPL",
    "gn:name":"Bommasandra",
    "gn:population":0,
    "gn:timezone":"Asia/Kolkata",
    "iso:country":"IN",
    "name:ben_x_preferred":[
        "\u09ac\u09cb\u09ae\u09cd\u09ae\u09b8\u09be\u09a8\u09cd\u09a6\u09cd\u09b0\u09be"
    ],
    "name:bpy_x_preferred":[
        "\u09ac\u09cb\u09ae\u09cd\u09ae\u09b8\u09be\u09a8\u09cd\u09a6\u09cd\u09b0\u09be"
    ],
    "name:ita_x_preferred":[
        "Bommasandra"
    ],
    "name:mlg_x_preferred":[
        "Bommasandra"
    ],
    "name:msa_x_preferred":[
        "Bommasandra"
    ],
    "name:new_x_preferred":[
        "\u092c\u094b\u0932\u094d\u0932\u093e\u0938\u0928\u094d\u0926\u094d\u0930\u093e"
    ],
    "name:nld_x_preferred":[
        "Bommasandra"
    ],
    "name:por_x_preferred":[
        "Bommasandra"
    ],
    "name:tam_x_preferred":[
        "\u0baa\u0bca\u0bae\u0bcd\u0bae\u0b9a\u0ba8\u0bcd\u0ba4\u0bbf\u0bb0\u0bae\u0bcd"
    ],
    "name:vie_x_preferred":[
        "Bommasandra"
    ],
    "name:zho_x_preferred":[
        "\u535a\u9a6c\u6851\u5fb7\u62c9"
    ],
    "wof:name":"Bommasandra",
    "wof:placetype":"locality"
},
  "geometry": {"coordinates":[77.60696,13.61281],"type":"Point"}
}