{
  "type": "Feature",
  "properties": {
    "iso:country":"IN",
    "ks:ks_name":"Gottemukkulawarichelka",
    "ks:ks_pop":453,
    "ks:ks_type":"HABITATION",
    "name:eng_x_preferred":[
        "Gottemukkulawarichelka"
    ],
    "wof:name":"Gottemukkulawarichelka",
    "wof:placetype":"locality",
    "wof:population":453
},
  "geometry": {"coordinates":[79.691383,17.213519],"type":"Point"}
}