{
  "type": "Feature",
  "properties": {
    "iso:country":"IN",
    "ks:ks_name":"Vardenahalli",
    "ks:ks_pop":32,
    "ks:ks_type":"VILLAGE",
    "ks:ks_uagg_main":0,
    "name:eng_x_preferred":[
        "Vardenahalli"
    ],
    "wof:name":"Vardenahalli",
    "wof:placetype":"neighbourhood",
    "wof:population":32
},
  "geometry": {"coordinates":[77.98938,13.016692],"type":"Point"}
}