{
  "type": "Feature",
  "properties": {
    "gn:admin1_code":"12.0",
    "gn:admin2_code":"010",
    "gn:asciiname":"Nambalan",
    "gn:country_code":"IN",
    "gn:dem":1893,
    "gn:feature_class":"P",
    "gn:feature_code":"PPL",
    "gn:name":"Nambalan",
    "gn:population":0,
    "gn:timezone":"Asia/Kolkata",
    "iso:country":"IN",
    "wof:name":"Nambalan",
    "wof:placetype":"locality"
},
  "geometry": {"coordinates":[74.96666999999999,34.11528],"type":"Point"}
}