{
  "type": "Feature",
  "properties": {
    "iso:country":"IN",
    "ks:ks_name":"Vallicode",
    "ks:ks_pop":20750,
    "ks:ks_type":"VILLAGE",
    "name:eng_x_preferred":[
        "Vallicode"
    ],
    "wof:name":"Vallicode",
    "wof:placetype":"locality",
    "wof:population":20750
},
  "geometry": {"coordinates":[76.771547,9.22693],"type":"Point"}
}