{
  "type": "Feature",
  "properties": {
    "iso:country":"IN",
    "ks:ks_name":"Ratal",
    "ks:ks_pop":40,
    "ks:ks_type":"HABITATION",
    "name:eng_x_preferred":[
        "Ratal"
    ],
    "wof:name":"Ratal",
    "wof:placetype":"locality",
    "wof:population":40
},
  "geometry": {"coordinates":[73.139422,18.712905],"type":"Point"}
}