{
  "type": "Feature",
  "properties": {
    "iso:country":"IN",
    "ks:ks_name":"Hardur",
    "ks:ks_pop":246,
    "ks:ks_type":"HABITATION",
    "name:eng_x_preferred":[
        "Hardur"
    ],
    "wof:name":"Hardur",
    "wof:placetype":"locality",
    "wof:population":246
},
  "geometry": {"coordinates":[75.825615,12.49243],"type":"Point"}
}