{
  "type": "Feature",
  "properties": {
    "gn:admin1_code":"13.0",
    "gn:admin2_code":"590.0",
    "gn:asciiname":"Mukkie",
    "gn:country_code":"IN",
    "gn:dem":748,
    "gn:feature_class":"P",
    "gn:feature_code":"PPL",
    "gn:name":"Mukkie",
    "gn:population":0,
    "gn:timezone":"Asia/Kolkata",
    "iso:country":"IN",
    "wof:name":"Mukkie",
    "wof:placetype":"locality"
},
  "geometry": {"coordinates":[75.83984,11.79334],"type":"Point"}
}