{
  "type": "Feature",
  "properties": {
    "iso:country":"IN",
    "ks:ks_name":"Ilahibagh",
    "ks:ks_pop":1212,
    "ks:ks_type":"VILLAGE",
    "ks:ks_uagg_main":0,
    "name:eng_x_preferred":[
        "Ilahibagh"
    ],
    "wof:name":"Ilahibagh",
    "wof:placetype":"locality",
    "wof:population":1212
},
  "geometry": {"coordinates":[85.19113,25.565065],"type":"Point"}
}