{
  "type": "Feature",
  "properties": {
    "iso:country":"IN",
    "ks:ks_name":"Goj Rathor",
    "ks:ks_pop":449,
    "ks:ks_type":"VILLAGE",
    "name:eng_x_preferred":[
        "Goj Rathor"
    ],
    "wof:name":"Goj Rathor",
    "wof:placetype":"locality",
    "wof:population":449
},
  "geometry": {"coordinates":[74.53027299999999,23.761538],"type":"Point"}
}