{
  "type": "Feature",
  "properties": {
    "gn:admin1_code":"10",
    "gn:admin2_code":"70.0",
    "gn:asciiname":"Ghasitpur",
    "gn:country_code":"IN",
    "gn:dem":274,
    "gn:feature_class":"P",
    "gn:feature_code":"PPL",
    "gn:name":"Ghas\u012btpur",
    "gn:population":0,
    "gn:timezone":"Asia/Kolkata",
    "iso:country":"IN",
    "ks:ks_name":"Ghasitpur",
    "ks:ks_pop":1323,
    "ks:ks_type":"VILLAGE",
    "ks:ks_uagg_main":0,
    "name:eng_x_preferred":[
        "Ghasitpur"
    ],
    "wof:name":"Ghasitpur",
    "wof:placetype":"locality",
    "wof:population":1323
},
  "geometry": {"coordinates":[76.858582,30.310509],"type":"Point"}
}