{
  "type": "Feature",
  "properties": {
    "iso:country":"IN",
    "ks:ks_name":"Pareya Chak",
    "ks:ks_pop":262,
    "ks:ks_type":"HABITATION",
    "name:eng_x_preferred":[
        "Pareya Chak"
    ],
    "wof:name":"Pareya Chak",
    "wof:placetype":"locality",
    "wof:population":262
},
  "geometry": {"coordinates":[84.75796699999999,25.321947],"type":"Point"}
}