{
  "type": "Feature",
  "properties": {
    "iso:country":"IN",
    "ks:ks_name":"21 JSN",
    "ks:ks_pop":170,
    "ks:ks_type":"VILLAGE",
    "name:eng_x_preferred":[
        "21 JSN"
    ],
    "wof:name":"21 JSN",
    "wof:placetype":"locality",
    "wof:population":170
},
  "geometry": {"coordinates":[74.81983099999999,29.277353],"type":"Point"}
}