{
  "type": "Feature",
  "properties": {
    "iso:country":"IN",
    "ks:ks_name":"Gumon Jyun",
    "ks:ks_pop":14,
    "ks:ks_type":"HABITATION",
    "name:eng_x_preferred":[
        "Gumon Jyun"
    ],
    "wof:name":"Gumon Jyun",
    "wof:placetype":"locality",
    "wof:population":14
},
  "geometry": {"coordinates":[79.055768,29.591464],"type":"Point"}
}