{
  "type": "Feature",
  "properties": {
    "iso:country":"IN",
    "ks:ks_alt_nam":"MAJOR WASTI",
    "ks:ks_name":"Major Wasti",
    "ks:ks_pop":131,
    "ks:ks_type":"HABITATION",
    "name:eng_x_preferred":[
        "Major Wasti"
    ],
    "wof:name":"Major Wasti",
    "wof:placetype":"locality",
    "wof:population":131
},
  "geometry": {"coordinates":[74.540513,18.753149],"type":"Point"}
}