{
  "type": "Feature",
  "properties": {
    "iso:country":"IN",
    "ks:ks_name":"Ghera-rasalgad",
    "ks:ks_pop":980,
    "ks:ks_type":"VILLAGE",
    "name:eng_x_preferred":[
        "Ghera-rasalgad"
    ],
    "wof:name":"Ghera-rasalgad",
    "wof:placetype":"locality",
    "wof:population":980
},
  "geometry": {"coordinates":[73.50075200000001,17.760375],"type":"Point"}
}