{
  "type": "Feature",
  "properties": {
    "gn:admin1_code":"17",
    "gn:admin2_code":"280.0",
    "gn:asciiname":"Shelkui Khunou",
    "gn:country_code":"IN",
    "gn:dem":1412,
    "gn:feature_class":"P",
    "gn:feature_code":"PPL",
    "gn:name":"Shelkui Khunou",
    "gn:population":0,
    "gn:timezone":"Asia/Kolkata",
    "iso:country":"IN",
    "wof:name":"Shelkui Khunou",
    "wof:placetype":"locality"
},
  "geometry": {"coordinates":[93.86794999999999,24.06435],"type":"Point"}
}