{
  "type": "Feature",
  "properties": {
    "gn:admin1_code":"21.0",
    "gn:admin2_code":"396.0",
    "gn:asciiname":"Mundibindha",
    "gn:country_code":"IN",
    "gn:dem":900,
    "gn:feature_class":"P",
    "gn:feature_code":"PPL",
    "gn:name":"Mundibindha",
    "gn:population":0,
    "gn:timezone":"Asia/Kolkata",
    "iso:country":"IN",
    "wof:name":"Mundibindha",
    "wof:placetype":"locality"
},
  "geometry": {"coordinates":[83.03305,19.05966],"type":"Point"}
}