{
  "type": "Feature",
  "properties": {
    "iso:country":"IN",
    "ks:ks_alt_nam":"Gudikunta thanda",
    "ks:ks_name":"Gudikunta Thanda",
    "ks:ks_pop":486,
    "ks:ks_type":"HABITATION",
    "name:eng_x_preferred":[
        "Gudikunta Thanda"
    ],
    "wof:name":"Gudikunta Thanda",
    "wof:placetype":"locality",
    "wof:population":486
},
  "geometry": {"coordinates":[79.445785,17.572571],"type":"Point"}
}