{
  "type": "Feature",
  "properties": {
    "iso:country":"IN",
    "ks:ks_name":"Hasan Chak",
    "ks:ks_pop":2277,
    "ks:ks_type":"VILLAGE",
    "name:eng_x_preferred":[
        "Hasan Chak"
    ],
    "wof:name":"Hasan Chak",
    "wof:placetype":"locality",
    "wof:population":2277
},
  "geometry": {"coordinates":[85.42397800000001,26.165986],"type":"Point"}
}