{
  "type": "Feature",
  "properties": {
    "iso:country":"IN",
    "ks:ks_alt_nam":"SHARMA TOLA 2",
    "ks:ks_name":"Sharma Tola 2",
    "ks:ks_pop":497,
    "ks:ks_type":"HABITATION",
    "name:eng_x_preferred":[
        "Sharma Tola 2"
    ],
    "wof:name":"Sharma Tola 2",
    "wof:placetype":"locality",
    "wof:population":497
},
  "geometry": {"coordinates":[87.029859,26.390889],"type":"Point"}
}