{
  "type": "Feature",
  "properties": {
    "gn:admin1_code":"36",
    "gn:admin2_code":"191.0",
    "gn:asciiname":"Palia Khas",
    "gn:country_code":"IN",
    "gn:dem":84,
    "gn:feature_class":"P",
    "gn:feature_code":"PPL",
    "gn:name":"Palia Kh\u0101s",
    "gn:population":0,
    "gn:timezone":"Asia/Kolkata",
    "iso:country":"IN",
    "ks:ks_alt_nam":"Palia Kh\u0101s",
    "ks:ks_name":"Palia Khas",
    "ks:ks_type":"VILLAGE",
    "ks:ks_uagg_main":0,
    "name:eng_x_preferred":[
        "Palia Khas"
    ],
    "name:eng_x_variant":[
        "Palia Kh\u0101s"
    ],
    "wof:name":"Palia Khas",
    "wof:placetype":"neighbourhood"
},
  "geometry": {"coordinates":[83.03963400000001,26.080619],"type":"Point"}
}