{
  "type": "Feature",
  "properties": {
    "gn:admin1_code":"36",
    "gn:admin2_code":"159.0",
    "gn:asciiname":"Radhu Ahir",
    "gn:country_code":"IN",
    "gn:dem":141,
    "gn:feature_class":"P",
    "gn:feature_code":"PPL",
    "gn:name":"R\u0101dhu Ah\u012br",
    "gn:population":0,
    "gn:timezone":"Asia/Kolkata",
    "iso:country":"IN",
    "wof:name":"Radhu Ahir",
    "wof:placetype":"neighbourhood"
},
  "geometry": {"coordinates":[79.56337000000001,27.43897],"type":"Point"}
}