{
  "type": "Feature",
  "properties": {
    "iso:country":"IN",
    "ks:ks_name":"Harijan Basti",
    "ks:ks_pop":73,
    "ks:ks_type":"HABITATION",
    "name:eng_x_preferred":[
        "Harijan Basti"
    ],
    "wof:name":"Harijan Basti",
    "wof:placetype":"locality",
    "wof:population":73
},
  "geometry": {"coordinates":[82.482207,26.722162],"type":"Point"}
}