{
  "type": "Feature",
  "properties": {
    "iso:country":"IN",
    "ks:ks_name":"Danmav",
    "ks:ks_pop":81,
    "ks:ks_type":"VILLAGE",
    "name:eng_x_preferred":[
        "Danmav"
    ],
    "wof:name":"Danmav",
    "wof:placetype":"locality",
    "wof:population":81
},
  "geometry": {"coordinates":[74.700405,14.329186],"type":"Point"}
}