{
  "type": "Feature",
  "properties": {
    "gn:admin1_code":"2.0",
    "gn:admin2_code":"554.0",
    "gn:asciiname":"Avulapalle",
    "gn:country_code":"IN",
    "gn:dem":1035,
    "gn:feature_class":"P",
    "gn:feature_code":"PPL",
    "gn:name":"\u0100vulapalle",
    "gn:population":0,
    "gn:timezone":"Asia/Kolkata",
    "iso:country":"IN",
    "wof:name":"Avulapalle",
    "wof:placetype":"neighbourhood"
},
  "geometry": {"coordinates":[78.38927,13.47452],"type":"Point"}
}