{
  "type": "Feature",
  "properties": {
    "iso:country":"IN",
    "ks:ks_name":"Kaduvathodu",
    "ks:ks_pop":576,
    "ks:ks_type":"HABITATION",
    "name:eng_x_preferred":[
        "Kaduvathodu"
    ],
    "wof:name":"Kaduvathodu",
    "wof:placetype":"locality",
    "wof:population":576
},
  "geometry": {"coordinates":[76.786665,9.113882],"type":"Point"}
}