{
  "type": "Feature",
  "properties": {
    "iso:country":"IN",
    "ks:ks_name":"Hatabasta",
    "ks:ks_pop":18,
    "ks:ks_type":"VILLAGE",
    "name:eng_x_preferred":[
        "Hatabasta"
    ],
    "wof:name":"Hatabasta",
    "wof:placetype":"locality",
    "wof:population":18
},
  "geometry": {"coordinates":[85.328816,20.191903],"type":"Point"}
}