{
  "type": "Feature",
  "properties": {
    "gn:admin1_code":"36.0",
    "gn:admin2_code":"174.0",
    "gn:asciiname":"Muhabbatpur Juta",
    "gn:country_code":"IN",
    "gn:dem":110,
    "gn:feature_class":"P",
    "gn:feature_code":"PPL",
    "gn:name":"Muhabbatpur J\u016bta",
    "gn:population":0,
    "gn:timezone":"Asia/Kolkata",
    "iso:country":"IN",
    "wof:name":"Muhabbatpur Juta",
    "wof:placetype":"locality"
},
  "geometry": {"coordinates":[81.34369000000002,25.75434],"type":"Point"}
}