{
  "type": "Feature",
  "properties": {
    "iso:country":"IN",
    "ks:ks_alt_nam":"KADNAIKHAS",
    "ks:ks_name":"Kadnaikhas",
    "ks:ks_pop":695,
    "ks:ks_type":"HABITATION",
    "name:eng_x_preferred":[
        "Kadnaikhas"
    ],
    "wof:name":"Kadnaikhas",
    "wof:placetype":"locality",
    "wof:population":695
},
  "geometry": {"coordinates":[83.32973800000001,22.914744],"type":"Point"}
}