{
  "type": "Feature",
  "properties": {
    "iso:country":"IN",
    "ks:ks_name":"Pandit Purwa",
    "ks:ks_pop":106,
    "ks:ks_type":"HABITATION",
    "name:eng_x_preferred":[
        "Pandit Purwa"
    ],
    "wof:name":"Pandit Purwa",
    "wof:placetype":"locality",
    "wof:population":106
},
  "geometry": {"coordinates":[82.644339,26.94248],"type":"Point"}
}