{
  "type": "Feature",
  "properties": {
    "iso:country":"IN",
    "ks:ks_name":"Dhangurabhati",
    "ks:ks_pop":230,
    "ks:ks_type":"HABITATION",
    "name:eng_x_preferred":[
        "Dhangurabhati"
    ],
    "wof:name":"Dhangurabhati",
    "wof:placetype":"locality",
    "wof:population":230
},
  "geometry": {"coordinates":[81.82564000000001,18.414257],"type":"Point"}
}