{
  "type": "Feature",
  "properties": {
    "gn:admin1_code":"34.0",
    "gn:admin2_code":"219.0",
    "gn:asciiname":"Mathia",
    "gn:country_code":"IN",
    "gn:dem":62,
    "gn:feature_class":"P",
    "gn:feature_code":"PPL",
    "gn:name":"Mathia",
    "gn:population":0,
    "gn:timezone":"Asia/Kolkata",
    "iso:country":"IN",
    "wof:name":"Mathia",
    "wof:placetype":"locality"
},
  "geometry": {"coordinates":[84.79785,26.12611],"type":"Point"}
}