{
  "type": "Feature",
  "properties": {
    "iso:country":"IN",
    "ks:ks_name":"Ranaguda",
    "ks:ks_pop":422,
    "ks:ks_type":"VILLAGE",
    "name:eng_x_preferred":[
        "Ranaguda"
    ],
    "wof:name":"Ranaguda",
    "wof:placetype":"locality",
    "wof:population":422
},
  "geometry": {"coordinates":[83.89128599999999,19.541139],"type":"Point"}
}