{
  "type": "Feature",
  "properties": {
    "iso:country":"IN",
    "ks:ks_name":"Ganjhar",
    "ks:ks_pop":68,
    "ks:ks_type":"VILLAGE",
    "name:eng_x_preferred":[
        "Ganjhar"
    ],
    "wof:name":"Ganjhar",
    "wof:placetype":"locality",
    "wof:population":68
},
  "geometry": {"coordinates":[84.022578,22.791229],"type":"Point"}
}