{
  "type": "Feature",
  "properties": {
    "gn:admin1_code":"11",
    "gn:admin2_code":"33.0",
    "gn:asciiname":"Fatenohi",
    "gn:country_code":"IN",
    "gn:dem":1601,
    "gn:feature_class":"P",
    "gn:feature_code":"PPL",
    "gn:name":"Fatenohi",
    "gn:population":0,
    "gn:timezone":"Asia/Kolkata",
    "iso:country":"IN",
    "wof:name":"Fatenohi",
    "wof:placetype":"locality"
},
  "geometry": {"coordinates":[77.09421999999998,31.11682],"type":"Point"}
}