{
  "type": "Feature",
  "properties": {
    "iso:country":"IN",
    "ks:ks_name":"Jaldihi",
    "ks:ks_pop":226,
    "ks:ks_type":"VILLAGE",
    "name:eng_x_preferred":[
        "Jaldihi"
    ],
    "wof:name":"Jaldihi",
    "wof:placetype":"locality",
    "wof:population":226
},
  "geometry": {"coordinates":[85.010824,21.832963],"type":"Point"}
}