{
  "type": "Feature",
  "properties": {
    "gn:admin1_code":"36.0",
    "gn:admin2_code":"152.0",
    "gn:asciiname":"Pokharpur Taluka Sarjupur",
    "gn:country_code":"IN",
    "gn:dem":161,
    "gn:feature_class":"P",
    "gn:feature_code":"PPL",
    "gn:name":"Pokharpur Tal\u016bka Sarjupur",
    "gn:population":0,
    "gn:timezone":"Asia/Kolkata",
    "iso:country":"IN",
    "wof:name":"Pokharpur Taluka Sarjupur",
    "wof:placetype":"neighbourhood"
},
  "geometry": {"coordinates":[79.58540000000001,28.02439],"type":"Point"}
}