{
  "type": "Feature",
  "properties": {
    "iso:country":"IN",
    "ks:ks_alt_nam":"jedigudige",
    "ks:ks_name":"Jedigudige",
    "ks:ks_pop":31,
    "ks:ks_type":"HABITATION",
    "name:eng_x_preferred":[
        "Jedigudige"
    ],
    "wof:name":"Jedigudige",
    "wof:placetype":"locality",
    "wof:population":31
},
  "geometry": {"coordinates":[75.518428,13.267336],"type":"Point"}
}