{
  "type": "Feature",
  "properties": {
    "iso:country":"IN",
    "ks:ks_name":"Katorewasti",
    "ks:ks_pop":531,
    "ks:ks_type":"HABITATION",
    "name:eng_x_preferred":[
        "Katorewasti"
    ],
    "wof:name":"Katorewasti",
    "wof:placetype":"locality",
    "wof:population":531
},
  "geometry": {"coordinates":[74.11153299999999,19.510008],"type":"Point"}
}