{
  "type": "Feature",
  "properties": {
    "gn:admin1_code":"19.0",
    "gn:admin2_code":"576.0",
    "gn:asciiname":"Harihara",
    "gn:country_code":"IN",
    "gn:dem":855,
    "gn:feature_class":"P",
    "gn:feature_code":"PPLL",
    "gn:name":"Harihara",
    "gn:population":0,
    "gn:timezone":"Asia/Kolkata",
    "iso:country":"IN",
    "name:ben_x_preferred":[
        "\u09b9\u09b0\u09bf\u09b9\u09b0"
    ],
    "name:deu_x_preferred":[
        "Harihara"
    ],
    "name:fra_x_preferred":[
        "Harihara"
    ],
    "name:hin_x_preferred":[
        "\u0939\u0930\u093f\u0939\u0930"
    ],
    "name:ind_x_preferred":[
        "Harihara"
    ],
    "name:ita_x_preferred":[
        "Harihara"
    ],
    "name:jpn_x_preferred":[
        "\u30cf\u30ea\u30cf\u30e9"
    ],
    "name:mal_x_preferred":[
        "\u0d36\u0d19\u0d4d\u0d15\u0d30\u0d28\u0d3e\u0d30\u0d3e\u0d2f\u0d23\u0d7b"
    ],
    "name:pol_x_preferred":[
        "Harihara"
    ],
    "name:rus_x_preferred":[
        "\u0425\u0430\u0440\u0438\u0445\u0430\u0440\u0430"
    ],
    "name:spa_x_preferred":[
        "Harihara"
    ],
    "name:tam_x_preferred":[
        "\u0bae\u0bbe\u0bb2\u0bca\u0bb0\u0bc1\u0baa\u0bbe\u0b95\u0ba9\u0bcd"
    ],
    "name:tha_x_preferred":[
        "\u0e1e\u0e23\u0e30\u0e2b\u0e23\u0e34\u0e2b\u0e23\u0e30"
    ],
    "name:urd_x_preferred":[
        "\u06c1\u0631\u06cc \u06c1\u0631"
    ],
    "wof:name":"Harihara",
    "wof:placetype":"locality"
},
  "geometry": {"coordinates":[75.99173,12.0556],"type":"Point"}
}