{
  "type": "Feature",
  "properties": {
    "gn:admin1_code":"36.0",
    "gn:admin2_code":"137.0",
    "gn:asciiname":"Gajana",
    "gn:country_code":"IN",
    "gn:dem":217,
    "gn:feature_class":"P",
    "gn:feature_code":"PPL",
    "gn:name":"Gaj\u0101na",
    "gn:population":0,
    "gn:timezone":"Asia/Kolkata",
    "iso:country":"IN",
    "name:guj_x_preferred":[
        "\u0a97\u0a9c\u0aa3\u0abe"
    ],
    "wof:name":"Gajana",
    "wof:placetype":"locality"
},
  "geometry": {"coordinates":[78.49475,28.97492],"type":"Point"}
}