{
  "type": "Feature",
  "properties": {
    "iso:country":"IN",
    "ks:ks_name":"Oddu Madi",
    "ks:ks_pop":87,
    "ks:ks_type":"HABITATION",
    "name:eng_x_preferred":[
        "Oddu Madi"
    ],
    "wof:name":"Oddu Madi",
    "wof:placetype":"locality",
    "wof:population":87
},
  "geometry": {"coordinates":[78.4252,12.847824],"type":"Point"}
}