{
  "type": "Feature",
  "properties": {
    "gn:admin1_code":"28.0",
    "gn:admin2_code":"341",
    "gn:asciiname":"Gangarampur",
    "gn:country_code":"IN",
    "gn:dem":11,
    "gn:feature_class":"P",
    "gn:feature_code":"PPL",
    "gn:name":"Gangarampur",
    "gn:population":0,
    "gn:timezone":"Asia/Kolkata",
    "iso:country":"IN",
    "name:ben_x_preferred":[
        "\u0997\u0999\u09cd\u0997\u09be\u09b0\u09be\u09ae\u09aa\u09c1\u09b0"
    ],
    "name:bpy_x_preferred":[
        "\u0997\u0999\u09cd\u0997\u09be\u09b0\u09be\u09ae\u09aa\u09c1\u09b0"
    ],
    "name:ceb_x_preferred":[
        "Gang\u0101r\u0101mpur"
    ],
    "name:hif_x_preferred":[
        "Gangarampur"
    ],
    "name:hin_x_preferred":[
        "\u0917\u0902\u0917\u093e\u0930\u093e\u092e\u092a\u0941\u0930"
    ],
    "name:ita_x_preferred":[
        "Gangarampur"
    ],
    "name:msa_x_preferred":[
        "Gangarampur"
    ],
    "name:new_x_preferred":[
        "\u0917\u0902\u0917\u093e\u0930\u093e\u092e\u092a\u0941\u0930"
    ],
    "name:ori_x_preferred":[
        "\u0b17\u0b19\u0b4d\u0b17\u0b3e\u0b30\u0b3e\u0b2e\u0b2a\u0b41\u0b30"
    ],
    "name:por_x_preferred":[
        "Gangarampur"
    ],
    "name:spa_x_preferred":[
        "Gangarampur"
    ],
    "name:swe_x_preferred":[
        "Gang\u0101r\u0101mpur"
    ],
    "name:vie_x_preferred":[
        "Gangarampur"
    ],
    "name:zho_x_preferred":[
        "\u5188\u683c\u963f\u62c9\u59c6\u666e\u5c14"
    ],
    "wof:name":"Gangarampur",
    "wof:placetype":"locality"
},
  "geometry": {"coordinates":[88.07832999999999,22.46528],"type":"Point"}
}