{
  "type": "Feature",
  "properties": {
    "iso:country":"IN",
    "ks:ks_name":"1 MLK-A",
    "ks:ks_pop":181,
    "ks:ks_type":"VILLAGE",
    "name:eng_x_preferred":[
        "1 MLK-A"
    ],
    "wof:name":"1 MLK-A",
    "wof:placetype":"locality",
    "wof:population":181
},
  "geometry": {"coordinates":[73.04618499999999,28.927826],"type":"Point"}
}