{
  "type": "Feature",
  "properties": {
    "gn:admin1_code":"36",
    "gn:admin2_code":"194.0",
    "gn:asciiname":"Garothan",
    "gn:country_code":"IN",
    "gn:dem":92,
    "gn:feature_class":"P",
    "gn:feature_code":"PPL",
    "gn:name":"Garothan",
    "gn:population":0,
    "gn:timezone":"Asia/Kolkata",
    "iso:country":"IN",
    "ks:ks_name":"Garothan",
    "ks:ks_pop":990,
    "ks:ks_type":"VILLAGE",
    "ks:ks_uagg_main":0,
    "name:eng_x_preferred":[
        "Garothan"
    ],
    "wof:name":"Garothan",
    "wof:placetype":"neighbourhood",
    "wof:population":990
},
  "geometry": {"coordinates":[82.619826,25.925905],"type":"Point"}
}