{
  "type": "Feature",
  "properties": {
    "iso:country":"IN",
    "ks:ks_name":"Kalvaraj",
    "ks:ks_pop":462,
    "ks:ks_type":"HABITATION",
    "name:eng_x_preferred":[
        "Kalvaraj"
    ],
    "wof:name":"Kalvaraj",
    "wof:placetype":"locality",
    "wof:population":462
},
  "geometry": {"coordinates":[77.625874,11.745759],"type":"Point"}
}