{
  "type": "Feature",
  "properties": {
    "iso:country":"IN",
    "ks:ks_name":"Ramaswamidoruvu",
    "ks:ks_pop":221,
    "ks:ks_type":"HABITATION",
    "name:eng_x_preferred":[
        "Ramaswamidoruvu"
    ],
    "wof:name":"Ramaswamidoruvu",
    "wof:placetype":"locality",
    "wof:population":221
},
  "geometry": {"coordinates":[80.083974,14.218445],"type":"Point"}
}