{
  "type": "Feature",
  "properties": {
    "iso:country":"IN",
    "ks:ks_name":"Tamodi",
    "ks:ks_pop":14,
    "ks:ks_type":"VILLAGE",
    "name:eng_x_preferred":[
        "Tamodi"
    ],
    "wof:name":"Tamodi",
    "wof:placetype":"locality",
    "wof:population":14
},
  "geometry": {"coordinates":[81.13827000000001,18.84313],"type":"Point"}
}