{
  "type": "Feature",
  "properties": {
    "gn:admin1_code":"19.0",
    "gn:admin2_code":"583.0",
    "gn:asciiname":"Kamdevanhalli",
    "gn:country_code":"IN",
    "gn:dem":899,
    "gn:feature_class":"P",
    "gn:feature_code":"PPL",
    "gn:name":"Kamdevanhalli",
    "gn:population":0,
    "gn:timezone":"Asia/Kolkata",
    "iso:country":"IN",
    "wof:name":"Kamdevanhalli",
    "wof:placetype":"neighbourhood"
},
  "geometry": {"coordinates":[77.65394000000001,13.22365],"type":"Point"}
}