{
  "type": "Feature",
  "properties": {
    "gn:admin1_code":"2.0",
    "gn:admin2_code":"552.0",
    "gn:asciiname":"Chintalapalle",
    "gn:country_code":"IN",
    "gn:dem":447,
    "gn:feature_class":"P",
    "gn:feature_code":"PPL",
    "gn:name":"Chintalapalle",
    "gn:population":0,
    "gn:timezone":"Asia/Kolkata",
    "iso:country":"IN",
    "name:hin_x_preferred":[
        "\u091a\u093f\u0902\u0924\u0932\u092a\u0932\u094d\u0932\u0946"
    ],
    "name:mal_x_preferred":[
        "\u0d1a\u0d3f\u0d28\u0d4d\u0d24\u0d32\u0d2a\u0d4d\u0d2a\u0d33\u0d4d\u0d33\u0d3f"
    ],
    "name:new_x_preferred":[
        "\u091a\u093f\u0902\u0924\u0932\u092a\u0932\u094d\u0932\u0946"
    ],
    "name:tel_x_preferred":[
        "\u0c1a\u0c3f\u0c02\u0c24\u0c32\u0c2a\u0c32\u0c4d\u0c32\u0c46"
    ],
    "name:urd_x_preferred":[
        "\u0686\u0646\u062a\u0644\u0627\u067e\u0644\u06cc"
    ],
    "wof:name":"Chintalapalle",
    "wof:placetype":"locality"
},
  "geometry": {"coordinates":[77.86289000000002,15.34274],"type":"Point"}
}