{
  "type": "Feature",
  "properties": {
    "gn:admin1_code":"2.0",
    "gn:admin2_code":"549.0",
    "gn:asciiname":"Chinnanallakalava",
    "gn:country_code":"IN",
    "gn:dem":207,
    "gn:feature_class":"P",
    "gn:feature_code":"PPL",
    "gn:name":"Chinnanallak\u0101lava",
    "gn:population":0,
    "gn:timezone":"Asia/Kolkata",
    "iso:country":"IN",
    "wof:name":"Chinnanallakalava",
    "wof:placetype":"neighbourhood"
},
  "geometry": {"coordinates":[79.02554000000001,15.5518],"type":"Point"}
}