{
  "type": "Feature",
  "properties": {
    "gn:country":"IN",
    "gn:fcode":"PPL",
    "gn:pop":33273,
    "iso:country":"IN",
    "name:ast_x_preferred":[
        "Shahpura"
    ],
    "name:cat_x_preferred":[
        "Shahpura"
    ],
    "name:deu_x_preferred":[
        "Shahpura"
    ],
    "name:eng_x_preferred":[
        "Shahpura"
    ],
    "name:fra_x_preferred":[
        "Shahpura"
    ],
    "name:ita_x_preferred":[
        "Shahpura"
    ],
    "name:msa_x_preferred":[
        "Shahpura"
    ],
    "name:nld_x_preferred":[
        "Shahpura"
    ],
    "name:ori_x_preferred":[
        "\u0b36\u0b3e\u0b39\u0b3e\u0b2a\u0b41\u0b30\u0b3e"
    ],
    "name:unk_x_variant":[
        "Sh\u0101hpura"
    ],
    "name:vie_x_preferred":[
        "Shahpura"
    ],
    "qs:name":"Shahpura",
    "qs:name_adm0":"India",
    "qs:name_adm1":"Rajasthan",
    "qs:photos_9r":0,
    "qs:photos_sr":0,
    "qs:placetype":"Town",
    "qs:pop_sr":"7",
    "wd:wordcount":53,
    "wof:name":"Shahpura",
    "wof:placetype":"locality",
    "wof:population":33273
},
  "geometry": {"coordinates":[75.95956,27.3912],"type":"Point"}
}