{
  "type": "Feature",
  "properties": {
    "iso:country":"IN",
    "ks:ks_name":"Bheh Guri",
    "ks:ks_pop":2733,
    "ks:ks_type":"VILLAGE",
    "name:eng_x_preferred":[
        "Bheh Guri"
    ],
    "wof:name":"Bheh Guri",
    "wof:placetype":"locality",
    "wof:population":2733
},
  "geometry": {"coordinates":[92.485872,26.354752],"type":"Point"}
}