{
  "type": "Feature",
  "properties": {
    "iso:country":"IN",
    "ks:ks_name":"Agbondha Bangali",
    "ks:ks_pop":1059,
    "ks:ks_type":"HABITATION",
    "name:eng_x_preferred":[
        "Agbondha Bangali"
    ],
    "wof:name":"Agbondha Bangali",
    "wof:placetype":"locality",
    "wof:population":1059
},
  "geometry": {"coordinates":[95.63539299999999,27.328184],"type":"Point"}
}