{
  "type": "Feature",
  "properties": {
    "gn:admin1_code":"21",
    "gn:admin2_code":"395.0",
    "gn:asciiname":"Pirol",
    "gn:country_code":"IN",
    "gn:dem":331,
    "gn:feature_class":"P",
    "gn:feature_code":"PPL",
    "gn:name":"Pirol",
    "gn:population":0,
    "gn:timezone":"Asia/Kolkata",
    "iso:country":"IN",
    "ks:ks_name":"Pirul",
    "ks:ks_pop":84,
    "ks:ks_type":"VILLAGE",
    "name:eng_x_preferred":[
        "Pirul"
    ],
    "name:eng_x_variant":[
        "Pirol"
    ],
    "wof:name":"Pirul",
    "wof:placetype":"locality",
    "wof:population":84
},
  "geometry": {"coordinates":[83.250747,19.925624],"type":"Point"}
}