{
  "type": "Feature",
  "properties": {
    "gn:admin1_code":"19.0",
    "gn:admin2_code":"570.0",
    "gn:asciiname":"Balekoppa",
    "gn:country_code":"IN",
    "gn:dem":651,
    "gn:feature_class":"P",
    "gn:feature_code":"PPL",
    "gn:name":"B\u0101lekoppa",
    "gn:population":0,
    "gn:timezone":"Asia/Kolkata",
    "iso:country":"IN",
    "ks:ks_name":"Balekoppa",
    "ks:ks_pop":47,
    "ks:ks_type":"HABITATION",
    "name:eng_x_preferred":[
        "Balekoppa"
    ],
    "wof:name":"Balekoppa",
    "wof:placetype":"locality",
    "wof:population":47
},
  "geometry": {"coordinates":[75.413653,13.622574],"type":"Point"}
}