{
  "type": "Feature",
  "properties": {
    "iso:country":"IN",
    "ks:ks_name":"Lailor",
    "ks:ks_pop":1113,
    "ks:ks_type":"VILLAGE",
    "name:eng_x_preferred":[
        "Lailor"
    ],
    "wof:name":"Lailor",
    "wof:placetype":"locality",
    "wof:population":1113
},
  "geometry": {"coordinates":[85.158328,22.315975],"type":"Point"}
}