{
  "type": "Feature",
  "properties": {
    "gn:admin1_code":"21.0",
    "gn:admin2_code":"396.0",
    "gn:asciiname":"Singari",
    "gn:country_code":"IN",
    "gn:dem":435,
    "gn:feature_class":"P",
    "gn:feature_code":"PPL",
    "gn:name":"Singari",
    "gn:population":0,
    "gn:timezone":"Asia/Kolkata",
    "iso:country":"IN",
    "name:tam_x_preferred":[
        "\u0b9a\u0bbf\u0b99\u0bcd\u0b95\u0bbe\u0bb0\u0bbf"
    ],
    "wof:name":"Singari",
    "wof:placetype":"locality"
},
  "geometry": {"coordinates":[83.60852,19.21861],"type":"Point"}
}