{
  "type": "Feature",
  "properties": {
    "iso:country":"IN",
    "ks:ks_name":"Takuli",
    "ks:ks_pop":573,
    "ks:ks_type":"VILLAGE",
    "ks:ks_uagg_main":0,
    "name:eng_x_preferred":[
        "Takuli"
    ],
    "wof:name":"Takuli",
    "wof:placetype":"neighbourhood",
    "wof:population":573
},
  "geometry": {"coordinates":[80.528865,25.348765],"type":"Point"}
}