{
  "type": "Feature",
  "properties": {
    "iso:country":"IN",
    "ks:ks_name":"Dompathi",
    "ks:ks_pop":0,
    "ks:ks_type":"VILLAGE",
    "name:eng_x_preferred":[
        "Dompathi"
    ],
    "wof:name":"Dompathi",
    "wof:placetype":"locality",
    "wof:population":0
},
  "geometry": {"coordinates":[86.33035,26.09971],"type":"Point"}
}