{
  "type": "Feature",
  "properties": {
    "iso:country":"IN",
    "ks:ks_name":"Salmara",
    "ks:ks_pop":125,
    "ks:ks_type":"HABITATION",
    "name:eng_x_preferred":[
        "Salmara"
    ],
    "wof:name":"Salmara",
    "wof:placetype":"locality",
    "wof:population":125
},
  "geometry": {"coordinates":[91.30169600000001,26.064839],"type":"Point"}
}