{
  "type": "Feature",
  "properties": {
    "iso:country":"IN",
    "ks:ks_name":"Tenginsara",
    "ks:ks_pop":42,
    "ks:ks_type":"HABITATION",
    "name:eng_x_preferred":[
        "Tenginsara"
    ],
    "wof:name":"Tenginsara",
    "wof:placetype":"locality",
    "wof:population":42
},
  "geometry": {"coordinates":[74.704272,14.420963],"type":"Point"}
}