{
  "type": "Feature",
  "properties": {
    "iso:country":"IN",
    "ks:ks_name":"Chithoorwadi",
    "ks:ks_pop":506,
    "ks:ks_type":"HABITATION",
    "name:eng_x_preferred":[
        "Chithoorwadi"
    ],
    "wof:name":"Chithoorwadi",
    "wof:placetype":"locality",
    "wof:population":506
},
  "geometry": {"coordinates":[78.931194,9.638131],"type":"Point"}
}