{
  "type": "Feature",
  "properties": {
    "gn:country":"IN",
    "gn:fcode":"PPL",
    "gn:pop":7369,
    "iso:country":"IN",
    "name:ben_x_preferred":[
        "\u0989\u0995\u0993\u09af\u09bc\u09be"
    ],
    "name:bpy_x_preferred":[
        "\u0989\u0995\u09f1\u09be"
    ],
    "name:eng_x_preferred":[
        "Ukwa"
    ],
    "name:fra_x_preferred":[
        "Ukwa"
    ],
    "name:ita_x_preferred":[
        "Ukwa"
    ],
    "name:mlg_x_preferred":[
        "Ukwa"
    ],
    "name:msa_x_preferred":[
        "Ukwa"
    ],
    "name:nan_x_preferred":[
        "Ukwa"
    ],
    "name:nld_x_preferred":[
        "Ukwa"
    ],
    "name:por_x_preferred":[
        "Ukwa"
    ],
    "name:swe_x_preferred":[
        "Ukwa"
    ],
    "name:unk_x_variant":[
        "Ukw\u0101"
    ],
    "name:vie_x_preferred":[
        "Ukwa"
    ],
    "name:zho_x_preferred":[
        "\u4e4c\u514b\u74e6"
    ],
    "qs:name":"Ukwa",
    "qs:name_adm0":"India",
    "qs:name_adm1":"Madhya Pradesh",
    "qs:photos_9r":0,
    "qs:photos_sr":0,
    "qs:placetype":"Town",
    "qs:pop_sr":"5",
    "wd:wordcount":268,
    "wof:name":"Ukwa",
    "wof:placetype":"locality",
    "wof:population":7369
},
  "geometry": {"coordinates":[80.46942,21.97248],"type":"Point"}
}