{
  "type": "Feature",
  "properties": {
    "iso:country":"IN",
    "ks:ks_alt_nam":"Phaddupur",
    "ks:ks_name":"Ghatampur",
    "ks:ks_pop":0,
    "ks:ks_type":"VILLAGE",
    "ks:ks_uagg_main":0,
    "name:eng_x_preferred":[
        "Ghatampur"
    ],
    "name:eng_x_variant":[
        "Phaddupur"
    ],
    "wof:name":"Ghatampur",
    "wof:placetype":"neighbourhood",
    "wof:population":0
},
  "geometry": {"coordinates":[83.29516599999999,25.79059],"type":"Point"}
}