{
  "type": "Feature",
  "properties": {
    "gn:admin1_code":"28.0",
    "gn:admin2_code":"332.0",
    "gn:asciiname":"Makhna",
    "gn:country_code":"IN",
    "gn:dem":34,
    "gn:feature_class":"P",
    "gn:feature_code":"PPL",
    "gn:name":"Makhna",
    "gn:population":0,
    "gn:timezone":"Asia/Kolkata",
    "iso:country":"IN",
    "wof:name":"Makhna",
    "wof:placetype":"locality"
},
  "geometry": {"coordinates":[87.90654000000001,25.48523],"type":"Point"}
}