{
  "type": "Feature",
  "properties": {
    "iso:country":"IN",
    "ks:ks_name":"Maldar Khurd",
    "ks:ks_pop":192,
    "ks:ks_type":"VILLAGE",
    "name:eng_x_preferred":[
        "Maldar Khurd"
    ],
    "wof:name":"Maldar Khurd",
    "wof:placetype":"locality",
    "wof:population":192
},
  "geometry": {"coordinates":[73.254419,24.426081],"type":"Point"}
}