{
  "type": "Feature",
  "properties": {
    "iso:country":"IN",
    "ks:ks_name":"Magar Durgulewasti",
    "ks:ks_pop":275,
    "ks:ks_type":"HABITATION",
    "name:eng_x_preferred":[
        "Magar Durgulewasti"
    ],
    "wof:name":"Magar Durgulewasti",
    "wof:placetype":"locality",
    "wof:population":275
},
  "geometry": {"coordinates":[75.235043,18.205835],"type":"Point"}
}