{
  "type": "Feature",
  "properties": {
    "gn:admin1_code":"36",
    "gn:admin2_code":"133.0",
    "gn:asciiname":"Mayapur",
    "gn:country_code":"IN",
    "gn:dem":243,
    "gn:feature_class":"P",
    "gn:feature_code":"PPL",
    "gn:name":"M\u0101y\u0101pur",
    "gn:population":0,
    "gn:timezone":"Asia/Kolkata",
    "iso:country":"IN",
    "wof:name":"Mayapur",
    "wof:placetype":"locality"
},
  "geometry": {"coordinates":[77.23181,29.38789],"type":"Point"}
}