{
  "type": "Feature",
  "properties": {
    "gn:admin1_code":"36",
    "gn:admin2_code":"133.0",
    "gn:asciiname":"Mayapur",
    "gn:country_code":"IN",
    "gn:dem":243,
    "gn:feature_class":"P",
    "gn:feature_code":"PPL",
    "gn:name":"M\u0101y\u0101pur",
    "gn:population":0,
    "gn:timezone":"Asia/Kolkata",
    "iso:country":"IN",
    "name:ara_x_preferred":[
        "\u0645\u0639\u0628\u062f \u0645\u0627\u064a\u0627\u0628\u0648\u0631"
    ],
    "name:ben_bn_x_preferred":[
        "\u09ae\u09be\u09df\u09be\u09aa\u09c1\u09b0"
    ],
    "name:ben_in_x_preferred":[
        "\u09ae\u09be\u09df\u09be\u09aa\u09c1\u09b0"
    ],
    "name:ben_x_preferred":[
        "\u09ae\u09be\u09af\u09bc\u09be\u09aa\u09c1\u09b0"
    ],
    "name:ces_x_preferred":[
        "Majapur"
    ],
    "name:deu_x_preferred":[
        "Mayapur"
    ],
    "name:fra_x_preferred":[
        "Mayapur"
    ],
    "name:guj_x_preferred":[
        "\u0aae\u0abe\u0aaf\u0abe\u0aaa\u0ac1\u0ab0"
    ],
    "name:hin_x_preferred":[
        "\u092e\u093e\u092f\u093e\u092a\u0941\u0930"
    ],
    "name:hun_x_preferred":[
        "M\u00e1j\u00e1pur"
    ],
    "name:kan_x_preferred":[
        "\u0cae\u0cbe\u0caf\u0cbe\u0caa\u0cc1\u0cb0"
    ],
    "name:mal_x_preferred":[
        "\u0d2e\u0d3e\u0d2f\u0d3e\u0d2a\u0d42\u0d7c"
    ],
    "name:mar_x_preferred":[
        "\u092e\u093e\u092f\u093e\u092a\u0942\u0930"
    ],
    "name:pan_x_preferred":[
        "\u0a2e\u0a3e\u0a07\u0a05\u0a2a\u0a41\u0a30"
    ],
    "name:pol_x_preferred":[
        "Majapur"
    ],
    "name:rus_x_preferred":[
        "\u041c\u0430\u044f\u043f\u0443\u0440"
    ],
    "name:spa_x_preferred":[
        "M\u0101y\u0101pur"
    ],
    "name:tam_x_preferred":[
        "\u0bae\u0bbe\u0baf\u0bbe\u0baa\u0bc2\u0bb0\u0bcd"
    ],
    "name:tat_x_preferred":[
        "\u041c\u0430\u044f\u043f\u0443\u0440"
    ],
    "name:tel_x_preferred":[
        "\u0c2e\u0c3e\u0c2f\u0c3e\u0c2a\u0c42\u0c30\u0c4d"
    ],
    "name:ukr_x_preferred":[
        "\u041c\u0430\u044f\u043f\u0443\u0440"
    ],
    "name:urd_x_preferred":[
        "\u0645\u0627\u06cc\u0627\u067e\u0648\u0631"
    ],
    "name:urd_x_variant":[
        "\u0645\u0627\u06cc\u0627 \u067e\u0648\u0631"
    ],
    "wof:name":"Mayapur",
    "wof:placetype":"locality"
},
  "geometry": {"coordinates":[77.23181,29.38789],"type":"Point"}
}