{
  "type": "Feature",
  "properties": {
    "iso:country":"IN",
    "ks:ks_name":"Rampura Ryt",
    "ks:ks_pop":306,
    "ks:ks_type":"VILLAGE",
    "name:eng_x_preferred":[
        "Rampura Ryt"
    ],
    "wof:name":"Rampura Ryt",
    "wof:placetype":"locality",
    "wof:population":306
},
  "geometry": {"coordinates":[79.184372,23.251208],"type":"Point"}
}