{
  "type": "Feature",
  "properties": {
    "iso:country":"IN",
    "ks:ks_name":"Sodon Ki Dhana",
    "ks:ks_pop":45,
    "ks:ks_type":"HABITATION",
    "name:eng_x_preferred":[
        "Sodon Ki Dhana"
    ],
    "wof:name":"Sodon Ki Dhana",
    "wof:placetype":"locality",
    "wof:population":45
},
  "geometry": {"coordinates":[73.774664,25.506786],"type":"Point"}
}