{
  "type": "Feature",
  "properties": {
    "iso:country":"IN",
    "ks:ks_name":"Parasrampur",
    "ks:ks_pop":43,
    "ks:ks_type":"VILLAGE",
    "ks:ks_uagg_main":0,
    "name:eng_x_preferred":[
        "Parasrampur"
    ],
    "wof:name":"Parasrampur",
    "wof:placetype":"neighbourhood",
    "wof:population":43
},
  "geometry": {"coordinates":[83.238553,25.350868],"type":"Point"}
}