{
  "type": "Feature",
  "properties": {
    "iso:country":"IN",
    "ks:ks_name":"Rachakonda",
    "ks:ks_pop":242,
    "ks:ks_type":"VILLAGE",
    "name:eng_x_preferred":[
        "Rachakonda"
    ],
    "wof:name":"Rachakonda",
    "wof:placetype":"locality",
    "wof:population":242
},
  "geometry": {"coordinates":[78.792113,17.182817],"type":"Point"}
}