{
  "type": "Feature",
  "properties": {
    "iso:country":"IN",
    "ks:ks_name":"Hatkara",
    "ks:ks_pop":1084,
    "ks:ks_type":"VILLAGE",
    "name:eng_x_preferred":[
        "Hatkara"
    ],
    "wof:name":"Hatkara",
    "wof:placetype":"locality",
    "wof:population":1084
},
  "geometry": {"coordinates":[81.26881400000001,20.234444],"type":"Point"}
}