{
  "type": "Feature",
  "properties": {
    "iso:country":"IN",
    "ks:ks_name":"Dihwa",
    "ks:ks_pop":772,
    "ks:ks_type":"HABITATION",
    "name:eng_x_preferred":[
        "Dihwa"
    ],
    "wof:name":"Dihwa",
    "wof:placetype":"locality",
    "wof:population":772
},
  "geometry": {"coordinates":[82.800479,27.369616],"type":"Point"}
}