{
  "type": "Feature",
  "properties": {
    "iso:country":"IN",
    "ks:ks_name":"Susuda",
    "ks:ks_pop":2586,
    "ks:ks_type":"VILLAGE",
    "ks:ks_uagg_main":0,
    "name:eng_x_preferred":[
        "Susuda"
    ],
    "wof:name":"Susuda",
    "wof:placetype":"neighbourhood",
    "wof:population":2586
},
  "geometry": {"coordinates":[85.111329,20.824461],"type":"Point"}
}