{
  "type": "Feature",
  "properties": {
    "iso:country":"IN",
    "ks:ks_name":"Chak Helal",
    "ks:ks_pop":499,
    "ks:ks_type":"VILLAGE",
    "name:eng_x_preferred":[
        "Chak Helal"
    ],
    "wof:name":"Chak Helal",
    "wof:placetype":"locality",
    "wof:population":499
},
  "geometry": {"coordinates":[85.54178899999999,26.106205],"type":"Point"}
}