{
  "type": "Feature",
  "properties": {
    "iso:country":"IN",
    "ks:ks_name":"Gelthi Udiyar",
    "ks:ks_pop":18,
    "ks:ks_type":"HABITATION",
    "name:eng_x_preferred":[
        "Gelthi Udiyar"
    ],
    "wof:name":"Gelthi Udiyar",
    "wof:placetype":"locality",
    "wof:population":18
},
  "geometry": {"coordinates":[80.031784,29.875487],"type":"Point"}
}