{
  "type": "Feature",
  "properties": {
    "gn:admin1_code":"36",
    "gn:admin2_code":"149.0",
    "gn:asciiname":"Itaua",
    "gn:country_code":"IN",
    "gn:dem":153,
    "gn:feature_class":"P",
    "gn:feature_code":"PPL",
    "gn:name":"Itaua",
    "gn:population":0,
    "gn:timezone":"Asia/Kolkata",
    "iso:country":"IN",
    "wof:name":"Itaua",
    "wof:placetype":"locality"
},
  "geometry": {"coordinates":[79.28943000000002,27.71698],"type":"Point"}
}