{
  "type": "Feature",
  "properties": {
    "iso:country":"IN",
    "ks:ks_name":"Nivi 540",
    "ks:ks_pop":847,
    "ks:ks_type":"HABITATION",
    "name:eng_x_preferred":[
        "Nivi 540"
    ],
    "wof:name":"Nivi 540",
    "wof:placetype":"locality",
    "wof:population":847
},
  "geometry": {"coordinates":[81.689858,24.785546],"type":"Point"}
}