{
  "type": "Feature",
  "properties": {
    "iso:country":"IN",
    "ks:ks_name":"N. Katori",
    "ks:ks_pop":226,
    "ks:ks_type":"HABITATION",
    "name:eng_x_preferred":[
        "N. Katori"
    ],
    "wof:name":"N. Katori",
    "wof:placetype":"locality",
    "wof:population":226
},
  "geometry": {"coordinates":[78.61639599999999,27.274837],"type":"Point"}
}