{
  "type": "Feature",
  "properties": {
    "iso:country":"IN",
    "ks:ks_alt_nam":"SARKPUR BASA",
    "ks:ks_name":"Sarkpur Basa",
    "ks:ks_pop":690,
    "ks:ks_type":"HABITATION",
    "name:eng_x_preferred":[
        "Sarkpur Basa"
    ],
    "wof:name":"Sarkpur Basa",
    "wof:placetype":"locality",
    "wof:population":690
},
  "geometry": {"coordinates":[86.77203,25.586122],"type":"Point"}
}