{
  "type": "Feature",
  "properties": {
    "iso:country":"IN",
    "ks:ks_name":"Patbanda",
    "ks:ks_pop":346,
    "ks:ks_type":"VILLAGE",
    "name:eng_x_preferred":[
        "Patbanda"
    ],
    "wof:name":"Patbanda",
    "wof:placetype":"locality",
    "wof:population":346
},
  "geometry": {"coordinates":[87.29650100000001,21.924844],"type":"Point"}
}