{
  "type": "Feature",
  "properties": {
    "iso:country":"IN",
    "ks:ks_name":"Sainagar",
    "ks:ks_pop":44,
    "ks:ks_type":"HABITATION",
    "name:eng_x_preferred":[
        "Sainagar"
    ],
    "wof:name":"Sainagar",
    "wof:placetype":"locality",
    "wof:population":44
},
  "geometry": {"coordinates":[73.4272,16.49761],"type":"Point"}
}