{
  "type": "Feature",
  "properties": {
    "gn:admin1_code":"35.0",
    "gn:admin2_code":"455.0",
    "gn:asciiname":"Babai",
    "gn:country_code":"IN",
    "gn:dem":686,
    "gn:feature_class":"P",
    "gn:feature_code":"PPL",
    "gn:name":"B\u0101bai",
    "gn:population":0,
    "gn:timezone":"Asia/Kolkata",
    "iso:country":"IN",
    "name:ceb_x_preferred":[
        "Babai"
    ],
    "name:deu_x_preferred":[
        "Babai"
    ],
    "name:fas_x_preferred":[
        "\u0628\u0627\u0628\u0627\u06cc\u06cc"
    ],
    "name:fra_x_preferred":[
        "Babai"
    ],
    "name:nld_x_preferred":[
        "Babai"
    ],
    "name:rus_x_preferred":[
        "\u0411\u0430\u0431\u0430\u0439"
    ],
    "name:spa_x_preferred":[
        "Babai"
    ],
    "name:swe_x_preferred":[
        "Babai"
    ],
    "name:ukr_x_preferred":[
        "\u0411\u0430\u0431\u0430\u0439"
    ],
    "wof:name":"Babai",
    "wof:placetype":"locality"
},
  "geometry": {"coordinates":[78.95215999999998,22.19696],"type":"Point"}
}