{
  "type": "Feature",
  "properties": {
    "gn:admin1_code":"37",
    "gn:admin2_code":"403.0",
    "gn:asciiname":"Salar",
    "gn:country_code":"IN",
    "gn:dem":222,
    "gn:feature_class":"P",
    "gn:feature_code":"PPL",
    "gn:name":"S\u0101lar",
    "gn:population":0,
    "gn:timezone":"Asia/Kolkata",
    "iso:country":"IN",
    "name:cat_x_preferred":[
        "Salar"
    ],
    "name:ceb_x_preferred":[
        "Salar"
    ],
    "name:deu_x_preferred":[
        "Salar"
    ],
    "name:fas_x_preferred":[
        "\u0633\u0627\u0644\u0627\u0631"
    ],
    "name:fra_x_preferred":[
        "Salar"
    ],
    "name:ita_x_preferred":[
        "Salar"
    ],
    "name:nld_x_preferred":[
        "Salar"
    ],
    "name:rus_x_preferred":[
        "\u0421\u0430\u043b\u0430\u0440"
    ],
    "name:spa_x_preferred":[
        "Salar"
    ],
    "name:swe_x_preferred":[
        "Salar"
    ],
    "name:tur_x_preferred":[
        "Salar"
    ],
    "name:uzb_x_preferred":[
        "Salor"
    ],
    "wof:name":"Salar",
    "wof:placetype":"locality"
},
  "geometry": {"coordinates":[83.14073,21.52278],"type":"Point"}
}