{
  "type": "Feature",
  "properties": {
    "iso:country":"IN",
    "ks:ks_name":"G Ambagura",
    "ks:ks_pop":358,
    "ks:ks_type":"HABITATION",
    "name:eng_x_preferred":[
        "G Ambagura"
    ],
    "wof:name":"G Ambagura",
    "wof:placetype":"locality",
    "wof:population":358
},
  "geometry": {"coordinates":[82.896998,18.455011],"type":"Point"}
}