{
  "type": "Feature",
  "properties": {
    "iso:country":"IN",
    "ks:ks_name":"Salmara Pt.VI",
    "ks:ks_pop":1547,
    "ks:ks_type":"VILLAGE",
    "name:eng_x_preferred":[
        "Salmara Pt.VI"
    ],
    "wof:name":"Salmara Pt.VI",
    "wof:placetype":"locality",
    "wof:population":1547
},
  "geometry": {"coordinates":[90.120757,26.153083],"type":"Point"}
}