{
  "type": "Feature",
  "properties": {
    "gn:admin1_code":"2.0",
    "gn:admin2_code":"552",
    "gn:asciiname":"Iiiuru Kottapeta",
    "gn:country_code":"IN",
    "gn:dem":214,
    "gn:feature_class":"P",
    "gn:feature_code":"PPL",
    "gn:name":"Iii\u016bru Kottapeta",
    "gn:population":0,
    "gn:timezone":"Asia/Kolkata",
    "iso:country":"IN",
    "name:und_x_variant":[
        "Iii\u016bru Kottapeta",
        "Ili\u016bru Kottapeta"
    ],
    "wof:name":"Iiiuru Kottapeta",
    "wof:placetype":"neighbourhood"
},
  "geometry": {"coordinates":[78.25736000000001,15.27741],"type":"Point"}
}