{
  "type": "Feature",
  "properties": {
    "iso:country":"IN",
    "ks:ks_name":"Ujoni Borbil",
    "ks:ks_pop":956,
    "ks:ks_type":"HABITATION",
    "name:eng_x_preferred":[
        "Ujoni Borbil"
    ],
    "wof:name":"Ujoni Borbil",
    "wof:placetype":"locality",
    "wof:population":956
},
  "geometry": {"coordinates":[94.045997,27.270933],"type":"Point"}
}