{
  "type": "Feature",
  "properties": {
    "gn:admin1_code":"3.0",
    "gn:admin2_code":"301.0",
    "gn:asciiname":"Kairapur",
    "gn:country_code":"IN",
    "gn:dem":43,
    "gn:feature_class":"P",
    "gn:feature_code":"PPL",
    "gn:name":"Kairapur",
    "gn:population":0,
    "gn:timezone":"Asia/Kolkata",
    "iso:country":"IN",
    "wof:name":"Kairapur",
    "wof:placetype":"locality"
},
  "geometry": {"coordinates":[89.8708,26.35934],"type":"Point"}
}