{
  "type": "Feature",
  "properties": {
    "iso:country":"IN",
    "ks:ks_name":"Thidi",
    "ks:ks_pop":895,
    "ks:ks_type":"HABITATION",
    "name:eng_x_preferred":[
        "Thidi"
    ],
    "wof:name":"Thidi",
    "wof:placetype":"locality",
    "wof:population":895
},
  "geometry": {"coordinates":[86.485135,21.028712],"type":"Point"}
}