{
  "type": "Feature",
  "properties": {
    "gn:admin1_code":"36.0",
    "gn:admin2_code":"135.0",
    "gn:asciiname":"Abhanpur",
    "gn:country_code":"IN",
    "gn:dem":194,
    "gn:feature_class":"P",
    "gn:feature_code":"PPL",
    "gn:name":"Abhanpur",
    "gn:population":0,
    "gn:timezone":"Asia/Kolkata",
    "iso:country":"IN",
    "name:fas_x_preferred":[
        "\u0627\u0628\u0647\u0646\u067e\u0648\u0631"
    ],
    "name:tgl_x_preferred":[
        "Abhanpur"
    ],
    "name:und_x_variant":[
        "Kundarkhri"
    ],
    "name:urd_x_preferred":[
        "\u0627\u0628\u06be\u0646 \u067e\u0648\u0631"
    ],
    "wof:name":"Abhanpur",
    "wof:placetype":"locality"
},
  "geometry": {"coordinates":[78.77639000000001,28.64951],"type":"Point"}
}