{
  "type": "Feature",
  "properties": {
    "iso:country":"IN",
    "ks:ks_name":"Ranikhudi",
    "ks:ks_pop":859,
    "ks:ks_type":"VILLAGE",
    "ks:ks_uagg_main":0,
    "name:eng_x_preferred":[
        "Ranikhudi"
    ],
    "wof:name":"Ranikhudi",
    "wof:placetype":"neighbourhood",
    "wof:population":859
},
  "geometry": {"coordinates":[87.23890400000001,21.589298],"type":"Point"}
}