{
  "type": "Feature",
  "properties": {
    "iso:country":"IN",
    "ks:ks_name":"Salempur",
    "ks:ks_pop":1451,
    "ks:ks_type":"VILLAGE",
    "name:eng_x_preferred":[
        "Salempur"
    ],
    "wof:name":"Salempur",
    "wof:placetype":"locality",
    "wof:population":1451
},
  "geometry": {"coordinates":[83.992206,25.696839],"type":"Point"}
}