{
  "type": "Feature",
  "properties": {
    "gn:admin1_code":"21",
    "gn:admin2_code":"395.0",
    "gn:asciiname":"Sureli",
    "gn:country_code":"IN",
    "gn:dem":231,
    "gn:feature_class":"P",
    "gn:feature_code":"PPL",
    "gn:name":"Sureli",
    "gn:population":0,
    "gn:timezone":"Asia/Kolkata",
    "iso:country":"IN",
    "ks:ks_name":"Sureli",
    "ks:ks_type":"VILLAGE",
    "name:eng_x_preferred":[
        "Sureli"
    ],
    "wof:name":"Sureli",
    "wof:placetype":"locality"
},
  "geometry": {"coordinates":[83.079679,19.853816],"type":"Point"}
}