{
  "type": "Feature",
  "properties": {
    "gn:admin1_code":"39.0",
    "gn:admin2_code":"63.0",
    "gn:asciiname":"Tobni",
    "gn:country_code":"IN",
    "gn:dem":2276,
    "gn:feature_class":"P",
    "gn:feature_code":"PPL",
    "gn:name":"Tobni",
    "gn:population":0,
    "gn:timezone":"Asia/Kolkata",
    "iso:country":"IN",
    "wof:name":"Tobni",
    "wof:placetype":"locality"
},
  "geometry": {"coordinates":[79.91996999999998,30.03824],"type":"Point"}
}