{
  "type": "Feature",
  "properties": {
    "iso:country":"IN",
    "ks:ks_name":"Besana Falia",
    "ks:ks_pop":280,
    "ks:ks_type":"HABITATION",
    "name:eng_x_preferred":[
        "Besana Falia"
    ],
    "wof:name":"Besana Falia",
    "wof:placetype":"locality",
    "wof:population":280
},
  "geometry": {"coordinates":[73.65181699999999,22.555133],"type":"Point"}
}