{
  "type": "Feature",
  "properties": {
    "iso:country":"IN",
    "ks:ks_name":"Purani Dhela",
    "ks:ks_pop":406,
    "ks:ks_type":"VILLAGE",
    "name:eng_x_preferred":[
        "Purani Dhela"
    ],
    "wof:name":"Purani Dhela",
    "wof:placetype":"locality",
    "wof:population":406
},
  "geometry": {"coordinates":[94.206352,27.06631],"type":"Point"}
}