{
  "type": "Feature",
  "properties": {
    "gn:admin1_code":"36",
    "gn:admin2_code":"152.0",
    "gn:asciiname":"Ballia",
    "gn:country_code":"IN",
    "gn:dem":157,
    "gn:feature_class":"P",
    "gn:feature_code":"PPL",
    "gn:name":"Ballia",
    "gn:population":0,
    "gn:timezone":"Asia/Kolkata",
    "iso:country":"IN",
    "ks:ks_name":"Ballia",
    "ks:ks_pop":2622,
    "ks:ks_type":"VILLAGE",
    "ks:ks_uagg_main":0,
    "name:ara_x_preferred":[
        "\u0628\u0627\u0644\u064a\u0627"
    ],
    "name:ben_bn_x_preferred":[
        "\u09ac\u09be\u09b2\u09bf\u09df\u09be"
    ],
    "name:ben_in_x_preferred":[
        "\u09ac\u09be\u09b2\u09bf\u09df\u09be"
    ],
    "name:bih_x_preferred":[
        "\u092c\u0932\u093f\u092f\u093e\u0901"
    ],
    "name:bpy_x_preferred":[
        "\u09ac\u09be\u09b2\u09cd\u09b2\u09bf\u09af\u09bc\u09be"
    ],
    "name:cat_x_preferred":[
        "Ballia"
    ],
    "name:ceb_x_preferred":[
        "Ballia"
    ],
    "name:deu_x_preferred":[
        "Ballia"
    ],
    "name:eng_x_preferred":[
        "Ballia"
    ],
    "name:fra_x_preferred":[
        "Ballia"
    ],
    "name:guj_x_preferred":[
        "\u0aac\u0ab2\u0abf\u0aaf\u0abe"
    ],
    "name:hin_x_preferred":[
        "\u092c\u0932\u093f\u092f\u093e"
    ],
    "name:ita_x_preferred":[
        "Ballia"
    ],
    "name:kan_x_preferred":[
        "\u0cac\u0cb2\u0ccd\u0cb2\u0cbf\u0caf\u0cbe"
    ],
    "name:mai_x_preferred":[
        "\u092c\u0932\u093f\u092f\u093e\u0901"
    ],
    "name:mal_x_preferred":[
        "\u0d2c\u0d3e\u0d32\u0d3f\u0d2f"
    ],
    "name:mar_x_preferred":[
        "\u092c\u0932\u093f\u092f\u093e"
    ],
    "name:mlg_x_preferred":[
        "Ballia"
    ],
    "name:msa_x_preferred":[
        "Ballia"
    ],
    "name:new_x_preferred":[
        "\u092c\u0932\u093f\u092f\u093e\u0901"
    ],
    "name:nld_x_preferred":[
        "Ballia"
    ],
    "name:pam_x_preferred":[
        "Ballia"
    ],
    "name:pan_x_preferred":[
        "\u0a2c\u0a32\u0a40\u0a06"
    ],
    "name:pnb_x_preferred":[
        "\u0628\u0644\u06cc\u06c1"
    ],
    "name:pol_x_preferred":[
        "Ballia"
    ],
    "name:rus_x_preferred":[
        "\u0411\u0430\u043b\u043b\u0438\u044f"
    ],
    "name:san_x_preferred":[
        "\u092c\u0932\u093f\u092f\u093e"
    ],
    "name:swe_x_preferred":[
        "Ballia"
    ],
    "name:tam_x_preferred":[
        "\u0baa\u0bb2\u0bcd\u0bb2\u0bbf\u0baf\u0bbe"
    ],
    "name:tel_x_preferred":[
        "\u0c2c\u0c32\u0c3f\u0c2f\u0c3e"
    ],
    "name:urd_x_preferred":[
        "\u0628\u0644\u06cc\u0627"
    ],
    "name:vie_x_preferred":[
        "Ballia"
    ],
    "name:zho_x_preferred":[
        "\u5df4\u5229\u4e9a"
    ],
    "wof:name":"Ballia",
    "wof:placetype":"locality",
    "wof:population":2622
},
  "geometry": {"coordinates":[79.952243,27.854524],"type":"Point"}
}