{
  "type": "Feature",
  "properties": {
    "gn:admin1_code":"40",
    "gn:admin2_code":"533.0",
    "gn:asciiname":"Dewara Buzurg",
    "gn:country_code":"IN",
    "gn:dem":372,
    "gn:feature_class":"P",
    "gn:feature_code":"PPL",
    "gn:name":"Dew\u0101ra Buzurg",
    "gn:population":0,
    "gn:timezone":"Asia/Kolkata",
    "iso:country":"IN",
    "wof:name":"Dewara Buzurg",
    "wof:placetype":"locality"
},
  "geometry": {"coordinates":[77.75644,18.40392],"type":"Point"}
}