{
  "type": "Feature",
  "properties": {
    "iso:country":"IN",
    "ks:ks_name":"Honnebena",
    "ks:ks_pop":44,
    "ks:ks_type":"HABITATION",
    "name:eng_x_preferred":[
        "Honnebena"
    ],
    "wof:name":"Honnebena",
    "wof:placetype":"locality",
    "wof:population":44
},
  "geometry": {"coordinates":[74.637721,14.821547],"type":"Point"}
}