{
  "type": "Feature",
  "properties": {
    "gn:admin1_code":"39.0",
    "gn:admin2_code":"65.0",
    "gn:asciiname":"Danda Malla",
    "gn:country_code":"IN",
    "gn:dem":837,
    "gn:feature_class":"P",
    "gn:feature_code":"PPL",
    "gn:name":"D\u0101nda Malla",
    "gn:population":0,
    "gn:timezone":"Asia/Kolkata",
    "iso:country":"IN",
    "wof:name":"Danda Malla",
    "wof:placetype":"locality"
},
  "geometry": {"coordinates":[79.94835,29.17045],"type":"Point"}
}