{
  "type": "Feature",
  "properties": {
    "iso:country":"IN",
    "ks:ks_name":"Chak Etbari",
    "ks:ks_pop":2140,
    "ks:ks_type":"VILLAGE",
    "ks:ks_uagg_main":0,
    "name:eng_x_preferred":[
        "Chak Etbari"
    ],
    "wof:name":"Chak Etbari",
    "wof:placetype":"locality",
    "wof:population":2140
},
  "geometry": {"coordinates":[88.19971200000001,22.414323],"type":"Point"}
}