{
  "type": "Feature",
  "properties": {
    "iso:country":"IN",
    "ks:ks_name":"Chhedi Bashyak",
    "ks:ks_pop":1298,
    "ks:ks_type":"HABITATION",
    "name:eng_x_preferred":[
        "Chhedi Bashyak"
    ],
    "wof:name":"Chhedi Bashyak",
    "wof:placetype":"locality",
    "wof:population":1298
},
  "geometry": {"coordinates":[79.88787000000001,25.811024],"type":"Point"}
}