{
  "type": "Feature",
  "properties": {
    "iso:country":"IN",
    "ks:ks_alt_nam":"koombanpara south",
    "ks:ks_name":"Koombanpara South",
    "ks:ks_pop":420,
    "ks:ks_type":"HABITATION",
    "name:eng_x_preferred":[
        "Koombanpara South"
    ],
    "wof:name":"Koombanpara South",
    "wof:placetype":"locality",
    "wof:population":420
},
  "geometry": {"coordinates":[76.99648500000001,10.011311],"type":"Point"}
}