{
  "type": "Feature",
  "properties": {
    "gn:admin1_code":"11.0",
    "gn:admin2_code":"32.0",
    "gn:asciiname":"Chaunpadharo",
    "gn:country_code":"IN",
    "gn:dem":1230,
    "gn:feature_class":"P",
    "gn:feature_code":"PPL",
    "gn:name":"Chaunpadh\u0101ro",
    "gn:population":0,
    "gn:timezone":"Asia/Kolkata",
    "iso:country":"IN",
    "wof:name":"Chaunpadharo",
    "wof:placetype":"locality"
},
  "geometry": {"coordinates":[77.23571,30.73242],"type":"Point"}
}