{
  "type": "Feature",
  "properties": {
    "gn:admin1_code":"34.0",
    "gn:admin2_code":"220.0",
    "gn:asciiname":"Rohna",
    "gn:country_code":"IN",
    "gn:dem":57,
    "gn:feature_class":"P",
    "gn:feature_code":"PPL",
    "gn:name":"Rohna",
    "gn:population":0,
    "gn:timezone":"Asia/Kolkata",
    "iso:country":"IN",
    "ks:ks_name":"Rohna",
    "ks:ks_pop":1397,
    "ks:ks_type":"VILLAGE",
    "name:eng_x_preferred":[
        "Rohna"
    ],
    "wof:name":"Rohna",
    "wof:placetype":"locality",
    "wof:population":1397
},
  "geometry": {"coordinates":[85.152576,25.996426],"type":"Point"}
}