{
  "type": "Feature",
  "properties": {
    "iso:country":"IN",
    "ks:ks_alt_nam":"DOMA DIN",
    "ks:ks_name":"Doma Din",
    "ks:ks_pop":230,
    "ks:ks_type":"HABITATION",
    "name:eng_x_preferred":[
        "Doma Din"
    ],
    "wof:name":"Doma Din",
    "wof:placetype":"locality",
    "wof:population":230
},
  "geometry": {"coordinates":[81.718506,26.431365],"type":"Point"}
}