{
  "type": "Feature",
  "properties": {
    "iso:country":"IN",
    "ks:ks_name":"Upper Arangloya",
    "ks:ks_pop":148,
    "ks:ks_type":"HABITATION",
    "name:eng_x_preferred":[
        "Upper Arangloya"
    ],
    "wof:name":"Upper Arangloya",
    "wof:placetype":"locality",
    "wof:population":148
},
  "geometry": {"coordinates":[84.33546800000001,23.370765],"type":"Point"}
}