{
  "type": "Feature",
  "properties": {
    "iso:country":"IN",
    "ks:ks_name":"Moga Jitsingh",
    "ks:ks_pop":682,
    "ks:ks_type":"VILLAGE",
    "ks:ks_uagg_main":0,
    "name:eng_x_preferred":[
        "Moga Jitsingh"
    ],
    "wof:name":"Moga Jitsingh",
    "wof:placetype":"locality",
    "wof:population":682
},
  "geometry": {"coordinates":[75.157449,30.792584],"type":"Point"}
}