{
  "type": "Feature",
  "properties": {
    "iso:country":"IN",
    "ks:ks_name":"Lalanawas Jetasari",
    "ks:ks_pop":706,
    "ks:ks_type":"VILLAGE",
    "name:eng_x_preferred":[
        "Lalanawas Jetasari"
    ],
    "wof:name":"Lalanawas Jetasari",
    "wof:placetype":"locality",
    "wof:population":706
},
  "geometry": {"coordinates":[74.916922,29.046833],"type":"Point"}
}