{
  "type": "Feature",
  "properties": {
    "iso:country":"IN",
    "ks:ks_name":"Alugula Thanda",
    "ks:ks_pop":79,
    "ks:ks_type":"HABITATION",
    "ks:ks_uagg_main":0,
    "name:eng_x_preferred":[
        "Alugula Thanda"
    ],
    "wof:name":"Alugula Thanda",
    "wof:placetype":"neighbourhood",
    "wof:population":79
},
  "geometry": {"coordinates":[79.395195,17.510253],"type":"Point"}
}