{
  "type": "Feature",
  "properties": {
    "iso:country":"IN",
    "ks:ks_name":"Jirapur",
    "ks:ks_pop":367,
    "ks:ks_type":"VILLAGE",
    "ks:ks_uagg_main":0,
    "name:eng_x_preferred":[
        "Jirapur"
    ],
    "wof:name":"Jirapur",
    "wof:placetype":"neighbourhood",
    "wof:population":367
},
  "geometry": {"coordinates":[74.142955,20.94915],"type":"Point"}
}