{
  "type": "Feature",
  "properties": {
    "iso:country":"IN",
    "ks:ks_name":"Gombura",
    "ks:ks_pop":234,
    "ks:ks_type":"HABITATION",
    "name:eng_x_preferred":[
        "Gombura"
    ],
    "wof:name":"Gombura",
    "wof:placetype":"locality",
    "wof:population":234
},
  "geometry": {"coordinates":[85.374307,22.874801],"type":"Point"}
}