{
  "type": "Feature",
  "properties": {
    "iso:country":"IN",
    "ks:ks_name":"Khotjuva",
    "ks:ks_pop":118,
    "ks:ks_type":"HABITATION",
    "name:eng_x_preferred":[
        "Khotjuva"
    ],
    "wof:name":"Khotjuva",
    "wof:placetype":"locality",
    "wof:population":118
},
  "geometry": {"coordinates":[73.479591,16.160336],"type":"Point"}
}