{
  "type": "Feature",
  "properties": {
    "gn:admin1_code":"2.0",
    "gn:admin2_code":"543.0",
    "gn:asciiname":"Gurla",
    "gn:country_code":"IN",
    "gn:dem":127,
    "gn:feature_class":"P",
    "gn:feature_code":"PPL",
    "gn:name":"Gurla",
    "gn:population":0,
    "gn:timezone":"Asia/Kolkata",
    "iso:country":"IN",
    "name:ceb_x_preferred":[
        "Gurla"
    ],
    "name:new_x_preferred":[
        "\u0917\u0941\u0930\u094d\u0932 \u092e\u0923\u094d\u0921\u0932"
    ],
    "name:swe_x_preferred":[
        "Gurla"
    ],
    "name:tam_x_preferred":[
        "\u0b95\u0bc1\u0bb0\u0bcd\u0bb2\u0bbe"
    ],
    "name:tel_x_preferred":[
        "\u0c17\u0c41\u0c30\u0c4d\u0c32"
    ],
    "name:urd_x_preferred":[
        "\u06af\u0648\u0631\u0644\u0627"
    ],
    "wof:name":"Gurla",
    "wof:placetype":"locality"
},
  "geometry": {"coordinates":[83.23564,18.30851],"type":"Point"}
}