{
  "type": "Feature",
  "properties": {
    "gn:admin1_code":"19.0",
    "gn:admin2_code":"576.0",
    "gn:asciiname":"Hebbale",
    "gn:country_code":"IN",
    "gn:dem":888,
    "gn:feature_class":"P",
    "gn:feature_code":"PPLL",
    "gn:name":"Hebbale",
    "gn:population":0,
    "gn:timezone":"Asia/Kolkata",
    "iso:country":"IN",
    "ks:ks_name":"Hebbale",
    "ks:ks_pop":4185,
    "ks:ks_type":"VILLAGE",
    "name:eng_x_preferred":[
        "Hebbale"
    ],
    "wof:name":"Hebbale",
    "wof:placetype":"locality",
    "wof:population":4185
},
  "geometry": {"coordinates":[75.9678,12.198327],"type":"Point"}
}