{
  "type": "Feature",
  "properties": {
    "gn:admin1_code":"36",
    "gn:admin2_code":"183.0",
    "gn:asciiname":"Pura Hanuman Singh",
    "gn:country_code":"IN",
    "gn:dem":105,
    "gn:feature_class":"P",
    "gn:feature_code":"PPL",
    "gn:name":"Pura Hanum\u0101n Singh",
    "gn:population":0,
    "gn:timezone":"Asia/Kolkata",
    "iso:country":"IN",
    "wof:name":"Pura Hanuman Singh",
    "wof:placetype":"neighbourhood"
},
  "geometry": {"coordinates":[81.99345,27.08691],"type":"Point"}
}