{
  "type": "Feature",
  "properties": {
    "gn:admin1_code":"24.0",
    "gn:admin2_code":"102",
    "gn:asciiname":"Bikasi",
    "gn:country_code":"IN",
    "gn:dem":269,
    "gn:feature_class":"P",
    "gn:feature_code":"PPL",
    "gn:name":"Bik\u0101si",
    "gn:population":0,
    "gn:timezone":"Asia/Kolkata",
    "iso:country":"IN",
    "name:und_x_variant":[
        "Bik\u0101si",
        "Bikasi"
    ],
    "wof:name":"Bikasi",
    "wof:placetype":"neighbourhood"
},
  "geometry": {"coordinates":[74.85352,28.43975],"type":"Point"}
}