{
  "type": "Feature",
  "properties": {
    "gn:admin1_code":"36",
    "gn:admin2_code":"199.0",
    "gn:asciiname":"Bilahi",
    "gn:country_code":"IN",
    "gn:dem":154,
    "gn:feature_class":"P",
    "gn:feature_code":"PPL",
    "gn:name":"Bil\u0101hi",
    "gn:population":0,
    "gn:timezone":"Asia/Kolkata",
    "iso:country":"IN",
    "ks:ks_name":"Belahi",
    "ks:ks_pop":168,
    "ks:ks_type":"VILLAGE",
    "name:eng_x_preferred":[
        "Belahi"
    ],
    "name:eng_x_variant":[
        "Bilahi"
    ],
    "wof:name":"Belahi",
    "wof:placetype":"locality",
    "wof:population":168
},
  "geometry": {"coordinates":[82.476696,25.036999],"type":"Point"}
}