{
  "type": "Feature",
  "properties": {
    "iso:country":"IN",
    "ks:ks_name":"Yadav Tola",
    "ks:ks_pop":100,
    "ks:ks_type":"HABITATION",
    "name:eng_x_preferred":[
        "Yadav Tola"
    ],
    "wof:name":"Yadav Tola",
    "wof:placetype":"locality",
    "wof:population":100
},
  "geometry": {"coordinates":[86.870407,24.57786],"type":"Point"}
}