{
  "type": "Feature",
  "properties": {
    "iso:country":"IN",
    "ks:ks_name":"Benepota",
    "ks:ks_pop":1223,
    "ks:ks_type":"HABITATION",
    "ks:ks_uagg_main":0,
    "name:eng_x_preferred":[
        "Benepota"
    ],
    "wof:name":"Benepota",
    "wof:placetype":"neighbourhood",
    "wof:population":1223
},
  "geometry": {"coordinates":[88.897491,22.541946],"type":"Point"}
}