{
  "type": "Feature",
  "properties": {
    "gn:admin1_code":"12",
    "gn:admin2_code":"21.0",
    "gn:asciiname":"Nikki Kul",
    "gn:country_code":"IN",
    "gn:dem":269,
    "gn:feature_class":"P",
    "gn:feature_code":"PPL",
    "gn:name":"Nikki K\u016bl",
    "gn:population":0,
    "gn:timezone":"Asia/Kolkata",
    "iso:country":"IN",
    "wof:name":"Nikki Kul",
    "wof:placetype":"locality"
},
  "geometry": {"coordinates":[74.80309,32.52834],"type":"Point"}
}