{
  "type": "Feature",
  "properties": {
    "iso:country":"IN",
    "ks:ks_name":"Thimmaravalasai",
    "ks:ks_pop":320,
    "ks:ks_type":"HABITATION",
    "name:eng_x_preferred":[
        "Thimmaravalasai"
    ],
    "wof:name":"Thimmaravalasai",
    "wof:placetype":"locality",
    "wof:population":320
},
  "geometry": {"coordinates":[78.725296,12.556661],"type":"Point"}
}