{
  "type": "Feature",
  "properties": {
    "gn:admin1_code":"21",
    "gn:admin2_code":"396.0",
    "gn:asciiname":"Tuta",
    "gn:country_code":"IN",
    "gn:dem":635,
    "gn:feature_class":"P",
    "gn:feature_code":"PPL",
    "gn:name":"Tuta",
    "gn:population":0,
    "gn:timezone":"Asia/Kolkata",
    "iso:country":"IN",
    "ks:ks_name":"Tuta",
    "ks:ks_pop":58,
    "ks:ks_type":"HABITATION",
    "name:ceb_x_preferred":[
        "Tuta"
    ],
    "name:deu_x_preferred":[
        "Tuta"
    ],
    "name:eng_x_preferred":[
        "Tuta"
    ],
    "name:fra_x_preferred":[
        "Tuta"
    ],
    "name:ita_x_preferred":[
        "Tuta"
    ],
    "name:por_x_preferred":[
        "Tuta"
    ],
    "name:spa_x_preferred":[
        "Tuta"
    ],
    "name:swe_x_preferred":[
        "Tuta"
    ],
    "wof:name":"Tuta",
    "wof:placetype":"locality",
    "wof:population":58
},
  "geometry": {"coordinates":[83.365898,19.533294],"type":"Point"}
}