{
  "type": "Feature",
  "properties": {
    "iso:country":"IN",
    "ks:ks_name":"Mahantatola",
    "ks:ks_pop":300,
    "ks:ks_type":"HABITATION",
    "name:eng_x_preferred":[
        "Mahantatola"
    ],
    "wof:name":"Mahantatola",
    "wof:placetype":"locality",
    "wof:population":300
},
  "geometry": {"coordinates":[84.96662999999999,22.234838],"type":"Point"}
}