{
  "type": "Feature",
  "properties": {
    "gn:admin1_code":"2.0",
    "gn:admin2_code":"544.0",
    "gn:asciiname":"Kinchamanda",
    "gn:country_code":"IN",
    "gn:dem":993,
    "gn:feature_class":"P",
    "gn:feature_code":"PPL",
    "gn:name":"Kinchamanda",
    "gn:population":0,
    "gn:timezone":"Asia/Kolkata",
    "iso:country":"IN",
    "wof:name":"Kinchamanda",
    "wof:placetype":"locality"
},
  "geometry": {"coordinates":[82.79552,18.24383],"type":"Point"}
}