{
  "type": "Feature",
  "properties": {
    "gn:admin1_code":"16",
    "gn:admin2_code":"511.0",
    "gn:asciiname":"Pandyacha Tanda",
    "gn:country_code":"IN",
    "gn:dem":522,
    "gn:feature_class":"P",
    "gn:feature_code":"PPL",
    "gn:name":"P\u0101ndy\u0101cha T\u0101nda",
    "gn:population":0,
    "gn:timezone":"Asia/Kolkata",
    "iso:country":"IN",
    "wof:name":"Pandyacha Tanda",
    "wof:placetype":"locality"
},
  "geometry": {"coordinates":[77.44785,18.37307],"type":"Point"}
}