{
  "type": "Feature",
  "properties": {
    "gn:admin1_code":"24",
    "gn:admin2_code":"129.0",
    "gn:asciiname":"Gulkheri",
    "gn:country_code":"IN",
    "gn:dem":272,
    "gn:feature_class":"P",
    "gn:feature_code":"PPL",
    "gn:name":"Gulkheri",
    "gn:population":0,
    "gn:timezone":"Asia/Kolkata",
    "iso:country":"IN",
    "wof:name":"Gulkheri",
    "wof:placetype":"locality"
},
  "geometry": {"coordinates":[76.31373000000001,24.81979],"type":"Point"}
}