{
  "type": "Feature",
  "properties": {
    "iso:country":"IN",
    "ks:ks_name":"Charnarayanpur",
    "ks:ks_pop":0,
    "ks:ks_type":"VILLAGE",
    "name:eng_x_preferred":[
        "Charnarayanpur"
    ],
    "wof:name":"Charnarayanpur",
    "wof:placetype":"locality",
    "wof:population":0
},
  "geometry": {"coordinates":[88.507007,23.900673],"type":"Point"}
}