{
  "type": "Feature",
  "properties": {
    "iso:country":"IN",
    "ks:ks_name":"Chatiapada",
    "ks:ks_pop":67,
    "ks:ks_type":"VILLAGE",
    "name:eng_x_preferred":[
        "Chatiapada"
    ],
    "wof:name":"Chatiapada",
    "wof:placetype":"locality",
    "wof:population":67
},
  "geometry": {"coordinates":[82.524683,18.654934],"type":"Point"}
}