{
  "type": "Feature",
  "properties": {
    "gn:admin1_code":"36",
    "gn:admin2_code":"160.0",
    "gn:asciiname":"Alha",
    "gn:country_code":"IN",
    "gn:dem":148,
    "gn:feature_class":"P",
    "gn:feature_code":"PPL",
    "gn:name":"Alha",
    "gn:population":0,
    "gn:timezone":"Asia/Kolkata",
    "iso:country":"IN",
    "name:bih_x_preferred":[
        "\u0906\u0932\u094d\u0939\u093e"
    ],
    "name:hin_x_preferred":[
        "\u0906\u0932\u094d\u0939\u093e"
    ],
    "wof:name":"Alha",
    "wof:placetype":"locality"
},
  "geometry": {"coordinates":[79.62026999999998,27.13816],"type":"Point"}
}