{
  "type": "Feature",
  "properties": {
    "iso:country":"IN",
    "ks:ks_name":"Bramha Wadi",
    "ks:ks_pop":240,
    "ks:ks_type":"HABITATION",
    "name:eng_x_preferred":[
        "Bramha Wadi"
    ],
    "wof:name":"Bramha Wadi",
    "wof:placetype":"locality",
    "wof:population":240
},
  "geometry": {"coordinates":[75.91136400000001,20.28473],"type":"Point"}
}