{
  "type": "Feature",
  "properties": {
    "gn:admin1_code":"16",
    "gn:admin2_code":"508.0",
    "gn:asciiname":"Kumalpar",
    "gn:country_code":"IN",
    "gn:dem":283,
    "gn:feature_class":"P",
    "gn:feature_code":"PPL",
    "gn:name":"Kumalp\u0101r",
    "gn:population":0,
    "gn:timezone":"Asia/Kolkata",
    "iso:country":"IN",
    "wof:name":"Kumalpar",
    "wof:placetype":"locality"
},
  "geometry": {"coordinates":[80.46562,20.4728],"type":"Point"}
}