{
  "type": "Feature",
  "properties": {
    "iso:country":"IN",
    "ks:ks_name":"Badabankapada",
    "ks:ks_pop":326,
    "ks:ks_type":"VILLAGE",
    "name:eng_x_preferred":[
        "Badabankapada"
    ],
    "wof:name":"Badabankapada",
    "wof:placetype":"locality",
    "wof:population":326
},
  "geometry": {"coordinates":[84.336178,20.805598],"type":"Point"}
}