{
  "type": "Feature",
  "properties": {
    "iso:country":"IN",
    "ks:ks_name":"Utara Falia",
    "ks:ks_pop":115,
    "ks:ks_type":"HABITATION",
    "name:eng_x_preferred":[
        "Utara Falia"
    ],
    "wof:name":"Utara Falia",
    "wof:placetype":"locality",
    "wof:population":115
},
  "geometry": {"coordinates":[73.192083,20.52475],"type":"Point"}
}