{
  "type": "Feature",
  "properties": {
    "iso:country":"IN",
    "ks:ks_name":"Baba Ki Bar",
    "ks:ks_pop":1066,
    "ks:ks_type":"VILLAGE",
    "name:eng_x_preferred":[
        "Baba Ki Bar"
    ],
    "wof:name":"Baba Ki Bar",
    "wof:placetype":"locality",
    "wof:population":1066
},
  "geometry": {"coordinates":[73.942262,23.517904],"type":"Point"}
}