{
  "type": "Feature",
  "properties": {
    "iso:country":"IN",
    "ks:ks_alt_nam":"GADRIYAN",
    "ks:ks_name":"Gadriyan",
    "ks:ks_pop":203,
    "ks:ks_type":"HABITATION",
    "name:eng_x_preferred":[
        "Gadriyan"
    ],
    "wof:name":"Gadriyan",
    "wof:placetype":"locality",
    "wof:population":203
},
  "geometry": {"coordinates":[81.757761,26.180072],"type":"Point"}
}