{
  "type": "Feature",
  "properties": {
    "gn:admin1_code":"37.0",
    "gn:admin2_code":"401",
    "gn:asciiname":"Daura",
    "gn:country_code":"IN",
    "gn:dem":697,
    "gn:feature_class":"P",
    "gn:feature_code":"PPL",
    "gn:name":"Daura",
    "gn:population":0,
    "gn:timezone":"Asia/Kolkata",
    "iso:country":"IN",
    "name:aze_x_preferred":[
        "Daura"
    ],
    "name:bul_x_preferred":[
        "\u0414\u0430\u0443\u0440\u0430"
    ],
    "name:cat_x_preferred":[
        "Daura"
    ],
    "name:ceb_x_preferred":[
        "Daura"
    ],
    "name:fra_x_preferred":[
        "Daura"
    ],
    "name:hau_x_preferred":[
        "Daura"
    ],
    "name:ita_x_preferred":[
        "Daura"
    ],
    "name:lit_x_preferred":[
        "Daura"
    ],
    "name:spa_x_preferred":[
        "Daura"
    ],
    "name:urd_x_preferred":[
        "\u062f\u0627\u0648\u0631\u0627"
    ],
    "wof:name":"Daura",
    "wof:placetype":"locality"
},
  "geometry": {"coordinates":[83.44816,23.52782],"type":"Point"}
}