{
  "type": "Feature",
  "properties": {
    "iso:country":"IN",
    "ks:ks_name":"Awaspara",
    "ks:ks_pop":24,
    "ks:ks_type":"HABITATION",
    "name:eng_x_preferred":[
        "Awaspara"
    ],
    "wof:name":"Awaspara",
    "wof:placetype":"locality",
    "wof:population":24
},
  "geometry": {"coordinates":[80.808164,20.630829],"type":"Point"}
}