{
  "type": "Feature",
  "properties": {
    "gn:admin1_code":"34.0",
    "gn:admin2_code":"218.0",
    "gn:asciiname":"Pharchhuhi",
    "gn:country_code":"IN",
    "gn:dem":68,
    "gn:feature_class":"P",
    "gn:feature_code":"PPL",
    "gn:name":"Pharchhuhi",
    "gn:population":0,
    "gn:timezone":"Asia/Kolkata",
    "iso:country":"IN",
    "ks:ks_name":"Pharchhuhi",
    "ks:ks_pop":527,
    "ks:ks_type":"VILLAGE",
    "ks:ks_uagg_main":0,
    "name:eng_x_preferred":[
        "Pharchhuhi"
    ],
    "wof:name":"Pharchhuhi",
    "wof:placetype":"neighbourhood",
    "wof:population":527
},
  "geometry": {"coordinates":[84.194666,26.225831],"type":"Point"}
}