{
  "type": "Feature",
  "properties": {
    "gn:admin1_code":"11",
    "gn:admin2_code":"30.0",
    "gn:asciiname":"Baggar",
    "gn:country_code":"IN",
    "gn:dem":500,
    "gn:feature_class":"P",
    "gn:feature_code":"PPL",
    "gn:name":"Baggar",
    "gn:population":0,
    "gn:timezone":"Asia/Kolkata",
    "iso:country":"IN",
    "name:ben_x_preferred":[
        "\u09ac\u09be\u0997\u09cd\u0997\u09be\u09b0"
    ],
    "name:bpy_x_preferred":[
        "\u09ac\u09be\u0997\u09cd\u0997\u09be\u09b0"
    ],
    "name:ita_x_preferred":[
        "Baggar"
    ],
    "name:mlg_x_preferred":[
        "Baggar"
    ],
    "name:msa_x_preferred":[
        "Baggar"
    ],
    "name:new_x_preferred":[
        "\u092c\u0917\u094d\u0917\u0930"
    ],
    "name:vie_x_preferred":[
        "Baggar"
    ],
    "name:zho_x_preferred":[
        "\u5df4\u52a0\u5c14"
    ],
    "wof:name":"Baggar",
    "wof:placetype":"locality"
},
  "geometry": {"coordinates":[76.7881,31.40458],"type":"Point"}
}