{
  "type": "Feature",
  "properties": {
    "gn:admin1_code":"12.0",
    "gn:admin2_code":"18.0",
    "gn:asciiname":"Phate",
    "gn:country_code":"IN",
    "gn:dem":1411,
    "gn:feature_class":"P",
    "gn:feature_code":"PPL",
    "gn:name":"Ph\u0101t\u0113",
    "gn:population":0,
    "gn:timezone":"Asia/Kolkata",
    "iso:country":"IN",
    "wof:name":"Phate",
    "wof:placetype":"locality"
},
  "geometry": {"coordinates":[75.82769999999999,33.16452],"type":"Point"}
}