{
  "type": "Feature",
  "properties": {
    "iso:country":"IN",
    "ks:ks_name":"Naujain",
    "ks:ks_pop":2258,
    "ks:ks_type":"HABITATION",
    "name:eng_x_preferred":[
        "Naujain"
    ],
    "wof:name":"Naujain",
    "wof:placetype":"locality",
    "wof:population":2258
},
  "geometry": {"coordinates":[86.828171,25.005072],"type":"Point"}
}