{
  "type": "Feature",
  "properties": {
    "iso:country":"IN",
    "ks:ks_alt_nam":"paschim tola",
    "ks:ks_name":"Paschim Tola",
    "ks:ks_pop":510,
    "ks:ks_type":"HABITATION",
    "name:eng_x_preferred":[
        "Paschim Tola"
    ],
    "wof:name":"Paschim Tola",
    "wof:placetype":"locality",
    "wof:population":510
},
  "geometry": {"coordinates":[85.91553999999999,25.652123],"type":"Point"}
}