{
  "type": "Feature",
  "properties": {
    "iso:country":"IN",
    "ks:ks_alt_nam":"BHUIYAN TOLA",
    "ks:ks_name":"Bhuiyan Tola",
    "ks:ks_pop":175,
    "ks:ks_type":"HABITATION",
    "name:eng_x_preferred":[
        "Bhuiyan Tola"
    ],
    "wof:name":"Bhuiyan Tola",
    "wof:placetype":"locality",
    "wof:population":175
},
  "geometry": {"coordinates":[84.88131199999999,24.259249],"type":"Point"}
}