{
  "type": "Feature",
  "properties": {
    "iso:country":"IN",
    "name:ara_x_preferred":[
        "\u0633\u0631\u064a \u0643\u0631\u0627\u064a\u0645"
    ],
    "name:ben_bn_x_preferred":[
        "\u09b6\u09cd\u09b0\u09c0 \u0995\u09b0\u09be\u09af\u09bc\u09be\u09ae"
    ],
    "name:ben_in_x_preferred":[
        "\u09b6\u09cd\u09b0\u09c0 \u0995\u09b0\u09be\u09af\u09bc\u09be\u09ae"
    ],
    "name:eng_x_preferred":[
        "Sree Karayam"
    ],
    "name:guj_x_preferred":[
        "\u0ab6\u0acd\u0ab0\u0ac0 \u0a95\u0abe\u0ab0\u0abe\u0aaf\u0aae"
    ],
    "name:hin_x_preferred":[
        "\u0936\u094d\u0930\u0940 \u0915\u093e\u0930\u094d\u092f\u092e"
    ],
    "name:kan_x_preferred":[
        "\u0cb6\u0ccd\u0cb0\u0cc0 \u0c95\u0cb0\u0caf\u0cae\u0ccd"
    ],
    "name:mal_x_preferred":[
        "\u0d36\u0d4d\u0d30\u0d40 \u0d15\u0d30\u0d2f\u0d02"
    ],
    "name:mar_x_preferred":[
        "\u0936\u094d\u0930\u0940 \u0915\u0930\u092f\u092e"
    ],
    "name:pan_x_preferred":[
        "\u0a38\u0a4d\u0a30\u0a40 \u0a15\u0a30\u0a3f\u0a2f\u0a2e"
    ],
    "name:tam_x_preferred":[
        "\u0bb6\u0bcd\u0bb0\u0bc0 \u0b95\u0bbe\u0bb0\u0baf\u0bae\u0bcd"
    ],
    "name:tel_x_preferred":[
        "\u0c36\u0c4d\u0c30\u0c40 \u0c15\u0c30\u0c2f\u0c02"
    ],
    "name:urd_x_preferred":[
        "\u0633\u0631\u06cc \u06a9\u0631\u0627\u06cc\u0645"
    ],
    "qs:gn_adm0_cc":"IN",
    "qs:gn_local":1254163,
    "qs:gn_nam_loc":"Thiruvananthapuram, Thiruvananthapuram, Kerala, IN",
    "qs:gn_namadm1":"13",
    "qs:local_max":394,
    "qs:local_sum":1454,
    "qs:localhoods":15,
    "qs:name":"Sree Karayam",
    "qs:name_adm0":"India",
    "qs:name_adm1":"Kerala",
    "qs:name_adm2":"Thiruvananthapuram",
    "qs:name_local":"Thiruvananthapuram",
    "qs:photo_max":5,
    "qs:photo_sum":6,
    "qs:placetype":"Suburb",
    "qs:quad_count":2,
    "qs:woe_adm0":23424848,
    "qs:woe_adm1":2345747,
    "qs:woe_adm2":12586476,
    "qs:woe_lau":0,
    "qs:woe_local":2295426,
    "qs:woe_ver":"7.10.0",
    "wof:lang":[
        "eng"
    ],
    "wof:name":"Sree Karayam",
    "wof:placetype":"neighbourhood"
},
  "geometry": {"coordinates":[76.922607,8.540281],"type":"Point"}
}