{
  "type": "Feature",
  "properties": {
    "iso:country":"IN",
    "ks:ks_name":"Holdicharra",
    "ks:ks_pop":540,
    "ks:ks_type":"HABITATION",
    "name:eng_x_preferred":[
        "Holdicharra"
    ],
    "wof:name":"Holdicharra",
    "wof:placetype":"locality",
    "wof:population":540
},
  "geometry": {"coordinates":[92.113327,24.248129],"type":"Point"}
}