{
  "type": "Feature",
  "properties": {
    "gn:admin1_code":"35",
    "gn:admin2_code":"428.0",
    "gn:asciiname":"Kakra",
    "gn:country_code":"IN",
    "gn:dem":349,
    "gn:feature_class":"P",
    "gn:feature_code":"PPL",
    "gn:name":"Kakra",
    "gn:population":0,
    "gn:timezone":"Asia/Kolkata",
    "iso:country":"IN",
    "name:fas_x_preferred":[
        "\u06a9\u06a9\u0631\u0627"
    ],
    "wof:name":"Kakra",
    "wof:placetype":"locality"
},
  "geometry": {"coordinates":[79.39941,23.9377],"type":"Point"}
}