{
  "type": "Feature",
  "properties": {
    "iso:country":"IN",
    "ks:ks_alt_nam":"khadila",
    "ks:ks_name":"Khadila",
    "ks:ks_pop":557,
    "ks:ks_type":"HABITATION",
    "name:eng_x_preferred":[
        "Khadila"
    ],
    "wof:name":"Khadila",
    "wof:placetype":"locality",
    "wof:population":557
},
  "geometry": {"coordinates":[84.12487299999999,25.854996],"type":"Point"}
}