{
  "type": "Feature",
  "properties": {
    "gn:admin1_code":"19.0",
    "gn:admin2_code":"568.0",
    "gn:asciiname":"Mallapura",
    "gn:country_code":"IN",
    "gn:dem":582,
    "gn:feature_class":"P",
    "gn:feature_code":"PPL",
    "gn:name":"Mall\u0101pura",
    "gn:population":0,
    "gn:timezone":"Asia/Kolkata",
    "iso:country":"IN",
    "ks:ks_alt_nam":"Mall\u0101pura",
    "ks:ks_name":"Mallapura",
    "ks:ks_pop":1151,
    "ks:ks_type":"VILLAGE",
    "ks:ks_uagg_main":0,
    "name:eng_x_preferred":[
        "Mallapura"
    ],
    "name:eng_x_variant":[
        "Mall\u0101pura"
    ],
    "wof:name":"Mallapura",
    "wof:placetype":"neighbourhood",
    "wof:population":1151
},
  "geometry": {"coordinates":[75.741484,14.033919],"type":"Point"}
}