{
  "type": "Feature",
  "properties": {
    "iso:country":"IN",
    "ks:ks_name":"Karawand Wadi",
    "ks:ks_pop":88,
    "ks:ks_type":"HABITATION",
    "name:eng_x_preferred":[
        "Karawand Wadi"
    ],
    "wof:name":"Karawand Wadi",
    "wof:placetype":"locality",
    "wof:population":88
},
  "geometry": {"coordinates":[75.804097,18.604845],"type":"Point"}
}