{
  "type": "Feature",
  "properties": {
    "iso:country":"IN",
    "ks:ks_name":"Pipalsahi",
    "ks:ks_pop":139,
    "ks:ks_type":"VILLAGE",
    "name:eng_x_preferred":[
        "Pipalsahi"
    ],
    "wof:name":"Pipalsahi",
    "wof:placetype":"locality",
    "wof:population":139
},
  "geometry": {"coordinates":[84.367142,20.407897],"type":"Point"}
}