{
  "type": "Feature",
  "properties": {
    "iso:country":"IN",
    "ks:ks_name":"Malik Para",
    "ks:ks_pop":514,
    "ks:ks_type":"HABITATION",
    "name:eng_x_preferred":[
        "Malik Para"
    ],
    "wof:name":"Malik Para",
    "wof:placetype":"locality",
    "wof:population":514
},
  "geometry": {"coordinates":[88.227819,22.379589],"type":"Point"}
}