{
  "type": "Feature",
  "properties": {
    "gn:admin1_code":"21",
    "gn:admin2_code":"396.0",
    "gn:asciiname":"Tuaguda",
    "gn:country_code":"IN",
    "gn:dem":489,
    "gn:feature_class":"P",
    "gn:feature_code":"PPL",
    "gn:name":"Tu\u0101guda",
    "gn:population":0,
    "gn:timezone":"Asia/Kolkata",
    "iso:country":"IN",
    "wof:name":"Tuaguda",
    "wof:placetype":"locality"
},
  "geometry": {"coordinates":[83.59815,19.78929],"type":"Point"}
}