{
  "type": "Feature",
  "properties": {
    "iso:country":"IN",
    "ks:ks_name":"Sarpanchpara",
    "ks:ks_pop":249,
    "ks:ks_type":"HABITATION",
    "name:eng_x_preferred":[
        "Sarpanchpara"
    ],
    "wof:name":"Sarpanchpara",
    "wof:placetype":"locality",
    "wof:population":249
},
  "geometry": {"coordinates":[81.31208700000001,18.625175],"type":"Point"}
}