{
  "type": "Feature",
  "properties": {
    "iso:country":"IN",
    "ks:ks_name":"Chintaluru",
    "ks:ks_pop":73,
    "ks:ks_type":"HABITATION",
    "name:eng_x_preferred":[
        "Chintaluru"
    ],
    "wof:name":"Chintaluru",
    "wof:placetype":"locality",
    "wof:population":73
},
  "geometry": {"coordinates":[82.59226099999999,17.919016],"type":"Point"}
}