{
  "type": "Feature",
  "properties": {
    "iso:country":"IN",
    "ks:ks_name":"Cheruvalpadi",
    "ks:ks_pop":575,
    "ks:ks_type":"HABITATION",
    "name:eng_x_preferred":[
        "Cheruvalpadi"
    ],
    "wof:name":"Cheruvalpadi",
    "wof:placetype":"locality",
    "wof:population":575
},
  "geometry": {"coordinates":[76.776265,9.120704],"type":"Point"}
}