{
  "type": "Feature",
  "properties": {
    "gn:admin1_code":"28.0",
    "gn:admin2_code":"345",
    "gn:asciiname":"Balughata",
    "gn:country_code":"IN",
    "gn:dem":10,
    "gn:feature_class":"P",
    "gn:feature_code":"PPL",
    "gn:name":"B\u0101lugh\u0101ta",
    "gn:population":0,
    "gn:timezone":"Asia/Kolkata",
    "iso:country":"IN",
    "ks:ks_alt_nam":"B\u0101lugh\u0101ta",
    "ks:ks_name":"Balughata",
    "ks:ks_type":"VILLAGE",
    "name:eng_x_preferred":[
        "Balughata"
    ],
    "name:eng_x_variant":[
        "B\u0101lugh\u0101ta"
    ],
    "wof:name":"Balughata",
    "wof:placetype":"locality"
},
  "geometry": {"coordinates":[88.03185000000001,22.073098],"type":"Point"}
}