{
  "type": "Feature",
  "properties": {
    "iso:country":"IN",
    "ks:ks_name":"Karanje Turf Parali",
    "ks:ks_pop":568,
    "ks:ks_type":"HABITATION",
    "name:eng_x_preferred":[
        "Karanje Turf Parali"
    ],
    "wof:name":"Karanje Turf Parali",
    "wof:placetype":"locality",
    "wof:population":568
},
  "geometry": {"coordinates":[73.917925,17.684653],"type":"Point"}
}