{
  "type": "Feature",
  "properties": {
    "gn:admin1_code":"19.0",
    "gn:admin2_code":"563.0",
    "gn:asciiname":"Kemmanjaddi",
    "gn:country_code":"IN",
    "gn:dem":533,
    "gn:feature_class":"P",
    "gn:feature_code":"PPL",
    "gn:name":"Kemmanjaddi",
    "gn:population":0,
    "gn:timezone":"Asia/Kolkata",
    "iso:country":"IN",
    "ks:ks_name":"Kammanjeddi",
    "ks:ks_pop":20,
    "ks:ks_type":"HABITATION",
    "name:eng_x_preferred":[
        "Kammanjeddi"
    ],
    "name:eng_x_variant":[
        "Kemmanjaddi"
    ],
    "wof:name":"Kammanjeddi",
    "wof:placetype":"locality",
    "wof:population":20
},
  "geometry": {"coordinates":[74.71470100000001,14.905908],"type":"Point"}
}