{
  "type": "Feature",
  "properties": {
    "gn:admin1_code":"2.0",
    "gn:admin2_code":"543.0",
    "gn:asciiname":"Ravivalasa",
    "gn:country_code":"IN",
    "gn:dem":131,
    "gn:feature_class":"P",
    "gn:feature_code":"PPL",
    "gn:name":"R\u0101vivalasa",
    "gn:population":0,
    "gn:timezone":"Asia/Kolkata",
    "iso:country":"IN",
    "ks:ks_name":"Ravivalasa",
    "ks:ks_pop":587,
    "ks:ks_type":"HABITATION",
    "name:eng_x_preferred":[
        "Ravivalasa"
    ],
    "name:tel_x_preferred":[
        "\u0c30\u0c3e\u0c35\u0c3f\u0c35\u0c32\u0c38"
    ],
    "wof:name":"Ravivalasa",
    "wof:placetype":"locality",
    "wof:population":587
},
  "geometry": {"coordinates":[83.414849,18.496955],"type":"Point"}
}