{
  "type": "Feature",
  "properties": {
    "iso:country":"IN",
    "ks:ks_name":"Botiakuva",
    "ks:ks_pop":173,
    "ks:ks_type":"HABITATION",
    "name:eng_x_preferred":[
        "Botiakuva"
    ],
    "wof:name":"Botiakuva",
    "wof:placetype":"locality",
    "wof:population":173
},
  "geometry": {"coordinates":[73.783264,21.985021],"type":"Point"}
}