{
  "type": "Feature",
  "properties": {
    "iso:country":"IN",
    "ks:ks_name":"Padipeta",
    "ks:ks_pop":31,
    "ks:ks_type":"HABITATION",
    "name:eng_x_preferred":[
        "Padipeta"
    ],
    "wof:name":"Padipeta",
    "wof:placetype":"locality",
    "wof:population":31
},
  "geometry": {"coordinates":[83.241708,18.202057],"type":"Point"}
}