{
  "type": "Feature",
  "properties": {
    "iso:country":"IN",
    "ks:ks_alt_nam":"Mukti Palli and satya Palli",
    "ks:ks_name":"Mukti Palli And Satya Palli",
    "ks:ks_pop":1785,
    "ks:ks_type":"HABITATION",
    "name:eng_x_preferred":[
        "Mukti Palli And Satya Palli"
    ],
    "wof:name":"Mukti Palli And Satya Palli",
    "wof:placetype":"locality",
    "wof:population":1785
},
  "geometry": {"coordinates":[88.197247,21.701552],"type":"Point"}
}