{
  "type": "Feature",
  "properties": {
    "gn:admin1_code":"23.0",
    "gn:admin2_code":"038",
    "gn:asciiname":"Badla",
    "gn:country_code":"IN",
    "gn:dem":389,
    "gn:feature_class":"P",
    "gn:feature_code":"PPL",
    "gn:name":"Badla",
    "gn:population":0,
    "gn:timezone":"Asia/Kolkata",
    "iso:country":"IN",
    "name:und_x_variant":[
        "Badia",
        "Badla"
    ],
    "wof:name":"Badla",
    "wof:placetype":"locality"
},
  "geometry": {"coordinates":[75.77321999999999,31.88645],"type":"Point"}
}