{
  "type": "Feature",
  "properties": {
    "iso:country":"IN",
    "ks:ks_alt_nam":"bringa toli",
    "ks:ks_name":"Bringa Toli",
    "ks:ks_pop":358,
    "ks:ks_type":"HABITATION",
    "name:eng_x_preferred":[
        "Bringa Toli"
    ],
    "wof:name":"Bringa Toli",
    "wof:placetype":"locality",
    "wof:population":358
},
  "geometry": {"coordinates":[84.49047299999999,22.565121],"type":"Point"}
}