{
  "type": "Feature",
  "properties": {
    "gn:admin1_code":"36.0",
    "gn:admin2_code":"136.0",
    "gn:asciiname":"Kankati",
    "gn:country_code":"IN",
    "gn:dem":185,
    "gn:feature_class":"P",
    "gn:feature_code":"PPL",
    "gn:name":"Kankati",
    "gn:population":0,
    "gn:timezone":"Asia/Kolkata",
    "iso:country":"IN",
    "name:und_x_variant":[
        "Kanakpuri"
    ],
    "wof:name":"Kankati",
    "wof:placetype":"neighbourhood"
},
  "geometry": {"coordinates":[79.35221,28.7421],"type":"Point"}
}