{
  "type": "Feature",
  "properties": {
    "iso:country":"IN",
    "ks:ks_name":"Budhawadi",
    "ks:ks_pop":21,
    "ks:ks_type":"HABITATION",
    "name:eng_x_preferred":[
        "Budhawadi"
    ],
    "wof:name":"Budhawadi",
    "wof:placetype":"locality",
    "wof:population":21
},
  "geometry": {"coordinates":[73.342114,18.088044],"type":"Point"}
}