{
  "type": "Feature",
  "properties": {
    "iso:country":"IN",
    "ks:ks_name":"Kukkiliyankadu",
    "ks:ks_pop":25,
    "ks:ks_type":"HABITATION",
    "name:eng_x_preferred":[
        "Kukkiliyankadu"
    ],
    "wof:name":"Kukkiliyankadu",
    "wof:placetype":"locality",
    "wof:population":25
},
  "geometry": {"coordinates":[77.724688,11.674992],"type":"Point"}
}