{
  "type": "Feature",
  "properties": {
    "gn:admin1_code":"24.0",
    "gn:admin2_code":"117.0",
    "gn:asciiname":"Lilara",
    "gn:country_code":"IN",
    "gn:dem":266,
    "gn:feature_class":"P",
    "gn:feature_code":"PPL",
    "gn:name":"Lilara",
    "gn:population":0,
    "gn:timezone":"Asia/Kolkata",
    "iso:country":"IN",
    "wof:name":"Lilara",
    "wof:placetype":"neighbourhood"
},
  "geometry": {"coordinates":[72.60062000000001,24.58719],"type":"Point"}
}