{
  "type": "Feature",
  "properties": {
    "iso:country":"IN",
    "ks:ks_name":"Kasam",
    "ks:ks_pop":301,
    "ks:ks_type":"HABITATION",
    "name:eng_x_preferred":[
        "Kasam"
    ],
    "wof:name":"Kasam",
    "wof:placetype":"locality",
    "wof:population":301
},
  "geometry": {"coordinates":[79.16674500000001,13.003714],"type":"Point"}
}