{
  "type": "Feature",
  "properties": {
    "gn:admin1_code":"40.0",
    "gn:admin2_code":"533.0",
    "gn:asciiname":"Datapuram",
    "gn:country_code":"IN",
    "gn:dem":351,
    "gn:feature_class":"P",
    "gn:feature_code":"PPL",
    "gn:name":"Dat\u0101puram",
    "gn:population":0,
    "gn:timezone":"Asia/Kolkata",
    "iso:country":"IN",
    "wof:name":"Datapuram",
    "wof:placetype":"locality"
},
  "geometry": {"coordinates":[78.19134,18.90564],"type":"Point"}
}