{
  "type": "Feature",
  "properties": {
    "gn:admin1_code":"36",
    "gn:admin2_code":"179.0",
    "gn:asciiname":"Khetal",
    "gn:country_code":"IN",
    "gn:dem":109,
    "gn:feature_class":"P",
    "gn:feature_code":"PPL",
    "gn:name":"Khetal",
    "gn:population":0,
    "gn:timezone":"Asia/Kolkata",
    "iso:country":"IN",
    "wof:name":"Khetal",
    "wof:placetype":"locality"
},
  "geometry": {"coordinates":[81.65446999999998,26.16504],"type":"Point"}
}