{
  "type": "Feature",
  "properties": {
    "iso:country":"IN",
    "ks:ks_name":"Hatya Tanr",
    "ks:ks_pop":247,
    "ks:ks_type":"HABITATION",
    "name:eng_x_preferred":[
        "Hatya Tanr"
    ],
    "wof:name":"Hatya Tanr",
    "wof:placetype":"locality",
    "wof:population":247
},
  "geometry": {"coordinates":[86.265992,23.952656],"type":"Point"}
}