{
  "type": "Feature",
  "properties": {
    "iso:country":"IN",
    "ks:ks_alt_nam":"NAGLA KHUSHRUPUR",
    "ks:ks_name":"Nagla Khushrupur",
    "ks:ks_pop":170,
    "ks:ks_type":"HABITATION",
    "ks:ks_uagg_main":0,
    "name:eng_x_preferred":[
        "Nagla Khushrupur"
    ],
    "wof:name":"Nagla Khushrupur",
    "wof:placetype":"neighbourhood",
    "wof:population":170
},
  "geometry": {"coordinates":[79.329981,26.824089],"type":"Point"}
}