{
  "type": "Feature",
  "properties": {
    "iso:country":"IN",
    "ks:ks_name":"Nandamahapatrabedha",
    "ks:ks_pop":19,
    "ks:ks_type":"VILLAGE",
    "ks:ks_uagg_main":0,
    "name:eng_x_preferred":[
        "Nandamahapatrabedha"
    ],
    "wof:name":"Nandamahapatrabedha",
    "wof:placetype":"neighbourhood",
    "wof:population":19
},
  "geometry": {"coordinates":[86.778339,21.433738],"type":"Point"}
}