{
  "type": "Feature",
  "properties": {
    "iso:country":"IN",
    "ks:ks_name":"Pothur",
    "ks:ks_pop":343,
    "ks:ks_type":"VILLAGE",
    "ks:ks_uagg_main":0,
    "name:eng_x_preferred":[
        "Pothur"
    ],
    "wof:name":"Pothur",
    "wof:placetype":"locality",
    "wof:population":343
},
  "geometry": {"coordinates":[80.15563299999999,13.157897],"type":"Point"}
}