{
  "type": "Feature",
  "properties": {
    "iso:country":"IN",
    "ks:ks_name":"Deuli",
    "ks:ks_pop":6021,
    "ks:ks_type":"VILLAGE",
    "ks:ks_uagg_main":0,
    "name:eng_x_preferred":[
        "Deuli"
    ],
    "wof:name":"Deuli",
    "wof:placetype":"neighbourhood",
    "wof:population":6021
},
  "geometry": {"coordinates":[87.974406,22.277601],"type":"Point"}
}