{
  "type": "Feature",
  "properties": {
    "iso:country":"IN",
    "ks:ks_name":"Jalalpur Bangri",
    "ks:ks_pop":1597,
    "ks:ks_type":"VILLAGE",
    "ks:ks_uagg_main":0,
    "name:eng_x_preferred":[
        "Jalalpur Bangri"
    ],
    "wof:name":"Jalalpur Bangri",
    "wof:placetype":"neighbourhood",
    "wof:population":1597
},
  "geometry": {"coordinates":[85.73790200000001,26.478544],"type":"Point"}
}