{
  "type": "Feature",
  "properties": {
    "iso:country":"IN",
    "ks:ks_name":"V Mettur",
    "ks:ks_pop":385,
    "ks:ks_type":"HABITATION",
    "ks:ks_uagg_main":0,
    "name:eng_x_preferred":[
        "V Mettur"
    ],
    "wof:name":"V Mettur",
    "wof:placetype":"neighbourhood",
    "wof:population":385
},
  "geometry": {"coordinates":[77.217595,10.908002],"type":"Point"}
}