{
  "type": "Feature",
  "properties": {
    "iso:country":"IN",
    "ks:ks_name":"Kankartala",
    "ks:ks_pop":3267,
    "ks:ks_type":"VILLAGE",
    "ks:ks_uagg_main":0,
    "name:eng_x_preferred":[
        "Kankartala"
    ],
    "wof:name":"Kankartala",
    "wof:placetype":"neighbourhood",
    "wof:population":3267
},
  "geometry": {"coordinates":[87.210151,23.786845],"type":"Point"}
}