{
  "type": "Feature",
  "properties": {
    "iso:country":"IN",
    "ks:ks_name":"Konwar Dhadumia Gaon",
    "ks:ks_pop":511,
    "ks:ks_type":"HABITATION",
    "name:eng_x_preferred":[
        "Konwar Dhadumia Gaon"
    ],
    "wof:name":"Konwar Dhadumia Gaon",
    "wof:placetype":"locality",
    "wof:population":511
},
  "geometry": {"coordinates":[94.64465300000001,26.823425],"type":"Point"}
}