{
  "type": "Feature",
  "properties": {
    "gn:admin1_code":"35",
    "gn:admin2_code":"426.0",
    "gn:asciiname":"Birampura",
    "gn:country_code":"IN",
    "gn:dem":428,
    "gn:feature_class":"P",
    "gn:feature_code":"PPL",
    "gn:name":"B\u012brampura",
    "gn:population":0,
    "gn:timezone":"Asia/Kolkata",
    "iso:country":"IN",
    "ks:ks_alt_nam":"B\u012brampura",
    "ks:ks_name":"Birampura",
    "ks:ks_pop":710,
    "ks:ks_type":"VILLAGE",
    "name:eng_x_preferred":[
        "Birampura"
    ],
    "name:eng_x_variant":[
        "B\u012brampura"
    ],
    "wof:name":"Birampura",
    "wof:placetype":"locality",
    "wof:population":710
},
  "geometry": {"coordinates":[79.942672,24.055662],"type":"Point"}
}