{
  "type": "Feature",
  "properties": {
    "gn:admin1_code":"36",
    "gn:admin2_code":"178.0",
    "gn:asciiname":"Jallapur",
    "gn:country_code":"IN",
    "gn:dem":91,
    "gn:feature_class":"P",
    "gn:feature_code":"PPL",
    "gn:name":"Jall\u0101pur",
    "gn:population":0,
    "gn:timezone":"Asia/Kolkata",
    "iso:country":"IN",
    "name:tel_x_preferred":[
        "\u0c1c\u0c32\u0c4d\u0c32\u0c3e\u0c2a\u0c42\u0c30\u0c4d"
    ],
    "wof:name":"Jallapur",
    "wof:placetype":"locality"
},
  "geometry": {"coordinates":[82.8463,26.43257],"type":"Point"}
}