{
  "type": "Feature",
  "properties": {
    "iso:country":"IN",
    "ks:ks_name":"Kismatdwarika",
    "ks:ks_pop":1353,
    "ks:ks_type":"VILLAGE",
    "ks:ks_uagg_main":0,
    "name:eng_x_preferred":[
        "Kismatdwarika"
    ],
    "wof:name":"Kismatdwarika",
    "wof:placetype":"neighbourhood",
    "wof:population":1353
},
  "geometry": {"coordinates":[90.810485,26.489824],"type":"Point"}
}