{
  "type": "Feature",
  "properties": {
    "iso:country":"IN",
    "ks:ks_name":"Renja",
    "ks:ks_pop":60,
    "ks:ks_type":"HABITATION",
    "name:eng_x_preferred":[
        "Renja"
    ],
    "wof:name":"Renja",
    "wof:placetype":"locality",
    "wof:population":60
},
  "geometry": {"coordinates":[74.991321,13.294927],"type":"Point"}
}