{
  "type": "Feature",
  "properties": {
    "gn:admin1_code":"19.0",
    "gn:admin2_code":"568.0",
    "gn:asciiname":"Hire Telgadde",
    "gn:country_code":"IN",
    "gn:dem":572,
    "gn:feature_class":"P",
    "gn:feature_code":"PPL",
    "gn:name":"Hire Telgadde",
    "gn:population":0,
    "gn:timezone":"Asia/Kolkata",
    "iso:country":"IN",
    "wof:name":"Hire Telgadde",
    "wof:placetype":"neighbourhood"
},
  "geometry": {"coordinates":[75.08938000000001,14.62326],"type":"Point"}
}