{
  "type": "Feature",
  "properties": {
    "iso:country":"IN",
    "ks:ks_alt_nam":"BHITARIYAPARA",
    "ks:ks_name":"Bhitariyapara",
    "ks:ks_pop":213,
    "ks:ks_type":"HABITATION",
    "name:eng_x_preferred":[
        "Bhitariyapara"
    ],
    "wof:name":"Bhitariyapara",
    "wof:placetype":"locality",
    "wof:population":213
},
  "geometry": {"coordinates":[81.836646,22.746876],"type":"Point"}
}