{
  "type": "Feature",
  "properties": {
    "iso:country":"IN",
    "ks:ks_name":"Pipalguda",
    "ks:ks_pop":39,
    "ks:ks_type":"HABITATION",
    "name:eng_x_preferred":[
        "Pipalguda"
    ],
    "wof:name":"Pipalguda",
    "wof:placetype":"locality",
    "wof:population":39
},
  "geometry": {"coordinates":[82.79218400000001,19.210485],"type":"Point"}
}