{
  "type": "Feature",
  "properties": {
    "iso:country":"IN",
    "ks:ks_alt_nam":"Turi tola",
    "ks:ks_name":"Turi Tola",
    "ks:ks_pop":328,
    "ks:ks_type":"HABITATION",
    "name:eng_x_preferred":[
        "Turi Tola"
    ],
    "wof:name":"Turi Tola",
    "wof:placetype":"locality",
    "wof:population":328
},
  "geometry": {"coordinates":[86.747739,24.77921],"type":"Point"}
}