{
  "type": "Feature",
  "properties": {
    "iso:country":"IN",
    "ks:ks_name":"Balibil",
    "ks:ks_pop":1774,
    "ks:ks_type":"VILLAGE",
    "ks:ks_uagg_main":0,
    "name:eng_x_preferred":[
        "Balibil"
    ],
    "wof:name":"Balibil",
    "wof:placetype":"neighbourhood",
    "wof:population":1774
},
  "geometry": {"coordinates":[87.243717,21.564828],"type":"Point"}
}