{
  "type": "Feature",
  "properties": {
    "iso:country":"IN",
    "ks:ks_name":"Pannottu",
    "ks:ks_pop":302,
    "ks:ks_type":"HABITATION",
    "name:eng_x_preferred":[
        "Pannottu"
    ],
    "wof:name":"Pannottu",
    "wof:placetype":"locality",
    "wof:population":302
},
  "geometry": {"coordinates":[75.273235,12.813534],"type":"Point"}
}