{
  "type": "Feature",
  "properties": {
    "gn:admin1_code":"2",
    "gn:admin2_code":"545.0",
    "gn:asciiname":"Vanamamidigundi",
    "gn:country_code":"IN",
    "gn:dem":341,
    "gn:feature_class":"P",
    "gn:feature_code":"PPL",
    "gn:name":"Vanam\u0101midigundi",
    "gn:population":0,
    "gn:timezone":"Asia/Kolkata",
    "iso:country":"IN",
    "ks:ks_name":"Vanamamidigondi",
    "ks:ks_pop":154,
    "ks:ks_type":"HABITATION",
    "name:eng_x_preferred":[
        "Vanamamidigondi"
    ],
    "name:eng_x_variant":[
        "Vanamamidigundi"
    ],
    "wof:name":"Vanamamidigondi",
    "wof:placetype":"locality",
    "wof:population":154
},
  "geometry": {"coordinates":[81.94749899999999,17.635203],"type":"Point"}
}