{
  "type": "Feature",
  "properties": {
    "iso:country":"IN",
    "ks:ks_name":"Thuppuru",
    "ks:ks_pop":782,
    "ks:ks_type":"VILLAGE",
    "name:eng_x_preferred":[
        "Thuppuru"
    ],
    "wof:name":"Thuppuru",
    "wof:placetype":"locality",
    "wof:population":782
},
  "geometry": {"coordinates":[75.308302,14.095744],"type":"Point"}
}