{
  "type": "Feature",
  "properties": {
    "gn:country":"IN",
    "gn:fcode":"PPL",
    "gn:pop":0,
    "iso:country":"IN",
    "name:eng_x_preferred":[
        "Melapalayam"
    ],
    "name:nld_x_preferred":[
        "Melapalayam"
    ],
    "name:unk_x_variant":[
        "Mel P\u0101laiyam"
    ],
    "qs:name":"Melappalaiyam",
    "qs:name_adm0":"India",
    "qs:name_adm1":"Tamil Nadu",
    "qs:photos":4,
    "qs:photos_1k":1,
    "qs:photos_9k":1,
    "qs:photos_9r":1,
    "qs:photos_all":4,
    "qs:photos_sr":1,
    "qs:placetype":"Town",
    "qs:pop_sr":"0",
    "wof:name":"Melappalaiyam",
    "wof:placetype":"locality",
    "wof:population":0
},
  "geometry": {"coordinates":[77.70656,8.70075],"type":"Point"}
}