{
  "type": "Feature",
  "properties": {
    "gn:country":"IN",
    "gn:fcode":"PPL",
    "gn:population":0,
    "iso:country":"IN",
    "name:ast_x_preferred":[
        "Melapalayam"
    ],
    "name:azb_x_preferred":[
        "\u0645\u0644\u0627\u067e\u0627\u0644\u0627\u06cc\u0627\u0645"
    ],
    "name:cym_x_preferred":[
        "Melapalayam"
    ],
    "name:eng_x_preferred":[
        "Melapalayam"
    ],
    "name:fas_x_preferred":[
        "\u0645\u0627\u0644\u0627\u067e\u0627\u0644\u0627\u06cc\u0645"
    ],
    "name:nld_x_preferred":[
        "Melapalayam"
    ],
    "name:tam_x_preferred":[
        "\u0bae\u0bc7\u0bb2\u0baa\u0bcd\u0baa\u0bbe\u0bb3\u0bc8\u0baf\u0bae\u0bcd"
    ],
    "name:und_x_variant":[
        "Mel P\u0101laiyam"
    ],
    "qs:name":"Melappalaiyam",
    "qs:name_adm0":"India",
    "qs:name_adm1":"Tamil Nadu",
    "qs:photos":4,
    "qs:photos_1k":1,
    "qs:photos_9k":1,
    "qs:photos_9r":1,
    "qs:photos_all":4,
    "qs:photos_sr":1,
    "qs:placetype":"Town",
    "qs:pop_sr":"0",
    "wof:name":"Melappalaiyam",
    "wof:placetype":"locality",
    "wof:population":0
},
  "geometry": {"coordinates":[77.70656,8.70075],"type":"Point"}
}