{
  "type": "Feature",
  "properties": {
    "gn:admin1_code":"35.0",
    "gn:admin2_code":"455.0",
    "gn:asciiname":"Kondadhana",
    "gn:country_code":"IN",
    "gn:dem":553,
    "gn:feature_class":"P",
    "gn:feature_code":"PPL",
    "gn:name":"Kond\u0101dh\u0101na",
    "gn:population":0,
    "gn:timezone":"Asia/Kolkata",
    "iso:country":"IN",
    "ks:ks_alt_nam":"Kond\u0101dh\u0101na",
    "ks:ks_name":"Kondadhana",
    "ks:ks_type":"VILLAGE",
    "name:eng_x_preferred":[
        "Kondadhana"
    ],
    "name:eng_x_variant":[
        "Kond\u0101dh\u0101na"
    ],
    "wof:name":"Kondadhana",
    "wof:placetype":"locality"
},
  "geometry": {"coordinates":[78.600677,22.553193],"type":"Point"}
}