{
  "type": "Feature",
  "properties": {
    "iso:country":"IN",
    "ks:ks_alt_nam":"DHARI RAYYAT",
    "ks:ks_name":"Dhari Rayyat",
    "ks:ks_pop":130,
    "ks:ks_type":"HABITATION",
    "name:eng_x_preferred":[
        "Dhari Rayyat"
    ],
    "wof:name":"Dhari Rayyat",
    "wof:placetype":"locality",
    "wof:population":130
},
  "geometry": {"coordinates":[77.548598,21.98068],"type":"Point"}
}