{
  "type": "Feature",
  "properties": {
    "iso:country":"IN",
    "ks:ks_name":"Charno Ki Dhani",
    "ks:ks_pop":65,
    "ks:ks_type":"HABITATION",
    "name:eng_x_preferred":[
        "Charno Ki Dhani"
    ],
    "wof:name":"Charno Ki Dhani",
    "wof:placetype":"locality",
    "wof:population":65
},
  "geometry": {"coordinates":[75.088106,27.374653],"type":"Point"}
}