{
  "type": "Feature",
  "properties": {
    "iso:country":"IN",
    "ks:ks_name":"Belgaria",
    "ks:ks_pop":3744,
    "ks:ks_type":"VILLAGE",
    "name:eng_x_preferred":[
        "Belgaria"
    ],
    "wof:name":"Belgaria",
    "wof:placetype":"neighbourhood",
    "wof:population":3744
},
  "geometry": {"coordinates":[86.476387,23.754289],"type":"Point"}
}