{
  "type": "Feature",
  "properties": {
    "gn:admin1_code":"34.0",
    "gn:admin2_code":"217.0",
    "gn:asciiname":"Mathia",
    "gn:country_code":"IN",
    "gn:dem":75,
    "gn:feature_class":"P",
    "gn:feature_code":"PPL",
    "gn:name":"Mathia",
    "gn:population":0,
    "gn:timezone":"Asia/Kolkata",
    "iso:country":"IN",
    "wof:name":"Mathia",
    "wof:placetype":"locality"
},
  "geometry": {"coordinates":[84.01476,26.48215],"type":"Point"}
}