{
  "type": "Feature",
  "properties": {
    "iso:country":"IN",
    "ks:ks_name":"Baudhwadi",
    "ks:ks_pop":229,
    "ks:ks_type":"HABITATION",
    "name:eng_x_preferred":[
        "Baudhwadi"
    ],
    "wof:name":"Baudhwadi",
    "wof:placetype":"locality",
    "wof:population":229
},
  "geometry": {"coordinates":[73.304394,17.818725],"type":"Point"}
}