{
  "type": "Feature",
  "properties": {
    "iso:country":"IN",
    "ks:ks_name":"Dinapalasa",
    "ks:ks_pop":30,
    "ks:ks_type":"VILLAGE",
    "name:eng_x_preferred":[
        "Dinapalasa"
    ],
    "wof:name":"Dinapalasa",
    "wof:placetype":"locality",
    "wof:population":30
},
  "geometry": {"coordinates":[86.76220600000001,21.620996],"type":"Point"}
}