{
  "type": "Feature",
  "properties": {
    "gn:gn_country":"IN",
    "gn:gn_fcode":"PPL",
    "gn:gn_pop":13715,
    "gn:population":13715,
    "iso:country":"IN",
    "name:ara_x_preferred":[
        "\u0641\u0627\u0646\u062f\u0627\u0644\u0648\u0631"
    ],
    "name:bpy_x_preferred":[
        "\u09ac\u09be\u09a8\u09cd\u09a6\u09be\u09b2\u09c1\u09b0"
    ],
    "name:eng_x_preferred":[
        "Vandalur"
    ],
    "name:fas_x_preferred":[
        "\u0648\u0646\u062f\u0644\u0648\u0631"
    ],
    "name:ita_x_preferred":[
        "Vandalur"
    ],
    "name:mlg_x_preferred":[
        "Vandalur"
    ],
    "name:msa_x_preferred":[
        "Vandalur"
    ],
    "name:new_x_preferred":[
        "\u0935\u0928\u094d\u0926\u0932\u0941\u0930"
    ],
    "name:nld_x_preferred":[
        "Vandalur"
    ],
    "name:por_x_preferred":[
        "Vandalur"
    ],
    "name:tam_x_preferred":[
        "\u0bb5\u0ba3\u0bcd\u0b9f\u0bb2\u0bc2\u0bb0\u0bcd"
    ],
    "name:und_x_preferred":[
        "Vandal\u016br"
    ],
    "name:unk_x_variant":[
        "Vandalur",
        "Vandal\u016br"
    ],
    "name:vie_x_preferred":[
        "Vandalur"
    ],
    "name:zho_min_nan_x_preferred":[
        "Vandalur"
    ],
    "name:zho_x_preferred":[
        "\u4e07\u8fbe\u5362\u5c14"
    ],
    "qs:gn_adm0_cc":"IN",
    "qs:gn_fcode":"PPL",
    "qs:gn_local":1268159,
    "qs:gn_nam_loc":"Kancheepuram, Kanchipuram, Tamil Nadu, IN",
    "qs:gn_namadm1":"25",
    "qs:gn_name":"Vandal\u016br",
    "qs:local_max":274,
    "qs:local_sum":2276,
    "qs:localhoods":28,
    "qs:name":"Vandalur",
    "qs:name_adm0":"India",
    "qs:name_adm1":"Tamil Nadu",
    "qs:name_adm2":"Kancheepuram",
    "qs:name_local":"Kanchipuram",
    "qs:photo_max":82,
    "qs:photo_sum":274,
    "qs:placetype":"Suburb",
    "qs:quad_count":21,
    "qs:woe_adm0":23424848,
    "qs:woe_adm1":2345758,
    "qs:woe_adm2":12586683,
    "qs:woe_lau":0,
    "qs:woe_local":55924325,
    "qs:woe_ver":"7.10.0",
    "qs_pg:aaroncc":"IN",
    "qs_pg:gn_country":"IN",
    "qs_pg:gn_fcode":"PPL",
    "qs_pg:gn_pop":13715,
    "qs_pg:name":"Vandalur",
    "qs_pg:name_adm0":"India",
    "qs_pg:name_adm1":"Tamil Nadu",
    "qs_pg:photos":270,
    "qs_pg:photos_1k":55,
    "qs_pg:photos_9k":1,
    "qs_pg:photos_9r":4,
    "qs_pg:photos_all":270,
    "qs_pg:photos_sr":5,
    "qs_pg:pop_sr":6,
    "qs_pg:qs_pg_placetype":"neighbourhood",
    "qs_pg:qs_pg_placetype_gp":"Suburb",
    "qs_pg:woe_adm0":23424848,
    "wd:wordcount":948,
    "wof:lang":[
        "eng"
    ],
    "wof:name":"Vandalur",
    "wof:placetype":"neighbourhood",
    "wof:population":13715
},
  "geometry": {"coordinates":[80.09295400000001,12.880638],"type":"Point"}
}