{
  "type": "Feature",
  "properties": {
    "gn:admin1_code":"34.0",
    "gn:admin2_code":"229.0",
    "gn:asciiname":"Imli Bigha",
    "gn:country_code":"IN",
    "gn:dem":50,
    "gn:feature_class":"P",
    "gn:feature_code":"PPL",
    "gn:name":"Imli Bigha",
    "gn:population":0,
    "gn:timezone":"Asia/Kolkata",
    "iso:country":"IN",
    "ks:ks_name":"Imli Bigha",
    "ks:ks_pop":386,
    "ks:ks_type":"HABITATION",
    "name:eng_x_preferred":[
        "Imli Bigha"
    ],
    "wof:name":"Imli Bigha",
    "wof:placetype":"locality",
    "wof:population":386
},
  "geometry": {"coordinates":[85.52467900000001,25.300443],"type":"Point"}
}