{
  "type": "Feature",
  "properties": {
    "gn:admin1_code":"12.0",
    "gn:admin2_code":"004",
    "gn:asciiname":"Barche",
    "gn:country_code":"IN",
    "gn:dem":3508,
    "gn:feature_class":"P",
    "gn:feature_code":"PPL",
    "gn:name":"Barche",
    "gn:population":0,
    "gn:timezone":"Asia/Kolkata",
    "iso:country":"IN",
    "wof:name":"Barche",
    "wof:placetype":"locality"
},
  "geometry": {"coordinates":[76.2375,34.575],"type":"Point"}
}