{
  "type": "Feature",
  "properties": {
    "gn:admin1_code":"34.0",
    "gn:admin2_code":"236.0",
    "gn:asciiname":"Paharpur",
    "gn:country_code":"IN",
    "gn:dem":141,
    "gn:feature_class":"P",
    "gn:feature_code":"PPL",
    "gn:name":"Pah\u0101rpur",
    "gn:population":0,
    "gn:timezone":"Asia/Kolkata",
    "iso:country":"IN",
    "ks:ks_alt_nam":"Pah\u0101rpur",
    "ks:ks_name":"Paharpur",
    "ks:ks_type":"VILLAGE",
    "ks:ks_uagg_main":0,
    "name:ben_x_preferred":[
        "\u09aa\u09be\u09b9\u09be\u09a1\u09bc\u09aa\u09c1\u09b0"
    ],
    "name:ceb_x_preferred":[
        "Paharpur"
    ],
    "name:eng_x_preferred":[
        "Paharpur"
    ],
    "name:eng_x_variant":[
        "Pah\u0101rpur"
    ],
    "name:nld_x_preferred":[
        "Paharpur"
    ],
    "wof:name":"Paharpur",
    "wof:placetype":"neighbourhood"
},
  "geometry": {"coordinates":[84.616511,24.629372],"type":"Point"}
}