{
  "type": "Feature",
  "properties": {
    "iso:country":"IN",
    "ks:ks_name":"Veeramsar",
    "ks:ks_pop":711,
    "ks:ks_type":"HABITATION",
    "name:eng_x_preferred":[
        "Veeramsar"
    ],
    "wof:name":"Veeramsar",
    "wof:placetype":"locality",
    "wof:population":711
},
  "geometry": {"coordinates":[72.350578,26.562558],"type":"Point"}
}