{
  "type": "Feature",
  "properties": {
    "iso:country":"IN",
    "ks:ks_name":"Tola Kewalpharaita",
    "ks:ks_pop":2774,
    "ks:ks_type":"VILLAGE",
    "name:eng_x_preferred":[
        "Tola Kewalpharaita"
    ],
    "wof:name":"Tola Kewalpharaita",
    "wof:placetype":"locality",
    "wof:population":2774
},
  "geometry": {"coordinates":[86.248412,24.801387],"type":"Point"}
}