{
  "type": "Feature",
  "properties": {
    "iso:country":"IN",
    "ks:ks_name":"Punaguda",
    "ks:ks_pop":116,
    "ks:ks_type":"HABITATION",
    "name:eng_x_preferred":[
        "Punaguda"
    ],
    "wof:name":"Punaguda",
    "wof:placetype":"locality",
    "wof:population":116
},
  "geometry": {"coordinates":[79.081045,19.30071],"type":"Point"}
}