{
  "type": "Feature",
  "properties": {
    "iso:country":"IN",
    "ks:ks_name":"Rajgurua",
    "ks:ks_pop":444,
    "ks:ks_type":"VILLAGE",
    "name:eng_x_preferred":[
        "Rajgurua"
    ],
    "wof:name":"Rajgurua",
    "wof:placetype":"locality",
    "wof:population":444
},
  "geometry": {"coordinates":[84.792252,24.291324],"type":"Point"}
}