{
  "type": "Feature",
  "properties": {
    "iso:country":"IN",
    "ks:ks_name":"Bandhadiha",
    "ks:ks_pop":3613,
    "ks:ks_type":"VILLAGE",
    "ks:ks_uagg_main":0,
    "name:eng_x_preferred":[
        "Bandhadiha"
    ],
    "wof:name":"Bandhadiha",
    "wof:placetype":"neighbourhood",
    "wof:population":3613
},
  "geometry": {"coordinates":[86.253972,20.716804],"type":"Point"}
}