{
  "type": "Feature",
  "properties": {
    "gn:admin1_code":"34.0",
    "gn:admin2_code":"225.0",
    "gn:asciiname":"Tahirpur",
    "gn:country_code":"IN",
    "gn:dem":52,
    "gn:feature_class":"P",
    "gn:feature_code":"PPL",
    "gn:name":"T\u0101hirpur",
    "gn:population":0,
    "gn:timezone":"Asia/Kolkata",
    "iso:country":"IN",
    "wof:name":"Tahirpur",
    "wof:placetype":"locality"
},
  "geometry": {"coordinates":[87.11664,25.04828],"type":"Point"}
}