{
  "type": "Feature",
  "properties": {
    "gn:admin1_code":"40",
    "gn:admin2_code":"533.0",
    "gn:asciiname":"Rajula",
    "gn:country_code":"IN",
    "gn:dem":381,
    "gn:feature_class":"P",
    "gn:feature_code":"PPL",
    "gn:name":"R\u0101j\u016bla",
    "gn:population":0,
    "gn:timezone":"Asia/Kolkata",
    "iso:country":"IN",
    "name:bpy_x_preferred":[
        "\u09b0\u09be\u099c\u09c1\u09b2\u09be"
    ],
    "name:ceb_x_preferred":[
        "R\u0101jula"
    ],
    "name:guj_x_preferred":[
        "\u0ab0\u0abe\u0a9c\u0ac1\u0ab2\u0abe"
    ],
    "name:hif_x_preferred":[
        "Rajula"
    ],
    "name:ita_x_preferred":[
        "Rajula"
    ],
    "name:msa_x_preferred":[
        "Rajula"
    ],
    "name:ori_x_preferred":[
        "\u0b30\u0b3e\u0b1c\u0b41\u0b32\u0b3e"
    ],
    "name:por_x_preferred":[
        "Rajula"
    ],
    "name:spa_x_preferred":[
        "Rajula"
    ],
    "name:swe_x_preferred":[
        "R\u0101jula"
    ],
    "name:vie_x_preferred":[
        "Rajula"
    ],
    "name:zho_x_preferred":[
        "\u62c9\u4e45\u62c9"
    ],
    "wof:name":"Rajula",
    "wof:placetype":"locality"
},
  "geometry": {"coordinates":[77.68281999999998,18.41561],"type":"Point"}
}