{
  "type": "Feature",
  "properties": {
    "gn:admin1_code":"3.0",
    "gn:admin2_code":"319.0",
    "gn:asciiname":"Dumergur",
    "gn:country_code":"IN",
    "gn:dem":44,
    "gn:feature_class":"P",
    "gn:feature_code":"PPL",
    "gn:name":"Dumergur",
    "gn:population":0,
    "gn:timezone":"Asia/Kolkata",
    "iso:country":"IN",
    "wof:name":"Dumergur",
    "wof:placetype":"locality"
},
  "geometry": {"coordinates":[90.74393000000001,26.32578],"type":"Point"}
}