{
  "type": "Feature",
  "properties": {
    "iso:country":"IN",
    "ks:ks_name":"Paharpur",
    "ks:ks_pop":137,
    "ks:ks_type":"HABITATION",
    "ks:ks_uagg_main":0,
    "name:eng_x_preferred":[
        "Paharpur"
    ],
    "wof:name":"Paharpur",
    "wof:placetype":"neighbourhood",
    "wof:population":137
},
  "geometry": {"coordinates":[86.59770399999999,24.80455],"type":"Point"}
}