{
  "type": "Feature",
  "properties": {
    "gn:admin1_code":"33",
    "gn:admin2_code":"585.0",
    "gn:asciiname":"Moira",
    "gn:country_code":"IN",
    "gn:dem":8,
    "gn:feature_class":"P",
    "gn:feature_code":"PPL",
    "gn:name":"Moira",
    "gn:population":0,
    "gn:timezone":"Asia/Kolkata",
    "iso:country":"IN",
    "ks:ks_name":"Moira",
    "ks:ks_pop":4206,
    "ks:ks_type":"URBAN",
    "name:deu_x_preferred":[
        "Ferdinand Cron"
    ],
    "name:eng_x_preferred":[
        "Moira"
    ],
    "wof:name":"Moira",
    "wof:placetype":"locality",
    "wof:population":4206
},
  "geometry": {"coordinates":[73.839017,15.60256],"type":"Point"}
}