{
  "type": "Feature",
  "properties": {
    "gn:admin1_code":"33",
    "gn:admin2_code":"585.0",
    "gn:asciiname":"Moira",
    "gn:country_code":"IN",
    "gn:dem":8,
    "gn:feature_class":"P",
    "gn:feature_code":"PPL",
    "gn:name":"Moira",
    "gn:population":0,
    "gn:timezone":"Asia/Kolkata",
    "iso:country":"IN",
    "name:deu_x_preferred":[
        "Ferdinand Cron"
    ],
    "wof:name":"Moira",
    "wof:placetype":"locality"
},
  "geometry": {"coordinates":[73.83901999999998,15.60256],"type":"Point"}
}