{
  "type": "Feature",
  "properties": {
    "iso:country":"IN",
    "ks:ks_name":"Thelkodadar",
    "ks:ks_pop":235,
    "ks:ks_type":"HABITATION",
    "name:eng_x_preferred":[
        "Thelkodadar"
    ],
    "wof:name":"Thelkodadar",
    "wof:placetype":"locality",
    "wof:population":235
},
  "geometry": {"coordinates":[84.16250100000001,21.002111],"type":"Point"}
}