{
  "type": "Feature",
  "properties": {
    "iso:country":"IN",
    "ks:ks_name":"Dangaskhal",
    "ks:ks_pop":578,
    "ks:ks_type":"HABITATION",
    "name:eng_x_preferred":[
        "Dangaskhal"
    ],
    "wof:name":"Dangaskhal",
    "wof:placetype":"locality",
    "wof:population":578
},
  "geometry": {"coordinates":[81.784023,18.336481],"type":"Point"}
}