{
  "type": "Feature",
  "properties": {
    "iso:country":"IN",
    "ks:ks_name":"Dhangarvadi",
    "ks:ks_pop":1864,
    "ks:ks_type":"HABITATION",
    "name:eng_x_preferred":[
        "Dhangarvadi"
    ],
    "wof:name":"Dhangarvadi",
    "wof:placetype":"locality",
    "wof:population":1864
},
  "geometry": {"coordinates":[74.353741,20.361386],"type":"Point"}
}