{
  "type": "Feature",
  "properties": {
    "iso:country":"IN",
    "ks:ks_name":"Rayada",
    "ks:ks_pop":124,
    "ks:ks_type":"VILLAGE",
    "name:eng_x_preferred":[
        "Rayada"
    ],
    "wof:name":"Rayada",
    "wof:placetype":"locality",
    "wof:population":124
},
  "geometry": {"coordinates":[84.165019,19.025225],"type":"Point"}
}