{
  "type": "Feature",
  "properties": {
    "iso:country":"IN",
    "ks:ks_name":"Teli Tola",
    "ks:ks_pop":659,
    "ks:ks_type":"HABITATION",
    "name:eng_x_preferred":[
        "Teli Tola"
    ],
    "wof:name":"Teli Tola",
    "wof:placetype":"locality",
    "wof:population":659
},
  "geometry": {"coordinates":[85.136336,26.211739],"type":"Point"}
}