{
  "type": "Feature",
  "properties": {
    "iso:country":"IN",
    "ks:ks_name":"Kichibheli",
    "ks:ks_pop":596,
    "ks:ks_type":"VILLAGE",
    "name:eng_x_preferred":[
        "Kichibheli"
    ],
    "wof:name":"Kichibheli",
    "wof:placetype":"locality",
    "wof:population":596
},
  "geometry": {"coordinates":[81.950574,18.261262],"type":"Point"}
}