{
  "type": "Feature",
  "properties": {
    "iso:country":"IN",
    "ks:ks_name":"Parsahi",
    "ks:ks_pop":411,
    "ks:ks_type":"HABITATION",
    "name:eng_x_preferred":[
        "Parsahi"
    ],
    "wof:name":"Parsahi",
    "wof:placetype":"locality",
    "wof:population":411
},
  "geometry": {"coordinates":[84.367181,23.853184],"type":"Point"}
}