{
  "type": "Feature",
  "properties": {
    "gn:admin1_code":"36.0",
    "gn:admin2_code":"161",
    "gn:asciiname":"Ruppur Sarai Bhikan",
    "gn:country_code":"IN",
    "gn:dem":152,
    "gn:feature_class":"P",
    "gn:feature_code":"PPL",
    "gn:name":"Ruppur Sarai Bhikan",
    "gn:population":0,
    "gn:timezone":"Asia/Kolkata",
    "iso:country":"IN",
    "name:und_x_variant":[
        "R\u016bppur Sar\u0101i Bhikan"
    ],
    "wof:name":"Ruppur Sarai Bhikan",
    "wof:placetype":"locality"
},
  "geometry": {"coordinates":[79.08348000000002,26.88816],"type":"Point"}
}