{
  "type": "Feature",
  "properties": {
    "iso:country":"IN",
    "ks:ks_name":"Deepmalwadi",
    "ks:ks_pop":35,
    "ks:ks_type":"HABITATION",
    "name:eng_x_preferred":[
        "Deepmalwadi"
    ],
    "wof:name":"Deepmalwadi",
    "wof:placetype":"locality",
    "wof:population":35
},
  "geometry": {"coordinates":[73.647761,16.196323],"type":"Point"}
}