{
  "type": "Feature",
  "properties": {
    "iso:country":"IN",
    "ks:ks_name":"Kasta Tripura Para",
    "ks:ks_pop":215,
    "ks:ks_type":"HABITATION",
    "name:eng_x_preferred":[
        "Kasta Tripura Para"
    ],
    "wof:name":"Kasta Tripura Para",
    "wof:placetype":"locality",
    "wof:population":215
},
  "geometry": {"coordinates":[91.679742,23.25217],"type":"Point"}
}