{
  "type": "Feature",
  "properties": {
    "iso:country":"IN",
    "ks:ks_name":"Nava Gaon Surata",
    "ks:ks_pop":1291,
    "ks:ks_type":"HABITATION",
    "name:eng_x_preferred":[
        "Nava Gaon Surata"
    ],
    "wof:name":"Nava Gaon Surata",
    "wof:placetype":"locality",
    "wof:population":1291
},
  "geometry": {"coordinates":[73.799263,23.715056],"type":"Point"}
}