{
  "type": "Feature",
  "properties": {
    "iso:country":"IN",
    "ks:ks_name":"Jamaitgarh",
    "ks:ks_type":"VILLAGE",
    "name:eng_x_preferred":[
        "Jamaitgarh"
    ],
    "wof:name":"Jamaitgarh",
    "wof:placetype":"locality"
},
  "geometry": {"coordinates":[77.269745,30.343757],"type":"Point"}
}