{
  "type": "Feature",
  "properties": {
    "iso:country":"IN",
    "ks:ks_name":"Icha Ahar",
    "ks:ks_pop":170,
    "ks:ks_type":"VILLAGE",
    "name:eng_x_preferred":[
        "Icha Ahar"
    ],
    "wof:name":"Icha Ahar",
    "wof:placetype":"locality",
    "wof:population":170
},
  "geometry": {"coordinates":[84.833504,24.063126],"type":"Point"}
}