{
  "type": "Feature",
  "properties": {
    "iso:country":"IN",
    "ks:ks_alt_nam":"kankale",
    "ks:ks_name":"Kankale",
    "ks:ks_pop":58,
    "ks:ks_type":"HABITATION",
    "name:eng_x_preferred":[
        "Kankale"
    ],
    "wof:name":"Kankale",
    "wof:placetype":"locality",
    "wof:population":58
},
  "geometry": {"coordinates":[75.24851200000001,13.640288],"type":"Point"}
}