{
  "type": "Feature",
  "properties": {
    "gn:admin1_code":"11",
    "gn:admin2_code":"24.0",
    "gn:asciiname":"Batlan",
    "gn:country_code":"IN",
    "gn:dem":514,
    "gn:feature_class":"P",
    "gn:feature_code":"PPL",
    "gn:name":"Batlan",
    "gn:population":0,
    "gn:timezone":"Asia/Kolkata",
    "iso:country":"IN",
    "wof:name":"Batlan",
    "wof:placetype":"locality"
},
  "geometry": {"coordinates":[76.26176,31.91159],"type":"Point"}
}