{
  "type": "Feature",
  "properties": {
    "iso:country":"IN",
    "ks:ks_name":"Baharpur",
    "ks:ks_pop":552,
    "ks:ks_type":"VILLAGE",
    "name:eng_x_preferred":[
        "Baharpur"
    ],
    "wof:name":"Baharpur",
    "wof:placetype":"locality",
    "wof:population":552
},
  "geometry": {"coordinates":[87.493459,23.271388],"type":"Point"}
}