{
  "type": "Feature",
  "properties": {
    "iso:country":"IN",
    "ks:ks_name":"Kalamgaon",
    "ks:ks_pop":174,
    "ks:ks_type":"VILLAGE",
    "name:eng_x_preferred":[
        "Kalamgaon"
    ],
    "wof:name":"Kalamgaon",
    "wof:placetype":"locality",
    "wof:population":174
},
  "geometry": {"coordinates":[73.381652,20.000884],"type":"Point"}
}