{
  "type": "Feature",
  "properties": {
    "iso:country":"IN",
    "ks:ks_name":"Madhopur",
    "ks:ks_pop":979,
    "ks:ks_type":"VILLAGE",
    "name:eng_x_preferred":[
        "Madhopur"
    ],
    "wof:name":"Madhopur",
    "wof:placetype":"neighbourhood",
    "wof:population":979
},
  "geometry": {"coordinates":[82.955439,25.213999],"type":"Point"}
}