{
  "type": "Feature",
  "properties": {
    "iso:country":"IN",
    "ks:ks_name":"Arepalya",
    "ks:ks_pop":249,
    "ks:ks_type":"VILLAGE",
    "name:eng_x_preferred":[
        "Arepalya"
    ],
    "wof:name":"Arepalya",
    "wof:placetype":"locality",
    "wof:population":249
},
  "geometry": {"coordinates":[77.150531,12.070001],"type":"Point"}
}