{
  "type": "Feature",
  "properties": {
    "iso:country":"IN",
    "ks:ks_name":"Marigebailu",
    "ks:ks_pop":66,
    "ks:ks_type":"HABITATION",
    "name:eng_x_preferred":[
        "Marigebailu"
    ],
    "wof:name":"Marigebailu",
    "wof:placetype":"locality",
    "wof:population":66
},
  "geometry": {"coordinates":[75.215109,13.471726],"type":"Point"}
}