{
  "type": "Feature",
  "properties": {
    "iso:country":"IN",
    "ks:ks_name":"Udamakki",
    "ks:ks_pop":39,
    "ks:ks_type":"HABITATION",
    "name:eng_x_preferred":[
        "Udamakki"
    ],
    "wof:name":"Udamakki",
    "wof:placetype":"locality",
    "wof:population":39
},
  "geometry": {"coordinates":[74.66798799999999,15.029648],"type":"Point"}
}