{
  "type": "Feature",
  "properties": {
    "iso:country":"IN",
    "ks:ks_name":"Ditafalia",
    "ks:ks_pop":492,
    "ks:ks_type":"HABITATION",
    "name:eng_x_preferred":[
        "Ditafalia"
    ],
    "wof:name":"Ditafalia",
    "wof:placetype":"locality",
    "wof:population":492
},
  "geometry": {"coordinates":[72.955167,20.696444],"type":"Point"}
}