{
  "type": "Feature",
  "properties": {
    "iso:country":"IN",
    "ks:ks_name":"Chak Muradpur",
    "ks:ks_pop":107,
    "ks:ks_type":"HABITATION",
    "name:eng_x_preferred":[
        "Chak Muradpur"
    ],
    "wof:name":"Chak Muradpur",
    "wof:placetype":"locality",
    "wof:population":107
},
  "geometry": {"coordinates":[76.297786,27.961911],"type":"Point"}
}