{
  "type": "Feature",
  "properties": {
    "gn:admin1_code":"19.0",
    "gn:admin2_code":"573.0",
    "gn:asciiname":"Siddegaudanakoppal",
    "gn:country_code":"IN",
    "gn:dem":765,
    "gn:feature_class":"P",
    "gn:feature_code":"PPL",
    "gn:name":"Siddegaudanakoppal",
    "gn:population":0,
    "gn:timezone":"Asia/Kolkata",
    "iso:country":"IN",
    "wof:name":"Siddegaudanakoppal",
    "wof:placetype":"locality"
},
  "geometry": {"coordinates":[76.77593,12.62872],"type":"Point"}
}