{
  "type": "Feature",
  "properties": {
    "gn:admin1_code":"19.0",
    "gn:admin2_code":"571.0",
    "gn:asciiname":"Shingravatanahalli",
    "gn:country_code":"IN",
    "gn:dem":692,
    "gn:feature_class":"P",
    "gn:feature_code":"PPL",
    "gn:name":"Shingravatanahalli",
    "gn:population":0,
    "gn:timezone":"Asia/Kolkata",
    "iso:country":"IN",
    "wof:name":"Shingravatanahalli",
    "wof:placetype":"locality"
},
  "geometry": {"coordinates":[77.04599,13.76268],"type":"Point"}
}