{
  "type": "Feature",
  "properties": {
    "iso:country":"IN",
    "ks:ks_name":"Voddi Indlu",
    "ks:ks_pop":102,
    "ks:ks_type":"HABITATION",
    "ks:ks_uagg_main":0,
    "name:eng_x_preferred":[
        "Voddi Indlu"
    ],
    "wof:name":"Voddi Indlu",
    "wof:placetype":"neighbourhood",
    "wof:population":102
},
  "geometry": {"coordinates":[79.179316,13.15966],"type":"Point"}
}