{
  "type": "Feature",
  "properties": {
    "iso:country":"IN",
    "ks:ks_name":"Jagdis Paran",
    "ks:ks_pop":807,
    "ks:ks_type":"VILLAGE",
    "name:eng_x_preferred":[
        "Jagdis Paran"
    ],
    "wof:name":"Jagdis Paran",
    "wof:placetype":"locality",
    "wof:population":807
},
  "geometry": {"coordinates":[85.742908,26.0074],"type":"Point"}
}