{
  "type": "Feature",
  "properties": {
    "iso:country":"IN",
    "ks:ks_name":"Keela Echampatty",
    "ks:ks_pop":174,
    "ks:ks_type":"HABITATION",
    "name:eng_x_preferred":[
        "Keela Echampatty"
    ],
    "wof:name":"Keela Echampatty",
    "wof:placetype":"locality",
    "wof:population":174
},
  "geometry": {"coordinates":[78.363741,10.534769],"type":"Point"}
}