{
  "type": "Feature",
  "properties": {
    "iso:country":"IN",
    "ks:ks_alt_nam":"Mallah tola",
    "ks:ks_name":"Mallah Tola",
    "ks:ks_pop":632,
    "ks:ks_type":"HABITATION",
    "ks:ks_uagg_main":0,
    "name:eng_x_preferred":[
        "Mallah Tola"
    ],
    "wof:name":"Mallah Tola",
    "wof:placetype":"neighbourhood",
    "wof:population":632
},
  "geometry": {"coordinates":[85.64032899999999,26.439256],"type":"Point"}
}