{
  "type": "Feature",
  "properties": {
    "iso:country":"IN",
    "ks:ks_name":"Dhubichimal",
    "ks:ks_pop":415,
    "ks:ks_type":"HABITATION",
    "name:eng_x_preferred":[
        "Dhubichimal"
    ],
    "wof:name":"Dhubichimal",
    "wof:placetype":"locality",
    "wof:population":415
},
  "geometry": {"coordinates":[73.332689,20.288326],"type":"Point"}
}