{
  "type": "Feature",
  "properties": {
    "iso:country":"IN",
    "ks:ks_name":"Ramavat",
    "ks:ks_pop":642,
    "ks:ks_type":"HABITATION",
    "name:eng_x_preferred":[
        "Ramavat"
    ],
    "wof:name":"Ramavat",
    "wof:placetype":"locality",
    "wof:population":642
},
  "geometry": {"coordinates":[73.451306,23.19225],"type":"Point"}
}