{
  "type": "Feature",
  "properties": {
    "iso:country":"IN",
    "ks:ks_name":"Cheruvumundaravuru",
    "ks:ks_pop":123,
    "ks:ks_type":"HABITATION",
    "name:eng_x_preferred":[
        "Cheruvumundaravuru"
    ],
    "wof:name":"Cheruvumundaravuru",
    "wof:placetype":"locality",
    "wof:population":123
},
  "geometry": {"coordinates":[79.112784,13.301696],"type":"Point"}
}