{
  "type": "Feature",
  "properties": {
    "gn:admin1_code":"35.0",
    "gn:admin2_code":"451.0",
    "gn:asciiname":"Kulon",
    "gn:country_code":"IN",
    "gn:dem":356,
    "gn:feature_class":"P",
    "gn:feature_code":"PPL",
    "gn:name":"Kulon",
    "gn:population":0,
    "gn:timezone":"Asia/Kolkata",
    "iso:country":"IN",
    "ks:ks_name":"Kulon",
    "ks:ks_pop":1076,
    "ks:ks_type":"VILLAGE",
    "name:eng_x_preferred":[
        "Kulon"
    ],
    "wof:name":"Kulon",
    "wof:placetype":"locality",
    "wof:population":1076
},
  "geometry": {"coordinates":[79.692503,23.104078],"type":"Point"}
}