{
  "type": "Feature",
  "properties": {
    "iso:country":"IN",
    "ks:ks_name":"Nargane",
    "ks:ks_pop":1407,
    "ks:ks_type":"HABITATION",
    "name:eng_x_preferred":[
        "Nargane"
    ],
    "wof:name":"Nargane",
    "wof:placetype":"locality",
    "wof:population":1407
},
  "geometry": {"coordinates":[75.798315,12.43773],"type":"Point"}
}