{
  "type": "Feature",
  "properties": {
    "iso:country":"IN",
    "ks:ks_name":"Gundeli",
    "ks:ks_pop":42,
    "ks:ks_type":"VILLAGE",
    "name:eng_x_preferred":[
        "Gundeli"
    ],
    "wof:name":"Gundeli",
    "wof:placetype":"locality",
    "wof:population":42
},
  "geometry": {"coordinates":[83.800292,20.293598],"type":"Point"}
}