{
  "type": "Feature",
  "properties": {
    "gn:admin1_code":"2.0",
    "gn:admin2_code":"554.0",
    "gn:asciiname":"Kollagunta",
    "gn:country_code":"IN",
    "gn:dem":171,
    "gn:feature_class":"P",
    "gn:feature_code":"PPL",
    "gn:name":"Koll\u0101gunta",
    "gn:population":0,
    "gn:timezone":"Asia/Kolkata",
    "iso:country":"IN",
    "name:tel_x_preferred":[
        "\u0c15\u0c4a\u0c32\u0c4d\u0c32\u0c17\u0c41\u0c02\u0c1f"
    ],
    "wof:name":"Kollagunta",
    "wof:placetype":"locality"
},
  "geometry": {"coordinates":[79.42189,13.34191],"type":"Point"}
}