{
  "type": "Feature",
  "properties": {
    "iso:country":"IN",
    "ks:ks_name":"Borehosahalli",
    "ks:ks_pop":220,
    "ks:ks_type":"HABITATION",
    "name:eng_x_preferred":[
        "Borehosahalli"
    ],
    "wof:name":"Borehosahalli",
    "wof:placetype":"locality",
    "wof:population":220
},
  "geometry": {"coordinates":[76.178102,12.328645],"type":"Point"}
}