{
  "type": "Feature",
  "properties": {
    "iso:country":"IN",
    "ks:ks_name":"Tiling Gaon",
    "ks:ks_pop":189,
    "ks:ks_type":"VILLAGE",
    "ks:ks_uagg_main":0,
    "name:eng_x_preferred":[
        "Tiling Gaon"
    ],
    "wof:name":"Tiling Gaon",
    "wof:placetype":"neighbourhood",
    "wof:population":189
},
  "geometry": {"coordinates":[91.710525,26.190478],"type":"Point"}
}