{
  "type": "Feature",
  "properties": {
    "iso:country":"IN",
    "ks:ks_name":"Nani Panyali",
    "ks:ks_pop":148,
    "ks:ks_type":"VILLAGE",
    "name:eng_x_preferred":[
        "Nani Panyali"
    ],
    "wof:name":"Nani Panyali",
    "wof:placetype":"locality",
    "wof:population":148
},
  "geometry": {"coordinates":[80.06952800000001,29.983344],"type":"Point"}
}