{
  "type": "Feature",
  "properties": {
    "gn:admin1_code":"12.0",
    "gn:admin2_code":"002",
    "gn:asciiname":"Rawalpur",
    "gn:country_code":"IN",
    "gn:dem":1592,
    "gn:feature_class":"P",
    "gn:feature_code":"PPL",
    "gn:name":"R\u0101walpur",
    "gn:population":0,
    "gn:timezone":"Asia/Kolkata",
    "iso:country":"IN",
    "wof:name":"Rawalpur",
    "wof:placetype":"locality"
},
  "geometry": {"coordinates":[74.79614000000002,34.0219],"type":"Point"}
}