{
  "type": "Feature",
  "properties": {
    "gn:admin1_code":"3.0",
    "gn:admin2_code":"305.0",
    "gn:asciiname":"Mikirgaon",
    "gn:country_code":"IN",
    "gn:dem":64,
    "gn:feature_class":"P",
    "gn:feature_code":"PPL",
    "gn:name":"Mikirg\u0101on",
    "gn:population":0,
    "gn:timezone":"Asia/Kolkata",
    "iso:country":"IN",
    "wof:name":"Mikirgaon",
    "wof:placetype":"locality"
},
  "geometry": {"coordinates":[92.69335,26.14073],"type":"Point"}
}