{
  "type": "Feature",
  "properties": {
    "gn:admin1_code":"3.0",
    "gn:admin2_code":"305.0",
    "gn:asciiname":"Mikirgaon",
    "gn:country_code":"IN",
    "gn:dem":64,
    "gn:feature_class":"P",
    "gn:feature_code":"PPL",
    "gn:name":"Mikirg\u0101on",
    "gn:population":0,
    "gn:timezone":"Asia/Kolkata",
    "iso:country":"IN",
    "ks:ks_alt_nam":"Mikirg\u0101on",
    "ks:ks_alt_nam_2":"Mikirgaon",
    "ks:ks_name":"Mikir Gaon",
    "ks:ks_pop":1287,
    "ks:ks_type":"VILLAGE",
    "name:eng_x_preferred":[
        "Mikir Gaon"
    ],
    "name:eng_x_variant":[
        "Mikirgaon",
        "Mikirg\u0101on"
    ],
    "wof:name":"Mikir Gaon",
    "wof:placetype":"locality",
    "wof:population":1287
},
  "geometry": {"coordinates":[92.69334600000001,26.140732],"type":"Point"}
}