{
  "type": "Feature",
  "properties": {
    "iso:country":"IN",
    "ks:ks_name":"Mahajenahalli",
    "ks:ks_pop":105,
    "ks:ks_type":"VILLAGE",
    "ks:ks_uagg_main":0,
    "name:eng_x_preferred":[
        "Mahajenahalli"
    ],
    "wof:name":"Mahajenahalli",
    "wof:placetype":"locality",
    "wof:population":105
},
  "geometry": {"coordinates":[75.803887,14.490954],"type":"Point"}
}