{
  "type": "Feature",
  "properties": {
    "gn:country":"IN",
    "gn:fcode":"PPL",
    "gn:pop":24177,
    "iso:country":"IN",
    "qs:name":"Indarpur",
    "qs:name_adm0":"India",
    "qs:name_adm1":"Uttar Pradesh",
    "qs:photos_9r":0,
    "qs:photos_sr":0,
    "qs:placetype":"Town",
    "qs:pop_sr":"7",
    "wof:name":"Indarpur",
    "wof:placetype":"locality",
    "wof:population":24177
},
  "geometry": {"coordinates":[84.05426,26.04306],"type":"Point"}
}