{
  "type": "Feature",
  "properties": {
    "iso:country":"IN",
    "ks:ks_name":"Attihalla",
    "ks:ks_pop":266,
    "ks:ks_type":"HABITATION",
    "name:eng_x_preferred":[
        "Attihalla"
    ],
    "wof:name":"Attihalla",
    "wof:placetype":"locality",
    "wof:population":266
},
  "geometry": {"coordinates":[74.655674,14.434397],"type":"Point"}
}