{
  "type": "Feature",
  "properties": {
    "iso:country":"IN",
    "ks:ks_alt_nam":"Yetigaddamadigapalle UI",
    "ks:ks_name":"Yetigaddamadigapalle Ui",
    "ks:ks_pop":1,
    "ks:ks_type":"HABITATION",
    "ks:ks_uagg_main":0,
    "name:eng_x_preferred":[
        "Yetigaddamadigapalle Ui"
    ],
    "wof:name":"Yetigaddamadigapalle Ui",
    "wof:placetype":"neighbourhood",
    "wof:population":1
},
  "geometry": {"coordinates":[79.043437,13.79901],"type":"Point"}
}