{
  "type": "Feature",
  "properties": {
    "iso:country":"IN",
    "ks:ks_name":"Harijan Adivashi Tola",
    "ks:ks_pop":331,
    "ks:ks_type":"HABITATION",
    "name:eng_x_preferred":[
        "Harijan Adivashi Tola"
    ],
    "wof:name":"Harijan Adivashi Tola",
    "wof:placetype":"locality",
    "wof:population":331
},
  "geometry": {"coordinates":[88.166568,26.396533],"type":"Point"}
}