{
  "type": "Feature",
  "properties": {
    "iso:country":"IN",
    "ks:ks_name":"Mal Khola Gairi Gaon",
    "ks:ks_pop":859,
    "ks:ks_type":"HABITATION",
    "name:eng_x_preferred":[
        "Mal Khola Gairi Gaon"
    ],
    "wof:name":"Mal Khola Gairi Gaon",
    "wof:placetype":"locality",
    "wof:population":859
},
  "geometry": {"coordinates":[88.720687,26.963224],"type":"Point"}
}