{
  "type": "Feature",
  "properties": {
    "gn:admin1_code":"16.0",
    "gn:admin2_code":"508",
    "gn:asciiname":"Kotgal",
    "gn:country_code":"IN",
    "gn:dem":406,
    "gn:feature_class":"P",
    "gn:feature_code":"PPL",
    "gn:name":"Kotgal",
    "gn:population":0,
    "gn:timezone":"Asia/Kolkata",
    "iso:country":"IN",
    "wof:name":"Kotgal",
    "wof:placetype":"locality"
},
  "geometry": {"coordinates":[80.56728000000003,20.54973],"type":"Point"}
}