{
  "type": "Feature",
  "properties": {
    "gn:country":"IN",
    "gn:fcode":"PPL",
    "gn:pop":41247,
    "iso:country":"IN",
    "name:ben_x_preferred":[
        "\u09a8\u09cc\u0997\u09be\u099b\u09bf\u09af\u09bc\u09be"
    ],
    "name:bpy_x_preferred":[
        "\u09a8\u09cc\u0997\u09be\u099b\u09bf\u09af\u09bc\u09be"
    ],
    "name:bul_x_preferred":[
        "\u041d\u0430\u0443\u0433\u0430\u0447\u0445\u0438\u0430"
    ],
    "name:chi_x_preferred":[
        "\u7459\u52a0\u5947\u5e0c\u4e9a"
    ],
    "name:dut_x_preferred":[
        "Naugachhia"
    ],
    "name:eng_x_preferred":[
        "Naugachia"
    ],
    "name:fre_x_preferred":[
        "Naugachia"
    ],
    "name:ger_x_preferred":[
        "Naugachhia"
    ],
    "name:guj_x_preferred":[
        "\u0aa8\u0acc\u0a97\u0abe\u0a9a\u0abf\u0a86"
    ],
    "name:ita_x_preferred":[
        "Naugachhia"
    ],
    "name:jpn_x_preferred":[
        "\u30ce\u30a6\u30ac\u30c1\u30a2"
    ],
    "name:kan_x_preferred":[
        "\u0ca8\u0ccc\u0c97\u0c9a\u0cbf\u0caf"
    ],
    "name:kor_x_preferred":[
        "\ub098\uc6b0\uac00\uce58\uc544"
    ],
    "name:may_x_preferred":[
        "Naugachhia"
    ],
    "name:nan_x_preferred":[
        "Naugachhia"
    ],
    "name:new_x_preferred":[
        "\u0928\u094c\u0917\u091b\u093f\u092f\u093e"
    ],
    "name:ori_x_preferred":[
        "\u0b28\u0b3e\u0b09\u0b17\u0b3e\u0b1b\u0b3f\u0b05"
    ],
    "name:por_x_preferred":[
        "Naugachhia"
    ],
    "name:rus_x_preferred":[
        "\u041d\u0430\u0443\u0433\u0430\u0447\u0438\u0430"
    ],
    "name:spa_x_preferred":[
        "Naugachhia"
    ],
    "name:swe_x_preferred":[
        "Naugachhia"
    ],
    "name:tam_x_preferred":[
        "\u0ba8\u0bbe\u0b95\u0bbe\u0b95\u0bcd\u0b95 \u0bb9\u0bbf\u0baf\u0bbe"
    ],
    "name:tel_x_preferred":[
        "\u0c28\u0c4c\u0c17\u0c3e\u0c1a\u0c3f\u0c2f\u0c3e"
    ],
    "name:unk_x_variant":[
        "Naugachia"
    ],
    "name:urd_x_preferred":[
        "\u0646\u0648\u06af\u0686\u06be\u06cc\u0627"
    ],
    "name:vie_x_preferred":[
        "Naugachhia"
    ],
    "qs:name":"Naugachhia",
    "qs:name_adm0":"India",
    "qs:name_adm1":"Bihar",
    "qs:photos_9k":1,
    "qs:photos_9r":3,
    "qs:photos_all":141,
    "qs:photos_sr":0,
    "qs:placetype":"Town",
    "qs:pop_sr":"7",
    "wd:wordcount":701,
    "wof:name":"Naugachhia",
    "wof:placetype":"locality",
    "wof:population":41247
},
  "geometry": {"coordinates":[87.09856000000001,25.38706],"type":"Point"}
}