{
  "type": "Feature",
  "properties": {
    "gn:admin1_code":"36",
    "gn:admin2_code":"155.0",
    "gn:asciiname":"Gadarian Khera",
    "gn:country_code":"IN",
    "gn:dem":135,
    "gn:feature_class":"P",
    "gn:feature_code":"PPL",
    "gn:name":"Gadari\u0101n Khera",
    "gn:population":0,
    "gn:timezone":"Asia/Kolkata",
    "iso:country":"IN",
    "ks:ks_name":"Gadariyan Khera",
    "ks:ks_pop":261,
    "ks:ks_type":"HABITATION",
    "name:eng_x_preferred":[
        "Gadariyan Khera"
    ],
    "name:eng_x_variant":[
        "Gadarian Khera"
    ],
    "wof:name":"Gadariyan Khera",
    "wof:placetype":"locality",
    "wof:population":261
},
  "geometry": {"coordinates":[80.555038,27.119369],"type":"Point"}
}