{
  "type": "Feature",
  "properties": {
    "iso:country":"IN",
    "ks:ks_name":"Khetura",
    "ks:ks_pop":2571,
    "ks:ks_type":"VILLAGE",
    "ks:ks_uagg_main":0,
    "name:eng_x_preferred":[
        "Khetura"
    ],
    "wof:name":"Khetura",
    "wof:placetype":"neighbourhood",
    "wof:population":2571
},
  "geometry": {"coordinates":[87.67737200000001,23.334385],"type":"Point"}
}