{
  "type": "Feature",
  "properties": {
    "iso:country":"IN",
    "ks:ks_alt_nam":"S\u0101vangi",
    "ks:ks_name":"Savangi",
    "ks:ks_type":"VILLAGE",
    "name:eng_x_preferred":[
        "Savangi"
    ],
    "name:eng_x_variant":[
        "S\u0101vangi"
    ],
    "wof:name":"Savangi",
    "wof:placetype":"locality"
},
  "geometry": {"coordinates":[77.795213,20.112321],"type":"Point"}
}