{
  "type": "Feature",
  "properties": {
    "gn:admin1_code":"36",
    "gn:admin2_code":"191.0",
    "gn:asciiname":"Jeropur",
    "gn:country_code":"IN",
    "gn:dem":85,
    "gn:feature_class":"P",
    "gn:feature_code":"PPL",
    "gn:name":"Jeropur",
    "gn:population":0,
    "gn:timezone":"Asia/Kolkata",
    "iso:country":"IN",
    "ks:ks_name":"Jeropur",
    "ks:ks_pop":434,
    "ks:ks_type":"VILLAGE",
    "name:eng_x_preferred":[
        "Jeropur"
    ],
    "wof:name":"Jeropur",
    "wof:placetype":"locality",
    "wof:population":434
},
  "geometry": {"coordinates":[82.87896000000001,26.14431],"type":"Point"}
}