{
  "type": "Feature",
  "properties": {
    "iso:country":"IN",
    "ks:ks_name":"Shatupur",
    "ks:ks_pop":309,
    "ks:ks_type":"VILLAGE",
    "name:eng_x_preferred":[
        "Shatupur"
    ],
    "wof:name":"Shatupur",
    "wof:placetype":"locality",
    "wof:population":309
},
  "geometry": {"coordinates":[87.75382500000001,22.122226],"type":"Point"}
}