{
  "type": "Feature",
  "properties": {
    "gn:admin1_code":"16.0",
    "gn:admin2_code":"515.0",
    "gn:asciiname":"Gandeshvar",
    "gn:country_code":"IN",
    "gn:dem":622,
    "gn:feature_class":"P",
    "gn:feature_code":"PPL",
    "gn:name":"Gandeshvar",
    "gn:population":0,
    "gn:timezone":"Asia/Kolkata",
    "iso:country":"IN",
    "wof:name":"Gandeshvar",
    "wof:placetype":"locality"
},
  "geometry": {"coordinates":[75.22807,20.18982],"type":"Point"}
}