{
  "type": "Feature",
  "properties": {
    "iso:country":"IN",
    "ks:ks_alt_nam":"INDRANAGAR",
    "ks:ks_name":"Indranagar",
    "ks:ks_pop":417,
    "ks:ks_type":"HABITATION",
    "name:eng_x_preferred":[
        "Indranagar"
    ],
    "wof:name":"Indranagar",
    "wof:placetype":"locality",
    "wof:population":417
},
  "geometry": {"coordinates":[83.493961,22.52611],"type":"Point"}
}