{
  "type": "Feature",
  "properties": {
    "iso:country":"IN",
    "ks:ks_name":"Gopalapattinam",
    "ks:ks_pop":166,
    "ks:ks_type":"HABITATION",
    "name:eng_x_preferred":[
        "Gopalapattinam"
    ],
    "wof:name":"Gopalapattinam",
    "wof:placetype":"locality",
    "wof:population":166
},
  "geometry": {"coordinates":[78.718127,9.829223],"type":"Point"}
}