{
  "type": "Feature",
  "properties": {
    "gn:admin1_code":"28.0",
    "gn:admin2_code":"344",
    "gn:asciiname":"Haripur Kismat",
    "gn:country_code":"IN",
    "gn:dem":33,
    "gn:feature_class":"P",
    "gn:feature_code":"PPL",
    "gn:name":"Har\u012bpur Kismat",
    "gn:population":0,
    "gn:timezone":"Asia/Kolkata",
    "iso:country":"IN",
    "wof:name":"Haripur Kismat",
    "wof:placetype":"locality"
},
  "geometry": {"coordinates":[87.36667,22.28333],"type":"Point"}
}