{
  "type": "Feature",
  "properties": {
    "iso:country":"IN",
    "ks:ks_name":"Motilal Kewat Ka Dera",
    "ks:ks_pop":81,
    "ks:ks_type":"HABITATION",
    "name:eng_x_preferred":[
        "Motilal Kewat Ka Dera"
    ],
    "wof:name":"Motilal Kewat Ka Dera",
    "wof:placetype":"locality",
    "wof:population":81
},
  "geometry": {"coordinates":[80.621252,25.443667],"type":"Point"}
}