{
  "type": "Feature",
  "properties": {
    "iso:country":"IN",
    "ks:ks_name":"Dhindapada",
    "ks:ks_pop":71,
    "ks:ks_type":"HABITATION",
    "name:eng_x_preferred":[
        "Dhindapada"
    ],
    "wof:name":"Dhindapada",
    "wof:placetype":"locality",
    "wof:population":71
},
  "geometry": {"coordinates":[73.110916,19.85062],"type":"Point"}
}