{
  "type": "Feature",
  "properties": {
    "iso:country":"IN",
    "ks:ks_name":"Paraja Kumuli",
    "ks:ks_pop":31,
    "ks:ks_type":"HABITATION",
    "name:eng_x_preferred":[
        "Paraja Kumuli"
    ],
    "wof:name":"Paraja Kumuli",
    "wof:placetype":"locality",
    "wof:population":31
},
  "geometry": {"coordinates":[82.821774,19.264973],"type":"Point"}
}