{
  "type": "Feature",
  "properties": {
    "gn:admin1_code":"2.0",
    "gn:admin2_code":"544.0",
    "gn:asciiname":"Chapagadda",
    "gn:country_code":"IN",
    "gn:dem":898,
    "gn:feature_class":"P",
    "gn:feature_code":"PPL",
    "gn:name":"Ch\u0101pagadda",
    "gn:population":0,
    "gn:timezone":"Asia/Kolkata",
    "iso:country":"IN",
    "ks:ks_alt_nam":"Ch\u0101pagadda",
    "ks:ks_name":"Chapagadda",
    "ks:ks_type":"VILLAGE",
    "name:eng_x_preferred":[
        "Chapagadda"
    ],
    "name:eng_x_variant":[
        "Ch\u0101pagadda"
    ],
    "wof:name":"Chapagadda",
    "wof:placetype":"locality"
},
  "geometry": {"coordinates":[82.433868,18.145061],"type":"Point"}
}