{
  "type": "Feature",
  "properties": {
    "iso:country":"IN",
    "ks:ks_name":"Kalyani",
    "ks:ks_pop":576,
    "ks:ks_type":"VILLAGE",
    "name:eng_x_preferred":[
        "Kalyani"
    ],
    "wof:name":"Kalyani",
    "wof:placetype":"locality",
    "wof:population":576
},
  "geometry": {"coordinates":[86.440972,21.223033],"type":"Point"}
}