{
  "type": "Feature",
  "properties": {
    "iso:country":"IN",
    "ks:ks_name":"Pachrukhi",
    "ks:ks_pop":152,
    "ks:ks_type":"VILLAGE",
    "name:eng_x_preferred":[
        "Pachrukhi"
    ],
    "wof:name":"Pachrukhi",
    "wof:placetype":"locality",
    "wof:population":152
},
  "geometry": {"coordinates":[85.359352,24.440319],"type":"Point"}
}