{
  "type": "Feature",
  "properties": {
    "gn:admin1_code":"39.0",
    "gn:admin2_code":"63.0",
    "gn:asciiname":"Devi Ka Bagar",
    "gn:country_code":"IN",
    "gn:dem":1049,
    "gn:feature_class":"P",
    "gn:feature_code":"PPL",
    "gn:name":"Devi Ka Bagar",
    "gn:population":0,
    "gn:timezone":"Asia/Kolkata",
    "iso:country":"IN",
    "wof:name":"Devi Ka Bagar",
    "wof:placetype":"locality"
},
  "geometry": {"coordinates":[79.89617,29.94018],"type":"Point"}
}