{
  "type": "Feature",
  "properties": {
    "iso:country":"IN",
    "ks:ks_name":"Denwadi",
    "ks:ks_pop":55,
    "ks:ks_type":"HABITATION",
    "name:eng_x_preferred":[
        "Denwadi"
    ],
    "wof:name":"Denwadi",
    "wof:placetype":"locality",
    "wof:population":55
},
  "geometry": {"coordinates":[73.378186,16.686992],"type":"Point"}
}