{
  "type": "Feature",
  "properties": {
    "gn:admin1_code":"36",
    "gn:admin2_code":"159.0",
    "gn:asciiname":"Muzaffarnagar",
    "gn:country_code":"IN",
    "gn:dem":157,
    "gn:feature_class":"P",
    "gn:feature_code":"PPL",
    "gn:name":"Muz\u0101ffarnagar",
    "gn:population":0,
    "gn:timezone":"Asia/Kolkata",
    "iso:country":"IN",
    "name:bih_x_preferred":[
        "\u092e\u0941\u091c\u092b\u094d\u092b\u0930\u0928\u0917\u0930"
    ],
    "name:cat_x_preferred":[
        "Muzaffarnagar"
    ],
    "name:ceb_x_preferred":[
        "Muzaffarnagar"
    ],
    "name:deu_x_preferred":[
        "Muzaffarnagar"
    ],
    "name:epo_x_preferred":[
        "Muzaffarnagar"
    ],
    "name:fas_x_preferred":[
        "\u0645\u0638\u0641\u0631\u0646\u06af\u0631"
    ],
    "name:fra_x_preferred":[
        "Muzaffarnagar"
    ],
    "name:guj_x_preferred":[
        "\u0aae\u0ac1\u0a9c\u0aab\u0acd\u0aab\u0ab0\u0aa8\u0a97\u0ab0"
    ],
    "name:hin_x_preferred":[
        "\u092e\u0941\u091c\u093c\u092b\u093c\u094d\u092b\u093c\u0930\u0928\u0917\u0930"
    ],
    "name:ind_x_preferred":[
        "Muzaffarnagar"
    ],
    "name:ita_x_preferred":[
        "Muzaffarnagar"
    ],
    "name:jpn_x_preferred":[
        "\u30e0\u30b6\u30c3\u30d5\u30a1\u30eb\u30ca\u30ac\u30eb"
    ],
    "name:mar_x_preferred":[
        "\u092e\u0941\u091d\u092b\u094d\u092b\u0930\u0928\u0917\u0930"
    ],
    "name:mlg_x_preferred":[
        "Muzaffarnagar"
    ],
    "name:msa_x_preferred":[
        "Muzaffarnagar"
    ],
    "name:new_x_preferred":[
        "\u092e\u0941\u091c\u092b\u094d\u092b\u0930\u0928\u0917\u0930"
    ],
    "name:nld_x_preferred":[
        "Muzaffarnagar"
    ],
    "name:ori_x_preferred":[
        "\u0b2e\u0b41\u0b1c\u0b2b\u0b30\u0b28\u0b17\u0b30"
    ],
    "name:pnb_x_preferred":[
        "\u0645\u0638\u0641\u0631\u0646\u06af\u0631"
    ],
    "name:pol_x_preferred":[
        "Muzaffarnagar"
    ],
    "name:san_x_preferred":[
        "\u092e\u0941\u091c\u092b\u094d\u092b\u0930\u0928\u0917\u0930\u092e\u094d"
    ],
    "name:srp_x_preferred":[
        "\u041c\u0443\u0437\u0430\u0444\u0430\u0440\u043d\u0430\u0433\u0430\u0440"
    ],
    "name:swe_x_preferred":[
        "Muzaffarnagar"
    ],
    "name:urd_x_preferred":[
        "\u0645\u0638\u0641\u0631 \u0646\u06af\u0631"
    ],
    "name:zho_x_preferred":[
        "\u7a46\u624e\u6cd5\u5c14\u7eb3\u52a0\u5c14"
    ],
    "wof:name":"Muzaffarnagar",
    "wof:placetype":"locality"
},
  "geometry": {"coordinates":[79.18600000000001,27.587],"type":"Point"}
}