{
  "type": "Feature",
  "properties": {
    "iso:country":"IN",
    "ks:ks_alt_nam":"Ar\u0101zi English",
    "ks:ks_name":"Arazi English",
    "ks:ks_type":"VILLAGE",
    "name:eng_x_preferred":[
        "Arazi English"
    ],
    "name:eng_x_variant":[
        "Ar\u0101zi English"
    ],
    "wof:name":"Arazi English",
    "wof:placetype":"locality"
},
  "geometry": {"coordinates":[83.76363000000001,24.982857],"type":"Point"}
}