{
  "type": "Feature",
  "properties": {
    "iso:country":"IN",
    "ks:ks_name":"Krishanganj",
    "ks:ks_pop":2471,
    "ks:ks_type":"HABITATION",
    "name:eng_x_preferred":[
        "Krishanganj"
    ],
    "wof:name":"Krishanganj",
    "wof:placetype":"locality",
    "wof:population":2471
},
  "geometry": {"coordinates":[77.372674,25.540745],"type":"Point"}
}