{
  "type": "Feature",
  "properties": {
    "iso:country":"IN",
    "ks:ks_name":"Pranpur",
    "ks:ks_pop":540,
    "ks:ks_type":"HABITATION",
    "name:eng_x_preferred":[
        "Pranpur"
    ],
    "wof:name":"Pranpur",
    "wof:placetype":"locality",
    "wof:population":540
},
  "geometry": {"coordinates":[84.22753299999999,25.895469],"type":"Point"}
}