{
  "type": "Feature",
  "properties": {
    "iso:country":"IN",
    "ks:ks_name":"Kalmettalu",
    "ks:ks_pop":6,
    "ks:ks_type":"HABITATION",
    "name:eng_x_preferred":[
        "Kalmettalu"
    ],
    "wof:name":"Kalmettalu",
    "wof:placetype":"locality",
    "wof:population":6
},
  "geometry": {"coordinates":[74.876672,14.057397],"type":"Point"}
}