{
  "type": "Feature",
  "properties": {
    "gn:admin1_code":"36",
    "gn:admin2_code":"161.0",
    "gn:asciiname":"Marhaiyan Khanyan",
    "gn:country_code":"IN",
    "gn:dem":136,
    "gn:feature_class":"P",
    "gn:feature_code":"PPL",
    "gn:name":"Marhaiy\u0101n Khany\u0101n",
    "gn:population":0,
    "gn:timezone":"Asia/Kolkata",
    "iso:country":"IN",
    "wof:name":"Marhaiyan Khanyan",
    "wof:placetype":"locality"
},
  "geometry": {"coordinates":[78.74721,26.91014],"type":"Point"}
}