{
  "type": "Feature",
  "properties": {
    "iso:country":"IN",
    "ks:ks_name":"Bootapeepla Fali",
    "ks:ks_pop":200,
    "ks:ks_type":"HABITATION",
    "name:eng_x_preferred":[
        "Bootapeepla Fali"
    ],
    "wof:name":"Bootapeepla Fali",
    "wof:placetype":"locality",
    "wof:population":200
},
  "geometry": {"coordinates":[72.924644,24.525614],"type":"Point"}
}