{
  "type": "Feature",
  "properties": {
    "iso:country":"IN",
    "ks:ks_name":"Sewaripara",
    "ks:ks_pop":408,
    "ks:ks_type":"HABITATION",
    "name:eng_x_preferred":[
        "Sewaripara"
    ],
    "wof:name":"Sewaripara",
    "wof:placetype":"locality",
    "wof:population":408
},
  "geometry": {"coordinates":[82.91565,23.515086],"type":"Point"}
}