{
  "type": "Feature",
  "properties": {
    "gn:admin1_code":"11.0",
    "gn:admin2_code":"33.0",
    "gn:asciiname":"Katar",
    "gn:country_code":"IN",
    "gn:dem":1649,
    "gn:feature_class":"P",
    "gn:feature_code":"PPL",
    "gn:name":"Kat\u0101r",
    "gn:population":0,
    "gn:timezone":"Asia/Kolkata",
    "iso:country":"IN",
    "name:bar_x_preferred":[
        "Katar"
    ],
    "name:ceb_x_preferred":[
        "Katar"
    ],
    "name:ces_x_preferred":[
        "Katar"
    ],
    "name:deu_x_preferred":[
        "Katar"
    ],
    "name:epo_x_preferred":[
        "Kataro"
    ],
    "name:heb_x_preferred":[
        "\u05e7\u05d8\u05e8"
    ],
    "name:jpn_x_preferred":[
        "\u30ab\u30bf\u30fc\u30eb"
    ],
    "name:pol_x_preferred":[
        "Katar"
    ],
    "name:rus_x_preferred":[
        "\u041a\u0430\u0442\u0430\u0440"
    ],
    "name:slk_x_preferred":[
        "Katar"
    ],
    "name:swe_x_preferred":[
        "Katar"
    ],
    "name:ukr_x_preferred":[
        "\u041a\u0430\u0442\u0430\u0440"
    ],
    "wof:name":"Katar",
    "wof:placetype":"locality"
},
  "geometry": {"coordinates":[77.42966,31.30118],"type":"Point"}
}