{
  "type": "Feature",
  "properties": {
    "iso:country":"IN",
    "ks:ks_name":"Shahpur Matiyo",
    "ks:ks_pop":590,
    "ks:ks_type":"VILLAGE",
    "name:eng_x_preferred":[
        "Shahpur Matiyo"
    ],
    "wof:name":"Shahpur Matiyo",
    "wof:placetype":"locality",
    "wof:population":590
},
  "geometry": {"coordinates":[85.172865,24.952918],"type":"Point"}
}