{
  "type": "Feature",
  "properties": {
    "iso:country":"IN",
    "ks:ks_name":"Torakarwadi",
    "ks:ks_pop":386,
    "ks:ks_type":"HABITATION",
    "name:eng_x_preferred":[
        "Torakarwadi"
    ],
    "wof:name":"Torakarwadi",
    "wof:placetype":"locality",
    "wof:population":386
},
  "geometry": {"coordinates":[74.982843,18.676203],"type":"Point"}
}