{
  "type": "Feature",
  "properties": {
    "gn:admin1_code":"34.0",
    "gn:admin2_code":"204.0",
    "gn:asciiname":"Misir",
    "gn:country_code":"IN",
    "gn:dem":70,
    "gn:feature_class":"P",
    "gn:feature_code":"PPL",
    "gn:name":"Misir",
    "gn:population":0,
    "gn:timezone":"Asia/Kolkata",
    "iso:country":"IN",
    "name:ron_x_preferred":[
        "R\u00e2ul Misir"
    ],
    "wof:name":"Misir",
    "wof:placetype":"locality"
},
  "geometry": {"coordinates":[84.70435000000001,26.57974],"type":"Point"}
}