{
  "type": "Feature",
  "properties": {
    "iso:country":"IN",
    "ks:ks_name":"Mudhukulam",
    "ks:ks_pop":1271,
    "ks:ks_type":"HABITATION",
    "name:eng_x_preferred":[
        "Mudhukulam"
    ],
    "wof:name":"Mudhukulam",
    "wof:placetype":"locality",
    "wof:population":1271
},
  "geometry": {"coordinates":[79.02101500000001,10.577028],"type":"Point"}
}