{
  "type": "Feature",
  "properties": {
    "iso:country":"IN",
    "ks:ks_name":"Pesalpara",
    "ks:ks_pop":183,
    "ks:ks_type":"HABITATION",
    "name:eng_x_preferred":[
        "Pesalpara"
    ],
    "wof:name":"Pesalpara",
    "wof:placetype":"locality",
    "wof:population":183
},
  "geometry": {"coordinates":[81.480127,18.455539],"type":"Point"}
}