{
  "type": "Feature",
  "properties": {
    "gn:admin1_code":"34.0",
    "gn:admin2_code":"217.0",
    "gn:asciiname":"Nawada Chatur Bagaha",
    "gn:country_code":"IN",
    "gn:dem":75,
    "gn:feature_class":"P",
    "gn:feature_code":"PPL",
    "gn:name":"Nawada Chatur Bagaha",
    "gn:population":0,
    "gn:timezone":"Asia/Kolkata",
    "iso:country":"IN",
    "ks:ks_name":"Nawada Chatur Bagaha",
    "ks:ks_type":"VILLAGE",
    "ks:ks_uagg_main":0,
    "name:eng_x_preferred":[
        "Nawada Chatur Bagaha"
    ],
    "wof:name":"Nawada Chatur Bagaha",
    "wof:placetype":"locality"
},
  "geometry": {"coordinates":[84.41848899999999,26.528511],"type":"Point"}
}