{
  "type": "Feature",
  "properties": {
    "iso:country":"IN",
    "ks:ks_name":"Khanch",
    "ks:ks_pop":396,
    "ks:ks_type":"HABITATION",
    "name:eng_x_preferred":[
        "Khanch"
    ],
    "wof:name":"Khanch",
    "wof:placetype":"locality",
    "wof:population":396
},
  "geometry": {"coordinates":[78.57593900000001,24.934409],"type":"Point"}
}