{
  "type": "Feature",
  "properties": {
    "gn:admin1_code":"25.0",
    "gn:admin2_code":"610.0",
    "gn:asciiname":"Sadapperiyakavundanur",
    "gn:country_code":"IN",
    "gn:dem":202,
    "gn:feature_class":"P",
    "gn:feature_code":"PPL",
    "gn:name":"Sad\u0101pperiyakavundan\u016br",
    "gn:population":0,
    "gn:timezone":"Asia/Kolkata",
    "iso:country":"IN",
    "wof:name":"Sadapperiyakavundanur",
    "wof:placetype":"locality"
},
  "geometry": {"coordinates":[77.71226999999998,11.61857],"type":"Point"}
}