{
  "type": "Feature",
  "properties": {
    "gn:admin1_code":"33",
    "gn:admin2_code":"586.0",
    "gn:asciiname":"Sulcorna",
    "gn:country_code":"IN",
    "gn:dem":137,
    "gn:feature_class":"P",
    "gn:feature_code":"PPL",
    "gn:name":"Sulcorna",
    "gn:population":0,
    "gn:timezone":"Asia/Kolkata",
    "iso:country":"IN",
    "ks:ks_name":"Sulcorna",
    "ks:ks_pop":638,
    "ks:ks_type":"VILLAGE",
    "name:eng_x_preferred":[
        "Sulcorna"
    ],
    "wof:name":"Sulcorna",
    "wof:placetype":"locality",
    "wof:population":638
},
  "geometry": {"coordinates":[74.172905,15.10423],"type":"Point"}
}