{
  "type": "Feature",
  "properties": {
    "iso:country":"IN",
    "ks:ks_name":"Panbari",
    "ks:ks_pop":141,
    "ks:ks_type":"HABITATION",
    "name:eng_x_preferred":[
        "Panbari"
    ],
    "wof:name":"Panbari",
    "wof:placetype":"locality",
    "wof:population":141
},
  "geometry": {"coordinates":[91.22819800000001,25.780966],"type":"Point"}
}