{
  "type": "Feature",
  "properties": {
    "iso:country":"IN",
    "ks:ks_name":"Kochare",
    "ks:ks_pop":36,
    "ks:ks_type":"HABITATION",
    "name:eng_x_preferred":[
        "Kochare"
    ],
    "wof:name":"Kochare",
    "wof:placetype":"locality",
    "wof:population":36
},
  "geometry": {"coordinates":[74.46267400000001,14.539032],"type":"Point"}
}