{
  "type": "Feature",
  "properties": {
    "iso:country":"IN",
    "ks:ks_name":"Jamahar",
    "ks:ks_pop":2459,
    "ks:ks_type":"HABITATION",
    "name:eng_x_preferred":[
        "Jamahar"
    ],
    "wof:name":"Jamahar",
    "wof:placetype":"neighbourhood",
    "wof:population":2459
},
  "geometry": {"coordinates":[78.173703,26.27982],"type":"Point"}
}