{
  "type": "Feature",
  "properties": {
    "iso:country":"IN",
    "ks:ks_name":"Raniganj",
    "ks:ks_type":"VILLAGE",
    "ks:ks_uagg_main":0,
    "name:eng_x_preferred":[
        "Raniganj"
    ],
    "wof:name":"Raniganj",
    "wof:placetype":"neighbourhood"
},
  "geometry": {"coordinates":[87.905784,25.853137],"type":"Point"}
}