{
  "type": "Feature",
  "properties": {
    "iso:country":"IN",
    "ks:ks_name":"Sundro",
    "ks:ks_pop":706,
    "ks:ks_type":"VILLAGE",
    "name:eng_x_preferred":[
        "Sundro"
    ],
    "wof:name":"Sundro",
    "wof:placetype":"locality",
    "wof:population":706
},
  "geometry": {"coordinates":[85.998242,23.534885],"type":"Point"}
}