{
  "type": "Feature",
  "properties": {
    "gn:admin1_code":"40",
    "gn:admin2_code":"539.0",
    "gn:asciiname":"Zillah Parishad",
    "gn:country_code":"IN",
    "gn:dem":320,
    "gn:feature_class":"P",
    "gn:feature_code":"PPL",
    "gn:name":"Zillah Parishad",
    "gn:population":0,
    "gn:timezone":"Asia/Kolkata",
    "iso:country":"IN",
    "wof:name":"Zillah Parishad",
    "wof:placetype":"locality"
},
  "geometry": {"coordinates":[79.09071,17.28456],"type":"Point"}
}