{
  "type": "Feature",
  "properties": {
    "iso:country":"IN",
    "ks:ks_name":"Barad Pichra",
    "ks:ks_pop":250,
    "ks:ks_type":"VILLAGE",
    "name:eng_x_preferred":[
        "Barad Pichra"
    ],
    "wof:name":"Barad Pichra",
    "wof:placetype":"locality",
    "wof:population":250
},
  "geometry": {"coordinates":[86.194801,24.641385],"type":"Point"}
}