{
  "type": "Feature",
  "properties": {
    "iso:country":"IN",
    "ks:ks_alt_nam":"K\u0101d\u0101lbera",
    "ks:ks_name":"Kadalbera",
    "ks:ks_pop":182,
    "ks:ks_type":"VILLAGE",
    "name:eng_x_preferred":[
        "Kadalbera"
    ],
    "name:eng_x_variant":[
        "K\u0101d\u0101lbera"
    ],
    "wof:name":"Kadalbera",
    "wof:placetype":"locality",
    "wof:population":182
},
  "geometry": {"coordinates":[85.882181,22.476794],"type":"Point"}
}