{
  "type": "Feature",
  "properties": {
    "gn:admin1_code":"16",
    "gn:admin2_code":"509.0",
    "gn:asciiname":"Kitadi",
    "gn:country_code":"IN",
    "gn:dem":192,
    "gn:feature_class":"P",
    "gn:feature_code":"PPL",
    "gn:name":"Kit\u0101di",
    "gn:population":0,
    "gn:timezone":"Asia/Kolkata",
    "iso:country":"IN",
    "name:und_x_variant":[
        "Kit\u0101di",
        "Dhorgh\u0101t"
    ],
    "wof:name":"Kitadi",
    "wof:placetype":"locality"
},
  "geometry": {"coordinates":[79.29745,20.05351],"type":"Point"}
}