{
  "type": "Feature",
  "properties": {
    "gn:admin1_code":"19",
    "gn:admin2_code":"579.0",
    "gn:asciiname":"Anwar",
    "gn:country_code":"IN",
    "gn:dem":449,
    "gn:feature_class":"P",
    "gn:feature_code":"PPL",
    "gn:name":"Anw\u0101r",
    "gn:population":0,
    "gn:timezone":"Asia/Kolkata",
    "iso:country":"IN",
    "name:aze_x_preferred":[
        "\u018fnv\u0259r"
    ],
    "name:ceb_x_preferred":[
        "Anwar"
    ],
    "name:deu_x_preferred":[
        "Anwar"
    ],
    "name:fra_x_preferred":[
        "Anwar"
    ],
    "name:hin_x_preferred":[
        "\u0905\u0928\u0935\u0930"
    ],
    "name:jpn_x_preferred":[
        "\u30a2\u30f3\u30ef\u30eb"
    ],
    "name:nld_x_preferred":[
        "Anwar"
    ],
    "name:rus_x_preferred":[
        "\u0410\u043d\u0432\u0430\u0440"
    ],
    "name:swe_x_preferred":[
        "Anwar"
    ],
    "name:vie_x_preferred":[
        "Anwar"
    ],
    "wof:name":"Anwar",
    "wof:placetype":"locality"
},
  "geometry": {"coordinates":[77.4171,17.40902],"type":"Point"}
}