{
  "type": "Feature",
  "properties": {
    "iso:country":"IN",
    "ks:ks_name":"Gunu",
    "ks:ks_pop":498,
    "ks:ks_type":"VILLAGE",
    "name:eng_x_preferred":[
        "Gunu"
    ],
    "wof:name":"Gunu",
    "wof:placetype":"locality",
    "wof:population":498
},
  "geometry": {"coordinates":[83.489339,22.325893],"type":"Point"}
}