{
  "type": "Feature",
  "properties": {
    "iso:country":"IN",
    "ks:ks_name":"Podelti",
    "ks:ks_pop":114,
    "ks:ks_type":"HABITATION",
    "name:eng_x_preferred":[
        "Podelti"
    ],
    "wof:name":"Podelti",
    "wof:placetype":"locality",
    "wof:population":114
},
  "geometry": {"coordinates":[82.87188399999999,18.104359],"type":"Point"}
}