{
  "type": "Feature",
  "properties": {
    "iso:country":"IN",
    "ks:ks_name":"Nali",
    "ks:ks_pop":754,
    "ks:ks_type":"VILLAGE",
    "name:eng_x_preferred":[
        "Nali"
    ],
    "wof:name":"Nali",
    "wof:placetype":"locality",
    "wof:population":754
},
  "geometry": {"coordinates":[80.08144799999999,29.558036],"type":"Point"}
}