{
  "type": "Feature",
  "properties": {
    "gn:country":"IN",
    "gn:fcode":"PPL",
    "gn:pop":48036,
    "iso:country":"IN",
    "name:unk_x_variant":[
        "Shri Dungargarh"
    ],
    "qs:name":"Sri Dungargarh",
    "qs:photos_9r":0,
    "qs:photos_sr":0,
    "qs:pop_sr":"7",
    "wd:wordcount":19,
    "wof:name":"Sri Dungargarh",
    "wof:placetype":"locality",
    "wof:population":48036
},
  "geometry": {"coordinates":[74.00937,28.09712],"type":"Point"}
}