{
  "type": "Feature",
  "properties": {
    "gn:country":"IN",
    "gn:fcode":"PPL",
    "gn:population":48036,
    "iso:country":"IN",
    "name:ben_x_preferred":[
        "\u09a6\u09c1\u0999\u09cd\u0997\u09be\u09b0\u0997\u09a1\u09bc"
    ],
    "name:bpy_x_preferred":[
        "\u09a6\u09c1\u0999\u09cd\u0997\u09be\u09b0\u0997\u09a1\u09bc"
    ],
    "name:ceb_x_preferred":[
        "Sri D\u016bngargarh"
    ],
    "name:deu_x_preferred":[
        "Dungargarh"
    ],
    "name:eng_x_preferred":[
        "Dungargarh"
    ],
    "name:fra_x_preferred":[
        "Dungargarh"
    ],
    "name:guj_x_preferred":[
        "\u0aa1\u0ac1\u0a82\u0a97\u0ab0\u0a97\u0aa2"
    ],
    "name:hin_x_preferred":[
        "\u0936\u094d\u0930\u0940 \u0921\u0942\u0902\u0917\u0930\u0917\u0922\u093c"
    ],
    "name:ita_x_preferred":[
        "Dungargarh"
    ],
    "name:jpn_x_preferred":[
        "\u30c9\u30a5\u30f3\u30ac\u30fc\u30ac\u30fc"
    ],
    "name:kan_x_preferred":[
        "\u0ca6\u0cc1\u0c82\u0c97\u0cbe\u0cb0\u0ccd\u0c97\u0ca2\u0ccd"
    ],
    "name:kor_x_preferred":[
        "\ub465\uac00\ub974\uac00\ub974"
    ],
    "name:mlg_x_preferred":[
        "Dungargarh"
    ],
    "name:msa_x_preferred":[
        "Dungamal"
    ],
    "name:new_x_preferred":[
        "\u0926\u0941\u0902\u0917\u0930\u0917\u0922"
    ],
    "name:nld_x_preferred":[
        "Dungargarh"
    ],
    "name:por_x_preferred":[
        "Dungargarh"
    ],
    "name:rus_x_preferred":[
        "\u0414\u0443\u043d\u0433\u0430\u0440\u0433\u0430\u0440\u0445"
    ],
    "name:spa_x_preferred":[
        "Dungargarh"
    ],
    "name:swe_x_preferred":[
        "Sri D\u016bngargarh"
    ],
    "name:tam_x_preferred":[
        "\u0b9f\u0bc1\u0ba3\u0bcd\u0b95\u0bb0\u0bcd\u0b95\u0bb0\u0bcd\u0bb9\u0bcd"
    ],
    "name:tel_x_preferred":[
        "\u0c26\u0c41\u0c02\u0c17\u0c3e\u0c30\u0c4d \u0c18\u0c30\u0c4d"
    ],
    "name:und_x_variant":[
        "Shri Dungargarh"
    ],
    "name:urd_x_preferred":[
        "\u062f\u0648\u0646\u062c\u0627\u0631\u06af\u0691\u06be"
    ],
    "name:vie_x_preferred":[
        "Dungargarh"
    ],
    "name:zho_x_preferred":[
        "\u4e1c\u683c\u963f\u5c14\u52a0\u5c14"
    ],
    "qs:name":"Sri Dungargarh",
    "qs:photos_9r":0,
    "qs:photos_sr":0,
    "qs:pop_sr":"7",
    "wd:wordcount":19,
    "wof:name":"Sri Dungargarh",
    "wof:placetype":"locality",
    "wof:population":48036
},
  "geometry": {"coordinates":[74.00937,28.09712],"type":"Point"}
}