{
  "type": "Feature",
  "properties": {
    "gn:admin1_code":"25.0",
    "gn:admin2_code":"633.0",
    "gn:asciiname":"Varadappakkavundanpudur",
    "gn:country_code":"IN",
    "gn:dem":293,
    "gn:feature_class":"P",
    "gn:feature_code":"PPL",
    "gn:name":"Varadappakkavundanpud\u016br",
    "gn:population":0,
    "gn:timezone":"Asia/Kolkata",
    "iso:country":"IN",
    "wof:name":"Varadappakkavundanpudur",
    "wof:placetype":"locality"
},
  "geometry": {"coordinates":[77.58065000000001,11.0415],"type":"Point"}
}