{
  "type": "Feature",
  "properties": {
    "iso:country":"IN",
    "ks:ks_name":"Lakhan",
    "ks:ks_pop":45,
    "ks:ks_type":"VILLAGE",
    "name:eng_x_preferred":[
        "Lakhan"
    ],
    "wof:name":"Lakhan",
    "wof:placetype":"locality",
    "wof:population":45
},
  "geometry": {"coordinates":[79.46442999999999,30.006136],"type":"Point"}
}