{
  "type": "Feature",
  "properties": {
    "gn:admin1_code":"23.0",
    "gn:admin2_code":"54.0",
    "gn:asciiname":"Tapa",
    "gn:country_code":"IN",
    "gn:dem":224,
    "gn:feature_class":"P",
    "gn:feature_code":"PPL",
    "gn:name":"Tapa",
    "gn:population":0,
    "gn:timezone":"Asia/Kolkata",
    "iso:country":"IN",
    "name:ben_x_preferred":[
        "\u09a4\u09be\u09aa\u09cd\u09aa\u09be"
    ],
    "name:bpy_x_preferred":[
        "\u09a4\u09be\u09aa\u09cd\u09aa\u09be"
    ],
    "name:cat_x_preferred":[
        "Tappa"
    ],
    "name:ita_x_preferred":[
        "Tapa"
    ],
    "name:msa_x_preferred":[
        "Tappa"
    ],
    "name:nld_x_preferred":[
        "Tappa"
    ],
    "name:por_x_preferred":[
        "Tappa"
    ],
    "name:spa_x_preferred":[
        "Tappa"
    ],
    "name:vie_x_preferred":[
        "Tappa"
    ],
    "wof:name":"Tapa",
    "wof:placetype":"locality"
},
  "geometry": {"coordinates":[75.36936,30.29794],"type":"Point"}
}