{
  "type": "Feature",
  "properties": {
    "iso:country":"IN",
    "ks:ks_name":"Gopalsahi",
    "ks:ks_pop":172,
    "ks:ks_type":"HABITATION",
    "name:eng_x_preferred":[
        "Gopalsahi"
    ],
    "wof:name":"Gopalsahi",
    "wof:placetype":"locality",
    "wof:population":172
},
  "geometry": {"coordinates":[86.03879999999999,21.153021],"type":"Point"}
}