{
  "type": "Feature",
  "properties": {
    "iso:country":"IN",
    "ks:ks_name":"Khaira",
    "ks:ks_type":"VILLAGE",
    "ks:ks_uagg_main":0,
    "name:eng_x_preferred":[
        "Khaira"
    ],
    "wof:name":"Khaira",
    "wof:placetype":"neighbourhood"
},
  "geometry": {"coordinates":[83.06954399999999,26.516732],"type":"Point"}
}