{
  "type": "Feature",
  "properties": {
    "iso:country":"IN",
    "ks:ks_name":"Erikula Colony",
    "ks:ks_pop":203,
    "ks:ks_type":"HABITATION",
    "name:eng_x_preferred":[
        "Erikula Colony"
    ],
    "wof:name":"Erikula Colony",
    "wof:placetype":"locality",
    "wof:population":203
},
  "geometry": {"coordinates":[79.741354,13.650931],"type":"Point"}
}