{
  "type": "Feature",
  "properties": {
    "iso:country":"IN",
    "ks:ks_name":"Dongewasti",
    "ks:ks_pop":134,
    "ks:ks_type":"HABITATION",
    "name:eng_x_preferred":[
        "Dongewasti"
    ],
    "wof:name":"Dongewasti",
    "wof:placetype":"locality",
    "wof:population":134
},
  "geometry": {"coordinates":[74.20462999999999,19.689469],"type":"Point"}
}