{
  "type": "Feature",
  "properties": {
    "iso:country":"IN",
    "ks:ks_name":"Shanti Nagar",
    "ks:ks_pop":1303,
    "ks:ks_type":"HABITATION",
    "name:eng_x_preferred":[
        "Shanti Nagar"
    ],
    "wof:name":"Shanti Nagar",
    "wof:placetype":"locality",
    "wof:population":1303
},
  "geometry": {"coordinates":[84.88569,25.645273],"type":"Point"}
}