{
  "type": "Feature",
  "properties": {
    "gn:admin1_code":"39.0",
    "gn:admin2_code":"64.0",
    "gn:asciiname":"Rewari",
    "gn:country_code":"IN",
    "gn:dem":1129,
    "gn:feature_class":"P",
    "gn:feature_code":"PPL",
    "gn:name":"Rew\u0101ri",
    "gn:population":0,
    "gn:timezone":"Asia/Kolkata",
    "iso:country":"IN",
    "name:ara_x_preferred":[
        "\u0631\u0648\u0627\u0631\u064a"
    ],
    "name:aze_x_preferred":[
        "Revari"
    ],
    "name:ben_bn_x_preferred":[
        "\u09b0\u09c7\u0993\u09af\u09bc\u09be\u09b0\u09c0"
    ],
    "name:ben_in_x_preferred":[
        "\u09b0\u09c7\u0993\u09af\u09bc\u09be\u09b0\u09c0"
    ],
    "name:ben_x_preferred":[
        "\u09b0\u09c7\u0993\u09af\u09bc\u09be\u09b0\u09c0"
    ],
    "name:bih_x_preferred":[
        "\u0930\u0947\u0935\u093e\u0921\u093c\u0940"
    ],
    "name:bpy_x_preferred":[
        "\u09b0\u09c7\u09f1\u09be\u09b0\u09c0"
    ],
    "name:cat_x_preferred":[
        "Rewari"
    ],
    "name:ceb_x_preferred":[
        "Rew\u0101ri"
    ],
    "name:deu_x_preferred":[
        "Rewari"
    ],
    "name:epo_x_preferred":[
        "Re\u016dari"
    ],
    "name:fra_x_preferred":[
        "Rewari"
    ],
    "name:guj_x_preferred":[
        "\u0ab0\u0ac7\u0ab5\u0abe\u0ab0\u0ac0"
    ],
    "name:hin_x_preferred":[
        "\u0930\u0947\u0935\u093e\u095c\u0940"
    ],
    "name:hin_x_variant":[
        "\u0930\u0947\u0935\u093e\u0921\u093c\u0940"
    ],
    "name:ita_x_preferred":[
        "Rewari"
    ],
    "name:jpn_x_preferred":[
        "\u30ec\u30fc\u30ef\u30fc\u30ea\u30fc"
    ],
    "name:kan_x_preferred":[
        "\u0cb0\u0cc6\u0cb5\u0cbe\u0cb0\u0cbf"
    ],
    "name:mal_x_preferred":[
        "\u0d30\u0d47\u0d35\u0d3e\u0d30\u0d3f"
    ],
    "name:mar_x_preferred":[
        "\u0930\u0947\u0935\u093e\u0921\u0940"
    ],
    "name:mlg_x_preferred":[
        "Rewari"
    ],
    "name:msa_x_preferred":[
        "Rewari"
    ],
    "name:nep_x_preferred":[
        "\u0930\u0947\u0935\u093e\u0921\u093c\u0940"
    ],
    "name:nld_x_preferred":[
        "Rewari"
    ],
    "name:ori_x_preferred":[
        "\u0b30\u0b47\u0b71\u0b3e\u0b30\u0b3f"
    ],
    "name:pan_x_preferred":[
        "\u0a30\u0a3f\u0a35\u0a3e\u0a5c\u0a40"
    ],
    "name:pol_x_preferred":[
        "Rewari"
    ],
    "name:rus_x_preferred":[
        "\u0420\u0435\u0432\u0430\u0440\u0438"
    ],
    "name:san_x_preferred":[
        "\u0930\u0947\u0935\u093e\u0921\u0940"
    ],
    "name:spa_x_preferred":[
        "Rewari"
    ],
    "name:swe_x_preferred":[
        "Rewari"
    ],
    "name:tam_x_preferred":[
        "\u0bb0\u0bc7\u0bb5\u0bbe\u0bb0\u0bbf"
    ],
    "name:tel_x_preferred":[
        "\u0c30\u0c47\u0c35\u0c3e\u0c30\u0c3f"
    ],
    "name:urd_x_preferred":[
        "\u0631\u06cc\u0648\u0627\u0691\u06cc"
    ],
    "name:vie_x_preferred":[
        "Rewari"
    ],
    "wof:name":"Rewari",
    "wof:placetype":"locality"
},
  "geometry": {"coordinates":[79.34617,29.93948],"type":"Point"}
}