{
  "type": "Feature",
  "properties": {
    "iso:country":"IN",
    "ks:ks_name":"Mehkhed",
    "ks:ks_pop":12,
    "ks:ks_type":"HABITATION",
    "name:eng_x_preferred":[
        "Mehkhed"
    ],
    "wof:name":"Mehkhed",
    "wof:placetype":"locality",
    "wof:population":12
},
  "geometry": {"coordinates":[76.912373,21.139481],"type":"Point"}
}