{
  "type": "Feature",
  "properties": {
    "gn:country":"IN",
    "gn:fcode":"PPLX",
    "gn:population":0,
    "iso:country":"IN",
    "name:ben_x_preferred":[
        "\u09b0\u09be\u09af\u09bc\u09aa\u09c7\u099f\u09cd\u099f\u09be"
    ],
    "name:eng_x_preferred":[
        "Royapettah"
    ],
    "name:nld_x_preferred":[
        "Royapettah"
    ],
    "name:tam_x_preferred":[
        "\u0bb0\u0bbe\u0baf\u0baa\u0bcd\u0baa\u0bc7\u0b9f\u0bcd\u0b9f\u0bc8"
    ],
    "qs:name":"Royapettah",
    "qs:name_adm0":"India",
    "qs:name_adm1":"Tamil Nadu",
    "qs:photos":241,
    "qs:photos_1k":49,
    "qs:photos_9k":1,
    "qs:photos_9r":4,
    "qs:photos_all":241,
    "qs:photos_sr":4,
    "qs:placetype":"Suburb",
    "qs:pop_sr":"0",
    "wd:wordcount":36,
    "wof:name":"Royapettah",
    "wof:placetype":"neighbourhood",
    "wof:population":0
},
  "geometry": {"coordinates":[80.26416999999999,13.05056],"type":"Point"}
}