{
  "type": "Feature",
  "properties": {
    "iso:country":"IN",
    "ks:ks_alt_nam":"5 ND",
    "ks:ks_name":"5 Nd",
    "ks:ks_pop":9,
    "ks:ks_type":"HABITATION",
    "name:eng_x_preferred":[
        "5 Nd"
    ],
    "wof:name":"5 Nd",
    "wof:placetype":"locality",
    "wof:population":9
},
  "geometry": {"coordinates":[73.35638899999999,29.061944],"type":"Point"}
}