{
  "type": "Feature",
  "properties": {
    "iso:country":"IN",
    "ks:ks_name":"Hebeda Bongali Gaon",
    "ks:ks_pop":382,
    "ks:ks_type":"VILLAGE",
    "ks:ks_uagg_main":0,
    "name:eng_x_preferred":[
        "Hebeda Bongali Gaon"
    ],
    "wof:name":"Hebeda Bongali Gaon",
    "wof:placetype":"neighbourhood",
    "wof:population":382
},
  "geometry": {"coordinates":[95.42881199999999,27.468872],"type":"Point"}
}