{
  "type": "Feature",
  "properties": {
    "iso:country":"IN",
    "ks:ks_name":"Kembaradoddy",
    "ks:ks_pop":98,
    "ks:ks_type":"HABITATION",
    "name:eng_x_preferred":[
        "Kembaradoddy"
    ],
    "wof:name":"Kembaradoddy",
    "wof:placetype":"locality",
    "wof:population":98
},
  "geometry": {"coordinates":[77.645777,12.466868],"type":"Point"}
}