{
  "type": "Feature",
  "properties": {
    "iso:country":"IN",
    "ks:ks_name":"Barjo",
    "ks:ks_pop":316,
    "ks:ks_type":"VILLAGE",
    "name:eng_x_preferred":[
        "Barjo"
    ],
    "wof:name":"Barjo",
    "wof:placetype":"locality",
    "wof:population":316
},
  "geometry": {"coordinates":[85.25886300000001,22.818597],"type":"Point"}
}