{
  "type": "Feature",
  "properties": {
    "iso:country":"IN",
    "ks:ks_name":"Dhodhia",
    "ks:ks_pop":66,
    "ks:ks_type":"HABITATION",
    "name:eng_x_preferred":[
        "Dhodhia"
    ],
    "wof:name":"Dhodhia",
    "wof:placetype":"locality",
    "wof:population":66
},
  "geometry": {"coordinates":[86.500928,24.502809],"type":"Point"}
}