{
  "type": "Feature",
  "properties": {
    "gn:admin1_code":"25",
    "gn:admin2_code":"604.0",
    "gn:asciiname":"Muttigainallankuppam",
    "gn:country_code":"IN",
    "gn:dem":34,
    "gn:feature_class":"P",
    "gn:feature_code":"PPL",
    "gn:name":"Muttigainall\u0101nkuppam",
    "gn:population":0,
    "gn:timezone":"Asia/Kolkata",
    "iso:country":"IN",
    "wof:name":"Muttigainallankuppam",
    "wof:placetype":"neighbourhood"
},
  "geometry": {"coordinates":[80.05483,12.59392],"type":"Point"}
}