{
  "type": "Feature",
  "properties": {
    "gn:admin1_code":"36",
    "gn:admin2_code":"194.0",
    "gn:asciiname":"Sar Sara Muafi",
    "gn:country_code":"IN",
    "gn:dem":92,
    "gn:feature_class":"P",
    "gn:feature_code":"PPL",
    "gn:name":"Sar Sar\u0101 Mu\u0101f\u012b",
    "gn:population":0,
    "gn:timezone":"Asia/Kolkata",
    "iso:country":"IN",
    "wof:name":"Sar Sara Muafi",
    "wof:placetype":"neighbourhood"
},
  "geometry": {"coordinates":[82.46749,25.56675],"type":"Point"}
}