{
  "type": "Feature",
  "properties": {
    "iso:country":"IN",
    "ks:ks_name":"Kallali",
    "ks:ks_pop":1452,
    "ks:ks_type":"HABITATION",
    "name:eng_x_preferred":[
        "Kallali"
    ],
    "wof:name":"Kallali",
    "wof:placetype":"locality",
    "wof:population":1452
},
  "geometry": {"coordinates":[75.096784,12.473682],"type":"Point"}
}