{
  "type": "Feature",
  "properties": {
    "iso:country":"IN",
    "ks:ks_name":"Ohwa",
    "ks:ks_pop":1187,
    "ks:ks_type":"VILLAGE",
    "name:eng_x_preferred":[
        "Ohwa"
    ],
    "wof:name":"Ohwa",
    "wof:placetype":"locality",
    "wof:population":1187
},
  "geometry": {"coordinates":[73.948077,21.665039],"type":"Point"}
}