{
  "type": "Feature",
  "properties": {
    "gn:admin1_code":"11.0",
    "gn:admin2_code":"32.0",
    "gn:asciiname":"Paure Sunal",
    "gn:country_code":"IN",
    "gn:dem":2050,
    "gn:feature_class":"P",
    "gn:feature_code":"PPL",
    "gn:name":"Paure Sunal",
    "gn:population":0,
    "gn:timezone":"Asia/Kolkata",
    "iso:country":"IN",
    "wof:name":"Paure Sunal",
    "wof:placetype":"locality"
},
  "geometry": {"coordinates":[77.61735999999998,30.69939],"type":"Point"}
}