{
  "type": "Feature",
  "properties": {
    "iso:country":"IN",
    "ks:ks_name":"Suntaradoddi",
    "ks:ks_pop":66,
    "ks:ks_type":"HABITATION",
    "name:eng_x_preferred":[
        "Suntaradoddi"
    ],
    "wof:name":"Suntaradoddi",
    "wof:placetype":"locality",
    "wof:population":66
},
  "geometry": {"coordinates":[77.469711,12.555874],"type":"Point"}
}