{
  "type": "Feature",
  "properties": {
    "iso:country":"IN",
    "ks:ks_name":"School Purwa",
    "ks:ks_pop":143,
    "ks:ks_type":"HABITATION",
    "name:eng_x_preferred":[
        "School Purwa"
    ],
    "wof:name":"School Purwa",
    "wof:placetype":"locality",
    "wof:population":143
},
  "geometry": {"coordinates":[81.526105,27.565685],"type":"Point"}
}