{
  "type": "Feature",
  "properties": {
    "gn:admin1_code":"36",
    "gn:admin2_code":"135.0",
    "gn:asciiname":"Khichri",
    "gn:country_code":"IN",
    "gn:dem":213,
    "gn:feature_class":"P",
    "gn:feature_code":"PPL",
    "gn:name":"Khichri",
    "gn:population":0,
    "gn:timezone":"Asia/Kolkata",
    "iso:country":"IN",
    "name:und_x_variant":[
        "S\u0101dikpur Mal\u016bkpur"
    ],
    "wof:name":"Khichri",
    "wof:placetype":"locality"
},
  "geometry": {"coordinates":[78.58663,29.02714000000001],"type":"Point"}
}