{
  "type": "Feature",
  "properties": {
    "iso:country":"IN",
    "ks:ks_name":"Gangemane",
    "ks:ks_pop":13,
    "ks:ks_type":"HABITATION",
    "name:eng_x_preferred":[
        "Gangemane"
    ],
    "wof:name":"Gangemane",
    "wof:placetype":"locality",
    "wof:population":13
},
  "geometry": {"coordinates":[74.68277999999999,14.92204],"type":"Point"}
}