{
  "type": "Feature",
  "properties": {
    "iso:country":"IN",
    "ks:ks_name":"Naron",
    "ks:ks_pop":663,
    "ks:ks_type":"VILLAGE",
    "name:eng_x_preferred":[
        "Naron"
    ],
    "wof:name":"Naron",
    "wof:placetype":"locality",
    "wof:population":663
},
  "geometry": {"coordinates":[78.109061,24.657484],"type":"Point"}
}