{
  "type": "Feature",
  "properties": {
    "gn:admin1_code":"40",
    "gn:admin2_code":"533.0",
    "gn:asciiname":"Akbarnagar",
    "gn:country_code":"IN",
    "gn:dem":397,
    "gn:feature_class":"P",
    "gn:feature_code":"PPL",
    "gn:name":"Akbarnagar",
    "gn:population":0,
    "gn:timezone":"Asia/Kolkata",
    "iso:country":"IN",
    "name:und_x_variant":[
        "V\u012br\u0101pur"
    ],
    "wof:name":"Akbarnagar",
    "wof:placetype":"locality"
},
  "geometry": {"coordinates":[77.88313000000002,18.56096],"type":"Point"}
}