{
  "type": "Feature",
  "properties": {
    "gn:admin1_code":"35.0",
    "gn:admin2_code":"441",
    "gn:asciiname":"Chirmira",
    "gn:country_code":"IN",
    "gn:dem":443,
    "gn:feature_class":"P",
    "gn:feature_code":"PPL",
    "gn:name":"Chirmira",
    "gn:population":0,
    "gn:timezone":"Asia/Kolkata",
    "iso:country":"IN",
    "wof:name":"Chirmira",
    "wof:placetype":"locality"
},
  "geometry": {"coordinates":[75.51463000000003,21.39337],"type":"Point"}
}