{
  "type": "Feature",
  "properties": {
    "iso:country":"IN",
    "ks:ks_name":"Jazira Char Dumuria",
    "ks:ks_pop":1550,
    "ks:ks_type":"VILLAGE",
    "name:eng_x_preferred":[
        "Jazira Char Dumuria"
    ],
    "wof:name":"Jazira Char Dumuria",
    "wof:placetype":"locality",
    "wof:population":1550
},
  "geometry": {"coordinates":[88.48667399999999,24.321165],"type":"Point"}
}