{
  "type": "Feature",
  "properties": {
    "gn:admin1_code":"36",
    "gn:admin2_code":"178.0",
    "gn:asciiname":"Misrana",
    "gn:country_code":"IN",
    "gn:dem":86,
    "gn:feature_class":"P",
    "gn:feature_code":"PPL",
    "gn:name":"Misr\u0101na",
    "gn:population":0,
    "gn:timezone":"Asia/Kolkata",
    "iso:country":"IN",
    "ks:ks_name":"Mishrana",
    "ks:ks_pop":100,
    "ks:ks_type":"HABITATION",
    "name:eng_x_preferred":[
        "Mishrana"
    ],
    "name:eng_x_variant":[
        "Misrana"
    ],
    "wof:name":"Mishrana",
    "wof:placetype":"locality",
    "wof:population":100
},
  "geometry": {"coordinates":[82.82768799999999,26.191722],"type":"Point"}
}