{
  "type": "Feature",
  "properties": {
    "iso:country":"IN",
    "ks:ks_name":"Janak Dhari Singh Tola",
    "ks:ks_pop":363,
    "ks:ks_type":"HABITATION",
    "ks:ks_uagg_main":0,
    "name:eng_x_preferred":[
        "Janak Dhari Singh Tola"
    ],
    "wof:name":"Janak Dhari Singh Tola",
    "wof:placetype":"neighbourhood",
    "wof:population":363
},
  "geometry": {"coordinates":[85.222498,26.435443],"type":"Point"}
}