{
  "type": "Feature",
  "properties": {
    "iso:country":"IN",
    "ks:ks_name":"Awaspara",
    "ks:ks_pop":207,
    "ks:ks_type":"HABITATION",
    "name:eng_x_preferred":[
        "Awaspara"
    ],
    "wof:name":"Awaspara",
    "wof:placetype":"locality",
    "wof:population":207
},
  "geometry": {"coordinates":[81.80181399999999,18.473544],"type":"Point"}
}