{
  "type": "Feature",
  "properties": {
    "iso:country":"IN",
    "ks:ks_name":"Puduparaipatty",
    "ks:ks_pop":18,
    "ks:ks_type":"HABITATION",
    "name:eng_x_preferred":[
        "Puduparaipatty"
    ],
    "wof:name":"Puduparaipatty",
    "wof:placetype":"locality",
    "wof:population":18
},
  "geometry": {"coordinates":[77.680269,10.353062],"type":"Point"}
}