{
  "type": "Feature",
  "properties": {
    "iso:country":"IN",
    "ks:ks_name":"Motiori P.G.R",
    "ks:ks_pop":3,
    "ks:ks_type":"VILLAGE",
    "name:eng_x_preferred":[
        "Motiori P.G.R"
    ],
    "wof:name":"Motiori P.G.R",
    "wof:placetype":"locality",
    "wof:population":3
},
  "geometry": {"coordinates":[94.43425000000001,26.952913],"type":"Point"}
}