{
  "type": "Feature",
  "properties": {
    "iso:country":"IN",
    "ks:ks_name":"Bela Pemu",
    "ks:ks_pop":520,
    "ks:ks_type":"VILLAGE",
    "ks:ks_uagg_main":0,
    "name:eng_x_preferred":[
        "Bela Pemu"
    ],
    "wof:name":"Bela Pemu",
    "wof:placetype":"neighbourhood",
    "wof:population":520
},
  "geometry": {"coordinates":[87.033979,25.816006],"type":"Point"}
}