{
  "type": "Feature",
  "properties": {
    "gn:admin1_code":"25.0",
    "gn:admin2_code":"618.0",
    "gn:asciiname":"Irunjur",
    "gn:country_code":"IN",
    "gn:dem":8,
    "gn:feature_class":"P",
    "gn:feature_code":"PPL",
    "gn:name":"Irunj\u016br",
    "gn:population":0,
    "gn:timezone":"Asia/Kolkata",
    "iso:country":"IN",
    "wof:name":"Irunjur",
    "wof:placetype":"neighbourhood"
},
  "geometry": {"coordinates":[79.74057000000001,10.70738],"type":"Point"}
}