{
  "type": "Feature",
  "properties": {
    "iso:country":"IN",
    "ks:ks_alt_nam":"khairwadi",
    "ks:ks_name":"Khairwadi",
    "ks:ks_pop":498,
    "ks:ks_type":"HABITATION",
    "name:eng_x_preferred":[
        "Khairwadi"
    ],
    "wof:name":"Khairwadi",
    "wof:placetype":"locality",
    "wof:population":498
},
  "geometry": {"coordinates":[75.957025,16.115325],"type":"Point"}
}