{
  "type": "Feature",
  "properties": {
    "gn:admin1_code":"19.0",
    "gn:admin2_code":"560",
    "gn:asciiname":"Kinnal",
    "gn:cc2":"IN",
    "gn:country_code":"IN",
    "gn:dem":540,
    "gn:feature_class":"P",
    "gn:feature_code":"PPL",
    "gn:name":"Kinnal",
    "gn:population":0,
    "gn:timezone":"Asia/Kolkata",
    "iso:country":"IN",
    "name:und_x_variant":[
        "Kinhal",
        "Kinh\u0101lu"
    ],
    "wof:name":"Kinnal",
    "wof:placetype":"locality"
},
  "geometry": {"coordinates":[76.13929,15.44458],"type":"Point"}
}