{
  "type": "Feature",
  "properties": {
    "gn:admin1_code":"35.0",
    "gn:admin2_code":"454.0",
    "gn:asciiname":"Gunwahi",
    "gn:country_code":"IN",
    "gn:dem":607,
    "gn:feature_class":"P",
    "gn:feature_code":"PPL",
    "gn:name":"Gunw\u0101hi",
    "gn:population":0,
    "gn:timezone":"Asia/Kolkata",
    "iso:country":"IN",
    "name:und_x_variant":[
        "Gunw\u0101hi",
        "Dhanw\u0101hi"
    ],
    "wof:name":"Gunwahi",
    "wof:placetype":"locality"
},
  "geometry": {"coordinates":[80.80195000000001,22.70928],"type":"Point"}
}