{
  "type": "Feature",
  "properties": {
    "iso:country":"IN",
    "ks:ks_name":"Kaje",
    "ks:ks_pop":380,
    "ks:ks_type":"HABITATION",
    "name:eng_x_preferred":[
        "Kaje"
    ],
    "wof:name":"Kaje",
    "wof:placetype":"locality",
    "wof:population":380
},
  "geometry": {"coordinates":[75.21556699999999,12.802863],"type":"Point"}
}