{
  "type": "Feature",
  "properties": {
    "gn:admin1_code":"16",
    "gn:admin2_code":"509.0",
    "gn:asciiname":"Mangli",
    "gn:country_code":"IN",
    "gn:dem":220,
    "gn:feature_class":"P",
    "gn:feature_code":"PPL",
    "gn:name":"M\u0101ngli",
    "gn:population":0,
    "gn:timezone":"Asia/Kolkata",
    "iso:country":"IN",
    "ks:ks_alt_nam":"M\u0101ngli",
    "ks:ks_name":"Mangli",
    "ks:ks_pop":78,
    "ks:ks_type":"VILLAGE",
    "name:eng_x_preferred":[
        "Mangli"
    ],
    "name:eng_x_variant":[
        "M\u0101ngli"
    ],
    "wof:name":"Mangli",
    "wof:placetype":"locality",
    "wof:population":78
},
  "geometry": {"coordinates":[79.788375,20.234045],"type":"Point"}
}