{
  "type": "Feature",
  "properties": {
    "iso:country":"IN",
    "ks:ks_name":"Jeevan Ka Bas",
    "ks:ks_pop":15,
    "ks:ks_type":"HABITATION",
    "name:eng_x_preferred":[
        "Jeevan Ka Bas"
    ],
    "wof:name":"Jeevan Ka Bas",
    "wof:placetype":"locality",
    "wof:population":15
},
  "geometry": {"coordinates":[75.118861,28.264667],"type":"Point"}
}