{
  "type": "Feature",
  "properties": {
    "iso:country":"IN",
    "ks:ks_alt_nam":"Pure daswan",
    "ks:ks_name":"Pure Daswan",
    "ks:ks_pop":242,
    "ks:ks_type":"HABITATION",
    "name:eng_x_preferred":[
        "Pure Daswan"
    ],
    "wof:name":"Pure Daswan",
    "wof:placetype":"locality",
    "wof:population":242
},
  "geometry": {"coordinates":[81.79354600000001,26.440797],"type":"Point"}
}