{
  "type": "Feature",
  "properties": {
    "iso:country":"IN",
    "ks:ks_name":"Devaya",
    "ks:ks_pop":0,
    "ks:ks_type":"VILLAGE",
    "name:eng_x_preferred":[
        "Devaya"
    ],
    "wof:name":"Devaya",
    "wof:placetype":"locality",
    "wof:population":0
},
  "geometry": {"coordinates":[82.586758,26.619187],"type":"Point"}
}