{
  "type": "Feature",
  "properties": {
    "iso:country":"IN",
    "ks:ks_name":"Vasimwadi",
    "ks:ks_pop":62,
    "ks:ks_type":"HABITATION",
    "name:eng_x_preferred":[
        "Vasimwadi"
    ],
    "wof:name":"Vasimwadi",
    "wof:placetype":"locality",
    "wof:population":62
},
  "geometry": {"coordinates":[73.69961600000001,16.379888],"type":"Point"}
}