{
  "type": "Feature",
  "properties": {
    "gn:admin1_code":"25.0",
    "gn:admin2_code":"631.0",
    "gn:asciiname":"Boganapalli",
    "gn:country_code":"IN",
    "gn:dem":505,
    "gn:feature_class":"P",
    "gn:feature_code":"PPL",
    "gn:name":"Boganapalli",
    "gn:population":0,
    "gn:timezone":"Asia/Kolkata",
    "iso:country":"IN",
    "ks:ks_name":"Boganapalli",
    "ks:ks_pop":1545,
    "ks:ks_type":"VILLAGE",
    "ks:ks_uagg_main":0,
    "name:eng_x_preferred":[
        "Boganapalli"
    ],
    "wof:name":"Boganapalli",
    "wof:placetype":"locality",
    "wof:population":1545
},
  "geometry": {"coordinates":[78.241178,12.537512],"type":"Point"}
}