{
  "type": "Feature",
  "properties": {
    "gn:country":"IN",
    "gn:fcode":"PPL",
    "gn:pop":0,
    "iso:country":"IN",
    "name:ben_x_preferred":[
        "\u099a\u09bf\u09ce\u09aa\u09c1\u09b0"
    ],
    "name:eng_x_preferred":[
        "Chitpur"
    ],
    "qs:name":"Chitpur",
    "qs:name_adm0":"India",
    "qs:name_adm1":"West Bengal",
    "qs:photos":2,
    "qs:photos_1k":1,
    "qs:photos_9k":1,
    "qs:photos_9r":1,
    "qs:photos_all":2,
    "qs:photos_sr":1,
    "qs:placetype":"Suburb",
    "qs:pop_sr":"0",
    "wd:wordcount":1190,
    "wof:name":"Chitpur",
    "wof:placetype":"neighbourhood",
    "wof:population":0
},
  "geometry": {"coordinates":[88.94194,22.80889],"type":"Point"}
}