{
  "type": "Feature",
  "properties": {
    "iso:country":"IN",
    "ks:ks_name":"Kaithi",
    "ks:ks_type":"VILLAGE",
    "name:eng_x_preferred":[
        "Kaithi"
    ],
    "wof:name":"Kaithi",
    "wof:placetype":"locality"
},
  "geometry": {"coordinates":[83.40504199999999,25.302319],"type":"Point"}
}