{
  "type": "Feature",
  "properties": {
    "iso:country":"IN",
    "ks:ks_name":"Ammadi",
    "ks:ks_pop":57,
    "ks:ks_type":"VILLAGE",
    "name:eng_x_preferred":[
        "Ammadi"
    ],
    "wof:name":"Ammadi",
    "wof:placetype":"locality",
    "wof:population":57
},
  "geometry": {"coordinates":[75.344641,13.545335],"type":"Point"}
}