{
  "type": "Feature",
  "properties": {
    "iso:country":"IN",
    "ks:ks_name":"Kumbhiguda",
    "ks:ks_pop":27,
    "ks:ks_type":"HABITATION",
    "name:eng_x_preferred":[
        "Kumbhiguda"
    ],
    "wof:name":"Kumbhiguda",
    "wof:placetype":"locality",
    "wof:population":27
},
  "geometry": {"coordinates":[83.01653,18.564638],"type":"Point"}
}