{
  "type": "Feature",
  "properties": {
    "iso:country":"IN",
    "ks:ks_name":"Malsa Khali Para",
    "ks:ks_pop":1480,
    "ks:ks_type":"HABITATION",
    "name:eng_x_preferred":[
        "Malsa Khali Para"
    ],
    "wof:name":"Malsa Khali Para",
    "wof:placetype":"locality",
    "wof:population":1480
},
  "geometry": {"coordinates":[88.858695,22.228902],"type":"Point"}
}