{
  "type": "Feature",
  "properties": {
    "iso:country":"IN",
    "ks:ks_name":"Barihaguda",
    "ks:ks_pop":162,
    "ks:ks_type":"HABITATION",
    "name:eng_x_preferred":[
        "Barihaguda"
    ],
    "wof:name":"Barihaguda",
    "wof:placetype":"locality",
    "wof:population":162
},
  "geometry": {"coordinates":[82.431736,18.856868],"type":"Point"}
}