{
  "type": "Feature",
  "properties": {
    "iso:country":"IN",
    "ks:ks_name":"Konadka",
    "ks:ks_pop":231,
    "ks:ks_type":"HABITATION",
    "name:eng_x_preferred":[
        "Konadka"
    ],
    "wof:name":"Konadka",
    "wof:placetype":"locality",
    "wof:population":231
},
  "geometry": {"coordinates":[75.52943999999999,12.691553],"type":"Point"}
}