{
  "type": "Feature",
  "properties": {
    "iso:country":"IN",
    "ks:ks_name":"Beni Jot",
    "ks:ks_pop":912,
    "ks:ks_type":"HABITATION",
    "name:eng_x_preferred":[
        "Beni Jot"
    ],
    "wof:name":"Beni Jot",
    "wof:placetype":"locality",
    "wof:population":912
},
  "geometry": {"coordinates":[82.260685,27.366908],"type":"Point"}
}