{
  "type": "Feature",
  "properties": {
    "gn:admin1_code":"36",
    "gn:admin2_code":"191.0",
    "gn:asciiname":"Kamaluddinpur",
    "gn:country_code":"IN",
    "gn:dem":78,
    "gn:feature_class":"P",
    "gn:feature_code":"PPL",
    "gn:name":"Kam\u0101ludd\u012bnpur",
    "gn:population":0,
    "gn:timezone":"Asia/Kolkata",
    "iso:country":"IN",
    "wof:name":"Kamaluddinpur",
    "wof:placetype":"locality"
},
  "geometry": {"coordinates":[83.32200999999998,25.88818],"type":"Point"}
}