{
  "type": "Feature",
  "properties": {
    "gn:admin1_code":"36",
    "gn:admin2_code":"191.0",
    "gn:asciiname":"Kamaluddinpur",
    "gn:country_code":"IN",
    "gn:dem":78,
    "gn:feature_class":"P",
    "gn:feature_code":"PPL",
    "gn:name":"Kam\u0101ludd\u012bnpur",
    "gn:population":0,
    "gn:timezone":"Asia/Kolkata",
    "iso:country":"IN",
    "ks:ks_name":"Kamaluddinpur",
    "ks:ks_pop":180,
    "ks:ks_type":"HABITATION",
    "name:eng_x_preferred":[
        "Kamaluddinpur"
    ],
    "wof:name":"Kamaluddinpur",
    "wof:placetype":"locality",
    "wof:population":180
},
  "geometry": {"coordinates":[83.320903,25.891898],"type":"Point"}
}