{
  "type": "Feature",
  "properties": {
    "iso:country":"IN",
    "ks:ks_name":"Ambedkar Nagar",
    "ks:ks_pop":282,
    "ks:ks_type":"HABITATION",
    "ks:ks_uagg_main":0,
    "name:eng_x_preferred":[
        "Ambedkar Nagar"
    ],
    "wof:name":"Ambedkar Nagar",
    "wof:placetype":"neighbourhood",
    "wof:population":282
},
  "geometry": {"coordinates":[80.001723,14.762894],"type":"Point"}
}