{
  "type": "Feature",
  "properties": {
    "gn:admin1_code":"12",
    "gn:admin2_code":"14.0",
    "gn:asciiname":"Phraslun",
    "gn:country_code":"IN",
    "gn:dem":2565,
    "gn:feature_class":"P",
    "gn:feature_code":"PPL",
    "gn:name":"Phraslun",
    "gn:population":0,
    "gn:timezone":"Asia/Kolkata",
    "iso:country":"IN",
    "wof:name":"Phraslun",
    "wof:placetype":"locality"
},
  "geometry": {"coordinates":[75.36816999999998,34.06415],"type":"Point"}
}