{
  "type": "Feature",
  "properties": {
    "iso:country":"IN",
    "ks:ks_name":"Jhinjhari",
    "ks:ks_pop":2302,
    "ks:ks_type":"VILLAGE",
    "name:eng_x_preferred":[
        "Jhinjhari"
    ],
    "wof:name":"Jhinjhari",
    "wof:placetype":"locality",
    "wof:population":2302
},
  "geometry": {"coordinates":[79.403643,28.175054],"type":"Point"}
}