{
  "type": "Feature",
  "properties": {
    "gn:admin1_code":"38",
    "gn:admin2_code":"346.0",
    "gn:asciiname":"Amba Khorea",
    "gn:country_code":"IN",
    "gn:dem":342,
    "gn:feature_class":"P",
    "gn:feature_code":"PPL",
    "gn:name":"Amba Khorea",
    "gn:population":0,
    "gn:timezone":"Asia/Kolkata",
    "iso:country":"IN",
    "ks:ks_name":"Amba Khorea",
    "ks:ks_pop":1597,
    "ks:ks_type":"VILLAGE",
    "name:eng_x_preferred":[
        "Amba Khorea"
    ],
    "wof:name":"Amba Khorea",
    "wof:placetype":"locality",
    "wof:population":1597
},
  "geometry": {"coordinates":[83.459476,24.088546],"type":"Point"}
}