{
  "type": "Feature",
  "properties": {
    "iso:country":"IN",
    "ks:ks_name":"Devli Nagar",
    "ks:ks_pop":426,
    "ks:ks_type":"HABITATION",
    "name:eng_x_preferred":[
        "Devli Nagar"
    ],
    "wof:name":"Devli Nagar",
    "wof:placetype":"locality",
    "wof:population":426
},
  "geometry": {"coordinates":[72.103289,27.360242],"type":"Point"}
}