{
  "type": "Feature",
  "properties": {
    "gn:admin1_code":"23",
    "gn:admin2_code":"38.0",
    "gn:asciiname":"Sarishtpur",
    "gn:country_code":"IN",
    "gn:dem":253,
    "gn:feature_class":"P",
    "gn:feature_code":"PPL",
    "gn:name":"Sarishtpur",
    "gn:population":0,
    "gn:timezone":"Asia/Kolkata",
    "iso:country":"IN",
    "ks:ks_name":"Sarishtpur",
    "ks:ks_pop":718,
    "ks:ks_type":"VILLAGE",
    "ks:ks_uagg_main":0,
    "name:eng_x_preferred":[
        "Sarishtpur"
    ],
    "wof:name":"Sarishtpur",
    "wof:placetype":"neighbourhood",
    "wof:population":718
},
  "geometry": {"coordinates":[75.69511799999999,31.579713],"type":"Point"}
}