{
  "type": "Feature",
  "properties": {
    "iso:country":"IN",
    "ks:ks_name":"Attahalli",
    "ks:ks_pop":36,
    "ks:ks_type":"HABITATION",
    "name:eng_x_preferred":[
        "Attahalli"
    ],
    "wof:name":"Attahalli",
    "wof:placetype":"locality",
    "wof:population":36
},
  "geometry": {"coordinates":[75.03804,13.782904],"type":"Point"}
}