{
  "type": "Feature",
  "properties": {
    "iso:country":"IN",
    "ks:ks_name":"Pargaon",
    "ks:ks_pop":1000,
    "ks:ks_type":"HABITATION",
    "name:eng_x_preferred":[
        "Pargaon"
    ],
    "wof:name":"Pargaon",
    "wof:placetype":"locality",
    "wof:population":1000
},
  "geometry": {"coordinates":[72.879375,19.75961],"type":"Point"}
}