{
  "type": "Feature",
  "properties": {
    "gn:admin1_code":"2",
    "gn:admin2_code":"544.0",
    "gn:asciiname":"Gollapalle",
    "gn:country_code":"IN",
    "gn:dem":865,
    "gn:feature_class":"P",
    "gn:feature_code":"PPL",
    "gn:name":"Gollapalle",
    "gn:population":0,
    "gn:timezone":"Asia/Kolkata",
    "iso:country":"IN",
    "name:tam_x_preferred":[
        "\u0b95\u0bca\u0bb2\u0bcd\u0bb2\u0baa\u0bcd\u0baa\u0bb3\u0bcd\u0bb3\u0bbf"
    ],
    "name:tel_x_preferred":[
        "\u0c17\u0c4a\u0c32\u0c4d\u0c32\u0c2a\u0c32\u0c4d\u0c32\u0c3f"
    ],
    "wof:name":"Gollapalle",
    "wof:placetype":"locality"
},
  "geometry": {"coordinates":[82.25617,17.95997000000001],"type":"Point"}
}