{
  "type": "Feature",
  "properties": {
    "iso:country":"IN",
    "ks:ks_alt_nam":"nagar",
    "ks:ks_name":"Nagar",
    "ks:ks_pop":52,
    "ks:ks_type":"HABITATION",
    "name:eng_x_preferred":[
        "Nagar"
    ],
    "wof:name":"Nagar",
    "wof:placetype":"locality",
    "wof:population":52
},
  "geometry": {"coordinates":[74.638223,14.234026],"type":"Point"}
}