{
  "type": "Feature",
  "properties": {
    "iso:country":"IN",
    "ks:ks_name":"Naddodi",
    "ks:ks_pop":250,
    "ks:ks_type":"HABITATION",
    "name:eng_x_preferred":[
        "Naddodi"
    ],
    "wof:name":"Naddodi",
    "wof:placetype":"locality",
    "wof:population":250
},
  "geometry": {"coordinates":[74.981922,13.119844],"type":"Point"}
}