{
  "type": "Feature",
  "properties": {
    "iso:country":"IN",
    "ks:ks_alt_nam":"Jholw\u0101ra",
    "ks:ks_name":"Jholwara",
    "ks:ks_type":"VILLAGE",
    "name:eng_x_preferred":[
        "Jholwara"
    ],
    "name:eng_x_variant":[
        "Jholw\u0101ra"
    ],
    "wof:name":"Jholwara",
    "wof:placetype":"locality"
},
  "geometry": {"coordinates":[76.383061,21.909338],"type":"Point"}
}