{
  "type": "Feature",
  "properties": {
    "iso:country":"IN",
    "ks:ks_name":"Jungle Jagdishpur",
    "ks:ks_pop":5528,
    "ks:ks_type":"VILLAGE",
    "name:eng_x_preferred":[
        "Jungle Jagdishpur"
    ],
    "wof:name":"Jungle Jagdishpur",
    "wof:placetype":"locality",
    "wof:population":5528
},
  "geometry": {"coordinates":[83.929295,26.954582],"type":"Point"}
}