{
  "type": "Feature",
  "properties": {
    "gn:admin1_code":"36",
    "gn:admin2_code":"200.0",
    "gn:asciiname":"Rantola",
    "gn:country_code":"IN",
    "gn:dem":324,
    "gn:feature_class":"P",
    "gn:feature_code":"PPL",
    "gn:name":"R\u0101ntola",
    "gn:population":0,
    "gn:timezone":"Asia/Kolkata",
    "iso:country":"IN",
    "ks:ks_name":"Rantola",
    "ks:ks_pop":868,
    "ks:ks_type":"VILLAGE",
    "name:eng_x_preferred":[
        "Rantola"
    ],
    "wof:name":"Rantola",
    "wof:placetype":"locality",
    "wof:population":868
},
  "geometry": {"coordinates":[83.100874,24.208116],"type":"Point"}
}