{
  "type": "Feature",
  "properties": {
    "iso:country":"IN",
    "ks:ks_name":"Katkariwadi",
    "ks:ks_pop":150,
    "ks:ks_type":"HABITATION",
    "name:eng_x_preferred":[
        "Katkariwadi"
    ],
    "wof:name":"Katkariwadi",
    "wof:placetype":"locality",
    "wof:population":150
},
  "geometry": {"coordinates":[73.313333,19.353056],"type":"Point"}
}