{
  "type": "Feature",
  "properties": {
    "gn:admin1_code":"24.0",
    "gn:admin2_code":"121",
    "gn:asciiname":"Khuentiyan",
    "gn:country_code":"IN",
    "gn:dem":268,
    "gn:feature_class":"P",
    "gn:feature_code":"PPL",
    "gn:name":"Khuent\u012by\u0101n",
    "gn:population":0,
    "gn:timezone":"Asia/Kolkata",
    "iso:country":"IN",
    "wof:name":"Khuentiyan",
    "wof:placetype":"neighbourhood"
},
  "geometry": {"coordinates":[75.52481,25.35294],"type":"Point"}
}