{
  "type": "Feature",
  "properties": {
    "iso:country":"IN",
    "name:ast_x_preferred":[
        "Chingoli"
    ],
    "name:eng_x_preferred":[
        "Chingoli"
    ],
    "name:mal_x_preferred":[
        "\u0d1a\u0d3f\u0d19\u0d4d\u0d19\u0d4b\u0d33\u0d3f"
    ],
    "name:nld_x_preferred":[
        "Chingoli"
    ],
    "qs:name":"Chingoli",
    "qs:name_adm0":"India",
    "qs:name_adm1":"Kerala",
    "qs:photos":30,
    "qs:photos_1k":6,
    "qs:photos_9k":1,
    "qs:photos_9r":2,
    "qs:photos_all":30,
    "qs:photos_sr":2,
    "qs:placetype":"Town",
    "qs:pop_sr":"0",
    "wd:wordcount":228,
    "wof:name":"Chingoli",
    "wof:placetype":"locality"
},
  "geometry": {"coordinates":[76.415694,9.2524955],"type":"Point"}
}