{
  "type": "Feature",
  "properties": {
    "iso:country":"IN",
    "ks:ks_name":"Pungaverikottam",
    "ks:ks_pop":144,
    "ks:ks_type":"HABITATION",
    "name:eng_x_preferred":[
        "Pungaverikottam"
    ],
    "wof:name":"Pungaverikottam",
    "wof:placetype":"locality",
    "wof:population":144
},
  "geometry": {"coordinates":[78.567216,11.002398],"type":"Point"}
}