{
  "type": "Feature",
  "properties": {
    "gn:admin1_code":"36",
    "gn:admin2_code":"170.0",
    "gn:asciiname":"Ghazipur",
    "gn:country_code":"IN",
    "gn:dem":119,
    "gn:feature_class":"P",
    "gn:feature_code":"PPL",
    "gn:name":"Gh\u0101z\u012bpur",
    "gn:population":0,
    "gn:timezone":"Asia/Kolkata",
    "iso:country":"IN",
    "wof:name":"Ghazipur",
    "wof:placetype":"locality"
},
  "geometry": {"coordinates":[80.40427,25.89637],"type":"Point"}
}