{
  "type": "Feature",
  "properties": {
    "iso:country":"IN",
    "ks:ks_name":"Teliwadi",
    "ks:ks_pop":99,
    "ks:ks_type":"HABITATION",
    "name:eng_x_preferred":[
        "Teliwadi"
    ],
    "wof:name":"Teliwadi",
    "wof:placetype":"locality",
    "wof:population":99
},
  "geometry": {"coordinates":[73.72002999999999,16.193079],"type":"Point"}
}