{
  "type": "Feature",
  "properties": {
    "gn:admin1_code":"35",
    "gn:admin2_code":"448.0",
    "gn:asciiname":"Jhiri",
    "gn:country_code":"IN",
    "gn:dem":340,
    "gn:feature_class":"P",
    "gn:feature_code":"PPL",
    "gn:name":"Jhiri",
    "gn:population":0,
    "gn:timezone":"Asia/Kolkata",
    "iso:country":"IN",
    "wof:name":"Jhiri",
    "wof:placetype":"locality"
},
  "geometry": {"coordinates":[77.18788000000001,22.15888],"type":"Point"}
}