{
  "type": "Feature",
  "properties": {
    "iso:country":"IN",
    "ks:ks_name":"Pelkadih",
    "ks:ks_pop":45,
    "ks:ks_type":"HABITATION",
    "name:eng_x_preferred":[
        "Pelkadih"
    ],
    "wof:name":"Pelkadih",
    "wof:placetype":"locality",
    "wof:population":45
},
  "geometry": {"coordinates":[85.78345,23.034888],"type":"Point"}
}