{
  "type": "Feature",
  "properties": {
    "iso:country":"IN",
    "ks:ks_alt_nam":"DHASAI MAL",
    "ks:ks_name":"Dhasai Mal",
    "ks:ks_pop":612,
    "ks:ks_type":"HABITATION",
    "name:eng_x_preferred":[
        "Dhasai Mal"
    ],
    "wof:name":"Dhasai Mal",
    "wof:placetype":"locality",
    "wof:population":612
},
  "geometry": {"coordinates":[77.946853,22.325916],"type":"Point"}
}