{
  "type": "Feature",
  "properties": {
    "gn:admin1_code":"24.0",
    "gn:admin2_code":"125.0",
    "gn:asciiname":"Timamauri",
    "gn:country_code":"IN",
    "gn:dem":273,
    "gn:feature_class":"P",
    "gn:feature_code":"PPL",
    "gn:name":"T\u012bm\u0101mauri",
    "gn:population":0,
    "gn:timezone":"Asia/Kolkata",
    "iso:country":"IN",
    "wof:name":"Timamauri",
    "wof:placetype":"locality"
},
  "geometry": {"coordinates":[74.3391,23.26822],"type":"Point"}
}