{
  "type": "Feature",
  "properties": {
    "gn:admin1_code":"39.0",
    "gn:admin2_code":"061",
    "gn:asciiname":"Nayunsari",
    "gn:country_code":"IN",
    "gn:dem":861,
    "gn:feature_class":"P",
    "gn:feature_code":"PPL",
    "gn:name":"N\u0101y\u016bns\u0101ri",
    "gn:population":0,
    "gn:timezone":"Asia/Kolkata",
    "iso:country":"IN",
    "wof:name":"Nayunsari",
    "wof:placetype":"locality"
},
  "geometry": {"coordinates":[78.70966,29.87718],"type":"Point"}
}