{
  "type": "Feature",
  "properties": {
    "gn:admin1_code":"30",
    "gn:admin2_code":"252.0",
    "gn:asciiname":"Ramsing",
    "gn:country_code":"IN",
    "gn:dem":686,
    "gn:feature_class":"P",
    "gn:feature_code":"PPL",
    "gn:name":"Ramsing",
    "gn:population":0,
    "gn:timezone":"Asia/Kolkata",
    "iso:country":"IN",
    "wof:name":"Ramsing",
    "wof:placetype":"locality"
},
  "geometry": {"coordinates":[94.98095000000001,28.65386],"type":"Point"}
}