{
  "type": "Feature",
  "properties": {
    "iso:country":"IN",
    "ks:ks_alt_nam":"PATIL WASTI",
    "ks:ks_name":"Patil Wasti",
    "ks:ks_pop":125,
    "ks:ks_type":"HABITATION",
    "name:eng_x_preferred":[
        "Patil Wasti"
    ],
    "wof:name":"Patil Wasti",
    "wof:placetype":"locality",
    "wof:population":125
},
  "geometry": {"coordinates":[74.309015,17.186341],"type":"Point"}
}