{
  "type": "Feature",
  "properties": {
    "iso:country":"IN",
    "ks:ks_name":"Pulimala",
    "ks:ks_pop":3010,
    "ks:ks_type":"HABITATION",
    "name:eng_x_preferred":[
        "Pulimala"
    ],
    "wof:name":"Pulimala",
    "wof:placetype":"locality",
    "wof:population":3010
},
  "geometry": {"coordinates":[76.51777199999999,10.112941],"type":"Point"}
}