{
  "type": "Feature",
  "properties": {
    "iso:country":"IN",
    "ks:ks_name":"Atal",
    "ks:ks_pop":231,
    "ks:ks_type":"VILLAGE",
    "name:eng_x_preferred":[
        "Atal"
    ],
    "wof:name":"Atal",
    "wof:placetype":"locality",
    "wof:population":231
},
  "geometry": {"coordinates":[72.307964,24.401029],"type":"Point"}
}