{
  "type": "Feature",
  "properties": {
    "iso:country":"IN",
    "ks:ks_name":"Gopapatna",
    "ks:ks_pop":434,
    "ks:ks_type":"VILLAGE",
    "ks:ks_uagg_main":0,
    "name:eng_x_preferred":[
        "Gopapatna"
    ],
    "wof:name":"Gopapatna",
    "wof:placetype":"neighbourhood",
    "wof:population":434
},
  "geometry": {"coordinates":[85.692902,20.067351],"type":"Point"}
}