{
  "type": "Feature",
  "properties": {
    "iso:country":"IN",
    "ks:ks_alt_nam":"Y\u016bsufpur Kotha",
    "ks:ks_name":"Yusufpur Kotha",
    "ks:ks_type":"VILLAGE",
    "name:eng_x_preferred":[
        "Yusufpur Kotha"
    ],
    "name:eng_x_variant":[
        "Y\u016bsufpur Kotha"
    ],
    "wof:name":"Yusufpur Kotha",
    "wof:placetype":"locality"
},
  "geometry": {"coordinates":[77.870352,28.823925],"type":"Point"}
}