{
  "type": "Feature",
  "properties": {
    "iso:country":"IN",
    "ks:ks_name":"Kakariguda",
    "ks:ks_pop":318,
    "ks:ks_type":"HABITATION",
    "name:eng_x_preferred":[
        "Kakariguda"
    ],
    "wof:name":"Kakariguda",
    "wof:placetype":"locality",
    "wof:population":318
},
  "geometry": {"coordinates":[81.674392,18.149241],"type":"Point"}
}