{
  "type": "Feature",
  "properties": {
    "gn:admin1_code":"36.0",
    "gn:admin2_code":"176",
    "gn:asciiname":"Burhwal",
    "gn:country_code":"IN",
    "gn:dem":116,
    "gn:feature_class":"P",
    "gn:feature_code":"PPL",
    "gn:name":"Burhwal",
    "gn:population":0,
    "gn:timezone":"Asia/Kolkata",
    "iso:country":"IN",
    "name:und_x_variant":[
        "Burhwal Junction",
        "Burhwal"
    ],
    "wof:name":"Burhwal",
    "wof:placetype":"locality"
},
  "geometry": {"coordinates":[81.39775,27.0906],"type":"Point"}
}