{
  "type": "Feature",
  "properties": {
    "gn:admin1_code":"16.0",
    "gn:admin2_code":"505.0",
    "gn:asciiname":"Tanda Labhani",
    "gn:country_code":"IN",
    "gn:dem":456,
    "gn:feature_class":"P",
    "gn:feature_code":"PPL",
    "gn:name":"T\u0101nda Labh\u0101ni",
    "gn:population":0,
    "gn:timezone":"Asia/Kolkata",
    "iso:country":"IN",
    "wof:name":"Tanda Labhani",
    "wof:placetype":"neighbourhood"
},
  "geometry": {"coordinates":[78.67950999999999,21.20415],"type":"Point"}
}