{
  "type": "Feature",
  "properties": {
    "iso:country":"IN",
    "ks:ks_alt_nam":"Vellimukku palli",
    "ks:ks_name":"Vellimukku Palli",
    "ks:ks_pop":1060,
    "ks:ks_type":"HABITATION",
    "name:eng_x_preferred":[
        "Vellimukku Palli"
    ],
    "wof:name":"Vellimukku Palli",
    "wof:placetype":"locality",
    "wof:population":1060
},
  "geometry": {"coordinates":[75.89722,11.085761],"type":"Point"}
}