{
  "type": "Feature",
  "properties": {
    "iso:country":"IN",
    "ks:ks_name":"Laskarwadi",
    "ks:ks_pop":260,
    "ks:ks_type":"HABITATION",
    "name:eng_x_preferred":[
        "Laskarwadi"
    ],
    "wof:name":"Laskarwadi",
    "wof:placetype":"locality",
    "wof:population":260
},
  "geometry": {"coordinates":[73.555132,18.859647],"type":"Point"}
}