{
  "type": "Feature",
  "properties": {
    "iso:country":"IN",
    "ks:ks_name":"Alampur Toda",
    "ks:ks_pop":0,
    "ks:ks_type":"VILLAGE",
    "name:eng_x_preferred":[
        "Alampur Toda"
    ],
    "wof:name":"Alampur Toda",
    "wof:placetype":"locality",
    "wof:population":0
},
  "geometry": {"coordinates":[78.290285,29.391925],"type":"Point"}
}