{
  "type": "Feature",
  "properties": {
    "iso:country":"IN",
    "ks:ks_name":"Sonarwadi",
    "ks:ks_pop":78,
    "ks:ks_type":"HABITATION",
    "name:eng_x_preferred":[
        "Sonarwadi"
    ],
    "wof:name":"Sonarwadi",
    "wof:placetype":"locality",
    "wof:population":78
},
  "geometry": {"coordinates":[73.39143900000001,19.848907],"type":"Point"}
}