{
  "type": "Feature",
  "properties": {
    "iso:country":"IN",
    "ks:ks_name":"Teghari",
    "ks:ks_pop":550,
    "ks:ks_type":"VILLAGE",
    "name:eng_x_preferred":[
        "Teghari"
    ],
    "wof:name":"Teghari",
    "wof:placetype":"locality",
    "wof:population":550
},
  "geometry": {"coordinates":[88.814905,23.188464],"type":"Point"}
}