{
  "type": "Feature",
  "properties": {
    "gn:admin1_code":"36",
    "gn:admin2_code":"191.0",
    "gn:asciiname":"Malpar",
    "gn:country_code":"IN",
    "gn:dem":82,
    "gn:feature_class":"P",
    "gn:feature_code":"PPL",
    "gn:name":"M\u0101lp\u0101r",
    "gn:population":0,
    "gn:timezone":"Asia/Kolkata",
    "iso:country":"IN",
    "ks:ks_alt_nam":"M\u0101lp\u0101r",
    "ks:ks_name":"Malpar",
    "ks:ks_pop":698,
    "ks:ks_type":"VILLAGE",
    "ks:ks_uagg_main":0,
    "name:eng_x_preferred":[
        "Malpar"
    ],
    "name:eng_x_variant":[
        "M\u0101lp\u0101r"
    ],
    "name:kan_x_preferred":[
        "\u0cae\u0cb2\u0ccd\u0caa\u0cbe\u0cb0\u0ccd"
    ],
    "wof:name":"Malpar",
    "wof:placetype":"neighbourhood",
    "wof:population":698
},
  "geometry": {"coordinates":[83.13563499999999,25.811073],"type":"Point"}
}