{
  "type": "Feature",
  "properties": {
    "iso:country":"IN",
    "ks:ks_name":"Turakapeta",
    "ks:ks_pop":317,
    "ks:ks_type":"HABITATION",
    "ks:ks_uagg_main":0,
    "name:eng_x_preferred":[
        "Turakapeta"
    ],
    "wof:name":"Turakapeta",
    "wof:placetype":"neighbourhood",
    "wof:population":317
},
  "geometry": {"coordinates":[84.668103,19.07015],"type":"Point"}
}