{
  "type": "Feature",
  "properties": {
    "gn:admin1_code":"34.0",
    "gn:admin2_code":"230.0",
    "gn:asciiname":"Ghordaur",
    "gn:country_code":"IN",
    "gn:dem":57,
    "gn:feature_class":"P",
    "gn:feature_code":"PPL",
    "gn:name":"Ghordaur",
    "gn:population":0,
    "gn:timezone":"Asia/Kolkata",
    "iso:country":"IN",
    "ks:ks_name":"Ghordaur",
    "ks:ks_pop":492,
    "ks:ks_type":"VILLAGE",
    "ks:ks_uagg_main":0,
    "name:eng_x_preferred":[
        "Ghordaur"
    ],
    "wof:name":"Ghordaur",
    "wof:placetype":"neighbourhood",
    "wof:population":492
},
  "geometry": {"coordinates":[85.13681,25.461873],"type":"Point"}
}