{
  "type": "Feature",
  "properties": {
    "gn:admin1_code":"36.0",
    "gn:admin2_code":"165.0",
    "gn:asciiname":"Kanchanpura",
    "gn:country_code":"IN",
    "gn:dem":147,
    "gn:feature_class":"P",
    "gn:feature_code":"PPL",
    "gn:name":"Kanchanpura",
    "gn:population":0,
    "gn:timezone":"Asia/Kolkata",
    "iso:country":"IN",
    "ks:ks_name":"Kanchanpur",
    "ks:ks_pop":212,
    "ks:ks_type":"VILLAGE",
    "name:eng_x_preferred":[
        "Kanchanpur"
    ],
    "name:eng_x_variant":[
        "Kanchanpura"
    ],
    "wof:name":"Kanchanpur",
    "wof:placetype":"locality",
    "wof:population":212
},
  "geometry": {"coordinates":[79.32683299999999,26.253606],"type":"Point"}
}