{
  "type": "Feature",
  "properties": {
    "gn:admin1_code":"36.0",
    "gn:admin2_code":"165.0",
    "gn:asciiname":"Kanchanpura",
    "gn:country_code":"IN",
    "gn:dem":147,
    "gn:feature_class":"P",
    "gn:feature_code":"PPL",
    "gn:name":"Kanchanpura",
    "gn:population":0,
    "gn:timezone":"Asia/Kolkata",
    "iso:country":"IN",
    "wof:name":"Kanchanpura",
    "wof:placetype":"locality"
},
  "geometry": {"coordinates":[79.31935,26.25573],"type":"Point"}
}