{
  "type": "Feature",
  "properties": {
    "iso:country":"IN",
    "ks:ks_name":"Malegaon",
    "ks:ks_pop":492,
    "ks:ks_type":"VILLAGE",
    "name:eng_x_preferred":[
        "Malegaon"
    ],
    "wof:name":"Malegaon",
    "wof:placetype":"locality",
    "wof:population":492
},
  "geometry": {"coordinates":[76.629462,19.59484],"type":"Point"}
}