{
  "type": "Feature",
  "properties": {
    "gn:admin1_code":"37.0",
    "gn:admin2_code":"416.0",
    "gn:asciiname":"Gamawada",
    "gn:country_code":"IN",
    "gn:dem":430,
    "gn:feature_class":"P",
    "gn:feature_code":"PPL",
    "gn:name":"Gam\u0101w\u0101da",
    "gn:population":0,
    "gn:timezone":"Asia/Kolkata",
    "iso:country":"IN",
    "ks:ks_alt_nam":"Gam\u0101w\u0101da",
    "ks:ks_name":"Gamawada",
    "ks:ks_pop":1502,
    "ks:ks_type":"VILLAGE",
    "name:eng_x_preferred":[
        "Gamawada"
    ],
    "name:eng_x_variant":[
        "Gam\u0101w\u0101da"
    ],
    "wof:name":"Gamawada",
    "wof:placetype":"locality",
    "wof:population":1502
},
  "geometry": {"coordinates":[81.297753,18.808976],"type":"Point"}
}