{
  "type": "Feature",
  "properties": {
    "iso:country":"IN",
    "ks:ks_name":"Maharipara",
    "ks:ks_pop":1055,
    "ks:ks_type":"VILLAGE",
    "ks:ks_uagg_main":0,
    "name:eng_x_preferred":[
        "Maharipara"
    ],
    "wof:name":"Maharipara",
    "wof:placetype":"neighbourhood",
    "wof:population":1055
},
  "geometry": {"coordinates":[91.727142,26.588756],"type":"Point"}
}