{
  "type": "Feature",
  "properties": {
    "gn:admin1_code":"36",
    "gn:admin2_code":"159.0",
    "gn:asciiname":"Deoraiya",
    "gn:country_code":"IN",
    "gn:dem":157,
    "gn:feature_class":"P",
    "gn:feature_code":"PPL",
    "gn:name":"Deoraiya",
    "gn:population":0,
    "gn:timezone":"Asia/Kolkata",
    "iso:country":"IN",
    "ks:ks_name":"Devraiya",
    "ks:ks_pop":451,
    "ks:ks_type":"VILLAGE",
    "ks:ks_uagg_main":0,
    "name:eng_x_preferred":[
        "Devraiya"
    ],
    "wof:name":"Devraiya",
    "wof:placetype":"neighbourhood",
    "wof:population":451
},
  "geometry": {"coordinates":[79.24614699999999,27.590004],"type":"Point"}
}