{
  "type": "Feature",
  "properties": {
    "gn:admin1_code":"11.0",
    "gn:admin2_code":"33.0",
    "gn:asciiname":"Chauth",
    "gn:country_code":"IN",
    "gn:dem":2008,
    "gn:feature_class":"P",
    "gn:feature_code":"PPL",
    "gn:name":"Chauth",
    "gn:population":0,
    "gn:timezone":"Asia/Kolkata",
    "iso:country":"IN",
    "name:cat_x_preferred":[
        "Chauth"
    ],
    "name:hin_x_preferred":[
        "\u091a\u094c\u0925"
    ],
    "name:ita_x_preferred":[
        "Chauth"
    ],
    "name:jpn_x_preferred":[
        "\u30c1\u30e3\u30a6\u30c8"
    ],
    "name:nld_x_preferred":[
        "Chauth"
    ],
    "wof:name":"Chauth",
    "wof:placetype":"locality"
},
  "geometry": {"coordinates":[77.55283,31.0272],"type":"Point"}
}