{
  "type": "Feature",
  "properties": {
    "iso:country":"IN",
    "ks:ks_alt_nam":"LEVAPARA",
    "ks:ks_name":"Levapara",
    "ks:ks_pop":1335,
    "ks:ks_type":"HABITATION",
    "name:eng_x_preferred":[
        "Levapara"
    ],
    "wof:name":"Levapara",
    "wof:placetype":"locality",
    "wof:population":1335
},
  "geometry": {"coordinates":[74.657207,23.734576],"type":"Point"}
}