{
  "type": "Feature",
  "properties": {
    "iso:country":"IN",
    "ks:ks_name":"Mulgam Falia",
    "ks:ks_pop":420,
    "ks:ks_type":"HABITATION",
    "name:eng_x_preferred":[
        "Mulgam Falia"
    ],
    "wof:name":"Mulgam Falia",
    "wof:placetype":"locality",
    "wof:population":420
},
  "geometry": {"coordinates":[73.29472199999999,20.2555],"type":"Point"}
}