{
  "type": "Feature",
  "properties": {
    "iso:country":"IN",
    "ks:ks_name":"Kollapattu",
    "ks:ks_pop":573,
    "ks:ks_type":"HABITATION",
    "name:eng_x_preferred":[
        "Kollapattu"
    ],
    "wof:name":"Kollapattu",
    "wof:placetype":"locality",
    "wof:population":573
},
  "geometry": {"coordinates":[80.14314899999999,13.776755],"type":"Point"}
}