{
  "type": "Feature",
  "properties": {
    "gn:admin1_code":"34.0",
    "gn:admin2_code":"221.0",
    "gn:asciiname":"Purkhotimpur",
    "gn:country_code":"IN",
    "gn:dem":52,
    "gn:feature_class":"P",
    "gn:feature_code":"PPL",
    "gn:name":"Purkhotimpur",
    "gn:population":0,
    "gn:timezone":"Asia/Kolkata",
    "iso:country":"IN",
    "ks:ks_name":"Purkhotimpur",
    "ks:ks_type":"VILLAGE",
    "name:eng_x_preferred":[
        "Purkhotimpur"
    ],
    "wof:name":"Purkhotimpur",
    "wof:placetype":"locality"
},
  "geometry": {"coordinates":[85.63845600000001,25.706652],"type":"Point"}
}