{
  "type": "Feature",
  "properties": {
    "gn:admin1_code":"39",
    "gn:admin2_code":"61.0",
    "gn:asciiname":"Khutera Talla",
    "gn:country_code":"IN",
    "gn:dem":1275,
    "gn:feature_class":"P",
    "gn:feature_code":"PPL",
    "gn:name":"Khutera Talla",
    "gn:population":0,
    "gn:timezone":"Asia/Kolkata",
    "iso:country":"IN",
    "ks:ks_name":"Khutera Talla",
    "ks:ks_type":"VILLAGE",
    "name:eng_x_preferred":[
        "Khutera Talla"
    ],
    "wof:name":"Khutera Talla",
    "wof:placetype":"locality"
},
  "geometry": {"coordinates":[78.989555,29.737108],"type":"Point"}
}