{
  "type": "Feature",
  "properties": {
    "iso:country":"IN",
    "ks:ks_name":"Char Nandan Bati",
    "ks:ks_pop":202,
    "ks:ks_type":"VILLAGE",
    "ks:ks_uagg_main":0,
    "name:eng_x_preferred":[
        "Char Nandan Bati"
    ],
    "wof:name":"Char Nandan Bati",
    "wof:placetype":"neighbourhood",
    "wof:population":202
},
  "geometry": {"coordinates":[88.414939,22.954899],"type":"Point"}
}