{
  "type": "Feature",
  "properties": {
    "iso:country":"IN",
    "ks:ks_name":"Tisangwadi",
    "ks:ks_pop":141,
    "ks:ks_type":"HABITATION",
    "name:eng_x_preferred":[
        "Tisangwadi"
    ],
    "wof:name":"Tisangwadi",
    "wof:placetype":"locality",
    "wof:population":141
},
  "geometry": {"coordinates":[73.449167,17.231111],"type":"Point"}
}