{
  "type": "Feature",
  "properties": {
    "iso:country":"IN",
    "ks:ks_name":"Godaba",
    "ks:ks_pop":200,
    "ks:ks_type":"HABITATION",
    "name:eng_x_preferred":[
        "Godaba"
    ],
    "wof:name":"Godaba",
    "wof:placetype":"locality",
    "wof:population":200
},
  "geometry": {"coordinates":[83.58072,19.493766],"type":"Point"}
}