{
  "type": "Feature",
  "properties": {
    "iso:country":"IN",
    "ks:ks_name":"Gangadpada",
    "ks:ks_pop":155,
    "ks:ks_type":"HABITATION",
    "name:eng_x_preferred":[
        "Gangadpada"
    ],
    "wof:name":"Gangadpada",
    "wof:placetype":"locality",
    "wof:population":155
},
  "geometry": {"coordinates":[73.152974,19.790046],"type":"Point"}
}