{
  "type": "Feature",
  "properties": {
    "iso:country":"IN",
    "ks:ks_name":"Ramnagar",
    "ks:ks_pop":692,
    "ks:ks_type":"VILLAGE",
    "ks:ks_uagg_main":0,
    "name:eng_x_preferred":[
        "Ramnagar"
    ],
    "name:hin_x_preferred":[
        "\u0930\u093e\u092e\u0928\u0917\u0930"
    ],
    "wof:name":"Ramnagar",
    "wof:placetype":"neighbourhood",
    "wof:population":692
},
  "geometry": {"coordinates":[80.158057,27.396885],"type":"Point"}
}