{
  "type": "Feature",
  "properties": {
    "gn:admin1_code":"34.0",
    "gn:admin2_code":"229.0",
    "gn:asciiname":"Mandachh Khurd",
    "gn:country_code":"IN",
    "gn:dem":63,
    "gn:feature_class":"P",
    "gn:feature_code":"PPL",
    "gn:name":"Mand\u0101chh Khurd",
    "gn:population":0,
    "gn:timezone":"Asia/Kolkata",
    "iso:country":"IN",
    "wof:name":"Mandachh Khurd",
    "wof:placetype":"locality"
},
  "geometry": {"coordinates":[85.46738000000001,25.18775],"type":"Point"}
}