{
  "type": "Feature",
  "properties": {
    "iso:country":"IN",
    "ks:ks_name":"Sitanathpur",
    "ks:ks_pop":310,
    "ks:ks_type":"VILLAGE",
    "name:eng_x_preferred":[
        "Sitanathpur"
    ],
    "wof:name":"Sitanathpur",
    "wof:placetype":"locality",
    "wof:population":310
},
  "geometry": {"coordinates":[87.273354,22.585203],"type":"Point"}
}