{
  "type": "Feature",
  "properties": {
    "iso:country":"IN",
    "ks:ks_name":"Depobail",
    "ks:ks_pop":123,
    "ks:ks_type":"HABITATION",
    "name:eng_x_preferred":[
        "Depobail"
    ],
    "wof:name":"Depobail",
    "wof:placetype":"locality",
    "wof:population":123
},
  "geometry": {"coordinates":[74.65935500000001,14.61784],"type":"Point"}
}