{
  "type": "Feature",
  "properties": {
    "gn:country":"IN",
    "gn:fcode":"PPL",
    "gn:population":97966,
    "iso:country":"IN",
    "name:bho_x_preferred":[
        "\u0936\u093e\u092e\u0932\u0940"
    ],
    "name:bpy_x_preferred":[
        "\u09b6\u09be\u09ae\u09b2\u09bf"
    ],
    "name:cat_x_preferred":[
        "Shamli"
    ],
    "name:ceb_x_preferred":[
        "Sh\u0101mli"
    ],
    "name:eng_x_preferred":[
        "Shamli"
    ],
    "name:fra_x_preferred":[
        "Shamli"
    ],
    "name:guj_x_preferred":[
        "\u0ab6\u0abe\u0aae\u0ab2\u0ac0"
    ],
    "name:hif_x_preferred":[
        "Shamli"
    ],
    "name:hin_x_preferred":[
        "\u0936\u093e\u092e\u0932\u0940"
    ],
    "name:ita_x_preferred":[
        "Shamli"
    ],
    "name:mlg_x_preferred":[
        "Shamli"
    ],
    "name:msa_x_preferred":[
        "Shamli"
    ],
    "name:nan_x_preferred":[
        "Shamli"
    ],
    "name:nld_x_preferred":[
        "Shamli"
    ],
    "name:ori_x_preferred":[
        "\u0b36\u0b3e\u0b2e\u0b33\u0b3f"
    ],
    "name:pnb_x_preferred":[
        "\u0634\u0627\u0645\u0644\u06cc"
    ],
    "name:pol_x_preferred":[
        "Shamli"
    ],
    "name:por_x_preferred":[
        "Shamli"
    ],
    "name:san_x_preferred":[
        "\u0936\u093e\u092e\u0932\u0940"
    ],
    "name:swe_x_preferred":[
        "Shamli"
    ],
    "name:urd_x_preferred":[
        "\u0634\u0627\u0645\u0644\u06cc"
    ],
    "name:vie_x_preferred":[
        "Shamli"
    ],
    "name:zho_x_preferred":[
        "\u65af\u54c8\u59c6\u5229"
    ],
    "qs:name":"Shamli",
    "qs:name_adm0":"India",
    "qs:name_adm1":"Uttar Pradesh",
    "qs:photos_9r":0,
    "qs:photos_sr":0,
    "qs:placetype":"Town",
    "qs:pop_sr":"8",
    "wd:wordcount":254,
    "wof:name":"Shamli",
    "wof:placetype":"locality",
    "wof:population":97966
},
  "geometry": {"coordinates":[77.31282,29.44934],"type":"Point"}
}