{
  "type": "Feature",
  "properties": {
    "gn:admin1_code":"35",
    "gn:admin2_code":"438.0",
    "gn:asciiname":"Nagda",
    "gn:country_code":"IN",
    "gn:dem":527,
    "gn:feature_class":"P",
    "gn:feature_code":"PPL",
    "gn:name":"N\u0101gda",
    "gn:population":0,
    "gn:timezone":"Asia/Kolkata",
    "iso:country":"IN",
    "name:ben_x_preferred":[
        "\u09a8\u0997\u09a6\u09be"
    ],
    "name:bih_x_preferred":[
        "\u0928\u093e\u0917\u0926\u093e"
    ],
    "name:bpy_x_preferred":[
        "\u09a8\u0997\u09a6\u09be"
    ],
    "name:ceb_x_preferred":[
        "Nagda"
    ],
    "name:deu_x_preferred":[
        "Nagda"
    ],
    "name:fra_x_preferred":[
        "Nagda"
    ],
    "name:hin_x_preferred":[
        "\u0928\u093e\u0917\u0926\u093e"
    ],
    "name:ita_x_preferred":[
        "Nagda"
    ],
    "name:mlg_x_preferred":[
        "Nagda"
    ],
    "name:msa_x_preferred":[
        "Nagda"
    ],
    "name:new_x_preferred":[
        "\u0928\u093e\u0917\u094d\u0926\u093e"
    ],
    "name:ori_x_preferred":[
        "\u0b28\u0b3e\u0b17\u0b21\u0b3c\u0b3e"
    ],
    "name:por_x_preferred":[
        "Nagda"
    ],
    "name:spa_x_preferred":[
        "Nagda"
    ],
    "name:swe_x_preferred":[
        "Nagda"
    ],
    "name:und_x_variant":[
        "N\u0101gda"
    ],
    "name:vie_x_preferred":[
        "Nagda"
    ],
    "name:zho_x_preferred":[
        "\u7eb3\u683c\u8fbe"
    ],
    "wof:name":"Nagda",
    "wof:placetype":"locality"
},
  "geometry": {"coordinates":[75.27840999999999,22.78945],"type":"Point"}
}