{
  "type": "Feature",
  "properties": {
    "gn:admin1_code":"35",
    "gn:admin2_code":"438.0",
    "gn:asciiname":"Nagda",
    "gn:country_code":"IN",
    "gn:dem":527,
    "gn:feature_class":"P",
    "gn:feature_code":"PPL",
    "gn:name":"N\u0101gda",
    "gn:population":0,
    "gn:timezone":"Asia/Kolkata",
    "iso:country":"IN",
    "name:und_x_variant":[
        "N\u0101gda"
    ],
    "wof:name":"Nagda",
    "wof:placetype":"locality"
},
  "geometry": {"coordinates":[75.27840999999999,22.78945],"type":"Point"}
}