{
  "type": "Feature",
  "properties": {
    "iso:country":"IN",
    "ks:ks_name":"Chakder",
    "ks:ks_pop":370,
    "ks:ks_type":"VILLAGE",
    "name:eng_x_preferred":[
        "Chakder"
    ],
    "wof:name":"Chakder",
    "wof:placetype":"locality",
    "wof:population":370
},
  "geometry": {"coordinates":[72.40920699999999,26.290117],"type":"Point"}
}