{
  "type": "Feature",
  "properties": {
    "iso:country":"IN",
    "ks:ks_name":"Pandey Ka Pura",
    "ks:ks_pop":33,
    "ks:ks_type":"HABITATION",
    "ks:ks_uagg_main":0,
    "name:eng_x_preferred":[
        "Pandey Ka Pura"
    ],
    "wof:name":"Pandey Ka Pura",
    "wof:placetype":"neighbourhood",
    "wof:population":33
},
  "geometry": {"coordinates":[81.659924,26.395058],"type":"Point"}
}