{
  "type": "Feature",
  "properties": {
    "gn:admin1_code":"36.0",
    "gn:admin2_code":"190.0",
    "gn:asciiname":"Deogaon",
    "gn:country_code":"IN",
    "gn:dem":84,
    "gn:feature_class":"P",
    "gn:feature_code":"PPL",
    "gn:name":"Deogaon",
    "gn:population":0,
    "gn:timezone":"Asia/Kolkata",
    "iso:country":"IN",
    "wof:name":"Deogaon",
    "wof:placetype":"locality"
},
  "geometry": {"coordinates":[83.68328000000002,26.60512],"type":"Point"}
}