{
  "type": "Feature",
  "properties": {
    "iso:country":"IN",
    "ks:ks_alt_nam":"HANDEMALA",
    "ks:ks_name":"Handemala",
    "ks:ks_pop":230,
    "ks:ks_type":"HABITATION",
    "name:eng_x_preferred":[
        "Handemala"
    ],
    "wof:name":"Handemala",
    "wof:placetype":"locality",
    "wof:population":230
},
  "geometry": {"coordinates":[74.23743399999999,16.95104],"type":"Point"}
}