{
  "type": "Feature",
  "properties": {
    "gn:admin1_code":"3.0",
    "gn:admin2_code":"315",
    "gn:asciiname":"Bara Digar",
    "gn:country_code":"IN",
    "gn:dem":313,
    "gn:feature_class":"P",
    "gn:feature_code":"PPL",
    "gn:name":"Bara Digar",
    "gn:population":0,
    "gn:timezone":"Asia/Kolkata",
    "iso:country":"IN",
    "name:und_x_variant":[
        "Barar Digar",
        "Bara Digar"
    ],
    "wof:name":"Bara Digar",
    "wof:placetype":"locality"
},
  "geometry": {"coordinates":[93.30216,25.37408],"type":"Point"}
}