{
  "type": "Feature",
  "properties": {
    "iso:country":"IN",
    "ks:ks_name":"Rabarika",
    "ks:ks_pop":513,
    "ks:ks_type":"VILLAGE",
    "name:eng_x_preferred":[
        "Rabarika"
    ],
    "wof:name":"Rabarika",
    "wof:placetype":"locality",
    "wof:population":513
},
  "geometry": {"coordinates":[71.5587,21.2946],"type":"Point"}
}