{
  "type": "Feature",
  "properties": {
    "iso:country":"IN",
    "ks:ks_name":"Chhatan Ka Purwa",
    "ks:ks_pop":20,
    "ks:ks_type":"HABITATION",
    "name:eng_x_preferred":[
        "Chhatan Ka Purwa"
    ],
    "wof:name":"Chhatan Ka Purwa",
    "wof:placetype":"locality",
    "wof:population":20
},
  "geometry": {"coordinates":[80.763605,25.236768],"type":"Point"}
}