{
  "type": "Feature",
  "properties": {
    "gn:admin1_code":"35.0",
    "gn:admin2_code":"438",
    "gn:asciiname":"Kod",
    "gn:country_code":"IN",
    "gn:dem":549,
    "gn:feature_class":"P",
    "gn:feature_code":"PPL",
    "gn:name":"Kod",
    "gn:population":0,
    "gn:timezone":"Asia/Kolkata",
    "iso:country":"IN",
    "name:ara_x_preferred":[
        "\u0643\u0648\u062f"
    ],
    "wof:name":"Kod",
    "wof:placetype":"locality"
},
  "geometry": {"coordinates":[75.18621999999998,22.88498],"type":"Point"}
}