{
  "type": "Feature",
  "properties": {
    "iso:country":"IN",
    "ks:ks_alt_nam":"Kol\u0101d",
    "ks:ks_name":"Kolad",
    "ks:ks_pop":652,
    "ks:ks_type":"VILLAGE",
    "name:eng_x_preferred":[
        "Kolad"
    ],
    "name:eng_x_variant":[
        "Kol\u0101d"
    ],
    "wof:name":"Kolad",
    "wof:placetype":"locality",
    "wof:population":652
},
  "geometry": {"coordinates":[85.418969,23.187267],"type":"Point"}
}