{
  "type": "Feature",
  "properties": {
    "iso:country":"IN",
    "ks:ks_alt_nam":"DOM TOLA",
    "ks:ks_name":"Dom Tola",
    "ks:ks_pop":86,
    "ks:ks_type":"HABITATION",
    "name:eng_x_preferred":[
        "Dom Tola"
    ],
    "wof:name":"Dom Tola",
    "wof:placetype":"locality",
    "wof:population":86
},
  "geometry": {"coordinates":[86.046201,25.112801],"type":"Point"}
}