{
  "type": "Feature",
  "properties": {
    "iso:country":"IN",
    "ks:ks_name":"Nidawan",
    "ks:ks_pop":697,
    "ks:ks_type":"HABITATION",
    "name:eng_x_preferred":[
        "Nidawan"
    ],
    "wof:name":"Nidawan",
    "wof:placetype":"locality",
    "wof:population":697
},
  "geometry": {"coordinates":[81.603218,23.072506],"type":"Point"}
}