{
  "type": "Feature",
  "properties": {
    "gn:admin1_code":"11",
    "gn:admin2_code":"23.0",
    "gn:asciiname":"Chihani",
    "gn:country_code":"IN",
    "gn:dem":1689,
    "gn:feature_class":"P",
    "gn:feature_code":"PPL",
    "gn:name":"Chih\u0101ni",
    "gn:population":0,
    "gn:timezone":"Asia/Kolkata",
    "iso:country":"IN",
    "name:ara_x_preferred":[
        "\u0627\u0644\u0634\u064a\u062d\u0627\u0646\u064a"
    ],
    "name:azb_x_preferred":[
        "\u0634\u06cc\u062d\u0627\u0646\u06cc"
    ],
    "name:deu_x_preferred":[
        "Chihani"
    ],
    "name:fas_x_preferred":[
        "\u0634\u06cc\u062d\u0627\u0646\u06cc"
    ],
    "name:fra_x_preferred":[
        "Chihani"
    ],
    "name:ita_x_preferred":[
        "Chihani"
    ],
    "name:msa_x_preferred":[
        "Chihani"
    ],
    "name:por_x_preferred":[
        "Chihani"
    ],
    "name:ron_x_preferred":[
        "Chihani"
    ],
    "name:spa_x_preferred":[
        "Chihani"
    ],
    "name:vie_x_preferred":[
        "Chihani"
    ],
    "name:zho_x_preferred":[
        "\u5e0c\u54c8\u5c3c"
    ],
    "wof:name":"Chihani",
    "wof:placetype":"locality"
},
  "geometry": {"coordinates":[76.57911999999997,32.47541],"type":"Point"}
}