{
  "type": "Feature",
  "properties": {
    "iso:country":"IN",
    "ks:ks_name":"Chakalipathar",
    "ks:ks_pop":214,
    "ks:ks_type":"VILLAGE",
    "name:eng_x_preferred":[
        "Chakalipathar"
    ],
    "wof:name":"Chakalipathar",
    "wof:placetype":"locality",
    "wof:population":214
},
  "geometry": {"coordinates":[93.941688,26.304831],"type":"Point"}
}