{
  "type": "Feature",
  "properties": {
    "iso:country":"IN",
    "ks:ks_alt_nam":"South tola",
    "ks:ks_name":"South Tola",
    "ks:ks_pop":524,
    "ks:ks_type":"HABITATION",
    "name:eng_x_preferred":[
        "South Tola"
    ],
    "wof:name":"South Tola",
    "wof:placetype":"locality",
    "wof:population":524
},
  "geometry": {"coordinates":[86.72055,24.7674],"type":"Point"}
}