{
  "type": "Feature",
  "properties": {
    "iso:country":"IN",
    "ks:ks_alt_nam":"naaraioorani",
    "ks:ks_name":"Naaraioorani",
    "ks:ks_pop":140,
    "ks:ks_type":"HABITATION",
    "name:eng_x_preferred":[
        "Naaraioorani"
    ],
    "wof:name":"Naaraioorani",
    "wof:placetype":"locality",
    "wof:population":140
},
  "geometry": {"coordinates":[78.414503,9.277637],"type":"Point"}
}