{
  "type": "Feature",
  "properties": {
    "iso:country":"IN",
    "ks:ks_name":"Bavadagudde Kukkundoor",
    "ks:ks_pop":75,
    "ks:ks_type":"HABITATION",
    "name:eng_x_preferred":[
        "Bavadagudde Kukkundoor"
    ],
    "wof:name":"Bavadagudde Kukkundoor",
    "wof:placetype":"locality",
    "wof:population":75
},
  "geometry": {"coordinates":[74.914473,13.232529],"type":"Point"}
}