{
  "type": "Feature",
  "properties": {
    "gn:admin1_code":"35",
    "gn:admin2_code":"449.0",
    "gn:asciiname":"Sankai",
    "gn:country_code":"IN",
    "gn:dem":392,
    "gn:feature_class":"P",
    "gn:feature_code":"PPL",
    "gn:name":"S\u0101nkai",
    "gn:population":0,
    "gn:timezone":"Asia/Kolkata",
    "iso:country":"IN",
    "name:fra_x_preferred":[
        "Sankai"
    ],
    "name:ita_x_preferred":[
        "Sankai"
    ],
    "name:spa_x_preferred":[
        "Sankai"
    ],
    "wof:name":"Sankai",
    "wof:placetype":"locality"
},
  "geometry": {"coordinates":[78.04469,22.43056],"type":"Point"}
}