{
  "type": "Feature",
  "properties": {
    "iso:country":"IN",
    "ks:ks_name":"Borsi",
    "ks:ks_pop":917,
    "ks:ks_type":"VILLAGE",
    "name:eng_x_preferred":[
        "Borsi"
    ],
    "wof:name":"Borsi",
    "wof:placetype":"locality",
    "wof:population":917
},
  "geometry": {"coordinates":[82.085781,21.750097],"type":"Point"}
}