{
  "type": "Feature",
  "properties": {
    "iso:country":"IN",
    "ks:ks_name":"Deevaramane",
    "ks:ks_pop":8,
    "ks:ks_type":"HABITATION",
    "name:eng_x_preferred":[
        "Deevaramane"
    ],
    "wof:name":"Deevaramane",
    "wof:placetype":"locality",
    "wof:population":8
},
  "geometry": {"coordinates":[74.728351,14.034835],"type":"Point"}
}