{
  "type": "Feature",
  "properties": {
    "iso:country":"IN",
    "ks:ks_name":"Mekalaguda",
    "ks:ks_pop":8,
    "ks:ks_type":"HABITATION",
    "name:eng_x_preferred":[
        "Mekalaguda"
    ],
    "wof:name":"Mekalaguda",
    "wof:placetype":"locality",
    "wof:population":8
},
  "geometry": {"coordinates":[79.26490800000001,19.293274],"type":"Point"}
}