{
  "type": "Feature",
  "properties": {
    "iso:country":"IN",
    "ks:ks_name":"Bharbari",
    "ks:ks_pop":1610,
    "ks:ks_type":"VILLAGE",
    "ks:ks_uagg_main":0,
    "name:eng_x_preferred":[
        "Bharbari"
    ],
    "wof:name":"Bharbari",
    "wof:placetype":"neighbourhood",
    "wof:population":1610
},
  "geometry": {"coordinates":[90.88083899999999,26.079432],"type":"Point"}
}