{
  "type": "Feature",
  "properties": {
    "iso:country":"IN",
    "ks:ks_name":"JungleBlock No-4",
    "ks:ks_pop":15,
    "ks:ks_type":"VILLAGE",
    "name:eng_x_preferred":[
        "JungleBlock No-4"
    ],
    "wof:name":"JungleBlock No-4",
    "wof:placetype":"locality",
    "wof:population":15
},
  "geometry": {"coordinates":[84.10626000000001,19.134921],"type":"Point"}
}