{
  "type": "Feature",
  "properties": {
    "gn:admin1_code":"2",
    "gn:admin2_code":"545.0",
    "gn:asciiname":"Chamavaram",
    "gn:country_code":"IN",
    "gn:dem":28,
    "gn:feature_class":"P",
    "gn:feature_code":"PPL",
    "gn:name":"Ch\u0101mavaram",
    "gn:population":0,
    "gn:timezone":"Asia/Kolkata",
    "iso:country":"IN",
    "name:tel_x_preferred":[
        "\u0c1a\u0c3e\u0c2e\u0c35\u0c30\u0c02"
    ],
    "wof:name":"Chamavaram",
    "wof:placetype":"locality"
},
  "geometry": {"coordinates":[82.51606,17.32492],"type":"Point"}
}