{
  "type": "Feature",
  "properties": {
    "gn:admin1_code":"19.0",
    "gn:admin2_code":"555.0",
    "gn:asciiname":"Dombarkop",
    "gn:country_code":"IN",
    "gn:dem":733,
    "gn:feature_class":"P",
    "gn:feature_code":"PPL",
    "gn:name":"Dombarkop",
    "gn:population":0,
    "gn:timezone":"Asia/Kolkata",
    "iso:country":"IN",
    "wof:name":"Dombarkop",
    "wof:placetype":"locality"
},
  "geometry": {"coordinates":[74.79680999999999,15.58586],"type":"Point"}
}