{
  "type": "Feature",
  "properties": {
    "iso:country":"IN",
    "ks:ks_name":"Rilkot",
    "ks:ks_pop":39,
    "ks:ks_type":"VILLAGE",
    "name:eng_x_preferred":[
        "Rilkot"
    ],
    "wof:name":"Rilkot",
    "wof:placetype":"locality",
    "wof:population":39
},
  "geometry": {"coordinates":[80.208254,30.309873],"type":"Point"}
}