{
  "type": "Feature",
  "properties": {
    "iso:country":"IN",
    "ks:ks_name":"Nagappankottai",
    "ks:ks_pop":136,
    "ks:ks_type":"HABITATION",
    "ks:ks_uagg_main":0,
    "name:eng_x_preferred":[
        "Nagappankottai"
    ],
    "wof:name":"Nagappankottai",
    "wof:placetype":"neighbourhood",
    "wof:population":136
},
  "geometry": {"coordinates":[78.16010300000001,12.445291],"type":"Point"}
}