{
  "type": "Feature",
  "properties": {
    "iso:country":"IN",
    "ks:ks_name":"P Belahan",
    "ks:ks_pop":135,
    "ks:ks_type":"HABITATION",
    "ks:ks_uagg_main":0,
    "name:eng_x_preferred":[
        "P Belahan"
    ],
    "wof:name":"P Belahan",
    "wof:placetype":"neighbourhood",
    "wof:population":135
},
  "geometry": {"coordinates":[81.415018,26.178155],"type":"Point"}
}