{
  "type": "Feature",
  "properties": {
    "iso:country":"IN",
    "ks:ks_alt_nam":"PIPALYA VEERAN",
    "ks:ks_name":"Pipalya Veeran",
    "ks:ks_pop":18,
    "ks:ks_type":"HABITATION",
    "name:eng_x_preferred":[
        "Pipalya Veeran"
    ],
    "wof:name":"Pipalya Veeran",
    "wof:placetype":"locality",
    "wof:population":18
},
  "geometry": {"coordinates":[74.74896,23.951957],"type":"Point"}
}