{
  "type": "Feature",
  "properties": {
    "gn:admin1_code":"29.0",
    "gn:admin2_code":"244.0",
    "gn:asciiname":"Chentang",
    "gn:country_code":"IN",
    "gn:dem":1385,
    "gn:feature_class":"P",
    "gn:feature_code":"PPL",
    "gn:name":"Chentang",
    "gn:population":0,
    "gn:timezone":"Asia/Kolkata",
    "iso:country":"IN",
    "name:ceb_x_preferred":[
        "Chentang"
    ],
    "name:swe_x_preferred":[
        "Chentang"
    ],
    "name:zho_x_preferred":[
        "\u9648\u5858\u9547"
    ],
    "wof:name":"Chentang",
    "wof:placetype":"locality"
},
  "geometry": {"coordinates":[88.72004,27.24587],"type":"Point"}
}