{
  "type": "Feature",
  "properties": {
    "gn:admin1_code":"36.0",
    "gn:admin2_code":"134.0",
    "gn:asciiname":"Timarpur",
    "gn:country_code":"IN",
    "gn:dem":248,
    "gn:feature_class":"P",
    "gn:feature_code":"PPL",
    "gn:name":"Timarpur",
    "gn:population":0,
    "gn:timezone":"Asia/Kolkata",
    "iso:country":"IN",
    "name:ara_x_preferred":[
        "\u062a\u064a\u0645\u0627\u0631\u0628\u0648\u0631"
    ],
    "name:ben_bn_x_preferred":[
        "\u09a4\u09bf\u09ae\u09be\u09b0\u09aa\u09c1\u09b0"
    ],
    "name:ben_in_x_preferred":[
        "\u09a4\u09bf\u09ae\u09be\u09b0\u09aa\u09c1\u09b0"
    ],
    "name:guj_x_preferred":[
        "\u0aa4\u0abf\u0aae\u0ab0\u0aaa\u0ac1\u0ab0"
    ],
    "name:hin_x_preferred":[
        "\u0924\u093f\u092e\u093e\u0930\u092a\u0941\u0930"
    ],
    "name:kan_x_preferred":[
        "\u0ca4\u0cbf\u0cae\u0cbe\u0cb0\u0ccd"
    ],
    "name:mal_x_preferred":[
        "\u0d24\u0d3f\u0d2e\u0d7c\u0d2a\u0d42\u0d7c"
    ],
    "name:mar_x_preferred":[
        "\u0924\u093f\u092e\u093e\u0930\u092a\u0942\u0930"
    ],
    "name:pan_x_preferred":[
        "\u0a24\u0a3f\u0a2e\u0a30\u0a2a\u0a41\u0a30"
    ],
    "name:tam_x_preferred":[
        "\u0ba4\u0bbf\u0bae\u0bbe\u0bb0\u0bcd\u0baa\u0bc2\u0bb0\u0bcd"
    ],
    "name:tel_x_preferred":[
        "\u0c1f\u0c3f\u0c2e\u0c30\u0c4d"
    ],
    "name:urd_x_preferred":[
        "\u062a\u06cc\u0645\u0627\u0631 \u067e\u0648\u0631"
    ],
    "wof:name":"Timarpur",
    "wof:placetype":"neighbourhood"
},
  "geometry": {"coordinates":[78.13603999999999,29.54233],"type":"Point"}
}