{
  "type": "Feature",
  "properties": {
    "gn:admin1_code":"40.0",
    "gn:admin2_code":"533.0",
    "gn:asciiname":"Macherla",
    "gn:country_code":"IN",
    "gn:dem":355,
    "gn:feature_class":"P",
    "gn:feature_code":"PPL",
    "gn:name":"Macherla",
    "gn:population":0,
    "gn:timezone":"Asia/Kolkata",
    "iso:country":"IN",
    "wof:name":"Macherla",
    "wof:placetype":"locality"
},
  "geometry": {"coordinates":[78.20425999999998,18.85957],"type":"Point"}
}