{
  "type": "Feature",
  "properties": {
    "iso:country":"IN",
    "ks:ks_name":"Aistala",
    "ks:ks_pop":19533,
    "ks:ks_type":"VILLAGE",
    "ks:ks_uagg_main":0,
    "name:eng_x_preferred":[
        "Aistala"
    ],
    "wof:name":"Aistala",
    "wof:placetype":"neighbourhood",
    "wof:population":19533
},
  "geometry": {"coordinates":[88.55669399999999,23.186587],"type":"Point"}
}