{
  "type": "Feature",
  "properties": {
    "iso:country":"IN",
    "ks:ks_name":"Jaisinghpura Was Bahlor",
    "ks:ks_pop":483,
    "ks:ks_type":"HABITATION",
    "name:eng_x_preferred":[
        "Jaisinghpura Was Bahlor"
    ],
    "wof:name":"Jaisinghpura Was Bahlor",
    "wof:placetype":"locality",
    "wof:population":483
},
  "geometry": {"coordinates":[76.10384500000001,27.202564],"type":"Point"}
}