{
  "type": "Feature",
  "properties": {
    "iso:country":"IN",
    "ks:ks_name":"Porotola",
    "ks:ks_pop":90,
    "ks:ks_type":"VILLAGE",
    "name:eng_x_preferred":[
        "Porotola"
    ],
    "wof:name":"Porotola",
    "wof:placetype":"locality",
    "wof:population":90
},
  "geometry": {"coordinates":[87.483943,24.991626],"type":"Point"}
}