{
  "type": "Feature",
  "properties": {
    "gn:admin1_code":"19.0",
    "gn:admin2_code":"573.0",
    "gn:asciiname":"Bhadragaudanakoppal",
    "gn:country_code":"IN",
    "gn:dem":827,
    "gn:feature_class":"P",
    "gn:feature_code":"PPL",
    "gn:name":"Bhadragaudanakoppal",
    "gn:population":0,
    "gn:timezone":"Asia/Kolkata",
    "iso:country":"IN",
    "wof:name":"Bhadragaudanakoppal",
    "wof:placetype":"locality"
},
  "geometry": {"coordinates":[76.72296999999998,12.80798],"type":"Point"}
}