{
  "type": "Feature",
  "properties": {
    "iso:country":"IN",
    "ks:ks_name":"Baghakanali",
    "ks:ks_pop":52,
    "ks:ks_type":"VILLAGE",
    "name:eng_x_preferred":[
        "Baghakanali"
    ],
    "wof:name":"Baghakanali",
    "wof:placetype":"locality",
    "wof:population":52
},
  "geometry": {"coordinates":[86.807012,24.083678],"type":"Point"}
}