{
  "type": "Feature",
  "properties": {
    "iso:country":"IN",
    "ks:ks_name":"Barghola Pt I",
    "ks:ks_pop":1561,
    "ks:ks_type":"VILLAGE",
    "name:eng_x_preferred":[
        "Barghola Pt I"
    ],
    "wof:name":"Barghola Pt I",
    "wof:placetype":"locality",
    "wof:population":1561
},
  "geometry": {"coordinates":[90.579498,26.281923],"type":"Point"}
}