{
  "type": "Feature",
  "properties": {
    "iso:country":"IN",
    "ks:ks_name":"Sumer Nagla",
    "ks:ks_pop":175,
    "ks:ks_type":"HABITATION",
    "ks:ks_uagg_main":0,
    "name:eng_x_preferred":[
        "Sumer Nagla"
    ],
    "wof:name":"Sumer Nagla",
    "wof:placetype":"neighbourhood",
    "wof:population":175
},
  "geometry": {"coordinates":[79.36664,27.293819],"type":"Point"}
}