{
  "type": "Feature",
  "properties": {
    "iso:country":"IN",
    "ks:ks_name":"Shyam Nagar",
    "ks:ks_pop":1236,
    "ks:ks_type":"HABITATION",
    "name:eng_x_preferred":[
        "Shyam Nagar"
    ],
    "wof:name":"Shyam Nagar",
    "wof:placetype":"locality",
    "wof:population":1236
},
  "geometry": {"coordinates":[75.18123300000001,26.886325],"type":"Point"}
}