{
  "type": "Feature",
  "properties": {
    "gn:admin1_code":"36.0",
    "gn:admin2_code":"143.0",
    "gn:asciiname":"Kauriaganj",
    "gn:country_code":"IN",
    "gn:dem":182,
    "gn:feature_class":"P",
    "gn:feature_code":"PPL",
    "gn:name":"Kauri\u0101ganj",
    "gn:population":0,
    "gn:timezone":"Asia/Kolkata",
    "iso:country":"IN",
    "name:bpy_x_preferred":[
        "\u0995\u09cc\u09b0\u09bf\u09af\u09bc\u09be\u0997\u099e\u09cd\u099c"
    ],
    "name:ita_x_preferred":[
        "Kauriaganj"
    ],
    "name:msa_x_preferred":[
        "Kauriaganj"
    ],
    "name:new_x_preferred":[
        "\u0915\u094c\u0930\u093f\u092f\u093e\u0917\u091e\u094d\u091c"
    ],
    "name:nld_x_preferred":[
        "Kauriaganj"
    ],
    "name:pol_x_preferred":[
        "Kauriaganj"
    ],
    "name:por_x_preferred":[
        "Kauriaganj"
    ],
    "name:und_x_variant":[
        "Kauri\u0101ganj",
        "Kaurj\u0101gani"
    ],
    "name:urd_x_preferred":[
        "\u06a9\u0648\u0631\u06cc\u0627 \u06af\u0646\u062c"
    ],
    "name:vie_x_preferred":[
        "Kauriaganj"
    ],
    "name:zho_x_preferred":[
        "\u8003\u91cc\u4e9a\u7518\u6770"
    ],
    "wof:name":"Kauriaganj",
    "wof:placetype":"locality"
},
  "geometry": {"coordinates":[78.3116,27.85774],"type":"Point"}
}