{
  "type": "Feature",
  "properties": {
    "gn:admin1_code":"36.0",
    "gn:admin2_code":"143.0",
    "gn:asciiname":"Kauriaganj",
    "gn:country_code":"IN",
    "gn:dem":182,
    "gn:feature_class":"P",
    "gn:feature_code":"PPL",
    "gn:name":"Kauri\u0101ganj",
    "gn:population":0,
    "gn:timezone":"Asia/Kolkata",
    "iso:country":"IN",
    "name:und_x_variant":[
        "Kauri\u0101ganj",
        "Kaurj\u0101gani"
    ],
    "wof:name":"Kauriaganj",
    "wof:placetype":"locality"
},
  "geometry": {"coordinates":[78.3116,27.85774],"type":"Point"}
}