{
  "type": "Feature",
  "properties": {
    "gn:admin1_code":"35.0",
    "gn:admin2_code":"443",
    "gn:asciiname":"Gyaraspur",
    "gn:country_code":"IN",
    "gn:dem":456,
    "gn:feature_class":"P",
    "gn:feature_code":"PPL",
    "gn:name":"Gy\u0101raspur",
    "gn:population":0,
    "gn:timezone":"Asia/Kolkata",
    "iso:country":"IN",
    "name:deu_x_preferred":[
        "Gyaraspur"
    ],
    "name:und_x_variant":[
        "Gy\u0101raspur"
    ],
    "wof:name":"Gyaraspur",
    "wof:placetype":"locality"
},
  "geometry": {"coordinates":[78.11439,23.66755],"type":"Point"}
}