{
  "type": "Feature",
  "properties": {
    "gn:admin1_code":"37",
    "gn:admin2_code":"410.0",
    "gn:asciiname":"Sarona",
    "gn:country_code":"IN",
    "gn:dem":284,
    "gn:feature_class":"P",
    "gn:feature_code":"PPL",
    "gn:name":"Sarona",
    "gn:population":0,
    "gn:timezone":"Asia/Kolkata",
    "iso:country":"IN",
    "name:ceb_x_preferred":[
        "Sarona"
    ],
    "name:heb_x_preferred":[
        "\u05e9\u05e8\u05d5\u05e0\u05d4"
    ],
    "name:rus_x_preferred":[
        "\u0421\u0430\u0440\u043e\u043d\u0430"
    ],
    "name:swe_x_preferred":[
        "Sarona"
    ],
    "wof:name":"Sarona",
    "wof:placetype":"neighbourhood"
},
  "geometry": {"coordinates":[81.57505,21.24481],"type":"Point"}
}