{
  "type": "Feature",
  "properties": {
    "gn:admin1_code":"11",
    "gn:admin2_code":"31.0",
    "gn:asciiname":"Ambka",
    "gn:country_code":"IN",
    "gn:dem":568,
    "gn:feature_class":"P",
    "gn:feature_code":"PPL",
    "gn:name":"Ambka",
    "gn:population":0,
    "gn:timezone":"Asia/Kolkata",
    "iso:country":"IN",
    "wof:name":"Ambka",
    "wof:placetype":"locality"
},
  "geometry": {"coordinates":[76.85630999999999,30.93899],"type":"Point"}
}