{
  "type": "Feature",
  "properties": {
    "iso:country":"IN",
    "ks:ks_name":"Khariya",
    "ks:ks_pop":367,
    "ks:ks_type":"HABITATION",
    "name:eng_x_preferred":[
        "Khariya"
    ],
    "wof:name":"Khariya",
    "wof:placetype":"locality",
    "wof:population":367
},
  "geometry": {"coordinates":[72.929778,22.925111],"type":"Point"}
}