{
  "type": "Feature",
  "properties": {
    "iso:country":"IN",
    "ks:ks_name":"Katlang",
    "ks:ks_pop":164,
    "ks:ks_type":"VILLAGE",
    "name:eng_x_preferred":[
        "Katlang"
    ],
    "wof:name":"Katlang",
    "wof:placetype":"locality",
    "wof:population":164
},
  "geometry": {"coordinates":[83.26069200000001,19.732636],"type":"Point"}
}