{
  "type": "Feature",
  "properties": {
    "iso:country":"IN",
    "ks:ks_name":"Darapara P I",
    "ks:ks_pop":323,
    "ks:ks_type":"HABITATION",
    "name:eng_x_preferred":[
        "Darapara P I"
    ],
    "wof:name":"Darapara P I",
    "wof:placetype":"locality",
    "wof:population":323
},
  "geometry": {"coordinates":[90.69996,25.985546],"type":"Point"}
}