{
  "type": "Feature",
  "properties": {
    "iso:country":"IN",
    "ks:ks_name":"Mahmdabad",
    "ks:ks_pop":895,
    "ks:ks_type":"VILLAGE",
    "ks:ks_uagg_main":0,
    "name:eng_x_preferred":[
        "Mahmdabad"
    ],
    "wof:name":"Mahmdabad",
    "wof:placetype":"neighbourhood",
    "wof:population":895
},
  "geometry": {"coordinates":[82.64665100000001,25.956439],"type":"Point"}
}