{
  "type": "Feature",
  "properties": {
    "iso:country":"IN",
    "ks:ks_name":"Morituni Missing",
    "ks:ks_pop":150,
    "ks:ks_type":"HABITATION",
    "ks:ks_uagg_main":0,
    "name:eng_x_preferred":[
        "Morituni Missing"
    ],
    "wof:name":"Morituni Missing",
    "wof:placetype":"neighbourhood",
    "wof:population":150
},
  "geometry": {"coordinates":[94.183381,26.967119],"type":"Point"}
}