{
  "type": "Feature",
  "properties": {
    "iso:country":"IN",
    "ks:ks_name":"Girgaon",
    "ks:ks_pop":2367,
    "ks:ks_type":"VILLAGE",
    "name:eng_x_preferred":[
        "Girgaon"
    ],
    "wof:name":"Girgaon",
    "wof:placetype":"locality",
    "wof:population":2367
},
  "geometry": {"coordinates":[72.835466,20.155383],"type":"Point"}
}