{
  "type": "Feature",
  "properties": {
    "iso:country":"IN",
    "ks:ks_name":"1 NGR",
    "ks:ks_pop":152,
    "ks:ks_type":"VILLAGE",
    "name:eng_x_preferred":[
        "1 NGR"
    ],
    "wof:name":"1 NGR",
    "wof:placetype":"locality",
    "wof:population":152
},
  "geometry": {"coordinates":[74.47118,29.69644],"type":"Point"}
}