{
  "type": "Feature",
  "properties": {
    "iso:country":"IN",
    "ks:ks_name":"Dhobana",
    "ks:ks_pop":91,
    "ks:ks_type":"VILLAGE",
    "name:eng_x_preferred":[
        "Dhobana"
    ],
    "wof:name":"Dhobana",
    "wof:placetype":"locality",
    "wof:population":91
},
  "geometry": {"coordinates":[87.492898,24.992986],"type":"Point"}
}