{
  "type": "Feature",
  "properties": {
    "iso:country":"IN",
    "ks:ks_alt_nam":"Eara south",
    "ks:ks_name":"Eara South",
    "ks:ks_pop":1030,
    "ks:ks_type":"HABITATION",
    "name:eng_x_preferred":[
        "Eara South"
    ],
    "wof:name":"Eara South",
    "wof:placetype":"locality",
    "wof:population":1030
},
  "geometry": {"coordinates":[76.499431,9.479999],"type":"Point"}
}