{
  "type": "Feature",
  "properties": {
    "iso:country":"IN",
    "ks:ks_name":"Pattakarimb",
    "ks:ks_pop":587,
    "ks:ks_type":"HABITATION",
    "name:eng_x_preferred":[
        "Pattakarimb"
    ],
    "wof:name":"Pattakarimb",
    "wof:placetype":"locality",
    "wof:population":587
},
  "geometry": {"coordinates":[76.365905,11.270035],"type":"Point"}
}