{
  "type": "Feature",
  "properties": {
    "iso:country":"IN",
    "ks:ks_name":"Arahans",
    "ks:ks_pop":367,
    "ks:ks_type":"VILLAGE",
    "name:eng_x_preferred":[
        "Arahans"
    ],
    "wof:name":"Arahans",
    "wof:placetype":"locality",
    "wof:population":367
},
  "geometry": {"coordinates":[84.234059,23.375912],"type":"Point"}
}