{
  "type": "Feature",
  "properties": {
    "gn:admin1_code":"34.0",
    "gn:admin2_code":"229.0",
    "gn:asciiname":"Kaipur",
    "gn:country_code":"IN",
    "gn:dem":64,
    "gn:feature_class":"P",
    "gn:feature_code":"PPL",
    "gn:name":"Kaipur",
    "gn:population":0,
    "gn:timezone":"Asia/Kolkata",
    "iso:country":"IN",
    "wof:name":"Kaipur",
    "wof:placetype":"neighbourhood"
},
  "geometry": {"coordinates":[85.57168,25.12018],"type":"Point"}
}