{
  "type": "Feature",
  "properties": {
    "gn:admin1_code":"38.0",
    "gn:admin2_code":"352.0",
    "gn:asciiname":"Karambi",
    "gn:country_code":"IN",
    "gn:dem":241,
    "gn:feature_class":"P",
    "gn:feature_code":"PPL",
    "gn:name":"Karambi",
    "gn:population":0,
    "gn:timezone":"Asia/Kolkata",
    "iso:country":"IN",
    "ks:ks_name":"Karambi",
    "ks:ks_pop":87,
    "ks:ks_type":"VILLAGE",
    "name:eng_x_preferred":[
        "Karambi"
    ],
    "wof:name":"Karambi",
    "wof:placetype":"locality",
    "wof:population":87
},
  "geometry": {"coordinates":[87.622254,25.22344],"type":"Point"}
}