{
  "type": "Feature",
  "properties": {
    "iso:country":"IN",
    "ks:ks_name":"Sahabad",
    "ks:ks_pop":521,
    "ks:ks_type":"VILLAGE",
    "ks:ks_uagg_main":0,
    "name:eng_x_preferred":[
        "Sahabad"
    ],
    "wof:name":"Sahabad",
    "wof:placetype":"neighbourhood",
    "wof:population":521
},
  "geometry": {"coordinates":[86.050659,20.369641],"type":"Point"}
}