{
  "type": "Feature",
  "properties": {
    "gn:admin1_code":"19.0",
    "gn:admin2_code":"584.0",
    "gn:asciiname":"Chikgopahalli",
    "gn:country_code":"IN",
    "gn:dem":687,
    "gn:feature_class":"P",
    "gn:feature_code":"PPL",
    "gn:name":"Chikgopahalli",
    "gn:population":0,
    "gn:timezone":"Asia/Kolkata",
    "iso:country":"IN",
    "wof:name":"Chikgopahalli",
    "wof:placetype":"locality"
},
  "geometry": {"coordinates":[77.40156,12.72827],"type":"Point"}
}