{
  "type": "Feature",
  "properties": {
    "iso:country":"IN",
    "ks:ks_name":"Sehapura",
    "ks:ks_pop":266,
    "ks:ks_type":"HABITATION",
    "ks:ks_uagg_main":0,
    "name:eng_x_preferred":[
        "Sehapura"
    ],
    "wof:name":"Sehapura",
    "wof:placetype":"neighbourhood",
    "wof:population":266
},
  "geometry": {"coordinates":[77.75454999999999,26.986405],"type":"Point"}
}