{
  "type": "Feature",
  "properties": {
    "iso:country":"IN",
    "ks:ks_name":"Chanaghar",
    "ks:ks_pop":1714,
    "ks:ks_type":"HABITATION",
    "name:eng_x_preferred":[
        "Chanaghar"
    ],
    "wof:name":"Chanaghar",
    "wof:placetype":"locality",
    "wof:population":1714
},
  "geometry": {"coordinates":[85.847044,19.99885],"type":"Point"}
}