{
  "type": "Feature",
  "properties": {
    "iso:country":"IN",
    "ks:ks_name":"Miani Malahan",
    "ks:ks_pop":16,
    "ks:ks_type":"VILLAGE",
    "name:eng_x_preferred":[
        "Miani Malahan"
    ],
    "wof:name":"Miani Malahan",
    "wof:placetype":"locality",
    "wof:population":16
},
  "geometry": {"coordinates":[75.544023,31.957082],"type":"Point"}
}