{
  "type": "Feature",
  "properties": {
    "iso:country":"IN",
    "ks:ks_name":"Narsing Runda",
    "ks:ks_pop":139,
    "ks:ks_type":"HABITATION",
    "name:eng_x_preferred":[
        "Narsing Runda"
    ],
    "wof:name":"Narsing Runda",
    "wof:placetype":"locality",
    "wof:population":139
},
  "geometry": {"coordinates":[74.689075,22.707947],"type":"Point"}
}