{
  "type": "Feature",
  "properties": {
    "gn:admin1_code":"25.0",
    "gn:admin2_code":"606.0",
    "gn:asciiname":"Perappanankadu",
    "gn:country_code":"IN",
    "gn:dem":72,
    "gn:feature_class":"P",
    "gn:feature_code":"PPL",
    "gn:name":"Perappanank\u0101du",
    "gn:population":0,
    "gn:timezone":"Asia/Kolkata",
    "iso:country":"IN",
    "ks:ks_name":"Parappanangadu",
    "ks:ks_pop":158,
    "ks:ks_type":"HABITATION",
    "name:eng_x_preferred":[
        "Parappanangadu"
    ],
    "name:eng_x_variant":[
        "Perappanankadu"
    ],
    "wof:name":"Parappanangadu",
    "wof:placetype":"locality",
    "wof:population":158
},
  "geometry": {"coordinates":[79.64702699999999,12.417099],"type":"Point"}
}