{
  "type": "Feature",
  "properties": {
    "gn:admin1_code":"12.0",
    "gn:admin2_code":"022",
    "gn:asciiname":"Chumbian",
    "gn:country_code":"IN",
    "gn:dem":312,
    "gn:feature_class":"P",
    "gn:feature_code":"PPL",
    "gn:name":"Chumb\u012b\u0101n",
    "gn:population":0,
    "gn:timezone":"Asia/Kolkata",
    "iso:country":"IN",
    "name:und_x_variant":[
        "Chumb\u012b\u0101n",
        "Chumb\u012by\u0101n"
    ],
    "wof:name":"Chumbian",
    "wof:placetype":"locality"
},
  "geometry": {"coordinates":[74.97615999999999,32.54344],"type":"Point"}
}