{
  "type": "Feature",
  "properties": {
    "gn:admin1_code":"36",
    "gn:admin2_code":"166.0",
    "gn:asciiname":"Hati",
    "gn:country_code":"IN",
    "gn:dem":230,
    "gn:feature_class":"P",
    "gn:feature_code":"PPL",
    "gn:name":"H\u0101ti",
    "gn:population":0,
    "gn:timezone":"Asia/Kolkata",
    "iso:country":"IN",
    "name:bul_x_preferred":[
        "\u0425\u0430\u0442\u0438"
    ],
    "name:ind_x_preferred":[
        "Hati"
    ],
    "name:lav_x_preferred":[
        "Hati"
    ],
    "name:nds_x_preferred":[
        "Hati"
    ],
    "name:rus_x_preferred":[
        "\u0425\u0430\u0442\u0438"
    ],
    "name:slv_x_preferred":[
        "Hati"
    ],
    "wof:name":"Hati",
    "wof:placetype":"locality"
},
  "geometry": {"coordinates":[78.92891,25.44517],"type":"Point"}
}