{
  "type": "Feature",
  "properties": {
    "gn:admin1_code":"21.0",
    "gn:admin2_code":"390.0",
    "gn:asciiname":"Jimabadi",
    "gn:country_code":"IN",
    "gn:dem":885,
    "gn:feature_class":"P",
    "gn:feature_code":"PPL",
    "gn:name":"Jim\u0101b\u0101di",
    "gn:population":0,
    "gn:timezone":"Asia/Kolkata",
    "iso:country":"IN",
    "ks:ks_name":"Jhimabadi",
    "ks:ks_pop":694,
    "ks:ks_type":"VILLAGE",
    "name:eng_x_preferred":[
        "Jhimabadi"
    ],
    "name:eng_x_variant":[
        "Jimabadi"
    ],
    "wof:name":"Jhimabadi",
    "wof:placetype":"locality",
    "wof:population":694
},
  "geometry": {"coordinates":[83.99372099999999,19.891658],"type":"Point"}
}