{
  "type": "Feature",
  "properties": {
    "iso:country":"IN",
    "ks:ks_alt_nam":"TAKIYA",
    "ks:ks_name":"Takiya",
    "ks:ks_pop":469,
    "ks:ks_type":"HABITATION",
    "name:eng_x_preferred":[
        "Takiya"
    ],
    "wof:name":"Takiya",
    "wof:placetype":"locality",
    "wof:population":469
},
  "geometry": {"coordinates":[81.56522,26.421803],"type":"Point"}
}