{
  "type": "Feature",
  "properties": {
    "iso:country":"IN",
    "ks:ks_name":"Arathil",
    "ks:ks_pop":1783,
    "ks:ks_type":"HABITATION",
    "ks:ks_uagg_main":0,
    "name:eng_x_preferred":[
        "Arathil"
    ],
    "wof:name":"Arathil",
    "wof:placetype":"neighbourhood",
    "wof:population":1783
},
  "geometry": {"coordinates":[75.352469,11.943476],"type":"Point"}
}