{
  "type": "Feature",
  "properties": {
    "iso:country":"IN",
    "ks:ks_name":"Badadurupa",
    "ks:ks_pop":134,
    "ks:ks_type":"VILLAGE",
    "name:eng_x_preferred":[
        "Badadurupa"
    ],
    "wof:name":"Badadurupa",
    "wof:placetype":"locality",
    "wof:population":134
},
  "geometry": {"coordinates":[84.916286,20.13869],"type":"Point"}
}