{
  "type": "Feature",
  "properties": {
    "gn:admin1_code":"2.0",
    "gn:admin2_code":"544.0",
    "gn:asciiname":"Karel",
    "gn:country_code":"IN",
    "gn:dem":936,
    "gn:feature_class":"P",
    "gn:feature_code":"PPL",
    "gn:name":"Karel",
    "gn:population":0,
    "gn:timezone":"Asia/Kolkata",
    "iso:country":"IN",
    "name:fra_x_preferred":[
        "Karel"
    ],
    "name:ita_x_preferred":[
        "Karel"
    ],
    "name:jpn_x_preferred":[
        "\u30ab\u30fc\u30eb"
    ],
    "name:nld_x_preferred":[
        "Karel"
    ],
    "name:rus_x_preferred":[
        "\u041a\u0430\u0440\u0435\u043b"
    ],
    "wof:name":"Karel",
    "wof:placetype":"locality"
},
  "geometry": {"coordinates":[82.67664000000001,18.05535],"type":"Point"}
}