{
  "type": "Feature",
  "properties": {
    "iso:country":"IN",
    "ks:ks_name":"Garoth Kasba",
    "ks:ks_pop":3481,
    "ks:ks_type":"VILLAGE",
    "name:eng_x_preferred":[
        "Garoth Kasba"
    ],
    "wof:name":"Garoth Kasba",
    "wof:placetype":"locality",
    "wof:population":3481
},
  "geometry": {"coordinates":[75.67218200000001,24.327102],"type":"Point"}
}