{
  "type": "Feature",
  "properties": {
    "iso:country":"IN",
    "ks:ks_name":"Kalegaon",
    "ks:ks_pop":467,
    "ks:ks_type":"HABITATION",
    "name:eng_x_preferred":[
        "Kalegaon"
    ],
    "wof:name":"Kalegaon",
    "wof:placetype":"locality",
    "wof:population":467
},
  "geometry": {"coordinates":[75.164,19.25268],"type":"Point"}
}