{
  "type": "Feature",
  "properties": {
    "iso:country":"IN",
    "ks:ks_name":"Kondhran",
    "ks:ks_pop":224,
    "ks:ks_type":"VILLAGE",
    "name:eng_x_preferred":[
        "Kondhran"
    ],
    "wof:name":"Kondhran",
    "wof:placetype":"locality",
    "wof:population":224
},
  "geometry": {"coordinates":[73.521275,17.027414],"type":"Point"}
}