{
  "type": "Feature",
  "properties": {
    "gn:admin1_code":"25.0",
    "gn:admin2_code":"620.0",
    "gn:asciiname":"Ettivayal",
    "gn:country_code":"IN",
    "gn:dem":13,
    "gn:feature_class":"P",
    "gn:feature_code":"PPL",
    "gn:name":"Ettivayal",
    "gn:population":0,
    "gn:timezone":"Asia/Kolkata",
    "iso:country":"IN",
    "name:tam_x_preferred":[
        "\u0b8e\u0b9f\u0bcd\u0b9f\u0bbf\u0bb5\u0baf\u0bb2\u0bcd"
    ],
    "wof:name":"Ettivayal",
    "wof:placetype":"locality"
},
  "geometry": {"coordinates":[79.31385999999998,10.30681],"type":"Point"}
}