{
  "type": "Feature",
  "properties": {
    "gn:admin1_code":"10",
    "gn:admin2_code":"81.0",
    "gn:asciiname":"Bhaini Jattan",
    "gn:country_code":"IN",
    "gn:dem":221,
    "gn:feature_class":"P",
    "gn:feature_code":"PPL",
    "gn:name":"Bhaini Jatt\u0101n",
    "gn:population":0,
    "gn:timezone":"Asia/Kolkata",
    "iso:country":"IN",
    "ks:ks_name":"Bhaini Jattan",
    "ks:ks_pop":1395,
    "ks:ks_type":"HABITATION",
    "ks:ks_uagg_main":0,
    "name:eng_x_preferred":[
        "Bhaini Jattan"
    ],
    "wof:name":"Bhaini Jattan",
    "wof:placetype":"neighbourhood",
    "wof:population":1395
},
  "geometry": {"coordinates":[76.102362,29.028285],"type":"Point"}
}