{
  "type": "Feature",
  "properties": {
    "iso:country":"IN",
    "ks:ks_name":"Balakkeri",
    "ks:ks_pop":20,
    "ks:ks_type":"HABITATION",
    "name:eng_x_preferred":[
        "Balakkeri"
    ],
    "wof:name":"Balakkeri",
    "wof:placetype":"locality",
    "wof:population":20
},
  "geometry": {"coordinates":[75.45551500000001,12.714274],"type":"Point"}
}