{
  "type": "Feature",
  "properties": {
    "gn:admin1_code":"10.0",
    "gn:admin2_code":"76.0",
    "gn:asciiname":"Lath",
    "gn:country_code":"IN",
    "gn:dem":230,
    "gn:feature_class":"P",
    "gn:feature_code":"PPL",
    "gn:name":"L\u0101th",
    "gn:population":0,
    "gn:timezone":"Asia/Kolkata",
    "iso:country":"IN",
    "name:bre_x_preferred":[
        "Goulazh"
    ],
    "name:dan_x_preferred":[
        "L\u00e6gte"
    ],
    "name:epo_x_preferred":[
        "Lato"
    ],
    "name:fin_x_preferred":[
        "Rima"
    ],
    "name:fra_x_preferred":[
        "Latte"
    ],
    "name:ido_x_preferred":[
        "Lato"
    ],
    "name:nno_x_preferred":[
        "Lekte"
    ],
    "name:nor_x_preferred":[
        "Lekte"
    ],
    "name:por_x_preferred":[
        "Ripa"
    ],
    "name:rus_x_preferred":[
        "\u041e\u0431\u0440\u0435\u0448\u0451\u0442\u043a\u0430"
    ],
    "name:swe_x_preferred":[
        "L\u00e4kt"
    ],
    "name:tha_x_preferred":[
        "\u0e23\u0e30\u0e41\u0e19\u0e07"
    ],
    "name:ukr_x_preferred":[
        "\u041e\u0431\u0440\u0435\u0448\u0456\u0442\u043a\u0430"
    ],
    "wof:name":"Lath",
    "wof:placetype":"locality"
},
  "geometry": {"coordinates":[76.78068,29.07366],"type":"Point"}
}