{
  "type": "Feature",
  "properties": {
    "iso:country":"IN",
    "ks:ks_name":"Lagasu Gaon",
    "ks:ks_pop":634,
    "ks:ks_type":"HABITATION",
    "name:eng_x_preferred":[
        "Lagasu Gaon"
    ],
    "wof:name":"Lagasu Gaon",
    "wof:placetype":"locality",
    "wof:population":634
},
  "geometry": {"coordinates":[93.96263,26.971555],"type":"Point"}
}