{
  "type": "Feature",
  "properties": {
    "gn:admin1_code":"36.0",
    "gn:admin2_code":"182.0",
    "gn:asciiname":"Baraipur",
    "gn:country_code":"IN",
    "gn:dem":113,
    "gn:feature_class":"P",
    "gn:feature_code":"PPL",
    "gn:name":"Baraipur",
    "gn:population":0,
    "gn:timezone":"Asia/Kolkata",
    "iso:country":"IN",
    "name:ceb_x_preferred":[
        "Baraipur"
    ],
    "name:msa_x_preferred":[
        "Baraipur"
    ],
    "name:pol_x_preferred":[
        "Baraipur"
    ],
    "wof:name":"Baraipur",
    "wof:placetype":"locality"
},
  "geometry": {"coordinates":[82.07866,27.4488],"type":"Point"}
}