{
  "type": "Feature",
  "properties": {
    "gn:admin1_code":"36",
    "gn:admin2_code":"134.0",
    "gn:asciiname":"Gadaika",
    "gn:country_code":"IN",
    "gn:dem":263,
    "gn:feature_class":"P",
    "gn:feature_code":"PPL",
    "gn:name":"Gad\u0101ika",
    "gn:population":0,
    "gn:timezone":"Asia/Kolkata",
    "iso:country":"IN",
    "name:und_x_variant":[
        "Gad\u0101ika",
        "Fazalpur M\u0101n\u016bn"
    ],
    "wof:name":"Gadaika",
    "wof:placetype":"neighbourhood"
},
  "geometry": {"coordinates":[78.27137,29.65125],"type":"Point"}
}