{
  "type": "Feature",
  "properties": {
    "iso:country":"IN",
    "ks:ks_name":"Salka Pranpatri",
    "ks:ks_pop":600,
    "ks:ks_type":"HABITATION",
    "name:eng_x_preferred":[
        "Salka Pranpatri"
    ],
    "wof:name":"Salka Pranpatri",
    "wof:placetype":"locality",
    "wof:population":600
},
  "geometry": {"coordinates":[82.76773300000001,22.905609],"type":"Point"}
}