{
  "type": "Feature",
  "properties": {
    "iso:country":"IN",
    "ks:ks_alt_nam":"SURESH SINGH PURWA",
    "ks:ks_name":"Suresh Singh Purwa",
    "ks:ks_pop":46,
    "ks:ks_type":"HABITATION",
    "name:eng_x_preferred":[
        "Suresh Singh Purwa"
    ],
    "wof:name":"Suresh Singh Purwa",
    "wof:placetype":"locality",
    "wof:population":46
},
  "geometry": {"coordinates":[81.702082,27.376385],"type":"Point"}
}