{
  "type": "Feature",
  "properties": {
    "iso:country":"IN",
    "ks:ks_alt_nam":"PANDIT KA PURWA",
    "ks:ks_name":"Pandit Ka Purwa",
    "ks:ks_pop":82,
    "ks:ks_type":"HABITATION",
    "ks:ks_uagg_main":0,
    "name:eng_x_preferred":[
        "Pandit Ka Purwa"
    ],
    "wof:name":"Pandit Ka Purwa",
    "wof:placetype":"neighbourhood",
    "wof:population":82
},
  "geometry": {"coordinates":[81.970455,26.355156],"type":"Point"}
}