{
  "type": "Feature",
  "properties": {
    "gn:admin1_code":"18.0",
    "gn:admin2_code":"297.0",
    "gn:asciiname":"Mawsmai",
    "gn:country_code":"IN",
    "gn:dem":149,
    "gn:feature_class":"P",
    "gn:feature_code":"PPL",
    "gn:name":"Mawsmai",
    "gn:population":0,
    "gn:timezone":"Asia/Kolkata",
    "iso:country":"IN",
    "wof:name":"Mawsmai",
    "wof:placetype":"locality"
},
  "geometry": {"coordinates":[91.87569999999999,26.09542],"type":"Point"}
}