{
  "type": "Feature",
  "properties": {
    "iso:country":"IN",
    "ks:ks_name":"Andurpar",
    "ks:ks_pop":523,
    "ks:ks_type":"VILLAGE",
    "ks:ks_uagg_main":0,
    "name:eng_x_preferred":[
        "Andurpar"
    ],
    "wof:name":"Andurpar",
    "wof:placetype":"neighbourhood",
    "wof:population":523
},
  "geometry": {"coordinates":[92.431915,24.560456],"type":"Point"}
}