{
  "type": "Feature",
  "properties": {
    "iso:country":"IN",
    "ks:ks_name":"Letharahapar",
    "ks:ks_pop":130,
    "ks:ks_type":"HABITATION",
    "name:eng_x_preferred":[
        "Letharahapar"
    ],
    "wof:name":"Letharahapar",
    "wof:placetype":"locality",
    "wof:population":130
},
  "geometry": {"coordinates":[81.401483,25.442186],"type":"Point"}
}