{
  "type": "Feature",
  "properties": {
    "gn:admin1_code":"23.0",
    "gn:admin2_code":"41.0",
    "gn:asciiname":"Razapur",
    "gn:country_code":"IN",
    "gn:dem":230,
    "gn:feature_class":"P",
    "gn:feature_code":"PPL",
    "gn:name":"Raz\u0101pur",
    "gn:population":0,
    "gn:timezone":"Asia/Kolkata",
    "iso:country":"IN",
    "ks:ks_alt_nam":"Raz\u0101pur",
    "ks:ks_name":"Razapur",
    "ks:ks_pop":464,
    "ks:ks_type":"VILLAGE",
    "name:eng_x_preferred":[
        "Razapur"
    ],
    "name:eng_x_variant":[
        "Raz\u0101pur"
    ],
    "wof:name":"Razapur",
    "wof:placetype":"locality",
    "wof:population":464
},
  "geometry": {"coordinates":[75.720849,30.984567],"type":"Point"}
}