{
  "type": "Feature",
  "properties": {
    "iso:country":"IN",
    "ks:ks_name":"Panasgandhi",
    "ks:ks_pop":56,
    "ks:ks_type":"VILLAGE",
    "name:eng_x_preferred":[
        "Panasgandhi"
    ],
    "wof:name":"Panasgandhi",
    "wof:placetype":"locality",
    "wof:population":56
},
  "geometry": {"coordinates":[82.197322,18.102244],"type":"Point"}
}