{
  "type": "Feature",
  "properties": {
    "iso:country":"IN",
    "ks:ks_name":"Hridaya Pur",
    "ks:ks_pop":476,
    "ks:ks_type":"HABITATION",
    "name:eng_x_preferred":[
        "Hridaya Pur"
    ],
    "wof:name":"Hridaya Pur",
    "wof:placetype":"locality",
    "wof:population":476
},
  "geometry": {"coordinates":[79.51877899999999,27.490286],"type":"Point"}
}