{
  "type": "Feature",
  "properties": {
    "iso:country":"IN",
    "ks:ks_alt_nam":"Badhaion wala Majra",
    "ks:ks_name":"Badhaion Wala Majra",
    "ks:ks_pop":2080,
    "ks:ks_type":"HABITATION",
    "name:eng_x_preferred":[
        "Badhaion Wala Majra"
    ],
    "wof:name":"Badhaion Wala Majra",
    "wof:placetype":"locality",
    "wof:population":2080
},
  "geometry": {"coordinates":[79.262384,28.754502],"type":"Point"}
}