{
  "type": "Feature",
  "properties": {
    "gn:admin1_code":"2.0",
    "gn:asciiname":"Ankireddi Kottapalli",
    "gn:country_code":"IN",
    "gn:dem":799,
    "gn:feature_class":"P",
    "gn:feature_code":"PPL",
    "gn:name":"Ankireddi Kottapalli",
    "gn:population":0,
    "gn:timezone":"Asia/Kolkata",
    "iso:country":"IN",
    "wof:name":"Ankireddi Kottapalli",
    "wof:placetype":"neighbourhood"
},
  "geometry": {"coordinates":[78.43523999999999,13.32491],"type":"Point"}
}