{
  "type": "Feature",
  "properties": {
    "gn:admin1_code":"25.0",
    "gn:admin2_code":"605.0",
    "gn:asciiname":"Setarampatti",
    "gn:country_code":"IN",
    "gn:dem":371,
    "gn:feature_class":"P",
    "gn:feature_code":"PPL",
    "gn:name":"Setarampatti",
    "gn:population":0,
    "gn:timezone":"Asia/Kolkata",
    "iso:country":"IN",
    "wof:name":"Setarampatti",
    "wof:placetype":"locality"
},
  "geometry": {"coordinates":[78.54046,12.42544],"type":"Point"}
}