{
  "type": "Feature",
  "properties": {
    "iso:country":"IN",
    "ks:ks_name":"Samlahan Falia",
    "ks:ks_pop":66,
    "ks:ks_type":"HABITATION",
    "ks:ks_uagg_main":0,
    "name:eng_x_preferred":[
        "Samlahan Falia"
    ],
    "wof:name":"Samlahan Falia",
    "wof:placetype":"neighbourhood",
    "wof:population":66
},
  "geometry": {"coordinates":[73.114965,20.457685],"type":"Point"}
}