{
  "type": "Feature",
  "properties": {
    "gn:admin1_code":"39",
    "gn:admin2_code":"56.0",
    "gn:asciiname":"Kotia Mund",
    "gn:country_code":"IN",
    "gn:dem":3041,
    "gn:feature_class":"P",
    "gn:feature_code":"PPL",
    "gn:name":"Kotia Mund",
    "gn:population":0,
    "gn:timezone":"Asia/Kolkata",
    "iso:country":"IN",
    "wof:name":"Kotia Mund",
    "wof:placetype":"locality"
},
  "geometry": {"coordinates":[77.9408,31.09835],"type":"Point"}
}