{
  "type": "Feature",
  "properties": {
    "iso:country":"IN",
    "ks:ks_name":"Barsuri",
    "ks:ks_pop":54,
    "ks:ks_type":"VILLAGE",
    "name:eng_x_preferred":[
        "Barsuri"
    ],
    "wof:name":"Barsuri",
    "wof:placetype":"locality",
    "wof:population":54
},
  "geometry": {"coordinates":[78.87750699999999,30.119383],"type":"Point"}
}