{
  "type": "Feature",
  "properties": {
    "gn:admin1_code":"11.0",
    "gn:admin2_code":"27.0",
    "gn:asciiname":"Kathaihlar",
    "gn:country_code":"IN",
    "gn:dem":2164,
    "gn:feature_class":"P",
    "gn:feature_code":"PPL",
    "gn:name":"Kathaihlar",
    "gn:population":0,
    "gn:timezone":"Asia/Kolkata",
    "iso:country":"IN",
    "wof:name":"Kathaihlar",
    "wof:placetype":"locality"
},
  "geometry": {"coordinates":[77.24206,31.41094],"type":"Point"}
}