{
  "type": "Feature",
  "properties": {
    "gn:admin1_code":"36.0",
    "gn:admin2_code":"184.0",
    "gn:asciiname":"Katha",
    "gn:country_code":"IN",
    "gn:dem":91,
    "gn:feature_class":"P",
    "gn:feature_code":"PPL",
    "gn:name":"Katha",
    "gn:population":0,
    "gn:timezone":"Asia/Kolkata",
    "iso:country":"IN",
    "name:ceb_x_preferred":[
        "Katha"
    ],
    "name:swe_x_preferred":[
        "Katha"
    ],
    "wof:name":"Katha",
    "wof:placetype":"locality"
},
  "geometry": {"coordinates":[82.90465,27.18736],"type":"Point"}
}