{
  "type": "Feature",
  "properties": {
    "iso:country":"IN",
    "ks:ks_name":"Chak Dhakra",
    "ks:ks_pop":242,
    "ks:ks_type":"HABITATION",
    "name:eng_x_preferred":[
        "Chak Dhakra"
    ],
    "wof:name":"Chak Dhakra",
    "wof:placetype":"locality",
    "wof:population":242
},
  "geometry": {"coordinates":[76.208528,26.427825],"type":"Point"}
}