{
  "type": "Feature",
  "properties": {
    "iso:country":"IN",
    "ks:ks_name":"Syankuri",
    "ks:ks_pop":665,
    "ks:ks_type":"VILLAGE",
    "name:eng_x_preferred":[
        "Syankuri"
    ],
    "wof:name":"Syankuri",
    "wof:placetype":"locality",
    "wof:population":665
},
  "geometry": {"coordinates":[80.57018600000001,29.936275],"type":"Point"}
}