{
  "type": "Feature",
  "properties": {
    "iso:country":"IN",
    "ks:ks_alt_nam":"KALBHAIRAV",
    "ks:ks_name":"Kalbhairav",
    "ks:ks_pop":75,
    "ks:ks_type":"HABITATION",
    "name:eng_x_preferred":[
        "Kalbhairav"
    ],
    "wof:name":"Kalbhairav",
    "wof:placetype":"locality",
    "wof:population":75
},
  "geometry": {"coordinates":[74.35771800000001,17.13813],"type":"Point"}
}