{
  "type": "Feature",
  "properties": {
    "gn:admin1_code":"16",
    "gn:admin2_code":"504.0",
    "gn:asciiname":"Rohankhera",
    "gn:country_code":"IN",
    "gn:dem":236,
    "gn:feature_class":"P",
    "gn:feature_code":"PPL",
    "gn:name":"Rohankhera",
    "gn:population":0,
    "gn:timezone":"Asia/Kolkata",
    "iso:country":"IN",
    "wof:name":"Rohankhera",
    "wof:placetype":"locality"
},
  "geometry": {"coordinates":[78.63913000000002,20.52549],"type":"Point"}
}