{
  "type": "Feature",
  "properties": {
    "iso:country":"IN",
    "ks:ks_name":"Odanga",
    "ks:ks_pop":951,
    "ks:ks_type":"VILLAGE",
    "ks:ks_uagg_main":0,
    "name:eng_x_preferred":[
        "Odanga"
    ],
    "wof:name":"Odanga",
    "wof:placetype":"neighbourhood",
    "wof:population":951
},
  "geometry": {"coordinates":[86.142303,20.792893],"type":"Point"}
}