{
  "type": "Feature",
  "properties": {
    "iso:country":"IN",
    "ks:ks_name":"Murugathampoondi",
    "ks:ks_pop":652,
    "ks:ks_type":"VILLAGE",
    "ks:ks_uagg_main":0,
    "name:eng_x_preferred":[
        "Murugathampoondi"
    ],
    "wof:name":"Murugathampoondi",
    "wof:placetype":"neighbourhood",
    "wof:population":652
},
  "geometry": {"coordinates":[79.466004,12.696812],"type":"Point"}
}