{
  "type": "Feature",
  "properties": {
    "gn:admin1_code":"37",
    "gn:admin2_code":"410.0",
    "gn:asciiname":"Amaseoni",
    "gn:country_code":"IN",
    "gn:dem":286,
    "gn:feature_class":"P",
    "gn:feature_code":"PPL",
    "gn:name":"\u0100m\u0101seoni",
    "gn:population":0,
    "gn:timezone":"Asia/Kolkata",
    "iso:country":"IN",
    "ks:ks_name":"Amaseoni",
    "ks:ks_pop":2142,
    "ks:ks_type":"VILLAGE",
    "ks:ks_uagg_main":0,
    "name:eng_x_preferred":[
        "Amaseoni"
    ],
    "wof:name":"Amaseoni",
    "wof:placetype":"locality",
    "wof:population":2142
},
  "geometry": {"coordinates":[81.711253,21.281345],"type":"Point"}
}