{
  "type": "Feature",
  "properties": {
    "iso:country":"IN",
    "ks:ks_name":"Mathura Purva",
    "ks:ks_pop":372,
    "ks:ks_type":"HABITATION",
    "name:eng_x_preferred":[
        "Mathura Purva"
    ],
    "wof:name":"Mathura Purva",
    "wof:placetype":"locality",
    "wof:population":372
},
  "geometry": {"coordinates":[80.00111699999999,27.05938],"type":"Point"}
}