{
  "type": "Feature",
  "properties": {
    "iso:country":"IN",
    "ks:ks_alt_nam":"TEHSIL",
    "ks:ks_name":"Tehsil",
    "ks:ks_pop":138,
    "ks:ks_type":"HABITATION",
    "ks:ks_uagg_main":0,
    "name:eng_x_preferred":[
        "Tehsil"
    ],
    "wof:name":"Tehsil",
    "wof:placetype":"neighbourhood",
    "wof:population":138
},
  "geometry": {"coordinates":[81.492515,27.582732],"type":"Point"}
}