{
  "type": "Feature",
  "properties": {
    "iso:country":"IN",
    "ks:ks_name":"Padinjattukara",
    "ks:ks_pop":304,
    "ks:ks_type":"HABITATION",
    "name:eng_x_preferred":[
        "Padinjattukara"
    ],
    "wof:name":"Padinjattukara",
    "wof:placetype":"neighbourhood",
    "wof:population":304
},
  "geometry": {"coordinates":[76.90035399999999,8.929333],"type":"Point"}
}