{
  "type": "Feature",
  "properties": {
    "iso:country":"IN",
    "ks:ks_name":"Badakalarakotha",
    "ks:ks_pop":147,
    "ks:ks_type":"VILLAGE",
    "name:eng_x_preferred":[
        "Badakalarakotha"
    ],
    "wof:name":"Badakalarakotha",
    "wof:placetype":"locality",
    "wof:population":147
},
  "geometry": {"coordinates":[83.711468,20.432705],"type":"Point"}
}