{
  "type": "Feature",
  "properties": {
    "iso:country":"IN",
    "ks:ks_name":"Koti",
    "ks:ks_pop":148,
    "ks:ks_type":"VILLAGE",
    "name:eng_x_preferred":[
        "Koti"
    ],
    "wof:name":"Koti",
    "wof:placetype":"locality",
    "wof:population":148
},
  "geometry": {"coordinates":[78.723945,30.315497],"type":"Point"}
}