{
  "type": "Feature",
  "properties": {
    "iso:country":"IN",
    "ks:ks_name":"Natagadia",
    "ks:ks_pop":0,
    "ks:ks_type":"VILLAGE",
    "name:eng_x_preferred":[
        "Natagadia"
    ],
    "wof:name":"Natagadia",
    "wof:placetype":"locality",
    "wof:population":0
},
  "geometry": {"coordinates":[86.205809,21.018727],"type":"Point"}
}