{
  "type": "Feature",
  "properties": {
    "gn:admin1_code":"12",
    "gn:asciiname":"Bujathala",
    "gn:country_code":"IN",
    "gn:dem":2050,
    "gn:feature_class":"P",
    "gn:feature_code":"PPL",
    "gn:name":"Bujathala",
    "gn:population":0,
    "gn:timezone":"Asia/Kolkata",
    "iso:country":"IN",
    "wof:name":"Bujathala",
    "wof:placetype":"locality"
},
  "geometry": {"coordinates":[74.15196,34.1638],"type":"Point"}
}