{
  "type": "Feature",
  "properties": {
    "gn:admin1_code":"38",
    "gn:admin2_code":"358.0",
    "gn:asciiname":"Sordiha",
    "gn:country_code":"IN",
    "gn:dem":211,
    "gn:feature_class":"P",
    "gn:feature_code":"PPL",
    "gn:name":"Sord\u012bha",
    "gn:population":0,
    "gn:timezone":"Asia/Kolkata",
    "iso:country":"IN",
    "ks:ks_alt_nam":"Sord\u012bha",
    "ks:ks_name":"Sordiha",
    "ks:ks_type":"VILLAGE",
    "ks:ks_uagg_main":0,
    "name:eng_x_preferred":[
        "Sordiha"
    ],
    "name:eng_x_variant":[
        "Sord\u012bha"
    ],
    "wof:name":"Sordiha",
    "wof:placetype":"neighbourhood"
},
  "geometry": {"coordinates":[83.92520500000001,24.246449],"type":"Point"}
}