{
  "type": "Feature",
  "properties": {
    "iso:country":"IN",
    "ks:ks_alt_nam":"KOHARAN KA PURWA",
    "ks:ks_name":"Koharan Ka Purwa",
    "ks:ks_pop":88,
    "ks:ks_type":"HABITATION",
    "name:eng_x_preferred":[
        "Koharan Ka Purwa"
    ],
    "wof:name":"Koharan Ka Purwa",
    "wof:placetype":"locality",
    "wof:population":88
},
  "geometry": {"coordinates":[81.878584,26.38079],"type":"Point"}
}