{
  "type": "Feature",
  "properties": {
    "gn:country":"IN",
    "gn:fcode":"PPL",
    "gn:pop":29392,
    "iso:country":"IN",
    "name:ben_x_preferred":[
        "\u09a4\u09be\u09b0\u09be\u09a8\u0997\u09b0"
    ],
    "name:bpy_x_preferred":[
        "\u09a4\u09be\u09b0\u09be\u09a8\u0997\u09b0"
    ],
    "name:chi_x_preferred":[
        "\u5854\u62c9\u7eb3\u52a0\u5c14"
    ],
    "name:dut_x_preferred":[
        "Taranagar"
    ],
    "name:eng_x_preferred":[
        "Taranagar"
    ],
    "name:fre_x_preferred":[
        "Taranagar"
    ],
    "name:ger_x_preferred":[
        "Taranagar"
    ],
    "name:guj_x_preferred":[
        "\u0aa4\u0abe\u0ab0\u0abe\u0aa8\u0a97\u0ab0"
    ],
    "name:ita_x_preferred":[
        "Taranagar"
    ],
    "name:jpn_x_preferred":[
        "\u30bf\u30e9\u30ca\u30ac\u30fc\u30eb"
    ],
    "name:kan_x_preferred":[
        "\u0ca4\u0cbe\u0cb0\u0cbe\u0ca8\u0c97\u0cb0\u0ccd"
    ],
    "name:kor_x_preferred":[
        "\ud0c0\ub77c\ub098\uac00\ub974"
    ],
    "name:may_x_preferred":[
        "Taranagar"
    ],
    "name:mlg_x_preferred":[
        "Taranagar"
    ],
    "name:ori_x_preferred":[
        "\u0b24\u0b3e\u0b30\u0b3e\u0b28\u0b17\u0b30"
    ],
    "name:por_x_preferred":[
        "Taranagar"
    ],
    "name:rus_x_preferred":[
        "\u0422\u0430\u0440\u0430\u043d\u0430\u0433\u0430\u0440"
    ],
    "name:spa_x_preferred":[
        "Taranagar"
    ],
    "name:swe_x_preferred":[
        "T\u0101r\u0101nagar"
    ],
    "name:tam_x_preferred":[
        "\u0ba4\u0bbe\u0bb0\u0ba3\u0b95\u0bb0\u0bcd"
    ],
    "name:tel_x_preferred":[
        "\u0c24\u0c3e\u0c30\u0c3e\u0c28\u0c17\u0c30\u0c4d"
    ],
    "name:unk_x_variant":[
        "Reni"
    ],
    "name:urd_x_preferred":[
        "\u062a\u0627\u0631\u0627\u0646\u06af\u0631"
    ],
    "name:vie_x_preferred":[
        "Taranagar"
    ],
    "qs:name":"Taranagar",
    "qs:name_adm0":"India",
    "qs:name_adm1":"Rajasthan",
    "qs:photos_9k":1,
    "qs:photos_9r":1,
    "qs:photos_all":1,
    "qs:photos_sr":0,
    "qs:placetype":"Town",
    "qs:pop_sr":"7",
    "wd:wordcount":1421,
    "wof:name":"Taranagar",
    "wof:placetype":"locality",
    "wof:population":29392
},
  "geometry": {"coordinates":[75.03207,28.6686],"type":"Point"}
}