{
  "type": "Feature",
  "properties": {
    "iso:country":"IN",
    "ks:ks_name":"Gair",
    "ks:ks_pop":302,
    "ks:ks_type":"VILLAGE",
    "name:eng_x_preferred":[
        "Gair"
    ],
    "wof:name":"Gair",
    "wof:placetype":"locality",
    "wof:population":302
},
  "geometry": {"coordinates":[78.193489,30.722179],"type":"Point"}
}