{
  "type": "Feature",
  "properties": {
    "gn:admin1_code":"35.0",
    "gn:admin2_code":"457.0",
    "gn:asciiname":"Gaonajhola",
    "gn:country_code":"IN",
    "gn:dem":617,
    "gn:feature_class":"P",
    "gn:feature_code":"PPL",
    "gn:name":"Gaon\u0101jhol\u0101",
    "gn:population":0,
    "gn:timezone":"Asia/Kolkata",
    "iso:country":"IN",
    "wof:name":"Gaonajhola",
    "wof:placetype":"locality"
},
  "geometry": {"coordinates":[80.36256999999998,22.00632],"type":"Point"}
}