{
  "type": "Feature",
  "properties": {
    "gn:admin1_code":"35.0",
    "gn:admin2_code":"457.0",
    "gn:asciiname":"Gaonajhola",
    "gn:country_code":"IN",
    "gn:dem":617,
    "gn:feature_class":"P",
    "gn:feature_code":"PPL",
    "gn:name":"Gaon\u0101jhol\u0101",
    "gn:population":0,
    "gn:timezone":"Asia/Kolkata",
    "iso:country":"IN",
    "ks:ks_name":"Gaunajhola",
    "ks:ks_pop":264,
    "ks:ks_type":"VILLAGE",
    "name:eng_x_preferred":[
        "Gaunajhola"
    ],
    "name:eng_x_variant":[
        "Gaonajhola"
    ],
    "wof:name":"Gaunajhola",
    "wof:placetype":"locality",
    "wof:population":264
},
  "geometry": {"coordinates":[80.362284,22.006715],"type":"Point"}
}