{
  "type": "Feature",
  "properties": {
    "iso:country":"IN",
    "ks:ks_name":"Athithurai",
    "ks:ks_pop":602,
    "ks:ks_type":"HABITATION",
    "name:eng_x_preferred":[
        "Athithurai"
    ],
    "wof:name":"Athithurai",
    "wof:placetype":"locality",
    "wof:population":602
},
  "geometry": {"coordinates":[77.305662,10.46991],"type":"Point"}
}