{
  "type": "Feature",
  "properties": {
    "gn:country":"IN",
    "gn:fcode":"PPL",
    "gn:population":43651,
    "iso:country":"IN",
    "name:ben_x_preferred":[
        "\u0995\u09cb\u099f\u09aa\u09c1\u09a4\u09b2\u09bf"
    ],
    "name:bpy_x_preferred":[
        "\u0995\u09cb\u099f\u09aa\u09c1\u09a4\u09b2\u09bf"
    ],
    "name:bul_x_preferred":[
        "\u041a\u043e\u0442\u043f\u0443\u0442\u043b\u0438"
    ],
    "name:ceb_x_preferred":[
        "Kotputli"
    ],
    "name:deu_x_preferred":[
        "Kotputli"
    ],
    "name:eng_x_preferred":[
        "Kotputli"
    ],
    "name:fra_x_preferred":[
        "Kotputli"
    ],
    "name:guj_x_preferred":[
        "\u0a95\u0acb\u0a9f\u0aaa\u0ac1\u0a9f\u0ab2\u0ac0"
    ],
    "name:hin_x_preferred":[
        "\u0915\u094b\u091f\u092a\u0941\u0924\u0932\u0940"
    ],
    "name:ita_x_preferred":[
        "Kotputli"
    ],
    "name:jpn_x_preferred":[
        "\u30b3\u30c3\u30c8\u30d7\u30c3\u30c8\u30ea"
    ],
    "name:kan_x_preferred":[
        "\u0c95\u0ccb\u0c9f\u0ccd\u0caa\u0cc1\u0c9f\u0ccd\u0cb2\u0cbf"
    ],
    "name:kor_x_preferred":[
        "\ucf54\ud2b8\ud478\ud2c0\ub9ac"
    ],
    "name:msa_x_preferred":[
        "Kotputli"
    ],
    "name:new_x_preferred":[
        "\u0915\u094b\u0924\u094d\u092a\u0941\u0924\u094d\u0932\u0940"
    ],
    "name:nld_x_preferred":[
        "Kotputli"
    ],
    "name:por_x_preferred":[
        "Kotputli"
    ],
    "name:rus_x_preferred":[
        "\u041a\u043e\u0442\u043f\u0443\u0442\u043b\u0438"
    ],
    "name:spa_x_preferred":[
        "Kotputli"
    ],
    "name:swe_x_preferred":[
        "Kotputli"
    ],
    "name:tam_x_preferred":[
        "\u0b95\u0bcb\u0b9f\u0bcd\u0baa\u0bc2\u0ba4\u0bcd\u0bb2\u0bbf"
    ],
    "name:tel_x_preferred":[
        "\u0c15\u0c4b\u0c1f\u0c4d \u0c2a\u0c41\u0c24\u0c4d\u0c32\u0c3f"
    ],
    "name:urd_x_preferred":[
        "\u06a9\u0648\u062a\u067e\u0648\u062a\u0644\u06cc"
    ],
    "name:vie_x_preferred":[
        "Kotputli"
    ],
    "name:zho_x_preferred":[
        "\u79d1\u7279\u666e\u7279\u5229"
    ],
    "qs:name":"Kotputli",
    "qs:name_adm0":"India",
    "qs:name_adm1":"Rajasthan",
    "qs:photos_9k":1,
    "qs:photos_9r":1,
    "qs:photos_all":2,
    "qs:photos_sr":0,
    "qs:placetype":"Town",
    "qs:pop_sr":"7",
    "wd:wordcount":637,
    "wof:name":"Kotputli",
    "wof:placetype":"locality",
    "wof:population":43651
},
  "geometry": {"coordinates":[76.19911,27.70207],"type":"Point"}
}