{
  "type": "Feature",
  "properties": {
    "iso:country":"IN",
    "ks:ks_name":"Pallathuruthy",
    "ks:ks_pop":1465,
    "ks:ks_type":"HABITATION",
    "name:eng_x_preferred":[
        "Pallathuruthy"
    ],
    "wof:name":"Pallathuruthy",
    "wof:placetype":"locality",
    "wof:population":1465
},
  "geometry": {"coordinates":[76.36313800000001,9.463922],"type":"Point"}
}