{
  "type": "Feature",
  "properties": {
    "gn:admin1_code":"24.0",
    "gn:admin2_code":"130.0",
    "gn:asciiname":"Bacheri",
    "gn:country_code":"IN",
    "gn:dem":468,
    "gn:feature_class":"P",
    "gn:feature_code":"PPL",
    "gn:name":"Bacheri",
    "gn:population":0,
    "gn:timezone":"Asia/Kolkata",
    "iso:country":"IN",
    "wof:name":"Bacheri",
    "wof:placetype":"neighbourhood"
},
  "geometry": {"coordinates":[74.14664999999999,24.70091],"type":"Point"}
}