{
  "type": "Feature",
  "properties": {
    "iso:country":"IN",
    "ks:ks_alt_nam":"Kheri M\u0101rkanda",
    "ks:ks_name":"Kheri Markanda",
    "ks:ks_type":"VILLAGE",
    "ks:ks_uagg_main":0,
    "name:eng_x_preferred":[
        "Kheri Markanda"
    ],
    "name:eng_x_variant":[
        "Kheri M\u0101rkanda"
    ],
    "wof:name":"Kheri Markanda",
    "wof:placetype":"neighbourhood"
},
  "geometry": {"coordinates":[76.867008,29.981918],"type":"Point"}
}