{
  "type": "Feature",
  "properties": {
    "iso:country":"IN",
    "ks:ks_name":"Lohari",
    "ks:ks_pop":343,
    "ks:ks_type":"VILLAGE",
    "name:eng_x_preferred":[
        "Lohari"
    ],
    "wof:name":"Lohari",
    "wof:placetype":"locality",
    "wof:population":343
},
  "geometry": {"coordinates":[87.291554,23.001002],"type":"Point"}
}