{
  "type": "Feature",
  "properties": {
    "iso:country":"IN",
    "ks:ks_name":"Morewadi",
    "ks:ks_pop":190,
    "ks:ks_type":"HABITATION",
    "name:eng_x_preferred":[
        "Morewadi"
    ],
    "wof:name":"Morewadi",
    "wof:placetype":"locality",
    "wof:population":190
},
  "geometry": {"coordinates":[73.908649,17.638073],"type":"Point"}
}