{
  "type": "Feature",
  "properties": {
    "iso:country":"IN",
    "ks:ks_name":"Nawadih",
    "ks:ks_pop":208,
    "ks:ks_type":"HABITATION",
    "name:eng_x_preferred":[
        "Nawadih"
    ],
    "wof:name":"Nawadih",
    "wof:placetype":"locality",
    "wof:population":208
},
  "geometry": {"coordinates":[85.645717,23.037912],"type":"Point"}
}