{
  "type": "Feature",
  "properties": {
    "iso:country":"IN",
    "ks:ks_name":"Ramulaguda",
    "ks:ks_pop":22,
    "ks:ks_type":"HABITATION",
    "name:eng_x_preferred":[
        "Ramulaguda"
    ],
    "wof:name":"Ramulaguda",
    "wof:placetype":"locality",
    "wof:population":22
},
  "geometry": {"coordinates":[78.36008099999999,19.606955],"type":"Point"}
}