{
  "type": "Feature",
  "properties": {
    "iso:country":"IN",
    "ks:ks_name":"Chhota Saray",
    "ks:ks_pop":350,
    "ks:ks_type":"HABITATION",
    "name:eng_x_preferred":[
        "Chhota Saray"
    ],
    "wof:name":"Chhota Saray",
    "wof:placetype":"locality",
    "wof:population":350
},
  "geometry": {"coordinates":[84.290277,23.33418],"type":"Point"}
}