{
  "type": "Feature",
  "properties": {
    "iso:country":"IN",
    "ks:ks_name":"Mulewadi",
    "ks:ks_pop":97,
    "ks:ks_type":"HABITATION",
    "name:eng_x_preferred":[
        "Mulewadi"
    ],
    "wof:name":"Mulewadi",
    "wof:placetype":"locality",
    "wof:population":97
},
  "geometry": {"coordinates":[73.64339099999999,16.065949],"type":"Point"}
}