{
  "type": "Feature",
  "properties": {
    "gn:admin1_code":"19.0",
    "gn:admin2_code":"573.0",
    "gn:asciiname":"Machagonahalli",
    "gn:country_code":"IN",
    "gn:dem":796,
    "gn:feature_class":"P",
    "gn:feature_code":"PPL",
    "gn:name":"M\u0101chagonahalli",
    "gn:population":0,
    "gn:timezone":"Asia/Kolkata",
    "iso:country":"IN",
    "wof:name":"Machagonahalli",
    "wof:placetype":"locality"
},
  "geometry": {"coordinates":[76.51623000000002,12.52303],"type":"Point"}
}