{
  "type": "Feature",
  "properties": {
    "gn:admin1_code":"21.0",
    "gn:admin2_code":"396.0",
    "gn:asciiname":"Sullipadu",
    "gn:country_code":"IN",
    "gn:dem":343,
    "gn:feature_class":"P",
    "gn:feature_code":"PPL",
    "gn:name":"Sullip\u0101du",
    "gn:population":0,
    "gn:timezone":"Asia/Kolkata",
    "iso:country":"IN",
    "wof:name":"Sullipadu",
    "wof:placetype":"locality"
},
  "geometry": {"coordinates":[83.86219,19.43564],"type":"Point"}
}