{
  "type": "Feature",
  "properties": {
    "iso:country":"IN",
    "ks:ks_name":"Dhanikpur",
    "ks:ks_type":"VILLAGE",
    "name:eng_x_preferred":[
        "Dhanikpur"
    ],
    "wof:name":"Dhanikpur",
    "wof:placetype":"locality"
},
  "geometry": {"coordinates":[82.430048,25.187313],"type":"Point"}
}