{
  "type": "Feature",
  "properties": {
    "gn:country":"IN",
    "gn:fcode":"PPL",
    "gn:population":26138,
    "iso:country":"IN",
    "name:ben_x_preferred":[
        "\u09ae\u09be\u09b0\u09b9\u09be\u0989\u09b0\u09be"
    ],
    "name:bpy_x_preferred":[
        "\u09ae\u09be\u09b0\u09b9\u09be\u0989\u09b0\u09be"
    ],
    "name:bul_x_preferred":[
        "\u041c\u0430\u0440\u0445\u0430\u0443\u0440\u0430"
    ],
    "name:ceb_x_preferred":[
        "Marhaura"
    ],
    "name:eng_x_preferred":[
        "Marhaura"
    ],
    "name:fra_x_preferred":[
        "Marhaura"
    ],
    "name:hif_x_preferred":[
        "Marhaura"
    ],
    "name:ita_x_preferred":[
        "Marhaura"
    ],
    "name:mlg_x_preferred":[
        "Marhaura"
    ],
    "name:msa_x_preferred":[
        "Marhaura"
    ],
    "name:nan_x_preferred":[
        "Marhaura"
    ],
    "name:new_x_preferred":[
        "\u092e\u0930\u094d\u0939\u094c\u0930\u093e"
    ],
    "name:nld_x_preferred":[
        "Marhaura"
    ],
    "name:ori_x_preferred":[
        "\u0b2e\u0b3e\u0b30\u0b4d\u0b39\u0b3e\u0b09\u0b30\u0b3e"
    ],
    "name:por_x_preferred":[
        "Marhaura"
    ],
    "name:swe_x_preferred":[
        "Marhaura"
    ],
    "name:urd_x_preferred":[
        "\u0645\u0631\u06c1\u0627\u0648\u0631\u0627"
    ],
    "name:vie_x_preferred":[
        "Marhaura"
    ],
    "name:zho_x_preferred":[
        "\u9a6c\u5c14\u8c6a\u62c9"
    ],
    "qs:name":"Mahwara",
    "qs:name_adm0":"India",
    "qs:name_adm1":"Bihar",
    "qs:photos_9r":0,
    "qs:photos_sr":0,
    "qs:placetype":"Town",
    "qs:pop_sr":"7",
    "wof:name":"Mahwara",
    "wof:placetype":"locality",
    "wof:population":26138
},
  "geometry": {"coordinates":[84.86221,25.96927],"type":"Point"}
}