{
  "type": "Feature",
  "properties": {
    "iso:country":"IN",
    "ks:ks_name":"Anadka",
    "ks:ks_pop":1040,
    "ks:ks_type":"HABITATION",
    "name:eng_x_preferred":[
        "Anadka"
    ],
    "wof:name":"Anadka",
    "wof:placetype":"locality",
    "wof:population":1040
},
  "geometry": {"coordinates":[75.184901,12.646273],"type":"Point"}
}