{
  "type": "Feature",
  "properties": {
    "iso:country":"IN",
    "ks:ks_alt_nam":"Telekhata Punji NC",
    "ks:ks_name":"Telekhata Punji Nc",
    "ks:ks_pop":175,
    "ks:ks_type":"HABITATION",
    "name:eng_x_preferred":[
        "Telekhata Punji Nc"
    ],
    "wof:name":"Telekhata Punji Nc",
    "wof:placetype":"locality",
    "wof:population":175
},
  "geometry": {"coordinates":[92.523991,24.456751],"type":"Point"}
}