{
  "type": "Feature",
  "properties": {
    "gn:admin1_code":"11",
    "gn:admin2_code":"23.0",
    "gn:asciiname":"Jamun Got",
    "gn:country_code":"IN",
    "gn:dem":3176,
    "gn:feature_class":"P",
    "gn:feature_code":"PPL",
    "gn:name":"Jam\u016bn Got",
    "gn:population":0,
    "gn:timezone":"Asia/Kolkata",
    "iso:country":"IN",
    "wof:name":"Jamun Got",
    "wof:placetype":"locality"
},
  "geometry": {"coordinates":[76.12679,32.96664000000001],"type":"Point"}
}