{
  "type": "Feature",
  "properties": {
    "gn:admin1_code":"2",
    "gn:admin2_code":"546.0",
    "gn:asciiname":"Buvvanapalle",
    "gn:country_code":"IN",
    "gn:dem":16,
    "gn:feature_class":"P",
    "gn:feature_code":"PPL",
    "gn:name":"Buvvanapalle",
    "gn:population":0,
    "gn:timezone":"Asia/Kolkata",
    "iso:country":"IN",
    "ks:ks_name":"Buvvanapalle",
    "ks:ks_pop":6297,
    "ks:ks_type":"VILLAGE",
    "ks:ks_uagg_main":0,
    "name:eng_x_preferred":[
        "Buvvanapalle"
    ],
    "wof:name":"Buvvanapalle",
    "wof:placetype":"neighbourhood",
    "wof:population":6297
},
  "geometry": {"coordinates":[81.448494,16.705357],"type":"Point"}
}