{
  "type": "Feature",
  "properties": {
    "iso:country":"IN",
    "ks:ks_name":"Golabahra",
    "ks:ks_pop":151,
    "ks:ks_type":"HABITATION",
    "name:eng_x_preferred":[
        "Golabahra"
    ],
    "wof:name":"Golabahra",
    "wof:placetype":"locality",
    "wof:population":151
},
  "geometry": {"coordinates":[82.18325400000001,22.835072],"type":"Point"}
}