{
  "type": "Feature",
  "properties": {
    "iso:country":"IN",
    "ks:ks_name":"Gangavalasa",
    "ks:ks_pop":28,
    "ks:ks_type":"HABITATION",
    "name:eng_x_preferred":[
        "Gangavalasa"
    ],
    "wof:name":"Gangavalasa",
    "wof:placetype":"locality",
    "wof:population":28
},
  "geometry": {"coordinates":[82.73203599999999,18.268724],"type":"Point"}
}