{
  "type": "Feature",
  "properties": {
    "gn:admin1_code":"10.0",
    "gn:admin2_code":"70.0",
    "gn:asciiname":"Mughal Majra",
    "gn:country_code":"IN",
    "gn:dem":338,
    "gn:feature_class":"P",
    "gn:feature_code":"PPL",
    "gn:name":"Mughal M\u0101jra",
    "gn:population":0,
    "gn:timezone":"Asia/Kolkata",
    "iso:country":"IN",
    "wof:name":"Mughal Majra",
    "wof:placetype":"locality"
},
  "geometry": {"coordinates":[77.15075999999998,30.51337],"type":"Point"}
}