{
  "type": "Feature",
  "properties": {
    "iso:country":"IN",
    "ks:ks_alt_nam":"Eyal city",
    "ks:ks_name":"Eyal City",
    "ks:ks_pop":350,
    "ks:ks_type":"HABITATION",
    "name:eng_x_preferred":[
        "Eyal City"
    ],
    "wof:name":"Eyal City",
    "wof:placetype":"locality",
    "wof:population":350
},
  "geometry": {"coordinates":[76.981702,9.866898],"type":"Point"}
}