{
  "type": "Feature",
  "properties": {
    "iso:country":"IN",
    "ks:ks_name":"Kelu Kheri",
    "ks:ks_pop":84,
    "ks:ks_type":"VILLAGE",
    "ks:ks_uagg_main":0,
    "name:eng_x_preferred":[
        "Kelu Kheri"
    ],
    "wof:name":"Kelu Kheri",
    "wof:placetype":"neighbourhood",
    "wof:population":84
},
  "geometry": {"coordinates":[75.718622,24.876972],"type":"Point"}
}