{
  "type": "Feature",
  "properties": {
    "iso:country":"IN",
    "ks:ks_name":"Arokiyapuram",
    "ks:ks_pop":382,
    "ks:ks_type":"HABITATION",
    "ks:ks_uagg_main":0,
    "name:eng_x_preferred":[
        "Arokiyapuram"
    ],
    "wof:name":"Arokiyapuram",
    "wof:placetype":"neighbourhood",
    "wof:population":382
},
  "geometry": {"coordinates":[79.69544500000001,12.622806],"type":"Point"}
}