{
  "type": "Feature",
  "properties": {
    "iso:country":"IN",
    "ks:ks_name":"Mavinhalli",
    "ks:ks_pop":189,
    "ks:ks_type":"HABITATION",
    "name:eng_x_preferred":[
        "Mavinhalli"
    ],
    "wof:name":"Mavinhalli",
    "wof:placetype":"locality",
    "wof:population":189
},
  "geometry": {"coordinates":[75.895833,12.403333],"type":"Point"}
}