{
  "type": "Feature",
  "properties": {
    "iso:country":"IN",
    "ks:ks_name":"Baishnabnagar",
    "ks:ks_pop":11525,
    "ks:ks_type":"VILLAGE",
    "ks:ks_uagg_main":0,
    "name:eng_x_preferred":[
        "Baishnabnagar"
    ],
    "wof:name":"Baishnabnagar",
    "wof:placetype":"neighbourhood",
    "wof:population":11525
},
  "geometry": {"coordinates":[87.972438,24.834263],"type":"Point"}
}