{
  "type": "Feature",
  "properties": {
    "iso:country":"IN",
    "ks:ks_name":"Baijnathpuwa",
    "ks:ks_pop":233,
    "ks:ks_type":"HABITATION",
    "name:eng_x_preferred":[
        "Baijnathpuwa"
    ],
    "wof:name":"Baijnathpuwa",
    "wof:placetype":"locality",
    "wof:population":233
},
  "geometry": {"coordinates":[80.887058,27.652653],"type":"Point"}
}