{
  "type": "Feature",
  "properties": {
    "iso:country":"IN",
    "ks:ks_alt_nam":"patilpada",
    "ks:ks_name":"Patilpada",
    "ks:ks_pop":83,
    "ks:ks_type":"HABITATION",
    "name:eng_x_preferred":[
        "Patilpada"
    ],
    "wof:name":"Patilpada",
    "wof:placetype":"locality",
    "wof:population":83
},
  "geometry": {"coordinates":[72.754969,19.856962],"type":"Point"}
}