{
  "type": "Feature",
  "properties": {
    "gn:admin1_code":"25",
    "gn:admin2_code":"607.0",
    "gn:asciiname":"Odiyattur",
    "gn:country_code":"IN",
    "gn:dem":93,
    "gn:feature_class":"P",
    "gn:feature_code":"PPL",
    "gn:name":"Odiy\u0101tt\u016br",
    "gn:population":0,
    "gn:timezone":"Asia/Kolkata",
    "iso:country":"IN",
    "wof:name":"Odiyattur",
    "wof:placetype":"locality"
},
  "geometry": {"coordinates":[79.35106,12.03108],"type":"Point"}
}