{
  "type": "Feature",
  "properties": {
    "iso:country":"IN",
    "ks:ks_name":"Phulnagar",
    "ks:ks_pop":1086,
    "ks:ks_type":"VILLAGE",
    "name:eng_x_preferred":[
        "Phulnagar"
    ],
    "wof:name":"Phulnagar",
    "wof:placetype":"locality",
    "wof:population":1086
},
  "geometry": {"coordinates":[87.468508,23.029488],"type":"Point"}
}