{
  "type": "Feature",
  "properties": {
    "iso:country":"IN",
    "ks:ks_name":"Rayasu",
    "ks:ks_pop":5,
    "ks:ks_type":"HABITATION",
    "name:eng_x_preferred":[
        "Rayasu"
    ],
    "wof:name":"Rayasu",
    "wof:placetype":"locality",
    "wof:population":5
},
  "geometry": {"coordinates":[78.343795,29.945267],"type":"Point"}
}