{
  "type": "Feature",
  "properties": {
    "iso:country":"IN",
    "ks:ks_name":"Manthakattur",
    "ks:ks_pop":249,
    "ks:ks_type":"HABITATION",
    "ks:ks_uagg_main":0,
    "name:eng_x_preferred":[
        "Manthakattur"
    ],
    "wof:name":"Manthakattur",
    "wof:placetype":"neighbourhood",
    "wof:population":249
},
  "geometry": {"coordinates":[77.593988,11.422402],"type":"Point"}
}