{
  "type": "Feature",
  "properties": {
    "iso:country":"IN",
    "ks:ks_name":"Gundiseedu",
    "ks:ks_pop":152,
    "ks:ks_type":"HABITATION",
    "name:eng_x_preferred":[
        "Gundiseedu"
    ],
    "wof:name":"Gundiseedu",
    "wof:placetype":"locality",
    "wof:population":152
},
  "geometry": {"coordinates":[77.597362,12.119711],"type":"Point"}
}