{
  "type": "Feature",
  "properties": {
    "iso:country":"IN",
    "ks:ks_name":"Varachi Sukamwadi",
    "ks:ks_pop":216,
    "ks:ks_type":"HABITATION",
    "name:eng_x_preferred":[
        "Varachi Sukamwadi"
    ],
    "wof:name":"Varachi Sukamwadi",
    "wof:placetype":"locality",
    "wof:population":216
},
  "geometry": {"coordinates":[73.631944,16.958333],"type":"Point"}
}