{
  "type": "Feature",
  "properties": {
    "gn:admin1_code":"37",
    "gn:admin2_code":"408.0",
    "gn:asciiname":"Gatapar",
    "gn:country_code":"IN",
    "gn:dem":381,
    "gn:feature_class":"P",
    "gn:feature_code":"PPL",
    "gn:name":"G\u0101t\u0101p\u0101r",
    "gn:population":0,
    "gn:timezone":"Asia/Kolkata",
    "iso:country":"IN",
    "wof:name":"Gatapar",
    "wof:placetype":"locality"
},
  "geometry": {"coordinates":[80.87936999999999,21.50475],"type":"Point"}
}