{
  "type": "Feature",
  "properties": {
    "gn:admin1_code":"17",
    "gn:admin2_code":"273.0",
    "gn:asciiname":"Phellong",
    "gn:country_code":"IN",
    "gn:dem":943,
    "gn:feature_class":"P",
    "gn:feature_code":"PPL",
    "gn:name":"Phellong",
    "gn:population":0,
    "gn:timezone":"Asia/Kolkata",
    "iso:country":"IN",
    "wof:name":"Phellong",
    "wof:placetype":"locality"
},
  "geometry": {"coordinates":[93.44307999999999,25.0971],"type":"Point"}
}