{
  "type": "Feature",
  "properties": {
    "iso:country":"IN",
    "ks:ks_name":"Kumbharshet",
    "ks:ks_pop":920,
    "ks:ks_type":"VILLAGE",
    "name:eng_x_preferred":[
        "Kumbharshet"
    ],
    "wof:name":"Kumbharshet",
    "wof:placetype":"locality",
    "wof:population":920
},
  "geometry": {"coordinates":[73.206976,18.547785],"type":"Point"}
}