{
  "type": "Feature",
  "properties": {
    "iso:country":"IN",
    "ks:ks_alt_nam":"J\u0101tarma",
    "ks:ks_name":"Jatarma",
    "ks:ks_pop":126,
    "ks:ks_type":"VILLAGE",
    "name:eng_x_preferred":[
        "Jatarma"
    ],
    "name:eng_x_variant":[
        "J\u0101tarma"
    ],
    "wof:name":"Jatarma",
    "wof:placetype":"locality",
    "wof:population":126
},
  "geometry": {"coordinates":[85.22253000000001,22.758728],"type":"Point"}
}