{
  "type": "Feature",
  "properties": {
    "gn:admin1_code":"35",
    "gn:admin2_code":"455.0",
    "gn:asciiname":"Sirekadhana",
    "gn:country_code":"IN",
    "gn:dem":894,
    "gn:feature_class":"P",
    "gn:feature_code":"PPL",
    "gn:name":"Sirek\u0101dh\u0101na",
    "gn:population":0,
    "gn:timezone":"Asia/Kolkata",
    "iso:country":"IN",
    "wof:name":"Sirekadhana",
    "wof:placetype":"locality"
},
  "geometry": {"coordinates":[78.90926,22.4774],"type":"Point"}
}