{
  "type": "Feature",
  "properties": {
    "gn:admin1_code":"21.0",
    "gn:admin2_code":"398.0",
    "gn:asciiname":"Dummuriguda",
    "gn:country_code":"IN",
    "gn:dem":874,
    "gn:feature_class":"P",
    "gn:feature_code":"PPL",
    "gn:name":"Dummuriguda",
    "gn:population":0,
    "gn:timezone":"Asia/Kolkata",
    "iso:country":"IN",
    "wof:name":"Dummuriguda",
    "wof:placetype":"locality"
},
  "geometry": {"coordinates":[82.78155,18.78146],"type":"Point"}
}