{
  "type": "Feature",
  "properties": {
    "gn:admin1_code":"10.0",
    "gn:admin2_code":"77.0",
    "gn:asciiname":"Kair Kheri",
    "gn:country_code":"IN",
    "gn:dem":229,
    "gn:feature_class":"P",
    "gn:feature_code":"PPL",
    "gn:name":"Kair Kheri",
    "gn:population":0,
    "gn:timezone":"Asia/Kolkata",
    "iso:country":"IN",
    "wof:name":"Kair Kheri",
    "wof:placetype":"locality"
},
  "geometry": {"coordinates":[76.30968,29.35809],"type":"Point"}
}