{
  "type": "Feature",
  "properties": {
    "iso:country":"IN",
    "ks:ks_name":"Bolibaitanda",
    "ks:ks_pop":54,
    "ks:ks_type":"HABITATION",
    "name:eng_x_preferred":[
        "Bolibaitanda"
    ],
    "wof:name":"Bolibaitanda",
    "wof:placetype":"locality",
    "wof:population":54
},
  "geometry": {"coordinates":[77.668972,17.094253],"type":"Point"}
}