{
  "type": "Feature",
  "properties": {
    "iso:country":"IN",
    "ks:ks_name":"Chak Mohamd Urf Pooresood",
    "ks:ks_pop":1480,
    "ks:ks_type":"VILLAGE",
    "name:eng_x_preferred":[
        "Chak Mohamd Urf Pooresood"
    ],
    "wof:name":"Chak Mohamd Urf Pooresood",
    "wof:placetype":"locality",
    "wof:population":1480
},
  "geometry": {"coordinates":[82.090114,25.519119],"type":"Point"}
}