{
  "type": "Feature",
  "properties": {
    "iso:country":"IN",
    "ks:ks_name":"Yemmegundi",
    "ks:ks_pop":37,
    "ks:ks_type":"HABITATION",
    "name:eng_x_preferred":[
        "Yemmegundi"
    ],
    "wof:name":"Yemmegundi",
    "wof:placetype":"locality",
    "wof:population":37
},
  "geometry": {"coordinates":[74.576786,14.514872],"type":"Point"}
}