{
  "type": "Feature",
  "properties": {
    "gn:admin1_code":"12.0",
    "gn:admin2_code":"13.0",
    "gn:asciiname":"Kongun",
    "gn:country_code":"IN",
    "gn:dem":1746,
    "gn:feature_class":"P",
    "gn:feature_code":"PPL",
    "gn:name":"Kongun",
    "gn:population":0,
    "gn:timezone":"Asia/Kolkata",
    "iso:country":"IN",
    "wof:name":"Kongun",
    "wof:placetype":"locality"
},
  "geometry": {"coordinates":[74.92059999999999,33.78406],"type":"Point"}
}