{
  "type": "Feature",
  "properties": {
    "iso:country":"IN",
    "ks:ks_name":"Chikatiya",
    "ks:ks_pop":1242,
    "ks:ks_type":"VILLAGE",
    "ks:ks_uagg_main":0,
    "name:eng_x_preferred":[
        "Chikatiya"
    ],
    "wof:name":"Chikatiya",
    "wof:placetype":"locality",
    "wof:population":1242
},
  "geometry": {"coordinates":[73.326747,20.750296],"type":"Point"}
}