{
  "type": "Feature",
  "properties": {
    "iso:country":"IN",
    "ks:ks_alt_nam":"Gollarhatti.S",
    "ks:ks_name":"Gollarhatti.s",
    "ks:ks_pop":245,
    "ks:ks_type":"HABITATION",
    "name:eng_x_preferred":[
        "Gollarhatti.s"
    ],
    "wof:name":"Gollarhatti.s",
    "wof:placetype":"locality",
    "wof:population":245
},
  "geometry": {"coordinates":[76.514611,15.998064],"type":"Point"}
}