{
  "type": "Feature",
  "properties": {
    "iso:country":"IN",
    "ks:ks_name":"Chaukidhar",
    "ks:ks_pop":137,
    "ks:ks_type":"HABITATION",
    "name:eng_x_preferred":[
        "Chaukidhar"
    ],
    "wof:name":"Chaukidhar",
    "wof:placetype":"locality",
    "wof:population":137
},
  "geometry": {"coordinates":[82.242392,27.71668],"type":"Point"}
}