{
  "type": "Feature",
  "properties": {
    "iso:country":"IN",
    "ks:ks_name":"Datirwasti No.2",
    "ks:ks_pop":174,
    "ks:ks_type":"HABITATION",
    "name:eng_x_preferred":[
        "Datirwasti No.2"
    ],
    "wof:name":"Datirwasti No.2",
    "wof:placetype":"locality",
    "wof:population":174
},
  "geometry": {"coordinates":[75.01705,19.20389],"type":"Point"}
}