{
  "type": "Feature",
  "properties": {
    "iso:country":"IN",
    "ks:ks_name":"Chhota Bichkani",
    "ks:ks_pop":0,
    "ks:ks_type":"VILLAGE",
    "name:eng_x_preferred":[
        "Chhota Bichkani"
    ],
    "wof:name":"Chhota Bichkani",
    "wof:placetype":"locality",
    "wof:population":0
},
  "geometry": {"coordinates":[87.677391,24.872066],"type":"Point"}
}