{
  "type": "Feature",
  "properties": {
    "iso:country":"IN",
    "ks:ks_name":"Ganget",
    "ks:ks_pop":1688,
    "ks:ks_type":"VILLAGE",
    "name:eng_x_preferred":[
        "Ganget"
    ],
    "wof:name":"Ganget",
    "wof:placetype":"locality",
    "wof:population":1688
},
  "geometry": {"coordinates":[72.16964,23.726137],"type":"Point"}
}