{
  "type": "Feature",
  "properties": {
    "gn:admin1_code":"11",
    "gn:admin2_code":"23.0",
    "gn:asciiname":"Jaddna",
    "gn:country_code":"IN",
    "gn:dem":2461,
    "gn:feature_class":"P",
    "gn:feature_code":"PPL",
    "gn:name":"Jaddna",
    "gn:population":0,
    "gn:timezone":"Asia/Kolkata",
    "iso:country":"IN",
    "wof:name":"Jaddna",
    "wof:placetype":"locality"
},
  "geometry": {"coordinates":[76.20116,32.80938],"type":"Point"}
}