{
  "type": "Feature",
  "properties": {
    "iso:country":"IN",
    "ks:ks_alt_nam":"gwjwn furi",
    "ks:ks_name":"Gwjwn Furi",
    "ks:ks_pop":60,
    "ks:ks_type":"HABITATION",
    "name:eng_x_preferred":[
        "Gwjwn Furi"
    ],
    "wof:name":"Gwjwn Furi",
    "wof:placetype":"locality",
    "wof:population":60
},
  "geometry": {"coordinates":[91.834231,26.631972],"type":"Point"}
}