{
  "type": "Feature",
  "properties": {
    "iso:country":"IN",
    "ks:ks_name":"Islampur",
    "ks:ks_pop":135,
    "ks:ks_type":"HABITATION",
    "name:eng_x_preferred":[
        "Islampur"
    ],
    "wof:name":"Islampur",
    "wof:placetype":"locality",
    "wof:population":135
},
  "geometry": {"coordinates":[84.50589100000001,24.819482],"type":"Point"}
}