{
  "type": "Feature",
  "properties": {
    "iso:country":"IN",
    "ks:ks_name":"Amlam",
    "ks:ks_pop":456,
    "ks:ks_type":"HABITATION",
    "name:eng_x_preferred":[
        "Amlam"
    ],
    "wof:name":"Amlam",
    "wof:placetype":"locality",
    "wof:population":456
},
  "geometry": {"coordinates":[85.323009,21.886313],"type":"Point"}
}