{
  "type": "Feature",
  "properties": {
    "gn:admin1_code":"29.0",
    "gn:admin2_code":"243.0",
    "gn:asciiname":"Suiram",
    "gn:country_code":"IN",
    "gn:dem":1418,
    "gn:feature_class":"P",
    "gn:feature_code":"PPL",
    "gn:name":"Su\u012br\u0101m",
    "gn:population":0,
    "gn:timezone":"Asia/Kolkata",
    "iso:country":"IN",
    "wof:name":"Suiram",
    "wof:placetype":"locality"
},
  "geometry": {"coordinates":[88.44797,27.17241],"type":"Point"}
}