{
  "type": "Feature",
  "properties": {
    "iso:country":"IN",
    "ks:ks_name":"Mannapara",
    "ks:ks_pop":711,
    "ks:ks_type":"HABITATION",
    "ks:ks_uagg_main":0,
    "name:eng_x_preferred":[
        "Mannapara"
    ],
    "wof:name":"Mannapara",
    "wof:placetype":"neighbourhood",
    "wof:population":711
},
  "geometry": {"coordinates":[87.961838,22.646251],"type":"Point"}
}