{
  "type": "Feature",
  "properties": {
    "iso:country":"IN",
    "ks:ks_name":"Tham",
    "ks:ks_pop":58,
    "ks:ks_type":"VILLAGE",
    "name:eng_x_preferred":[
        "Tham"
    ],
    "wof:name":"Tham",
    "wof:placetype":"locality",
    "wof:population":58
},
  "geometry": {"coordinates":[80.35433,29.773691],"type":"Point"}
}