{
  "type": "Feature",
  "properties": {
    "iso:country":"IN",
    "ks:ks_name":"Chandpur",
    "ks:ks_pop":3309,
    "ks:ks_type":"VILLAGE",
    "ks:ks_uagg_main":0,
    "name:eng_x_preferred":[
        "Chandpur"
    ],
    "name:hin_x_preferred":[
        "\u091a\u093e\u0902\u0926\u092a\u0941\u0930"
    ],
    "wof:name":"Chandpur",
    "wof:placetype":"neighbourhood",
    "wof:population":3309
},
  "geometry": {"coordinates":[88.501366,23.969469],"type":"Point"}
}