{
  "type": "Feature",
  "properties": {
    "iso:country":"IN",
    "ks:ks_alt_nam":"TIKAM KI DHANI",
    "ks:ks_name":"Tikam Ki Dhani",
    "ks:ks_pop":299,
    "ks:ks_type":"HABITATION",
    "name:eng_x_preferred":[
        "Tikam Ki Dhani"
    ],
    "wof:name":"Tikam Ki Dhani",
    "wof:placetype":"locality",
    "wof:population":299
},
  "geometry": {"coordinates":[70.438864,25.979511],"type":"Point"}
}