{
  "type": "Feature",
  "properties": {
    "iso:country":"IN",
    "ks:ks_name":"Thottackad",
    "ks:ks_pop":15391,
    "ks:ks_type":"VILLAGE",
    "name:eng_x_preferred":[
        "Thottackad"
    ],
    "wof:name":"Thottackad",
    "wof:placetype":"locality",
    "wof:population":15391
},
  "geometry": {"coordinates":[76.60253899999999,9.520712],"type":"Point"}
}