{
  "type": "Feature",
  "properties": {
    "iso:country":"IN",
    "ks:ks_name":"Badlipura Kalan",
    "ks:ks_pop":383,
    "ks:ks_type":"VILLAGE",
    "name:eng_x_preferred":[
        "Badlipura Kalan"
    ],
    "wof:name":"Badlipura Kalan",
    "wof:placetype":"locality",
    "wof:population":383
},
  "geometry": {"coordinates":[75.167232,22.474032],"type":"Point"}
}