{
  "type": "Feature",
  "properties": {
    "iso:country":"IN",
    "ks:ks_name":"Rauchak Chauki",
    "ks:ks_pop":16,
    "ks:ks_type":"VILLAGE",
    "name:eng_x_preferred":[
        "Rauchak Chauki"
    ],
    "wof:name":"Rauchak Chauki",
    "wof:placetype":"locality",
    "wof:population":16
},
  "geometry": {"coordinates":[79.108729,30.56826],"type":"Point"}
}