{
  "type": "Feature",
  "properties": {
    "gn:admin1_code":"36",
    "gn:admin2_code":"194.0",
    "gn:asciiname":"Lachhanpur",
    "gn:country_code":"IN",
    "gn:dem":87,
    "gn:feature_class":"P",
    "gn:feature_code":"PPL",
    "gn:name":"Lachhanpur",
    "gn:population":0,
    "gn:timezone":"Asia/Kolkata",
    "iso:country":"IN",
    "ks:ks_name":"Lachhanpur",
    "ks:ks_pop":901,
    "ks:ks_type":"VILLAGE",
    "ks:ks_uagg_main":0,
    "name:eng_x_preferred":[
        "Lachhanpur"
    ],
    "wof:name":"Lachhanpur",
    "wof:placetype":"neighbourhood",
    "wof:population":901
},
  "geometry": {"coordinates":[82.699139,25.543323],"type":"Point"}
}