{
  "type": "Feature",
  "properties": {
    "iso:country":"IN",
    "ks:ks_name":"Nangli Khaleel",
    "ks:ks_pop":108,
    "ks:ks_type":"VILLAGE",
    "name:eng_x_preferred":[
        "Nangli Khaleel"
    ],
    "wof:name":"Nangli Khaleel",
    "wof:placetype":"locality",
    "wof:population":108
},
  "geometry": {"coordinates":[76.675275,27.713733],"type":"Point"}
}