{
  "type": "Feature",
  "properties": {
    "iso:country":"IN",
    "ks:ks_name":"Arunthathiar Colony",
    "ks:ks_pop":140,
    "ks:ks_type":"HABITATION",
    "name:eng_x_preferred":[
        "Arunthathiar Colony"
    ],
    "wof:name":"Arunthathiar Colony",
    "wof:placetype":"locality",
    "wof:population":140
},
  "geometry": {"coordinates":[80.011484,13.313034],"type":"Point"}
}