{
  "type": "Feature",
  "properties": {
    "iso:country":"IN",
    "ks:ks_name":"Pali Khera",
    "ks:ks_pop":2807,
    "ks:ks_type":"VILLAGE",
    "ks:ks_uagg_main":0,
    "name:eng_x_preferred":[
        "Pali Khera"
    ],
    "wof:name":"Pali Khera",
    "wof:placetype":"neighbourhood",
    "wof:population":2807
},
  "geometry": {"coordinates":[77.640153,27.47491],"type":"Point"}
}