{
  "type": "Feature",
  "properties": {
    "iso:country":"IN",
    "ks:ks_name":"Garo Bosti",
    "ks:ks_pop":84,
    "ks:ks_type":"HABITATION",
    "ks:ks_uagg_main":0,
    "name:eng_x_preferred":[
        "Garo Bosti"
    ],
    "wof:name":"Garo Bosti",
    "wof:placetype":"neighbourhood",
    "wof:population":84
},
  "geometry": {"coordinates":[93.79256599999999,26.085973],"type":"Point"}
}