{
  "type": "Feature",
  "properties": {
    "gn:admin1_code":"23.0",
    "gn:admin2_code":"041",
    "gn:asciiname":"Jarg",
    "gn:country_code":"IN",
    "gn:dem":262,
    "gn:feature_class":"P",
    "gn:feature_code":"PPL",
    "gn:name":"Jarg",
    "gn:population":0,
    "gn:timezone":"Asia/Kolkata",
    "iso:country":"IN",
    "wof:name":"Jarg",
    "wof:placetype":"locality"
},
  "geometry": {"coordinates":[76.06941999999999,30.61318],"type":"Point"}
}