{
  "type": "Feature",
  "properties": {
    "gn:admin1_code":"13.0",
    "gn:admin2_code":"596.0",
    "gn:asciiname":"Tattakannankudi",
    "gn:country_code":"IN",
    "gn:dem":140,
    "gn:feature_class":"P",
    "gn:feature_code":"PPL",
    "gn:name":"Tattakannankudi",
    "gn:population":0,
    "gn:timezone":"Asia/Kolkata",
    "iso:country":"IN",
    "wof:name":"Tattakannankudi",
    "wof:placetype":"locality"
},
  "geometry": {"coordinates":[76.88365999999998,10.00037],"type":"Point"}
}