{
  "type": "Feature",
  "properties": {
    "gn:admin1_code":"36",
    "gn:admin2_code":"154.0",
    "gn:asciiname":"Jafarpur",
    "gn:country_code":"IN",
    "gn:dem":123,
    "gn:feature_class":"P",
    "gn:feature_code":"PPL",
    "gn:name":"J\u0101farpur",
    "gn:population":0,
    "gn:timezone":"Asia/Kolkata",
    "iso:country":"IN",
    "ks:ks_alt_nam":"JafarPurwa",
    "ks:ks_name":"Jafarpurwa",
    "ks:ks_pop":236,
    "ks:ks_type":"HABITATION",
    "ks:ks_uagg_main":0,
    "name:ben_x_preferred":[
        "\u099c\u09be\u09ab\u09b0\u09aa\u09c1\u09b0"
    ],
    "name:bpy_x_preferred":[
        "\u099c\u09be\u09ab\u09b0\u09aa\u09c1\u09b0"
    ],
    "name:ceb_x_preferred":[
        "J\u0101farpur"
    ],
    "name:eng_x_preferred":[
        "Jafarpurwa"
    ],
    "name:ita_x_preferred":[
        "Jafarpur"
    ],
    "name:msa_x_preferred":[
        "Jafarpur"
    ],
    "name:new_x_preferred":[
        "\u091c\u092b\u0930\u092a\u0941\u0930"
    ],
    "name:nld_x_preferred":[
        "Jafarpur"
    ],
    "name:por_x_preferred":[
        "Jafarpur"
    ],
    "name:swe_x_preferred":[
        "J\u0101farpur"
    ],
    "name:urd_x_preferred":[
        "\u062c\u0641\u0631\u067e\u0648\u0631"
    ],
    "name:vie_x_preferred":[
        "Jafarpur"
    ],
    "name:zho_x_preferred":[
        "\u8d3e\u6cd5\u5c14\u666e\u5c14"
    ],
    "wof:name":"Jafarpurwa",
    "wof:placetype":"neighbourhood",
    "wof:population":236
},
  "geometry": {"coordinates":[81.252954,27.607108],"type":"Point"}
}