{
  "type": "Feature",
  "properties": {
    "iso:country":"IN",
    "ks:ks_name":"Bona",
    "ks:ks_pop":1062,
    "ks:ks_type":"VILLAGE",
    "ks:ks_uagg_main":0,
    "name:eng_x_preferred":[
        "Bona"
    ],
    "wof:name":"Bona",
    "wof:placetype":"neighbourhood",
    "wof:population":1062
},
  "geometry": {"coordinates":[78.266071,25.993218],"type":"Point"}
}