{
  "type": "Feature",
  "properties": {
    "iso:country":"IN",
    "ks:ks_name":"Chainasar",
    "ks:ks_pop":640,
    "ks:ks_type":"HABITATION",
    "name:eng_x_preferred":[
        "Chainasar"
    ],
    "wof:name":"Chainasar",
    "wof:placetype":"locality",
    "wof:population":640
},
  "geometry": {"coordinates":[73.706861,27.585778],"type":"Point"}
}