{
  "type": "Feature",
  "properties": {
    "iso:country":"IN",
    "ks:ks_name":"Manigudde",
    "ks:ks_pop":41,
    "ks:ks_type":"HABITATION",
    "name:eng_x_preferred":[
        "Manigudde"
    ],
    "wof:name":"Manigudde",
    "wof:placetype":"locality",
    "wof:population":41
},
  "geometry": {"coordinates":[74.420962,14.603802],"type":"Point"}
}