{
  "type": "Feature",
  "properties": {
    "iso:country":"IN",
    "ks:ks_name":"Nauka Tola",
    "ks:ks_pop":1671,
    "ks:ks_type":"VILLAGE",
    "ks:ks_uagg_main":0,
    "name:eng_x_preferred":[
        "Nauka Tola"
    ],
    "wof:name":"Nauka Tola",
    "wof:placetype":"neighbourhood",
    "wof:population":1671
},
  "geometry": {"coordinates":[83.995808,26.502716],"type":"Point"}
}