{
  "type": "Feature",
  "properties": {
    "iso:country":"IN",
    "ks:ks_alt_nam":"Yadu Roy ke Tola",
    "ks:ks_name":"Yadu Roy Ke Tola",
    "ks:ks_pop":629,
    "ks:ks_type":"HABITATION",
    "name:eng_x_preferred":[
        "Yadu Roy Ke Tola"
    ],
    "wof:name":"Yadu Roy Ke Tola",
    "wof:placetype":"locality",
    "wof:population":629
},
  "geometry": {"coordinates":[84.418937,26.721696],"type":"Point"}
}