{
  "type": "Feature",
  "properties": {
    "iso:country":"IN",
    "ks:ks_name":"Saliwada",
    "ks:ks_pop":0,
    "ks:ks_type":"VILLAGE",
    "name:eng_x_preferred":[
        "Saliwada"
    ],
    "wof:name":"Saliwada",
    "wof:placetype":"locality",
    "wof:population":0
},
  "geometry": {"coordinates":[78.28483,23.604144],"type":"Point"}
}