{
  "type": "Feature",
  "properties": {
    "iso:country":"IN",
    "ks:ks_name":"Nuapada",
    "ks:ks_pop":809,
    "ks:ks_type":"VILLAGE",
    "ks:ks_uagg_main":0,
    "name:eng_x_preferred":[
        "Nuapada"
    ],
    "wof:name":"Nuapada",
    "wof:placetype":"neighbourhood",
    "wof:population":809
},
  "geometry": {"coordinates":[85.427702,19.928862],"type":"Point"}
}