{
  "type": "Feature",
  "properties": {
    "gn:admin1_code":"19.0",
    "gn:admin2_code":"584.0",
    "gn:asciiname":"Arlalsandra",
    "gn:country_code":"IN",
    "gn:dem":651,
    "gn:feature_class":"P",
    "gn:feature_code":"PPL",
    "gn:name":"Arlalsandra",
    "gn:population":0,
    "gn:timezone":"Asia/Kolkata",
    "iso:country":"IN",
    "wof:name":"Arlalsandra",
    "wof:placetype":"locality"
},
  "geometry": {"coordinates":[77.41131999999998,12.58709],"type":"Point"}
}