{
  "type": "Feature",
  "properties": {
    "gn:admin1_code":"9.0",
    "gn:admin2_code":"468",
    "gn:asciiname":"Gadhada",
    "gn:country_code":"IN",
    "gn:dem":33,
    "gn:feature_class":"P",
    "gn:feature_code":"PPL",
    "gn:name":"Gadhada",
    "gn:population":0,
    "gn:timezone":"Asia/Kolkata",
    "iso:country":"IN",
    "name:und_x_variant":[
        "Gadra",
        "Gadhada"
    ],
    "wof:name":"Gadhada",
    "wof:placetype":"locality"
},
  "geometry": {"coordinates":[70.37564,23.86823],"type":"Point"}
}