{
  "type": "Feature",
  "properties": {
    "gn:admin1_code":"9.0",
    "gn:admin2_code":"468",
    "gn:asciiname":"Gadhada",
    "gn:country_code":"IN",
    "gn:dem":33,
    "gn:feature_class":"P",
    "gn:feature_code":"PPL",
    "gn:name":"Gadhada",
    "gn:population":0,
    "gn:timezone":"Asia/Kolkata",
    "iso:country":"IN",
    "name:bpy_x_preferred":[
        "\u0997\u09a7\u09be\u09a6\u09be"
    ],
    "name:ceb_x_preferred":[
        "Gadhada"
    ],
    "name:guj_x_preferred":[
        "\u0a97\u0aa2\u0aa1\u0abe"
    ],
    "name:hin_x_preferred":[
        "\u0917\u0922\u0921\u093c\u093e"
    ],
    "name:ind_x_preferred":[
        "Gadhada"
    ],
    "name:ita_x_preferred":[
        "Gadhada"
    ],
    "name:msa_x_preferred":[
        "Gadhada"
    ],
    "name:new_x_preferred":[
        "\u0917\u0927\u0926\u093e"
    ],
    "name:por_x_preferred":[
        "Gadhada"
    ],
    "name:spa_x_preferred":[
        "Gadhada"
    ],
    "name:swe_x_preferred":[
        "Gadhada"
    ],
    "name:und_x_variant":[
        "Gadra"
    ],
    "name:vie_x_preferred":[
        "Gadhada"
    ],
    "name:zho_x_preferred":[
        "\u52a0\u8fbe\u8fbe"
    ],
    "wof:name":"Gadhada",
    "wof:placetype":"locality"
},
  "geometry": {"coordinates":[70.37564,23.86823],"type":"Point"}
}