{
  "type": "Feature",
  "properties": {
    "gn:admin1_code":"36.0",
    "gn:admin2_code":"150.0",
    "gn:asciiname":"Bohit",
    "gn:country_code":"IN",
    "gn:dem":176,
    "gn:feature_class":"P",
    "gn:feature_code":"PPL",
    "gn:name":"Bohit",
    "gn:population":0,
    "gn:timezone":"Asia/Kolkata",
    "iso:country":"IN",
    "wof:name":"Bohit",
    "wof:placetype":"locality"
},
  "geometry": {"coordinates":[79.38703000000002,28.45639000000001],"type":"Point"}
}