{
  "type": "Feature",
  "properties": {
    "iso:country":"IN",
    "ks:ks_name":"Panre Keso",
    "ks:ks_pop":611,
    "ks:ks_type":"VILLAGE",
    "name:eng_x_preferred":[
        "Panre Keso"
    ],
    "wof:name":"Panre Keso",
    "wof:placetype":"locality",
    "wof:population":611
},
  "geometry": {"coordinates":[87.013572,24.553221],"type":"Point"}
}