{
  "type": "Feature",
  "properties": {
    "gn:admin1_code":"39",
    "gn:admin2_code":"56.0",
    "gn:asciiname":"Thanwara",
    "gn:country_code":"IN",
    "gn:dem":2191,
    "gn:feature_class":"P",
    "gn:feature_code":"PPL",
    "gn:name":"Thanw\u0101ra",
    "gn:population":0,
    "gn:timezone":"Asia/Kolkata",
    "iso:country":"IN",
    "wof:name":"Thanwara",
    "wof:placetype":"locality"
},
  "geometry": {"coordinates":[77.85753000000003,31.02216],"type":"Point"}
}