{
  "type": "Feature",
  "properties": {
    "gn:admin1_code":"2.0",
    "gn:admin2_code":"553.0",
    "gn:asciiname":"Chandakacherla",
    "gn:country_code":"IN",
    "gn:dem":633,
    "gn:feature_class":"P",
    "gn:feature_code":"PPL",
    "gn:name":"Chandakacherla",
    "gn:population":0,
    "gn:timezone":"Asia/Kolkata",
    "iso:country":"IN",
    "wof:name":"Chandakacherla",
    "wof:placetype":"locality"
},
  "geometry": {"coordinates":[77.31983000000002,14.00638],"type":"Point"}
}