{
  "type": "Feature",
  "properties": {
    "gn:admin1_code":"38.0",
    "gn:admin2_code":"353.0",
    "gn:asciiname":"Gaurpara",
    "gn:country_code":"IN",
    "gn:dem":264,
    "gn:feature_class":"P",
    "gn:feature_code":"PPL",
    "gn:name":"Gaurp\u0101ra",
    "gn:population":0,
    "gn:timezone":"Asia/Kolkata",
    "iso:country":"IN",
    "ks:ks_name":"Gorpara",
    "ks:ks_pop":473,
    "ks:ks_type":"VILLAGE",
    "name:eng_x_preferred":[
        "Gorpara"
    ],
    "name:eng_x_variant":[
        "Gaurpara"
    ],
    "wof:name":"Gorpara",
    "wof:placetype":"locality",
    "wof:population":473
},
  "geometry": {"coordinates":[87.518141,24.621263],"type":"Point"}
}