{
  "type": "Feature",
  "properties": {
    "gn:admin1_code":"36.0",
    "gn:admin2_code":"132.0",
    "gn:asciiname":"Nai Nagli",
    "gn:country_code":"IN",
    "gn:dem":266,
    "gn:feature_class":"P",
    "gn:feature_code":"PPL",
    "gn:name":"N\u0101i Nagli",
    "gn:population":0,
    "gn:timezone":"Asia/Kolkata",
    "iso:country":"IN",
    "name:und_x_variant":[
        "N\u0101i Nagli",
        "M\u0101zri"
    ],
    "wof:name":"Nai Nagli",
    "wof:placetype":"locality"
},
  "geometry": {"coordinates":[77.39788,29.81338],"type":"Point"}
}