{
  "type": "Feature",
  "properties": {
    "iso:country":"IN",
    "ks:ks_name":"Magarasar",
    "ks:ks_pop":261,
    "ks:ks_type":"HABITATION",
    "name:eng_x_preferred":[
        "Magarasar"
    ],
    "wof:name":"Magarasar",
    "wof:placetype":"locality",
    "wof:population":261
},
  "geometry": {"coordinates":[72.747592,25.913328],"type":"Point"}
}