{
  "type": "Feature",
  "properties": {
    "iso:country":"IN",
    "ks:ks_name":"Ustumvaripalli",
    "ks:ks_pop":403,
    "ks:ks_type":"HABITATION",
    "name:eng_x_preferred":[
        "Ustumvaripalli"
    ],
    "wof:name":"Ustumvaripalli",
    "wof:placetype":"locality",
    "wof:population":403
},
  "geometry": {"coordinates":[79.4641,15.279193],"type":"Point"}
}