{
  "type": "Feature",
  "properties": {
    "iso:country":"IN",
    "ks:ks_name":"Bhattagere",
    "ks:ks_pop":102,
    "ks:ks_type":"HABITATION",
    "name:eng_x_preferred":[
        "Bhattagere"
    ],
    "wof:name":"Bhattagere",
    "wof:placetype":"locality",
    "wof:population":102
},
  "geometry": {"coordinates":[74.729643,14.461084],"type":"Point"}
}