{
  "type": "Feature",
  "properties": {
    "gn:admin1_code":"34.0",
    "gn:admin2_code":"227.0",
    "gn:asciiname":"Indupur",
    "gn:country_code":"IN",
    "gn:dem":50,
    "gn:feature_class":"P",
    "gn:feature_code":"PPL",
    "gn:name":"Indupur",
    "gn:population":0,
    "gn:timezone":"Asia/Kolkata",
    "iso:country":"IN",
    "wof:name":"Indupur",
    "wof:placetype":"locality"
},
  "geometry": {"coordinates":[86.02291,25.27368],"type":"Point"}
}