{
  "type": "Feature",
  "properties": {
    "iso:country":"IN",
    "ks:ks_name":"Usraina",
    "ks:ks_pop":163,
    "ks:ks_type":"HABITATION",
    "name:eng_x_preferred":[
        "Usraina"
    ],
    "wof:name":"Usraina",
    "wof:placetype":"locality",
    "wof:population":163
},
  "geometry": {"coordinates":[81.160945,25.95416],"type":"Point"}
}