{
  "type": "Feature",
  "properties": {
    "iso:country":"IN",
    "ks:ks_alt_nam":"DEEPLING TE",
    "ks:ks_name":"Deepling Te",
    "ks:ks_pop":91,
    "ks:ks_type":"HABITATION",
    "ks:ks_uagg_main":0,
    "name:eng_x_preferred":[
        "Deepling Te"
    ],
    "wof:name":"Deepling Te",
    "wof:placetype":"neighbourhood",
    "wof:population":91
},
  "geometry": {"coordinates":[95.041426,27.114697],"type":"Point"}
}