{
  "type": "Feature",
  "properties": {
    "gn:admin1_code":"35.0",
    "gn:admin2_code":"437",
    "gn:asciiname":"Bikrampur",
    "gn:country_code":"IN",
    "gn:dem":359,
    "gn:feature_class":"P",
    "gn:feature_code":"PPL",
    "gn:name":"Bikrampur",
    "gn:population":0,
    "gn:timezone":"Asia/Kolkata",
    "iso:country":"IN",
    "name:ben_x_preferred":[
        "\u09ac\u09bf\u0995\u09cd\u09b0\u09ae\u09aa\u09c1\u09b0"
    ],
    "name:cat_x_preferred":[
        "Bikrampur"
    ],
    "name:epo_x_preferred":[
        "Bikrampur"
    ],
    "name:und_x_variant":[
        "Bikramp\u016br"
    ],
    "wof:name":"Bikrampur",
    "wof:placetype":"locality"
},
  "geometry": {"coordinates":[76.85654,22.75848],"type":"Point"}
}