{
  "type": "Feature",
  "properties": {
    "iso:country":"IN",
    "ks:ks_name":"Toskarwadi",
    "ks:ks_pop":157,
    "ks:ks_type":"HABITATION",
    "name:eng_x_preferred":[
        "Toskarwadi"
    ],
    "wof:name":"Toskarwadi",
    "wof:placetype":"locality",
    "wof:population":157
},
  "geometry": {"coordinates":[73.38204899999999,16.804354],"type":"Point"}
}