{
  "type": "Feature",
  "properties": {
    "iso:country":"IN",
    "ks:ks_name":"Naisaram Roaja Para",
    "ks:ks_pop":465,
    "ks:ks_type":"HABITATION",
    "name:eng_x_preferred":[
        "Naisaram Roaja Para"
    ],
    "wof:name":"Naisaram Roaja Para",
    "wof:placetype":"locality",
    "wof:population":465
},
  "geometry": {"coordinates":[92.070105,23.699886],"type":"Point"}
}