{
  "type": "Feature",
  "properties": {
    "iso:country":"IN",
    "ks:ks_name":"Kudumbala",
    "ks:ks_pop":2392,
    "ks:ks_type":"HABITATION",
    "name:eng_x_preferred":[
        "Kudumbala"
    ],
    "wof:name":"Kudumbala",
    "wof:placetype":"locality",
    "wof:population":2392
},
  "geometry": {"coordinates":[76.45498499999999,10.535608],"type":"Point"}
}