{
  "type": "Feature",
  "properties": {
    "iso:country":"IN",
    "ks:ks_name":"Udaiya Nagla",
    "ks:ks_pop":235,
    "ks:ks_type":"HABITATION",
    "name:eng_x_preferred":[
        "Udaiya Nagla"
    ],
    "wof:name":"Udaiya Nagla",
    "wof:placetype":"locality",
    "wof:population":235
},
  "geometry": {"coordinates":[79.228697,27.735515],"type":"Point"}
}