{
  "type": "Feature",
  "properties": {
    "iso:country":"IN",
    "ks:ks_name":"H Hosahalli",
    "ks:ks_pop":757,
    "ks:ks_type":"HABITATION",
    "name:eng_x_preferred":[
        "H Hosahalli"
    ],
    "wof:name":"H Hosahalli",
    "wof:placetype":"locality",
    "wof:population":757
},
  "geometry": {"coordinates":[77.100652,12.45956],"type":"Point"}
}