{
  "type": "Feature",
  "properties": {
    "iso:country":"IN",
    "ks:ks_name":"Buddhwadi",
    "ks:ks_pop":13,
    "ks:ks_type":"HABITATION",
    "name:eng_x_preferred":[
        "Buddhwadi"
    ],
    "wof:name":"Buddhwadi",
    "wof:placetype":"locality",
    "wof:population":13
},
  "geometry": {"coordinates":[73.672303,16.619953],"type":"Point"}
}