{
  "type": "Feature",
  "properties": {
    "iso:country":"IN",
    "ks:ks_name":"Kothapalle",
    "ks:ks_pop":9,
    "ks:ks_type":"HABITATION",
    "name:eng_x_preferred":[
        "Kothapalle"
    ],
    "wof:name":"Kothapalle",
    "wof:placetype":"locality",
    "wof:population":9
},
  "geometry": {"coordinates":[78.561351,13.854216],"type":"Point"}
}