{
  "type": "Feature",
  "properties": {
    "iso:country":"IN",
    "ks:ks_alt_nam":"Bunda pahar",
    "ks:ks_name":"Bunda Pahar",
    "ks:ks_pop":11,
    "ks:ks_type":"HABITATION",
    "name:eng_x_preferred":[
        "Bunda Pahar"
    ],
    "wof:name":"Bunda Pahar",
    "wof:placetype":"locality",
    "wof:population":11
},
  "geometry": {"coordinates":[87.615382,25.132036],"type":"Point"}
}