{
  "type": "Feature",
  "properties": {
    "gn:admin1_code":"36.0",
    "gn:admin2_code":"142.0",
    "gn:asciiname":"Azampur",
    "gn:country_code":"IN",
    "gn:dem":192,
    "gn:feature_class":"P",
    "gn:feature_code":"PPL",
    "gn:name":"\u0100zampur",
    "gn:population":0,
    "gn:timezone":"Asia/Kolkata",
    "iso:country":"IN",
    "name:ben_x_preferred":[
        "\u0986\u099c\u09ae\u09aa\u09c1\u09b0"
    ],
    "wof:name":"Azampur",
    "wof:placetype":"locality"
},
  "geometry": {"coordinates":[78.25758,28.39466],"type":"Point"}
}