{
  "type": "Feature",
  "properties": {
    "iso:country":"IN",
    "ks:ks_name":"Mahulpali",
    "ks:ks_pop":55,
    "ks:ks_type":"VILLAGE",
    "name:eng_x_preferred":[
        "Mahulpali"
    ],
    "wof:name":"Mahulpali",
    "wof:placetype":"locality",
    "wof:population":55
},
  "geometry": {"coordinates":[83.634677,20.644563],"type":"Point"}
}