{
  "type": "Feature",
  "properties": {
    "iso:country":"IN",
    "ks:ks_alt_nam":"Daledunga FV",
    "ks:ks_name":"Daledunga Fv",
    "ks:ks_pop":459,
    "ks:ks_type":"HABITATION",
    "name:eng_x_preferred":[
        "Daledunga Fv"
    ],
    "wof:name":"Daledunga Fv",
    "wof:placetype":"locality",
    "wof:population":459
},
  "geometry": {"coordinates":[91.35596099999999,25.955358],"type":"Point"}
}