{
  "type": "Feature",
  "properties": {
    "iso:country":"IN",
    "ks:ks_name":"Mohanpur",
    "ks:ks_pop":374,
    "ks:ks_type":"VILLAGE",
    "name:eng_x_preferred":[
        "Mohanpur"
    ],
    "wof:name":"Mohanpur",
    "wof:placetype":"locality",
    "wof:population":374
},
  "geometry": {"coordinates":[87.46342799999999,24.322431],"type":"Point"}
}