{
  "type": "Feature",
  "properties": {
    "iso:country":"IN",
    "ks:ks_alt_nam":"Vallanthode colony",
    "ks:ks_name":"Vallanthode Colony",
    "ks:ks_pop":458,
    "ks:ks_type":"HABITATION",
    "name:eng_x_preferred":[
        "Vallanthode Colony"
    ],
    "wof:name":"Vallanthode Colony",
    "wof:placetype":"locality",
    "wof:population":458
},
  "geometry": {"coordinates":[75.73903900000001,11.759413],"type":"Point"}
}