{
  "type": "Feature",
  "properties": {
    "iso:country":"IN",
    "ks:ks_name":"Janochiveri Falia",
    "ks:ks_pop":302,
    "ks:ks_type":"HABITATION",
    "name:eng_x_preferred":[
        "Janochiveri Falia"
    ],
    "wof:name":"Janochiveri Falia",
    "wof:placetype":"locality",
    "wof:population":302
},
  "geometry": {"coordinates":[73.17149999999999,20.23675],"type":"Point"}
}