{
  "type": "Feature",
  "properties": {
    "gn:admin1_code":"36",
    "gn:admin2_code":"135.0",
    "gn:asciiname":"Dhapura",
    "gn:country_code":"IN",
    "gn:dem":209,
    "gn:feature_class":"P",
    "gn:feature_code":"PPL",
    "gn:name":"Dh\u0101pura",
    "gn:population":0,
    "gn:timezone":"Asia/Kolkata",
    "iso:country":"IN",
    "ks:ks_alt_nam":"Dh\u0101pura",
    "ks:ks_name":"Dhapura",
    "ks:ks_type":"VILLAGE",
    "name:eng_x_preferred":[
        "Dhapura"
    ],
    "name:eng_x_variant":[
        "Dh\u0101pura"
    ],
    "wof:name":"Dhapura",
    "wof:placetype":"locality"
},
  "geometry": {"coordinates":[78.65724400000001,29.100023],"type":"Point"}
}