{
  "type": "Feature",
  "properties": {
    "iso:country":"IN",
    "ks:ks_name":"Virajina Chhapra",
    "ks:ks_pop":235,
    "ks:ks_type":"HABITATION",
    "name:eng_x_preferred":[
        "Virajina Chhapra"
    ],
    "wof:name":"Virajina Chhapra",
    "wof:placetype":"locality",
    "wof:population":235
},
  "geometry": {"coordinates":[72.85980600000001,23.069972],"type":"Point"}
}