{
  "type": "Feature",
  "properties": {
    "iso:country":"IN",
    "ks:ks_name":"Chak Lokya",
    "ks:ks_pop":120,
    "ks:ks_type":"HABITATION",
    "name:eng_x_preferred":[
        "Chak Lokya"
    ],
    "wof:name":"Chak Lokya",
    "wof:placetype":"locality",
    "wof:population":120
},
  "geometry": {"coordinates":[76.607792,25.276363],"type":"Point"}
}