{
  "type": "Feature",
  "properties": {
    "iso:country":"IN",
    "ks:ks_name":"Sunoli Talli",
    "ks:ks_pop":319,
    "ks:ks_type":"HABITATION",
    "name:eng_x_preferred":[
        "Sunoli Talli"
    ],
    "wof:name":"Sunoli Talli",
    "wof:placetype":"locality",
    "wof:population":319
},
  "geometry": {"coordinates":[79.435844,29.707131],"type":"Point"}
}