{
  "type": "Feature",
  "properties": {
    "gn:admin1_code":"39",
    "gn:admin2_code":"61.0",
    "gn:asciiname":"Chameli",
    "gn:country_code":"IN",
    "gn:dem":1113,
    "gn:feature_class":"P",
    "gn:feature_code":"PPL",
    "gn:name":"Chameli",
    "gn:population":0,
    "gn:timezone":"Asia/Kolkata",
    "iso:country":"IN",
    "ks:ks_name":"Chameli",
    "ks:ks_pop":41,
    "ks:ks_type":"VILLAGE",
    "name:ben_x_preferred":[
        "\u099a\u09be\u09ae\u09c7\u09b2\u09c0"
    ],
    "name:eng_x_preferred":[
        "Chameli"
    ],
    "wof:name":"Chameli",
    "wof:placetype":"locality",
    "wof:population":41
},
  "geometry": {"coordinates":[78.77194299999999,29.857209],"type":"Point"}
}