{
  "type": "Feature",
  "properties": {
    "gn:admin1_code":"38.0",
    "gn:admin2_code":"348.0",
    "gn:asciiname":"Nandodih",
    "gn:country_code":"IN",
    "gn:dem":363,
    "gn:feature_class":"P",
    "gn:feature_code":"PPL",
    "gn:name":"Nandodih",
    "gn:population":0,
    "gn:timezone":"Asia/Kolkata",
    "iso:country":"IN",
    "wof:name":"Nandodih",
    "wof:placetype":"locality"
},
  "geometry": {"coordinates":[85.72239999999999,24.33295],"type":"Point"}
}