{
  "type": "Feature",
  "properties": {
    "iso:country":"IN",
    "ks:ks_name":"Ghonsewadi",
    "ks:ks_pop":266,
    "ks:ks_type":"HABITATION",
    "name:eng_x_preferred":[
        "Ghonsewadi"
    ],
    "wof:name":"Ghonsewadi",
    "wof:placetype":"locality",
    "wof:population":266
},
  "geometry": {"coordinates":[73.75869400000001,15.789333],"type":"Point"}
}