{
  "type": "Feature",
  "properties": {
    "gn:admin1_code":"2.0",
    "gn:admin2_code":"551.0",
    "gn:asciiname":"Peddapalle",
    "gn:country_code":"IN",
    "gn:dem":409,
    "gn:feature_class":"P",
    "gn:feature_code":"PPL",
    "gn:name":"Peddapalle",
    "gn:population":0,
    "gn:timezone":"Asia/Kolkata",
    "iso:country":"IN",
    "name:pam_x_preferred":[
        "Peddapalle"
    ],
    "wof:name":"Peddapalle",
    "wof:placetype":"locality"
},
  "geometry": {"coordinates":[78.91003000000001,14.0495],"type":"Point"}
}