{
  "type": "Feature",
  "properties": {
    "iso:country":"IN",
    "ks:ks_name":"Bhimavaram",
    "ks:ks_pop":208,
    "ks:ks_type":"HABITATION",
    "name:eng_x_preferred":[
        "Bhimavaram"
    ],
    "name:hin_x_preferred":[
        "\u092d\u0940\u092e\u093e\u0935\u0930\u092e"
    ],
    "name:tel_x_preferred":[
        "\u0c2d\u0c40\u0c2e\u0c35\u0c30\u0c02"
    ],
    "name:urd_x_preferred":[
        "\u0628\u06be\u06cc\u0645\u0627\u0648\u0631\u0645"
    ],
    "wof:name":"Bhimavaram",
    "wof:placetype":"locality",
    "wof:population":208
},
  "geometry": {"coordinates":[83.904843,18.668604],"type":"Point"}
}