{
  "type": "Feature",
  "properties": {
    "iso:country":"IN",
    "ks:ks_name":"Bhimavaram",
    "ks:ks_pop":208,
    "ks:ks_type":"HABITATION",
    "name:eng_x_preferred":[
        "Bhimavaram"
    ],
    "wof:name":"Bhimavaram",
    "wof:placetype":"locality",
    "wof:population":208
},
  "geometry": {"coordinates":[83.904843,18.668604],"type":"Point"}
}