{
  "type": "Feature",
  "properties": {
    "gn:admin1_code":"19.0",
    "gn:admin2_code":"576.0",
    "gn:asciiname":"Gowdara Hitlu",
    "gn:country_code":"IN",
    "gn:dem":884,
    "gn:feature_class":"P",
    "gn:feature_code":"PPL",
    "gn:name":"Gowdara Hitlu",
    "gn:population":0,
    "gn:timezone":"Asia/Kolkata",
    "iso:country":"IN",
    "wof:name":"Gowdara Hitlu",
    "wof:placetype":"locality"
},
  "geometry": {"coordinates":[75.88993000000001,12.46812],"type":"Point"}
}