{
  "type": "Feature",
  "properties": {
    "iso:country":"IN",
    "ks:ks_alt_nam":"wabalevasti salunkhevasti",
    "ks:ks_name":"Wabalevasti Salunkhevasti",
    "ks:ks_pop":89,
    "ks:ks_type":"HABITATION",
    "name:eng_x_preferred":[
        "Wabalevasti Salunkhevasti"
    ],
    "wof:name":"Wabalevasti Salunkhevasti",
    "wof:placetype":"locality",
    "wof:population":89
},
  "geometry": {"coordinates":[74.4318,18.2652],"type":"Point"}
}