{
  "type": "Feature",
  "properties": {
    "gn:admin1_code":"36",
    "gn:admin2_code":"188.0",
    "gn:asciiname":"Bhatiari",
    "gn:country_code":"IN",
    "gn:dem":85,
    "gn:feature_class":"P",
    "gn:feature_code":"PPL",
    "gn:name":"Bhati\u0101ri",
    "gn:population":0,
    "gn:timezone":"Asia/Kolkata",
    "iso:country":"IN",
    "name:ben_x_preferred":[
        "\u09ad\u09be\u099f\u09bf\u09af\u09bc\u09be\u09b0\u09c0"
    ],
    "wof:name":"Bhatiari",
    "wof:placetype":"neighbourhood"
},
  "geometry": {"coordinates":[83.20631,26.59159],"type":"Point"}
}