{
  "type": "Feature",
  "properties": {
    "iso:country":"IN",
    "ks:ks_name":"Kanersingha",
    "ks:ks_pop":378,
    "ks:ks_type":"VILLAGE",
    "name:eng_x_preferred":[
        "Kanersingha"
    ],
    "wof:name":"Kanersingha",
    "wof:placetype":"locality",
    "wof:population":378
},
  "geometry": {"coordinates":[83.644682,20.426953],"type":"Point"}
}