{
  "type": "Feature",
  "properties": {
    "iso:country":"IN",
    "ks:ks_name":"Gaurkha",
    "ks:ks_pop":375,
    "ks:ks_type":"HABITATION",
    "name:eng_x_preferred":[
        "Gaurkha"
    ],
    "wof:name":"Gaurkha",
    "wof:placetype":"locality",
    "wof:population":375
},
  "geometry": {"coordinates":[80.652782,27.49788],"type":"Point"}
}