{
  "type": "Feature",
  "properties": {
    "iso:country":"IN",
    "ks:ks_alt_nam":"CHAMAR TOLA",
    "ks:ks_name":"Chamar Tola",
    "ks:ks_pop":119,
    "ks:ks_type":"HABITATION",
    "name:eng_x_preferred":[
        "Chamar Tola"
    ],
    "wof:name":"Chamar Tola",
    "wof:placetype":"locality",
    "wof:population":119
},
  "geometry": {"coordinates":[86.51961799999999,26.174793],"type":"Point"}
}