{
  "type": "Feature",
  "properties": {
    "gn:admin1_code":"36.0",
    "gn:admin2_code":"179",
    "gn:asciiname":"Keoripur",
    "gn:country_code":"IN",
    "gn:dem":92,
    "gn:feature_class":"P",
    "gn:feature_code":"PPL",
    "gn:name":"Keoripur",
    "gn:population":0,
    "gn:timezone":"Asia/Kolkata",
    "iso:country":"IN",
    "wof:name":"Keoripur",
    "wof:placetype":"locality"
},
  "geometry": {"coordinates":[82.34170999999998,26.02957],"type":"Point"}
}