{
  "type": "Feature",
  "properties": {
    "iso:country":"IN",
    "ks:ks_name":"Sukhesh",
    "ks:ks_pop":4723,
    "ks:ks_type":"VILLAGE",
    "name:eng_x_preferred":[
        "Sukhesh"
    ],
    "wof:name":"Sukhesh",
    "wof:placetype":"locality",
    "wof:population":4723
},
  "geometry": {"coordinates":[73.006681,20.49684],"type":"Point"}
}