{
  "type": "Feature",
  "properties": {
    "gn:admin1_code":"12.0",
    "gn:admin2_code":"021",
    "gn:asciiname":"Bhalwal Molu",
    "gn:country_code":"IN",
    "gn:dem":265,
    "gn:feature_class":"P",
    "gn:feature_code":"PPL",
    "gn:name":"Bhalw\u0101l Molu",
    "gn:population":0,
    "gn:timezone":"Asia/Kolkata",
    "iso:country":"IN",
    "name:und_x_variant":[
        "Bhalw\u0101l Molu",
        "Bhaiw\u0101l Molu"
    ],
    "wof:name":"Bhalwal Molu",
    "wof:placetype":"locality"
},
  "geometry": {"coordinates":[74.61075,32.78335999999999],"type":"Point"}
}