{
  "type": "Feature",
  "properties": {
    "gn:admin1_code":"21",
    "gn:admin2_code":"398.0",
    "gn:asciiname":"Sidumetta",
    "gn:country_code":"IN",
    "gn:dem":1021,
    "gn:feature_class":"P",
    "gn:feature_code":"PPL",
    "gn:name":"S\u012bdumetta",
    "gn:population":0,
    "gn:timezone":"Asia/Kolkata",
    "iso:country":"IN",
    "wof:name":"Sidumetta",
    "wof:placetype":"locality"
},
  "geometry": {"coordinates":[82.95426999999999,18.45595],"type":"Point"}
}