{
  "type": "Feature",
  "properties": {
    "iso:country":"IN",
    "ks:ks_alt_nam":"SARAIYA",
    "ks:ks_name":"Saraiya",
    "ks:ks_pop":191,
    "ks:ks_type":"HABITATION",
    "name:eng_x_preferred":[
        "Saraiya"
    ],
    "wof:name":"Saraiya",
    "wof:placetype":"locality",
    "wof:population":191
},
  "geometry": {"coordinates":[82.096283,26.375717],"type":"Point"}
}