{
  "type": "Feature",
  "properties": {
    "gn:admin1_code":"24.0",
    "gn:admin2_code":"123.0",
    "gn:asciiname":"Jaitakhera",
    "gn:country_code":"IN",
    "gn:dem":527,
    "gn:feature_class":"P",
    "gn:feature_code":"PPL",
    "gn:name":"Jait\u0101khera",
    "gn:population":0,
    "gn:timezone":"Asia/Kolkata",
    "iso:country":"IN",
    "ks:ks_name":"Jeta Khera",
    "ks:ks_pop":817,
    "ks:ks_type":"VILLAGE",
    "name:eng_x_preferred":[
        "Jeta Khera"
    ],
    "name:eng_x_variant":[
        "Jaitakhera"
    ],
    "wof:name":"Jeta Khera",
    "wof:placetype":"locality",
    "wof:population":817
},
  "geometry": {"coordinates":[74.299778,25.947406],"type":"Point"}
}