{
  "type": "Feature",
  "properties": {
    "iso:country":"IN",
    "ks:ks_alt_nam":"Gotake  nagari",
    "ks:ks_name":"Gotake Nagari",
    "ks:ks_pop":35,
    "ks:ks_type":"HABITATION",
    "name:eng_x_preferred":[
        "Gotake Nagari"
    ],
    "name:eng_x_variant":[
        "Gotake  nagari"
    ],
    "wof:name":"Gotake Nagari",
    "wof:placetype":"locality",
    "wof:population":35
},
  "geometry": {"coordinates":[74.33042500000001,15.387418],"type":"Point"}
}