{
  "type": "Feature",
  "properties": {
    "iso:country":"IN",
    "ks:ks_name":"Purunapani",
    "ks:ks_pop":369,
    "ks:ks_type":"VILLAGE",
    "name:eng_x_preferred":[
        "Purunapani"
    ],
    "wof:name":"Purunapani",
    "wof:placetype":"locality",
    "wof:population":369
},
  "geometry": {"coordinates":[86.613446,21.712687],"type":"Point"}
}