{
  "type": "Feature",
  "properties": {
    "iso:country":"IN",
    "ks:ks_name":"Udalpura",
    "ks:ks_pop":667,
    "ks:ks_type":"HABITATION",
    "name:eng_x_preferred":[
        "Udalpura"
    ],
    "wof:name":"Udalpura",
    "wof:placetype":"locality",
    "wof:population":667
},
  "geometry": {"coordinates":[74.548506,25.608606],"type":"Point"}
}