{
  "type": "Feature",
  "properties": {
    "iso:country":"IN",
    "ks:ks_name":"Shakti Nagar",
    "ks:ks_pop":176,
    "ks:ks_type":"HABITATION",
    "name:eng_x_preferred":[
        "Shakti Nagar"
    ],
    "wof:name":"Shakti Nagar",
    "wof:placetype":"locality",
    "wof:population":176
},
  "geometry": {"coordinates":[71.33427500000001,24.876936],"type":"Point"}
}