{
  "type": "Feature",
  "properties": {
    "gn:admin1_code":"38.0",
    "gn:admin2_code":"347.0",
    "gn:asciiname":"Kachanpur",
    "gn:country_code":"IN",
    "gn:dem":405,
    "gn:feature_class":"P",
    "gn:feature_code":"PPL",
    "gn:name":"Kachanpur",
    "gn:population":0,
    "gn:timezone":"Asia/Kolkata",
    "iso:country":"IN",
    "ks:ks_name":"Kanchanpur",
    "ks:ks_pop":262,
    "ks:ks_type":"VILLAGE",
    "name:eng_x_preferred":[
        "Kanchanpur"
    ],
    "name:eng_x_variant":[
        "Kachanpur"
    ],
    "wof:name":"Kanchanpur",
    "wof:placetype":"locality",
    "wof:population":262
},
  "geometry": {"coordinates":[85.301751,24.31137],"type":"Point"}
}