{
  "type": "Feature",
  "properties": {
    "gn:admin1_code":"38.0",
    "gn:admin2_code":"358.0",
    "gn:asciiname":"Korami",
    "gn:country_code":"IN",
    "gn:dem":267,
    "gn:feature_class":"P",
    "gn:feature_code":"PPL",
    "gn:name":"Kor\u0101m\u012b",
    "gn:population":0,
    "gn:timezone":"Asia/Kolkata",
    "iso:country":"IN",
    "ks:ks_alt_nam":"Kor\u0101m\u012b",
    "ks:ks_name":"Korami",
    "ks:ks_pop":707,
    "ks:ks_type":"VILLAGE",
    "ks:ks_uagg_main":0,
    "name:eng_x_preferred":[
        "Korami"
    ],
    "name:eng_x_variant":[
        "Kor\u0101m\u012b"
    ],
    "wof:name":"Korami",
    "wof:placetype":"neighbourhood",
    "wof:population":707
},
  "geometry": {"coordinates":[84.299494,24.352602],"type":"Point"}
}