{
  "type": "Feature",
  "properties": {
    "gn:admin1_code":"10.0",
    "gn:admin2_code":"76.0",
    "gn:asciiname":"Reoli",
    "gn:country_code":"IN",
    "gn:dem":219,
    "gn:feature_class":"P",
    "gn:feature_code":"PPL",
    "gn:name":"Reoli",
    "gn:population":0,
    "gn:timezone":"Asia/Kolkata",
    "iso:country":"IN",
    "ks:ks_name":"Revli",
    "ks:ks_pop":2284,
    "ks:ks_type":"VILLAGE",
    "ks:ks_uagg_main":0,
    "name:eng_x_preferred":[
        "Revli"
    ],
    "name:und_x_variant":[
        "Riwali"
    ],
    "wof:name":"Revli",
    "wof:placetype":"neighbourhood",
    "wof:population":2284
},
  "geometry": {"coordinates":[77.063333,29.009402],"type":"Point"}
}