{
  "type": "Feature",
  "properties": {
    "gn:admin1_code":"35",
    "gn:admin2_code":"443.0",
    "gn:asciiname":"Isagarh",
    "gn:country_code":"IN",
    "gn:dem":530,
    "gn:feature_class":"P",
    "gn:feature_code":"PPL",
    "gn:name":"Is\u0101garh",
    "gn:population":0,
    "gn:timezone":"Asia/Kolkata",
    "iso:country":"IN",
    "ks:ks_name":"Esagarh",
    "ks:ks_pop":718,
    "ks:ks_type":"VILLAGE",
    "name:ben_x_preferred":[
        "\u0987\u09b8\u0997\u09a1\u09bc"
    ],
    "name:bpy_x_preferred":[
        "\u0987\u09b8\u0997\u09a1\u09bc"
    ],
    "name:ceb_x_preferred":[
        "Is\u0101garh"
    ],
    "name:eng_x_preferred":[
        "Esagarh"
    ],
    "name:eng_x_variant":[
        "Isagarh"
    ],
    "name:hin_x_preferred":[
        "\u0908\u0938\u093e\u0917\u0922\u093c"
    ],
    "name:ita_x_preferred":[
        "Isagarh"
    ],
    "name:msa_x_preferred":[
        "Isagarh"
    ],
    "name:new_x_preferred":[
        "\u0907\u0938\u093e\u0917\u0922"
    ],
    "name:nld_x_preferred":[
        "Isagarh"
    ],
    "name:por_x_preferred":[
        "Isagarh"
    ],
    "name:swe_x_preferred":[
        "Is\u0101garh"
    ],
    "name:vie_x_preferred":[
        "Isagarh"
    ],
    "name:zho_x_preferred":[
        "\u4f0a\u8428\u52a0\u5c14"
    ],
    "wof:name":"Esagarh",
    "wof:placetype":"locality",
    "wof:population":718
},
  "geometry": {"coordinates":[77.375787,24.134165],"type":"Point"}
}