{
  "type": "Feature",
  "properties": {
    "gn:admin1_code":"35",
    "gn:admin2_code":"456.0",
    "gn:asciiname":"Kopijhola",
    "gn:country_code":"IN",
    "gn:dem":374,
    "gn:feature_class":"P",
    "gn:feature_code":"PPL",
    "gn:name":"Kop\u012bjhola",
    "gn:population":0,
    "gn:timezone":"Asia/Kolkata",
    "iso:country":"IN",
    "ks:ks_alt_nam":"Kop\u012bjhola",
    "ks:ks_name":"Kopijhola",
    "ks:ks_pop":493,
    "ks:ks_type":"VILLAGE",
    "name:eng_x_preferred":[
        "Kopijhola"
    ],
    "name:eng_x_variant":[
        "Kop\u012bjhola"
    ],
    "wof:name":"Kopijhola",
    "wof:placetype":"locality",
    "wof:population":493
},
  "geometry": {"coordinates":[79.902969,22.176295],"type":"Point"}
}