{
  "type": "Feature",
  "properties": {
    "iso:country":"IN",
    "ks:ks_name":"Sharkaj Nahar Pakki",
    "ks:ks_pop":164,
    "ks:ks_type":"VILLAGE",
    "name:eng_x_preferred":[
        "Sharkaj Nahar Pakki"
    ],
    "wof:name":"Sharkaj Nahar Pakki",
    "wof:placetype":"locality",
    "wof:population":164
},
  "geometry": {"coordinates":[73.963425,30.117673],"type":"Point"}
}