{
  "type": "Feature",
  "properties": {
    "gn:admin1_code":"39.0",
    "gn:admin2_code":"64.0",
    "gn:asciiname":"Bhulbagar",
    "gn:country_code":"IN",
    "gn:dem":1482,
    "gn:feature_class":"P",
    "gn:feature_code":"PPL",
    "gn:name":"Bh\u016blbagar",
    "gn:population":0,
    "gn:timezone":"Asia/Kolkata",
    "iso:country":"IN",
    "ks:ks_alt_nam":"Bh\u016blbagar",
    "ks:ks_name":"Bhulbagar",
    "ks:ks_pop":236,
    "ks:ks_type":"VILLAGE",
    "name:eng_x_preferred":[
        "Bhulbagar"
    ],
    "name:eng_x_variant":[
        "Bh\u016blbagar"
    ],
    "wof:name":"Bhulbagar",
    "wof:placetype":"locality",
    "wof:population":236
},
  "geometry": {"coordinates":[79.174053,29.747092],"type":"Point"}
}