{
  "type": "Feature",
  "properties": {
    "gn:admin1_code":"40",
    "gn:admin2_code":"541.0",
    "gn:asciiname":"Hydershahipet",
    "gn:country_code":"IN",
    "gn:dem":157,
    "gn:feature_class":"P",
    "gn:feature_code":"PPL",
    "gn:name":"Hydersh\u0101hipet",
    "gn:population":0,
    "gn:timezone":"Asia/Kolkata",
    "iso:country":"IN",
    "name:eng_x_preferred":[
        "Hydersh\u0101hipet"
    ],
    "wof:name":"Hydershahipet",
    "wof:placetype":"locality"
},
  "geometry": {"coordinates":[79.98142,17.38945],"type":"Point"}
}