{
  "type": "Feature",
  "properties": {
    "iso:country":"IN",
    "ks:ks_name":"Mathia Tola",
    "ks:ks_pop":690,
    "ks:ks_type":"HABITATION",
    "name:eng_x_preferred":[
        "Mathia Tola"
    ],
    "wof:name":"Mathia Tola",
    "wof:placetype":"locality",
    "wof:population":690
},
  "geometry": {"coordinates":[84.310478,26.276991],"type":"Point"}
}