{
  "type": "Feature",
  "properties": {
    "gn:admin1_code":"2",
    "gn:admin2_code":"544.0",
    "gn:asciiname":"Rajakoduru",
    "gn:country_code":"IN",
    "gn:dem":17,
    "gn:feature_class":"P",
    "gn:feature_code":"PPL",
    "gn:name":"R\u0101jakod\u016bru",
    "gn:population":0,
    "gn:timezone":"Asia/Kolkata",
    "iso:country":"IN",
    "wof:name":"Rajakoduru",
    "wof:placetype":"locality"
},
  "geometry": {"coordinates":[82.93025,17.51197],"type":"Point"}
}