{
  "type": "Feature",
  "properties": {
    "iso:country":"IN",
    "ks:ks_alt_nam":"datta wasti",
    "ks:ks_name":"Datta Wasti",
    "ks:ks_pop":110,
    "ks:ks_type":"HABITATION",
    "name:eng_x_preferred":[
        "Datta Wasti"
    ],
    "wof:name":"Datta Wasti",
    "wof:placetype":"locality",
    "wof:population":110
},
  "geometry": {"coordinates":[75.900448,18.751501],"type":"Point"}
}