{
  "type": "Feature",
  "properties": {
    "iso:country":"IN",
    "ks:ks_name":"Kamarda",
    "ks:ks_pop":1110,
    "ks:ks_type":"VILLAGE",
    "ks:ks_uagg_main":0,
    "name:eng_x_preferred":[
        "Kamarda"
    ],
    "wof:name":"Kamarda",
    "wof:placetype":"neighbourhood",
    "wof:population":1110
},
  "geometry": {"coordinates":[87.734684,21.865571],"type":"Point"}
}