{
  "type": "Feature",
  "properties": {
    "iso:country":"IN",
    "ks:ks_name":"Araji Mafi Kaithauli",
    "ks:ks_pop":0,
    "ks:ks_type":"VILLAGE",
    "name:eng_x_preferred":[
        "Araji Mafi Kaithauli"
    ],
    "wof:name":"Araji Mafi Kaithauli",
    "wof:placetype":"locality",
    "wof:population":0
},
  "geometry": {"coordinates":[83.984353,25.70761],"type":"Point"}
}