{
  "type": "Feature",
  "properties": {
    "iso:country":"IN",
    "ks:ks_name":"Kaluchak",
    "ks:ks_pop":123,
    "ks:ks_type":"VILLAGE",
    "name:eng_x_preferred":[
        "Kaluchak"
    ],
    "wof:name":"Kaluchak",
    "wof:placetype":"locality",
    "wof:population":123
},
  "geometry": {"coordinates":[87.507458,22.411335],"type":"Point"}
}