{
  "type": "Feature",
  "properties": {
    "iso:country":"IN",
    "ks:ks_name":"Darlipada",
    "ks:ks_pop":305,
    "ks:ks_type":"HABITATION",
    "name:eng_x_preferred":[
        "Darlipada"
    ],
    "wof:name":"Darlipada",
    "wof:placetype":"locality",
    "wof:population":305
},
  "geometry": {"coordinates":[82.785088,19.919057],"type":"Point"}
}