{
  "type": "Feature",
  "properties": {
    "iso:country":"IN",
    "ks:ks_name":"4 KKSM",
    "ks:ks_pop":58,
    "ks:ks_type":"VILLAGE",
    "name:eng_x_preferred":[
        "4 KKSM"
    ],
    "wof:name":"4 KKSM",
    "wof:placetype":"locality",
    "wof:population":58
},
  "geometry": {"coordinates":[74.409938,29.09374],"type":"Point"}
}