{
  "type": "Feature",
  "properties": {
    "iso:country":"IN",
    "ks:ks_name":"Taparkela Sarnapara",
    "ks:ks_pop":488,
    "ks:ks_type":"HABITATION",
    "name:eng_x_preferred":[
        "Taparkela Sarnapara"
    ],
    "wof:name":"Taparkela Sarnapara",
    "wof:placetype":"locality",
    "wof:population":488
},
  "geometry": {"coordinates":[83.276011,22.984101],"type":"Point"}
}