{
  "type": "Feature",
  "properties": {
    "iso:country":"IN",
    "ks:ks_alt_nam":"Lakhan  tola",
    "ks:ks_name":"Lakhan Tola",
    "ks:ks_pop":1306,
    "ks:ks_type":"HABITATION",
    "name:eng_x_preferred":[
        "Lakhan Tola"
    ],
    "name:eng_x_variant":[
        "Lakhan  tola"
    ],
    "wof:name":"Lakhan Tola",
    "wof:placetype":"locality",
    "wof:population":1306
},
  "geometry": {"coordinates":[87.046108,25.609482],"type":"Point"}
}