{
  "type": "Feature",
  "properties": {
    "gn:admin1_code":"12.0",
    "gn:admin2_code":"19.0",
    "gn:asciiname":"Rinlu",
    "gn:country_code":"IN",
    "gn:dem":2458,
    "gn:feature_class":"P",
    "gn:feature_code":"PPL",
    "gn:name":"Rinlu",
    "gn:population":0,
    "gn:timezone":"Asia/Kolkata",
    "iso:country":"IN",
    "wof:name":"Rinlu",
    "wof:placetype":"locality"
},
  "geometry": {"coordinates":[75.58303000000002,32.74508],"type":"Point"}
}