{
  "type": "Feature",
  "properties": {
    "gn:admin1_code":"9.0",
    "gn:admin2_code":"471.0",
    "gn:asciiname":"Wajapur",
    "gn:country_code":"IN",
    "gn:dem":211,
    "gn:feature_class":"P",
    "gn:feature_code":"PPL",
    "gn:name":"Waj\u0101pur",
    "gn:population":0,
    "gn:timezone":"Asia/Kolkata",
    "iso:country":"IN",
    "wof:name":"Wajapur",
    "wof:placetype":"locality"
},
  "geometry": {"coordinates":[72.78019999999999,24.0779],"type":"Point"}
}