{
  "type": "Feature",
  "properties": {
    "iso:country":"IN",
    "ks:ks_name":"Harijan Basti",
    "ks:ks_pop":128,
    "ks:ks_type":"HABITATION",
    "name:eng_x_preferred":[
        "Harijan Basti"
    ],
    "wof:name":"Harijan Basti",
    "wof:placetype":"locality",
    "wof:population":128
},
  "geometry": {"coordinates":[83.698025,27.128496],"type":"Point"}
}