{
  "type": "Feature",
  "properties": {
    "iso:country":"IN",
    "ks:ks_name":"Baghadafa",
    "ks:ks_pop":0,
    "ks:ks_type":"VILLAGE",
    "name:eng_x_preferred":[
        "Baghadafa"
    ],
    "wof:name":"Baghadafa",
    "wof:placetype":"locality",
    "wof:population":0
},
  "geometry": {"coordinates":[86.193201,21.397851],"type":"Point"}
}