{
  "type": "Feature",
  "properties": {
    "gn:admin1_code":"19.0",
    "gn:admin2_code":"573.0",
    "gn:asciiname":"Yagatihallikoppal",
    "gn:country_code":"IN",
    "gn:dem":775,
    "gn:feature_class":"P",
    "gn:feature_code":"PPL",
    "gn:name":"Yagatihallikoppal",
    "gn:population":0,
    "gn:timezone":"Asia/Kolkata",
    "iso:country":"IN",
    "wof:name":"Yagatihallikoppal",
    "wof:placetype":"locality"
},
  "geometry": {"coordinates":[76.79335,12.89131],"type":"Point"}
}