{
  "type": "Feature",
  "properties": {
    "iso:country":"IN",
    "ks:ks_name":"Talagihal",
    "ks:ks_pop":407,
    "ks:ks_type":"VILLAGE",
    "name:eng_x_preferred":[
        "Talagihal"
    ],
    "wof:name":"Talagihal",
    "wof:placetype":"locality",
    "wof:population":407
},
  "geometry": {"coordinates":[75.768478,16.292579],"type":"Point"}
}