{
  "type": "Feature",
  "properties": {
    "iso:country":"IN",
    "ks:ks_name":"Kudopi",
    "ks:ks_pop":359,
    "ks:ks_type":"VILLAGE",
    "name:eng_x_preferred":[
        "Kudopi"
    ],
    "wof:name":"Kudopi",
    "wof:placetype":"locality",
    "wof:population":359
},
  "geometry": {"coordinates":[73.51644899999999,16.267377],"type":"Point"}
}