{
  "type": "Feature",
  "properties": {
    "iso:country":"IN",
    "ks:ks_name":"Budachikoppa",
    "ks:ks_pop":42,
    "ks:ks_type":"HABITATION",
    "name:eng_x_preferred":[
        "Budachikoppa"
    ],
    "wof:name":"Budachikoppa",
    "wof:placetype":"locality",
    "wof:population":42
},
  "geometry": {"coordinates":[75.16821899999999,13.484145],"type":"Point"}
}