{
  "type": "Feature",
  "properties": {
    "iso:country":"IN",
    "ks:ks_name":"Sullemane",
    "ks:ks_pop":36,
    "ks:ks_type":"HABITATION",
    "name:eng_x_preferred":[
        "Sullemane"
    ],
    "wof:name":"Sullemane",
    "wof:placetype":"locality",
    "wof:population":36
},
  "geometry": {"coordinates":[74.831807,13.682797],"type":"Point"}
}