{
  "type": "Feature",
  "properties": {
    "iso:country":"IN",
    "ks:ks_name":"Sadatpur",
    "ks:ks_pop":2572,
    "ks:ks_type":"VILLAGE",
    "ks:ks_uagg_main":0,
    "name:eng_x_preferred":[
        "Sadatpur"
    ],
    "wof:name":"Sadatpur",
    "wof:placetype":"locality",
    "wof:population":2572
},
  "geometry": {"coordinates":[87.25963,22.343991],"type":"Point"}
}