{
  "type": "Feature",
  "properties": {
    "iso:country":"IN",
    "ks:ks_name":"Abdulanagar",
    "ks:ks_pop":350,
    "ks:ks_type":"VILLAGE",
    "name:eng_x_preferred":[
        "Abdulanagar"
    ],
    "wof:name":"Abdulanagar",
    "wof:placetype":"locality",
    "wof:population":350
},
  "geometry": {"coordinates":[86.771997,21.387501],"type":"Point"}
}