{
  "type": "Feature",
  "properties": {
    "iso:country":"IN",
    "ks:ks_alt_nam":"Nari\u0101w\u0101l",
    "ks:ks_name":"Nariawal",
    "ks:ks_type":"VILLAGE",
    "name:eng_x_preferred":[
        "Nariawal"
    ],
    "name:eng_x_variant":[
        "Nari\u0101w\u0101l"
    ],
    "wof:name":"Nariawal",
    "wof:placetype":"locality"
},
  "geometry": {"coordinates":[79.480282,28.317907],"type":"Point"}
}