{
  "type": "Feature",
  "properties": {
    "gn:admin1_code":"12.0",
    "gn:admin2_code":"022",
    "gn:asciiname":"Chak Gaurean",
    "gn:country_code":"IN",
    "gn:dem":304,
    "gn:feature_class":"P",
    "gn:feature_code":"PPL",
    "gn:name":"Chak Gaure\u0101n",
    "gn:population":0,
    "gn:timezone":"Asia/Kolkata",
    "iso:country":"IN",
    "name:und_x_variant":[
        "Chak Gaure\u0101n",
        "Chak Gur\u0101n"
    ],
    "wof:name":"Chak Gaurean",
    "wof:placetype":"locality"
},
  "geometry": {"coordinates":[74.93236999999998,32.54602],"type":"Point"}
}