{
  "type": "Feature",
  "properties": {
    "gn:admin1_code":"34.0",
    "gn:admin2_code":"223.0",
    "gn:asciiname":"Chatra",
    "gn:country_code":"IN",
    "gn:dem":42,
    "gn:feature_class":"P",
    "gn:feature_code":"PPL",
    "gn:name":"Chatra",
    "gn:population":0,
    "gn:timezone":"Asia/Kolkata",
    "iso:country":"IN",
    "name:ara_x_preferred":[
        "\u062a\u0634\u0627\u062a\u0631\u0627"
    ],
    "name:ben_bn_x_preferred":[
        "\u099b\u09be\u09a4\u09cd\u09b0\u09be"
    ],
    "name:ben_in_x_preferred":[
        "\u099b\u09be\u09a4\u09cd\u09b0\u09be"
    ],
    "name:guj_x_preferred":[
        "\u0a9b\u0abe\u0aa4\u0acd\u0ab0\u0abe"
    ],
    "name:hin_x_preferred":[
        "\u091a\u0924\u094d\u0930\u093e"
    ],
    "name:kan_x_preferred":[
        "\u0c9b\u0cbe\u0ca4\u0ccd\u0cb0\u0cbe"
    ],
    "name:mal_x_preferred":[
        "\u0d1a\u0d24\u0d4d\u0d30"
    ],
    "name:mar_x_preferred":[
        "\u091a\u0924\u094d\u0930\u093e"
    ],
    "name:pan_x_preferred":[
        "\u0a1a\u0a24\u0a30\u0a3e"
    ],
    "name:tam_x_preferred":[
        "\u0b9a\u0ba4\u0bcd\u0bb0\u0bbe"
    ],
    "name:tel_x_preferred":[
        "\u0c1a\u0c24\u0c4d\u0c30\u0c3e"
    ],
    "name:urd_x_preferred":[
        "\u0686\u062a\u0631\u0627"
    ],
    "wof:name":"Chatra",
    "wof:placetype":"neighbourhood"
},
  "geometry": {"coordinates":[86.52791999999999,25.52001],"type":"Point"}
}