{
  "type": "Feature",
  "properties": {
    "iso:country":"IN",
    "ks:ks_name":"Chavarukonam",
    "ks:ks_pop":524,
    "ks:ks_type":"HABITATION",
    "name:eng_x_preferred":[
        "Chavarukonam"
    ],
    "wof:name":"Chavarukonam",
    "wof:placetype":"locality",
    "wof:population":524
},
  "geometry": {"coordinates":[76.81849,8.931251],"type":"Point"}
}