{
  "type": "Feature",
  "properties": {
    "iso:country":"IN",
    "ks:ks_name":"Nekurseni",
    "ks:ks_pop":519,
    "ks:ks_type":"HABITATION",
    "name:eng_x_preferred":[
        "Nekurseni"
    ],
    "wof:name":"Nekurseni",
    "wof:placetype":"locality",
    "wof:population":519
},
  "geometry": {"coordinates":[87.279032,22.016564],"type":"Point"}
}