{
  "type": "Feature",
  "properties": {
    "gn:admin1_code":"12.0",
    "gn:admin2_code":"5.0",
    "gn:asciiname":"Dumka",
    "gn:country_code":"IN",
    "gn:dem":1629,
    "gn:feature_class":"P",
    "gn:feature_code":"PPL",
    "gn:name":"Dumka",
    "gn:population":0,
    "gn:timezone":"Asia/Kolkata",
    "iso:country":"IN",
    "name:ara_x_preferred":[
        "\u062f\u0648\u0645\u0643\u0627"
    ],
    "name:ben_bn_x_preferred":[
        "\u09a6\u09c1\u09ae\u0995\u09be"
    ],
    "name:ben_in_x_preferred":[
        "\u09a6\u09c1\u09ae\u0995\u09be"
    ],
    "name:bih_x_preferred":[
        "\u0926\u0941\u092e\u0915\u093e"
    ],
    "name:bpy_x_preferred":[
        "\u09a6\u09c1\u09ae\u0995\u09be"
    ],
    "name:ceb_x_preferred":[
        "Dumka"
    ],
    "name:fra_x_preferred":[
        "Dumka"
    ],
    "name:guj_x_preferred":[
        "\u0aa1\u0ac1\u0aae\u0a95\u0abe"
    ],
    "name:hin_x_preferred":[
        "\u0926\u0941\u092e\u0915\u093e"
    ],
    "name:ita_x_preferred":[
        "Dumka"
    ],
    "name:kan_x_preferred":[
        "\u0ca1\u0cc1\u0cae\u0ccd\u0c95\u0cbe"
    ],
    "name:mai_x_preferred":[
        "\u0926\u0941\u092e\u0915\u093e"
    ],
    "name:mal_x_preferred":[
        "\u0d21\u0d41\u0d02\u0d15"
    ],
    "name:mar_x_preferred":[
        "\u0926\u0941\u092e\u0915\u093e"
    ],
    "name:mar_x_variant":[
        "\u0921\u0941\u092e\u0915\u093e"
    ],
    "name:mlg_x_preferred":[
        "Dumka"
    ],
    "name:msa_x_preferred":[
        "Dumka"
    ],
    "name:nep_x_preferred":[
        "\u0926\u0941\u092e\u0915\u093e"
    ],
    "name:new_x_preferred":[
        "\u0926\u0941\u092e\u094d\u0915\u093e"
    ],
    "name:nor_x_preferred":[
        "Dumka"
    ],
    "name:ori_x_preferred":[
        "\u0b21\u0b41\u0b2e\u0b15\u0b3e"
    ],
    "name:pan_x_preferred":[
        "\u0a21\u0a41\u0a2e\u0a15\u0a3e"
    ],
    "name:pnb_x_preferred":[
        "\u062f\u0645\u06a9\u0627"
    ],
    "name:san_x_preferred":[
        "\u0926\u0941\u092e\u0915\u093e"
    ],
    "name:sat_x_preferred":[
        "\u1c6b\u1c69\u1c62\u1c60\u1c5f"
    ],
    "name:spa_x_preferred":[
        "Dumka"
    ],
    "name:swe_x_preferred":[
        "Dumka"
    ],
    "name:tam_x_preferred":[
        "\u0b9f\u0bc1\u0bae\u0bcd\u0b95\u0bbe"
    ],
    "name:tel_x_preferred":[
        "\u0c21\u0c41\u0c2e\u0c4d\u0c15\u0c3e"
    ],
    "name:urd_x_preferred":[
        "\u062f\u0645\u06a9\u0627"
    ],
    "name:vie_x_preferred":[
        "Dumka"
    ],
    "name:zho_x_preferred":[
        "\u675c\u59c6\u5361"
    ],
    "wof:name":"Dumka",
    "wof:placetype":"locality"
},
  "geometry": {"coordinates":[74.20049,33.48244],"type":"Point"}
}