{
  "type": "Feature",
  "properties": {
    "iso:country":"IN",
    "ks:ks_name":"Patol",
    "ks:ks_pop":309,
    "ks:ks_type":"VILLAGE",
    "ks:ks_uagg_main":0,
    "name:eng_x_preferred":[
        "Patol"
    ],
    "wof:name":"Patol",
    "wof:placetype":"neighbourhood",
    "wof:population":309
},
  "geometry": {"coordinates":[88.202134,25.712197],"type":"Point"}
}