{
  "type": "Feature",
  "properties": {
    "gn:admin1_code":"36",
    "gn:admin2_code":"154.0",
    "gn:asciiname":"Purnia",
    "gn:country_code":"IN",
    "gn:dem":139,
    "gn:feature_class":"P",
    "gn:feature_code":"PPL",
    "gn:name":"Purnia",
    "gn:population":0,
    "gn:timezone":"Asia/Kolkata",
    "iso:country":"IN",
    "name:ara_x_preferred":[
        "\u0628\u0648\u0631\u0646\u064a\u0627"
    ],
    "name:azb_x_preferred":[
        "\u067e\u0648\u0631\u0646\u06cc\u0627"
    ],
    "name:ben_x_preferred":[
        "\u09aa\u09c2\u09b0\u09cd\u09a3\u09bf\u09af\u09bc\u09be"
    ],
    "name:bih_x_preferred":[
        "\u092a\u0942\u0930\u094d\u0923\u093f\u092f\u093e"
    ],
    "name:bpy_x_preferred":[
        "\u09aa\u09c1\u09b0\u09a8\u09bf\u09af\u09bc\u09be"
    ],
    "name:cat_x_preferred":[
        "Purnia"
    ],
    "name:ceb_x_preferred":[
        "Purnia"
    ],
    "name:deu_x_preferred":[
        "Purnia"
    ],
    "name:fas_x_preferred":[
        "\u067e\u0648\u0631\u0646\u06cc\u0627"
    ],
    "name:fra_x_preferred":[
        "Purnia"
    ],
    "name:hin_x_preferred":[
        "\u092a\u0942\u0930\u094d\u0923\u093f\u092f\u093e"
    ],
    "name:ita_x_preferred":[
        "Purnia"
    ],
    "name:mai_x_preferred":[
        "\u092a\u0942\u0930\u094d\u0923\u093f\u092f\u093e"
    ],
    "name:mar_x_preferred":[
        "\u092a\u0942\u0930\u094d\u0923\u093f\u092f\u093e"
    ],
    "name:mlg_x_preferred":[
        "Purnia"
    ],
    "name:msa_x_preferred":[
        "Purnia"
    ],
    "name:nep_x_preferred":[
        "\u092a\u0942\u0930\u094d\u0923\u093f\u092f\u093e"
    ],
    "name:ori_x_preferred":[
        "\u0b2a\u0b41\u0b30\u0b4d\u0b28\u0b3f\u0b06"
    ],
    "name:pol_x_preferred":[
        "Purnia"
    ],
    "name:por_x_preferred":[
        "Purnia"
    ],
    "name:rus_x_preferred":[
        "\u041f\u0443\u0440\u043d\u0438\u044f"
    ],
    "name:san_x_preferred":[
        "\u092a\u0942\u0930\u094d\u0923\u093f\u092f\u093e"
    ],
    "name:spa_x_preferred":[
        "Purnia"
    ],
    "name:srp_x_preferred":[
        "\u041f\u0443\u0440\u043d\u0438\u0458\u0430"
    ],
    "name:swe_x_preferred":[
        "Purnia"
    ],
    "name:tam_x_preferred":[
        "\u0baa\u0bc2\u0bb0\u0bcd\u0ba3\u0bbf\u0baf\u0bbe"
    ],
    "name:tgl_x_preferred":[
        "Purnia"
    ],
    "name:urd_x_preferred":[
        "\u067e\u0648\u0631\u0646\u06cc\u06c1"
    ],
    "name:vie_x_preferred":[
        "Purnia"
    ],
    "name:war_x_preferred":[
        "Purnia"
    ],
    "name:zho_x_preferred":[
        "\u666e\u5c14\u5c3c\u4e9a"
    ],
    "wof:name":"Purnia",
    "wof:placetype":"locality"
},
  "geometry": {"coordinates":[80.8828,27.36921],"type":"Point"}
}