{
  "type": "Feature",
  "properties": {
    "gn:admin1_code":"23",
    "gn:admin2_code":"38.0",
    "gn:asciiname":"Manju Muzara",
    "gn:country_code":"IN",
    "gn:dem":262,
    "gn:feature_class":"P",
    "gn:feature_code":"PPL",
    "gn:name":"Manju Muz\u0101ra",
    "gn:population":0,
    "gn:timezone":"Asia/Kolkata",
    "iso:country":"IN",
    "ks:ks_alt_nam":"Manju Muz\u0101ra",
    "ks:ks_name":"Manju Muzara",
    "ks:ks_pop":762,
    "ks:ks_type":"VILLAGE",
    "ks:ks_uagg_main":0,
    "name:eng_x_preferred":[
        "Manju Muzara"
    ],
    "name:eng_x_variant":[
        "Manju Muz\u0101ra"
    ],
    "wof:name":"Manju Muzara",
    "wof:placetype":"neighbourhood",
    "wof:population":762
},
  "geometry": {"coordinates":[75.916039,31.365834],"type":"Point"}
}