{
  "type": "Feature",
  "properties": {
    "iso:country":"IN",
    "ks:ks_name":"Niveli",
    "ks:ks_pop":133,
    "ks:ks_type":"VILLAGE",
    "name:eng_x_preferred":[
        "Niveli"
    ],
    "wof:name":"Niveli",
    "wof:placetype":"locality",
    "wof:population":133
},
  "geometry": {"coordinates":[73.403593,16.576179],"type":"Point"}
}