{
  "type": "Feature",
  "properties": {
    "gn:admin1_code":"35",
    "gn:admin2_code":"446.0",
    "gn:asciiname":"Dimaria",
    "gn:country_code":"IN",
    "gn:dem":326,
    "gn:feature_class":"P",
    "gn:feature_code":"PPL",
    "gn:name":"Dim\u0101ria",
    "gn:population":0,
    "gn:timezone":"Asia/Kolkata",
    "iso:country":"IN",
    "wof:name":"Dimaria",
    "wof:placetype":"locality"
},
  "geometry": {"coordinates":[78.12477,23.04549],"type":"Point"}
}