{
  "type": "Feature",
  "properties": {
    "iso:country":"IN",
    "ks:ks_name":"Tarkari",
    "ks:ks_pop":93,
    "ks:ks_type":"VILLAGE",
    "name:eng_x_preferred":[
        "Tarkari"
    ],
    "wof:name":"Tarkari",
    "wof:placetype":"locality",
    "wof:population":93
},
  "geometry": {"coordinates":[83.881283,20.444472],"type":"Point"}
}