{
  "type": "Feature",
  "properties": {
    "gn:admin1_code":"34.0",
    "gn:admin2_code":"219.0",
    "gn:asciiname":"Awari",
    "gn:country_code":"IN",
    "gn:dem":60,
    "gn:feature_class":"P",
    "gn:feature_code":"PPL",
    "gn:name":"Aw\u0101ri",
    "gn:population":0,
    "gn:timezone":"Asia/Kolkata",
    "iso:country":"IN",
    "ks:ks_alt_nam":"Aw\u0101ri",
    "ks:ks_name":"Awari",
    "ks:ks_pop":3696,
    "ks:ks_type":"VILLAGE",
    "ks:ks_uagg_main":0,
    "name:eng_x_preferred":[
        "Awari"
    ],
    "name:eng_x_variant":[
        "Aw\u0101ri"
    ],
    "wof:name":"Awari",
    "wof:placetype":"neighbourhood",
    "wof:population":3696
},
  "geometry": {"coordinates":[84.829883,25.964286],"type":"Point"}
}