{
  "type": "Feature",
  "properties": {
    "gn:admin1_code":"25.0",
    "gn:admin2_code":"631.0",
    "gn:asciiname":"Kundurapalli",
    "gn:country_code":"IN",
    "gn:dem":516,
    "gn:feature_class":"P",
    "gn:feature_code":"PPL",
    "gn:name":"Kund\u016brapalli",
    "gn:population":0,
    "gn:timezone":"Asia/Kolkata",
    "iso:country":"IN",
    "ks:ks_name":"Kundarapalli",
    "ks:ks_pop":770,
    "ks:ks_type":"VILLAGE",
    "ks:ks_uagg_main":0,
    "name:eng_x_preferred":[
        "Kundarapalli"
    ],
    "wof:name":"Kundarapalli",
    "wof:placetype":"locality",
    "wof:population":770
},
  "geometry": {"coordinates":[78.177654,12.571012],"type":"Point"}
}