{
  "type": "Feature",
  "properties": {
    "iso:country":"IN",
    "ks:ks_name":"Singasarai",
    "ks:ks_pop":184,
    "ks:ks_type":"HABITATION",
    "name:eng_x_preferred":[
        "Singasarai"
    ],
    "wof:name":"Singasarai",
    "wof:placetype":"locality",
    "wof:population":184
},
  "geometry": {"coordinates":[85.724277,23.510169],"type":"Point"}
}