{
  "type": "Feature",
  "properties": {
    "iso:country":"IN",
    "ks:ks_name":"Ataulapur",
    "ks:ks_pop":193,
    "ks:ks_type":"VILLAGE",
    "name:eng_x_preferred":[
        "Ataulapur"
    ],
    "wof:name":"Ataulapur",
    "wof:placetype":"locality",
    "wof:population":193
},
  "geometry": {"coordinates":[83.65953500000001,25.685918],"type":"Point"}
}