{
  "type": "Feature",
  "properties": {
    "iso:country":"IN",
    "ks:ks_name":"Turaipadu",
    "ks:ks_pop":97,
    "ks:ks_type":"VILLAGE",
    "name:eng_x_preferred":[
        "Turaipadu"
    ],
    "wof:name":"Turaipadu",
    "wof:placetype":"locality",
    "wof:population":97
},
  "geometry": {"coordinates":[83.07035999999999,18.414217],"type":"Point"}
}