{
  "type": "Feature",
  "properties": {
    "iso:country":"IN",
    "ks:ks_name":"Halanayakanahalli",
    "ks:ks_pop":701,
    "ks:ks_type":"VILLAGE",
    "ks:ks_uagg_main":0,
    "name:eng_x_preferred":[
        "Halanayakanahalli"
    ],
    "wof:name":"Halanayakanahalli",
    "wof:placetype":"locality",
    "wof:population":701
},
  "geometry": {"coordinates":[77.68743000000001,12.899578],"type":"Point"}
}