{
  "type": "Feature",
  "properties": {
    "iso:country":"IN",
    "ks:ks_name":"Natekal",
    "ks:ks_pop":360,
    "ks:ks_type":"HABITATION",
    "name:eng_x_preferred":[
        "Natekal"
    ],
    "wof:name":"Natekal",
    "wof:placetype":"locality",
    "wof:population":360
},
  "geometry": {"coordinates":[75.023025,12.7868],"type":"Point"}
}