{
  "type": "Feature",
  "properties": {
    "gn:admin1_code":"39.0",
    "gn:admin2_code":"67.0",
    "gn:asciiname":"Barua Bagh",
    "gn:country_code":"IN",
    "gn:dem":220,
    "gn:feature_class":"P",
    "gn:feature_code":"PPL",
    "gn:name":"Bar\u016ba B\u0101gh",
    "gn:population":0,
    "gn:timezone":"Asia/Kolkata",
    "iso:country":"IN",
    "wof:name":"Barua Bagh",
    "wof:placetype":"locality"
},
  "geometry": {"coordinates":[79.69986,28.97338],"type":"Point"}
}