{
  "type": "Feature",
  "properties": {
    "iso:country":"IN",
    "ks:ks_name":"Shamsam Mohalla",
    "ks:ks_pop":499,
    "ks:ks_type":"HABITATION",
    "name:eng_x_preferred":[
        "Shamsam Mohalla"
    ],
    "wof:name":"Shamsam Mohalla",
    "wof:placetype":"locality",
    "wof:population":499
},
  "geometry": {"coordinates":[73.22238299999999,17.289759],"type":"Point"}
}