{
  "type": "Feature",
  "properties": {
    "iso:country":"IN",
    "ks:ks_alt_nam":"AURALL WASTI",
    "ks:ks_name":"Aurall Wasti",
    "ks:ks_pop":200,
    "ks:ks_type":"HABITATION",
    "name:eng_x_preferred":[
        "Aurall Wasti"
    ],
    "wof:name":"Aurall Wasti",
    "wof:placetype":"locality",
    "wof:population":200
},
  "geometry": {"coordinates":[75.609809,17.081913],"type":"Point"}
}