{
  "type": "Feature",
  "properties": {
    "iso:country":"IN",
    "ks:ks_name":"Pursari 12 Biswa",
    "ks:ks_pop":206,
    "ks:ks_type":"VILLAGE",
    "name:eng_x_preferred":[
        "Pursari 12 Biswa"
    ],
    "wof:name":"Pursari 12 Biswa",
    "wof:placetype":"locality",
    "wof:population":206
},
  "geometry": {"coordinates":[78.979585,27.616654],"type":"Point"}
}