{
  "type": "Feature",
  "properties": {
    "iso:country":"IN",
    "ks:ks_name":"Naikarkeri",
    "ks:ks_pop":165,
    "ks:ks_type":"HABITATION",
    "name:eng_x_preferred":[
        "Naikarkeri"
    ],
    "wof:name":"Naikarkeri",
    "wof:placetype":"locality",
    "wof:population":165
},
  "geometry": {"coordinates":[74.543136,14.248836],"type":"Point"}
}