{
  "type": "Feature",
  "properties": {
    "iso:country":"IN",
    "ks:ks_alt_nam":"savigudde sc calony",
    "ks:ks_name":"Savigudde Sc Calony",
    "ks:ks_pop":35,
    "ks:ks_type":"HABITATION",
    "name:eng_x_preferred":[
        "Savigudde Sc Calony"
    ],
    "wof:name":"Savigudde Sc Calony",
    "wof:placetype":"locality",
    "wof:population":35
},
  "geometry": {"coordinates":[75.465384,12.589495],"type":"Point"}
}