{
  "type": "Feature",
  "properties": {
    "iso:country":"IN",
    "ks:ks_name":"Bhandari",
    "ks:ks_pop":27,
    "ks:ks_type":"VILLAGE",
    "name:eng_x_preferred":[
        "Bhandari"
    ],
    "wof:name":"Bhandari",
    "wof:placetype":"locality",
    "wof:population":27
},
  "geometry": {"coordinates":[86.299888,24.515953],"type":"Point"}
}