{
  "type": "Feature",
  "properties": {
    "gn:admin1_code":"23",
    "gn:admin2_code":"38.0",
    "gn:asciiname":"Barnala",
    "gn:country_code":"IN",
    "gn:dem":269,
    "gn:feature_class":"P",
    "gn:feature_code":"PPL",
    "gn:name":"Barn\u0101la",
    "gn:population":0,
    "gn:timezone":"Asia/Kolkata",
    "iso:country":"IN",
    "ks:ks_name":"Barnala",
    "ks:ks_pop":774,
    "ks:ks_type":"VILLAGE",
    "ks:ks_uagg_main":0,
    "name:ara_x_preferred":[
        "\u0628\u0627\u0631\u0646\u0627\u0644\u0627"
    ],
    "name:ben_bn_x_preferred":[
        "\u09ac\u09b0\u09a8\u09be\u09b2\u09be"
    ],
    "name:ben_in_x_preferred":[
        "\u09ac\u09b0\u09a8\u09be\u09b2\u09be"
    ],
    "name:ben_x_preferred":[
        "\u09ac\u09be\u09b0\u09cd\u09a8\u09be\u09b2\u09be"
    ],
    "name:bih_x_preferred":[
        "\u092c\u0930\u0928\u093e\u0932\u093e"
    ],
    "name:bpy_x_preferred":[
        "\u09ac\u09be\u09b0\u09cd\u09a8\u09be\u09b2\u09be"
    ],
    "name:ceb_x_preferred":[
        "Barn\u0101la"
    ],
    "name:deu_x_preferred":[
        "Barnala"
    ],
    "name:eng_x_preferred":[
        "Barnala"
    ],
    "name:guj_x_preferred":[
        "\u0aac\u0ab0\u0acd\u0aa8\u0abe\u0ab2\u0abe"
    ],
    "name:hin_x_preferred":[
        "\u092c\u0930\u0928\u093e\u0932\u093e"
    ],
    "name:ita_x_preferred":[
        "Barnala"
    ],
    "name:kan_x_preferred":[
        "\u0cac\u0cb0\u0ccd\u0ca8\u0cbe\u0cb2\u0cbe"
    ],
    "name:mal_x_preferred":[
        "\u0d2c\u0d7c\u0d23\u0d3e\u0d32"
    ],
    "name:mar_x_preferred":[
        "\u092c\u0930\u0928\u093e\u0932\u093e"
    ],
    "name:mlg_x_preferred":[
        "Barnala"
    ],
    "name:msa_x_preferred":[
        "Barnala"
    ],
    "name:new_x_preferred":[
        "\u092c\u0930\u0928\u093e\u0932\u093e"
    ],
    "name:nld_x_preferred":[
        "Barnala"
    ],
    "name:nor_x_preferred":[
        "Barnala"
    ],
    "name:ori_x_preferred":[
        "\u0b2c\u0b30\u0b4d\u0b28\u0b3e\u0b32\u0b3e"
    ],
    "name:pan_x_preferred":[
        "\u0a2c\u0a30\u0a28\u0a3e\u0a32\u0a3e"
    ],
    "name:pol_x_preferred":[
        "Barnala"
    ],
    "name:por_x_preferred":[
        "Barnala"
    ],
    "name:rus_x_preferred":[
        "\u0411\u0430\u0440\u043d\u0430\u043b\u0430"
    ],
    "name:san_x_preferred":[
        "\u092c\u0930\u094d\u0928\u093e\u0932\u093e"
    ],
    "name:spa_x_preferred":[
        "Barnala"
    ],
    "name:swe_x_preferred":[
        "Barnala"
    ],
    "name:tam_x_preferred":[
        "\u0baa\u0bb0\u0bcd\u0ba9\u0bbe\u0bb2\u0bbe"
    ],
    "name:tel_x_preferred":[
        "\u0c2c\u0c30\u0c4d\u0c28\u0c3e\u0c32\u0c3e"
    ],
    "name:urd_x_preferred":[
        "\u0628\u0631\u0646\u0627\u0644\u0627"
    ],
    "name:urd_x_variant":[
        "\u0628\u0631\u0646\u0627\u0644\u06c1"
    ],
    "name:vie_x_preferred":[
        "Barnala"
    ],
    "name:zho_x_preferred":[
        "\u5df4\u5c14\u7eb3\u62c9"
    ],
    "wof:name":"Barnala",
    "wof:placetype":"neighbourhood",
    "wof:population":774
},
  "geometry": {"coordinates":[75.69313699999999,31.903241],"type":"Point"}
}