{
  "type": "Feature",
  "properties": {
    "gn:admin1_code":"23",
    "gn:admin2_code":"37.0",
    "gn:asciiname":"Shekhupur",
    "gn:country_code":"IN",
    "gn:dem":241,
    "gn:feature_class":"P",
    "gn:feature_code":"PPL",
    "gn:name":"Shekh\u016bpur",
    "gn:population":0,
    "gn:timezone":"Asia/Kolkata",
    "iso:country":"IN",
    "wof:name":"Shekhupur",
    "wof:placetype":"locality"
},
  "geometry": {"coordinates":[75.72618,31.07185],"type":"Point"}
}