{
  "type": "Feature",
  "properties": {
    "iso:country":"IN",
    "ks:ks_alt_nam":"kesavapura",
    "ks:ks_name":"Kesavapura",
    "ks:ks_pop":68,
    "ks:ks_type":"HABITATION",
    "name:eng_x_preferred":[
        "Kesavapura"
    ],
    "wof:name":"Kesavapura",
    "wof:placetype":"locality",
    "wof:population":68
},
  "geometry": {"coordinates":[75.24815599999999,13.734029],"type":"Point"}
}