{
  "type": "Feature",
  "properties": {
    "gn:admin1_code":"38.0",
    "gn:admin2_code":"347.0",
    "gn:asciiname":"Dari",
    "gn:country_code":"IN",
    "gn:dem":412,
    "gn:feature_class":"P",
    "gn:feature_code":"PPL",
    "gn:name":"D\u0101r\u012b",
    "gn:population":0,
    "gn:timezone":"Asia/Kolkata",
    "iso:country":"IN",
    "ks:ks_alt_nam":"D\u0101r\u012b",
    "ks:ks_name":"Dari",
    "ks:ks_pop":447,
    "ks:ks_type":"VILLAGE",
    "name:ceb_x_preferred":[
        "Dari"
    ],
    "name:deu_x_preferred":[
        "Dari"
    ],
    "name:ell_x_preferred":[
        "\u039d\u03c4\u03b1\u03c1\u03af"
    ],
    "name:eng_x_preferred":[
        "Dari"
    ],
    "name:eng_x_variant":[
        "D\u0101r\u012b"
    ],
    "name:fas_x_preferred":[
        "\u062f\u0631\u06cc"
    ],
    "name:ind_x_preferred":[
        "Dari"
    ],
    "name:ita_x_preferred":[
        "Dari"
    ],
    "name:jpn_x_preferred":[
        "\u30c0\u30ea\u30fc\u8a9e"
    ],
    "name:kur_x_preferred":[
        "Der\u00ee"
    ],
    "name:slk_x_preferred":[
        "Dar\u00edj\u010dina"
    ],
    "name:spa_x_preferred":[
        "Dari"
    ],
    "name:sun_x_preferred":[
        "Dari"
    ],
    "name:swe_x_preferred":[
        "Dari"
    ],
    "name:vie_x_preferred":[
        "Dari"
    ],
    "wof:name":"Dari",
    "wof:placetype":"locality",
    "wof:population":447
},
  "geometry": {"coordinates":[84.71632,24.248948],"type":"Point"}
}