{
  "type": "Feature",
  "properties": {
    "gn:admin1_code":"11",
    "gn:admin2_code":"23.0",
    "gn:asciiname":"Satwas",
    "gn:country_code":"IN",
    "gn:dem":3190,
    "gn:feature_class":"P",
    "gn:feature_code":"PPL",
    "gn:name":"Satw\u0101s",
    "gn:population":0,
    "gn:timezone":"Asia/Kolkata",
    "iso:country":"IN",
    "name:ben_x_preferred":[
        "\u09b8\u09a4\u0993\u09af\u09bc\u09be\u09b8"
    ],
    "name:bpy_x_preferred":[
        "\u09b8\u09a4\u09f1\u09be\u09b8"
    ],
    "name:ceb_x_preferred":[
        "Satw\u0101s"
    ],
    "name:ita_x_preferred":[
        "Satwas"
    ],
    "name:mlg_x_preferred":[
        "Satwas"
    ],
    "name:msa_x_preferred":[
        "Satwas"
    ],
    "name:nld_x_preferred":[
        "Satwas"
    ],
    "name:por_x_preferred":[
        "Satwas"
    ],
    "name:swe_x_preferred":[
        "Satw\u0101s"
    ],
    "name:vie_x_preferred":[
        "Satwas"
    ],
    "name:zho_x_preferred":[
        "\u8428\u7279\u74e6\u65af"
    ],
    "wof:name":"Satwas",
    "wof:placetype":"locality"
},
  "geometry": {"coordinates":[76.44929,33.08822],"type":"Point"}
}