{
  "type": "Feature",
  "properties": {
    "gn:admin1_code":"36",
    "gn:admin2_code":"186.0",
    "gn:asciiname":"Madarpur",
    "gn:country_code":"IN",
    "gn:dem":88,
    "gn:feature_class":"P",
    "gn:feature_code":"PPL",
    "gn:name":"Mad\u0101rpur",
    "gn:population":0,
    "gn:timezone":"Asia/Kolkata",
    "iso:country":"IN",
    "name:fra_x_preferred":[
        "Madarpur"
    ],
    "name:hif_x_preferred":[
        "Madarpur"
    ],
    "wof:name":"Madarpur",
    "wof:placetype":"locality"
},
  "geometry": {"coordinates":[82.94014,26.89967],"type":"Point"}
}