{
  "type": "Feature",
  "properties": {
    "iso:country":"IN",
    "ks:ks_name":"Miyalu",
    "ks:ks_pop":117,
    "ks:ks_type":"HABITATION",
    "name:eng_x_preferred":[
        "Miyalu"
    ],
    "wof:name":"Miyalu",
    "wof:placetype":"locality",
    "wof:population":117
},
  "geometry": {"coordinates":[74.940529,13.460723],"type":"Point"}
}