{
  "type": "Feature",
  "properties": {
    "gn:admin1_code":"16.0",
    "gn:admin2_code":"498.0",
    "gn:asciiname":"Mamana",
    "gn:country_code":"IN",
    "gn:dem":133,
    "gn:feature_class":"P",
    "gn:feature_code":"PPL",
    "gn:name":"Mam\u0101na",
    "gn:population":0,
    "gn:timezone":"Asia/Kolkata",
    "iso:country":"IN",
    "ks:ks_name":"Mamane",
    "ks:ks_pop":1145,
    "ks:ks_type":"HABITATION",
    "ks:ks_uagg_main":0,
    "name:eng_x_preferred":[
        "Mamane"
    ],
    "wof:name":"Mamane",
    "wof:placetype":"neighbourhood",
    "wof:population":1145
},
  "geometry": {"coordinates":[74.70048199999999,21.410706],"type":"Point"}
}