{
  "type": "Feature",
  "properties": {
    "gn:admin1_code":"36.0",
    "gn:admin2_code":"175.0",
    "gn:asciiname":"Shahabpur",
    "gn:country_code":"IN",
    "gn:dem":102,
    "gn:feature_class":"P",
    "gn:feature_code":"PPL",
    "gn:name":"Shah\u0101bpur",
    "gn:population":0,
    "gn:timezone":"Asia/Kolkata",
    "iso:country":"IN",
    "name:fas_x_preferred":[
        "\u0634\u0647\u0627\u0628\u067e\u0648\u0631"
    ],
    "name:por_x_preferred":[
        "Shahabpur"
    ],
    "wof:name":"Shahabpur",
    "wof:placetype":"neighbourhood"
},
  "geometry": {"coordinates":[81.79406,25.57527],"type":"Point"}
}