{
  "type": "Feature",
  "properties": {
    "gn:admin1_code":"9.0",
    "gn:admin2_code":"493",
    "gn:asciiname":"Behera",
    "gn:country_code":"IN",
    "gn:dem":65,
    "gn:feature_class":"P",
    "gn:feature_code":"PPL",
    "gn:name":"Behera",
    "gn:population":0,
    "gn:timezone":"Asia/Kolkata",
    "iso:country":"IN",
    "wof:name":"Behera",
    "wof:placetype":"locality"
},
  "geometry": {"coordinates":[73.28003000000002,20.94989],"type":"Point"}
}