{
  "type": "Feature",
  "properties": {
    "iso:country":"IN",
    "ks:ks_name":"Raghurampur",
    "ks:ks_pop":641,
    "ks:ks_type":"VILLAGE",
    "ks:ks_uagg_main":0,
    "name:eng_x_preferred":[
        "Raghurampur"
    ],
    "wof:name":"Raghurampur",
    "wof:placetype":"neighbourhood",
    "wof:population":641
},
  "geometry": {"coordinates":[85.499084,20.427164],"type":"Point"}
}