{
  "type": "Feature",
  "properties": {
    "iso:country":"IN",
    "ks:ks_name":"Chinchani",
    "ks:ks_pop":1294,
    "ks:ks_type":"URBAN",
    "name:eng_x_preferred":[
        "Chinchani"
    ],
    "wof:name":"Chinchani",
    "wof:placetype":"neighbourhood",
    "wof:population":1294
},
  "geometry": {"coordinates":[72.68391099999999,19.873043],"type":"Point"}
}