{
  "type": "Feature",
  "properties": {
    "iso:country":"IN",
    "ks:ks_alt_nam":"Kharp\u0101ni",
    "ks:ks_name":"Kharpani",
    "ks:ks_pop":265,
    "ks:ks_type":"VILLAGE",
    "name:eng_x_preferred":[
        "Kharpani"
    ],
    "name:eng_x_variant":[
        "Kharp\u0101ni"
    ],
    "wof:name":"Kharpani",
    "wof:placetype":"locality",
    "wof:population":265
},
  "geometry": {"coordinates":[84.561751,22.875338],"type":"Point"}
}