{
  "type": "Feature",
  "properties": {
    "gn:admin1_code":"2.0",
    "gn:admin2_code":"543.0",
    "gn:asciiname":"Viranarayanam",
    "gn:country_code":"IN",
    "gn:dem":75,
    "gn:feature_class":"P",
    "gn:feature_code":"PPL",
    "gn:name":"V\u012bran\u0101r\u0101yanam",
    "gn:population":0,
    "gn:timezone":"Asia/Kolkata",
    "iso:country":"IN",
    "wof:name":"Viranarayanam",
    "wof:placetype":"locality"
},
  "geometry": {"coordinates":[83.12751999999998,18.0651],"type":"Point"}
}