{
  "type": "Feature",
  "properties": {
    "gn:admin1_code":"11",
    "gn:admin2_code":"27.0",
    "gn:asciiname":"Katehr",
    "gn:country_code":"IN",
    "gn:dem":950,
    "gn:feature_class":"P",
    "gn:feature_code":"PPL",
    "gn:name":"Katehr",
    "gn:population":0,
    "gn:timezone":"Asia/Kolkata",
    "iso:country":"IN",
    "wof:name":"Katehr",
    "wof:placetype":"locality"
},
  "geometry": {"coordinates":[76.96769999999999,31.68185],"type":"Point"}
}