{
  "type": "Feature",
  "properties": {
    "iso:country":"IN",
    "ks:ks_alt_nam":"K\u0101tingkel",
    "ks:ks_name":"Katingkel",
    "ks:ks_pop":260,
    "ks:ks_type":"VILLAGE",
    "name:eng_x_preferred":[
        "Katingkel"
    ],
    "name:eng_x_variant":[
        "K\u0101tingkel"
    ],
    "wof:name":"Katingkel",
    "wof:placetype":"locality",
    "wof:population":260
},
  "geometry": {"coordinates":[85.358345,22.835114],"type":"Point"}
}