{
  "type": "Feature",
  "properties": {
    "iso:country":"IN",
    "ks:ks_name":"Pansa",
    "ks:ks_pop":552,
    "ks:ks_type":"VILLAGE",
    "ks:ks_uagg_main":0,
    "name:eng_x_preferred":[
        "Pansa"
    ],
    "wof:name":"Pansa",
    "wof:placetype":"neighbourhood",
    "wof:population":552
},
  "geometry": {"coordinates":[87.13370500000001,21.610792],"type":"Point"}
}