{
  "type": "Feature",
  "properties": {
    "iso:country":"IN",
    "ks:ks_name":"Kuppuchipalayam",
    "ks:ks_pop":112,
    "ks:ks_type":"HABITATION",
    "ks:ks_uagg_main":0,
    "name:eng_x_preferred":[
        "Kuppuchipalayam"
    ],
    "wof:name":"Kuppuchipalayam",
    "wof:placetype":"neighbourhood",
    "wof:population":112
},
  "geometry": {"coordinates":[77.41462900000001,10.813041],"type":"Point"}
}