{
  "type": "Feature",
  "properties": {
    "iso:country":"IN",
    "qs:name":"Guruvayoor",
    "qs:name_adm0":"India",
    "qs:name_adm1":"Kerala",
    "qs:photos":321,
    "qs:photos_1k":65,
    "qs:photos_9k":1,
    "qs:photos_9r":5,
    "qs:photos_all":321,
    "qs:photos_sr":5,
    "qs:placetype":"Town",
    "qs:pop_sr":"0",
    "wd:wordcount":1429,
    "wof:name":"Guruvayoor",
    "wof:placetype":"locality"
},
  "geometry": {"coordinates":[76.039413,10.596179],"type":"Point"}
}