{
  "type": "Feature",
  "properties": {
    "iso:country":"IN",
    "ks:ks_alt_nam":"Bijori fv",
    "ks:ks_name":"Bijori Fv",
    "ks:ks_pop":1052,
    "ks:ks_type":"HABITATION",
    "name:eng_x_preferred":[
        "Bijori Fv"
    ],
    "wof:name":"Bijori Fv",
    "wof:placetype":"locality",
    "wof:population":1052
},
  "geometry": {"coordinates":[81.58530399999999,22.628757],"type":"Point"}
}