{
  "type": "Feature",
  "properties": {
    "iso:country":"IN",
    "ks:ks_name":"Narsapur",
    "ks:ks_pop":230,
    "ks:ks_type":"VILLAGE",
    "name:eng_x_preferred":[
        "Narsapur"
    ],
    "wof:name":"Narsapur",
    "wof:placetype":"locality",
    "wof:population":230
},
  "geometry": {"coordinates":[80.915926,18.438402],"type":"Point"}
}