{
  "type": "Feature",
  "properties": {
    "iso:country":"IN",
    "ks:ks_name":"Senguttai",
    "ks:ks_pop":260,
    "ks:ks_type":"HABITATION",
    "name:eng_x_preferred":[
        "Senguttai"
    ],
    "wof:name":"Senguttai",
    "wof:placetype":"locality",
    "wof:population":260
},
  "geometry": {"coordinates":[78.588899,11.468439],"type":"Point"}
}