{
  "type": "Feature",
  "properties": {
    "iso:country":"IN",
    "ks:ks_name":"Paundkhar",
    "ks:ks_pop":1210,
    "ks:ks_type":"VILLAGE",
    "name:eng_x_preferred":[
        "Paundkhar"
    ],
    "wof:name":"Paundkhar",
    "wof:placetype":"locality",
    "wof:population":1210
},
  "geometry": {"coordinates":[73.023608,18.924764],"type":"Point"}
}