{
  "type": "Feature",
  "properties": {
    "gn:admin1_code":"2.0",
    "gn:admin2_code":"547.0",
    "gn:asciiname":"Annaraopeta",
    "gn:country_code":"IN",
    "gn:dem":126,
    "gn:feature_class":"P",
    "gn:feature_code":"PPL",
    "gn:name":"Annar\u0101opeta",
    "gn:population":0,
    "gn:timezone":"Asia/Kolkata",
    "iso:country":"IN",
    "wof:name":"Annaraopeta",
    "wof:placetype":"locality"
},
  "geometry": {"coordinates":[80.75716,16.88579],"type":"Point"}
}