{
  "type": "Feature",
  "properties": {
    "iso:country":"IN",
    "ks:ks_name":"Bankata",
    "ks:ks_pop":0,
    "ks:ks_type":"VILLAGE",
    "name:eng_x_preferred":[
        "Bankata"
    ],
    "wof:name":"Bankata",
    "wof:placetype":"locality",
    "wof:population":0
},
  "geometry": {"coordinates":[86.799356,23.794431],"type":"Point"}
}