{
  "type": "Feature",
  "properties": {
    "iso:country":"IN",
    "ks:ks_name":"Sankarpur",
    "ks:ks_pop":1962,
    "ks:ks_type":"VILLAGE",
    "ks:ks_uagg_main":0,
    "name:eng_x_preferred":[
        "Sankarpur"
    ],
    "wof:name":"Sankarpur",
    "wof:placetype":"neighbourhood",
    "wof:population":1962
},
  "geometry": {"coordinates":[88.312403,22.169614],"type":"Point"}
}