{
  "type": "Feature",
  "properties": {
    "iso:country":"IN",
    "ks:ks_name":"Patel Falia",
    "ks:ks_pop":215,
    "ks:ks_type":"HABITATION",
    "name:eng_x_preferred":[
        "Patel Falia"
    ],
    "wof:name":"Patel Falia",
    "wof:placetype":"locality",
    "wof:population":215
},
  "geometry": {"coordinates":[73.85802099999999,20.926153],"type":"Point"}
}