{
  "type": "Feature",
  "properties": {
    "iso:country":"IN",
    "ks:ks_name":"Labbakkada",
    "ks:ks_pop":250,
    "ks:ks_type":"HABITATION",
    "name:eng_x_preferred":[
        "Labbakkada"
    ],
    "wof:name":"Labbakkada",
    "wof:placetype":"locality",
    "wof:population":250
},
  "geometry": {"coordinates":[77.066337,9.738001],"type":"Point"}
}