{
  "type": "Feature",
  "properties": {
    "iso:country":"IN",
    "ks:ks_name":"Melaarasoor",
    "ks:ks_pop":125,
    "ks:ks_type":"HABITATION",
    "name:eng_x_preferred":[
        "Melaarasoor"
    ],
    "wof:name":"Melaarasoor",
    "wof:placetype":"locality",
    "wof:population":125
},
  "geometry": {"coordinates":[78.05952600000001,8.507344],"type":"Point"}
}