{
  "type": "Feature",
  "properties": {
    "iso:country":"IN",
    "ks:ks_alt_nam":"Muchiparatha jn",
    "ks:ks_name":"Muchiparatha Jn",
    "ks:ks_pop":988,
    "ks:ks_type":"HABITATION",
    "name:eng_x_preferred":[
        "Muchiparatha Jn"
    ],
    "wof:name":"Muchiparatha Jn",
    "wof:placetype":"locality",
    "wof:population":988
},
  "geometry": {"coordinates":[76.24121,11.343846],"type":"Point"}
}