{
  "type": "Feature",
  "properties": {
    "iso:country":"IN",
    "ks:ks_name":"Bhagaton Ka Gurha",
    "ks:ks_pop":294,
    "ks:ks_type":"HABITATION",
    "name:eng_x_preferred":[
        "Bhagaton Ka Gurha"
    ],
    "wof:name":"Bhagaton Ka Gurha",
    "wof:placetype":"locality",
    "wof:population":294
},
  "geometry": {"coordinates":[74.43350599999999,24.080553],"type":"Point"}
}