{
  "type": "Feature",
  "properties": {
    "iso:country":"IN",
    "ks:ks_name":"Mandbera",
    "ks:ks_pop":216,
    "ks:ks_type":"HABITATION",
    "name:eng_x_preferred":[
        "Mandbera"
    ],
    "wof:name":"Mandbera",
    "wof:placetype":"locality",
    "wof:population":216
},
  "geometry": {"coordinates":[85.791112,22.492224],"type":"Point"}
}