{
  "type": "Feature",
  "properties": {
    "gn:admin1_code":"39",
    "gn:admin2_code":"58.0",
    "gn:asciiname":"Kanda",
    "gn:country_code":"IN",
    "gn:dem":3231,
    "gn:feature_class":"P",
    "gn:feature_code":"PPL",
    "gn:name":"K\u0101nda",
    "gn:population":0,
    "gn:timezone":"Asia/Kolkata",
    "iso:country":"IN",
    "name:ara_x_preferred":[
        "\u0643\u0627\u0646\u062f\u0627"
    ],
    "name:ben_bn_x_preferred":[
        "\u0995\u09be\u09a8\u09cd\u09a6\u09be"
    ],
    "name:ben_in_x_preferred":[
        "\u0995\u09be\u09a8\u09cd\u09a6\u09be"
    ],
    "name:cat_x_preferred":[
        "Kanda"
    ],
    "name:ceb_x_preferred":[
        "Kanda"
    ],
    "name:deu_x_preferred":[
        "Kanda"
    ],
    "name:epo_x_preferred":[
        "Kanda"
    ],
    "name:fas_x_preferred":[
        "\u06a9\u0627\u0646\u062f\u0627"
    ],
    "name:fra_x_preferred":[
        "Kanda"
    ],
    "name:guj_x_preferred":[
        "\u0a95\u0abe\u0a82\u0aa1\u0abe"
    ],
    "name:hin_x_preferred":[
        "\u0915\u093e\u0902\u0921\u093e"
    ],
    "name:kan_x_preferred":[
        "\u0c95\u0c82\u0ca1\u0cbe"
    ],
    "name:mal_x_preferred":[
        "\u0d15\u0d43\u0d37\u0d4d\u0d23"
    ],
    "name:mar_x_preferred":[
        "\u0915\u093e\u0902\u0921\u093e"
    ],
    "name:new_x_preferred":[
        "\u0915\u093e\u0901\u0921\u093e \u0917\u093e\u0935\u093f\u0938"
    ],
    "name:pan_x_preferred":[
        "\u0a15\u0a70\u0a21\u0a3e"
    ],
    "name:por_x_preferred":[
        "Kanda"
    ],
    "name:rus_x_preferred":[
        "\u041a\u0430\u043d\u0434\u0430"
    ],
    "name:swa_x_preferred":[
        "Kanda"
    ],
    "name:swe_x_preferred":[
        "Kanda"
    ],
    "name:tam_x_preferred":[
        "\u0b95\u0ba9\u0bcd\u0b9f\u0bbe"
    ],
    "name:tel_x_preferred":[
        "\u0c15\u0c02\u0c26\u0c3e"
    ],
    "name:ukr_x_preferred":[
        "\u041a\u0430\u043d\u0434\u0430"
    ],
    "name:urd_x_preferred":[
        "\u06a9\u0627\u0646\u0688\u0627"
    ],
    "wof:name":"Kanda",
    "wof:placetype":"locality"
},
  "geometry": {"coordinates":[79.22357,30.50159],"type":"Point"}
}