{
  "type": "Feature",
  "properties": {
    "iso:country":"IN",
    "ks:ks_name":"Gokalpur",
    "ks:ks_pop":230,
    "ks:ks_type":"VILLAGE",
    "ks:ks_uagg_main":0,
    "name:eng_x_preferred":[
        "Gokalpur"
    ],
    "wof:name":"Gokalpur",
    "wof:placetype":"neighbourhood",
    "wof:population":230
},
  "geometry": {"coordinates":[86.20147900000001,20.586751],"type":"Point"}
}