{
  "type": "Feature",
  "properties": {
    "gn:admin1_code":"13.0",
    "gn:admin2_code":"593.0",
    "gn:asciiname":"Nagalassheri",
    "gn:country_code":"IN",
    "gn:dem":43,
    "gn:feature_class":"P",
    "gn:feature_code":"PPL",
    "gn:name":"Nagalassh\u0113ri",
    "gn:population":0,
    "gn:timezone":"Asia/Kolkata",
    "iso:country":"IN",
    "ks:ks_name":"Nagalassery",
    "ks:ks_pop":2115,
    "ks:ks_type":"VILLAGE",
    "name:eng_x_preferred":[
        "Nagalassery"
    ],
    "name:eng_x_variant":[
        "Nagalassheri"
    ],
    "wof:name":"Nagalassery",
    "wof:placetype":"locality",
    "wof:population":2115
},
  "geometry": {"coordinates":[76.139993,10.756537],"type":"Point"}
}