{
  "type": "Feature",
  "properties": {
    "gn:admin1_code":"16",
    "gn:admin2_code":"525.0",
    "gn:asciiname":"Udatpur",
    "gn:country_code":"IN",
    "gn:dem":613,
    "gn:feature_class":"P",
    "gn:feature_code":"PPL",
    "gn:name":"Udatpur",
    "gn:population":0,
    "gn:timezone":"Asia/Kolkata",
    "iso:country":"IN",
    "ks:ks_name":"Udatpur",
    "ks:ks_pop":1212,
    "ks:ks_type":"VILLAGE",
    "name:eng_x_preferred":[
        "Udatpur"
    ],
    "wof:name":"Udatpur",
    "wof:placetype":"locality",
    "wof:population":1212
},
  "geometry": {"coordinates":[76.473072,17.98004],"type":"Point"}
}