{
  "type": "Feature",
  "properties": {
    "iso:country":"IN",
    "ks:ks_name":"Akola Kh.",
    "ks:ks_pop":1275,
    "ks:ks_type":"VILLAGE",
    "ks:ks_uagg_main":0,
    "name:eng_x_preferred":[
        "Akola Kh."
    ],
    "wof:name":"Akola Kh.",
    "wof:placetype":"neighbourhood",
    "wof:population":1275
},
  "geometry": {"coordinates":[76.499174,20.974837],"type":"Point"}
}