{
  "type": "Feature",
  "properties": {
    "iso:country":"IN",
    "ks:ks_name":"Kolyapura",
    "ks:ks_pop":0,
    "ks:ks_type":"VILLAGE",
    "name:eng_x_preferred":[
        "Kolyapura"
    ],
    "wof:name":"Kolyapura",
    "wof:placetype":"locality",
    "wof:population":0
},
  "geometry": {"coordinates":[75.516972,21.731111],"type":"Point"}
}