{
  "type": "Feature",
  "properties": {
    "gn:admin1_code":"39",
    "gn:admin2_code":"61.0",
    "gn:asciiname":"Thunda",
    "gn:country_code":"IN",
    "gn:dem":1107,
    "gn:feature_class":"P",
    "gn:feature_code":"PPL",
    "gn:name":"Thunda",
    "gn:population":0,
    "gn:timezone":"Asia/Kolkata",
    "iso:country":"IN",
    "ks:ks_name":"Thunda",
    "ks:ks_pop":228,
    "ks:ks_type":"VILLAGE",
    "name:eng_x_preferred":[
        "Thunda"
    ],
    "wof:name":"Thunda",
    "wof:placetype":"locality",
    "wof:population":228
},
  "geometry": {"coordinates":[78.405754,29.962792],"type":"Point"}
}