{
  "type": "Feature",
  "properties": {
    "iso:country":"IN",
    "ks:ks_name":"Ghuswapur",
    "ks:ks_pop":232,
    "ks:ks_type":"HABITATION",
    "name:eng_x_preferred":[
        "Ghuswapur"
    ],
    "wof:name":"Ghuswapur",
    "wof:placetype":"locality",
    "wof:population":232
},
  "geometry": {"coordinates":[84.616373,26.960502],"type":"Point"}
}