{
  "type": "Feature",
  "properties": {
    "gn:admin1_code":"11.0",
    "gn:admin2_code":"32.0",
    "gn:asciiname":"Tangra",
    "gn:country_code":"IN",
    "gn:dem":1620,
    "gn:feature_class":"P",
    "gn:feature_code":"PPL",
    "gn:name":"T\u0101ngra",
    "gn:population":0,
    "gn:timezone":"Asia/Kolkata",
    "iso:country":"IN",
    "name:bul_x_preferred":[
        "\u0422\u0430\u043d\u0433\u0440\u0430"
    ],
    "name:fra_x_preferred":[
        "Tangra"
    ],
    "name:swe_x_preferred":[
        "Tangra"
    ],
    "wof:name":"Tangra",
    "wof:placetype":"locality"
},
  "geometry": {"coordinates":[77.63585,30.67343],"type":"Point"}
}