{
  "type": "Feature",
  "properties": {
    "iso:country":"IN",
    "ks:ks_name":"Regulabai",
    "ks:ks_pop":16,
    "ks:ks_type":"HABITATION",
    "name:eng_x_preferred":[
        "Regulabai"
    ],
    "wof:name":"Regulabai",
    "wof:placetype":"locality",
    "wof:population":16
},
  "geometry": {"coordinates":[79.068753,17.442802],"type":"Point"}
}