{
  "type": "Feature",
  "properties": {
    "gn:admin1_code":"12",
    "gn:admin2_code":"15.0",
    "gn:asciiname":"Chogalpur",
    "gn:country_code":"IN",
    "gn:dem":2016,
    "gn:feature_class":"P",
    "gn:feature_code":"PPL",
    "gn:name":"Chogalp\u016br",
    "gn:population":0,
    "gn:timezone":"Asia/Kolkata",
    "iso:country":"IN",
    "wof:name":"Chogalpur",
    "wof:placetype":"locality"
},
  "geometry": {"coordinates":[74.88053000000002,33.62913],"type":"Point"}
}