{
  "type": "Feature",
  "properties": {
    "iso:country":"IN",
    "ks:ks_name":"Ponkola",
    "ks:ks_pop":37,
    "ks:ks_type":"HABITATION",
    "name:eng_x_preferred":[
        "Ponkola"
    ],
    "wof:name":"Ponkola",
    "wof:placetype":"locality",
    "wof:population":37
},
  "geometry": {"coordinates":[84.526488,19.036962],"type":"Point"}
}