{
  "type": "Feature",
  "properties": {
    "iso:country":"IN",
    "ks:ks_name":"Rengdon Bangali Para",
    "ks:ks_pop":129,
    "ks:ks_type":"HABITATION",
    "ks:ks_uagg_main":0,
    "name:eng_x_preferred":[
        "Rengdon Bangali Para"
    ],
    "wof:name":"Rengdon Bangali Para",
    "wof:placetype":"neighbourhood",
    "wof:population":129
},
  "geometry": {"coordinates":[91.638873,23.732489],"type":"Point"}
}