{
  "type": "Feature",
  "properties": {
    "iso:country":"IN",
    "ks:ks_name":"Peddabai",
    "ks:ks_pop":49,
    "ks:ks_type":"HABITATION",
    "name:eng_x_preferred":[
        "Peddabai"
    ],
    "wof:name":"Peddabai",
    "wof:placetype":"locality",
    "wof:population":49
},
  "geometry": {"coordinates":[79.104187,17.389955],"type":"Point"}
}