{
  "type": "Feature",
  "properties": {
    "gn:admin1_code":"36",
    "gn:admin2_code":"147.0",
    "gn:asciiname":"Katena Harsah",
    "gn:country_code":"IN",
    "gn:dem":170,
    "gn:feature_class":"P",
    "gn:feature_code":"PPL",
    "gn:name":"Katen\u0101 Harsah",
    "gn:population":0,
    "gn:timezone":"Asia/Kolkata",
    "iso:country":"IN",
    "wof:name":"Katena Harsah",
    "wof:placetype":"locality"
},
  "geometry": {"coordinates":[78.57165999999999,27.17653],"type":"Point"}
}