{
  "type": "Feature",
  "properties": {
    "iso:country":"IN",
    "ks:ks_name":"Mundagimane",
    "ks:ks_pop":85,
    "ks:ks_type":"HABITATION",
    "name:eng_x_preferred":[
        "Mundagimane"
    ],
    "wof:name":"Mundagimane",
    "wof:placetype":"locality",
    "wof:population":85
},
  "geometry": {"coordinates":[74.562594,14.02982],"type":"Point"}
}