{
  "type": "Feature",
  "properties": {
    "gn:admin1_code":"37",
    "gn:admin2_code":"404.0",
    "gn:asciiname":"Ranaikhet",
    "gn:country_code":"IN",
    "gn:dem":958,
    "gn:feature_class":"P",
    "gn:feature_code":"PPL",
    "gn:name":"Ranaikhet",
    "gn:population":0,
    "gn:timezone":"Asia/Kolkata",
    "iso:country":"IN",
    "wof:name":"Ranaikhet",
    "wof:placetype":"locality"
},
  "geometry": {"coordinates":[82.92814,22.49124],"type":"Point"}
}