{
  "type": "Feature",
  "properties": {
    "gn:admin1_code":"34.0",
    "gn:admin2_code":"218.0",
    "gn:asciiname":"Dhonrhpur",
    "gn:country_code":"IN",
    "gn:dem":64,
    "gn:feature_class":"P",
    "gn:feature_code":"PPL",
    "gn:name":"Dhonrhpur",
    "gn:population":0,
    "gn:timezone":"Asia/Kolkata",
    "iso:country":"IN",
    "ks:ks_name":"Dhonrhpur",
    "ks:ks_pop":491,
    "ks:ks_type":"VILLAGE",
    "name:eng_x_preferred":[
        "Dhonrhpur"
    ],
    "wof:name":"Dhonrhpur",
    "wof:placetype":"locality",
    "wof:population":491
},
  "geometry": {"coordinates":[84.594336,26.073498],"type":"Point"}
}