{
  "type": "Feature",
  "properties": {
    "iso:country":"IN",
    "ks:ks_name":"Wajidpur",
    "ks:ks_pop":0,
    "ks:ks_type":"VILLAGE",
    "name:eng_x_preferred":[
        "Wajidpur"
    ],
    "wof:name":"Wajidpur",
    "wof:placetype":"locality",
    "wof:population":0
},
  "geometry": {"coordinates":[83.82684399999999,25.619701],"type":"Point"}
}