{
  "type": "Feature",
  "properties": {
    "gn:admin1_code":"12.0",
    "gn:admin2_code":"17.0",
    "gn:asciiname":"Rechal",
    "gn:country_code":"IN",
    "gn:dem":2451,
    "gn:feature_class":"P",
    "gn:feature_code":"PPL",
    "gn:name":"R\u0113chal",
    "gn:population":0,
    "gn:timezone":"Asia/Kolkata",
    "iso:country":"IN",
    "wof:name":"Rechal",
    "wof:placetype":"locality"
},
  "geometry": {"coordinates":[75.33289000000001,33.32548],"type":"Point"}
}