{
  "type": "Feature",
  "properties": {
    "iso:country":"IN",
    "ks:ks_name":"Jayar",
    "ks:ks_pop":92,
    "ks:ks_type":"VILLAGE",
    "name:eng_x_preferred":[
        "Jayar"
    ],
    "wof:name":"Jayar",
    "wof:placetype":"locality",
    "wof:population":92
},
  "geometry": {"coordinates":[80.136385,29.347844],"type":"Point"}
}