{
  "type": "Feature",
  "properties": {
    "iso:country":"IN",
    "ks:ks_name":"Rakha",
    "ks:ks_pop":104,
    "ks:ks_type":"VILLAGE",
    "name:eng_x_preferred":[
        "Rakha"
    ],
    "wof:name":"Rakha",
    "wof:placetype":"locality",
    "wof:population":104
},
  "geometry": {"coordinates":[87.463643,24.64951],"type":"Point"}
}