{
  "type": "Feature",
  "properties": {
    "iso:country":"IN",
    "ks:ks_alt_nam":"patti tol",
    "ks:ks_name":"Patti Tol",
    "ks:ks_pop":1066,
    "ks:ks_type":"HABITATION",
    "name:eng_x_preferred":[
        "Patti Tol"
    ],
    "wof:name":"Patti Tol",
    "wof:placetype":"locality",
    "wof:population":1066
},
  "geometry": {"coordinates":[86.229921,26.277371],"type":"Point"}
}