{
  "type": "Feature",
  "properties": {
    "iso:country":"IN",
    "ks:ks_name":"Ghasbera",
    "ks:ks_pop":49,
    "ks:ks_type":"VILLAGE",
    "name:eng_x_preferred":[
        "Ghasbera"
    ],
    "wof:name":"Ghasbera",
    "wof:placetype":"locality",
    "wof:population":49
},
  "geometry": {"coordinates":[87.604026,23.945838],"type":"Point"}
}