{
  "type": "Feature",
  "properties": {
    "gn:admin1_code":"24.0",
    "gn:admin2_code":"103.0",
    "gn:asciiname":"Patusar",
    "gn:country_code":"IN",
    "gn:dem":288,
    "gn:feature_class":"P",
    "gn:feature_code":"PPL",
    "gn:name":"P\u0101tusar",
    "gn:population":0,
    "gn:timezone":"Asia/Kolkata",
    "iso:country":"IN",
    "wof:name":"Patusar",
    "wof:placetype":"neighbourhood"
},
  "geometry": {"coordinates":[75.15848,28.32006],"type":"Point"}
}