{
  "type": "Feature",
  "properties": {
    "iso:country":"IN",
    "ks:ks_name":"Bonduguda",
    "ks:ks_pop":164,
    "ks:ks_type":"HABITATION",
    "name:eng_x_preferred":[
        "Bonduguda"
    ],
    "wof:name":"Bonduguda",
    "wof:placetype":"locality",
    "wof:population":164
},
  "geometry": {"coordinates":[82.872041,18.219006],"type":"Point"}
}