{
  "type": "Feature",
  "properties": {
    "iso:country":"IN",
    "ks:ks_name":"Banguramal",
    "ks:ks_pop":0,
    "ks:ks_type":"VILLAGE",
    "ks:ks_uagg_main":0,
    "name:eng_x_preferred":[
        "Banguramal"
    ],
    "wof:name":"Banguramal",
    "wof:placetype":"neighbourhood",
    "wof:population":0
},
  "geometry": {"coordinates":[85.714595,20.797254],"type":"Point"}
}