{
  "type": "Feature",
  "properties": {
    "gn:admin1_code":"38.0",
    "gn:admin2_code":"358.0",
    "gn:asciiname":"Majhauli",
    "gn:country_code":"IN",
    "gn:dem":340,
    "gn:feature_class":"P",
    "gn:feature_code":"PPL",
    "gn:name":"Majhaul\u012b",
    "gn:population":0,
    "gn:timezone":"Asia/Kolkata",
    "iso:country":"IN",
    "wof:name":"Majhauli",
    "wof:placetype":"locality"
},
  "geometry": {"coordinates":[84.41175,24.21504],"type":"Point"}
}