{
  "type": "Feature",
  "properties": {
    "gn:admin1_code":"19",
    "gn:admin2_code":"568.0",
    "gn:asciiname":"Kesavapura",
    "gn:country_code":"IN",
    "gn:dem":589,
    "gn:feature_class":"P",
    "gn:feature_code":"PPL",
    "gn:name":"Kesav\u0101pura",
    "gn:population":0,
    "gn:timezone":"Asia/Kolkata",
    "iso:country":"IN",
    "ks:ks_name":"Keswavapur",
    "ks:ks_pop":17,
    "ks:ks_type":"HABITATION",
    "name:eng_x_preferred":[
        "Keswavapur"
    ],
    "name:eng_x_variant":[
        "Kesavapura"
    ],
    "wof:name":"Keswavapur",
    "wof:placetype":"locality",
    "wof:population":17
},
  "geometry": {"coordinates":[74.772307,14.018754],"type":"Point"}
}