{
  "type": "Feature",
  "properties": {
    "iso:country":"IN",
    "ks:ks_name":"Puregosai Das",
    "ks:ks_pop":704,
    "ks:ks_type":"HABITATION",
    "name:eng_x_preferred":[
        "Puregosai Das"
    ],
    "wof:name":"Puregosai Das",
    "wof:placetype":"locality",
    "wof:population":704
},
  "geometry": {"coordinates":[82.46534,25.308481],"type":"Point"}
}