{
  "type": "Feature",
  "properties": {
    "iso:country":"IN",
    "ks:ks_name":"Talla Matela",
    "ks:ks_pop":78,
    "ks:ks_type":"HABITATION",
    "name:eng_x_preferred":[
        "Talla Matela"
    ],
    "wof:name":"Talla Matela",
    "wof:placetype":"locality",
    "wof:population":78
},
  "geometry": {"coordinates":[79.19206800000001,29.803647],"type":"Point"}
}