{
  "type": "Feature",
  "properties": {
    "iso:country":"IN",
    "ks:ks_name":"Kamapadu",
    "ks:ks_pop":58,
    "ks:ks_type":"HABITATION",
    "name:eng_x_preferred":[
        "Kamapadu"
    ],
    "wof:name":"Kamapadu",
    "wof:placetype":"locality",
    "wof:population":58
},
  "geometry": {"coordinates":[82.97272,18.55455],"type":"Point"}
}