{
  "type": "Feature",
  "properties": {
    "gn:admin1_code":"36.0",
    "gn:admin2_code":"135.0",
    "gn:asciiname":"Mirzapur",
    "gn:country_code":"IN",
    "gn:dem":191,
    "gn:feature_class":"P",
    "gn:feature_code":"PPL",
    "gn:name":"Mirz\u0101pur",
    "gn:population":0,
    "gn:timezone":"Asia/Kolkata",
    "iso:country":"IN",
    "name:und_x_variant":[
        "Mirz\u0101pur",
        "Nasirull\u0101hpur"
    ],
    "wof:name":"Mirzapur",
    "wof:placetype":"locality"
},
  "geometry": {"coordinates":[78.6575,28.38088],"type":"Point"}
}