{
  "type": "Feature",
  "properties": {
    "gn:admin1_code":"36.0",
    "gn:admin2_code":"160.0",
    "gn:asciiname":"Fatehpur",
    "gn:country_code":"IN",
    "gn:dem":144,
    "gn:feature_class":"P",
    "gn:feature_code":"PPL",
    "gn:name":"Fatehpur",
    "gn:population":0,
    "gn:timezone":"Asia/Kolkata",
    "iso:country":"IN",
    "name:ara_x_preferred":[
        "\u0641\u0627\u062a\u062d \u0628\u0648\u0631"
    ],
    "name:ben_bn_x_preferred":[
        "\u09ab\u09a4\u09c7\u09aa\u09c1\u09b0"
    ],
    "name:ben_in_x_preferred":[
        "\u09ab\u09a4\u09c7\u09aa\u09c1\u09b0"
    ],
    "name:ben_x_preferred":[
        "\u09ab\u09a4\u09c7\u09b9\u09aa\u09c1\u09b0"
    ],
    "name:bih_x_preferred":[
        "\u092b\u0924\u0947\u0939\u092a\u0941\u0930"
    ],
    "name:ceb_x_preferred":[
        "Fatehpur"
    ],
    "name:deu_x_preferred":[
        "Fatehpur"
    ],
    "name:guj_x_preferred":[
        "\u0aab\u0aa4\u0ac7\u0ab9\u0aaa\u0ac1\u0ab0"
    ],
    "name:hin_x_preferred":[
        "\u095e\u0924\u0947\u0939\u092a\u0941\u0930"
    ],
    "name:kan_x_preferred":[
        "\u0cab\u0ca4\u0cc7\u0cb9\u0ccd"
    ],
    "name:mal_x_preferred":[
        "\u0d2b\u0d24\u0d4d\u0d24\u0d47\u0d2a\u0d42\u0d7c"
    ],
    "name:mar_x_preferred":[
        "\u092b\u0924\u0947\u0939\u092a\u0942\u0930"
    ],
    "name:new_x_preferred":[
        "\u092b\u0924\u0947\u0939\u092a\u0941\u0930"
    ],
    "name:nld_x_preferred":[
        "Fatehpur"
    ],
    "name:pan_x_preferred":[
        "\u0a2b\u0a24\u0a47\u0a39\u0a2a\u0a41\u0a30"
    ],
    "name:pnb_x_preferred":[
        "\u0641\u062a\u062d \u067e\u0648\u0631"
    ],
    "name:pol_x_preferred":[
        "Fatehpur"
    ],
    "name:spa_x_preferred":[
        "Fatehpur"
    ],
    "name:swe_x_preferred":[
        "Fatehpur"
    ],
    "name:tam_x_preferred":[
        "\u0b83\u0baa\u0ba4\u0bc7\u0baa\u0bc2\u0bb0\u0bcd"
    ],
    "name:tel_x_preferred":[
        "\u0c2b\u0c24\u0c47\u0c2a\u0c42\u0c30\u0c4d"
    ],
    "name:urd_x_preferred":[
        "\u0641\u062a\u062d \u067e\u0648\u0631"
    ],
    "wof:name":"Fatehpur",
    "wof:placetype":"locality"
},
  "geometry": {"coordinates":[79.71903,26.97669],"type":"Point"}
}