{
  "type": "Feature",
  "properties": {
    "iso:country":"IN",
    "ks:ks_name":"Digpadar",
    "ks:ks_pop":43,
    "ks:ks_type":"VILLAGE",
    "name:eng_x_preferred":[
        "Digpadar"
    ],
    "wof:name":"Digpadar",
    "wof:placetype":"locality",
    "wof:population":43
},
  "geometry": {"coordinates":[84.439387,20.552056],"type":"Point"}
}