{
  "type": "Feature",
  "properties": {
    "iso:country":"IN",
    "ks:ks_name":"Bargarchumbak",
    "ks:ks_pop":960,
    "ks:ks_type":"VILLAGE",
    "ks:ks_uagg_main":0,
    "name:eng_x_preferred":[
        "Bargarchumbak"
    ],
    "wof:name":"Bargarchumbak",
    "wof:placetype":"neighbourhood",
    "wof:population":960
},
  "geometry": {"coordinates":[88.047275,22.348463],"type":"Point"}
}