{
  "type": "Feature",
  "properties": {
    "iso:country":"IN",
    "ks:ks_name":"Dabri Ubari",
    "ks:ks_pop":554,
    "ks:ks_type":"VILLAGE",
    "ks:ks_uagg_main":0,
    "name:eng_x_preferred":[
        "Dabri Ubari"
    ],
    "wof:name":"Dabri Ubari",
    "wof:placetype":"neighbourhood",
    "wof:population":554
},
  "geometry": {"coordinates":[76.57072700000001,22.121096],"type":"Point"}
}