{
  "type": "Feature",
  "properties": {
    "iso:country":"IN",
    "ks:ks_name":"Harichandanpur",
    "ks:ks_pop":109,
    "ks:ks_type":"VILLAGE",
    "name:eng_x_preferred":[
        "Harichandanpur"
    ],
    "wof:name":"Harichandanpur",
    "wof:placetype":"locality",
    "wof:population":109
},
  "geometry": {"coordinates":[84.555779,19.503502],"type":"Point"}
}