{
  "type": "Feature",
  "properties": {
    "iso:country":"IN",
    "ks:ks_alt_nam":"Aonr\u0101d\u012bh",
    "ks:ks_name":"Aonradih",
    "ks:ks_pop":971,
    "ks:ks_type":"VILLAGE",
    "name:eng_x_preferred":[
        "Aonradih"
    ],
    "name:eng_x_variant":[
        "Aonr\u0101d\u012bh"
    ],
    "wof:name":"Aonradih",
    "wof:placetype":"locality",
    "wof:population":971
},
  "geometry": {"coordinates":[85.799905,23.495936],"type":"Point"}
}