{
  "type": "Feature",
  "properties": {
    "gn:admin1_code":"11.0",
    "gn:admin2_code":"32.0",
    "gn:asciiname":"Mach",
    "gn:country_code":"IN",
    "gn:dem":1413,
    "gn:feature_class":"P",
    "gn:feature_code":"PPL",
    "gn:name":"Mach",
    "gn:population":0,
    "gn:timezone":"Asia/Kolkata",
    "iso:country":"IN",
    "name:cat_x_preferred":[
        "Mach"
    ],
    "name:ceb_x_preferred":[
        "Mach"
    ],
    "name:ces_x_preferred":[
        "Mach"
    ],
    "name:deu_x_preferred":[
        "Mach"
    ],
    "name:ell_x_preferred":[
        "\u039c\u03b1\u03c7"
    ],
    "name:fas_x_preferred":[
        "\u0645\u0627\u062e"
    ],
    "name:fin_x_preferred":[
        "Mach"
    ],
    "name:fra_x_preferred":[
        "Mach"
    ],
    "name:heb_x_preferred":[
        "\u05de\u05d0\u05da"
    ],
    "name:ita_x_preferred":[
        "Mach"
    ],
    "name:jpn_x_preferred":[
        "\u30de\u30c3\u30cf"
    ],
    "name:kor_x_preferred":[
        "\ub9c8\ud558"
    ],
    "name:lav_x_preferred":[
        "Mahs"
    ],
    "name:nld_x_preferred":[
        "Mach"
    ],
    "name:pol_x_preferred":[
        "Mach"
    ],
    "name:por_x_preferred":[
        "Mach"
    ],
    "name:ron_x_preferred":[
        "Mach"
    ],
    "name:rus_x_preferred":[
        "\u041c\u0430\u0445"
    ],
    "name:slk_x_preferred":[
        "Mach"
    ],
    "name:spa_x_preferred":[
        "Mach"
    ],
    "name:swe_x_preferred":[
        "Mach"
    ],
    "name:ukr_x_preferred":[
        "\u041c\u0430\u0445"
    ],
    "name:vie_x_preferred":[
        "Mach"
    ],
    "wof:name":"Mach",
    "wof:placetype":"locality"
},
  "geometry": {"coordinates":[77.52004000000002,30.6289],"type":"Point"}
}