{
  "type": "Feature",
  "properties": {
    "iso:country":"IN",
    "ks:ks_name":"Badapurunapani",
    "ks:ks_pop":818,
    "ks:ks_type":"VILLAGE",
    "name:eng_x_preferred":[
        "Badapurunapani"
    ],
    "wof:name":"Badapurunapani",
    "wof:placetype":"locality",
    "wof:population":818
},
  "geometry": {"coordinates":[86.131383,21.441593],"type":"Point"}
}