{
  "type": "Feature",
  "properties": {
    "iso:country":"IN",
    "ks:ks_alt_nam":"Doharia Barg\u0101h",
    "ks:ks_name":"Doharia Bargah",
    "ks:ks_type":"VILLAGE",
    "ks:ks_uagg_main":0,
    "name:eng_x_preferred":[
        "Doharia Bargah"
    ],
    "name:eng_x_variant":[
        "Doharia Barg\u0101h"
    ],
    "wof:name":"Doharia Bargah",
    "wof:placetype":"neighbourhood"
},
  "geometry": {"coordinates":[83.25671,26.636467],"type":"Point"}
}