{
  "type": "Feature",
  "properties": {
    "iso:country":"IN",
    "ks:ks_name":"Henchalli",
    "ks:ks_pop":105,
    "ks:ks_type":"HABITATION",
    "name:eng_x_preferred":[
        "Henchalli"
    ],
    "wof:name":"Henchalli",
    "wof:placetype":"locality",
    "wof:population":105
},
  "geometry": {"coordinates":[75.397105,13.224567],"type":"Point"}
}