{
  "type": "Feature",
  "properties": {
    "iso:country":"IN",
    "ks:ks_name":"Dhitaipur",
    "ks:ks_pop":0,
    "ks:ks_type":"VILLAGE",
    "name:eng_x_preferred":[
        "Dhitaipur"
    ],
    "wof:name":"Dhitaipur",
    "wof:placetype":"locality",
    "wof:population":0
},
  "geometry": {"coordinates":[87.664581,23.906981],"type":"Point"}
}