{
  "type": "Feature",
  "properties": {
    "gn:admin1_code":"34",
    "gn:admin2_code":"234.0",
    "gn:asciiname":"Sanwan Dihri",
    "gn:country_code":"IN",
    "gn:dem":87,
    "gn:feature_class":"P",
    "gn:feature_code":"PPL",
    "gn:name":"S\u0101nw\u0101n D\u012bhri",
    "gn:population":0,
    "gn:timezone":"Asia/Kolkata",
    "iso:country":"IN",
    "ks:ks_name":"Sanwandehri",
    "ks:ks_pop":724,
    "ks:ks_type":"VILLAGE",
    "name:eng_x_preferred":[
        "Sanwandehri"
    ],
    "name:eng_x_variant":[
        "Sanwan Dihri"
    ],
    "wof:name":"Sanwandehri",
    "wof:placetype":"locality",
    "wof:population":724
},
  "geometry": {"coordinates":[83.949367,25.180549],"type":"Point"}
}