{
  "type": "Feature",
  "properties": {
    "iso:country":"IN",
    "ks:ks_name":"Sutgirni Wasti",
    "ks:ks_pop":214,
    "ks:ks_type":"HABITATION",
    "name:eng_x_preferred":[
        "Sutgirni Wasti"
    ],
    "wof:name":"Sutgirni Wasti",
    "wof:placetype":"locality",
    "wof:population":214
},
  "geometry": {"coordinates":[75.854702,19.797504],"type":"Point"}
}