{
  "type": "Feature",
  "properties": {
    "iso:country":"IN",
    "ks:ks_name":"Rajwara",
    "ks:ks_pop":2370,
    "ks:ks_type":"VILLAGE",
    "ks:ks_uagg_main":0,
    "name:eng_x_preferred":[
        "Rajwara"
    ],
    "wof:name":"Rajwara",
    "wof:placetype":"neighbourhood",
    "wof:population":2370
},
  "geometry": {"coordinates":[85.621225,26.816764],"type":"Point"}
}