{
  "type": "Feature",
  "properties": {
    "iso:country":"IN",
    "ks:ks_name":"Alakone",
    "ks:ks_pop":25,
    "ks:ks_type":"HABITATION",
    "name:eng_x_preferred":[
        "Alakone"
    ],
    "wof:name":"Alakone",
    "wof:placetype":"locality",
    "wof:population":25
},
  "geometry": {"coordinates":[74.722692,14.367897],"type":"Point"}
}