{
  "type": "Feature",
  "properties": {
    "iso:country":"IN",
    "ks:ks_name":"Nidhichak",
    "ks:ks_pop":188,
    "ks:ks_type":"VILLAGE",
    "name:eng_x_preferred":[
        "Nidhichak"
    ],
    "wof:name":"Nidhichak",
    "wof:placetype":"locality",
    "wof:population":188
},
  "geometry": {"coordinates":[87.475731,22.046848],"type":"Point"}
}