{
  "type": "Feature",
  "properties": {
    "gn:admin1_code":"2.0",
    "gn:admin2_code":"547.0",
    "gn:asciiname":"Lakshmipuram",
    "gn:country_code":"IN",
    "gn:dem":10,
    "gn:feature_class":"P",
    "gn:feature_code":"PPL",
    "gn:name":"Lakshmipuram",
    "gn:population":0,
    "gn:timezone":"Asia/Kolkata",
    "iso:country":"IN",
    "ks:ks_name":"Lakshmipuram",
    "ks:ks_pop":311,
    "ks:ks_type":"HABITATION",
    "name:ara_x_preferred":[
        "\u0644\u0627\u0643\u0634\u0645\u064a\u0628\u0648\u0631\u0627\u0645"
    ],
    "name:ben_bn_x_preferred":[
        "\u09b2\u0995\u09cd\u09b7\u09cd\u09ae\u09c0\u09aa\u09c1\u09b0\u09ae"
    ],
    "name:ben_in_x_preferred":[
        "\u09b2\u0995\u09cd\u09b7\u09cd\u09ae\u09c0\u09aa\u09c1\u09b0\u09ae"
    ],
    "name:eng_x_preferred":[
        "Lakshmipuram"
    ],
    "name:guj_x_preferred":[
        "\u0ab2\u0a95\u0acd\u0ab7\u0acd\u0aae\u0abf\u0aaa\u0ac1\u0ab0\u0aae"
    ],
    "name:hin_x_preferred":[
        "\u0932\u0915\u094d\u0937\u094d\u092e\u0940\u092a\u0941\u0930\u092e"
    ],
    "name:kan_x_preferred":[
        "\u0cb2\u0c95\u0ccd\u0cb7\u0ccd\u0cae\u0cc0\u0caa\u0cc1\u0cb0\u0cae\u0ccd"
    ],
    "name:mal_x_preferred":[
        "\u0d32\u0d15\u0d4d\u0d37\u0d4d\u0d2e\u0d3f\u0d2a\u0d41\u0d30\u0d02"
    ],
    "name:mar_x_preferred":[
        "\u0932\u0915\u094d\u0937\u094d\u092e\u0940\u092a\u0941\u0930\u092e"
    ],
    "name:pan_x_preferred":[
        "\u0a32\u0a15\u0a36\u0a2e\u0a40\u0a2a\u0a41\u0a30\u0a2e"
    ],
    "name:tam_x_preferred":[
        "\u0bb2\u0b9f\u0bcd\u0b9a\u0bc1\u0bae\u0bbf\u0baa\u0bc1\u0bb0\u0bae\u0bcd"
    ],
    "name:tel_x_preferred":[
        "\u0c32\u0c15\u0c4d\u0c37\u0c4d\u0c2e\u0c3f\u0c2a\u0c41\u0c30\u0c02"
    ],
    "name:urd_x_preferred":[
        "\u0644\u06a9\u0634\u0645\u06cc \u067e\u0648\u0631\u0645"
    ],
    "wof:name":"Lakshmipuram",
    "wof:placetype":"locality",
    "wof:population":311
},
  "geometry": {"coordinates":[80.924808,16.457183],"type":"Point"}
}