{
  "type": "Feature",
  "properties": {
    "iso:country":"IN",
    "ks:ks_name":"Peichuni",
    "ks:ks_pop":169,
    "ks:ks_type":"VILLAGE",
    "name:eng_x_preferred":[
        "Peichuni"
    ],
    "wof:name":"Peichuni",
    "wof:placetype":"locality",
    "wof:population":169
},
  "geometry": {"coordinates":[79.373383,29.882473],"type":"Point"}
}