{
  "type": "Feature",
  "properties": {
    "gn:country":"IN",
    "gn:fcode":"PPL",
    "gn:pop":52492,
    "iso:country":"IN",
    "qs:name":"Kosi",
    "qs:photos_9r":0,
    "qs:photos_sr":0,
    "qs:pop_sr":"8",
    "wof:name":"Kosi",
    "wof:placetype":"locality",
    "wof:population":52492
},
  "geometry": {"coordinates":[77.4383,27.794],"type":"Point"}
}