{
  "type": "Feature",
  "properties": {
    "iso:country":"IN",
    "ks:ks_name":"Dedhiya Nana Mota",
    "ks:ks_pop":669,
    "ks:ks_type":"HABITATION",
    "name:eng_x_preferred":[
        "Dedhiya Nana Mota"
    ],
    "wof:name":"Dedhiya Nana Mota",
    "wof:placetype":"locality",
    "wof:population":669
},
  "geometry": {"coordinates":[69.78671900000001,23.710553],"type":"Point"}
}