{
  "type": "Feature",
  "properties": {
    "gn:admin1_code":"33.0",
    "gn:admin2_code":"585.0",
    "gn:asciiname":"Biroudem",
    "gn:country_code":"IN",
    "gn:dem":389,
    "gn:feature_class":"P",
    "gn:feature_code":"PPL",
    "gn:name":"Biroudem",
    "gn:population":0,
    "gn:timezone":"Asia/Kolkata",
    "iso:country":"IN",
    "wof:name":"Biroudem",
    "wof:placetype":"locality"
},
  "geometry": {"coordinates":[74.24347,15.51299],"type":"Point"}
}