{
  "type": "Feature",
  "properties": {
    "iso:country":"IN",
    "ks:ks_name":"Kerabani",
    "ks:ks_pop":593,
    "ks:ks_type":"VILLAGE",
    "name:eng_x_preferred":[
        "Kerabani"
    ],
    "wof:name":"Kerabani",
    "wof:placetype":"locality",
    "wof:population":593
},
  "geometry": {"coordinates":[87.298641,24.385773],"type":"Point"}
}