{
  "type": "Feature",
  "properties": {
    "gn:admin1_code":"13.0",
    "gn:admin2_code":"590.0",
    "gn:asciiname":"Naduvanthur",
    "gn:country_code":"IN",
    "gn:dem":781,
    "gn:feature_class":"P",
    "gn:feature_code":"PPL",
    "gn:name":"Naduvanthur",
    "gn:population":0,
    "gn:timezone":"Asia/Kolkata",
    "iso:country":"IN",
    "wof:name":"Naduvanthur",
    "wof:placetype":"locality"
},
  "geometry": {"coordinates":[76.01241,11.8889],"type":"Point"}
}