{
  "type": "Feature",
  "properties": {
    "iso:country":"IN",
    "ks:ks_name":"Talagadala",
    "ks:ks_pop":433,
    "ks:ks_type":"VILLAGE",
    "name:eng_x_preferred":[
        "Talagadala"
    ],
    "wof:name":"Talagadala",
    "wof:placetype":"locality",
    "wof:population":433
},
  "geometry": {"coordinates":[82.93439100000001,19.117874],"type":"Point"}
}