{
  "type": "Feature",
  "properties": {
    "iso:country":"IN",
    "ks:ks_name":"Wayanganiwadi",
    "ks:ks_pop":111,
    "ks:ks_type":"HABITATION",
    "name:eng_x_preferred":[
        "Wayanganiwadi"
    ],
    "wof:name":"Wayanganiwadi",
    "wof:placetype":"locality",
    "wof:population":111
},
  "geometry": {"coordinates":[73.79573600000001,16.001415],"type":"Point"}
}