{
  "type": "Feature",
  "properties": {
    "gn:admin1_code":"35.0",
    "gn:admin2_code":"424",
    "gn:asciiname":"Paigakherra",
    "gn:country_code":"IN",
    "gn:dem":260,
    "gn:feature_class":"P",
    "gn:feature_code":"PPL",
    "gn:name":"Paig\u0101kherra",
    "gn:population":0,
    "gn:timezone":"Asia/Kolkata",
    "iso:country":"IN",
    "name:und_x_variant":[
        "Paig\u0101kherra",
        "Palg\u0101khera"
    ],
    "wof:name":"Paigakherra",
    "wof:placetype":"neighbourhood"
},
  "geometry": {"coordinates":[78.95999,25.16514],"type":"Point"}
}