{
  "type": "Feature",
  "properties": {
    "iso:country":"IN",
    "ks:ks_alt_nam":"BIHARI TOLA",
    "ks:ks_name":"Bihari Tola",
    "ks:ks_pop":655,
    "ks:ks_type":"HABITATION",
    "name:eng_x_preferred":[
        "Bihari Tola"
    ],
    "wof:name":"Bihari Tola",
    "wof:placetype":"locality",
    "wof:population":655
},
  "geometry": {"coordinates":[84.159722,25.429737],"type":"Point"}
}