{
  "type": "Feature",
  "properties": {
    "iso:country":"IN",
    "ks:ks_name":"Kodhar Roadikheda",
    "ks:ks_pop":250,
    "ks:ks_type":"VILLAGE",
    "name:eng_x_preferred":[
        "Kodhar Roadikheda"
    ],
    "wof:name":"Kodhar Roadikheda",
    "wof:placetype":"locality",
    "wof:population":250
},
  "geometry": {"coordinates":[78.72841099999999,21.524987],"type":"Point"}
}