{
  "type": "Feature",
  "properties": {
    "gn:admin1_code":"19.0",
    "gn:admin2_code":"581.0",
    "gn:asciiname":"Dinnuru",
    "gn:country_code":"IN",
    "gn:dem":823,
    "gn:feature_class":"P",
    "gn:feature_code":"PPL",
    "gn:name":"Dinn\u016bru",
    "gn:population":0,
    "gn:timezone":"Asia/Kolkata",
    "iso:country":"IN",
    "wof:name":"Dinnuru",
    "wof:placetype":"neighbourhood"
},
  "geometry": {"coordinates":[78.13827999999999,13.23006],"type":"Point"}
}