{
  "type": "Feature",
  "properties": {
    "iso:country":"IN",
    "ks:ks_alt_nam":"DATAM",
    "ks:ks_name":"Datam",
    "ks:ks_pop":485,
    "ks:ks_type":"HABITATION",
    "name:eng_x_preferred":[
        "Datam"
    ],
    "wof:name":"Datam",
    "wof:placetype":"locality",
    "wof:population":485
},
  "geometry": {"coordinates":[84.03206299999999,23.951981],"type":"Point"}
}