{
  "type": "Feature",
  "properties": {
    "gn:admin1_code":"38",
    "gn:admin2_code":"346.0",
    "gn:asciiname":"Serasam",
    "gn:country_code":"IN",
    "gn:dem":323,
    "gn:feature_class":"P",
    "gn:feature_code":"PPL",
    "gn:name":"Ser\u0101s\u0101m",
    "gn:population":0,
    "gn:timezone":"Asia/Kolkata",
    "iso:country":"IN",
    "ks:ks_alt_nam":"Ser\u0101s\u0101m",
    "ks:ks_name":"Serasam",
    "ks:ks_pop":770,
    "ks:ks_type":"VILLAGE",
    "name:eng_x_preferred":[
        "Serasam"
    ],
    "name:eng_x_variant":[
        "Ser\u0101s\u0101m"
    ],
    "wof:name":"Serasam",
    "wof:placetype":"locality",
    "wof:population":770
},
  "geometry": {"coordinates":[83.789599,24.028812],"type":"Point"}
}