{
  "type": "Feature",
  "properties": {
    "gn:admin1_code":"11.0",
    "gn:admin2_code":"023",
    "gn:asciiname":"Alas",
    "gn:country_code":"IN",
    "gn:dem":1611,
    "gn:feature_class":"P",
    "gn:feature_code":"PPL",
    "gn:name":"Alas",
    "gn:population":0,
    "gn:timezone":"Asia/Kolkata",
    "iso:country":"IN",
    "wof:name":"Alas",
    "wof:placetype":"locality"
},
  "geometry": {"coordinates":[75.96866999999997,32.76524000000001],"type":"Point"}
}