{
  "type": "Feature",
  "properties": {
    "gn:admin1_code":"11.0",
    "gn:admin2_code":"023",
    "gn:asciiname":"Alas",
    "gn:country_code":"IN",
    "gn:dem":1611,
    "gn:feature_class":"P",
    "gn:feature_code":"PPL",
    "gn:name":"Alas",
    "gn:population":0,
    "gn:timezone":"Asia/Kolkata",
    "iso:country":"IN",
    "name:cat_x_preferred":[
        "Al\u00e0s"
    ],
    "name:ceb_x_preferred":[
        "Alas"
    ],
    "name:deu_x_preferred":[
        "Alas"
    ],
    "name:fra_x_preferred":[
        "Alas"
    ],
    "name:ind_x_preferred":[
        "Alas"
    ],
    "name:nld_x_preferred":[
        "Alas"
    ],
    "name:oci_x_preferred":[
        "Al\u00e0s"
    ],
    "name:por_x_preferred":[
        "Alas"
    ],
    "name:spa_x_preferred":[
        "Alas"
    ],
    "wof:name":"Alas",
    "wof:placetype":"locality"
},
  "geometry": {"coordinates":[75.96866999999997,32.76524000000001],"type":"Point"}
}