{
  "type": "Feature",
  "properties": {
    "iso:country":"IN",
    "ks:ks_name":"Kalungupatti",
    "ks:ks_pop":466,
    "ks:ks_type":"HABITATION",
    "name:eng_x_preferred":[
        "Kalungupatti"
    ],
    "wof:name":"Kalungupatti",
    "wof:placetype":"locality",
    "wof:population":466
},
  "geometry": {"coordinates":[77.93978,9.969638],"type":"Point"}
}