{
  "type": "Feature",
  "properties": {
    "gn:admin1_code":"9.0",
    "gn:admin2_code":"469",
    "gn:asciiname":"Bhildi",
    "gn:country_code":"IN",
    "gn:dem":112,
    "gn:feature_class":"P",
    "gn:feature_code":"PPL",
    "gn:name":"Bh\u012bldi",
    "gn:population":0,
    "gn:timezone":"Asia/Kolkata",
    "iso:country":"IN",
    "name:ceb_x_preferred":[
        "Bh\u012bldi"
    ],
    "name:guj_x_preferred":[
        "\u0aad\u0ac0\u0ab2\u0aa1\u0ac0"
    ],
    "name:swe_x_preferred":[
        "Bh\u012bldi"
    ],
    "name:und_x_variant":[
        "Bhilari"
    ],
    "wof:name":"Bhildi",
    "wof:placetype":"locality"
},
  "geometry": {"coordinates":[72.00709000000001,24.18556],"type":"Point"}
}