{
  "type": "Feature",
  "properties": {
    "gn:admin1_code":"2.0",
    "gn:admin2_code":"544.0",
    "gn:asciiname":"Bongjangi",
    "gn:country_code":"IN",
    "gn:dem":709,
    "gn:feature_class":"P",
    "gn:feature_code":"PPL",
    "gn:name":"Bongjangi",
    "gn:population":0,
    "gn:timezone":"Asia/Kolkata",
    "iso:country":"IN",
    "wof:name":"Bongjangi",
    "wof:placetype":"locality"
},
  "geometry": {"coordinates":[82.38636,18.20053],"type":"Point"}
}