{
  "type": "Feature",
  "properties": {
    "gn:admin1_code":"11",
    "gn:admin2_code":"28.0",
    "gn:asciiname":"Sasan",
    "gn:country_code":"IN",
    "gn:dem":541,
    "gn:feature_class":"P",
    "gn:feature_code":"PPL",
    "gn:name":"S\u0101san",
    "gn:population":0,
    "gn:timezone":"Asia/Kolkata",
    "iso:country":"IN",
    "name:ara_x_preferred":[
        "\u0633\u0627\u0633\u0627\u0646"
    ],
    "name:bel_x_preferred":[
        "\u0421\u0430\u0441\u0430\u043d"
    ],
    "name:cat_x_preferred":[
        "Sassan"
    ],
    "name:ces_x_preferred":[
        "S\u00e1s\u00e1n"
    ],
    "name:deu_x_preferred":[
        "Sassan"
    ],
    "name:ell_x_preferred":[
        "\u03a3\u03b1\u03c3\u03c3\u03ac\u03bd"
    ],
    "name:epo_x_preferred":[
        "Sasano"
    ],
    "name:fas_x_preferred":[
        "\u0633\u0627\u0633\u0627\u0646"
    ],
    "name:fra_x_preferred":[
        "Sassan"
    ],
    "name:hrv_x_preferred":[
        "Sasan"
    ],
    "name:por_x_preferred":[
        "Sasano"
    ],
    "name:rus_x_preferred":[
        "\u0421\u0430\u0441\u0430\u043d"
    ],
    "name:slk_x_preferred":[
        "S\u00e1s\u00e1n"
    ],
    "name:spa_x_preferred":[
        "Sas\u00e1n"
    ],
    "name:swe_x_preferred":[
        "Sasan"
    ],
    "name:tgk_x_preferred":[
        "\u0421\u043e\u0441\u043e\u043d"
    ],
    "name:tur_x_preferred":[
        "Sasan"
    ],
    "name:ukr_x_preferred":[
        "\u0421\u0430\u0441\u0430\u043d"
    ],
    "name:urd_x_preferred":[
        "\u0633\u0627\u0633\u0627\u0646"
    ],
    "name:uzb_x_preferred":[
        "Soson"
    ],
    "wof:name":"Sasan",
    "wof:placetype":"locality"
},
  "geometry": {"coordinates":[76.4145,31.75853],"type":"Point"}
}