{
  "type": "Feature",
  "properties": {
    "iso:country":"IN",
    "ks:ks_name":"Sirisgatar",
    "ks:ks_pop":36,
    "ks:ks_type":"HABITATION",
    "name:eng_x_preferred":[
        "Sirisgatar"
    ],
    "wof:name":"Sirisgatar",
    "wof:placetype":"locality",
    "wof:population":36
},
  "geometry": {"coordinates":[86.955884,23.121211],"type":"Point"}
}