{
  "type": "Feature",
  "properties": {
    "iso:country":"IN",
    "ks:ks_name":"Pottilanka",
    "ks:ks_pop":542,
    "ks:ks_type":"HABITATION",
    "name:eng_x_preferred":[
        "Pottilanka"
    ],
    "wof:name":"Pottilanka",
    "wof:placetype":"locality",
    "wof:population":542
},
  "geometry": {"coordinates":[82.063085,16.674909],"type":"Point"}
}