{
  "type": "Feature",
  "properties": {
    "iso:country":"IN",
    "ks:ks_alt_nam":"Ishwarp\u0101li",
    "ks:ks_name":"Ishwarpali",
    "ks:ks_type":"VILLAGE",
    "name:eng_x_preferred":[
        "Ishwarpali"
    ],
    "name:eng_x_variant":[
        "Ishwarp\u0101li"
    ],
    "wof:name":"Ishwarpali",
    "wof:placetype":"locality"
},
  "geometry": {"coordinates":[84.654144,21.411507],"type":"Point"}
}