{
  "type": "Feature",
  "properties": {
    "gn:admin1_code":"11.0",
    "gn:admin2_code":"27.0",
    "gn:asciiname":"Hal",
    "gn:country_code":"IN",
    "gn:dem":2216,
    "gn:feature_class":"P",
    "gn:feature_code":"PPL",
    "gn:name":"Hal",
    "gn:population":0,
    "gn:timezone":"Asia/Kolkata",
    "iso:country":"IN",
    "name:nld_x_preferred":[
        "Hal"
    ],
    "name:pol_x_preferred":[
        "Hal"
    ],
    "name:spa_x_preferred":[
        "Hal"
    ],
    "name:swe_x_preferred":[
        "Hal"
    ],
    "wof:name":"Hal",
    "wof:placetype":"locality"
},
  "geometry": {"coordinates":[77.30261,31.48156],"type":"Point"}
}