{
  "type": "Feature",
  "properties": {
    "iso:country":"IN",
    "ks:ks_name":"Soladanga Dwitia Khanda",
    "ks:ks_pop":671,
    "ks:ks_type":"VILLAGE",
    "name:eng_x_preferred":[
        "Soladanga Dwitia Khanda"
    ],
    "wof:name":"Soladanga Dwitia Khanda",
    "wof:placetype":"locality",
    "wof:population":671
},
  "geometry": {"coordinates":[89.55849499999999,26.293554],"type":"Point"}
}