{
  "type": "Feature",
  "properties": {
    "gn:admin1_code":"36.0",
    "gn:admin2_code":"173.0",
    "gn:asciiname":"Sukulpur Pachaiyan",
    "gn:country_code":"IN",
    "gn:dem":107,
    "gn:feature_class":"P",
    "gn:feature_code":"PPL",
    "gn:name":"Sukulpur Pachaiy\u0101n",
    "gn:population":0,
    "gn:timezone":"Asia/Kolkata",
    "iso:country":"IN",
    "wof:name":"Sukulpur Pachaiyan",
    "wof:placetype":"neighbourhood"
},
  "geometry": {"coordinates":[81.68532999999999,25.74744],"type":"Point"}
}