{
  "type": "Feature",
  "properties": {
    "iso:country":"IN",
    "ks:ks_name":"Buddhawadi",
    "ks:ks_pop":65,
    "ks:ks_type":"HABITATION",
    "name:eng_x_preferred":[
        "Buddhawadi"
    ],
    "wof:name":"Buddhawadi",
    "wof:placetype":"locality",
    "wof:population":65
},
  "geometry": {"coordinates":[73.425214,17.664353],"type":"Point"}
}