{
  "type": "Feature",
  "properties": {
    "iso:country":"IN",
    "ks:ks_name":"Padarri Khurd",
    "ks:ks_pop":100,
    "ks:ks_type":"VILLAGE",
    "name:eng_x_preferred":[
        "Padarri Khurd"
    ],
    "wof:name":"Padarri Khurd",
    "wof:placetype":"locality",
    "wof:population":100
},
  "geometry": {"coordinates":[71.79366,25.065671],"type":"Point"}
}