{
  "type": "Feature",
  "properties": {
    "gn:admin1_code":"39.0",
    "gn:admin2_code":"61.0",
    "gn:asciiname":"Dharkot",
    "gn:country_code":"IN",
    "gn:dem":1420,
    "gn:feature_class":"P",
    "gn:feature_code":"PPL",
    "gn:name":"Dh\u0101rkot",
    "gn:population":0,
    "gn:timezone":"Asia/Kolkata",
    "iso:country":"IN",
    "ks:ks_alt_nam":"Dh\u0101rkot",
    "ks:ks_name":"Dharkot",
    "ks:ks_pop":148,
    "ks:ks_type":"VILLAGE",
    "name:eng_x_preferred":[
        "Dharkot"
    ],
    "name:eng_x_variant":[
        "Dh\u0101rkot"
    ],
    "wof:name":"Dharkot",
    "wof:placetype":"locality",
    "wof:population":148
},
  "geometry": {"coordinates":[79.213137,29.946422],"type":"Point"}
}