{
  "type": "Feature",
  "properties": {
    "iso:country":"IN",
    "ks:ks_name":"Nikamwasti",
    "ks:ks_pop":210,
    "ks:ks_type":"HABITATION",
    "name:eng_x_preferred":[
        "Nikamwasti"
    ],
    "wof:name":"Nikamwasti",
    "wof:placetype":"locality",
    "wof:population":210
},
  "geometry": {"coordinates":[75.4455,17.317614],"type":"Point"}
}