{
  "type": "Feature",
  "properties": {
    "iso:country":"IN",
    "ks:ks_name":"Dagarewadi",
    "ks:ks_pop":97,
    "ks:ks_type":"HABITATION",
    "name:eng_x_preferred":[
        "Dagarewadi"
    ],
    "wof:name":"Dagarewadi",
    "wof:placetype":"locality",
    "wof:population":97
},
  "geometry": {"coordinates":[73.406583,16.299918],"type":"Point"}
}