{
  "type": "Feature",
  "properties": {
    "gn:admin1_code":"25.0",
    "gn:admin2_code":"608.0",
    "gn:asciiname":"Varakuttaparateruyu",
    "gn:country_code":"IN",
    "gn:dem":288,
    "gn:feature_class":"P",
    "gn:feature_code":"PPL",
    "gn:name":"Varakuttaparateruyu",
    "gn:population":0,
    "gn:timezone":"Asia/Kolkata",
    "iso:country":"IN",
    "wof:name":"Varakuttaparateruyu",
    "wof:placetype":"locality"
},
  "geometry": {"coordinates":[77.99384000000001,11.74893],"type":"Point"}
}