{
  "type": "Feature",
  "properties": {
    "iso:country":"IN",
    "ks:ks_name":"Godatopa",
    "ks:ks_pop":494,
    "ks:ks_type":"VILLAGE",
    "name:eng_x_preferred":[
        "Godatopa"
    ],
    "wof:name":"Godatopa",
    "wof:placetype":"locality",
    "wof:population":494
},
  "geometry": {"coordinates":[85.48447899999999,21.791238],"type":"Point"}
}