{
  "type": "Feature",
  "properties": {
    "iso:country":"IN",
    "ks:ks_name":"Kurunthangudi",
    "ks:ks_pop":250,
    "ks:ks_type":"HABITATION",
    "name:eng_x_preferred":[
        "Kurunthangudi"
    ],
    "wof:name":"Kurunthangudi",
    "wof:placetype":"locality",
    "wof:population":250
},
  "geometry": {"coordinates":[78.72426299999999,9.783367],"type":"Point"}
}