{
  "type": "Feature",
  "properties": {
    "gn:admin1_code":"12.0",
    "gn:admin2_code":"17.0",
    "gn:asciiname":"Dung",
    "gn:country_code":"IN",
    "gn:dem":2089,
    "gn:feature_class":"P",
    "gn:feature_code":"PPL",
    "gn:name":"Dung",
    "gn:population":0,
    "gn:timezone":"Asia/Kolkata",
    "iso:country":"IN",
    "name:ceb_x_preferred":[
        "Dung"
    ],
    "name:deu_x_preferred":[
        "Dung"
    ],
    "wof:name":"Dung",
    "wof:placetype":"locality"
},
  "geometry": {"coordinates":[75.31407,33.25785],"type":"Point"}
}