{
  "type": "Feature",
  "properties": {
    "iso:country":"IN",
    "name:ben_x_preferred":[
        "\u09b6\u09bf\u09b2\u0982 \u0995\u09cd\u09af\u09be\u09a8\u09cd\u099f\u09a8\u09ae\u09c7\u09a8\u09cd\u099f"
    ],
    "name:bpy_x_preferred":[
        "\u09b6\u09bf\u09b2\u0982 \u0995\u09cd\u09af\u09be\u09a8\u09cd\u099f\u09a8\u09ae\u09c7\u09a8\u09cd\u099f"
    ],
    "name:eng_x_preferred":[
        "Shillong Cantonment"
    ],
    "name:fra_x_preferred":[
        "Shillong Cantonment"
    ],
    "name:hin_x_preferred":[
        "\u0936\u093f\u0932\u093e\u0902\u0917 \u091b\u093e\u0935\u0928\u0940"
    ],
    "name:ita_x_preferred":[
        "Shillong Cantonment"
    ],
    "name:mlg_x_preferred":[
        "Shillong Cantonment"
    ],
    "name:msa_x_preferred":[
        "Shillong Cantt."
    ],
    "name:nan_x_preferred":[
        "Shillong Cantonment"
    ],
    "name:nld_x_preferred":[
        "Shillong Cantonment"
    ],
    "name:vie_x_preferred":[
        "Shillong Cantt."
    ],
    "name:zho_x_preferred":[
        "\u65af\u5e0c\u9686\u683c\u5175\u7ad9"
    ],
    "qs:name":"Shillong Cantt",
    "qs:name_adm0":"India",
    "qs:name_adm1":"Meghalaya",
    "qs:photos":20,
    "qs:photos_1k":4,
    "qs:photos_9k":1,
    "qs:photos_9r":1,
    "qs:photos_all":20,
    "qs:photos_sr":1,
    "qs:placetype":"Town",
    "qs:pop_sr":"0",
    "wd:wordcount":109,
    "wof:name":"Shillong Cantt",
    "wof:placetype":"neighbourhood"
},
  "geometry": {"coordinates":[91.898938,25.563012],"type":"Point"}
}