{
  "type": "Feature",
  "properties": {
    "iso:country":"IN",
    "ks:ks_name":"Pemparada",
    "ks:ks_pop":111,
    "ks:ks_type":"VILLAGE",
    "name:eng_x_preferred":[
        "Pemparada"
    ],
    "wof:name":"Pemparada",
    "wof:placetype":"locality",
    "wof:population":111
},
  "geometry": {"coordinates":[84.68370400000001,20.390556],"type":"Point"}
}