{
  "type": "Feature",
  "properties": {
    "iso:country":"IN",
    "ks:ks_name":"Jagdispur",
    "ks:ks_pop":404,
    "ks:ks_type":"VILLAGE",
    "ks:ks_uagg_main":0,
    "name:eng_x_preferred":[
        "Jagdispur"
    ],
    "wof:name":"Jagdispur",
    "wof:placetype":"neighbourhood",
    "wof:population":404
},
  "geometry": {"coordinates":[85.09087700000001,24.55184],"type":"Point"}
}