{
  "type": "Feature",
  "properties": {
    "gn:admin1_code":"39.0",
    "gn:admin2_code":"64.0",
    "gn:asciiname":"Sanana",
    "gn:country_code":"IN",
    "gn:dem":857,
    "gn:feature_class":"P",
    "gn:feature_code":"PPL",
    "gn:name":"Sanana",
    "gn:population":0,
    "gn:timezone":"Asia/Kolkata",
    "iso:country":"IN",
    "ks:ks_name":"Sanana",
    "ks:ks_type":"VILLAGE",
    "name:ara_x_preferred":[
        "\u062c\u0632\u064a\u0631\u0629 \u0633\u0627\u0646\u0627\u0646\u0627"
    ],
    "name:deu_x_preferred":[
        "Sanana"
    ],
    "name:eng_x_preferred":[
        "Sanana"
    ],
    "name:fra_x_preferred":[
        "Sanana"
    ],
    "name:glg_x_preferred":[
        "Sanana"
    ],
    "name:ind_x_preferred":[
        "Sanana"
    ],
    "name:ita_x_preferred":[
        "Sanana"
    ],
    "name:jav_x_preferred":[
        "Sanana"
    ],
    "name:jpn_x_preferred":[
        "\u30b5\u30ca\u30ca\u5cf6"
    ],
    "name:msa_x_preferred":[
        "Sanana"
    ],
    "name:nld_x_preferred":[
        "Sanana"
    ],
    "name:pol_x_preferred":[
        "Sanana"
    ],
    "name:por_x_preferred":[
        "Sanana"
    ],
    "name:spa_x_preferred":[
        "Sanana"
    ],
    "name:vie_x_preferred":[
        "Sanana"
    ],
    "name:wuu_x_preferred":[
        "\u85a9\u7d0d\u7d0d\u5cf6"
    ],
    "name:zho_x_preferred":[
        "\u85a9\u7d0d\u7d0d\u5cf6"
    ],
    "wof:name":"Sanana",
    "wof:placetype":"locality"
},
  "geometry": {"coordinates":[79.237019,29.767406],"type":"Point"}
}