{
  "type": "Feature",
  "properties": {
    "iso:country":"IN",
    "ks:ks_name":"Akkaraivalavu",
    "ks:ks_pop":210,
    "ks:ks_type":"HABITATION",
    "name:eng_x_preferred":[
        "Akkaraivalavu"
    ],
    "wof:name":"Akkaraivalavu",
    "wof:placetype":"locality",
    "wof:population":210
},
  "geometry": {"coordinates":[78.326432,11.374348],"type":"Point"}
}