{
  "type": "Feature",
  "properties": {
    "gn:admin1_code":"39",
    "gn:admin2_code":"60.0",
    "gn:asciiname":"Minjaun",
    "gn:country_code":"IN",
    "gn:dem":1452,
    "gn:feature_class":"P",
    "gn:feature_code":"PPL",
    "gn:name":"Minjaun",
    "gn:population":0,
    "gn:timezone":"Asia/Kolkata",
    "iso:country":"IN",
    "wof:name":"Minjaun",
    "wof:placetype":"locality"
},
  "geometry": {"coordinates":[77.82173,30.79153],"type":"Point"}
}