{
  "type": "Feature",
  "properties": {
    "iso:country":"IN",
    "ks:ks_alt_nam":"MARAUNA PUNERVAS",
    "ks:ks_name":"Marauna Punervas",
    "ks:ks_pop":900,
    "ks:ks_type":"HABITATION",
    "ks:ks_uagg_main":0,
    "name:eng_x_preferred":[
        "Marauna Punervas"
    ],
    "wof:name":"Marauna Punervas",
    "wof:placetype":"neighbourhood",
    "wof:population":900
},
  "geometry": {"coordinates":[86.451415,26.172987],"type":"Point"}
}