{
  "type": "Feature",
  "properties": {
    "gn:admin1_code":"40",
    "gn:admin2_code":"538.0",
    "gn:asciiname":"Lingareddiguda",
    "gn:country_code":"IN",
    "gn:dem":661,
    "gn:feature_class":"P",
    "gn:feature_code":"PPL",
    "gn:name":"Ling\u0101reddiguda",
    "gn:population":0,
    "gn:timezone":"Asia/Kolkata",
    "iso:country":"IN",
    "ks:ks_name":"Lingareddyguda",
    "ks:ks_pop":237,
    "ks:ks_type":"HABITATION",
    "name:eng_x_preferred":[
        "Lingareddyguda"
    ],
    "name:eng_x_variant":[
        "Lingareddiguda"
    ],
    "wof:name":"Lingareddyguda",
    "wof:placetype":"locality",
    "wof:population":237
},
  "geometry": {"coordinates":[78.10294500000001,17.09303],"type":"Point"}
}