{
  "type": "Feature",
  "properties": {
    "gn:admin1_code":"28.0",
    "gn:admin2_code":"330.0",
    "gn:asciiname":"Janamjai",
    "gn:country_code":"IN",
    "gn:dem":48,
    "gn:feature_class":"P",
    "gn:feature_code":"PPL",
    "gn:name":"Janamjai",
    "gn:population":0,
    "gn:timezone":"Asia/Kolkata",
    "iso:country":"IN",
    "ks:ks_name":"Janamjai",
    "ks:ks_pop":605,
    "ks:ks_type":"VILLAGE",
    "ks:ks_uagg_main":0,
    "name:eng_x_preferred":[
        "Janamjai"
    ],
    "wof:name":"Janamjai",
    "wof:placetype":"neighbourhood",
    "wof:population":605
},
  "geometry": {"coordinates":[87.85206100000001,26.008272],"type":"Point"}
}