{
  "type": "Feature",
  "properties": {
    "iso:country":"IN",
    "ks:ks_name":"Sutoli",
    "ks:ks_pop":97,
    "ks:ks_type":"VILLAGE",
    "name:eng_x_preferred":[
        "Sutoli"
    ],
    "wof:name":"Sutoli",
    "wof:placetype":"locality",
    "wof:population":97
},
  "geometry": {"coordinates":[79.227009,29.717815],"type":"Point"}
}