{
  "type": "Feature",
  "properties": {
    "iso:country":"IN",
    "ks:ks_name":"Tabarsing",
    "ks:ks_pop":515,
    "ks:ks_type":"VILLAGE",
    "name:eng_x_preferred":[
        "Tabarsing"
    ],
    "wof:name":"Tabarsing",
    "wof:placetype":"locality",
    "wof:population":515
},
  "geometry": {"coordinates":[84.30506800000001,19.135164],"type":"Point"}
}