{
  "type": "Feature",
  "properties": {
    "iso:country":"IN",
    "ks:ks_name":"Moran Chah Comp. 18 39 No Fs 2",
    "ks:ks_pop":579,
    "ks:ks_type":"HABITATION",
    "name:eng_x_preferred":[
        "Moran Chah Comp. 18 39 No Fs 2"
    ],
    "wof:name":"Moran Chah Comp. 18 39 No Fs 2",
    "wof:placetype":"locality",
    "wof:population":579
},
  "geometry": {"coordinates":[94.877906,27.156373],"type":"Point"}
}