{
  "type": "Feature",
  "properties": {
    "iso:country":"IN",
    "ks:ks_name":"Balupalle",
    "ks:ks_pop":184,
    "ks:ks_type":"HABITATION",
    "name:eng_x_preferred":[
        "Balupalle"
    ],
    "wof:name":"Balupalle",
    "wof:placetype":"locality",
    "wof:population":184
},
  "geometry": {"coordinates":[79.293935,13.412937],"type":"Point"}
}