{
  "type": "Feature",
  "properties": {
    "gn:admin1_code":"34.0",
    "gn:admin2_code":"234.0",
    "gn:asciiname":"Ghurdihan",
    "gn:country_code":"IN",
    "gn:dem":101,
    "gn:feature_class":"P",
    "gn:feature_code":"PPL",
    "gn:name":"Ghurdih\u0101n",
    "gn:population":0,
    "gn:timezone":"Asia/Kolkata",
    "iso:country":"IN",
    "ks:ks_name":"Ghurdihan",
    "ks:ks_pop":1099,
    "ks:ks_type":"VILLAGE",
    "name:eng_x_preferred":[
        "Ghurdihan"
    ],
    "wof:name":"Ghurdihan",
    "wof:placetype":"locality",
    "wof:population":1099
},
  "geometry": {"coordinates":[84.143156,25.087275],"type":"Point"}
}