{
  "type": "Feature",
  "properties": {
    "gn:admin1_code":"2.0",
    "gn:admin2_code":"553.0",
    "gn:asciiname":"Honnampalle",
    "gn:country_code":"IN",
    "gn:dem":622,
    "gn:feature_class":"P",
    "gn:feature_code":"PPL",
    "gn:name":"Honnampalle",
    "gn:population":0,
    "gn:timezone":"Asia/Kolkata",
    "iso:country":"IN",
    "wof:name":"Honnampalle",
    "wof:placetype":"locality"
},
  "geometry": {"coordinates":[77.42712,13.8918],"type":"Point"}
}