{
  "type": "Feature",
  "properties": {
    "gn:admin1_code":"16",
    "gn:admin2_code":"501.0",
    "gn:asciiname":"Bramhi Bai",
    "gn:country_code":"IN",
    "gn:dem":284,
    "gn:feature_class":"P",
    "gn:feature_code":"PPL",
    "gn:name":"Bramhi B\u0101i",
    "gn:population":0,
    "gn:timezone":"Asia/Kolkata",
    "iso:country":"IN",
    "wof:name":"Bramhi Bai",
    "wof:placetype":"locality"
},
  "geometry": {"coordinates":[77.43248,20.78255],"type":"Point"}
}