{
  "type": "Feature",
  "properties": {
    "gn:admin1_code":"28.0",
    "gn:admin2_code":"337.0",
    "gn:asciiname":"Hatgachha",
    "gn:country_code":"IN",
    "gn:dem":3,
    "gn:feature_class":"P",
    "gn:feature_code":"PPL",
    "gn:name":"Hatgachha",
    "gn:population":0,
    "gn:timezone":"Asia/Kolkata",
    "iso:country":"IN",
    "name:ben_x_preferred":[
        "\u09b9\u09be\u099f\u0997\u09be\u099b\u09be"
    ],
    "name:bpy_x_preferred":[
        "\u09b9\u09be\u099f\u0997\u09be\u099b\u09be"
    ],
    "name:hif_x_preferred":[
        "Hatgachha"
    ],
    "name:ita_x_preferred":[
        "Hatgachha"
    ],
    "name:msa_x_preferred":[
        "Hatgachha"
    ],
    "name:new_x_preferred":[
        "\u0939\u093e\u091f\u0917\u091b\u093e"
    ],
    "name:nld_x_preferred":[
        "Hatgachha"
    ],
    "name:por_x_preferred":[
        "Hatgachha"
    ],
    "name:vie_x_preferred":[
        "Hatgachha"
    ],
    "name:zho_x_preferred":[
        "\u54c8\u7279\u52a0\u6070"
    ],
    "wof:name":"Hatgachha",
    "wof:placetype":"locality"
},
  "geometry": {"coordinates":[88.9366,22.34819],"type":"Point"}
}