{
  "type": "Feature",
  "properties": {
    "iso:country":"IN",
    "ks:ks_name":"Bar Godagudar",
    "ks:ks_pop":9824,
    "ks:ks_type":"VILLAGE",
    "name:eng_x_preferred":[
        "Bar Godagudar"
    ],
    "wof:name":"Bar Godagudar",
    "wof:placetype":"locality",
    "wof:population":9824
},
  "geometry": {"coordinates":[87.82540299999999,22.220617],"type":"Point"}
}