{
  "type": "Feature",
  "properties": {
    "iso:country":"IN",
    "ks:ks_name":"Ghoghriryt",
    "ks:ks_pop":754,
    "ks:ks_type":"HABITATION",
    "name:eng_x_preferred":[
        "Ghoghriryt"
    ],
    "wof:name":"Ghoghriryt",
    "wof:placetype":"locality",
    "wof:population":754
},
  "geometry": {"coordinates":[79.87360200000001,22.54094],"type":"Point"}
}