{
  "type": "Feature",
  "properties": {
    "iso:country":"IN",
    "ks:ks_name":"Barah Kurwa",
    "ks:ks_pop":417,
    "ks:ks_type":"VILLAGE",
    "ks:ks_uagg_main":0,
    "name:eng_x_preferred":[
        "Barah Kurwa"
    ],
    "wof:name":"Barah Kurwa",
    "wof:placetype":"neighbourhood",
    "wof:population":417
},
  "geometry": {"coordinates":[84.627735,24.62967],"type":"Point"}
}