{
  "type": "Feature",
  "properties": {
    "gn:admin1_code":"12.0",
    "gn:admin2_code":"006",
    "gn:asciiname":"Drangar",
    "gn:country_code":"IN",
    "gn:dem":566,
    "gn:feature_class":"P",
    "gn:feature_code":"PPL",
    "gn:name":"Drang\u0101r",
    "gn:population":0,
    "gn:timezone":"Asia/Kolkata",
    "iso:country":"IN",
    "wof:name":"Drangar",
    "wof:placetype":"locality"
},
  "geometry": {"coordinates":[74.36084,33.12349],"type":"Point"}
}