{
  "type": "Feature",
  "properties": {
    "iso:country":"IN",
    "ks:ks_alt_nam":"KHARADEPATILWASTI",
    "ks:ks_name":"Kharadepatilwasti",
    "ks:ks_pop":50,
    "ks:ks_type":"HABITATION",
    "name:eng_x_preferred":[
        "Kharadepatilwasti"
    ],
    "wof:name":"Kharadepatilwasti",
    "wof:placetype":"locality",
    "wof:population":50
},
  "geometry": {"coordinates":[74.63017600000001,17.134905],"type":"Point"}
}