{
  "type": "Feature",
  "properties": {
    "iso:country":"IN",
    "ks:ks_name":"Uniyara",
    "ks:ks_pop":580,
    "ks:ks_type":"VILLAGE",
    "name:eng_x_preferred":[
        "Uniyara"
    ],
    "wof:name":"Uniyara",
    "wof:placetype":"locality",
    "wof:population":580
},
  "geometry": {"coordinates":[79.12913,30.577354],"type":"Point"}
}