{
  "type": "Feature",
  "properties": {
    "gn:admin1_code":"12.0",
    "gn:admin2_code":"010",
    "gn:asciiname":"Mantimahal",
    "gn:country_code":"IN",
    "gn:dem":1586,
    "gn:feature_class":"P",
    "gn:feature_code":"PPL",
    "gn:name":"M\u0101ntimahal",
    "gn:population":0,
    "gn:timezone":"Asia/Kolkata",
    "iso:country":"IN",
    "wof:name":"Mantimahal",
    "wof:placetype":"locality"
},
  "geometry": {"coordinates":[74.86034000000002,34.11753],"type":"Point"}
}