{
  "type": "Feature",
  "properties": {
    "gn:admin1_code":"23.0",
    "gn:admin2_code":"43.0",
    "gn:asciiname":"Shahtirwala",
    "gn:country_code":"IN",
    "gn:dem":181,
    "gn:feature_class":"P",
    "gn:feature_code":"PPL",
    "gn:name":"Sh\u0101htirw\u0101la",
    "gn:population":0,
    "gn:timezone":"Asia/Kolkata",
    "iso:country":"IN",
    "ks:ks_alt_nam":"Sh\u0101htirw\u0101la",
    "ks:ks_name":"Shahtirwala",
    "ks:ks_pop":2261,
    "ks:ks_type":"VILLAGE",
    "ks:ks_uagg_main":0,
    "name:eng_x_preferred":[
        "Shahtirwala"
    ],
    "name:eng_x_variant":[
        "Sh\u0101htirw\u0101la"
    ],
    "wof:name":"Shahtirwala",
    "wof:placetype":"neighbourhood",
    "wof:population":2261
},
  "geometry": {"coordinates":[74.001349,30.270176],"type":"Point"}
}