{
  "type": "Feature",
  "properties": {
    "gn:admin1_code":"25.0",
    "gn:admin2_code":"633.0",
    "gn:asciiname":"Erukkalangattuvalasu",
    "gn:country_code":"IN",
    "gn:dem":232,
    "gn:feature_class":"P",
    "gn:feature_code":"PPL",
    "gn:name":"Erukk\u0101lang\u0101ttuvalasu",
    "gn:population":0,
    "gn:timezone":"Asia/Kolkata",
    "iso:country":"IN",
    "wof:name":"Erukkalangattuvalasu",
    "wof:placetype":"locality"
},
  "geometry": {"coordinates":[77.69155000000001,11.02278],"type":"Point"}
}