{
  "type": "Feature",
  "properties": {
    "iso:country":"IN",
    "ks:ks_name":"Digava Ivarupalli",
    "ks:ks_pop":321,
    "ks:ks_type":"HABITATION",
    "name:eng_x_preferred":[
        "Digava Ivarupalli"
    ],
    "wof:name":"Digava Ivarupalli",
    "wof:placetype":"locality",
    "wof:population":321
},
  "geometry": {"coordinates":[77.840093,13.857201],"type":"Point"}
}