{
  "type": "Feature",
  "properties": {
    "iso:country":"IN",
    "ks:ks_name":"5 SKM-A",
    "ks:ks_pop":130,
    "ks:ks_type":"VILLAGE",
    "name:eng_x_preferred":[
        "5 SKM-A"
    ],
    "wof:name":"5 SKM-A",
    "wof:placetype":"locality",
    "wof:population":130
},
  "geometry": {"coordinates":[72.905681,28.960657],"type":"Point"}
}