{
  "type": "Feature",
  "properties": {
    "gn:admin1_code":"34.0",
    "gn:admin2_code":"220.0",
    "gn:asciiname":"Mayil",
    "gn:country_code":"IN",
    "gn:dem":58,
    "gn:feature_class":"P",
    "gn:feature_code":"PPL",
    "gn:name":"M\u0101yil",
    "gn:population":0,
    "gn:timezone":"Asia/Kolkata",
    "iso:country":"IN",
    "ks:ks_alt_nam":"M\u0101yil",
    "ks:ks_name":"Mayil",
    "ks:ks_pop":5073,
    "ks:ks_type":"VILLAGE",
    "name:eng_x_preferred":[
        "Mayil"
    ],
    "name:eng_x_variant":[
        "M\u0101yil"
    ],
    "wof:name":"Mayil",
    "wof:placetype":"locality",
    "wof:population":5073
},
  "geometry": {"coordinates":[85.29283700000001,25.653298],"type":"Point"}
}