{
  "type": "Feature",
  "properties": {
    "iso:country":"IN",
    "ks:ks_name":"Sikabeda",
    "ks:ks_pop":508,
    "ks:ks_type":"VILLAGE",
    "name:eng_x_preferred":[
        "Sikabeda"
    ],
    "wof:name":"Sikabeda",
    "wof:placetype":"locality",
    "wof:population":508
},
  "geometry": {"coordinates":[86.090969,21.442369],"type":"Point"}
}