{
  "type": "Feature",
  "properties": {
    "iso:country":"IN",
    "ks:ks_name":"Khandar",
    "ks:ks_pop":132,
    "ks:ks_type":"VILLAGE",
    "name:eng_x_preferred":[
        "Khandar"
    ],
    "wof:name":"Khandar",
    "wof:placetype":"locality",
    "wof:population":132
},
  "geometry": {"coordinates":[80.051664,29.881558],"type":"Point"}
}