{
  "type": "Feature",
  "properties": {
    "iso:country":"IN",
    "ks:ks_name":"Kempegowdana Hundi",
    "ks:ks_pop":110,
    "ks:ks_type":"HABITATION",
    "name:eng_x_preferred":[
        "Kempegowdana Hundi"
    ],
    "wof:name":"Kempegowdana Hundi",
    "wof:placetype":"locality",
    "wof:population":110
},
  "geometry": {"coordinates":[76.30982299999999,11.969037],"type":"Point"}
}