{
  "type": "Feature",
  "properties": {
    "iso:country":"IN",
    "ks:ks_name":"Handibhanga",
    "ks:ks_pop":566,
    "ks:ks_type":"VILLAGE",
    "ks:ks_uagg_main":0,
    "name:eng_x_preferred":[
        "Handibhanga"
    ],
    "wof:name":"Handibhanga",
    "wof:placetype":"neighbourhood",
    "wof:population":566
},
  "geometry": {"coordinates":[86.91610300000001,21.92244],"type":"Point"}
}