{
  "type": "Feature",
  "properties": {
    "iso:country":"IN",
    "ks:ks_alt_nam":"KS Electric board colony",
    "ks:ks_name":"Ks Electric Board Colony",
    "ks:ks_pop":120,
    "ks:ks_type":"HABITATION",
    "ks:ks_uagg_main":0,
    "name:eng_x_preferred":[
        "Ks Electric Board Colony"
    ],
    "wof:name":"Ks Electric Board Colony",
    "wof:placetype":"neighbourhood",
    "wof:population":120
},
  "geometry": {"coordinates":[76.974327,9.329693],"type":"Point"}
}