{
  "type": "Feature",
  "properties": {
    "iso:country":"IN",
    "ks:ks_name":"Ravulagaddathanda",
    "ks:ks_pop":66,
    "ks:ks_type":"HABITATION",
    "name:eng_x_preferred":[
        "Ravulagaddathanda"
    ],
    "wof:name":"Ravulagaddathanda",
    "wof:placetype":"locality",
    "wof:population":66
},
  "geometry": {"coordinates":[79.437524,16.636045],"type":"Point"}
}