{
  "type": "Feature",
  "properties": {
    "iso:country":"IN",
    "ks:ks_name":"Panasput",
    "ks:ks_pop":223,
    "ks:ks_type":"HABITATION",
    "name:eng_x_preferred":[
        "Panasput"
    ],
    "wof:name":"Panasput",
    "wof:placetype":"locality",
    "wof:population":223
},
  "geometry": {"coordinates":[82.66602,18.716412],"type":"Point"}
}