{
  "type": "Feature",
  "properties": {
    "gn:admin1_code":"11.0",
    "gn:admin2_code":"32.0",
    "gn:asciiname":"Bhalauna",
    "gn:country_code":"IN",
    "gn:dem":1662,
    "gn:feature_class":"P",
    "gn:feature_code":"PPL",
    "gn:name":"Bhalauna",
    "gn:population":0,
    "gn:timezone":"Asia/Kolkata",
    "iso:country":"IN",
    "wof:name":"Bhalauna",
    "wof:placetype":"locality"
},
  "geometry": {"coordinates":[77.56068,30.73209],"type":"Point"}
}