{
  "type": "Feature",
  "properties": {
    "iso:country":"IN",
    "ks:ks_alt_nam":"Nilegao tanda 2",
    "ks:ks_name":"Nilegao Tanda 2",
    "ks:ks_pop":131,
    "ks:ks_type":"HABITATION",
    "name:eng_x_preferred":[
        "Nilegao Tanda 2"
    ],
    "wof:name":"Nilegao Tanda 2",
    "wof:placetype":"locality",
    "wof:population":131
},
  "geometry": {"coordinates":[76.189667,17.687581],"type":"Point"}
}