{
  "type": "Feature",
  "properties": {
    "iso:country":"IN",
    "ks:ks_name":"Madappadi",
    "ks:ks_pop":9,
    "ks:ks_type":"HABITATION",
    "name:eng_x_preferred":[
        "Madappadi"
    ],
    "wof:name":"Madappadi",
    "wof:placetype":"locality",
    "wof:population":9
},
  "geometry": {"coordinates":[75.20705599999999,12.702078],"type":"Point"}
}