{
  "type": "Feature",
  "properties": {
    "iso:country":"IN",
    "ks:ks_name":"Bandhasahi",
    "ks:ks_pop":305,
    "ks:ks_type":"HABITATION",
    "name:eng_x_preferred":[
        "Bandhasahi"
    ],
    "wof:name":"Bandhasahi",
    "wof:placetype":"locality",
    "wof:population":305
},
  "geometry": {"coordinates":[86.98287500000001,21.82518],"type":"Point"}
}