{
  "type": "Feature",
  "properties": {
    "iso:country":"IN",
    "ks:ks_alt_nam":"PANDEY BAGI TOLA",
    "ks:ks_name":"Pandey Bagi Tola",
    "ks:ks_pop":417,
    "ks:ks_type":"HABITATION",
    "name:eng_x_preferred":[
        "Pandey Bagi Tola"
    ],
    "wof:name":"Pandey Bagi Tola",
    "wof:placetype":"locality",
    "wof:population":417
},
  "geometry": {"coordinates":[85.01536299999999,24.21223],"type":"Point"}
}