{
  "type": "Feature",
  "properties": {
    "gn:admin1_code":"36",
    "gn:admin2_code":"191.0",
    "gn:asciiname":"Raghunathpur",
    "gn:country_code":"IN",
    "gn:dem":81,
    "gn:feature_class":"P",
    "gn:feature_code":"PPL",
    "gn:name":"Ragh\u016bn\u0101thpur",
    "gn:population":0,
    "gn:timezone":"Asia/Kolkata",
    "iso:country":"IN",
    "ks:ks_name":"Raghunathpur",
    "ks:ks_pop":354,
    "ks:ks_type":"VILLAGE",
    "ks:ks_uagg_main":0,
    "name:bpy_x_preferred":[
        "\u09b0\u0998\u09c1\u09a8\u09be\u09a5\u09aa\u09c1\u09b0"
    ],
    "name:ceb_x_preferred":[
        "Raghunathpur"
    ],
    "name:eng_x_preferred":[
        "Raghunathpur"
    ],
    "name:fra_x_preferred":[
        "Raghunathpur"
    ],
    "name:hif_x_preferred":[
        "Raghunathpur"
    ],
    "name:new_x_preferred":[
        "\u0930\u0918\u0941\u0928\u093e\u0925\u092a\u0941\u0930"
    ],
    "name:nld_x_preferred":[
        "Raghunathpur"
    ],
    "name:pol_x_preferred":[
        "Raghunathpur"
    ],
    "name:swe_x_preferred":[
        "Raghunathpur"
    ],
    "wof:name":"Raghunathpur",
    "wof:placetype":"locality",
    "wof:population":354
},
  "geometry": {"coordinates":[83.25131500000001,26.041418],"type":"Point"}
}