{
  "type": "Feature",
  "properties": {
    "iso:country":"IN",
    "ks:ks_name":"Asnasinagha",
    "ks:ks_pop":867,
    "ks:ks_type":"VILLAGE",
    "ks:ks_uagg_main":0,
    "name:eng_x_preferred":[
        "Asnasinagha"
    ],
    "wof:name":"Asnasinagha",
    "wof:placetype":"neighbourhood",
    "wof:population":867
},
  "geometry": {"coordinates":[86.287865,23.876222],"type":"Point"}
}