{
  "type": "Feature",
  "properties": {
    "iso:country":"IN",
    "ks:ks_name":"Chauhanpura",
    "ks:ks_pop":812,
    "ks:ks_type":"HABITATION",
    "name:eng_x_preferred":[
        "Chauhanpura"
    ],
    "wof:name":"Chauhanpura",
    "wof:placetype":"locality",
    "wof:population":812
},
  "geometry": {"coordinates":[72.99766700000001,22.411194],"type":"Point"}
}