{
  "type": "Feature",
  "properties": {
    "iso:country":"IN",
    "ks:ks_name":"Ananden",
    "ks:ks_pop":927,
    "ks:ks_type":"HABITATION",
    "name:eng_x_preferred":[
        "Ananden"
    ],
    "wof:name":"Ananden",
    "wof:placetype":"locality",
    "wof:population":927
},
  "geometry": {"coordinates":[88.193389,27.093721],"type":"Point"}
}