{
  "type": "Feature",
  "properties": {
    "gn:admin1_code":"19",
    "gn:admin2_code":"569.0",
    "gn:asciiname":"Bannadi",
    "gn:country_code":"IN",
    "gn:dem":14,
    "gn:feature_class":"P",
    "gn:feature_code":"PPLL",
    "gn:name":"Bann\u0101di",
    "gn:population":0,
    "gn:timezone":"Asia/Kolkata",
    "iso:country":"IN",
    "ks:ks_name":"Bannadi",
    "ks:ks_pop":179,
    "ks:ks_type":"HABITATION",
    "name:eng_x_preferred":[
        "Bannadi"
    ],
    "wof:name":"Bannadi",
    "wof:placetype":"locality",
    "wof:population":179
},
  "geometry": {"coordinates":[74.722613,13.507877],"type":"Point"}
}