{
  "type": "Feature",
  "properties": {
    "iso:country":"IN",
    "ks:ks_name":"Dalabaripahar",
    "ks:ks_pop":55,
    "ks:ks_type":"VILLAGE",
    "name:eng_x_preferred":[
        "Dalabaripahar"
    ],
    "wof:name":"Dalabaripahar",
    "wof:placetype":"locality",
    "wof:population":55
},
  "geometry": {"coordinates":[87.667092,25.044436],"type":"Point"}
}