{
  "type": "Feature",
  "properties": {
    "iso:country":"IN",
    "ks:ks_name":"Kenchappanapalya",
    "ks:ks_pop":235,
    "ks:ks_type":"HABITATION",
    "name:eng_x_preferred":[
        "Kenchappanapalya"
    ],
    "wof:name":"Kenchappanapalya",
    "wof:placetype":"locality",
    "wof:population":235
},
  "geometry": {"coordinates":[77.09895,14.061492],"type":"Point"}
}