{
  "type": "Feature",
  "properties": {
    "gn:admin1_code":"40.0",
    "gn:admin2_code":"540.0",
    "gn:asciiname":"Kondanapalli",
    "gn:country_code":"IN",
    "gn:dem":187,
    "gn:feature_class":"P",
    "gn:feature_code":"PPL",
    "gn:name":"Kondanapalli",
    "gn:population":0,
    "gn:timezone":"Asia/Kolkata",
    "iso:country":"IN",
    "wof:name":"Kondanapalli",
    "wof:placetype":"locality"
},
  "geometry": {"coordinates":[79.59469,18.40956],"type":"Point"}
}