{
  "type": "Feature",
  "properties": {
    "iso:country":"IN",
    "ks:ks_name":"Bundu",
    "ks:ks_pop":535,
    "ks:ks_type":"VILLAGE",
    "name:eng_x_preferred":[
        "Bundu"
    ],
    "wof:name":"Bundu",
    "wof:placetype":"locality",
    "wof:population":535
},
  "geometry": {"coordinates":[85.394338,22.351163],"type":"Point"}
}