{
  "type": "Feature",
  "properties": {
    "iso:country":"IN",
    "ks:ks_alt_nam":"KUDABURU",
    "ks:ks_name":"Kudaburu",
    "ks:ks_pop":1355,
    "ks:ks_type":"HABITATION",
    "name:eng_x_preferred":[
        "Kudaburu"
    ],
    "wof:name":"Kudaburu",
    "wof:placetype":"locality",
    "wof:population":1355
},
  "geometry": {"coordinates":[85.335488,22.706676],"type":"Point"}
}