{
  "type": "Feature",
  "properties": {
    "iso:country":"IN",
    "ks:ks_name":"Lembujharan",
    "ks:ks_pop":145,
    "ks:ks_type":"VILLAGE",
    "name:eng_x_preferred":[
        "Lembujharan"
    ],
    "wof:name":"Lembujharan",
    "wof:placetype":"locality",
    "wof:population":145
},
  "geometry": {"coordinates":[86.345854,21.845809],"type":"Point"}
}