{
  "type": "Feature",
  "properties": {
    "iso:country":"IN",
    "ks:ks_name":"Gorouli",
    "ks:ks_pop":1102,
    "ks:ks_type":"VILLAGE",
    "ks:ks_uagg_main":0,
    "name:eng_x_preferred":[
        "Gorouli"
    ],
    "wof:name":"Gorouli",
    "wof:placetype":"neighbourhood",
    "wof:population":1102
},
  "geometry": {"coordinates":[83.88650199999999,26.194192],"type":"Point"}
}