{
  "type": "Feature",
  "properties": {
    "iso:country":"IN",
    "ks:ks_name":"Tand Khera",
    "ks:ks_pop":788,
    "ks:ks_type":"HABITATION",
    "name:eng_x_preferred":[
        "Tand Khera"
    ],
    "wof:name":"Tand Khera",
    "wof:placetype":"locality",
    "wof:population":788
},
  "geometry": {"coordinates":[80.787634,26.891853],"type":"Point"}
}