{
  "type": "Feature",
  "properties": {
    "gn:admin1_code":"39.0",
    "gn:admin2_code":"64.0",
    "gn:asciiname":"Pipalkhal",
    "gn:country_code":"IN",
    "gn:dem":1173,
    "gn:feature_class":"P",
    "gn:feature_code":"PPL",
    "gn:name":"Pipalkh\u0101l",
    "gn:population":0,
    "gn:timezone":"Asia/Kolkata",
    "iso:country":"IN",
    "ks:ks_name":"Pipalkhal",
    "ks:ks_pop":274,
    "ks:ks_type":"VILLAGE",
    "name:eng_x_preferred":[
        "Pipalkhal"
    ],
    "wof:name":"Pipalkhal",
    "wof:placetype":"locality",
    "wof:population":274
},
  "geometry": {"coordinates":[79.185624,29.827157],"type":"Point"}
}