{
  "type": "Feature",
  "properties": {
    "gn:admin1_code":"38.0",
    "gn:admin2_code":"352.0",
    "gn:asciiname":"Parsa",
    "gn:country_code":"IN",
    "gn:dem":123,
    "gn:feature_class":"P",
    "gn:feature_code":"PPL",
    "gn:name":"Parsa",
    "gn:population":0,
    "gn:timezone":"Asia/Kolkata",
    "iso:country":"IN",
    "ks:ks_name":"Parsa",
    "ks:ks_pop":143,
    "ks:ks_type":"VILLAGE",
    "name:bak_x_preferred":[
        "\u041f\u0430\u0440\u0441\u0430"
    ],
    "name:cat_x_preferred":[
        "Parsuwaix"
    ],
    "name:ceb_x_preferred":[
        "Parsa"
    ],
    "name:deu_x_preferred":[
        "Parsa"
    ],
    "name:eng_x_preferred":[
        "Parsa"
    ],
    "name:fas_x_preferred":[
        "\u067e\u0627\u0631\u0633\u0627"
    ],
    "name:hin_x_preferred":[
        "\u092a\u0930\u094d\u0938\u093e"
    ],
    "name:rus_x_preferred":[
        "\u041f\u0430\u0440\u0441\u0430"
    ],
    "name:swe_x_preferred":[
        "Parsa"
    ],
    "wof:name":"Parsa",
    "wof:placetype":"locality",
    "wof:population":143
},
  "geometry": {"coordinates":[87.530856,25.075013],"type":"Point"}
}