{
  "type": "Feature",
  "properties": {
    "iso:country":"IN",
    "ks:ks_name":"Hojeagewasti",
    "ks:ks_pop":91,
    "ks:ks_type":"HABITATION",
    "name:eng_x_preferred":[
        "Hojeagewasti"
    ],
    "wof:name":"Hojeagewasti",
    "wof:placetype":"locality",
    "wof:population":91
},
  "geometry": {"coordinates":[73.770809,18.982149],"type":"Point"}
}