{
  "type": "Feature",
  "properties": {
    "iso:country":"IN",
    "ks:ks_alt_nam":"PARA KWTAL",
    "ks:ks_name":"Para Kwtal",
    "ks:ks_pop":17,
    "ks:ks_type":"HABITATION",
    "name:eng_x_preferred":[
        "Para Kwtal"
    ],
    "wof:name":"Para Kwtal",
    "wof:placetype":"locality",
    "wof:population":17
},
  "geometry": {"coordinates":[91.52618099999999,23.894685],"type":"Point"}
}