{
  "type": "Feature",
  "properties": {
    "gn:admin1_code":"34",
    "gn:admin2_code":"218.0",
    "gn:asciiname":"Kajrasan",
    "gn:country_code":"IN",
    "gn:dem":66,
    "gn:feature_class":"P",
    "gn:feature_code":"PPL",
    "gn:name":"Kajr\u0101san",
    "gn:population":0,
    "gn:timezone":"Asia/Kolkata",
    "iso:country":"IN",
    "wof:name":"Kajrasan",
    "wof:placetype":"locality"
},
  "geometry": {"coordinates":[84.33785,26.00457],"type":"Point"}
}