{
  "type": "Feature",
  "properties": {
    "iso:country":"IN",
    "ks:ks_name":"Nankao Purwa",
    "ks:ks_pop":94,
    "ks:ks_type":"HABITATION",
    "name:eng_x_preferred":[
        "Nankao Purwa"
    ],
    "wof:name":"Nankao Purwa",
    "wof:placetype":"locality",
    "wof:population":94
},
  "geometry": {"coordinates":[81.453024,27.354274],"type":"Point"}
}