{
  "type": "Feature",
  "properties": {
    "iso:country":"IN",
    "ks:ks_name":"Lower Soreng",
    "ks:ks_pop":815,
    "ks:ks_type":"HABITATION",
    "name:eng_x_preferred":[
        "Lower Soreng"
    ],
    "wof:name":"Lower Soreng",
    "wof:placetype":"locality",
    "wof:population":815
},
  "geometry": {"coordinates":[88.416552,27.037005],"type":"Point"}
}