{
  "type": "Feature",
  "properties": {
    "iso:country":"IN",
    "ks:ks_name":"Kondabamreng",
    "ks:ks_pop":74,
    "ks:ks_type":"VILLAGE",
    "name:eng_x_preferred":[
        "Kondabamreng"
    ],
    "wof:name":"Kondabamreng",
    "wof:placetype":"locality",
    "wof:population":74
},
  "geometry": {"coordinates":[82.190077,18.301475],"type":"Point"}
}