{
  "type": "Feature",
  "properties": {
    "iso:country":"IN",
    "ks:ks_alt_nam":"thakarepada",
    "ks:ks_name":"Thakarepada",
    "ks:ks_pop":55,
    "ks:ks_type":"HABITATION",
    "name:eng_x_preferred":[
        "Thakarepada"
    ],
    "wof:name":"Thakarepada",
    "wof:placetype":"locality",
    "wof:population":55
},
  "geometry": {"coordinates":[73.08511900000001,19.554292],"type":"Point"}
}