{
  "type": "Feature",
  "properties": {
    "gn:admin1_code":"19.0",
    "gn:admin2_code":"583.0",
    "gn:asciiname":"Kondasandra",
    "gn:country_code":"IN",
    "gn:dem":927,
    "gn:feature_class":"P",
    "gn:feature_code":"PPL",
    "gn:name":"Kondasandra",
    "gn:population":0,
    "gn:timezone":"Asia/Kolkata",
    "iso:country":"IN",
    "wof:name":"Kondasandra",
    "wof:placetype":"locality"
},
  "geometry": {"coordinates":[77.57052,13.38153],"type":"Point"}
}