{
  "type": "Feature",
  "properties": {
    "iso:country":"IN",
    "ks:ks_name":"Shaistapur",
    "ks:ks_pop":1089,
    "ks:ks_type":"HABITATION",
    "name:eng_x_preferred":[
        "Shaistapur"
    ],
    "wof:name":"Shaistapur",
    "wof:placetype":"locality",
    "wof:population":1089
},
  "geometry": {"coordinates":[85.32465000000001,25.52623],"type":"Point"}
}