{
  "type": "Feature",
  "properties": {
    "iso:country":"IN",
    "ks:ks_name":"Benajira",
    "ks:ks_pop":441,
    "ks:ks_type":"VILLAGE",
    "name:eng_x_preferred":[
        "Benajira"
    ],
    "wof:name":"Benajira",
    "wof:placetype":"locality",
    "wof:population":441
},
  "geometry": {"coordinates":[87.06731499999999,23.17974],"type":"Point"}
}