{
  "type": "Feature",
  "properties": {
    "gn:admin1_code":"24.0",
    "gn:admin2_code":"102",
    "gn:asciiname":"Karuwasar",
    "gn:country_code":"IN",
    "gn:dem":285,
    "gn:feature_class":"P",
    "gn:feature_code":"PPL",
    "gn:name":"Karuw\u0101sar",
    "gn:population":0,
    "gn:timezone":"Asia/Kolkata",
    "iso:country":"IN",
    "name:und_x_variant":[
        "Karuw\u0101sar",
        "Karwasir"
    ],
    "wof:name":"Karuwasar",
    "wof:placetype":"locality"
},
  "geometry": {"coordinates":[74.98424,28.36058],"type":"Point"}
}