{
  "type": "Feature",
  "properties": {
    "iso:country":"IN",
    "ks:ks_name":"Koldi",
    "ks:ks_pop":346,
    "ks:ks_type":"VILLAGE",
    "ks:ks_uagg_main":0,
    "name:eng_x_preferred":[
        "Koldi"
    ],
    "wof:name":"Koldi",
    "wof:placetype":"neighbourhood",
    "wof:population":346
},
  "geometry": {"coordinates":[86.450951,23.243642],"type":"Point"}
}