{
  "type": "Feature",
  "properties": {
    "iso:country":"IN",
    "ks:ks_name":"Raja Deeh",
    "ks:ks_pop":200,
    "ks:ks_type":"HABITATION",
    "name:eng_x_preferred":[
        "Raja Deeh"
    ],
    "wof:name":"Raja Deeh",
    "wof:placetype":"locality",
    "wof:population":200
},
  "geometry": {"coordinates":[82.957362,27.318033],"type":"Point"}
}