{
  "type": "Feature",
  "properties": {
    "iso:country":"IN",
    "ks:ks_name":"Ringani",
    "ks:ks_pop":5,
    "ks:ks_type":"VILLAGE",
    "name:eng_x_preferred":[
        "Ringani"
    ],
    "wof:name":"Ringani",
    "wof:placetype":"locality",
    "wof:population":5
},
  "geometry": {"coordinates":[78.731022,20.856918],"type":"Point"}
}