{
  "type": "Feature",
  "properties": {
    "iso:country":"IN",
    "ks:ks_name":"Harijanwadi",
    "ks:ks_pop":181,
    "ks:ks_type":"HABITATION",
    "name:eng_x_preferred":[
        "Harijanwadi"
    ],
    "wof:name":"Harijanwadi",
    "wof:placetype":"locality",
    "wof:population":181
},
  "geometry": {"coordinates":[73.686741,15.858839],"type":"Point"}
}