{
  "type": "Feature",
  "properties": {
    "iso:country":"IN",
    "ks:ks_alt_nam":"GORE WASTI",
    "ks:ks_name":"Gore Wasti",
    "ks:ks_pop":164,
    "ks:ks_type":"HABITATION",
    "name:eng_x_preferred":[
        "Gore Wasti"
    ],
    "wof:name":"Gore Wasti",
    "wof:placetype":"locality",
    "wof:population":164
},
  "geometry": {"coordinates":[74.91803,19.25301],"type":"Point"}
}