{
  "type": "Feature",
  "properties": {
    "iso:country":"IN",
    "ks:ks_name":"Hootanajanmane",
    "ks:ks_pop":111,
    "ks:ks_type":"HABITATION",
    "name:eng_x_preferred":[
        "Hootanajanmane"
    ],
    "wof:name":"Hootanajanmane",
    "wof:placetype":"locality",
    "wof:population":111
},
  "geometry": {"coordinates":[74.785296,14.596746],"type":"Point"}
}