{
  "type": "Feature",
  "properties": {
    "gn:admin1_code":"34.0",
    "gn:admin2_code":"228.0",
    "gn:asciiname":"Kamalgarh",
    "gn:country_code":"IN",
    "gn:dem":51,
    "gn:feature_class":"P",
    "gn:feature_code":"PPL",
    "gn:name":"Kamalgarh",
    "gn:population":0,
    "gn:timezone":"Asia/Kolkata",
    "iso:country":"IN",
    "wof:name":"Kamalgarh",
    "wof:placetype":"locality"
},
  "geometry": {"coordinates":[85.89584000000001,25.11709],"type":"Point"}
}