{
  "type": "Feature",
  "properties": {
    "iso:country":"IN",
    "ks:ks_alt_nam":"Ul\u0101tu",
    "ks:ks_name":"Ulatu",
    "ks:ks_pop":1042,
    "ks:ks_type":"VILLAGE",
    "name:eng_x_preferred":[
        "Ulatu"
    ],
    "name:eng_x_variant":[
        "Ul\u0101tu"
    ],
    "wof:name":"Ulatu",
    "wof:placetype":"locality",
    "wof:population":1042
},
  "geometry": {"coordinates":[85.430414,23.189903],"type":"Point"}
}