{
  "type": "Feature",
  "properties": {
    "iso:country":"IN",
    "ks:ks_alt_nam":"Yedewasti pimpalachamala",
    "ks:ks_name":"Yedewasti Pimpalachamala",
    "ks:ks_pop":381,
    "ks:ks_type":"HABITATION",
    "name:eng_x_preferred":[
        "Yedewasti Pimpalachamala"
    ],
    "wof:name":"Yedewasti Pimpalachamala",
    "wof:placetype":"locality",
    "wof:population":381
},
  "geometry": {"coordinates":[74.45050000000001,18.2503],"type":"Point"}
}