{
  "type": "Feature",
  "properties": {
    "iso:country":"IN",
    "ks:ks_name":"Singipur",
    "ks:ks_pop":543,
    "ks:ks_type":"VILLAGE",
    "ks:ks_uagg_main":0,
    "name:eng_x_preferred":[
        "Singipur"
    ],
    "wof:name":"Singipur",
    "wof:placetype":"neighbourhood",
    "wof:population":543
},
  "geometry": {"coordinates":[85.14505699999999,19.669725],"type":"Point"}
}