{
  "type": "Feature",
  "properties": {
    "iso:country":"IN",
    "ks:ks_name":"Kaliyavad",
    "ks:ks_pop":3211,
    "ks:ks_type":"VILLAGE",
    "name:eng_x_preferred":[
        "Kaliyavad"
    ],
    "wof:name":"Kaliyavad",
    "wof:placetype":"locality",
    "wof:population":3211
},
  "geometry": {"coordinates":[74.11063900000001,22.738778],"type":"Point"}
}