{
  "type": "Feature",
  "properties": {
    "gn:admin1_code":"19.0",
    "gn:admin2_code":"555.0",
    "gn:asciiname":"Yenagi",
    "gn:country_code":"IN",
    "gn:dem":651,
    "gn:feature_class":"P",
    "gn:feature_code":"PPL",
    "gn:name":"Yenagi",
    "gn:population":0,
    "gn:timezone":"Asia/Kolkata",
    "iso:country":"IN",
    "name:kan_x_preferred":[
        "\u0c8e\u0ca8\u0c97\u0cbf"
    ],
    "name:urd_x_preferred":[
        "\u06cc\u0646\u06af\u06cc"
    ],
    "wof:name":"Yenagi",
    "wof:placetype":"locality"
},
  "geometry": {"coordinates":[74.96173,15.75777],"type":"Point"}
}