{
  "type": "Feature",
  "properties": {
    "iso:country":"IN",
    "ks:ks_name":"Jagdalewasti",
    "ks:ks_pop":249,
    "ks:ks_type":"HABITATION",
    "name:eng_x_preferred":[
        "Jagdalewasti"
    ],
    "wof:name":"Jagdalewasti",
    "wof:placetype":"locality",
    "wof:population":249
},
  "geometry": {"coordinates":[74.851766,18.786992],"type":"Point"}
}