{
  "type": "Feature",
  "properties": {
    "iso:country":"IN",
    "ks:ks_name":"Adiwasiwadi",
    "ks:ks_pop":58,
    "ks:ks_type":"HABITATION",
    "name:eng_x_preferred":[
        "Adiwasiwadi"
    ],
    "wof:name":"Adiwasiwadi",
    "wof:placetype":"locality",
    "wof:population":58
},
  "geometry": {"coordinates":[73.500083,18.091556],"type":"Point"}
}