{
  "type": "Feature",
  "properties": {
    "gn:admin1_code":"19.0",
    "gn:admin2_code":"570.0",
    "gn:asciiname":"Tanudi",
    "gn:country_code":"IN",
    "gn:dem":844,
    "gn:feature_class":"P",
    "gn:feature_code":"PPL",
    "gn:name":"Tan\u016bdi",
    "gn:population":0,
    "gn:timezone":"Asia/Kolkata",
    "iso:country":"IN",
    "ks:ks_name":"Thanudi",
    "ks:ks_pop":432,
    "ks:ks_type":"VILLAGE",
    "name:eng_x_preferred":[
        "Thanudi"
    ],
    "name:eng_x_variant":[
        "Tanudi"
    ],
    "wof:name":"Thanudi",
    "wof:placetype":"locality",
    "wof:population":432
},
  "geometry": {"coordinates":[75.421004,13.295501],"type":"Point"}
}