{
  "type": "Feature",
  "properties": {
    "gn:admin1_code":"19.0",
    "gn:admin2_code":"570.0",
    "gn:asciiname":"Tanudi",
    "gn:country_code":"IN",
    "gn:dem":844,
    "gn:feature_class":"P",
    "gn:feature_code":"PPL",
    "gn:name":"Tan\u016bdi",
    "gn:population":0,
    "gn:timezone":"Asia/Kolkata",
    "iso:country":"IN",
    "wof:name":"Tanudi",
    "wof:placetype":"locality"
},
  "geometry": {"coordinates":[75.41920999999998,13.29195],"type":"Point"}
}