{
  "type": "Feature",
  "properties": {
    "gn:admin1_code":"34.0",
    "gn:admin2_code":"235.0",
    "gn:asciiname":"Kolhua",
    "gn:country_code":"IN",
    "gn:dem":126,
    "gn:feature_class":"P",
    "gn:feature_code":"PPL",
    "gn:name":"Kolhua",
    "gn:population":0,
    "gn:timezone":"Asia/Kolkata",
    "iso:country":"IN",
    "wof:name":"Kolhua",
    "wof:placetype":"locality"
},
  "geometry": {"coordinates":[84.61086,24.68068],"type":"Point"}
}