{
  "type": "Feature",
  "properties": {
    "iso:country":"IN",
    "ks:ks_name":"Harridih",
    "ks:ks_pop":78,
    "ks:ks_type":"VILLAGE",
    "name:eng_x_preferred":[
        "Harridih"
    ],
    "wof:name":"Harridih",
    "wof:placetype":"locality",
    "wof:population":78
},
  "geometry": {"coordinates":[82.28887,23.567474],"type":"Point"}
}