{
  "type": "Feature",
  "properties": {
    "iso:country":"IN",
    "ks:ks_name":"Ninrdi",
    "ks:ks_pop":200,
    "ks:ks_type":"HABITATION",
    "name:eng_x_preferred":[
        "Ninrdi"
    ],
    "wof:name":"Ninrdi",
    "wof:placetype":"locality",
    "wof:population":200
},
  "geometry": {"coordinates":[75.334318,13.063845],"type":"Point"}
}