{
  "type": "Feature",
  "properties": {
    "iso:country":"IN",
    "ks:ks_name":"Line Pod",
    "ks:ks_pop":64,
    "ks:ks_type":"HABITATION",
    "name:eng_x_preferred":[
        "Line Pod"
    ],
    "wof:name":"Line Pod",
    "wof:placetype":"locality",
    "wof:population":64
},
  "geometry": {"coordinates":[78.69548399999999,20.106195],"type":"Point"}
}