{
  "type": "Feature",
  "properties": {
    "iso:country":"IN",
    "ks:ks_name":"Bhom Bagseu",
    "ks:ks_pop":354,
    "ks:ks_type":"VILLAGE",
    "ks:ks_uagg_main":0,
    "name:eng_x_preferred":[
        "Bhom Bagseu"
    ],
    "wof:name":"Bhom Bagseu",
    "wof:placetype":"neighbourhood",
    "wof:population":354
},
  "geometry": {"coordinates":[73.805638,27.596505],"type":"Point"}
}