{
  "type": "Feature",
  "properties": {
    "iso:country":"IN",
    "ks:ks_name":"Khadikasol",
    "ks:ks_pop":183,
    "ks:ks_type":"VILLAGE",
    "name:eng_x_preferred":[
        "Khadikasol"
    ],
    "wof:name":"Khadikasol",
    "wof:placetype":"locality",
    "wof:population":183
},
  "geometry": {"coordinates":[86.91090800000001,21.786494],"type":"Point"}
}