{
  "type": "Feature",
  "properties": {
    "iso:country":"IN",
    "ks:ks_name":"Manik Munda",
    "ks:ks_pop":0,
    "ks:ks_type":"VILLAGE",
    "name:eng_x_preferred":[
        "Manik Munda"
    ],
    "wof:name":"Manik Munda",
    "wof:placetype":"locality",
    "wof:population":0
},
  "geometry": {"coordinates":[85.862347,24.291856],"type":"Point"}
}