{
  "type": "Feature",
  "properties": {
    "iso:country":"IN",
    "ks:ks_name":"Najama Dih",
    "ks:ks_pop":140,
    "ks:ks_type":"HABITATION",
    "name:eng_x_preferred":[
        "Najama Dih"
    ],
    "wof:name":"Najama Dih",
    "wof:placetype":"locality",
    "wof:population":140
},
  "geometry": {"coordinates":[84.504462,24.341155],"type":"Point"}
}