{
  "type": "Feature",
  "properties": {
    "gn:admin1_code":"19.0",
    "gn:admin2_code":"563.0",
    "gn:asciiname":"Swarnagadde",
    "gn:country_code":"IN",
    "gn:dem":7,
    "gn:feature_class":"P",
    "gn:feature_code":"PPL",
    "gn:name":"Swarnagadde",
    "gn:population":0,
    "gn:timezone":"Asia/Kolkata",
    "iso:country":"IN",
    "ks:ks_name":"Suvarna Gadde",
    "ks:ks_pop":194,
    "ks:ks_type":"HABITATION",
    "name:eng_x_preferred":[
        "Suvarna Gadde"
    ],
    "name:eng_x_variant":[
        "Swarnagadde"
    ],
    "wof:name":"Suvarna Gadde",
    "wof:placetype":"locality",
    "wof:population":194
},
  "geometry": {"coordinates":[74.411941,14.352145],"type":"Point"}
}