{
  "type": "Feature",
  "properties": {
    "gn:admin1_code":"35",
    "gn:admin2_code":"447.0",
    "gn:asciiname":"Sonadeh",
    "gn:country_code":"IN",
    "gn:dem":425,
    "gn:feature_class":"P",
    "gn:feature_code":"PPL",
    "gn:name":"Son\u0101deh",
    "gn:population":0,
    "gn:timezone":"Asia/Kolkata",
    "iso:country":"IN",
    "ks:ks_alt_nam":"Son\u0101deh",
    "ks:ks_name":"Sonadeh",
    "ks:ks_pop":619,
    "ks:ks_type":"VILLAGE",
    "name:eng_x_preferred":[
        "Sonadeh"
    ],
    "name:eng_x_variant":[
        "Son\u0101deh"
    ],
    "wof:name":"Sonadeh",
    "wof:placetype":"locality",
    "wof:population":619
},
  "geometry": {"coordinates":[77.80947500000001,22.261492],"type":"Point"}
}