{
  "type": "Feature",
  "properties": {
    "iso:country":"IN",
    "ks:ks_name":"Dugasara",
    "ks:ks_pop":92,
    "ks:ks_type":"VILLAGE",
    "name:eng_x_preferred":[
        "Dugasara"
    ],
    "wof:name":"Dugasara",
    "wof:placetype":"locality",
    "wof:population":92
},
  "geometry": {"coordinates":[79.35003,24.287423],"type":"Point"}
}