{
  "type": "Feature",
  "properties": {
    "gn:admin1_code":"28.0",
    "gn:admin2_code":"339",
    "gn:asciiname":"Bankadaha",
    "gn:country_code":"IN",
    "gn:dem":64,
    "gn:feature_class":"P",
    "gn:feature_code":"PPL",
    "gn:name":"B\u0101nk\u0101d\u0101ha",
    "gn:population":0,
    "gn:timezone":"Asia/Kolkata",
    "iso:country":"IN",
    "wof:name":"Bankadaha",
    "wof:placetype":"locality"
},
  "geometry": {"coordinates":[87.35786999999998,22.97927],"type":"Point"}
}