{
  "type": "Feature",
  "properties": {
    "gn:admin1_code":"36.0",
    "gn:admin2_code":"136.0",
    "gn:asciiname":"Khabaria",
    "gn:country_code":"IN",
    "gn:dem":217,
    "gn:feature_class":"P",
    "gn:feature_code":"PPL",
    "gn:name":"Khabaria",
    "gn:population":0,
    "gn:timezone":"Asia/Kolkata",
    "iso:country":"IN",
    "ks:ks_name":"Khabaria",
    "ks:ks_type":"VILLAGE",
    "name:eng_x_preferred":[
        "Khabaria"
    ],
    "name:und_x_variant":[
        "Shams\u0101b\u0101d"
    ],
    "wof:name":"Khabaria",
    "wof:placetype":"locality"
},
  "geometry": {"coordinates":[78.997556,29.100042],"type":"Point"}
}