{
  "type": "Feature",
  "properties": {
    "iso:country":"IN",
    "ks:ks_name":"Dumuripadar",
    "ks:ks_pop":102,
    "ks:ks_type":"VILLAGE",
    "name:eng_x_preferred":[
        "Dumuripadar"
    ],
    "wof:name":"Dumuripadar",
    "wof:placetype":"locality",
    "wof:population":102
},
  "geometry": {"coordinates":[83.276326,19.44471],"type":"Point"}
}