{
  "type": "Feature",
  "properties": {
    "gn:admin1_code":"13.0",
    "gn:admin2_code":"594.0",
    "gn:asciiname":"Teruvalayanur",
    "gn:country_code":"IN",
    "gn:dem":16,
    "gn:feature_class":"P",
    "gn:feature_code":"PPL",
    "gn:name":"Teruvalayan\u016br",
    "gn:population":0,
    "gn:timezone":"Asia/Kolkata",
    "iso:country":"IN",
    "wof:name":"Teruvalayanur",
    "wof:placetype":"locality"
},
  "geometry": {"coordinates":[76.00291999999997,10.65302],"type":"Point"}
}