{
  "type": "Feature",
  "properties": {
    "iso:country":"IN",
    "ks:ks_alt_nam":"\u0100nkun",
    "ks:ks_name":"Ankun",
    "ks:ks_type":"VILLAGE",
    "name:eng_x_preferred":[
        "Ankun"
    ],
    "name:eng_x_variant":[
        "\u0100nkun"
    ],
    "wof:name":"Ankun",
    "wof:placetype":"locality"
},
  "geometry": {"coordinates":[84.11782100000001,20.671642],"type":"Point"}
}