{
  "type": "Feature",
  "properties": {
    "iso:country":"IN",
    "ks:ks_alt_nam":"Tel\u012bpura",
    "ks:ks_name":"Telipura",
    "ks:ks_type":"VILLAGE",
    "name:eng_x_preferred":[
        "Telipura"
    ],
    "name:eng_x_variant":[
        "Tel\u012bpura"
    ],
    "wof:name":"Telipura",
    "wof:placetype":"locality"
},
  "geometry": {"coordinates":[78.34179899999999,28.82026],"type":"Point"}
}