{
  "type": "Feature",
  "properties": {
    "iso:country":"IN",
    "ks:ks_name":"Ahmadabad",
    "ks:ks_pop":1,
    "ks:ks_type":"VILLAGE",
    "name:eng_x_preferred":[
        "Ahmadabad"
    ],
    "wof:name":"Ahmadabad",
    "wof:placetype":"locality",
    "wof:population":1
},
  "geometry": {"coordinates":[77.990726,21.29904],"type":"Point"}
}