{
  "type": "Feature",
  "properties": {
    "gn:admin1_code":"19.0",
    "gn:admin2_code":"570.0",
    "gn:asciiname":"Bhandigadi",
    "gn:country_code":"IN",
    "gn:dem":656,
    "gn:feature_class":"P",
    "gn:feature_code":"PPL",
    "gn:name":"Bhandigadi",
    "gn:population":0,
    "gn:timezone":"Asia/Kolkata",
    "iso:country":"IN",
    "name:kan_x_preferred":[
        "\u0cad\u0c82\u0ca1\u0cbf\u0c97\u0ca1\u0cbf"
    ],
    "name:vie_x_preferred":[
        "Bhandigadi"
    ],
    "wof:name":"Bhandigadi",
    "wof:placetype":"locality"
},
  "geometry": {"coordinates":[75.28308,13.56982],"type":"Point"}
}