{
  "type": "Feature",
  "properties": {
    "gn:admin1_code":"19.0",
    "gn:admin2_code":"572.0",
    "gn:asciiname":"Agara",
    "gn:country_code":"IN",
    "gn:dem":767,
    "gn:feature_class":"P",
    "gn:feature_code":"PPL",
    "gn:name":"Agara",
    "gn:population":0,
    "gn:timezone":"Asia/Kolkata",
    "iso:country":"IN",
    "ks:ks_name":"Agara",
    "ks:ks_pop":3612,
    "ks:ks_type":"VILLAGE",
    "ks:ks_uagg_main":1,
    "name:ceb_x_preferred":[
        "Agara"
    ],
    "name:eng_x_preferred":[
        "Agara"
    ],
    "name:swe_x_preferred":[
        "Agara"
    ],
    "wof:name":"Agara",
    "wof:placetype":"locality",
    "wof:population":3612
},
  "geometry": {"coordinates":[77.50392600000001,12.832143],"type":"Point"}
}