{
  "type": "Feature",
  "properties": {
    "iso:country":"IN",
    "ks:ks_name":"T Pappankulam",
    "ks:ks_pop":98,
    "ks:ks_type":"HABITATION",
    "name:eng_x_preferred":[
        "T Pappankulam"
    ],
    "wof:name":"T Pappankulam",
    "wof:placetype":"locality",
    "wof:population":98
},
  "geometry": {"coordinates":[78.365498,9.503628],"type":"Point"}
}