{
  "type": "Feature",
  "properties": {
    "iso:country":"IN",
    "ks:ks_name":"Byrapura",
    "ks:ks_type":"VILLAGE",
    "name:eng_x_preferred":[
        "Byrapura"
    ],
    "wof:name":"Byrapura",
    "wof:placetype":"locality"
},
  "geometry": {"coordinates":[76.13189800000001,13.343662],"type":"Point"}
}