{
  "type": "Feature",
  "properties": {
    "iso:country":"IN",
    "ks:ks_name":"Talagopbindha",
    "ks:ks_pop":2206,
    "ks:ks_type":"VILLAGE",
    "name:eng_x_preferred":[
        "Talagopbindha"
    ],
    "wof:name":"Talagopbindha",
    "wof:placetype":"locality",
    "wof:population":2206
},
  "geometry": {"coordinates":[86.55600200000001,20.97113],"type":"Point"}
}