{
  "type": "Feature",
  "properties": {
    "iso:country":"IN",
    "ks:ks_name":"Sarwani Jagir",
    "ks:ks_pop":913,
    "ks:ks_type":"VILLAGE",
    "name:eng_x_preferred":[
        "Sarwani Jagir"
    ],
    "wof:name":"Sarwani Jagir",
    "wof:placetype":"locality",
    "wof:population":913
},
  "geometry": {"coordinates":[75.053956,23.191814],"type":"Point"}
}