{
  "type": "Feature",
  "properties": {
    "iso:country":"IN",
    "ks:ks_name":"Farabari",
    "ks:ks_pop":559,
    "ks:ks_type":"HABITATION",
    "name:eng_x_preferred":[
        "Farabari"
    ],
    "wof:name":"Farabari",
    "wof:placetype":"locality",
    "wof:population":559
},
  "geometry": {"coordinates":[88.272229,26.601784],"type":"Point"}
}