{
  "type": "Feature",
  "properties": {
    "gn:admin1_code":"39.0",
    "gn:admin2_code":"66.0",
    "gn:asciiname":"Kholgadda Got",
    "gn:country_code":"IN",
    "gn:dem":596,
    "gn:feature_class":"P",
    "gn:feature_code":"PPL",
    "gn:name":"Kholgadda Got",
    "gn:population":0,
    "gn:timezone":"Asia/Kolkata",
    "iso:country":"IN",
    "wof:name":"Kholgadda Got",
    "wof:placetype":"locality"
},
  "geometry": {"coordinates":[79.84746,29.14957],"type":"Point"}
}