{
  "type": "Feature",
  "properties": {
    "iso:country":"IN",
    "ks:ks_name":"Damgram",
    "ks:ks_pop":327,
    "ks:ks_type":"HABITATION",
    "ks:ks_uagg_main":0,
    "name:eng_x_preferred":[
        "Damgram"
    ],
    "wof:name":"Damgram",
    "wof:placetype":"neighbourhood",
    "wof:population":327
},
  "geometry": {"coordinates":[86.806297,22.179424],"type":"Point"}
}