{
  "type": "Feature",
  "properties": {
    "iso:country":"IN",
    "ks:ks_name":"Jayanti Colony",
    "ks:ks_pop":181,
    "ks:ks_type":"HABITATION",
    "name:eng_x_preferred":[
        "Jayanti Colony"
    ],
    "wof:name":"Jayanti Colony",
    "wof:placetype":"locality",
    "wof:population":181
},
  "geometry": {"coordinates":[74.777598,14.600731],"type":"Point"}
}