{
  "type": "Feature",
  "properties": {
    "gn:admin1_code":"38.0",
    "gn:admin2_code":"353.0",
    "gn:asciiname":"Beldanga",
    "gn:country_code":"IN",
    "gn:dem":39,
    "gn:feature_class":"P",
    "gn:feature_code":"PPL",
    "gn:name":"Beld\u0101nga",
    "gn:population":0,
    "gn:timezone":"Asia/Kolkata",
    "iso:country":"IN",
    "ks:ks_alt_nam":"Beld\u0101nga",
    "ks:ks_name":"Beldanga",
    "ks:ks_pop":84,
    "ks:ks_type":"VILLAGE",
    "ks:ks_uagg_main":0,
    "name:ben_x_preferred":[
        "\u09ac\u09c7\u09b2\u09a1\u09be\u0999\u09be"
    ],
    "name:bpy_x_preferred":[
        "\u09ac\u09c7\u09b2\u09a1\u09be\u0999\u09be"
    ],
    "name:ceb_x_preferred":[
        "Beld\u0101nga"
    ],
    "name:eng_x_preferred":[
        "Beldanga"
    ],
    "name:eng_x_variant":[
        "Beld\u0101nga"
    ],
    "name:fra_x_preferred":[
        "Beldanga"
    ],
    "name:ita_x_preferred":[
        "Beldanga"
    ],
    "name:msa_x_preferred":[
        "Beldanga"
    ],
    "name:new_x_preferred":[
        "\u092c\u0947\u0932\u094d\u0926\u0902\u0917\u093e"
    ],
    "name:por_x_preferred":[
        "Beldanga"
    ],
    "name:spa_x_preferred":[
        "Beldanga"
    ],
    "name:swe_x_preferred":[
        "Beld\u0101nga"
    ],
    "name:vie_x_preferred":[
        "Beldanga"
    ],
    "name:zho_x_preferred":[
        "\u8d1d\u5c14\u5f53\u683c\u963f"
    ],
    "wof:name":"Beldanga",
    "wof:placetype":"neighbourhood",
    "wof:population":84
},
  "geometry": {"coordinates":[87.85210600000001,24.625156],"type":"Point"}
}