{
  "type": "Feature",
  "properties": {
    "iso:country":"IN",
    "ks:ks_name":"Bagbeda1",
    "ks:ks_pop":597,
    "ks:ks_type":"HABITATION",
    "name:eng_x_preferred":[
        "Bagbeda1"
    ],
    "wof:name":"Bagbeda1",
    "wof:placetype":"locality",
    "wof:population":597
},
  "geometry": {"coordinates":[82.238767,18.787244],"type":"Point"}
}