{
  "type": "Feature",
  "properties": {
    "iso:country":"IN",
    "ks:ks_name":"Mothiguda",
    "ks:ks_pop":33,
    "ks:ks_type":"HABITATION",
    "name:eng_x_preferred":[
        "Mothiguda"
    ],
    "wof:name":"Mothiguda",
    "wof:placetype":"locality",
    "wof:population":33
},
  "geometry": {"coordinates":[79.272519,19.198266],"type":"Point"}
}