{
  "type": "Feature",
  "properties": {
    "iso:country":"IN",
    "ks:ks_name":"Karivali",
    "ks:ks_pop":12932,
    "ks:ks_type":"URBAN",
    "ks:ks_uagg_main":0,
    "name:eng_x_preferred":[
        "Karivali"
    ],
    "wof:name":"Karivali",
    "wof:placetype":"neighbourhood",
    "wof:population":12932
},
  "geometry": {"coordinates":[73.03964000000001,19.295929],"type":"Point"}
}