{
  "type": "Feature",
  "properties": {
    "gn:admin1_code":"2.0",
    "gn:admin2_code":"553",
    "gn:asciiname":"Beluguppa",
    "gn:country_code":"IN",
    "gn:dem":476,
    "gn:feature_class":"P",
    "gn:feature_code":"PPL",
    "gn:name":"Beluguppa",
    "gn:population":0,
    "gn:timezone":"Asia/Kolkata",
    "iso:country":"IN",
    "wof:name":"Beluguppa",
    "wof:placetype":"locality"
},
  "geometry": {"coordinates":[77.13632,14.71463],"type":"Point"}
}