{
  "type": "Feature",
  "properties": {
    "gn:admin1_code":"2.0",
    "gn:admin2_code":"553",
    "gn:asciiname":"Beluguppa",
    "gn:country_code":"IN",
    "gn:dem":476,
    "gn:feature_class":"P",
    "gn:feature_code":"PPL",
    "gn:name":"Beluguppa",
    "gn:population":0,
    "gn:timezone":"Asia/Kolkata",
    "iso:country":"IN",
    "name:new_x_preferred":[
        "\u092c\u0947\u0932\u0941\u0917\u0941\u092a\u094d\u092a \u092e\u0923\u094d\u0921\u0932"
    ],
    "name:tam_x_preferred":[
        "\u0baa\u0bc6\u0bb2\u0bc1\u0b95\u0bc1\u0baa\u0bcd\u0baa\u0bbe"
    ],
    "name:tel_x_preferred":[
        "\u0c2c\u0c46\u0c32\u0c41\u0c17\u0c41\u0c2a\u0c4d\u0c2a"
    ],
    "name:tgl_x_preferred":[
        "Beluguppa"
    ],
    "name:urd_x_preferred":[
        "\u0628\u06cc\u0644\u0648\u06af\u0648\u067e\u0627"
    ],
    "wof:name":"Beluguppa",
    "wof:placetype":"locality"
},
  "geometry": {"coordinates":[77.13632,14.71463],"type":"Point"}
}