{
  "type": "Feature",
  "properties": {
    "iso:country":"IN",
    "ks:ks_name":"Bhuria Falia",
    "ks:ks_pop":359,
    "ks:ks_type":"HABITATION",
    "name:eng_x_preferred":[
        "Bhuria Falia"
    ],
    "wof:name":"Bhuria Falia",
    "wof:placetype":"locality",
    "wof:population":359
},
  "geometry": {"coordinates":[73.962056,23.049639],"type":"Point"}
}