{
  "type": "Feature",
  "properties": {
    "iso:country":"IN",
    "ks:ks_name":"Tank",
    "ks:ks_pop":962,
    "ks:ks_type":"VILLAGE",
    "name:eng_x_preferred":[
        "Tank"
    ],
    "wof:name":"Tank",
    "wof:placetype":"locality",
    "wof:population":962
},
  "geometry": {"coordinates":[73.66051899999999,15.791617],"type":"Point"}
}