{
  "type": "Feature",
  "properties": {
    "iso:country":"IN",
    "ks:ks_name":"Gavdewadi",
    "ks:ks_pop":60,
    "ks:ks_type":"HABITATION",
    "name:eng_x_preferred":[
        "Gavdewadi"
    ],
    "wof:name":"Gavdewadi",
    "wof:placetype":"locality",
    "wof:population":60
},
  "geometry": {"coordinates":[73.434124,17.417173],"type":"Point"}
}