{
  "type": "Feature",
  "properties": {
    "iso:country":"IN",
    "ks:ks_name":"Seluvathi",
    "ks:ks_pop":117,
    "ks:ks_type":"HABITATION",
    "name:eng_x_preferred":[
        "Seluvathi"
    ],
    "wof:name":"Seluvathi",
    "wof:placetype":"locality",
    "wof:population":117
},
  "geometry": {"coordinates":[78.80404799999999,9.862288],"type":"Point"}
}