{
  "type": "Feature",
  "properties": {
    "iso:country":"IN",
    "ks:ks_name":"Palayapudur",
    "ks:ks_pop":140,
    "ks:ks_type":"HABITATION",
    "ks:ks_uagg_main":0,
    "name:eng_x_preferred":[
        "Palayapudur"
    ],
    "wof:name":"Palayapudur",
    "wof:placetype":"neighbourhood",
    "wof:population":140
},
  "geometry": {"coordinates":[77.60396799999999,10.951978],"type":"Point"}
}