{
  "type": "Feature",
  "properties": {
    "iso:country":"IN",
    "ks:ks_alt_nam":"Oruv\u0101yi Reserved Forest",
    "ks:ks_name":"Oruvayi Reserved Forest",
    "ks:ks_type":"VILLAGE",
    "name:eng_x_preferred":[
        "Oruvayi Reserved Forest"
    ],
    "name:eng_x_variant":[
        "Oruv\u0101yi Reserved Forest"
    ],
    "wof:name":"Oruvayi Reserved Forest",
    "wof:placetype":"locality"
},
  "geometry": {"coordinates":[78.25091,13.940499],"type":"Point"}
}