{
  "type": "Feature",
  "properties": {
    "gn:admin1_code":"36",
    "gn:admin2_code":"146.0",
    "gn:asciiname":"Shala",
    "gn:country_code":"IN",
    "gn:dem":167,
    "gn:feature_class":"P",
    "gn:feature_code":"PPL",
    "gn:name":"Sh\u0101la",
    "gn:population":0,
    "gn:timezone":"Asia/Kolkata",
    "iso:country":"IN",
    "name:deu_x_preferred":[
        "\u0160ala"
    ],
    "name:eus_x_preferred":[
        "Shala"
    ],
    "name:fra_x_preferred":[
        "Shala"
    ],
    "name:nld_x_preferred":[
        "Sjala"
    ],
    "name:rus_x_preferred":[
        "\u0428\u0430\u043b\u0430"
    ],
    "name:spa_x_preferred":[
        "Shala"
    ],
    "name:zho_x_preferred":[
        "\u6c99\u62c9"
    ],
    "wof:name":"Shala",
    "wof:placetype":"locality"
},
  "geometry": {"coordinates":[78.00846999999997,27.02524],"type":"Point"}
}