{
  "type": "Feature",
  "properties": {
    "gn:admin1_code":"2.0",
    "gn:admin2_code":"554.0",
    "gn:asciiname":"Kariyapalli",
    "gn:country_code":"IN",
    "gn:dem":744,
    "gn:feature_class":"P",
    "gn:feature_code":"PPL",
    "gn:name":"Kariyapalli",
    "gn:population":0,
    "gn:timezone":"Asia/Kolkata",
    "iso:country":"IN",
    "wof:name":"Kariyapalli",
    "wof:placetype":"neighbourhood"
},
  "geometry": {"coordinates":[78.49055,12.98381],"type":"Point"}
}