{
  "type": "Feature",
  "properties": {
    "gn:admin1_code":"21",
    "gn:admin2_code":"390.0",
    "gn:asciiname":"Bandika",
    "gn:country_code":"IN",
    "gn:dem":742,
    "gn:feature_class":"P",
    "gn:feature_code":"PPL",
    "gn:name":"Bandika",
    "gn:population":0,
    "gn:timezone":"Asia/Kolkata",
    "iso:country":"IN",
    "ks:ks_name":"Bandaka",
    "ks:ks_pop":107,
    "ks:ks_type":"VILLAGE",
    "name:eng_x_preferred":[
        "Bandaka"
    ],
    "name:eng_x_variant":[
        "Bandika"
    ],
    "wof:name":"Bandaka",
    "wof:placetype":"locality",
    "wof:population":107
},
  "geometry": {"coordinates":[83.689652,19.824477],"type":"Point"}
}