{
  "type": "Feature",
  "properties": {
    "iso:country":"IN",
    "ks:ks_name":"Phansaiwadi",
    "ks:ks_pop":54,
    "ks:ks_type":"HABITATION",
    "name:eng_x_preferred":[
        "Phansaiwadi"
    ],
    "wof:name":"Phansaiwadi",
    "wof:placetype":"locality",
    "wof:population":54
},
  "geometry": {"coordinates":[73.50230999999999,16.46601],"type":"Point"}
}