{
  "type": "Feature",
  "properties": {
    "iso:country":"IN",
    "ks:ks_name":"Olubedda",
    "ks:ks_pop":472,
    "ks:ks_type":"HABITATION",
    "name:eng_x_preferred":[
        "Olubedda"
    ],
    "wof:name":"Olubedda",
    "wof:placetype":"locality",
    "wof:population":472
},
  "geometry": {"coordinates":[82.70178199999999,18.228641],"type":"Point"}
}