{
  "type": "Feature",
  "properties": {
    "iso:country":"IN",
    "ks:ks_name":"Venkatumma",
    "ks:ks_pop":93,
    "ks:ks_type":"HABITATION",
    "name:eng_x_preferred":[
        "Venkatumma"
    ],
    "wof:name":"Venkatumma",
    "wof:placetype":"locality",
    "wof:population":93
},
  "geometry": {"coordinates":[78.713184,19.329801],"type":"Point"}
}