{
  "type": "Feature",
  "properties": {
    "iso:country":"IN",
    "ks:ks_alt_nam":"koduveli church",
    "ks:ks_name":"Koduveli Church",
    "ks:ks_pop":496,
    "ks:ks_type":"HABITATION",
    "ks:ks_uagg_main":0,
    "name:eng_x_preferred":[
        "Koduveli Church"
    ],
    "wof:name":"Koduveli Church",
    "wof:placetype":"neighbourhood",
    "wof:population":496
},
  "geometry": {"coordinates":[76.78940299999999,9.956011],"type":"Point"}
}