{
  "type": "Feature",
  "properties": {
    "iso:country":"IN",
    "ks:ks_name":"Parasgaon",
    "ks:ks_pop":315,
    "ks:ks_type":"VILLAGE",
    "name:eng_x_preferred":[
        "Parasgaon"
    ],
    "wof:name":"Parasgaon",
    "wof:placetype":"locality",
    "wof:population":315
},
  "geometry": {"coordinates":[81.541721,20.133955],"type":"Point"}
}