{
  "type": "Feature",
  "properties": {
    "iso:country":"IN",
    "ks:ks_name":"Patha",
    "ks:ks_pop":0,
    "ks:ks_type":"VILLAGE",
    "name:eng_x_preferred":[
        "Patha"
    ],
    "wof:name":"Patha",
    "wof:placetype":"locality",
    "wof:population":0
},
  "geometry": {"coordinates":[79.61067199999999,24.425158],"type":"Point"}
}