{
  "type": "Feature",
  "properties": {
    "gn:admin1_code":"39.0",
    "gn:admin2_code":"64.0",
    "gn:asciiname":"Gandak",
    "gn:country_code":"IN",
    "gn:dem":2007,
    "gn:feature_class":"P",
    "gn:feature_code":"PPL",
    "gn:name":"Gandak",
    "gn:population":0,
    "gn:timezone":"Asia/Kolkata",
    "iso:country":"IN",
    "name:ell_x_preferred":[
        "\u0393\u03ba\u03b1\u03bd\u03c4\u03ac\u03ba"
    ],
    "name:heb_x_preferred":[
        "\u05d2\u05e0\u05d3\u05d0\u05e7"
    ],
    "name:hun_x_preferred":[
        "Gandak"
    ],
    "name:ind_x_preferred":[
        "Gandak"
    ],
    "name:kor_x_preferred":[
        "\uac04\ub2e4\ud06c"
    ],
    "name:tur_x_preferred":[
        "Gandak"
    ],
    "wof:name":"Gandak",
    "wof:placetype":"locality"
},
  "geometry": {"coordinates":[79.83074000000001,29.63142],"type":"Point"}
}