{
  "type": "Feature",
  "properties": {
    "iso:country":"IN",
    "ks:ks_name":"Janki Nagar",
    "ks:ks_pop":681,
    "ks:ks_type":"HABITATION",
    "name:eng_x_preferred":[
        "Janki Nagar"
    ],
    "wof:name":"Janki Nagar",
    "wof:placetype":"locality",
    "wof:population":681
},
  "geometry": {"coordinates":[82.068122,27.785052],"type":"Point"}
}