{
  "type": "Feature",
  "properties": {
    "iso:country":"IN",
    "ks:ks_name":"Narendrapur",
    "ks:ks_pop":817,
    "ks:ks_type":"VILLAGE",
    "ks:ks_uagg_main":0,
    "name:eng_x_preferred":[
        "Narendrapur"
    ],
    "wof:name":"Narendrapur",
    "wof:placetype":"neighbourhood",
    "wof:population":817
},
  "geometry": {"coordinates":[86.693415,23.193819],"type":"Point"}
}