{
  "type": "Feature",
  "properties": {
    "gn:admin1_code":"39.0",
    "gn:admin2_code":"63.0",
    "gn:asciiname":"Gwar",
    "gn:country_code":"IN",
    "gn:dem":1195,
    "gn:feature_class":"P",
    "gn:feature_code":"PPL",
    "gn:name":"Gw\u0101r",
    "gn:population":0,
    "gn:timezone":"Asia/Kolkata",
    "iso:country":"IN",
    "ks:ks_alt_nam":"Gw\u0101r",
    "ks:ks_name":"Gwar",
    "ks:ks_type":"VILLAGE",
    "name:deu_x_preferred":[
        "Gwar"
    ],
    "name:ell_x_preferred":[
        "Gwar"
    ],
    "name:eng_x_preferred":[
        "Gwar"
    ],
    "name:eng_x_variant":[
        "Gw\u0101r"
    ],
    "name:fra_x_preferred":[
        "Gwar"
    ],
    "name:jpn_x_preferred":[
        "\u30b0\u30ef\u30a1\u30fc"
    ],
    "name:pol_x_preferred":[
        "Gwar"
    ],
    "name:por_x_preferred":[
        "Gwar"
    ],
    "name:spa_x_preferred":[
        "Gwar"
    ],
    "wof:name":"Gwar",
    "wof:placetype":"locality"
},
  "geometry": {"coordinates":[79.60685100000001,29.937617],"type":"Point"}
}