{
  "type": "Feature",
  "properties": {
    "iso:country":"IN",
    "ks:ks_name":"Kalagundikoppa",
    "ks:ks_pop":223,
    "ks:ks_type":"HABITATION",
    "name:eng_x_preferred":[
        "Kalagundikoppa"
    ],
    "wof:name":"Kalagundikoppa",
    "wof:placetype":"locality",
    "wof:population":223
},
  "geometry": {"coordinates":[74.93907900000001,14.581565],"type":"Point"}
}