{
  "type": "Feature",
  "properties": {
    "iso:country":"IN",
    "ks:ks_name":"Kaiyalu",
    "ks:ks_pop":310,
    "ks:ks_type":"HABITATION",
    "name:eng_x_preferred":[
        "Kaiyalu"
    ],
    "wof:name":"Kaiyalu",
    "wof:placetype":"locality",
    "wof:population":310
},
  "geometry": {"coordinates":[74.873829,13.380546],"type":"Point"}
}