{
  "type": "Feature",
  "properties": {
    "gn:admin1_code":"36",
    "gn:admin2_code":"166.0",
    "gn:asciiname":"Ratauli",
    "gn:country_code":"IN",
    "gn:dem":280,
    "gn:feature_class":"P",
    "gn:feature_code":"PPL",
    "gn:name":"R\u0101tauli",
    "gn:population":0,
    "gn:timezone":"Asia/Kolkata",
    "iso:country":"IN",
    "ks:ks_alt_nam":"R\u0101tauli",
    "ks:ks_name":"Ratauli",
    "ks:ks_type":"VILLAGE",
    "name:ceb_x_preferred":[
        "Ratauli"
    ],
    "name:eng_x_preferred":[
        "Ratauli"
    ],
    "name:eng_x_variant":[
        "R\u0101tauli"
    ],
    "name:mai_x_preferred":[
        "\u0930\u0924\u094c\u0932\u0940"
    ],
    "name:msa_x_preferred":[
        "Ratauli"
    ],
    "name:new_x_preferred":[
        "\u0930\u0924\u094c\u0932\u0940"
    ],
    "name:pol_x_preferred":[
        "Ratauli"
    ],
    "wof:name":"Ratauli",
    "wof:placetype":"locality"
},
  "geometry": {"coordinates":[78.433289,25.27069],"type":"Point"}
}