{
  "type": "Feature",
  "properties": {
    "gn:admin1_code":"36",
    "gn:admin2_code":"166.0",
    "gn:asciiname":"Ratauli",
    "gn:country_code":"IN",
    "gn:dem":280,
    "gn:feature_class":"P",
    "gn:feature_code":"PPL",
    "gn:name":"R\u0101tauli",
    "gn:population":0,
    "gn:timezone":"Asia/Kolkata",
    "iso:country":"IN",
    "wof:name":"Ratauli",
    "wof:placetype":"locality"
},
  "geometry": {"coordinates":[78.43329,25.27069],"type":"Point"}
}