{
  "type": "Feature",
  "properties": {
    "iso:country":"IN",
    "ks:ks_name":"Societykeri",
    "ks:ks_pop":65,
    "ks:ks_type":"HABITATION",
    "name:eng_x_preferred":[
        "Societykeri"
    ],
    "wof:name":"Societykeri",
    "wof:placetype":"locality",
    "wof:population":65
},
  "geometry": {"coordinates":[74.60829,14.658462],"type":"Point"}
}