{
  "type": "Feature",
  "properties": {
    "gn:admin1_code":"35",
    "gn:admin2_code":"425.0",
    "gn:asciiname":"Balya",
    "gn:country_code":"IN",
    "gn:dem":313,
    "gn:feature_class":"P",
    "gn:feature_code":"PPL",
    "gn:name":"Balya",
    "gn:population":0,
    "gn:timezone":"Asia/Kolkata",
    "iso:country":"IN",
    "name:ara_x_preferred":[
        "\u0628\u0627\u0644\u064a\u0627"
    ],
    "name:ceb_x_preferred":[
        "Balya \u0130l\u00e7esi"
    ],
    "name:deu_x_preferred":[
        "Balya"
    ],
    "name:ell_x_preferred":[
        "\u039c\u03c0\u03ac\u03bb\u03b9\u03b1"
    ],
    "name:fra_x_preferred":[
        "Balya"
    ],
    "name:hun_x_preferred":[
        "Balya"
    ],
    "name:mrj_x_preferred":[
        "\u0411\u0430\u043b\u044c\u044f"
    ],
    "name:msa_x_preferred":[
        "Balya"
    ],
    "name:nld_x_preferred":[
        "Balya"
    ],
    "name:nor_x_preferred":[
        "Balya"
    ],
    "name:rus_x_preferred":[
        "\u0411\u0430\u043b\u044c\u044f"
    ],
    "name:swa_x_preferred":[
        "Balya"
    ],
    "name:tur_x_preferred":[
        "Balya"
    ],
    "name:ukr_x_preferred":[
        "\u0411\u0430\u043b\u044c\u044f"
    ],
    "name:urd_x_preferred":[
        "\u0628\u0627\u0644\u06cc\u0627"
    ],
    "name:vie_x_preferred":[
        "Balya"
    ],
    "wof:name":"Balya",
    "wof:placetype":"locality"
},
  "geometry": {"coordinates":[79.37321999999998,24.62058],"type":"Point"}
}