{
  "type": "Feature",
  "properties": {
    "iso:country":"IN",
    "ks:ks_name":"Ramdeo Nagar",
    "ks:ks_pop":838,
    "ks:ks_type":"HABITATION",
    "name:eng_x_preferred":[
        "Ramdeo Nagar"
    ],
    "wof:name":"Ramdeo Nagar",
    "wof:placetype":"locality",
    "wof:population":838
},
  "geometry": {"coordinates":[71.401625,24.860911],"type":"Point"}
}