{
  "type": "Feature",
  "properties": {
    "gn:admin1_code":"34.0",
    "gn:admin2_code":"236.0",
    "gn:asciiname":"Dhokra",
    "gn:country_code":"IN",
    "gn:dem":129,
    "gn:feature_class":"P",
    "gn:feature_code":"PPL",
    "gn:name":"Dhokra",
    "gn:population":0,
    "gn:timezone":"Asia/Kolkata",
    "iso:country":"IN",
    "name:ben_x_preferred":[
        "\u09a1\u09cb\u0995\u09b0\u09be"
    ],
    "name:ori_x_preferred":[
        "\u0b21\u0b4b\u0b15\u0b30\u0b3e"
    ],
    "name:tel_x_preferred":[
        "\u0c2c\u0c38\u0c4d\u0c24\u0c30\u0c4d \u0c22\u0c4b\u0c15\u0c4d\u0c30\u0c3e"
    ],
    "wof:name":"Dhokra",
    "wof:placetype":"locality"
},
  "geometry": {"coordinates":[84.84979,24.70044],"type":"Point"}
}