{
  "type": "Feature",
  "properties": {
    "iso:country":"IN",
    "ks:ks_name":"Karkal",
    "ks:ks_pop":189,
    "ks:ks_type":"HABITATION",
    "name:eng_x_preferred":[
        "Karkal"
    ],
    "wof:name":"Karkal",
    "wof:placetype":"locality",
    "wof:population":189
},
  "geometry": {"coordinates":[74.25124099999999,14.872924],"type":"Point"}
}