{
  "type": "Feature",
  "properties": {
    "iso:country":"IN",
    "ks:ks_name":"Panangalathamme",
    "ks:ks_pop":59,
    "ks:ks_type":"HABITATION",
    "name:eng_x_preferred":[
        "Panangalathamme"
    ],
    "wof:name":"Panangalathamme",
    "wof:placetype":"locality",
    "wof:population":59
},
  "geometry": {"coordinates":[75.634444,12.240278],"type":"Point"}
}