{
  "type": "Feature",
  "properties": {
    "iso:country":"IN",
    "ks:ks_name":"5 BLW",
    "ks:ks_pop":85,
    "ks:ks_type":"VILLAGE",
    "name:eng_x_preferred":[
        "5 BLW"
    ],
    "wof:name":"5 BLW",
    "wof:placetype":"locality",
    "wof:population":85
},
  "geometry": {"coordinates":[73.899286,29.642617],"type":"Point"}
}