{
  "type": "Feature",
  "properties": {
    "iso:country":"IN",
    "ks:ks_name":"Muslimguda",
    "ks:ks_pop":96,
    "ks:ks_type":"HABITATION",
    "ks:ks_uagg_main":0,
    "name:eng_x_preferred":[
        "Muslimguda"
    ],
    "wof:name":"Muslimguda",
    "wof:placetype":"neighbourhood",
    "wof:population":96
},
  "geometry": {"coordinates":[78.91504999999999,19.399756],"type":"Point"}
}