{
  "type": "Feature",
  "properties": {
    "gn:admin1_code":"35",
    "gn:admin2_code":"456.0",
    "gn:asciiname":"Magarkata",
    "gn:country_code":"IN",
    "gn:dem":593,
    "gn:feature_class":"P",
    "gn:feature_code":"PPL",
    "gn:name":"Magarkata",
    "gn:population":0,
    "gn:timezone":"Asia/Kolkata",
    "iso:country":"IN",
    "ks:ks_name":"Magarkatha",
    "ks:ks_pop":144,
    "ks:ks_type":"VILLAGE",
    "name:eng_x_preferred":[
        "Magarkatha"
    ],
    "name:eng_x_variant":[
        "Magarkata"
    ],
    "wof:name":"Magarkatha",
    "wof:placetype":"locality",
    "wof:population":144
},
  "geometry": {"coordinates":[79.675389,21.873752],"type":"Point"}
}