{
  "type": "Feature",
  "properties": {
    "gn:admin1_code":"35",
    "gn:admin2_code":"456.0",
    "gn:asciiname":"Magarkata",
    "gn:country_code":"IN",
    "gn:dem":593,
    "gn:feature_class":"P",
    "gn:feature_code":"PPL",
    "gn:name":"Magarkata",
    "gn:population":0,
    "gn:timezone":"Asia/Kolkata",
    "iso:country":"IN",
    "wof:name":"Magarkata",
    "wof:placetype":"locality"
},
  "geometry": {"coordinates":[79.67596999999998,21.87416],"type":"Point"}
}