{
  "type": "Feature",
  "properties": {
    "iso:country":"IN",
    "ks:ks_name":"Bhillare Wasti",
    "ks:ks_pop":165,
    "ks:ks_type":"HABITATION",
    "name:eng_x_preferred":[
        "Bhillare Wasti"
    ],
    "wof:name":"Bhillare Wasti",
    "wof:placetype":"locality",
    "wof:population":165
},
  "geometry": {"coordinates":[75.353989,18.526356],"type":"Point"}
}