{
  "type": "Feature",
  "properties": {
    "gn:admin1_code":"19.0",
    "gn:admin2_code":"570.0",
    "gn:asciiname":"Kogodu",
    "gn:country_code":"IN",
    "gn:dem":821,
    "gn:feature_class":"P",
    "gn:feature_code":"PPL",
    "gn:name":"Kogodu",
    "gn:population":0,
    "gn:timezone":"Asia/Kolkata",
    "iso:country":"IN",
    "ks:ks_name":"Kugodu",
    "ks:ks_pop":35,
    "ks:ks_type":"HABITATION",
    "name:eng_x_preferred":[
        "Kugodu"
    ],
    "name:eng_x_variant":[
        "Kogodu"
    ],
    "wof:name":"Kugodu",
    "wof:placetype":"locality",
    "wof:population":35
},
  "geometry": {"coordinates":[75.382869,13.340733],"type":"Point"}
}