{
  "type": "Feature",
  "properties": {
    "iso:country":"IN",
    "ks:ks_name":"Mendi",
    "ks:ks_pop":370,
    "ks:ks_type":"HABITATION",
    "name:eng_x_preferred":[
        "Mendi"
    ],
    "wof:name":"Mendi",
    "wof:placetype":"locality",
    "wof:population":370
},
  "geometry": {"coordinates":[76.68750799999999,27.005497],"type":"Point"}
}