{
  "type": "Feature",
  "properties": {
    "iso:country":"IN",
    "ks:ks_name":"Thara Jhikla",
    "ks:ks_pop":4348,
    "ks:ks_type":"HABITATION",
    "name:eng_x_preferred":[
        "Thara Jhikla"
    ],
    "wof:name":"Thara Jhikla",
    "wof:placetype":"locality",
    "wof:population":4348
},
  "geometry": {"coordinates":[75.74863499999999,32.419011],"type":"Point"}
}