{
  "type": "Feature",
  "properties": {
    "iso:country":"IN",
    "ks:ks_name":"Jhintikakhol",
    "ks:ks_pop":20,
    "ks:ks_type":"VILLAGE",
    "name:eng_x_preferred":[
        "Jhintikakhol"
    ],
    "wof:name":"Jhintikakhol",
    "wof:placetype":"locality",
    "wof:population":20
},
  "geometry": {"coordinates":[84.395635,21.044286],"type":"Point"}
}