{
  "type": "Feature",
  "properties": {
    "gn:country":"IN",
    "gn:fcode":"PPL",
    "gn:population":81433,
    "iso:country":"IN",
    "name:ben_x_preferred":[
        "\u09b0\u09be\u09af\u09bc\u099a\u09cb\u099f\u09bf"
    ],
    "name:bpy_x_preferred":[
        "\u09b0\u09be\u09af\u09bc\u09be\u099a\u09cb\u09a4\u09bf"
    ],
    "name:ceb_x_preferred":[
        "R\u0101yachoti"
    ],
    "name:deu_x_preferred":[
        "Rayachoti"
    ],
    "name:eng_x_preferred":[
        "Rayachoti"
    ],
    "name:fra_x_preferred":[
        "Rayachoti"
    ],
    "name:guj_x_preferred":[
        "\u0ab0\u0abe\u0aaf\u0abe\u0a9a\u0acb\u0a9f\u0ac0"
    ],
    "name:ita_x_preferred":[
        "Rayachoti"
    ],
    "name:jpn_x_preferred":[
        "\u30e9\u30e4\u30c1\u30e7\u30c3\u30c6\u30a3"
    ],
    "name:kan_x_preferred":[
        "\u0cb0\u0cbe\u0caf\u0c9a\u0ccc\u0c9f\u0cbf"
    ],
    "name:kor_x_preferred":[
        "\ub77c\uc57c\ucf54\ud2f0"
    ],
    "name:mar_x_preferred":[
        "\u0930\u093e\u092f\u093e\u091a\u094b\u091f\u0940"
    ],
    "name:msa_x_preferred":[
        "Rayachoti"
    ],
    "name:nan_x_preferred":[
        "Rayachoti"
    ],
    "name:new_x_preferred":[
        "\u0930\u093e\u092f\u091a\u094b\u091f\u093f \u092e\u0923\u094d\u0921\u0932"
    ],
    "name:nld_x_preferred":[
        "Rayachoti"
    ],
    "name:ori_x_preferred":[
        "\u0b30\u0b3e\u0b5f\u0b3e\u0b1a\u0b4b\u0b1f\u0b3f"
    ],
    "name:pam_x_preferred":[
        "Rayachoti"
    ],
    "name:por_x_preferred":[
        "Rayachoti"
    ],
    "name:rus_x_preferred":[
        "\u0420\u0430\u044f\u0447\u043e\u0442\u0438"
    ],
    "name:spa_x_preferred":[
        "Rayachoti"
    ],
    "name:swe_x_preferred":[
        "Rayachoti"
    ],
    "name:tam_x_preferred":[
        "\u0bb0\u0bbe\u0baf\u0b95\u0bcd\u0b95\u0bcb\u0b9f\u0bbf"
    ],
    "name:tel_x_preferred":[
        "\u0c30\u0c3e\u0c2f\u0c1a\u0c4b\u0c1f\u0c3f"
    ],
    "name:tgl_x_preferred":[
        "Rayachoti"
    ],
    "name:urd_x_preferred":[
        "\u0631\u0627\u0626\u06d2 \u0686\u0648\u0679\u06cc"
    ],
    "name:vie_x_preferred":[
        "Rayachoti"
    ],
    "name:zho_x_preferred":[
        "\u62c9\u8036\u4e54\u8482"
    ],
    "qs:name":"Rayachoti",
    "qs:name_adm0":"India",
    "qs:name_adm1":"Andhra Pradesh",
    "qs:photos_9k":1,
    "qs:photos_9r":1,
    "qs:photos_all":3,
    "qs:photos_sr":0,
    "qs:placetype":"Town",
    "qs:pop_sr":"8",
    "wd:wordcount":749,
    "wof:name":"Rayachoti",
    "wof:placetype":"locality",
    "wof:population":81433
},
  "geometry": {"coordinates":[78.75127000000001,14.0568],"type":"Point"}
}