{
  "type": "Feature",
  "properties": {
    "iso:country":"IN",
    "ks:ks_name":"Bugyalgaon",
    "ks:ks_pop":408,
    "ks:ks_type":"VILLAGE",
    "name:eng_x_preferred":[
        "Bugyalgaon"
    ],
    "wof:name":"Bugyalgaon",
    "wof:placetype":"locality",
    "wof:population":408
},
  "geometry": {"coordinates":[78.44775,30.742692],"type":"Point"}
}