{
  "type": "Feature",
  "properties": {
    "iso:country":"IN",
    "ks:ks_name":"Payalavaripalli",
    "ks:ks_pop":50,
    "ks:ks_type":"HABITATION",
    "ks:ks_uagg_main":0,
    "name:eng_x_preferred":[
        "Payalavaripalli"
    ],
    "wof:name":"Payalavaripalli",
    "wof:placetype":"neighbourhood",
    "wof:population":50
},
  "geometry": {"coordinates":[78.799609,13.465656],"type":"Point"}
}