{
  "type": "Feature",
  "properties": {
    "gn:admin1_code":"36.0",
    "gn:admin2_code":"153.0",
    "gn:asciiname":"Harkhapur",
    "gn:country_code":"IN",
    "gn:dem":156,
    "gn:feature_class":"P",
    "gn:feature_code":"PPL",
    "gn:name":"Harkhapur",
    "gn:population":0,
    "gn:timezone":"Asia/Kolkata",
    "iso:country":"IN",
    "ks:ks_name":"Harikhapur",
    "ks:ks_pop":557,
    "ks:ks_type":"VILLAGE",
    "name:eng_x_preferred":[
        "Harikhapur"
    ],
    "name:eng_x_variant":[
        "Harkhapur"
    ],
    "wof:name":"Harikhapur",
    "wof:placetype":"locality",
    "wof:population":557
},
  "geometry": {"coordinates":[80.087981,27.843193],"type":"Point"}
}