{
  "type": "Feature",
  "properties": {
    "gn:admin1_code":"25.0",
    "gn:admin2_code":"611.0",
    "gn:asciiname":"Manalcheri",
    "gn:country_code":"IN",
    "gn:dem":1856,
    "gn:feature_class":"P",
    "gn:feature_code":"PPL",
    "gn:name":"Manalch\u0113ri",
    "gn:population":0,
    "gn:timezone":"Asia/Kolkata",
    "iso:country":"IN",
    "wof:name":"Manalcheri",
    "wof:placetype":"locality"
},
  "geometry": {"coordinates":[76.77413,11.36281],"type":"Point"}
}