{
  "type": "Feature",
  "properties": {
    "iso:country":"IN",
    "ks:ks_name":"Mantagaria",
    "ks:ks_pop":122,
    "ks:ks_type":"VILLAGE",
    "name:eng_x_preferred":[
        "Mantagaria"
    ],
    "wof:name":"Mantagaria",
    "wof:placetype":"locality",
    "wof:population":122
},
  "geometry": {"coordinates":[86.33556900000001,21.014745],"type":"Point"}
}