{
  "type": "Feature",
  "properties": {
    "iso:country":"IN",
    "ks:ks_name":"Turukkata",
    "ks:ks_pop":1289,
    "ks:ks_type":"VILLAGE",
    "name:eng_x_preferred":[
        "Turukkata"
    ],
    "wof:name":"Turukkata",
    "wof:placetype":"locality",
    "wof:population":1289
},
  "geometry": {"coordinates":[89.59932499999999,26.07985],"type":"Point"}
}