{
  "type": "Feature",
  "properties": {
    "iso:country":"IN",
    "ks:ks_name":"Bandhwari",
    "ks:ks_pop":4104,
    "ks:ks_type":"VILLAGE",
    "name:eng_x_preferred":[
        "Bandhwari"
    ],
    "wof:name":"Bandhwari",
    "wof:placetype":"locality",
    "wof:population":4104
},
  "geometry": {"coordinates":[77.14277199999999,28.415435],"type":"Point"}
}