{
  "type": "Feature",
  "properties": {
    "iso:country":"IN",
    "ks:ks_name":"Rajrawal",
    "ks:ks_pop":96,
    "ks:ks_type":"VILLAGE",
    "name:eng_x_preferred":[
        "Rajrawal"
    ],
    "wof:name":"Rajrawal",
    "wof:placetype":"locality",
    "wof:population":96
},
  "geometry": {"coordinates":[82.04823399999999,23.745336],"type":"Point"}
}