{
  "type": "Feature",
  "properties": {
    "gn:admin1_code":"25.0",
    "gn:admin2_code":"631.0",
    "gn:asciiname":"Gollahalli",
    "gn:country_code":"IN",
    "gn:dem":722,
    "gn:feature_class":"P",
    "gn:feature_code":"PPL",
    "gn:name":"Gollahalli",
    "gn:population":0,
    "gn:timezone":"Asia/Kolkata",
    "iso:country":"IN",
    "wof:name":"Gollahalli",
    "wof:placetype":"locality"
},
  "geometry": {"coordinates":[78.00139,12.54395],"type":"Point"}
}