{
  "type": "Feature",
  "properties": {
    "iso:country":"IN",
    "ks:ks_alt_nam":"arkala",
    "ks:ks_name":"Arkala",
    "ks:ks_pop":18,
    "ks:ks_type":"HABITATION",
    "name:eng_x_preferred":[
        "Arkala"
    ],
    "wof:name":"Arkala",
    "wof:placetype":"locality",
    "wof:population":18
},
  "geometry": {"coordinates":[74.653778,14.043196],"type":"Point"}
}