{
  "type": "Feature",
  "properties": {
    "iso:country":"IN",
    "ks:ks_name":"Sukunkhet",
    "ks:ks_pop":42,
    "ks:ks_type":"VILLAGE",
    "name:eng_x_preferred":[
        "Sukunkhet"
    ],
    "wof:name":"Sukunkhet",
    "wof:placetype":"locality",
    "wof:population":42
},
  "geometry": {"coordinates":[80.070741,29.745391],"type":"Point"}
}