{
  "type": "Feature",
  "properties": {
    "iso:country":"IN",
    "ks:ks_name":"Pailani Dera",
    "ks:ks_pop":300,
    "ks:ks_type":"HABITATION",
    "name:eng_x_preferred":[
        "Pailani Dera"
    ],
    "wof:name":"Pailani Dera",
    "wof:placetype":"locality",
    "wof:population":300
},
  "geometry": {"coordinates":[80.445435,25.628603],"type":"Point"}
}