{
  "type": "Feature",
  "properties": {
    "gn:admin1_code":"35.0",
    "gn:admin2_code":"453.0",
    "gn:asciiname":"Kailwara",
    "gn:country_code":"IN",
    "gn:dem":807,
    "gn:feature_class":"P",
    "gn:feature_code":"PPL",
    "gn:name":"Kailw\u0101ra",
    "gn:population":0,
    "gn:timezone":"Asia/Kolkata",
    "iso:country":"IN",
    "wof:name":"Kailwara",
    "wof:placetype":"neighbourhood"
},
  "geometry": {"coordinates":[80.84813,23.21064],"type":"Point"}
}