{
  "type": "Feature",
  "properties": {
    "iso:country":"IN",
    "ks:ks_name":"Colonypada",
    "ks:ks_pop":560,
    "ks:ks_type":"HABITATION",
    "name:eng_x_preferred":[
        "Colonypada"
    ],
    "wof:name":"Colonypada",
    "wof:placetype":"locality",
    "wof:population":560
},
  "geometry": {"coordinates":[82.817595,19.4381],"type":"Point"}
}