{
  "type": "Feature",
  "properties": {
    "iso:country":"IN",
    "ks:ks_name":"Hulugaruthotta",
    "ks:ks_pop":23,
    "ks:ks_type":"HABITATION",
    "name:eng_x_preferred":[
        "Hulugaruthotta"
    ],
    "wof:name":"Hulugaruthotta",
    "wof:placetype":"locality",
    "wof:population":23
},
  "geometry": {"coordinates":[75.279549,13.459284],"type":"Point"}
}