{
  "type": "Feature",
  "properties": {
    "iso:country":"IN",
    "ks:ks_alt_nam":"ramapuram",
    "ks:ks_name":"Ramapuram",
    "ks:ks_pop":1308,
    "ks:ks_type":"HABITATION",
    "name:eng_x_preferred":[
        "Ramapuram"
    ],
    "wof:name":"Ramapuram",
    "wof:placetype":"locality",
    "wof:population":1308
},
  "geometry": {"coordinates":[75.28236800000001,12.153518],"type":"Point"}
}