{
  "type": "Feature",
  "properties": {
    "gn:admin1_code":"19.0",
    "gn:admin2_code":"570.0",
    "gn:asciiname":"Attiganalu",
    "gn:country_code":"IN",
    "gn:dem":696,
    "gn:feature_class":"P",
    "gn:feature_code":"PPL",
    "gn:name":"Attigan\u0101lu",
    "gn:population":0,
    "gn:timezone":"Asia/Kolkata",
    "iso:country":"IN",
    "wof:name":"Attiganalu",
    "wof:placetype":"locality"
},
  "geometry": {"coordinates":[75.80726999999997,13.69276],"type":"Point"}
}