{
  "type": "Feature",
  "properties": {
    "iso:country":"IN",
    "ks:ks_name":"Semraha Nankar",
    "ks:ks_pop":213,
    "ks:ks_type":"VILLAGE",
    "ks:ks_uagg_main":0,
    "name:eng_x_preferred":[
        "Semraha Nankar"
    ],
    "wof:name":"Semraha Nankar",
    "wof:placetype":"neighbourhood",
    "wof:population":213
},
  "geometry": {"coordinates":[85.238623,26.404695],"type":"Point"}
}