{
  "type": "Feature",
  "properties": {
    "iso:country":"IN",
    "ks:ks_name":"Karampada",
    "ks:ks_pop":840,
    "ks:ks_type":"VILLAGE",
    "name:eng_x_preferred":[
        "Karampada"
    ],
    "wof:name":"Karampada",
    "wof:placetype":"locality",
    "wof:population":840
},
  "geometry": {"coordinates":[85.23617400000001,22.060923],"type":"Point"}
}