{
  "type": "Feature",
  "properties": {
    "gn:admin1_code":"1.0",
    "gn:admin2_code":"640",
    "gn:asciiname":"Hope Town RV",
    "gn:country_code":"IN",
    "gn:dem":165,
    "gn:feature_class":"P",
    "gn:feature_code":"PPL",
    "gn:name":"Hope Town RV",
    "gn:population":0,
    "gn:timezone":"Asia/Kolkata",
    "iso:country":"IN",
    "wof:name":"Hope Town RV",
    "wof:placetype":"locality"
},
  "geometry": {"coordinates":[92.73614999999999,11.70553],"type":"Point"}
}