{
  "type": "Feature",
  "properties": {
    "iso:country":"IN",
    "ks:ks_name":"Khairbari South",
    "ks:ks_pop":944,
    "ks:ks_type":"HABITATION",
    "name:eng_x_preferred":[
        "Khairbari South"
    ],
    "wof:name":"Khairbari South",
    "wof:placetype":"locality",
    "wof:population":944
},
  "geometry": {"coordinates":[89.27766699999999,26.717267],"type":"Point"}
}