{
  "type": "Feature",
  "properties": {
    "iso:country":"IN",
    "ks:ks_name":"Pandusai",
    "ks:ks_pop":682,
    "ks:ks_type":"VILLAGE",
    "name:eng_x_preferred":[
        "Pandusai"
    ],
    "wof:name":"Pandusai",
    "wof:placetype":"locality",
    "wof:population":682
},
  "geometry": {"coordinates":[86.41366600000001,22.44856],"type":"Point"}
}