{
  "type": "Feature",
  "properties": {
    "iso:country":"IN",
    "ks:ks_name":"15 SLD",
    "ks:ks_pop":178,
    "ks:ks_type":"VILLAGE",
    "name:eng_x_preferred":[
        "15 SLD"
    ],
    "wof:name":"15 SLD",
    "wof:placetype":"locality",
    "wof:population":178
},
  "geometry": {"coordinates":[73.203114,28.875911],"type":"Point"}
}