{
  "type": "Feature",
  "properties": {
    "gn:admin1_code":"25.0",
    "gn:admin2_code":"631.0",
    "gn:asciiname":"Soraguriki",
    "gn:country_code":"IN",
    "gn:dem":680,
    "gn:feature_class":"P",
    "gn:feature_code":"PPL",
    "gn:name":"Soraguriki",
    "gn:population":0,
    "gn:timezone":"Asia/Kolkata",
    "iso:country":"IN",
    "wof:name":"Soraguriki",
    "wof:placetype":"locality"
},
  "geometry": {"coordinates":[77.95288000000002,12.5004],"type":"Point"}
}