{
  "type": "Feature",
  "properties": {
    "iso:country":"IN",
    "ks:ks_name":"Navinagri",
    "ks:ks_pop":63,
    "ks:ks_type":"HABITATION",
    "name:eng_x_preferred":[
        "Navinagri"
    ],
    "wof:name":"Navinagri",
    "wof:placetype":"locality",
    "wof:population":63
},
  "geometry": {"coordinates":[72.75765800000001,20.120801],"type":"Point"}
}