{
  "type": "Feature",
  "properties": {
    "iso:country":"IN",
    "ks:ks_name":"Thareru Uparhar",
    "ks:ks_pop":789,
    "ks:ks_type":"VILLAGE",
    "name:eng_x_preferred":[
        "Thareru Uparhar"
    ],
    "wof:name":"Thareru Uparhar",
    "wof:placetype":"locality",
    "wof:population":789
},
  "geometry": {"coordinates":[81.898911,26.799658],"type":"Point"}
}