{
  "type": "Feature",
  "properties": {
    "iso:country":"IN",
    "ks:ks_name":"Mundaje",
    "ks:ks_pop":178,
    "ks:ks_type":"HABITATION",
    "name:eng_x_preferred":[
        "Mundaje"
    ],
    "wof:name":"Mundaje",
    "wof:placetype":"locality",
    "wof:population":178
},
  "geometry": {"coordinates":[75.030993,12.765403],"type":"Point"}
}