{
  "type": "Feature",
  "properties": {
    "gn:admin1_code":"28.0",
    "gn:admin2_code":"343",
    "gn:asciiname":"Netra",
    "gn:country_code":"IN",
    "gn:dem":9,
    "gn:feature_class":"P",
    "gn:feature_code":"PPL",
    "gn:name":"Netra",
    "gn:population":0,
    "gn:timezone":"Asia/Kolkata",
    "iso:country":"IN",
    "ks:ks_name":"Netra",
    "ks:ks_pop":2996,
    "ks:ks_type":"VILLAGE",
    "ks:ks_uagg_main":0,
    "name:deu_x_preferred":[
        "Norddeutsche Erdgas-Transversale"
    ],
    "name:eng_x_preferred":[
        "Netra"
    ],
    "name:ukr_x_preferred":[
        "Netra"
    ],
    "wof:name":"Netra",
    "wof:placetype":"neighbourhood",
    "wof:population":2996
},
  "geometry": {"coordinates":[88.25783199999999,22.214129],"type":"Point"}
}