{
  "type": "Feature",
  "properties": {
    "gn:country":"IN",
    "gn:fcode":"PPL",
    "gn:pop":14456,
    "iso:country":"IN",
    "name:bpy_x_preferred":[
        "\u098f\u09b2\u09c1\u09ae\u09be\u09b2\u09be\u0987"
    ],
    "name:bul_x_preferred":[
        "\u0415\u043b\u0443\u043c\u0430\u043b\u0430\u0438"
    ],
    "name:eng_x_preferred":[
        "Elumalai"
    ],
    "name:fra_x_preferred":[
        "Elumalai"
    ],
    "name:ita_x_preferred":[
        "Elumalai"
    ],
    "name:msa_x_preferred":[
        "Elumalai"
    ],
    "name:nan_x_preferred":[
        "Elumalai"
    ],
    "name:new_x_preferred":[
        "\u090f\u0932\u0941\u092e\u0932\u0907"
    ],
    "name:nld_x_preferred":[
        "Elumalai"
    ],
    "name:por_x_preferred":[
        "Elumalai"
    ],
    "name:swe_x_preferred":[
        "Elumalai"
    ],
    "name:tam_x_preferred":[
        "\u0b8f\u0bb4\u0bc1\u0bae\u0bb2\u0bc8"
    ],
    "name:vie_x_preferred":[
        "Elumalai"
    ],
    "name:zho_x_preferred":[
        "\u57c3\u5362\u9a6c\u83b1"
    ],
    "qs:name":"Elumalai",
    "qs:name_adm0":"India",
    "qs:name_adm1":"Tamil Nadu",
    "qs:photos_9r":0,
    "qs:photos_sr":0,
    "qs:placetype":"Town",
    "qs:pop_sr":"6",
    "wd:wordcount":557,
    "wof:name":"Elumalai",
    "wof:placetype":"locality",
    "wof:population":14456
},
  "geometry": {"coordinates":[77.69938999999999,9.86376],"type":"Point"}
}