{
  "type": "Feature",
  "properties": {
    "iso:country":"IN",
    "ks:ks_name":"Matehana Arazi",
    "ks:ks_pop":374,
    "ks:ks_type":"VILLAGE",
    "ks:ks_uagg_main":0,
    "name:eng_x_preferred":[
        "Matehana Arazi"
    ],
    "wof:name":"Matehana Arazi",
    "wof:placetype":"neighbourhood",
    "wof:population":374
},
  "geometry": {"coordinates":[83.123048,27.39242],"type":"Point"}
}