{
  "type": "Feature",
  "properties": {
    "iso:country":"IN",
    "ks:ks_name":"Ekkal",
    "ks:ks_pop":1327,
    "ks:ks_type":"HABITATION",
    "name:eng_x_preferred":[
        "Ekkal"
    ],
    "wof:name":"Ekkal",
    "wof:placetype":"locality",
    "wof:population":1327
},
  "geometry": {"coordinates":[75.503266,11.888519],"type":"Point"}
}