{
  "type": "Feature",
  "properties": {
    "iso:country":"IN",
    "ks:ks_name":"Benageria",
    "ks:ks_pop":115,
    "ks:ks_type":"VILLAGE",
    "ks:ks_uagg_main":0,
    "name:eng_x_preferred":[
        "Benageria"
    ],
    "wof:name":"Benageria",
    "wof:placetype":"neighbourhood",
    "wof:population":115
},
  "geometry": {"coordinates":[86.989206,23.142118],"type":"Point"}
}