{
  "type": "Feature",
  "properties": {
    "gn:admin1_code":"24.0",
    "gn:admin2_code":"112",
    "gn:asciiname":"Bhakri",
    "gn:country_code":"IN",
    "gn:dem":406,
    "gn:feature_class":"P",
    "gn:feature_code":"PPL",
    "gn:name":"Bhakri",
    "gn:population":0,
    "gn:timezone":"Asia/Kolkata",
    "iso:country":"IN",
    "name:fra_x_preferred":[
        "Bhakri"
    ],
    "name:guj_x_preferred":[
        "\u0aad\u0abe\u0a96\u0ab0\u0ac0"
    ],
    "name:kor_x_preferred":[
        "\ubc14\ud06c\ub9ac"
    ],
    "name:mar_x_preferred":[
        "\u092d\u093e\u0915\u0930\u0940"
    ],
    "name:spa_x_preferred":[
        "Bhakri"
    ],
    "wof:name":"Bhakri",
    "wof:placetype":"neighbourhood"
},
  "geometry": {"coordinates":[74.51428,26.78141],"type":"Point"}
}