{
  "type": "Feature",
  "properties": {
    "iso:country":"IN",
    "ks:ks_name":"Neerullipalem",
    "ks:ks_pop":258,
    "ks:ks_type":"HABITATION",
    "name:eng_x_preferred":[
        "Neerullipalem"
    ],
    "wof:name":"Neerullipalem",
    "wof:placetype":"locality",
    "wof:population":258
},
  "geometry": {"coordinates":[81.83010899999999,16.542063],"type":"Point"}
}