{
  "type": "Feature",
  "properties": {
    "iso:country":"IN",
    "ks:ks_name":"Pathetipalem",
    "ks:ks_pop":34,
    "ks:ks_type":"VILLAGE",
    "name:eng_x_preferred":[
        "Pathetipalem"
    ],
    "wof:name":"Pathetipalem",
    "wof:placetype":"locality",
    "wof:population":34
},
  "geometry": {"coordinates":[80.120249,14.036726],"type":"Point"}
}