{
  "type": "Feature",
  "properties": {
    "gn:admin1_code":"36",
    "gn:admin2_code":"191.0",
    "gn:asciiname":"Bhuilauli Khalsa",
    "gn:country_code":"IN",
    "gn:dem":82,
    "gn:feature_class":"P",
    "gn:feature_code":"PPL",
    "gn:name":"Bhuilauli Kh\u0101lsa",
    "gn:population":0,
    "gn:timezone":"Asia/Kolkata",
    "iso:country":"IN",
    "ks:ks_alt_nam":"Bhuilauli Kh\u0101lsa",
    "ks:ks_name":"Bhuilauli Khalsa",
    "ks:ks_type":"VILLAGE",
    "ks:ks_uagg_main":0,
    "name:eng_x_preferred":[
        "Bhuilauli Khalsa"
    ],
    "name:eng_x_variant":[
        "Bhuilauli Kh\u0101lsa"
    ],
    "wof:name":"Bhuilauli Khalsa",
    "wof:placetype":"neighbourhood"
},
  "geometry": {"coordinates":[83.054807,26.078364],"type":"Point"}
}