{
  "type": "Feature",
  "properties": {
    "iso:country":"IN",
    "ks:ks_name":"Sherpura",
    "ks:ks_pop":238,
    "ks:ks_type":"VILLAGE",
    "name:eng_x_preferred":[
        "Sherpura"
    ],
    "wof:name":"Sherpura",
    "wof:placetype":"locality",
    "wof:population":238
},
  "geometry": {"coordinates":[73.17269400000001,21.897917],"type":"Point"}
}