{
  "type": "Feature",
  "properties": {
    "iso:country":"IN",
    "ks:ks_name":"Addala Thimmapur",
    "ks:ks_pop":170,
    "ks:ks_type":"HABITATION",
    "name:eng_x_preferred":[
        "Addala Thimmapur"
    ],
    "wof:name":"Addala Thimmapur",
    "wof:placetype":"locality",
    "wof:population":170
},
  "geometry": {"coordinates":[78.719728,19.273541],"type":"Point"}
}