{
  "type": "Feature",
  "properties": {
    "gn:admin1_code":"36.0",
    "gn:admin2_code":"180.0",
    "gn:asciiname":"Aima",
    "gn:country_code":"IN",
    "gn:dem":111,
    "gn:feature_class":"P",
    "gn:feature_code":"PPL",
    "gn:name":"Aima",
    "gn:population":0,
    "gn:timezone":"Asia/Kolkata",
    "iso:country":"IN",
    "wof:name":"Aima",
    "wof:placetype":"locality"
},
  "geometry": {"coordinates":[81.55289999999999,27.1751],"type":"Point"}
}