{
  "type": "Feature",
  "properties": {
    "gn:admin1_code":"34.0",
    "gn:admin2_code":"217.0",
    "gn:asciiname":"Bhikhampur",
    "gn:country_code":"IN",
    "gn:dem":68,
    "gn:feature_class":"P",
    "gn:feature_code":"PPL",
    "gn:name":"Bhikhampur",
    "gn:population":0,
    "gn:timezone":"Asia/Kolkata",
    "iso:country":"IN",
    "ks:ks_name":"Bhikhampur",
    "ks:ks_pop":1279,
    "ks:ks_type":"VILLAGE",
    "ks:ks_uagg_main":0,
    "name:eng_x_preferred":[
        "Bhikhampur"
    ],
    "wof:name":"Bhikhampur",
    "wof:placetype":"neighbourhood",
    "wof:population":1279
},
  "geometry": {"coordinates":[84.598634,26.315991],"type":"Point"}
}