{
  "type": "Feature",
  "properties": {
    "iso:country":"IN",
    "ks:ks_name":"Dakhin Moutupi",
    "ks:ks_pop":648,
    "ks:ks_type":"HABITATION",
    "ks:ks_uagg_main":0,
    "name:eng_x_preferred":[
        "Dakhin Moutupi"
    ],
    "wof:name":"Dakhin Moutupi",
    "wof:placetype":"neighbourhood",
    "wof:population":648
},
  "geometry": {"coordinates":[90.962543,26.449444],"type":"Point"}
}