{
  "type": "Feature",
  "properties": {
    "iso:country":"IN",
    "ks:ks_name":"Ratnagiri",
    "ks:ks_pop":465,
    "ks:ks_type":"VILLAGE",
    "name:eng_x_preferred":[
        "Ratnagiri"
    ],
    "wof:name":"Ratnagiri",
    "wof:placetype":"locality",
    "wof:population":465
},
  "geometry": {"coordinates":[75.756255,18.842577],"type":"Point"}
}