{
  "type": "Feature",
  "properties": {
    "gn:admin1_code":"36",
    "gn:admin2_code":"176.0",
    "gn:asciiname":"Talak Purwa",
    "gn:country_code":"IN",
    "gn:dem":123,
    "gn:feature_class":"P",
    "gn:feature_code":"PPL",
    "gn:name":"Tal\u0101k Purwa",
    "gn:population":0,
    "gn:timezone":"Asia/Kolkata",
    "iso:country":"IN",
    "wof:name":"Talak Purwa",
    "wof:placetype":"locality"
},
  "geometry": {"coordinates":[81.09466999999999,26.91892],"type":"Point"}
}