{
  "type": "Feature",
  "properties": {
    "iso:country":"IN",
    "ks:ks_alt_nam":"2 DPN",
    "ks:ks_name":"2 Dpn",
    "ks:ks_pop":44,
    "ks:ks_type":"HABITATION",
    "name:eng_x_preferred":[
        "2 Dpn"
    ],
    "wof:name":"2 Dpn",
    "wof:placetype":"locality",
    "wof:population":44
},
  "geometry": {"coordinates":[75.103274,29.172289],"type":"Point"}
}