{
  "type": "Feature",
  "properties": {
    "iso:country":"IN",
    "ks:ks_name":"Padari",
    "ks:ks_pop":99,
    "ks:ks_type":"VILLAGE",
    "name:eng_x_preferred":[
        "Padari"
    ],
    "wof:name":"Padari",
    "wof:placetype":"locality",
    "wof:population":99
},
  "geometry": {"coordinates":[87.644514,24.852039],"type":"Point"}
}