{
  "type": "Feature",
  "properties": {
    "iso:country":"IN",
    "ks:ks_name":"Bishunpur Jainarayan Urf Cham.",
    "ks:ks_pop":2081,
    "ks:ks_type":"VILLAGE",
    "name:eng_x_preferred":[
        "Bishunpur Jainarayan Urf Cham."
    ],
    "wof:name":"Bishunpur Jainarayan Urf Cham.",
    "wof:placetype":"locality",
    "wof:population":2081
},
  "geometry": {"coordinates":[85.583106,25.918538],"type":"Point"}
}