{
  "type": "Feature",
  "properties": {
    "gn:admin1_code":"34.0",
    "gn:admin2_code":"221.0",
    "gn:asciiname":"Sarhad Madho",
    "gn:country_code":"IN",
    "gn:dem":51,
    "gn:feature_class":"P",
    "gn:feature_code":"PPL",
    "gn:name":"Sarhad M\u0101dho",
    "gn:population":0,
    "gn:timezone":"Asia/Kolkata",
    "iso:country":"IN",
    "name:eng_x_preferred":[
        "Sarhad M\u0101dho"
    ],
    "wof:name":"Sarhad Madho",
    "wof:placetype":"locality"
},
  "geometry": {"coordinates":[85.62994,25.58031],"type":"Point"}
}