{
  "type": "Feature",
  "properties": {
    "iso:country":"IN",
    "ks:ks_alt_nam":"Bayyannachervu thanda",
    "ks:ks_name":"Bayyannachervu Thanda",
    "ks:ks_pop":416,
    "ks:ks_type":"HABITATION",
    "name:eng_x_preferred":[
        "Bayyannachervu Thanda"
    ],
    "wof:name":"Bayyannachervu Thanda",
    "wof:placetype":"locality",
    "wof:population":416
},
  "geometry": {"coordinates":[79.148145,17.982343],"type":"Point"}
}