{
  "type": "Feature",
  "properties": {
    "gn:admin1_code":"36",
    "gn:admin2_code":"188.0",
    "gn:asciiname":"Usri",
    "gn:country_code":"IN",
    "gn:dem":75,
    "gn:feature_class":"P",
    "gn:feature_code":"PPL",
    "gn:name":"Usri",
    "gn:population":0,
    "gn:timezone":"Asia/Kolkata",
    "iso:country":"IN",
    "ks:ks_name":"Usri",
    "ks:ks_type":"VILLAGE",
    "name:eng_x_preferred":[
        "Usri"
    ],
    "wof:name":"Usri",
    "wof:placetype":"locality"
},
  "geometry": {"coordinates":[83.49323,26.296554],"type":"Point"}
}