{
  "type": "Feature",
  "properties": {
    "iso:country":"IN",
    "ks:ks_name":"10 O",
    "ks:ks_pop":666,
    "ks:ks_type":"VILLAGE",
    "name:eng_x_preferred":[
        "10 O"
    ],
    "wof:name":"10 O",
    "wof:placetype":"locality",
    "wof:population":666
},
  "geometry": {"coordinates":[73.562358,29.838811],"type":"Point"}
}