{
  "type": "Feature",
  "properties": {
    "gn:admin1_code":"23.0",
    "gn:admin2_code":"35.0",
    "gn:asciiname":"Kukar",
    "gn:country_code":"IN",
    "gn:dem":256,
    "gn:feature_class":"P",
    "gn:feature_code":"PPL",
    "gn:name":"Kukar",
    "gn:population":0,
    "gn:timezone":"Asia/Kolkata",
    "iso:country":"IN",
    "ks:ks_name":"Kukar",
    "ks:ks_pop":210,
    "ks:ks_type":"VILLAGE",
    "name:eng_x_preferred":[
        "Kukar"
    ],
    "name:swe_x_preferred":[
        "Kukar"
    ],
    "wof:name":"Kukar",
    "wof:placetype":"locality",
    "wof:population":210
},
  "geometry": {"coordinates":[75.320156,32.198671],"type":"Point"}
}