{
  "type": "Feature",
  "properties": {
    "gn:admin1_code":"23.0",
    "gn:admin2_code":"35.0",
    "gn:asciiname":"Kukar",
    "gn:country_code":"IN",
    "gn:dem":256,
    "gn:feature_class":"P",
    "gn:feature_code":"PPL",
    "gn:name":"Kukar",
    "gn:population":0,
    "gn:timezone":"Asia/Kolkata",
    "iso:country":"IN",
    "name:swe_x_preferred":[
        "Kukar"
    ],
    "wof:name":"Kukar",
    "wof:placetype":"locality"
},
  "geometry": {"coordinates":[75.33433000000002,32.19634],"type":"Point"}
}