{
  "type": "Feature",
  "properties": {
    "gn:admin1_code":"02",
    "gn:admin2_code":"554.0",
    "gn:asciiname":"Rayalapeta",
    "gn:country_code":"IN",
    "gn:dem":732,
    "gn:feature_class":"P",
    "gn:feature_code":"PPL",
    "gn:name":"R\u0101yalapeta",
    "gn:population":0,
    "gn:timezone":"Asia/Kolkata",
    "iso:country":"IN",
    "wof:name":"Rayalapeta",
    "wof:placetype":"locality"
},
  "geometry": {"coordinates":[78.72509000000002,13.32986],"type":"Point"}
}