{
  "type": "Feature",
  "properties": {
    "gn:admin1_code":"10.0",
    "gn:admin2_code":"69.0",
    "gn:asciiname":"Khetri",
    "gn:country_code":"IN",
    "gn:dem":623,
    "gn:feature_class":"P",
    "gn:feature_code":"PPL",
    "gn:name":"Khetri",
    "gn:population":0,
    "gn:timezone":"Asia/Kolkata",
    "iso:country":"IN",
    "name:ben_x_preferred":[
        "\u0996\u09c7\u09a4\u09cd\u09b0\u09bf"
    ],
    "name:bpy_x_preferred":[
        "\u0996\u09c7\u09a4\u09cd\u09b0\u09bf"
    ],
    "name:cat_x_preferred":[
        "Khetri"
    ],
    "name:ceb_x_preferred":[
        "Khetri"
    ],
    "name:hin_x_preferred":[
        "\u0916\u0947\u0924\u0921\u093c\u0940"
    ],
    "name:ita_x_preferred":[
        "Khetri"
    ],
    "name:mlg_x_preferred":[
        "Khetri"
    ],
    "name:msa_x_preferred":[
        "Khetri"
    ],
    "name:new_x_preferred":[
        "\u0916\u0947\u0930\u094d\u0924\u0940"
    ],
    "name:swe_x_preferred":[
        "Khetri"
    ],
    "name:urd_x_preferred":[
        "\u06a9\u06be\u06cc\u062a\u0691\u06cc"
    ],
    "name:vie_x_preferred":[
        "Khetri"
    ],
    "name:zho_x_preferred":[
        "\u51ef\u7279\u91cc"
    ],
    "wof:name":"Khetri",
    "wof:placetype":"locality"
},
  "geometry": {"coordinates":[77.06036,30.68184],"type":"Point"}
}