{
  "type": "Feature",
  "properties": {
    "iso:country":"IN",
    "ks:ks_alt_nam":"Rangenahalli Junction Railroad Station",
    "ks:ks_name":"Rangenahalli",
    "ks:ks_type":"VILLAGE",
    "name:eng_x_preferred":[
        "Rangenahalli"
    ],
    "name:eng_x_variant":[
        "Rangenahalli Junction Railroad Station"
    ],
    "wof:name":"Rangenahalli",
    "wof:placetype":"locality"
},
  "geometry": {"coordinates":[75.69655899999999,13.707837],"type":"Point"}
}