{
  "type": "Feature",
  "properties": {
    "iso:country":"IN",
    "ks:ks_name":"Jagadalewasti",
    "ks:ks_pop":188,
    "ks:ks_type":"HABITATION",
    "ks:ks_uagg_main":0,
    "name:eng_x_preferred":[
        "Jagadalewasti"
    ],
    "wof:name":"Jagadalewasti",
    "wof:placetype":"neighbourhood",
    "wof:population":188
},
  "geometry": {"coordinates":[75.126744,18.669567],"type":"Point"}
}