{
  "type": "Feature",
  "properties": {
    "iso:country":"IN",
    "ks:ks_name":"Gajula Vadde Palle",
    "ks:ks_pop":62,
    "ks:ks_type":"HABITATION",
    "name:eng_x_preferred":[
        "Gajula Vadde Palle"
    ],
    "wof:name":"Gajula Vadde Palle",
    "wof:placetype":"locality",
    "wof:population":62
},
  "geometry": {"coordinates":[78.89797799999999,14.003514],"type":"Point"}
}