{
  "type": "Feature",
  "properties": {
    "gn:admin1_code":"36",
    "gn:admin2_code":"170.0",
    "gn:asciiname":"Bhadsen",
    "gn:country_code":"IN",
    "gn:dem":146,
    "gn:feature_class":"P",
    "gn:feature_code":"PPL",
    "gn:name":"Bhadsen",
    "gn:population":0,
    "gn:timezone":"Asia/Kolkata",
    "iso:country":"IN",
    "wof:name":"Bhadsen",
    "wof:placetype":"locality"
},
  "geometry": {"coordinates":[80.43956,25.15846],"type":"Point"}
}