{
  "type": "Feature",
  "properties": {
    "iso:country":"IN",
    "ks:ks_name":"Shivpada",
    "ks:ks_pop":282,
    "ks:ks_type":"HABITATION",
    "name:eng_x_preferred":[
        "Shivpada"
    ],
    "wof:name":"Shivpada",
    "wof:placetype":"locality",
    "wof:population":282
},
  "geometry": {"coordinates":[72.88467199999999,20.196493],"type":"Point"}
}