{
  "type": "Feature",
  "properties": {
    "gn:admin1_code":"36",
    "gn:admin2_code":"152.0",
    "gn:asciiname":"Itawa",
    "gn:country_code":"IN",
    "gn:dem":151,
    "gn:feature_class":"P",
    "gn:feature_code":"PPL",
    "gn:name":"Itawa",
    "gn:population":0,
    "gn:timezone":"Asia/Kolkata",
    "iso:country":"IN",
    "ks:ks_name":"Itawa",
    "ks:ks_type":"VILLAGE",
    "name:eng_x_preferred":[
        "Itawa"
    ],
    "wof:name":"Itawa",
    "wof:placetype":"locality"
},
  "geometry": {"coordinates":[79.507876,27.840878],"type":"Point"}
}