{
  "type": "Feature",
  "properties": {
    "iso:country":"IN",
    "ks:ks_name":"Sujavalpur",
    "ks:ks_pop":6699,
    "ks:ks_type":"VILLAGE",
    "ks:ks_uagg_main":0,
    "name:eng_x_preferred":[
        "Sujavalpur"
    ],
    "wof:name":"Sujavalpur",
    "wof:placetype":"neighbourhood",
    "wof:population":6699
},
  "geometry": {"coordinates":[78.933581,27.735049],"type":"Point"}
}