{
  "type": "Feature",
  "properties": {
    "iso:country":"IN",
    "ks:ks_name":"Titkumar",
    "ks:ks_pop":2500,
    "ks:ks_type":"HABITATION",
    "name:eng_x_preferred":[
        "Titkumar"
    ],
    "wof:name":"Titkumar",
    "wof:placetype":"locality",
    "wof:population":2500
},
  "geometry": {"coordinates":[88.765716,22.328007],"type":"Point"}
}