{
  "type": "Feature",
  "properties": {
    "iso:country":"IN",
    "ks:ks_name":"Perayyapeta",
    "ks:ks_pop":689,
    "ks:ks_type":"HABITATION",
    "name:eng_x_preferred":[
        "Perayyapeta"
    ],
    "wof:name":"Perayyapeta",
    "wof:placetype":"locality",
    "wof:population":689
},
  "geometry": {"coordinates":[82.01264500000001,16.607107],"type":"Point"}
}