{
  "type": "Feature",
  "properties": {
    "iso:country":"IN",
    "ks:ks_name":"Pura Ki Nagariya",
    "ks:ks_pop":299,
    "ks:ks_type":"HABITATION",
    "name:eng_x_preferred":[
        "Pura Ki Nagariya"
    ],
    "wof:name":"Pura Ki Nagariya",
    "wof:placetype":"locality",
    "wof:population":299
},
  "geometry": {"coordinates":[78.475555,27.021892],"type":"Point"}
}