{
  "type": "Feature",
  "properties": {
    "iso:country":"IN",
    "ks:ks_name":"Pirthi Chak",
    "ks:ks_pop":84,
    "ks:ks_type":"VILLAGE",
    "ks:ks_uagg_main":0,
    "name:eng_x_preferred":[
        "Pirthi Chak"
    ],
    "wof:name":"Pirthi Chak",
    "wof:placetype":"neighbourhood",
    "wof:population":84
},
  "geometry": {"coordinates":[83.81285699999999,24.337342],"type":"Point"}
}