{
  "type": "Feature",
  "properties": {
    "iso:country":"IN",
    "ks:ks_name":"Kopasa Faliya",
    "ks:ks_pop":80,
    "ks:ks_type":"HABITATION",
    "name:eng_x_preferred":[
        "Kopasa Faliya"
    ],
    "wof:name":"Kopasa Faliya",
    "wof:placetype":"locality",
    "wof:population":80
},
  "geometry": {"coordinates":[73.466487,23.712705],"type":"Point"}
}