{
  "type": "Feature",
  "properties": {
    "gn:admin1_code":"36.0",
    "gn:admin2_code":"138.0",
    "gn:asciiname":"Kherki Muzakkipur",
    "gn:country_code":"IN",
    "gn:dem":225,
    "gn:feature_class":"P",
    "gn:feature_code":"PPL",
    "gn:name":"Kherki Muzakk\u012bpur",
    "gn:population":0,
    "gn:timezone":"Asia/Kolkata",
    "iso:country":"IN",
    "wof:name":"Kherki Muzakkipur",
    "wof:placetype":"locality"
},
  "geometry": {"coordinates":[77.58081,28.97603],"type":"Point"}
}