{
  "type": "Feature",
  "properties": {
    "gn:admin1_code":"19.0",
    "gn:admin2_code":"583.0",
    "gn:asciiname":"Tonchinkuppe",
    "gn:country_code":"IN",
    "gn:dem":864,
    "gn:feature_class":"P",
    "gn:feature_code":"PPL",
    "gn:name":"Tonchinkuppe",
    "gn:population":0,
    "gn:timezone":"Asia/Kolkata",
    "iso:country":"IN",
    "ks:ks_name":"Tonachinakuppe",
    "ks:ks_pop":716,
    "ks:ks_type":"VILLAGE",
    "ks:ks_uagg_main":0,
    "name:eng_x_preferred":[
        "Tonachinakuppe"
    ],
    "wof:name":"Tonachinakuppe",
    "wof:placetype":"locality",
    "wof:population":716
},
  "geometry": {"coordinates":[77.34630900000001,13.14052],"type":"Point"}
}