{
  "type": "Feature",
  "properties": {
    "iso:country":"IN",
    "ks:ks_alt_nam":"kalanalaborokachari",
    "ks:ks_name":"Kalanalaborokachari",
    "ks:ks_pop":100,
    "ks:ks_type":"HABITATION",
    "name:eng_x_preferred":[
        "Kalanalaborokachari"
    ],
    "wof:name":"Kalanalaborokachari",
    "wof:placetype":"locality",
    "wof:population":100
},
  "geometry": {"coordinates":[92.813678,25.696938],"type":"Point"}
}