{
  "type": "Feature",
  "properties": {
    "iso:country":"IN",
    "ks:ks_name":"Sarnawas",
    "ks:ks_pop":927,
    "ks:ks_type":"HABITATION",
    "name:eng_x_preferred":[
        "Sarnawas"
    ],
    "wof:name":"Sarnawas",
    "wof:placetype":"locality",
    "wof:population":927
},
  "geometry": {"coordinates":[71.720314,24.864311],"type":"Point"}
}