{
  "type": "Feature",
  "properties": {
    "gn:admin1_code":"19.0",
    "gn:admin2_code":"582.0",
    "gn:asciiname":"Cbikhoshalli",
    "gn:country_code":"IN",
    "gn:dem":777,
    "gn:feature_class":"P",
    "gn:feature_code":"PPL",
    "gn:name":"Cbikhoshalli",
    "gn:population":0,
    "gn:timezone":"Asia/Kolkata",
    "iso:country":"IN",
    "wof:name":"Cbikhoshalli",
    "wof:placetype":"neighbourhood"
},
  "geometry": {"coordinates":[77.52691,13.45669],"type":"Point"}
}