{
  "type": "Feature",
  "properties": {
    "gn:admin1_code":"36",
    "gn:admin2_code":"136.0",
    "gn:asciiname":"Saidaliganj Banjaria",
    "gn:country_code":"IN",
    "gn:dem":200,
    "gn:feature_class":"P",
    "gn:feature_code":"PPL",
    "gn:name":"Saidal\u012bganj Banjaria",
    "gn:population":0,
    "gn:timezone":"Asia/Kolkata",
    "iso:country":"IN",
    "wof:name":"Saidaliganj Banjaria",
    "wof:placetype":"locality"
},
  "geometry": {"coordinates":[78.96082,28.88743],"type":"Point"}
}