{
  "type": "Feature",
  "properties": {
    "gn:admin1_code":"13.0",
    "gn:admin2_code":"593.0",
    "gn:asciiname":"Konnakkalkadavu",
    "gn:country_code":"IN",
    "gn:dem":114,
    "gn:feature_class":"P",
    "gn:feature_code":"PPL",
    "gn:name":"Konnakkalkadavu",
    "gn:population":0,
    "gn:timezone":"Asia/Kolkata",
    "iso:country":"IN",
    "ks:ks_alt_nam":"Ponnikkel kadavu",
    "ks:ks_name":"Ponnikkel Kadavu",
    "ks:ks_pop":250,
    "ks:ks_type":"HABITATION",
    "name:eng_x_preferred":[
        "Ponnikkel Kadavu"
    ],
    "name:eng_x_variant":[
        "Konnakkalkadavu"
    ],
    "wof:name":"Ponnikkel Kadavu",
    "wof:placetype":"locality",
    "wof:population":250
},
  "geometry": {"coordinates":[76.485918,10.525989],"type":"Point"}
}