{
  "type": "Feature",
  "properties": {
    "iso:country":"IN",
    "ks:ks_name":"Karigar Purwa",
    "ks:ks_pop":190,
    "ks:ks_type":"HABITATION",
    "name:eng_x_preferred":[
        "Karigar Purwa"
    ],
    "wof:name":"Karigar Purwa",
    "wof:placetype":"locality",
    "wof:population":190
},
  "geometry": {"coordinates":[81.17440000000001,25.276383],"type":"Point"}
}