{
  "type": "Feature",
  "properties": {
    "iso:country":"IN",
    "ks:ks_name":"Nibiya",
    "ks:ks_pop":11,
    "ks:ks_type":"VILLAGE",
    "name:eng_x_preferred":[
        "Nibiya"
    ],
    "wof:name":"Nibiya",
    "wof:placetype":"locality",
    "wof:population":11
},
  "geometry": {"coordinates":[70.706069,26.797905],"type":"Point"}
}