{
  "type": "Feature",
  "properties": {
    "gn:admin1_code":"34.0",
    "gn:admin2_code":"226.0",
    "gn:asciiname":"Kothua",
    "gn:country_code":"IN",
    "gn:dem":66,
    "gn:feature_class":"P",
    "gn:feature_code":"PPL",
    "gn:name":"Kothua",
    "gn:population":0,
    "gn:timezone":"Asia/Kolkata",
    "iso:country":"IN",
    "ks:ks_name":"Kothwa",
    "ks:ks_pop":240,
    "ks:ks_type":"VILLAGE",
    "name:eng_x_preferred":[
        "Kothwa"
    ],
    "name:eng_x_variant":[
        "Kothua"
    ],
    "wof:name":"Kothwa",
    "wof:placetype":"locality",
    "wof:population":240
},
  "geometry": {"coordinates":[86.432648,25.196078],"type":"Point"}
}