{
  "type": "Feature",
  "properties": {
    "iso:country":"IN",
    "ks:ks_name":"Wali",
    "ks:ks_pop":839,
    "ks:ks_type":"HABITATION",
    "name:eng_x_preferred":[
        "Wali"
    ],
    "wof:name":"Wali",
    "wof:placetype":"locality",
    "wof:population":839
},
  "geometry": {"coordinates":[74.814359,23.516175],"type":"Point"}
}