{
  "type": "Feature",
  "properties": {
    "iso:country":"IN",
    "ks:ks_name":"Kashipur",
    "ks:ks_pop":429,
    "ks:ks_type":"HABITATION",
    "name:eng_x_preferred":[
        "Kashipur"
    ],
    "wof:name":"Kashipur",
    "wof:placetype":"locality",
    "wof:population":429
},
  "geometry": {"coordinates":[85.149856,25.341987],"type":"Point"}
}