{
  "type": "Feature",
  "properties": {
    "gn:admin1_code":"39",
    "gn:admin2_code":"61.0",
    "gn:asciiname":"Kandai",
    "gn:country_code":"IN",
    "gn:dem":1171,
    "gn:feature_class":"P",
    "gn:feature_code":"PPL",
    "gn:name":"K\u0101nd\u0101i",
    "gn:population":0,
    "gn:timezone":"Asia/Kolkata",
    "iso:country":"IN",
    "wof:name":"Kandai",
    "wof:placetype":"locality"
},
  "geometry": {"coordinates":[78.85805000000001,29.76254],"type":"Point"}
}