{
  "type": "Feature",
  "properties": {
    "iso:country":"IN",
    "ks:ks_name":"Gothe",
    "ks:ks_pop":280,
    "ks:ks_type":"HABITATION",
    "name:eng_x_preferred":[
        "Gothe"
    ],
    "wof:name":"Gothe",
    "wof:placetype":"locality",
    "wof:population":280
},
  "geometry": {"coordinates":[75.666555,16.235364],"type":"Point"}
}