{
  "type": "Feature",
  "properties": {
    "iso:country":"IN",
    "ks:ks_name":"Batilgad",
    "ks:ks_pop":158,
    "ks:ks_type":"HABITATION",
    "name:eng_x_preferred":[
        "Batilgad"
    ],
    "wof:name":"Batilgad",
    "wof:placetype":"locality",
    "wof:population":158
},
  "geometry": {"coordinates":[80.597962,19.940094],"type":"Point"}
}