{
  "type": "Feature",
  "properties": {
    "iso:country":"IN",
    "ks:ks_name":"18 PBN-B",
    "ks:ks_pop":104,
    "ks:ks_type":"VILLAGE",
    "name:eng_x_preferred":[
        "18 PBN-B"
    ],
    "wof:name":"18 PBN-B",
    "wof:placetype":"locality",
    "wof:population":104
},
  "geometry": {"coordinates":[74.01843100000001,29.474403],"type":"Point"}
}