{
  "type": "Feature",
  "properties": {
    "gn:admin1_code":"39.0",
    "gn:admin2_code":"63.0",
    "gn:asciiname":"Uttardug",
    "gn:country_code":"IN",
    "gn:dem":1333,
    "gn:feature_class":"P",
    "gn:feature_code":"PPL",
    "gn:name":"Uttardug",
    "gn:population":0,
    "gn:timezone":"Asia/Kolkata",
    "iso:country":"IN",
    "ks:ks_name":"Uttardug",
    "ks:ks_type":"VILLAGE",
    "name:eng_x_preferred":[
        "Uttardug"
    ],
    "wof:name":"Uttardug",
    "wof:placetype":"locality"
},
  "geometry": {"coordinates":[79.971917,29.880086],"type":"Point"}
}