{
  "type": "Feature",
  "properties": {
    "iso:country":"IN",
    "ks:ks_name":"Badkhed",
    "ks:ks_pop":582,
    "ks:ks_type":"VILLAGE",
    "ks:ks_uagg_main":0,
    "name:eng_x_preferred":[
        "Badkhed"
    ],
    "wof:name":"Badkhed",
    "wof:placetype":"neighbourhood",
    "wof:population":582
},
  "geometry": {"coordinates":[76.81404499999999,21.130033],"type":"Point"}
}