{
  "type": "Feature",
  "properties": {
    "gn:admin1_code":"38.0",
    "gn:admin2_code":"351.0",
    "gn:asciiname":"Gudia",
    "gn:country_code":"IN",
    "gn:dem":82,
    "gn:feature_class":"P",
    "gn:feature_code":"PPL",
    "gn:name":"Gudia",
    "gn:population":0,
    "gn:timezone":"Asia/Kolkata",
    "iso:country":"IN",
    "ks:ks_name":"Gudia",
    "ks:ks_pop":322,
    "ks:ks_type":"VILLAGE",
    "ks:ks_uagg_main":0,
    "name:eng_x_preferred":[
        "Gudia"
    ],
    "wof:name":"Gudia",
    "wof:placetype":"neighbourhood",
    "wof:population":322
},
  "geometry": {"coordinates":[87.31223900000001,25.021603],"type":"Point"}
}