{
  "type": "Feature",
  "properties": {
    "gn:admin1_code":"2.0",
    "gn:admin2_code":"553.0",
    "gn:asciiname":"Chinnaeddulapalle",
    "gn:country_code":"IN",
    "gn:dem":606,
    "gn:feature_class":"P",
    "gn:feature_code":"PPL",
    "gn:name":"Chinnaeddulapalle",
    "gn:population":0,
    "gn:timezone":"Asia/Kolkata",
    "iso:country":"IN",
    "wof:name":"Chinnaeddulapalle",
    "wof:placetype":"locality"
},
  "geometry": {"coordinates":[78.22083000000001,13.81584],"type":"Point"}
}