{
  "type": "Feature",
  "properties": {
    "gn:admin1_code":"19.0",
    "gn:admin2_code":"570",
    "gn:asciiname":"Gonebidu",
    "gn:country_code":"IN",
    "gn:dem":927,
    "gn:feature_class":"P",
    "gn:feature_code":"PPL",
    "gn:name":"Gonebidu",
    "gn:population":0,
    "gn:timezone":"Asia/Kolkata",
    "iso:country":"IN",
    "name:und_x_variant":[
        "Gonibid",
        "Gonebidu"
    ],
    "wof:name":"Gonebidu",
    "wof:placetype":"locality"
},
  "geometry": {"coordinates":[75.70814,13.08835],"type":"Point"}
}