{
  "type": "Feature",
  "properties": {
    "iso:country":"IN",
    "ks:ks_name":"Korakara",
    "ks:ks_pop":480,
    "ks:ks_type":"VILLAGE",
    "name:eng_x_preferred":[
        "Korakara"
    ],
    "wof:name":"Korakara",
    "wof:placetype":"locality",
    "wof:population":480
},
  "geometry": {"coordinates":[86.120818,20.852725],"type":"Point"}
}