{
  "type": "Feature",
  "properties": {
    "gn:admin1_code":"19.0",
    "gn:admin2_code":"582.0",
    "gn:asciiname":"Cheruvukindapalli",
    "gn:country_code":"IN",
    "gn:dem":785,
    "gn:feature_class":"P",
    "gn:feature_code":"PPL",
    "gn:name":"Cheruvukindapalli",
    "gn:population":0,
    "gn:timezone":"Asia/Kolkata",
    "iso:country":"IN",
    "wof:name":"Cheruvukindapalli",
    "wof:placetype":"locality"
},
  "geometry": {"coordinates":[77.94682,13.63979],"type":"Point"}
}