{
  "type": "Feature",
  "properties": {
    "iso:country":"IN",
    "ks:ks_name":"Karayathumchal",
    "ks:ks_pop":1501,
    "ks:ks_type":"HABITATION",
    "name:eng_x_preferred":[
        "Karayathumchal"
    ],
    "wof:name":"Karayathumchal",
    "wof:placetype":"locality",
    "wof:population":1501
},
  "geometry": {"coordinates":[75.52047899999999,12.094307],"type":"Point"}
}