{
  "type": "Feature",
  "properties": {
    "iso:country":"IN",
    "ks:ks_name":"Dadawa",
    "ks:ks_pop":366,
    "ks:ks_type":"HABITATION",
    "name:eng_x_preferred":[
        "Dadawa"
    ],
    "wof:name":"Dadawa",
    "wof:placetype":"locality",
    "wof:population":366
},
  "geometry": {"coordinates":[83.32959200000001,25.203361],"type":"Point"}
}