{
  "type": "Feature",
  "properties": {
    "gn:admin1_code":"39.0",
    "gn:admin2_code":"63.0",
    "gn:asciiname":"Dumlot",
    "gn:country_code":"IN",
    "gn:dem":1688,
    "gn:feature_class":"P",
    "gn:feature_code":"PPL",
    "gn:name":"Dumlot",
    "gn:population":0,
    "gn:timezone":"Asia/Kolkata",
    "iso:country":"IN",
    "ks:ks_name":"Dumlot",
    "ks:ks_type":"VILLAGE",
    "name:eng_x_preferred":[
        "Dumlot"
    ],
    "wof:name":"Dumlot",
    "wof:placetype":"locality"
},
  "geometry": {"coordinates":[79.565586,29.868812],"type":"Point"}
}