{
  "type": "Feature",
  "properties": {
    "iso:country":"IN",
    "ks:ks_alt_nam":"Dhaniyajhor FV",
    "ks:ks_name":"Dhaniyajhor Fv",
    "ks:ks_pop":256,
    "ks:ks_type":"HABITATION",
    "name:eng_x_preferred":[
        "Dhaniyajhor Fv"
    ],
    "wof:name":"Dhaniyajhor Fv",
    "wof:placetype":"locality",
    "wof:population":256
},
  "geometry": {"coordinates":[80.720979,22.259592],"type":"Point"}
}