{
  "type": "Feature",
  "properties": {
    "gn:admin1_code":"39.0",
    "gn:admin2_code":"66.0",
    "gn:asciiname":"Timar",
    "gn:country_code":"IN",
    "gn:dem":1488,
    "gn:feature_class":"P",
    "gn:feature_code":"PPL",
    "gn:name":"Timar",
    "gn:population":0,
    "gn:timezone":"Asia/Kolkata",
    "iso:country":"IN",
    "name:ara_x_preferred":[
        "\u062a\u064a\u0645\u0627\u0631"
    ],
    "name:bos_x_preferred":[
        "Timar"
    ],
    "name:bul_x_preferred":[
        "\u0422\u0438\u043c\u0430\u0440"
    ],
    "name:ces_x_preferred":[
        "Timar"
    ],
    "name:deu_x_preferred":[
        "T\u0131mar"
    ],
    "name:ell_x_preferred":[
        "\u03a4\u03b9\u03bc\u03ac\u03c1\u03b9\u03bf"
    ],
    "name:fra_x_preferred":[
        "Timar"
    ],
    "name:heb_x_preferred":[
        "\u05d8\u05d9\u05de\u05d0\u05e8"
    ],
    "name:ita_x_preferred":[
        "Timar"
    ],
    "name:mkd_x_preferred":[
        "\u0422\u0438\u043c\u0430\u0440"
    ],
    "name:pol_x_preferred":[
        "Timar"
    ],
    "name:rus_x_preferred":[
        "\u0422\u0438\u043c\u0430\u0440"
    ],
    "name:slv_x_preferred":[
        "Timar"
    ],
    "name:sqi_x_preferred":[
        "Timari"
    ],
    "name:srp_x_preferred":[
        "Timar"
    ],
    "name:tur_x_preferred":[
        "T\u0131mar"
    ],
    "name:ukr_x_preferred":[
        "\u0422\u0456\u043c\u0430\u0440"
    ],
    "wof:name":"Timar",
    "wof:placetype":"locality"
},
  "geometry": {"coordinates":[79.72606,29.26889000000001],"type":"Point"}
}