{
  "type": "Feature",
  "properties": {
    "gn:admin1_code":"23",
    "gn:admin2_code":"48.0",
    "gn:asciiname":"Hasampur",
    "gn:country_code":"IN",
    "gn:dem":273,
    "gn:feature_class":"P",
    "gn:feature_code":"PPL",
    "gn:name":"Hasampur",
    "gn:population":0,
    "gn:timezone":"Asia/Kolkata",
    "iso:country":"IN",
    "wof:name":"Hasampur",
    "wof:placetype":"locality"
},
  "geometry": {"coordinates":[76.66136999999998,30.43143],"type":"Point"}
}