{
  "type": "Feature",
  "properties": {
    "iso:country":"IN",
    "ks:ks_name":"Gangaram Guttala",
    "ks:ks_pop":118,
    "ks:ks_type":"HABITATION",
    "name:eng_x_preferred":[
        "Gangaram Guttala"
    ],
    "wof:name":"Gangaram Guttala",
    "wof:placetype":"locality",
    "wof:population":118
},
  "geometry": {"coordinates":[80.366795,18.568706],"type":"Point"}
}