{
  "type": "Feature",
  "properties": {
    "iso:country":"IN",
    "ks:ks_name":"Dhediya No Nal",
    "ks:ks_pop":143,
    "ks:ks_type":"HABITATION",
    "name:eng_x_preferred":[
        "Dhediya No Nal"
    ],
    "wof:name":"Dhediya No Nal",
    "wof:placetype":"locality",
    "wof:population":143
},
  "geometry": {"coordinates":[73.928972,23.04125],"type":"Point"}
}