{
  "type": "Feature",
  "properties": {
    "iso:country":"IN",
    "ks:ks_name":"Vadi Udafa",
    "ks:ks_pop":203,
    "ks:ks_type":"VILLAGE",
    "name:eng_x_preferred":[
        "Vadi Udafa"
    ],
    "wof:name":"Vadi Udafa",
    "wof:placetype":"locality",
    "wof:population":203
},
  "geometry": {"coordinates":[73.61071699999999,23.175443],"type":"Point"}
}