{
  "type": "Feature",
  "properties": {
    "iso:country":"IN",
    "ks:ks_name":"Merha",
    "ks:ks_pop":60,
    "ks:ks_type":"VILLAGE",
    "name:eng_x_preferred":[
        "Merha"
    ],
    "wof:name":"Merha",
    "wof:placetype":"locality",
    "wof:population":60
},
  "geometry": {"coordinates":[85.33951399999999,23.209667],"type":"Point"}
}