{
  "type": "Feature",
  "properties": {
    "iso:country":"IN",
    "ks:ks_name":"Balewada",
    "ks:ks_pop":341,
    "ks:ks_type":"HABITATION",
    "name:eng_x_preferred":[
        "Balewada"
    ],
    "wof:name":"Balewada",
    "wof:placetype":"locality",
    "wof:population":341
},
  "geometry": {"coordinates":[74.262303,14.870014],"type":"Point"}
}