{
  "type": "Feature",
  "properties": {
    "iso:country":"IN",
    "ks:ks_name":"Neuri Harijan Basti",
    "ks:ks_pop":470,
    "ks:ks_type":"HABITATION",
    "name:eng_x_preferred":[
        "Neuri Harijan Basti"
    ],
    "wof:name":"Neuri Harijan Basti",
    "wof:placetype":"locality",
    "wof:population":470
},
  "geometry": {"coordinates":[82.86998699999999,26.379335],"type":"Point"}
}