{
  "type": "Feature",
  "properties": {
    "gn:admin1_code":"2.0",
    "gn:admin2_code":"551.0",
    "gn:asciiname":"Bhakarapeta",
    "gn:country_code":"IN",
    "gn:dem":124,
    "gn:feature_class":"P",
    "gn:feature_code":"PPL",
    "gn:name":"Bhakarapeta",
    "gn:population":0,
    "gn:timezone":"Asia/Kolkata",
    "iso:country":"IN",
    "ks:ks_name":"Bhakarapeta",
    "ks:ks_pop":956,
    "ks:ks_type":"HABITATION",
    "name:eng_x_preferred":[
        "Bhakarapeta"
    ],
    "wof:name":"Bhakarapeta",
    "wof:placetype":"locality",
    "wof:population":956
},
  "geometry": {"coordinates":[79.050392,14.710268],"type":"Point"}
}