{
  "type": "Feature",
  "properties": {
    "gn:admin1_code":"11.0",
    "gn:admin2_code":"31.0",
    "gn:asciiname":"Rajiman",
    "gn:country_code":"IN",
    "gn:dem":1053,
    "gn:feature_class":"P",
    "gn:feature_code":"PPL",
    "gn:name":"Raj\u012bman",
    "gn:population":0,
    "gn:timezone":"Asia/Kolkata",
    "iso:country":"IN",
    "wof:name":"Rajiman",
    "wof:placetype":"locality"
},
  "geometry": {"coordinates":[77.01034,30.99853],"type":"Point"}
}