{
  "type": "Feature",
  "properties": {
    "gn:admin1_code":"2.0",
    "gn:admin2_code":"550.0",
    "gn:asciiname":"Padugupadu",
    "gn:country_code":"IN",
    "gn:dem":23,
    "gn:feature_class":"P",
    "gn:feature_code":"PPL",
    "gn:name":"Padugup\u0101du",
    "gn:population":0,
    "gn:timezone":"Asia/Kolkata",
    "iso:country":"IN",
    "ks:ks_alt_nam":"Padugup\u0101du",
    "ks:ks_name":"Padugupadu",
    "ks:ks_pop":7440,
    "ks:ks_type":"VILLAGE",
    "ks:ks_uagg_main":0,
    "name:eng_x_preferred":[
        "Padugupadu"
    ],
    "name:eng_x_variant":[
        "Padugup\u0101du"
    ],
    "wof:name":"Padugupadu",
    "wof:placetype":"neighbourhood",
    "wof:population":7440
},
  "geometry": {"coordinates":[79.99154900000001,14.48907],"type":"Point"}
}