{
  "type": "Feature",
  "properties": {
    "iso:country":"IN",
    "ks:ks_name":"Chidambarampillaikadu",
    "ks:ks_pop":616,
    "ks:ks_type":"HABITATION",
    "name:eng_x_preferred":[
        "Chidambarampillaikadu"
    ],
    "wof:name":"Chidambarampillaikadu",
    "wof:placetype":"locality",
    "wof:population":616
},
  "geometry": {"coordinates":[79.71674,10.414843],"type":"Point"}
}