{
  "type": "Feature",
  "properties": {
    "iso:country":"IN",
    "ks:ks_alt_nam":"Notun Mati F.V",
    "ks:ks_name":"Notun Mati F.v",
    "ks:ks_pop":250,
    "ks:ks_type":"HABITATION",
    "name:eng_x_preferred":[
        "Notun Mati F.v"
    ],
    "wof:name":"Notun Mati F.v",
    "wof:placetype":"locality",
    "wof:population":250
},
  "geometry": {"coordinates":[90.72628400000001,26.641729],"type":"Point"}
}