{
  "type": "Feature",
  "properties": {
    "iso:country":"IN",
    "ks:ks_alt_nam":"NIMDANGA",
    "ks:ks_name":"Nimdanga",
    "ks:ks_pop":248,
    "ks:ks_type":"HABITATION",
    "name:eng_x_preferred":[
        "Nimdanga"
    ],
    "wof:name":"Nimdanga",
    "wof:placetype":"locality",
    "wof:population":248
},
  "geometry": {"coordinates":[86.71617999999999,22.51181],"type":"Point"}
}