{
  "type": "Feature",
  "properties": {
    "iso:country":"IN",
    "ks:ks_alt_nam":"N.Siu",
    "ks:ks_name":"N.siu",
    "ks:ks_pop":263,
    "ks:ks_type":"HABITATION",
    "name:eng_x_preferred":[
        "N.siu"
    ],
    "wof:name":"N.siu",
    "wof:placetype":"locality",
    "wof:population":263
},
  "geometry": {"coordinates":[78.217286,27.49879],"type":"Point"}
}