{
  "type": "Feature",
  "properties": {
    "iso:country":"IN",
    "ks:ks_name":"Musalman Ki Dhani",
    "ks:ks_pop":519,
    "ks:ks_type":"HABITATION",
    "name:eng_x_preferred":[
        "Musalman Ki Dhani"
    ],
    "wof:name":"Musalman Ki Dhani",
    "wof:placetype":"locality",
    "wof:population":519
},
  "geometry": {"coordinates":[70.993925,25.651089],"type":"Point"}
}