{
  "type": "Feature",
  "properties": {
    "iso:country":"IN",
    "ks:ks_name":"Kurpai",
    "ks:ks_pop":3027,
    "ks:ks_type":"VILLAGE",
    "name:eng_x_preferred":[
        "Kurpai"
    ],
    "wof:name":"Kurpai",
    "wof:placetype":"locality",
    "wof:population":3027
},
  "geometry": {"coordinates":[87.84414200000001,22.287988],"type":"Point"}
}