{
  "type": "Feature",
  "properties": {
    "gn:admin1_code":"35",
    "gn:admin2_code":"437.0",
    "gn:asciiname":"Kallukheri",
    "gn:country_code":"IN",
    "gn:dem":455,
    "gn:feature_class":"P",
    "gn:feature_code":"PPL",
    "gn:name":"Kall\u016bkheri",
    "gn:population":0,
    "gn:timezone":"Asia/Kolkata",
    "iso:country":"IN",
    "wof:name":"Kallukheri",
    "wof:placetype":"locality"
},
  "geometry": {"coordinates":[76.37772,23.13432],"type":"Point"}
}