{
  "type": "Feature",
  "properties": {
    "iso:country":"IN",
    "ks:ks_name":"Nigude",
    "ks:ks_pop":1205,
    "ks:ks_type":"VILLAGE",
    "name:eng_x_preferred":[
        "Nigude"
    ],
    "wof:name":"Nigude",
    "wof:placetype":"locality",
    "wof:population":1205
},
  "geometry": {"coordinates":[73.829627,15.826918],"type":"Point"}
}