{
  "type": "Feature",
  "properties": {
    "iso:country":"IN",
    "ks:ks_name":"Bidarahalli",
    "ks:ks_pop":188,
    "ks:ks_type":"HABITATION",
    "name:eng_x_preferred":[
        "Bidarahalli"
    ],
    "wof:name":"Bidarahalli",
    "wof:placetype":"locality",
    "wof:population":188
},
  "geometry": {"coordinates":[76.143975,13.144284],"type":"Point"}
}