{
  "type": "Feature",
  "properties": {
    "gn:admin1_code":"11",
    "gn:admin2_code":"23.0",
    "gn:asciiname":"Turi",
    "gn:country_code":"IN",
    "gn:dem":1699,
    "gn:feature_class":"P",
    "gn:feature_code":"PPL",
    "gn:name":"Turi",
    "gn:population":0,
    "gn:timezone":"Asia/Kolkata",
    "iso:country":"IN",
    "name:bel_x_preferred":[
        "\u0422\u0443\u0440\u044b"
    ],
    "name:cat_x_preferred":[
        "Turi"
    ],
    "name:ceb_x_preferred":[
        "Turi"
    ],
    "name:deu_x_preferred":[
        "Turi"
    ],
    "name:fra_x_preferred":[
        "Turi"
    ],
    "name:ind_x_preferred":[
        "Turi"
    ],
    "name:ita_x_preferred":[
        "Turi"
    ],
    "name:nld_x_preferred":[
        "Turi"
    ],
    "name:pol_x_preferred":[
        "Turi"
    ],
    "name:por_x_preferred":[
        "Turi"
    ],
    "name:ron_x_preferred":[
        "Turi"
    ],
    "name:rus_x_preferred":[
        "\u0422\u0443\u0440\u044b"
    ],
    "name:scn_x_preferred":[
        "Turi"
    ],
    "name:spa_x_preferred":[
        "Turi"
    ],
    "name:srp_x_preferred":[
        "\u0422\u0443\u0440\u0438"
    ],
    "name:swe_x_preferred":[
        "Turi"
    ],
    "name:ukr_x_preferred":[
        "\u0422\u0443\u0440\u0456"
    ],
    "wof:name":"Turi",
    "wof:placetype":"locality"
},
  "geometry": {"coordinates":[76.25351999999999,32.5745],"type":"Point"}
}