{
  "type": "Feature",
  "properties": {
    "gn:admin1_code":"35",
    "gn:admin2_code":"423.0",
    "gn:asciiname":"Rijoda",
    "gn:country_code":"IN",
    "gn:dem":424,
    "gn:feature_class":"P",
    "gn:feature_code":"PPL",
    "gn:name":"Rijoda",
    "gn:population":0,
    "gn:timezone":"Asia/Kolkata",
    "iso:country":"IN",
    "ks:ks_name":"Rijoda",
    "ks:ks_pop":753,
    "ks:ks_type":"VILLAGE",
    "name:eng_x_preferred":[
        "Rijoda"
    ],
    "wof:name":"Rijoda",
    "wof:placetype":"locality",
    "wof:population":753
},
  "geometry": {"coordinates":[78.003541,24.91733],"type":"Point"}
}