{
  "type": "Feature",
  "properties": {
    "iso:country":"IN",
    "ks:ks_alt_nam":"B.Shanubogana hally",
    "ks:ks_name":"B.shanubogana Hally",
    "ks:ks_pop":122,
    "ks:ks_type":"HABITATION",
    "name:eng_x_preferred":[
        "B.shanubogana Hally"
    ],
    "wof:name":"B.shanubogana Hally",
    "wof:placetype":"locality",
    "wof:population":122
},
  "geometry": {"coordinates":[76.671566,12.787877],"type":"Point"}
}