{
  "type": "Feature",
  "properties": {
    "gn:admin1_code":"16.0",
    "gn:admin2_code":"510.0",
    "gn:asciiname":"Pardi",
    "gn:country_code":"IN",
    "gn:dem":352,
    "gn:feature_class":"P",
    "gn:feature_code":"PPL",
    "gn:name":"P\u0101rdi",
    "gn:population":0,
    "gn:timezone":"Asia/Kolkata",
    "iso:country":"IN",
    "wof:name":"Pardi",
    "wof:placetype":"locality"
},
  "geometry": {"coordinates":[77.52469000000001,19.9294],"type":"Point"}
}