{
  "type": "Feature",
  "properties": {
    "gn:admin1_code":"3.0",
    "gn:admin2_code":"313.0",
    "gn:asciiname":"Beloguri",
    "gn:country_code":"IN",
    "gn:dem":79,
    "gn:feature_class":"P",
    "gn:feature_code":"PPL",
    "gn:name":"Beloguri",
    "gn:population":0,
    "gn:timezone":"Asia/Kolkata",
    "iso:country":"IN",
    "wof:name":"Beloguri",
    "wof:placetype":"locality"
},
  "geometry": {"coordinates":[93.59899,26.67772],"type":"Point"}
}