{
  "type": "Feature",
  "properties": {
    "iso:country":"IN",
    "ks:ks_name":"Baghodi",
    "ks:ks_pop":668,
    "ks:ks_type":"HABITATION",
    "name:eng_x_preferred":[
        "Baghodi"
    ],
    "wof:name":"Baghodi",
    "wof:placetype":"locality",
    "wof:population":668
},
  "geometry": {"coordinates":[79.45934,22.039558],"type":"Point"}
}