{
  "type": "Feature",
  "properties": {
    "iso:country":"IN",
    "ks:ks_name":"Khamkarwasti",
    "ks:ks_pop":395,
    "ks:ks_type":"HABITATION",
    "name:eng_x_preferred":[
        "Khamkarwasti"
    ],
    "wof:name":"Khamkarwasti",
    "wof:placetype":"locality",
    "wof:population":395
},
  "geometry": {"coordinates":[74.24271299999999,19.013049],"type":"Point"}
}