{
  "type": "Feature",
  "properties": {
    "iso:country":"IN",
    "ks:ks_name":"Eguvamadiga Palle",
    "ks:ks_pop":114,
    "ks:ks_type":"HABITATION",
    "name:eng_x_preferred":[
        "Eguvamadiga Palle"
    ],
    "wof:name":"Eguvamadiga Palle",
    "wof:placetype":"locality",
    "wof:population":114
},
  "geometry": {"coordinates":[78.685502,13.988922],"type":"Point"}
}