{
  "type": "Feature",
  "properties": {
    "gn:admin1_code":"36",
    "gn:admin2_code":"173.0",
    "gn:asciiname":"Nakahra Bhilamdeo",
    "gn:country_code":"IN",
    "gn:dem":92,
    "gn:feature_class":"P",
    "gn:feature_code":"PPL",
    "gn:name":"Nakahra Bh\u012blamdeo",
    "gn:population":0,
    "gn:timezone":"Asia/Kolkata",
    "iso:country":"IN",
    "wof:name":"Nakahra Bhilamdeo",
    "wof:placetype":"locality"
},
  "geometry": {"coordinates":[82.41282,25.98315],"type":"Point"}
}