{
  "type": "Feature",
  "properties": {
    "gn:admin1_code":"21",
    "gn:admin2_code":"374.0",
    "gn:asciiname":"Khuntipani",
    "gn:country_code":"IN",
    "gn:dem":327,
    "gn:feature_class":"P",
    "gn:feature_code":"PPL",
    "gn:name":"Kh\u016bntip\u0101ni",
    "gn:population":0,
    "gn:timezone":"Asia/Kolkata",
    "iso:country":"IN",
    "ks:ks_alt_nam":"Kh\u016bntip\u0101ni",
    "ks:ks_name":"Khuntipani",
    "ks:ks_type":"VILLAGE",
    "name:eng_x_preferred":[
        "Khuntipani"
    ],
    "name:eng_x_variant":[
        "Kh\u016bntip\u0101ni"
    ],
    "wof:name":"Khuntipani",
    "wof:placetype":"locality"
},
  "geometry": {"coordinates":[83.649385,21.951388],"type":"Point"}
}