{
  "type": "Feature",
  "properties": {
    "iso:country":"IN",
    "ks:ks_name":"Panjrapal",
    "ks:ks_pop":330,
    "ks:ks_type":"HABITATION",
    "name:eng_x_preferred":[
        "Panjrapal"
    ],
    "wof:name":"Panjrapal",
    "wof:placetype":"locality",
    "wof:population":330
},
  "geometry": {"coordinates":[73.239667,22.392361],"type":"Point"}
}