{
  "type": "Feature",
  "properties": {
    "gn:admin1_code":"19.0",
    "gn:admin2_code":"566.0",
    "gn:asciiname":"Palavvanahalli",
    "gn:country_code":"IN",
    "gn:dem":708,
    "gn:feature_class":"P",
    "gn:feature_code":"PPL",
    "gn:name":"P\u0101lavvanahalli",
    "gn:population":0,
    "gn:timezone":"Asia/Kolkata",
    "iso:country":"IN",
    "wof:name":"Palavvanahalli",
    "wof:placetype":"locality"
},
  "geometry": {"coordinates":[76.47954,14.14477],"type":"Point"}
}