{
  "type": "Feature",
  "properties": {
    "iso:country":"IN",
    "ks:ks_name":"Sankujaddi",
    "ks:ks_pop":43,
    "ks:ks_type":"HABITATION",
    "name:eng_x_preferred":[
        "Sankujaddi"
    ],
    "wof:name":"Sankujaddi",
    "wof:placetype":"locality",
    "wof:population":43
},
  "geometry": {"coordinates":[74.79093399999999,14.493913],"type":"Point"}
}