{
  "type": "Feature",
  "properties": {
    "iso:country":"IN",
    "ks:ks_name":"Lankewadi",
    "ks:ks_pop":121,
    "ks:ks_type":"HABITATION",
    "name:eng_x_preferred":[
        "Lankewadi"
    ],
    "wof:name":"Lankewadi",
    "wof:placetype":"locality",
    "wof:population":121
},
  "geometry": {"coordinates":[73.584396,18.810094],"type":"Point"}
}