{
  "type": "Feature",
  "properties": {
    "iso:country":"IN",
    "ks:ks_name":"Sah Tola",
    "ks:ks_pop":381,
    "ks:ks_type":"HABITATION",
    "name:eng_x_preferred":[
        "Sah Tola"
    ],
    "wof:name":"Sah Tola",
    "wof:placetype":"locality",
    "wof:population":381
},
  "geometry": {"coordinates":[86.989983,25.135057],"type":"Point"}
}