{
  "type": "Feature",
  "properties": {
    "gn:admin1_code":"36.0",
    "gn:admin2_code":"136.0",
    "gn:asciiname":"Milak Mian Ghulam Bari",
    "gn:country_code":"IN",
    "gn:dem":207,
    "gn:feature_class":"P",
    "gn:feature_code":"PPL",
    "gn:name":"Milak Mi\u0101n Ghul\u0101m B\u0101ri",
    "gn:population":0,
    "gn:timezone":"Asia/Kolkata",
    "iso:country":"IN",
    "wof:name":"Milak Mian Ghulam Bari",
    "wof:placetype":"locality"
},
  "geometry": {"coordinates":[79.14121,29.03763],"type":"Point"}
}