{
  "type": "Feature",
  "properties": {
    "gn:admin1_code":"39.0",
    "gn:admin2_code":"68.0",
    "gn:asciiname":"Kanewali Raisingh",
    "gn:country_code":"IN",
    "gn:dem":233,
    "gn:feature_class":"P",
    "gn:feature_code":"PPL",
    "gn:name":"K\u0101new\u0101li R\u0101isingh",
    "gn:population":0,
    "gn:timezone":"Asia/Kolkata",
    "iso:country":"IN",
    "wof:name":"Kanewali Raisingh",
    "wof:placetype":"locality"
},
  "geometry": {"coordinates":[78.04319,29.68734000000001],"type":"Point"}
}