{
  "type": "Feature",
  "properties": {
    "iso:country":"IN",
    "ks:ks_alt_nam":"Someshwara HC",
    "ks:ks_name":"Someshwara Hc",
    "ks:ks_pop":78,
    "ks:ks_type":"HABITATION",
    "name:eng_x_preferred":[
        "Someshwara Hc"
    ],
    "wof:name":"Someshwara Hc",
    "wof:placetype":"locality",
    "wof:population":78
},
  "geometry": {"coordinates":[75.064345,13.488839],"type":"Point"}
}