{
  "type": "Feature",
  "properties": {
    "iso:country":"IN",
    "ks:ks_name":"Kichchabbi Hadlu",
    "ks:ks_pop":117,
    "ks:ks_type":"HABITATION",
    "name:eng_x_preferred":[
        "Kichchabbi Hadlu"
    ],
    "wof:name":"Kichchabbi Hadlu",
    "wof:placetype":"locality",
    "wof:population":117
},
  "geometry": {"coordinates":[75.493785,13.452691],"type":"Point"}
}