{
  "type": "Feature",
  "properties": {
    "iso:country":"IN",
    "ks:ks_name":"Pashtyewadi",
    "ks:ks_pop":232,
    "ks:ks_type":"HABITATION",
    "name:eng_x_preferred":[
        "Pashtyewadi"
    ],
    "wof:name":"Pashtyewadi",
    "wof:placetype":"locality",
    "wof:population":232
},
  "geometry": {"coordinates":[73.478523,16.878484],"type":"Point"}
}