{
  "type": "Feature",
  "properties": {
    "gn:admin1_code":"36.0",
    "gn:admin2_code":"149.0",
    "gn:asciiname":"Husainpur",
    "gn:country_code":"IN",
    "gn:dem":181,
    "gn:feature_class":"P",
    "gn:feature_code":"PPL",
    "gn:name":"Husainpur",
    "gn:population":0,
    "gn:timezone":"Asia/Kolkata",
    "iso:country":"IN",
    "wof:name":"Husainpur",
    "wof:placetype":"locality"
},
  "geometry": {"coordinates":[78.89926,28.28243],"type":"Point"}
}