{
  "type": "Feature",
  "properties": {
    "iso:country":"IN",
    "ks:ks_name":"Ajab Ka Par",
    "ks:ks_pop":130,
    "ks:ks_type":"VILLAGE",
    "name:eng_x_preferred":[
        "Ajab Ka Par"
    ],
    "wof:name":"Ajab Ka Par",
    "wof:placetype":"locality",
    "wof:population":130
},
  "geometry": {"coordinates":[70.772739,25.705681],"type":"Point"}
}