{
  "type": "Feature",
  "properties": {
    "iso:country":"IN",
    "ks:ks_name":"Kazhuveliparampil Shaji",
    "ks:ks_pop":296,
    "ks:ks_type":"HABITATION",
    "ks:ks_uagg_main":0,
    "name:eng_x_preferred":[
        "Kazhuveliparampil Shaji"
    ],
    "wof:name":"Kazhuveliparampil Shaji",
    "wof:placetype":"neighbourhood",
    "wof:population":296
},
  "geometry": {"coordinates":[76.378996,10.304778],"type":"Point"}
}