{
  "type": "Feature",
  "properties": {
    "iso:country":"IN",
    "ks:ks_alt_nam":"Ganga Gh\u0101t",
    "ks:ks_name":"Ganga Ghat",
    "ks:ks_type":"VILLAGE",
    "ks:ks_uagg_main":0,
    "name:eng_x_preferred":[
        "Ganga Ghat"
    ],
    "name:eng_x_variant":[
        "Ganga Gh\u0101t"
    ],
    "wof:name":"Ganga Ghat",
    "wof:placetype":"locality"
},
  "geometry": {"coordinates":[80.395914,26.498515],"type":"Point"}
}