{
  "type": "Feature",
  "properties": {
    "iso:country":"IN",
    "ks:ks_name":"Jetpur Navagadh",
    "ks:ks_type":"URBAN",
    "name:eng_x_preferred":[
        "Jetpur Navagadh"
    ],
    "wof:name":"Jetpur Navagadh",
    "wof:placetype":"locality"
},
  "geometry": {"coordinates":[70.596549,21.767905],"type":"Point"}
}