{
  "type": "Feature",
  "properties": {
    "gn:admin1_code":"36.0",
    "gn:admin2_code":"153.0",
    "gn:asciiname":"Kashipur",
    "gn:country_code":"IN",
    "gn:dem":157,
    "gn:feature_class":"P",
    "gn:feature_code":"PPL",
    "gn:name":"K\u0101shipur",
    "gn:population":0,
    "gn:timezone":"Asia/Kolkata",
    "iso:country":"IN",
    "ks:ks_alt_nam":"K\u0101shipur",
    "ks:ks_name":"Kashipur",
    "ks:ks_pop":699,
    "ks:ks_type":"VILLAGE",
    "ks:ks_uagg_main":0,
    "name:eng_x_preferred":[
        "Kashipur"
    ],
    "name:eng_x_variant":[
        "K\u0101shipur"
    ],
    "name:hin_x_preferred":[
        "\u0915\u093e\u0936\u0940\u092a\u0941\u0930"
    ],
    "name:rus_x_preferred":[
        "\u041a\u0430\u0448\u0438\u043f\u0443\u0440"
    ],
    "wof:name":"Kashipur",
    "wof:placetype":"neighbourhood",
    "wof:population":699
},
  "geometry": {"coordinates":[80.218054,27.84965],"type":"Point"}
}