{
  "type": "Feature",
  "properties": {
    "gn:admin1_code":"36.0",
    "gn:admin2_code":"177.0",
    "gn:asciiname":"Paharganj",
    "gn:country_code":"IN",
    "gn:dem":104,
    "gn:feature_class":"P",
    "gn:feature_code":"PPL",
    "gn:name":"Pah\u0101rganj",
    "gn:population":0,
    "gn:timezone":"Asia/Kolkata",
    "iso:country":"IN",
    "name:hin_x_preferred":[
        "\u092a\u0939\u093e\u0921\u093c\u0917\u0902\u091c"
    ],
    "name:jpn_x_preferred":[
        "\u30d1\u30cf\u30fc\u30eb\u30ac\u30f3\u30b8"
    ],
    "name:por_x_preferred":[
        "Paharganj"
    ],
    "name:spa_x_preferred":[
        "Paharganj"
    ],
    "name:swe_x_preferred":[
        "Paharganj"
    ],
    "name:tam_x_preferred":[
        "\u0baa\u0b95\u0bbe\u0b9f\u0bcd \u0b95\u0b9e\u0bcd\u0b9a\u0bc1"
    ],
    "name:urd_x_preferred":[
        "\u067e\u06c1\u0627\u0691 \u06af\u0646\u062c"
    ],
    "wof:name":"Paharganj",
    "wof:placetype":"locality"
},
  "geometry": {"coordinates":[82.13893,26.76184000000001],"type":"Point"}
}