{
  "type": "Feature",
  "properties": {
    "iso:country":"IN",
    "ks:ks_name":"Begadali",
    "ks:ks_pop":86,
    "ks:ks_type":"VILLAGE",
    "name:eng_x_preferred":[
        "Begadali"
    ],
    "wof:name":"Begadali",
    "wof:placetype":"locality",
    "wof:population":86
},
  "geometry": {"coordinates":[75.095467,13.649762],"type":"Point"}
}