{
  "type": "Feature",
  "properties": {
    "gn:admin1_code":"19.0",
    "gn:admin2_code":"563.0",
    "gn:asciiname":"Golikar",
    "gn:country_code":"IN",
    "gn:dem":518,
    "gn:feature_class":"P",
    "gn:feature_code":"PPL",
    "gn:name":"Golik\u0101r",
    "gn:population":0,
    "gn:timezone":"Asia/Kolkata",
    "iso:country":"IN",
    "ks:ks_name":"Golikai",
    "ks:ks_pop":151,
    "ks:ks_type":"HABITATION",
    "name:eng_x_preferred":[
        "Golikai"
    ],
    "name:eng_x_variant":[
        "Golikar"
    ],
    "wof:name":"Golikai",
    "wof:placetype":"locality",
    "wof:population":151
},
  "geometry": {"coordinates":[74.73638699999999,14.430766],"type":"Point"}
}