{
  "type": "Feature",
  "properties": {
    "iso:country":"IN",
    "ks:ks_name":"Tajela",
    "ks:ks_pop":126,
    "ks:ks_type":"VILLAGE",
    "name:eng_x_preferred":[
        "Tajela"
    ],
    "wof:name":"Tajela",
    "wof:placetype":"locality",
    "wof:population":126
},
  "geometry": {"coordinates":[74.40325300000001,24.295364],"type":"Point"}
}