{
  "type": "Feature",
  "properties": {
    "gn:admin1_code":"35.0",
    "gn:admin2_code":"459",
    "gn:asciiname":"Nanoti",
    "gn:country_code":"IN",
    "gn:dem":407,
    "gn:feature_class":"P",
    "gn:feature_code":"PPL",
    "gn:name":"N\u0101noti",
    "gn:population":0,
    "gn:timezone":"Asia/Kolkata",
    "iso:country":"IN",
    "ks:ks_name":"Nanoti",
    "ks:ks_pop":221,
    "ks:ks_type":"HABITATION",
    "name:eng_x_preferred":[
        "Nanoti"
    ],
    "wof:name":"Nanoti",
    "wof:placetype":"locality",
    "wof:population":221
},
  "geometry": {"coordinates":[78.016623,24.260849],"type":"Point"}
}