{
  "type": "Feature",
  "properties": {
    "iso:country":"IN",
    "ks:ks_name":"Nilosi",
    "ks:ks_pop":1500,
    "ks:ks_type":"VILLAGE",
    "name:eng_x_preferred":[
        "Nilosi"
    ],
    "wof:name":"Nilosi",
    "wof:placetype":"locality",
    "wof:population":1500
},
  "geometry": {"coordinates":[73.26687,20.264107],"type":"Point"}
}