{
  "type": "Feature",
  "properties": {
    "iso:country":"IN",
    "ks:ks_name":"Jamchuwa",
    "ks:ks_pop":170,
    "ks:ks_type":"VILLAGE",
    "name:eng_x_preferred":[
        "Jamchuwa"
    ],
    "wof:name":"Jamchuwa",
    "wof:placetype":"locality",
    "wof:population":170
},
  "geometry": {"coordinates":[83.28257499999999,22.010554],"type":"Point"}
}