{
  "type": "Feature",
  "properties": {
    "iso:country":"IN",
    "ks:ks_name":"Bahadurpur",
    "ks:ks_pop":665,
    "ks:ks_type":"VILLAGE",
    "name:eng_x_preferred":[
        "Bahadurpur"
    ],
    "wof:name":"Bahadurpur",
    "wof:placetype":"locality",
    "wof:population":665
},
  "geometry": {"coordinates":[87.094221,22.148154],"type":"Point"}
}