{
  "type": "Feature",
  "properties": {
    "gn:admin1_code":"10.0",
    "gn:admin2_code":"80.0",
    "gn:asciiname":"Nyoli Khurd",
    "gn:country_code":"IN",
    "gn:dem":212,
    "gn:feature_class":"P",
    "gn:feature_code":"PPL",
    "gn:name":"Nyoli Khurd",
    "gn:population":0,
    "gn:timezone":"Asia/Kolkata",
    "iso:country":"IN",
    "wof:name":"Nyoli Khurd",
    "wof:placetype":"locality"
},
  "geometry": {"coordinates":[75.61386999999998,29.21727000000001],"type":"Point"}
}