{
  "type": "Feature",
  "properties": {
    "iso:country":"IN",
    "ks:ks_alt_nam":"LILANAGAR",
    "ks:ks_name":"Lilanagar",
    "ks:ks_pop":356,
    "ks:ks_type":"HABITATION",
    "name:eng_x_preferred":[
        "Lilanagar"
    ],
    "wof:name":"Lilanagar",
    "wof:placetype":"locality",
    "wof:population":356
},
  "geometry": {"coordinates":[85.275087,23.932358],"type":"Point"}
}