{
  "type": "Feature",
  "properties": {
    "iso:country":"IN",
    "ks:ks_name":"Chhangeria Patna",
    "ks:ks_pop":37,
    "ks:ks_type":"VILLAGE",
    "name:eng_x_preferred":[
        "Chhangeria Patna"
    ],
    "wof:name":"Chhangeria Patna",
    "wof:placetype":"locality",
    "wof:population":37
},
  "geometry": {"coordinates":[87.408772,21.845462],"type":"Point"}
}