{
  "type": "Feature",
  "properties": {
    "iso:country":"IN",
    "ks:ks_alt_nam":"Bhutupunjee MSection",
    "ks:ks_name":"Bhutupunjee Msection",
    "ks:ks_pop":1029,
    "ks:ks_type":"HABITATION",
    "name:eng_x_preferred":[
        "Bhutupunjee Msection"
    ],
    "wof:name":"Bhutupunjee Msection",
    "wof:placetype":"locality",
    "wof:population":1029
},
  "geometry": {"coordinates":[92.432723,24.367583],"type":"Point"}
}