{
  "type": "Feature",
  "properties": {
    "iso:country":"IN",
    "ks:ks_alt_nam":"MUSHAR BASTI",
    "ks:ks_name":"Mushar Basti",
    "ks:ks_pop":134,
    "ks:ks_type":"HABITATION",
    "ks:ks_uagg_main":0,
    "name:eng_x_preferred":[
        "Mushar Basti"
    ],
    "wof:name":"Mushar Basti",
    "wof:placetype":"neighbourhood",
    "wof:population":134
},
  "geometry": {"coordinates":[82.852682,25.49105],"type":"Point"}
}