{
  "type": "Feature",
  "properties": {
    "gn:admin1_code":"21.0",
    "gn:admin2_code":"396.0",
    "gn:asciiname":"Anandapuram",
    "gn:country_code":"IN",
    "gn:dem":270,
    "gn:feature_class":"P",
    "gn:feature_code":"PPL",
    "gn:name":"\u0100nand\u0101puram",
    "gn:population":0,
    "gn:timezone":"Asia/Kolkata",
    "iso:country":"IN",
    "name:msa_x_preferred":[
        "Anandapuram"
    ],
    "name:tam_x_preferred":[
        "\u0b86\u0ba9\u0ba8\u0bcd\u0ba4\u0baa\u0bc1\u0bb0\u0bae\u0bcd \u0bae\u0ba3\u0bcd\u0b9f\u0bb2\u0bae\u0bcd"
    ],
    "name:tel_x_preferred":[
        "\u0c06\u0c28\u0c02\u0c26\u0c2a\u0c41\u0c30\u0c02"
    ],
    "name:urd_x_preferred":[
        "\u0622\u0646\u0646\u062f\u0627\u067e\u0648\u0631\u0645"
    ],
    "wof:name":"Anandapuram",
    "wof:placetype":"locality"
},
  "geometry": {"coordinates":[83.39355,19.32737],"type":"Point"}
}