{
  "type": "Feature",
  "properties": {
    "gn:admin1_code":"36.0",
    "gn:admin2_code":"167",
    "gn:asciiname":"Bucha",
    "gn:country_code":"IN",
    "gn:dem":377,
    "gn:feature_class":"P",
    "gn:feature_code":"PPL",
    "gn:name":"B\u016bcha",
    "gn:population":0,
    "gn:timezone":"Asia/Kolkata",
    "iso:country":"IN",
    "name:ceb_x_preferred":[
        "Bucha"
    ],
    "name:deu_x_preferred":[
        "Bucha"
    ],
    "name:epo_x_preferred":[
        "Bucha"
    ],
    "name:eus_x_preferred":[
        "Bucha"
    ],
    "name:ita_x_preferred":[
        "Bucha"
    ],
    "name:nld_x_preferred":[
        "Bucha"
    ],
    "name:pol_x_preferred":[
        "Bucha"
    ],
    "name:por_x_preferred":[
        "Bucha"
    ],
    "name:rus_x_preferred":[
        "\u0411\u0443\u0447\u0430"
    ],
    "name:swe_x_preferred":[
        "Bucha"
    ],
    "name:ukr_x_preferred":[
        "\u0411\u0443\u0447\u0430"
    ],
    "name:vol_x_preferred":[
        "Bucha"
    ],
    "wof:name":"Bucha",
    "wof:placetype":"locality"
},
  "geometry": {"coordinates":[78.36708,24.81158],"type":"Point"}
}