{
  "type": "Feature",
  "properties": {
    "iso:country":"IN",
    "ks:ks_name":"Shivanekaval",
    "ks:ks_pop":11,
    "ks:ks_type":"VILLAGE",
    "name:eng_x_preferred":[
        "Shivanekaval"
    ],
    "wof:name":"Shivanekaval",
    "wof:placetype":"locality",
    "wof:population":11
},
  "geometry": {"coordinates":[76.056538,13.849038],"type":"Point"}
}