{
  "type": "Feature",
  "properties": {
    "gn:admin1_code":"2",
    "gn:admin2_code":"544.0",
    "gn:asciiname":"Rallaputti",
    "gn:country_code":"IN",
    "gn:dem":1155,
    "gn:feature_class":"P",
    "gn:feature_code":"PPL",
    "gn:name":"Rallaputti",
    "gn:population":0,
    "gn:timezone":"Asia/Kolkata",
    "iso:country":"IN",
    "wof:name":"Rallaputti",
    "wof:placetype":"locality"
},
  "geometry": {"coordinates":[82.54725999999999,17.95107],"type":"Point"}
}