{
  "type": "Feature",
  "properties": {
    "gn:admin1_code":"2",
    "gn:admin2_code":"544.0",
    "gn:asciiname":"Rallaputti",
    "gn:country_code":"IN",
    "gn:dem":1155,
    "gn:feature_class":"P",
    "gn:feature_code":"PPL",
    "gn:name":"Rallaputti",
    "gn:population":0,
    "gn:timezone":"Asia/Kolkata",
    "iso:country":"IN",
    "ks:ks_name":"Rallaputtu",
    "ks:ks_pop":237,
    "ks:ks_type":"HABITATION",
    "name:eng_x_preferred":[
        "Rallaputtu"
    ],
    "name:eng_x_variant":[
        "Rallaputti"
    ],
    "wof:name":"Rallaputtu",
    "wof:placetype":"locality",
    "wof:population":237
},
  "geometry": {"coordinates":[82.547315,17.95057],"type":"Point"}
}