{
  "type": "Feature",
  "properties": {
    "gn:admin1_code":"34.0",
    "gn:admin2_code":"232.0",
    "gn:asciiname":"Kamdharpur",
    "gn:country_code":"IN",
    "gn:dem":75,
    "gn:feature_class":"P",
    "gn:feature_code":"PPL",
    "gn:name":"K\u0101mdharpur",
    "gn:population":0,
    "gn:timezone":"Asia/Kolkata",
    "iso:country":"IN",
    "ks:ks_alt_nam":"K\u0101mdharpur",
    "ks:ks_name":"Kamdharpur",
    "ks:ks_pop":503,
    "ks:ks_type":"VILLAGE",
    "name:eng_x_preferred":[
        "Kamdharpur"
    ],
    "name:eng_x_variant":[
        "K\u0101mdharpur"
    ],
    "wof:name":"Kamdharpur",
    "wof:placetype":"locality",
    "wof:population":503
},
  "geometry": {"coordinates":[84.103495,25.470985],"type":"Point"}
}