{
  "type": "Feature",
  "properties": {
    "gn:admin1_code":"16.0",
    "gn:admin2_code":"508.0",
    "gn:asciiname":"Rajpalli",
    "gn:country_code":"IN",
    "gn:dem":149,
    "gn:feature_class":"P",
    "gn:feature_code":"PPL",
    "gn:name":"Rajpalli",
    "gn:population":0,
    "gn:timezone":"Asia/Kolkata",
    "iso:country":"IN",
    "ks:ks_name":"Raspalli S",
    "ks:ks_pop":889,
    "ks:ks_type":"VILLAGE",
    "name:eng_x_preferred":[
        "Raspalli S"
    ],
    "name:eng_x_variant":[
        "Rajpalli"
    ],
    "wof:name":"Raspalli S",
    "wof:placetype":"locality",
    "wof:population":889
},
  "geometry": {"coordinates":[80.150496,19.083625],"type":"Point"}
}