{
  "type": "Feature",
  "properties": {
    "iso:country":"IN",
    "ks:ks_name":"T Hosahalli",
    "ks:ks_pop":846,
    "ks:ks_type":"VILLAGE",
    "ks:ks_uagg_main":0,
    "name:eng_x_preferred":[
        "T Hosahalli"
    ],
    "wof:name":"T Hosahalli",
    "wof:placetype":"neighbourhood",
    "wof:population":846
},
  "geometry": {"coordinates":[77.02846,12.961065],"type":"Point"}
}