{
  "type": "Feature",
  "properties": {
    "iso:country":"IN",
    "ks:ks_name":"Ullarthi Kaval",
    "ks:ks_pop":96,
    "ks:ks_type":"VILLAGE",
    "name:eng_x_preferred":[
        "Ullarthi Kaval"
    ],
    "wof:name":"Ullarthi Kaval",
    "wof:placetype":"locality",
    "wof:population":96
},
  "geometry": {"coordinates":[76.71445900000001,14.390125],"type":"Point"}
}