{
  "type": "Feature",
  "properties": {
    "gn:admin1_code":"24.0",
    "gn:admin2_code":"102.0",
    "gn:asciiname":"Bandra",
    "gn:country_code":"IN",
    "gn:dem":213,
    "gn:feature_class":"P",
    "gn:feature_code":"PPL",
    "gn:name":"Bandra",
    "gn:population":0,
    "gn:timezone":"Asia/Kolkata",
    "iso:country":"IN",
    "name:ben_x_preferred":[
        "\u09ac\u09be\u09a8\u09cd\u09a6\u09cd\u09b0\u09be"
    ],
    "name:cat_x_preferred":[
        "Bandra"
    ],
    "name:fra_x_preferred":[
        "Bandra"
    ],
    "name:guj_x_preferred":[
        "\u0aac\u0abe\u0a82\u0aa6\u0acd\u0ab0\u0abe"
    ],
    "name:hin_x_preferred":[
        "\u092c\u093e\u0902\u0926\u094d\u0930\u093e"
    ],
    "name:ind_x_preferred":[
        "Bandra"
    ],
    "name:ita_x_preferred":[
        "Bandra"
    ],
    "name:mal_x_preferred":[
        "\u0d2c\u0d3e\u0d28\u0d4d\u0d26\u0d4d\u0d30"
    ],
    "name:mar_x_preferred":[
        "\u0935\u093e\u0902\u0926\u094d\u0930\u0947"
    ],
    "name:nld_x_preferred":[
        "Bandra"
    ],
    "name:por_x_preferred":[
        "Bandor\u00e1"
    ],
    "name:swe_x_preferred":[
        "Bandra"
    ],
    "name:urd_x_preferred":[
        "\u0628\u0627\u0646\u062f\u0631\u06c1"
    ],
    "wof:name":"Bandra",
    "wof:placetype":"locality"
},
  "geometry": {"coordinates":[75.08856,28.79311],"type":"Point"}
}