{
  "type": "Feature",
  "properties": {
    "gn:admin1_code":"39.0",
    "gn:admin2_code":"66.0",
    "gn:asciiname":"Thum",
    "gn:country_code":"IN",
    "gn:dem":1632,
    "gn:feature_class":"P",
    "gn:feature_code":"PPL",
    "gn:name":"Thum",
    "gn:population":0,
    "gn:timezone":"Asia/Kolkata",
    "iso:country":"IN",
    "name:azb_x_preferred":[
        "\u062a\u0648\u0645"
    ],
    "name:bak_x_preferred":[
        "\u0422\u0443\u043c"
    ],
    "name:ceb_x_preferred":[
        "Thum"
    ],
    "name:deu_x_preferred":[
        "Thum"
    ],
    "name:epo_x_preferred":[
        "Thum"
    ],
    "name:est_x_preferred":[
        "Thum"
    ],
    "name:fas_x_preferred":[
        "\u062a\u0648\u0645"
    ],
    "name:fra_x_preferred":[
        "Thum"
    ],
    "name:hrv_x_preferred":[
        "Thum"
    ],
    "name:hun_x_preferred":[
        "Thum"
    ],
    "name:ido_x_preferred":[
        "Thum"
    ],
    "name:ita_x_preferred":[
        "Thum"
    ],
    "name:lav_x_preferred":[
        "Tuma"
    ],
    "name:mkd_x_preferred":[
        "\u0422\u0443\u043c"
    ],
    "name:msa_x_preferred":[
        "Thum"
    ],
    "name:nld_x_preferred":[
        "Thum"
    ],
    "name:nor_x_preferred":[
        "Thum"
    ],
    "name:pol_x_preferred":[
        "Thum"
    ],
    "name:por_x_preferred":[
        "Thum"
    ],
    "name:ron_x_preferred":[
        "Thum"
    ],
    "name:rus_x_preferred":[
        "\u0422\u0443\u043c"
    ],
    "name:spa_x_preferred":[
        "Thum"
    ],
    "name:srp_x_preferred":[
        "\u0422\u0443\u043c"
    ],
    "name:swe_x_preferred":[
        "Thum"
    ],
    "name:ukr_x_preferred":[
        "\u0422\u0443\u043c"
    ],
    "name:uzb_x_preferred":[
        "Thum"
    ],
    "name:vol_x_preferred":[
        "Thum"
    ],
    "name:war_x_preferred":[
        "Thum"
    ],
    "wof:name":"Thum",
    "wof:placetype":"locality"
},
  "geometry": {"coordinates":[79.60918000000002,29.35799],"type":"Point"}
}