{
  "type": "Feature",
  "properties": {
    "gn:admin1_code":"39.0",
    "gn:admin2_code":"66.0",
    "gn:asciiname":"Thum",
    "gn:country_code":"IN",
    "gn:dem":1632,
    "gn:feature_class":"P",
    "gn:feature_code":"PPL",
    "gn:name":"Thum",
    "gn:population":0,
    "gn:timezone":"Asia/Kolkata",
    "iso:country":"IN",
    "wof:name":"Thum",
    "wof:placetype":"locality"
},
  "geometry": {"coordinates":[79.60918000000002,29.35799],"type":"Point"}
}