{
  "type": "Feature",
  "properties": {
    "gn:admin1_code":"35",
    "gn:admin2_code":"455.0",
    "gn:asciiname":"Titri",
    "gn:country_code":"IN",
    "gn:dem":594,
    "gn:feature_class":"P",
    "gn:feature_code":"PPL",
    "gn:name":"T\u012btri",
    "gn:population":0,
    "gn:timezone":"Asia/Kolkata",
    "iso:country":"IN",
    "wof:name":"Titri",
    "wof:placetype":"locality"
},
  "geometry": {"coordinates":[79.15657,21.90291],"type":"Point"}
}