{
  "type": "Feature",
  "properties": {
    "gn:admin1_code":"39.0",
    "gn:admin2_code":"64.0",
    "gn:asciiname":"Barakunda",
    "gn:country_code":"IN",
    "gn:dem":1782,
    "gn:feature_class":"P",
    "gn:feature_code":"PPL",
    "gn:name":"Barakunda",
    "gn:population":0,
    "gn:timezone":"Asia/Kolkata",
    "iso:country":"IN",
    "ks:ks_name":"Barakuna",
    "ks:ks_pop":234,
    "ks:ks_type":"VILLAGE",
    "name:eng_x_preferred":[
        "Barakuna"
    ],
    "name:eng_x_variant":[
        "Barakunda"
    ],
    "wof:name":"Barakuna",
    "wof:placetype":"locality",
    "wof:population":234
},
  "geometry": {"coordinates":[79.88987,29.594317],"type":"Point"}
}