{
  "type": "Feature",
  "properties": {
    "gn:admin1_code":"39.0",
    "gn:admin2_code":"64.0",
    "gn:asciiname":"Barakunda",
    "gn:country_code":"IN",
    "gn:dem":1782,
    "gn:feature_class":"P",
    "gn:feature_code":"PPL",
    "gn:name":"Barakunda",
    "gn:population":0,
    "gn:timezone":"Asia/Kolkata",
    "iso:country":"IN",
    "wof:name":"Barakunda",
    "wof:placetype":"locality"
},
  "geometry": {"coordinates":[79.88909,29.58804],"type":"Point"}
}