{
  "type": "Feature",
  "properties": {
    "iso:country":"IN",
    "ks:ks_alt_nam":"Thalaikaran kottai",
    "ks:ks_name":"Thalaikaran Kottai",
    "ks:ks_pop":296,
    "ks:ks_type":"HABITATION",
    "ks:ks_uagg_main":0,
    "name:eng_x_preferred":[
        "Thalaikaran Kottai"
    ],
    "wof:name":"Thalaikaran Kottai",
    "wof:placetype":"neighbourhood",
    "wof:population":296
},
  "geometry": {"coordinates":[78.22994,12.171207],"type":"Point"}
}