{
  "type": "Feature",
  "properties": {
    "gn:admin1_code":"36",
    "gn:admin2_code":"196.0",
    "gn:asciiname":"Naugarh",
    "gn:country_code":"IN",
    "gn:dem":276,
    "gn:feature_class":"P",
    "gn:feature_code":"PPL",
    "gn:name":"Naugarh",
    "gn:population":0,
    "gn:timezone":"Asia/Kolkata",
    "iso:country":"IN",
    "name:und_x_variant":[
        "N\u0101ugarh"
    ],
    "wof:name":"Naugarh",
    "wof:placetype":"locality"
},
  "geometry": {"coordinates":[83.25845,24.83324],"type":"Point"}
}