{
  "type": "Feature",
  "properties": {
    "iso:country":"IN",
    "ks:ks_name":"Tatiya",
    "ks:ks_pop":626,
    "ks:ks_type":"HABITATION",
    "ks:ks_uagg_main":0,
    "name:eng_x_preferred":[
        "Tatiya"
    ],
    "wof:name":"Tatiya",
    "wof:placetype":"neighbourhood",
    "wof:population":626
},
  "geometry": {"coordinates":[82.680363,26.403277],"type":"Point"}
}