{
  "type": "Feature",
  "properties": {
    "gn:admin1_code":"19.0",
    "gn:admin2_code":"583.0",
    "gn:asciiname":"Banahalli",
    "gn:country_code":"IN",
    "gn:dem":886,
    "gn:feature_class":"P",
    "gn:feature_code":"PPL",
    "gn:name":"Banahalli",
    "gn:population":0,
    "gn:timezone":"Asia/Kolkata",
    "iso:country":"IN",
    "wof:name":"Banahalli",
    "wof:placetype":"locality"
},
  "geometry": {"coordinates":[77.91204999999999,13.21442],"type":"Point"}
}