{
  "type": "Feature",
  "properties": {
    "iso:country":"IN",
    "ks:ks_name":"Hasanpur",
    "ks:ks_pop":298,
    "ks:ks_type":"HABITATION",
    "name:eng_x_preferred":[
        "Hasanpur"
    ],
    "wof:name":"Hasanpur",
    "wof:placetype":"locality",
    "wof:population":298
},
  "geometry": {"coordinates":[81.67651600000001,26.494655],"type":"Point"}
}