{
  "type": "Feature",
  "properties": {
    "iso:country":"IN",
    "ks:ks_name":"Bharkuriya",
    "ks:ks_pop":486,
    "ks:ks_type":"VILLAGE",
    "ks:ks_uagg_main":0,
    "name:eng_x_preferred":[
        "Bharkuriya"
    ],
    "wof:name":"Bharkuriya",
    "wof:placetype":"neighbourhood",
    "wof:population":486
},
  "geometry": {"coordinates":[84.274355,25.24011],"type":"Point"}
}