{
  "type": "Feature",
  "properties": {
    "iso:country":"IN",
    "ks:ks_name":"Madgar",
    "ks:ks_pop":27,
    "ks:ks_type":"HABITATION",
    "name:eng_x_preferred":[
        "Madgar"
    ],
    "wof:name":"Madgar",
    "wof:placetype":"locality",
    "wof:population":27
},
  "geometry": {"coordinates":[74.202501,14.868404],"type":"Point"}
}