{
  "type": "Feature",
  "properties": {
    "iso:country":"IN",
    "ks:ks_name":"Sarmundapal",
    "ks:ks_pop":51,
    "ks:ks_type":"VILLAGE",
    "name:eng_x_preferred":[
        "Sarmundapal"
    ],
    "wof:name":"Sarmundapal",
    "wof:placetype":"locality",
    "wof:population":51
},
  "geometry": {"coordinates":[83.91865199999999,21.103167],"type":"Point"}
}