{
  "type": "Feature",
  "properties": {
    "iso:country":"IN",
    "ks:ks_name":"Bhaluyani",
    "ks:ks_pop":575,
    "ks:ks_type":"HABITATION",
    "name:eng_x_preferred":[
        "Bhaluyani"
    ],
    "wof:name":"Bhaluyani",
    "wof:placetype":"locality",
    "wof:population":575
},
  "geometry": {"coordinates":[85.249233,24.545203],"type":"Point"}
}