{
  "type": "Feature",
  "properties": {
    "gn:admin1_code":"39.0",
    "gn:admin2_code":"65.0",
    "gn:asciiname":"Binhalgaon",
    "gn:country_code":"IN",
    "gn:dem":1291,
    "gn:feature_class":"P",
    "gn:feature_code":"PPL",
    "gn:name":"Binh\u0101lgaon",
    "gn:population":0,
    "gn:timezone":"Asia/Kolkata",
    "iso:country":"IN",
    "ks:ks_name":"Binwal Gaon",
    "ks:ks_pop":458,
    "ks:ks_type":"VILLAGE",
    "name:eng_x_preferred":[
        "Binwal Gaon"
    ],
    "name:eng_x_variant":[
        "Binhalgaon"
    ],
    "wof:name":"Binwal Gaon",
    "wof:placetype":"locality",
    "wof:population":458
},
  "geometry": {"coordinates":[79.847683,29.29812],"type":"Point"}
}