{
  "type": "Feature",
  "properties": {
    "gn:admin1_code":"39.0",
    "gn:admin2_code":"65.0",
    "gn:asciiname":"Binhalgaon",
    "gn:country_code":"IN",
    "gn:dem":1291,
    "gn:feature_class":"P",
    "gn:feature_code":"PPL",
    "gn:name":"Binh\u0101lgaon",
    "gn:population":0,
    "gn:timezone":"Asia/Kolkata",
    "iso:country":"IN",
    "wof:name":"Binhalgaon",
    "wof:placetype":"locality"
},
  "geometry": {"coordinates":[79.84978000000002,29.30506],"type":"Point"}
}