{
  "type": "Feature",
  "properties": {
    "iso:country":"IN",
    "ks:ks_name":"Palakunnu",
    "ks:ks_pop":809,
    "ks:ks_type":"HABITATION",
    "ks:ks_uagg_main":0,
    "name:eng_x_preferred":[
        "Palakunnu"
    ],
    "wof:name":"Palakunnu",
    "wof:placetype":"neighbourhood",
    "wof:population":809
},
  "geometry": {"coordinates":[75.02264099999999,12.423948],"type":"Point"}
}