{
  "type": "Feature",
  "properties": {
    "iso:country":"IN",
    "ks:ks_name":"Devrajpura",
    "ks:ks_pop":340,
    "ks:ks_type":"HABITATION",
    "name:eng_x_preferred":[
        "Devrajpura"
    ],
    "wof:name":"Devrajpura",
    "wof:placetype":"locality",
    "wof:population":340
},
  "geometry": {"coordinates":[71.65647300000001,24.13117],"type":"Point"}
}