{
  "type": "Feature",
  "properties": {
    "iso:country":"IN",
    "ks:ks_name":"Narangapoyil",
    "ks:ks_pop":101,
    "ks:ks_type":"HABITATION",
    "name:eng_x_preferred":[
        "Narangapoyil"
    ],
    "wof:name":"Narangapoyil",
    "wof:placetype":"locality",
    "wof:population":101
},
  "geometry": {"coordinates":[76.270673,11.439948],"type":"Point"}
}