{
  "type": "Feature",
  "properties": {
    "gn:admin1_code":"36",
    "gn:admin2_code":"178.0",
    "gn:asciiname":"Sasna",
    "gn:country_code":"IN",
    "gn:dem":84,
    "gn:feature_class":"P",
    "gn:feature_code":"PPL",
    "gn:name":"Sasna",
    "gn:population":0,
    "gn:timezone":"Asia/Kolkata",
    "iso:country":"IN",
    "name:deu_x_preferred":[
        "Sassen"
    ],
    "name:fra_x_preferred":[
        "Sasna"
    ],
    "name:lit_x_preferred":[
        "Sasna"
    ],
    "name:pol_x_preferred":[
        "Ziemia Sasin\u00f3w"
    ],
    "name:rus_x_preferred":[
        "\u0421\u0430\u0441\u0441\u043e\u0432\u0438\u044f"
    ],
    "name:ukr_x_preferred":[
        "\u0421\u0430\u0441\u0441\u0456\u044f"
    ],
    "wof:name":"Sasna",
    "wof:placetype":"locality"
},
  "geometry": {"coordinates":[83.05516999999998,26.28978],"type":"Point"}
}