{
  "type": "Feature",
  "properties": {
    "iso:country":"IN",
    "ks:ks_name":"Gunupur",
    "ks:ks_pop":118,
    "ks:ks_type":"HABITATION",
    "name:eng_x_preferred":[
        "Gunupur"
    ],
    "wof:name":"Gunupur",
    "wof:placetype":"locality",
    "wof:population":118
},
  "geometry": {"coordinates":[82.196743,18.123161],"type":"Point"}
}