{
  "type": "Feature",
  "properties": {
    "iso:country":"IN",
    "ks:ks_name":"Pantnagar",
    "ks:ks_pop":300,
    "ks:ks_type":"HABITATION",
    "name:eng_x_preferred":[
        "Pantnagar"
    ],
    "wof:name":"Pantnagar",
    "wof:placetype":"locality",
    "wof:population":300
},
  "geometry": {"coordinates":[80.102161,26.521012],"type":"Point"}
}