{
  "type": "Feature",
  "properties": {
    "iso:country":"IN",
    "ks:ks_name":"Kothodumar",
    "ks:ks_pop":0,
    "ks:ks_type":"VILLAGE",
    "name:eng_x_preferred":[
        "Kothodumar"
    ],
    "wof:name":"Kothodumar",
    "wof:placetype":"locality",
    "wof:population":0
},
  "geometry": {"coordinates":[85.23885199999999,24.42351],"type":"Point"}
}