{
  "type": "Feature",
  "properties": {
    "gn:admin1_code":"36",
    "gn:admin2_code":"185.0",
    "gn:asciiname":"Goshain Singhpur",
    "gn:country_code":"IN",
    "gn:dem":89,
    "gn:feature_class":"P",
    "gn:feature_code":"PPL",
    "gn:name":"Gosh\u0101in Singhpur",
    "gn:population":0,
    "gn:timezone":"Asia/Kolkata",
    "iso:country":"IN",
    "ks:ks_alt_nam":"Gosh\u0101in Singhpur",
    "ks:ks_name":"Goshain Singhpur",
    "ks:ks_type":"VILLAGE",
    "ks:ks_uagg_main":0,
    "name:eng_x_preferred":[
        "Goshain Singhpur"
    ],
    "name:eng_x_variant":[
        "Gosh\u0101in Singhpur"
    ],
    "wof:name":"Goshain Singhpur",
    "wof:placetype":"neighbourhood"
},
  "geometry": {"coordinates":[82.72714499999999,26.598391],"type":"Point"}
}