{
  "type": "Feature",
  "properties": {
    "iso:country":"IN",
    "ks:ks_name":"Pirmahammadpur",
    "ks:ks_pop":833,
    "ks:ks_type":"VILLAGE",
    "name:eng_x_preferred":[
        "Pirmahammadpur"
    ],
    "wof:name":"Pirmahammadpur",
    "wof:placetype":"locality",
    "wof:population":833
},
  "geometry": {"coordinates":[85.449414,26.131346],"type":"Point"}
}