{
  "type": "Feature",
  "properties": {
    "iso:country":"IN",
    "ks:ks_name":"Rampuri Rakhi",
    "ks:ks_pop":546,
    "ks:ks_type":"HABITATION",
    "name:eng_x_preferred":[
        "Rampuri Rakhi"
    ],
    "wof:name":"Rampuri Rakhi",
    "wof:placetype":"locality",
    "wof:population":546
},
  "geometry": {"coordinates":[80.53202899999999,23.095259],"type":"Point"}
}