{
  "type": "Feature",
  "properties": {
    "iso:country":"IN",
    "ks:ks_name":"Astalakshmi Nagar",
    "ks:ks_pop":400,
    "ks:ks_type":"HABITATION",
    "ks:ks_uagg_main":0,
    "name:eng_x_preferred":[
        "Astalakshmi Nagar"
    ],
    "wof:name":"Astalakshmi Nagar",
    "wof:placetype":"locality",
    "wof:population":400
},
  "geometry": {"coordinates":[80.096987,12.973741],"type":"Point"}
}