{
  "type": "Feature",
  "properties": {
    "iso:country":"IN",
    "ks:ks_name":"Yedulagaruvu",
    "ks:ks_pop":101,
    "ks:ks_type":"HABITATION",
    "name:eng_x_preferred":[
        "Yedulagaruvu"
    ],
    "wof:name":"Yedulagaruvu",
    "wof:placetype":"locality",
    "wof:population":101
},
  "geometry": {"coordinates":[82.62679,18.001636],"type":"Point"}
}