{
  "type": "Feature",
  "properties": {
    "gn:admin1_code":"34.0",
    "gn:admin2_code":"220.0",
    "gn:asciiname":"Balempur Salkhani",
    "gn:country_code":"IN",
    "gn:dem":54,
    "gn:feature_class":"P",
    "gn:feature_code":"PPL",
    "gn:name":"B\u0101lempur S\u0101lkhani",
    "gn:population":0,
    "gn:timezone":"Asia/Kolkata",
    "iso:country":"IN",
    "ks:ks_name":"Salempur Salkhani",
    "ks:ks_pop":541,
    "ks:ks_type":"VILLAGE",
    "name:eng_x_preferred":[
        "Salempur Salkhani"
    ],
    "name:eng_x_variant":[
        "Balempur Salkhani"
    ],
    "wof:name":"Salempur Salkhani",
    "wof:placetype":"locality",
    "wof:population":541
},
  "geometry": {"coordinates":[85.489859,25.828964],"type":"Point"}
}