{
  "type": "Feature",
  "properties": {
    "gn:admin1_code":"2.0",
    "gn:admin2_code":"551.0",
    "gn:asciiname":"Rachapalli",
    "gn:country_code":"IN",
    "gn:dem":151,
    "gn:feature_class":"P",
    "gn:feature_code":"PPL",
    "gn:name":"Rachapalli",
    "gn:population":0,
    "gn:timezone":"Asia/Kolkata",
    "iso:country":"IN",
    "wof:name":"Rachapalli",
    "wof:placetype":"locality"
},
  "geometry": {"coordinates":[79.10021,14.26113],"type":"Point"}
}