{
  "type": "Feature",
  "properties": {
    "gn:admin1_code":"36.0",
    "gn:admin2_code":"190.0",
    "gn:asciiname":"Khardaha Ghansiam",
    "gn:country_code":"IN",
    "gn:dem":70,
    "gn:feature_class":"P",
    "gn:feature_code":"PPL",
    "gn:name":"Khardaha Ghansi\u0101m",
    "gn:population":0,
    "gn:timezone":"Asia/Kolkata",
    "iso:country":"IN",
    "wof:name":"Khardaha Ghansiam",
    "wof:placetype":"locality"
},
  "geometry": {"coordinates":[83.95050000000001,26.16983],"type":"Point"}
}