{
  "type": "Feature",
  "properties": {
    "iso:country":"IN",
    "ks:ks_name":"18 NDR",
    "ks:ks_pop":36,
    "ks:ks_type":"VILLAGE",
    "name:eng_x_preferred":[
        "18 NDR"
    ],
    "wof:name":"18 NDR",
    "wof:placetype":"locality",
    "wof:population":36
},
  "geometry": {"coordinates":[74.356106,29.425028],"type":"Point"}
}