{
  "type": "Feature",
  "properties": {
    "gn:admin1_code":"10.0",
    "gn:admin2_code":"070",
    "gn:asciiname":"Mohri",
    "gn:country_code":"IN",
    "gn:dem":269,
    "gn:feature_class":"P",
    "gn:feature_code":"PPL",
    "gn:name":"Mohri",
    "gn:population":0,
    "gn:timezone":"Asia/Kolkata",
    "iso:country":"IN",
    "wof:name":"Mohri",
    "wof:placetype":"locality"
},
  "geometry": {"coordinates":[76.85136999999997,30.24837],"type":"Point"}
}