{
  "type": "Feature",
  "properties": {
    "iso:country":"IN",
    "ks:ks_name":"Shivpura",
    "ks:ks_pop":507,
    "ks:ks_type":"HABITATION",
    "name:eng_x_preferred":[
        "Shivpura"
    ],
    "wof:name":"Shivpura",
    "wof:placetype":"locality",
    "wof:population":507
},
  "geometry": {"coordinates":[74.178887,23.187406],"type":"Point"}
}