{
  "type": "Feature",
  "properties": {
    "gn:admin1_code":"35.0",
    "gn:admin2_code":"450",
    "gn:asciiname":"Belehri",
    "gn:country_code":"IN",
    "gn:dem":400,
    "gn:feature_class":"P",
    "gn:feature_code":"PPL",
    "gn:name":"Belehri",
    "gn:population":0,
    "gn:timezone":"Asia/Kolkata",
    "iso:country":"IN",
    "name:und_x_variant":[
        "Bilher\u012b"
    ],
    "wof:name":"Belehri",
    "wof:placetype":"locality"
},
  "geometry": {"coordinates":[80.27254000000001,23.79413],"type":"Point"}
}