{
  "type": "Feature",
  "properties": {
    "iso:country":"IN",
    "ks:ks_name":"Diwanbhag",
    "ks:ks_pop":168,
    "ks:ks_type":"HABITATION",
    "name:eng_x_preferred":[
        "Diwanbhag"
    ],
    "wof:name":"Diwanbhag",
    "wof:placetype":"locality",
    "wof:population":168
},
  "geometry": {"coordinates":[73.767594,16.897719],"type":"Point"}
}