{
  "type": "Feature",
  "properties": {
    "gn:admin1_code":"11",
    "gn:admin2_code":"24.0",
    "gn:asciiname":"Pat Guali",
    "gn:country_code":"IN",
    "gn:dem":941,
    "gn:feature_class":"P",
    "gn:feature_code":"PPL",
    "gn:name":"Pat Gu\u0101li",
    "gn:population":0,
    "gn:timezone":"Asia/Kolkata",
    "iso:country":"IN",
    "wof:name":"Pat Guali",
    "wof:placetype":"locality"
},
  "geometry": {"coordinates":[76.56516999999999,32.02675],"type":"Point"}
}