{
  "type": "Feature",
  "properties": {
    "gn:admin1_code":"35.0",
    "gn:admin2_code":"441.0",
    "gn:asciiname":"Devnali",
    "gn:country_code":"IN",
    "gn:dem":302,
    "gn:feature_class":"P",
    "gn:feature_code":"PPL",
    "gn:name":"Devnali",
    "gn:population":0,
    "gn:timezone":"Asia/Kolkata",
    "iso:country":"IN",
    "ks:ks_name":"Deonali",
    "ks:ks_pop":866,
    "ks:ks_type":"VILLAGE",
    "name:eng_x_preferred":[
        "Deonali"
    ],
    "name:eng_x_variant":[
        "Devnali"
    ],
    "wof:name":"Deonali",
    "wof:placetype":"locality",
    "wof:population":866
},
  "geometry": {"coordinates":[75.232095,21.787246],"type":"Point"}
}