{
  "type": "Feature",
  "properties": {
    "gn:admin1_code":"36",
    "gn:admin2_code":"134.0",
    "gn:asciiname":"Bala Nagla",
    "gn:country_code":"IN",
    "gn:dem":219,
    "gn:feature_class":"P",
    "gn:feature_code":"PPL",
    "gn:name":"Bala Nagla",
    "gn:population":0,
    "gn:timezone":"Asia/Kolkata",
    "iso:country":"IN",
    "ks:ks_name":"Bala Nagla",
    "ks:ks_type":"VILLAGE",
    "ks:ks_uagg_main":0,
    "name:eng_x_preferred":[
        "Bala Nagla"
    ],
    "wof:name":"Bala Nagla",
    "wof:placetype":"neighbourhood"
},
  "geometry": {"coordinates":[78.52854000000001,29.077185],"type":"Point"}
}