{
  "type": "Feature",
  "properties": {
    "gn:admin1_code":"36",
    "gn:admin2_code":"194.0",
    "gn:asciiname":"Parsurampur",
    "gn:country_code":"IN",
    "gn:dem":90,
    "gn:feature_class":"P",
    "gn:feature_code":"PPL",
    "gn:name":"Parsur\u0101mpur",
    "gn:population":0,
    "gn:timezone":"Asia/Kolkata",
    "iso:country":"IN",
    "name:mai_x_preferred":[
        "\u092a\u0930\u0936\u0941\u0930\u093e\u092e\u092a\u0941\u0930"
    ],
    "name:msa_x_preferred":[
        "Parsurampur"
    ],
    "name:nep_x_preferred":[
        "\u092a\u0930\u0936\u0941\u0930\u093e\u092e\u092a\u0941\u0930"
    ],
    "name:pol_x_preferred":[
        "Prasurmpur"
    ],
    "wof:name":"Parsurampur",
    "wof:placetype":"neighbourhood"
},
  "geometry": {"coordinates":[82.64048,25.95484],"type":"Point"}
}