{
  "type": "Feature",
  "properties": {
    "iso:country":"IN",
    "ks:ks_name":"Dharmpura",
    "ks:ks_pop":651,
    "ks:ks_type":"VILLAGE",
    "name:eng_x_preferred":[
        "Dharmpura"
    ],
    "wof:name":"Dharmpura",
    "wof:placetype":"locality",
    "wof:population":651
},
  "geometry": {"coordinates":[75.53085400000001,27.611796],"type":"Point"}
}