{
  "type": "Feature",
  "properties": {
    "iso:country":"IN",
    "ks:ks_name":"Yadav Basti",
    "ks:ks_pop":247,
    "ks:ks_type":"HABITATION",
    "name:eng_x_preferred":[
        "Yadav Basti"
    ],
    "wof:name":"Yadav Basti",
    "wof:placetype":"locality",
    "wof:population":247
},
  "geometry": {"coordinates":[83.15774500000001,25.492692],"type":"Point"}
}