{
  "type": "Feature",
  "properties": {
    "gn:admin1_code":"11.0",
    "gn:admin2_code":"33.0",
    "gn:asciiname":"Bion",
    "gn:country_code":"IN",
    "gn:dem":2389,
    "gn:feature_class":"P",
    "gn:feature_code":"PPL",
    "gn:name":"Bion",
    "gn:population":0,
    "gn:timezone":"Asia/Kolkata",
    "iso:country":"IN",
    "name:ceb_x_preferred":[
        "Bion"
    ],
    "name:deu_x_preferred":[
        "Bion"
    ],
    "name:ell_x_preferred":[
        "\u0392\u03af\u03c9\u03bd"
    ],
    "name:fin_x_preferred":[
        "Bion"
    ],
    "name:fra_x_preferred":[
        "Bion"
    ],
    "name:ita_x_preferred":[
        "Bion"
    ],
    "name:lat_x_preferred":[
        "Bion"
    ],
    "name:lmo_x_preferred":[
        "Bion"
    ],
    "name:nld_x_preferred":[
        "Bion"
    ],
    "name:oci_x_preferred":[
        "Bion"
    ],
    "name:pol_x_preferred":[
        "Bion"
    ],
    "name:rus_x_preferred":[
        "\u0411\u0438\u043e\u043d"
    ],
    "name:spa_x_preferred":[
        "Bion"
    ],
    "name:swe_x_preferred":[
        "Bion"
    ],
    "name:ukr_x_preferred":[
        "\u0411\u0456\u043e\u043d"
    ],
    "wof:name":"Bion",
    "wof:placetype":"locality"
},
  "geometry": {"coordinates":[77.29321,31.07866],"type":"Point"}
}