{
  "type": "Feature",
  "properties": {
    "iso:country":"IN",
    "ks:ks_name":"Danpura Gagoni Huda",
    "ks:ks_pop":157,
    "ks:ks_type":"HABITATION",
    "name:eng_x_preferred":[
        "Danpura Gagoni Huda"
    ],
    "wof:name":"Danpura Gagoni Huda",
    "wof:placetype":"locality",
    "wof:population":157
},
  "geometry": {"coordinates":[71.481953,25.686592],"type":"Point"}
}