{
  "type": "Feature",
  "properties": {
    "iso:country":"IN",
    "ks:ks_name":"Softanp",
    "ks:ks_pop":88,
    "ks:ks_type":"HABITATION",
    "ks:ks_uagg_main":0,
    "name:eng_x_preferred":[
        "Softanp"
    ],
    "wof:name":"Softanp",
    "wof:placetype":"neighbourhood",
    "wof:population":88
},
  "geometry": {"coordinates":[81.931292,27.549134],"type":"Point"}
}