{
  "type": "Feature",
  "properties": {
    "gn:admin1_code":"19.0",
    "gn:admin2_code":"574.0",
    "gn:asciiname":"Kyatanahalli",
    "gn:country_code":"IN",
    "gn:dem":881,
    "gn:feature_class":"P",
    "gn:feature_code":"PPL",
    "gn:name":"Ky\u0101tanahalli",
    "gn:population":0,
    "gn:timezone":"Asia/Kolkata",
    "iso:country":"IN",
    "wof:name":"Kyatanahalli",
    "wof:placetype":"locality"
},
  "geometry": {"coordinates":[76.19038,12.84674],"type":"Point"}
}