{
  "type": "Feature",
  "properties": {
    "iso:country":"IN",
    "ks:ks_name":"Uttar Bengai",
    "ks:ks_pop":166,
    "ks:ks_type":"VILLAGE",
    "name:eng_x_preferred":[
        "Uttar Bengai"
    ],
    "wof:name":"Uttar Bengai",
    "wof:placetype":"locality",
    "wof:population":166
},
  "geometry": {"coordinates":[87.36314400000001,22.416418],"type":"Point"}
}