{
  "type": "Feature",
  "properties": {
    "gn:admin1_code":"35",
    "gn:admin2_code":"447.0",
    "gn:asciiname":"Garagohan",
    "gn:country_code":"IN",
    "gn:dem":558,
    "gn:feature_class":"P",
    "gn:feature_code":"PPL",
    "gn:name":"G\u0101r\u0101goh\u0101n",
    "gn:population":0,
    "gn:timezone":"Asia/Kolkata",
    "iso:country":"IN",
    "wof:name":"Garagohan",
    "wof:placetype":"locality"
},
  "geometry": {"coordinates":[77.61060999999999,21.74613],"type":"Point"}
}