{
  "type": "Feature",
  "properties": {
    "iso:country":"IN",
    "ks:ks_name":"Badgaon Jarkhiya",
    "ks:ks_pop":180,
    "ks:ks_type":"HABITATION",
    "name:eng_x_preferred":[
        "Badgaon Jarkhiya"
    ],
    "wof:name":"Badgaon Jarkhiya",
    "wof:placetype":"locality",
    "wof:population":180
},
  "geometry": {"coordinates":[75.173828,26.35742],"type":"Point"}
}