{
  "type": "Feature",
  "properties": {
    "gn:admin1_code":"13.0",
    "gn:admin2_code":"596.0",
    "gn:asciiname":"Kuttikkanam",
    "gn:country_code":"IN",
    "gn:dem":1077,
    "gn:feature_class":"P",
    "gn:feature_code":"PPL",
    "gn:name":"Kuttikkanam",
    "gn:population":0,
    "gn:timezone":"Asia/Kolkata",
    "iso:country":"IN",
    "name:mal_x_preferred":[
        "\u0d15\u0d41\u0d1f\u0d4d\u0d1f\u0d3f\u0d15\u0d4d\u0d15\u0d3e\u0d28\u0d02"
    ],
    "wof:name":"Kuttikkanam",
    "wof:placetype":"locality"
},
  "geometry": {"coordinates":[76.97166999999997,9.5803],"type":"Point"}
}