{
  "type": "Feature",
  "properties": {
    "gn:admin1_code":"36",
    "gn:admin2_code":"194.0",
    "gn:asciiname":"Chorari",
    "gn:country_code":"IN",
    "gn:dem":88,
    "gn:feature_class":"P",
    "gn:feature_code":"PPL",
    "gn:name":"Chor\u0101ri",
    "gn:population":0,
    "gn:timezone":"Asia/Kolkata",
    "iso:country":"IN",
    "ks:ks_alt_nam":"Chor\u0101ri",
    "ks:ks_name":"Chorari",
    "ks:ks_pop":3896,
    "ks:ks_type":"VILLAGE",
    "ks:ks_uagg_main":0,
    "name:eng_x_preferred":[
        "Chorari"
    ],
    "name:eng_x_variant":[
        "Chor\u0101ri"
    ],
    "wof:name":"Chorari",
    "wof:placetype":"neighbourhood",
    "wof:population":3896
},
  "geometry": {"coordinates":[82.644311,25.590495],"type":"Point"}
}