{
  "type": "Feature",
  "properties": {
    "iso:country":"IN",
    "ks:ks_name":"Brahmandiha",
    "ks:ks_pop":268,
    "ks:ks_type":"HABITATION",
    "name:eng_x_preferred":[
        "Brahmandiha"
    ],
    "wof:name":"Brahmandiha",
    "wof:placetype":"locality",
    "wof:population":268
},
  "geometry": {"coordinates":[87.043627,21.515734],"type":"Point"}
}