{
  "type": "Feature",
  "properties": {
    "gn:admin1_code":"19.0",
    "gn:admin2_code":"574.0",
    "gn:asciiname":"Mallapur",
    "gn:country_code":"IN",
    "gn:dem":941,
    "gn:feature_class":"P",
    "gn:feature_code":"PPL",
    "gn:name":"Mallapur",
    "gn:population":0,
    "gn:timezone":"Asia/Kolkata",
    "iso:country":"IN",
    "name:pam_x_preferred":[
        "Mallapur"
    ],
    "wof:name":"Mallapur",
    "wof:placetype":"locality"
},
  "geometry": {"coordinates":[75.85458,12.85766],"type":"Point"}
}