{
  "type": "Feature",
  "properties": {
    "iso:country":"IN",
    "ks:ks_name":"Rotee",
    "ks:ks_pop":229,
    "ks:ks_type":"HABITATION",
    "name:eng_x_preferred":[
        "Rotee"
    ],
    "wof:name":"Rotee",
    "wof:placetype":"locality",
    "wof:population":229
},
  "geometry": {"coordinates":[84.41640599999999,23.093556],"type":"Point"}
}