{
  "type": "Feature",
  "properties": {
    "iso:country":"IN",
    "ks:ks_alt_nam":"kolchai Falia",
    "ks:ks_name":"Kolchai Falia",
    "ks:ks_pop":80,
    "ks:ks_type":"HABITATION",
    "name:eng_x_preferred":[
        "Kolchai Falia"
    ],
    "wof:name":"Kolchai Falia",
    "wof:placetype":"locality",
    "wof:population":80
},
  "geometry": {"coordinates":[73.179444,20.320861],"type":"Point"}
}