{
  "type": "Feature",
  "properties": {
    "gn:admin1_code":"36",
    "gn:admin2_code":"179.0",
    "gn:asciiname":"Kalaiya",
    "gn:country_code":"IN",
    "gn:dem":90,
    "gn:feature_class":"P",
    "gn:feature_code":"PPL",
    "gn:name":"Kalaiya",
    "gn:population":0,
    "gn:timezone":"Asia/Kolkata",
    "iso:country":"IN",
    "name:bih_x_preferred":[
        "\u0915\u0932\u0948\u092f\u093e"
    ],
    "name:deu_x_preferred":[
        "Kalaiya"
    ],
    "name:fra_x_preferred":[
        "Kalaiya"
    ],
    "name:mai_x_preferred":[
        "\u0915\u0932\u0948\u092f\u093e \u0928\u0917\u0930\u092a\u093e\u0932\u093f\u0915\u093e"
    ],
    "name:nep_x_preferred":[
        "\u0915\u0932\u0948\u092f\u093e \u0928\u0917\u0930\u092a\u093e\u0932\u093f\u0915\u093e"
    ],
    "name:new_x_preferred":[
        "\u0915\u0932\u0948\u092f\u093e \u0928\u0917\u0930\u092a\u093e\u0932\u093f\u0915\u093e"
    ],
    "name:nld_x_preferred":[
        "Kalaiya"
    ],
    "name:pol_x_preferred":[
        "Kalaiya"
    ],
    "name:por_x_preferred":[
        "Kalaiya"
    ],
    "name:rus_x_preferred":[
        "\u041a\u0430\u043b\u0430\u0439\u044f"
    ],
    "name:tam_x_preferred":[
        "\u0b95\u0bb2\u0bc8\u0baf\u0bbe"
    ],
    "name:urd_x_preferred":[
        "\u06a9\u0644\u0626\u06cc\u0627"
    ],
    "name:zho_x_preferred":[
        "\u5361\u840a\u4e9e"
    ],
    "wof:name":"Kalaiya",
    "wof:placetype":"locality"
},
  "geometry": {"coordinates":[82.65858,26.25322],"type":"Point"}
}