{
  "type": "Feature",
  "properties": {
    "iso:country":"IN",
    "ks:ks_name":"Dalkisahi",
    "ks:ks_pop":135,
    "ks:ks_type":"HABITATION",
    "name:eng_x_preferred":[
        "Dalkisahi"
    ],
    "wof:name":"Dalkisahi",
    "wof:placetype":"locality",
    "wof:population":135
},
  "geometry": {"coordinates":[85.954398,21.184746],"type":"Point"}
}