{
  "type": "Feature",
  "properties": {
    "iso:country":"IN",
    "ks:ks_name":"10 SPM Temporary",
    "ks:ks_pop":374,
    "ks:ks_type":"VILLAGE",
    "name:eng_x_preferred":[
        "10 SPM Temporary"
    ],
    "wof:name":"10 SPM Temporary",
    "wof:placetype":"locality",
    "wof:population":374
},
  "geometry": {"coordinates":[74.52935600000001,29.214826],"type":"Point"}
}