{
  "type": "Feature",
  "properties": {
    "iso:country":"IN",
    "ks:ks_name":"Kanamareisahi",
    "ks:ks_pop":436,
    "ks:ks_type":"VILLAGE",
    "name:eng_x_preferred":[
        "Kanamareisahi"
    ],
    "wof:name":"Kanamareisahi",
    "wof:placetype":"locality",
    "wof:population":436
},
  "geometry": {"coordinates":[84.991653,20.059312],"type":"Point"}
}