{
  "type": "Feature",
  "properties": {
    "gn:admin1_code":"2.0",
    "gn:admin2_code":"554.0",
    "gn:asciiname":"Lakavaripalli",
    "gn:country_code":"IN",
    "gn:dem":487,
    "gn:feature_class":"P",
    "gn:feature_code":"PPL",
    "gn:name":"Lakav\u0101ripalli",
    "gn:population":0,
    "gn:timezone":"Asia/Kolkata",
    "iso:country":"IN",
    "wof:name":"Lakavaripalli",
    "wof:placetype":"locality"
},
  "geometry": {"coordinates":[79.00717,13.6866],"type":"Point"}
}