{
  "type": "Feature",
  "properties": {
    "gn:admin1_code":"19.0",
    "gn:admin2_code":"568.0",
    "gn:asciiname":"Bilve",
    "gn:country_code":"IN",
    "gn:dem":620,
    "gn:feature_class":"P",
    "gn:feature_code":"PPL",
    "gn:name":"Bilve",
    "gn:population":0,
    "gn:timezone":"Asia/Kolkata",
    "iso:country":"IN",
    "ks:ks_name":"Biluve",
    "ks:ks_pop":130,
    "ks:ks_type":"HABITATION",
    "name:eng_x_preferred":[
        "Biluve"
    ],
    "name:eng_x_variant":[
        "Bilve"
    ],
    "wof:name":"Biluve",
    "wof:placetype":"locality",
    "wof:population":130
},
  "geometry": {"coordinates":[75.28313199999999,13.734869],"type":"Point"}
}