{
  "type": "Feature",
  "properties": {
    "iso:country":"IN",
    "ks:ks_name":"Manepur",
    "ks:ks_pop":1200,
    "ks:ks_type":"HABITATION",
    "name:eng_x_preferred":[
        "Manepur"
    ],
    "wof:name":"Manepur",
    "wof:placetype":"locality",
    "wof:population":1200
},
  "geometry": {"coordinates":[80.24887699999999,25.96134],"type":"Point"}
}