{
  "type": "Feature",
  "properties": {
    "iso:country":"IN",
    "ks:ks_name":"Kacham Bila",
    "ks:ks_pop":77,
    "ks:ks_type":"HABITATION",
    "name:eng_x_preferred":[
        "Kacham Bila"
    ],
    "wof:name":"Kacham Bila",
    "wof:placetype":"locality",
    "wof:population":77
},
  "geometry": {"coordinates":[86.73909500000001,22.1906],"type":"Point"}
}