{
  "type": "Feature",
  "properties": {
    "gn:admin1_code":"2.0",
    "gn:admin2_code":"545.0",
    "gn:asciiname":"Madduluru",
    "gn:country_code":"IN",
    "gn:dem":436,
    "gn:feature_class":"P",
    "gn:feature_code":"PPL",
    "gn:name":"Maddul\u016bru",
    "gn:population":0,
    "gn:timezone":"Asia/Kolkata",
    "iso:country":"IN",
    "ks:ks_alt_nam":"Maddul\u016bru",
    "ks:ks_name":"Madduluru",
    "ks:ks_type":"VILLAGE",
    "name:eng_x_preferred":[
        "Madduluru"
    ],
    "name:eng_x_variant":[
        "Maddul\u016bru"
    ],
    "wof:name":"Madduluru",
    "wof:placetype":"locality"
},
  "geometry": {"coordinates":[81.604422,17.591867],"type":"Point"}
}