{
  "type": "Feature",
  "properties": {
    "iso:country":"IN",
    "ks:ks_name":"Kharkaguda",
    "ks:ks_pop":190,
    "ks:ks_type":"VILLAGE",
    "name:eng_x_preferred":[
        "Kharkaguda"
    ],
    "wof:name":"Kharkaguda",
    "wof:placetype":"locality",
    "wof:population":190
},
  "geometry": {"coordinates":[82.159282,18.278898],"type":"Point"}
}