{
  "type": "Feature",
  "properties": {
    "iso:country":"IN",
    "ks:ks_name":"Turiadih",
    "ks:ks_pop":344,
    "ks:ks_type":"HABITATION",
    "name:eng_x_preferred":[
        "Turiadih"
    ],
    "wof:name":"Turiadih",
    "wof:placetype":"locality",
    "wof:population":344
},
  "geometry": {"coordinates":[84.566312,23.429891],"type":"Point"}
}