{
  "type": "Feature",
  "properties": {
    "gn:admin1_code":"40",
    "gn:admin2_code":"538.0",
    "gn:asciiname":"Bhimawaram",
    "gn:country_code":"IN",
    "gn:dem":600,
    "gn:feature_class":"P",
    "gn:feature_code":"PPL",
    "gn:name":"Bh\u012bm\u0101waram",
    "gn:population":0,
    "gn:timezone":"Asia/Kolkata",
    "iso:country":"IN",
    "wof:name":"Bhimawaram",
    "wof:placetype":"locality"
},
  "geometry": {"coordinates":[78.09899999999998,16.99896],"type":"Point"}
}