{
  "type": "Feature",
  "properties": {
    "iso:country":"IN",
    "ks:ks_name":"Belwa",
    "ks:ks_pop":306,
    "ks:ks_type":"HABITATION",
    "name:eng_x_preferred":[
        "Belwa"
    ],
    "wof:name":"Belwa",
    "wof:placetype":"locality",
    "wof:population":306
},
  "geometry": {"coordinates":[83.24198699999999,27.287444],"type":"Point"}
}