{
  "type": "Feature",
  "properties": {
    "iso:country":"IN",
    "ks:ks_name":"Andhuti",
    "ks:ks_pop":508,
    "ks:ks_type":"HABITATION",
    "name:eng_x_preferred":[
        "Andhuti"
    ],
    "wof:name":"Andhuti",
    "wof:placetype":"locality",
    "wof:population":508
},
  "geometry": {"coordinates":[85.918295,20.242669],"type":"Point"}
}