{
  "type": "Feature",
  "properties": {
    "iso:country":"IN",
    "ks:ks_name":"Talwali Pipli",
    "ks:ks_pop":1175,
    "ks:ks_type":"HABITATION",
    "name:eng_x_preferred":[
        "Talwali Pipli"
    ],
    "wof:name":"Talwali Pipli",
    "wof:placetype":"locality",
    "wof:population":1175
},
  "geometry": {"coordinates":[75.144383,30.280317],"type":"Point"}
}