{
  "type": "Feature",
  "properties": {
    "iso:country":"IN",
    "ks:ks_name":"Gavnangwadi",
    "ks:ks_pop":136,
    "ks:ks_type":"HABITATION",
    "name:eng_x_preferred":[
        "Gavnangwadi"
    ],
    "wof:name":"Gavnangwadi",
    "wof:placetype":"locality",
    "wof:population":136
},
  "geometry": {"coordinates":[73.438317,17.486086],"type":"Point"}
}