{
  "type": "Feature",
  "properties": {
    "iso:country":"IN",
    "ks:ks_name":"Chitewani",
    "ks:ks_pop":102,
    "ks:ks_type":"HABITATION",
    "name:eng_x_preferred":[
        "Chitewani"
    ],
    "wof:name":"Chitewani",
    "wof:placetype":"locality",
    "wof:population":102
},
  "geometry": {"coordinates":[79.769953,21.600364],"type":"Point"}
}