{
  "type": "Feature",
  "properties": {
    "iso:country":"IN",
    "ks:ks_name":"Chakmurmur",
    "ks:ks_pop":2761,
    "ks:ks_type":"VILLAGE",
    "name:eng_x_preferred":[
        "Chakmurmur"
    ],
    "wof:name":"Chakmurmur",
    "wof:placetype":"locality",
    "wof:population":2761
},
  "geometry": {"coordinates":[85.340144,26.138452],"type":"Point"}
}