{
  "type": "Feature",
  "properties": {
    "iso:country":"IN",
    "ks:ks_name":"Barar Tola",
    "ks:ks_pop":422,
    "ks:ks_type":"HABITATION",
    "ks:ks_uagg_main":0,
    "name:eng_x_preferred":[
        "Barar Tola"
    ],
    "wof:name":"Barar Tola",
    "wof:placetype":"neighbourhood",
    "wof:population":422
},
  "geometry": {"coordinates":[84.85189800000001,26.65901],"type":"Point"}
}