{
  "type": "Feature",
  "properties": {
    "gn:admin1_code":"25.0",
    "gn:admin2_code":"631.0",
    "gn:asciiname":"Kristnapuram",
    "gn:country_code":"IN",
    "gn:dem":356,
    "gn:feature_class":"P",
    "gn:feature_code":"PPL",
    "gn:name":"Kristn\u0101puram",
    "gn:population":0,
    "gn:timezone":"Asia/Kolkata",
    "iso:country":"IN",
    "ks:ks_name":"Krishnapuram",
    "ks:ks_pop":180,
    "ks:ks_type":"HABITATION",
    "name:eng_x_preferred":[
        "Krishnapuram"
    ],
    "name:eng_x_variant":[
        "Kristnapuram"
    ],
    "wof:name":"Krishnapuram",
    "wof:placetype":"locality",
    "wof:population":180
},
  "geometry": {"coordinates":[78.565363,12.388988],"type":"Point"}
}