{
  "type": "Feature",
  "properties": {
    "gn:admin1_code":"39.0",
    "gn:admin2_code":"64.0",
    "gn:asciiname":"Baughar",
    "gn:country_code":"IN",
    "gn:dem":1144,
    "gn:feature_class":"P",
    "gn:feature_code":"PPL",
    "gn:name":"Baugh\u0101r",
    "gn:population":0,
    "gn:timezone":"Asia/Kolkata",
    "iso:country":"IN",
    "wof:name":"Baughar",
    "wof:placetype":"locality"
},
  "geometry": {"coordinates":[79.28404999999999,29.74899000000001],"type":"Point"}
}