{
  "type": "Feature",
  "properties": {
    "iso:country":"IN",
    "ks:ks_name":"Mosalesal",
    "ks:ks_pop":837,
    "ks:ks_type":"HABITATION",
    "name:eng_x_preferred":[
        "Mosalesal"
    ],
    "wof:name":"Mosalesal",
    "wof:placetype":"locality",
    "wof:population":837
},
  "geometry": {"coordinates":[74.37909500000001,14.508926],"type":"Point"}
}