{
  "type": "Feature",
  "properties": {
    "iso:country":"IN",
    "ks:ks_name":"Palhapur",
    "ks:ks_pop":800,
    "ks:ks_type":"HABITATION",
    "ks:ks_uagg_main":0,
    "name:eng_x_preferred":[
        "Palhapur"
    ],
    "wof:name":"Palhapur",
    "wof:placetype":"neighbourhood",
    "wof:population":800
},
  "geometry": {"coordinates":[80.40636499999999,27.891724],"type":"Point"}
}