{
  "type": "Feature",
  "properties": {
    "iso:country":"IN",
    "ks:ks_name":"Shivnath Purwa",
    "ks:ks_pop":110,
    "ks:ks_type":"HABITATION",
    "name:eng_x_preferred":[
        "Shivnath Purwa"
    ],
    "wof:name":"Shivnath Purwa",
    "wof:placetype":"locality",
    "wof:population":110
},
  "geometry": {"coordinates":[81.33212,27.351576],"type":"Point"}
}