{
  "type": "Feature",
  "properties": {
    "gn:admin1_code":"11",
    "gn:admin2_code":"27.0",
    "gn:asciiname":"Gahan",
    "gn:country_code":"IN",
    "gn:dem":2143,
    "gn:feature_class":"P",
    "gn:feature_code":"PPL",
    "gn:name":"Gahan",
    "gn:population":0,
    "gn:timezone":"Asia/Kolkata",
    "iso:country":"IN",
    "name:deu_x_preferred":[
        "Gahan"
    ],
    "name:fra_x_preferred":[
        "Gahan"
    ],
    "wof:name":"Gahan",
    "wof:placetype":"locality"
},
  "geometry": {"coordinates":[76.99507,31.34663],"type":"Point"}
}