{
  "type": "Feature",
  "properties": {
    "gn:admin1_code":"11",
    "gn:admin2_code":"33.0",
    "gn:asciiname":"Dadi",
    "gn:country_code":"IN",
    "gn:dem":2051,
    "gn:feature_class":"P",
    "gn:feature_code":"PPL",
    "gn:name":"D\u0101di",
    "gn:population":0,
    "gn:timezone":"Asia/Kolkata",
    "iso:country":"IN",
    "name:ceb_x_preferred":[
        "Dadi"
    ],
    "name:deu_x_preferred":[
        "Dadi"
    ],
    "name:ita_x_preferred":[
        "Dadi"
    ],
    "name:pol_x_preferred":[
        "Dadi"
    ],
    "name:rus_x_preferred":[
        "Dadi"
    ],
    "name:swe_x_preferred":[
        "Dadi"
    ],
    "wof:name":"Dadi",
    "wof:placetype":"locality"
},
  "geometry": {"coordinates":[77.78944,31.07759],"type":"Point"}
}