{
  "type": "Feature",
  "properties": {
    "iso:country":"IN",
    "ks:ks_name":"Pure Joghan",
    "ks:ks_pop":253,
    "ks:ks_type":"HABITATION",
    "name:eng_x_preferred":[
        "Pure Joghan"
    ],
    "wof:name":"Pure Joghan",
    "wof:placetype":"locality",
    "wof:population":253
},
  "geometry": {"coordinates":[81.953181,26.907216],"type":"Point"}
}