{
  "type": "Feature",
  "properties": {
    "iso:country":"IN",
    "ks:ks_name":"Vardusar",
    "ks:ks_pop":104,
    "ks:ks_type":"VILLAGE",
    "name:eng_x_preferred":[
        "Vardusar"
    ],
    "wof:name":"Vardusar",
    "wof:placetype":"locality",
    "wof:population":104
},
  "geometry": {"coordinates":[70.862838,23.09474],"type":"Point"}
}