{
  "type": "Feature",
  "properties": {
    "gn:admin1_code":"19.0",
    "gn:admin2_code":"569.0",
    "gn:asciiname":"Gulyadi",
    "gn:country_code":"IN",
    "gn:dem":20,
    "gn:feature_class":"P",
    "gn:feature_code":"PPL",
    "gn:name":"Guly\u0101di",
    "gn:population":0,
    "gn:timezone":"Asia/Kolkata",
    "iso:country":"IN",
    "ks:ks_alt_nam":"Gulv\u0101di",
    "ks:ks_name":"Gulvadi",
    "ks:ks_pop":4181,
    "ks:ks_type":"VILLAGE",
    "name:eng_x_preferred":[
        "Gulvadi"
    ],
    "name:eng_x_variant":[
        "Gulyadi",
        "Gulv\u0101di"
    ],
    "wof:name":"Gulvadi",
    "wof:placetype":"locality",
    "wof:population":4181
},
  "geometry": {"coordinates":[74.78198399999999,13.662204],"type":"Point"}
}