{
  "type": "Feature",
  "properties": {
    "gn:admin1_code":"36",
    "gn:admin2_code":"185.0",
    "gn:asciiname":"Pachperwa",
    "gn:country_code":"IN",
    "gn:dem":87,
    "gn:feature_class":"P",
    "gn:feature_code":"PPL",
    "gn:name":"Pachperwa",
    "gn:population":0,
    "gn:timezone":"Asia/Kolkata",
    "iso:country":"IN",
    "name:bpy_x_preferred":[
        "\u09aa\u09be\u099a\u09aa\u09c7\u09b0\u09c1\u09f1\u09be"
    ],
    "name:ceb_x_preferred":[
        "Pachperwa"
    ],
    "name:ita_x_preferred":[
        "Pachperwa"
    ],
    "name:mlg_x_preferred":[
        "Pachperwa"
    ],
    "name:msa_x_preferred":[
        "Pachperwa"
    ],
    "name:nld_x_preferred":[
        "Pachperwa"
    ],
    "name:pol_x_preferred":[
        "Pachperwa"
    ],
    "name:por_x_preferred":[
        "Pachperwa"
    ],
    "name:swe_x_preferred":[
        "Pachperwa"
    ],
    "name:urd_x_preferred":[
        "\u067e\u0686\u067e\u06cc\u0631\u0648\u0627"
    ],
    "name:vie_x_preferred":[
        "Pachperwa"
    ],
    "name:zho_x_preferred":[
        "\u5e15\u5947\u4f69\u5c14\u74e6"
    ],
    "wof:name":"Pachperwa",
    "wof:placetype":"locality"
},
  "geometry": {"coordinates":[82.85596,26.65717],"type":"Point"}
}