{
  "type": "Feature",
  "properties": {
    "gn:admin1_code":"28.0",
    "gn:admin2_code":"334.0",
    "gn:asciiname":"Dewanganj",
    "gn:country_code":"IN",
    "gn:dem":78,
    "gn:feature_class":"P",
    "gn:feature_code":"PPL",
    "gn:name":"Dew\u0101nganj",
    "gn:population":0,
    "gn:timezone":"Asia/Kolkata",
    "iso:country":"IN",
    "name:mai_x_preferred":[
        "\u0926\u0947\u0935\u093e\u0928\u0917\u091e\u094d\u091c \u0917\u093e\u0909\u0901\u092a\u093e\u0932\u093f\u0915\u093e"
    ],
    "name:nep_x_preferred":[
        "\u0926\u0947\u0935\u093e\u0928\u0917\u091e\u094d\u091c \u0917\u093e\u0909\u0901\u092a\u093e\u0932\u093f\u0915\u093e"
    ],
    "wof:name":"Dewanganj",
    "wof:placetype":"locality"
},
  "geometry": {"coordinates":[87.58808000000001,24.06102000000001],"type":"Point"}
}