{
  "type": "Feature",
  "properties": {
    "iso:country":"IN",
    "ks:ks_name":"Nagla Sapera2",
    "ks:ks_pop":101,
    "ks:ks_type":"HABITATION",
    "name:eng_x_preferred":[
        "Nagla Sapera2"
    ],
    "wof:name":"Nagla Sapera2",
    "wof:placetype":"locality",
    "wof:population":101
},
  "geometry": {"coordinates":[78.135096,26.986144],"type":"Point"}
}