{
  "type": "Feature",
  "properties": {
    "iso:country":"IN",
    "ks:ks_name":"Lokhiram",
    "ks:ks_pop":20,
    "ks:ks_type":"HABITATION",
    "ks:ks_uagg_main":0,
    "name:eng_x_preferred":[
        "Lokhiram"
    ],
    "wof:name":"Lokhiram",
    "wof:placetype":"neighbourhood",
    "wof:population":20
},
  "geometry": {"coordinates":[93.768655,26.361451],"type":"Point"}
}