{
  "type": "Feature",
  "properties": {
    "iso:country":"IN",
    "ks:ks_name":"Rajeev Nagar",
    "ks:ks_pop":20,
    "ks:ks_type":"VILLAGE",
    "name:eng_x_preferred":[
        "Rajeev Nagar"
    ],
    "wof:name":"Rajeev Nagar",
    "wof:placetype":"locality",
    "wof:population":20
},
  "geometry": {"coordinates":[71.072147,25.690853],"type":"Point"}
}