{
  "type": "Feature",
  "properties": {
    "gn:admin1_code":"39.0",
    "gn:admin2_code":"60.0",
    "gn:asciiname":"Dumet",
    "gn:country_code":"IN",
    "gn:dem":508,
    "gn:feature_class":"P",
    "gn:feature_code":"PPL",
    "gn:name":"Dumet",
    "gn:population":0,
    "gn:timezone":"Asia/Kolkata",
    "iso:country":"IN",
    "wof:name":"Dumet",
    "wof:placetype":"locality"
},
  "geometry": {"coordinates":[77.84617,30.5055],"type":"Point"}
}