{
  "type": "Feature",
  "properties": {
    "iso:country":"IN",
    "ks:ks_name":"171 RDAS",
    "ks:ks_pop":106,
    "ks:ks_type":"VILLAGE",
    "name:eng_x_preferred":[
        "171 RDAS"
    ],
    "wof:name":"171 RDAS",
    "wof:placetype":"locality",
    "wof:population":106
},
  "geometry": {"coordinates":[73.227531,29.117635],"type":"Point"}
}