{
  "type": "Feature",
  "properties": {
    "iso:country":"IN",
    "ks:ks_alt_nam":"Ravat faliya",
    "ks:ks_name":"Ravat Faliya",
    "ks:ks_pop":320,
    "ks:ks_type":"HABITATION",
    "name:eng_x_preferred":[
        "Ravat Faliya"
    ],
    "wof:name":"Ravat Faliya",
    "wof:placetype":"locality",
    "wof:population":320
},
  "geometry": {"coordinates":[73.871028,22.962472],"type":"Point"}
}