{
  "type": "Feature",
  "properties": {
    "gn:admin1_code":"3.0",
    "gn:admin2_code":"310.0",
    "gn:asciiname":"Merbil Grant",
    "gn:country_code":"IN",
    "gn:dem":117,
    "gn:feature_class":"P",
    "gn:feature_code":"PPL",
    "gn:name":"Merbil Grant",
    "gn:population":0,
    "gn:timezone":"Asia/Kolkata",
    "iso:country":"IN",
    "wof:name":"Merbil Grant",
    "wof:placetype":"neighbourhood"
},
  "geometry": {"coordinates":[95.22797,27.30676],"type":"Point"}
}