{
  "type": "Feature",
  "properties": {
    "iso:country":"IN",
    "ks:ks_name":"Makodipura",
    "ks:ks_pop":115,
    "ks:ks_type":"HABITATION",
    "name:eng_x_preferred":[
        "Makodipura"
    ],
    "wof:name":"Makodipura",
    "wof:placetype":"locality",
    "wof:population":115
},
  "geometry": {"coordinates":[72.789011,22.7536],"type":"Point"}
}