{
  "type": "Feature",
  "properties": {
    "iso:country":"IN",
    "ks:ks_name":"Bhagat Garh",
    "ks:ks_pop":208,
    "ks:ks_type":"VILLAGE",
    "name:eng_x_preferred":[
        "Bhagat Garh"
    ],
    "wof:name":"Bhagat Garh",
    "wof:placetype":"locality",
    "wof:population":208
},
  "geometry": {"coordinates":[72.487622,26.461839],"type":"Point"}
}