{
  "type": "Feature",
  "properties": {
    "gn:admin1_code":"34.0",
    "gn:admin2_code":"237.0",
    "gn:asciiname":"Kalaunda",
    "gn:country_code":"IN",
    "gn:dem":185,
    "gn:feature_class":"P",
    "gn:feature_code":"PPL",
    "gn:name":"Kalaunda",
    "gn:population":0,
    "gn:timezone":"Asia/Kolkata",
    "iso:country":"IN",
    "ks:ks_alt_nam":"KALAUNDA",
    "ks:ks_name":"Kalaunda",
    "ks:ks_pop":70,
    "ks:ks_type":"HABITATION",
    "name:eng_x_preferred":[
        "Kalaunda"
    ],
    "wof:name":"Kalaunda",
    "wof:placetype":"locality",
    "wof:population":70
},
  "geometry": {"coordinates":[85.359759,24.580808],"type":"Point"}
}