{
  "type": "Feature",
  "properties": {
    "iso:country":"IN",
    "ks:ks_name":"Ainchhar",
    "ks:ks_type":"VILLAGE",
    "ks:ks_uagg_main":0,
    "name:eng_x_preferred":[
        "Ainchhar"
    ],
    "wof:name":"Ainchhar",
    "wof:placetype":"neighbourhood"
},
  "geometry": {"coordinates":[77.54172,28.465693],"type":"Point"}
}