{
  "type": "Feature",
  "properties": {
    "iso:country":"IN",
    "ks:ks_alt_nam":"Sop\u0101r\u0101m",
    "ks:ks_name":"Soparam",
    "ks:ks_pop":144,
    "ks:ks_type":"VILLAGE",
    "name:eng_x_preferred":[
        "Soparam"
    ],
    "name:eng_x_variant":[
        "Sop\u0101r\u0101m"
    ],
    "wof:name":"Soparam",
    "wof:placetype":"locality",
    "wof:population":144
},
  "geometry": {"coordinates":[84.77779200000001,23.811005],"type":"Point"}
}