{
  "type": "Feature",
  "properties": {
    "iso:country":"IN",
    "ks:ks_name":"Jodibhatta",
    "ks:ks_pop":410,
    "ks:ks_type":"HABITATION",
    "ks:ks_uagg_main":0,
    "name:eng_x_preferred":[
        "Jodibhatta"
    ],
    "wof:name":"Jodibhatta",
    "wof:placetype":"neighbourhood",
    "wof:population":410
},
  "geometry": {"coordinates":[82.07584900000001,19.720446],"type":"Point"}
}