{
  "type": "Feature",
  "properties": {
    "gn:admin1_code":"34.0",
    "gn:admin2_code":"236.0",
    "gn:asciiname":"Kachnar",
    "gn:country_code":"IN",
    "gn:dem":288,
    "gn:feature_class":"P",
    "gn:feature_code":"PPL",
    "gn:name":"Kachn\u0101r",
    "gn:population":0,
    "gn:timezone":"Asia/Kolkata",
    "iso:country":"IN",
    "ks:ks_alt_nam":"KACHNAR",
    "ks:ks_name":"Kachnar",
    "ks:ks_pop":297,
    "ks:ks_type":"HABITATION",
    "name:eng_x_preferred":[
        "Kachnar"
    ],
    "wof:name":"Kachnar",
    "wof:placetype":"locality",
    "wof:population":297
},
  "geometry": {"coordinates":[84.414334,24.509215],"type":"Point"}
}