{
  "type": "Feature",
  "properties": {
    "iso:country":"IN",
    "ks:ks_name":"Dukhiya Kobra Para",
    "ks:ks_pop":165,
    "ks:ks_type":"HABITATION",
    "ks:ks_uagg_main":0,
    "name:eng_x_preferred":[
        "Dukhiya Kobra Para"
    ],
    "wof:name":"Dukhiya Kobra Para",
    "wof:placetype":"neighbourhood",
    "wof:population":165
},
  "geometry": {"coordinates":[91.448278,23.776014],"type":"Point"}
}