{
  "type": "Feature",
  "properties": {
    "iso:country":"IN",
    "ks:ks_name":"English",
    "ks:ks_pop":146,
    "ks:ks_type":"VILLAGE",
    "name:eng_x_preferred":[
        "English"
    ],
    "wof:name":"English",
    "wof:placetype":"locality",
    "wof:population":146
},
  "geometry": {"coordinates":[84.758,25.68],"type":"Point"}
}