{
  "type": "Feature",
  "properties": {
    "gn:admin1_code":"13.0",
    "gn:admin2_code":"592.0",
    "gn:asciiname":"Puzhakkattiri",
    "gn:country_code":"IN",
    "gn:dem":42,
    "gn:feature_class":"P",
    "gn:feature_code":"PPL",
    "gn:name":"Puzhakk\u0101ttiri",
    "gn:population":0,
    "gn:timezone":"Asia/Kolkata",
    "iso:country":"IN",
    "name:mal_x_preferred":[
        "\u0d2a\u0d41\u0d34\u0d15\u0d4d\u0d15\u0d3e\u0d1f\u0d4d\u0d1f\u0d3f\u0d30\u0d3f \u0d17\u0d4d\u0d30\u0d3e\u0d2e\u0d2a\u0d1e\u0d4d\u0d1a\u0d3e\u0d2f\u0d24\u0d4d\u0d24\u0d4d"
    ],
    "wof:name":"Puzhakkattiri",
    "wof:placetype":"locality"
},
  "geometry": {"coordinates":[76.15384,10.97869],"type":"Point"}
}