{
  "type": "Feature",
  "properties": {
    "iso:country":"IN",
    "ks:ks_name":"Muddanagaripalli",
    "ks:ks_pop":158,
    "ks:ks_type":"HABITATION",
    "ks:ks_uagg_main":0,
    "name:eng_x_preferred":[
        "Muddanagaripalli"
    ],
    "wof:name":"Muddanagaripalli",
    "wof:placetype":"neighbourhood",
    "wof:population":158
},
  "geometry": {"coordinates":[78.237065,14.103317],"type":"Point"}
}