{
  "type": "Feature",
  "properties": {
    "iso:country":"IN",
    "ks:ks_name":"Pirnagar",
    "ks:ks_pop":803,
    "ks:ks_type":"VILLAGE",
    "name:eng_x_preferred":[
        "Pirnagar"
    ],
    "wof:name":"Pirnagar",
    "wof:placetype":"locality",
    "wof:population":803
},
  "geometry": {"coordinates":[92.457589,24.973869],"type":"Point"}
}