{
  "type": "Feature",
  "properties": {
    "iso:country":"IN",
    "ks:ks_name":"Murudabada",
    "ks:ks_pop":430,
    "ks:ks_type":"VILLAGE",
    "name:eng_x_preferred":[
        "Murudabada"
    ],
    "wof:name":"Murudabada",
    "wof:placetype":"locality",
    "wof:population":430
},
  "geometry": {"coordinates":[86.215565,20.470308],"type":"Point"}
}