{
  "type": "Feature",
  "properties": {
    "iso:country":"IN",
    "ks:ks_name":"Tokalavarigudem",
    "ks:ks_pop":94,
    "ks:ks_type":"HABITATION",
    "name:eng_x_preferred":[
        "Tokalavarigudem"
    ],
    "wof:name":"Tokalavarigudem",
    "wof:placetype":"locality",
    "wof:population":94
},
  "geometry": {"coordinates":[79.69117,16.842777],"type":"Point"}
}