{
  "type": "Feature",
  "properties": {
    "iso:country":"IN",
    "ks:ks_name":"Benda Danda",
    "ks:ks_pop":708,
    "ks:ks_type":"VILLAGE",
    "name:eng_x_preferred":[
        "Benda Danda"
    ],
    "wof:name":"Benda Danda",
    "wof:placetype":"locality",
    "wof:population":708
},
  "geometry": {"coordinates":[79.56270499999999,25.878858],"type":"Point"}
}