{
  "type": "Feature",
  "properties": {
    "iso:country":"IN",
    "ks:ks_name":"Ranudih",
    "ks:ks_pop":171,
    "ks:ks_type":"VILLAGE",
    "name:eng_x_preferred":[
        "Ranudih"
    ],
    "wof:name":"Ranudih",
    "wof:placetype":"locality",
    "wof:population":171
},
  "geometry": {"coordinates":[83.90758599999999,23.938399],"type":"Point"}
}