{
  "type": "Feature",
  "properties": {
    "iso:country":"IN",
    "ks:ks_name":"Keregodu",
    "ks:ks_pop":21,
    "ks:ks_type":"HABITATION",
    "name:eng_x_preferred":[
        "Keregodu"
    ],
    "wof:name":"Keregodu",
    "wof:placetype":"locality",
    "wof:population":21
},
  "geometry": {"coordinates":[74.997491,13.79405],"type":"Point"}
}