{
  "type": "Feature",
  "properties": {
    "iso:country":"IN",
    "ks:ks_name":"Braja Kishorpur",
    "ks:ks_pop":1132,
    "ks:ks_type":"VILLAGE",
    "ks:ks_uagg_main":0,
    "name:eng_x_preferred":[
        "Braja Kishorpur"
    ],
    "wof:name":"Braja Kishorpur",
    "wof:placetype":"neighbourhood",
    "wof:population":1132
},
  "geometry": {"coordinates":[87.626408,21.967203],"type":"Point"}
}