{
  "type": "Feature",
  "properties": {
    "iso:country":"IN",
    "ks:ks_name":"Jogwadi",
    "ks:ks_pop":155,
    "ks:ks_type":"HABITATION",
    "name:eng_x_preferred":[
        "Jogwadi"
    ],
    "wof:name":"Jogwadi",
    "wof:placetype":"locality",
    "wof:population":155
},
  "geometry": {"coordinates":[73.550956,17.362389],"type":"Point"}
}