{
  "type": "Feature",
  "properties": {
    "iso:country":"IN",
    "ks:ks_alt_nam":"PIPERTOLA Syahi",
    "ks:ks_name":"Pipertola Syahi",
    "ks:ks_pop":380,
    "ks:ks_type":"HABITATION",
    "name:eng_x_preferred":[
        "Pipertola Syahi"
    ],
    "wof:name":"Pipertola Syahi",
    "wof:placetype":"locality",
    "wof:population":380
},
  "geometry": {"coordinates":[83.25719599999999,23.841589],"type":"Point"}
}