{
  "type": "Feature",
  "properties": {
    "iso:country":"IN",
    "ks:ks_name":"Khunta Ratna",
    "ks:ks_pop":295,
    "ks:ks_type":"VILLAGE",
    "name:eng_x_preferred":[
        "Khunta Ratna"
    ],
    "wof:name":"Khunta Ratna",
    "wof:placetype":"locality",
    "wof:population":295
},
  "geometry": {"coordinates":[74.264747,23.216681],"type":"Point"}
}