{
  "type": "Feature",
  "properties": {
    "iso:country":"IN",
    "ks:ks_name":"Lwarkha",
    "ks:ks_pop":279,
    "ks:ks_type":"VILLAGE",
    "name:eng_x_preferred":[
        "Lwarkha"
    ],
    "wof:name":"Lwarkha",
    "wof:placetype":"locality",
    "wof:population":279
},
  "geometry": {"coordinates":[78.37638699999999,30.478794],"type":"Point"}
}