{
  "type": "Feature",
  "properties": {
    "iso:country":"IN",
    "ks:ks_name":"Ponnaiyagoundanur",
    "ks:ks_pop":142,
    "ks:ks_type":"HABITATION",
    "name:eng_x_preferred":[
        "Ponnaiyagoundanur"
    ],
    "wof:name":"Ponnaiyagoundanur",
    "wof:placetype":"locality",
    "wof:population":142
},
  "geometry": {"coordinates":[77.680668,11.54168],"type":"Point"}
}