{
  "type": "Feature",
  "properties": {
    "iso:country":"IN",
    "ks:ks_name":"Kharechekond",
    "ks:ks_pop":56,
    "ks:ks_type":"HABITATION",
    "name:eng_x_preferred":[
        "Kharechekond"
    ],
    "wof:name":"Kharechekond",
    "wof:placetype":"locality",
    "wof:population":56
},
  "geometry": {"coordinates":[73.504232,16.946473],"type":"Point"}
}