{
  "type": "Feature",
  "properties": {
    "gn:admin1_code":"34.0",
    "gn:admin2_code":"216.0",
    "gn:asciiname":"Gopalpur Khurd",
    "gn:country_code":"IN",
    "gn:dem":52,
    "gn:feature_class":"P",
    "gn:feature_code":"PPL",
    "gn:name":"Gop\u0101lpur Khurd",
    "gn:population":0,
    "gn:timezone":"Asia/Kolkata",
    "iso:country":"IN",
    "ks:ks_alt_nam":"Gop\u0101lpur Khurd",
    "ks:ks_name":"Gopalpur Khurd",
    "ks:ks_pop":738,
    "ks:ks_type":"VILLAGE",
    "name:eng_x_preferred":[
        "Gopalpur Khurd"
    ],
    "name:eng_x_variant":[
        "Gop\u0101lpur Khurd"
    ],
    "wof:name":"Gopalpur Khurd",
    "wof:placetype":"locality",
    "wof:population":738
},
  "geometry": {"coordinates":[85.549605,25.992263],"type":"Point"}
}