{
  "type": "Feature",
  "properties": {
    "iso:country":"IN",
    "ks:ks_name":"Banskhedi",
    "ks:ks_pop":276,
    "ks:ks_type":"HABITATION",
    "name:eng_x_preferred":[
        "Banskhedi"
    ],
    "wof:name":"Banskhedi",
    "wof:placetype":"locality",
    "wof:population":276
},
  "geometry": {"coordinates":[76.778503,23.970682],"type":"Point"}
}