{
  "type": "Feature",
  "properties": {
    "iso:country":"IN",
    "ks:ks_name":"Gopalwadi",
    "ks:ks_pop":137,
    "ks:ks_type":"HABITATION",
    "name:eng_x_preferred":[
        "Gopalwadi"
    ],
    "wof:name":"Gopalwadi",
    "wof:placetype":"locality",
    "wof:population":137
},
  "geometry": {"coordinates":[73.25617200000001,17.783406],"type":"Point"}
}