{
  "type": "Feature",
  "properties": {
    "iso:country":"IN",
    "ks:ks_name":"Sadullahpur",
    "ks:ks_pop":348,
    "ks:ks_type":"VILLAGE",
    "name:eng_x_preferred":[
        "Sadullahpur"
    ],
    "wof:name":"Sadullahpur",
    "wof:placetype":"locality",
    "wof:population":348
},
  "geometry": {"coordinates":[85.42823199999999,26.180058],"type":"Point"}
}