{
  "type": "Feature",
  "properties": {
    "iso:country":"IN",
    "ks:ks_name":"Boudhwadi",
    "ks:ks_pop":268,
    "ks:ks_type":"HABITATION",
    "name:eng_x_preferred":[
        "Boudhwadi"
    ],
    "wof:name":"Boudhwadi",
    "wof:placetype":"locality",
    "wof:population":268
},
  "geometry": {"coordinates":[73.62261100000001,17.120077],"type":"Point"}
}