{
  "type": "Feature",
  "properties": {
    "gn:admin1_code":"40",
    "gn:admin2_code":"533.0",
    "gn:asciiname":"Chincholi",
    "gn:country_code":"IN",
    "gn:dem":377,
    "gn:feature_class":"P",
    "gn:feature_code":"PPL",
    "gn:name":"Chincholi",
    "gn:population":0,
    "gn:timezone":"Asia/Kolkata",
    "iso:country":"IN",
    "name:ben_x_preferred":[
        "\u099a\u09bf\u09a8\u099a\u09cb\u09b2\u09bf"
    ],
    "name:bpy_x_preferred":[
        "\u099a\u09bf\u09a8\u099a\u09cb\u09b2\u09bf"
    ],
    "name:ceb_x_preferred":[
        "Chincholi Taluk"
    ],
    "name:ita_x_preferred":[
        "Chincholi"
    ],
    "name:kan_x_preferred":[
        "\u0c9a\u0cbf\u0c82\u0c9a\u0ccb\u0cb3\u0cbf"
    ],
    "name:mlg_x_preferred":[
        "Chincholi"
    ],
    "name:msa_x_preferred":[
        "Chincholi"
    ],
    "name:new_x_preferred":[
        "\u091a\u093f\u0928\u094d\u091a\u094b\u0932\u0940"
    ],
    "name:nld_x_preferred":[
        "Chincholi"
    ],
    "name:por_x_preferred":[
        "Chincholi"
    ],
    "name:spa_x_preferred":[
        "Chincholi"
    ],
    "name:swe_x_preferred":[
        "Chincholi Taluk"
    ],
    "name:vie_x_preferred":[
        "Chincholi"
    ],
    "name:zho_x_preferred":[
        "\u5947\u6069\u4e54\u5229"
    ],
    "wof:name":"Chincholi",
    "wof:placetype":"locality"
},
  "geometry": {"coordinates":[77.81133,18.42403],"type":"Point"}
}