{
  "type": "Feature",
  "properties": {
    "iso:country":"IN",
    "ks:ks_name":"Misharan Purwa",
    "ks:ks_pop":198,
    "ks:ks_type":"HABITATION",
    "ks:ks_uagg_main":0,
    "name:eng_x_preferred":[
        "Misharan Purwa"
    ],
    "wof:name":"Misharan Purwa",
    "wof:placetype":"neighbourhood",
    "wof:population":198
},
  "geometry": {"coordinates":[82.221452,27.223767],"type":"Point"}
}