{
  "type": "Feature",
  "properties": {
    "iso:country":"IN",
    "ks:ks_alt_nam":"NAGASHAR BASA",
    "ks:ks_name":"Nagashar Basa",
    "ks:ks_pop":166,
    "ks:ks_type":"HABITATION",
    "name:eng_x_preferred":[
        "Nagashar Basa"
    ],
    "wof:name":"Nagashar Basa",
    "wof:placetype":"locality",
    "wof:population":166
},
  "geometry": {"coordinates":[86.71439100000001,25.578321],"type":"Point"}
}