{
  "type": "Feature",
  "properties": {
    "gn:admin1_code":"38.0",
    "gn:admin2_code":"354.0",
    "gn:asciiname":"Chirkunda",
    "gn:country_code":"IN",
    "gn:dem":129,
    "gn:feature_class":"P",
    "gn:feature_code":"PPL",
    "gn:name":"Chirkunda",
    "gn:population":0,
    "gn:timezone":"Asia/Kolkata",
    "iso:country":"IN",
    "name:bih_x_preferred":[
        "\u091a\u093f\u0930\u0915\u0941\u0902\u0921\u093e"
    ],
    "name:bpy_x_preferred":[
        "\u099a\u09bf\u09b0\u0995\u09c1\u09a8\u09cd\u09a1"
    ],
    "name:hif_x_preferred":[
        "Chirkunda"
    ],
    "name:ita_x_preferred":[
        "Chirkunda"
    ],
    "name:msa_x_preferred":[
        "Chirkunda"
    ],
    "name:new_x_preferred":[
        "\u091a\u093f\u0930\u094d\u0915\u0941\u0923\u094d\u0921"
    ],
    "name:nld_x_preferred":[
        "Chirkunda"
    ],
    "name:ori_x_preferred":[
        "\u0b1a\u0b3f\u0b30\u0b4d\u0b15\u0b41\u0b28\u0b4d\u0b26\u0b3e"
    ],
    "name:pnb_x_preferred":[
        "\u0686\u06cc\u0631\u06a9\u0646\u0688\u0627"
    ],
    "name:por_x_preferred":[
        "Chirkunda"
    ],
    "name:spa_x_preferred":[
        "Chirkunda"
    ],
    "name:swe_x_preferred":[
        "Chirkunda"
    ],
    "name:urd_x_preferred":[
        "\u0686\u06cc\u0631\u06a9\u0646\u0688\u0627"
    ],
    "name:vie_x_preferred":[
        "Chirkunda"
    ],
    "name:zho_x_preferred":[
        "\u5947\u5c14\u5e93\u6069\u8fbe"
    ],
    "wof:name":"Chirkunda",
    "wof:placetype":"neighbourhood"
},
  "geometry": {"coordinates":[86.78804,23.74771],"type":"Point"}
}