{
  "type": "Feature",
  "properties": {
    "iso:country":"IN",
    "ks:ks_name":"Balarampur",
    "ks:ks_pop":910,
    "ks:ks_type":"VILLAGE",
    "name:eng_x_preferred":[
        "Balarampur"
    ],
    "wof:name":"Balarampur",
    "wof:placetype":"locality",
    "wof:population":910
},
  "geometry": {"coordinates":[87.692261,22.486741],"type":"Point"}
}