{
  "type": "Feature",
  "properties": {
    "gn:admin1_code":"40",
    "gn:admin2_code":"540.0",
    "gn:asciiname":"Mangapet",
    "gn:country_code":"IN",
    "gn:dem":80,
    "gn:feature_class":"P",
    "gn:feature_code":"PPL",
    "gn:name":"Mangapet",
    "gn:population":0,
    "gn:timezone":"Asia/Kolkata",
    "iso:country":"IN",
    "name:ceb_x_preferred":[
        "Mangapet"
    ],
    "name:new_x_preferred":[
        "\u092e\u0902\u0917\u092a\u0947\u091f \u092e\u0923\u094d\u0921\u0932"
    ],
    "name:swe_x_preferred":[
        "Mangapet"
    ],
    "name:tel_x_preferred":[
        "\u0c2e\u0c02\u0c17\u0c2a\u0c47\u0c1f \u0c2e\u0c02\u0c21\u0c32\u0c02"
    ],
    "name:und_x_variant":[
        "Mangapel"
    ],
    "wof:name":"Mangapet",
    "wof:placetype":"locality"
},
  "geometry": {"coordinates":[80.51980999999998,18.25396],"type":"Point"}
}