{
  "type": "Feature",
  "properties": {
    "iso:country":"IN",
    "ks:ks_name":"Bhat Bigha",
    "ks:ks_pop":267,
    "ks:ks_type":"HABITATION",
    "name:eng_x_preferred":[
        "Bhat Bigha"
    ],
    "wof:name":"Bhat Bigha",
    "wof:placetype":"locality",
    "wof:population":267
},
  "geometry": {"coordinates":[84.809301,24.992518],"type":"Point"}
}