{
  "type": "Feature",
  "properties": {
    "gn:admin1_code":"11",
    "gn:admin2_code":"27.0",
    "gn:asciiname":"Kothi",
    "gn:country_code":"IN",
    "gn:dem":1142,
    "gn:feature_class":"P",
    "gn:feature_code":"PPL",
    "gn:name":"Kothi",
    "gn:population":0,
    "gn:timezone":"Asia/Kolkata",
    "iso:country":"IN",
    "name:ceb_x_preferred":[
        "Kothi"
    ],
    "name:swe_x_preferred":[
        "Kothi"
    ],
    "wof:name":"Kothi",
    "wof:placetype":"locality"
},
  "geometry": {"coordinates":[76.79484000000002,31.75365],"type":"Point"}
}