{
  "type": "Feature",
  "properties": {
    "iso:country":"IN",
    "ks:ks_alt_nam":"KAHAR TOLA",
    "ks:ks_name":"Kahar Tola",
    "ks:ks_pop":193,
    "ks:ks_type":"HABITATION",
    "ks:ks_uagg_main":0,
    "name:eng_x_preferred":[
        "Kahar Tola"
    ],
    "wof:name":"Kahar Tola",
    "wof:placetype":"neighbourhood",
    "wof:population":193
},
  "geometry": {"coordinates":[85.929136,25.513653],"type":"Point"}
}