{
  "type": "Feature",
  "properties": {
    "iso:country":"IN",
    "ks:ks_name":"Lahiripur Majher Para",
    "ks:ks_pop":1501,
    "ks:ks_type":"HABITATION",
    "name:eng_x_preferred":[
        "Lahiripur Majher Para"
    ],
    "wof:name":"Lahiripur Majher Para",
    "wof:placetype":"locality",
    "wof:population":1501
},
  "geometry": {"coordinates":[88.915809,22.103308],"type":"Point"}
}