{
  "type": "Feature",
  "properties": {
    "iso:country":"IN",
    "ks:ks_name":"Nungapadar",
    "ks:ks_pop":289,
    "ks:ks_type":"HABITATION",
    "name:eng_x_preferred":[
        "Nungapadar"
    ],
    "wof:name":"Nungapadar",
    "wof:placetype":"locality",
    "wof:population":289
},
  "geometry": {"coordinates":[81.149308,19.919931],"type":"Point"}
}