{
  "type": "Feature",
  "properties": {
    "iso:country":"IN",
    "ks:ks_name":"Halua Gaon",
    "ks:ks_pop":1050,
    "ks:ks_type":"VILLAGE",
    "ks:ks_uagg_main":0,
    "name:eng_x_preferred":[
        "Halua Gaon"
    ],
    "wof:name":"Halua Gaon",
    "wof:placetype":"neighbourhood",
    "wof:population":1050
},
  "geometry": {"coordinates":[94.745695,26.856854],"type":"Point"}
}