{
  "type": "Feature",
  "properties": {
    "iso:country":"IN",
    "ks:ks_name":"Neem Ka Khera",
    "ks:ks_pop":61,
    "ks:ks_type":"VILLAGE",
    "name:eng_x_preferred":[
        "Neem Ka Khera"
    ],
    "wof:name":"Neem Ka Khera",
    "wof:placetype":"locality",
    "wof:population":61
},
  "geometry": {"coordinates":[75.578953,24.96717],"type":"Point"}
}