{
  "type": "Feature",
  "properties": {
    "iso:country":"IN",
    "ks:ks_name":"Roksa",
    "ks:ks_pop":10224,
    "ks:ks_type":"VILLAGE",
    "name:eng_x_preferred":[
        "Roksa"
    ],
    "wof:name":"Roksa",
    "wof:placetype":"locality",
    "wof:population":10224
},
  "geometry": {"coordinates":[85.23625699999999,26.141932],"type":"Point"}
}