{
  "type": "Feature",
  "properties": {
    "iso:country":"IN",
    "ks:ks_name":"Patiem",
    "ks:ks_pop":312,
    "ks:ks_type":"VILLAGE",
    "name:eng_x_preferred":[
        "Patiem"
    ],
    "wof:name":"Patiem",
    "wof:placetype":"locality",
    "wof:population":312
},
  "geometry": {"coordinates":[74.21884799999999,15.24436],"type":"Point"}
}