{
  "type": "Feature",
  "properties": {
    "iso:country":"IN",
    "ks:ks_name":"Gollavaripalle",
    "ks:ks_pop":4,
    "ks:ks_type":"HABITATION",
    "name:eng_x_preferred":[
        "Gollavaripalle"
    ],
    "wof:name":"Gollavaripalle",
    "wof:placetype":"locality",
    "wof:population":4
},
  "geometry": {"coordinates":[78.904833,13.839843],"type":"Point"}
}