{
  "type": "Feature",
  "properties": {
    "gn:admin1_code":"36",
    "gn:admin2_code":"147.0",
    "gn:asciiname":"Mehri",
    "gn:country_code":"IN",
    "gn:dem":167,
    "gn:feature_class":"P",
    "gn:feature_code":"PPL",
    "gn:name":"Mehri",
    "gn:population":0,
    "gn:timezone":"Asia/Kolkata",
    "iso:country":"IN",
    "name:fra_x_preferred":[
        "Mehri"
    ],
    "wof:name":"Mehri",
    "wof:placetype":"neighbourhood"
},
  "geometry": {"coordinates":[78.59032999999999,27.2686],"type":"Point"}
}