{
  "type": "Feature",
  "properties": {
    "iso:country":"IN",
    "ks:ks_name":"Rajiva Grama",
    "ks:ks_pop":1088,
    "ks:ks_type":"HABITATION",
    "name:eng_x_preferred":[
        "Rajiva Grama"
    ],
    "wof:name":"Rajiva Grama",
    "wof:placetype":"locality",
    "wof:population":1088
},
  "geometry": {"coordinates":[75.994221,12.334435],"type":"Point"}
}