{
  "type": "Feature",
  "properties": {
    "gn:country":"IN",
    "gn:fcode":"PPL",
    "gn:population":14528,
    "iso:country":"IN",
    "name:ceb_x_preferred":[
        "Amm\u0101pettai"
    ],
    "name:eng_x_preferred":[
        "Ammapettai"
    ],
    "name:fas_x_preferred":[
        "\u0627\u0645\u0627\u067e\u062a\u0627\u06cc\u060c \u062a\u0646\u062c\u0648\u0648\u0631"
    ],
    "name:fas_x_variant":[
        "\u0627\u0645\u0627\u067e\u062a\u0627\u06cc"
    ],
    "name:ita_x_preferred":[
        "Ammapettai"
    ],
    "name:min_x_preferred":[
        "Ammapettai"
    ],
    "name:msa_x_preferred":[
        "Ammapettai"
    ],
    "name:nld_x_preferred":[
        "Ammapettai"
    ],
    "name:swe_x_preferred":[
        "Amm\u0101pettai"
    ],
    "name:tam_x_preferred":[
        "\u0b85\u0bae\u0bcd\u0bae\u0bbe\u0baa\u0bcd\u0baa\u0bc7\u0b9f\u0bcd\u0b9f\u0bc8"
    ],
    "name:und_x_variant":[
        "Ammapet"
    ],
    "qs:name":"Ammapettai",
    "qs:name_adm0":"India",
    "qs:name_adm1":"Tamil Nadu",
    "qs:photos_9r":0,
    "qs:photos_sr":0,
    "qs:placetype":"Town",
    "qs:pop_sr":"6",
    "wd:wordcount":26,
    "wof:name":"Ammapettai",
    "wof:placetype":"locality",
    "wof:population":14528
},
  "geometry": {"coordinates":[79.31836,10.79588],"type":"Point"}
}