{
  "type": "Feature",
  "properties": {
    "gn:admin1_code":"34.0",
    "gn:admin2_code":"226.0",
    "gn:asciiname":"Deogaon",
    "gn:country_code":"IN",
    "gn:dem":59,
    "gn:feature_class":"P",
    "gn:feature_code":"PPL",
    "gn:name":"Deogaon",
    "gn:population":0,
    "gn:timezone":"Asia/Kolkata",
    "iso:country":"IN",
    "name:cat_x_preferred":[
        "Deogaon"
    ],
    "name:fas_x_preferred":[
        "\u062f\u0626\u0648\u06af\u0627\u0626\u0648\u0646"
    ],
    "name:jpn_x_preferred":[
        "\u30c7\u30fc\u30aa\u30ac\u30fc\u30aa\u30f3"
    ],
    "wof:name":"Deogaon",
    "wof:placetype":"locality"
},
  "geometry": {"coordinates":[86.65664,25.08066],"type":"Point"}
}