{
  "type": "Feature",
  "properties": {
    "iso:country":"IN",
    "ks:ks_name":"Platparaq",
    "ks:ks_pop":329,
    "ks:ks_type":"HABITATION",
    "ks:ks_uagg_main":0,
    "name:eng_x_preferred":[
        "Platparaq"
    ],
    "wof:name":"Platparaq",
    "wof:placetype":"neighbourhood",
    "wof:population":329
},
  "geometry": {"coordinates":[81.275172,19.710188],"type":"Point"}
}