{
  "type": "Feature",
  "properties": {
    "iso:country":"IN",
    "ks:ks_alt_nam":"Bardaha west tola",
    "ks:ks_name":"Bardaha West Tola",
    "ks:ks_pop":1211,
    "ks:ks_type":"HABITATION",
    "name:eng_x_preferred":[
        "Bardaha West Tola"
    ],
    "wof:name":"Bardaha West Tola",
    "wof:placetype":"locality",
    "wof:population":1211
},
  "geometry": {"coordinates":[87.525052,26.347954],"type":"Point"}
}