{
  "type": "Feature",
  "properties": {
    "iso:country":"IN",
    "ks:ks_name":"Vajramuneshwara Temple",
    "ks:ks_pop":180,
    "ks:ks_type":"HABITATION",
    "name:eng_x_preferred":[
        "Vajramuneshwara Temple"
    ],
    "wof:name":"Vajramuneshwara Temple",
    "wof:placetype":"locality",
    "wof:population":180
},
  "geometry": {"coordinates":[77.525659,12.852014],"type":"Point"}
}