{
  "type": "Feature",
  "properties": {
    "iso:country":"IN",
    "ks:ks_name":"Dhoba",
    "ks:ks_pop":302,
    "ks:ks_type":"VILLAGE",
    "name:eng_x_preferred":[
        "Dhoba"
    ],
    "wof:name":"Dhoba",
    "wof:placetype":"locality",
    "wof:population":302
},
  "geometry": {"coordinates":[94.054321,27.175855],"type":"Point"}
}