{
  "type": "Feature",
  "properties": {
    "iso:country":"IN",
    "ks:ks_name":"Naduvoor",
    "ks:ks_pop":140,
    "ks:ks_type":"HABITATION",
    "name:eng_x_preferred":[
        "Naduvoor"
    ],
    "wof:name":"Naduvoor",
    "wof:placetype":"locality",
    "wof:population":140
},
  "geometry": {"coordinates":[78.885323,12.607381],"type":"Point"}
}