{
  "type": "Feature",
  "properties": {
    "iso:country":"IN",
    "ks:ks_name":"Jamuna",
    "ks:ks_pop":1055,
    "ks:ks_type":"VILLAGE",
    "name:eng_x_preferred":[
        "Jamuna"
    ],
    "wof:name":"Jamuna",
    "wof:placetype":"locality",
    "wof:population":1055
},
  "geometry": {"coordinates":[86.692463,21.777635],"type":"Point"}
}