{
  "type": "Feature",
  "properties": {
    "gn:admin1_code":"34.0",
    "gn:admin2_code":"240.0",
    "gn:asciiname":"Kodmarai",
    "gn:country_code":"IN",
    "gn:dem":76,
    "gn:feature_class":"P",
    "gn:feature_code":"PPL",
    "gn:name":"Kodmarai",
    "gn:population":0,
    "gn:timezone":"Asia/Kolkata",
    "iso:country":"IN",
    "wof:name":"Kodmarai",
    "wof:placetype":"locality"
},
  "geometry": {"coordinates":[84.79184000000002,25.1609],"type":"Point"}
}