{
  "type": "Feature",
  "properties": {
    "iso:country":"IN",
    "ks:ks_name":"Paigambarpur Tola Ramnagar",
    "ks:ks_pop":1504,
    "ks:ks_type":"VILLAGE",
    "ks:ks_uagg_main":0,
    "name:eng_x_preferred":[
        "Paigambarpur Tola Ramnagar"
    ],
    "wof:name":"Paigambarpur Tola Ramnagar",
    "wof:placetype":"neighbourhood",
    "wof:population":1504
},
  "geometry": {"coordinates":[85.23083099999999,26.355461],"type":"Point"}
}