{
  "type": "Feature",
  "properties": {
    "gn:admin1_code":"25.0",
    "gn:admin2_code":"620.0",
    "gn:asciiname":"Rajagiri",
    "gn:country_code":"IN",
    "gn:dem":40,
    "gn:feature_class":"P",
    "gn:feature_code":"PPL",
    "gn:name":"R\u0101jagiri",
    "gn:population":0,
    "gn:timezone":"Asia/Kolkata",
    "iso:country":"IN",
    "ks:ks_alt_nam":"R\u0101jagiri",
    "ks:ks_name":"Rajagiri",
    "ks:ks_pop":2678,
    "ks:ks_type":"VILLAGE",
    "ks:ks_uagg_main":0,
    "name:eng_x_preferred":[
        "Rajagiri"
    ],
    "name:eng_x_variant":[
        "R\u0101jagiri"
    ],
    "wof:name":"Rajagiri",
    "wof:placetype":"neighbourhood",
    "wof:population":2678
},
  "geometry": {"coordinates":[79.246853,10.919495],"type":"Point"}
}