{
  "type": "Feature",
  "properties": {
    "iso:country":"IN",
    "ks:ks_name":"Thamh",
    "ks:ks_pop":0,
    "ks:ks_type":"VILLAGE",
    "name:eng_x_preferred":[
        "Thamh"
    ],
    "wof:name":"Thamh",
    "wof:placetype":"locality",
    "wof:population":0
},
  "geometry": {"coordinates":[85.239718,24.921955],"type":"Point"}
}