{
  "type": "Feature",
  "properties": {
    "iso:country":"IN",
    "ks:ks_name":"Eder",
    "ks:ks_pop":153,
    "ks:ks_type":"HABITATION",
    "name:eng_x_preferred":[
        "Eder"
    ],
    "wof:name":"Eder",
    "wof:placetype":"locality",
    "wof:population":153
},
  "geometry": {"coordinates":[80.977284,19.095881],"type":"Point"}
}