{
  "type": "Feature",
  "properties": {
    "iso:country":"IN",
    "ks:ks_name":"Dhukuria",
    "ks:ks_pop":0,
    "ks:ks_type":"VILLAGE",
    "name:eng_x_preferred":[
        "Dhukuria"
    ],
    "wof:name":"Dhukuria",
    "wof:placetype":"locality",
    "wof:population":0
},
  "geometry": {"coordinates":[86.888738,22.343661],"type":"Point"}
}