{
  "type": "Feature",
  "properties": {
    "iso:country":"IN",
    "ks:ks_name":"4 SPD-A",
    "ks:ks_pop":11,
    "ks:ks_type":"VILLAGE",
    "name:eng_x_preferred":[
        "4 SPD-A"
    ],
    "wof:name":"4 SPD-A",
    "wof:placetype":"locality",
    "wof:population":11
},
  "geometry": {"coordinates":[74.272526,29.248376],"type":"Point"}
}