{
  "type": "Feature",
  "properties": {
    "iso:country":"IN",
    "ks:ks_alt_nam":"Subav kala",
    "ks:ks_name":"Subav Kala",
    "ks:ks_pop":748,
    "ks:ks_type":"HABITATION",
    "name:eng_x_preferred":[
        "Subav Kala"
    ],
    "wof:name":"Subav Kala",
    "wof:placetype":"locality",
    "wof:population":748
},
  "geometry": {"coordinates":[82.287042,24.884941],"type":"Point"}
}