{
  "type": "Feature",
  "properties": {
    "iso:country":"IN",
    "ks:ks_name":"Gadain Disao",
    "ks:ks_pop":50,
    "ks:ks_type":"HABITATION",
    "name:eng_x_preferred":[
        "Gadain Disao"
    ],
    "wof:name":"Gadain Disao",
    "wof:placetype":"locality",
    "wof:population":50
},
  "geometry": {"coordinates":[92.994182,25.307697],"type":"Point"}
}