{
  "type": "Feature",
  "properties": {
    "iso:country":"IN",
    "ks:ks_name":"Rupakheda",
    "ks:ks_pop":483,
    "ks:ks_type":"VILLAGE",
    "name:eng_x_preferred":[
        "Rupakheda"
    ],
    "wof:name":"Rupakheda",
    "wof:placetype":"locality",
    "wof:population":483
},
  "geometry": {"coordinates":[74.452809,22.938263],"type":"Point"}
}