{
  "type": "Feature",
  "properties": {
    "iso:country":"IN",
    "ks:ks_alt_nam":"Viris\u016br",
    "ks:ks_name":"Virisur",
    "ks:ks_pop":594,
    "ks:ks_type":"VILLAGE",
    "name:eng_x_preferred":[
        "Virisur"
    ],
    "name:eng_x_variant":[
        "Viris\u016br"
    ],
    "wof:name":"Virisur",
    "wof:placetype":"locality",
    "wof:population":594
},
  "geometry": {"coordinates":[78.79861,9.800948],"type":"Point"}
}