{
  "type": "Feature",
  "properties": {
    "gn:admin1_code":"39.0",
    "gn:admin2_code":"64.0",
    "gn:asciiname":"Masankhal",
    "gn:country_code":"IN",
    "gn:dem":2011,
    "gn:feature_class":"P",
    "gn:feature_code":"PPL",
    "gn:name":"Mas\u0101nkh\u0101l",
    "gn:population":0,
    "gn:timezone":"Asia/Kolkata",
    "iso:country":"IN",
    "wof:name":"Masankhal",
    "wof:placetype":"locality"
},
  "geometry": {"coordinates":[79.75334000000002,29.4487],"type":"Point"}
}