{
  "type": "Feature",
  "properties": {
    "iso:country":"IN",
    "ks:ks_name":"Kadamwasti",
    "ks:ks_pop":528,
    "ks:ks_type":"HABITATION",
    "name:eng_x_preferred":[
        "Kadamwasti"
    ],
    "wof:name":"Kadamwasti",
    "wof:placetype":"locality",
    "wof:population":528
},
  "geometry": {"coordinates":[75.642381,18.007214],"type":"Point"}
}