{
  "type": "Feature",
  "properties": {
    "iso:country":"IN",
    "ks:ks_name":"Magro Malla",
    "ks:ks_pop":80,
    "ks:ks_type":"VILLAGE",
    "name:eng_x_preferred":[
        "Magro Malla"
    ],
    "wof:name":"Magro Malla",
    "wof:placetype":"locality",
    "wof:population":80
},
  "geometry": {"coordinates":[79.070142,29.889123],"type":"Point"}
}