{
  "type": "Feature",
  "properties": {
    "iso:country":"IN",
    "ks:ks_name":"Ethenic Village",
    "ks:ks_pop":405,
    "ks:ks_type":"HABITATION",
    "name:eng_x_preferred":[
        "Ethenic Village"
    ],
    "wof:name":"Ethenic Village",
    "wof:placetype":"locality",
    "wof:population":405
},
  "geometry": {"coordinates":[93.415781,26.580416],"type":"Point"}
}