{
  "type": "Feature",
  "properties": {
    "gn:admin1_code":"36.0",
    "gn:admin2_code":"150.0",
    "gn:asciiname":"Jaju Naga",
    "gn:country_code":"IN",
    "gn:dem":197,
    "gn:feature_class":"P",
    "gn:feature_code":"PPL",
    "gn:name":"J\u0101ju N\u0101ga",
    "gn:population":0,
    "gn:timezone":"Asia/Kolkata",
    "iso:country":"IN",
    "wof:name":"Jaju Naga",
    "wof:placetype":"locality"
},
  "geometry": {"coordinates":[79.52148000000003,28.78775],"type":"Point"}
}