{
  "type": "Feature",
  "properties": {
    "iso:country":"IN",
    "ks:ks_name":"5 KNM I",
    "ks:ks_pop":28,
    "ks:ks_type":"VILLAGE",
    "name:eng_x_preferred":[
        "5 KNM I"
    ],
    "wof:name":"5 KNM I",
    "wof:placetype":"locality",
    "wof:population":28
},
  "geometry": {"coordinates":[72.741997,28.930084],"type":"Point"}
}