{
  "type": "Feature",
  "properties": {
    "gn:admin1_code":"23.0",
    "gn:admin2_code":"35.0",
    "gn:asciiname":"Pakho Chak",
    "gn:country_code":"IN",
    "gn:dem":266,
    "gn:feature_class":"P",
    "gn:feature_code":"PPL",
    "gn:name":"Pakho Chak",
    "gn:population":0,
    "gn:timezone":"Asia/Kolkata",
    "iso:country":"IN",
    "ks:ks_name":"Pakho Chak",
    "ks:ks_pop":955,
    "ks:ks_type":"VILLAGE",
    "ks:ks_uagg_main":0,
    "name:eng_x_preferred":[
        "Pakho Chak"
    ],
    "wof:name":"Pakho Chak",
    "wof:placetype":"neighbourhood",
    "wof:population":955
},
  "geometry": {"coordinates":[75.465824,32.186353],"type":"Point"}
}