{
  "type": "Feature",
  "properties": {
    "gn:admin1_code":"24.0",
    "gn:admin2_code":"124.0",
    "gn:asciiname":"Pardi",
    "gn:country_code":"IN",
    "gn:dem":147,
    "gn:feature_class":"P",
    "gn:feature_code":"PPL",
    "gn:name":"Pardi",
    "gn:population":0,
    "gn:timezone":"Asia/Kolkata",
    "iso:country":"IN",
    "name:bpy_x_preferred":[
        "\u09aa\u09be\u09b0\u09cd\u09a6\u09bf"
    ],
    "name:ceb_x_preferred":[
        "P\u0101rdi"
    ],
    "name:guj_x_preferred":[
        "\u0aaa\u0abe\u0ab0\u0aa1\u0ac0"
    ],
    "name:ita_x_preferred":[
        "Pardi"
    ],
    "name:mlg_x_preferred":[
        "Pardi"
    ],
    "name:msa_x_preferred":[
        "Pardi"
    ],
    "name:ori_x_preferred":[
        "\u0b2a\u0b3e\u0b30\u0b4d\u0b26\u0b3f"
    ],
    "name:swe_x_preferred":[
        "P\u0101rdi"
    ],
    "name:tam_x_preferred":[
        "\u0baa\u0bbe\u0bb0\u0bcd\u0b9f\u0bbf"
    ],
    "name:vie_x_preferred":[
        "Pardi"
    ],
    "name:zho_x_preferred":[
        "\u5e15\u5c14\u8fea"
    ],
    "wof:name":"Pardi",
    "wof:placetype":"locality"
},
  "geometry": {"coordinates":[73.96179000000002,23.436],"type":"Point"}
}