{
  "type": "Feature",
  "properties": {
    "iso:country":"IN",
    "ks:ks_name":"Raisima Uttar",
    "ks:ks_pop":454,
    "ks:ks_type":"VILLAGE",
    "name:eng_x_preferred":[
        "Raisima Uttar"
    ],
    "wof:name":"Raisima Uttar",
    "wof:placetype":"locality",
    "wof:population":454
},
  "geometry": {"coordinates":[87.330066,21.943043],"type":"Point"}
}