{
  "type": "Feature",
  "properties": {
    "iso:country":"IN",
    "ks:ks_name":"Purbi Turhapatti",
    "ks:ks_pop":4518,
    "ks:ks_type":"HABITATION",
    "name:eng_x_preferred":[
        "Purbi Turhapatti"
    ],
    "wof:name":"Purbi Turhapatti",
    "wof:placetype":"locality",
    "wof:population":4518
},
  "geometry": {"coordinates":[84.47232,26.853363],"type":"Point"}
}