{
  "type": "Feature",
  "properties": {
    "iso:country":"IN",
    "ks:ks_name":"Uttar Putimari",
    "ks:ks_pop":1485,
    "ks:ks_type":"VILLAGE",
    "ks:ks_uagg_main":0,
    "name:eng_x_preferred":[
        "Uttar Putimari"
    ],
    "wof:name":"Uttar Putimari",
    "wof:placetype":"neighbourhood",
    "wof:population":1485
},
  "geometry": {"coordinates":[88.800406,26.515239],"type":"Point"}
}