{
  "type": "Feature",
  "properties": {
    "iso:country":"IN",
    "ks:ks_name":"Raksa",
    "ks:ks_pop":39,
    "ks:ks_type":"VILLAGE",
    "name:eng_x_preferred":[
        "Raksa"
    ],
    "wof:name":"Raksa",
    "wof:placetype":"locality",
    "wof:population":39
},
  "geometry": {"coordinates":[78.525811,24.870344],"type":"Point"}
}