{
  "type": "Feature",
  "properties": {
    "gn:admin1_code":"19.0",
    "gn:admin2_code":"581.0",
    "gn:asciiname":"Alaganahalli",
    "gn:country_code":"IN",
    "gn:dem":845,
    "gn:feature_class":"P",
    "gn:feature_code":"PPL",
    "gn:name":"Alag\u0101nahalli",
    "gn:population":0,
    "gn:timezone":"Asia/Kolkata",
    "iso:country":"IN",
    "wof:name":"Alaganahalli",
    "wof:placetype":"locality"
},
  "geometry": {"coordinates":[78.20999999999999,13.03796],"type":"Point"}
}