{
  "type": "Feature",
  "properties": {
    "iso:country":"IN",
    "ks:ks_name":"Nakkametta",
    "ks:ks_pop":76,
    "ks:ks_type":"HABITATION",
    "name:eng_x_preferred":[
        "Nakkametta"
    ],
    "wof:name":"Nakkametta",
    "wof:placetype":"locality",
    "wof:population":76
},
  "geometry": {"coordinates":[82.479089,18.094952],"type":"Point"}
}