{
  "type": "Feature",
  "properties": {
    "iso:country":"IN",
    "ks:ks_alt_nam":"5 LPM-B",
    "ks:ks_name":"5 Lpm-b",
    "ks:ks_pop":243,
    "ks:ks_type":"HABITATION",
    "name:eng_x_preferred":[
        "5 Lpm-b"
    ],
    "wof:name":"5 Lpm-b",
    "wof:placetype":"locality",
    "wof:population":243
},
  "geometry": {"coordinates":[73.276864,29.387829],"type":"Point"}
}