{
  "type": "Feature",
  "properties": {
    "iso:country":"IN",
    "ks:ks_name":"Naganeshiyan Dhoondha",
    "ks:ks_pop":1649,
    "ks:ks_type":"HABITATION",
    "name:eng_x_preferred":[
        "Naganeshiyan Dhoondha"
    ],
    "wof:name":"Naganeshiyan Dhoondha",
    "wof:placetype":"locality",
    "wof:population":1649
},
  "geometry": {"coordinates":[71.536131,25.819631],"type":"Point"}
}