{
  "type": "Feature",
  "properties": {
    "iso:country":"IN",
    "ks:ks_name":"Gaujiyana",
    "ks:ks_pop":274,
    "ks:ks_type":"VILLAGE",
    "name:eng_x_preferred":[
        "Gaujiyana"
    ],
    "wof:name":"Gaujiyana",
    "wof:placetype":"locality",
    "wof:population":274
},
  "geometry": {"coordinates":[78.617876,30.409061],"type":"Point"}
}