{
  "type": "Feature",
  "properties": {
    "iso:country":"IN",
    "ks:ks_name":"Ekal",
    "ks:ks_pop":229,
    "ks:ks_type":"VILLAGE",
    "name:eng_x_preferred":[
        "Ekal"
    ],
    "wof:name":"Ekal",
    "wof:placetype":"locality",
    "wof:population":229
},
  "geometry": {"coordinates":[71.034819,24.856947],"type":"Point"}
}