{
  "type": "Feature",
  "properties": {
    "iso:country":"IN",
    "ks:ks_alt_nam":"STATION COLONY",
    "ks:ks_name":"Station Colony",
    "ks:ks_pop":618,
    "ks:ks_type":"HABITATION",
    "ks:ks_uagg_main":0,
    "name:eng_x_preferred":[
        "Station Colony"
    ],
    "wof:name":"Station Colony",
    "wof:placetype":"neighbourhood",
    "wof:population":618
},
  "geometry": {"coordinates":[88.58752800000001,26.596669],"type":"Point"}
}