{
  "type": "Feature",
  "properties": {
    "iso:country":"IN",
    "ks:ks_name":"Ganga Putri Purwa",
    "ks:ks_pop":140,
    "ks:ks_type":"HABITATION",
    "name:eng_x_preferred":[
        "Ganga Putri Purwa"
    ],
    "wof:name":"Ganga Putri Purwa",
    "wof:placetype":"locality",
    "wof:population":140
},
  "geometry": {"coordinates":[82.04235199999999,26.947013],"type":"Point"}
}