{
  "type": "Feature",
  "properties": {
    "iso:country":"IN",
    "ks:ks_name":"Kherdanda",
    "ks:ks_pop":327,
    "ks:ks_type":"VILLAGE",
    "ks:ks_uagg_main":0,
    "name:eng_x_preferred":[
        "Kherdanda"
    ],
    "wof:name":"Kherdanda",
    "wof:placetype":"neighbourhood",
    "wof:population":327
},
  "geometry": {"coordinates":[90.565814,26.644353],"type":"Point"}
}