{
  "type": "Feature",
  "properties": {
    "gn:admin1_code":"2.0",
    "gn:admin2_code":"543.0",
    "gn:asciiname":"Neradavalasa",
    "gn:country_code":"IN",
    "gn:dem":788,
    "gn:feature_class":"P",
    "gn:feature_code":"PPL",
    "gn:name":"Neradavalasa",
    "gn:population":0,
    "gn:timezone":"Asia/Kolkata",
    "iso:country":"IN",
    "ks:ks_name":"Neredivalasa",
    "ks:ks_pop":93,
    "ks:ks_type":"HABITATION",
    "name:eng_x_preferred":[
        "Neredivalasa"
    ],
    "name:eng_x_variant":[
        "Neradavalasa"
    ],
    "wof:name":"Neredivalasa",
    "wof:placetype":"locality",
    "wof:population":93
},
  "geometry": {"coordinates":[83.17246900000001,18.367899],"type":"Point"}
}