{
  "type": "Feature",
  "properties": {
    "iso:country":"IN",
    "ks:ks_name":"Kudada",
    "ks:ks_pop":167,
    "ks:ks_type":"HABITATION",
    "name:eng_x_preferred":[
        "Kudada"
    ],
    "wof:name":"Kudada",
    "wof:placetype":"locality",
    "wof:population":167
},
  "geometry": {"coordinates":[85.509371,22.819129],"type":"Point"}
}