{
  "type": "Feature",
  "properties": {
    "iso:country":"IN",
    "ks:ks_name":"Gollarahatti",
    "ks:ks_pop":74,
    "ks:ks_type":"HABITATION",
    "name:eng_x_preferred":[
        "Gollarahatti"
    ],
    "wof:name":"Gollarahatti",
    "wof:placetype":"locality",
    "wof:population":74
},
  "geometry": {"coordinates":[77.158868,13.711211],"type":"Point"}
}