{
  "type": "Feature",
  "properties": {
    "iso:country":"IN",
    "ks:ks_name":"Kuppanamakki",
    "ks:ks_pop":22,
    "ks:ks_type":"HABITATION",
    "name:eng_x_preferred":[
        "Kuppanamakki"
    ],
    "wof:name":"Kuppanamakki",
    "wof:placetype":"locality",
    "wof:population":22
},
  "geometry": {"coordinates":[75.203929,13.500749],"type":"Point"}
}