{
  "type": "Feature",
  "properties": {
    "iso:country":"IN",
    "ks:ks_name":"Ennemajalu",
    "ks:ks_pop":205,
    "ks:ks_type":"HABITATION",
    "name:eng_x_preferred":[
        "Ennemajalu"
    ],
    "wof:name":"Ennemajalu",
    "wof:placetype":"locality",
    "wof:population":205
},
  "geometry": {"coordinates":[75.528713,12.683059],"type":"Point"}
}