{
  "type": "Feature",
  "properties": {
    "iso:country":"IN",
    "ks:ks_name":"Vettimalapalli",
    "ks:ks_pop":295,
    "ks:ks_type":"HABITATION",
    "ks:ks_uagg_main":0,
    "name:eng_x_preferred":[
        "Vettimalapalli"
    ],
    "wof:name":"Vettimalapalli",
    "wof:placetype":"neighbourhood",
    "wof:population":295
},
  "geometry": {"coordinates":[80.593402,15.904939],"type":"Point"}
}