{
  "type": "Feature",
  "properties": {
    "iso:country":"IN",
    "ks:ks_name":"River Block No. 7",
    "ks:ks_pop":30,
    "ks:ks_type":"HABITATION",
    "name:eng_x_preferred":[
        "River Block No. 7"
    ],
    "wof:name":"River Block No. 7",
    "wof:placetype":"locality",
    "wof:population":30
},
  "geometry": {"coordinates":[90.113275,26.008177],"type":"Point"}
}