{
  "type": "Feature",
  "properties": {
    "gn:admin1_code":"11.0",
    "gn:admin2_code":"27.0",
    "gn:asciiname":"Lot",
    "gn:country_code":"IN",
    "gn:dem":2037,
    "gn:feature_class":"P",
    "gn:feature_code":"PPL",
    "gn:name":"Lot",
    "gn:population":0,
    "gn:timezone":"Asia/Kolkata",
    "iso:country":"IN",
    "wof:name":"Lot",
    "wof:placetype":"locality"
},
  "geometry": {"coordinates":[77.11799999999999,31.56384000000001],"type":"Point"}
}