{
  "type": "Feature",
  "properties": {
    "iso:country":"IN",
    "ks:ks_alt_nam":"Dyodi urf Pokhrara",
    "ks:ks_name":"Dyodi Urf Pokhrara",
    "ks:ks_pop":30,
    "ks:ks_type":"HABITATION",
    "name:eng_x_preferred":[
        "Dyodi Urf Pokhrara"
    ],
    "wof:name":"Dyodi Urf Pokhrara",
    "wof:placetype":"locality",
    "wof:population":30
},
  "geometry": {"coordinates":[78.71163,29.795744],"type":"Point"}
}