{
  "type": "Feature",
  "properties": {
    "gn:admin1_code":"35",
    "gn:admin2_code":"425.0",
    "gn:asciiname":"Narsinghgarh",
    "gn:country_code":"IN",
    "gn:dem":320,
    "gn:feature_class":"P",
    "gn:feature_code":"PPL",
    "gn:name":"Narsinghgarh",
    "gn:population":0,
    "gn:timezone":"Asia/Kolkata",
    "iso:country":"IN",
    "ks:ks_name":"Narsinghgarh",
    "ks:ks_pop":2734,
    "ks:ks_type":"VILLAGE",
    "ks:ks_uagg_main":0,
    "name:ceb_x_preferred":[
        "Narsinghgarh"
    ],
    "name:deu_x_preferred":[
        "Narsinghgarh"
    ],
    "name:eng_x_preferred":[
        "Narsinghgarh"
    ],
    "name:swe_x_preferred":[
        "Narsinghgarh"
    ],
    "wof:name":"Narsinghgarh",
    "wof:placetype":"locality",
    "wof:population":2734
},
  "geometry": {"coordinates":[79.58924399999999,24.893606],"type":"Point"}
}