{
  "type": "Feature",
  "properties": {
    "gn:admin1_code":"34.0",
    "gn:admin2_code":"220",
    "gn:asciiname":"Fatehpur Shahbaz",
    "gn:country_code":"IN",
    "gn:dem":55,
    "gn:feature_class":"P",
    "gn:feature_code":"PPL",
    "gn:name":"Fatehpur Sh\u0101hb\u0101z",
    "gn:population":0,
    "gn:timezone":"Asia/Kolkata",
    "iso:country":"IN",
    "wof:name":"Fatehpur Shahbaz",
    "wof:placetype":"locality"
},
  "geometry": {"coordinates":[85.34366999999997,25.56977],"type":"Point"}
}