{
  "type": "Feature",
  "properties": {
    "iso:country":"IN",
    "ks:ks_name":"Mavadi",
    "ks:ks_pop":640,
    "ks:ks_type":"HABITATION",
    "name:eng_x_preferred":[
        "Mavadi"
    ],
    "wof:name":"Mavadi",
    "wof:placetype":"locality",
    "wof:population":640
},
  "geometry": {"coordinates":[75.767201,11.884937],"type":"Point"}
}