{
  "type": "Feature",
  "properties": {
    "iso:country":"IN",
    "ks:ks_name":"Chak Katokhar Khas",
    "ks:ks_pop":307,
    "ks:ks_type":"HABITATION",
    "name:eng_x_preferred":[
        "Chak Katokhar Khas"
    ],
    "wof:name":"Chak Katokhar Khas",
    "wof:placetype":"locality",
    "wof:population":307
},
  "geometry": {"coordinates":[82.827432,26.501112],"type":"Point"}
}