{
  "type": "Feature",
  "properties": {
    "gn:admin1_code":"36.0",
    "gn:admin2_code":"142.0",
    "gn:asciiname":"Bachchikhera",
    "gn:country_code":"IN",
    "gn:dem":189,
    "gn:feature_class":"P",
    "gn:feature_code":"PPL",
    "gn:name":"Bachch\u012bkhera",
    "gn:population":0,
    "gn:timezone":"Asia/Kolkata",
    "iso:country":"IN",
    "ks:ks_alt_nam":"Bachch\u012bkhera",
    "ks:ks_name":"Bachchikhera",
    "ks:ks_type":"VILLAGE",
    "name:eng_x_preferred":[
        "Bachchikhera"
    ],
    "name:eng_x_variant":[
        "Bachch\u012bkhera"
    ],
    "wof:name":"Bachchikhera",
    "wof:placetype":"locality"
},
  "geometry": {"coordinates":[78.258629,28.389155],"type":"Point"}
}