{
  "type": "Feature",
  "properties": {
    "iso:country":"IN",
    "ks:ks_alt_nam":"BASINAIK THANDA",
    "ks:ks_name":"Basinaik Thanda",
    "ks:ks_pop":717,
    "ks:ks_type":"HABITATION",
    "name:eng_x_preferred":[
        "Basinaik Thanda"
    ],
    "wof:name":"Basinaik Thanda",
    "wof:placetype":"locality",
    "wof:population":717
},
  "geometry": {"coordinates":[78.843881,18.57237],"type":"Point"}
}