{
  "type": "Feature",
  "properties": {
    "gn:admin1_code":"36.0",
    "gn:admin2_code":"171.0",
    "gn:asciiname":"Kolhuwa Muafi",
    "gn:country_code":"IN",
    "gn:dem":186,
    "gn:feature_class":"P",
    "gn:feature_code":"PPL",
    "gn:name":"Kolhuwa Mu\u0101fi",
    "gn:population":0,
    "gn:timezone":"Asia/Kolkata",
    "iso:country":"IN",
    "ks:ks_name":"Kolhua Mafi",
    "ks:ks_pop":250,
    "ks:ks_type":"VILLAGE",
    "name:eng_x_preferred":[
        "Kolhua Mafi"
    ],
    "name:eng_x_variant":[
        "Kolhuwa Muafi"
    ],
    "wof:name":"Kolhua Mafi",
    "wof:placetype":"locality",
    "wof:population":250
},
  "geometry": {"coordinates":[80.72717,25.076895],"type":"Point"}
}