{
  "type": "Feature",
  "properties": {
    "gn:admin1_code":"19.0",
    "gn:admin2_code":"574.0",
    "gn:asciiname":"Nidagarvalli",
    "gn:country_code":"IN",
    "gn:dem":951,
    "gn:feature_class":"P",
    "gn:feature_code":"PPL",
    "gn:name":"Nidagarvalli",
    "gn:population":0,
    "gn:timezone":"Asia/Kolkata",
    "iso:country":"IN",
    "wof:name":"Nidagarvalli",
    "wof:placetype":"locality"
},
  "geometry": {"coordinates":[75.93599,12.88072],"type":"Point"}
}