{
  "type": "Feature",
  "properties": {
    "iso:country":"IN",
    "ks:ks_name":"Dudhnai",
    "ks:ks_pop":2225,
    "ks:ks_type":"VILLAGE",
    "ks:ks_uagg_main":0,
    "name:eng_x_preferred":[
        "Dudhnai"
    ],
    "wof:name":"Dudhnai",
    "wof:placetype":"locality",
    "wof:population":2225
},
  "geometry": {"coordinates":[88.459746,22.344433],"type":"Point"}
}