{
  "type": "Feature",
  "properties": {
    "gn:admin1_code":"11",
    "gn:admin2_code":"23.0",
    "gn:asciiname":"Lamhaota",
    "gn:country_code":"IN",
    "gn:dem":2183,
    "gn:feature_class":"P",
    "gn:feature_code":"PPL",
    "gn:name":"Lamh\u0101ota",
    "gn:population":0,
    "gn:timezone":"Asia/Kolkata",
    "iso:country":"IN",
    "wof:name":"Lamhaota",
    "wof:placetype":"locality"
},
  "geometry": {"coordinates":[76.09567,32.79362],"type":"Point"}
}