{
  "type": "Feature",
  "properties": {
    "iso:country":"IN",
    "ks:ks_name":"Ajaguni",
    "ks:ks_pop":45,
    "ks:ks_type":"HABITATION",
    "name:eng_x_preferred":[
        "Ajaguni"
    ],
    "wof:name":"Ajaguni",
    "wof:placetype":"locality",
    "wof:population":45
},
  "geometry": {"coordinates":[74.881384,14.522041],"type":"Point"}
}