{
  "type": "Feature",
  "properties": {
    "gn:admin1_code":"37",
    "gn:admin2_code":"405.0",
    "gn:asciiname":"Kekrabhat",
    "gn:country_code":"IN",
    "gn:dem":243,
    "gn:feature_class":"P",
    "gn:feature_code":"PPL",
    "gn:name":"Kekrabh\u0101t",
    "gn:population":0,
    "gn:timezone":"Asia/Kolkata",
    "iso:country":"IN",
    "wof:name":"Kekrabhat",
    "wof:placetype":"locality"
},
  "geometry": {"coordinates":[82.86151,21.90084],"type":"Point"}
}