{
  "type": "Feature",
  "properties": {
    "iso:country":"IN",
    "ks:ks_name":"Taribagil",
    "ks:ks_pop":13,
    "ks:ks_type":"HABITATION",
    "name:eng_x_preferred":[
        "Taribagil"
    ],
    "wof:name":"Taribagil",
    "wof:placetype":"locality",
    "wof:population":13
},
  "geometry": {"coordinates":[74.81171999999999,14.234425],"type":"Point"}
}