{
  "type": "Feature",
  "properties": {
    "iso:country":"IN",
    "ks:ks_name":"Bhathisarai",
    "ks:ks_pop":568,
    "ks:ks_type":"VILLAGE",
    "name:eng_x_preferred":[
        "Bhathisarai"
    ],
    "wof:name":"Bhathisarai",
    "wof:placetype":"locality",
    "wof:population":568
},
  "geometry": {"coordinates":[82.097887,23.133744],"type":"Point"}
}