{
  "type": "Feature",
  "properties": {
    "gn:admin1_code":"35",
    "gn:admin2_code":"456.0",
    "gn:asciiname":"Raigarh",
    "gn:country_code":"IN",
    "gn:dem":806,
    "gn:feature_class":"P",
    "gn:feature_code":"PPL",
    "gn:name":"R\u0101igarh",
    "gn:population":0,
    "gn:timezone":"Asia/Kolkata",
    "iso:country":"IN",
    "name:ara_x_preferred":[
        "\u0631\u0627\u064a\u062c\u0627\u0631\u0647"
    ],
    "name:ben_x_preferred":[
        "\u09b0\u09be\u09af\u09bc\u0997\u09a1\u09bc"
    ],
    "name:bih_x_preferred":[
        "\u0930\u093e\u092f\u0917\u0922\u093c"
    ],
    "name:bpy_x_preferred":[
        "\u09b0\u09be\u09af\u09bc\u0997\u09a1\u09bc"
    ],
    "name:cat_x_preferred":[
        "Raigarh"
    ],
    "name:ceb_x_preferred":[
        "Raigarh"
    ],
    "name:deu_x_preferred":[
        "Raigarh"
    ],
    "name:fra_x_preferred":[
        "Raig\u00e2rh"
    ],
    "name:guj_x_preferred":[
        "\u0ab0\u0abe\u0aaf\u0a97\u0aa2"
    ],
    "name:hin_x_preferred":[
        "\u0930\u093e\u092f\u0917\u0922\u093c"
    ],
    "name:ita_x_preferred":[
        "Raigarh"
    ],
    "name:mar_x_preferred":[
        "\u0930\u093e\u092f\u0917\u0922"
    ],
    "name:mlg_x_preferred":[
        "Raigarh"
    ],
    "name:msa_x_preferred":[
        "Raigarh"
    ],
    "name:ori_x_preferred":[
        "\u0b30\u0b3e\u0b5f\u0b17\u0b22"
    ],
    "name:pam_x_preferred":[
        "Raigarh"
    ],
    "name:pol_x_preferred":[
        "Rajgarh"
    ],
    "name:rus_x_preferred":[
        "\u0420\u0430\u0439\u0433\u0430\u0440\u0445"
    ],
    "name:san_x_preferred":[
        "\u0930\u093e\u092f\u0917\u0922"
    ],
    "name:spa_x_preferred":[
        "Raigarh"
    ],
    "name:swe_x_preferred":[
        "Raigarh"
    ],
    "name:tgl_x_preferred":[
        "Raigarh"
    ],
    "name:urd_x_preferred":[
        "\u0631\u0627\u0626\u06d2 \u06af\u0691\u06be"
    ],
    "name:vie_x_preferred":[
        "Raigarh"
    ],
    "name:war_x_preferred":[
        "Raigarh"
    ],
    "name:zho_x_preferred":[
        "\u8d56\u52a0\u5c14"
    ],
    "wof:name":"Raigarh",
    "wof:placetype":"locality"
},
  "geometry": {"coordinates":[79.24767,22.46738],"type":"Point"}
}