{
  "type": "Feature",
  "properties": {
    "iso:country":"IN",
    "ks:ks_name":"Sanegala",
    "ks:ks_pop":200,
    "ks:ks_type":"VILLAGE",
    "name:eng_x_preferred":[
        "Sanegala"
    ],
    "wof:name":"Sanegala",
    "wof:placetype":"locality",
    "wof:population":200
},
  "geometry": {"coordinates":[76.87038200000001,11.854568],"type":"Point"}
}