{
  "type": "Feature",
  "properties": {
    "iso:country":"IN",
    "ks:ks_name":"Patipura",
    "ks:ks_pop":111,
    "ks:ks_type":"VILLAGE",
    "name:eng_x_preferred":[
        "Patipura"
    ],
    "wof:name":"Patipura",
    "wof:placetype":"locality",
    "wof:population":111
},
  "geometry": {"coordinates":[76.838877,26.208352],"type":"Point"}
}