{
  "type": "Feature",
  "properties": {
    "gn:admin1_code":"19.0",
    "gn:admin2_code":"560.0",
    "gn:asciiname":"Jainapur",
    "gn:country_code":"IN",
    "gn:dem":615,
    "gn:feature_class":"P",
    "gn:feature_code":"PPL",
    "gn:name":"Jainapur",
    "gn:population":0,
    "gn:timezone":"Asia/Kolkata",
    "iso:country":"IN",
    "name:urd_x_preferred":[
        "\u062c\u06cc\u0646\u067e\u0631"
    ],
    "wof:name":"Jainapur",
    "wof:placetype":"locality"
},
  "geometry": {"coordinates":[76.25735999999998,15.49066],"type":"Point"}
}