{
  "type": "Feature",
  "properties": {
    "iso:country":"IN",
    "ks:ks_name":"Abbur",
    "ks:ks_pop":53,
    "ks:ks_type":"HABITATION",
    "name:eng_x_preferred":[
        "Abbur"
    ],
    "wof:name":"Abbur",
    "wof:placetype":"locality",
    "wof:population":53
},
  "geometry": {"coordinates":[75.957222,12.243333],"type":"Point"}
}