{
  "type": "Feature",
  "properties": {
    "iso:country":"IN",
    "ks:ks_name":"Bilaput",
    "ks:ks_pop":218,
    "ks:ks_type":"VILLAGE",
    "name:eng_x_preferred":[
        "Bilaput"
    ],
    "wof:name":"Bilaput",
    "wof:placetype":"locality",
    "wof:population":218
},
  "geometry": {"coordinates":[82.74605200000001,18.486766],"type":"Point"}
}