{
  "type": "Feature",
  "properties": {
    "iso:country":"IN",
    "ks:ks_name":"Baishy Toli",
    "ks:ks_pop":980,
    "ks:ks_type":"HABITATION",
    "ks:ks_uagg_main":0,
    "name:eng_x_preferred":[
        "Baishy Toli"
    ],
    "wof:name":"Baishy Toli",
    "wof:placetype":"locality",
    "wof:population":980
},
  "geometry": {"coordinates":[84.71853900000001,25.831195],"type":"Point"}
}