{
  "type": "Feature",
  "properties": {
    "gn:admin1_code":"36",
    "gn:admin2_code":"191.0",
    "gn:asciiname":"Sunsara",
    "gn:country_code":"IN",
    "gn:dem":84,
    "gn:feature_class":"P",
    "gn:feature_code":"PPL",
    "gn:name":"Suns\u0101ra",
    "gn:population":0,
    "gn:timezone":"Asia/Kolkata",
    "iso:country":"IN",
    "ks:ks_name":"Sonsara",
    "ks:ks_pop":668,
    "ks:ks_type":"VILLAGE",
    "ks:ks_uagg_main":0,
    "name:eng_x_preferred":[
        "Sonsara"
    ],
    "wof:name":"Sonsara",
    "wof:placetype":"neighbourhood",
    "wof:population":668
},
  "geometry": {"coordinates":[83.081005,26.246265],"type":"Point"}
}