{
  "type": "Feature",
  "properties": {
    "gn:admin1_code":"9",
    "gn:admin2_code":"485.0",
    "gn:asciiname":"Raipura",
    "gn:country_code":"IN",
    "gn:dem":263,
    "gn:feature_class":"P",
    "gn:feature_code":"PPL",
    "gn:name":"Raipura",
    "gn:population":0,
    "gn:timezone":"Asia/Kolkata",
    "iso:country":"IN",
    "ks:ks_alt_nam":"R\u0101mpura",
    "ks:ks_name":"Rampura",
    "ks:ks_pop":616,
    "ks:ks_type":"VILLAGE",
    "name:eng_x_preferred":[
        "Rampura"
    ],
    "name:eng_x_variant":[
        "Raipura",
        "R\u0101mpura"
    ],
    "name:msa_x_preferred":[
        "Raipura"
    ],
    "wof:name":"Rampura",
    "wof:placetype":"locality",
    "wof:population":616
},
  "geometry": {"coordinates":[74.26644400000001,23.095333],"type":"Point"}
}