{
  "type": "Feature",
  "properties": {
    "iso:country":"IN",
    "ks:ks_name":"Utterpurwa",
    "ks:ks_pop":124,
    "ks:ks_type":"HABITATION",
    "name:eng_x_preferred":[
        "Utterpurwa"
    ],
    "wof:name":"Utterpurwa",
    "wof:placetype":"locality",
    "wof:population":124
},
  "geometry": {"coordinates":[80.219283,27.701701],"type":"Point"}
}