{
  "type": "Feature",
  "properties": {
    "iso:country":"IN",
    "ks:ks_name":"Narimogru",
    "ks:ks_pop":3089,
    "ks:ks_type":"VILLAGE",
    "name:eng_x_preferred":[
        "Narimogru"
    ],
    "wof:name":"Narimogru",
    "wof:placetype":"locality",
    "wof:population":3089
},
  "geometry": {"coordinates":[75.234118,12.763179],"type":"Point"}
}