{
  "type": "Feature",
  "properties": {
    "iso:country":"IN",
    "ks:ks_name":"Panwa",
    "ks:ks_pop":1595,
    "ks:ks_type":"VILLAGE",
    "name:eng_x_preferred":[
        "Panwa"
    ],
    "wof:name":"Panwa",
    "wof:placetype":"locality",
    "wof:population":1595
},
  "geometry": {"coordinates":[75.468529,22.138898],"type":"Point"}
}