{
  "type": "Feature",
  "properties": {
    "iso:country":"IN",
    "ks:ks_alt_nam":"Kalagamangalam ADC",
    "ks:ks_name":"Kalagamangalam Adc",
    "ks:ks_pop":250,
    "ks:ks_type":"HABITATION",
    "name:eng_x_preferred":[
        "Kalagamangalam Adc"
    ],
    "wof:name":"Kalagamangalam Adc",
    "wof:placetype":"locality",
    "wof:population":250
},
  "geometry": {"coordinates":[79.205012,10.117827],"type":"Point"}
}