{
  "type": "Feature",
  "properties": {
    "iso:country":"IN",
    "ks:ks_name":"Thikariya",
    "ks:ks_pop":687,
    "ks:ks_type":"HABITATION",
    "name:eng_x_preferred":[
        "Thikariya"
    ],
    "wof:name":"Thikariya",
    "wof:placetype":"locality",
    "wof:population":687
},
  "geometry": {"coordinates":[74.602214,23.583442],"type":"Point"}
}