{
  "type": "Feature",
  "properties": {
    "gn:admin1_code":"34.0",
    "gn:admin2_code":"217.0",
    "gn:asciiname":"Rajapur",
    "gn:country_code":"IN",
    "gn:dem":76,
    "gn:feature_class":"P",
    "gn:feature_code":"PPL",
    "gn:name":"R\u0101j\u0101pur",
    "gn:population":0,
    "gn:timezone":"Asia/Kolkata",
    "iso:country":"IN",
    "ks:ks_alt_nam":"R\u0101j\u0101pur",
    "ks:ks_name":"Rajapur",
    "ks:ks_pop":1699,
    "ks:ks_type":"VILLAGE",
    "name:ceb_x_preferred":[
        "Rajapur"
    ],
    "name:eng_x_preferred":[
        "Rajapur"
    ],
    "name:eng_x_variant":[
        "R\u0101j\u0101pur"
    ],
    "name:fra_x_preferred":[
        "Rajapur"
    ],
    "name:ita_x_preferred":[
        "Rajapur"
    ],
    "name:pol_x_preferred":[
        "Rajapur"
    ],
    "name:swe_x_preferred":[
        "Rajapur"
    ],
    "wof:name":"Rajapur",
    "wof:placetype":"locality",
    "wof:population":1699
},
  "geometry": {"coordinates":[84.164067,26.500343],"type":"Point"}
}