{
  "type": "Feature",
  "properties": {
    "iso:country":"IN",
    "ks:ks_name":"Maidaswala",
    "ks:ks_pop":1976,
    "ks:ks_type":"VILLAGE",
    "name:eng_x_preferred":[
        "Maidaswala"
    ],
    "wof:name":"Maidaswala",
    "wof:placetype":"locality",
    "wof:population":1976
},
  "geometry": {"coordinates":[78.501143,29.559046],"type":"Point"}
}