{
  "type": "Feature",
  "properties": {
    "iso:country":"IN",
    "ks:ks_name":"Vadakudi",
    "ks:ks_pop":540,
    "ks:ks_type":"HABITATION",
    "name:eng_x_preferred":[
        "Vadakudi"
    ],
    "wof:name":"Vadakudi",
    "wof:placetype":"locality",
    "wof:population":540
},
  "geometry": {"coordinates":[79.706098,11.073276],"type":"Point"}
}