{
  "type": "Feature",
  "properties": {
    "gn:admin1_code":"23",
    "gn:admin2_code":"38.0",
    "gn:asciiname":"Nangal Jamal",
    "gn:country_code":"IN",
    "gn:dem":252,
    "gn:feature_class":"P",
    "gn:feature_code":"PPL",
    "gn:name":"Nangal Jam\u0101l",
    "gn:population":0,
    "gn:timezone":"Asia/Kolkata",
    "iso:country":"IN",
    "ks:ks_name":"Nangal Jamal",
    "ks:ks_pop":422,
    "ks:ks_type":"VILLAGE",
    "name:eng_x_preferred":[
        "Nangal Jamal"
    ],
    "wof:name":"Nangal Jamal",
    "wof:placetype":"locality",
    "wof:population":422
},
  "geometry": {"coordinates":[75.70253099999999,31.606739],"type":"Point"}
}