{
  "type": "Feature",
  "properties": {
    "gn:admin1_code":"24.0",
    "gn:admin2_code":"102",
    "gn:asciiname":"Mangasar",
    "gn:country_code":"IN",
    "gn:dem":281,
    "gn:feature_class":"P",
    "gn:feature_code":"PPL",
    "gn:name":"M\u0101ng\u0101sar",
    "gn:population":0,
    "gn:timezone":"Asia/Kolkata",
    "iso:country":"IN",
    "name:und_x_variant":[
        "M\u0101ng\u0101sar",
        "Mang\u0101sar"
    ],
    "wof:name":"Mangasar",
    "wof:placetype":"locality"
},
  "geometry": {"coordinates":[74.51934,28.27866],"type":"Point"}
}