{
  "type": "Feature",
  "properties": {
    "iso:country":"IN",
    "ks:ks_alt_nam":"Mahu\u0101ri",
    "ks:ks_name":"Mahuari",
    "ks:ks_pop":663,
    "ks:ks_type":"VILLAGE",
    "ks:ks_uagg_main":0,
    "name:eng_x_preferred":[
        "Mahuari"
    ],
    "name:eng_x_variant":[
        "Mahu\u0101ri"
    ],
    "wof:name":"Mahuari",
    "wof:placetype":"neighbourhood",
    "wof:population":663
},
  "geometry": {"coordinates":[84.881232,23.428972],"type":"Point"}
}