{
  "type": "Feature",
  "properties": {
    "gn:admin1_code":"16.0",
    "gn:admin2_code":"499.0",
    "gn:asciiname":"Bornad",
    "gn:country_code":"IN",
    "gn:dem":225,
    "gn:feature_class":"P",
    "gn:feature_code":"PPL",
    "gn:name":"Born\u0101d",
    "gn:population":0,
    "gn:timezone":"Asia/Kolkata",
    "iso:country":"IN",
    "wof:name":"Bornad",
    "wof:placetype":"locality"
},
  "geometry": {"coordinates":[75.43589,20.84604],"type":"Point"}
}