{
  "type": "Feature",
  "properties": {
    "gn:admin1_code":"17.0",
    "gn:admin2_code":"274.0",
    "gn:asciiname":"Bukpi",
    "gn:country_code":"IN",
    "gn:dem":1064,
    "gn:feature_class":"P",
    "gn:feature_code":"PPL",
    "gn:name":"Bukpi",
    "gn:population":0,
    "gn:timezone":"Asia/Kolkata",
    "iso:country":"IN",
    "wof:name":"Bukpi",
    "wof:placetype":"locality"
},
  "geometry": {"coordinates":[93.24198,24.21277000000001],"type":"Point"}
}