{
  "type": "Feature",
  "properties": {
    "gn:admin1_code":"34",
    "gn:admin2_code":"207.0",
    "gn:asciiname":"Pandaul",
    "gn:country_code":"IN",
    "gn:dem":62,
    "gn:feature_class":"P",
    "gn:feature_code":"PPL",
    "gn:name":"Pandaul",
    "gn:population":0,
    "gn:timezone":"Asia/Kolkata",
    "iso:country":"IN",
    "name:ceb_x_preferred":[
        "Pandaul"
    ],
    "name:spa_x_preferred":[
        "Pandaul"
    ],
    "name:swe_x_preferred":[
        "Pandaul"
    ],
    "wof:name":"Pandaul",
    "wof:placetype":"locality"
},
  "geometry": {"coordinates":[86.07469,26.25171],"type":"Point"}
}