{
  "type": "Feature",
  "properties": {
    "gn:admin1_code":"35",
    "gn:admin2_code":"443.0",
    "gn:asciiname":"Fatanpur",
    "gn:country_code":"IN",
    "gn:dem":405,
    "gn:feature_class":"P",
    "gn:feature_code":"PPL",
    "gn:name":"Fatanpur",
    "gn:population":0,
    "gn:timezone":"Asia/Kolkata",
    "iso:country":"IN",
    "wof:name":"Fatanpur",
    "wof:placetype":"locality"
},
  "geometry": {"coordinates":[77.96308000000001,24.05085],"type":"Point"}
}