{
  "type": "Feature",
  "properties": {
    "gn:admin1_code":"11",
    "gn:admin2_code":"31.0",
    "gn:asciiname":"Bhagal",
    "gn:country_code":"IN",
    "gn:dem":844,
    "gn:feature_class":"P",
    "gn:feature_code":"PPL",
    "gn:name":"Bh\u0101gal",
    "gn:population":0,
    "gn:timezone":"Asia/Kolkata",
    "iso:country":"IN",
    "name:guj_x_preferred":[
        "\u0aad\u0abe\u0a97\u0ab3"
    ],
    "wof:name":"Bhagal",
    "wof:placetype":"locality"
},
  "geometry": {"coordinates":[76.91849000000001,30.93387],"type":"Point"}
}