{
  "type": "Feature",
  "properties": {
    "iso:country":"IN",
    "ks:ks_name":"Tanda Falia",
    "ks:ks_pop":1046,
    "ks:ks_type":"HABITATION",
    "name:eng_x_preferred":[
        "Tanda Falia"
    ],
    "wof:name":"Tanda Falia",
    "wof:placetype":"locality",
    "wof:population":1046
},
  "geometry": {"coordinates":[73.919583,22.724167],"type":"Point"}
}