{
  "type": "Feature",
  "properties": {
    "gn:admin1_code":"37.0",
    "gn:asciiname":"Burugudem",
    "gn:country_code":"IN",
    "gn:dem":99,
    "gn:feature_class":"P",
    "gn:feature_code":"PPL",
    "gn:name":"B\u016brugudem",
    "gn:population":0,
    "gn:timezone":"Asia/Kolkata",
    "iso:country":"IN",
    "ks:ks_alt_nam":"B\u016brugudem",
    "ks:ks_name":"Burugudem",
    "ks:ks_type":"VILLAGE",
    "name:eng_x_preferred":[
        "Burugudem"
    ],
    "name:eng_x_variant":[
        "B\u016brugudem"
    ],
    "wof:name":"Burugudem",
    "wof:placetype":"locality"
},
  "geometry": {"coordinates":[80.298575,18.684866],"type":"Point"}
}