{
  "type": "Feature",
  "properties": {
    "iso:country":"IN",
    "ks:ks_name":"Karchhuna Malla",
    "ks:ks_pop":90,
    "ks:ks_type":"VILLAGE",
    "name:eng_x_preferred":[
        "Karchhuna Malla"
    ],
    "wof:name":"Karchhuna Malla",
    "wof:placetype":"locality",
    "wof:population":90
},
  "geometry": {"coordinates":[79.186554,30.297059],"type":"Point"}
}