{
  "type": "Feature",
  "properties": {
    "iso:country":"IN",
    "ks:ks_name":"Tholi",
    "ks:ks_pop":250,
    "ks:ks_type":"HABITATION",
    "name:eng_x_preferred":[
        "Tholi"
    ],
    "wof:name":"Tholi",
    "wof:placetype":"locality",
    "wof:population":250
},
  "geometry": {"coordinates":[79.29844799999999,29.665039],"type":"Point"}
}