{
  "type": "Feature",
  "properties": {
    "gn:admin1_code":"35",
    "gn:admin2_code":"462.0",
    "gn:asciiname":"Baki",
    "gn:country_code":"IN",
    "gn:dem":241,
    "gn:feature_class":"P",
    "gn:feature_code":"PPL",
    "gn:name":"B\u0101ki",
    "gn:population":0,
    "gn:timezone":"Asia/Kolkata",
    "iso:country":"IN",
    "name:cat_x_preferred":[
        "Baki"
    ],
    "name:ceb_x_preferred":[
        "Baki"
    ],
    "name:deu_x_preferred":[
        "Baki"
    ],
    "name:fin_x_preferred":[
        "Baki"
    ],
    "name:fra_x_preferred":[
        "Baki"
    ],
    "name:hun_x_preferred":[
        "Baki"
    ],
    "name:ita_x_preferred":[
        "Baki"
    ],
    "name:mlg_x_preferred":[
        "Baki"
    ],
    "name:nld_x_preferred":[
        "Baki"
    ],
    "name:pol_x_preferred":[
        "Baki"
    ],
    "name:rus_x_preferred":[
        "\u0411\u0430\u043a\u0438"
    ],
    "name:swa_x_preferred":[
        "Baki"
    ],
    "name:swe_x_preferred":[
        "Baki"
    ],
    "name:tha_x_preferred":[
        "\u0e1a\u0e32\u0e01\u0e34"
    ],
    "name:tur_x_preferred":[
        "Baki"
    ],
    "wof:name":"Baki",
    "wof:placetype":"locality"
},
  "geometry": {"coordinates":[82.24675999999999,24.58514],"type":"Point"}
}