{
  "type": "Feature",
  "properties": {
    "iso:country":"IN",
    "ks:ks_name":"Pipliyasinghadiya",
    "ks:ks_pop":425,
    "ks:ks_type":"VILLAGE",
    "name:eng_x_preferred":[
        "Pipliyasinghadiya"
    ],
    "wof:name":"Pipliyasinghadiya",
    "wof:placetype":"locality",
    "wof:population":425
},
  "geometry": {"coordinates":[75.326831,24.397651],"type":"Point"}
}