{
  "type": "Feature",
  "properties": {
    "iso:country":"IN",
    "ks:ks_name":"Periadka",
    "ks:ks_pop":23,
    "ks:ks_type":"HABITATION",
    "name:eng_x_preferred":[
        "Periadka"
    ],
    "wof:name":"Periadka",
    "wof:placetype":"locality",
    "wof:population":23
},
  "geometry": {"coordinates":[75.41622599999999,12.987064],"type":"Point"}
}