{
  "type": "Feature",
  "properties": {
    "gn:admin1_code":"34.0",
    "gn:admin2_code":"220.0",
    "gn:asciiname":"Chintamanpur",
    "gn:country_code":"IN",
    "gn:dem":59,
    "gn:feature_class":"P",
    "gn:feature_code":"PPL",
    "gn:name":"Chint\u0101manpur",
    "gn:population":0,
    "gn:timezone":"Asia/Kolkata",
    "iso:country":"IN",
    "ks:ks_alt_nam":"Chint\u0101manpur",
    "ks:ks_name":"Chintamanpur",
    "ks:ks_type":"VILLAGE",
    "name:eng_x_preferred":[
        "Chintamanpur"
    ],
    "name:eng_x_variant":[
        "Chint\u0101manpur"
    ],
    "wof:name":"Chintamanpur",
    "wof:placetype":"locality"
},
  "geometry": {"coordinates":[85.264532,25.953705],"type":"Point"}
}