{
  "type": "Feature",
  "properties": {
    "gn:admin1_code":"35",
    "gn:admin2_code":"458.0",
    "gn:asciiname":"Uni",
    "gn:country_code":"IN",
    "gn:dem":430,
    "gn:feature_class":"P",
    "gn:feature_code":"PPL",
    "gn:name":"Uni",
    "gn:population":0,
    "gn:timezone":"Asia/Kolkata",
    "iso:country":"IN",
    "name:ceb_x_preferred":[
        "Uni"
    ],
    "name:ces_x_preferred":[
        "Uni"
    ],
    "name:dan_x_preferred":[
        "Uni"
    ],
    "name:deu_x_preferred":[
        "Uni"
    ],
    "name:fin_x_preferred":[
        "Uni"
    ],
    "name:nld_x_preferred":[
        "Uni"
    ],
    "name:pol_x_preferred":[
        "Uni"
    ],
    "name:por_x_preferred":[
        "Uni"
    ],
    "name:rus_x_preferred":[
        "\u0423\u043d\u0438"
    ],
    "name:ukr_x_preferred":[
        "\u0423\u043d\u0456"
    ],
    "wof:name":"Uni",
    "wof:placetype":"locality"
},
  "geometry": {"coordinates":[77.23145,24.21618],"type":"Point"}
}