{
  "type": "Feature",
  "properties": {
    "gn:admin1_code":"2.0",
    "gn:admin2_code":"550.0",
    "gn:asciiname":"Valamedu",
    "gn:country_code":"IN",
    "gn:dem":9,
    "gn:feature_class":"P",
    "gn:feature_code":"PPL",
    "gn:name":"V\u0101lamedu",
    "gn:population":0,
    "gn:timezone":"Asia/Kolkata",
    "iso:country":"IN",
    "ks:ks_alt_nam":"V\u0101lamedu",
    "ks:ks_name":"Valamedu",
    "ks:ks_pop":663,
    "ks:ks_type":"VILLAGE",
    "name:eng_x_preferred":[
        "Valamedu"
    ],
    "name:eng_x_variant":[
        "V\u0101lamedu"
    ],
    "wof:name":"Valamedu",
    "wof:placetype":"locality",
    "wof:population":663
},
  "geometry": {"coordinates":[80.115364,14.042061],"type":"Point"}
}