{
  "type": "Feature",
  "properties": {
    "iso:country":"IN",
    "ks:ks_name":"Plotpada",
    "ks:ks_pop":58,
    "ks:ks_type":"HABITATION",
    "name:eng_x_preferred":[
        "Plotpada"
    ],
    "wof:name":"Plotpada",
    "wof:placetype":"locality",
    "wof:population":58
},
  "geometry": {"coordinates":[73.02318099999999,19.622349],"type":"Point"}
}