{
  "type": "Feature",
  "properties": {
    "gn:admin1_code":"24.0",
    "gn:admin2_code":"115.0",
    "gn:asciiname":"Talib ka Par",
    "gn:country_code":"IN",
    "gn:dem":163,
    "gn:feature_class":"P",
    "gn:feature_code":"PPL",
    "gn:name":"Talib ka P\u0101r",
    "gn:population":0,
    "gn:timezone":"Asia/Kolkata",
    "iso:country":"IN",
    "wof:name":"Talib ka Par",
    "wof:placetype":"locality"
},
  "geometry": {"coordinates":[70.6733,25.58995],"type":"Point"}
}