{
  "type": "Feature",
  "properties": {
    "iso:country":"IN",
    "ks:ks_name":"Turturi",
    "ks:ks_pop":1823,
    "ks:ks_type":"VILLAGE",
    "name:eng_x_preferred":[
        "Turturi"
    ],
    "wof:name":"Turturi",
    "wof:placetype":"locality",
    "wof:population":1823
},
  "geometry": {"coordinates":[89.69775199999999,26.627199],"type":"Point"}
}