{
  "type": "Feature",
  "properties": {
    "iso:country":"IN",
    "ks:ks_alt_nam":"KOLEKAR CHAVAN WASTI",
    "ks:ks_name":"Kolekar Chavan Wasti",
    "ks:ks_pop":166,
    "ks:ks_type":"HABITATION",
    "name:eng_x_preferred":[
        "Kolekar Chavan Wasti"
    ],
    "wof:name":"Kolekar Chavan Wasti",
    "wof:placetype":"locality",
    "wof:population":166
},
  "geometry": {"coordinates":[74.84983200000001,16.985107],"type":"Point"}
}