{
  "type": "Feature",
  "properties": {
    "gn:admin1_code":"11.0",
    "gn:admin2_code":"031",
    "gn:asciiname":"Siahtaj",
    "gn:country_code":"IN",
    "gn:dem":1219,
    "gn:feature_class":"P",
    "gn:feature_code":"PPL",
    "gn:name":"S\u012b\u0101htaj",
    "gn:population":0,
    "gn:timezone":"Asia/Kolkata",
    "iso:country":"IN",
    "name:und_x_variant":[
        "S\u012b\u0101htaj",
        "Sy\u0101tha"
    ],
    "wof:name":"Siahtaj",
    "wof:placetype":"locality"
},
  "geometry": {"coordinates":[77.01769,31.14454000000001],"type":"Point"}
}