{
  "type": "Feature",
  "properties": {
    "gn:admin1_code":"34.0",
    "gn:admin2_code":"220.0",
    "gn:asciiname":"Narangi Sarsikan",
    "gn:country_code":"IN",
    "gn:dem":55,
    "gn:feature_class":"P",
    "gn:feature_code":"PPL",
    "gn:name":"Narangi Sarsikan",
    "gn:population":0,
    "gn:timezone":"Asia/Kolkata",
    "iso:country":"IN",
    "wof:name":"Narangi Sarsikan",
    "wof:placetype":"locality"
},
  "geometry": {"coordinates":[85.36458,25.85798],"type":"Point"}
}