{
  "type": "Feature",
  "properties": {
    "gn:admin1_code":"35.0",
    "gn:admin2_code":"456.0",
    "gn:asciiname":"Kimachi",
    "gn:country_code":"IN",
    "gn:dem":437,
    "gn:feature_class":"P",
    "gn:feature_code":"PPL",
    "gn:name":"Kim\u0101ch\u012b",
    "gn:population":0,
    "gn:timezone":"Asia/Kolkata",
    "iso:country":"IN",
    "wof:name":"Kimachi",
    "wof:placetype":"locality"
},
  "geometry": {"coordinates":[80.05341999999997,22.45129],"type":"Point"}
}