{
  "type": "Feature",
  "properties": {
    "iso:country":"IN",
    "ks:ks_alt_nam":"RADHA COBRA PARA",
    "ks:ks_name":"Radha Cobra Para",
    "ks:ks_pop":245,
    "ks:ks_type":"HABITATION",
    "name:eng_x_preferred":[
        "Radha Cobra Para"
    ],
    "wof:name":"Radha Cobra Para",
    "wof:placetype":"locality",
    "wof:population":245
},
  "geometry": {"coordinates":[91.67271700000001,23.820878],"type":"Point"}
}