{
  "type": "Feature",
  "properties": {
    "gn:admin1_code":"12.0",
    "gn:admin2_code":"16.0",
    "gn:asciiname":"Dedu",
    "gn:country_code":"IN",
    "gn:dem":2304,
    "gn:feature_class":"P",
    "gn:feature_code":"PPL",
    "gn:name":"Ded\u016b",
    "gn:population":0,
    "gn:timezone":"Asia/Kolkata",
    "iso:country":"IN",
    "name:ceb_x_preferred":[
        "Dedu"
    ],
    "name:swe_x_preferred":[
        "Dedu"
    ],
    "wof:name":"Dedu",
    "wof:placetype":"locality"
},
  "geometry": {"coordinates":[75.3445,33.25281],"type":"Point"}
}