{
  "type": "Feature",
  "properties": {
    "gn:admin1_code":"10.0",
    "gn:admin2_code":"86.0",
    "gn:asciiname":"Jauniawas",
    "gn:country_code":"IN",
    "gn:dem":227,
    "gn:feature_class":"P",
    "gn:feature_code":"PPL",
    "gn:name":"Jauni\u0101w\u0101s",
    "gn:population":0,
    "gn:timezone":"Asia/Kolkata",
    "iso:country":"IN",
    "wof:name":"Jauniawas",
    "wof:placetype":"locality"
},
  "geometry": {"coordinates":[76.81005,28.39439],"type":"Point"}
}