{
  "type": "Feature",
  "properties": {
    "gn:admin1_code":"23.0",
    "gn:asciiname":"Machhiwara",
    "gn:country_code":"IN",
    "gn:dem":197,
    "gn:feature_class":"P",
    "gn:feature_code":"PPL",
    "gn:name":"Machhiw\u0101ra",
    "gn:population":0,
    "gn:timezone":"Asia/Karachi",
    "iso:country":"IN",
    "name:ben_x_preferred":[
        "\u09ae\u09be\u099b\u09bf\u0993\u09af\u09bc\u09be\u09b0\u09be"
    ],
    "name:bpy_x_preferred":[
        "\u09ae\u09be\u099b\u09bf\u09f1\u09be\u09b0\u09be"
    ],
    "name:ceb_x_preferred":[
        "M\u0101chh\u012bw\u0101ra"
    ],
    "name:ita_x_preferred":[
        "Machhiwara"
    ],
    "name:msa_x_preferred":[
        "Machhiwara"
    ],
    "name:new_x_preferred":[
        "\u092e\u093e\u091b\u0940\u0935\u093e\u0930\u093e"
    ],
    "name:nld_x_preferred":[
        "Machhiwara"
    ],
    "name:pan_x_preferred":[
        "\u0a2e\u0a3e\u0a1b\u0a40\u0a35\u0a3e\u0a5c\u0a3e"
    ],
    "name:pnb_x_preferred":[
        "\u0645\u0627\u0686\u06be\u06cc \u0648\u0627\u0691\u0627"
    ],
    "name:por_x_preferred":[
        "Machhiwara"
    ],
    "name:spa_x_preferred":[
        "Machhiwara"
    ],
    "name:swe_x_preferred":[
        "M\u0101chh\u012bw\u0101ra"
    ],
    "name:tam_x_preferred":[
        "\u0bae\u0bbe\u0b9a\u0bcd\u0b9a\u0bc0\u0bb5\u0bbe\u0b9f\u0bbe"
    ],
    "name:urd_x_preferred":[
        "\u0645\u0627\u0686\u06be\u06cc\u0648\u0627\u0631\u0627"
    ],
    "name:vie_x_preferred":[
        "Machhiwara"
    ],
    "name:zho_x_preferred":[
        "\u9a6c\u5947\u74e6\u62c9"
    ],
    "wof:name":"Machhiwara",
    "wof:placetype":"locality"
},
  "geometry": {"coordinates":[74.54276,31.01799],"type":"Point"}
}