{
  "type": "Feature",
  "properties": {
    "gn:admin1_code":"23.0",
    "gn:asciiname":"Machhiwara",
    "gn:country_code":"IN",
    "gn:dem":197,
    "gn:feature_class":"P",
    "gn:feature_code":"PPL",
    "gn:name":"Machhiw\u0101ra",
    "gn:population":0,
    "gn:timezone":"Asia/Karachi",
    "iso:country":"IN",
    "wof:name":"Machhiwara",
    "wof:placetype":"locality"
},
  "geometry": {"coordinates":[74.54276,31.01799],"type":"Point"}
}