{
  "type": "Feature",
  "properties": {
    "iso:country":"IN",
    "ks:ks_name":"Okanimaria Kachari Gaon",
    "ks:ks_pop":1006,
    "ks:ks_type":"VILLAGE",
    "ks:ks_uagg_main":0,
    "name:eng_x_preferred":[
        "Okanimaria Kachari Gaon"
    ],
    "wof:name":"Okanimaria Kachari Gaon",
    "wof:placetype":"locality",
    "wof:population":1006
},
  "geometry": {"coordinates":[95.301496,27.49152],"type":"Point"}
}