{
  "type": "Feature",
  "properties": {
    "iso:country":"IN",
    "ks:ks_name":"Talakdhari Tola",
    "ks:ks_pop":405,
    "ks:ks_type":"HABITATION",
    "name:eng_x_preferred":[
        "Talakdhari Tola"
    ],
    "wof:name":"Talakdhari Tola",
    "wof:placetype":"locality",
    "wof:population":405
},
  "geometry": {"coordinates":[87.487303,25.332517],"type":"Point"}
}