{
  "type": "Feature",
  "properties": {
    "iso:country":"IN",
    "ks:ks_name":"Siarbuda",
    "ks:ks_pop":238,
    "ks:ks_type":"HABITATION",
    "name:eng_x_preferred":[
        "Siarbuda"
    ],
    "wof:name":"Siarbuda",
    "wof:placetype":"locality",
    "wof:population":238
},
  "geometry": {"coordinates":[83.70263300000001,22.300403],"type":"Point"}
}