{
  "type": "Feature",
  "properties": {
    "iso:country":"IN",
    "ks:ks_name":"Kewti",
    "ks:ks_pop":604,
    "ks:ks_type":"VILLAGE",
    "name:eng_x_preferred":[
        "Kewti"
    ],
    "wof:name":"Kewti",
    "wof:placetype":"locality",
    "wof:population":604
},
  "geometry": {"coordinates":[81.63175,19.646762],"type":"Point"}
}