{
  "type": "Feature",
  "properties": {
    "iso:country":"IN",
    "ks:ks_name":"Khodiyar Nes",
    "ks:ks_pop":12,
    "ks:ks_type":"VILLAGE",
    "name:eng_x_preferred":[
        "Khodiyar Nes"
    ],
    "wof:name":"Khodiyar Nes",
    "wof:placetype":"locality",
    "wof:population":12
},
  "geometry": {"coordinates":[69.702083,21.81975],"type":"Point"}
}