{
  "type": "Feature",
  "properties": {
    "gn:admin1_code":"24.0",
    "gn:admin2_code":"103.0",
    "gn:asciiname":"Tiloka Bas",
    "gn:country_code":"IN",
    "gn:dem":313,
    "gn:feature_class":"P",
    "gn:feature_code":"PPL",
    "gn:name":"Tiloka B\u0101s",
    "gn:population":0,
    "gn:timezone":"Asia/Kolkata",
    "iso:country":"IN",
    "wof:name":"Tiloka Bas",
    "wof:placetype":"locality"
},
  "geometry": {"coordinates":[75.20902,28.18199000000001],"type":"Point"}
}