{
  "type": "Feature",
  "properties": {
    "iso:country":"IN",
    "ks:ks_name":"Uraonpara",
    "ks:ks_pop":124,
    "ks:ks_type":"HABITATION",
    "name:eng_x_preferred":[
        "Uraonpara"
    ],
    "wof:name":"Uraonpara",
    "wof:placetype":"locality",
    "wof:population":124
},
  "geometry": {"coordinates":[83.198683,22.501547],"type":"Point"}
}