{
  "type": "Feature",
  "properties": {
    "gn:admin1_code":"21",
    "gn:admin2_code":"397.0",
    "gn:asciiname":"Tarenga",
    "gn:country_code":"IN",
    "gn:dem":640,
    "gn:feature_class":"P",
    "gn:feature_code":"PPL",
    "gn:name":"Tarenga",
    "gn:population":0,
    "gn:timezone":"Asia/Kolkata",
    "iso:country":"IN",
    "ks:ks_name":"Torenga",
    "ks:ks_pop":2622,
    "ks:ks_type":"VILLAGE",
    "name:eng_x_preferred":[
        "Torenga"
    ],
    "name:eng_x_variant":[
        "Tarenga"
    ],
    "wof:name":"Torenga",
    "wof:placetype":"locality",
    "wof:population":2622
},
  "geometry": {"coordinates":[82.11070100000001,19.48479],"type":"Point"}
}