{
  "type": "Feature",
  "properties": {
    "gn:admin1_code":"21",
    "gn:admin2_code":"397.0",
    "gn:asciiname":"Tarenga",
    "gn:country_code":"IN",
    "gn:dem":640,
    "gn:feature_class":"P",
    "gn:feature_code":"PPL",
    "gn:name":"Tarenga",
    "gn:population":0,
    "gn:timezone":"Asia/Kolkata",
    "iso:country":"IN",
    "wof:name":"Tarenga",
    "wof:placetype":"locality"
},
  "geometry": {"coordinates":[82.1228,19.48787],"type":"Point"}
}