{
  "type": "Feature",
  "properties": {
    "iso:country":"IN",
    "ks:ks_name":"Kachalu Pathar No 2",
    "ks:ks_pop":802,
    "ks:ks_type":"VILLAGE",
    "ks:ks_uagg_main":0,
    "name:eng_x_preferred":[
        "Kachalu Pathar No 2"
    ],
    "wof:name":"Kachalu Pathar No 2",
    "wof:placetype":"neighbourhood",
    "wof:population":802
},
  "geometry": {"coordinates":[95.167253,27.237913],"type":"Point"}
}