{
  "type": "Feature",
  "properties": {
    "gn:admin1_code":"19.0",
    "gn:admin2_code":"571.0",
    "gn:asciiname":"Devanur",
    "gn:country_code":"IN",
    "gn:dem":836,
    "gn:feature_class":"P",
    "gn:feature_code":"PPL",
    "gn:name":"Devan\u016br",
    "gn:population":0,
    "gn:timezone":"Asia/Kolkata",
    "iso:country":"IN",
    "name:tam_x_preferred":[
        "\u0ba4\u0bc7\u0bb5\u0ba9\u0bc1\u0bb0\u0bcd"
    ],
    "name:vie_x_preferred":[
        "Devanur"
    ],
    "wof:name":"Devanur",
    "wof:placetype":"locality"
},
  "geometry": {"coordinates":[77.11596,13.32347],"type":"Point"}
}