{
  "type": "Feature",
  "properties": {
    "iso:country":"IN",
    "ks:ks_name":"Khaspara 1",
    "ks:ks_pop":1963,
    "ks:ks_type":"HABITATION",
    "name:eng_x_preferred":[
        "Khaspara 1"
    ],
    "wof:name":"Khaspara 1",
    "wof:placetype":"locality",
    "wof:population":1963
},
  "geometry": {"coordinates":[81.654776,19.857617],"type":"Point"}
}