{
  "type": "Feature",
  "properties": {
    "iso:country":"IN",
    "ks:ks_name":"Gorkaychegalu",
    "ks:ks_pop":90,
    "ks:ks_type":"HABITATION",
    "name:eng_x_preferred":[
        "Gorkaychegalu"
    ],
    "wof:name":"Gorkaychegalu",
    "wof:placetype":"locality",
    "wof:population":90
},
  "geometry": {"coordinates":[73.764917,15.904444],"type":"Point"}
}