{
  "type": "Feature",
  "properties": {
    "gn:admin1_code":"24.0",
    "gn:admin2_code":"117.0",
    "gn:asciiname":"Paba",
    "gn:country_code":"IN",
    "gn:dem":435,
    "gn:feature_class":"P",
    "gn:feature_code":"PPL",
    "gn:name":"Paba",
    "gn:population":0,
    "gn:timezone":"Asia/Kolkata",
    "iso:country":"IN",
    "wof:name":"Paba",
    "wof:placetype":"locality"
},
  "geometry": {"coordinates":[72.95492,24.47574],"type":"Point"}
}