{
  "type": "Feature",
  "properties": {
    "gn:admin1_code":"24.0",
    "gn:admin2_code":"117.0",
    "gn:asciiname":"Paba",
    "gn:country_code":"IN",
    "gn:dem":435,
    "gn:feature_class":"P",
    "gn:feature_code":"PPL",
    "gn:name":"Paba",
    "gn:population":0,
    "gn:timezone":"Asia/Kolkata",
    "iso:country":"IN",
    "ks:ks_name":"Paba",
    "ks:ks_pop":126,
    "ks:ks_type":"VILLAGE",
    "name:eng_x_preferred":[
        "Paba"
    ],
    "wof:name":"Paba",
    "wof:placetype":"locality",
    "wof:population":126
},
  "geometry": {"coordinates":[72.97314299999999,24.476718],"type":"Point"}
}