{
  "type": "Feature",
  "properties": {
    "iso:country":"IN",
    "ks:ks_alt_nam":"Kechery Aloor Rd jun",
    "ks:ks_name":"Kechery Aloor Rd Jun",
    "ks:ks_pop":125,
    "ks:ks_type":"HABITATION",
    "name:eng_x_preferred":[
        "Kechery Aloor Rd Jun"
    ],
    "wof:name":"Kechery Aloor Rd Jun",
    "wof:placetype":"locality",
    "wof:population":125
},
  "geometry": {"coordinates":[76.09724,10.617689],"type":"Point"}
}