{
  "type": "Feature",
  "properties": {
    "iso:country":"IN",
    "ks:ks_name":"Kookanadu",
    "ks:ks_pop":187,
    "ks:ks_type":"HABITATION",
    "name:eng_x_preferred":[
        "Kookanadu"
    ],
    "wof:name":"Kookanadu",
    "wof:placetype":"locality",
    "wof:population":187
},
  "geometry": {"coordinates":[74.729771,13.689832],"type":"Point"}
}