{
  "type": "Feature",
  "properties": {
    "iso:country":"IN",
    "ks:ks_name":"Viper Island",
    "ks:ks_type":"VILLAGE",
    "name:eng_x_preferred":[
        "Viper Island"
    ],
    "wof:name":"Viper Island",
    "wof:placetype":"locality"
},
  "geometry": {"coordinates":[92.69733600000001,11.661523],"type":"Point"}
}