{
  "type": "Feature",
  "properties": {
    "gn:admin1_code":"34.0",
    "gn:admin2_code":"225.0",
    "gn:asciiname":"Sirai",
    "gn:country_code":"IN",
    "gn:dem":117,
    "gn:feature_class":"P",
    "gn:feature_code":"PPL",
    "gn:name":"Sir\u0101i",
    "gn:population":0,
    "gn:timezone":"Asia/Kolkata",
    "iso:country":"IN",
    "ks:ks_alt_nam":"Sir\u0101i",
    "ks:ks_name":"Sirai",
    "ks:ks_pop":1216,
    "ks:ks_type":"VILLAGE",
    "ks:ks_uagg_main":0,
    "name:eng_x_preferred":[
        "Sirai"
    ],
    "name:eng_x_variant":[
        "Sir\u0101i"
    ],
    "name:tam_x_preferred":[
        "\u0b9a\u0bbf\u0bb1\u0bc8"
    ],
    "wof:name":"Sirai",
    "wof:placetype":"neighbourhood",
    "wof:population":1216
},
  "geometry": {"coordinates":[87.013902,24.794922],"type":"Point"}
}