{
  "type": "Feature",
  "properties": {
    "iso:country":"IN",
    "ks:ks_name":"Kachomari No 1",
    "ks:ks_pop":461,
    "ks:ks_type":"HABITATION",
    "name:eng_x_preferred":[
        "Kachomari No 1"
    ],
    "wof:name":"Kachomari No 1",
    "wof:placetype":"locality",
    "wof:population":461
},
  "geometry": {"coordinates":[93.10263399999999,26.055444],"type":"Point"}
}