{
  "type": "Feature",
  "properties": {
    "gn:admin1_code":"34.0",
    "gn:admin2_code":"229.0",
    "gn:asciiname":"Makanpur",
    "gn:country_code":"IN",
    "gn:dem":58,
    "gn:feature_class":"P",
    "gn:feature_code":"PPL",
    "gn:name":"Mak\u0101npur",
    "gn:population":0,
    "gn:timezone":"Asia/Kolkata",
    "iso:country":"IN",
    "name:urd_x_preferred":[
        "\u0645\u06a9\u0646 \u067e\u0648\u0631"
    ],
    "wof:name":"Makanpur",
    "wof:placetype":"locality"
},
  "geometry": {"coordinates":[85.31466,25.245],"type":"Point"}
}