{
  "type": "Feature",
  "properties": {
    "gn:admin1_code":"36",
    "gn:admin2_code":"188.0",
    "gn:asciiname":"Rajupur Urf Mahmudpur",
    "gn:country_code":"IN",
    "gn:dem":82,
    "gn:feature_class":"P",
    "gn:feature_code":"PPL",
    "gn:name":"Raj\u016bpur Urf Mahm\u016bdpur",
    "gn:population":0,
    "gn:timezone":"Asia/Kolkata",
    "iso:country":"IN",
    "wof:name":"Rajupur Urf Mahmudpur",
    "wof:placetype":"locality"
},
  "geometry": {"coordinates":[83.25435,26.40336],"type":"Point"}
}