{
  "type": "Feature",
  "properties": {
    "gn:admin1_code":"19.0",
    "gn:admin2_code":"582.0",
    "gn:asciiname":"Kotanahalli",
    "gn:country_code":"IN",
    "gn:dem":673,
    "gn:feature_class":"P",
    "gn:feature_code":"PPL",
    "gn:name":"Kotanahalli",
    "gn:population":0,
    "gn:timezone":"Asia/Kolkata",
    "iso:country":"IN",
    "wof:name":"Kotanahalli",
    "wof:placetype":"locality"
},
  "geometry": {"coordinates":[77.63616999999998,13.76731],"type":"Point"}
}