{
  "type": "Feature",
  "properties": {
    "iso:country":"IN",
    "ks:ks_name":"5 F",
    "ks:ks_pop":110,
    "ks:ks_type":"VILLAGE",
    "name:eng_x_preferred":[
        "5 F"
    ],
    "wof:name":"5 F",
    "wof:placetype":"locality",
    "wof:population":110
},
  "geometry": {"coordinates":[73.844847,30.003872],"type":"Point"}
}