{
  "type": "Feature",
  "properties": {
    "gn:admin1_code":"19.0",
    "gn:admin2_code":"581.0",
    "gn:asciiname":"Yarrachinnenahalli",
    "gn:country_code":"IN",
    "gn:dem":774,
    "gn:feature_class":"P",
    "gn:feature_code":"PPL",
    "gn:name":"Yarrachinnenahalli",
    "gn:population":0,
    "gn:timezone":"Asia/Kolkata",
    "iso:country":"IN",
    "wof:name":"Yarrachinnenahalli",
    "wof:placetype":"locality"
},
  "geometry": {"coordinates":[78.45974,13.13636],"type":"Point"}
}