{
  "type": "Feature",
  "properties": {
    "iso:country":"IN",
    "ks:ks_alt_nam":"Kunti panthulu thanda",
    "ks:ks_name":"Kunti Panthulu Thanda",
    "ks:ks_pop":142,
    "ks:ks_type":"HABITATION",
    "name:eng_x_preferred":[
        "Kunti Panthulu Thanda"
    ],
    "wof:name":"Kunti Panthulu Thanda",
    "wof:placetype":"locality",
    "wof:population":142
},
  "geometry": {"coordinates":[79.70486099999999,17.820584],"type":"Point"}
}