{
  "type": "Feature",
  "properties": {
    "gn:admin1_code":"23.0",
    "gn:admin2_code":"53.0",
    "gn:asciiname":"Moonak",
    "gn:country_code":"IN",
    "gn:dem":228,
    "gn:feature_class":"P",
    "gn:feature_code":"PPL",
    "gn:name":"Moonak",
    "gn:population":0,
    "gn:timezone":"Asia/Kolkata",
    "iso:country":"IN",
    "name:ben_x_preferred":[
        "\u09ae\u09cb\u09a8\u09be\u0995"
    ],
    "name:bpy_x_preferred":[
        "\u09ae\u09cb\u09a8\u09be\u0995"
    ],
    "name:hin_x_preferred":[
        "\u092e\u0942\u0928\u0915"
    ],
    "name:ita_x_preferred":[
        "Moonak"
    ],
    "name:msa_x_preferred":[
        "Moonak"
    ],
    "name:new_x_preferred":[
        "\u092e\u0942\u0928\u0915"
    ],
    "name:nld_x_preferred":[
        "Moonak"
    ],
    "name:por_x_preferred":[
        "Moonak"
    ],
    "name:vie_x_preferred":[
        "Moonak"
    ],
    "name:zho_x_preferred":[
        "\u83ab\u5965\u7eb3\u514b"
    ],
    "wof:name":"Moonak",
    "wof:placetype":"locality"
},
  "geometry": {"coordinates":[75.89055,29.82529000000001],"type":"Point"}
}