{
  "type": "Feature",
  "properties": {
    "iso:country":"IN",
    "ks:ks_alt_nam":"CHIKHLDA FV",
    "ks:ks_name":"Chikhlda Fv",
    "ks:ks_pop":506,
    "ks:ks_type":"HABITATION",
    "name:eng_x_preferred":[
        "Chikhlda Fv"
    ],
    "wof:name":"Chikhlda Fv",
    "wof:placetype":"locality",
    "wof:population":506
},
  "geometry": {"coordinates":[77.403578,21.936916],"type":"Point"}
}