{
  "type": "Feature",
  "properties": {
    "gn:admin1_code":"25.0",
    "gn:admin2_code":"612.0",
    "gn:asciiname":"Vadippatti",
    "gn:country_code":"IN",
    "gn:dem":335,
    "gn:feature_class":"P",
    "gn:feature_code":"PPL",
    "gn:name":"V\u0101dippatti",
    "gn:population":0,
    "gn:timezone":"Asia/Kolkata",
    "iso:country":"IN",
    "wof:name":"Vadippatti",
    "wof:placetype":"neighbourhood"
},
  "geometry": {"coordinates":[77.42748,10.45067],"type":"Point"}
}