{
  "type": "Feature",
  "properties": {
    "iso:country":"IN",
    "ks:ks_name":"Jangirivalsa",
    "ks:ks_pop":346,
    "ks:ks_type":"VILLAGE",
    "name:eng_x_preferred":[
        "Jangirivalsa"
    ],
    "wof:name":"Jangirivalsa",
    "wof:placetype":"locality",
    "wof:population":346
},
  "geometry": {"coordinates":[83.25100999999999,18.858009],"type":"Point"}
}