{
  "type": "Feature",
  "properties": {
    "iso:country":"IN",
    "ks:ks_name":"Dhibrapar",
    "ks:ks_pop":390,
    "ks:ks_type":"HABITATION",
    "name:eng_x_preferred":[
        "Dhibrapar"
    ],
    "wof:name":"Dhibrapar",
    "wof:placetype":"locality",
    "wof:population":390
},
  "geometry": {"coordinates":[84.850897,24.954144],"type":"Point"}
}