{
  "type": "Feature",
  "properties": {
    "iso:country":"IN",
    "ks:ks_name":"Devi Jot",
    "ks:ks_pop":276,
    "ks:ks_type":"HABITATION",
    "ks:ks_uagg_main":0,
    "name:eng_x_preferred":[
        "Devi Jot"
    ],
    "wof:name":"Devi Jot",
    "wof:placetype":"neighbourhood",
    "wof:population":276
},
  "geometry": {"coordinates":[83.258782,27.210102],"type":"Point"}
}