{
  "type": "Feature",
  "properties": {
    "iso:country":"IN",
    "ks:ks_name":"Palamala",
    "ks:ks_pop":580,
    "ks:ks_type":"HABITATION",
    "name:eng_x_preferred":[
        "Palamala"
    ],
    "wof:name":"Palamala",
    "wof:placetype":"locality",
    "wof:population":580
},
  "geometry": {"coordinates":[76.29265599999999,11.230401],"type":"Point"}
}