{
  "type": "Feature",
  "properties": {
    "iso:country":"IN",
    "ks:ks_name":"Baman Para",
    "ks:ks_pop":527,
    "ks:ks_type":"HABITATION",
    "name:eng_x_preferred":[
        "Baman Para"
    ],
    "wof:name":"Baman Para",
    "wof:placetype":"locality",
    "wof:population":527
},
  "geometry": {"coordinates":[81.878826,19.288174],"type":"Point"}
}