{
  "type": "Feature",
  "properties": {
    "gn:admin1_code":"19.0",
    "gn:admin2_code":"577.0",
    "gn:asciiname":"Sannamalapura",
    "gn:country_code":"IN",
    "gn:dem":676,
    "gn:feature_class":"P",
    "gn:feature_code":"PPL",
    "gn:name":"Sannamal\u0101pura",
    "gn:population":0,
    "gn:timezone":"Asia/Kolkata",
    "iso:country":"IN",
    "ks:ks_name":"Sannamlalupura",
    "ks:ks_pop":221,
    "ks:ks_type":"HABITATION",
    "name:eng_x_preferred":[
        "Sannamlalupura"
    ],
    "name:eng_x_variant":[
        "Sannamalapura"
    ],
    "wof:name":"Sannamlalupura",
    "wof:placetype":"locality",
    "wof:population":221
},
  "geometry": {"coordinates":[76.79349499999999,12.132847],"type":"Point"}
}