{
  "type": "Feature",
  "properties": {
    "gn:admin1_code":"35",
    "gn:admin2_code":"430.0",
    "gn:asciiname":"Barwah",
    "gn:country_code":"IN",
    "gn:dem":321,
    "gn:feature_class":"P",
    "gn:feature_code":"PPL",
    "gn:name":"Barw\u0101h",
    "gn:population":0,
    "gn:timezone":"Asia/Kolkata",
    "iso:country":"IN",
    "ks:ks_name":"Barwah",
    "ks:ks_pop":784,
    "ks:ks_type":"HABITATION",
    "name:eng_x_preferred":[
        "Barwah"
    ],
    "wof:name":"Barwah",
    "wof:placetype":"locality",
    "wof:population":784
},
  "geometry": {"coordinates":[81.234154,24.60061],"type":"Point"}
}