{
  "type": "Feature",
  "properties": {
    "gn:admin1_code":"36",
    "gn:admin2_code":"134.0",
    "gn:asciiname":"Samaspur Khora",
    "gn:country_code":"IN",
    "gn:dem":249,
    "gn:feature_class":"P",
    "gn:feature_code":"PPL",
    "gn:name":"Samaspur Khora",
    "gn:population":0,
    "gn:timezone":"Asia/Kolkata",
    "iso:country":"IN",
    "ks:ks_name":"Samaspur Khora",
    "ks:ks_type":"VILLAGE",
    "name:eng_x_preferred":[
        "Samaspur Khora"
    ],
    "wof:name":"Samaspur Khora",
    "wof:placetype":"locality"
},
  "geometry": {"coordinates":[78.30862500000001,29.45726],"type":"Point"}
}