{
  "type": "Feature",
  "properties": {
    "iso:country":"IN",
    "ks:ks_name":"Lower Gopla Maran",
    "ks:ks_pop":145,
    "ks:ks_type":"HABITATION",
    "name:eng_x_preferred":[
        "Lower Gopla Maran"
    ],
    "wof:name":"Lower Gopla Maran",
    "wof:placetype":"locality",
    "wof:population":145
},
  "geometry": {"coordinates":[86.530784,24.727225],"type":"Point"}
}