{
  "type": "Feature",
  "properties": {
    "iso:country":"IN",
    "ks:ks_alt_nam":"Hempur Day\u0101",
    "ks:ks_name":"Hempur Daya",
    "ks:ks_pop":658,
    "ks:ks_type":"VILLAGE",
    "ks:ks_uagg_main":0,
    "name:eng_x_preferred":[
        "Hempur Daya"
    ],
    "name:eng_x_variant":[
        "Hempur Day\u0101"
    ],
    "wof:name":"Hempur Daya",
    "wof:placetype":"neighbourhood",
    "wof:population":658
},
  "geometry": {"coordinates":[79.009602,29.300076],"type":"Point"}
}