{
  "type": "Feature",
  "properties": {
    "gn:admin1_code":"16",
    "gn:admin2_code":"498.0",
    "gn:asciiname":"Dahyane",
    "gn:country_code":"IN",
    "gn:dem":345,
    "gn:feature_class":"P",
    "gn:feature_code":"PPL",
    "gn:name":"D\u0101hy\u0101ne",
    "gn:population":0,
    "gn:timezone":"Asia/Kolkata",
    "iso:country":"IN",
    "wof:name":"Dahyane",
    "wof:placetype":"locality"
},
  "geometry": {"coordinates":[74.68988,20.85569],"type":"Point"}
}