{
  "type": "Feature",
  "properties": {
    "iso:country":"IN",
    "ks:ks_alt_nam":"Raqba R\u0101mpur",
    "ks:ks_name":"Raqba Rampur",
    "ks:ks_type":"VILLAGE",
    "name:eng_x_preferred":[
        "Raqba Rampur"
    ],
    "name:eng_x_variant":[
        "Raqba R\u0101mpur"
    ],
    "wof:name":"Raqba Rampur",
    "wof:placetype":"locality"
},
  "geometry": {"coordinates":[84.11816,26.57975],"type":"Point"}
}