{
  "type": "Feature",
  "properties": {
    "iso:country":"IN",
    "ks:ks_name":"Mundasai",
    "ks:ks_pop":409,
    "ks:ks_type":"HABITATION",
    "name:eng_x_preferred":[
        "Mundasai"
    ],
    "wof:name":"Mundasai",
    "wof:placetype":"locality",
    "wof:population":409
},
  "geometry": {"coordinates":[85.55800600000001,22.136029],"type":"Point"}
}