{
  "type": "Feature",
  "properties": {
    "iso:country":"IN",
    "ks:ks_alt_nam":"D\u016blahpur",
    "ks:ks_name":"Dulahpur",
    "ks:ks_type":"VILLAGE",
    "name:eng_x_preferred":[
        "Dulahpur"
    ],
    "name:eng_x_variant":[
        "D\u016blahpur"
    ],
    "wof:name":"Dulahpur",
    "wof:placetype":"locality"
},
  "geometry": {"coordinates":[82.339831,25.025069],"type":"Point"}
}