{
  "type": "Feature",
  "properties": {
    "gn:admin1_code":"12.0",
    "gn:admin2_code":"008",
    "gn:asciiname":"Badra Bala",
    "gn:country_code":"IN",
    "gn:dem":1612,
    "gn:feature_class":"P",
    "gn:feature_code":"PPL",
    "gn:name":"Badra Bala",
    "gn:population":0,
    "gn:timezone":"Asia/Kolkata",
    "iso:country":"IN",
    "wof:name":"Badra Bala",
    "wof:placetype":"locality"
},
  "geometry": {"coordinates":[74.34437,34.33027],"type":"Point"}
}