{
  "type": "Feature",
  "properties": {
    "iso:country":"IN",
    "ks:ks_name":"Bamiyala",
    "ks:ks_pop":382,
    "ks:ks_type":"VILLAGE",
    "name:eng_x_preferred":[
        "Bamiyala"
    ],
    "wof:name":"Bamiyala",
    "wof:placetype":"locality",
    "wof:population":382
},
  "geometry": {"coordinates":[79.31228,30.151166],"type":"Point"}
}