{
  "type": "Feature",
  "properties": {
    "gn:admin1_code":"35",
    "gn:admin2_code":"435.0",
    "gn:asciiname":"Labaicha",
    "gn:country_code":"IN",
    "gn:dem":477,
    "gn:feature_class":"P",
    "gn:feature_code":"PPL",
    "gn:name":"Labaicha",
    "gn:population":0,
    "gn:timezone":"Asia/Kolkata",
    "iso:country":"IN",
    "ks:ks_name":"Labaycha",
    "ks:ks_pop":431,
    "ks:ks_type":"VILLAGE",
    "name:eng_x_preferred":[
        "Labaycha"
    ],
    "name:eng_x_variant":[
        "Labaicha"
    ],
    "wof:name":"Labaycha",
    "wof:placetype":"locality",
    "wof:population":431
},
  "geometry": {"coordinates":[75.487734,23.197658],"type":"Point"}
}