{
  "type": "Feature",
  "properties": {
    "iso:country":"IN",
    "ks:ks_name":"3 BPM",
    "ks:ks_pop":164,
    "ks:ks_type":"VILLAGE",
    "name:eng_x_preferred":[
        "3 BPM"
    ],
    "wof:name":"3 BPM",
    "wof:placetype":"locality",
    "wof:population":164
},
  "geometry": {"coordinates":[74.486,29.299428],"type":"Point"}
}