{
  "type": "Feature",
  "properties": {
    "iso:country":"IN",
    "ks:ks_name":"Nilerat",
    "ks:ks_pop":1324,
    "ks:ks_type":"VILLAGE",
    "ks:ks_uagg_main":0,
    "name:eng_x_preferred":[
        "Nilerat"
    ],
    "wof:name":"Nilerat",
    "wof:placetype":"neighbourhood",
    "wof:population":1324
},
  "geometry": {"coordinates":[88.30985099999999,21.986806],"type":"Point"}
}