{
  "type": "Feature",
  "properties": {
    "iso:country":"IN",
    "ks:ks_name":"Chilliputtu",
    "ks:ks_pop":19,
    "ks:ks_type":"HABITATION",
    "name:eng_x_preferred":[
        "Chilliputtu"
    ],
    "wof:name":"Chilliputtu",
    "wof:placetype":"locality",
    "wof:population":19
},
  "geometry": {"coordinates":[82.501057,18.409213],"type":"Point"}
}