{
  "type": "Feature",
  "properties": {
    "iso:country":"IN",
    "ks:ks_alt_nam":"HANAKRAI PARA",
    "ks:ks_name":"Hanakrai Para",
    "ks:ks_pop":25,
    "ks:ks_type":"HABITATION",
    "name:eng_x_preferred":[
        "Hanakrai Para"
    ],
    "wof:name":"Hanakrai Para",
    "wof:placetype":"locality",
    "wof:population":25
},
  "geometry": {"coordinates":[91.376413,23.660141],"type":"Point"}
}