{
  "type": "Feature",
  "properties": {
    "iso:country":"IN",
    "ks:ks_name":"Thambankadavu",
    "ks:ks_pop":1938,
    "ks:ks_type":"HABITATION",
    "name:eng_x_preferred":[
        "Thambankadavu"
    ],
    "wof:name":"Thambankadavu",
    "wof:placetype":"locality",
    "wof:population":1938
},
  "geometry": {"coordinates":[76.072751,10.442777],"type":"Point"}
}