{
  "type": "Feature",
  "properties": {
    "iso:country":"IN",
    "ks:ks_name":"Dhagaria",
    "ks:ks_pop":1307,
    "ks:ks_type":"VILLAGE",
    "name:eng_x_preferred":[
        "Dhagaria"
    ],
    "wof:name":"Dhagaria",
    "wof:placetype":"locality",
    "wof:population":1307
},
  "geometry": {"coordinates":[87.50719100000001,23.247998],"type":"Point"}
}