{
  "type": "Feature",
  "properties": {
    "iso:country":"IN",
    "ks:ks_name":"Simaldhab",
    "ks:ks_pop":182,
    "ks:ks_type":"VILLAGE",
    "name:eng_x_preferred":[
        "Simaldhab"
    ],
    "wof:name":"Simaldhab",
    "wof:placetype":"locality",
    "wof:population":182
},
  "geometry": {"coordinates":[87.38659699999999,24.86087],"type":"Point"}
}