{
  "type": "Feature",
  "properties": {
    "iso:country":"IN",
    "ks:ks_name":"Dhangarwadi",
    "ks:ks_pop":427,
    "ks:ks_type":"HABITATION",
    "name:eng_x_preferred":[
        "Dhangarwadi"
    ],
    "wof:name":"Dhangarwadi",
    "wof:placetype":"locality",
    "wof:population":427
},
  "geometry": {"coordinates":[75.21730599999999,20.457266],"type":"Point"}
}