{
  "type": "Feature",
  "properties": {
    "iso:country":"IN",
    "name:ara_x_preferred":[
        "\u062a\u064a\u0644\u0648\u062b"
    ],
    "name:ben_bn_x_preferred":[
        "\u099f\u09bf\u09b2\u09cb\u09a5"
    ],
    "name:ben_in_x_preferred":[
        "\u099f\u09bf\u09b2\u09cb\u09a5"
    ],
    "name:eng_x_preferred":[
        "Tiloth"
    ],
    "name:guj_x_preferred":[
        "\u0aa4\u0abf\u0ab2\u0acb\u0aa5"
    ],
    "name:hin_x_preferred":[
        "\u0924\u093f\u0932\u094b\u0925"
    ],
    "name:kan_x_preferred":[
        "\u0ca4\u0cbf\u0cb2\u0ccb\u0ca4\u0ccd"
    ],
    "name:mal_x_preferred":[
        "\u0d24\u0d3f\u0d32\u0d4b\u0d24\u0d4d\u0d24\u0d4d"
    ],
    "name:mar_x_preferred":[
        "\u091f\u093f\u0932\u094b\u0925"
    ],
    "name:pan_x_preferred":[
        "\u0a1f\u0a3f\u0a32\u0a4c\u0a25"
    ],
    "name:tam_x_preferred":[
        "\u0ba4\u0bbf\u0bb2\u0bcb\u0ba4\u0bcd"
    ],
    "name:tel_x_preferred":[
        "\u0c1f\u0c3f\u0c32\u0c4b\u0c24\u0c4d"
    ],
    "name:urd_x_preferred":[
        "\u0679\u06cc\u0644\u0648\u062a\u06be"
    ],
    "qs:gn_adm0_cc":"IN",
    "qs:gn_local":1253628,
    "qs:gn_nam_loc":"Uttarkashi, Uttarkashi, Uttarakhand, IN",
    "qs:gn_namadm1":"39",
    "qs:local_max":74,
    "qs:local_sum":74,
    "qs:localhoods":1,
    "qs:name":"Tiloth",
    "qs:name_adm0":"India",
    "qs:name_adm1":"Uttarakhand",
    "qs:name_adm2":"Uttarkashi",
    "qs:name_local":"Uttarkashi",
    "qs:photo_max":41,
    "qs:photo_sum":74,
    "qs:placetype":"Suburb",
    "qs:quad_count":5,
    "qs:woe_adm0":23424848,
    "qs:woe_adm1":20070462,
    "qs:woe_adm2":12586793,
    "qs:woe_lau":0,
    "qs:woe_local":2287943,
    "qs:woe_ver":"7.10.0",
    "wof:lang":[
        "eng"
    ],
    "wof:name":"Tiloth",
    "wof:placetype":"neighbourhood"
},
  "geometry": {"coordinates":[78.44811799999999,30.727304],"type":"Point"}
}