{
  "type": "Feature",
  "properties": {
    "gn:admin1_code":"35.0",
    "gn:admin2_code":"455.0",
    "gn:asciiname":"Chikhalmau",
    "gn:country_code":"IN",
    "gn:dem":795,
    "gn:feature_class":"P",
    "gn:feature_code":"PPL",
    "gn:name":"Ch\u012bkhalmau",
    "gn:population":0,
    "gn:timezone":"Asia/Kolkata",
    "iso:country":"IN",
    "wof:name":"Chikhalmau",
    "wof:placetype":"locality"
},
  "geometry": {"coordinates":[78.59702,22.21425],"type":"Point"}
}