{
  "type": "Feature",
  "properties": {
    "iso:country":"IN",
    "ks:ks_name":"N. Murli",
    "ks:ks_pop":263,
    "ks:ks_type":"HABITATION",
    "ks:ks_uagg_main":0,
    "name:eng_x_preferred":[
        "N. Murli"
    ],
    "wof:name":"N. Murli",
    "wof:placetype":"neighbourhood",
    "wof:population":263
},
  "geometry": {"coordinates":[78.560554,27.444831],"type":"Point"}
}