{
  "type": "Feature",
  "properties": {
    "iso:country":"IN",
    "ks:ks_name":"Belabadan Milik",
    "ks:ks_pop":127,
    "ks:ks_type":"VILLAGE",
    "ks:ks_uagg_main":0,
    "name:eng_x_preferred":[
        "Belabadan Milik"
    ],
    "wof:name":"Belabadan Milik",
    "wof:placetype":"neighbourhood",
    "wof:population":127
},
  "geometry": {"coordinates":[87.118779,25.926304],"type":"Point"}
}