{
  "type": "Feature",
  "properties": {
    "gn:admin1_code":"37",
    "gn:admin2_code":"408.0",
    "gn:asciiname":"Kandari",
    "gn:country_code":"IN",
    "gn:dem":370,
    "gn:feature_class":"P",
    "gn:feature_code":"PPL",
    "gn:name":"Kand\u0101ri",
    "gn:population":0,
    "gn:timezone":"Asia/Kolkata",
    "iso:country":"IN",
    "name:ben_x_preferred":[
        "\u0995\u09be\u09a8\u09cd\u09a6\u09be\u09b0\u09bf"
    ],
    "name:bpy_x_preferred":[
        "\u0995\u09be\u09a8\u09cd\u09a6\u09be\u09b0\u09bf"
    ],
    "name:ita_x_preferred":[
        "Kandari"
    ],
    "name:msa_x_preferred":[
        "Kandari"
    ],
    "name:new_x_preferred":[
        "\u0915\u0928\u094d\u0926\u0930\u0940"
    ],
    "name:nld_x_preferred":[
        "Kandari"
    ],
    "name:por_x_preferred":[
        "Kandari"
    ],
    "name:vie_x_preferred":[
        "Kandari"
    ],
    "name:zho_x_preferred":[
        "\u574e\u8fbe\u91cc"
    ],
    "wof:name":"Kandari",
    "wof:placetype":"locality"
},
  "geometry": {"coordinates":[80.71706999999998,20.48767],"type":"Point"}
}