{
  "type": "Feature",
  "properties": {
    "gn:admin1_code":"37",
    "gn:admin2_code":"410.0",
    "gn:asciiname":"Amdi",
    "gn:country_code":"IN",
    "gn:dem":340,
    "gn:feature_class":"P",
    "gn:feature_code":"PPL",
    "gn:name":"\u0100mdi",
    "gn:population":0,
    "gn:timezone":"Asia/Kolkata",
    "iso:country":"IN",
    "ks:ks_alt_nam":"\u0100mdi",
    "ks:ks_name":"Amdi",
    "ks:ks_type":"VILLAGE",
    "ks:ks_uagg_main":0,
    "name:eng_x_preferred":[
        "Amdi"
    ],
    "name:eng_x_variant":[
        "\u0100mdi"
    ],
    "wof:name":"Amdi",
    "wof:placetype":"neighbourhood"
},
  "geometry": {"coordinates":[82.050444,20.633207],"type":"Point"}
}