{
  "type": "Feature",
  "properties": {
    "gn:admin1_code":"11.0",
    "gn:asciiname":"Beonla",
    "gn:country_code":"IN",
    "gn:dem":1003,
    "gn:feature_class":"P",
    "gn:feature_code":"PPL",
    "gn:name":"Beonla",
    "gn:population":0,
    "gn:timezone":"Asia/Kolkata",
    "iso:country":"IN",
    "wof:name":"Beonla",
    "wof:placetype":"locality"
},
  "geometry": {"coordinates":[77.15512,30.66704],"type":"Point"}
}