{
  "type": "Feature",
  "properties": {
    "gn:admin1_code":"35",
    "gn:admin2_code":"436.0",
    "gn:asciiname":"Tilawad",
    "gn:country_code":"IN",
    "gn:dem":467,
    "gn:feature_class":"P",
    "gn:feature_code":"PPL",
    "gn:name":"Tilawad",
    "gn:population":0,
    "gn:timezone":"Asia/Kolkata",
    "iso:country":"IN",
    "name:und_x_variant":[
        "Til\u0101wad"
    ],
    "wof:name":"Tilawad",
    "wof:placetype":"locality"
},
  "geometry": {"coordinates":[76.70456,23.20828],"type":"Point"}
}