{
  "type": "Feature",
  "properties": {
    "gn:admin1_code":"19.0",
    "gn:admin2_code":"574.0",
    "gn:asciiname":"Kallahalli",
    "gn:country_code":"IN",
    "gn:dem":867,
    "gn:feature_class":"P",
    "gn:feature_code":"PPL",
    "gn:name":"Kallahalli",
    "gn:population":0,
    "gn:timezone":"Asia/Kolkata",
    "iso:country":"IN",
    "wof:name":"Kallahalli",
    "wof:placetype":"locality"
},
  "geometry": {"coordinates":[76.16575,13.2886],"type":"Point"}
}