{
  "type": "Feature",
  "properties": {
    "iso:country":"IN",
    "ks:ks_name":"Pakri Jagarnath",
    "ks:ks_pop":260,
    "ks:ks_type":"VILLAGE",
    "ks:ks_uagg_main":0,
    "name:eng_x_preferred":[
        "Pakri Jagarnath"
    ],
    "wof:name":"Pakri Jagarnath",
    "wof:placetype":"neighbourhood",
    "wof:population":260
},
  "geometry": {"coordinates":[85.280974,26.318405],"type":"Point"}
}