{
  "type": "Feature",
  "properties": {
    "iso:country":"IN",
    "qs:name":"Bharathipuram",
    "qs:name_adm0":"India",
    "qs:name_adm1":"Tamil Nadu",
    "qs:photos":29,
    "qs:photos_1k":6,
    "qs:photos_9k":1,
    "qs:photos_9r":2,
    "qs:photos_all":29,
    "qs:photos_sr":2,
    "qs:placetype":"Suburb",
    "qs:pop_sr":"0",
    "wof:name":"Bharathipuram",
    "wof:placetype":"neighbourhood"
},
  "geometry": {"coordinates":[80.220665,13.079018],"type":"Point"}
}