{
  "type": "Feature",
  "properties": {
    "iso:country":"IN",
    "ks:ks_name":"Panve",
    "ks:ks_pop":434,
    "ks:ks_type":"VILLAGE",
    "name:eng_x_preferred":[
        "Panve"
    ],
    "wof:name":"Panve",
    "wof:placetype":"locality",
    "wof:population":434
},
  "geometry": {"coordinates":[73.116462,18.058453],"type":"Point"}
}