{
  "type": "Feature",
  "properties": {
    "iso:country":"IN",
    "ks:ks_alt_nam":"THAKURAN",
    "ks:ks_name":"Thakuran",
    "ks:ks_pop":417,
    "ks:ks_type":"HABITATION",
    "name:eng_x_preferred":[
        "Thakuran"
    ],
    "wof:name":"Thakuran",
    "wof:placetype":"locality",
    "wof:population":417
},
  "geometry": {"coordinates":[82.14688,25.3556],"type":"Point"}
}