{
  "type": "Feature",
  "properties": {
    "iso:country":"IN",
    "ks:ks_name":"Kalikapur",
    "ks:ks_pop":1222,
    "ks:ks_type":"VILLAGE",
    "name:eng_x_preferred":[
        "Kalikapur"
    ],
    "wof:name":"Kalikapur",
    "wof:placetype":"locality",
    "wof:population":1222
},
  "geometry": {"coordinates":[87.29190800000001,21.702599],"type":"Point"}
}