{
  "type": "Feature",
  "properties": {
    "iso:country":"IN",
    "ks:ks_alt_nam":"R\u0101mpur Bakli",
    "ks:ks_name":"Rampur Bakli",
    "ks:ks_type":"VILLAGE",
    "ks:ks_uagg_main":0,
    "name:eng_x_preferred":[
        "Rampur Bakli"
    ],
    "name:eng_x_variant":[
        "R\u0101mpur Bakli"
    ],
    "wof:name":"Rampur Bakli",
    "wof:placetype":"neighbourhood"
},
  "geometry": {"coordinates":[78.15188000000001,29.376833],"type":"Point"}
}