{
  "type": "Feature",
  "properties": {
    "iso:country":"IN",
    "ks:ks_name":"Prab Tola",
    "ks:ks_pop":100,
    "ks:ks_type":"HABITATION",
    "name:eng_x_preferred":[
        "Prab Tola"
    ],
    "wof:name":"Prab Tola",
    "wof:placetype":"locality",
    "wof:population":100
},
  "geometry": {"coordinates":[84.49878699999999,27.10745],"type":"Point"}
}