{
  "type": "Feature",
  "properties": {
    "iso:country":"IN",
    "ks:ks_name":"Singaria Beel",
    "ks:ks_pop":77,
    "ks:ks_type":"VILLAGE",
    "name:eng_x_preferred":[
        "Singaria Beel"
    ],
    "wof:name":"Singaria Beel",
    "wof:placetype":"locality",
    "wof:population":77
},
  "geometry": {"coordinates":[94.073312,26.920391],"type":"Point"}
}