{
  "type": "Feature",
  "properties": {
    "gn:admin1_code":"39.0",
    "gn:admin2_code":"64.0",
    "gn:asciiname":"Pokhri",
    "gn:country_code":"IN",
    "gn:dem":1611,
    "gn:feature_class":"P",
    "gn:feature_code":"PPL",
    "gn:name":"Pokhri",
    "gn:population":0,
    "gn:timezone":"Asia/Kolkata",
    "iso:country":"IN",
    "ks:ks_name":"Pokhari",
    "ks:ks_pop":58,
    "ks:ks_type":"VILLAGE",
    "name:eng_x_preferred":[
        "Pokhari"
    ],
    "name:eng_x_variant":[
        "Pokhri"
    ],
    "wof:name":"Pokhari",
    "wof:placetype":"locality",
    "wof:population":58
},
  "geometry": {"coordinates":[79.507498,29.770606],"type":"Point"}
}