{
  "type": "Feature",
  "properties": {
    "iso:country":"IN",
    "ks:ks_name":"Chimatawasti",
    "ks:ks_pop":307,
    "ks:ks_type":"HABITATION",
    "name:eng_x_preferred":[
        "Chimatawasti"
    ],
    "wof:name":"Chimatawasti",
    "wof:placetype":"locality",
    "wof:population":307
},
  "geometry": {"coordinates":[74.07719899999999,19.091227],"type":"Point"}
}