{
  "type": "Feature",
  "properties": {
    "iso:country":"IN",
    "ks:ks_alt_nam":"PATKAULI",
    "ks:ks_name":"Patkauli",
    "ks:ks_pop":59,
    "ks:ks_type":"HABITATION",
    "name:eng_x_preferred":[
        "Patkauli"
    ],
    "wof:name":"Patkauli",
    "wof:placetype":"locality",
    "wof:population":59
},
  "geometry": {"coordinates":[82.314019,26.307922],"type":"Point"}
}