{
  "type": "Feature",
  "properties": {
    "iso:country":"IN",
    "ks:ks_name":"Chatotangvita",
    "ks:ks_pop":166,
    "ks:ks_type":"HABITATION",
    "name:eng_x_preferred":[
        "Chatotangvita"
    ],
    "wof:name":"Chatotangvita",
    "wof:placetype":"locality",
    "wof:population":166
},
  "geometry": {"coordinates":[90.22777600000001,26.126567],"type":"Point"}
}