{
  "type": "Feature",
  "properties": {
    "gn:admin1_code":"37",
    "gn:admin2_code":"409.0",
    "gn:asciiname":"Nawagaon Kalan",
    "gn:country_code":"IN",
    "gn:dem":295,
    "gn:feature_class":"P",
    "gn:feature_code":"PPL",
    "gn:name":"Naw\u0101gaon Kal\u0101n",
    "gn:population":0,
    "gn:timezone":"Asia/Kolkata",
    "iso:country":"IN",
    "ks:ks_alt_nam":"Naw\u0101gaon Kal\u0101n",
    "ks:ks_name":"Nawagaon Kalan",
    "ks:ks_type":"VILLAGE",
    "ks:ks_uagg_main":0,
    "name:eng_x_preferred":[
        "Nawagaon Kalan"
    ],
    "name:eng_x_variant":[
        "Naw\u0101gaon Kal\u0101n"
    ],
    "wof:name":"Nawagaon Kalan",
    "wof:placetype":"neighbourhood"
},
  "geometry": {"coordinates":[81.50218599999999,21.983078],"type":"Point"}
}