{
  "type": "Feature",
  "properties": {
    "gn:admin1_code":"36",
    "gn:admin2_code":"178.0",
    "gn:asciiname":"Puraina",
    "gn:country_code":"IN",
    "gn:dem":91,
    "gn:feature_class":"P",
    "gn:feature_code":"PPL",
    "gn:name":"Puraina",
    "gn:population":0,
    "gn:timezone":"Asia/Kolkata",
    "iso:country":"IN",
    "ks:ks_name":"Puraina",
    "ks:ks_pop":500,
    "ks:ks_type":"HABITATION",
    "ks:ks_uagg_main":0,
    "name:ceb_x_preferred":[
        "Puraina"
    ],
    "name:eng_x_preferred":[
        "Puraina"
    ],
    "name:mai_x_preferred":[
        "\u092a\u0941\u0930\u0948\u0928\u093e"
    ],
    "name:msa_x_preferred":[
        "Puraina"
    ],
    "name:nep_x_preferred":[
        "\u092a\u0941\u0930\u0948\u0928\u093e"
    ],
    "name:new_x_preferred":[
        "\u092a\u0941\u0930\u0948\u0928\u093e"
    ],
    "name:pol_x_preferred":[
        "Puraina"
    ],
    "wof:name":"Puraina",
    "wof:placetype":"neighbourhood",
    "wof:population":500
},
  "geometry": {"coordinates":[82.80671599999999,26.327042],"type":"Point"}
}