{
  "type": "Feature",
  "properties": {
    "iso:country":"IN",
    "ks:ks_name":"Thenapparamba",
    "ks:ks_pop":693,
    "ks:ks_type":"HABITATION",
    "name:eng_x_preferred":[
        "Thenapparamba"
    ],
    "wof:name":"Thenapparamba",
    "wof:placetype":"locality",
    "wof:population":693
},
  "geometry": {"coordinates":[76.144395,10.913747],"type":"Point"}
}