{
  "type": "Feature",
  "properties": {
    "iso:country":"IN",
    "ks:ks_name":"Edavazhikadavu",
    "ks:ks_pop":1444,
    "ks:ks_type":"HABITATION",
    "ks:ks_uagg_main":0,
    "name:eng_x_preferred":[
        "Edavazhikadavu"
    ],
    "wof:name":"Edavazhikadavu",
    "wof:placetype":"neighbourhood",
    "wof:population":1444
},
  "geometry": {"coordinates":[75.966221,11.265837],"type":"Point"}
}