{
  "type": "Feature",
  "properties": {
    "gn:gn_country":"IN",
    "gn:gn_fcode":"PPL",
    "gn:gn_pop":52690,
    "gn:population":52690,
    "iso:country":"IN",
    "name:ben_x_preferred":[
        "\u0986\u09ae\u09b2\u09be\u09aa\u09c1\u09b0\u09be\u09ae"
    ],
    "name:bpy_x_preferred":[
        "\u0986\u09ae\u09b2\u09aa\u09c1\u09b0\u09ae"
    ],
    "name:deu_x_preferred":[
        "Amalapuram"
    ],
    "name:eng_x_preferred":[
        "Amalapuram"
    ],
    "name:fas_x_preferred":[
        "\u0627\u0645\u0627\u0644\u0627\u067e\u0648\u0631\u0627\u0645"
    ],
    "name:fra_x_preferred":[
        "Amalapuram"
    ],
    "name:guj_x_preferred":[
        "\u0a85\u0aae\u0ab2\u0abe\u0aaa\u0ac1\u0ab0\u0aae"
    ],
    "name:hin_x_preferred":[
        "\u0905\u092e\u0932\u093e\u092a\u0941\u0930\u092e"
    ],
    "name:ita_x_preferred":[
        "Amalapuram"
    ],
    "name:jpn_x_preferred":[
        "\u30a2\u30de\u30e9\u30d7\u30e9\u30fc\u30e0"
    ],
    "name:kan_x_preferred":[
        "\u0c85\u0cae\u0cb2\u0cbe\u0caa\u0cc1\u0cb0\u0cae\u0ccd"
    ],
    "name:kor_x_preferred":[
        "\uc544\ub9d0\ub77c\ud478\ub78c"
    ],
    "name:mal_x_preferred":[
        "\u0d05\u0d2e\u0d32\u0d3e\u0d2a\u0d41\u0d30\u0d02"
    ],
    "name:min_x_preferred":[
        "Amalapuram"
    ],
    "name:mlg_x_preferred":[
        "Amalapuram"
    ],
    "name:msa_x_preferred":[
        "Amalapuram"
    ],
    "name:nep_x_preferred":[
        "\u0905\u092e\u0932\u093e\u092a\u0941\u0930\u092e"
    ],
    "name:new_x_preferred":[
        "\u0905\u092e\u0932\u092a\u0941\u0930\u092e"
    ],
    "name:nld_x_preferred":[
        "Amalapuram"
    ],
    "name:ori_x_preferred":[
        "\u0b06\u0b2e\u0b32\u0b3e\u0b2a\u0b41\u0b30\u0b2e"
    ],
    "name:pan_x_preferred":[
        "\u0a05\u0a2e\u0a32\u0a3e\u0a2a\u0a41\u0a30\u0a2e"
    ],
    "name:pnb_x_preferred":[
        "\u0627\u0645\u0627\u0644\u0627\u067e\u0648\u0631\u0645"
    ],
    "name:por_x_preferred":[
        "Amalapuram"
    ],
    "name:rus_x_preferred":[
        "\u0410\u043c\u0430\u043b\u0430\u043f\u0443\u0440\u0430\u043c"
    ],
    "name:spa_x_preferred":[
        "Amalapuram"
    ],
    "name:swe_x_preferred":[
        "Amal\u0101puram"
    ],
    "name:tam_x_preferred":[
        "\u0b85\u0bae\u0bb2\u0baa\u0bc1\u0bb0\u0bae\u0bcd"
    ],
    "name:tel_x_preferred":[
        "\u0c05\u0c2e\u0c32\u0c3e\u0c2a\u0c41\u0c30\u0c02"
    ],
    "name:unk_x_variant":[
        "Amal\u0101puram"
    ],
    "name:urd_x_preferred":[
        "\u0627\u0645\u0627\u0644\u0627\u067e\u0648\u0631\u0645"
    ],
    "name:vie_x_preferred":[
        "Amalapuram"
    ],
    "name:zho_x_preferred":[
        "\u963f\u9a6c\u62c9\u666e\u62c9\u59c6"
    ],
    "qs_pg:aaroncc":"IN",
    "qs_pg:gn_country":"IN",
    "qs_pg:gn_fcode":"PPL",
    "qs_pg:gn_pop":52690,
    "qs_pg:name":"Malkapuram",
    "qs_pg:name_adm0":"India",
    "qs_pg:name_adm1":"Andhra Pradesh",
    "qs_pg:photos_9r":0,
    "qs_pg:photos_sr":0,
    "qs_pg:pop_sr":8,
    "qs_pg:qs_pg_placetype":"locality",
    "qs_pg:qs_pg_placetype_gp":"Town",
    "qs_pg:woe_adm0":23424848,
    "woe:adm0_id":23424848,
    "woe:name_adm0":"India",
    "woe:name_adm1":"Andhra Pradesh",
    "woe:placetype":"Town",
    "wof:name":"Malkapuram",
    "wof:placetype":"locality",
    "wof:population":52690
},
  "geometry": {"coordinates":[82.00609,16.57868],"type":"Point"}
}