{
  "type": "Feature",
  "properties": {
    "iso:country":"IN",
    "ks:ks_name":"Hinotiya",
    "ks:ks_pop":1453,
    "ks:ks_type":"HABITATION",
    "name:eng_x_preferred":[
        "Hinotiya"
    ],
    "wof:name":"Hinotiya",
    "wof:placetype":"locality",
    "wof:population":1453
},
  "geometry": {"coordinates":[77.54158,23.580563],"type":"Point"}
}