{
  "type": "Feature",
  "properties": {
    "iso:country":"IN",
    "ks:ks_alt_nam":"SUBHANKERPUR",
    "ks:ks_name":"Subhankerpur",
    "ks:ks_pop":591,
    "ks:ks_type":"HABITATION",
    "name:eng_x_preferred":[
        "Subhankerpur"
    ],
    "wof:name":"Subhankerpur",
    "wof:placetype":"locality",
    "wof:population":591
},
  "geometry": {"coordinates":[86.11503,26.248127],"type":"Point"}
}