{
  "type": "Feature",
  "properties": {
    "iso:country":"IN",
    "ks:ks_name":"Fakirdanga",
    "ks:ks_pop":1050,
    "ks:ks_type":"HABITATION",
    "ks:ks_uagg_main":0,
    "name:eng_x_preferred":[
        "Fakirdanga"
    ],
    "wof:name":"Fakirdanga",
    "wof:placetype":"neighbourhood",
    "wof:population":1050
},
  "geometry": {"coordinates":[87.863259,22.875892],"type":"Point"}
}