{
  "type": "Feature",
  "properties": {
    "iso:country":"IN",
    "ks:ks_name":"Kandiga",
    "ks:ks_pop":224,
    "ks:ks_type":"HABITATION",
    "name:eng_x_preferred":[
        "Kandiga"
    ],
    "wof:name":"Kandiga",
    "wof:placetype":"locality",
    "wof:population":224
},
  "geometry": {"coordinates":[75.049029,13.008462],"type":"Point"}
}