{
  "type": "Feature",
  "properties": {
    "iso:country":"IN",
    "ks:ks_name":"Guddeyangady Kanthavara",
    "ks:ks_pop":196,
    "ks:ks_type":"HABITATION",
    "name:eng_x_preferred":[
        "Guddeyangady Kanthavara"
    ],
    "wof:name":"Guddeyangady Kanthavara",
    "wof:placetype":"locality",
    "wof:population":196
},
  "geometry": {"coordinates":[74.946206,13.143108],"type":"Point"}
}