{
  "type": "Feature",
  "properties": {
    "gn:admin1_code":"36",
    "gn:admin2_code":"172.0",
    "gn:asciiname":"Bandi",
    "gn:country_code":"IN",
    "gn:dem":119,
    "gn:feature_class":"P",
    "gn:feature_code":"PPL",
    "gn:name":"Bandi",
    "gn:population":0,
    "gn:timezone":"Asia/Kolkata",
    "iso:country":"IN",
    "name:ceb_x_preferred":[
        "Bandi"
    ],
    "name:deu_x_preferred":[
        "Bandi"
    ],
    "name:fra_x_preferred":[
        "Bandi"
    ],
    "name:ita_x_preferred":[
        "Bandi"
    ],
    "name:slv_x_preferred":[
        "Bandi"
    ],
    "name:swe_x_preferred":[
        "Bandi"
    ],
    "name:vie_x_preferred":[
        "Bandi"
    ],
    "wof:name":"Bandi",
    "wof:placetype":"neighbourhood"
},
  "geometry": {"coordinates":[80.67254,25.92235],"type":"Point"}
}