{
  "type": "Feature",
  "properties": {
    "gn:admin1_code":"34",
    "gn:admin2_code":"234.0",
    "gn:asciiname":"Madhkupia",
    "gn:country_code":"IN",
    "gn:dem":153,
    "gn:feature_class":"P",
    "gn:feature_code":"PPL",
    "gn:name":"Madhkupia",
    "gn:population":0,
    "gn:timezone":"Asia/Kolkata",
    "iso:country":"IN",
    "wof:name":"Madhkupia",
    "wof:placetype":"locality"
},
  "geometry": {"coordinates":[83.64397,24.52448],"type":"Point"}
}