{
  "type": "Feature",
  "properties": {
    "iso:country":"IN",
    "ks:ks_name":"Deehpurwa",
    "ks:ks_pop":115,
    "ks:ks_type":"HABITATION",
    "name:eng_x_preferred":[
        "Deehpurwa"
    ],
    "wof:name":"Deehpurwa",
    "wof:placetype":"locality",
    "wof:population":115
},
  "geometry": {"coordinates":[80.811077,27.663146],"type":"Point"}
}