{
  "type": "Feature",
  "properties": {
    "iso:country":"IN",
    "ks:ks_name":"Gundanapalli",
    "ks:ks_pop":64,
    "ks:ks_type":"VILLAGE",
    "name:eng_x_preferred":[
        "Gundanapalli"
    ],
    "wof:name":"Gundanapalli",
    "wof:placetype":"locality",
    "wof:population":64
},
  "geometry": {"coordinates":[75.73844699999999,16.380224],"type":"Point"}
}