{
  "type": "Feature",
  "properties": {
    "iso:country":"IN",
    "ks:ks_alt_nam":"H\u012br\u0101pur",
    "ks:ks_name":"Hirapur",
    "ks:ks_pop":0,
    "ks:ks_type":"VILLAGE",
    "name:eng_x_preferred":[
        "Hirapur"
    ],
    "name:eng_x_variant":[
        "H\u012br\u0101pur"
    ],
    "wof:name":"Hirapur",
    "wof:placetype":"locality",
    "wof:population":0
},
  "geometry": {"coordinates":[78.86793400000001,24.09566],"type":"Point"}
}