{
  "type": "Feature",
  "properties": {
    "iso:country":"IN",
    "ks:ks_name":"Nayapara",
    "ks:ks_pop":231,
    "ks:ks_type":"HABITATION",
    "name:eng_x_preferred":[
        "Nayapara"
    ],
    "wof:name":"Nayapara",
    "wof:placetype":"locality",
    "wof:population":231
},
  "geometry": {"coordinates":[81.91319799999999,19.724837],"type":"Point"}
}