{
  "type": "Feature",
  "properties": {
    "gn:admin1_code":"36",
    "gn:admin2_code":"178.0",
    "gn:asciiname":"Chandaini",
    "gn:country_code":"IN",
    "gn:dem":96,
    "gn:feature_class":"P",
    "gn:feature_code":"PPL",
    "gn:name":"Chandaini",
    "gn:population":0,
    "gn:timezone":"Asia/Kolkata",
    "iso:country":"IN",
    "ks:ks_name":"Chandaini",
    "ks:ks_pop":956,
    "ks:ks_type":"VILLAGE",
    "name:eng_x_preferred":[
        "Chandaini"
    ],
    "wof:name":"Chandaini",
    "wof:placetype":"locality",
    "wof:population":956
},
  "geometry": {"coordinates":[82.536136,26.523604],"type":"Point"}
}