{
  "type": "Feature",
  "properties": {
    "iso:country":"IN",
    "ks:ks_alt_nam":"13 JSN",
    "ks:ks_name":"13 Jsn",
    "ks:ks_pop":17,
    "ks:ks_type":"HABITATION",
    "name:eng_x_preferred":[
        "13 Jsn"
    ],
    "wof:name":"13 Jsn",
    "wof:placetype":"locality",
    "wof:population":17
},
  "geometry": {"coordinates":[74.91521899999999,29.288281],"type":"Point"}
}