{
  "type": "Feature",
  "properties": {
    "gn:admin1_code":"09",
    "gn:admin2_code":"488.0",
    "gn:asciiname":"Vengni",
    "gn:country_code":"IN",
    "gn:dem":12,
    "gn:feature_class":"P",
    "gn:feature_code":"PPL",
    "gn:name":"Vengni",
    "gn:population":0,
    "gn:timezone":"Asia/Kolkata",
    "iso:country":"IN",
    "name:und_x_variant":[
        "Vingni",
        "Vengni"
    ],
    "wof:name":"Vengni",
    "wof:placetype":"locality"
},
  "geometry": {"coordinates":[72.71353000000001,21.68624],"type":"Point"}
}