{
  "type": "Feature",
  "properties": {
    "iso:country":"IN",
    "ks:ks_alt_nam":"Ganyanaik tanda",
    "ks:ks_name":"Ganyanaik Tanda",
    "ks:ks_pop":93,
    "ks:ks_type":"HABITATION",
    "name:eng_x_preferred":[
        "Ganyanaik Tanda"
    ],
    "wof:name":"Ganyanaik Tanda",
    "wof:placetype":"locality",
    "wof:population":93
},
  "geometry": {"coordinates":[78.20964499999999,16.252808],"type":"Point"}
}