{
  "type": "Feature",
  "properties": {
    "iso:country":"IN",
    "ks:ks_alt_nam":"BANKAL",
    "ks:ks_name":"Bankal",
    "ks:ks_pop":206,
    "ks:ks_type":"HABITATION",
    "ks:ks_uagg_main":0,
    "name:eng_x_preferred":[
        "Bankal"
    ],
    "wof:name":"Bankal",
    "wof:placetype":"neighbourhood",
    "wof:population":206
},
  "geometry": {"coordinates":[86.640625,25.619163],"type":"Point"}
}