{
  "type": "Feature",
  "properties": {
    "iso:country":"IN",
    "ks:ks_alt_nam":"Pure Mitai pandey",
    "ks:ks_name":"Pure Mitai Pandey",
    "ks:ks_pop":181,
    "ks:ks_type":"HABITATION",
    "name:eng_x_preferred":[
        "Pure Mitai Pandey"
    ],
    "wof:name":"Pure Mitai Pandey",
    "wof:placetype":"locality",
    "wof:population":181
},
  "geometry": {"coordinates":[81.874674,26.372808],"type":"Point"}
}