{
  "type": "Feature",
  "properties": {
    "iso:country":"IN",
    "ks:ks_name":"Kadam Beria",
    "ks:ks_pop":691,
    "ks:ks_type":"VILLAGE",
    "name:eng_x_preferred":[
        "Kadam Beria"
    ],
    "wof:name":"Kadam Beria",
    "wof:placetype":"locality",
    "wof:population":691
},
  "geometry": {"coordinates":[86.813033,22.992089],"type":"Point"}
}