{
  "type": "Feature",
  "properties": {
    "iso:country":"IN",
    "ks:ks_name":"Kadamdiha",
    "ks:ks_pop":133,
    "ks:ks_type":"VILLAGE",
    "name:eng_x_preferred":[
        "Kadamdiha"
    ],
    "wof:name":"Kadamdiha",
    "wof:placetype":"locality",
    "wof:population":133
},
  "geometry": {"coordinates":[86.32267899999999,22.025438],"type":"Point"}
}