{
  "type": "Feature",
  "properties": {
    "gn:admin1_code":"19.0",
    "gn:admin2_code":"563.0",
    "gn:asciiname":"Kodlagadde",
    "gn:country_code":"IN",
    "gn:dem":81,
    "gn:feature_class":"P",
    "gn:feature_code":"PPL",
    "gn:name":"Kodlagadde",
    "gn:population":0,
    "gn:timezone":"Asia/Kolkata",
    "iso:country":"IN",
    "ks:ks_name":"Kodlagadde",
    "ks:ks_pop":421,
    "ks:ks_type":"VILLAGE",
    "name:eng_x_preferred":[
        "Kodlagadde"
    ],
    "wof:name":"Kodlagadde",
    "wof:placetype":"locality",
    "wof:population":421
},
  "geometry": {"coordinates":[74.597632,14.829768],"type":"Point"}
}