{
  "type": "Feature",
  "properties": {
    "iso:country":"IN",
    "ks:ks_name":"Taragar",
    "ks:ks_pop":64,
    "ks:ks_type":"HABITATION",
    "name:eng_x_preferred":[
        "Taragar"
    ],
    "wof:name":"Taragar",
    "wof:placetype":"locality",
    "wof:population":64
},
  "geometry": {"coordinates":[74.58223,14.893197],"type":"Point"}
}