{
  "type": "Feature",
  "properties": {
    "iso:country":"IN",
    "ks:ks_name":"Benidihwa",
    "ks:ks_pop":426,
    "ks:ks_type":"HABITATION",
    "name:eng_x_preferred":[
        "Benidihwa"
    ],
    "wof:name":"Benidihwa",
    "wof:placetype":"locality",
    "wof:population":426
},
  "geometry": {"coordinates":[82.008636,27.863468],"type":"Point"}
}