{
  "type": "Feature",
  "properties": {
    "iso:country":"IN",
    "ks:ks_name":"Maranayakana Halli",
    "ks:ks_pop":331,
    "ks:ks_type":"VILLAGE",
    "ks:ks_uagg_main":0,
    "name:eng_x_preferred":[
        "Maranayakana Halli"
    ],
    "wof:name":"Maranayakana Halli",
    "wof:placetype":"neighbourhood",
    "wof:population":331
},
  "geometry": {"coordinates":[77.64576,13.167658],"type":"Point"}
}