{
  "type": "Feature",
  "properties": {
    "gn:admin1_code":"11",
    "gn:admin2_code":"31.0",
    "gn:asciiname":"Duhgi Maithal",
    "gn:country_code":"IN",
    "gn:dem":694,
    "gn:feature_class":"P",
    "gn:feature_code":"PPL",
    "gn:name":"Duhgi Maithal",
    "gn:population":0,
    "gn:timezone":"Asia/Kolkata",
    "iso:country":"IN",
    "wof:name":"Duhgi Maithal",
    "wof:placetype":"locality"
},
  "geometry": {"coordinates":[76.73329,31.10704],"type":"Point"}
}