{
  "type": "Feature",
  "properties": {
    "gn:admin1_code":"35",
    "gn:admin2_code":"458.0",
    "gn:asciiname":"Kherli",
    "gn:country_code":"IN",
    "gn:dem":534,
    "gn:feature_class":"P",
    "gn:feature_code":"PPL",
    "gn:name":"Kherli",
    "gn:population":0,
    "gn:timezone":"Asia/Kolkata",
    "iso:country":"IN",
    "name:ben_x_preferred":[
        "\u0996\u09c7\u09b0\u09b2\u09bf"
    ],
    "name:bpy_x_preferred":[
        "\u0996\u09c7\u09b0\u09b2\u09bf"
    ],
    "name:ita_x_preferred":[
        "Kherli"
    ],
    "name:mlg_x_preferred":[
        "Kherli"
    ],
    "name:msa_x_preferred":[
        "Kherli"
    ],
    "name:new_x_preferred":[
        "\u0916\u0947\u0930\u094d\u0932\u0940"
    ],
    "name:por_x_preferred":[
        "Kherli"
    ],
    "name:und_x_variant":[
        "Govindpur"
    ],
    "name:vie_x_preferred":[
        "Kherli"
    ],
    "name:zho_x_preferred":[
        "\u51ef\u5c14\u5229"
    ],
    "wof:name":"Kherli",
    "wof:placetype":"locality"
},
  "geometry": {"coordinates":[77.33526999999999,24.18074],"type":"Point"}
}