{
  "type": "Feature",
  "properties": {
    "iso:country":"IN",
    "ks:ks_name":"Kurkal",
    "ks:ks_pop":211,
    "ks:ks_type":"HABITATION",
    "name:eng_x_preferred":[
        "Kurkal"
    ],
    "wof:name":"Kurkal",
    "wof:placetype":"locality",
    "wof:population":211
},
  "geometry": {"coordinates":[74.79172,13.222882],"type":"Point"}
}