{
  "type": "Feature",
  "properties": {
    "iso:country":"IN",
    "ks:ks_name":"Kuchawat",
    "ks:ks_pop":129,
    "ks:ks_type":"HABITATION",
    "name:eng_x_preferred":[
        "Kuchawat"
    ],
    "wof:name":"Kuchawat",
    "wof:placetype":"locality",
    "wof:population":129
},
  "geometry": {"coordinates":[81.643884,24.910328],"type":"Point"}
}