{
  "type": "Feature",
  "properties": {
    "iso:country":"IN",
    "ks:ks_alt_nam":"mnlinemanchikeri",
    "ks:ks_name":"Mnlinemanchikeri",
    "ks:ks_pop":90,
    "ks:ks_type":"HABITATION",
    "name:eng_x_preferred":[
        "Mnlinemanchikeri"
    ],
    "wof:name":"Mnlinemanchikeri",
    "wof:placetype":"locality",
    "wof:population":90
},
  "geometry": {"coordinates":[74.80927800000001,14.864114],"type":"Point"}
}