{
  "type": "Feature",
  "properties": {
    "iso:country":"IN",
    "ks:ks_name":"Chinakorumilli",
    "ks:ks_pop":97,
    "ks:ks_type":"HABITATION",
    "name:eng_x_preferred":[
        "Chinakorumilli"
    ],
    "wof:name":"Chinakorumilli",
    "wof:placetype":"locality",
    "wof:population":97
},
  "geometry": {"coordinates":[81.84327500000001,17.44644],"type":"Point"}
}