{
  "type": "Feature",
  "properties": {
    "iso:country":"IN",
    "ks:ks_name":"Ullas Vayal",
    "ks:ks_pop":442,
    "ks:ks_type":"HABITATION",
    "name:eng_x_preferred":[
        "Ullas Vayal"
    ],
    "wof:name":"Ullas Vayal",
    "wof:placetype":"locality",
    "wof:population":442
},
  "geometry": {"coordinates":[76.777371,8.94486],"type":"Point"}
}