{
  "type": "Feature",
  "properties": {
    "iso:country":"IN",
    "ks:ks_name":"Kanakkuru",
    "ks:ks_pop":12,
    "ks:ks_type":"HABITATION",
    "name:eng_x_preferred":[
        "Kanakkuru"
    ],
    "wof:name":"Kanakkuru",
    "wof:placetype":"locality",
    "wof:population":12
},
  "geometry": {"coordinates":[75.31715800000001,12.503951],"type":"Point"}
}