{
  "type": "Feature",
  "properties": {
    "iso:country":"IN",
    "ks:ks_name":"Patilwadi",
    "ks:ks_pop":45,
    "ks:ks_type":"HABITATION",
    "name:eng_x_preferred":[
        "Patilwadi"
    ],
    "wof:name":"Patilwadi",
    "wof:placetype":"locality",
    "wof:population":45
},
  "geometry": {"coordinates":[73.662425,17.033767],"type":"Point"}
}