{
  "type": "Feature",
  "properties": {
    "iso:country":"IN",
    "ks:ks_alt_nam":"Khajiri khera",
    "ks:ks_name":"Khajiri Khera",
    "ks:ks_pop":768,
    "ks:ks_type":"HABITATION",
    "name:eng_x_preferred":[
        "Khajiri Khera"
    ],
    "wof:name":"Khajiri Khera",
    "wof:placetype":"locality",
    "wof:population":768
},
  "geometry": {"coordinates":[74.822228,23.834078],"type":"Point"}
}