{
  "type": "Feature",
  "properties": {
    "iso:country":"IN",
    "ks:ks_name":"Moho Faliya",
    "ks:ks_pop":62,
    "ks:ks_type":"HABITATION",
    "name:eng_x_preferred":[
        "Moho Faliya"
    ],
    "wof:name":"Moho Faliya",
    "wof:placetype":"locality",
    "wof:population":62
},
  "geometry": {"coordinates":[73.464609,20.532105],"type":"Point"}
}