{
  "type": "Feature",
  "properties": {
    "iso:country":"IN",
    "ks:ks_name":"Nishal Falia",
    "ks:ks_pop":751,
    "ks:ks_type":"HABITATION",
    "name:eng_x_preferred":[
        "Nishal Falia"
    ],
    "wof:name":"Nishal Falia",
    "wof:placetype":"locality",
    "wof:population":751
},
  "geometry": {"coordinates":[74.01049999999999,22.926972],"type":"Point"}
}