{
  "type": "Feature",
  "properties": {
    "gn:admin1_code":"36.0",
    "gn:admin2_code":"184.0",
    "gn:asciiname":"Madarpur",
    "gn:country_code":"IN",
    "gn:dem":97,
    "gn:feature_class":"P",
    "gn:feature_code":"PPL",
    "gn:name":"Mad\u0101rpur",
    "gn:population":0,
    "gn:timezone":"Asia/Kolkata",
    "iso:country":"IN",
    "name:fra_x_preferred":[
        "Madarpur"
    ],
    "name:hif_x_preferred":[
        "Madarpur"
    ],
    "wof:name":"Madarpur",
    "wof:placetype":"neighbourhood"
},
  "geometry": {"coordinates":[82.59647,27.17486],"type":"Point"}
}