{
  "type": "Feature",
  "properties": {
    "iso:country":"IN",
    "ks:ks_name":"Belbuni",
    "ks:ks_pop":1512,
    "ks:ks_type":"VILLAGE",
    "name:eng_x_preferred":[
        "Belbuni"
    ],
    "wof:name":"Belbuni",
    "wof:placetype":"locality",
    "wof:population":1512
},
  "geometry": {"coordinates":[87.15719,23.283484],"type":"Point"}
}