{
  "type": "Feature",
  "properties": {
    "iso:country":"IN",
    "ks:ks_name":"Tunera",
    "ks:ks_pop":15,
    "ks:ks_type":"VILLAGE",
    "name:eng_x_preferred":[
        "Tunera"
    ],
    "wof:name":"Tunera",
    "wof:placetype":"locality",
    "wof:population":15
},
  "geometry": {"coordinates":[80.15526,29.804368],"type":"Point"}
}