{
  "type": "Feature",
  "properties": {
    "gn:admin1_code":"35.0",
    "gn:admin2_code":"421.0",
    "gn:asciiname":"Jahangirpur",
    "gn:country_code":"IN",
    "gn:dem":189,
    "gn:feature_class":"P",
    "gn:feature_code":"PPL",
    "gn:name":"Jah\u0101ng\u012brpur",
    "gn:population":0,
    "gn:timezone":"Asia/Kolkata",
    "iso:country":"IN",
    "ks:ks_alt_nam":"Jah\u0101ng\u012brpur",
    "ks:ks_name":"Jahangirpur",
    "ks:ks_pop":691,
    "ks:ks_type":"VILLAGE",
    "name:eng_x_preferred":[
        "Jahangirpur"
    ],
    "name:eng_x_variant":[
        "Jah\u0101ng\u012brpur"
    ],
    "name:pol_x_preferred":[
        "Jahangirpur"
    ],
    "wof:name":"Jahangirpur",
    "wof:placetype":"locality",
    "wof:population":691
},
  "geometry": {"coordinates":[78.26125399999999,26.263361],"type":"Point"}
}