{
  "type": "Feature",
  "properties": {
    "gn:admin1_code":"35.0",
    "gn:admin2_code":"421.0",
    "gn:asciiname":"Jahangirpur",
    "gn:country_code":"IN",
    "gn:dem":189,
    "gn:feature_class":"P",
    "gn:feature_code":"PPL",
    "gn:name":"Jah\u0101ng\u012brpur",
    "gn:population":0,
    "gn:timezone":"Asia/Kolkata",
    "iso:country":"IN",
    "name:eng_x_preferred":[
        "Jah\u0101ng\u012brpur"
    ],
    "name:pol_x_preferred":[
        "Jahangirpur"
    ],
    "wof:name":"Jahangirpur",
    "wof:placetype":"locality"
},
  "geometry": {"coordinates":[78.26040999999999,26.26282],"type":"Point"}
}