{
  "type": "Feature",
  "properties": {
    "gn:admin1_code":"11.0",
    "gn:admin2_code":"31.0",
    "gn:asciiname":"Dhar ki Ser",
    "gn:country_code":"IN",
    "gn:dem":1393,
    "gn:feature_class":"P",
    "gn:feature_code":"PPL",
    "gn:name":"Dh\u0101r ki Ser",
    "gn:population":0,
    "gn:timezone":"Asia/Kolkata",
    "iso:country":"IN",
    "wof:name":"Dhar ki Ser",
    "wof:placetype":"locality"
},
  "geometry": {"coordinates":[77.16361999999999,30.98633],"type":"Point"}
}