{
  "type": "Feature",
  "properties": {
    "iso:country":"IN",
    "ks:ks_name":"Barui",
    "ks:ks_pop":54,
    "ks:ks_type":"VILLAGE",
    "name:eng_x_preferred":[
        "Barui"
    ],
    "wof:name":"Barui",
    "wof:placetype":"locality",
    "wof:population":54
},
  "geometry": {"coordinates":[80.925239,24.87377],"type":"Point"}
}