{
  "type": "Feature",
  "properties": {
    "iso:country":"IN",
    "ks:ks_name":"Bekare Dhangarwadi",
    "ks:ks_pop":40,
    "ks:ks_type":"HABITATION",
    "name:eng_x_preferred":[
        "Bekare Dhangarwadi"
    ],
    "wof:name":"Bekare Dhangarwadi",
    "wof:placetype":"locality",
    "wof:population":40
},
  "geometry": {"coordinates":[73.32642,18.986124],"type":"Point"}
}