{
  "type": "Feature",
  "properties": {
    "iso:country":"IN",
    "ks:ks_name":"Pade",
    "ks:ks_pop":91,
    "ks:ks_type":"HABITATION",
    "name:eng_x_preferred":[
        "Pade"
    ],
    "wof:name":"Pade",
    "wof:placetype":"locality",
    "wof:population":91
},
  "geometry": {"coordinates":[75.18560100000001,12.892904],"type":"Point"}
}