{
  "type": "Feature",
  "properties": {
    "iso:country":"IN",
    "ks:ks_name":"Agarwadi",
    "ks:ks_pop":259,
    "ks:ks_type":"HABITATION",
    "name:eng_x_preferred":[
        "Agarwadi"
    ],
    "wof:name":"Agarwadi",
    "wof:placetype":"locality",
    "wof:population":259
},
  "geometry": {"coordinates":[73.53527800000001,16.673611],"type":"Point"}
}