{
  "type": "Feature",
  "properties": {
    "gn:admin1_code":"35.0",
    "gn:admin2_code":"466",
    "gn:asciiname":"Attar",
    "gn:country_code":"IN",
    "gn:dem":269,
    "gn:feature_class":"P",
    "gn:feature_code":"PPL",
    "gn:name":"Att\u0101r",
    "gn:population":0,
    "gn:timezone":"Asia/Kolkata",
    "iso:country":"IN",
    "name:und_x_variant":[
        "Att\u0101r",
        "Attar"
    ],
    "wof:name":"Attar",
    "wof:placetype":"locality"
},
  "geometry": {"coordinates":[76.20725999999998,22.00944],"type":"Point"}
}