{
  "type": "Feature",
  "properties": {
    "gn:admin1_code":"35.0",
    "gn:admin2_code":"466",
    "gn:asciiname":"Attar",
    "gn:country_code":"IN",
    "gn:dem":269,
    "gn:feature_class":"P",
    "gn:feature_code":"PPL",
    "gn:name":"Att\u0101r",
    "gn:population":0,
    "gn:timezone":"Asia/Kolkata",
    "iso:country":"IN",
    "name:ara_x_preferred":[
        "\u0639\u0637\u0627\u0631"
    ],
    "name:deu_x_preferred":[
        "Attar"
    ],
    "name:fra_x_preferred":[
        "Attar"
    ],
    "name:heb_x_preferred":[
        "\u05e2\u05d8\u05e8"
    ],
    "name:ita_x_preferred":[
        "Attar"
    ],
    "name:rus_x_preferred":[
        "\u0410\u0442\u0442\u0430\u0440"
    ],
    "name:spa_x_preferred":[
        "Attar"
    ],
    "name:und_x_variant":[
        "Att\u0101r"
    ],
    "wof:name":"Attar",
    "wof:placetype":"locality"
},
  "geometry": {"coordinates":[76.20725999999998,22.00944],"type":"Point"}
}