{
  "type": "Feature",
  "properties": {
    "gn:admin1_code":"40.0",
    "gn:admin2_code":"541.0",
    "gn:asciiname":"Mallempeta",
    "gn:country_code":"IN",
    "gn:dem":111,
    "gn:feature_class":"P",
    "gn:feature_code":"PPL",
    "gn:name":"Mallempeta",
    "gn:population":0,
    "gn:timezone":"Asia/Kolkata",
    "iso:country":"IN",
    "ks:ks_name":"Mallampete",
    "ks:ks_pop":204,
    "ks:ks_type":"HABITATION",
    "name:eng_x_preferred":[
        "Mallampete"
    ],
    "name:eng_x_variant":[
        "Mallempeta"
    ],
    "wof:name":"Mallampete",
    "wof:placetype":"locality",
    "wof:population":204
},
  "geometry": {"coordinates":[81.16117300000001,17.849883],"type":"Point"}
}