{
  "type": "Feature",
  "properties": {
    "gn:admin1_code":"36.0",
    "gn:admin2_code":"133.0",
    "gn:asciiname":"Gawri",
    "gn:country_code":"IN",
    "gn:dem":236,
    "gn:feature_class":"P",
    "gn:feature_code":"PPL",
    "gn:name":"G\u0101wri",
    "gn:population":0,
    "gn:timezone":"Asia/Kolkata",
    "iso:country":"IN",
    "name:und_x_variant":[
        "G\u0101wri",
        "Asadull\u0101nagar"
    ],
    "wof:name":"Gawri",
    "wof:placetype":"locality"
},
  "geometry": {"coordinates":[77.64015999999999,29.25234],"type":"Point"}
}