{
  "type": "Feature",
  "properties": {
    "gn:admin1_code":"19",
    "gn:admin2_code":"563.0",
    "gn:asciiname":"Kumbharvada",
    "gn:country_code":"IN",
    "gn:dem":591,
    "gn:feature_class":"P",
    "gn:feature_code":"PPL",
    "gn:name":"Kumbh\u0101rv\u0101da",
    "gn:population":0,
    "gn:timezone":"Asia/Kolkata",
    "iso:country":"IN",
    "wof:name":"Kumbharvada",
    "wof:placetype":"neighbourhood"
},
  "geometry": {"coordinates":[74.40470000000001,15.12763],"type":"Point"}
}