{
  "type": "Feature",
  "properties": {
    "gn:admin1_code":"24",
    "gn:admin2_code":"104.0",
    "gn:asciiname":"Baroli",
    "gn:country_code":"IN",
    "gn:dem":213,
    "gn:feature_class":"P",
    "gn:feature_code":"PPL",
    "gn:name":"B\u0101roli",
    "gn:population":0,
    "gn:timezone":"Asia/Kolkata",
    "iso:country":"IN",
    "wof:name":"Baroli",
    "wof:placetype":"locality"
},
  "geometry": {"coordinates":[77.01085999999999,27.523],"type":"Point"}
}