{
  "type": "Feature",
  "properties": {
    "iso:country":"IN",
    "ks:ks_name":"Vankar Ravan Faliya",
    "ks:ks_pop":508,
    "ks:ks_type":"HABITATION",
    "name:eng_x_preferred":[
        "Vankar Ravan Faliya"
    ],
    "wof:name":"Vankar Ravan Faliya",
    "wof:placetype":"locality",
    "wof:population":508
},
  "geometry": {"coordinates":[73.811806,22.939722],"type":"Point"}
}