{
  "type": "Feature",
  "properties": {
    "gn:admin1_code":"34.0",
    "gn:admin2_code":"210.0",
    "gn:asciiname":"Najarpur",
    "gn:country_code":"IN",
    "gn:dem":53,
    "gn:feature_class":"P",
    "gn:feature_code":"PPL",
    "gn:name":"Najarpur",
    "gn:population":0,
    "gn:timezone":"Asia/Kolkata",
    "iso:country":"IN",
    "name:nep_x_preferred":[
        "\u0928\u091c\u0930\u092a\u0941\u0930"
    ],
    "wof:name":"Najarpur",
    "wof:placetype":"neighbourhood"
},
  "geometry": {"coordinates":[87.85635000000001,26.15012],"type":"Point"}
}