{
  "type": "Feature",
  "properties": {
    "iso:country":"IN",
    "ks:ks_name":"Pandripani Kumar",
    "ks:ks_pop":75,
    "ks:ks_type":"VILLAGE",
    "name:eng_x_preferred":[
        "Pandripani Kumar"
    ],
    "wof:name":"Pandripani Kumar",
    "wof:placetype":"locality",
    "wof:population":75
},
  "geometry": {"coordinates":[82.24775200000001,20.723192],"type":"Point"}
}