{
  "type": "Feature",
  "properties": {
    "gn:admin1_code":"19.0",
    "gn:admin2_code":"566.0",
    "gn:asciiname":"Tonachenahalli",
    "gn:country_code":"IN",
    "gn:dem":702,
    "gn:feature_class":"P",
    "gn:feature_code":"PPL",
    "gn:name":"Tonachenahalli",
    "gn:population":0,
    "gn:timezone":"Asia/Kolkata",
    "iso:country":"IN",
    "wof:name":"Tonachenahalli",
    "wof:placetype":"locality"
},
  "geometry": {"coordinates":[76.35369,13.66508],"type":"Point"}
}