{
  "type": "Feature",
  "properties": {
    "gn:admin1_code":"11.0",
    "gn:admin2_code":"32.0",
    "gn:asciiname":"Maona",
    "gn:country_code":"IN",
    "gn:dem":1309,
    "gn:feature_class":"P",
    "gn:feature_code":"PPL",
    "gn:name":"Maona",
    "gn:population":0,
    "gn:timezone":"Asia/Kolkata",
    "iso:country":"IN",
    "name:cat_x_preferred":[
        "Maona"
    ],
    "name:ell_x_preferred":[
        "\u039c\u03b1\u03cc\u03bd\u03b1"
    ],
    "name:fra_x_preferred":[
        "Maona"
    ],
    "name:ita_x_preferred":[
        "Maona"
    ],
    "name:nld_x_preferred":[
        "Maona"
    ],
    "wof:name":"Maona",
    "wof:placetype":"locality"
},
  "geometry": {"coordinates":[77.59124,30.5815],"type":"Point"}
}