{
  "type": "Feature",
  "properties": {
    "gn:admin1_code":"36.0",
    "gn:admin2_code":"162.0",
    "gn:asciiname":"Udampur",
    "gn:country_code":"IN",
    "gn:dem":142,
    "gn:feature_class":"P",
    "gn:feature_code":"PPL",
    "gn:name":"Udampur",
    "gn:population":0,
    "gn:timezone":"Asia/Kolkata",
    "iso:country":"IN",
    "ks:ks_name":"Udampur",
    "ks:ks_pop":1109,
    "ks:ks_type":"VILLAGE",
    "name:eng_x_preferred":[
        "Udampur"
    ],
    "wof:name":"Udampur",
    "wof:placetype":"locality",
    "wof:population":1109
},
  "geometry": {"coordinates":[79.44864099999999,26.534578],"type":"Point"}
}