{
  "type": "Feature",
  "properties": {
    "iso:country":"IN",
    "ks:ks_alt_nam":"PURWARI TOLA",
    "ks:ks_name":"Purwari Tola",
    "ks:ks_pop":404,
    "ks:ks_type":"HABITATION",
    "name:eng_x_preferred":[
        "Purwari Tola"
    ],
    "wof:name":"Purwari Tola",
    "wof:placetype":"locality",
    "wof:population":404
},
  "geometry": {"coordinates":[85.46381,24.870807],"type":"Point"}
}