{
  "type": "Feature",
  "properties": {
    "iso:country":"IN",
    "ks:ks_alt_nam":"BAZARTILLA",
    "ks:ks_name":"Bazartilla",
    "ks:ks_pop":207,
    "ks:ks_type":"HABITATION",
    "name:eng_x_preferred":[
        "Bazartilla"
    ],
    "wof:name":"Bazartilla",
    "wof:placetype":"locality",
    "wof:population":207
},
  "geometry": {"coordinates":[91.17700499999999,23.737894],"type":"Point"}
}