{
  "type": "Feature",
  "properties": {
    "iso:country":"IN",
    "ks:ks_name":"Sulewadi",
    "ks:ks_pop":1427,
    "ks:ks_type":"VILLAGE",
    "name:eng_x_preferred":[
        "Sulewadi"
    ],
    "wof:name":"Sulewadi",
    "wof:placetype":"locality",
    "wof:population":1427
},
  "geometry": {"coordinates":[74.928259,17.678598],"type":"Point"}
}