{
  "type": "Feature",
  "properties": {
    "gn:admin1_code":"35",
    "gn:admin2_code":"419.0",
    "gn:asciiname":"Tikri",
    "gn:country_code":"IN",
    "gn:dem":212,
    "gn:feature_class":"P",
    "gn:feature_code":"PPL",
    "gn:name":"Tikri",
    "gn:population":0,
    "gn:timezone":"Asia/Kolkata",
    "iso:country":"IN",
    "name:ceb_x_preferred":[
        "Tikri"
    ],
    "name:swe_x_preferred":[
        "Tikri"
    ],
    "wof:name":"Tikri",
    "wof:placetype":"locality"
},
  "geometry": {"coordinates":[78.23333000000002,26.31667],"type":"Point"}
}