{
  "type": "Feature",
  "properties": {
    "gn:admin1_code":"35",
    "gn:admin2_code":"419.0",
    "gn:asciiname":"Tikri",
    "gn:country_code":"IN",
    "gn:dem":212,
    "gn:feature_class":"P",
    "gn:feature_code":"PPL",
    "gn:name":"Tikri",
    "gn:population":0,
    "gn:timezone":"Asia/Kolkata",
    "iso:country":"IN",
    "ks:ks_name":"Tikari",
    "ks:ks_pop":557,
    "ks:ks_type":"VILLAGE",
    "name:ceb_x_preferred":[
        "Tikri"
    ],
    "name:eng_x_preferred":[
        "Tikari"
    ],
    "name:eng_x_variant":[
        "Tikri"
    ],
    "name:swe_x_preferred":[
        "Tikri"
    ],
    "wof:name":"Tikari",
    "wof:placetype":"locality",
    "wof:population":557
},
  "geometry": {"coordinates":[78.22399900000001,26.306387],"type":"Point"}
}