{
  "type": "Feature",
  "properties": {
    "iso:country":"IN",
    "ks:ks_name":"Kanchikuli",
    "ks:ks_pop":14,
    "ks:ks_type":"HABITATION",
    "name:eng_x_preferred":[
        "Kanchikuli"
    ],
    "wof:name":"Kanchikuli",
    "wof:placetype":"locality",
    "wof:population":14
},
  "geometry": {"coordinates":[74.606033,14.873113],"type":"Point"}
}