{
  "type": "Feature",
  "properties": {
    "iso:country":"IN",
    "ks:ks_alt_nam":"PARIMAL MITRA NAGAR",
    "ks:ks_name":"Parimal Mitra Nagar",
    "ks:ks_pop":875,
    "ks:ks_type":"HABITATION",
    "ks:ks_uagg_main":0,
    "name:eng_x_preferred":[
        "Parimal Mitra Nagar"
    ],
    "wof:name":"Parimal Mitra Nagar",
    "wof:placetype":"neighbourhood",
    "wof:population":875
},
  "geometry": {"coordinates":[88.812907,26.868997],"type":"Point"}
}