{
  "type": "Feature",
  "properties": {
    "gn:admin1_code":"19.0",
    "gn:admin2_code":"574",
    "gn:asciiname":"Halli Mysore",
    "gn:country_code":"IN",
    "gn:dem":880,
    "gn:feature_class":"P",
    "gn:feature_code":"PPL",
    "gn:name":"Halli Mysore",
    "gn:population":0,
    "gn:timezone":"Asia/Kolkata",
    "iso:country":"IN",
    "wof:name":"Halli Mysore",
    "wof:placetype":"locality"
},
  "geometry": {"coordinates":[76.25819,12.65792],"type":"Point"}
}