{
  "type": "Feature",
  "properties": {
    "iso:country":"IN",
    "ks:ks_name":"Shai Dih",
    "ks:ks_pop":712,
    "ks:ks_type":"HABITATION",
    "name:eng_x_preferred":[
        "Shai Dih"
    ],
    "wof:name":"Shai Dih",
    "wof:placetype":"locality",
    "wof:population":712
},
  "geometry": {"coordinates":[82.209298,27.343672],"type":"Point"}
}