{
  "type": "Feature",
  "properties": {
    "gn:admin1_code":"36.0",
    "gn:admin2_code":"139.0",
    "gn:asciiname":"Karmalipurgarhi",
    "gn:country_code":"IN",
    "gn:dem":225,
    "gn:feature_class":"P",
    "gn:feature_code":"PPL",
    "gn:name":"Karmal\u012bpurgarhi",
    "gn:population":0,
    "gn:timezone":"Asia/Kolkata",
    "iso:country":"IN",
    "wof:name":"Karmalipurgarhi",
    "wof:placetype":"locality"
},
  "geometry": {"coordinates":[77.32221,29.00984],"type":"Point"}
}