{
  "type": "Feature",
  "properties": {
    "iso:country":"IN",
    "ks:ks_alt_nam":"Nagla bhan",
    "ks:ks_name":"Nagla Bhan",
    "ks:ks_pop":244,
    "ks:ks_type":"HABITATION",
    "ks:ks_uagg_main":0,
    "name:eng_x_preferred":[
        "Nagla Bhan"
    ],
    "wof:name":"Nagla Bhan",
    "wof:placetype":"neighbourhood",
    "wof:population":244
},
  "geometry": {"coordinates":[79.548097,27.063463],"type":"Point"}
}