{
  "type": "Feature",
  "properties": {
    "iso:country":"IN",
    "ks:ks_name":"Gidha North Musahari",
    "ks:ks_pop":299,
    "ks:ks_type":"HABITATION",
    "ks:ks_uagg_main":0,
    "name:eng_x_preferred":[
        "Gidha North Musahari"
    ],
    "wof:name":"Gidha North Musahari",
    "wof:placetype":"neighbourhood",
    "wof:population":299
},
  "geometry": {"coordinates":[86.89623400000001,25.946838],"type":"Point"}
}