{
  "type": "Feature",
  "properties": {
    "iso:country":"IN",
    "ks:ks_name":"Siddarabanu",
    "ks:ks_pop":65,
    "ks:ks_type":"HABITATION",
    "name:eng_x_preferred":[
        "Siddarabanu"
    ],
    "wof:name":"Siddarabanu",
    "wof:placetype":"locality",
    "wof:population":65
},
  "geometry": {"coordinates":[75.642049,13.385143],"type":"Point"}
}