{
  "type": "Feature",
  "properties": {
    "iso:country":"IN",
    "ks:ks_name":"Birajianga",
    "ks:ks_pop":9,
    "ks:ks_type":"VILLAGE",
    "name:eng_x_preferred":[
        "Birajianga"
    ],
    "wof:name":"Birajianga",
    "wof:placetype":"locality",
    "wof:population":9
},
  "geometry": {"coordinates":[85.681301,20.532613],"type":"Point"}
}