{
  "type": "Feature",
  "properties": {
    "gn:admin1_code":"35",
    "gn:admin2_code":"426.0",
    "gn:asciiname":"Kolkarahiya",
    "gn:country_code":"IN",
    "gn:dem":318,
    "gn:feature_class":"P",
    "gn:feature_code":"PPL",
    "gn:name":"Kolkarahiya",
    "gn:population":0,
    "gn:timezone":"Asia/Kolkata",
    "iso:country":"IN",
    "name:eng_x_preferred":[
        "Kolkarahiya"
    ],
    "wof:name":"Kolkarahiya",
    "wof:placetype":"locality"
},
  "geometry": {"coordinates":[79.82420999999999,24.27646],"type":"Point"}
}