{
  "type": "Feature",
  "properties": {
    "iso:country":"IN",
    "ks:ks_name":"Gomda Pokhar",
    "ks:ks_pop":507,
    "ks:ks_type":"VILLAGE",
    "name:eng_x_preferred":[
        "Gomda Pokhar"
    ],
    "wof:name":"Gomda Pokhar",
    "wof:placetype":"locality",
    "wof:population":507
},
  "geometry": {"coordinates":[85.975047,22.40412],"type":"Point"}
}