{
  "type": "Feature",
  "properties": {
    "iso:country":"IN",
    "ks:ks_name":"Amla Chaturi",
    "ks:ks_pop":134,
    "ks:ks_type":"VILLAGE",
    "name:eng_x_preferred":[
        "Amla Chaturi"
    ],
    "wof:name":"Amla Chaturi",
    "wof:placetype":"locality",
    "wof:population":134
},
  "geometry": {"coordinates":[87.39873299999999,23.966662],"type":"Point"}
}