{
  "type": "Feature",
  "properties": {
    "iso:country":"IN",
    "ks:ks_name":"Pandrisila",
    "ks:ks_pop":163,
    "ks:ks_type":"VILLAGE",
    "name:eng_x_preferred":[
        "Pandrisila"
    ],
    "wof:name":"Pandrisila",
    "wof:placetype":"locality",
    "wof:population":163
},
  "geometry": {"coordinates":[84.51172200000001,21.156351],"type":"Point"}
}