{
  "type": "Feature",
  "properties": {
    "gn:admin1_code":"21.0",
    "gn:admin2_code":"398.0",
    "gn:asciiname":"Kunjiri",
    "gn:country_code":"IN",
    "gn:dem":566,
    "gn:feature_class":"P",
    "gn:feature_code":"PPL",
    "gn:name":"Kunjiri",
    "gn:population":0,
    "gn:timezone":"Asia/Kolkata",
    "iso:country":"IN",
    "ks:ks_name":"Kunjeri",
    "ks:ks_pop":163,
    "ks:ks_type":"VILLAGE",
    "name:eng_x_preferred":[
        "Kunjeri"
    ],
    "name:eng_x_variant":[
        "Kunjiri"
    ],
    "wof:name":"Kunjeri",
    "wof:placetype":"locality",
    "wof:population":163
},
  "geometry": {"coordinates":[83.201728,18.946395],"type":"Point"}
}