{
  "type": "Feature",
  "properties": {
    "gn:admin1_code":"39.0",
    "gn:admin2_code":"60.0",
    "gn:asciiname":"Sahasradhara",
    "gn:country_code":"IN",
    "gn:dem":857,
    "gn:feature_class":"P",
    "gn:feature_code":"PPL",
    "gn:name":"Sahasradh\u0101ra",
    "gn:population":0,
    "gn:timezone":"Asia/Kolkata",
    "iso:country":"IN",
    "name:guj_x_preferred":[
        "\u0ab8\u0ab9\u0ab8\u0acd\u0aa4\u0acd\u0ab0\u0aa7\u0abe\u0ab0\u0abe"
    ],
    "name:hin_x_preferred":[
        "\u0938\u0939\u0938\u094d\u0930\u0927\u093e\u0930\u093e"
    ],
    "wof:name":"Sahasradhara",
    "wof:placetype":"neighbourhood"
},
  "geometry": {"coordinates":[78.12891999999999,30.38528],"type":"Point"}
}