{
  "type": "Feature",
  "properties": {
    "iso:country":"IN",
    "ks:ks_name":"Chhota Janaki",
    "ks:ks_pop":396,
    "ks:ks_type":"VILLAGE",
    "name:eng_x_preferred":[
        "Chhota Janaki"
    ],
    "wof:name":"Chhota Janaki",
    "wof:placetype":"locality",
    "wof:population":396
},
  "geometry": {"coordinates":[86.771646,24.482714],"type":"Point"}
}