{
  "type": "Feature",
  "properties": {
    "gn:admin1_code":"16.0",
    "gn:admin2_code":"531",
    "gn:asciiname":"Karajgi",
    "gn:country_code":"IN",
    "gn:dem":505,
    "gn:feature_class":"P",
    "gn:feature_code":"PPL",
    "gn:name":"Karajgi",
    "gn:population":0,
    "gn:timezone":"Asia/Kolkata",
    "iso:country":"IN",
    "name:ceb_x_preferred":[
        "Karajgi"
    ],
    "name:swe_x_preferred":[
        "Karajgi"
    ],
    "name:und_x_variant":[
        "Karajagi"
    ],
    "wof:name":"Karajgi",
    "wof:placetype":"locality"
},
  "geometry": {"coordinates":[75.57523,17.12453],"type":"Point"}
}