{
  "type": "Feature",
  "properties": {
    "gn:admin1_code":"12.0",
    "gn:admin2_code":"004",
    "gn:asciiname":"Yaldoda",
    "gn:country_code":"IN",
    "gn:dem":3342,
    "gn:feature_class":"P",
    "gn:feature_code":"PPL",
    "gn:name":"Yaldoda",
    "gn:population":0,
    "gn:timezone":"Asia/Kolkata",
    "iso:country":"IN",
    "wof:name":"Yaldoda",
    "wof:placetype":"locality"
},
  "geometry": {"coordinates":[76.47778000000002,34.67639],"type":"Point"}
}