{
  "type": "Feature",
  "properties": {
    "iso:country":"IN",
    "ks:ks_name":"Kumbharwadi",
    "ks:ks_pop":414,
    "ks:ks_type":"HABITATION",
    "name:eng_x_preferred":[
        "Kumbharwadi"
    ],
    "wof:name":"Kumbharwadi",
    "wof:placetype":"locality",
    "wof:population":414
},
  "geometry": {"coordinates":[73.488724,16.211327],"type":"Point"}
}