{
  "type": "Feature",
  "properties": {
    "iso:country":"IN",
    "ks:ks_name":"Charichmal",
    "ks:ks_pop":100,
    "ks:ks_type":"HABITATION",
    "name:eng_x_preferred":[
        "Charichmal"
    ],
    "wof:name":"Charichmal",
    "wof:placetype":"locality",
    "wof:population":100
},
  "geometry": {"coordinates":[73.055466,19.998082],"type":"Point"}
}