{
  "type": "Feature",
  "properties": {
    "iso:country":"IN",
    "ks:ks_name":"Bamangwali",
    "ks:ks_pop":145,
    "ks:ks_type":"VILLAGE",
    "name:eng_x_preferred":[
        "Bamangwali"
    ],
    "wof:name":"Bamangwali",
    "wof:placetype":"locality",
    "wof:population":145
},
  "geometry": {"coordinates":[79.363027,29.86659],"type":"Point"}
}