{
  "type": "Feature",
  "properties": {
    "iso:country":"IN",
    "ks:ks_alt_nam":"Muslim Para-II",
    "ks:ks_name":"Muslim Para-ii",
    "ks:ks_pop":619,
    "ks:ks_type":"HABITATION",
    "ks:ks_uagg_main":0,
    "name:eng_x_preferred":[
        "Muslim Para-ii"
    ],
    "wof:name":"Muslim Para-ii",
    "wof:placetype":"neighbourhood",
    "wof:population":619
},
  "geometry": {"coordinates":[91.326886,23.22112],"type":"Point"}
}