{
  "type": "Feature",
  "properties": {
    "iso:country":"IN",
    "ks:ks_alt_nam":"TEKACHIWASTI",
    "ks:ks_name":"Tekachiwasti",
    "ks:ks_pop":101,
    "ks:ks_type":"HABITATION",
    "name:eng_x_preferred":[
        "Tekachiwasti"
    ],
    "wof:name":"Tekachiwasti",
    "wof:placetype":"locality",
    "wof:population":101
},
  "geometry": {"coordinates":[74.894324,17.272994],"type":"Point"}
}