{
  "type": "Feature",
  "properties": {
    "gn:admin1_code":"2",
    "gn:admin2_code":"544.0",
    "gn:asciiname":"Mulagalametta",
    "gn:country_code":"IN",
    "gn:dem":201,
    "gn:feature_class":"P",
    "gn:feature_code":"PPL",
    "gn:name":"Mulagalametta",
    "gn:population":0,
    "gn:timezone":"Asia/Kolkata",
    "iso:country":"IN",
    "ks:ks_name":"Mulagalametta",
    "ks:ks_type":"VILLAGE",
    "name:eng_x_preferred":[
        "Mulagalametta"
    ],
    "wof:name":"Mulagalametta",
    "wof:placetype":"locality"
},
  "geometry": {"coordinates":[82.379575,17.713302],"type":"Point"}
}