{
  "type": "Feature",
  "properties": {
    "gn:admin1_code":"19.0",
    "gn:admin2_code":"582.0",
    "gn:asciiname":"Etigaddagollahalli",
    "gn:country_code":"IN",
    "gn:dem":745,
    "gn:feature_class":"P",
    "gn:feature_code":"PPL",
    "gn:name":"Etigaddagollahalli",
    "gn:population":0,
    "gn:timezone":"Asia/Kolkata",
    "iso:country":"IN",
    "wof:name":"Etigaddagollahalli",
    "wof:placetype":"locality"
},
  "geometry": {"coordinates":[78.10614,13.56164],"type":"Point"}
}