{
  "type": "Feature",
  "properties": {
    "gn:admin1_code":"16",
    "gn:admin2_code":"524.0",
    "gn:asciiname":"Gadhvewadi",
    "gn:country_code":"IN",
    "gn:dem":624,
    "gn:feature_class":"P",
    "gn:feature_code":"PPL",
    "gn:name":"G\u0101dhvew\u0101di",
    "gn:population":0,
    "gn:timezone":"Asia/Kolkata",
    "iso:country":"IN",
    "wof:name":"Gadhvewadi",
    "wof:placetype":"locality"
},
  "geometry": {"coordinates":[76.53511,18.14662],"type":"Point"}
}