{
  "type": "Feature",
  "properties": {
    "gn:admin1_code":"35",
    "gn:admin2_code":"462.0",
    "gn:asciiname":"Khoha",
    "gn:country_code":"IN",
    "gn:dem":330,
    "gn:feature_class":"P",
    "gn:feature_code":"PPL",
    "gn:name":"Khoha",
    "gn:population":0,
    "gn:timezone":"Asia/Kolkata",
    "iso:country":"IN",
    "ks:ks_name":"Khoha",
    "ks:ks_pop":778,
    "ks:ks_type":"VILLAGE",
    "name:eng_x_preferred":[
        "Khoha"
    ],
    "name:und_x_variant":[
        "G\u0101ndh\u012bgr\u0101m"
    ],
    "wof:name":"Khoha",
    "wof:placetype":"locality",
    "wof:population":778
},
  "geometry": {"coordinates":[82.011385,24.382938],"type":"Point"}
}