{
  "type": "Feature",
  "properties": {
    "iso:country":"IN",
    "ks:ks_name":"Lodhan",
    "ks:ks_pop":1663,
    "ks:ks_type":"VILLAGE",
    "name:eng_x_preferred":[
        "Lodhan"
    ],
    "wof:name":"Lodhan",
    "wof:placetype":"locality",
    "wof:population":1663
},
  "geometry": {"coordinates":[73.810694,22.348361],"type":"Point"}
}