{
  "type": "Feature",
  "properties": {
    "iso:country":"IN",
    "ks:ks_name":"Roldih",
    "ks:ks_pop":61,
    "ks:ks_type":"VILLAGE",
    "name:eng_x_preferred":[
        "Roldih"
    ],
    "wof:name":"Roldih",
    "wof:placetype":"locality",
    "wof:population":61
},
  "geometry": {"coordinates":[87.48616699999999,24.634458],"type":"Point"}
}