{
  "type": "Feature",
  "properties": {
    "iso:country":"IN",
    "ks:ks_alt_nam":"Lower Relling II",
    "ks:ks_name":"Lower Relling Ii",
    "ks:ks_pop":618,
    "ks:ks_type":"HABITATION",
    "name:eng_x_preferred":[
        "Lower Relling Ii"
    ],
    "wof:name":"Lower Relling Ii",
    "wof:placetype":"locality",
    "wof:population":618
},
  "geometry": {"coordinates":[88.177177,27.059689],"type":"Point"}
}