{
  "type": "Feature",
  "properties": {
    "iso:country":"IN",
    "ks:ks_name":"Anchhidongri",
    "ks:ks_pop":341,
    "ks:ks_type":"VILLAGE",
    "name:eng_x_preferred":[
        "Anchhidongri"
    ],
    "wof:name":"Anchhidongri",
    "wof:placetype":"locality",
    "wof:population":341
},
  "geometry": {"coordinates":[81.757935,20.259082],"type":"Point"}
}