{
  "type": "Feature",
  "properties": {
    "gn:admin1_code":"35",
    "gn:admin2_code":"427.0",
    "gn:asciiname":"Mohali",
    "gn:country_code":"IN",
    "gn:dem":435,
    "gn:feature_class":"P",
    "gn:feature_code":"PPL",
    "gn:name":"Mohali",
    "gn:population":0,
    "gn:timezone":"Asia/Kolkata",
    "iso:country":"IN",
    "name:bih_x_preferred":[
        "\u092e\u094b\u0939\u093e\u0932\u0940"
    ],
    "name:bpy_x_preferred":[
        "\u098f\u09b8.\u098f.\u098f\u09b8. \u09a8\u0997\u09b0"
    ],
    "name:ceb_x_preferred":[
        "Mohali"
    ],
    "name:fas_x_preferred":[
        "\u0627\u062c\u06cc\u062a\u06af\u0627\u0631\u0627"
    ],
    "name:fra_x_preferred":[
        "Mohali"
    ],
    "name:guj_x_preferred":[
        "\u0aae\u0acb\u0ab9\u0abe\u0ab2\u0ac0"
    ],
    "name:hin_x_preferred":[
        "\u0905\u091c\u0940\u0924\u0917\u0922\u093c"
    ],
    "name:kan_x_preferred":[
        "\u0cae\u0cca\u0cb9\u0cbe\u0cb2\u0cbf"
    ],
    "name:mal_x_preferred":[
        "\u0d2e\u0d4a\u0d39\u0d3e\u0d32\u0d3f"
    ],
    "name:mar_x_preferred":[
        "\u092e\u094b\u0939\u093e\u0932\u0940"
    ],
    "name:msa_x_preferred":[
        "S.A.S. Nagar"
    ],
    "name:nep_x_preferred":[
        "\u092e\u094b\u0939\u093e\u0932\u0940"
    ],
    "name:nld_x_preferred":[
        "Ajitgarh"
    ],
    "name:ori_x_preferred":[
        "\u0b2e\u0b4b\u0b39\u0b3e\u0b32\u0b3f"
    ],
    "name:pam_x_preferred":[
        "Mohali"
    ],
    "name:pan_x_preferred":[
        "\u0a05\u0a1c\u0a40\u0a24\u0a17\u0a5c\u0a4d\u0a39"
    ],
    "name:pnb_x_preferred":[
        "\u0645\u0648\u06c1\u0627\u0644\u06cc"
    ],
    "name:rus_x_preferred":[
        "\u041c\u043e\u0445\u0430\u043b\u0438"
    ],
    "name:san_x_preferred":[
        "\u0938\u093e\u0939\u093f\u092c\u091c\u093e\u0926\u093e-\u0905\u091c\u093f\u0924\u0938\u093f\u0902\u0939\u0928\u0917\u0930\u092e\u094d"
    ],
    "name:spa_x_preferred":[
        "Mohali"
    ],
    "name:swe_x_preferred":[
        "Ajitgarh"
    ],
    "name:tam_x_preferred":[
        "\u0bae\u0bca\u0b95\u0bbe\u0bb2\u0bbf"
    ],
    "name:urd_x_preferred":[
        "\u0627\u062c\u06cc\u062a \u06af\u0691\u06be"
    ],
    "name:vie_x_preferred":[
        "S.A.S. Nagar"
    ],
    "wof:name":"Mohali",
    "wof:placetype":"locality"
},
  "geometry": {"coordinates":[79.22578,23.52913],"type":"Point"}
}