{
  "type": "Feature",
  "properties": {
    "iso:country":"IN",
    "ks:ks_name":"Hatimunda",
    "ks:ks_pop":73,
    "ks:ks_type":"VILLAGE",
    "name:eng_x_preferred":[
        "Hatimunda"
    ],
    "wof:name":"Hatimunda",
    "wof:placetype":"locality",
    "wof:population":73
},
  "geometry": {"coordinates":[84.35832000000001,19.919636],"type":"Point"}
}