{
  "type": "Feature",
  "properties": {
    "iso:country":"IN",
    "ks:ks_name":"Serani Nagar",
    "ks:ks_pop":436,
    "ks:ks_type":"HABITATION",
    "name:eng_x_preferred":[
        "Serani Nagar"
    ],
    "wof:name":"Serani Nagar",
    "wof:placetype":"locality",
    "wof:population":436
},
  "geometry": {"coordinates":[72.70725299999999,26.210639],"type":"Point"}
}