{
  "type": "Feature",
  "properties": {
    "iso:country":"IN",
    "ks:ks_name":"Thiyagarajapuram",
    "ks:ks_pop":258,
    "ks:ks_type":"HABITATION",
    "name:eng_x_preferred":[
        "Thiyagarajapuram"
    ],
    "wof:name":"Thiyagarajapuram",
    "wof:placetype":"locality",
    "wof:population":258
},
  "geometry": {"coordinates":[79.70198499999999,10.69164],"type":"Point"}
}