{
  "type": "Feature",
  "properties": {
    "iso:country":"IN",
    "ks:ks_name":"Bodamundai",
    "ks:ks_pop":983,
    "ks:ks_type":"VILLAGE",
    "ks:ks_uagg_main":0,
    "name:eng_x_preferred":[
        "Bodamundai"
    ],
    "wof:name":"Bodamundai",
    "wof:placetype":"neighbourhood",
    "wof:population":983
},
  "geometry": {"coordinates":[86.115954,20.500549],"type":"Point"}
}