{
  "type": "Feature",
  "properties": {
    "gn:admin1_code":"36.0",
    "gn:admin2_code":"161.0",
    "gn:asciiname":"Baisauli Bhanpur",
    "gn:country_code":"IN",
    "gn:dem":145,
    "gn:feature_class":"P",
    "gn:feature_code":"PPL",
    "gn:name":"Baisauli Bh\u0101npur",
    "gn:population":0,
    "gn:timezone":"Asia/Kolkata",
    "iso:country":"IN",
    "ks:ks_alt_nam":"Baisauli Bh\u0101npur",
    "ks:ks_name":"Baisauli Bhanpur",
    "ks:ks_type":"VILLAGE",
    "name:eng_x_preferred":[
        "Baisauli Bhanpur"
    ],
    "name:eng_x_variant":[
        "Baisauli Bh\u0101npur"
    ],
    "wof:name":"Baisauli Bhanpur",
    "wof:placetype":"locality"
},
  "geometry": {"coordinates":[79.262224,26.702917],"type":"Point"}
}