{
  "type": "Feature",
  "properties": {
    "iso:country":"IN",
    "ks:ks_alt_nam":"CHAINPURWA",
    "ks:ks_name":"Chainpurwa",
    "ks:ks_pop":115,
    "ks:ks_type":"HABITATION",
    "name:eng_x_preferred":[
        "Chainpurwa"
    ],
    "wof:name":"Chainpurwa",
    "wof:placetype":"locality",
    "wof:population":115
},
  "geometry": {"coordinates":[81.18911199999999,28.130885],"type":"Point"}
}