{
  "type": "Feature",
  "properties": {
    "iso:country":"IN",
    "ks:ks_name":"Bandarchua",
    "ks:ks_pop":23,
    "ks:ks_type":"VILLAGE",
    "name:eng_x_preferred":[
        "Bandarchua"
    ],
    "wof:name":"Bandarchua",
    "wof:placetype":"locality",
    "wof:population":23
},
  "geometry": {"coordinates":[86.773821,24.21053],"type":"Point"}
}