{
  "type": "Feature",
  "properties": {
    "iso:country":"IN",
    "ks:ks_name":"Chougalewadi",
    "ks:ks_pop":132,
    "ks:ks_type":"HABITATION",
    "name:eng_x_preferred":[
        "Chougalewadi"
    ],
    "wof:name":"Chougalewadi",
    "wof:placetype":"locality",
    "wof:population":132
},
  "geometry": {"coordinates":[74.03274999999999,16.705506],"type":"Point"}
}