{
  "type": "Feature",
  "properties": {
    "iso:country":"IN",
    "ks:ks_name":"Devarahatti",
    "ks:ks_pop":471,
    "ks:ks_type":"HABITATION",
    "name:eng_x_preferred":[
        "Devarahatti"
    ],
    "wof:name":"Devarahatti",
    "wof:placetype":"locality",
    "wof:population":471
},
  "geometry": {"coordinates":[77.126529,13.954592],"type":"Point"}
}