{
  "type": "Feature",
  "properties": {
    "iso:country":"IN",
    "ks:ks_name":"Yelplavwadi",
    "ks:ks_pop":32,
    "ks:ks_type":"HABITATION",
    "name:eng_x_preferred":[
        "Yelplavwadi"
    ],
    "wof:name":"Yelplavwadi",
    "wof:placetype":"locality",
    "wof:population":32
},
  "geometry": {"coordinates":[73.72119000000001,15.998704],"type":"Point"}
}