{
  "type": "Feature",
  "properties": {
    "gn:admin1_code":"21.0",
    "gn:admin2_code":"398.0",
    "gn:asciiname":"Eguva Kuntigam",
    "gn:country_code":"IN",
    "gn:dem":1123,
    "gn:feature_class":"P",
    "gn:feature_code":"PPL",
    "gn:name":"Eguva Kuntig\u0101m",
    "gn:population":0,
    "gn:timezone":"Asia/Kolkata",
    "iso:country":"IN",
    "wof:name":"Eguva Kuntigam",
    "wof:placetype":"neighbourhood"
},
  "geometry": {"coordinates":[83.00527,18.69434],"type":"Point"}
}