{
  "type": "Feature",
  "properties": {
    "iso:country":"IN",
    "ks:ks_name":"Kamatchipuram",
    "ks:ks_pop":220,
    "ks:ks_type":"HABITATION",
    "name:eng_x_preferred":[
        "Kamatchipuram"
    ],
    "wof:name":"Kamatchipuram",
    "wof:placetype":"locality",
    "wof:population":220
},
  "geometry": {"coordinates":[77.832815,9.984014],"type":"Point"}
}