{
  "type": "Feature",
  "properties": {
    "gn:admin1_code":"34.0",
    "gn:admin2_code":"207.0",
    "gn:asciiname":"Ranipatti",
    "gn:country_code":"IN",
    "gn:dem":73,
    "gn:feature_class":"P",
    "gn:feature_code":"PPL",
    "gn:name":"R\u0101n\u012bpatti",
    "gn:population":0,
    "gn:timezone":"Asia/Kolkata",
    "iso:country":"IN",
    "ks:ks_alt_nam":"RANIPATTI",
    "ks:ks_name":"Ranipatti",
    "ks:ks_pop":1043,
    "ks:ks_type":"HABITATION",
    "ks:ks_uagg_main":0,
    "name:eng_x_preferred":[
        "Ranipatti"
    ],
    "wof:name":"Ranipatti",
    "wof:placetype":"neighbourhood",
    "wof:population":1043
},
  "geometry": {"coordinates":[85.98655100000001,26.63812],"type":"Point"}
}