{
  "type": "Feature",
  "properties": {
    "gn:admin1_code":"39.0",
    "gn:admin2_code":"60.0",
    "gn:asciiname":"Kaul",
    "gn:country_code":"IN",
    "gn:dem":1308,
    "gn:feature_class":"P",
    "gn:feature_code":"PPL",
    "gn:name":"Kaul",
    "gn:population":0,
    "gn:timezone":"Asia/Kolkata",
    "iso:country":"IN",
    "name:deu_x_preferred":[
        "Kaul"
    ],
    "name:hin_x_preferred":[
        "\u0915\u094c\u0932"
    ],
    "name:por_x_preferred":[
        "Kaul"
    ],
    "wof:name":"Kaul",
    "wof:placetype":"locality"
},
  "geometry": {"coordinates":[77.76725,30.69156],"type":"Point"}
}