{
  "type": "Feature",
  "properties": {
    "gn:admin1_code":"33",
    "gn:admin2_code":"585.0",
    "gn:asciiname":"Pomburpa",
    "gn:country_code":"IN",
    "gn:dem":83,
    "gn:feature_class":"P",
    "gn:feature_code":"PPL",
    "gn:name":"Pomburpa",
    "gn:population":0,
    "gn:timezone":"Asia/Kolkata",
    "iso:country":"IN",
    "ks:ks_name":"Pomburpa",
    "ks:ks_pop":3315,
    "ks:ks_type":"VILLAGE",
    "name:eng_x_preferred":[
        "Pomburpa"
    ],
    "wof:name":"Pomburpa",
    "wof:placetype":"locality",
    "wof:population":3315
},
  "geometry": {"coordinates":[73.856595,15.567282],"type":"Point"}
}