{
  "type": "Feature",
  "properties": {
    "gn:admin1_code":"36",
    "gn:admin2_code":"191.0",
    "gn:asciiname":"Durjanpur",
    "gn:country_code":"IN",
    "gn:dem":85,
    "gn:feature_class":"P",
    "gn:feature_code":"PPL",
    "gn:name":"Durjanpur",
    "gn:population":0,
    "gn:timezone":"Asia/Kolkata",
    "iso:country":"IN",
    "ks:ks_name":"Durjanpur",
    "ks:ks_type":"VILLAGE",
    "name:eng_x_preferred":[
        "Durjanpur"
    ],
    "wof:name":"Durjanpur",
    "wof:placetype":"locality"
},
  "geometry": {"coordinates":[83.099735,26.054193],"type":"Point"}
}