{
  "type": "Feature",
  "properties": {
    "iso:country":"IN",
    "ks:ks_alt_nam":"TUFANIA LUNGA",
    "ks:ks_name":"Tufania Lunga",
    "ks:ks_pop":673,
    "ks:ks_type":"HABITATION",
    "ks:ks_uagg_main":0,
    "name:eng_x_preferred":[
        "Tufania Lunga"
    ],
    "wof:name":"Tufania Lunga",
    "wof:placetype":"neighbourhood",
    "wof:population":673
},
  "geometry": {"coordinates":[91.28319999999999,23.925599],"type":"Point"}
}