{
  "type": "Feature",
  "properties": {
    "gn:admin1_code":"11",
    "gn:admin2_code":"23.0",
    "gn:asciiname":"Jadoli",
    "gn:country_code":"IN",
    "gn:dem":1444,
    "gn:feature_class":"P",
    "gn:feature_code":"PPL",
    "gn:name":"Jadoli",
    "gn:population":0,
    "gn:timezone":"Asia/Kolkata",
    "iso:country":"IN",
    "wof:name":"Jadoli",
    "wof:placetype":"locality"
},
  "geometry": {"coordinates":[76.29113000000002,32.47116],"type":"Point"}
}