{
  "type": "Feature",
  "properties": {
    "iso:country":"IN",
    "ks:ks_name":"Talapajupahad",
    "ks:ks_pop":5,
    "ks:ks_type":"VILLAGE",
    "name:eng_x_preferred":[
        "Talapajupahad"
    ],
    "wof:name":"Talapajupahad",
    "wof:placetype":"locality",
    "wof:population":5
},
  "geometry": {"coordinates":[84.562513,20.375606],"type":"Point"}
}