{
  "type": "Feature",
  "properties": {
    "gn:admin1_code":"39.0",
    "gn:admin2_code":"61.0",
    "gn:asciiname":"Kolli",
    "gn:country_code":"IN",
    "gn:dem":1389,
    "gn:feature_class":"P",
    "gn:feature_code":"PPL",
    "gn:name":"Kolli",
    "gn:population":0,
    "gn:timezone":"Asia/Kolkata",
    "iso:country":"IN",
    "name:deu_x_preferred":[
        "Kolli"
    ],
    "name:fin_x_preferred":[
        "Kolli"
    ],
    "name:tel_x_preferred":[
        "\u0c15\u0c4a\u0c32\u0c4d\u0c32\u0c3f"
    ],
    "wof:name":"Kolli",
    "wof:placetype":"locality"
},
  "geometry": {"coordinates":[79.06206,29.70999],"type":"Point"}
}