{
  "type": "Feature",
  "properties": {
    "gn:admin1_code":"36.0",
    "gn:admin2_code":"159",
    "gn:asciiname":"Kainchia",
    "gn:country_code":"IN",
    "gn:dem":146,
    "gn:feature_class":"P",
    "gn:feature_code":"PPL",
    "gn:name":"Kainchia",
    "gn:population":0,
    "gn:timezone":"Asia/Kolkata",
    "iso:country":"IN",
    "wof:name":"Kainchia",
    "wof:placetype":"locality"
},
  "geometry": {"coordinates":[79.51023000000001,27.51408],"type":"Point"}
}