{
  "type": "Feature",
  "properties": {
    "gn:admin1_code":"16.0",
    "gn:admin2_code":"508.0",
    "gn:asciiname":"Peta",
    "gn:country_code":"IN",
    "gn:dem":286,
    "gn:feature_class":"P",
    "gn:feature_code":"PPL",
    "gn:name":"Peta",
    "gn:population":0,
    "gn:timezone":"Asia/Kolkata",
    "iso:country":"IN",
    "ks:ks_name":"Peta",
    "ks:ks_pop":176,
    "ks:ks_type":"VILLAGE",
    "name:eng_x_preferred":[
        "Peta"
    ],
    "name:isl_x_preferred":[
        "Peta"
    ],
    "wof:name":"Peta",
    "wof:placetype":"locality",
    "wof:population":176
},
  "geometry": {"coordinates":[80.31974599999999,19.792798],"type":"Point"}
}