{
  "type": "Feature",
  "properties": {
    "gn:admin1_code":"16.0",
    "gn:admin2_code":"508.0",
    "gn:asciiname":"Peta",
    "gn:country_code":"IN",
    "gn:dem":286,
    "gn:feature_class":"P",
    "gn:feature_code":"PPL",
    "gn:name":"Peta",
    "gn:population":0,
    "gn:timezone":"Asia/Kolkata",
    "iso:country":"IN",
    "name:isl_x_preferred":[
        "Peta"
    ],
    "wof:name":"Peta",
    "wof:placetype":"locality"
},
  "geometry": {"coordinates":[80.31975,19.7928],"type":"Point"}
}