{
  "type": "Feature",
  "properties": {
    "iso:country":"IN",
    "ks:ks_name":"Purnachandrapur",
    "ks:ks_pop":259,
    "ks:ks_type":"VILLAGE",
    "name:eng_x_preferred":[
        "Purnachandrapur"
    ],
    "wof:name":"Purnachandrapur",
    "wof:placetype":"locality",
    "wof:population":259
},
  "geometry": {"coordinates":[86.633144,21.82612],"type":"Point"}
}