{
  "type": "Feature",
  "properties": {
    "gn:admin1_code":"19.0",
    "gn:admin2_code":"568.0",
    "gn:asciiname":"Gersa",
    "gn:country_code":"IN",
    "gn:dem":643,
    "gn:feature_class":"P",
    "gn:feature_code":"PPL",
    "gn:name":"Gersa",
    "gn:population":0,
    "gn:timezone":"Asia/Kolkata",
    "iso:country":"IN",
    "ks:ks_name":"Gerasa",
    "ks:ks_pop":125,
    "ks:ks_type":"HABITATION",
    "name:eng_x_preferred":[
        "Gerasa"
    ],
    "name:eng_x_variant":[
        "Gersa"
    ],
    "wof:name":"Gerasa",
    "wof:placetype":"locality",
    "wof:population":125
},
  "geometry": {"coordinates":[75.240548,13.664645],"type":"Point"}
}