{
  "type": "Feature",
  "properties": {
    "iso:country":"IN",
    "ks:ks_name":"Sabuda",
    "ks:ks_pop":255,
    "ks:ks_type":"HABITATION",
    "name:eng_x_preferred":[
        "Sabuda"
    ],
    "wof:name":"Sabuda",
    "wof:placetype":"locality",
    "wof:population":255
},
  "geometry": {"coordinates":[92.158208,25.708075],"type":"Point"}
}