{
  "type": "Feature",
  "properties": {
    "iso:country":"IN",
    "ks:ks_name":"Bilaritola",
    "ks:ks_pop":111,
    "ks:ks_type":"HABITATION",
    "name:eng_x_preferred":[
        "Bilaritola"
    ],
    "wof:name":"Bilaritola",
    "wof:placetype":"locality",
    "wof:population":111
},
  "geometry": {"coordinates":[82.698639,23.884023],"type":"Point"}
}