{
  "type": "Feature",
  "properties": {
    "iso:country":"IN",
    "ks:ks_name":"Minya Tola",
    "ks:ks_pop":1908,
    "ks:ks_type":"HABITATION",
    "ks:ks_uagg_main":0,
    "name:eng_x_preferred":[
        "Minya Tola"
    ],
    "wof:name":"Minya Tola",
    "wof:placetype":"neighbourhood",
    "wof:population":1908
},
  "geometry": {"coordinates":[84.312122,27.105536],"type":"Point"}
}