{
  "type": "Feature",
  "properties": {
    "iso:country":"IN",
    "ks:ks_name":"Meleki Gaon",
    "ks:ks_pop":21,
    "ks:ks_type":"VILLAGE",
    "ks:ks_uagg_main":0,
    "name:eng_x_preferred":[
        "Meleki Gaon"
    ],
    "wof:name":"Meleki Gaon",
    "wof:placetype":"neighbourhood",
    "wof:population":21
},
  "geometry": {"coordinates":[94.400144,27.32368],"type":"Point"}
}