{
  "type": "Feature",
  "properties": {
    "iso:country":"IN",
    "ks:ks_name":"Padampur",
    "ks:ks_pop":120,
    "ks:ks_type":"HABITATION",
    "name:eng_x_preferred":[
        "Padampur"
    ],
    "wof:name":"Padampur",
    "wof:placetype":"locality",
    "wof:population":120
},
  "geometry": {"coordinates":[82.02512400000001,18.093614],"type":"Point"}
}