{
  "type": "Feature",
  "properties": {
    "iso:country":"IN",
    "ks:ks_name":"Umerpur Bakhtauri",
    "ks:ks_pop":566,
    "ks:ks_type":"HABITATION",
    "ks:ks_uagg_main":0,
    "name:eng_x_preferred":[
        "Umerpur Bakhtauri"
    ],
    "wof:name":"Umerpur Bakhtauri",
    "wof:placetype":"neighbourhood",
    "wof:population":566
},
  "geometry": {"coordinates":[80.141994,26.913451],"type":"Point"}
}