{
  "type": "Feature",
  "properties": {
    "iso:country":"IN",
    "ks:ks_name":"Paliarpur",
    "ks:ks_pop":1610,
    "ks:ks_type":"VILLAGE",
    "name:eng_x_preferred":[
        "Paliarpur"
    ],
    "wof:name":"Paliarpur",
    "wof:placetype":"locality",
    "wof:population":1610
},
  "geometry": {"coordinates":[86.454104,26.009613],"type":"Point"}
}