{
  "type": "Feature",
  "properties": {
    "gn:admin1_code":"02",
    "gn:admin2_code":"552.0",
    "gn:asciiname":"Molagavalli",
    "gn:country_code":"IN",
    "gn:dem":474,
    "gn:feature_class":"P",
    "gn:feature_code":"PPL",
    "gn:name":"Molagavalli",
    "gn:population":0,
    "gn:timezone":"Asia/Kolkata",
    "iso:country":"IN",
    "name:hin_x_preferred":[
        "\u092e\u094a\u0932\u0917\u0935\u0932\u094d\u0932\u093f"
    ],
    "name:new_x_preferred":[
        "\u092e\u094a\u0932\u0917\u0935\u0932\u094d\u0932\u093f"
    ],
    "name:tel_x_preferred":[
        "\u0c2e\u0c4a\u0c32\u0c17\u0c35\u0c32\u0c4d\u0c32\u0c3f"
    ],
    "wof:name":"Molagavalli",
    "wof:placetype":"locality"
},
  "geometry": {"coordinates":[77.33098000000003,15.35721],"type":"Point"}
}