{
  "type": "Feature",
  "properties": {
    "gn:admin1_code":"02",
    "gn:admin2_code":"552.0",
    "gn:asciiname":"Molagavalli",
    "gn:country_code":"IN",
    "gn:dem":474,
    "gn:feature_class":"P",
    "gn:feature_code":"PPL",
    "gn:name":"Molagavalli",
    "gn:population":0,
    "gn:timezone":"Asia/Kolkata",
    "iso:country":"IN",
    "wof:name":"Molagavalli",
    "wof:placetype":"locality"
},
  "geometry": {"coordinates":[77.33098000000003,15.35721],"type":"Point"}
}