{
  "type": "Feature",
  "properties": {
    "iso:country":"IN",
    "ks:ks_name":"N Lujharsahi",
    "ks:ks_pop":334,
    "ks:ks_type":"HABITATION",
    "name:eng_x_preferred":[
        "N Lujharsahi"
    ],
    "wof:name":"N Lujharsahi",
    "wof:placetype":"locality",
    "wof:population":334
},
  "geometry": {"coordinates":[84.826668,21.852879],"type":"Point"}
}