{
  "type": "Feature",
  "properties": {
    "iso:country":"IN",
    "ks:ks_name":"Mundelu",
    "ks:ks_pop":100,
    "ks:ks_type":"HABITATION",
    "name:eng_x_preferred":[
        "Mundelu"
    ],
    "wof:name":"Mundelu",
    "wof:placetype":"locality",
    "wof:population":100
},
  "geometry": {"coordinates":[75.162491,13.033333],"type":"Point"}
}