{
  "type": "Feature",
  "properties": {
    "iso:country":"IN",
    "ks:ks_name":"Pabni Khurd",
    "ks:ks_pop":402,
    "ks:ks_type":"VILLAGE",
    "name:eng_x_preferred":[
        "Pabni Khurd"
    ],
    "wof:name":"Pabni Khurd",
    "wof:placetype":"locality",
    "wof:population":402
},
  "geometry": {"coordinates":[77.250469,30.255227],"type":"Point"}
}