{
  "type": "Feature",
  "properties": {
    "iso:country":"IN",
    "ks:ks_name":"Poovalur Vadavayal",
    "ks:ks_pop":110,
    "ks:ks_type":"HABITATION",
    "name:eng_x_preferred":[
        "Poovalur Vadavayal"
    ],
    "wof:name":"Poovalur Vadavayal",
    "wof:placetype":"locality",
    "wof:population":110
},
  "geometry": {"coordinates":[79.091339,10.057118],"type":"Point"}
}