{
  "type": "Feature",
  "properties": {
    "iso:country":"IN",
    "ks:ks_name":"Banjipadar",
    "ks:ks_pop":366,
    "ks:ks_type":"VILLAGE",
    "ks:ks_uagg_main":0,
    "name:eng_x_preferred":[
        "Banjipadar"
    ],
    "wof:name":"Banjipadar",
    "wof:placetype":"neighbourhood",
    "wof:population":366
},
  "geometry": {"coordinates":[82.96825699999999,20.276432],"type":"Point"}
}