{
  "type": "Feature",
  "properties": {
    "iso:country":"IN",
    "ks:ks_name":"Mangamamba Puram",
    "ks:ks_pop":36,
    "ks:ks_type":"HABITATION",
    "name:eng_x_preferred":[
        "Mangamamba Puram"
    ],
    "wof:name":"Mangamamba Puram",
    "wof:placetype":"locality",
    "wof:population":36
},
  "geometry": {"coordinates":[79.23207600000001,13.203859],"type":"Point"}
}