{
  "type": "Feature",
  "properties": {
    "iso:country":"IN",
    "ks:ks_name":"Pallippadi Myladikunnu",
    "ks:ks_pop":200,
    "ks:ks_type":"HABITATION",
    "ks:ks_uagg_main":0,
    "name:eng_x_preferred":[
        "Pallippadi Myladikunnu"
    ],
    "wof:name":"Pallippadi Myladikunnu",
    "wof:placetype":"neighbourhood",
    "wof:population":200
},
  "geometry": {"coordinates":[76.03684800000001,11.679975],"type":"Point"}
}