{
  "type": "Feature",
  "properties": {
    "iso:country":"IN",
    "ks:ks_name":"Vanzar Fa",
    "ks:ks_pop":168,
    "ks:ks_type":"HABITATION",
    "name:eng_x_preferred":[
        "Vanzar Fa"
    ],
    "wof:name":"Vanzar Fa",
    "wof:placetype":"locality",
    "wof:population":168
},
  "geometry": {"coordinates":[73.02847199999999,20.440278],"type":"Point"}
}