{
  "type": "Feature",
  "properties": {
    "gn:admin1_code":"35.0",
    "gn:admin2_code":"425.0",
    "gn:asciiname":"Purwa Bamhori",
    "gn:country_code":"IN",
    "gn:dem":167,
    "gn:feature_class":"P",
    "gn:feature_code":"PPL",
    "gn:name":"Purwa Bamhori",
    "gn:population":0,
    "gn:timezone":"Asia/Kolkata",
    "iso:country":"IN",
    "wof:name":"Purwa Bamhori",
    "wof:placetype":"locality"
},
  "geometry": {"coordinates":[80.04785,25.19127000000001],"type":"Point"}
}