{
  "type": "Feature",
  "properties": {
    "gn:admin1_code":"35.0",
    "gn:admin2_code":"455.0",
    "gn:asciiname":"Bijakwara",
    "gn:country_code":"IN",
    "gn:dem":815,
    "gn:feature_class":"P",
    "gn:feature_code":"PPL",
    "gn:name":"Bijakw\u0101ra",
    "gn:population":0,
    "gn:timezone":"Asia/Kolkata",
    "iso:country":"IN",
    "wof:name":"Bijakwara",
    "wof:placetype":"locality"
},
  "geometry": {"coordinates":[78.71460999999999,22.10464],"type":"Point"}
}