{
  "type": "Feature",
  "properties": {
    "iso:country":"IN",
    "ks:ks_name":"Mal",
    "ks:ks_pop":682,
    "ks:ks_type":"VILLAGE",
    "name:eng_x_preferred":[
        "Mal"
    ],
    "wof:name":"Mal",
    "wof:placetype":"locality",
    "wof:population":682
},
  "geometry": {"coordinates":[73.544,24.0944],"type":"Point"}
}