{
  "type": "Feature",
  "properties": {
    "gn:admin1_code":"35",
    "gn:admin2_code":"443.0",
    "gn:asciiname":"Simarhar",
    "gn:country_code":"IN",
    "gn:dem":437,
    "gn:feature_class":"P",
    "gn:feature_code":"PPL",
    "gn:name":"Simarh\u0101r",
    "gn:population":0,
    "gn:timezone":"Asia/Kolkata",
    "iso:country":"IN",
    "wof:name":"Simarhar",
    "wof:placetype":"locality"
},
  "geometry": {"coordinates":[77.98421999999999,23.61229],"type":"Point"}
}