{
  "type": "Feature",
  "properties": {
    "gn:admin1_code":"25.0",
    "gn:asciiname":"Hulimavu",
    "gn:country_code":"IN",
    "gn:dem":917,
    "gn:feature_class":"P",
    "gn:feature_code":"PPL",
    "gn:name":"Hulimavu",
    "gn:population":0,
    "gn:timezone":"Asia/Kolkata",
    "iso:country":"IN",
    "wof:name":"Hulimavu",
    "wof:placetype":"neighbourhood"
},
  "geometry": {"coordinates":[77.59558,12.87707],"type":"Point"}
}