{
  "type": "Feature",
  "properties": {
    "iso:country":"IN",
    "ks:ks_name":"Phajilpura",
    "ks:ks_pop":310,
    "ks:ks_type":"HABITATION",
    "name:eng_x_preferred":[
        "Phajilpura"
    ],
    "wof:name":"Phajilpura",
    "wof:placetype":"locality",
    "wof:population":310
},
  "geometry": {"coordinates":[75.592324,21.858197],"type":"Point"}
}