{
  "type": "Feature",
  "properties": {
    "gn:admin1_code":"16.0",
    "gn:admin2_code":"509.0",
    "gn:asciiname":"Dahegaon",
    "gn:country_code":"IN",
    "gn:dem":169,
    "gn:feature_class":"P",
    "gn:feature_code":"PPL",
    "gn:name":"D\u0101hegaon",
    "gn:population":0,
    "gn:timezone":"Asia/Kolkata",
    "iso:country":"IN",
    "name:pam_x_preferred":[
        "Dahegaon"
    ],
    "name:tel_x_preferred":[
        "\u0c26\u0c39\u0c47\u0c17\u0c3e\u0c35\u0c4d"
    ],
    "name:vie_x_preferred":[
        "Dahegaon"
    ],
    "wof:name":"Dahegaon",
    "wof:placetype":"neighbourhood"
},
  "geometry": {"coordinates":[79.69875999999999,19.60955],"type":"Point"}
}