{
  "type": "Feature",
  "properties": {
    "iso:country":"IN",
    "ks:ks_name":"Keloth Vayal",
    "ks:ks_pop":1920,
    "ks:ks_type":"HABITATION",
    "name:eng_x_preferred":[
        "Keloth Vayal"
    ],
    "wof:name":"Keloth Vayal",
    "wof:placetype":"locality",
    "wof:population":1920
},
  "geometry": {"coordinates":[75.824223,11.552914],"type":"Point"}
}