{
  "type": "Feature",
  "properties": {
    "iso:country":"IN",
    "ks:ks_name":"Nanukua",
    "ks:ks_pop":1380,
    "ks:ks_type":"VILLAGE",
    "ks:ks_uagg_main":0,
    "name:eng_x_preferred":[
        "Nanukua"
    ],
    "wof:name":"Nanukua",
    "wof:placetype":"neighbourhood",
    "wof:population":1380
},
  "geometry": {"coordinates":[86.572531,20.307314],"type":"Point"}
}