{
  "type": "Feature",
  "properties": {
    "iso:country":"IN",
    "ks:ks_alt_nam":"Thathapuram ADC",
    "ks:ks_name":"Thathapuram Adc",
    "ks:ks_pop":1000,
    "ks:ks_type":"HABITATION",
    "name:eng_x_preferred":[
        "Thathapuram Adc"
    ],
    "wof:name":"Thathapuram Adc",
    "wof:placetype":"locality",
    "wof:population":1000
},
  "geometry": {"coordinates":[79.608947,12.343168],"type":"Point"}
}