{
  "type": "Feature",
  "properties": {
    "iso:country":"IN",
    "ks:ks_name":"Sarpanch Fa",
    "ks:ks_pop":322,
    "ks:ks_type":"HABITATION",
    "name:eng_x_preferred":[
        "Sarpanch Fa"
    ],
    "wof:name":"Sarpanch Fa",
    "wof:placetype":"locality",
    "wof:population":322
},
  "geometry": {"coordinates":[72.982083,20.473111],"type":"Point"}
}