{
  "type": "Feature",
  "properties": {
    "iso:country":"IN",
    "ks:ks_name":"Barahi",
    "ks:ks_pop":670,
    "ks:ks_type":"HABITATION",
    "name:eng_x_preferred":[
        "Barahi"
    ],
    "wof:name":"Barahi",
    "wof:placetype":"locality",
    "wof:population":670
},
  "geometry": {"coordinates":[82.582705,19.832285],"type":"Point"}
}