{
  "type": "Feature",
  "properties": {
    "gn:admin1_code":"19.0",
    "gn:admin2_code":"568.0",
    "gn:asciiname":"Kunnur",
    "gn:country_code":"IN",
    "gn:dem":663,
    "gn:feature_class":"P",
    "gn:feature_code":"PPL",
    "gn:name":"Kunn\u016br",
    "gn:population":0,
    "gn:timezone":"Asia/Kolkata",
    "iso:country":"IN",
    "name:msa_x_preferred":[
        "Kunnur"
    ],
    "wof:name":"Kunnur",
    "wof:placetype":"locality"
},
  "geometry": {"coordinates":[75.18225,13.91683],"type":"Point"}
}