{
  "type": "Feature",
  "properties": {
    "iso:country":"IN",
    "ks:ks_name":"Khurait",
    "ks:ks_pop":338,
    "ks:ks_type":"VILLAGE",
    "name:eng_x_preferred":[
        "Khurait"
    ],
    "wof:name":"Khurait",
    "wof:placetype":"locality",
    "wof:population":338
},
  "geometry": {"coordinates":[78.31684799999999,30.403901],"type":"Point"}
}