{
  "type": "Feature",
  "properties": {
    "iso:country":"IN",
    "ks:ks_name":"Omankadu",
    "ks:ks_pop":108,
    "ks:ks_type":"HABITATION",
    "name:eng_x_preferred":[
        "Omankadu"
    ],
    "wof:name":"Omankadu",
    "wof:placetype":"locality",
    "wof:population":108
},
  "geometry": {"coordinates":[79.53768100000001,10.405217],"type":"Point"}
}