{
  "type": "Feature",
  "properties": {
    "iso:country":"IN",
    "ks:ks_name":"Manive",
    "ks:ks_pop":28,
    "ks:ks_type":"HABITATION",
    "name:eng_x_preferred":[
        "Manive"
    ],
    "wof:name":"Manive",
    "wof:placetype":"locality",
    "wof:population":28
},
  "geometry": {"coordinates":[75.40640399999999,13.755496],"type":"Point"}
}