{
  "type": "Feature",
  "properties": {
    "iso:country":"IN",
    "ks:ks_name":"Singo Ki Jod",
    "ks:ks_pop":163,
    "ks:ks_type":"HABITATION",
    "name:eng_x_preferred":[
        "Singo Ki Jod"
    ],
    "wof:name":"Singo Ki Jod",
    "wof:placetype":"locality",
    "wof:population":163
},
  "geometry": {"coordinates":[73.07358000000001,24.601768],"type":"Point"}
}