{
  "type": "Feature",
  "properties": {
    "iso:country":"IN",
    "ks:ks_name":"Meivalisalai",
    "ks:ks_pop":352,
    "ks:ks_type":"HABITATION",
    "ks:ks_uagg_main":0,
    "name:eng_x_preferred":[
        "Meivalisalai"
    ],
    "wof:name":"Meivalisalai",
    "wof:placetype":"neighbourhood",
    "wof:population":352
},
  "geometry": {"coordinates":[78.733045,10.481072],"type":"Point"}
}