{
  "type": "Feature",
  "properties": {
    "iso:country":"IN",
    "ks:ks_name":"Suzawali",
    "ks:ks_pop":215,
    "ks:ks_type":"HABITATION",
    "name:eng_x_preferred":[
        "Suzawali"
    ],
    "wof:name":"Suzawali",
    "wof:placetype":"locality",
    "wof:population":215
},
  "geometry": {"coordinates":[78.72237,27.94357],"type":"Point"}
}