{
  "type": "Feature",
  "properties": {
    "gn:admin1_code":"36.0",
    "gn:admin2_code":"183.0",
    "gn:asciiname":"Muhammadpur",
    "gn:country_code":"IN",
    "gn:dem":110,
    "gn:feature_class":"P",
    "gn:feature_code":"PPL",
    "gn:name":"Muhammadpur",
    "gn:population":0,
    "gn:timezone":"Asia/Kolkata",
    "iso:country":"IN",
    "wof:name":"Muhammadpur",
    "wof:placetype":"locality"
},
  "geometry": {"coordinates":[81.66840999999999,27.21157],"type":"Point"}
}