{
  "type": "Feature",
  "properties": {
    "iso:country":"IN",
    "ks:ks_name":"Sautadewasti",
    "ks:ks_pop":100,
    "ks:ks_type":"HABITATION",
    "name:eng_x_preferred":[
        "Sautadewasti"
    ],
    "wof:name":"Sautadewasti",
    "wof:placetype":"locality",
    "wof:population":100
},
  "geometry": {"coordinates":[74.75271600000001,18.687781],"type":"Point"}
}