{
  "type": "Feature",
  "properties": {
    "iso:country":"IN",
    "ks:ks_name":"Allipur",
    "ks:ks_pop":0,
    "ks:ks_type":"VILLAGE",
    "name:eng_x_preferred":[
        "Allipur"
    ],
    "wof:name":"Allipur",
    "wof:placetype":"locality",
    "wof:population":0
},
  "geometry": {"coordinates":[77.772482,28.503795],"type":"Point"}
}