{
  "type": "Feature",
  "properties": {
    "gn:admin1_code":"2.0",
    "gn:admin2_code":"544.0",
    "gn:asciiname":"Jarjulu",
    "gn:country_code":"IN",
    "gn:dem":817,
    "gn:feature_class":"P",
    "gn:feature_code":"PPL",
    "gn:name":"Jarjulu",
    "gn:population":0,
    "gn:timezone":"Asia/Kolkata",
    "iso:country":"IN",
    "wof:name":"Jarjulu",
    "wof:placetype":"locality"
},
  "geometry": {"coordinates":[82.46954000000002,18.3434],"type":"Point"}
}