{
  "type": "Feature",
  "properties": {
    "iso:country":"IN",
    "ks:ks_name":"Ukharapara",
    "ks:ks_pop":569,
    "ks:ks_type":"VILLAGE",
    "name:eng_x_preferred":[
        "Ukharapara"
    ],
    "wof:name":"Ukharapara",
    "wof:placetype":"locality",
    "wof:population":569
},
  "geometry": {"coordinates":[87.813804,22.358532],"type":"Point"}
}