{
  "type": "Feature",
  "properties": {
    "iso:country":"IN",
    "ks:ks_name":"Khotwadi",
    "ks:ks_pop":42,
    "ks:ks_type":"HABITATION",
    "name:eng_x_preferred":[
        "Khotwadi"
    ],
    "wof:name":"Khotwadi",
    "wof:placetype":"locality",
    "wof:population":42
},
  "geometry": {"coordinates":[73.235772,17.80295],"type":"Point"}
}