{
  "type": "Feature",
  "properties": {
    "gn:admin1_code":"11",
    "gn:admin2_code":"23.0",
    "gn:asciiname":"Sakreti",
    "gn:country_code":"IN",
    "gn:dem":1533,
    "gn:feature_class":"P",
    "gn:feature_code":"PPL",
    "gn:name":"Sakreti",
    "gn:population":0,
    "gn:timezone":"Asia/Kolkata",
    "iso:country":"IN",
    "wof:name":"Sakreti",
    "wof:placetype":"locality"
},
  "geometry": {"coordinates":[76.33511999999997,32.45487],"type":"Point"}
}