{
  "type": "Feature",
  "properties": {
    "gn:admin1_code":"12",
    "gn:admin2_code":"14.0",
    "gn:asciiname":"Tsandian",
    "gn:country_code":"IN",
    "gn:dem":1643,
    "gn:feature_class":"P",
    "gn:feature_code":"PPL",
    "gn:name":"Tsandian",
    "gn:population":0,
    "gn:timezone":"Asia/Kolkata",
    "iso:country":"IN",
    "wof:name":"Tsandian",
    "wof:placetype":"locality"
},
  "geometry": {"coordinates":[75.12196999999998,33.65731],"type":"Point"}
}