{
  "type": "Feature",
  "properties": {
    "gn:admin1_code":"25.0",
    "gn:admin2_code":"604",
    "gn:asciiname":"Chunampet",
    "gn:country_code":"IN",
    "gn:dem":11,
    "gn:feature_class":"P",
    "gn:feature_code":"PPL",
    "gn:name":"Ch\u016bn\u0101mpet",
    "gn:population":0,
    "gn:timezone":"Asia/Kolkata",
    "iso:country":"IN",
    "name:und_x_variant":[
        "Ch\u016bn\u0101mpet",
        "Ch\u016bn\u0101mpettai"
    ],
    "wof:name":"Chunampet",
    "wof:placetype":"neighbourhood"
},
  "geometry": {"coordinates":[79.90331999999999,12.25585],"type":"Point"}
}