{
  "type": "Feature",
  "properties": {
    "iso:country":"IN",
    "ks:ks_name":"Urkiapadar",
    "ks:ks_pop":297,
    "ks:ks_type":"VILLAGE",
    "name:eng_x_preferred":[
        "Urkiapadar"
    ],
    "wof:name":"Urkiapadar",
    "wof:placetype":"locality",
    "wof:population":297
},
  "geometry": {"coordinates":[84.09853699999999,20.288572],"type":"Point"}
}