{
  "type": "Feature",
  "properties": {
    "iso:country":"IN",
    "ks:ks_name":"Khai Engti",
    "ks:ks_pop":114,
    "ks:ks_type":"HABITATION",
    "name:eng_x_preferred":[
        "Khai Engti"
    ],
    "wof:name":"Khai Engti",
    "wof:placetype":"locality",
    "wof:population":114
},
  "geometry": {"coordinates":[93.24464500000001,26.375182],"type":"Point"}
}