{
  "type": "Feature",
  "properties": {
    "gn:admin1_code":"16",
    "gn:admin2_code":"500.0",
    "gn:asciiname":"Madakhed",
    "gn:country_code":"IN",
    "gn:dem":262,
    "gn:feature_class":"P",
    "gn:feature_code":"PPL",
    "gn:name":"Mad\u0101khed",
    "gn:population":0,
    "gn:timezone":"Asia/Kolkata",
    "iso:country":"IN",
    "name:und_x_variant":[
        "Madhakhed-Bujruk",
        "Mad\u0101khed"
    ],
    "wof:name":"Madakhed",
    "wof:placetype":"neighbourhood"
},
  "geometry": {"coordinates":[76.58772,20.97658],"type":"Point"}
}