{
  "type": "Feature",
  "properties": {
    "iso:country":"IN",
    "ks:ks_name":"Bhalaguri",
    "ks:ks_pop":78,
    "ks:ks_type":"HABITATION",
    "name:eng_x_preferred":[
        "Bhalaguri"
    ],
    "wof:name":"Bhalaguri",
    "wof:placetype":"locality",
    "wof:population":78
},
  "geometry": {"coordinates":[91.227974,26.732983],"type":"Point"}
}