{
  "type": "Feature",
  "properties": {
    "iso:country":"IN",
    "ks:ks_name":"Sharmawasti",
    "ks:ks_pop":300,
    "ks:ks_type":"HABITATION",
    "name:eng_x_preferred":[
        "Sharmawasti"
    ],
    "wof:name":"Sharmawasti",
    "wof:placetype":"locality",
    "wof:population":300
},
  "geometry": {"coordinates":[74.37023600000001,20.572252],"type":"Point"}
}