{
  "type": "Feature",
  "properties": {
    "iso:country":"IN",
    "ks:ks_name":"Varadappanaidukandiga",
    "ks:ks_pop":26,
    "ks:ks_type":"HABITATION",
    "ks:ks_uagg_main":0,
    "name:eng_x_preferred":[
        "Varadappanaidukandiga"
    ],
    "wof:name":"Varadappanaidukandiga",
    "wof:placetype":"neighbourhood",
    "wof:population":26
},
  "geometry": {"coordinates":[79.296851,13.194355],"type":"Point"}
}