{
  "type": "Feature",
  "properties": {
    "iso:country":"IN",
    "ks:ks_name":"Sukndevpur",
    "ks:ks_pop":360,
    "ks:ks_type":"HABITATION",
    "ks:ks_uagg_main":0,
    "name:eng_x_preferred":[
        "Sukndevpur"
    ],
    "wof:name":"Sukndevpur",
    "wof:placetype":"neighbourhood",
    "wof:population":360
},
  "geometry": {"coordinates":[82.77342299999999,25.512038],"type":"Point"}
}