{
  "type": "Feature",
  "properties": {
    "iso:country":"IN",
    "ks:ks_alt_nam":"Chikkaduvodika thanda",
    "ks:ks_name":"Chikkaduvodika Thanda",
    "ks:ks_pop":50,
    "ks:ks_type":"HABITATION",
    "name:eng_x_preferred":[
        "Chikkaduvodika Thanda"
    ],
    "wof:name":"Chikkaduvodika Thanda",
    "wof:placetype":"locality",
    "wof:population":50
},
  "geometry": {"coordinates":[77.99843199999999,16.79975],"type":"Point"}
}