{
  "type": "Feature",
  "properties": {
    "gn:admin1_code":"36.0",
    "gn:admin2_code":"137.0",
    "gn:asciiname":"Madipura",
    "gn:country_code":"IN",
    "gn:dem":217,
    "gn:feature_class":"P",
    "gn:feature_code":"PPL",
    "gn:name":"Madipura",
    "gn:population":0,
    "gn:timezone":"Asia/Kolkata",
    "iso:country":"IN",
    "name:und_x_variant":[
        "P\u012bpli Kal\u0101n"
    ],
    "wof:name":"Madipura",
    "wof:placetype":"locality"
},
  "geometry": {"coordinates":[78.35548,28.87894],"type":"Point"}
}