{
  "type": "Feature",
  "properties": {
    "gn:admin1_code":"34.0",
    "gn:admin2_code":"221.0",
    "gn:asciiname":"Jan Muhammadpur",
    "gn:country_code":"IN",
    "gn:dem":50,
    "gn:feature_class":"P",
    "gn:feature_code":"PPL",
    "gn:name":"J\u0101n Muhammadpur",
    "gn:population":0,
    "gn:timezone":"Asia/Kolkata",
    "iso:country":"IN",
    "ks:ks_name":"Jan Mohamadpur",
    "ks:ks_pop":497,
    "ks:ks_type":"VILLAGE",
    "name:eng_x_preferred":[
        "Jan Mohamadpur"
    ],
    "name:eng_x_variant":[
        "Jan Muhammadpur"
    ],
    "wof:name":"Jan Mohamadpur",
    "wof:placetype":"locality",
    "wof:population":497
},
  "geometry": {"coordinates":[85.657867,25.712855],"type":"Point"}
}