{
  "type": "Feature",
  "properties": {
    "iso:country":"IN",
    "ks:ks_name":"Kutlupur",
    "ks:ks_pop":434,
    "ks:ks_type":"VILLAGE",
    "name:eng_x_preferred":[
        "Kutlupur"
    ],
    "wof:name":"Kutlupur",
    "wof:placetype":"neighbourhood",
    "wof:population":434
},
  "geometry": {"coordinates":[75.517634,31.321615],"type":"Point"}
}