{
  "type": "Feature",
  "properties": {
    "gn:admin1_code":"37.0",
    "gn:admin2_code":"401",
    "gn:asciiname":"Khormul",
    "gn:country_code":"IN",
    "gn:dem":423,
    "gn:feature_class":"P",
    "gn:feature_code":"PPL",
    "gn:name":"Khormul",
    "gn:population":0,
    "gn:timezone":"Asia/Kolkata",
    "iso:country":"IN",
    "wof:name":"Khormul",
    "wof:placetype":"locality"
},
  "geometry": {"coordinates":[82.83333,23.51667],"type":"Point"}
}