{
  "type": "Feature",
  "properties": {
    "iso:country":"IN",
    "ks:ks_name":"Nunhunda",
    "ks:ks_pop":2915,
    "ks:ks_type":"VILLAGE",
    "name:eng_x_preferred":[
        "Nunhunda"
    ],
    "wof:name":"Nunhunda",
    "wof:placetype":"locality",
    "wof:population":2915
},
  "geometry": {"coordinates":[87.73059600000001,22.081572],"type":"Point"}
}