{
  "type": "Feature",
  "properties": {
    "iso:country":"IN",
    "ks:ks_name":"Soliye",
    "ks:ks_pop":67,
    "ks:ks_type":"HABITATION",
    "name:eng_x_preferred":[
        "Soliye"
    ],
    "wof:name":"Soliye",
    "wof:placetype":"locality",
    "wof:population":67
},
  "geometry": {"coordinates":[74.33538900000001,15.282602],"type":"Point"}
}