{
  "type": "Feature",
  "properties": {
    "gn:admin1_code":"2.0",
    "gn:admin2_code":"544.0",
    "gn:asciiname":"Karakavalasa",
    "gn:country_code":"IN",
    "gn:dem":936,
    "gn:feature_class":"P",
    "gn:feature_code":"PPL",
    "gn:name":"Karakavalasa",
    "gn:population":0,
    "gn:timezone":"Asia/Kolkata",
    "iso:country":"IN",
    "wof:name":"Karakavalasa",
    "wof:placetype":"locality"
},
  "geometry": {"coordinates":[83.00024000000001,18.28913],"type":"Point"}
}