{
  "type": "Feature",
  "properties": {
    "iso:country":"IN",
    "ks:ks_name":"Mushahari",
    "ks:ks_pop":510,
    "ks:ks_type":"HABITATION",
    "name:eng_x_preferred":[
        "Mushahari"
    ],
    "wof:name":"Mushahari",
    "wof:placetype":"locality",
    "wof:population":510
},
  "geometry": {"coordinates":[87.037431,25.993984],"type":"Point"}
}