{
  "type": "Feature",
  "properties": {
    "gn:admin1_code":"12.0",
    "gn:admin2_code":"005",
    "gn:asciiname":"Fazulwala",
    "gn:country_code":"IN",
    "gn:dem":2341,
    "gn:feature_class":"P",
    "gn:feature_code":"PPL",
    "gn:name":"Fazulw\u0101la",
    "gn:population":0,
    "gn:timezone":"Asia/Kolkata",
    "iso:country":"IN",
    "wof:name":"Fazulwala",
    "wof:placetype":"locality"
},
  "geometry": {"coordinates":[74.3001,33.77475],"type":"Point"}
}