{
  "type": "Feature",
  "properties": {
    "iso:country":"IN",
    "ks:ks_name":"Pikkili Malai Reserved Forest",
    "ks:ks_type":"VILLAGE",
    "name:eng_x_preferred":[
        "Pikkili Malai Reserved Forest"
    ],
    "wof:name":"Pikkili Malai Reserved Forest",
    "wof:placetype":"locality"
},
  "geometry": {"coordinates":[77.988482,12.217223],"type":"Point"}
}