{
  "type": "Feature",
  "properties": {
    "iso:country":"IN",
    "ks:ks_name":"Rosana",
    "ks:ks_pop":16,
    "ks:ks_type":"VILLAGE",
    "name:eng_x_preferred":[
        "Rosana"
    ],
    "wof:name":"Rosana",
    "wof:placetype":"locality",
    "wof:population":16
},
  "geometry": {"coordinates":[87.12235099999999,22.90464],"type":"Point"}
}