{
  "type": "Feature",
  "properties": {
    "iso:country":"IN",
    "ks:ks_name":"Rajnagar Colony Ward 4",
    "ks:ks_pop":755,
    "ks:ks_type":"HABITATION",
    "name:eng_x_preferred":[
        "Rajnagar Colony Ward 4"
    ],
    "wof:name":"Rajnagar Colony Ward 4",
    "wof:placetype":"locality",
    "wof:population":755
},
  "geometry": {"coordinates":[92.117918,24.307787],"type":"Point"}
}