{
  "type": "Feature",
  "properties": {
    "iso:country":"IN",
    "ks:ks_name":"Teliya Dhad",
    "ks:ks_pop":706,
    "ks:ks_type":"VILLAGE",
    "name:eng_x_preferred":[
        "Teliya Dhad"
    ],
    "wof:name":"Teliya Dhad",
    "wof:placetype":"locality",
    "wof:population":706
},
  "geometry": {"coordinates":[76.683466,21.512647],"type":"Point"}
}