{
  "type": "Feature",
  "properties": {
    "gn:admin1_code":"38.0",
    "gn:admin2_code":"351.0",
    "gn:asciiname":"Rupia Mal",
    "gn:country_code":"IN",
    "gn:dem":88,
    "gn:feature_class":"P",
    "gn:feature_code":"PPL",
    "gn:name":"Rupia M\u0101l",
    "gn:population":0,
    "gn:timezone":"Asia/Kolkata",
    "iso:country":"IN",
    "ks:ks_name":"Rupiyamal",
    "ks:ks_pop":1106,
    "ks:ks_type":"VILLAGE",
    "ks:ks_uagg_main":0,
    "name:eng_x_preferred":[
        "Rupiyamal"
    ],
    "wof:name":"Rupiyamal",
    "wof:placetype":"locality",
    "wof:population":1106
},
  "geometry": {"coordinates":[87.195504,24.835816],"type":"Point"}
}