{
  "type": "Feature",
  "properties": {
    "iso:country":"IN",
    "ks:ks_name":"Eringalur",
    "ks:ks_pop":225,
    "ks:ks_type":"HABITATION",
    "name:eng_x_preferred":[
        "Eringalur"
    ],
    "wof:name":"Eringalur",
    "wof:placetype":"locality",
    "wof:population":225
},
  "geometry": {"coordinates":[78.46599500000001,12.477851],"type":"Point"}
}