{
  "type": "Feature",
  "properties": {
    "iso:country":"IN",
    "ks:ks_name":"Gopalapuram",
    "ks:ks_pop":110,
    "ks:ks_type":"HABITATION",
    "name:eng_x_preferred":[
        "Gopalapuram"
    ],
    "wof:name":"Gopalapuram",
    "wof:placetype":"locality",
    "wof:population":110
},
  "geometry": {"coordinates":[77.858177,9.340631],"type":"Point"}
}