{
  "type": "Feature",
  "properties": {
    "iso:country":"IN",
    "ks:ks_name":"Dambarudiha",
    "ks:ks_pop":735,
    "ks:ks_type":"VILLAGE",
    "name:eng_x_preferred":[
        "Dambarudiha"
    ],
    "wof:name":"Dambarudiha",
    "wof:placetype":"locality",
    "wof:population":735
},
  "geometry": {"coordinates":[86.677604,21.626385],"type":"Point"}
}