{
  "type": "Feature",
  "properties": {
    "iso:country":"IN",
    "ks:ks_name":"Edayapattiyanpatty",
    "ks:ks_pop":292,
    "ks:ks_type":"HABITATION",
    "name:eng_x_preferred":[
        "Edayapattiyanpatty"
    ],
    "wof:name":"Edayapattiyanpatty",
    "wof:placetype":"locality",
    "wof:population":292
},
  "geometry": {"coordinates":[78.388356,10.599255],"type":"Point"}
}