{
  "type": "Feature",
  "properties": {
    "iso:country":"IN",
    "ks:ks_name":"Muspanj",
    "ks:ks_pop":70,
    "ks:ks_type":"HABITATION",
    "name:eng_x_preferred":[
        "Muspanj"
    ],
    "wof:name":"Muspanj",
    "wof:placetype":"locality",
    "wof:population":70
},
  "geometry": {"coordinates":[83.229151,19.538039],"type":"Point"}
}