{
  "type": "Feature",
  "properties": {
    "iso:country":"IN",
    "ks:ks_name":"Ghesar",
    "ks:ks_pop":800,
    "ks:ks_type":"VILLAGE",
    "name:eng_x_preferred":[
        "Ghesar"
    ],
    "wof:name":"Ghesar",
    "wof:placetype":"locality",
    "wof:population":800
},
  "geometry": {"coordinates":[73.08446000000001,19.152258],"type":"Point"}
}