{
  "type": "Feature",
  "properties": {
    "gn:admin1_code":"36.0",
    "gn:admin2_code":"158.0",
    "gn:asciiname":"Najepur",
    "gn:country_code":"IN",
    "gn:dem":117,
    "gn:feature_class":"P",
    "gn:feature_code":"PPL",
    "gn:name":"N\u0101jepur",
    "gn:population":0,
    "gn:timezone":"Asia/Kolkata",
    "iso:country":"IN",
    "ks:ks_name":"Naje Pur",
    "ks:ks_pop":368,
    "ks:ks_type":"HABITATION",
    "ks:ks_uagg_main":0,
    "name:eng_x_preferred":[
        "Naje Pur"
    ],
    "wof:name":"Naje Pur",
    "wof:placetype":"neighbourhood",
    "wof:population":368
},
  "geometry": {"coordinates":[81.232201,25.911044],"type":"Point"}
}