{
  "type": "Feature",
  "properties": {
    "gn:admin1_code":"36.0",
    "gn:admin2_code":"158.0",
    "gn:asciiname":"Pura Maharajbakhsh",
    "gn:country_code":"IN",
    "gn:dem":119,
    "gn:feature_class":"P",
    "gn:feature_code":"PPL",
    "gn:name":"Pura M\u0101h\u0101rajbakhsh",
    "gn:population":0,
    "gn:timezone":"Asia/Kolkata",
    "iso:country":"IN",
    "wof:name":"Pura Maharajbakhsh",
    "wof:placetype":"neighbourhood"
},
  "geometry": {"coordinates":[81.08402,26.17739],"type":"Point"}
}