{
  "type": "Feature",
  "properties": {
    "iso:country":"IN",
    "ks:ks_name":"Morkheri",
    "ks:ks_pop":311,
    "ks:ks_type":"HABITATION",
    "name:eng_x_preferred":[
        "Morkheri"
    ],
    "wof:name":"Morkheri",
    "wof:placetype":"locality",
    "wof:population":311
},
  "geometry": {"coordinates":[77.13049700000001,24.905499],"type":"Point"}
}