{
  "type": "Feature",
  "properties": {
    "iso:country":"IN",
    "ks:ks_name":"Limbakhedi Falia",
    "ks:ks_pop":807,
    "ks:ks_type":"HABITATION",
    "name:eng_x_preferred":[
        "Limbakhedi Falia"
    ],
    "wof:name":"Limbakhedi Falia",
    "wof:placetype":"locality",
    "wof:population":807
},
  "geometry": {"coordinates":[74.02805600000001,23.194056],"type":"Point"}
}