{
  "type": "Feature",
  "properties": {
    "iso:country":"IN",
    "ks:ks_name":"Padri Kumhari",
    "ks:ks_pop":340,
    "ks:ks_type":"VILLAGE",
    "name:eng_x_preferred":[
        "Padri Kumhari"
    ],
    "wof:name":"Padri Kumhari",
    "wof:placetype":"locality",
    "wof:population":340
},
  "geometry": {"coordinates":[79.776747,23.884266],"type":"Point"}
}