{
  "type": "Feature",
  "properties": {
    "iso:country":"IN",
    "ks:ks_name":"Pure Tiwaripur",
    "ks:ks_pop":441,
    "ks:ks_type":"HABITATION",
    "ks:ks_uagg_main":0,
    "name:eng_x_preferred":[
        "Pure Tiwaripur"
    ],
    "wof:name":"Pure Tiwaripur",
    "wof:placetype":"neighbourhood",
    "wof:population":441
},
  "geometry": {"coordinates":[81.4012,26.519],"type":"Point"}
}