{
  "type": "Feature",
  "properties": {
    "iso:country":"IN",
    "ks:ks_name":"Bilasi",
    "ks:ks_pop":785,
    "ks:ks_type":"VILLAGE",
    "ks:ks_uagg_main":0,
    "name:eng_x_preferred":[
        "Bilasi"
    ],
    "wof:name":"Bilasi",
    "wof:placetype":"locality",
    "wof:population":785
},
  "geometry": {"coordinates":[88.60876399999999,22.686323],"type":"Point"}
}