{
  "type": "Feature",
  "properties": {
    "iso:country":"IN",
    "ks:ks_name":"Naini Urf Choprakot",
    "ks:ks_pop":175,
    "ks:ks_type":"VILLAGE",
    "name:eng_x_preferred":[
        "Naini Urf Choprakot"
    ],
    "wof:name":"Naini Urf Choprakot",
    "wof:placetype":"locality",
    "wof:population":175
},
  "geometry": {"coordinates":[79.39681899999999,30.291091],"type":"Point"}
}