{
  "type": "Feature",
  "properties": {
    "gn:admin1_code":"39",
    "gn:admin2_code":"61.0",
    "gn:asciiname":"Kolindkhal",
    "gn:country_code":"IN",
    "gn:dem":1170,
    "gn:feature_class":"P",
    "gn:feature_code":"PPL",
    "gn:name":"Kolindkh\u0101l",
    "gn:population":0,
    "gn:timezone":"Asia/Kolkata",
    "iso:country":"IN",
    "wof:name":"Kolindkhal",
    "wof:placetype":"locality"
},
  "geometry": {"coordinates":[78.90118000000002,29.82738],"type":"Point"}
}