{
  "type": "Feature",
  "properties": {
    "iso:country":"IN",
    "ks:ks_name":"Komalinenivaripalem",
    "ks:ks_pop":1648,
    "ks:ks_type":"HABITATION",
    "ks:ks_uagg_main":0,
    "name:eng_x_preferred":[
        "Komalinenivaripalem"
    ],
    "wof:name":"Komalinenivaripalem",
    "wof:placetype":"neighbourhood",
    "wof:population":1648
},
  "geometry": {"coordinates":[80.11601,16.162511],"type":"Point"}
}