{
  "type": "Feature",
  "properties": {
    "iso:country":"IN",
    "ks:ks_name":"Savalaperi",
    "ks:ks_pop":1343,
    "ks:ks_type":"HABITATION",
    "name:eng_x_preferred":[
        "Savalaperi"
    ],
    "wof:name":"Savalaperi",
    "wof:placetype":"locality",
    "wof:population":1343
},
  "geometry": {"coordinates":[77.851625,8.811952],"type":"Point"}
}