{
  "type": "Feature",
  "properties": {
    "iso:country":"IN",
    "ks:ks_name":"Chinnamatalanpatti",
    "ks:ks_pop":460,
    "ks:ks_type":"HABITATION",
    "name:eng_x_preferred":[
        "Chinnamatalanpatti"
    ],
    "wof:name":"Chinnamatalanpatti",
    "wof:placetype":"locality",
    "wof:population":460
},
  "geometry": {"coordinates":[78.190907,12.225023],"type":"Point"}
}