{
  "type": "Feature",
  "properties": {
    "iso:country":"IN",
    "ks:ks_name":"Bhalukajuri",
    "ks:ks_pop":123,
    "ks:ks_type":"VILLAGE",
    "ks:ks_uagg_main":0,
    "name:eng_x_preferred":[
        "Bhalukajuri"
    ],
    "wof:name":"Bhalukajuri",
    "wof:placetype":"neighbourhood",
    "wof:population":123
},
  "geometry": {"coordinates":[92.100719,26.272761],"type":"Point"}
}