{
  "type": "Feature",
  "properties": {
    "iso:country":"IN",
    "ks:ks_name":"2 C",
    "ks:ks_pop":488,
    "ks:ks_type":"VILLAGE",
    "name:eng_x_preferred":[
        "2 C"
    ],
    "wof:name":"2 C",
    "wof:placetype":"locality",
    "wof:population":488
},
  "geometry": {"coordinates":[73.950175,30.105844],"type":"Point"}
}