{
  "type": "Feature",
  "properties": {
    "iso:country":"IN",
    "ks:ks_name":"Chak Agaya",
    "ks:ks_pop":0,
    "ks:ks_type":"VILLAGE",
    "name:eng_x_preferred":[
        "Chak Agaya"
    ],
    "wof:name":"Chak Agaya",
    "wof:placetype":"locality",
    "wof:population":0
},
  "geometry": {"coordinates":[87.301638,23.977678],"type":"Point"}
}