{
  "type": "Feature",
  "properties": {
    "iso:country":"IN",
    "ks:ks_alt_nam":"Pudupp\u0101laiyam",
    "ks:ks_name":"Puduppalaiyam",
    "ks:ks_type":"VILLAGE",
    "ks:ks_uagg_main":0,
    "name:eng_x_preferred":[
        "Puduppalaiyam"
    ],
    "name:eng_x_variant":[
        "Pudupp\u0101laiyam"
    ],
    "wof:name":"Puduppalaiyam",
    "wof:placetype":"neighbourhood"
},
  "geometry": {"coordinates":[78.39944300000001,11.647452],"type":"Point"}
}