{
  "type": "Feature",
  "properties": {
    "iso:country":"IN",
    "ks:ks_name":"Kotpada",
    "ks:ks_pop":1100,
    "ks:ks_type":"VILLAGE",
    "name:eng_x_preferred":[
        "Kotpada"
    ],
    "wof:name":"Kotpada",
    "wof:placetype":"locality",
    "wof:population":1100
},
  "geometry": {"coordinates":[87.22499000000001,21.989094],"type":"Point"}
}