{
  "type": "Feature",
  "properties": {
    "iso:country":"IN",
    "ks:ks_name":"Edaiyanavayal",
    "ks:ks_pop":304,
    "ks:ks_type":"HABITATION",
    "name:eng_x_preferred":[
        "Edaiyanavayal"
    ],
    "wof:name":"Edaiyanavayal",
    "wof:placetype":"locality",
    "wof:population":304
},
  "geometry": {"coordinates":[79.213004,10.103427],"type":"Point"}
}