{
  "type": "Feature",
  "properties": {
    "iso:country":"IN",
    "ks:ks_alt_nam":"JADHAV  BANDSARGAR WASTI",
    "ks:ks_name":"Jadhav Bandsargar Wasti",
    "ks:ks_pop":129,
    "ks:ks_type":"HABITATION",
    "name:eng_x_preferred":[
        "Jadhav Bandsargar Wasti"
    ],
    "name:eng_x_variant":[
        "JADHAV  BANDSARGAR WASTI"
    ],
    "wof:name":"Jadhav Bandsargar Wasti",
    "wof:placetype":"locality",
    "wof:population":129
},
  "geometry": {"coordinates":[75.549003,17.258258],"type":"Point"}
}