{
  "type": "Feature",
  "properties": {
    "iso:country":"IN",
    "ks:ks_alt_nam":"dalvipada",
    "ks:ks_name":"Dalvipada",
    "ks:ks_pop":366,
    "ks:ks_type":"HABITATION",
    "name:eng_x_preferred":[
        "Dalvipada"
    ],
    "wof:name":"Dalvipada",
    "wof:placetype":"locality",
    "wof:population":366
},
  "geometry": {"coordinates":[72.956221,19.642315],"type":"Point"}
}