{
  "type": "Feature",
  "properties": {
    "iso:country":"IN",
    "ks:ks_name":"Devache Gothane",
    "ks:ks_pop":1144,
    "ks:ks_type":"VILLAGE",
    "name:eng_x_preferred":[
        "Devache Gothane"
    ],
    "wof:name":"Devache Gothane",
    "wof:placetype":"locality",
    "wof:population":1144
},
  "geometry": {"coordinates":[73.42082000000001,16.622365],"type":"Point"}
}