{
  "type": "Feature",
  "properties": {
    "iso:country":"IN",
    "ks:ks_name":"Chand Pukhuria",
    "ks:ks_pop":82,
    "ks:ks_type":"VILLAGE",
    "name:eng_x_preferred":[
        "Chand Pukhuria"
    ],
    "wof:name":"Chand Pukhuria",
    "wof:placetype":"locality",
    "wof:population":82
},
  "geometry": {"coordinates":[88.783417,25.292771],"type":"Point"}
}