{
  "type": "Feature",
  "properties": {
    "gn:admin1_code":"37",
    "gn:admin2_code":"417.0",
    "gn:asciiname":"Kanchal",
    "gn:country_code":"IN",
    "gn:dem":142,
    "gn:feature_class":"P",
    "gn:feature_code":"PPL",
    "gn:name":"Kanchal",
    "gn:population":0,
    "gn:timezone":"Asia/Kolkata",
    "iso:country":"IN",
    "ks:ks_name":"Kanchal",
    "ks:ks_pop":143,
    "ks:ks_type":"HABITATION",
    "name:eng_x_preferred":[
        "Kanchal"
    ],
    "wof:name":"Kanchal",
    "wof:placetype":"locality",
    "wof:population":143
},
  "geometry": {"coordinates":[80.991034,18.28561],"type":"Point"}
}