{
  "type": "Feature",
  "properties": {
    "iso:country":"IN",
    "ks:ks_name":"Bhujangpurwa",
    "ks:ks_pop":46,
    "ks:ks_type":"HABITATION",
    "ks:ks_uagg_main":0,
    "name:eng_x_preferred":[
        "Bhujangpurwa"
    ],
    "wof:name":"Bhujangpurwa",
    "wof:placetype":"neighbourhood",
    "wof:population":46
},
  "geometry": {"coordinates":[81.53283999999999,27.541642],"type":"Point"}
}