{
  "type": "Feature",
  "properties": {
    "iso:country":"IN",
    "ks:ks_name":"Raikula",
    "ks:ks_pop":1545,
    "ks:ks_type":"VILLAGE",
    "name:eng_x_preferred":[
        "Raikula"
    ],
    "wof:name":"Raikula",
    "wof:placetype":"locality",
    "wof:population":1545
},
  "geometry": {"coordinates":[86.55875399999999,21.241926],"type":"Point"}
}