{
  "type": "Feature",
  "properties": {
    "iso:country":"IN",
    "ks:ks_name":"Heso",
    "ks:ks_pop":535,
    "ks:ks_type":"HABITATION",
    "name:eng_x_preferred":[
        "Heso"
    ],
    "wof:name":"Heso",
    "wof:placetype":"locality",
    "wof:population":535
},
  "geometry": {"coordinates":[85.536941,23.263362],"type":"Point"}
}