{
  "type": "Feature",
  "properties": {
    "iso:country":"IN",
    "ks:ks_name":"Brahamaniguda",
    "ks:ks_pop":52,
    "ks:ks_type":"HABITATION",
    "name:eng_x_preferred":[
        "Brahamaniguda"
    ],
    "wof:name":"Brahamaniguda",
    "wof:placetype":"locality",
    "wof:population":52
},
  "geometry": {"coordinates":[83.335994,19.478264],"type":"Point"}
}