{
  "type": "Feature",
  "properties": {
    "iso:country":"IN",
    "ks:ks_name":"Deasin",
    "ks:ks_pop":1570,
    "ks:ks_type":"VILLAGE",
    "ks:ks_uagg_main":0,
    "name:eng_x_preferred":[
        "Deasin"
    ],
    "wof:name":"Deasin",
    "wof:placetype":"neighbourhood",
    "wof:population":1570
},
  "geometry": {"coordinates":[88.197328,23.556455],"type":"Point"}
}