{
  "type": "Feature",
  "properties": {
    "iso:country":"IN",
    "ks:ks_name":"Sargarhi",
    "ks:ks_pop":602,
    "ks:ks_type":"VILLAGE",
    "name:eng_x_preferred":[
        "Sargarhi"
    ],
    "wof:name":"Sargarhi",
    "wof:placetype":"locality",
    "wof:population":602
},
  "geometry": {"coordinates":[83.45912199999999,23.486497],"type":"Point"}
}