{
  "type": "Feature",
  "properties": {
    "iso:country":"IN",
    "ks:ks_name":"Shahpur T. Gauspur",
    "ks:ks_pop":34,
    "ks:ks_type":"VILLAGE",
    "name:eng_x_preferred":[
        "Shahpur T. Gauspur"
    ],
    "wof:name":"Shahpur T. Gauspur",
    "wof:placetype":"locality",
    "wof:population":34
},
  "geometry": {"coordinates":[83.704891,25.617577],"type":"Point"}
}