{
  "type": "Feature",
  "properties": {
    "gn:admin1_code":"19.0",
    "gn:admin2_code":"584.0",
    "gn:asciiname":"Hunasanhalli",
    "gn:country_code":"IN",
    "gn:dem":626,
    "gn:feature_class":"P",
    "gn:feature_code":"PPL",
    "gn:name":"Hunasanhalli",
    "gn:population":0,
    "gn:timezone":"Asia/Kolkata",
    "iso:country":"IN",
    "ks:ks_name":"Hunasanahalli",
    "ks:ks_pop":851,
    "ks:ks_type":"VILLAGE",
    "ks:ks_uagg_main":0,
    "name:eng_x_preferred":[
        "Hunasanahalli"
    ],
    "wof:name":"Hunasanahalli",
    "wof:placetype":"neighbourhood",
    "wof:population":851
},
  "geometry": {"coordinates":[77.213713,12.546088],"type":"Point"}
}