{
  "type": "Feature",
  "properties": {
    "gn:admin1_code":"36",
    "gn:admin2_code":"199.0",
    "gn:asciiname":"Chhato",
    "gn:country_code":"IN",
    "gn:dem":130,
    "gn:feature_class":"P",
    "gn:feature_code":"PPL",
    "gn:name":"Chh\u0101to",
    "gn:population":0,
    "gn:timezone":"Asia/Kolkata",
    "iso:country":"IN",
    "ks:ks_alt_nam":"Chh\u0101to",
    "ks:ks_name":"Chhato",
    "ks:ks_pop":294,
    "ks:ks_type":"VILLAGE",
    "name:eng_x_preferred":[
        "Chhato"
    ],
    "name:eng_x_variant":[
        "Chh\u0101to"
    ],
    "wof:name":"Chhato",
    "wof:placetype":"locality",
    "wof:population":294
},
  "geometry": {"coordinates":[83.035043,24.964353],"type":"Point"}
}