{
  "type": "Feature",
  "properties": {
    "gn:admin1_code":"10.0",
    "gn:admin2_code":"80.0",
    "gn:asciiname":"Bheri",
    "gn:country_code":"IN",
    "gn:dem":225,
    "gn:feature_class":"P",
    "gn:feature_code":"PPL",
    "gn:name":"Bheri",
    "gn:population":0,
    "gn:timezone":"Asia/Kolkata",
    "iso:country":"IN",
    "name:slk_x_preferred":[
        "Bheri"
    ],
    "name:und_x_variant":[
        "Akbarpur"
    ],
    "wof:name":"Bheri",
    "wof:placetype":"locality"
},
  "geometry": {"coordinates":[75.87057,29.49161],"type":"Point"}
}