{
  "type": "Feature",
  "properties": {
    "gn:admin1_code":"35.0",
    "gn:admin2_code":"420.0",
    "gn:asciiname":"Pali",
    "gn:country_code":"IN",
    "gn:dem":178,
    "gn:feature_class":"P",
    "gn:feature_code":"PPL",
    "gn:name":"P\u0101li",
    "gn:population":0,
    "gn:timezone":"Asia/Kolkata",
    "iso:country":"IN",
    "name:eng_x_preferred":[
        "P\u0101li"
    ],
    "wof:name":"Pali",
    "wof:placetype":"locality"
},
  "geometry": {"coordinates":[78.47969999999999,26.28473],"type":"Point"}
}