{
  "type": "Feature",
  "properties": {
    "iso:country":"IN",
    "ks:ks_name":"Billakamba",
    "ks:ks_pop":72,
    "ks:ks_type":"VILLAGE",
    "name:eng_x_preferred":[
        "Billakamba"
    ],
    "wof:name":"Billakamba",
    "wof:placetype":"locality",
    "wof:population":72
},
  "geometry": {"coordinates":[82.92818,18.096731],"type":"Point"}
}