{
  "type": "Feature",
  "properties": {
    "iso:country":"IN",
    "ks:ks_name":"Maithan Gaon",
    "ks:ks_pop":11,
    "ks:ks_type":"VILLAGE",
    "name:eng_x_preferred":[
        "Maithan Gaon"
    ],
    "wof:name":"Maithan Gaon",
    "wof:placetype":"locality",
    "wof:population":11
},
  "geometry": {"coordinates":[78.76114,30.208563],"type":"Point"}
}