{
  "type": "Feature",
  "properties": {
    "gn:admin1_code":"25.0",
    "gn:admin2_code":"605.0",
    "gn:asciiname":"Subbanaiyakkanpalaiyam",
    "gn:country_code":"IN",
    "gn:dem":311,
    "gn:feature_class":"P",
    "gn:feature_code":"PPL",
    "gn:name":"Subbanaiyakkanp\u0101laiyam",
    "gn:population":0,
    "gn:timezone":"Asia/Kolkata",
    "iso:country":"IN",
    "wof:name":"Subbanaiyakkanpalaiyam",
    "wof:placetype":"neighbourhood"
},
  "geometry": {"coordinates":[78.88616,12.80248],"type":"Point"}
}