{
  "type": "Feature",
  "properties": {
    "iso:country":"IN",
    "ks:ks_name":"Bela",
    "ks:ks_pop":364,
    "ks:ks_type":"VILLAGE",
    "name:eng_x_preferred":[
        "Bela"
    ],
    "wof:name":"Bela",
    "wof:placetype":"locality",
    "wof:population":364
},
  "geometry": {"coordinates":[85.622759,24.751059],"type":"Point"}
}