{
  "type": "Feature",
  "properties": {
    "gn:admin1_code":"36",
    "gn:admin2_code":"144.0",
    "gn:asciiname":"Kunda",
    "gn:country_code":"IN",
    "gn:dem":177,
    "gn:feature_class":"P",
    "gn:feature_code":"PPL",
    "gn:name":"Kunda",
    "gn:population":0,
    "gn:timezone":"Asia/Kolkata",
    "iso:country":"IN",
    "name:ceb_x_preferred":[
        "Kunda"
    ],
    "name:ces_x_preferred":[
        "Kunda"
    ],
    "name:deu_x_preferred":[
        "Kunda"
    ],
    "name:fra_x_preferred":[
        "Kunda"
    ],
    "name:new_x_preferred":[
        "\u0915\u0941\u0928\u094d\u0926\u093e"
    ],
    "name:nld_x_preferred":[
        "Kunda"
    ],
    "name:pol_x_preferred":[
        "Kunda"
    ],
    "name:ron_x_preferred":[
        "Kunda"
    ],
    "name:sco_x_preferred":[
        "Kunda"
    ],
    "name:slk_x_preferred":[
        "Kunda"
    ],
    "name:spa_x_preferred":[
        "Kunda"
    ],
    "name:swe_x_preferred":[
        "Kunda"
    ],
    "name:vie_x_preferred":[
        "Kunda"
    ],
    "wof:name":"Kunda",
    "wof:placetype":"locality"
},
  "geometry": {"coordinates":[78.2748,27.53698],"type":"Point"}
}