{
  "type": "Feature",
  "properties": {
    "iso:country":"IN",
    "ks:ks_name":"Awadhi Harizan Basti Tola",
    "ks:ks_pop":208,
    "ks:ks_type":"HABITATION",
    "ks:ks_uagg_main":0,
    "name:eng_x_preferred":[
        "Awadhi Harizan Basti Tola"
    ],
    "wof:name":"Awadhi Harizan Basti Tola",
    "wof:placetype":"neighbourhood",
    "wof:population":208
},
  "geometry": {"coordinates":[83.514032,26.659482],"type":"Point"}
}