{
  "type": "Feature",
  "properties": {
    "gn:admin1_code":"19.0",
    "gn:admin2_code":"570.0",
    "gn:asciiname":"Alagatta",
    "gn:country_code":"IN",
    "gn:dem":729,
    "gn:feature_class":"P",
    "gn:feature_code":"PPL",
    "gn:name":"\u0100lagatta",
    "gn:population":0,
    "gn:timezone":"Asia/Kolkata",
    "iso:country":"IN",
    "ks:ks_alt_nam":"\u0100lagatta",
    "ks:ks_name":"Alagatta",
    "ks:ks_pop":545,
    "ks:ks_type":"VILLAGE",
    "name:eng_x_preferred":[
        "Alagatta"
    ],
    "name:eng_x_variant":[
        "\u0100lagatta"
    ],
    "wof:name":"Alagatta",
    "wof:placetype":"locality",
    "wof:population":545
},
  "geometry": {"coordinates":[76.14088,13.523456],"type":"Point"}
}