{
  "type": "Feature",
  "properties": {
    "gn:admin1_code":"23",
    "gn:admin2_code":"38.0",
    "gn:asciiname":"Gaggar",
    "gn:country_code":"IN",
    "gn:dem":348,
    "gn:feature_class":"P",
    "gn:feature_code":"PPL",
    "gn:name":"Gaggar",
    "gn:population":0,
    "gn:timezone":"Asia/Kolkata",
    "iso:country":"IN",
    "ks:ks_name":"Gagar",
    "ks:ks_pop":473,
    "ks:ks_type":"VILLAGE",
    "ks:ks_uagg_main":0,
    "name:eng_x_preferred":[
        "Gagar"
    ],
    "wof:name":"Gagar",
    "wof:placetype":"neighbourhood",
    "wof:population":473
},
  "geometry": {"coordinates":[75.744809,31.951637],"type":"Point"}
}