{
  "type": "Feature",
  "properties": {
    "gn:admin1_code":"24.0",
    "gn:admin2_code":"111.0",
    "gn:asciiname":"Bhakra ki Balodl",
    "gn:country_code":"IN",
    "gn:dem":338,
    "gn:feature_class":"P",
    "gn:feature_code":"PPL",
    "gn:name":"Bh\u0101kra ki Balodl",
    "gn:population":0,
    "gn:timezone":"Asia/Kolkata",
    "iso:country":"IN",
    "wof:name":"Bhakra ki Balodl",
    "wof:placetype":"neighbourhood"
},
  "geometry": {"coordinates":[75.08251,28.0021],"type":"Point"}
}