{
  "type": "Feature",
  "properties": {
    "gn:admin1_code":"22.0",
    "gn:admin2_code":"637",
    "gn:asciiname":"Mel Kasakkudi",
    "gn:country_code":"IN",
    "gn:dem":8,
    "gn:feature_class":"P",
    "gn:feature_code":"PPL",
    "gn:name":"Mel K\u0101s\u0101kkudi",
    "gn:population":0,
    "gn:timezone":"Asia/Kolkata",
    "iso:country":"IN",
    "name:und_x_variant":[
        "Mel K\u0101s\u0101kkudi",
        "K\u012bl K\u0101s\u0101kkudi"
    ],
    "wof:name":"Mel Kasakkudi",
    "wof:placetype":"locality"
},
  "geometry": {"coordinates":[79.79331999999999,10.9545],"type":"Point"}
}