{
  "type": "Feature",
  "properties": {
    "iso:country":"IN",
    "ks:ks_name":"N. Tej",
    "ks:ks_pop":71,
    "ks:ks_type":"HABITATION",
    "name:eng_x_preferred":[
        "N. Tej"
    ],
    "wof:name":"N. Tej",
    "wof:placetype":"locality",
    "wof:population":71
},
  "geometry": {"coordinates":[79.1096,26.999333],"type":"Point"}
}