{
  "type": "Feature",
  "properties": {
    "iso:country":"IN",
    "ks:ks_alt_nam":"INAMDAR MALA",
    "ks:ks_name":"Inamdar Mala",
    "ks:ks_pop":300,
    "ks:ks_type":"HABITATION",
    "name:eng_x_preferred":[
        "Inamdar Mala"
    ],
    "wof:name":"Inamdar Mala",
    "wof:placetype":"locality",
    "wof:population":300
},
  "geometry": {"coordinates":[74.278262,16.977562],"type":"Point"}
}