{
  "type": "Feature",
  "properties": {
    "iso:country":"IN",
    "ks:ks_name":"Harmat Nagar Parabhaniyo Ki Dhlani",
    "ks:ks_pop":152,
    "ks:ks_type":"HABITATION",
    "name:eng_x_preferred":[
        "Harmat Nagar Parabhaniyo Ki Dhlani"
    ],
    "wof:name":"Harmat Nagar Parabhaniyo Ki Dhlani",
    "wof:placetype":"locality",
    "wof:population":152
},
  "geometry": {"coordinates":[72.2099,26.137919],"type":"Point"}
}