{
  "type": "Feature",
  "properties": {
    "iso:country":"IN",
    "ks:ks_name":"Marbeda",
    "ks:ks_pop":112,
    "ks:ks_type":"VILLAGE",
    "name:eng_x_preferred":[
        "Marbeda"
    ],
    "wof:name":"Marbeda",
    "wof:placetype":"locality",
    "wof:population":112
},
  "geometry": {"coordinates":[80.63969,19.79405],"type":"Point"}
}