{
  "type": "Feature",
  "properties": {
    "iso:country":"IN",
    "ks:ks_name":"Durgapur",
    "ks:ks_pop":281,
    "ks:ks_type":"VILLAGE",
    "name:ben_x_preferred":[
        "\u09a6\u09c1\u09b0\u09cd\u0997\u09be\u09aa\u09c1\u09b0"
    ],
    "name:eng_x_preferred":[
        "Durgapur"
    ],
    "name:hin_x_preferred":[
        "\u0926\u0941\u0930\u094d\u0917\u093e\u092a\u0941\u0930"
    ],
    "wof:name":"Durgapur",
    "wof:placetype":"locality",
    "wof:population":281
},
  "geometry": {"coordinates":[86.968107,21.924143],"type":"Point"}
}