{
  "type": "Feature",
  "properties": {
    "iso:country":"IN",
    "ks:ks_name":"Durgapur",
    "ks:ks_pop":281,
    "ks:ks_type":"VILLAGE",
    "name:eng_x_preferred":[
        "Durgapur"
    ],
    "wof:name":"Durgapur",
    "wof:placetype":"locality",
    "wof:population":281
},
  "geometry": {"coordinates":[86.968107,21.924143],"type":"Point"}
}