{
  "type": "Feature",
  "properties": {
    "iso:country":"IN",
    "ks:ks_name":"Burusingi",
    "ks:ks_pop":40,
    "ks:ks_type":"VILLAGE",
    "name:eng_x_preferred":[
        "Burusingi"
    ],
    "wof:name":"Burusingi",
    "wof:placetype":"locality",
    "wof:population":40
},
  "geometry": {"coordinates":[84.41905,18.918928],"type":"Point"}
}