{
  "type": "Feature",
  "properties": {
    "iso:country":"IN",
    "ks:ks_name":"South Tol",
    "ks:ks_pop":1550,
    "ks:ks_type":"HABITATION",
    "name:eng_x_preferred":[
        "South Tol"
    ],
    "wof:name":"South Tol",
    "wof:placetype":"locality",
    "wof:population":1550
},
  "geometry": {"coordinates":[86.315196,26.230979],"type":"Point"}
}