{
  "type": "Feature",
  "properties": {
    "gn:admin1_code":"19.0",
    "gn:admin2_code":"576.0",
    "gn:asciiname":"Dandhalli",
    "gn:country_code":"IN",
    "gn:dem":936,
    "gn:feature_class":"P",
    "gn:feature_code":"PPL",
    "gn:name":"Dandhalli",
    "gn:population":0,
    "gn:timezone":"Asia/Kolkata",
    "iso:country":"IN",
    "wof:name":"Dandhalli",
    "wof:placetype":"locality"
},
  "geometry": {"coordinates":[75.86610999999998,12.74527],"type":"Point"}
}