{
  "type": "Feature",
  "properties": {
    "iso:country":"IN",
    "ks:ks_name":"Kiswan Gaon",
    "ks:ks_pop":4,
    "ks:ks_type":"VILLAGE",
    "name:eng_x_preferred":[
        "Kiswan Gaon"
    ],
    "wof:name":"Kiswan Gaon",
    "wof:placetype":"locality",
    "wof:population":4
},
  "geometry": {"coordinates":[78.750483,30.189683],"type":"Point"}
}