{
  "type": "Feature",
  "properties": {
    "gn:admin1_code":"16.0",
    "gn:admin2_code":"520",
    "gn:asciiname":"Khandale",
    "gn:country_code":"IN",
    "gn:dem":26,
    "gn:feature_class":"P",
    "gn:feature_code":"PPL",
    "gn:name":"Khand\u0101le",
    "gn:population":0,
    "gn:timezone":"Asia/Kolkata",
    "iso:country":"IN",
    "ks:ks_alt_nam":"Khand\u0101le",
    "ks:ks_name":"Khandale",
    "ks:ks_type":"VILLAGE",
    "ks:ks_uagg_main":0,
    "name:eng_x_preferred":[
        "Khandale"
    ],
    "name:eng_x_variant":[
        "Khand\u0101le"
    ],
    "wof:name":"Khandale",
    "wof:placetype":"neighbourhood"
},
  "geometry": {"coordinates":[72.911839,18.673472],"type":"Point"}
}