{
  "type": "Feature",
  "properties": {
    "gn:admin1_code":"11.0",
    "gn:admin2_code":"26.0",
    "gn:asciiname":"Diaugi",
    "gn:country_code":"IN",
    "gn:dem":2335,
    "gn:feature_class":"P",
    "gn:feature_code":"PPL",
    "gn:name":"Di\u0101\u016bgi",
    "gn:population":0,
    "gn:timezone":"Asia/Kolkata",
    "iso:country":"IN",
    "wof:name":"Diaugi",
    "wof:placetype":"locality"
},
  "geometry": {"coordinates":[77.53185999999999,31.5435],"type":"Point"}
}