{
  "type": "Feature",
  "properties": {
    "gn:admin1_code":"34.0",
    "gn:admin2_code":"220.0",
    "gn:asciiname":"Nasir Chak",
    "gn:country_code":"IN",
    "gn:dem":54,
    "gn:feature_class":"P",
    "gn:feature_code":"PPL",
    "gn:name":"N\u0101sir Chak",
    "gn:population":0,
    "gn:timezone":"Asia/Kolkata",
    "iso:country":"IN",
    "ks:ks_alt_nam":"N\u0101sir Chak",
    "ks:ks_name":"Nasir Chak",
    "ks:ks_pop":3224,
    "ks:ks_type":"VILLAGE",
    "name:eng_x_preferred":[
        "Nasir Chak"
    ],
    "name:eng_x_variant":[
        "N\u0101sir Chak"
    ],
    "wof:name":"Nasir Chak",
    "wof:placetype":"locality",
    "wof:population":3224
},
  "geometry": {"coordinates":[85.520903,25.884797],"type":"Point"}
}