{
  "type": "Feature",
  "properties": {
    "gn:admin1_code":"36.0",
    "gn:admin2_code":"185.0",
    "gn:asciiname":"Daulat Pura",
    "gn:country_code":"IN",
    "gn:dem":95,
    "gn:feature_class":"P",
    "gn:feature_code":"PPL",
    "gn:name":"Daulat Pura",
    "gn:population":0,
    "gn:timezone":"Asia/Kolkata",
    "iso:country":"IN",
    "name:fas_x_preferred":[
        "\u062f\u0648\u0644\u062a \u067e\u0648\u0631\u0647"
    ],
    "name:urd_x_preferred":[
        "\u062f\u0648\u0644\u062a \u067e\u0648\u0631\u06c1"
    ],
    "wof:name":"Daulat Pura",
    "wof:placetype":"locality"
},
  "geometry": {"coordinates":[82.58513000000001,27.04765],"type":"Point"}
}