{
  "type": "Feature",
  "properties": {
    "iso:country":"IN",
    "ks:ks_name":"9 PSD-B",
    "ks:ks_pop":142,
    "ks:ks_type":"VILLAGE",
    "name:eng_x_preferred":[
        "9 PSD-B"
    ],
    "wof:name":"9 PSD-B",
    "wof:placetype":"locality",
    "wof:population":142
},
  "geometry": {"coordinates":[72.919203,28.838784],"type":"Point"}
}