{
  "type": "Feature",
  "properties": {
    "iso:country":"IN",
    "ks:ks_name":"Maddilapadu",
    "ks:ks_pop":11,
    "ks:ks_type":"HABITATION",
    "name:eng_x_preferred":[
        "Maddilapadu"
    ],
    "wof:name":"Maddilapadu",
    "wof:placetype":"locality",
    "wof:population":11
},
  "geometry": {"coordinates":[83.147486,18.369686],"type":"Point"}
}