{
  "type": "Feature",
  "properties": {
    "gn:admin1_code":"36.0",
    "gn:admin2_code":"190.0",
    "gn:asciiname":"Deoria Misir",
    "gn:country_code":"IN",
    "gn:dem":76,
    "gn:feature_class":"P",
    "gn:feature_code":"PPL",
    "gn:name":"Deori\u0101 Misir",
    "gn:population":0,
    "gn:timezone":"Asia/Kolkata",
    "iso:country":"IN",
    "wof:name":"Deoria Misir",
    "wof:placetype":"neighbourhood"
},
  "geometry": {"coordinates":[83.72014,26.38416],"type":"Point"}
}