{
  "type": "Feature",
  "properties": {
    "gn:admin1_code":"19",
    "gn:admin2_code":"580.0",
    "gn:asciiname":"Ghanapur",
    "gn:country_code":"IN",
    "gn:dem":429,
    "gn:feature_class":"P",
    "gn:feature_code":"PPL",
    "gn:name":"Ghanapur",
    "gn:population":0,
    "gn:timezone":"Asia/Kolkata",
    "iso:country":"IN",
    "wof:name":"Ghanapur",
    "wof:placetype":"locality"
},
  "geometry": {"coordinates":[77.3122,16.75455],"type":"Point"}
}