{
  "type": "Feature",
  "properties": {
    "iso:country":"IN",
    "ks:ks_alt_nam":"suvarnawadi",
    "ks:ks_name":"Suvarnawadi",
    "ks:ks_pop":274,
    "ks:ks_type":"HABITATION",
    "name:eng_x_preferred":[
        "Suvarnawadi"
    ],
    "wof:name":"Suvarnawadi",
    "wof:placetype":"locality",
    "wof:population":274
},
  "geometry": {"coordinates":[73.369578,16.5895],"type":"Point"}
}