{
  "type": "Feature",
  "properties": {
    "iso:country":"IN",
    "ks:ks_name":"Ramnagar",
    "ks:ks_pop":374,
    "ks:ks_type":"VILLAGE",
    "name:eng_x_preferred":[
        "Ramnagar"
    ],
    "wof:name":"Ramnagar",
    "wof:placetype":"locality",
    "wof:population":374
},
  "geometry": {"coordinates":[75.33727399999999,24.910938],"type":"Point"}
}