{
  "type": "Feature",
  "properties": {
    "gn:admin1_code":"36",
    "gn:admin2_code":"188.0",
    "gn:asciiname":"Naurdeor",
    "gn:country_code":"IN",
    "gn:dem":84,
    "gn:feature_class":"P",
    "gn:feature_code":"PPL",
    "gn:name":"Naurdeor",
    "gn:population":0,
    "gn:timezone":"Asia/Kolkata",
    "iso:country":"IN",
    "ks:ks_name":"Naurdeor",
    "ks:ks_pop":538,
    "ks:ks_type":"VILLAGE",
    "ks:ks_uagg_main":0,
    "name:eng_x_preferred":[
        "Naurdeor"
    ],
    "wof:name":"Naurdeor",
    "wof:placetype":"neighbourhood",
    "wof:population":538
},
  "geometry": {"coordinates":[83.38545499999999,26.606044],"type":"Point"}
}