{
  "type": "Feature",
  "properties": {
    "gn:admin1_code":"36",
    "gn:admin2_code":"154.0",
    "gn:asciiname":"Bishnupur",
    "gn:country_code":"IN",
    "gn:dem":147,
    "gn:feature_class":"P",
    "gn:feature_code":"PPL",
    "gn:name":"Bishn\u016bpur",
    "gn:population":0,
    "gn:timezone":"Asia/Kolkata",
    "iso:country":"IN",
    "name:ben_x_preferred":[
        "\u09ac\u09bf\u09b7\u09cd\u09a3\u09c1\u09aa\u09c1\u09b0"
    ],
    "name:bpy_x_preferred":[
        "\u09ac\u09bf\u09b7\u09cd\u09a3\u09c1\u09aa\u09c1\u09b0"
    ],
    "name:ceb_x_preferred":[
        "Bishnupur"
    ],
    "name:deu_x_preferred":[
        "Bishnupur"
    ],
    "name:ita_x_preferred":[
        "Bishnupur"
    ],
    "name:new_x_preferred":[
        "\u0935\u093f\u0937\u094d\u0923\u0941\u092a\u0941\u0930"
    ],
    "name:nld_x_preferred":[
        "Bishnupur"
    ],
    "name:rus_x_preferred":[
        "\u0412\u0438\u0448\u043d\u0443\u043f\u0443\u0440"
    ],
    "name:spa_x_preferred":[
        "Bishnupur"
    ],
    "name:swe_x_preferred":[
        "Bishnupur"
    ],
    "name:zho_x_preferred":[
        "\u6bd4\u65af\u8d6b\u52aa\u666e\u5c14"
    ],
    "wof:name":"Bishnupur",
    "wof:placetype":"locality"
},
  "geometry": {"coordinates":[80.80422,27.7852],"type":"Point"}
}