{
  "type": "Feature",
  "properties": {
    "gn:admin1_code":"36",
    "gn:admin2_code":"154.0",
    "gn:asciiname":"Bishnupur",
    "gn:country_code":"IN",
    "gn:dem":147,
    "gn:feature_class":"P",
    "gn:feature_code":"PPL",
    "gn:name":"Bishn\u016bpur",
    "gn:population":0,
    "gn:timezone":"Asia/Kolkata",
    "iso:country":"IN",
    "name:ara_x_preferred":[
        "\u0628\u064a\u0634\u0646\u0628\u0648\u0631"
    ],
    "name:ben_bn_x_preferred":[
        "\u09ac\u09bf\u09b7\u09cd\u09a3\u09c1\u09aa\u09c1\u09b0"
    ],
    "name:ben_in_x_preferred":[
        "\u09ac\u09bf\u09b7\u09cd\u09a3\u09c1\u09aa\u09c1\u09b0"
    ],
    "name:ben_x_preferred":[
        "\u09ac\u09bf\u09b7\u09cd\u09a3\u09c1\u09aa\u09c1\u09b0"
    ],
    "name:bpy_x_preferred":[
        "\u09ac\u09bf\u09b7\u09cd\u09a3\u09c1\u09aa\u09c1\u09b0"
    ],
    "name:ceb_x_preferred":[
        "Bishnupur"
    ],
    "name:deu_x_preferred":[
        "Bishnupur"
    ],
    "name:guj_x_preferred":[
        "\u0ab5\u0abf\u0ab7\u0acd\u0aa3\u0ac1\u0aaa\u0ac1\u0ab0"
    ],
    "name:hin_x_preferred":[
        "\u092c\u093f\u0937\u094d\u0923\u0941\u092a\u0941\u0930"
    ],
    "name:ita_x_preferred":[
        "Bishnupur"
    ],
    "name:kan_x_preferred":[
        "\u0cac\u0cbf\u0cb7\u0ccd\u0ca3\u0cc1\u0caa\u0cc1\u0cb0\u0ccd"
    ],
    "name:mal_x_preferred":[
        "\u0d2c\u0d3f\u0d37\u0d4d\u0d23\u0d41\u0d2a\u0d42\u0d7c"
    ],
    "name:mar_x_preferred":[
        "\u092c\u093f\u0937\u094d\u0923\u0941\u092a\u0942\u0930"
    ],
    "name:new_x_preferred":[
        "\u0935\u093f\u0937\u094d\u0923\u0941\u092a\u0941\u0930"
    ],
    "name:nld_x_preferred":[
        "Bishnupur"
    ],
    "name:pan_x_preferred":[
        "\u0a2c\u0a3f\u0a36\u0a28\u0a42\u0a2a\u0a41\u0a30"
    ],
    "name:rus_x_preferred":[
        "\u0412\u0438\u0448\u043d\u0443\u043f\u0443\u0440"
    ],
    "name:spa_x_preferred":[
        "Bishnupur"
    ],
    "name:swe_x_preferred":[
        "Bishnupur"
    ],
    "name:tam_x_preferred":[
        "\u0baa\u0bbf\u0bb7\u0bcd\u0ba9\u0bc1\u0baa\u0bc2\u0bb0\u0bcd"
    ],
    "name:tel_x_preferred":[
        "\u0c2c\u0c3f\u0c37\u0c4d\u0c23\u0c41\u0c2a\u0c42\u0c30\u0c4d"
    ],
    "name:urd_x_preferred":[
        "\u0628\u0634\u0646 \u067e\u0648\u0631"
    ],
    "name:zho_x_preferred":[
        "\u6bd4\u65af\u8d6b\u52aa\u666e\u5c14"
    ],
    "wof:name":"Bishnupur",
    "wof:placetype":"locality"
},
  "geometry": {"coordinates":[80.80422,27.7852],"type":"Point"}
}