{
  "type": "Feature",
  "properties": {
    "iso:country":"IN",
    "ks:ks_alt_nam":"B\u0101lenahalli",
    "ks:ks_name":"Balenahalli",
    "ks:ks_type":"VILLAGE",
    "name:eng_x_preferred":[
        "Balenahalli"
    ],
    "name:eng_x_variant":[
        "B\u0101lenahalli"
    ],
    "wof:name":"Balenahalli",
    "wof:placetype":"locality"
},
  "geometry": {"coordinates":[75.91745299999999,13.047443],"type":"Point"}
}