{
  "type": "Feature",
  "properties": {
    "iso:country":"IN",
    "ks:ks_name":"Dumerkhol",
    "ks:ks_pop":490,
    "ks:ks_type":"VILLAGE",
    "name:eng_x_preferred":[
        "Dumerkhol"
    ],
    "wof:name":"Dumerkhol",
    "wof:placetype":"locality",
    "wof:population":490
},
  "geometry": {"coordinates":[83.627431,20.880587],"type":"Point"}
}