{
  "type": "Feature",
  "properties": {
    "iso:country":"IN",
    "ks:ks_name":"Ahiran",
    "ks:ks_pop":1309,
    "ks:ks_type":"HABITATION",
    "name:eng_x_preferred":[
        "Ahiran"
    ],
    "wof:name":"Ahiran",
    "wof:placetype":"locality",
    "wof:population":1309
},
  "geometry": {"coordinates":[82.08229,25.45049],"type":"Point"}
}