{
  "type": "Feature",
  "properties": {
    "iso:country":"IN",
    "ks:ks_name":"Pathalghatta",
    "ks:ks_pop":266,
    "ks:ks_type":"HABITATION",
    "name:eng_x_preferred":[
        "Pathalghatta"
    ],
    "wof:name":"Pathalghatta",
    "wof:placetype":"locality",
    "wof:population":266
},
  "geometry": {"coordinates":[86.44417300000001,24.933066],"type":"Point"}
}