{
  "type": "Feature",
  "properties": {
    "iso:country":"IN",
    "ks:ks_name":"Dokrguda",
    "ks:ks_pop":100,
    "ks:ks_type":"HABITATION",
    "name:eng_x_preferred":[
        "Dokrguda"
    ],
    "wof:name":"Dokrguda",
    "wof:placetype":"locality",
    "wof:population":100
},
  "geometry": {"coordinates":[83.33242,19.654974],"type":"Point"}
}