{
  "type": "Feature",
  "properties": {
    "gn:admin1_code":"16",
    "gn:admin2_code":"506.0",
    "gn:asciiname":"Kurora",
    "gn:country_code":"IN",
    "gn:dem":256,
    "gn:feature_class":"P",
    "gn:feature_code":"PPL",
    "gn:name":"Kurora",
    "gn:population":0,
    "gn:timezone":"Asia/Kolkata",
    "iso:country":"IN",
    "wof:name":"Kurora",
    "wof:placetype":"locality"
},
  "geometry": {"coordinates":[79.75487,21.27071],"type":"Point"}
}