{
  "type": "Feature",
  "properties": {
    "iso:country":"IN",
    "ks:ks_name":"Janathamane",
    "ks:ks_pop":82,
    "ks:ks_type":"HABITATION",
    "name:eng_x_preferred":[
        "Janathamane"
    ],
    "wof:name":"Janathamane",
    "wof:placetype":"locality",
    "wof:population":82
},
  "geometry": {"coordinates":[74.77668,14.690679],"type":"Point"}
}