{
  "type": "Feature",
  "properties": {
    "iso:country":"IN",
    "ks:ks_name":"Haripur",
    "ks:ks_pop":136,
    "ks:ks_type":"VILLAGE",
    "name:eng_x_preferred":[
        "Haripur"
    ],
    "wof:name":"Haripur",
    "wof:placetype":"locality",
    "wof:population":136
},
  "geometry": {"coordinates":[85.14589700000001,19.746921],"type":"Point"}
}