{
  "type": "Feature",
  "properties": {
    "iso:country":"IN",
    "ks:ks_name":"Pariorada",
    "ks:ks_pop":2015,
    "ks:ks_type":"VILLAGE",
    "name:eng_x_preferred":[
        "Pariorada"
    ],
    "wof:name":"Pariorada",
    "wof:placetype":"locality",
    "wof:population":2015
},
  "geometry": {"coordinates":[85.359711,19.907251],"type":"Point"}
}