{
  "type": "Feature",
  "properties": {
    "iso:country":"IN",
    "ks:ks_name":"Jheepatola",
    "ks:ks_pop":192,
    "ks:ks_type":"HABITATION",
    "name:eng_x_preferred":[
        "Jheepatola"
    ],
    "wof:name":"Jheepatola",
    "wof:placetype":"locality",
    "wof:population":192
},
  "geometry": {"coordinates":[81.727116,20.485496],"type":"Point"}
}