{
  "type": "Feature",
  "properties": {
    "gn:admin1_code":"38.0",
    "gn:admin2_code":"348.0",
    "gn:asciiname":"Dhab",
    "gn:country_code":"IN",
    "gn:dem":400,
    "gn:feature_class":"P",
    "gn:feature_code":"PPL",
    "gn:name":"Dh\u0101b",
    "gn:population":0,
    "gn:timezone":"Asia/Kolkata",
    "iso:country":"IN",
    "ks:ks_alt_nam":"Dh\u0101b",
    "ks:ks_name":"Dhab",
    "ks:ks_pop":1237,
    "ks:ks_type":"VILLAGE",
    "ks:ks_uagg_main":0,
    "name:eng_x_preferred":[
        "Dhab"
    ],
    "name:eng_x_variant":[
        "Dh\u0101b"
    ],
    "wof:name":"Dhab",
    "wof:placetype":"neighbourhood",
    "wof:population":1237
},
  "geometry": {"coordinates":[85.431461,24.383779],"type":"Point"}
}