{
  "type": "Feature",
  "properties": {
    "iso:country":"IN",
    "ks:ks_name":"Khemakachari",
    "ks:ks_pop":1338,
    "ks:ks_type":"VILLAGE",
    "ks:ks_uagg_main":0,
    "name:eng_x_preferred":[
        "Khemakachari"
    ],
    "wof:name":"Khemakachari",
    "wof:placetype":"neighbourhood",
    "wof:population":1338
},
  "geometry": {"coordinates":[94.13048000000001,26.461798],"type":"Point"}
}