{
  "type": "Feature",
  "properties": {
    "iso:country":"IN",
    "ks:ks_name":"Bara Bhaudi",
    "ks:ks_pop":107,
    "ks:ks_type":"VILLAGE",
    "ks:ks_uagg_main":0,
    "name:eng_x_preferred":[
        "Bara Bhaudi"
    ],
    "wof:name":"Bara Bhaudi",
    "wof:placetype":"neighbourhood",
    "wof:population":107
},
  "geometry": {"coordinates":[87.161682,22.380115],"type":"Point"}
}