{
  "type": "Feature",
  "properties": {
    "gn:admin1_code":"36",
    "gn:admin2_code":"147.0",
    "gn:asciiname":"Nagla Balodia",
    "gn:country_code":"IN",
    "gn:dem":161,
    "gn:feature_class":"P",
    "gn:feature_code":"PPL",
    "gn:name":"Nagla Balodi\u0101",
    "gn:population":0,
    "gn:timezone":"Asia/Kolkata",
    "iso:country":"IN",
    "ks:ks_name":"Nagla Bilotia",
    "ks:ks_pop":648,
    "ks:ks_type":"HABITATION",
    "ks:ks_uagg_main":0,
    "name:eng_x_preferred":[
        "Nagla Bilotia"
    ],
    "wof:name":"Nagla Bilotia",
    "wof:placetype":"neighbourhood",
    "wof:population":648
},
  "geometry": {"coordinates":[78.59877899999999,27.068144],"type":"Point"}
}