{
  "type": "Feature",
  "properties": {
    "iso:country":"IN",
    "ks:ks_name":"Ranjeetpur",
    "ks:ks_pop":200,
    "ks:ks_type":"HABITATION",
    "name:eng_x_preferred":[
        "Ranjeetpur"
    ],
    "wof:name":"Ranjeetpur",
    "wof:placetype":"locality",
    "wof:population":200
},
  "geometry": {"coordinates":[81.827882,27.166644],"type":"Point"}
}