{
  "type": "Feature",
  "properties": {
    "iso:country":"IN",
    "ks:ks_name":"Jalalpur",
    "ks:ks_pop":29,
    "ks:ks_type":"HABITATION",
    "ks:ks_uagg_main":0,
    "name:eng_x_preferred":[
        "Jalalpur"
    ],
    "wof:name":"Jalalpur",
    "wof:placetype":"neighbourhood",
    "wof:population":29
},
  "geometry": {"coordinates":[82.169912,26.699481],"type":"Point"}
}