{
  "type": "Feature",
  "properties": {
    "iso:country":"IN",
    "ks:ks_alt_nam":"Manamp\u016bndi",
    "ks:ks_name":"Manampundi",
    "ks:ks_type":"VILLAGE",
    "ks:ks_uagg_main":0,
    "name:eng_x_preferred":[
        "Manampundi"
    ],
    "name:eng_x_variant":[
        "Manamp\u016bndi"
    ],
    "wof:name":"Manampundi",
    "wof:placetype":"neighbourhood"
},
  "geometry": {"coordinates":[79.20339,11.977005],"type":"Point"}
}