{
  "type": "Feature",
  "properties": {
    "iso:country":"IN",
    "ks:ks_name":"Kotgaon Upper",
    "ks:ks_pop":67,
    "ks:ks_type":"HABITATION",
    "name:eng_x_preferred":[
        "Kotgaon Upper"
    ],
    "wof:name":"Kotgaon Upper",
    "wof:placetype":"locality",
    "wof:population":67
},
  "geometry": {"coordinates":[81.277287,20.215571],"type":"Point"}
}