{
  "type": "Feature",
  "properties": {
    "iso:country":"IN",
    "ks:ks_name":"Mahatgaon",
    "ks:ks_pop":146,
    "ks:ks_type":"HABITATION",
    "name:eng_x_preferred":[
        "Mahatgaon"
    ],
    "wof:name":"Mahatgaon",
    "wof:placetype":"locality",
    "wof:population":146
},
  "geometry": {"coordinates":[80.34716899999999,29.725578],"type":"Point"}
}