{
  "type": "Feature",
  "properties": {
    "gn:admin1_code":"35.0",
    "gn:admin2_code":"455.0",
    "gn:asciiname":"Amajhiri",
    "gn:country_code":"IN",
    "gn:dem":673,
    "gn:feature_class":"P",
    "gn:feature_code":"PPL",
    "gn:name":"\u0100m\u0101jhiri",
    "gn:population":0,
    "gn:timezone":"Asia/Kolkata",
    "iso:country":"IN",
    "ks:ks_name":"Ambajhiri",
    "ks:ks_pop":1095,
    "ks:ks_type":"HABITATION",
    "name:eng_x_preferred":[
        "Ambajhiri"
    ],
    "name:eng_x_variant":[
        "Amajhiri"
    ],
    "wof:name":"Ambajhiri",
    "wof:placetype":"locality",
    "wof:population":1095
},
  "geometry": {"coordinates":[78.829551,21.834536],"type":"Point"}
}