{
  "type": "Feature",
  "properties": {
    "gn:admin1_code":"36",
    "gn:admin2_code":"166.0",
    "gn:asciiname":"Kumhrar",
    "gn:country_code":"IN",
    "gn:dem":183,
    "gn:feature_class":"P",
    "gn:feature_code":"PPL",
    "gn:name":"Kumhr\u0101r",
    "gn:population":0,
    "gn:timezone":"Asia/Kolkata",
    "iso:country":"IN",
    "name:ben_x_preferred":[
        "\u0995\u09c1\u09ae\u09cd\u09ad\u09b0\u09be\u09b0"
    ],
    "name:ces_x_preferred":[
        "Kumrah\u00e1r"
    ],
    "name:hin_x_preferred":[
        "\u0915\u0941\u092e\u094d\u0930\u0939\u093e\u0930 \u092a\u0930\u093f\u0938\u0930"
    ],
    "name:tam_x_preferred":[
        "\u0b95\u0bc1\u0bae\u0bcd\u0bb9\u0bb0\u0bbe\u0bb0\u0bcd"
    ],
    "name:urd_x_preferred":[
        "\u06a9\u0645\u06c1\u0631\u0627\u0631"
    ],
    "wof:name":"Kumhrar",
    "wof:placetype":"locality"
},
  "geometry": {"coordinates":[78.96692,25.6926],"type":"Point"}
}