{
  "type": "Feature",
  "properties": {
    "iso:country":"IN",
    "ks:ks_name":"Araji Dhankuni",
    "ks:ks_pop":54,
    "ks:ks_type":"VILLAGE",
    "name:eng_x_preferred":[
        "Araji Dhankuni"
    ],
    "wof:name":"Araji Dhankuni",
    "wof:placetype":"locality",
    "wof:population":54
},
  "geometry": {"coordinates":[79.827596,28.709853],"type":"Point"}
}