{
  "type": "Feature",
  "properties": {
    "iso:country":"IN",
    "ks:ks_name":"Chhatrang Kirwahipara",
    "ks:ks_pop":283,
    "ks:ks_type":"HABITATION",
    "name:eng_x_preferred":[
        "Chhatrang Kirwahipara"
    ],
    "wof:name":"Chhatrang Kirwahipara",
    "wof:placetype":"locality",
    "wof:population":283
},
  "geometry": {"coordinates":[82.58877200000001,23.545458],"type":"Point"}
}