{
  "type": "Feature",
  "properties": {
    "gn:admin1_code":"37.0",
    "gn:admin2_code":"416.0",
    "gn:asciiname":"Chandragudem",
    "gn:country_code":"IN",
    "gn:dem":103,
    "gn:feature_class":"P",
    "gn:feature_code":"PPL",
    "gn:name":"Chandrag\u016bdem",
    "gn:population":0,
    "gn:timezone":"Asia/Kolkata",
    "iso:country":"IN",
    "name:hin_x_preferred":[
        "\u091a\u0902\u0926\u094d\u0930\u0917\u0942\u0921\u0946\u0902"
    ],
    "name:new_x_preferred":[
        "\u091a\u0902\u0926\u094d\u0930\u0917\u0942\u0921\u0946\u0902"
    ],
    "name:tat_x_preferred":[
        "\u0427\u0430\u043d\u0434\u0440\u0430\u0433\u0443\u0434\u0435\u043c"
    ],
    "name:tel_x_preferred":[
        "\u0c1a\u0c02\u0c21\u0c4d\u0c30\u0c17\u0c42\u0c21\u0c46\u0c02"
    ],
    "wof:name":"Chandragudem",
    "wof:placetype":"locality"
},
  "geometry": {"coordinates":[81.02508,17.95752000000001],"type":"Point"}
}