{
  "type": "Feature",
  "properties": {
    "iso:country":"IN",
    "ks:ks_name":"Ambatoli",
    "ks:ks_pop":40,
    "ks:ks_type":"HABITATION",
    "name:eng_x_preferred":[
        "Ambatoli"
    ],
    "wof:name":"Ambatoli",
    "wof:placetype":"locality",
    "wof:population":40
},
  "geometry": {"coordinates":[84.205958,22.389196],"type":"Point"}
}