{
  "type": "Feature",
  "properties": {
    "iso:country":"IN",
    "ks:ks_name":"Jaim",
    "ks:ks_pop":40,
    "ks:ks_type":"VILLAGE",
    "name:eng_x_preferred":[
        "Jaim"
    ],
    "wof:name":"Jaim",
    "wof:placetype":"locality",
    "wof:population":40
},
  "geometry": {"coordinates":[79.221114,30.155646],"type":"Point"}
}