{
  "type": "Feature",
  "properties": {
    "iso:country":"IN",
    "ks:ks_alt_nam":"Naw\u0101dih",
    "ks:ks_name":"Nawadih",
    "ks:ks_pop":195,
    "ks:ks_type":"VILLAGE",
    "name:eng_x_preferred":[
        "Nawadih"
    ],
    "name:eng_x_variant":[
        "Naw\u0101dih"
    ],
    "wof:name":"Nawadih",
    "wof:placetype":"locality",
    "wof:population":195
},
  "geometry": {"coordinates":[85.651189,23.877474],"type":"Point"}
}