{
  "type": "Feature",
  "properties": {
    "gn:admin1_code":"38.0",
    "gn:admin2_code":"358.0",
    "gn:asciiname":"Raksahi",
    "gn:country_code":"IN",
    "gn:dem":138,
    "gn:feature_class":"P",
    "gn:feature_code":"PPL",
    "gn:name":"Raks\u0101h\u012b",
    "gn:population":0,
    "gn:timezone":"Asia/Kolkata",
    "iso:country":"IN",
    "wof:name":"Raksahi",
    "wof:placetype":"locality"
},
  "geometry": {"coordinates":[84.03338000000002,24.60604],"type":"Point"}
}