{
  "type": "Feature",
  "properties": {
    "iso:country":"IN",
    "ks:ks_name":"Pupri Urf Nuripur",
    "ks:ks_pop":1557,
    "ks:ks_type":"VILLAGE",
    "name:eng_x_preferred":[
        "Pupri Urf Nuripur"
    ],
    "wof:name":"Pupri Urf Nuripur",
    "wof:placetype":"locality",
    "wof:population":1557
},
  "geometry": {"coordinates":[85.369595,26.044397],"type":"Point"}
}