{
  "type": "Feature",
  "properties": {
    "gn:admin1_code":"34.0",
    "gn:admin2_code":"226.0",
    "gn:asciiname":"Baijnathmahatotola",
    "gn:country_code":"IN",
    "gn:dem":40,
    "gn:feature_class":"P",
    "gn:feature_code":"PPL",
    "gn:name":"Baijn\u0101thmah\u0101totola",
    "gn:population":0,
    "gn:timezone":"Asia/Kolkata",
    "iso:country":"IN",
    "wof:name":"Baijnathmahatotola",
    "wof:placetype":"locality"
},
  "geometry": {"coordinates":[86.32266,25.31018],"type":"Point"}
}