{
  "type": "Feature",
  "properties": {
    "iso:country":"IN",
    "ks:ks_alt_nam":"2 DLP",
    "ks:ks_name":"2 Dlp",
    "ks:ks_pop":351,
    "ks:ks_type":"HABITATION",
    "name:eng_x_preferred":[
        "2 Dlp"
    ],
    "wof:name":"2 Dlp",
    "wof:placetype":"locality",
    "wof:population":351
},
  "geometry": {"coordinates":[74.417717,29.77248],"type":"Point"}
}