{
  "type": "Feature",
  "properties": {
    "iso:country":"IN",
    "ks:ks_name":"Sandhera",
    "ks:ks_pop":93,
    "ks:ks_type":"HABITATION",
    "name:eng_x_preferred":[
        "Sandhera"
    ],
    "wof:name":"Sandhera",
    "wof:placetype":"locality",
    "wof:population":93
},
  "geometry": {"coordinates":[72.55649,23.5682],"type":"Point"}
}