{
  "type": "Feature",
  "properties": {
    "iso:country":"IN",
    "ks:ks_name":"Mulgam",
    "ks:ks_pop":364,
    "ks:ks_type":"HABITATION",
    "name:eng_x_preferred":[
        "Mulgam"
    ],
    "wof:name":"Mulgam",
    "wof:placetype":"locality",
    "wof:population":364
},
  "geometry": {"coordinates":[73.310389,20.285917],"type":"Point"}
}