{
  "type": "Feature",
  "properties": {
    "gn:admin1_code":"36",
    "gn:admin2_code":"168.0",
    "gn:asciiname":"Birhat",
    "gn:country_code":"IN",
    "gn:dem":130,
    "gn:feature_class":"P",
    "gn:feature_code":"PPL",
    "gn:name":"Birhat",
    "gn:population":0,
    "gn:timezone":"Asia/Kolkata",
    "iso:country":"IN",
    "ks:ks_name":"Birhat",
    "ks:ks_pop":1314,
    "ks:ks_type":"VILLAGE",
    "name:eng_x_preferred":[
        "Birhat"
    ],
    "wof:name":"Birhat",
    "wof:placetype":"locality",
    "wof:population":1314
},
  "geometry": {"coordinates":[79.532143,25.815576],"type":"Point"}
}