{
  "type": "Feature",
  "properties": {
    "iso:country":"IN",
    "ks:ks_name":"Devulanaikthanda",
    "ks:ks_pop":205,
    "ks:ks_type":"HABITATION",
    "ks:ks_uagg_main":0,
    "name:eng_x_preferred":[
        "Devulanaikthanda"
    ],
    "wof:name":"Devulanaikthanda",
    "wof:placetype":"neighbourhood",
    "wof:population":205
},
  "geometry": {"coordinates":[78.908137,16.63399],"type":"Point"}
}