{
  "type": "Feature",
  "properties": {
    "iso:country":"IN",
    "ks:ks_name":"Kompalli",
    "ks:ks_type":"VILLAGE",
    "name:eng_x_preferred":[
        "Kompalli"
    ],
    "wof:name":"Kompalli",
    "wof:placetype":"locality"
},
  "geometry": {"coordinates":[77.42995999999999,17.014092],"type":"Point"}
}