{
  "type": "Feature",
  "properties": {
    "iso:country":"IN",
    "ks:ks_name":"Sijhuabahiar",
    "ks:ks_pop":242,
    "ks:ks_type":"VILLAGE",
    "ks:ks_uagg_main":0,
    "name:eng_x_preferred":[
        "Sijhuabahiar"
    ],
    "wof:name":"Sijhuabahiar",
    "wof:placetype":"neighbourhood",
    "wof:population":242
},
  "geometry": {"coordinates":[87.134208,24.487155],"type":"Point"}
}