{
  "type": "Feature",
  "properties": {
    "gn:admin1_code":"19.0",
    "gn:admin2_code":"573.0",
    "gn:asciiname":"Tavarekere",
    "gn:country_code":"IN",
    "gn:dem":756,
    "gn:feature_class":"P",
    "gn:feature_code":"PPL",
    "gn:name":"T\u0101varekere",
    "gn:population":0,
    "gn:timezone":"Asia/Kolkata",
    "iso:country":"IN",
    "ks:ks_alt_nam":"T\u0101varekere",
    "ks:ks_name":"Tavarekere",
    "ks:ks_pop":648,
    "ks:ks_type":"VILLAGE",
    "name:eng_x_preferred":[
        "Tavarekere"
    ],
    "name:eng_x_variant":[
        "T\u0101varekere"
    ],
    "wof:name":"Tavarekere",
    "wof:placetype":"locality",
    "wof:population":648
},
  "geometry": {"coordinates":[76.842372,12.717946],"type":"Point"}
}