{
  "type": "Feature",
  "properties": {
    "iso:country":"IN",
    "ks:ks_alt_nam":"GACHHI  TOLA",
    "ks:ks_name":"Gachhi Tola",
    "ks:ks_pop":358,
    "ks:ks_type":"HABITATION",
    "name:eng_x_preferred":[
        "Gachhi Tola"
    ],
    "name:eng_x_variant":[
        "GACHHI  TOLA"
    ],
    "wof:name":"Gachhi Tola",
    "wof:placetype":"locality",
    "wof:population":358
},
  "geometry": {"coordinates":[86.269783,25.996567],"type":"Point"}
}