{
  "type": "Feature",
  "properties": {
    "iso:country":"IN",
    "ks:ks_name":"Nagla Braj",
    "ks:ks_pop":552,
    "ks:ks_type":"HABITATION",
    "ks:ks_uagg_main":0,
    "name:eng_x_preferred":[
        "Nagla Braj"
    ],
    "wof:name":"Nagla Braj",
    "wof:placetype":"neighbourhood",
    "wof:population":552
},
  "geometry": {"coordinates":[78.725183,26.854973],"type":"Point"}
}