{
  "type": "Feature",
  "properties": {
    "iso:country":"IN",
    "ks:ks_name":"Barreh Maniram",
    "ks:ks_pop":7,
    "ks:ks_type":"HABITATION",
    "name:eng_x_preferred":[
        "Barreh Maniram"
    ],
    "wof:name":"Barreh Maniram",
    "wof:placetype":"locality",
    "wof:population":7
},
  "geometry": {"coordinates":[80.98372000000001,24.33597],"type":"Point"}
}