{
  "type": "Feature",
  "properties": {
    "iso:country":"IN",
    "ks:ks_name":"Chikamharpur",
    "ks:ks_type":"VILLAGE",
    "ks:ks_uagg_main":0,
    "name:eng_x_preferred":[
        "Chikamharpur"
    ],
    "wof:name":"Chikamharpur",
    "wof:placetype":"neighbourhood"
},
  "geometry": {"coordinates":[77.329803,28.673687],"type":"Point"}
}