{
  "type": "Feature",
  "properties": {
    "iso:country":"IN",
    "ks:ks_name":"Red",
    "ks:ks_pop":402,
    "ks:ks_type":"VILLAGE",
    "name:eng_x_preferred":[
        "Red"
    ],
    "wof:name":"Red",
    "wof:placetype":"locality",
    "wof:population":402
},
  "geometry": {"coordinates":[81.869542,23.691376],"type":"Point"}
}