{
  "type": "Feature",
  "properties": {
    "gn:admin1_code":"19.0",
    "gn:admin2_code":"573.0",
    "gn:asciiname":"Marachakanahalli",
    "gn:country_code":"IN",
    "gn:dem":749,
    "gn:feature_class":"P",
    "gn:feature_code":"PPL",
    "gn:name":"M\u0101rach\u0101kanahalli",
    "gn:population":0,
    "gn:timezone":"Asia/Kolkata",
    "iso:country":"IN",
    "wof:name":"Marachakanahalli",
    "wof:placetype":"locality"
},
  "geometry": {"coordinates":[76.78551999999998,12.54173],"type":"Point"}
}