{
  "type": "Feature",
  "properties": {
    "iso:country":"IN",
    "ks:ks_name":"Pitti",
    "ks:ks_type":"VILLAGE",
    "name:eng_x_preferred":[
        "Pitti"
    ],
    "wof:name":"Pitti",
    "wof:placetype":"locality"
},
  "geometry": {"coordinates":[73.62782799999999,10.073539],"type":"Point"}
}