{
  "type": "Feature",
  "properties": {
    "iso:country":"IN",
    "ks:ks_name":"Lingegowdanadoddi",
    "ks:ks_pop":334,
    "ks:ks_type":"HABITATION",
    "name:eng_x_preferred":[
        "Lingegowdanadoddi"
    ],
    "wof:name":"Lingegowdanadoddi",
    "wof:placetype":"locality",
    "wof:population":334
},
  "geometry": {"coordinates":[77.321939,12.581707],"type":"Point"}
}