{
  "type": "Feature",
  "properties": {
    "iso:country":"IN",
    "ks:ks_alt_nam":"Indira colony",
    "ks:ks_name":"Indira Colony",
    "ks:ks_pop":514,
    "ks:ks_type":"HABITATION",
    "name:eng_x_preferred":[
        "Indira Colony"
    ],
    "wof:name":"Indira Colony",
    "wof:placetype":"locality",
    "wof:population":514
},
  "geometry": {"coordinates":[72.702493,22.404432],"type":"Point"}
}