{
  "type": "Feature",
  "properties": {
    "iso:country":"IN",
    "ks:ks_name":"Metial",
    "ks:ks_pop":410,
    "ks:ks_type":"VILLAGE",
    "ks:ks_uagg_main":0,
    "name:eng_x_preferred":[
        "Metial"
    ],
    "wof:name":"Metial",
    "wof:placetype":"neighbourhood",
    "wof:population":410
},
  "geometry": {"coordinates":[87.105239,22.44636],"type":"Point"}
}