{
  "type": "Feature",
  "properties": {
    "iso:country":"IN",
    "ks:ks_name":"Naya Tola",
    "ks:ks_pop":415,
    "ks:ks_type":"HABITATION",
    "name:eng_x_preferred":[
        "Naya Tola"
    ],
    "wof:name":"Naya Tola",
    "wof:placetype":"locality",
    "wof:population":415
},
  "geometry": {"coordinates":[85.62178400000001,26.866208],"type":"Point"}
}