{
  "type": "Feature",
  "properties": {
    "iso:country":"IN",
    "ks:ks_name":"Master",
    "ks:ks_pop":123,
    "ks:ks_type":"HABITATION",
    "name:eng_x_preferred":[
        "Master"
    ],
    "wof:name":"Master",
    "wof:placetype":"locality",
    "wof:population":123
},
  "geometry": {"coordinates":[73.190907,21.010325],"type":"Point"}
}