{
  "type": "Feature",
  "properties": {
    "iso:country":"IN",
    "ks:ks_name":"Ravidas Pura",
    "ks:ks_pop":48,
    "ks:ks_type":"HABITATION",
    "ks:ks_uagg_main":0,
    "name:eng_x_preferred":[
        "Ravidas Pura"
    ],
    "wof:name":"Ravidas Pura",
    "wof:placetype":"neighbourhood",
    "wof:population":48
},
  "geometry": {"coordinates":[81.66667700000001,27.376152],"type":"Point"}
}