{
  "type": "Feature",
  "properties": {
    "iso:country":"IN",
    "ks:ks_name":"Panphoolpara",
    "ks:ks_pop":1344,
    "ks:ks_type":"HABITATION",
    "ks:ks_uagg_main":0,
    "name:eng_x_preferred":[
        "Panphoolpara"
    ],
    "wof:name":"Panphoolpara",
    "wof:placetype":"locality",
    "wof:population":1344
},
  "geometry": {"coordinates":[88.209062,22.797506],"type":"Point"}
}