{
  "type": "Feature",
  "properties": {
    "iso:country":"IN",
    "ks:ks_name":"Dhanori",
    "ks:ks_pop":41,
    "ks:ks_type":"HABITATION",
    "name:eng_x_preferred":[
        "Dhanori"
    ],
    "wof:name":"Dhanori",
    "wof:placetype":"locality",
    "wof:population":41
},
  "geometry": {"coordinates":[76.504346,22.854876],"type":"Point"}
}