{
  "type": "Feature",
  "properties": {
    "gn:admin1_code":"19.0",
    "gn:admin2_code":"575.0",
    "gn:asciiname":"Kavalamudur",
    "gn:country_code":"IN",
    "gn:dem":71,
    "gn:feature_class":"P",
    "gn:feature_code":"PPLL",
    "gn:name":"K\u0101valam\u016bd\u016br",
    "gn:population":0,
    "gn:timezone":"Asia/Kolkata",
    "iso:country":"IN",
    "ks:ks_name":"Kavalmudur",
    "ks:ks_pop":4361,
    "ks:ks_type":"VILLAGE",
    "name:eng_x_preferred":[
        "Kavalmudur"
    ],
    "name:eng_x_variant":[
        "Kavalamudur"
    ],
    "wof:name":"Kavalmudur",
    "wof:placetype":"locality",
    "wof:population":4361
},
  "geometry": {"coordinates":[75.13980100000001,12.918798],"type":"Point"}
}