{
  "type": "Feature",
  "properties": {
    "iso:country":"IN",
    "ks:ks_name":"Kanammana Colony",
    "ks:ks_pop":29,
    "ks:ks_type":"HABITATION",
    "name:eng_x_preferred":[
        "Kanammana Colony"
    ],
    "wof:name":"Kanammana Colony",
    "wof:placetype":"locality",
    "wof:population":29
},
  "geometry": {"coordinates":[74.425133,14.465587],"type":"Point"}
}