{
  "type": "Feature",
  "properties": {
    "iso:country":"IN",
    "ks:ks_name":"Raowadi",
    "ks:ks_pop":71,
    "ks:ks_type":"HABITATION",
    "name:eng_x_preferred":[
        "Raowadi"
    ],
    "wof:name":"Raowadi",
    "wof:placetype":"locality",
    "wof:population":71
},
  "geometry": {"coordinates":[73.606792,16.882661],"type":"Point"}
}