{
  "type": "Feature",
  "properties": {
    "gn:admin1_code":"24",
    "gn:admin2_code":"129.0",
    "gn:asciiname":"Banni",
    "gn:country_code":"IN",
    "gn:dem":277,
    "gn:feature_class":"P",
    "gn:feature_code":"PPL",
    "gn:name":"Banni",
    "gn:population":0,
    "gn:timezone":"Asia/Kolkata",
    "iso:country":"IN",
    "name:deu_x_preferred":[
        "Banni"
    ],
    "wof:name":"Banni",
    "wof:placetype":"locality"
},
  "geometry": {"coordinates":[76.30537,24.77113],"type":"Point"}
}