{
  "type": "Feature",
  "properties": {
    "iso:country":"IN",
    "ks:ks_alt_nam":"TURKAULI MALHAUTI",
    "ks:ks_name":"Turkauli Malhauti",
    "ks:ks_pop":280,
    "ks:ks_type":"HABITATION",
    "ks:ks_uagg_main":0,
    "name:eng_x_preferred":[
        "Turkauli Malhauti"
    ],
    "wof:name":"Turkauli Malhauti",
    "wof:placetype":"neighbourhood",
    "wof:population":280
},
  "geometry": {"coordinates":[82.395962,26.054435],"type":"Point"}
}