{
  "type": "Feature",
  "properties": {
    "iso:country":"IN",
    "ks:ks_name":"Kamarajnagar",
    "ks:ks_pop":62,
    "ks:ks_type":"HABITATION",
    "name:eng_x_preferred":[
        "Kamarajnagar"
    ],
    "wof:name":"Kamarajnagar",
    "wof:placetype":"locality",
    "wof:population":62
},
  "geometry": {"coordinates":[78.1071,10.390795],"type":"Point"}
}