{
  "type": "Feature",
  "properties": {
    "gn:admin1_code":"36",
    "gn:admin2_code":"145.0",
    "gn:asciiname":"Nagla Badam",
    "gn:country_code":"IN",
    "gn:dem":179,
    "gn:feature_class":"P",
    "gn:feature_code":"PPL",
    "gn:name":"Nagla B\u0101d\u0101m",
    "gn:population":0,
    "gn:timezone":"Asia/Kolkata",
    "iso:country":"IN",
    "wof:name":"Nagla Badam",
    "wof:placetype":"locality"
},
  "geometry": {"coordinates":[77.76966,27.50035],"type":"Point"}
}