{
  "type": "Feature",
  "properties": {
    "iso:country":"IN",
    "ks:ks_name":"Guluti",
    "ks:ks_pop":348,
    "ks:ks_type":"VILLAGE",
    "name:eng_x_preferred":[
        "Guluti"
    ],
    "wof:name":"Guluti",
    "wof:placetype":"locality",
    "wof:population":348
},
  "geometry": {"coordinates":[83.663858,19.181974],"type":"Point"}
}