{
  "type": "Feature",
  "properties": {
    "gn:admin1_code":"37",
    "gn:admin2_code":"406.0",
    "gn:asciiname":"Khaira",
    "gn:country_code":"IN",
    "gn:dem":306,
    "gn:feature_class":"P",
    "gn:feature_code":"PPL",
    "gn:name":"Khaira",
    "gn:population":0,
    "gn:timezone":"Asia/Kolkata",
    "iso:country":"IN",
    "ks:ks_name":"Khaira",
    "ks:ks_pop":1154,
    "ks:ks_type":"VILLAGE",
    "name:eng_x_preferred":[
        "Khaira"
    ],
    "name:hin_x_preferred":[
        "\u0916\u0948\u0930\u093e"
    ],
    "name:new_x_preferred":[
        "\u0916\u0948\u0930\u093e"
    ],
    "wof:name":"Khaira",
    "wof:placetype":"locality",
    "wof:population":1154
},
  "geometry": {"coordinates":[81.54082099999999,22.121179],"type":"Point"}
}