{
  "type": "Feature",
  "properties": {
    "iso:country":"IN",
    "ks:ks_name":"Purnia",
    "ks:ks_pop":201,
    "ks:ks_type":"VILLAGE",
    "name:eng_x_preferred":[
        "Purnia"
    ],
    "wof:name":"Purnia",
    "wof:placetype":"locality",
    "wof:population":201
},
  "geometry": {"coordinates":[87.47927300000001,25.136897],"type":"Point"}
}