{
  "type": "Feature",
  "properties": {
    "gn:admin1_code":"19.0",
    "gn:admin2_code":"576.0",
    "gn:asciiname":"Hanagallu Shetthalli",
    "gn:country_code":"IN",
    "gn:dem":1166,
    "gn:feature_class":"P",
    "gn:feature_code":"PPL",
    "gn:name":"Hanagallu Shetthalli",
    "gn:population":0,
    "gn:timezone":"Asia/Kolkata",
    "iso:country":"IN",
    "wof:name":"Hanagallu Shetthalli",
    "wof:placetype":"locality"
},
  "geometry": {"coordinates":[75.82555000000001,12.60693],"type":"Point"}
}