{
  "type": "Feature",
  "properties": {
    "iso:country":"IN",
    "ks:ks_name":"Daukiyon Ki Dhani",
    "ks:ks_pop":200,
    "ks:ks_type":"VILLAGE",
    "name:eng_x_preferred":[
        "Daukiyon Ki Dhani"
    ],
    "wof:name":"Daukiyon Ki Dhani",
    "wof:placetype":"locality",
    "wof:population":200
},
  "geometry": {"coordinates":[71.625497,25.813775],"type":"Point"}
}