{
  "type": "Feature",
  "properties": {
    "iso:country":"IN",
    "ks:ks_name":"Bhaiswaha",
    "ks:ks_pop":48,
    "ks:ks_type":"VILLAGE",
    "name:eng_x_preferred":[
        "Bhaiswaha"
    ],
    "wof:name":"Bhaiswaha",
    "wof:placetype":"locality",
    "wof:population":48
},
  "geometry": {"coordinates":[78.329088,24.336146],"type":"Point"}
}