{
  "type": "Feature",
  "properties": {
    "gn:admin1_code":"23.0",
    "gn:admin2_code":"048",
    "gn:asciiname":"Kachhwa",
    "gn:country_code":"IN",
    "gn:dem":252,
    "gn:feature_class":"P",
    "gn:feature_code":"PPL",
    "gn:name":"Kachhwa",
    "gn:population":0,
    "gn:timezone":"Asia/Kolkata",
    "iso:country":"IN",
    "name:bpy_x_preferred":[
        "\u0995\u09be\u099b\u09cc\u09f1\u09be"
    ],
    "name:ceb_x_preferred":[
        "Kachhw\u0101"
    ],
    "name:ita_x_preferred":[
        "Kachhwa"
    ],
    "name:mlg_x_preferred":[
        "Kachhwa"
    ],
    "name:msa_x_preferred":[
        "Kachhwa"
    ],
    "name:new_x_preferred":[
        "\u0915\u091b\u094d\u0935\u093e"
    ],
    "name:nld_x_preferred":[
        "Kachhwa"
    ],
    "name:pol_x_preferred":[
        "Kachhwa"
    ],
    "name:por_x_preferred":[
        "Kachhwa"
    ],
    "name:swe_x_preferred":[
        "Kachhw\u0101"
    ],
    "name:urd_x_preferred":[
        "\u06a9\u0686\u06be\u0648\u0627"
    ],
    "name:vie_x_preferred":[
        "Kachhwa"
    ],
    "name:zho_x_preferred":[
        "\u5361\u5947\u74e6"
    ],
    "wof:name":"Kachhwa",
    "wof:placetype":"locality"
},
  "geometry": {"coordinates":[76.5831,30.17667],"type":"Point"}
}