{
  "type": "Feature",
  "properties": {
    "gn:admin1_code":"19.0",
    "gn:admin2_code":"568.0",
    "gn:asciiname":"Salagadi",
    "gn:country_code":"IN",
    "gn:dem":642,
    "gn:feature_class":"P",
    "gn:feature_code":"PPL",
    "gn:name":"Salagadi",
    "gn:population":0,
    "gn:timezone":"Asia/Kolkata",
    "iso:country":"IN",
    "ks:ks_name":"Salgadi",
    "ks:ks_pop":165,
    "ks:ks_type":"VILLAGE",
    "name:eng_x_preferred":[
        "Salgadi"
    ],
    "name:eng_x_variant":[
        "Salagadi"
    ],
    "wof:name":"Salgadi",
    "wof:placetype":"locality",
    "wof:population":165
},
  "geometry": {"coordinates":[75.328908,13.644177],"type":"Point"}
}