{
  "type": "Feature",
  "properties": {
    "iso:country":"IN",
    "ks:ks_alt_nam":"J\u0101mkundia",
    "ks:ks_name":"Jamkundia",
    "ks:ks_type":"VILLAGE",
    "name:eng_x_preferred":[
        "Jamkundia"
    ],
    "name:eng_x_variant":[
        "J\u0101mkundia"
    ],
    "wof:name":"Jamkundia",
    "wof:placetype":"locality"
},
  "geometry": {"coordinates":[85.31548600000001,22.254274],"type":"Point"}
}