{
  "type": "Feature",
  "properties": {
    "iso:country":"IN",
    "ks:ks_name":"Kunarpal",
    "ks:ks_pop":319,
    "ks:ks_type":"HABITATION",
    "name:eng_x_preferred":[
        "Kunarpal"
    ],
    "wof:name":"Kunarpal",
    "wof:placetype":"locality",
    "wof:population":319
},
  "geometry": {"coordinates":[86.70932999999999,21.658335],"type":"Point"}
}