{
  "type": "Feature",
  "properties": {
    "iso:country":"IN",
    "ks:ks_name":"Raghabpur Colony",
    "ks:ks_pop":527,
    "ks:ks_type":"HABITATION",
    "ks:ks_uagg_main":0,
    "name:eng_x_preferred":[
        "Raghabpur Colony"
    ],
    "wof:name":"Raghabpur Colony",
    "wof:placetype":"neighbourhood",
    "wof:population":527
},
  "geometry": {"coordinates":[88.718857,23.223298],"type":"Point"}
}