{
  "type": "Feature",
  "properties": {
    "iso:country":"IN",
    "ks:ks_name":"Jodidhara",
    "ks:ks_pop":141,
    "ks:ks_type":"HABITATION",
    "name:eng_x_preferred":[
        "Jodidhara"
    ],
    "wof:name":"Jodidhara",
    "wof:placetype":"locality",
    "wof:population":141
},
  "geometry": {"coordinates":[82.278452,18.710105],"type":"Point"}
}