{
  "type": "Feature",
  "properties": {
    "gn:admin1_code":"36",
    "gn:admin2_code":"194.0",
    "gn:asciiname":"Kanakpur",
    "gn:country_code":"IN",
    "gn:dem":85,
    "gn:feature_class":"P",
    "gn:feature_code":"PPL",
    "gn:name":"Kanakpur",
    "gn:population":0,
    "gn:timezone":"Asia/Kolkata",
    "iso:country":"IN",
    "ks:ks_name":"Kanakpur",
    "ks:ks_pop":768,
    "ks:ks_type":"VILLAGE",
    "name:ceb_x_preferred":[
        "Kakanpur"
    ],
    "name:eng_x_preferred":[
        "Kanakpur"
    ],
    "name:fra_x_preferred":[
        "Kakanpur"
    ],
    "name:mai_x_preferred":[
        "\u0915\u0928\u0915\u092a\u0942\u0930"
    ],
    "name:msa_x_preferred":[
        "Kakanpur"
    ],
    "name:nep_x_preferred":[
        "\u0915\u0928\u0915\u092a\u0942\u0930"
    ],
    "name:new_x_preferred":[
        "\u0915\u0915\u0928\u092a\u0941\u0930"
    ],
    "name:pol_x_preferred":[
        "Kakanpur"
    ],
    "wof:name":"Kanakpur",
    "wof:placetype":"locality",
    "wof:population":768
},
  "geometry": {"coordinates":[82.46062999999999,25.988322],"type":"Point"}
}