{
  "type": "Feature",
  "properties": {
    "iso:country":"IN",
    "ks:ks_name":"Batnan",
    "ks:ks_pop":2014,
    "ks:ks_type":"VILLAGE",
    "name:eng_x_preferred":[
        "Batnan"
    ],
    "wof:name":"Batnan",
    "wof:placetype":"locality",
    "wof:population":2014
},
  "geometry": {"coordinates":[87.808301,22.117298],"type":"Point"}
}