{
  "type": "Feature",
  "properties": {
    "gn:admin1_code":"11",
    "gn:admin2_code":"24.0",
    "gn:asciiname":"Kerta",
    "gn:country_code":"IN",
    "gn:dem":515,
    "gn:feature_class":"P",
    "gn:feature_code":"PPL",
    "gn:name":"Kerta",
    "gn:population":0,
    "gn:timezone":"Asia/Kolkata",
    "iso:country":"IN",
    "name:ces_x_preferred":[
        "Kerta"
    ],
    "name:epo_x_preferred":[
        "Kerta"
    ],
    "name:fas_x_preferred":[
        "\u06a9\u0631\u062a\u0627"
    ],
    "name:fra_x_preferred":[
        "Kerta"
    ],
    "name:hun_x_preferred":[
        "Kerta"
    ],
    "name:ita_x_preferred":[
        "Kerta"
    ],
    "name:msa_x_preferred":[
        "Kerta"
    ],
    "name:nld_x_preferred":[
        "Kerta"
    ],
    "name:ron_x_preferred":[
        "Kerta"
    ],
    "name:slk_x_preferred":[
        "Kerta"
    ],
    "name:slv_x_preferred":[
        "Kerta"
    ],
    "name:swe_x_preferred":[
        "Kerta"
    ],
    "name:vie_x_preferred":[
        "Kerta"
    ],
    "name:zho_x_preferred":[
        "\u51ef\u5c14\u9676"
    ],
    "wof:name":"Kerta",
    "wof:placetype":"locality"
},
  "geometry": {"coordinates":[76.04584,32.1997],"type":"Point"}
}