{
  "type": "Feature",
  "properties": {
    "iso:country":"IN",
    "ks:ks_alt_nam":"BAZAR",
    "ks:ks_name":"Bazar",
    "ks:ks_pop":729,
    "ks:ks_type":"HABITATION",
    "ks:ks_uagg_main":0,
    "name:eng_x_preferred":[
        "Bazar"
    ],
    "wof:name":"Bazar",
    "wof:placetype":"neighbourhood",
    "wof:population":729
},
  "geometry": {"coordinates":[81.968526,25.379858],"type":"Point"}
}