{
  "type": "Feature",
  "properties": {
    "iso:country":"IN",
    "ks:ks_name":"MV 36",
    "ks:ks_pop":1394,
    "ks:ks_type":"VILLAGE",
    "name:eng_x_preferred":[
        "MV 36"
    ],
    "wof:name":"MV 36",
    "wof:placetype":"locality",
    "wof:population":1394
},
  "geometry": {"coordinates":[82.09783899999999,18.269257],"type":"Point"}
}