{
  "type": "Feature",
  "properties": {
    "iso:country":"IN",
    "ks:ks_name":"Dharni",
    "ks:ks_pop":493,
    "ks:ks_type":"VILLAGE",
    "name:eng_x_preferred":[
        "Dharni"
    ],
    "wof:name":"Dharni",
    "wof:placetype":"locality",
    "wof:population":493
},
  "geometry": {"coordinates":[73.23777,18.869356],"type":"Point"}
}