{
  "type": "Feature",
  "properties": {
    "gn:admin1_code":"23",
    "gn:admin2_code":"52.0",
    "gn:asciiname":"Papri",
    "gn:country_code":"IN",
    "gn:dem":307,
    "gn:feature_class":"P",
    "gn:feature_code":"PPL",
    "gn:name":"P\u0101pri",
    "gn:population":0,
    "gn:timezone":"Asia/Kolkata",
    "iso:country":"IN",
    "ks:ks_alt_nam":"P\u0101pri",
    "ks:ks_name":"Papri",
    "ks:ks_type":"VILLAGE",
    "ks:ks_uagg_main":0,
    "name:eng_x_preferred":[
        "Papri"
    ],
    "name:eng_x_variant":[
        "P\u0101pri"
    ],
    "wof:name":"Papri",
    "wof:placetype":"neighbourhood"
},
  "geometry": {"coordinates":[76.742002,30.658434],"type":"Point"}
}