{
  "type": "Feature",
  "properties": {
    "gn:admin1_code":"39.0",
    "gn:admin2_code":"63.0",
    "gn:asciiname":"Rikhel",
    "gn:country_code":"IN",
    "gn:dem":1395,
    "gn:feature_class":"P",
    "gn:feature_code":"PPL",
    "gn:name":"Rikhel",
    "gn:population":0,
    "gn:timezone":"Asia/Kolkata",
    "iso:country":"IN",
    "ks:ks_name":"Rikhel",
    "ks:ks_type":"VILLAGE",
    "name:eng_x_preferred":[
        "Rikhel"
    ],
    "name:fas_x_preferred":[
        "\u0631\u06cc\u062e\u0644"
    ],
    "name:fra_x_preferred":[
        "Rikhel"
    ],
    "wof:name":"Rikhel",
    "wof:placetype":"locality"
},
  "geometry": {"coordinates":[79.783733,29.797198],"type":"Point"}
}