{
  "type": "Feature",
  "properties": {
    "gn:admin1_code":"34.0",
    "gn:admin2_code":"221.0",
    "gn:asciiname":"Baikunthpur",
    "gn:country_code":"IN",
    "gn:dem":54,
    "gn:feature_class":"P",
    "gn:feature_code":"PPL",
    "gn:name":"Baikunthpur",
    "gn:population":0,
    "gn:timezone":"Asia/Kolkata",
    "iso:country":"IN",
    "name:ceb_x_preferred":[
        "Baikunthpur"
    ],
    "name:ita_x_preferred":[
        "Baikunthpur"
    ],
    "name:nld_x_preferred":[
        "Baikunthpur"
    ],
    "name:swe_x_preferred":[
        "Baikunthpur"
    ],
    "wof:name":"Baikunthpur",
    "wof:placetype":"locality"
},
  "geometry": {"coordinates":[85.76761999999999,25.68273],"type":"Point"}
}