{
  "type": "Feature",
  "properties": {
    "iso:country":"IN",
    "ks:ks_name":"Maitygheri",
    "ks:ks_pop":2082,
    "ks:ks_type":"HABITATION",
    "name:eng_x_preferred":[
        "Maitygheri"
    ],
    "wof:name":"Maitygheri",
    "wof:placetype":"locality",
    "wof:population":2082
},
  "geometry": {"coordinates":[88.449299,21.943565],"type":"Point"}
}