{
  "type": "Feature",
  "properties": {
    "gn:admin1_code":"23.0",
    "gn:admin2_code":"36.0",
    "gn:asciiname":"Pajian",
    "gn:country_code":"IN",
    "gn:dem":217,
    "gn:feature_class":"P",
    "gn:feature_code":"PPL",
    "gn:name":"P\u0101ji\u0101n",
    "gn:population":0,
    "gn:timezone":"Asia/Kolkata",
    "iso:country":"IN",
    "name:und_x_variant":[
        "P\u0101ji\u0101n",
        "Kam\u0101lpur"
    ],
    "wof:name":"Pajian",
    "wof:placetype":"locality"
},
  "geometry": {"coordinates":[75.29389,31.26299],"type":"Point"}
}