{
  "type": "Feature",
  "properties": {
    "iso:country":"IN",
    "ks:ks_alt_nam":"PURA DABBU RAMAYAN PRASSAN",
    "ks:ks_name":"Pura Dabbu Ramayan Prassan",
    "ks:ks_pop":631,
    "ks:ks_type":"HABITATION",
    "ks:ks_uagg_main":0,
    "name:eng_x_preferred":[
        "Pura Dabbu Ramayan Prassan"
    ],
    "wof:name":"Pura Dabbu Ramayan Prassan",
    "wof:placetype":"neighbourhood",
    "wof:population":631
},
  "geometry": {"coordinates":[81.885017,25.063914],"type":"Point"}
}