{
  "type": "Feature",
  "properties": {
    "iso:country":"IN",
    "ks:ks_alt_nam":"Gobal faliya",
    "ks:ks_name":"Gobal Faliya",
    "ks:ks_pop":156,
    "ks:ks_type":"HABITATION",
    "name:eng_x_preferred":[
        "Gobal Faliya"
    ],
    "wof:name":"Gobal Faliya",
    "wof:placetype":"locality",
    "wof:population":156
},
  "geometry": {"coordinates":[73.229698,20.593108],"type":"Point"}
}