{
  "type": "Feature",
  "properties": {
    "iso:country":"IN",
    "ks:ks_name":"Bordubi",
    "ks:ks_pop":750,
    "ks:ks_type":"HABITATION",
    "ks:ks_uagg_main":0,
    "name:eng_x_preferred":[
        "Bordubi"
    ],
    "wof:name":"Bordubi",
    "wof:placetype":"neighbourhood",
    "wof:population":750
},
  "geometry": {"coordinates":[94.026804,26.317684],"type":"Point"}
}