{
  "type": "Feature",
  "properties": {
    "gn:admin1_code":"38",
    "gn:admin2_code":"346.0",
    "gn:asciiname":"Pato",
    "gn:country_code":"IN",
    "gn:dem":241,
    "gn:feature_class":"P",
    "gn:feature_code":"PPL",
    "gn:name":"P\u0101to",
    "gn:population":0,
    "gn:timezone":"Asia/Kolkata",
    "iso:country":"IN",
    "ks:ks_alt_nam":"P\u0101to",
    "ks:ks_name":"Pato",
    "ks:ks_type":"VILLAGE",
    "name:ara_x_preferred":[
        "\u0628\u0627\u062a\u0648"
    ],
    "name:cat_x_preferred":[
        "Pato"
    ],
    "name:deu_x_preferred":[
        "Pato"
    ],
    "name:eng_x_preferred":[
        "Pato"
    ],
    "name:eng_x_variant":[
        "P\u0101to"
    ],
    "name:fas_x_preferred":[
        "\u067e\u0627\u062a\u0648"
    ],
    "name:fin_x_preferred":[
        "Pato"
    ],
    "name:fra_x_preferred":[
        "Pato"
    ],
    "name:new_x_preferred":[
        "\u092a\u093e\u091f\u094b"
    ],
    "name:oci_x_preferred":[
        "Pato"
    ],
    "name:por_x_preferred":[
        "Pato"
    ],
    "name:spa_x_preferred":[
        "Pato"
    ],
    "name:swe_x_preferred":[
        "Pato"
    ],
    "wof:name":"Pato",
    "wof:placetype":"locality"
},
  "geometry": {"coordinates":[83.626833,24.327015],"type":"Point"}
}