{
  "type": "Feature",
  "properties": {
    "iso:country":"IN",
    "ks:ks_name":"Bhandarwadi",
    "ks:ks_pop":155,
    "ks:ks_type":"HABITATION",
    "name:eng_x_preferred":[
        "Bhandarwadi"
    ],
    "wof:name":"Bhandarwadi",
    "wof:placetype":"locality",
    "wof:population":155
},
  "geometry": {"coordinates":[73.40616900000001,16.617061],"type":"Point"}
}