{
  "type": "Feature",
  "properties": {
    "iso:country":"IN",
    "ks:ks_name":"Sonhata",
    "ks:ks_pop":1173,
    "ks:ks_type":"VILLAGE",
    "name:eng_x_preferred":[
        "Sonhata"
    ],
    "wof:name":"Sonhata",
    "wof:placetype":"locality",
    "wof:population":1173
},
  "geometry": {"coordinates":[82.948027,23.790802],"type":"Point"}
}