{
  "type": "Feature",
  "properties": {
    "iso:country":"IN",
    "ks:ks_name":"Bamsuguda",
    "ks:ks_pop":189,
    "ks:ks_type":"HABITATION",
    "name:eng_x_preferred":[
        "Bamsuguda"
    ],
    "wof:name":"Bamsuguda",
    "wof:placetype":"locality",
    "wof:population":189
},
  "geometry": {"coordinates":[82.866725,18.225701],"type":"Point"}
}