{
  "type": "Feature",
  "properties": {
    "iso:country":"IN",
    "ks:ks_name":"Adattari",
    "ks:ks_pop":170,
    "ks:ks_type":"VILLAGE",
    "name:eng_x_preferred":[
        "Adattari"
    ],
    "wof:name":"Adattari",
    "wof:placetype":"locality",
    "wof:population":170
},
  "geometry": {"coordinates":[91.344976,26.309908],"type":"Point"}
}