{
  "type": "Feature",
  "properties": {
    "iso:country":"IN",
    "ks:ks_name":"Chat Panisala",
    "ks:ks_pop":1386,
    "ks:ks_type":"HABITATION",
    "name:eng_x_preferred":[
        "Chat Panisala"
    ],
    "wof:name":"Chat Panisala",
    "wof:placetype":"locality",
    "wof:population":1386
},
  "geometry": {"coordinates":[89.54468300000001,26.251017],"type":"Point"}
}