{
  "type": "Feature",
  "properties": {
    "iso:country":"IN",
    "ks:ks_name":"Pari Palei",
    "ks:ks_pop":1359,
    "ks:ks_type":"VILLAGE",
    "ks:ks_uagg_main":0,
    "name:eng_x_preferred":[
        "Pari Palei"
    ],
    "wof:name":"Pari Palei",
    "wof:placetype":"neighbourhood",
    "wof:population":1359
},
  "geometry": {"coordinates":[86.286597,20.584296],"type":"Point"}
}