{
  "type": "Feature",
  "properties": {
    "iso:country":"IN",
    "ks:ks_name":"Udaipura",
    "ks:ks_pop":616,
    "ks:ks_type":"HABITATION",
    "name:eng_x_preferred":[
        "Udaipura"
    ],
    "wof:name":"Udaipura",
    "wof:placetype":"locality",
    "wof:population":616
},
  "geometry": {"coordinates":[76.363811,26.763231],"type":"Point"}
}