{
  "type": "Feature",
  "properties": {
    "iso:country":"IN",
    "ks:ks_name":"Gavanwadi",
    "ks:ks_pop":125,
    "ks:ks_type":"HABITATION",
    "name:eng_x_preferred":[
        "Gavanwadi"
    ],
    "wof:name":"Gavanwadi",
    "wof:placetype":"locality",
    "wof:population":125
},
  "geometry": {"coordinates":[73.25765,18.048911],"type":"Point"}
}