{
  "type": "Feature",
  "properties": {
    "gn:admin1_code":"39.0",
    "gn:admin2_code":"64.0",
    "gn:asciiname":"Pipalkot",
    "gn:country_code":"IN",
    "gn:dem":1275,
    "gn:feature_class":"P",
    "gn:feature_code":"PPL",
    "gn:name":"P\u012bpalkot",
    "gn:population":0,
    "gn:timezone":"Asia/Kolkata",
    "iso:country":"IN",
    "name:nep_x_preferred":[
        "\u092a\u093f\u092a\u0932\u0915\u094b\u091f"
    ],
    "name:pol_x_preferred":[
        "Pipalkot"
    ],
    "wof:name":"Pipalkot",
    "wof:placetype":"locality"
},
  "geometry": {"coordinates":[79.3107,29.68559],"type":"Point"}
}