{
  "type": "Feature",
  "properties": {
    "gn:admin1_code":"13.0",
    "gn:admin2_code":"600.0",
    "gn:asciiname":"Kadapa",
    "gn:country_code":"IN",
    "gn:dem":23,
    "gn:feature_class":"P",
    "gn:feature_code":"PPL",
    "gn:name":"Kadapa",
    "gn:population":0,
    "gn:timezone":"Asia/Kolkata",
    "iso:country":"IN",
    "name:ben_x_preferred":[
        "\u0995\u09be\u09a1\u09be\u09aa\u09be"
    ],
    "name:bih_x_preferred":[
        "\u0915\u0921\u092a\u093e"
    ],
    "name:bpy_x_preferred":[
        "\u099a\u09c1\u09a6\u09cd\u09a6\u09be\u09aa\u09be"
    ],
    "name:cat_x_preferred":[
        "Kadapa"
    ],
    "name:ceb_x_preferred":[
        "Cuddapah"
    ],
    "name:deu_x_preferred":[
        "Kadapa"
    ],
    "name:fas_x_preferred":[
        "\u06a9\u0627\u062f\u0627\u067e\u0627"
    ],
    "name:fin_x_preferred":[
        "Kadapa"
    ],
    "name:fra_x_preferred":[
        "Kadapa"
    ],
    "name:guj_x_preferred":[
        "\u0a95\u0aa1\u0aaa\u0acd\u0aaa\u0abe"
    ],
    "name:hin_x_preferred":[
        "\u0915\u0921\u092a\u093e"
    ],
    "name:ita_x_preferred":[
        "Kadapa"
    ],
    "name:jpn_x_preferred":[
        "\u30ab\u30c0\u30d1"
    ],
    "name:kan_x_preferred":[
        "\u0c95\u0ca1\u0caa"
    ],
    "name:mar_x_preferred":[
        "\u0915\u0921\u092a\u094d\u092a\u093e"
    ],
    "name:mlg_x_preferred":[
        "Kadapa"
    ],
    "name:msa_x_preferred":[
        "Cuddapah"
    ],
    "name:nep_x_preferred":[
        "\u0915\u0941\u0921\u092a\u094d\u092a\u093e"
    ],
    "name:new_x_preferred":[
        "\u0915\u0921\u092a"
    ],
    "name:ori_x_preferred":[
        "\u0b15\u0b21\u0b2a\u0b4d\u0b2a\u0b3e"
    ],
    "name:pam_x_preferred":[
        "Kadapa"
    ],
    "name:pol_x_preferred":[
        "Kadapa"
    ],
    "name:por_x_preferred":[
        "Kadapa"
    ],
    "name:rus_x_preferred":[
        "\u041a\u0430\u0434\u0430\u043f\u0430"
    ],
    "name:san_x_preferred":[
        "\u0915\u0921\u092a\u093e-\u0928\u0917\u0930\u092e\u094d"
    ],
    "name:spa_x_preferred":[
        "Kadapa"
    ],
    "name:srp_x_preferred":[
        "\u041a\u0430\u0434\u0430\u043f\u0430"
    ],
    "name:swe_x_preferred":[
        "Kadapa"
    ],
    "name:tam_x_preferred":[
        "\u0b95\u0b9f\u0baa\u0bcd\u0baa\u0bbe"
    ],
    "name:tel_x_preferred":[
        "\u0c15\u0c21\u0c2a"
    ],
    "name:tgl_x_preferred":[
        "Kadapa"
    ],
    "name:ukr_x_preferred":[
        "\u041a\u0430\u0434\u0430\u043f\u0430"
    ],
    "name:urd_x_preferred":[
        "\u06a9\u0688\u067e\u06c1"
    ],
    "name:vie_x_preferred":[
        "Kadapa"
    ],
    "name:war_x_preferred":[
        "Kadapa"
    ],
    "name:zho_x_preferred":[
        "\u4e18\u5fb7\u8fbe\u5e15"
    ],
    "wof:name":"Kadapa",
    "wof:placetype":"locality"
},
  "geometry": {"coordinates":[76.58427,9.04247],"type":"Point"}
}