{
  "type": "Feature",
  "properties": {
    "iso:country":"IN",
    "ks:ks_name":"Wakanwasti",
    "ks:ks_pop":444,
    "ks:ks_type":"HABITATION",
    "name:eng_x_preferred":[
        "Wakanwasti"
    ],
    "wof:name":"Wakanwasti",
    "wof:placetype":"locality",
    "wof:population":444
},
  "geometry": {"coordinates":[74.26331999999999,19.563232],"type":"Point"}
}