{
  "type": "Feature",
  "properties": {
    "iso:country":"IN",
    "ks:ks_alt_nam":"Naw\u0101dih",
    "ks:ks_name":"Nawadih",
    "ks:ks_type":"VILLAGE",
    "ks:ks_uagg_main":0,
    "name:eng_x_preferred":[
        "Nawadih"
    ],
    "name:eng_x_variant":[
        "Naw\u0101dih"
    ],
    "wof:name":"Nawadih",
    "wof:placetype":"neighbourhood"
},
  "geometry": {"coordinates":[86.310965,24.727585],"type":"Point"}
}