{
  "type": "Feature",
  "properties": {
    "iso:country":"IN",
    "ks:ks_name":"Gadeibar",
    "ks:ks_pop":44,
    "ks:ks_type":"VILLAGE",
    "name:eng_x_preferred":[
        "Gadeibar"
    ],
    "wof:name":"Gadeibar",
    "wof:placetype":"locality",
    "wof:population":44
},
  "geometry": {"coordinates":[87.390535,21.76233],"type":"Point"}
}