{
  "type": "Feature",
  "properties": {
    "gn:admin1_code":"39",
    "gn:admin2_code":"60.0",
    "gn:asciiname":"Garhi",
    "gn:country_code":"IN",
    "gn:dem":352,
    "gn:feature_class":"P",
    "gn:feature_code":"PPL",
    "gn:name":"Garh\u012b",
    "gn:population":0,
    "gn:timezone":"Asia/Kolkata",
    "iso:country":"IN",
    "name:cat_x_preferred":[
        "Garhi"
    ],
    "wof:name":"Garhi",
    "wof:placetype":"locality"
},
  "geometry": {"coordinates":[78.21986,30.06863],"type":"Point"}
}