{
  "type": "Feature",
  "properties": {
    "iso:country":"IN",
    "ks:ks_name":"Mohambariyankuppam",
    "ks:ks_pop":319,
    "ks:ks_type":"HABITATION",
    "name:eng_x_preferred":[
        "Mohambariyankuppam"
    ],
    "wof:name":"Mohambariyankuppam",
    "wof:placetype":"locality",
    "wof:population":319
},
  "geometry": {"coordinates":[79.39246199999999,11.646693],"type":"Point"}
}