{
  "type": "Feature",
  "properties": {
    "iso:country":"IN",
    "ks:ks_name":"Pokhari",
    "ks:ks_pop":120,
    "ks:ks_type":"VILLAGE",
    "name:eng_x_preferred":[
        "Pokhari"
    ],
    "wof:name":"Pokhari",
    "wof:placetype":"locality",
    "wof:population":120
},
  "geometry": {"coordinates":[78.814284,29.865757],"type":"Point"}
}