{
  "type": "Feature",
  "properties": {
    "gn:admin1_code":"16",
    "gn:admin2_code":"510.0",
    "gn:asciiname":"Wasari",
    "gn:country_code":"IN",
    "gn:dem":249,
    "gn:feature_class":"P",
    "gn:feature_code":"PPL",
    "gn:name":"W\u0101sari",
    "gn:population":0,
    "gn:timezone":"Asia/Kolkata",
    "iso:country":"IN",
    "ks:ks_alt_nam":"W\u0101sari",
    "ks:ks_name":"Wasari",
    "ks:ks_type":"VILLAGE",
    "name:eng_x_preferred":[
        "Wasari"
    ],
    "name:eng_x_variant":[
        "W\u0101sari"
    ],
    "wof:name":"Wasari",
    "wof:placetype":"locality"
},
  "geometry": {"coordinates":[78.55224800000001,19.864896],"type":"Point"}
}