{
  "type": "Feature",
  "properties": {
    "gn:admin1_code":"16",
    "gn:admin2_code":"510.0",
    "gn:asciiname":"Wasari",
    "gn:country_code":"IN",
    "gn:dem":249,
    "gn:feature_class":"P",
    "gn:feature_code":"PPL",
    "gn:name":"W\u0101sari",
    "gn:population":0,
    "gn:timezone":"Asia/Kolkata",
    "iso:country":"IN",
    "wof:name":"Wasari",
    "wof:placetype":"locality"
},
  "geometry": {"coordinates":[78.55225,19.8649],"type":"Point"}
}