{
  "type": "Feature",
  "properties": {
    "iso:country":"IN",
    "ks:ks_name":"Sukanpukhuri",
    "ks:ks_pop":838,
    "ks:ks_type":"VILLAGE",
    "ks:ks_uagg_main":0,
    "name:eng_x_preferred":[
        "Sukanpukhuri"
    ],
    "wof:name":"Sukanpukhuri",
    "wof:placetype":"neighbourhood",
    "wof:population":838
},
  "geometry": {"coordinates":[94.745678,27.15446],"type":"Point"}
}