{
  "type": "Feature",
  "properties": {
    "iso:country":"IN",
    "ks:ks_alt_nam":"AHRAULI JAGIR",
    "ks:ks_name":"Ahrauli Jagir",
    "ks:ks_pop":1016,
    "ks:ks_type":"HABITATION",
    "name:eng_x_preferred":[
        "Ahrauli Jagir"
    ],
    "wof:name":"Ahrauli Jagir",
    "wof:placetype":"locality",
    "wof:population":1016
},
  "geometry": {"coordinates":[84.142416,25.935789],"type":"Point"}
}