{
  "type": "Feature",
  "properties": {
    "iso:country":"IN",
    "ks:ks_name":"Central School",
    "ks:ks_pop":116,
    "ks:ks_type":"HABITATION",
    "ks:ks_uagg_main":0,
    "name:eng_x_preferred":[
        "Central School"
    ],
    "wof:name":"Central School",
    "wof:placetype":"neighbourhood",
    "wof:population":116
},
  "geometry": {"coordinates":[78.361377,13.723147],"type":"Point"}
}