{
  "type": "Feature",
  "properties": {
    "iso:country":"IN",
    "ks:ks_name":"Hirau Ka Purwa",
    "ks:ks_pop":105,
    "ks:ks_type":"HABITATION",
    "ks:ks_uagg_main":0,
    "name:eng_x_preferred":[
        "Hirau Ka Purwa"
    ],
    "wof:name":"Hirau Ka Purwa",
    "wof:placetype":"neighbourhood",
    "wof:population":105
},
  "geometry": {"coordinates":[82.09363,26.571049],"type":"Point"}
}