{
  "type": "Feature",
  "properties": {
    "iso:country":"IN",
    "ks:ks_name":"Dewoolwadi",
    "ks:ks_pop":179,
    "ks:ks_type":"HABITATION",
    "name:eng_x_preferred":[
        "Dewoolwadi"
    ],
    "wof:name":"Dewoolwadi",
    "wof:placetype":"locality",
    "wof:population":179
},
  "geometry": {"coordinates":[73.72369399999999,15.87478],"type":"Point"}
}