{
  "type": "Feature",
  "properties": {
    "iso:country":"IN",
    "ks:ks_alt_nam":"MATIA BIL",
    "ks:ks_name":"Matia Bil",
    "ks:ks_pop":45,
    "ks:ks_type":"HABITATION",
    "name:eng_x_preferred":[
        "Matia Bil"
    ],
    "wof:name":"Matia Bil",
    "wof:placetype":"locality",
    "wof:population":45
},
  "geometry": {"coordinates":[91.507651,24.079955],"type":"Point"}
}