{
  "type": "Feature",
  "properties": {
    "iso:country":"IN",
    "ks:ks_alt_nam":"baredpada",
    "ks:ks_name":"Baredpada",
    "ks:ks_pop":139,
    "ks:ks_type":"HABITATION",
    "name:eng_x_preferred":[
        "Baredpada"
    ],
    "wof:name":"Baredpada",
    "wof:placetype":"locality",
    "wof:population":139
},
  "geometry": {"coordinates":[72.873098,19.707123],"type":"Point"}
}