{
  "type": "Feature",
  "properties": {
    "iso:country":"IN",
    "ks:ks_name":"Gura Hema",
    "ks:ks_pop":2849,
    "ks:ks_type":"VILLAGE",
    "name:eng_x_preferred":[
        "Gura Hema"
    ],
    "wof:name":"Gura Hema",
    "wof:placetype":"locality",
    "wof:population":2849
},
  "geometry": {"coordinates":[71.753946,25.040666],"type":"Point"}
}