{
  "type": "Feature",
  "properties": {
    "gn:admin1_code":"2.0",
    "gn:admin2_code":"551.0",
    "gn:asciiname":"Gunthamvaripalli",
    "gn:country_code":"IN",
    "gn:dem":182,
    "gn:feature_class":"P",
    "gn:feature_code":"PPL",
    "gn:name":"Gunthamv\u0101ripalli",
    "gn:population":0,
    "gn:timezone":"Asia/Kolkata",
    "iso:country":"IN",
    "ks:ks_name":"Gandamvaripalli",
    "ks:ks_pop":12,
    "ks:ks_type":"HABITATION",
    "name:eng_x_preferred":[
        "Gandamvaripalli"
    ],
    "name:eng_x_variant":[
        "Gunthamvaripalli"
    ],
    "wof:name":"Gandamvaripalli",
    "wof:placetype":"locality",
    "wof:population":12
},
  "geometry": {"coordinates":[79.150374,14.087898],"type":"Point"}
}