{
  "type": "Feature",
  "properties": {
    "gn:admin1_code":"35.0",
    "gn:admin2_code":"450.0",
    "gn:asciiname":"Deori Kalan",
    "gn:country_code":"IN",
    "gn:dem":399,
    "gn:feature_class":"P",
    "gn:feature_code":"PPL",
    "gn:name":"Deori Kal\u0101n",
    "gn:population":0,
    "gn:timezone":"Asia/Kolkata",
    "iso:country":"IN",
    "wof:name":"Deori Kalan",
    "wof:placetype":"neighbourhood"
},
  "geometry": {"coordinates":[80.33317,23.76026],"type":"Point"}
}