{
  "type": "Feature",
  "properties": {
    "iso:country":"IN",
    "ks:ks_name":"Maduthittuveli",
    "ks:ks_pop":120,
    "ks:ks_type":"HABITATION",
    "name:eng_x_preferred":[
        "Maduthittuveli"
    ],
    "wof:name":"Maduthittuveli",
    "wof:placetype":"locality",
    "wof:population":120
},
  "geometry": {"coordinates":[79.66018099999999,11.412247],"type":"Point"}
}