{
  "type": "Feature",
  "properties": {
    "iso:country":"IN",
    "ks:ks_name":"Keredande",
    "ks:ks_pop":27,
    "ks:ks_type":"HABITATION",
    "name:eng_x_preferred":[
        "Keredande"
    ],
    "wof:name":"Keredande",
    "wof:placetype":"locality",
    "wof:population":27
},
  "geometry": {"coordinates":[75.182283,13.420367],"type":"Point"}
}