{
  "type": "Feature",
  "properties": {
    "gn:admin1_code":"11.0",
    "gn:admin2_code":"26.0",
    "gn:asciiname":"Bari Lanj",
    "gn:country_code":"IN",
    "gn:dem":1418,
    "gn:feature_class":"P",
    "gn:feature_code":"PPL",
    "gn:name":"Bari L\u0101nj",
    "gn:population":0,
    "gn:timezone":"Asia/Kolkata",
    "iso:country":"IN",
    "wof:name":"Bari Lanj",
    "wof:placetype":"locality"
},
  "geometry": {"coordinates":[77.53438,31.4639],"type":"Point"}
}