{
  "type": "Feature",
  "properties": {
    "iso:country":"IN",
    "ks:ks_name":"Kurubandha",
    "ks:ks_pop":20,
    "ks:ks_type":"VILLAGE",
    "name:eng_x_preferred":[
        "Kurubandha"
    ],
    "wof:name":"Kurubandha",
    "wof:placetype":"locality",
    "wof:population":20
},
  "geometry": {"coordinates":[83.857544,19.52803],"type":"Point"}
}