{
  "type": "Feature",
  "properties": {
    "gn:admin1_code":"35",
    "gn:admin2_code":"421.0",
    "gn:asciiname":"Renhat",
    "gn:country_code":"IN",
    "gn:dem":353,
    "gn:feature_class":"P",
    "gn:feature_code":"PPL",
    "gn:name":"Renhat",
    "gn:population":0,
    "gn:timezone":"Asia/Kolkata",
    "iso:country":"IN",
    "ks:ks_name":"Renhat",
    "ks:ks_pop":1643,
    "ks:ks_type":"VILLAGE",
    "name:eng_x_preferred":[
        "Renhat"
    ],
    "wof:name":"Renhat",
    "wof:placetype":"locality",
    "wof:population":1643
},
  "geometry": {"coordinates":[77.83629000000001,25.987281],"type":"Point"}
}