{
  "type": "Feature",
  "properties": {
    "iso:country":"IN",
    "ks:ks_name":"Dhombarambedu",
    "ks:ks_pop":300,
    "ks:ks_type":"HABITATION",
    "name:eng_x_preferred":[
        "Dhombarambedu"
    ],
    "wof:name":"Dhombarambedu",
    "wof:placetype":"locality",
    "wof:population":300
},
  "geometry": {"coordinates":[79.91557299999999,13.331456],"type":"Point"}
}