{
  "type": "Feature",
  "properties": {
    "gn:admin1_code":"24",
    "gn:admin2_code":"127.0",
    "gn:asciiname":"Amritkuwa",
    "gn:country_code":"IN",
    "gn:dem":272,
    "gn:feature_class":"P",
    "gn:feature_code":"PPL",
    "gn:name":"Amritkuwa",
    "gn:population":0,
    "gn:timezone":"Asia/Kolkata",
    "iso:country":"IN",
    "wof:name":"Amritkuwa",
    "wof:placetype":"locality"
},
  "geometry": {"coordinates":[76.27838,24.8474],"type":"Point"}
}