{
  "type": "Feature",
  "properties": {
    "gn:admin1_code":"9.0",
    "gn:admin2_code":"484.0",
    "gn:asciiname":"Rangeli",
    "gn:country_code":"IN",
    "gn:dem":108,
    "gn:feature_class":"P",
    "gn:feature_code":"PPL",
    "gn:name":"Rangeli",
    "gn:population":0,
    "gn:timezone":"Asia/Kolkata",
    "iso:country":"IN",
    "name:deu_x_preferred":[
        "Rangeli"
    ],
    "name:hin_x_preferred":[
        "\u0930\u0902\u0917\u0947\u0932\u0940"
    ],
    "name:mai_x_preferred":[
        "\u0930\u0902\u0917\u0947\u0932\u0940 \u0928\u0917\u0930\u092a\u093e\u0932\u093f\u0915\u093e"
    ],
    "name:msa_x_preferred":[
        "Rangeli"
    ],
    "name:nep_x_preferred":[
        "\u0930\u0902\u0917\u0947\u0932\u0940 \u0928\u0917\u0930\u092a\u093e\u0932\u093f\u0915\u093e"
    ],
    "name:new_x_preferred":[
        "\u0930\u0902\u0917\u0947\u0932\u0940"
    ],
    "wof:name":"Rangeli",
    "wof:placetype":"locality"
},
  "geometry": {"coordinates":[73.6484,23.27851],"type":"Point"}
}