{
  "type": "Feature",
  "properties": {
    "gn:admin1_code":"36.0",
    "gn:admin2_code":"152.0",
    "gn:asciiname":"Gahra",
    "gn:country_code":"IN",
    "gn:dem":160,
    "gn:feature_class":"P",
    "gn:feature_code":"PPL",
    "gn:name":"Gahra",
    "gn:population":0,
    "gn:timezone":"Asia/Kolkata",
    "iso:country":"IN",
    "wof:name":"Gahra",
    "wof:placetype":"locality"
},
  "geometry": {"coordinates":[80.02858000000001,27.93846],"type":"Point"}
}