{
  "type": "Feature",
  "properties": {
    "iso:country":"IN",
    "ks:ks_name":"Kaliyampuzha",
    "ks:ks_pop":626,
    "ks:ks_type":"HABITATION",
    "name:eng_x_preferred":[
        "Kaliyampuzha"
    ],
    "wof:name":"Kaliyampuzha",
    "wof:placetype":"locality",
    "wof:population":626
},
  "geometry": {"coordinates":[76.032319,11.393266],"type":"Point"}
}