{
  "type": "Feature",
  "properties": {
    "gn:admin1_code":"2.0",
    "gn:admin2_code":"544.0",
    "gn:asciiname":"Chinna Sariyapalle",
    "gn:country_code":"IN",
    "gn:dem":865,
    "gn:feature_class":"P",
    "gn:feature_code":"PPL",
    "gn:name":"Chinna Sariyapalle",
    "gn:population":0,
    "gn:timezone":"Asia/Kolkata",
    "iso:country":"IN",
    "ks:ks_name":"Chinasariyapalli",
    "ks:ks_pop":38,
    "ks:ks_type":"HABITATION",
    "name:eng_x_preferred":[
        "Chinasariyapalli"
    ],
    "name:eng_x_variant":[
        "Chinna Sariyapalle"
    ],
    "wof:name":"Chinasariyapalli",
    "wof:placetype":"locality",
    "wof:population":38
},
  "geometry": {"coordinates":[82.44102700000001,18.28114],"type":"Point"}
}