{
  "type": "Feature",
  "properties": {
    "iso:country":"IN",
    "ks:ks_name":"Wadishidyal",
    "ks:ks_pop":550,
    "ks:ks_type":"HABITATION",
    "name:eng_x_preferred":[
        "Wadishidyal"
    ],
    "wof:name":"Wadishidyal",
    "wof:placetype":"locality",
    "wof:population":550
},
  "geometry": {"coordinates":[74.463245,16.069027],"type":"Point"}
}