{
  "type": "Feature",
  "properties": {
    "gn:admin1_code":"12.0",
    "gn:admin2_code":"6.0",
    "gn:asciiname":"Motal",
    "gn:country_code":"IN",
    "gn:dem":1640,
    "gn:feature_class":"P",
    "gn:feature_code":"PPL",
    "gn:name":"Motal",
    "gn:population":0,
    "gn:timezone":"Asia/Kolkata",
    "iso:country":"IN",
    "wof:name":"Motal",
    "wof:placetype":"locality"
},
  "geometry": {"coordinates":[74.64497,33.25272],"type":"Point"}
}