{
  "type": "Feature",
  "properties": {
    "gn:admin1_code":"12.0",
    "gn:admin2_code":"6.0",
    "gn:asciiname":"Motal",
    "gn:country_code":"IN",
    "gn:dem":1640,
    "gn:feature_class":"P",
    "gn:feature_code":"PPL",
    "gn:name":"Motal",
    "gn:population":0,
    "gn:timezone":"Asia/Kolkata",
    "iso:country":"IN",
    "name:afr_x_preferred":[
        "Motal"
    ],
    "name:ang_x_preferred":[
        "Motol"
    ],
    "name:bel_x_preferred":[
        "\u041c\u043e\u0442\u0430\u043b\u044c"
    ],
    "name:ces_x_preferred":[
        "Motal"
    ],
    "name:deu_x_preferred":[
        "Motal"
    ],
    "name:epo_x_preferred":[
        "Motal"
    ],
    "name:est_x_preferred":[
        "Motal"
    ],
    "name:fra_x_preferred":[
        "Motal"
    ],
    "name:fry_x_preferred":[
        "Motol"
    ],
    "name:heb_x_preferred":[
        "\u05de\u05d5\u05d8\u05dc\u05d4"
    ],
    "name:ita_x_preferred":[
        "Motal"
    ],
    "name:jpn_x_preferred":[
        "\u30e2\u30bf\u30ea"
    ],
    "name:lav_x_preferred":[
        "Mota\u013ca"
    ],
    "name:nld_x_preferred":[
        "Motal"
    ],
    "name:pol_x_preferred":[
        "Motol"
    ],
    "name:rue_x_preferred":[
        "\u041c\u043e\u0442\u043e\u043b\u044c"
    ],
    "name:rus_x_preferred":[
        "\u041c\u043e\u0442\u043e\u043b\u044c"
    ],
    "name:ukr_x_preferred":[
        "\u041c\u043e\u0442\u043e\u043b\u044c"
    ],
    "name:zho_x_preferred":[
        "\u83ab\u6258\u5229"
    ],
    "wof:name":"Motal",
    "wof:placetype":"locality"
},
  "geometry": {"coordinates":[74.64497,33.25272],"type":"Point"}
}