{
  "type": "Feature",
  "properties": {
    "iso:country":"IN",
    "ks:ks_name":"Kharchimari",
    "ks:ks_pop":653,
    "ks:ks_type":"VILLAGE",
    "name:eng_x_preferred":[
        "Kharchimari"
    ],
    "wof:name":"Kharchimari",
    "wof:placetype":"locality",
    "wof:population":653
},
  "geometry": {"coordinates":[90.422645,26.221587],"type":"Point"}
}