{
  "type": "Feature",
  "properties": {
    "iso:country":"IN",
    "ks:ks_name":"Bheemanahally",
    "ks:ks_pop":863,
    "ks:ks_type":"HABITATION",
    "name:eng_x_preferred":[
        "Bheemanahally"
    ],
    "wof:name":"Bheemanahally",
    "wof:placetype":"locality",
    "wof:population":863
},
  "geometry": {"coordinates":[77.267951,12.459673],"type":"Point"}
}