{
  "type": "Feature",
  "properties": {
    "iso:country":"IN",
    "ks:ks_name":"Ganjhutoli",
    "ks:ks_pop":107,
    "ks:ks_type":"HABITATION",
    "name:eng_x_preferred":[
        "Ganjhutoli"
    ],
    "wof:name":"Ganjhutoli",
    "wof:placetype":"locality",
    "wof:population":107
},
  "geometry": {"coordinates":[84.795762,22.573458],"type":"Point"}
}