{
  "type": "Feature",
  "properties": {
    "iso:country":"IN",
    "ks:ks_name":"Pahadpur",
    "ks:ks_pop":49,
    "ks:ks_type":"VILLAGE",
    "name:eng_x_preferred":[
        "Pahadpur"
    ],
    "wof:name":"Pahadpur",
    "wof:placetype":"locality",
    "wof:population":49
},
  "geometry": {"coordinates":[86.023523,22.008249],"type":"Point"}
}