{
  "type": "Feature",
  "properties": {
    "iso:country":"IN",
    "ks:ks_name":"Bechalli",
    "ks:ks_pop":180,
    "ks:ks_type":"HABITATION",
    "name:eng_x_preferred":[
        "Bechalli"
    ],
    "wof:name":"Bechalli",
    "wof:placetype":"locality",
    "wof:population":180
},
  "geometry": {"coordinates":[74.937095,13.660584],"type":"Point"}
}