{
  "type": "Feature",
  "properties": {
    "iso:country":"IN",
    "ks:ks_name":"Patehara",
    "ks:ks_pop":1252,
    "ks:ks_type":"HABITATION",
    "name:eng_x_preferred":[
        "Patehara"
    ],
    "wof:name":"Patehara",
    "wof:placetype":"locality",
    "wof:population":1252
},
  "geometry": {"coordinates":[80.726135,24.240269],"type":"Point"}
}