{
  "type": "Feature",
  "properties": {
    "iso:country":"IN",
    "ks:ks_name":"Jurpania",
    "ks:ks_pop":528,
    "ks:ks_type":"HABITATION",
    "name:eng_x_preferred":[
        "Jurpania"
    ],
    "wof:name":"Jurpania",
    "wof:placetype":"locality",
    "wof:population":528
},
  "geometry": {"coordinates":[86.450785,24.70369],"type":"Point"}
}