{
  "type": "Feature",
  "properties": {
    "gn:admin1_code":"19.0",
    "gn:admin2_code":"566.0",
    "gn:asciiname":"Huchchavvanahalli",
    "gn:country_code":"IN",
    "gn:dem":616,
    "gn:feature_class":"P",
    "gn:feature_code":"PPL",
    "gn:name":"Huchchavvanahalli",
    "gn:population":0,
    "gn:timezone":"Asia/Kolkata",
    "iso:country":"IN",
    "wof:name":"Huchchavvanahalli",
    "wof:placetype":"locality"
},
  "geometry": {"coordinates":[76.58790999999999,13.96695],"type":"Point"}
}