{
  "type": "Feature",
  "properties": {
    "gn:admin1_code":"19.0",
    "gn:admin2_code":"566.0",
    "gn:asciiname":"Huchchavvanahalli",
    "gn:country_code":"IN",
    "gn:dem":616,
    "gn:feature_class":"P",
    "gn:feature_code":"PPL",
    "gn:name":"Huchchavvanahalli",
    "gn:population":0,
    "gn:timezone":"Asia/Kolkata",
    "iso:country":"IN",
    "ks:ks_name":"Huchavvanahalli",
    "ks:ks_pop":1304,
    "ks:ks_type":"VILLAGE",
    "name:eng_x_preferred":[
        "Huchavvanahalli"
    ],
    "name:eng_x_variant":[
        "Huchchavvanahalli"
    ],
    "wof:name":"Huchavvanahalli",
    "wof:placetype":"locality",
    "wof:population":1304
},
  "geometry": {"coordinates":[76.58147599999999,13.964828],"type":"Point"}
}