{
  "type": "Feature",
  "properties": {
    "iso:country":"IN",
    "ks:ks_name":"Girijatoli",
    "ks:ks_pop":150,
    "ks:ks_type":"HABITATION",
    "name:eng_x_preferred":[
        "Girijatoli"
    ],
    "wof:name":"Girijatoli",
    "wof:placetype":"locality",
    "wof:population":150
},
  "geometry": {"coordinates":[84.523297,22.184528],"type":"Point"}
}