{
  "type": "Feature",
  "properties": {
    "iso:country":"IN",
    "ks:ks_name":"Shidoli",
    "ks:ks_pop":81,
    "ks:ks_type":"HABITATION",
    "name:eng_x_preferred":[
        "Shidoli"
    ],
    "wof:name":"Shidoli",
    "wof:placetype":"locality",
    "wof:population":81
},
  "geometry": {"coordinates":[74.47249100000001,15.076388],"type":"Point"}
}