{
  "type": "Feature",
  "properties": {
    "iso:country":"IN",
    "ks:ks_alt_nam":"11 KND-A",
    "ks:ks_name":"11 Knd-a",
    "ks:ks_pop":198,
    "ks:ks_type":"HABITATION",
    "name:eng_x_preferred":[
        "11 Knd-a"
    ],
    "wof:name":"11 Knd-a",
    "wof:placetype":"locality",
    "wof:population":198
},
  "geometry": {"coordinates":[72.740731,28.872008],"type":"Point"}
}