{
  "type": "Feature",
  "properties": {
    "iso:country":"IN",
    "ks:ks_name":"Purwa Chandraman",
    "ks:ks_pop":385,
    "ks:ks_type":"VILLAGE",
    "ks:ks_uagg_main":0,
    "name:eng_x_preferred":[
        "Purwa Chandraman"
    ],
    "wof:name":"Purwa Chandraman",
    "wof:placetype":"neighbourhood",
    "wof:population":385
},
  "geometry": {"coordinates":[79.34158600000001,26.695956],"type":"Point"}
}