{
  "type": "Feature",
  "properties": {
    "iso:country":"IN",
    "ks:ks_name":"Palpara",
    "ks:ks_pop":49,
    "ks:ks_type":"HABITATION",
    "name:eng_x_preferred":[
        "Palpara"
    ],
    "wof:name":"Palpara",
    "wof:placetype":"locality",
    "wof:population":49
},
  "geometry": {"coordinates":[82.36569799999999,22.733317],"type":"Point"}
}