{
  "type": "Feature",
  "properties": {
    "iso:country":"IN",
    "ks:ks_alt_nam":"Katarupalli cross",
    "ks:ks_name":"Katarupalli Cross",
    "ks:ks_pop":258,
    "ks:ks_type":"HABITATION",
    "name:eng_x_preferred":[
        "Katarupalli Cross"
    ],
    "wof:name":"Katarupalli Cross",
    "wof:placetype":"locality",
    "wof:population":258
},
  "geometry": {"coordinates":[78.239392,14.100387],"type":"Point"}
}