{
  "type": "Feature",
  "properties": {
    "iso:country":"IN",
    "ks:ks_name":"Salaiya Pandupur Mal.",
    "ks:ks_pop":484,
    "ks:ks_type":"VILLAGE",
    "name:eng_x_preferred":[
        "Salaiya Pandupur Mal."
    ],
    "wof:name":"Salaiya Pandupur Mal.",
    "wof:placetype":"locality",
    "wof:population":484
},
  "geometry": {"coordinates":[81.124976,22.674811],"type":"Point"}
}