{
  "type": "Feature",
  "properties": {
    "iso:country":"IN",
    "ks:ks_name":"Hinchiban",
    "ks:ks_pop":394,
    "ks:ks_type":"HABITATION",
    "name:eng_x_preferred":[
        "Hinchiban"
    ],
    "wof:name":"Hinchiban",
    "wof:placetype":"locality",
    "wof:population":394
},
  "geometry": {"coordinates":[87.627932,21.939314],"type":"Point"}
}