{
  "type": "Feature",
  "properties": {
    "gn:admin1_code":"36",
    "gn:admin2_code":"197.0",
    "gn:asciiname":"Mirza Murad",
    "gn:country_code":"IN",
    "gn:dem":89,
    "gn:feature_class":"P",
    "gn:feature_code":"PPL",
    "gn:name":"Mirza Mur\u0101d",
    "gn:population":0,
    "gn:timezone":"Asia/Kolkata",
    "iso:country":"IN",
    "name:und_x_variant":[
        "Gaur",
        "Mirza Mur\u0101d"
    ],
    "wof:name":"Mirza Murad",
    "wof:placetype":"locality"
},
  "geometry": {"coordinates":[82.77679999999999,25.2865],"type":"Point"}
}