{
  "type": "Feature",
  "properties": {
    "iso:country":"IN",
    "ks:ks_name":"Gajraulla Jabti",
    "ks:ks_pop":397,
    "ks:ks_type":"VILLAGE",
    "ks:ks_uagg_main":0,
    "name:eng_x_preferred":[
        "Gajraulla Jabti"
    ],
    "wof:name":"Gajraulla Jabti",
    "wof:placetype":"neighbourhood",
    "wof:population":397
},
  "geometry": {"coordinates":[80.10497100000001,28.474064],"type":"Point"}
}