{
  "type": "Feature",
  "properties": {
    "iso:country":"IN",
    "ks:ks_name":"Khaspara 4 Ghotiya",
    "ks:ks_pop":578,
    "ks:ks_type":"HABITATION",
    "ks:ks_uagg_main":0,
    "name:eng_x_preferred":[
        "Khaspara 4 Ghotiya"
    ],
    "wof:name":"Khaspara 4 Ghotiya",
    "wof:placetype":"neighbourhood",
    "wof:population":578
},
  "geometry": {"coordinates":[81.75735899999999,19.222265],"type":"Point"}
}