{
  "type": "Feature",
  "properties": {
    "iso:country":"IN",
    "ks:ks_name":"Pure Budhana",
    "ks:ks_pop":280,
    "ks:ks_type":"HABITATION",
    "name:eng_x_preferred":[
        "Pure Budhana"
    ],
    "wof:name":"Pure Budhana",
    "wof:placetype":"locality",
    "wof:population":280
},
  "geometry": {"coordinates":[81.551303,26.408636],"type":"Point"}
}