{
  "type": "Feature",
  "properties": {
    "gn:admin1_code":"23.0",
    "gn:admin2_code":"35.0",
    "gn:asciiname":"Said Mubarik",
    "gn:country_code":"IN",
    "gn:dem":242,
    "gn:feature_class":"P",
    "gn:feature_code":"PPL",
    "gn:name":"Said Mub\u0101rik",
    "gn:population":0,
    "gn:timezone":"Asia/Kolkata",
    "iso:country":"IN",
    "ks:ks_alt_nam":"Said Mub\u0101rik",
    "ks:ks_name":"Said Mubarik",
    "ks:ks_pop":799,
    "ks:ks_type":"VILLAGE",
    "name:eng_x_preferred":[
        "Said Mubarik"
    ],
    "name:eng_x_variant":[
        "Said Mub\u0101rik"
    ],
    "wof:name":"Said Mubarik",
    "wof:placetype":"locality",
    "wof:population":799
},
  "geometry": {"coordinates":[75.16076099999999,31.805851],"type":"Point"}
}