{
  "type": "Feature",
  "properties": {
    "gn:admin1_code":"23.0",
    "gn:admin2_code":"35.0",
    "gn:asciiname":"Said Mubarik",
    "gn:country_code":"IN",
    "gn:dem":242,
    "gn:feature_class":"P",
    "gn:feature_code":"PPL",
    "gn:name":"Said Mub\u0101rik",
    "gn:population":0,
    "gn:timezone":"Asia/Kolkata",
    "iso:country":"IN",
    "wof:name":"Said Mubarik",
    "wof:placetype":"locality"
},
  "geometry": {"coordinates":[75.16076,31.80585],"type":"Point"}
}