{
  "type": "Feature",
  "properties": {
    "iso:country":"IN",
    "ks:ks_name":"Basahi",
    "ks:ks_type":"VILLAGE",
    "ks:ks_uagg_main":0,
    "name:eng_x_preferred":[
        "Basahi"
    ],
    "wof:name":"Basahi",
    "wof:placetype":"neighbourhood"
},
  "geometry": {"coordinates":[82.533728,25.145999],"type":"Point"}
}