{
  "type": "Feature",
  "properties": {
    "gn:admin1_code":"24.0",
    "gn:admin2_code":"120.0",
    "gn:asciiname":"Jagsura",
    "gn:country_code":"IN",
    "gn:dem":282,
    "gn:feature_class":"P",
    "gn:feature_code":"PPL",
    "gn:name":"Jagsura",
    "gn:population":0,
    "gn:timezone":"Asia/Kolkata",
    "iso:country":"IN",
    "wof:name":"Jagsura",
    "wof:placetype":"locality"
},
  "geometry": {"coordinates":[76.12794,26.51861],"type":"Point"}
}