{
  "type": "Feature",
  "properties": {
    "gn:admin1_code":"37",
    "gn:admin2_code":"408.0",
    "gn:asciiname":"Bacheraband",
    "gn:country_code":"IN",
    "gn:dem":386,
    "gn:feature_class":"P",
    "gn:feature_code":"PPL",
    "gn:name":"Bacher\u0101b\u0101nd",
    "gn:population":0,
    "gn:timezone":"Asia/Kolkata",
    "iso:country":"IN",
    "wof:name":"Bacheraband",
    "wof:placetype":"neighbourhood"
},
  "geometry": {"coordinates":[80.74315,21.21555],"type":"Point"}
}