{
  "type": "Feature",
  "properties": {
    "iso:country":"IN",
    "ks:ks_name":"Ektali",
    "ks:ks_pop":180,
    "ks:ks_type":"VILLAGE",
    "name:eng_x_preferred":[
        "Ektali"
    ],
    "wof:name":"Ektali",
    "wof:placetype":"locality",
    "wof:population":180
},
  "geometry": {"coordinates":[86.417474,22.114821],"type":"Point"}
}