{
  "type": "Feature",
  "properties": {
    "iso:country":"IN",
    "ks:ks_name":"Voojuru",
    "ks:ks_pop":281,
    "ks:ks_type":"HABITATION",
    "name:eng_x_preferred":[
        "Voojuru"
    ],
    "wof:name":"Voojuru",
    "wof:placetype":"locality",
    "wof:population":281
},
  "geometry": {"coordinates":[75.00243,13.441406],"type":"Point"}
}