{
  "type": "Feature",
  "properties": {
    "gn:admin1_code":"38.0",
    "gn:admin2_code":"357",
    "gn:asciiname":"Dublabera",
    "gn:country_code":"IN",
    "gn:dem":266,
    "gn:feature_class":"P",
    "gn:feature_code":"PPL",
    "gn:name":"Dubl\u0101ber\u0101",
    "gn:population":0,
    "gn:timezone":"Asia/Kolkata",
    "iso:country":"IN",
    "wof:name":"Dublabera",
    "wof:placetype":"locality"
},
  "geometry": {"coordinates":[86.28929000000002,22.49215],"type":"Point"}
}