{
  "type": "Feature",
  "properties": {
    "iso:country":"IN",
    "ks:ks_name":"Gajpatia",
    "ks:ks_pop":569,
    "ks:ks_type":"VILLAGE",
    "name:eng_x_preferred":[
        "Gajpatia"
    ],
    "wof:name":"Gajpatia",
    "wof:placetype":"locality",
    "wof:population":569
},
  "geometry": {"coordinates":[87.137423,22.433268],"type":"Point"}
}