{
  "type": "Feature",
  "properties": {
    "iso:country":"IN",
    "ks:ks_name":"Kubri",
    "ks:ks_pop":34,
    "ks:ks_type":"HABITATION",
    "name:eng_x_preferred":[
        "Kubri"
    ],
    "wof:name":"Kubri",
    "wof:placetype":"locality",
    "wof:population":34
},
  "geometry": {"coordinates":[80.788267,24.124294],"type":"Point"}
}