{
  "type": "Feature",
  "properties": {
    "gn:admin1_code":"13.0",
    "gn:admin2_code":"593.0",
    "gn:asciiname":"Tenur",
    "gn:country_code":"IN",
    "gn:dem":91,
    "gn:feature_class":"P",
    "gn:feature_code":"PPL",
    "gn:name":"T\u0113n\u016br",
    "gn:population":0,
    "gn:timezone":"Asia/Kolkata",
    "iso:country":"IN",
    "wof:name":"Tenur",
    "wof:placetype":"neighbourhood"
},
  "geometry": {"coordinates":[76.53569,10.80328],"type":"Point"}
}