{
  "type": "Feature",
  "properties": {
    "iso:country":"IN",
    "ks:ks_name":"Kumbia",
    "ks:ks_pop":290,
    "ks:ks_type":"VILLAGE",
    "name:eng_x_preferred":[
        "Kumbia"
    ],
    "wof:name":"Kumbia",
    "wof:placetype":"locality",
    "wof:population":290
},
  "geometry": {"coordinates":[85.326503,22.29345],"type":"Point"}
}