{
  "type": "Feature",
  "properties": {
    "iso:country":"IN",
    "ks:ks_name":"Kushahai",
    "ks:ks_pop":8,
    "ks:ks_type":"HABITATION",
    "name:eng_x_preferred":[
        "Kushahai"
    ],
    "wof:name":"Kushahai",
    "wof:placetype":"locality",
    "wof:population":8
},
  "geometry": {"coordinates":[81.814418,24.626173],"type":"Point"}
}