{
  "type": "Feature",
  "properties": {
    "iso:country":"IN",
    "ks:ks_name":"Pure Ramnagar",
    "ks:ks_pop":302,
    "ks:ks_type":"HABITATION",
    "name:eng_x_preferred":[
        "Pure Ramnagar"
    ],
    "wof:name":"Pure Ramnagar",
    "wof:placetype":"locality",
    "wof:population":302
},
  "geometry": {"coordinates":[81.5147,26.4527],"type":"Point"}
}