{
  "type": "Feature",
  "properties": {
    "iso:country":"IN",
    "ks:ks_name":"Chak Ratanpur",
    "ks:ks_pop":811,
    "ks:ks_type":"VILLAGE",
    "ks:ks_uagg_main":0,
    "name:eng_x_preferred":[
        "Chak Ratanpur"
    ],
    "wof:name":"Chak Ratanpur",
    "wof:placetype":"neighbourhood",
    "wof:population":811
},
  "geometry": {"coordinates":[80.224722,26.525833],"type":"Point"}
}