{
  "type": "Feature",
  "properties": {
    "iso:country":"IN",
    "ks:ks_alt_nam":"Kor\u0101dih",
    "ks:ks_name":"Koradih",
    "ks:ks_type":"VILLAGE",
    "ks:ks_uagg_main":0,
    "name:eng_x_preferred":[
        "Koradih"
    ],
    "name:eng_x_variant":[
        "Kor\u0101dih"
    ],
    "wof:name":"Koradih",
    "wof:placetype":"neighbourhood"
},
  "geometry": {"coordinates":[86.342609,24.67163],"type":"Point"}
}