{
  "type": "Feature",
  "properties": {
    "iso:country":"IN",
    "ks:ks_alt_nam":"barwaha",
    "ks:ks_name":"Barwaha",
    "ks:ks_pop":832,
    "ks:ks_type":"HABITATION",
    "name:eng_x_preferred":[
        "Barwaha"
    ],
    "wof:name":"Barwaha",
    "wof:placetype":"locality",
    "wof:population":832
},
  "geometry": {"coordinates":[83.689376,23.899305],"type":"Point"}
}