{
  "type": "Feature",
  "properties": {
    "iso:country":"IN",
    "ks:ks_name":"7 SPD",
    "ks:ks_pop":51,
    "ks:ks_type":"VILLAGE",
    "name:eng_x_preferred":[
        "7 SPD"
    ],
    "wof:name":"7 SPD",
    "wof:placetype":"locality",
    "wof:population":51
},
  "geometry": {"coordinates":[74.26025300000001,29.31049],"type":"Point"}
}