{
  "type": "Feature",
  "properties": {
    "gn:admin1_code":"35",
    "gn:admin2_code":"420.0",
    "gn:asciiname":"Bijora",
    "gn:country_code":"IN",
    "gn:dem":138,
    "gn:feature_class":"P",
    "gn:feature_code":"PPL",
    "gn:name":"Bijora",
    "gn:population":0,
    "gn:timezone":"Asia/Kolkata",
    "iso:country":"IN",
    "wof:name":"Bijora",
    "wof:placetype":"locality"
},
  "geometry": {"coordinates":[78.78934,26.75148],"type":"Point"}
}