{
  "type": "Feature",
  "properties": {
    "iso:country":"IN",
    "ks:ks_name":"Kesarogora",
    "ks:ks_pop":31,
    "ks:ks_type":"VILLAGE",
    "name:eng_x_preferred":[
        "Kesarogora"
    ],
    "wof:name":"Kesarogora",
    "wof:placetype":"locality",
    "wof:population":31
},
  "geometry": {"coordinates":[87.46763,24.970902],"type":"Point"}
}