{
  "type": "Feature",
  "properties": {
    "iso:country":"IN",
    "ks:ks_name":"Kuiyo",
    "ks:ks_pop":208,
    "ks:ks_type":"VILLAGE",
    "name:eng_x_preferred":[
        "Kuiyo"
    ],
    "wof:name":"Kuiyo",
    "wof:placetype":"locality",
    "wof:population":208
},
  "geometry": {"coordinates":[84.453552,23.120876],"type":"Point"}
}