{
  "type": "Feature",
  "properties": {
    "iso:country":"IN",
    "ks:ks_name":"Basutya",
    "ks:ks_pop":624,
    "ks:ks_type":"VILLAGE",
    "name:eng_x_preferred":[
        "Basutya"
    ],
    "wof:name":"Basutya",
    "wof:placetype":"locality",
    "wof:population":624
},
  "geometry": {"coordinates":[87.417993,22.058354],"type":"Point"}
}