{
  "type": "Feature",
  "properties": {
    "iso:country":"IN",
    "ks:ks_name":"Kanto",
    "ks:ks_pop":18,
    "ks:ks_type":"HABITATION",
    "name:eng_x_preferred":[
        "Kanto"
    ],
    "wof:name":"Kanto",
    "wof:placetype":"locality",
    "wof:population":18
},
  "geometry": {"coordinates":[82.283163,23.580755],"type":"Point"}
}