{
  "type": "Feature",
  "properties": {
    "iso:country":"IN",
    "ks:ks_name":"Vitthal Thombarewasti",
    "ks:ks_pop":274,
    "ks:ks_type":"HABITATION",
    "name:eng_x_preferred":[
        "Vitthal Thombarewasti"
    ],
    "wof:name":"Vitthal Thombarewasti",
    "wof:placetype":"locality",
    "wof:population":274
},
  "geometry": {"coordinates":[74.88,18.177],"type":"Point"}
}