{
  "type": "Feature",
  "properties": {
    "iso:country":"IN",
    "ks:ks_alt_nam":"TETULTALA",
    "ks:ks_name":"Tetultala",
    "ks:ks_pop":1031,
    "ks:ks_type":"HABITATION",
    "name:eng_x_preferred":[
        "Tetultala"
    ],
    "wof:name":"Tetultala",
    "wof:placetype":"locality",
    "wof:population":1031
},
  "geometry": {"coordinates":[89.040648,26.627915],"type":"Point"}
}