{
  "type": "Feature",
  "properties": {
    "iso:country":"IN",
    "ks:ks_name":"Modalakali 1",
    "ks:ks_pop":15,
    "ks:ks_type":"HABITATION",
    "name:eng_x_preferred":[
        "Modalakali 1"
    ],
    "wof:name":"Modalakali 1",
    "wof:placetype":"locality",
    "wof:population":15
},
  "geometry": {"coordinates":[75.185941,12.673309],"type":"Point"}
}