{
  "type": "Feature",
  "properties": {
    "iso:country":"IN",
    "ks:ks_alt_nam":"Mus\u0101k\u0101ni",
    "ks:ks_name":"Musakani",
    "ks:ks_type":"VILLAGE",
    "name:eng_x_preferred":[
        "Musakani"
    ],
    "name:eng_x_variant":[
        "Mus\u0101k\u0101ni"
    ],
    "wof:name":"Musakani",
    "wof:placetype":"locality"
},
  "geometry": {"coordinates":[84.568741,21.235815],"type":"Point"}
}