{
  "type": "Feature",
  "properties": {
    "iso:country":"IN",
    "ks:ks_name":"Tarangapur",
    "ks:ks_pop":3956,
    "ks:ks_type":"VILLAGE",
    "ks:ks_uagg_main":0,
    "name:eng_x_preferred":[
        "Tarangapur"
    ],
    "wof:name":"Tarangapur",
    "wof:placetype":"locality",
    "wof:population":3956
},
  "geometry": {"coordinates":[88.305474,25.613051],"type":"Point"}
}