{
  "type": "Feature",
  "properties": {
    "gn:admin1_code":"09",
    "gn:admin2_code":"477.0",
    "gn:asciiname":"Lamba",
    "gn:country_code":"IN",
    "gn:dem":22,
    "gn:feature_class":"P",
    "gn:feature_code":"PPL",
    "gn:name":"L\u0101mba",
    "gn:population":0,
    "gn:timezone":"Asia/Kolkata",
    "iso:country":"IN",
    "name:ara_x_preferred":[
        "\u0644\u0627\u0645\u0628\u0627"
    ],
    "name:ben_bn_x_preferred":[
        "\u09b2\u09be\u09ae\u09ac\u09be"
    ],
    "name:ben_in_x_preferred":[
        "\u09b2\u09be\u09ae\u09ac\u09be"
    ],
    "name:ceb_x_preferred":[
        "Lamba"
    ],
    "name:deu_x_preferred":[
        "Lamba"
    ],
    "name:fra_x_preferred":[
        "Lamba"
    ],
    "name:guj_x_preferred":[
        "\u0ab2\u0abe\u0a82\u0aac\u0abe"
    ],
    "name:hin_x_preferred":[
        "\u0932\u093e\u0902\u092c\u093e"
    ],
    "name:hye_x_preferred":[
        "\u053c\u0561\u0574\u0562\u0561"
    ],
    "name:kan_x_preferred":[
        "\u0cb2\u0c82\u0cac\u0cbe"
    ],
    "name:mal_x_preferred":[
        "\u0d32\u0d3e\u0d02\u0d2c"
    ],
    "name:mar_x_preferred":[
        "\u0932\u093e\u0902\u092c\u093e"
    ],
    "name:nld_x_preferred":[
        "Lamba"
    ],
    "name:nor_x_preferred":[
        "Lamba"
    ],
    "name:pan_x_preferred":[
        "\u0a32\u0a70\u0a2c\u0a3e"
    ],
    "name:rus_x_preferred":[
        "\u041b\u0430\u043c\u0431\u0430"
    ],
    "name:swe_x_preferred":[
        "Lamba"
    ],
    "name:tam_x_preferred":[
        "\u0bb2\u0bae\u0bcd\u0baa\u0bbe"
    ],
    "name:tel_x_preferred":[
        "\u0c32\u0c02\u0c2c\u0c3e"
    ],
    "name:tur_x_preferred":[
        "Lamba"
    ],
    "name:ukr_x_preferred":[
        "\u041b\u0430\u043c\u0431\u0430"
    ],
    "name:urd_x_preferred":[
        "\u0644\u0627\u0645\u0628\u0627"
    ],
    "wof:name":"Lamba",
    "wof:placetype":"locality"
},
  "geometry": {"coordinates":[69.31565000000001,21.90208],"type":"Point"}
}