{
  "type": "Feature",
  "properties": {
    "iso:country":"IN",
    "ks:ks_name":"Ramnagar",
    "ks:ks_pop":1653,
    "ks:ks_type":"VILLAGE",
    "name:eng_x_preferred":[
        "Ramnagar"
    ],
    "wof:name":"Ramnagar",
    "wof:placetype":"locality",
    "wof:population":1653
},
  "geometry": {"coordinates":[88.307035,22.924488],"type":"Point"}
}