{
  "type": "Feature",
  "properties": {
    "iso:country":"IN",
    "ks:ks_name":"Belyadi",
    "ks:ks_pop":3244,
    "ks:ks_type":"VILLAGE",
    "ks:ks_uagg_main":0,
    "name:eng_x_preferred":[
        "Belyadi"
    ],
    "wof:name":"Belyadi",
    "wof:placetype":"neighbourhood",
    "wof:population":3244
},
  "geometry": {"coordinates":[86.003096,23.37916],"type":"Point"}
}