{
  "type": "Feature",
  "properties": {
    "iso:country":"IN",
    "ks:ks_alt_nam":"GANESHWASTI",
    "ks:ks_name":"Ganeshwasti",
    "ks:ks_pop":164,
    "ks:ks_type":"HABITATION",
    "name:eng_x_preferred":[
        "Ganeshwasti"
    ],
    "wof:name":"Ganeshwasti",
    "wof:placetype":"locality",
    "wof:population":164
},
  "geometry": {"coordinates":[75.89582799999999,18.987098],"type":"Point"}
}