{
  "type": "Feature",
  "properties": {
    "iso:country":"IN",
    "ks:ks_name":"Madalagiri",
    "ks:ks_pop":213,
    "ks:ks_type":"HABITATION",
    "name:eng_x_preferred":[
        "Madalagiri"
    ],
    "wof:name":"Madalagiri",
    "wof:placetype":"locality",
    "wof:population":213
},
  "geometry": {"coordinates":[74.47226499999999,14.475963],"type":"Point"}
}