{
  "type": "Feature",
  "properties": {
    "iso:country":"IN",
    "ks:ks_alt_nam":"JUNAPARA",
    "ks:ks_name":"Junapara",
    "ks:ks_pop":584,
    "ks:ks_type":"HABITATION",
    "name:eng_x_preferred":[
        "Junapara"
    ],
    "wof:name":"Junapara",
    "wof:placetype":"locality",
    "wof:population":584
},
  "geometry": {"coordinates":[83.33275,22.782205],"type":"Point"}
}