{
  "type": "Feature",
  "properties": {
    "iso:country":"IN",
    "ks:ks_name":"Bakkachinthalapally",
    "ks:ks_pop":170,
    "ks:ks_type":"HABITATION",
    "name:eng_x_preferred":[
        "Bakkachinthalapally"
    ],
    "wof:name":"Bakkachinthalapally",
    "wof:placetype":"locality",
    "wof:population":170
},
  "geometry": {"coordinates":[80.089118,17.88682],"type":"Point"}
}