{
  "type": "Feature",
  "properties": {
    "iso:country":"IN",
    "ks:ks_alt_nam":"Panjai cha odha",
    "ks:ks_name":"Panjai Cha Odha",
    "ks:ks_pop":90,
    "ks:ks_type":"HABITATION",
    "name:eng_x_preferred":[
        "Panjai Cha Odha"
    ],
    "wof:name":"Panjai Cha Odha",
    "wof:placetype":"locality",
    "wof:population":90
},
  "geometry": {"coordinates":[74.20711,18.45315],"type":"Point"}
}