{
  "type": "Feature",
  "properties": {
    "iso:country":"IN",
    "ks:ks_alt_nam":"MARGACHIWADI",
    "ks:ks_name":"Margachiwadi",
    "ks:ks_pop":420,
    "ks:ks_type":"HABITATION",
    "name:eng_x_preferred":[
        "Margachiwadi"
    ],
    "wof:name":"Margachiwadi",
    "wof:placetype":"locality",
    "wof:population":420
},
  "geometry": {"coordinates":[74.955085,16.997578],"type":"Point"}
}