{
  "type": "Feature",
  "properties": {
    "iso:country":"IN",
    "ks:ks_name":"Mukhchuma",
    "ks:ks_pop":20,
    "ks:ks_type":"VILLAGE",
    "name:eng_x_preferred":[
        "Mukhchuma"
    ],
    "wof:name":"Mukhchuma",
    "wof:placetype":"locality",
    "wof:population":20
},
  "geometry": {"coordinates":[85.644254,23.874174],"type":"Point"}
}