{
  "type": "Feature",
  "properties": {
    "iso:country":"IN",
    "ks:ks_name":"Mugerakala",
    "ks:ks_pop":130,
    "ks:ks_type":"HABITATION",
    "name:eng_x_preferred":[
        "Mugerakala"
    ],
    "wof:name":"Mugerakala",
    "wof:placetype":"locality",
    "wof:population":130
},
  "geometry": {"coordinates":[75.04335,13.227965],"type":"Point"}
}