{
  "type": "Feature",
  "properties": {
    "iso:country":"IN",
    "ks:ks_name":"Sarupada",
    "ks:ks_pop":124,
    "ks:ks_type":"VILLAGE",
    "name:eng_x_preferred":[
        "Sarupada"
    ],
    "wof:name":"Sarupada",
    "wof:placetype":"locality",
    "wof:population":124
},
  "geometry": {"coordinates":[83.949685,20.286942],"type":"Point"}
}