{
  "type": "Feature",
  "properties": {
    "gn:admin1_code":"36.0",
    "gn:admin2_code":"155.0",
    "gn:asciiname":"Jahangirpur",
    "gn:country_code":"IN",
    "gn:dem":132,
    "gn:feature_class":"P",
    "gn:feature_code":"PPL",
    "gn:name":"Jah\u0101ng\u012brpur",
    "gn:population":0,
    "gn:timezone":"Asia/Kolkata",
    "iso:country":"IN",
    "name:ben_x_preferred":[
        "\u099c\u09be\u09b9\u09be\u0999\u09cd\u0997\u09c0\u09b0\u09aa\u09c1\u09b0"
    ],
    "name:hin_x_preferred":[
        "\u091c\u0939\u093e\u0902\u0917\u0940\u0930\u092a\u0941\u0930"
    ],
    "name:pol_x_preferred":[
        "Jahangirpur"
    ],
    "wof:name":"Jahangirpur",
    "wof:placetype":"neighbourhood"
},
  "geometry": {"coordinates":[80.00530999999999,27.17464],"type":"Point"}
}