{
  "type": "Feature",
  "properties": {
    "gn:admin1_code":"25.0",
    "gn:admin2_code":"631.0",
    "gn:asciiname":"Anandur",
    "gn:country_code":"IN",
    "gn:dem":410,
    "gn:feature_class":"P",
    "gn:feature_code":"PPL",
    "gn:name":"\u0100nand\u016br",
    "gn:population":0,
    "gn:timezone":"Asia/Kolkata",
    "iso:country":"IN",
    "wof:name":"Anandur",
    "wof:placetype":"locality"
},
  "geometry": {"coordinates":[78.37548000000002,12.26159],"type":"Point"}
}