{
  "type": "Feature",
  "properties": {
    "iso:country":"IN",
    "ks:ks_name":"Akongapara",
    "ks:ks_pop":237,
    "ks:ks_type":"HABITATION",
    "name:eng_x_preferred":[
        "Akongapara"
    ],
    "wof:name":"Akongapara",
    "wof:placetype":"locality",
    "wof:population":237
},
  "geometry": {"coordinates":[90.55915299999999,25.929756],"type":"Point"}
}