{
  "type": "Feature",
  "properties": {
    "iso:country":"IN",
    "ks:ks_name":"Kukur Bhukwa",
    "ks:ks_pop":412,
    "ks:ks_type":"HABITATION",
    "ks:ks_uagg_main":0,
    "name:eng_x_preferred":[
        "Kukur Bhukwa"
    ],
    "wof:name":"Kukur Bhukwa",
    "wof:placetype":"neighbourhood",
    "wof:population":412
},
  "geometry": {"coordinates":[81.82733500000001,27.186936],"type":"Point"}
}