{
  "type": "Feature",
  "properties": {
    "iso:country":"IN",
    "ks:ks_name":"Holebail",
    "ks:ks_pop":34,
    "ks:ks_type":"HABITATION",
    "name:eng_x_preferred":[
        "Holebail"
    ],
    "wof:name":"Holebail",
    "wof:placetype":"locality",
    "wof:population":34
},
  "geometry": {"coordinates":[74.555887,14.570511],"type":"Point"}
}