{
  "type": "Feature",
  "properties": {
    "iso:country":"IN",
    "ks:ks_name":"Mathapada",
    "ks:ks_pop":3432,
    "ks:ks_type":"HABITATION",
    "name:eng_x_preferred":[
        "Mathapada"
    ],
    "wof:name":"Mathapada",
    "wof:placetype":"locality",
    "wof:population":3432
},
  "geometry": {"coordinates":[82.334801,18.778221],"type":"Point"}
}