{
  "type": "Feature",
  "properties": {
    "gn:admin1_code":"28.0",
    "gn:admin2_code":"341",
    "gn:asciiname":"Bargachia",
    "gn:country_code":"IN",
    "gn:dem":9,
    "gn:feature_class":"P",
    "gn:feature_code":"PPL",
    "gn:name":"Barg\u0101chia",
    "gn:population":0,
    "gn:timezone":"Asia/Kolkata",
    "iso:country":"IN",
    "ks:ks_name":"Bargachhia",
    "ks:ks_pop":4206,
    "ks:ks_type":"VILLAGE",
    "ks:ks_uagg_main":0,
    "name:eng_x_preferred":[
        "Bargachhia"
    ],
    "wof:name":"Bargachhia",
    "wof:placetype":"neighbourhood",
    "wof:population":4206
},
  "geometry": {"coordinates":[88.144194,22.660782],"type":"Point"}
}