{
  "type": "Feature",
  "properties": {
    "gn:admin1_code":"36.0",
    "gn:admin2_code":"157.0",
    "gn:asciiname":"Bargadi Kalan",
    "gn:country_code":"IN",
    "gn:dem":123,
    "gn:feature_class":"P",
    "gn:feature_code":"PPL",
    "gn:name":"Bargadi Kal\u0101n",
    "gn:population":0,
    "gn:timezone":"Asia/Kolkata",
    "iso:country":"IN",
    "wof:name":"Bargadi Kalan",
    "wof:placetype":"locality"
},
  "geometry": {"coordinates":[80.88285999999999,27.05005],"type":"Point"}
}