{
  "type": "Feature",
  "properties": {
    "iso:country":"IN",
    "ks:ks_name":"Hanlokrok",
    "ks:ks_pop":899,
    "ks:ks_type":"HABITATION",
    "ks:ks_uagg_main":0,
    "name:eng_x_preferred":[
        "Hanlokrok"
    ],
    "wof:name":"Hanlokrok",
    "wof:placetype":"neighbourhood",
    "wof:population":899
},
  "geometry": {"coordinates":[92.707176,26.017335],"type":"Point"}
}