{
  "type": "Feature",
  "properties": {
    "iso:country":"IN",
    "ks:ks_alt_nam":"Kothuru at Roddavalasa",
    "ks:ks_name":"Kothuru At Roddavalasa",
    "ks:ks_pop":117,
    "ks:ks_type":"HABITATION",
    "name:eng_x_preferred":[
        "Kothuru At Roddavalasa"
    ],
    "wof:name":"Kothuru At Roddavalasa",
    "wof:placetype":"locality",
    "wof:population":117
},
  "geometry": {"coordinates":[83.08889499999999,18.526022],"type":"Point"}
}