{
  "type": "Feature",
  "properties": {
    "iso:country":"IN",
    "ks:ks_alt_nam":"Devilal ki Dhani",
    "ks:ks_name":"Devilal Ki Dhani",
    "ks:ks_pop":1,
    "ks:ks_type":"HABITATION",
    "name:eng_x_preferred":[
        "Devilal Ki Dhani"
    ],
    "wof:name":"Devilal Ki Dhani",
    "wof:placetype":"locality",
    "wof:population":1
},
  "geometry": {"coordinates":[74.53215,29.888045],"type":"Point"}
}