{
  "type": "Feature",
  "properties": {
    "iso:country":"IN",
    "ks:ks_alt_nam":"puthukottuthazham",
    "ks:ks_name":"Puthukottuthazham",
    "ks:ks_pop":450,
    "ks:ks_type":"HABITATION",
    "name:eng_x_preferred":[
        "Puthukottuthazham"
    ],
    "wof:name":"Puthukottuthazham",
    "wof:placetype":"locality",
    "wof:population":450
},
  "geometry": {"coordinates":[75.73140100000001,11.574636],"type":"Point"}
}