{
  "type": "Feature",
  "properties": {
    "iso:country":"IN",
    "ks:ks_name":"Angira",
    "ks:ks_pop":747,
    "ks:ks_type":"VILLAGE",
    "ks:ks_uagg_main":0,
    "name:eng_x_preferred":[
        "Angira"
    ],
    "wof:name":"Angira",
    "wof:placetype":"neighbourhood",
    "wof:population":747
},
  "geometry": {"coordinates":[86.264067,20.13307],"type":"Point"}
}