{
  "type": "Feature",
  "properties": {
    "iso:country":"IN",
    "ks:ks_name":"Baldev Singh Ki Dhani",
    "ks:ks_pop":30,
    "ks:ks_type":"HABITATION",
    "name:eng_x_preferred":[
        "Baldev Singh Ki Dhani"
    ],
    "wof:name":"Baldev Singh Ki Dhani",
    "wof:placetype":"locality",
    "wof:population":30
},
  "geometry": {"coordinates":[74.41015,29.785667],"type":"Point"}
}