{
  "type": "Feature",
  "properties": {
    "iso:country":"IN",
    "ks:ks_name":"Gulikana",
    "ks:ks_pop":29,
    "ks:ks_type":"HABITATION",
    "name:eng_x_preferred":[
        "Gulikana"
    ],
    "wof:name":"Gulikana",
    "wof:placetype":"locality",
    "wof:population":29
},
  "geometry": {"coordinates":[75.617597,12.530148],"type":"Point"}
}