{
  "type": "Feature",
  "properties": {
    "iso:country":"IN",
    "ks:ks_name":"Kherwa Chhit",
    "ks:ks_pop":290,
    "ks:ks_type":"VILLAGE",
    "name:eng_x_preferred":[
        "Kherwa Chhit"
    ],
    "wof:name":"Kherwa Chhit",
    "wof:placetype":"locality",
    "wof:population":290
},
  "geometry": {"coordinates":[87.045366,24.402083],"type":"Point"}
}