{
  "type": "Feature",
  "properties": {
    "gn:admin1_code":"25",
    "gn:admin2_code":"622.0",
    "gn:asciiname":"Paganeri",
    "gn:country_code":"IN",
    "gn:dem":71,
    "gn:feature_class":"P",
    "gn:feature_code":"PPL",
    "gn:name":"Paganeri",
    "gn:population":0,
    "gn:timezone":"Asia/Kolkata",
    "iso:country":"IN",
    "wof:name":"Paganeri",
    "wof:placetype":"locality"
},
  "geometry": {"coordinates":[78.59999999999999,9.95],"type":"Point"}
}