{
  "type": "Feature",
  "properties": {
    "iso:country":"IN",
    "ks:ks_name":"Chilkara",
    "ks:ks_pop":221,
    "ks:ks_type":"HABITATION",
    "name:eng_x_preferred":[
        "Chilkara"
    ],
    "wof:name":"Chilkara",
    "wof:placetype":"locality",
    "wof:population":221
},
  "geometry": {"coordinates":[86.834242,24.738547],"type":"Point"}
}