{
  "type": "Feature",
  "properties": {
    "iso:country":"IN",
    "ks:ks_name":"Parabrahma Petrol Pumb Jn",
    "ks:ks_pop":2915,
    "ks:ks_type":"HABITATION",
    "name:eng_x_preferred":[
        "Parabrahma Petrol Pumb Jn"
    ],
    "wof:name":"Parabrahma Petrol Pumb Jn",
    "wof:placetype":"locality",
    "wof:population":2915
},
  "geometry": {"coordinates":[76.516533,9.127301],"type":"Point"}
}