{
  "type": "Feature",
  "properties": {
    "gn:admin1_code":"13.0",
    "gn:admin2_code":"596.0",
    "gn:asciiname":"Kadavappara",
    "gn:country_code":"IN",
    "gn:dem":571,
    "gn:feature_class":"P",
    "gn:feature_code":"PPL",
    "gn:name":"Kadavapp\u0101ra",
    "gn:population":0,
    "gn:timezone":"Asia/Kolkata",
    "iso:country":"IN",
    "wof:name":"Kadavappara",
    "wof:placetype":"locality"
},
  "geometry": {"coordinates":[76.96488000000002,9.5577],"type":"Point"}
}