{
  "type": "Feature",
  "properties": {
    "iso:country":"IN",
    "ks:ks_alt_nam":"\u0100bdull\u0101h Chak",
    "ks:ks_name":"Abdullah Chak",
    "ks:ks_pop":435,
    "ks:ks_type":"VILLAGE",
    "ks:ks_uagg_main":0,
    "name:eng_x_preferred":[
        "Abdullah Chak"
    ],
    "name:eng_x_variant":[
        "\u0100bdull\u0101h Chak"
    ],
    "wof:name":"Abdullah Chak",
    "wof:placetype":"neighbourhood",
    "wof:population":435
},
  "geometry": {"coordinates":[85.179615,25.550514],"type":"Point"}
}