{
  "type": "Feature",
  "properties": {
    "iso:country":"IN",
    "ks:ks_alt_nam":"BHOJKODGAON",
    "ks:ks_name":"Bhojkodgaon",
    "ks:ks_pop":77,
    "ks:ks_type":"HABITATION",
    "name:eng_x_preferred":[
        "Bhojkodgaon"
    ],
    "wof:name":"Bhojkodgaon",
    "wof:placetype":"locality",
    "wof:population":77
},
  "geometry": {"coordinates":[75.19105399999999,17.230416],"type":"Point"}
}