{
  "type": "Feature",
  "properties": {
    "iso:country":"IN",
    "ks:ks_name":"Baheriya Khurd",
    "ks:ks_pop":26,
    "ks:ks_type":"VILLAGE",
    "name:eng_x_preferred":[
        "Baheriya Khurd"
    ],
    "wof:name":"Baheriya Khurd",
    "wof:placetype":"locality",
    "wof:population":26
},
  "geometry": {"coordinates":[79.094731,23.490867],"type":"Point"}
}