{
  "type": "Feature",
  "properties": {
    "iso:country":"IN",
    "ks:ks_name":"Guti",
    "ks:ks_pop":24,
    "ks:ks_type":"HABITATION",
    "name:eng_x_preferred":[
        "Guti"
    ],
    "wof:name":"Guti",
    "wof:placetype":"locality",
    "wof:population":24
},
  "geometry": {"coordinates":[87.65080399999999,25.204782],"type":"Point"}
}