{
  "type": "Feature",
  "properties": {
    "iso:country":"IN",
    "ks:ks_name":"Alavalpur",
    "ks:ks_pop":0,
    "ks:ks_type":"VILLAGE",
    "name:eng_x_preferred":[
        "Alavalpur"
    ],
    "wof:name":"Alavalpur",
    "wof:placetype":"locality",
    "wof:population":0
},
  "geometry": {"coordinates":[79.97971800000001,27.545605],"type":"Point"}
}