{
  "type": "Feature",
  "properties": {
    "iso:country":"IN",
    "ks:ks_name":"Nagarewasti",
    "ks:ks_pop":375,
    "ks:ks_type":"HABITATION",
    "name:eng_x_preferred":[
        "Nagarewasti"
    ],
    "wof:name":"Nagarewasti",
    "wof:placetype":"locality",
    "wof:population":375
},
  "geometry": {"coordinates":[74.587816,18.670305],"type":"Point"}
}