{
  "type": "Feature",
  "properties": {
    "iso:country":"IN",
    "ks:ks_name":"Gurmichhariya",
    "ks:ks_pop":105,
    "ks:ks_type":"HABITATION",
    "name:eng_x_preferred":[
        "Gurmichhariya"
    ],
    "wof:name":"Gurmichhariya",
    "wof:placetype":"locality",
    "wof:population":105
},
  "geometry": {"coordinates":[82.45972,22.700785],"type":"Point"}
}