{
  "type": "Feature",
  "properties": {
    "iso:country":"IN",
    "ks:ks_name":"Muthanthully",
    "ks:ks_pop":290,
    "ks:ks_type":"HABITATION",
    "name:eng_x_preferred":[
        "Muthanthully"
    ],
    "wof:name":"Muthanthully",
    "wof:placetype":"locality",
    "wof:population":290
},
  "geometry": {"coordinates":[76.93053,9.927142],"type":"Point"}
}