{
  "type": "Feature",
  "properties": {
    "iso:country":"IN",
    "qs:name":"Bhoothanahalli",
    "qs:name_adm0":"India",
    "qs:name_adm1":"Karnataka",
    "qs:photos":175,
    "qs:photos_1k":35,
    "qs:photos_9k":1,
    "qs:photos_9r":4,
    "qs:photos_all":175,
    "qs:photos_sr":4,
    "qs:placetype":"Town",
    "qs:pop_sr":"0",
    "wof:name":"Bhoothanahalli",
    "wof:placetype":"locality"
},
  "geometry": {"coordinates":[77.565708,12.801841],"type":"Point"}
}