{
  "type": "Feature",
  "properties": {
    "iso:country":"IN",
    "ks:ks_name":"Halebaragal",
    "ks:ks_pop":73,
    "ks:ks_type":"HABITATION",
    "name:eng_x_preferred":[
        "Halebaragal"
    ],
    "wof:name":"Halebaragal",
    "wof:placetype":"locality",
    "wof:population":73
},
  "geometry": {"coordinates":[74.73795800000001,14.319731],"type":"Point"}
}