{
  "type": "Feature",
  "properties": {
    "iso:country":"IN",
    "ks:ks_alt_nam":"musharna palar",
    "ks:ks_name":"Musharna Palar",
    "ks:ks_pop":714,
    "ks:ks_type":"HABITATION",
    "name:eng_x_preferred":[
        "Musharna Palar"
    ],
    "wof:name":"Musharna Palar",
    "wof:placetype":"locality",
    "wof:population":714
},
  "geometry": {"coordinates":[86.843356,26.379581],"type":"Point"}
}