{
  "type": "Feature",
  "properties": {
    "iso:country":"IN",
    "ks:ks_name":"Rabda",
    "ks:ks_pop":90,
    "ks:ks_type":"VILLAGE",
    "name:eng_x_preferred":[
        "Rabda"
    ],
    "wof:name":"Rabda",
    "wof:placetype":"locality",
    "wof:population":90
},
  "geometry": {"coordinates":[84.53172600000001,24.300554],"type":"Point"}
}