{
  "type": "Feature",
  "properties": {
    "iso:country":"IN",
    "ks:ks_name":"Pora",
    "ks:ks_pop":859,
    "ks:ks_type":"VILLAGE",
    "name:eng_x_preferred":[
        "Pora"
    ],
    "wof:name":"Pora",
    "wof:placetype":"locality",
    "wof:population":859
},
  "geometry": {"coordinates":[73.16613599999999,21.772081],"type":"Point"}
}