{
  "type": "Feature",
  "properties": {
    "iso:country":"IN",
    "ks:ks_name":"Gajna",
    "ks:ks_pop":94,
    "ks:ks_type":"VILLAGE",
    "ks:ks_uagg_main":0,
    "name:eng_x_preferred":[
        "Gajna"
    ],
    "wof:name":"Gajna",
    "wof:placetype":"neighbourhood",
    "wof:population":94
},
  "geometry": {"coordinates":[87.326145,22.053241],"type":"Point"}
}