{
  "type": "Feature",
  "properties": {
    "iso:country":"IN",
    "ks:ks_name":"Thakurwadi",
    "ks:ks_pop":540,
    "ks:ks_type":"HABITATION",
    "name:eng_x_preferred":[
        "Thakurwadi"
    ],
    "wof:name":"Thakurwadi",
    "wof:placetype":"locality",
    "wof:population":540
},
  "geometry": {"coordinates":[73.22521,18.817119],"type":"Point"}
}