{
  "type": "Feature",
  "properties": {
    "gn:admin1_code":"34.0",
    "gn:admin2_code":"237.0",
    "gn:asciiname":"Mafi",
    "gn:country_code":"IN",
    "gn:dem":75,
    "gn:feature_class":"P",
    "gn:feature_code":"PPL",
    "gn:name":"M\u0101fi",
    "gn:population":0,
    "gn:timezone":"Asia/Kolkata",
    "iso:country":"IN",
    "name:ceb_x_preferred":[
        "Mafi"
    ],
    "name:deu_x_preferred":[
        "Mafi"
    ],
    "name:rus_x_preferred":[
        "\u041c\u0430\u0444\u0438"
    ],
    "name:swe_x_preferred":[
        "Mafi"
    ],
    "wof:name":"Mafi",
    "wof:placetype":"locality"
},
  "geometry": {"coordinates":[85.62766999999999,25.01482],"type":"Point"}
}