{
  "type": "Feature",
  "properties": {
    "gn:admin1_code":"36.0",
    "gn:admin2_code":"153.0",
    "gn:asciiname":"Adharpur",
    "gn:country_code":"IN",
    "gn:dem":152,
    "gn:feature_class":"P",
    "gn:feature_code":"PPL",
    "gn:name":"Adh\u0101rpur",
    "gn:population":0,
    "gn:timezone":"Asia/Kolkata",
    "iso:country":"IN",
    "ks:ks_alt_nam":"Adh\u0101rpur",
    "ks:ks_name":"Adharpur",
    "ks:ks_pop":0,
    "ks:ks_type":"VILLAGE",
    "name:eng_x_preferred":[
        "Adharpur"
    ],
    "name:eng_x_variant":[
        "Adh\u0101rpur"
    ],
    "wof:name":"Adharpur",
    "wof:placetype":"locality",
    "wof:population":0
},
  "geometry": {"coordinates":[80.194751,27.808609],"type":"Point"}
}