{
  "type": "Feature",
  "properties": {
    "iso:country":"IN",
    "ks:ks_name":"Sharma Tola",
    "ks:ks_pop":464,
    "ks:ks_type":"HABITATION",
    "name:eng_x_preferred":[
        "Sharma Tola"
    ],
    "wof:name":"Sharma Tola",
    "wof:placetype":"locality",
    "wof:population":464
},
  "geometry": {"coordinates":[85.747361,25.635197],"type":"Point"}
}