{
  "type": "Feature",
  "properties": {
    "gn:admin1_code":"36",
    "gn:admin2_code":"194.0",
    "gn:asciiname":"Parasrampur",
    "gn:country_code":"IN",
    "gn:dem":88,
    "gn:feature_class":"P",
    "gn:feature_code":"PPL",
    "gn:name":"Parasr\u0101mpur",
    "gn:population":0,
    "gn:timezone":"Asia/Kolkata",
    "iso:country":"IN",
    "ks:ks_name":"Paras Rampur",
    "ks:ks_pop":877,
    "ks:ks_type":"VILLAGE",
    "name:eng_x_preferred":[
        "Paras Rampur"
    ],
    "name:eng_x_variant":[
        "Parasrampur"
    ],
    "wof:name":"Paras Rampur",
    "wof:placetype":"locality",
    "wof:population":877
},
  "geometry": {"coordinates":[82.692488,25.567249],"type":"Point"}
}