{
  "type": "Feature",
  "properties": {
    "iso:country":"IN",
    "ks:ks_name":"Singhra",
    "ks:ks_pop":999,
    "ks:ks_type":"VILLAGE",
    "name:eng_x_preferred":[
        "Singhra"
    ],
    "wof:name":"Singhra",
    "wof:placetype":"locality",
    "wof:population":999
},
  "geometry": {"coordinates":[83.15805899999999,23.443124],"type":"Point"}
}