{
  "type": "Feature",
  "properties": {
    "iso:country":"IN",
    "ks:ks_name":"Jambe",
    "ks:ks_pop":226,
    "ks:ks_type":"HABITATION",
    "name:eng_x_preferred":[
        "Jambe"
    ],
    "wof:name":"Jambe",
    "wof:placetype":"locality",
    "wof:population":226
},
  "geometry": {"coordinates":[74.858521,13.783817],"type":"Point"}
}