{
  "type": "Feature",
  "properties": {
    "iso:country":"IN",
    "ks:ks_name":"Kurumpatti",
    "ks:ks_pop":160,
    "ks:ks_type":"VILLAGE",
    "name:eng_x_preferred":[
        "Kurumpatti"
    ],
    "wof:name":"Kurumpatti",
    "wof:placetype":"locality",
    "wof:population":160
},
  "geometry": {"coordinates":[78.475086,12.13678],"type":"Point"}
}