{
  "type": "Feature",
  "properties": {
    "iso:country":"IN",
    "ks:ks_name":"Pamulabai Thanda",
    "ks:ks_pop":50,
    "ks:ks_type":"HABITATION",
    "name:eng_x_preferred":[
        "Pamulabai Thanda"
    ],
    "wof:name":"Pamulabai Thanda",
    "wof:placetype":"locality",
    "wof:population":50
},
  "geometry": {"coordinates":[79.38012000000001,17.541178],"type":"Point"}
}