{
  "type": "Feature",
  "properties": {
    "iso:country":"IN",
    "ks:ks_name":"Bagwadi",
    "ks:ks_pop":451,
    "ks:ks_type":"HABITATION",
    "name:eng_x_preferred":[
        "Bagwadi"
    ],
    "wof:name":"Bagwadi",
    "wof:placetype":"locality",
    "wof:population":451
},
  "geometry": {"coordinates":[73.611209,16.011027],"type":"Point"}
}