{
  "type": "Feature",
  "properties": {
    "iso:country":"IN",
    "ks:ks_name":"Kallottu Padavu",
    "ks:ks_pop":460,
    "ks:ks_type":"HABITATION",
    "name:eng_x_preferred":[
        "Kallottu Padavu"
    ],
    "wof:name":"Kallottu Padavu",
    "wof:placetype":"locality",
    "wof:population":460
},
  "geometry": {"coordinates":[74.892516,13.149453],"type":"Point"}
}