{
  "type": "Feature",
  "properties": {
    "iso:country":"IN",
    "ks:ks_name":"Bhaiyapura",
    "ks:ks_pop":45,
    "ks:ks_type":"VILLAGE",
    "name:eng_x_preferred":[
        "Bhaiyapura"
    ],
    "wof:name":"Bhaiyapura",
    "wof:placetype":"locality",
    "wof:population":45
},
  "geometry": {"coordinates":[76.281503,27.056806],"type":"Point"}
}