{
  "type": "Feature",
  "properties": {
    "iso:country":"IN",
    "ks:ks_name":"Mahguwan",
    "ks:ks_pop":244,
    "ks:ks_type":"VILLAGE",
    "name:eng_x_preferred":[
        "Mahguwan"
    ],
    "wof:name":"Mahguwan",
    "wof:placetype":"locality",
    "wof:population":244
},
  "geometry": {"coordinates":[79.19293500000001,23.215821],"type":"Point"}
}