{
  "type": "Feature",
  "properties": {
    "iso:country":"IN",
    "ks:ks_name":"Marhaiya",
    "ks:ks_pop":100,
    "ks:ks_type":"HABITATION",
    "name:eng_x_preferred":[
        "Marhaiya"
    ],
    "wof:name":"Marhaiya",
    "wof:placetype":"locality",
    "wof:population":100
},
  "geometry": {"coordinates":[79.87939299999999,26.906273],"type":"Point"}
}