{
  "type": "Feature",
  "properties": {
    "iso:country":"IN",
    "ks:ks_name":"Umhi",
    "ks:ks_pop":113,
    "ks:ks_type":"HABITATION",
    "name:eng_x_preferred":[
        "Umhi"
    ],
    "wof:name":"Umhi",
    "wof:placetype":"locality",
    "wof:population":113
},
  "geometry": {"coordinates":[92.187512,25.846376],"type":"Point"}
}