{
  "type": "Feature",
  "properties": {
    "gn:admin1_code":"24",
    "gn:admin2_code":"106.0",
    "gn:asciiname":"Phulpur",
    "gn:country_code":"IN",
    "gn:dem":176,
    "gn:feature_class":"P",
    "gn:feature_code":"PPL",
    "gn:name":"Ph\u016blpur",
    "gn:population":0,
    "gn:timezone":"Asia/Kolkata",
    "iso:country":"IN",
    "name:ita_x_preferred":[
        "Phulpur"
    ],
    "name:pol_x_preferred":[
        "Phulpur"
    ],
    "wof:name":"Phulpur",
    "wof:placetype":"locality"
},
  "geometry": {"coordinates":[77.79813,26.80184],"type":"Point"}
}