{
  "type": "Feature",
  "properties": {
    "iso:country":"IN",
    "ks:ks_alt_nam":"gandihambala",
    "ks:ks_name":"Gandihambala",
    "ks:ks_pop":128,
    "ks:ks_type":"HABITATION",
    "name:eng_x_preferred":[
        "Gandihambala"
    ],
    "wof:name":"Gandihambala",
    "wof:placetype":"locality",
    "wof:population":128
},
  "geometry": {"coordinates":[75.587468,13.457855],"type":"Point"}
}