{
  "type": "Feature",
  "properties": {
    "iso:country":"IN",
    "ks:ks_name":"Aseji Nagar",
    "ks:ks_pop":308,
    "ks:ks_type":"HABITATION",
    "name:eng_x_preferred":[
        "Aseji Nagar"
    ],
    "wof:name":"Aseji Nagar",
    "wof:placetype":"locality",
    "wof:population":308
},
  "geometry": {"coordinates":[72.277967,27.219],"type":"Point"}
}