{
  "type": "Feature",
  "properties": {
    "iso:country":"IN",
    "ks:ks_name":"Naturia Srirampur",
    "ks:ks_pop":1288,
    "ks:ks_type":"VILLAGE",
    "ks:ks_uagg_main":0,
    "name:eng_x_preferred":[
        "Naturia Srirampur"
    ],
    "wof:name":"Naturia Srirampur",
    "wof:placetype":"neighbourhood",
    "wof:population":1288
},
  "geometry": {"coordinates":[88.754017,22.749081],"type":"Point"}
}