{
  "type": "Feature",
  "properties": {
    "iso:country":"IN",
    "ks:ks_name":"Nazeerbegpalle",
    "ks:ks_pop":595,
    "ks:ks_type":"VILLAGE",
    "ks:ks_uagg_main":0,
    "name:eng_x_preferred":[
        "Nazeerbegpalle"
    ],
    "wof:name":"Nazeerbegpalle",
    "wof:placetype":"neighbourhood",
    "wof:population":595
},
  "geometry": {"coordinates":[78.832128,14.548554],"type":"Point"}
}