{
  "type": "Feature",
  "properties": {
    "iso:country":"IN",
    "ks:ks_alt_nam":"NAGLA MALHA",
    "ks:ks_name":"Nagla Malha",
    "ks:ks_pop":610,
    "ks:ks_type":"HABITATION",
    "name:eng_x_preferred":[
        "Nagla Malha"
    ],
    "wof:name":"Nagla Malha",
    "wof:placetype":"locality",
    "wof:population":610
},
  "geometry": {"coordinates":[79.066346,26.849166],"type":"Point"}
}