{
  "type": "Feature",
  "properties": {
    "iso:country":"IN",
    "ks:ks_alt_nam":"Nerlameedi tanda",
    "ks:ks_name":"Nerlameedi Tanda",
    "ks:ks_pop":65,
    "ks:ks_type":"HABITATION",
    "name:eng_x_preferred":[
        "Nerlameedi Tanda"
    ],
    "wof:name":"Nerlameedi Tanda",
    "wof:placetype":"locality",
    "wof:population":65
},
  "geometry": {"coordinates":[77.804812,17.104646],"type":"Point"}
}