{
  "type": "Feature",
  "properties": {
    "iso:country":"IN",
    "ks:ks_name":"Malagan",
    "ks:ks_pop":326,
    "ks:ks_type":"VILLAGE",
    "name:eng_x_preferred":[
        "Malagan"
    ],
    "wof:name":"Malagan",
    "wof:placetype":"locality",
    "wof:population":326
},
  "geometry": {"coordinates":[84.394372,20.247912],"type":"Point"}
}