{
  "type": "Feature",
  "properties": {
    "iso:country":"IN",
    "ks:ks_name":"Fuljharan",
    "ks:ks_pop":301,
    "ks:ks_type":"VILLAGE",
    "name:eng_x_preferred":[
        "Fuljharan"
    ],
    "wof:name":"Fuljharan",
    "wof:placetype":"locality",
    "wof:population":301
},
  "geometry": {"coordinates":[86.469275,22.286046],"type":"Point"}
}