{
  "type": "Feature",
  "properties": {
    "gn:admin1_code":"9.0",
    "gn:admin2_code":"492",
    "gn:asciiname":"Deogad",
    "gn:country_code":"IN",
    "gn:dem":82,
    "gn:feature_class":"P",
    "gn:feature_code":"PPL",
    "gn:name":"Deogad",
    "gn:population":0,
    "gn:timezone":"Asia/Kolkata",
    "iso:country":"IN",
    "wof:name":"Deogad",
    "wof:placetype":"locality"
},
  "geometry": {"coordinates":[73.33655999999998,21.38956],"type":"Point"}
}