{
  "type": "Feature",
  "properties": {
    "iso:country":"IN",
    "ks:ks_alt_nam":"Sarainoor nagar",
    "ks:ks_name":"Sarainoor Nagar",
    "ks:ks_pop":1725,
    "ks:ks_type":"HABITATION",
    "ks:ks_uagg_main":0,
    "name:eng_x_preferred":[
        "Sarainoor Nagar"
    ],
    "wof:name":"Sarainoor Nagar",
    "wof:placetype":"neighbourhood",
    "wof:population":1725
},
  "geometry": {"coordinates":[85.922977,25.617067],"type":"Point"}
}