{
  "type": "Feature",
  "properties": {
    "gn:admin1_code":"19",
    "gn:admin2_code":"558.0",
    "gn:asciiname":"Lingdhalli",
    "gn:country_code":"IN",
    "gn:dem":520,
    "gn:feature_class":"P",
    "gn:feature_code":"PPL",
    "gn:name":"Lingdhalli",
    "gn:population":0,
    "gn:timezone":"Asia/Kolkata",
    "iso:country":"IN",
    "wof:name":"Lingdhalli",
    "wof:placetype":"locality"
},
  "geometry": {"coordinates":[77.54944999999999,18.23793],"type":"Point"}
}