{
  "type": "Feature",
  "properties": {
    "iso:country":"IN",
    "ks:ks_name":"Irular Colony",
    "ks:ks_pop":110,
    "ks:ks_type":"HABITATION",
    "ks:ks_uagg_main":0,
    "name:eng_x_preferred":[
        "Irular Colony"
    ],
    "wof:name":"Irular Colony",
    "wof:placetype":"neighbourhood",
    "wof:population":110
},
  "geometry": {"coordinates":[79.366911,13.113867],"type":"Point"}
}