{
  "type": "Feature",
  "properties": {
    "gn:admin1_code":"11",
    "gn:admin2_code":"23.0",
    "gn:asciiname":"Kandlot Got",
    "gn:country_code":"IN",
    "gn:dem":2670,
    "gn:feature_class":"P",
    "gn:feature_code":"PPL",
    "gn:name":"K\u0101ndlot Got",
    "gn:population":0,
    "gn:timezone":"Asia/Kolkata",
    "iso:country":"IN",
    "wof:name":"Kandlot Got",
    "wof:placetype":"locality"
},
  "geometry": {"coordinates":[76.25944,32.70032],"type":"Point"}
}