{
  "type": "Feature",
  "properties": {
    "iso:country":"IN",
    "ks:ks_name":"Dadari",
    "ks:ks_pop":503,
    "ks:ks_type":"HABITATION",
    "name:eng_x_preferred":[
        "Dadari"
    ],
    "wof:name":"Dadari",
    "wof:placetype":"locality",
    "wof:population":503
},
  "geometry": {"coordinates":[73.295917,21.187139],"type":"Point"}
}