{
  "type": "Feature",
  "properties": {
    "iso:country":"IN",
    "ks:ks_name":"Sarajapur",
    "ks:ks_pop":863,
    "ks:ks_type":"VILLAGE",
    "name:eng_x_preferred":[
        "Sarajapur"
    ],
    "wof:name":"Sarajapur",
    "wof:placetype":"locality",
    "wof:population":863
},
  "geometry": {"coordinates":[77.522319,25.245941],"type":"Point"}
}