{
  "type": "Feature",
  "properties": {
    "iso:country":"IN",
    "ks:ks_alt_nam":"KULLU",
    "ks:ks_name":"Kullu",
    "ks:ks_pop":113,
    "ks:ks_type":"HABITATION",
    "name:eng_x_preferred":[
        "Kullu"
    ],
    "wof:name":"Kullu",
    "wof:placetype":"locality",
    "wof:population":113
},
  "geometry": {"coordinates":[84.865218,24.337003],"type":"Point"}
}