{
  "type": "Feature",
  "properties": {
    "iso:country":"IN",
    "ks:ks_name":"Khodadpur",
    "ks:ks_pop":538,
    "ks:ks_type":"VILLAGE",
    "ks:ks_uagg_main":0,
    "name:eng_x_preferred":[
        "Khodadpur"
    ],
    "wof:name":"Khodadpur",
    "wof:placetype":"neighbourhood",
    "wof:population":538
},
  "geometry": {"coordinates":[85.094919,26.402277],"type":"Point"}
}