{
  "type": "Feature",
  "properties": {
    "gn:admin1_code":"03",
    "gn:admin2_code":"322.0",
    "gn:asciiname":"Margang",
    "gn:country_code":"IN",
    "gn:dem":236,
    "gn:feature_class":"P",
    "gn:feature_code":"PPL",
    "gn:name":"M\u0101rg\u0101ng",
    "gn:population":0,
    "gn:timezone":"Asia/Kolkata",
    "iso:country":"IN",
    "wof:name":"Margang",
    "wof:placetype":"locality"
},
  "geometry": {"coordinates":[91.99663,26.05709],"type":"Point"}
}