{
  "type": "Feature",
  "properties": {
    "gn:admin1_code":"34.0",
    "gn:admin2_code":"210.0",
    "gn:asciiname":"Phulbari",
    "gn:country_code":"IN",
    "gn:dem":70,
    "gn:feature_class":"P",
    "gn:feature_code":"PPL",
    "gn:name":"Phulb\u0101ri",
    "gn:population":0,
    "gn:timezone":"Asia/Kolkata",
    "iso:country":"IN",
    "ks:ks_alt_nam":"Phulb\u0101ri",
    "ks:ks_name":"Phulbari",
    "ks:ks_pop":644,
    "ks:ks_type":"VILLAGE",
    "ks:ks_uagg_main":0,
    "name:eng_x_preferred":[
        "Phulbari"
    ],
    "name:eng_x_variant":[
        "Phulb\u0101ri"
    ],
    "wof:name":"Phulbari",
    "wof:placetype":"neighbourhood",
    "wof:population":644
},
  "geometry": {"coordinates":[87.664923,26.382994],"type":"Point"}
}