{
  "type": "Feature",
  "properties": {
    "gn:admin1_code":"19.0",
    "gn:admin2_code":"574.0",
    "gn:asciiname":"Dodda Jakkenahalli",
    "gn:country_code":"IN",
    "gn:dem":940,
    "gn:feature_class":"P",
    "gn:feature_code":"PPL",
    "gn:name":"Dodda Jakkenahalli",
    "gn:population":0,
    "gn:timezone":"Asia/Kolkata",
    "iso:country":"IN",
    "wof:name":"Dodda Jakkenahalli",
    "wof:placetype":"locality"
},
  "geometry": {"coordinates":[76.24304000000002,13.00512],"type":"Point"}
}