{
  "type": "Feature",
  "properties": {
    "iso:country":"IN",
    "ks:ks_alt_nam":"Khichroki dhani",
    "ks:ks_name":"Khichroki Dhani",
    "ks:ks_pop":757,
    "ks:ks_type":"HABITATION",
    "name:eng_x_preferred":[
        "Khichroki Dhani"
    ],
    "wof:name":"Khichroki Dhani",
    "wof:placetype":"locality",
    "wof:population":757
},
  "geometry": {"coordinates":[72.68156399999999,27.23615],"type":"Point"}
}