{
  "type": "Feature",
  "properties": {
    "iso:country":"IN",
    "ks:ks_name":"Bas Seowa",
    "ks:ks_pop":524,
    "ks:ks_type":"VILLAGE",
    "ks:ks_uagg_main":0,
    "name:eng_x_preferred":[
        "Bas Seowa"
    ],
    "wof:name":"Bas Seowa",
    "wof:placetype":"neighbourhood",
    "wof:population":524
},
  "geometry": {"coordinates":[75.15714699999999,28.637889],"type":"Point"}
}