{
  "type": "Feature",
  "properties": {
    "gn:admin1_code":"39.0",
    "gn:admin2_code":"60.0",
    "gn:asciiname":"Kulhal",
    "gn:country_code":"IN",
    "gn:dem":389,
    "gn:feature_class":"P",
    "gn:feature_code":"PPL",
    "gn:name":"Kulh\u0101l",
    "gn:population":0,
    "gn:timezone":"Asia/Kolkata",
    "iso:country":"IN",
    "wof:name":"Kulhal",
    "wof:placetype":"locality"
},
  "geometry": {"coordinates":[77.62087,30.42951],"type":"Point"}
}