{
  "type": "Feature",
  "properties": {
    "gn:admin1_code":"19.0",
    "gn:admin2_code":"555",
    "gn:asciiname":"Bekud",
    "gn:country_code":"IN",
    "gn:dem":625,
    "gn:feature_class":"P",
    "gn:feature_code":"PPL",
    "gn:name":"Bekud",
    "gn:population":0,
    "gn:timezone":"Asia/Kolkata",
    "iso:country":"IN",
    "name:und_x_variant":[
        "Adgal",
        "Bekud"
    ],
    "wof:name":"Bekud",
    "wof:placetype":"locality"
},
  "geometry": {"coordinates":[74.83684000000002,16.43114],"type":"Point"}
}