{
  "type": "Feature",
  "properties": {
    "iso:country":"IN",
    "ks:ks_name":"Neemoda",
    "ks:ks_pop":1472,
    "ks:ks_type":"HABITATION",
    "name:eng_x_preferred":[
        "Neemoda"
    ],
    "wof:name":"Neemoda",
    "wof:placetype":"locality",
    "wof:population":1472
},
  "geometry": {"coordinates":[77.246084,26.287997],"type":"Point"}
}