{
  "type": "Feature",
  "properties": {
    "gn:admin1_code":"35",
    "gn:admin2_code":"462.0",
    "gn:asciiname":"Jonki",
    "gn:country_code":"IN",
    "gn:dem":262,
    "gn:feature_class":"P",
    "gn:feature_code":"PPL",
    "gn:name":"Jonki",
    "gn:population":0,
    "gn:timezone":"Asia/Kolkata",
    "iso:country":"IN",
    "name:pol_x_preferred":[
        "Jonki"
    ],
    "name:ukr_x_preferred":[
        "\u0419\u043e\u043d\u043a\u0456"
    ],
    "wof:name":"Jonki",
    "wof:placetype":"locality"
},
  "geometry": {"coordinates":[82.14530999999999,24.58204],"type":"Point"}
}