{
  "type": "Feature",
  "properties": {
    "gn:admin1_code":"35",
    "gn:admin2_code":"462.0",
    "gn:asciiname":"Jonki",
    "gn:country_code":"IN",
    "gn:dem":262,
    "gn:feature_class":"P",
    "gn:feature_code":"PPL",
    "gn:name":"Jonki",
    "gn:population":0,
    "gn:timezone":"Asia/Kolkata",
    "iso:country":"IN",
    "ks:ks_name":"Joki",
    "ks:ks_pop":758,
    "ks:ks_type":"HABITATION",
    "name:eng_x_preferred":[
        "Joki"
    ],
    "name:eng_x_variant":[
        "Jonki"
    ],
    "name:pol_x_preferred":[
        "Jonki"
    ],
    "name:ukr_x_preferred":[
        "\u0419\u043e\u043d\u043a\u0456"
    ],
    "wof:name":"Joki",
    "wof:placetype":"locality",
    "wof:population":758
},
  "geometry": {"coordinates":[82.14685,24.581114],"type":"Point"}
}