{
  "type": "Feature",
  "properties": {
    "gn:admin1_code":"39.0",
    "gn:admin2_code":"64.0",
    "gn:asciiname":"Matila",
    "gn:country_code":"IN",
    "gn:dem":1670,
    "gn:feature_class":"P",
    "gn:feature_code":"PPL",
    "gn:name":"Mat\u012bla",
    "gn:population":0,
    "gn:timezone":"Asia/Kolkata",
    "iso:country":"IN",
    "wof:name":"Matila",
    "wof:placetype":"locality"
},
  "geometry": {"coordinates":[79.36511999999998,29.60279],"type":"Point"}
}