{
  "type": "Feature",
  "properties": {
    "iso:country":"IN",
    "ks:ks_alt_nam":"DULESAR",
    "ks:ks_name":"Dulesar",
    "ks:ks_pop":138,
    "ks:ks_type":"HABITATION",
    "name:eng_x_preferred":[
        "Dulesar"
    ],
    "wof:name":"Dulesar",
    "wof:placetype":"locality",
    "wof:population":138
},
  "geometry": {"coordinates":[83.825987,26.004612],"type":"Point"}
}