{
  "type": "Feature",
  "properties": {
    "iso:country":"IN",
    "ks:ks_name":"Dumgi Baramasia",
    "ks:ks_pop":140,
    "ks:ks_type":"VILLAGE",
    "name:eng_x_preferred":[
        "Dumgi Baramasia"
    ],
    "wof:name":"Dumgi Baramasia",
    "wof:placetype":"locality",
    "wof:population":140
},
  "geometry": {"coordinates":[87.747619,24.691786],"type":"Point"}
}