{
  "type": "Feature",
  "properties": {
    "gn:admin1_code":"34.0",
    "gn:admin2_code":"226.0",
    "gn:asciiname":"Isripur Qasim Mahatotola",
    "gn:country_code":"IN",
    "gn:dem":42,
    "gn:feature_class":"P",
    "gn:feature_code":"PPL",
    "gn:name":"Isr\u012bpur Q\u0101sim Mah\u0101totola",
    "gn:population":0,
    "gn:timezone":"Asia/Kolkata",
    "iso:country":"IN",
    "wof:name":"Isripur Qasim Mahatotola",
    "wof:placetype":"locality"
},
  "geometry": {"coordinates":[86.44816999999998,25.36114],"type":"Point"}
}