{
  "type": "Feature",
  "properties": {
    "iso:country":"IN",
    "name:ceb_x_preferred":[
        "Gundu Island"
    ],
    "name:eng_x_preferred":[
        "Gundu Island"
    ],
    "name:new_x_preferred":[
        "\u0917\u0941\u0928\u094d\u0921\u0941"
    ],
    "name:nld_x_preferred":[
        "Gundu Island"
    ],
    "name:spa_x_preferred":[
        "Isla Gundu"
    ],
    "name:swe_x_preferred":[
        "Gundu Island"
    ],
    "name:tam_x_preferred":[
        "\u0b95\u0bc1\u0ba3\u0bcd\u0b9f\u0bc1\u0ba4\u0bcd \u0ba4\u0bc0\u0bb5\u0bc1"
    ],
    "name:urd_x_preferred":[
        "\u06af\u0646\u0688\u0648 \u0679\u0627\u067e\u0648"
    ],
    "qs:gn_local":0,
    "qs:local_max":3383,
    "qs:local_sum":8346,
    "qs:localhoods":12,
    "qs:name":"Gundu Island",
    "qs:name_adm0":"India",
    "qs:name_adm1":"Kerala",
    "qs:name_adm2":"Ernakulam",
    "qs:name_local":"Kochi",
    "qs:photo_max":69,
    "qs:photo_sum":182,
    "qs:placetype":"Suburb",
    "qs:quad_count":9,
    "qs:woe_adm0":23424848,
    "qs:woe_adm1":2345747,
    "qs:woe_adm2":12586468,
    "qs:woe_lau":0,
    "qs:woe_local":2295423,
    "qs:woe_ver":"7.10.0",
    "wd:wordcount":133,
    "wof:lang":[
        "eng"
    ],
    "wof:name":"Gundu Island",
    "wof:placetype":"neighbourhood"
},
  "geometry": {"coordinates":[76.23498499999999,9.980332],"type":"Point"}
}