{
  "type": "Feature",
  "properties": {
    "iso:country":"IN",
    "name:ara_x_preferred":[
        "\u062c\u0632\u064a\u0631\u0629 \u062c\u0648\u0646\u062f\u0648"
    ],
    "name:ben_bn_x_preferred":[
        "\u0997\u09c1\u09a8\u09cd\u09a1\u09c1 \u0986\u0987\u09b2\u09cd\u09af\u09be\u09a8\u09cd\u09a1"
    ],
    "name:ben_in_x_preferred":[
        "\u0997\u09c1\u09a8\u09cd\u09a1\u09c1 \u0986\u0987\u09b2\u09cd\u09af\u09be\u09a8\u09cd\u09a1"
    ],
    "name:ceb_x_preferred":[
        "Gundu Island"
    ],
    "name:eng_x_preferred":[
        "Gundu Island"
    ],
    "name:guj_x_preferred":[
        "\u0a97\u0ac1\u0a82\u0aa1\u0ac1 \u0a9f\u0abe\u0aaa\u0ac1"
    ],
    "name:hin_x_preferred":[
        "\u0917\u0941\u0902\u0921\u0942 \u0926\u094d\u0935\u0940\u092a"
    ],
    "name:kan_x_preferred":[
        "\u0c97\u0cc1\u0c82\u0ca1\u0cc1 \u0c90\u0cb2\u0ccd\u0caf\u0cbe\u0c82\u0ca1\u0ccd"
    ],
    "name:mal_x_preferred":[
        "\u0d17\u0d41\u0d23\u0d4d\u0d1f\u0d41 \u0d26\u0d4d\u0d35\u0d40\u0d2a\u0d4d"
    ],
    "name:mar_x_preferred":[
        "\u0917\u0941\u0902\u0921\u0942 \u092c\u0947\u091f"
    ],
    "name:new_x_preferred":[
        "\u0917\u0941\u0928\u094d\u0921\u0941"
    ],
    "name:nld_x_preferred":[
        "Gundu Island"
    ],
    "name:pan_x_preferred":[
        "\u0a17\u0a41\u0a70\u0a21\u0a42 \u0a06\u0a08\u0a32\u0a48\u0a02\u0a21"
    ],
    "name:spa_x_preferred":[
        "Isla Gundu"
    ],
    "name:swe_x_preferred":[
        "Gundu Island"
    ],
    "name:tam_x_preferred":[
        "\u0b95\u0bc1\u0ba9\u0bcd\u0b9f\u0bc1\u0ba4\u0bcd \u0ba4\u0bc0\u0bb5\u0bc1"
    ],
    "name:tam_x_variant":[
        "\u0b95\u0bc1\u0ba3\u0bcd\u0b9f\u0bc1\u0ba4\u0bcd \u0ba4\u0bc0\u0bb5\u0bc1"
    ],
    "name:tel_x_preferred":[
        "\u0c17\u0c41\u0c02\u0c21\u0c41 \u0c26\u0c40\u0c35\u0c3f"
    ],
    "name:urd_x_preferred":[
        "\u06af\u0646\u0688\u0648 \u0622\u0626\u0644\u06cc\u0646\u0688"
    ],
    "name:urd_x_variant":[
        "\u06af\u0646\u0688\u0648 \u0679\u0627\u067e\u0648"
    ],
    "qs:gn_local":0,
    "qs:local_max":3383,
    "qs:local_sum":8346,
    "qs:localhoods":12,
    "qs:name":"Gundu Island",
    "qs:name_adm0":"India",
    "qs:name_adm1":"Kerala",
    "qs:name_adm2":"Ernakulam",
    "qs:name_local":"Kochi",
    "qs:photo_max":69,
    "qs:photo_sum":182,
    "qs:placetype":"Suburb",
    "qs:quad_count":9,
    "qs:woe_adm0":23424848,
    "qs:woe_adm1":2345747,
    "qs:woe_adm2":12586468,
    "qs:woe_lau":0,
    "qs:woe_local":2295423,
    "qs:woe_ver":"7.10.0",
    "wd:wordcount":133,
    "wof:lang":[
        "eng"
    ],
    "wof:name":"Gundu Island",
    "wof:placetype":"neighbourhood"
},
  "geometry": {"coordinates":[76.23498499999999,9.980332],"type":"Point"}
}