{
  "type": "Feature",
  "properties": {
    "gn:admin1_code":"34.0",
    "gn:admin2_code":"211.0",
    "gn:asciiname":"Khari",
    "gn:country_code":"IN",
    "gn:dem":42,
    "gn:feature_class":"P",
    "gn:feature_code":"PPL",
    "gn:name":"Kh\u0101ri",
    "gn:population":0,
    "gn:timezone":"Asia/Kolkata",
    "iso:country":"IN",
    "ks:ks_name":"Khari",
    "ks:ks_pop":384,
    "ks:ks_type":"VILLAGE",
    "ks:ks_uagg_main":0,
    "name:ceb_x_preferred":[
        "Khari"
    ],
    "name:deu_x_preferred":[
        "Khari"
    ],
    "name:eng_x_preferred":[
        "Khari"
    ],
    "name:msa_x_preferred":[
        "Khari"
    ],
    "name:new_x_preferred":[
        "\u0916\u0930\u0940"
    ],
    "name:pol_x_preferred":[
        "Khari"
    ],
    "wof:name":"Khari",
    "wof:placetype":"neighbourhood",
    "wof:population":384
},
  "geometry": {"coordinates":[87.77977199999999,25.941231],"type":"Point"}
}