{
  "type": "Feature",
  "properties": {
    "gn:admin1_code":"25.0",
    "gn:admin2_code":"604.0",
    "gn:asciiname":"Perianattam",
    "gn:country_code":"IN",
    "gn:dem":75,
    "gn:feature_class":"P",
    "gn:feature_code":"PPL",
    "gn:name":"Perianattam",
    "gn:population":0,
    "gn:timezone":"Asia/Kolkata",
    "iso:country":"IN",
    "ks:ks_name":"Periyanatham",
    "ks:ks_pop":362,
    "ks:ks_type":"HABITATION",
    "name:eng_x_preferred":[
        "Periyanatham"
    ],
    "name:eng_x_variant":[
        "Perianattam"
    ],
    "wof:name":"Periyanatham",
    "wof:placetype":"locality",
    "wof:population":362
},
  "geometry": {"coordinates":[79.74137399999999,12.779772],"type":"Point"}
}