{
  "type": "Feature",
  "properties": {
    "iso:country":"IN",
    "ks:ks_name":"Vadlavaripalle",
    "ks:ks_pop":220,
    "ks:ks_type":"HABITATION",
    "name:eng_x_preferred":[
        "Vadlavaripalle"
    ],
    "wof:name":"Vadlavaripalle",
    "wof:placetype":"locality",
    "wof:population":220
},
  "geometry": {"coordinates":[78.171308,14.460212],"type":"Point"}
}