{
  "type": "Feature",
  "properties": {
    "iso:country":"IN",
    "ks:ks_alt_nam":"TAL BORDER BAJ",
    "ks:ks_name":"Tal Border Baj",
    "ks:ks_pop":50,
    "ks:ks_type":"HABITATION",
    "name:eng_x_preferred":[
        "Tal Border Baj"
    ],
    "wof:name":"Tal Border Baj",
    "wof:placetype":"locality",
    "wof:population":50
},
  "geometry": {"coordinates":[75.04089500000001,17.020587],"type":"Point"}
}