{
  "type": "Feature",
  "properties": {
    "iso:country":"IN",
    "ks:ks_name":"Umarpur Nathan",
    "ks:ks_pop":994,
    "ks:ks_type":"VILLAGE",
    "ks:ks_uagg_main":0,
    "name:eng_x_preferred":[
        "Umarpur Nathan"
    ],
    "wof:name":"Umarpur Nathan",
    "wof:placetype":"neighbourhood",
    "wof:population":994
},
  "geometry": {"coordinates":[78.79128900000001,29.425859],"type":"Point"}
}