{
  "type": "Feature",
  "properties": {
    "gn:country":"IN",
    "gn:fcode":"PPL",
    "gn:pop":0,
    "iso:country":"IN",
    "name:unk_x_variant":[
        "Spitok"
    ],
    "qs:name":"Spituk",
    "qs:name_adm0":"India",
    "qs:name_adm1":"Jammu and Kashmir",
    "qs:photos":523,
    "qs:photos_1k":106,
    "qs:photos_9k":2,
    "qs:photos_9r":5,
    "qs:photos_all":523,
    "qs:photos_sr":7,
    "qs:placetype":"Town",
    "qs:pop_sr":"0",
    "wof:name":"Spituk",
    "wof:placetype":"locality",
    "wof:population":0
},
  "geometry": {"coordinates":[77.53604,34.13908],"type":"Point"}
}