{
  "type": "Feature",
  "properties": {
    "gn:admin1_code":"36.0",
    "gn:admin2_code":"133.0",
    "gn:asciiname":"Sikandarpur Kalan",
    "gn:country_code":"IN",
    "gn:dem":238,
    "gn:feature_class":"P",
    "gn:feature_code":"PPL",
    "gn:name":"Sikandarpur Kal\u0101n",
    "gn:population":0,
    "gn:timezone":"Asia/Kolkata",
    "iso:country":"IN",
    "ks:ks_name":"Sikandarpur Kalan",
    "ks:ks_pop":3648,
    "ks:ks_type":"VILLAGE",
    "ks:ks_uagg_main":0,
    "name:eng_x_preferred":[
        "Sikandarpur Kalan"
    ],
    "wof:name":"Sikandarpur Kalan",
    "wof:placetype":"neighbourhood",
    "wof:population":3648
},
  "geometry": {"coordinates":[77.658834,29.266891],"type":"Point"}
}