{
  "type": "Feature",
  "properties": {
    "iso:country":"IN",
    "ks:ks_name":"Dowerbond Grant",
    "ks:ks_pop":3185,
    "ks:ks_type":"HABITATION",
    "name:eng_x_preferred":[
        "Dowerbond Grant"
    ],
    "wof:name":"Dowerbond Grant",
    "wof:placetype":"locality",
    "wof:population":3185
},
  "geometry": {"coordinates":[92.71196500000001,24.629482],"type":"Point"}
}