{
  "type": "Feature",
  "properties": {
    "gn:admin1_code":"19.0",
    "gn:admin2_code":"571.0",
    "gn:asciiname":"Sabarupalya",
    "gn:country_code":"IN",
    "gn:dem":804,
    "gn:feature_class":"P",
    "gn:feature_code":"PPL",
    "gn:name":"S\u0101barup\u0101lya",
    "gn:population":0,
    "gn:timezone":"Asia/Kolkata",
    "iso:country":"IN",
    "wof:name":"Sabarupalya",
    "wof:placetype":"locality"
},
  "geometry": {"coordinates":[76.39949,13.36496],"type":"Point"}
}