{
  "type": "Feature",
  "properties": {
    "gn:admin1_code":"19.0",
    "gn:admin2_code":"571.0",
    "gn:asciiname":"Sabarupalya",
    "gn:country_code":"IN",
    "gn:dem":804,
    "gn:feature_class":"P",
    "gn:feature_code":"PPL",
    "gn:name":"S\u0101barup\u0101lya",
    "gn:population":0,
    "gn:timezone":"Asia/Kolkata",
    "iso:country":"IN",
    "ks:ks_name":"Sabarapalya",
    "ks:ks_pop":75,
    "ks:ks_type":"HABITATION",
    "name:eng_x_preferred":[
        "Sabarapalya"
    ],
    "name:eng_x_variant":[
        "Sabarupalya"
    ],
    "wof:name":"Sabarapalya",
    "wof:placetype":"locality",
    "wof:population":75
},
  "geometry": {"coordinates":[76.401788,13.358884],"type":"Point"}
}