{
  "type": "Feature",
  "properties": {
    "iso:country":"IN",
    "ks:ks_alt_nam":"SARAI KHEMA",
    "ks:ks_name":"Sarai Khema",
    "ks:ks_pop":3223,
    "ks:ks_type":"HABITATION",
    "name:eng_x_preferred":[
        "Sarai Khema"
    ],
    "wof:name":"Sarai Khema",
    "wof:placetype":"locality",
    "wof:population":3223
},
  "geometry": {"coordinates":[81.81829500000001,26.192534],"type":"Point"}
}