{
  "type": "Feature",
  "properties": {
    "gn:country":"IN",
    "gn:fcode":"PPL",
    "gn:pop":12591,
    "iso:country":"IN",
    "name:bpy_x_preferred":[
        "\u09ae\u09be\u09b2\u0995\u09c7\u09b0\u09be"
    ],
    "name:bul_x_preferred":[
        "\u041c\u0430\u043b\u043a\u0435\u0440\u0430"
    ],
    "name:chi_x_preferred":[
        "\u9a6c\u5c14\u51ef\u62c9"
    ],
    "name:dut_x_preferred":[
        "Malkera"
    ],
    "name:eng_x_preferred":[
        "Malkera"
    ],
    "name:fre_x_preferred":[
        "Malkera"
    ],
    "name:ita_x_preferred":[
        "Malkera"
    ],
    "name:may_x_preferred":[
        "Malkera"
    ],
    "name:nan_x_preferred":[
        "Malkera"
    ],
    "name:new_x_preferred":[
        "\u092e\u0932\u094d\u0915\u0947\u0930\u093e"
    ],
    "name:por_x_preferred":[
        "Malkera"
    ],
    "name:swe_x_preferred":[
        "Malkera"
    ],
    "name:vie_x_preferred":[
        "Malkera"
    ],
    "qs:name":"Malkera",
    "qs:name_adm0":"India",
    "qs:name_adm1":"Jharkhand",
    "qs:photos_9r":0,
    "qs:photos_sr":0,
    "qs:placetype":"Town",
    "qs:pop_sr":"6",
    "wd:wordcount":347,
    "wof:name":"Malkera",
    "wof:placetype":"locality",
    "wof:population":12591
},
  "geometry": {"coordinates":[86.28767000000001,23.78212],"type":"Point"}
}