{
  "type": "Feature",
  "properties": {
    "iso:country":"IN",
    "ks:ks_name":"Ezhamthala",
    "ks:ks_pop":49,
    "ks:ks_type":"HABITATION",
    "name:eng_x_preferred":[
        "Ezhamthala"
    ],
    "wof:name":"Ezhamthala",
    "wof:placetype":"locality",
    "wof:population":49
},
  "geometry": {"coordinates":[76.971142,9.239878],"type":"Point"}
}