{
  "type": "Feature",
  "properties": {
    "iso:country":"IN",
    "ks:ks_name":"Satasi Chak",
    "ks:ks_pop":0,
    "ks:ks_type":"VILLAGE",
    "name:eng_x_preferred":[
        "Satasi Chak"
    ],
    "wof:name":"Satasi Chak",
    "wof:placetype":"locality",
    "wof:population":0
},
  "geometry": {"coordinates":[84.973367,25.291828],"type":"Point"}
}