{
  "type": "Feature",
  "properties": {
    "gn:admin1_code":"35",
    "gn:admin2_code":"446.0",
    "gn:asciiname":"Chora Kamraura",
    "gn:country_code":"IN",
    "gn:dem":415,
    "gn:feature_class":"P",
    "gn:feature_code":"PPL",
    "gn:name":"Chora Kamraura",
    "gn:population":0,
    "gn:timezone":"Asia/Kolkata",
    "iso:country":"IN",
    "ks:ks_alt_nam":"Choura kamrora",
    "ks:ks_name":"Choura Kamrora",
    "ks:ks_pop":1519,
    "ks:ks_type":"HABITATION",
    "name:eng_x_preferred":[
        "Choura Kamrora"
    ],
    "name:eng_x_variant":[
        "Chora Kamraura"
    ],
    "wof:name":"Choura Kamrora",
    "wof:placetype":"locality",
    "wof:population":1519
},
  "geometry": {"coordinates":[78.12109,23.188932],"type":"Point"}
}