{
  "type": "Feature",
  "properties": {
    "iso:country":"IN",
    "name:eng_x_preferred":[
        "Wadala"
    ],
    "name:eng_x_variant":[
        "Bombay Wadala",
        "Wadala Village",
        "Yadala"
    ],
    "name:jpn_x_preferred":[
        "\u30ef\u30c0\u30e9"
    ],
    "name:mar_x_preferred":[
        "\u0935\u0921\u093e\u0933\u093e"
    ],
    "name:por_x_preferred":[
        "Vadala"
    ],
    "name:urd_x_preferred":[
        "\u0648\u0688\u0627\u0644\u0627"
    ],
    "name:zho_x_preferred":[
        "\u74e6\u9054\u62c9"
    ],
    "qs:gn_adm0_cc":"IN",
    "qs:gn_fcode":"PPLX",
    "qs:gn_local":1275339,
    "qs:gn_namadm1":"16",
    "qs:gn_name":"Wadala",
    "qs:local_max":3819,
    "qs:local_sum":50908,
    "qs:localhoods":70,
    "qs:name":"Wadala",
    "qs:name_adm0":"India",
    "qs:name_adm1":"Maharashtra",
    "qs:name_adm2":"Mumbai",
    "qs:name_local":"Mumbai",
    "qs:photo_max":73,
    "qs:photo_sum":129,
    "qs:placetype":"Suburb",
    "qs:quad_count":10,
    "qs:woe_adm0":23424848,
    "qs:woe_adm1":2345750,
    "qs:woe_adm2":12586539,
    "qs:woe_lau":0,
    "qs:woe_local":2295411,
    "qs:woe_ver":"7.10.0",
    "wd:wordcount":1815,
    "wof:lang":[
        "eng"
    ],
    "wof:name":"Wadala",
    "wof:placetype":"neighbourhood"
},
  "geometry": {"coordinates":[72.86004200000001,19.01159],"type":"Point"}
}