{
  "type": "Feature",
  "properties": {
    "iso:country":"IN",
    "ks:ks_name":"Hat Pilkhandi",
    "ks:ks_pop":1386,
    "ks:ks_type":"VILLAGE",
    "ks:ks_uagg_main":0,
    "name:eng_x_preferred":[
        "Hat Pilkhandi"
    ],
    "wof:name":"Hat Pilkhandi",
    "wof:placetype":"neighbourhood",
    "wof:population":1386
},
  "geometry": {"coordinates":[88.12066299999999,23.776851],"type":"Point"}
}