{
  "type": "Feature",
  "properties": {
    "iso:country":"IN",
    "ks:ks_name":"Rangabhita",
    "ks:ks_pop":4423,
    "ks:ks_type":"URBAN",
    "ks:ks_uagg_main":0,
    "name:eng_x_preferred":[
        "Rangabhita"
    ],
    "wof:name":"Rangabhita",
    "wof:placetype":"neighbourhood",
    "wof:population":4423
},
  "geometry": {"coordinates":[88.18593,25.209183],"type":"Point"}
}