{
  "type": "Feature",
  "properties": {
    "gn:admin1_code":"24",
    "gn:admin2_code":"123.0",
    "gn:asciiname":"Kari",
    "gn:country_code":"IN",
    "gn:dem":610,
    "gn:feature_class":"P",
    "gn:feature_code":"PPL",
    "gn:name":"K\u0101ri",
    "gn:population":0,
    "gn:timezone":"Asia/Kolkata",
    "iso:country":"IN",
    "name:ben_x_preferred":[
        "\u0995\u09be\u09b0\u09bf"
    ],
    "name:bpy_x_preferred":[
        "\u0995\u09be\u09b0\u09bf"
    ],
    "name:bul_x_preferred":[
        "\u041a\u044a\u0440\u0438"
    ],
    "name:ceb_x_preferred":[
        "Kari"
    ],
    "name:ces_x_preferred":[
        "Kari"
    ],
    "name:deu_x_preferred":[
        "Kari"
    ],
    "name:fin_x_preferred":[
        "Kari"
    ],
    "name:fra_x_preferred":[
        "Kari"
    ],
    "name:ita_x_preferred":[
        "Kari"
    ],
    "name:new_x_preferred":[
        "\u0915\u093e\u0930\u0940"
    ],
    "name:nld_x_preferred":[
        "Kari"
    ],
    "name:pol_x_preferred":[
        "Kari"
    ],
    "name:slk_x_preferred":[
        "Kari"
    ],
    "name:slv_x_preferred":[
        "Kari"
    ],
    "name:spa_x_preferred":[
        "Kari"
    ],
    "name:swe_x_preferred":[
        "Kari"
    ],
    "wof:name":"Kari",
    "wof:placetype":"neighbourhood"
},
  "geometry": {"coordinates":[73.98457000000001,25.61314],"type":"Point"}
}