{
  "type": "Feature",
  "properties": {
    "iso:country":"IN",
    "ks:ks_name":"Ed Sindari",
    "ks:ks_pop":1734,
    "ks:ks_type":"VILLAGE",
    "name:eng_x_preferred":[
        "Ed Sindari"
    ],
    "wof:name":"Ed Sindari",
    "wof:placetype":"locality",
    "wof:population":1734
},
  "geometry": {"coordinates":[71.859056,25.541244],"type":"Point"}
}