{
  "type": "Feature",
  "properties": {
    "iso:country":"IN",
    "ks:ks_name":"Langhin Bazar Bl 1",
    "ks:ks_pop":947,
    "ks:ks_type":"HABITATION",
    "ks:ks_uagg_main":0,
    "name:eng_x_preferred":[
        "Langhin Bazar Bl 1"
    ],
    "wof:name":"Langhin Bazar Bl 1",
    "wof:placetype":"neighbourhood",
    "wof:population":947
},
  "geometry": {"coordinates":[93.12955100000001,26.203515],"type":"Point"}
}