{
  "type": "Feature",
  "properties": {
    "iso:country":"IN",
    "ks:ks_name":"Ramdiri",
    "ks:ks_pop":4723,
    "ks:ks_type":"VILLAGE",
    "name:eng_x_preferred":[
        "Ramdiri"
    ],
    "wof:name":"Ramdiri",
    "wof:placetype":"locality",
    "wof:population":4723
},
  "geometry": {"coordinates":[86.066187,25.417829],"type":"Point"}
}