{
  "type": "Feature",
  "properties": {
    "iso:country":"IN",
    "ks:ks_name":"Sita Ram Ka Purwa",
    "ks:ks_pop":105,
    "ks:ks_type":"HABITATION",
    "ks:ks_uagg_main":0,
    "name:eng_x_preferred":[
        "Sita Ram Ka Purwa"
    ],
    "wof:name":"Sita Ram Ka Purwa",
    "wof:placetype":"neighbourhood",
    "wof:population":105
},
  "geometry": {"coordinates":[82.24653600000001,26.413477],"type":"Point"}
}