{
  "type": "Feature",
  "properties": {
    "gn:admin1_code":"25.0",
    "gn:admin2_code":"607.0",
    "gn:asciiname":"Maruderi",
    "gn:country_code":"IN",
    "gn:dem":68,
    "gn:feature_class":"P",
    "gn:feature_code":"PPL",
    "gn:name":"Maruderi",
    "gn:population":0,
    "gn:timezone":"Asia/Kolkata",
    "iso:country":"IN",
    "ks:ks_name":"Maruderi",
    "ks:ks_type":"VILLAGE",
    "name:eng_x_preferred":[
        "Maruderi"
    ],
    "wof:name":"Maruderi",
    "wof:placetype":"locality"
},
  "geometry": {"coordinates":[79.518862,12.244154],"type":"Point"}
}