{
  "type": "Feature",
  "properties": {
    "iso:country":"IN",
    "ks:ks_name":"Vengallullathara",
    "ks:ks_pop":1946,
    "ks:ks_type":"HABITATION",
    "name:eng_x_preferred":[
        "Vengallullathara"
    ],
    "wof:name":"Vengallullathara",
    "wof:placetype":"locality",
    "wof:population":1946
},
  "geometry": {"coordinates":[75.740968,11.704105],"type":"Point"}
}