{
  "type": "Feature",
  "properties": {
    "gn:admin1_code":"25.0",
    "gn:admin2_code":"604.0",
    "gn:asciiname":"Ammanambakkam",
    "gn:country_code":"IN",
    "gn:dem":41,
    "gn:feature_class":"P",
    "gn:feature_code":"PPL",
    "gn:name":"Ammanamb\u0101kkam",
    "gn:population":0,
    "gn:timezone":"Asia/Kolkata",
    "iso:country":"IN",
    "wof:name":"Ammanambakkam",
    "wof:placetype":"locality"
},
  "geometry": {"coordinates":[79.99554999999999,12.69869],"type":"Point"}
}