{
  "type": "Feature",
  "properties": {
    "iso:country":"IN",
    "ks:ks_name":"Mohudi",
    "ks:ks_pop":737,
    "ks:ks_type":"VILLAGE",
    "name:eng_x_preferred":[
        "Mohudi"
    ],
    "wof:name":"Mohudi",
    "wof:placetype":"locality",
    "wof:population":737
},
  "geometry": {"coordinates":[74.795281,22.829061],"type":"Point"}
}