{
  "type": "Feature",
  "properties": {
    "iso:country":"IN",
    "ks:ks_alt_nam":"Mozabari Ghop para",
    "ks:ks_name":"Mozabari Ghop Para",
    "ks:ks_pop":225,
    "ks:ks_type":"HABITATION",
    "name:eng_x_preferred":[
        "Mozabari Ghop Para"
    ],
    "wof:name":"Mozabari Ghop Para",
    "wof:placetype":"locality",
    "wof:population":225
},
  "geometry": {"coordinates":[90.387384,26.538258],"type":"Point"}
}