{
  "type": "Feature",
  "properties": {
    "gn:admin1_code":"16.0",
    "gn:admin2_code":"520",
    "gn:asciiname":"Zirad",
    "gn:country_code":"IN",
    "gn:dem":21,
    "gn:feature_class":"P",
    "gn:feature_code":"PPL",
    "gn:name":"Z\u012brad",
    "gn:population":0,
    "gn:timezone":"Asia/Kolkata",
    "iso:country":"IN",
    "wof:name":"Zirad",
    "wof:placetype":"locality"
},
  "geometry": {"coordinates":[72.89,18.75472],"type":"Point"}
}