{
  "type": "Feature",
  "properties": {
    "iso:country":"IN",
    "ks:ks_name":"Parashiya",
    "ks:ks_pop":152,
    "ks:ks_type":"VILLAGE",
    "name:eng_x_preferred":[
        "Parashiya"
    ],
    "wof:name":"Parashiya",
    "wof:placetype":"locality",
    "wof:population":152
},
  "geometry": {"coordinates":[86.74180200000001,22.273641],"type":"Point"}
}