{
  "type": "Feature",
  "properties": {
    "iso:country":"IN",
    "ks:ks_name":"Kuttagam",
    "ks:ks_pop":258,
    "ks:ks_type":"VILLAGE",
    "name:eng_x_preferred":[
        "Kuttagam"
    ],
    "wof:name":"Kuttagam",
    "wof:placetype":"locality",
    "wof:population":258
},
  "geometry": {"coordinates":[77.218407,11.336031],"type":"Point"}
}