{
  "type": "Feature",
  "properties": {
    "iso:country":"IN",
    "ks:ks_name":"Denganaka",
    "ks:ks_pop":17,
    "ks:ks_type":"VILLAGE",
    "name:eng_x_preferred":[
        "Denganaka"
    ],
    "wof:name":"Denganaka",
    "wof:placetype":"locality",
    "wof:population":17
},
  "geometry": {"coordinates":[83.505212,19.894065],"type":"Point"}
}