{
  "type": "Feature",
  "properties": {
    "gn:admin1_code":"21.0",
    "gn:admin2_code":"396.0",
    "gn:asciiname":"Badu",
    "gn:country_code":"IN",
    "gn:dem":424,
    "gn:feature_class":"P",
    "gn:feature_code":"PPL",
    "gn:name":"Badu",
    "gn:population":0,
    "gn:timezone":"Asia/Kolkata",
    "iso:country":"IN",
    "name:ceb_x_preferred":[
        "Badu"
    ],
    "name:deu_x_preferred":[
        "Badu"
    ],
    "name:fra_x_preferred":[
        "Badu"
    ],
    "name:rus_x_preferred":[
        "\u0411\u0430\u0434\u0443"
    ],
    "name:swe_x_preferred":[
        "Badu"
    ],
    "wof:name":"Badu",
    "wof:placetype":"locality"
},
  "geometry": {"coordinates":[83.66669,19.30075],"type":"Point"}
}