{
  "type": "Feature",
  "properties": {
    "gn:admin1_code":"16.0",
    "gn:admin2_code":"497.0",
    "gn:asciiname":"Paula",
    "gn:country_code":"IN",
    "gn:dem":375,
    "gn:feature_class":"P",
    "gn:feature_code":"PPL",
    "gn:name":"Paula",
    "gn:population":0,
    "gn:timezone":"Asia/Kolkata",
    "iso:country":"IN",
    "name:cat_x_preferred":[
        "Paula"
    ],
    "name:ceb_x_preferred":[
        "Paula"
    ],
    "name:deu_x_preferred":[
        "Paula"
    ],
    "name:fra_x_preferred":[
        "Paula"
    ],
    "name:heb_x_preferred":[
        "\u05e4\u05d0\u05d5\u05dc\u05d4"
    ],
    "name:ita_x_preferred":[
        "Paula"
    ],
    "name:jpn_x_preferred":[
        "\u30dd\u30fc\u30e9"
    ],
    "name:por_x_preferred":[
        "Paula"
    ],
    "name:spa_x_preferred":[
        "Paula"
    ],
    "name:swe_x_preferred":[
        "Paula"
    ],
    "name:tha_x_preferred":[
        "\u0e1e\u0e2d\u0e25\u0e25\u0e32"
    ],
    "wof:name":"Paula",
    "wof:placetype":"locality"
},
  "geometry": {"coordinates":[74.03242,21.88773],"type":"Point"}
}