{
  "type": "Feature",
  "properties": {
    "iso:country":"IN",
    "ks:ks_alt_nam":"sewatari",
    "ks:ks_name":"Sewatari",
    "ks:ks_pop":420,
    "ks:ks_type":"HABITATION",
    "name:eng_x_preferred":[
        "Sewatari"
    ],
    "wof:name":"Sewatari",
    "wof:placetype":"locality",
    "wof:population":420
},
  "geometry": {"coordinates":[82.389163,22.350228],"type":"Point"}
}