{
  "type": "Feature",
  "properties": {
    "gn:admin1_code":"2.0",
    "gn:admin2_code":"554.0",
    "gn:asciiname":"Muppireddivaripalli",
    "gn:country_code":"IN",
    "gn:dem":499,
    "gn:feature_class":"P",
    "gn:feature_code":"PPL",
    "gn:name":"Muppireddiv\u0101ripalli",
    "gn:population":0,
    "gn:timezone":"Asia/Kolkata",
    "iso:country":"IN",
    "wof:name":"Muppireddivaripalli",
    "wof:placetype":"locality"
},
  "geometry": {"coordinates":[79.02996,13.68622],"type":"Point"}
}