{
  "type": "Feature",
  "properties": {
    "iso:country":"IN",
    "ks:ks_name":"Dhanora",
    "ks:ks_pop":280,
    "ks:ks_type":"VILLAGE",
    "name:eng_x_preferred":[
        "Dhanora"
    ],
    "wof:name":"Dhanora",
    "wof:placetype":"locality",
    "wof:population":280
},
  "geometry": {"coordinates":[70.99100300000001,25.632189],"type":"Point"}
}