{
  "type": "Feature",
  "properties": {
    "iso:country":"IN",
    "ks:ks_alt_nam":"HARIZON TOLA",
    "ks:ks_name":"Harizon Tola",
    "ks:ks_pop":709,
    "ks:ks_type":"HABITATION",
    "ks:ks_uagg_main":0,
    "name:eng_x_preferred":[
        "Harizon Tola"
    ],
    "wof:name":"Harizon Tola",
    "wof:placetype":"neighbourhood",
    "wof:population":709
},
  "geometry": {"coordinates":[85.920789,25.52673],"type":"Point"}
}