{
  "type": "Feature",
  "properties": {
    "iso:country":"IN",
    "ks:ks_alt_nam":"thammemane",
    "ks:ks_name":"Thammemane",
    "ks:ks_pop":63,
    "ks:ks_type":"HABITATION",
    "name:eng_x_preferred":[
        "Thammemane"
    ],
    "wof:name":"Thammemane",
    "wof:placetype":"locality",
    "wof:population":63
},
  "geometry": {"coordinates":[75.10284799999999,13.62659],"type":"Point"}
}