{
  "type": "Feature",
  "properties": {
    "iso:country":"IN",
    "ks:ks_name":"Jamdapal",
    "ks:ks_pop":418,
    "ks:ks_type":"VILLAGE",
    "name:eng_x_preferred":[
        "Jamdapal"
    ],
    "wof:name":"Jamdapal",
    "wof:placetype":"locality",
    "wof:population":418
},
  "geometry": {"coordinates":[86.712281,21.858142],"type":"Point"}
}