{
  "type": "Feature",
  "properties": {
    "iso:country":"IN",
    "ks:ks_name":"Ranipokhari",
    "ks:ks_pop":418,
    "ks:ks_type":"VILLAGE",
    "name:eng_x_preferred":[
        "Ranipokhari"
    ],
    "wof:name":"Ranipokhari",
    "wof:placetype":"locality",
    "wof:population":418
},
  "geometry": {"coordinates":[86.08741000000001,20.641968],"type":"Point"}
}