{
  "type": "Feature",
  "properties": {
    "iso:country":"IN",
    "ks:ks_name":"Chhoto Palasi",
    "ks:ks_pop":237,
    "ks:ks_type":"HABITATION",
    "ks:ks_uagg_main":0,
    "name:eng_x_preferred":[
        "Chhoto Palasi"
    ],
    "wof:name":"Chhoto Palasi",
    "wof:placetype":"neighbourhood",
    "wof:population":237
},
  "geometry": {"coordinates":[87.05754399999999,22.503864],"type":"Point"}
}