{
  "type": "Feature",
  "properties": {
    "gn:admin1_code":"13.0",
    "gn:admin2_code":"599.0",
    "gn:asciiname":"Angadikkal Tekkekara",
    "gn:country_code":"IN",
    "gn:dem":44,
    "gn:feature_class":"P",
    "gn:feature_code":"PPL",
    "gn:name":"Ang\u0101dikkal Tekkekara",
    "gn:population":0,
    "gn:timezone":"Asia/Kolkata",
    "iso:country":"IN",
    "wof:name":"Angadikkal Tekkekara",
    "wof:placetype":"locality"
},
  "geometry": {"coordinates":[76.78416,9.19623],"type":"Point"}
}