{
  "type": "Feature",
  "properties": {
    "iso:country":"IN",
    "ks:ks_name":"Kiridivalasa",
    "ks:ks_pop":61,
    "ks:ks_type":"HABITATION",
    "name:eng_x_preferred":[
        "Kiridivalasa"
    ],
    "wof:name":"Kiridivalasa",
    "wof:placetype":"locality",
    "wof:population":61
},
  "geometry": {"coordinates":[83.88613599999999,18.659434],"type":"Point"}
}