{
  "type": "Feature",
  "properties": {
    "iso:country":"IN",
    "ks:ks_name":"Jatauli",
    "ks:ks_type":"VILLAGE",
    "ks:ks_uagg_main":0,
    "name:eng_x_preferred":[
        "Jatauli"
    ],
    "wof:name":"Jatauli",
    "wof:placetype":"neighbourhood"
},
  "geometry": {"coordinates":[77.693591,29.040816],"type":"Point"}
}