{
  "type": "Feature",
  "properties": {
    "iso:country":"IN",
    "ks:ks_name":"Kanhasagar",
    "ks:ks_pop":307,
    "ks:ks_type":"HABITATION",
    "name:eng_x_preferred":[
        "Kanhasagar"
    ],
    "wof:name":"Kanhasagar",
    "wof:placetype":"locality",
    "wof:population":307
},
  "geometry": {"coordinates":[79.156988,21.850254],"type":"Point"}
}