{
  "type": "Feature",
  "properties": {
    "iso:country":"IN",
    "ks:ks_name":"Paschim Sangapara",
    "ks:ks_pop":921,
    "ks:ks_type":"VILLAGE",
    "name:eng_x_preferred":[
        "Paschim Sangapara"
    ],
    "wof:name":"Paschim Sangapara",
    "wof:placetype":"locality",
    "wof:population":921
},
  "geometry": {"coordinates":[88.714568,26.658604],"type":"Point"}
}