{
  "type": "Feature",
  "properties": {
    "gn:admin1_code":"16.0",
    "gn:admin2_code":"525.0",
    "gn:asciiname":"Pawarwari",
    "gn:country_code":"IN",
    "gn:dem":669,
    "gn:feature_class":"P",
    "gn:feature_code":"PPL",
    "gn:name":"Paw\u0101rw\u0101ri",
    "gn:population":0,
    "gn:timezone":"Asia/Kolkata",
    "iso:country":"IN",
    "wof:name":"Pawarwari",
    "wof:placetype":"locality"
},
  "geometry": {"coordinates":[76.09522,18.27716],"type":"Point"}
}