{
  "type": "Feature",
  "properties": {
    "gn:admin1_code":"25.0",
    "gn:admin2_code":"605.0",
    "gn:asciiname":"Hodsonpettai",
    "gn:country_code":"IN",
    "gn:dem":407,
    "gn:feature_class":"P",
    "gn:feature_code":"PPL",
    "gn:name":"Hodsonpettai",
    "gn:population":0,
    "gn:timezone":"Asia/Kolkata",
    "iso:country":"IN",
    "wof:name":"Hodsonpettai",
    "wof:placetype":"locality"
},
  "geometry": {"coordinates":[78.57488000000002,12.57787],"type":"Point"}
}