{
  "type": "Feature",
  "properties": {
    "gn:admin1_code":"23.0",
    "gn:admin2_code":"49.0",
    "gn:asciiname":"Dande",
    "gn:country_code":"IN",
    "gn:dem":221,
    "gn:feature_class":"P",
    "gn:feature_code":"PPL",
    "gn:name":"Dande",
    "gn:population":0,
    "gn:timezone":"Asia/Kolkata",
    "iso:country":"IN",
    "name:cat_x_preferred":[
        "Dande"
    ],
    "name:deu_x_preferred":[
        "Dande"
    ],
    "name:frr_x_preferred":[
        "Dande"
    ],
    "name:ita_x_preferred":[
        "Dande"
    ],
    "name:por_x_preferred":[
        "Dande"
    ],
    "wof:name":"Dande",
    "wof:placetype":"locality"
},
  "geometry": {"coordinates":[74.6104,31.61714000000001],"type":"Point"}
}