{
  "type": "Feature",
  "properties": {
    "iso:country":"IN",
    "ks:ks_name":"Rimapara",
    "ks:ks_pop":305,
    "ks:ks_type":"HABITATION",
    "name:eng_x_preferred":[
        "Rimapara"
    ],
    "wof:name":"Rimapara",
    "wof:placetype":"locality",
    "wof:population":305
},
  "geometry": {"coordinates":[81.372342,18.584237],"type":"Point"}
}