{
  "type": "Feature",
  "properties": {
    "iso:country":"IN",
    "ks:ks_name":"Tashuli",
    "ks:ks_pop":994,
    "ks:ks_type":"VILLAGE",
    "name:eng_x_preferred":[
        "Tashuli"
    ],
    "wof:name":"Tashuli",
    "wof:placetype":"locality",
    "wof:population":994
},
  "geometry": {"coordinates":[87.569875,23.268867],"type":"Point"}
}