{
  "type": "Feature",
  "properties": {
    "iso:country":"IN",
    "ks:ks_name":"Jora Hunhe Alias Jora",
    "ks:ks_pop":496,
    "ks:ks_type":"VILLAGE",
    "ks:ks_uagg_main":0,
    "name:eng_x_preferred":[
        "Jora Hunhe Alias Jora"
    ],
    "wof:name":"Jora Hunhe Alias Jora",
    "wof:placetype":"neighbourhood",
    "wof:population":496
},
  "geometry": {"coordinates":[84.258741,23.91911],"type":"Point"}
}