{
  "type": "Feature",
  "properties": {
    "gn:admin1_code":"36",
    "gn:admin2_code":"157.0",
    "gn:asciiname":"Ambar Khera",
    "gn:country_code":"IN",
    "gn:dem":131,
    "gn:feature_class":"P",
    "gn:feature_code":"PPL",
    "gn:name":"Ambar Khera",
    "gn:population":0,
    "gn:timezone":"Asia/Kolkata",
    "iso:country":"IN",
    "ks:ks_name":"Amber Khera",
    "ks:ks_pop":558,
    "ks:ks_type":"HABITATION",
    "ks:ks_uagg_main":0,
    "name:eng_x_preferred":[
        "Amber Khera"
    ],
    "wof:name":"Amber Khera",
    "wof:placetype":"neighbourhood",
    "wof:population":558
},
  "geometry": {"coordinates":[80.652303,27.024566],"type":"Point"}
}