{
  "type": "Feature",
  "properties": {
    "iso:country":"IN",
    "ks:ks_name":"Rukunibori",
    "ks:ks_pop":65,
    "ks:ks_type":"VILLAGE",
    "name:eng_x_preferred":[
        "Rukunibori"
    ],
    "wof:name":"Rukunibori",
    "wof:placetype":"locality",
    "wof:population":65
},
  "geometry": {"coordinates":[83.481126,19.838795],"type":"Point"}
}