{
  "type": "Feature",
  "properties": {
    "iso:country":"IN",
    "ks:ks_name":"Tukra No.3",
    "ks:ks_pop":0,
    "ks:ks_type":"VILLAGE",
    "name:eng_x_preferred":[
        "Tukra No.3"
    ],
    "wof:name":"Tukra No.3",
    "wof:placetype":"locality",
    "wof:population":0
},
  "geometry": {"coordinates":[75.282601,31.481278],"type":"Point"}
}