{
  "type": "Feature",
  "properties": {
    "iso:country":"IN",
    "ks:ks_alt_nam":"SABAR BASTI PARA",
    "ks:ks_name":"Sabar Basti Para",
    "ks:ks_pop":151,
    "ks:ks_type":"HABITATION",
    "name:eng_x_preferred":[
        "Sabar Basti Para"
    ],
    "wof:name":"Sabar Basti Para",
    "wof:placetype":"locality",
    "wof:population":151
},
  "geometry": {"coordinates":[91.660399,24.121267],"type":"Point"}
}