{
  "type": "Feature",
  "properties": {
    "gn:admin1_code":"35.0",
    "gn:admin2_code":"439.0",
    "gn:asciiname":"Bargaon",
    "gn:country_code":"IN",
    "gn:dem":618,
    "gn:feature_class":"P",
    "gn:feature_code":"PPL",
    "gn:name":"Bargaon",
    "gn:population":0,
    "gn:timezone":"Asia/Kolkata",
    "iso:country":"IN",
    "ks:ks_name":"Badgaon",
    "ks:ks_pop":208,
    "ks:ks_type":"HABITATION",
    "name:eng_x_preferred":[
        "Badgaon"
    ],
    "name:eng_x_variant":[
        "Bargaon"
    ],
    "wof:name":"Badgaon",
    "wof:placetype":"locality",
    "wof:population":208
},
  "geometry": {"coordinates":[75.65534,22.431851],"type":"Point"}
}