{
  "type": "Feature",
  "properties": {
    "gn:admin1_code":"34.0",
    "gn:admin2_code":"204.0",
    "gn:asciiname":"Nauka",
    "gn:country_code":"IN",
    "gn:dem":71,
    "gn:feature_class":"P",
    "gn:feature_code":"PPL",
    "gn:name":"Nauka",
    "gn:population":0,
    "gn:timezone":"Asia/Kolkata",
    "iso:country":"IN",
    "name:jpn_x_preferred":[
        "\u30ca\u30a6\u30ab"
    ],
    "name:rus_x_preferred":[
        "\u041d\u0430\u0443\u043a\u0430"
    ],
    "name:ukr_x_preferred":[
        "\u041d\u0430\u0443\u043a\u0430"
    ],
    "wof:name":"Nauka",
    "wof:placetype":"neighbourhood"
},
  "geometry": {"coordinates":[84.8359,26.57386],"type":"Point"}
}