{
  "type": "Feature",
  "properties": {
    "gn:admin1_code":"24",
    "gn:admin2_code":"119.0",
    "gn:asciiname":"Rupangarh",
    "gn:country_code":"IN",
    "gn:dem":399,
    "gn:feature_class":"P",
    "gn:feature_code":"PPL",
    "gn:name":"R\u016bpangarh",
    "gn:population":0,
    "gn:timezone":"Asia/Kolkata",
    "iso:country":"IN",
    "name:und_x_variant":[
        "R\u016bpangarh",
        "R\u016bpnagar"
    ],
    "wof:name":"Rupangarh",
    "wof:placetype":"neighbourhood"
},
  "geometry": {"coordinates":[74.85157,26.79612],"type":"Point"}
}