{
  "type": "Feature",
  "properties": {
    "gn:admin1_code":"35.0",
    "gn:admin2_code":"455.0",
    "gn:asciiname":"Jaithari",
    "gn:country_code":"IN",
    "gn:dem":775,
    "gn:feature_class":"P",
    "gn:feature_code":"PPL",
    "gn:name":"Jaith\u0101ri",
    "gn:population":0,
    "gn:timezone":"Asia/Kolkata",
    "iso:country":"IN",
    "name:ben_x_preferred":[
        "\u099c\u09af\u09bc\u09a5\u09be\u09b0\u09bf"
    ],
    "name:bpy_x_preferred":[
        "\u099c\u09af\u09bc\u09a5\u09be\u09b0\u09bf"
    ],
    "name:ind_x_preferred":[
        "Jaithari"
    ],
    "name:ita_x_preferred":[
        "Jaithari"
    ],
    "name:msa_x_preferred":[
        "Jaithari"
    ],
    "name:new_x_preferred":[
        "\u091c\u092f\u0925\u0930\u0940"
    ],
    "name:nld_x_preferred":[
        "Jaithari"
    ],
    "name:por_x_preferred":[
        "Jaithari"
    ],
    "name:urd_x_preferred":[
        "\u062c\u06cc\u0679\u06be\u0691\u06cc"
    ],
    "name:vie_x_preferred":[
        "Jaithari"
    ],
    "name:zho_x_preferred":[
        "\u8d3e\u4f0a\u5854\u91cc"
    ],
    "wof:name":"Jaithari",
    "wof:placetype":"locality"
},
  "geometry": {"coordinates":[78.86129,22.15376],"type":"Point"}
}