{
  "type": "Feature",
  "properties": {
    "iso:country":"IN",
    "ks:ks_name":"Ganjhutoli",
    "ks:ks_pop":122,
    "ks:ks_type":"HABITATION",
    "name:eng_x_preferred":[
        "Ganjhutoli"
    ],
    "wof:name":"Ganjhutoli",
    "wof:placetype":"locality",
    "wof:population":122
},
  "geometry": {"coordinates":[84.335396,22.467875],"type":"Point"}
}