{
  "type": "Feature",
  "properties": {
    "iso:country":"IN",
    "ks:ks_name":"Metkar Wasti",
    "ks:ks_pop":210,
    "ks:ks_type":"HABITATION",
    "name:eng_x_preferred":[
        "Metkar Wasti"
    ],
    "wof:name":"Metkar Wasti",
    "wof:placetype":"locality",
    "wof:population":210
},
  "geometry": {"coordinates":[75.44923199999999,17.334909],"type":"Point"}
}