{
  "type": "Feature",
  "properties": {
    "iso:country":"IN",
    "ks:ks_name":"Ambajati",
    "ks:ks_pop":466,
    "ks:ks_type":"VILLAGE",
    "name:eng_x_preferred":[
        "Ambajati"
    ],
    "wof:name":"Ambajati",
    "wof:placetype":"locality",
    "wof:population":466
},
  "geometry": {"coordinates":[73.598271,22.87933],"type":"Point"}
}