{
  "type": "Feature",
  "properties": {
    "iso:country":"IN",
    "ks:ks_name":"Malka Khedi",
    "ks:ks_pop":37,
    "ks:ks_type":"VILLAGE",
    "name:eng_x_preferred":[
        "Malka Khedi"
    ],
    "wof:name":"Malka Khedi",
    "wof:placetype":"locality",
    "wof:population":37
},
  "geometry": {"coordinates":[77.329454,22.494128],"type":"Point"}
}