{
  "type": "Feature",
  "properties": {
    "gn:admin1_code":"9.0",
    "gn:admin2_code":"484.0",
    "gn:asciiname":"Lavana",
    "gn:country_code":"IN",
    "gn:dem":153,
    "gn:feature_class":"P",
    "gn:feature_code":"PPL",
    "gn:name":"Lav\u0101na",
    "gn:population":0,
    "gn:timezone":"Asia/Kolkata",
    "iso:country":"IN",
    "ks:ks_alt_nam":"Lav\u0101na",
    "ks:ks_name":"Lavana",
    "ks:ks_pop":1204,
    "ks:ks_type":"VILLAGE",
    "name:eng_x_preferred":[
        "Lavana"
    ],
    "name:eng_x_variant":[
        "Lav\u0101na"
    ],
    "wof:name":"Lavana",
    "wof:placetype":"locality",
    "wof:population":1204
},
  "geometry": {"coordinates":[73.571924,23.328839],"type":"Point"}
}