{
  "type": "Feature",
  "properties": {
    "gn:admin1_code":"11.0",
    "gn:asciiname":"Pipalwali",
    "gn:country_code":"IN",
    "gn:dem":530,
    "gn:feature_class":"P",
    "gn:feature_code":"PPL",
    "gn:name":"P\u012bpalw\u0101li",
    "gn:population":0,
    "gn:timezone":"Asia/Kolkata",
    "iso:country":"IN",
    "wof:name":"Pipalwali",
    "wof:placetype":"locality"
},
  "geometry": {"coordinates":[77.16063,30.61728],"type":"Point"}
}