{
  "type": "Feature",
  "properties": {
    "gn:admin1_code":"34.0",
    "gn:admin2_code":"228",
    "gn:asciiname":"Husainabad",
    "gn:country_code":"IN",
    "gn:dem":57,
    "gn:feature_class":"P",
    "gn:feature_code":"PPL",
    "gn:name":"Husain\u0101b\u0101d",
    "gn:population":0,
    "gn:timezone":"Asia/Kolkata",
    "iso:country":"IN",
    "wof:name":"Husainabad",
    "wof:placetype":"locality"
},
  "geometry": {"coordinates":[85.85701,25.10669],"type":"Point"}
}