{
  "type": "Feature",
  "properties": {
    "gn:admin1_code":"16",
    "gn:admin2_code":"507.0",
    "gn:asciiname":"Mehsuli",
    "gn:country_code":"IN",
    "gn:dem":294,
    "gn:feature_class":"P",
    "gn:feature_code":"PPL",
    "gn:name":"Mehsuli",
    "gn:population":0,
    "gn:timezone":"Asia/Kolkata",
    "iso:country":"IN",
    "name:und_x_variant":[
        "M\u0101hajantola"
    ],
    "wof:name":"Mehsuli",
    "wof:placetype":"locality"
},
  "geometry": {"coordinates":[80.29844,20.962],"type":"Point"}
}