{
  "type": "Feature",
  "properties": {
    "iso:country":"IN",
    "ks:ks_name":"Guptamau",
    "ks:ks_pop":0,
    "ks:ks_type":"VILLAGE",
    "name:eng_x_preferred":[
        "Guptamau"
    ],
    "wof:name":"Guptamau",
    "wof:placetype":"locality",
    "wof:population":0
},
  "geometry": {"coordinates":[79.715626,25.480657],"type":"Point"}
}