{
  "type": "Feature",
  "properties": {
    "gn:admin1_code":"2.0",
    "gn:admin2_code":"552.0",
    "gn:asciiname":"Mallapuram",
    "gn:country_code":"IN",
    "gn:dem":312,
    "gn:feature_class":"P",
    "gn:feature_code":"PPL",
    "gn:name":"Mall\u0101puram",
    "gn:population":0,
    "gn:timezone":"Asia/Kolkata",
    "iso:country":"IN",
    "name:tam_x_preferred":[
        "\u0bae\u0bb2\u0bcd\u0bb2\u0baa\u0bc1\u0bb0\u0bae\u0bcd"
    ],
    "wof:name":"Mallapuram",
    "wof:placetype":"locality"
},
  "geometry": {"coordinates":[77.80468,15.81672],"type":"Point"}
}