{
  "type": "Feature",
  "properties": {
    "gn:admin1_code":"25.0",
    "gn:admin2_code":"606.0",
    "gn:asciiname":"Mallappanayakanpalaiyam",
    "gn:country_code":"IN",
    "gn:dem":185,
    "gn:feature_class":"P",
    "gn:feature_code":"PPL",
    "gn:name":"Mallappan\u0101yakanp\u0101laiyam",
    "gn:population":0,
    "gn:timezone":"Asia/Kolkata",
    "iso:country":"IN",
    "wof:name":"Mallappanayakanpalaiyam",
    "wof:placetype":"locality"
},
  "geometry": {"coordinates":[79.13558,12.3952],"type":"Point"}
}