{
  "type": "Feature",
  "properties": {
    "iso:country":"IN",
    "ks:ks_name":"Imadul Mulak",
    "ks:ks_pop":413,
    "ks:ks_type":"VILLAGE",
    "ks:ks_uagg_main":0,
    "name:eng_x_preferred":[
        "Imadul Mulak"
    ],
    "wof:name":"Imadul Mulak",
    "wof:placetype":"neighbourhood",
    "wof:population":413
},
  "geometry": {"coordinates":[78.539248,28.600197],"type":"Point"}
}