{
  "type": "Feature",
  "properties": {
    "gn:admin1_code":"40",
    "gn:admin2_code":"534.0",
    "gn:asciiname":"Melacheru",
    "gn:country_code":"IN",
    "gn:dem":428,
    "gn:feature_class":"P",
    "gn:feature_code":"PPL",
    "gn:name":"Melacheru",
    "gn:population":0,
    "gn:timezone":"Asia/Kolkata",
    "iso:country":"IN",
    "wof:name":"Melacheru",
    "wof:placetype":"locality"
},
  "geometry": {"coordinates":[78.87739999999999,18.24709],"type":"Point"}
}