{
  "type": "Feature",
  "properties": {
    "iso:country":"IN",
    "ks:ks_name":"Chamrahia",
    "ks:ks_pop":50,
    "ks:ks_type":"HABITATION",
    "name:eng_x_preferred":[
        "Chamrahia"
    ],
    "wof:name":"Chamrahia",
    "wof:placetype":"locality",
    "wof:population":50
},
  "geometry": {"coordinates":[82.458187,26.832289],"type":"Point"}
}