{
  "type": "Feature",
  "properties": {
    "iso:country":"IN",
    "ks:ks_name":"Tantipara",
    "ks:ks_pop":656,
    "ks:ks_type":"VILLAGE",
    "ks:ks_uagg_main":0,
    "name:eng_x_preferred":[
        "Tantipara"
    ],
    "wof:name":"Tantipara",
    "wof:placetype":"neighbourhood",
    "wof:population":656
},
  "geometry": {"coordinates":[88.265221,24.257882],"type":"Point"}
}