{
  "type": "Feature",
  "properties": {
    "iso:country":"IN",
    "ks:ks_name":"Shivbaran Dhobi Ka Purwa",
    "ks:ks_pop":125,
    "ks:ks_type":"HABITATION",
    "name:eng_x_preferred":[
        "Shivbaran Dhobi Ka Purwa"
    ],
    "wof:name":"Shivbaran Dhobi Ka Purwa",
    "wof:placetype":"locality",
    "wof:population":125
},
  "geometry": {"coordinates":[81.08534899999999,25.27874],"type":"Point"}
}