{
  "type": "Feature",
  "properties": {
    "iso:country":"IN",
    "ks:ks_name":"Kallakattani",
    "ks:ks_pop":350,
    "ks:ks_type":"HABITATION",
    "name:eng_x_preferred":[
        "Kallakattani"
    ],
    "wof:name":"Kallakattani",
    "wof:placetype":"locality",
    "wof:population":350
},
  "geometry": {"coordinates":[75.250795,12.905232],"type":"Point"}
}