{
  "type": "Feature",
  "properties": {
    "iso:country":"IN",
    "ks:ks_name":"Sursu",
    "ks:ks_pop":983,
    "ks:ks_type":"HABITATION",
    "name:eng_x_preferred":[
        "Sursu"
    ],
    "wof:name":"Sursu",
    "wof:placetype":"locality",
    "wof:population":983
},
  "geometry": {"coordinates":[85.681808,23.425964],"type":"Point"}
}