{
  "type": "Feature",
  "properties": {
    "iso:country":"IN",
    "ks:ks_name":"Pundubasai",
    "ks:ks_pop":92,
    "ks:ks_type":"HABITATION",
    "name:eng_x_preferred":[
        "Pundubasai"
    ],
    "wof:name":"Pundubasai",
    "wof:placetype":"locality",
    "wof:population":92
},
  "geometry": {"coordinates":[85.824421,22.22983],"type":"Point"}
}