{
  "type": "Feature",
  "properties": {
    "iso:country":"IN",
    "ks:ks_name":"Sugipahari",
    "ks:ks_pop":323,
    "ks:ks_type":"VILLAGE",
    "name:eng_x_preferred":[
        "Sugipahari"
    ],
    "wof:name":"Sugipahari",
    "wof:placetype":"locality",
    "wof:population":323
},
  "geometry": {"coordinates":[87.068753,24.423085],"type":"Point"}
}