{
  "type": "Feature",
  "properties": {
    "iso:country":"IN",
    "ks:ks_name":"Tirla",
    "ks:ks_pop":257,
    "ks:ks_type":"VILLAGE",
    "name:eng_x_preferred":[
        "Tirla"
    ],
    "wof:name":"Tirla",
    "wof:placetype":"locality",
    "wof:population":257
},
  "geometry": {"coordinates":[85.33973,22.836459],"type":"Point"}
}