{
  "type": "Feature",
  "properties": {
    "iso:country":"IN",
    "ks:ks_name":"Tiliya",
    "ks:ks_pop":101,
    "ks:ks_type":"HABITATION",
    "name:eng_x_preferred":[
        "Tiliya"
    ],
    "wof:name":"Tiliya",
    "wof:placetype":"locality",
    "wof:population":101
},
  "geometry": {"coordinates":[80.16357000000001,26.840866],"type":"Point"}
}