{
  "type": "Feature",
  "properties": {
    "gn:admin1_code":"36",
    "gn:admin2_code":"178.0",
    "gn:asciiname":"Rampur Tendwa",
    "gn:country_code":"IN",
    "gn:dem":95,
    "gn:feature_class":"P",
    "gn:feature_code":"PPL",
    "gn:name":"R\u0101mpur Tendwa",
    "gn:population":0,
    "gn:timezone":"Asia/Kolkata",
    "iso:country":"IN",
    "name:und_x_variant":[
        "R\u0101mpur Tendwa",
        "Sibt\u012bpur"
    ],
    "wof:name":"Rampur Tendwa",
    "wof:placetype":"locality"
},
  "geometry": {"coordinates":[82.62631,26.47237],"type":"Point"}
}