{
  "type": "Feature",
  "properties": {
    "gn:admin1_code":"25",
    "gn:admin2_code":"633.0",
    "gn:asciiname":"Tayampalaiyam",
    "gn:country_code":"IN",
    "gn:dem":294,
    "gn:feature_class":"P",
    "gn:feature_code":"PPL",
    "gn:name":"T\u0101yamp\u0101laiyam",
    "gn:population":0,
    "gn:timezone":"Asia/Kolkata",
    "iso:country":"IN",
    "ks:ks_name":"Thayampalayam",
    "ks:ks_pop":160,
    "ks:ks_type":"HABITATION",
    "ks:ks_uagg_main":0,
    "name:eng_x_preferred":[
        "Thayampalayam"
    ],
    "name:und_x_variant":[
        "Tayampalayam",
        "T\u0101yamp\u0101laiyam"
    ],
    "wof:name":"Thayampalayam",
    "wof:placetype":"neighbourhood",
    "wof:population":160
},
  "geometry": {"coordinates":[77.488535,10.883784],"type":"Point"}
}