{
  "type": "Feature",
  "properties": {
    "gn:admin1_code":"11",
    "gn:admin2_code":"24.0",
    "gn:asciiname":"Mathrehr",
    "gn:country_code":"IN",
    "gn:dem":1174,
    "gn:feature_class":"P",
    "gn:feature_code":"PPL",
    "gn:name":"Mathrehr",
    "gn:population":0,
    "gn:timezone":"Asia/Kolkata",
    "iso:country":"IN",
    "wof:name":"Mathrehr",
    "wof:placetype":"locality"
},
  "geometry": {"coordinates":[76.46628,32.12178],"type":"Point"}
}