{
  "type": "Feature",
  "properties": {
    "gn:admin1_code":"10",
    "gn:admin2_code":"70.0",
    "gn:asciiname":"Chandpura",
    "gn:country_code":"IN",
    "gn:dem":280,
    "gn:feature_class":"P",
    "gn:feature_code":"PPL",
    "gn:name":"Chandpura",
    "gn:population":0,
    "gn:timezone":"Asia/Kolkata",
    "iso:country":"IN",
    "wof:name":"Chandpura",
    "wof:placetype":"locality"
},
  "geometry": {"coordinates":[76.8904,30.3527],"type":"Point"}
}