{
  "type": "Feature",
  "properties": {
    "iso:country":"IN",
    "ks:ks_name":"Krishnaperi",
    "ks:ks_pop":586,
    "ks:ks_type":"VILLAGE",
    "name:eng_x_preferred":[
        "Krishnaperi"
    ],
    "wof:name":"Krishnaperi",
    "wof:placetype":"locality",
    "wof:population":586
},
  "geometry": {"coordinates":[77.728376,9.515478],"type":"Point"}
}