{
  "type": "Feature",
  "properties": {
    "iso:country":"IN",
    "ks:ks_name":"Toransar",
    "ks:ks_pop":35,
    "ks:ks_type":"HABITATION",
    "name:eng_x_preferred":[
        "Toransar"
    ],
    "wof:name":"Toransar",
    "wof:placetype":"locality",
    "wof:population":35
},
  "geometry": {"coordinates":[74.809512,14.880703],"type":"Point"}
}