{
  "type": "Feature",
  "properties": {
    "iso:country":"IN",
    "ks:ks_name":"Pudupalayam",
    "ks:ks_pop":5440,
    "ks:ks_type":"VILLAGE",
    "ks:ks_uagg_main":0,
    "name:eng_x_preferred":[
        "Pudupalayam"
    ],
    "wof:name":"Pudupalayam",
    "wof:placetype":"locality",
    "wof:population":5440
},
  "geometry": {"coordinates":[78.19410999999999,11.479084],"type":"Point"}
}