{
  "type": "Feature",
  "properties": {
    "gn:admin1_code":"35.0",
    "gn:admin2_code":"455.0",
    "gn:asciiname":"Chhindboh",
    "gn:country_code":"IN",
    "gn:dem":591,
    "gn:feature_class":"P",
    "gn:feature_code":"PPL",
    "gn:name":"Chh\u012bndboh",
    "gn:population":0,
    "gn:timezone":"Asia/Kolkata",
    "iso:country":"IN",
    "wof:name":"Chhindboh",
    "wof:placetype":"locality"
},
  "geometry": {"coordinates":[78.62456,21.9296],"type":"Point"}
}