{
  "type": "Feature",
  "properties": {
    "gn:admin1_code":"2.0",
    "gn:admin2_code":"553",
    "gn:asciiname":"Cherlopalle",
    "gn:country_code":"IN",
    "gn:dem":578,
    "gn:feature_class":"P",
    "gn:feature_code":"PPL",
    "gn:name":"Cherlopalle",
    "gn:population":0,
    "gn:timezone":"Asia/Kolkata",
    "iso:country":"IN",
    "wof:name":"Cherlopalle",
    "wof:placetype":"locality"
},
  "geometry": {"coordinates":[77.05794,14.41701],"type":"Point"}
}