{
  "type": "Feature",
  "properties": {
    "iso:country":"IN",
    "ks:ks_name":"Devarapalya",
    "ks:ks_pop":200,
    "ks:ks_type":"HABITATION",
    "name:eng_x_preferred":[
        "Devarapalya"
    ],
    "wof:name":"Devarapalya",
    "wof:placetype":"locality",
    "wof:population":200
},
  "geometry": {"coordinates":[77.051123,13.053029],"type":"Point"}
}