{
  "type": "Feature",
  "properties": {
    "iso:country":"IN",
    "ks:ks_name":"Forest Range Office",
    "ks:ks_pop":506,
    "ks:ks_type":"HABITATION",
    "name:eng_x_preferred":[
        "Forest Range Office"
    ],
    "wof:name":"Forest Range Office",
    "wof:placetype":"locality",
    "wof:population":506
},
  "geometry": {"coordinates":[76.36998,10.378646],"type":"Point"}
}