{
  "type": "Feature",
  "properties": {
    "iso:country":"IN",
    "ks:ks_alt_nam":"Tad pada",
    "ks:ks_name":"Tad Pada",
    "ks:ks_pop":290,
    "ks:ks_type":"HABITATION",
    "name:eng_x_preferred":[
        "Tad Pada"
    ],
    "wof:name":"Tad Pada",
    "wof:placetype":"locality",
    "wof:population":290
},
  "geometry": {"coordinates":[73.317694,20.523139],"type":"Point"}
}