{
  "type": "Feature",
  "properties": {
    "gn:admin1_code":"36.0",
    "gn:admin2_code":"182.0",
    "gn:asciiname":"Pura Malang",
    "gn:country_code":"IN",
    "gn:dem":111,
    "gn:feature_class":"P",
    "gn:feature_code":"PPL",
    "gn:name":"Pura Malang",
    "gn:population":0,
    "gn:timezone":"Asia/Kolkata",
    "iso:country":"IN",
    "wof:name":"Pura Malang",
    "wof:placetype":"locality"
},
  "geometry": {"coordinates":[82.08351,27.52208],"type":"Point"}
}