{
  "type": "Feature",
  "properties": {
    "iso:country":"IN",
    "ks:ks_alt_nam":"Ahl\u0101dpur",
    "ks:ks_name":"Ahladpur",
    "ks:ks_pop":1923,
    "ks:ks_type":"VILLAGE",
    "name:eng_x_preferred":[
        "Ahladpur"
    ],
    "name:eng_x_variant":[
        "Ahl\u0101dpur"
    ],
    "wof:name":"Ahladpur",
    "wof:placetype":"neighbourhood",
    "wof:population":1923
},
  "geometry": {"coordinates":[79.494128,28.408774],"type":"Point"}
}