{
  "type": "Feature",
  "properties": {
    "iso:country":"IN",
    "ks:ks_name":"Reddiapatti",
    "ks:ks_pop":1500,
    "ks:ks_type":"HABITATION",
    "name:eng_x_preferred":[
        "Reddiapatti"
    ],
    "wof:name":"Reddiapatti",
    "wof:placetype":"locality",
    "wof:population":1500
},
  "geometry": {"coordinates":[77.559195,9.316428],"type":"Point"}
}