{
  "type": "Feature",
  "properties": {
    "gn:admin1_code":"24",
    "gn:admin2_code":"100.0",
    "gn:asciiname":"Ranisar",
    "gn:country_code":"IN",
    "gn:dem":204,
    "gn:feature_class":"P",
    "gn:feature_code":"PPL",
    "gn:name":"R\u0101nisar",
    "gn:population":0,
    "gn:timezone":"Asia/Kolkata",
    "iso:country":"IN",
    "wof:name":"Ranisar",
    "wof:placetype":"locality"
},
  "geometry": {"coordinates":[74.60871999999998,28.95209],"type":"Point"}
}