{
  "type": "Feature",
  "properties": {
    "iso:country":"IN",
    "ks:ks_name":"Ram Prakash Ki Thar",
    "ks:ks_pop":131,
    "ks:ks_type":"HABITATION",
    "name:eng_x_preferred":[
        "Ram Prakash Ki Thar"
    ],
    "wof:name":"Ram Prakash Ki Thar",
    "wof:placetype":"locality",
    "wof:population":131
},
  "geometry": {"coordinates":[78.399272,26.970975],"type":"Point"}
}