{
  "type": "Feature",
  "properties": {
    "iso:country":"IN",
    "ks:ks_name":"Sirischandrapur",
    "ks:ks_pop":163,
    "ks:ks_type":"HABITATION",
    "name:eng_x_preferred":[
        "Sirischandrapur"
    ],
    "wof:name":"Sirischandrapur",
    "wof:placetype":"locality",
    "wof:population":163
},
  "geometry": {"coordinates":[86.614405,21.807232],"type":"Point"}
}