{
  "type": "Feature",
  "properties": {
    "gn:admin1_code":"21.0",
    "gn:admin2_code":"396.0",
    "gn:asciiname":"Gavuduguda",
    "gn:country_code":"IN",
    "gn:dem":288,
    "gn:feature_class":"P",
    "gn:feature_code":"PPL",
    "gn:name":"Gavuduguda",
    "gn:population":0,
    "gn:timezone":"Asia/Kolkata",
    "iso:country":"IN",
    "wof:name":"Gavuduguda",
    "wof:placetype":"locality"
},
  "geometry": {"coordinates":[83.42362,19.36069],"type":"Point"}
}