{
  "type": "Feature",
  "properties": {
    "iso:country":"IN",
    "ks:ks_name":"Raghunathpur",
    "ks:ks_pop":1739,
    "ks:ks_type":"VILLAGE",
    "ks:ks_uagg_main":0,
    "name:eng_x_preferred":[
        "Raghunathpur"
    ],
    "wof:name":"Raghunathpur",
    "wof:placetype":"locality",
    "wof:population":1739
},
  "geometry": {"coordinates":[88.49551,22.97084],"type":"Point"}
}