{
  "type": "Feature",
  "properties": {
    "iso:country":"IN",
    "ks:ks_name":"Sarifnagar",
    "ks:ks_pop":871,
    "ks:ks_type":"VILLAGE",
    "name:eng_x_preferred":[
        "Sarifnagar"
    ],
    "wof:name":"Sarifnagar",
    "wof:placetype":"locality",
    "wof:population":871
},
  "geometry": {"coordinates":[88.343363,22.165403],"type":"Point"}
}