{
  "type": "Feature",
  "properties": {
    "iso:country":"IN",
    "ks:ks_name":"Chiri",
    "ks:ks_pop":500,
    "ks:ks_type":"HABITATION",
    "name:eng_x_preferred":[
        "Chiri"
    ],
    "wof:name":"Chiri",
    "wof:placetype":"locality",
    "wof:population":500
},
  "geometry": {"coordinates":[72.593108,27.267842],"type":"Point"}
}