{
  "type": "Feature",
  "properties": {
    "iso:country":"IN",
    "ks:ks_alt_nam":"Mondal and Naskar Para",
    "ks:ks_name":"Mondal And Naskar Para",
    "ks:ks_pop":800,
    "ks:ks_type":"HABITATION",
    "name:eng_x_preferred":[
        "Mondal And Naskar Para"
    ],
    "wof:name":"Mondal And Naskar Para",
    "wof:placetype":"locality",
    "wof:population":800
},
  "geometry": {"coordinates":[88.500624,22.104436],"type":"Point"}
}