{
  "type": "Feature",
  "properties": {
    "iso:country":"IN",
    "ks:ks_name":"Kayandoor",
    "ks:ks_pop":177,
    "ks:ks_type":"HABITATION",
    "name:eng_x_preferred":[
        "Kayandoor"
    ],
    "wof:name":"Kayandoor",
    "wof:placetype":"locality",
    "wof:population":177
},
  "geometry": {"coordinates":[75.484048,12.752275],"type":"Point"}
}