{
  "type": "Feature",
  "properties": {
    "iso:country":"IN",
    "ks:ks_name":"Kamanahalli",
    "ks:ks_pop":194,
    "ks:ks_type":"VILLAGE",
    "name:eng_x_preferred":[
        "Kamanahalli"
    ],
    "wof:name":"Kamanahalli",
    "wof:placetype":"locality",
    "wof:population":194
},
  "geometry": {"coordinates":[76.632026,13.483793],"type":"Point"}
}