{
  "type": "Feature",
  "properties": {
    "gn:admin1_code":"19.0",
    "gn:admin2_code":"555.0",
    "gn:asciiname":"Lakhinaikankop",
    "gn:country_code":"IN",
    "gn:dem":601,
    "gn:feature_class":"P",
    "gn:feature_code":"PPL",
    "gn:name":"Lakhin\u0101ikankop",
    "gn:population":0,
    "gn:timezone":"Asia/Kolkata",
    "iso:country":"IN",
    "wof:name":"Lakhinaikankop",
    "wof:placetype":"locality"
},
  "geometry": {"coordinates":[75.32500999999998,15.87813],"type":"Point"}
}