{
  "type": "Feature",
  "properties": {
    "iso:country":"IN",
    "ks:ks_name":"Wadpada",
    "ks:ks_pop":374,
    "ks:ks_type":"HABITATION",
    "name:eng_x_preferred":[
        "Wadpada"
    ],
    "wof:name":"Wadpada",
    "wof:placetype":"locality",
    "wof:population":374
},
  "geometry": {"coordinates":[73.49075999999999,20.359161],"type":"Point"}
}