{
  "type": "Feature",
  "properties": {
    "gn:admin1_code":"9.0",
    "gn:admin2_code":"485.0",
    "gn:asciiname":"Maunala",
    "gn:country_code":"IN",
    "gn:dem":285,
    "gn:feature_class":"P",
    "gn:feature_code":"PPL",
    "gn:name":"Maunala",
    "gn:population":0,
    "gn:timezone":"Asia/Kolkata",
    "iso:country":"IN",
    "ks:ks_name":"Mahunala",
    "ks:ks_pop":955,
    "ks:ks_type":"VILLAGE",
    "name:eng_x_preferred":[
        "Mahunala"
    ],
    "name:eng_x_variant":[
        "Maunala"
    ],
    "wof:name":"Mahunala",
    "wof:placetype":"locality",
    "wof:population":955
},
  "geometry": {"coordinates":[74.07336100000001,22.746],"type":"Point"}
}