{
  "type": "Feature",
  "properties": {
    "iso:country":"IN",
    "ks:ks_name":"Behradi",
    "ks:ks_pop":182,
    "ks:ks_type":"VILLAGE",
    "name:eng_x_preferred":[
        "Behradi"
    ],
    "wof:name":"Behradi",
    "wof:placetype":"locality",
    "wof:population":182
},
  "geometry": {"coordinates":[86.380439,23.93167],"type":"Point"}
}