{
  "type": "Feature",
  "properties": {
    "iso:country":"IN",
    "ks:ks_name":"Buridiganikunta",
    "ks:ks_pop":167,
    "ks:ks_type":"HABITATION",
    "name:eng_x_preferred":[
        "Buridiganikunta"
    ],
    "wof:name":"Buridiganikunta",
    "wof:placetype":"locality",
    "wof:population":167
},
  "geometry": {"coordinates":[78.269085,12.748823],"type":"Point"}
}