{
  "type": "Feature",
  "properties": {
    "iso:country":"IN",
    "ks:ks_name":"Dubaha",
    "ks:ks_pop":38,
    "ks:ks_type":"VILLAGE",
    "ks:ks_uagg_main":0,
    "name:eng_x_preferred":[
        "Dubaha"
    ],
    "wof:name":"Dubaha",
    "wof:placetype":"locality",
    "wof:population":38
},
  "geometry": {"coordinates":[81.316924,24.576079],"type":"Point"}
}