{
  "type": "Feature",
  "properties": {
    "gn:admin1_code":"34.0",
    "gn:admin2_code":"239.0",
    "gn:asciiname":"Mohan Bigha",
    "gn:country_code":"IN",
    "gn:dem":68,
    "gn:feature_class":"P",
    "gn:feature_code":"PPL",
    "gn:name":"Mohan Bigha",
    "gn:population":0,
    "gn:timezone":"Asia/Kolkata",
    "iso:country":"IN",
    "wof:name":"Mohan Bigha",
    "wof:placetype":"locality"
},
  "geometry": {"coordinates":[84.89278,25.26412],"type":"Point"}
}