{
  "type": "Feature",
  "properties": {
    "iso:country":"IN",
    "ks:ks_alt_nam":"Palsi pada",
    "ks:ks_name":"Palsi Pada",
    "ks:ks_pop":594,
    "ks:ks_type":"HABITATION",
    "name:eng_x_preferred":[
        "Palsi Pada"
    ],
    "wof:name":"Palsi Pada",
    "wof:placetype":"locality",
    "wof:population":594
},
  "geometry": {"coordinates":[83.131111,19.87449],"type":"Point"}
}