{
  "type": "Feature",
  "properties": {
    "iso:country":"IN",
    "ks:ks_name":"Denguguda",
    "ks:ks_pop":295,
    "ks:ks_type":"VILLAGE",
    "name:eng_x_preferred":[
        "Denguguda"
    ],
    "wof:name":"Denguguda",
    "wof:placetype":"locality",
    "wof:population":295
},
  "geometry": {"coordinates":[83.25841200000001,20.0641],"type":"Point"}
}