{
  "type": "Feature",
  "properties": {
    "iso:country":"IN",
    "ks:ks_alt_nam":"A.Karadi",
    "ks:ks_name":"A.karadi",
    "ks:ks_pop":3756,
    "ks:ks_type":"HABITATION",
    "name:eng_x_preferred":[
        "A.karadi"
    ],
    "wof:name":"A.karadi",
    "wof:placetype":"locality",
    "wof:population":3756
},
  "geometry": {"coordinates":[75.836944,12.228333],"type":"Point"}
}