{
  "type": "Feature",
  "properties": {
    "iso:country":"IN",
    "ks:ks_alt_nam":"DOM TOLA",
    "ks:ks_name":"Dom Tola",
    "ks:ks_pop":26,
    "ks:ks_type":"HABITATION",
    "ks:ks_uagg_main":0,
    "name:eng_x_preferred":[
        "Dom Tola"
    ],
    "wof:name":"Dom Tola",
    "wof:placetype":"neighbourhood",
    "wof:population":26
},
  "geometry": {"coordinates":[86.666664,26.355982],"type":"Point"}
}