{
  "type": "Feature",
  "properties": {
    "iso:country":"IN",
    "ks:ks_name":"Pasin Purwa",
    "ks:ks_pop":184,
    "ks:ks_type":"HABITATION",
    "ks:ks_uagg_main":0,
    "name:eng_x_preferred":[
        "Pasin Purwa"
    ],
    "wof:name":"Pasin Purwa",
    "wof:placetype":"neighbourhood",
    "wof:population":184
},
  "geometry": {"coordinates":[82.04794,27.109039],"type":"Point"}
}