{
  "type": "Feature",
  "properties": {
    "iso:country":"IN",
    "ks:ks_name":"Alighata",
    "ks:ks_pop":377,
    "ks:ks_type":"VILLAGE",
    "ks:ks_uagg_main":0,
    "name:eng_x_preferred":[
        "Alighata"
    ],
    "wof:name":"Alighata",
    "wof:placetype":"neighbourhood",
    "wof:population":377
},
  "geometry": {"coordinates":[88.278845,24.346717],"type":"Point"}
}