{
  "type": "Feature",
  "properties": {
    "iso:country":"IN",
    "ks:ks_name":"Bankati",
    "ks:ks_pop":100,
    "ks:ks_type":"HABITATION",
    "name:eng_x_preferred":[
        "Bankati"
    ],
    "wof:name":"Bankati",
    "wof:placetype":"locality",
    "wof:population":100
},
  "geometry": {"coordinates":[82.37988199999999,27.627685],"type":"Point"}
}