{
  "type": "Feature",
  "properties": {
    "iso:country":"IN",
    "ks:ks_name":"Modigaon Gurung Gaon",
    "ks:ks_pop":352,
    "ks:ks_type":"HABITATION",
    "ks:ks_uagg_main":0,
    "name:eng_x_preferred":[
        "Modigaon Gurung Gaon"
    ],
    "wof:name":"Modigaon Gurung Gaon",
    "wof:placetype":"neighbourhood",
    "wof:population":352
},
  "geometry": {"coordinates":[88.211536,26.921705],"type":"Point"}
}