{
  "type": "Feature",
  "properties": {
    "iso:country":"IN",
    "ks:ks_name":"Sagahan No 2",
    "ks:ks_pop":57,
    "ks:ks_type":"HABITATION",
    "name:eng_x_preferred":[
        "Sagahan No 2"
    ],
    "wof:name":"Sagahan No 2",
    "wof:placetype":"locality",
    "wof:population":57
},
  "geometry": {"coordinates":[81.966491,24.73956],"type":"Point"}
}