{
  "type": "Feature",
  "properties": {
    "gn:country":"IN",
    "gn:fcode":"PPL",
    "gn:pop":0,
    "iso:country":"IN",
    "name:unk_x_variant":[
        "Canari"
    ],
    "qs:name":"Kanlad",
    "qs:name_adm0":"India",
    "qs:name_adm1":"Maharashtra",
    "qs:photos_9r":0,
    "qs:photos_sr":0,
    "qs:placetype":"Town",
    "qs:pop_sr":"0",
    "wof:name":"Kanlad",
    "wof:placetype":"locality",
    "wof:population":0
},
  "geometry": {"coordinates":[72.93104,20.24654],"type":"Point"}
}