{
  "type": "Feature",
  "properties": {
    "iso:country":"IN",
    "ks:ks_name":"Harkhola",
    "ks:ks_pop":152,
    "ks:ks_type":"HABITATION",
    "name:eng_x_preferred":[
        "Harkhola"
    ],
    "wof:name":"Harkhola",
    "wof:placetype":"locality",
    "wof:population":152
},
  "geometry": {"coordinates":[80.27845499999999,29.733744],"type":"Point"}
}