{
  "type": "Feature",
  "properties": {
    "iso:country":"IN",
    "ks:ks_name":"20 KSD",
    "ks:ks_pop":170,
    "ks:ks_type":"VILLAGE",
    "name:eng_x_preferred":[
        "20 KSD"
    ],
    "wof:name":"20 KSD",
    "wof:placetype":"locality",
    "wof:population":170
},
  "geometry": {"coordinates":[74.23847499999999,29.923108],"type":"Point"}
}