{
  "type": "Feature",
  "properties": {
    "gn:admin1_code":"13.0",
    "gn:admin2_code":"590.0",
    "gn:asciiname":"Marot",
    "gn:country_code":"IN",
    "gn:dem":873,
    "gn:feature_class":"P",
    "gn:feature_code":"PPL",
    "gn:name":"M\u0101rot",
    "gn:population":0,
    "gn:timezone":"Asia/Kolkata",
    "iso:country":"IN",
    "name:fas_x_preferred":[
        "\u0645\u0631\u0648\u062a"
    ],
    "name:por_x_preferred":[
        "Fort Abbas"
    ],
    "name:urd_x_preferred":[
        "\u0645\u0631\u0648\u0679"
    ],
    "wof:name":"Marot",
    "wof:placetype":"locality"
},
  "geometry": {"coordinates":[76.32921999999998,11.69308],"type":"Point"}
}