{
  "type": "Feature",
  "properties": {
    "iso:country":"IN",
    "ks:ks_name":"Hara Chandra Roaja Para",
    "ks:ks_pop":292,
    "ks:ks_type":"HABITATION",
    "ks:ks_uagg_main":0,
    "name:eng_x_preferred":[
        "Hara Chandra Roaja Para"
    ],
    "wof:name":"Hara Chandra Roaja Para",
    "wof:placetype":"neighbourhood",
    "wof:population":292
},
  "geometry": {"coordinates":[91.915159,23.493449],"type":"Point"}
}