{
  "type": "Feature",
  "properties": {
    "iso:country":"IN",
    "ks:ks_name":"Shelkipada",
    "ks:ks_pop":118,
    "ks:ks_type":"HABITATION",
    "name:eng_x_preferred":[
        "Shelkipada"
    ],
    "wof:name":"Shelkipada",
    "wof:placetype":"locality",
    "wof:population":118
},
  "geometry": {"coordinates":[72.987202,19.806054],"type":"Point"}
}