{
  "type": "Feature",
  "properties": {
    "iso:country":"IN",
    "ks:ks_alt_nam":"Dhan kurali",
    "ks:ks_name":"Dhan Kurali",
    "ks:ks_pop":291,
    "ks:ks_type":"HABITATION",
    "name:eng_x_preferred":[
        "Dhan Kurali"
    ],
    "wof:name":"Dhan Kurali",
    "wof:placetype":"locality",
    "wof:population":291
},
  "geometry": {"coordinates":[78.870642,30.404301],"type":"Point"}
}