{
  "type": "Feature",
  "properties": {
    "iso:country":"IN",
    "ks:ks_alt_nam":"Moovar road",
    "ks:ks_name":"Moovar Road",
    "ks:ks_pop":89,
    "ks:ks_type":"HABITATION",
    "ks:ks_uagg_main":0,
    "name:eng_x_preferred":[
        "Moovar Road"
    ],
    "wof:name":"Moovar Road",
    "wof:placetype":"neighbourhood",
    "wof:population":89
},
  "geometry": {"coordinates":[79.146174,10.508024],"type":"Point"}
}