{
  "type": "Feature",
  "properties": {
    "iso:country":"IN",
    "ks:ks_name":"Bicholi",
    "ks:ks_pop":0,
    "ks:ks_type":"VILLAGE",
    "name:eng_x_preferred":[
        "Bicholi"
    ],
    "wof:name":"Bicholi",
    "wof:placetype":"locality",
    "wof:population":0
},
  "geometry": {"coordinates":[78.34090999999999,26.796722],"type":"Point"}
}