{
  "type": "Feature",
  "properties": {
    "iso:country":"IN",
    "ks:ks_name":"Partekond",
    "ks:ks_pop":100,
    "ks:ks_type":"HABITATION",
    "name:eng_x_preferred":[
        "Partekond"
    ],
    "wof:name":"Partekond",
    "wof:placetype":"locality",
    "wof:population":100
},
  "geometry": {"coordinates":[73.453608,17.998564],"type":"Point"}
}