{
  "type": "Feature",
  "properties": {
    "iso:country":"IN",
    "ks:ks_name":"Ali Chak",
    "ks:ks_pop":460,
    "ks:ks_type":"VILLAGE",
    "name:eng_x_preferred":[
        "Ali Chak"
    ],
    "wof:name":"Ali Chak",
    "wof:placetype":"locality",
    "wof:population":460
},
  "geometry": {"coordinates":[75.487472,32.091473],"type":"Point"}
}