{
  "type": "Feature",
  "properties": {
    "iso:country":"IN",
    "ks:ks_name":"Ekpai",
    "ks:ks_pop":398,
    "ks:ks_type":"HABITATION",
    "name:eng_x_preferred":[
        "Ekpai"
    ],
    "wof:name":"Ekpai",
    "wof:placetype":"locality",
    "wof:population":398
},
  "geometry": {"coordinates":[82.672594,23.980263],"type":"Point"}
}