{
  "type": "Feature",
  "properties": {
    "gn:admin1_code":"36",
    "gn:admin2_code":"179.0",
    "gn:asciiname":"Sherkhanpur",
    "gn:country_code":"IN",
    "gn:dem":93,
    "gn:feature_class":"P",
    "gn:feature_code":"PPL",
    "gn:name":"Sherkh\u0101npur",
    "gn:population":0,
    "gn:timezone":"Asia/Kolkata",
    "iso:country":"IN",
    "ks:ks_name":"Shekhanpur",
    "ks:ks_pop":810,
    "ks:ks_type":"VILLAGE",
    "name:eng_x_preferred":[
        "Shekhanpur"
    ],
    "name:eng_x_variant":[
        "Sherkhanpur"
    ],
    "wof:name":"Shekhanpur",
    "wof:placetype":"locality",
    "wof:population":810
},
  "geometry": {"coordinates":[82.38763899999999,26.314833],"type":"Point"}
}