{
  "type": "Feature",
  "properties": {
    "iso:country":"IN",
    "ks:ks_name":"Jidingisahi",
    "ks:ks_pop":202,
    "ks:ks_type":"HABITATION",
    "name:eng_x_preferred":[
        "Jidingisahi"
    ],
    "wof:name":"Jidingisahi",
    "wof:placetype":"locality",
    "wof:population":202
},
  "geometry": {"coordinates":[84.361609,20.243401],"type":"Point"}
}