{
  "type": "Feature",
  "properties": {
    "iso:country":"IN",
    "ks:ks_name":"Kotekallu",
    "ks:ks_pop":47,
    "ks:ks_type":"HABITATION",
    "name:eng_x_preferred":[
        "Kotekallu"
    ],
    "wof:name":"Kotekallu",
    "wof:placetype":"locality",
    "wof:population":47
},
  "geometry": {"coordinates":[75.761111,12.348611],"type":"Point"}
}