{
  "type": "Feature",
  "properties": {
    "iso:country":"IN",
    "ks:ks_name":"Gamro",
    "ks:ks_pop":56,
    "ks:ks_type":"HABITATION",
    "name:eng_x_preferred":[
        "Gamro"
    ],
    "wof:name":"Gamro",
    "wof:placetype":"locality",
    "wof:population":56
},
  "geometry": {"coordinates":[87.371995,24.791717],"type":"Point"}
}