{
  "type": "Feature",
  "properties": {
    "gn:admin1_code":"38",
    "gn:admin2_code":"346.0",
    "gn:asciiname":"Pokhariya",
    "gn:country_code":"IN",
    "gn:dem":275,
    "gn:feature_class":"P",
    "gn:feature_code":"PPL",
    "gn:name":"Pokhariya",
    "gn:population":0,
    "gn:timezone":"Asia/Kolkata",
    "iso:country":"IN",
    "name:bih_x_preferred":[
        "\u092a\u094b\u0916\u0930\u093f\u092f\u093e"
    ],
    "name:hin_x_preferred":[
        "\u092a\u094b\u0916\u0930\u093f\u092f\u093e"
    ],
    "name:nep_x_preferred":[
        "\u092a\u094b\u0916\u0930\u093f\u092f\u093e"
    ],
    "name:new_x_preferred":[
        "\u092a\u094b\u0916\u0930\u093f\u092f\u093e"
    ],
    "wof:name":"Pokhariya",
    "wof:placetype":"locality"
},
  "geometry": {"coordinates":[83.67291999999998,24.08312],"type":"Point"}
}