{
  "type": "Feature",
  "properties": {
    "iso:country":"IN",
    "ks:ks_name":"Silamohakhati 9",
    "ks:ks_pop":221,
    "ks:ks_type":"HABITATION",
    "ks:ks_uagg_main":0,
    "name:eng_x_preferred":[
        "Silamohakhati 9"
    ],
    "wof:name":"Silamohakhati 9",
    "wof:placetype":"neighbourhood",
    "wof:population":221
},
  "geometry": {"coordinates":[91.67623500000001,26.206513],"type":"Point"}
}