{
  "type": "Feature",
  "properties": {
    "iso:country":"IN",
    "ks:ks_name":"Eredih",
    "ks:ks_type":"VILLAGE",
    "name:eng_x_preferred":[
        "Eredih"
    ],
    "wof:name":"Eredih",
    "wof:placetype":"locality"
},
  "geometry": {"coordinates":[86.436041,24.486552],"type":"Point"}
}