{
  "type": "Feature",
  "properties": {
    "iso:country":"IN",
    "ks:ks_name":"Wailwada",
    "ks:ks_pop":162,
    "ks:ks_type":"HABITATION",
    "name:eng_x_preferred":[
        "Wailwada"
    ],
    "wof:name":"Wailwada",
    "wof:placetype":"locality",
    "wof:population":162
},
  "geometry": {"coordinates":[74.108823,14.879394],"type":"Point"}
}