{
  "type": "Feature",
  "properties": {
    "iso:country":"IN",
    "ks:ks_name":"Mundum\t",
    "ks:ks_pop":262,
    "ks:ks_type":"HABITATION",
    "name:eng_x_preferred":[
        "Mundum\t"
    ],
    "wof:name":"Mundum\t",
    "wof:placetype":"locality",
    "wof:population":262
},
  "geometry": {"coordinates":[81.622454,18.595903],"type":"Point"}
}