{
  "type": "Feature",
  "properties": {
    "iso:country":"IN",
    "ks:ks_name":"Sitakahabar",
    "ks:ks_pop":502,
    "ks:ks_type":"VILLAGE",
    "name:eng_x_preferred":[
        "Sitakahabar"
    ],
    "wof:name":"Sitakahabar",
    "wof:placetype":"locality",
    "wof:population":502
},
  "geometry": {"coordinates":[87.218373,24.238572],"type":"Point"}
}