{
  "type": "Feature",
  "properties": {
    "iso:country":"IN",
    "ks:ks_name":"Vakathanam",
    "ks:ks_pop":251,
    "ks:ks_type":"HABITATION",
    "name:eng_x_preferred":[
        "Vakathanam"
    ],
    "wof:name":"Vakathanam",
    "wof:placetype":"locality",
    "wof:population":251
},
  "geometry": {"coordinates":[77.070128,9.91653],"type":"Point"}
}