{
  "type": "Feature",
  "properties": {
    "gn:admin1_code":"19.0",
    "gn:admin2_code":"572.0",
    "gn:asciiname":"Hunsur",
    "gn:country_code":"IN",
    "gn:dem":889,
    "gn:feature_class":"P",
    "gn:feature_code":"PPL",
    "gn:name":"Huns\u016br",
    "gn:population":0,
    "gn:timezone":"Asia/Kolkata",
    "iso:country":"IN",
    "wof:name":"Hunsur",
    "wof:placetype":"locality"
},
  "geometry": {"coordinates":[77.71143000000002,13.1802],"type":"Point"}
}