{
  "type": "Feature",
  "properties": {
    "gn:admin1_code":"19.0",
    "gn:admin2_code":"582.0",
    "gn:asciiname":"Gundlahalli",
    "gn:country_code":"IN",
    "gn:dem":768,
    "gn:feature_class":"P",
    "gn:feature_code":"PPL",
    "gn:name":"Gundlahalli",
    "gn:population":0,
    "gn:timezone":"Asia/Kolkata",
    "iso:country":"IN",
    "wof:name":"Gundlahalli",
    "wof:placetype":"locality"
},
  "geometry": {"coordinates":[77.84081999999999,13.66316],"type":"Point"}
}