{
  "type": "Feature",
  "properties": {
    "gn:admin1_code":"38.0",
    "gn:admin2_code":"358.0",
    "gn:asciiname":"Koirihadih Kalan",
    "gn:country_code":"IN",
    "gn:dem":240,
    "gn:feature_class":"P",
    "gn:feature_code":"PPL",
    "gn:name":"Koir\u012bh\u0101d\u012bh Kal\u0101n",
    "gn:population":0,
    "gn:timezone":"Asia/Kolkata",
    "iso:country":"IN",
    "ks:ks_name":"Koiriadih Kalan",
    "ks:ks_pop":262,
    "ks:ks_type":"VILLAGE",
    "ks:ks_uagg_main":0,
    "name:eng_x_preferred":[
        "Koiriadih Kalan"
    ],
    "wof:name":"Koiriadih Kalan",
    "wof:placetype":"neighbourhood",
    "wof:population":262
},
  "geometry": {"coordinates":[84.19608599999999,24.137324],"type":"Point"}
}