{
  "type": "Feature",
  "properties": {
    "iso:country":"IN",
    "ks:ks_name":"Balijan Kath Gaon",
    "ks:ks_pop":293,
    "ks:ks_type":"HABITATION",
    "name:eng_x_preferred":[
        "Balijan Kath Gaon"
    ],
    "wof:name":"Balijan Kath Gaon",
    "wof:placetype":"locality",
    "wof:population":293
},
  "geometry": {"coordinates":[95.153639,27.529737],"type":"Point"}
}