{
  "type": "Feature",
  "properties": {
    "iso:country":"IN",
    "ks:ks_name":"Dudhajor",
    "ks:ks_pop":116,
    "ks:ks_type":"VILLAGE",
    "name:eng_x_preferred":[
        "Dudhajor"
    ],
    "wof:name":"Dudhajor",
    "wof:placetype":"locality",
    "wof:population":116
},
  "geometry": {"coordinates":[87.424341,24.529397],"type":"Point"}
}