{
  "type": "Feature",
  "properties": {
    "iso:country":"IN",
    "ks:ks_name":"Sutharon Ki Dhani",
    "ks:ks_pop":640,
    "ks:ks_type":"HABITATION",
    "name:eng_x_preferred":[
        "Sutharon Ki Dhani"
    ],
    "wof:name":"Sutharon Ki Dhani",
    "wof:placetype":"locality",
    "wof:population":640
},
  "geometry": {"coordinates":[71.92483300000001,26.204558],"type":"Point"}
}