{
  "type": "Feature",
  "properties": {
    "iso:country":"IN",
    "ks:ks_name":"Urki",
    "ks:ks_pop":166,
    "ks:ks_type":"HABITATION",
    "name:eng_x_preferred":[
        "Urki"
    ],
    "wof:name":"Urki",
    "wof:placetype":"locality",
    "wof:population":166
},
  "geometry": {"coordinates":[75.34870100000001,12.802395],"type":"Point"}
}