{
  "type": "Feature",
  "properties": {
    "iso:country":"IN",
    "ks:ks_name":"J H C",
    "ks:ks_pop":174,
    "ks:ks_type":"HABITATION",
    "name:eng_x_preferred":[
        "J H C"
    ],
    "wof:name":"J H C",
    "wof:placetype":"locality",
    "wof:population":174
},
  "geometry": {"coordinates":[74.850014,13.583336],"type":"Point"}
}