{
  "type": "Feature",
  "properties": {
    "iso:country":"IN",
    "ks:ks_name":"Naharkhansar",
    "ks:ks_pop":809,
    "ks:ks_type":"HABITATION",
    "name:eng_x_preferred":[
        "Naharkhansar"
    ],
    "wof:name":"Naharkhansar",
    "wof:placetype":"locality",
    "wof:population":809
},
  "geometry": {"coordinates":[71.714214,26.607406],"type":"Point"}
}