{
  "type": "Feature",
  "properties": {
    "gn:admin1_code":"21",
    "gn:admin2_code":"391.0",
    "gn:asciiname":"Podropoda",
    "gn:country_code":"IN",
    "gn:dem":122,
    "gn:feature_class":"P",
    "gn:feature_code":"PPL",
    "gn:name":"Podropoda",
    "gn:population":0,
    "gn:timezone":"Asia/Kolkata",
    "iso:country":"IN",
    "wof:name":"Podropoda",
    "wof:placetype":"locality"
},
  "geometry": {"coordinates":[83.91667,20.75],"type":"Point"}
}