{
  "type": "Feature",
  "properties": {
    "iso:country":"IN",
    "ks:ks_name":"Mankhedi Bk",
    "ks:ks_pop":728,
    "ks:ks_type":"HABITATION",
    "name:eng_x_preferred":[
        "Mankhedi Bk"
    ],
    "wof:name":"Mankhedi Bk",
    "wof:placetype":"locality",
    "wof:population":728
},
  "geometry": {"coordinates":[74.163163,21.77583],"type":"Point"}
}