{
  "type": "Feature",
  "properties": {
    "iso:country":"IN",
    "ks:ks_name":"Jonai Mukhkaw",
    "ks:ks_pop":188,
    "ks:ks_type":"HABITATION",
    "name:eng_x_preferred":[
        "Jonai Mukhkaw"
    ],
    "wof:name":"Jonai Mukhkaw",
    "wof:placetype":"locality",
    "wof:population":188
},
  "geometry": {"coordinates":[95.17448400000001,27.729671],"type":"Point"}
}