{
  "type": "Feature",
  "properties": {
    "gn:admin1_code":"12",
    "gn:admin2_code":"20.0",
    "gn:asciiname":"Ranglaen",
    "gn:country_code":"IN",
    "gn:dem":1980,
    "gn:feature_class":"P",
    "gn:feature_code":"PPL",
    "gn:name":"Rangl\u0101en",
    "gn:population":0,
    "gn:timezone":"Asia/Kolkata",
    "iso:country":"IN",
    "wof:name":"Ranglaen",
    "wof:placetype":"locality"
},
  "geometry": {"coordinates":[74.91866,33.39530999999999],"type":"Point"}
}