{
  "type": "Feature",
  "properties": {
    "gn:admin1_code":"36.0",
    "gn:admin2_code":"161",
    "gn:asciiname":"Makhanpur",
    "gn:country_code":"IN",
    "gn:dem":151,
    "gn:feature_class":"P",
    "gn:feature_code":"PPL",
    "gn:name":"Makhanpur",
    "gn:population":0,
    "gn:timezone":"Asia/Kolkata",
    "iso:country":"IN",
    "name:und_x_variant":[
        "Makkhanpur"
    ],
    "wof:name":"Makhanpur",
    "wof:placetype":"locality"
},
  "geometry": {"coordinates":[79.11483,26.87929],"type":"Point"}
}