{
  "type": "Feature",
  "properties": {
    "iso:country":"IN",
    "ks:ks_name":"Kachaharia Tola",
    "ks:ks_pop":1237,
    "ks:ks_type":"HABITATION",
    "ks:ks_uagg_main":0,
    "name:eng_x_preferred":[
        "Kachaharia Tola"
    ],
    "wof:name":"Kachaharia Tola",
    "wof:placetype":"neighbourhood",
    "wof:population":1237
},
  "geometry": {"coordinates":[84.965052,26.860433],"type":"Point"}
}