{
  "type": "Feature",
  "properties": {
    "gn:admin1_code":"36.0",
    "gn:admin2_code":"133.0",
    "gn:asciiname":"Lakhnauti",
    "gn:country_code":"IN",
    "gn:dem":256,
    "gn:feature_class":"P",
    "gn:feature_code":"PPL",
    "gn:name":"Lakhnauti",
    "gn:population":0,
    "gn:timezone":"Asia/Kolkata",
    "iso:country":"IN",
    "ks:ks_name":"Lakhnoti",
    "ks:ks_pop":1235,
    "ks:ks_type":"VILLAGE",
    "ks:ks_uagg_main":0,
    "name:eng_x_preferred":[
        "Lakhnoti"
    ],
    "wof:name":"Lakhnoti",
    "wof:placetype":"neighbourhood",
    "wof:population":1235
},
  "geometry": {"coordinates":[77.82307299999999,29.64836],"type":"Point"}
}