{
  "type": "Feature",
  "properties": {
    "iso:country":"IN",
    "ks:ks_name":"Gazi Bil Chuk",
    "ks:ks_pop":371,
    "ks:ks_type":"HABITATION",
    "ks:ks_uagg_main":0,
    "name:eng_x_preferred":[
        "Gazi Bil Chuk"
    ],
    "wof:name":"Gazi Bil Chuk",
    "wof:placetype":"neighbourhood",
    "wof:population":371
},
  "geometry": {"coordinates":[94.950216,27.031616],"type":"Point"}
}