{
  "type": "Feature",
  "properties": {
    "gn:admin1_code":"34",
    "gn:admin2_code":"233.0",
    "gn:asciiname":"Rupapatti",
    "gn:country_code":"IN",
    "gn:dem":91,
    "gn:feature_class":"P",
    "gn:feature_code":"PPL",
    "gn:name":"R\u016bp\u0101patti",
    "gn:population":0,
    "gn:timezone":"Asia/Kolkata",
    "iso:country":"IN",
    "ks:ks_name":"Rupa Patti",
    "ks:ks_pop":863,
    "ks:ks_type":"VILLAGE",
    "name:eng_x_preferred":[
        "Rupa Patti"
    ],
    "name:eng_x_variant":[
        "Rupapatti"
    ],
    "wof:name":"Rupa Patti",
    "wof:placetype":"locality",
    "wof:population":863
},
  "geometry": {"coordinates":[83.535106,25.016759],"type":"Point"}
}