{
  "type": "Feature",
  "properties": {
    "iso:country":"IN",
    "ks:ks_name":"Wakana",
    "ks:ks_pop":1678,
    "ks:ks_type":"VILLAGE",
    "ks:ks_uagg_main":0,
    "name:eng_x_preferred":[
        "Wakana"
    ],
    "wof:name":"Wakana",
    "wof:placetype":"neighbourhood",
    "wof:population":1678
},
  "geometry": {"coordinates":[76.61942000000001,21.007433],"type":"Point"}
}