{
  "type": "Feature",
  "properties": {
    "iso:country":"IN",
    "ks:ks_name":"Samaspur",
    "ks:ks_pop":1378,
    "ks:ks_type":"VILLAGE",
    "ks:ks_uagg_main":0,
    "name:eng_x_preferred":[
        "Samaspur"
    ],
    "wof:name":"Samaspur",
    "wof:placetype":"neighbourhood",
    "wof:population":1378
},
  "geometry": {"coordinates":[88.67071300000001,22.518923],"type":"Point"}
}