{
  "type": "Feature",
  "properties": {
    "iso:country":"IN",
    "ks:ks_name":"Gadakhol",
    "ks:ks_pop":23,
    "ks:ks_type":"VILLAGE",
    "name:eng_x_preferred":[
        "Gadakhol"
    ],
    "wof:name":"Gadakhol",
    "wof:placetype":"locality",
    "wof:population":23
},
  "geometry": {"coordinates":[84.28503499999999,20.51756],"type":"Point"}
}