{
  "type": "Feature",
  "properties": {
    "iso:country":"IN",
    "ks:ks_name":"Jhilikibeda",
    "ks:ks_pop":153,
    "ks:ks_type":"HABITATION",
    "name:eng_x_preferred":[
        "Jhilikibeda"
    ],
    "wof:name":"Jhilikibeda",
    "wof:placetype":"locality",
    "wof:population":153
},
  "geometry": {"coordinates":[82.735558,18.950222],"type":"Point"}
}