{
  "type": "Feature",
  "properties": {
    "gn:admin1_code":"19.0",
    "gn:admin2_code":"575.0",
    "gn:asciiname":"Putlaje",
    "gn:country_code":"IN",
    "gn:dem":137,
    "gn:feature_class":"P",
    "gn:feature_code":"PPL",
    "gn:name":"Putlaje",
    "gn:population":0,
    "gn:timezone":"Asia/Kolkata",
    "iso:country":"IN",
    "wof:name":"Putlaje",
    "wof:placetype":"locality"
},
  "geometry": {"coordinates":[75.46926999999999,13.00569],"type":"Point"}
}