{
  "type": "Feature",
  "properties": {
    "gn:admin1_code":"19.0",
    "gn:admin2_code":"575.0",
    "gn:asciiname":"Putlaje",
    "gn:country_code":"IN",
    "gn:dem":137,
    "gn:feature_class":"P",
    "gn:feature_code":"PPL",
    "gn:name":"Putlaje",
    "gn:population":0,
    "gn:timezone":"Asia/Kolkata",
    "iso:country":"IN",
    "ks:ks_name":"Pullaje",
    "ks:ks_pop":200,
    "ks:ks_type":"HABITATION",
    "name:eng_x_preferred":[
        "Pullaje"
    ],
    "name:eng_x_variant":[
        "Putlaje"
    ],
    "wof:name":"Pullaje",
    "wof:placetype":"locality",
    "wof:population":200
},
  "geometry": {"coordinates":[75.471035,13.008289],"type":"Point"}
}