{
  "type": "Feature",
  "properties": {
    "iso:country":"IN",
    "ks:ks_name":"Kaumari",
    "ks:ks_pop":1130,
    "ks:ks_type":"VILLAGE",
    "ks:ks_uagg_main":0,
    "name:eng_x_preferred":[
        "Kaumari"
    ],
    "wof:name":"Kaumari",
    "wof:placetype":"neighbourhood",
    "wof:population":1130
},
  "geometry": {"coordinates":[87.225561,21.573168],"type":"Point"}
}