{
  "type": "Feature",
  "properties": {
    "gn:admin1_code":"35.0",
    "gn:admin2_code":"421.0",
    "gn:asciiname":"Samaya",
    "gn:country_code":"IN",
    "gn:dem":233,
    "gn:feature_class":"P",
    "gn:feature_code":"PPL",
    "gn:name":"Sam\u0101ya",
    "gn:population":0,
    "gn:timezone":"Asia/Kolkata",
    "iso:country":"IN",
    "name:jpn_x_preferred":[
        "\u4e09\u6627\u8036\u6212"
    ],
    "name:lat_x_preferred":[
        "Samaya"
    ],
    "name:pol_x_preferred":[
        "Samaja"
    ],
    "wof:name":"Samaya",
    "wof:placetype":"locality"
},
  "geometry": {"coordinates":[78.20574000000001,25.93816],"type":"Point"}
}