{
  "type": "Feature",
  "properties": {
    "iso:country":"IN",
    "ks:ks_name":"Bahadurpur",
    "ks:ks_pop":1802,
    "ks:ks_type":"VILLAGE",
    "ks:ks_uagg_main":0,
    "name:eng_x_preferred":[
        "Bahadurpur"
    ],
    "wof:name":"Bahadurpur",
    "wof:placetype":"neighbourhood",
    "wof:population":1802
},
  "geometry": {"coordinates":[92.313166,24.684248],"type":"Point"}
}