{
  "type": "Feature",
  "properties": {
    "gn:admin1_code":"12.0",
    "gn:asciiname":"Mandhan",
    "gn:country_code":"IN",
    "gn:dem":334,
    "gn:feature_class":"P",
    "gn:feature_code":"PPL",
    "gn:name":"Mandh\u0101n",
    "gn:population":0,
    "gn:timezone":"Asia/Kolkata",
    "iso:country":"IN",
    "name:und_x_variant":[
        "Mandh\u0101n",
        "Mandhar"
    ],
    "wof:name":"Mandhan",
    "wof:placetype":"locality"
},
  "geometry": {"coordinates":[74.41516,32.95285],"type":"Point"}
}