{
  "type": "Feature",
  "properties": {
    "gn:admin1_code":"40.0",
    "gn:admin2_code":"539",
    "gn:asciiname":"Nemargomla",
    "gn:country_code":"IN",
    "gn:dem":485,
    "gn:feature_class":"P",
    "gn:feature_code":"PPL",
    "gn:name":"Nemargomla",
    "gn:population":0,
    "gn:timezone":"Asia/Kolkata",
    "iso:country":"IN",
    "name:und_x_variant":[
        "Nimarugomla",
        "Nemargomla"
    ],
    "wof:name":"Nemargomla",
    "wof:placetype":"locality"
},
  "geometry": {"coordinates":[78.7306,17.48086],"type":"Point"}
}