{
  "type": "Feature",
  "properties": {
    "iso:country":"IN",
    "ks:ks_alt_nam":"BALWARI",
    "ks:ks_name":"Balwari",
    "ks:ks_pop":310,
    "ks:ks_type":"HABITATION",
    "ks:ks_uagg_main":0,
    "name:eng_x_preferred":[
        "Balwari"
    ],
    "wof:name":"Balwari",
    "wof:placetype":"neighbourhood",
    "wof:population":310
},
  "geometry": {"coordinates":[81.88403700000001,26.0983],"type":"Point"}
}