{
  "type": "Feature",
  "properties": {
    "iso:country":"IN",
    "ks:ks_name":"Lala Toli",
    "ks:ks_pop":100,
    "ks:ks_type":"HABITATION",
    "ks:ks_uagg_main":0,
    "name:eng_x_preferred":[
        "Lala Toli"
    ],
    "wof:name":"Lala Toli",
    "wof:placetype":"neighbourhood",
    "wof:population":100
},
  "geometry": {"coordinates":[85.255349,24.62945],"type":"Point"}
}