{
  "type": "Feature",
  "properties": {
    "iso:country":"IN",
    "ks:ks_name":"Colimpada",
    "ks:ks_pop":245,
    "ks:ks_type":"HABITATION",
    "name:eng_x_preferred":[
        "Colimpada"
    ],
    "wof:name":"Colimpada",
    "wof:placetype":"locality",
    "wof:population":245
},
  "geometry": {"coordinates":[72.921836,20.020763],"type":"Point"}
}