{
  "type": "Feature",
  "properties": {
    "gn:admin1_code":"34.0",
    "gn:admin2_code":"226.0",
    "gn:asciiname":"Gauripur",
    "gn:country_code":"IN",
    "gn:dem":48,
    "gn:feature_class":"P",
    "gn:feature_code":"PPL",
    "gn:name":"Gaur\u012bpur",
    "gn:population":0,
    "gn:timezone":"Asia/Kolkata",
    "iso:country":"IN",
    "ks:ks_alt_nam":"Gaur\u012bpur",
    "ks:ks_name":"Gauripur",
    "ks:ks_pop":1872,
    "ks:ks_type":"VILLAGE",
    "ks:ks_uagg_main":0,
    "name:ceb_x_preferred":[
        "Gauripur"
    ],
    "name:eng_x_preferred":[
        "Gauripur"
    ],
    "name:eng_x_variant":[
        "Gaur\u012bpur"
    ],
    "name:sco_x_preferred":[
        "Gauripur"
    ],
    "name:swe_x_preferred":[
        "Gauripur"
    ],
    "wof:name":"Gauripur",
    "wof:placetype":"neighbourhood",
    "wof:population":1872
},
  "geometry": {"coordinates":[86.481049,25.33645],"type":"Point"}
}