{
  "type": "Feature",
  "properties": {
    "iso:country":"IN",
    "ks:ks_name":"Perukia",
    "ks:ks_pop":0,
    "ks:ks_type":"VILLAGE",
    "name:eng_x_preferred":[
        "Perukia"
    ],
    "wof:name":"Perukia",
    "wof:placetype":"locality",
    "wof:population":0
},
  "geometry": {"coordinates":[83.26694999999999,25.065278],"type":"Point"}
}