{
  "type": "Feature",
  "properties": {
    "gn:admin1_code":"34.0",
    "gn:admin2_code":"232.0",
    "gn:asciiname":"Dhanrajepur",
    "gn:country_code":"IN",
    "gn:dem":65,
    "gn:feature_class":"P",
    "gn:feature_code":"PPL",
    "gn:name":"Dhanrajepur",
    "gn:population":0,
    "gn:timezone":"Asia/Kolkata",
    "iso:country":"IN",
    "wof:name":"Dhanrajepur",
    "wof:placetype":"locality"
},
  "geometry": {"coordinates":[84.11991,25.616],"type":"Point"}
}