{
  "type": "Feature",
  "properties": {
    "iso:country":"IN",
    "ks:ks_name":"Sutharo Ki Dhani",
    "ks:ks_pop":8,
    "ks:ks_type":"HABITATION",
    "name:eng_x_preferred":[
        "Sutharo Ki Dhani"
    ],
    "wof:name":"Sutharo Ki Dhani",
    "wof:placetype":"locality",
    "wof:population":8
},
  "geometry": {"coordinates":[70.877397,27.172708],"type":"Point"}
}