{
  "type": "Feature",
  "properties": {
    "iso:country":"IN",
    "ks:ks_name":"Takipur Tulsi",
    "ks:ks_pop":127,
    "ks:ks_type":"VILLAGE",
    "ks:ks_uagg_main":0,
    "name:eng_x_preferred":[
        "Takipur Tulsi"
    ],
    "wof:name":"Takipur Tulsi",
    "wof:placetype":"neighbourhood",
    "wof:population":127
},
  "geometry": {"coordinates":[78.44104299999999,29.446671],"type":"Point"}
}