{
  "type": "Feature",
  "properties": {
    "gn:admin1_code":"34",
    "gn:admin2_code":"234.0",
    "gn:asciiname":"Mahaicha",
    "gn:country_code":"IN",
    "gn:dem":104,
    "gn:feature_class":"P",
    "gn:feature_code":"PPL",
    "gn:name":"Mahaicha",
    "gn:population":0,
    "gn:timezone":"Asia/Kolkata",
    "iso:country":"IN",
    "ks:ks_name":"Maihaicha",
    "ks:ks_pop":334,
    "ks:ks_type":"VILLAGE",
    "name:eng_x_preferred":[
        "Maihaicha"
    ],
    "name:eng_x_variant":[
        "Mahaicha"
    ],
    "wof:name":"Maihaicha",
    "wof:placetype":"locality",
    "wof:population":334
},
  "geometry": {"coordinates":[83.82711500000001,24.887869],"type":"Point"}
}