{
  "type": "Feature",
  "properties": {
    "iso:country":"IN",
    "ks:ks_name":"Chamaranpurwa",
    "ks:ks_pop":231,
    "ks:ks_type":"HABITATION",
    "name:eng_x_preferred":[
        "Chamaranpurwa"
    ],
    "wof:name":"Chamaranpurwa",
    "wof:placetype":"locality",
    "wof:population":231
},
  "geometry": {"coordinates":[80.78255799999999,27.720461],"type":"Point"}
}