{
  "type": "Feature",
  "properties": {
    "iso:country":"IN",
    "ks:ks_name":"Amrutpur",
    "ks:ks_pop":545,
    "ks:ks_type":"VILLAGE",
    "ks:ks_uagg_main":0,
    "name:eng_x_preferred":[
        "Amrutpur"
    ],
    "wof:name":"Amrutpur",
    "wof:placetype":"neighbourhood",
    "wof:population":545
},
  "geometry": {"coordinates":[86.77794799999999,20.953908],"type":"Point"}
}