{
  "type": "Feature",
  "properties": {
    "iso:country":"IN",
    "ks:ks_name":"Thandapur",
    "ks:ks_pop":495,
    "ks:ks_type":"VILLAGE",
    "ks:ks_uagg_main":0,
    "name:eng_x_preferred":[
        "Thandapur"
    ],
    "wof:name":"Thandapur",
    "wof:placetype":"neighbourhood",
    "wof:population":495
},
  "geometry": {"coordinates":[92.591196,24.87383],"type":"Point"}
}