{
  "type": "Feature",
  "properties": {
    "iso:country":"IN",
    "ks:ks_name":"Savra Para",
    "ks:ks_pop":116,
    "ks:ks_type":"HABITATION",
    "name:eng_x_preferred":[
        "Savra Para"
    ],
    "wof:name":"Savra Para",
    "wof:placetype":"locality",
    "wof:population":116
},
  "geometry": {"coordinates":[82.155328,19.203826],"type":"Point"}
}