{
  "type": "Feature",
  "properties": {
    "iso:country":"IN",
    "ks:ks_name":"Parashu Rampur",
    "ks:ks_pop":384,
    "ks:ks_type":"VILLAGE",
    "ks:ks_uagg_main":0,
    "name:eng_x_preferred":[
        "Parashu Rampur"
    ],
    "wof:name":"Parashu Rampur",
    "wof:placetype":"neighbourhood",
    "wof:population":384
},
  "geometry": {"coordinates":[83.877456,26.809017],"type":"Point"}
}