{
  "type": "Feature",
  "properties": {
    "gn:admin1_code":"25.0",
    "gn:asciiname":"Narapparajakhandrika",
    "gn:country_code":"IN",
    "gn:dem":79,
    "gn:feature_class":"P",
    "gn:feature_code":"PPL",
    "gn:name":"Narappar\u0101jakhandrika",
    "gn:population":0,
    "gn:timezone":"Asia/Kolkata",
    "iso:country":"IN",
    "wof:name":"Narapparajakhandrika",
    "wof:placetype":"neighbourhood"
},
  "geometry": {"coordinates":[79.78700000000001,13.23445],"type":"Point"}
}