{
  "type": "Feature",
  "properties": {
    "iso:country":"IN",
    "ks:ks_alt_nam":"BIHRA",
    "ks:ks_name":"Bihra",
    "ks:ks_pop":1198,
    "ks:ks_type":"HABITATION",
    "name:eng_x_preferred":[
        "Bihra"
    ],
    "wof:name":"Bihra",
    "wof:placetype":"locality",
    "wof:population":1198
},
  "geometry": {"coordinates":[84.382696,23.963181],"type":"Point"}
}