{
  "type": "Feature",
  "properties": {
    "gn:admin1_code":"34.0",
    "gn:admin2_code":"217.0",
    "gn:asciiname":"Mathurapur",
    "gn:country_code":"IN",
    "gn:dem":71,
    "gn:feature_class":"P",
    "gn:feature_code":"PPL",
    "gn:name":"Mathur\u0101pur",
    "gn:population":0,
    "gn:timezone":"Asia/Kolkata",
    "iso:country":"IN",
    "ks:ks_alt_nam":"Mathur\u0101pur",
    "ks:ks_name":"Mathurapur",
    "ks:ks_pop":454,
    "ks:ks_type":"VILLAGE",
    "ks:ks_uagg_main":0,
    "name:eng_x_preferred":[
        "Mathurapur"
    ],
    "name:eng_x_variant":[
        "Mathur\u0101pur"
    ],
    "wof:name":"Mathurapur",
    "wof:placetype":"neighbourhood",
    "wof:population":454
},
  "geometry": {"coordinates":[84.549319,26.337205],"type":"Point"}
}