{
  "type": "Feature",
  "properties": {
    "iso:country":"IN",
    "ks:ks_name":"Nallisalu",
    "ks:ks_pop":9,
    "ks:ks_type":"HABITATION",
    "name:eng_x_preferred":[
        "Nallisalu"
    ],
    "wof:name":"Nallisalu",
    "wof:placetype":"locality",
    "wof:population":9
},
  "geometry": {"coordinates":[74.690488,14.869877],"type":"Point"}
}