{
  "type": "Feature",
  "properties": {
    "gn:admin1_code":"35.0",
    "gn:admin2_code":"455.0",
    "gn:asciiname":"Chhipanala",
    "gn:country_code":"IN",
    "gn:dem":627,
    "gn:feature_class":"P",
    "gn:feature_code":"PPL",
    "gn:name":"Chh\u012bp\u0101n\u0101la",
    "gn:population":0,
    "gn:timezone":"Asia/Kolkata",
    "iso:country":"IN",
    "ks:ks_alt_nam":"Chh\u012bp\u0101n\u0101la",
    "ks:ks_name":"Chhipanala",
    "ks:ks_type":"VILLAGE",
    "name:eng_x_preferred":[
        "Chhipanala"
    ],
    "name:eng_x_variant":[
        "Chh\u012bp\u0101n\u0101la"
    ],
    "wof:name":"Chhipanala",
    "wof:placetype":"locality"
},
  "geometry": {"coordinates":[78.595843,21.932295],"type":"Point"}
}