{
  "type": "Feature",
  "properties": {
    "iso:country":"IN",
    "ks:ks_name":"Kozhinjikattur",
    "ks:ks_pop":575,
    "ks:ks_type":"HABITATION",
    "name:eng_x_preferred":[
        "Kozhinjikattur"
    ],
    "wof:name":"Kozhinjikattur",
    "wof:placetype":"locality",
    "wof:population":575
},
  "geometry": {"coordinates":[77.907991,11.519103],"type":"Point"}
}