{
  "type": "Feature",
  "properties": {
    "iso:country":"IN",
    "ks:ks_name":"Panch Pukhuria",
    "ks:ks_pop":0,
    "ks:ks_type":"VILLAGE",
    "name:eng_x_preferred":[
        "Panch Pukhuria"
    ],
    "wof:name":"Panch Pukhuria",
    "wof:placetype":"locality",
    "wof:population":0
},
  "geometry": {"coordinates":[87.34953899999999,23.837664],"type":"Point"}
}