{
  "type": "Feature",
  "properties": {
    "iso:country":"IN",
    "ks:ks_name":"Karunkadu",
    "ks:ks_pop":135,
    "ks:ks_type":"HABITATION",
    "name:eng_x_preferred":[
        "Karunkadu"
    ],
    "wof:name":"Karunkadu",
    "wof:placetype":"locality",
    "wof:population":135
},
  "geometry": {"coordinates":[79.06993799999999,10.07027],"type":"Point"}
}