{
  "type": "Feature",
  "properties": {
    "gn:admin1_code":"34.0",
    "gn:admin2_code":"207.0",
    "gn:asciiname":"Rampur",
    "gn:country_code":"IN",
    "gn:dem":68,
    "gn:feature_class":"P",
    "gn:feature_code":"PPL",
    "gn:name":"R\u0101mpur",
    "gn:population":0,
    "gn:timezone":"Asia/Kolkata",
    "iso:country":"IN",
    "wof:name":"Rampur",
    "wof:placetype":"locality"
},
  "geometry": {"coordinates":[86.30488000000003,26.43785],"type":"Point"}
}