{
  "type": "Feature",
  "properties": {
    "gn:admin1_code":"09",
    "gn:admin2_code":"474.0",
    "gn:asciiname":"Vehelal",
    "gn:country_code":"IN",
    "gn:dem":64,
    "gn:feature_class":"P",
    "gn:feature_code":"PPL",
    "gn:name":"Vehel\u0101l",
    "gn:population":0,
    "gn:timezone":"Asia/Kolkata",
    "iso:country":"IN",
    "name:und_x_variant":[
        "Vahelala",
        "Vehel\u0101l"
    ],
    "wof:name":"Vehelal",
    "wof:placetype":"locality"
},
  "geometry": {"coordinates":[72.75928,23.07792],"type":"Point"}
}