{
  "type": "Feature",
  "properties": {
    "iso:country":"IN",
    "ks:ks_name":"Da Barahi No1",
    "ks:ks_pop":265,
    "ks:ks_type":"HABITATION",
    "name:eng_x_preferred":[
        "Da Barahi No1"
    ],
    "wof:name":"Da Barahi No1",
    "wof:placetype":"locality",
    "wof:population":265
},
  "geometry": {"coordinates":[94.062556,26.480006],"type":"Point"}
}