{
  "type": "Feature",
  "properties": {
    "iso:country":"IN",
    "ks:ks_name":"Upper Langsomepi",
    "ks:ks_pop":537,
    "ks:ks_type":"HABITATION",
    "name:eng_x_preferred":[
        "Upper Langsomepi"
    ],
    "wof:name":"Upper Langsomepi",
    "wof:placetype":"locality",
    "wof:population":537
},
  "geometry": {"coordinates":[93.816818,26.346268],"type":"Point"}
}