{
  "type": "Feature",
  "properties": {
    "gn:admin1_code":"36.0",
    "gn:admin2_code":"175.0",
    "gn:asciiname":"Shah Muhammadpur",
    "gn:country_code":"IN",
    "gn:dem":97,
    "gn:feature_class":"P",
    "gn:feature_code":"PPL",
    "gn:name":"Sh\u0101h Muhammadpur",
    "gn:population":0,
    "gn:timezone":"Asia/Kolkata",
    "iso:country":"IN",
    "ks:ks_name":"Shah Mohamdpur",
    "ks:ks_pop":324,
    "ks:ks_type":"VILLAGE",
    "ks:ks_uagg_main":0,
    "name:eng_x_preferred":[
        "Shah Mohamdpur"
    ],
    "wof:name":"Shah Mohamdpur",
    "wof:placetype":"neighbourhood",
    "wof:population":324
},
  "geometry": {"coordinates":[81.95862099999999,25.439659],"type":"Point"}
}