{
  "type": "Feature",
  "properties": {
    "iso:country":"IN",
    "ks:ks_alt_nam":"dalavipada",
    "ks:ks_name":"Dalavipada",
    "ks:ks_pop":56,
    "ks:ks_type":"HABITATION",
    "name:eng_x_preferred":[
        "Dalavipada"
    ],
    "wof:name":"Dalavipada",
    "wof:placetype":"locality",
    "wof:population":56
},
  "geometry": {"coordinates":[73.16560800000001,19.681901],"type":"Point"}
}