{
  "type": "Feature",
  "properties": {
    "iso:country":"IN",
    "ks:ks_name":"Surudipai",
    "ks:ks_pop":29,
    "ks:ks_type":"VILLAGE",
    "name:eng_x_preferred":[
        "Surudipai"
    ],
    "wof:name":"Surudipai",
    "wof:placetype":"locality",
    "wof:population":29
},
  "geometry": {"coordinates":[83.418587,19.633227],"type":"Point"}
}