{
  "type": "Feature",
  "properties": {
    "iso:country":"IN",
    "ks:ks_name":"Suraj Pahar Tetartoli",
    "ks:ks_pop":108,
    "ks:ks_type":"HABITATION",
    "name:eng_x_preferred":[
        "Suraj Pahar Tetartoli"
    ],
    "wof:name":"Suraj Pahar Tetartoli",
    "wof:placetype":"locality",
    "wof:population":108
},
  "geometry": {"coordinates":[84.490703,22.519685],"type":"Point"}
}