{
  "type": "Feature",
  "properties": {
    "gn:admin1_code":"36",
    "gn:admin2_code":"158.0",
    "gn:asciiname":"Kuti Baba Jungh Das",
    "gn:country_code":"IN",
    "gn:dem":112,
    "gn:feature_class":"P",
    "gn:feature_code":"PPL",
    "gn:name":"Kuti B\u0101ba Jungh D\u0101s",
    "gn:population":0,
    "gn:timezone":"Asia/Kolkata",
    "iso:country":"IN",
    "wof:name":"Kuti Baba Jungh Das",
    "wof:placetype":"locality"
},
  "geometry": {"coordinates":[81.27127,26.12375],"type":"Point"}
}