{
  "type": "Feature",
  "properties": {
    "iso:country":"IN",
    "ks:ks_name":"Kherkhedikhurd",
    "ks:ks_pop":258,
    "ks:ks_type":"VILLAGE",
    "name:eng_x_preferred":[
        "Kherkhedikhurd"
    ],
    "wof:name":"Kherkhedikhurd",
    "wof:placetype":"locality",
    "wof:population":258
},
  "geometry": {"coordinates":[76.608597,24.141109],"type":"Point"}
}