{
  "type": "Feature",
  "properties": {
    "iso:country":"IN",
    "ks:ks_alt_nam":"lakshamvidu colony",
    "ks:ks_name":"Lakshamvidu Colony",
    "ks:ks_pop":694,
    "ks:ks_type":"HABITATION",
    "name:eng_x_preferred":[
        "Lakshamvidu Colony"
    ],
    "wof:name":"Lakshamvidu Colony",
    "wof:placetype":"locality",
    "wof:population":694
},
  "geometry": {"coordinates":[75.690668,11.61528],"type":"Point"}
}