{
  "type": "Feature",
  "properties": {
    "gn:admin1_code":"19.0",
    "gn:admin2_code":"560.0",
    "gn:asciiname":"Adur",
    "gn:country_code":"IN",
    "gn:dem":606,
    "gn:feature_class":"P",
    "gn:feature_code":"PPL",
    "gn:name":"\u0100d\u016br",
    "gn:population":0,
    "gn:timezone":"Asia/Kolkata",
    "iso:country":"IN",
    "name:cat_x_preferred":[
        "Adur"
    ],
    "name:ceb_x_preferred":[
        "Adur"
    ],
    "name:deu_x_preferred":[
        "Adur"
    ],
    "name:fra_x_preferred":[
        "Adur"
    ],
    "name:kat_x_preferred":[
        "\u10d0\u10d3\u10e3\u10e0\u10d8"
    ],
    "name:pol_x_preferred":[
        "Adur"
    ],
    "name:rus_x_preferred":[
        "\u0410\u0434\u0443\u0440"
    ],
    "name:spa_x_preferred":[
        "Adur"
    ],
    "name:swe_x_preferred":[
        "Adur"
    ],
    "wof:name":"Adur",
    "wof:placetype":"neighbourhood"
},
  "geometry": {"coordinates":[75.98087,15.53046],"type":"Point"}
}