{
  "type": "Feature",
  "properties": {
    "gn:admin1_code":"36",
    "gn:admin2_code":"143.0",
    "gn:asciiname":"Hardaspur",
    "gn:country_code":"IN",
    "gn:dem":190,
    "gn:feature_class":"P",
    "gn:feature_code":"PPL",
    "gn:name":"Hard\u0101spur",
    "gn:population":0,
    "gn:timezone":"Asia/Kolkata",
    "iso:country":"IN",
    "ks:ks_alt_nam":"Hard\u0101spur",
    "ks:ks_name":"Hardaspur",
    "ks:ks_pop":1424,
    "ks:ks_type":"VILLAGE",
    "ks:ks_uagg_main":0,
    "name:eng_x_preferred":[
        "Hardaspur"
    ],
    "name:eng_x_variant":[
        "Hard\u0101spur"
    ],
    "wof:name":"Hardaspur",
    "wof:placetype":"locality",
    "wof:population":1424
},
  "geometry": {"coordinates":[78.01568899999999,27.898595],"type":"Point"}
}