{
  "type": "Feature",
  "properties": {
    "iso:country":"IN",
    "ks:ks_name":"Harijanbasti",
    "ks:ks_pop":402,
    "ks:ks_type":"HABITATION",
    "name:eng_x_preferred":[
        "Harijanbasti"
    ],
    "wof:name":"Harijanbasti",
    "wof:placetype":"locality",
    "wof:population":402
},
  "geometry": {"coordinates":[83.262322,24.474268],"type":"Point"}
}