{
  "type": "Feature",
  "properties": {
    "iso:country":"IN",
    "ks:ks_name":"Muslim Tola",
    "ks:ks_pop":516,
    "ks:ks_type":"HABITATION",
    "name:eng_x_preferred":[
        "Muslim Tola"
    ],
    "wof:name":"Muslim Tola",
    "wof:placetype":"locality",
    "wof:population":516
},
  "geometry": {"coordinates":[85.32017399999999,25.830083],"type":"Point"}
}