{
  "type": "Feature",
  "properties": {
    "gn:admin1_code":"36",
    "gn:admin2_code":"156.0",
    "gn:asciiname":"Baba Khera",
    "gn:country_code":"IN",
    "gn:dem":122,
    "gn:feature_class":"P",
    "gn:feature_code":"PPL",
    "gn:name":"B\u0101ba Khera",
    "gn:population":0,
    "gn:timezone":"Asia/Kolkata",
    "iso:country":"IN",
    "ks:ks_alt_nam":"baba khera",
    "ks:ks_name":"Baba Khera",
    "ks:ks_pop":399,
    "ks:ks_type":"HABITATION",
    "ks:ks_uagg_main":0,
    "name:eng_x_preferred":[
        "Baba Khera"
    ],
    "wof:name":"Baba Khera",
    "wof:placetype":"neighbourhood",
    "wof:population":399
},
  "geometry": {"coordinates":[80.831114,26.548971],"type":"Point"}
}