{
  "type": "Feature",
  "properties": {
    "iso:country":"IN",
    "ks:ks_name":"Hardo Patti",
    "ks:ks_type":"VILLAGE",
    "name:eng_x_preferred":[
        "Hardo Patti"
    ],
    "wof:name":"Hardo Patti",
    "wof:placetype":"locality"
},
  "geometry": {"coordinates":[79.73688199999999,27.792147],"type":"Point"}
}