{
  "type": "Feature",
  "properties": {
    "iso:country":"IN",
    "ks:ks_name":"Bariasirsa",
    "ks:ks_pop":153,
    "ks:ks_type":"VILLAGE",
    "name:eng_x_preferred":[
        "Bariasirsa"
    ],
    "wof:name":"Bariasirsa",
    "wof:placetype":"locality",
    "wof:population":153
},
  "geometry": {"coordinates":[87.47673899999999,25.118221],"type":"Point"}
}