{
  "type": "Feature",
  "properties": {
    "gn:admin1_code":"35",
    "gn:admin2_code":"453.0",
    "gn:asciiname":"Jarasurang",
    "gn:country_code":"IN",
    "gn:dem":778,
    "gn:feature_class":"P",
    "gn:feature_code":"PPL",
    "gn:name":"J\u0101r\u0101surang",
    "gn:population":0,
    "gn:timezone":"Asia/Kolkata",
    "iso:country":"IN",
    "ks:ks_name":"Jadasurang",
    "ks:ks_pop":771,
    "ks:ks_type":"HABITATION",
    "name:eng_x_preferred":[
        "Jadasurang"
    ],
    "name:eng_x_variant":[
        "Jarasurang"
    ],
    "wof:name":"Jadasurang",
    "wof:placetype":"locality",
    "wof:population":771
},
  "geometry": {"coordinates":[81.19109400000001,22.639619],"type":"Point"}
}