{
  "type": "Feature",
  "properties": {
    "iso:country":"IN",
    "ks:ks_name":"Rol",
    "ks:ks_pop":3411,
    "ks:ks_type":"VILLAGE",
    "name:eng_x_preferred":[
        "Rol"
    ],
    "wof:name":"Rol",
    "wof:placetype":"locality",
    "wof:population":3411
},
  "geometry": {"coordinates":[87.650363,23.176985],"type":"Point"}
}