{
  "type": "Feature",
  "properties": {
    "iso:country":"IN",
    "ks:ks_name":"Gairi",
    "ks:ks_pop":102,
    "ks:ks_type":"HABITATION",
    "name:eng_x_preferred":[
        "Gairi"
    ],
    "wof:name":"Gairi",
    "wof:placetype":"locality",
    "wof:population":102
},
  "geometry": {"coordinates":[80.082587,29.459237],"type":"Point"}
}