{
  "type": "Feature",
  "properties": {
    "iso:country":"IN",
    "ks:ks_name":"Sabhahitarmane",
    "ks:ks_pop":25,
    "ks:ks_type":"HABITATION",
    "name:eng_x_preferred":[
        "Sabhahitarmane"
    ],
    "wof:name":"Sabhahitarmane",
    "wof:placetype":"locality",
    "wof:population":25
},
  "geometry": {"coordinates":[74.6062,14.66435],"type":"Point"}
}