{
  "type": "Feature",
  "properties": {
    "gn:admin1_code":"09",
    "gn:admin2_code":"471.0",
    "gn:asciiname":"Sardarpur",
    "gn:country_code":"IN",
    "gn:dem":141,
    "gn:feature_class":"P",
    "gn:feature_code":"PPL",
    "gn:name":"Sard\u0101rpur",
    "gn:population":0,
    "gn:timezone":"Asia/Kolkata",
    "iso:country":"IN",
    "ks:ks_alt_nam":"Sard\u0101rpur",
    "ks:ks_name":"Sardarpur",
    "ks:ks_pop":3724,
    "ks:ks_type":"VILLAGE",
    "ks:ks_uagg_main":0,
    "name:ben_x_preferred":[
        "\u09b8\u09b0\u09a6\u09be\u09b0\u09aa\u09c1\u09b0"
    ],
    "name:bpy_x_preferred":[
        "\u09b8\u09b0\u09a6\u09be\u09b0\u09aa\u09c1\u09b0"
    ],
    "name:cat_x_preferred":[
        "Sardarpur"
    ],
    "name:ceb_x_preferred":[
        "Sird\u0101rpore"
    ],
    "name:eng_x_preferred":[
        "Sardarpur"
    ],
    "name:eng_x_variant":[
        "Sard\u0101rpur"
    ],
    "name:ita_x_preferred":[
        "Sardarpur"
    ],
    "name:mlg_x_preferred":[
        "Sardarpur"
    ],
    "name:msa_x_preferred":[
        "Sardarpur"
    ],
    "name:nld_x_preferred":[
        "Sardarpur"
    ],
    "name:por_x_preferred":[
        "Sardarpur"
    ],
    "name:swe_x_preferred":[
        "Sird\u0101rpore"
    ],
    "name:vie_x_preferred":[
        "Sardarpur"
    ],
    "name:zho_x_preferred":[
        "\u8428\u5c14\u8fbe\u5c14\u666e\u5c14"
    ],
    "wof:name":"Sardarpur",
    "wof:placetype":"neighbourhood",
    "wof:population":3724
},
  "geometry": {"coordinates":[72.76918999999999,23.68929],"type":"Point"}
}