{
  "type": "Feature",
  "properties": {
    "iso:country":"IN",
    "ks:ks_name":"Bheruadol",
    "ks:ks_pop":955,
    "ks:ks_type":"HABITATION",
    "name:eng_x_preferred":[
        "Bheruadol"
    ],
    "wof:name":"Bheruadol",
    "wof:placetype":"locality",
    "wof:population":955
},
  "geometry": {"coordinates":[91.83872700000001,26.474186],"type":"Point"}
}