{
  "type": "Feature",
  "properties": {
    "iso:country":"IN",
    "ks:ks_alt_nam":"AGORE",
    "ks:ks_name":"Agore",
    "ks:ks_pop":160,
    "ks:ks_type":"HABITATION",
    "name:eng_x_preferred":[
        "Agore"
    ],
    "wof:name":"Agore",
    "wof:placetype":"locality",
    "wof:population":160
},
  "geometry": {"coordinates":[71.11051399999999,25.517078],"type":"Point"}
}