{
  "type": "Feature",
  "properties": {
    "gn:admin1_code":"19",
    "gn:admin2_code":"579.0",
    "gn:asciiname":"Balwandgi",
    "gn:country_code":"IN",
    "gn:dem":407,
    "gn:feature_class":"P",
    "gn:feature_code":"PPL",
    "gn:name":"Balwandgi",
    "gn:population":0,
    "gn:timezone":"Asia/Kolkata",
    "iso:country":"IN",
    "wof:name":"Balwandgi",
    "wof:placetype":"locality"
},
  "geometry": {"coordinates":[76.49824,17.05851],"type":"Point"}
}