{
  "type": "Feature",
  "properties": {
    "iso:country":"IN",
    "ks:ks_name":"Gotlapadu",
    "ks:ks_pop":66,
    "ks:ks_type":"HABITATION",
    "name:eng_x_preferred":[
        "Gotlapadu"
    ],
    "wof:name":"Gotlapadu",
    "wof:placetype":"locality",
    "wof:population":66
},
  "geometry": {"coordinates":[82.013856,17.629824],"type":"Point"}
}