{
  "type": "Feature",
  "properties": {
    "iso:country":"IN",
    "ks:ks_name":"Kotulbeda",
    "ks:ks_pop":119,
    "ks:ks_type":"HABITATION",
    "name:eng_x_preferred":[
        "Kotulbeda"
    ],
    "wof:name":"Kotulbeda",
    "wof:placetype":"locality",
    "wof:population":119
},
  "geometry": {"coordinates":[80.981691,20.090731],"type":"Point"}
}