{
  "type": "Feature",
  "properties": {
    "iso:country":"IN",
    "ks:ks_alt_nam":"SAIDAHA JALALPUR",
    "ks:ks_name":"Saidaha Jalalpur",
    "ks:ks_pop":651,
    "ks:ks_type":"HABITATION",
    "name:eng_x_preferred":[
        "Saidaha Jalalpur"
    ],
    "wof:name":"Saidaha Jalalpur",
    "wof:placetype":"locality",
    "wof:population":651
},
  "geometry": {"coordinates":[82.13191999999999,25.45926],"type":"Point"}
}