{
  "type": "Feature",
  "properties": {
    "iso:country":"IN",
    "ks:ks_name":"Ajjapanmanekeri",
    "ks:ks_pop":291,
    "ks:ks_type":"HABITATION",
    "name:eng_x_preferred":[
        "Ajjapanmanekeri"
    ],
    "wof:name":"Ajjapanmanekeri",
    "wof:placetype":"locality",
    "wof:population":291
},
  "geometry": {"coordinates":[74.575132,13.940022],"type":"Point"}
}