{
  "type": "Feature",
  "properties": {
    "gn:admin1_code":"36.0",
    "gn:admin2_code":"155",
    "gn:asciiname":"Malin Purwa",
    "gn:country_code":"IN",
    "gn:dem":135,
    "gn:feature_class":"P",
    "gn:feature_code":"PPL",
    "gn:name":"M\u0101lin Purwa",
    "gn:population":0,
    "gn:timezone":"Asia/Kolkata",
    "iso:country":"IN",
    "ks:ks_name":"Malir Purwa",
    "ks:ks_pop":188,
    "ks:ks_type":"HABITATION",
    "name:eng_x_preferred":[
        "Malir Purwa"
    ],
    "name:eng_x_variant":[
        "Malin Purwa"
    ],
    "wof:name":"Malir Purwa",
    "wof:placetype":"locality",
    "wof:population":188
},
  "geometry": {"coordinates":[79.860097,27.196414],"type":"Point"}
}