{
  "type": "Feature",
  "properties": {
    "iso:country":"IN",
    "ks:ks_name":"No 8 G B Para",
    "ks:ks_pop":1975,
    "ks:ks_type":"HABITATION",
    "name:eng_x_preferred":[
        "No 8 G B Para"
    ],
    "wof:name":"No 8 G B Para",
    "wof:placetype":"locality",
    "wof:population":1975
},
  "geometry": {"coordinates":[88.64870500000001,22.134769],"type":"Point"}
}