{
  "type": "Feature",
  "properties": {
    "gn:admin1_code":"35.0",
    "gn:admin2_code":"429.0",
    "gn:asciiname":"Piparawakhand",
    "gn:country_code":"IN",
    "gn:dem":384,
    "gn:feature_class":"P",
    "gn:feature_code":"PPL",
    "gn:name":"Pipar\u0101wakhand",
    "gn:population":0,
    "gn:timezone":"Asia/Kolkata",
    "iso:country":"IN",
    "wof:name":"Piparawakhand",
    "wof:placetype":"locality"
},
  "geometry": {"coordinates":[80.86338000000001,24.13726],"type":"Point"}
}