{
  "type": "Feature",
  "properties": {
    "gn:admin1_code":"12.0",
    "gn:admin2_code":"010",
    "gn:asciiname":"Sangam",
    "gn:country_code":"IN",
    "gn:dem":1587,
    "gn:feature_class":"P",
    "gn:feature_code":"PPL",
    "gn:name":"Sangam",
    "gn:population":0,
    "gn:timezone":"Asia/Kolkata",
    "iso:country":"IN",
    "name:ben_x_preferred":[
        "\u09b8\u0999\u09cd\u0997\u09ae"
    ],
    "name:bih_x_preferred":[
        "\u0938\u0902\u0917\u092e"
    ],
    "name:deu_x_preferred":[
        "Sangam"
    ],
    "name:hin_x_preferred":[
        "\u0938\u0902\u0917\u092e"
    ],
    "name:kan_x_preferred":[
        "\u0cb8\u0c82\u0c97\u0cae"
    ],
    "wof:name":"Sangam",
    "wof:placetype":"locality"
},
  "geometry": {"coordinates":[74.77058000000002,34.13695999999999],"type":"Point"}
}