{
  "type": "Feature",
  "properties": {
    "gn:admin1_code":"11",
    "gn:admin2_code":"23.0",
    "gn:asciiname":"Daunriaru",
    "gn:country_code":"IN",
    "gn:dem":2106,
    "gn:feature_class":"P",
    "gn:feature_code":"PPL",
    "gn:name":"Daunri\u0101ru",
    "gn:population":0,
    "gn:timezone":"Asia/Kolkata",
    "iso:country":"IN",
    "wof:name":"Daunriaru",
    "wof:placetype":"locality"
},
  "geometry": {"coordinates":[76.11413,32.38466],"type":"Point"}
}