{
  "type": "Feature",
  "properties": {
    "iso:country":"IN",
    "ks:ks_name":"Kasiapada",
    "ks:ks_pop":183,
    "ks:ks_type":"HABITATION",
    "name:eng_x_preferred":[
        "Kasiapada"
    ],
    "wof:name":"Kasiapada",
    "wof:placetype":"locality",
    "wof:population":183
},
  "geometry": {"coordinates":[85.645715,20.626501],"type":"Point"}
}