{
  "type": "Feature",
  "properties": {
    "iso:country":"IN",
    "ks:ks_name":"Mahawadiya",
    "ks:ks_pop":1194,
    "ks:ks_type":"HABITATION",
    "name:eng_x_preferred":[
        "Mahawadiya"
    ],
    "wof:name":"Mahawadiya",
    "wof:placetype":"locality",
    "wof:population":1194
},
  "geometry": {"coordinates":[77.398566,23.135245],"type":"Point"}
}