{
  "type": "Feature",
  "properties": {
    "iso:country":"IN",
    "ks:ks_alt_nam":"S\u0101her",
    "ks:ks_name":"Saher",
    "ks:ks_pop":2932,
    "ks:ks_type":"VILLAGE",
    "name:eng_x_preferred":[
        "Saher"
    ],
    "name:eng_x_variant":[
        "S\u0101her"
    ],
    "wof:name":"Saher",
    "wof:placetype":"locality",
    "wof:population":2932
},
  "geometry": {"coordinates":[85.170875,23.307499],"type":"Point"}
}