{
  "type": "Feature",
  "properties": {
    "iso:country":"IN",
    "ks:ks_name":"Jamdiha",
    "ks:ks_pop":882,
    "ks:ks_type":"VILLAGE",
    "name:eng_x_preferred":[
        "Jamdiha"
    ],
    "wof:name":"Jamdiha",
    "wof:placetype":"locality",
    "wof:population":882
},
  "geometry": {"coordinates":[85.495591,23.931834],"type":"Point"}
}