{
  "type": "Feature",
  "properties": {
    "gn:admin1_code":"37",
    "gn:admin2_code":"403.0",
    "gn:asciiname":"Bijepur",
    "gn:country_code":"IN",
    "gn:dem":225,
    "gn:feature_class":"P",
    "gn:feature_code":"PPL",
    "gn:name":"B\u012bjepur",
    "gn:population":0,
    "gn:timezone":"Asia/Kolkata",
    "iso:country":"IN",
    "name:ori_x_preferred":[
        "\u0b2c\u0b3f\u0b1c\u0b47\u0b2a\u0b41\u0b30"
    ],
    "wof:name":"Bijepur",
    "wof:placetype":"locality"
},
  "geometry": {"coordinates":[83.10185,21.58281],"type":"Point"}
}