{
  "type": "Feature",
  "properties": {
    "gn:admin1_code":"39.0",
    "gn:admin2_code":"63.0",
    "gn:asciiname":"Sirani",
    "gn:country_code":"IN",
    "gn:dem":1651,
    "gn:feature_class":"P",
    "gn:feature_code":"PPL",
    "gn:name":"Sir\u0101ni",
    "gn:population":0,
    "gn:timezone":"Asia/Kolkata",
    "iso:country":"IN",
    "name:deu_x_preferred":[
        "Sirani"
    ],
    "name:fra_x_preferred":[
        "Sirani"
    ],
    "name:ita_x_preferred":[
        "Sirani"
    ],
    "name:spa_x_preferred":[
        "Sirani"
    ],
    "wof:name":"Sirani",
    "wof:placetype":"locality"
},
  "geometry": {"coordinates":[79.64845,29.99386],"type":"Point"}
}