{
  "type": "Feature",
  "properties": {
    "iso:country":"IN",
    "ks:ks_name":"Kerekoppa",
    "ks:ks_pop":101,
    "ks:ks_type":"HABITATION",
    "name:eng_x_preferred":[
        "Kerekoppa"
    ],
    "wof:name":"Kerekoppa",
    "wof:placetype":"locality",
    "wof:population":101
},
  "geometry": {"coordinates":[75.164303,14.038528],"type":"Point"}
}