{
  "type": "Feature",
  "properties": {
    "iso:country":"IN",
    "ks:ks_name":"Khelajoypara",
    "ks:ks_pop":321,
    "ks:ks_type":"HABITATION",
    "name:eng_x_preferred":[
        "Khelajoypara"
    ],
    "wof:name":"Khelajoypara",
    "wof:placetype":"locality",
    "wof:population":321
},
  "geometry": {"coordinates":[92.093822,24.232057],"type":"Point"}
}