{
  "type": "Feature",
  "properties": {
    "gn:country":"IN",
    "gn:fcode":"PPL",
    "gn:pop":0,
    "iso:country":"IN",
    "name:dut_x_preferred":[
        "Uppala"
    ],
    "name:eng_x_preferred":[
        "Uppala"
    ],
    "name:mal_x_preferred":[
        "\u0d09\u0d2a\u0d4d\u0d2a\u0d33"
    ],
    "name:urd_x_preferred":[
        "\u0627\u064f\u067e\u0627\u0644\u0627"
    ],
    "qs:name":"Uppala",
    "qs:name_adm0":"India",
    "qs:name_adm1":"Kerala",
    "qs:photos_9k":1,
    "qs:photos_9r":1,
    "qs:photos_all":1,
    "qs:photos_sr":0,
    "qs:placetype":"Town",
    "qs:pop_sr":"0",
    "wd:wordcount":1763,
    "wof:name":"Uppala",
    "wof:placetype":"locality",
    "wof:population":0
},
  "geometry": {"coordinates":[74.90067999999999,12.68436],"type":"Point"}
}