{
  "type": "Feature",
  "properties": {
    "gn:admin1_code":"36.0",
    "gn:admin2_code":"183.0",
    "gn:asciiname":"Bagahi",
    "gn:country_code":"IN",
    "gn:dem":113,
    "gn:feature_class":"P",
    "gn:feature_code":"PPL",
    "gn:name":"Bag\u0101hi",
    "gn:population":0,
    "gn:timezone":"Asia/Kolkata",
    "iso:country":"IN",
    "name:fra_x_preferred":[
        "Bagahi"
    ],
    "name:pol_x_preferred":[
        "Bagahi"
    ],
    "wof:name":"Bagahi",
    "wof:placetype":"locality"
},
  "geometry": {"coordinates":[82.04956,27.31281],"type":"Point"}
}