{
  "type": "Feature",
  "properties": {
    "gn:admin1_code":"25.0",
    "gn:admin2_code":"619.0",
    "gn:asciiname":"Attikkottai",
    "gn:country_code":"IN",
    "gn:dem":30,
    "gn:feature_class":"P",
    "gn:feature_code":"PPL",
    "gn:name":"Attikkottai",
    "gn:population":0,
    "gn:timezone":"Asia/Kolkata",
    "iso:country":"IN",
    "ks:ks_name":"Athikkottai",
    "ks:ks_pop":1381,
    "ks:ks_type":"HABITATION",
    "name:eng_x_preferred":[
        "Athikkottai"
    ],
    "name:eng_x_variant":[
        "Attikkottai"
    ],
    "wof:name":"Athikkottai",
    "wof:placetype":"locality",
    "wof:population":1381
},
  "geometry": {"coordinates":[79.39769200000001,10.640457],"type":"Point"}
}