{
  "type": "Feature",
  "properties": {
    "iso:country":"IN",
    "ks:ks_name":"Sonaria",
    "ks:ks_pop":2370,
    "ks:ks_type":"VILLAGE",
    "ks:ks_uagg_main":0,
    "name:eng_x_preferred":[
        "Sonaria"
    ],
    "wof:name":"Sonaria",
    "wof:placetype":"locality",
    "wof:population":2370
},
  "geometry": {"coordinates":[88.18176200000001,22.352674],"type":"Point"}
}