{
  "type": "Feature",
  "properties": {
    "iso:country":"IN",
    "ks:ks_name":"Deonalya",
    "ks:ks_pop":3463,
    "ks:ks_type":"VILLAGE",
    "name:eng_x_preferred":[
        "Deonalya"
    ],
    "wof:name":"Deonalya",
    "wof:placetype":"locality",
    "wof:population":3463
},
  "geometry": {"coordinates":[75.208637,21.729196],"type":"Point"}
}