{
  "type": "Feature",
  "properties": {
    "iso:country":"IN",
    "ks:ks_name":"Gorapahar",
    "ks:ks_pop":234,
    "ks:ks_type":"HABITATION",
    "name:eng_x_preferred":[
        "Gorapahar"
    ],
    "wof:name":"Gorapahar",
    "wof:placetype":"locality",
    "wof:population":234
},
  "geometry": {"coordinates":[84.25423000000001,23.36318],"type":"Point"}
}