{
  "type": "Feature",
  "properties": {
    "iso:country":"IN",
    "ks:ks_alt_nam":"maruthammoodu",
    "ks:ks_name":"Maruthammoodu",
    "ks:ks_pop":2100,
    "ks:ks_type":"HABITATION",
    "name:eng_x_preferred":[
        "Maruthammoodu"
    ],
    "wof:name":"Maruthammoodu",
    "wof:placetype":"locality",
    "wof:population":2100
},
  "geometry": {"coordinates":[76.952461,8.685026],"type":"Point"}
}