{
  "type": "Feature",
  "properties": {
    "iso:country":"IN",
    "ks:ks_alt_nam":"Gopal Nagar of Kothavangallu",
    "ks:ks_name":"Gopal Nagar Of Kothavangallu",
    "ks:ks_pop":60,
    "ks:ks_type":"HABITATION",
    "name:eng_x_preferred":[
        "Gopal Nagar Of Kothavangallu"
    ],
    "wof:name":"Gopal Nagar Of Kothavangallu",
    "wof:placetype":"locality",
    "wof:population":60
},
  "geometry": {"coordinates":[79.929035,14.585836],"type":"Point"}
}