{
  "type": "Feature",
  "properties": {
    "gn:admin1_code":"34.0",
    "gn:admin2_code":"220.0",
    "gn:asciiname":"Terabasia Diara",
    "gn:country_code":"IN",
    "gn:dem":51,
    "gn:feature_class":"P",
    "gn:feature_code":"PPL",
    "gn:name":"Ter\u0101basia Di\u0101ra",
    "gn:population":0,
    "gn:timezone":"Asia/Kolkata",
    "iso:country":"IN",
    "wof:name":"Terabasia Diara",
    "wof:placetype":"locality"
},
  "geometry": {"coordinates":[85.24101,25.62624],"type":"Point"}
}