{
  "type": "Feature",
  "properties": {
    "iso:country":"IN",
    "ks:ks_name":"Hanotiya",
    "ks:ks_pop":346,
    "ks:ks_type":"VILLAGE",
    "name:eng_x_preferred":[
        "Hanotiya"
    ],
    "wof:name":"Hanotiya",
    "wof:placetype":"locality",
    "wof:population":346
},
  "geometry": {"coordinates":[77.26148999999999,25.370109],"type":"Point"}
}