{
  "type": "Feature",
  "properties": {
    "iso:country":"IN",
    "ks:ks_name":"Tambhari",
    "ks:ks_pop":292,
    "ks:ks_type":"HABITATION",
    "name:eng_x_preferred":[
        "Tambhari"
    ],
    "wof:name":"Tambhari",
    "wof:placetype":"locality",
    "wof:population":292
},
  "geometry": {"coordinates":[78.793785,20.531974],"type":"Point"}
}