{
  "type": "Feature",
  "properties": {
    "iso:country":"IN",
    "ks:ks_name":"Dhanoura",
    "ks:ks_pop":14,
    "ks:ks_type":"VILLAGE",
    "name:eng_x_preferred":[
        "Dhanoura"
    ],
    "wof:name":"Dhanoura",
    "wof:placetype":"locality",
    "wof:population":14
},
  "geometry": {"coordinates":[79.154183,24.137754],"type":"Point"}
}