{
  "type": "Feature",
  "properties": {
    "gn:country":"IN",
    "gn:fcode":"PPL",
    "gn:pop":0,
    "iso:country":"IN",
    "name:ben_x_preferred":[
        "\u09a8\u09be\u09af\u09bc\u09a8\u09be \u09a6\u09c7\u09ac\u09c0"
    ],
    "name:bpy_x_preferred":[
        "\u09a8\u09be\u09af\u09bc\u09a8\u09be \u09a6\u09c7\u09ac\u09c0"
    ],
    "name:deu_x_preferred":[
        "Naina Devi"
    ],
    "name:eng_x_preferred":[
        "Naina Devi"
    ],
    "name:fra_x_preferred":[
        "Naina Devi"
    ],
    "name:hin_x_preferred":[
        "\u0928\u0948\u0928\u093e \u0926\u0947\u0935\u0940 \u092e\u0902\u0926\u093f\u0930"
    ],
    "name:ita_x_preferred":[
        "Naina Devi"
    ],
    "name:mlg_x_preferred":[
        "Naina Devi"
    ],
    "name:msa_x_preferred":[
        "Naina Devi"
    ],
    "name:nan_x_preferred":[
        "Naina Devi"
    ],
    "name:new_x_preferred":[
        "\u0928\u0948\u0928\u093e \u0926\u0947\u0935\u0940"
    ],
    "name:nld_x_preferred":[
        "Naina Devi"
    ],
    "name:pan_x_preferred":[
        "\u0a28\u0a48\u0a23\u0a3e \u0a26\u0a47\u0a35\u0a40"
    ],
    "name:pnb_x_preferred":[
        "\u0646\u06cc\u0646\u0627 \u062f\u06cc\u0648\u06cc"
    ],
    "name:tam_x_preferred":[
        "\u0ba8\u0bc8\u0ba9\u0bbe \u0ba4\u0bc7\u0bb5\u0bbf"
    ],
    "name:tel_x_preferred":[
        "\u0c28\u0c48\u0c28\u0c3e \u0c26\u0c47\u0c35\u0c3f"
    ],
    "name:vie_x_preferred":[
        "Naina Devi"
    ],
    "name:zho_x_preferred":[
        "\u5948\u7eb3\u5fb7\u7ef4"
    ],
    "qs:name":"Naina Devi",
    "qs:name_adm0":"India",
    "qs:name_adm1":"Himachal Pradesh",
    "qs:photos":39,
    "qs:photos_1k":8,
    "qs:photos_9k":1,
    "qs:photos_9r":2,
    "qs:photos_all":39,
    "qs:photos_sr":2,
    "qs:placetype":"Town",
    "qs:pop_sr":"0",
    "wd:wordcount":920,
    "wof:name":"Naina Devi",
    "wof:placetype":"locality",
    "wof:population":0
},
  "geometry": {"coordinates":[76.86159000000001,30.72374],"type":"Point"}
}