{
  "type": "Feature",
  "properties": {
    "iso:country":"IN",
    "ks:ks_name":"Shivpur",
    "ks:ks_pop":305,
    "ks:ks_type":"HABITATION",
    "ks:ks_uagg_main":0,
    "name:eng_x_preferred":[
        "Shivpur"
    ],
    "wof:name":"Shivpur",
    "wof:placetype":"neighbourhood",
    "wof:population":305
},
  "geometry": {"coordinates":[84.220068,25.755291],"type":"Point"}
}