{
  "type": "Feature",
  "properties": {
    "gn:admin1_code":"9.0",
    "gn:admin2_code":"481",
    "gn:asciiname":"Chok",
    "gn:country_code":"IN",
    "gn:dem":52,
    "gn:feature_class":"P",
    "gn:feature_code":"PPL",
    "gn:name":"Chok",
    "gn:population":0,
    "gn:timezone":"Asia/Kolkata",
    "iso:country":"IN",
    "name:dan_x_preferred":[
        "Chok"
    ],
    "wof:name":"Chok",
    "wof:placetype":"locality"
},
  "geometry": {"coordinates":[71.76206999999999,21.41800000000001],"type":"Point"}
}