{
  "type": "Feature",
  "properties": {
    "gn:admin1_code":"9.0",
    "gn:admin2_code":"481",
    "gn:asciiname":"Chok",
    "gn:country_code":"IN",
    "gn:dem":52,
    "gn:feature_class":"P",
    "gn:feature_code":"PPL",
    "gn:name":"Chok",
    "gn:population":0,
    "gn:timezone":"Asia/Kolkata",
    "iso:country":"IN",
    "ks:ks_name":"Chok",
    "ks:ks_pop":1293,
    "ks:ks_type":"VILLAGE",
    "name:dan_x_preferred":[
        "Chok"
    ],
    "name:eng_x_preferred":[
        "Chok"
    ],
    "wof:name":"Chok",
    "wof:placetype":"locality",
    "wof:population":1293
},
  "geometry": {"coordinates":[71.76206999999999,21.417997],"type":"Point"}
}