{
  "type": "Feature",
  "properties": {
    "iso:country":"IN",
    "ks:ks_name":"Uchhati Beri",
    "ks:ks_pop":58,
    "ks:ks_type":"HABITATION",
    "name:eng_x_preferred":[
        "Uchhati Beri"
    ],
    "wof:name":"Uchhati Beri",
    "wof:placetype":"locality",
    "wof:population":58
},
  "geometry": {"coordinates":[73.36645,24.519414],"type":"Point"}
}