{
  "type": "Feature",
  "properties": {
    "iso:country":"IN",
    "ks:ks_name":"Sriramankulam",
    "ks:ks_pop":250,
    "ks:ks_type":"HABITATION",
    "name:eng_x_preferred":[
        "Sriramankulam"
    ],
    "wof:name":"Sriramankulam",
    "wof:placetype":"locality",
    "wof:population":250
},
  "geometry": {"coordinates":[77.80784,8.658145],"type":"Point"}
}