{
  "type": "Feature",
  "properties": {
    "iso:country":"IN",
    "ks:ks_name":"Chitoor",
    "ks:ks_pop":3274,
    "ks:ks_type":"HABITATION",
    "name:eng_x_preferred":[
        "Chitoor"
    ],
    "wof:name":"Chitoor",
    "wof:placetype":"locality",
    "wof:population":3274
},
  "geometry": {"coordinates":[76.271036,10.033654],"type":"Point"}
}