{
  "type": "Feature",
  "properties": {
    "iso:country":"IN",
    "ks:ks_name":"Jogiyakanali",
    "ks:ks_pop":31,
    "ks:ks_type":"VILLAGE",
    "name:eng_x_preferred":[
        "Jogiyakanali"
    ],
    "wof:name":"Jogiyakanali",
    "wof:placetype":"locality",
    "wof:population":31
},
  "geometry": {"coordinates":[86.77431,24.463894],"type":"Point"}
}