{
  "type": "Feature",
  "properties": {
    "gn:admin1_code":"11.0",
    "gn:admin2_code":"33.0",
    "gn:asciiname":"Barair",
    "gn:country_code":"IN",
    "gn:dem":1965,
    "gn:feature_class":"P",
    "gn:feature_code":"PPL",
    "gn:name":"Barair",
    "gn:population":0,
    "gn:timezone":"Asia/Kolkata",
    "iso:country":"IN",
    "wof:name":"Barair",
    "wof:placetype":"locality"
},
  "geometry": {"coordinates":[77.47870999999998,31.05599],"type":"Point"}
}