{
  "type": "Feature",
  "properties": {
    "gn:admin1_code":"24.0",
    "gn:admin2_code":"130.0",
    "gn:asciiname":"Patia",
    "gn:country_code":"IN",
    "gn:dem":559,
    "gn:feature_class":"P",
    "gn:feature_code":"PPL",
    "gn:name":"P\u0101tia",
    "gn:population":0,
    "gn:timezone":"Asia/Kolkata",
    "iso:country":"IN",
    "name:ara_x_preferred":[
        "\u0628\u0627\u062a\u064a\u0627"
    ],
    "name:ast_x_preferred":[
        "Patia"
    ],
    "name:ben_bn_x_preferred":[
        "\u09aa\u09be\u09a4\u09bf\u09df\u09be"
    ],
    "name:ben_in_x_preferred":[
        "\u09aa\u09be\u09a4\u09bf\u09df\u09be"
    ],
    "name:ceb_x_preferred":[
        "Patia"
    ],
    "name:fra_x_preferred":[
        "Patia"
    ],
    "name:guj_x_preferred":[
        "\u0aaa\u0a9f\u0abf\u0aaf\u0abe"
    ],
    "name:hin_x_preferred":[
        "\u092a\u093e\u091f\u093f\u092f\u093e"
    ],
    "name:kan_x_preferred":[
        "\u0caa\u0c9f\u0cbf\u0caf\u0cbe"
    ],
    "name:lat_x_preferred":[
        "Patia"
    ],
    "name:mal_x_preferred":[
        "\u0d2a\u0d3e\u0d1f\u0d4d\u0d1f\u0d3f\u0d2f"
    ],
    "name:mar_x_preferred":[
        "\u092a\u093e\u091f\u093f\u092f\u093e"
    ],
    "name:nld_x_preferred":[
        "Patia"
    ],
    "name:nor_x_preferred":[
        "Patia"
    ],
    "name:pan_x_preferred":[
        "\u0a2a\u0a1f\u0a40\u0a06"
    ],
    "name:rus_x_preferred":[
        "Patia"
    ],
    "name:spa_x_preferred":[
        "Patia"
    ],
    "name:swe_x_preferred":[
        "Patia"
    ],
    "name:tam_x_preferred":[
        "\u0baa\u0b9f\u0bbf\u0baf\u0bbe"
    ],
    "name:tel_x_preferred":[
        "\u0c2a\u0c3e\u0c1f\u0c3f\u0c2f\u0c3e"
    ],
    "name:urd_x_preferred":[
        "\u067e\u0679\u06cc\u0627"
    ],
    "name:vie_x_preferred":[
        "Patia"
    ],
    "name:war_x_preferred":[
        "Patia"
    ],
    "name:zho_x_preferred":[
        "\u676f\u7c89\u8776\u5c6c"
    ],
    "wof:name":"Patia",
    "wof:placetype":"locality"
},
  "geometry": {"coordinates":[73.39519,24.22348],"type":"Point"}
}