{
  "type": "Feature",
  "properties": {
    "iso:country":"IN",
    "ks:ks_name":"Goldahari",
    "ks:ks_pop":109,
    "ks:ks_type":"VILLAGE",
    "ks:ks_uagg_main":0,
    "name:eng_x_preferred":[
        "Goldahari"
    ],
    "wof:name":"Goldahari",
    "wof:placetype":"neighbourhood",
    "wof:population":109
},
  "geometry": {"coordinates":[87.29164900000001,22.671135],"type":"Point"}
}