{
  "type": "Feature",
  "properties": {
    "gn:admin1_code":"38",
    "gn:admin2_code":"347.0",
    "gn:asciiname":"Lowalang",
    "gn:country_code":"IN",
    "gn:dem":486,
    "gn:feature_class":"P",
    "gn:feature_code":"PPL",
    "gn:name":"Low\u0101l\u0101ng",
    "gn:population":0,
    "gn:timezone":"Asia/Kolkata",
    "iso:country":"IN",
    "wof:name":"Lowalang",
    "wof:placetype":"locality"
},
  "geometry": {"coordinates":[84.74011999999998,24.07499],"type":"Point"}
}