{
  "type": "Feature",
  "properties": {
    "gn:admin1_code":"12.0",
    "gn:admin2_code":"2.0",
    "gn:asciiname":"Gudur",
    "gn:country_code":"IN",
    "gn:dem":1600,
    "gn:feature_class":"P",
    "gn:feature_code":"PPL",
    "gn:name":"Gudur",
    "gn:population":0,
    "gn:timezone":"Asia/Kolkata",
    "iso:country":"IN",
    "name:hin_x_preferred":[
        "\u0917\u0941\u0921\u0942\u0930"
    ],
    "name:tel_x_preferred":[
        "\u0c17\u0c42\u0c21\u0c42\u0c30\u0c41"
    ],
    "name:urd_x_preferred":[
        "\u06af\u0648\u0688\u0648\u0631"
    ],
    "wof:name":"Gudur",
    "wof:placetype":"locality"
},
  "geometry": {"coordinates":[74.89549,33.90746],"type":"Point"}
}