{
  "type": "Feature",
  "properties": {
    "gn:admin1_code":"12.0",
    "gn:admin2_code":"2.0",
    "gn:asciiname":"Hamakhal",
    "gn:country_code":"IN",
    "gn:dem":2784,
    "gn:feature_class":"P",
    "gn:feature_code":"PPL",
    "gn:name":"Hamakhal",
    "gn:population":0,
    "gn:timezone":"Asia/Kolkata",
    "iso:country":"IN",
    "wof:name":"Hamakhal",
    "wof:placetype":"locality"
},
  "geometry": {"coordinates":[74.61094,33.81344],"type":"Point"}
}