{
  "type": "Feature",
  "properties": {
    "iso:country":"IN",
    "ks:ks_alt_nam":"M\u016bndka",
    "ks:ks_name":"Mundka",
    "ks:ks_type":"VILLAGE",
    "ks:ks_uagg_main":0,
    "name:eng_x_preferred":[
        "Mundka"
    ],
    "name:eng_x_variant":[
        "M\u016bndka"
    ],
    "wof:name":"Mundka",
    "wof:placetype":"neighbourhood"
},
  "geometry": {"coordinates":[77.029752,28.680117],"type":"Point"}
}