{
  "type": "Feature",
  "properties": {
    "gn:admin1_code":"11",
    "gn:admin2_code":"23.0",
    "gn:asciiname":"Ralosh",
    "gn:country_code":"IN",
    "gn:dem":3328,
    "gn:feature_class":"P",
    "gn:feature_code":"PPL",
    "gn:name":"Ralosh",
    "gn:population":0,
    "gn:timezone":"Asia/Kolkata",
    "iso:country":"IN",
    "wof:name":"Ralosh",
    "wof:placetype":"locality"
},
  "geometry": {"coordinates":[76.4513,33.14717],"type":"Point"}
}