{
  "type": "Feature",
  "properties": {
    "gn:admin1_code":"16.0",
    "gn:admin2_code":"504.0",
    "gn:asciiname":"Savli",
    "gn:country_code":"IN",
    "gn:dem":482,
    "gn:feature_class":"P",
    "gn:feature_code":"PPL",
    "gn:name":"S\u0101vli",
    "gn:population":0,
    "gn:timezone":"Asia/Kolkata",
    "iso:country":"IN",
    "name:ceb_x_preferred":[
        "S\u0101vli"
    ],
    "name:guj_x_preferred":[
        "\u0ab8\u0abe\u0ab5\u0ab2\u0ac0"
    ],
    "name:spa_x_preferred":[
        "Savli"
    ],
    "name:swe_x_preferred":[
        "S\u0101vli"
    ],
    "wof:name":"Savli",
    "wof:placetype":"locality"
},
  "geometry": {"coordinates":[78.52027,21.13519],"type":"Point"}
}