{
  "type": "Feature",
  "properties": {
    "gn:admin1_code":"36.0",
    "gn:admin2_code":"150.0",
    "gn:asciiname":"Bilaua Taluka Nagaria",
    "gn:country_code":"IN",
    "gn:dem":163,
    "gn:feature_class":"P",
    "gn:feature_code":"PPL",
    "gn:name":"Bilaua Taluka Nagaria",
    "gn:population":0,
    "gn:timezone":"Asia/Kolkata",
    "iso:country":"IN",
    "wof:name":"Bilaua Taluka Nagaria",
    "wof:placetype":"locality"
},
  "geometry": {"coordinates":[79.63916999999999,28.19984],"type":"Point"}
}