{
  "type": "Feature",
  "properties": {
    "iso:country":"IN",
    "ks:ks_name":"Chikhalgaon",
    "ks:ks_pop":9918,
    "ks:ks_type":"VILLAGE",
    "ks:ks_uagg_main":0,
    "name:eng_x_preferred":[
        "Chikhalgaon"
    ],
    "wof:name":"Chikhalgaon",
    "wof:placetype":"neighbourhood",
    "wof:population":9918
},
  "geometry": {"coordinates":[78.940594,20.067744],"type":"Point"}
}