{
  "type": "Feature",
  "properties": {
    "iso:country":"IN",
    "ks:ks_name":"Barbam Grant",
    "ks:ks_pop":3416,
    "ks:ks_type":"VILLAGE",
    "ks:ks_uagg_main":0,
    "name:eng_x_preferred":[
        "Barbam Grant"
    ],
    "wof:name":"Barbam Grant",
    "wof:placetype":"neighbourhood",
    "wof:population":3416
},
  "geometry": {"coordinates":[94.533312,26.804159],"type":"Point"}
}