{
  "type": "Feature",
  "properties": {
    "iso:country":"IN",
    "ks:ks_name":"Kharkaya",
    "ks:ks_pop":609,
    "ks:ks_type":"HABITATION",
    "name:eng_x_preferred":[
        "Kharkaya"
    ],
    "wof:name":"Kharkaya",
    "wof:placetype":"locality",
    "wof:population":609
},
  "geometry": {"coordinates":[73.427744,23.914261],"type":"Point"}
}