{
  "type": "Feature",
  "properties": {
    "iso:country":"IN",
    "ks:ks_name":"Amrattari",
    "ks:ks_pop":794,
    "ks:ks_type":"VILLAGE",
    "name:eng_x_preferred":[
        "Amrattari"
    ],
    "wof:name":"Amrattari",
    "wof:placetype":"locality",
    "wof:population":794
},
  "geometry": {"coordinates":[91.272113,26.286645],"type":"Point"}
}