{
  "type": "Feature",
  "properties": {
    "iso:country":"IN",
    "ks:ks_name":"Bukkigudde Kukkuje",
    "ks:ks_pop":37,
    "ks:ks_type":"HABITATION",
    "name:eng_x_preferred":[
        "Bukkigudde Kukkuje"
    ],
    "wof:name":"Bukkigudde Kukkuje",
    "wof:placetype":"locality",
    "wof:population":37
},
  "geometry": {"coordinates":[74.96102399999999,13.325624],"type":"Point"}
}