{
  "type": "Feature",
  "properties": {
    "iso:country":"IN",
    "ks:ks_name":"Talashi",
    "ks:ks_pop":65,
    "ks:ks_type":"VILLAGE",
    "name:eng_x_preferred":[
        "Talashi"
    ],
    "wof:name":"Talashi",
    "wof:placetype":"locality",
    "wof:population":65
},
  "geometry": {"coordinates":[84.30074999999999,19.02695],"type":"Point"}
}