{
  "type": "Feature",
  "properties": {
    "iso:country":"IN",
    "ks:ks_name":"Geengala",
    "ks:ks_pop":1539,
    "ks:ks_type":"VILLAGE",
    "name:eng_x_preferred":[
        "Geengala"
    ],
    "wof:name":"Geengala",
    "wof:placetype":"locality",
    "wof:population":1539
},
  "geometry": {"coordinates":[73.12617,26.87807],"type":"Point"}
}