{
  "type": "Feature",
  "properties": {
    "iso:country":"IN",
    "ks:ks_alt_nam":"Naw\u0101da",
    "ks:ks_name":"Nawada",
    "ks:ks_pop":461,
    "ks:ks_type":"VILLAGE",
    "name:eng_x_preferred":[
        "Nawada"
    ],
    "name:eng_x_variant":[
        "Naw\u0101da"
    ],
    "wof:name":"Nawada",
    "wof:placetype":"locality",
    "wof:population":461
},
  "geometry": {"coordinates":[85.49328,22.788434],"type":"Point"}
}