{
  "type": "Feature",
  "properties": {
    "gn:admin1_code":"36.0",
    "gn:admin2_code":"136.0",
    "gn:asciiname":"Bagi",
    "gn:country_code":"IN",
    "gn:dem":205,
    "gn:feature_class":"P",
    "gn:feature_code":"PPL",
    "gn:name":"Bag\u012b",
    "gn:population":0,
    "gn:timezone":"Asia/Kolkata",
    "iso:country":"IN",
    "name:ceb_x_preferred":[
        "Bagi"
    ],
    "name:deu_x_preferred":[
        "Bagi"
    ],
    "name:swe_x_preferred":[
        "Bagi"
    ],
    "wof:name":"Bagi",
    "wof:placetype":"locality"
},
  "geometry": {"coordinates":[79.1807,28.98562],"type":"Point"}
}