{
  "type": "Feature",
  "properties": {
    "gn:admin1_code":"12.0",
    "gn:admin2_code":"16.0",
    "gn:asciiname":"Draman",
    "gn:country_code":"IN",
    "gn:dem":2776,
    "gn:feature_class":"P",
    "gn:feature_code":"PPL",
    "gn:name":"Draman",
    "gn:population":0,
    "gn:timezone":"Asia/Kolkata",
    "iso:country":"IN",
    "wof:name":"Draman",
    "wof:placetype":"locality"
},
  "geometry": {"coordinates":[75.50274,33.25048],"type":"Point"}
}