{
  "type": "Feature",
  "properties": {
    "iso:country":"IN",
    "ks:ks_alt_nam":"DONGRAIMALA",
    "ks:ks_name":"Dongraimala",
    "ks:ks_pop":138,
    "ks:ks_type":"HABITATION",
    "name:eng_x_preferred":[
        "Dongraimala"
    ],
    "wof:name":"Dongraimala",
    "wof:placetype":"locality",
    "wof:population":138
},
  "geometry": {"coordinates":[74.300771,17.27627],"type":"Point"}
}