{
  "type": "Feature",
  "properties": {
    "iso:country":"IN",
    "ks:ks_alt_nam":"pooyamkutty",
    "ks:ks_name":"Pooyamkutty",
    "ks:ks_pop":741,
    "ks:ks_type":"HABITATION",
    "name:eng_x_preferred":[
        "Pooyamkutty"
    ],
    "wof:name":"Pooyamkutty",
    "wof:placetype":"locality",
    "wof:population":741
},
  "geometry": {"coordinates":[76.78648,10.161302],"type":"Point"}
}