{
  "type": "Feature",
  "properties": {
    "iso:country":"IN",
    "ks:ks_name":"Jamenajeddi",
    "ks:ks_pop":42,
    "ks:ks_type":"HABITATION",
    "name:eng_x_preferred":[
        "Jamenajeddi"
    ],
    "wof:name":"Jamenajeddi",
    "wof:placetype":"locality",
    "wof:population":42
},
  "geometry": {"coordinates":[74.72608200000001,14.960907],"type":"Point"}
}