{
  "type": "Feature",
  "properties": {
    "gn:admin1_code":"23",
    "gn:admin2_code":"38.0",
    "gn:asciiname":"Ahrana",
    "gn:country_code":"IN",
    "gn:dem":257,
    "gn:feature_class":"P",
    "gn:feature_code":"PPL",
    "gn:name":"Ahr\u0101na",
    "gn:population":0,
    "gn:timezone":"Asia/Kolkata",
    "iso:country":"IN",
    "ks:ks_alt_nam":"Ahr\u0101na",
    "ks:ks_name":"Ahrana",
    "ks:ks_pop":4746,
    "ks:ks_type":"VILLAGE",
    "name:eng_x_preferred":[
        "Ahrana"
    ],
    "name:eng_x_variant":[
        "Ahr\u0101na"
    ],
    "wof:name":"Ahrana",
    "wof:placetype":"locality",
    "wof:population":4746
},
  "geometry": {"coordinates":[75.836803,31.422519],"type":"Point"}
}