{
  "type": "Feature",
  "properties": {
    "gn:admin1_code":"19.0",
    "gn:admin2_code":"555.0",
    "gn:asciiname":"Kallapur",
    "gn:country_code":"IN",
    "gn:dem":616,
    "gn:feature_class":"P",
    "gn:feature_code":"PPL",
    "gn:name":"Kall\u0101pur",
    "gn:population":0,
    "gn:timezone":"Asia/Kolkata",
    "iso:country":"IN",
    "wof:name":"Kallapur",
    "wof:placetype":"locality"
},
  "geometry": {"coordinates":[75.26276999999997,15.86175],"type":"Point"}
}