{
  "type": "Feature",
  "properties": {
    "iso:country":"IN",
    "ks:ks_name":"Kovilur",
    "ks:ks_pop":245,
    "ks:ks_type":"HABITATION",
    "name:eng_x_preferred":[
        "Kovilur"
    ],
    "wof:name":"Kovilur",
    "wof:placetype":"locality",
    "wof:population":245
},
  "geometry": {"coordinates":[77.41200000000001,11.739242],"type":"Point"}
}