{
  "type": "Feature",
  "properties": {
    "iso:country":"IN",
    "ks:ks_name":"Kulda",
    "ks:ks_pop":237,
    "ks:ks_type":"VILLAGE",
    "name:eng_x_preferred":[
        "Kulda"
    ],
    "wof:name":"Kulda",
    "wof:placetype":"locality",
    "wof:population":237
},
  "geometry": {"coordinates":[85.257525,22.840127],"type":"Point"}
}