{
  "type": "Feature",
  "properties": {
    "iso:country":"IN",
    "ks:ks_name":"Parvi",
    "ks:ks_pop":408,
    "ks:ks_type":"HABITATION",
    "name:eng_x_preferred":[
        "Parvi"
    ],
    "wof:name":"Parvi",
    "wof:placetype":"locality",
    "wof:population":408
},
  "geometry": {"coordinates":[81.1168,20.226981],"type":"Point"}
}