{
  "type": "Feature",
  "properties": {
    "gn:admin1_code":"16",
    "gn:admin2_code":"501.0",
    "gn:asciiname":"Varudi",
    "gn:country_code":"IN",
    "gn:dem":276,
    "gn:feature_class":"P",
    "gn:feature_code":"PPL",
    "gn:name":"Varudi",
    "gn:population":0,
    "gn:timezone":"Asia/Kolkata",
    "iso:country":"IN",
    "name:est_x_preferred":[
        "Varudi"
    ],
    "name:hye_x_preferred":[
        "\u054e\u0561\u057c\u0578\u0582\u0564\u056b"
    ],
    "name:vol_x_preferred":[
        "Varudi"
    ],
    "wof:name":"Varudi",
    "wof:placetype":"locality"
},
  "geometry": {"coordinates":[77.127,20.7615],"type":"Point"}
}