{
  "type": "Feature",
  "properties": {
    "gn:admin1_code":"25.0",
    "gn:admin2_code":"631.0",
    "gn:asciiname":"Odikuppam",
    "gn:country_code":"IN",
    "gn:dem":543,
    "gn:feature_class":"P",
    "gn:feature_code":"PPL",
    "gn:name":"Odikuppam",
    "gn:population":0,
    "gn:timezone":"Asia/Kolkata",
    "iso:country":"IN",
    "ks:ks_name":"Othikuppam",
    "ks:ks_pop":348,
    "ks:ks_type":"HABITATION",
    "ks:ks_uagg_main":0,
    "name:eng_x_preferred":[
        "Othikuppam"
    ],
    "wof:name":"Othikuppam",
    "wof:placetype":"neighbourhood",
    "wof:population":348
},
  "geometry": {"coordinates":[78.33304200000001,12.616307],"type":"Point"}
}