{
  "type": "Feature",
  "properties": {
    "iso:country":"IN",
    "ks:ks_name":"Guddadakeri",
    "ks:ks_pop":25,
    "ks:ks_type":"HABITATION",
    "name:eng_x_preferred":[
        "Guddadakeri"
    ],
    "wof:name":"Guddadakeri",
    "wof:placetype":"locality",
    "wof:population":25
},
  "geometry": {"coordinates":[74.82206600000001,14.588602],"type":"Point"}
}