{
  "type": "Feature",
  "properties": {
    "iso:country":"IN",
    "ks:ks_name":"Bhurkanda",
    "ks:ks_pop":0,
    "ks:ks_type":"VILLAGE",
    "name:eng_x_preferred":[
        "Bhurkanda"
    ],
    "wof:name":"Bhurkanda",
    "wof:placetype":"locality",
    "wof:population":0
},
  "geometry": {"coordinates":[87.263412,22.041176],"type":"Point"}
}