{
  "type": "Feature",
  "properties": {
    "iso:country":"IN",
    "ks:ks_name":"Nagapur",
    "ks:ks_pop":2148,
    "ks:ks_type":"VILLAGE",
    "name:eng_x_preferred":[
        "Nagapur"
    ],
    "wof:name":"Nagapur",
    "wof:placetype":"locality",
    "wof:population":2148
},
  "geometry": {"coordinates":[86.282051,20.14688],"type":"Point"}
}