{
  "type": "Feature",
  "properties": {
    "iso:country":"IN",
    "ks:ks_name":"Pharaskot",
    "ks:ks_pop":558,
    "ks:ks_type":"HABITATION",
    "name:eng_x_preferred":[
        "Pharaskot"
    ],
    "wof:name":"Pharaskot",
    "wof:placetype":"locality",
    "wof:population":558
},
  "geometry": {"coordinates":[81.09292499999999,20.225775],"type":"Point"}
}