{
  "type": "Feature",
  "properties": {
    "iso:country":"IN",
    "ks:ks_name":"Gayal Gadia",
    "ks:ks_pop":136,
    "ks:ks_type":"VILLAGE",
    "name:eng_x_preferred":[
        "Gayal Gadia"
    ],
    "wof:name":"Gayal Gadia",
    "wof:placetype":"locality",
    "wof:population":136
},
  "geometry": {"coordinates":[86.130872,21.019694],"type":"Point"}
}