{
  "type": "Feature",
  "properties": {
    "gn:admin1_code":"35.0",
    "gn:admin2_code":"454.0",
    "gn:asciiname":"Gujar",
    "gn:country_code":"IN",
    "gn:dem":468,
    "gn:feature_class":"P",
    "gn:feature_code":"PPL",
    "gn:name":"G\u016bjar",
    "gn:population":0,
    "gn:timezone":"Asia/Kolkata",
    "iso:country":"IN",
    "name:ceb_x_preferred":[
        "Gujar"
    ],
    "name:fas_x_preferred":[
        "\u06af\u0648\u062c\u0631"
    ],
    "wof:name":"Gujar",
    "wof:placetype":"locality"
},
  "geometry": {"coordinates":[80.06418000000002,22.94416],"type":"Point"}
}