{
  "type": "Feature",
  "properties": {
    "gn:admin1_code":"35.0",
    "gn:admin2_code":"454.0",
    "gn:asciiname":"Gujar",
    "gn:country_code":"IN",
    "gn:dem":468,
    "gn:feature_class":"P",
    "gn:feature_code":"PPL",
    "gn:name":"G\u016bjar",
    "gn:population":0,
    "gn:timezone":"Asia/Kolkata",
    "iso:country":"IN",
    "ks:ks_alt_nam":"G\u016bjar",
    "ks:ks_name":"Gujar",
    "ks:ks_pop":228,
    "ks:ks_type":"VILLAGE",
    "name:ceb_x_preferred":[
        "Gujar"
    ],
    "name:eng_x_preferred":[
        "Gujar"
    ],
    "name:eng_x_variant":[
        "G\u016bjar"
    ],
    "name:fas_x_preferred":[
        "\u06af\u0648\u062c\u0631"
    ],
    "wof:name":"Gujar",
    "wof:placetype":"locality",
    "wof:population":228
},
  "geometry": {"coordinates":[80.063565,22.942755],"type":"Point"}
}