{
  "type": "Feature",
  "properties": {
    "iso:country":"IN",
    "ks:ks_name":"Narainpur Vikrampur",
    "ks:ks_pop":324,
    "ks:ks_type":"VILLAGE",
    "ks:ks_uagg_main":0,
    "name:eng_x_preferred":[
        "Narainpur Vikrampur"
    ],
    "wof:name":"Narainpur Vikrampur",
    "wof:placetype":"neighbourhood",
    "wof:population":324
},
  "geometry": {"coordinates":[80.270574,28.209032],"type":"Point"}
}