{
  "type": "Feature",
  "properties": {
    "iso:country":"IN",
    "ks:ks_name":"Lakhirbond Pt I",
    "ks:ks_pop":788,
    "ks:ks_type":"VILLAGE",
    "name:eng_x_preferred":[
        "Lakhirbond Pt I"
    ],
    "wof:name":"Lakhirbond Pt I",
    "wof:placetype":"locality",
    "wof:population":788
},
  "geometry": {"coordinates":[92.57193599999999,24.709678],"type":"Point"}
}