{
  "type": "Feature",
  "properties": {
    "iso:country":"IN",
    "ks:ks_alt_nam":"Kalcheni Balabari supa",
    "ks:ks_name":"Kalcheni Balabari Supa",
    "ks:ks_pop":340,
    "ks:ks_type":"HABITATION",
    "ks:ks_uagg_main":0,
    "name:eng_x_preferred":[
        "Kalcheni Balabari Supa"
    ],
    "wof:name":"Kalcheni Balabari Supa",
    "wof:placetype":"neighbourhood",
    "wof:population":340
},
  "geometry": {"coordinates":[91.678012,26.68713],"type":"Point"}
}