{
  "type": "Feature",
  "properties": {
    "iso:country":"IN",
    "ks:ks_name":"Turiyajoshi",
    "ks:ks_pop":59,
    "ks:ks_type":"HABITATION",
    "name:eng_x_preferred":[
        "Turiyajoshi"
    ],
    "wof:name":"Turiyajoshi",
    "wof:placetype":"locality",
    "wof:population":59
},
  "geometry": {"coordinates":[79.48411400000001,29.520589],"type":"Point"}
}