{
  "type": "Feature",
  "properties": {
    "iso:country":"IN",
    "ks:ks_name":"Beritoli",
    "ks:ks_pop":474,
    "ks:ks_type":"HABITATION",
    "name:eng_x_preferred":[
        "Beritoli"
    ],
    "wof:name":"Beritoli",
    "wof:placetype":"locality",
    "wof:population":474
},
  "geometry": {"coordinates":[84.78980199999999,23.197775],"type":"Point"}
}