{
  "type": "Feature",
  "properties": {
    "gn:admin1_code":"24",
    "gn:asciiname":"Jhapra",
    "gn:country_code":"IN",
    "gn:dem":181,
    "gn:feature_class":"P",
    "gn:feature_code":"PPL",
    "gn:name":"Jh\u0101pra",
    "gn:population":0,
    "gn:timezone":"Asia/Kolkata",
    "iso:country":"IN",
    "name:ceb_x_preferred":[
        "Jhapra"
    ],
    "name:mai_x_preferred":[
        "\u091d\u093e\u092a\u094d\u0930\u093e"
    ],
    "name:msa_x_preferred":[
        "Jhapra"
    ],
    "name:nep_x_preferred":[
        "\u091d\u093e\u092a\u094d\u0930\u093e"
    ],
    "name:new_x_preferred":[
        "\u091d\u093e\u092a\u094d\u0930\u093e"
    ],
    "name:pol_x_preferred":[
        "Jhapra"
    ],
    "wof:name":"Jhapra",
    "wof:placetype":"locality"
},
  "geometry": {"coordinates":[77.58521,27.32538],"type":"Point"}
}