{
  "type": "Feature",
  "properties": {
    "gn:admin1_code":"24",
    "gn:asciiname":"Jhapra",
    "gn:country_code":"IN",
    "gn:dem":181,
    "gn:feature_class":"P",
    "gn:feature_code":"PPL",
    "gn:name":"Jh\u0101pra",
    "gn:population":0,
    "gn:timezone":"Asia/Kolkata",
    "iso:country":"IN",
    "wof:name":"Jhapra",
    "wof:placetype":"locality"
},
  "geometry": {"coordinates":[77.58521,27.32538],"type":"Point"}
}