{
  "type": "Feature",
  "properties": {
    "iso:country":"IN",
    "ks:ks_alt_nam":"bhawani khera",
    "ks:ks_name":"Bhawani Khera",
    "ks:ks_pop":400,
    "ks:ks_type":"HABITATION",
    "ks:ks_uagg_main":0,
    "name:eng_x_preferred":[
        "Bhawani Khera"
    ],
    "wof:name":"Bhawani Khera",
    "wof:placetype":"neighbourhood",
    "wof:population":400
},
  "geometry": {"coordinates":[80.549978,26.48065],"type":"Point"}
}