{
  "type": "Feature",
  "properties": {
    "gn:admin1_code":"38",
    "gn:admin2_code":"346.0",
    "gn:asciiname":"Husru",
    "gn:country_code":"IN",
    "gn:dem":190,
    "gn:feature_class":"P",
    "gn:feature_code":"PPL",
    "gn:name":"Husru",
    "gn:population":0,
    "gn:timezone":"Asia/Kolkata",
    "iso:country":"IN",
    "ks:ks_name":"Husru",
    "ks:ks_pop":906,
    "ks:ks_type":"VILLAGE",
    "name:eng_x_preferred":[
        "Husru"
    ],
    "wof:name":"Husru",
    "wof:placetype":"locality",
    "wof:population":906
},
  "geometry": {"coordinates":[83.44151100000001,24.46577],"type":"Point"}
}