{
  "type": "Feature",
  "properties": {
    "iso:country":"IN",
    "ks:ks_name":"Marapadaay",
    "ks:ks_pop":526,
    "ks:ks_type":"HABITATION",
    "name:eng_x_preferred":[
        "Marapadaay"
    ],
    "wof:name":"Marapadaay",
    "wof:placetype":"locality",
    "wof:population":526
},
  "geometry": {"coordinates":[76.26584699999999,10.248083],"type":"Point"}
}