{
  "type": "Feature",
  "properties": {
    "iso:country":"IN",
    "ks:ks_name":"Chimauwa",
    "ks:ks_pop":361,
    "ks:ks_type":"HABITATION",
    "name:eng_x_preferred":[
        "Chimauwa"
    ],
    "wof:name":"Chimauwa",
    "wof:placetype":"locality",
    "wof:population":361
},
  "geometry": {"coordinates":[79.10253,22.232158],"type":"Point"}
}