{
  "type": "Feature",
  "properties": {
    "gn:admin1_code":"38.0",
    "gn:admin2_code":"348.0",
    "gn:asciiname":"Bakbaratoli",
    "gn:country_code":"IN",
    "gn:dem":373,
    "gn:feature_class":"P",
    "gn:feature_code":"PPL",
    "gn:name":"Bakb\u0101r\u0101toli",
    "gn:population":0,
    "gn:timezone":"Asia/Kolkata",
    "iso:country":"IN",
    "wof:name":"Bakbaratoli",
    "wof:placetype":"locality"
},
  "geometry": {"coordinates":[85.24016,24.41135],"type":"Point"}
}