{
  "type": "Feature",
  "properties": {
    "iso:country":"IN",
    "ks:ks_name":"Hethla Fa",
    "ks:ks_pop":258,
    "ks:ks_type":"HABITATION",
    "name:eng_x_preferred":[
        "Hethla Fa"
    ],
    "wof:name":"Hethla Fa",
    "wof:placetype":"locality",
    "wof:population":258
},
  "geometry": {"coordinates":[72.98011099999999,20.380611],"type":"Point"}
}