{
  "type": "Feature",
  "properties": {
    "iso:country":"IN",
    "ks:ks_name":"Jogewadi",
    "ks:ks_pop":1077,
    "ks:ks_type":"HABITATION",
    "name:eng_x_preferred":[
        "Jogewadi"
    ],
    "wof:name":"Jogewadi",
    "wof:placetype":"locality",
    "wof:population":1077
},
  "geometry": {"coordinates":[75.270229,19.155029],"type":"Point"}
}