{
  "type": "Feature",
  "properties": {
    "iso:country":"IN",
    "ks:ks_name":"Dalsargi",
    "ks:ks_pop":181,
    "ks:ks_type":"HABITATION",
    "name:eng_x_preferred":[
        "Dalsargi"
    ],
    "wof:name":"Dalsargi",
    "wof:placetype":"locality",
    "wof:population":181
},
  "geometry": {"coordinates":[82.690539,19.731542],"type":"Point"}
}