{
  "type": "Feature",
  "properties": {
    "iso:country":"IN",
    "ks:ks_name":"Tara T E 31",
    "ks:ks_pop":1020,
    "ks:ks_type":"HABITATION",
    "name:eng_x_preferred":[
        "Tara T E 31"
    ],
    "wof:name":"Tara T E 31",
    "wof:placetype":"locality",
    "wof:population":1020
},
  "geometry": {"coordinates":[95.60793,27.523248],"type":"Point"}
}