{
  "type": "Feature",
  "properties": {
    "iso:country":"IN",
    "ks:ks_name":"Navgharwadi",
    "ks:ks_pop":316,
    "ks:ks_type":"HABITATION",
    "name:eng_x_preferred":[
        "Navgharwadi"
    ],
    "wof:name":"Navgharwadi",
    "wof:placetype":"locality",
    "wof:population":316
},
  "geometry": {"coordinates":[73.540695,16.044403],"type":"Point"}
}