{
  "type": "Feature",
  "properties": {
    "gn:admin1_code":"10.0",
    "gn:admin2_code":"084",
    "gn:asciiname":"Bashipur",
    "gn:country_code":"IN",
    "gn:dem":336,
    "gn:feature_class":"P",
    "gn:feature_code":"PPL",
    "gn:name":"Bash\u012bpur",
    "gn:population":0,
    "gn:timezone":"Asia/Kolkata",
    "iso:country":"IN",
    "wof:name":"Bashipur",
    "wof:placetype":"locality"
},
  "geometry": {"coordinates":[76.04236999999998,28.00392],"type":"Point"}
}