{
  "type": "Feature",
  "properties": {
    "gn:admin1_code":"16.0",
    "gn:admin2_code":"521.0",
    "gn:asciiname":"Warvand",
    "gn:country_code":"IN",
    "gn:dem":555,
    "gn:feature_class":"P",
    "gn:feature_code":"PPL",
    "gn:name":"Warvand",
    "gn:population":0,
    "gn:timezone":"Asia/Kolkata",
    "iso:country":"IN",
    "wof:name":"Warvand",
    "wof:placetype":"locality"
},
  "geometry": {"coordinates":[74.41240000000001,18.4441],"type":"Point"}
}