{
  "type": "Feature",
  "properties": {
    "gn:admin1_code":"36",
    "gn:admin2_code":"176.0",
    "gn:asciiname":"Alwa",
    "gn:country_code":"IN",
    "gn:dem":119,
    "gn:feature_class":"P",
    "gn:feature_code":"PPL",
    "gn:name":"Alwa",
    "gn:population":0,
    "gn:timezone":"Asia/Kolkata",
    "iso:country":"IN",
    "name:cat_x_preferred":[
        "Alwa"
    ],
    "name:deu_x_preferred":[
        "Alwa"
    ],
    "wof:name":"Alwa",
    "wof:placetype":"locality"
},
  "geometry": {"coordinates":[81.34299,26.86366],"type":"Point"}
}