{
  "type": "Feature",
  "properties": {
    "gn:admin1_code":"36",
    "gn:admin2_code":"168.0",
    "gn:asciiname":"Benda",
    "gn:country_code":"IN",
    "gn:dem":142,
    "gn:feature_class":"P",
    "gn:feature_code":"PPL",
    "gn:name":"Benda",
    "gn:population":0,
    "gn:timezone":"Asia/Kolkata",
    "iso:country":"IN",
    "wof:name":"Benda",
    "wof:placetype":"locality"
},
  "geometry": {"coordinates":[79.57135,25.86908],"type":"Point"}
}