{
  "type": "Feature",
  "properties": {
    "iso:country":"IN",
    "ks:ks_alt_nam":"Nayuduvaripalle A.W.",
    "ks:ks_name":"Nayuduvaripalle A.w.",
    "ks:ks_pop":125,
    "ks:ks_type":"HABITATION",
    "ks:ks_uagg_main":0,
    "name:eng_x_preferred":[
        "Nayuduvaripalle A.w."
    ],
    "wof:name":"Nayuduvaripalle A.w.",
    "wof:placetype":"neighbourhood",
    "wof:population":125
},
  "geometry": {"coordinates":[79.265539,14.258964],"type":"Point"}
}