{
  "type": "Feature",
  "properties": {
    "gn:admin1_code":"35.0",
    "gn:admin2_code":"450.0",
    "gn:asciiname":"Bargawan",
    "gn:country_code":"IN",
    "gn:dem":381,
    "gn:feature_class":"P",
    "gn:feature_code":"PPL",
    "gn:name":"Bargaw\u0101n",
    "gn:population":0,
    "gn:timezone":"Asia/Kolkata",
    "iso:country":"IN",
    "ks:ks_alt_nam":"Bargaw\u0101n",
    "ks:ks_name":"Bargawan",
    "ks:ks_type":"VILLAGE",
    "ks:ks_uagg_main":0,
    "name:eng_x_preferred":[
        "Bargawan"
    ],
    "name:eng_x_variant":[
        "Bargaw\u0101n"
    ],
    "wof:name":"Bargawan",
    "wof:placetype":"neighbourhood"
},
  "geometry": {"coordinates":[80.38353499999999,23.823377],"type":"Point"}
}