{
  "type": "Feature",
  "properties": {
    "iso:country":"IN",
    "ks:ks_name":"Desau",
    "ks:ks_pop":238,
    "ks:ks_type":"HABITATION",
    "name:eng_x_preferred":[
        "Desau"
    ],
    "wof:name":"Desau",
    "wof:placetype":"locality",
    "wof:population":238
},
  "geometry": {"coordinates":[77.794768,30.572996],"type":"Point"}
}