{
  "type": "Feature",
  "properties": {
    "gn:admin1_code":"16",
    "gn:admin2_code":"510.0",
    "gn:asciiname":"Injhapur",
    "gn:country_code":"IN",
    "gn:dem":228,
    "gn:feature_class":"P",
    "gn:feature_code":"PPL",
    "gn:name":"Injh\u0101pur",
    "gn:population":0,
    "gn:timezone":"Asia/Kolkata",
    "iso:country":"IN",
    "wof:name":"Injhapur",
    "wof:placetype":"locality"
},
  "geometry": {"coordinates":[78.58121,20.4123],"type":"Point"}
}