{
  "type": "Feature",
  "properties": {
    "iso:country":"IN",
    "ks:ks_name":"Harijan Purwa",
    "ks:ks_pop":60,
    "ks:ks_type":"HABITATION",
    "name:eng_x_preferred":[
        "Harijan Purwa"
    ],
    "wof:name":"Harijan Purwa",
    "wof:placetype":"locality",
    "wof:population":60
},
  "geometry": {"coordinates":[82.576179,26.69711],"type":"Point"}
}