{
  "type": "Feature",
  "properties": {
    "gn:admin1_code":"23",
    "gn:admin2_code":"49.0",
    "gn:asciiname":"Saurian",
    "gn:country_code":"IN",
    "gn:dem":226,
    "gn:feature_class":"P",
    "gn:feature_code":"PPL",
    "gn:name":"S\u0101uri\u0101n",
    "gn:population":0,
    "gn:timezone":"Asia/Kolkata",
    "iso:country":"IN",
    "name:und_x_variant":[
        "S\u0101uri\u0101n",
        "Sauri\u0101n"
    ],
    "wof:name":"Saurian",
    "wof:placetype":"locality"
},
  "geometry": {"coordinates":[74.66298,31.76527],"type":"Point"}
}