{
  "type": "Feature",
  "properties": {
    "gn:admin1_code":"37",
    "gn:admin2_code":"406.0",
    "gn:asciiname":"Pondi",
    "gn:country_code":"IN",
    "gn:dem":256,
    "gn:feature_class":"P",
    "gn:feature_code":"PPL",
    "gn:name":"Pondi",
    "gn:population":0,
    "gn:timezone":"Asia/Kolkata",
    "iso:country":"IN",
    "name:ceb_x_preferred":[
        "Pondi"
    ],
    "name:swe_x_preferred":[
        "Pondi"
    ],
    "wof:name":"Pondi",
    "wof:placetype":"locality"
},
  "geometry": {"coordinates":[81.88244,21.95822],"type":"Point"}
}