{
  "type": "Feature",
  "properties": {
    "iso:country":"IN",
    "ks:ks_name":"Talakilabadi",
    "ks:ks_pop":43,
    "ks:ks_type":"VILLAGE",
    "name:eng_x_preferred":[
        "Talakilabadi"
    ],
    "wof:name":"Talakilabadi",
    "wof:placetype":"locality",
    "wof:population":43
},
  "geometry": {"coordinates":[84.260351,19.897726],"type":"Point"}
}