{
  "type": "Feature",
  "properties": {
    "gn:admin1_code":"19.0",
    "gn:admin2_code":"573.0",
    "gn:asciiname":"Chikkanahalli",
    "gn:country_code":"IN",
    "gn:dem":756,
    "gn:feature_class":"P",
    "gn:feature_code":"PPL",
    "gn:name":"Chikkanahalli",
    "gn:population":0,
    "gn:timezone":"Asia/Kolkata",
    "iso:country":"IN",
    "wof:name":"Chikkanahalli",
    "wof:placetype":"neighbourhood"
},
  "geometry": {"coordinates":[76.79134000000001,12.46058],"type":"Point"}
}