{
  "type": "Feature",
  "properties": {
    "iso:country":"IN",
    "ks:ks_name":"Goripur Araji",
    "ks:ks_pop":200,
    "ks:ks_type":"HABITATION",
    "name:eng_x_preferred":[
        "Goripur Araji"
    ],
    "wof:name":"Goripur Araji",
    "wof:placetype":"locality",
    "wof:population":200
},
  "geometry": {"coordinates":[87.014388,25.739977],"type":"Point"}
}