{
  "type": "Feature",
  "properties": {
    "iso:country":"IN",
    "ks:ks_name":"Benjamin Taro",
    "ks:ks_pop":188,
    "ks:ks_type":"HABITATION",
    "name:eng_x_preferred":[
        "Benjamin Taro"
    ],
    "wof:name":"Benjamin Taro",
    "wof:placetype":"locality",
    "wof:population":188
},
  "geometry": {"coordinates":[93.153712,26.150505],"type":"Point"}
}