{
  "type": "Feature",
  "properties": {
    "iso:country":"IN",
    "ks:ks_alt_nam":"Mavilam colony",
    "ks:ks_name":"Mavilam Colony",
    "ks:ks_pop":644,
    "ks:ks_type":"HABITATION",
    "name:eng_x_preferred":[
        "Mavilam Colony"
    ],
    "wof:name":"Mavilam Colony",
    "wof:placetype":"locality",
    "wof:population":644
},
  "geometry": {"coordinates":[75.24818500000001,12.215858],"type":"Point"}
}