{
  "type": "Feature",
  "properties": {
    "gn:admin1_code":"34.0",
    "gn:admin2_code":"234.0",
    "gn:asciiname":"Gansadih",
    "gn:country_code":"IN",
    "gn:dem":105,
    "gn:feature_class":"P",
    "gn:feature_code":"PPL",
    "gn:name":"Gans\u0101dih",
    "gn:population":0,
    "gn:timezone":"Asia/Kolkata",
    "iso:country":"IN",
    "ks:ks_name":"Gansadih",
    "ks:ks_pop":2695,
    "ks:ks_type":"HABITATION",
    "name:eng_x_preferred":[
        "Gansadih"
    ],
    "wof:name":"Gansadih",
    "wof:placetype":"locality",
    "wof:population":2695
},
  "geometry": {"coordinates":[84.13232000000001,24.994761],"type":"Point"}
}