{
  "type": "Feature",
  "properties": {
    "iso:country":"IN",
    "ks:ks_name":"Naghera",
    "ks:ks_pop":479,
    "ks:ks_type":"VILLAGE",
    "name:eng_x_preferred":[
        "Naghera"
    ],
    "wof:name":"Naghera",
    "wof:placetype":"locality",
    "wof:population":479
},
  "geometry": {"coordinates":[77.253877,24.925782],"type":"Point"}
}