{
  "type": "Feature",
  "properties": {
    "gn:admin1_code":"2.0",
    "gn:admin2_code":"542.0",
    "gn:asciiname":"Gangammapeta",
    "gn:country_code":"IN",
    "gn:dem":37,
    "gn:feature_class":"P",
    "gn:feature_code":"PPL",
    "gn:name":"Gangammapeta",
    "gn:population":0,
    "gn:timezone":"Asia/Kolkata",
    "iso:country":"IN",
    "ks:ks_name":"Gangampeta",
    "ks:ks_pop":553,
    "ks:ks_type":"VILLAGE",
    "ks:ks_uagg_main":0,
    "name:eng_x_preferred":[
        "Gangampeta"
    ],
    "wof:name":"Gangampeta",
    "wof:placetype":"neighbourhood",
    "wof:population":553
},
  "geometry": {"coordinates":[83.82116000000001,18.500347],"type":"Point"}
}