{
  "type": "Feature",
  "properties": {
    "iso:country":"IN",
    "ks:ks_name":"Vizhunthamavadi",
    "ks:ks_pop":5848,
    "ks:ks_type":"VILLAGE",
    "ks:ks_uagg_main":0,
    "name:eng_x_preferred":[
        "Vizhunthamavadi"
    ],
    "wof:name":"Vizhunthamavadi",
    "wof:placetype":"neighbourhood",
    "wof:population":5848
},
  "geometry": {"coordinates":[79.83511799999999,10.596357],"type":"Point"}
}