{
  "type": "Feature",
  "properties": {
    "iso:country":"IN",
    "ks:ks_name":"Alingara",
    "ks:ks_pop":17,
    "ks:ks_type":"HABITATION",
    "name:eng_x_preferred":[
        "Alingara"
    ],
    "wof:name":"Alingara",
    "wof:placetype":"locality",
    "wof:population":17
},
  "geometry": {"coordinates":[75.440766,12.689805],"type":"Point"}
}