{
  "type": "Feature",
  "properties": {
    "iso:country":"IN",
    "ks:ks_name":"New Ratachera",
    "ks:ks_pop":627,
    "ks:ks_type":"HABITATION",
    "name:eng_x_preferred":[
        "New Ratachera"
    ],
    "wof:name":"New Ratachera",
    "wof:placetype":"locality",
    "wof:population":627
},
  "geometry": {"coordinates":[92.440376,25.037788],"type":"Point"}
}