{
  "type": "Feature",
  "properties": {
    "gn:admin1_code":"11",
    "gn:admin2_code":"24.0",
    "gn:asciiname":"Barwari",
    "gn:country_code":"IN",
    "gn:dem":507,
    "gn:feature_class":"P",
    "gn:feature_code":"PPL",
    "gn:name":"Barw\u0101ri",
    "gn:population":0,
    "gn:timezone":"Asia/Kolkata",
    "iso:country":"IN",
    "name:ara_x_preferred":[
        "\u0628\u0631\u0648\u0627\u0631\u064a"
    ],
    "name:vie_x_preferred":[
        "Barur"
    ],
    "wof:name":"Barwari",
    "wof:placetype":"locality"
},
  "geometry": {"coordinates":[76.22799000000001,31.90531],"type":"Point"}
}