{
  "type": "Feature",
  "properties": {
    "gn:admin1_code":"2",
    "gn:admin2_code":"544.0",
    "gn:asciiname":"Peddabayalu",
    "gn:country_code":"IN",
    "gn:dem":1026,
    "gn:feature_class":"P",
    "gn:feature_code":"PPL",
    "gn:name":"Peddabayalu",
    "gn:population":0,
    "gn:timezone":"Asia/Kolkata",
    "iso:country":"IN",
    "ks:ks_name":"Pedabayalu",
    "ks:ks_pop":211,
    "ks:ks_type":"HABITATION",
    "name:eng_x_preferred":[
        "Pedabayalu"
    ],
    "name:eng_x_variant":[
        "Peddabayalu"
    ],
    "wof:name":"Pedabayalu",
    "wof:placetype":"locality",
    "wof:population":211
},
  "geometry": {"coordinates":[82.516295,17.972587],"type":"Point"}
}