{
  "type": "Feature",
  "properties": {
    "gn:admin1_code":"16",
    "gn:admin2_code":"501.0",
    "gn:asciiname":"Malkapur Gond",
    "gn:country_code":"IN",
    "gn:dem":461,
    "gn:feature_class":"P",
    "gn:feature_code":"PPL",
    "gn:name":"Malk\u0101pur Gond",
    "gn:population":0,
    "gn:timezone":"Asia/Kolkata",
    "iso:country":"IN",
    "wof:name":"Malkapur Gond",
    "wof:placetype":"locality"
},
  "geometry": {"coordinates":[77.05915,21.22069],"type":"Point"}
}