{
  "type": "Feature",
  "properties": {
    "gn:admin1_code":"25.0",
    "gn:admin2_code":"609.0",
    "gn:asciiname":"Chinna Kavundanpalaiyam",
    "gn:country_code":"IN",
    "gn:dem":134,
    "gn:feature_class":"P",
    "gn:feature_code":"PPL",
    "gn:name":"Chinna Kavundanp\u0101laiyam",
    "gn:population":0,
    "gn:timezone":"Asia/Kolkata",
    "iso:country":"IN",
    "wof:name":"Chinna Kavundanpalaiyam",
    "wof:placetype":"neighbourhood"
},
  "geometry": {"coordinates":[77.91059,11.08079],"type":"Point"}
}