{
  "type": "Feature",
  "properties": {
    "gn:admin1_code":"40.0",
    "gn:admin2_code":"535.0",
    "gn:asciiname":"Badrikunta",
    "gn:country_code":"IN",
    "gn:dem":605,
    "gn:feature_class":"P",
    "gn:feature_code":"PPL",
    "gn:name":"Badrikunta",
    "gn:population":0,
    "gn:timezone":"Asia/Kolkata",
    "iso:country":"IN",
    "wof:name":"Badrikunta",
    "wof:placetype":"locality"
},
  "geometry": {"coordinates":[78.51691,17.70997000000001],"type":"Point"}
}