{
  "type": "Feature",
  "properties": {
    "iso:country":"IN",
    "ks:ks_name":"Alama",
    "ks:ks_pop":326,
    "ks:ks_type":"HABITATION",
    "name:eng_x_preferred":[
        "Alama"
    ],
    "wof:name":"Alama",
    "wof:placetype":"locality",
    "wof:population":326
},
  "geometry": {"coordinates":[75.19382,13.105778],"type":"Point"}
}