{
  "type": "Feature",
  "properties": {
    "iso:country":"IN",
    "ks:ks_alt_nam":"KHARHOR",
    "ks:ks_name":"Kharhor",
    "ks:ks_pop":526,
    "ks:ks_type":"HABITATION",
    "name:eng_x_preferred":[
        "Kharhor"
    ],
    "wof:name":"Kharhor",
    "wof:placetype":"locality",
    "wof:population":526
},
  "geometry": {"coordinates":[86.496814,26.104744],"type":"Point"}
}