{
  "type": "Feature",
  "properties": {
    "iso:country":"IN",
    "ks:ks_name":"Dhirkona",
    "ks:ks_pop":520,
    "ks:ks_type":"VILLAGE",
    "name:eng_x_preferred":[
        "Dhirkona"
    ],
    "wof:name":"Dhirkona",
    "wof:placetype":"locality",
    "wof:population":520
},
  "geometry": {"coordinates":[87.34788,23.166046],"type":"Point"}
}