{
  "type": "Feature",
  "properties": {
    "iso:country":"IN",
    "ks:ks_name":"5 KKSM",
    "ks:ks_pop":57,
    "ks:ks_type":"VILLAGE",
    "name:eng_x_preferred":[
        "5 KKSM"
    ],
    "wof:name":"5 KKSM",
    "wof:placetype":"locality",
    "wof:population":57
},
  "geometry": {"coordinates":[74.420096,29.090056],"type":"Point"}
}