{
  "type": "Feature",
  "properties": {
    "gn:admin1_code":"40",
    "gn:admin2_code":"532.0",
    "gn:asciiname":"Badi",
    "gn:country_code":"IN",
    "gn:dem":246,
    "gn:feature_class":"P",
    "gn:feature_code":"PPL",
    "gn:name":"B\u0101di",
    "gn:population":0,
    "gn:timezone":"Asia/Kolkata",
    "iso:country":"IN",
    "name:ceb_x_preferred":[
        "Badi"
    ],
    "name:deu_x_preferred":[
        "Badi"
    ],
    "name:ita_x_preferred":[
        "Badi"
    ],
    "name:rus_x_preferred":[
        "\u0411\u0430\u0434\u0438"
    ],
    "name:swe_x_preferred":[
        "Badi"
    ],
    "name:tur_x_preferred":[
        "Badi"
    ],
    "wof:name":"Badi",
    "wof:placetype":"locality"
},
  "geometry": {"coordinates":[78.71588,19.69671],"type":"Point"}
}