{
  "type": "Feature",
  "properties": {
    "gn:admin1_code":"36.0",
    "gn:admin2_code":"185.0",
    "gn:asciiname":"Dariapur Jangal",
    "gn:country_code":"IN",
    "gn:dem":94,
    "gn:feature_class":"P",
    "gn:feature_code":"PPL",
    "gn:name":"Dari\u0101pur Jangal",
    "gn:population":0,
    "gn:timezone":"Asia/Kolkata",
    "iso:country":"IN",
    "wof:name":"Dariapur Jangal",
    "wof:placetype":"locality"
},
  "geometry": {"coordinates":[82.59033000000002,27.04628],"type":"Point"}
}