{
  "type": "Feature",
  "properties": {
    "gn:admin1_code":"2.0",
    "gn:admin2_code":"542.0",
    "gn:asciiname":"Kuvargaduguda",
    "gn:country_code":"IN",
    "gn:dem":677,
    "gn:feature_class":"P",
    "gn:feature_code":"PPL",
    "gn:name":"Kuvargadug\u016bda",
    "gn:population":0,
    "gn:timezone":"Asia/Kolkata",
    "iso:country":"IN",
    "wof:name":"Kuvargaduguda",
    "wof:placetype":"locality"
},
  "geometry": {"coordinates":[83.75041999999998,18.76179],"type":"Point"}
}