{
  "type": "Feature",
  "properties": {
    "iso:country":"IN",
    "ks:ks_name":"Hemawas",
    "ks:ks_pop":793,
    "ks:ks_type":"VILLAGE",
    "name:eng_x_preferred":[
        "Hemawas"
    ],
    "wof:name":"Hemawas",
    "wof:placetype":"locality",
    "wof:population":793
},
  "geometry": {"coordinates":[71.239812,24.904418],"type":"Point"}
}