{
  "type": "Feature",
  "properties": {
    "gn:admin1_code":"16",
    "gn:admin2_code":"512.0",
    "gn:asciiname":"Wakhari",
    "gn:country_code":"IN",
    "gn:dem":400,
    "gn:feature_class":"P",
    "gn:feature_code":"PPL",
    "gn:name":"W\u0101kh\u0101ri",
    "gn:population":0,
    "gn:timezone":"Asia/Kolkata",
    "iso:country":"IN",
    "wof:name":"Wakhari",
    "wof:placetype":"locality"
},
  "geometry": {"coordinates":[77.14563000000003,19.24695],"type":"Point"}
}