{
  "type": "Feature",
  "properties": {
    "iso:country":"IN",
    "ks:ks_alt_nam":"shiv gadi",
    "ks:ks_name":"Shiv Gadi",
    "ks:ks_pop":140,
    "ks:ks_type":"HABITATION",
    "ks:ks_uagg_main":0,
    "name:eng_x_preferred":[
        "Shiv Gadi"
    ],
    "wof:name":"Shiv Gadi",
    "wof:placetype":"neighbourhood",
    "wof:population":140
},
  "geometry": {"coordinates":[80.44071,26.816391],"type":"Point"}
}