{
  "type": "Feature",
  "properties": {
    "iso:country":"IN",
    "ks:ks_name":"Korihan",
    "ks:ks_pop":33,
    "ks:ks_type":"VILLAGE",
    "name:eng_x_preferred":[
        "Korihan"
    ],
    "wof:name":"Korihan",
    "wof:placetype":"locality",
    "wof:population":33
},
  "geometry": {"coordinates":[85.11869900000001,20.976512],"type":"Point"}
}