{
  "type": "Feature",
  "properties": {
    "gn:admin1_code":"16",
    "gn:admin2_code":"525.0",
    "gn:asciiname":"Supatgaon",
    "gn:country_code":"IN",
    "gn:dem":619,
    "gn:feature_class":"P",
    "gn:feature_code":"PPL",
    "gn:name":"Supatgaon",
    "gn:population":0,
    "gn:timezone":"Asia/Kolkata",
    "iso:country":"IN",
    "wof:name":"Supatgaon",
    "wof:placetype":"locality"
},
  "geometry": {"coordinates":[76.43375999999998,17.8963],"type":"Point"}
}