{
  "type": "Feature",
  "properties": {
    "iso:country":"IN",
    "ks:ks_alt_nam":"NORTH TOLA",
    "ks:ks_name":"North Tola",
    "ks:ks_pop":661,
    "ks:ks_type":"HABITATION",
    "name:eng_x_preferred":[
        "North Tola"
    ],
    "wof:name":"North Tola",
    "wof:placetype":"locality",
    "wof:population":661
},
  "geometry": {"coordinates":[84.883664,25.875901],"type":"Point"}
}