{
  "type": "Feature",
  "properties": {
    "iso:country":"IN",
    "ks:ks_name":"Birda",
    "ks:ks_pop":1123,
    "ks:ks_type":"VILLAGE",
    "name:eng_x_preferred":[
        "Birda"
    ],
    "wof:name":"Birda",
    "wof:placetype":"locality",
    "wof:population":1123
},
  "geometry": {"coordinates":[82.64262600000001,22.280558],"type":"Point"}
}