{
  "type": "Feature",
  "properties": {
    "iso:country":"IN",
    "ks:ks_name":"Humabera",
    "ks:ks_pop":54,
    "ks:ks_type":"HABITATION",
    "name:eng_x_preferred":[
        "Humabera"
    ],
    "wof:name":"Humabera",
    "wof:placetype":"locality",
    "wof:population":54
},
  "geometry": {"coordinates":[83.12133900000001,20.975996],"type":"Point"}
}