{
  "type": "Feature",
  "properties": {
    "gn:admin1_code":"36.0",
    "gn:admin2_code":"189.0",
    "gn:asciiname":"Tilakpatti",
    "gn:country_code":"IN",
    "gn:dem":89,
    "gn:feature_class":"P",
    "gn:feature_code":"PPL",
    "gn:name":"Tilakpatti",
    "gn:population":0,
    "gn:timezone":"Asia/Kolkata",
    "iso:country":"IN",
    "ks:ks_name":"Tilakpatti",
    "ks:ks_type":"VILLAGE",
    "name:eng_x_preferred":[
        "Tilakpatti"
    ],
    "wof:name":"Tilakpatti",
    "wof:placetype":"locality"
},
  "geometry": {"coordinates":[84.131045,26.830546],"type":"Point"}
}