{
  "type": "Feature",
  "properties": {
    "iso:country":"IN",
    "ks:ks_name":"Anjavayal",
    "ks:ks_pop":114,
    "ks:ks_type":"HABITATION",
    "name:eng_x_preferred":[
        "Anjavayal"
    ],
    "wof:name":"Anjavayal",
    "wof:placetype":"locality",
    "wof:population":114
},
  "geometry": {"coordinates":[78.701713,9.731877],"type":"Point"}
}