{
  "type": "Feature",
  "properties": {
    "iso:country":"IN",
    "ks:ks_name":"Ghuguloni Bongali",
    "ks:ks_pop":711,
    "ks:ks_type":"HABITATION",
    "name:eng_x_preferred":[
        "Ghuguloni Bongali"
    ],
    "wof:name":"Ghuguloni Bongali",
    "wof:placetype":"locality",
    "wof:population":711
},
  "geometry": {"coordinates":[94.94529900000001,27.259789],"type":"Point"}
}