{
  "type": "Feature",
  "properties": {
    "iso:country":"IN",
    "ks:ks_alt_nam":"BANDHPER",
    "ks:ks_name":"Bandhper",
    "ks:ks_pop":337,
    "ks:ks_type":"HABITATION",
    "name:eng_x_preferred":[
        "Bandhper"
    ],
    "wof:name":"Bandhper",
    "wof:placetype":"locality",
    "wof:population":337
},
  "geometry": {"coordinates":[84.04904000000001,24.67983],"type":"Point"}
}