{
  "type": "Feature",
  "properties": {
    "iso:country":"IN",
    "ks:ks_name":"Rasoolpur",
    "ks:ks_pop":350,
    "ks:ks_type":"HABITATION",
    "name:eng_x_preferred":[
        "Rasoolpur"
    ],
    "wof:name":"Rasoolpur",
    "wof:placetype":"locality",
    "wof:population":350
},
  "geometry": {"coordinates":[80.727073,27.449038],"type":"Point"}
}