{
  "type": "Feature",
  "properties": {
    "gn:admin1_code":"36.0",
    "gn:admin2_code":"173.0",
    "gn:asciiname":"Sarai Bahelia",
    "gn:country_code":"IN",
    "gn:dem":102,
    "gn:feature_class":"P",
    "gn:feature_code":"PPL",
    "gn:name":"Sar\u0101i Bahelia",
    "gn:population":0,
    "gn:timezone":"Asia/Kolkata",
    "iso:country":"IN",
    "ks:ks_name":"Sarai Baheliya",
    "ks:ks_pop":1765,
    "ks:ks_type":"VILLAGE",
    "ks:ks_uagg_main":0,
    "name:eng_x_preferred":[
        "Sarai Baheliya"
    ],
    "wof:name":"Sarai Baheliya",
    "wof:placetype":"neighbourhood",
    "wof:population":1765
},
  "geometry": {"coordinates":[81.97761300000001,25.880131],"type":"Point"}
}