{
  "type": "Feature",
  "properties": {
    "iso:country":"IN",
    "ks:ks_alt_nam":"POROB BERA",
    "ks:ks_name":"Porob Bera",
    "ks:ks_pop":215,
    "ks:ks_type":"HABITATION",
    "name:eng_x_preferred":[
        "Porob Bera"
    ],
    "wof:name":"Porob Bera",
    "wof:placetype":"locality",
    "wof:population":215
},
  "geometry": {"coordinates":[85.502081,22.306988],"type":"Point"}
}