{
  "type": "Feature",
  "properties": {
    "gn:admin1_code":"19.0",
    "gn:admin2_code":"571.0",
    "gn:asciiname":"Hodeghatta",
    "gn:country_code":"IN",
    "gn:dem":864,
    "gn:feature_class":"P",
    "gn:feature_code":"PPL",
    "gn:name":"Hodeghatta",
    "gn:population":0,
    "gn:timezone":"Asia/Kolkata",
    "iso:country":"IN",
    "wof:name":"Hodeghatta",
    "wof:placetype":"locality"
},
  "geometry": {"coordinates":[77.14551,12.95109],"type":"Point"}
}