{
  "type": "Feature",
  "properties": {
    "iso:country":"IN",
    "ks:ks_name":"Upperpoda",
    "ks:ks_pop":55,
    "ks:ks_type":"HABITATION",
    "name:eng_x_preferred":[
        "Upperpoda"
    ],
    "wof:name":"Upperpoda",
    "wof:placetype":"locality",
    "wof:population":55
},
  "geometry": {"coordinates":[83.151421,19.389541],"type":"Point"}
}