{
  "type": "Feature",
  "properties": {
    "iso:country":"IN",
    "ks:ks_name":"Basanta Choudhury Para",
    "ks:ks_pop":65,
    "ks:ks_type":"HABITATION",
    "name:eng_x_preferred":[
        "Basanta Choudhury Para"
    ],
    "wof:name":"Basanta Choudhury Para",
    "wof:placetype":"locality",
    "wof:population":65
},
  "geometry": {"coordinates":[91.629971,23.07828],"type":"Point"}
}