{
  "type": "Feature",
  "properties": {
    "iso:country":"IN",
    "ks:ks_name":"Sohair",
    "ks:ks_pop":675,
    "ks:ks_type":"VILLAGE",
    "name:eng_x_preferred":[
        "Sohair"
    ],
    "wof:name":"Sohair",
    "wof:placetype":"locality",
    "wof:population":675
},
  "geometry": {"coordinates":[88.151348,25.445028],"type":"Point"}
}