{
  "type": "Feature",
  "properties": {
    "iso:country":"IN",
    "ks:ks_name":"Khodyachiwadi",
    "ks:ks_pop":140,
    "ks:ks_type":"HABITATION",
    "name:eng_x_preferred":[
        "Khodyachiwadi"
    ],
    "wof:name":"Khodyachiwadi",
    "wof:placetype":"locality",
    "wof:population":140
},
  "geometry": {"coordinates":[73.138031,18.701732],"type":"Point"}
}