{
  "type": "Feature",
  "properties": {
    "iso:country":"IN",
    "ks:ks_name":"Sardinkhapara",
    "ks:ks_pop":162,
    "ks:ks_type":"VILLAGE",
    "name:eng_x_preferred":[
        "Sardinkhapara"
    ],
    "wof:name":"Sardinkhapara",
    "wof:placetype":"locality",
    "wof:population":162
},
  "geometry": {"coordinates":[91.83117900000001,23.715449],"type":"Point"}
}