{
  "type": "Feature",
  "properties": {
    "iso:country":"IN",
    "ks:ks_name":"Lawkhwa",
    "ks:ks_pop":1665,
    "ks:ks_type":"HABITATION",
    "name:eng_x_preferred":[
        "Lawkhwa"
    ],
    "wof:name":"Lawkhwa",
    "wof:placetype":"locality",
    "wof:population":1665
},
  "geometry": {"coordinates":[82.33523,27.49122],"type":"Point"}
}