{
  "type": "Feature",
  "properties": {
    "iso:country":"IN",
    "ks:ks_name":"Kepnasgadde",
    "ks:ks_pop":41,
    "ks:ks_type":"HABITATION",
    "name:eng_x_preferred":[
        "Kepnasgadde"
    ],
    "wof:name":"Kepnasgadde",
    "wof:placetype":"locality",
    "wof:population":41
},
  "geometry": {"coordinates":[74.73233500000001,14.478335],"type":"Point"}
}