{
  "type": "Feature",
  "properties": {
    "iso:country":"IN",
    "ks:ks_name":"Masjid Wali Dhani",
    "ks:ks_pop":1687,
    "ks:ks_type":"HABITATION",
    "name:eng_x_preferred":[
        "Masjid Wali Dhani"
    ],
    "wof:name":"Masjid Wali Dhani",
    "wof:placetype":"locality",
    "wof:population":1687
},
  "geometry": {"coordinates":[72.42482800000001,26.891111],"type":"Point"}
}