{
  "type": "Feature",
  "properties": {
    "gn:admin1_code":"21",
    "gn:admin2_code":"395.0",
    "gn:asciiname":"Budhipadar",
    "gn:country_code":"IN",
    "gn:dem":354,
    "gn:feature_class":"P",
    "gn:feature_code":"PPL",
    "gn:name":"Budhipadar",
    "gn:population":0,
    "gn:timezone":"Asia/Kolkata",
    "iso:country":"IN",
    "ks:ks_name":"Budhipadar",
    "ks:ks_pop":1103,
    "ks:ks_type":"VILLAGE",
    "name:eng_x_preferred":[
        "Budhipadar"
    ],
    "wof:name":"Budhipadar",
    "wof:placetype":"locality",
    "wof:population":1103
},
  "geometry": {"coordinates":[83.20072999999999,19.844122],"type":"Point"}
}