{
  "type": "Feature",
  "properties": {
    "iso:country":"IN",
    "ks:ks_name":"Mylom",
    "ks:ks_pop":1598,
    "ks:ks_type":"VILLAGE",
    "name:eng_x_preferred":[
        "Mylom"
    ],
    "wof:name":"Mylom",
    "wof:placetype":"locality",
    "wof:population":1598
},
  "geometry": {"coordinates":[76.77995199999999,9.026758],"type":"Point"}
}