{
  "type": "Feature",
  "properties": {
    "gn:admin1_code":"16",
    "gn:admin2_code":"505.0",
    "gn:asciiname":"Surera",
    "gn:country_code":"IN",
    "gn:dem":337,
    "gn:feature_class":"P",
    "gn:feature_code":"PPL",
    "gn:name":"Surera",
    "gn:population":0,
    "gn:timezone":"Asia/Kolkata",
    "iso:country":"IN",
    "ks:ks_name":"Surera",
    "ks:ks_pop":153,
    "ks:ks_type":"HABITATION",
    "name:eng_x_preferred":[
        "Surera"
    ],
    "wof:name":"Surera",
    "wof:placetype":"locality",
    "wof:population":153
},
  "geometry": {"coordinates":[79.17768700000001,21.552278],"type":"Point"}
}