{
  "type": "Feature",
  "properties": {
    "iso:country":"IN",
    "ks:ks_name":"M Bhimavaram",
    "ks:ks_pop":141,
    "ks:ks_type":"HABITATION",
    "name:eng_x_preferred":[
        "M Bhimavaram"
    ],
    "wof:name":"M Bhimavaram",
    "wof:placetype":"locality",
    "wof:population":141
},
  "geometry": {"coordinates":[82.147938,17.608797],"type":"Point"}
}