{
  "type": "Feature",
  "properties": {
    "gn:admin1_code":"40",
    "gn:admin2_code":"533.0",
    "gn:asciiname":"Satyanarayanpuram",
    "gn:country_code":"IN",
    "gn:dem":401,
    "gn:feature_class":"P",
    "gn:feature_code":"PPL",
    "gn:name":"Satyan\u0101r\u0101yanpuram",
    "gn:population":0,
    "gn:timezone":"Asia/Kolkata",
    "iso:country":"IN",
    "name:und_x_variant":[
        "Satyan\u0101r\u0101yanpuram",
        "Warni Cross"
    ],
    "wof:name":"Satyanarayanpuram",
    "wof:placetype":"locality"
},
  "geometry": {"coordinates":[77.89416,18.53252],"type":"Point"}
}