{
  "type": "Feature",
  "properties": {
    "iso:country":"IN",
    "ks:ks_name":"Putupparambu",
    "ks:ks_pop":1377,
    "ks:ks_type":"HABITATION",
    "name:eng_x_preferred":[
        "Putupparambu"
    ],
    "wof:name":"Putupparambu",
    "wof:placetype":"locality",
    "wof:population":1377
},
  "geometry": {"coordinates":[75.83965000000001,11.13114],"type":"Point"}
}