{
  "type": "Feature",
  "properties": {
    "gn:admin1_code":"12.0",
    "gn:admin2_code":"009",
    "gn:asciiname":"Kanzdor",
    "gn:country_code":"IN",
    "gn:dem":3224,
    "gn:feature_class":"P",
    "gn:feature_code":"PPL",
    "gn:name":"Kanzdor",
    "gn:population":0,
    "gn:timezone":"Asia/Kolkata",
    "iso:country":"IN",
    "wof:name":"Kanzdor",
    "wof:placetype":"locality"
},
  "geometry": {"coordinates":[74.76810999999999,34.35691],"type":"Point"}
}