{
  "type": "Feature",
  "properties": {
    "iso:country":"IN",
    "ks:ks_name":"Pashim Mollapara",
    "ks:ks_pop":1323,
    "ks:ks_type":"VILLAGE",
    "ks:ks_uagg_main":0,
    "name:eng_x_preferred":[
        "Pashim Mollapara"
    ],
    "wof:name":"Pashim Mollapara",
    "wof:placetype":"neighbourhood",
    "wof:population":1323
},
  "geometry": {"coordinates":[88.316046,25.521535],"type":"Point"}
}