{
  "type": "Feature",
  "properties": {
    "iso:country":"IN",
    "ks:ks_name":"Mandoli Malli",
    "ks:ks_pop":234,
    "ks:ks_type":"HABITATION",
    "name:eng_x_preferred":[
        "Mandoli Malli"
    ],
    "wof:name":"Mandoli Malli",
    "wof:placetype":"locality",
    "wof:population":234
},
  "geometry": {"coordinates":[78.69966100000001,29.860482],"type":"Point"}
}