{
  "type": "Feature",
  "properties": {
    "gn:admin1_code":"2",
    "gn:admin2_code":"546.0",
    "gn:asciiname":"Madupalle",
    "gn:country_code":"IN",
    "gn:dem":40,
    "gn:feature_class":"P",
    "gn:feature_code":"PPL",
    "gn:name":"Madupalle",
    "gn:population":0,
    "gn:timezone":"Asia/Kolkata",
    "iso:country":"IN",
    "wof:name":"Madupalle",
    "wof:placetype":"locality"
},
  "geometry": {"coordinates":[81.62299,17.34922000000001],"type":"Point"}
}