{
  "type": "Feature",
  "properties": {
    "gn:admin1_code":"36",
    "gn:admin2_code":"202.0",
    "gn:asciiname":"Rehta Yusufnagar",
    "gn:country_code":"IN",
    "gn:dem":167,
    "gn:feature_class":"P",
    "gn:feature_code":"PPL",
    "gn:name":"Rehta Y\u016bsufnagar",
    "gn:population":0,
    "gn:timezone":"Asia/Kolkata",
    "iso:country":"IN",
    "wof:name":"Rehta Yusufnagar",
    "wof:placetype":"locality"
},
  "geometry": {"coordinates":[78.92584000000002,27.6494],"type":"Point"}
}