{
  "type": "Feature",
  "properties": {
    "iso:country":"IN",
    "ks:ks_name":"Khamariya",
    "ks:ks_pop":960,
    "ks:ks_type":"VILLAGE",
    "name:eng_x_preferred":[
        "Khamariya"
    ],
    "wof:name":"Khamariya",
    "wof:placetype":"locality",
    "wof:population":960
},
  "geometry": {"coordinates":[75.531104,23.740279],"type":"Point"}
}