{
  "type": "Feature",
  "properties": {
    "iso:country":"IN",
    "ks:ks_name":"Varchi Sawantwadi",
    "ks:ks_pop":128,
    "ks:ks_type":"HABITATION",
    "ks:ks_uagg_main":0,
    "name:eng_x_preferred":[
        "Varchi Sawantwadi"
    ],
    "wof:name":"Varchi Sawantwadi",
    "wof:placetype":"neighbourhood",
    "wof:population":128
},
  "geometry": {"coordinates":[73.5325,16.904722],"type":"Point"}
}