{
  "type": "Feature",
  "properties": {
    "gn:admin1_code":"3.0",
    "gn:admin2_code":"300.0",
    "gn:asciiname":"Padmabil",
    "gn:country_code":"IN",
    "gn:dem":50,
    "gn:feature_class":"P",
    "gn:feature_code":"PPL",
    "gn:name":"Padmab\u012bl",
    "gn:population":0,
    "gn:timezone":"Asia/Kolkata",
    "iso:country":"IN",
    "ks:ks_name":"Padmabil",
    "ks:ks_pop":4652,
    "ks:ks_type":"URBAN",
    "ks:ks_uagg_main":0,
    "name:eng_x_preferred":[
        "Padmabil"
    ],
    "wof:name":"Padmabil",
    "wof:placetype":"neighbourhood",
    "wof:population":4652
},
  "geometry": {"coordinates":[89.969092,26.449441],"type":"Point"}
}