{
  "type": "Feature",
  "properties": {
    "gn:admin1_code":"36",
    "gn:admin2_code":"200.0",
    "gn:asciiname":"Navgawan Nandlal",
    "gn:country_code":"IN",
    "gn:dem":296,
    "gn:feature_class":"P",
    "gn:feature_code":"PPL",
    "gn:name":"Navgaw\u0101n Nandl\u0101l",
    "gn:population":0,
    "gn:timezone":"Asia/Kolkata",
    "iso:country":"IN",
    "wof:name":"Navgawan Nandlal",
    "wof:placetype":"neighbourhood"
},
  "geometry": {"coordinates":[82.76188999999999,24.7627],"type":"Point"}
}