{
  "type": "Feature",
  "properties": {
    "iso:country":"IN",
    "ks:ks_name":"Paswan Tola",
    "ks:ks_pop":167,
    "ks:ks_type":"HABITATION",
    "name:eng_x_preferred":[
        "Paswan Tola"
    ],
    "wof:name":"Paswan Tola",
    "wof:placetype":"locality",
    "wof:population":167
},
  "geometry": {"coordinates":[85.956709,25.549859],"type":"Point"}
}