{
  "type": "Feature",
  "properties": {
    "iso:country":"IN",
    "ks:ks_name":"1 JSN",
    "ks:ks_pop":73,
    "ks:ks_type":"VILLAGE",
    "name:eng_x_preferred":[
        "1 JSN"
    ],
    "wof:name":"1 JSN",
    "wof:placetype":"locality",
    "wof:population":73
},
  "geometry": {"coordinates":[74.91943000000001,29.365675],"type":"Point"}
}