{
  "type": "Feature",
  "properties": {
    "iso:country":"IN",
    "ks:ks_name":"Dongripada",
    "ks:ks_pop":95,
    "ks:ks_type":"HABITATION",
    "name:eng_x_preferred":[
        "Dongripada"
    ],
    "wof:name":"Dongripada",
    "wof:placetype":"locality",
    "wof:population":95
},
  "geometry": {"coordinates":[73.071169,19.726235],"type":"Point"}
}