{
  "type": "Feature",
  "properties": {
    "iso:country":"IN",
    "ks:ks_name":"Khamaria Badi",
    "ks:ks_pop":308,
    "ks:ks_type":"VILLAGE",
    "name:eng_x_preferred":[
        "Khamaria Badi"
    ],
    "wof:name":"Khamaria Badi",
    "wof:placetype":"locality",
    "wof:population":308
},
  "geometry": {"coordinates":[80.538884,24.232767],"type":"Point"}
}