{
  "type": "Feature",
  "properties": {
    "iso:country":"IN",
    "ks:ks_name":"Gadwasti",
    "ks:ks_pop":40,
    "ks:ks_type":"HABITATION",
    "name:eng_x_preferred":[
        "Gadwasti"
    ],
    "wof:name":"Gadwasti",
    "wof:placetype":"locality",
    "wof:population":40
},
  "geometry": {"coordinates":[74.441008,17.851461],"type":"Point"}
}