{
  "type": "Feature",
  "properties": {
    "iso:country":"IN",
    "ks:ks_name":"Jamkanali",
    "ks:ks_pop":0,
    "ks:ks_type":"VILLAGE",
    "name:eng_x_preferred":[
        "Jamkanali"
    ],
    "wof:name":"Jamkanali",
    "wof:placetype":"locality",
    "wof:population":0
},
  "geometry": {"coordinates":[86.821996,23.413194],"type":"Point"}
}