{
  "type": "Feature",
  "properties": {
    "iso:country":"IN",
    "ks:ks_name":"1 NDR",
    "ks:ks_pop":174,
    "ks:ks_type":"VILLAGE",
    "name:eng_x_preferred":[
        "1 NDR"
    ],
    "wof:name":"1 NDR",
    "wof:placetype":"locality",
    "wof:population":174
},
  "geometry": {"coordinates":[74.52005,29.455389],"type":"Point"}
}