{
  "type": "Feature",
  "properties": {
    "gn:admin1_code":"36.0",
    "gn:admin2_code":"174.0",
    "gn:asciiname":"Pachama",
    "gn:country_code":"IN",
    "gn:dem":109,
    "gn:feature_class":"P",
    "gn:feature_code":"PPL",
    "gn:name":"Pach\u0101ma",
    "gn:population":0,
    "gn:timezone":"Asia/Kolkata",
    "iso:country":"IN",
    "ks:ks_alt_nam":"Pach\u0101ma",
    "ks:ks_name":"Pachama",
    "ks:ks_pop":109,
    "ks:ks_type":"VILLAGE",
    "ks:ks_uagg_main":0,
    "name:eng_x_preferred":[
        "Pachama"
    ],
    "name:eng_x_variant":[
        "Pach\u0101ma"
    ],
    "name:spa_x_preferred":[
        "Pachama"
    ],
    "wof:name":"Pachama",
    "wof:placetype":"neighbourhood",
    "wof:population":109
},
  "geometry": {"coordinates":[81.25233299999999,25.419579],"type":"Point"}
}