{
  "type": "Feature",
  "properties": {
    "iso:country":"IN",
    "ks:ks_name":"Adavikuntapalle",
    "ks:ks_pop":32,
    "ks:ks_type":"HABITATION",
    "name:eng_x_preferred":[
        "Adavikuntapalle"
    ],
    "wof:name":"Adavikuntapalle",
    "wof:placetype":"locality",
    "wof:population":32
},
  "geometry": {"coordinates":[78.469436,13.730784],"type":"Point"}
}