{
  "type": "Feature",
  "properties": {
    "gn:admin1_code":"35.0",
    "gn:admin2_code":"454.0",
    "gn:asciiname":"Lato",
    "gn:country_code":"IN",
    "gn:dem":538,
    "gn:feature_class":"P",
    "gn:feature_code":"PPL",
    "gn:name":"L\u0101to",
    "gn:population":0,
    "gn:timezone":"Asia/Kolkata",
    "iso:country":"IN",
    "name:bul_x_preferred":[
        "\u041b\u0430\u0442\u043e"
    ],
    "name:cat_x_preferred":[
        "Lat\u00f3"
    ],
    "name:ceb_x_preferred":[
        "Lat\u00f3 Et\u00e9ra"
    ],
    "name:deu_x_preferred":[
        "Lato"
    ],
    "name:ell_x_preferred":[
        "\u039b\u03b1\u03c4\u03ce"
    ],
    "name:fin_x_preferred":[
        "Lato"
    ],
    "name:fra_x_preferred":[
        "Lato"
    ],
    "name:hye_x_preferred":[
        "\u053c\u0561\u057f\u0578"
    ],
    "name:por_x_preferred":[
        "Lato"
    ],
    "name:rus_x_preferred":[
        "\u041b\u0430\u0442\u043e"
    ],
    "name:spa_x_preferred":[
        "Lato"
    ],
    "name:swe_x_preferred":[
        "Lat\u00f3 Et\u00e9ra"
    ],
    "name:ukr_x_preferred":[
        "\u041b\u0430\u0442\u043e"
    ],
    "wof:name":"Lato",
    "wof:placetype":"locality"
},
  "geometry": {"coordinates":[80.7281,22.65938],"type":"Point"}
}