{
  "type": "Feature",
  "properties": {
    "iso:country":"IN",
    "ks:ks_name":"Sarathi Kachigollara Camp",
    "ks:ks_pop":177,
    "ks:ks_type":"HABITATION",
    "name:eng_x_preferred":[
        "Sarathi Kachigollara Camp"
    ],
    "wof:name":"Sarathi Kachigollara Camp",
    "wof:placetype":"locality",
    "wof:population":177
},
  "geometry": {"coordinates":[75.8421,13.98026],"type":"Point"}
}