{
  "type": "Feature",
  "properties": {
    "iso:country":"IN",
    "ks:ks_name":"Behta Nihal",
    "ks:ks_pop":0,
    "ks:ks_type":"VILLAGE",
    "name:eng_x_preferred":[
        "Behta Nihal"
    ],
    "wof:name":"Behta Nihal",
    "wof:placetype":"locality",
    "wof:population":0
},
  "geometry": {"coordinates":[79.493331,27.569861],"type":"Point"}
}