{
  "type": "Feature",
  "properties": {
    "iso:country":"IN",
    "ks:ks_name":"Vaddarahalli",
    "ks:ks_pop":1181,
    "ks:ks_type":"VILLAGE",
    "name:eng_x_preferred":[
        "Vaddarahalli"
    ],
    "wof:name":"Vaddarahalli",
    "wof:placetype":"locality",
    "wof:population":1181
},
  "geometry": {"coordinates":[77.07541999999999,13.261519],"type":"Point"}
}