{
  "type": "Feature",
  "properties": {
    "gn:admin1_code":"35",
    "gn:admin2_code":"419.0",
    "gn:asciiname":"Samal ka Pura",
    "gn:country_code":"IN",
    "gn:dem":161,
    "gn:feature_class":"P",
    "gn:feature_code":"PPL",
    "gn:name":"S\u0101mal ka Pura",
    "gn:population":0,
    "gn:timezone":"Asia/Kolkata",
    "iso:country":"IN",
    "wof:name":"Samal ka Pura",
    "wof:placetype":"locality"
},
  "geometry": {"coordinates":[78.45295,26.71649],"type":"Point"}
}