{
  "type": "Feature",
  "properties": {
    "iso:country":"IN",
    "ks:ks_name":"Hebbail",
    "ks:ks_pop":515,
    "ks:ks_type":"VILLAGE",
    "name:eng_x_preferred":[
        "Hebbail"
    ],
    "wof:name":"Hebbail",
    "wof:placetype":"locality",
    "wof:population":515
},
  "geometry": {"coordinates":[74.54886500000001,14.489477],"type":"Point"}
}