{
  "type": "Feature",
  "properties": {
    "iso:country":"IN",
    "ks:ks_name":"Sarpanch",
    "ks:ks_pop":364,
    "ks:ks_type":"HABITATION",
    "name:eng_x_preferred":[
        "Sarpanch"
    ],
    "wof:name":"Sarpanch",
    "wof:placetype":"locality",
    "wof:population":364
},
  "geometry": {"coordinates":[73.186683,20.943117],"type":"Point"}
}