{
  "type": "Feature",
  "properties": {
    "gn:admin1_code":"36",
    "gn:admin2_code":"176.0",
    "gn:asciiname":"Poeni",
    "gn:country_code":"IN",
    "gn:dem":113,
    "gn:feature_class":"P",
    "gn:feature_code":"PPL",
    "gn:name":"Poeni",
    "gn:population":0,
    "gn:timezone":"Asia/Kolkata",
    "iso:country":"IN",
    "name:ceb_x_preferred":[
        "Poeni"
    ],
    "name:srp_x_preferred":[
        "\u041f\u043e\u0435\u043d\u0438"
    ],
    "wof:name":"Poeni",
    "wof:placetype":"locality"
},
  "geometry": {"coordinates":[81.52678,26.75903],"type":"Point"}
}