{
  "type": "Feature",
  "properties": {
    "iso:country":"IN",
    "ks:ks_name":"Horotoli",
    "ks:ks_pop":120,
    "ks:ks_type":"HABITATION",
    "name:eng_x_preferred":[
        "Horotoli"
    ],
    "wof:name":"Horotoli",
    "wof:placetype":"locality",
    "wof:population":120
},
  "geometry": {"coordinates":[84.680846,22.513509],"type":"Point"}
}