{
  "type": "Feature",
  "properties": {
    "iso:country":"IN",
    "ks:ks_name":"Rajamdiha",
    "ks:ks_pop":198,
    "ks:ks_type":"HABITATION",
    "name:eng_x_preferred":[
        "Rajamdiha"
    ],
    "wof:name":"Rajamdiha",
    "wof:placetype":"locality",
    "wof:population":198
},
  "geometry": {"coordinates":[86.594297,23.930626],"type":"Point"}
}