{
  "type": "Feature",
  "properties": {
    "gn:admin1_code":"24",
    "gn:admin2_code":"128.0",
    "gn:asciiname":"Diloda",
    "gn:country_code":"IN",
    "gn:dem":280,
    "gn:feature_class":"P",
    "gn:feature_code":"PPL",
    "gn:name":"D\u012bloda",
    "gn:population":0,
    "gn:timezone":"Asia/Kolkata",
    "iso:country":"IN",
    "wof:name":"Diloda",
    "wof:placetype":"locality"
},
  "geometry": {"coordinates":[76.47796,24.96344],"type":"Point"}
}