{
  "type": "Feature",
  "properties": {
    "iso:country":"IN",
    "ks:ks_name":"Kenduatanr",
    "ks:ks_pop":17,
    "ks:ks_type":"HABITATION",
    "name:eng_x_preferred":[
        "Kenduatanr"
    ],
    "wof:name":"Kenduatanr",
    "wof:placetype":"locality",
    "wof:population":17
},
  "geometry": {"coordinates":[86.500642,24.672776],"type":"Point"}
}