{
  "type": "Feature",
  "properties": {
    "gn:admin1_code":"28",
    "gn:admin2_code":"332.0",
    "gn:asciiname":"Panchanandapur",
    "gn:country_code":"IN",
    "gn:dem":28,
    "gn:feature_class":"P",
    "gn:feature_code":"PPL",
    "gn:name":"Panch\u0101nandapur",
    "gn:population":0,
    "gn:timezone":"Asia/Kolkata",
    "iso:country":"IN",
    "wof:name":"Panchanandapur",
    "wof:placetype":"neighbourhood"
},
  "geometry": {"coordinates":[87.97547,24.85296],"type":"Point"}
}