{
  "type": "Feature",
  "properties": {
    "iso:country":"IN",
    "ks:ks_name":"Pimparimura",
    "ks:ks_pop":39,
    "ks:ks_type":"HABITATION",
    "name:eng_x_preferred":[
        "Pimparimura"
    ],
    "wof:name":"Pimparimura",
    "wof:placetype":"locality",
    "wof:population":39
},
  "geometry": {"coordinates":[73.71519000000001,17.732719],"type":"Point"}
}