{
  "type": "Feature",
  "properties": {
    "iso:country":"IN",
    "ks:ks_name":"Peddagaruvu",
    "ks:ks_pop":83,
    "ks:ks_type":"HABITATION",
    "name:eng_x_preferred":[
        "Peddagaruvu"
    ],
    "wof:name":"Peddagaruvu",
    "wof:placetype":"locality",
    "wof:population":83
},
  "geometry": {"coordinates":[82.46229,18.126384],"type":"Point"}
}