{
  "type": "Feature",
  "properties": {
    "gn:admin1_code":"16",
    "gn:admin2_code":"524.0",
    "gn:asciiname":"Bakli",
    "gn:country_code":"IN",
    "gn:dem":580,
    "gn:feature_class":"P",
    "gn:feature_code":"PPL",
    "gn:name":"B\u0101kli",
    "gn:population":0,
    "gn:timezone":"Asia/Kolkata",
    "iso:country":"IN",
    "wof:name":"Bakli",
    "wof:placetype":"locality"
},
  "geometry": {"coordinates":[76.834,18.25212],"type":"Point"}
}