{
  "type": "Feature",
  "properties": {
    "iso:country":"IN",
    "ks:ks_name":"Harizan Basti",
    "ks:ks_pop":410,
    "ks:ks_type":"HABITATION",
    "name:eng_x_preferred":[
        "Harizan Basti"
    ],
    "wof:name":"Harizan Basti",
    "wof:placetype":"locality",
    "wof:population":410
},
  "geometry": {"coordinates":[83.011957,25.527631],"type":"Point"}
}