{
  "type": "Feature",
  "properties": {
    "iso:country":"IN",
    "ks:ks_name":"Kalighati",
    "ks:ks_pop":408,
    "ks:ks_type":"HABITATION",
    "name:eng_x_preferred":[
        "Kalighati"
    ],
    "wof:name":"Kalighati",
    "wof:placetype":"locality",
    "wof:population":408
},
  "geometry": {"coordinates":[75.36936300000001,22.3471],"type":"Point"}
}