{
  "type": "Feature",
  "properties": {
    "gn:admin1_code":"24.0",
    "gn:admin2_code":"101",
    "gn:asciiname":"Kalu",
    "gn:country_code":"IN",
    "gn:dem":207,
    "gn:feature_class":"P",
    "gn:feature_code":"PPL",
    "gn:name":"K\u0101lu",
    "gn:population":0,
    "gn:timezone":"Asia/Kolkata",
    "iso:country":"IN",
    "name:cat_x_preferred":[
        "Kalu"
    ],
    "name:ceb_x_preferred":[
        "Kalu"
    ],
    "name:deu_x_preferred":[
        "Kalu"
    ],
    "name:fin_x_preferred":[
        "Kalu"
    ],
    "name:fra_x_preferred":[
        "Kalu"
    ],
    "name:rus_x_preferred":[
        "\u041a\u0430\u043b\u0443"
    ],
    "name:srp_x_preferred":[
        "\u041a\u0430\u043b\u0443"
    ],
    "name:swe_x_preferred":[
        "Kalu"
    ],
    "wof:name":"Kalu",
    "wof:placetype":"locality"
},
  "geometry": {"coordinates":[73.89184,28.37957],"type":"Point"}
}