{
  "type": "Feature",
  "properties": {
    "iso:country":"IN",
    "ks:ks_name":"Niz Saidaria",
    "ks:ks_pop":2615,
    "ks:ks_type":"VILLAGE",
    "ks:ks_uagg_main":0,
    "name:eng_x_preferred":[
        "Niz Saidaria"
    ],
    "wof:name":"Niz Saidaria",
    "wof:placetype":"neighbourhood",
    "wof:population":2615
},
  "geometry": {"coordinates":[92.751763,26.441259],"type":"Point"}
}