{
  "type": "Feature",
  "properties": {
    "gn:admin1_code":"35.0",
    "gn:admin2_code":"437.0",
    "gn:asciiname":"Tisi",
    "gn:country_code":"IN",
    "gn:dem":538,
    "gn:feature_class":"P",
    "gn:feature_code":"PPL",
    "gn:name":"T\u012bsi",
    "gn:population":0,
    "gn:timezone":"Asia/Kolkata",
    "iso:country":"IN",
    "wof:name":"Tisi",
    "wof:placetype":"locality"
},
  "geometry": {"coordinates":[76.28660000000001,22.72537],"type":"Point"}
}