{
  "type": "Feature",
  "properties": {
    "gn:admin1_code":"11",
    "gn:admin2_code":"24.0",
    "gn:asciiname":"Har",
    "gn:country_code":"IN",
    "gn:dem":482,
    "gn:feature_class":"P",
    "gn:feature_code":"PPL",
    "gn:name":"H\u0101r",
    "gn:population":0,
    "gn:timezone":"Asia/Kolkata",
    "iso:country":"IN",
    "name:ceb_x_preferred":[
        "Har"
    ],
    "name:isl_x_preferred":[
        "H\u00e1r"
    ],
    "name:por_x_preferred":[
        "Har"
    ],
    "name:swe_x_preferred":[
        "Har"
    ],
    "wof:name":"Har",
    "wof:placetype":"locality"
},
  "geometry": {"coordinates":[76.38734000000002,31.78986],"type":"Point"}
}