{
  "type": "Feature",
  "properties": {
    "gn:admin1_code":"36",
    "gn:admin2_code":"179.0",
    "gn:asciiname":"Pachehri",
    "gn:country_code":"IN",
    "gn:dem":111,
    "gn:feature_class":"P",
    "gn:feature_code":"PPL",
    "gn:name":"Pachehri",
    "gn:population":0,
    "gn:timezone":"Asia/Kolkata",
    "iso:country":"IN",
    "ks:ks_name":"Pachehri",
    "ks:ks_pop":1482,
    "ks:ks_type":"VILLAGE",
    "ks:ks_uagg_main":0,
    "name:eng_x_preferred":[
        "Pachehri"
    ],
    "wof:name":"Pachehri",
    "wof:placetype":"neighbourhood",
    "wof:population":1482
},
  "geometry": {"coordinates":[81.681009,26.19592],"type":"Point"}
}