{
  "type": "Feature",
  "properties": {
    "iso:country":"IN",
    "qs:name":"Kunnumpuram Pullukadu",
    "qs:name_adm0":"India",
    "qs:name_adm1":"Kerala",
    "qs:photos":8,
    "qs:photos_1k":2,
    "qs:photos_9k":1,
    "qs:photos_9r":1,
    "qs:photos_all":8,
    "qs:photos_sr":1,
    "qs:placetype":"Suburb",
    "qs:pop_sr":"0",
    "wof:name":"Kunnumpuram Pullukadu",
    "wof:placetype":"neighbourhood"
},
  "geometry": {"coordinates":[76.893929,8.520924],"type":"Point"}
}