{
  "type": "Feature",
  "properties": {
    "iso:country":"IN",
    "name:ara_x_preferred":[
        "\u0643\u0648\u0646\u0648\u0645\u0628\u0648\u0631\u0627\u0645 \u0628\u0648\u0644\u0648\u0643\u0627\u062f\u0648"
    ],
    "name:ben_bn_x_preferred":[
        "\u0995\u09c1\u09a8\u09cd\u09a8\u09c1\u09ae\u09aa\u09c1\u09b0\u09ae \u09aa\u09c1\u09b2\u09c1\u0995\u09be\u09a1\u09c1"
    ],
    "name:ben_in_x_preferred":[
        "\u0995\u09c1\u09a8\u09cd\u09a8\u09c1\u09ae\u09aa\u09c1\u09b0\u09ae \u09aa\u09c1\u09b2\u09c1\u0995\u09be\u09a1\u09c1"
    ],
    "name:guj_x_preferred":[
        "\u0a95\u0ac1\u0aa8\u0acd\u0aa8\u0aae\u0acd\u0aaa\u0ac1\u0ab0\u0aae\u0acd \u0aaa\u0ac1\u0ab2\u0ac1\u0a95\u0abe\u0aa6\u0ac1"
    ],
    "name:hin_x_preferred":[
        "\u0915\u0941\u0928\u094d\u0928\u092e\u092a\u0941\u0930\u092e \u092a\u0932\u094d\u0932\u0941\u0915\u095c\u0942"
    ],
    "name:kan_x_preferred":[
        "\u0c95\u0cc1\u0ca8\u0ccd\u0ca8\u0cc1\u0cae\u0ccd"
    ],
    "name:mal_x_preferred":[
        "\u0d15\u0d41\u0d28\u0d4d\u0d28\u0d41\u0d2e\u0d4d\u0d2a\u0d41\u0d31\u0d02 \u0d2a\u0d41\u0d32\u0d4d\u0d32\u0d41\u0d15\u0d3e\u0d1f\u0d4d"
    ],
    "name:mar_x_preferred":[
        "\u0915\u0941\u0928\u094d\u0928\u092e\u094d\u092a\u0941\u0930\u092e \u092a\u0941\u0932\u0941\u0915\u093e\u0926\u0942"
    ],
    "name:pan_x_preferred":[
        "\u0a15\u0a41\u0a28\u0a41\u0a2e\u0a2a\u0a41\u0a30\u0a2e \u0a2a\u0a41\u0a71\u0a32\u0a42\u0a15\u0a5c\u0a42"
    ],
    "name:tam_x_preferred":[
        "\u0b95\u0bc1\u0ba9\u0bcd\u0ba9\u0bc1\u0bae\u0bcd\u0baa\u0bc1\u0bb0\u0bae\u0bcd \u0baa\u0bc1\u0bb2\u0bcd\u0bb2\u0bc1\u0b95\u0bcd\u0b95\u0bbe\u0b9f\u0bc1"
    ],
    "name:tel_x_preferred":[
        "\u0c15\u0c28\u0c4d\u0c28\u0c41\u0c02\u0c2a\u0c41\u0c30\u0c02 \u0c2a\u0c41\u0c32\u0c4d\u0c32\u0c41\u0c15\u0c3e\u0c21\u0c41"
    ],
    "name:urd_x_preferred":[
        "\u06a9\u0646\u0651\u0645 \u067e\u0648\u0631\u0645 \u067e\u0644\u0651\u0648\u06a9\u0627\u0688\u0648"
    ],
    "qs:name":"Kunnumpuram Pullukadu",
    "qs:name_adm0":"India",
    "qs:name_adm1":"Kerala",
    "qs:photos":8,
    "qs:photos_1k":2,
    "qs:photos_9k":1,
    "qs:photos_9r":1,
    "qs:photos_all":8,
    "qs:photos_sr":1,
    "qs:placetype":"Suburb",
    "qs:pop_sr":"0",
    "wof:name":"Kunnumpuram Pullukadu",
    "wof:placetype":"neighbourhood"
},
  "geometry": {"coordinates":[76.893929,8.520924],"type":"Point"}
}