{
  "type": "Feature",
  "properties": {
    "iso:country":"IN",
    "ks:ks_name":"Chauraha",
    "ks:ks_pop":62,
    "ks:ks_type":"HABITATION",
    "name:eng_x_preferred":[
        "Chauraha"
    ],
    "wof:name":"Chauraha",
    "wof:placetype":"locality",
    "wof:population":62
},
  "geometry": {"coordinates":[81.61122,26.532818],"type":"Point"}
}