{
  "type": "Feature",
  "properties": {
    "gn:admin1_code":"39",
    "gn:admin2_code":"61.0",
    "gn:asciiname":"Marora",
    "gn:country_code":"IN",
    "gn:dem":1405,
    "gn:feature_class":"P",
    "gn:feature_code":"PPL",
    "gn:name":"Marora",
    "gn:population":0,
    "gn:timezone":"Asia/Kolkata",
    "iso:country":"IN",
    "ks:ks_name":"Marora",
    "ks:ks_type":"VILLAGE",
    "name:eng_x_preferred":[
        "Marora"
    ],
    "wof:name":"Marora",
    "wof:placetype":"locality"
},
  "geometry": {"coordinates":[78.869848,29.992099],"type":"Point"}
}