{
  "type": "Feature",
  "properties": {
    "iso:country":"IN",
    "ks:ks_name":"Barangpadar",
    "ks:ks_pop":51,
    "ks:ks_type":"VILLAGE",
    "name:eng_x_preferred":[
        "Barangpadar"
    ],
    "wof:name":"Barangpadar",
    "wof:placetype":"locality",
    "wof:population":51
},
  "geometry": {"coordinates":[83.282245,19.919437],"type":"Point"}
}