{
  "type": "Feature",
  "properties": {
    "iso:country":"IN",
    "ks:ks_name":"Dak Mura",
    "ks:ks_pop":403,
    "ks:ks_type":"HABITATION",
    "name:eng_x_preferred":[
        "Dak Mura"
    ],
    "wof:name":"Dak Mura",
    "wof:placetype":"locality",
    "wof:population":403
},
  "geometry": {"coordinates":[91.600554,23.733597],"type":"Point"}
}