{
  "type": "Feature",
  "properties": {
    "gn:admin1_code":"2",
    "gn:admin2_code":"544.0",
    "gn:asciiname":"Jirayati Chintuva",
    "gn:country_code":"IN",
    "gn:dem":19,
    "gn:feature_class":"P",
    "gn:feature_code":"PPL",
    "gn:name":"Jir\u0101yati Chintuva",
    "gn:population":0,
    "gn:timezone":"Asia/Kolkata",
    "iso:country":"IN",
    "wof:name":"Jirayati Chintuva",
    "wof:placetype":"locality"
},
  "geometry": {"coordinates":[82.95326999999997,17.47878],"type":"Point"}
}