{
  "type": "Feature",
  "properties": {
    "iso:country":"IN",
    "ks:ks_alt_nam":"Gor\u0101ri",
    "ks:ks_name":"Gorari",
    "ks:ks_type":"VILLAGE",
    "name:eng_x_preferred":[
        "Gorari"
    ],
    "name:eng_x_variant":[
        "Gor\u0101ri"
    ],
    "wof:name":"Gorari",
    "wof:placetype":"locality"
},
  "geometry": {"coordinates":[83.36467,26.563499],"type":"Point"}
}