{
  "type": "Feature",
  "properties": {
    "gn:admin1_code":"40",
    "gn:admin2_code":"541.0",
    "gn:asciiname":"Niala Kondapalle",
    "gn:country_code":"IN",
    "gn:dem":118,
    "gn:feature_class":"P",
    "gn:feature_code":"PPL",
    "gn:name":"Ni\u0101la Kondapalle",
    "gn:population":0,
    "gn:timezone":"Asia/Kolkata",
    "iso:country":"IN",
    "ks:ks_alt_nam":"Ni\u0101la Kondapalli",
    "ks:ks_name":"Niala Kondapalli",
    "ks:ks_type":"VILLAGE",
    "ks:ks_uagg_main":0,
    "name:eng_x_preferred":[
        "Niala Kondapalli"
    ],
    "name:eng_x_variant":[
        "Ni\u0101la Kondapalli"
    ],
    "name:und_x_variant":[
        "Ni\u0101la Kondapalli",
        "Ni\u0101la Kondapalle"
    ],
    "wof:name":"Niala Kondapalli",
    "wof:placetype":"neighbourhood"
},
  "geometry": {"coordinates":[80.053274,17.10253],"type":"Point"}
}