{
  "type": "Feature",
  "properties": {
    "iso:country":"IN",
    "ks:ks_name":"Kukudabhadi",
    "ks:ks_pop":22,
    "ks:ks_type":"HABITATION",
    "name:eng_x_preferred":[
        "Kukudabhadi"
    ],
    "wof:name":"Kukudabhadi",
    "wof:placetype":"locality",
    "wof:population":22
},
  "geometry": {"coordinates":[83.13698599999999,20.000737],"type":"Point"}
}