{
  "type": "Feature",
  "properties": {
    "iso:country":"IN",
    "ks:ks_name":"Bandaguda",
    "ks:ks_pop":426,
    "ks:ks_type":"HABITATION",
    "name:eng_x_preferred":[
        "Bandaguda"
    ],
    "wof:name":"Bandaguda",
    "wof:placetype":"locality",
    "wof:population":426
},
  "geometry": {"coordinates":[80.90236400000001,18.499952],"type":"Point"}
}