{
  "type": "Feature",
  "properties": {
    "iso:country":"IN",
    "ks:ks_name":"Hajarani",
    "ks:ks_pop":420,
    "ks:ks_type":"HABITATION",
    "ks:ks_uagg_main":0,
    "name:eng_x_preferred":[
        "Hajarani"
    ],
    "wof:name":"Hajarani",
    "wof:placetype":"neighbourhood",
    "wof:population":420
},
  "geometry": {"coordinates":[91.455619,25.947411],"type":"Point"}
}