{
  "type": "Feature",
  "properties": {
    "gn:admin1_code":"35.0",
    "gn:admin2_code":"442.0",
    "gn:asciiname":"Nipanyagarhi",
    "gn:country_code":"IN",
    "gn:dem":446,
    "gn:feature_class":"P",
    "gn:feature_code":"PPL",
    "gn:name":"Nip\u0101ny\u0101garhi",
    "gn:population":0,
    "gn:timezone":"Asia/Kolkata",
    "iso:country":"IN",
    "wof:name":"Nipanyagarhi",
    "wof:placetype":"locality"
},
  "geometry": {"coordinates":[76.86856,23.66891],"type":"Point"}
}