{
  "type": "Feature",
  "properties": {
    "gn:admin1_code":"36",
    "gn:admin2_code":"200.0",
    "gn:asciiname":"Bhawna",
    "gn:country_code":"IN",
    "gn:dem":301,
    "gn:feature_class":"P",
    "gn:feature_code":"PPL",
    "gn:name":"Bhawna",
    "gn:population":0,
    "gn:timezone":"Asia/Kolkata",
    "iso:country":"IN",
    "ks:ks_name":"Bhawana",
    "ks:ks_pop":788,
    "ks:ks_type":"VILLAGE",
    "name:eng_x_preferred":[
        "Bhawana"
    ],
    "name:eng_x_variant":[
        "Bhawna"
    ],
    "wof:name":"Bhawana",
    "wof:placetype":"locality",
    "wof:population":788
},
  "geometry": {"coordinates":[82.745238,24.76816],"type":"Point"}
}