{
  "type": "Feature",
  "properties": {
    "gn:admin1_code":"9.0",
    "gn:admin2_code":"485.0",
    "gn:asciiname":"Punakota",
    "gn:country_code":"IN",
    "gn:dem":423,
    "gn:feature_class":"P",
    "gn:feature_code":"PPL",
    "gn:name":"Pun\u0101kota",
    "gn:population":0,
    "gn:timezone":"Asia/Kolkata",
    "iso:country":"IN",
    "ks:ks_name":"Punakota",
    "ks:ks_pop":1130,
    "ks:ks_type":"VILLAGE",
    "name:eng_x_preferred":[
        "Punakota"
    ],
    "wof:name":"Punakota",
    "wof:placetype":"locality",
    "wof:population":1130
},
  "geometry": {"coordinates":[74.173688,22.636273],"type":"Point"}
}