{
  "type": "Feature",
  "properties": {
    "gn:admin1_code":"36",
    "gn:admin2_code":"169.0",
    "gn:asciiname":"Bamhauri Khurd",
    "gn:country_code":"IN",
    "gn:dem":194,
    "gn:feature_class":"P",
    "gn:feature_code":"PPL",
    "gn:name":"Bamhauri Khurd",
    "gn:population":0,
    "gn:timezone":"Asia/Kolkata",
    "iso:country":"IN",
    "wof:name":"Bamhauri Khurd",
    "wof:placetype":"locality"
},
  "geometry": {"coordinates":[79.6799,25.31925],"type":"Point"}
}