{
  "type": "Feature",
  "properties": {
    "iso:country":"IN",
    "ks:ks_name":"Talekarwadi",
    "ks:ks_pop":107,
    "ks:ks_type":"HABITATION",
    "name:eng_x_preferred":[
        "Talekarwadi"
    ],
    "wof:name":"Talekarwadi",
    "wof:placetype":"locality",
    "wof:population":107
},
  "geometry": {"coordinates":[73.41512899999999,16.763584],"type":"Point"}
}