{
  "type": "Feature",
  "properties": {
    "iso:country":"IN",
    "ks:ks_name":"Mankayam",
    "ks:ks_pop":682,
    "ks:ks_type":"HABITATION",
    "name:eng_x_preferred":[
        "Mankayam"
    ],
    "wof:name":"Mankayam",
    "wof:placetype":"locality",
    "wof:population":682
},
  "geometry": {"coordinates":[75.885215,11.486984],"type":"Point"}
}