{
  "type": "Feature",
  "properties": {
    "iso:country":"IN",
    "ks:ks_name":"Jodapokhari",
    "ks:ks_pop":532,
    "ks:ks_type":"HABITATION",
    "name:eng_x_preferred":[
        "Jodapokhari"
    ],
    "wof:name":"Jodapokhari",
    "wof:placetype":"locality",
    "wof:population":532
},
  "geometry": {"coordinates":[86.124188,22.152318],"type":"Point"}
}