{
  "type": "Feature",
  "properties": {
    "iso:country":"IN",
    "ks:ks_name":"Magnri Mttarsai",
    "ks:ks_pop":939,
    "ks:ks_type":"HABITATION",
    "name:eng_x_preferred":[
        "Magnri Mttarsai"
    ],
    "wof:name":"Magnri Mttarsai",
    "wof:placetype":"locality",
    "wof:population":939
},
  "geometry": {"coordinates":[87.767167,22.318766],"type":"Point"}
}