{
  "type": "Feature",
  "properties": {
    "iso:country":"IN",
    "ks:ks_name":"Moy",
    "ks:ks_pop":451,
    "ks:ks_type":"HABITATION",
    "ks:ks_uagg_main":0,
    "name:eng_x_preferred":[
        "Moy"
    ],
    "wof:name":"Moy",
    "wof:placetype":"neighbourhood",
    "wof:population":451
},
  "geometry": {"coordinates":[85.20143400000001,26.316772],"type":"Point"}
}