{
  "type": "Feature",
  "properties": {
    "iso:country":"IN",
    "ks:ks_name":"Merada",
    "ks:ks_pop":322,
    "ks:ks_type":"HABITATION",
    "name:eng_x_preferred":[
        "Merada"
    ],
    "wof:name":"Merada",
    "wof:placetype":"locality",
    "wof:population":322
},
  "geometry": {"coordinates":[72.33471900000001,23.204275],"type":"Point"}
}