{
  "type": "Feature",
  "properties": {
    "gn:admin1_code":"12",
    "gn:admin2_code":"18.0",
    "gn:asciiname":"Nagini",
    "gn:country_code":"IN",
    "gn:dem":3620,
    "gn:feature_class":"P",
    "gn:feature_code":"PPL",
    "gn:name":"N\u0101gini",
    "gn:population":0,
    "gn:timezone":"Asia/Kolkata",
    "iso:country":"IN",
    "wof:name":"Nagini",
    "wof:placetype":"locality"
},
  "geometry": {"coordinates":[76.33925000000001,33.18148],"type":"Point"}
}