{
  "type": "Feature",
  "properties": {
    "iso:country":"IN",
    "ks:ks_name":"Silangi",
    "ks:ks_pop":384,
    "ks:ks_type":"VILLAGE",
    "name:eng_x_preferred":[
        "Silangi"
    ],
    "wof:name":"Silangi",
    "wof:placetype":"locality",
    "wof:population":384
},
  "geometry": {"coordinates":[79.293674,30.033743],"type":"Point"}
}