{
  "type": "Feature",
  "properties": {
    "gn:admin1_code":"10.0",
    "gn:admin2_code":"79.0",
    "gn:asciiname":"Manak Diwan",
    "gn:country_code":"IN",
    "gn:dem":203,
    "gn:feature_class":"P",
    "gn:feature_code":"PPL",
    "gn:name":"M\u0101nak Diw\u0101n",
    "gn:population":0,
    "gn:timezone":"Asia/Kolkata",
    "iso:country":"IN",
    "wof:name":"Manak Diwan",
    "wof:placetype":"locality"
},
  "geometry": {"coordinates":[75.11424,29.40088],"type":"Point"}
}