{
  "type": "Feature",
  "properties": {
    "gn:admin1_code":"34",
    "gn:admin2_code":"234.0",
    "gn:asciiname":"Belthua",
    "gn:country_code":"IN",
    "gn:dem":108,
    "gn:feature_class":"P",
    "gn:feature_code":"PPL",
    "gn:name":"Belthua",
    "gn:population":0,
    "gn:timezone":"Asia/Kolkata",
    "iso:country":"IN",
    "ks:ks_name":"Belthua",
    "ks:ks_pop":475,
    "ks:ks_type":"VILLAGE",
    "ks:ks_uagg_main":0,
    "name:eng_x_preferred":[
        "Belthua"
    ],
    "wof:name":"Belthua",
    "wof:placetype":"neighbourhood",
    "wof:population":475
},
  "geometry": {"coordinates":[83.985238,24.952821],"type":"Point"}
}