{
  "type": "Feature",
  "properties": {
    "gn:admin1_code":"28.0",
    "gn:admin2_code":"332.0",
    "gn:asciiname":"Maharapara",
    "gn:country_code":"IN",
    "gn:dem":32,
    "gn:feature_class":"P",
    "gn:feature_code":"PPL",
    "gn:name":"Mahar\u0101p\u0101ra",
    "gn:population":0,
    "gn:timezone":"Asia/Kolkata",
    "iso:country":"IN",
    "ks:ks_alt_nam":"Mahar\u0101p\u0101ra",
    "ks:ks_name":"Maharapara",
    "ks:ks_pop":1000,
    "ks:ks_type":"VILLAGE",
    "ks:ks_uagg_main":0,
    "name:eng_x_preferred":[
        "Maharapara"
    ],
    "name:eng_x_variant":[
        "Mahar\u0101p\u0101ra"
    ],
    "wof:name":"Maharapara",
    "wof:placetype":"neighbourhood",
    "wof:population":1000
},
  "geometry": {"coordinates":[87.78587400000001,25.417966],"type":"Point"}
}