{
  "type": "Feature",
  "properties": {
    "iso:country":"IN",
    "ks:ks_name":"Saharbera",
    "ks:ks_pop":1492,
    "ks:ks_type":"VILLAGE",
    "name:eng_x_preferred":[
        "Saharbera"
    ],
    "wof:name":"Saharbera",
    "wof:placetype":"locality",
    "wof:population":1492
},
  "geometry": {"coordinates":[86.05394,22.939097],"type":"Point"}
}