{
  "type": "Feature",
  "properties": {
    "iso:country":"IN",
    "ks:ks_name":"Kanmanesike",
    "ks:ks_pop":40,
    "ks:ks_type":"HABITATION",
    "name:eng_x_preferred":[
        "Kanmanesike"
    ],
    "wof:name":"Kanmanesike",
    "wof:placetype":"locality",
    "wof:population":40
},
  "geometry": {"coordinates":[74.94967200000001,13.881389],"type":"Point"}
}