{
  "type": "Feature",
  "properties": {
    "iso:country":"IN",
    "ks:ks_name":"Chikni Darmeani",
    "ks:ks_pop":945,
    "ks:ks_type":"VILLAGE",
    "ks:ks_uagg_main":0,
    "name:eng_x_preferred":[
        "Chikni Darmeani"
    ],
    "wof:name":"Chikni Darmeani",
    "wof:placetype":"neighbourhood",
    "wof:population":945
},
  "geometry": {"coordinates":[86.640334,25.781162],"type":"Point"}
}