{
  "type": "Feature",
  "properties": {
    "iso:country":"IN",
    "ks:ks_name":"Madhopur Kesho",
    "ks:ks_pop":310,
    "ks:ks_type":"VILLAGE",
    "ks:ks_uagg_main":0,
    "name:eng_x_preferred":[
        "Madhopur Kesho"
    ],
    "wof:name":"Madhopur Kesho",
    "wof:placetype":"neighbourhood",
    "wof:population":310
},
  "geometry": {"coordinates":[85.194535,26.340183],"type":"Point"}
}