{
  "type": "Feature",
  "properties": {
    "iso:country":"IN",
    "ks:ks_name":"Wanjabaida",
    "ks:ks_pop":1316,
    "ks:ks_type":"VILLAGE",
    "name:eng_x_preferred":[
        "Wanjabaida"
    ],
    "wof:name":"Wanjabaida",
    "wof:placetype":"locality",
    "wof:population":1316
},
  "geometry": {"coordinates":[74.5727,22.372724],"type":"Point"}
}