{
  "type": "Feature",
  "properties": {
    "gn:admin1_code":"36",
    "gn:admin2_code":"144.0",
    "gn:asciiname":"Lodhipur",
    "gn:country_code":"IN",
    "gn:dem":185,
    "gn:feature_class":"P",
    "gn:feature_code":"PPL",
    "gn:name":"Lodh\u012bpur",
    "gn:population":0,
    "gn:timezone":"Asia/Kolkata",
    "iso:country":"IN",
    "name:por_x_preferred":[
        "Lodhipur"
    ],
    "wof:name":"Lodhipur",
    "wof:placetype":"locality"
},
  "geometry": {"coordinates":[78.30334000000001,27.64405],"type":"Point"}
}