{
  "type": "Feature",
  "properties": {
    "gn:admin1_code":"37",
    "gn:admin2_code":"410.0",
    "gn:asciiname":"Chhatona",
    "gn:country_code":"IN",
    "gn:dem":289,
    "gn:feature_class":"P",
    "gn:feature_code":"PPL",
    "gn:name":"Chhatona",
    "gn:population":0,
    "gn:timezone":"Asia/Kolkata",
    "iso:country":"IN",
    "name:ceb_x_preferred":[
        "Chhatona"
    ],
    "name:fra_x_preferred":[
        "Chhatona"
    ],
    "name:mai_x_preferred":[
        "\u091b\u0924\u094c\u0928\u093e"
    ],
    "name:nep_x_preferred":[
        "\u091b\u0924\u094b\u0928\u093e"
    ],
    "name:new_x_preferred":[
        "\u091b\u0924\u094b\u0928\u093e"
    ],
    "name:pol_x_preferred":[
        "Chhatona"
    ],
    "wof:name":"Chhatona",
    "wof:placetype":"locality"
},
  "geometry": {"coordinates":[81.94473000000001,21.27048],"type":"Point"}
}