{
  "type": "Feature",
  "properties": {
    "iso:country":"IN",
    "ks:ks_name":"Rajpura",
    "ks:ks_pop":397,
    "ks:ks_type":"HABITATION",
    "name:eng_x_preferred":[
        "Rajpura"
    ],
    "name:hin_x_preferred":[
        "\u0930\u093e\u091c\u092a\u0941\u0930\u093e"
    ],
    "name:pan_x_preferred":[
        "\u0a30\u0a3e\u0a1c\u0a2a\u0a41\u0a30\u0a3e"
    ],
    "wof:name":"Rajpura",
    "wof:placetype":"locality",
    "wof:population":397
},
  "geometry": {"coordinates":[77.136565,24.398798],"type":"Point"}
}