{
  "type": "Feature",
  "properties": {
    "iso:country":"IN",
    "ks:ks_name":"Rajpura",
    "ks:ks_pop":397,
    "ks:ks_type":"HABITATION",
    "name:eng_x_preferred":[
        "Rajpura"
    ],
    "wof:name":"Rajpura",
    "wof:placetype":"locality",
    "wof:population":397
},
  "geometry": {"coordinates":[77.136565,24.398798],"type":"Point"}
}