{
  "type": "Feature",
  "properties": {
    "gn:admin1_code":"21",
    "gn:admin2_code":"392.0",
    "gn:asciiname":"Daltangar",
    "gn:country_code":"IN",
    "gn:dem":151,
    "gn:feature_class":"P",
    "gn:feature_code":"PPL",
    "gn:name":"Dalt\u0101ngar",
    "gn:population":0,
    "gn:timezone":"Asia/Kolkata",
    "iso:country":"IN",
    "wof:name":"Daltangar",
    "wof:placetype":"locality"
},
  "geometry": {"coordinates":[83.87064000000002,21.05167],"type":"Point"}
}