{
  "type": "Feature",
  "properties": {
    "gn:admin1_code":"35.0",
    "gn:admin2_code":"445",
    "gn:asciiname":"Ginnurgarh",
    "gn:country_code":"IN",
    "gn:dem":553,
    "gn:feature_class":"P",
    "gn:feature_code":"PPL",
    "gn:name":"Ginnurgarh",
    "gn:population":0,
    "gn:timezone":"Asia/Kolkata",
    "iso:country":"IN",
    "wof:name":"Ginnurgarh",
    "wof:placetype":"locality"
},
  "geometry": {"coordinates":[77.53882,22.84505],"type":"Point"}
}