{
  "type": "Feature",
  "properties": {
    "gn:admin1_code":"35.0",
    "gn:admin2_code":"458.0",
    "gn:asciiname":"Subhanaik Ka Chak",
    "gn:country_code":"IN",
    "gn:dem":429,
    "gn:feature_class":"P",
    "gn:feature_code":"PPL",
    "gn:name":"Subh\u0101n\u0101ik Ka Chak",
    "gn:population":0,
    "gn:timezone":"Asia/Kolkata",
    "iso:country":"IN",
    "wof:name":"Subhanaik Ka Chak",
    "wof:placetype":"locality"
},
  "geometry": {"coordinates":[76.88476,24.38794],"type":"Point"}
}