{
  "type": "Feature",
  "properties": {
    "iso:country":"IN",
    "ks:ks_name":"Deoriduba",
    "ks:ks_pop":624,
    "ks:ks_type":"HABITATION",
    "name:eng_x_preferred":[
        "Deoriduba"
    ],
    "wof:name":"Deoriduba",
    "wof:placetype":"locality",
    "wof:population":624
},
  "geometry": {"coordinates":[91.27562,26.114734],"type":"Point"}
}