{
  "type": "Feature",
  "properties": {
    "iso:country":"IN",
    "ks:ks_name":"Gumropahar",
    "ks:ks_pop":81,
    "ks:ks_type":"VILLAGE",
    "name:eng_x_preferred":[
        "Gumropahar"
    ],
    "wof:name":"Gumropahar",
    "wof:placetype":"locality",
    "wof:population":81
},
  "geometry": {"coordinates":[87.540566,24.166944],"type":"Point"}
}