{
  "type": "Feature",
  "properties": {
    "iso:country":"IN",
    "ks:ks_name":"Siko",
    "ks:ks_pop":0,
    "ks:ks_type":"VILLAGE",
    "name:eng_x_preferred":[
        "Siko"
    ],
    "wof:name":"Siko",
    "wof:placetype":"locality",
    "wof:population":0
},
  "geometry": {"coordinates":[83.22708,25.139821],"type":"Point"}
}