{
  "type": "Feature",
  "properties": {
    "iso:country":"IN",
    "ks:ks_name":"Devatekoppa",
    "ks:ks_pop":8,
    "ks:ks_type":"HABITATION",
    "name:eng_x_preferred":[
        "Devatekoppa"
    ],
    "wof:name":"Devatekoppa",
    "wof:placetype":"locality",
    "wof:population":8
},
  "geometry": {"coordinates":[74.794748,13.979613],"type":"Point"}
}