{
  "type": "Feature",
  "properties": {
    "iso:country":"IN",
    "ks:ks_name":"S V Mangalam North",
    "ks:ks_pop":940,
    "ks:ks_type":"HABITATION",
    "name:eng_x_preferred":[
        "S V Mangalam North"
    ],
    "wof:name":"S V Mangalam North",
    "wof:placetype":"locality",
    "wof:population":940
},
  "geometry": {"coordinates":[78.75205200000001,9.496791],"type":"Point"}
}