{
  "type": "Feature",
  "properties": {
    "iso:country":"IN",
    "ks:ks_name":"Narekarpada",
    "ks:ks_pop":260,
    "ks:ks_type":"HABITATION",
    "name:eng_x_preferred":[
        "Narekarpada"
    ],
    "wof:name":"Narekarpada",
    "wof:placetype":"locality",
    "wof:population":260
},
  "geometry": {"coordinates":[73.105502,19.485298],"type":"Point"}
}