{
  "type": "Feature",
  "properties": {
    "gn:admin1_code":"17.0",
    "gn:admin2_code":"280",
    "gn:asciiname":"Kampang",
    "gn:country_code":"IN",
    "gn:dem":1301,
    "gn:feature_class":"P",
    "gn:feature_code":"PPL",
    "gn:name":"Kamp\u0101ng",
    "gn:population":0,
    "gn:timezone":"Asia/Kolkata",
    "iso:country":"IN",
    "wof:name":"Kampang",
    "wof:placetype":"locality"
},
  "geometry": {"coordinates":[94.23934,24.44065],"type":"Point"}
}