{
  "type": "Feature",
  "properties": {
    "gn:admin1_code":"34.0",
    "gn:admin2_code":"236.0",
    "gn:asciiname":"Kundri",
    "gn:country_code":"IN",
    "gn:dem":310,
    "gn:feature_class":"P",
    "gn:feature_code":"PPL",
    "gn:name":"Kundr\u012b",
    "gn:population":0,
    "gn:timezone":"Asia/Kolkata",
    "iso:country":"IN",
    "ks:ks_name":"Kundari",
    "ks:ks_pop":43,
    "ks:ks_type":"VILLAGE",
    "name:eng_x_preferred":[
        "Kundari"
    ],
    "name:eng_x_variant":[
        "Kundri"
    ],
    "wof:name":"Kundari",
    "wof:placetype":"locality",
    "wof:population":43
},
  "geometry": {"coordinates":[84.36995400000001,24.492697],"type":"Point"}
}