{
  "type": "Feature",
  "properties": {
    "iso:country":"IN",
    "ks:ks_name":"Kitingi",
    "ks:ks_pop":40,
    "ks:ks_type":"HABITATION",
    "name:eng_x_preferred":[
        "Kitingi"
    ],
    "wof:name":"Kitingi",
    "wof:placetype":"locality",
    "wof:population":40
},
  "geometry": {"coordinates":[83.503364,19.43914],"type":"Point"}
}