{
  "type": "Feature",
  "properties": {
    "gn:admin1_code":"34.0",
    "gn:admin2_code":"223.0",
    "gn:asciiname":"Goas",
    "gn:country_code":"IN",
    "gn:dem":41,
    "gn:feature_class":"P",
    "gn:feature_code":"PPL",
    "gn:name":"Go\u0101s",
    "gn:population":0,
    "gn:timezone":"Asia/Kolkata",
    "iso:country":"IN",
    "name:cat_x_preferred":[
        "Gohans"
    ],
    "name:ceb_x_preferred":[
        "Goas"
    ],
    "name:deu_x_preferred":[
        "Goas"
    ],
    "name:eus_x_preferred":[
        "Goas"
    ],
    "name:fra_x_preferred":[
        "Goas"
    ],
    "name:hun_x_preferred":[
        "Goas"
    ],
    "name:ita_x_preferred":[
        "Goas"
    ],
    "name:lat_x_preferred":[
        "Goas"
    ],
    "name:mlg_x_preferred":[
        "Goas"
    ],
    "name:msa_x_preferred":[
        "Goas"
    ],
    "name:nld_x_preferred":[
        "Goas"
    ],
    "name:oci_x_preferred":[
        "Gohans"
    ],
    "name:pms_x_preferred":[
        "Goas"
    ],
    "name:pol_x_preferred":[
        "Goas"
    ],
    "name:por_x_preferred":[
        "Goas"
    ],
    "name:ron_x_preferred":[
        "Goas"
    ],
    "name:slk_x_preferred":[
        "Goas"
    ],
    "name:spa_x_preferred":[
        "Goas"
    ],
    "name:srp_x_preferred":[
        "\u0413\u043e\u0430"
    ],
    "name:swe_x_preferred":[
        "Goas"
    ],
    "name:ukr_x_preferred":[
        "\u0413\u043e\u0430\u0441"
    ],
    "name:vie_x_preferred":[
        "Goas"
    ],
    "name:vol_x_preferred":[
        "Goas"
    ],
    "name:war_x_preferred":[
        "Goas"
    ],
    "wof:name":"Goas",
    "wof:placetype":"locality"
},
  "geometry": {"coordinates":[86.69826999999999,25.58434],"type":"Point"}
}