{
  "type": "Feature",
  "properties": {
    "gn:admin1_code":"34.0",
    "gn:admin2_code":"223.0",
    "gn:asciiname":"Goas",
    "gn:country_code":"IN",
    "gn:dem":41,
    "gn:feature_class":"P",
    "gn:feature_code":"PPL",
    "gn:name":"Go\u0101s",
    "gn:population":0,
    "gn:timezone":"Asia/Kolkata",
    "iso:country":"IN",
    "wof:name":"Goas",
    "wof:placetype":"locality"
},
  "geometry": {"coordinates":[86.69826999999999,25.58434],"type":"Point"}
}