{
  "type": "Feature",
  "properties": {
    "iso:country":"IN",
    "ks:ks_name":"Shendagewasti",
    "ks:ks_pop":160,
    "ks:ks_type":"HABITATION",
    "name:eng_x_preferred":[
        "Shendagewasti"
    ],
    "wof:name":"Shendagewasti",
    "wof:placetype":"locality",
    "wof:population":160
},
  "geometry": {"coordinates":[75.12174400000001,17.769054],"type":"Point"}
}