{
  "type": "Feature",
  "properties": {
    "gn:admin1_code":"10.0",
    "gn:admin2_code":"71.0",
    "gn:asciiname":"Balachaur",
    "gn:country_code":"IN",
    "gn:dem":282,
    "gn:feature_class":"P",
    "gn:feature_code":"PPL",
    "gn:name":"Bal\u0101chaur",
    "gn:population":0,
    "gn:timezone":"Asia/Kolkata",
    "iso:country":"IN",
    "name:ben_x_preferred":[
        "\u09ac\u09be\u09b2\u09be\u099a\u09cc\u09b0"
    ],
    "name:bpy_x_preferred":[
        "\u09ac\u09be\u09b2\u09be\u099a\u09cc\u09b0"
    ],
    "name:hin_x_preferred":[
        "\u092c\u0932\u093e\u091a\u094c\u0930"
    ],
    "name:ita_x_preferred":[
        "Balachaur"
    ],
    "name:mlg_x_preferred":[
        "Balachaur"
    ],
    "name:msa_x_preferred":[
        "Balachaur"
    ],
    "name:new_x_preferred":[
        "\u092c\u0932\u091a\u094c\u0930"
    ],
    "name:nld_x_preferred":[
        "Balachaur"
    ],
    "name:por_x_preferred":[
        "Balachaur"
    ],
    "name:spa_x_preferred":[
        "Balachaur"
    ],
    "name:vie_x_preferred":[
        "Balachaur"
    ],
    "name:zho_x_preferred":[
        "\u5df4\u62c9\u4e54\u5c14"
    ],
    "wof:name":"Balachaur",
    "wof:placetype":"locality"
},
  "geometry": {"coordinates":[77.37704000000002,30.22899],"type":"Point"}
}