{
  "type": "Feature",
  "properties": {
    "gn:admin1_code":"19.0",
    "gn:admin2_code":"583.0",
    "gn:asciiname":"Manchenhalli",
    "gn:country_code":"IN",
    "gn:dem":862,
    "gn:feature_class":"P",
    "gn:feature_code":"PPL",
    "gn:name":"Manchenhalli",
    "gn:population":0,
    "gn:timezone":"Asia/Kolkata",
    "iso:country":"IN",
    "wof:name":"Manchenhalli",
    "wof:placetype":"locality"
},
  "geometry": {"coordinates":[77.35795999999998,13.03581],"type":"Point"}
}