{
  "type": "Feature",
  "properties": {
    "iso:country":"IN",
    "ks:ks_name":"Ramnagar Diara",
    "ks:ks_type":"VILLAGE",
    "name:eng_x_preferred":[
        "Ramnagar Diara"
    ],
    "wof:name":"Ramnagar Diara",
    "wof:placetype":"locality"
},
  "geometry": {"coordinates":[85.48938,25.483709],"type":"Point"}
}