{
  "type": "Feature",
  "properties": {
    "gn:admin1_code":"37.0",
    "gn:asciiname":"Asurgarh",
    "gn:country_code":"IN",
    "gn:dem":229,
    "gn:feature_class":"P",
    "gn:feature_code":"PPL",
    "gn:name":"Asurgarh",
    "gn:population":0,
    "gn:timezone":"Asia/Kolkata",
    "iso:country":"IN",
    "name:cat_x_preferred":[
        "Asurgarh"
    ],
    "wof:name":"Asurgarh",
    "wof:placetype":"locality"
},
  "geometry": {"coordinates":[83.35334,20.07851],"type":"Point"}
}