{
  "type": "Feature",
  "properties": {
    "iso:country":"IN",
    "ks:ks_name":"Balli Bigha",
    "ks:ks_pop":141,
    "ks:ks_type":"HABITATION",
    "name:eng_x_preferred":[
        "Balli Bigha"
    ],
    "wof:name":"Balli Bigha",
    "wof:placetype":"locality",
    "wof:population":141
},
  "geometry": {"coordinates":[84.54285,24.911898],"type":"Point"}
}