{
  "type": "Feature",
  "properties": {
    "iso:country":"IN",
    "ks:ks_name":"Babhani",
    "ks:ks_pop":592,
    "ks:ks_type":"VILLAGE",
    "ks:ks_uagg_main":0,
    "name:eng_x_preferred":[
        "Babhani"
    ],
    "wof:name":"Babhani",
    "wof:placetype":"neighbourhood",
    "wof:population":592
},
  "geometry": {"coordinates":[81.55305,27.689392],"type":"Point"}
}