{
  "type": "Feature",
  "properties": {
    "iso:country":"IN",
    "ks:ks_name":"Ridal",
    "ks:ks_pop":320,
    "ks:ks_type":"VILLAGE",
    "name:eng_x_preferred":[
        "Ridal"
    ],
    "wof:name":"Ridal",
    "wof:placetype":"locality",
    "wof:population":320
},
  "geometry": {"coordinates":[82.418115,18.543109],"type":"Point"}
}