{
  "type": "Feature",
  "properties": {
    "iso:country":"IN",
    "ks:ks_name":"Caki Damodarpur",
    "ks:ks_pop":560,
    "ks:ks_type":"HABITATION",
    "ks:ks_uagg_main":0,
    "name:eng_x_preferred":[
        "Caki Damodarpur"
    ],
    "wof:name":"Caki Damodarpur",
    "wof:placetype":"neighbourhood",
    "wof:population":560
},
  "geometry": {"coordinates":[82.54673699999999,26.373376],"type":"Point"}
}