{
  "type": "Feature",
  "properties": {
    "gn:admin1_code":"11",
    "gn:admin2_code":"24.0",
    "gn:asciiname":"Nain",
    "gn:country_code":"IN",
    "gn:dem":1259,
    "gn:feature_class":"P",
    "gn:feature_code":"PPL",
    "gn:name":"Nain",
    "gn:population":0,
    "gn:timezone":"Asia/Kolkata",
    "iso:country":"IN",
    "name:cat_x_preferred":[
        "Nain"
    ],
    "name:ceb_x_preferred":[
        "Nain"
    ],
    "name:deu_x_preferred":[
        "Nain"
    ],
    "name:fas_x_preferred":[
        "\u0646\u0627\u06cc\u06cc\u0646"
    ],
    "name:fra_x_preferred":[
        "Nain"
    ],
    "name:heb_x_preferred":[
        "\u05e0\u05d0\u05d9\u05df"
    ],
    "name:hun_x_preferred":[
        "Nain"
    ],
    "name:ita_x_preferred":[
        "Nain"
    ],
    "name:nld_x_preferred":[
        "Nain"
    ],
    "name:pnb_x_preferred":[
        "\u0646\u0627\u06cc\u06cc\u0646"
    ],
    "name:swe_x_preferred":[
        "Nain"
    ],
    "wof:name":"Nain",
    "wof:placetype":"locality"
},
  "geometry": {"coordinates":[76.57581,32.09996],"type":"Point"}
}