{
  "type": "Feature",
  "properties": {
    "iso:country":"IN",
    "ks:ks_name":"Ajagar Pahar N.C.",
    "ks:ks_pop":708,
    "ks:ks_type":"VILLAGE",
    "name:eng_x_preferred":[
        "Ajagar Pahar N.C."
    ],
    "wof:name":"Ajagar Pahar N.C.",
    "wof:placetype":"locality",
    "wof:population":708
},
  "geometry": {"coordinates":[90.528755,26.028728],"type":"Point"}
}