{
  "type": "Feature",
  "properties": {
    "iso:country":"IN",
    "ks:ks_name":"Barahi Mohan",
    "ks:ks_pop":2680,
    "ks:ks_type":"VILLAGE",
    "ks:ks_uagg_main":0,
    "name:eng_x_preferred":[
        "Barahi Mohan"
    ],
    "wof:name":"Barahi Mohan",
    "wof:placetype":"neighbourhood",
    "wof:population":2680
},
  "geometry": {"coordinates":[85.30305199999999,26.627788],"type":"Point"}
}