{
  "type": "Feature",
  "properties": {
    "iso:country":"IN",
    "ks:ks_alt_nam":"TANGERDIH",
    "ks:ks_name":"Tangerdih",
    "ks:ks_pop":422,
    "ks:ks_type":"HABITATION",
    "name:eng_x_preferred":[
        "Tangerdih"
    ],
    "wof:name":"Tangerdih",
    "wof:placetype":"locality",
    "wof:population":422
},
  "geometry": {"coordinates":[83.677178,22.953492],"type":"Point"}
}