{
  "type": "Feature",
  "properties": {
    "iso:country":"IN",
    "ks:ks_name":"Kerebail",
    "ks:ks_pop":240,
    "ks:ks_type":"HABITATION",
    "name:eng_x_preferred":[
        "Kerebail"
    ],
    "wof:name":"Kerebail",
    "wof:placetype":"locality",
    "wof:population":240
},
  "geometry": {"coordinates":[74.75986899999999,13.597598],"type":"Point"}
}