{
  "type": "Feature",
  "properties": {
    "gn:admin1_code":"35.0",
    "gn:admin2_code":"463.0",
    "gn:asciiname":"Barda",
    "gn:country_code":"IN",
    "gn:dem":386,
    "gn:feature_class":"P",
    "gn:feature_code":"PPL",
    "gn:name":"B\u0101rda",
    "gn:population":0,
    "gn:timezone":"Asia/Kolkata",
    "iso:country":"IN",
    "name:aze_x_preferred":[
        "B\u0259rd\u0259"
    ],
    "name:bel_x_preferred":[
        "\u0411\u0430\u0440\u0434\u0430"
    ],
    "name:cat_x_preferred":[
        "Barda"
    ],
    "name:ceb_x_preferred":[
        "Barda"
    ],
    "name:ces_x_preferred":[
        "Barda"
    ],
    "name:dan_x_preferred":[
        "Barda"
    ],
    "name:deu_x_preferred":[
        "Barda"
    ],
    "name:fas_x_preferred":[
        "\u0628\u0631\u062f\u0647"
    ],
    "name:fra_x_preferred":[
        "Barda"
    ],
    "name:heb_x_preferred":[
        "\u05d1\u05e8\u05d3\u05d4"
    ],
    "name:hun_x_preferred":[
        "Barda"
    ],
    "name:ind_x_preferred":[
        "Barda"
    ],
    "name:kat_x_preferred":[
        "\u10d1\u10d0\u10e0\u10d3\u10d0"
    ],
    "name:pnb_x_preferred":[
        "\u0628\u06cc\u0631\u0627\u062f\u0627"
    ],
    "name:pol_x_preferred":[
        "Barda"
    ],
    "name:rus_x_preferred":[
        "\u0411\u0430\u0440\u0434\u0430"
    ],
    "name:spa_x_preferred":[
        "Barda"
    ],
    "name:swe_x_preferred":[
        "Barda"
    ],
    "name:ukr_x_preferred":[
        "\u0411\u0430\u0440\u0434\u0430"
    ],
    "name:uzb_x_preferred":[
        "Barda"
    ],
    "wof:name":"Barda",
    "wof:placetype":"locality"
},
  "geometry": {"coordinates":[82.51210999999998,24.40842],"type":"Point"}
}