{
  "type": "Feature",
  "properties": {
    "gn:admin1_code":"36",
    "gn:admin2_code":"198.0",
    "gn:asciiname":"Lokmanpur",
    "gn:country_code":"IN",
    "gn:dem":91,
    "gn:feature_class":"P",
    "gn:feature_code":"PPL",
    "gn:name":"Lokm\u0101npur",
    "gn:population":0,
    "gn:timezone":"Asia/Kolkata",
    "iso:country":"IN",
    "ks:ks_alt_nam":"Lokm\u0101npur",
    "ks:ks_name":"Lokmanpur",
    "ks:ks_type":"VILLAGE",
    "ks:ks_uagg_main":0,
    "name:eng_x_preferred":[
        "Lokmanpur"
    ],
    "name:eng_x_variant":[
        "Lokm\u0101npur"
    ],
    "wof:name":"Lokmanpur",
    "wof:placetype":"neighbourhood"
},
  "geometry": {"coordinates":[82.366936,25.395026],"type":"Point"}
}