{
  "type": "Feature",
  "properties": {
    "gn:admin1_code":"36",
    "gn:admin2_code":"176.0",
    "gn:asciiname":"Takia",
    "gn:country_code":"IN",
    "gn:dem":115,
    "gn:feature_class":"P",
    "gn:feature_code":"PPL",
    "gn:name":"Takia",
    "gn:population":0,
    "gn:timezone":"Asia/Kolkata",
    "iso:country":"IN",
    "wof:name":"Takia",
    "wof:placetype":"locality"
},
  "geometry": {"coordinates":[81.27431,27.29344],"type":"Point"}
}