{
  "type": "Feature",
  "properties": {
    "gn:admin1_code":"36.0",
    "gn:admin2_code":"186.0",
    "gn:asciiname":"Chetkapwa",
    "gn:country_code":"IN",
    "gn:dem":86,
    "gn:feature_class":"P",
    "gn:feature_code":"PPL",
    "gn:name":"Chetkapwa",
    "gn:population":0,
    "gn:timezone":"Asia/Kolkata",
    "iso:country":"IN",
    "wof:name":"Chetkapwa",
    "wof:placetype":"locality"
},
  "geometry": {"coordinates":[82.90746,27.00543],"type":"Point"}
}