{
  "type": "Feature",
  "properties": {
    "iso:country":"IN",
    "ks:ks_name":"Karibail",
    "ks:ks_pop":82,
    "ks:ks_type":"HABITATION",
    "name:eng_x_preferred":[
        "Karibail"
    ],
    "wof:name":"Karibail",
    "wof:placetype":"locality",
    "wof:population":82
},
  "geometry": {"coordinates":[74.715687,14.344955],"type":"Point"}
}