{
  "type": "Feature",
  "properties": {
    "iso:country":"IN",
    "ks:ks_name":"Bhimakanda",
    "ks:ks_pop":216,
    "ks:ks_type":"VILLAGE",
    "name:eng_x_preferred":[
        "Bhimakanda"
    ],
    "wof:name":"Bhimakanda",
    "wof:placetype":"locality",
    "wof:population":216
},
  "geometry": {"coordinates":[85.232416,21.522641],"type":"Point"}
}