{
  "type": "Feature",
  "properties": {
    "iso:country":"IN",
    "ks:ks_name":"Machhiyari",
    "ks:ks_pop":121,
    "ks:ks_type":"VILLAGE",
    "name:eng_x_preferred":[
        "Machhiyari"
    ],
    "wof:name":"Machhiyari",
    "wof:placetype":"locality",
    "wof:population":121
},
  "geometry": {"coordinates":[78.630861,30.326072],"type":"Point"}
}