{
  "type": "Feature",
  "properties": {
    "iso:country":"IN",
    "ks:ks_alt_nam":"GangapurKhaspara",
    "ks:ks_name":"Gangapurkhaspara",
    "ks:ks_pop":1104,
    "ks:ks_type":"HABITATION",
    "name:eng_x_preferred":[
        "Gangapurkhaspara"
    ],
    "wof:name":"Gangapurkhaspara",
    "wof:placetype":"locality",
    "wof:population":1104
},
  "geometry": {"coordinates":[83.321189,23.043769],"type":"Point"}
}