{
  "type": "Feature",
  "properties": {
    "iso:country":"IN",
    "ks:ks_name":"Pashang",
    "ks:ks_pop":1804,
    "ks:ks_type":"VILLAGE",
    "name:eng_x_preferred":[
        "Pashang"
    ],
    "wof:name":"Pashang",
    "wof:placetype":"locality",
    "wof:population":1804
},
  "geometry": {"coordinates":[87.60105900000001,22.335548],"type":"Point"}
}