{
  "type": "Feature",
  "properties": {
    "iso:country":"IN",
    "ks:ks_name":"Dhengbahara",
    "ks:ks_pop":274,
    "ks:ks_type":"VILLAGE",
    "name:eng_x_preferred":[
        "Dhengbahara"
    ],
    "wof:name":"Dhengbahara",
    "wof:placetype":"locality",
    "wof:population":274
},
  "geometry": {"coordinates":[87.150597,22.620145],"type":"Point"}
}