{
  "type": "Feature",
  "properties": {
    "iso:country":"IN",
    "ks:ks_name":"Degra",
    "ks:ks_pop":248,
    "ks:ks_type":"VILLAGE",
    "name:eng_x_preferred":[
        "Degra"
    ],
    "wof:name":"Degra",
    "wof:placetype":"locality",
    "wof:population":248
},
  "geometry": {"coordinates":[82.107202,18.372649],"type":"Point"}
}