{
  "type": "Feature",
  "properties": {
    "iso:country":"IN",
    "ks:ks_name":"Adiguda",
    "ks:ks_pop":210,
    "ks:ks_type":"HABITATION",
    "name:eng_x_preferred":[
        "Adiguda"
    ],
    "wof:name":"Adiguda",
    "wof:placetype":"locality",
    "wof:population":210
},
  "geometry": {"coordinates":[84.04128900000001,19.464307],"type":"Point"}
}