{
  "type": "Feature",
  "properties": {
    "iso:country":"IN",
    "ks:ks_name":"Pure Banmanush",
    "ks:ks_pop":41,
    "ks:ks_type":"HABITATION",
    "name:eng_x_preferred":[
        "Pure Banmanush"
    ],
    "wof:name":"Pure Banmanush",
    "wof:placetype":"locality",
    "wof:population":41
},
  "geometry": {"coordinates":[82.037909,26.434838],"type":"Point"}
}