{
  "type": "Feature",
  "properties": {
    "iso:country":"IN",
    "ks:ks_name":"Deobil Chamuguri No 2",
    "ks:ks_pop":549,
    "ks:ks_type":"HABITATION",
    "name:eng_x_preferred":[
        "Deobil Chamuguri No 2"
    ],
    "wof:name":"Deobil Chamuguri No 2",
    "wof:placetype":"locality",
    "wof:population":549
},
  "geometry": {"coordinates":[94.05924899999999,27.179135],"type":"Point"}
}