{
  "type": "Feature",
  "properties": {
    "gn:admin1_code":"19.0",
    "gn:admin2_code":"576.0",
    "gn:asciiname":"Heggademane",
    "gn:country_code":"IN",
    "gn:dem":968,
    "gn:feature_class":"P",
    "gn:feature_code":"PPL",
    "gn:name":"Heggademane",
    "gn:population":0,
    "gn:timezone":"Asia/Kolkata",
    "iso:country":"IN",
    "ks:ks_name":"Heggadamane",
    "ks:ks_pop":28,
    "ks:ks_type":"HABITATION",
    "name:eng_x_preferred":[
        "Heggadamane"
    ],
    "name:eng_x_variant":[
        "Heggademane"
    ],
    "wof:name":"Heggadamane",
    "wof:placetype":"locality",
    "wof:population":28
},
  "geometry": {"coordinates":[75.711111,12.666667],"type":"Point"}
}