{
  "type": "Feature",
  "properties": {
    "gn:admin1_code":"34.0",
    "gn:admin2_code":"204.0",
    "gn:asciiname":"Panditpur",
    "gn:country_code":"IN",
    "gn:dem":78,
    "gn:feature_class":"P",
    "gn:feature_code":"PPL",
    "gn:name":"Panditpur",
    "gn:population":0,
    "gn:timezone":"Asia/Kolkata",
    "iso:country":"IN",
    "name:und_x_variant":[
        "Bandarhelwa"
    ],
    "wof:name":"Panditpur",
    "wof:placetype":"neighbourhood"
},
  "geometry": {"coordinates":[84.63697999999999,26.68204],"type":"Point"}
}