{
  "type": "Feature",
  "properties": {
    "iso:country":"IN",
    "ks:ks_name":"10BD",
    "ks:ks_pop":2170,
    "ks:ks_type":"VILLAGE",
    "name:eng_x_preferred":[
        "10BD"
    ],
    "wof:name":"10BD",
    "wof:placetype":"locality",
    "wof:population":2170
},
  "geometry": {"coordinates":[72.63601800000001,28.857275],"type":"Point"}
}