{
  "type": "Feature",
  "properties": {
    "iso:country":"IN",
    "ks:ks_name":"Bajrapur",
    "ks:ks_pop":272,
    "ks:ks_type":"VILLAGE",
    "ks:ks_uagg_main":0,
    "name:eng_x_preferred":[
        "Bajrapur"
    ],
    "wof:name":"Bajrapur",
    "wof:placetype":"neighbourhood",
    "wof:population":272
},
  "geometry": {"coordinates":[86.801526,20.951421],"type":"Point"}
}