{
  "type": "Feature",
  "properties": {
    "iso:country":"IN",
    "ks:ks_name":"Eman Tari",
    "ks:ks_pop":917,
    "ks:ks_type":"HABITATION",
    "name:eng_x_preferred":[
        "Eman Tari"
    ],
    "wof:name":"Eman Tari",
    "wof:placetype":"locality",
    "wof:population":917
},
  "geometry": {"coordinates":[89.24742999999999,26.409282],"type":"Point"}
}