{
  "type": "Feature",
  "properties": {
    "gn:admin1_code":"40",
    "gn:admin2_code":"538.0",
    "gn:asciiname":"Potanpalli",
    "gn:country_code":"IN",
    "gn:dem":430,
    "gn:feature_class":"P",
    "gn:feature_code":"PPL",
    "gn:name":"Potanpalli",
    "gn:population":0,
    "gn:timezone":"Asia/Kolkata",
    "iso:country":"IN",
    "wof:name":"Potanpalli",
    "wof:placetype":"locality"
},
  "geometry": {"coordinates":[77.86903000000002,16.68741],"type":"Point"}
}