{
  "type": "Feature",
  "properties": {
    "gn:admin1_code":"19.0",
    "gn:admin2_code":"571.0",
    "gn:asciiname":"Settipura",
    "gn:country_code":"IN",
    "gn:dem":705,
    "gn:feature_class":"P",
    "gn:feature_code":"PPL",
    "gn:name":"Settipura",
    "gn:population":0,
    "gn:timezone":"Asia/Kolkata",
    "iso:country":"IN",
    "ks:ks_name":"Shettipura",
    "ks:ks_pop":302,
    "ks:ks_type":"VILLAGE",
    "name:eng_x_preferred":[
        "Shettipura"
    ],
    "name:eng_x_variant":[
        "Settipura"
    ],
    "wof:name":"Shettipura",
    "wof:placetype":"locality",
    "wof:population":302
},
  "geometry": {"coordinates":[76.94810200000001,12.887215],"type":"Point"}
}