{
  "type": "Feature",
  "properties": {
    "iso:country":"IN",
    "ks:ks_name":"Sahariya Basti",
    "ks:ks_pop":389,
    "ks:ks_type":"HABITATION",
    "name:eng_x_preferred":[
        "Sahariya Basti"
    ],
    "wof:name":"Sahariya Basti",
    "wof:placetype":"locality",
    "wof:population":389
},
  "geometry": {"coordinates":[78.57709800000001,24.765687],"type":"Point"}
}