{
  "type": "Feature",
  "properties": {
    "iso:country":"IN",
    "ks:ks_name":"Bishra",
    "ks:ks_pop":1394,
    "ks:ks_type":"VILLAGE",
    "ks:ks_uagg_main":0,
    "name:eng_x_preferred":[
        "Bishra"
    ],
    "wof:name":"Bishra",
    "wof:placetype":"neighbourhood",
    "wof:population":1394
},
  "geometry": {"coordinates":[88.109855,22.283938],"type":"Point"}
}