{
  "type": "Feature",
  "properties": {
    "gn:admin1_code":"37.0",
    "gn:admin2_code":"414.0",
    "gn:asciiname":"Ardeli",
    "gn:country_code":"IN",
    "gn:dem":654,
    "gn:feature_class":"P",
    "gn:feature_code":"PPL",
    "gn:name":"Ardeli",
    "gn:population":0,
    "gn:timezone":"Asia/Kolkata",
    "iso:country":"IN",
    "wof:name":"Ardeli",
    "wof:placetype":"neighbourhood"
},
  "geometry": {"coordinates":[81.78861000000001,19.85652],"type":"Point"}
}