{
  "type": "Feature",
  "properties": {
    "gn:admin1_code":"24.0",
    "gn:admin2_code":"131",
    "gn:asciiname":"Boria",
    "gn:country_code":"IN",
    "gn:dem":200,
    "gn:feature_class":"P",
    "gn:feature_code":"PPL",
    "gn:name":"Boria",
    "gn:population":0,
    "gn:timezone":"Asia/Kolkata",
    "iso:country":"IN",
    "wof:name":"Boria",
    "wof:placetype":"locality"
},
  "geometry": {"coordinates":[74.51963000000001,23.89325],"type":"Point"}
}