{
  "type": "Feature",
  "properties": {
    "iso:country":"IN",
    "ks:ks_name":"Redya Thanda",
    "ks:ks_pop":116,
    "ks:ks_type":"HABITATION",
    "name:eng_x_preferred":[
        "Redya Thanda"
    ],
    "wof:name":"Redya Thanda",
    "wof:placetype":"locality",
    "wof:population":116
},
  "geometry": {"coordinates":[79.790629,17.382155],"type":"Point"}
}