{
  "type": "Feature",
  "properties": {
    "gn:admin1_code":"36",
    "gn:admin2_code":"146.0",
    "gn:asciiname":"Tanora",
    "gn:country_code":"IN",
    "gn:dem":154,
    "gn:feature_class":"P",
    "gn:feature_code":"PPL",
    "gn:name":"Tanora",
    "gn:population":0,
    "gn:timezone":"Asia/Kolkata",
    "iso:country":"IN",
    "name:spa_x_preferred":[
        "Tanora"
    ],
    "name:tur_x_preferred":[
        "Tanora"
    ],
    "wof:name":"Tanora",
    "wof:placetype":"neighbourhood"
},
  "geometry": {"coordinates":[78.18226,27.17392],"type":"Point"}
}