{
  "type": "Feature",
  "properties": {
    "iso:country":"IN",
    "ks:ks_alt_nam":"SURJEET  HAR BHAJAN KI DHANI",
    "ks:ks_name":"Surjeet Har Bhajan Ki Dhani",
    "ks:ks_pop":29,
    "ks:ks_type":"HABITATION",
    "name:eng_x_preferred":[
        "Surjeet Har Bhajan Ki Dhani"
    ],
    "name:eng_x_variant":[
        "SURJEET  HAR BHAJAN KI DHANI"
    ],
    "wof:name":"Surjeet Har Bhajan Ki Dhani",
    "wof:placetype":"locality",
    "wof:population":29
},
  "geometry": {"coordinates":[73.933042,30.127361],"type":"Point"}
}