{
  "type": "Feature",
  "properties": {
    "gn:admin1_code":"12.0",
    "gn:admin2_code":"020",
    "gn:asciiname":"Riala",
    "gn:country_code":"IN",
    "gn:dem":658,
    "gn:feature_class":"P",
    "gn:feature_code":"PPL",
    "gn:name":"R\u012b\u0101la",
    "gn:population":0,
    "gn:timezone":"Asia/Kolkata",
    "iso:country":"IN",
    "wof:name":"Riala",
    "wof:placetype":"locality"
},
  "geometry": {"coordinates":[74.88455999999999,32.96907],"type":"Point"}
}