{
  "type": "Feature",
  "properties": {
    "gn:admin1_code":"12.0",
    "gn:admin2_code":"020",
    "gn:asciiname":"Riala",
    "gn:country_code":"IN",
    "gn:dem":658,
    "gn:feature_class":"P",
    "gn:feature_code":"PPL",
    "gn:name":"R\u012b\u0101la",
    "gn:population":0,
    "gn:timezone":"Asia/Kolkata",
    "iso:country":"IN",
    "name:ceb_x_preferred":[
        "Riala"
    ],
    "name:fas_x_preferred":[
        "\u0631\u06cc\u0627\u0644\u0627"
    ],
    "name:ita_x_preferred":[
        "Riala"
    ],
    "name:nld_x_preferred":[
        "Riala"
    ],
    "name:nno_x_preferred":[
        "Riala"
    ],
    "name:nor_x_preferred":[
        "Riala"
    ],
    "name:swe_x_preferred":[
        "Riala"
    ],
    "wof:name":"Riala",
    "wof:placetype":"locality"
},
  "geometry": {"coordinates":[74.88455999999999,32.96907],"type":"Point"}
}