{
  "type": "Feature",
  "properties": {
    "iso:country":"IN",
    "ks:ks_name":"Dom Toli",
    "ks:ks_pop":145,
    "ks:ks_type":"HABITATION",
    "name:eng_x_preferred":[
        "Dom Toli"
    ],
    "wof:name":"Dom Toli",
    "wof:placetype":"locality",
    "wof:population":145
},
  "geometry": {"coordinates":[84.346012,27.07796],"type":"Point"}
}