{
  "type": "Feature",
  "properties": {
    "gn:admin1_code":"34.0",
    "gn:admin2_code":"215.0",
    "gn:asciiname":"Ujan",
    "gn:country_code":"IN",
    "gn:dem":57,
    "gn:feature_class":"P",
    "gn:feature_code":"PPL",
    "gn:name":"Uj\u0101n",
    "gn:population":0,
    "gn:timezone":"Asia/Kolkata",
    "iso:country":"IN",
    "name:ara_x_preferred":[
        "\u0623\u0648\u062c\u0627\u0646"
    ],
    "name:aze_x_preferred":[
        "Ucan"
    ],
    "name:fas_x_preferred":[
        "\u0627\u0648\u062c\u0627\u0646"
    ],
    "name:fra_x_preferred":[
        "Ujan"
    ],
    "name:hye_x_preferred":[
        "\u0548\u0582\u057b\u0561\u0576"
    ],
    "name:ita_x_preferred":[
        "Udjan"
    ],
    "name:kat_x_preferred":[
        "\u10e3\u10ef\u10d0\u10dc\u10d8"
    ],
    "name:msa_x_preferred":[
        "Ujan"
    ],
    "name:rus_x_preferred":[
        "\u0423\u0434\u0436\u0430\u043d"
    ],
    "name:spa_x_preferred":[
        "Ujan"
    ],
    "name:ukr_x_preferred":[
        "\u0423\u0434\u0436\u0430\u043d"
    ],
    "name:vie_x_preferred":[
        "Udjan"
    ],
    "wof:name":"Ujan",
    "wof:placetype":"locality"
},
  "geometry": {"coordinates":[86.22636999999997,26.20801],"type":"Point"}
}