{
  "type": "Feature",
  "properties": {
    "iso:country":"IN",
    "ks:ks_name":"Kalikapur",
    "ks:ks_pop":2004,
    "ks:ks_type":"VILLAGE",
    "ks:ks_uagg_main":0,
    "name:eng_x_preferred":[
        "Kalikapur"
    ],
    "wof:name":"Kalikapur",
    "wof:placetype":"locality",
    "wof:population":2004
},
  "geometry": {"coordinates":[88.404312,22.339741],"type":"Point"}
}