{
  "type": "Feature",
  "properties": {
    "gn:admin1_code":"13.0",
    "gn:admin2_code":"597.0",
    "gn:asciiname":"Aymanam",
    "gn:country_code":"IN",
    "gn:dem":9,
    "gn:feature_class":"P",
    "gn:feature_code":"PPL",
    "gn:name":"Aymanam",
    "gn:population":0,
    "gn:timezone":"Asia/Kolkata",
    "iso:country":"IN",
    "name:ceb_x_preferred":[
        "Aymanam"
    ],
    "name:mal_x_preferred":[
        "\u0d05\u0d2f\u0d4d\u0d2e\u0d28\u0d02"
    ],
    "name:swe_x_preferred":[
        "Aymanam"
    ],
    "wof:name":"Aymanam",
    "wof:placetype":"locality"
},
  "geometry": {"coordinates":[76.50055,9.60684],"type":"Point"}
}