{
  "type": "Feature",
  "properties": {
    "iso:country":"IN",
    "ks:ks_name":"Ramfal Ka Purwa",
    "ks:ks_pop":104,
    "ks:ks_type":"HABITATION",
    "name:eng_x_preferred":[
        "Ramfal Ka Purwa"
    ],
    "wof:name":"Ramfal Ka Purwa",
    "wof:placetype":"locality",
    "wof:population":104
},
  "geometry": {"coordinates":[82.12459699999999,26.512976],"type":"Point"}
}