{
  "type": "Feature",
  "properties": {
    "iso:country":"IN",
    "ks:ks_name":"Bandhasai",
    "ks:ks_pop":140,
    "ks:ks_type":"HABITATION",
    "name:eng_x_preferred":[
        "Bandhasai"
    ],
    "wof:name":"Bandhasai",
    "wof:placetype":"locality",
    "wof:population":140
},
  "geometry": {"coordinates":[85.53201799999999,22.533359],"type":"Point"}
}