{
  "type": "Feature",
  "properties": {
    "iso:country":"IN",
    "ks:ks_name":"Budhuaha",
    "ks:ks_pop":911,
    "ks:ks_type":"VILLAGE",
    "name:eng_x_preferred":[
        "Budhuaha"
    ],
    "wof:name":"Budhuaha",
    "wof:placetype":"locality",
    "wof:population":911
},
  "geometry": {"coordinates":[85.012927,26.862817],"type":"Point"}
}