{
  "type": "Feature",
  "properties": {
    "gn:admin1_code":"2.0",
    "gn:admin2_code":"542.0",
    "gn:asciiname":"Turakapeta",
    "gn:country_code":"IN",
    "gn:dem":35,
    "gn:feature_class":"P",
    "gn:feature_code":"PPL",
    "gn:name":"Turakapeta",
    "gn:population":0,
    "gn:timezone":"Asia/Kolkata",
    "iso:country":"IN",
    "wof:name":"Turakapeta",
    "wof:placetype":"locality"
},
  "geometry": {"coordinates":[83.94275999999998,18.58664],"type":"Point"}
}