{
  "type": "Feature",
  "properties": {
    "iso:country":"IN",
    "ks:ks_name":"Mandiram",
    "ks:ks_pop":268,
    "ks:ks_type":"HABITATION",
    "name:eng_x_preferred":[
        "Mandiram"
    ],
    "wof:name":"Mandiram",
    "wof:placetype":"locality",
    "wof:population":268
},
  "geometry": {"coordinates":[80.075788,14.647153],"type":"Point"}
}