{
  "type": "Feature",
  "properties": {
    "iso:country":"IN",
    "ks:ks_name":"Bursum Bari",
    "ks:ks_pop":712,
    "ks:ks_type":"VILLAGE",
    "name:eng_x_preferred":[
        "Bursum Bari"
    ],
    "wof:name":"Bursum Bari",
    "wof:placetype":"locality",
    "wof:population":712
},
  "geometry": {"coordinates":[80.093822,29.614355],"type":"Point"}
}