{
  "type": "Feature",
  "properties": {
    "iso:country":"IN",
    "ks:ks_name":"Salyabadli",
    "ks:ks_pop":196,
    "ks:ks_type":"HABITATION",
    "name:eng_x_preferred":[
        "Salyabadli"
    ],
    "wof:name":"Salyabadli",
    "wof:placetype":"locality",
    "wof:population":196
},
  "geometry": {"coordinates":[74.62313899999999,23.404314],"type":"Point"}
}