{
  "type": "Feature",
  "properties": {
    "gn:admin1_code":"40",
    "gn:admin2_code":"532.0",
    "gn:asciiname":"Arigela",
    "gn:country_code":"IN",
    "gn:dem":336,
    "gn:feature_class":"P",
    "gn:feature_code":"PPL",
    "gn:name":"Arigela",
    "gn:population":0,
    "gn:timezone":"Asia/Kolkata",
    "iso:country":"IN",
    "ks:ks_name":"Arigela",
    "ks:ks_type":"VILLAGE",
    "name:eng_x_preferred":[
        "Arigela"
    ],
    "wof:name":"Arigela",
    "wof:placetype":"locality"
},
  "geometry": {"coordinates":[78.173913,19.045277],"type":"Point"}
}