{
  "type": "Feature",
  "properties": {
    "iso:country":"IN",
    "ks:ks_name":"Muthakhowa Pt 3",
    "ks:ks_pop":1556,
    "ks:ks_type":"HABITATION",
    "name:eng_x_preferred":[
        "Muthakhowa Pt 3"
    ],
    "wof:name":"Muthakhowa Pt 3",
    "wof:placetype":"locality",
    "wof:population":1556
},
  "geometry": {"coordinates":[89.90343,25.906684],"type":"Point"}
}