{
  "type": "Feature",
  "properties": {
    "iso:country":"IN",
    "ks:ks_name":"Amlot",
    "ks:ks_pop":72,
    "ks:ks_type":"HABITATION",
    "name:eng_x_preferred":[
        "Amlot"
    ],
    "wof:name":"Amlot",
    "wof:placetype":"locality",
    "wof:population":72
},
  "geometry": {"coordinates":[82.41332,20.43744],"type":"Point"}
}