{
  "type": "Feature",
  "properties": {
    "iso:country":"IN",
    "ks:ks_name":"Kachur Thota",
    "ks:ks_pop":300,
    "ks:ks_type":"HABITATION",
    "name:eng_x_preferred":[
        "Kachur Thota"
    ],
    "wof:name":"Kachur Thota",
    "wof:placetype":"locality",
    "wof:population":300
},
  "geometry": {"coordinates":[74.743314,13.462651],"type":"Point"}
}