{
  "type": "Feature",
  "properties": {
    "gn:admin1_code":"34.0",
    "gn:admin2_code":"204.0",
    "gn:asciiname":"Parsauni Kapuer",
    "gn:country_code":"IN",
    "gn:dem":68,
    "gn:feature_class":"P",
    "gn:feature_code":"PPL",
    "gn:name":"Parsauni Kap\u00fcr",
    "gn:population":0,
    "gn:timezone":"Asia/Kolkata",
    "iso:country":"IN",
    "wof:name":"Parsauni Kapuer",
    "wof:placetype":"locality"
},
  "geometry": {"coordinates":[85.14494000000001,26.55914000000001],"type":"Point"}
}