{
  "type": "Feature",
  "properties": {
    "iso:country":"IN",
    "ks:ks_name":"Maranakodige",
    "ks:ks_pop":22,
    "ks:ks_type":"HABITATION",
    "name:eng_x_preferred":[
        "Maranakodige"
    ],
    "wof:name":"Maranakodige",
    "wof:placetype":"locality",
    "wof:population":22
},
  "geometry": {"coordinates":[75.30364,13.389409],"type":"Point"}
}