{
  "type": "Feature",
  "properties": {
    "iso:country":"IN",
    "ks:ks_name":"Nayakapuguda",
    "ks:ks_pop":59,
    "ks:ks_type":"HABITATION",
    "name:eng_x_preferred":[
        "Nayakapuguda"
    ],
    "wof:name":"Nayakapuguda",
    "wof:placetype":"locality",
    "wof:population":59
},
  "geometry": {"coordinates":[79.29429500000001,19.184603],"type":"Point"}
}