{
  "type": "Feature",
  "properties": {
    "iso:country":"IN",
    "ks:ks_name":"Chithoor J H C",
    "ks:ks_pop":228,
    "ks:ks_type":"HABITATION",
    "name:eng_x_preferred":[
        "Chithoor J H C"
    ],
    "wof:name":"Chithoor J H C",
    "wof:placetype":"locality",
    "wof:population":228
},
  "geometry": {"coordinates":[74.77225300000001,13.730181],"type":"Point"}
}