{
  "type": "Feature",
  "properties": {
    "iso:country":"IN",
    "ks:ks_alt_nam":"TIWARI PUR",
    "ks:ks_name":"Tiwari Pur",
    "ks:ks_pop":100,
    "ks:ks_type":"HABITATION",
    "name:eng_x_preferred":[
        "Tiwari Pur"
    ],
    "wof:name":"Tiwari Pur",
    "wof:placetype":"locality",
    "wof:population":100
},
  "geometry": {"coordinates":[81.786599,26.052643],"type":"Point"}
}