{
  "type": "Feature",
  "properties": {
    "iso:country":"IN",
    "ks:ks_name":"Sampekatte",
    "ks:ks_pop":86,
    "ks:ks_type":"HABITATION",
    "name:eng_x_preferred":[
        "Sampekatte"
    ],
    "wof:name":"Sampekatte",
    "wof:placetype":"locality",
    "wof:population":86
},
  "geometry": {"coordinates":[75.251532,13.543583],"type":"Point"}
}