{
  "type": "Feature",
  "properties": {
    "iso:country":"IN",
    "ks:ks_name":"Niz Moderkhat",
    "ks:ks_pop":578,
    "ks:ks_type":"HABITATION",
    "name:eng_x_preferred":[
        "Niz Moderkhat"
    ],
    "wof:name":"Niz Moderkhat",
    "wof:placetype":"locality",
    "wof:population":578
},
  "geometry": {"coordinates":[95.060879,27.42859],"type":"Point"}
}