{
  "type": "Feature",
  "properties": {
    "gn:admin1_code":"39.0",
    "gn:admin2_code":"60.0",
    "gn:asciiname":"Bauta",
    "gn:country_code":"IN",
    "gn:dem":1271,
    "gn:feature_class":"P",
    "gn:feature_code":"PPL",
    "gn:name":"Bauta",
    "gn:population":0,
    "gn:timezone":"Asia/Kolkata",
    "iso:country":"IN",
    "name:ceb_x_preferred":[
        "Bauta"
    ],
    "name:deu_x_preferred":[
        "Bauta"
    ],
    "name:fra_x_preferred":[
        "Bauta"
    ],
    "name:ita_x_preferred":[
        "Bauta"
    ],
    "name:vec_x_preferred":[
        "Bauta"
    ],
    "wof:name":"Bauta",
    "wof:placetype":"locality"
},
  "geometry": {"coordinates":[78.13248,30.364],"type":"Point"}
}