{
  "type": "Feature",
  "properties": {
    "iso:country":"IN",
    "ks:ks_name":"Venugopalapuram",
    "ks:ks_pop":47,
    "ks:ks_type":"HABITATION",
    "name:eng_x_preferred":[
        "Venugopalapuram"
    ],
    "wof:name":"Venugopalapuram",
    "wof:placetype":"locality",
    "wof:population":47
},
  "geometry": {"coordinates":[79.341042,13.50446],"type":"Point"}
}