{
  "type": "Feature",
  "properties": {
    "gn:admin1_code":"39.0",
    "gn:admin2_code":"63.0",
    "gn:asciiname":"Patal",
    "gn:country_code":"IN",
    "gn:dem":1532,
    "gn:feature_class":"P",
    "gn:feature_code":"PPL",
    "gn:name":"P\u0101tal",
    "gn:population":0,
    "gn:timezone":"Asia/Kolkata",
    "iso:country":"IN",
    "name:fas_x_preferred":[
        "\u067e\u0627\u062a\u0644"
    ],
    "wof:name":"Patal",
    "wof:placetype":"locality"
},
  "geometry": {"coordinates":[79.98702,29.86738],"type":"Point"}
}