{
  "type": "Feature",
  "properties": {
    "iso:country":"IN",
    "ks:ks_name":"Bhaura",
    "ks:ks_pop":549,
    "ks:ks_type":"VILLAGE",
    "name:eng_x_preferred":[
        "Bhaura"
    ],
    "wof:name":"Bhaura",
    "wof:placetype":"locality",
    "wof:population":549
},
  "geometry": {"coordinates":[71.46043299999999,25.120711],"type":"Point"}
}