{
  "type": "Feature",
  "properties": {
    "iso:country":"IN",
    "ks:ks_alt_nam":"Usara falia",
    "ks:ks_name":"Usara Falia",
    "ks:ks_pop":367,
    "ks:ks_type":"HABITATION",
    "ks:ks_uagg_main":0,
    "name:eng_x_preferred":[
        "Usara Falia"
    ],
    "wof:name":"Usara Falia",
    "wof:placetype":"neighbourhood",
    "wof:population":367
},
  "geometry": {"coordinates":[74.20097199999999,22.91175],"type":"Point"}
}