{
  "type": "Feature",
  "properties": {
    "iso:country":"IN",
    "ks:ks_name":"Kadiyapa",
    "ks:ks_pop":345,
    "ks:ks_type":"HABITATION",
    "name:eng_x_preferred":[
        "Kadiyapa"
    ],
    "wof:name":"Kadiyapa",
    "wof:placetype":"locality",
    "wof:population":345
},
  "geometry": {"coordinates":[74.04346700000001,25.768194],"type":"Point"}
}