{
  "type": "Feature",
  "properties": {
    "iso:country":"IN",
    "ks:ks_name":"Yaddahalli Site",
    "ks:ks_pop":45,
    "ks:ks_type":"HABITATION",
    "name:eng_x_preferred":[
        "Yaddahalli Site"
    ],
    "wof:name":"Yaddahalli Site",
    "wof:placetype":"locality",
    "wof:population":45
},
  "geometry": {"coordinates":[75.20856999999999,13.375334],"type":"Point"}
}