{
  "type": "Feature",
  "properties": {
    "iso:country":"IN",
    "ks:ks_name":"Karanjharan",
    "ks:ks_pop":501,
    "ks:ks_type":"VILLAGE",
    "name:eng_x_preferred":[
        "Karanjharan"
    ],
    "wof:name":"Karanjharan",
    "wof:placetype":"locality",
    "wof:population":501
},
  "geometry": {"coordinates":[86.258295,22.146751],"type":"Point"}
}