{
  "type": "Feature",
  "properties": {
    "iso:country":"IN",
    "ks:ks_name":"Dakbangla",
    "ks:ks_pop":395,
    "ks:ks_type":"HABITATION",
    "name:eng_x_preferred":[
        "Dakbangla"
    ],
    "wof:name":"Dakbangla",
    "wof:placetype":"locality",
    "wof:population":395
},
  "geometry": {"coordinates":[78.568045,25.122923],"type":"Point"}
}