{
  "type": "Feature",
  "properties": {
    "iso:country":"IN",
    "ks:ks_name":"Byaspur",
    "ks:ks_pop":2262,
    "ks:ks_type":"VILLAGE",
    "name:eng_x_preferred":[
        "Byaspur"
    ],
    "wof:name":"Byaspur",
    "wof:placetype":"locality",
    "wof:population":2262
},
  "geometry": {"coordinates":[88.364727,22.274778],"type":"Point"}
}