{
  "type": "Feature",
  "properties": {
    "iso:country":"IN",
    "ks:ks_name":"Dedagaon",
    "ks:ks_pop":225,
    "ks:ks_type":"VILLAGE",
    "name:eng_x_preferred":[
        "Dedagaon"
    ],
    "wof:name":"Dedagaon",
    "wof:placetype":"locality",
    "wof:population":225
},
  "geometry": {"coordinates":[83.36049199999999,19.82161],"type":"Point"}
}