{
  "type": "Feature",
  "properties": {
    "gn:admin1_code":"16.0",
    "gn:admin2_code":"523.0",
    "gn:asciiname":"Hiwra Buzurg",
    "gn:country_code":"IN",
    "gn:dem":413,
    "gn:feature_class":"P",
    "gn:feature_code":"PPL",
    "gn:name":"Hiwra Buzurg",
    "gn:population":0,
    "gn:timezone":"Asia/Kolkata",
    "iso:country":"IN",
    "wof:name":"Hiwra Buzurg",
    "wof:placetype":"locality"
},
  "geometry": {"coordinates":[76.09089,19.27906],"type":"Point"}
}