{
  "type": "Feature",
  "properties": {
    "iso:country":"IN",
    "ks:ks_name":"Ecangadu",
    "ks:ks_pop":127,
    "ks:ks_type":"HABITATION",
    "name:eng_x_preferred":[
        "Ecangadu"
    ],
    "wof:name":"Ecangadu",
    "wof:placetype":"locality",
    "wof:population":127
},
  "geometry": {"coordinates":[79.66416,12.559878],"type":"Point"}
}