{
  "type": "Feature",
  "properties": {
    "iso:country":"IN",
    "ks:ks_name":"Damor Falia",
    "ks:ks_pop":195,
    "ks:ks_type":"HABITATION",
    "name:eng_x_preferred":[
        "Damor Falia"
    ],
    "wof:name":"Damor Falia",
    "wof:placetype":"locality",
    "wof:population":195
},
  "geometry": {"coordinates":[74.075664,23.156397],"type":"Point"}
}