{
  "type": "Feature",
  "properties": {
    "gn:admin1_code":"2.0",
    "gn:admin2_code":"542.0",
    "gn:asciiname":"Somalingapuram",
    "gn:country_code":"IN",
    "gn:dem":140,
    "gn:feature_class":"P",
    "gn:feature_code":"PPL",
    "gn:name":"Somalingapuram",
    "gn:population":0,
    "gn:timezone":"Asia/Kolkata",
    "iso:country":"IN",
    "name:tel_x_preferred":[
        "\u0c38\u0c4b\u0c2e\u0c32\u0c3f\u0c02\u0c17\u0c3e\u0c2a\u0c41\u0c30\u0c02"
    ],
    "wof:name":"Somalingapuram",
    "wof:placetype":"locality"
},
  "geometry": {"coordinates":[83.47910999999998,18.41123],"type":"Point"}
}