{
  "type": "Feature",
  "properties": {
    "gn:admin1_code":"12",
    "gn:admin2_code":"3.0",
    "gn:asciiname":"Nischu",
    "gn:cc2":"IN",
    "gn:country_code":"IN",
    "gn:dem":5601,
    "gn:feature_class":"P",
    "gn:feature_code":"PPL",
    "gn:name":"Nischu",
    "gn:population":0,
    "gn:timezone":"Asia/Kolkata",
    "iso:country":"IN",
    "name:und_x_variant":[
        "Nisichu",
        "Nischu"
    ],
    "name:zho_x_preferred":[
        "\u5c3c\u65af\u695a"
    ],
    "wof:name":"Nischu",
    "wof:placetype":"locality"
},
  "geometry": {"coordinates":[79.10813,34.5224],"type":"Point"}
}