{
  "type": "Feature",
  "properties": {
    "iso:country":"IN",
    "ks:ks_name":"Dadhari",
    "ks:ks_pop":551,
    "ks:ks_type":"VILLAGE",
    "name:eng_x_preferred":[
        "Dadhari"
    ],
    "wof:name":"Dadhari",
    "wof:placetype":"locality",
    "wof:population":551
},
  "geometry": {"coordinates":[73.229913,20.04715],"type":"Point"}
}