{
  "type": "Feature",
  "properties": {
    "iso:country":"IN",
    "ks:ks_name":"Chengmari Gaon",
    "ks:ks_pop":5,
    "ks:ks_type":"VILLAGE",
    "ks:ks_uagg_main":0,
    "name:eng_x_preferred":[
        "Chengmari Gaon"
    ],
    "wof:name":"Chengmari Gaon",
    "wof:placetype":"neighbourhood",
    "wof:population":5
},
  "geometry": {"coordinates":[92.02077800000001,26.257932],"type":"Point"}
}