{
  "type": "Feature",
  "properties": {
    "iso:country":"IN",
    "ks:ks_name":"Chanauli",
    "ks:ks_pop":141,
    "ks:ks_type":"VILLAGE",
    "name:eng_x_preferred":[
        "Chanauli"
    ],
    "wof:name":"Chanauli",
    "wof:placetype":"locality",
    "wof:population":141
},
  "geometry": {"coordinates":[80.33617700000001,29.659115],"type":"Point"}
}