{
  "type": "Feature",
  "properties": {
    "iso:country":"IN",
    "ks:ks_name":"Kulagan no-2",
    "ks:ks_pop":1040,
    "ks:ks_type":"VILLAGE",
    "ks:ks_uagg_main":0,
    "name:eng_x_preferred":[
        "Kulagan no-2"
    ],
    "wof:name":"Kulagan no-2",
    "wof:placetype":"neighbourhood",
    "wof:population":1040
},
  "geometry": {"coordinates":[86.20623000000001,20.794744],"type":"Point"}
}