{
  "type": "Feature",
  "properties": {
    "iso:country":"IN",
    "ks:ks_name":"Paschim Benchimari",
    "ks:ks_pop":457,
    "ks:ks_type":"HABITATION",
    "name:eng_x_preferred":[
        "Paschim Benchimari"
    ],
    "wof:name":"Paschim Benchimari",
    "wof:placetype":"locality",
    "wof:population":457
},
  "geometry": {"coordinates":[91.416355,26.696951],"type":"Point"}
}