{
  "type": "Feature",
  "properties": {
    "iso:country":"IN",
    "ks:ks_name":"Tagheju",
    "ks:ks_pop":8,
    "ks:ks_type":"HABITATION",
    "name:eng_x_preferred":[
        "Tagheju"
    ],
    "wof:name":"Tagheju",
    "wof:placetype":"locality",
    "wof:population":8
},
  "geometry": {"coordinates":[83.70991600000001,20.323397],"type":"Point"}
}