{
  "type": "Feature",
  "properties": {
    "iso:country":"IN",
    "ks:ks_name":"Somajithanda",
    "ks:ks_pop":273,
    "ks:ks_type":"HABITATION",
    "name:eng_x_preferred":[
        "Somajithanda"
    ],
    "wof:name":"Somajithanda",
    "wof:placetype":"locality",
    "wof:population":273
},
  "geometry": {"coordinates":[79.167653,18.048195],"type":"Point"}
}