{
  "type": "Feature",
  "properties": {
    "gn:admin1_code":"21",
    "gn:admin2_code":"394.0",
    "gn:asciiname":"Sitlikhalia",
    "gn:country_code":"IN",
    "gn:dem":245,
    "gn:feature_class":"P",
    "gn:feature_code":"PPL",
    "gn:name":"S\u012btl\u012bkhalia",
    "gn:population":0,
    "gn:timezone":"Asia/Kolkata",
    "iso:country":"IN",
    "wof:name":"Sitlikhalia",
    "wof:placetype":"locality"
},
  "geometry": {"coordinates":[82.73427,20.12619],"type":"Point"}
}