{
  "type": "Feature",
  "properties": {
    "gn:admin1_code":"19.0",
    "gn:admin2_code":"574.0",
    "gn:asciiname":"Thoti",
    "gn:country_code":"IN",
    "gn:dem":882,
    "gn:feature_class":"P",
    "gn:feature_code":"PPL",
    "gn:name":"Thoti",
    "gn:population":0,
    "gn:timezone":"Asia/Kolkata",
    "iso:country":"IN",
    "name:hin_x_preferred":[
        "\u0925\u094b\u0924\u0940 \u091c\u0928\u091c\u093e\u0924\u093f"
    ],
    "wof:name":"Thoti",
    "wof:placetype":"locality"
},
  "geometry": {"coordinates":[76.55203,12.98437],"type":"Point"}
}