{
  "type": "Feature",
  "properties": {
    "iso:country":"IN",
    "ks:ks_name":"Koragarasale",
    "ks:ks_pop":99,
    "ks:ks_type":"HABITATION",
    "name:eng_x_preferred":[
        "Koragarasale"
    ],
    "wof:name":"Koragarasale",
    "wof:placetype":"locality",
    "wof:population":99
},
  "geometry": {"coordinates":[74.836747,13.812664],"type":"Point"}
}