{
  "type": "Feature",
  "properties": {
    "iso:country":"IN",
    "ks:ks_name":"Bonla Tanda",
    "ks:ks_pop":236,
    "ks:ks_type":"HABITATION",
    "name:eng_x_preferred":[
        "Bonla Tanda"
    ],
    "wof:name":"Bonla Tanda",
    "wof:placetype":"locality",
    "wof:population":236
},
  "geometry": {"coordinates":[77.414734,18.454831],"type":"Point"}
}