{
  "type": "Feature",
  "properties": {
    "gn:admin1_code":"19.0",
    "gn:admin2_code":"577.0",
    "gn:asciiname":"Benkipura",
    "gn:country_code":"IN",
    "gn:dem":771,
    "gn:feature_class":"P",
    "gn:feature_code":"PPL",
    "gn:name":"Benkipura",
    "gn:population":0,
    "gn:timezone":"Asia/Kolkata",
    "iso:country":"IN",
    "wof:name":"Benkipura",
    "wof:placetype":"locality"
},
  "geometry": {"coordinates":[76.41974,12.25615],"type":"Point"}
}