{
  "type": "Feature",
  "properties": {
    "iso:country":"IN",
    "ks:ks_alt_nam":"Agnu ka Pura",
    "ks:ks_name":"Agnu Ka Pura",
    "ks:ks_pop":138,
    "ks:ks_type":"HABITATION",
    "name:eng_x_preferred":[
        "Agnu Ka Pura"
    ],
    "wof:name":"Agnu Ka Pura",
    "wof:placetype":"locality",
    "wof:population":138
},
  "geometry": {"coordinates":[82.31501900000001,25.207404],"type":"Point"}
}