{
  "type": "Feature",
  "properties": {
    "iso:country":"IN",
    "ks:ks_name":"21 KND",
    "ks:ks_pop":220,
    "ks:ks_type":"VILLAGE",
    "name:eng_x_preferred":[
        "21 KND"
    ],
    "wof:name":"21 KND",
    "wof:placetype":"locality",
    "wof:population":220
},
  "geometry": {"coordinates":[72.68297800000001,28.877339],"type":"Point"}
}