{
  "type": "Feature",
  "properties": {
    "iso:country":"IN",
    "ks:ks_name":"Jginwada",
    "ks:ks_pop":41,
    "ks:ks_type":"HABITATION",
    "name:eng_x_preferred":[
        "Jginwada"
    ],
    "wof:name":"Jginwada",
    "wof:placetype":"locality",
    "wof:population":41
},
  "geometry": {"coordinates":[74.495214,15.157385],"type":"Point"}
}