{
  "type": "Feature",
  "properties": {
    "gn:admin1_code":"34.0",
    "gn:admin2_code":"235.0",
    "gn:asciiname":"Sonbarsa",
    "gn:country_code":"IN",
    "gn:dem":107,
    "gn:feature_class":"P",
    "gn:feature_code":"PPL",
    "gn:name":"Sonbarsa",
    "gn:population":0,
    "gn:timezone":"Asia/Kolkata",
    "iso:country":"IN",
    "name:ceb_x_preferred":[
        "Sonbarsa"
    ],
    "name:mai_x_preferred":[
        "\u0938\u094b\u0928\u092c\u0930\u094d\u0937\u093e"
    ],
    "name:msa_x_preferred":[
        "Sonbarsa"
    ],
    "name:nep_x_preferred":[
        "\u0938\u094b\u0928\u092c\u0930\u094d\u0937\u093e"
    ],
    "name:new_x_preferred":[
        "\u0938\u094b\u0928\u0935\u0930\u094d\u0937"
    ],
    "name:pol_x_preferred":[
        "Sonbarsa"
    ],
    "wof:name":"Sonbarsa",
    "wof:placetype":"locality"
},
  "geometry": {"coordinates":[84.26295999999998,24.87058],"type":"Point"}
}