{
  "type": "Feature",
  "properties": {
    "gn:admin1_code":"11.0",
    "gn:admin2_code":"31.0",
    "gn:asciiname":"Daghil",
    "gn:country_code":"IN",
    "gn:dem":1428,
    "gn:feature_class":"P",
    "gn:feature_code":"PPL",
    "gn:name":"Dagh\u012bl",
    "gn:population":0,
    "gn:timezone":"Asia/Kolkata",
    "iso:country":"IN",
    "wof:name":"Daghil",
    "wof:placetype":"locality"
},
  "geometry": {"coordinates":[77.17676,30.94098],"type":"Point"}
}