{
  "type": "Feature",
  "properties": {
    "gn:admin1_code":"39.0",
    "gn:admin2_code":"61.0",
    "gn:asciiname":"Dungri",
    "gn:country_code":"IN",
    "gn:dem":1220,
    "gn:feature_class":"P",
    "gn:feature_code":"PPL",
    "gn:name":"D\u016bngri",
    "gn:population":0,
    "gn:timezone":"Asia/Kolkata",
    "iso:country":"IN",
    "wof:name":"Dungri",
    "wof:placetype":"locality"
},
  "geometry": {"coordinates":[79.0742,29.70317],"type":"Point"}
}