{
  "type": "Feature",
  "properties": {
    "iso:country":"IN",
    "ks:ks_name":"Khori Pada",
    "ks:ks_pop":455,
    "ks:ks_type":"HABITATION",
    "name:eng_x_preferred":[
        "Khori Pada"
    ],
    "wof:name":"Khori Pada",
    "wof:placetype":"locality",
    "wof:population":455
},
  "geometry": {"coordinates":[73.24936099999999,20.391083],"type":"Point"}
}