{
  "type": "Feature",
  "properties": {
    "iso:country":"IN",
    "ks:ks_alt_nam":"mohalla no. 2",
    "ks:ks_name":"Mohalla No. 2",
    "ks:ks_pop":259,
    "ks:ks_type":"HABITATION",
    "name:eng_x_preferred":[
        "Mohalla No. 2"
    ],
    "wof:name":"Mohalla No. 2",
    "wof:placetype":"locality",
    "wof:population":259
},
  "geometry": {"coordinates":[73.584444,17.486389],"type":"Point"}
}