{
  "type": "Feature",
  "properties": {
    "iso:country":"IN",
    "ks:ks_name":"Baburipurwa",
    "ks:ks_pop":210,
    "ks:ks_type":"HABITATION",
    "name:eng_x_preferred":[
        "Baburipurwa"
    ],
    "wof:name":"Baburipurwa",
    "wof:placetype":"locality",
    "wof:population":210
},
  "geometry": {"coordinates":[80.965255,27.636021],"type":"Point"}
}