{
  "type": "Feature",
  "properties": {
    "gn:admin1_code":"36.0",
    "gn:admin2_code":"145.0",
    "gn:asciiname":"Bhagosa",
    "gn:country_code":"IN",
    "gn:dem":186,
    "gn:feature_class":"P",
    "gn:feature_code":"PPL",
    "gn:name":"Bhagosa",
    "gn:population":0,
    "gn:timezone":"Asia/Kolkata",
    "iso:country":"IN",
    "wof:name":"Bhagosa",
    "wof:placetype":"locality"
},
  "geometry": {"coordinates":[77.43086,27.52975],"type":"Point"}
}