{
  "type": "Feature",
  "properties": {
    "iso:country":"IN",
    "ks:ks_name":"Praharajpur",
    "ks:ks_pop":1056,
    "ks:ks_type":"VILLAGE",
    "name:eng_x_preferred":[
        "Praharajpur"
    ],
    "wof:name":"Praharajpur",
    "wof:placetype":"locality",
    "wof:population":1056
},
  "geometry": {"coordinates":[87.127916,21.804294],"type":"Point"}
}