{
  "type": "Feature",
  "properties": {
    "iso:country":"IN",
    "ks:ks_name":"Jamrepara",
    "ks:ks_pop":1034,
    "ks:ks_type":"VILLAGE",
    "ks:ks_uagg_main":0,
    "name:eng_x_preferred":[
        "Jamrepara"
    ],
    "wof:name":"Jamrepara",
    "wof:placetype":"neighbourhood",
    "wof:population":1034
},
  "geometry": {"coordinates":[87.006553,22.717328],"type":"Point"}
}