{
  "type": "Feature",
  "properties": {
    "gn:admin1_code":"28.0",
    "gn:admin2_code":"344.0",
    "gn:asciiname":"Ajurya",
    "gn:country_code":"IN",
    "gn:dem":15,
    "gn:feature_class":"P",
    "gn:feature_code":"PPL",
    "gn:name":"Ajurya",
    "gn:population":0,
    "gn:timezone":"Asia/Kolkata",
    "iso:country":"IN",
    "wof:name":"Ajurya",
    "wof:placetype":"locality"
},
  "geometry": {"coordinates":[87.77755999999999,22.52862],"type":"Point"}
}