{
  "type": "Feature",
  "properties": {
    "iso:country":"IN",
    "ks:ks_alt_nam":"K.RUDAKOTA",
    "ks:ks_name":"K.rudakota",
    "ks:ks_pop":204,
    "ks:ks_type":"HABITATION",
    "name:eng_x_preferred":[
        "K.rudakota"
    ],
    "wof:name":"K.rudakota",
    "wof:placetype":"locality",
    "wof:population":204
},
  "geometry": {"coordinates":[82.464001,18.2944],"type":"Point"}
}