{
  "type": "Feature",
  "properties": {
    "gn:admin1_code":"19.0",
    "gn:admin2_code":"573.0",
    "gn:asciiname":"Marenahalli",
    "gn:country_code":"IN",
    "gn:dem":865,
    "gn:feature_class":"P",
    "gn:feature_code":"PPL",
    "gn:name":"M\u0101renahalli",
    "gn:population":0,
    "gn:timezone":"Asia/Kolkata",
    "iso:country":"IN",
    "wof:name":"Marenahalli",
    "wof:placetype":"locality"
},
  "geometry": {"coordinates":[76.48416999999998,12.77647],"type":"Point"}
}