{
  "type": "Feature",
  "properties": {
    "gn:admin1_code":"2.0",
    "gn:admin2_code":"544.0",
    "gn:asciiname":"Peddagondi",
    "gn:country_code":"IN",
    "gn:dem":970,
    "gn:feature_class":"P",
    "gn:feature_code":"PPL",
    "gn:name":"Peddagondi",
    "gn:population":0,
    "gn:timezone":"Asia/Kolkata",
    "iso:country":"IN",
    "wof:name":"Peddagondi",
    "wof:placetype":"locality"
},
  "geometry": {"coordinates":[82.59350999999999,18.17437],"type":"Point"}
}