{
  "type": "Feature",
  "properties": {
    "gn:admin1_code":"2.0",
    "gn:admin2_code":"544.0",
    "gn:asciiname":"Peddagondi",
    "gn:country_code":"IN",
    "gn:dem":970,
    "gn:feature_class":"P",
    "gn:feature_code":"PPL",
    "gn:name":"Peddagondi",
    "gn:population":0,
    "gn:timezone":"Asia/Kolkata",
    "iso:country":"IN",
    "ks:ks_name":"Pedagondi",
    "ks:ks_pop":106,
    "ks:ks_type":"HABITATION",
    "name:eng_x_preferred":[
        "Pedagondi"
    ],
    "name:eng_x_variant":[
        "Peddagondi"
    ],
    "wof:name":"Pedagondi",
    "wof:placetype":"locality",
    "wof:population":106
},
  "geometry": {"coordinates":[82.594126,18.17447],"type":"Point"}
}