{
  "type": "Feature",
  "properties": {
    "iso:country":"IN",
    "ks:ks_name":"Plavazhikom",
    "ks:ks_pop":890,
    "ks:ks_type":"HABITATION",
    "name:eng_x_preferred":[
        "Plavazhikom"
    ],
    "wof:name":"Plavazhikom",
    "wof:placetype":"locality",
    "wof:population":890
},
  "geometry": {"coordinates":[76.751653,8.698474],"type":"Point"}
}