{
  "type": "Feature",
  "properties": {
    "gn:admin1_code":"19.0",
    "gn:admin2_code":"572",
    "gn:asciiname":"Yarub Nagar",
    "gn:country_code":"IN",
    "gn:dem":914,
    "gn:feature_class":"P",
    "gn:feature_code":"PPL",
    "gn:name":"Yarub Nagar",
    "gn:population":0,
    "gn:timezone":"Asia/Kolkata",
    "iso:country":"IN",
    "wof:name":"Yarub Nagar",
    "wof:placetype":"neighbourhood"
},
  "geometry": {"coordinates":[77.56775,12.9169],"type":"Point"}
}