{
  "type": "Feature",
  "properties": {
    "iso:country":"IN",
    "ks:ks_alt_nam":"LOYALAPARA",
    "ks:ks_name":"Loyalapara",
    "ks:ks_pop":491,
    "ks:ks_type":"HABITATION",
    "name:eng_x_preferred":[
        "Loyalapara"
    ],
    "wof:name":"Loyalapara",
    "wof:placetype":"locality",
    "wof:population":491
},
  "geometry": {"coordinates":[83.94387,22.723917],"type":"Point"}
}