{
  "type": "Feature",
  "properties": {
    "iso:country":"IN",
    "ks:ks_name":"Kurubahalli",
    "ks:ks_pop":482,
    "ks:ks_type":"HABITATION",
    "name:eng_x_preferred":[
        "Kurubahalli"
    ],
    "wof:name":"Kurubahalli",
    "wof:placetype":"locality",
    "wof:population":482
},
  "geometry": {"coordinates":[76.892,12.356],"type":"Point"}
}