{
  "type": "Feature",
  "properties": {
    "iso:country":"IN",
    "ks:ks_name":"Kharika",
    "ks:ks_pop":503,
    "ks:ks_type":"VILLAGE",
    "name:eng_x_preferred":[
        "Kharika"
    ],
    "wof:name":"Kharika",
    "wof:placetype":"locality",
    "wof:population":503
},
  "geometry": {"coordinates":[86.98809199999999,22.90431],"type":"Point"}
}