{
  "type": "Feature",
  "properties": {
    "gn:admin1_code":"25.0",
    "gn:asciiname":"Pillaichavadi",
    "gn:country_code":"IN",
    "gn:dem":11,
    "gn:feature_class":"P",
    "gn:feature_code":"PPL",
    "gn:name":"Pillaich\u0101vadi",
    "gn:population":0,
    "gn:timezone":"Asia/Kolkata",
    "iso:country":"IN",
    "wof:name":"Pillaichavadi",
    "wof:placetype":"neighbourhood"
},
  "geometry": {"coordinates":[79.85574,12.00668],"type":"Point"}
}