{
  "type": "Feature",
  "properties": {
    "gn:admin1_code":"40",
    "gn:admin2_code":"534.0",
    "gn:asciiname":"Mahadeopur",
    "gn:country_code":"IN",
    "gn:dem":123,
    "gn:feature_class":"P",
    "gn:feature_code":"PPL",
    "gn:name":"Mah\u0101deopur",
    "gn:population":0,
    "gn:timezone":"Asia/Kolkata",
    "iso:country":"IN",
    "wof:name":"Mahadeopur",
    "wof:placetype":"locality"
},
  "geometry": {"coordinates":[79.98504,18.72879],"type":"Point"}
}