{
  "type": "Feature",
  "properties": {
    "iso:country":"IN",
    "ks:ks_name":"Belapada",
    "ks:ks_pop":44,
    "ks:ks_type":"VILLAGE",
    "name:eng_x_preferred":[
        "Belapada"
    ],
    "wof:name":"Belapada",
    "wof:placetype":"locality",
    "wof:population":44
},
  "geometry": {"coordinates":[84.169571,18.953426],"type":"Point"}
}