{
  "type": "Feature",
  "properties": {
    "iso:country":"IN",
    "ks:ks_name":"Nagwan",
    "ks:ks_pop":1831,
    "ks:ks_type":"HABITATION",
    "name:eng_x_preferred":[
        "Nagwan"
    ],
    "wof:name":"Nagwan",
    "wof:placetype":"neighbourhood",
    "wof:population":1831
},
  "geometry": {"coordinates":[80.34957,26.373999],"type":"Point"}
}