{
  "type": "Feature",
  "properties": {
    "gn:admin1_code":"40.0",
    "gn:admin2_code":"532.0",
    "gn:asciiname":"Boparam",
    "gn:country_code":"IN",
    "gn:dem":329,
    "gn:feature_class":"P",
    "gn:feature_code":"PPL",
    "gn:name":"Bop\u0101ram",
    "gn:population":0,
    "gn:timezone":"Asia/Kolkata",
    "iso:country":"IN",
    "ks:ks_alt_nam":"Bop\u0101ram",
    "ks:ks_alt_nam_2":"Boparam",
    "ks:ks_name":"Bopparam",
    "ks:ks_pop":0,
    "ks:ks_type":"VILLAGE",
    "name:eng_x_preferred":[
        "Bopparam"
    ],
    "name:eng_x_variant":[
        "Boparam",
        "Bop\u0101ram"
    ],
    "wof:name":"Bopparam",
    "wof:placetype":"locality",
    "wof:population":0
},
  "geometry": {"coordinates":[78.295783,18.968424],"type":"Point"}
}