{
  "type": "Feature",
  "properties": {
    "gn:admin1_code":"11",
    "gn:admin2_code":"28.0",
    "gn:asciiname":"Andara",
    "gn:country_code":"IN",
    "gn:dem":507,
    "gn:feature_class":"P",
    "gn:feature_code":"PPL",
    "gn:name":"And\u0101ra",
    "gn:population":0,
    "gn:timezone":"Asia/Kolkata",
    "iso:country":"IN",
    "wof:name":"Andara",
    "wof:placetype":"locality"
},
  "geometry": {"coordinates":[76.39587,31.77922],"type":"Point"}
}