{
  "type": "Feature",
  "properties": {
    "gn:admin1_code":"34.0",
    "gn:admin2_code":"230.0",
    "gn:asciiname":"Bijawar",
    "gn:country_code":"IN",
    "gn:dem":60,
    "gn:feature_class":"P",
    "gn:feature_code":"PPL",
    "gn:name":"Bij\u0101war",
    "gn:population":0,
    "gn:timezone":"Asia/Kolkata",
    "iso:country":"IN",
    "ks:ks_name":"Bijawar",
    "ks:ks_pop":1222,
    "ks:ks_type":"HABITATION",
    "name:ben_x_preferred":[
        "\u09ac\u09bf\u099c\u0993\u09af\u09bc\u09be\u09b0"
    ],
    "name:bpy_x_preferred":[
        "\u09ac\u09bf\u099c\u09f1\u09be\u09b0"
    ],
    "name:ceb_x_preferred":[
        "Bij\u0101war"
    ],
    "name:deu_x_preferred":[
        "Bijawar"
    ],
    "name:eng_x_preferred":[
        "Bijawar"
    ],
    "name:ita_x_preferred":[
        "Bijawar"
    ],
    "name:jpn_x_preferred":[
        "\u30d3\u30b8\u30e3\u30fc\u30ef\u30eb"
    ],
    "name:mlg_x_preferred":[
        "Bijawar"
    ],
    "name:msa_x_preferred":[
        "Bijawar"
    ],
    "name:new_x_preferred":[
        "\u092c\u093f\u091c\u093e\u0935\u0930"
    ],
    "name:nld_x_preferred":[
        "Bijawar"
    ],
    "name:por_x_preferred":[
        "Bijawar"
    ],
    "name:spa_x_preferred":[
        "Bijawar"
    ],
    "name:swe_x_preferred":[
        "Bijawar"
    ],
    "name:vie_x_preferred":[
        "Bijawar"
    ],
    "name:zho_x_preferred":[
        "\u6bd4\u8d3e\u74e6\u5c14"
    ],
    "wof:name":"Bijawar",
    "wof:placetype":"locality",
    "wof:population":1222
},
  "geometry": {"coordinates":[85.068703,25.415796],"type":"Point"}
}