{
  "type": "Feature",
  "properties": {
    "iso:country":"IN",
    "ks:ks_name":"Sarheta",
    "ks:ks_pop":228,
    "ks:ks_type":"VILLAGE",
    "name:eng_x_preferred":[
        "Sarheta"
    ],
    "wof:name":"Sarheta",
    "wof:placetype":"locality",
    "wof:population":228
},
  "geometry": {"coordinates":[86.745654,24.242254],"type":"Point"}
}