{
  "type": "Feature",
  "properties": {
    "gn:admin1_code":"19.0",
    "gn:admin2_code":"573.0",
    "gn:asciiname":"Mallanathapura",
    "gn:country_code":"IN",
    "gn:dem":707,
    "gn:feature_class":"P",
    "gn:feature_code":"PPL",
    "gn:name":"Mallan\u0101thapura",
    "gn:population":0,
    "gn:timezone":"Asia/Kolkata",
    "iso:country":"IN",
    "ks:ks_name":"Mallinathpura",
    "ks:ks_pop":197,
    "ks:ks_type":"HABITATION",
    "name:eng_x_preferred":[
        "Mallinathpura"
    ],
    "name:eng_x_variant":[
        "Mallanathapura"
    ],
    "wof:name":"Mallinathpura",
    "wof:placetype":"locality",
    "wof:population":197
},
  "geometry": {"coordinates":[76.87479,12.7927],"type":"Point"}
}