{
  "type": "Feature",
  "properties": {
    "iso:country":"IN",
    "ks:ks_name":"Lower Tola",
    "ks:ks_pop":199,
    "ks:ks_type":"HABITATION",
    "name:eng_x_preferred":[
        "Lower Tola"
    ],
    "wof:name":"Lower Tola",
    "wof:placetype":"locality",
    "wof:population":199
},
  "geometry": {"coordinates":[86.446164,24.529079],"type":"Point"}
}