{
  "type": "Feature",
  "properties": {
    "gn:admin1_code":"16.0",
    "gn:admin2_code":"509.0",
    "gn:asciiname":"Tarbhuj",
    "gn:country_code":"IN",
    "gn:dem":214,
    "gn:feature_class":"P",
    "gn:feature_code":"PPL",
    "gn:name":"T\u0101rbh\u016bj",
    "gn:population":0,
    "gn:timezone":"Asia/Kolkata",
    "iso:country":"IN",
    "ks:ks_name":"Tadbhuj",
    "ks:ks_pop":166,
    "ks:ks_type":"VILLAGE",
    "name:eng_x_preferred":[
        "Tadbhuj"
    ],
    "name:eng_x_variant":[
        "Tarbhuj"
    ],
    "wof:name":"Tadbhuj",
    "wof:placetype":"locality",
    "wof:population":166
},
  "geometry": {"coordinates":[79.716469,20.16234],"type":"Point"}
}