{
  "type": "Feature",
  "properties": {
    "iso:country":"IN",
    "ks:ks_name":"Enithadka",
    "ks:ks_pop":330,
    "ks:ks_type":"HABITATION",
    "name:eng_x_preferred":[
        "Enithadka"
    ],
    "wof:name":"Enithadka",
    "wof:placetype":"locality",
    "wof:population":330
},
  "geometry": {"coordinates":[75.322609,12.759462],"type":"Point"}
}