{
  "type": "Feature",
  "properties": {
    "iso:country":"IN",
    "ks:ks_alt_nam":"KAMAKHYAGURI 1 SOUTH",
    "ks:ks_name":"Kamakhyaguri 1 South",
    "ks:ks_pop":242,
    "ks:ks_type":"HABITATION",
    "name:eng_x_preferred":[
        "Kamakhyaguri 1 South"
    ],
    "wof:name":"Kamakhyaguri 1 South",
    "wof:placetype":"locality",
    "wof:population":242
},
  "geometry": {"coordinates":[89.762338,26.470757],"type":"Point"}
}