{
  "type": "Feature",
  "properties": {
    "iso:country":"IN",
    "ks:ks_name":"Kallimar",
    "ks:ks_pop":104,
    "ks:ks_type":"HABITATION",
    "name:eng_x_preferred":[
        "Kallimar"
    ],
    "wof:name":"Kallimar",
    "wof:placetype":"locality",
    "wof:population":104
},
  "geometry": {"coordinates":[74.871224,13.138504],"type":"Point"}
}