{
  "type": "Feature",
  "properties": {
    "iso:country":"IN",
    "ks:ks_name":"Bangarupeta",
    "ks:ks_pop":3798,
    "ks:ks_type":"HABITATION",
    "name:eng_x_preferred":[
        "Bangarupeta"
    ],
    "wof:name":"Bangarupeta",
    "wof:placetype":"locality",
    "wof:population":3798
},
  "geometry": {"coordinates":[79.580862,13.993493],"type":"Point"}
}