{
  "type": "Feature",
  "properties": {
    "iso:country":"IN",
    "ks:ks_name":"Guriguda",
    "ks:ks_pop":385,
    "ks:ks_type":"VILLAGE",
    "name:eng_x_preferred":[
        "Guriguda"
    ],
    "wof:name":"Guriguda",
    "wof:placetype":"locality",
    "wof:population":385
},
  "geometry": {"coordinates":[84.202905,19.394565],"type":"Point"}
}