{
  "type": "Feature",
  "properties": {
    "iso:country":"IN",
    "ks:ks_name":"Mittamalapalle",
    "ks:ks_pop":137,
    "ks:ks_type":"HABITATION",
    "name:eng_x_preferred":[
        "Mittamalapalle"
    ],
    "wof:name":"Mittamalapalle",
    "wof:placetype":"locality",
    "wof:population":137
},
  "geometry": {"coordinates":[78.45337000000001,13.811048],"type":"Point"}
}