{
  "type": "Feature",
  "properties": {
    "gn:admin1_code":"35",
    "gn:admin2_code":"451.0",
    "gn:asciiname":"Achloni",
    "gn:country_code":"IN",
    "gn:dem":378,
    "gn:feature_class":"P",
    "gn:feature_code":"PPL",
    "gn:name":"Achloni",
    "gn:population":0,
    "gn:timezone":"Asia/Kolkata",
    "iso:country":"IN",
    "wof:name":"Achloni",
    "wof:placetype":"locality"
},
  "geometry": {"coordinates":[79.83249000000001,23.31628],"type":"Point"}
}