{
  "type": "Feature",
  "properties": {
    "iso:country":"IN",
    "ks:ks_name":"Bole Naik Thanda",
    "ks:ks_pop":65,
    "ks:ks_type":"HABITATION",
    "name:eng_x_preferred":[
        "Bole Naik Thanda"
    ],
    "wof:name":"Bole Naik Thanda",
    "wof:placetype":"locality",
    "wof:population":65
},
  "geometry": {"coordinates":[78.15372600000001,13.836098],"type":"Point"}
}