{
  "type": "Feature",
  "properties": {
    "iso:country":"IN",
    "ks:ks_alt_nam":"Rabha supa",
    "ks:ks_name":"Rabha Supa",
    "ks:ks_pop":156,
    "ks:ks_type":"HABITATION",
    "name:eng_x_preferred":[
        "Rabha Supa"
    ],
    "wof:name":"Rabha Supa",
    "wof:placetype":"locality",
    "wof:population":156
},
  "geometry": {"coordinates":[91.04773400000001,26.613712],"type":"Point"}
}