{
  "type": "Feature",
  "properties": {
    "iso:country":"IN",
    "ks:ks_name":"Gobindpur",
    "ks:ks_pop":260,
    "ks:ks_type":"VILLAGE",
    "name:eng_x_preferred":[
        "Gobindpur"
    ],
    "wof:name":"Gobindpur",
    "wof:placetype":"locality",
    "wof:population":260
},
  "geometry": {"coordinates":[86.21564100000001,21.062442],"type":"Point"}
}