{
  "type": "Feature",
  "properties": {
    "iso:country":"IN",
    "ks:ks_alt_nam":"MotiMogri",
    "ks:ks_name":"Motimogri",
    "ks:ks_pop":504,
    "ks:ks_type":"HABITATION",
    "name:eng_x_preferred":[
        "Motimogri"
    ],
    "wof:name":"Motimogri",
    "wof:placetype":"locality",
    "wof:population":504
},
  "geometry": {"coordinates":[73.743117,21.606017],"type":"Point"}
}