{
  "type": "Feature",
  "properties": {
    "gn:admin1_code":"36",
    "gn:admin2_code":"188.0",
    "gn:asciiname":"Narotampur",
    "gn:country_code":"IN",
    "gn:dem":77,
    "gn:feature_class":"P",
    "gn:feature_code":"PPL",
    "gn:name":"Narotampur",
    "gn:population":0,
    "gn:timezone":"Asia/Kolkata",
    "iso:country":"IN",
    "ks:ks_name":"Narottampur",
    "ks:ks_pop":64,
    "ks:ks_type":"HABITATION",
    "name:eng_x_preferred":[
        "Narottampur"
    ],
    "name:eng_x_variant":[
        "Narotampur"
    ],
    "wof:name":"Narottampur",
    "wof:placetype":"locality",
    "wof:population":64
},
  "geometry": {"coordinates":[83.375519,26.365303],"type":"Point"}
}