{
  "type": "Feature",
  "properties": {
    "iso:country":"IN",
    "ks:ks_name":"Narayanpur",
    "ks:ks_pop":260,
    "ks:ks_type":"VILLAGE",
    "name:eng_x_preferred":[
        "Narayanpur"
    ],
    "wof:name":"Narayanpur",
    "wof:placetype":"locality",
    "wof:population":260
},
  "geometry": {"coordinates":[83.351241,20.600893],"type":"Point"}
}