{
  "type": "Feature",
  "properties": {
    "iso:country":"IN",
    "ks:ks_name":"Kolim Sarovar",
    "ks:ks_pop":52,
    "ks:ks_type":"VILLAGE",
    "name:eng_x_preferred":[
        "Kolim Sarovar"
    ],
    "wof:name":"Kolim Sarovar",
    "wof:placetype":"locality",
    "wof:population":52
},
  "geometry": {"coordinates":[73.245903,19.682266],"type":"Point"}
}