{
  "type": "Feature",
  "properties": {
    "gn:admin1_code":"9.0",
    "gn:admin2_code":"483.0",
    "gn:asciiname":"Motipura Muwara",
    "gn:country_code":"IN",
    "gn:dem":80,
    "gn:feature_class":"P",
    "gn:feature_code":"PPL",
    "gn:name":"Motipura Muwara",
    "gn:population":0,
    "gn:timezone":"Asia/Kolkata",
    "iso:country":"IN",
    "wof:name":"Motipura Muwara",
    "wof:placetype":"locality"
},
  "geometry": {"coordinates":[73.10434000000002,23.06392],"type":"Point"}
}