{
  "type": "Feature",
  "properties": {
    "gn:admin1_code":"24.0",
    "gn:admin2_code":"123.0",
    "gn:asciiname":"Joj",
    "gn:country_code":"IN",
    "gn:dem":666,
    "gn:feature_class":"P",
    "gn:feature_code":"PPL",
    "gn:name":"Joj",
    "gn:population":0,
    "gn:timezone":"Asia/Kolkata",
    "iso:country":"IN",
    "ks:ks_name":"Joj",
    "ks:ks_pop":748,
    "ks:ks_type":"HABITATION",
    "name:eng_x_preferred":[
        "Joj"
    ],
    "wof:name":"Joj",
    "wof:placetype":"locality",
    "wof:population":748
},
  "geometry": {"coordinates":[73.827472,25.262917],"type":"Point"}
}