{
  "type": "Feature",
  "properties": {
    "gn:admin1_code":"40.0",
    "gn:admin2_code":"535",
    "gn:asciiname":"Kodekal",
    "gn:country_code":"IN",
    "gn:dem":535,
    "gn:feature_class":"P",
    "gn:feature_code":"PPL",
    "gn:name":"Kodekal",
    "gn:population":0,
    "gn:timezone":"Asia/Kolkata",
    "iso:country":"IN",
    "name:ceb_x_preferred":[
        "Kodekal"
    ],
    "name:swe_x_preferred":[
        "Kodekal"
    ],
    "wof:name":"Kodekal",
    "wof:placetype":"locality"
},
  "geometry": {"coordinates":[78.00635,17.80389],"type":"Point"}
}