{
  "type": "Feature",
  "properties": {
    "iso:country":"IN",
    "ks:ks_alt_nam":"LEMBU CHARA WEST",
    "ks:ks_name":"Lembu Chara West",
    "ks:ks_pop":1450,
    "ks:ks_type":"HABITATION",
    "name:eng_x_preferred":[
        "Lembu Chara West"
    ],
    "wof:name":"Lembu Chara West",
    "wof:placetype":"locality",
    "wof:population":1450
},
  "geometry": {"coordinates":[91.35633300000001,23.807181],"type":"Point"}
}