{
  "type": "Feature",
  "properties": {
    "iso:country":"IN",
    "ks:ks_name":"Husenpur",
    "ks:ks_pop":250,
    "ks:ks_type":"VILLAGE",
    "name:eng_x_preferred":[
        "Husenpur"
    ],
    "wof:name":"Husenpur",
    "wof:placetype":"locality",
    "wof:population":250
},
  "geometry": {"coordinates":[86.281633,25.362358],"type":"Point"}
}