{
  "type": "Feature",
  "properties": {
    "iso:country":"IN",
    "ks:ks_name":"Korrha Uparwar",
    "ks:ks_pop":6636,
    "ks:ks_type":"VILLAGE",
    "name:eng_x_preferred":[
        "Korrha Uparwar"
    ],
    "wof:name":"Korrha Uparwar",
    "wof:placetype":"locality",
    "wof:population":6636
},
  "geometry": {"coordinates":[84.559725,25.747448],"type":"Point"}
}