{
  "type": "Feature",
  "properties": {
    "gn:admin1_code":"36.0",
    "gn:admin2_code":"150.0",
    "gn:asciiname":"Jit Nagla",
    "gn:country_code":"IN",
    "gn:dem":156,
    "gn:feature_class":"P",
    "gn:feature_code":"PPL",
    "gn:name":"Jit Nagla",
    "gn:population":0,
    "gn:timezone":"Asia/Kolkata",
    "iso:country":"IN",
    "name:und_x_variant":[
        "Gang\u0101pur"
    ],
    "wof:name":"Jit Nagla",
    "wof:placetype":"locality"
},
  "geometry": {"coordinates":[79.49208,28.04335],"type":"Point"}
}