{
  "type": "Feature",
  "properties": {
    "gn:admin1_code":"39",
    "gn:admin2_code":"61.0",
    "gn:asciiname":"Pata",
    "gn:country_code":"IN",
    "gn:dem":1233,
    "gn:feature_class":"P",
    "gn:feature_code":"PPL",
    "gn:name":"P\u0101ta",
    "gn:population":0,
    "gn:timezone":"Asia/Kolkata",
    "iso:country":"IN",
    "ks:ks_alt_nam":"P\u0101ta",
    "ks:ks_name":"Pata",
    "ks:ks_pop":133,
    "ks:ks_type":"VILLAGE",
    "name:ceb_x_preferred":[
        "Pata"
    ],
    "name:ces_x_preferred":[
        "Pata"
    ],
    "name:eng_x_preferred":[
        "Pata"
    ],
    "name:eng_x_variant":[
        "P\u0101ta"
    ],
    "name:epo_x_preferred":[
        "Pata"
    ],
    "name:fin_x_preferred":[
        "Pata"
    ],
    "name:fra_x_preferred":[
        "Pata"
    ],
    "name:hun_x_preferred":[
        "Pata"
    ],
    "name:ita_x_preferred":[
        "Pata"
    ],
    "name:kor_x_preferred":[
        "\ud30c\ud0c0"
    ],
    "name:por_x_preferred":[
        "Pata"
    ],
    "name:que_x_preferred":[
        "Pata"
    ],
    "name:sco_x_preferred":[
        "Pata"
    ],
    "name:spa_x_preferred":[
        "Pata"
    ],
    "name:swe_x_preferred":[
        "Pata"
    ],
    "name:war_x_preferred":[
        "Pata"
    ],
    "wof:name":"Pata",
    "wof:placetype":"locality",
    "wof:population":133
},
  "geometry": {"coordinates":[78.434802,29.989255],"type":"Point"}
}