{
  "type": "Feature",
  "properties": {
    "iso:country":"IN",
    "ks:ks_alt_nam":"MUSHARI TOLA",
    "ks:ks_name":"Mushari Tola",
    "ks:ks_pop":196,
    "ks:ks_type":"HABITATION",
    "name:eng_x_preferred":[
        "Mushari Tola"
    ],
    "wof:name":"Mushari Tola",
    "wof:placetype":"locality",
    "wof:population":196
},
  "geometry": {"coordinates":[86.89137700000001,26.41441],"type":"Point"}
}