{
  "type": "Feature",
  "properties": {
    "iso:country":"IN",
    "ks:ks_name":"Chawkadapalu",
    "ks:ks_pop":750,
    "ks:ks_type":"HABITATION",
    "name:eng_x_preferred":[
        "Chawkadapalu"
    ],
    "wof:name":"Chawkadapalu",
    "wof:placetype":"locality",
    "wof:population":750
},
  "geometry": {"coordinates":[75.026954,12.821759],"type":"Point"}
}