{
  "type": "Feature",
  "properties": {
    "gn:admin1_code":"36.0",
    "gn:admin2_code":"138.0",
    "gn:asciiname":"Nagla Sahu",
    "gn:country_code":"IN",
    "gn:dem":227,
    "gn:feature_class":"P",
    "gn:feature_code":"PPL",
    "gn:name":"Nagla S\u0101hu",
    "gn:population":0,
    "gn:timezone":"Asia/Kolkata",
    "iso:country":"IN",
    "ks:ks_alt_nam":"Nagla S\u0101hu",
    "ks:ks_name":"Nagla Sahu",
    "ks:ks_pop":5857,
    "ks:ks_type":"VILLAGE",
    "ks:ks_uagg_main":0,
    "name:eng_x_preferred":[
        "Nagla Sahu"
    ],
    "name:eng_x_variant":[
        "Nagla S\u0101hu"
    ],
    "wof:name":"Nagla Sahu",
    "wof:placetype":"neighbourhood",
    "wof:population":5857
},
  "geometry": {"coordinates":[77.846221,28.987567],"type":"Point"}
}