{
  "type": "Feature",
  "properties": {
    "iso:country":"IN",
    "ks:ks_name":"Brahmanwadi",
    "ks:ks_pop":9,
    "ks:ks_type":"HABITATION",
    "name:eng_x_preferred":[
        "Brahmanwadi"
    ],
    "wof:name":"Brahmanwadi",
    "wof:placetype":"locality",
    "wof:population":9
},
  "geometry": {"coordinates":[73.260175,17.256934],"type":"Point"}
}