{
  "type": "Feature",
  "properties": {
    "gn:admin1_code":"19.0",
    "gn:admin2_code":"559.0",
    "gn:asciiname":"Pothnal",
    "gn:country_code":"IN",
    "gn:dem":379,
    "gn:feature_class":"P",
    "gn:feature_code":"PPL",
    "gn:name":"Pothnal",
    "gn:population":0,
    "gn:timezone":"Asia/Kolkata",
    "iso:country":"IN",
    "wof:name":"Pothnal",
    "wof:placetype":"neighbourhood"
},
  "geometry": {"coordinates":[76.89073999999999,15.92493],"type":"Point"}
}