{
  "type": "Feature",
  "properties": {
    "iso:country":"IN",
    "ks:ks_name":"Jagannathpur",
    "ks:ks_pop":294,
    "ks:ks_type":"HABITATION",
    "name:eng_x_preferred":[
        "Jagannathpur"
    ],
    "wof:name":"Jagannathpur",
    "wof:placetype":"locality",
    "wof:population":294
},
  "geometry": {"coordinates":[87.80726300000001,24.532639],"type":"Point"}
}