{
  "type": "Feature",
  "properties": {
    "iso:country":"IN",
    "ks:ks_name":"Ramakrishnapuram",
    "ks:ks_pop":596,
    "ks:ks_type":"HABITATION",
    "ks:ks_uagg_main":0,
    "name:eng_x_preferred":[
        "Ramakrishnapuram"
    ],
    "wof:name":"Ramakrishnapuram",
    "wof:placetype":"neighbourhood",
    "wof:population":596
},
  "geometry": {"coordinates":[78.98045500000001,14.412785],"type":"Point"}
}