{
  "type": "Feature",
  "properties": {
    "gn:admin1_code":"40.0",
    "gn:admin2_code":"541.0",
    "gn:asciiname":"Uppanapalle",
    "gn:country_code":"IN",
    "gn:dem":167,
    "gn:feature_class":"P",
    "gn:feature_code":"PPL",
    "gn:name":"Uppanapalle",
    "gn:population":0,
    "gn:timezone":"Asia/Kolkata",
    "iso:country":"IN",
    "ks:ks_name":"Uppanapalle",
    "ks:ks_type":"VILLAGE",
    "name:eng_x_preferred":[
        "Uppanapalle"
    ],
    "wof:name":"Uppanapalle",
    "wof:placetype":"locality"
},
  "geometry": {"coordinates":[81.22465800000001,17.699077],"type":"Point"}
}