{
  "type": "Feature",
  "properties": {
    "iso:country":"IN",
    "ks:ks_name":"Ramfal",
    "ks:ks_pop":328,
    "ks:ks_type":"HABITATION",
    "ks:ks_uagg_main":0,
    "name:eng_x_preferred":[
        "Ramfal"
    ],
    "wof:name":"Ramfal",
    "wof:placetype":"neighbourhood",
    "wof:population":328
},
  "geometry": {"coordinates":[83.225645,27.160646],"type":"Point"}
}