{
  "type": "Feature",
  "properties": {
    "gn:admin1_code":"19",
    "gn:admin2_code":"557.0",
    "gn:asciiname":"Gornal",
    "gn:country_code":"IN",
    "gn:dem":464,
    "gn:feature_class":"P",
    "gn:feature_code":"PPL",
    "gn:name":"Gornal",
    "gn:population":0,
    "gn:timezone":"Asia/Kolkata",
    "iso:country":"IN",
    "wof:name":"Gornal",
    "wof:placetype":"locality"
},
  "geometry": {"coordinates":[76.00794999999999,17.05486],"type":"Point"}
}