{
  "type": "Feature",
  "properties": {
    "iso:country":"IN",
    "ks:ks_name":"Bhikhi",
    "ks:ks_pop":575,
    "ks:ks_type":"VILLAGE",
    "name:eng_x_preferred":[
        "Bhikhi"
    ],
    "wof:name":"Bhikhi",
    "wof:placetype":"locality",
    "wof:population":575
},
  "geometry": {"coordinates":[85.876217,24.578769],"type":"Point"}
}