{
  "type": "Feature",
  "properties": {
    "iso:country":"IN",
    "ks:ks_alt_nam":"HATKAR PATILVASTI",
    "ks:ks_name":"Hatkar Patilvasti",
    "ks:ks_pop":78,
    "ks:ks_type":"HABITATION",
    "name:eng_x_preferred":[
        "Hatkar Patilvasti"
    ],
    "wof:name":"Hatkar Patilvasti",
    "wof:placetype":"locality",
    "wof:population":78
},
  "geometry": {"coordinates":[75.38495899999999,17.072286],"type":"Point"}
}