{
  "type": "Feature",
  "properties": {
    "iso:country":"IN",
    "ks:ks_name":"Siragamputtu",
    "ks:ks_pop":54,
    "ks:ks_type":"HABITATION",
    "name:eng_x_preferred":[
        "Siragamputtu"
    ],
    "wof:name":"Siragamputtu",
    "wof:placetype":"locality",
    "wof:population":54
},
  "geometry": {"coordinates":[82.384624,18.347008],"type":"Point"}
}