{
  "type": "Feature",
  "properties": {
    "iso:country":"IN",
    "ks:ks_name":"Maheshwar",
    "ks:ks_pop":1132,
    "ks:ks_type":"VILLAGE",
    "ks:ks_uagg_main":0,
    "name:eng_x_preferred":[
        "Maheshwar"
    ],
    "wof:name":"Maheshwar",
    "wof:placetype":"neighbourhood",
    "wof:population":1132
},
  "geometry": {"coordinates":[89.493466,26.037661],"type":"Point"}
}