{
  "type": "Feature",
  "properties": {
    "iso:country":"IN",
    "ks:ks_name":"Bilbarpada",
    "ks:ks_pop":433,
    "ks:ks_type":"HABITATION",
    "name:eng_x_preferred":[
        "Bilbarpada"
    ],
    "wof:name":"Bilbarpada",
    "wof:placetype":"locality",
    "wof:population":433
},
  "geometry": {"coordinates":[74.153842,21.76287],"type":"Point"}
}