{
  "type": "Feature",
  "properties": {
    "gn:admin1_code":"36",
    "gn:admin2_code":"176.0",
    "gn:asciiname":"Pariwan",
    "gn:country_code":"IN",
    "gn:dem":121,
    "gn:feature_class":"P",
    "gn:feature_code":"PPL",
    "gn:name":"Pariw\u0101n",
    "gn:population":0,
    "gn:timezone":"Asia/Kolkata",
    "iso:country":"IN",
    "ks:ks_alt_nam":"Pariw\u0101n",
    "ks:ks_name":"Pariwan",
    "ks:ks_pop":632,
    "ks:ks_type":"VILLAGE",
    "ks:ks_uagg_main":0,
    "name:eng_x_preferred":[
        "Pariwan"
    ],
    "name:eng_x_variant":[
        "Pariw\u0101n"
    ],
    "wof:name":"Pariwan",
    "wof:placetype":"neighbourhood",
    "wof:population":632
},
  "geometry": {"coordinates":[81.18695700000001,26.634752],"type":"Point"}
}