{
  "type": "Feature",
  "properties": {
    "gn:admin1_code":"24.0",
    "gn:admin2_code":"125.0",
    "gn:asciiname":"Wardia",
    "gn:country_code":"IN",
    "gn:dem":190,
    "gn:feature_class":"P",
    "gn:feature_code":"PPL",
    "gn:name":"Wardia",
    "gn:population":0,
    "gn:timezone":"Asia/Kolkata",
    "iso:country":"IN",
    "name:ceb_x_preferred":[
        "Wardia hygrometrica"
    ],
    "name:swe_x_preferred":[
        "Wardia hygrometrica"
    ],
    "name:vie_x_preferred":[
        "Wardia hygrometrica"
    ],
    "wof:name":"Wardia",
    "wof:placetype":"locality"
},
  "geometry": {"coordinates":[74.10534,23.35807],"type":"Point"}
}