{
  "type": "Feature",
  "properties": {
    "gn:admin1_code":"34.0",
    "gn:admin2_code":"214.0",
    "gn:asciiname":"Singhrauli",
    "gn:country_code":"IN",
    "gn:dem":44,
    "gn:feature_class":"P",
    "gn:feature_code":"PPL",
    "gn:name":"Singhrauli",
    "gn:population":0,
    "gn:timezone":"Asia/Kolkata",
    "iso:country":"IN",
    "wof:name":"Singhrauli",
    "wof:placetype":"locality"
},
  "geometry": {"coordinates":[86.51798000000002,25.78659],"type":"Point"}
}