{
  "type": "Feature",
  "properties": {
    "gn:admin1_code":"36.0",
    "gn:admin2_code":"135.0",
    "gn:asciiname":"Bahadurpur Patti",
    "gn:country_code":"IN",
    "gn:dem":219,
    "gn:feature_class":"P",
    "gn:feature_code":"PPL",
    "gn:name":"Bah\u0101durpur Patti",
    "gn:population":0,
    "gn:timezone":"Asia/Kolkata",
    "iso:country":"IN",
    "ks:ks_alt_nam":"Bah\u0101durpur Patti",
    "ks:ks_name":"Bahadurpur Patti",
    "ks:ks_type":"VILLAGE",
    "name:eng_x_preferred":[
        "Bahadurpur Patti"
    ],
    "name:eng_x_variant":[
        "Bah\u0101durpur Patti"
    ],
    "wof:name":"Bahadurpur Patti",
    "wof:placetype":"locality"
},
  "geometry": {"coordinates":[78.947946,29.107765],"type":"Point"}
}