{
  "type": "Feature",
  "properties": {
    "iso:country":"IN",
    "ks:ks_name":"Malaguli",
    "ks:ks_pop":36,
    "ks:ks_type":"HABITATION",
    "name:eng_x_preferred":[
        "Malaguli"
    ],
    "wof:name":"Malaguli",
    "wof:placetype":"locality",
    "wof:population":36
},
  "geometry": {"coordinates":[74.75218599999999,14.328784],"type":"Point"}
}