{
  "type": "Feature",
  "properties": {
    "iso:country":"IN",
    "ks:ks_name":"Mayali Lagga Danda",
    "ks:ks_pop":51,
    "ks:ks_type":"VILLAGE",
    "name:eng_x_preferred":[
        "Mayali Lagga Danda"
    ],
    "wof:name":"Mayali Lagga Danda",
    "wof:placetype":"locality",
    "wof:population":51
},
  "geometry": {"coordinates":[78.63514499999999,30.235834],"type":"Point"}
}