{
  "type": "Feature",
  "properties": {
    "iso:country":"IN",
    "ks:ks_alt_nam":"Eachnal tanda-I",
    "ks:ks_name":"Eachnal Tanda-i",
    "ks:ks_pop":492,
    "ks:ks_type":"HABITATION",
    "name:eng_x_preferred":[
        "Eachnal Tanda-i"
    ],
    "wof:name":"Eachnal Tanda-i",
    "wof:placetype":"locality",
    "wof:population":492
},
  "geometry": {"coordinates":[76.46319699999999,16.169277],"type":"Point"}
}