{
  "type": "Feature",
  "properties": {
    "iso:country":"IN",
    "ks:ks_alt_nam":"BERKALWADI",
    "ks:ks_name":"Berkalwadi",
    "ks:ks_pop":135,
    "ks:ks_type":"HABITATION",
    "name:eng_x_preferred":[
        "Berkalwadi"
    ],
    "wof:name":"Berkalwadi",
    "wof:placetype":"locality",
    "wof:population":135
},
  "geometry": {"coordinates":[74.076781,16.604839],"type":"Point"}
}