{
  "type": "Feature",
  "properties": {
    "iso:country":"IN",
    "ks:ks_name":"Jagheena",
    "ks:ks_pop":10445,
    "ks:ks_type":"VILLAGE",
    "ks:ks_uagg_main":0,
    "name:eng_x_preferred":[
        "Jagheena"
    ],
    "wof:name":"Jagheena",
    "wof:placetype":"locality",
    "wof:population":10445
},
  "geometry": {"coordinates":[77.522564,27.239176],"type":"Point"}
}