{
  "type": "Feature",
  "properties": {
    "iso:country":"IN",
    "ks:ks_name":"Kund",
    "ks:ks_pop":43,
    "ks:ks_type":"VILLAGE",
    "name:eng_x_preferred":[
        "Kund"
    ],
    "wof:name":"Kund",
    "wof:placetype":"locality",
    "wof:population":43
},
  "geometry": {"coordinates":[78.841684,30.065111],"type":"Point"}
}