{
  "type": "Feature",
  "properties": {
    "iso:country":"IN",
    "ks:ks_name":"Shiv Nagari Khajuriyaa Dih",
    "ks:ks_pop":21,
    "ks:ks_type":"HABITATION",
    "name:eng_x_preferred":[
        "Shiv Nagari Khajuriyaa Dih"
    ],
    "wof:name":"Shiv Nagari Khajuriyaa Dih",
    "wof:placetype":"locality",
    "wof:population":21
},
  "geometry": {"coordinates":[84.463543,24.458318],"type":"Point"}
}