{
  "type": "Feature",
  "properties": {
    "iso:country":"IN",
    "ks:ks_name":"Khairhuri",
    "ks:ks_pop":275,
    "ks:ks_type":"VILLAGE",
    "name:eng_x_preferred":[
        "Khairhuri"
    ],
    "wof:name":"Khairhuri",
    "wof:placetype":"locality",
    "wof:population":275
},
  "geometry": {"coordinates":[85.543261,22.677026],"type":"Point"}
}