{
  "type": "Feature",
  "properties": {
    "iso:country":"IN",
    "ks:ks_name":"Kendtanr",
    "ks:ks_pop":729,
    "ks:ks_type":"VILLAGE",
    "name:eng_x_preferred":[
        "Kendtanr"
    ],
    "wof:name":"Kendtanr",
    "wof:placetype":"locality",
    "wof:population":729
},
  "geometry": {"coordinates":[86.755374,23.372628],"type":"Point"}
}