{
  "type": "Feature",
  "properties": {
    "iso:country":"IN",
    "ks:ks_name":"Madalapalli",
    "ks:ks_pop":86,
    "ks:ks_type":"VILLAGE",
    "name:eng_x_preferred":[
        "Madalapalli"
    ],
    "wof:name":"Madalapalli",
    "wof:placetype":"locality",
    "wof:population":86
},
  "geometry": {"coordinates":[84.562567,19.491287],"type":"Point"}
}