{
  "type": "Feature",
  "properties": {
    "gn:admin1_code":"12",
    "gn:admin2_code":"15.0",
    "gn:asciiname":"Lamar",
    "gn:country_code":"IN",
    "gn:dem":1820,
    "gn:feature_class":"P",
    "gn:feature_code":"PPL",
    "gn:name":"L\u0101mar",
    "gn:population":0,
    "gn:timezone":"Asia/Kolkata",
    "iso:country":"IN",
    "name:ben_x_preferred":[
        "\u09b2\u09be\u09ae\u09be\u09b0"
    ],
    "name:bul_x_preferred":[
        "\u041b\u0430\u043c\u0430\u0440"
    ],
    "name:cat_x_preferred":[
        "Lamar"
    ],
    "name:ceb_x_preferred":[
        "Lamar"
    ],
    "name:deu_x_preferred":[
        "Lamar"
    ],
    "name:ell_x_preferred":[
        "\u039b\u03b1\u03bc\u03ac\u03c1"
    ],
    "name:fin_x_preferred":[
        "Lamar"
    ],
    "name:fra_x_preferred":[
        "Lamar"
    ],
    "name:heb_x_preferred":[
        "\u05dc\u05de\u05d0\u05e8"
    ],
    "name:hin_x_preferred":[
        "\u0932\u092e\u093e\u0930"
    ],
    "name:hun_x_preferred":[
        "Lamar"
    ],
    "name:ind_x_preferred":[
        "Lamar"
    ],
    "name:ita_x_preferred":[
        "Lamar"
    ],
    "name:kor_x_preferred":[
        "\ub77c\ub9c8"
    ],
    "name:nld_x_preferred":[
        "Lamar"
    ],
    "name:pol_x_preferred":[
        "Lamar"
    ],
    "name:por_x_preferred":[
        "Lamar"
    ],
    "name:rus_x_preferred":[
        "\u041b\u0430\u043c\u0430\u0440"
    ],
    "name:srp_x_preferred":[
        "\u041b\u0430\u043c\u0430\u0440"
    ],
    "name:swe_x_preferred":[
        "Lamar"
    ],
    "name:ukr_x_preferred":[
        "\u041b\u0430\u043c\u0430\u0440"
    ],
    "name:vol_x_preferred":[
        "Lamar"
    ],
    "wof:name":"Lamar",
    "wof:placetype":"locality"
},
  "geometry": {"coordinates":[75.08224,33.58845],"type":"Point"}
}