{
  "type": "Feature",
  "properties": {
    "gn:admin1_code":"34.0",
    "gn:admin2_code":"218.0",
    "gn:asciiname":"Bishunpur Mahuari",
    "gn:country_code":"IN",
    "gn:dem":65,
    "gn:feature_class":"P",
    "gn:feature_code":"PPL",
    "gn:name":"Bishunpur Mahuari",
    "gn:population":0,
    "gn:timezone":"Asia/Kolkata",
    "iso:country":"IN",
    "ks:ks_name":"Bishunpur Mahuari",
    "ks:ks_pop":4060,
    "ks:ks_type":"VILLAGE",
    "ks:ks_uagg_main":0,
    "name:eng_x_preferred":[
        "Bishunpur Mahuari"
    ],
    "wof:name":"Bishunpur Mahuari",
    "wof:placetype":"neighbourhood",
    "wof:population":4060
},
  "geometry": {"coordinates":[84.537344,26.121982],"type":"Point"}
}