{
  "type": "Feature",
  "properties": {
    "iso:country":"IN",
    "ks:ks_name":"Rawar Para",
    "ks:ks_pop":158,
    "ks:ks_type":"HABITATION",
    "name:eng_x_preferred":[
        "Rawar Para"
    ],
    "wof:name":"Rawar Para",
    "wof:placetype":"locality",
    "wof:population":158
},
  "geometry": {"coordinates":[81.85454799999999,19.292702],"type":"Point"}
}