{
  "type": "Feature",
  "properties": {
    "gn:admin1_code":"37",
    "gn:admin2_code":"404.0",
    "gn:asciiname":"Ramakachhar",
    "gn:country_code":"IN",
    "gn:dem":743,
    "gn:feature_class":"P",
    "gn:feature_code":"PPL",
    "gn:name":"R\u0101m\u0101kachh\u0101r",
    "gn:population":0,
    "gn:timezone":"Asia/Kolkata",
    "iso:country":"IN",
    "ks:ks_alt_nam":"R\u0101m\u0101kachh\u0101r",
    "ks:ks_name":"Ramakachhar",
    "ks:ks_pop":414,
    "ks:ks_type":"VILLAGE",
    "name:eng_x_preferred":[
        "Ramakachhar"
    ],
    "name:eng_x_variant":[
        "R\u0101m\u0101kachh\u0101r"
    ],
    "wof:name":"Ramakachhar",
    "wof:placetype":"locality",
    "wof:population":414
},
  "geometry": {"coordinates":[82.2927,22.606651],"type":"Point"}
}