{
  "type": "Feature",
  "properties": {
    "gn:admin1_code":"2.0",
    "gn:admin2_code":"543.0",
    "gn:asciiname":"Gandra",
    "gn:country_code":"IN",
    "gn:dem":251,
    "gn:feature_class":"P",
    "gn:feature_code":"PPL",
    "gn:name":"Gandra",
    "gn:population":0,
    "gn:timezone":"Asia/Kolkata",
    "iso:country":"IN",
    "ks:ks_name":"Gandra",
    "ks:ks_pop":126,
    "ks:ks_type":"HABITATION",
    "name:ceb_x_preferred":[
        "Gandra"
    ],
    "name:deu_x_preferred":[
        "Gandra"
    ],
    "name:eng_x_preferred":[
        "Gandra"
    ],
    "name:fra_x_preferred":[
        "Gandra"
    ],
    "name:nld_x_preferred":[
        "Gandra"
    ],
    "name:por_x_preferred":[
        "Gandra"
    ],
    "name:rus_x_preferred":[
        "\u0413\u0430\u043d\u0434\u0440\u0430"
    ],
    "name:spa_x_preferred":[
        "Gandra"
    ],
    "name:tur_x_preferred":[
        "Gandra"
    ],
    "name:ukr_x_preferred":[
        "\u0413\u0430\u043d\u0434\u0440\u0430"
    ],
    "wof:name":"Gandra",
    "wof:placetype":"locality",
    "wof:population":126
},
  "geometry": {"coordinates":[83.576972,18.959195],"type":"Point"}
}