{
  "type": "Feature",
  "properties": {
    "iso:country":"IN",
    "ks:ks_name":"Nayakapu Gudem",
    "ks:ks_pop":166,
    "ks:ks_type":"HABITATION",
    "name:eng_x_preferred":[
        "Nayakapu Gudem"
    ],
    "wof:name":"Nayakapu Gudem",
    "wof:placetype":"locality",
    "wof:population":166
},
  "geometry": {"coordinates":[78.868083,19.008557],"type":"Point"}
}