{
  "type": "Feature",
  "properties": {
    "iso:country":"IN",
    "ks:ks_name":"Charghara",
    "ks:ks_pop":32,
    "ks:ks_type":"VILLAGE",
    "name:eng_x_preferred":[
        "Charghara"
    ],
    "wof:name":"Charghara",
    "wof:placetype":"locality",
    "wof:population":32
},
  "geometry": {"coordinates":[87.08639700000001,24.423528],"type":"Point"}
}