{
  "type": "Feature",
  "properties": {
    "iso:country":"IN",
    "ks:ks_name":"Mataha",
    "ks:ks_pop":20,
    "ks:ks_type":"HABITATION",
    "name:eng_x_preferred":[
        "Mataha"
    ],
    "wof:name":"Mataha",
    "wof:placetype":"locality",
    "wof:population":20
},
  "geometry": {"coordinates":[81.243982,24.303696],"type":"Point"}
}