{
  "type": "Feature",
  "properties": {
    "gn:admin1_code":"36.0",
    "gn:admin2_code":"143.0",
    "gn:asciiname":"Morahni",
    "gn:country_code":"IN",
    "gn:dem":195,
    "gn:feature_class":"P",
    "gn:feature_code":"PPL",
    "gn:name":"Morahni",
    "gn:population":0,
    "gn:timezone":"Asia/Kolkata",
    "iso:country":"IN",
    "wof:name":"Morahni",
    "wof:placetype":"neighbourhood"
},
  "geometry": {"coordinates":[77.99191,27.75541],"type":"Point"}
}