{
  "type": "Feature",
  "properties": {
    "iso:country":"IN",
    "ks:ks_name":"Awaspara",
    "ks:ks_pop":167,
    "ks:ks_type":"HABITATION",
    "name:eng_x_preferred":[
        "Awaspara"
    ],
    "wof:name":"Awaspara",
    "wof:placetype":"locality",
    "wof:population":167
},
  "geometry": {"coordinates":[81.167092,18.860954],"type":"Point"}
}