{
  "type": "Feature",
  "properties": {
    "gn:admin1_code":"19.0",
    "gn:admin2_code":"572.0",
    "gn:asciiname":"Vishvanat Nagenhalli",
    "gn:country_code":"IN",
    "gn:dem":898,
    "gn:feature_class":"P",
    "gn:feature_code":"PPL",
    "gn:name":"Vishvan\u0101t N\u0101genhalli",
    "gn:population":0,
    "gn:timezone":"Asia/Kolkata",
    "iso:country":"IN",
    "wof:name":"Vishvanat Nagenhalli",
    "wof:placetype":"locality"
},
  "geometry": {"coordinates":[77.604,13.03897],"type":"Point"}
}