{
  "type": "Feature",
  "properties": {
    "iso:country":"IN",
    "ks:ks_name":"Lodhanpurwa",
    "ks:ks_pop":245,
    "ks:ks_type":"HABITATION",
    "name:eng_x_preferred":[
        "Lodhanpurwa"
    ],
    "wof:name":"Lodhanpurwa",
    "wof:placetype":"locality",
    "wof:population":245
},
  "geometry": {"coordinates":[80.973102,27.935724],"type":"Point"}
}