{
  "type": "Feature",
  "properties": {
    "iso:country":"IN",
    "ks:ks_name":"Banti Pathak Tola W",
    "ks:ks_pop":222,
    "ks:ks_type":"HABITATION",
    "name:eng_x_preferred":[
        "Banti Pathak Tola W"
    ],
    "wof:name":"Banti Pathak Tola W",
    "wof:placetype":"locality",
    "wof:population":222
},
  "geometry": {"coordinates":[84.29943299999999,26.53638],"type":"Point"}
}