{
  "type": "Feature",
  "properties": {
    "gn:admin1_code":"34.0",
    "gn:admin2_code":"217.0",
    "gn:asciiname":"Chauraon",
    "gn:country_code":"IN",
    "gn:dem":76,
    "gn:feature_class":"P",
    "gn:feature_code":"PPL",
    "gn:name":"Chaur\u0101on",
    "gn:population":0,
    "gn:timezone":"Asia/Kolkata",
    "iso:country":"IN",
    "ks:ks_name":"Chauranw",
    "ks:ks_pop":1181,
    "ks:ks_type":"VILLAGE",
    "name:eng_x_preferred":[
        "Chauranw"
    ],
    "name:eng_x_variant":[
        "Chauraon"
    ],
    "wof:name":"Chauranw",
    "wof:placetype":"locality",
    "wof:population":1181
},
  "geometry": {"coordinates":[84.335348,26.530758],"type":"Point"}
}