{
  "type": "Feature",
  "properties": {
    "iso:country":"IN",
    "ks:ks_name":"Gudhana Mal",
    "ks:ks_pop":697,
    "ks:ks_type":"HABITATION",
    "name:eng_x_preferred":[
        "Gudhana Mal"
    ],
    "wof:name":"Gudhana Mal",
    "wof:placetype":"locality",
    "wof:population":697
},
  "geometry": {"coordinates":[79.596058,22.42794],"type":"Point"}
}