{
  "type": "Feature",
  "properties": {
    "gn:admin1_code":"34.0",
    "gn:admin2_code":"238",
    "gn:asciiname":"Karangarh",
    "gn:country_code":"IN",
    "gn:dem":308,
    "gn:feature_class":"P",
    "gn:feature_code":"PPL",
    "gn:name":"Karangarh",
    "gn:population":0,
    "gn:timezone":"Asia/Kolkata",
    "iso:country":"IN",
    "wof:name":"Karangarh",
    "wof:placetype":"locality"
},
  "geometry": {"coordinates":[86.47059,24.59886],"type":"Point"}
}