{
  "type": "Feature",
  "properties": {
    "gn:admin1_code":"34.0",
    "gn:admin2_code":"238",
    "gn:asciiname":"Karangarh",
    "gn:country_code":"IN",
    "gn:dem":308,
    "gn:feature_class":"P",
    "gn:feature_code":"PPL",
    "gn:name":"Karangarh",
    "gn:population":0,
    "gn:timezone":"Asia/Kolkata",
    "iso:country":"IN",
    "ks:ks_alt_nam":"karangah",
    "ks:ks_name":"Karangah",
    "ks:ks_pop":100,
    "ks:ks_type":"HABITATION",
    "name:eng_x_preferred":[
        "Karangah"
    ],
    "name:eng_x_variant":[
        "Karangarh"
    ],
    "wof:name":"Karangah",
    "wof:placetype":"locality",
    "wof:population":100
},
  "geometry": {"coordinates":[86.472065,24.614948],"type":"Point"}
}