{
  "type": "Feature",
  "properties": {
    "iso:country":"IN",
    "ks:ks_name":"Pantha",
    "ks:ks_pop":535,
    "ks:ks_type":"HABITATION",
    "name:eng_x_preferred":[
        "Pantha"
    ],
    "wof:name":"Pantha",
    "wof:placetype":"locality",
    "wof:population":535
},
  "geometry": {"coordinates":[75.014411,22.529268],"type":"Point"}
}