{
  "type": "Feature",
  "properties": {
    "iso:country":"IN",
    "ks:ks_name":"Dahivali Kond",
    "ks:ks_pop":1195,
    "ks:ks_type":"VILLAGE",
    "ks:ks_uagg_main":0,
    "name:eng_x_preferred":[
        "Dahivali Kond"
    ],
    "wof:name":"Dahivali Kond",
    "wof:placetype":"neighbourhood",
    "wof:population":1195
},
  "geometry": {"coordinates":[73.265263,18.194271],"type":"Point"}
}