{
  "type": "Feature",
  "properties": {
    "gn:admin1_code":"19.0",
    "gn:admin2_code":"557",
    "gn:asciiname":"Kakhandiki",
    "gn:country_code":"IN",
    "gn:dem":592,
    "gn:feature_class":"P",
    "gn:feature_code":"PPL",
    "gn:name":"K\u0101khandiki",
    "gn:population":0,
    "gn:timezone":"Asia/Kolkata",
    "iso:country":"IN",
    "name:und_x_variant":[
        "Kakhandi",
        "K\u0101khandiki"
    ],
    "wof:name":"Kakhandiki",
    "wof:placetype":"locality"
},
  "geometry": {"coordinates":[75.64053,16.60035],"type":"Point"}
}