{
  "type": "Feature",
  "properties": {
    "gn:admin1_code":"39.0",
    "gn:admin2_code":"64.0",
    "gn:asciiname":"Khauri",
    "gn:country_code":"IN",
    "gn:dem":1448,
    "gn:feature_class":"P",
    "gn:feature_code":"PPL",
    "gn:name":"Khauri",
    "gn:population":0,
    "gn:timezone":"Asia/Kolkata",
    "iso:country":"IN",
    "ks:ks_name":"Khauri",
    "ks:ks_type":"VILLAGE",
    "name:eng_x_preferred":[
        "Khauri"
    ],
    "wof:name":"Khauri",
    "wof:placetype":"locality"
},
  "geometry": {"coordinates":[79.54901,29.667017],"type":"Point"}
}