{
  "type": "Feature",
  "properties": {
    "iso:country":"IN",
    "ks:ks_name":"Jayatapur",
    "ks:ks_pop":0,
    "ks:ks_type":"VILLAGE",
    "name:eng_x_preferred":[
        "Jayatapur"
    ],
    "wof:name":"Jayatapur",
    "wof:placetype":"locality",
    "wof:population":0
},
  "geometry": {"coordinates":[78.030248,21.197116],"type":"Point"}
}