{
  "type": "Feature",
  "properties": {
    "gn:admin1_code":"25.0",
    "gn:admin2_code":"611.0",
    "gn:asciiname":"Toraihatti",
    "gn:country_code":"IN",
    "gn:dem":1771,
    "gn:feature_class":"P",
    "gn:feature_code":"PPL",
    "gn:name":"Toraihatti",
    "gn:population":0,
    "gn:timezone":"Asia/Kolkata",
    "iso:country":"IN",
    "wof:name":"Toraihatti",
    "wof:placetype":"locality"
},
  "geometry": {"coordinates":[76.75119000000002,11.47215],"type":"Point"}
}