{
  "type": "Feature",
  "properties": {
    "iso:country":"IN",
    "ks:ks_name":"Shikarpur",
    "ks:ks_pop":1938,
    "ks:ks_type":"VILLAGE",
    "ks:ks_uagg_main":0,
    "name:eng_x_preferred":[
        "Shikarpur"
    ],
    "wof:name":"Shikarpur",
    "wof:placetype":"neighbourhood",
    "wof:population":1938
},
  "geometry": {"coordinates":[89.642555,26.300679],"type":"Point"}
}