{
  "type": "Feature",
  "properties": {
    "gn:admin1_code":"36",
    "gn:admin2_code":"202.0",
    "gn:asciiname":"Khilaura",
    "gn:country_code":"IN",
    "gn:dem":158,
    "gn:feature_class":"P",
    "gn:feature_code":"PPL",
    "gn:name":"Khilaura",
    "gn:population":0,
    "gn:timezone":"Asia/Kolkata",
    "iso:country":"IN",
    "ks:ks_name":"Khalaura",
    "ks:ks_pop":253,
    "ks:ks_type":"VILLAGE",
    "name:eng_x_preferred":[
        "Khalaura"
    ],
    "name:eng_x_variant":[
        "Khilaura"
    ],
    "wof:name":"Khalaura",
    "wof:placetype":"locality",
    "wof:population":253
},
  "geometry": {"coordinates":[79.04951,27.697212],"type":"Point"}
}