{
  "type": "Feature",
  "properties": {
    "iso:country":"IN",
    "ks:ks_name":"Masauli Dihara",
    "ks:ks_pop":200,
    "ks:ks_type":"HABITATION",
    "ks:ks_uagg_main":0,
    "name:eng_x_preferred":[
        "Masauli Dihara"
    ],
    "wof:name":"Masauli Dihara",
    "wof:placetype":"neighbourhood",
    "wof:population":200
},
  "geometry": {"coordinates":[82.622865,26.272509],"type":"Point"}
}