{
  "type": "Feature",
  "properties": {
    "gn:admin1_code":"36",
    "gn:admin2_code":"186.0",
    "gn:asciiname":"Kari Khuntwa",
    "gn:country_code":"IN",
    "gn:dem":87,
    "gn:feature_class":"P",
    "gn:feature_code":"PPL",
    "gn:name":"K\u0101ri Khuntwa",
    "gn:population":0,
    "gn:timezone":"Asia/Kolkata",
    "iso:country":"IN",
    "ks:ks_alt_nam":"K\u0101ri Khuntwa",
    "ks:ks_name":"Kari Khuntwa",
    "ks:ks_type":"VILLAGE",
    "ks:ks_uagg_main":0,
    "name:eng_x_preferred":[
        "Kari Khuntwa"
    ],
    "name:eng_x_variant":[
        "K\u0101ri Khuntwa"
    ],
    "wof:name":"Kari Khuntwa",
    "wof:placetype":"neighbourhood"
},
  "geometry": {"coordinates":[83.053811,26.918107],"type":"Point"}
}