{
  "type": "Feature",
  "properties": {
    "iso:country":"IN",
    "ks:ks_alt_nam":"sankateshwar",
    "ks:ks_name":"Sankateshwar",
    "ks:ks_pop":320,
    "ks:ks_type":"HABITATION",
    "name:eng_x_preferred":[
        "Sankateshwar"
    ],
    "wof:name":"Sankateshwar",
    "wof:placetype":"locality",
    "wof:population":320
},
  "geometry": {"coordinates":[74.887142,19.641534],"type":"Point"}
}