{
  "type": "Feature",
  "properties": {
    "iso:country":"IN",
    "ks:ks_name":"Agari",
    "ks:ks_pop":1649,
    "ks:ks_type":"HABITATION",
    "name:eng_x_preferred":[
        "Agari"
    ],
    "wof:name":"Agari",
    "wof:placetype":"locality",
    "wof:population":1649
},
  "geometry": {"coordinates":[77.809641,28.315368],"type":"Point"}
}