{
  "type": "Feature",
  "properties": {
    "gn:admin1_code":"38.0",
    "gn:admin2_code":"352.0",
    "gn:asciiname":"Sidhari",
    "gn:country_code":"IN",
    "gn:dem":221,
    "gn:feature_class":"P",
    "gn:feature_code":"PPL",
    "gn:name":"Sidh\u0101ri",
    "gn:population":0,
    "gn:timezone":"Asia/Kolkata",
    "iso:country":"IN",
    "ks:ks_alt_nam":"Sidh\u0101ri",
    "ks:ks_name":"Sidhari",
    "ks:ks_pop":13,
    "ks:ks_type":"VILLAGE",
    "name:eng_x_preferred":[
        "Sidhari"
    ],
    "name:eng_x_variant":[
        "Sidh\u0101ri"
    ],
    "wof:name":"Sidhari",
    "wof:placetype":"locality",
    "wof:population":13
},
  "geometry": {"coordinates":[87.625068,25.174283],"type":"Point"}
}