{
  "type": "Feature",
  "properties": {
    "gn:admin1_code":"39.0",
    "gn:admin2_code":"66.0",
    "gn:asciiname":"Maitoligaon",
    "gn:country_code":"IN",
    "gn:dem":1876,
    "gn:feature_class":"P",
    "gn:feature_code":"PPL",
    "gn:name":"Maitoligaon",
    "gn:population":0,
    "gn:timezone":"Asia/Kolkata",
    "iso:country":"IN",
    "wof:name":"Maitoligaon",
    "wof:placetype":"neighbourhood"
},
  "geometry": {"coordinates":[79.71531,29.41531],"type":"Point"}
}