{
  "type": "Feature",
  "properties": {
    "iso:country":"IN",
    "ks:ks_name":"Bhambhoo Ka Bas",
    "ks:ks_pop":175,
    "ks:ks_type":"HABITATION",
    "name:eng_x_preferred":[
        "Bhambhoo Ka Bas"
    ],
    "wof:name":"Bhambhoo Ka Bas",
    "wof:placetype":"locality",
    "wof:population":175
},
  "geometry": {"coordinates":[75.17316700000001,28.229639],"type":"Point"}
}