{
  "type": "Feature",
  "properties": {
    "iso:country":"IN",
    "ks:ks_alt_nam":"Kaneer thota",
    "ks:ks_name":"Kaneer Thota",
    "ks:ks_pop":1018,
    "ks:ks_type":"HABITATION",
    "ks:ks_uagg_main":0,
    "name:eng_x_preferred":[
        "Kaneer Thota"
    ],
    "wof:name":"Kaneer Thota",
    "wof:placetype":"neighbourhood",
    "wof:population":1018
},
  "geometry": {"coordinates":[74.86642999999999,12.799933],"type":"Point"}
}