{
  "type": "Feature",
  "properties": {
    "gn:admin1_code":"36",
    "gn:admin2_code":"194.0",
    "gn:asciiname":"Mai Dih",
    "gn:country_code":"IN",
    "gn:dem":93,
    "gn:feature_class":"P",
    "gn:feature_code":"PPL",
    "gn:name":"Mai D\u012bh",
    "gn:population":0,
    "gn:timezone":"Asia/Kolkata",
    "iso:country":"IN",
    "wof:name":"Mai Dih",
    "wof:placetype":"neighbourhood"
},
  "geometry": {"coordinates":[82.58762,25.62358],"type":"Point"}
}