{
  "type": "Feature",
  "properties": {
    "gn:admin1_code":"16.0",
    "gn:admin2_code":"514.0",
    "gn:asciiname":"Hatdi",
    "gn:country_code":"IN",
    "gn:dem":480,
    "gn:feature_class":"P",
    "gn:feature_code":"PPL",
    "gn:name":"H\u0101tdi",
    "gn:population":0,
    "gn:timezone":"Asia/Kolkata",
    "iso:country":"IN",
    "wof:name":"Hatdi",
    "wof:placetype":"locality"
},
  "geometry": {"coordinates":[76.15313,19.50787],"type":"Point"}
}