{
  "type": "Feature",
  "properties": {
    "gn:admin1_code":"39",
    "gn:admin2_code":"61.0",
    "gn:asciiname":"Nandpur",
    "gn:country_code":"IN",
    "gn:dem":437,
    "gn:feature_class":"P",
    "gn:feature_code":"PPL",
    "gn:name":"Nandpur",
    "gn:population":0,
    "gn:timezone":"Asia/Kolkata",
    "iso:country":"IN",
    "ks:ks_name":"Nandpur",
    "ks:ks_pop":1310,
    "ks:ks_type":"VILLAGE",
    "ks:ks_uagg_main":0,
    "name:eng_x_preferred":[
        "Nandpur"
    ],
    "wof:name":"Nandpur",
    "wof:placetype":"locality",
    "wof:population":1310
},
  "geometry": {"coordinates":[78.46160399999999,29.76715],"type":"Point"}
}