{
  "type": "Feature",
  "properties": {
    "iso:country":"IN",
    "ks:ks_alt_nam":"Brahman tola",
    "ks:ks_name":"Brahman Tola",
    "ks:ks_pop":2388,
    "ks:ks_type":"HABITATION",
    "name:eng_x_preferred":[
        "Brahman Tola"
    ],
    "wof:name":"Brahman Tola",
    "wof:placetype":"locality",
    "wof:population":2388
},
  "geometry": {"coordinates":[87.412448,26.292997],"type":"Point"}
}