{
  "type": "Feature",
  "properties": {
    "iso:country":"IN",
    "ks:ks_name":"Pahariapada",
    "ks:ks_pop":58,
    "ks:ks_type":"HABITATION",
    "name:eng_x_preferred":[
        "Pahariapada"
    ],
    "wof:name":"Pahariapada",
    "wof:placetype":"locality",
    "wof:population":58
},
  "geometry": {"coordinates":[82.39143300000001,20.141525],"type":"Point"}
}