{
  "type": "Feature",
  "properties": {
    "iso:country":"IN",
    "ks:ks_name":"Dhurwapara",
    "ks:ks_pop":677,
    "ks:ks_type":"HABITATION",
    "name:eng_x_preferred":[
        "Dhurwapara"
    ],
    "wof:name":"Dhurwapara",
    "wof:placetype":"locality",
    "wof:population":677
},
  "geometry": {"coordinates":[81.679253,19.074579],"type":"Point"}
}