{
  "type": "Feature",
  "properties": {
    "iso:country":"IN",
    "ks:ks_name":"Paharpur",
    "ks:ks_pop":283,
    "ks:ks_type":"VILLAGE",
    "ks:ks_uagg_main":0,
    "name:eng_x_preferred":[
        "Paharpur"
    ],
    "wof:name":"Paharpur",
    "wof:placetype":"locality",
    "wof:population":283
},
  "geometry": {"coordinates":[86.613443,24.291124],"type":"Point"}
}