{
  "type": "Feature",
  "properties": {
    "gn:admin1_code":"36",
    "gn:admin2_code":"200.0",
    "gn:asciiname":"Dharan",
    "gn:country_code":"IN",
    "gn:dem":525,
    "gn:feature_class":"P",
    "gn:feature_code":"PPL",
    "gn:name":"Dhar\u0101n",
    "gn:population":0,
    "gn:timezone":"Asia/Kolkata",
    "iso:country":"IN",
    "name:bih_x_preferred":[
        "\u0927\u0930\u093e\u0928"
    ],
    "name:ceb_x_preferred":[
        "Dhar\u0101n B\u0101z\u0101r"
    ],
    "name:dan_x_preferred":[
        "Dharan"
    ],
    "name:deu_x_preferred":[
        "Dharan"
    ],
    "name:dty_x_preferred":[
        "\u0927\u0930\u093e\u0928"
    ],
    "name:epo_x_preferred":[
        "Dharan"
    ],
    "name:eus_x_preferred":[
        "Dharan"
    ],
    "name:fin_x_preferred":[
        "Dharan"
    ],
    "name:fra_x_preferred":[
        "Dharan"
    ],
    "name:heb_x_preferred":[
        "\u05d3\u05d4\u05d0\u05e8\u05d0\u05df"
    ],
    "name:hin_x_preferred":[
        "\u0927\u0930\u093e\u0928"
    ],
    "name:ita_x_preferred":[
        "Dharan"
    ],
    "name:jpn_x_preferred":[
        "\u30c0\u30fc\u30e9\u30f3"
    ],
    "name:kor_x_preferred":[
        "\ub2e4\ub780"
    ],
    "name:lit_x_preferred":[
        "Dharanas"
    ],
    "name:mai_x_preferred":[
        "\u0927\u0930\u093e\u0928 \u0909\u092a\u092e\u0939\u093e\u0928\u0917\u0930\u092a\u093e\u0932\u093f\u0915\u093e"
    ],
    "name:msa_x_preferred":[
        "Dharan"
    ],
    "name:nep_x_preferred":[
        "\u0927\u0930\u093e\u0928 \u0909\u092a\u092e\u0939\u093e\u0928\u0917\u0930\u092a\u093e\u0932\u093f\u0915\u093e"
    ],
    "name:new_x_preferred":[
        "\u0927\u0930\u093e\u0928"
    ],
    "name:nor_x_preferred":[
        "Dharan"
    ],
    "name:pol_x_preferred":[
        "Dharan"
    ],
    "name:rus_x_preferred":[
        "\u0414\u0445\u0430\u0440\u0430\u043d"
    ],
    "name:spa_x_preferred":[
        "Dharan"
    ],
    "name:urd_x_preferred":[
        "\u062f\u06be\u0627\u0631\u0646"
    ],
    "wof:name":"Dharan",
    "wof:placetype":"locality"
},
  "geometry": {"coordinates":[83.20517,24.54925],"type":"Point"}
}