{
  "type": "Feature",
  "properties": {
    "gn:admin1_code":"36",
    "gn:admin2_code":"146.0",
    "gn:asciiname":"Basai Gujar",
    "gn:country_code":"IN",
    "gn:dem":155,
    "gn:feature_class":"P",
    "gn:feature_code":"PPL",
    "gn:name":"Basai G\u016bjar",
    "gn:population":0,
    "gn:timezone":"Asia/Kolkata",
    "iso:country":"IN",
    "ks:ks_name":"Basai Gujar",
    "ks:ks_pop":231,
    "ks:ks_type":"VILLAGE",
    "name:eng_x_preferred":[
        "Basai Gujar"
    ],
    "wof:name":"Basai Gujar",
    "wof:placetype":"locality",
    "wof:population":231
},
  "geometry": {"coordinates":[78.291673,26.934336],"type":"Point"}
}