{
  "type": "Feature",
  "properties": {
    "iso:country":"IN",
    "ks:ks_name":"Matiyala",
    "ks:ks_pop":171,
    "ks:ks_type":"VILLAGE",
    "name:eng_x_preferred":[
        "Matiyala"
    ],
    "wof:name":"Matiyala",
    "wof:placetype":"locality",
    "wof:population":171
},
  "geometry": {"coordinates":[79.28689,30.175211],"type":"Point"}
}