{
  "type": "Feature",
  "properties": {
    "iso:country":"IN",
    "ks:ks_name":"Sukhwasi",
    "ks:ks_pop":1508,
    "ks:ks_type":"VILLAGE",
    "name:eng_x_preferred":[
        "Sukhwasi"
    ],
    "wof:name":"Sukhwasi",
    "wof:placetype":"locality",
    "wof:population":1508
},
  "geometry": {"coordinates":[73.54468900000001,27.216617],"type":"Point"}
}