{
  "type": "Feature",
  "properties": {
    "iso:country":"IN",
    "ks:ks_name":"Kushgram",
    "ks:ks_pop":975,
    "ks:ks_type":"VILLAGE",
    "ks:ks_uagg_main":0,
    "name:eng_x_preferred":[
        "Kushgram"
    ],
    "wof:name":"Kushgram",
    "wof:placetype":"locality",
    "wof:population":975
},
  "geometry": {"coordinates":[88.25511400000001,25.528034],"type":"Point"}
}