{
  "type": "Feature",
  "properties": {
    "iso:country":"IN",
    "ks:ks_name":"Naiduguda",
    "ks:ks_pop":40,
    "ks:ks_type":"HABITATION",
    "name:eng_x_preferred":[
        "Naiduguda"
    ],
    "wof:name":"Naiduguda",
    "wof:placetype":"locality",
    "wof:population":40
},
  "geometry": {"coordinates":[84.01473799999999,18.790397],"type":"Point"}
}