{
  "type": "Feature",
  "properties": {
    "iso:country":"IN",
    "ks:ks_name":"Dinbhuni Chak",
    "ks:ks_pop":423,
    "ks:ks_type":"VILLAGE",
    "ks:ks_uagg_main":0,
    "name:eng_x_preferred":[
        "Dinbhuni Chak"
    ],
    "wof:name":"Dinbhuni Chak",
    "wof:placetype":"neighbourhood",
    "wof:population":423
},
  "geometry": {"coordinates":[87.937051,22.074565],"type":"Point"}
}