{
  "type": "Feature",
  "properties": {
    "iso:country":"IN",
    "ks:ks_name":"Gatkal Wasti",
    "ks:ks_pop":292,
    "ks:ks_type":"HABITATION",
    "name:eng_x_preferred":[
        "Gatkal Wasti"
    ],
    "wof:name":"Gatkal Wasti",
    "wof:placetype":"locality",
    "wof:population":292
},
  "geometry": {"coordinates":[75.48199200000001,18.567465],"type":"Point"}
}