{
  "type": "Feature",
  "properties": {
    "gn:admin1_code":"16",
    "gn:admin2_code":"503.0",
    "gn:asciiname":"Patur",
    "gn:country_code":"IN",
    "gn:dem":344,
    "gn:feature_class":"P",
    "gn:feature_code":"PPL",
    "gn:name":"P\u0101t\u016br",
    "gn:population":0,
    "gn:timezone":"Asia/Kolkata",
    "iso:country":"IN",
    "name:ben_x_preferred":[
        "\u09aa\u09be\u09a4\u09c1\u09b0"
    ],
    "name:bpy_x_preferred":[
        "\u09aa\u09be\u09a4\u09c1\u09b0"
    ],
    "name:ceb_x_preferred":[
        "P\u0101t\u016br"
    ],
    "name:hif_x_preferred":[
        "Patur"
    ],
    "name:ita_x_preferred":[
        "Patur"
    ],
    "name:mar_x_preferred":[
        "\u092a\u093e\u0924\u0942\u0930"
    ],
    "name:msa_x_preferred":[
        "Patur"
    ],
    "name:nld_x_preferred":[
        "Patur"
    ],
    "name:ori_x_preferred":[
        "\u0b2a\u0b3e\u0b24\u0b41\u0b30"
    ],
    "name:por_x_preferred":[
        "Patur"
    ],
    "name:swe_x_preferred":[
        "P\u0101t\u016br"
    ],
    "name:urd_x_preferred":[
        "\u067e\u0627\u062a\u0648\u0691"
    ],
    "name:vie_x_preferred":[
        "Patur"
    ],
    "name:zho_x_preferred":[
        "\u5e15\u56fe\u5c14"
    ],
    "wof:name":"Patur",
    "wof:placetype":"locality"
},
  "geometry": {"coordinates":[77.83998000000003,21.16197],"type":"Point"}
}