{
  "type": "Feature",
  "properties": {
    "iso:country":"IN",
    "ks:ks_name":"Pulichangadu",
    "ks:ks_pop":1199,
    "ks:ks_type":"VILLAGE",
    "name:eng_x_preferred":[
        "Pulichangadu"
    ],
    "wof:name":"Pulichangadu",
    "wof:placetype":"locality",
    "wof:population":1199
},
  "geometry": {"coordinates":[79.12394500000001,10.326543],"type":"Point"}
}