{
  "type": "Feature",
  "properties": {
    "gn:admin1_code":"12.0",
    "gn:admin2_code":"021",
    "gn:asciiname":"Jamana Bela",
    "gn:country_code":"IN",
    "gn:dem":262,
    "gn:feature_class":"P",
    "gn:feature_code":"PPL",
    "gn:name":"Jam\u0101na Bela",
    "gn:population":0,
    "gn:timezone":"Asia/Kolkata",
    "iso:country":"IN",
    "wof:name":"Jamana Bela",
    "wof:placetype":"locality"
},
  "geometry": {"coordinates":[74.60084000000001,32.77124],"type":"Point"}
}