{
  "type": "Feature",
  "properties": {
    "gn:admin1_code":"16.0",
    "gn:admin2_code":"497.0",
    "gn:asciiname":"Chandseli",
    "gn:country_code":"IN",
    "gn:dem":729,
    "gn:feature_class":"P",
    "gn:feature_code":"PPL",
    "gn:name":"Ch\u0101ndseli",
    "gn:population":0,
    "gn:timezone":"Asia/Kolkata",
    "iso:country":"IN",
    "ks:ks_name":"Chandsali",
    "ks:ks_pop":1946,
    "ks:ks_type":"VILLAGE",
    "name:eng_x_preferred":[
        "Chandsali"
    ],
    "name:eng_x_variant":[
        "Chandseli"
    ],
    "wof:name":"Chandsali",
    "wof:placetype":"locality",
    "wof:population":1946
},
  "geometry": {"coordinates":[74.202319,21.697327],"type":"Point"}
}