{
  "type": "Feature",
  "properties": {
    "iso:country":"IN",
    "ks:ks_name":"Karamanikuppam",
    "ks:ks_pop":1593,
    "ks:ks_type":"VILLAGE",
    "ks:ks_uagg_main":0,
    "name:eng_x_preferred":[
        "Karamanikuppam"
    ],
    "wof:name":"Karamanikuppam",
    "wof:placetype":"neighbourhood",
    "wof:population":1593
},
  "geometry": {"coordinates":[79.692021,11.767315],"type":"Point"}
}