{
  "type": "Feature",
  "properties": {
    "iso:country":"IN",
    "ks:ks_name":"Ranala Annapurna",
    "ks:ks_pop":124,
    "ks:ks_type":"HABITATION",
    "name:eng_x_preferred":[
        "Ranala Annapurna"
    ],
    "wof:name":"Ranala Annapurna",
    "wof:placetype":"locality",
    "wof:population":124
},
  "geometry": {"coordinates":[79.537741,20.756298],"type":"Point"}
}