{
  "type": "Feature",
  "properties": {
    "gn:admin1_code":"39",
    "gn:admin2_code":"61.0",
    "gn:asciiname":"Chai Damrara",
    "gn:country_code":"IN",
    "gn:dem":1023,
    "gn:feature_class":"P",
    "gn:feature_code":"PPL",
    "gn:name":"Chai Damr\u0101ra",
    "gn:population":0,
    "gn:timezone":"Asia/Kolkata",
    "iso:country":"IN",
    "wof:name":"Chai Damrara",
    "wof:placetype":"locality"
},
  "geometry": {"coordinates":[78.43375999999998,29.96569],"type":"Point"}
}