{
  "type": "Feature",
  "properties": {
    "gn:admin1_code":"19.0",
    "gn:admin2_code":"575.0",
    "gn:asciiname":"Perna",
    "gn:country_code":"IN",
    "gn:dem":58,
    "gn:feature_class":"P",
    "gn:feature_code":"PPL",
    "gn:name":"Perna",
    "gn:population":0,
    "gn:timezone":"Asia/Kolkata",
    "iso:country":"IN",
    "name:bos_x_preferred":[
        "Perna"
    ],
    "name:ceb_x_preferred":[
        "Perna"
    ],
    "name:ces_x_preferred":[
        "Pern\u00e1"
    ],
    "name:deu_x_preferred":[
        "Perna"
    ],
    "name:fra_x_preferred":[
        "Perna"
    ],
    "name:hrv_x_preferred":[
        "Perna"
    ],
    "name:hun_x_preferred":[
        "Perna"
    ],
    "name:ita_x_preferred":[
        "Perna"
    ],
    "name:jpn_x_preferred":[
        "\u30da\u30eb\u30ca"
    ],
    "name:nld_x_preferred":[
        "Perna"
    ],
    "name:por_x_preferred":[
        "Perna"
    ],
    "name:srp_x_preferred":[
        "\u041f\u0435\u0440\u043d\u0430"
    ],
    "name:swe_x_preferred":[
        "Perna"
    ],
    "wof:name":"Perna",
    "wof:placetype":"locality"
},
  "geometry": {"coordinates":[74.93871,12.82068],"type":"Point"}
}