{
  "type": "Feature",
  "properties": {
    "gn:admin1_code":"36.0",
    "gn:admin2_code":"168",
    "gn:asciiname":"Chandaut",
    "gn:country_code":"IN",
    "gn:dem":136,
    "gn:feature_class":"P",
    "gn:feature_code":"PPL",
    "gn:name":"Chandaut",
    "gn:population":0,
    "gn:timezone":"Asia/Kolkata",
    "iso:country":"IN",
    "wof:name":"Chandaut",
    "wof:placetype":"neighbourhood"
},
  "geometry": {"coordinates":[79.66482000000001,25.90297],"type":"Point"}
}