{
  "type": "Feature",
  "properties": {
    "iso:country":"IN",
    "ks:ks_name":"Dattapur",
    "ks:ks_pop":62,
    "ks:ks_type":"HABITATION",
    "name:eng_x_preferred":[
        "Dattapur"
    ],
    "wof:name":"Dattapur",
    "wof:placetype":"locality",
    "wof:population":62
},
  "geometry": {"coordinates":[77.70668000000001,21.219725],"type":"Point"}
}