{
  "type": "Feature",
  "properties": {
    "iso:country":"IN",
    "ks:ks_name":"Enthal",
    "ks:ks_pop":325,
    "ks:ks_type":"HABITATION",
    "name:eng_x_preferred":[
        "Enthal"
    ],
    "wof:name":"Enthal",
    "wof:placetype":"locality",
    "wof:population":325
},
  "geometry": {"coordinates":[79.319124,11.174106],"type":"Point"}
}