{
  "type": "Feature",
  "properties": {
    "iso:country":"IN",
    "ks:ks_name":"Iravipuram",
    "ks:ks_type":"VILLAGE",
    "name:eng_x_preferred":[
        "Iravipuram"
    ],
    "wof:name":"Iravipuram",
    "wof:placetype":"locality"
},
  "geometry": {"coordinates":[76.617577,8.857546],"type":"Point"}
}