{
  "type": "Feature",
  "properties": {
    "iso:country":"IN",
    "ks:ks_name":"Bhatabari Janta",
    "ks:ks_pop":379,
    "ks:ks_type":"HABITATION",
    "name:eng_x_preferred":[
        "Bhatabari Janta"
    ],
    "wof:name":"Bhatabari Janta",
    "wof:placetype":"locality",
    "wof:population":379
},
  "geometry": {"coordinates":[87.78128100000001,26.271633],"type":"Point"}
}