{
  "type": "Feature",
  "properties": {
    "iso:country":"IN",
    "ks:ks_name":"Kharntiya",
    "ks:ks_pop":411,
    "ks:ks_type":"VILLAGE",
    "name:eng_x_preferred":[
        "Kharntiya"
    ],
    "wof:name":"Kharntiya",
    "wof:placetype":"locality",
    "wof:population":411
},
  "geometry": {"coordinates":[71.78015000000001,25.692969],"type":"Point"}
}