{
  "type": "Feature",
  "properties": {
    "gn:admin1_code":"36.0",
    "gn:admin2_code":"138.0",
    "gn:asciiname":"Baparsi",
    "gn:country_code":"IN",
    "gn:dem":226,
    "gn:feature_class":"P",
    "gn:feature_code":"PPL",
    "gn:name":"Bap\u0101rsi",
    "gn:population":0,
    "gn:timezone":"Asia/Kolkata",
    "iso:country":"IN",
    "wof:name":"Baparsi",
    "wof:placetype":"locality"
},
  "geometry": {"coordinates":[77.50156,29.18179],"type":"Point"}
}