{
  "type": "Feature",
  "properties": {
    "iso:country":"IN",
    "ks:ks_name":"Mulkibettu",
    "ks:ks_pop":200,
    "ks:ks_type":"HABITATION",
    "name:eng_x_preferred":[
        "Mulkibettu"
    ],
    "wof:name":"Mulkibettu",
    "wof:placetype":"locality",
    "wof:population":200
},
  "geometry": {"coordinates":[74.975944,13.249533],"type":"Point"}
}