{
  "type": "Feature",
  "properties": {
    "iso:country":"IN",
    "ks:ks_name":"Bamaniya Falia",
    "ks:ks_pop":320,
    "ks:ks_type":"HABITATION",
    "ks:ks_uagg_main":0,
    "name:eng_x_preferred":[
        "Bamaniya Falia"
    ],
    "wof:name":"Bamaniya Falia",
    "wof:placetype":"neighbourhood",
    "wof:population":320
},
  "geometry": {"coordinates":[73.63583300000001,22.814683],"type":"Point"}
}