{
  "type": "Feature",
  "properties": {
    "iso:country":"IN",
    "ks:ks_alt_nam":"Simariya khurd",
    "ks:ks_name":"Simariya Khurd",
    "ks:ks_pop":90,
    "ks:ks_type":"HABITATION",
    "name:eng_x_preferred":[
        "Simariya Khurd"
    ],
    "wof:name":"Simariya Khurd",
    "wof:placetype":"locality",
    "wof:population":90
},
  "geometry": {"coordinates":[78.87796400000001,23.069211],"type":"Point"}
}