{
  "type": "Feature",
  "properties": {
    "gn:admin1_code":"34.0",
    "gn:admin2_code":"230.0",
    "gn:asciiname":"Bhinak Bigha",
    "gn:country_code":"IN",
    "gn:dem":68,
    "gn:feature_class":"P",
    "gn:feature_code":"PPL",
    "gn:name":"Bhinak Bigha",
    "gn:population":0,
    "gn:timezone":"Asia/Kolkata",
    "iso:country":"IN",
    "ks:ks_alt_nam":"VINAK BIGHA",
    "ks:ks_name":"Vinak Bigha",
    "ks:ks_pop":179,
    "ks:ks_type":"HABITATION",
    "name:eng_x_preferred":[
        "Vinak Bigha"
    ],
    "name:eng_x_variant":[
        "Bhinak Bigha"
    ],
    "wof:name":"Vinak Bigha",
    "wof:placetype":"locality",
    "wof:population":179
},
  "geometry": {"coordinates":[84.885712,25.287922],"type":"Point"}
}