{
  "type": "Feature",
  "properties": {
    "gn:admin1_code":"36.0",
    "gn:admin2_code":"153.0",
    "gn:asciiname":"Baraula",
    "gn:country_code":"IN",
    "gn:dem":154,
    "gn:feature_class":"P",
    "gn:feature_code":"PPL",
    "gn:name":"Baraula",
    "gn:population":0,
    "gn:timezone":"Asia/Kolkata",
    "iso:country":"IN",
    "name:ceb_x_preferred":[
        "Baraula"
    ],
    "name:mai_x_preferred":[
        "\u092c\u0930\u094c\u0932\u093e"
    ],
    "name:msa_x_preferred":[
        "Baraula"
    ],
    "name:nep_x_preferred":[
        "\u092c\u0930\u094c\u0932\u093e"
    ],
    "name:pol_x_preferred":[
        "Baraula"
    ],
    "wof:name":"Baraula",
    "wof:placetype":"locality"
},
  "geometry": {"coordinates":[80.47377,27.94633],"type":"Point"}
}