{
  "type": "Feature",
  "properties": {
    "gn:admin1_code":"25.0",
    "gn:admin2_code":"605.0",
    "gn:asciiname":"Kodagumalai",
    "gn:country_code":"IN",
    "gn:dem":833,
    "gn:feature_class":"P",
    "gn:feature_code":"PPL",
    "gn:name":"Kodagumalai",
    "gn:population":0,
    "gn:timezone":"Asia/Kolkata",
    "iso:country":"IN",
    "wof:name":"Kodagumalai",
    "wof:placetype":"locality"
},
  "geometry": {"coordinates":[78.68835,12.5029],"type":"Point"}
}