{
  "type": "Feature",
  "properties": {
    "gn:admin1_code":"36",
    "gn:admin2_code":"173.0",
    "gn:asciiname":"Mustafabad",
    "gn:country_code":"IN",
    "gn:dem":102,
    "gn:feature_class":"P",
    "gn:feature_code":"PPL",
    "gn:name":"Mustaf\u0101b\u0101d",
    "gn:population":0,
    "gn:timezone":"Asia/Kolkata",
    "iso:country":"IN",
    "ks:ks_alt_nam":"Mustaf\u0101b\u0101d",
    "ks:ks_name":"Mustafabad",
    "ks:ks_pop":5100,
    "ks:ks_type":"VILLAGE",
    "name:eng_x_preferred":[
        "Mustafabad"
    ],
    "name:eng_x_variant":[
        "Mustaf\u0101b\u0101d"
    ],
    "wof:name":"Mustafabad",
    "wof:placetype":"locality",
    "wof:population":5100
},
  "geometry": {"coordinates":[81.542838,26.027863],"type":"Point"}
}