{
  "type": "Feature",
  "properties": {
    "gn:admin1_code":"35",
    "gn:admin2_code":"453.0",
    "gn:asciiname":"Jogigwara",
    "gn:country_code":"IN",
    "gn:dem":852,
    "gn:feature_class":"P",
    "gn:feature_code":"PPL",
    "gn:name":"Jogigw\u0101ra",
    "gn:population":0,
    "gn:timezone":"Asia/Kolkata",
    "iso:country":"IN",
    "ks:ks_name":"Jogirwara",
    "ks:ks_pop":669,
    "ks:ks_type":"VILLAGE",
    "name:eng_x_preferred":[
        "Jogirwara"
    ],
    "name:eng_x_variant":[
        "Jogigwara"
    ],
    "wof:name":"Jogirwara",
    "wof:placetype":"locality",
    "wof:population":669
},
  "geometry": {"coordinates":[81.62543100000001,22.666256],"type":"Point"}
}