{
  "type": "Feature",
  "properties": {
    "iso:country":"IN",
    "ks:ks_alt_nam":"BIND TOLA",
    "ks:ks_name":"Bind Tola",
    "ks:ks_pop":381,
    "ks:ks_type":"HABITATION",
    "name:eng_x_preferred":[
        "Bind Tola"
    ],
    "wof:name":"Bind Tola",
    "wof:placetype":"locality",
    "wof:population":381
},
  "geometry": {"coordinates":[83.569208,25.109277],"type":"Point"}
}