{
  "type": "Feature",
  "properties": {
    "iso:country":"IN",
    "ks:ks_name":"Khetawas",
    "ks:ks_pop":921,
    "ks:ks_type":"VILLAGE",
    "name:eng_x_preferred":[
        "Khetawas"
    ],
    "wof:name":"Khetawas",
    "wof:placetype":"neighbourhood",
    "wof:population":921
},
  "geometry": {"coordinates":[76.877773,28.437241],"type":"Point"}
}