{
  "type": "Feature",
  "properties": {
    "iso:country":"IN",
    "ks:ks_name":"Gachergan",
    "ks:ks_pop":146,
    "ks:ks_type":"VILLAGE",
    "name:eng_x_preferred":[
        "Gachergan"
    ],
    "wof:name":"Gachergan",
    "wof:placetype":"locality",
    "wof:population":146
},
  "geometry": {"coordinates":[83.68218400000001,19.980685],"type":"Point"}
}