{
  "type": "Feature",
  "properties": {
    "gn:admin1_code":"35",
    "gn:admin2_code":"425.0",
    "gn:asciiname":"Bhadaura",
    "gn:country_code":"IN",
    "gn:dem":370,
    "gn:feature_class":"P",
    "gn:feature_code":"PPL",
    "gn:name":"Bhadaura",
    "gn:population":0,
    "gn:timezone":"Asia/Kolkata",
    "iso:country":"IN",
    "wof:name":"Bhadaura",
    "wof:placetype":"locality"
},
  "geometry": {"coordinates":[79.042,24.42894],"type":"Point"}
}