{
  "type": "Feature",
  "properties": {
    "iso:country":"IN",
    "ks:ks_name":"Rangenahalli",
    "ks:ks_type":"VILLAGE",
    "name:eng_x_preferred":[
        "Rangenahalli"
    ],
    "wof:name":"Rangenahalli",
    "wof:placetype":"locality"
},
  "geometry": {"coordinates":[76.472346,13.77084],"type":"Point"}
}