{
  "type": "Feature",
  "properties": {
    "iso:country":"IN",
    "ks:ks_name":"Santoshpur",
    "ks:ks_pop":1456,
    "ks:ks_type":"VILLAGE",
    "ks:ks_uagg_main":0,
    "name:eng_x_preferred":[
        "Santoshpur"
    ],
    "wof:name":"Santoshpur",
    "wof:placetype":"locality",
    "wof:population":1456
},
  "geometry": {"coordinates":[88.511257,22.776652],"type":"Point"}
}