{
  "type": "Feature",
  "properties": {
    "gn:admin1_code":"36.0",
    "gn:admin2_code":"148",
    "gn:asciiname":"Daher",
    "gn:country_code":"IN",
    "gn:dem":148,
    "gn:feature_class":"P",
    "gn:feature_code":"PPL",
    "gn:name":"Daher",
    "gn:population":0,
    "gn:timezone":"Asia/Kolkata",
    "iso:country":"IN",
    "wof:name":"Daher",
    "wof:placetype":"locality"
},
  "geometry": {"coordinates":[79.33339000000002,27.22941],"type":"Point"}
}