{
  "type": "Feature",
  "properties": {
    "iso:country":"IN",
    "ks:ks_name":"Kanja Misir",
    "ks:ks_pop":12,
    "ks:ks_type":"VILLAGE",
    "name:eng_x_preferred":[
        "Kanja Misir"
    ],
    "wof:name":"Kanja Misir",
    "wof:placetype":"locality",
    "wof:population":12
},
  "geometry": {"coordinates":[82.340751,26.750579],"type":"Point"}
}