{
  "type": "Feature",
  "properties": {
    "gn:admin1_code":"19",
    "gn:admin2_code":"558.0",
    "gn:asciiname":"Sangvi",
    "gn:country_code":"IN",
    "gn:dem":541,
    "gn:feature_class":"P",
    "gn:feature_code":"PPL",
    "gn:name":"S\u0101ngvi",
    "gn:population":0,
    "gn:timezone":"Asia/Kolkata",
    "iso:country":"IN",
    "ks:ks_alt_nam":"S\u0101ngvi",
    "ks:ks_name":"Sangvi",
    "ks:ks_pop":498,
    "ks:ks_type":"VILLAGE",
    "name:eng_x_preferred":[
        "Sangvi"
    ],
    "name:eng_x_variant":[
        "S\u0101ngvi"
    ],
    "name:fra_x_preferred":[
        "Sangvi"
    ],
    "wof:name":"Sangvi",
    "wof:placetype":"locality",
    "wof:population":498
},
  "geometry": {"coordinates":[77.411621,18.051125],"type":"Point"}
}