{
  "type": "Feature",
  "properties": {
    "iso:country":"IN",
    "ks:ks_name":"Itaiya",
    "ks:ks_pop":0,
    "ks:ks_type":"VILLAGE",
    "name:eng_x_preferred":[
        "Itaiya"
    ],
    "wof:name":"Itaiya",
    "wof:placetype":"locality",
    "wof:population":0
},
  "geometry": {"coordinates":[78.437185,23.593323],"type":"Point"}
}