{
  "type": "Feature",
  "properties": {
    "iso:country":"IN",
    "ks:ks_name":"Palam",
    "ks:ks_pop":472,
    "ks:ks_type":"HABITATION",
    "ks:ks_uagg_main":0,
    "name:eng_x_preferred":[
        "Palam"
    ],
    "wof:name":"Palam",
    "wof:placetype":"neighbourhood",
    "wof:population":472
},
  "geometry": {"coordinates":[76.744928,10.752335],"type":"Point"}
}