{
  "type": "Feature",
  "properties": {
    "iso:country":"IN",
    "ks:ks_name":"Malapalli",
    "ks:ks_pop":31,
    "ks:ks_type":"HABITATION",
    "name:eng_x_preferred":[
        "Malapalli"
    ],
    "wof:name":"Malapalli",
    "wof:placetype":"locality",
    "wof:population":31
},
  "geometry": {"coordinates":[78.632544,14.186252],"type":"Point"}
}