{
  "type": "Feature",
  "properties": {
    "iso:country":"IN",
    "ks:ks_name":"Hemram",
    "ks:ks_pop":494,
    "ks:ks_type":"VILLAGE",
    "name:eng_x_preferred":[
        "Hemram"
    ],
    "wof:name":"Hemram",
    "wof:placetype":"locality",
    "wof:population":494
},
  "geometry": {"coordinates":[85.499577,23.008595],"type":"Point"}
}