{
  "type": "Feature",
  "properties": {
    "iso:country":"IN",
    "ks:ks_name":"Haripur",
    "ks:ks_pop":1925,
    "ks:ks_type":"VILLAGE",
    "name:eng_x_preferred":[
        "Haripur"
    ],
    "wof:name":"Haripur",
    "wof:placetype":"locality",
    "wof:population":1925
},
  "geometry": {"coordinates":[91.067351,26.468031],"type":"Point"}
}