{
  "type": "Feature",
  "properties": {
    "iso:country":"IN",
    "ks:ks_name":"Talav Falia",
    "ks:ks_pop":859,
    "ks:ks_type":"HABITATION",
    "name:eng_x_preferred":[
        "Talav Falia"
    ],
    "wof:name":"Talav Falia",
    "wof:placetype":"locality",
    "wof:population":859
},
  "geometry": {"coordinates":[74.410111,22.872722],"type":"Point"}
}