{
  "type": "Feature",
  "properties": {
    "iso:country":"IN",
    "ks:ks_alt_nam":"yadav basti",
    "ks:ks_name":"Yadav Basti",
    "ks:ks_pop":43,
    "ks:ks_type":"HABITATION",
    "name:eng_x_preferred":[
        "Yadav Basti"
    ],
    "wof:name":"Yadav Basti",
    "wof:placetype":"locality",
    "wof:population":43
},
  "geometry": {"coordinates":[83.31833399999999,25.071129],"type":"Point"}
}