{
  "type": "Feature",
  "properties": {
    "iso:country":"IN",
    "ks:ks_name":"Pilipaju",
    "ks:ks_pop":170,
    "ks:ks_type":"VILLAGE",
    "name:eng_x_preferred":[
        "Pilipaju"
    ],
    "wof:name":"Pilipaju",
    "wof:placetype":"locality",
    "wof:population":170
},
  "geometry": {"coordinates":[84.762412,20.257726],"type":"Point"}
}