{
  "type": "Feature",
  "properties": {
    "gn:admin1_code":"24.0",
    "gn:admin2_code":"102",
    "gn:asciiname":"Ramdevra",
    "gn:country_code":"IN",
    "gn:dem":291,
    "gn:feature_class":"P",
    "gn:feature_code":"PPL",
    "gn:name":"R\u0101mdevra",
    "gn:population":0,
    "gn:timezone":"Asia/Kolkata",
    "iso:country":"IN",
    "name:und_x_variant":[
        "R\u0101mdevra",
        "R\u0101m Deora"
    ],
    "wof:name":"Ramdevra",
    "wof:placetype":"locality"
},
  "geometry": {"coordinates":[74.79644999999999,28.30269],"type":"Point"}
}