{
  "type": "Feature",
  "properties": {
    "iso:country":"IN",
    "ks:ks_name":"Gauripur",
    "ks:ks_pop":361,
    "ks:ks_type":"VILLAGE",
    "name:eng_x_preferred":[
        "Gauripur"
    ],
    "wof:name":"Gauripur",
    "wof:placetype":"locality",
    "wof:population":361
},
  "geometry": {"coordinates":[88.05532100000001,25.466698],"type":"Point"}
}