{
  "type": "Feature",
  "properties": {
    "iso:country":"IN",
    "ks:ks_name":"Sagavi",
    "ks:ks_pop":1065,
    "ks:ks_type":"VILLAGE",
    "ks:ks_uagg_main":0,
    "name:eng_x_preferred":[
        "Sagavi"
    ],
    "wof:name":"Sagavi",
    "wof:placetype":"neighbourhood",
    "wof:population":1065
},
  "geometry": {"coordinates":[75.732603,22.04989],"type":"Point"}
}