{
  "type": "Feature",
  "properties": {
    "iso:country":"IN",
    "ks:ks_alt_nam":"Hat faliya",
    "ks:ks_name":"Hat Faliya",
    "ks:ks_pop":272,
    "ks:ks_type":"HABITATION",
    "name:eng_x_preferred":[
        "Hat Faliya"
    ],
    "wof:name":"Hat Faliya",
    "wof:placetype":"locality",
    "wof:population":272
},
  "geometry": {"coordinates":[73.320778,20.533389],"type":"Point"}
}