{
  "type": "Feature",
  "properties": {
    "iso:country":"IN",
    "ks:ks_name":"Bahadurpur",
    "ks:ks_pop":391,
    "ks:ks_type":"VILLAGE",
    "name:eng_x_preferred":[
        "Bahadurpur"
    ],
    "wof:name":"Bahadurpur",
    "wof:placetype":"locality",
    "wof:population":391
},
  "geometry": {"coordinates":[85.682265,24.59648],"type":"Point"}
}