{
  "type": "Feature",
  "properties": {
    "iso:country":"IN",
    "ks:ks_name":"Birahiya Tola",
    "ks:ks_pop":587,
    "ks:ks_type":"HABITATION",
    "name:eng_x_preferred":[
        "Birahiya Tola"
    ],
    "wof:name":"Birahiya Tola",
    "wof:placetype":"locality",
    "wof:population":587
},
  "geometry": {"coordinates":[82.325339,24.886435],"type":"Point"}
}