{
  "type": "Feature",
  "properties": {
    "gn:admin1_code":"36",
    "gn:admin2_code":"180.0",
    "gn:asciiname":"Sahbapur Mahpal Singh",
    "gn:country_code":"IN",
    "gn:dem":117,
    "gn:feature_class":"P",
    "gn:feature_code":"PPL",
    "gn:name":"Sahb\u0101pur Mahp\u0101l Singh",
    "gn:population":0,
    "gn:timezone":"Asia/Kolkata",
    "iso:country":"IN",
    "wof:name":"Sahbapur Mahpal Singh",
    "wof:placetype":"locality"
},
  "geometry": {"coordinates":[81.49333,27.4168],"type":"Point"}
}