{
  "type": "Feature",
  "properties": {
    "gn:admin1_code":"19",
    "gn:admin2_code":"563.0",
    "gn:asciiname":"Bidramane",
    "gn:country_code":"IN",
    "gn:dem":533,
    "gn:feature_class":"P",
    "gn:feature_code":"PPL",
    "gn:name":"Bidramane",
    "gn:population":0,
    "gn:timezone":"Asia/Kolkata",
    "iso:country":"IN",
    "ks:ks_alt_nam":"bidramane",
    "ks:ks_name":"Bidramane",
    "ks:ks_pop":40,
    "ks:ks_type":"HABITATION",
    "name:eng_x_preferred":[
        "Bidramane"
    ],
    "wof:name":"Bidramane",
    "wof:placetype":"locality",
    "wof:population":40
},
  "geometry": {"coordinates":[74.762079,14.481501],"type":"Point"}
}