{
  "type": "Feature",
  "properties": {
    "gn:admin1_code":"36.0",
    "gn:admin2_code":"179.0",
    "gn:asciiname":"Nagar Dih",
    "gn:country_code":"IN",
    "gn:dem":104,
    "gn:feature_class":"P",
    "gn:feature_code":"PPL",
    "gn:name":"Nagar D\u012bh",
    "gn:population":0,
    "gn:timezone":"Asia/Kolkata",
    "iso:country":"IN",
    "ks:ks_alt_nam":"NAGAR DEEH",
    "ks:ks_name":"Nagar Deeh",
    "ks:ks_pop":2129,
    "ks:ks_type":"HABITATION",
    "name:eng_x_preferred":[
        "Nagar Deeh"
    ],
    "name:eng_x_variant":[
        "Nagar Dih"
    ],
    "wof:name":"Nagar Deeh",
    "wof:placetype":"locality",
    "wof:population":2129
},
  "geometry": {"coordinates":[81.966742,26.12764],"type":"Point"}
}