{
  "type": "Feature",
  "properties": {
    "gn:admin1_code":"37.0",
    "gn:admin2_code":"413.0",
    "gn:asciiname":"Kanagaon",
    "gn:country_code":"IN",
    "gn:dem":473,
    "gn:feature_class":"P",
    "gn:feature_code":"PPL",
    "gn:name":"K\u0101nagaon",
    "gn:population":0,
    "gn:timezone":"Asia/Kolkata",
    "iso:country":"IN",
    "ks:ks_alt_nam":"K\u0101nagaon",
    "ks:ks_name":"Kanagaon",
    "ks:ks_pop":339,
    "ks:ks_type":"VILLAGE",
    "name:eng_x_preferred":[
        "Kanagaon"
    ],
    "name:eng_x_variant":[
        "K\u0101nagaon"
    ],
    "wof:name":"Kanagaon",
    "wof:placetype":"locality",
    "wof:population":339
},
  "geometry": {"coordinates":[81.34313,20.193386],"type":"Point"}
}