{
  "type": "Feature",
  "properties": {
    "gn:admin1_code":"16.0",
    "gn:admin2_code":"529",
    "gn:asciiname":"Kokesra",
    "gn:country_code":"IN",
    "gn:dem":95,
    "gn:feature_class":"P",
    "gn:feature_code":"PPL",
    "gn:name":"Kokesra",
    "gn:population":0,
    "gn:timezone":"Asia/Kolkata",
    "iso:country":"IN",
    "name:und_x_variant":[
        "Kokisra",
        "Kokesra"
    ],
    "wof:name":"Kokesra",
    "wof:placetype":"neighbourhood"
},
  "geometry": {"coordinates":[73.73183,16.47572],"type":"Point"}
}