{
  "type": "Feature",
  "properties": {
    "gn:admin1_code":"24",
    "gn:admin2_code":"125.0",
    "gn:asciiname":"Mashka Bara",
    "gn:country_code":"IN",
    "gn:dem":260,
    "gn:feature_class":"P",
    "gn:feature_code":"PPL",
    "gn:name":"M\u0101shka Bara",
    "gn:population":0,
    "gn:timezone":"Asia/Kolkata",
    "iso:country":"IN",
    "wof:name":"Mashka Bara",
    "wof:placetype":"locality"
},
  "geometry": {"coordinates":[74.32519000000001,23.14035],"type":"Point"}
}