{
  "type": "Feature",
  "properties": {
    "iso:country":"IN",
    "ks:ks_name":"Rungdung",
    "ks:ks_pop":1675,
    "ks:ks_type":"HABITATION",
    "name:eng_x_preferred":[
        "Rungdung"
    ],
    "wof:name":"Rungdung",
    "wof:placetype":"locality",
    "wof:population":1675
},
  "geometry": {"coordinates":[88.327331,27.096442],"type":"Point"}
}