{
  "type": "Feature",
  "properties": {
    "iso:country":"IN",
    "ks:ks_name":"Beladula",
    "ks:ks_type":"VILLAGE",
    "ks:ks_uagg_main":0,
    "name:eng_x_preferred":[
        "Beladula"
    ],
    "wof:name":"Beladula",
    "wof:placetype":"neighbourhood"
},
  "geometry": {"coordinates":[83.407746,21.900498],"type":"Point"}
}