{
  "type": "Feature",
  "properties": {
    "gn:admin1_code":"37.0",
    "gn:admin2_code":"408.0",
    "gn:asciiname":"Nandia",
    "gn:country_code":"IN",
    "gn:dem":331,
    "gn:feature_class":"P",
    "gn:feature_code":"PPL",
    "gn:name":"N\u0101ndia",
    "gn:population":0,
    "gn:timezone":"Asia/Kolkata",
    "iso:country":"IN",
    "name:eng_x_preferred":[
        "N\u0101ndia"
    ],
    "wof:name":"Nandia",
    "wof:placetype":"locality"
},
  "geometry": {"coordinates":[81.10639999999999,21.70268],"type":"Point"}
}