{
  "type": "Feature",
  "properties": {
    "gn:admin1_code":"19.0",
    "gn:admin2_code":"578.0",
    "gn:asciiname":"Singanallur",
    "gn:country_code":"IN",
    "gn:dem":678,
    "gn:feature_class":"P",
    "gn:feature_code":"PPL",
    "gn:name":"Sing\u0101nall\u016br",
    "gn:population":0,
    "gn:timezone":"Asia/Kolkata",
    "iso:country":"IN",
    "name:tam_x_preferred":[
        "\u0b9a\u0bbf\u0b99\u0bcd\u0b95\u0bbe\u0ba8\u0bb2\u0bcd\u0bb2\u0bc2\u0bb0\u0bcd"
    ],
    "name:und_x_variant":[
        "Sing\u0101nall\u016br",
        "Sing\u0101nallur"
    ],
    "wof:name":"Singanallur",
    "wof:placetype":"locality"
},
  "geometry": {"coordinates":[77.21977,12.14484],"type":"Point"}
}