{
  "type": "Feature",
  "properties": {
    "gn:admin1_code":"19.0",
    "gn:admin2_code":"583.0",
    "gn:asciiname":"Bidalur",
    "gn:country_code":"IN",
    "gn:dem":922,
    "gn:feature_class":"P",
    "gn:feature_code":"PPL",
    "gn:name":"Bidal\u016br",
    "gn:population":0,
    "gn:timezone":"Asia/Kolkata",
    "iso:country":"IN",
    "name:ara_x_preferred":[
        "\u0628\u064a\u062f\u0627\u0644\u0648\u0631"
    ],
    "name:ben_bn_x_preferred":[
        "\u09ac\u09bf\u09a6\u09be\u09b2\u09c1\u09b0"
    ],
    "name:ben_in_x_preferred":[
        "\u09ac\u09bf\u09a6\u09be\u09b2\u09c1\u09b0"
    ],
    "name:guj_x_preferred":[
        "\u0aac\u0abf\u0aa6\u0abe\u0ab2\u0ac1\u0ab0"
    ],
    "name:hin_x_preferred":[
        "\u092c\u093f\u0926\u0932\u0942\u0930"
    ],
    "name:kan_x_preferred":[
        "\u0cac\u0cbf\u0ca6\u0cb2\u0cc2\u0cb0\u0cc1"
    ],
    "name:mal_x_preferred":[
        "\u0d2c\u0d3f\u0d26\u0d32\u0d42\u0d7c"
    ],
    "name:mar_x_preferred":[
        "\u092c\u093f\u0926\u093e\u0932\u0942\u0930"
    ],
    "name:pan_x_preferred":[
        "\u0a2c\u0a3f\u0a26\u0a3e\u0a32\u0a41\u0a30"
    ],
    "name:tam_x_preferred":[
        "\u0baa\u0bbf\u0ba4\u0bb2\u0bc2\u0bb0\u0bcd"
    ],
    "name:tel_x_preferred":[
        "\u0c2c\u0c3f\u0c21\u0c32\u0c42\u0c30\u0c4d"
    ],
    "name:urd_x_preferred":[
        "\u0628\u06cc\u062f\u0627\u0644\u0648\u0631"
    ],
    "wof:name":"Bidalur",
    "wof:placetype":"locality"
},
  "geometry": {"coordinates":[77.6915,13.28726],"type":"Point"}
}