{
  "type": "Feature",
  "properties": {
    "iso:country":"IN",
    "ks:ks_name":"Madhya Para",
    "ks:ks_pop":394,
    "ks:ks_type":"HABITATION",
    "name:eng_x_preferred":[
        "Madhya Para"
    ],
    "wof:name":"Madhya Para",
    "wof:placetype":"locality",
    "wof:population":394
},
  "geometry": {"coordinates":[91.405225,23.582608],"type":"Point"}
}