{
  "type": "Feature",
  "properties": {
    "gn:admin1_code":"23",
    "gn:admin2_code":"39.0",
    "gn:asciiname":"Hussain Chak",
    "gn:country_code":"IN",
    "gn:dem":258,
    "gn:feature_class":"P",
    "gn:feature_code":"PPL",
    "gn:name":"Hussain Chak",
    "gn:population":0,
    "gn:timezone":"Asia/Kolkata",
    "iso:country":"IN",
    "ks:ks_name":"Hussain Chak",
    "ks:ks_type":"VILLAGE",
    "name:eng_x_preferred":[
        "Hussain Chak"
    ],
    "name:por_x_preferred":[
        "Hussain Chak"
    ],
    "wof:name":"Hussain Chak",
    "wof:placetype":"locality"
},
  "geometry": {"coordinates":[76.095027,31.093483],"type":"Point"}
}