{
  "type": "Feature",
  "properties": {
    "iso:country":"IN",
    "ks:ks_name":"Uttar Paschimpara",
    "ks:ks_pop":510,
    "ks:ks_type":"HABITATION",
    "name:eng_x_preferred":[
        "Uttar Paschimpara"
    ],
    "wof:name":"Uttar Paschimpara",
    "wof:placetype":"locality",
    "wof:population":510
},
  "geometry": {"coordinates":[91.263119,23.498525],"type":"Point"}
}