{
  "type": "Feature",
  "properties": {
    "iso:country":"IN",
    "ks:ks_name":"Mitakipara",
    "ks:ks_pop":209,
    "ks:ks_type":"HABITATION",
    "name:eng_x_preferred":[
        "Mitakipara"
    ],
    "wof:name":"Mitakipara",
    "wof:placetype":"locality",
    "wof:population":209
},
  "geometry": {"coordinates":[81.40304,19.159238],"type":"Point"}
}