{
  "type": "Feature",
  "properties": {
    "gn:country":"IN",
    "gn:fcode":"PPL",
    "gn:population":0,
    "iso:country":"IN",
    "name:aze_x_preferred":[
        "Bhangarh Rajasthan"
    ],
    "name:ckb_x_preferred":[
        "\u0628\u06d5\u06be\u0627\u0646\u06af\u0627\u0631\u06d5"
    ],
    "name:hin_x_preferred":[
        "\u092d\u093e\u0928\u0917\u0922\u093c"
    ],
    "name:kor_x_preferred":[
        "\ubc18\uac00\ub77c"
    ],
    "name:mal_x_preferred":[
        "\u0d2d\u0d3e\u0d7b\u0d17\u0d7c"
    ],
    "name:pan_x_preferred":[
        "\u0a2d\u0a3e\u0a28\u0a17\u0a5c\u0a4d\u0a39"
    ],
    "name:srp_x_preferred":[
        "\u0411\u0430\u043d\u0433\u0430\u0440"
    ],
    "name:und_x_variant":[
        "Bishangrah"
    ],
    "qs_pg:aaroncc":"IN",
    "qs_pg:gn_country":"IN",
    "qs_pg:gn_fcode":"PPL",
    "qs_pg:gn_pop":0,
    "qs_pg:name":"Bhangarh",
    "qs_pg:name_adm0":"India",
    "qs_pg:name_adm1":"Haryana",
    "qs_pg:photos_9r":0,
    "qs_pg:photos_sr":0,
    "qs_pg:pop_sr":0,
    "qs_pg:qs_pg_placetype":"locality",
    "qs_pg:qs_pg_placetype_gp":"Town",
    "qs_pg:woe_adm0":23424848,
    "woe:adm0_id":23424848,
    "woe:name_adm0":"India",
    "woe:name_adm1":"Haryana",
    "woe:placetype":"Town",
    "wof:name":"Bhangarh",
    "wof:placetype":"locality"
},
  "geometry": {"coordinates":[75.25199000000001,28.44124],"type":"Point"}
}