{
  "type": "Feature",
  "properties": {
    "iso:country":"IN",
    "ks:ks_name":"Asalkanti",
    "ks:ks_pop":146,
    "ks:ks_type":"VILLAGE",
    "name:eng_x_preferred":[
        "Asalkanti"
    ],
    "wof:name":"Asalkanti",
    "wof:placetype":"locality",
    "wof:population":146
},
  "geometry": {"coordinates":[73.256333,20.167694],"type":"Point"}
}