{
  "type": "Feature",
  "properties": {
    "iso:country":"IN",
    "ks:ks_name":"Kumbhakaral",
    "ks:ks_pop":686,
    "ks:ks_type":"VILLAGE",
    "name:eng_x_preferred":[
        "Kumbhakaral"
    ],
    "wof:name":"Kumbhakaral",
    "wof:placetype":"locality",
    "wof:population":686
},
  "geometry": {"coordinates":[86.31245,21.108414],"type":"Point"}
}