{
  "type": "Feature",
  "properties": {
    "iso:country":"IN",
    "ks:ks_name":"Kattathevanpatti",
    "ks:ks_pop":1390,
    "ks:ks_type":"HABITATION",
    "name:eng_x_preferred":[
        "Kattathevanpatti"
    ],
    "wof:name":"Kattathevanpatti",
    "wof:placetype":"locality",
    "wof:population":1390
},
  "geometry": {"coordinates":[77.83608700000001,9.918107],"type":"Point"}
}