{
  "type": "Feature",
  "properties": {
    "gn:admin1_code":"35.0",
    "gn:admin2_code":"437.0",
    "gn:asciiname":"Amla Taj",
    "gn:country_code":"IN",
    "gn:dem":502,
    "gn:feature_class":"P",
    "gn:feature_code":"PPL",
    "gn:name":"Amla Taj",
    "gn:population":0,
    "gn:timezone":"Asia/Kolkata",
    "iso:country":"IN",
    "wof:name":"Amla Taj",
    "wof:placetype":"locality"
},
  "geometry": {"coordinates":[76.41654,22.86765],"type":"Point"}
}