{
  "type": "Feature",
  "properties": {
    "iso:country":"IN",
    "ks:ks_alt_nam":"Walore Chilhawale wasti",
    "ks:ks_name":"Walore Chilhawale Wasti",
    "ks:ks_pop":175,
    "ks:ks_type":"HABITATION",
    "name:eng_x_preferred":[
        "Walore Chilhawale Wasti"
    ],
    "wof:name":"Walore Chilhawale Wasti",
    "wof:placetype":"locality",
    "wof:population":175
},
  "geometry": {"coordinates":[74.119788,18.293688],"type":"Point"}
}