{
  "type": "Feature",
  "properties": {
    "gn:admin1_code":"36",
    "gn:admin2_code":"173.0",
    "gn:asciiname":"Fattupur",
    "gn:country_code":"IN",
    "gn:dem":94,
    "gn:feature_class":"P",
    "gn:feature_code":"PPL",
    "gn:name":"Fatt\u016bpur",
    "gn:population":0,
    "gn:timezone":"Asia/Kolkata",
    "iso:country":"IN",
    "ks:ks_alt_nam":"Fatt\u016bpur",
    "ks:ks_name":"Fattupur",
    "ks:ks_pop":616,
    "ks:ks_type":"VILLAGE",
    "name:eng_x_preferred":[
        "Fattupur"
    ],
    "name:eng_x_variant":[
        "Fatt\u016bpur"
    ],
    "wof:name":"Fattupur",
    "wof:placetype":"locality",
    "wof:population":616
},
  "geometry": {"coordinates":[82.28982499999999,25.885838],"type":"Point"}
}