{
  "type": "Feature",
  "properties": {
    "iso:country":"IN",
    "ks:ks_alt_nam":"NAWAR NAGU",
    "ks:ks_name":"Nawar Nagu",
    "ks:ks_pop":182,
    "ks:ks_type":"HABITATION",
    "name:eng_x_preferred":[
        "Nawar Nagu"
    ],
    "wof:name":"Nawar Nagu",
    "wof:placetype":"locality",
    "wof:population":182
},
  "geometry": {"coordinates":[84.245655,23.847937],"type":"Point"}
}