{
  "type": "Feature",
  "properties": {
    "iso:country":"IN",
    "ks:ks_name":"Are Bk.",
    "ks:ks_pop":464,
    "ks:ks_type":"VILLAGE",
    "name:eng_x_preferred":[
        "Are Bk."
    ],
    "wof:name":"Are Bk.",
    "wof:placetype":"locality",
    "wof:population":464
},
  "geometry": {"coordinates":[73.06966199999999,18.4627],"type":"Point"}
}