{
  "type": "Feature",
  "properties": {
    "iso:country":"IN",
    "ks:ks_name":"Gatingia",
    "ks:ks_pop":224,
    "ks:ks_type":"VILLAGE",
    "ks:ks_uagg_main":0,
    "name:eng_x_preferred":[
        "Gatingia"
    ],
    "wof:name":"Gatingia",
    "wof:placetype":"neighbourhood",
    "wof:population":224
},
  "geometry": {"coordinates":[83.81298700000001,20.222183],"type":"Point"}
}