{
  "type": "Feature",
  "properties": {
    "iso:country":"IN",
    "ks:ks_name":"Karthoru",
    "ks:ks_pop":113,
    "ks:ks_type":"HABITATION",
    "name:eng_x_preferred":[
        "Karthoru"
    ],
    "wof:name":"Karthoru",
    "wof:placetype":"locality",
    "wof:population":113
},
  "geometry": {"coordinates":[75.258923,12.926582],"type":"Point"}
}