{
  "type": "Feature",
  "properties": {
    "iso:country":"IN",
    "ks:ks_name":"Bhom Gondusar",
    "ks:ks_pop":245,
    "ks:ks_type":"VILLAGE",
    "name:eng_x_preferred":[
        "Bhom Gondusar"
    ],
    "wof:name":"Bhom Gondusar",
    "wof:placetype":"locality",
    "wof:population":245
},
  "geometry": {"coordinates":[74.10820699999999,27.621765],"type":"Point"}
}