{
  "type": "Feature",
  "properties": {
    "iso:country":"IN",
    "ks:ks_name":"Vaskhra",
    "ks:ks_pop":459,
    "ks:ks_type":"HABITATION",
    "name:eng_x_preferred":[
        "Vaskhra"
    ],
    "wof:name":"Vaskhra",
    "wof:placetype":"locality",
    "wof:population":459
},
  "geometry": {"coordinates":[82.934758,23.940443],"type":"Point"}
}