{
  "type": "Feature",
  "properties": {
    "gn:admin1_code":"12.0",
    "gn:admin2_code":"006",
    "gn:asciiname":"Chhati Miari",
    "gn:country_code":"IN",
    "gn:dem":898,
    "gn:feature_class":"P",
    "gn:feature_code":"PPL",
    "gn:name":"Chhati Mi\u0101ri",
    "gn:population":0,
    "gn:timezone":"Asia/Kolkata",
    "iso:country":"IN",
    "name:und_x_variant":[
        "Chhati Mi\u0101ri",
        "Chhoti Mi\u0101ri"
    ],
    "wof:name":"Chhati Miari",
    "wof:placetype":"locality"
},
  "geometry": {"coordinates":[74.23823,33.32911],"type":"Point"}
}