{
  "type": "Feature",
  "properties": {
    "iso:country":"IN",
    "ks:ks_name":"Mohapada",
    "ks:ks_pop":798,
    "ks:ks_type":"HABITATION",
    "name:eng_x_preferred":[
        "Mohapada"
    ],
    "wof:name":"Mohapada",
    "wof:placetype":"locality",
    "wof:population":798
},
  "geometry": {"coordinates":[73.31825000000001,20.213194],"type":"Point"}
}