{
  "type": "Feature",
  "properties": {
    "gn:admin1_code":"09",
    "gn:admin2_code":"471.0",
    "gn:asciiname":"Umta",
    "gn:country_code":"IN",
    "gn:dem":141,
    "gn:feature_class":"P",
    "gn:feature_code":"PPL",
    "gn:name":"Umta",
    "gn:population":0,
    "gn:timezone":"Asia/Kolkata",
    "iso:country":"IN",
    "wof:name":"Umta",
    "wof:placetype":"locality"
},
  "geometry": {"coordinates":[72.55525,23.78082],"type":"Point"}
}