{
  "type": "Feature",
  "properties": {
    "gn:admin1_code":"11",
    "gn:admin2_code":"23.0",
    "gn:asciiname":"Chamuhan",
    "gn:country_code":"IN",
    "gn:dem":1374,
    "gn:feature_class":"P",
    "gn:feature_code":"PPL",
    "gn:name":"Chamuhan",
    "gn:population":0,
    "gn:timezone":"Asia/Kolkata",
    "iso:country":"IN",
    "wof:name":"Chamuhan",
    "wof:placetype":"locality"
},
  "geometry": {"coordinates":[76.11336999999997,32.61292],"type":"Point"}
}