{
  "type": "Feature",
  "properties": {
    "iso:country":"IN",
    "ks:ks_name":"Ch Palli",
    "ks:ks_pop":212,
    "ks:ks_type":"HABITATION",
    "name:eng_x_preferred":[
        "Ch Palli"
    ],
    "wof:name":"Ch Palli",
    "wof:placetype":"locality",
    "wof:population":212
},
  "geometry": {"coordinates":[84.426968,19.390907],"type":"Point"}
}