{
  "type": "Feature",
  "properties": {
    "iso:country":"IN",
    "ks:ks_name":"Borbaruah Dihingia No. 1",
    "ks:ks_pop":708,
    "ks:ks_type":"HABITATION",
    "ks:ks_uagg_main":0,
    "name:eng_x_preferred":[
        "Borbaruah Dihingia No. 1"
    ],
    "wof:name":"Borbaruah Dihingia No. 1",
    "wof:placetype":"neighbourhood",
    "wof:population":708
},
  "geometry": {"coordinates":[94.87642200000001,27.406166],"type":"Point"}
}