{
  "type": "Feature",
  "properties": {
    "iso:country":"IN",
    "ks:ks_name":"Kandanassery",
    "ks:ks_pop":12343,
    "ks:ks_type":"VILLAGE",
    "name:eng_x_preferred":[
        "Kandanassery"
    ],
    "wof:name":"Kandanassery",
    "wof:placetype":"locality",
    "wof:population":12343
},
  "geometry": {"coordinates":[76.078785,10.598365],"type":"Point"}
}