{
  "type": "Feature",
  "properties": {
    "iso:country":"IN",
    "ks:ks_alt_nam":"BINARAMAN GANJ",
    "ks:ks_name":"Binaraman Ganj",
    "ks:ks_pop":828,
    "ks:ks_type":"HABITATION",
    "name:eng_x_preferred":[
        "Binaraman Ganj"
    ],
    "wof:name":"Binaraman Ganj",
    "wof:placetype":"locality",
    "wof:population":828
},
  "geometry": {"coordinates":[84.80438100000001,25.215379],"type":"Point"}
}