{
  "type": "Feature",
  "properties": {
    "iso:country":"IN",
    "ks:ks_name":"Baheriya",
    "ks:ks_pop":106,
    "ks:ks_type":"HABITATION",
    "name:eng_x_preferred":[
        "Baheriya"
    ],
    "wof:name":"Baheriya",
    "wof:placetype":"locality",
    "wof:population":106
},
  "geometry": {"coordinates":[79.072726,22.81336],"type":"Point"}
}