{
  "type": "Feature",
  "properties": {
    "iso:country":"IN",
    "ks:ks_name":"Bogatola",
    "ks:ks_pop":950,
    "ks:ks_type":"HABITATION",
    "name:eng_x_preferred":[
        "Bogatola"
    ],
    "wof:name":"Bogatola",
    "wof:placetype":"locality",
    "wof:population":950
},
  "geometry": {"coordinates":[80.382925,20.341545],"type":"Point"}
}