{
  "type": "Feature",
  "properties": {
    "gn:admin1_code":"24",
    "gn:admin2_code":"106.0",
    "gn:asciiname":"Pipret",
    "gn:country_code":"IN",
    "gn:dem":237,
    "gn:feature_class":"P",
    "gn:feature_code":"PPL",
    "gn:name":"Pipret",
    "gn:population":0,
    "gn:timezone":"Asia/Kolkata",
    "iso:country":"IN",
    "ks:ks_name":"Pipret",
    "ks:ks_pop":704,
    "ks:ks_type":"VILLAGE",
    "ks:ks_uagg_main":0,
    "name:eng_x_preferred":[
        "Pipret"
    ],
    "wof:name":"Pipret",
    "wof:placetype":"neighbourhood",
    "wof:population":704
},
  "geometry": {"coordinates":[77.459542,26.600499],"type":"Point"}
}