{
  "type": "Feature",
  "properties": {
    "gn:admin1_code":"36",
    "gn:admin2_code":"200.0",
    "gn:asciiname":"Jhalarsarai",
    "gn:country_code":"IN",
    "gn:dem":341,
    "gn:feature_class":"P",
    "gn:feature_code":"PPL",
    "gn:name":"Jh\u0101larsarai",
    "gn:population":0,
    "gn:timezone":"Asia/Kolkata",
    "iso:country":"IN",
    "ks:ks_name":"Jhalar Sarai",
    "ks:ks_pop":193,
    "ks:ks_type":"HABITATION",
    "name:eng_x_preferred":[
        "Jhalar Sarai"
    ],
    "name:eng_x_variant":[
        "Jhalarsarai"
    ],
    "wof:name":"Jhalar Sarai",
    "wof:placetype":"locality",
    "wof:population":193
},
  "geometry": {"coordinates":[83.194221,24.015866],"type":"Point"}
}