{
  "type": "Feature",
  "properties": {
    "iso:country":"IN",
    "ks:ks_name":"Malahi Tola",
    "ks:ks_pop":117,
    "ks:ks_type":"HABITATION",
    "name:eng_x_preferred":[
        "Malahi Tola"
    ],
    "wof:name":"Malahi Tola",
    "wof:placetype":"locality",
    "wof:population":117
},
  "geometry": {"coordinates":[84.493886,26.497479],"type":"Point"}
}