{
  "type": "Feature",
  "properties": {
    "gn:admin1_code":"36",
    "gn:admin2_code":"199.0",
    "gn:asciiname":"Marihan",
    "gn:country_code":"IN",
    "gn:dem":255,
    "gn:feature_class":"P",
    "gn:feature_code":"PPL",
    "gn:name":"Marih\u0101n",
    "gn:population":0,
    "gn:timezone":"Asia/Kolkata",
    "iso:country":"IN",
    "name:und_x_variant":[
        "Marih\u0101n",
        "Mari\u0101han"
    ],
    "wof:name":"Marihan",
    "wof:placetype":"locality"
},
  "geometry": {"coordinates":[82.68701,24.92919],"type":"Point"}
}