{
  "type": "Feature",
  "properties": {
    "gn:admin1_code":"36.0",
    "gn:admin2_code":"160",
    "gn:asciiname":"Pakra",
    "gn:country_code":"IN",
    "gn:dem":141,
    "gn:feature_class":"P",
    "gn:feature_code":"PPL",
    "gn:name":"Pakra",
    "gn:population":0,
    "gn:timezone":"Asia/Kolkata",
    "iso:country":"IN",
    "name:hrv_x_preferred":[
        "Pakra"
    ],
    "name:spa_x_preferred":[
        "R\u00edo Pakra"
    ],
    "name:zho_x_preferred":[
        "\u5e15\u514b\u62c9\u6cb3"
    ],
    "wof:name":"Pakra",
    "wof:placetype":"locality"
},
  "geometry": {"coordinates":[79.78603000000003,27.1347],"type":"Point"}
}