{
  "type": "Feature",
  "properties": {
    "iso:country":"IN",
    "ks:ks_name":"Nagla Shivlal",
    "ks:ks_pop":525,
    "ks:ks_type":"HABITATION",
    "ks:ks_uagg_main":0,
    "name:eng_x_preferred":[
        "Nagla Shivlal"
    ],
    "wof:name":"Nagla Shivlal",
    "wof:placetype":"neighbourhood",
    "wof:population":525
},
  "geometry": {"coordinates":[78.090175,27.073643],"type":"Point"}
}