{
  "type": "Feature",
  "properties": {
    "iso:country":"IN",
    "ks:ks_name":"Nathoon",
    "ks:ks_pop":1076,
    "ks:ks_type":"HABITATION",
    "name:eng_x_preferred":[
        "Nathoon"
    ],
    "wof:name":"Nathoon",
    "wof:placetype":"locality",
    "wof:population":1076
},
  "geometry": {"coordinates":[75.317847,25.532375],"type":"Point"}
}