{
  "type": "Feature",
  "properties": {
    "gn:admin1_code":"36.0",
    "gn:admin2_code":"167",
    "gn:asciiname":"Buti",
    "gn:country_code":"IN",
    "gn:dem":352,
    "gn:feature_class":"P",
    "gn:feature_code":"PPL",
    "gn:name":"B\u016bti",
    "gn:population":0,
    "gn:timezone":"Asia/Kolkata",
    "iso:country":"IN",
    "wof:name":"Buti",
    "wof:placetype":"locality"
},
  "geometry": {"coordinates":[78.68040000000001,24.69805],"type":"Point"}
}