{
  "type": "Feature",
  "properties": {
    "iso:country":"IN",
    "ks:ks_name":"Chepakkam",
    "ks:ks_pop":118,
    "ks:ks_type":"HABITATION",
    "name:eng_x_preferred":[
        "Chepakkam"
    ],
    "wof:name":"Chepakkam",
    "wof:placetype":"locality",
    "wof:population":118
},
  "geometry": {"coordinates":[80.30371599999999,13.278142],"type":"Point"}
}