{
  "type": "Feature",
  "properties": {
    "gn:admin1_code":"28",
    "gn:admin2_code":"338.0",
    "gn:asciiname":"Mandra",
    "gn:country_code":"IN",
    "gn:dem":10,
    "gn:feature_class":"P",
    "gn:feature_code":"PPL",
    "gn:name":"M\u0101ndr\u0101",
    "gn:population":0,
    "gn:timezone":"Asia/Kolkata",
    "iso:country":"IN",
    "name:ara_x_preferred":[
        "\u0645\u0627\u0646\u062f\u0631\u0627"
    ],
    "name:bul_x_preferred":[
        "\u041c\u0430\u043d\u0434\u0440\u0430"
    ],
    "name:ceb_x_preferred":[
        "M\u00e1ndra"
    ],
    "name:ell_x_preferred":[
        "\u0394\u03ae\u03bc\u03bf\u03c2 \u039c\u03ac\u03bd\u03b4\u03c1\u03b1\u03c2"
    ],
    "name:fin_x_preferred":[
        "M\u00e1ndra"
    ],
    "name:hye_x_preferred":[
        "\u0544\u0561\u0576\u0564\u0580\u0561"
    ],
    "name:ita_x_preferred":[
        "Mandra"
    ],
    "name:nno_x_preferred":[
        "M\u00e1ndra"
    ],
    "name:swe_x_preferred":[
        "M\u00e1ndra"
    ],
    "name:tur_x_preferred":[
        "Mandra"
    ],
    "name:urd_x_preferred":[
        "\u0645\u0627\u0646\u062f\u0631\u0627"
    ],
    "name:vie_x_preferred":[
        "M\u00e2ndra"
    ],
    "wof:name":"Mandra",
    "wof:placetype":"locality"
},
  "geometry": {"coordinates":[88.08333,22.83333],"type":"Point"}
}