{
  "type": "Feature",
  "properties": {
    "iso:country":"IN",
    "ks:ks_name":"Beerampura",
    "ks:ks_pop":337,
    "ks:ks_type":"HABITATION",
    "name:eng_x_preferred":[
        "Beerampura"
    ],
    "wof:name":"Beerampura",
    "wof:placetype":"locality",
    "wof:population":337
},
  "geometry": {"coordinates":[76.760288,23.929103],"type":"Point"}
}