{
  "type": "Feature",
  "properties": {
    "iso:country":"IN",
    "ks:ks_name":"Ambaliyara",
    "ks:ks_pop":340,
    "ks:ks_type":"HABITATION",
    "name:eng_x_preferred":[
        "Ambaliyara"
    ],
    "wof:name":"Ambaliyara",
    "wof:placetype":"locality",
    "wof:population":340
},
  "geometry": {"coordinates":[73.240639,23.659278],"type":"Point"}
}