{
  "type": "Feature",
  "properties": {
    "iso:country":"IN",
    "ks:ks_name":"Mulluhakkal",
    "ks:ks_pop":30,
    "ks:ks_type":"HABITATION",
    "name:eng_x_preferred":[
        "Mulluhakkal"
    ],
    "wof:name":"Mulluhakkal",
    "wof:placetype":"locality",
    "wof:population":30
},
  "geometry": {"coordinates":[74.604855,14.82788],"type":"Point"}
}