{
  "type": "Feature",
  "properties": {
    "iso:country":"IN",
    "ks:ks_name":"Ghahi Gaon",
    "ks:ks_pop":1006,
    "ks:ks_type":"VILLAGE",
    "name:eng_x_preferred":[
        "Ghahi Gaon"
    ],
    "wof:name":"Ghahi Gaon",
    "wof:placetype":"locality",
    "wof:population":1006
},
  "geometry": {"coordinates":[93.494131,26.843855],"type":"Point"}
}