{
  "type": "Feature",
  "properties": {
    "gn:admin1_code":"17.0",
    "gn:admin2_code":"278.0",
    "gn:asciiname":"Sengmai",
    "gn:country_code":"IN",
    "gn:dem":823,
    "gn:feature_class":"P",
    "gn:feature_code":"PPL",
    "gn:name":"Sengmai",
    "gn:population":0,
    "gn:timezone":"Asia/Kolkata",
    "iso:country":"IN",
    "wof:name":"Sengmai",
    "wof:placetype":"locality"
},
  "geometry": {"coordinates":[93.8814,24.94563],"type":"Point"}
}