{
  "type": "Feature",
  "properties": {
    "gn:admin1_code":"35",
    "gn:admin2_code":"426.0",
    "gn:asciiname":"Dighaura",
    "gn:country_code":"IN",
    "gn:dem":354,
    "gn:feature_class":"P",
    "gn:feature_code":"PPL",
    "gn:name":"Dighaura",
    "gn:population":0,
    "gn:timezone":"Asia/Kolkata",
    "iso:country":"IN",
    "ks:ks_name":"Dighaura",
    "ks:ks_pop":303,
    "ks:ks_type":"HABITATION",
    "name:eng_x_preferred":[
        "Dighaura"
    ],
    "wof:name":"Dighaura",
    "wof:placetype":"locality",
    "wof:population":303
},
  "geometry": {"coordinates":[80.26731599999999,24.411928],"type":"Point"}
}