{
  "type": "Feature",
  "properties": {
    "gn:admin1_code":"39.0",
    "gn:admin2_code":"61.0",
    "gn:asciiname":"Simkholi",
    "gn:country_code":"IN",
    "gn:dem":1540,
    "gn:feature_class":"P",
    "gn:feature_code":"PPL",
    "gn:name":"Simkholi",
    "gn:population":0,
    "gn:timezone":"Asia/Kolkata",
    "iso:country":"IN",
    "wof:name":"Simkholi",
    "wof:placetype":"locality"
},
  "geometry": {"coordinates":[79.04368000000002,29.93599],"type":"Point"}
}