{
  "type": "Feature",
  "properties": {
    "gn:admin1_code":"39.0",
    "gn:admin2_code":"61.0",
    "gn:asciiname":"Simkholi",
    "gn:country_code":"IN",
    "gn:dem":1540,
    "gn:feature_class":"P",
    "gn:feature_code":"PPL",
    "gn:name":"Simkholi",
    "gn:population":0,
    "gn:timezone":"Asia/Kolkata",
    "iso:country":"IN",
    "ks:ks_name":"Simkholi",
    "ks:ks_pop":70,
    "ks:ks_type":"VILLAGE",
    "name:eng_x_preferred":[
        "Simkholi"
    ],
    "wof:name":"Simkholi",
    "wof:placetype":"locality",
    "wof:population":70
},
  "geometry": {"coordinates":[79.043001,29.935144],"type":"Point"}
}