{
  "type": "Feature",
  "properties": {
    "gn:admin1_code":"28.0",
    "gn:admin2_code":"327.0",
    "gn:asciiname":"Sherbator",
    "gn:country_code":"IN",
    "gn:dem":1622,
    "gn:feature_class":"P",
    "gn:feature_code":"PPL",
    "gn:name":"Sherb\u0101t\u014dr",
    "gn:population":0,
    "gn:timezone":"Asia/Kolkata",
    "iso:country":"IN",
    "wof:name":"Sherbator",
    "wof:placetype":"locality"
},
  "geometry": {"coordinates":[88.6707,27.05745],"type":"Point"}
}