{
  "type": "Feature",
  "properties": {
    "gn:admin1_code":"35.0",
    "gn:admin2_code":"457.0",
    "gn:asciiname":"Katorli",
    "gn:country_code":"IN",
    "gn:dem":341,
    "gn:feature_class":"P",
    "gn:feature_code":"PPL",
    "gn:name":"K\u0101torl\u012b",
    "gn:population":0,
    "gn:timezone":"Asia/Kolkata",
    "iso:country":"IN",
    "ks:ks_name":"Katurli",
    "ks:ks_pop":86,
    "ks:ks_type":"HABITATION",
    "name:eng_x_preferred":[
        "Katurli"
    ],
    "name:eng_x_variant":[
        "Katorli"
    ],
    "wof:name":"Katurli",
    "wof:placetype":"locality",
    "wof:population":86
},
  "geometry": {"coordinates":[80.19998,22.045036],"type":"Point"}
}