{
  "type": "Feature",
  "properties": {
    "iso:country":"IN",
    "ks:ks_alt_nam":"KISHAN KOBRA",
    "ks:ks_name":"Kishan Kobra",
    "ks:ks_pop":229,
    "ks:ks_type":"HABITATION",
    "name:eng_x_preferred":[
        "Kishan Kobra"
    ],
    "wof:name":"Kishan Kobra",
    "wof:placetype":"locality",
    "wof:population":229
},
  "geometry": {"coordinates":[91.381383,23.882725],"type":"Point"}
}