{
  "type": "Feature",
  "properties": {
    "iso:country":"IN",
    "ks:ks_name":"Rain",
    "ks:ks_pop":4471,
    "ks:ks_type":"VILLAGE",
    "name:eng_x_preferred":[
        "Rain"
    ],
    "wof:name":"Rain",
    "wof:placetype":"locality",
    "wof:population":4471
},
  "geometry": {"coordinates":[87.867133,22.470615],"type":"Point"}
}