{
  "type": "Feature",
  "properties": {
    "iso:country":"IN",
    "ks:ks_name":"Busiputtu",
    "ks:ks_pop":48,
    "ks:ks_type":"HABITATION",
    "name:eng_x_preferred":[
        "Busiputtu"
    ],
    "wof:name":"Busiputtu",
    "wof:placetype":"locality",
    "wof:population":48
},
  "geometry": {"coordinates":[82.674592,18.245939],"type":"Point"}
}