{
  "type": "Feature",
  "properties": {
    "iso:country":"IN",
    "ks:ks_name":"Madiga Wada",
    "ks:ks_pop":31,
    "ks:ks_type":"HABITATION",
    "name:eng_x_preferred":[
        "Madiga Wada"
    ],
    "wof:name":"Madiga Wada",
    "wof:placetype":"locality",
    "wof:population":31
},
  "geometry": {"coordinates":[79.638234,13.335953],"type":"Point"}
}