{
  "type": "Feature",
  "properties": {
    "iso:country":"IN",
    "ks:ks_name":"Nisahara Milik",
    "ks:ks_pop":1180,
    "ks:ks_type":"VILLAGE",
    "ks:ks_uagg_main":0,
    "name:eng_x_preferred":[
        "Nisahara Milik"
    ],
    "wof:name":"Nisahara Milik",
    "wof:placetype":"neighbourhood",
    "wof:population":1180
},
  "geometry": {"coordinates":[87.395267,25.504259],"type":"Point"}
}