{
  "type": "Feature",
  "properties": {
    "iso:country":"IN",
    "ks:ks_name":"Manimala",
    "ks:ks_pop":546,
    "ks:ks_type":"HABITATION",
    "name:eng_x_preferred":[
        "Manimala"
    ],
    "wof:name":"Manimala",
    "wof:placetype":"locality",
    "wof:population":546
},
  "geometry": {"coordinates":[75.719638,11.610312],"type":"Point"}
}