{
  "type": "Feature",
  "properties": {
    "iso:country":"IN",
    "ks:ks_name":"Arjunpur Alias Amkhoh",
    "ks:ks_pop":1377,
    "ks:ks_type":"VILLAGE",
    "name:eng_x_preferred":[
        "Arjunpur Alias Amkhoh"
    ],
    "wof:name":"Arjunpur Alias Amkhoh",
    "wof:placetype":"locality",
    "wof:population":1377
},
  "geometry": {"coordinates":[82.616456,23.109318],"type":"Point"}
}