{
  "type": "Feature",
  "properties": {
    "iso:country":"IN",
    "ks:ks_name":"Thoppur Checkpost",
    "ks:ks_pop":801,
    "ks:ks_type":"HABITATION",
    "ks:ks_uagg_main":0,
    "name:eng_x_preferred":[
        "Thoppur Checkpost"
    ],
    "wof:name":"Thoppur Checkpost",
    "wof:placetype":"neighbourhood",
    "wof:population":801
},
  "geometry": {"coordinates":[78.04692900000001,11.947392],"type":"Point"}
}