{
  "type": "Feature",
  "properties": {
    "iso:country":"IN",
    "ks:ks_name":"Talia Coloney",
    "ks:ks_pop":796,
    "ks:ks_type":"HABITATION",
    "name:eng_x_preferred":[
        "Talia Coloney"
    ],
    "wof:name":"Talia Coloney",
    "wof:placetype":"locality",
    "wof:population":796
},
  "geometry": {"coordinates":[92.040553,24.219951],"type":"Point"}
}