{
  "type": "Feature",
  "properties": {
    "iso:country":"IN",
    "ks:ks_name":"Chorgali",
    "ks:ks_pop":547,
    "ks:ks_type":"VILLAGE",
    "name:eng_x_preferred":[
        "Chorgali"
    ],
    "wof:name":"Chorgali",
    "wof:placetype":"locality",
    "wof:population":547
},
  "geometry": {"coordinates":[86.551868,23.28253],"type":"Point"}
}