{
  "type": "Feature",
  "properties": {
    "gn:admin1_code":"23",
    "gn:admin2_code":"36.0",
    "gn:asciiname":"Akala",
    "gn:country_code":"IN",
    "gn:dem":232,
    "gn:feature_class":"P",
    "gn:feature_code":"PPL",
    "gn:name":"Ak\u0101la",
    "gn:population":0,
    "gn:timezone":"Asia/Kolkata",
    "iso:country":"IN",
    "name:srp_x_preferred":[
        "\u0410\u043a\u0430\u043b\u0430"
    ],
    "wof:name":"Akala",
    "wof:placetype":"locality"
},
  "geometry": {"coordinates":[75.53598000000002,31.56048],"type":"Point"}
}