{
  "type": "Feature",
  "properties": {
    "iso:country":"IN",
    "ks:ks_name":"Madhupurnaugava",
    "ks:ks_pop":45,
    "ks:ks_type":"VILLAGE",
    "name:eng_x_preferred":[
        "Madhupurnaugava"
    ],
    "wof:name":"Madhupurnaugava",
    "wof:placetype":"locality",
    "wof:population":45
},
  "geometry": {"coordinates":[79.66546700000001,27.340362],"type":"Point"}
}