{
  "type": "Feature",
  "properties": {
    "gn:admin1_code":"19.0",
    "gn:admin2_code":"573.0",
    "gn:asciiname":"Agatahalli",
    "gn:country_code":"IN",
    "gn:dem":762,
    "gn:feature_class":"P",
    "gn:feature_code":"PPL",
    "gn:name":"Agatahalli",
    "gn:population":0,
    "gn:timezone":"Asia/Kolkata",
    "iso:country":"IN",
    "name:fas_x_preferred":[
        "\u0627\u06af\u0627\u062a\u0647\u0627\u0644\u06cc"
    ],
    "name:vie_x_preferred":[
        "Agatahalli"
    ],
    "wof:name":"Agatahalli",
    "wof:placetype":"locality"
},
  "geometry": {"coordinates":[76.78421999999998,12.52326],"type":"Point"}
}