{
  "type": "Feature",
  "properties": {
    "gn:country":"IN",
    "gn:fcode":"PPL",
    "gn:pop":7472,
    "iso:country":"IN",
    "name:ben_x_preferred":[
        "\u0995\u09be\u09a6\u09bf\u09aa\u09c1\u09b0"
    ],
    "name:bpy_x_preferred":[
        "\u0995\u09be\u09a6\u09bf\u09aa\u09c1\u09b0"
    ],
    "name:deu_x_preferred":[
        "Kadipur"
    ],
    "name:eng_x_preferred":[
        "Kadipur"
    ],
    "name:fra_x_preferred":[
        "Kadipur"
    ],
    "name:guj_x_preferred":[
        "\u0a95\u0aa1\u0ac0\u0aaa\u0ac1\u0ab0"
    ],
    "name:hin_x_preferred":[
        "\u0915\u093e\u0926\u0940\u092a\u0941\u0930"
    ],
    "name:ita_x_preferred":[
        "Kadipur"
    ],
    "name:jpn_x_preferred":[
        "\u30ab\u30c7\u30a3\u30d7\u30fc\u30eb"
    ],
    "name:kan_x_preferred":[
        "\u0c95\u0ca1\u0cbf\u0caa\u0cc1\u0cb0\u0ccd"
    ],
    "name:kor_x_preferred":[
        "\uce74\ub514\ud478\ub974"
    ],
    "name:mlg_x_preferred":[
        "Kadipur"
    ],
    "name:msa_x_preferred":[
        "Kadipur"
    ],
    "name:nan_x_preferred":[
        "Kadipur"
    ],
    "name:new_x_preferred":[
        "\u0915\u093e\u0921\u093f\u092a\u0941\u0930"
    ],
    "name:nld_x_preferred":[
        "Kadipur"
    ],
    "name:pol_x_preferred":[
        "Kadipur"
    ],
    "name:por_x_preferred":[
        "Kadipur"
    ],
    "name:rus_x_preferred":[
        "\u041a\u0430\u0434\u0438\u043f\u0443\u0440"
    ],
    "name:spa_x_preferred":[
        "Kadipur"
    ],
    "name:swe_x_preferred":[
        "K\u0101d\u012bpur"
    ],
    "name:tam_x_preferred":[
        "\u0b95\u0b9f\u0bbf\u0baa\u0bcd\u0baa\u0bc2\u0bb0\u0bcd"
    ],
    "name:tel_x_preferred":[
        "\u0c15\u0c21\u0c3f\u0c2a\u0c42\u0c30\u0c4d"
    ],
    "name:unk_x_variant":[
        "K\u0101d\u012bpur"
    ],
    "name:urd_x_preferred":[
        "\u06a9\u062f\u06cc \u067e\u0648\u0631"
    ],
    "name:vie_x_preferred":[
        "Kadipur"
    ],
    "name:zho_x_preferred":[
        "\u5361\u8fea\u666e\u5c14"
    ],
    "qs:name":"Kadipur",
    "qs:name_adm0":"India",
    "qs:name_adm1":"Uttar Pradesh",
    "qs:photos_9r":0,
    "qs:photos_sr":0,
    "qs:placetype":"Town",
    "qs:pop_sr":"5",
    "wd:wordcount":515,
    "wof:name":"Kadipur",
    "wof:placetype":"locality",
    "wof:population":7472
},
  "geometry": {"coordinates":[82.37027999999999,26.16779],"type":"Point"}
}