{
  "type": "Feature",
  "properties": {
    "iso:country":"IN",
    "ks:ks_alt_nam":"HONGROTOLI",
    "ks:ks_name":"Hongrotoli",
    "ks:ks_pop":190,
    "ks:ks_type":"HABITATION",
    "name:eng_x_preferred":[
        "Hongrotoli"
    ],
    "wof:name":"Hongrotoli",
    "wof:placetype":"locality",
    "wof:population":190
},
  "geometry": {"coordinates":[83.919719,22.644826],"type":"Point"}
}