{
  "type": "Feature",
  "properties": {
    "iso:country":"IN",
    "ks:ks_name":"Deoulkond",
    "ks:ks_pop":75,
    "ks:ks_type":"HABITATION",
    "name:eng_x_preferred":[
        "Deoulkond"
    ],
    "wof:name":"Deoulkond",
    "wof:placetype":"locality",
    "wof:population":75
},
  "geometry": {"coordinates":[73.51433299999999,18.087389],"type":"Point"}
}