{
  "type": "Feature",
  "properties": {
    "gn:admin1_code":"36",
    "gn:admin2_code":"176.0",
    "gn:asciiname":"Asai",
    "gn:country_code":"IN",
    "gn:dem":118,
    "gn:feature_class":"P",
    "gn:feature_code":"PPL",
    "gn:name":"Asai",
    "gn:population":0,
    "gn:timezone":"Asia/Kolkata",
    "iso:country":"IN",
    "name:ceb_x_preferred":[
        "Asai"
    ],
    "name:deu_x_preferred":[
        "Asai"
    ],
    "name:nld_x_preferred":[
        "Asai"
    ],
    "wof:name":"Asai",
    "wof:placetype":"locality"
},
  "geometry": {"coordinates":[81.1767,26.86803],"type":"Point"}
}