{
  "type": "Feature",
  "properties": {
    "iso:country":"IN",
    "ks:ks_name":"Gweeth Gaon",
    "ks:ks_pop":465,
    "ks:ks_type":"VILLAGE",
    "name:eng_x_preferred":[
        "Gweeth Gaon"
    ],
    "wof:name":"Gweeth Gaon",
    "wof:placetype":"locality",
    "wof:population":465
},
  "geometry": {"coordinates":[79.01528399999999,30.106049],"type":"Point"}
}