{
  "type": "Feature",
  "properties": {
    "gn:admin1_code":"39",
    "gn:admin2_code":"61.0",
    "gn:asciiname":"Tandion",
    "gn:country_code":"IN",
    "gn:dem":1567,
    "gn:feature_class":"P",
    "gn:feature_code":"PPL",
    "gn:name":"T\u0101ndion",
    "gn:population":0,
    "gn:timezone":"Asia/Kolkata",
    "iso:country":"IN",
    "ks:ks_alt_nam":"T\u0101ndion",
    "ks:ks_name":"Tandion",
    "ks:ks_type":"VILLAGE",
    "name:eng_x_preferred":[
        "Tandion"
    ],
    "name:eng_x_variant":[
        "T\u0101ndion"
    ],
    "wof:name":"Tandion",
    "wof:placetype":"locality"
},
  "geometry": {"coordinates":[78.939545,29.793215],"type":"Point"}
}