{
  "type": "Feature",
  "properties": {
    "iso:country":"IN",
    "ks:ks_name":"Radha Ballabhpur",
    "ks:ks_pop":453,
    "ks:ks_type":"VILLAGE",
    "name:eng_x_preferred":[
        "Radha Ballabhpur"
    ],
    "wof:name":"Radha Ballabhpur",
    "wof:placetype":"locality",
    "wof:population":453
},
  "geometry": {"coordinates":[87.65217,22.591976],"type":"Point"}
}