{
  "type": "Feature",
  "properties": {
    "iso:country":"IN",
    "ks:ks_name":"Bamun Teron",
    "ks:ks_pop":246,
    "ks:ks_type":"HABITATION",
    "ks:ks_uagg_main":0,
    "name:eng_x_preferred":[
        "Bamun Teron"
    ],
    "wof:name":"Bamun Teron",
    "wof:placetype":"neighbourhood",
    "wof:population":246
},
  "geometry": {"coordinates":[93.43727,26.583186],"type":"Point"}
}