{
  "type": "Feature",
  "properties": {
    "gn:admin1_code":"19",
    "gn:admin2_code":"580.0",
    "gn:asciiname":"Hegganadoddi",
    "gn:country_code":"IN",
    "gn:dem":430,
    "gn:feature_class":"P",
    "gn:feature_code":"PPL",
    "gn:name":"Hegganadoddi",
    "gn:population":0,
    "gn:timezone":"Asia/Kolkata",
    "iso:country":"IN",
    "wof:name":"Hegganadoddi",
    "wof:placetype":"locality"
},
  "geometry": {"coordinates":[76.63231999999998,16.59504],"type":"Point"}
}