{
  "type": "Feature",
  "properties": {
    "iso:country":"IN",
    "ks:ks_name":"Raghunathpur",
    "ks:ks_pop":296,
    "ks:ks_type":"VILLAGE",
    "name:eng_x_preferred":[
        "Raghunathpur"
    ],
    "wof:name":"Raghunathpur",
    "wof:placetype":"locality",
    "wof:population":296
},
  "geometry": {"coordinates":[87.632901,24.759986],"type":"Point"}
}