{
  "type": "Feature",
  "properties": {
    "iso:country":"IN",
    "ks:ks_name":"Subhashnagar",
    "ks:ks_pop":714,
    "ks:ks_type":"HABITATION",
    "name:eng_x_preferred":[
        "Subhashnagar"
    ],
    "wof:name":"Subhashnagar",
    "wof:placetype":"locality",
    "wof:population":714
},
  "geometry": {"coordinates":[71.637603,26.523561],"type":"Point"}
}