{
  "type": "Feature",
  "properties": {
    "iso:country":"IN",
    "ks:ks_name":"Tambadwadi",
    "ks:ks_pop":132,
    "ks:ks_type":"HABITATION",
    "name:eng_x_preferred":[
        "Tambadwadi"
    ],
    "wof:name":"Tambadwadi",
    "wof:placetype":"locality",
    "wof:population":132
},
  "geometry": {"coordinates":[73.378889,17.536389],"type":"Point"}
}