{
  "type": "Feature",
  "properties": {
    "gn:admin1_code":"38.0",
    "gn:admin2_code":"351.0",
    "gn:asciiname":"Satbandha",
    "gn:country_code":"IN",
    "gn:dem":136,
    "gn:feature_class":"P",
    "gn:feature_code":"PPL",
    "gn:name":"S\u0101tbandha",
    "gn:population":0,
    "gn:timezone":"Asia/Kolkata",
    "iso:country":"IN",
    "ks:ks_name":"Sat Bandha",
    "ks:ks_pop":802,
    "ks:ks_type":"VILLAGE",
    "name:eng_x_preferred":[
        "Sat Bandha"
    ],
    "name:eng_x_variant":[
        "Satbandha"
    ],
    "wof:name":"Sat Bandha",
    "wof:placetype":"locality",
    "wof:population":802
},
  "geometry": {"coordinates":[87.144364,24.737388],"type":"Point"}
}