{
  "type": "Feature",
  "properties": {
    "iso:country":"IN",
    "ks:ks_name":"Sanachandrasekharpur",
    "ks:ks_pop":192,
    "ks:ks_type":"VILLAGE",
    "name:eng_x_preferred":[
        "Sanachandrasekharpur"
    ],
    "wof:name":"Sanachandrasekharpur",
    "wof:placetype":"locality",
    "wof:population":192
},
  "geometry": {"coordinates":[85.555835,19.96559],"type":"Point"}
}