{
  "type": "Feature",
  "properties": {
    "iso:country":"IN",
    "ks:ks_name":"Kathoutiya A",
    "ks:ks_pop":147,
    "ks:ks_type":"HABITATION",
    "name:eng_x_preferred":[
        "Kathoutiya A"
    ],
    "wof:name":"Kathoutiya A",
    "wof:placetype":"locality",
    "wof:population":147
},
  "geometry": {"coordinates":[79.243556,22.848865],"type":"Point"}
}