{
  "type": "Feature",
  "properties": {
    "iso:country":"IN",
    "ks:ks_name":"Virpurpada",
    "ks:ks_pop":355,
    "ks:ks_type":"VILLAGE",
    "name:eng_x_preferred":[
        "Virpurpada"
    ],
    "wof:name":"Virpurpada",
    "wof:placetype":"locality",
    "wof:population":355
},
  "geometry": {"coordinates":[75.159659,22.476124],"type":"Point"}
}