{
  "type": "Feature",
  "properties": {
    "iso:country":"IN",
    "ks:ks_name":"Lawadag",
    "ks:ks_pop":1157,
    "ks:ks_type":"VILLAGE",
    "ks:ks_uagg_main":0,
    "name:eng_x_preferred":[
        "Lawadag"
    ],
    "wof:name":"Lawadag",
    "wof:placetype":"neighbourhood",
    "wof:population":1157
},
  "geometry": {"coordinates":[84.05944100000001,24.428388],"type":"Point"}
}