{
  "type": "Feature",
  "properties": {
    "gn:admin1_code":"36.0",
    "gn:admin2_code":"161",
    "gn:asciiname":"Alampur Taraia",
    "gn:country_code":"IN",
    "gn:dem":151,
    "gn:feature_class":"P",
    "gn:feature_code":"PPL",
    "gn:name":"\u0100lampur Taraia",
    "gn:population":0,
    "gn:timezone":"Asia/Kolkata",
    "iso:country":"IN",
    "name:und_x_variant":[
        "\u0100lampur Taraia",
        "\u0100lampur"
    ],
    "wof:name":"Alampur Taraia",
    "wof:placetype":"locality"
},
  "geometry": {"coordinates":[79.18516,26.81234000000001],"type":"Point"}
}