{
  "type": "Feature",
  "properties": {
    "gn:admin1_code":"36",
    "gn:admin2_code":"194.0",
    "gn:asciiname":"Ghandi Gahna",
    "gn:country_code":"IN",
    "gn:dem":86,
    "gn:feature_class":"P",
    "gn:feature_code":"PPL",
    "gn:name":"Gh\u0101ndi Gahna",
    "gn:population":0,
    "gn:timezone":"Asia/Kolkata",
    "iso:country":"IN",
    "ks:ks_name":"Chandi Gahna",
    "ks:ks_pop":906,
    "ks:ks_type":"VILLAGE",
    "ks:ks_uagg_main":0,
    "name:eng_x_preferred":[
        "Chandi Gahna"
    ],
    "wof:name":"Chandi Gahna",
    "wof:placetype":"neighbourhood",
    "wof:population":906
},
  "geometry": {"coordinates":[82.74368800000001,25.809992],"type":"Point"}
}