{
  "type": "Feature",
  "properties": {
    "iso:country":"IN",
    "ks:ks_name":"Dumri",
    "ks:ks_pop":75,
    "ks:ks_type":"VILLAGE",
    "name:eng_x_preferred":[
        "Dumri"
    ],
    "wof:name":"Dumri",
    "wof:placetype":"locality",
    "wof:population":75
},
  "geometry": {"coordinates":[85.297022,24.118521],"type":"Point"}
}