{
  "type": "Feature",
  "properties": {
    "gn:admin1_code":"2.0",
    "gn:admin2_code":"543.0",
    "gn:asciiname":"Chintapallepeta",
    "gn:country_code":"IN",
    "gn:dem":93,
    "gn:feature_class":"P",
    "gn:feature_code":"PPL",
    "gn:name":"Chint\u0101pallepeta",
    "gn:population":0,
    "gn:timezone":"Asia/Kolkata",
    "iso:country":"IN",
    "ks:ks_name":"Chinthapallipeta",
    "ks:ks_pop":649,
    "ks:ks_type":"VILLAGE",
    "ks:ks_uagg_main":0,
    "name:eng_x_preferred":[
        "Chinthapallipeta"
    ],
    "wof:name":"Chinthapallipeta",
    "wof:placetype":"neighbourhood",
    "wof:population":649
},
  "geometry": {"coordinates":[83.525963,18.274149],"type":"Point"}
}