{
  "type": "Feature",
  "properties": {
    "gn:admin1_code":"24.0",
    "gn:admin2_code":"108.0",
    "gn:asciiname":"Gujar Baroda",
    "gn:country_code":"IN",
    "gn:dem":255,
    "gn:feature_class":"P",
    "gn:feature_code":"PPL",
    "gn:name":"G\u016bjar Baroda",
    "gn:population":0,
    "gn:timezone":"Asia/Kolkata",
    "iso:country":"IN",
    "wof:name":"Gujar Baroda",
    "wof:placetype":"locality"
},
  "geometry": {"coordinates":[76.60448000000002,26.48046],"type":"Point"}
}