{
  "type": "Feature",
  "properties": {
    "gn:admin1_code":"25.0",
    "gn:admin2_code":"613.0",
    "gn:asciiname":"Papparvalasu",
    "gn:country_code":"IN",
    "gn:dem":176,
    "gn:feature_class":"P",
    "gn:feature_code":"PPL",
    "gn:name":"P\u0101pp\u0101rvalasu",
    "gn:population":0,
    "gn:timezone":"Asia/Kolkata",
    "iso:country":"IN",
    "wof:name":"Papparvalasu",
    "wof:placetype":"locality"
},
  "geometry": {"coordinates":[77.81770999999998,11.04972],"type":"Point"}
}