{
  "type": "Feature",
  "properties": {
    "iso:country":"IN",
    "ks:ks_name":"Mathni",
    "ks:ks_pop":15,
    "ks:ks_type":"VILLAGE",
    "name:eng_x_preferred":[
        "Mathni"
    ],
    "wof:name":"Mathni",
    "wof:placetype":"locality",
    "wof:population":15
},
  "geometry": {"coordinates":[77.167766,22.462263],"type":"Point"}
}