{
  "type": "Feature",
  "properties": {
    "iso:country":"IN",
    "ks:ks_name":"Magalu Hosakoppa",
    "ks:ks_pop":41,
    "ks:ks_type":"HABITATION",
    "name:eng_x_preferred":[
        "Magalu Hosakoppa"
    ],
    "wof:name":"Magalu Hosakoppa",
    "wof:placetype":"locality",
    "wof:population":41
},
  "geometry": {"coordinates":[75.20147900000001,13.435839],"type":"Point"}
}