{
  "type": "Feature",
  "properties": {
    "iso:country":"IN",
    "ks:ks_name":"Balisuch",
    "ks:ks_pop":330,
    "ks:ks_type":"HABITATION",
    "name:eng_x_preferred":[
        "Balisuch"
    ],
    "wof:name":"Balisuch",
    "wof:placetype":"locality",
    "wof:population":330
},
  "geometry": {"coordinates":[87.25976300000001,22.051254],"type":"Point"}
}