{
  "type": "Feature",
  "properties": {
    "gn:admin1_code":"38",
    "gn:admin2_code":"358.0",
    "gn:asciiname":"Sarja",
    "gn:country_code":"IN",
    "gn:dem":387,
    "gn:feature_class":"P",
    "gn:feature_code":"PPL",
    "gn:name":"Sarj\u0101",
    "gn:population":0,
    "gn:timezone":"Asia/Kolkata",
    "iso:country":"IN",
    "ks:ks_alt_nam":"Sarj\u0101",
    "ks:ks_name":"Sarja",
    "ks:ks_pop":871,
    "ks:ks_type":"VILLAGE",
    "name:deu_x_preferred":[
        "Sarja"
    ],
    "name:eng_x_preferred":[
        "Sarja"
    ],
    "name:eng_x_variant":[
        "Sarj\u0101"
    ],
    "name:fin_x_preferred":[
        "Sarja"
    ],
    "name:lav_x_preferred":[
        "Sarja"
    ],
    "name:swe_x_preferred":[
        "Sarja"
    ],
    "wof:name":"Sarja",
    "wof:placetype":"locality",
    "wof:population":871
},
  "geometry": {"coordinates":[83.985795,23.883984],"type":"Point"}
}