{
  "type": "Feature",
  "properties": {
    "gn:admin1_code":"38",
    "gn:admin2_code":"358.0",
    "gn:asciiname":"Sarja",
    "gn:country_code":"IN",
    "gn:dem":387,
    "gn:feature_class":"P",
    "gn:feature_code":"PPL",
    "gn:name":"Sarj\u0101",
    "gn:population":0,
    "gn:timezone":"Asia/Kolkata",
    "iso:country":"IN",
    "wof:name":"Sarja",
    "wof:placetype":"locality"
},
  "geometry": {"coordinates":[83.98579000000002,23.88398],"type":"Point"}
}