{
  "type": "Feature",
  "properties": {
    "gn:admin1_code":"16.0",
    "gn:admin2_code":"530.0",
    "gn:asciiname":"Kurni Bujavade",
    "gn:country_code":"IN",
    "gn:dem":722,
    "gn:feature_class":"P",
    "gn:feature_code":"PPL",
    "gn:name":"Kurni Bujavade",
    "gn:population":0,
    "gn:timezone":"Asia/Kolkata",
    "iso:country":"IN",
    "wof:name":"Kurni Bujavade",
    "wof:placetype":"locality"
},
  "geometry": {"coordinates":[74.15275,15.99704],"type":"Point"}
}