{
  "type": "Feature",
  "properties": {
    "gn:admin1_code":"36.0",
    "gn:admin2_code":"149",
    "gn:asciiname":"Gura Barela",
    "gn:country_code":"IN",
    "gn:dem":156,
    "gn:feature_class":"P",
    "gn:feature_code":"PPL",
    "gn:name":"G\u016bra Barela",
    "gn:population":0,
    "gn:timezone":"Asia/Kolkata",
    "iso:country":"IN",
    "wof:name":"Gura Barela",
    "wof:placetype":"locality"
},
  "geometry": {"coordinates":[79.36549000000002,27.84646],"type":"Point"}
}