{
  "type": "Feature",
  "properties": {
    "gn:admin1_code":"23.0",
    "gn:admin2_code":"36.0",
    "gn:asciiname":"Shahwala",
    "gn:country_code":"IN",
    "gn:dem":210,
    "gn:feature_class":"P",
    "gn:feature_code":"PPL",
    "gn:name":"Sh\u0101hw\u0101la",
    "gn:population":0,
    "gn:timezone":"Asia/Kolkata",
    "iso:country":"IN",
    "ks:ks_alt_nam":"Sh\u0101hw\u0101la",
    "ks:ks_name":"Shahwala",
    "ks:ks_pop":32,
    "ks:ks_type":"VILLAGE",
    "name:eng_x_preferred":[
        "Shahwala"
    ],
    "name:eng_x_variant":[
        "Sh\u0101hw\u0101la"
    ],
    "wof:name":"Shahwala",
    "wof:placetype":"locality",
    "wof:population":32
},
  "geometry": {"coordinates":[75.055148,31.158049],"type":"Point"}
}