{
  "type": "Feature",
  "properties": {
    "gn:admin1_code":"25.0",
    "gn:admin2_code":"605.0",
    "gn:asciiname":"Lalapettai",
    "gn:country_code":"IN",
    "gn:dem":211,
    "gn:feature_class":"P",
    "gn:feature_code":"PPL",
    "gn:name":"L\u0101l\u0101pettai",
    "gn:population":0,
    "gn:timezone":"Asia/Kolkata",
    "iso:country":"IN",
    "name:und_x_variant":[
        "L\u0101l\u0101pettai",
        "Mukundar\u0101yapuram"
    ],
    "wof:name":"Lalapettai",
    "wof:placetype":"locality"
},
  "geometry": {"coordinates":[79.30324,12.99192],"type":"Point"}
}