{
  "type": "Feature",
  "properties": {
    "iso:country":"IN",
    "ks:ks_name":"Deega",
    "ks:ks_pop":838,
    "ks:ks_type":"HABITATION",
    "name:eng_x_preferred":[
        "Deega"
    ],
    "wof:name":"Deega",
    "wof:placetype":"locality",
    "wof:population":838
},
  "geometry": {"coordinates":[70.995903,27.530441],"type":"Point"}
}