{
  "type": "Feature",
  "properties": {
    "iso:country":"IN",
    "ks:ks_name":"Aralikere",
    "ks:ks_pop":1134,
    "ks:ks_type":"HABITATION",
    "name:eng_x_preferred":[
        "Aralikere"
    ],
    "wof:name":"Aralikere",
    "wof:placetype":"locality",
    "wof:population":1134
},
  "geometry": {"coordinates":[76.444316,13.55828],"type":"Point"}
}