{
  "type": "Feature",
  "properties": {
    "iso:country":"IN",
    "ks:ks_name":"Chimalilawa",
    "ks:ks_pop":280,
    "ks:ks_type":"HABITATION",
    "name:eng_x_preferred":[
        "Chimalilawa"
    ],
    "wof:name":"Chimalilawa",
    "wof:placetype":"locality",
    "wof:population":280
},
  "geometry": {"coordinates":[81.285775,18.406414],"type":"Point"}
}