{
  "type": "Feature",
  "properties": {
    "gn:admin1_code":"25.0",
    "gn:admin2_code":"604.0",
    "gn:asciiname":"Sirukkaveripakkam",
    "gn:country_code":"IN",
    "gn:dem":91,
    "gn:feature_class":"P",
    "gn:feature_code":"PPL",
    "gn:name":"Sirukk\u0101verip\u0101kkam",
    "gn:population":0,
    "gn:timezone":"Asia/Kolkata",
    "iso:country":"IN",
    "ks:ks_name":"Sirukaveripakkam",
    "ks:ks_pop":3874,
    "ks:ks_type":"URBAN",
    "ks:ks_uagg_main":0,
    "name:eng_x_preferred":[
        "Sirukaveripakkam"
    ],
    "wof:name":"Sirukaveripakkam",
    "wof:placetype":"neighbourhood",
    "wof:population":3874
},
  "geometry": {"coordinates":[79.677082,12.852877],"type":"Point"}
}