{
  "type": "Feature",
  "properties": {
    "iso:country":"IN",
    "ks:ks_name":"Sorisapokhari",
    "ks:ks_pop":59,
    "ks:ks_type":"VILLAGE",
    "name:eng_x_preferred":[
        "Sorisapokhari"
    ],
    "wof:name":"Sorisapokhari",
    "wof:placetype":"locality",
    "wof:population":59
},
  "geometry": {"coordinates":[86.33213000000001,20.196759],"type":"Point"}
}