{
  "type": "Feature",
  "properties": {
    "gn:admin1_code":"39.0",
    "gn:admin2_code":"061",
    "gn:asciiname":"Pokhri",
    "gn:country_code":"IN",
    "gn:dem":1099,
    "gn:feature_class":"P",
    "gn:feature_code":"PPL",
    "gn:name":"Pokhri",
    "gn:population":0,
    "gn:timezone":"Asia/Kolkata",
    "iso:country":"IN",
    "ks:ks_name":"Pokhri",
    "ks:ks_type":"VILLAGE",
    "name:eng_x_preferred":[
        "Pokhri"
    ],
    "wof:name":"Pokhri",
    "wof:placetype":"locality"
},
  "geometry": {"coordinates":[78.506896,29.819997],"type":"Point"}
}