{
  "type": "Feature",
  "properties": {
    "gn:admin1_code":"11.0",
    "gn:admin2_code":"26.0",
    "gn:asciiname":"Ghatu",
    "gn:country_code":"IN",
    "gn:dem":1312,
    "gn:feature_class":"P",
    "gn:feature_code":"PPL",
    "gn:name":"Gh\u0101tu",
    "gn:population":0,
    "gn:timezone":"Asia/Kolkata",
    "iso:country":"IN",
    "name:ben_x_preferred":[
        "\u0998\u09be\u099f\u09c1 \u0997\u09be\u09a8"
    ],
    "wof:name":"Ghatu",
    "wof:placetype":"locality"
},
  "geometry": {"coordinates":[77.54978,31.44863],"type":"Point"}
}