{
  "type": "Feature",
  "properties": {
    "iso:country":"IN",
    "ks:ks_name":"Aripada",
    "ks:ks_pop":506,
    "ks:ks_type":"VILLAGE",
    "name:eng_x_preferred":[
        "Aripada"
    ],
    "wof:name":"Aripada",
    "wof:placetype":"locality",
    "wof:population":506
},
  "geometry": {"coordinates":[86.35214999999999,20.471567],"type":"Point"}
}