{
  "type": "Feature",
  "properties": {
    "gn:admin1_code":"21",
    "gn:admin2_code":"396.0",
    "gn:asciiname":"Hingabadi",
    "gn:country_code":"IN",
    "gn:dem":823,
    "gn:feature_class":"P",
    "gn:feature_code":"PPL",
    "gn:name":"Hing\u0101b\u0101di",
    "gn:population":0,
    "gn:timezone":"Asia/Kolkata",
    "iso:country":"IN",
    "ks:ks_name":"Hingubari",
    "ks:ks_pop":104,
    "ks:ks_type":"VILLAGE",
    "name:eng_x_preferred":[
        "Hingubari"
    ],
    "name:eng_x_variant":[
        "Hingabadi"
    ],
    "wof:name":"Hingubari",
    "wof:placetype":"locality",
    "wof:population":104
},
  "geometry": {"coordinates":[83.44936800000001,19.529906],"type":"Point"}
}