{
  "type": "Feature",
  "properties": {
    "gn:admin1_code":"16",
    "gn:admin2_code":"515.0",
    "gn:asciiname":"Loni",
    "gn:country_code":"IN",
    "gn:dem":581,
    "gn:feature_class":"P",
    "gn:feature_code":"PPL",
    "gn:name":"Loni",
    "gn:population":0,
    "gn:timezone":"Asia/Kolkata",
    "iso:country":"IN",
    "name:bih_x_preferred":[
        "\u0932\u094b\u0928\u0940"
    ],
    "name:gom_x_preferred":[
        "\u0932\u094b\u0923\u0940"
    ],
    "name:pus_x_preferred":[
        "\u0644\u0648\u0646\u064a"
    ],
    "wof:name":"Loni",
    "wof:placetype":"neighbourhood"
},
  "geometry": {"coordinates":[74.8222,20.15026],"type":"Point"}
}