{
  "type": "Feature",
  "properties": {
    "iso:country":"IN",
    "ks:ks_name":"Tinkapara",
    "ks:ks_pop":206,
    "ks:ks_type":"HABITATION",
    "name:eng_x_preferred":[
        "Tinkapara"
    ],
    "wof:name":"Tinkapara",
    "wof:placetype":"locality",
    "wof:population":206
},
  "geometry": {"coordinates":[81.829424,19.246371],"type":"Point"}
}