{
  "type": "Feature",
  "properties": {
    "iso:country":"IN",
    "ks:ks_name":"Belahiya",
    "ks:ks_pop":209,
    "ks:ks_type":"VILLAGE",
    "name:eng_x_preferred":[
        "Belahiya"
    ],
    "wof:name":"Belahiya",
    "wof:placetype":"locality",
    "wof:population":209
},
  "geometry": {"coordinates":[82.285116,22.823619],"type":"Point"}
}