{
  "type": "Feature",
  "properties": {
    "iso:country":"IN",
    "ks:ks_name":"Ganeshpur",
    "ks:ks_pop":498,
    "ks:ks_type":"VILLAGE",
    "name:eng_x_preferred":[
        "Ganeshpur"
    ],
    "wof:name":"Ganeshpur",
    "wof:placetype":"locality",
    "wof:population":498
},
  "geometry": {"coordinates":[85.53308199999999,23.523749],"type":"Point"}
}