{
  "type": "Feature",
  "properties": {
    "iso:country":"IN",
    "ks:ks_name":"Kureli",
    "ks:ks_pop":122,
    "ks:ks_type":"HABITATION",
    "name:eng_x_preferred":[
        "Kureli"
    ],
    "wof:name":"Kureli",
    "wof:placetype":"locality",
    "wof:population":122
},
  "geometry": {"coordinates":[79.882504,28.030396],"type":"Point"}
}