{
  "type": "Feature",
  "properties": {
    "iso:country":"IN",
    "ks:ks_name":"Majjigebailu",
    "ks:ks_pop":207,
    "ks:ks_type":"HABITATION",
    "name:eng_x_preferred":[
        "Majjigebailu"
    ],
    "wof:name":"Majjigebailu",
    "wof:placetype":"locality",
    "wof:population":207
},
  "geometry": {"coordinates":[74.817971,13.539479],"type":"Point"}
}