{
  "type": "Feature",
  "properties": {
    "iso:country":"IN",
    "ks:ks_name":"Sekh Tola",
    "ks:ks_pop":420,
    "ks:ks_type":"HABITATION",
    "name:eng_x_preferred":[
        "Sekh Tola"
    ],
    "wof:name":"Sekh Tola",
    "wof:placetype":"locality",
    "wof:population":420
},
  "geometry": {"coordinates":[84.53681899999999,27.136206],"type":"Point"}
}