{
  "type": "Feature",
  "properties": {
    "gn:admin1_code":"13.0",
    "gn:admin2_code":"595.0",
    "gn:asciiname":"Vengola Kizhakkumbagam",
    "gn:country_code":"IN",
    "gn:dem":34,
    "gn:feature_class":"P",
    "gn:feature_code":"PPL",
    "gn:name":"Vengola Kizhakkumb\u0101gam",
    "gn:population":0,
    "gn:timezone":"Asia/Kolkata",
    "iso:country":"IN",
    "wof:name":"Vengola Kizhakkumbagam",
    "wof:placetype":"locality"
},
  "geometry": {"coordinates":[76.47606,10.06374],"type":"Point"}
}