{
  "type": "Feature",
  "properties": {
    "gn:admin1_code":"11",
    "gn:admin2_code":"31.0",
    "gn:asciiname":"Chhatraun",
    "gn:country_code":"IN",
    "gn:dem":999,
    "gn:feature_class":"P",
    "gn:feature_code":"PPL",
    "gn:name":"Chhatraun",
    "gn:population":0,
    "gn:timezone":"Asia/Kolkata",
    "iso:country":"IN",
    "wof:name":"Chhatraun",
    "wof:placetype":"locality"
},
  "geometry": {"coordinates":[76.73766999999999,31.19937],"type":"Point"}
}