{
  "type": "Feature",
  "properties": {
    "iso:country":"IN",
    "ks:ks_name":"Haldikhol",
    "ks:ks_pop":61,
    "ks:ks_type":"HABITATION",
    "name:eng_x_preferred":[
        "Haldikhol"
    ],
    "wof:name":"Haldikhol",
    "wof:placetype":"locality",
    "wof:population":61
},
  "geometry": {"coordinates":[83.66143,22.141569],"type":"Point"}
}