{
  "type": "Feature",
  "properties": {
    "iso:country":"IN",
    "ks:ks_name":"Birhum Killing",
    "ks:ks_pop":167,
    "ks:ks_type":"HABITATION",
    "ks:ks_uagg_main":0,
    "name:eng_x_preferred":[
        "Birhum Killing"
    ],
    "wof:name":"Birhum Killing",
    "wof:placetype":"neighbourhood",
    "wof:population":167
},
  "geometry": {"coordinates":[93.56151300000001,26.576276],"type":"Point"}
}