{
  "type": "Feature",
  "properties": {
    "iso:country":"IN",
    "ks:ks_alt_nam":"Golapara",
    "ks:ks_name":"Gola",
    "ks:ks_type":"VILLAGE",
    "name:eng_x_preferred":[
        "Gola"
    ],
    "name:eng_x_variant":[
        "Golapara"
    ],
    "wof:name":"Gola",
    "wof:placetype":"locality"
},
  "geometry": {"coordinates":[74.694907,22.73022],"type":"Point"}
}