{
  "type": "Feature",
  "properties": {
    "iso:country":"IN",
    "ks:ks_name":"Amyari",
    "ks:ks_pop":428,
    "ks:ks_type":"VILLAGE",
    "name:eng_x_preferred":[
        "Amyari"
    ],
    "wof:name":"Amyari",
    "wof:placetype":"locality",
    "wof:population":428
},
  "geometry": {"coordinates":[79.38413799999999,29.666495],"type":"Point"}
}