{
  "type": "Feature",
  "properties": {
    "iso:country":"IN",
    "ks:ks_name":"Jeevan Purwa",
    "ks:ks_pop":75,
    "ks:ks_type":"HABITATION",
    "ks:ks_uagg_main":0,
    "name:eng_x_preferred":[
        "Jeevan Purwa"
    ],
    "wof:name":"Jeevan Purwa",
    "wof:placetype":"neighbourhood",
    "wof:population":75
},
  "geometry": {"coordinates":[81.41042,27.50898],"type":"Point"}
}