{
  "type": "Feature",
  "properties": {
    "gn:admin1_code":"24",
    "gn:admin2_code":"124.0",
    "gn:asciiname":"Thakarda",
    "gn:country_code":"IN",
    "gn:dem":194,
    "gn:feature_class":"P",
    "gn:feature_code":"PPL",
    "gn:name":"Thakarda",
    "gn:population":0,
    "gn:timezone":"Asia/Kolkata",
    "iso:country":"IN",
    "wof:name":"Thakarda",
    "wof:placetype":"locality"
},
  "geometry": {"coordinates":[73.95195,23.70658],"type":"Point"}
}