{
  "type": "Feature",
  "properties": {
    "iso:country":"IN",
    "ks:ks_name":"Kantapadar",
    "ks:ks_pop":224,
    "ks:ks_type":"VILLAGE",
    "name:eng_x_preferred":[
        "Kantapadar"
    ],
    "wof:name":"Kantapadar",
    "wof:placetype":"locality",
    "wof:population":224
},
  "geometry": {"coordinates":[84.13086,19.385431],"type":"Point"}
}