{
  "type": "Feature",
  "properties": {
    "iso:country":"IN",
    "ks:ks_name":"Garhi Pataria",
    "ks:ks_pop":193,
    "ks:ks_type":"HABITATION",
    "name:eng_x_preferred":[
        "Garhi Pataria"
    ],
    "wof:name":"Garhi Pataria",
    "wof:placetype":"locality",
    "wof:population":193
},
  "geometry": {"coordinates":[78.039384,26.991384],"type":"Point"}
}