{
  "type": "Feature",
  "properties": {
    "gn:admin1_code":"23.0",
    "gn:admin2_code":"53.0",
    "gn:asciiname":"Ghanaur Rajputan",
    "gn:country_code":"IN",
    "gn:dem":242,
    "gn:feature_class":"P",
    "gn:feature_code":"PPL",
    "gn:name":"Ghanaur R\u0101jp\u016bt\u0101n",
    "gn:population":0,
    "gn:timezone":"Asia/Kolkata",
    "iso:country":"IN",
    "wof:name":"Ghanaur Rajputan",
    "wof:placetype":"locality"
},
  "geometry": {"coordinates":[76.06003,30.12585],"type":"Point"}
}