{
  "type": "Feature",
  "properties": {
    "iso:country":"IN",
    "ks:ks_name":"Baligan",
    "ks:ks_pop":718,
    "ks:ks_type":"VILLAGE",
    "ks:ks_uagg_main":0,
    "name:eng_x_preferred":[
        "Baligan"
    ],
    "wof:name":"Baligan",
    "wof:placetype":"neighbourhood",
    "wof:population":718
},
  "geometry": {"coordinates":[85.863992,20.00159],"type":"Point"}
}