{
  "type": "Feature",
  "properties": {
    "iso:country":"IN",
    "ks:ks_name":"Mudukeri",
    "ks:ks_pop":234,
    "ks:ks_type":"HABITATION",
    "name:eng_x_preferred":[
        "Mudukeri"
    ],
    "wof:name":"Mudukeri",
    "wof:placetype":"locality",
    "wof:population":234
},
  "geometry": {"coordinates":[74.75713,13.459212],"type":"Point"}
}