{
  "type": "Feature",
  "properties": {
    "iso:country":"IN",
    "ks:ks_name":"Jalampura",
    "ks:ks_pop":594,
    "ks:ks_type":"VILLAGE",
    "name:eng_x_preferred":[
        "Jalampura"
    ],
    "wof:name":"Jalampura",
    "wof:placetype":"locality",
    "wof:population":594
},
  "geometry": {"coordinates":[72.654667,25.667631],"type":"Point"}
}