{
  "type": "Feature",
  "properties": {
    "iso:country":"IN",
    "ks:ks_name":"Apsarkonda",
    "ks:ks_pop":256,
    "ks:ks_type":"HABITATION",
    "name:eng_x_preferred":[
        "Apsarkonda"
    ],
    "wof:name":"Apsarkonda",
    "wof:placetype":"locality",
    "wof:population":256
},
  "geometry": {"coordinates":[74.446679,14.23545],"type":"Point"}
}