{
  "type": "Feature",
  "properties": {
    "iso:country":"IN",
    "ks:ks_name":"Saluni",
    "ks:ks_pop":335,
    "ks:ks_type":"VILLAGE",
    "ks:ks_uagg_main":0,
    "name:eng_x_preferred":[
        "Saluni"
    ],
    "wof:name":"Saluni",
    "wof:placetype":"neighbourhood",
    "wof:population":335
},
  "geometry": {"coordinates":[85.171723,19.826698],"type":"Point"}
}