{
  "type": "Feature",
  "properties": {
    "iso:country":"IN",
    "ks:ks_name":"Chinnakottakulam",
    "ks:ks_pop":213,
    "ks:ks_type":"HABITATION",
    "name:eng_x_preferred":[
        "Chinnakottakulam"
    ],
    "wof:name":"Chinnakottakulam",
    "wof:placetype":"locality",
    "wof:population":213
},
  "geometry": {"coordinates":[78.388113,12.250345],"type":"Point"}
}