{
  "type": "Feature",
  "properties": {
    "iso:country":"IN",
    "ks:ks_name":"Pakairbahar",
    "ks:ks_pop":531,
    "ks:ks_type":"VILLAGE",
    "name:eng_x_preferred":[
        "Pakairbahar"
    ],
    "wof:name":"Pakairbahar",
    "wof:placetype":"locality",
    "wof:population":531
},
  "geometry": {"coordinates":[84.339702,22.429683],"type":"Point"}
}