{
  "type": "Feature",
  "properties": {
    "gn:admin1_code":"10",
    "gn:admin2_code":"69.0",
    "gn:asciiname":"Mahadeo",
    "gn:country_code":"IN",
    "gn:dem":437,
    "gn:feature_class":"P",
    "gn:feature_code":"PPL",
    "gn:name":"Mah\u0101deo",
    "gn:population":0,
    "gn:timezone":"Asia/Kolkata",
    "iso:country":"IN",
    "name:ceb_x_preferred":[
        "Mahadeo"
    ],
    "wof:name":"Mahadeo",
    "wof:placetype":"locality"
},
  "geometry": {"coordinates":[76.85099,30.76841],"type":"Point"}
}