{
  "type": "Feature",
  "properties": {
    "iso:country":"IN",
    "ks:ks_name":"Rohanpur",
    "ks:ks_pop":276,
    "ks:ks_type":"VILLAGE",
    "name:eng_x_preferred":[
        "Rohanpur"
    ],
    "wof:name":"Rohanpur",
    "wof:placetype":"locality",
    "wof:population":276
},
  "geometry": {"coordinates":[87.02153800000001,24.455348],"type":"Point"}
}