{
  "type": "Feature",
  "properties": {
    "iso:country":"IN",
    "ks:ks_name":"Tipomiya No 2",
    "ks:ks_pop":82,
    "ks:ks_type":"HABITATION",
    "name:eng_x_preferred":[
        "Tipomiya No 2"
    ],
    "wof:name":"Tipomiya No 2",
    "wof:placetype":"locality",
    "wof:population":82
},
  "geometry": {"coordinates":[95.18899,27.232999],"type":"Point"}
}