{
  "type": "Feature",
  "properties": {
    "iso:country":"IN",
    "ks:ks_name":"Morakura",
    "ks:ks_pop":243,
    "ks:ks_type":"HABITATION",
    "name:eng_x_preferred":[
        "Morakura"
    ],
    "wof:name":"Morakura",
    "wof:placetype":"locality",
    "wof:population":243
},
  "geometry": {"coordinates":[89.87376399999999,26.192477],"type":"Point"}
}