{
  "type": "Feature",
  "properties": {
    "iso:country":"IN",
    "ks:ks_name":"Panacha Road End",
    "ks:ks_pop":465,
    "ks:ks_type":"HABITATION",
    "name:eng_x_preferred":[
        "Panacha Road End"
    ],
    "wof:name":"Panacha Road End",
    "wof:placetype":"locality",
    "wof:population":465
},
  "geometry": {"coordinates":[76.260621,10.202426],"type":"Point"}
}