{
  "type": "Feature",
  "properties": {
    "gn:admin1_code":"11",
    "gn:admin2_code":"23.0",
    "gn:asciiname":"Narwar",
    "gn:country_code":"IN",
    "gn:dem":1774,
    "gn:feature_class":"P",
    "gn:feature_code":"PPL",
    "gn:name":"Narw\u0101r",
    "gn:population":0,
    "gn:timezone":"Asia/Kolkata",
    "iso:country":"IN",
    "name:ben_x_preferred":[
        "\u09a8\u09b0\u0993\u09af\u09bc\u09be\u09b0"
    ],
    "name:bpy_x_preferred":[
        "\u09a8\u09b0\u09f1\u09be\u09b0"
    ],
    "name:ceb_x_preferred":[
        "Narwar"
    ],
    "name:hin_x_preferred":[
        "\u0928\u0930\u0935\u0930"
    ],
    "name:ita_x_preferred":[
        "Narwar"
    ],
    "name:mlg_x_preferred":[
        "Narwar"
    ],
    "name:msa_x_preferred":[
        "Narwar"
    ],
    "name:new_x_preferred":[
        "\u0928\u0930\u094d\u0935\u093e\u0930"
    ],
    "name:nld_x_preferred":[
        "Narwar"
    ],
    "name:por_x_preferred":[
        "Narwar"
    ],
    "name:spa_x_preferred":[
        "Narwar"
    ],
    "name:vie_x_preferred":[
        "Narwar"
    ],
    "name:zho_x_preferred":[
        "\u7eb3\u5c14\u74e6\u5c14"
    ],
    "wof:name":"Narwar",
    "wof:placetype":"locality"
},
  "geometry": {"coordinates":[76.13164,32.8678],"type":"Point"}
}