{
  "type": "Feature",
  "properties": {
    "iso:country":"IN",
    "ks:ks_name":"Kangulaveedhi",
    "ks:ks_pop":28,
    "ks:ks_type":"HABITATION",
    "name:eng_x_preferred":[
        "Kangulaveedhi"
    ],
    "wof:name":"Kangulaveedhi",
    "wof:placetype":"locality",
    "wof:population":28
},
  "geometry": {"coordinates":[82.507136,18.244559],"type":"Point"}
}