{
  "type": "Feature",
  "properties": {
    "iso:country":"IN",
    "ks:ks_name":"Kalyanpur",
    "ks:ks_pop":115,
    "ks:ks_type":"HABITATION",
    "name:eng_x_preferred":[
        "Kalyanpur"
    ],
    "wof:name":"Kalyanpur",
    "wof:placetype":"locality",
    "wof:population":115
},
  "geometry": {"coordinates":[80.47785,26.178148],"type":"Point"}
}