{
  "type": "Feature",
  "properties": {
    "iso:country":"IN",
    "ks:ks_alt_nam":"rangai purwa",
    "ks:ks_name":"Rangai Purwa",
    "ks:ks_pop":84,
    "ks:ks_type":"HABITATION",
    "ks:ks_uagg_main":0,
    "name:eng_x_preferred":[
        "Rangai Purwa"
    ],
    "wof:name":"Rangai Purwa",
    "wof:placetype":"neighbourhood",
    "wof:population":84
},
  "geometry": {"coordinates":[81.54073699999999,27.21196],"type":"Point"}
}