{
  "type": "Feature",
  "properties": {
    "iso:country":"IN",
    "ks:ks_name":"Narangapadar",
    "ks:ks_pop":54,
    "ks:ks_type":"HABITATION",
    "name:eng_x_preferred":[
        "Narangapadar"
    ],
    "wof:name":"Narangapadar",
    "wof:placetype":"locality",
    "wof:population":54
},
  "geometry": {"coordinates":[83.544353,19.71197],"type":"Point"}
}