{
  "type": "Feature",
  "properties": {
    "gn:admin1_code":"21",
    "gn:admin2_code":"385.0",
    "gn:asciiname":"Oragaon",
    "gn:country_code":"IN",
    "gn:dem":131,
    "gn:feature_class":"P",
    "gn:feature_code":"PPL",
    "gn:name":"Oragaon",
    "gn:population":0,
    "gn:timezone":"Asia/Kolkata",
    "iso:country":"IN",
    "name:und_x_variant":[
        "Orhag\u0101n"
    ],
    "wof:name":"Oragaon",
    "wof:placetype":"locality"
},
  "geometry": {"coordinates":[84.98111999999998,20.02505],"type":"Point"}
}