{
  "type": "Feature",
  "properties": {
    "gn:admin1_code":"12.0",
    "gn:admin2_code":"6.0",
    "gn:asciiname":"Tarkundi",
    "gn:country_code":"IN",
    "gn:dem":1564,
    "gn:feature_class":"P",
    "gn:feature_code":"PPL",
    "gn:name":"Tarkundi",
    "gn:population":0,
    "gn:timezone":"Asia/Kolkata",
    "iso:country":"IN",
    "wof:name":"Tarkundi",
    "wof:placetype":"locality"
},
  "geometry": {"coordinates":[74.1883,33.4402],"type":"Point"}
}