{
  "type": "Feature",
  "properties": {
    "gn:admin1_code":"36.0",
    "gn:admin2_code":"152.0",
    "gn:asciiname":"Ismailpur",
    "gn:country_code":"IN",
    "gn:dem":164,
    "gn:feature_class":"P",
    "gn:feature_code":"PPL",
    "gn:name":"Ism\u0101ilpur",
    "gn:population":0,
    "gn:timezone":"Asia/Kolkata",
    "iso:country":"IN",
    "name:und_x_variant":[
        "Ism\u0101ilpur",
        "Naw\u0101da"
    ],
    "wof:name":"Ismailpur",
    "wof:placetype":"neighbourhood"
},
  "geometry": {"coordinates":[79.70972999999999,28.00473],"type":"Point"}
}