{
  "type": "Feature",
  "properties": {
    "iso:country":"IN",
    "ks:ks_name":"Dubrajkundu",
    "ks:ks_pop":466,
    "ks:ks_type":"VILLAGE",
    "name:eng_x_preferred":[
        "Dubrajkundu"
    ],
    "wof:name":"Dubrajkundu",
    "wof:placetype":"locality",
    "wof:population":466
},
  "geometry": {"coordinates":[87.671114,22.624195],"type":"Point"}
}