{
  "type": "Feature",
  "properties": {
    "iso:country":"IN",
    "ks:ks_name":"Dongrewasti",
    "ks:ks_pop":79,
    "ks:ks_type":"HABITATION",
    "name:eng_x_preferred":[
        "Dongrewasti"
    ],
    "wof:name":"Dongrewasti",
    "wof:placetype":"locality",
    "wof:population":79
},
  "geometry": {"coordinates":[76.279494,18.627763],"type":"Point"}
}