{
  "type": "Feature",
  "properties": {
    "iso:country":"IN",
    "ks:ks_name":"Umbarachapad",
    "ks:ks_pop":185,
    "ks:ks_type":"HABITATION",
    "name:eng_x_preferred":[
        "Umbarachapad"
    ],
    "wof:name":"Umbarachapad",
    "wof:placetype":"locality",
    "wof:population":185
},
  "geometry": {"coordinates":[73.54943299999999,20.577412],"type":"Point"}
}