{
  "type": "Feature",
  "properties": {
    "iso:country":"IN",
    "ks:ks_name":"Khori Mahuri",
    "ks:ks_pop":400,
    "ks:ks_type":"VILLAGE",
    "name:eng_x_preferred":[
        "Khori Mahuri"
    ],
    "wof:name":"Khori Mahuri",
    "wof:placetype":"locality",
    "wof:population":400
},
  "geometry": {"coordinates":[73.748778,24.2115],"type":"Point"}
}