{
  "type": "Feature",
  "properties": {
    "iso:country":"IN",
    "ks:ks_name":"Majra Fatehganj",
    "ks:ks_pop":389,
    "ks:ks_type":"HABITATION",
    "ks:ks_uagg_main":0,
    "name:eng_x_preferred":[
        "Majra Fatehganj"
    ],
    "wof:name":"Majra Fatehganj",
    "wof:placetype":"neighbourhood",
    "wof:population":389
},
  "geometry": {"coordinates":[79.043975,29.107217],"type":"Point"}
}