{
  "type": "Feature",
  "properties": {
    "iso:country":"IN",
    "ks:ks_name":"Khanpur Khas",
    "ks:ks_pop":659,
    "ks:ks_type":"HABITATION",
    "ks:ks_uagg_main":0,
    "name:eng_x_preferred":[
        "Khanpur Khas"
    ],
    "wof:name":"Khanpur Khas",
    "wof:placetype":"neighbourhood",
    "wof:population":659
},
  "geometry": {"coordinates":[82.551101,26.586822],"type":"Point"}
}