{
  "type": "Feature",
  "properties": {
    "gn:admin1_code":"11",
    "gn:admin2_code":"23.0",
    "gn:asciiname":"Bassu Kothi",
    "gn:country_code":"IN",
    "gn:dem":1760,
    "gn:feature_class":"P",
    "gn:feature_code":"PPL",
    "gn:name":"Bassu Kothi",
    "gn:population":0,
    "gn:timezone":"Asia/Kolkata",
    "iso:country":"IN",
    "wof:name":"Bassu Kothi",
    "wof:placetype":"locality"
},
  "geometry": {"coordinates":[76.28341,32.46816],"type":"Point"}
}