{
  "type": "Feature",
  "properties": {
    "iso:country":"IN",
    "ks:ks_name":"Nagariya Faliyu",
    "ks:ks_pop":226,
    "ks:ks_type":"HABITATION",
    "ks:ks_uagg_main":0,
    "name:eng_x_preferred":[
        "Nagariya Faliyu"
    ],
    "wof:name":"Nagariya Faliyu",
    "wof:placetype":"neighbourhood",
    "wof:population":226
},
  "geometry": {"coordinates":[72.79947199999999,20.286694],"type":"Point"}
}