{
  "type": "Feature",
  "properties": {
    "iso:country":"IN",
    "ks:ks_name":"Mahudi Dungari",
    "ks:ks_pop":952,
    "ks:ks_type":"VILLAGE",
    "name:eng_x_preferred":[
        "Mahudi Dungari"
    ],
    "wof:name":"Mahudi Dungari",
    "wof:placetype":"locality",
    "wof:population":952
},
  "geometry": {"coordinates":[74.52634999999999,22.741761],"type":"Point"}
}