{
  "type": "Feature",
  "properties": {
    "iso:country":"IN",
    "ks:ks_name":"Hanumannager",
    "ks:ks_pop":16,
    "ks:ks_type":"HABITATION",
    "name:eng_x_preferred":[
        "Hanumannager"
    ],
    "wof:name":"Hanumannager",
    "wof:placetype":"locality",
    "wof:population":16
},
  "geometry": {"coordinates":[73.484168,16.35343],"type":"Point"}
}