{
  "type": "Feature",
  "properties": {
    "iso:country":"IN",
    "ks:ks_name":"Hirapur",
    "ks:ks_type":"VILLAGE",
    "ks:ks_uagg_main":0,
    "name:eng_x_preferred":[
        "Hirapur"
    ],
    "wof:name":"Hirapur",
    "wof:placetype":"neighbourhood"
},
  "geometry": {"coordinates":[85.56458600000001,21.964593],"type":"Point"}
}