{
  "type": "Feature",
  "properties": {
    "iso:country":"IN",
    "ks:ks_name":"Ainlabhata",
    "ks:ks_pop":7,
    "ks:ks_type":"VILLAGE",
    "name:eng_x_preferred":[
        "Ainlabhata"
    ],
    "wof:name":"Ainlabhata",
    "wof:placetype":"locality",
    "wof:population":7
},
  "geometry": {"coordinates":[82.983324,19.882612],"type":"Point"}
}