{
  "type": "Feature",
  "properties": {
    "iso:country":"IN",
    "ks:ks_alt_nam":"ARARPAI",
    "ks:ks_name":"Ararpai",
    "ks:ks_pop":60,
    "ks:ks_type":"HABITATION",
    "name:eng_x_preferred":[
        "Ararpai"
    ],
    "wof:name":"Ararpai",
    "wof:placetype":"locality",
    "wof:population":60
},
  "geometry": {"coordinates":[85.87573,22.103679],"type":"Point"}
}