{
  "type": "Feature",
  "properties": {
    "iso:country":"IN",
    "ks:ks_name":"Pure Visenan",
    "ks:ks_pop":100,
    "ks:ks_type":"HABITATION",
    "name:eng_x_preferred":[
        "Pure Visenan"
    ],
    "wof:name":"Pure Visenan",
    "wof:placetype":"locality",
    "wof:population":100
},
  "geometry": {"coordinates":[81.554007,26.647777],"type":"Point"}
}