{
  "type": "Feature",
  "properties": {
    "gn:admin1_code":"11.0",
    "gn:admin2_code":"26.0",
    "gn:asciiname":"Phadauhr",
    "gn:country_code":"IN",
    "gn:dem":1597,
    "gn:feature_class":"P",
    "gn:feature_code":"PPL",
    "gn:name":"Phadauhr",
    "gn:population":0,
    "gn:timezone":"Asia/Kolkata",
    "iso:country":"IN",
    "wof:name":"Phadauhr",
    "wof:placetype":"locality"
},
  "geometry": {"coordinates":[77.52141999999998,31.39234],"type":"Point"}
}