{
  "type": "Feature",
  "properties": {
    "iso:country":"IN",
    "ks:ks_name":"Chhote Miya Ka Pura",
    "ks:ks_pop":270,
    "ks:ks_type":"HABITATION",
    "ks:ks_uagg_main":0,
    "name:eng_x_preferred":[
        "Chhote Miya Ka Pura"
    ],
    "wof:name":"Chhote Miya Ka Pura",
    "wof:placetype":"neighbourhood",
    "wof:population":270
},
  "geometry": {"coordinates":[81.393062,25.557283],"type":"Point"}
}