{
  "type": "Feature",
  "properties": {
    "iso:country":"IN",
    "ks:ks_alt_nam":"KRISHNA KAMAL PARA",
    "ks:ks_name":"Krishna Kamal Para",
    "ks:ks_pop":30,
    "ks:ks_type":"HABITATION",
    "ks:ks_uagg_main":0,
    "name:eng_x_preferred":[
        "Krishna Kamal Para"
    ],
    "wof:name":"Krishna Kamal Para",
    "wof:placetype":"neighbourhood",
    "wof:population":30
},
  "geometry": {"coordinates":[91.495762,23.719722],"type":"Point"}
}