{
  "type": "Feature",
  "properties": {
    "iso:country":"IN",
    "ks:ks_name":"Balungadihi",
    "ks:ks_pop":0,
    "ks:ks_type":"VILLAGE",
    "name:eng_x_preferred":[
        "Balungadihi"
    ],
    "wof:name":"Balungadihi",
    "wof:placetype":"locality",
    "wof:population":0
},
  "geometry": {"coordinates":[85.407881,19.918236],"type":"Point"}
}