{
  "type": "Feature",
  "properties": {
    "iso:country":"IN",
    "ks:ks_name":"Duwarsai",
    "ks:ks_pop":431,
    "ks:ks_type":"VILLAGE",
    "name:eng_x_preferred":[
        "Duwarsai"
    ],
    "wof:name":"Duwarsai",
    "wof:placetype":"locality",
    "wof:population":431
},
  "geometry": {"coordinates":[85.538848,22.276926],"type":"Point"}
}