{
  "type": "Feature",
  "properties": {
    "iso:country":"IN",
    "ks:ks_alt_nam":"ESTATE",
    "ks:ks_name":"Estate",
    "ks:ks_pop":521,
    "ks:ks_type":"HABITATION",
    "name:eng_x_preferred":[
        "Estate"
    ],
    "wof:name":"Estate",
    "wof:placetype":"locality",
    "wof:population":521
},
  "geometry": {"coordinates":[76.784768,9.958909],"type":"Point"}
}