{
  "type": "Feature",
  "properties": {
    "gn:admin1_code":"19",
    "gn:admin2_code":"579.0",
    "gn:asciiname":"Jamga Buzurg",
    "gn:country_code":"IN",
    "gn:dem":512,
    "gn:feature_class":"P",
    "gn:feature_code":"PPL",
    "gn:name":"J\u0101mga Buzurg",
    "gn:population":0,
    "gn:timezone":"Asia/Kolkata",
    "iso:country":"IN",
    "wof:name":"Jamga Buzurg",
    "wof:placetype":"neighbourhood"
},
  "geometry": {"coordinates":[76.79649000000001,17.44351],"type":"Point"}
}