{
  "type": "Feature",
  "properties": {
    "iso:country":"IN",
    "ks:ks_name":"Ghahtora",
    "ks:ks_pop":131,
    "ks:ks_type":"VILLAGE",
    "name:eng_x_preferred":[
        "Ghahtora"
    ],
    "wof:name":"Ghahtora",
    "wof:placetype":"locality",
    "wof:population":131
},
  "geometry": {"coordinates":[79.961618,29.390875],"type":"Point"}
}