{
  "type": "Feature",
  "properties": {
    "gn:admin1_code":"37",
    "gn:admin2_code":"400.0",
    "gn:asciiname":"Majgaona",
    "gn:country_code":"IN",
    "gn:dem":711,
    "gn:feature_class":"P",
    "gn:feature_code":"PPL",
    "gn:name":"Majgaona",
    "gn:population":0,
    "gn:timezone":"Asia/Kolkata",
    "iso:country":"IN",
    "wof:name":"Majgaona",
    "wof:placetype":"locality"
},
  "geometry": {"coordinates":[82.54586999999999,23.58279],"type":"Point"}
}