{
  "type": "Feature",
  "properties": {
    "iso:country":"IN",
    "ks:ks_name":"Bhapkarwadi",
    "ks:ks_pop":127,
    "ks:ks_type":"HABITATION",
    "name:eng_x_preferred":[
        "Bhapkarwadi"
    ],
    "wof:name":"Bhapkarwadi",
    "wof:placetype":"locality",
    "wof:population":127
},
  "geometry": {"coordinates":[74.694607,18.825993],"type":"Point"}
}