{
  "type": "Feature",
  "properties": {
    "iso:country":"IN",
    "ks:ks_name":"Haddinagadde",
    "ks:ks_pop":1,
    "ks:ks_type":"HABITATION",
    "name:eng_x_preferred":[
        "Haddinagadde"
    ],
    "wof:name":"Haddinagadde",
    "wof:placetype":"locality",
    "wof:population":1
},
  "geometry": {"coordinates":[74.49557,14.464631],"type":"Point"}
}