{
  "type": "Feature",
  "properties": {
    "iso:country":"IN",
    "ks:ks_name":"Jerkani",
    "ks:ks_pop":105,
    "ks:ks_type":"VILLAGE",
    "name:eng_x_preferred":[
        "Jerkani"
    ],
    "wof:name":"Jerkani",
    "wof:placetype":"locality",
    "wof:population":105
},
  "geometry": {"coordinates":[86.42584100000001,22.020471],"type":"Point"}
}