{
  "type": "Feature",
  "properties": {
    "iso:country":"IN",
    "ks:ks_name":"Phitingpara",
    "ks:ks_pop":134,
    "ks:ks_type":"HABITATION",
    "name:eng_x_preferred":[
        "Phitingpara"
    ],
    "wof:name":"Phitingpara",
    "wof:placetype":"locality",
    "wof:population":134
},
  "geometry": {"coordinates":[83.190528,22.745309],"type":"Point"}
}