{
  "type": "Feature",
  "properties": {
    "iso:country":"IN",
    "ks:ks_alt_nam":"L\u0101tu",
    "ks:ks_name":"Latu",
    "ks:ks_pop":1778,
    "ks:ks_type":"VILLAGE",
    "name:eng_x_preferred":[
        "Latu"
    ],
    "name:eng_x_variant":[
        "L\u0101tu"
    ],
    "wof:name":"Latu",
    "wof:placetype":"locality",
    "wof:population":1778
},
  "geometry": {"coordinates":[84.34361199999999,22.990439],"type":"Point"}
}