{
  "type": "Feature",
  "properties": {
    "iso:country":"IN",
    "ks:ks_name":"Malabettu",
    "ks:ks_pop":210,
    "ks:ks_type":"HABITATION",
    "name:eng_x_preferred":[
        "Malabettu"
    ],
    "wof:name":"Malabettu",
    "wof:placetype":"locality",
    "wof:population":210
},
  "geometry": {"coordinates":[75.306646,12.964573],"type":"Point"}
}