{
  "type": "Feature",
  "properties": {
    "gn:admin1_code":"16.0",
    "gn:admin2_code":"530",
    "gn:asciiname":"Bavda",
    "gn:country_code":"IN",
    "gn:dem":627,
    "gn:feature_class":"P",
    "gn:feature_code":"PPL",
    "gn:name":"B\u0101vda",
    "gn:population":0,
    "gn:timezone":"Asia/Kolkata",
    "iso:country":"IN",
    "name:und_x_variant":[
        "Bowra",
        "B\u0101vda"
    ],
    "wof:name":"Bavda",
    "wof:placetype":"locality"
},
  "geometry": {"coordinates":[73.82878000000002,16.54427],"type":"Point"}
}