{
  "type": "Feature",
  "properties": {
    "iso:country":"IN",
    "ks:ks_name":"Maholi",
    "ks:ks_pop":729,
    "ks:ks_type":"VILLAGE",
    "ks:ks_uagg_main":0,
    "name:eng_x_preferred":[
        "Maholi"
    ],
    "wof:name":"Maholi",
    "wof:placetype":"neighbourhood",
    "wof:population":729
},
  "geometry": {"coordinates":[74.95208,19.720123],"type":"Point"}
}