{
  "type": "Feature",
  "properties": {
    "iso:country":"IN",
    "ks:ks_name":"Gorahari",
    "ks:ks_pop":250,
    "ks:ks_type":"HABITATION",
    "name:eng_x_preferred":[
        "Gorahari"
    ],
    "wof:name":"Gorahari",
    "wof:placetype":"locality",
    "wof:population":250
},
  "geometry": {"coordinates":[81.458697,26.435548],"type":"Point"}
}