{
  "type": "Feature",
  "properties": {
    "gn:admin1_code":"35",
    "gn:admin2_code":"419.0",
    "gn:asciiname":"Rauriyapura",
    "gn:country_code":"IN",
    "gn:dem":170,
    "gn:feature_class":"P",
    "gn:feature_code":"PPL",
    "gn:name":"Rauriy\u0101pura",
    "gn:population":0,
    "gn:timezone":"Asia/Kolkata",
    "iso:country":"IN",
    "wof:name":"Rauriyapura",
    "wof:placetype":"locality"
},
  "geometry": {"coordinates":[78.2129,26.66036],"type":"Point"}
}