{
  "type": "Feature",
  "properties": {
    "gn:admin1_code":"16",
    "gn:admin2_code":"509.0",
    "gn:asciiname":"Saongi",
    "gn:country_code":"IN",
    "gn:dem":229,
    "gn:feature_class":"P",
    "gn:feature_code":"PPL",
    "gn:name":"S\u0101ongi",
    "gn:population":0,
    "gn:timezone":"Asia/Kolkata",
    "iso:country":"IN",
    "name:und_x_variant":[
        "S\u0101ongi",
        "Badge"
    ],
    "wof:name":"Saongi",
    "wof:placetype":"locality"
},
  "geometry": {"coordinates":[79.69065000000001,20.46236],"type":"Point"}
}