{
  "type": "Feature",
  "properties": {
    "iso:country":"IN",
    "ks:ks_name":"Haragobindapur",
    "ks:ks_pop":0,
    "ks:ks_type":"VILLAGE",
    "name:eng_x_preferred":[
        "Haragobindapur"
    ],
    "wof:name":"Haragobindapur",
    "wof:placetype":"locality",
    "wof:population":0
},
  "geometry": {"coordinates":[87.352223,22.064511],"type":"Point"}
}