{
  "type": "Feature",
  "properties": {
    "iso:country":"IN",
    "ks:ks_name":"Kinamanr",
    "ks:ks_pop":390,
    "ks:ks_type":"VILLAGE",
    "ks:ks_uagg_main":0,
    "name:eng_x_preferred":[
        "Kinamanr"
    ],
    "wof:name":"Kinamanr",
    "wof:placetype":"neighbourhood",
    "wof:population":390
},
  "geometry": {"coordinates":[84.515388,23.728328],"type":"Point"}
}