{
  "type": "Feature",
  "properties": {
    "gn:admin1_code":"25",
    "gn:admin2_code":"621.0",
    "gn:asciiname":"Manamelkudi",
    "gn:cc2":"IN",
    "gn:country_code":"IN",
    "gn:dem":6,
    "gn:feature_class":"P",
    "gn:feature_code":"PPL",
    "gn:name":"Manamelkudi",
    "gn:population":0,
    "gn:timezone":"Asia/Kolkata",
    "iso:country":"IN",
    "name:und_x_variant":[
        "Manamalkudi",
        "Manamelkudi"
    ],
    "wof:name":"Manamelkudi",
    "wof:placetype":"locality"
},
  "geometry": {"coordinates":[79.22988000000002,10.04433],"type":"Point"}
}