{
  "type": "Feature",
  "properties": {
    "iso:country":"IN",
    "ks:ks_alt_nam":"SWAMI VASTI",
    "ks:ks_name":"Swami Vasti",
    "ks:ks_pop":88,
    "ks:ks_type":"HABITATION",
    "name:eng_x_preferred":[
        "Swami Vasti"
    ],
    "wof:name":"Swami Vasti",
    "wof:placetype":"locality",
    "wof:population":88
},
  "geometry": {"coordinates":[74.66785,16.752618],"type":"Point"}
}