{
  "type": "Feature",
  "properties": {
    "iso:country":"IN",
    "ks:ks_name":"Phutusahid Tola",
    "ks:ks_pop":67,
    "ks:ks_type":"HABITATION",
    "name:eng_x_preferred":[
        "Phutusahid Tola"
    ],
    "wof:name":"Phutusahid Tola",
    "wof:placetype":"locality",
    "wof:population":67
},
  "geometry": {"coordinates":[84.49021,24.304509],"type":"Point"}
}