{
  "type": "Feature",
  "properties": {
    "iso:country":"IN",
    "ks:ks_name":"Swarupnagar",
    "ks:ks_pop":2535,
    "ks:ks_type":"VILLAGE",
    "ks:ks_uagg_main":0,
    "name:eng_x_preferred":[
        "Swarupnagar"
    ],
    "wof:name":"Swarupnagar",
    "wof:placetype":"neighbourhood",
    "wof:population":2535
},
  "geometry": {"coordinates":[88.731437,22.693852],"type":"Point"}
}