{
  "type": "Feature",
  "properties": {
    "iso:country":"IN",
    "ks:ks_alt_nam":"REGNIA",
    "ks:ks_name":"Regnia",
    "ks:ks_pop":1313,
    "ks:ks_type":"HABITATION",
    "ks:ks_uagg_main":0,
    "name:eng_x_preferred":[
        "Regnia"
    ],
    "wof:name":"Regnia",
    "wof:placetype":"neighbourhood",
    "wof:population":1313
},
  "geometry": {"coordinates":[85.099512,26.863856],"type":"Point"}
}