{
  "type": "Feature",
  "properties": {
    "iso:country":"IN",
    "ks:ks_name":"Kol Bhalupani",
    "ks:ks_pop":0,
    "ks:ks_type":"VILLAGE",
    "name:eng_x_preferred":[
        "Kol Bhalupani"
    ],
    "wof:name":"Kol Bhalupani",
    "wof:placetype":"locality",
    "wof:population":0
},
  "geometry": {"coordinates":[85.542822,22.733983],"type":"Point"}
}