{
  "type": "Feature",
  "properties": {
    "iso:country":"IN",
    "ks:ks_name":"Bamunpara",
    "ks:ks_pop":1384,
    "ks:ks_type":"HABITATION",
    "name:eng_x_preferred":[
        "Bamunpara"
    ],
    "wof:name":"Bamunpara",
    "wof:placetype":"locality",
    "wof:population":1384
},
  "geometry": {"coordinates":[88.690055,22.920735],"type":"Point"}
}