{
  "type": "Feature",
  "properties": {
    "gn:admin1_code":"34.0",
    "gn:admin2_code":"207.0",
    "gn:asciiname":"Dhedua",
    "gn:country_code":"IN",
    "gn:dem":64,
    "gn:feature_class":"P",
    "gn:feature_code":"PPL",
    "gn:name":"Dhedua",
    "gn:population":0,
    "gn:timezone":"Asia/Kolkata",
    "iso:country":"IN",
    "wof:name":"Dhedua",
    "wof:placetype":"locality"
},
  "geometry": {"coordinates":[86.29179999999999,26.41639],"type":"Point"}
}