{
  "type": "Feature",
  "properties": {
    "gn:admin1_code":"37",
    "gn:admin2_code":"412.0",
    "gn:asciiname":"Kurmajhar",
    "gn:country_code":"IN",
    "gn:dem":416,
    "gn:feature_class":"P",
    "gn:feature_code":"PPL",
    "gn:name":"Kurm\u0101jhar",
    "gn:population":0,
    "gn:timezone":"Asia/Kolkata",
    "iso:country":"IN",
    "ks:ks_alt_nam":"Kurm\u0101jhar",
    "ks:ks_name":"Kurmajhar",
    "ks:ks_pop":102,
    "ks:ks_type":"VILLAGE",
    "name:eng_x_preferred":[
        "Kurmajhar"
    ],
    "name:eng_x_variant":[
        "Kurm\u0101jhar"
    ],
    "wof:name":"Kurmajhar",
    "wof:placetype":"locality",
    "wof:population":102
},
  "geometry": {"coordinates":[81.702687,20.551674],"type":"Point"}
}