{
  "type": "Feature",
  "properties": {
    "gn:admin1_code":"19.0",
    "gn:admin2_code":"555.0",
    "gn:asciiname":"Katmalli",
    "gn:country_code":"IN",
    "gn:dem":681,
    "gn:feature_class":"P",
    "gn:feature_code":"PPL",
    "gn:name":"Katmalli",
    "gn:population":0,
    "gn:timezone":"Asia/Kolkata",
    "iso:country":"IN",
    "wof:name":"Katmalli",
    "wof:placetype":"locality"
},
  "geometry": {"coordinates":[75.15675999999998,15.79479],"type":"Point"}
}