{
  "type": "Feature",
  "properties": {
    "iso:country":"IN",
    "ks:ks_name":"Kaharangsingh",
    "ks:ks_pop":241,
    "ks:ks_type":"HABITATION",
    "name:eng_x_preferred":[
        "Kaharangsingh"
    ],
    "wof:name":"Kaharangsingh",
    "wof:placetype":"locality",
    "wof:population":241
},
  "geometry": {"coordinates":[91.510987,23.6484],"type":"Point"}
}