{
  "type": "Feature",
  "properties": {
    "iso:country":"IN",
    "ks:ks_name":"Kutingpadar",
    "ks:ks_pop":198,
    "ks:ks_type":"VILLAGE",
    "name:eng_x_preferred":[
        "Kutingpadar"
    ],
    "wof:name":"Kutingpadar",
    "wof:placetype":"locality",
    "wof:population":198
},
  "geometry": {"coordinates":[83.391338,19.830072],"type":"Point"}
}