{
  "type": "Feature",
  "properties": {
    "gn:admin1_code":"19.0",
    "gn:admin2_code":"555.0",
    "gn:asciiname":"Harsanvadi",
    "gn:country_code":"IN",
    "gn:dem":702,
    "gn:feature_class":"P",
    "gn:feature_code":"PPL",
    "gn:name":"Harsanv\u0101di",
    "gn:population":0,
    "gn:timezone":"Asia/Kolkata",
    "iso:country":"IN",
    "wof:name":"Harsanvadi",
    "wof:placetype":"locality"
},
  "geometry": {"coordinates":[74.46798000000003,15.65978],"type":"Point"}
}