{
  "type": "Feature",
  "properties": {
    "iso:country":"IN",
    "ks:ks_name":"Bhortirawa",
    "ks:ks_pop":505,
    "ks:ks_type":"HABITATION",
    "name:eng_x_preferred":[
        "Bhortirawa"
    ],
    "wof:name":"Bhortirawa",
    "wof:placetype":"locality",
    "wof:population":505
},
  "geometry": {"coordinates":[82.82405900000001,24.543721],"type":"Point"}
}