{
  "type": "Feature",
  "properties": {
    "gn:admin1_code":"2.0",
    "gn:admin2_code":"549.0",
    "gn:asciiname":"Rangampeta",
    "gn:country_code":"IN",
    "gn:dem":153,
    "gn:feature_class":"P",
    "gn:feature_code":"PPL",
    "gn:name":"Rangampeta",
    "gn:population":0,
    "gn:timezone":"Asia/Kolkata",
    "iso:country":"IN",
    "name:tgl_x_preferred":[
        "Rangampeta"
    ],
    "name:urd_x_preferred":[
        "\u0631\u0646\u06af\u0645 \u067e\u06cc\u0679\u0627"
    ],
    "name:vie_x_preferred":[
        "Rangampeta"
    ],
    "wof:name":"Rangampeta",
    "wof:placetype":"locality"
},
  "geometry": {"coordinates":[79.30739,15.49728],"type":"Point"}
}