{
  "type": "Feature",
  "properties": {
    "iso:country":"IN",
    "ks:ks_name":"Madhaliwadi",
    "ks:ks_pop":137,
    "ks:ks_type":"HABITATION",
    "name:eng_x_preferred":[
        "Madhaliwadi"
    ],
    "wof:name":"Madhaliwadi",
    "wof:placetype":"locality",
    "wof:population":137
},
  "geometry": {"coordinates":[73.773625,16.197844],"type":"Point"}
}