{
  "type": "Feature",
  "properties": {
    "iso:country":"IN",
    "ks:ks_name":"Kandula Puram",
    "ks:ks_pop":7737,
    "ks:ks_type":"VILLAGE",
    "ks:ks_uagg_main":0,
    "name:eng_x_preferred":[
        "Kandula Puram"
    ],
    "wof:name":"Kandula Puram",
    "wof:placetype":"neighbourhood",
    "wof:population":7737
},
  "geometry": {"coordinates":[79.116316,15.588682],"type":"Point"}
}