{
  "type": "Feature",
  "properties": {
    "gn:admin1_code":"13.0",
    "gn:asciiname":"Karattura",
    "gn:country_code":"IN",
    "gn:dem":10,
    "gn:feature_class":"P",
    "gn:feature_code":"PPL",
    "gn:name":"K\u0101r\u0101ttura",
    "gn:population":0,
    "gn:timezone":"Asia/Kolkata",
    "iso:country":"IN",
    "wof:name":"Karattura",
    "wof:placetype":"locality"
},
  "geometry": {"coordinates":[76.52906,8.9749],"type":"Point"}
}