{
  "type": "Feature",
  "properties": {
    "gn:country":"IN",
    "gn:fcode":"PPL",
    "gn:population":45184,
    "iso:country":"IN",
    "name:ben_x_preferred":[
        "\u09ae\u09a8\u09cd\u09a6\u09b2\u09be"
    ],
    "name:bpy_x_preferred":[
        "\u09ae\u09a8\u09cd\u09a6\u09b2\u09be"
    ],
    "name:cat_x_preferred":[
        "Mandla"
    ],
    "name:ceb_x_preferred":[
        "Mandl\u0101"
    ],
    "name:deu_x_preferred":[
        "Mandla"
    ],
    "name:eng_x_preferred":[
        "Mandla"
    ],
    "name:fas_x_preferred":[
        "\u0645\u0627\u0646\u062f\u0644\u0627"
    ],
    "name:fra_x_preferred":[
        "Mandla"
    ],
    "name:guj_x_preferred":[
        "\u0aae\u0a82\u0aa1\u0ab2\u0abe"
    ],
    "name:hin_x_preferred":[
        "\u092e\u093e\u0902\u0921\u0932\u093e"
    ],
    "name:ita_x_preferred":[
        "Mandla"
    ],
    "name:jpn_x_preferred":[
        "\u30de\u30f3\u30c9\u30e9"
    ],
    "name:kan_x_preferred":[
        "\u0cae\u0c82\u0ca1\u0ccd\u0cb2\u0cbe"
    ],
    "name:kor_x_preferred":[
        "\ub9cc\ub4e4\ub77c"
    ],
    "name:mar_x_preferred":[
        "\u092e\u0902\u0921\u0932\u093e"
    ],
    "name:mlg_x_preferred":[
        "Mandla"
    ],
    "name:msa_x_preferred":[
        "Mandla"
    ],
    "name:new_x_preferred":[
        "\u092e\u0928\u094d\u0926\u094d\u0932\u093e"
    ],
    "name:nld_x_preferred":[
        "Mandla"
    ],
    "name:ori_x_preferred":[
        "\u0b2e\u0b3e\u0b28\u0b4d\u0b26\u0b4d\u0b32\u0b3e"
    ],
    "name:por_x_preferred":[
        "Mandla"
    ],
    "name:rus_x_preferred":[
        "\u041c\u0430\u043d\u0434\u043b\u0430"
    ],
    "name:san_x_preferred":[
        "\u092e\u0923\u094d\u0921\u0932\u093e"
    ],
    "name:spa_x_preferred":[
        "Mandla"
    ],
    "name:swe_x_preferred":[
        "Mandla"
    ],
    "name:tam_x_preferred":[
        "\u0bae\u0bbe\u0ba3\u0bcd\u0b9f\u0bcd\u0bb2\u0bbe"
    ],
    "name:tel_x_preferred":[
        "\u0c2e\u0c02\u0c21\u0c4d\u0c32"
    ],
    "name:urd_x_preferred":[
        "\u0645\u0627\u0646\u0688\u0644\u0627"
    ],
    "name:vie_x_preferred":[
        "Mandla"
    ],
    "qs:name":"Mandla",
    "qs:name_adm0":"India",
    "qs:name_adm1":"Madhya Pradesh",
    "qs:photos":27,
    "qs:photos_1k":5,
    "qs:photos_9k":1,
    "qs:photos_9r":2,
    "qs:photos_all":27,
    "qs:photos_sr":2,
    "qs:placetype":"Town",
    "qs:pop_sr":"7",
    "wd:wordcount":1868,
    "wof:name":"Mandla",
    "wof:placetype":"locality",
    "wof:population":45184
},
  "geometry": {"coordinates":[80.37108000000001,22.59974],"type":"Point"}
}