{
  "type": "Feature",
  "properties": {
    "gn:admin1_code":"11",
    "gn:admin2_code":"27.0",
    "gn:asciiname":"Sihl",
    "gn:country_code":"IN",
    "gn:dem":668,
    "gn:feature_class":"P",
    "gn:feature_code":"PPL",
    "gn:name":"S\u012bhl",
    "gn:population":0,
    "gn:timezone":"Asia/Kolkata",
    "iso:country":"IN",
    "name:als_x_preferred":[
        "Sihl"
    ],
    "name:bel_x_preferred":[
        "\u0417\u0456\u043b\u044c"
    ],
    "name:ceb_x_preferred":[
        "Sihl"
    ],
    "name:deu_x_preferred":[
        "Sihl"
    ],
    "name:epo_x_preferred":[
        "Sihl"
    ],
    "name:fin_x_preferred":[
        "Sihl"
    ],
    "name:fra_x_preferred":[
        "Sihl"
    ],
    "name:ita_x_preferred":[
        "Sihl"
    ],
    "name:nld_x_preferred":[
        "Sihl"
    ],
    "name:nno_x_preferred":[
        "Sihl"
    ],
    "name:pol_x_preferred":[
        "Sihl"
    ],
    "name:ron_x_preferred":[
        "R\u00e2ul Sihl"
    ],
    "name:rus_x_preferred":[
        "\u0417\u0438\u043b\u044c"
    ],
    "name:spa_x_preferred":[
        "R\u00edo Sihl"
    ],
    "name:swe_x_preferred":[
        "Sihl"
    ],
    "name:tur_x_preferred":[
        "Sihl"
    ],
    "name:ukr_x_preferred":[
        "\u0417\u0456\u043b\u044c"
    ],
    "wof:name":"Sihl",
    "wof:placetype":"locality"
},
  "geometry": {"coordinates":[76.82328000000003,31.4418],"type":"Point"}
}