{
  "type": "Feature",
  "properties": {
    "iso:country":"IN",
    "ks:ks_name":"Nadri",
    "ks:ks_pop":926,
    "ks:ks_type":"VILLAGE",
    "ks:ks_uagg_main":0,
    "name:eng_x_preferred":[
        "Nadri"
    ],
    "wof:name":"Nadri",
    "wof:placetype":"neighbourhood",
    "wof:population":926
},
  "geometry": {"coordinates":[72.6165,23.355111],"type":"Point"}
}