{
  "type": "Feature",
  "properties": {
    "gn:admin1_code":"24.0",
    "gn:admin2_code":"113",
    "gn:asciiname":"Bhetnanda",
    "gn:country_code":"IN",
    "gn:dem":211,
    "gn:feature_class":"P",
    "gn:feature_code":"PPL",
    "gn:name":"Bhetnanda",
    "gn:population":0,
    "gn:timezone":"Asia/Kolkata",
    "iso:country":"IN",
    "wof:name":"Bhetnanda",
    "wof:placetype":"locality"
},
  "geometry": {"coordinates":[73.29481,26.08119],"type":"Point"}
}