{
  "type": "Feature",
  "properties": {
    "iso:country":"IN",
    "ks:ks_name":"Sawantwadi",
    "ks:ks_pop":40,
    "ks:ks_type":"HABITATION",
    "name:eng_x_preferred":[
        "Sawantwadi"
    ],
    "wof:name":"Sawantwadi",
    "wof:placetype":"locality",
    "wof:population":40
},
  "geometry": {"coordinates":[73.97578799999999,16.069871],"type":"Point"}
}