{
  "type": "Feature",
  "properties": {
    "iso:country":"IN",
    "ks:ks_name":"Ganga Nagar",
    "ks:ks_pop":559,
    "ks:ks_type":"HABITATION",
    "name:eng_x_preferred":[
        "Ganga Nagar"
    ],
    "wof:name":"Ganga Nagar",
    "wof:placetype":"locality",
    "wof:population":559
},
  "geometry": {"coordinates":[91.825317,24.20492],"type":"Point"}
}