{
  "type": "Feature",
  "properties": {
    "iso:country":"IN",
    "ks:ks_name":"Patapadar",
    "ks:ks_pop":170,
    "ks:ks_type":"VILLAGE",
    "name:eng_x_preferred":[
        "Patapadar"
    ],
    "wof:name":"Patapadar",
    "wof:placetype":"locality",
    "wof:population":170
},
  "geometry": {"coordinates":[84.35862,19.404384],"type":"Point"}
}