{
  "type": "Feature",
  "properties": {
    "iso:country":"IN",
    "ks:ks_name":"Chikkabinthala",
    "ks:ks_pop":28,
    "ks:ks_type":"HABITATION",
    "name:eng_x_preferred":[
        "Chikkabinthala"
    ],
    "wof:name":"Chikkabinthala",
    "wof:placetype":"locality",
    "wof:population":28
},
  "geometry": {"coordinates":[75.198436,13.683018],"type":"Point"}
}