{
  "type": "Feature",
  "properties": {
    "iso:country":"IN",
    "ks:ks_name":"Sadhawala",
    "ks:ks_pop":203,
    "ks:ks_type":"VILLAGE",
    "name:eng_x_preferred":[
        "Sadhawala"
    ],
    "wof:name":"Sadhawala",
    "wof:placetype":"locality",
    "wof:population":203
},
  "geometry": {"coordinates":[70.246629,27.641934],"type":"Point"}
}