{
  "type": "Feature",
  "properties": {
    "gn:admin1_code":"12.0",
    "gn:admin2_code":"7.0",
    "gn:asciiname":"Kopri",
    "gn:country_code":"IN",
    "gn:dem":666,
    "gn:feature_class":"P",
    "gn:feature_code":"PPL",
    "gn:name":"Kopri",
    "gn:population":0,
    "gn:timezone":"Asia/Kolkata",
    "iso:country":"IN",
    "name:ara_x_preferred":[
        "\u0643\u0648\u0628\u0631\u064a"
    ],
    "name:ben_bn_x_preferred":[
        "\u0995\u09cb\u09aa\u09b0\u09bf"
    ],
    "name:ben_in_x_preferred":[
        "\u0995\u09cb\u09aa\u09cd\u09b0\u09bf"
    ],
    "name:guj_x_preferred":[
        "\u0a95\u0acb\u0aaa\u0ab0\u0ac0"
    ],
    "name:hin_x_preferred":[
        "\u0915\u094b\u092a\u0930\u0940"
    ],
    "name:kan_x_preferred":[
        "\u0c95\u0cca\u0caa\u0ccd\u0cb0\u0cbf"
    ],
    "name:mal_x_preferred":[
        "\u0d15\u0d4b\u0d2a\u0d4d\u0d30\u0d3f"
    ],
    "name:mar_x_preferred":[
        "\u0915\u094b\u092a\u0930\u0940"
    ],
    "name:pan_x_preferred":[
        "\u0a15\u0a4c\u0a2a\u0a30\u0a40"
    ],
    "name:tam_x_preferred":[
        "\u0b95\u0bca\u0baa\u0bcd\u0bb0\u0bbf"
    ],
    "name:tam_x_variant":[
        "\u0b95\u0bcb\u0baa\u0bcd\u0bb0\u0bbf"
    ],
    "name:tel_x_preferred":[
        "\u0c15\u0c4b\u0c2a\u0c4d\u0c30\u0c3f"
    ],
    "name:urd_x_preferred":[
        "\u06a9\u0648\u067e\u0631\u06cc"
    ],
    "wof:name":"Kopri",
    "wof:placetype":"locality"
},
  "geometry": {"coordinates":[75.64485000000001,32.54574],"type":"Point"}
}