{
  "type": "Feature",
  "properties": {
    "gn:admin1_code":"12.0",
    "gn:admin2_code":"7.0",
    "gn:asciiname":"Kopri",
    "gn:country_code":"IN",
    "gn:dem":666,
    "gn:feature_class":"P",
    "gn:feature_code":"PPL",
    "gn:name":"Kopri",
    "gn:population":0,
    "gn:timezone":"Asia/Kolkata",
    "iso:country":"IN",
    "name:hin_x_preferred":[
        "\u0915\u094b\u092a\u0930\u0940"
    ],
    "name:mar_x_preferred":[
        "\u0915\u094b\u092a\u0930\u0940"
    ],
    "name:tam_x_preferred":[
        "\u0b95\u0bcb\u0baa\u0bcd\u0bb0\u0bbf"
    ],
    "wof:name":"Kopri",
    "wof:placetype":"locality"
},
  "geometry": {"coordinates":[75.64485000000001,32.54574],"type":"Point"}
}