{
  "type": "Feature",
  "properties": {
    "iso:country":"IN",
    "ks:ks_name":"Yadav Tola",
    "ks:ks_pop":199,
    "ks:ks_type":"HABITATION",
    "name:eng_x_preferred":[
        "Yadav Tola"
    ],
    "wof:name":"Yadav Tola",
    "wof:placetype":"locality",
    "wof:population":199
},
  "geometry": {"coordinates":[85.66252299999999,25.375951],"type":"Point"}
}