{
  "type": "Feature",
  "properties": {
    "iso:country":"IN",
    "ks:ks_name":"Dharmpur",
    "ks:ks_type":"VILLAGE",
    "ks:ks_uagg_main":0,
    "name:eng_x_preferred":[
        "Dharmpur"
    ],
    "wof:name":"Dharmpur",
    "wof:placetype":"neighbourhood"
},
  "geometry": {"coordinates":[76.924548,30.810436],"type":"Point"}
}