{
  "type": "Feature",
  "properties": {
    "iso:country":"IN",
    "ks:ks_name":"Kallippara",
    "ks:ks_pop":325,
    "ks:ks_type":"HABITATION",
    "name:eng_x_preferred":[
        "Kallippara"
    ],
    "wof:name":"Kallippara",
    "wof:placetype":"locality",
    "wof:population":325
},
  "geometry": {"coordinates":[77.222424,9.955368],"type":"Point"}
}