{
  "type": "Feature",
  "properties": {
    "gn:admin1_code":"19.0",
    "gn:admin2_code":"570.0",
    "gn:asciiname":"Nidagodu",
    "gn:country_code":"IN",
    "gn:dem":1017,
    "gn:feature_class":"P",
    "gn:feature_code":"PPL",
    "gn:name":"Nidagodu",
    "gn:population":0,
    "gn:timezone":"Asia/Kolkata",
    "iso:country":"IN",
    "ks:ks_alt_nam":"nidugod",
    "ks:ks_name":"Nidugod",
    "ks:ks_pop":265,
    "ks:ks_type":"HABITATION",
    "name:eng_x_preferred":[
        "Nidugod"
    ],
    "name:eng_x_variant":[
        "Nidagodu"
    ],
    "wof:name":"Nidugod",
    "wof:placetype":"locality",
    "wof:population":265
},
  "geometry": {"coordinates":[75.62558799999999,13.376739],"type":"Point"}
}