{
  "type": "Feature",
  "properties": {
    "iso:country":"IN",
    "ks:ks_name":"Chavan Mestriwadi",
    "ks:ks_pop":37,
    "ks:ks_type":"HABITATION",
    "name:eng_x_preferred":[
        "Chavan Mestriwadi"
    ],
    "wof:name":"Chavan Mestriwadi",
    "wof:placetype":"locality",
    "wof:population":37
},
  "geometry": {"coordinates":[73.56726999999999,16.179577],"type":"Point"}
}