{
  "type": "Feature",
  "properties": {
    "iso:country":"IN",
    "ks:ks_alt_nam":"BISWAMONI PARA",
    "ks:ks_name":"Biswamoni Para",
    "ks:ks_pop":68,
    "ks:ks_type":"HABITATION",
    "name:eng_x_preferred":[
        "Biswamoni Para"
    ],
    "wof:name":"Biswamoni Para",
    "wof:placetype":"locality",
    "wof:population":68
},
  "geometry": {"coordinates":[91.751831,23.781449],"type":"Point"}
}