{
  "type": "Feature",
  "properties": {
    "iso:country":"IN",
    "ks:ks_name":"Varachiwadi",
    "ks:ks_pop":132,
    "ks:ks_type":"HABITATION",
    "name:eng_x_preferred":[
        "Varachiwadi"
    ],
    "wof:name":"Varachiwadi",
    "wof:placetype":"locality",
    "wof:population":132
},
  "geometry": {"coordinates":[73.649636,16.386179],"type":"Point"}
}