{
  "type": "Feature",
  "properties": {
    "gn:admin1_code":"9.0",
    "gn:admin2_code":"483.0",
    "gn:asciiname":"Chayusa Muwara",
    "gn:country_code":"IN",
    "gn:dem":92,
    "gn:feature_class":"P",
    "gn:feature_code":"PPL",
    "gn:name":"Chayusa Muwara",
    "gn:population":0,
    "gn:timezone":"Asia/Kolkata",
    "iso:country":"IN",
    "wof:name":"Chayusa Muwara",
    "wof:placetype":"neighbourhood"
},
  "geometry": {"coordinates":[73.22329999999999,23.00254],"type":"Point"}
}