{
  "type": "Feature",
  "properties": {
    "iso:country":"IN",
    "ks:ks_name":"Singipur",
    "ks:ks_pop":923,
    "ks:ks_type":"VILLAGE",
    "ks:ks_uagg_main":0,
    "name:eng_x_preferred":[
        "Singipur"
    ],
    "wof:name":"Singipur",
    "wof:placetype":"neighbourhood",
    "wof:population":923
},
  "geometry": {"coordinates":[84.94898999999999,19.437404],"type":"Point"}
}