{
  "type": "Feature",
  "properties": {
    "gn:admin1_code":"24.0",
    "gn:admin2_code":"122.0",
    "gn:asciiname":"Chamaro ki Jhupriyan",
    "gn:country_code":"IN",
    "gn:dem":411,
    "gn:feature_class":"P",
    "gn:feature_code":"PPL",
    "gn:name":"Chamaro ki Jhupriy\u0101n",
    "gn:population":0,
    "gn:timezone":"Asia/Kolkata",
    "iso:country":"IN",
    "wof:name":"Chamaro ki Jhupriyan",
    "wof:placetype":"locality"
},
  "geometry": {"coordinates":[74.63800000000001,25.20652],"type":"Point"}
}