{
  "type": "Feature",
  "properties": {
    "iso:country":"IN",
    "ks:ks_name":"Baliposh",
    "ks:ks_pop":197,
    "ks:ks_type":"HABITATION",
    "name:eng_x_preferred":[
        "Baliposh"
    ],
    "wof:name":"Baliposh",
    "wof:placetype":"locality",
    "wof:population":197
},
  "geometry": {"coordinates":[86.30060899999999,22.619682],"type":"Point"}
}