{
  "type": "Feature",
  "properties": {
    "iso:country":"IN",
    "ks:ks_alt_nam":"Ch.Y.Tuni",
    "ks:ks_name":"Ch.y.tuni",
    "ks:ks_pop":233,
    "ks:ks_type":"HABITATION",
    "name:eng_x_preferred":[
        "Ch.y.tuni"
    ],
    "wof:name":"Ch.y.tuni",
    "wof:placetype":"locality",
    "wof:population":233
},
  "geometry": {"coordinates":[82.890131,17.581372],"type":"Point"}
}