{
  "type": "Feature",
  "properties": {
    "gn:admin1_code":"34.0",
    "gn:admin2_code":"213.0",
    "gn:asciiname":"Chakla",
    "gn:country_code":"IN",
    "gn:dem":49,
    "gn:feature_class":"P",
    "gn:feature_code":"PPL",
    "gn:name":"Chakla",
    "gn:population":0,
    "gn:timezone":"Asia/Kolkata",
    "iso:country":"IN",
    "name:hin_x_preferred":[
        "\u091a\u0915\u0932\u093e"
    ],
    "wof:name":"Chakla",
    "wof:placetype":"neighbourhood"
},
  "geometry": {"coordinates":[86.65282000000001,25.94729],"type":"Point"}
}