{
  "type": "Feature",
  "properties": {
    "iso:country":"IN",
    "ks:ks_name":"Barakuda",
    "ks:ks_pop":211,
    "ks:ks_type":"HABITATION",
    "name:eng_x_preferred":[
        "Barakuda"
    ],
    "wof:name":"Barakuda",
    "wof:placetype":"locality",
    "wof:population":211
},
  "geometry": {"coordinates":[84.558215,20.088036],"type":"Point"}
}