{
  "type": "Feature",
  "properties": {
    "iso:country":"IN",
    "ks:ks_name":"Barar",
    "ks:ks_pop":206,
    "ks:ks_type":"VILLAGE",
    "name:eng_x_preferred":[
        "Barar"
    ],
    "wof:name":"Barar",
    "wof:placetype":"locality",
    "wof:population":206
},
  "geometry": {"coordinates":[80.139353,29.823972],"type":"Point"}
}