{
  "type": "Feature",
  "properties": {
    "iso:country":"IN",
    "ks:ks_name":"Prabhudevar Hatti",
    "ks:ks_pop":43,
    "ks:ks_type":"HABITATION",
    "name:eng_x_preferred":[
        "Prabhudevar Hatti"
    ],
    "wof:name":"Prabhudevar Hatti",
    "wof:placetype":"locality",
    "wof:population":43
},
  "geometry": {"coordinates":[75.954201,16.927638],"type":"Point"}
}