{
  "type": "Feature",
  "properties": {
    "iso:country":"IN",
    "ks:ks_alt_nam":"chillithodu",
    "ks:ks_name":"Chillithodu",
    "ks:ks_pop":893,
    "ks:ks_type":"HABITATION",
    "name:eng_x_preferred":[
        "Chillithodu"
    ],
    "wof:name":"Chillithodu",
    "wof:placetype":"locality",
    "wof:population":893
},
  "geometry": {"coordinates":[76.86675099999999,10.040763],"type":"Point"}
}