{
  "type": "Feature",
  "properties": {
    "iso:country":"IN",
    "ks:ks_name":"Dokapara",
    "ks:ks_pop":97,
    "ks:ks_type":"HABITATION",
    "name:eng_x_preferred":[
        "Dokapara"
    ],
    "wof:name":"Dokapara",
    "wof:placetype":"locality",
    "wof:population":97
},
  "geometry": {"coordinates":[81.388818,18.496931],"type":"Point"}
}