{
  "type": "Feature",
  "properties": {
    "iso:country":"IN",
    "ks:ks_name":"Chalkewadi",
    "ks:ks_pop":762,
    "ks:ks_type":"VILLAGE",
    "name:eng_x_preferred":[
        "Chalkewadi"
    ],
    "wof:name":"Chalkewadi",
    "wof:placetype":"locality",
    "wof:population":762
},
  "geometry": {"coordinates":[73.842023,17.596997],"type":"Point"}
}