{
  "type": "Feature",
  "properties": {
    "gn:admin1_code":"19.0",
    "gn:admin2_code":"570.0",
    "gn:asciiname":"Madhalu",
    "gn:country_code":"IN",
    "gn:dem":729,
    "gn:feature_class":"P",
    "gn:feature_code":"PPL",
    "gn:name":"M\u0101dh\u0101lu",
    "gn:population":0,
    "gn:timezone":"Asia/Kolkata",
    "iso:country":"IN",
    "wof:name":"Madhalu",
    "wof:placetype":"locality"
},
  "geometry": {"coordinates":[76.10614,13.51212],"type":"Point"}
}