{
  "type": "Feature",
  "properties": {
    "iso:country":"IN",
    "ks:ks_name":"Kaduvettikollai",
    "ks:ks_pop":125,
    "ks:ks_type":"HABITATION",
    "name:eng_x_preferred":[
        "Kaduvettikollai"
    ],
    "wof:name":"Kaduvettikollai",
    "wof:placetype":"locality",
    "wof:population":125
},
  "geometry": {"coordinates":[79.161343,10.075287],"type":"Point"}
}