{
  "type": "Feature",
  "properties": {
    "iso:country":"IN",
    "ks:ks_alt_nam":"\u0100ladahalli",
    "ks:ks_name":"Aladahalli",
    "ks:ks_type":"VILLAGE",
    "name:eng_x_preferred":[
        "Aladahalli"
    ],
    "name:eng_x_variant":[
        "\u0100ladahalli"
    ],
    "wof:name":"Aladahalli",
    "wof:placetype":"locality"
},
  "geometry": {"coordinates":[76.074951,13.594159],"type":"Point"}
}