{
  "type": "Feature",
  "properties": {
    "gn:admin1_code":"34.0",
    "gn:admin2_code":"232.0",
    "gn:asciiname":"Balapur",
    "gn:country_code":"IN",
    "gn:dem":68,
    "gn:feature_class":"P",
    "gn:feature_code":"PPL",
    "gn:name":"B\u0101l\u0101pur",
    "gn:population":0,
    "gn:timezone":"Asia/Kolkata",
    "iso:country":"IN",
    "name:mar_x_preferred":[
        "\u092c\u093e\u0933\u093e\u092a\u0942\u0930"
    ],
    "wof:name":"Balapur",
    "wof:placetype":"locality"
},
  "geometry": {"coordinates":[84.03789999999999,25.58997],"type":"Point"}
}