{
  "type": "Feature",
  "properties": {
    "gn:admin1_code":"25.0",
    "gn:admin2_code":"605.0",
    "gn:asciiname":"Melvayattanankuppam",
    "gn:country_code":"IN",
    "gn:dem":299,
    "gn:feature_class":"P",
    "gn:feature_code":"PPL",
    "gn:name":"M\u0113lvayatt\u0101n\u0101nkuppam",
    "gn:population":0,
    "gn:timezone":"Asia/Kolkata",
    "iso:country":"IN",
    "wof:name":"Melvayattanankuppam",
    "wof:placetype":"neighbourhood"
},
  "geometry": {"coordinates":[78.77549999999999,12.84962],"type":"Point"}
}