{
  "type": "Feature",
  "properties": {
    "iso:country":"IN",
    "ks:ks_name":"Ramapada",
    "ks:ks_pop":446,
    "ks:ks_type":"VILLAGE",
    "name:eng_x_preferred":[
        "Ramapada"
    ],
    "wof:name":"Ramapada",
    "wof:placetype":"locality",
    "wof:population":446
},
  "geometry": {"coordinates":[85.249154,20.272743],"type":"Point"}
}