{
  "type": "Feature",
  "properties": {
    "iso:country":"IN",
    "ks:ks_alt_nam":"PURB HARIZAN BASTI",
    "ks:ks_name":"Purb Harizan Basti",
    "ks:ks_pop":350,
    "ks:ks_type":"HABITATION",
    "name:eng_x_preferred":[
        "Purb Harizan Basti"
    ],
    "wof:name":"Purb Harizan Basti",
    "wof:placetype":"locality",
    "wof:population":350
},
  "geometry": {"coordinates":[83.992172,25.890126],"type":"Point"}
}