{
  "type": "Feature",
  "properties": {
    "gn:admin1_code":"36",
    "gn:admin2_code":"134.0",
    "gn:asciiname":"Birchand Nagla",
    "gn:country_code":"IN",
    "gn:dem":242,
    "gn:feature_class":"P",
    "gn:feature_code":"PPL",
    "gn:name":"B\u012brchand Nagla",
    "gn:population":0,
    "gn:timezone":"Asia/Kolkata",
    "iso:country":"IN",
    "name:und_x_variant":[
        "B\u012brchand Nagla",
        "Basehra Desu"
    ],
    "wof:name":"Birchand Nagla",
    "wof:placetype":"locality"
},
  "geometry": {"coordinates":[78.44365999999999,29.35989],"type":"Point"}
}