{
  "type": "Feature",
  "properties": {
    "gn:admin1_code":"25.0",
    "gn:admin2_code":"604.0",
    "gn:asciiname":"Vedanarayanapuram",
    "gn:country_code":"IN",
    "gn:dem":36,
    "gn:feature_class":"P",
    "gn:feature_code":"PPL",
    "gn:name":"Vedan\u0101r\u0101yanapuram",
    "gn:population":0,
    "gn:timezone":"Asia/Kolkata",
    "iso:country":"IN",
    "wof:name":"Vedanarayanapuram",
    "wof:placetype":"locality"
},
  "geometry": {"coordinates":[79.96545,12.65324],"type":"Point"}
}