{
  "type": "Feature",
  "properties": {
    "gn:admin1_code":"25.0",
    "gn:admin2_code":"631.0",
    "gn:asciiname":"Maddanapalli",
    "gn:country_code":"IN",
    "gn:dem":737,
    "gn:feature_class":"P",
    "gn:feature_code":"PPL",
    "gn:name":"Maddanapalli",
    "gn:population":0,
    "gn:timezone":"Asia/Kolkata",
    "iso:country":"IN",
    "wof:name":"Maddanapalli",
    "wof:placetype":"locality"
},
  "geometry": {"coordinates":[77.97981999999998,12.54422],"type":"Point"}
}