{
  "type": "Feature",
  "properties": {
    "iso:country":"IN",
    "ks:ks_name":"Songuda",
    "ks:ks_pop":807,
    "ks:ks_type":"VILLAGE",
    "name:eng_x_preferred":[
        "Songuda"
    ],
    "wof:name":"Songuda",
    "wof:placetype":"locality",
    "wof:population":807
},
  "geometry": {"coordinates":[82.70473,22.464459],"type":"Point"}
}