{
  "type": "Feature",
  "properties": {
    "gn:admin1_code":"19.0",
    "gn:admin2_code":"563.0",
    "gn:asciiname":"Kache",
    "gn:country_code":"IN",
    "gn:dem":29,
    "gn:feature_class":"P",
    "gn:feature_code":"PPL",
    "gn:name":"K\u0101che",
    "gn:population":0,
    "gn:timezone":"Asia/Kolkata",
    "iso:country":"IN",
    "wof:name":"Kache",
    "wof:placetype":"locality"
},
  "geometry": {"coordinates":[74.24731,14.90016],"type":"Point"}
}