{
  "type": "Feature",
  "properties": {
    "gn:admin1_code":"16",
    "gn:admin2_code":"524.0",
    "gn:asciiname":"Padarwadi",
    "gn:country_code":"IN",
    "gn:dem":633,
    "gn:feature_class":"P",
    "gn:feature_code":"PPL",
    "gn:name":"Padarw\u0101di",
    "gn:population":0,
    "gn:timezone":"Asia/Kolkata",
    "iso:country":"IN",
    "wof:name":"Padarwadi",
    "wof:placetype":"neighbourhood"
},
  "geometry": {"coordinates":[76.38258999999999,18.14968],"type":"Point"}
}