{
  "type": "Feature",
  "properties": {
    "iso:country":"IN",
    "ks:ks_name":"Farangipete",
    "ks:ks_pop":1004,
    "ks:ks_type":"HABITATION",
    "ks:ks_uagg_main":0,
    "name:eng_x_preferred":[
        "Farangipete"
    ],
    "wof:name":"Farangipete",
    "wof:placetype":"neighbourhood",
    "wof:population":1004
},
  "geometry": {"coordinates":[74.95768,12.874144],"type":"Point"}
}