{
  "type": "Feature",
  "properties": {
    "iso:country":"IN",
    "ks:ks_name":"Ujirhati",
    "ks:ks_pop":271,
    "ks:ks_type":"VILLAGE",
    "ks:ks_uagg_main":0,
    "name:eng_x_preferred":[
        "Ujirhati"
    ],
    "wof:name":"Ujirhati",
    "wof:placetype":"neighbourhood",
    "wof:population":271
},
  "geometry": {"coordinates":[87.816709,23.07502],"type":"Point"}
}