{
  "type": "Feature",
  "properties": {
    "gn:admin1_code":"24.0",
    "gn:admin2_code":"102.0",
    "gn:asciiname":"Degan Dhani",
    "gn:country_code":"IN",
    "gn:dem":278,
    "gn:feature_class":"P",
    "gn:feature_code":"PPL",
    "gn:name":"Deg\u0101n Dh\u0101ni",
    "gn:population":0,
    "gn:timezone":"Asia/Kolkata",
    "iso:country":"IN",
    "wof:name":"Degan Dhani",
    "wof:placetype":"locality"
},
  "geometry": {"coordinates":[74.49139,28.27304],"type":"Point"}
}