{
  "type": "Feature",
  "properties": {
    "gn:admin1_code":"35",
    "gn:admin2_code":"457.0",
    "gn:asciiname":"Jamuniya",
    "gn:country_code":"IN",
    "gn:dem":364,
    "gn:feature_class":"P",
    "gn:feature_code":"PPL",
    "gn:name":"Jamuniya",
    "gn:population":0,
    "gn:timezone":"Asia/Kolkata",
    "iso:country":"IN",
    "name:fra_x_preferred":[
        "Jamuniya"
    ],
    "name:nep_x_preferred":[
        "\u091c\u092e\u0941\u0928\u093f\u092f\u093e"
    ],
    "wof:name":"Jamuniya",
    "wof:placetype":"locality"
},
  "geometry": {"coordinates":[79.8248,21.82364],"type":"Point"}
}