{
  "type": "Feature",
  "properties": {
    "iso:country":"IN",
    "ks:ks_name":"Sankiliguda",
    "ks:ks_pop":32,
    "ks:ks_type":"HABITATION",
    "name:eng_x_preferred":[
        "Sankiliguda"
    ],
    "wof:name":"Sankiliguda",
    "wof:placetype":"locality",
    "wof:population":32
},
  "geometry": {"coordinates":[83.79487899999999,18.733948],"type":"Point"}
}