{
  "type": "Feature",
  "properties": {
    "gn:admin1_code":"19.0",
    "gn:admin2_code":"565.0",
    "gn:asciiname":"Mallapuram",
    "gn:country_code":"IN",
    "gn:dem":618,
    "gn:feature_class":"P",
    "gn:feature_code":"PPL",
    "gn:name":"Mall\u0101puram",
    "gn:population":0,
    "gn:timezone":"Asia/Kolkata",
    "iso:country":"IN",
    "name:tam_x_preferred":[
        "\u0bae\u0bb2\u0bcd\u0bb2\u0baa\u0bc1\u0bb0\u0bae\u0bcd"
    ],
    "wof:name":"Mallapuram",
    "wof:placetype":"neighbourhood"
},
  "geometry": {"coordinates":[76.69858000000001,15.02224],"type":"Point"}
}