{
  "type": "Feature",
  "properties": {
    "iso:country":"IN",
    "ks:ks_name":"Mandupara",
    "ks:ks_pop":53,
    "ks:ks_type":"HABITATION",
    "name:eng_x_preferred":[
        "Mandupara"
    ],
    "wof:name":"Mandupara",
    "wof:placetype":"locality",
    "wof:population":53
},
  "geometry": {"coordinates":[81.080568,18.43636],"type":"Point"}
}