{
  "type": "Feature",
  "properties": {
    "iso:country":"IN",
    "ks:ks_name":"Indrajhor",
    "ks:ks_pop":608,
    "ks:ks_type":"VILLAGE",
    "name:eng_x_preferred":[
        "Indrajhor"
    ],
    "wof:name":"Indrajhor",
    "wof:placetype":"locality",
    "wof:population":608
},
  "geometry": {"coordinates":[86.928304,22.880638],"type":"Point"}
}