{
  "type": "Feature",
  "properties": {
    "gn:admin1_code":"36",
    "gn:admin2_code":"193.0",
    "gn:asciiname":"Dehri Shahkarpur",
    "gn:country_code":"IN",
    "gn:dem":69,
    "gn:feature_class":"P",
    "gn:feature_code":"PPL",
    "gn:name":"Dehr\u012b Shahkarpur",
    "gn:population":0,
    "gn:timezone":"Asia/Kolkata",
    "iso:country":"IN",
    "wof:name":"Dehri Shahkarpur",
    "wof:placetype":"locality"
},
  "geometry": {"coordinates":[83.92298000000002,25.91042],"type":"Point"}
}