{
  "type": "Feature",
  "properties": {
    "gn:admin1_code":"25.0",
    "gn:admin2_code":"633.0",
    "gn:asciiname":"Kangayampalaiyampudur",
    "gn:country_code":"IN",
    "gn:dem":296,
    "gn:feature_class":"P",
    "gn:feature_code":"PPL",
    "gn:name":"K\u0101ngayamp\u0101laiyampud\u016br",
    "gn:population":0,
    "gn:timezone":"Asia/Kolkata",
    "iso:country":"IN",
    "wof:name":"Kangayampalaiyampudur",
    "wof:placetype":"neighbourhood"
},
  "geometry": {"coordinates":[77.36291,11.0996],"type":"Point"}
}