{
  "type": "Feature",
  "properties": {
    "gn:admin1_code":"11.0",
    "gn:admin2_code":"33.0",
    "gn:asciiname":"Chatti",
    "gn:country_code":"IN",
    "gn:dem":2225,
    "gn:feature_class":"P",
    "gn:feature_code":"PPL",
    "gn:name":"Chatti",
    "gn:population":0,
    "gn:timezone":"Asia/Kolkata",
    "iso:country":"IN",
    "name:ang_x_preferred":[
        "Hetware"
    ],
    "name:ara_x_preferred":[
        "\u062e\u0627\u062a\u064a\u0648\u0646"
    ],
    "name:bul_x_preferred":[
        "\u0425\u0430\u0442\u0438"
    ],
    "name:cat_x_preferred":[
        "Cats"
    ],
    "name:ces_x_preferred":[
        "Chattov\u00e9"
    ],
    "name:chv_x_preferred":[
        "\u0425\u0430\u0442\u0442\u0441\u0435\u043c"
    ],
    "name:dan_x_preferred":[
        "Chattere"
    ],
    "name:deu_x_preferred":[
        "Chatten"
    ],
    "name:ell_x_preferred":[
        "\u03a7\u03ac\u03c4\u03c4\u03b5\u03c2"
    ],
    "name:epo_x_preferred":[
        "\u0124atoj"
    ],
    "name:eus_x_preferred":[
        "Kato"
    ],
    "name:fin_x_preferred":[
        "Khattit"
    ],
    "name:fra_x_preferred":[
        "Chattes"
    ],
    "name:fry_x_preferred":[
        "Sjatten"
    ],
    "name:glg_x_preferred":[
        "Chatti"
    ],
    "name:hun_x_preferred":[
        "Chattusok"
    ],
    "name:ita_x_preferred":[
        "Catti"
    ],
    "name:kor_x_preferred":[
        "\uce74\ud2f0\uc871"
    ],
    "name:lat_x_preferred":[
        "Chatti"
    ],
    "name:ltz_x_preferred":[
        "Chatten"
    ],
    "name:mkd_x_preferred":[
        "\u0425\u0430\u0442\u0438"
    ],
    "name:nld_x_preferred":[
        "Chatten"
    ],
    "name:nor_x_preferred":[
        "Chattere"
    ],
    "name:pol_x_preferred":[
        "Chattowie"
    ],
    "name:por_x_preferred":[
        "Catos"
    ],
    "name:ron_x_preferred":[
        "Chatti"
    ],
    "name:rus_x_preferred":[
        "\u0425\u0430\u0442\u0442\u044b"
    ],
    "name:slv_x_preferred":[
        "Hati"
    ],
    "name:spa_x_preferred":[
        "Catos"
    ],
    "name:srp_x_preferred":[
        "\u0425\u0430\u0442\u0438"
    ],
    "name:swe_x_preferred":[
        "Chatter"
    ],
    "name:ukr_x_preferred":[
        "\u0425\u0430\u0442\u0442\u0438"
    ],
    "wof:name":"Chatti",
    "wof:placetype":"locality"
},
  "geometry": {"coordinates":[77.48554,31.29289],"type":"Point"}
}