{
  "type": "Feature",
  "properties": {
    "iso:country":"IN",
    "ks:ks_name":"Jatiakholdihi",
    "ks:ks_pop":265,
    "ks:ks_type":"VILLAGE",
    "name:eng_x_preferred":[
        "Jatiakholdihi"
    ],
    "wof:name":"Jatiakholdihi",
    "wof:placetype":"locality",
    "wof:population":265
},
  "geometry": {"coordinates":[84.34541400000001,21.606372],"type":"Point"}
}