{
  "type": "Feature",
  "properties": {
    "iso:country":"IN",
    "ks:ks_name":"Adipadar",
    "ks:ks_pop":40,
    "ks:ks_type":"VILLAGE",
    "name:eng_x_preferred":[
        "Adipadar"
    ],
    "wof:name":"Adipadar",
    "wof:placetype":"locality",
    "wof:population":40
},
  "geometry": {"coordinates":[84.505443,20.556506],"type":"Point"}
}