{
  "type": "Feature",
  "properties": {
    "iso:country":"IN",
    "ks:ks_name":"Banthivada Lalakumpa",
    "ks:ks_pop":1365,
    "ks:ks_type":"VILLAGE",
    "name:eng_x_preferred":[
        "Banthivada Lalakumpa"
    ],
    "wof:name":"Banthivada Lalakumpa",
    "wof:placetype":"locality",
    "wof:population":1365
},
  "geometry": {"coordinates":[73.52306400000001,23.46564],"type":"Point"}
}