{
  "type": "Feature",
  "properties": {
    "gn:admin1_code":"24",
    "gn:admin2_code":"101.0",
    "gn:asciiname":"Punrasar",
    "gn:country_code":"IN",
    "gn:dem":220,
    "gn:feature_class":"P",
    "gn:feature_code":"PPL",
    "gn:name":"Punr\u0101sar",
    "gn:population":0,
    "gn:timezone":"Asia/Kolkata",
    "iso:country":"IN",
    "name:und_x_variant":[
        "Punr\u0101sar"
    ],
    "wof:name":"Punrasar",
    "wof:placetype":"locality"
},
  "geometry": {"coordinates":[73.78870999999999,28.20949],"type":"Point"}
}