{
  "type": "Feature",
  "properties": {
    "gn:admin1_code":"36.0",
    "gn:admin2_code":"183.0",
    "gn:asciiname":"Khiraura Shahbaz",
    "gn:country_code":"IN",
    "gn:dem":111,
    "gn:feature_class":"P",
    "gn:feature_code":"PPL",
    "gn:name":"Khiraura Sh\u0101hb\u0101z",
    "gn:population":0,
    "gn:timezone":"Asia/Kolkata",
    "iso:country":"IN",
    "wof:name":"Khiraura Shahbaz",
    "wof:placetype":"locality"
},
  "geometry": {"coordinates":[82.01691,27.24108],"type":"Point"}
}