{
  "type": "Feature",
  "properties": {
    "iso:country":"IN",
    "ks:ks_alt_nam":"Peela ka Tapra",
    "ks:ks_name":"Peela Ka Tapra",
    "ks:ks_pop":50,
    "ks:ks_type":"HABITATION",
    "ks:ks_uagg_main":0,
    "name:eng_x_preferred":[
        "Peela Ka Tapra"
    ],
    "wof:name":"Peela Ka Tapra",
    "wof:placetype":"neighbourhood",
    "wof:population":50
},
  "geometry": {"coordinates":[76.254047,26.174933],"type":"Point"}
}