{
  "type": "Feature",
  "properties": {
    "iso:country":"IN",
    "ks:ks_name":"Jamukhole",
    "ks:ks_pop":135,
    "ks:ks_type":"HABITATION",
    "name:eng_x_preferred":[
        "Jamukhole"
    ],
    "wof:name":"Jamukhole",
    "wof:placetype":"locality",
    "wof:population":135
},
  "geometry": {"coordinates":[83.839523,20.632708],"type":"Point"}
}