{
  "type": "Feature",
  "properties": {
    "gn:admin1_code":"39.0",
    "gn:admin2_code":"64.0",
    "gn:asciiname":"Dabhari",
    "gn:country_code":"IN",
    "gn:dem":1492,
    "gn:feature_class":"P",
    "gn:feature_code":"PPL",
    "gn:name":"D\u0101bhari",
    "gn:population":0,
    "gn:timezone":"Asia/Kolkata",
    "iso:country":"IN",
    "wof:name":"Dabhari",
    "wof:placetype":"locality"
},
  "geometry": {"coordinates":[79.36190999999999,29.63104],"type":"Point"}
}