{
  "type": "Feature",
  "properties": {
    "gn:admin1_code":"36",
    "gn:admin2_code":"158.0",
    "gn:asciiname":"Bakhri",
    "gn:country_code":"IN",
    "gn:dem":122,
    "gn:feature_class":"P",
    "gn:feature_code":"PPL",
    "gn:name":"Bakhri",
    "gn:population":0,
    "gn:timezone":"Asia/Kolkata",
    "iso:country":"IN",
    "wof:name":"Bakhri",
    "wof:placetype":"locality"
},
  "geometry": {"coordinates":[80.99459,26.24194],"type":"Point"}
}