{
  "type": "Feature",
  "properties": {
    "gn:admin1_code":"37",
    "gn:admin2_code":"411.0",
    "gn:asciiname":"Dumarpali",
    "gn:country_code":"IN",
    "gn:dem":312,
    "gn:feature_class":"P",
    "gn:feature_code":"PPL",
    "gn:name":"Dumarp\u0101li",
    "gn:population":0,
    "gn:timezone":"Asia/Kolkata",
    "iso:country":"IN",
    "ks:ks_alt_nam":"Dumarp\u0101li",
    "ks:ks_name":"Dumarpali",
    "ks:ks_pop":967,
    "ks:ks_type":"VILLAGE",
    "name:eng_x_preferred":[
        "Dumarpali"
    ],
    "name:eng_x_variant":[
        "Dumarp\u0101li"
    ],
    "wof:name":"Dumarpali",
    "wof:placetype":"locality",
    "wof:population":967
},
  "geometry": {"coordinates":[82.43679,21.238577],"type":"Point"}
}