{
  "type": "Feature",
  "properties": {
    "iso:country":"IN",
    "ks:ks_name":"Vatitarani",
    "ks:ks_pop":26,
    "ks:ks_type":"HABITATION",
    "name:eng_x_preferred":[
        "Vatitarani"
    ],
    "wof:name":"Vatitarani",
    "wof:placetype":"locality",
    "wof:population":26
},
  "geometry": {"coordinates":[74.32671000000001,14.542044],"type":"Point"}
}