{
  "type": "Feature",
  "properties": {
    "gn:admin1_code":"25.0",
    "gn:admin2_code":"611.0",
    "gn:asciiname":"Bennehadi",
    "gn:country_code":"IN",
    "gn:dem":975,
    "gn:feature_class":"P",
    "gn:feature_code":"PPL",
    "gn:name":"Bennehadi",
    "gn:population":0,
    "gn:timezone":"Asia/Kolkata",
    "iso:country":"IN",
    "wof:name":"Bennehadi",
    "wof:placetype":"locality"
},
  "geometry": {"coordinates":[76.3978,11.59581],"type":"Point"}
}