{
  "type": "Feature",
  "properties": {
    "iso:country":"IN",
    "ks:ks_name":"Lakhai Beni Nagar",
    "ks:ks_pop":1008,
    "ks:ks_type":"HABITATION",
    "name:eng_x_preferred":[
        "Lakhai Beni Nagar"
    ],
    "wof:name":"Lakhai Beni Nagar",
    "wof:placetype":"locality",
    "wof:population":1008
},
  "geometry": {"coordinates":[81.94546099999999,27.708298],"type":"Point"}
}