{
  "type": "Feature",
  "properties": {
    "gn:admin1_code":"34",
    "gn:admin2_code":"224.0",
    "gn:asciiname":"Sonahula",
    "gn:country_code":"IN",
    "gn:dem":50,
    "gn:feature_class":"P",
    "gn:feature_code":"PPL",
    "gn:name":"Sonahula",
    "gn:population":0,
    "gn:timezone":"Asia/Kolkata",
    "iso:country":"IN",
    "wof:name":"Sonahula",
    "wof:placetype":"locality"
},
  "geometry": {"coordinates":[87.16226,25.09002000000001],"type":"Point"}
}