{
  "type": "Feature",
  "properties": {
    "gn:admin1_code":"2.0",
    "gn:admin2_code":"554.0",
    "gn:asciiname":"Nakirepalle",
    "gn:country_code":"IN",
    "gn:dem":777,
    "gn:feature_class":"P",
    "gn:feature_code":"PPL",
    "gn:name":"N\u0101kirepalle",
    "gn:population":0,
    "gn:timezone":"Asia/Kolkata",
    "iso:country":"IN",
    "wof:name":"Nakirepalle",
    "wof:placetype":"locality"
},
  "geometry": {"coordinates":[78.49264000000002,13.31361],"type":"Point"}
}