{
  "type": "Feature",
  "properties": {
    "gn:admin1_code":"24.0",
    "gn:admin2_code":"131.0",
    "gn:asciiname":"Saipura",
    "gn:country_code":"IN",
    "gn:dem":233,
    "gn:feature_class":"P",
    "gn:feature_code":"PPL",
    "gn:name":"Saipura",
    "gn:population":0,
    "gn:timezone":"Asia/Kolkata",
    "iso:country":"IN",
    "wof:name":"Saipura",
    "wof:placetype":"locality"
},
  "geometry": {"coordinates":[74.49065,24.08276],"type":"Point"}
}