{
  "type": "Feature",
  "properties": {
    "gn:admin1_code":"10.0",
    "gn:admin2_code":"073",
    "gn:asciiname":"Jakhauli",
    "gn:country_code":"IN",
    "gn:dem":235,
    "gn:feature_class":"P",
    "gn:feature_code":"PPL",
    "gn:name":"Jakhauli",
    "gn:population":0,
    "gn:timezone":"Asia/Kolkata",
    "iso:country":"IN",
    "wof:name":"Jakhauli",
    "wof:placetype":"locality"
},
  "geometry": {"coordinates":[76.43878000000002,29.65515],"type":"Point"}
}