{
  "type": "Feature",
  "properties": {
    "gn:admin1_code":"34.0",
    "gn:admin2_code":"220.0",
    "gn:asciiname":"Chak Roshan",
    "gn:country_code":"IN",
    "gn:dem":56,
    "gn:feature_class":"P",
    "gn:feature_code":"PPL",
    "gn:name":"Chak Roshan",
    "gn:population":0,
    "gn:timezone":"Asia/Kolkata",
    "iso:country":"IN",
    "ks:ks_name":"Chak Roshan",
    "ks:ks_pop":259,
    "ks:ks_type":"VILLAGE",
    "name:eng_x_preferred":[
        "Chak Roshan"
    ],
    "wof:name":"Chak Roshan",
    "wof:placetype":"locality",
    "wof:population":259
},
  "geometry": {"coordinates":[85.26332600000001,25.808113],"type":"Point"}
}