{
  "type": "Feature",
  "properties": {
    "iso:country":"IN",
    "ks:ks_name":"Baburbani",
    "ks:ks_pop":433,
    "ks:ks_type":"VILLAGE",
    "name:eng_x_preferred":[
        "Baburbani"
    ],
    "wof:name":"Baburbani",
    "wof:placetype":"locality",
    "wof:population":433
},
  "geometry": {"coordinates":[87.123589,22.159894],"type":"Point"}
}