{
  "type": "Feature",
  "properties": {
    "iso:country":"IN",
    "ks:ks_name":"Hatheedo",
    "ks:ks_pop":462,
    "ks:ks_type":"VILLAGE",
    "name:eng_x_preferred":[
        "Hatheedo"
    ],
    "wof:name":"Hatheedo",
    "wof:placetype":"locality",
    "wof:population":462
},
  "geometry": {"coordinates":[74.10358100000001,24.385803],"type":"Point"}
}