{
  "type": "Feature",
  "properties": {
    "iso:country":"IN",
    "qs:name":"Chandni Chowk Area",
    "qs:name_adm0":"India",
    "qs:name_adm1":"West Bengal",
    "qs:photos":159,
    "qs:photos_1k":32,
    "qs:photos_9k":1,
    "qs:photos_9r":4,
    "qs:photos_all":159,
    "qs:photos_sr":4,
    "qs:placetype":"Suburb",
    "qs:pop_sr":"0",
    "wof:name":"Chandni Chowk Area",
    "wof:placetype":"neighbourhood"
},
  "geometry": {"coordinates":[88.360805,22.564719],"type":"Point"}
}