{
  "type": "Feature",
  "properties": {
    "iso:country":"IN",
    "name:ara_x_preferred":[
        "\u0645\u0646\u0637\u0642\u0629 \u0634\u0627\u0646\u062f\u064a \u0634\u0648\u0643"
    ],
    "name:ben_bn_x_preferred":[
        "\u099a\u09be\u0981\u09a6\u09a8\u09c0 \u099a\u0995 \u0985\u099e\u09cd\u099a\u09b2"
    ],
    "name:ben_in_x_preferred":[
        "\u099a\u09be\u0981\u09a6\u09a8\u09c0 \u099a\u0995 \u0985\u099e\u09cd\u099a\u09b2"
    ],
    "name:guj_x_preferred":[
        "\u0a9a\u0abe\u0a82\u0aa6\u0aa8\u0ac0 \u0a9a\u0acb\u0a95 \u0ab5\u0abf\u0ab8\u0acd\u0aa4\u0abe\u0ab0"
    ],
    "name:hin_x_preferred":[
        "\u091a\u093e\u0902\u0926\u0928\u0940 \u091a\u094c\u0915"
    ],
    "name:kan_x_preferred":[
        "\u0c9a\u0cbe\u0c82\u0ca6\u0ccd\u0ca8\u0cbf \u0c9a\u0ccc\u0c95\u0ccd"
    ],
    "name:mal_x_preferred":[
        "\u0d1a\u0d3e\u0d28\u0d4d\u0d26\u0d4d\u0d28\u0d3f \u0d1a\u0d57\u0d15\u0d4d\u0d15\u0d4d \u0d0f\u0d30\u0d3f\u0d2f"
    ],
    "name:mar_x_preferred":[
        "\u091a\u093e\u0902\u0926\u0923\u0940 \u091a\u094c\u0915 \u092a\u0930\u093f\u0938\u0930"
    ],
    "name:pan_x_preferred":[
        "\u0a1a\u0a3e\u0a02\u0a26\u0a28\u0a40 \u0a1a\u0a4c\u0a15 \u0a0f\u0a30\u0a40\u0a06"
    ],
    "name:tam_x_preferred":[
        "\u0b9a\u0bbe\u0ba8\u0bcd\u0ba4\u0bbf\u0ba9\u0bbf \u0b9a\u0bcc\u0b95\u0bcd \u0baa\u0b95\u0bc1\u0ba4\u0bbf"
    ],
    "name:tel_x_preferred":[
        "\u0c1a\u0c3e\u0c02\u0c26\u0c3f\u0c28\u0c3f \u0c1a\u0c4c\u0c15\u0c4d \u0c0f\u0c30\u0c3f\u0c2f\u0c3e"
    ],
    "name:urd_x_preferred":[
        "\u0686\u0627\u0646\u062f\u0646\u06cc \u0686\u0648\u06a9 \u0627\u06cc\u0631\u06cc\u0627"
    ],
    "qs:name":"Chandni Chowk Area",
    "qs:name_adm0":"India",
    "qs:name_adm1":"West Bengal",
    "qs:photos":159,
    "qs:photos_1k":32,
    "qs:photos_9k":1,
    "qs:photos_9r":4,
    "qs:photos_all":159,
    "qs:photos_sr":4,
    "qs:placetype":"Suburb",
    "qs:pop_sr":"0",
    "wof:name":"Chandni Chowk Area",
    "wof:placetype":"neighbourhood"
},
  "geometry": {"coordinates":[88.360805,22.564719],"type":"Point"}
}