{
  "type": "Feature",
  "properties": {
    "gn:admin1_code":"19.0",
    "gn:admin2_code":"573.0",
    "gn:asciiname":"Gundapura",
    "gn:country_code":"IN",
    "gn:dem":769,
    "gn:feature_class":"P",
    "gn:feature_code":"PPL",
    "gn:name":"Gund\u0101pura",
    "gn:population":0,
    "gn:timezone":"Asia/Kolkata",
    "iso:country":"IN",
    "ks:ks_alt_nam":"Gund\u0101pura",
    "ks:ks_name":"Gundapura",
    "ks:ks_pop":123,
    "ks:ks_type":"VILLAGE",
    "name:eng_x_preferred":[
        "Gundapura"
    ],
    "name:eng_x_variant":[
        "Gund\u0101pura"
    ],
    "wof:name":"Gundapura",
    "wof:placetype":"locality",
    "wof:population":123
},
  "geometry": {"coordinates":[76.810806,12.716855],"type":"Point"}
}