{
  "type": "Feature",
  "properties": {
    "gn:admin1_code":"19",
    "gn:admin2_code":"568.0",
    "gn:asciiname":"Nerlige",
    "gn:country_code":"IN",
    "gn:dem":580,
    "gn:feature_class":"P",
    "gn:feature_code":"PPL",
    "gn:name":"Nerlige",
    "gn:population":0,
    "gn:timezone":"Asia/Kolkata",
    "iso:country":"IN",
    "wof:name":"Nerlige",
    "wof:placetype":"locality"
},
  "geometry": {"coordinates":[74.98939,14.20623],"type":"Point"}
}