{
  "type": "Feature",
  "properties": {
    "iso:country":"IN",
    "ks:ks_alt_nam":"mayangichal",
    "ks:ks_name":"Mayangichal",
    "ks:ks_pop":950,
    "ks:ks_type":"HABITATION",
    "name:eng_x_preferred":[
        "Mayangichal"
    ],
    "wof:name":"Mayangichal",
    "wof:placetype":"locality",
    "wof:population":950
},
  "geometry": {"coordinates":[75.780677,11.422098],"type":"Point"}
}