{
  "type": "Feature",
  "properties": {
    "iso:country":"IN",
    "ks:ks_name":"Jadhavwadi",
    "ks:ks_pop":553,
    "ks:ks_type":"HABITATION",
    "name:eng_x_preferred":[
        "Jadhavwadi"
    ],
    "wof:name":"Jadhavwadi",
    "wof:placetype":"locality",
    "wof:population":553
},
  "geometry": {"coordinates":[76.047166,18.427006],"type":"Point"}
}