{
  "type": "Feature",
  "properties": {
    "iso:country":"IN",
    "ks:ks_alt_nam":"MOTI GIRI KA MAKHA",
    "ks:ks_name":"Moti Giri Ka Makha",
    "ks:ks_pop":37,
    "ks:ks_type":"HABITATION",
    "ks:ks_uagg_main":0,
    "name:eng_x_preferred":[
        "Moti Giri Ka Makha"
    ],
    "wof:name":"Moti Giri Ka Makha",
    "wof:placetype":"neighbourhood",
    "wof:population":37
},
  "geometry": {"coordinates":[81.902564,26.46288],"type":"Point"}
}