{
  "type": "Feature",
  "properties": {
    "iso:country":"IN",
    "ks:ks_name":"Singatanr",
    "ks:ks_pop":64,
    "ks:ks_type":"VILLAGE",
    "name:eng_x_preferred":[
        "Singatanr"
    ],
    "wof:name":"Singatanr",
    "wof:placetype":"locality",
    "wof:population":64
},
  "geometry": {"coordinates":[87.66197200000001,24.796371],"type":"Point"}
}