{
  "type": "Feature",
  "properties": {
    "iso:country":"IN",
    "ks:ks_name":"Jayanagara Form",
    "ks:ks_pop":109,
    "ks:ks_type":"HABITATION",
    "name:eng_x_preferred":[
        "Jayanagara Form"
    ],
    "wof:name":"Jayanagara Form",
    "wof:placetype":"locality",
    "wof:population":109
},
  "geometry": {"coordinates":[76.231944,13.8575],"type":"Point"}
}