{
  "type": "Feature",
  "properties": {
    "gn:admin1_code":"3.0",
    "gn:admin2_code":"300.0",
    "gn:asciiname":"Habrubil",
    "gn:country_code":"IN",
    "gn:dem":51,
    "gn:feature_class":"P",
    "gn:feature_code":"PPL",
    "gn:name":"H\u0101brub\u012bl",
    "gn:population":0,
    "gn:timezone":"Asia/Kolkata",
    "iso:country":"IN",
    "ks:ks_name":"Habrubil",
    "ks:ks_pop":3582,
    "ks:ks_type":"VILLAGE",
    "ks:ks_uagg_main":0,
    "name:eng_x_preferred":[
        "Habrubil"
    ],
    "wof:name":"Habrubil",
    "wof:placetype":"neighbourhood",
    "wof:population":3582
},
  "geometry": {"coordinates":[89.97476899999999,26.453415],"type":"Point"}
}