{
  "type": "Feature",
  "properties": {
    "iso:country":"IN",
    "ks:ks_name":"Gatiram Para",
    "ks:ks_pop":223,
    "ks:ks_type":"HABITATION",
    "name:eng_x_preferred":[
        "Gatiram Para"
    ],
    "wof:name":"Gatiram Para",
    "wof:placetype":"locality",
    "wof:population":223
},
  "geometry": {"coordinates":[91.729169,23.528971],"type":"Point"}
}