{
  "type": "Feature",
  "properties": {
    "iso:country":"IN",
    "ks:ks_alt_nam":"Patel faliya",
    "ks:ks_name":"Patel Faliya",
    "ks:ks_pop":133,
    "ks:ks_type":"HABITATION",
    "name:eng_x_preferred":[
        "Patel Faliya"
    ],
    "wof:name":"Patel Faliya",
    "wof:placetype":"locality",
    "wof:population":133
},
  "geometry": {"coordinates":[73.186694,20.580583],"type":"Point"}
}