{
  "type": "Feature",
  "properties": {
    "gn:admin1_code":"11",
    "gn:admin2_code":"27.0",
    "gn:asciiname":"Shagnal",
    "gn:country_code":"IN",
    "gn:dem":1777,
    "gn:feature_class":"P",
    "gn:feature_code":"PPL",
    "gn:name":"Shagn\u0101l",
    "gn:population":0,
    "gn:timezone":"Asia/Kolkata",
    "iso:country":"IN",
    "wof:name":"Shagnal",
    "wof:placetype":"locality"
},
  "geometry": {"coordinates":[76.98658,31.91265],"type":"Point"}
}