{
  "type": "Feature",
  "properties": {
    "gn:admin1_code":"36",
    "gn:admin2_code":"137.0",
    "gn:asciiname":"Bastapur",
    "gn:country_code":"IN",
    "gn:dem":218,
    "gn:feature_class":"P",
    "gn:feature_code":"PPL",
    "gn:name":"Bast\u0101pur",
    "gn:population":0,
    "gn:timezone":"Asia/Kolkata",
    "iso:country":"IN",
    "ks:ks_alt_nam":"Bast\u0101pur",
    "ks:ks_name":"Bastapur",
    "ks:ks_type":"VILLAGE",
    "ks:ks_uagg_main":0,
    "name:eng_x_preferred":[
        "Bastapur"
    ],
    "name:eng_x_variant":[
        "Bast\u0101pur"
    ],
    "wof:name":"Bastapur",
    "wof:placetype":"neighbourhood"
},
  "geometry": {"coordinates":[78.435697,29.023011],"type":"Point"}
}