{
  "type": "Feature",
  "properties": {
    "iso:country":"IN",
    "ks:ks_alt_nam":"Nars\u012bpura",
    "ks:ks_alt_nam_2":"Narsipura",
    "ks:ks_name":"Narasipura",
    "ks:ks_type":"VILLAGE",
    "name:eng_x_preferred":[
        "Narasipura"
    ],
    "name:eng_x_variant":[
        "Nars\u012bpura",
        "Narsipura"
    ],
    "wof:name":"Narasipura",
    "wof:placetype":"locality"
},
  "geometry": {"coordinates":[76.018912,14.239975],"type":"Point"}
}