{
  "type": "Feature",
  "properties": {
    "iso:country":"IN",
    "ks:ks_name":"Garuoli",
    "ks:ks_pop":1152,
    "ks:ks_type":"HABITATION",
    "name:eng_x_preferred":[
        "Garuoli"
    ],
    "wof:name":"Garuoli",
    "wof:placetype":"locality",
    "wof:population":1152
},
  "geometry": {"coordinates":[81.309545,25.457349],"type":"Point"}
}