{
  "type": "Feature",
  "properties": {
    "iso:country":"IN",
    "ks:ks_name":"Aoratanr",
    "ks:ks_pop":30,
    "ks:ks_type":"VILLAGE",
    "name:eng_x_preferred":[
        "Aoratanr"
    ],
    "wof:name":"Aoratanr",
    "wof:placetype":"locality",
    "wof:population":30
},
  "geometry": {"coordinates":[86.54762100000001,24.050232],"type":"Point"}
}