{
  "type": "Feature",
  "properties": {
    "iso:country":"IN",
    "ks:ks_name":"Kohat Mal",
    "ks:ks_pop":664,
    "ks:ks_type":"VILLAGE",
    "name:eng_x_preferred":[
        "Kohat Mal"
    ],
    "wof:name":"Kohat Mal",
    "wof:placetype":"locality",
    "wof:population":664
},
  "geometry": {"coordinates":[78.61653699999999,21.958283],"type":"Point"}
}