{
  "type": "Feature",
  "properties": {
    "iso:country":"IN",
    "ks:ks_name":"Gombepal",
    "ks:ks_pop":18,
    "ks:ks_type":"HABITATION",
    "name:eng_x_preferred":[
        "Gombepal"
    ],
    "wof:name":"Gombepal",
    "wof:placetype":"locality",
    "wof:population":18
},
  "geometry": {"coordinates":[74.690488,14.954765],"type":"Point"}
}