{
  "type": "Feature",
  "properties": {
    "gn:admin1_code":"38.0",
    "gn:admin2_code":"351.0",
    "gn:asciiname":"Bansbhita",
    "gn:country_code":"IN",
    "gn:dem":88,
    "gn:feature_class":"P",
    "gn:feature_code":"PPL",
    "gn:name":"B\u0101nsbhita",
    "gn:population":0,
    "gn:timezone":"Asia/Kolkata",
    "iso:country":"IN",
    "ks:ks_alt_nam":"B\u0101nsbhita",
    "ks:ks_name":"Bansbhita",
    "ks:ks_pop":223,
    "ks:ks_type":"VILLAGE",
    "name:eng_x_preferred":[
        "Bansbhita"
    ],
    "name:eng_x_variant":[
        "B\u0101nsbhita"
    ],
    "wof:name":"Bansbhita",
    "wof:placetype":"locality",
    "wof:population":223
},
  "geometry": {"coordinates":[87.491111,25.057764],"type":"Point"}
}