{
  "type": "Feature",
  "properties": {
    "iso:country":"IN",
    "ks:ks_alt_nam":"Kurilakadavu palam",
    "ks:ks_name":"Kurilakadavu Palam",
    "ks:ks_pop":255,
    "ks:ks_type":"HABITATION",
    "name:eng_x_preferred":[
        "Kurilakadavu Palam"
    ],
    "wof:name":"Kurilakadavu Palam",
    "wof:placetype":"locality",
    "wof:population":255
},
  "geometry": {"coordinates":[76.146697,10.377698],"type":"Point"}
}