{
  "type": "Feature",
  "properties": {
    "gn:admin1_code":"36.0",
    "gn:admin2_code":"184.0",
    "gn:asciiname":"Kosi",
    "gn:country_code":"IN",
    "gn:dem":99,
    "gn:feature_class":"P",
    "gn:feature_code":"PPL",
    "gn:name":"Kosi",
    "gn:population":0,
    "gn:timezone":"Asia/Kolkata",
    "iso:country":"IN",
    "ks:ks_name":"Kosi",
    "ks:ks_type":"VILLAGE",
    "ks:ks_uagg_main":0,
    "name:bul_x_preferred":[
        "\u041a\u043e\u0441\u0438"
    ],
    "name:ceb_x_preferred":[
        "Kosi"
    ],
    "name:deu_x_preferred":[
        "Kosi"
    ],
    "name:eng_x_preferred":[
        "Kosi"
    ],
    "name:nld_x_preferred":[
        "Kosi"
    ],
    "name:rus_x_preferred":[
        "\u041a\u043e\u0441\u0438"
    ],
    "name:slv_x_preferred":[
        "Kosi"
    ],
    "name:swe_x_preferred":[
        "Kosi"
    ],
    "name:ukr_x_preferred":[
        "\u041a\u043e\u0441\u0438"
    ],
    "wof:name":"Kosi",
    "wof:placetype":"neighbourhood"
},
  "geometry": {"coordinates":[82.65016300000001,27.196031],"type":"Point"}
}