{
  "type": "Feature",
  "properties": {
    "gn:admin1_code":"19.0",
    "gn:admin2_code":"582.0",
    "gn:asciiname":"Devaganhalli",
    "gn:country_code":"IN",
    "gn:dem":890,
    "gn:feature_class":"P",
    "gn:feature_code":"PPL",
    "gn:name":"Devag\u0101nhalli",
    "gn:population":0,
    "gn:timezone":"Asia/Kolkata",
    "iso:country":"IN",
    "wof:name":"Devaganhalli",
    "wof:placetype":"locality"
},
  "geometry": {"coordinates":[77.86153,13.27026],"type":"Point"}
}