{
  "type": "Feature",
  "properties": {
    "gn:admin1_code":"36",
    "gn:admin2_code":"187.0",
    "gn:asciiname":"Bishunathpur",
    "gn:country_code":"IN",
    "gn:dem":98,
    "gn:feature_class":"P",
    "gn:feature_code":"PPL",
    "gn:name":"Bishun\u0101thpur",
    "gn:population":0,
    "gn:timezone":"Asia/Kolkata",
    "iso:country":"IN",
    "name:und_x_variant":[
        "Bishun\u0101thpur",
        "Parwani\u0101"
    ],
    "wof:name":"Bishunathpur",
    "wof:placetype":"locality"
},
  "geometry": {"coordinates":[83.64513000000002,27.15041],"type":"Point"}
}