{
  "type": "Feature",
  "properties": {
    "iso:country":"IN",
    "ks:ks_name":"Wadakwasti",
    "ks:ks_pop":77,
    "ks:ks_type":"HABITATION",
    "name:eng_x_preferred":[
        "Wadakwasti"
    ],
    "wof:name":"Wadakwasti",
    "wof:placetype":"locality",
    "wof:population":77
},
  "geometry": {"coordinates":[74.403757,19.589067],"type":"Point"}
}