{
  "type": "Feature",
  "properties": {
    "iso:country":"IN",
    "ks:ks_name":"Subbarajupeta",
    "ks:ks_pop":536,
    "ks:ks_type":"HABITATION",
    "name:eng_x_preferred":[
        "Subbarajupeta"
    ],
    "wof:name":"Subbarajupeta",
    "wof:placetype":"locality",
    "wof:population":536
},
  "geometry": {"coordinates":[81.936481,16.687709],"type":"Point"}
}