{
  "type": "Feature",
  "properties": {
    "iso:country":"IN",
    "ks:ks_name":"Ainyachiwadi",
    "ks:ks_pop":210,
    "ks:ks_type":"HABITATION",
    "name:eng_x_preferred":[
        "Ainyachiwadi"
    ],
    "wof:name":"Ainyachiwadi",
    "wof:placetype":"locality",
    "wof:population":210
},
  "geometry": {"coordinates":[73.485119,19.125879],"type":"Point"}
}