{
  "type": "Feature",
  "properties": {
    "iso:country":"IN",
    "ks:ks_name":"Nayarangamatia",
    "ks:ks_pop":1506,
    "ks:ks_type":"VILLAGE",
    "name:eng_x_preferred":[
        "Nayarangamatia"
    ],
    "wof:name":"Nayarangamatia",
    "wof:placetype":"locality",
    "wof:population":1506
},
  "geometry": {"coordinates":[86.515061,21.634357],"type":"Point"}
}