{
  "type": "Feature",
  "properties": {
    "gn:admin1_code":"36.0",
    "gn:admin2_code":"162.0",
    "gn:asciiname":"Khera",
    "gn:country_code":"IN",
    "gn:dem":147,
    "gn:feature_class":"P",
    "gn:feature_code":"PPL",
    "gn:name":"Khera",
    "gn:population":0,
    "gn:timezone":"Asia/Kolkata",
    "iso:country":"IN",
    "name:ara_x_preferred":[
        "\u062e\u064a\u0631\u0627"
    ],
    "name:ben_bn_x_preferred":[
        "\u0996\u09c7\u09b0\u09be"
    ],
    "name:ben_in_x_preferred":[
        "\u0996\u09c7\u09b0\u09be"
    ],
    "name:guj_x_preferred":[
        "\u0a96\u0ac7\u0ab0\u0abe"
    ],
    "name:hin_x_preferred":[
        "\u0916\u0947\u095c\u093e"
    ],
    "name:kan_x_preferred":[
        "\u0c96\u0cc7\u0cb0\u0cbe"
    ],
    "name:mal_x_preferred":[
        "\u0d16\u0d47\u0d30"
    ],
    "name:mar_x_preferred":[
        "\u0916\u0947\u0930\u093e"
    ],
    "name:pan_x_preferred":[
        "\u0a16\u0a47\u0a5c\u0a3e"
    ],
    "name:tam_x_preferred":[
        "\u0b95\u0bc7\u0bb0\u0bbe"
    ],
    "name:tel_x_preferred":[
        "\u0c16\u0c47\u0c30\u0c3e"
    ],
    "name:urd_x_preferred":[
        "\u06a9\u06be\u06cc\u0691\u0627"
    ],
    "wof:name":"Khera",
    "wof:placetype":"locality"
},
  "geometry": {"coordinates":[79.56251,26.75479],"type":"Point"}
}