{
  "type": "Feature",
  "properties": {
    "gn:admin1_code":"36.0",
    "gn:admin2_code":"162.0",
    "gn:asciiname":"Khera",
    "gn:country_code":"IN",
    "gn:dem":147,
    "gn:feature_class":"P",
    "gn:feature_code":"PPL",
    "gn:name":"Khera",
    "gn:population":0,
    "gn:timezone":"Asia/Kolkata",
    "iso:country":"IN",
    "wof:name":"Khera",
    "wof:placetype":"locality"
},
  "geometry": {"coordinates":[79.56251,26.75479],"type":"Point"}
}