{
  "type": "Feature",
  "properties": {
    "iso:country":"IN",
    "ks:ks_name":"Nochipalayam",
    "ks:ks_pop":258,
    "ks:ks_type":"HABITATION",
    "ks:ks_uagg_main":0,
    "name:eng_x_preferred":[
        "Nochipalayam"
    ],
    "wof:name":"Nochipalayam",
    "wof:placetype":"neighbourhood",
    "wof:population":258
},
  "geometry": {"coordinates":[78.01960099999999,10.99969],"type":"Point"}
}