{
  "type": "Feature",
  "properties": {
    "iso:country":"IN",
    "ks:ks_name":"Sudorshonpur Pt III",
    "ks:ks_pop":3458,
    "ks:ks_type":"VILLAGE",
    "name:eng_x_preferred":[
        "Sudorshonpur Pt III"
    ],
    "wof:name":"Sudorshonpur Pt III",
    "wof:placetype":"locality",
    "wof:population":3458
},
  "geometry": {"coordinates":[92.63497099999999,24.613869],"type":"Point"}
}