{
  "type": "Feature",
  "properties": {
    "iso:country":"IN",
    "ks:ks_name":"Dohad",
    "ks:ks_pop":0,
    "ks:ks_type":"VILLAGE",
    "name:eng_x_preferred":[
        "Dohad"
    ],
    "wof:name":"Dohad",
    "wof:placetype":"locality",
    "wof:population":0
},
  "geometry": {"coordinates":[75.937691,21.803874],"type":"Point"}
}