{
  "type": "Feature",
  "properties": {
    "iso:country":"IN",
    "ks:ks_name":"Menakapur",
    "ks:ks_pop":2837,
    "ks:ks_type":"VILLAGE",
    "name:eng_x_preferred":[
        "Menakapur"
    ],
    "wof:name":"Menakapur",
    "wof:placetype":"locality",
    "wof:population":2837
},
  "geometry": {"coordinates":[87.353949,21.938234],"type":"Point"}
}