{
  "type": "Feature",
  "properties": {
    "iso:country":"IN",
    "ks:ks_name":"Yeliyar",
    "ks:ks_pop":159,
    "ks:ks_type":"HABITATION",
    "name:eng_x_preferred":[
        "Yeliyar"
    ],
    "wof:name":"Yeliyar",
    "wof:placetype":"locality",
    "wof:population":159
},
  "geometry": {"coordinates":[74.90472800000001,12.839874],"type":"Point"}
}