{
  "type": "Feature",
  "properties": {
    "gn:country":"IN",
    "gn:fcode":"HSE",
    "gn:pop":4,
    "iso:country":"IN",
    "qs:name":"lakshmi nivasa",
    "qs:photos_9r":0,
    "qs:photos_sr":0,
    "qs:pop_sr":"1",
    "wd:wordcount":114,
    "wof:name":"lakshmi nivasa",
    "wof:placetype":"locality",
    "wof:population":4
},
  "geometry": {"coordinates":[77.49934,12.95492],"type":"Point"}
}