{
  "type": "Feature",
  "properties": {
    "iso:country":"IN",
    "ks:ks_alt_nam":"M\u0101l\u012b",
    "ks:ks_name":"Mali",
    "ks:ks_pop":206,
    "ks:ks_type":"VILLAGE",
    "name:eng_x_preferred":[
        "Mali"
    ],
    "name:eng_x_variant":[
        "M\u0101l\u012b"
    ],
    "wof:name":"Mali",
    "wof:placetype":"locality",
    "wof:population":206
},
  "geometry": {"coordinates":[84.79268500000001,24.094776],"type":"Point"}
}