{
  "type": "Feature",
  "properties": {
    "iso:country":"IN",
    "ks:ks_name":"Bandhuguda",
    "ks:ks_pop":0,
    "ks:ks_type":"VILLAGE",
    "name:eng_x_preferred":[
        "Bandhuguda"
    ],
    "wof:name":"Bandhuguda",
    "wof:placetype":"locality",
    "wof:population":0
},
  "geometry": {"coordinates":[83.59801400000001,19.730548],"type":"Point"}
}