{
  "type": "Feature",
  "properties": {
    "gn:admin1_code":"12",
    "gn:admin2_code":"20.0",
    "gn:asciiname":"Chodhaman",
    "gn:country_code":"IN",
    "gn:dem":1851,
    "gn:feature_class":"P",
    "gn:feature_code":"PPL",
    "gn:name":"Chodhaman",
    "gn:population":0,
    "gn:timezone":"Asia/Kolkata",
    "iso:country":"IN",
    "wof:name":"Chodhaman",
    "wof:placetype":"locality"
},
  "geometry": {"coordinates":[74.79368000000002,33.28496],"type":"Point"}
}