{
  "type": "Feature",
  "properties": {
    "iso:country":"IN",
    "ks:ks_name":"Silamohakhati",
    "ks:ks_pop":803,
    "ks:ks_type":"HABITATION",
    "ks:ks_uagg_main":0,
    "name:eng_x_preferred":[
        "Silamohakhati"
    ],
    "wof:name":"Silamohakhati",
    "wof:placetype":"neighbourhood",
    "wof:population":803
},
  "geometry": {"coordinates":[91.674029,26.19951],"type":"Point"}
}