{
  "type": "Feature",
  "properties": {
    "gn:admin1_code":"09",
    "gn:admin2_code":"490.0",
    "gn:asciiname":"Sisodra",
    "gn:country_code":"IN",
    "gn:dem":16,
    "gn:feature_class":"P",
    "gn:feature_code":"PPL",
    "gn:name":"Sisodra",
    "gn:population":0,
    "gn:timezone":"Asia/Kolkata",
    "iso:country":"IN",
    "ks:ks_name":"Sisodra",
    "ks:ks_pop":7645,
    "ks:ks_type":"VILLAGE",
    "ks:ks_uagg_main":0,
    "name:eng_x_preferred":[
        "Sisodra"
    ],
    "wof:name":"Sisodra",
    "wof:placetype":"locality",
    "wof:population":7645
},
  "geometry": {"coordinates":[72.97938000000001,20.935727],"type":"Point"}
}