{
  "type": "Feature",
  "properties": {
    "iso:country":"IN",
    "ks:ks_name":"Faredua Upreti",
    "ks:ks_pop":2013,
    "ks:ks_type":"VILLAGE",
    "ks:ks_uagg_main":0,
    "name:eng_x_preferred":[
        "Faredua Upreti"
    ],
    "wof:name":"Faredua Upreti",
    "wof:placetype":"neighbourhood",
    "wof:population":2013
},
  "geometry": {"coordinates":[77.011133,25.149609],"type":"Point"}
}