{
  "type": "Feature",
  "properties": {
    "gn:admin1_code":"36",
    "gn:admin2_code":"192.0",
    "gn:asciiname":"Domanpur",
    "gn:country_code":"IN",
    "gn:dem":74,
    "gn:feature_class":"P",
    "gn:feature_code":"PPL",
    "gn:name":"Domanpur",
    "gn:population":0,
    "gn:timezone":"Asia/Kolkata",
    "iso:country":"IN",
    "wof:name":"Domanpur",
    "wof:placetype":"locality"
},
  "geometry": {"coordinates":[83.54489000000002,25.96452],"type":"Point"}
}