{
  "type": "Feature",
  "properties": {
    "iso:country":"IN",
    "ks:ks_alt_nam":"nadepada",
    "ks:ks_name":"Nadepada",
    "ks:ks_pop":66,
    "ks:ks_type":"HABITATION",
    "name:eng_x_preferred":[
        "Nadepada"
    ],
    "wof:name":"Nadepada",
    "wof:placetype":"locality",
    "wof:population":66
},
  "geometry": {"coordinates":[73.139111,19.71495],"type":"Point"}
}