{
  "type": "Feature",
  "properties": {
    "iso:country":"IN",
    "ks:ks_name":"Salempur",
    "ks:ks_type":"VILLAGE",
    "name:eng_x_preferred":[
        "Salempur"
    ],
    "wof:name":"Salempur",
    "wof:placetype":"locality"
},
  "geometry": {"coordinates":[82.257251,26.743929],"type":"Point"}
}