{
  "type": "Feature",
  "properties": {
    "gn:admin1_code":"16",
    "gn:admin2_code":"523.0",
    "gn:asciiname":"Motegaon",
    "gn:country_code":"IN",
    "gn:dem":617,
    "gn:feature_class":"P",
    "gn:feature_code":"PPL",
    "gn:name":"Motegaon",
    "gn:population":0,
    "gn:timezone":"Asia/Kolkata",
    "iso:country":"IN",
    "wof:name":"Motegaon",
    "wof:placetype":"locality"
},
  "geometry": {"coordinates":[76.41954,18.58647],"type":"Point"}
}