{
  "type": "Feature",
  "properties": {
    "iso:country":"IN",
    "ks:ks_name":"Hadagarh",
    "ks:ks_pop":0,
    "ks:ks_type":"VILLAGE",
    "name:eng_x_preferred":[
        "Hadagarh"
    ],
    "wof:name":"Hadagarh",
    "wof:placetype":"locality",
    "wof:population":0
},
  "geometry": {"coordinates":[85.577108,20.752396],"type":"Point"}
}