{
  "type": "Feature",
  "properties": {
    "iso:country":"IN",
    "ks:ks_name":"Maliguda",
    "ks:ks_pop":198,
    "ks:ks_type":"HABITATION",
    "name:eng_x_preferred":[
        "Maliguda"
    ],
    "wof:name":"Maliguda",
    "wof:placetype":"locality",
    "wof:population":198
},
  "geometry": {"coordinates":[82.613175,18.708341],"type":"Point"}
}