{
  "type": "Feature",
  "properties": {
    "iso:country":"IN",
    "ks:ks_name":"Chipitiguda",
    "ks:ks_pop":174,
    "ks:ks_type":"HABITATION",
    "name:eng_x_preferred":[
        "Chipitiguda"
    ],
    "wof:name":"Chipitiguda",
    "wof:placetype":"locality",
    "wof:population":174
},
  "geometry": {"coordinates":[82.725419,19.160074],"type":"Point"}
}