{
  "type": "Feature",
  "properties": {
    "gn:admin1_code":"36",
    "gn:admin2_code":"178.0",
    "gn:asciiname":"Chak Kulahal Patti",
    "gn:country_code":"IN",
    "gn:dem":90,
    "gn:feature_class":"P",
    "gn:feature_code":"PPL",
    "gn:name":"Chak Kul\u0101hal Patti",
    "gn:population":0,
    "gn:timezone":"Asia/Kolkata",
    "iso:country":"IN",
    "wof:name":"Chak Kulahal Patti",
    "wof:placetype":"neighbourhood"
},
  "geometry": {"coordinates":[82.86814,26.16885],"type":"Point"}
}