{
  "type": "Feature",
  "properties": {
    "iso:country":"IN",
    "ks:ks_name":"Madhaliwadi",
    "ks:ks_pop":30,
    "ks:ks_type":"HABITATION",
    "name:eng_x_preferred":[
        "Madhaliwadi"
    ],
    "wof:name":"Madhaliwadi",
    "wof:placetype":"locality",
    "wof:population":30
},
  "geometry": {"coordinates":[73.698611,17.037222],"type":"Point"}
}