{
  "type": "Feature",
  "properties": {
    "iso:country":"IN",
    "ks:ks_alt_nam":"Salaiyur ad  colony",
    "ks:ks_name":"Salaiyur Ad Colony",
    "ks:ks_pop":175,
    "ks:ks_type":"HABITATION",
    "ks:ks_uagg_main":0,
    "name:eng_x_preferred":[
        "Salaiyur Ad Colony"
    ],
    "name:eng_x_variant":[
        "Salaiyur ad  colony"
    ],
    "wof:name":"Salaiyur Ad Colony",
    "wof:placetype":"neighbourhood",
    "wof:population":175
},
  "geometry": {"coordinates":[78.077977,10.588973],"type":"Point"}
}