{
  "type": "Feature",
  "properties": {
    "iso:country":"IN",
    "ks:ks_alt_nam":"TETRAHI",
    "ks:ks_name":"Tetrahi",
    "ks:ks_pop":270,
    "ks:ks_type":"HABITATION",
    "name:eng_x_preferred":[
        "Tetrahi"
    ],
    "wof:name":"Tetrahi",
    "wof:placetype":"locality",
    "wof:population":270
},
  "geometry": {"coordinates":[86.546605,26.240325],"type":"Point"}
}