{
  "type": "Feature",
  "properties": {
    "iso:country":"IN",
    "ks:ks_name":"Kunwarpur",
    "ks:ks_pop":150,
    "ks:ks_type":"HABITATION",
    "name:eng_x_preferred":[
        "Kunwarpur"
    ],
    "wof:name":"Kunwarpur",
    "wof:placetype":"locality",
    "wof:population":150
},
  "geometry": {"coordinates":[80.350016,25.401189],"type":"Point"}
}