{
  "type": "Feature",
  "properties": {
    "iso:country":"IN",
    "ks:ks_name":"Raghudaspur",
    "ks:ks_pop":299,
    "ks:ks_type":"VILLAGE",
    "ks:ks_uagg_main":0,
    "name:eng_x_preferred":[
        "Raghudaspur"
    ],
    "wof:name":"Raghudaspur",
    "wof:placetype":"neighbourhood",
    "wof:population":299
},
  "geometry": {"coordinates":[86.07444099999999,20.601751],"type":"Point"}
}