{
  "type": "Feature",
  "properties": {
    "iso:country":"IN",
    "ks:ks_name":"Tendupara",
    "ks:ks_pop":460,
    "ks:ks_type":"HABITATION",
    "name:eng_x_preferred":[
        "Tendupara"
    ],
    "wof:name":"Tendupara",
    "wof:placetype":"locality",
    "wof:population":460
},
  "geometry": {"coordinates":[82.550443,22.894419],"type":"Point"}
}