{
  "type": "Feature",
  "properties": {
    "gn:admin1_code":"36",
    "gn:admin2_code":"196.0",
    "gn:asciiname":"Sarai",
    "gn:country_code":"IN",
    "gn:dem":80,
    "gn:feature_class":"P",
    "gn:feature_code":"PPL",
    "gn:name":"Sar\u0101i",
    "gn:population":0,
    "gn:timezone":"Asia/Kolkata",
    "iso:country":"IN",
    "wof:name":"Sarai",
    "wof:placetype":"locality"
},
  "geometry": {"coordinates":[83.25097,25.42889],"type":"Point"}
}