{
  "type": "Feature",
  "properties": {
    "gn:admin1_code":"16.0",
    "gn:admin2_code":"527",
    "gn:asciiname":"Dhamni",
    "gn:country_code":"IN",
    "gn:dem":687,
    "gn:feature_class":"P",
    "gn:feature_code":"PPL",
    "gn:name":"Dhamni",
    "gn:population":0,
    "gn:timezone":"Asia/Kolkata",
    "iso:country":"IN",
    "wof:name":"Dhamni",
    "wof:placetype":"locality"
},
  "geometry": {"coordinates":[74.67423000000002,17.62375],"type":"Point"}
}