{
  "type": "Feature",
  "properties": {
    "gn:admin1_code":"11.0",
    "gn:admin2_code":"32.0",
    "gn:asciiname":"Kandan",
    "gn:country_code":"IN",
    "gn:dem":1640,
    "gn:feature_class":"P",
    "gn:feature_code":"PPL",
    "gn:name":"K\u0101ndan",
    "gn:population":0,
    "gn:timezone":"Asia/Kolkata",
    "iso:country":"IN",
    "wof:name":"Kandan",
    "wof:placetype":"locality"
},
  "geometry": {"coordinates":[77.57356,30.74426],"type":"Point"}
}