{
  "type": "Feature",
  "properties": {
    "iso:country":"IN",
    "ks:ks_name":"Lakhopada",
    "ks:ks_pop":134,
    "ks:ks_type":"HABITATION",
    "name:eng_x_preferred":[
        "Lakhopada"
    ],
    "wof:name":"Lakhopada",
    "wof:placetype":"locality",
    "wof:population":134
},
  "geometry": {"coordinates":[84.29190699999999,21.824912],"type":"Point"}
}