{
  "type": "Feature",
  "properties": {
    "iso:country":"IN",
    "ks:ks_name":"Ghosh Khamar",
    "ks:ks_pop":361,
    "ks:ks_type":"HABITATION",
    "ks:ks_uagg_main":0,
    "name:eng_x_preferred":[
        "Ghosh Khamar"
    ],
    "wof:name":"Ghosh Khamar",
    "wof:placetype":"neighbourhood",
    "wof:population":361
},
  "geometry": {"coordinates":[91.333468,23.201506],"type":"Point"}
}