{
  "type": "Feature",
  "properties": {
    "iso:country":"IN",
    "ks:ks_name":"Mirjapur Tilak",
    "ks:ks_pop":1200,
    "ks:ks_type":"VILLAGE",
    "ks:ks_uagg_main":0,
    "name:eng_x_preferred":[
        "Mirjapur Tilak"
    ],
    "wof:name":"Mirjapur Tilak",
    "wof:placetype":"neighbourhood",
    "wof:population":1200
},
  "geometry": {"coordinates":[81.657269,27.901546],"type":"Point"}
}