{
  "type": "Feature",
  "properties": {
    "gn:admin1_code":"10",
    "gn:admin2_code":"73.0",
    "gn:asciiname":"Shergarh",
    "gn:country_code":"IN",
    "gn:dem":237,
    "gn:feature_class":"P",
    "gn:feature_code":"PPL",
    "gn:name":"Shergarh",
    "gn:population":0,
    "gn:timezone":"Asia/Kolkata",
    "iso:country":"IN",
    "ks:ks_name":"Sher Garh",
    "ks:ks_pop":1133,
    "ks:ks_type":"VILLAGE",
    "ks:ks_uagg_main":0,
    "name:ceb_x_preferred":[
        "Shergarh"
    ],
    "name:eng_x_preferred":[
        "Sher Garh"
    ],
    "name:pol_x_preferred":[
        "Shergarh"
    ],
    "name:swe_x_preferred":[
        "Shergarh"
    ],
    "wof:name":"Sher Garh",
    "wof:placetype":"locality",
    "wof:population":1133
},
  "geometry": {"coordinates":[76.421384,29.776461],"type":"Point"}
}