{
  "type": "Feature",
  "properties": {
    "gn:admin1_code":"37.0",
    "gn:admin2_code":"416.0",
    "gn:asciiname":"Pendulnar",
    "gn:country_code":"IN",
    "gn:dem":283,
    "gn:feature_class":"P",
    "gn:feature_code":"PPL",
    "gn:name":"Penduln\u0101r",
    "gn:population":0,
    "gn:timezone":"Asia/Kolkata",
    "iso:country":"IN",
    "ks:ks_alt_nam":"Penduln\u0101r",
    "ks:ks_name":"Pendulnar",
    "ks:ks_type":"VILLAGE",
    "name:eng_x_preferred":[
        "Pendulnar"
    ],
    "name:eng_x_variant":[
        "Penduln\u0101r"
    ],
    "wof:name":"Pendulnar",
    "wof:placetype":"locality"
},
  "geometry": {"coordinates":[81.636425,18.594297],"type":"Point"}
}