{
  "type": "Feature",
  "properties": {
    "iso:country":"IN",
    "ks:ks_name":"Devalapuram",
    "ks:ks_pop":1290,
    "ks:ks_type":"VILLAGE",
    "ks:ks_uagg_main":0,
    "name:eng_x_preferred":[
        "Devalapuram"
    ],
    "wof:name":"Devalapuram",
    "wof:placetype":"neighbourhood",
    "wof:population":1290
},
  "geometry": {"coordinates":[78.707301,12.787451],"type":"Point"}
}