{
  "type": "Feature",
  "properties": {
    "iso:country":"IN",
    "ks:ks_name":"Bara",
    "ks:ks_pop":124,
    "ks:ks_type":"VILLAGE",
    "ks:ks_uagg_main":0,
    "name:eng_x_preferred":[
        "Bara"
    ],
    "wof:name":"Bara",
    "wof:placetype":"neighbourhood",
    "wof:population":124
},
  "geometry": {"coordinates":[80.5622,24.621386],"type":"Point"}
}