{
  "type": "Feature",
  "properties": {
    "iso:country":"IN",
    "ks:ks_name":"Rajendranagar",
    "ks:ks_pop":318,
    "ks:ks_type":"HABITATION",
    "name:eng_x_preferred":[
        "Rajendranagar"
    ],
    "wof:name":"Rajendranagar",
    "wof:placetype":"locality",
    "wof:population":318
},
  "geometry": {"coordinates":[76.694273,11.305323],"type":"Point"}
}