{
  "type": "Feature",
  "properties": {
    "iso:country":"IN",
    "ks:ks_alt_nam":"KANHOBA WASTI",
    "ks:ks_name":"Kanhoba Wasti",
    "ks:ks_pop":127,
    "ks:ks_type":"HABITATION",
    "name:eng_x_preferred":[
        "Kanhoba Wasti"
    ],
    "wof:name":"Kanhoba Wasti",
    "wof:placetype":"locality",
    "wof:population":127
},
  "geometry": {"coordinates":[75.073104,18.632133],"type":"Point"}
}