{
  "type": "Feature",
  "properties": {
    "iso:country":"IN",
    "ks:ks_alt_nam":"Mahu\u0101toli",
    "ks:ks_alt_nam_2":"Mahuatoli",
    "ks:ks_name":"Mahua",
    "ks:ks_pop":783,
    "ks:ks_type":"VILLAGE",
    "name:eng_x_preferred":[
        "Mahua"
    ],
    "name:eng_x_variant":[
        "Mahu\u0101toli",
        "Mahuatoli"
    ],
    "wof:name":"Mahua",
    "wof:placetype":"locality",
    "wof:population":783
},
  "geometry": {"coordinates":[84.24389499999999,22.503083],"type":"Point"}
}