{
  "type": "Feature",
  "properties": {
    "iso:country":"IN",
    "ks:ks_name":"Sangatimallayyagari Palle",
    "ks:ks_pop":15,
    "ks:ks_type":"HABITATION",
    "name:eng_x_preferred":[
        "Sangatimallayyagari Palle"
    ],
    "wof:name":"Sangatimallayyagari Palle",
    "wof:placetype":"locality",
    "wof:population":15
},
  "geometry": {"coordinates":[78.842157,13.911436],"type":"Point"}
}