{
  "type": "Feature",
  "properties": {
    "gn:admin1_code":"37",
    "gn:admin2_code":"406.0",
    "gn:asciiname":"Khargahna",
    "gn:country_code":"IN",
    "gn:dem":298,
    "gn:feature_class":"P",
    "gn:feature_code":"PPL",
    "gn:name":"Khargahn\u0101",
    "gn:population":0,
    "gn:timezone":"Asia/Kolkata",
    "iso:country":"IN",
    "wof:name":"Khargahna",
    "wof:placetype":"locality"
},
  "geometry": {"coordinates":[82.07303,22.2396],"type":"Point"}
}