{
  "type": "Feature",
  "properties": {
    "iso:country":"IN",
    "ks:ks_name":"Gelapukhuri T E No 261 Nlr",
    "ks:ks_pop":357,
    "ks:ks_type":"HABITATION",
    "name:eng_x_preferred":[
        "Gelapukhuri T E No 261 Nlr"
    ],
    "wof:name":"Gelapukhuri T E No 261 Nlr",
    "wof:placetype":"locality",
    "wof:population":357
},
  "geometry": {"coordinates":[95.346839,27.534002],"type":"Point"}
}