{
  "type": "Feature",
  "properties": {
    "iso:country":"IN",
    "ks:ks_name":"Muslim Tola",
    "ks:ks_pop":59,
    "ks:ks_type":"HABITATION",
    "name:eng_x_preferred":[
        "Muslim Tola"
    ],
    "wof:name":"Muslim Tola",
    "wof:placetype":"locality",
    "wof:population":59
},
  "geometry": {"coordinates":[86.297451,24.409379],"type":"Point"}
}