{
  "type": "Feature",
  "properties": {
    "iso:country":"IN",
    "ks:ks_name":"Chhota Raidi",
    "ks:ks_pop":146,
    "ks:ks_type":"VILLAGE",
    "name:eng_x_preferred":[
        "Chhota Raidi"
    ],
    "wof:name":"Chhota Raidi",
    "wof:placetype":"locality",
    "wof:population":146
},
  "geometry": {"coordinates":[87.10663,24.065351],"type":"Point"}
}