{
  "type": "Feature",
  "properties": {
    "gn:admin1_code":"34.0",
    "gn:admin2_code":"219.0",
    "gn:asciiname":"Naudiha",
    "gn:country_code":"IN",
    "gn:dem":55,
    "gn:feature_class":"P",
    "gn:feature_code":"PPL",
    "gn:name":"Naudiha",
    "gn:population":0,
    "gn:timezone":"Asia/Kolkata",
    "iso:country":"IN",
    "ks:ks_name":"Naudiha",
    "ks:ks_type":"VILLAGE",
    "name:eng_x_preferred":[
        "Naudiha"
    ],
    "wof:name":"Naudiha",
    "wof:placetype":"locality"
},
  "geometry": {"coordinates":[85.093408,25.716344],"type":"Point"}
}