{
  "type": "Feature",
  "properties": {
    "iso:country":"IN",
    "ks:ks_alt_nam":"UPPER TOLA",
    "ks:ks_name":"Upper Tola",
    "ks:ks_pop":150,
    "ks:ks_type":"HABITATION",
    "name:eng_x_preferred":[
        "Upper Tola"
    ],
    "wof:name":"Upper Tola",
    "wof:placetype":"locality",
    "wof:population":150
},
  "geometry": {"coordinates":[86.76159,24.9809],"type":"Point"}
}