{
  "type": "Feature",
  "properties": {
    "iso:country":"IN",
    "ks:ks_alt_nam":"Danda goda",
    "ks:ks_name":"Danda Goda",
    "ks:ks_pop":22,
    "ks:ks_type":"HABITATION",
    "name:eng_x_preferred":[
        "Danda Goda"
    ],
    "wof:name":"Danda Goda",
    "wof:placetype":"locality",
    "wof:population":22
},
  "geometry": {"coordinates":[87.475728,24.999959],"type":"Point"}
}