{
  "type": "Feature",
  "properties": {
    "iso:country":"IN",
    "ks:ks_name":"Sibarampur",
    "ks:ks_pop":178,
    "ks:ks_type":"VILLAGE",
    "name:eng_x_preferred":[
        "Sibarampur"
    ],
    "wof:name":"Sibarampur",
    "wof:placetype":"locality",
    "wof:population":178
},
  "geometry": {"coordinates":[86.78442800000001,22.998323],"type":"Point"}
}