{
  "type": "Feature",
  "properties": {
    "iso:country":"IN",
    "ks:ks_name":"Kalra",
    "ks:ks_pop":48,
    "ks:ks_type":"HABITATION",
    "name:eng_x_preferred":[
        "Kalra"
    ],
    "wof:name":"Kalra",
    "wof:placetype":"locality",
    "wof:population":48
},
  "geometry": {"coordinates":[81.683723,24.704949],"type":"Point"}
}