{
  "type": "Feature",
  "properties": {
    "gn:admin1_code":"40.0",
    "gn:admin2_code":"541.0",
    "gn:asciiname":"Maredubudi",
    "gn:country_code":"IN",
    "gn:dem":109,
    "gn:feature_class":"P",
    "gn:feature_code":"PPL",
    "gn:name":"Maredubudi",
    "gn:population":0,
    "gn:timezone":"Asia/Kolkata",
    "iso:country":"IN",
    "ks:ks_name":"Maredupudi",
    "ks:ks_pop":22,
    "ks:ks_type":"VILLAGE",
    "name:eng_x_preferred":[
        "Maredupudi"
    ],
    "name:eng_x_variant":[
        "Maredubudi"
    ],
    "wof:name":"Maredupudi",
    "wof:placetype":"locality",
    "wof:population":22
},
  "geometry": {"coordinates":[81.39033499999999,17.522433],"type":"Point"}
}