{
  "type": "Feature",
  "properties": {
    "iso:country":"IN",
    "ks:ks_name":"Lower Maneydanra",
    "ks:ks_pop":728,
    "ks:ks_type":"HABITATION",
    "name:eng_x_preferred":[
        "Lower Maneydanra"
    ],
    "wof:name":"Lower Maneydanra",
    "wof:placetype":"locality",
    "wof:population":728
},
  "geometry": {"coordinates":[88.32590500000001,27.080778],"type":"Point"}
}