{
  "type": "Feature",
  "properties": {
    "iso:country":"IN",
    "ks:ks_name":"Gandhinagar",
    "ks:ks_pop":220,
    "ks:ks_type":"HABITATION",
    "ks:ks_uagg_main":0,
    "name:eng_x_preferred":[
        "Gandhinagar"
    ],
    "wof:name":"Gandhinagar",
    "wof:placetype":"neighbourhood",
    "wof:population":220
},
  "geometry": {"coordinates":[78.648425,12.454495],"type":"Point"}
}