{
  "type": "Feature",
  "properties": {
    "iso:country":"IN",
    "ks:ks_name":"Gandhinagar",
    "ks:ks_pop":220,
    "ks:ks_type":"HABITATION",
    "ks:ks_uagg_main":0,
    "name:eng_x_preferred":[
        "Gandhinagar"
    ],
    "name:guj_x_preferred":[
        "\u0a97\u0abe\u0a82\u0aa7\u0ac0\u0aa8\u0a97\u0ab0"
    ],
    "name:hin_x_preferred":[
        "\u0917\u093e\u0902\u0927\u0940\u0928\u0917\u0930"
    ],
    "wof:name":"Gandhinagar",
    "wof:placetype":"neighbourhood",
    "wof:population":220
},
  "geometry": {"coordinates":[78.648425,12.454495],"type":"Point"}
}