{
  "type": "Feature",
  "properties": {
    "iso:country":"IN",
    "ks:ks_name":"Kabgar",
    "ks:ks_pop":126,
    "ks:ks_type":"HABITATION",
    "name:eng_x_preferred":[
        "Kabgar"
    ],
    "wof:name":"Kabgar",
    "wof:placetype":"locality",
    "wof:population":126
},
  "geometry": {"coordinates":[74.720922,14.361373],"type":"Point"}
}