{
  "type": "Feature",
  "properties": {
    "iso:country":"IN",
    "ks:ks_name":"Madi",
    "ks:ks_pop":377,
    "ks:ks_type":"VILLAGE",
    "name:eng_x_preferred":[
        "Madi"
    ],
    "wof:name":"Madi",
    "wof:placetype":"locality",
    "wof:population":377
},
  "geometry": {"coordinates":[80.61543500000001,21.825097],"type":"Point"}
}