{
  "type": "Feature",
  "properties": {
    "iso:country":"IN",
    "ks:ks_name":"Uppingadde",
    "ks:ks_pop":19,
    "ks:ks_type":"HABITATION",
    "name:eng_x_preferred":[
        "Uppingadde"
    ],
    "wof:name":"Uppingadde",
    "wof:placetype":"locality",
    "wof:population":19
},
  "geometry": {"coordinates":[74.659873,14.363455],"type":"Point"}
}