{
  "type": "Feature",
  "properties": {
    "iso:country":"IN",
    "ks:ks_alt_nam":"sakrutham",
    "ks:ks_name":"Sakrutham",
    "ks:ks_pop":347,
    "ks:ks_type":"HABITATION",
    "name:eng_x_preferred":[
        "Sakrutham"
    ],
    "wof:name":"Sakrutham",
    "wof:placetype":"locality",
    "wof:population":347
},
  "geometry": {"coordinates":[76.21678199999999,10.250353],"type":"Point"}
}