{
  "type": "Feature",
  "properties": {
    "iso:country":"IN",
    "ks:ks_name":"Naeralakatte",
    "ks:ks_pop":232,
    "ks:ks_type":"HABITATION",
    "name:eng_x_preferred":[
        "Naeralakatte"
    ],
    "wof:name":"Naeralakatte",
    "wof:placetype":"locality",
    "wof:population":232
},
  "geometry": {"coordinates":[75.141622,12.956678],"type":"Point"}
}