{
  "type": "Feature",
  "properties": {
    "iso:country":"IN",
    "ks:ks_name":"Sennivanam",
    "ks:ks_pop":748,
    "ks:ks_type":"HABITATION",
    "name:eng_x_preferred":[
        "Sennivanam"
    ],
    "wof:name":"Sennivanam",
    "wof:placetype":"locality",
    "wof:population":748
},
  "geometry": {"coordinates":[79.142853,11.186848],"type":"Point"}
}