{
  "type": "Feature",
  "properties": {
    "iso:country":"IN",
    "ks:ks_name":"Dhari",
    "ks:ks_pop":67,
    "ks:ks_type":"VILLAGE",
    "name:eng_x_preferred":[
        "Dhari"
    ],
    "wof:name":"Dhari",
    "wof:placetype":"locality",
    "wof:population":67
},
  "geometry": {"coordinates":[82.41648000000001,24.949202],"type":"Point"}
}