{
  "type": "Feature",
  "properties": {
    "gn:admin1_code":"35.0",
    "gn:admin2_code":"440.0",
    "gn:asciiname":"Devlia",
    "gn:country_code":"IN",
    "gn:dem":385,
    "gn:feature_class":"P",
    "gn:feature_code":"PPL",
    "gn:name":"Devlia",
    "gn:population":0,
    "gn:timezone":"Asia/Kolkata",
    "iso:country":"IN",
    "name:cat_x_preferred":[
        "Dewalia"
    ],
    "wof:name":"Devlia",
    "wof:placetype":"locality"
},
  "geometry": {"coordinates":[75.97532,21.63022],"type":"Point"}
}