{
  "type": "Feature",
  "properties": {
    "iso:country":"IN",
    "ks:ks_alt_nam":"NTR Nagar Colony",
    "ks:ks_name":"Ntr Nagar Colony",
    "ks:ks_pop":145,
    "ks:ks_type":"HABITATION",
    "name:eng_x_preferred":[
        "Ntr Nagar Colony"
    ],
    "wof:name":"Ntr Nagar Colony",
    "wof:placetype":"locality",
    "wof:population":145
},
  "geometry": {"coordinates":[80.79593199999999,17.772253],"type":"Point"}
}