{
  "type": "Feature",
  "properties": {
    "gn:admin1_code":"36.0",
    "gn:admin2_code":"150.0",
    "gn:asciiname":"Gurwa",
    "gn:country_code":"IN",
    "gn:dem":185,
    "gn:feature_class":"P",
    "gn:feature_code":"PPL",
    "gn:name":"G\u016brwa",
    "gn:population":0,
    "gn:timezone":"Asia/Kolkata",
    "iso:country":"IN",
    "ks:ks_alt_nam":"G\u016brwa",
    "ks:ks_name":"Gurwa",
    "ks:ks_type":"VILLAGE",
    "ks:ks_uagg_main":0,
    "name:eng_x_preferred":[
        "Gurwa"
    ],
    "name:eng_x_variant":[
        "G\u016brwa"
    ],
    "wof:name":"Gurwa",
    "wof:placetype":"neighbourhood"
},
  "geometry": {"coordinates":[79.09319000000001,28.48182],"type":"Point"}
}