{
  "type": "Feature",
  "properties": {
    "iso:country":"IN",
    "ks:ks_name":"Bala",
    "ks:ks_pop":360,
    "ks:ks_type":"VILLAGE",
    "name:eng_x_preferred":[
        "Bala"
    ],
    "wof:name":"Bala",
    "wof:placetype":"locality",
    "wof:population":360
},
  "geometry": {"coordinates":[82.336,23.422835],"type":"Point"}
}