{
  "type": "Feature",
  "properties": {
    "iso:country":"IN",
    "ks:ks_name":"Mulla Vasti",
    "ks:ks_pop":166,
    "ks:ks_type":"HABITATION",
    "name:eng_x_preferred":[
        "Mulla Vasti"
    ],
    "wof:name":"Mulla Vasti",
    "wof:placetype":"locality",
    "wof:population":166
},
  "geometry": {"coordinates":[75.48517,16.688743],"type":"Point"}
}