{
  "type": "Feature",
  "properties": {
    "iso:country":"IN",
    "ks:ks_name":"Garikuri Bebejia",
    "ks:ks_pop":361,
    "ks:ks_type":"VILLAGE",
    "name:eng_x_preferred":[
        "Garikuri Bebejia"
    ],
    "wof:name":"Garikuri Bebejia",
    "wof:placetype":"locality",
    "wof:population":361
},
  "geometry": {"coordinates":[92.623419,26.297661],"type":"Point"}
}