{
  "type": "Feature",
  "properties": {
    "iso:country":"IN",
    "ks:ks_name":"Harampur",
    "ks:ks_type":"VILLAGE",
    "name:eng_x_preferred":[
        "Harampur"
    ],
    "wof:name":"Harampur",
    "wof:placetype":"locality"
},
  "geometry": {"coordinates":[77.240301,28.774529],"type":"Point"}
}