{
  "type": "Feature",
  "properties": {
    "iso:country":"IN",
    "ks:ks_name":"Palthady",
    "ks:ks_pop":352,
    "ks:ks_type":"HABITATION",
    "name:eng_x_preferred":[
        "Palthady"
    ],
    "wof:name":"Palthady",
    "wof:placetype":"locality",
    "wof:population":352
},
  "geometry": {"coordinates":[75.27126800000001,12.811836],"type":"Point"}
}