{
  "type": "Feature",
  "properties": {
    "gn:admin1_code":"36",
    "gn:admin2_code":"145.0",
    "gn:asciiname":"Nagri",
    "gn:country_code":"IN",
    "gn:dem":176,
    "gn:feature_class":"P",
    "gn:feature_code":"PPL",
    "gn:name":"Nagri",
    "gn:population":0,
    "gn:timezone":"Asia/Kolkata",
    "iso:country":"IN",
    "name:ind_x_preferred":[
        "Negeri"
    ],
    "name:sun_x_preferred":[
        "Nagri"
    ],
    "wof:name":"Nagri",
    "wof:placetype":"locality"
},
  "geometry": {"coordinates":[77.60194,27.41474],"type":"Point"}
}