{
  "type": "Feature",
  "properties": {
    "iso:country":"IN",
    "ks:ks_name":"Kalluviduthi",
    "ks:ks_pop":250,
    "ks:ks_type":"HABITATION",
    "name:eng_x_preferred":[
        "Kalluviduthi"
    ],
    "wof:name":"Kalluviduthi",
    "wof:placetype":"locality",
    "wof:population":250
},
  "geometry": {"coordinates":[78.93239699999999,10.45541],"type":"Point"}
}