{
  "type": "Feature",
  "properties": {
    "gn:country":"IN",
    "gn:fcode":"PPL",
    "gn:pop":15136,
    "iso:country":"IN",
    "name:ben_x_preferred":[
        "\u0995\u09c1\u09b0\u0993\u09af\u09bc\u09be\u0987"
    ],
    "name:bpy_x_preferred":[
        "\u0995\u09c1\u09b0\u09f1\u09be\u0987"
    ],
    "name:cat_x_preferred":[
        "Kurwai"
    ],
    "name:chi_x_preferred":[
        "\u5e93\u5c14\u74e6\u4f0a"
    ],
    "name:dut_x_preferred":[
        "Kurwai"
    ],
    "name:eng_x_preferred":[
        "Kurwai"
    ],
    "name:fre_x_preferred":[
        "Kurwai"
    ],
    "name:ger_x_preferred":[
        "Kurwai"
    ],
    "name:guj_x_preferred":[
        "\u0a95\u0ac1\u0ab0\u0ab5\u0a87"
    ],
    "name:ita_x_preferred":[
        "Kurwai"
    ],
    "name:jpn_x_preferred":[
        "\u30af\u30fc\u30ef\u30a4"
    ],
    "name:kan_x_preferred":[
        "\u0c95\u0cc1\u0cb0\u0ccd\u0cb5\u0cbe\u0caf\u0cbf"
    ],
    "name:kor_x_preferred":[
        "\ucfe0\ub974\uc640\uc774"
    ],
    "name:may_x_preferred":[
        "Kurwai"
    ],
    "name:mlg_x_preferred":[
        "Kurwai"
    ],
    "name:nan_x_preferred":[
        "Kurwai"
    ],
    "name:new_x_preferred":[
        "\u0915\u0941\u0930\u094d\u0935\u093e\u0908"
    ],
    "name:pol_x_preferred":[
        "Kurwai"
    ],
    "name:por_x_preferred":[
        "Kurwai"
    ],
    "name:rus_x_preferred":[
        "\u041a\u0443\u0440\u0432\u0430\u0438"
    ],
    "name:spa_x_preferred":[
        "Kurwai"
    ],
    "name:swe_x_preferred":[
        "Kurwai"
    ],
    "name:tam_x_preferred":[
        "\u0b95\u0bc2\u0bb0\u0bcd\u0bb5\u0bbe\u0baf\u0bcd"
    ],
    "name:tel_x_preferred":[
        "\u0c15\u0c41\u0c30\u0c4d\u0c35\u0c48"
    ],
    "name:urd_x_preferred":[
        "\u06a9\u0648\u0631\u0648\u06d2"
    ],
    "name:vie_x_preferred":[
        "Kurwai"
    ],
    "qs:name":"Kurwai",
    "qs:name_adm0":"India",
    "qs:name_adm1":"Madhya Pradesh",
    "qs:photos_9r":0,
    "qs:photos_sr":0,
    "qs:placetype":"Town",
    "qs:pop_sr":"6",
    "wd:wordcount":311,
    "wof:name":"Kurwai",
    "wof:placetype":"locality",
    "wof:population":15136
},
  "geometry": {"coordinates":[78.04007,24.11774],"type":"Point"}
}