{
  "type": "Feature",
  "properties": {
    "iso:country":"IN",
    "ks:ks_name":"Gaothanwadi",
    "ks:ks_pop":813,
    "ks:ks_type":"HABITATION",
    "ks:ks_uagg_main":0,
    "name:eng_x_preferred":[
        "Gaothanwadi"
    ],
    "wof:name":"Gaothanwadi",
    "wof:placetype":"neighbourhood",
    "wof:population":813
},
  "geometry": {"coordinates":[73.495214,17.584542],"type":"Point"}
}