{
  "type": "Feature",
  "properties": {
    "gn:admin1_code":"39.0",
    "gn:admin2_code":"60.0",
    "gn:asciiname":"Sammi ka That",
    "gn:country_code":"IN",
    "gn:dem":1827,
    "gn:feature_class":"P",
    "gn:feature_code":"PPL",
    "gn:name":"Sammi ka Th\u0101t",
    "gn:population":0,
    "gn:timezone":"Asia/Kolkata",
    "iso:country":"IN",
    "wof:name":"Sammi ka That",
    "wof:placetype":"locality"
},
  "geometry": {"coordinates":[77.82562,30.70226],"type":"Point"}
}