{
  "type": "Feature",
  "properties": {
    "iso:country":"IN",
    "ks:ks_name":"Togyana",
    "ks:ks_pop":32,
    "ks:ks_type":"VILLAGE",
    "name:eng_x_preferred":[
        "Togyana"
    ],
    "wof:name":"Togyana",
    "wof:placetype":"locality",
    "wof:population":32
},
  "geometry": {"coordinates":[79.006018,29.653585],"type":"Point"}
}