{
  "type": "Feature",
  "properties": {
    "iso:country":"IN",
    "ks:ks_name":"Madhopur Basu Urf Alipur",
    "ks:ks_pop":1364,
    "ks:ks_type":"VILLAGE",
    "name:eng_x_preferred":[
        "Madhopur Basu Urf Alipur"
    ],
    "wof:name":"Madhopur Basu Urf Alipur",
    "wof:placetype":"locality",
    "wof:population":1364
},
  "geometry": {"coordinates":[85.363446,25.733757],"type":"Point"}
}