{
  "type": "Feature",
  "properties": {
    "gn:admin1_code":"19.0",
    "gn:admin2_code":"584.0",
    "gn:asciiname":"Bhimanhalli",
    "gn:country_code":"IN",
    "gn:dem":749,
    "gn:feature_class":"P",
    "gn:feature_code":"PPL",
    "gn:name":"Bhimanhalli",
    "gn:population":0,
    "gn:timezone":"Asia/Kolkata",
    "iso:country":"IN",
    "wof:name":"Bhimanhalli",
    "wof:placetype":"locality"
},
  "geometry": {"coordinates":[77.40895999999999,12.81499],"type":"Point"}
}