{
  "type": "Feature",
  "properties": {
    "iso:country":"IN",
    "ks:ks_name":"Bashghari Namsibusty",
    "ks:ks_pop":432,
    "ks:ks_type":"HABITATION",
    "name:eng_x_preferred":[
        "Bashghari Namsibusty"
    ],
    "wof:name":"Bashghari Namsibusty",
    "wof:placetype":"locality",
    "wof:population":432
},
  "geometry": {"coordinates":[88.25803500000001,26.903276],"type":"Point"}
}