{
  "type": "Feature",
  "properties": {
    "gn:admin1_code":"13.0",
    "gn:admin2_code":"598.0",
    "gn:asciiname":"Pattur",
    "gn:country_code":"IN",
    "gn:dem":29,
    "gn:feature_class":"P",
    "gn:feature_code":"PPL",
    "gn:name":"Patt\u016br",
    "gn:population":0,
    "gn:timezone":"Asia/Kolkata",
    "iso:country":"IN",
    "wof:name":"Pattur",
    "wof:placetype":"locality"
},
  "geometry": {"coordinates":[76.63557,9.21507],"type":"Point"}
}