{
  "type": "Feature",
  "properties": {
    "iso:country":"IN",
    "ks:ks_name":"Aadiwasiwadi",
    "ks:ks_pop":30,
    "ks:ks_type":"HABITATION",
    "name:eng_x_preferred":[
        "Aadiwasiwadi"
    ],
    "wof:name":"Aadiwasiwadi",
    "wof:placetype":"locality",
    "wof:population":30
},
  "geometry": {"coordinates":[73.178431,17.996633],"type":"Point"}
}