{
  "type": "Feature",
  "properties": {
    "iso:country":"IN",
    "ks:ks_name":"Raykera",
    "ks:ks_pop":127,
    "ks:ks_type":"VILLAGE",
    "name:eng_x_preferred":[
        "Raykera"
    ],
    "wof:name":"Raykera",
    "wof:placetype":"locality",
    "wof:population":127
},
  "geometry": {"coordinates":[85.007818,22.909302],"type":"Point"}
}