{
  "type": "Feature",
  "properties": {
    "iso:country":"IN",
    "ks:ks_name":"Chak Bore",
    "ks:ks_type":"VILLAGE",
    "name:eng_x_preferred":[
        "Chak Bore"
    ],
    "wof:name":"Chak Bore",
    "wof:placetype":"locality"
},
  "geometry": {"coordinates":[81.11489,25.936032],"type":"Point"}
}