{
  "type": "Feature",
  "properties": {
    "iso:country":"IN",
    "ks:ks_name":"Gadgepada",
    "ks:ks_pop":215,
    "ks:ks_type":"HABITATION",
    "name:eng_x_preferred":[
        "Gadgepada"
    ],
    "wof:name":"Gadgepada",
    "wof:placetype":"locality",
    "wof:population":215
},
  "geometry": {"coordinates":[73.167559,20.035722],"type":"Point"}
}