{
  "type": "Feature",
  "properties": {
    "iso:country":"IN",
    "ks:ks_name":"Jiridamali",
    "ks:ks_pop":2558,
    "ks:ks_type":"VILLAGE",
    "ks:ks_uagg_main":0,
    "name:eng_x_preferred":[
        "Jiridamali"
    ],
    "wof:name":"Jiridamali",
    "wof:placetype":"neighbourhood",
    "wof:population":2558
},
  "geometry": {"coordinates":[85.56060100000001,20.932781],"type":"Point"}
}