{
  "type": "Feature",
  "properties": {
    "iso:country":"IN",
    "ks:ks_name":"Tharhiara",
    "ks:ks_pop":477,
    "ks:ks_type":"VILLAGE",
    "name:eng_x_preferred":[
        "Tharhiara"
    ],
    "wof:name":"Tharhiara",
    "wof:placetype":"locality",
    "wof:population":477
},
  "geometry": {"coordinates":[86.80329399999999,24.591315],"type":"Point"}
}