{
  "type": "Feature",
  "properties": {
    "iso:country":"IN",
    "ks:ks_alt_nam":"JORAWARDIH",
    "ks:ks_name":"Jorawardih",
    "ks:ks_pop":1030,
    "ks:ks_type":"HABITATION",
    "name:eng_x_preferred":[
        "Jorawardih"
    ],
    "wof:name":"Jorawardih",
    "wof:placetype":"locality",
    "wof:population":1030
},
  "geometry": {"coordinates":[85.874343,24.84527],"type":"Point"}
}