{
  "type": "Feature",
  "properties": {
    "iso:country":"IN",
    "ks:ks_name":"Puvena",
    "ks:ks_pop":481,
    "ks:ks_type":"VILLAGE",
    "ks:ks_uagg_main":0,
    "name:eng_x_preferred":[
        "Puvena"
    ],
    "wof:name":"Puvena",
    "wof:placetype":"neighbourhood",
    "wof:population":481
},
  "geometry": {"coordinates":[78.464023,29.170621],"type":"Point"}
}