{
  "type": "Feature",
  "properties": {
    "iso:country":"IN",
    "ks:ks_name":"Kabadpur",
    "ks:ks_pop":0,
    "ks:ks_type":"VILLAGE",
    "name:eng_x_preferred":[
        "Kabadpur"
    ],
    "wof:name":"Kabadpur",
    "wof:placetype":"locality",
    "wof:population":0
},
  "geometry": {"coordinates":[86.579325,25.19314],"type":"Point"}
}