{
  "type": "Feature",
  "properties": {
    "iso:country":"IN",
    "ks:ks_name":"Aswatari",
    "ks:ks_pop":0,
    "ks:ks_type":"VILLAGE",
    "name:eng_x_preferred":[
        "Aswatari"
    ],
    "wof:name":"Aswatari",
    "wof:placetype":"locality",
    "wof:population":0
},
  "geometry": {"coordinates":[85.53133099999999,24.683235],"type":"Point"}
}