{
  "type": "Feature",
  "properties": {
    "iso:country":"IN",
    "ks:ks_alt_nam":"Harangajao deswali",
    "ks:ks_name":"Harangajao Deswali",
    "ks:ks_pop":1006,
    "ks:ks_type":"HABITATION",
    "ks:ks_uagg_main":0,
    "name:eng_x_preferred":[
        "Harangajao Deswali"
    ],
    "wof:name":"Harangajao Deswali",
    "wof:placetype":"neighbourhood",
    "wof:population":1006
},
  "geometry": {"coordinates":[92.852007,25.112683],"type":"Point"}
}