{
  "type": "Feature",
  "properties": {
    "iso:country":"IN",
    "ks:ks_name":"Tarakpada",
    "ks:ks_pop":56,
    "ks:ks_type":"HABITATION",
    "name:eng_x_preferred":[
        "Tarakpada"
    ],
    "wof:name":"Tarakpada",
    "wof:placetype":"locality",
    "wof:population":56
},
  "geometry": {"coordinates":[73.00936900000001,19.675159],"type":"Point"}
}