{
  "type": "Feature",
  "properties": {
    "iso:country":"IN",
    "ks:ks_name":"Silukapatti",
    "ks:ks_pop":531,
    "ks:ks_type":"HABITATION",
    "ks:ks_uagg_main":0,
    "name:eng_x_preferred":[
        "Silukapatti"
    ],
    "wof:name":"Silukapatti",
    "wof:placetype":"neighbourhood",
    "wof:population":531
},
  "geometry": {"coordinates":[78.20996700000001,9.426065],"type":"Point"}
}