{
  "type": "Feature",
  "properties": {
    "iso:country":"IN",
    "ks:ks_name":"Palolithazha",
    "ks:ks_pop":400,
    "ks:ks_type":"HABITATION",
    "name:eng_x_preferred":[
        "Palolithazha"
    ],
    "wof:name":"Palolithazha",
    "wof:placetype":"locality",
    "wof:population":400
},
  "geometry": {"coordinates":[75.76932100000001,11.69581],"type":"Point"}
}