{
  "type": "Feature",
  "properties": {
    "iso:country":"IN",
    "ks:ks_name":"Chakbela",
    "ks:ks_pop":292,
    "ks:ks_type":"VILLAGE",
    "name:eng_x_preferred":[
        "Chakbela"
    ],
    "wof:name":"Chakbela",
    "wof:placetype":"locality",
    "wof:population":292
},
  "geometry": {"coordinates":[87.09441099999999,21.680112],"type":"Point"}
}