{
  "type": "Feature",
  "properties": {
    "gn:admin1_code":"24",
    "gn:admin2_code":"101.0",
    "gn:asciiname":"Mokam",
    "gn:country_code":"IN",
    "gn:dem":309,
    "gn:feature_class":"P",
    "gn:feature_code":"PPL",
    "gn:name":"Mokam",
    "gn:population":0,
    "gn:timezone":"Asia/Kolkata",
    "iso:country":"IN",
    "ks:ks_name":"Mukam",
    "ks:ks_pop":712,
    "ks:ks_type":"VILLAGE",
    "ks:ks_uagg_main":0,
    "name:eng_x_preferred":[
        "Mukam"
    ],
    "wof:name":"Mukam",
    "wof:placetype":"neighbourhood",
    "wof:population":712
},
  "geometry": {"coordinates":[73.61878299999999,27.625767],"type":"Point"}
}