{
  "type": "Feature",
  "properties": {
    "gn:admin1_code":"36",
    "gn:admin2_code":"147.0",
    "gn:asciiname":"Urawar Hasht Taraf",
    "gn:country_code":"IN",
    "gn:dem":144,
    "gn:feature_class":"P",
    "gn:feature_code":"PPL",
    "gn:name":"Ur\u0101war Hasht Taraf",
    "gn:population":0,
    "gn:timezone":"Asia/Kolkata",
    "iso:country":"IN",
    "wof:name":"Urawar Hasht Taraf",
    "wof:placetype":"neighbourhood"
},
  "geometry": {"coordinates":[78.67112,26.92468],"type":"Point"}
}