{
  "type": "Feature",
  "properties": {
    "gn:admin1_code":"37",
    "gn:admin2_code":"411.0",
    "gn:asciiname":"Gotiyapani",
    "gn:country_code":"IN",
    "gn:dem":382,
    "gn:feature_class":"P",
    "gn:feature_code":"PPL",
    "gn:name":"Gotiyap\u0101ni",
    "gn:population":0,
    "gn:timezone":"Asia/Kolkata",
    "iso:country":"IN",
    "ks:ks_name":"Ghotiyapani",
    "ks:ks_pop":514,
    "ks:ks_type":"VILLAGE",
    "name:eng_x_preferred":[
        "Ghotiyapani"
    ],
    "name:eng_x_variant":[
        "Gotiyapani"
    ],
    "wof:name":"Ghotiyapani",
    "wof:placetype":"locality",
    "wof:population":514
},
  "geometry": {"coordinates":[82.322474,20.971131],"type":"Point"}
}