{
  "type": "Feature",
  "properties": {
    "iso:country":"IN",
    "ks:ks_name":"Odaimedu",
    "ks:ks_pop":325,
    "ks:ks_type":"HABITATION",
    "ks:ks_uagg_main":0,
    "name:eng_x_preferred":[
        "Odaimedu"
    ],
    "wof:name":"Odaimedu",
    "wof:placetype":"neighbourhood",
    "wof:population":325
},
  "geometry": {"coordinates":[79.826071,10.829796],"type":"Point"}
}