{
  "type": "Feature",
  "properties": {
    "gn:admin1_code":"36",
    "gn:admin2_code":"188.0",
    "gn:asciiname":"Marchipar Khurd",
    "gn:country_code":"IN",
    "gn:dem":80,
    "gn:feature_class":"P",
    "gn:feature_code":"PPL",
    "gn:name":"March\u012bp\u0101r Khurd",
    "gn:population":0,
    "gn:timezone":"Asia/Kolkata",
    "iso:country":"IN",
    "wof:name":"Marchipar Khurd",
    "wof:placetype":"locality"
},
  "geometry": {"coordinates":[83.42211999999998,26.33019],"type":"Point"}
}