{
  "type": "Feature",
  "properties": {
    "gn:admin1_code":"37.0",
    "gn:admin2_code":"416.0",
    "gn:asciiname":"Jaunga",
    "gn:country_code":"IN",
    "gn:dem":426,
    "gn:feature_class":"P",
    "gn:feature_code":"PPL",
    "gn:name":"Jaunga",
    "gn:population":0,
    "gn:timezone":"Asia/Kolkata",
    "iso:country":"IN",
    "ks:ks_name":"Jaunga",
    "ks:ks_pop":1317,
    "ks:ks_type":"VILLAGE",
    "name:eng_x_preferred":[
        "Jaunga"
    ],
    "wof:name":"Jaunga",
    "wof:placetype":"locality",
    "wof:population":1317
},
  "geometry": {"coordinates":[81.441439,18.961788],"type":"Point"}
}