{
  "type": "Feature",
  "properties": {
    "gn:admin1_code":"36.0",
    "gn:admin2_code":"190.0",
    "gn:asciiname":"Mailauta",
    "gn:country_code":"IN",
    "gn:dem":73,
    "gn:feature_class":"P",
    "gn:feature_code":"PPL",
    "gn:name":"Mailauta",
    "gn:population":0,
    "gn:timezone":"Asia/Kolkata",
    "iso:country":"IN",
    "ks:ks_alt_nam":"Mailauta",
    "ks:ks_name":"Mailaut",
    "ks:ks_type":"VILLAGE",
    "ks:ks_uagg_main":0,
    "name:eng_x_preferred":[
        "Mailaut"
    ],
    "name:eng_x_variant":[
        "Mailauta"
    ],
    "wof:name":"Mailaut",
    "wof:placetype":"neighbourhood"
},
  "geometry": {"coordinates":[83.849695,26.226048],"type":"Point"}
}