{
  "type": "Feature",
  "properties": {
    "iso:country":"IN",
    "ks:ks_name":"Ashrafpur",
    "ks:ks_type":"VILLAGE",
    "name:eng_x_preferred":[
        "Ashrafpur"
    ],
    "wof:name":"Ashrafpur",
    "wof:placetype":"locality"
},
  "geometry": {"coordinates":[77.12312799999999,20.586269],"type":"Point"}
}