{
  "type": "Feature",
  "properties": {
    "gn:admin1_code":"25.0",
    "gn:admin2_code":"618.0",
    "gn:asciiname":"Iluppur",
    "gn:country_code":"IN",
    "gn:dem":10,
    "gn:feature_class":"P",
    "gn:feature_code":"PPL",
    "gn:name":"Ilupp\u016br",
    "gn:population":0,
    "gn:timezone":"Asia/Kolkata",
    "iso:country":"IN",
    "name:bpy_x_preferred":[
        "\u0987\u09b2\u09c1\u09aa\u09cd\u09aa\u09c1\u09b0"
    ],
    "name:ceb_x_preferred":[
        "Ilupp\u016br"
    ],
    "name:ita_x_preferred":[
        "Iluppur"
    ],
    "name:msa_x_preferred":[
        "Iluppur"
    ],
    "name:new_x_preferred":[
        "\u0907\u0932\u0941\u092a\u094d\u092a\u0941\u0930"
    ],
    "name:nld_x_preferred":[
        "Iluppur"
    ],
    "name:por_x_preferred":[
        "Ilupur"
    ],
    "name:swe_x_preferred":[
        "Ilupp\u016br"
    ],
    "name:tam_x_preferred":[
        "\u0b87\u0bb2\u0bc1\u0baa\u0bcd\u0baa\u0bc2\u0bb0\u0bcd"
    ],
    "name:vie_x_preferred":[
        "Iluppur"
    ],
    "name:zho_x_preferred":[
        "\u4f0a\u5362\u666e\u5c14"
    ],
    "wof:name":"Iluppur",
    "wof:placetype":"locality"
},
  "geometry": {"coordinates":[79.73137,10.73766],"type":"Point"}
}