{
  "type": "Feature",
  "properties": {
    "gn:admin1_code":"37",
    "gn:admin2_code":"414.0",
    "gn:asciiname":"Kondawal",
    "gn:country_code":"IN",
    "gn:dem":552,
    "gn:feature_class":"P",
    "gn:feature_code":"PPL",
    "gn:name":"Kond\u0101wal",
    "gn:population":0,
    "gn:timezone":"Asia/Kolkata",
    "iso:country":"IN",
    "wof:name":"Kondawal",
    "wof:placetype":"locality"
},
  "geometry": {"coordinates":[81.99885999999999,19.1276],"type":"Point"}
}