{
  "type": "Feature",
  "properties": {
    "iso:country":"IN",
    "ks:ks_alt_nam":"CHINTALWADI THANDA",
    "ks:ks_name":"Chintalwadi Thanda",
    "ks:ks_pop":100,
    "ks:ks_type":"HABITATION",
    "name:eng_x_preferred":[
        "Chintalwadi Thanda"
    ],
    "wof:name":"Chintalwadi Thanda",
    "wof:placetype":"locality",
    "wof:population":100
},
  "geometry": {"coordinates":[77.63918700000001,18.296257],"type":"Point"}
}