{
  "type": "Feature",
  "properties": {
    "iso:country":"IN",
    "ks:ks_name":"Satbhaiyapara",
    "ks:ks_pop":258,
    "ks:ks_type":"VILLAGE",
    "name:eng_x_preferred":[
        "Satbhaiyapara"
    ],
    "wof:name":"Satbhaiyapara",
    "wof:placetype":"locality",
    "wof:population":258
},
  "geometry": {"coordinates":[91.911665,23.706396],"type":"Point"}
}