{
  "type": "Feature",
  "properties": {
    "gn:admin1_code":"02",
    "gn:admin2_code":"543.0",
    "gn:asciiname":"Lakkavarapukota",
    "gn:country_code":"IN",
    "gn:dem":60,
    "gn:feature_class":"P",
    "gn:feature_code":"PPL",
    "gn:name":"Lakkavarapukota",
    "gn:population":0,
    "gn:timezone":"Asia/Kolkata",
    "iso:country":"IN",
    "wof:name":"Lakkavarapukota",
    "wof:placetype":"locality"
},
  "geometry": {"coordinates":[83.15679,18.0239],"type":"Point"}
}