{
  "type": "Feature",
  "properties": {
    "gn:admin1_code":"02",
    "gn:admin2_code":"543.0",
    "gn:asciiname":"Lakkavarapukota",
    "gn:country_code":"IN",
    "gn:dem":60,
    "gn:feature_class":"P",
    "gn:feature_code":"PPL",
    "gn:name":"Lakkavarapukota",
    "gn:population":0,
    "gn:timezone":"Asia/Kolkata",
    "iso:country":"IN",
    "name:new_x_preferred":[
        "\u0932\u0915\u094d\u0915\u0935\u0930\u092a\u0941\u0915\u094b\u091f \u092e\u0923\u094d\u0921\u0932"
    ],
    "name:tam_x_preferred":[
        "\u0bb2\u0b95\u0bcd\u0b95\u0bb5\u0bb0\u0baa\u0bcd\u0baa\u0bc1\u0b95\u0bcb\u0b9f\u0bcd\u0b9f\u0bc8"
    ],
    "name:tel_x_preferred":[
        "\u0c32\u0c15\u0c4d\u0c15\u0c35\u0c30\u0c2a\u0c41\u0c15\u0c4b\u0c1f"
    ],
    "name:urd_x_preferred":[
        "\u0644\u0627\u06a9\u0627\u0648\u0627\u0631\u0627\u067e\u0648\u06a9\u0648\u0679\u0627"
    ],
    "wof:name":"Lakkavarapukota",
    "wof:placetype":"locality"
},
  "geometry": {"coordinates":[83.15679,18.0239],"type":"Point"}
}