{
  "type": "Feature",
  "properties": {
    "iso:country":"IN",
    "ks:ks_name":"Kalyakhedi",
    "ks:ks_pop":50,
    "ks:ks_type":"VILLAGE",
    "name:eng_x_preferred":[
        "Kalyakhedi"
    ],
    "wof:name":"Kalyakhedi",
    "wof:placetype":"locality",
    "wof:population":50
},
  "geometry": {"coordinates":[74.896049,24.369604],"type":"Point"}
}