{
  "type": "Feature",
  "properties": {
    "gn:admin1_code":"13.0",
    "gn:admin2_code":"598.0",
    "gn:asciiname":"Ochira",
    "gn:country_code":"IN",
    "gn:dem":10,
    "gn:feature_class":"P",
    "gn:feature_code":"PPL",
    "gn:name":"Ochira",
    "gn:population":0,
    "gn:timezone":"Asia/Kolkata",
    "iso:country":"IN",
    "ks:ks_name":"Ochira",
    "ks:ks_pop":3450,
    "ks:ks_type":"HABITATION",
    "name:eng_x_preferred":[
        "Ochira"
    ],
    "wof:name":"Ochira",
    "wof:placetype":"locality",
    "wof:population":3450
},
  "geometry": {"coordinates":[76.511715,9.137023],"type":"Point"}
}