{
  "type": "Feature",
  "properties": {
    "iso:country":"IN",
    "ks:ks_name":"Basudeipur",
    "ks:ks_pop":1016,
    "ks:ks_type":"VILLAGE",
    "ks:ks_uagg_main":0,
    "name:eng_x_preferred":[
        "Basudeipur"
    ],
    "wof:name":"Basudeipur",
    "wof:placetype":"neighbourhood",
    "wof:population":1016
},
  "geometry": {"coordinates":[85.225253,20.2752],"type":"Point"}
}