{
  "type": "Feature",
  "properties": {
    "iso:country":"IN",
    "ks:ks_name":"Olikana",
    "ks:ks_pop":604,
    "ks:ks_type":"VILLAGE",
    "ks:ks_uagg_main":0,
    "name:eng_x_preferred":[
        "Olikana"
    ],
    "wof:name":"Olikana",
    "wof:placetype":"neighbourhood",
    "wof:population":604
},
  "geometry": {"coordinates":[85.93611799999999,20.081672],"type":"Point"}
}