{
  "type": "Feature",
  "properties": {
    "iso:country":"IN",
    "ks:ks_name":"Naha Tola",
    "ks:ks_pop":265,
    "ks:ks_type":"HABITATION",
    "name:eng_x_preferred":[
        "Naha Tola"
    ],
    "wof:name":"Naha Tola",
    "wof:placetype":"locality",
    "wof:population":265
},
  "geometry": {"coordinates":[86.552097,25.854049],"type":"Point"}
}