{
  "type": "Feature",
  "properties": {
    "iso:country":"IN",
    "ks:ks_name":"Ramna",
    "ks:ks_pop":300,
    "ks:ks_type":"VILLAGE",
    "ks:ks_uagg_main":0,
    "name:eng_x_preferred":[
        "Ramna"
    ],
    "wof:name":"Ramna",
    "wof:placetype":"neighbourhood",
    "wof:population":300
},
  "geometry": {"coordinates":[83.008202,25.227947],"type":"Point"}
}