{
  "type": "Feature",
  "properties": {
    "gn:admin1_code":"35",
    "gn:admin2_code":"459.0",
    "gn:asciiname":"Marhi Kanungo",
    "gn:country_code":"IN",
    "gn:dem":491,
    "gn:feature_class":"P",
    "gn:feature_code":"PPL",
    "gn:name":"Marhi K\u0101n\u016bngo",
    "gn:population":0,
    "gn:timezone":"Asia/Kolkata",
    "iso:country":"IN",
    "wof:name":"Marhi Kanungo",
    "wof:placetype":"locality"
},
  "geometry": {"coordinates":[77.53305999999998,24.55955],"type":"Point"}
}