{
  "type": "Feature",
  "properties": {
    "gn:admin1_code":"10.0",
    "gn:admin2_code":"78.0",
    "gn:asciiname":"Dhani Gahlakhera",
    "gn:country_code":"IN",
    "gn:dem":207,
    "gn:feature_class":"P",
    "gn:feature_code":"PPL",
    "gn:name":"Dh\u0101ni Gahl\u0101khera",
    "gn:population":0,
    "gn:timezone":"Asia/Kolkata",
    "iso:country":"IN",
    "wof:name":"Dhani Gahlakhera",
    "wof:placetype":"locality"
},
  "geometry": {"coordinates":[75.29541999999999,29.51176],"type":"Point"}
}