{
  "type": "Feature",
  "properties": {
    "iso:country":"IN",
    "ks:ks_name":"Nikhirda",
    "ks:ks_pop":84,
    "ks:ks_type":"VILLAGE",
    "name:eng_x_preferred":[
        "Nikhirda"
    ],
    "wof:name":"Nikhirda",
    "wof:placetype":"locality",
    "wof:population":84
},
  "geometry": {"coordinates":[86.438138,21.892579],"type":"Point"}
}