{
  "type": "Feature",
  "properties": {
    "iso:country":"IN",
    "ks:ks_name":"Pacharuwa Kainhargaon",
    "ks:ks_pop":38,
    "ks:ks_type":"VILLAGE",
    "name:eng_x_preferred":[
        "Pacharuwa Kainhargaon"
    ],
    "wof:name":"Pacharuwa Kainhargaon",
    "wof:placetype":"locality",
    "wof:population":38
},
  "geometry": {"coordinates":[79.227924,29.862372],"type":"Point"}
}