{
  "type": "Feature",
  "properties": {
    "gn:admin1_code":"19",
    "gn:admin2_code":"567.0",
    "gn:asciiname":"Vaddanhal",
    "gn:country_code":"IN",
    "gn:dem":710,
    "gn:feature_class":"P",
    "gn:feature_code":"PPL",
    "gn:name":"Vaddanh\u0101l",
    "gn:population":0,
    "gn:timezone":"Asia/Kolkata",
    "iso:country":"IN",
    "ks:ks_name":"Vaddanalu",
    "ks:ks_pop":2673,
    "ks:ks_type":"VILLAGE",
    "name:eng_x_preferred":[
        "Vaddanalu"
    ],
    "name:eng_x_variant":[
        "Vaddanhal"
    ],
    "wof:name":"Vaddanalu",
    "wof:placetype":"locality",
    "wof:population":2673
},
  "geometry": {"coordinates":[75.99853899999999,13.991342],"type":"Point"}
}