{
  "type": "Feature",
  "properties": {
    "gn:admin1_code":"19",
    "gn:admin2_code":"567.0",
    "gn:asciiname":"Vaddanhal",
    "gn:country_code":"IN",
    "gn:dem":710,
    "gn:feature_class":"P",
    "gn:feature_code":"PPL",
    "gn:name":"Vaddanh\u0101l",
    "gn:population":0,
    "gn:timezone":"Asia/Kolkata",
    "iso:country":"IN",
    "wof:name":"Vaddanhal",
    "wof:placetype":"locality"
},
  "geometry": {"coordinates":[76.00345,13.99041],"type":"Point"}
}