{
  "type": "Feature",
  "properties": {
    "iso:country":"IN",
    "ks:ks_alt_nam":"Chh\u0101na Bilw\u0101l",
    "ks:ks_alt_nam_2":"Chhana Bilwal",
    "ks:ks_name":"Chhana",
    "ks:ks_type":"VILLAGE",
    "name:eng_x_preferred":[
        "Chhana"
    ],
    "name:eng_x_variant":[
        "Chh\u0101na Bilw\u0101l",
        "Chhana Bilwal"
    ],
    "wof:name":"Chhana",
    "wof:placetype":"locality"
},
  "geometry": {"coordinates":[79.475025,29.704906],"type":"Point"}
}