{
  "type": "Feature",
  "properties": {
    "gn:admin1_code":"34.0",
    "gn:admin2_code":"220.0",
    "gn:asciiname":"Sadabpur Mahuwa",
    "gn:country_code":"IN",
    "gn:dem":54,
    "gn:feature_class":"P",
    "gn:feature_code":"PPL",
    "gn:name":"S\u0101dabpur Mahuwa",
    "gn:population":0,
    "gn:timezone":"Asia/Kolkata",
    "iso:country":"IN",
    "ks:ks_name":"Sadabpur Mahua",
    "ks:ks_pop":3366,
    "ks:ks_type":"VILLAGE",
    "name:eng_x_preferred":[
        "Sadabpur Mahua"
    ],
    "name:eng_x_variant":[
        "Sadabpur Mahuwa"
    ],
    "wof:name":"Sadabpur Mahua",
    "wof:placetype":"locality",
    "wof:population":3366
},
  "geometry": {"coordinates":[85.39896899999999,25.807808],"type":"Point"}
}