{
  "type": "Feature",
  "properties": {
    "gn:admin1_code":"23.0",
    "gn:admin2_code":"38.0",
    "gn:asciiname":"Sajan",
    "gn:country_code":"IN",
    "gn:dem":300,
    "gn:feature_class":"P",
    "gn:feature_code":"PPL",
    "gn:name":"Sajan",
    "gn:population":0,
    "gn:timezone":"Asia/Kolkata",
    "iso:country":"IN",
    "name:ceb_x_preferred":[
        "Sajan"
    ],
    "name:deu_x_preferred":[
        "Sajan"
    ],
    "name:srp_x_preferred":[
        "\u0421\u0430\u0458\u0430\u043d"
    ],
    "name:swe_x_preferred":[
        "Sajan"
    ],
    "wof:name":"Sajan",
    "wof:placetype":"locality"
},
  "geometry": {"coordinates":[75.88871999999998,31.55876],"type":"Point"}
}