{
  "type": "Feature",
  "properties": {
    "iso:country":"IN",
    "ks:ks_name":"Jajar Adai",
    "ks:ks_pop":234,
    "ks:ks_type":"VILLAGE",
    "name:eng_x_preferred":[
        "Jajar Adai"
    ],
    "wof:name":"Jajar Adai",
    "wof:placetype":"locality",
    "wof:population":234
},
  "geometry": {"coordinates":[83.969414,25.607446],"type":"Point"}
}