{
  "type": "Feature",
  "properties": {
    "gn:admin1_code":"12",
    "gn:asciiname":"Kopra",
    "gn:country_code":"IN",
    "gn:dem":2533,
    "gn:feature_class":"P",
    "gn:feature_code":"PPL",
    "gn:name":"Kopra",
    "gn:population":0,
    "gn:timezone":"Asia/Kolkata",
    "iso:country":"IN",
    "wof:name":"Kopra",
    "wof:placetype":"locality"
},
  "geometry": {"coordinates":[74.10256,34.18029],"type":"Point"}
}