{
  "type": "Feature",
  "properties": {
    "iso:country":"IN",
    "ks:ks_name":"Doluipara1",
    "ks:ks_pop":677,
    "ks:ks_type":"HABITATION",
    "name:eng_x_preferred":[
        "Doluipara1"
    ],
    "wof:name":"Doluipara1",
    "wof:placetype":"locality",
    "wof:population":677
},
  "geometry": {"coordinates":[87.985406,22.658951],"type":"Point"}
}