{
  "type": "Feature",
  "properties": {
    "iso:country":"IN",
    "ks:ks_name":"Koviladianpatty",
    "ks:ks_pop":167,
    "ks:ks_type":"HABITATION",
    "name:eng_x_preferred":[
        "Koviladianpatty"
    ],
    "wof:name":"Koviladianpatty",
    "wof:placetype":"locality",
    "wof:population":167
},
  "geometry": {"coordinates":[78.548992,10.445281],"type":"Point"}
}