{
  "type": "Feature",
  "properties": {
    "gn:admin1_code":"35",
    "gn:admin2_code":"436.0",
    "gn:asciiname":"Bhataheri",
    "gn:country_code":"IN",
    "gn:dem":422,
    "gn:feature_class":"P",
    "gn:feature_code":"PPL",
    "gn:name":"Bh\u0101t\u0101heri",
    "gn:population":0,
    "gn:timezone":"Asia/Kolkata",
    "iso:country":"IN",
    "wof:name":"Bhataheri",
    "wof:placetype":"locality"
},
  "geometry": {"coordinates":[76.25717,23.59991],"type":"Point"}
}