{
  "type": "Feature",
  "properties": {
    "iso:country":"IN",
    "ks:ks_name":"Pipalya",
    "ks:ks_pop":717,
    "ks:ks_type":"VILLAGE",
    "name:eng_x_preferred":[
        "Pipalya"
    ],
    "wof:name":"Pipalya",
    "wof:placetype":"locality",
    "wof:population":717
},
  "geometry": {"coordinates":[76.69636,22.113939],"type":"Point"}
}