{
  "type": "Feature",
  "properties": {
    "iso:country":"IN",
    "ks:ks_name":"Bairigadde",
    "ks:ks_pop":100,
    "ks:ks_type":"HABITATION",
    "name:eng_x_preferred":[
        "Bairigadde"
    ],
    "wof:name":"Bairigadde",
    "wof:placetype":"locality",
    "wof:population":100
},
  "geometry": {"coordinates":[75.56092599999999,13.227556],"type":"Point"}
}