{
  "type": "Feature",
  "properties": {
    "gn:admin1_code":"35",
    "gn:admin2_code":"437.0",
    "gn:asciiname":"Talod",
    "gn:country_code":"IN",
    "gn:dem":486,
    "gn:feature_class":"P",
    "gn:feature_code":"PPL",
    "gn:name":"T\u0101lod",
    "gn:population":0,
    "gn:timezone":"Asia/Kolkata",
    "iso:country":"IN",
    "name:bpy_x_preferred":[
        "\u09a4\u09be\u09b2\u09cb\u09a6"
    ],
    "name:guj_x_preferred":[
        "\u0aa4\u0ab2\u0acb\u0aa6"
    ],
    "name:hin_x_preferred":[
        "\u0924\u0932\u094b\u0926"
    ],
    "name:ita_x_preferred":[
        "Talod"
    ],
    "name:msa_x_preferred":[
        "Talod"
    ],
    "name:por_x_preferred":[
        "Talod"
    ],
    "name:spa_x_preferred":[
        "Talod"
    ],
    "name:vie_x_preferred":[
        "Talod"
    ],
    "name:zho_x_preferred":[
        "\u5854\u6d1b\u5fb7"
    ],
    "wof:name":"Talod",
    "wof:placetype":"locality"
},
  "geometry": {"coordinates":[76.41523000000002,23.02125],"type":"Point"}
}