{
  "type": "Feature",
  "properties": {
    "iso:country":"IN",
    "ks:ks_name":"Chevo",
    "ks:ks_pop":0,
    "ks:ks_type":"VILLAGE",
    "name:eng_x_preferred":[
        "Chevo"
    ],
    "wof:name":"Chevo",
    "wof:placetype":"locality",
    "wof:population":0
},
  "geometry": {"coordinates":[87.619124,24.779511],"type":"Point"}
}