{
  "type": "Feature",
  "properties": {
    "iso:country":"IN",
    "ks:ks_name":"Bharkatta",
    "ks:ks_pop":1477,
    "ks:ks_type":"VILLAGE",
    "ks:ks_uagg_main":0,
    "name:eng_x_preferred":[
        "Bharkatta"
    ],
    "wof:name":"Bharkatta",
    "wof:placetype":"neighbourhood",
    "wof:population":1477
},
  "geometry": {"coordinates":[86.027282,24.21544],"type":"Point"}
}