{
  "type": "Feature",
  "properties": {
    "iso:country":"IN",
    "ks:ks_name":"Asman",
    "ks:ks_pop":406,
    "ks:ks_type":"HABITATION",
    "name:eng_x_preferred":[
        "Asman"
    ],
    "wof:name":"Asman",
    "wof:placetype":"locality",
    "wof:population":406
},
  "geometry": {"coordinates":[79.70894699999999,26.631283],"type":"Point"}
}