{
  "type": "Feature",
  "properties": {
    "iso:country":"IN",
    "ks:ks_name":"Doddegowdana Kopplu",
    "ks:ks_pop":212,
    "ks:ks_type":"HABITATION",
    "name:eng_x_preferred":[
        "Doddegowdana Kopplu"
    ],
    "wof:name":"Doddegowdana Kopplu",
    "wof:placetype":"locality",
    "wof:population":212
},
  "geometry": {"coordinates":[76.202467,12.48994],"type":"Point"}
}