{
  "type": "Feature",
  "properties": {
    "iso:country":"IN",
    "ks:ks_name":"Chalkipara",
    "ks:ks_pop":697,
    "ks:ks_type":"HABITATION",
    "name:eng_x_preferred":[
        "Chalkipara"
    ],
    "wof:name":"Chalkipara",
    "wof:placetype":"locality",
    "wof:population":697
},
  "geometry": {"coordinates":[81.401996,18.92601],"type":"Point"}
}