{
  "type": "Feature",
  "properties": {
    "gn:admin1_code":"21.0",
    "gn:admin2_code":"396.0",
    "gn:asciiname":"Guriti",
    "gn:country_code":"IN",
    "gn:dem":409,
    "gn:feature_class":"P",
    "gn:feature_code":"PPL",
    "gn:name":"Guriti",
    "gn:population":0,
    "gn:timezone":"Asia/Kolkata",
    "iso:country":"IN",
    "ks:ks_name":"Guruti",
    "ks:ks_pop":109,
    "ks:ks_type":"VILLAGE",
    "name:eng_x_preferred":[
        "Guruti"
    ],
    "name:eng_x_variant":[
        "Guriti"
    ],
    "wof:name":"Guruti",
    "wof:placetype":"locality",
    "wof:population":109
},
  "geometry": {"coordinates":[83.339608,19.23817],"type":"Point"}
}