{
  "type": "Feature",
  "properties": {
    "gn:admin1_code":"25.0",
    "gn:admin2_code":"604.0",
    "gn:asciiname":"Villiyambakkam",
    "gn:country_code":"IN",
    "gn:dem":44,
    "gn:feature_class":"P",
    "gn:feature_code":"PPL",
    "gn:name":"Villiyamb\u0101kkam",
    "gn:population":0,
    "gn:timezone":"Asia/Kolkata",
    "iso:country":"IN",
    "ks:ks_alt_nam":"Villiyamb\u0101kkam",
    "ks:ks_name":"Villiyambakkam",
    "ks:ks_type":"VILLAGE",
    "ks:ks_uagg_main":0,
    "name:eng_x_preferred":[
        "Villiyambakkam"
    ],
    "name:eng_x_variant":[
        "Villiyamb\u0101kkam"
    ],
    "wof:name":"Villiyambakkam",
    "wof:placetype":"locality"
},
  "geometry": {"coordinates":[79.943195,12.752884],"type":"Point"}
}