{
  "type": "Feature",
  "properties": {
    "iso:country":"IN",
    "ks:ks_name":"Koorahu",
    "ks:ks_pop":467,
    "ks:ks_type":"HABITATION",
    "name:eng_x_preferred":[
        "Koorahu"
    ],
    "wof:name":"Koorahu",
    "wof:placetype":"locality",
    "wof:population":467
},
  "geometry": {"coordinates":[80.68223500000001,25.105702],"type":"Point"}
}