{
  "type": "Feature",
  "properties": {
    "gn:admin1_code":"34.0",
    "gn:admin2_code":"234.0",
    "gn:asciiname":"Bisrampur",
    "gn:country_code":"IN",
    "gn:dem":88,
    "gn:feature_class":"P",
    "gn:feature_code":"PPL",
    "gn:name":"Bisr\u0101mpur",
    "gn:population":0,
    "gn:timezone":"Asia/Kolkata",
    "iso:country":"IN",
    "name:ceb_x_preferred":[
        "Bisrampur"
    ],
    "name:mai_x_preferred":[
        "\u0935\u093f\u0936\u094d\u0930\u093e\u092e\u092a\u0941\u0930"
    ],
    "name:msa_x_preferred":[
        "Bisrampur"
    ],
    "name:nep_x_preferred":[
        "\u0935\u093f\u0936\u094d\u0930\u093e\u092e\u092a\u0941\u0930"
    ],
    "name:new_x_preferred":[
        "\u0935\u093f\u0938\u094d\u0930\u093e\u092e\u092a\u0941\u0930"
    ],
    "name:pol_x_preferred":[
        "Bisrampur"
    ],
    "wof:name":"Bisrampur",
    "wof:placetype":"locality"
},
  "geometry": {"coordinates":[84.03605999999998,25.19531],"type":"Point"}
}