{
  "type": "Feature",
  "properties": {
    "iso:country":"IN",
    "ks:ks_name":"Dasoriya",
    "ks:ks_pop":1332,
    "ks:ks_type":"VILLAGE",
    "name:eng_x_preferred":[
        "Dasoriya"
    ],
    "wof:name":"Dasoriya",
    "wof:placetype":"locality",
    "wof:population":1332
},
  "geometry": {"coordinates":[71.236861,24.763731],"type":"Point"}
}