{
  "type": "Feature",
  "properties": {
    "iso:country":"IN",
    "ks:ks_name":"Sethuvarayanatham",
    "ks:ks_pop":110,
    "ks:ks_type":"HABITATION",
    "ks:ks_uagg_main":0,
    "name:eng_x_preferred":[
        "Sethuvarayanatham"
    ],
    "wof:name":"Sethuvarayanatham",
    "wof:placetype":"neighbourhood",
    "wof:population":110
},
  "geometry": {"coordinates":[79.37581400000001,11.066509],"type":"Point"}
}