{
  "type": "Feature",
  "properties": {
    "gn:admin1_code":"36",
    "gn:admin2_code":"184.0",
    "gn:asciiname":"Sairapar",
    "gn:country_code":"IN",
    "gn:dem":88,
    "gn:feature_class":"P",
    "gn:feature_code":"PPL",
    "gn:name":"Sair\u0101p\u0101r",
    "gn:population":0,
    "gn:timezone":"Asia/Kolkata",
    "iso:country":"IN",
    "wof:name":"Sairapar",
    "wof:placetype":"neighbourhood"
},
  "geometry": {"coordinates":[83.05580999999999,27.21967],"type":"Point"}
}