{
  "type": "Feature",
  "properties": {
    "iso:country":"IN",
    "ks:ks_name":"Malikpur",
    "ks:ks_pop":345,
    "ks:ks_type":"HABITATION",
    "name:eng_x_preferred":[
        "Malikpur"
    ],
    "wof:name":"Malikpur",
    "wof:placetype":"locality",
    "wof:population":345
},
  "geometry": {"coordinates":[85.92789999999999,24.94668],"type":"Point"}
}