{
  "type": "Feature",
  "properties": {
    "gn:admin1_code":"12.0",
    "gn:admin2_code":"006",
    "gn:asciiname":"Kakadan",
    "gn:country_code":"IN",
    "gn:dem":827,
    "gn:feature_class":"P",
    "gn:feature_code":"PPL",
    "gn:name":"K\u0101kadan",
    "gn:population":0,
    "gn:timezone":"Asia/Kolkata",
    "iso:country":"IN",
    "wof:name":"Kakadan",
    "wof:placetype":"locality"
},
  "geometry": {"coordinates":[74.34999999999999,33.225],"type":"Point"}
}