{
  "type": "Feature",
  "properties": {
    "iso:country":"IN",
    "ks:ks_name":"Rifuji Colony",
    "ks:ks_pop":713,
    "ks:ks_type":"HABITATION",
    "ks:ks_uagg_main":0,
    "name:eng_x_preferred":[
        "Rifuji Colony"
    ],
    "wof:name":"Rifuji Colony",
    "wof:placetype":"neighbourhood",
    "wof:population":713
},
  "geometry": {"coordinates":[84.93841,26.572265],"type":"Point"}
}