{
  "type": "Feature",
  "properties": {
    "gn:admin1_code":"39.0",
    "gn:admin2_code":"61.0",
    "gn:asciiname":"Dobriyalsar",
    "gn:country_code":"IN",
    "gn:dem":1329,
    "gn:feature_class":"P",
    "gn:feature_code":"PPL",
    "gn:name":"Dobriy\u0101ls\u0101r",
    "gn:population":0,
    "gn:timezone":"Asia/Kolkata",
    "iso:country":"IN",
    "wof:name":"Dobriyalsar",
    "wof:placetype":"locality"
},
  "geometry": {"coordinates":[79.07325,29.70739],"type":"Point"}
}