{
  "type": "Feature",
  "properties": {
    "gn:admin1_code":"3.0",
    "gn:admin2_code":"316.0",
    "gn:asciiname":"Tikalpur",
    "gn:country_code":"IN",
    "gn:dem":38,
    "gn:feature_class":"P",
    "gn:feature_code":"PPL",
    "gn:name":"Tikalpur",
    "gn:population":0,
    "gn:timezone":"Asia/Kolkata",
    "iso:country":"IN",
    "wof:name":"Tikalpur",
    "wof:placetype":"locality"
},
  "geometry": {"coordinates":[92.96292,24.94947],"type":"Point"}
}