{
  "type": "Feature",
  "properties": {
    "iso:country":"IN",
    "ks:ks_name":"Jogidih",
    "ks:ks_pop":431,
    "ks:ks_type":"VILLAGE",
    "ks:ks_uagg_main":0,
    "name:eng_x_preferred":[
        "Jogidih"
    ],
    "wof:name":"Jogidih",
    "wof:placetype":"neighbourhood",
    "wof:population":431
},
  "geometry": {"coordinates":[85.802556,24.382374],"type":"Point"}
}