{
  "type": "Feature",
  "properties": {
    "iso:country":"IN",
    "ks:ks_name":"Khudra",
    "ks:ks_pop":0,
    "ks:ks_type":"VILLAGE",
    "name:eng_x_preferred":[
        "Khudra"
    ],
    "wof:name":"Khudra",
    "wof:placetype":"locality",
    "wof:population":0
},
  "geometry": {"coordinates":[83.76195199999999,25.524387],"type":"Point"}
}