{
  "type": "Feature",
  "properties": {
    "iso:country":"IN",
    "ks:ks_name":"Beednaulakha",
    "ks:ks_pop":6,
    "ks:ks_type":"VILLAGE",
    "name:eng_x_preferred":[
        "Beednaulakha"
    ],
    "wof:name":"Beednaulakha",
    "wof:placetype":"locality",
    "wof:population":6
},
  "geometry": {"coordinates":[75.04258400000001,24.040821],"type":"Point"}
}