{
  "type": "Feature",
  "properties": {
    "gn:admin1_code":"21",
    "gn:admin2_code":"395.0",
    "gn:asciiname":"Rakastunda",
    "gn:country_code":"IN",
    "gn:dem":268,
    "gn:feature_class":"P",
    "gn:feature_code":"PPL",
    "gn:name":"Rakastunda",
    "gn:population":0,
    "gn:timezone":"Asia/Kolkata",
    "iso:country":"IN",
    "ks:ks_name":"Rakastunda",
    "ks:ks_type":"VILLAGE",
    "name:eng_x_preferred":[
        "Rakastunda"
    ],
    "wof:name":"Rakastunda",
    "wof:placetype":"locality"
},
  "geometry": {"coordinates":[83.105622,19.81058],"type":"Point"}
}