{
  "type": "Feature",
  "properties": {
    "iso:country":"IN",
    "ks:ks_name":"Dikoi Tokbi",
    "ks:ks_pop":113,
    "ks:ks_type":"HABITATION",
    "name:eng_x_preferred":[
        "Dikoi Tokbi"
    ],
    "wof:name":"Dikoi Tokbi",
    "wof:placetype":"locality",
    "wof:population":113
},
  "geometry": {"coordinates":[93.042284,26.138555],"type":"Point"}
}