{
  "type": "Feature",
  "properties": {
    "gn:admin1_code":"36.0",
    "gn:admin2_code":"183.0",
    "gn:asciiname":"Dun",
    "gn:country_code":"IN",
    "gn:dem":104,
    "gn:feature_class":"P",
    "gn:feature_code":"PPL",
    "gn:name":"Dun",
    "gn:population":0,
    "gn:timezone":"Asia/Kolkata",
    "iso:country":"IN",
    "name:bul_x_preferred":[
        "\u0414\u0443\u043d"
    ],
    "name:cat_x_preferred":[
        "Dun"
    ],
    "name:deu_x_preferred":[
        "Dun"
    ],
    "name:epo_x_preferred":[
        "Dun"
    ],
    "name:fas_x_preferred":[
        "\u062f\u0627\u0646"
    ],
    "name:fra_x_preferred":[
        "Dun"
    ],
    "name:ita_x_preferred":[
        "Dun"
    ],
    "name:kor_x_preferred":[
        "\ub454"
    ],
    "name:nld_x_preferred":[
        "Dun"
    ],
    "name:nor_x_preferred":[
        "Dun"
    ],
    "name:por_x_preferred":[
        "Dun"
    ],
    "name:rus_x_preferred":[
        "\u0414\u0443\u043d"
    ],
    "name:sco_x_preferred":[
        "Dun"
    ],
    "name:zho_x_preferred":[
        "\u51f1\u723e\u7279\u5821\u5be8"
    ],
    "wof:name":"Dun",
    "wof:placetype":"locality"
},
  "geometry": {"coordinates":[81.68219999999999,27.01044000000001],"type":"Point"}
}