{
  "type": "Feature",
  "properties": {
    "iso:country":"IN",
    "ks:ks_alt_nam":"Rajamani thottam",
    "ks:ks_name":"Rajamani Thottam",
    "ks:ks_pop":232,
    "ks:ks_type":"HABITATION",
    "name:eng_x_preferred":[
        "Rajamani Thottam"
    ],
    "wof:name":"Rajamani Thottam",
    "wof:placetype":"locality",
    "wof:population":232
},
  "geometry": {"coordinates":[77.883697,11.499985],"type":"Point"}
}