{
  "type": "Feature",
  "properties": {
    "iso:country":"IN",
    "ks:ks_alt_nam":"yadav Tola East",
    "ks:ks_name":"Yadav Tola East",
    "ks:ks_pop":102,
    "ks:ks_type":"HABITATION",
    "name:eng_x_preferred":[
        "Yadav Tola East"
    ],
    "wof:name":"Yadav Tola East",
    "wof:placetype":"locality",
    "wof:population":102
},
  "geometry": {"coordinates":[85.58552,25.62017],"type":"Point"}
}