{
  "type": "Feature",
  "properties": {
    "gn:admin1_code":"39.0",
    "gn:admin2_code":"63.0",
    "gn:asciiname":"Bilori",
    "gn:country_code":"IN",
    "gn:dem":1476,
    "gn:feature_class":"P",
    "gn:feature_code":"PPL",
    "gn:name":"Bilori",
    "gn:population":0,
    "gn:timezone":"Asia/Kolkata",
    "iso:country":"IN",
    "ks:ks_name":"Bilori",
    "ks:ks_type":"VILLAGE",
    "name:eng_x_preferred":[
        "Bilori"
    ],
    "wof:name":"Bilori",
    "wof:placetype":"locality"
},
  "geometry": {"coordinates":[79.740127,29.766269],"type":"Point"}
}