{
  "type": "Feature",
  "properties": {
    "gn:admin1_code":"21",
    "gn:admin2_code":"370.0",
    "gn:asciiname":"Saraikela",
    "gn:country_code":"IN",
    "gn:dem":224,
    "gn:feature_class":"P",
    "gn:feature_code":"PPL",
    "gn:name":"Saraikela",
    "gn:population":0,
    "gn:timezone":"Asia/Kolkata",
    "iso:country":"IN",
    "name:bih_x_preferred":[
        "\u0938\u0930\u093e\u092f\u0915\u0947\u0932\u093e"
    ],
    "name:bpy_x_preferred":[
        "\u09b8\u09c7\u09b0\u09be\u0987\u0995\u09c7\u09b2\u09be"
    ],
    "name:cat_x_preferred":[
        "Saraikela"
    ],
    "name:ceb_x_preferred":[
        "Saraikela"
    ],
    "name:fra_x_preferred":[
        "Seraikela"
    ],
    "name:guj_x_preferred":[
        "\u0ab8\u0ab0\u0abe\u0a88\u0a95\u0ac7\u0ab2\u0abe \u0a96\u0ab0\u0ab8\u0abe\u0ab5\u0abe\u0a82"
    ],
    "name:hin_x_preferred":[
        "\u0938\u0930\u093e\u0907\u0915\u0947\u0932\u093e"
    ],
    "name:ita_x_preferred":[
        "Seraikela"
    ],
    "name:mar_x_preferred":[
        "\u0938\u0930\u093e\u0907\u0915\u0947\u0932\u093e"
    ],
    "name:msa_x_preferred":[
        "Seraikela"
    ],
    "name:san_x_preferred":[
        "\u0938\u0930\u093e\u0907\u0915\u0947\u0932\u093e"
    ],
    "name:spa_x_preferred":[
        "Saraikela"
    ],
    "name:swe_x_preferred":[
        "Seraikela"
    ],
    "name:urd_x_preferred":[
        "\u0633\u0631\u0627\u0626\u06d2 \u0642\u0644\u0639\u06c1"
    ],
    "name:vie_x_preferred":[
        "Seraikela"
    ],
    "name:zho_x_preferred":[
        "\u585e\u8d56\u51ef\u62c9"
    ],
    "wof:name":"Saraikela",
    "wof:placetype":"locality"
},
  "geometry": {"coordinates":[82.9734,21.10152],"type":"Point"}
}