{
  "type": "Feature",
  "properties": {
    "iso:country":"IN",
    "ks:ks_name":"Hadalpada",
    "ks:ks_pop":247,
    "ks:ks_type":"HABITATION",
    "name:eng_x_preferred":[
        "Hadalpada"
    ],
    "wof:name":"Hadalpada",
    "wof:placetype":"locality",
    "wof:population":247
},
  "geometry": {"coordinates":[72.78792300000001,20.013387],"type":"Point"}
}