{
  "type": "Feature",
  "properties": {
    "iso:country":"IN",
    "ks:ks_name":"Khervani",
    "ks:ks_pop":1073,
    "ks:ks_type":"HABITATION",
    "name:eng_x_preferred":[
        "Khervani"
    ],
    "wof:name":"Khervani",
    "wof:placetype":"locality",
    "wof:population":1073
},
  "geometry": {"coordinates":[74.50429800000001,22.024744],"type":"Point"}
}