{
  "type": "Feature",
  "properties": {
    "iso:country":"IN",
    "ks:ks_name":"Sitoia",
    "ks:ks_pop":0,
    "ks:ks_type":"VILLAGE",
    "name:eng_x_preferred":[
        "Sitoia"
    ],
    "wof:name":"Sitoia",
    "wof:placetype":"locality",
    "wof:population":0
},
  "geometry": {"coordinates":[85.793036,24.474738],"type":"Point"}
}