{
  "type": "Feature",
  "properties": {
    "iso:country":"IN",
    "ks:ks_name":"Marauti Tola",
    "ks:ks_pop":51,
    "ks:ks_type":"HABITATION",
    "ks:ks_uagg_main":0,
    "name:eng_x_preferred":[
        "Marauti Tola"
    ],
    "wof:name":"Marauti Tola",
    "wof:placetype":"neighbourhood",
    "wof:population":51
},
  "geometry": {"coordinates":[83.411389,27.015923],"type":"Point"}
}