{
  "type": "Feature",
  "properties": {
    "iso:country":"IN",
    "ks:ks_name":"Bhabhanauti",
    "ks:ks_pop":505,
    "ks:ks_type":"HABITATION",
    "name:eng_x_preferred":[
        "Bhabhanauti"
    ],
    "wof:name":"Bhabhanauti",
    "wof:placetype":"locality",
    "wof:population":505
},
  "geometry": {"coordinates":[82.529796,26.043525],"type":"Point"}
}