{
  "type": "Feature",
  "properties": {
    "iso:country":"IN",
    "ks:ks_alt_nam":"RAMCHANDRA CHOW PARA",
    "ks:ks_name":"Ramchandra Chow Para",
    "ks:ks_pop":45,
    "ks:ks_type":"HABITATION",
    "ks:ks_uagg_main":0,
    "name:eng_x_preferred":[
        "Ramchandra Chow Para"
    ],
    "wof:name":"Ramchandra Chow Para",
    "wof:placetype":"neighbourhood",
    "wof:population":45
},
  "geometry": {"coordinates":[91.5162,24.07406],"type":"Point"}
}