{
  "type": "Feature",
  "properties": {
    "iso:country":"IN",
    "ks:ks_name":"Maharajpur",
    "ks:ks_pop":3053,
    "ks:ks_type":"VILLAGE",
    "name:eng_x_preferred":[
        "Maharajpur"
    ],
    "wof:name":"Maharajpur",
    "wof:placetype":"locality",
    "wof:population":3053
},
  "geometry": {"coordinates":[87.667845,22.629865],"type":"Point"}
}