{
  "type": "Feature",
  "properties": {
    "iso:country":"IN",
    "ks:ks_name":"Samiyuranipatti",
    "ks:ks_pop":80,
    "ks:ks_type":"HABITATION",
    "name:eng_x_preferred":[
        "Samiyuranipatti"
    ],
    "wof:name":"Samiyuranipatti",
    "wof:placetype":"locality",
    "wof:population":80
},
  "geometry": {"coordinates":[78.667911,10.652203],"type":"Point"}
}