{
  "type": "Feature",
  "properties": {
    "gn:admin1_code":"40.0",
    "gn:admin2_code":"533",
    "gn:asciiname":"Konasamudram",
    "gn:country_code":"IN",
    "gn:dem":392,
    "gn:feature_class":"P",
    "gn:feature_code":"PPL",
    "gn:name":"Konasamudram",
    "gn:population":0,
    "gn:timezone":"Asia/Kolkata",
    "iso:country":"IN",
    "wof:name":"Konasamudram",
    "wof:placetype":"locality"
},
  "geometry": {"coordinates":[78.52308000000002,18.729],"type":"Point"}
}