{
  "type": "Feature",
  "properties": {
    "iso:country":"IN",
    "ks:ks_alt_nam":"Kolkkalam rd",
    "ks:ks_name":"Kolkkalam Rd",
    "ks:ks_pop":468,
    "ks:ks_type":"HABITATION",
    "ks:ks_uagg_main":0,
    "name:eng_x_preferred":[
        "Kolkkalam Rd"
    ],
    "wof:name":"Kolkkalam Rd",
    "wof:placetype":"neighbourhood",
    "wof:population":468
},
  "geometry": {"coordinates":[76.08307499999999,10.973629],"type":"Point"}
}