{
  "type": "Feature",
  "properties": {
    "iso:country":"IN",
    "ks:ks_name":"Champailo",
    "ks:ks_pop":758,
    "ks:ks_type":"VILLAGE",
    "name:eng_x_preferred":[
        "Champailo"
    ],
    "wof:name":"Champailo",
    "wof:placetype":"locality",
    "wof:population":758
},
  "geometry": {"coordinates":[85.364806,20.186797],"type":"Point"}
}