{
  "type": "Feature",
  "properties": {
    "iso:country":"IN",
    "ks:ks_name":"Lakhapali",
    "ks:ks_pop":31,
    "ks:ks_type":"HABITATION",
    "name:eng_x_preferred":[
        "Lakhapali"
    ],
    "wof:name":"Lakhapali",
    "wof:placetype":"locality",
    "wof:population":31
},
  "geometry": {"coordinates":[84.99523499999999,21.636847],"type":"Point"}
}