{
  "type": "Feature",
  "properties": {
    "iso:country":"IN",
    "ks:ks_name":"Shankarpur",
    "ks:ks_pop":489,
    "ks:ks_type":"HABITATION",
    "ks:ks_uagg_main":0,
    "name:eng_x_preferred":[
        "Shankarpur"
    ],
    "wof:name":"Shankarpur",
    "wof:placetype":"neighbourhood",
    "wof:population":489
},
  "geometry": {"coordinates":[86.232755,25.686021],"type":"Point"}
}