{
  "type": "Feature",
  "properties": {
    "gn:admin1_code":"36.0",
    "gn:admin2_code":"183.0",
    "gn:asciiname":"Kahla Tindwa",
    "gn:country_code":"IN",
    "gn:dem":115,
    "gn:feature_class":"P",
    "gn:feature_code":"PPL",
    "gn:name":"Kahla Tindwa",
    "gn:population":0,
    "gn:timezone":"Asia/Kolkata",
    "iso:country":"IN",
    "ks:ks_name":"Kahla Tendua",
    "ks:ks_pop":657,
    "ks:ks_type":"VILLAGE",
    "ks:ks_uagg_main":0,
    "name:eng_x_preferred":[
        "Kahla Tendua"
    ],
    "wof:name":"Kahla Tendua",
    "wof:placetype":"neighbourhood",
    "wof:population":657
},
  "geometry": {"coordinates":[81.943609,27.414216],"type":"Point"}
}