{
  "type": "Feature",
  "properties": {
    "iso:country":"IN",
    "ks:ks_name":"Potkadih",
    "ks:ks_pop":595,
    "ks:ks_type":"HABITATION",
    "name:eng_x_preferred":[
        "Potkadih"
    ],
    "wof:name":"Potkadih",
    "wof:placetype":"locality",
    "wof:population":595
},
  "geometry": {"coordinates":[86.286924,22.984459],"type":"Point"}
}