{
  "type": "Feature",
  "properties": {
    "iso:country":"IN",
    "ks:ks_name":"Bommenahalli Koppalu",
    "ks:ks_pop":133,
    "ks:ks_type":"HABITATION",
    "name:eng_x_preferred":[
        "Bommenahalli Koppalu"
    ],
    "wof:name":"Bommenahalli Koppalu",
    "wof:placetype":"locality",
    "wof:population":133
},
  "geometry": {"coordinates":[75.83477000000001,13.190455],"type":"Point"}
}