{
  "type": "Feature",
  "properties": {
    "iso:country":"IN",
    "ks:ks_name":"Bhojuka Purwa (m)",
    "ks:ks_pop":296,
    "ks:ks_type":"HABITATION",
    "name:eng_x_preferred":[
        "Bhojuka Purwa (m)"
    ],
    "wof:name":"Bhojuka Purwa (m)",
    "wof:placetype":"locality",
    "wof:population":296
},
  "geometry": {"coordinates":[82.87966400000001,26.567787],"type":"Point"}
}