{
  "type": "Feature",
  "properties": {
    "iso:country":"IN",
    "ks:ks_alt_nam":"6 KRW DHANI KHINCHRAN",
    "ks:ks_name":"6 Krw Dhani Khinchran",
    "ks:ks_pop":562,
    "ks:ks_type":"HABITATION",
    "name:eng_x_preferred":[
        "6 Krw Dhani Khinchran"
    ],
    "wof:name":"6 Krw Dhani Khinchran",
    "wof:placetype":"locality",
    "wof:population":562
},
  "geometry": {"coordinates":[74.231842,29.891407],"type":"Point"}
}