{
  "type": "Feature",
  "properties": {
    "iso:country":"IN",
    "ks:ks_name":"Gambharia Ichhapur",
    "ks:ks_pop":315,
    "ks:ks_type":"HABITATION",
    "name:eng_x_preferred":[
        "Gambharia Ichhapur"
    ],
    "wof:name":"Gambharia Ichhapur",
    "wof:placetype":"locality",
    "wof:population":315
},
  "geometry": {"coordinates":[85.917182,20.79151],"type":"Point"}
}