{
  "type": "Feature",
  "properties": {
    "iso:country":"IN",
    "ks:ks_name":"Baman Bhanada",
    "ks:ks_pop":387,
    "ks:ks_type":"HABITATION",
    "name:eng_x_preferred":[
        "Baman Bhanada"
    ],
    "wof:name":"Baman Bhanada",
    "wof:placetype":"locality",
    "wof:population":387
},
  "geometry": {"coordinates":[74.413117,24.074102],"type":"Point"}
}