{
  "type": "Feature",
  "properties": {
    "iso:country":"IN",
    "ks:ks_name":"Girdalpara",
    "ks:ks_pop":275,
    "ks:ks_type":"HABITATION",
    "name:eng_x_preferred":[
        "Girdalpara"
    ],
    "wof:name":"Girdalpara",
    "wof:placetype":"locality",
    "wof:population":275
},
  "geometry": {"coordinates":[81.577048,18.305214],"type":"Point"}
}