{
  "type": "Feature",
  "properties": {
    "iso:country":"IN",
    "ks:ks_name":"Kalaincherra Bagicha",
    "ks:ks_pop":190,
    "ks:ks_type":"HABITATION",
    "name:eng_x_preferred":[
        "Kalaincherra Bagicha"
    ],
    "wof:name":"Kalaincherra Bagicha",
    "wof:placetype":"locality",
    "wof:population":190
},
  "geometry": {"coordinates":[92.51771100000001,25.014216],"type":"Point"}
}