{
  "type": "Feature",
  "properties": {
    "iso:country":"IN",
    "ks:ks_alt_nam":"murtiya",
    "ks:ks_name":"Murtiya",
    "ks:ks_pop":100,
    "ks:ks_type":"HABITATION",
    "name:eng_x_preferred":[
        "Murtiya"
    ],
    "wof:name":"Murtiya",
    "wof:placetype":"locality",
    "wof:population":100
},
  "geometry": {"coordinates":[85.510908,24.13396],"type":"Point"}
}