{
  "type": "Feature",
  "properties": {
    "iso:country":"IN",
    "ks:ks_name":"Bisatipura",
    "ks:ks_pop":431,
    "ks:ks_type":"VILLAGE",
    "ks:ks_uagg_main":0,
    "name:eng_x_preferred":[
        "Bisatipura"
    ],
    "wof:name":"Bisatipura",
    "wof:placetype":"neighbourhood",
    "wof:population":431
},
  "geometry": {"coordinates":[77.82625,26.752705],"type":"Point"}
}