{
  "type": "Feature",
  "properties": {
    "gn:admin1_code":"34.0",
    "gn:admin2_code":"229.0",
    "gn:asciiname":"Kamal Bigha",
    "gn:country_code":"IN",
    "gn:dem":71,
    "gn:feature_class":"P",
    "gn:feature_code":"PPL",
    "gn:name":"Kam\u0101l Bigha",
    "gn:population":0,
    "gn:timezone":"Asia/Kolkata",
    "iso:country":"IN",
    "ks:ks_alt_nam":"Kam\u0101l Bigha",
    "ks:ks_name":"Kamal Bigha",
    "ks:ks_pop":625,
    "ks:ks_type":"VILLAGE",
    "name:eng_x_preferred":[
        "Kamal Bigha"
    ],
    "name:eng_x_variant":[
        "Kam\u0101l Bigha"
    ],
    "wof:name":"Kamal Bigha",
    "wof:placetype":"locality",
    "wof:population":625
},
  "geometry": {"coordinates":[85.48065,25.05534],"type":"Point"}
}