{
  "type": "Feature",
  "properties": {
    "iso:country":"IN",
    "ks:ks_name":"Takiya",
    "ks:ks_pop":254,
    "ks:ks_type":"HABITATION",
    "ks:ks_uagg_main":0,
    "name:eng_x_preferred":[
        "Takiya"
    ],
    "wof:name":"Takiya",
    "wof:placetype":"neighbourhood",
    "wof:population":254
},
  "geometry": {"coordinates":[81.79431,26.337524],"type":"Point"}
}