{
  "type": "Feature",
  "properties": {
    "gn:admin1_code":"37",
    "gn:admin2_code":"407.0",
    "gn:asciiname":"Mungadih",
    "gn:country_code":"IN",
    "gn:dem":401,
    "gn:feature_class":"P",
    "gn:feature_code":"PPL",
    "gn:name":"Mung\u0101dih",
    "gn:population":0,
    "gn:timezone":"Asia/Kolkata",
    "iso:country":"IN",
    "wof:name":"Mungadih",
    "wof:placetype":"locality"
},
  "geometry": {"coordinates":[81.40978,22.34557],"type":"Point"}
}