{
  "type": "Feature",
  "properties": {
    "iso:country":"IN",
    "ks:ks_name":"Tiphuk Chah Bagisha",
    "ks:ks_pop":1389,
    "ks:ks_type":"VILLAGE",
    "name:eng_x_preferred":[
        "Tiphuk Chah Bagisha"
    ],
    "wof:name":"Tiphuk Chah Bagisha",
    "wof:placetype":"locality",
    "wof:population":1389
},
  "geometry": {"coordinates":[94.59489600000001,26.788525],"type":"Point"}
}