{
  "type": "Feature",
  "properties": {
    "gn:admin1_code":"24.0",
    "gn:admin2_code":"101.0",
    "gn:asciiname":"Surjansar",
    "gn:country_code":"IN",
    "gn:dem":242,
    "gn:feature_class":"P",
    "gn:feature_code":"PPL",
    "gn:name":"Surjansar",
    "gn:population":0,
    "gn:timezone":"Asia/Kolkata",
    "iso:country":"IN",
    "wof:name":"Surjansar",
    "wof:placetype":"locality"
},
  "geometry": {"coordinates":[74.16322,28.25967],"type":"Point"}
}