{
  "type": "Feature",
  "properties": {
    "iso:country":"IN",
    "ks:ks_name":"Anantpur",
    "ks:ks_pop":55,
    "ks:ks_type":"VILLAGE",
    "name:eng_x_preferred":[
        "Anantpur"
    ],
    "wof:name":"Anantpur",
    "wof:placetype":"locality",
    "wof:population":55
},
  "geometry": {"coordinates":[82.652474,25.759267],"type":"Point"}
}