{
  "type": "Feature",
  "properties": {
    "gn:admin1_code":"35",
    "gn:admin2_code":"466.0",
    "gn:asciiname":"Surgaonjoshi",
    "gn:country_code":"IN",
    "gn:dem":339,
    "gn:feature_class":"P",
    "gn:feature_code":"PPL",
    "gn:name":"Surgaonjoshi",
    "gn:population":0,
    "gn:timezone":"Asia/Kolkata",
    "iso:country":"IN",
    "wof:name":"Surgaonjoshi",
    "wof:placetype":"locality"
},
  "geometry": {"coordinates":[76.27367,21.83837],"type":"Point"}
}