{
  "type": "Feature",
  "properties": {
    "iso:country":"IN",
    "ks:ks_name":"Dhani Patoda",
    "ks:ks_pop":245,
    "ks:ks_type":"HABITATION",
    "name:eng_x_preferred":[
        "Dhani Patoda"
    ],
    "wof:name":"Dhani Patoda",
    "wof:placetype":"locality",
    "wof:population":245
},
  "geometry": {"coordinates":[75.11975,28.14325],"type":"Point"}
}