{
  "type": "Feature",
  "properties": {
    "iso:country":"IN",
    "ks:ks_name":"Heravanadu Pannya",
    "ks:ks_pop":18,
    "ks:ks_type":"HABITATION",
    "name:eng_x_preferred":[
        "Heravanadu Pannya"
    ],
    "wof:name":"Heravanadu Pannya",
    "wof:placetype":"locality",
    "wof:population":18
},
  "geometry": {"coordinates":[75.71638900000001,12.394444],"type":"Point"}
}