{
  "type": "Feature",
  "properties": {
    "iso:country":"IN",
    "ks:ks_name":"Timirpura",
    "ks:ks_pop":1092,
    "ks:ks_type":"HABITATION",
    "ks:ks_uagg_main":0,
    "name:eng_x_preferred":[
        "Timirpura"
    ],
    "wof:name":"Timirpura",
    "wof:placetype":"neighbourhood",
    "wof:population":1092
},
  "geometry": {"coordinates":[87.80147599999999,25.40195],"type":"Point"}
}