{
  "type": "Feature",
  "properties": {
    "iso:country":"IN",
    "ks:ks_name":"Loyade",
    "ks:ks_pop":171,
    "ks:ks_type":"HABITATION",
    "name:eng_x_preferred":[
        "Loyade"
    ],
    "wof:name":"Loyade",
    "wof:placetype":"locality",
    "wof:population":171
},
  "geometry": {"coordinates":[86.72665499999999,22.582538],"type":"Point"}
}