{
  "type": "Feature",
  "properties": {
    "iso:country":"IN",
    "ks:ks_name":"Gadakhol",
    "ks:ks_pop":66,
    "ks:ks_type":"VILLAGE",
    "name:eng_x_preferred":[
        "Gadakhol"
    ],
    "wof:name":"Gadakhol",
    "wof:placetype":"locality",
    "wof:population":66
},
  "geometry": {"coordinates":[84.25324500000001,21.03228],"type":"Point"}
}