{
  "type": "Feature",
  "properties": {
    "iso:country":"IN",
    "ks:ks_name":"Arembi",
    "ks:ks_pop":18,
    "ks:ks_type":"HABITATION",
    "name:eng_x_preferred":[
        "Arembi"
    ],
    "wof:name":"Arembi",
    "wof:placetype":"locality",
    "wof:population":18
},
  "geometry": {"coordinates":[75.422552,12.683003],"type":"Point"}
}