{
  "type": "Feature",
  "properties": {
    "iso:country":"IN",
    "ks:ks_name":"Bhetuli",
    "ks:ks_pop":88,
    "ks:ks_type":"VILLAGE",
    "name:eng_x_preferred":[
        "Bhetuli"
    ],
    "wof:name":"Bhetuli",
    "wof:placetype":"locality",
    "wof:population":88
},
  "geometry": {"coordinates":[78.697999,30.003573],"type":"Point"}
}