{
  "type": "Feature",
  "properties": {
    "iso:country":"IN",
    "ks:ks_name":"Dhanghari",
    "ks:ks_pop":663,
    "ks:ks_type":"VILLAGE",
    "name:eng_x_preferred":[
        "Dhanghari"
    ],
    "wof:name":"Dhanghari",
    "wof:placetype":"locality",
    "wof:population":663
},
  "geometry": {"coordinates":[86.781243,22.353438],"type":"Point"}
}