{
  "type": "Feature",
  "properties": {
    "gn:admin1_code":"36.0",
    "gn:admin2_code":"173.0",
    "gn:asciiname":"Basupur",
    "gn:country_code":"IN",
    "gn:dem":104,
    "gn:feature_class":"P",
    "gn:feature_code":"PPL",
    "gn:name":"B\u0101s\u016bpur",
    "gn:population":0,
    "gn:timezone":"Asia/Kolkata",
    "iso:country":"IN",
    "ks:ks_alt_nam":"B\u0101s\u016bpur",
    "ks:ks_name":"Basupur",
    "ks:ks_pop":653,
    "ks:ks_type":"VILLAGE",
    "ks:ks_uagg_main":0,
    "name:eng_x_preferred":[
        "Basupur"
    ],
    "name:eng_x_variant":[
        "B\u0101s\u016bpur"
    ],
    "wof:name":"Basupur",
    "wof:placetype":"neighbourhood",
    "wof:population":653
},
  "geometry": {"coordinates":[81.875033,25.798638],"type":"Point"}
}