{
  "type": "Feature",
  "properties": {
    "iso:country":"IN",
    "ks:ks_name":"Takhubakharak Para",
    "ks:ks_pop":62,
    "ks:ks_type":"HABITATION",
    "name:eng_x_preferred":[
        "Takhubakharak Para"
    ],
    "wof:name":"Takhubakharak Para",
    "wof:placetype":"locality",
    "wof:population":62
},
  "geometry": {"coordinates":[91.499275,23.972681],"type":"Point"}
}