{
  "type": "Feature",
  "properties": {
    "gn:admin1_code":"36",
    "gn:admin2_code":"198.0",
    "gn:asciiname":"Rajaipur",
    "gn:country_code":"IN",
    "gn:dem":88,
    "gn:feature_class":"P",
    "gn:feature_code":"PPL",
    "gn:name":"Rajaipur",
    "gn:population":0,
    "gn:timezone":"Asia/Kolkata",
    "iso:country":"IN",
    "ks:ks_name":"Rajaipur",
    "ks:ks_pop":940,
    "ks:ks_type":"VILLAGE",
    "ks:ks_uagg_main":0,
    "name:eng_x_preferred":[
        "Rajaipur"
    ],
    "wof:name":"Rajaipur",
    "wof:placetype":"neighbourhood",
    "wof:population":940
},
  "geometry": {"coordinates":[82.65971500000001,25.306799],"type":"Point"}
}