{
  "type": "Feature",
  "properties": {
    "iso:country":"IN",
    "ks:ks_name":"Ratnarot Alias Bankata",
    "ks:ks_pop":94,
    "ks:ks_type":"HABITATION",
    "name:eng_x_preferred":[
        "Ratnarot Alias Bankata"
    ],
    "wof:name":"Ratnarot Alias Bankata",
    "wof:placetype":"locality",
    "wof:population":94
},
  "geometry": {"coordinates":[86.692063,23.105556],"type":"Point"}
}