{
  "type": "Feature",
  "properties": {
    "iso:country":"IN",
    "ks:ks_name":"Rokkaland",
    "ks:ks_pop":504,
    "ks:ks_type":"HABITATION",
    "name:eng_x_preferred":[
        "Rokkaland"
    ],
    "wof:name":"Rokkaland",
    "wof:placetype":"locality",
    "wof:population":504
},
  "geometry": {"coordinates":[76.248473,10.247318],"type":"Point"}
}