{
  "type": "Feature",
  "properties": {
    "iso:country":"IN",
    "ks:ks_name":"Govt Farm",
    "ks:ks_pop":165,
    "ks:ks_type":"HABITATION",
    "name:eng_x_preferred":[
        "Govt Farm"
    ],
    "wof:name":"Govt Farm",
    "wof:placetype":"locality",
    "wof:population":165
},
  "geometry": {"coordinates":[79.607923,12.836947],"type":"Point"}
}