{
  "type": "Feature",
  "properties": {
    "gn:admin1_code":"36",
    "gn:admin2_code":"180.0",
    "gn:asciiname":"Pura Ramtaria Bhawanidin",
    "gn:country_code":"IN",
    "gn:dem":114,
    "gn:feature_class":"P",
    "gn:feature_code":"PPL",
    "gn:name":"Pura R\u0101mtaria Bhaw\u0101n\u012bd\u012bn",
    "gn:population":0,
    "gn:timezone":"Asia/Kolkata",
    "iso:country":"IN",
    "wof:name":"Pura Ramtaria Bhawanidin",
    "wof:placetype":"locality"
},
  "geometry": {"coordinates":[81.58298000000001,27.37016],"type":"Point"}
}