{
  "type": "Feature",
  "properties": {
    "iso:country":"IN",
    "ks:ks_name":"Himmatpuri",
    "ks:ks_pop":123,
    "ks:ks_type":"HABITATION",
    "name:eng_x_preferred":[
        "Himmatpuri"
    ],
    "wof:name":"Himmatpuri",
    "wof:placetype":"locality",
    "wof:population":123
},
  "geometry": {"coordinates":[74.55364400000001,23.440344],"type":"Point"}
}