{
  "type": "Feature",
  "properties": {
    "iso:country":"IN",
    "ks:ks_name":"Purba Jarayotar Barbotay",
    "ks:ks_pop":669,
    "ks:ks_type":"HABITATION",
    "name:eng_x_preferred":[
        "Purba Jarayotar Barbotay"
    ],
    "wof:name":"Purba Jarayotar Barbotay",
    "wof:placetype":"locality",
    "wof:population":669
},
  "geometry": {"coordinates":[88.48145700000001,26.923613],"type":"Point"}
}