{
  "type": "Feature",
  "properties": {
    "iso:country":"IN",
    "ks:ks_name":"Mathura Tea Garden",
    "ks:ks_pop":8472,
    "ks:ks_type":"VILLAGE",
    "name:eng_x_preferred":[
        "Mathura Tea Garden"
    ],
    "wof:name":"Mathura Tea Garden",
    "wof:placetype":"locality",
    "wof:population":8472
},
  "geometry": {"coordinates":[89.397943,26.516064],"type":"Point"}
}