{
  "type": "Feature",
  "properties": {
    "iso:country":"IN",
    "ks:ks_name":"Nagampara",
    "ks:ks_pop":283,
    "ks:ks_type":"HABITATION",
    "name:eng_x_preferred":[
        "Nagampara"
    ],
    "wof:name":"Nagampara",
    "wof:placetype":"locality",
    "wof:population":283
},
  "geometry": {"coordinates":[75.805375,11.69006],"type":"Point"}
}