{
  "type": "Feature",
  "properties": {
    "gn:admin1_code":"40.0",
    "gn:admin2_code":"539",
    "gn:asciiname":"Jamilapet",
    "gn:country_code":"IN",
    "gn:dem":494,
    "gn:feature_class":"P",
    "gn:feature_code":"PPL",
    "gn:name":"Jam\u012bl\u0101pet",
    "gn:population":0,
    "gn:timezone":"Asia/Kolkata",
    "iso:country":"IN",
    "name:und_x_variant":[
        "Jamilpet",
        "Jam\u012bl\u0101pet"
    ],
    "wof:name":"Jamilapet",
    "wof:placetype":"locality"
},
  "geometry": {"coordinates":[78.72579,17.49407],"type":"Point"}
}