{
  "type": "Feature",
  "properties": {
    "gn:admin1_code":"40.0",
    "gn:admin2_code":"541",
    "gn:asciiname":"Bommakal",
    "gn:country_code":"IN",
    "gn:dem":90,
    "gn:feature_class":"P",
    "gn:feature_code":"PPL",
    "gn:name":"Bommakal",
    "gn:population":0,
    "gn:timezone":"Asia/Kolkata",
    "iso:country":"IN",
    "name:und_x_variant":[
        "Bonakalu",
        "Bommakal"
    ],
    "wof:name":"Bommakal",
    "wof:placetype":"locality"
},
  "geometry": {"coordinates":[80.26869000000001,17.01972],"type":"Point"}
}