{
  "type": "Feature",
  "properties": {
    "iso:country":"IN",
    "ks:ks_name":"Shiv Charan Ka Pura",
    "ks:ks_pop":550,
    "ks:ks_type":"HABITATION",
    "name:eng_x_preferred":[
        "Shiv Charan Ka Pura"
    ],
    "wof:name":"Shiv Charan Ka Pura",
    "wof:placetype":"locality",
    "wof:population":550
},
  "geometry": {"coordinates":[81.37154,25.478925],"type":"Point"}
}