{
  "type": "Feature",
  "properties": {
    "iso:country":"IN",
    "ks:ks_name":"Kistapur",
    "ks:ks_pop":228,
    "ks:ks_type":"VILLAGE",
    "name:eng_x_preferred":[
        "Kistapur"
    ],
    "wof:name":"Kistapur",
    "wof:placetype":"locality",
    "wof:population":228
},
  "geometry": {"coordinates":[78.140299,16.296355],"type":"Point"}
}