{
  "type": "Feature",
  "properties": {
    "gn:admin1_code":"36.0",
    "gn:admin2_code":"173.0",
    "gn:asciiname":"Bhikhampur",
    "gn:country_code":"IN",
    "gn:dem":103,
    "gn:feature_class":"P",
    "gn:feature_code":"PPL",
    "gn:name":"Bh\u012bkhampur",
    "gn:population":0,
    "gn:timezone":"Asia/Kolkata",
    "iso:country":"IN",
    "ks:ks_alt_nam":"Bh\u012bkhampur",
    "ks:ks_name":"Bhikhampur",
    "ks:ks_pop":483,
    "ks:ks_type":"VILLAGE",
    "ks:ks_uagg_main":0,
    "name:eng_x_preferred":[
        "Bhikhampur"
    ],
    "name:eng_x_variant":[
        "Bh\u012bkhampur"
    ],
    "wof:name":"Bhikhampur",
    "wof:placetype":"neighbourhood",
    "wof:population":483
},
  "geometry": {"coordinates":[81.805038,25.816371],"type":"Point"}
}