{
  "type": "Feature",
  "properties": {
    "iso:country":"IN",
    "ks:ks_name":"Tilwari",
    "ks:ks_pop":234,
    "ks:ks_type":"VILLAGE",
    "name:eng_x_preferred":[
        "Tilwari"
    ],
    "wof:name":"Tilwari",
    "wof:placetype":"locality",
    "wof:population":234
},
  "geometry": {"coordinates":[76.385693,27.21526],"type":"Point"}
}