{
  "type": "Feature",
  "properties": {
    "iso:country":"IN",
    "ks:ks_name":"Jhikilata",
    "ks:ks_pop":424,
    "ks:ks_type":"HABITATION",
    "name:eng_x_preferred":[
        "Jhikilata"
    ],
    "wof:name":"Jhikilata",
    "wof:placetype":"locality",
    "wof:population":424
},
  "geometry": {"coordinates":[85.660455,22.313766],"type":"Point"}
}