{
  "type": "Feature",
  "properties": {
    "iso:country":"IN",
    "ks:ks_name":"Laupara",
    "ks:ks_pop":147,
    "ks:ks_type":"VILLAGE",
    "name:eng_x_preferred":[
        "Laupara"
    ],
    "wof:name":"Laupara",
    "wof:placetype":"locality",
    "wof:population":147
},
  "geometry": {"coordinates":[86.95881799999999,22.724215],"type":"Point"}
}