{
  "type": "Feature",
  "properties": {
    "iso:country":"IN",
    "ks:ks_name":"Badagigadde",
    "ks:ks_pop":83,
    "ks:ks_type":"HABITATION",
    "name:eng_x_preferred":[
        "Badagigadde"
    ],
    "wof:name":"Badagigadde",
    "wof:placetype":"locality",
    "wof:population":83
},
  "geometry": {"coordinates":[74.692932,14.518],"type":"Point"}
}