{
  "type": "Feature",
  "properties": {
    "iso:country":"IN",
    "ks:ks_name":"Kajribhitha",
    "ks:ks_pop":91,
    "ks:ks_type":"HABITATION",
    "name:eng_x_preferred":[
        "Kajribhitha"
    ],
    "wof:name":"Kajribhitha",
    "wof:placetype":"locality",
    "wof:population":91
},
  "geometry": {"coordinates":[87.41886599999999,24.993877],"type":"Point"}
}