{
  "type": "Feature",
  "properties": {
    "gn:admin1_code":"35.0",
    "gn:admin2_code":"452.0",
    "gn:asciiname":"Pachama",
    "gn:country_code":"IN",
    "gn:dem":356,
    "gn:feature_class":"P",
    "gn:feature_code":"PPL",
    "gn:name":"Pach\u0101ma",
    "gn:population":0,
    "gn:timezone":"Asia/Kolkata",
    "iso:country":"IN",
    "name:spa_x_preferred":[
        "Pachama"
    ],
    "wof:name":"Pachama",
    "wof:placetype":"locality"
},
  "geometry": {"coordinates":[78.71160999999999,22.84542],"type":"Point"}
}