{
  "type": "Feature",
  "properties": {
    "iso:country":"IN",
    "ks:ks_name":"Marthala",
    "ks:ks_pop":5,
    "ks:ks_type":"HABITATION",
    "name:eng_x_preferred":[
        "Marthala"
    ],
    "wof:name":"Marthala",
    "wof:placetype":"locality",
    "wof:population":5
},
  "geometry": {"coordinates":[75.749743,29.780725],"type":"Point"}
}