{
  "type": "Feature",
  "properties": {
    "iso:country":"IN",
    "ks:ks_alt_nam":"Paikandara III",
    "ks:ks_name":"Paikandara Iii",
    "ks:ks_pop":49,
    "ks:ks_type":"HABITATION",
    "name:eng_x_preferred":[
        "Paikandara Iii"
    ],
    "wof:name":"Paikandara Iii",
    "wof:placetype":"locality",
    "wof:population":49
},
  "geometry": {"coordinates":[90.03605399999999,26.185087],"type":"Point"}
}