{
  "type": "Feature",
  "properties": {
    "iso:country":"IN",
    "ks:ks_name":"Uttar Kambuk Charra",
    "ks:ks_pop":126,
    "ks:ks_type":"HABITATION",
    "name:eng_x_preferred":[
        "Uttar Kambuk Charra"
    ],
    "wof:name":"Uttar Kambuk Charra",
    "wof:placetype":"locality",
    "wof:population":126
},
  "geometry": {"coordinates":[91.456686,23.997656],"type":"Point"}
}