{
  "type": "Feature",
  "properties": {
    "gn:admin1_code":"21.0",
    "gn:admin2_code":"396.0",
    "gn:asciiname":"Kindiripadar",
    "gn:country_code":"IN",
    "gn:dem":830,
    "gn:feature_class":"P",
    "gn:feature_code":"PPL",
    "gn:name":"Kindiripadar",
    "gn:population":0,
    "gn:timezone":"Asia/Kolkata",
    "iso:country":"IN",
    "wof:name":"Kindiripadar",
    "wof:placetype":"locality"
},
  "geometry": {"coordinates":[83.11033,19.11411],"type":"Point"}
}