{
  "type": "Feature",
  "properties": {
    "gn:admin1_code":"23.0",
    "gn:admin2_code":"35.0",
    "gn:asciiname":"Gobindsar",
    "gn:country_code":"IN",
    "gn:dem":283,
    "gn:feature_class":"P",
    "gn:feature_code":"PPL",
    "gn:name":"Gobinds\u0101r",
    "gn:population":0,
    "gn:timezone":"Asia/Kolkata",
    "iso:country":"IN",
    "name:fas_x_preferred":[
        "\u06af\u0648\u0628\u0646\u062f\u0633\u0631"
    ],
    "name:urd_x_preferred":[
        "\u06af\u0648\u0628\u0646\u062f\u0633\u0631"
    ],
    "wof:name":"Gobindsar",
    "wof:placetype":"locality"
},
  "geometry": {"coordinates":[75.5412,32.24256],"type":"Point"}
}