{
  "type": "Feature",
  "properties": {
    "gn:admin1_code":"36",
    "gn:admin2_code":"188.0",
    "gn:asciiname":"Bhopa",
    "gn:country_code":"IN",
    "gn:dem":82,
    "gn:feature_class":"P",
    "gn:feature_code":"PPL",
    "gn:name":"Bhopa",
    "gn:population":0,
    "gn:timezone":"Asia/Kolkata",
    "iso:country":"IN",
    "name:hin_x_preferred":[
        "\u092d\u094b\u092a\u093e"
    ],
    "wof:name":"Bhopa",
    "wof:placetype":"locality"
},
  "geometry": {"coordinates":[83.58308000000002,26.64601],"type":"Point"}
}