{
  "type": "Feature",
  "properties": {
    "iso:country":"IN",
    "ks:ks_alt_nam":"G.H.Koppalu",
    "ks:ks_name":"G.h.koppalu",
    "ks:ks_pop":60,
    "ks:ks_type":"HABITATION",
    "name:eng_x_preferred":[
        "G.h.koppalu"
    ],
    "wof:name":"G.h.koppalu",
    "wof:placetype":"locality",
    "wof:population":60
},
  "geometry": {"coordinates":[76.68667499999999,12.760762],"type":"Point"}
}