{
  "type": "Feature",
  "properties": {
    "iso:country":"IN",
    "ks:ks_name":"Thenkudi",
    "ks:ks_pop":130,
    "ks:ks_type":"HABITATION",
    "name:eng_x_preferred":[
        "Thenkudi"
    ],
    "wof:name":"Thenkudi",
    "wof:placetype":"locality",
    "wof:population":130
},
  "geometry": {"coordinates":[78.96236,10.055467],"type":"Point"}
}