{
  "type": "Feature",
  "properties": {
    "gn:admin1_code":"38.0",
    "gn:admin2_code":"347.0",
    "gn:asciiname":"Karmahi",
    "gn:country_code":"IN",
    "gn:dem":247,
    "gn:feature_class":"P",
    "gn:feature_code":"PPL",
    "gn:name":"Karm\u0101hi",
    "gn:population":0,
    "gn:timezone":"Asia/Kolkata",
    "iso:country":"IN",
    "ks:ks_alt_nam":"Karm\u0101hi",
    "ks:ks_name":"Karmahi",
    "ks:ks_pop":21,
    "ks:ks_type":"VILLAGE",
    "name:eng_x_preferred":[
        "Karmahi"
    ],
    "name:eng_x_variant":[
        "Karm\u0101hi"
    ],
    "wof:name":"Karmahi",
    "wof:placetype":"locality",
    "wof:population":21
},
  "geometry": {"coordinates":[84.66307500000001,24.339764],"type":"Point"}
}