{
  "type": "Feature",
  "properties": {
    "iso:country":"IN",
    "ks:ks_name":"Kheramamawas",
    "ks:ks_pop":1098,
    "ks:ks_type":"HABITATION",
    "name:eng_x_preferred":[
        "Kheramamawas"
    ],
    "wof:name":"Kheramamawas",
    "wof:placetype":"locality",
    "wof:population":1098
},
  "geometry": {"coordinates":[74.11539999999999,26.172567],"type":"Point"}
}