{
  "type": "Feature",
  "properties": {
    "iso:country":"IN",
    "ks:ks_name":"Mira Sarai Choti",
    "ks:ks_pop":1075,
    "ks:ks_type":"HABITATION",
    "name:eng_x_preferred":[
        "Mira Sarai Choti"
    ],
    "wof:name":"Mira Sarai Choti",
    "wof:placetype":"locality",
    "wof:population":1075
},
  "geometry": {"coordinates":[78.49079399999999,28.875156],"type":"Point"}
}