{
  "type": "Feature",
  "properties": {
    "iso:country":"IN",
    "ks:ks_name":"Puvalur",
    "ks:ks_pop":384,
    "ks:ks_type":"VILLAGE",
    "name:eng_x_preferred":[
        "Puvalur"
    ],
    "wof:name":"Puvalur",
    "wof:placetype":"locality",
    "wof:population":384
},
  "geometry": {"coordinates":[79.098213,10.055129],"type":"Point"}
}