{
  "type": "Feature",
  "properties": {
    "iso:country":"IN",
    "ks:ks_name":"Sevak Dayalpurwa",
    "ks:ks_pop":191,
    "ks:ks_type":"HABITATION",
    "name:eng_x_preferred":[
        "Sevak Dayalpurwa"
    ],
    "wof:name":"Sevak Dayalpurwa",
    "wof:placetype":"locality",
    "wof:population":191
},
  "geometry": {"coordinates":[80.757007,27.725279],"type":"Point"}
}