{
  "type": "Feature",
  "properties": {
    "iso:country":"IN",
    "ks:ks_name":"Kati Tola",
    "ks:ks_pop":163,
    "ks:ks_type":"HABITATION",
    "name:eng_x_preferred":[
        "Kati Tola"
    ],
    "wof:name":"Kati Tola",
    "wof:placetype":"locality",
    "wof:population":163
},
  "geometry": {"coordinates":[83.410614,27.253152],"type":"Point"}
}