{
  "type": "Feature",
  "properties": {
    "iso:country":"IN",
    "ks:ks_name":"Sawantwadi",
    "ks:ks_pop":308,
    "ks:ks_type":"HABITATION",
    "name:eng_x_preferred":[
        "Sawantwadi"
    ],
    "wof:name":"Sawantwadi",
    "wof:placetype":"locality",
    "wof:population":308
},
  "geometry": {"coordinates":[73.433937,16.246635],"type":"Point"}
}