{
  "type": "Feature",
  "properties": {
    "iso:country":"IN",
    "ks:ks_name":"Sultanabad",
    "ks:ks_pop":237,
    "ks:ks_type":"VILLAGE",
    "name:eng_x_preferred":[
        "Sultanabad"
    ],
    "wof:name":"Sultanabad",
    "wof:placetype":"locality",
    "wof:population":237
},
  "geometry": {"coordinates":[75.26173300000001,20.123635],"type":"Point"}
}