{
  "type": "Feature",
  "properties": {
    "gn:admin1_code":"10",
    "gn:admin2_code":"80.0",
    "gn:asciiname":"Sandlana",
    "gn:country_code":"IN",
    "gn:dem":225,
    "gn:feature_class":"P",
    "gn:feature_code":"PPL",
    "gn:name":"Sandl\u0101na",
    "gn:population":0,
    "gn:timezone":"Asia/Kolkata",
    "iso:country":"IN",
    "wof:name":"Sandlana",
    "wof:placetype":"locality"
},
  "geometry": {"coordinates":[76.07273000000001,29.41773],"type":"Point"}
}