{
  "type": "Feature",
  "properties": {
    "iso:country":"IN",
    "ks:ks_name":"Sildubi Grant",
    "ks:ks_pop":15607,
    "ks:ks_type":"VILLAGE",
    "name:eng_x_preferred":[
        "Sildubi Grant"
    ],
    "wof:name":"Sildubi Grant",
    "wof:placetype":"locality",
    "wof:population":15607
},
  "geometry": {"coordinates":[92.78733099999999,24.702123],"type":"Point"}
}