{
  "type": "Feature",
  "properties": {
    "iso:country":"IN",
    "ks:ks_name":"Permapal",
    "ks:ks_pop":521,
    "ks:ks_type":"VILLAGE",
    "name:eng_x_preferred":[
        "Permapal"
    ],
    "wof:name":"Permapal",
    "wof:placetype":"locality",
    "wof:population":521
},
  "geometry": {"coordinates":[81.423986,19.488586],"type":"Point"}
}