{
  "type": "Feature",
  "properties": {
    "iso:country":"IN",
    "ks:ks_alt_nam":"Karnel Singh ki Dhani",
    "ks:ks_name":"Karnel Singh Ki Dhani",
    "ks:ks_pop":30,
    "ks:ks_type":"HABITATION",
    "name:eng_x_preferred":[
        "Karnel Singh Ki Dhani"
    ],
    "wof:name":"Karnel Singh Ki Dhani",
    "wof:placetype":"locality",
    "wof:population":30
},
  "geometry": {"coordinates":[74.510789,29.930054],"type":"Point"}
}