{
  "type": "Feature",
  "properties": {
    "iso:country":"IN",
    "ks:ks_alt_nam":"Sadrau (Pohar)",
    "ks:ks_name":"Sadrau (pohar)",
    "ks:ks_pop":774,
    "ks:ks_type":"HABITATION",
    "name:eng_x_preferred":[
        "Sadrau (pohar)"
    ],
    "wof:name":"Sadrau (pohar)",
    "wof:placetype":"locality",
    "wof:population":774
},
  "geometry": {"coordinates":[71.073547,27.375531],"type":"Point"}
}