{
  "type": "Feature",
  "properties": {
    "gn:admin1_code":"37",
    "gn:admin2_code":"409.0",
    "gn:asciiname":"Dongritola",
    "gn:country_code":"IN",
    "gn:dem":402,
    "gn:feature_class":"P",
    "gn:feature_code":"PPL",
    "gn:name":"Dongr\u012btola",
    "gn:population":0,
    "gn:timezone":"Asia/Kolkata",
    "iso:country":"IN",
    "wof:name":"Dongritola",
    "wof:placetype":"locality"
},
  "geometry": {"coordinates":[81.09968000000001,20.63704],"type":"Point"}
}