{
  "type": "Feature",
  "properties": {
    "gn:admin1_code":"9.0",
    "gn:admin2_code":"487.0",
    "gn:asciiname":"Vavdi",
    "gn:country_code":"IN",
    "gn:dem":62,
    "gn:feature_class":"P",
    "gn:feature_code":"PPL",
    "gn:name":"V\u0101vdi",
    "gn:population":0,
    "gn:timezone":"Asia/Kolkata",
    "iso:country":"IN",
    "wof:name":"Vavdi",
    "wof:placetype":"locality"
},
  "geometry": {"coordinates":[73.55747,21.85179],"type":"Point"}
}