{
  "type": "Feature",
  "properties": {
    "gn:admin1_code":"9.0",
    "gn:admin2_code":"487.0",
    "gn:asciiname":"Vavdi",
    "gn:country_code":"IN",
    "gn:dem":62,
    "gn:feature_class":"P",
    "gn:feature_code":"PPL",
    "gn:name":"V\u0101vdi",
    "gn:population":0,
    "gn:timezone":"Asia/Kolkata",
    "iso:country":"IN",
    "ks:ks_alt_nam":"V\u0101vdi",
    "ks:ks_name":"Vavdi",
    "ks:ks_pop":2443,
    "ks:ks_type":"VILLAGE",
    "name:eng_x_preferred":[
        "Vavdi"
    ],
    "name:eng_x_variant":[
        "V\u0101vdi"
    ],
    "wof:name":"Vavdi",
    "wof:placetype":"locality",
    "wof:population":2443
},
  "geometry": {"coordinates":[73.557473,21.851789],"type":"Point"}
}