{
  "type": "Feature",
  "properties": {
    "gn:admin1_code":"11",
    "gn:admin2_code":"24.0",
    "gn:asciiname":"Manjbar",
    "gn:country_code":"IN",
    "gn:dem":719,
    "gn:feature_class":"P",
    "gn:feature_code":"PPL",
    "gn:name":"Manjb\u0101r",
    "gn:population":0,
    "gn:timezone":"Asia/Kolkata",
    "iso:country":"IN",
    "wof:name":"Manjbar",
    "wof:placetype":"locality"
},
  "geometry": {"coordinates":[76.18783000000001,32.19967],"type":"Point"}
}