{
  "type": "Feature",
  "properties": {
    "iso:country":"IN",
    "qs:name":"Karol",
    "qs:name_adm0":"India",
    "qs:name_adm1":"Himachal Pradesh",
    "qs:photos":117,
    "qs:photos_1k":24,
    "qs:photos_9k":1,
    "qs:photos_9r":3,
    "qs:photos_all":117,
    "qs:photos_sr":3,
    "qs:placetype":"Suburb",
    "qs:pop_sr":"0",
    "wd:wordcount":329,
    "wof:name":"Karol",
    "wof:placetype":"neighbourhood"
},
  "geometry": {"coordinates":[76.302795,32.240464],"type":"Point"}
}