{
  "type": "Feature",
  "properties": {
    "iso:country":"IN",
    "ks:ks_alt_nam":"Vijayanagara B camp",
    "ks:ks_name":"Vijayanagara B Camp",
    "ks:ks_pop":366,
    "ks:ks_type":"HABITATION",
    "name:eng_x_preferred":[
        "Vijayanagara B Camp"
    ],
    "wof:name":"Vijayanagara B Camp",
    "wof:placetype":"locality",
    "wof:population":366
},
  "geometry": {"coordinates":[76.93303,15.314184],"type":"Point"}
}