{
  "type": "Feature",
  "properties": {
    "iso:country":"IN",
    "ks:ks_name":"Babhulanepada",
    "ks:ks_pop":178,
    "ks:ks_type":"HABITATION",
    "name:eng_x_preferred":[
        "Babhulanepada"
    ],
    "wof:name":"Babhulanepada",
    "wof:placetype":"locality",
    "wof:population":178
},
  "geometry": {"coordinates":[73.346667,20.069126],"type":"Point"}
}