{
  "type": "Feature",
  "properties": {
    "gn:admin1_code":"35",
    "gn:admin2_code":"436.0",
    "gn:asciiname":"Pura",
    "gn:country_code":"IN",
    "gn:dem":510,
    "gn:feature_class":"P",
    "gn:feature_code":"PPL",
    "gn:name":"Pura",
    "gn:population":0,
    "gn:timezone":"Asia/Kolkata",
    "iso:country":"IN",
    "name:ceb_x_preferred":[
        "Pura"
    ],
    "name:deu_x_preferred":[
        "Pura"
    ],
    "name:epo_x_preferred":[
        "Pura"
    ],
    "name:est_x_preferred":[
        "Pura"
    ],
    "name:eus_x_preferred":[
        "Pura"
    ],
    "name:fra_x_preferred":[
        "Pura"
    ],
    "name:ita_x_preferred":[
        "Pura"
    ],
    "name:nld_x_preferred":[
        "Pura"
    ],
    "name:por_x_preferred":[
        "Pura"
    ],
    "name:rus_x_preferred":[
        "\u041f\u0443\u0440\u0430"
    ],
    "name:spa_x_preferred":[
        "Pura"
    ],
    "name:swe_x_preferred":[
        "Pura"
    ],
    "name:ukr_x_preferred":[
        "\u041f\u0443\u0440\u0430"
    ],
    "name:und_x_variant":[
        "S\u0101hubh\u0101gar"
    ],
    "name:war_x_preferred":[
        "Pura"
    ],
    "wof:name":"Pura",
    "wof:placetype":"neighbourhood"
},
  "geometry": {"coordinates":[76.01967999999999,23.67939],"type":"Point"}
}