{
  "type": "Feature",
  "properties": {
    "gn:admin1_code":"37.0",
    "gn:admin2_code":"417.0",
    "gn:asciiname":"Bhadrakali",
    "gn:country_code":"IN",
    "gn:dem":120,
    "gn:feature_class":"P",
    "gn:feature_code":"PPL",
    "gn:name":"Bhadrak\u0101li",
    "gn:population":0,
    "gn:timezone":"Asia/Kolkata",
    "iso:country":"IN",
    "name:ben_x_preferred":[
        "\u09ad\u09a6\u09cd\u09b0\u0995\u09be\u09b2\u09c0"
    ],
    "name:gom_x_preferred":[
        "Bhadrakali"
    ],
    "name:hin_x_preferred":[
        "\u092d\u0926\u094d\u0930\u0915\u093e\u0932\u0940"
    ],
    "name:new_x_preferred":[
        "\u092d\u0926\u094d\u0930\u0915\u093e\u0932\u0940"
    ],
    "name:ori_x_preferred":[
        "\u0b2d\u0b26\u0b4d\u0b30\u0b15\u0b3e\u0b33\u0b40"
    ],
    "name:pan_x_preferred":[
        "\u0a2d\u0a26\u0a4d\u0a30\u0a15\u0a3e\u0a32\u0a40"
    ],
    "name:pol_x_preferred":[
        "Bhadrakali"
    ],
    "name:sin_x_preferred":[
        "\u0db7\u0daf\u0dca\u200d\u0dbb\u0d9a\u0dcf\u0dbd\u0dd3"
    ],
    "wof:name":"Bhadrakali",
    "wof:placetype":"locality"
},
  "geometry": {"coordinates":[80.29895999999999,18.72238],"type":"Point"}
}