{
  "type": "Feature",
  "properties": {
    "gn:admin1_code":"34.0",
    "gn:admin2_code":"231.0",
    "gn:asciiname":"Baruna",
    "gn:country_code":"IN",
    "gn:dem":75,
    "gn:feature_class":"P",
    "gn:feature_code":"PPL",
    "gn:name":"Baruna",
    "gn:population":0,
    "gn:timezone":"Asia/Kolkata",
    "iso:country":"IN",
    "ks:ks_name":"Baruna",
    "ks:ks_pop":2623,
    "ks:ks_type":"VILLAGE",
    "name:eng_x_preferred":[
        "Baruna"
    ],
    "wof:name":"Baruna",
    "wof:placetype":"locality",
    "wof:population":2623
},
  "geometry": {"coordinates":[84.608266,25.311525],"type":"Point"}
}