{
  "type": "Feature",
  "properties": {
    "iso:country":"IN",
    "ks:ks_name":"Puthiyambalalam",
    "ks:ks_pop":1567,
    "ks:ks_type":"HABITATION",
    "name:eng_x_preferred":[
        "Puthiyambalalam"
    ],
    "wof:name":"Puthiyambalalam",
    "wof:placetype":"locality",
    "wof:population":1567
},
  "geometry": {"coordinates":[75.255954,12.562714],"type":"Point"}
}