{
  "type": "Feature",
  "properties": {
    "gn:admin1_code":"36.0",
    "gn:asciiname":"Mandawali Gujar",
    "gn:country_code":"IN",
    "gn:dem":277,
    "gn:feature_class":"P",
    "gn:feature_code":"PPL",
    "gn:name":"Mand\u0101w\u0101li Gujar",
    "gn:population":0,
    "gn:timezone":"Asia/Kolkata",
    "iso:country":"IN",
    "wof:name":"Mandawali Gujar",
    "wof:placetype":"locality"
},
  "geometry": {"coordinates":[77.41901,30.15012],"type":"Point"}
}