{
  "type": "Feature",
  "properties": {
    "iso:country":"IN",
    "ks:ks_name":"Veerampalem",
    "ks:ks_pop":900,
    "ks:ks_type":"HABITATION",
    "name:eng_x_preferred":[
        "Veerampalem"
    ],
    "wof:name":"Veerampalem",
    "wof:placetype":"locality",
    "wof:population":900
},
  "geometry": {"coordinates":[82.01983300000001,17.615384],"type":"Point"}
}