{
  "type": "Feature",
  "properties": {
    "iso:country":"IN",
    "ks:ks_name":"Chigilipallipeta",
    "ks:ks_pop":10,
    "ks:ks_type":"HABITATION",
    "name:eng_x_preferred":[
        "Chigilipallipeta"
    ],
    "wof:name":"Chigilipallipeta",
    "wof:placetype":"locality",
    "wof:population":10
},
  "geometry": {"coordinates":[83.819988,18.349223],"type":"Point"}
}