{
  "type": "Feature",
  "properties": {
    "gn:admin1_code":"25.0",
    "gn:admin2_code":"602.0",
    "gn:asciiname":"Pudukandigai",
    "gn:country_code":"IN",
    "gn:dem":23,
    "gn:feature_class":"P",
    "gn:feature_code":"PPL",
    "gn:name":"Pudukandigai",
    "gn:population":0,
    "gn:timezone":"Asia/Kolkata",
    "iso:country":"IN",
    "wof:name":"Pudukandigai",
    "wof:placetype":"locality"
},
  "geometry": {"coordinates":[80.07816,13.41059],"type":"Point"}
}