{
  "type": "Feature",
  "properties": {
    "iso:country":"IN",
    "ks:ks_name":"Banhijli",
    "ks:ks_pop":2906,
    "ks:ks_type":"VILLAGE",
    "ks:ks_uagg_main":0,
    "name:eng_x_preferred":[
        "Banhijli"
    ],
    "wof:name":"Banhijli",
    "wof:placetype":"neighbourhood",
    "wof:population":2906
},
  "geometry": {"coordinates":[87.843763,22.628736],"type":"Point"}
}