{
  "type": "Feature",
  "properties": {
    "iso:country":"IN",
    "ks:ks_name":"Dandagaon",
    "ks:ks_pop":171,
    "ks:ks_type":"HABITATION",
    "name:eng_x_preferred":[
        "Dandagaon"
    ],
    "wof:name":"Dandagaon",
    "wof:placetype":"locality",
    "wof:population":171
},
  "geometry": {"coordinates":[78.370107,30.700659],"type":"Point"}
}