{
  "type": "Feature",
  "properties": {
    "iso:country":"IN",
    "ks:ks_name":"Bajejama Chilakhana Dwitia Khanda",
    "ks:ks_pop":362,
    "ks:ks_type":"VILLAGE",
    "name:eng_x_preferred":[
        "Bajejama Chilakhana Dwitia Khanda"
    ],
    "wof:name":"Bajejama Chilakhana Dwitia Khanda",
    "wof:placetype":"locality",
    "wof:population":362
},
  "geometry": {"coordinates":[89.599936,26.352543],"type":"Point"}
}