{
  "type": "Feature",
  "properties": {
    "iso:country":"IN",
    "ks:ks_name":"Burhidangal",
    "ks:ks_pop":299,
    "ks:ks_type":"VILLAGE",
    "name:eng_x_preferred":[
        "Burhidangal"
    ],
    "wof:name":"Burhidangal",
    "wof:placetype":"locality",
    "wof:population":299
},
  "geometry": {"coordinates":[87.42528799999999,24.405853],"type":"Point"}
}