{
  "type": "Feature",
  "properties": {
    "gn:admin1_code":"34.0",
    "gn:admin2_code":"237.0",
    "gn:asciiname":"Meghipur",
    "gn:country_code":"IN",
    "gn:dem":84,
    "gn:feature_class":"P",
    "gn:feature_code":"PPL",
    "gn:name":"Meghipur",
    "gn:population":0,
    "gn:timezone":"Asia/Kolkata",
    "iso:country":"IN",
    "wof:name":"Meghipur",
    "wof:placetype":"locality"
},
  "geometry": {"coordinates":[85.69166,24.9444],"type":"Point"}
}