{
  "type": "Feature",
  "properties": {
    "iso:country":"IN",
    "ks:ks_name":"Chatarapatana",
    "ks:ks_pop":63,
    "ks:ks_type":"VILLAGE",
    "ks:ks_uagg_main":0,
    "name:eng_x_preferred":[
        "Chatarapatana"
    ],
    "wof:name":"Chatarapatana",
    "wof:placetype":"neighbourhood",
    "wof:population":63
},
  "geometry": {"coordinates":[86.79414199999999,21.437049],"type":"Point"}
}