{
  "type": "Feature",
  "properties": {
    "iso:country":"IN",
    "ks:ks_name":"Dewahara",
    "ks:ks_pop":90,
    "ks:ks_type":"HABITATION",
    "name:eng_x_preferred":[
        "Dewahara"
    ],
    "wof:name":"Dewahara",
    "wof:placetype":"locality",
    "wof:population":90
},
  "geometry": {"coordinates":[82.669082,26.966747],"type":"Point"}
}