{
  "type": "Feature",
  "properties": {
    "iso:country":"IN",
    "ks:ks_name":"Moirahuchi",
    "ks:ks_pop":36,
    "ks:ks_type":"HABITATION",
    "name:eng_x_preferred":[
        "Moirahuchi"
    ],
    "wof:name":"Moirahuchi",
    "wof:placetype":"locality",
    "wof:population":36
},
  "geometry": {"coordinates":[91.343135,26.023436],"type":"Point"}
}