{
  "type": "Feature",
  "properties": {
    "gn:admin1_code":"36",
    "gn:admin2_code":"179.0",
    "gn:asciiname":"Sompur Mankanth",
    "gn:country_code":"IN",
    "gn:dem":112,
    "gn:feature_class":"P",
    "gn:feature_code":"PPL",
    "gn:name":"Sompur Mankanth",
    "gn:population":0,
    "gn:timezone":"Asia/Kolkata",
    "iso:country":"IN",
    "ks:ks_alt_nam":"SONPUR MANKANTH",
    "ks:ks_name":"Sonpur Mankanth",
    "ks:ks_pop":112,
    "ks:ks_type":"HABITATION",
    "name:eng_x_preferred":[
        "Sonpur Mankanth"
    ],
    "name:eng_x_variant":[
        "Sompur Mankanth"
    ],
    "wof:name":"Sonpur Mankanth",
    "wof:placetype":"locality",
    "wof:population":112
},
  "geometry": {"coordinates":[81.747248,26.151187],"type":"Point"}
}