{
  "type": "Feature",
  "properties": {
    "gn:admin1_code":"36",
    "gn:admin2_code":"142.0",
    "gn:asciiname":"Potha",
    "gn:country_code":"IN",
    "gn:dem":203,
    "gn:feature_class":"P",
    "gn:feature_code":"PPL",
    "gn:name":"Potha",
    "gn:population":0,
    "gn:timezone":"Asia/Kolkata",
    "iso:country":"IN",
    "name:und_x_variant":[
        "B\u0101dsh\u0101hp\u016br"
    ],
    "wof:name":"Potha",
    "wof:placetype":"locality"
},
  "geometry": {"coordinates":[78.18949000000001,28.44129],"type":"Point"}
}