{
  "type": "Feature",
  "properties": {
    "gn:admin1_code":"25.0",
    "gn:asciiname":"Velanthavalam",
    "gn:country_code":"IN",
    "gn:dem":193,
    "gn:feature_class":"P",
    "gn:feature_code":"PPL",
    "gn:name":"Velanth\u0101valam",
    "gn:population":0,
    "gn:timezone":"Asia/Kolkata",
    "iso:country":"IN",
    "wof:name":"Velanthavalam",
    "wof:placetype":"locality"
},
  "geometry": {"coordinates":[76.86140999999998,10.81599],"type":"Point"}
}