{
  "type": "Feature",
  "properties": {
    "gn:admin1_code":"36",
    "gn:admin2_code":"142.0",
    "gn:asciiname":"Ram Balon",
    "gn:country_code":"IN",
    "gn:dem":188,
    "gn:feature_class":"P",
    "gn:feature_code":"PPL",
    "gn:name":"R\u0101m Balon",
    "gn:population":0,
    "gn:timezone":"Asia/Kolkata",
    "iso:country":"IN",
    "ks:ks_alt_nam":"R\u0101m Balon",
    "ks:ks_name":"Ram Balon",
    "ks:ks_type":"VILLAGE",
    "name:eng_x_preferred":[
        "Ram Balon"
    ],
    "name:eng_x_variant":[
        "R\u0101m Balon"
    ],
    "wof:name":"Ram Balon",
    "wof:placetype":"locality"
},
  "geometry": {"coordinates":[78.33286699999999,28.198763],"type":"Point"}
}