{
  "type": "Feature",
  "properties": {
    "gn:admin1_code":"39.0",
    "gn:admin2_code":"64.0",
    "gn:asciiname":"Pakauna",
    "gn:country_code":"IN",
    "gn:dem":1232,
    "gn:feature_class":"P",
    "gn:feature_code":"PPL",
    "gn:name":"Pakauna",
    "gn:population":0,
    "gn:timezone":"Asia/Kolkata",
    "iso:country":"IN",
    "ks:ks_alt_nam":"Pakauna",
    "ks:ks_name":"Pakaun",
    "ks:ks_type":"VILLAGE",
    "name:eng_x_preferred":[
        "Pakaun"
    ],
    "name:eng_x_variant":[
        "Pakauna"
    ],
    "wof:name":"Pakaun",
    "wof:placetype":"locality"
},
  "geometry": {"coordinates":[79.959194,29.570325],"type":"Point"}
}