{
  "type": "Feature",
  "properties": {
    "gn:admin1_code":"30",
    "gn:admin2_code":"260.0",
    "gn:asciiname":"Plongliang",
    "gn:country_code":"IN",
    "gn:dem":1087,
    "gn:feature_class":"P",
    "gn:feature_code":"PPL",
    "gn:name":"Plongliang",
    "gn:population":0,
    "gn:timezone":"Asia/Kolkata",
    "iso:country":"IN",
    "name:und_x_variant":[
        "Plonliang",
        "Plongliang"
    ],
    "wof:name":"Plongliang",
    "wof:placetype":"locality"
},
  "geometry": {"coordinates":[96.55544,28.27842],"type":"Point"}
}