{
  "type": "Feature",
  "properties": {
    "gn:admin1_code":"16.0",
    "gn:admin2_code":"514.0",
    "gn:asciiname":"Nagapur",
    "gn:country_code":"IN",
    "gn:dem":431,
    "gn:feature_class":"P",
    "gn:feature_code":"PPL",
    "gn:name":"N\u0101g\u0101pur",
    "gn:population":0,
    "gn:timezone":"Asia/Kolkata",
    "iso:country":"IN",
    "wof:name":"Nagapur",
    "wof:placetype":"locality"
},
  "geometry": {"coordinates":[76.26868,19.60381],"type":"Point"}
}