{
  "type": "Feature",
  "properties": {
    "gn:admin1_code":"16.0",
    "gn:admin2_code":"514.0",
    "gn:asciiname":"Nagapur",
    "gn:country_code":"IN",
    "gn:dem":431,
    "gn:feature_class":"P",
    "gn:feature_code":"PPL",
    "gn:name":"N\u0101g\u0101pur",
    "gn:population":0,
    "gn:timezone":"Asia/Kolkata",
    "iso:country":"IN",
    "ks:ks_alt_nam":"N\u0101g\u0101pur",
    "ks:ks_name":"Nagapur",
    "ks:ks_pop":328,
    "ks:ks_type":"VILLAGE",
    "name:ben_x_preferred":[
        "\u09a8\u09be\u0997\u09be\u09aa\u09c1\u09b0"
    ],
    "name:bpy_x_preferred":[
        "\u09a8\u09be\u0997\u09be\u09aa\u09c1\u09b0"
    ],
    "name:ceb_x_preferred":[
        "N\u0101g\u0101pur"
    ],
    "name:eng_x_preferred":[
        "Nagapur"
    ],
    "name:eng_x_variant":[
        "N\u0101g\u0101pur"
    ],
    "name:ita_x_preferred":[
        "Nagapur"
    ],
    "name:mlg_x_preferred":[
        "Nagapur"
    ],
    "name:msa_x_preferred":[
        "Nagapur"
    ],
    "name:new_x_preferred":[
        "\u0928\u093e\u0917\u093e\u092a\u0941\u0930"
    ],
    "name:nld_x_preferred":[
        "Nagapur"
    ],
    "name:por_x_preferred":[
        "Nagapur"
    ],
    "name:swe_x_preferred":[
        "N\u0101g\u0101pur"
    ],
    "name:urd_x_preferred":[
        "\u0646\u0627\u06af\u0627\u067e\u0648\u0631"
    ],
    "name:vie_x_preferred":[
        "Nagapur"
    ],
    "name:zho_x_preferred":[
        "\u7eb3\u52a0\u666e\u5c14"
    ],
    "wof:name":"Nagapur",
    "wof:placetype":"locality",
    "wof:population":328
},
  "geometry": {"coordinates":[76.26868399999999,19.603813],"type":"Point"}
}