{
  "type": "Feature",
  "properties": {
    "iso:country":"IN",
    "ks:ks_name":"Uttamdi Rengtudi",
    "ks:ks_pop":403,
    "ks:ks_type":"HABITATION",
    "name:eng_x_preferred":[
        "Uttamdi Rengtudi"
    ],
    "wof:name":"Uttamdi Rengtudi",
    "wof:placetype":"locality",
    "wof:population":403
},
  "geometry": {"coordinates":[85.988372,23.210337],"type":"Point"}
}