{
  "type": "Feature",
  "properties": {
    "iso:country":"IN",
    "ks:ks_name":"Gobardhan Bigha",
    "ks:ks_pop":216,
    "ks:ks_type":"HABITATION",
    "name:eng_x_preferred":[
        "Gobardhan Bigha"
    ],
    "wof:name":"Gobardhan Bigha",
    "wof:placetype":"locality",
    "wof:population":216
},
  "geometry": {"coordinates":[84.78321,24.799004],"type":"Point"}
}