{
  "type": "Feature",
  "properties": {
    "iso:country":"IN",
    "ks:ks_name":"Rautbati",
    "ks:ks_pop":1535,
    "ks:ks_type":"VILLAGE",
    "name:eng_x_preferred":[
        "Rautbati"
    ],
    "wof:name":"Rautbati",
    "wof:placetype":"locality",
    "wof:population":1535
},
  "geometry": {"coordinates":[88.608937,23.873156],"type":"Point"}
}