{
  "type": "Feature",
  "properties": {
    "gn:admin1_code":"40.0",
    "gn:admin2_code":"532.0",
    "gn:asciiname":"Indapur",
    "gn:country_code":"IN",
    "gn:dem":283,
    "gn:feature_class":"P",
    "gn:feature_code":"PPL",
    "gn:name":"Ind\u0101pur",
    "gn:population":0,
    "gn:timezone":"Asia/Kolkata",
    "iso:country":"IN",
    "name:ben_x_preferred":[
        "\u0987\u09a8\u09cd\u09a6\u09be\u09aa\u09c1\u09b0"
    ],
    "name:bpy_x_preferred":[
        "\u0987\u09a8\u09cd\u09a6\u09be\u09aa\u09c1\u09b0"
    ],
    "name:ceb_x_preferred":[
        "Ind\u0101pur"
    ],
    "name:ita_x_preferred":[
        "Indapur"
    ],
    "name:mar_x_preferred":[
        "\u0907\u0902\u0926\u093e\u092a\u0942\u0930"
    ],
    "name:msa_x_preferred":[
        "Indapur"
    ],
    "name:new_x_preferred":[
        "\u0907\u0928\u094d\u0926\u093e\u092a\u0941\u0930"
    ],
    "name:nld_x_preferred":[
        "Indapur"
    ],
    "name:por_x_preferred":[
        "Indapur"
    ],
    "name:ukr_x_preferred":[
        "\u0406\u043d\u0434\u0430\u043f\u0443\u0440"
    ],
    "name:urd_x_preferred":[
        "\u0627\u0646\u062f\u0627\u067e\u0648\u0631"
    ],
    "name:vie_x_preferred":[
        "Indapur"
    ],
    "name:zho_x_preferred":[
        "\u4f0a\u6069\u8fbe\u666e\u5c14"
    ],
    "wof:name":"Indapur",
    "wof:placetype":"locality"
},
  "geometry": {"coordinates":[79.13656999999998,19.45471],"type":"Point"}
}