{
  "type": "Feature",
  "properties": {
    "iso:country":"IN",
    "ks:ks_name":"Malvnnagar",
    "ks:ks_pop":618,
    "ks:ks_type":"HABITATION",
    "ks:ks_uagg_main":0,
    "name:eng_x_preferred":[
        "Malvnnagar"
    ],
    "wof:name":"Malvnnagar",
    "wof:placetype":"neighbourhood",
    "wof:population":618
},
  "geometry": {"coordinates":[84.53402699999999,23.018215],"type":"Point"}
}