{
  "type": "Feature",
  "properties": {
    "iso:country":"IN",
    "ks:ks_name":"Asapur",
    "ks:ks_pop":747,
    "ks:ks_type":"VILLAGE",
    "ks:ks_uagg_main":0,
    "name:eng_x_preferred":[
        "Asapur"
    ],
    "wof:name":"Asapur",
    "wof:placetype":"neighbourhood",
    "wof:population":747
},
  "geometry": {"coordinates":[88.11972299999999,22.228113],"type":"Point"}
}