{
  "type": "Feature",
  "properties": {
    "iso:country":"IN",
    "ks:ks_name":"Jadhavwadi",
    "ks:ks_pop":75,
    "ks:ks_type":"HABITATION",
    "name:eng_x_preferred":[
        "Jadhavwadi"
    ],
    "wof:name":"Jadhavwadi",
    "wof:placetype":"locality",
    "wof:population":75
},
  "geometry": {"coordinates":[73.52136400000001,17.332031],"type":"Point"}
}