{
  "type": "Feature",
  "properties": {
    "iso:country":"IN",
    "ks:ks_name":"Alkusha",
    "ks:ks_pop":0,
    "ks:ks_type":"VILLAGE",
    "name:eng_x_preferred":[
        "Alkusha"
    ],
    "wof:name":"Alkusha",
    "wof:placetype":"locality",
    "wof:population":0
},
  "geometry": {"coordinates":[86.78657699999999,23.687504],"type":"Point"}
}