{
  "type": "Feature",
  "properties": {
    "iso:country":"IN",
    "ks:ks_name":"Bangalipada 2",
    "ks:ks_pop":153,
    "ks:ks_type":"HABITATION",
    "name:eng_x_preferred":[
        "Bangalipada 2"
    ],
    "wof:name":"Bangalipada 2",
    "wof:placetype":"locality",
    "wof:population":153
},
  "geometry": {"coordinates":[86.69946299999999,20.996576],"type":"Point"}
}