{
  "type": "Feature",
  "properties": {
    "iso:country":"IN",
    "ks:ks_name":"Ganjuguda",
    "ks:ks_pop":50,
    "ks:ks_type":"VILLAGE",
    "name:eng_x_preferred":[
        "Ganjuguda"
    ],
    "wof:name":"Ganjuguda",
    "wof:placetype":"locality",
    "wof:population":50
},
  "geometry": {"coordinates":[84.246765,20.045673],"type":"Point"}
}