{
  "type": "Feature",
  "properties": {
    "gn:admin1_code":"11.0",
    "gn:admin2_code":"27.0",
    "gn:asciiname":"Nohra",
    "gn:country_code":"IN",
    "gn:dem":1776,
    "gn:feature_class":"P",
    "gn:feature_code":"PPL",
    "gn:name":"Nohra",
    "gn:population":0,
    "gn:timezone":"Asia/Kolkata",
    "iso:country":"IN",
    "name:bak_x_preferred":[
        "\u041d\u043e\u0440\u0430"
    ],
    "name:deu_x_preferred":[
        "Nohra"
    ],
    "name:epo_x_preferred":[
        "Nohra"
    ],
    "name:eus_x_preferred":[
        "Nohra"
    ],
    "name:fas_x_preferred":[
        "\u0646\u0648\u0647\u0631\u0627"
    ],
    "name:fin_x_preferred":[
        "Nohra"
    ],
    "name:fra_x_preferred":[
        "Nohra"
    ],
    "name:hun_x_preferred":[
        "Nohra"
    ],
    "name:ita_x_preferred":[
        "Nohra"
    ],
    "name:kaz_x_preferred":[
        "\u041d\u043e\u0440\u0430"
    ],
    "name:kir_x_preferred":[
        "\u041d\u043e\u0440\u0430"
    ],
    "name:mkd_x_preferred":[
        "\u041d\u043e\u0440\u0430"
    ],
    "name:msa_x_preferred":[
        "Nohra"
    ],
    "name:nld_x_preferred":[
        "Nohra"
    ],
    "name:pol_x_preferred":[
        "Nohra"
    ],
    "name:ron_x_preferred":[
        "Nohra"
    ],
    "name:rus_x_preferred":[
        "\u041d\u043e\u0440\u0430"
    ],
    "name:spa_x_preferred":[
        "Nohra"
    ],
    "name:srp_x_preferred":[
        "\u041d\u043e\u0440\u0430"
    ],
    "name:ukr_x_preferred":[
        "\u041d\u043e\u0440\u0430"
    ],
    "name:uzb_x_preferred":[
        "Nohra"
    ],
    "name:vie_x_preferred":[
        "Nohra"
    ],
    "name:vol_x_preferred":[
        "Nohra"
    ],
    "name:war_x_preferred":[
        "Nohra"
    ],
    "wof:name":"Nohra",
    "wof:placetype":"locality"
},
  "geometry": {"coordinates":[77.25754999999999,31.38159000000001],"type":"Point"}
}