{
  "type": "Feature",
  "properties": {
    "gn:admin1_code":"11.0",
    "gn:admin2_code":"27.0",
    "gn:asciiname":"Nohra",
    "gn:country_code":"IN",
    "gn:dem":1776,
    "gn:feature_class":"P",
    "gn:feature_code":"PPL",
    "gn:name":"Nohra",
    "gn:population":0,
    "gn:timezone":"Asia/Kolkata",
    "iso:country":"IN",
    "wof:name":"Nohra",
    "wof:placetype":"locality"
},
  "geometry": {"coordinates":[77.25754999999999,31.38159000000001],"type":"Point"}
}