{
  "type": "Feature",
  "properties": {
    "iso:country":"IN",
    "ks:ks_name":"Jahanar Ghola",
    "ks:ks_pop":395,
    "ks:ks_type":"VILLAGE",
    "ks:ks_uagg_main":0,
    "name:eng_x_preferred":[
        "Jahanar Ghola"
    ],
    "wof:name":"Jahanar Ghola",
    "wof:placetype":"neighbourhood",
    "wof:population":395
},
  "geometry": {"coordinates":[90.817706,26.220364],"type":"Point"}
}