{
  "type": "Feature",
  "properties": {
    "gn:admin1_code":"34.0",
    "gn:admin2_code":"239.0",
    "gn:asciiname":"Ghosi",
    "gn:country_code":"IN",
    "gn:dem":74,
    "gn:feature_class":"P",
    "gn:feature_code":"PPL",
    "gn:name":"Ghosi",
    "gn:population":0,
    "gn:timezone":"Asia/Kolkata",
    "iso:country":"IN",
    "name:bpy_x_preferred":[
        "\u0998\u09cc\u09b8\u09bf"
    ],
    "name:ceb_x_preferred":[
        "Ghosi"
    ],
    "name:hin_x_preferred":[
        "\u0918\u094b\u0938\u0940"
    ],
    "name:ita_x_preferred":[
        "Ghosi"
    ],
    "name:mlg_x_preferred":[
        "Ghosi"
    ],
    "name:msa_x_preferred":[
        "Ghosi"
    ],
    "name:new_x_preferred":[
        "\u0918\u094b\u0938\u0940"
    ],
    "name:nld_x_preferred":[
        "Ghosi"
    ],
    "name:pol_x_preferred":[
        "Ghosi"
    ],
    "name:por_x_preferred":[
        "Ghosi"
    ],
    "name:swe_x_preferred":[
        "Ghosi"
    ],
    "name:urd_x_preferred":[
        "\u06af\u06be\u0648\u0633\u06cc"
    ],
    "name:vie_x_preferred":[
        "Ghosi"
    ],
    "wof:name":"Ghosi",
    "wof:placetype":"locality"
},
  "geometry": {"coordinates":[84.9284,25.16659],"type":"Point"}
}