{
  "type": "Feature",
  "properties": {
    "gn:admin1_code":"36",
    "gn:admin2_code":"158.0",
    "gn:asciiname":"Rajapur",
    "gn:country_code":"IN",
    "gn:dem":114,
    "gn:feature_class":"P",
    "gn:feature_code":"PPL",
    "gn:name":"R\u0101japur",
    "gn:population":0,
    "gn:timezone":"Asia/Kolkata",
    "iso:country":"IN",
    "wof:name":"Rajapur",
    "wof:placetype":"locality"
},
  "geometry": {"coordinates":[81.54756999999999,26.30177],"type":"Point"}
}