{
  "type": "Feature",
  "properties": {
    "gn:admin1_code":"2",
    "gn:admin2_code":"548.0",
    "gn:asciiname":"Kakumanu",
    "gn:country_code":"IN",
    "gn:dem":12,
    "gn:feature_class":"P",
    "gn:feature_code":"PPL",
    "gn:name":"K\u0101kum\u0101nu",
    "gn:population":0,
    "gn:timezone":"Asia/Kolkata",
    "iso:country":"IN",
    "name:new_x_preferred":[
        "\u0915\u093e\u0915\u0941\u092e\u093e\u0928\u0941 \u092e\u0923\u094d\u0921\u0932"
    ],
    "name:pam_x_preferred":[
        "Kakumanu"
    ],
    "name:tel_x_preferred":[
        "\u0c15\u0c3e\u0c15\u0c41\u0c2e\u0c3e\u0c28\u0c41"
    ],
    "name:tgl_x_preferred":[
        "Kakumanu"
    ],
    "name:vie_x_preferred":[
        "Kakumanu"
    ],
    "wof:name":"Kakumanu",
    "wof:placetype":"locality"
},
  "geometry": {"coordinates":[80.39809,16.05421],"type":"Point"}
}