{
  "type": "Feature",
  "properties": {
    "gn:admin1_code":"40.0",
    "gn:admin2_code":"539",
    "gn:asciiname":"Chalkapalli",
    "gn:country_code":"IN",
    "gn:dem":388,
    "gn:feature_class":"P",
    "gn:feature_code":"PPL",
    "gn:name":"Chalk\u0101palli",
    "gn:population":0,
    "gn:timezone":"Asia/Kolkata",
    "iso:country":"IN",
    "wof:name":"Chalkapalli",
    "wof:placetype":"locality"
},
  "geometry": {"coordinates":[78.86610999999998,17.31417],"type":"Point"}
}