{
  "type": "Feature",
  "properties": {
    "gn:admin1_code":"35",
    "gn:admin2_code":"442.0",
    "gn:asciiname":"Dabri",
    "gn:country_code":"IN",
    "gn:dem":414,
    "gn:feature_class":"P",
    "gn:feature_code":"PPL",
    "gn:name":"D\u0101bri",
    "gn:population":0,
    "gn:timezone":"Asia/Kolkata",
    "iso:country":"IN",
    "name:urd_x_preferred":[
        "\u062f\u0627\u0628\u0691\u06cc"
    ],
    "wof:name":"Dabri",
    "wof:placetype":"locality"
},
  "geometry": {"coordinates":[76.73654000000001,23.82793],"type":"Point"}
}