{
  "type": "Feature",
  "properties": {
    "gn:admin1_code":"36",
    "gn:admin2_code":"194.0",
    "gn:asciiname":"Qalondarpur",
    "gn:country_code":"IN",
    "gn:dem":82,
    "gn:feature_class":"P",
    "gn:feature_code":"PPL",
    "gn:name":"Qalondarpur",
    "gn:population":0,
    "gn:timezone":"Asia/Kolkata",
    "iso:country":"IN",
    "ks:ks_name":"Kalandarpur",
    "ks:ks_pop":394,
    "ks:ks_type":"VILLAGE",
    "ks:ks_uagg_main":0,
    "name:eng_x_preferred":[
        "Kalandarpur"
    ],
    "wof:name":"Kalandarpur",
    "wof:placetype":"neighbourhood",
    "wof:population":394
},
  "geometry": {"coordinates":[82.73675299999999,25.708748],"type":"Point"}
}