{
  "type": "Feature",
  "properties": {
    "iso:country":"IN",
    "ks:ks_name":"Badabazar",
    "ks:ks_pop":397,
    "ks:ks_type":"VILLAGE",
    "name:eng_x_preferred":[
        "Badabazar"
    ],
    "wof:name":"Badabazar",
    "wof:placetype":"locality",
    "wof:population":397
},
  "geometry": {"coordinates":[87.053451,21.702947],"type":"Point"}
}