{
  "type": "Feature",
  "properties": {
    "gn:admin1_code":"12",
    "gn:admin2_code":"13.0",
    "gn:asciiname":"Wotu",
    "gn:country_code":"IN",
    "gn:dem":2145,
    "gn:feature_class":"P",
    "gn:feature_code":"PPL",
    "gn:name":"Wot\u016b",
    "gn:population":0,
    "gn:timezone":"Asia/Kolkata",
    "iso:country":"IN",
    "wof:name":"Wotu",
    "wof:placetype":"locality"
},
  "geometry": {"coordinates":[74.83036,33.64088],"type":"Point"}
}