{
  "type": "Feature",
  "properties": {
    "iso:country":"IN",
    "ks:ks_name":"Kathigudem",
    "ks:ks_pop":1016,
    "ks:ks_type":"VILLAGE",
    "name:eng_x_preferred":[
        "Kathigudem"
    ],
    "wof:name":"Kathigudem",
    "wof:placetype":"locality",
    "wof:population":1016
},
  "geometry": {"coordinates":[80.65387200000001,18.169527],"type":"Point"}
}