{
  "type": "Feature",
  "properties": {
    "iso:country":"IN",
    "ks:ks_name":"Madhala Mohalla",
    "ks:ks_pop":112,
    "ks:ks_type":"HABITATION",
    "name:eng_x_preferred":[
        "Madhala Mohalla"
    ],
    "wof:name":"Madhala Mohalla",
    "wof:placetype":"locality",
    "wof:population":112
},
  "geometry": {"coordinates":[73.242391,17.560664],"type":"Point"}
}