{
  "type": "Feature",
  "properties": {
    "gn:admin1_code":"35",
    "gn:admin2_code":"424.0",
    "gn:asciiname":"Umri",
    "gn:country_code":"IN",
    "gn:dem":256,
    "gn:feature_class":"P",
    "gn:feature_code":"PPL",
    "gn:name":"\u016amri",
    "gn:population":0,
    "gn:timezone":"Asia/Kolkata",
    "iso:country":"IN",
    "name:ceb_x_preferred":[
        "Umri"
    ],
    "name:pol_x_preferred":[
        "Umri"
    ],
    "name:swe_x_preferred":[
        "Umri"
    ],
    "wof:name":"Umri",
    "wof:placetype":"locality"
},
  "geometry": {"coordinates":[78.93321,25.31187000000001],"type":"Point"}
}