{
  "type": "Feature",
  "properties": {
    "iso:country":"IN",
    "ks:ks_name":"Marsleeba Junction",
    "ks:ks_pop":2146,
    "ks:ks_type":"HABITATION",
    "name:eng_x_preferred":[
        "Marsleeba Junction"
    ],
    "wof:name":"Marsleeba Junction",
    "wof:placetype":"locality",
    "wof:population":2146
},
  "geometry": {"coordinates":[76.44286700000001,9.772059],"type":"Point"}
}