{
  "type": "Feature",
  "properties": {
    "gn:admin1_code":"21",
    "gn:admin2_code":"396.0",
    "gn:asciiname":"Ballipadar",
    "gn:country_code":"IN",
    "gn:dem":462,
    "gn:feature_class":"P",
    "gn:feature_code":"PPL",
    "gn:name":"Ballipadar",
    "gn:population":0,
    "gn:timezone":"Asia/Kolkata",
    "iso:country":"IN",
    "name:ori_x_preferred":[
        "\u0b2c\u0b3e\u0b32\u0b3f\u0b2a\u0b26\u0b30"
    ],
    "wof:name":"Ballipadar",
    "wof:placetype":"locality"
},
  "geometry": {"coordinates":[83.49913000000002,19.85382],"type":"Point"}
}