{
  "type": "Feature",
  "properties": {
    "gn:admin1_code":"19.0",
    "gn:admin2_code":"570.0",
    "gn:asciiname":"Bukkamallanahalli",
    "gn:country_code":"IN",
    "gn:dem":712,
    "gn:feature_class":"P",
    "gn:feature_code":"PPL",
    "gn:name":"Bukkamallanahalli",
    "gn:population":0,
    "gn:timezone":"Asia/Kolkata",
    "iso:country":"IN",
    "ks:ks_name":"Bukkamallanahalli",
    "ks:ks_type":"VILLAGE",
    "name:eng_x_preferred":[
        "Bukkamallanahalli"
    ],
    "wof:name":"Bukkamallanahalli",
    "wof:placetype":"locality"
},
  "geometry": {"coordinates":[76.129757,13.573072],"type":"Point"}
}