{
  "type": "Feature",
  "properties": {
    "iso:country":"IN",
    "ks:ks_name":"Sambhusar",
    "ks:ks_pop":440,
    "ks:ks_type":"HABITATION",
    "name:eng_x_preferred":[
        "Sambhusar"
    ],
    "wof:name":"Sambhusar",
    "wof:placetype":"locality",
    "wof:population":440
},
  "geometry": {"coordinates":[71.499623,26.274266],"type":"Point"}
}