{
  "type": "Feature",
  "properties": {
    "gn:admin1_code":"11.0",
    "gn:admin2_code":"27.0",
    "gn:asciiname":"Khaneot",
    "gn:country_code":"IN",
    "gn:dem":1869,
    "gn:feature_class":"P",
    "gn:feature_code":"PPL",
    "gn:name":"Khaneot",
    "gn:population":0,
    "gn:timezone":"Asia/Kolkata",
    "iso:country":"IN",
    "wof:name":"Khaneot",
    "wof:placetype":"locality"
},
  "geometry": {"coordinates":[77.34808000000002,31.41911],"type":"Point"}
}