{
  "type": "Feature",
  "properties": {
    "iso:country":"IN",
    "ks:ks_name":"Bhoikond",
    "ks:ks_pop":300,
    "ks:ks_type":"HABITATION",
    "name:eng_x_preferred":[
        "Bhoikond"
    ],
    "wof:name":"Bhoikond",
    "wof:placetype":"locality",
    "wof:population":300
},
  "geometry": {"coordinates":[73.473748,18.084133],"type":"Point"}
}