{
  "type": "Feature",
  "properties": {
    "gn:admin1_code":"2.0",
    "gn:admin2_code":"542.0",
    "gn:asciiname":"Padali",
    "gn:country_code":"IN",
    "gn:dem":59,
    "gn:feature_class":"P",
    "gn:feature_code":"PPL",
    "gn:name":"P\u0101dali",
    "gn:population":0,
    "gn:timezone":"Asia/Kolkata",
    "iso:country":"IN",
    "name:ceb_x_preferred":[
        "Padal\u012b"
    ],
    "name:fas_x_preferred":[
        "\u067e\u062f\u0644\u06cc"
    ],
    "name:swe_x_preferred":[
        "Padal\u012b"
    ],
    "wof:name":"Padali",
    "wof:placetype":"locality"
},
  "geometry": {"coordinates":[83.91285999999999,18.68159],"type":"Point"}
}