{
  "type": "Feature",
  "properties": {
    "gn:admin1_code":"25.0",
    "gn:admin2_code":"611.0",
    "gn:asciiname":"Fernhill",
    "gn:country_code":"IN",
    "gn:dem":2259,
    "gn:feature_class":"P",
    "gn:feature_code":"PPL",
    "gn:name":"Fernhill",
    "gn:population":0,
    "gn:timezone":"Asia/Kolkata",
    "iso:country":"IN",
    "name:ces_x_preferred":[
        "Fernhill"
    ],
    "name:cym_x_preferred":[
        "Fernhill"
    ],
    "name:deu_x_preferred":[
        "Fernhill"
    ],
    "wof:name":"Fernhill",
    "wof:placetype":"locality"
},
  "geometry": {"coordinates":[76.68671999999999,11.39542],"type":"Point"}
}