{
  "type": "Feature",
  "properties": {
    "gn:admin1_code":"36",
    "gn:admin2_code":"135.0",
    "gn:asciiname":"Pipli Umarpur Aliabad",
    "gn:country_code":"IN",
    "gn:dem":211,
    "gn:feature_class":"P",
    "gn:feature_code":"PPL",
    "gn:name":"P\u012bpli Umarpur Al\u012b\u0101b\u0101d",
    "gn:population":0,
    "gn:timezone":"Asia/Kolkata",
    "iso:country":"IN",
    "wof:name":"Pipli Umarpur Aliabad",
    "wof:placetype":"locality"
},
  "geometry": {"coordinates":[78.73204,29.11721],"type":"Point"}
}