{
  "type": "Feature",
  "properties": {
    "gn:admin1_code":"11.0",
    "gn:admin2_code":"32.0",
    "gn:asciiname":"Chamba",
    "gn:country_code":"IN",
    "gn:dem":1344,
    "gn:feature_class":"P",
    "gn:feature_code":"PPL",
    "gn:name":"Chamba",
    "gn:population":0,
    "gn:timezone":"Asia/Kolkata",
    "iso:country":"IN",
    "name:ara_x_preferred":[
        "\u0634\u0627\u0645\u0628\u0627"
    ],
    "name:ben_x_preferred":[
        "\u099a\u09be\u09ae\u09cd\u09ac\u09be"
    ],
    "name:ceb_x_preferred":[
        "Chamba"
    ],
    "name:deu_x_preferred":[
        "Chamba"
    ],
    "name:fra_x_preferred":[
        "Chamba"
    ],
    "name:ita_x_preferred":[
        "Chamba"
    ],
    "name:mal_x_preferred":[
        "\u0d1a\u0d2e\u0d4d\u0d2a"
    ],
    "name:nld_x_preferred":[
        "Chamba"
    ],
    "name:pan_x_preferred":[
        "\u0a1a\u0a70\u0a2c\u0a3e"
    ],
    "name:pol_x_preferred":[
        "Chamba"
    ],
    "name:spa_x_preferred":[
        "Chamba"
    ],
    "name:swe_x_preferred":[
        "Chamba"
    ],
    "wof:name":"Chamba",
    "wof:placetype":"locality"
},
  "geometry": {"coordinates":[77.35665999999998,30.65783],"type":"Point"}
}