{
  "type": "Feature",
  "properties": {
    "iso:country":"IN",
    "ks:ks_alt_nam":"13 MD-B",
    "ks:ks_name":"13 Md-b",
    "ks:ks_pop":20,
    "ks:ks_type":"HABITATION",
    "name:eng_x_preferred":[
        "13 Md-b"
    ],
    "wof:name":"13 Md-b",
    "wof:placetype":"locality",
    "wof:population":20
},
  "geometry": {"coordinates":[73.07293900000001,29.049381],"type":"Point"}
}