{
  "type": "Feature",
  "properties": {
    "gn:admin1_code":"36",
    "gn:admin2_code":"138.0",
    "gn:asciiname":"Birnagar",
    "gn:country_code":"IN",
    "gn:dem":211,
    "gn:feature_class":"P",
    "gn:feature_code":"PPL",
    "gn:name":"B\u012brnagar",
    "gn:population":0,
    "gn:timezone":"Asia/Kolkata",
    "iso:country":"IN",
    "name:ben_x_preferred":[
        "\u09ac\u09c0\u09b0\u09a8\u0997\u09b0"
    ],
    "name:bpy_x_preferred":[
        "\u09ac\u09c0\u09b0\u09a8\u0997\u09b0"
    ],
    "name:ita_x_preferred":[
        "Birnagar"
    ],
    "name:msa_x_preferred":[
        "Birnagar"
    ],
    "name:new_x_preferred":[
        "\u0935\u0940\u0930\u0928\u0917\u0930"
    ],
    "name:por_x_preferred":[
        "Birnagar"
    ],
    "name:spa_x_preferred":[
        "Birnagar"
    ],
    "name:swe_x_preferred":[
        "Birnagar"
    ],
    "name:vie_x_preferred":[
        "Birnagar"
    ],
    "name:zho_x_preferred":[
        "\u6bd4\u5c14\u7eb3\u52a0\u5c14"
    ],
    "wof:name":"Birnagar",
    "wof:placetype":"locality"
},
  "geometry": {"coordinates":[78.03946999999999,29.02399],"type":"Point"}
}