{
  "type": "Feature",
  "properties": {
    "gn:admin1_code":"12.0",
    "gn:admin2_code":"005",
    "gn:asciiname":"Kulian da Kotha",
    "gn:country_code":"IN",
    "gn:dem":2642,
    "gn:feature_class":"P",
    "gn:feature_code":"PPL",
    "gn:name":"Kuli\u0101n da Kotha",
    "gn:population":0,
    "gn:timezone":"Asia/Kolkata",
    "iso:country":"IN",
    "wof:name":"Kulian da Kotha",
    "wof:placetype":"locality"
},
  "geometry": {"coordinates":[74.34388,33.8698],"type":"Point"}
}