{
  "type": "Feature",
  "properties": {
    "iso:country":"IN",
    "ks:ks_alt_nam":"Jamuna Terang gaon",
    "ks:ks_name":"Jamuna Terang Gaon",
    "ks:ks_pop":181,
    "ks:ks_type":"HABITATION",
    "name:eng_x_preferred":[
        "Jamuna Terang Gaon"
    ],
    "wof:name":"Jamuna Terang Gaon",
    "wof:placetype":"locality",
    "wof:population":181
},
  "geometry": {"coordinates":[93.03552500000001,26.135965],"type":"Point"}
}