{
  "type": "Feature",
  "properties": {
    "gn:admin1_code":"12.0",
    "gn:admin2_code":"008",
    "gn:asciiname":"Lohar Chak",
    "gn:country_code":"IN",
    "gn:dem":1586,
    "gn:feature_class":"P",
    "gn:feature_code":"PPL",
    "gn:name":"Lohar Chak",
    "gn:population":0,
    "gn:timezone":"Asia/Kolkata",
    "iso:country":"IN",
    "wof:name":"Lohar Chak",
    "wof:placetype":"locality"
},
  "geometry": {"coordinates":[74.63775,34.09372],"type":"Point"}
}