{
  "type": "Feature",
  "properties": {
    "iso:country":"IN",
    "ks:ks_name":"Vengannagumpu",
    "ks:ks_pop":69,
    "ks:ks_type":"HABITATION",
    "name:eng_x_preferred":[
        "Vengannagumpu"
    ],
    "wof:name":"Vengannagumpu",
    "wof:placetype":"locality",
    "wof:population":69
},
  "geometry": {"coordinates":[80.67855400000001,17.781525],"type":"Point"}
}