{
  "type": "Feature",
  "properties": {
    "gn:admin1_code":"37",
    "gn:admin2_code":"409.0",
    "gn:asciiname":"Tala",
    "gn:country_code":"IN",
    "gn:dem":274,
    "gn:feature_class":"P",
    "gn:feature_code":"PPL",
    "gn:name":"T\u0101la",
    "gn:population":0,
    "gn:timezone":"Asia/Kolkata",
    "iso:country":"IN",
    "name:ara_x_preferred":[
        "\u062a\u0627\u0644\u0627"
    ],
    "name:aze_x_preferred":[
        "Tala"
    ],
    "name:ben_bn_x_preferred":[
        "\u09a4\u09be\u09b2\u09be"
    ],
    "name:ben_in_x_preferred":[
        "\u09a4\u09be\u09b2\u09be"
    ],
    "name:ceb_x_preferred":[
        "Tala"
    ],
    "name:deu_x_preferred":[
        "Tala"
    ],
    "name:ell_x_preferred":[
        "\u03a4\u03ac\u03bb\u03b1"
    ],
    "name:epo_x_preferred":[
        "Tala"
    ],
    "name:est_x_preferred":[
        "Tala"
    ],
    "name:fin_x_preferred":[
        "Tala"
    ],
    "name:fra_x_preferred":[
        "Tala"
    ],
    "name:guj_x_preferred":[
        "\u0aa4\u0ab2\u0abe"
    ],
    "name:hin_x_preferred":[
        "\u0924\u093e\u0932\u093e"
    ],
    "name:ind_x_preferred":[
        "Tala"
    ],
    "name:isl_x_preferred":[
        "Tala"
    ],
    "name:ita_x_preferred":[
        "Tala"
    ],
    "name:kan_x_preferred":[
        "\u0ca4\u0cbe\u0cb2\u0cbe"
    ],
    "name:lit_x_preferred":[
        "Tala"
    ],
    "name:mal_x_preferred":[
        "\u0d24\u0d3e\u0d32"
    ],
    "name:mar_x_preferred":[
        "\u091f\u093e\u0932\u093e"
    ],
    "name:nld_x_preferred":[
        "Tala"
    ],
    "name:pan_x_preferred":[
        "\u0a1f\u0a3e\u0a32\u0a3e"
    ],
    "name:por_x_preferred":[
        "Tala"
    ],
    "name:rus_x_preferred":[
        "\u0422\u0430\u043b\u0430"
    ],
    "name:spa_x_preferred":[
        "Tala"
    ],
    "name:srp_x_preferred":[
        "\u0422\u0430\u043b\u0430"
    ],
    "name:swe_x_preferred":[
        "Tala"
    ],
    "name:tam_x_preferred":[
        "\u0b9f\u0bb2\u0bbe"
    ],
    "name:tel_x_preferred":[
        "\u0c24\u0c3e\u0c32\u0c3e"
    ],
    "name:tgl_x_preferred":[
        "Tala"
    ],
    "name:urd_x_preferred":[
        "\u062a\u0627\u0644\u0627"
    ],
    "wof:name":"Tala",
    "wof:placetype":"neighbourhood"
},
  "geometry": {"coordinates":[81.59457999999999,21.67398],"type":"Point"}
}