{
  "type": "Feature",
  "properties": {
    "gn:admin1_code":"36.0",
    "gn:admin2_code":"136.0",
    "gn:asciiname":"Wazirganj",
    "gn:country_code":"IN",
    "gn:dem":188,
    "gn:feature_class":"P",
    "gn:feature_code":"PPL",
    "gn:name":"Waz\u012brganj",
    "gn:population":0,
    "gn:timezone":"Asia/Kolkata",
    "iso:country":"IN",
    "name:bpy_x_preferred":[
        "\u09f1\u09be\u099c\u09bf\u09b0\u0997\u099e\u09cd\u099c"
    ],
    "name:ceb_x_preferred":[
        "Waz\u012brganj"
    ],
    "name:fas_x_preferred":[
        "\u0648\u0632\u06cc\u0631\u06af\u0646\u062c"
    ],
    "name:ita_x_preferred":[
        "Wazirganj"
    ],
    "name:mlg_x_preferred":[
        "Wazirganj"
    ],
    "name:msa_x_preferred":[
        "Wazirganj"
    ],
    "name:new_x_preferred":[
        "\u0935\u091c\u0940\u0930\u0917\u091e\u094d\u091c"
    ],
    "name:nld_x_preferred":[
        "Wazirganj"
    ],
    "name:pol_x_preferred":[
        "Wazirganj"
    ],
    "name:por_x_preferred":[
        "Wazirganj"
    ],
    "name:swe_x_preferred":[
        "Waz\u012brganj"
    ],
    "name:urd_x_preferred":[
        "\u0648\u0632\u06cc\u0631 \u06af\u0646\u062c"
    ],
    "name:vie_x_preferred":[
        "Wazirganj"
    ],
    "name:zho_x_preferred":[
        "\u74e6\u9f50\u5c14\u7518\u6770"
    ],
    "wof:name":"Wazirganj",
    "wof:placetype":"locality"
},
  "geometry": {"coordinates":[79.25452,28.81217],"type":"Point"}
}