{
  "type": "Feature",
  "properties": {
    "iso:country":"IN",
    "ks:ks_name":"Judawaniya",
    "ks:ks_pop":129,
    "ks:ks_type":"VILLAGE",
    "name:eng_x_preferred":[
        "Judawaniya"
    ],
    "wof:name":"Judawaniya",
    "wof:placetype":"locality",
    "wof:population":129
},
  "geometry": {"coordinates":[82.658894,23.772064],"type":"Point"}
}