{
  "type": "Feature",
  "properties": {
    "gn:admin1_code":"37.0",
    "gn:admin2_code":"413.0",
    "gn:asciiname":"Murpar",
    "gn:country_code":"IN",
    "gn:dem":382,
    "gn:feature_class":"P",
    "gn:feature_code":"PPL",
    "gn:name":"Murp\u0101r",
    "gn:population":0,
    "gn:timezone":"Asia/Kolkata",
    "iso:country":"IN",
    "wof:name":"Murpar",
    "wof:placetype":"locality"
},
  "geometry": {"coordinates":[81.47986999999998,20.36825],"type":"Point"}
}