{
  "type": "Feature",
  "properties": {
    "iso:country":"IN",
    "ks:ks_name":"Burusahi",
    "ks:ks_pop":201,
    "ks:ks_type":"HABITATION",
    "name:eng_x_preferred":[
        "Burusahi"
    ],
    "wof:name":"Burusahi",
    "wof:placetype":"locality",
    "wof:population":201
},
  "geometry": {"coordinates":[85.863626,21.106736],"type":"Point"}
}