{
  "type": "Feature",
  "properties": {
    "iso:country":"IN",
    "ks:ks_name":"Bhilaibani",
    "ks:ks_pop":194,
    "ks:ks_type":"VILLAGE",
    "name:eng_x_preferred":[
        "Bhilaibani"
    ],
    "wof:name":"Bhilaibani",
    "wof:placetype":"locality",
    "wof:population":194
},
  "geometry": {"coordinates":[87.506109,22.716235],"type":"Point"}
}