{
  "type": "Feature",
  "properties": {
    "gn:admin1_code":"19.0",
    "gn:admin2_code":"582.0",
    "gn:asciiname":"Battalapalli",
    "gn:country_code":"IN",
    "gn:dem":908,
    "gn:feature_class":"P",
    "gn:feature_code":"PPL",
    "gn:name":"Battalapalli",
    "gn:population":0,
    "gn:timezone":"Asia/Kolkata",
    "iso:country":"IN",
    "wof:name":"Battalapalli",
    "wof:placetype":"locality"
},
  "geometry": {"coordinates":[77.95851,13.43987],"type":"Point"}
}