{
  "type": "Feature",
  "properties": {
    "gn:admin1_code":"11",
    "gn:admin2_code":"23.0",
    "gn:asciiname":"Khij",
    "gn:country_code":"IN",
    "gn:dem":1905,
    "gn:feature_class":"P",
    "gn:feature_code":"PPL",
    "gn:name":"Khij",
    "gn:population":0,
    "gn:timezone":"Asia/Kolkata",
    "iso:country":"IN",
    "name:fas_x_preferred":[
        "\u062e\u06cc\u062c"
    ],
    "wof:name":"Khij",
    "wof:placetype":"locality"
},
  "geometry": {"coordinates":[76.27800999999999,32.75614],"type":"Point"}
}