{
  "type": "Feature",
  "properties": {
    "gn:admin1_code":"36",
    "gn:admin2_code":"132.0",
    "gn:asciiname":"Abdullahpur",
    "gn:country_code":"IN",
    "gn:dem":309,
    "gn:feature_class":"P",
    "gn:feature_code":"PPL",
    "gn:name":"Abdull\u0101hpur",
    "gn:population":0,
    "gn:timezone":"Asia/Kolkata",
    "iso:country":"IN",
    "wof:name":"Abdullahpur",
    "wof:placetype":"locality"
},
  "geometry": {"coordinates":[77.6377,30.1723],"type":"Point"}
}