{
  "type": "Feature",
  "properties": {
    "iso:country":"IN",
    "ks:ks_name":"Basantpur Urf Mohiuddinpur",
    "ks:ks_pop":1548,
    "ks:ks_type":"VILLAGE",
    "name:eng_x_preferred":[
        "Basantpur Urf Mohiuddinpur"
    ],
    "wof:name":"Basantpur Urf Mohiuddinpur",
    "wof:placetype":"locality",
    "wof:population":1548
},
  "geometry": {"coordinates":[85.443512,25.721106],"type":"Point"}
}