{
  "type": "Feature",
  "properties": {
    "iso:country":"IN",
    "ks:ks_name":"Paikpadar",
    "ks:ks_pop":72,
    "ks:ks_type":"VILLAGE",
    "name:eng_x_preferred":[
        "Paikpadar"
    ],
    "wof:name":"Paikpadar",
    "wof:placetype":"locality",
    "wof:population":72
},
  "geometry": {"coordinates":[82.896394,19.377045],"type":"Point"}
}