{
  "type": "Feature",
  "properties": {
    "iso:country":"IN",
    "ks:ks_alt_nam":"Mulgam faliya",
    "ks:ks_name":"Mulgam Faliya",
    "ks:ks_pop":256,
    "ks:ks_type":"HABITATION",
    "name:eng_x_preferred":[
        "Mulgam Faliya"
    ],
    "wof:name":"Mulgam Faliya",
    "wof:placetype":"locality",
    "wof:population":256
},
  "geometry": {"coordinates":[73.35392299999999,20.393007],"type":"Point"}
}