{
  "type": "Feature",
  "properties": {
    "iso:country":"IN",
    "ks:ks_name":"Nadpura",
    "ks:ks_pop":783,
    "ks:ks_type":"HABITATION",
    "name:eng_x_preferred":[
        "Nadpura"
    ],
    "wof:name":"Nadpura",
    "wof:placetype":"locality",
    "wof:population":783
},
  "geometry": {"coordinates":[72.980306,22.436944],"type":"Point"}
}