{
  "type": "Feature",
  "properties": {
    "gn:admin1_code":"9.0",
    "gn:admin2_code":"485.0",
    "gn:asciiname":"Malipara Para",
    "gn:country_code":"IN",
    "gn:dem":287,
    "gn:feature_class":"P",
    "gn:feature_code":"PPL",
    "gn:name":"M\u0101lipara Para",
    "gn:population":0,
    "gn:timezone":"Asia/Kolkata",
    "iso:country":"IN",
    "wof:name":"Malipara Para",
    "wof:placetype":"locality"
},
  "geometry": {"coordinates":[74.34945999999999,22.87874],"type":"Point"}
}