{
  "type": "Feature",
  "properties": {
    "iso:country":"IN",
    "ks:ks_name":"Harijanwasti Dund",
    "ks:ks_pop":184,
    "ks:ks_type":"HABITATION",
    "name:eng_x_preferred":[
        "Harijanwasti Dund"
    ],
    "wof:name":"Harijanwasti Dund",
    "wof:placetype":"locality",
    "wof:population":184
},
  "geometry": {"coordinates":[73.82901,17.739346],"type":"Point"}
}