{
  "type": "Feature",
  "properties": {
    "iso:country":"IN",
    "ks:ks_name":"Manthoni",
    "ks:ks_pop":1853,
    "ks:ks_type":"HABITATION",
    "name:eng_x_preferred":[
        "Manthoni"
    ],
    "wof:name":"Manthoni",
    "wof:placetype":"locality",
    "wof:population":1853
},
  "geometry": {"coordinates":[76.52074399999999,11.014001],"type":"Point"}
}