{
  "type": "Feature",
  "properties": {
    "gn:admin1_code":"34.0",
    "gn:admin2_code":"219.0",
    "gn:asciiname":"Daur Chhapra",
    "gn:country_code":"IN",
    "gn:dem":61,
    "gn:feature_class":"P",
    "gn:feature_code":"PPL",
    "gn:name":"Daur Chhapra",
    "gn:population":0,
    "gn:timezone":"Asia/Kolkata",
    "iso:country":"IN",
    "ks:ks_name":"Daur Chhapra",
    "ks:ks_pop":748,
    "ks:ks_type":"VILLAGE",
    "name:eng_x_preferred":[
        "Daur Chhapra"
    ],
    "wof:name":"Daur Chhapra",
    "wof:placetype":"locality",
    "wof:population":748
},
  "geometry": {"coordinates":[84.95266599999999,26.003656],"type":"Point"}
}