{
  "type": "Feature",
  "properties": {
    "gn:admin1_code":"25.0",
    "gn:admin2_code":"604.0",
    "gn:asciiname":"Tandarai",
    "gn:country_code":"IN",
    "gn:dem":77,
    "gn:feature_class":"P",
    "gn:feature_code":"PPL",
    "gn:name":"Tandarai",
    "gn:population":0,
    "gn:timezone":"Asia/Kolkata",
    "iso:country":"IN",
    "name:ceb_x_preferred":[
        "Tandarai"
    ],
    "name:swe_x_preferred":[
        "Tandarai"
    ],
    "name:tam_x_preferred":[
        "\u0ba4\u0ba3\u0bcd\u0b9f\u0bb0\u0bc8"
    ],
    "wof:name":"Tandarai",
    "wof:placetype":"locality"
},
  "geometry": {"coordinates":[79.67348,12.60422],"type":"Point"}
}