{
  "type": "Feature",
  "properties": {
    "iso:country":"IN",
    "ks:ks_name":"Hoshkatta",
    "ks:ks_pop":250,
    "ks:ks_type":"HABITATION",
    "name:eng_x_preferred":[
        "Hoshkatta"
    ],
    "wof:name":"Hoshkatta",
    "wof:placetype":"locality",
    "wof:population":250
},
  "geometry": {"coordinates":[74.359583,14.554884],"type":"Point"}
}