{
  "type": "Feature",
  "properties": {
    "iso:country":"IN",
    "ks:ks_name":"Gangubasti",
    "ks:ks_pop":336,
    "ks:ks_type":"HABITATION",
    "name:eng_x_preferred":[
        "Gangubasti"
    ],
    "wof:name":"Gangubasti",
    "wof:placetype":"locality",
    "wof:population":336
},
  "geometry": {"coordinates":[84.718255,22.305772],"type":"Point"}
}