{
  "type": "Feature",
  "properties": {
    "iso:country":"IN",
    "ks:ks_name":"Walkundewasti",
    "ks:ks_pop":150,
    "ks:ks_type":"HABITATION",
    "name:eng_x_preferred":[
        "Walkundewasti"
    ],
    "wof:name":"Walkundewasti",
    "wof:placetype":"locality",
    "wof:population":150
},
  "geometry": {"coordinates":[75.050984,17.785587],"type":"Point"}
}