{
  "type": "Feature",
  "properties": {
    "iso:country":"IN",
    "ks:ks_name":"Korlagundi",
    "ks:ks_pop":20,
    "ks:ks_type":"HABITATION",
    "name:eng_x_preferred":[
        "Korlagundi"
    ],
    "wof:name":"Korlagundi",
    "wof:placetype":"locality",
    "wof:population":20
},
  "geometry": {"coordinates":[74.870029,14.216992],"type":"Point"}
}