{
  "type": "Feature",
  "properties": {
    "gn:admin1_code":"40",
    "gn:admin2_code":"532.0",
    "gn:asciiname":"Lakshmi Sagar",
    "gn:country_code":"IN",
    "gn:dem":228,
    "gn:feature_class":"P",
    "gn:feature_code":"PPL",
    "gn:name":"Lakshmi Sag\u0101r",
    "gn:population":0,
    "gn:timezone":"Asia/Kolkata",
    "iso:country":"IN",
    "ks:ks_name":"Laxmisagar",
    "ks:ks_pop":520,
    "ks:ks_type":"VILLAGE",
    "ks:ks_uagg_main":0,
    "name:eng_x_preferred":[
        "Laxmisagar"
    ],
    "wof:name":"Laxmisagar",
    "wof:placetype":"neighbourhood",
    "wof:population":520
},
  "geometry": {"coordinates":[78.753766,19.053627],"type":"Point"}
}