{
  "type": "Feature",
  "properties": {
    "iso:country":"IN",
    "ks:ks_name":"Darrapara",
    "ks:ks_pop":382,
    "ks:ks_type":"HABITATION",
    "name:eng_x_preferred":[
        "Darrapara"
    ],
    "wof:name":"Darrapara",
    "wof:placetype":"locality",
    "wof:population":382
},
  "geometry": {"coordinates":[83.74360299999999,22.332464],"type":"Point"}
}