{
  "type": "Feature",
  "properties": {
    "gn:admin1_code":"12.0",
    "gn:admin2_code":"010",
    "gn:asciiname":"Tsunt Wali War",
    "gn:country_code":"IN",
    "gn:dem":2041,
    "gn:feature_class":"P",
    "gn:feature_code":"PPL",
    "gn:name":"Ts\u016bnt Wali War",
    "gn:population":0,
    "gn:timezone":"Asia/Kolkata",
    "iso:country":"IN",
    "name:eng_x_preferred":[
        "Ts\u016bnt Wali War"
    ],
    "name:eng_x_variant":[
        "Ts\u016bnt Wali W\u0101r"
    ],
    "wof:name":"Tsunt Wali War",
    "wof:placetype":"locality"
},
  "geometry": {"coordinates":[74.74414,34.28552],"type":"Point"}
}