{
  "type": "Feature",
  "properties": {
    "iso:country":"IN",
    "ks:ks_name":"Chataurara",
    "ks:ks_pop":479,
    "ks:ks_type":"VILLAGE",
    "ks:ks_uagg_main":0,
    "name:eng_x_preferred":[
        "Chataurara"
    ],
    "wof:name":"Chataurara",
    "wof:placetype":"neighbourhood",
    "wof:population":479
},
  "geometry": {"coordinates":[82.853707,26.68226],"type":"Point"}
}