{
  "type": "Feature",
  "properties": {
    "iso:country":"IN",
    "ks:ks_name":"Kambale Lavgan",
    "ks:ks_pop":561,
    "ks:ks_type":"VILLAGE",
    "name:eng_x_preferred":[
        "Kambale Lavgan"
    ],
    "wof:name":"Kambale Lavgan",
    "wof:placetype":"locality",
    "wof:population":561
},
  "geometry": {"coordinates":[73.263577,17.247416],"type":"Point"}
}