{
  "type": "Feature",
  "properties": {
    "gn:admin1_code":"11",
    "gn:admin2_code":"24.0",
    "gn:asciiname":"Sohran",
    "gn:country_code":"IN",
    "gn:dem":689,
    "gn:feature_class":"P",
    "gn:feature_code":"PPL",
    "gn:name":"Sohran",
    "gn:population":0,
    "gn:timezone":"Asia/Kolkata",
    "iso:country":"IN",
    "name:fas_x_preferred":[
        "\u0633\u0647\u0631\u0627\u0646"
    ],
    "wof:name":"Sohran",
    "wof:placetype":"locality"
},
  "geometry": {"coordinates":[76.27081,31.94911],"type":"Point"}
}