{
  "type": "Feature",
  "properties": {
    "iso:country":"IN",
    "ks:ks_alt_nam":"L\u0101lpur Mirz\u0101pur",
    "ks:ks_name":"Lalpur Mirzapur",
    "ks:ks_type":"VILLAGE",
    "name:eng_x_preferred":[
        "Lalpur Mirzapur"
    ],
    "name:eng_x_variant":[
        "L\u0101lpur Mirz\u0101pur"
    ],
    "wof:name":"Lalpur Mirzapur",
    "wof:placetype":"locality"
},
  "geometry": {"coordinates":[80.036209,27.15473],"type":"Point"}
}