{
  "type": "Feature",
  "properties": {
    "gn:admin1_code":"37",
    "gn:admin2_code":"408.0",
    "gn:asciiname":"Shikari Mahka",
    "gn:country_code":"IN",
    "gn:dem":341,
    "gn:feature_class":"P",
    "gn:feature_code":"PPL",
    "gn:name":"Shik\u0101r\u012b Mahka",
    "gn:population":0,
    "gn:timezone":"Asia/Kolkata",
    "iso:country":"IN",
    "ks:ks_alt_nam":"Shik\u0101r\u012b Mahka",
    "ks:ks_name":"Shikari Mahka",
    "ks:ks_pop":1143,
    "ks:ks_type":"VILLAGE",
    "name:eng_x_preferred":[
        "Shikari Mahka"
    ],
    "name:eng_x_variant":[
        "Shik\u0101r\u012b Mahka"
    ],
    "wof:name":"Shikari Mahka",
    "wof:placetype":"locality",
    "wof:population":1143
},
  "geometry": {"coordinates":[80.68061299999999,21.004274],"type":"Point"}
}