{
  "type": "Feature",
  "properties": {
    "iso:country":"IN",
    "ks:ks_name":"Changmaji Mikir Pathar",
    "ks:ks_pop":1513,
    "ks:ks_type":"VILLAGE",
    "ks:ks_uagg_main":0,
    "name:eng_x_preferred":[
        "Changmaji Mikir Pathar"
    ],
    "wof:name":"Changmaji Mikir Pathar",
    "wof:placetype":"neighbourhood",
    "wof:population":1513
},
  "geometry": {"coordinates":[92.819513,26.116295],"type":"Point"}
}