{
  "type": "Feature",
  "properties": {
    "iso:country":"IN",
    "ks:ks_name":"Madhupura",
    "ks:ks_pop":118,
    "ks:ks_type":"VILLAGE",
    "name:eng_x_preferred":[
        "Madhupura"
    ],
    "wof:name":"Madhupura",
    "wof:placetype":"locality",
    "wof:population":118
},
  "geometry": {"coordinates":[87.032403,21.963311],"type":"Point"}
}