{
  "type": "Feature",
  "properties": {
    "iso:country":"IN",
    "ks:ks_name":"Lachana Gunth",
    "ks:ks_pop":99,
    "ks:ks_type":"HABITATION",
    "name:eng_x_preferred":[
        "Lachana Gunth"
    ],
    "wof:name":"Lachana Gunth",
    "wof:placetype":"locality",
    "wof:population":99
},
  "geometry": {"coordinates":[79.83926700000001,29.648531],"type":"Point"}
}