{
  "type": "Feature",
  "properties": {
    "iso:country":"IN",
    "ks:ks_name":"Shivasagara",
    "ks:ks_pop":110,
    "ks:ks_type":"HABITATION",
    "name:eng_x_preferred":[
        "Shivasagara"
    ],
    "wof:name":"Shivasagara",
    "wof:placetype":"locality",
    "wof:population":110
},
  "geometry": {"coordinates":[75.968796,12.944146],"type":"Point"}
}