{
  "type": "Feature",
  "properties": {
    "gn:admin1_code":"38",
    "gn:admin2_code":"367.0",
    "gn:asciiname":"Tamra",
    "gn:country_code":"IN",
    "gn:dem":418,
    "gn:feature_class":"P",
    "gn:feature_code":"PPL",
    "gn:name":"Tamra",
    "gn:population":0,
    "gn:timezone":"Asia/Kolkata",
    "iso:country":"IN",
    "wof:name":"Tamra",
    "wof:placetype":"locality"
},
  "geometry": {"coordinates":[84.50995,22.68769],"type":"Point"}
}