{
  "type": "Feature",
  "properties": {
    "iso:country":"IN",
    "ks:ks_alt_nam":"Akna-I",
    "ks:ks_name":"Akna-i",
    "ks:ks_pop":599,
    "ks:ks_type":"HABITATION",
    "name:eng_x_preferred":[
        "Akna-i"
    ],
    "wof:name":"Akna-i",
    "wof:placetype":"locality",
    "wof:population":599
},
  "geometry": {"coordinates":[86.844463,22.248142],"type":"Point"}
}