{
  "type": "Feature",
  "properties": {
    "gn:admin1_code":"36",
    "gn:admin2_code":"176.0",
    "gn:asciiname":"Gjan Khera",
    "gn:country_code":"IN",
    "gn:dem":121,
    "gn:feature_class":"P",
    "gn:feature_code":"PPL",
    "gn:name":"Gj\u0101n Khera",
    "gn:population":0,
    "gn:timezone":"Asia/Kolkata",
    "iso:country":"IN",
    "ks:ks_name":"Gyan Khera",
    "ks:ks_pop":470,
    "ks:ks_type":"HABITATION",
    "ks:ks_uagg_main":0,
    "name:eng_x_preferred":[
        "Gyan Khera"
    ],
    "wof:name":"Gyan Khera",
    "wof:placetype":"neighbourhood",
    "wof:population":470
},
  "geometry": {"coordinates":[81.302269,26.545],"type":"Point"}
}