{
  "type": "Feature",
  "properties": {
    "iso:country":"IN",
    "ks:ks_name":"Madathiparambu",
    "ks:ks_pop":984,
    "ks:ks_type":"HABITATION",
    "name:eng_x_preferred":[
        "Madathiparambu"
    ],
    "wof:name":"Madathiparambu",
    "wof:placetype":"locality",
    "wof:population":984
},
  "geometry": {"coordinates":[76.33302399999999,9.899815],"type":"Point"}
}