{
  "type": "Feature",
  "properties": {
    "iso:country":"IN",
    "ks:ks_alt_nam":"BADALI",
    "ks:ks_name":"Badali",
    "ks:ks_pop":4123,
    "ks:ks_type":"HABITATION",
    "name:eng_x_preferred":[
        "Badali"
    ],
    "wof:name":"Badali",
    "wof:placetype":"locality",
    "wof:population":4123
},
  "geometry": {"coordinates":[81.798113,18.162523],"type":"Point"}
}