{
  "type": "Feature",
  "properties": {
    "iso:country":"IN",
    "ks:ks_name":"Pradhan Para Bazrapur",
    "ks:ks_pop":1195,
    "ks:ks_type":"HABITATION",
    "name:eng_x_preferred":[
        "Pradhan Para Bazrapur"
    ],
    "wof:name":"Pradhan Para Bazrapur",
    "wof:placetype":"locality",
    "wof:population":1195
},
  "geometry": {"coordinates":[89.775898,26.432431],"type":"Point"}
}