{
  "type": "Feature",
  "properties": {
    "iso:country":"IN",
    "ks:ks_name":"Pachim Suba",
    "ks:ks_pop":502,
    "ks:ks_type":"HABITATION",
    "name:eng_x_preferred":[
        "Pachim Suba"
    ],
    "wof:name":"Pachim Suba",
    "wof:placetype":"locality",
    "wof:population":502
},
  "geometry": {"coordinates":[91.201444,26.070566],"type":"Point"}
}