{
  "type": "Feature",
  "properties": {
    "gn:admin1_code":"10.0",
    "gn:admin2_code":"73.0",
    "gn:asciiname":"Ahun",
    "gn:country_code":"IN",
    "gn:dem":250,
    "gn:feature_class":"P",
    "gn:feature_code":"PPL",
    "gn:name":"Ah\u016bn",
    "gn:population":0,
    "gn:timezone":"Asia/Kolkata",
    "iso:country":"IN",
    "name:cat_x_preferred":[
        "A\u00fcn"
    ],
    "name:ceb_x_preferred":[
        "Ahun"
    ],
    "name:deu_x_preferred":[
        "Ahun"
    ],
    "name:epo_x_preferred":[
        "Ahun"
    ],
    "name:eus_x_preferred":[
        "Aiun"
    ],
    "name:fra_x_preferred":[
        "Ahun"
    ],
    "name:hun_x_preferred":[
        "Ahun"
    ],
    "name:ind_x_preferred":[
        "Ahun"
    ],
    "name:ita_x_preferred":[
        "Ahun"
    ],
    "name:kaz_x_preferred":[
        "\u0410\u0435\u043d"
    ],
    "name:lat_x_preferred":[
        "Acitodunum"
    ],
    "name:msa_x_preferred":[
        "Ahun"
    ],
    "name:nld_x_preferred":[
        "Ahun"
    ],
    "name:oci_x_preferred":[
        "Aiun"
    ],
    "name:pms_x_preferred":[
        "Ahun"
    ],
    "name:pol_x_preferred":[
        "Ahun"
    ],
    "name:por_x_preferred":[
        "Ahun"
    ],
    "name:ron_x_preferred":[
        "Ahun"
    ],
    "name:rus_x_preferred":[
        "\u0410\u044d\u043d"
    ],
    "name:slk_x_preferred":[
        "Ahun"
    ],
    "name:slv_x_preferred":[
        "Ahun"
    ],
    "name:spa_x_preferred":[
        "Ahun"
    ],
    "name:sqi_x_preferred":[
        "Ahun"
    ],
    "name:srp_x_preferred":[
        "\u0410\u0435\u043d"
    ],
    "name:swe_x_preferred":[
        "Ahun"
    ],
    "name:ukr_x_preferred":[
        "\u0410\u0435\u043d"
    ],
    "name:uzb_x_preferred":[
        "Ahun"
    ],
    "name:vie_x_preferred":[
        "Ahun"
    ],
    "name:vol_x_preferred":[
        "Ahun"
    ],
    "name:war_x_preferred":[
        "Ahun"
    ],
    "wof:name":"Ahun",
    "wof:placetype":"locality"
},
  "geometry": {"coordinates":[76.67950999999999,29.78638],"type":"Point"}
}