{
  "type": "Feature",
  "properties": {
    "iso:country":"IN",
    "ks:ks_name":"Heregallu",
    "ks:ks_pop":171,
    "ks:ks_type":"HABITATION",
    "name:eng_x_preferred":[
        "Heregallu"
    ],
    "wof:name":"Heregallu",
    "wof:placetype":"locality",
    "wof:population":171
},
  "geometry": {"coordinates":[75.114214,13.867518],"type":"Point"}
}