{
  "type": "Feature",
  "properties": {
    "gn:admin1_code":"25.0",
    "gn:admin2_code":"602.0",
    "gn:asciiname":"Ramasamudram",
    "gn:country_code":"IN",
    "gn:dem":136,
    "gn:feature_class":"P",
    "gn:feature_code":"PPL",
    "gn:name":"R\u0101masamudram",
    "gn:population":0,
    "gn:timezone":"Asia/Kolkata",
    "iso:country":"IN",
    "name:pam_x_preferred":[
        "Ramasamudram"
    ],
    "name:tam_x_preferred":[
        "\u0bb0\u0bbe\u0bae\u0b9a\u0bae\u0bc1\u0ba4\u0bcd\u0ba4\u0bbf\u0bb0\u0bae\u0bcd"
    ],
    "name:tel_x_preferred":[
        "\u0c30\u0c3e\u0c2e\u0c38\u0c2e\u0c41\u0c26\u0c4d\u0c30\u0c02"
    ],
    "name:tgl_x_preferred":[
        "Ramasamudram"
    ],
    "name:urd_x_preferred":[
        "\u0631\u0627\u0645\u0627\u0633\u0645\u062f\u0631\u0645"
    ],
    "name:vie_x_preferred":[
        "Ramasamudram"
    ],
    "wof:name":"Ramasamudram",
    "wof:placetype":"locality"
},
  "geometry": {"coordinates":[79.51560000000001,13.22793],"type":"Point"}
}