{
  "type": "Feature",
  "properties": {
    "iso:country":"IN",
    "ks:ks_name":"Bharanya",
    "ks:ks_pop":0,
    "ks:ks_type":"VILLAGE",
    "name:eng_x_preferred":[
        "Bharanya"
    ],
    "wof:name":"Bharanya",
    "wof:placetype":"locality",
    "wof:population":0
},
  "geometry": {"coordinates":[75.71323099999999,22.074158],"type":"Point"}
}