{
  "type": "Feature",
  "properties": {
    "gn:admin1_code":"36",
    "gn:admin2_code":"191.0",
    "gn:asciiname":"Karasar",
    "gn:country_code":"IN",
    "gn:dem":76,
    "gn:feature_class":"P",
    "gn:feature_code":"PPL",
    "gn:name":"Kar\u0101sar",
    "gn:population":0,
    "gn:timezone":"Asia/Kolkata",
    "iso:country":"IN",
    "ks:ks_alt_nam":"Kar\u0101sar",
    "ks:ks_name":"Karasar",
    "ks:ks_type":"VILLAGE",
    "ks:ks_uagg_main":0,
    "name:eng_x_preferred":[
        "Karasar"
    ],
    "name:eng_x_variant":[
        "Kar\u0101sar"
    ],
    "wof:name":"Karasar",
    "wof:placetype":"neighbourhood"
},
  "geometry": {"coordinates":[83.35460999999999,25.918904],"type":"Point"}
}