{
  "type": "Feature",
  "properties": {
    "gn:admin1_code":"24",
    "gn:admin2_code":"103.0",
    "gn:asciiname":"Mandrela",
    "gn:country_code":"IN",
    "gn:dem":302,
    "gn:feature_class":"P",
    "gn:feature_code":"PPL",
    "gn:name":"Mandrela",
    "gn:population":0,
    "gn:timezone":"Asia/Kolkata",
    "iso:country":"IN",
    "name:und_x_variant":[
        "Mandela",
        "Mandrela"
    ],
    "wof:name":"Mandrela",
    "wof:placetype":"locality"
},
  "geometry": {"coordinates":[75.43514,28.31365],"type":"Point"}
}