{
  "type": "Feature",
  "properties": {
    "iso:country":"IN",
    "ks:ks_name":"Dostpur Khadauli",
    "ks:ks_pop":3756,
    "ks:ks_type":"VILLAGE",
    "ks:ks_uagg_main":0,
    "name:eng_x_preferred":[
        "Dostpur Khadauli"
    ],
    "wof:name":"Dostpur Khadauli",
    "wof:placetype":"locality",
    "wof:population":3756
},
  "geometry": {"coordinates":[85.53076799999999,26.625779],"type":"Point"}
}