{
  "type": "Feature",
  "properties": {
    "gn:admin1_code":"36",
    "gn:admin2_code":"197.0",
    "gn:asciiname":"Bhikhampur",
    "gn:country_code":"IN",
    "gn:dem":84,
    "gn:feature_class":"P",
    "gn:feature_code":"PPL",
    "gn:name":"Bhikhampur",
    "gn:population":0,
    "gn:timezone":"Asia/Kolkata",
    "iso:country":"IN",
    "ks:ks_name":"Bhikhampur",
    "ks:ks_pop":1645,
    "ks:ks_type":"VILLAGE",
    "ks:ks_uagg_main":0,
    "name:eng_x_preferred":[
        "Bhikhampur"
    ],
    "wof:name":"Bhikhampur",
    "wof:placetype":"neighbourhood",
    "wof:population":1645
},
  "geometry": {"coordinates":[82.852847,25.235187],"type":"Point"}
}