{
  "type": "Feature",
  "properties": {
    "gn:admin1_code":"16.0",
    "gn:admin2_code":"510",
    "gn:asciiname":"Kosdani",
    "gn:country_code":"IN",
    "gn:dem":272,
    "gn:feature_class":"P",
    "gn:feature_code":"PPL",
    "gn:name":"Kosdani",
    "gn:population":0,
    "gn:timezone":"Asia/Kolkata",
    "iso:country":"IN",
    "wof:name":"Kosdani",
    "wof:placetype":"locality"
},
  "geometry": {"coordinates":[77.92265999999999,19.9224],"type":"Point"}
}