{
  "type": "Feature",
  "properties": {
    "iso:country":"IN",
    "ks:ks_name":"Thathankattlai",
    "ks:ks_pop":223,
    "ks:ks_type":"HABITATION",
    "name:eng_x_preferred":[
        "Thathankattlai"
    ],
    "wof:name":"Thathankattlai",
    "wof:placetype":"locality",
    "wof:population":223
},
  "geometry": {"coordinates":[79.699241,10.850083],"type":"Point"}
}