{
  "type": "Feature",
  "properties": {
    "iso:country":"IN",
    "ks:ks_name":"Kattampally",
    "ks:ks_pop":430,
    "ks:ks_type":"HABITATION",
    "name:eng_x_preferred":[
        "Kattampally"
    ],
    "wof:name":"Kattampally",
    "wof:placetype":"locality",
    "wof:population":430
},
  "geometry": {"coordinates":[76.951476,8.865915],"type":"Point"}
}