{
  "type": "Feature",
  "properties": {
    "iso:country":"IN",
    "ks:ks_alt_nam":"South ponnanpadugai",
    "ks:ks_name":"South Ponnanpadugai",
    "ks:ks_pop":83,
    "ks:ks_type":"HABITATION",
    "name:eng_x_preferred":[
        "South Ponnanpadugai"
    ],
    "wof:name":"South Ponnanpadugai",
    "wof:placetype":"locality",
    "wof:population":83
},
  "geometry": {"coordinates":[77.488619,9.74339],"type":"Point"}
}