{
  "type": "Feature",
  "properties": {
    "gn:admin1_code":"36.0",
    "gn:admin2_code":"136.0",
    "gn:asciiname":"Piyas",
    "gn:country_code":"IN",
    "gn:dem":182,
    "gn:feature_class":"P",
    "gn:feature_code":"PPL",
    "gn:name":"P\u012by\u0101s",
    "gn:population":0,
    "gn:timezone":"Asia/Kolkata",
    "iso:country":"IN",
    "wof:name":"Piyas",
    "wof:placetype":"locality"
},
  "geometry": {"coordinates":[79.09631999999998,28.49155],"type":"Point"}
}