{
  "type": "Feature",
  "properties": {
    "gn:admin1_code":"36.0",
    "gn:admin2_code":"165.0",
    "gn:asciiname":"Itwa Jalaun",
    "gn:country_code":"IN",
    "gn:dem":145,
    "gn:feature_class":"P",
    "gn:feature_code":"PPL",
    "gn:name":"Itwa J\u0101laun",
    "gn:population":0,
    "gn:timezone":"Asia/Kolkata",
    "iso:country":"IN",
    "ks:ks_name":"Itwa Jalaun",
    "ks:ks_pop":855,
    "ks:ks_type":"HABITATION",
    "name:eng_x_preferred":[
        "Itwa Jalaun"
    ],
    "wof:name":"Itwa Jalaun",
    "wof:placetype":"locality",
    "wof:population":855
},
  "geometry": {"coordinates":[79.3711,26.021],"type":"Point"}
}