{
  "type": "Feature",
  "properties": {
    "gn:admin1_code":"11.0",
    "gn:admin2_code":"32.0",
    "gn:asciiname":"Sunkair",
    "gn:country_code":"IN",
    "gn:dem":2380,
    "gn:feature_class":"P",
    "gn:feature_code":"PPL",
    "gn:name":"Sunkair",
    "gn:population":0,
    "gn:timezone":"Asia/Kolkata",
    "iso:country":"IN",
    "wof:name":"Sunkair",
    "wof:placetype":"locality"
},
  "geometry": {"coordinates":[77.64411,30.70609],"type":"Point"}
}