{
  "type": "Feature",
  "properties": {
    "iso:country":"IN",
    "ks:ks_name":"Tharma",
    "ks:ks_pop":375,
    "ks:ks_type":"VILLAGE",
    "ks:ks_uagg_main":0,
    "name:eng_x_preferred":[
        "Tharma"
    ],
    "wof:name":"Tharma",
    "wof:placetype":"neighbourhood",
    "wof:population":375
},
  "geometry": {"coordinates":[85.71287700000001,26.093796],"type":"Point"}
}