{
  "type": "Feature",
  "properties": {
    "iso:country":"IN",
    "ks:ks_name":"Jamnemal",
    "ks:ks_pop":172,
    "ks:ks_type":"HABITATION",
    "name:eng_x_preferred":[
        "Jamnemal"
    ],
    "wof:name":"Jamnemal",
    "wof:placetype":"locality",
    "wof:population":172
},
  "geometry": {"coordinates":[73.699879,20.545886],"type":"Point"}
}