{
  "type": "Feature",
  "properties": {
    "gn:admin1_code":"30.0",
    "gn:admin2_code":"247.0",
    "gn:asciiname":"Sebba",
    "gn:country_code":"IN",
    "gn:dem":685,
    "gn:feature_class":"P",
    "gn:feature_code":"PPL",
    "gn:name":"Sebba",
    "gn:population":0,
    "gn:timezone":"Asia/Kolkata",
    "iso:country":"IN",
    "name:ben_x_preferred":[
        "\u09b8\u09c7\u09ac\u09cd\u09ac\u09be"
    ],
    "name:deu_x_preferred":[
        "Sebba"
    ],
    "name:fas_x_preferred":[
        "\u0633\u0628\u0627"
    ],
    "name:fra_x_preferred":[
        "Sebba"
    ],
    "name:heb_x_preferred":[
        "\u05e1\u05d1\u05d4"
    ],
    "name:hin_x_preferred":[
        "\u0938\u0947\u092c\u094d\u092c\u093e"
    ],
    "name:hun_x_preferred":[
        "Sebba"
    ],
    "name:ind_x_preferred":[
        "Sebba"
    ],
    "name:ita_x_preferred":[
        "Sebba"
    ],
    "name:kor_x_preferred":[
        "\uc138\ubc14"
    ],
    "name:nld_x_preferred":[
        "Sebba"
    ],
    "name:pol_x_preferred":[
        "Sebba"
    ],
    "name:por_x_preferred":[
        "Sebba"
    ],
    "name:ron_x_preferred":[
        "Sebba"
    ],
    "name:rus_x_preferred":[
        "\u0421\u0435\u0431\u0431\u0430"
    ],
    "name:swe_x_preferred":[
        "Sebba"
    ],
    "name:tur_x_preferred":[
        "Sebba"
    ],
    "name:ukr_x_preferred":[
        "\u0421\u0435\u0431\u0431\u0430"
    ],
    "name:urd_x_preferred":[
        "\u0633\u06cc\u0628\u0627"
    ],
    "name:vie_x_preferred":[
        "Sebba"
    ],
    "name:war_x_preferred":[
        "Sebba"
    ],
    "name:zho_cn_x_preferred":[
        "\u585e\u5df4"
    ],
    "name:zho_tw_x_preferred":[
        "\u585e\u5df4"
    ],
    "wof:name":"Sebba",
    "wof:placetype":"locality"
},
  "geometry": {"coordinates":[93.02983,27.22767],"type":"Point"}
}