{
  "type": "Feature",
  "properties": {
    "gn:admin1_code":"30.0",
    "gn:admin2_code":"247.0",
    "gn:asciiname":"Sebba",
    "gn:country_code":"IN",
    "gn:dem":685,
    "gn:feature_class":"P",
    "gn:feature_code":"PPL",
    "gn:name":"Sebba",
    "gn:population":0,
    "gn:timezone":"Asia/Kolkata",
    "iso:country":"IN",
    "name:deu_x_preferred":[
        "Sebba"
    ],
    "name:fra_x_preferred":[
        "Sebba"
    ],
    "name:ita_x_preferred":[
        "Sebba"
    ],
    "name:nld_x_preferred":[
        "Sebba"
    ],
    "name:pol_x_preferred":[
        "Sebba"
    ],
    "name:por_x_preferred":[
        "Sebba"
    ],
    "name:ron_x_preferred":[
        "Sebba"
    ],
    "name:rus_x_preferred":[
        "\u0421\u0435\u0431\u0431\u0430"
    ],
    "name:ukr_x_preferred":[
        "\u0421\u0435\u0431\u0431\u0430"
    ],
    "name:urd_x_preferred":[
        "\u0633\u06cc\u0628\u0627"
    ],
    "name:war_x_preferred":[
        "Sebba"
    ],
    "wof:name":"Sebba",
    "wof:placetype":"locality"
},
  "geometry": {"coordinates":[93.02983,27.22767],"type":"Point"}
}