{
  "type": "Feature",
  "properties": {
    "iso:country":"IN",
    "ks:ks_name":"Maurakilla Paschim",
    "ks:ks_pop":595,
    "ks:ks_type":"HABITATION",
    "name:eng_x_preferred":[
        "Maurakilla Paschim"
    ],
    "wof:name":"Maurakilla Paschim",
    "wof:placetype":"locality",
    "wof:population":595
},
  "geometry": {"coordinates":[91.443927,23.470219],"type":"Point"}
}