{
  "type": "Feature",
  "properties": {
    "iso:country":"IN",
    "ks:ks_name":"Minjumla",
    "ks:ks_pop":0,
    "ks:ks_type":"VILLAGE",
    "name:eng_x_preferred":[
        "Minjumla"
    ],
    "wof:name":"Minjumla",
    "wof:placetype":"locality",
    "wof:population":0
},
  "geometry": {"coordinates":[84.978894,25.1589],"type":"Point"}
}