{
  "type": "Feature",
  "properties": {
    "gn:admin1_code":"24.0",
    "gn:admin2_code":"110.0",
    "gn:asciiname":"Chamanpura",
    "gn:country_code":"IN",
    "gn:dem":485,
    "gn:feature_class":"P",
    "gn:feature_code":"PPL",
    "gn:name":"Chamanpura",
    "gn:population":0,
    "gn:timezone":"Asia/Kolkata",
    "iso:country":"IN",
    "wof:name":"Chamanpura",
    "wof:placetype":"locality"
},
  "geometry": {"coordinates":[75.70544,27.23318],"type":"Point"}
}