{
  "type": "Feature",
  "properties": {
    "gn:admin1_code":"12.0",
    "gn:admin2_code":"11.0",
    "gn:asciiname":"Dupkhod",
    "gn:country_code":"IN",
    "gn:dem":2545,
    "gn:feature_class":"P",
    "gn:feature_code":"PPL",
    "gn:name":"Dupkhod",
    "gn:population":0,
    "gn:timezone":"Asia/Kolkata",
    "iso:country":"IN",
    "wof:name":"Dupkhod",
    "wof:placetype":"locality"
},
  "geometry": {"coordinates":[74.93755999999998,34.29437],"type":"Point"}
}