{
  "type": "Feature",
  "properties": {
    "gn:admin1_code":"29.0",
    "gn:admin2_code":"243.0",
    "gn:asciiname":"Payong",
    "gn:country_code":"IN",
    "gn:dem":839,
    "gn:feature_class":"P",
    "gn:feature_code":"PPL",
    "gn:name":"Payong",
    "gn:population":0,
    "gn:timezone":"Asia/Kolkata",
    "iso:country":"IN",
    "wof:name":"Payong",
    "wof:placetype":"locality"
},
  "geometry": {"coordinates":[88.44898000000001,27.10804000000001],"type":"Point"}
}