{
  "type": "Feature",
  "properties": {
    "iso:country":"IN",
    "ks:ks_name":"Gandhinagar",
    "ks:ks_pop":590,
    "ks:ks_type":"HABITATION",
    "name:eng_x_preferred":[
        "Gandhinagar"
    ],
    "wof:name":"Gandhinagar",
    "wof:placetype":"locality",
    "wof:population":590
},
  "geometry": {"coordinates":[77.04411,9.709087],"type":"Point"}
}