{
  "type": "Feature",
  "properties": {
    "iso:country":"IN",
    "ks:ks_alt_nam":"PUJARWASTI",
    "ks:ks_name":"Pujarwasti",
    "ks:ks_pop":101,
    "ks:ks_type":"HABITATION",
    "name:eng_x_preferred":[
        "Pujarwasti"
    ],
    "wof:name":"Pujarwasti",
    "wof:placetype":"locality",
    "wof:population":101
},
  "geometry": {"coordinates":[74.949781,17.36962],"type":"Point"}
}