{
  "type": "Feature",
  "properties": {
    "iso:country":"IN",
    "ks:ks_alt_nam":"bheemaiahnapalem",
    "ks:ks_name":"Bheemaiahnapalem",
    "ks:ks_pop":257,
    "ks:ks_type":"HABITATION",
    "ks:ks_uagg_main":0,
    "name:eng_x_preferred":[
        "Bheemaiahnapalem"
    ],
    "wof:name":"Bheemaiahnapalem",
    "wof:placetype":"neighbourhood",
    "wof:population":257
},
  "geometry": {"coordinates":[77.151535,13.988018],"type":"Point"}
}