{
  "type": "Feature",
  "properties": {
    "iso:country":"IN",
    "ks:ks_name":"Sunia",
    "ks:ks_pop":908,
    "ks:ks_type":"VILLAGE",
    "name:eng_x_preferred":[
        "Sunia"
    ],
    "wof:name":"Sunia",
    "wof:placetype":"locality",
    "wof:population":908
},
  "geometry": {"coordinates":[87.829944,21.901604],"type":"Point"}
}