{
  "type": "Feature",
  "properties": {
    "gn:admin1_code":"16.0",
    "gn:admin2_code":"523.0",
    "gn:asciiname":"Khatgavhan",
    "gn:country_code":"IN",
    "gn:dem":397,
    "gn:feature_class":"P",
    "gn:feature_code":"PPL",
    "gn:name":"Kh\u0101tgavh\u0101n",
    "gn:population":0,
    "gn:timezone":"Asia/Kolkata",
    "iso:country":"IN",
    "wof:name":"Khatgavhan",
    "wof:placetype":"locality"
},
  "geometry": {"coordinates":[76.36865999999998,19.12275],"type":"Point"}
}