{
  "type": "Feature",
  "properties": {
    "gn:admin1_code":"23",
    "gn:admin2_code":"38.0",
    "gn:asciiname":"Nangal Khanauran",
    "gn:country_code":"IN",
    "gn:dem":490,
    "gn:feature_class":"P",
    "gn:feature_code":"PPL",
    "gn:name":"Nangal Khanaur\u0101n",
    "gn:population":0,
    "gn:timezone":"Asia/Kolkata",
    "iso:country":"IN",
    "wof:name":"Nangal Khanauran",
    "wof:placetype":"locality"
},
  "geometry": {"coordinates":[75.94329,31.85688],"type":"Point"}
}