{
  "type": "Feature",
  "properties": {
    "gn:admin1_code":"36",
    "gn:admin2_code":"191.0",
    "gn:asciiname":"Ismailpur",
    "gn:country_code":"IN",
    "gn:dem":82,
    "gn:feature_class":"P",
    "gn:feature_code":"PPL",
    "gn:name":"Ism\u0101ilpur",
    "gn:population":0,
    "gn:timezone":"Asia/Kolkata",
    "iso:country":"IN",
    "name:und_x_variant":[
        "Ism\u0101ilpur",
        "Barheti"
    ],
    "wof:name":"Ismailpur",
    "wof:placetype":"neighbourhood"
},
  "geometry": {"coordinates":[83.00458999999999,25.75906],"type":"Point"}
}