{
  "type": "Feature",
  "properties": {
    "iso:country":"IN",
    "ks:ks_name":"Tengra Khali",
    "ks:ks_pop":1074,
    "ks:ks_type":"VILLAGE",
    "ks:ks_uagg_main":0,
    "name:eng_x_preferred":[
        "Tengra Khali"
    ],
    "wof:name":"Tengra Khali",
    "wof:placetype":"neighbourhood",
    "wof:population":1074
},
  "geometry": {"coordinates":[88.64026,22.297659],"type":"Point"}
}