{
  "type": "Feature",
  "properties": {
    "iso:country":"IN",
    "ks:ks_name":"Mahtotoli",
    "ks:ks_pop":105,
    "ks:ks_type":"HABITATION",
    "name:eng_x_preferred":[
        "Mahtotoli"
    ],
    "wof:name":"Mahtotoli",
    "wof:placetype":"locality",
    "wof:population":105
},
  "geometry": {"coordinates":[85.259407,23.559005],"type":"Point"}
}