{
  "type": "Feature",
  "properties": {
    "gn:admin1_code":"39.0",
    "gn:admin2_code":"63.0",
    "gn:asciiname":"Jurchhani",
    "gn:country_code":"IN",
    "gn:dem":1837,
    "gn:feature_class":"P",
    "gn:feature_code":"PPL",
    "gn:name":"Jurchh\u0101ni",
    "gn:population":0,
    "gn:timezone":"Asia/Kolkata",
    "iso:country":"IN",
    "wof:name":"Jurchhani",
    "wof:placetype":"locality"
},
  "geometry": {"coordinates":[79.98461999999998,29.85919],"type":"Point"}
}