{
  "type": "Feature",
  "properties": {
    "iso:country":"IN",
    "ks:ks_name":"Sunda Nagar",
    "ks:ks_pop":262,
    "ks:ks_type":"VILLAGE",
    "name:eng_x_preferred":[
        "Sunda Nagar"
    ],
    "wof:name":"Sunda Nagar",
    "wof:placetype":"locality",
    "wof:population":262
},
  "geometry": {"coordinates":[72.431703,26.950325],"type":"Point"}
}