{
  "type": "Feature",
  "properties": {
    "gn:admin1_code":"35",
    "gn:admin2_code":"446.0",
    "gn:asciiname":"Dhaniyakheri Khurd",
    "gn:country_code":"IN",
    "gn:dem":428,
    "gn:feature_class":"P",
    "gn:feature_code":"PPL",
    "gn:name":"Dhaniy\u0101kheri Khurd",
    "gn:population":0,
    "gn:timezone":"Asia/Kolkata",
    "iso:country":"IN",
    "wof:name":"Dhaniyakheri Khurd",
    "wof:placetype":"locality"
},
  "geometry": {"coordinates":[77.75256,23.45596],"type":"Point"}
}