{
  "type": "Feature",
  "properties": {
    "iso:country":"IN",
    "ks:ks_name":"Jhulenbar",
    "ks:ks_pop":0,
    "ks:ks_type":"VILLAGE",
    "name:eng_x_preferred":[
        "Jhulenbar"
    ],
    "wof:name":"Jhulenbar",
    "wof:placetype":"locality",
    "wof:population":0
},
  "geometry": {"coordinates":[82.642809,19.511608],"type":"Point"}
}