{
  "type": "Feature",
  "properties": {
    "iso:country":"IN",
    "ks:ks_name":"Uttar Baligaon",
    "ks:ks_pop":303,
    "ks:ks_type":"HABITATION",
    "name:eng_x_preferred":[
        "Uttar Baligaon"
    ],
    "wof:name":"Uttar Baligaon",
    "wof:placetype":"locality",
    "wof:population":303
},
  "geometry": {"coordinates":[92.755405,25.925708],"type":"Point"}
}