{
  "type": "Feature",
  "properties": {
    "iso:country":"IN",
    "ks:ks_alt_nam":"BARUSAI",
    "ks:ks_name":"Barusai",
    "ks:ks_pop":122,
    "ks:ks_type":"HABITATION",
    "name:eng_x_preferred":[
        "Barusai"
    ],
    "wof:name":"Barusai",
    "wof:placetype":"locality",
    "wof:population":122
},
  "geometry": {"coordinates":[85.80654699999999,22.316199],"type":"Point"}
}