{
  "type": "Feature",
  "properties": {
    "gn:admin1_code":"38.0",
    "gn:admin2_code":"360.0",
    "gn:asciiname":"Sijhua",
    "gn:country_code":"IN",
    "gn:dem":582,
    "gn:feature_class":"P",
    "gn:feature_code":"PPL",
    "gn:name":"Sijhu\u0101",
    "gn:population":0,
    "gn:timezone":"Asia/Kolkata",
    "iso:country":"IN",
    "ks:ks_alt_nam":"Sijhu\u0101",
    "ks:ks_name":"Sijhua",
    "ks:ks_pop":1125,
    "ks:ks_type":"VILLAGE",
    "ks:ks_uagg_main":0,
    "name:bih_x_preferred":[
        "\u0938\u093f\u091d\u0941\u0906"
    ],
    "name:bpy_x_preferred":[
        "\u09b8\u09bf\u099d\u09c1\u09f1\u09be"
    ],
    "name:eng_x_preferred":[
        "Sijhua"
    ],
    "name:eng_x_variant":[
        "Sijhu\u0101"
    ],
    "name:ita_x_preferred":[
        "Sijhua"
    ],
    "name:msa_x_preferred":[
        "Sijhua"
    ],
    "name:nld_x_preferred":[
        "Sijhua"
    ],
    "name:por_x_preferred":[
        "Sijhua"
    ],
    "name:vie_x_preferred":[
        "Sijhua"
    ],
    "name:zho_x_preferred":[
        "\u897f\u4e45\u963f"
    ],
    "wof:name":"Sijhua",
    "wof:placetype":"neighbourhood",
    "wof:population":1125
},
  "geometry": {"coordinates":[85.38556,24.104192],"type":"Point"}
}