{
  "type": "Feature",
  "properties": {
    "iso:country":"IN",
    "ks:ks_name":"Gopinathpur",
    "ks:ks_pop":67,
    "ks:ks_type":"VILLAGE",
    "name:eng_x_preferred":[
        "Gopinathpur"
    ],
    "wof:name":"Gopinathpur",
    "wof:placetype":"locality",
    "wof:population":67
},
  "geometry": {"coordinates":[86.50828,23.970498],"type":"Point"}
}