{
  "type": "Feature",
  "properties": {
    "gn:admin1_code":"39.0",
    "gn:admin2_code":"57.0",
    "gn:asciiname":"Ung",
    "gn:country_code":"IN",
    "gn:dem":2324,
    "gn:feature_class":"P",
    "gn:feature_code":"PPL",
    "gn:name":"\u016ang",
    "gn:population":0,
    "gn:timezone":"Asia/Kolkata",
    "iso:country":"IN",
    "name:ceb_x_preferred":[
        "Ung"
    ],
    "name:deu_x_preferred":[
        "Ung"
    ],
    "name:hun_x_preferred":[
        "Ung"
    ],
    "name:nld_x_preferred":[
        "Ung"
    ],
    "name:swe_x_preferred":[
        "Ung"
    ],
    "wof:name":"Ung",
    "wof:placetype":"locality"
},
  "geometry": {"coordinates":[79.54978,30.0757],"type":"Point"}
}