{
  "type": "Feature",
  "properties": {
    "iso:country":"IN",
    "ks:ks_name":"Bamunbari West",
    "ks:ks_pop":120,
    "ks:ks_type":"HABITATION",
    "name:eng_x_preferred":[
        "Bamunbari West"
    ],
    "wof:name":"Bamunbari West",
    "wof:placetype":"locality",
    "wof:population":120
},
  "geometry": {"coordinates":[91.065288,26.419489],"type":"Point"}
}