{
  "type": "Feature",
  "properties": {
    "iso:country":"IN",
    "ks:ks_name":"Vavar",
    "ks:ks_pop":2134,
    "ks:ks_type":"VILLAGE",
    "name:eng_x_preferred":[
        "Vavar"
    ],
    "wof:name":"Vavar",
    "wof:placetype":"locality",
    "wof:population":2134
},
  "geometry": {"coordinates":[73.374456,20.341431],"type":"Point"}
}