{
  "type": "Feature",
  "properties": {
    "gn:admin1_code":"36",
    "gn:admin2_code":"162.0",
    "gn:asciiname":"Muchaha",
    "gn:country_code":"IN",
    "gn:dem":139,
    "gn:feature_class":"P",
    "gn:feature_code":"PPL",
    "gn:name":"Muchaha",
    "gn:population":0,
    "gn:timezone":"Asia/Kolkata",
    "iso:country":"IN",
    "wof:name":"Muchaha",
    "wof:placetype":"locality"
},
  "geometry": {"coordinates":[79.60366999999999,26.55225],"type":"Point"}
}