{
  "type": "Feature",
  "properties": {
    "iso:country":"IN",
    "ks:ks_alt_nam":"Manasha tilla",
    "ks:ks_name":"Manasha Tilla",
    "ks:ks_pop":607,
    "ks:ks_type":"HABITATION",
    "name:eng_x_preferred":[
        "Manasha Tilla"
    ],
    "wof:name":"Manasha Tilla",
    "wof:placetype":"locality",
    "wof:population":607
},
  "geometry": {"coordinates":[91.457966,23.50953],"type":"Point"}
}