{
  "type": "Feature",
  "properties": {
    "gn:admin1_code":"21.0",
    "gn:admin2_code":"398.0",
    "gn:asciiname":"Gadoputtu",
    "gn:country_code":"IN",
    "gn:dem":619,
    "gn:feature_class":"P",
    "gn:feature_code":"PPL",
    "gn:name":"Gadoputtu",
    "gn:population":0,
    "gn:timezone":"Asia/Kolkata",
    "iso:country":"IN",
    "name:und_x_variant":[
        "Bodonaikg\u016bda"
    ],
    "wof:name":"Gadoputtu",
    "wof:placetype":"locality"
},
  "geometry": {"coordinates":[82.43947,18.66151],"type":"Point"}
}