{
  "type": "Feature",
  "properties": {
    "iso:country":"IN",
    "ks:ks_name":"Kunjbari",
    "ks:ks_pop":0,
    "ks:ks_type":"VILLAGE",
    "name:eng_x_preferred":[
        "Kunjbari"
    ],
    "wof:name":"Kunjbari",
    "wof:placetype":"locality",
    "wof:population":0
},
  "geometry": {"coordinates":[88.083519,25.991692],"type":"Point"}
}