{
  "type": "Feature",
  "properties": {
    "iso:country":"IN",
    "ks:ks_name":"Bahavanipeta",
    "ks:ks_pop":42,
    "ks:ks_type":"HABITATION",
    "name:eng_x_preferred":[
        "Bahavanipeta"
    ],
    "wof:name":"Bahavanipeta",
    "wof:placetype":"locality",
    "wof:population":42
},
  "geometry": {"coordinates":[84.512641,18.771871],"type":"Point"}
}