{
  "type": "Feature",
  "properties": {
    "iso:country":"IN",
    "ks:ks_name":"Talebajar",
    "ks:ks_pop":684,
    "ks:ks_type":"VILLAGE",
    "name:eng_x_preferred":[
        "Talebajar"
    ],
    "wof:name":"Talebajar",
    "wof:placetype":"locality",
    "wof:population":684
},
  "geometry": {"coordinates":[73.476285,16.394341],"type":"Point"}
}