{
  "type": "Feature",
  "properties": {
    "iso:country":"IN",
    "ks:ks_name":"Ravadas",
    "ks:ks_pop":1376,
    "ks:ks_type":"VILLAGE",
    "name:eng_x_preferred":[
        "Ravadas"
    ],
    "wof:name":"Ravadas",
    "wof:placetype":"locality",
    "wof:population":1376
},
  "geometry": {"coordinates":[73.55561899999999,15.972811],"type":"Point"}
}