{
  "type": "Feature",
  "properties": {
    "iso:country":"IN",
    "ks:ks_name":"Rajpura",
    "ks:ks_pop":26,
    "ks:ks_type":"HABITATION",
    "name:eng_x_preferred":[
        "Rajpura"
    ],
    "wof:name":"Rajpura",
    "wof:placetype":"locality",
    "wof:population":26
},
  "geometry": {"coordinates":[73.26222199999999,22.515417],"type":"Point"}
}