{
  "type": "Feature",
  "properties": {
    "gn:admin1_code":"24",
    "gn:admin2_code":"114.0",
    "gn:asciiname":"Shyambhar ki Dhani",
    "gn:country_code":"IN",
    "gn:dem":149,
    "gn:feature_class":"P",
    "gn:feature_code":"PPL",
    "gn:name":"Shy\u0101mbhar ki Dhani",
    "gn:population":0,
    "gn:timezone":"Asia/Kolkata",
    "iso:country":"IN",
    "name:und_x_variant":[
        "Shy\u0101mbhar ki Dhani",
        "Si\u0101mbar"
    ],
    "wof:name":"Shyambhar ki Dhani",
    "wof:placetype":"locality"
},
  "geometry": {"coordinates":[70.30216999999999,27.03832],"type":"Point"}
}