{
  "type": "Feature",
  "properties": {
    "iso:country":"IN",
    "ks:ks_name":"Bandor",
    "ks:ks_pop":172,
    "ks:ks_type":"VILLAGE",
    "name:eng_x_preferred":[
        "Bandor"
    ],
    "wof:name":"Bandor",
    "wof:placetype":"locality",
    "wof:population":172
},
  "geometry": {"coordinates":[87.557574,24.972589],"type":"Point"}
}