{
  "type": "Feature",
  "properties": {
    "gn:admin1_code":"36",
    "gn:admin2_code":"201.0",
    "gn:asciiname":"Rupnagar",
    "gn:country_code":"IN",
    "gn:dem":171,
    "gn:feature_class":"P",
    "gn:feature_code":"PPL",
    "gn:name":"R\u016bpnagar",
    "gn:population":0,
    "gn:timezone":"Asia/Kolkata",
    "iso:country":"IN",
    "name:ara_x_preferred":[
        "\u0631\u0648\u0628 \u0646\u0627\u062c\u0627\u0631"
    ],
    "name:ben_bn_x_preferred":[
        "\u09b0\u09c2\u09aa\u09a8\u0997\u09b0"
    ],
    "name:ben_in_x_preferred":[
        "\u09b0\u09c2\u09aa\u09a8\u0997\u09b0"
    ],
    "name:ben_x_preferred":[
        "\u09b0\u09c2\u09aa\u09a8\u0997\u09b0"
    ],
    "name:bpy_x_preferred":[
        "\u09b0\u09c2\u09aa\u09a8\u0997\u09b0"
    ],
    "name:cat_x_preferred":[
        "Rupnagar"
    ],
    "name:ceb_x_preferred":[
        "Rupnagar"
    ],
    "name:deu_x_preferred":[
        "Rupnagar"
    ],
    "name:fra_x_preferred":[
        "Rupnagar"
    ],
    "name:guj_x_preferred":[
        "\u0ab0\u0ac2\u0aaa\u0abe\u0aa8\u0a97\u0ab0"
    ],
    "name:guj_x_variant":[
        "\u0ab0\u0ac1\u0aaa\u0aa8\u0a97\u0ab0"
    ],
    "name:hin_x_preferred":[
        "\u0930\u0942\u092a\u0928\u0917\u0930"
    ],
    "name:ita_x_preferred":[
        "Rupnagar"
    ],
    "name:kan_x_preferred":[
        "\u0cb0\u0cc2\u0caa\u0ccd"
    ],
    "name:mal_x_preferred":[
        "\u0d30\u0d42\u0d2a\u0d28\u0d17\u0d7c"
    ],
    "name:mar_x_preferred":[
        "\u0930\u0942\u092a\u0928\u0917\u0930"
    ],
    "name:mar_x_variant":[
        "\u0930\u094b\u092a\u0921"
    ],
    "name:mlg_x_preferred":[
        "Rupnagar"
    ],
    "name:msa_x_preferred":[
        "Rupnagar"
    ],
    "name:new_x_preferred":[
        "\u0930\u0941\u092a\u0928\u0917\u0930"
    ],
    "name:nld_x_preferred":[
        "Rupnagar"
    ],
    "name:ori_x_preferred":[
        "\u0b30\u0b42\u0b2a\u0b28\u0b17\u0b30"
    ],
    "name:pan_x_preferred":[
        "\u0a30\u0a42\u0a2a\u0a28\u0a17\u0a30"
    ],
    "name:rus_x_preferred":[
        "\u0420\u0443\u043f\u0430\u0440"
    ],
    "name:san_x_preferred":[
        "\u0930\u0942\u092a\u0928\u0917\u0930\u092e\u094d"
    ],
    "name:spa_x_preferred":[
        "Rupnagar"
    ],
    "name:swe_x_preferred":[
        "Rupnagar"
    ],
    "name:tam_x_preferred":[
        "\u0bb0\u0bc2\u0baa\u0bcd\u0ba8\u0b95\u0bb0\u0bcd"
    ],
    "name:tel_x_preferred":[
        "\u0c30\u0c42\u0c2a\u0c4d"
    ],
    "name:urd_x_preferred":[
        "\u0631\u0648\u067e \u0646\u06af\u0631"
    ],
    "name:urd_x_variant":[
        "\u0631\u0648\u067e\u0646\u06af\u0631"
    ],
    "name:vie_x_preferred":[
        "Rupnagar"
    ],
    "name:zho_x_preferred":[
        "\u9c81\u666e\u7eb3\u52a0\u5c14"
    ],
    "wof:name":"Rupnagar",
    "wof:placetype":"neighbourhood"
},
  "geometry": {"coordinates":[78.62929,27.68689],"type":"Point"}
}