{
  "type": "Feature",
  "properties": {
    "iso:country":"IN",
    "ks:ks_name":"Daukhedi",
    "ks:ks_pop":384,
    "ks:ks_type":"VILLAGE",
    "name:eng_x_preferred":[
        "Daukhedi"
    ],
    "wof:name":"Daukhedi",
    "wof:placetype":"locality",
    "wof:population":384
},
  "geometry": {"coordinates":[75.884084,23.134687],"type":"Point"}
}