{
  "type": "Feature",
  "properties": {
    "gn:admin1_code":"37.0",
    "gn:admin2_code":"409.0",
    "gn:asciiname":"Gotatola",
    "gn:country_code":"IN",
    "gn:dem":418,
    "gn:feature_class":"P",
    "gn:feature_code":"PPL",
    "gn:name":"Got\u0101tola",
    "gn:population":0,
    "gn:timezone":"Asia/Kolkata",
    "iso:country":"IN",
    "ks:ks_alt_nam":"Got\u0101tola",
    "ks:ks_name":"Gotatola",
    "ks:ks_pop":153,
    "ks:ks_type":"VILLAGE",
    "name:eng_x_preferred":[
        "Gotatola"
    ],
    "name:eng_x_variant":[
        "Got\u0101tola"
    ],
    "wof:name":"Gotatola",
    "wof:placetype":"locality",
    "wof:population":153
},
  "geometry": {"coordinates":[81.35328,20.590619],"type":"Point"}
}