{
  "type": "Feature",
  "properties": {
    "gn:admin1_code":"25.0",
    "gn:admin2_code":"606.0",
    "gn:asciiname":"Saramarathur",
    "gn:country_code":"IN",
    "gn:dem":753,
    "gn:feature_class":"P",
    "gn:feature_code":"PPL",
    "gn:name":"Saramarath\u016br",
    "gn:population":0,
    "gn:timezone":"Asia/Kolkata",
    "iso:country":"IN",
    "wof:name":"Saramarathur",
    "wof:placetype":"locality"
},
  "geometry": {"coordinates":[78.91504999999999,12.58],"type":"Point"}
}