{
  "type": "Feature",
  "properties": {
    "iso:country":"IN",
    "ks:ks_name":"Ramlal Ka Purwa",
    "ks:ks_pop":75,
    "ks:ks_type":"HABITATION",
    "name:eng_x_preferred":[
        "Ramlal Ka Purwa"
    ],
    "wof:name":"Ramlal Ka Purwa",
    "wof:placetype":"locality",
    "wof:population":75
},
  "geometry": {"coordinates":[80.83622699999999,25.181805],"type":"Point"}
}