{
  "type": "Feature",
  "properties": {
    "iso:country":"IN",
    "ks:ks_name":"Tola Gurmha",
    "ks:ks_pop":176,
    "ks:ks_type":"VILLAGE",
    "name:eng_x_preferred":[
        "Tola Gurmha"
    ],
    "wof:name":"Tola Gurmha",
    "wof:placetype":"locality",
    "wof:population":176
},
  "geometry": {"coordinates":[86.327045,25.086357],"type":"Point"}
}