{
  "type": "Feature",
  "properties": {
    "iso:country":"IN",
    "ks:ks_alt_nam":"UMA CHARAN PARA",
    "ks:ks_name":"Uma Charan Para",
    "ks:ks_pop":86,
    "ks:ks_type":"HABITATION",
    "name:eng_x_preferred":[
        "Uma Charan Para"
    ],
    "wof:name":"Uma Charan Para",
    "wof:placetype":"locality",
    "wof:population":86
},
  "geometry": {"coordinates":[91.50315999999999,24.060333],"type":"Point"}
}