{
  "type": "Feature",
  "properties": {
    "iso:country":"IN",
    "ks:ks_name":"Noudhiwa",
    "ks:ks_pop":363,
    "ks:ks_type":"HABITATION",
    "ks:ks_uagg_main":0,
    "name:eng_x_preferred":[
        "Noudhiwa"
    ],
    "wof:name":"Noudhiwa",
    "wof:placetype":"neighbourhood",
    "wof:population":363
},
  "geometry": {"coordinates":[83.620955,27.447615],"type":"Point"}
}