{
  "type": "Feature",
  "properties": {
    "iso:country":"IN",
    "ks:ks_alt_nam":"Padamati thanda",
    "ks:ks_name":"Padamati Thanda",
    "ks:ks_pop":139,
    "ks:ks_type":"HABITATION",
    "name:eng_x_preferred":[
        "Padamati Thanda"
    ],
    "wof:name":"Padamati Thanda",
    "wof:placetype":"locality",
    "wof:population":139
},
  "geometry": {"coordinates":[78.83161699999999,16.929581],"type":"Point"}
}