{
  "type": "Feature",
  "properties": {
    "gn:admin1_code":"11.0",
    "gn:admin2_code":"31.0",
    "gn:asciiname":"Tikri",
    "gn:country_code":"IN",
    "gn:dem":1057,
    "gn:feature_class":"P",
    "gn:feature_code":"PPL",
    "gn:name":"Tikri",
    "gn:population":0,
    "gn:timezone":"Asia/Kolkata",
    "iso:country":"IN",
    "name:ceb_x_preferred":[
        "Tikri"
    ],
    "name:swe_x_preferred":[
        "Tikri"
    ],
    "wof:name":"Tikri",
    "wof:placetype":"locality"
},
  "geometry": {"coordinates":[77.24268000000002,30.91698],"type":"Point"}
}