{
  "type": "Feature",
  "properties": {
    "gn:admin1_code":"36.0",
    "gn:admin2_code":"161.0",
    "gn:asciiname":"Tandehar",
    "gn:country_code":"IN",
    "gn:dem":154,
    "gn:feature_class":"P",
    "gn:feature_code":"PPL",
    "gn:name":"Tandehar",
    "gn:population":0,
    "gn:timezone":"Asia/Kolkata",
    "iso:country":"IN",
    "ks:ks_name":"Tandehar",
    "ks:ks_type":"VILLAGE",
    "name:eng_x_preferred":[
        "Tandehar"
    ],
    "wof:name":"Tandehar",
    "wof:placetype":"locality"
},
  "geometry": {"coordinates":[79.270072,26.964419],"type":"Point"}
}