{
  "type": "Feature",
  "properties": {
    "gn:admin1_code":"25.0",
    "gn:admin2_code":"602.0",
    "gn:asciiname":"Venmanambudur",
    "gn:country_code":"IN",
    "gn:dem":52,
    "gn:feature_class":"P",
    "gn:feature_code":"PPL",
    "gn:name":"Venmanambud\u016br",
    "gn:population":0,
    "gn:timezone":"Asia/Kolkata",
    "iso:country":"IN",
    "ks:ks_alt_nam":"Venmanambud\u016br",
    "ks:ks_name":"Venmanambudur",
    "ks:ks_type":"VILLAGE",
    "ks:ks_uagg_main":0,
    "name:eng_x_preferred":[
        "Venmanambudur"
    ],
    "name:eng_x_variant":[
        "Venmanambud\u016br"
    ],
    "wof:name":"Venmanambudur",
    "wof:placetype":"neighbourhood"
},
  "geometry": {"coordinates":[79.85547200000001,13.104368],"type":"Point"}
}