{
  "type": "Feature",
  "properties": {
    "gn:admin1_code":"23",
    "gn:admin2_code":"39.0",
    "gn:asciiname":"Rolda Kotha",
    "gn:country_code":"IN",
    "gn:dem":249,
    "gn:feature_class":"P",
    "gn:feature_code":"PPL",
    "gn:name":"Rolda Kotha",
    "gn:population":0,
    "gn:timezone":"Asia/Kolkata",
    "iso:country":"IN",
    "wof:name":"Rolda Kotha",
    "wof:placetype":"locality"
},
  "geometry": {"coordinates":[76.12914000000001,31.02757],"type":"Point"}
}