{
  "type": "Feature",
  "properties": {
    "iso:country":"IN",
    "ks:ks_name":"Bagahi",
    "ks:ks_pop":113,
    "ks:ks_type":"HABITATION",
    "name:eng_x_preferred":[
        "Bagahi"
    ],
    "wof:name":"Bagahi",
    "wof:placetype":"locality",
    "wof:population":113
},
  "geometry": {"coordinates":[84.211851,25.911731],"type":"Point"}
}