{
  "type": "Feature",
  "properties": {
    "gn:admin1_code":"39.0",
    "gn:admin2_code":"60.0",
    "gn:asciiname":"Dhadau",
    "gn:country_code":"IN",
    "gn:dem":1113,
    "gn:feature_class":"P",
    "gn:feature_code":"PPL",
    "gn:name":"Dhadau",
    "gn:population":0,
    "gn:timezone":"Asia/Kolkata",
    "iso:country":"IN",
    "wof:name":"Dhadau",
    "wof:placetype":"locality"
},
  "geometry": {"coordinates":[77.86133000000002,30.57347],"type":"Point"}
}