{
  "type": "Feature",
  "properties": {
    "iso:country":"IN",
    "ks:ks_name":"Tola Jogiraidih",
    "ks:ks_pop":128,
    "ks:ks_type":"VILLAGE",
    "name:eng_x_preferred":[
        "Tola Jogiraidih"
    ],
    "wof:name":"Tola Jogiraidih",
    "wof:placetype":"locality",
    "wof:population":128
},
  "geometry": {"coordinates":[86.465687,24.419062],"type":"Point"}
}