{
  "type": "Feature",
  "properties": {
    "iso:country":"IN",
    "ks:ks_name":"Hatichhad",
    "ks:ks_pop":397,
    "ks:ks_type":"VILLAGE",
    "name:eng_x_preferred":[
        "Hatichhad"
    ],
    "wof:name":"Hatichhad",
    "wof:placetype":"locality",
    "wof:population":397
},
  "geometry": {"coordinates":[86.43898799999999,22.22099],"type":"Point"}
}