{
  "type": "Feature",
  "properties": {
    "iso:country":"IN",
    "ks:ks_name":"Puchhiapali",
    "ks:ks_pop":518,
    "ks:ks_type":"VILLAGE",
    "name:eng_x_preferred":[
        "Puchhiapali"
    ],
    "wof:name":"Puchhiapali",
    "wof:placetype":"locality",
    "wof:population":518
},
  "geometry": {"coordinates":[83.04700699999999,22.101858],"type":"Point"}
}