{
  "type": "Feature",
  "properties": {
    "gn:admin1_code":"28.0",
    "gn:admin2_code":"336",
    "gn:asciiname":"Chakdaha",
    "gn:country_code":"IN",
    "gn:dem":13,
    "gn:feature_class":"P",
    "gn:feature_code":"PPL",
    "gn:name":"Ch\u0101kdaha",
    "gn:population":0,
    "gn:timezone":"Asia/Kolkata",
    "iso:country":"IN",
    "name:und_x_variant":[
        "Ch\u0101kdaha"
    ],
    "wof:name":"Chakdaha",
    "wof:placetype":"locality"
},
  "geometry": {"coordinates":[88.52871999999998,23.07558],"type":"Point"}
}