{
  "type": "Feature",
  "properties": {
    "iso:country":"IN",
    "ks:ks_name":"Jusavada",
    "ks:ks_pop":350,
    "ks:ks_type":"VILLAGE",
    "name:eng_x_preferred":[
        "Jusavada"
    ],
    "wof:name":"Jusavada",
    "wof:placetype":"locality",
    "wof:population":350
},
  "geometry": {"coordinates":[73.348583,23.908444],"type":"Point"}
}