{
  "type": "Feature",
  "properties": {
    "iso:country":"IN",
    "ks:ks_name":"Varam",
    "ks:ks_pop":1962,
    "ks:ks_type":"VILLAGE",
    "name:eng_x_preferred":[
        "Varam"
    ],
    "wof:name":"Varam",
    "wof:placetype":"locality",
    "wof:population":1962
},
  "geometry": {"coordinates":[75.408574,11.906745],"type":"Point"}
}