{
  "type": "Feature",
  "properties": {
    "iso:country":"IN",
    "ks:ks_name":"26 PTP",
    "ks:ks_pop":14,
    "ks:ks_type":"VILLAGE",
    "name:eng_x_preferred":[
        "26 PTP"
    ],
    "wof:name":"26 PTP",
    "wof:placetype":"locality",
    "wof:population":14
},
  "geometry": {"coordinates":[74.210594,29.84785],"type":"Point"}
}