{
  "type": "Feature",
  "properties": {
    "gn:admin1_code":"36.0",
    "gn:admin2_code":"183.0",
    "gn:asciiname":"Mahabir Singh",
    "gn:country_code":"IN",
    "gn:dem":105,
    "gn:feature_class":"P",
    "gn:feature_code":"PPL",
    "gn:name":"Mah\u0101b\u012br Singh",
    "gn:population":0,
    "gn:timezone":"Asia/Kolkata",
    "iso:country":"IN",
    "name:ces_x_preferred":[
        "Mahabir Singh"
    ],
    "name:pol_x_preferred":[
        "Mahabir Singh"
    ],
    "wof:name":"Mahabir Singh",
    "wof:placetype":"locality"
},
  "geometry": {"coordinates":[81.79658000000001,26.96544],"type":"Point"}
}