{
  "type": "Feature",
  "properties": {
    "iso:country":"IN",
    "ks:ks_name":"Rawon Ki Dhani",
    "ks:ks_pop":35,
    "ks:ks_type":"HABITATION",
    "name:eng_x_preferred":[
        "Rawon Ki Dhani"
    ],
    "wof:name":"Rawon Ki Dhani",
    "wof:placetype":"locality",
    "wof:population":35
},
  "geometry": {"coordinates":[74.43880799999999,29.781527],"type":"Point"}
}