{
  "type": "Feature",
  "properties": {
    "gn:country":"IN",
    "gn:fcode":"PPL",
    "gn:population":0,
    "iso:country":"IN",
    "name:ara_x_preferred":[
        "\u0631\u0627\u062a\u0627\u0646\u062f\u0627"
    ],
    "name:ben_bn_x_preferred":[
        "\u09b0\u09a4\u09a8\u09be\u09a6\u09be"
    ],
    "name:ben_in_x_preferred":[
        "\u09b0\u09a4\u09a8\u09be\u09a6\u09be"
    ],
    "name:guj_x_preferred":[
        "\u0ab0\u0aa4\u0aa8\u0aa6\u0abe"
    ],
    "name:hin_x_preferred":[
        "\u0930\u0924\u0928\u093e\u0921\u093e"
    ],
    "name:kan_x_preferred":[
        "\u0cb0\u0ca4\u0ca8\u0ca1\u0cbe"
    ],
    "name:mal_x_preferred":[
        "\u0d30\u0d24\u0d28\u0d3e\u0d1f"
    ],
    "name:mar_x_preferred":[
        "\u0930\u0924\u0928\u0926\u093e"
    ],
    "name:pan_x_preferred":[
        "\u0a30\u0a24\u0a28\u0a5c\u0a3e"
    ],
    "name:tam_x_preferred":[
        "\u0bb0\u0ba4\u0ba9\u0b9f\u0bbe"
    ],
    "name:tel_x_preferred":[
        "\u0c30\u0c24\u0c28\u0c3e\u0c21\u0c3e"
    ],
    "name:urd_x_preferred":[
        "\u0631\u062a\u0646\u0627\u0691\u0627"
    ],
    "qs:name":"Ratanada",
    "qs:name_adm0":"India",
    "qs:name_adm1":"Rajasthan",
    "qs:photos":7,
    "qs:photos_1k":1,
    "qs:photos_9k":1,
    "qs:photos_9r":1,
    "qs:photos_all":7,
    "qs:photos_sr":1,
    "qs:placetype":"Suburb",
    "qs:pop_sr":"0",
    "wof:name":"Ratanada",
    "wof:placetype":"neighbourhood",
    "wof:population":0
},
  "geometry": {"coordinates":[73.02930000000001,26.28097],"type":"Point"}
}