{
  "type": "Feature",
  "properties": {
    "gn:admin1_code":"9.0",
    "gn:admin2_code":"484.0",
    "gn:asciiname":"Garia",
    "gn:country_code":"IN",
    "gn:dem":182,
    "gn:feature_class":"P",
    "gn:feature_code":"PPL",
    "gn:name":"G\u0101ria",
    "gn:population":0,
    "gn:timezone":"Asia/Kolkata",
    "iso:country":"IN",
    "name:ben_x_preferred":[
        "\u0997\u09a1\u09bc\u09bf\u09af\u09bc\u09be"
    ],
    "wof:name":"Garia",
    "wof:placetype":"neighbourhood"
},
  "geometry": {"coordinates":[73.92282,23.10256],"type":"Point"}
}