{
  "type": "Feature",
  "properties": {
    "gn:admin1_code":"39",
    "gn:admin2_code":"60.0",
    "gn:asciiname":"Kalla Thar",
    "gn:country_code":"IN",
    "gn:dem":2488,
    "gn:feature_class":"P",
    "gn:feature_code":"PPL",
    "gn:name":"Kalla Thar",
    "gn:population":0,
    "gn:timezone":"Asia/Kolkata",
    "iso:country":"IN",
    "wof:name":"Kalla Thar",
    "wof:placetype":"locality"
},
  "geometry": {"coordinates":[77.96808,30.75951],"type":"Point"}
}