{
  "type": "Feature",
  "properties": {
    "iso:country":"IN",
    "ks:ks_name":"Sugar Factory",
    "ks:ks_pop":283,
    "ks:ks_type":"HABITATION",
    "name:eng_x_preferred":[
        "Sugar Factory"
    ],
    "wof:name":"Sugar Factory",
    "wof:placetype":"locality",
    "wof:population":283
},
  "geometry": {"coordinates":[74.54226,15.64558],"type":"Point"}
}