{
  "type": "Feature",
  "properties": {
    "gn:admin1_code":"19.0",
    "gn:admin2_code":"571.0",
    "gn:asciiname":"Kengalapura",
    "gn:country_code":"IN",
    "gn:dem":792,
    "gn:feature_class":"P",
    "gn:feature_code":"PPL",
    "gn:name":"Keng\u0101lapura",
    "gn:population":0,
    "gn:timezone":"Asia/Kolkata",
    "iso:country":"IN",
    "wof:name":"Kengalapura",
    "wof:placetype":"locality"
},
  "geometry": {"coordinates":[76.43012,13.47491],"type":"Point"}
}