{
  "type": "Feature",
  "properties": {
    "iso:country":"IN",
    "ks:ks_name":"Banga Mura",
    "ks:ks_pop":304,
    "ks:ks_type":"HABITATION",
    "name:eng_x_preferred":[
        "Banga Mura"
    ],
    "wof:name":"Banga Mura",
    "wof:placetype":"locality",
    "wof:population":304
},
  "geometry": {"coordinates":[92.008737,23.927771],"type":"Point"}
}