{
  "type": "Feature",
  "properties": {
    "iso:country":"IN",
    "ks:ks_name":"18 PTD-A",
    "ks:ks_pop":256,
    "ks:ks_type":"VILLAGE",
    "name:eng_x_preferred":[
        "18 PTD-A"
    ],
    "wof:name":"18 PTD-A",
    "wof:placetype":"locality",
    "wof:population":256
},
  "geometry": {"coordinates":[73.255788,29.401342],"type":"Point"}
}