{
  "type": "Feature",
  "properties": {
    "iso:country":"IN",
    "ks:ks_name":"Chakkalakalpadi",
    "ks:ks_pop":400,
    "ks:ks_type":"HABITATION",
    "name:eng_x_preferred":[
        "Chakkalakalpadi"
    ],
    "wof:name":"Chakkalakalpadi",
    "wof:placetype":"locality",
    "wof:population":400
},
  "geometry": {"coordinates":[76.886377,9.98386],"type":"Point"}
}