{
  "type": "Feature",
  "properties": {
    "iso:country":"IN",
    "ks:ks_name":"Bettada Kadu",
    "ks:ks_pop":219,
    "ks:ks_type":"HABITATION",
    "name:eng_x_preferred":[
        "Bettada Kadu"
    ],
    "wof:name":"Bettada Kadu",
    "wof:placetype":"locality",
    "wof:population":219
},
  "geometry": {"coordinates":[75.850556,12.410002],"type":"Point"}
}