{
  "type": "Feature",
  "properties": {
    "iso:country":"IN",
    "ks:ks_name":"Tad Faliya",
    "ks:ks_pop":315,
    "ks:ks_type":"HABITATION",
    "name:eng_x_preferred":[
        "Tad Faliya"
    ],
    "wof:name":"Tad Faliya",
    "wof:placetype":"locality",
    "wof:population":315
},
  "geometry": {"coordinates":[73.821944,22.972472],"type":"Point"}
}