{
  "type": "Feature",
  "properties": {
    "iso:country":"IN",
    "ks:ks_name":"Rawoolwadi",
    "ks:ks_pop":107,
    "ks:ks_type":"HABITATION",
    "name:eng_x_preferred":[
        "Rawoolwadi"
    ],
    "wof:name":"Rawoolwadi",
    "wof:placetype":"locality",
    "wof:population":107
},
  "geometry": {"coordinates":[73.93210500000001,15.978199],"type":"Point"}
}