{
  "type": "Feature",
  "properties": {
    "iso:country":"IN",
    "ks:ks_name":"Sayara Block Factory",
    "ks:ks_pop":212,
    "ks:ks_type":"HABITATION",
    "name:eng_x_preferred":[
        "Sayara Block Factory"
    ],
    "wof:name":"Sayara Block Factory",
    "wof:placetype":"locality",
    "wof:population":212
},
  "geometry": {"coordinates":[73.338572,23.48963],"type":"Point"}
}