{
  "type": "Feature",
  "properties": {
    "iso:country":"IN",
    "ks:ks_name":"Jharna",
    "ks:ks_pop":186,
    "ks:ks_type":"VILLAGE",
    "ks:ks_uagg_main":0,
    "name:eng_x_preferred":[
        "Jharna"
    ],
    "wof:name":"Jharna",
    "wof:placetype":"neighbourhood",
    "wof:population":186
},
  "geometry": {"coordinates":[84.186972,24.448784],"type":"Point"}
}