{
  "type": "Feature",
  "properties": {
    "iso:country":"IN",
    "ks:ks_alt_nam":"shivapur",
    "ks:ks_name":"Shivapur",
    "ks:ks_pop":1450,
    "ks:ks_type":"HABITATION",
    "name:eng_x_preferred":[
        "Shivapur"
    ],
    "wof:name":"Shivapur",
    "wof:placetype":"locality",
    "wof:population":1450
},
  "geometry": {"coordinates":[75.46855499999999,14.747109],"type":"Point"}
}