{
  "type": "Feature",
  "properties": {
    "iso:country":"IN",
    "ks:ks_name":"Sultanpur Darwesh Ali",
    "ks:ks_pop":662,
    "ks:ks_type":"VILLAGE",
    "ks:ks_uagg_main":0,
    "name:eng_x_preferred":[
        "Sultanpur Darwesh Ali"
    ],
    "wof:name":"Sultanpur Darwesh Ali",
    "wof:placetype":"neighbourhood",
    "wof:population":662
},
  "geometry": {"coordinates":[82.65732,25.734315],"type":"Point"}
}