{
  "type": "Feature",
  "properties": {
    "gn:admin1_code":"24.0",
    "gn:admin2_code":"125.0",
    "gn:asciiname":"Saliapara",
    "gn:country_code":"IN",
    "gn:dem":414,
    "gn:feature_class":"P",
    "gn:feature_code":"PPL",
    "gn:name":"S\u0101liap\u0101ra",
    "gn:population":0,
    "gn:timezone":"Asia/Kolkata",
    "iso:country":"IN",
    "wof:name":"Saliapara",
    "wof:placetype":"locality"
},
  "geometry": {"coordinates":[74.43326999999999,23.36536],"type":"Point"}
}