{
  "type": "Feature",
  "properties": {
    "gn:admin1_code":"25.0",
    "gn:admin2_code":"620.0",
    "gn:asciiname":"Tirukkarugavur",
    "gn:country_code":"IN",
    "gn:dem":36,
    "gn:feature_class":"P",
    "gn:feature_code":"PPL",
    "gn:name":"Tirukkarug\u0101v\u016br",
    "gn:population":0,
    "gn:timezone":"Asia/Kolkata",
    "iso:country":"IN",
    "wof:name":"Tirukkarugavur",
    "wof:placetype":"locality"
},
  "geometry": {"coordinates":[79.27507,10.86878],"type":"Point"}
}