{
  "type": "Feature",
  "properties": {
    "iso:country":"IN",
    "ks:ks_alt_nam":"Malleshwer thanda",
    "ks:ks_name":"Malleshwer Thanda",
    "ks:ks_pop":40,
    "ks:ks_type":"HABITATION",
    "name:eng_x_preferred":[
        "Malleshwer Thanda"
    ],
    "wof:name":"Malleshwer Thanda",
    "wof:placetype":"locality",
    "wof:population":40
},
  "geometry": {"coordinates":[77.932074,19.292408],"type":"Point"}
}