{
  "type": "Feature",
  "properties": {
    "gn:admin1_code":"36",
    "gn:admin2_code":"199.0",
    "gn:asciiname":"Karyat Sikhar",
    "gn:country_code":"IN",
    "gn:dem":82,
    "gn:feature_class":"P",
    "gn:feature_code":"PPL",
    "gn:name":"Kary\u0101t S\u012bkhar",
    "gn:population":0,
    "gn:timezone":"Asia/Kolkata",
    "iso:country":"IN",
    "wof:name":"Karyat Sikhar",
    "wof:placetype":"locality"
},
  "geometry": {"coordinates":[82.81565999999999,25.1291],"type":"Point"}
}