{
  "type": "Feature",
  "properties": {
    "gn:admin1_code":"36",
    "gn:admin2_code":"202.0",
    "gn:asciiname":"Nauli",
    "gn:country_code":"IN",
    "gn:dem":165,
    "gn:feature_class":"P",
    "gn:feature_code":"PPL",
    "gn:name":"Nauli",
    "gn:population":0,
    "gn:timezone":"Asia/Kolkata",
    "iso:country":"IN",
    "name:deu_x_preferred":[
        "Nauli"
    ],
    "name:fra_x_preferred":[
        "Nauli"
    ],
    "name:nld_x_preferred":[
        "Nauli"
    ],
    "wof:name":"Nauli",
    "wof:placetype":"neighbourhood"
},
  "geometry": {"coordinates":[78.85279,27.89276],"type":"Point"}
}