{
  "type": "Feature",
  "properties": {
    "iso:country":"IN",
    "ks:ks_name":"38 MMK",
    "ks:ks_pop":182,
    "ks:ks_type":"VILLAGE",
    "name:eng_x_preferred":[
        "38 MMK"
    ],
    "wof:name":"38 MMK",
    "wof:placetype":"locality",
    "wof:population":182
},
  "geometry": {"coordinates":[74.109494,29.770763],"type":"Point"}
}