{
  "type": "Feature",
  "properties": {
    "iso:country":"IN",
    "ks:ks_name":"Bhatiya Faliya",
    "ks:ks_pop":292,
    "ks:ks_type":"HABITATION",
    "name:eng_x_preferred":[
        "Bhatiya Faliya"
    ],
    "wof:name":"Bhatiya Faliya",
    "wof:placetype":"locality",
    "wof:population":292
},
  "geometry": {"coordinates":[73.471611,23.120139],"type":"Point"}
}