{
  "type": "Feature",
  "properties": {
    "iso:country":"IN",
    "ks:ks_name":"Chak Mahmud Chisti",
    "ks:ks_pop":1063,
    "ks:ks_type":"VILLAGE",
    "name:eng_x_preferred":[
        "Chak Mahmud Chisti"
    ],
    "wof:name":"Chak Mahmud Chisti",
    "wof:placetype":"locality",
    "wof:population":1063
},
  "geometry": {"coordinates":[85.23259899999999,25.662394],"type":"Point"}
}