{
  "type": "Feature",
  "properties": {
    "gn:admin1_code":"19.0",
    "gn:admin2_code":"574.0",
    "gn:asciiname":"Kanavebasvanhalli",
    "gn:country_code":"IN",
    "gn:dem":956,
    "gn:feature_class":"P",
    "gn:feature_code":"PPL",
    "gn:name":"Kanavebasvanhalli",
    "gn:population":0,
    "gn:timezone":"Asia/Kolkata",
    "iso:country":"IN",
    "wof:name":"Kanavebasvanhalli",
    "wof:placetype":"locality"
},
  "geometry": {"coordinates":[75.94251,12.85236],"type":"Point"}
}