{
  "type": "Feature",
  "properties": {
    "gn:admin1_code":"19.0",
    "gn:admin2_code":"574.0",
    "gn:asciiname":"Kanavebasvanhalli",
    "gn:country_code":"IN",
    "gn:dem":956,
    "gn:feature_class":"P",
    "gn:feature_code":"PPL",
    "gn:name":"Kanavebasvanhalli",
    "gn:population":0,
    "gn:timezone":"Asia/Kolkata",
    "iso:country":"IN",
    "ks:ks_name":"Kanive Basavanahalli",
    "ks:ks_pop":232,
    "ks:ks_type":"VILLAGE",
    "name:eng_x_preferred":[
        "Kanive Basavanahalli"
    ],
    "name:eng_x_variant":[
        "Kanavebasvanhalli"
    ],
    "wof:name":"Kanive Basavanahalli",
    "wof:placetype":"locality",
    "wof:population":232
},
  "geometry": {"coordinates":[75.943359,12.857702],"type":"Point"}
}