{
  "type": "Feature",
  "properties": {
    "iso:country":"IN",
    "ks:ks_name":"Kadma",
    "ks:ks_pop":0,
    "ks:ks_type":"VILLAGE",
    "name:eng_x_preferred":[
        "Kadma"
    ],
    "wof:name":"Kadma",
    "wof:placetype":"locality",
    "wof:population":0
},
  "geometry": {"coordinates":[88.24630500000001,26.75309],"type":"Point"}
}