{
  "type": "Feature",
  "properties": {
    "iso:country":"IN",
    "ks:ks_name":"Salmara",
    "ks:ks_pop":582,
    "ks:ks_type":"VILLAGE",
    "name:eng_x_preferred":[
        "Salmara"
    ],
    "wof:name":"Salmara",
    "wof:placetype":"locality",
    "wof:population":582
},
  "geometry": {"coordinates":[94.068617,27.073338],"type":"Point"}
}