{
  "type": "Feature",
  "properties": {
    "iso:country":"IN",
    "ks:ks_name":"Lakhapada",
    "ks:ks_pop":532,
    "ks:ks_type":"VILLAGE",
    "name:eng_x_preferred":[
        "Lakhapada"
    ],
    "wof:name":"Lakhapada",
    "wof:placetype":"locality",
    "wof:population":532
},
  "geometry": {"coordinates":[85.416467,20.06638],"type":"Point"}
}