{
  "type": "Feature",
  "properties": {
    "gn:admin1_code":"34.0",
    "gn:admin2_code":"217.0",
    "gn:asciiname":"Shahpur Batarha",
    "gn:country_code":"IN",
    "gn:dem":74,
    "gn:feature_class":"P",
    "gn:feature_code":"PPL",
    "gn:name":"Sh\u0101hpur Batarha",
    "gn:population":0,
    "gn:timezone":"Asia/Kolkata",
    "iso:country":"IN",
    "ks:ks_name":"Shahpur Batraha",
    "ks:ks_pop":588,
    "ks:ks_type":"VILLAGE",
    "ks:ks_uagg_main":0,
    "name:eng_x_preferred":[
        "Shahpur Batraha"
    ],
    "wof:name":"Shahpur Batraha",
    "wof:placetype":"neighbourhood",
    "wof:population":588
},
  "geometry": {"coordinates":[84.208332,26.430035],"type":"Point"}
}