{
  "type": "Feature",
  "properties": {
    "gn:admin1_code":"34.0",
    "gn:admin2_code":"234.0",
    "gn:asciiname":"Murarpur",
    "gn:country_code":"IN",
    "gn:dem":89,
    "gn:feature_class":"P",
    "gn:feature_code":"PPL",
    "gn:name":"Mur\u0101rpur",
    "gn:population":0,
    "gn:timezone":"Asia/Kolkata",
    "iso:country":"IN",
    "ks:ks_name":"Murarpur",
    "ks:ks_pop":313,
    "ks:ks_type":"VILLAGE",
    "name:eng_x_preferred":[
        "Murarpur"
    ],
    "wof:name":"Murarpur",
    "wof:placetype":"locality",
    "wof:population":313
},
  "geometry": {"coordinates":[84.317863,25.192595],"type":"Point"}
}