{
  "type": "Feature",
  "properties": {
    "gn:admin1_code":"36",
    "gn:admin2_code":"188.0",
    "gn:asciiname":"Bailu Chak",
    "gn:country_code":"IN",
    "gn:dem":84,
    "gn:feature_class":"P",
    "gn:feature_code":"PPL",
    "gn:name":"Bailu Chak",
    "gn:population":0,
    "gn:timezone":"Asia/Kolkata",
    "iso:country":"IN",
    "ks:ks_name":"Ballochak",
    "ks:ks_pop":221,
    "ks:ks_type":"VILLAGE",
    "name:eng_x_preferred":[
        "Ballochak"
    ],
    "name:eng_x_variant":[
        "Bailu Chak"
    ],
    "wof:name":"Ballochak",
    "wof:placetype":"locality",
    "wof:population":221
},
  "geometry": {"coordinates":[83.271353,26.56709],"type":"Point"}
}