{
  "type": "Feature",
  "properties": {
    "gn:admin1_code":"35.0",
    "gn:admin2_code":"454",
    "gn:asciiname":"Chabi",
    "gn:country_code":"IN",
    "gn:dem":482,
    "gn:feature_class":"P",
    "gn:feature_code":"PPL",
    "gn:name":"Ch\u0101b\u012b",
    "gn:population":0,
    "gn:timezone":"Asia/Kolkata",
    "iso:country":"IN",
    "name:fin_x_preferred":[
        "Chabi"
    ],
    "name:fra_x_preferred":[
        "Chabi"
    ],
    "name:jpn_x_preferred":[
        "\u30c1\u30e3\u30d6\u30a4"
    ],
    "name:kat_x_preferred":[
        "\u10e9\u10d0\u10d1\u10d8"
    ],
    "name:kor_x_preferred":[
        "\ucc28\ube0c\uc774 \uce74\ud230"
    ],
    "name:mon_x_preferred":[
        "\u0427\u0430\u0431\u0438 \u0445\u0430\u0442\u0430\u043d"
    ],
    "name:rus_x_preferred":[
        "\u0427\u0430\u0431\u0438"
    ],
    "name:sin_x_preferred":[
        "\u0da0\u0dcf\u0db6\u0dd2"
    ],
    "name:swe_x_preferred":[
        "Chabi"
    ],
    "name:tha_x_preferred":[
        "\u0e09\u0e32\u0e1b\u0e35\u0e49"
    ],
    "name:und_x_variant":[
        "Ch\u0101b\u012b",
        "Ch\u0101bi"
    ],
    "name:urd_x_preferred":[
        "\u0686\u0627\u0628\u06cc"
    ],
    "name:vie_x_preferred":[
        "S\u00e1t T\u1ea5t"
    ],
    "name:zho_x_preferred":[
        "\u5bdf\u5fc5\u7687\u540e"
    ],
    "wof:name":"Chabi",
    "wof:placetype":"locality"
},
  "geometry": {"coordinates":[80.70026,22.82545],"type":"Point"}
}