{
  "type": "Feature",
  "properties": {
    "gn:admin1_code":"35.0",
    "gn:admin2_code":"454",
    "gn:asciiname":"Chabi",
    "gn:country_code":"IN",
    "gn:dem":482,
    "gn:feature_class":"P",
    "gn:feature_code":"PPL",
    "gn:name":"Ch\u0101b\u012b",
    "gn:population":0,
    "gn:timezone":"Asia/Kolkata",
    "iso:country":"IN",
    "name:und_x_variant":[
        "Ch\u0101b\u012b",
        "Ch\u0101bi"
    ],
    "wof:name":"Chabi",
    "wof:placetype":"locality"
},
  "geometry": {"coordinates":[80.70026,22.82545],"type":"Point"}
}