{
  "type": "Feature",
  "properties": {
    "iso:country":"IN",
    "ks:ks_name":"Anaje",
    "ks:ks_pop":510,
    "ks:ks_type":"HABITATION",
    "name:eng_x_preferred":[
        "Anaje"
    ],
    "wof:name":"Anaje",
    "wof:placetype":"locality",
    "wof:population":510
},
  "geometry": {"coordinates":[75.222393,12.674197],"type":"Point"}
}