{
  "type": "Feature",
  "properties": {
    "iso:country":"IN",
    "ks:ks_name":"Irusumanda",
    "ks:ks_pop":699,
    "ks:ks_type":"VILLAGE",
    "name:eng_x_preferred":[
        "Irusumanda"
    ],
    "wof:name":"Irusumanda",
    "wof:placetype":"locality",
    "wof:population":699
},
  "geometry": {"coordinates":[81.852485,16.421338],"type":"Point"}
}