{
  "type": "Feature",
  "properties": {
    "iso:country":"IN",
    "ks:ks_name":"Athikadu",
    "ks:ks_pop":136,
    "ks:ks_type":"HABITATION",
    "name:eng_x_preferred":[
        "Athikadu"
    ],
    "wof:name":"Athikadu",
    "wof:placetype":"locality",
    "wof:population":136
},
  "geometry": {"coordinates":[77.489007,11.363063],"type":"Point"}
}