{
  "type": "Feature",
  "properties": {
    "gn:admin1_code":"2.0",
    "gn:admin2_code":"543.0",
    "gn:asciiname":"Lakshminarayanapeta",
    "gn:country_code":"IN",
    "gn:dem":126,
    "gn:feature_class":"P",
    "gn:feature_code":"PPL",
    "gn:name":"Lakshm\u012bn\u0101rayanapeta",
    "gn:population":0,
    "gn:timezone":"Asia/Kolkata",
    "iso:country":"IN",
    "wof:name":"Lakshminarayanapeta",
    "wof:placetype":"locality"
},
  "geometry": {"coordinates":[83.36013,18.73907],"type":"Point"}
}