{
  "type": "Feature",
  "properties": {
    "gn:admin1_code":"36",
    "gn:admin2_code":"177.0",
    "gn:asciiname":"Bahram Khan",
    "gn:country_code":"IN",
    "gn:dem":113,
    "gn:feature_class":"P",
    "gn:feature_code":"PPL",
    "gn:name":"Bahr\u0101m Kh\u0101n",
    "gn:population":0,
    "gn:timezone":"Asia/Kolkata",
    "iso:country":"IN",
    "name:ben_x_preferred":[
        "\u09a4\u09be\u09a4\u09be\u09b0 \u0996\u09be\u09a8"
    ],
    "wof:name":"Bahram Khan",
    "wof:placetype":"locality"
},
  "geometry": {"coordinates":[81.66363,26.76646],"type":"Point"}
}