{
  "type": "Feature",
  "properties": {
    "iso:country":"IN",
    "ks:ks_name":"Mulani Wasti",
    "ks:ks_pop":622,
    "ks:ks_type":"HABITATION",
    "name:eng_x_preferred":[
        "Mulani Wasti"
    ],
    "wof:name":"Mulani Wasti",
    "wof:placetype":"locality",
    "wof:population":622
},
  "geometry": {"coordinates":[75.26508200000001,17.79863],"type":"Point"}
}