{
  "type": "Feature",
  "properties": {
    "iso:country":"IN",
    "ks:ks_name":"Nuyagram",
    "ks:ks_pop":475,
    "ks:ks_type":"VILLAGE",
    "name:eng_x_preferred":[
        "Nuyagram"
    ],
    "wof:name":"Nuyagram",
    "wof:placetype":"locality",
    "wof:population":475
},
  "geometry": {"coordinates":[86.421871,22.439616],"type":"Point"}
}