{
  "type": "Feature",
  "properties": {
    "iso:country":"IN",
    "ks:ks_alt_nam":"companipadi",
    "ks:ks_name":"Companipadi",
    "ks:ks_pop":347,
    "ks:ks_type":"HABITATION",
    "ks:ks_uagg_main":0,
    "name:eng_x_preferred":[
        "Companipadi"
    ],
    "wof:name":"Companipadi",
    "wof:placetype":"neighbourhood",
    "wof:population":347
},
  "geometry": {"coordinates":[76.1853,10.283776],"type":"Point"}
}