{
  "type": "Feature",
  "properties": {
    "iso:country":"IN",
    "ks:ks_name":"Raghubindha",
    "ks:ks_pop":408,
    "ks:ks_type":"VILLAGE",
    "name:eng_x_preferred":[
        "Raghubindha"
    ],
    "wof:name":"Raghubindha",
    "wof:placetype":"locality",
    "wof:population":408
},
  "geometry": {"coordinates":[86.55664899999999,21.191849],"type":"Point"}
}