{
  "type": "Feature",
  "properties": {
    "gn:admin1_code":"39.0",
    "gn:admin2_code":"63.0",
    "gn:asciiname":"Parmati",
    "gn:country_code":"IN",
    "gn:dem":1141,
    "gn:feature_class":"P",
    "gn:feature_code":"PPL",
    "gn:name":"Parmati",
    "gn:population":0,
    "gn:timezone":"Asia/Kolkata",
    "iso:country":"IN",
    "wof:name":"Parmati",
    "wof:placetype":"locality"
},
  "geometry": {"coordinates":[79.91401999999999,29.98948],"type":"Point"}
}