{
  "type": "Feature",
  "properties": {
    "iso:country":"IN",
    "ks:ks_alt_nam":"RADHA SADU PARA",
    "ks:ks_name":"Radha Sadu Para",
    "ks:ks_pop":52,
    "ks:ks_type":"HABITATION",
    "ks:ks_uagg_main":0,
    "name:eng_x_preferred":[
        "Radha Sadu Para"
    ],
    "wof:name":"Radha Sadu Para",
    "wof:placetype":"neighbourhood",
    "wof:population":52
},
  "geometry": {"coordinates":[91.570228,23.927402],"type":"Point"}
}