{
  "type": "Feature",
  "properties": {
    "iso:country":"IN",
    "ks:ks_name":"Rajabasa",
    "ks:ks_pop":215,
    "ks:ks_type":"HABITATION",
    "name:eng_x_preferred":[
        "Rajabasa"
    ],
    "wof:name":"Rajabasa",
    "wof:placetype":"locality",
    "wof:population":215
},
  "geometry": {"coordinates":[85.709158,22.863358],"type":"Point"}
}