{
  "type": "Feature",
  "properties": {
    "gn:admin1_code":"16",
    "gn:admin2_code":"510.0",
    "gn:asciiname":"Sakhi",
    "gn:country_code":"IN",
    "gn:dem":304,
    "gn:feature_class":"P",
    "gn:feature_code":"PPL",
    "gn:name":"Sakhi",
    "gn:population":0,
    "gn:timezone":"Asia/Kolkata",
    "iso:country":"IN",
    "name:cat_x_preferred":[
        "Sakhi"
    ],
    "name:hin_x_preferred":[
        "\u0938\u0916\u0940 \u0938\u0902\u092a\u094d\u0930\u0926\u093e\u092f"
    ],
    "wof:name":"Sakhi",
    "wof:placetype":"locality"
},
  "geometry": {"coordinates":[78.52279,20.22762],"type":"Point"}
}