{
  "type": "Feature",
  "properties": {
    "gn:admin1_code":"12.0",
    "gn:admin2_code":"17.0",
    "gn:asciiname":"Marlab",
    "gn:country_code":"IN",
    "gn:dem":2522,
    "gn:feature_class":"P",
    "gn:feature_code":"PPL",
    "gn:name":"Marlab",
    "gn:population":0,
    "gn:timezone":"Asia/Kolkata",
    "iso:country":"IN",
    "wof:name":"Marlab",
    "wof:placetype":"locality"
},
  "geometry": {"coordinates":[75.31235,33.33067],"type":"Point"}
}