{
  "type": "Feature",
  "properties": {
    "iso:country":"IN",
    "name:ara_x_preferred":[
        "\u0636\u0627\u062d\u064a\u0629 \u0643\u0627\u0644\u064a\u0627\u0646\u064a \u0646\u0627\u062c\u0627\u0631"
    ],
    "name:ben_bn_x_preferred":[
        "\u0995\u09b2\u09cd\u09af\u09be\u09a3\u09c0 \u09a8\u0997\u09b0"
    ],
    "name:ben_in_x_preferred":[
        "\u0995\u09b2\u09cd\u09af\u09be\u09a3\u09c0 \u09a8\u0997\u09b0"
    ],
    "name:eng_x_preferred":[
        "Kalyani Nagar"
    ],
    "name:guj_x_preferred":[
        "\u0a95\u0ab2\u0acd\u0aaf\u0abe\u0aa3\u0ac0 \u0aa8\u0a97\u0ab0"
    ],
    "name:hin_x_preferred":[
        "\u0915\u0932\u094d\u092f\u093e\u0923\u0940 \u0928\u0917\u0930"
    ],
    "name:kan_x_preferred":[
        "\u0c95\u0cb2\u0ccd\u0caf\u0cbe\u0ca3\u0cbf \u0ca8\u0c97\u0cb0\u0ccd"
    ],
    "name:mal_x_preferred":[
        "\u0d15\u0d32\u0d4d\u0d2f\u0d3e\u0d23\u0d3f \u0d28\u0d17\u0d7c"
    ],
    "name:mar_x_preferred":[
        "\u0915\u0932\u094d\u092f\u093e\u0923\u0940 \u0928\u0917\u0930"
    ],
    "name:mar_x_variant":[
        "Viman Nagar"
    ],
    "name:pan_x_preferred":[
        "\u0a15\u0a32\u0a3f\u0a06\u0a23\u0a40 \u0a28\u0a17\u0a30"
    ],
    "name:tam_x_preferred":[
        "\u0b95\u0bb2\u0bcd\u0baf\u0bbe\u0ba3\u0bbf \u0ba8\u0b95\u0bb0\u0bcd"
    ],
    "name:tel_x_preferred":[
        "\u0c15\u0c32\u0c4d\u0c2f\u0c3e\u0c23\u0c3f \u0c28\u0c17\u0c30\u0c4d"
    ],
    "name:urd_x_preferred":[
        "\u06a9\u0644\u06cc\u0627\u0646\u06cc \u0646\u06af\u0631"
    ],
    "qs:gn_adm0_cc":"IN",
    "qs:gn_fcode":"PPL",
    "qs:gn_local":1259229,
    "qs:gn_nam_loc":"Pune, Pune, Maharashtra, IN",
    "qs:gn_namadm1":"16",
    "qs:gn_name":"Kalyani Nagar",
    "qs:local_max":2969,
    "qs:local_sum":13446,
    "qs:localhoods":37,
    "qs:name":"Kalyani Nagar",
    "qs:name_adm0":"India",
    "qs:name_adm1":"Maharashtra",
    "qs:name_adm2":"Pune",
    "qs:name_local":"Pune",
    "qs:photo_max":183,
    "qs:photo_sum":458,
    "qs:placetype":"Suburb",
    "qs:quad_count":12,
    "qs:woe_adm0":23424848,
    "qs:woe_adm1":2345750,
    "qs:woe_adm2":12586544,
    "qs:woe_lau":0,
    "qs:woe_local":2295412,
    "qs:woe_ver":"7.10.0",
    "wd:wordcount":176,
    "wof:lang":[
        "eng"
    ],
    "wof:name":"Kalyani Nagar",
    "wof:placetype":"neighbourhood"
},
  "geometry": {"coordinates":[73.906953,18.541879],"type":"Point"}
}