{
  "type": "Feature",
  "properties": {
    "iso:country":"IN",
    "name:eng_x_preferred":[
        "Kalyani Nagar"
    ],
    "name:hin_x_preferred":[
        "\u0915\u0932\u094d\u092f\u093e\u0923\u0940 \u0928\u0917\u0930"
    ],
    "name:mar_x_preferred":[
        "\u0915\u0932\u094d\u092f\u093e\u0923\u0940 \u0928\u0917\u0930"
    ],
    "name:mar_x_variant":[
        "Viman Nagar"
    ],
    "qs:gn_adm0_cc":"IN",
    "qs:gn_fcode":"PPL",
    "qs:gn_local":1259229,
    "qs:gn_nam_loc":"Pune, Pune, Maharashtra, IN",
    "qs:gn_namadm1":"16",
    "qs:gn_name":"Kalyani Nagar",
    "qs:local_max":2969,
    "qs:local_sum":13446,
    "qs:localhoods":37,
    "qs:name":"Kalyani Nagar",
    "qs:name_adm0":"India",
    "qs:name_adm1":"Maharashtra",
    "qs:name_adm2":"Pune",
    "qs:name_local":"Pune",
    "qs:photo_max":183,
    "qs:photo_sum":458,
    "qs:placetype":"Suburb",
    "qs:quad_count":12,
    "qs:woe_adm0":23424848,
    "qs:woe_adm1":2345750,
    "qs:woe_adm2":12586544,
    "qs:woe_lau":0,
    "qs:woe_local":2295412,
    "qs:woe_ver":"7.10.0",
    "wd:wordcount":176,
    "wof:lang":[
        "eng"
    ],
    "wof:name":"Kalyani Nagar",
    "wof:placetype":"neighbourhood"
},
  "geometry": {"coordinates":[73.906953,18.541879],"type":"Point"}
}