{
  "type": "Feature",
  "properties": {
    "iso:country":"IN",
    "ks:ks_name":"Gayatapara",
    "ks:ks_pop":14,
    "ks:ks_type":"HABITATION",
    "name:eng_x_preferred":[
        "Gayatapara"
    ],
    "wof:name":"Gayatapara",
    "wof:placetype":"locality",
    "wof:population":14
},
  "geometry": {"coordinates":[81.13867399999999,18.941848],"type":"Point"}
}