{
  "type": "Feature",
  "properties": {
    "iso:country":"IN",
    "ks:ks_name":"Berapara",
    "ks:ks_pop":546,
    "ks:ks_type":"HABITATION",
    "ks:ks_uagg_main":0,
    "name:eng_x_preferred":[
        "Berapara"
    ],
    "wof:name":"Berapara",
    "wof:placetype":"neighbourhood",
    "wof:population":546
},
  "geometry": {"coordinates":[87.982187,22.719661],"type":"Point"}
}