{
  "type": "Feature",
  "properties": {
    "iso:country":"IN",
    "ks:ks_name":"Shankartola",
    "ks:ks_pop":128,
    "ks:ks_type":"HABITATION",
    "name:eng_x_preferred":[
        "Shankartola"
    ],
    "wof:name":"Shankartola",
    "wof:placetype":"locality",
    "wof:population":128
},
  "geometry": {"coordinates":[80.500957,21.266871],"type":"Point"}
}