{
  "type": "Feature",
  "properties": {
    "iso:country":"IN",
    "ks:ks_name":"Baramad Pur Khas",
    "ks:ks_pop":400,
    "ks:ks_type":"HABITATION",
    "name:eng_x_preferred":[
        "Baramad Pur Khas"
    ],
    "wof:name":"Baramad Pur Khas",
    "wof:placetype":"locality",
    "wof:population":400
},
  "geometry": {"coordinates":[82.46347400000001,26.433048],"type":"Point"}
}