{
  "type": "Feature",
  "properties": {
    "iso:country":"IN",
    "ks:ks_name":"Banharpali",
    "ks:ks_pop":90,
    "ks:ks_type":"HABITATION",
    "name:eng_x_preferred":[
        "Banharpali"
    ],
    "wof:name":"Banharpali",
    "wof:placetype":"locality",
    "wof:population":90
},
  "geometry": {"coordinates":[83.05828,20.952467],"type":"Point"}
}