{
  "type": "Feature",
  "properties": {
    "iso:country":"IN",
    "ks:ks_name":"Nuaguda 3",
    "ks:ks_pop":187,
    "ks:ks_type":"HABITATION",
    "name:eng_x_preferred":[
        "Nuaguda 3"
    ],
    "wof:name":"Nuaguda 3",
    "wof:placetype":"locality",
    "wof:population":187
},
  "geometry": {"coordinates":[82.37338,18.91041],"type":"Point"}
}