{
  "type": "Feature",
  "properties": {
    "gn:admin1_code":"19.0",
    "gn:asciiname":"Koditipalli",
    "gn:country_code":"IN",
    "gn:dem":766,
    "gn:feature_class":"P",
    "gn:feature_code":"PPL",
    "gn:name":"Koditipalli",
    "gn:population":0,
    "gn:timezone":"Asia/Kolkata",
    "iso:country":"IN",
    "wof:name":"Koditipalli",
    "wof:placetype":"locality"
},
  "geometry": {"coordinates":[78.43839,12.89139],"type":"Point"}
}