{
  "type": "Feature",
  "properties": {
    "iso:country":"IN",
    "ks:ks_name":"Ulipiri",
    "ks:ks_pop":58,
    "ks:ks_type":"HABITATION",
    "name:eng_x_preferred":[
        "Ulipiri"
    ],
    "wof:name":"Ulipiri",
    "wof:placetype":"locality",
    "wof:population":58
},
  "geometry": {"coordinates":[85.502456,23.018511],"type":"Point"}
}