{
  "type": "Feature",
  "properties": {
    "gn:admin1_code":"11.0",
    "gn:admin2_code":"33.0",
    "gn:asciiname":"Shili",
    "gn:country_code":"IN",
    "gn:dem":1946,
    "gn:feature_class":"P",
    "gn:feature_code":"PPL",
    "gn:name":"Sh\u012bli",
    "gn:population":0,
    "gn:timezone":"Asia/Kolkata",
    "iso:country":"IN",
    "name:ara_x_preferred":[
        "\u0634\u064a\u0644\u064a"
    ],
    "name:fas_x_preferred":[
        "\u0634\u06cc\u0644\u06cc"
    ],
    "name:msa_x_preferred":[
        "Shili"
    ],
    "wof:name":"Shili",
    "wof:placetype":"locality"
},
  "geometry": {"coordinates":[77.45322,30.93093],"type":"Point"}
}