{
  "type": "Feature",
  "properties": {
    "gn:admin1_code":"36.0",
    "gn:asciiname":"Mankara",
    "gn:country_code":"IN",
    "gn:dem":203,
    "gn:feature_class":"P",
    "gn:feature_code":"PPL",
    "gn:name":"Mankara",
    "gn:population":0,
    "gn:timezone":"Asia/Kolkata",
    "iso:country":"IN",
    "name:ceb_x_preferred":[
        "Mankara"
    ],
    "name:swe_x_preferred":[
        "Mankara"
    ],
    "wof:name":"Mankara",
    "wof:placetype":"locality"
},
  "geometry": {"coordinates":[79.67775,28.85385],"type":"Point"}
}