{
  "type": "Feature",
  "properties": {
    "iso:country":"IN",
    "ks:ks_name":"Palbasti",
    "ks:ks_pop":412,
    "ks:ks_type":"HABITATION",
    "name:eng_x_preferred":[
        "Palbasti"
    ],
    "wof:name":"Palbasti",
    "wof:placetype":"locality",
    "wof:population":412
},
  "geometry": {"coordinates":[83.41631599999999,24.74435],"type":"Point"}
}