{
  "type": "Feature",
  "properties": {
    "iso:country":"IN",
    "name:ara_x_preferred":[
        "\u062a\u064a\u0648\u0627\u0645\u0648"
    ],
    "name:ben_bn_x_preferred":[
        "\u09a4\u09bf\u0993\u09df\u09be\u09ae\u09be\u0989"
    ],
    "name:ben_in_x_preferred":[
        "\u09a4\u09bf\u0993\u09df\u09be\u09ae\u09be\u0989"
    ],
    "name:eng_x_preferred":[
        "Tiwamau"
    ],
    "name:guj_x_preferred":[
        "\u0aa4\u0abf\u0ab5\u0abe\u0aae\u0abe\u0a89"
    ],
    "name:hin_x_preferred":[
        "\u0924\u093f\u0935\u093e\u092e\u093e\u090a"
    ],
    "name:kan_x_preferred":[
        "\u0ca4\u0cbf\u0cb5\u0cbe\u0cae\u0cbe\u0cb5\u0cc1"
    ],
    "name:mal_x_preferred":[
        "\u0d24\u0d3f\u0d35\u0d3e\u0d2e\u0d41"
    ],
    "name:mar_x_preferred":[
        "\u0924\u093f\u0935\u093e\u092e\u093e\u090a"
    ],
    "name:pan_x_preferred":[
        "\u0a24\u0a3f\u0a35\u0a3e\u0a2e\u0a3e\u0a13"
    ],
    "name:tam_x_preferred":[
        "\u0b9f\u0bbf\u0bb5\u0bae\u0bcc"
    ],
    "name:tel_x_preferred":[
        "\u0c24\u0c3f\u0c35\u0c3e\u0c2e\u0c4c"
    ],
    "name:urd_x_preferred":[
        "\u062a\u06cc\u0648\u0627 \u0645\u0626\u0648"
    ],
    "qs:gn_adm0_cc":"IN",
    "qs:gn_local":1264733,
    "qs:local_max":321,
    "qs:local_sum":1015,
    "qs:localhoods":8,
    "qs:name":"Tiwamau",
    "qs:name_adm0":"India",
    "qs:name_adm1":"Uttar Pradesh",
    "qs:name_adm2":"Lucknow",
    "qs:name_local":"Lucknow",
    "qs:photo_max":42,
    "qs:photo_sum":61,
    "qs:placetype":"Suburb",
    "qs:quad_count":5,
    "qs:woe_adm0":23424848,
    "qs:woe_adm1":2345760,
    "qs:woe_adm2":12586761,
    "qs:woe_lau":0,
    "qs:woe_local":2295377,
    "qs:woe_ver":"7.10.0",
    "wof:lang":[
        "eng"
    ],
    "wof:name":"Tiwamau",
    "wof:placetype":"neighbourhood"
},
  "geometry": {"coordinates":[80.97214200000001,26.849803],"type":"Point"}
}