{
  "type": "Feature",
  "properties": {
    "gn:admin1_code":"12.0",
    "gn:admin2_code":"8.0",
    "gn:asciiname":"Hakabor",
    "gn:country_code":"IN",
    "gn:dem":1583,
    "gn:feature_class":"P",
    "gn:feature_code":"PPL",
    "gn:name":"H\u0101kabor",
    "gn:population":0,
    "gn:timezone":"Asia/Kolkata",
    "iso:country":"IN",
    "name:eng_x_preferred":[
        "H\u0101kabor"
    ],
    "wof:name":"Hakabor",
    "wof:placetype":"locality"
},
  "geometry": {"coordinates":[74.63164,34.28104],"type":"Point"}
}