{
  "type": "Feature",
  "properties": {
    "gn:admin1_code":"25.0",
    "gn:admin2_code":"620.0",
    "gn:asciiname":"Nayinankulam",
    "gn:country_code":"IN",
    "gn:dem":22,
    "gn:feature_class":"P",
    "gn:feature_code":"PPL",
    "gn:name":"Nayin\u0101nkulam",
    "gn:population":0,
    "gn:timezone":"Asia/Kolkata",
    "iso:country":"IN",
    "ks:ks_name":"Nainankulam",
    "ks:ks_pop":647,
    "ks:ks_type":"VILLAGE",
    "ks:ks_uagg_main":0,
    "name:eng_x_preferred":[
        "Nainankulam"
    ],
    "wof:name":"Nainankulam",
    "wof:placetype":"locality",
    "wof:population":647
},
  "geometry": {"coordinates":[79.316185,10.39819],"type":"Point"}
}