{
  "type": "Feature",
  "properties": {
    "gn:admin1_code":"16",
    "gn:admin2_code":"510.0",
    "gn:asciiname":"Marwadi",
    "gn:country_code":"IN",
    "gn:dem":284,
    "gn:feature_class":"P",
    "gn:feature_code":"PPL",
    "gn:name":"M\u0101rw\u0101di",
    "gn:population":0,
    "gn:timezone":"Asia/Kolkata",
    "iso:country":"IN",
    "ks:ks_alt_nam":"M\u0101rw\u0101di",
    "ks:ks_name":"Marwadi",
    "ks:ks_pop":397,
    "ks:ks_type":"VILLAGE",
    "name:eng_x_preferred":[
        "Marwadi"
    ],
    "name:eng_x_variant":[
        "M\u0101rw\u0101di"
    ],
    "wof:name":"Marwadi",
    "wof:placetype":"locality",
    "wof:population":397
},
  "geometry": {"coordinates":[77.910169,20.58305],"type":"Point"}
}