{
  "type": "Feature",
  "properties": {
    "iso:country":"IN",
    "ks:ks_name":"Sargiguda",
    "ks:ks_pop":331,
    "ks:ks_type":"VILLAGE",
    "name:eng_x_preferred":[
        "Sargiguda"
    ],
    "wof:name":"Sargiguda",
    "wof:placetype":"locality",
    "wof:population":331
},
  "geometry": {"coordinates":[82.02565,18.4299],"type":"Point"}
}