{
  "type": "Feature",
  "properties": {
    "iso:country":"IN",
    "ks:ks_name":"Panchayathukavala",
    "ks:ks_pop":1865,
    "ks:ks_type":"HABITATION",
    "name:eng_x_preferred":[
        "Panchayathukavala"
    ],
    "wof:name":"Panchayathukavala",
    "wof:placetype":"locality",
    "wof:population":1865
},
  "geometry": {"coordinates":[76.332488,9.626597],"type":"Point"}
}