{
  "type": "Feature",
  "properties": {
    "gn:admin1_code":"39.0",
    "gn:admin2_code":"65.0",
    "gn:asciiname":"Diwali",
    "gn:country_code":"IN",
    "gn:dem":863,
    "gn:feature_class":"P",
    "gn:feature_code":"PPL",
    "gn:name":"Diw\u0101l\u012b",
    "gn:population":0,
    "gn:timezone":"Asia/Kolkata",
    "iso:country":"IN",
    "wof:name":"Diwali",
    "wof:placetype":"locality"
},
  "geometry": {"coordinates":[80.05192,29.24976],"type":"Point"}
}