{
  "type": "Feature",
  "properties": {
    "iso:country":"IN",
    "ks:ks_name":"Durganagar",
    "ks:ks_pop":1959,
    "ks:ks_type":"VILLAGE",
    "name:eng_x_preferred":[
        "Durganagar"
    ],
    "wof:name":"Durganagar",
    "wof:placetype":"locality",
    "wof:population":1959
},
  "geometry": {"coordinates":[89.569247,26.08994],"type":"Point"}
}