{
  "type": "Feature",
  "properties": {
    "iso:country":"IN",
    "ks:ks_name":"Ramnagar",
    "ks:ks_pop":1677,
    "ks:ks_type":"HABITATION",
    "name:eng_x_preferred":[
        "Ramnagar"
    ],
    "wof:name":"Ramnagar",
    "wof:placetype":"locality",
    "wof:population":1677
},
  "geometry": {"coordinates":[74.893736,27.141456],"type":"Point"}
}