{
  "type": "Feature",
  "properties": {
    "gn:admin1_code":"19.0",
    "gn:admin2_code":"570.0",
    "gn:asciiname":"Kodur",
    "gn:country_code":"IN",
    "gn:dem":657,
    "gn:feature_class":"P",
    "gn:feature_code":"PPL",
    "gn:name":"Kodur",
    "gn:population":0,
    "gn:timezone":"Asia/Kolkata",
    "iso:country":"IN",
    "ks:ks_name":"Kodur",
    "ks:ks_pop":1004,
    "ks:ks_type":"VILLAGE",
    "name:eng_x_preferred":[
        "Kodur"
    ],
    "wof:name":"Kodur",
    "wof:placetype":"locality",
    "wof:population":1004
},
  "geometry": {"coordinates":[75.230993,13.512571],"type":"Point"}
}