{
  "type": "Feature",
  "properties": {
    "iso:country":"IN",
    "ks:ks_alt_nam":"bhoka pur",
    "ks:ks_name":"Bhoka Pur",
    "ks:ks_pop":337,
    "ks:ks_type":"HABITATION",
    "name:eng_x_preferred":[
        "Bhoka Pur"
    ],
    "wof:name":"Bhoka Pur",
    "wof:placetype":"locality",
    "wof:population":337
},
  "geometry": {"coordinates":[80.940575,26.690698],"type":"Point"}
}