{
  "type": "Feature",
  "properties": {
    "iso:country":"IN",
    "ks:ks_name":"Khandekarwasti",
    "ks:ks_pop":160,
    "ks:ks_type":"HABITATION",
    "name:eng_x_preferred":[
        "Khandekarwasti"
    ],
    "wof:name":"Khandekarwasti",
    "wof:placetype":"locality",
    "wof:population":160
},
  "geometry": {"coordinates":[75.60530900000001,17.394297],"type":"Point"}
}