{
  "type": "Feature",
  "properties": {
    "gn:admin1_code":"13.0",
    "gn:admin2_code":"595.0",
    "gn:asciiname":"Nedungad",
    "gn:country_code":"IN",
    "gn:dem":7,
    "gn:feature_class":"P",
    "gn:feature_code":"PPL",
    "gn:name":"Nedungad",
    "gn:population":0,
    "gn:timezone":"Asia/Kolkata",
    "iso:country":"IN",
    "ks:ks_name":"Nedungad",
    "ks:ks_pop":457,
    "ks:ks_type":"HABITATION",
    "name:eng_x_preferred":[
        "Nedungad"
    ],
    "name:spa_x_preferred":[
        "Nedungad"
    ],
    "wof:name":"Nedungad",
    "wof:placetype":"locality",
    "wof:population":457
},
  "geometry": {"coordinates":[76.215945,10.078673],"type":"Point"}
}