{
  "type": "Feature",
  "properties": {
    "iso:country":"IN",
    "ks:ks_alt_nam":"mushartoli",
    "ks:ks_name":"Mushartoli",
    "ks:ks_pop":441,
    "ks:ks_type":"HABITATION",
    "name:eng_x_preferred":[
        "Mushartoli"
    ],
    "wof:name":"Mushartoli",
    "wof:placetype":"locality",
    "wof:population":441
},
  "geometry": {"coordinates":[84.939133,25.027772],"type":"Point"}
}