{
  "type": "Feature",
  "properties": {
    "iso:country":"IN",
    "ks:ks_name":"Bapanmode",
    "ks:ks_pop":257,
    "ks:ks_type":"HABITATION",
    "name:eng_x_preferred":[
        "Bapanmode"
    ],
    "wof:name":"Bapanmode",
    "wof:placetype":"locality",
    "wof:population":257
},
  "geometry": {"coordinates":[78.97453400000001,16.501578],"type":"Point"}
}