{
  "type": "Feature",
  "properties": {
    "gn:admin1_code":"34.0",
    "gn:admin2_code":"228.0",
    "gn:asciiname":"Karima Bigha",
    "gn:country_code":"IN",
    "gn:dem":63,
    "gn:feature_class":"P",
    "gn:feature_code":"PPL",
    "gn:name":"Karima Bigha",
    "gn:population":0,
    "gn:timezone":"Asia/Kolkata",
    "iso:country":"IN",
    "wof:name":"Karima Bigha",
    "wof:placetype":"locality"
},
  "geometry": {"coordinates":[85.79111999999998,25.04931],"type":"Point"}
}