{
  "type": "Feature",
  "properties": {
    "iso:country":"IN",
    "ks:ks_name":"Momin Chak",
    "ks:ks_type":"VILLAGE",
    "name:eng_x_preferred":[
        "Momin Chak"
    ],
    "wof:name":"Momin Chak",
    "wof:placetype":"locality"
},
  "geometry": {"coordinates":[78.60199,29.228562],"type":"Point"}
}