{
  "type": "Feature",
  "properties": {
    "iso:country":"IN",
    "ks:ks_name":"Battahole",
    "ks:ks_pop":52,
    "ks:ks_type":"HABITATION",
    "name:eng_x_preferred":[
        "Battahole"
    ],
    "wof:name":"Battahole",
    "wof:placetype":"locality",
    "wof:population":52
},
  "geometry": {"coordinates":[75.069264,13.243416],"type":"Point"}
}