{
  "type": "Feature",
  "properties": {
    "gn:admin1_code":"19.0",
    "gn:admin2_code":"570.0",
    "gn:asciiname":"Kallumane",
    "gn:country_code":"IN",
    "gn:dem":925,
    "gn:feature_class":"P",
    "gn:feature_code":"PPL",
    "gn:name":"Kalluman\u0113",
    "gn:population":0,
    "gn:timezone":"Asia/Kolkata",
    "iso:country":"IN",
    "ks:ks_name":"Kalmane",
    "ks:ks_pop":258,
    "ks:ks_type":"VILLAGE",
    "name:eng_x_preferred":[
        "Kalmane"
    ],
    "name:eng_x_variant":[
        "Kallumane"
    ],
    "wof:name":"Kalmane",
    "wof:placetype":"locality",
    "wof:population":258
},
  "geometry": {"coordinates":[75.484376,13.218109],"type":"Point"}
}