{
  "type": "Feature",
  "properties": {
    "iso:country":"IN",
    "ks:ks_name":"Bajari",
    "ks:ks_pop":264,
    "ks:ks_type":"VILLAGE",
    "name:eng_x_preferred":[
        "Bajari"
    ],
    "wof:name":"Bajari",
    "wof:placetype":"locality",
    "wof:population":264
},
  "geometry": {"coordinates":[78.333984,30.907524],"type":"Point"}
}