{
  "type": "Feature",
  "properties": {
    "iso:country":"IN",
    "ks:ks_name":"Mudakaru",
    "ks:ks_pop":161,
    "ks:ks_type":"HABITATION",
    "name:eng_x_preferred":[
        "Mudakaru"
    ],
    "wof:name":"Mudakaru",
    "wof:placetype":"locality",
    "wof:population":161
},
  "geometry": {"coordinates":[83.073599,18.675063],"type":"Point"}
}