{
  "type": "Feature",
  "properties": {
    "iso:country":"IN",
    "ks:ks_name":"Chak Paran",
    "ks:ks_pop":1258,
    "ks:ks_type":"VILLAGE",
    "ks:ks_uagg_main":0,
    "name:eng_x_preferred":[
        "Chak Paran"
    ],
    "wof:name":"Chak Paran",
    "wof:placetype":"locality",
    "wof:population":1258
},
  "geometry": {"coordinates":[88.201633,22.40266],"type":"Point"}
}