{
  "type": "Feature",
  "properties": {
    "iso:country":"IN",
    "ks:ks_name":"Kotwalia",
    "ks:ks_pop":130,
    "ks:ks_type":"HABITATION",
    "name:eng_x_preferred":[
        "Kotwalia"
    ],
    "wof:name":"Kotwalia",
    "wof:placetype":"locality",
    "wof:population":130
},
  "geometry": {"coordinates":[73.67663899999999,21.157167],"type":"Point"}
}