{
  "type": "Feature",
  "properties": {
    "gn:admin1_code":"28.0",
    "gn:admin2_code":"343",
    "gn:asciiname":"Kismat",
    "gn:country_code":"IN",
    "gn:dem":6,
    "gn:feature_class":"P",
    "gn:feature_code":"PPL",
    "gn:name":"Kismat",
    "gn:population":0,
    "gn:timezone":"Asia/Kolkata",
    "iso:country":"IN",
    "name:hin_x_preferred":[
        "\u0915\u093f\u0938\u094d\u092e\u0924"
    ],
    "wof:name":"Kismat",
    "wof:placetype":"locality"
},
  "geometry": {"coordinates":[88.26139000000001,22.29361],"type":"Point"}
}