{
  "type": "Feature",
  "properties": {
    "iso:country":"IN",
    "ks:ks_name":"Thakuran",
    "ks:ks_pop":60,
    "ks:ks_type":"HABITATION",
    "name:eng_x_preferred":[
        "Thakuran"
    ],
    "wof:name":"Thakuran",
    "wof:placetype":"locality",
    "wof:population":60
},
  "geometry": {"coordinates":[82.763356,25.119253],"type":"Point"}
}