{
  "type": "Feature",
  "properties": {
    "iso:country":"IN",
    "ks:ks_name":"Silingi",
    "ks:ks_pop":41,
    "ks:ks_type":"VILLAGE",
    "name:eng_x_preferred":[
        "Silingi"
    ],
    "wof:name":"Silingi",
    "wof:placetype":"locality",
    "wof:population":41
},
  "geometry": {"coordinates":[83.662631,20.018195],"type":"Point"}
}