{
  "type": "Feature",
  "properties": {
    "gn:admin1_code":"36.0",
    "gn:admin2_code":"173.0",
    "gn:asciiname":"Baranpur",
    "gn:country_code":"IN",
    "gn:dem":100,
    "gn:feature_class":"P",
    "gn:feature_code":"PPL",
    "gn:name":"Baranpur",
    "gn:population":0,
    "gn:timezone":"Asia/Kolkata",
    "iso:country":"IN",
    "ks:ks_name":"Baranpur",
    "ks:ks_pop":1063,
    "ks:ks_type":"VILLAGE",
    "ks:ks_uagg_main":0,
    "name:eng_x_preferred":[
        "Baranpur"
    ],
    "wof:name":"Baranpur",
    "wof:placetype":"neighbourhood",
    "wof:population":1063
},
  "geometry": {"coordinates":[81.95358400000001,25.887797],"type":"Point"}
}