{
  "type": "Feature",
  "properties": {
    "iso:country":"IN",
    "ks:ks_name":"Adegaon Khurd",
    "ks:ks_pop":1385,
    "ks:ks_type":"VILLAGE",
    "name:eng_x_preferred":[
        "Adegaon Khurd"
    ],
    "wof:name":"Adegaon Khurd",
    "wof:placetype":"locality",
    "wof:population":1385
},
  "geometry": {"coordinates":[78.787862,22.799979],"type":"Point"}
}