{
  "type": "Feature",
  "properties": {
    "iso:country":"IN",
    "ks:ks_name":"Pindeware",
    "ks:ks_pop":769,
    "ks:ks_type":"HABITATION",
    "name:eng_x_preferred":[
        "Pindeware"
    ],
    "wof:name":"Pindeware",
    "wof:placetype":"locality",
    "wof:population":769
},
  "geometry": {"coordinates":[74.0996,16.361428],"type":"Point"}
}