{
  "type": "Feature",
  "properties": {
    "gn:admin1_code":"10.0",
    "gn:admin2_code":"88.0",
    "gn:asciiname":"Dadsia",
    "gn:country_code":"IN",
    "gn:dem":204,
    "gn:feature_class":"P",
    "gn:feature_code":"PPL",
    "gn:name":"Dadsia",
    "gn:population":0,
    "gn:timezone":"Asia/Kolkata",
    "iso:country":"IN",
    "wof:name":"Dadsia",
    "wof:placetype":"locality"
},
  "geometry": {"coordinates":[77.36979000000002,28.4646],"type":"Point"}
}