{
  "type": "Feature",
  "properties": {
    "iso:country":"IN",
    "ks:ks_name":"Suddabanda",
    "ks:ks_pop":24,
    "ks:ks_type":"HABITATION",
    "name:eng_x_preferred":[
        "Suddabanda"
    ],
    "wof:name":"Suddabanda",
    "wof:placetype":"locality",
    "wof:population":24
},
  "geometry": {"coordinates":[78.97998800000001,17.37408],"type":"Point"}
}