{
  "type": "Feature",
  "properties": {
    "iso:country":"IN",
    "ks:ks_name":"Maganiya",
    "ks:ks_pop":254,
    "ks:ks_type":"HABITATION",
    "name:eng_x_preferred":[
        "Maganiya"
    ],
    "wof:name":"Maganiya",
    "wof:placetype":"locality",
    "wof:population":254
},
  "geometry": {"coordinates":[81.76555,24.740264],"type":"Point"}
}