{
  "type": "Feature",
  "properties": {
    "gn:admin1_code":"21",
    "gn:admin2_code":"370.0",
    "gn:asciiname":"Dungri",
    "gn:country_code":"IN",
    "gn:dem":212,
    "gn:feature_class":"P",
    "gn:feature_code":"PPL",
    "gn:name":"Dungri",
    "gn:population":0,
    "gn:timezone":"Asia/Kolkata",
    "iso:country":"IN",
    "wof:name":"Dungri",
    "wof:placetype":"locality"
},
  "geometry": {"coordinates":[83.56222,21.70034],"type":"Point"}
}