{
  "type": "Feature",
  "properties": {
    "iso:country":"IN",
    "ks:ks_name":"Pachma",
    "ks:ks_type":"VILLAGE",
    "name:eng_x_preferred":[
        "Pachma"
    ],
    "wof:name":"Pachma",
    "wof:placetype":"locality"
},
  "geometry": {"coordinates":[83.438563,26.429627],"type":"Point"}
}