{
  "type": "Feature",
  "properties": {
    "iso:country":"IN",
    "ks:ks_name":"Kotkodo",
    "ks:ks_pop":164,
    "ks:ks_type":"VILLAGE",
    "name:eng_x_preferred":[
        "Kotkodo"
    ],
    "wof:name":"Kotkodo",
    "wof:placetype":"locality",
    "wof:population":164
},
  "geometry": {"coordinates":[81.30246200000001,19.931393],"type":"Point"}
}