{
  "type": "Feature",
  "properties": {
    "iso:country":"IN",
    "ks:ks_name":"Dalua Charra",
    "ks:ks_pop":573,
    "ks:ks_type":"HABITATION",
    "name:eng_x_preferred":[
        "Dalua Charra"
    ],
    "wof:name":"Dalua Charra",
    "wof:placetype":"locality",
    "wof:population":573
},
  "geometry": {"coordinates":[92.33748900000001,24.44416],"type":"Point"}
}