{
  "type": "Feature",
  "properties": {
    "gn:admin1_code":"24.0",
    "gn:admin2_code":"118.0",
    "gn:asciiname":"Keranji ka Gurha",
    "gn:country_code":"IN",
    "gn:dem":306,
    "gn:feature_class":"P",
    "gn:feature_code":"PPL",
    "gn:name":"Keranji ka G\u016brha",
    "gn:population":0,
    "gn:timezone":"Asia/Kolkata",
    "iso:country":"IN",
    "wof:name":"Keranji ka Gurha",
    "wof:placetype":"locality"
},
  "geometry": {"coordinates":[73.49403000000002,25.38906],"type":"Point"}
}