{
  "type": "Feature",
  "properties": {
    "gn:admin1_code":"12.0",
    "gn:asciiname":"Amokhor",
    "gn:country_code":"IN",
    "gn:dem":590,
    "gn:feature_class":"P",
    "gn:feature_code":"PPL",
    "gn:name":"Amokhor",
    "gn:population":0,
    "gn:timezone":"Asia/Kolkata",
    "iso:country":"IN",
    "wof:name":"Amokhor",
    "wof:placetype":"locality"
},
  "geometry": {"coordinates":[74.38914,33.02248],"type":"Point"}
}