{
  "type": "Feature",
  "properties": {
    "iso:country":"IN",
    "ks:ks_alt_nam":"PROPER RANGAMATI",
    "ks:ks_name":"Proper Rangamati",
    "ks:ks_pop":558,
    "ks:ks_type":"HABITATION",
    "ks:ks_uagg_main":0,
    "name:eng_x_preferred":[
        "Proper Rangamati"
    ],
    "wof:name":"Proper Rangamati",
    "wof:placetype":"neighbourhood",
    "wof:population":558
},
  "geometry": {"coordinates":[92.291611,24.279754],"type":"Point"}
}