{
  "type": "Feature",
  "properties": {
    "iso:country":"IN",
    "ks:ks_alt_nam":"MAFI MAHUAHI",
    "ks:ks_name":"Mafi Mahuahi",
    "ks:ks_pop":857,
    "ks:ks_type":"HABITATION",
    "name:eng_x_preferred":[
        "Mafi Mahuahi"
    ],
    "wof:name":"Mafi Mahuahi",
    "wof:placetype":"locality",
    "wof:population":857
},
  "geometry": {"coordinates":[86.31089299999999,26.434496],"type":"Point"}
}