{
  "type": "Feature",
  "properties": {
    "iso:country":"IN",
    "ks:ks_name":"Chakla Par",
    "ks:ks_pop":142,
    "ks:ks_type":"HABITATION",
    "name:eng_x_preferred":[
        "Chakla Par"
    ],
    "wof:name":"Chakla Par",
    "wof:placetype":"locality",
    "wof:population":142
},
  "geometry": {"coordinates":[84.349374,24.413654],"type":"Point"}
}