{
  "type": "Feature",
  "properties": {
    "iso:country":"IN",
    "ks:ks_name":"Rowale",
    "ks:ks_pop":442,
    "ks:ks_type":"VILLAGE",
    "name:eng_x_preferred":[
        "Rowale"
    ],
    "wof:name":"Rowale",
    "wof:placetype":"locality",
    "wof:population":442
},
  "geometry": {"coordinates":[73.09511999999999,17.907751],"type":"Point"}
}