{
  "type": "Feature",
  "properties": {
    "gn:admin1_code":"11",
    "gn:admin2_code":"30.0",
    "gn:asciiname":"Bareda",
    "gn:country_code":"IN",
    "gn:dem":1012,
    "gn:feature_class":"P",
    "gn:feature_code":"PPL",
    "gn:name":"Bareda",
    "gn:population":0,
    "gn:timezone":"Asia/Kolkata",
    "iso:country":"IN",
    "wof:name":"Bareda",
    "wof:placetype":"locality"
},
  "geometry": {"coordinates":[76.75294,31.44718],"type":"Point"}
}