{
  "type": "Feature",
  "properties": {
    "iso:country":"IN",
    "ks:ks_name":"Nagla Dugar",
    "ks:ks_pop":200,
    "ks:ks_type":"HABITATION",
    "name:eng_x_preferred":[
        "Nagla Dugar"
    ],
    "wof:name":"Nagla Dugar",
    "wof:placetype":"locality",
    "wof:population":200
},
  "geometry": {"coordinates":[78.59237400000001,27.985721],"type":"Point"}
}