{
  "type": "Feature",
  "properties": {
    "gn:admin1_code":"21",
    "gn:admin2_code":"370.0",
    "gn:asciiname":"Mumdabahal",
    "gn:country_code":"IN",
    "gn:dem":233,
    "gn:feature_class":"P",
    "gn:feature_code":"PPL",
    "gn:name":"Mumdabah\u0101l",
    "gn:population":0,
    "gn:timezone":"Asia/Kolkata",
    "iso:country":"IN",
    "ks:ks_name":"Mundabahal",
    "ks:ks_pop":242,
    "ks:ks_type":"VILLAGE",
    "name:eng_x_preferred":[
        "Mundabahal"
    ],
    "name:eng_x_variant":[
        "Mumdabahal"
    ],
    "wof:name":"Mundabahal",
    "wof:placetype":"locality",
    "wof:population":242
},
  "geometry": {"coordinates":[83.378282,21.499815],"type":"Point"}
}