{
  "type": "Feature",
  "properties": {
    "gn:admin1_code":"36.0",
    "gn:admin2_code":"161",
    "gn:asciiname":"Zahirpura",
    "gn:country_code":"IN",
    "gn:dem":143,
    "gn:feature_class":"P",
    "gn:feature_code":"PPL",
    "gn:name":"Z\u0101hirpura",
    "gn:population":0,
    "gn:timezone":"Asia/Kolkata",
    "iso:country":"IN",
    "name:und_x_variant":[
        "Z\u0101hirpura",
        "Z\u0101harpura"
    ],
    "wof:name":"Zahirpura",
    "wof:placetype":"locality"
},
  "geometry": {"coordinates":[79.13629,26.49984000000001],"type":"Point"}
}