{
  "type": "Feature",
  "properties": {
    "iso:country":"IN",
    "ks:ks_name":"Jambad",
    "ks:ks_pop":152,
    "ks:ks_type":"VILLAGE",
    "name:eng_x_preferred":[
        "Jambad"
    ],
    "wof:name":"Jambad",
    "wof:placetype":"locality",
    "wof:population":152
},
  "geometry": {"coordinates":[86.763475,23.298213],"type":"Point"}
}