{
  "type": "Feature",
  "properties": {
    "iso:country":"IN",
    "ks:ks_name":"Pakhanna Bhairabpur",
    "ks:ks_pop":1210,
    "ks:ks_type":"VILLAGE",
    "ks:ks_uagg_main":0,
    "name:eng_x_preferred":[
        "Pakhanna Bhairabpur"
    ],
    "wof:name":"Pakhanna Bhairabpur",
    "wof:placetype":"neighbourhood",
    "wof:population":1210
},
  "geometry": {"coordinates":[87.37182900000001,23.414665],"type":"Point"}
}