{
  "type": "Feature",
  "properties": {
    "gn:admin1_code":"2.0",
    "gn:admin2_code":"544.0",
    "gn:asciiname":"Dalupadu",
    "gn:country_code":"IN",
    "gn:dem":1075,
    "gn:feature_class":"P",
    "gn:feature_code":"PPL",
    "gn:name":"Dalup\u0101du",
    "gn:population":0,
    "gn:timezone":"Asia/Kolkata",
    "iso:country":"IN",
    "wof:name":"Dalupadu",
    "wof:placetype":"locality"
},
  "geometry": {"coordinates":[83.06341,18.37136],"type":"Point"}
}