{
  "type": "Feature",
  "properties": {
    "iso:country":"IN",
    "ks:ks_name":"Jamli Chhoti",
    "ks:ks_pop":682,
    "ks:ks_type":"VILLAGE",
    "name:eng_x_preferred":[
        "Jamli Chhoti"
    ],
    "wof:name":"Jamli Chhoti",
    "wof:placetype":"locality",
    "wof:population":682
},
  "geometry": {"coordinates":[74.575019,22.494091],"type":"Point"}
}