{
  "type": "Feature",
  "properties": {
    "iso:country":"IN",
    "ks:ks_name":"Hiremath",
    "ks:ks_pop":728,
    "ks:ks_type":"HABITATION",
    "ks:ks_uagg_main":0,
    "name:eng_x_preferred":[
        "Hiremath"
    ],
    "wof:name":"Hiremath",
    "wof:placetype":"neighbourhood",
    "wof:population":728
},
  "geometry": {"coordinates":[74.43419799999999,14.267626],"type":"Point"}
}