{
  "type": "Feature",
  "properties": {
    "iso:country":"IN",
    "ks:ks_name":"Kolathur North",
    "ks:ks_pop":898,
    "ks:ks_type":"HABITATION",
    "name:eng_x_preferred":[
        "Kolathur North"
    ],
    "wof:name":"Kolathur North",
    "wof:placetype":"locality",
    "wof:population":898
},
  "geometry": {"coordinates":[75.78217100000001,11.422471],"type":"Point"}
}