{
  "type": "Feature",
  "properties": {
    "gn:admin1_code":"11",
    "gn:admin2_code":"30.0",
    "gn:asciiname":"Pojahn",
    "gn:country_code":"IN",
    "gn:dem":1112,
    "gn:feature_class":"P",
    "gn:feature_code":"PPL",
    "gn:name":"Poj\u0101hn",
    "gn:population":0,
    "gn:timezone":"Asia/Kolkata",
    "iso:country":"IN",
    "wof:name":"Pojahn",
    "wof:placetype":"locality"
},
  "geometry": {"coordinates":[76.68149,31.23641],"type":"Point"}
}