{
  "type": "Feature",
  "properties": {
    "iso:country":"IN",
    "ks:ks_alt_nam":"N. RATI",
    "ks:ks_name":"N. Rati",
    "ks:ks_pop":96,
    "ks:ks_type":"HABITATION",
    "name:eng_x_preferred":[
        "N. Rati"
    ],
    "wof:name":"N. Rati",
    "wof:placetype":"locality",
    "wof:population":96
},
  "geometry": {"coordinates":[78.653633,27.255687],"type":"Point"}
}