{
  "type": "Feature",
  "properties": {
    "gn:admin1_code":"19.0",
    "gn:admin2_code":"568.0",
    "gn:asciiname":"Baragi",
    "gn:country_code":"IN",
    "gn:dem":609,
    "gn:feature_class":"P",
    "gn:feature_code":"PPL",
    "gn:name":"Baragi",
    "gn:population":0,
    "gn:timezone":"Asia/Kolkata",
    "iso:country":"IN",
    "ks:ks_name":"Baragi",
    "ks:ks_pop":499,
    "ks:ks_type":"VILLAGE",
    "name:eng_x_preferred":[
        "Baragi"
    ],
    "name:vie_x_preferred":[
        "Baragi"
    ],
    "wof:name":"Baragi",
    "wof:placetype":"locality",
    "wof:population":499
},
  "geometry": {"coordinates":[75.07994100000001,14.261064],"type":"Point"}
}