{
  "type": "Feature",
  "properties": {
    "iso:country":"IN",
    "ks:ks_name":"Maniyamthadam",
    "ks:ks_pop":816,
    "ks:ks_type":"HABITATION",
    "name:eng_x_preferred":[
        "Maniyamthadam"
    ],
    "wof:name":"Maniyamthadam",
    "wof:placetype":"locality",
    "wof:population":816
},
  "geometry": {"coordinates":[76.683065,9.9338],"type":"Point"}
}