{
  "type": "Feature",
  "properties": {
    "iso:country":"IN",
    "ks:ks_name":"Mallaram",
    "ks:ks_pop":2270,
    "ks:ks_type":"VILLAGE",
    "name:eng_x_preferred":[
        "Mallaram"
    ],
    "wof:name":"Mallaram",
    "wof:placetype":"locality",
    "wof:population":2270
},
  "geometry": {"coordinates":[79.777011,18.560167],"type":"Point"}
}