{
  "type": "Feature",
  "properties": {
    "iso:country":"IN",
    "ks:ks_name":"Panchudihchhit",
    "ks:ks_pop":469,
    "ks:ks_type":"VILLAGE",
    "ks:ks_uagg_main":0,
    "name:eng_x_preferred":[
        "Panchudihchhit"
    ],
    "wof:name":"Panchudihchhit",
    "wof:placetype":"neighbourhood",
    "wof:population":469
},
  "geometry": {"coordinates":[86.79787,24.370573],"type":"Point"}
}