{
  "type": "Feature",
  "properties": {
    "gn:admin1_code":"36.0",
    "gn:admin2_code":"181.0",
    "gn:asciiname":"Hardahi Tarhar",
    "gn:country_code":"IN",
    "gn:dem":111,
    "gn:feature_class":"P",
    "gn:feature_code":"PPL",
    "gn:name":"Hard\u0101hi Tarhar",
    "gn:population":0,
    "gn:timezone":"Asia/Kolkata",
    "iso:country":"IN",
    "wof:name":"Hardahi Tarhar",
    "wof:placetype":"locality"
},
  "geometry": {"coordinates":[81.79398,27.30917],"type":"Point"}
}