{
  "type": "Feature",
  "properties": {
    "iso:country":"IN",
    "ks:ks_name":"Jatindra Para",
    "ks:ks_pop":338,
    "ks:ks_type":"HABITATION",
    "name:eng_x_preferred":[
        "Jatindra Para"
    ],
    "wof:name":"Jatindra Para",
    "wof:placetype":"locality",
    "wof:population":338
},
  "geometry": {"coordinates":[91.87754099999999,23.974711],"type":"Point"}
}