{
  "type": "Feature",
  "properties": {
    "iso:country":"IN",
    "ks:ks_name":"Keezha Mavilai",
    "ks:ks_pop":394,
    "ks:ks_type":"HABITATION",
    "name:eng_x_preferred":[
        "Keezha Mavilai"
    ],
    "wof:name":"Keezha Mavilai",
    "wof:placetype":"locality",
    "wof:population":394
},
  "geometry": {"coordinates":[77.400802,8.130658],"type":"Point"}
}