{
  "type": "Feature",
  "properties": {
    "iso:country":"IN",
    "ks:ks_name":"Khera Pal",
    "ks:ks_pop":182,
    "ks:ks_type":"HABITATION",
    "name:eng_x_preferred":[
        "Khera Pal"
    ],
    "wof:name":"Khera Pal",
    "wof:placetype":"locality",
    "wof:population":182
},
  "geometry": {"coordinates":[73.503456,23.768825],"type":"Point"}
}