{
  "type": "Feature",
  "properties": {
    "gn:admin1_code":"39.0",
    "gn:admin2_code":"061",
    "gn:asciiname":"Bhalgaon",
    "gn:country_code":"IN",
    "gn:dem":1038,
    "gn:feature_class":"P",
    "gn:feature_code":"PPL",
    "gn:name":"Bhalgaon",
    "gn:population":0,
    "gn:timezone":"Asia/Kolkata",
    "iso:country":"IN",
    "wof:name":"Bhalgaon",
    "wof:placetype":"locality"
},
  "geometry": {"coordinates":[78.60531,29.88021],"type":"Point"}
}