{
  "type": "Feature",
  "properties": {
    "gn:admin1_code":"19.0",
    "gn:admin2_code":"572",
    "gn:asciiname":"Jarganahalli",
    "gn:country_code":"IN",
    "gn:dem":909,
    "gn:feature_class":"P",
    "gn:feature_code":"PPL",
    "gn:name":"Jarganahalli",
    "gn:population":0,
    "gn:timezone":"Asia/Kolkata",
    "iso:country":"IN",
    "wof:name":"Jarganahalli",
    "wof:placetype":"locality"
},
  "geometry": {"coordinates":[77.57609000000002,12.90151],"type":"Point"}
}