{
  "type": "Feature",
  "properties": {
    "iso:country":"IN",
    "ks:ks_name":"Kuttikkunnu Ambalam",
    "ks:ks_pop":717,
    "ks:ks_type":"HABITATION",
    "name:eng_x_preferred":[
        "Kuttikkunnu Ambalam"
    ],
    "wof:name":"Kuttikkunnu Ambalam",
    "wof:placetype":"locality",
    "wof:population":717
},
  "geometry": {"coordinates":[76.10171,10.919831],"type":"Point"}
}