{
  "type": "Feature",
  "properties": {
    "gn:admin1_code":"36",
    "gn:admin2_code":"185.0",
    "gn:asciiname":"Nalhiapur Mafi",
    "gn:country_code":"IN",
    "gn:dem":96,
    "gn:feature_class":"P",
    "gn:feature_code":"PPL",
    "gn:name":"Nalhi\u0101pur M\u0101fi",
    "gn:population":0,
    "gn:timezone":"Asia/Kolkata",
    "iso:country":"IN",
    "name:und_x_variant":[
        "Nalhi\u0101pur M\u0101fi",
        "Nalhi\u0101pur"
    ],
    "wof:name":"Nalhiapur Mafi",
    "wof:placetype":"neighbourhood"
},
  "geometry": {"coordinates":[82.38713,26.77506],"type":"Point"}
}