{
  "type": "Feature",
  "properties": {
    "iso:country":"IN",
    "ks:ks_name":"Jhanjhra",
    "ks:ks_pop":586,
    "ks:ks_type":"VILLAGE",
    "ks:ks_uagg_main":0,
    "name:eng_x_preferred":[
        "Jhanjhra"
    ],
    "wof:name":"Jhanjhra",
    "wof:placetype":"neighbourhood",
    "wof:population":586
},
  "geometry": {"coordinates":[88.32865700000001,22.412503],"type":"Point"}
}