{
  "type": "Feature",
  "properties": {
    "gn:country":"IN",
    "gn:fcode":"PPL",
    "gn:population":0,
    "iso:country":"IN",
    "name:ara_x_preferred":[
        "\u0643\u064a\u0644\u0643\u0627\u062a\u0627\u0644\u0627\u064a"
    ],
    "name:ben_bn_x_preferred":[
        "\u0995\u09c0\u09b2\u0995\u09be\u09a4\u09cd\u09a4\u09be\u09b2\u09be\u0987"
    ],
    "name:ben_in_x_preferred":[
        "\u0995\u09c0\u09b2\u0995\u09be\u09a4\u09cd\u09a4\u09be\u09b2\u09be\u0987"
    ],
    "name:guj_x_preferred":[
        "\u0a95\u0abf\u0ab2\u0a95\u0a9f\u0acd\u0a9f\u0ab2\u0abe\u0a88"
    ],
    "name:hin_x_preferred":[
        "\u0915\u093f\u0932\u094d\u0915\u093e\u0924\u0932\u093e\u0908"
    ],
    "name:kan_x_preferred":[
        "\u0c95\u0cbf\u0cb2\u0ccd\u0c95\u0c9f\u0ccd\u0c9f\u0cb2\u0caf\u0ccd"
    ],
    "name:mal_x_preferred":[
        "\u0d15\u0d3f\u0d7d\u0d15\u0d4d\u0d15\u0d1f\u0d4d\u0d1f\u0d32\u0d48"
    ],
    "name:mar_x_preferred":[
        "\u0915\u093f\u0932\u0915\u091f\u094d\u091f\u0932\u093e\u092f"
    ],
    "name:pan_x_preferred":[
        "\u0a15\u0a3f\u0a32\u0a15\u0a71\u0a1f\u0a3e\u0a32\u0a3e\u0a07"
    ],
    "name:tam_x_preferred":[
        "\u0b95\u0bc0\u0bb4\u0bcd\u0b95\u0bcd\u0b95\u0b9f\u0bcd\u0b9f\u0bb3\u0bc8"
    ],
    "name:tel_x_preferred":[
        "\u0c15\u0c3f\u0c32\u0c4d\u0c15\u0c3e\u0c1f\u0c4d\u0c1f\u0c32\u0c3e\u0c2f\u0c4d"
    ],
    "name:urd_x_preferred":[
        "\u06a9\u0650\u0644\u06a9\u0679\u0651\u0627 \u0644\u0627\u0626\u06cc"
    ],
    "qs:name":"Kilkattalai",
    "qs:name_adm0":"India",
    "qs:name_adm1":"Tamil Nadu",
    "qs:photos":3,
    "qs:photos_1k":1,
    "qs:photos_9k":1,
    "qs:photos_9r":1,
    "qs:photos_all":3,
    "qs:photos_sr":1,
    "qs:placetype":"Suburb",
    "qs:pop_sr":"0",
    "wof:name":"Kilkattalai",
    "wof:placetype":"neighbourhood",
    "wof:population":0
},
  "geometry": {"coordinates":[80.18167,12.95667],"type":"Point"}
}