{
  "type": "Feature",
  "properties": {
    "iso:country":"IN",
    "ks:ks_name":"Marar",
    "ks:ks_pop":252,
    "ks:ks_type":"VILLAGE",
    "name:eng_x_preferred":[
        "Marar"
    ],
    "wof:name":"Marar",
    "wof:placetype":"locality",
    "wof:population":252
},
  "geometry": {"coordinates":[83.23253699999999,26.412532],"type":"Point"}
}