{
  "type": "Feature",
  "properties": {
    "iso:country":"IN",
    "ks:ks_name":"Dimiripada",
    "ks:ks_pop":128,
    "ks:ks_type":"VILLAGE",
    "name:eng_x_preferred":[
        "Dimiripada"
    ],
    "wof:name":"Dimiripada",
    "wof:placetype":"locality",
    "wof:population":128
},
  "geometry": {"coordinates":[84.15010700000001,20.52339],"type":"Point"}
}