{
  "type": "Feature",
  "properties": {
    "iso:country":"IN",
    "ks:ks_name":"Subdi",
    "ks:ks_pop":574,
    "ks:ks_type":"VILLAGE",
    "ks:ks_uagg_main":0,
    "name:eng_x_preferred":[
        "Subdi"
    ],
    "wof:name":"Subdi",
    "wof:placetype":"locality",
    "wof:population":574
},
  "geometry": {"coordinates":[87.767726,21.765171],"type":"Point"}
}