{
  "type": "Feature",
  "properties": {
    "iso:country":"IN",
    "ks:ks_name":"Fanasmade",
    "ks:ks_pop":61,
    "ks:ks_type":"HABITATION",
    "name:eng_x_preferred":[
        "Fanasmade"
    ],
    "wof:name":"Fanasmade",
    "wof:placetype":"locality",
    "wof:population":61
},
  "geometry": {"coordinates":[73.75937,15.792263],"type":"Point"}
}