{
  "type": "Feature",
  "properties": {
    "iso:country":"IN",
    "ks:ks_name":"Panchur",
    "ks:ks_pop":691,
    "ks:ks_type":"VILLAGE",
    "name:eng_x_preferred":[
        "Panchur"
    ],
    "wof:name":"Panchur",
    "wof:placetype":"locality",
    "wof:population":691
},
  "geometry": {"coordinates":[86.955831,22.85121],"type":"Point"}
}