{
  "type": "Feature",
  "properties": {
    "iso:country":"IN",
    "ks:ks_name":"Debendra Das Para",
    "ks:ks_pop":208,
    "ks:ks_type":"HABITATION",
    "name:eng_x_preferred":[
        "Debendra Das Para"
    ],
    "wof:name":"Debendra Das Para",
    "wof:placetype":"locality",
    "wof:population":208
},
  "geometry": {"coordinates":[91.815431,23.576766],"type":"Point"}
}