{
  "type": "Feature",
  "properties": {
    "gn:admin1_code":"35.0",
    "gn:admin2_code":"420",
    "gn:asciiname":"Jameh Behar",
    "gn:country_code":"IN",
    "gn:dem":148,
    "gn:feature_class":"P",
    "gn:feature_code":"PPL",
    "gn:name":"Jameh Behar",
    "gn:population":0,
    "gn:timezone":"Asia/Kolkata",
    "iso:country":"IN",
    "name:und_x_variant":[
        "Behar ki Jameh"
    ],
    "wof:name":"Jameh Behar",
    "wof:placetype":"locality"
},
  "geometry": {"coordinates":[79.06114000000002,26.44562],"type":"Point"}
}