{
  "type": "Feature",
  "properties": {
    "iso:country":"IN",
    "ks:ks_name":"Gadatoli",
    "ks:ks_pop":165,
    "ks:ks_type":"HABITATION",
    "name:eng_x_preferred":[
        "Gadatoli"
    ],
    "wof:name":"Gadatoli",
    "wof:placetype":"locality",
    "wof:population":165
},
  "geometry": {"coordinates":[84.685191,22.170468],"type":"Point"}
}