{
  "type": "Feature",
  "properties": {
    "iso:country":"IN",
    "ks:ks_alt_nam":"Dulmid\u012bh",
    "ks:ks_name":"Dulmidih",
    "ks:ks_pop":525,
    "ks:ks_type":"VILLAGE",
    "name:eng_x_preferred":[
        "Dulmidih"
    ],
    "name:eng_x_variant":[
        "Dulmid\u012bh"
    ],
    "wof:name":"Dulmidih",
    "wof:placetype":"locality",
    "wof:population":525
},
  "geometry": {"coordinates":[85.86516399999999,23.070719],"type":"Point"}
}