{
  "type": "Feature",
  "properties": {
    "iso:country":"IN",
    "ks:ks_name":"Madanpur",
    "ks:ks_pop":206,
    "ks:ks_type":"VILLAGE",
    "name:eng_x_preferred":[
        "Madanpur"
    ],
    "wof:name":"Madanpur",
    "wof:placetype":"locality",
    "wof:population":206
},
  "geometry": {"coordinates":[83.3978,22.40668],"type":"Point"}
}