{
  "type": "Feature",
  "properties": {
    "gn:country":"IN",
    "gn:fcode":"PPL",
    "gn:pop":29664,
    "iso:country":"IN",
    "name:unk_x_variant":[
        "Muvatupuzha"
    ],
    "qs:name":"M\u016bvattupula",
    "qs:photos_9r":0,
    "qs:photos_sr":0,
    "qs:pop_sr":"7",
    "wd:wordcount":5413,
    "wof:name":"M\u016bvattupula",
    "wof:placetype":"locality",
    "wof:population":29664
},
  "geometry": {"coordinates":[76.57728,9.98493],"type":"Point"}
}