{
  "type": "Feature",
  "properties": {
    "gn:country":"IN",
    "gn:fcode":"PPL",
    "gn:population":29664,
    "iso:country":"IN",
    "name:ben_x_preferred":[
        "\u09ae\u09c1\u09ac\u09be\u09a4\u09cd\u09a4\u09c1\u09aa\u09c1\u09af\u09cd\u09b9"
    ],
    "name:bpy_x_preferred":[
        "\u09ae\u09c1\u09ac\u09be\u09a4\u09cd\u09a4\u09c1\u09aa\u09c1\u09af\u09cd\u09b9"
    ],
    "name:bul_x_preferred":[
        "\u041c\u0443\u0432\u0430\u0442\u0443\u043f\u0443\u0436\u0430"
    ],
    "name:ceb_x_preferred":[
        "Muvattupuzha"
    ],
    "name:deu_x_preferred":[
        "Muvattupuzha"
    ],
    "name:eng_x_preferred":[
        "Muvattupuzha"
    ],
    "name:fra_x_preferred":[
        "Muvattupula"
    ],
    "name:guj_x_preferred":[
        "\u0aae\u0ac1\u0ab5\u0abe\u0a9f\u0acd\u0a9f\u0ac1\u0aaa\u0ac1\u0a9d\u0abe"
    ],
    "name:hin_x_preferred":[
        "\u092e\u0942\u0935\u093e\u091f\u094d\u091f\u0941\u092a\u0941\u0937\u093e"
    ],
    "name:ita_x_preferred":[
        "Muvattupuzha"
    ],
    "name:jpn_x_preferred":[
        "\u30e0\u30d0\u30c3\u30c8\u30a5\u30d7\u30c3\u30b6"
    ],
    "name:kan_x_preferred":[
        "\u0cae\u0cc1\u0cb5\u0ca4\u0ccd\u0ca4\u0cc1\u0caa\u0cc1\u0cb0"
    ],
    "name:kor_x_preferred":[
        "\ubb34\ubc14\ud22c\ud478\uc790"
    ],
    "name:mal_x_preferred":[
        "\u0d2e\u0d42\u0d35\u0d3e\u0d31\u0d4d\u0d31\u0d41\u0d2a\u0d41\u0d34"
    ],
    "name:mlg_x_preferred":[
        "Muvattupuzha"
    ],
    "name:msa_x_preferred":[
        "Muvattupuzha"
    ],
    "name:new_x_preferred":[
        "\u092e\u0941\u0935\u093e\u0924\u094d\u0924\u0941\u092a\u0941\u091d\u093e"
    ],
    "name:nld_x_preferred":[
        "Muvattupuzha"
    ],
    "name:ori_x_preferred":[
        "Muvattupuzha"
    ],
    "name:pol_x_preferred":[
        "Muvattupuzha"
    ],
    "name:por_x_preferred":[
        "Muvattupuzha"
    ],
    "name:rus_x_preferred":[
        "\u041c\u0443\u0432\u0430\u0442\u0442\u0443\u043f\u0443\u0440\u0430"
    ],
    "name:spa_x_preferred":[
        "Muvattupuzha"
    ],
    "name:swe_x_preferred":[
        "Muvattupuzha"
    ],
    "name:tam_x_preferred":[
        "\u0bae\u0bc2\u0bb5\u0bbe\u0b9f\u0bcd\u0b9f\u0bc1\u0baa\u0bc1\u0bb4"
    ],
    "name:tel_x_preferred":[
        "\u0c2e\u0c41\u0c35\u0c24\u0c4d\u0c24\u0c41\u0c2a\u0c41\u0c1c"
    ],
    "name:und_x_variant":[
        "Muvatupuzha"
    ],
    "name:urd_x_preferred":[
        "\u0645\u0648\u0648\u0627\u0679\u0648\u067e\u0648\u0698\u0627"
    ],
    "name:vie_x_preferred":[
        "Muvattupuzha"
    ],
    "name:zho_x_preferred":[
        "\u7a46\u74e6\u7279\u56fe\u666e\u624e"
    ],
    "qs:name":"M\u016bvattupula",
    "qs:photos_9r":0,
    "qs:photos_sr":0,
    "qs:pop_sr":"7",
    "wd:wordcount":5413,
    "wof:name":"M\u016bvattupula",
    "wof:placetype":"locality",
    "wof:population":29664
},
  "geometry": {"coordinates":[76.57728,9.98493],"type":"Point"}
}