{
  "type": "Feature",
  "properties": {
    "iso:country":"IN",
    "ks:ks_name":"Maryachiwadi",
    "ks:ks_pop":292,
    "ks:ks_type":"HABITATION",
    "name:eng_x_preferred":[
        "Maryachiwadi"
    ],
    "wof:name":"Maryachiwadi",
    "wof:placetype":"locality",
    "wof:population":292
},
  "geometry": {"coordinates":[73.310067,19.052077],"type":"Point"}
}