{
  "type": "Feature",
  "properties": {
    "iso:country":"IN",
    "ks:ks_name":"Talpada",
    "ks:ks_pop":150,
    "ks:ks_type":"HABITATION",
    "name:eng_x_preferred":[
        "Talpada"
    ],
    "wof:name":"Talpada",
    "wof:placetype":"locality",
    "wof:population":150
},
  "geometry": {"coordinates":[82.864487,19.599109],"type":"Point"}
}