{
  "type": "Feature",
  "properties": {
    "iso:country":"IN",
    "ks:ks_name":"Dani Kor Singh",
    "ks:ks_pop":20,
    "ks:ks_type":"HABITATION",
    "name:eng_x_preferred":[
        "Dani Kor Singh"
    ],
    "wof:name":"Dani Kor Singh",
    "wof:placetype":"locality",
    "wof:population":20
},
  "geometry": {"coordinates":[74.317572,29.554942],"type":"Point"}
}