{
  "type": "Feature",
  "properties": {
    "gn:admin1_code":"37.0",
    "gn:admin2_code":"416.0",
    "gn:asciiname":"Mondpalli",
    "gn:country_code":"IN",
    "gn:dem":175,
    "gn:feature_class":"P",
    "gn:feature_code":"PPL",
    "gn:name":"Mondpalli",
    "gn:population":0,
    "gn:timezone":"Asia/Kolkata",
    "iso:country":"IN",
    "ks:ks_name":"Mundpalli",
    "ks:ks_pop":415,
    "ks:ks_type":"VILLAGE",
    "name:eng_x_preferred":[
        "Mundpalli"
    ],
    "name:eng_x_variant":[
        "Mondpalli"
    ],
    "wof:name":"Mundpalli",
    "wof:placetype":"locality",
    "wof:population":415
},
  "geometry": {"coordinates":[81.47610400000001,18.243144],"type":"Point"}
}