{
  "type": "Feature",
  "properties": {
    "iso:country":"IN",
    "ks:ks_name":"Ranidi",
    "ks:ks_pop":581,
    "ks:ks_type":"VILLAGE",
    "name:eng_x_preferred":[
        "Ranidi"
    ],
    "wof:name":"Ranidi",
    "wof:placetype":"locality",
    "wof:population":581
},
  "geometry": {"coordinates":[86.733407,24.141683],"type":"Point"}
}