{
  "type": "Feature",
  "properties": {
    "gn:admin1_code":"24",
    "gn:admin2_code":"123.0",
    "gn:asciiname":"Arwara",
    "gn:country_code":"IN",
    "gn:dem":602,
    "gn:feature_class":"P",
    "gn:feature_code":"PPL",
    "gn:name":"\u0100rw\u0101ra",
    "gn:population":0,
    "gn:timezone":"Asia/Kolkata",
    "iso:country":"IN",
    "wof:name":"Arwara",
    "wof:placetype":"locality"
},
  "geometry": {"coordinates":[73.83802,25.21364],"type":"Point"}
}