{
  "type": "Feature",
  "properties": {
    "gn:admin1_code":"36",
    "gn:admin2_code":"179.0",
    "gn:asciiname":"Subhdhan Patti",
    "gn:country_code":"IN",
    "gn:dem":97,
    "gn:feature_class":"P",
    "gn:feature_code":"PPL",
    "gn:name":"Subhdh\u0101n Patti",
    "gn:population":0,
    "gn:timezone":"Asia/Kolkata",
    "iso:country":"IN",
    "wof:name":"Subhdhan Patti",
    "wof:placetype":"neighbourhood"
},
  "geometry": {"coordinates":[82.18031999999999,26.06377],"type":"Point"}
}