{
  "type": "Feature",
  "properties": {
    "iso:country":"IN",
    "ks:ks_alt_nam":"Kundupadi colony",
    "ks:ks_name":"Kundupadi Colony",
    "ks:ks_pop":530,
    "ks:ks_type":"HABITATION",
    "name:eng_x_preferred":[
        "Kundupadi Colony"
    ],
    "wof:name":"Kundupadi Colony",
    "wof:placetype":"locality",
    "wof:population":530
},
  "geometry": {"coordinates":[76.132987,11.831054],"type":"Point"}
}