{
  "type": "Feature",
  "properties": {
    "iso:country":"IN",
    "ks:ks_name":"Gudepal",
    "ks:ks_pop":52,
    "ks:ks_type":"HABITATION",
    "name:eng_x_preferred":[
        "Gudepal"
    ],
    "wof:name":"Gudepal",
    "wof:placetype":"locality",
    "wof:population":52
},
  "geometry": {"coordinates":[74.6811,14.956639],"type":"Point"}
}