{
  "type": "Feature",
  "properties": {
    "gn:admin1_code":"28.0",
    "gn:admin2_code":"341",
    "gn:asciiname":"Sibpur",
    "gn:country_code":"IN",
    "gn:dem":10,
    "gn:feature_class":"P",
    "gn:feature_code":"PPL",
    "gn:name":"Sibpur",
    "gn:population":0,
    "gn:timezone":"Asia/Kolkata",
    "iso:country":"IN",
    "wof:name":"Sibpur",
    "wof:placetype":"locality"
},
  "geometry": {"coordinates":[88.03381,22.22399],"type":"Point"}
}