{
  "type": "Feature",
  "properties": {
    "iso:country":"IN",
    "ks:ks_name":"Chandore",
    "ks:ks_pop":2791,
    "ks:ks_type":"VILLAGE",
    "name:eng_x_preferred":[
        "Chandore"
    ],
    "wof:name":"Chandore",
    "wof:placetype":"locality",
    "wof:population":2791
},
  "geometry": {"coordinates":[87.827344,24.761923],"type":"Point"}
}