{
  "type": "Feature",
  "properties": {
    "iso:country":"IN",
    "ks:ks_name":"Penugondavaripalle",
    "ks:ks_pop":211,
    "ks:ks_type":"HABITATION",
    "name:eng_x_preferred":[
        "Penugondavaripalle"
    ],
    "wof:name":"Penugondavaripalle",
    "wof:placetype":"locality",
    "wof:population":211
},
  "geometry": {"coordinates":[79.04708100000001,13.832988],"type":"Point"}
}