{
  "type": "Feature",
  "properties": {
    "iso:country":"IN",
    "ks:ks_name":"Rajeev Nagar",
    "ks:ks_pop":818,
    "ks:ks_type":"HABITATION",
    "name:eng_x_preferred":[
        "Rajeev Nagar"
    ],
    "wof:name":"Rajeev Nagar",
    "wof:placetype":"locality",
    "wof:population":818
},
  "geometry": {"coordinates":[78.792569,13.655084],"type":"Point"}
}