{
  "type": "Feature",
  "properties": {
    "gn:admin1_code":"25.0",
    "gn:admin2_code":"631.0",
    "gn:asciiname":"Nerlatti",
    "gn:country_code":"IN",
    "gn:dem":928,
    "gn:feature_class":"P",
    "gn:feature_code":"PPL",
    "gn:name":"Nerlatti",
    "gn:population":0,
    "gn:timezone":"Asia/Kolkata",
    "iso:country":"IN",
    "ks:ks_name":"Neralatty",
    "ks:ks_pop":510,
    "ks:ks_type":"HABITATION",
    "name:eng_x_preferred":[
        "Neralatty"
    ],
    "name:eng_x_variant":[
        "Nerlatti"
    ],
    "wof:name":"Neralatty",
    "wof:placetype":"locality",
    "wof:population":510
},
  "geometry": {"coordinates":[77.689269,12.531936],"type":"Point"}
}