{
  "type": "Feature",
  "properties": {
    "iso:country":"IN",
    "ks:ks_name":"Kumaralli",
    "ks:ks_pop":749,
    "ks:ks_type":"VILLAGE",
    "name:eng_x_preferred":[
        "Kumaralli"
    ],
    "wof:name":"Kumaralli",
    "wof:placetype":"locality",
    "wof:population":749
},
  "geometry": {"coordinates":[75.709232,12.681517],"type":"Point"}
}