{
  "type": "Feature",
  "properties": {
    "gn:admin1_code":"35.0",
    "gn:admin2_code":"440",
    "gn:asciiname":"Bagaud",
    "gn:country_code":"IN",
    "gn:dem":249,
    "gn:feature_class":"P",
    "gn:feature_code":"PPL",
    "gn:name":"B\u0101gaud",
    "gn:population":0,
    "gn:timezone":"Asia/Kolkata",
    "iso:country":"IN",
    "wof:name":"Bagaud",
    "wof:placetype":"neighbourhood"
},
  "geometry": {"coordinates":[75.87012,22.32089],"type":"Point"}
}