{
  "type": "Feature",
  "properties": {
    "iso:country":"IN",
    "ks:ks_name":"Agiria",
    "ks:ks_pop":446,
    "ks:ks_type":"VILLAGE",
    "name:eng_x_preferred":[
        "Agiria"
    ],
    "wof:name":"Agiria",
    "wof:placetype":"locality",
    "wof:population":446
},
  "geometry": {"coordinates":[86.59097,20.99829],"type":"Point"}
}