{
  "type": "Feature",
  "properties": {
    "gn:admin1_code":"12",
    "gn:admin2_code":"3.0",
    "gn:asciiname":"Tangtse",
    "gn:country_code":"IN",
    "gn:dem":3933,
    "gn:feature_class":"P",
    "gn:feature_code":"PPL",
    "gn:name":"Tangtse",
    "gn:population":0,
    "gn:timezone":"Asia/Kolkata",
    "iso:country":"IN",
    "name:und_x_variant":[
        "T\u0101nkse",
        "Tanktse",
        "Tangtse"
    ],
    "wof:name":"Tangtse",
    "wof:placetype":"locality"
},
  "geometry": {"coordinates":[78.16983,34.03452],"type":"Point"}
}