{
  "type": "Feature",
  "properties": {
    "gn:admin1_code":"11.0",
    "gn:asciiname":"Papro",
    "gn:country_code":"IN",
    "gn:dem":1002,
    "gn:feature_class":"P",
    "gn:feature_code":"PPL",
    "gn:name":"Papro",
    "gn:population":0,
    "gn:timezone":"Asia/Kolkata",
    "iso:country":"IN",
    "wof:name":"Papro",
    "wof:placetype":"locality"
},
  "geometry": {"coordinates":[77.12899999999998,30.71418],"type":"Point"}
}