{
  "type": "Feature",
  "properties": {
    "iso:country":"IN",
    "ks:ks_name":"Kurhadepada",
    "ks:ks_pop":61,
    "ks:ks_type":"HABITATION",
    "name:eng_x_preferred":[
        "Kurhadepada"
    ],
    "wof:name":"Kurhadepada",
    "wof:placetype":"locality",
    "wof:population":61
},
  "geometry": {"coordinates":[73.202686,19.637622],"type":"Point"}
}