{
  "type": "Feature",
  "properties": {
    "gn:admin1_code":"36",
    "gn:admin2_code":"144.0",
    "gn:asciiname":"Baghna",
    "gn:country_code":"IN",
    "gn:dem":182,
    "gn:feature_class":"P",
    "gn:feature_code":"PPL",
    "gn:name":"Baghna",
    "gn:population":0,
    "gn:timezone":"Asia/Kolkata",
    "iso:country":"IN",
    "wof:name":"Baghna",
    "wof:placetype":"locality"
},
  "geometry": {"coordinates":[78.06586999999998,27.51723],"type":"Point"}
}