{
  "type": "Feature",
  "properties": {
    "iso:country":"IN",
    "ks:ks_name":"Anghora Diwan",
    "ks:ks_pop":1449,
    "ks:ks_type":"VILLAGE",
    "name:eng_x_preferred":[
        "Anghora Diwan"
    ],
    "wof:name":"Anghora Diwan",
    "wof:placetype":"locality",
    "wof:population":1449
},
  "geometry": {"coordinates":[77.92224299999999,24.927296],"type":"Point"}
}