{
  "type": "Feature",
  "properties": {
    "gn:admin1_code":"19.0",
    "gn:admin2_code":"572.0",
    "gn:asciiname":"Harohalli",
    "gn:country_code":"IN",
    "gn:dem":907,
    "gn:feature_class":"P",
    "gn:feature_code":"PPL",
    "gn:name":"H\u0101rohalli",
    "gn:population":0,
    "gn:timezone":"Asia/Kolkata",
    "iso:country":"IN",
    "ks:ks_name":"Harohalli",
    "ks:ks_pop":1578,
    "ks:ks_type":"VILLAGE",
    "ks:ks_uagg_main":0,
    "name:ceb_x_preferred":[
        "H\u0101rohalli"
    ],
    "name:swe_x_preferred":[
        "H\u0101rohalli"
    ],
    "name:vie_x_preferred":[
        "Harohalli"
    ],
    "wof:name":"Harohalli",
    "wof:placetype":"neighbourhood"
},
  "geometry": {"coordinates":[77.58072,13.13102],"type":"Point"}
}