{
  "type": "Feature",
  "properties": {
    "iso:country":"IN",
    "ks:ks_name":"Harser",
    "ks:ks_pop":844,
    "ks:ks_type":"VILLAGE",
    "ks:ks_uagg_main":0,
    "name:eng_x_preferred":[
        "Harser"
    ],
    "wof:name":"Harser",
    "wof:placetype":"neighbourhood",
    "wof:population":844
},
  "geometry": {"coordinates":[85.261341,23.305221],"type":"Point"}
}