{
  "type": "Feature",
  "properties": {
    "iso:country":"IN",
    "ks:ks_name":"Rasgari",
    "ks:ks_pop":162,
    "ks:ks_type":"VILLAGE",
    "name:eng_x_preferred":[
        "Rasgari"
    ],
    "wof:name":"Rasgari",
    "wof:placetype":"locality",
    "wof:population":162
},
  "geometry": {"coordinates":[80.341989,29.750674],"type":"Point"}
}