{
  "type": "Feature",
  "properties": {
    "gn:admin1_code":"36.0",
    "gn:admin2_code":"177.0",
    "gn:asciiname":"Ratanpur",
    "gn:country_code":"IN",
    "gn:dem":116,
    "gn:feature_class":"P",
    "gn:feature_code":"PPL",
    "gn:name":"Ratanpur",
    "gn:population":0,
    "gn:timezone":"Asia/Kolkata",
    "iso:country":"IN",
    "wof:name":"Ratanpur",
    "wof:placetype":"locality"
},
  "geometry": {"coordinates":[81.62942,26.68416],"type":"Point"}
}