{
  "type": "Feature",
  "properties": {
    "iso:country":"IN",
    "ks:ks_name":"Katara",
    "ks:ks_pop":3269,
    "ks:ks_type":"VILLAGE",
    "name:eng_x_preferred":[
        "Katara"
    ],
    "wof:name":"Katara",
    "wof:placetype":"locality",
    "wof:population":3269
},
  "geometry": {"coordinates":[71.86306399999999,23.801658],"type":"Point"}
}