{
  "type": "Feature",
  "properties": {
    "gn:admin1_code":"40",
    "gn:admin2_code":"541.0",
    "gn:asciiname":"Kukunuru",
    "gn:country_code":"IN",
    "gn:dem":49,
    "gn:feature_class":"P",
    "gn:feature_code":"PPL",
    "gn:name":"Kukun\u016bru",
    "gn:population":0,
    "gn:timezone":"Asia/Kolkata",
    "iso:country":"IN",
    "wof:name":"Kukunuru",
    "wof:placetype":"neighbourhood"
},
  "geometry": {"coordinates":[81.17610000000001,17.55782],"type":"Point"}
}