{
  "type": "Feature",
  "properties": {
    "iso:country":"IN",
    "ks:ks_name":"Patel Falia",
    "ks:ks_pop":340,
    "ks:ks_type":"HABITATION",
    "name:eng_x_preferred":[
        "Patel Falia"
    ],
    "wof:name":"Patel Falia",
    "wof:placetype":"locality",
    "wof:population":340
},
  "geometry": {"coordinates":[72.997806,20.228833],"type":"Point"}
}