{
  "type": "Feature",
  "properties": {
    "gn:admin1_code":"36",
    "gn:admin2_code":"191.0",
    "gn:asciiname":"Isahakpur",
    "gn:country_code":"IN",
    "gn:dem":79,
    "gn:feature_class":"P",
    "gn:feature_code":"PPL",
    "gn:name":"Isah\u0101kpur",
    "gn:population":0,
    "gn:timezone":"Asia/Kolkata",
    "iso:country":"IN",
    "ks:ks_alt_nam":"Isah\u0101kpur",
    "ks:ks_name":"Isahakpur",
    "ks:ks_type":"VILLAGE",
    "ks:ks_uagg_main":0,
    "name:eng_x_preferred":[
        "Isahakpur"
    ],
    "name:eng_x_variant":[
        "Isah\u0101kpur"
    ],
    "wof:name":"Isahakpur",
    "wof:placetype":"locality"
},
  "geometry": {"coordinates":[83.185435,26.101451],"type":"Point"}
}