{
  "type": "Feature",
  "properties": {
    "iso:country":"IN",
    "ks:ks_name":"Panchaniyon Ki Dhani",
    "ks:ks_pop":993,
    "ks:ks_type":"HABITATION",
    "name:eng_x_preferred":[
        "Panchaniyon Ki Dhani"
    ],
    "wof:name":"Panchaniyon Ki Dhani",
    "wof:placetype":"locality",
    "wof:population":993
},
  "geometry": {"coordinates":[71.499728,26.067258],"type":"Point"}
}