{
  "type": "Feature",
  "properties": {
    "gn:admin1_code":"35.0",
    "gn:asciiname":"Kanera",
    "gn:country_code":"IN",
    "gn:dem":551,
    "gn:feature_class":"P",
    "gn:feature_code":"PPL",
    "gn:name":"Kanera",
    "gn:population":0,
    "gn:timezone":"Asia/Kolkata",
    "iso:country":"IN",
    "wof:name":"Kanera",
    "wof:placetype":"locality"
},
  "geometry": {"coordinates":[74.89778000000003,24.7102],"type":"Point"}
}