{
  "type": "Feature",
  "properties": {
    "iso:country":"IN",
    "ks:ks_name":"Dera Purwa",
    "ks:ks_pop":85,
    "ks:ks_type":"HABITATION",
    "name:eng_x_preferred":[
        "Dera Purwa"
    ],
    "wof:name":"Dera Purwa",
    "wof:placetype":"locality",
    "wof:population":85
},
  "geometry": {"coordinates":[81.034485,28.217799],"type":"Point"}
}