{
  "type": "Feature",
  "properties": {
    "iso:country":"IN",
    "ks:ks_name":"Bedpur",
    "ks:ks_pop":234,
    "ks:ks_type":"VILLAGE",
    "name:eng_x_preferred":[
        "Bedpur"
    ],
    "wof:name":"Bedpur",
    "wof:placetype":"locality",
    "wof:population":234
},
  "geometry": {"coordinates":[86.65380999999999,21.204754],"type":"Point"}
}