{
  "type": "Feature",
  "properties": {
    "gn:admin1_code":"16",
    "gn:admin2_code":"511.0",
    "gn:asciiname":"Panshevadi Tanda",
    "gn:country_code":"IN",
    "gn:dem":487,
    "gn:feature_class":"P",
    "gn:feature_code":"PPL",
    "gn:name":"P\u0101nshevadi T\u0101nda",
    "gn:population":0,
    "gn:timezone":"Asia/Kolkata",
    "iso:country":"IN",
    "wof:name":"Panshevadi Tanda",
    "wof:placetype":"neighbourhood"
},
  "geometry": {"coordinates":[77.19395,18.80376],"type":"Point"}
}