{
  "type": "Feature",
  "properties": {
    "gn:admin1_code":"16",
    "gn:admin2_code":"510.0",
    "gn:asciiname":"Lingi",
    "gn:country_code":"IN",
    "gn:dem":384,
    "gn:feature_class":"P",
    "gn:feature_code":"PPL",
    "gn:name":"Lingi",
    "gn:population":0,
    "gn:timezone":"Asia/Kolkata",
    "iso:country":"IN",
    "wof:name":"Lingi",
    "wof:placetype":"locality"
},
  "geometry": {"coordinates":[77.98189000000001,19.4913],"type":"Point"}
}