{
  "type": "Feature",
  "properties": {
    "gn:admin1_code":"25.0",
    "gn:admin2_code":"633.0",
    "gn:asciiname":"Ardarnarlpalalyam",
    "gn:country_code":"IN",
    "gn:dem":316,
    "gn:feature_class":"P",
    "gn:feature_code":"PPL",
    "gn:name":"Ardarnarlp\u0101lalyam",
    "gn:population":0,
    "gn:timezone":"Asia/Kolkata",
    "iso:country":"IN",
    "wof:name":"Ardarnarlpalalyam",
    "wof:placetype":"neighbourhood"
},
  "geometry": {"coordinates":[77.44654,11.29065],"type":"Point"}
}