{
  "type": "Feature",
  "properties": {
    "gn:admin1_code":"16.0",
    "gn:admin2_code":"497.0",
    "gn:asciiname":"Padali",
    "gn:country_code":"IN",
    "gn:dem":577,
    "gn:feature_class":"P",
    "gn:feature_code":"PPL",
    "gn:name":"P\u0101dali",
    "gn:population":0,
    "gn:timezone":"Asia/Kolkata",
    "iso:country":"IN",
    "ks:ks_alt_nam":"P\u0101dali",
    "ks:ks_name":"Padali",
    "ks:ks_pop":1954,
    "ks:ks_type":"VILLAGE",
    "name:ceb_x_preferred":[
        "Padal\u012b"
    ],
    "name:eng_x_preferred":[
        "Padali"
    ],
    "name:eng_x_variant":[
        "P\u0101dali"
    ],
    "name:fas_x_preferred":[
        "\u067e\u062f\u0644\u06cc"
    ],
    "name:swe_x_preferred":[
        "Padal\u012b"
    ],
    "wof:name":"Padali",
    "wof:placetype":"locality",
    "wof:population":1954
},
  "geometry": {"coordinates":[74.159592,21.731532],"type":"Point"}
}