{
  "type": "Feature",
  "properties": {
    "iso:country":"IN",
    "ks:ks_name":"Kolahardanda",
    "ks:ks_pop":524,
    "ks:ks_type":"HABITATION",
    "name:eng_x_preferred":[
        "Kolahardanda"
    ],
    "wof:name":"Kolahardanda",
    "wof:placetype":"locality",
    "wof:population":524
},
  "geometry": {"coordinates":[86.87615700000001,24.646936],"type":"Point"}
}