{
  "type": "Feature",
  "properties": {
    "gn:admin1_code":"9.0",
    "gn:admin2_code":"469.0",
    "gn:asciiname":"Andhari",
    "gn:country_code":"IN",
    "gn:dem":241,
    "gn:feature_class":"P",
    "gn:feature_code":"PPL",
    "gn:name":"Andh\u0101ri",
    "gn:population":0,
    "gn:timezone":"Asia/Kolkata",
    "iso:country":"IN",
    "wof:name":"Andhari",
    "wof:placetype":"neighbourhood"
},
  "geometry": {"coordinates":[72.67791,24.14755],"type":"Point"}
}