{
  "type": "Feature",
  "properties": {
    "gn:admin1_code":"2",
    "gn:admin2_code":"545.0",
    "gn:asciiname":"Bapandhara",
    "gn:country_code":"IN",
    "gn:dem":363,
    "gn:feature_class":"P",
    "gn:feature_code":"PPL",
    "gn:name":"B\u0101pandh\u0101ra",
    "gn:population":0,
    "gn:timezone":"Asia/Kolkata",
    "iso:country":"IN",
    "ks:ks_name":"Bapannadhara",
    "ks:ks_pop":275,
    "ks:ks_type":"VILLAGE",
    "name:eng_x_preferred":[
        "Bapannadhara"
    ],
    "name:eng_x_variant":[
        "Bapandhara"
    ],
    "wof:name":"Bapannadhara",
    "wof:placetype":"locality",
    "wof:population":275
},
  "geometry": {"coordinates":[82.238207,17.396902],"type":"Point"}
}