{
  "type": "Feature",
  "properties": {
    "gn:admin1_code":"28.0",
    "gn:admin2_code":"333.0",
    "gn:asciiname":"Tantibiral",
    "gn:country_code":"IN",
    "gn:dem":35,
    "gn:feature_class":"P",
    "gn:feature_code":"PPL",
    "gn:name":"T\u0101ntibiral",
    "gn:population":0,
    "gn:timezone":"Asia/Kolkata",
    "iso:country":"IN",
    "ks:ks_name":"Tantibiral",
    "ks:ks_pop":441,
    "ks:ks_type":"VILLAGE",
    "name:eng_x_preferred":[
        "Tantibiral"
    ],
    "wof:name":"Tantibiral",
    "wof:placetype":"locality",
    "wof:population":441
},
  "geometry": {"coordinates":[87.97853499999999,24.368807],"type":"Point"}
}