{
  "type": "Feature",
  "properties": {
    "iso:country":"IN",
    "ks:ks_name":"Ponnampalampatty",
    "ks:ks_pop":424,
    "ks:ks_type":"HABITATION",
    "name:eng_x_preferred":[
        "Ponnampalampatty"
    ],
    "wof:name":"Ponnampalampatty",
    "wof:placetype":"locality",
    "wof:population":424
},
  "geometry": {"coordinates":[78.545146,11.071209],"type":"Point"}
}