{
  "type": "Feature",
  "properties": {
    "iso:country":"IN",
    "ks:ks_name":"Hulekalleshwarabetta",
    "ks:ks_pop":91,
    "ks:ks_type":"HABITATION",
    "name:eng_x_preferred":[
        "Hulekalleshwarabetta"
    ],
    "wof:name":"Hulekalleshwarabetta",
    "wof:placetype":"locality",
    "wof:population":91
},
  "geometry": {"coordinates":[76.05070000000001,13.19712],"type":"Point"}
}