{
  "type": "Feature",
  "properties": {
    "gn:admin1_code":"25.0",
    "gn:admin2_code":"606.0",
    "gn:asciiname":"Andalur",
    "gn:country_code":"IN",
    "gn:dem":146,
    "gn:feature_class":"P",
    "gn:feature_code":"PPL",
    "gn:name":"Andalur",
    "gn:population":0,
    "gn:timezone":"Asia/Kolkata",
    "iso:country":"IN",
    "ks:ks_name":"Andalor",
    "ks:ks_pop":262,
    "ks:ks_type":"HABITATION",
    "name:eng_x_preferred":[
        "Andalor"
    ],
    "name:eng_x_variant":[
        "Andalur"
    ],
    "wof:name":"Andalor",
    "wof:placetype":"locality",
    "wof:population":262
},
  "geometry": {"coordinates":[79.24896099999999,12.573969],"type":"Point"}
}