{
  "type": "Feature",
  "properties": {
    "iso:country":"IN",
    "ks:ks_name":"Ennekere Kaval",
    "ks:ks_pop":89,
    "ks:ks_type":"HABITATION",
    "name:eng_x_preferred":[
        "Ennekere Kaval"
    ],
    "wof:name":"Ennekere Kaval",
    "wof:placetype":"locality",
    "wof:population":89
},
  "geometry": {"coordinates":[76.422893,12.216565],"type":"Point"}
}