{
  "type": "Feature",
  "properties": {
    "iso:country":"IN",
    "name:ben_x_preferred":[
        "\u0995\u09be\u09af\u09bc\u09b8\u09be\u09b0 \u09ac\u09be\u0997"
    ],
    "name:eng_x_preferred":[
        "Kaisarbagh"
    ],
    "name:eng_x_variant":[
        "Qaisar Bagh"
    ],
    "name:fas_x_preferred":[
        "\u0628\u0627\u063a \u0642\u06cc\u0635\u0631"
    ],
    "name:hin_x_preferred":[
        "\u0915\u0948\u0938\u0930\u092c\u093e\u0917"
    ],
    "name:kan_x_preferred":[
        "\u0c95\u0cc8\u0cb8\u0cb0\u0ccd \u0cac\u0cbe\u0c97\u0ccd"
    ],
    "name:por_x_preferred":[
        "Qaisar Bagh"
    ],
    "name:sqi_x_preferred":[
        "Qaisar Baghu"
    ],
    "name:urd_x_preferred":[
        "\u0642\u06cc\u0635\u0631 \u0628\u0627\u063a"
    ],
    "qs:gn_adm0_cc":"IN",
    "qs:gn_local":1264733,
    "qs:local_max":321,
    "qs:local_sum":1015,
    "qs:localhoods":8,
    "qs:name":"Kaisarbagh",
    "qs:name_adm0":"India",
    "qs:name_adm1":"Uttar Pradesh",
    "qs:name_adm2":"Lucknow",
    "qs:name_local":"Lucknow",
    "qs:photo_max":77,
    "qs:photo_sum":230,
    "qs:placetype":"Suburb",
    "qs:quad_count":16,
    "qs:woe_adm0":23424848,
    "qs:woe_adm1":2345760,
    "qs:woe_adm2":12586761,
    "qs:woe_lau":0,
    "qs:woe_local":2295377,
    "qs:woe_ver":"7.10.0",
    "wd:wordcount":95,
    "wof:lang":[
        "eng"
    ],
    "wof:name":"Kaisarbagh",
    "wof:placetype":"neighbourhood"
},
  "geometry": {"coordinates":[80.93462100000001,26.85513],"type":"Point"}
}