{
  "type": "Feature",
  "properties": {
    "iso:country":"IN",
    "name:ara_x_preferred":[
        "\u0642\u064a\u0635\u0631 \u0628\u0627\u063a"
    ],
    "name:ben_bn_x_preferred":[
        "\u0995\u0987\u09b8\u09b0\u09ac\u09be\u0997"
    ],
    "name:ben_in_x_preferred":[
        "\u0995\u0987\u09b8\u09b0\u09ac\u09be\u0997"
    ],
    "name:ben_x_preferred":[
        "\u0995\u09be\u09af\u09bc\u09b8\u09be\u09b0 \u09ac\u09be\u0997"
    ],
    "name:eng_x_preferred":[
        "Kaisarbagh"
    ],
    "name:eng_x_variant":[
        "Qaisar Bagh"
    ],
    "name:fas_x_preferred":[
        "\u0628\u0627\u063a \u0642\u06cc\u0635\u0631"
    ],
    "name:guj_x_preferred":[
        "\u0a95\u0ac8\u0ab8\u0ab0\u0aac\u0abe\u0a97"
    ],
    "name:hin_x_preferred":[
        "\u0915\u0948\u0938\u0930\u092c\u093e\u0917"
    ],
    "name:kan_x_preferred":[
        "\u0c95\u0cc8\u0cb8\u0cb0\u0ccd"
    ],
    "name:kan_x_variant":[
        "\u0c95\u0cc8\u0cb8\u0cb0\u0ccd \u0cac\u0cbe\u0c97\u0ccd"
    ],
    "name:mal_x_preferred":[
        "\u0d15\u0d48\u0d38\u0d7c\u0d2c\u0d3e\u0d17\u0d4d"
    ],
    "name:mar_x_preferred":[
        "\u0915\u0948\u0938\u0930\u092c\u093e\u0917"
    ],
    "name:pan_x_preferred":[
        "\u0a15\u0a48\u0a38\u0a30\u0a2c\u0a3e\u0a17"
    ],
    "name:por_x_preferred":[
        "Qaisar Bagh"
    ],
    "name:sqi_x_preferred":[
        "Qaisar Baghu"
    ],
    "name:tam_x_preferred":[
        "\u0b95\u0bc8\u0b9a\u0bb0\u0bcd\u0baa\u0bbe\u0b95\u0bcd"
    ],
    "name:tel_x_preferred":[
        "\u0c15\u0c47\u0c38\u0c30\u0c4d"
    ],
    "name:urd_x_preferred":[
        "\u0642\u06cc\u0635\u0631 \u0628\u0627\u063a"
    ],
    "qs:gn_adm0_cc":"IN",
    "qs:gn_local":1264733,
    "qs:local_max":321,
    "qs:local_sum":1015,
    "qs:localhoods":8,
    "qs:name":"Kaisarbagh",
    "qs:name_adm0":"India",
    "qs:name_adm1":"Uttar Pradesh",
    "qs:name_adm2":"Lucknow",
    "qs:name_local":"Lucknow",
    "qs:photo_max":77,
    "qs:photo_sum":230,
    "qs:placetype":"Suburb",
    "qs:quad_count":16,
    "qs:woe_adm0":23424848,
    "qs:woe_adm1":2345760,
    "qs:woe_adm2":12586761,
    "qs:woe_lau":0,
    "qs:woe_local":2295377,
    "qs:woe_ver":"7.10.0",
    "wd:wordcount":95,
    "wof:lang":[
        "eng"
    ],
    "wof:name":"Kaisarbagh",
    "wof:placetype":"neighbourhood"
},
  "geometry": {"coordinates":[80.93462100000001,26.85513],"type":"Point"}
}