{
  "type": "Feature",
  "properties": {
    "gn:admin1_code":"13.0",
    "gn:admin2_code":"600.0",
    "gn:asciiname":"Ayanavelikulangara Tekku",
    "gn:country_code":"IN",
    "gn:dem":11,
    "gn:feature_class":"P",
    "gn:feature_code":"PPL",
    "gn:name":"Ayanavelikulangara Tekku",
    "gn:population":0,
    "gn:timezone":"Asia/Kolkata",
    "iso:country":"IN",
    "wof:name":"Ayanavelikulangara Tekku",
    "wof:placetype":"locality"
},
  "geometry": {"coordinates":[76.52774000000002,9.03838],"type":"Point"}
}