{
  "type": "Feature",
  "properties": {
    "iso:country":"IN",
    "ks:ks_name":"Natwahi",
    "ks:ks_pop":381,
    "ks:ks_type":"VILLAGE",
    "name:eng_x_preferred":[
        "Natwahi"
    ],
    "wof:name":"Natwahi",
    "wof:placetype":"locality",
    "wof:population":381
},
  "geometry": {"coordinates":[82.38327700000001,23.67683],"type":"Point"}
}