{
  "type": "Feature",
  "properties": {
    "iso:country":"IN",
    "ks:ks_name":"Kismat Bangsor No 2",
    "ks:ks_pop":90,
    "ks:ks_type":"HABITATION",
    "name:eng_x_preferred":[
        "Kismat Bangsor No 2"
    ],
    "wof:name":"Kismat Bangsor No 2",
    "wof:placetype":"locality",
    "wof:population":90
},
  "geometry": {"coordinates":[91.57211100000001,26.209336],"type":"Point"}
}