{
  "type": "Feature",
  "properties": {
    "iso:country":"IN",
    "ks:ks_name":"Parbatpur",
    "ks:ks_pop":865,
    "ks:ks_type":"VILLAGE",
    "name:eng_x_preferred":[
        "Parbatpur"
    ],
    "wof:name":"Parbatpur",
    "wof:placetype":"locality",
    "wof:population":865
},
  "geometry": {"coordinates":[86.45388699999999,23.940322],"type":"Point"}
}