{
  "type": "Feature",
  "properties": {
    "iso:country":"IN",
    "ks:ks_name":"47 LNP II",
    "ks:ks_pop":102,
    "ks:ks_type":"VILLAGE",
    "name:eng_x_preferred":[
        "47 LNP II"
    ],
    "wof:name":"47 LNP II",
    "wof:placetype":"locality",
    "wof:population":102
},
  "geometry": {"coordinates":[73.799667,29.650578],"type":"Point"}
}