{
  "type": "Feature",
  "properties": {
    "gn:admin1_code":"23.0",
    "gn:admin2_code":"041",
    "gn:asciiname":"Nasrali",
    "gn:country_code":"IN",
    "gn:dem":259,
    "gn:feature_class":"P",
    "gn:feature_code":"PPL",
    "gn:name":"Nasr\u0101li",
    "gn:population":0,
    "gn:timezone":"Asia/Kolkata",
    "iso:country":"IN",
    "name:pan_x_preferred":[
        "\u0a28\u0a38\u0a30\u0a3e\u0a32\u0a40"
    ],
    "wof:name":"Nasrali",
    "wof:placetype":"locality"
},
  "geometry": {"coordinates":[76.08553000000001,30.66241],"type":"Point"}
}