{
  "type": "Feature",
  "properties": {
    "iso:country":"IN",
    "ks:ks_name":"Khodibar",
    "ks:ks_pop":286,
    "ks:ks_type":"HABITATION",
    "ks:ks_uagg_main":0,
    "name:eng_x_preferred":[
        "Khodibar"
    ],
    "wof:name":"Khodibar",
    "wof:placetype":"neighbourhood",
    "wof:population":286
},
  "geometry": {"coordinates":[82.64271599999999,26.344213],"type":"Point"}
}