{
  "type": "Feature",
  "properties": {
    "iso:country":"IN",
    "ks:ks_name":"Dagarpada",
    "ks:ks_pop":559,
    "ks:ks_type":"VILLAGE",
    "ks:ks_uagg_main":0,
    "name:eng_x_preferred":[
        "Dagarpada"
    ],
    "wof:name":"Dagarpada",
    "wof:placetype":"neighbourhood",
    "wof:population":559
},
  "geometry": {"coordinates":[86.38002400000001,20.268096],"type":"Point"}
}