{
  "type": "Feature",
  "properties": {
    "gn:admin1_code":"39.0",
    "gn:admin2_code":"60.0",
    "gn:asciiname":"Kular",
    "gn:country_code":"IN",
    "gn:dem":1731,
    "gn:feature_class":"P",
    "gn:feature_code":"PPL",
    "gn:name":"Kul\u0101r",
    "gn:population":0,
    "gn:timezone":"Asia/Kolkata",
    "iso:country":"IN",
    "wof:name":"Kular",
    "wof:placetype":"locality"
},
  "geometry": {"coordinates":[77.79361,30.72861],"type":"Point"}
}