{
  "type": "Feature",
  "properties": {
    "gn:admin1_code":"36",
    "gn:admin2_code":"144.0",
    "gn:asciiname":"Fatehpur Bahera",
    "gn:country_code":"IN",
    "gn:dem":178,
    "gn:feature_class":"P",
    "gn:feature_code":"PPL",
    "gn:name":"Fatehpur Bahera",
    "gn:population":0,
    "gn:timezone":"Asia/Kolkata",
    "iso:country":"IN",
    "wof:name":"Fatehpur Bahera",
    "wof:placetype":"locality"
},
  "geometry": {"coordinates":[78.37546,27.63459000000001],"type":"Point"}
}