{
  "type": "Feature",
  "properties": {
    "gn:admin1_code":"24",
    "gn:asciiname":"Birar",
    "gn:country_code":"IN",
    "gn:dem":170,
    "gn:feature_class":"P",
    "gn:feature_code":"PPL",
    "gn:name":"Bir\u0101r",
    "gn:population":0,
    "gn:timezone":"Asia/Kolkata",
    "iso:country":"IN",
    "name:und_x_variant":[
        "Bir\u0101r",
        "Ramgarha"
    ],
    "wof:name":"Birar",
    "wof:placetype":"locality"
},
  "geometry": {"coordinates":[78.10224000000002,26.91781],"type":"Point"}
}