{
  "type": "Feature",
  "properties": {
    "iso:country":"IN",
    "ks:ks_alt_nam":"Mahipal thanda",
    "ks:ks_name":"Mahipal Thanda",
    "ks:ks_pop":65,
    "ks:ks_type":"HABITATION",
    "name:eng_x_preferred":[
        "Mahipal Thanda"
    ],
    "wof:name":"Mahipal Thanda",
    "wof:placetype":"locality",
    "wof:population":65
},
  "geometry": {"coordinates":[78.468541,18.555479],"type":"Point"}
}