{
  "type": "Feature",
  "properties": {
    "gn:admin1_code":"19.0",
    "gn:admin2_code":"575.0",
    "gn:asciiname":"Alantaya",
    "gn:country_code":"IN",
    "gn:dem":126,
    "gn:feature_class":"P",
    "gn:feature_code":"PPLL",
    "gn:name":"\u0100lant\u0101ya",
    "gn:population":0,
    "gn:timezone":"Asia/Kolkata",
    "iso:country":"IN",
    "ks:ks_name":"Alanthaya",
    "ks:ks_pop":274,
    "ks:ks_type":"VILLAGE",
    "name:eng_x_preferred":[
        "Alanthaya"
    ],
    "name:eng_x_variant":[
        "Alantaya"
    ],
    "wof:name":"Alanthaya",
    "wof:placetype":"locality",
    "wof:population":274
},
  "geometry": {"coordinates":[75.358526,12.827285],"type":"Point"}
}