{
  "type": "Feature",
  "properties": {
    "gn:admin1_code":"9.0",
    "gn:admin2_code":"468",
    "gn:asciiname":"Jatawada",
    "gn:country_code":"IN",
    "gn:dem":27,
    "gn:feature_class":"P",
    "gn:feature_code":"PPL",
    "gn:name":"Jatawada",
    "gn:population":0,
    "gn:timezone":"Asia/Kolkata",
    "iso:country":"IN",
    "wof:name":"Jatawada",
    "wof:placetype":"locality"
},
  "geometry": {"coordinates":[70.71458,23.83389],"type":"Point"}
}