{
  "type": "Feature",
  "properties": {
    "gn:country":"IN",
    "gn:fcode":"PPL",
    "gn:pop":0,
    "iso:country":"IN",
    "name:unk_x_variant":[
        "Corakhpyr"
    ],
    "qs:name":"Gorakhpur",
    "qs:name_adm0":"India",
    "qs:name_adm1":"Uttarakhand",
    "qs:photos":6,
    "qs:photos_1k":1,
    "qs:photos_9k":1,
    "qs:photos_9r":1,
    "qs:photos_all":6,
    "qs:photos_sr":1,
    "qs:placetype":"Suburb",
    "qs:pop_sr":"0",
    "wd:elevation":84.0,
    "wd:wordcount":664,
    "wof:name":"Gorakhpur",
    "wof:placetype":"neighbourhood",
    "wof:population":0
},
  "geometry": {"coordinates":[77.96232999999999,30.31498],"type":"Point"}
}