{
  "type": "Feature",
  "properties": {
    "gn:admin1_code":"40",
    "gn:admin2_code":"538.0",
    "gn:asciiname":"Pulimamidi",
    "gn:country_code":"IN",
    "gn:dem":397,
    "gn:feature_class":"P",
    "gn:feature_code":"PPL",
    "gn:name":"Pulim\u0101midi",
    "gn:population":0,
    "gn:timezone":"Asia/Kolkata",
    "iso:country":"IN",
    "name:tel_x_preferred":[
        "\u0c2a\u0c41\u0c32\u0c3f\u0c2e\u0c3e\u0c2e\u0c3f\u0c21\u0c3f"
    ],
    "wof:name":"Pulimamidi",
    "wof:placetype":"locality"
},
  "geometry": {"coordinates":[77.59213000000003,16.58542000000001],"type":"Point"}
}