{
  "type": "Feature",
  "properties": {
    "iso:country":"IN",
    "ks:ks_name":"Patre",
    "ks:ks_pop":54,
    "ks:ks_type":"HABITATION",
    "name:eng_x_preferred":[
        "Patre"
    ],
    "wof:name":"Patre",
    "wof:placetype":"locality",
    "wof:population":54
},
  "geometry": {"coordinates":[74.42282400000001,15.085965],"type":"Point"}
}