{
  "type": "Feature",
  "properties": {
    "gn:admin1_code":"36",
    "gn:admin2_code":"187.0",
    "gn:asciiname":"Lotan",
    "gn:country_code":"IN",
    "gn:dem":93,
    "gn:feature_class":"P",
    "gn:feature_code":"PPL",
    "gn:name":"Lotan",
    "gn:population":0,
    "gn:timezone":"Asia/Kolkata",
    "iso:country":"IN",
    "name:ast_x_preferred":[
        "Lotan"
    ],
    "name:spa_x_preferred":[
        "Lotan"
    ],
    "wof:name":"Lotan",
    "wof:placetype":"locality"
},
  "geometry": {"coordinates":[83.24479000000002,27.28239],"type":"Point"}
}