{
  "type": "Feature",
  "properties": {
    "gn:admin1_code":"40.0",
    "gn:admin2_code":"534",
    "gn:asciiname":"Atmakur",
    "gn:country_code":"IN",
    "gn:dem":339,
    "gn:feature_class":"P",
    "gn:feature_code":"PPL",
    "gn:name":"Atm\u0101k\u016br",
    "gn:population":0,
    "gn:timezone":"Asia/Kolkata",
    "iso:country":"IN",
    "wof:name":"Atmakur",
    "wof:placetype":"locality"
},
  "geometry": {"coordinates":[78.62127,18.74949],"type":"Point"}
}