{
  "type": "Feature",
  "properties": {
    "gn:admin1_code":"11",
    "gn:admin2_code":"33.0",
    "gn:asciiname":"Berti",
    "gn:country_code":"IN",
    "gn:dem":1456,
    "gn:feature_class":"P",
    "gn:feature_code":"PPL",
    "gn:name":"Berti",
    "gn:population":0,
    "gn:timezone":"Asia/Kolkata",
    "iso:country":"IN",
    "name:dan_x_preferred":[
        "Berti"
    ],
    "name:deu_x_preferred":[
        "Berti"
    ],
    "name:fra_x_preferred":[
        "Berti"
    ],
    "name:ita_x_preferred":[
        "Berti"
    ],
    "name:rus_x_preferred":[
        "\u0411\u0435\u0440\u0442\u0438"
    ],
    "name:slv_x_preferred":[
        "Berti"
    ],
    "name:spa_x_preferred":[
        "Berti"
    ],
    "wof:name":"Berti",
    "wof:placetype":"locality"
},
  "geometry": {"coordinates":[77.22655,31.18673],"type":"Point"}
}