{
  "type": "Feature",
  "properties": {
    "gn:admin1_code":"16",
    "gn:admin2_code":"509.0",
    "gn:asciiname":"Kharkada",
    "gn:country_code":"IN",
    "gn:dem":223,
    "gn:feature_class":"P",
    "gn:feature_code":"PPL",
    "gn:name":"Khark\u0101da",
    "gn:population":0,
    "gn:timezone":"Asia/Kolkata",
    "iso:country":"IN",
    "name:ceb_x_preferred":[
        "Kharkada"
    ],
    "name:fra_x_preferred":[
        "Kharkada"
    ],
    "name:mai_x_preferred":[
        "\u0916\u0930\u094d\u0915\u0921\u093e"
    ],
    "name:msa_x_preferred":[
        "Kharkada"
    ],
    "name:nep_x_preferred":[
        "\u0916\u0930\u0915\u0921\u093e"
    ],
    "name:new_x_preferred":[
        "\u0916\u0930\u094d\u0915\u093e\u0921\u093e"
    ],
    "name:pol_x_preferred":[
        "Kharkada"
    ],
    "wof:name":"Kharkada",
    "wof:placetype":"locality"
},
  "geometry": {"coordinates":[79.93338,20.53953],"type":"Point"}
}