{
  "type": "Feature",
  "properties": {
    "iso:country":"IN",
    "ks:ks_alt_nam":"SAHANI TOLA",
    "ks:ks_name":"Sahani Tola",
    "ks:ks_pop":1102,
    "ks:ks_type":"HABITATION",
    "ks:ks_uagg_main":0,
    "name:eng_x_preferred":[
        "Sahani Tola"
    ],
    "wof:name":"Sahani Tola",
    "wof:placetype":"neighbourhood",
    "wof:population":1102
},
  "geometry": {"coordinates":[86.03228,25.71652],"type":"Point"}
}