{
  "type": "Feature",
  "properties": {
    "gn:admin1_code":"12.0",
    "gn:asciiname":"Phalwari",
    "gn:country_code":"IN",
    "gn:dem":585,
    "gn:feature_class":"P",
    "gn:feature_code":"PPL",
    "gn:name":"Phalw\u0101ri",
    "gn:population":0,
    "gn:timezone":"Asia/Kolkata",
    "iso:country":"IN",
    "name:fas_x_preferred":[
        "\u067e\u0647\u0644\u0648\u0627\u0631\u06cc"
    ],
    "name:urd_x_preferred":[
        "\u067e\u06c1\u0644\u0648\u0627\u0631\u06cc"
    ],
    "wof:name":"Phalwari",
    "wof:placetype":"locality"
},
  "geometry": {"coordinates":[74.48569000000001,33.04189],"type":"Point"}
}