{
  "type": "Feature",
  "properties": {
    "iso:country":"IN",
    "ks:ks_name":"Mairapalla",
    "ks:ks_pop":359,
    "ks:ks_type":"HABITATION",
    "name:eng_x_preferred":[
        "Mairapalla"
    ],
    "wof:name":"Mairapalla",
    "wof:placetype":"locality",
    "wof:population":359
},
  "geometry": {"coordinates":[75.44074000000001,12.612307],"type":"Point"}
}