{
  "type": "Feature",
  "properties": {
    "gn:admin1_code":"16.0",
    "gn:admin2_code":"513.0",
    "gn:asciiname":"Arvi",
    "gn:country_code":"IN",
    "gn:dem":410,
    "gn:feature_class":"P",
    "gn:feature_code":"PPL",
    "gn:name":"\u0100rvi",
    "gn:population":0,
    "gn:timezone":"Asia/Kolkata",
    "iso:country":"IN",
    "wof:name":"Arvi",
    "wof:placetype":"locality"
},
  "geometry": {"coordinates":[76.70043000000003,19.35817],"type":"Point"}
}