{
  "type": "Feature",
  "properties": {
    "gn:admin1_code":"16.0",
    "gn:admin2_code":"510.0",
    "gn:asciiname":"Panas",
    "gn:country_code":"IN",
    "gn:dem":272,
    "gn:feature_class":"P",
    "gn:feature_code":"PPL",
    "gn:name":"P\u0101nas",
    "gn:population":0,
    "gn:timezone":"Asia/Kolkata",
    "iso:country":"IN",
    "name:deu_x_preferred":[
        "Panas"
    ],
    "name:rus_x_preferred":[
        "\u041f\u0430\u043d\u0430\u0441"
    ],
    "name:ukr_x_preferred":[
        "\u041f\u0430\u043d\u0430\u0441"
    ],
    "wof:name":"Panas",
    "wof:placetype":"locality"
},
  "geometry": {"coordinates":[78.10925999999998,20.55418],"type":"Point"}
}