{
  "type": "Feature",
  "properties": {
    "iso:country":"IN",
    "ks:ks_alt_nam":"DAKSHIN TILBHUM FV",
    "ks:ks_name":"Dakshin Tilbhum Fv",
    "ks:ks_pop":752,
    "ks:ks_type":"HABITATION",
    "name:eng_x_preferred":[
        "Dakshin Tilbhum Fv"
    ],
    "wof:name":"Dakshin Tilbhum Fv",
    "wof:placetype":"locality",
    "wof:population":752
},
  "geometry": {"coordinates":[92.270099,24.491685],"type":"Point"}
}