{
  "type": "Feature",
  "properties": {
    "iso:country":"IN",
    "ks:ks_name":"Devjhiri",
    "ks:ks_pop":48,
    "ks:ks_type":"HABITATION",
    "name:eng_x_preferred":[
        "Devjhiri"
    ],
    "wof:name":"Devjhiri",
    "wof:placetype":"locality",
    "wof:population":48
},
  "geometry": {"coordinates":[75.54489700000001,22.384433],"type":"Point"}
}