{
  "type": "Feature",
  "properties": {
    "gn:admin1_code":"24.0",
    "gn:admin2_code":"114.0",
    "gn:asciiname":"Morani",
    "gn:country_code":"IN",
    "gn:dem":223,
    "gn:feature_class":"P",
    "gn:feature_code":"PPL",
    "gn:name":"Morani",
    "gn:population":0,
    "gn:timezone":"Asia/Kolkata",
    "iso:country":"IN",
    "ks:ks_name":"Morani",
    "ks:ks_pop":1180,
    "ks:ks_type":"HABITATION",
    "name:eng_x_preferred":[
        "Morani"
    ],
    "wof:name":"Morani",
    "wof:placetype":"locality",
    "wof:population":1180
},
  "geometry": {"coordinates":[71.99574,26.887426],"type":"Point"}
}