{
  "type": "Feature",
  "properties": {
    "gn:admin1_code":"19",
    "gn:admin2_code":"579.0",
    "gn:asciiname":"Ramatirth",
    "gn:country_code":"IN",
    "gn:dem":516,
    "gn:feature_class":"P",
    "gn:feature_code":"PPL",
    "gn:name":"R\u0101mat\u012brth",
    "gn:population":0,
    "gn:timezone":"Asia/Kolkata",
    "iso:country":"IN",
    "wof:name":"Ramatirth",
    "wof:placetype":"locality"
},
  "geometry": {"coordinates":[77.17874999999999,16.97772],"type":"Point"}
}