{
  "type": "Feature",
  "properties": {
    "iso:country":"IN",
    "ks:ks_name":"Khadriya Durgi",
    "ks:ks_pop":251,
    "ks:ks_type":"HABITATION",
    "name:eng_x_preferred":[
        "Khadriya Durgi"
    ],
    "wof:name":"Khadriya Durgi",
    "wof:placetype":"locality",
    "wof:population":251
},
  "geometry": {"coordinates":[82.757564,27.267638],"type":"Point"}
}