{
  "type": "Feature",
  "properties": {
    "iso:country":"IN",
    "ks:ks_name":"Dhansimulia",
    "ks:ks_pop":1374,
    "ks:ks_type":"VILLAGE",
    "ks:ks_uagg_main":0,
    "name:eng_x_preferred":[
        "Dhansimulia"
    ],
    "wof:name":"Dhansimulia",
    "wof:placetype":"neighbourhood",
    "wof:population":1374
},
  "geometry": {"coordinates":[87.274991,21.797556],"type":"Point"}
}