{
  "type": "Feature",
  "properties": {
    "iso:country":"IN",
    "ks:ks_name":"Naranpur",
    "ks:ks_pop":385,
    "ks:ks_type":"VILLAGE",
    "ks:ks_uagg_main":0,
    "name:eng_x_preferred":[
        "Naranpur"
    ],
    "wof:name":"Naranpur",
    "wof:placetype":"neighbourhood",
    "wof:population":385
},
  "geometry": {"coordinates":[86.553314,21.320145],"type":"Point"}
}