{
  "type": "Feature",
  "properties": {
    "iso:country":"IN",
    "ks:ks_name":"Pure Baba Ghar",
    "ks:ks_pop":6,
    "ks:ks_type":"HABITATION",
    "name:eng_x_preferred":[
        "Pure Baba Ghar"
    ],
    "wof:name":"Pure Baba Ghar",
    "wof:placetype":"locality",
    "wof:population":6
},
  "geometry": {"coordinates":[81.5258,26.4405],"type":"Point"}
}