{
  "type": "Feature",
  "properties": {
    "iso:country":"IN",
    "ks:ks_name":"Kathiya",
    "ks:ks_type":"VILLAGE",
    "name:eng_x_preferred":[
        "Kathiya"
    ],
    "wof:name":"Kathiya",
    "wof:placetype":"locality"
},
  "geometry": {"coordinates":[78.236419,24.422039],"type":"Point"}
}