{
  "type": "Feature",
  "properties": {
    "iso:country":"IN",
    "ks:ks_name":"Mudakupatty",
    "ks:ks_pop":236,
    "ks:ks_type":"HABITATION",
    "name:eng_x_preferred":[
        "Mudakupatty"
    ],
    "wof:name":"Mudakupatty",
    "wof:placetype":"locality",
    "wof:population":236
},
  "geometry": {"coordinates":[78.55110999999999,11.434065],"type":"Point"}
}