{
  "type": "Feature",
  "properties": {
    "gn:admin1_code":"19.0",
    "gn:admin2_code":"575.0",
    "gn:asciiname":"Panna",
    "gn:country_code":"IN",
    "gn:dem":167,
    "gn:feature_class":"P",
    "gn:feature_code":"PPL",
    "gn:name":"Panna",
    "gn:population":0,
    "gn:timezone":"Asia/Kolkata",
    "iso:country":"IN",
    "name:ara_x_preferred":[
        "\u0628\u0627\u0646\u0627"
    ],
    "name:ben_bn_x_preferred":[
        "\u09aa\u09be\u09a8\u09cd\u09a8\u09be"
    ],
    "name:ben_in_x_preferred":[
        "\u09aa\u09be\u09a8\u09cd\u09a8\u09be"
    ],
    "name:ceb_x_preferred":[
        "Panna"
    ],
    "name:ces_x_preferred":[
        "Panna"
    ],
    "name:deu_x_preferred":[
        "Panna"
    ],
    "name:fin_x_preferred":[
        "Panna"
    ],
    "name:guj_x_preferred":[
        "\u0aaa\u0aa8\u0acd\u0aa8\u0abe"
    ],
    "name:hin_x_preferred":[
        "\u092a\u0928\u094d\u0928\u093e"
    ],
    "name:ita_x_preferred":[
        "Panna"
    ],
    "name:kan_x_preferred":[
        "\u0caa\u0ca8\u0ccd\u0ca8\u0cbe"
    ],
    "name:mal_x_preferred":[
        "\u0d2a\u0d28\u0d4d\u0d28"
    ],
    "name:mar_x_preferred":[
        "\u092a\u0928\u094d\u0928\u093e"
    ],
    "name:nld_x_preferred":[
        "Panna"
    ],
    "name:pan_x_preferred":[
        "\u0a2a\u0a70\u0a28\u0a3e"
    ],
    "name:pol_x_preferred":[
        "Panna"
    ],
    "name:slk_x_preferred":[
        "Panna"
    ],
    "name:spa_x_preferred":[
        "Panna"
    ],
    "name:swe_x_preferred":[
        "Panna"
    ],
    "name:tam_x_preferred":[
        "\u0baa\u0ba9\u0bcd\u0ba9\u0bbe"
    ],
    "name:tel_x_preferred":[
        "\u0c2a\u0c28\u0c4d\u0c28\u0c3e"
    ],
    "name:urd_x_preferred":[
        "\u067e\u0646\u0651\u0627"
    ],
    "wof:name":"Panna",
    "wof:placetype":"locality"
},
  "geometry": {"coordinates":[75.62088,12.56129],"type":"Point"}
}