{
  "type": "Feature",
  "properties": {
    "iso:country":"IN",
    "ks:ks_alt_nam":"N\u0101ranga",
    "ks:ks_name":"Naranga",
    "ks:ks_pop":823,
    "ks:ks_type":"VILLAGE",
    "name:eng_x_preferred":[
        "Naranga"
    ],
    "name:eng_x_variant":[
        "N\u0101ranga"
    ],
    "wof:name":"Naranga",
    "wof:placetype":"locality",
    "wof:population":823
},
  "geometry": {"coordinates":[85.45846400000001,22.566757],"type":"Point"}
}