{
  "type": "Feature",
  "properties": {
    "iso:country":"IN",
    "ks:ks_alt_nam":"Tukura P III",
    "ks:ks_name":"Tukura P Iii",
    "ks:ks_pop":1897,
    "ks:ks_type":"HABITATION",
    "name:eng_x_preferred":[
        "Tukura P Iii"
    ],
    "wof:name":"Tukura P Iii",
    "wof:placetype":"locality",
    "wof:population":1897
},
  "geometry": {"coordinates":[90.614902,26.036922],"type":"Point"}
}