{
  "type": "Feature",
  "properties": {
    "iso:country":"IN",
    "ks:ks_alt_nam":"JACK CHERRA",
    "ks:ks_name":"Jack Cherra",
    "ks:ks_pop":446,
    "ks:ks_type":"HABITATION",
    "name:eng_x_preferred":[
        "Jack Cherra"
    ],
    "wof:name":"Jack Cherra",
    "wof:placetype":"locality",
    "wof:population":446
},
  "geometry": {"coordinates":[91.71078900000001,24.01208],"type":"Point"}
}