{
  "type": "Feature",
  "properties": {
    "gn:admin1_code":"12.0",
    "gn:admin2_code":"16.0",
    "gn:asciiname":"Tsibbe",
    "gn:country_code":"IN",
    "gn:dem":1578,
    "gn:feature_class":"P",
    "gn:feature_code":"PPL",
    "gn:name":"Tsibbe",
    "gn:population":0,
    "gn:timezone":"Asia/Kolkata",
    "iso:country":"IN",
    "wof:name":"Tsibbe",
    "wof:placetype":"locality"
},
  "geometry": {"coordinates":[75.80315,33.13305],"type":"Point"}
}