{
  "type": "Feature",
  "properties": {
    "iso:country":"IN",
    "ks:ks_name":"Ghutake",
    "ks:ks_pop":151,
    "ks:ks_type":"VILLAGE",
    "name:eng_x_preferred":[
        "Ghutake"
    ],
    "wof:name":"Ghutake",
    "wof:placetype":"locality",
    "wof:population":151
},
  "geometry": {"coordinates":[73.381322,18.533119],"type":"Point"}
}