{
  "type": "Feature",
  "properties": {
    "iso:country":"IN",
    "ks:ks_name":"Sinti",
    "ks:ks_pop":5920,
    "ks:ks_type":"VILLAGE",
    "name:eng_x_preferred":[
        "Sinti"
    ],
    "wof:name":"Sinti",
    "wof:placetype":"locality",
    "wof:population":5920
},
  "geometry": {"coordinates":[87.964878,22.69574],"type":"Point"}
}