{
  "type": "Feature",
  "properties": {
    "gn:admin1_code":"11",
    "gn:admin2_code":"23.0",
    "gn:asciiname":"Khandiasu",
    "gn:country_code":"IN",
    "gn:dem":1626,
    "gn:feature_class":"P",
    "gn:feature_code":"PPL",
    "gn:name":"Khandi\u0101su",
    "gn:population":0,
    "gn:timezone":"Asia/Kolkata",
    "iso:country":"IN",
    "wof:name":"Khandiasu",
    "wof:placetype":"locality"
},
  "geometry": {"coordinates":[76.13594000000001,32.65225],"type":"Point"}
}