{
  "type": "Feature",
  "properties": {
    "iso:country":"IN",
    "ks:ks_name":"Ruisahar",
    "ks:ks_pop":955,
    "ks:ks_type":"HABITATION",
    "name:eng_x_preferred":[
        "Ruisahar"
    ],
    "wof:name":"Ruisahar",
    "wof:placetype":"locality",
    "wof:population":955
},
  "geometry": {"coordinates":[87.451481,23.095199],"type":"Point"}
}