{
  "type": "Feature",
  "properties": {
    "gn:admin1_code":"36",
    "gn:admin2_code":"145.0",
    "gn:asciiname":"Shahzadpur Gujjar",
    "gn:country_code":"IN",
    "gn:dem":177,
    "gn:feature_class":"P",
    "gn:feature_code":"PPL",
    "gn:name":"Shahz\u0101dpur Gujjar",
    "gn:population":0,
    "gn:timezone":"Asia/Kolkata",
    "iso:country":"IN",
    "wof:name":"Shahzadpur Gujjar",
    "wof:placetype":"locality"
},
  "geometry": {"coordinates":[77.65529000000002,27.27141],"type":"Point"}
}