{
  "type": "Feature",
  "properties": {
    "iso:country":"IN",
    "name:eng_x_preferred":[
        "Gaddi Colony"
    ],
    "name:unk_x_variant":[
        "Gaddi Colony"
    ],
    "qs:gn_adm0_cc":"IN",
    "qs:gn_local":1269507,
    "qs:gn_nam_loc":"Jaisalmer, Jaisalmer, Rajasthan, IN",
    "qs:gn_namadm1":"24",
    "qs:local_max":4971,
    "qs:local_sum":7463,
    "qs:localhoods":8,
    "qs:name":"Gaddi Colony",
    "qs:name_adm0":"India",
    "qs:name_adm1":"Rajasthan",
    "qs:name_adm2":"Jaisalmer",
    "qs:name_local":"Jaisalmer",
    "qs:photo_max":45,
    "qs:photo_sum":60,
    "qs:placetype":"Suburb",
    "qs:quad_count":10,
    "qs:woe_adm0":23424848,
    "qs:woe_adm1":2345757,
    "qs:woe_adm2":12586663,
    "qs:woe_lau":0,
    "qs:woe_local":2290948,
    "qs:woe_ver":"7.10.0",
    "wof:lang":[
        "eng"
    ],
    "wof:name":"Gaddi Colony",
    "wof:placetype":"neighbourhood"
},
  "geometry": {"coordinates":[70.88825199999999,26.923967],"type":"Point"}
}