{
  "type": "Feature",
  "properties": {
    "iso:country":"IN",
    "name:ara_x_preferred":[
        "\u0645\u0633\u062a\u0639\u0645\u0631\u0629 \u062c\u0627\u062f\u064a"
    ],
    "name:ben_bn_x_preferred":[
        "\u0997\u09be\u09a6\u09cd\u09a6\u09bf \u0995\u09b2\u09cb\u09a8\u09c0"
    ],
    "name:ben_in_x_preferred":[
        "\u0997\u09be\u09a6\u09cd\u09a6\u09bf \u0995\u09b2\u09cb\u09a8\u09c0"
    ],
    "name:eng_x_preferred":[
        "Gaddi Colony"
    ],
    "name:guj_x_preferred":[
        "\u0a97\u0aa1\u0acd\u0aa1\u0ac0 \u0a95\u0acb\u0ab2\u0acb\u0aa8\u0ac0"
    ],
    "name:hin_x_preferred":[
        "\u0917\u0926\u094d\u0926\u0940 \u0915\u0949\u0932\u094b\u0928\u0940"
    ],
    "name:kan_x_preferred":[
        "\u0c97\u0ca1\u0ccd\u0ca1\u0cbf \u0c95\u0cbe\u0cb2\u0cca\u0ca8\u0cbf"
    ],
    "name:mal_x_preferred":[
        "\u0d17\u0d3e\u0d21\u0d4d\u0d21\u0d3f \u0d15\u0d4b\u0d33\u0d28\u0d3f"
    ],
    "name:mar_x_preferred":[
        "\u0917\u0921\u0921\u0940 \u0915\u0949\u0932\u0928\u0940"
    ],
    "name:pan_x_preferred":[
        "\u0a17\u0a71\u0a21\u0a40 \u0a15\u0a32\u0a4c\u0a28\u0a40"
    ],
    "name:tam_x_preferred":[
        "\u0b95\u0b9f\u0bcd\u0b9f\u0bbf \u0b95\u0bc1\u0b9f\u0bbf\u0baf\u0bbf\u0bb0\u0bc1\u0baa\u0bcd\u0baa\u0bc1"
    ],
    "name:tel_x_preferred":[
        "\u0c17\u0c21\u0c4d\u0c21\u0c3f \u0c15\u0c3e\u0c32\u0c28\u0c40"
    ],
    "name:urd_x_preferred":[
        "\u06af\u062f\u0651\u06cc \u06a9\u0627\u0644\u0648\u0646\u06cc"
    ],
    "qs:gn_adm0_cc":"IN",
    "qs:gn_local":1269507,
    "qs:gn_nam_loc":"Jaisalmer, Jaisalmer, Rajasthan, IN",
    "qs:gn_namadm1":"24",
    "qs:local_max":4971,
    "qs:local_sum":7463,
    "qs:localhoods":8,
    "qs:name":"Gaddi Colony",
    "qs:name_adm0":"India",
    "qs:name_adm1":"Rajasthan",
    "qs:name_adm2":"Jaisalmer",
    "qs:name_local":"Jaisalmer",
    "qs:photo_max":45,
    "qs:photo_sum":60,
    "qs:placetype":"Suburb",
    "qs:quad_count":10,
    "qs:woe_adm0":23424848,
    "qs:woe_adm1":2345757,
    "qs:woe_adm2":12586663,
    "qs:woe_lau":0,
    "qs:woe_local":2290948,
    "qs:woe_ver":"7.10.0",
    "wof:lang":[
        "eng"
    ],
    "wof:name":"Gaddi Colony",
    "wof:placetype":"neighbourhood"
},
  "geometry": {"coordinates":[70.88825199999999,26.923967],"type":"Point"}
}