{
  "type": "Feature",
  "properties": {
    "iso:country":"IN",
    "ks:ks_name":"Bhalki",
    "ks:ks_pop":162,
    "ks:ks_type":"VILLAGE",
    "name:eng_x_preferred":[
        "Bhalki"
    ],
    "wof:name":"Bhalki",
    "wof:placetype":"locality",
    "wof:population":162
},
  "geometry": {"coordinates":[87.41255200000001,24.209233],"type":"Point"}
}