{
  "type": "Feature",
  "properties": {
    "iso:country":"IN",
    "ks:ks_name":"Guzarpur",
    "ks:ks_pop":3644,
    "ks:ks_type":"VILLAGE",
    "ks:ks_uagg_main":0,
    "name:eng_x_preferred":[
        "Guzarpur"
    ],
    "wof:name":"Guzarpur",
    "wof:placetype":"locality",
    "wof:population":3644
},
  "geometry": {"coordinates":[88.018485,22.57137],"type":"Point"}
}