{
  "type": "Feature",
  "properties": {
    "iso:country":"IN",
    "ks:ks_name":"2 DBL",
    "ks:ks_pop":53,
    "ks:ks_type":"VILLAGE",
    "name:eng_x_preferred":[
        "2 DBL"
    ],
    "wof:name":"2 DBL",
    "wof:placetype":"locality",
    "wof:population":53
},
  "geometry": {"coordinates":[74.521553,29.410169],"type":"Point"}
}