{
  "type": "Feature",
  "properties": {
    "iso:country":"IN",
    "ks:ks_alt_nam":"Karattu KV",
    "ks:ks_name":"Karattu Kv",
    "ks:ks_pop":610,
    "ks:ks_type":"HABITATION",
    "ks:ks_uagg_main":0,
    "name:eng_x_preferred":[
        "Karattu Kv"
    ],
    "wof:name":"Karattu Kv",
    "wof:placetype":"neighbourhood",
    "wof:population":610
},
  "geometry": {"coordinates":[77.898948,11.65298],"type":"Point"}
}