{
  "type": "Feature",
  "properties": {
    "iso:country":"IN",
    "ks:ks_alt_nam":"RAMANASARA",
    "ks:ks_name":"Ramanasara",
    "ks:ks_pop":12,
    "ks:ks_type":"HABITATION",
    "name:eng_x_preferred":[
        "Ramanasara"
    ],
    "wof:name":"Ramanasara",
    "wof:placetype":"locality",
    "wof:population":12
},
  "geometry": {"coordinates":[75.23772,13.794683],"type":"Point"}
}