{
  "type": "Feature",
  "properties": {
    "iso:country":"IN",
    "ks:ks_name":"Dihingia",
    "ks:ks_pop":800,
    "ks:ks_type":"HABITATION",
    "ks:ks_uagg_main":0,
    "name:eng_x_preferred":[
        "Dihingia"
    ],
    "wof:name":"Dihingia",
    "wof:placetype":"locality",
    "wof:population":800
},
  "geometry": {"coordinates":[94.260398,26.77183],"type":"Point"}
}