{
  "type": "Feature",
  "properties": {
    "iso:country":"IN",
    "ks:ks_name":"Gundiyala",
    "ks:ks_pop":26,
    "ks:ks_type":"HABITATION",
    "name:eng_x_preferred":[
        "Gundiyala"
    ],
    "wof:name":"Gundiyala",
    "wof:placetype":"locality",
    "wof:population":26
},
  "geometry": {"coordinates":[75.896944,12.113056],"type":"Point"}
}