{
  "type": "Feature",
  "properties": {
    "iso:country":"IN",
    "ks:ks_name":"Bulungi",
    "ks:ks_pop":93,
    "ks:ks_type":"VILLAGE",
    "name:eng_x_preferred":[
        "Bulungi"
    ],
    "wof:name":"Bulungi",
    "wof:placetype":"locality",
    "wof:population":93
},
  "geometry": {"coordinates":[84.215746,20.458953],"type":"Point"}
}