{
  "type": "Feature",
  "properties": {
    "gn:admin1_code":"39",
    "gn:admin2_code":"61.0",
    "gn:asciiname":"Margaon",
    "gn:country_code":"IN",
    "gn:dem":983,
    "gn:feature_class":"P",
    "gn:feature_code":"PPL",
    "gn:name":"Margaon",
    "gn:population":0,
    "gn:timezone":"Asia/Kolkata",
    "iso:country":"IN",
    "ks:ks_name":"Margaon",
    "ks:ks_type":"VILLAGE",
    "name:eng_x_preferred":[
        "Margaon"
    ],
    "wof:name":"Margaon",
    "wof:placetype":"locality"
},
  "geometry": {"coordinates":[78.92847500000001,30.231248],"type":"Point"}
}