{
  "type": "Feature",
  "properties": {
    "iso:country":"IN",
    "ks:ks_name":"Jodimanuguda",
    "ks:ks_pop":75,
    "ks:ks_type":"HABITATION",
    "name:eng_x_preferred":[
        "Jodimanuguda"
    ],
    "wof:name":"Jodimanuguda",
    "wof:placetype":"locality",
    "wof:population":75
},
  "geometry": {"coordinates":[83.817307,18.634696],"type":"Point"}
}