{
  "type": "Feature",
  "properties": {
    "iso:country":"IN",
    "ks:ks_name":"Bannadybettu",
    "ks:ks_pop":126,
    "ks:ks_type":"HABITATION",
    "name:eng_x_preferred":[
        "Bannadybettu"
    ],
    "wof:name":"Bannadybettu",
    "wof:placetype":"locality",
    "wof:population":126
},
  "geometry": {"coordinates":[74.721626,13.502939],"type":"Point"}
}