{
  "type": "Feature",
  "properties": {
    "iso:country":"IN",
    "ks:ks_name":"Tergalwadi",
    "ks:ks_pop":180,
    "ks:ks_type":"HABITATION",
    "name:eng_x_preferred":[
        "Tergalwadi"
    ],
    "wof:name":"Tergalwadi",
    "wof:placetype":"locality",
    "wof:population":180
},
  "geometry": {"coordinates":[73.94442100000001,16.033431],"type":"Point"}
}