{
  "type": "Feature",
  "properties": {
    "gn:admin1_code":"25.0",
    "gn:admin2_code":"607.0",
    "gn:asciiname":"Kudavampundi",
    "gn:country_code":"IN",
    "gn:dem":138,
    "gn:feature_class":"P",
    "gn:feature_code":"PPL",
    "gn:name":"K\u016bdav\u0101mp\u016bndi",
    "gn:population":0,
    "gn:timezone":"Asia/Kolkata",
    "iso:country":"IN",
    "wof:name":"Kudavampundi",
    "wof:placetype":"neighbourhood"
},
  "geometry": {"coordinates":[79.3582,12.40143],"type":"Point"}
}