{
  "type": "Feature",
  "properties": {
    "iso:country":"IN",
    "ks:ks_name":"Bodumalladinne",
    "ks:ks_pop":466,
    "ks:ks_type":"HABITATION",
    "name:eng_x_preferred":[
        "Bodumalladinne"
    ],
    "wof:name":"Bodumalladinne",
    "wof:placetype":"locality",
    "wof:population":466
},
  "geometry": {"coordinates":[78.550202,13.565487],"type":"Point"}
}