{
  "type": "Feature",
  "properties": {
    "iso:country":"IN",
    "ks:ks_name":"Shettyganahally",
    "ks:ks_pop":239,
    "ks:ks_type":"HABITATION",
    "name:eng_x_preferred":[
        "Shettyganahally"
    ],
    "wof:name":"Shettyganahally",
    "wof:placetype":"locality",
    "wof:population":239
},
  "geometry": {"coordinates":[76.97228200000001,13.968578],"type":"Point"}
}