{
  "type": "Feature",
  "properties": {
    "gn:admin1_code":"36",
    "gn:admin2_code":"147.0",
    "gn:asciiname":"Ganeshpur Nagaria",
    "gn:country_code":"IN",
    "gn:dem":170,
    "gn:feature_class":"P",
    "gn:feature_code":"PPL",
    "gn:name":"Ganeshpur Nagaria",
    "gn:population":0,
    "gn:timezone":"Asia/Kolkata",
    "iso:country":"IN",
    "wof:name":"Ganeshpur Nagaria",
    "wof:placetype":"locality"
},
  "geometry": {"coordinates":[78.61456,27.40102000000001],"type":"Point"}
}