{
  "type": "Feature",
  "properties": {
    "iso:country":"IN",
    "ks:ks_name":"Senssowa",
    "ks:ks_pop":625,
    "ks:ks_type":"HABITATION",
    "name:eng_x_preferred":[
        "Senssowa"
    ],
    "wof:name":"Senssowa",
    "wof:placetype":"locality",
    "wof:population":625
},
  "geometry": {"coordinates":[94.265823,27.406535],"type":"Point"}
}