{
  "type": "Feature",
  "properties": {
    "iso:country":"IN",
    "ks:ks_name":"Rengai",
    "ks:ks_pop":95,
    "ks:ks_type":"VILLAGE",
    "name:eng_x_preferred":[
        "Rengai"
    ],
    "wof:name":"Rengai",
    "wof:placetype":"locality",
    "wof:population":95
},
  "geometry": {"coordinates":[84.41752,23.964671],"type":"Point"}
}