{
  "type": "Feature",
  "properties": {
    "gn:admin1_code":"36",
    "gn:admin2_code":"166.0",
    "gn:asciiname":"Bajranggarh",
    "gn:country_code":"IN",
    "gn:dem":277,
    "gn:feature_class":"P",
    "gn:feature_code":"PPL",
    "gn:name":"Bajranggarh",
    "gn:population":0,
    "gn:timezone":"Asia/Kolkata",
    "iso:country":"IN",
    "wof:name":"Bajranggarh",
    "wof:placetype":"locality"
},
  "geometry": {"coordinates":[78.46451999999999,25.36857],"type":"Point"}
}