{
  "type": "Feature",
  "properties": {
    "iso:country":"IN",
    "ks:ks_name":"Rahman Tola",
    "ks:ks_pop":616,
    "ks:ks_type":"HABITATION",
    "ks:ks_uagg_main":0,
    "name:eng_x_preferred":[
        "Rahman Tola"
    ],
    "wof:name":"Rahman Tola",
    "wof:placetype":"neighbourhood",
    "wof:population":616
},
  "geometry": {"coordinates":[87.12551499999999,25.928375],"type":"Point"}
}