{
  "type": "Feature",
  "properties": {
    "iso:country":"IN",
    "ks:ks_name":"Kese",
    "ks:ks_pop":667,
    "ks:ks_type":"VILLAGE",
    "name:eng_x_preferred":[
        "Kese"
    ],
    "wof:name":"Kese",
    "wof:placetype":"locality",
    "wof:population":667
},
  "geometry": {"coordinates":[86.89872099999999,22.890659],"type":"Point"}
}