{
  "type": "Feature",
  "properties": {
    "iso:country":"IN",
    "ks:ks_name":"Middle Bahadur Adarsha Gaon",
    "ks:ks_pop":546,
    "ks:ks_type":"HABITATION",
    "name:eng_x_preferred":[
        "Middle Bahadur Adarsha Gaon"
    ],
    "wof:name":"Middle Bahadur Adarsha Gaon",
    "wof:placetype":"locality",
    "wof:population":546
},
  "geometry": {"coordinates":[92.279695,26.857891],"type":"Point"}
}