{
  "type": "Feature",
  "properties": {
    "iso:country":"IN",
    "ks:ks_name":"Thaviwadi",
    "ks:ks_pop":32,
    "ks:ks_type":"HABITATION",
    "name:eng_x_preferred":[
        "Thaviwadi"
    ],
    "wof:name":"Thaviwadi",
    "wof:placetype":"locality",
    "wof:population":32
},
  "geometry": {"coordinates":[73.58775199999999,16.027047],"type":"Point"}
}