{
  "type": "Feature",
  "properties": {
    "gn:admin1_code":"11.0",
    "gn:admin2_code":"32.0",
    "gn:asciiname":"Parli",
    "gn:country_code":"IN",
    "gn:dem":972,
    "gn:feature_class":"P",
    "gn:feature_code":"PPL",
    "gn:name":"P\u0101rli",
    "gn:population":0,
    "gn:timezone":"Asia/Kolkata",
    "iso:country":"IN",
    "name:deu_x_preferred":[
        "Parli"
    ],
    "name:hin_x_preferred":[
        "\u092a\u0930\u0932\u0940"
    ],
    "name:mar_x_preferred":[
        "\u092a\u0930\u0933\u0940"
    ],
    "wof:name":"Parli",
    "wof:placetype":"locality"
},
  "geometry": {"coordinates":[77.73282,30.68686],"type":"Point"}
}