{
  "type": "Feature",
  "properties": {
    "iso:country":"IN",
    "ks:ks_name":"Benjeng",
    "ks:ks_pop":120,
    "ks:ks_type":"HABITATION",
    "name:eng_x_preferred":[
        "Benjeng"
    ],
    "wof:name":"Benjeng",
    "wof:placetype":"locality",
    "wof:population":120
},
  "geometry": {"coordinates":[91.212532,25.786514],"type":"Point"}
}