{
  "type": "Feature",
  "properties": {
    "gn:admin1_code":"24",
    "gn:admin2_code":"125.0",
    "gn:asciiname":"Chitoria",
    "gn:country_code":"IN",
    "gn:dem":266,
    "gn:feature_class":"P",
    "gn:feature_code":"PPL",
    "gn:name":"Chitoria",
    "gn:population":0,
    "gn:timezone":"Asia/Kolkata",
    "iso:country":"IN",
    "name:ast_x_preferred":[
        "Chitoria"
    ],
    "name:fas_x_preferred":[
        "\u0627\u0645\u067e\u0631\u0627\u062a\u0648\u0631\u06cc\u0627\u0646 \u0686\u06cc\u062a\u0648\u0631\u06cc\u0627"
    ],
    "name:hun_x_preferred":[
        "Chitoria"
    ],
    "name:nld_x_preferred":[
        "Chitoria"
    ],
    "name:nor_x_preferred":[
        "Chitoria"
    ],
    "name:rus_x_preferred":[
        "Chitoria"
    ],
    "name:spa_x_preferred":[
        "Chitoria"
    ],
    "name:vie_x_preferred":[
        "Chitoria"
    ],
    "name:zho_x_preferred":[
        "\u93a7\u86fa\u8776\u5c6c"
    ],
    "wof:name":"Chitoria",
    "wof:placetype":"locality"
},
  "geometry": {"coordinates":[74.30847,23.20192],"type":"Point"}
}