{
  "type": "Feature",
  "properties": {
    "gn:admin1_code":"24",
    "gn:admin2_code":"125.0",
    "gn:asciiname":"Chitoria",
    "gn:country_code":"IN",
    "gn:dem":266,
    "gn:feature_class":"P",
    "gn:feature_code":"PPL",
    "gn:name":"Chitoria",
    "gn:population":0,
    "gn:timezone":"Asia/Kolkata",
    "iso:country":"IN",
    "wof:name":"Chitoria",
    "wof:placetype":"locality"
},
  "geometry": {"coordinates":[74.30847,23.20192],"type":"Point"}
}