{
  "type": "Feature",
  "properties": {
    "iso:country":"IN",
    "ks:ks_name":"Murikenchal",
    "ks:ks_pop":110,
    "ks:ks_type":"HABITATION",
    "name:eng_x_preferred":[
        "Murikenchal"
    ],
    "wof:name":"Murikenchal",
    "wof:placetype":"locality",
    "wof:population":110
},
  "geometry": {"coordinates":[76.02876999999999,11.426549],"type":"Point"}
}