{
  "type": "Feature",
  "properties": {
    "iso:country":"IN",
    "ks:ks_name":"Bahigawan Jogipur Jagdishpur",
    "ks:ks_pop":222,
    "ks:ks_type":"HABITATION",
    "name:eng_x_preferred":[
        "Bahigawan Jogipur Jagdishpur"
    ],
    "wof:name":"Bahigawan Jogipur Jagdishpur",
    "wof:placetype":"locality",
    "wof:population":222
},
  "geometry": {"coordinates":[82.880084,26.410435],"type":"Point"}
}