{
  "type": "Feature",
  "properties": {
    "gn:admin1_code":"36",
    "gn:admin2_code":"194.0",
    "gn:asciiname":"Dharnidharpur",
    "gn:country_code":"IN",
    "gn:dem":78,
    "gn:feature_class":"P",
    "gn:feature_code":"PPL",
    "gn:name":"Dharn\u012bdharpur",
    "gn:population":0,
    "gn:timezone":"Asia/Kolkata",
    "iso:country":"IN",
    "ks:ks_name":"Dharanidharpur",
    "ks:ks_pop":414,
    "ks:ks_type":"VILLAGE",
    "ks:ks_uagg_main":0,
    "name:eng_x_preferred":[
        "Dharanidharpur"
    ],
    "wof:name":"Dharanidharpur",
    "wof:placetype":"locality",
    "wof:population":414
},
  "geometry": {"coordinates":[82.703701,25.760353],"type":"Point"}
}