{
  "type": "Feature",
  "properties": {
    "gn:admin1_code":"34",
    "gn:admin2_code":"233.0",
    "gn:asciiname":"Gamhariya",
    "gn:country_code":"IN",
    "gn:dem":413,
    "gn:feature_class":"P",
    "gn:feature_code":"PPL",
    "gn:name":"Gamhariya",
    "gn:population":0,
    "gn:timezone":"Asia/Kolkata",
    "iso:country":"IN",
    "wof:name":"Gamhariya",
    "wof:placetype":"locality"
},
  "geometry": {"coordinates":[83.54810999999999,24.76291],"type":"Point"}
}