{
  "type": "Feature",
  "properties": {
    "iso:country":"IN",
    "ks:ks_name":"Neduvilai",
    "ks:ks_pop":477,
    "ks:ks_type":"HABITATION",
    "name:eng_x_preferred":[
        "Neduvilai"
    ],
    "wof:name":"Neduvilai",
    "wof:placetype":"locality",
    "wof:population":477
},
  "geometry": {"coordinates":[77.58197199999999,8.570412],"type":"Point"}
}