{
  "type": "Feature",
  "properties": {
    "iso:country":"IN",
    "ks:ks_name":"Bisokhar",
    "ks:ks_type":"VILLAGE",
    "ks:ks_uagg_main":0,
    "name:eng_x_preferred":[
        "Bisokhar"
    ],
    "wof:name":"Bisokhar",
    "wof:placetype":"neighbourhood"
},
  "geometry": {"coordinates":[77.58420099999999,28.851501],"type":"Point"}
}