{
  "type": "Feature",
  "properties": {
    "iso:country":"IN",
    "ks:ks_name":"Lohala",
    "ks:ks_pop":583,
    "ks:ks_type":"HABITATION",
    "ks:ks_uagg_main":0,
    "name:eng_x_preferred":[
        "Lohala"
    ],
    "wof:name":"Lohala",
    "wof:placetype":"neighbourhood",
    "wof:population":583
},
  "geometry": {"coordinates":[75.74848,32.366364],"type":"Point"}
}