{
  "type": "Feature",
  "properties": {
    "iso:country":"IN",
    "ks:ks_name":"Markada",
    "ks:ks_pop":195,
    "ks:ks_type":"VILLAGE",
    "name:eng_x_preferred":[
        "Markada"
    ],
    "wof:name":"Markada",
    "wof:placetype":"locality",
    "wof:population":195
},
  "geometry": {"coordinates":[84.260673,18.920651],"type":"Point"}
}