{
  "type": "Feature",
  "properties": {
    "iso:country":"IN",
    "ks:ks_name":"Koilseemai",
    "ks:ks_pop":587,
    "ks:ks_type":"HABITATION",
    "name:eng_x_preferred":[
        "Koilseemai"
    ],
    "wof:name":"Koilseemai",
    "wof:placetype":"locality",
    "wof:population":587
},
  "geometry": {"coordinates":[79.219172,11.006337],"type":"Point"}
}