{
  "type": "Feature",
  "properties": {
    "iso:country":"IN",
    "ks:ks_name":"Vaniampatty",
    "ks:ks_pop":250,
    "ks:ks_type":"HABITATION",
    "name:eng_x_preferred":[
        "Vaniampatty"
    ],
    "wof:name":"Vaniampatty",
    "wof:placetype":"locality",
    "wof:population":250
},
  "geometry": {"coordinates":[77.837003,9.302289],"type":"Point"}
}