{
  "type": "Feature",
  "properties": {
    "iso:country":"IN",
    "ks:ks_name":"Phuluribania",
    "ks:ks_type":"VILLAGE",
    "name:eng_x_preferred":[
        "Phuluribania"
    ],
    "wof:name":"Phuluribania",
    "wof:placetype":"locality"
},
  "geometry": {"coordinates":[84.61459499999999,20.848636],"type":"Point"}
}