{
  "type": "Feature",
  "properties": {
    "iso:country":"IN",
    "ks:ks_name":"Chadumanahalli",
    "ks:ks_pop":3,
    "ks:ks_type":"VILLAGE",
    "name:eng_x_preferred":[
        "Chadumanahalli"
    ],
    "wof:name":"Chadumanahalli",
    "wof:placetype":"locality",
    "wof:population":3
},
  "geometry": {"coordinates":[77.68607299999999,13.681689],"type":"Point"}
}