{
  "type": "Feature",
  "properties": {
    "iso:country":"IN",
    "ks:ks_name":"Machpara",
    "ks:ks_pop":1682,
    "ks:ks_type":"HABITATION",
    "name:eng_x_preferred":[
        "Machpara"
    ],
    "wof:name":"Machpara",
    "wof:placetype":"locality",
    "wof:population":1682
},
  "geometry": {"coordinates":[90.184951,26.230442],"type":"Point"}
}