{
  "type": "Feature",
  "properties": {
    "iso:country":"IN",
    "ks:ks_name":"Khalchi Bouddhwadi",
    "ks:ks_pop":90,
    "ks:ks_type":"HABITATION",
    "name:eng_x_preferred":[
        "Khalchi Bouddhwadi"
    ],
    "wof:name":"Khalchi Bouddhwadi",
    "wof:placetype":"locality",
    "wof:population":90
},
  "geometry": {"coordinates":[73.64357099999999,16.208389],"type":"Point"}
}