{
  "type": "Feature",
  "properties": {
    "iso:country":"IN",
    "ks:ks_alt_nam":"Kergandi",
    "ks:ks_name":"Kergondi",
    "ks:ks_pop":0,
    "ks:ks_type":"VILLAGE",
    "name:eng_x_preferred":[
        "Kergondi"
    ],
    "name:eng_x_variant":[
        "Kergandi"
    ],
    "wof:name":"Kergondi",
    "wof:placetype":"locality",
    "wof:population":0
},
  "geometry": {"coordinates":[78.72844000000001,20.978741],"type":"Point"}
}