{
  "type": "Feature",
  "properties": {
    "iso:country":"IN",
    "ks:ks_alt_nam":"pipalda",
    "ks:ks_name":"Pipalda",
    "ks:ks_pop":70,
    "ks:ks_type":"HABITATION",
    "name:eng_x_preferred":[
        "Pipalda"
    ],
    "wof:name":"Pipalda",
    "wof:placetype":"locality",
    "wof:population":70
},
  "geometry": {"coordinates":[76.78058799999999,22.384502],"type":"Point"}
}