{
  "type": "Feature",
  "properties": {
    "iso:country":"IN",
    "ks:ks_name":"Nadupatti",
    "ks:ks_pop":390,
    "ks:ks_type":"HABITATION",
    "name:eng_x_preferred":[
        "Nadupatti"
    ],
    "wof:name":"Nadupatti",
    "wof:placetype":"locality",
    "wof:population":390
},
  "geometry": {"coordinates":[78.754192,10.700423],"type":"Point"}
}