{
  "type": "Feature",
  "properties": {
    "iso:country":"IN",
    "ks:ks_name":"Lili",
    "ks:ks_pop":614,
    "ks:ks_type":"VILLAGE",
    "name:eng_x_preferred":[
        "Lili"
    ],
    "wof:name":"Lili",
    "wof:placetype":"locality",
    "wof:population":614
},
  "geometry": {"coordinates":[79.861819,29.943335],"type":"Point"}
}