{
  "type": "Feature",
  "properties": {
    "iso:country":"IN",
    "ks:ks_name":"Bhoppanadu",
    "ks:ks_pop":589,
    "ks:ks_type":"VILLAGE",
    "name:eng_x_preferred":[
        "Bhoppanadu"
    ],
    "wof:name":"Bhoppanadu",
    "wof:placetype":"locality",
    "wof:population":589
},
  "geometry": {"coordinates":[76.96371499999999,13.840251],"type":"Point"}
}