{
  "type": "Feature",
  "properties": {
    "iso:country":"IN",
    "ks:ks_alt_nam":"Balimora T.E. A",
    "ks:ks_name":"Balimora T.e. A",
    "ks:ks_pop":302,
    "ks:ks_type":"HABITATION",
    "name:eng_x_preferred":[
        "Balimora T.e. A"
    ],
    "wof:name":"Balimora T.e. A",
    "wof:placetype":"locality",
    "wof:population":302
},
  "geometry": {"coordinates":[95.33199999999999,27.238171],"type":"Point"}
}