{
  "type": "Feature",
  "properties": {
    "iso:country":"IN",
    "ks:ks_name":"Raja Bigha",
    "ks:ks_pop":150,
    "ks:ks_type":"HABITATION",
    "name:eng_x_preferred":[
        "Raja Bigha"
    ],
    "wof:name":"Raja Bigha",
    "wof:placetype":"locality",
    "wof:population":150
},
  "geometry": {"coordinates":[85.474636,25.21249],"type":"Point"}
}