{
  "type": "Feature",
  "properties": {
    "iso:country":"IN",
    "ks:ks_name":"Biruhi Jore",
    "ks:ks_pop":300,
    "ks:ks_type":"HABITATION",
    "name:eng_x_preferred":[
        "Biruhi Jore"
    ],
    "wof:name":"Biruhi Jore",
    "wof:placetype":"locality",
    "wof:population":300
},
  "geometry": {"coordinates":[80.16192700000001,27.439611],"type":"Point"}
}