{
  "type": "Feature",
  "properties": {
    "iso:country":"IN",
    "ks:ks_alt_nam":"urenia",
    "ks:ks_name":"Urenia",
    "ks:ks_pop":697,
    "ks:ks_type":"HABITATION",
    "name:eng_x_preferred":[
        "Urenia"
    ],
    "wof:name":"Urenia",
    "wof:placetype":"locality",
    "wof:population":697
},
  "geometry": {"coordinates":[85.468226,22.632101],"type":"Point"}
}