{
  "type": "Feature",
  "properties": {
    "gn:admin1_code":"19.0",
    "gn:admin2_code":"583.0",
    "gn:asciiname":"Yartiganhalli",
    "gn:country_code":"IN",
    "gn:dem":903,
    "gn:feature_class":"P",
    "gn:feature_code":"PPL",
    "gn:name":"Yartiganhalli",
    "gn:population":0,
    "gn:timezone":"Asia/Kolkata",
    "iso:country":"IN",
    "ks:ks_name":"Yerthiganahalli",
    "ks:ks_pop":803,
    "ks:ks_type":"VILLAGE",
    "ks:ks_uagg_main":0,
    "name:eng_x_preferred":[
        "Yerthiganahalli"
    ],
    "wof:name":"Yerthiganahalli",
    "wof:placetype":"neighbourhood",
    "wof:population":803
},
  "geometry": {"coordinates":[77.675241,13.195054],"type":"Point"}
}