{
  "type": "Feature",
  "properties": {
    "gn:country":"IN",
    "gn:fcode":"PPL",
    "gn:population":0,
    "iso:country":"IN",
    "name:cat_x_preferred":[
        "Dawar"
    ],
    "name:eng_x_preferred":[
        "Dawar"
    ],
    "name:fas_x_preferred":[
        "\u062f\u0627\u0648\u0631 \u0628\u062e\u0634"
    ],
    "name:fra_x_preferred":[
        "Bul\u00e2ki"
    ],
    "name:heb_x_preferred":[
        "\u05d3\u05d5\u05d5\u05d0\u05e8"
    ],
    "name:nld_x_preferred":[
        "Dawar"
    ],
    "name:spa_x_preferred":[
        "Dawar"
    ],
    "name:swe_x_preferred":[
        "Dawar Baksh"
    ],
    "name:urd_x_preferred":[
        "\u062f\u0627\u0648\u0631 \u0628\u062e\u0634"
    ],
    "qs:name":"Dawar",
    "qs:name_adm0":"India",
    "qs:name_adm1":"Jammu and Kashmir",
    "qs:photos_9k":1,
    "qs:photos_9r":1,
    "qs:photos_all":2,
    "qs:photos_sr":0,
    "qs:placetype":"Town",
    "qs:pop_sr":"0",
    "wd:wordcount":517,
    "wof:name":"Dawar",
    "wof:placetype":"locality",
    "wof:population":0
},
  "geometry": {"coordinates":[74.45292999999999,34.45771],"type":"Point"}
}