{
  "type": "Feature",
  "properties": {
    "iso:country":"IN",
    "ks:ks_name":"Adali",
    "ks:ks_type":"VILLAGE",
    "name:eng_x_preferred":[
        "Adali"
    ],
    "wof:name":"Adali",
    "wof:placetype":"locality"
},
  "geometry": {"coordinates":[78.33018300000001,30.178351],"type":"Point"}
}