{
  "type": "Feature",
  "properties": {
    "gn:admin1_code":"37",
    "gn:admin2_code":"400.0",
    "gn:asciiname":"Manjapara",
    "gn:country_code":"IN",
    "gn:dem":447,
    "gn:feature_class":"P",
    "gn:feature_code":"PPL",
    "gn:name":"Manj\u0101p\u0101ra",
    "gn:population":0,
    "gn:timezone":"Asia/Kolkata",
    "iso:country":"IN",
    "wof:name":"Manjapara",
    "wof:placetype":"locality"
},
  "geometry": {"coordinates":[82.51250999999998,22.98162],"type":"Point"}
}