{
  "type": "Feature",
  "properties": {
    "iso:country":"IN",
    "ks:ks_name":"Dombargudisai",
    "ks:ks_pop":140,
    "ks:ks_type":"HABITATION",
    "name:eng_x_preferred":[
        "Dombargudisai"
    ],
    "wof:name":"Dombargudisai",
    "wof:placetype":"locality",
    "wof:population":140
},
  "geometry": {"coordinates":[77.975217,12.827373],"type":"Point"}
}