{
  "type": "Feature",
  "properties": {
    "iso:country":"IN",
    "ks:ks_name":"Keratoli",
    "ks:ks_pop":158,
    "ks:ks_type":"HABITATION",
    "name:eng_x_preferred":[
        "Keratoli"
    ],
    "wof:name":"Keratoli",
    "wof:placetype":"locality",
    "wof:population":158
},
  "geometry": {"coordinates":[84.33722,22.808077],"type":"Point"}
}