{
  "type": "Feature",
  "properties": {
    "iso:country":"IN",
    "ks:ks_alt_nam":"channapattana",
    "ks:ks_name":"Channapattana",
    "ks:ks_pop":1042,
    "ks:ks_type":"HABITATION",
    "name:eng_x_preferred":[
        "Channapattana"
    ],
    "wof:name":"Channapattana",
    "wof:placetype":"locality",
    "wof:population":1042
},
  "geometry": {"coordinates":[75.548574,15.191176],"type":"Point"}
}