{
  "type": "Feature",
  "properties": {
    "iso:country":"IN",
    "ks:ks_name":"Athanikkal Jn",
    "ks:ks_pop":2386,
    "ks:ks_type":"HABITATION",
    "name:eng_x_preferred":[
        "Athanikkal Jn"
    ],
    "wof:name":"Athanikkal Jn",
    "wof:placetype":"locality",
    "wof:population":2386
},
  "geometry": {"coordinates":[76.061492,11.191839],"type":"Point"}
}