{
  "type": "Feature",
  "properties": {
    "gn:admin1_code":"36.0",
    "gn:admin2_code":"165",
    "gn:asciiname":"Lachhmanpura",
    "gn:country_code":"IN",
    "gn:dem":145,
    "gn:feature_class":"P",
    "gn:feature_code":"PPL",
    "gn:name":"Lachhmanpura",
    "gn:population":0,
    "gn:timezone":"Asia/Kolkata",
    "iso:country":"IN",
    "wof:name":"Lachhmanpura",
    "wof:placetype":"locality"
},
  "geometry": {"coordinates":[79.11135,26.38455],"type":"Point"}
}