{
  "type": "Feature",
  "properties": {
    "gn:admin1_code":"16.0",
    "gn:admin2_code":"512.0",
    "gn:asciiname":"Hudi",
    "gn:country_code":"IN",
    "gn:dem":431,
    "gn:feature_class":"P",
    "gn:feature_code":"PPL",
    "gn:name":"H\u016bdi",
    "gn:population":0,
    "gn:timezone":"Asia/Kolkata",
    "iso:country":"IN",
    "ks:ks_alt_nam":"H\u016bdi",
    "ks:ks_name":"Hudi",
    "ks:ks_pop":423,
    "ks:ks_type":"VILLAGE",
    "name:eng_x_preferred":[
        "Hudi"
    ],
    "name:eng_x_variant":[
        "H\u016bdi"
    ],
    "name:fas_x_preferred":[
        "\u0647\u0648\u062f\u06cc"
    ],
    "name:msa_x_preferred":[
        "Hudi"
    ],
    "name:ukr_x_preferred":[
        "\u0425\u0443\u0434\u0456"
    ],
    "name:ukr_x_variant":[
        "\u0413\u0443\u0434\u0456"
    ],
    "name:urd_x_preferred":[
        "\u06c1\u0648\u062f\u06cc"
    ],
    "name:vie_x_preferred":[
        "S\u00f4ng Hudi"
    ],
    "name:zho_cn_x_preferred":[
        "\u80e1\u8fea\u6cb3"
    ],
    "name:zho_tw_x_preferred":[
        "\u80e1\u7b2c\u6cb3"
    ],
    "wof:name":"Hudi",
    "wof:placetype":"locality",
    "wof:population":423
},
  "geometry": {"coordinates":[76.856444,19.707605],"type":"Point"}
}