{
  "type": "Feature",
  "properties": {
    "gn:admin1_code":"19.0",
    "gn:admin2_code":"584.0",
    "gn:asciiname":"Siddegowdandoddi",
    "gn:country_code":"IN",
    "gn:dem":641,
    "gn:feature_class":"P",
    "gn:feature_code":"PPL",
    "gn:name":"Siddegowdandoddi",
    "gn:population":0,
    "gn:timezone":"Asia/Kolkata",
    "iso:country":"IN",
    "ks:ks_name":"Siddegowdana Doddi",
    "ks:ks_pop":66,
    "ks:ks_type":"HABITATION",
    "name:eng_x_preferred":[
        "Siddegowdana Doddi"
    ],
    "name:eng_x_variant":[
        "Siddegowdandoddi"
    ],
    "wof:name":"Siddegowdana Doddi",
    "wof:placetype":"locality",
    "wof:population":66
},
  "geometry": {"coordinates":[77.22655399999999,12.588404],"type":"Point"}
}