{
  "type": "Feature",
  "properties": {
    "iso:country":"IN",
    "ks:ks_name":"Pichhoura",
    "ks:ks_pop":158,
    "ks:ks_type":"HABITATION",
    "name:eng_x_preferred":[
        "Pichhoura"
    ],
    "wof:name":"Pichhoura",
    "wof:placetype":"locality",
    "wof:population":158
},
  "geometry": {"coordinates":[83.02914699999999,27.41018],"type":"Point"}
}