{
  "type": "Feature",
  "properties": {
    "iso:country":"IN",
    "ks:ks_name":"Rajwal Madarha",
    "ks:ks_pop":1427,
    "ks:ks_type":"VILLAGE",
    "name:eng_x_preferred":[
        "Rajwal Madarha"
    ],
    "wof:name":"Rajwal Madarha",
    "wof:placetype":"locality",
    "wof:population":1427
},
  "geometry": {"coordinates":[83.801469,27.117808],"type":"Point"}
}