{
  "type": "Feature",
  "properties": {
    "iso:country":"IN",
    "ks:ks_name":"Colony",
    "ks:ks_pop":313,
    "ks:ks_type":"HABITATION",
    "ks:ks_uagg_main":0,
    "name:eng_x_preferred":[
        "Colony"
    ],
    "wof:name":"Colony",
    "wof:placetype":"neighbourhood",
    "wof:population":313
},
  "geometry": {"coordinates":[76.366688,10.243764],"type":"Point"}
}