{
  "type": "Feature",
  "properties": {
    "iso:country":"IN",
    "ks:ks_alt_nam":"Bindis\u0101i",
    "ks:ks_name":"Bindisai",
    "ks:ks_pop":533,
    "ks:ks_type":"VILLAGE",
    "name:eng_x_preferred":[
        "Bindisai"
    ],
    "name:eng_x_variant":[
        "Bindis\u0101i"
    ],
    "wof:name":"Bindisai",
    "wof:placetype":"locality",
    "wof:population":533
},
  "geometry": {"coordinates":[85.714574,22.246137],"type":"Point"}
}