{
  "type": "Feature",
  "properties": {
    "iso:country":"IN",
    "ks:ks_name":"Autikiri",
    "ks:ks_pop":21,
    "ks:ks_type":"VILLAGE",
    "ks:ks_uagg_main":0,
    "name:eng_x_preferred":[
        "Autikiri"
    ],
    "wof:name":"Autikiri",
    "wof:placetype":"neighbourhood",
    "wof:population":21
},
  "geometry": {"coordinates":[86.282535,20.242832],"type":"Point"}
}