{
  "type": "Feature",
  "properties": {
    "iso:country":"IN",
    "ks:ks_name":"Rautwasti",
    "ks:ks_pop":308,
    "ks:ks_type":"HABITATION",
    "name:eng_x_preferred":[
        "Rautwasti"
    ],
    "wof:name":"Rautwasti",
    "wof:placetype":"locality",
    "wof:population":308
},
  "geometry": {"coordinates":[75.353048,17.933273],"type":"Point"}
}