{
  "type": "Feature",
  "properties": {
    "gn:admin1_code":"2.0",
    "gn:admin2_code":"551.0",
    "gn:asciiname":"Velavali",
    "gn:country_code":"IN",
    "gn:dem":154,
    "gn:feature_class":"P",
    "gn:feature_code":"PPL",
    "gn:name":"Velavali",
    "gn:population":0,
    "gn:timezone":"Asia/Kolkata",
    "iso:country":"IN",
    "name:hin_x_preferred":[
        "\u0935\u0946\u0932\u0935\u0932\u093f"
    ],
    "name:new_x_preferred":[
        "\u0935\u0946\u0932\u0935\u0932\u093f"
    ],
    "name:tel_x_preferred":[
        "\u0c35\u0c46\u0c32\u0c35\u0c32\u0c3f"
    ],
    "wof:name":"Velavali",
    "wof:placetype":"locality"
},
  "geometry": {"coordinates":[78.61355,14.83196],"type":"Point"}
}