{
  "type": "Feature",
  "properties": {
    "gn:country":"IN",
    "gn:fcode":"PPL",
    "gn:pop":9396,
    "iso:country":"IN",
    "name:ben_x_preferred":[
        "\u0996\u09be\u09ae\u09be\u09a8\u09cb\u09a8"
    ],
    "name:bpy_x_preferred":[
        "\u0996\u09be\u09ae\u09be\u09a8\u09cb\u09a8"
    ],
    "name:ceb_x_preferred":[
        "Kham\u0101non"
    ],
    "name:deu_x_preferred":[
        "Khamanon"
    ],
    "name:eng_x_preferred":[
        "Khamanon"
    ],
    "name:fra_x_preferred":[
        "Khamanon"
    ],
    "name:guj_x_preferred":[
        "\u0a96\u0abe\u0aae\u0abe\u0aa8\u0acb\u0aa8"
    ],
    "name:ita_x_preferred":[
        "Khamanon"
    ],
    "name:jpn_x_preferred":[
        "\u30ab\u30fc\u30de\u30ce\u30f3"
    ],
    "name:kan_x_preferred":[
        "\u0c96\u0cae\u0ca8\u0cca\u0ca8\u0ccd"
    ],
    "name:kor_x_preferred":[
        "\uce74\ub9c8\ub17c"
    ],
    "name:msa_x_preferred":[
        "Khamanon"
    ],
    "name:nan_x_preferred":[
        "Khamanon"
    ],
    "name:new_x_preferred":[
        "\u0916\u092e\u093e\u0928\u094b\u0928"
    ],
    "name:nld_x_preferred":[
        "Khamanon"
    ],
    "name:pam_x_preferred":[
        "Khamanon"
    ],
    "name:pan_x_preferred":[
        "\u0a16\u0a2e\u0a3e\u0a23\u0a4b\u0a02"
    ],
    "name:pnb_x_preferred":[
        "\u06a9\u06be\u0645\u0627\u0646\u0648\u06ba"
    ],
    "name:por_x_preferred":[
        "Khamanon"
    ],
    "name:rus_x_preferred":[
        "\u041a\u0445\u0430\u043c\u0430\u043d\u043e\u043d"
    ],
    "name:spa_x_preferred":[
        "Khamanon"
    ],
    "name:swe_x_preferred":[
        "Kham\u0101non"
    ],
    "name:tam_x_preferred":[
        "\u0b95\u0bbe\u0bae\u0ba9\u0bcb\u0ba9\u0bcd"
    ],
    "name:tel_x_preferred":[
        "\u0c16\u0c2e\u0c28\u0c4b\u0c28\u0c4d"
    ],
    "name:unk_x_variant":[
        "Kham\u0101non Kal\u0101n"
    ],
    "name:urd_x_preferred":[
        "\u062e\u0627\u0645\u0627\u0646\u0648\u0646"
    ],
    "name:vie_x_preferred":[
        "Khamanon"
    ],
    "name:zho_x_preferred":[
        "\u5361\u9a6c\u519c"
    ],
    "qs:name":"Khamanon",
    "qs:name_adm0":"India",
    "qs:name_adm1":"Punjab",
    "qs:photos_9r":0,
    "qs:photos_sr":0,
    "qs:placetype":"Town",
    "qs:pop_sr":"5",
    "wd:wordcount":107,
    "wof:name":"Khamanon",
    "wof:placetype":"locality",
    "wof:population":9396
},
  "geometry": {"coordinates":[76.3531,30.81675],"type":"Point"}
}