{
  "type": "Feature",
  "properties": {
    "iso:country":"IN",
    "ks:ks_name":"Gopalpur",
    "ks:ks_pop":519,
    "ks:ks_type":"VILLAGE",
    "name:eng_x_preferred":[
        "Gopalpur"
    ],
    "wof:name":"Gopalpur",
    "wof:placetype":"locality",
    "wof:population":519
},
  "geometry": {"coordinates":[87.67188400000001,23.130147],"type":"Point"}
}