{
  "type": "Feature",
  "properties": {
    "gn:admin1_code":"19.0",
    "gn:admin2_code":"584.0",
    "gn:asciiname":"Harohallidoddi",
    "gn:country_code":"IN",
    "gn:dem":707,
    "gn:feature_class":"P",
    "gn:feature_code":"PPL",
    "gn:name":"Harohallidoddi",
    "gn:population":0,
    "gn:timezone":"Asia/Kolkata",
    "iso:country":"IN",
    "wof:name":"Harohallidoddi",
    "wof:placetype":"locality"
},
  "geometry": {"coordinates":[77.13058000000002,12.72861],"type":"Point"}
}