{
  "type": "Feature",
  "properties": {
    "iso:country":"IN",
    "ks:ks_alt_nam":"kandholpada",
    "ks:ks_name":"Kandholpada",
    "ks:ks_pop":813,
    "ks:ks_type":"HABITATION",
    "name:eng_x_preferred":[
        "Kandholpada"
    ],
    "wof:name":"Kandholpada",
    "wof:placetype":"locality",
    "wof:population":813
},
  "geometry": {"coordinates":[72.830833,19.953091],"type":"Point"}
}