{
  "type": "Feature",
  "properties": {
    "iso:country":"IN",
    "ks:ks_name":"Sohraia",
    "ks:ks_pop":0,
    "ks:ks_type":"VILLAGE",
    "name:eng_x_preferred":[
        "Sohraia"
    ],
    "wof:name":"Sohraia",
    "wof:placetype":"locality",
    "wof:population":0
},
  "geometry": {"coordinates":[86.241568,25.667423],"type":"Point"}
}