{
  "type": "Feature",
  "properties": {
    "iso:country":"IN",
    "ks:ks_name":"Dulduli",
    "ks:ks_pop":2078,
    "ks:ks_type":"HABITATION",
    "name:eng_x_preferred":[
        "Dulduli"
    ],
    "wof:name":"Dulduli",
    "wof:placetype":"locality",
    "wof:population":2078
},
  "geometry": {"coordinates":[86.77808,24.876148],"type":"Point"}
}