{
  "type": "Feature",
  "properties": {
    "iso:country":"IN",
    "ks:ks_name":"Kullaballi",
    "ks:ks_pop":222,
    "ks:ks_type":"HABITATION",
    "name:eng_x_preferred":[
        "Kullaballi"
    ],
    "wof:name":"Kullaballi",
    "wof:placetype":"locality",
    "wof:population":222
},
  "geometry": {"coordinates":[74.835131,13.742314],"type":"Point"}
}