{
  "type": "Feature",
  "properties": {
    "gn:admin1_code":"34.0",
    "gn:admin2_code":"220.0",
    "gn:asciiname":"Mamsai",
    "gn:country_code":"IN",
    "gn:dem":53,
    "gn:feature_class":"P",
    "gn:feature_code":"PPL",
    "gn:name":"Mamsai",
    "gn:population":0,
    "gn:timezone":"Asia/Kolkata",
    "iso:country":"IN",
    "name:eng_x_preferred":[
        "Mamsai"
    ],
    "wof:name":"Mamsai",
    "wof:placetype":"locality"
},
  "geometry": {"coordinates":[85.50839000000001,25.69883],"type":"Point"}
}