{
  "type": "Feature",
  "properties": {
    "iso:country":"IN",
    "ks:ks_name":"Vasalmada",
    "ks:ks_pop":75,
    "ks:ks_type":"HABITATION",
    "name:eng_x_preferred":[
        "Vasalmada"
    ],
    "wof:name":"Vasalmada",
    "wof:placetype":"locality",
    "wof:population":75
},
  "geometry": {"coordinates":[79.333764,19.213458],"type":"Point"}
}