{
  "type": "Feature",
  "properties": {
    "iso:country":"IN",
    "ks:ks_name":"Vathiyarkudiyrippu",
    "ks:ks_pop":134,
    "ks:ks_type":"HABITATION",
    "name:eng_x_preferred":[
        "Vathiyarkudiyrippu"
    ],
    "wof:name":"Vathiyarkudiyrippu",
    "wof:placetype":"locality",
    "wof:population":134
},
  "geometry": {"coordinates":[79.012918,9.323064],"type":"Point"}
}