{
  "type": "Feature",
  "properties": {
    "gn:admin1_code":"24",
    "gn:admin2_code":"119.0",
    "gn:asciiname":"Amarpura",
    "gn:country_code":"IN",
    "gn:dem":410,
    "gn:feature_class":"P",
    "gn:feature_code":"PPL",
    "gn:name":"Amarpura",
    "gn:population":0,
    "gn:timezone":"Asia/Kolkata",
    "iso:country":"IN",
    "wof:name":"Amarpura",
    "wof:placetype":"locality"
},
  "geometry": {"coordinates":[74.67893000000002,26.16648],"type":"Point"}
}