{
  "type": "Feature",
  "properties": {
    "iso:country":"IN",
    "ks:ks_name":"Belahi Urf Beli",
    "ks:ks_pop":547,
    "ks:ks_type":"VILLAGE",
    "ks:ks_uagg_main":0,
    "name:eng_x_preferred":[
        "Belahi Urf Beli"
    ],
    "wof:name":"Belahi Urf Beli",
    "wof:placetype":"neighbourhood",
    "wof:population":547
},
  "geometry": {"coordinates":[85.486358,26.514796],"type":"Point"}
}