{
  "type": "Feature",
  "properties": {
    "iso:country":"IN",
    "ks:ks_name":"Kurdujeta",
    "ks:ks_pop":1622,
    "ks:ks_type":"VILLAGE",
    "name:eng_x_preferred":[
        "Kurdujeta"
    ],
    "wof:name":"Kurdujeta",
    "wof:placetype":"locality",
    "wof:population":1622
},
  "geometry": {"coordinates":[74.842832,22.404349],"type":"Point"}
}