{
  "type": "Feature",
  "properties": {
    "iso:country":"IN",
    "ks:ks_name":"Kheda",
    "ks:ks_pop":621,
    "ks:ks_type":"VILLAGE",
    "name:eng_x_preferred":[
        "Kheda"
    ],
    "name:guj_x_preferred":[
        "\u0a96\u0ac7\u0aa1\u0abe"
    ],
    "name:hin_x_preferred":[
        "\u0916\u0947\u0921\u093c\u093e"
    ],
    "wof:name":"Kheda",
    "wof:placetype":"locality",
    "wof:population":621
},
  "geometry": {"coordinates":[73.204472,23.296167],"type":"Point"}
}