{
  "type": "Feature",
  "properties": {
    "gn:admin1_code":"24",
    "gn:admin2_code":"105.0",
    "gn:asciiname":"Taunga",
    "gn:country_code":"IN",
    "gn:dem":177,
    "gn:feature_class":"P",
    "gn:feature_code":"PPL",
    "gn:name":"Taunga",
    "gn:population":0,
    "gn:timezone":"Asia/Kolkata",
    "iso:country":"IN",
    "name:ceb_x_preferred":[
        "Taunga"
    ],
    "name:ton_x_preferred":[
        "Taunga"
    ],
    "wof:name":"Taunga",
    "wof:placetype":"locality"
},
  "geometry": {"coordinates":[77.49916,27.25229],"type":"Point"}
}