{
  "type": "Feature",
  "properties": {
    "gn:admin1_code":"16",
    "gn:admin2_code":"513.0",
    "gn:asciiname":"Martandwadi",
    "gn:country_code":"IN",
    "gn:dem":429,
    "gn:feature_class":"P",
    "gn:feature_code":"PPL",
    "gn:name":"M\u0101rtandw\u0101di",
    "gn:population":0,
    "gn:timezone":"Asia/Kolkata",
    "iso:country":"IN",
    "wof:name":"Martandwadi",
    "wof:placetype":"locality"
},
  "geometry": {"coordinates":[76.88458,18.86705],"type":"Point"}
}