{
  "type": "Feature",
  "properties": {
    "iso:country":"IN",
    "ks:ks_name":"Kandi Gram",
    "ks:ks_pop":353,
    "ks:ks_type":"HABITATION",
    "name:eng_x_preferred":[
        "Kandi Gram"
    ],
    "wof:name":"Kandi Gram",
    "wof:placetype":"locality",
    "wof:population":353
},
  "geometry": {"coordinates":[91.80641300000001,24.136299],"type":"Point"}
}