{
  "type": "Feature",
  "properties": {
    "iso:country":"IN",
    "ks:ks_name":"Chandramapatapursasan",
    "ks:ks_pop":645,
    "ks:ks_type":"VILLAGE",
    "ks:ks_uagg_main":0,
    "name:eng_x_preferred":[
        "Chandramapatapursasan"
    ],
    "wof:name":"Chandramapatapursasan",
    "wof:placetype":"neighbourhood",
    "wof:population":645
},
  "geometry": {"coordinates":[85.54956900000001,20.028534],"type":"Point"}
}