{
  "type": "Feature",
  "properties": {
    "iso:country":"IN",
    "ks:ks_name":"Baikhunta",
    "ks:ks_pop":265,
    "ks:ks_type":"VILLAGE",
    "name:eng_x_preferred":[
        "Baikhunta"
    ],
    "wof:name":"Baikhunta",
    "wof:placetype":"locality",
    "wof:population":265
},
  "geometry": {"coordinates":[86.90365,21.713032],"type":"Point"}
}