{
  "type": "Feature",
  "properties": {
    "iso:country":"IN",
    "ks:ks_name":"Solaguda",
    "ks:ks_pop":4,
    "ks:ks_type":"HABITATION",
    "name:eng_x_preferred":[
        "Solaguda"
    ],
    "wof:name":"Solaguda",
    "wof:placetype":"locality",
    "wof:population":4
},
  "geometry": {"coordinates":[84.024823,20.087582],"type":"Point"}
}