{
  "type": "Feature",
  "properties": {
    "iso:country":"IN",
    "ks:ks_name":"Abadi Khas",
    "ks:ks_pop":240,
    "ks:ks_type":"HABITATION",
    "name:eng_x_preferred":[
        "Abadi Khas"
    ],
    "wof:name":"Abadi Khas",
    "wof:placetype":"locality",
    "wof:population":240
},
  "geometry": {"coordinates":[82.576599,25.980348],"type":"Point"}
}