{
  "type": "Feature",
  "properties": {
    "iso:country":"IN",
    "ks:ks_name":"Madapura Gollarahatti",
    "ks:ks_pop":380,
    "ks:ks_type":"HABITATION",
    "name:eng_x_preferred":[
        "Madapura Gollarahatti"
    ],
    "wof:name":"Madapura Gollarahatti",
    "wof:placetype":"locality",
    "wof:population":380
},
  "geometry": {"coordinates":[76.50123000000001,13.435915],"type":"Point"}
}