{
  "type": "Feature",
  "properties": {
    "iso:country":"IN",
    "ks:ks_name":"Goradangal",
    "ks:ks_pop":412,
    "ks:ks_type":"VILLAGE",
    "name:eng_x_preferred":[
        "Goradangal"
    ],
    "wof:name":"Goradangal",
    "wof:placetype":"locality",
    "wof:population":412
},
  "geometry": {"coordinates":[87.321477,24.208067],"type":"Point"}
}