{
  "type": "Feature",
  "properties": {
    "gn:admin1_code":"38.0",
    "gn:admin2_code":"351.0",
    "gn:asciiname":"Asanbana",
    "gn:country_code":"IN",
    "gn:dem":110,
    "gn:feature_class":"P",
    "gn:feature_code":"PPL",
    "gn:name":"Asanb\u0101na",
    "gn:population":0,
    "gn:timezone":"Asia/Kolkata",
    "iso:country":"IN",
    "ks:ks_name":"Asanbuna",
    "ks:ks_pop":163,
    "ks:ks_type":"VILLAGE",
    "name:eng_x_preferred":[
        "Asanbuna"
    ],
    "name:eng_x_variant":[
        "Asanbana"
    ],
    "wof:name":"Asanbuna",
    "wof:placetype":"locality",
    "wof:population":163
},
  "geometry": {"coordinates":[87.499627,25.06107],"type":"Point"}
}