{
  "type": "Feature",
  "properties": {
    "iso:country":"IN",
    "ks:ks_name":"Kundal",
    "ks:ks_pop":733,
    "ks:ks_type":"HABITATION",
    "name:eng_x_preferred":[
        "Kundal"
    ],
    "wof:name":"Kundal",
    "wof:placetype":"locality",
    "wof:population":733
},
  "geometry": {"coordinates":[73.246847,24.50688],"type":"Point"}
}