{
  "type": "Feature",
  "properties": {
    "iso:country":"IN",
    "ks:ks_name":"Rajo Tola",
    "ks:ks_pop":298,
    "ks:ks_type":"HABITATION",
    "name:eng_x_preferred":[
        "Rajo Tola"
    ],
    "wof:name":"Rajo Tola",
    "wof:placetype":"locality",
    "wof:population":298
},
  "geometry": {"coordinates":[82.90223,24.000551],"type":"Point"}
}