{
  "type": "Feature",
  "properties": {
    "gn:admin1_code":"39",
    "gn:admin2_code":"61.0",
    "gn:asciiname":"Dhamoli",
    "gn:country_code":"IN",
    "gn:dem":1086,
    "gn:feature_class":"P",
    "gn:feature_code":"PPL",
    "gn:name":"Dhamoli",
    "gn:population":0,
    "gn:timezone":"Asia/Kolkata",
    "iso:country":"IN",
    "wof:name":"Dhamoli",
    "wof:placetype":"locality"
},
  "geometry": {"coordinates":[78.77506,30.00931],"type":"Point"}
}