{
  "type": "Feature",
  "properties": {
    "iso:country":"IN",
    "ks:ks_name":"Tilaia",
    "ks:ks_pop":178,
    "ks:ks_type":"VILLAGE",
    "name:eng_x_preferred":[
        "Tilaia"
    ],
    "wof:name":"Tilaia",
    "wof:placetype":"locality",
    "wof:population":178
},
  "geometry": {"coordinates":[85.87521700000001,24.700437],"type":"Point"}
}