{
  "type": "Feature",
  "properties": {
    "iso:country":"IN",
    "ks:ks_name":"Gogar",
    "ks:ks_pop":553,
    "ks:ks_type":"VILLAGE",
    "ks:ks_uagg_main":0,
    "name:eng_x_preferred":[
        "Gogar"
    ],
    "wof:name":"Gogar",
    "wof:placetype":"neighbourhood",
    "wof:population":553
},
  "geometry": {"coordinates":[87.65819,25.748907],"type":"Point"}
}