{
  "type": "Feature",
  "properties": {
    "iso:country":"IN",
    "ks:ks_name":"Kulharia",
    "ks:ks_pop":0,
    "ks:ks_type":"VILLAGE",
    "name:eng_x_preferred":[
        "Kulharia"
    ],
    "wof:name":"Kulharia",
    "wof:placetype":"locality",
    "wof:population":0
},
  "geometry": {"coordinates":[81.648931,25.124188],"type":"Point"}
}