{
  "type": "Feature",
  "properties": {
    "iso:country":"IN",
    "ks:ks_name":"Chak Sihara",
    "ks:ks_pop":0,
    "ks:ks_type":"VILLAGE",
    "name:eng_x_preferred":[
        "Chak Sihara"
    ],
    "wof:name":"Chak Sihara",
    "wof:placetype":"locality",
    "wof:population":0
},
  "geometry": {"coordinates":[88.02424499999999,24.265187],"type":"Point"}
}