{
  "type": "Feature",
  "properties": {
    "iso:country":"IN",
    "ks:ks_name":"Brajendra Colony",
    "ks:ks_pop":294,
    "ks:ks_type":"HABITATION",
    "name:eng_x_preferred":[
        "Brajendra Colony"
    ],
    "wof:name":"Brajendra Colony",
    "wof:placetype":"locality",
    "wof:population":294
},
  "geometry": {"coordinates":[91.425437,23.342367],"type":"Point"}
}