{
  "type": "Feature",
  "properties": {
    "gn:admin1_code":"11.0",
    "gn:admin2_code":"32.0",
    "gn:asciiname":"Jhimmidhar",
    "gn:country_code":"IN",
    "gn:dem":1854,
    "gn:feature_class":"P",
    "gn:feature_code":"PPL",
    "gn:name":"Jhimmidhar",
    "gn:population":0,
    "gn:timezone":"Asia/Kolkata",
    "iso:country":"IN",
    "wof:name":"Jhimmidhar",
    "wof:placetype":"locality"
},
  "geometry": {"coordinates":[77.3601,30.92673],"type":"Point"}
}