{
  "type": "Feature",
  "properties": {
    "iso:country":"IN",
    "ks:ks_name":"8 PTD-A",
    "ks:ks_pop":64,
    "ks:ks_type":"VILLAGE",
    "name:eng_x_preferred":[
        "8 PTD-A"
    ],
    "wof:name":"8 PTD-A",
    "wof:placetype":"locality",
    "wof:population":64
},
  "geometry": {"coordinates":[73.339585,29.380129],"type":"Point"}
}