{
  "type": "Feature",
  "properties": {
    "gn:admin1_code":"24",
    "gn:admin2_code":"111.0",
    "gn:asciiname":"Mavanda Tarla",
    "gn:country_code":"IN",
    "gn:dem":413,
    "gn:feature_class":"P",
    "gn:feature_code":"PPL",
    "gn:name":"M\u0101vanda Tarla",
    "gn:population":0,
    "gn:timezone":"Asia/Kolkata",
    "iso:country":"IN",
    "name:und_x_variant":[
        "M\u0101vanda Tarla",
        "Maonda Tarla"
    ],
    "wof:name":"Mavanda Tarla",
    "wof:placetype":"neighbourhood"
},
  "geometry": {"coordinates":[75.80807,27.81827],"type":"Point"}
}