{
  "type": "Feature",
  "properties": {
    "iso:country":"IN",
    "ks:ks_name":"Naya Para",
    "ks:ks_pop":819,
    "ks:ks_type":"HABITATION",
    "name:eng_x_preferred":[
        "Naya Para"
    ],
    "wof:name":"Naya Para",
    "wof:placetype":"locality",
    "wof:population":819
},
  "geometry": {"coordinates":[91.407714,23.459233],"type":"Point"}
}