{
  "type": "Feature",
  "properties": {
    "gn:admin1_code":"11",
    "gn:admin2_code":"24.0",
    "gn:asciiname":"Chakol Beru",
    "gn:country_code":"IN",
    "gn:dem":878,
    "gn:feature_class":"P",
    "gn:feature_code":"PPL",
    "gn:name":"Chakol Beru",
    "gn:population":0,
    "gn:timezone":"Asia/Kolkata",
    "iso:country":"IN",
    "wof:name":"Chakol Beru",
    "wof:placetype":"locality"
},
  "geometry": {"coordinates":[76.61959,32.03756],"type":"Point"}
}