{
  "type": "Feature",
  "properties": {
    "iso:country":"IN",
    "ks:ks_alt_nam":"BILIGERE",
    "ks:ks_name":"Biligere",
    "ks:ks_pop":56,
    "ks:ks_type":"HABITATION",
    "name:eng_x_preferred":[
        "Biligere"
    ],
    "wof:name":"Biligere",
    "wof:placetype":"locality",
    "wof:population":56
},
  "geometry": {"coordinates":[75.13354,13.40094],"type":"Point"}
}