{
  "type": "Feature",
  "properties": {
    "gn:admin1_code":"35",
    "gn:admin2_code":"463.0",
    "gn:asciiname":"Jurwar",
    "gn:country_code":"IN",
    "gn:dem":480,
    "gn:feature_class":"P",
    "gn:feature_code":"PPL",
    "gn:name":"Jurw\u0101r",
    "gn:population":0,
    "gn:timezone":"Asia/Kolkata",
    "iso:country":"IN",
    "ks:ks_name":"Judwar",
    "ks:ks_pop":1238,
    "ks:ks_type":"VILLAGE",
    "name:eng_x_preferred":[
        "Judwar"
    ],
    "name:eng_x_variant":[
        "Jurwar"
    ],
    "wof:name":"Judwar",
    "wof:placetype":"locality",
    "wof:population":1238
},
  "geometry": {"coordinates":[82.476139,24.330531],"type":"Point"}
}