{
  "type": "Feature",
  "properties": {
    "gn:admin1_code":"11",
    "gn:admin2_code":"24.0",
    "gn:asciiname":"Behra Banjar",
    "gn:country_code":"IN",
    "gn:dem":772,
    "gn:feature_class":"P",
    "gn:feature_code":"PPL",
    "gn:name":"Behra Banjar",
    "gn:population":0,
    "gn:timezone":"Asia/Kolkata",
    "iso:country":"IN",
    "wof:name":"Behra Banjar",
    "wof:placetype":"locality"
},
  "geometry": {"coordinates":[76.34130999999999,32.08741],"type":"Point"}
}