{
  "type": "Feature",
  "properties": {
    "gn:admin1_code":"38.0",
    "gn:admin2_code":"351.0",
    "gn:asciiname":"Dasu Chakla",
    "gn:country_code":"IN",
    "gn:dem":45,
    "gn:feature_class":"P",
    "gn:feature_code":"PPL",
    "gn:name":"D\u0101su Chakla",
    "gn:population":0,
    "gn:timezone":"Asia/Kolkata",
    "iso:country":"IN",
    "ks:ks_name":"Dasu Chakla",
    "ks:ks_pop":983,
    "ks:ks_type":"VILLAGE",
    "ks:ks_uagg_main":0,
    "name:eng_x_preferred":[
        "Dasu Chakla"
    ],
    "wof:name":"Dasu Chakla",
    "wof:placetype":"neighbourhood",
    "wof:population":983
},
  "geometry": {"coordinates":[87.37134,25.163325],"type":"Point"}
}