{
  "type": "Feature",
  "properties": {
    "iso:country":"IN",
    "ks:ks_name":"Kattadikunnu",
    "ks:ks_pop":537,
    "ks:ks_type":"HABITATION",
    "name:eng_x_preferred":[
        "Kattadikunnu"
    ],
    "wof:name":"Kattadikunnu",
    "wof:placetype":"locality",
    "wof:population":537
},
  "geometry": {"coordinates":[75.93923599999999,11.435809],"type":"Point"}
}