{
  "type": "Feature",
  "properties": {
    "iso:country":"IN",
    "ks:ks_name":"Golibail",
    "ks:ks_pop":24,
    "ks:ks_type":"HABITATION",
    "name:eng_x_preferred":[
        "Golibail"
    ],
    "wof:name":"Golibail",
    "wof:placetype":"locality",
    "wof:population":24
},
  "geometry": {"coordinates":[74.801642,14.476445],"type":"Point"}
}