{
  "type": "Feature",
  "properties": {
    "iso:country":"IN",
    "ks:ks_name":"Semari Deeh",
    "ks:ks_pop":250,
    "ks:ks_type":"HABITATION",
    "name:eng_x_preferred":[
        "Semari Deeh"
    ],
    "wof:name":"Semari Deeh",
    "wof:placetype":"locality",
    "wof:population":250
},
  "geometry": {"coordinates":[82.59710699999999,27.229611],"type":"Point"}
}