{
  "type": "Feature",
  "properties": {
    "gn:admin1_code":"16.0",
    "gn:admin2_code":"508.0",
    "gn:asciiname":"Pendulwahi",
    "gn:country_code":"IN",
    "gn:dem":321,
    "gn:feature_class":"P",
    "gn:feature_code":"PPL",
    "gn:name":"Pendulw\u0101hi",
    "gn:population":0,
    "gn:timezone":"Asia/Kolkata",
    "iso:country":"IN",
    "ks:ks_alt_nam":"Pendulw\u0101hi",
    "ks:ks_name":"Pendulwahi",
    "ks:ks_pop":204,
    "ks:ks_type":"VILLAGE",
    "name:eng_x_preferred":[
        "Pendulwahi"
    ],
    "name:eng_x_variant":[
        "Pendulw\u0101hi"
    ],
    "wof:name":"Pendulwahi",
    "wof:placetype":"locality",
    "wof:population":204
},
  "geometry": {"coordinates":[80.393187,19.928364],"type":"Point"}
}