{
  "type": "Feature",
  "properties": {
    "iso:country":"IN",
    "ks:ks_name":"Bavalikadu",
    "ks:ks_pop":280,
    "ks:ks_type":"HABITATION",
    "name:eng_x_preferred":[
        "Bavalikadu"
    ],
    "wof:name":"Bavalikadu",
    "wof:placetype":"locality",
    "wof:population":280
},
  "geometry": {"coordinates":[75.382403,12.919188],"type":"Point"}
}