{
  "type": "Feature",
  "properties": {
    "iso:country":"IN",
    "ks:ks_name":"Pujari Para",
    "ks:ks_pop":428,
    "ks:ks_type":"HABITATION",
    "name:eng_x_preferred":[
        "Pujari Para"
    ],
    "wof:name":"Pujari Para",
    "wof:placetype":"locality",
    "wof:population":428
},
  "geometry": {"coordinates":[81.629009,19.532841],"type":"Point"}
}