{
  "type": "Feature",
  "properties": {
    "iso:country":"IN",
    "ks:ks_name":"Mathasahi",
    "ks:ks_pop":292,
    "ks:ks_type":"HABITATION",
    "name:eng_x_preferred":[
        "Mathasahi"
    ],
    "wof:name":"Mathasahi",
    "wof:placetype":"locality",
    "wof:population":292
},
  "geometry": {"coordinates":[86.20755200000001,21.277487],"type":"Point"}
}