{
  "type": "Feature",
  "properties": {
    "iso:country":"IN",
    "ks:ks_name":"Hajraberya",
    "ks:ks_pop":823,
    "ks:ks_type":"VILLAGE",
    "name:eng_x_preferred":[
        "Hajraberya"
    ],
    "wof:name":"Hajraberya",
    "wof:placetype":"locality",
    "wof:population":823
},
  "geometry": {"coordinates":[87.76582399999999,22.613861],"type":"Point"}
}