{
  "type": "Feature",
  "properties": {
    "iso:country":"IN",
    "ks:ks_name":"Devpara",
    "ks:ks_pop":530,
    "ks:ks_type":"HABITATION",
    "ks:ks_uagg_main":0,
    "name:eng_x_preferred":[
        "Devpara"
    ],
    "wof:name":"Devpara",
    "wof:placetype":"neighbourhood",
    "wof:population":530
},
  "geometry": {"coordinates":[70.398639,22.463389],"type":"Point"}
}