{
  "type": "Feature",
  "properties": {
    "iso:country":"IN",
    "ks:ks_name":"Nanda Kapasia",
    "ks:ks_pop":32,
    "ks:ks_type":"VILLAGE",
    "name:eng_x_preferred":[
        "Nanda Kapasia"
    ],
    "wof:name":"Nanda Kapasia",
    "wof:placetype":"locality",
    "wof:population":32
},
  "geometry": {"coordinates":[87.306376,21.915988],"type":"Point"}
}