{
  "type": "Feature",
  "properties": {
    "gn:admin1_code":"19.0",
    "gn:admin2_code":"584.0",
    "gn:asciiname":"Honnopur",
    "gn:country_code":"IN",
    "gn:dem":833,
    "gn:feature_class":"P",
    "gn:feature_code":"PPL",
    "gn:name":"Honnopur",
    "gn:population":0,
    "gn:timezone":"Asia/Kolkata",
    "iso:country":"IN",
    "wof:name":"Honnopur",
    "wof:placetype":"locality"
},
  "geometry": {"coordinates":[77.12768,13.14338],"type":"Point"}
}