{
  "type": "Feature",
  "properties": {
    "iso:country":"IN",
    "ks:ks_name":"Singarikhadika",
    "ks:ks_pop":258,
    "ks:ks_type":"VILLAGE",
    "name:eng_x_preferred":[
        "Singarikhadika"
    ],
    "wof:name":"Singarikhadika",
    "wof:placetype":"locality",
    "wof:population":258
},
  "geometry": {"coordinates":[82.957189,19.415562],"type":"Point"}
}