{
  "type": "Feature",
  "properties": {
    "gn:admin1_code":"37.0",
    "gn:admin2_code":"403.0",
    "gn:asciiname":"Pali",
    "gn:country_code":"IN",
    "gn:dem":258,
    "gn:feature_class":"P",
    "gn:feature_code":"PPL",
    "gn:name":"Pali",
    "gn:population":0,
    "gn:timezone":"Asia/Kolkata",
    "iso:country":"IN",
    "wof:name":"Pali",
    "wof:placetype":"locality"
},
  "geometry": {"coordinates":[83.37626999999998,21.98268],"type":"Point"}
}