{
  "type": "Feature",
  "properties": {
    "iso:country":"IN",
    "ks:ks_name":"Badagudde",
    "ks:ks_pop":168,
    "ks:ks_type":"HABITATION",
    "name:eng_x_preferred":[
        "Badagudde"
    ],
    "wof:name":"Badagudde",
    "wof:placetype":"locality",
    "wof:population":168
},
  "geometry": {"coordinates":[74.861824,13.529981],"type":"Point"}
}