{
  "type": "Feature",
  "properties": {
    "gn:admin1_code":"19",
    "gn:admin2_code":"563.0",
    "gn:asciiname":"Titvali",
    "gn:country_code":"IN",
    "gn:dem":546,
    "gn:feature_class":"P",
    "gn:feature_code":"PPL",
    "gn:name":"Titv\u0101li",
    "gn:population":0,
    "gn:timezone":"Asia/Kolkata",
    "iso:country":"IN",
    "ks:ks_alt_nam":"Titv\u0101li",
    "ks:ks_name":"Titvali",
    "ks:ks_type":"VILLAGE",
    "name:eng_x_preferred":[
        "Titvali"
    ],
    "name:eng_x_variant":[
        "Titv\u0101li"
    ],
    "wof:name":"Titvali",
    "wof:placetype":"locality"
},
  "geometry": {"coordinates":[74.415828,15.32768],"type":"Point"}
}