{
  "type": "Feature",
  "properties": {
    "iso:country":"IN",
    "ks:ks_name":"Hijli",
    "ks:ks_pop":280,
    "ks:ks_type":"VILLAGE",
    "name:eng_x_preferred":[
        "Hijli"
    ],
    "wof:name":"Hijli",
    "wof:placetype":"locality",
    "wof:population":280
},
  "geometry": {"coordinates":[87.47751100000001,22.483201],"type":"Point"}
}