{
  "type": "Feature",
  "properties": {
    "gn:admin1_code":"35.0",
    "gn:admin2_code":"455.0",
    "gn:asciiname":"Rendai",
    "gn:country_code":"IN",
    "gn:dem":760,
    "gn:feature_class":"P",
    "gn:feature_code":"PPL",
    "gn:name":"Rendai",
    "gn:population":0,
    "gn:timezone":"Asia/Kolkata",
    "iso:country":"IN",
    "wof:name":"Rendai",
    "wof:placetype":"locality"
},
  "geometry": {"coordinates":[78.51625,22.08082000000001],"type":"Point"}
}