{
  "type": "Feature",
  "properties": {
    "iso:country":"IN",
    "ks:ks_name":"Mamariguda",
    "ks:ks_pop":348,
    "ks:ks_type":"VILLAGE",
    "ks:ks_uagg_main":0,
    "name:eng_x_preferred":[
        "Mamariguda"
    ],
    "wof:name":"Mamariguda",
    "wof:placetype":"neighbourhood",
    "wof:population":348
},
  "geometry": {"coordinates":[80.380959,18.861563],"type":"Point"}
}