{
  "type": "Feature",
  "properties": {
    "gn:country":"IN",
    "gn:fcode":"PPL",
    "gn:population":10000,
    "iso:country":"IN",
    "qs:name":"Makhajan",
    "qs:name_adm0":"India",
    "qs:name_adm1":"Maharashtra",
    "qs:photos_9r":0,
    "qs:photos_sr":0,
    "qs:placetype":"Town",
    "qs:pop_sr":"5",
    "wof:name":"Makhajan",
    "wof:placetype":"locality",
    "wof:population":10000
},
  "geometry": {"coordinates":[73.50031,17.2698],"type":"Point"}
}