{
  "type": "Feature",
  "properties": {
    "iso:country":"IN",
    "ks:ks_name":"Ayyanapalya",
    "ks:ks_pop":249,
    "ks:ks_type":"HABITATION",
    "name:eng_x_preferred":[
        "Ayyanapalya"
    ],
    "wof:name":"Ayyanapalya",
    "wof:placetype":"locality",
    "wof:population":249
},
  "geometry": {"coordinates":[76.667798,13.322616],"type":"Point"}
}