{
  "type": "Feature",
  "properties": {
    "iso:country":"IN",
    "ks:ks_name":"Nichekulhi",
    "ks:ks_pop":37,
    "ks:ks_type":"HABITATION",
    "name:eng_x_preferred":[
        "Nichekulhi"
    ],
    "wof:name":"Nichekulhi",
    "wof:placetype":"locality",
    "wof:population":37
},
  "geometry": {"coordinates":[86.217034,23.952215],"type":"Point"}
}