{
  "type": "Feature",
  "properties": {
    "iso:country":"IN",
    "ks:ks_name":"Palligadde",
    "ks:ks_pop":10,
    "ks:ks_type":"HABITATION",
    "name:eng_x_preferred":[
        "Palligadde"
    ],
    "wof:name":"Palligadde",
    "wof:placetype":"locality",
    "wof:population":10
},
  "geometry": {"coordinates":[75.59860999999999,12.709016],"type":"Point"}
}