{
  "type": "Feature",
  "properties": {
    "gn:admin1_code":"36.0",
    "gn:admin2_code":"150.0",
    "gn:asciiname":"Shahbazpur",
    "gn:country_code":"IN",
    "gn:dem":180,
    "gn:feature_class":"P",
    "gn:feature_code":"PPL",
    "gn:name":"Sh\u0101hb\u0101zpur",
    "gn:population":0,
    "gn:timezone":"Asia/Kolkata",
    "iso:country":"IN",
    "ks:ks_alt_nam":"Sh\u0101hb\u0101zpur",
    "ks:ks_name":"Shahbazpur",
    "ks:ks_type":"VILLAGE",
    "ks:ks_uagg_main":0,
    "name:eng_x_preferred":[
        "Shahbazpur"
    ],
    "name:eng_x_variant":[
        "Sh\u0101hb\u0101zpur"
    ],
    "wof:name":"Shahbazpur",
    "wof:placetype":"neighbourhood"
},
  "geometry": {"coordinates":[79.086946,28.420071],"type":"Point"}
}