{
  "type": "Feature",
  "properties": {
    "iso:country":"IN",
    "ks:ks_name":"Samsikhra",
    "ks:ks_pop":4191,
    "ks:ks_type":"VILLAGE",
    "ks:ks_uagg_main":0,
    "name:eng_x_preferred":[
        "Samsikhra"
    ],
    "wof:name":"Samsikhra",
    "wof:placetype":"neighbourhood",
    "wof:population":4191
},
  "geometry": {"coordinates":[86.34471000000001,23.745231],"type":"Point"}
}