{
  "type": "Feature",
  "properties": {
    "iso:country":"IN",
    "ks:ks_name":"Mukhya Tola",
    "ks:ks_pop":1198,
    "ks:ks_type":"HABITATION",
    "name:eng_x_preferred":[
        "Mukhya Tola"
    ],
    "wof:name":"Mukhya Tola",
    "wof:placetype":"locality",
    "wof:population":1198
},
  "geometry": {"coordinates":[85.74028300000001,25.684934],"type":"Point"}
}