{
  "type": "Feature",
  "properties": {
    "iso:country":"IN",
    "ks:ks_name":"Pidimpalem",
    "ks:ks_pop":115,
    "ks:ks_type":"HABITATION",
    "name:eng_x_preferred":[
        "Pidimpalem"
    ],
    "wof:name":"Pidimpalem",
    "wof:placetype":"locality",
    "wof:population":115
},
  "geometry": {"coordinates":[82.658241,17.813547],"type":"Point"}
}