{
  "type": "Feature",
  "properties": {
    "iso:country":"IN",
    "ks:ks_name":"Baghnipadar",
    "ks:ks_pop":47,
    "ks:ks_type":"VILLAGE",
    "name:eng_x_preferred":[
        "Baghnipadar"
    ],
    "wof:name":"Baghnipadar",
    "wof:placetype":"locality",
    "wof:population":47
},
  "geometry": {"coordinates":[83.401999,19.930073],"type":"Point"}
}