{
  "type": "Feature",
  "properties": {
    "gn:admin1_code":"16.0",
    "gn:admin2_code":"511.0",
    "gn:asciiname":"Talni",
    "gn:country_code":"IN",
    "gn:dem":426,
    "gn:feature_class":"P",
    "gn:feature_code":"PPL",
    "gn:name":"Talni",
    "gn:population":0,
    "gn:timezone":"Asia/Kolkata",
    "iso:country":"IN",
    "wof:name":"Talni",
    "wof:placetype":"locality"
},
  "geometry": {"coordinates":[77.53211999999998,19.64063],"type":"Point"}
}