{
  "type": "Feature",
  "properties": {
    "iso:country":"IN",
    "ks:ks_name":"Kayee Mari",
    "ks:ks_pop":1971,
    "ks:ks_type":"VILLAGE",
    "name:eng_x_preferred":[
        "Kayee Mari"
    ],
    "wof:name":"Kayee Mari",
    "wof:placetype":"locality",
    "wof:population":1971
},
  "geometry": {"coordinates":[92.66994200000001,26.426831],"type":"Point"}
}