{
  "type": "Feature",
  "properties": {
    "iso:country":"IN",
    "ks:ks_name":"Aamajhola",
    "ks:ks_pop":290,
    "ks:ks_type":"VILLAGE",
    "name:eng_x_preferred":[
        "Aamajhola"
    ],
    "wof:name":"Aamajhola",
    "wof:placetype":"locality",
    "wof:population":290
},
  "geometry": {"coordinates":[81.47257500000001,20.200367],"type":"Point"}
}