{
  "type": "Feature",
  "properties": {
    "iso:country":"IN",
    "ks:ks_name":"Pahridih",
    "ks:ks_pop":200,
    "ks:ks_type":"VILLAGE",
    "name:eng_x_preferred":[
        "Pahridih"
    ],
    "wof:name":"Pahridih",
    "wof:placetype":"locality",
    "wof:population":200
},
  "geometry": {"coordinates":[86.969131,24.464938],"type":"Point"}
}