{
  "type": "Feature",
  "properties": {
    "iso:country":"IN",
    "ks:ks_name":"Hunsageri",
    "ks:ks_pop":30,
    "ks:ks_type":"HABITATION",
    "name:eng_x_preferred":[
        "Hunsageri"
    ],
    "wof:name":"Hunsageri",
    "wof:placetype":"locality",
    "wof:population":30
},
  "geometry": {"coordinates":[74.80836600000001,15.112146],"type":"Point"}
}