{
  "type": "Feature",
  "properties": {
    "gn:admin1_code":"24",
    "gn:admin2_code":"106.0",
    "gn:asciiname":"Makra",
    "gn:country_code":"IN",
    "gn:dem":184,
    "gn:feature_class":"P",
    "gn:feature_code":"PPL",
    "gn:name":"M\u0101kra",
    "gn:population":0,
    "gn:timezone":"Asia/Kolkata",
    "iso:country":"IN",
    "name:ceb_x_preferred":[
        "Makra"
    ],
    "name:deu_x_preferred":[
        "Makra"
    ],
    "name:fra_x_preferred":[
        "Makra"
    ],
    "name:swe_x_preferred":[
        "Makra"
    ],
    "wof:name":"Makra",
    "wof:placetype":"locality"
},
  "geometry": {"coordinates":[77.71443000000002,26.82261],"type":"Point"}
}