{
  "type": "Feature",
  "properties": {
    "gn:admin1_code":"35",
    "gn:admin2_code":"451.0",
    "gn:asciiname":"Dojia",
    "gn:country_code":"IN",
    "gn:dem":374,
    "gn:feature_class":"P",
    "gn:feature_code":"PPL",
    "gn:name":"Dojia",
    "gn:population":0,
    "gn:timezone":"Asia/Kolkata",
    "iso:country":"IN",
    "ks:ks_name":"Dojiya",
    "ks:ks_pop":237,
    "ks:ks_type":"VILLAGE",
    "name:eng_x_preferred":[
        "Dojiya"
    ],
    "name:eng_x_variant":[
        "Dojia"
    ],
    "wof:name":"Dojiya",
    "wof:placetype":"locality",
    "wof:population":237
},
  "geometry": {"coordinates":[79.946037,23.384376],"type":"Point"}
}