{
  "type": "Feature",
  "properties": {
    "iso:country":"IN",
    "ks:ks_name":"Kopadka",
    "ks:ks_pop":14,
    "ks:ks_type":"HABITATION",
    "name:eng_x_preferred":[
        "Kopadka"
    ],
    "wof:name":"Kopadka",
    "wof:placetype":"locality",
    "wof:population":14
},
  "geometry": {"coordinates":[75.61480400000001,12.613572],"type":"Point"}
}