{
  "type": "Feature",
  "properties": {
    "iso:country":"IN",
    "ks:ks_name":"Runakura",
    "ks:ks_pop":400,
    "ks:ks_type":"HABITATION",
    "name:eng_x_preferred":[
        "Runakura"
    ],
    "wof:name":"Runakura",
    "wof:placetype":"locality",
    "wof:population":400
},
  "geometry": {"coordinates":[86.99559000000001,23.849993],"type":"Point"}
}