{
  "type": "Feature",
  "properties": {
    "gn:admin1_code":"39.0",
    "gn:admin2_code":"66.0",
    "gn:asciiname":"Raheli",
    "gn:country_code":"IN",
    "gn:dem":1273,
    "gn:feature_class":"P",
    "gn:feature_code":"PPL",
    "gn:name":"Raheli",
    "gn:population":0,
    "gn:timezone":"Asia/Kolkata",
    "iso:country":"IN",
    "ks:ks_name":"Raheli",
    "ks:ks_pop":64,
    "ks:ks_type":"VILLAGE",
    "name:eng_x_preferred":[
        "Raheli"
    ],
    "wof:name":"Raheli",
    "wof:placetype":"locality",
    "wof:population":64
},
  "geometry": {"coordinates":[79.438974,29.529401],"type":"Point"}
}