{
  "type": "Feature",
  "properties": {
    "iso:country":"IN",
    "ks:ks_name":"Siruvatti",
    "ks:ks_pop":2066,
    "ks:ks_type":"VILLAGE",
    "name:eng_x_preferred":[
        "Siruvatti"
    ],
    "wof:name":"Siruvatti",
    "wof:placetype":"locality",
    "wof:population":2066
},
  "geometry": {"coordinates":[78.79978,9.863537],"type":"Point"}
}