{
  "type": "Feature",
  "properties": {
    "iso:country":"IN",
    "ks:ks_alt_nam":"Nimihat\u0101",
    "ks:ks_name":"Nimihata",
    "ks:ks_type":"VILLAGE",
    "name:eng_x_preferred":[
        "Nimihata"
    ],
    "name:eng_x_variant":[
        "Nimihat\u0101"
    ],
    "wof:name":"Nimihata",
    "wof:placetype":"locality"
},
  "geometry": {"coordinates":[85.167029,21.250907],"type":"Point"}
}