{
  "type": "Feature",
  "properties": {
    "iso:country":"IN",
    "ks:ks_alt_nam":"HASANPUR.",
    "ks:ks_name":"Hasanpur.",
    "ks:ks_pop":160,
    "ks:ks_type":"HABITATION",
    "ks:ks_uagg_main":0,
    "name:eng_x_preferred":[
        "Hasanpur."
    ],
    "wof:name":"Hasanpur.",
    "wof:placetype":"neighbourhood",
    "wof:population":160
},
  "geometry": {"coordinates":[84.664379,24.673228],"type":"Point"}
}