{
  "type": "Feature",
  "properties": {
    "iso:country":"IN",
    "ks:ks_name":"Kavumpady",
    "ks:ks_pop":2568,
    "ks:ks_type":"HABITATION",
    "name:eng_x_preferred":[
        "Kavumpady"
    ],
    "wof:name":"Kavumpady",
    "wof:placetype":"locality",
    "wof:population":2568
},
  "geometry": {"coordinates":[76.646452,10.00172],"type":"Point"}
}