{
  "type": "Feature",
  "properties": {
    "iso:country":"IN",
    "ks:ks_name":"Belkarpada",
    "ks:ks_pop":191,
    "ks:ks_type":"HABITATION",
    "name:eng_x_preferred":[
        "Belkarpada"
    ],
    "wof:name":"Belkarpada",
    "wof:placetype":"locality",
    "wof:population":191
},
  "geometry": {"coordinates":[73.002855,19.940811],"type":"Point"}
}