{
  "type": "Feature",
  "properties": {
    "gn:admin1_code":"36",
    "gn:admin2_code":"188.0",
    "gn:asciiname":"Raghuadih Buzurg",
    "gn:country_code":"IN",
    "gn:dem":83,
    "gn:feature_class":"P",
    "gn:feature_code":"PPL",
    "gn:name":"Raghu\u0101d\u012bh Buzurg",
    "gn:population":0,
    "gn:timezone":"Asia/Kolkata",
    "iso:country":"IN",
    "wof:name":"Raghuadih Buzurg",
    "wof:placetype":"locality"
},
  "geometry": {"coordinates":[83.30594000000001,26.57021],"type":"Point"}
}