{
  "type": "Feature",
  "properties": {
    "gn:admin1_code":"36",
    "gn:admin2_code":"177.0",
    "gn:asciiname":"Jahanpur",
    "gn:country_code":"IN",
    "gn:dem":110,
    "gn:feature_class":"P",
    "gn:feature_code":"PPL",
    "gn:name":"Jah\u0101npur",
    "gn:population":0,
    "gn:timezone":"Asia/Kolkata",
    "iso:country":"IN",
    "ks:ks_alt_nam":"Jah\u0101npur",
    "ks:ks_name":"Jahanpur",
    "ks:ks_pop":307,
    "ks:ks_type":"VILLAGE",
    "ks:ks_uagg_main":0,
    "name:eng_x_preferred":[
        "Jahanpur"
    ],
    "name:eng_x_variant":[
        "Jah\u0101npur"
    ],
    "wof:name":"Jahanpur",
    "wof:placetype":"neighbourhood",
    "wof:population":307
},
  "geometry": {"coordinates":[81.744147,26.769679],"type":"Point"}
}