{
  "type": "Feature",
  "properties": {
    "iso:country":"IN",
    "ks:ks_name":"Mattara",
    "ks:ks_pop":2012,
    "ks:ks_type":"HABITATION",
    "name:eng_x_preferred":[
        "Mattara"
    ],
    "wof:name":"Mattara",
    "wof:placetype":"locality",
    "wof:population":2012
},
  "geometry": {"coordinates":[75.669282,12.092704],"type":"Point"}
}