{
  "type": "Feature",
  "properties": {
    "iso:country":"IN",
    "ks:ks_name":"Hingalpada",
    "ks:ks_pop":350,
    "ks:ks_type":"HABITATION",
    "name:eng_x_preferred":[
        "Hingalpada"
    ],
    "wof:name":"Hingalpada",
    "wof:placetype":"locality",
    "wof:population":350
},
  "geometry": {"coordinates":[73.39137100000001,20.538494],"type":"Point"}
}