{
  "type": "Feature",
  "properties": {
    "iso:country":"IN",
    "ks:ks_name":"Belhaliya Tola",
    "ks:ks_pop":423,
    "ks:ks_type":"HABITATION",
    "ks:ks_uagg_main":0,
    "name:eng_x_preferred":[
        "Belhaliya Tola"
    ],
    "wof:name":"Belhaliya Tola",
    "wof:placetype":"neighbourhood",
    "wof:population":423
},
  "geometry": {"coordinates":[83.621495,27.054289],"type":"Point"}
}