{
  "type": "Feature",
  "properties": {
    "iso:country":"IN",
    "ks:ks_name":"Mahupura",
    "ks:ks_pop":51,
    "ks:ks_type":"HABITATION",
    "name:eng_x_preferred":[
        "Mahupura"
    ],
    "wof:name":"Mahupura",
    "wof:placetype":"locality",
    "wof:population":51
},
  "geometry": {"coordinates":[74.868385,24.805265],"type":"Point"}
}