{
  "type": "Feature",
  "properties": {
    "iso:country":"IN",
    "ks:ks_name":"P Thakur",
    "ks:ks_pop":197,
    "ks:ks_type":"HABITATION",
    "name:eng_x_preferred":[
        "P Thakur"
    ],
    "wof:name":"P Thakur",
    "wof:placetype":"locality",
    "wof:population":197
},
  "geometry": {"coordinates":[81.30010900000001,25.931297],"type":"Point"}
}