{
  "type": "Feature",
  "properties": {
    "iso:country":"IN",
    "ks:ks_name":"Nav Toli",
    "ks:ks_pop":300,
    "ks:ks_type":"HABITATION",
    "name:eng_x_preferred":[
        "Nav Toli"
    ],
    "wof:name":"Nav Toli",
    "wof:placetype":"locality",
    "wof:population":300
},
  "geometry": {"coordinates":[86.542075,25.728998],"type":"Point"}
}