{
  "type": "Feature",
  "properties": {
    "iso:country":"IN",
    "ks:ks_name":"Ushamrai Para",
    "ks:ks_pop":105,
    "ks:ks_type":"HABITATION",
    "name:eng_x_preferred":[
        "Ushamrai Para"
    ],
    "wof:name":"Ushamrai Para",
    "wof:placetype":"locality",
    "wof:population":105
},
  "geometry": {"coordinates":[91.68550500000001,23.30804],"type":"Point"}
}