{
  "type": "Feature",
  "properties": {
    "gn:admin1_code":"2.0",
    "gn:admin2_code":"549.0",
    "gn:asciiname":"Chintalapalem",
    "gn:country_code":"IN",
    "gn:dem":104,
    "gn:feature_class":"P",
    "gn:feature_code":"PPL",
    "gn:name":"Chintalap\u0101lem",
    "gn:population":0,
    "gn:timezone":"Asia/Kolkata",
    "iso:country":"IN",
    "name:tel_x_preferred":[
        "\u0c1a\u0c3f\u0c02\u0c24\u0c32\u0c2a\u0c3e\u0c32\u0c46\u0c02"
    ],
    "wof:name":"Chintalapalem",
    "wof:placetype":"neighbourhood"
},
  "geometry": {"coordinates":[79.52352,15.39385],"type":"Point"}
}