{
  "type": "Feature",
  "properties": {
    "gn:admin1_code":"20.0",
    "gn:admin2_code":"271.0",
    "gn:asciiname":"Phuitomi",
    "gn:country_code":"IN",
    "gn:dem":1057,
    "gn:feature_class":"P",
    "gn:feature_code":"PPL",
    "gn:name":"Phuitomi",
    "gn:population":0,
    "gn:timezone":"Asia/Kolkata",
    "iso:country":"IN",
    "wof:name":"Phuitomi",
    "wof:placetype":"locality"
},
  "geometry": {"coordinates":[93.76466000000001,25.47324],"type":"Point"}
}