{
  "type": "Feature",
  "properties": {
    "gn:admin1_code":"36.0",
    "gn:admin2_code":"183.0",
    "gn:asciiname":"Mahabali",
    "gn:country_code":"IN",
    "gn:dem":107,
    "gn:feature_class":"P",
    "gn:feature_code":"PPL",
    "gn:name":"Mah\u0101bali",
    "gn:population":0,
    "gn:timezone":"Asia/Kolkata",
    "iso:country":"IN",
    "name:deu_x_preferred":[
        "Bali"
    ],
    "name:fra_x_preferred":[
        "Bali"
    ],
    "name:hin_x_preferred":[
        "\u0930\u093e\u091c\u093e \u092c\u0932\u093f"
    ],
    "name:ind_x_preferred":[
        "Mahabali"
    ],
    "name:jpn_x_preferred":[
        "\u30de\u30cf\u30fc\u30d0\u30ea"
    ],
    "name:kan_x_preferred":[
        "\u0cac\u0cb2\u0cbf"
    ],
    "name:lit_x_preferred":[
        "Mahabalis"
    ],
    "name:mal_x_preferred":[
        "\u0d2e\u0d39\u0d3e\u0d2c\u0d32\u0d3f"
    ],
    "name:mar_x_preferred":[
        "\u092c\u0933\u0940"
    ],
    "name:nep_x_preferred":[
        "\u092c\u0932\u093f \u0930\u093e\u091c\u093e"
    ],
    "name:nld_x_preferred":[
        "Bali"
    ],
    "name:ori_x_preferred":[
        "\u0b2c\u0b33\u0b3f"
    ],
    "name:por_x_preferred":[
        "Mahabali"
    ],
    "name:rus_x_preferred":[
        "\u0411\u0430\u043b\u0438"
    ],
    "name:san_x_preferred":[
        "\u092c\u0932\u093f\u091a\u0915\u094d\u0930\u0935\u0930\u094d\u0924\u0940"
    ],
    "name:slk_x_preferred":[
        "Mah\u00e1bal\u00ed"
    ],
    "name:spa_x_preferred":[
        "Bali"
    ],
    "name:tam_x_preferred":[
        "\u0bae\u0b95\u0bbe\u0baa\u0bb2\u0bbf \u0b9a\u0b95\u0bcd\u0b95\u0bb0\u0bb5\u0bb0\u0bcd\u0ba4\u0bcd\u0ba4\u0bbf"
    ],
    "name:tat_x_preferred":[
        "\u0411\u0430\u043b\u0438 \u041c\u0430\u0445\u0430\u0440\u0430\u0434\u0436"
    ],
    "name:tel_x_preferred":[
        "\u0c2c\u0c32\u0c3f \u0c1a\u0c15\u0c4d\u0c30\u0c35\u0c30\u0c4d\u0c24\u0c3f"
    ],
    "wof:name":"Mahabali",
    "wof:placetype":"neighbourhood"
},
  "geometry": {"coordinates":[81.74105,27.01181],"type":"Point"}
}