{
  "type": "Feature",
  "properties": {
    "iso:country":"IN",
    "ks:ks_name":"Muraina Ram Datta",
    "ks:ks_pop":1821,
    "ks:ks_type":"VILLAGE",
    "name:eng_x_preferred":[
        "Muraina Ram Datta"
    ],
    "wof:name":"Muraina Ram Datta",
    "wof:placetype":"locality",
    "wof:population":1821
},
  "geometry": {"coordinates":[79.389884,26.61097],"type":"Point"}
}