{
  "type": "Feature",
  "properties": {
    "iso:country":"IN",
    "ks:ks_name":"17 PTD",
    "ks:ks_pop":136,
    "ks:ks_type":"VILLAGE",
    "name:eng_x_preferred":[
        "17 PTD"
    ],
    "wof:name":"17 PTD",
    "wof:placetype":"locality",
    "wof:population":136
},
  "geometry": {"coordinates":[73.265383,29.406547],"type":"Point"}
}