{
  "type": "Feature",
  "properties": {
    "iso:country":"IN",
    "ks:ks_name":"Kalapana",
    "ks:ks_pop":160,
    "ks:ks_type":"HABITATION",
    "name:eng_x_preferred":[
        "Kalapana"
    ],
    "wof:name":"Kalapana",
    "wof:placetype":"locality",
    "wof:population":160
},
  "geometry": {"coordinates":[73.24119399999999,23.645806],"type":"Point"}
}