{
  "type": "Feature",
  "properties": {
    "iso:country":"IN",
    "ks:ks_name":"Kithalangi",
    "ks:ks_pop":1156,
    "ks:ks_type":"HABITATION",
    "name:eng_x_preferred":[
        "Kithalangi"
    ],
    "wof:name":"Kithalangi",
    "wof:placetype":"locality",
    "wof:population":1156
},
  "geometry": {"coordinates":[82.826176,18.25222],"type":"Point"}
}