{
  "type": "Feature",
  "properties": {
    "iso:country":"IN",
    "ks:ks_name":"Navi Rati Devadi",
    "ks:ks_pop":896,
    "ks:ks_type":"HABITATION",
    "name:eng_x_preferred":[
        "Navi Rati Devadi"
    ],
    "wof:name":"Navi Rati Devadi",
    "wof:placetype":"locality",
    "wof:population":896
},
  "geometry": {"coordinates":[70.920917,22.629611],"type":"Point"}
}