{
  "type": "Feature",
  "properties": {
    "gn:admin1_code":"24.0",
    "gn:admin2_code":"102",
    "gn:asciiname":"Bungi",
    "gn:country_code":"IN",
    "gn:dem":230,
    "gn:feature_class":"P",
    "gn:feature_code":"PPL",
    "gn:name":"Bungi",
    "gn:population":0,
    "gn:timezone":"Asia/Kolkata",
    "iso:country":"IN",
    "wof:name":"Bungi",
    "wof:placetype":"locality"
},
  "geometry": {"coordinates":[75.27181,28.72787000000001],"type":"Point"}
}