{
  "type": "Feature",
  "properties": {
    "gn:admin1_code":"11",
    "gn:admin2_code":"33.0",
    "gn:asciiname":"Bazari",
    "gn:country_code":"IN",
    "gn:dem":2282,
    "gn:feature_class":"P",
    "gn:feature_code":"PPL",
    "gn:name":"Baz\u0101ri",
    "gn:population":0,
    "gn:timezone":"Asia/Kolkata",
    "iso:country":"IN",
    "wof:name":"Bazari",
    "wof:placetype":"locality"
},
  "geometry": {"coordinates":[77.56533,30.88499],"type":"Point"}
}