{
  "type": "Feature",
  "properties": {
    "gn:admin1_code":"36",
    "gn:admin2_code":"176.0",
    "gn:asciiname":"Sarthara",
    "gn:country_code":"IN",
    "gn:dem":122,
    "gn:feature_class":"P",
    "gn:feature_code":"PPL",
    "gn:name":"Sarthara",
    "gn:population":0,
    "gn:timezone":"Asia/Kolkata",
    "iso:country":"IN",
    "ks:ks_name":"Sarthara",
    "ks:ks_pop":1175,
    "ks:ks_type":"VILLAGE",
    "ks:ks_uagg_main":0,
    "name:eng_x_preferred":[
        "Sarthara"
    ],
    "wof:name":"Sarthara",
    "wof:placetype":"neighbourhood",
    "wof:population":1175
},
  "geometry": {"coordinates":[81.118746,26.901999],"type":"Point"}
}