{
  "type": "Feature",
  "properties": {
    "gn:admin1_code":"28.0",
    "gn:admin2_code":"332.0",
    "gn:asciiname":"Saira",
    "gn:country_code":"IN",
    "gn:dem":34,
    "gn:feature_class":"P",
    "gn:feature_code":"PPL",
    "gn:name":"Saira",
    "gn:population":0,
    "gn:timezone":"Asia/Kolkata",
    "iso:country":"IN",
    "name:deu_x_preferred":[
        "Saira"
    ],
    "name:nds_x_preferred":[
        "Saira"
    ],
    "wof:name":"Saira",
    "wof:placetype":"locality"
},
  "geometry": {"coordinates":[87.87224000000001,25.45968],"type":"Point"}
}