{
  "type": "Feature",
  "properties": {
    "gn:admin1_code":"39.0",
    "gn:admin2_code":"068",
    "gn:asciiname":"Tanda Deshraj",
    "gn:country_code":"IN",
    "gn:dem":340,
    "gn:feature_class":"P",
    "gn:feature_code":"PPL",
    "gn:name":"T\u0101nda Deshr\u0101j",
    "gn:population":0,
    "gn:timezone":"Asia/Kolkata",
    "iso:country":"IN",
    "name:und_x_variant":[
        "T\u0101nda Deshr\u0101j",
        "T\u0101nda Deshr\u0101l"
    ],
    "wof:name":"Tanda Deshraj",
    "wof:placetype":"locality"
},
  "geometry": {"coordinates":[77.89873,30.09283],"type":"Point"}
}