{
  "type": "Feature",
  "properties": {
    "gn:admin1_code":"2.0",
    "gn:admin2_code":"549.0",
    "gn:asciiname":"Korlamadugu",
    "gn:country_code":"IN",
    "gn:dem":69,
    "gn:feature_class":"P",
    "gn:feature_code":"PPL",
    "gn:name":"Korlamadugu",
    "gn:population":0,
    "gn:timezone":"Asia/Kolkata",
    "iso:country":"IN",
    "ks:ks_name":"Korlamadugu",
    "ks:ks_pop":141,
    "ks:ks_type":"VILLAGE",
    "name:eng_x_preferred":[
        "Korlamadugu"
    ],
    "wof:name":"Korlamadugu",
    "wof:placetype":"locality",
    "wof:population":141
},
  "geometry": {"coordinates":[79.69507900000001,15.656679],"type":"Point"}
}