{
  "type": "Feature",
  "properties": {
    "iso:country":"IN",
    "ks:ks_alt_nam":"DAS PARA",
    "ks:ks_name":"Das Para",
    "ks:ks_pop":153,
    "ks:ks_type":"HABITATION",
    "name:eng_x_preferred":[
        "Das Para"
    ],
    "wof:name":"Das Para",
    "wof:placetype":"locality",
    "wof:population":153
},
  "geometry": {"coordinates":[91.35949100000001,23.740602],"type":"Point"}
}