{
  "type": "Feature",
  "properties": {
    "iso:country":"IN",
    "ks:ks_alt_nam":"D.Debnath Para",
    "ks:ks_name":"D.debnath Para",
    "ks:ks_pop":266,
    "ks:ks_type":"HABITATION",
    "ks:ks_uagg_main":0,
    "name:eng_x_preferred":[
        "D.debnath Para"
    ],
    "wof:name":"D.debnath Para",
    "wof:placetype":"neighbourhood",
    "wof:population":266
},
  "geometry": {"coordinates":[91.617262,23.127268],"type":"Point"}
}