{
  "type": "Feature",
  "properties": {
    "iso:country":"IN",
    "ks:ks_name":"Kholadangiani",
    "ks:ks_pop":176,
    "ks:ks_type":"VILLAGE",
    "name:eng_x_preferred":[
        "Kholadangiani"
    ],
    "wof:name":"Kholadangiani",
    "wof:placetype":"locality",
    "wof:population":176
},
  "geometry": {"coordinates":[84.59231,20.962311],"type":"Point"}
}