{
  "type": "Feature",
  "properties": {
    "iso:country":"IN",
    "ks:ks_name":"Khadipal",
    "ks:ks_pop":0,
    "ks:ks_type":"VILLAGE",
    "name:eng_x_preferred":[
        "Khadipal"
    ],
    "wof:name":"Khadipal",
    "wof:placetype":"locality",
    "wof:population":0
},
  "geometry": {"coordinates":[86.118899,21.579799],"type":"Point"}
}