{
  "type": "Feature",
  "properties": {
    "iso:country":"IN",
    "ks:ks_name":"Lalapettai",
    "ks:ks_pop":1163,
    "ks:ks_type":"HABITATION",
    "name:eng_x_preferred":[
        "Lalapettai"
    ],
    "wof:name":"Lalapettai",
    "wof:placetype":"locality",
    "wof:population":1163
},
  "geometry": {"coordinates":[78.715203,12.53689],"type":"Point"}
}