{
  "type": "Feature",
  "properties": {
    "iso:country":"IN",
    "ks:ks_name":"Bodivistar",
    "ks:ks_pop":861,
    "ks:ks_type":"HABITATION",
    "name:eng_x_preferred":[
        "Bodivistar"
    ],
    "wof:name":"Bodivistar",
    "wof:placetype":"locality",
    "wof:population":861
},
  "geometry": {"coordinates":[72.97886099999999,22.497639],"type":"Point"}
}