{
  "type": "Feature",
  "properties": {
    "iso:country":"IN",
    "ks:ks_alt_nam":"5 BLM",
    "ks:ks_name":"5 Blm",
    "ks:ks_pop":141,
    "ks:ks_type":"HABITATION",
    "name:eng_x_preferred":[
        "5 Blm"
    ],
    "wof:name":"5 Blm",
    "wof:placetype":"locality",
    "wof:population":141
},
  "geometry": {"coordinates":[73.520833,29.281389],"type":"Point"}
}