{
  "type": "Feature",
  "properties": {
    "iso:country":"IN",
    "ks:ks_name":"Biskhowa Pt.V",
    "ks:ks_pop":1325,
    "ks:ks_type":"VILLAGE",
    "name:eng_x_preferred":[
        "Biskhowa Pt.V"
    ],
    "wof:name":"Biskhowa Pt.V",
    "wof:placetype":"locality",
    "wof:population":1325
},
  "geometry": {"coordinates":[89.785999,26.138159],"type":"Point"}
}