{
  "type": "Feature",
  "properties": {
    "gn:admin1_code":"38.0",
    "gn:admin2_code":"347.0",
    "gn:asciiname":"Manamath",
    "gn:country_code":"IN",
    "gn:dem":385,
    "gn:feature_class":"P",
    "gn:feature_code":"PPL",
    "gn:name":"Man\u0101math",
    "gn:population":0,
    "gn:timezone":"Asia/Kolkata",
    "iso:country":"IN",
    "ks:ks_name":"Mana Math",
    "ks:ks_pop":241,
    "ks:ks_type":"VILLAGE",
    "name:eng_x_preferred":[
        "Mana Math"
    ],
    "name:eng_x_variant":[
        "Manamath"
    ],
    "wof:name":"Mana Math",
    "wof:placetype":"locality",
    "wof:population":241
},
  "geometry": {"coordinates":[84.744347,24.25731],"type":"Point"}
}