{
  "type": "Feature",
  "properties": {
    "gn:admin1_code":"37.0",
    "gn:admin2_code":"417.0",
    "gn:asciiname":"Palnar",
    "gn:country_code":"IN",
    "gn:dem":360,
    "gn:feature_class":"P",
    "gn:feature_code":"PPL",
    "gn:name":"P\u0101ln\u0101r",
    "gn:population":0,
    "gn:timezone":"Asia/Kolkata",
    "iso:country":"IN",
    "ks:ks_alt_nam":"P\u0101ln\u0101r",
    "ks:ks_name":"Palnar",
    "ks:ks_pop":298,
    "ks:ks_type":"VILLAGE",
    "name:eng_x_preferred":[
        "Palnar"
    ],
    "name:eng_x_variant":[
        "P\u0101ln\u0101r"
    ],
    "wof:name":"Palnar",
    "wof:placetype":"locality",
    "wof:population":298
},
  "geometry": {"coordinates":[80.98224500000001,18.736449],"type":"Point"}
}