{
  "type": "Feature",
  "properties": {
    "gn:admin1_code":"35",
    "gn:admin2_code":"435.0",
    "gn:asciiname":"Amla",
    "gn:country_code":"IN",
    "gn:dem":514,
    "gn:feature_class":"P",
    "gn:feature_code":"PPL",
    "gn:name":"Amla",
    "gn:population":0,
    "gn:timezone":"Asia/Kolkata",
    "iso:country":"IN",
    "name:ben_x_preferred":[
        "\u0986\u09ae\u09b2\u09be"
    ],
    "name:fra_x_preferred":[
        "Amla"
    ],
    "wof:name":"Amla",
    "wof:placetype":"locality"
},
  "geometry": {"coordinates":[75.32838000000002,23.01292],"type":"Point"}
}