{
  "type": "Feature",
  "properties": {
    "iso:country":"IN",
    "ks:ks_alt_nam":"paliyamankulangara",
    "ks:ks_name":"Paliyamankulangara",
    "ks:ks_pop":11904,
    "ks:ks_type":"HABITATION",
    "ks:ks_uagg_main":0,
    "name:eng_x_preferred":[
        "Paliyamankulangara"
    ],
    "wof:name":"Paliyamankulangara",
    "wof:placetype":"neighbourhood",
    "wof:population":11904
},
  "geometry": {"coordinates":[76.201179,10.111171],"type":"Point"}
}