{
  "type": "Feature",
  "properties": {
    "gn:admin1_code":"39",
    "gn:admin2_code":"57.0",
    "gn:asciiname":"Gwalabagar",
    "gn:country_code":"IN",
    "gn:dem":3506,
    "gn:feature_class":"P",
    "gn:feature_code":"PPL",
    "gn:name":"Gw\u0101labagar",
    "gn:population":0,
    "gn:timezone":"Asia/Kolkata",
    "iso:country":"IN",
    "name:und_x_variant":[
        "Gw\u0101labagar",
        "Dharmsala"
    ],
    "wof:name":"Gwalabagar",
    "wof:placetype":"locality"
},
  "geometry": {"coordinates":[79.2255,30.51058],"type":"Point"}
}