{
  "type": "Feature",
  "properties": {
    "gn:admin1_code":"39.0",
    "gn:admin2_code":"64.0",
    "gn:asciiname":"Tarkhet",
    "gn:country_code":"IN",
    "gn:dem":1543,
    "gn:feature_class":"P",
    "gn:feature_code":"PPL",
    "gn:name":"Tarkhet",
    "gn:population":0,
    "gn:timezone":"Asia/Kolkata",
    "iso:country":"IN",
    "wof:name":"Tarkhet",
    "wof:placetype":"neighbourhood"
},
  "geometry": {"coordinates":[79.40525,29.61477],"type":"Point"}
}