{
  "type": "Feature",
  "properties": {
    "iso:country":"IN",
    "ks:ks_name":"Kartorayadih",
    "ks:ks_pop":206,
    "ks:ks_type":"VILLAGE",
    "name:eng_x_preferred":[
        "Kartorayadih"
    ],
    "wof:name":"Kartorayadih",
    "wof:placetype":"locality",
    "wof:population":206
},
  "geometry": {"coordinates":[86.58015399999999,24.430593],"type":"Point"}
}