{
  "type": "Feature",
  "properties": {
    "iso:country":"IN",
    "ks:ks_alt_nam":"NORTH TOLA",
    "ks:ks_name":"North Tola",
    "ks:ks_pop":88,
    "ks:ks_type":"HABITATION",
    "name:eng_x_preferred":[
        "North Tola"
    ],
    "wof:name":"North Tola",
    "wof:placetype":"locality",
    "wof:population":88
},
  "geometry": {"coordinates":[86.01008400000001,25.124097],"type":"Point"}
}