{
  "type": "Feature",
  "properties": {
    "gn:admin1_code":"35",
    "gn:admin2_code":"436.0",
    "gn:asciiname":"Khera Madhopur",
    "gn:country_code":"IN",
    "gn:dem":438,
    "gn:feature_class":"P",
    "gn:feature_code":"PPL",
    "gn:name":"Khera M\u0101dhopur",
    "gn:population":0,
    "gn:timezone":"Asia/Kolkata",
    "iso:country":"IN",
    "wof:name":"Khera Madhopur",
    "wof:placetype":"locality"
},
  "geometry": {"coordinates":[76.11861999999998,23.76812],"type":"Point"}
}