{
  "type": "Feature",
  "properties": {
    "gn:admin1_code":"35.0",
    "gn:admin2_code":"438.0",
    "gn:asciiname":"Rangaon",
    "gn:country_code":"IN",
    "gn:dem":308,
    "gn:feature_class":"P",
    "gn:feature_code":"PPL",
    "gn:name":"Rangaon",
    "gn:population":0,
    "gn:timezone":"Asia/Kolkata",
    "iso:country":"IN",
    "ks:ks_name":"Rangaon",
    "ks:ks_pop":2361,
    "ks:ks_type":"VILLAGE",
    "name:eng_x_preferred":[
        "Rangaon"
    ],
    "wof:name":"Rangaon",
    "wof:placetype":"locality",
    "wof:population":2361
},
  "geometry": {"coordinates":[74.585939,22.18639],"type":"Point"}
}