{
  "type": "Feature",
  "properties": {
    "gn:admin1_code":"35.0",
    "gn:admin2_code":"438.0",
    "gn:asciiname":"Rangaon",
    "gn:country_code":"IN",
    "gn:dem":308,
    "gn:feature_class":"P",
    "gn:feature_code":"PPL",
    "gn:name":"Rangaon",
    "gn:population":0,
    "gn:timezone":"Asia/Kolkata",
    "iso:country":"IN",
    "wof:name":"Rangaon",
    "wof:placetype":"locality"
},
  "geometry": {"coordinates":[74.59665,22.18847],"type":"Point"}
}