{
  "type": "Feature",
  "properties": {
    "iso:country":"IN",
    "ks:ks_name":"Rojwepur",
    "ks:ks_pop":585,
    "ks:ks_type":"HABITATION",
    "name:eng_x_preferred":[
        "Rojwepur"
    ],
    "wof:name":"Rojwepur",
    "wof:placetype":"locality",
    "wof:population":585
},
  "geometry": {"coordinates":[75.360449,20.375005],"type":"Point"}
}