{
  "type": "Feature",
  "properties": {
    "iso:country":"IN",
    "ks:ks_name":"Poli Paliyal",
    "ks:ks_pop":270,
    "ks:ks_type":"VILLAGE",
    "name:eng_x_preferred":[
        "Poli Paliyal"
    ],
    "wof:name":"Poli Paliyal",
    "wof:placetype":"locality",
    "wof:population":270
},
  "geometry": {"coordinates":[80.01223,29.596982],"type":"Point"}
}