{
  "type": "Feature",
  "properties": {
    "iso:country":"IN",
    "ks:ks_name":"West Fulbari",
    "ks:ks_pop":603,
    "ks:ks_type":"HABITATION",
    "name:eng_x_preferred":[
        "West Fulbari"
    ],
    "wof:name":"West Fulbari",
    "wof:placetype":"locality",
    "wof:population":603
},
  "geometry": {"coordinates":[89.38712200000001,26.150422],"type":"Point"}
}