{
  "type": "Feature",
  "properties": {
    "iso:country":"IN",
    "ks:ks_name":"Khairahai",
    "ks:ks_pop":372,
    "ks:ks_type":"HABITATION",
    "name:eng_x_preferred":[
        "Khairahai"
    ],
    "wof:name":"Khairahai",
    "wof:placetype":"locality",
    "wof:population":372
},
  "geometry": {"coordinates":[82.806236,24.404347],"type":"Point"}
}