{
  "type": "Feature",
  "properties": {
    "iso:country":"IN",
    "ks:ks_name":"Balluguda",
    "ks:ks_pop":67,
    "ks:ks_type":"HABITATION",
    "name:eng_x_preferred":[
        "Balluguda"
    ],
    "wof:name":"Balluguda",
    "wof:placetype":"locality",
    "wof:population":67
},
  "geometry": {"coordinates":[83.66027200000001,18.714891],"type":"Point"}
}