{
  "type": "Feature",
  "properties": {
    "gn:admin1_code":"21",
    "gn:admin2_code":"393.0",
    "gn:asciiname":"Nuagaon",
    "gn:country_code":"IN",
    "gn:dem":175,
    "gn:feature_class":"P",
    "gn:feature_code":"PPL",
    "gn:name":"Nuagaon",
    "gn:population":0,
    "gn:timezone":"Asia/Kolkata",
    "iso:country":"IN",
    "wof:name":"Nuagaon",
    "wof:placetype":"locality"
},
  "geometry": {"coordinates":[83.30831999999999,21.01823],"type":"Point"}
}