{
  "type": "Feature",
  "properties": {
    "iso:country":"IN",
    "ks:ks_alt_nam":"Sagjore U.S",
    "ks:ks_name":"Sagjore U.s",
    "ks:ks_pop":2189,
    "ks:ks_type":"HABITATION",
    "name:eng_x_preferred":[
        "Sagjore U.s"
    ],
    "wof:name":"Sagjore U.s",
    "wof:placetype":"locality",
    "wof:population":2189
},
  "geometry": {"coordinates":[83.87,22.215715],"type":"Point"}
}