{
  "type": "Feature",
  "properties": {
    "gn:admin1_code":"28.0",
    "gn:admin2_code":"334.0",
    "gn:asciiname":"Debagram",
    "gn:country_code":"IN",
    "gn:dem":38,
    "gn:feature_class":"P",
    "gn:feature_code":"PPL",
    "gn:name":"Debagr\u0101m",
    "gn:population":0,
    "gn:timezone":"Asia/Kolkata",
    "iso:country":"IN",
    "name:ceb_x_preferred":[
        "Debagr\u0101m"
    ],
    "name:swe_x_preferred":[
        "Debagr\u0101m"
    ],
    "wof:name":"Debagram",
    "wof:placetype":"locality"
},
  "geometry": {"coordinates":[87.92553000000002,24.27894],"type":"Point"}
}