{
  "type": "Feature",
  "properties": {
    "gn:admin1_code":"36",
    "gn:admin2_code":"179.0",
    "gn:asciiname":"Kitkauli",
    "gn:country_code":"IN",
    "gn:dem":103,
    "gn:feature_class":"P",
    "gn:feature_code":"PPL",
    "gn:name":"Kitkauli",
    "gn:population":0,
    "gn:timezone":"Asia/Kolkata",
    "iso:country":"IN",
    "ks:ks_name":"Katkawli",
    "ks:ks_pop":666,
    "ks:ks_type":"VILLAGE",
    "ks:ks_uagg_main":0,
    "name:eng_x_preferred":[
        "Katkawli"
    ],
    "wof:name":"Katkawli",
    "wof:placetype":"neighbourhood",
    "wof:population":666
},
  "geometry": {"coordinates":[82.0248,26.184142],"type":"Point"}
}