{
  "type": "Feature",
  "properties": {
    "iso:country":"IN",
    "ks:ks_name":"Patelpara",
    "ks:ks_pop":208,
    "ks:ks_type":"HABITATION",
    "name:eng_x_preferred":[
        "Patelpara"
    ],
    "wof:name":"Patelpara",
    "wof:placetype":"locality",
    "wof:population":208
},
  "geometry": {"coordinates":[80.981121,20.098987],"type":"Point"}
}