{
  "type": "Feature",
  "properties": {
    "iso:country":"IN",
    "ks:ks_alt_nam":"Gungardi falia",
    "ks:ks_name":"Gungardi Falia",
    "ks:ks_pop":1116,
    "ks:ks_type":"HABITATION",
    "name:eng_x_preferred":[
        "Gungardi Falia"
    ],
    "wof:name":"Gungardi Falia",
    "wof:placetype":"locality",
    "wof:population":1116
},
  "geometry": {"coordinates":[74.296389,22.701694],"type":"Point"}
}