{
  "type": "Feature",
  "properties": {
    "iso:country":"IN",
    "ks:ks_name":"5 MW",
    "ks:ks_pop":795,
    "ks:ks_type":"VILLAGE",
    "name:eng_x_preferred":[
        "5 MW"
    ],
    "wof:name":"5 MW",
    "wof:placetype":"locality",
    "wof:population":795
},
  "geometry": {"coordinates":[74.369719,29.423589],"type":"Point"}
}