{
  "type": "Feature",
  "properties": {
    "gn:admin1_code":"36.0",
    "gn:admin2_code":"132.0",
    "gn:asciiname":"Shivdaspur",
    "gn:country_code":"IN",
    "gn:dem":262,
    "gn:feature_class":"P",
    "gn:feature_code":"PPL",
    "gn:name":"Shivd\u0101spur",
    "gn:population":0,
    "gn:timezone":"Asia/Kolkata",
    "iso:country":"IN",
    "name:bih_x_preferred":[
        "\u0936\u093f\u0935\u0926\u093e\u0938\u092a\u0941\u0930"
    ],
    "name:bpy_x_preferred":[
        "\u09b6\u09bf\u09ac\u09a6\u09be\u09b8\u09aa\u09c1\u09b0"
    ],
    "name:ita_x_preferred":[
        "Shivdaspur"
    ],
    "name:mlg_x_preferred":[
        "Shivdaspur"
    ],
    "name:msa_x_preferred":[
        "Shivdaspur"
    ],
    "name:nld_x_preferred":[
        "Shivdaspur"
    ],
    "name:pol_x_preferred":[
        "Shivdaspur"
    ],
    "name:urd_x_preferred":[
        "\u0634\u06cc\u0648\u062f\u0627\u0633 \u067e\u0648\u0631"
    ],
    "name:vie_x_preferred":[
        "Shivdaspur"
    ],
    "name:zho_x_preferred":[
        "\u65af\u5e0c\u6c83\u8fbe\u65af\u666e\u5c14"
    ],
    "wof:name":"Shivdaspur",
    "wof:placetype":"locality"
},
  "geometry": {"coordinates":[77.49079999999999,29.76724],"type":"Point"}
}