{
  "type": "Feature",
  "properties": {
    "gn:admin1_code":"35",
    "gn:admin2_code":"451.0",
    "gn:asciiname":"Hathleva",
    "gn:country_code":"IN",
    "gn:dem":377,
    "gn:feature_class":"P",
    "gn:feature_code":"PPL",
    "gn:name":"Hathleva",
    "gn:population":0,
    "gn:timezone":"Asia/Kolkata",
    "iso:country":"IN",
    "wof:name":"Hathleva",
    "wof:placetype":"locality"
},
  "geometry": {"coordinates":[79.97419000000002,23.45448],"type":"Point"}
}