{
  "type": "Feature",
  "properties": {
    "iso:country":"IN",
    "ks:ks_name":"Jhatari",
    "ks:ks_pop":675,
    "ks:ks_type":"VILLAGE",
    "ks:ks_uagg_main":0,
    "name:eng_x_preferred":[
        "Jhatari"
    ],
    "wof:name":"Jhatari",
    "wof:placetype":"neighbourhood",
    "wof:population":675
},
  "geometry": {"coordinates":[78.159284,25.007016],"type":"Point"}
}