{
  "type": "Feature",
  "properties": {
    "gn:country":"IN",
    "gn:fcode":"PPL",
    "gn:pop":12093,
    "iso:country":"IN",
    "name:bpy_x_preferred":[
        "\u0995\u09cb\u09ae\u09be\u09b0\u09b2\u09bf\u0999\u09cd\u0997\u09ae"
    ],
    "name:eng_x_preferred":[
        "Komaralingam"
    ],
    "name:fra_x_preferred":[
        "Komaralingam"
    ],
    "name:ita_x_preferred":[
        "Komaralingam"
    ],
    "name:msa_x_preferred":[
        "Komaralingam"
    ],
    "name:nan_x_preferred":[
        "Komaralingam"
    ],
    "name:new_x_preferred":[
        "\u0915\u094b\u092e\u093e\u0930\u0932\u093f\u0902\u0917\u092e"
    ],
    "name:nld_x_preferred":[
        "Komaralingam"
    ],
    "name:por_x_preferred":[
        "Komaralingam"
    ],
    "name:tam_x_preferred":[
        "\u0b95\u0bca\u0bae\u0bbe\u0bb0\u0bb2\u0bbf\u0b99\u0bcd\u0b95\u0bae\u0bcd"
    ],
    "name:vie_x_preferred":[
        "Komaralingam"
    ],
    "name:zho_x_preferred":[
        "\u79d1\u9a6c\u62c9\u6797\u683c\u963f\u59c6"
    ],
    "qs:name":"Komaralingam",
    "qs:name_adm0":"India",
    "qs:name_adm1":"Tamil Nadu",
    "qs:photos_9r":0,
    "qs:photos_sr":0,
    "qs:placetype":"Town",
    "qs:pop_sr":"6",
    "wd:wordcount":104,
    "wof:name":"Komaralingam",
    "wof:placetype":"locality",
    "wof:population":12093
},
  "geometry": {"coordinates":[77.35053000000001,10.48801],"type":"Point"}
}