{
  "type": "Feature",
  "properties": {
    "iso:country":"IN",
    "ks:ks_name":"Malpara",
    "ks:ks_pop":110,
    "ks:ks_type":"HABITATION",
    "name:eng_x_preferred":[
        "Malpara"
    ],
    "wof:name":"Malpara",
    "wof:placetype":"locality",
    "wof:population":110
},
  "geometry": {"coordinates":[84.182869,22.292512],"type":"Point"}
}