{
  "type": "Feature",
  "properties": {
    "iso:country":"IN",
    "ks:ks_name":"Mallikapadar",
    "ks:ks_pop":9,
    "ks:ks_type":"VILLAGE",
    "name:eng_x_preferred":[
        "Mallikapadar"
    ],
    "wof:name":"Mallikapadar",
    "wof:placetype":"locality",
    "wof:population":9
},
  "geometry": {"coordinates":[84.273185,20.514112],"type":"Point"}
}