{
  "type": "Feature",
  "properties": {
    "gn:admin1_code":"37",
    "gn:admin2_code":"414.0",
    "gn:asciiname":"Kakapal",
    "gn:country_code":"IN",
    "gn:dem":560,
    "gn:feature_class":"P",
    "gn:feature_code":"PPL",
    "gn:name":"Kakap\u0101l",
    "gn:population":0,
    "gn:timezone":"Asia/Kolkata",
    "iso:country":"IN",
    "wof:name":"Kakapal",
    "wof:placetype":"locality"
},
  "geometry": {"coordinates":[82.04101,19.05928],"type":"Point"}
}