{
  "type": "Feature",
  "properties": {
    "iso:country":"IN",
    "ks:ks_name":"Mudukoppala",
    "ks:ks_pop":541,
    "ks:ks_type":"HABITATION",
    "name:eng_x_preferred":[
        "Mudukoppala"
    ],
    "wof:name":"Mudukoppala",
    "wof:placetype":"locality",
    "wof:population":541
},
  "geometry": {"coordinates":[74.786659,13.051521],"type":"Point"}
}