{
  "type": "Feature",
  "properties": {
    "iso:country":"IN",
    "ks:ks_alt_nam":"Gor thana",
    "ks:ks_name":"Gor Thana",
    "ks:ks_pop":1178,
    "ks:ks_type":"HABITATION",
    "name:eng_x_preferred":[
        "Gor Thana"
    ],
    "wof:name":"Gor Thana",
    "wof:placetype":"locality",
    "wof:population":1178
},
  "geometry": {"coordinates":[70.901585,23.437553],"type":"Point"}
}