{
  "type": "Feature",
  "properties": {
    "gn:admin1_code":"23",
    "gn:admin2_code":"37.0",
    "gn:asciiname":"Meda",
    "gn:country_code":"IN",
    "gn:dem":216,
    "gn:feature_class":"P",
    "gn:feature_code":"PPL",
    "gn:name":"Meda",
    "gn:population":0,
    "gn:timezone":"Asia/Kolkata",
    "iso:country":"IN",
    "name:cat_x_preferred":[
        "Meda"
    ],
    "name:ceb_x_preferred":[
        "Meda"
    ],
    "name:deu_x_preferred":[
        "Meda"
    ],
    "name:fra_x_preferred":[
        "Meda"
    ],
    "name:glg_x_preferred":[
        "Meda"
    ],
    "name:hun_x_preferred":[
        "Meda"
    ],
    "name:ita_x_preferred":[
        "Meda"
    ],
    "name:pol_x_preferred":[
        "MEDA"
    ],
    "name:por_x_preferred":[
        "Meda"
    ],
    "name:ron_x_preferred":[
        "Meda"
    ],
    "name:rus_x_preferred":[
        "\u041c\u0435\u0434\u0430"
    ],
    "name:spa_x_preferred":[
        "Meda"
    ],
    "name:srp_x_preferred":[
        "Meda"
    ],
    "name:swe_x_preferred":[
        "Meda"
    ],
    "name:tur_x_preferred":[
        "Meda"
    ],
    "name:ukr_x_preferred":[
        "\u041c\u0435\u0434\u0430"
    ],
    "wof:name":"Meda",
    "wof:placetype":"locality"
},
  "geometry": {"coordinates":[75.26989,31.11979],"type":"Point"}
}