{
  "type": "Feature",
  "properties": {
    "iso:country":"IN",
    "ks:ks_alt_nam":"BHUIYAN TOLA",
    "ks:ks_name":"Bhuiyan Tola",
    "ks:ks_pop":140,
    "ks:ks_type":"HABITATION",
    "name:eng_x_preferred":[
        "Bhuiyan Tola"
    ],
    "wof:name":"Bhuiyan Tola",
    "wof:placetype":"locality",
    "wof:population":140
},
  "geometry": {"coordinates":[84.828035,24.466075],"type":"Point"}
}