{
  "type": "Feature",
  "properties": {
    "iso:country":"IN",
    "ks:ks_name":"Mankkeri",
    "ks:ks_pop":1465,
    "ks:ks_type":"HABITATION",
    "ks:ks_uagg_main":0,
    "name:eng_x_preferred":[
        "Mankkeri"
    ],
    "wof:name":"Mankkeri",
    "wof:placetype":"neighbourhood",
    "wof:population":1465
},
  "geometry": {"coordinates":[76.08507400000001,10.854025],"type":"Point"}
}