{
  "type": "Feature",
  "properties": {
    "iso:country":"IN",
    "ks:ks_name":"Achedimba",
    "ks:ks_pop":46,
    "ks:ks_type":"HABITATION",
    "name:eng_x_preferred":[
        "Achedimba"
    ],
    "wof:name":"Achedimba",
    "wof:placetype":"locality",
    "wof:population":46
},
  "geometry": {"coordinates":[75.149427,14.175109],"type":"Point"}
}