{
  "type": "Feature",
  "properties": {
    "gn:admin1_code":"38.0",
    "gn:admin2_code":"353.0",
    "gn:asciiname":"Darbarpur",
    "gn:country_code":"IN",
    "gn:dem":192,
    "gn:feature_class":"P",
    "gn:feature_code":"PPL",
    "gn:name":"Darb\u0101rpur",
    "gn:population":0,
    "gn:timezone":"Asia/Kolkata",
    "iso:country":"IN",
    "ks:ks_alt_nam":"Darb\u0101rpur",
    "ks:ks_name":"Darbarpur",
    "ks:ks_pop":152,
    "ks:ks_type":"VILLAGE",
    "name:eng_x_preferred":[
        "Darbarpur"
    ],
    "name:eng_x_variant":[
        "Darb\u0101rpur"
    ],
    "wof:name":"Darbarpur",
    "wof:placetype":"locality",
    "wof:population":152
},
  "geometry": {"coordinates":[87.52771199999999,24.623179],"type":"Point"}
}