{
  "type": "Feature",
  "properties": {
    "gn:admin1_code":"19.0",
    "gn:admin2_code":"563",
    "gn:asciiname":"Kaiga",
    "gn:country_code":"IN",
    "gn:dem":57,
    "gn:feature_class":"P",
    "gn:feature_code":"PPL",
    "gn:name":"Kaiga",
    "gn:population":0,
    "gn:timezone":"Asia/Kolkata",
    "iso:country":"IN",
    "ks:ks_name":"Kaiga",
    "ks:ks_pop":97,
    "ks:ks_type":"VILLAGE",
    "name:eng_x_preferred":[
        "Kaiga"
    ],
    "name:tam_x_preferred":[
        "\u0b95\u0bc8\u0b95\u0bbe"
    ],
    "wof:name":"Kaiga",
    "wof:placetype":"locality",
    "wof:population":97
},
  "geometry": {"coordinates":[74.444216,14.851724],"type":"Point"}
}