{
  "type": "Feature",
  "properties": {
    "iso:country":"IN",
    "ks:ks_alt_nam":"haki baba ka ashram",
    "ks:ks_name":"Haki Baba Ka Ashram",
    "ks:ks_pop":12,
    "ks:ks_type":"HABITATION",
    "name:eng_x_preferred":[
        "Haki Baba Ka Ashram"
    ],
    "wof:name":"Haki Baba Ka Ashram",
    "wof:placetype":"locality",
    "wof:population":12
},
  "geometry": {"coordinates":[81.955917,26.118808],"type":"Point"}
}