{
  "type": "Feature",
  "properties": {
    "gn:admin1_code":"36",
    "gn:admin2_code":"171.0",
    "gn:asciiname":"Kalwara Khurd",
    "gn:country_code":"IN",
    "gn:dem":113,
    "gn:feature_class":"P",
    "gn:feature_code":"PPL",
    "gn:name":"Kalw\u0101ra Khurd",
    "gn:population":0,
    "gn:timezone":"Asia/Kolkata",
    "iso:country":"IN",
    "ks:ks_alt_nam":"Kalw\u0101ra Khurd",
    "ks:ks_name":"Kalwara Khurd",
    "ks:ks_pop":554,
    "ks:ks_type":"VILLAGE",
    "name:eng_x_preferred":[
        "Kalwara Khurd"
    ],
    "name:eng_x_variant":[
        "Kalw\u0101ra Khurd"
    ],
    "wof:name":"Kalwara Khurd",
    "wof:placetype":"locality",
    "wof:population":554
},
  "geometry": {"coordinates":[80.962902,25.400942],"type":"Point"}
}