{
  "type": "Feature",
  "properties": {
    "iso:country":"IN",
    "ks:ks_name":"Taruk Gerya",
    "ks:ks_pop":154,
    "ks:ks_type":"VILLAGE",
    "name:eng_x_preferred":[
        "Taruk Gerya"
    ],
    "wof:name":"Taruk Gerya",
    "wof:placetype":"locality",
    "wof:population":154
},
  "geometry": {"coordinates":[87.473007,22.484393],"type":"Point"}
}