{
  "type": "Feature",
  "properties": {
    "iso:country":"IN",
    "ks:ks_name":"Nagaguda",
    "ks:ks_pop":12,
    "ks:ks_type":"HABITATION",
    "name:eng_x_preferred":[
        "Nagaguda"
    ],
    "wof:name":"Nagaguda",
    "wof:placetype":"locality",
    "wof:population":12
},
  "geometry": {"coordinates":[82.628789,19.162934],"type":"Point"}
}