{
  "type": "Feature",
  "properties": {
    "gn:admin1_code":"10",
    "gn:admin2_code":"83.0",
    "gn:asciiname":"Saludah",
    "gn:country_code":"IN",
    "gn:dem":224,
    "gn:feature_class":"P",
    "gn:feature_code":"PPL",
    "gn:name":"Salud\u0101h",
    "gn:population":0,
    "gn:timezone":"Asia/Kolkata",
    "iso:country":"IN",
    "wof:name":"Saludah",
    "wof:placetype":"neighbourhood"
},
  "geometry": {"coordinates":[76.63266,28.54473],"type":"Point"}
}