{
  "type": "Feature",
  "properties": {
    "iso:country":"IN",
    "ks:ks_name":"Machhiwara",
    "ks:ks_pop":78,
    "ks:ks_type":"VILLAGE",
    "name:eng_x_preferred":[
        "Machhiwara"
    ],
    "wof:name":"Machhiwara",
    "wof:placetype":"locality",
    "wof:population":78
},
  "geometry": {"coordinates":[74.563811,31.012361],"type":"Point"}
}