{
  "type": "Feature",
  "properties": {
    "gn:admin1_code":"36.0",
    "gn:admin2_code":"134.0",
    "gn:asciiname":"Humayunpur Chandarpal",
    "gn:country_code":"IN",
    "gn:dem":239,
    "gn:feature_class":"P",
    "gn:feature_code":"PPL",
    "gn:name":"Hum\u0101y\u016bnpur Chandarp\u0101l",
    "gn:population":0,
    "gn:timezone":"Asia/Kolkata",
    "iso:country":"IN",
    "wof:name":"Humayunpur Chandarpal",
    "wof:placetype":"locality"
},
  "geometry": {"coordinates":[78.52126,29.34655],"type":"Point"}
}