{
  "type": "Feature",
  "properties": {
    "iso:country":"IN",
    "ks:ks_name":"Bamanbindha",
    "ks:ks_pop":2184,
    "ks:ks_type":"VILLAGE",
    "ks:ks_uagg_main":0,
    "name:eng_x_preferred":[
        "Bamanbindha"
    ],
    "wof:name":"Bamanbindha",
    "wof:placetype":"neighbourhood",
    "wof:population":2184
},
  "geometry": {"coordinates":[86.72047999999999,20.949351],"type":"Point"}
}