{
  "type": "Feature",
  "properties": {
    "gn:admin1_code":"35",
    "gn:admin2_code":"426.0",
    "gn:asciiname":"Devendranagar",
    "gn:country_code":"IN",
    "gn:dem":353,
    "gn:feature_class":"P",
    "gn:feature_code":"PPL",
    "gn:name":"Devendranagar",
    "gn:population":0,
    "gn:timezone":"Asia/Kolkata",
    "iso:country":"IN",
    "name:ben_x_preferred":[
        "\u09a6\u09c7\u09ac\u09c7\u09a8\u09cd\u09a6\u09cd\u09b0\u09a8\u0997\u09b0"
    ],
    "name:bpy_x_preferred":[
        "\u09a6\u09c7\u09ac\u09c7\u09a8\u09cd\u09a6\u09cd\u09b0\u09a8\u0997\u09b0"
    ],
    "name:ita_x_preferred":[
        "Devendranagar"
    ],
    "name:msa_x_preferred":[
        "Devendranagar"
    ],
    "name:new_x_preferred":[
        "\u0926\u0947\u0935\u0947\u0928\u094d\u0926\u094d\u0930\u0928\u0917\u0930"
    ],
    "name:nld_x_preferred":[
        "Devendranagar"
    ],
    "name:por_x_preferred":[
        "Devendranagar"
    ],
    "name:vie_x_preferred":[
        "Devendranagar"
    ],
    "name:zho_x_preferred":[
        "\u5fb7\u97e6\u6069\u5fb7\u62c9\u7eb3\u52a0\u5c14"
    ],
    "wof:name":"Devendranagar",
    "wof:placetype":"locality"
},
  "geometry": {"coordinates":[80.37889,24.61688],"type":"Point"}
}