{
  "type": "Feature",
  "properties": {
    "iso:country":"IN",
    "ks:ks_alt_nam":"BODDAVALASA",
    "ks:ks_name":"Boddavalasa",
    "ks:ks_pop":173,
    "ks:ks_type":"HABITATION",
    "name:eng_x_preferred":[
        "Boddavalasa"
    ],
    "wof:name":"Boddavalasa",
    "wof:placetype":"locality",
    "wof:population":173
},
  "geometry": {"coordinates":[83.160218,18.273754],"type":"Point"}
}