{
  "type": "Feature",
  "properties": {
    "iso:country":"IN",
    "ks:ks_name":"Metera",
    "ks:ks_pop":107,
    "ks:ks_type":"VILLAGE",
    "ks:ks_uagg_main":0,
    "name:eng_x_preferred":[
        "Metera"
    ],
    "wof:name":"Metera",
    "wof:placetype":"neighbourhood",
    "wof:population":107
},
  "geometry": {"coordinates":[92.992733,26.720139],"type":"Point"}
}