{
  "type": "Feature",
  "properties": {
    "gn:country":"IN",
    "gn:fcode":"PPL",
    "gn:population":8753,
    "iso:country":"IN",
    "qs:name":"Bhigvan",
    "qs:name_adm0":"India",
    "qs:name_adm1":"Maharashtra",
    "qs:photos_9k":1,
    "qs:photos_9r":4,
    "qs:photos_all":188,
    "qs:photos_sr":0,
    "qs:placetype":"Town",
    "qs:pop_sr":"5",
    "wof:name":"Bhigvan",
    "wof:placetype":"locality",
    "wof:population":8753
},
  "geometry": {"coordinates":[74.76701,18.3007],"type":"Point"}
}