{
  "type": "Feature",
  "properties": {
    "gn:admin1_code":"35",
    "gn:admin2_code":"456.0",
    "gn:asciiname":"Mohgaon",
    "gn:country_code":"IN",
    "gn:dem":467,
    "gn:feature_class":"P",
    "gn:feature_code":"PPL",
    "gn:name":"Mohgaon",
    "gn:population":0,
    "gn:timezone":"Asia/Kolkata",
    "iso:country":"IN",
    "name:ben_x_preferred":[
        "\u09ae\u09cb\u09b9\u0997\u09be\u0981\u0993"
    ],
    "name:bpy_x_preferred":[
        "\u09ae\u09cb\u09b9\u0997\u09be\u0981\u0993"
    ],
    "name:ceb_x_preferred":[
        "Mohgaon"
    ],
    "name:ita_x_preferred":[
        "Mohgaon"
    ],
    "name:msa_x_preferred":[
        "Mohgaon"
    ],
    "name:new_x_preferred":[
        "\u092e\u094b\u0939\u0917\u093e\u0902\u0935"
    ],
    "name:nld_x_preferred":[
        "Mohgaon"
    ],
    "name:por_x_preferred":[
        "Mohgaon"
    ],
    "name:swe_x_preferred":[
        "Mohgaon"
    ],
    "name:vie_x_preferred":[
        "Mohgaon"
    ],
    "name:zho_x_preferred":[
        "\u83ab\u8d6b\u52a0\u5965\u6069"
    ],
    "wof:name":"Mohgaon",
    "wof:placetype":"locality"
},
  "geometry": {"coordinates":[79.81369000000002,22.41986],"type":"Point"}
}