{
  "type": "Feature",
  "properties": {
    "iso:country":"IN",
    "ks:ks_name":"Nattapattu",
    "ks:ks_pop":3437,
    "ks:ks_type":"VILLAGE",
    "ks:ks_uagg_main":0,
    "name:eng_x_preferred":[
        "Nattapattu"
    ],
    "wof:name":"Nattapattu",
    "wof:placetype":"neighbourhood",
    "wof:population":3437
},
  "geometry": {"coordinates":[79.715611,11.777806],"type":"Point"}
}