{
  "type": "Feature",
  "properties": {
    "gn:admin1_code":"11",
    "gn:admin2_code":"23.0",
    "gn:asciiname":"Raibanj Adwar",
    "gn:country_code":"IN",
    "gn:dem":2483,
    "gn:feature_class":"P",
    "gn:feature_code":"PPL",
    "gn:name":"Raibanj Adw\u0101r",
    "gn:population":0,
    "gn:timezone":"Asia/Kolkata",
    "iso:country":"IN",
    "wof:name":"Raibanj Adwar",
    "wof:placetype":"locality"
},
  "geometry": {"coordinates":[76.00843,32.86543],"type":"Point"}
}