{
  "type": "Feature",
  "properties": {
    "gn:admin1_code":"36.0",
    "gn:admin2_code":"175.0",
    "gn:asciiname":"Saifkhanpur",
    "gn:country_code":"IN",
    "gn:dem":101,
    "gn:feature_class":"P",
    "gn:feature_code":"PPL",
    "gn:name":"Saifkh\u0101npur",
    "gn:population":0,
    "gn:timezone":"Asia/Kolkata",
    "iso:country":"IN",
    "name:und_x_variant":[
        "Saifkh\u0101npur",
        "Chilhani"
    ],
    "wof:name":"Saifkhanpur",
    "wof:placetype":"locality"
},
  "geometry": {"coordinates":[81.96639,25.57687],"type":"Point"}
}