{
  "type": "Feature",
  "properties": {
    "iso:country":"IN",
    "ks:ks_name":"Bandhili",
    "ks:ks_pop":49,
    "ks:ks_type":"VILLAGE",
    "name:eng_x_preferred":[
        "Bandhili"
    ],
    "wof:name":"Bandhili",
    "wof:placetype":"locality",
    "wof:population":49
},
  "geometry": {"coordinates":[84.707695,21.334055],"type":"Point"}
}