{
  "type": "Feature",
  "properties": {
    "gn:admin1_code":"36",
    "gn:admin2_code":"187.0",
    "gn:asciiname":"Bankatwa",
    "gn:country_code":"IN",
    "gn:dem":89,
    "gn:feature_class":"P",
    "gn:feature_code":"PPL",
    "gn:name":"Bankatwa",
    "gn:population":0,
    "gn:timezone":"Asia/Kolkata",
    "iso:country":"IN",
    "ks:ks_name":"Bankatawa",
    "ks:ks_pop":272,
    "ks:ks_type":"HABITATION",
    "ks:ks_uagg_main":0,
    "name:eng_x_preferred":[
        "Bankatawa"
    ],
    "wof:name":"Bankatawa",
    "wof:placetype":"neighbourhood",
    "wof:population":272
},
  "geometry": {"coordinates":[83.20756900000001,27.17853],"type":"Point"}
}