{
  "type": "Feature",
  "properties": {
    "iso:country":"IN",
    "ks:ks_name":"Shiwnandi",
    "ks:ks_pop":71,
    "ks:ks_type":"VILLAGE",
    "name:eng_x_preferred":[
        "Shiwnandi"
    ],
    "wof:name":"Shiwnandi",
    "wof:placetype":"locality",
    "wof:population":71
},
  "geometry": {"coordinates":[79.071573,30.295323],"type":"Point"}
}