{
  "type": "Feature",
  "properties": {
    "iso:country":"IN",
    "ks:ks_name":"Ganeshpura",
    "ks:ks_pop":245,
    "ks:ks_type":"HABITATION",
    "name:eng_x_preferred":[
        "Ganeshpura"
    ],
    "wof:name":"Ganeshpura",
    "wof:placetype":"locality",
    "wof:population":245
},
  "geometry": {"coordinates":[76.30276000000001,12.159105],"type":"Point"}
}