{
  "type": "Feature",
  "properties": {
    "iso:country":"IN",
    "ks:ks_name":"Baimila",
    "ks:ks_pop":367,
    "ks:ks_type":"VILLAGE",
    "name:eng_x_preferred":[
        "Baimila"
    ],
    "wof:name":"Baimila",
    "wof:placetype":"locality",
    "wof:population":367
},
  "geometry": {"coordinates":[84.172451,19.946099],"type":"Point"}
}