{
  "type": "Feature",
  "properties": {
    "iso:country":"IN",
    "ks:ks_alt_nam":"Irrigepalli-Gollahalli",
    "ks:ks_name":"Irrigepalli-gollahalli",
    "ks:ks_pop":414,
    "ks:ks_type":"HABITATION",
    "name:eng_x_preferred":[
        "Irrigepalli-gollahalli"
    ],
    "wof:name":"Irrigepalli-gollahalli",
    "wof:placetype":"locality",
    "wof:population":414
},
  "geometry": {"coordinates":[77.02818000000001,13.796353],"type":"Point"}
}