{
  "type": "Feature",
  "properties": {
    "gn:admin1_code":"24.0",
    "gn:admin2_code":"122.0",
    "gn:asciiname":"Sarsia",
    "gn:country_code":"IN",
    "gn:dem":347,
    "gn:feature_class":"P",
    "gn:feature_code":"PPL",
    "gn:name":"Sarsia",
    "gn:population":0,
    "gn:timezone":"Asia/Kolkata",
    "iso:country":"IN",
    "name:ceb_x_preferred":[
        "Sarsia"
    ],
    "name:fra_x_preferred":[
        "Sarsia"
    ],
    "name:nld_x_preferred":[
        "Sarsia"
    ],
    "name:swe_x_preferred":[
        "Sarsia"
    ],
    "name:war_x_preferred":[
        "Sarsia"
    ],
    "wof:name":"Sarsia",
    "wof:placetype":"neighbourhood"
},
  "geometry": {"coordinates":[75.15443,25.57332],"type":"Point"}
}