{
  "type": "Feature",
  "properties": {
    "iso:country":"IN",
    "ks:ks_alt_nam":"kaspada",
    "ks:ks_name":"Kaspada",
    "ks:ks_pop":118,
    "ks:ks_type":"HABITATION",
    "name:eng_x_preferred":[
        "Kaspada"
    ],
    "wof:name":"Kaspada",
    "wof:placetype":"locality",
    "wof:population":118
},
  "geometry": {"coordinates":[72.946523,19.662203],"type":"Point"}
}