{
  "type": "Feature",
  "properties": {
    "iso:country":"IN",
    "ks:ks_name":"Luburi",
    "ks:ks_pop":340,
    "ks:ks_type":"VILLAGE",
    "name:eng_x_preferred":[
        "Luburi"
    ],
    "wof:name":"Luburi",
    "wof:placetype":"locality",
    "wof:population":340
},
  "geometry": {"coordinates":[84.649703,21.104185],"type":"Point"}
}