{
  "type": "Feature",
  "properties": {
    "gn:admin1_code":"37.0",
    "gn:admin2_code":"416.0",
    "gn:asciiname":"Toylanka",
    "gn:country_code":"IN",
    "gn:dem":633,
    "gn:feature_class":"P",
    "gn:feature_code":"PPL",
    "gn:name":"Toylanka",
    "gn:population":0,
    "gn:timezone":"Asia/Kolkata",
    "iso:country":"IN",
    "wof:name":"Toylanka",
    "wof:placetype":"locality"
},
  "geometry": {"coordinates":[81.50715,18.82676],"type":"Point"}
}