{
  "type": "Feature",
  "properties": {
    "iso:country":"IN",
    "ks:ks_name":"Ghoshpur",
    "ks:ks_pop":15556,
    "ks:ks_type":"VILLAGE",
    "name:eng_x_preferred":[
        "Ghoshpur"
    ],
    "wof:name":"Ghoshpur",
    "wof:placetype":"locality",
    "wof:population":15556
},
  "geometry": {"coordinates":[87.785307,22.734996],"type":"Point"}
}