{
  "type": "Feature",
  "properties": {
    "iso:country":"IN",
    "ks:ks_name":"Kalapura",
    "ks:ks_pop":256,
    "ks:ks_type":"HABITATION",
    "name:eng_x_preferred":[
        "Kalapura"
    ],
    "wof:name":"Kalapura",
    "wof:placetype":"locality",
    "wof:population":256
},
  "geometry": {"coordinates":[71.5514,25.340994],"type":"Point"}
}