{
  "type": "Feature",
  "properties": {
    "iso:country":"IN",
    "ks:ks_name":"Chak Morna",
    "ks:ks_pop":129,
    "ks:ks_type":"VILLAGE",
    "ks:ks_uagg_main":0,
    "name:eng_x_preferred":[
        "Chak Morna"
    ],
    "wof:name":"Chak Morna",
    "wof:placetype":"neighbourhood",
    "wof:population":129
},
  "geometry": {"coordinates":[77.506692,28.99108],"type":"Point"}
}