{
  "type": "Feature",
  "properties": {
    "iso:country":"IN",
    "ks:ks_name":"Koshtewadi",
    "ks:ks_pop":267,
    "ks:ks_type":"HABITATION",
    "name:eng_x_preferred":[
        "Koshtewadi"
    ],
    "wof:name":"Koshtewadi",
    "wof:placetype":"locality",
    "wof:population":267
},
  "geometry": {"coordinates":[73.486667,17.353056],"type":"Point"}
}