{
  "type": "Feature",
  "properties": {
    "gn:admin1_code":"24.0",
    "gn:admin2_code":"118.0",
    "gn:asciiname":"Barana",
    "gn:country_code":"IN",
    "gn:dem":235,
    "gn:feature_class":"P",
    "gn:feature_code":"PPL",
    "gn:name":"Bar\u0101na",
    "gn:population":0,
    "gn:timezone":"Asia/Kolkata",
    "iso:country":"IN",
    "name:fas_x_preferred":[
        "\u0628\u0631\u0627\u0646\u0627"
    ],
    "name:urd_x_preferred":[
        "\u0628\u0631\u0627\u0646\u0627"
    ],
    "wof:name":"Barana",
    "wof:placetype":"locality"
},
  "geometry": {"coordinates":[73.05667,25.30049],"type":"Point"}
}