{
  "type": "Feature",
  "properties": {
    "gn:admin1_code":"36.0",
    "gn:admin2_code":"166.0",
    "gn:asciiname":"Kedartai",
    "gn:country_code":"IN",
    "gn:dem":182,
    "gn:feature_class":"P",
    "gn:feature_code":"PPL",
    "gn:name":"Ked\u0101rt\u0101i",
    "gn:population":0,
    "gn:timezone":"Asia/Kolkata",
    "iso:country":"IN",
    "ks:ks_name":"Kedar Tai",
    "ks:ks_pop":1415,
    "ks:ks_type":"VILLAGE",
    "name:eng_x_preferred":[
        "Kedar Tai"
    ],
    "name:eng_x_variant":[
        "Kedartai"
    ],
    "wof:name":"Kedar Tai",
    "wof:placetype":"locality",
    "wof:population":1415
},
  "geometry": {"coordinates":[79.260454,25.463458],"type":"Point"}
}