{
  "type": "Feature",
  "properties": {
    "iso:country":"IN",
    "ks:ks_name":"Sallsamakki",
    "ks:ks_pop":25,
    "ks:ks_type":"HABITATION",
    "name:eng_x_preferred":[
        "Sallsamakki"
    ],
    "wof:name":"Sallsamakki",
    "wof:placetype":"locality",
    "wof:population":25
},
  "geometry": {"coordinates":[75.41854600000001,13.587186],"type":"Point"}
}