{
  "type": "Feature",
  "properties": {
    "iso:country":"IN",
    "ks:ks_name":"Sheikhmanpur",
    "ks:ks_pop":52,
    "ks:ks_type":"HABITATION",
    "name:eng_x_preferred":[
        "Sheikhmanpur"
    ],
    "wof:name":"Sheikhmanpur",
    "wof:placetype":"locality",
    "wof:population":52
},
  "geometry": {"coordinates":[77.93727,13.101968],"type":"Point"}
}