{
  "type": "Feature",
  "properties": {
    "iso:country":"IN",
    "ks:ks_name":"Pali",
    "ks:ks_pop":1166,
    "ks:ks_type":"VILLAGE",
    "ks:ks_uagg_main":0,
    "name:eng_x_preferred":[
        "Pali"
    ],
    "wof:name":"Pali",
    "wof:placetype":"neighbourhood",
    "wof:population":1166
},
  "geometry": {"coordinates":[77.079728,26.849214],"type":"Point"}
}