{
  "type": "Feature",
  "properties": {
    "gn:admin1_code":"36.0",
    "gn:admin2_code":"180.0",
    "gn:asciiname":"Koili",
    "gn:country_code":"IN",
    "gn:dem":111,
    "gn:feature_class":"P",
    "gn:feature_code":"PPL",
    "gn:name":"Koili",
    "gn:population":0,
    "gn:timezone":"Asia/Kolkata",
    "iso:country":"IN",
    "name:bul_x_preferred":[
        "\u041a\u0438\u043b\u0438"
    ],
    "name:ceb_x_preferred":[
        "Ko\u00edli"
    ],
    "name:ell_x_preferred":[
        "\u039a\u03bf\u03af\u03bb\u03b7 \u03a0\u03ac\u03c6\u03bf\u03c5"
    ],
    "name:hye_x_preferred":[
        "\u053f\u056b\u056c\u056b"
    ],
    "name:pol_x_preferred":[
        "Kili"
    ],
    "name:swe_x_preferred":[
        "Ko\u00edli"
    ],
    "name:urd_x_preferred":[
        "\u06a9\u0648\u06cc\u0644\u06cc"
    ],
    "wof:name":"Koili",
    "wof:placetype":"neighbourhood"
},
  "geometry": {"coordinates":[81.51631,27.14954],"type":"Point"}
}