{
  "type": "Feature",
  "properties": {
    "gn:admin1_code":"35",
    "gn:admin2_code":"451.0",
    "gn:asciiname":"Tinsa",
    "gn:country_code":"IN",
    "gn:dem":418,
    "gn:feature_class":"P",
    "gn:feature_code":"PPL",
    "gn:name":"Tinsa",
    "gn:population":0,
    "gn:timezone":"Asia/Kolkata",
    "iso:country":"IN",
    "wof:name":"Tinsa",
    "wof:placetype":"neighbourhood"
},
  "geometry": {"coordinates":[79.83477000000001,22.96995],"type":"Point"}
}