{
  "type": "Feature",
  "properties": {
    "gn:admin1_code":"36",
    "gn:admin2_code":"142.0",
    "gn:asciiname":"Rasulpur",
    "gn:country_code":"IN",
    "gn:dem":195,
    "gn:feature_class":"P",
    "gn:feature_code":"PPL",
    "gn:name":"Ras\u016blpur",
    "gn:population":0,
    "gn:timezone":"Asia/Kolkata",
    "iso:country":"IN",
    "name:und_x_variant":[
        "Ras\u016blpur",
        "Nar\u0101inpur"
    ],
    "wof:name":"Rasulpur",
    "wof:placetype":"locality"
},
  "geometry": {"coordinates":[78.18845999999998,28.17058],"type":"Point"}
}