{
  "type": "Feature",
  "properties": {
    "iso:country":"IN",
    "ks:ks_alt_nam":"AMALIPARA  B",
    "ks:ks_name":"Amalipara B",
    "ks:ks_pop":218,
    "ks:ks_type":"HABITATION",
    "name:eng_x_preferred":[
        "Amalipara B"
    ],
    "name:eng_x_variant":[
        "AMALIPARA  B"
    ],
    "wof:name":"Amalipara B",
    "wof:placetype":"locality",
    "wof:population":218
},
  "geometry": {"coordinates":[82.05035599999999,22.345272],"type":"Point"}
}