{
  "type": "Feature",
  "properties": {
    "iso:country":"IN",
    "ks:ks_name":"Jhakua Para",
    "ks:ks_pop":624,
    "ks:ks_type":"HABITATION",
    "name:eng_x_preferred":[
        "Jhakua Para"
    ],
    "wof:name":"Jhakua Para",
    "wof:placetype":"locality",
    "wof:population":624
},
  "geometry": {"coordinates":[89.498574,26.344105],"type":"Point"}
}