{
  "type": "Feature",
  "properties": {
    "iso:country":"IN",
    "ks:ks_name":"Kalarpara",
    "ks:ks_pop":161,
    "ks:ks_type":"HABITATION",
    "name:eng_x_preferred":[
        "Kalarpara"
    ],
    "wof:name":"Kalarpara",
    "wof:placetype":"locality",
    "wof:population":161
},
  "geometry": {"coordinates":[81.836815,19.362824],"type":"Point"}
}