{
  "type": "Feature",
  "properties": {
    "iso:country":"IN",
    "ks:ks_name":"Kuppanmane",
    "ks:ks_pop":27,
    "ks:ks_type":"HABITATION",
    "name:eng_x_preferred":[
        "Kuppanmane"
    ],
    "wof:name":"Kuppanmane",
    "wof:placetype":"locality",
    "wof:population":27
},
  "geometry": {"coordinates":[74.72127500000001,14.62207],"type":"Point"}
}