{
  "type": "Feature",
  "properties": {
    "iso:country":"IN",
    "ks:ks_name":"Harachha",
    "ks:ks_pop":3106,
    "ks:ks_type":"VILLAGE",
    "ks:ks_uagg_main":0,
    "name:eng_x_preferred":[
        "Harachha"
    ],
    "wof:name":"Harachha",
    "wof:placetype":"neighbourhood",
    "wof:population":3106
},
  "geometry": {"coordinates":[85.970308,26.030098],"type":"Point"}
}