{
  "type": "Feature",
  "properties": {
    "gn:admin1_code":"40.0",
    "gn:admin2_code":"541.0",
    "gn:asciiname":"Tatukuru",
    "gn:country_code":"IN",
    "gn:dem":49,
    "gn:feature_class":"P",
    "gn:feature_code":"PPL",
    "gn:name":"T\u0101tuk\u016bru",
    "gn:population":0,
    "gn:timezone":"Asia/Kolkata",
    "iso:country":"IN",
    "ks:ks_name":"Thatkuru",
    "ks:ks_pop":280,
    "ks:ks_type":"HABITATION",
    "name:eng_x_preferred":[
        "Thatkuru"
    ],
    "name:eng_x_variant":[
        "Tatukuru"
    ],
    "wof:name":"Thatkuru",
    "wof:placetype":"locality",
    "wof:population":280
},
  "geometry": {"coordinates":[81.274164,17.535344],"type":"Point"}
}