{
  "type": "Feature",
  "properties": {
    "iso:country":"IN",
    "ks:ks_name":"Valluruvaripalle",
    "ks:ks_pop":35,
    "ks:ks_type":"HABITATION",
    "ks:ks_uagg_main":0,
    "name:eng_x_preferred":[
        "Valluruvaripalle"
    ],
    "wof:name":"Valluruvaripalle",
    "wof:placetype":"neighbourhood",
    "wof:population":35
},
  "geometry": {"coordinates":[79.073511,13.513263],"type":"Point"}
}