{
  "type": "Feature",
  "properties": {
    "gn:admin1_code":"36",
    "gn:admin2_code":"172.0",
    "gn:asciiname":"Bakhshpur",
    "gn:country_code":"IN",
    "gn:dem":119,
    "gn:feature_class":"P",
    "gn:feature_code":"PPL",
    "gn:name":"Bakhshpur",
    "gn:population":0,
    "gn:timezone":"Asia/Kolkata",
    "iso:country":"IN",
    "ks:ks_name":"Bakshapur",
    "ks:ks_pop":1071,
    "ks:ks_type":"HABITATION",
    "name:eng_x_preferred":[
        "Bakshapur"
    ],
    "name:eng_x_variant":[
        "Bakhshpur"
    ],
    "wof:name":"Bakshapur",
    "wof:placetype":"locality",
    "wof:population":1071
},
  "geometry": {"coordinates":[80.92301,25.852384],"type":"Point"}
}