{
  "type": "Feature",
  "properties": {
    "iso:country":"IN",
    "ks:ks_name":"Vihrojpur Khas",
    "ks:ks_pop":575,
    "ks:ks_type":"HABITATION",
    "ks:ks_uagg_main":0,
    "name:eng_x_preferred":[
        "Vihrojpur Khas"
    ],
    "wof:name":"Vihrojpur Khas",
    "wof:placetype":"neighbourhood",
    "wof:population":575
},
  "geometry": {"coordinates":[82.624709,26.518866],"type":"Point"}
}