{
  "type": "Feature",
  "properties": {
    "iso:country":"IN",
    "ks:ks_name":"Sadara Karenahalli",
    "ks:ks_pop":82,
    "ks:ks_type":"HABITATION",
    "name:eng_x_preferred":[
        "Sadara Karenahalli"
    ],
    "wof:name":"Sadara Karenahalli",
    "wof:placetype":"locality",
    "wof:population":82
},
  "geometry": {"coordinates":[76.771407,13.671076],"type":"Point"}
}