{
  "type": "Feature",
  "properties": {
    "iso:country":"IN",
    "ks:ks_name":"Sibyoli",
    "ks:ks_pop":390,
    "ks:ks_type":"HABITATION",
    "name:eng_x_preferred":[
        "Sibyoli"
    ],
    "wof:name":"Sibyoli",
    "wof:placetype":"locality",
    "wof:population":390
},
  "geometry": {"coordinates":[79.96739100000001,29.474404],"type":"Point"}
}