{
  "type": "Feature",
  "properties": {
    "gn:admin1_code":"36",
    "gn:admin2_code":"146.0",
    "gn:asciiname":"Jajpur",
    "gn:country_code":"IN",
    "gn:dem":165,
    "gn:feature_class":"P",
    "gn:feature_code":"PPL",
    "gn:name":"J\u0101jpur",
    "gn:population":0,
    "gn:timezone":"Asia/Kolkata",
    "iso:country":"IN",
    "name:ara_x_preferred":[
        "\u062c\u0627\u062c\u0628\u0648\u0631"
    ],
    "name:ben_x_preferred":[
        "\u09af\u09be\u099c\u09aa\u09c1\u09b0"
    ],
    "name:bpy_x_preferred":[
        "\u099c\u09be\u099c\u09be\u09aa\u09c1\u09b0"
    ],
    "name:cat_x_preferred":[
        "Jajpur"
    ],
    "name:ceb_x_preferred":[
        "J\u0101jpur"
    ],
    "name:deu_x_preferred":[
        "Jajpur"
    ],
    "name:fra_x_preferred":[
        "Jajpur"
    ],
    "name:hin_x_preferred":[
        "\u091c\u093e\u091c\u092a\u0941\u0930"
    ],
    "name:ita_x_preferred":[
        "Jajpur"
    ],
    "name:mlg_x_preferred":[
        "Jajpur"
    ],
    "name:msa_x_preferred":[
        "Jajapur"
    ],
    "name:ori_x_preferred":[
        "\u0b2f\u0b3e\u0b1c\u0b2a\u0b41\u0b30"
    ],
    "name:por_x_preferred":[
        "Jajapur"
    ],
    "name:rus_x_preferred":[
        "\u0414\u0436\u0430\u0434\u0436\u043f\u0443\u0440"
    ],
    "name:swe_x_preferred":[
        "Jajapur"
    ],
    "name:urd_x_preferred":[
        "\u062c\u062c\u067e\u0648\u0631"
    ],
    "name:vie_x_preferred":[
        "Jajapur"
    ],
    "name:zho_x_preferred":[
        "\u8d3e\u8d3e\u666e\u5c14"
    ],
    "wof:name":"Jajpur",
    "wof:placetype":"locality"
},
  "geometry": {"coordinates":[78.38091,27.02457],"type":"Point"}
}