{
  "type": "Feature",
  "properties": {
    "iso:country":"IN",
    "ks:ks_name":"Putura",
    "ks:ks_pop":796,
    "ks:ks_type":"VILLAGE",
    "name:eng_x_preferred":[
        "Putura"
    ],
    "wof:name":"Putura",
    "wof:placetype":"locality",
    "wof:population":796
},
  "geometry": {"coordinates":[87.154504,21.664035],"type":"Point"}
}