{
  "type": "Feature",
  "properties": {
    "iso:country":"IN",
    "ks:ks_name":"Ambapani",
    "ks:ks_pop":196,
    "ks:ks_type":"HABITATION",
    "name:eng_x_preferred":[
        "Ambapani"
    ],
    "wof:name":"Ambapani",
    "wof:placetype":"locality",
    "wof:population":196
},
  "geometry": {"coordinates":[75.326694,21.454399],"type":"Point"}
}