{
  "type": "Feature",
  "properties": {
    "iso:country":"IN",
    "ks:ks_name":"Khanpur",
    "ks:ks_pop":4,
    "ks:ks_type":"VILLAGE",
    "name:eng_x_preferred":[
        "Khanpur"
    ],
    "wof:name":"Khanpur",
    "wof:placetype":"locality",
    "wof:population":4
},
  "geometry": {"coordinates":[87.3745,23.862846],"type":"Point"}
}