{
  "type": "Feature",
  "properties": {
    "iso:country":"IN",
    "ks:ks_name":"Hathiya Pathar",
    "ks:ks_pop":849,
    "ks:ks_type":"VILLAGE",
    "name:eng_x_preferred":[
        "Hathiya Pathar"
    ],
    "wof:name":"Hathiya Pathar",
    "wof:placetype":"locality",
    "wof:population":849
},
  "geometry": {"coordinates":[87.098354,23.929437],"type":"Point"}
}