{
  "type": "Feature",
  "properties": {
    "gn:admin1_code":"25.0",
    "gn:admin2_code":"611.0",
    "gn:asciiname":"Bogadi",
    "gn:country_code":"IN",
    "gn:dem":979,
    "gn:feature_class":"P",
    "gn:feature_code":"PPL",
    "gn:name":"Bogadi",
    "gn:population":0,
    "gn:timezone":"Asia/Kolkata",
    "iso:country":"IN",
    "name:ceb_x_preferred":[
        "Bogadi"
    ],
    "name:nep_x_preferred":[
        "\u092c\u094b\u0917\u093e\u0921\u0940"
    ],
    "name:new_x_preferred":[
        "\u092c\u094b\u0917\u093e\u0921\u0940"
    ],
    "name:pol_x_preferred":[
        "Bogadi"
    ],
    "name:vie_x_preferred":[
        "Bogadi"
    ],
    "wof:name":"Bogadi",
    "wof:placetype":"locality"
},
  "geometry": {"coordinates":[76.45201,11.56325],"type":"Point"}
}