{
  "type": "Feature",
  "properties": {
    "iso:country":"IN",
    "ks:ks_name":"Dabakpada",
    "ks:ks_pop":150,
    "ks:ks_type":"HABITATION",
    "name:eng_x_preferred":[
        "Dabakpada"
    ],
    "wof:name":"Dabakpada",
    "wof:placetype":"locality",
    "wof:population":150
},
  "geometry": {"coordinates":[73.024321,19.587898],"type":"Point"}
}