{
  "type": "Feature",
  "properties": {
    "iso:country":"IN",
    "ks:ks_name":"Hosenabad",
    "ks:ks_pop":1782,
    "ks:ks_type":"VILLAGE",
    "ks:ks_uagg_main":0,
    "name:eng_x_preferred":[
        "Hosenabad"
    ],
    "wof:name":"Hosenabad",
    "wof:placetype":"neighbourhood",
    "wof:population":1782
},
  "geometry": {"coordinates":[87.341268,22.413227],"type":"Point"}
}