{
  "type": "Feature",
  "properties": {
    "iso:country":"IN",
    "ks:ks_alt_nam":"HARIJAN BASTI2",
    "ks:ks_name":"Harijan Basti2",
    "ks:ks_pop":540,
    "ks:ks_type":"HABITATION",
    "name:eng_x_preferred":[
        "Harijan Basti2"
    ],
    "wof:name":"Harijan Basti2",
    "wof:placetype":"locality",
    "wof:population":540
},
  "geometry": {"coordinates":[83.989244,26.029643],"type":"Point"}
}