{
  "type": "Feature",
  "properties": {
    "iso:country":"IN",
    "ks:ks_name":"Thiruppaniendhal",
    "ks:ks_pop":301,
    "ks:ks_type":"HABITATION",
    "name:eng_x_preferred":[
        "Thiruppaniendhal"
    ],
    "wof:name":"Thiruppaniendhal",
    "wof:placetype":"locality",
    "wof:population":301
},
  "geometry": {"coordinates":[78.921519,10.046113],"type":"Point"}
}