{
  "type": "Feature",
  "properties": {
    "gn:admin1_code":"35.0",
    "gn:admin2_code":"419.0",
    "gn:asciiname":"Gangolihar",
    "gn:country_code":"IN",
    "gn:dem":186,
    "gn:feature_class":"P",
    "gn:feature_code":"PPL",
    "gn:name":"Gangol\u012bh\u0101r",
    "gn:population":0,
    "gn:timezone":"Asia/Kolkata",
    "iso:country":"IN",
    "wof:name":"Gangolihar",
    "wof:placetype":"locality"
},
  "geometry": {"coordinates":[77.80056,26.41082],"type":"Point"}
}