{
  "type": "Feature",
  "properties": {
    "iso:country":"IN",
    "ks:ks_alt_nam":"Nayyar Dam JN",
    "ks:ks_name":"Nayyar Dam Jn",
    "ks:ks_pop":2070,
    "ks:ks_type":"HABITATION",
    "ks:ks_uagg_main":0,
    "name:eng_x_preferred":[
        "Nayyar Dam Jn"
    ],
    "wof:name":"Nayyar Dam Jn",
    "wof:placetype":"neighbourhood",
    "wof:population":2070
},
  "geometry": {"coordinates":[77.150248,8.428585],"type":"Point"}
}