{
  "type": "Feature",
  "properties": {
    "iso:country":"IN",
    "ks:ks_alt_nam":"AMOL SINGH KE MADIYA",
    "ks:ks_name":"Amol Singh Ke Madiya",
    "ks:ks_pop":175,
    "ks:ks_type":"HABITATION",
    "name:eng_x_preferred":[
        "Amol Singh Ke Madiya"
    ],
    "wof:name":"Amol Singh Ke Madiya",
    "wof:placetype":"locality",
    "wof:population":175
},
  "geometry": {"coordinates":[79.007384,26.632357],"type":"Point"}
}