{
  "type": "Feature",
  "properties": {
    "gn:admin1_code":"23.0",
    "gn:admin2_code":"42.0",
    "gn:asciiname":"Singhpura",
    "gn:country_code":"IN",
    "gn:dem":217,
    "gn:feature_class":"P",
    "gn:feature_code":"PPL",
    "gn:name":"Singhpura",
    "gn:population":0,
    "gn:timezone":"Asia/Kolkata",
    "iso:country":"IN",
    "name:und_x_variant":[
        "Mun\u0101n"
    ],
    "wof:name":"Singhpura",
    "wof:placetype":"locality"
},
  "geometry": {"coordinates":[75.09664000000002,30.93411],"type":"Point"}
}