{
  "type": "Feature",
  "properties": {
    "gn:admin1_code":"36",
    "gn:admin2_code":"170.0",
    "gn:asciiname":"Lala Dera",
    "gn:country_code":"IN",
    "gn:dem":118,
    "gn:feature_class":"P",
    "gn:feature_code":"PPL",
    "gn:name":"L\u0101la Dera",
    "gn:population":0,
    "gn:timezone":"Asia/Kolkata",
    "iso:country":"IN",
    "wof:name":"Lala Dera",
    "wof:placetype":"locality"
},
  "geometry": {"coordinates":[80.33089,25.84055],"type":"Point"}
}