{
  "type": "Feature",
  "properties": {
    "iso:country":"IN",
    "ks:ks_name":"Harijan Tola Piraridih",
    "ks:ks_pop":656,
    "ks:ks_type":"HABITATION",
    "ks:ks_uagg_main":0,
    "name:eng_x_preferred":[
        "Harijan Tola Piraridih"
    ],
    "wof:name":"Harijan Tola Piraridih",
    "wof:placetype":"neighbourhood",
    "wof:population":656
},
  "geometry": {"coordinates":[84.94547300000001,25.857085],"type":"Point"}
}