{
  "type": "Feature",
  "properties": {
    "iso:country":"IN",
    "ks:ks_name":"Karimarkatte",
    "ks:ks_pop":351,
    "ks:ks_type":"HABITATION",
    "name:eng_x_preferred":[
        "Karimarkatte"
    ],
    "wof:name":"Karimarkatte",
    "wof:placetype":"locality",
    "wof:population":351
},
  "geometry": {"coordinates":[75.05076800000001,13.193872],"type":"Point"}
}