{
  "type": "Feature",
  "properties": {
    "gn:admin1_code":"35.0",
    "gn:admin2_code":"425",
    "gn:asciiname":"Gathaura",
    "gn:country_code":"IN",
    "gn:dem":296,
    "gn:feature_class":"P",
    "gn:feature_code":"PPL",
    "gn:name":"Gathaura",
    "gn:population":0,
    "gn:timezone":"Asia/Kolkata",
    "iso:country":"IN",
    "wof:name":"Gathaura",
    "wof:placetype":"locality"
},
  "geometry": {"coordinates":[79.65000000000001,24.91667],"type":"Point"}
}