{
  "type": "Feature",
  "properties": {
    "iso:country":"IN",
    "ks:ks_alt_nam":"Guriya toli",
    "ks:ks_name":"Guriya Toli",
    "ks:ks_pop":305,
    "ks:ks_type":"HABITATION",
    "name:eng_x_preferred":[
        "Guriya Toli"
    ],
    "wof:name":"Guriya Toli",
    "wof:placetype":"locality",
    "wof:population":305
},
  "geometry": {"coordinates":[84.613342,22.438826],"type":"Point"}
}