{
  "type": "Feature",
  "properties": {
    "iso:country":"IN",
    "ks:ks_name":"17 GG",
    "ks:ks_pop":88,
    "ks:ks_type":"VILLAGE",
    "name:eng_x_preferred":[
        "17 GG"
    ],
    "wof:name":"17 GG",
    "wof:placetype":"locality",
    "wof:population":88
},
  "geometry": {"coordinates":[73.868369,29.832367],"type":"Point"}
}