{
  "type": "Feature",
  "properties": {
    "iso:country":"IN",
    "ks:ks_name":"Anja",
    "ks:ks_pop":120,
    "ks:ks_type":"HABITATION",
    "name:eng_x_preferred":[
        "Anja"
    ],
    "wof:name":"Anja",
    "wof:placetype":"locality",
    "wof:population":120
},
  "geometry": {"coordinates":[84.106708,19.020089],"type":"Point"}
}