{
  "type": "Feature",
  "properties": {
    "gn:admin1_code":"36",
    "gn:admin2_code":"159.0",
    "gn:asciiname":"Mohiuddinpur",
    "gn:country_code":"IN",
    "gn:dem":160,
    "gn:feature_class":"P",
    "gn:feature_code":"PPL",
    "gn:name":"Mohiudd\u012bnpur",
    "gn:population":0,
    "gn:timezone":"Asia/Kolkata",
    "iso:country":"IN",
    "name:bpy_x_preferred":[
        "\u09ae\u09cb\u09b9\u09bf\u0989\u09a6\u09cd\u09a6\u09a8\u09aa\u09c1\u09b0"
    ],
    "name:ita_x_preferred":[
        "Mohiuddinpur"
    ],
    "name:msa_x_preferred":[
        "Mohiuddinpur"
    ],
    "name:new_x_preferred":[
        "\u092e\u094b\u0939\u093f\u0909\u0926\u094d\u0926\u0940\u0928\u092a\u0941\u0930"
    ],
    "name:nld_x_preferred":[
        "Mohiuddinpur"
    ],
    "name:pol_x_preferred":[
        "Mohiuddinpur"
    ],
    "name:por_x_preferred":[
        "Mohiuddinpur"
    ],
    "name:vie_x_preferred":[
        "Mohiuddinpur"
    ],
    "name:zho_x_preferred":[
        "\u83ab\u5e0c\u4e4c\u4e01\u666e\u5c14"
    ],
    "wof:name":"Mohiuddinpur",
    "wof:placetype":"locality"
},
  "geometry": {"coordinates":[79.25971,27.54912],"type":"Point"}
}