{
  "type": "Feature",
  "properties": {
    "gn:country":"IN",
    "gn:fcode":"PPL",
    "gn:pop":47343,
    "iso:country":"IN",
    "name:ben_x_preferred":[
        "\u09ac\u09be\u09b0\u0993\u09af\u09bc\u09be\u09a8\u09bf"
    ],
    "name:bpy_x_preferred":[
        "\u09ac\u09be\u09b0\u09f1\u09be\u09a8\u09bf"
    ],
    "name:cat_x_preferred":[
        "Barwani"
    ],
    "name:chi_x_preferred":[
        "\u5df4\u5c14\u74e6\u5c3c"
    ],
    "name:dut_x_preferred":[
        "Barwani"
    ],
    "name:eng_x_preferred":[
        "Barwani"
    ],
    "name:fre_x_preferred":[
        "Barwani"
    ],
    "name:ger_x_preferred":[
        "Barwani"
    ],
    "name:guj_x_preferred":[
        "\u0aac\u0ab0\u0ab5\u0abe\u0aa8\u0ac0"
    ],
    "name:ita_x_preferred":[
        "Barwani"
    ],
    "name:jpn_x_preferred":[
        "\u30d0\u30fc\u30ef\u30cb"
    ],
    "name:kan_x_preferred":[
        "\u0cac\u0cb0\u0ccd\u0cb5\u0cbe\u0ca8\u0cbf"
    ],
    "name:kor_x_preferred":[
        "\ubc14\ub974\uc640\ub2c8"
    ],
    "name:may_x_preferred":[
        "Barwani"
    ],
    "name:mlg_x_preferred":[
        "Barwani"
    ],
    "name:new_x_preferred":[
        "\u092c\u0930\u094d\u0935\u093e\u0928\u0940"
    ],
    "name:pam_x_preferred":[
        "Barwani"
    ],
    "name:por_x_preferred":[
        "Barwani"
    ],
    "name:rus_x_preferred":[
        "\u0411\u0430\u0440\u0432\u0430\u043d\u0438"
    ],
    "name:san_x_preferred":[
        "\u092c\u0921\u0935\u093e\u0928\u0940"
    ],
    "name:spa_x_preferred":[
        "Barwani"
    ],
    "name:swe_x_preferred":[
        "Barwani"
    ],
    "name:tam_x_preferred":[
        "\u0baa\u0bb0\u0bcd\u0bb5\u0bbe\u0ba9\u0bbf"
    ],
    "name:tel_x_preferred":[
        "\u0c2c\u0c30\u0c4d\u0c35\u0c3e\u0c28\u0c3f"
    ],
    "name:unk_x_variant":[
        "Barw\u0101ni"
    ],
    "name:urd_x_preferred":[
        "\u0628\u0627\u0631\u0648\u0627\u0646\u06cc"
    ],
    "name:vie_x_preferred":[
        "Barwani"
    ],
    "qs:name":"Barwani",
    "qs:name_adm0":"India",
    "qs:name_adm1":"Madhya Pradesh",
    "qs:photos_9r":0,
    "qs:photos_sr":0,
    "qs:placetype":"Town",
    "qs:pop_sr":"7",
    "wd:elevation":178.0,
    "wd:wordcount":1130,
    "wof:name":"Barwani",
    "wof:placetype":"locality",
    "wof:population":47343
},
  "geometry": {"coordinates":[74.89807999999999,22.03261],"type":"Point"}
}