{
  "type": "Feature",
  "properties": {
    "iso:country":"IN",
    "ks:ks_name":"Badasireipurdorabada",
    "ks:ks_pop":806,
    "ks:ks_type":"VILLAGE",
    "name:eng_x_preferred":[
        "Badasireipurdorabada"
    ],
    "wof:name":"Badasireipurdorabada",
    "wof:placetype":"locality",
    "wof:population":806
},
  "geometry": {"coordinates":[85.156417,19.850036],"type":"Point"}
}