{
  "type": "Feature",
  "properties": {
    "iso:country":"IN",
    "ks:ks_name":"Hasot",
    "ks:ks_pop":615,
    "ks:ks_type":"VILLAGE",
    "name:eng_x_preferred":[
        "Hasot"
    ],
    "wof:name":"Hasot",
    "wof:placetype":"locality",
    "wof:population":615
},
  "geometry": {"coordinates":[84.902271,24.265308],"type":"Point"}
}