{
  "type": "Feature",
  "properties": {
    "iso:country":"IN",
    "ks:ks_name":"Gavasewadi",
    "ks:ks_pop":747,
    "ks:ks_type":"HABITATION",
    "name:eng_x_preferred":[
        "Gavasewadi"
    ],
    "wof:name":"Gavasewadi",
    "wof:placetype":"locality",
    "wof:population":747
},
  "geometry": {"coordinates":[73.761641,16.211142],"type":"Point"}
}