{
  "type": "Feature",
  "properties": {
    "gn:admin1_code":"36",
    "gn:admin2_code":"143.0",
    "gn:asciiname":"Sumera Daryapur",
    "gn:country_code":"IN",
    "gn:dem":194,
    "gn:feature_class":"P",
    "gn:feature_code":"PPL",
    "gn:name":"Sumera Dary\u0101pur",
    "gn:population":0,
    "gn:timezone":"Asia/Kolkata",
    "iso:country":"IN",
    "name:und_x_variant":[
        "Sumera Dary\u0101pur",
        "Sumera"
    ],
    "wof:name":"Sumera Daryapur",
    "wof:placetype":"locality"
},
  "geometry": {"coordinates":[78.09459,28.0342],"type":"Point"}
}