{
  "type": "Feature",
  "properties": {
    "iso:country":"IN",
    "ks:ks_alt_nam":"DEVKALI KA PURA",
    "ks:ks_name":"Devkali Ka Pura",
    "ks:ks_pop":69,
    "ks:ks_type":"HABITATION",
    "name:eng_x_preferred":[
        "Devkali Ka Pura"
    ],
    "wof:name":"Devkali Ka Pura",
    "wof:placetype":"locality",
    "wof:population":69
},
  "geometry": {"coordinates":[82.06873,26.225284],"type":"Point"}
}