{
  "type": "Feature",
  "properties": {
    "iso:country":"IN",
    "ks:ks_name":"Surjan Pur",
    "ks:ks_pop":228,
    "ks:ks_type":"HABITATION",
    "name:eng_x_preferred":[
        "Surjan Pur"
    ],
    "wof:name":"Surjan Pur",
    "wof:placetype":"locality",
    "wof:population":228
},
  "geometry": {"coordinates":[79.794549,27.369664],"type":"Point"}
}