{
  "type": "Feature",
  "properties": {
    "iso:country":"IN",
    "ks:ks_name":"Simgoan",
    "ks:ks_pop":137,
    "ks:ks_type":"VILLAGE",
    "name:eng_x_preferred":[
        "Simgoan"
    ],
    "wof:name":"Simgoan",
    "wof:placetype":"locality",
    "wof:population":137
},
  "geometry": {"coordinates":[79.16919,29.880253],"type":"Point"}
}