{
  "type": "Feature",
  "properties": {
    "iso:country":"IN",
    "ks:ks_name":"Jamadar F",
    "ks:ks_pop":431,
    "ks:ks_type":"HABITATION",
    "ks:ks_uagg_main":0,
    "name:eng_x_preferred":[
        "Jamadar F"
    ],
    "wof:name":"Jamadar F",
    "wof:placetype":"neighbourhood",
    "wof:population":431
},
  "geometry": {"coordinates":[73.36538899999999,20.741778],"type":"Point"}
}