{
  "type": "Feature",
  "properties": {
    "gn:admin1_code":"36",
    "gn:admin2_code":"152.0",
    "gn:asciiname":"Gangaura",
    "gn:country_code":"IN",
    "gn:dem":152,
    "gn:feature_class":"P",
    "gn:feature_code":"PPL",
    "gn:name":"Gangaura",
    "gn:population":0,
    "gn:timezone":"Asia/Kolkata",
    "iso:country":"IN",
    "wof:name":"Gangaura",
    "wof:placetype":"locality"
},
  "geometry": {"coordinates":[79.42364999999999,27.73839000000001],"type":"Point"}
}