{
  "type": "Feature",
  "properties": {
    "gn:admin1_code":"19.0",
    "gn:admin2_code":"584.0",
    "gn:asciiname":"Achalu",
    "gn:country_code":"IN",
    "gn:dem":702,
    "gn:feature_class":"P",
    "gn:feature_code":"PPL",
    "gn:name":"Achalu",
    "gn:population":0,
    "gn:timezone":"Asia/Kolkata",
    "iso:country":"IN",
    "name:fas_x_preferred":[
        "\u0627\u0686\u0627\u0644\u0648"
    ],
    "wof:name":"Achalu",
    "wof:placetype":"locality"
},
  "geometry": {"coordinates":[77.36336999999997,12.47556],"type":"Point"}
}