{
  "type": "Feature",
  "properties": {
    "gn:admin1_code":"10",
    "gn:admin2_code":"87.0",
    "gn:asciiname":"Sikrawa Ka Nagla",
    "gn:country_code":"IN",
    "gn:dem":191,
    "gn:feature_class":"P",
    "gn:feature_code":"PPL",
    "gn:name":"Sikr\u0101wa Ka Nagla",
    "gn:population":0,
    "gn:timezone":"Asia/Kolkata",
    "iso:country":"IN",
    "wof:name":"Sikrawa Ka Nagla",
    "wof:placetype":"neighbourhood"
},
  "geometry": {"coordinates":[77.13448,27.95584],"type":"Point"}
}