{
  "type": "Feature",
  "properties": {
    "iso:country":"IN",
    "ks:ks_alt_nam":"Elluparai ADC",
    "ks:ks_name":"Elluparai Adc",
    "ks:ks_pop":489,
    "ks:ks_type":"HABITATION",
    "name:eng_x_preferred":[
        "Elluparai Adc"
    ],
    "wof:name":"Elluparai Adc",
    "wof:placetype":"locality",
    "wof:population":489
},
  "geometry": {"coordinates":[79.03648,12.47196],"type":"Point"}
}