{
  "type": "Feature",
  "properties": {
    "gn:admin1_code":"19.0",
    "gn:admin2_code":"564.0",
    "gn:asciiname":"Suriihalli",
    "gn:country_code":"IN",
    "gn:dem":539,
    "gn:feature_class":"P",
    "gn:feature_code":"PPL",
    "gn:name":"Suriihalli",
    "gn:population":0,
    "gn:timezone":"Asia/Kolkata",
    "iso:country":"IN",
    "wof:name":"Suriihalli",
    "wof:placetype":"locality"
},
  "geometry": {"coordinates":[75.33145999999998,14.85585],"type":"Point"}
}