{
  "type": "Feature",
  "properties": {
    "iso:country":"IN",
    "ks:ks_name":"Doomana",
    "ks:ks_pop":29,
    "ks:ks_type":"HABITATION",
    "name:eng_x_preferred":[
        "Doomana"
    ],
    "wof:name":"Doomana",
    "wof:placetype":"locality",
    "wof:population":29
},
  "geometry": {"coordinates":[80.14067900000001,29.51387],"type":"Point"}
}