{
  "type": "Feature",
  "properties": {
    "iso:country":"IN",
    "ks:ks_alt_nam":"kotekoppa",
    "ks:ks_name":"Kotekoppa",
    "ks:ks_pop":59,
    "ks:ks_type":"HABITATION",
    "name:eng_x_preferred":[
        "Kotekoppa"
    ],
    "wof:name":"Kotekoppa",
    "wof:placetype":"locality",
    "wof:population":59
},
  "geometry": {"coordinates":[74.840701,14.70706],"type":"Point"}
}