{
  "type": "Feature",
  "properties": {
    "gn:admin1_code":"35.0",
    "gn:admin2_code":"465.0",
    "gn:asciiname":"Bhanpura",
    "gn:country_code":"IN",
    "gn:dem":281,
    "gn:feature_class":"P",
    "gn:feature_code":"PPL",
    "gn:name":"Bh\u0101npura",
    "gn:population":0,
    "gn:timezone":"Asia/Kolkata",
    "iso:country":"IN",
    "name:ben_x_preferred":[
        "\u09ad\u09be\u09a8\u09aa\u09c1\u09b0\u09be"
    ],
    "name:bpy_x_preferred":[
        "\u09ad\u09be\u09a8\u09aa\u09c1\u09b0\u09be"
    ],
    "name:ceb_x_preferred":[
        "Bh\u0101npura"
    ],
    "name:deu_x_preferred":[
        "Bhanpura"
    ],
    "name:ind_x_preferred":[
        "Bhanpura"
    ],
    "name:ita_x_preferred":[
        "Bhanpura"
    ],
    "name:jpn_x_preferred":[
        "\u30d0\u30fc\u30f3\u30d7\u30e9"
    ],
    "name:mlg_x_preferred":[
        "Bhanpura"
    ],
    "name:msa_x_preferred":[
        "Bhanpura"
    ],
    "name:new_x_preferred":[
        "\u092d\u0928\u092a\u0941\u0930\u093e"
    ],
    "name:nld_x_preferred":[
        "Bhanpura"
    ],
    "name:por_x_preferred":[
        "Bhanpura"
    ],
    "name:spa_x_preferred":[
        "Bhanpura"
    ],
    "name:swe_x_preferred":[
        "Bh\u0101npura"
    ],
    "name:vie_x_preferred":[
        "Bhanpura"
    ],
    "name:zho_x_preferred":[
        "\u73ed\u666e\u62c9"
    ],
    "wof:name":"Bhanpura",
    "wof:placetype":"locality"
},
  "geometry": {"coordinates":[74.56115,22.34748],"type":"Point"}
}