{
  "type": "Feature",
  "properties": {
    "gn:admin1_code":"25.0",
    "gn:admin2_code":"611.0",
    "gn:asciiname":"Sholurkokal",
    "gn:country_code":"IN",
    "gn:dem":1896,
    "gn:feature_class":"P",
    "gn:feature_code":"PPL",
    "gn:name":"Sh\u014dl\u016brkokal",
    "gn:population":0,
    "gn:timezone":"Asia/Kolkata",
    "iso:country":"IN",
    "wof:name":"Sholurkokal",
    "wof:placetype":"locality"
},
  "geometry": {"coordinates":[76.64376,11.48622],"type":"Point"}
}