{
  "type": "Feature",
  "properties": {
    "gn:admin1_code":"2.0",
    "gn:admin2_code":"542.0",
    "gn:asciiname":"Bommidalapeta",
    "gn:country_code":"IN",
    "gn:dem":27,
    "gn:feature_class":"P",
    "gn:feature_code":"PPL",
    "gn:name":"Bommidalapeta",
    "gn:population":0,
    "gn:timezone":"Asia/Kolkata",
    "iso:country":"IN",
    "ks:ks_name":"Bommidalapeta",
    "ks:ks_pop":80,
    "ks:ks_type":"HABITATION",
    "ks:ks_uagg_main":0,
    "name:eng_x_preferred":[
        "Bommidalapeta"
    ],
    "wof:name":"Bommidalapeta",
    "wof:placetype":"neighbourhood",
    "wof:population":80
},
  "geometry": {"coordinates":[83.885604,18.377331],"type":"Point"}
}