{
  "type": "Feature",
  "properties": {
    "gn:admin1_code":"36",
    "gn:admin2_code":"154.0",
    "gn:asciiname":"Baraiya Pind",
    "gn:country_code":"IN",
    "gn:dem":126,
    "gn:feature_class":"P",
    "gn:feature_code":"PPL",
    "gn:name":"Baraiya Pind",
    "gn:population":0,
    "gn:timezone":"Asia/Kolkata",
    "iso:country":"IN",
    "name:und_x_variant":[
        "Garhi"
    ],
    "wof:name":"Baraiya Pind",
    "wof:placetype":"neighbourhood"
},
  "geometry": {"coordinates":[81.15177,27.6577],"type":"Point"}
}