{
  "type": "Feature",
  "properties": {
    "gn:admin1_code":"11.0",
    "gn:admin2_code":"33.0",
    "gn:asciiname":"Kalwan",
    "gn:country_code":"IN",
    "gn:dem":2054,
    "gn:feature_class":"P",
    "gn:feature_code":"PPL",
    "gn:name":"Kalw\u0101n",
    "gn:population":0,
    "gn:timezone":"Asia/Kolkata",
    "iso:country":"IN",
    "name:fas_x_preferred":[
        "\u06a9\u0627\u0644\u0648\u0627\u0646"
    ],
    "name:guj_x_preferred":[
        "\u0a95\u0ab3\u0ab5\u0aa3"
    ],
    "wof:name":"Kalwan",
    "wof:placetype":"locality"
},
  "geometry": {"coordinates":[77.36194999999999,31.20369],"type":"Point"}
}