{
  "type": "Feature",
  "properties": {
    "iso:country":"IN",
    "ks:ks_name":"Thar Laxmi Narayan",
    "ks:ks_pop":344,
    "ks:ks_type":"HABITATION",
    "name:eng_x_preferred":[
        "Thar Laxmi Narayan"
    ],
    "wof:name":"Thar Laxmi Narayan",
    "wof:placetype":"locality",
    "wof:population":344
},
  "geometry": {"coordinates":[78.357207,27.06405],"type":"Point"}
}