{
  "type": "Feature",
  "properties": {
    "iso:country":"IN",
    "ks:ks_alt_nam":"RAINIDAND",
    "ks:ks_name":"Rainidand",
    "ks:ks_pop":131,
    "ks:ks_type":"HABITATION",
    "name:eng_x_preferred":[
        "Rainidand"
    ],
    "wof:name":"Rainidand",
    "wof:placetype":"locality",
    "wof:population":131
},
  "geometry": {"coordinates":[83.995671,22.817552],"type":"Point"}
}