{
  "type": "Feature",
  "properties": {
    "iso:country":"IN",
    "ks:ks_name":"Khadakval",
    "ks:ks_pop":2744,
    "ks:ks_type":"VILLAGE",
    "name:eng_x_preferred":[
        "Khadakval"
    ],
    "wof:name":"Khadakval",
    "wof:placetype":"locality",
    "wof:population":2744
},
  "geometry": {"coordinates":[73.21665,20.301287],"type":"Point"}
}