{
  "type": "Feature",
  "properties": {
    "iso:country":"IN",
    "ks:ks_name":"Kadingia",
    "ks:ks_pop":191,
    "ks:ks_type":"VILLAGE",
    "name:eng_x_preferred":[
        "Kadingia"
    ],
    "wof:name":"Kadingia",
    "wof:placetype":"locality",
    "wof:population":191
},
  "geometry": {"coordinates":[84.280641,20.005161],"type":"Point"}
}