{
  "type": "Feature",
  "properties": {
    "gn:admin1_code":"36.0",
    "gn:admin2_code":"150.0",
    "gn:asciiname":"Rampuria Taluka Budhauli",
    "gn:country_code":"IN",
    "gn:dem":166,
    "gn:feature_class":"P",
    "gn:feature_code":"PPL",
    "gn:name":"Rampuria Taluka Budhauli",
    "gn:population":0,
    "gn:timezone":"Asia/Kolkata",
    "iso:country":"IN",
    "wof:name":"Rampuria Taluka Budhauli",
    "wof:placetype":"locality"
},
  "geometry": {"coordinates":[79.65899999999998,28.24197],"type":"Point"}
}