{
  "type": "Feature",
  "properties": {
    "iso:country":"IN",
    "ks:ks_name":"Manuh Pura",
    "ks:ks_pop":53,
    "ks:ks_type":"VILLAGE",
    "name:eng_x_preferred":[
        "Manuh Pura"
    ],
    "wof:name":"Manuh Pura",
    "wof:placetype":"locality",
    "wof:population":53
},
  "geometry": {"coordinates":[92.61203399999999,26.251839],"type":"Point"}
}