{
  "type": "Feature",
  "properties": {
    "gn:admin1_code":"12.0",
    "gn:admin2_code":"006",
    "gn:asciiname":"Mangalnar",
    "gn:country_code":"IN",
    "gn:dem":1409,
    "gn:feature_class":"P",
    "gn:feature_code":"PPL",
    "gn:name":"Mangaln\u0101r",
    "gn:population":0,
    "gn:timezone":"Asia/Kolkata",
    "iso:country":"IN",
    "wof:name":"Mangalnar",
    "wof:placetype":"locality"
},
  "geometry": {"coordinates":[74.24129000000001,33.48639],"type":"Point"}
}