{
  "type": "Feature",
  "properties": {
    "gn:admin1_code":"34.0",
    "gn:admin2_code":"204.0",
    "gn:asciiname":"Gaighat",
    "gn:country_code":"IN",
    "gn:dem":72,
    "gn:feature_class":"P",
    "gn:feature_code":"PPL",
    "gn:name":"G\u0101igh\u0101t",
    "gn:population":0,
    "gn:timezone":"Asia/Kolkata",
    "iso:country":"IN",
    "ks:ks_name":"Gay Ghat",
    "ks:ks_pop":1920,
    "ks:ks_type":"VILLAGE",
    "ks:ks_uagg_main":0,
    "name:eng_x_preferred":[
        "Gay Ghat"
    ],
    "wof:name":"Gay Ghat",
    "wof:placetype":"neighbourhood",
    "wof:population":1920
},
  "geometry": {"coordinates":[84.760214,26.599827],"type":"Point"}
}