{
  "type": "Feature",
  "properties": {
    "iso:country":"IN",
    "ks:ks_name":"North River Tola",
    "ks:ks_pop":533,
    "ks:ks_type":"HABITATION",
    "name:eng_x_preferred":[
        "North River Tola"
    ],
    "wof:name":"North River Tola",
    "wof:placetype":"locality",
    "wof:population":533
},
  "geometry": {"coordinates":[84.482,26.6055],"type":"Point"}
}