{
  "type": "Feature",
  "properties": {
    "iso:country":"IN",
    "ks:ks_name":"Ellampalayam",
    "ks:ks_pop":205,
    "ks:ks_type":"HABITATION",
    "ks:ks_uagg_main":0,
    "name:eng_x_preferred":[
        "Ellampalayam"
    ],
    "wof:name":"Ellampalayam",
    "wof:placetype":"neighbourhood",
    "wof:population":205
},
  "geometry": {"coordinates":[77.59844,11.623931],"type":"Point"}
}