{
  "type": "Feature",
  "properties": {
    "gn:admin1_code":"12.0",
    "gn:admin2_code":"16.0",
    "gn:asciiname":"Sinbhal",
    "gn:country_code":"IN",
    "gn:dem":2256,
    "gn:feature_class":"P",
    "gn:feature_code":"PPL",
    "gn:name":"S\u012bnbhal",
    "gn:population":0,
    "gn:timezone":"Asia/Kolkata",
    "iso:country":"IN",
    "wof:name":"Sinbhal",
    "wof:placetype":"locality"
},
  "geometry": {"coordinates":[75.34409000000002,33.31741],"type":"Point"}
}