{
  "type": "Feature",
  "properties": {
    "iso:country":"IN",
    "ks:ks_name":"Baheratari",
    "ks:ks_pop":0,
    "ks:ks_type":"VILLAGE",
    "name:eng_x_preferred":[
        "Baheratari"
    ],
    "wof:name":"Baheratari",
    "wof:placetype":"locality",
    "wof:population":0
},
  "geometry": {"coordinates":[86.209727,24.815519],"type":"Point"}
}