{
  "type": "Feature",
  "properties": {
    "iso:country":"IN",
    "ks:ks_name":"Baghad Mal.",
    "ks:ks_pop":409,
    "ks:ks_type":"VILLAGE",
    "name:eng_x_preferred":[
        "Baghad Mal."
    ],
    "wof:name":"Baghad Mal.",
    "wof:placetype":"locality",
    "wof:population":409
},
  "geometry": {"coordinates":[81.120256,23.19767],"type":"Point"}
}