{
  "type": "Feature",
  "properties": {
    "iso:country":"IN",
    "ks:ks_name":"Biginimul",
    "ks:ks_pop":92,
    "ks:ks_type":"HABITATION",
    "name:eng_x_preferred":[
        "Biginimul"
    ],
    "wof:name":"Biginimul",
    "wof:placetype":"locality",
    "wof:population":92
},
  "geometry": {"coordinates":[86.28608,20.529258],"type":"Point"}
}