{
  "type": "Feature",
  "properties": {
    "iso:country":"IN",
    "ks:ks_name":"Trichimkalipandoba Pt-ii",
    "ks:ks_pop":263,
    "ks:ks_type":"VILLAGE",
    "name:eng_x_preferred":[
        "Trichimkalipandoba Pt-ii"
    ],
    "wof:name":"Trichimkalipandoba Pt-ii",
    "wof:placetype":"locality",
    "wof:population":263
},
  "geometry": {"coordinates":[90.422529,26.045659],"type":"Point"}
}