{
  "type": "Feature",
  "properties": {
    "iso:country":"IN",
    "ks:ks_alt_nam":"Dakshin kodaili",
    "ks:ks_name":"Dakshin Kodaili",
    "ks:ks_pop":51,
    "ks:ks_type":"HABITATION",
    "name:eng_x_preferred":[
        "Dakshin Kodaili"
    ],
    "wof:name":"Dakshin Kodaili",
    "wof:placetype":"locality",
    "wof:population":51
},
  "geometry": {"coordinates":[81.82351300000001,26.414194],"type":"Point"}
}