{
  "type": "Feature",
  "properties": {
    "iso:country":"IN",
    "ks:ks_name":"Asanbani",
    "ks:ks_pop":498,
    "ks:ks_type":"VILLAGE",
    "name:eng_x_preferred":[
        "Asanbani"
    ],
    "wof:name":"Asanbani",
    "wof:placetype":"locality",
    "wof:population":498
},
  "geometry": {"coordinates":[86.560125,22.319643],"type":"Point"}
}