{
  "type": "Feature",
  "properties": {
    "gn:admin1_code":"16.0",
    "gn:admin2_code":"515.0",
    "gn:asciiname":"Sarai",
    "gn:country_code":"IN",
    "gn:dem":710,
    "gn:feature_class":"P",
    "gn:feature_code":"PPL",
    "gn:name":"Sar\u0101i",
    "gn:population":0,
    "gn:timezone":"Asia/Kolkata",
    "iso:country":"IN",
    "name:cat_x_preferred":[
        "Sarai"
    ],
    "name:ceb_x_preferred":[
        "Sarai"
    ],
    "name:deu_x_preferred":[
        "Sarai"
    ],
    "name:fra_x_preferred":[
        "Sarai"
    ],
    "name:ind_x_preferred":[
        "Sarai"
    ],
    "name:jpn_x_preferred":[
        "\u30b5\u30e9\u30a4"
    ],
    "name:nld_x_preferred":[
        "Sarai"
    ],
    "name:swe_x_preferred":[
        "Sarai"
    ],
    "name:tgl_x_preferred":[
        "Sarai"
    ],
    "name:und_x_variant":[
        "Sar\u0101i",
        "In\u0101mi"
    ],
    "wof:name":"Sarai",
    "wof:placetype":"locality"
},
  "geometry": {"coordinates":[75.21769,20.01657],"type":"Point"}
}