{
  "type": "Feature",
  "properties": {
    "gn:admin1_code":"36",
    "gn:admin2_code":"134.0",
    "gn:asciiname":"Alupur",
    "gn:country_code":"IN",
    "gn:dem":260,
    "gn:feature_class":"P",
    "gn:feature_code":"PPL",
    "gn:name":"\u0100l\u016bpur",
    "gn:population":0,
    "gn:timezone":"Asia/Kolkata",
    "iso:country":"IN",
    "ks:ks_alt_nam":"\u0100l\u016bpur",
    "ks:ks_name":"Alupur",
    "ks:ks_type":"VILLAGE",
    "name:eng_x_preferred":[
        "Alupur"
    ],
    "name:eng_x_variant":[
        "\u0100l\u016bpur"
    ],
    "name:und_x_variant":[
        "\u0100l\u016bpur",
        "R\u0101j\u0101r\u0101mpur Fazal"
    ],
    "wof:name":"Alupur",
    "wof:placetype":"locality"
},
  "geometry": {"coordinates":[78.275576,29.600722],"type":"Point"}
}