{
  "type": "Feature",
  "properties": {
    "gn:admin1_code":"36",
    "gn:admin2_code":"134.0",
    "gn:asciiname":"Alupur",
    "gn:country_code":"IN",
    "gn:dem":260,
    "gn:feature_class":"P",
    "gn:feature_code":"PPL",
    "gn:name":"\u0100l\u016bpur",
    "gn:population":0,
    "gn:timezone":"Asia/Kolkata",
    "iso:country":"IN",
    "name:und_x_variant":[
        "\u0100l\u016bpur",
        "R\u0101j\u0101r\u0101mpur Fazal"
    ],
    "wof:name":"Alupur",
    "wof:placetype":"locality"
},
  "geometry": {"coordinates":[78.27558000000001,29.60072000000001],"type":"Point"}
}