{
  "type": "Feature",
  "properties": {
    "iso:country":"IN",
    "ks:ks_name":"Bhujbalmalavi",
    "ks:ks_pop":103,
    "ks:ks_type":"HABITATION",
    "ks:ks_uagg_main":0,
    "name:eng_x_preferred":[
        "Bhujbalmalavi"
    ],
    "wof:name":"Bhujbalmalavi",
    "wof:placetype":"neighbourhood",
    "wof:population":103
},
  "geometry": {"coordinates":[74.605463,17.78926],"type":"Point"}
}