{
  "type": "Feature",
  "properties": {
    "iso:country":"IN",
    "ks:ks_alt_nam":"Motibari Ram tola",
    "ks:ks_name":"Motibari Ram Tola",
    "ks:ks_pop":496,
    "ks:ks_type":"HABITATION",
    "name:eng_x_preferred":[
        "Motibari Ram Tola"
    ],
    "wof:name":"Motibari Ram Tola",
    "wof:placetype":"locality",
    "wof:population":496
},
  "geometry": {"coordinates":[86.83869199999999,25.726921],"type":"Point"}
}