{
  "type": "Feature",
  "properties": {
    "iso:country":"IN",
    "ks:ks_name":"Pokalagi Pt V",
    "ks:ks_pop":2050,
    "ks:ks_type":"VILLAGE",
    "name:eng_x_preferred":[
        "Pokalagi Pt V"
    ],
    "wof:name":"Pokalagi Pt V",
    "wof:placetype":"locality",
    "wof:population":2050
},
  "geometry": {"coordinates":[89.76525700000001,26.257002],"type":"Point"}
}