{
  "type": "Feature",
  "properties": {
    "gn:admin1_code":"34.0",
    "gn:admin2_code":"240.0",
    "gn:asciiname":"Kansupur",
    "gn:country_code":"IN",
    "gn:dem":81,
    "gn:feature_class":"P",
    "gn:feature_code":"PPL",
    "gn:name":"Kansupur",
    "gn:population":0,
    "gn:timezone":"Asia/Kolkata",
    "iso:country":"IN",
    "ks:ks_name":"Kansupur",
    "ks:ks_pop":535,
    "ks:ks_type":"VILLAGE",
    "name:eng_x_preferred":[
        "Kansupur"
    ],
    "wof:name":"Kansupur",
    "wof:placetype":"locality",
    "wof:population":535
},
  "geometry": {"coordinates":[84.63896,25.212833],"type":"Point"}
}