{
  "type": "Feature",
  "properties": {
    "iso:country":"IN",
    "ks:ks_alt_nam":"R\u0101libera",
    "ks:ks_name":"Ralibera",
    "ks:ks_pop":221,
    "ks:ks_type":"VILLAGE",
    "name:eng_x_preferred":[
        "Ralibera"
    ],
    "name:eng_x_variant":[
        "R\u0101libera"
    ],
    "wof:name":"Ralibera",
    "wof:placetype":"locality",
    "wof:population":221
},
  "geometry": {"coordinates":[85.995542,22.132881],"type":"Point"}
}