{
  "type": "Feature",
  "properties": {
    "iso:country":"IN",
    "ks:ks_name":"Rampura",
    "ks:ks_pop":649,
    "ks:ks_type":"VILLAGE",
    "name:eng_x_preferred":[
        "Rampura"
    ],
    "wof:name":"Rampura",
    "wof:placetype":"locality",
    "wof:population":649
},
  "geometry": {"coordinates":[72.226311,24.613214],"type":"Point"}
}