{
  "type": "Feature",
  "properties": {
    "iso:country":"IN",
    "ks:ks_name":"Kuvale",
    "ks:ks_pop":1301,
    "ks:ks_type":"VILLAGE",
    "name:eng_x_preferred":[
        "Kuvale"
    ],
    "wof:name":"Kuvale",
    "wof:placetype":"locality",
    "wof:population":1301
},
  "geometry": {"coordinates":[73.60364199999999,16.313461],"type":"Point"}
}