{
  "type": "Feature",
  "properties": {
    "iso:country":"IN",
    "ks:ks_name":"Tentulipasi",
    "ks:ks_type":"VILLAGE",
    "name:eng_x_preferred":[
        "Tentulipasi"
    ],
    "wof:name":"Tentulipasi",
    "wof:placetype":"locality"
},
  "geometry": {"coordinates":[85.183486,20.746438],"type":"Point"}
}