{
  "type": "Feature",
  "properties": {
    "iso:country":"IN",
    "ks:ks_name":"Notelia",
    "ks:ks_pop":1216,
    "ks:ks_type":"HABITATION",
    "name:eng_x_preferred":[
        "Notelia"
    ],
    "wof:name":"Notelia",
    "wof:placetype":"locality",
    "wof:population":1216
},
  "geometry": {"coordinates":[92.98021799999999,26.723561],"type":"Point"}
}