{
  "type": "Feature",
  "properties": {
    "iso:country":"IN",
    "ks:ks_name":"Naikarkeri",
    "ks:ks_pop":82,
    "ks:ks_type":"HABITATION",
    "name:eng_x_preferred":[
        "Naikarkeri"
    ],
    "wof:name":"Naikarkeri",
    "wof:placetype":"locality",
    "wof:population":82
},
  "geometry": {"coordinates":[74.4953,14.709783],"type":"Point"}
}