{
  "type": "Feature",
  "properties": {
    "gn:admin1_code":"19",
    "gn:admin2_code":"580.0",
    "gn:asciiname":"Sagar",
    "gn:country_code":"IN",
    "gn:dem":420,
    "gn:feature_class":"P",
    "gn:feature_code":"PPL",
    "gn:name":"S\u0101gar",
    "gn:population":0,
    "gn:timezone":"Asia/Kolkata",
    "iso:country":"IN",
    "name:ara_x_preferred":[
        "\u0633\u0627\u062c\u0627\u0631"
    ],
    "name:ben_bn_x_preferred":[
        "\u09b8\u09be\u0997\u09b0"
    ],
    "name:ben_in_x_preferred":[
        "\u09b8\u09be\u0997\u09b0"
    ],
    "name:ceb_x_preferred":[
        "Sagar"
    ],
    "name:deu_x_preferred":[
        "Sagar"
    ],
    "name:fas_x_preferred":[
        "\u0633\u0627\u063a\u0631"
    ],
    "name:guj_x_preferred":[
        "\u0ab8\u0abe\u0a97\u0ab0"
    ],
    "name:heb_x_preferred":[
        "\u05e1\u05d2\u05d0\u05e8"
    ],
    "name:hin_x_preferred":[
        "\u0938\u093e\u0917\u0930"
    ],
    "name:hun_x_preferred":[
        "Sagar"
    ],
    "name:kan_x_preferred":[
        "\u0cb8\u0cbe\u0c97\u0cb0\u0ccd"
    ],
    "name:mal_x_preferred":[
        "\u0d38\u0d3e\u0d17\u0d7c"
    ],
    "name:mar_x_preferred":[
        "\u0938\u093e\u0917\u0930"
    ],
    "name:nld_x_preferred":[
        "Sagar"
    ],
    "name:pan_x_preferred":[
        "\u0a38\u0a3e\u0a17\u0a30"
    ],
    "name:rus_x_preferred":[
        "\u0421\u0435\u0439\u0433\u0430\u0440"
    ],
    "name:swe_x_preferred":[
        "Sagar"
    ],
    "name:tam_x_preferred":[
        "\u0b9a\u0bbe\u0b95\u0bb0\u0bcd"
    ],
    "name:tel_x_preferred":[
        "\u0c38\u0c3e\u0c17\u0c30\u0c4d"
    ],
    "name:und_x_variant":[
        "S\u0101gar"
    ],
    "name:urd_x_preferred":[
        "\u0633\u0627\u06af\u0631"
    ],
    "name:vie_x_preferred":[
        "Sagar"
    ],
    "wof:name":"Sagar",
    "wof:placetype":"locality"
},
  "geometry": {"coordinates":[76.80146999999999,16.62486],"type":"Point"}
}