{
  "type": "Feature",
  "properties": {
    "iso:country":"IN",
    "ks:ks_alt_nam":"jamguri",
    "ks:ks_name":"Jamguri",
    "ks:ks_pop":564,
    "ks:ks_type":"HABITATION",
    "name:eng_x_preferred":[
        "Jamguri"
    ],
    "wof:name":"Jamguri",
    "wof:placetype":"locality",
    "wof:population":564
},
  "geometry": {"coordinates":[91.054417,26.626898],"type":"Point"}
}