{
  "type": "Feature",
  "properties": {
    "iso:country":"IN",
    "ks:ks_alt_nam":"MADHYA DWARIKAPUR",
    "ks:ks_name":"Madhya Dwarikapur",
    "ks:ks_pop":150,
    "ks:ks_type":"HABITATION",
    "name:eng_x_preferred":[
        "Madhya Dwarikapur"
    ],
    "wof:name":"Madhya Dwarikapur",
    "wof:placetype":"locality",
    "wof:population":150
},
  "geometry": {"coordinates":[91.60980000000001,23.958757],"type":"Point"}
}