{
  "type": "Feature",
  "properties": {
    "iso:country":"IN",
    "ks:ks_name":"Anudha",
    "ks:ks_pop":545,
    "ks:ks_type":"HABITATION",
    "name:eng_x_preferred":[
        "Anudha"
    ],
    "wof:name":"Anudha",
    "wof:placetype":"locality",
    "wof:population":545
},
  "geometry": {"coordinates":[80.308611,26.365556],"type":"Point"}
}