{
  "type": "Feature",
  "properties": {
    "gn:admin1_code":"35.0",
    "gn:admin2_code":"420.0",
    "gn:asciiname":"Banjaron ka Pura",
    "gn:country_code":"IN",
    "gn:dem":175,
    "gn:feature_class":"P",
    "gn:feature_code":"PPL",
    "gn:name":"Banj\u0101ron ka Pura",
    "gn:population":0,
    "gn:timezone":"Asia/Kolkata",
    "iso:country":"IN",
    "name:eng_x_preferred":[
        "Banj\u0101ron ka Pura"
    ],
    "wof:name":"Banjaron ka Pura",
    "wof:placetype":"locality"
},
  "geometry": {"coordinates":[78.4307,26.29991],"type":"Point"}
}