{
  "type": "Feature",
  "properties": {
    "gn:admin1_code":"35.0",
    "gn:admin2_code":"431.0",
    "gn:asciiname":"Bhanupur",
    "gn:country_code":"IN",
    "gn:dem":516,
    "gn:feature_class":"P",
    "gn:feature_code":"PPL",
    "gn:name":"Bhanupur",
    "gn:population":0,
    "gn:timezone":"Asia/Kolkata",
    "iso:country":"IN",
    "ks:ks_name":"Bhanpura",
    "ks:ks_pop":1326,
    "ks:ks_type":"VILLAGE",
    "name:eng_x_preferred":[
        "Bhanpura"
    ],
    "name:eng_x_variant":[
        "Bhanupur"
    ],
    "wof:name":"Bhanpura",
    "wof:placetype":"locality",
    "wof:population":1326
},
  "geometry": {"coordinates":[80.787795,23.334605],"type":"Point"}
}