{
  "type": "Feature",
  "properties": {
    "gn:admin1_code":"35",
    "gn:admin2_code":"451.0",
    "gn:asciiname":"Premnagar",
    "gn:country_code":"IN",
    "gn:dem":401,
    "gn:feature_class":"P",
    "gn:feature_code":"PPL",
    "gn:name":"Premnagar",
    "gn:population":0,
    "gn:timezone":"Asia/Kolkata",
    "iso:country":"IN",
    "name:ara_x_preferred":[
        "\u0628\u0631\u064a\u0645 \u0646\u0627\u062c\u0627\u0631"
    ],
    "name:ben_bn_x_preferred":[
        "\u09aa\u09cd\u09b0\u09c7\u09ae\u09a8\u0997\u09b0"
    ],
    "name:ben_in_x_preferred":[
        "\u09aa\u09cd\u09b0\u09c7\u09ae\u09a8\u0997\u09b0"
    ],
    "name:guj_x_preferred":[
        "\u0aaa\u0acd\u0ab0\u0ac7\u0aae\u0aa8\u0a97\u0ab0"
    ],
    "name:hin_x_preferred":[
        "\u092a\u094d\u0930\u0947\u092e \u0928\u0917\u0930"
    ],
    "name:kan_x_preferred":[
        "\u0caa\u0ccd\u0cb0\u0cc7\u0cae\u0ccd"
    ],
    "name:mal_x_preferred":[
        "\u0d2a\u0d4d\u0d30\u0d47\u0d02\u0d28\u0d17\u0d7c"
    ],
    "name:mar_x_preferred":[
        "\u092a\u094d\u0930\u0947\u092e\u0928\u0917\u0930"
    ],
    "name:pan_x_preferred":[
        "\u0a2a\u0a30\u0a47\u0a2e\u0a28\u0a17\u0a30"
    ],
    "name:tam_x_preferred":[
        "\u0baa\u0bbf\u0bb0\u0bc7\u0bae\u0bcd\u0ba8\u0b95\u0bb0\u0bcd"
    ],
    "name:tel_x_preferred":[
        "\u0c2a\u0c4d\u0c30\u0c47\u0c2e\u0c4d"
    ],
    "name:urd_x_preferred":[
        "\u067e\u0631\u06cc\u0645 \u0646\u06af\u0631"
    ],
    "wof:name":"Premnagar",
    "wof:placetype":"neighbourhood"
},
  "geometry": {"coordinates":[79.91848,23.15262],"type":"Point"}
}