{
  "type": "Feature",
  "properties": {
    "gn:admin1_code":"11",
    "gn:admin2_code":"27.0",
    "gn:asciiname":"Pasal Har",
    "gn:country_code":"IN",
    "gn:dem":1279,
    "gn:feature_class":"P",
    "gn:feature_code":"PPL",
    "gn:name":"Pasal H\u0101r",
    "gn:population":0,
    "gn:timezone":"Asia/Kolkata",
    "iso:country":"IN",
    "wof:name":"Pasal Har",
    "wof:placetype":"locality"
},
  "geometry": {"coordinates":[76.73206999999999,32.01495999999999],"type":"Point"}
}