{
  "type": "Feature",
  "properties": {
    "iso:country":"IN",
    "ks:ks_name":"Timbholi",
    "ks:ks_pop":340,
    "ks:ks_type":"VILLAGE",
    "name:eng_x_preferred":[
        "Timbholi"
    ],
    "wof:name":"Timbholi",
    "wof:placetype":"locality",
    "wof:population":340
},
  "geometry": {"coordinates":[74.510419,15.378674],"type":"Point"}
}