{
  "type": "Feature",
  "properties": {
    "gn:admin1_code":"24.0",
    "gn:admin2_code":"123.0",
    "gn:asciiname":"Jogion ka Baria",
    "gn:country_code":"IN",
    "gn:dem":553,
    "gn:feature_class":"P",
    "gn:feature_code":"PPL",
    "gn:name":"Jogion ka B\u0101ria",
    "gn:population":0,
    "gn:timezone":"Asia/Kolkata",
    "iso:country":"IN",
    "wof:name":"Jogion ka Baria",
    "wof:placetype":"locality"
},
  "geometry": {"coordinates":[74.15812,25.78325],"type":"Point"}
}