{
  "type": "Feature",
  "properties": {
    "gn:admin1_code":"19.0",
    "gn:admin2_code":"572",
    "gn:asciiname":"Sita Circle",
    "gn:country_code":"IN",
    "gn:dem":889,
    "gn:feature_class":"P",
    "gn:feature_code":"PPL",
    "gn:name":"Sita Circle",
    "gn:population":0,
    "gn:timezone":"Asia/Kolkata",
    "iso:country":"IN",
    "wof:name":"Sita Circle",
    "wof:placetype":"locality"
},
  "geometry": {"coordinates":[77.54852,12.93882],"type":"Point"}
}