{
  "type": "Feature",
  "properties": {
    "iso:country":"IN",
    "ks:ks_name":"Phulboram",
    "ks:ks_pop":217,
    "ks:ks_type":"HABITATION",
    "name:eng_x_preferred":[
        "Phulboram"
    ],
    "wof:name":"Phulboram",
    "wof:placetype":"locality",
    "wof:population":217
},
  "geometry": {"coordinates":[93.534654,25.728414],"type":"Point"}
}