{
  "type": "Feature",
  "properties": {
    "iso:country":"IN",
    "ks:ks_name":"Kadamguda",
    "ks:ks_pop":133,
    "ks:ks_type":"HABITATION",
    "name:eng_x_preferred":[
        "Kadamguda"
    ],
    "wof:name":"Kadamguda",
    "wof:placetype":"locality",
    "wof:population":133
},
  "geometry": {"coordinates":[82.863962,18.672344],"type":"Point"}
}