{
  "type": "Feature",
  "properties": {
    "iso:country":"IN",
    "ks:ks_name":"Vaddivanicheruvu",
    "ks:ks_pop":93,
    "ks:ks_type":"HABITATION",
    "name:eng_x_preferred":[
        "Vaddivanicheruvu"
    ],
    "wof:name":"Vaddivanicheruvu",
    "wof:placetype":"locality",
    "wof:population":93
},
  "geometry": {"coordinates":[78.95149000000001,13.321357],"type":"Point"}
}