{
  "type": "Feature",
  "properties": {
    "gn:admin1_code":"25.0",
    "gn:admin2_code":"630.0",
    "gn:asciiname":"Varasettipatti",
    "gn:country_code":"IN",
    "gn:dem":377,
    "gn:feature_class":"P",
    "gn:feature_code":"PPL",
    "gn:name":"Varasettipatti",
    "gn:population":0,
    "gn:timezone":"Asia/Kolkata",
    "iso:country":"IN",
    "wof:name":"Varasettipatti",
    "wof:placetype":"locality"
},
  "geometry": {"coordinates":[78.44648000000002,12.03041],"type":"Point"}
}