{
  "type": "Feature",
  "properties": {
    "iso:country":"IN",
    "ks:ks_name":"Siddappanakatte",
    "ks:ks_pop":43,
    "ks:ks_type":"VILLAGE",
    "name:eng_x_preferred":[
        "Siddappanakatte"
    ],
    "wof:name":"Siddappanakatte",
    "wof:placetype":"locality",
    "wof:population":43
},
  "geometry": {"coordinates":[77.12296600000001,14.133088],"type":"Point"}
}