{
  "type": "Feature",
  "properties": {
    "iso:country":"IN",
    "ks:ks_name":"Josnadi",
    "ks:ks_pop":313,
    "ks:ks_type":"VILLAGE",
    "name:eng_x_preferred":[
        "Josnadi"
    ],
    "wof:name":"Josnadi",
    "wof:placetype":"locality",
    "wof:population":313
},
  "geometry": {"coordinates":[86.72703300000001,23.754648],"type":"Point"}
}