{
  "type": "Feature",
  "properties": {
    "iso:country":"IN",
    "ks:ks_name":"Sonad",
    "ks:ks_pop":0,
    "ks:ks_type":"VILLAGE",
    "name:eng_x_preferred":[
        "Sonad"
    ],
    "wof:name":"Sonad",
    "wof:placetype":"locality",
    "wof:population":0
},
  "geometry": {"coordinates":[86.443241,23.98826],"type":"Point"}
}