{
  "type": "Feature",
  "properties": {
    "gn:admin1_code":"35.0",
    "gn:admin2_code":"427.0",
    "gn:asciiname":"Sahajpuri Bujurg",
    "gn:country_code":"IN",
    "gn:dem":594,
    "gn:feature_class":"P",
    "gn:feature_code":"PPL",
    "gn:name":"Sahajpuri Bujurg",
    "gn:population":0,
    "gn:timezone":"Asia/Kolkata",
    "iso:country":"IN",
    "wof:name":"Sahajpuri Bujurg",
    "wof:placetype":"locality"
},
  "geometry": {"coordinates":[78.70555,23.59218],"type":"Point"}
}