{
  "type": "Feature",
  "properties": {
    "gn:admin1_code":"36.0",
    "gn:admin2_code":"158.0",
    "gn:asciiname":"Pura Bibi Bakhshan",
    "gn:country_code":"IN",
    "gn:dem":111,
    "gn:feature_class":"P",
    "gn:feature_code":"PPL",
    "gn:name":"Pura B\u012bbi Bakhshan",
    "gn:population":0,
    "gn:timezone":"Asia/Kolkata",
    "iso:country":"IN",
    "wof:name":"Pura Bibi Bakhshan",
    "wof:placetype":"neighbourhood"
},
  "geometry": {"coordinates":[81.53642000000001,26.51258],"type":"Point"}
}