{
  "type": "Feature",
  "properties": {
    "gn:admin1_code":"16.0",
    "gn:admin2_code":"497",
    "gn:asciiname":"Dhadgaon",
    "gn:country_code":"IN",
    "gn:dem":350,
    "gn:feature_class":"P",
    "gn:feature_code":"PPL",
    "gn:name":"Dhadgaon",
    "gn:population":0,
    "gn:timezone":"Asia/Kolkata",
    "iso:country":"IN",
    "name:guj_x_preferred":[
        "\u0a85\u0a95\u0ab0\u0abe\u0aa3\u0ac0 \u0aa4\u0abe\u0ab2\u0ac1\u0a95\u0acb"
    ],
    "name:mar_x_preferred":[
        "\u0905\u0915\u094d\u0930\u093e\u0923\u0940"
    ],
    "wof:name":"Dhadgaon",
    "wof:placetype":"locality"
},
  "geometry": {"coordinates":[74.21805000000001,21.82436],"type":"Point"}
}