{
  "type": "Feature",
  "properties": {
    "iso:country":"IN",
    "ks:ks_name":"Sursundi",
    "ks:ks_pop":774,
    "ks:ks_type":"HABITATION",
    "name:eng_x_preferred":[
        "Sursundi"
    ],
    "wof:name":"Sursundi",
    "wof:placetype":"locality",
    "wof:population":774
},
  "geometry": {"coordinates":[80.236104,20.309018],"type":"Point"}
}