{
  "type": "Feature",
  "properties": {
    "iso:country":"IN",
    "ks:ks_name":"Devali Tarf Khoj",
    "ks:ks_pop":368,
    "ks:ks_type":"HABITATION",
    "name:eng_x_preferred":[
        "Devali Tarf Khoj"
    ],
    "wof:name":"Devali Tarf Khoj",
    "wof:placetype":"locality",
    "wof:population":368
},
  "geometry": {"coordinates":[73.021663,19.662083],"type":"Point"}
}