{
  "type": "Feature",
  "properties": {
    "iso:country":"IN",
    "ks:ks_name":"Kendgare",
    "ks:ks_pop":111,
    "ks:ks_type":"VILLAGE",
    "name:eng_x_preferred":[
        "Kendgare"
    ],
    "wof:name":"Kendgare",
    "wof:placetype":"locality",
    "wof:population":111
},
  "geometry": {"coordinates":[87.525026,23.235614],"type":"Point"}
}