{
  "type": "Feature",
  "properties": {
    "iso:country":"IN",
    "ks:ks_name":"Nagra Kishantola",
    "ks:ks_pop":927,
    "ks:ks_type":"HABITATION",
    "name:eng_x_preferred":[
        "Nagra Kishantola"
    ],
    "wof:name":"Nagra Kishantola",
    "wof:placetype":"locality",
    "wof:population":927
},
  "geometry": {"coordinates":[83.72581700000001,23.734682],"type":"Point"}
}