{
  "type": "Feature",
  "properties": {
    "gn:admin1_code":"16.0",
    "gn:admin2_code":"526",
    "gn:asciiname":"Jamgaon Khurd",
    "gn:country_code":"IN",
    "gn:dem":467,
    "gn:feature_class":"P",
    "gn:feature_code":"PPL",
    "gn:name":"J\u0101mgaon Khurd",
    "gn:population":0,
    "gn:timezone":"Asia/Kolkata",
    "iso:country":"IN",
    "wof:name":"Jamgaon Khurd",
    "wof:placetype":"locality"
},
  "geometry": {"coordinates":[75.68796999999998,17.56786],"type":"Point"}
}