{
  "type": "Feature",
  "properties": {
    "iso:country":"IN",
    "ks:ks_name":"Vadakadu",
    "ks:ks_pop":835,
    "ks:ks_type":"HABITATION",
    "name:eng_x_preferred":[
        "Vadakadu"
    ],
    "wof:name":"Vadakadu",
    "wof:placetype":"locality",
    "wof:population":835
},
  "geometry": {"coordinates":[79.79635399999999,10.401983],"type":"Point"}
}