{
  "type": "Feature",
  "properties": {
    "iso:country":"IN",
    "ks:ks_alt_nam":"Gajrauli",
    "ks:ks_name":"Gajraula",
    "ks:ks_pop":828,
    "ks:ks_type":"VILLAGE",
    "name:eng_x_preferred":[
        "Gajraula"
    ],
    "name:eng_x_variant":[
        "Gajrauli"
    ],
    "wof:name":"Gajraula",
    "wof:placetype":"locality",
    "wof:population":828
},
  "geometry": {"coordinates":[77.985394,29.080391],"type":"Point"}
}