{
  "type": "Feature",
  "properties": {
    "iso:country":"IN",
    "ks:ks_name":"Sundara",
    "ks:ks_pop":800,
    "ks:ks_type":"VILLAGE",
    "name:eng_x_preferred":[
        "Sundara"
    ],
    "wof:name":"Sundara",
    "wof:placetype":"locality",
    "wof:population":800
},
  "geometry": {"coordinates":[73.54294400000001,23.972678],"type":"Point"}
}