{
  "type": "Feature",
  "properties": {
    "iso:country":"IN",
    "ks:ks_name":"Paschim Ankorbari",
    "ks:ks_pop":1643,
    "ks:ks_type":"VILLAGE",
    "ks:ks_uagg_main":0,
    "name:eng_x_preferred":[
        "Paschim Ankorbari"
    ],
    "wof:name":"Paschim Ankorbari",
    "wof:placetype":"neighbourhood",
    "wof:population":1643
},
  "geometry": {"coordinates":[90.496745,26.56939],"type":"Point"}
}