{
  "type": "Feature",
  "properties": {
    "iso:country":"IN",
    "ks:ks_name":"Dadwar Shukul",
    "ks:ks_pop":389,
    "ks:ks_type":"HABITATION",
    "name:eng_x_preferred":[
        "Dadwar Shukul"
    ],
    "wof:name":"Dadwar Shukul",
    "wof:placetype":"locality",
    "wof:population":389
},
  "geometry": {"coordinates":[82.92742699999999,27.13543],"type":"Point"}
}