{
  "type": "Feature",
  "properties": {
    "gn:admin1_code":"39.0",
    "gn:admin2_code":"61.0",
    "gn:asciiname":"Kaphaltanda",
    "gn:country_code":"IN",
    "gn:dem":1331,
    "gn:feature_class":"P",
    "gn:feature_code":"PPL",
    "gn:name":"Kaphalt\u0101nda",
    "gn:population":0,
    "gn:timezone":"Asia/Kolkata",
    "iso:country":"IN",
    "ks:ks_alt_nam":"Kaphalt\u0101nda",
    "ks:ks_name":"Kaphaltanda",
    "ks:ks_type":"VILLAGE",
    "name:eng_x_preferred":[
        "Kaphaltanda"
    ],
    "name:eng_x_variant":[
        "Kaphalt\u0101nda"
    ],
    "wof:name":"Kaphaltanda",
    "wof:placetype":"locality"
},
  "geometry": {"coordinates":[79.046229,29.682054],"type":"Point"}
}