{
  "type": "Feature",
  "properties": {
    "gn:admin1_code":"39.0",
    "gn:admin2_code":"61.0",
    "gn:asciiname":"Kaphaltanda",
    "gn:country_code":"IN",
    "gn:dem":1331,
    "gn:feature_class":"P",
    "gn:feature_code":"PPL",
    "gn:name":"Kaphalt\u0101nda",
    "gn:population":0,
    "gn:timezone":"Asia/Kolkata",
    "iso:country":"IN",
    "wof:name":"Kaphaltanda",
    "wof:placetype":"locality"
},
  "geometry": {"coordinates":[79.04623000000002,29.68205],"type":"Point"}
}