{
  "type": "Feature",
  "properties": {
    "iso:country":"IN",
    "ks:ks_alt_nam":"eranjimukku",
    "ks:ks_name":"Eranjimukku",
    "ks:ks_pop":356,
    "ks:ks_type":"HABITATION",
    "name:eng_x_preferred":[
        "Eranjimukku"
    ],
    "wof:name":"Eranjimukku",
    "wof:placetype":"locality",
    "wof:population":356
},
  "geometry": {"coordinates":[75.67792300000001,11.638369],"type":"Point"}
}