{
  "type": "Feature",
  "properties": {
    "iso:country":"IN",
    "ks:ks_alt_nam":"Chari pada",
    "ks:ks_name":"Chari Pada",
    "ks:ks_pop":298,
    "ks:ks_type":"HABITATION",
    "name:eng_x_preferred":[
        "Chari Pada"
    ],
    "wof:name":"Chari Pada",
    "wof:placetype":"locality",
    "wof:population":298
},
  "geometry": {"coordinates":[73.276,20.406278],"type":"Point"}
}