{
  "type": "Feature",
  "properties": {
    "iso:country":"IN",
    "ks:ks_name":"Etapada",
    "ks:ks_pop":237,
    "ks:ks_type":"VILLAGE",
    "name:eng_x_preferred":[
        "Etapada"
    ],
    "wof:name":"Etapada",
    "wof:placetype":"locality",
    "wof:population":237
},
  "geometry": {"coordinates":[86.20989400000001,20.224351],"type":"Point"}
}