{
  "type": "Feature",
  "properties": {
    "gn:admin1_code":"30.0",
    "gn:admin2_code":"255",
    "gn:asciiname":"Hachi",
    "gn:country_code":"IN",
    "gn:dem":843,
    "gn:feature_class":"P",
    "gn:feature_code":"PPL",
    "gn:name":"Hachi",
    "gn:population":0,
    "gn:timezone":"Asia/Kolkata",
    "iso:country":"IN",
    "name:fra_x_preferred":[
        "Hachi"
    ],
    "name:vie_x_preferred":[
        "Hachi"
    ],
    "wof:name":"Hachi",
    "wof:placetype":"locality"
},
  "geometry": {"coordinates":[94.01848,27.7719],"type":"Point"}
}