{
  "type": "Feature",
  "properties": {
    "iso:country":"IN",
    "ks:ks_name":"Shibau",
    "ks:ks_pop":113,
    "ks:ks_type":"VILLAGE",
    "name:eng_x_preferred":[
        "Shibau"
    ],
    "wof:name":"Shibau",
    "wof:placetype":"locality",
    "wof:population":113
},
  "geometry": {"coordinates":[77.938975,30.644608],"type":"Point"}
}