{
  "type": "Feature",
  "properties": {
    "gn:admin1_code":"11.0",
    "gn:admin2_code":"32.0",
    "gn:asciiname":"Chauki Shalna",
    "gn:country_code":"IN",
    "gn:dem":1595,
    "gn:feature_class":"P",
    "gn:feature_code":"PPL",
    "gn:name":"Chauki Sh\u0101lna",
    "gn:population":0,
    "gn:timezone":"Asia/Kolkata",
    "iso:country":"IN",
    "wof:name":"Chauki Shalna",
    "wof:placetype":"locality"
},
  "geometry": {"coordinates":[77.67536,30.60445],"type":"Point"}
}