{
  "type": "Feature",
  "properties": {
    "iso:country":"IN",
    "ks:ks_name":"Khori",
    "ks:ks_pop":1065,
    "ks:ks_type":"VILLAGE",
    "name:eng_x_preferred":[
        "Khori"
    ],
    "wof:name":"Khori",
    "wof:placetype":"locality",
    "wof:population":1065
},
  "geometry": {"coordinates":[77.23284700000001,23.283299],"type":"Point"}
}