{
  "type": "Feature",
  "properties": {
    "iso:country":"IN",
    "ks:ks_alt_nam":"meenpannai colony",
    "ks:ks_name":"Meenpannai Colony",
    "ks:ks_pop":396,
    "ks:ks_type":"HABITATION",
    "ks:ks_uagg_main":0,
    "name:eng_x_preferred":[
        "Meenpannai Colony"
    ],
    "wof:name":"Meenpannai Colony",
    "wof:placetype":"neighbourhood",
    "wof:population":396
},
  "geometry": {"coordinates":[77.594195,10.050317],"type":"Point"}
}