{
  "type": "Feature",
  "properties": {
    "iso:country":"IN",
    "ks:ks_name":"Koti",
    "ks:ks_pop":617,
    "ks:ks_type":"VILLAGE",
    "name:eng_x_preferred":[
        "Koti"
    ],
    "wof:name":"Koti",
    "wof:placetype":"locality",
    "wof:population":617
},
  "geometry": {"coordinates":[79.282577,30.160736],"type":"Point"}
}