{
  "type": "Feature",
  "properties": {
    "gn:admin1_code":"2",
    "gn:admin2_code":"545.0",
    "gn:asciiname":"Krishnavaram",
    "gn:country_code":"IN",
    "gn:dem":43,
    "gn:feature_class":"P",
    "gn:feature_code":"PPL",
    "gn:name":"Krishnavaram",
    "gn:population":0,
    "gn:timezone":"Asia/Kolkata",
    "iso:country":"IN",
    "name:hin_x_preferred":[
        "\u0915\u0943\u0937\u094d\u0923\u0935\u0930\u0902"
    ],
    "name:new_x_preferred":[
        "\u0915\u0943\u0937\u094d\u0923\u0935\u0930\u0902"
    ],
    "name:tel_x_preferred":[
        "\u0c15\u0c43\u0c37\u0c4d\u0c23\u0c35\u0c30\u0c02"
    ],
    "wof:name":"Krishnavaram",
    "wof:placetype":"locality"
},
  "geometry": {"coordinates":[82.12224999999999,17.21132],"type":"Point"}
}