{
  "type": "Feature",
  "properties": {
    "iso:country":"IN",
    "ks:ks_name":"Gosain Milik",
    "ks:ks_pop":0,
    "ks:ks_type":"VILLAGE",
    "name:eng_x_preferred":[
        "Gosain Milik"
    ],
    "wof:name":"Gosain Milik",
    "wof:placetype":"locality",
    "wof:population":0
},
  "geometry": {"coordinates":[87.335359,25.636162],"type":"Point"}
}