{
  "type": "Feature",
  "properties": {
    "iso:country":"IN",
    "ks:ks_name":"Boyagudesulu",
    "ks:ks_pop":235,
    "ks:ks_type":"HABITATION",
    "name:eng_x_preferred":[
        "Boyagudesulu"
    ],
    "wof:name":"Boyagudesulu",
    "wof:placetype":"locality",
    "wof:population":235
},
  "geometry": {"coordinates":[77.838061,16.944521],"type":"Point"}
}