{
  "type": "Feature",
  "properties": {
    "iso:country":"IN",
    "ks:ks_name":"Khairwar",
    "ks:ks_pop":263,
    "ks:ks_type":"HABITATION",
    "name:eng_x_preferred":[
        "Khairwar"
    ],
    "wof:name":"Khairwar",
    "wof:placetype":"locality",
    "wof:population":263
},
  "geometry": {"coordinates":[80.752673,21.107257],"type":"Point"}
}