{
  "type": "Feature",
  "properties": {
    "iso:country":"IN",
    "ks:ks_name":"Bharda Chandora",
    "ks:ks_pop":428,
    "ks:ks_type":"HABITATION",
    "name:eng_x_preferred":[
        "Bharda Chandora"
    ],
    "wof:name":"Bharda Chandora",
    "wof:placetype":"locality",
    "wof:population":428
},
  "geometry": {"coordinates":[77.938956,23.287369],"type":"Point"}
}