{
  "type": "Feature",
  "properties": {
    "iso:country":"IN",
    "ks:ks_alt_nam":"Saher\u0101",
    "ks:ks_name":"Sahera",
    "ks:ks_pop":385,
    "ks:ks_type":"VILLAGE",
    "ks:ks_uagg_main":0,
    "name:eng_x_preferred":[
        "Sahera"
    ],
    "name:eng_x_variant":[
        "Saher\u0101"
    ],
    "wof:name":"Sahera",
    "wof:placetype":"neighbourhood",
    "wof:population":385
},
  "geometry": {"coordinates":[85.389909,23.281409],"type":"Point"}
}