{
  "type": "Feature",
  "properties": {
    "iso:country":"IN",
    "ks:ks_name":"Khorwatoli",
    "ks:ks_pop":98,
    "ks:ks_type":"HABITATION",
    "name:eng_x_preferred":[
        "Khorwatoli"
    ],
    "wof:name":"Khorwatoli",
    "wof:placetype":"locality",
    "wof:population":98
},
  "geometry": {"coordinates":[84.903395,23.062785],"type":"Point"}
}