{
  "type": "Feature",
  "properties": {
    "iso:country":"IN",
    "ks:ks_name":"Gouripur",
    "ks:ks_pop":1973,
    "ks:ks_type":"VILLAGE",
    "ks:ks_uagg_main":0,
    "name:eng_x_preferred":[
        "Gouripur"
    ],
    "wof:name":"Gouripur",
    "wof:placetype":"neighbourhood",
    "wof:population":1973
},
  "geometry": {"coordinates":[88.245921,22.077901],"type":"Point"}
}