{
  "type": "Feature",
  "properties": {
    "iso:country":"IN",
    "ks:ks_name":"Nawal Garh",
    "ks:ks_pop":421,
    "ks:ks_type":"HABITATION",
    "name:eng_x_preferred":[
        "Nawal Garh"
    ],
    "wof:name":"Nawal Garh",
    "wof:placetype":"locality",
    "wof:population":421
},
  "geometry": {"coordinates":[72.587681,26.547978],"type":"Point"}
}