{
  "type": "Feature",
  "properties": {
    "iso:country":"IN",
    "ks:ks_name":"Ghaneda",
    "ks:ks_pop":267,
    "ks:ks_type":"HABITATION",
    "name:eng_x_preferred":[
        "Ghaneda"
    ],
    "wof:name":"Ghaneda",
    "wof:placetype":"locality",
    "wof:population":267
},
  "geometry": {"coordinates":[73.00877199999999,19.797084],"type":"Point"}
}