{
  "type": "Feature",
  "properties": {
    "gn:admin1_code":"35.0",
    "gn:admin2_code":"464.0",
    "gn:asciiname":"Pawagoi Bara",
    "gn:country_code":"IN",
    "gn:dem":287,
    "gn:feature_class":"P",
    "gn:feature_code":"PPL",
    "gn:name":"Pawagoi Bara",
    "gn:population":0,
    "gn:timezone":"Asia/Kolkata",
    "iso:country":"IN",
    "ks:ks_name":"Pawagoi Badi",
    "ks:ks_pop":1018,
    "ks:ks_type":"VILLAGE",
    "name:eng_x_preferred":[
        "Pawagoi Badi"
    ],
    "name:eng_x_variant":[
        "Pawagoi Bara"
    ],
    "wof:name":"Pawagoi Badi",
    "wof:placetype":"locality",
    "wof:population":1018
},
  "geometry": {"coordinates":[74.51875200000001,22.98594],"type":"Point"}
}