{
  "type": "Feature",
  "properties": {
    "iso:country":"IN",
    "ks:ks_name":"Panchagochhia Jungle",
    "ks:ks_pop":49,
    "ks:ks_type":"HABITATION",
    "name:eng_x_preferred":[
        "Panchagochhia Jungle"
    ],
    "wof:name":"Panchagochhia Jungle",
    "wof:placetype":"locality",
    "wof:population":49
},
  "geometry": {"coordinates":[85.12359499999999,20.504044],"type":"Point"}
}