{
  "type": "Feature",
  "properties": {
    "iso:country":"IN",
    "ks:ks_name":"Tamandala Mal",
    "ks:ks_pop":58,
    "ks:ks_type":"HABITATION",
    "name:eng_x_preferred":[
        "Tamandala Mal"
    ],
    "wof:name":"Tamandala Mal",
    "wof:placetype":"locality",
    "wof:population":58
},
  "geometry": {"coordinates":[79.999813,18.845223],"type":"Point"}
}