{
  "type": "Feature",
  "properties": {
    "iso:country":"IN",
    "ks:ks_name":"Poosangudi",
    "ks:ks_pop":342,
    "ks:ks_type":"HABITATION",
    "name:eng_x_preferred":[
        "Poosangudi"
    ],
    "wof:name":"Poosangudi",
    "wof:placetype":"locality",
    "wof:population":342
},
  "geometry": {"coordinates":[79.651527,11.181124],"type":"Point"}
}