{
  "type": "Feature",
  "properties": {
    "iso:country":"IN",
    "ks:ks_name":"Hinjal",
    "ks:ks_pop":257,
    "ks:ks_type":"HABITATION",
    "name:eng_x_preferred":[
        "Hinjal"
    ],
    "wof:name":"Hinjal",
    "wof:placetype":"locality",
    "wof:population":257
},
  "geometry": {"coordinates":[84.699414,20.523677],"type":"Point"}
}