{
  "type": "Feature",
  "properties": {
    "gn:admin1_code":"2",
    "gn:admin2_code":"549.0",
    "gn:asciiname":"Edubadu Agraharam",
    "gn:country_code":"IN",
    "gn:dem":22,
    "gn:feature_class":"P",
    "gn:feature_code":"PPL",
    "gn:name":"Edub\u0101du Agrah\u0101ram",
    "gn:population":0,
    "gn:timezone":"Asia/Kolkata",
    "iso:country":"IN",
    "wof:name":"Edubadu Agraharam",
    "wof:placetype":"locality"
},
  "geometry": {"coordinates":[80.25203,16.04381],"type":"Point"}
}