{
  "type": "Feature",
  "properties": {
    "gn:admin1_code":"2",
    "gn:admin2_code":"544.0",
    "gn:asciiname":"Baski",
    "gn:country_code":"IN",
    "gn:dem":1102,
    "gn:feature_class":"P",
    "gn:feature_code":"PPL",
    "gn:name":"Baski",
    "gn:population":0,
    "gn:timezone":"Asia/Kolkata",
    "iso:country":"IN",
    "ks:ks_name":"Baski",
    "ks:ks_pop":798,
    "ks:ks_type":"VILLAGE",
    "name:eng_x_preferred":[
        "Baski"
    ],
    "wof:name":"Baski",
    "wof:placetype":"locality",
    "wof:population":798
},
  "geometry": {"coordinates":[82.89044800000001,18.235911],"type":"Point"}
}