{
  "type": "Feature",
  "properties": {
    "gn:admin1_code":"2",
    "gn:admin2_code":"544.0",
    "gn:asciiname":"Baski",
    "gn:country_code":"IN",
    "gn:dem":1102,
    "gn:feature_class":"P",
    "gn:feature_code":"PPL",
    "gn:name":"Baski",
    "gn:population":0,
    "gn:timezone":"Asia/Kolkata",
    "iso:country":"IN",
    "wof:name":"Baski",
    "wof:placetype":"locality"
},
  "geometry": {"coordinates":[82.89024000000001,18.23587],"type":"Point"}
}