{
  "type": "Feature",
  "properties": {
    "iso:country":"IN",
    "ks:ks_name":"Nail",
    "ks:ks_pop":154,
    "ks:ks_type":"HABITATION",
    "name:eng_x_preferred":[
        "Nail"
    ],
    "wof:name":"Nail",
    "wof:placetype":"locality",
    "wof:population":154
},
  "geometry": {"coordinates":[79.24978900000001,29.641126],"type":"Point"}
}