{
  "type": "Feature",
  "properties": {
    "iso:country":"IN",
    "ks:ks_name":"Amarpura",
    "ks:ks_pop":501,
    "ks:ks_type":"VILLAGE",
    "name:eng_x_preferred":[
        "Amarpura"
    ],
    "wof:name":"Amarpura",
    "wof:placetype":"locality",
    "wof:population":501
},
  "geometry": {"coordinates":[73.435281,24.445547],"type":"Point"}
}