{
  "type": "Feature",
  "properties": {
    "gn:admin1_code":"16",
    "gn:admin2_code":"504.0",
    "gn:asciiname":"Sirpur",
    "gn:country_code":"IN",
    "gn:dem":249,
    "gn:feature_class":"P",
    "gn:feature_code":"PPL",
    "gn:name":"Sirpur",
    "gn:population":0,
    "gn:timezone":"Asia/Kolkata",
    "iso:country":"IN",
    "name:und_x_variant":[
        "Yashvantnagar"
    ],
    "wof:name":"Sirpur",
    "wof:placetype":"locality"
},
  "geometry": {"coordinates":[78.38946999999997,20.52987000000001],"type":"Point"}
}