{
  "type": "Feature",
  "properties": {
    "gn:admin1_code":"35",
    "gn:admin2_code":"455.0",
    "gn:asciiname":"Gola",
    "gn:country_code":"IN",
    "gn:dem":989,
    "gn:feature_class":"P",
    "gn:feature_code":"PPL",
    "gn:name":"Gola",
    "gn:population":0,
    "gn:timezone":"Asia/Kolkata",
    "iso:country":"IN",
    "wof:name":"Gola",
    "wof:placetype":"locality"
},
  "geometry": {"coordinates":[78.30988000000001,22.23137],"type":"Point"}
}