{
  "type": "Feature",
  "properties": {
    "gn:admin1_code":"21",
    "gn:admin2_code":"372.0",
    "gn:asciiname":"Ranibandh",
    "gn:country_code":"IN",
    "gn:dem":183,
    "gn:feature_class":"P",
    "gn:feature_code":"PPL",
    "gn:name":"R\u0101nibandh",
    "gn:population":0,
    "gn:timezone":"Asia/Kolkata",
    "iso:country":"IN",
    "wof:name":"Ranibandh",
    "wof:placetype":"locality"
},
  "geometry": {"coordinates":[83.95884000000002,21.52838],"type":"Point"}
}