{
  "type": "Feature",
  "properties": {
    "iso:country":"IN",
    "ks:ks_name":"Mazeri",
    "ks:ks_pop":255,
    "ks:ks_type":"VILLAGE",
    "name:eng_x_preferred":[
        "Mazeri"
    ],
    "wof:name":"Mazeri",
    "wof:placetype":"locality",
    "wof:population":255
},
  "geometry": {"coordinates":[73.692516,18.093549],"type":"Point"}
}