{
  "type": "Feature",
  "properties": {
    "iso:country":"IN",
    "ks:ks_name":"Katan Ke Basti",
    "ks:ks_pop":94,
    "ks:ks_type":"HABITATION",
    "name:eng_x_preferred":[
        "Katan Ke Basti"
    ],
    "wof:name":"Katan Ke Basti",
    "wof:placetype":"locality",
    "wof:population":94
},
  "geometry": {"coordinates":[82.381136,26.720486],"type":"Point"}
}