{
  "type": "Feature",
  "properties": {
    "iso:country":"IN",
    "ks:ks_name":"Gaonda",
    "ks:ks_pop":486,
    "ks:ks_type":"VILLAGE",
    "name:eng_x_preferred":[
        "Gaonda"
    ],
    "wof:name":"Gaonda",
    "wof:placetype":"locality",
    "wof:population":486
},
  "geometry": {"coordinates":[75.46545999999999,22.4464],"type":"Point"}
}