{
  "type": "Feature",
  "properties": {
    "gn:admin1_code":"16",
    "gn:admin2_code":"500.0",
    "gn:asciiname":"Kothli",
    "gn:country_code":"IN",
    "gn:dem":360,
    "gn:feature_class":"P",
    "gn:feature_code":"PPL",
    "gn:name":"Kothli",
    "gn:population":0,
    "gn:timezone":"Asia/Kolkata",
    "iso:country":"IN",
    "wof:name":"Kothli",
    "wof:placetype":"locality"
},
  "geometry": {"coordinates":[76.26348,20.63526],"type":"Point"}
}