{
  "type": "Feature",
  "properties": {
    "iso:country":"IN",
    "ks:ks_alt_nam":"Heairbond Pt II",
    "ks:ks_name":"Heairbond Pt Ii",
    "ks:ks_pop":746,
    "ks:ks_type":"HABITATION",
    "name:eng_x_preferred":[
        "Heairbond Pt Ii"
    ],
    "wof:name":"Heairbond Pt Ii",
    "wof:placetype":"locality",
    "wof:population":746
},
  "geometry": {"coordinates":[92.69836100000001,24.916238],"type":"Point"}
}