{
  "type": "Feature",
  "properties": {
    "iso:country":"IN",
    "ks:ks_name":"Gawarai",
    "ks:ks_pop":458,
    "ks:ks_type":"HABITATION",
    "name:eng_x_preferred":[
        "Gawarai"
    ],
    "wof:name":"Gawarai",
    "wof:placetype":"locality",
    "wof:population":458
},
  "geometry": {"coordinates":[78.23979,27.099472],"type":"Point"}
}