{
  "type": "Feature",
  "properties": {
    "iso:country":"IN",
    "ks:ks_name":"Chinchaghar",
    "ks:ks_pop":643,
    "ks:ks_type":"VILLAGE",
    "name:eng_x_preferred":[
        "Chinchaghar"
    ],
    "wof:name":"Chinchaghar",
    "wof:placetype":"locality",
    "wof:population":643
},
  "geometry": {"coordinates":[73.128439,17.945929],"type":"Point"}
}