{
  "type": "Feature",
  "properties": {
    "iso:country":"IN",
    "ks:ks_name":"Begpara",
    "ks:ks_pop":652,
    "ks:ks_type":"HABITATION",
    "ks:ks_uagg_main":0,
    "name:eng_x_preferred":[
        "Begpara"
    ],
    "wof:name":"Begpara",
    "wof:placetype":"locality",
    "wof:population":652
},
  "geometry": {"coordinates":[88.033603,22.556627],"type":"Point"}
}