{
  "type": "Feature",
  "properties": {
    "iso:country":"IN",
    "ks:ks_name":"Nayabad",
    "ks:ks_pop":51,
    "ks:ks_type":"VILLAGE",
    "name:eng_x_preferred":[
        "Nayabad"
    ],
    "wof:name":"Nayabad",
    "wof:placetype":"locality",
    "wof:population":51
},
  "geometry": {"coordinates":[88.09174299999999,24.951518],"type":"Point"}
}