{
  "type": "Feature",
  "properties": {
    "iso:country":"IN",
    "ks:ks_name":"Choteduled",
    "ks:ks_pop":493,
    "ks:ks_type":"HABITATION",
    "name:eng_x_preferred":[
        "Choteduled"
    ],
    "wof:name":"Choteduled",
    "wof:placetype":"locality",
    "wof:population":493
},
  "geometry": {"coordinates":[81.125382,18.234229],"type":"Point"}
}