{
  "type": "Feature",
  "properties": {
    "iso:country":"IN",
    "ks:ks_name":"Sangollimane",
    "ks:ks_pop":37,
    "ks:ks_type":"HABITATION",
    "name:eng_x_preferred":[
        "Sangollimane"
    ],
    "wof:name":"Sangollimane",
    "wof:placetype":"locality",
    "wof:population":37
},
  "geometry": {"coordinates":[74.68136,14.386864],"type":"Point"}
}