{
  "type": "Feature",
  "properties": {
    "iso:country":"IN",
    "ks:ks_alt_nam":"SONDARLAL PURWA",
    "ks:ks_name":"Sondarlal Purwa",
    "ks:ks_pop":60,
    "ks:ks_type":"HABITATION",
    "name:eng_x_preferred":[
        "Sondarlal Purwa"
    ],
    "wof:name":"Sondarlal Purwa",
    "wof:placetype":"locality",
    "wof:population":60
},
  "geometry": {"coordinates":[81.58846800000001,27.360352],"type":"Point"}
}