{
  "type": "Feature",
  "properties": {
    "gn:admin1_code":"23",
    "gn:admin2_code":"38.0",
    "gn:asciiname":"Atalgarh",
    "gn:country_code":"IN",
    "gn:dem":285,
    "gn:feature_class":"P",
    "gn:feature_code":"PPL",
    "gn:name":"At\u0101lgarh",
    "gn:population":0,
    "gn:timezone":"Asia/Kolkata",
    "iso:country":"IN",
    "wof:name":"Atalgarh",
    "wof:placetype":"locality"
},
  "geometry": {"coordinates":[75.90106999999998,31.48086],"type":"Point"}
}