{
  "type": "Feature",
  "properties": {
    "gn:country":"IN",
    "gn:fcode":"PPL",
    "gn:pop":45321,
    "iso:country":"IN",
    "name:ben_x_preferred":[
        "\u0996\u09b2\u09bf\u09b2\u09be\u09ac\u09be\u09a6"
    ],
    "name:bho_x_preferred":[
        "\u0916\u0932\u0940\u0932\u093e\u092c\u093e\u0926"
    ],
    "name:bpy_x_preferred":[
        "\u0996\u09b2\u09bf\u09b2\u09be\u09ac\u09be\u09a6"
    ],
    "name:ceb_x_preferred":[
        "Khal\u012bl\u0101b\u0101d"
    ],
    "name:deu_x_preferred":[
        "Khalilabad"
    ],
    "name:eng_x_preferred":[
        "Khalilabad"
    ],
    "name:fas_x_preferred":[
        "\u062e\u0644\u06cc\u0644\u200c\u0622\u0628\u0627\u062f\u060c \u0647\u0646\u062f"
    ],
    "name:fas_x_variant":[
        "\u062e\u0644\u06cc\u0644\u200c\u0622\u0628\u0627\u062f"
    ],
    "name:fra_x_preferred":[
        "Khalilabad"
    ],
    "name:guj_x_preferred":[
        "\u0a96\u0ab2\u0abf\u0ab2\u0abe\u0aac\u0abe\u0aa6"
    ],
    "name:hin_x_preferred":[
        "\u0916\u0932\u0940\u0932\u093e\u092c\u093e\u0926"
    ],
    "name:ita_x_preferred":[
        "Khalilabad"
    ],
    "name:jpn_x_preferred":[
        "\u30ab\u30ea\u30e9\u30d0\u30c3\u30c9"
    ],
    "name:kan_x_preferred":[
        "\u0c96\u0cb2\u0cc0\u0cb2\u0cbe\u0cac\u0cbe\u0ca6\u0ccd"
    ],
    "name:kor_x_preferred":[
        "\uce7c\ub9b4\ub77c\ubc14\ub4dc"
    ],
    "name:mar_x_preferred":[
        "\u0916\u0932\u0940\u0932\u093e\u092c\u093e\u0926"
    ],
    "name:msa_x_preferred":[
        "Khalilabad"
    ],
    "name:nan_x_preferred":[
        "Khalilabad"
    ],
    "name:new_x_preferred":[
        "\u0916\u0932\u093f\u0932\u093e\u092c\u093e\u0926"
    ],
    "name:nld_x_preferred":[
        "Khalilabad"
    ],
    "name:pol_x_preferred":[
        "Khalilabad"
    ],
    "name:por_x_preferred":[
        "Khalilabad"
    ],
    "name:rus_x_preferred":[
        "\u041a\u0445\u0430\u043b\u0438\u043b\u0430\u0431\u0430\u0434"
    ],
    "name:san_x_preferred":[
        "\u0916\u0932\u093f\u0932\u093e\u092c\u093e\u0926\u094d"
    ],
    "name:spa_x_preferred":[
        "Khalilabad"
    ],
    "name:swe_x_preferred":[
        "Khalilabad"
    ],
    "name:tam_x_preferred":[
        "\u0b95\u0bbe\u0bb2\u0bbf\u0bb2\u0bbe\u0baa\u0bbe\u0ba4\u0bcd"
    ],
    "name:tel_x_preferred":[
        "\u0c16\u0c32\u0c3f\u0c32\u0c3e\u0c2c\u0c3e\u0c26\u0c4d"
    ],
    "name:urd_x_preferred":[
        "\u062e\u0644\u06cc\u0644 \u0622\u0628\u0627\u062f"
    ],
    "name:vie_x_preferred":[
        "Khalilabad"
    ],
    "name:zho_x_preferred":[
        "\u5361\u5229\u62c9\u5df4\u5fb7"
    ],
    "qs:name":"Khal\u012bl\u0101b\u0101d",
    "qs:photos_9r":0,
    "qs:photos_sr":0,
    "qs:pop_sr":"7",
    "wof:name":"Khal\u012bl\u0101b\u0101d",
    "wof:placetype":"locality",
    "wof:population":45321
},
  "geometry": {"coordinates":[83.07089999999999,26.77447],"type":"Point"}
}