{
  "type": "Feature",
  "properties": {
    "iso:country":"IN",
    "ks:ks_name":"Nagla Daulat",
    "ks:ks_pop":535,
    "ks:ks_type":"HABITATION",
    "name:eng_x_preferred":[
        "Nagla Daulat"
    ],
    "wof:name":"Nagla Daulat",
    "wof:placetype":"locality",
    "wof:population":535
},
  "geometry": {"coordinates":[79.396518,26.910389],"type":"Point"}
}