{
  "type": "Feature",
  "properties": {
    "iso:country":"IN",
    "ks:ks_name":"Harzan Basti",
    "ks:ks_pop":1320,
    "ks:ks_type":"HABITATION",
    "name:eng_x_preferred":[
        "Harzan Basti"
    ],
    "wof:name":"Harzan Basti",
    "wof:placetype":"locality",
    "wof:population":1320
},
  "geometry": {"coordinates":[82.731128,25.367643],"type":"Point"}
}