{
  "type": "Feature",
  "properties": {
    "iso:country":"IN",
    "ks:ks_name":"Chenakata",
    "ks:ks_pop":1310,
    "ks:ks_type":"VILLAGE",
    "name:eng_x_preferred":[
        "Chenakata"
    ],
    "wof:name":"Chenakata",
    "wof:placetype":"locality",
    "wof:population":1310
},
  "geometry": {"coordinates":[89.093563,26.367811],"type":"Point"}
}