{
  "type": "Feature",
  "properties": {
    "iso:country":"IN",
    "ks:ks_name":"Agrala",
    "ks:ks_pop":288,
    "ks:ks_type":"HABITATION",
    "name:eng_x_preferred":[
        "Agrala"
    ],
    "wof:name":"Agrala",
    "wof:placetype":"locality",
    "wof:population":288
},
  "geometry": {"coordinates":[75.162181,12.729473],"type":"Point"}
}