{
  "type": "Feature",
  "properties": {
    "iso:country":"IN",
    "ks:ks_name":"Navalkarwadi",
    "ks:ks_pop":92,
    "ks:ks_type":"HABITATION",
    "name:eng_x_preferred":[
        "Navalkarwadi"
    ],
    "wof:name":"Navalkarwadi",
    "wof:placetype":"locality",
    "wof:population":92
},
  "geometry": {"coordinates":[74.166803,16.165508],"type":"Point"}
}