{
  "type": "Feature",
  "properties": {
    "gn:admin1_code":"39.0",
    "gn:admin2_code":"63.0",
    "gn:asciiname":"Gairkhet",
    "gn:country_code":"IN",
    "gn:dem":1082,
    "gn:feature_class":"P",
    "gn:feature_code":"PPL",
    "gn:name":"Gairkhet",
    "gn:population":0,
    "gn:timezone":"Asia/Kolkata",
    "iso:country":"IN",
    "ks:ks_name":"Gairkhet",
    "ks:ks_pop":496,
    "ks:ks_type":"VILLAGE",
    "name:eng_x_preferred":[
        "Gairkhet"
    ],
    "wof:name":"Gairkhet",
    "wof:placetype":"locality",
    "wof:population":496
},
  "geometry": {"coordinates":[79.842483,29.919653],"type":"Point"}
}