{
  "type": "Feature",
  "properties": {
    "iso:country":"IN",
    "ks:ks_name":"Bin Tola",
    "ks:ks_pop":700,
    "ks:ks_type":"HABITATION",
    "name:eng_x_preferred":[
        "Bin Tola"
    ],
    "wof:name":"Bin Tola",
    "wof:placetype":"locality",
    "wof:population":700
},
  "geometry": {"coordinates":[84.884755,26.327411],"type":"Point"}
}