{
  "type": "Feature",
  "properties": {
    "iso:country":"IN",
    "ks:ks_name":"Mirzapur",
    "ks:ks_pop":7295,
    "ks:ks_type":"VILLAGE",
    "name:eng_x_preferred":[
        "Mirzapur"
    ],
    "wof:name":"Mirzapur",
    "wof:placetype":"locality",
    "wof:population":7295
},
  "geometry": {"coordinates":[85.918913,26.032052],"type":"Point"}
}