{
  "type": "Feature",
  "properties": {
    "gn:admin1_code":"24",
    "gn:admin2_code":"122.0",
    "gn:asciiname":"Jikli",
    "gn:country_code":"IN",
    "gn:dem":348,
    "gn:feature_class":"P",
    "gn:feature_code":"PPL",
    "gn:name":"J\u012bkli",
    "gn:population":0,
    "gn:timezone":"Asia/Kolkata",
    "iso:country":"IN",
    "wof:name":"Jikli",
    "wof:placetype":"locality"
},
  "geometry": {"coordinates":[75.33561,25.54518],"type":"Point"}
}