{
  "type": "Feature",
  "properties": {
    "iso:country":"IN",
    "ks:ks_name":"Gaothanwadi",
    "ks:ks_pop":350,
    "ks:ks_type":"HABITATION",
    "name:eng_x_preferred":[
        "Gaothanwadi"
    ],
    "wof:name":"Gaothanwadi",
    "wof:placetype":"locality",
    "wof:population":350
},
  "geometry": {"coordinates":[73.624167,17.440278],"type":"Point"}
}