{
  "type": "Feature",
  "properties": {
    "iso:country":"IN",
    "ks:ks_name":"Wangli",
    "ks:ks_pop":511,
    "ks:ks_type":"VILLAGE",
    "name:eng_x_preferred":[
        "Wangli"
    ],
    "wof:name":"Wangli",
    "wof:placetype":"locality",
    "wof:population":511
},
  "geometry": {"coordinates":[73.373817,24.458292],"type":"Point"}
}