{
  "type": "Feature",
  "properties": {
    "gn:admin1_code":"25.0",
    "gn:admin2_code":"633.0",
    "gn:asciiname":"Vadugapalaiyam Pudur",
    "gn:country_code":"IN",
    "gn:dem":375,
    "gn:feature_class":"P",
    "gn:feature_code":"PPL",
    "gn:name":"Vadugap\u0101laiyam Pud\u016br",
    "gn:population":0,
    "gn:timezone":"Asia/Kolkata",
    "iso:country":"IN",
    "wof:name":"Vadugapalaiyam Pudur",
    "wof:placetype":"neighbourhood"
},
  "geometry": {"coordinates":[77.28765,10.98362],"type":"Point"}
}