{
  "type": "Feature",
  "properties": {
    "iso:country":"IN",
    "ks:ks_name":"Serha Kham",
    "ks:ks_pop":46,
    "ks:ks_type":"VILLAGE",
    "ks:ks_uagg_main":0,
    "name:eng_x_preferred":[
        "Serha Kham"
    ],
    "wof:name":"Serha Kham",
    "wof:placetype":"neighbourhood",
    "wof:population":46
},
  "geometry": {"coordinates":[79.49515700000001,28.088275],"type":"Point"}
}