{
  "type": "Feature",
  "properties": {
    "iso:country":"IN",
    "ks:ks_name":"Ramakrishnapuram",
    "ks:ks_pop":240,
    "ks:ks_type":"HABITATION",
    "name:eng_x_preferred":[
        "Ramakrishnapuram"
    ],
    "wof:name":"Ramakrishnapuram",
    "wof:placetype":"locality",
    "wof:population":240
},
  "geometry": {"coordinates":[78.831096,13.409844],"type":"Point"}
}