{
  "type": "Feature",
  "properties": {
    "iso:country":"IN",
    "ks:ks_alt_nam":"baba nagar",
    "ks:ks_name":"Baba Nagar",
    "ks:ks_pop":591,
    "ks:ks_type":"HABITATION",
    "name:eng_x_preferred":[
        "Baba Nagar"
    ],
    "wof:name":"Baba Nagar",
    "wof:placetype":"locality",
    "wof:population":591
},
  "geometry": {"coordinates":[72.417794,26.911833],"type":"Point"}
}