{
  "type": "Feature",
  "properties": {
    "iso:country":"IN",
    "ks:ks_name":"South Babura",
    "ks:ks_pop":1954,
    "ks:ks_type":"HABITATION",
    "name:eng_x_preferred":[
        "South Babura"
    ],
    "wof:name":"South Babura",
    "wof:placetype":"locality",
    "wof:population":1954
},
  "geometry": {"coordinates":[84.773878,25.678255],"type":"Point"}
}