{
  "type": "Feature",
  "properties": {
    "gn:admin1_code":"35",
    "gn:admin2_code":"463.0",
    "gn:asciiname":"Ajani",
    "gn:country_code":"IN",
    "gn:dem":393,
    "gn:feature_class":"P",
    "gn:feature_code":"PPL",
    "gn:name":"Ajani",
    "gn:population":0,
    "gn:timezone":"Asia/Kolkata",
    "iso:country":"IN",
    "ks:ks_name":"Ajani",
    "ks:ks_pop":408,
    "ks:ks_type":"VILLAGE",
    "name:eng_x_preferred":[
        "Ajani"
    ],
    "wof:name":"Ajani",
    "wof:placetype":"locality",
    "wof:population":408
},
  "geometry": {"coordinates":[82.54524499999999,24.237253],"type":"Point"}
}