{
  "type": "Feature",
  "properties": {
    "iso:country":"IN",
    "ks:ks_name":"Ekarya",
    "ks:ks_pop":70,
    "ks:ks_type":"VILLAGE",
    "name:eng_x_preferred":[
        "Ekarya"
    ],
    "wof:name":"Ekarya",
    "wof:placetype":"locality",
    "wof:population":70
},
  "geometry": {"coordinates":[87.242063,23.339223],"type":"Point"}
}