{
  "type": "Feature",
  "properties": {
    "gn:admin1_code":"36",
    "gn:admin2_code":"146.0",
    "gn:asciiname":"Nagla Gadarian",
    "gn:country_code":"IN",
    "gn:dem":171,
    "gn:feature_class":"P",
    "gn:feature_code":"PPL",
    "gn:name":"Nagla Gadarian",
    "gn:population":0,
    "gn:timezone":"Asia/Kolkata",
    "iso:country":"IN",
    "wof:name":"Nagla Gadarian",
    "wof:placetype":"neighbourhood"
},
  "geometry": {"coordinates":[78.06211999999999,27.28099],"type":"Point"}
}