{
  "type": "Feature",
  "properties": {
    "iso:country":"IN",
    "ks:ks_name":"Westtola",
    "ks:ks_pop":50,
    "ks:ks_type":"HABITATION",
    "name:eng_x_preferred":[
        "Westtola"
    ],
    "wof:name":"Westtola",
    "wof:placetype":"locality",
    "wof:population":50
},
  "geometry": {"coordinates":[85.490731,23.346747],"type":"Point"}
}