{
  "type": "Feature",
  "properties": {
    "gn:admin1_code":"34.0",
    "gn:admin2_code":"219.0",
    "gn:asciiname":"Sheikhpura",
    "gn:country_code":"IN",
    "gn:dem":57,
    "gn:feature_class":"P",
    "gn:feature_code":"PPL",
    "gn:name":"Sheikhpura",
    "gn:population":0,
    "gn:timezone":"Asia/Kolkata",
    "iso:country":"IN",
    "ks:ks_name":"Shekhpura",
    "ks:ks_pop":7,
    "ks:ks_type":"VILLAGE",
    "ks:ks_uagg_main":0,
    "name:ara_x_preferred":[
        "\u0634\u064a\u062e \u0628\u0648\u0631\u0627"
    ],
    "name:ben_bn_x_preferred":[
        "\u09b6\u09c7\u0996\u09aa\u09c1\u09b0\u09be"
    ],
    "name:ben_in_x_preferred":[
        "\u09b6\u09c7\u0996\u09aa\u09c1\u09b0\u09be"
    ],
    "name:ben_x_preferred":[
        "\u09b6\u09c7\u0996\u09aa\u09c1\u09b0\u09be"
    ],
    "name:bih_x_preferred":[
        "\u0936\u0947\u0916\u092a\u0941\u0930\u093e"
    ],
    "name:bpy_x_preferred":[
        "\u09b6\u09c7\u0996\u09aa\u09c1\u09b0"
    ],
    "name:eng_x_preferred":[
        "Shekhpura"
    ],
    "name:guj_x_preferred":[
        "\u0ab6\u0ac8\u0a96\u0aaa\u0ac1\u0ab0\u0abe"
    ],
    "name:guj_x_variant":[
        "\u0ab6\u0ac7\u0a96\u0aaa\u0ac1\u0ab0\u0abe"
    ],
    "name:hin_x_preferred":[
        "\u0936\u0947\u0916\u092a\u0941\u0930\u093e"
    ],
    "name:ita_x_preferred":[
        "Sheikhpura"
    ],
    "name:kan_x_preferred":[
        "\u0cb6\u0cc7\u0c96\u0ccd"
    ],
    "name:mal_x_preferred":[
        "\u0d37\u0d46\u0d2f\u0d4d\u0d16\u0d4d\u0d2a\u0d41\u0d30"
    ],
    "name:mar_x_preferred":[
        "\u0936\u0947\u0916\u092a\u0941\u0930\u093e"
    ],
    "name:mlg_x_preferred":[
        "Sheikhpura"
    ],
    "name:msa_x_preferred":[
        "Sheikhpura"
    ],
    "name:nep_x_preferred":[
        "\u0936\u0947\u0916\u092a\u0941\u0930\u093e"
    ],
    "name:ori_x_preferred":[
        "\u0b36\u0b47\u0b07\u0b16\u0b2a\u0b41\u0b30\u0b3e"
    ],
    "name:pan_x_preferred":[
        "\u0a36\u0a47\u0a16\u0a2a\u0a41\u0a30\u0a3e"
    ],
    "name:por_x_preferred":[
        "Sheikhpura"
    ],
    "name:rus_x_preferred":[
        "\u0428\u0435\u0439\u0445\u043f\u0443\u0440\u0430"
    ],
    "name:san_x_preferred":[
        "\u0936\u0947\u0916\u092a\u0941\u0930\u093e"
    ],
    "name:spa_x_preferred":[
        "Sheikhpura"
    ],
    "name:tam_x_preferred":[
        "\u0bb7\u0bc7\u0b95\u0bcd\u0baa\u0bc1\u0bb0\u0bbe"
    ],
    "name:tel_x_preferred":[
        "\u0c37\u0c47\u0c15\u0c4d"
    ],
    "name:urd_x_preferred":[
        "\u0634\u06cc\u062e \u067e\u0648\u0631\u06c1"
    ],
    "name:vie_x_preferred":[
        "Sheikhpura"
    ],
    "name:zho_x_preferred":[
        "\u65af\u8d6b\u4f0a\u514b\u666e\u62c9"
    ],
    "wof:name":"Shekhpura",
    "wof:placetype":"neighbourhood",
    "wof:population":7
},
  "geometry": {"coordinates":[84.919957,25.91827],"type":"Point"}
}