{
  "type": "Feature",
  "properties": {
    "iso:country":"IN",
    "ks:ks_name":"Karijhal",
    "ks:ks_pop":272,
    "ks:ks_type":"VILLAGE",
    "name:eng_x_preferred":[
        "Karijhal"
    ],
    "wof:name":"Karijhal",
    "wof:placetype":"locality",
    "wof:population":272
},
  "geometry": {"coordinates":[86.40463,24.62783],"type":"Point"}
}