{
  "type": "Feature",
  "properties": {
    "iso:country":"IN",
    "ks:ks_name":"Singanalli Tanda",
    "ks:ks_pop":155,
    "ks:ks_type":"HABITATION",
    "name:eng_x_preferred":[
        "Singanalli Tanda"
    ],
    "wof:name":"Singanalli Tanda",
    "wof:placetype":"locality",
    "wof:population":155
},
  "geometry": {"coordinates":[76.76092800000001,16.772814],"type":"Point"}
}