{
  "type": "Feature",
  "properties": {
    "iso:country":"IN",
    "ks:ks_name":"Pure Kheamipur",
    "ks:ks_pop":159,
    "ks:ks_type":"HABITATION",
    "name:eng_x_preferred":[
        "Pure Kheamipur"
    ],
    "wof:name":"Pure Kheamipur",
    "wof:placetype":"locality",
    "wof:population":159
},
  "geometry": {"coordinates":[82.248853,26.603983],"type":"Point"}
}