{
  "type": "Feature",
  "properties": {
    "gn:admin1_code":"2.0",
    "gn:admin2_code":"554.0",
    "gn:asciiname":"Jangamvandlapalle",
    "gn:country_code":"IN",
    "gn:dem":623,
    "gn:feature_class":"P",
    "gn:feature_code":"PPL",
    "gn:name":"Jangamv\u0101ndlapalle",
    "gn:population":0,
    "gn:timezone":"Asia/Kolkata",
    "iso:country":"IN",
    "wof:name":"Jangamvandlapalle",
    "wof:placetype":"locality"
},
  "geometry": {"coordinates":[78.27930000000001,13.71057],"type":"Point"}
}