{
  "type": "Feature",
  "properties": {
    "iso:country":"IN",
    "ks:ks_alt_nam":"AGASARAMAKKI",
    "ks:ks_name":"Agasaramakki",
    "ks:ks_pop":107,
    "ks:ks_type":"HABITATION",
    "name:eng_x_preferred":[
        "Agasaramakki"
    ],
    "wof:name":"Agasaramakki",
    "wof:placetype":"locality",
    "wof:population":107
},
  "geometry": {"coordinates":[75.3181,13.671171],"type":"Point"}
}