{
  "type": "Feature",
  "properties": {
    "gn:admin1_code":"39.0",
    "gn:admin2_code":"61.0",
    "gn:asciiname":"Naruwajhal",
    "gn:country_code":"IN",
    "gn:dem":1811,
    "gn:feature_class":"P",
    "gn:feature_code":"PPL",
    "gn:name":"Naruw\u0101jh\u0101l",
    "gn:population":0,
    "gn:timezone":"Asia/Kolkata",
    "iso:country":"IN",
    "wof:name":"Naruwajhal",
    "wof:placetype":"locality"
},
  "geometry": {"coordinates":[79.11679000000002,29.8979],"type":"Point"}
}