{
  "type": "Feature",
  "properties": {
    "iso:country":"IN",
    "ks:ks_name":"Santokpura",
    "ks:ks_pop":111,
    "ks:ks_type":"HABITATION",
    "name:eng_x_preferred":[
        "Santokpura"
    ],
    "wof:name":"Santokpura",
    "wof:placetype":"locality",
    "wof:population":111
},
  "geometry": {"coordinates":[72.53745000000001,23.61118],"type":"Point"}
}