{
  "type": "Feature",
  "properties": {
    "iso:country":"IN",
    "ks:ks_name":"Kurumbapatti",
    "ks:ks_pop":197,
    "ks:ks_type":"HABITATION",
    "name:eng_x_preferred":[
        "Kurumbapatti"
    ],
    "wof:name":"Kurumbapatti",
    "wof:placetype":"locality",
    "wof:population":197
},
  "geometry": {"coordinates":[77.900976,10.337078],"type":"Point"}
}