{
  "type": "Feature",
  "properties": {
    "iso:country":"IN",
    "ks:ks_name":"Samaspur",
    "ks:ks_pop":784,
    "ks:ks_type":"VILLAGE",
    "ks:ks_uagg_main":0,
    "name:eng_x_preferred":[
        "Samaspur"
    ],
    "wof:name":"Samaspur",
    "wof:placetype":"neighbourhood",
    "wof:population":784
},
  "geometry": {"coordinates":[87.837126,25.005521],"type":"Point"}
}