{
  "type": "Feature",
  "properties": {
    "iso:country":"IN",
    "ks:ks_name":"Kachari Gaon",
    "ks:ks_pop":313,
    "ks:ks_type":"HABITATION",
    "ks:ks_uagg_main":0,
    "name:eng_x_preferred":[
        "Kachari Gaon"
    ],
    "wof:name":"Kachari Gaon",
    "wof:placetype":"neighbourhood",
    "wof:population":313
},
  "geometry": {"coordinates":[93.860319,26.289101],"type":"Point"}
}