{
  "type": "Feature",
  "properties": {
    "gn:admin1_code":"39.0",
    "gn:admin2_code":"60.0",
    "gn:asciiname":"Talon ki Chhani",
    "gn:country_code":"IN",
    "gn:dem":1465,
    "gn:feature_class":"P",
    "gn:feature_code":"PPL",
    "gn:name":"Talon ki Chh\u0101ni",
    "gn:population":0,
    "gn:timezone":"Asia/Kolkata",
    "iso:country":"IN",
    "wof:name":"Talon ki Chhani",
    "wof:placetype":"locality"
},
  "geometry": {"coordinates":[77.80991,30.7351],"type":"Point"}
}