{
  "type": "Feature",
  "properties": {
    "gn:admin1_code":"34.0",
    "gn:admin2_code":"203.0",
    "gn:asciiname":"Nautanwa",
    "gn:country_code":"IN",
    "gn:dem":97,
    "gn:feature_class":"P",
    "gn:feature_code":"PPL",
    "gn:name":"Nautanwa",
    "gn:population":0,
    "gn:timezone":"Asia/Kolkata",
    "iso:country":"IN",
    "name:bih_x_preferred":[
        "\u0928\u094c\u0924\u0928\u0935\u093e"
    ],
    "name:bpy_x_preferred":[
        "\u09a8\u09cc\u09a4\u09be\u09a8\u09f1\u09be"
    ],
    "name:ceb_x_preferred":[
        "Nautanwa"
    ],
    "name:ita_x_preferred":[
        "Nautanwa"
    ],
    "name:mlg_x_preferred":[
        "Nautanwa"
    ],
    "name:msa_x_preferred":[
        "Nautanwa"
    ],
    "name:new_x_preferred":[
        "\u0928\u094c\u0924\u0928\u094d\u0935\u093e"
    ],
    "name:nld_x_preferred":[
        "Nautanwa"
    ],
    "name:ori_x_preferred":[
        "\u0b28\u0b09\u0b24\u0b28\u0b71\u0b3e"
    ],
    "name:pnb_x_preferred":[
        "\u0646\u0648\u062a\u0646\u0648\u0627"
    ],
    "name:pol_x_preferred":[
        "Nautanwa"
    ],
    "name:swe_x_preferred":[
        "Nautanwa"
    ],
    "name:urd_x_preferred":[
        "\u0646\u0648\u062a\u0646\u0648\u0627"
    ],
    "name:vie_x_preferred":[
        "Nautanwa"
    ],
    "name:zho_x_preferred":[
        "\u7459\u5766\u74e6"
    ],
    "wof:name":"Nautanwa",
    "wof:placetype":"locality"
},
  "geometry": {"coordinates":[84.55564,27.16373],"type":"Point"}
}