{
  "type": "Feature",
  "properties": {
    "iso:country":"IN",
    "ks:ks_name":"Musamari",
    "ks:ks_pop":575,
    "ks:ks_type":"VILLAGE",
    "name:eng_x_preferred":[
        "Musamari"
    ],
    "wof:name":"Musamari",
    "wof:placetype":"locality",
    "wof:population":575
},
  "geometry": {"coordinates":[86.418421,22.178051],"type":"Point"}
}