{
  "type": "Feature",
  "properties": {
    "gn:admin1_code":"9",
    "gn:admin2_code":"485.0",
    "gn:asciiname":"Piplia",
    "gn:country_code":"IN",
    "gn:dem":203,
    "gn:feature_class":"P",
    "gn:feature_code":"PPL",
    "gn:name":"P\u012bplia",
    "gn:population":0,
    "gn:timezone":"Asia/Kolkata",
    "iso:country":"IN",
    "ks:ks_name":"Pipliya",
    "ks:ks_pop":724,
    "ks:ks_type":"VILLAGE",
    "name:eng_x_preferred":[
        "Pipliya"
    ],
    "name:eng_x_variant":[
        "Piplia"
    ],
    "wof:name":"Pipliya",
    "wof:placetype":"locality",
    "wof:population":724
},
  "geometry": {"coordinates":[74.057755,23.198789],"type":"Point"}
}