{
  "type": "Feature",
  "properties": {
    "iso:country":"IN",
    "ks:ks_name":"Sardartari",
    "ks:ks_pop":1152,
    "ks:ks_type":"HABITATION",
    "name:eng_x_preferred":[
        "Sardartari"
    ],
    "wof:name":"Sardartari",
    "wof:placetype":"locality",
    "wof:population":1152
},
  "geometry": {"coordinates":[89.127139,26.385195],"type":"Point"}
}