{
  "type": "Feature",
  "properties": {
    "gn:admin1_code":"2.0",
    "gn:admin2_code":"554.0",
    "gn:asciiname":"Subbarayanipalle",
    "gn:country_code":"IN",
    "gn:dem":621,
    "gn:feature_class":"P",
    "gn:feature_code":"PPL",
    "gn:name":"Subbar\u0101yanipalle",
    "gn:population":0,
    "gn:timezone":"Asia/Kolkata",
    "iso:country":"IN",
    "wof:name":"Subbarayanipalle",
    "wof:placetype":"locality"
},
  "geometry": {"coordinates":[78.24446,13.71835],"type":"Point"}
}