{
  "type": "Feature",
  "properties": {
    "gn:admin1_code":"37",
    "gn:admin2_code":"411.0",
    "gn:asciiname":"Darbekera",
    "gn:country_code":"IN",
    "gn:dem":330,
    "gn:feature_class":"P",
    "gn:feature_code":"PPL",
    "gn:name":"Darbekera",
    "gn:population":0,
    "gn:timezone":"Asia/Kolkata",
    "iso:country":"IN",
    "ks:ks_name":"Darbekera",
    "ks:ks_pop":376,
    "ks:ks_type":"VILLAGE",
    "name:eng_x_preferred":[
        "Darbekera"
    ],
    "wof:name":"Darbekera",
    "wof:placetype":"locality",
    "wof:population":376
},
  "geometry": {"coordinates":[82.444007,20.95571],"type":"Point"}
}