{
  "type": "Feature",
  "properties": {
    "gn:admin1_code":"11.0",
    "gn:admin2_code":"27.0",
    "gn:asciiname":"Nichli Balahni",
    "gn:country_code":"IN",
    "gn:dem":1639,
    "gn:feature_class":"P",
    "gn:feature_code":"PPL",
    "gn:name":"Nichli Bal\u0101hni",
    "gn:population":0,
    "gn:timezone":"Asia/Kolkata",
    "iso:country":"IN",
    "wof:name":"Nichli Balahni",
    "wof:placetype":"locality"
},
  "geometry": {"coordinates":[77.31131999999999,31.36371],"type":"Point"}
}