{
  "type": "Feature",
  "properties": {
    "iso:country":"IN",
    "ks:ks_name":"Chak Habib",
    "ks:ks_pop":925,
    "ks:ks_type":"VILLAGE",
    "name:eng_x_preferred":[
        "Chak Habib"
    ],
    "wof:name":"Chak Habib",
    "wof:placetype":"locality",
    "wof:population":925
},
  "geometry": {"coordinates":[85.17874399999999,25.916472],"type":"Point"}
}