{
  "type": "Feature",
  "properties": {
    "iso:country":"IN",
    "ks:ks_alt_nam":"Satsabighan Char pt III",
    "ks:ks_name":"Satsabighan Char Pt Iii",
    "ks:ks_pop":357,
    "ks:ks_type":"HABITATION",
    "name:eng_x_preferred":[
        "Satsabighan Char Pt Iii"
    ],
    "wof:name":"Satsabighan Char Pt Iii",
    "wof:placetype":"locality",
    "wof:population":357
},
  "geometry": {"coordinates":[90.52227999999999,26.248344],"type":"Point"}
}