{
  "type": "Feature",
  "properties": {
    "iso:country":"IN",
    "ks:ks_name":"Gogana Talla",
    "ks:ks_pop":86,
    "ks:ks_type":"HABITATION",
    "name:eng_x_preferred":[
        "Gogana Talla"
    ],
    "wof:name":"Gogana Talla",
    "wof:placetype":"locality",
    "wof:population":86
},
  "geometry": {"coordinates":[79.32123900000001,29.953909],"type":"Point"}
}