{
  "type": "Feature",
  "properties": {
    "iso:country":"IN",
    "ks:ks_name":"Bhoj Nagar",
    "ks:ks_pop":250,
    "ks:ks_type":"VILLAGE",
    "name:eng_x_preferred":[
        "Bhoj Nagar"
    ],
    "wof:name":"Bhoj Nagar",
    "wof:placetype":"locality",
    "wof:population":250
},
  "geometry": {"coordinates":[72.14413500000001,27.249709],"type":"Point"}
}