{
  "type": "Feature",
  "properties": {
    "iso:country":"IN",
    "ks:ks_name":"Chhidakudar",
    "ks:ks_pop":634,
    "ks:ks_type":"VILLAGE",
    "name:eng_x_preferred":[
        "Chhidakudar"
    ],
    "wof:name":"Chhidakudar",
    "wof:placetype":"locality",
    "wof:population":634
},
  "geometry": {"coordinates":[84.939814,21.984737],"type":"Point"}
}