{
  "type": "Feature",
  "properties": {
    "gn:admin1_code":"16.0",
    "gn:admin2_code":"522.0",
    "gn:asciiname":"Adalgaon",
    "gn:country_code":"IN",
    "gn:dem":569,
    "gn:feature_class":"P",
    "gn:feature_code":"PPL",
    "gn:name":"Adalgaon",
    "gn:population":0,
    "gn:timezone":"Asia/Kolkata",
    "iso:country":"IN",
    "wof:name":"Adalgaon",
    "wof:placetype":"locality"
},
  "geometry": {"coordinates":[74.76380999999998,18.63631],"type":"Point"}
}