{
  "type": "Feature",
  "properties": {
    "iso:country":"IN",
    "ks:ks_name":"Bisweswarbati",
    "ks:ks_pop":352,
    "ks:ks_type":"VILLAGE",
    "ks:ks_uagg_main":0,
    "name:eng_x_preferred":[
        "Bisweswarbati"
    ],
    "wof:name":"Bisweswarbati",
    "wof:placetype":"neighbourhood",
    "wof:population":352
},
  "geometry": {"coordinates":[87.90019700000001,23.067597],"type":"Point"}
}