{
  "type": "Feature",
  "properties": {
    "gn:admin1_code":"39",
    "gn:admin2_code":"61.0",
    "gn:asciiname":"Bawani",
    "gn:country_code":"IN",
    "gn:dem":1252,
    "gn:feature_class":"P",
    "gn:feature_code":"PPL",
    "gn:name":"Baw\u0101ni",
    "gn:population":0,
    "gn:timezone":"Asia/Kolkata",
    "iso:country":"IN",
    "ks:ks_alt_nam":"Baw\u0101ni",
    "ks:ks_name":"Bawani",
    "ks:ks_pop":203,
    "ks:ks_type":"VILLAGE",
    "name:eng_x_preferred":[
        "Bawani"
    ],
    "name:eng_x_variant":[
        "Baw\u0101ni"
    ],
    "wof:name":"Bawani",
    "wof:placetype":"locality",
    "wof:population":203
},
  "geometry": {"coordinates":[78.983642,29.641587],"type":"Point"}
}