{
  "type": "Feature",
  "properties": {
    "iso:country":"IN",
    "ks:ks_alt_nam":"KUNBIWADI",
    "ks:ks_name":"Kunbiwadi",
    "ks:ks_pop":356,
    "ks:ks_type":"HABITATION",
    "name:eng_x_preferred":[
        "Kunbiwadi"
    ],
    "wof:name":"Kunbiwadi",
    "wof:placetype":"locality",
    "wof:population":356
},
  "geometry": {"coordinates":[73.357832,17.297872],"type":"Point"}
}