{
  "type": "Feature",
  "properties": {
    "gn:admin1_code":"2",
    "gn:admin2_code":"546.0",
    "gn:asciiname":"Singanapalle",
    "gn:country_code":"IN",
    "gn:dem":34,
    "gn:feature_class":"P",
    "gn:feature_code":"PPL",
    "gn:name":"Singanapalle",
    "gn:population":0,
    "gn:timezone":"Asia/Kolkata",
    "iso:country":"IN",
    "ks:ks_name":"Singanapalle",
    "ks:ks_type":"VILLAGE",
    "name:eng_x_preferred":[
        "Singanapalle"
    ],
    "wof:name":"Singanapalle",
    "wof:placetype":"locality"
},
  "geometry": {"coordinates":[81.63776900000001,17.322558],"type":"Point"}
}