{
  "type": "Feature",
  "properties": {
    "iso:country":"IN",
    "ks:ks_name":"Matiyala Laga Kirsal",
    "ks:ks_pop":79,
    "ks:ks_type":"VILLAGE",
    "name:eng_x_preferred":[
        "Matiyala Laga Kirsal"
    ],
    "wof:name":"Matiyala Laga Kirsal",
    "wof:placetype":"locality",
    "wof:population":79
},
  "geometry": {"coordinates":[79.169529,30.178752],"type":"Point"}
}