{
  "type": "Feature",
  "properties": {
    "iso:country":"IN",
    "ks:ks_name":"Rupawar",
    "ks:ks_pop":155,
    "ks:ks_type":"HABITATION",
    "name:eng_x_preferred":[
        "Rupawar"
    ],
    "wof:name":"Rupawar",
    "wof:placetype":"locality",
    "wof:population":155
},
  "geometry": {"coordinates":[84.195601,25.792152],"type":"Point"}
}