{
  "type": "Feature",
  "properties": {
    "gn:admin1_code":"12.0",
    "gn:admin2_code":"2.0",
    "gn:asciiname":"Dargahtolan",
    "gn:country_code":"IN",
    "gn:dem":2772,
    "gn:feature_class":"P",
    "gn:feature_code":"PPL",
    "gn:name":"Darg\u0101htolan",
    "gn:population":0,
    "gn:timezone":"Asia/Kolkata",
    "iso:country":"IN",
    "wof:name":"Dargahtolan",
    "wof:placetype":"locality"
},
  "geometry": {"coordinates":[74.63285999999999,33.79129],"type":"Point"}
}