{
  "type": "Feature",
  "properties": {
    "iso:country":"IN",
    "ks:ks_name":"Tawarahi",
    "ks:ks_pop":136,
    "ks:ks_type":"HABITATION",
    "name:eng_x_preferred":[
        "Tawarahi"
    ],
    "wof:name":"Tawarahi",
    "wof:placetype":"locality",
    "wof:population":136
},
  "geometry": {"coordinates":[84.490696,23.859657],"type":"Point"}
}