{
  "type": "Feature",
  "properties": {
    "gn:admin1_code":"2.0",
    "gn:admin2_code":"553.0",
    "gn:asciiname":"Kenchanahalli",
    "gn:country_code":"IN",
    "gn:dem":476,
    "gn:feature_class":"P",
    "gn:feature_code":"PPL",
    "gn:name":"Kench\u0101nahalli",
    "gn:population":0,
    "gn:timezone":"Asia/Kolkata",
    "iso:country":"IN",
    "wof:name":"Kenchanahalli",
    "wof:placetype":"locality"
},
  "geometry": {"coordinates":[77.04944999999999,14.67015],"type":"Point"}
}