{
  "type": "Feature",
  "properties": {
    "iso:country":"IN",
    "ks:ks_name":"Sankhandeita",
    "ks:ks_pop":0,
    "ks:ks_type":"VILLAGE",
    "name:eng_x_preferred":[
        "Sankhandeita"
    ],
    "wof:name":"Sankhandeita",
    "wof:placetype":"locality",
    "wof:population":0
},
  "geometry": {"coordinates":[86.070125,20.371469],"type":"Point"}
}