{
  "type": "Feature",
  "properties": {
    "gn:admin1_code":"11.0",
    "gn:admin2_code":"031",
    "gn:asciiname":"Thalog",
    "gn:country_code":"IN",
    "gn:dem":1193,
    "gn:feature_class":"P",
    "gn:feature_code":"PPL",
    "gn:name":"Th\u0101log",
    "gn:population":0,
    "gn:timezone":"Asia/Kolkata",
    "iso:country":"IN",
    "name:und_x_variant":[
        "Th\u0101log",
        "Thalog"
    ],
    "wof:name":"Thalog",
    "wof:placetype":"locality"
},
  "geometry": {"coordinates":[77.00296,31.17565],"type":"Point"}
}