{
  "type": "Feature",
  "properties": {
    "gn:admin1_code":"37",
    "gn:admin2_code":"404.0",
    "gn:asciiname":"Jhinka",
    "gn:country_code":"IN",
    "gn:dem":264,
    "gn:feature_class":"P",
    "gn:feature_code":"PPL",
    "gn:name":"Jh\u012bnk\u0101",
    "gn:population":0,
    "gn:timezone":"Asia/Kolkata",
    "iso:country":"IN",
    "ks:ks_alt_nam":"Jh\u012bnk\u0101",
    "ks:ks_name":"Jhinka",
    "ks:ks_pop":392,
    "ks:ks_type":"VILLAGE",
    "name:eng_x_preferred":[
        "Jhinka"
    ],
    "name:eng_x_variant":[
        "Jh\u012bnk\u0101"
    ],
    "wof:name":"Jhinka",
    "wof:placetype":"locality",
    "wof:population":392
},
  "geometry": {"coordinates":[82.669884,22.188985],"type":"Point"}
}