{
  "type": "Feature",
  "properties": {
    "iso:country":"IN",
    "ks:ks_alt_nam":"SIKARI BARI",
    "ks:ks_name":"Sikari Bari",
    "ks:ks_pop":126,
    "ks:ks_type":"HABITATION",
    "name:eng_x_preferred":[
        "Sikari Bari"
    ],
    "wof:name":"Sikari Bari",
    "wof:placetype":"locality",
    "wof:population":126
},
  "geometry": {"coordinates":[91.70734899999999,24.12146],"type":"Point"}
}