{
  "type": "Feature",
  "properties": {
    "iso:country":"IN",
    "ks:ks_name":"Gajuwa Kewat Ka Purwa",
    "ks:ks_pop":56,
    "ks:ks_type":"HABITATION",
    "name:eng_x_preferred":[
        "Gajuwa Kewat Ka Purwa"
    ],
    "wof:name":"Gajuwa Kewat Ka Purwa",
    "wof:placetype":"locality",
    "wof:population":56
},
  "geometry": {"coordinates":[80.77245499999999,25.455055],"type":"Point"}
}