{
  "type": "Feature",
  "properties": {
    "iso:country":"IN",
    "ks:ks_name":"Bas Kishansingh",
    "ks:ks_pop":155,
    "ks:ks_type":"HABITATION",
    "ks:ks_uagg_main":0,
    "name:eng_x_preferred":[
        "Bas Kishansingh"
    ],
    "wof:name":"Bas Kishansingh",
    "wof:placetype":"neighbourhood",
    "wof:population":155
},
  "geometry": {"coordinates":[78.160968,27.283725],"type":"Point"}
}