{
  "type": "Feature",
  "properties": {
    "iso:country":"IN",
    "ks:ks_name":"Madhura West",
    "ks:ks_pop":4990,
    "ks:ks_type":"HABITATION",
    "name:eng_x_preferred":[
        "Madhura West"
    ],
    "wof:name":"Madhura West",
    "wof:placetype":"locality",
    "wof:population":4990
},
  "geometry": {"coordinates":[87.103944,26.343882],"type":"Point"}
}