{
  "type": "Feature",
  "properties": {
    "gn:admin1_code":"36",
    "gn:admin2_code":"197.0",
    "gn:asciiname":"Bhopapur",
    "gn:country_code":"IN",
    "gn:dem":82,
    "gn:feature_class":"P",
    "gn:feature_code":"PPL",
    "gn:name":"Bhop\u0101pur",
    "gn:population":0,
    "gn:timezone":"Asia/Kolkata",
    "iso:country":"IN",
    "ks:ks_alt_nam":"Bhop\u0101pur",
    "ks:ks_name":"Bhopapur",
    "ks:ks_pop":575,
    "ks:ks_type":"VILLAGE",
    "ks:ks_uagg_main":0,
    "name:eng_x_preferred":[
        "Bhopapur"
    ],
    "name:eng_x_variant":[
        "Bhop\u0101pur"
    ],
    "wof:name":"Bhopapur",
    "wof:placetype":"neighbourhood",
    "wof:population":575
},
  "geometry": {"coordinates":[82.930944,25.463036],"type":"Point"}
}