{
  "type": "Feature",
  "properties": {
    "gn:admin1_code":"35.0",
    "gn:admin2_code":"453.0",
    "gn:asciiname":"Sidho",
    "gn:country_code":"IN",
    "gn:dem":662,
    "gn:feature_class":"P",
    "gn:feature_code":"PPL",
    "gn:name":"S\u012bdho",
    "gn:population":0,
    "gn:timezone":"Asia/Kolkata",
    "iso:country":"IN",
    "wof:name":"Sidho",
    "wof:placetype":"locality"
},
  "geometry": {"coordinates":[80.83327,23.04329],"type":"Point"}
}