{
  "type": "Feature",
  "properties": {
    "gn:admin1_code":"25.0",
    "gn:admin2_code":"606.0",
    "gn:asciiname":"Subanravpettai",
    "gn:country_code":"IN",
    "gn:dem":140,
    "gn:feature_class":"P",
    "gn:feature_code":"PPL",
    "gn:name":"Sub\u0101nr\u0101vpettai",
    "gn:population":0,
    "gn:timezone":"Asia/Kolkata",
    "iso:country":"IN",
    "ks:ks_alt_nam":"Subanrao pettai",
    "ks:ks_name":"Subanrao Pettai",
    "ks:ks_pop":361,
    "ks:ks_type":"HABITATION",
    "ks:ks_uagg_main":0,
    "name:eng_x_preferred":[
        "Subanrao Pettai"
    ],
    "wof:name":"Subanrao Pettai",
    "wof:placetype":"locality",
    "wof:population":361
},
  "geometry": {"coordinates":[79.314038,12.6759],"type":"Point"}
}