{
  "type": "Feature",
  "properties": {
    "iso:country":"IN",
    "ks:ks_name":"Patbil",
    "ks:ks_pop":7,
    "ks:ks_type":"HABITATION",
    "name:eng_x_preferred":[
        "Patbil"
    ],
    "wof:name":"Patbil",
    "wof:placetype":"locality",
    "wof:population":7
},
  "geometry": {"coordinates":[86.162818,21.628062],"type":"Point"}
}