{
  "type": "Feature",
  "properties": {
    "iso:country":"IN",
    "ks:ks_name":"Vasanthumadigapalli",
    "ks:ks_pop":79,
    "ks:ks_type":"HABITATION",
    "name:eng_x_preferred":[
        "Vasanthumadigapalli"
    ],
    "wof:name":"Vasanthumadigapalli",
    "wof:placetype":"locality",
    "wof:population":79
},
  "geometry": {"coordinates":[78.698837,14.228773],"type":"Point"}
}