{
  "type": "Feature",
  "properties": {
    "iso:country":"IN",
    "ks:ks_name":"Metaguda",
    "ks:ks_pop":62,
    "ks:ks_type":"HABITATION",
    "name:eng_x_preferred":[
        "Metaguda"
    ],
    "wof:name":"Metaguda",
    "wof:placetype":"locality",
    "wof:population":62
},
  "geometry": {"coordinates":[81.58902399999999,18.085861],"type":"Point"}
}