{
  "type": "Feature",
  "properties": {
    "gn:admin1_code":"39.0",
    "gn:admin2_code":"66.0",
    "gn:asciiname":"Mahrora",
    "gn:country_code":"IN",
    "gn:dem":1583,
    "gn:feature_class":"P",
    "gn:feature_code":"PPL",
    "gn:name":"Mahrora",
    "gn:population":0,
    "gn:timezone":"Asia/Kolkata",
    "iso:country":"IN",
    "ks:ks_name":"Mahrora",
    "ks:ks_pop":605,
    "ks:ks_type":"VILLAGE",
    "name:eng_x_preferred":[
        "Mahrora"
    ],
    "wof:name":"Mahrora",
    "wof:placetype":"locality",
    "wof:population":605
},
  "geometry": {"coordinates":[79.395112,29.429299],"type":"Point"}
}