{
  "type": "Feature",
  "properties": {
    "iso:country":"IN",
    "ks:ks_name":"Majhitoli",
    "ks:ks_pop":376,
    "ks:ks_type":"HABITATION",
    "name:eng_x_preferred":[
        "Majhitoli"
    ],
    "wof:name":"Majhitoli",
    "wof:placetype":"locality",
    "wof:population":376
},
  "geometry": {"coordinates":[85.262929,23.557734],"type":"Point"}
}