{
  "type": "Feature",
  "properties": {
    "gn:admin1_code":"23.0",
    "gn:admin2_code":"52.0",
    "gn:asciiname":"Kotla Adhrera",
    "gn:country_code":"IN",
    "gn:dem":300,
    "gn:feature_class":"P",
    "gn:feature_code":"PPL",
    "gn:name":"Kotla Adhrera",
    "gn:population":0,
    "gn:timezone":"Asia/Kolkata",
    "iso:country":"IN",
    "wof:name":"Kotla Adhrera",
    "wof:placetype":"neighbourhood"
},
  "geometry": {"coordinates":[76.57622000000001,30.8512],"type":"Point"}
}