{
  "type": "Feature",
  "properties": {
    "iso:country":"IN",
    "ks:ks_name":"Arappuleeswararkovil",
    "ks:ks_pop":34,
    "ks:ks_type":"HABITATION",
    "ks:ks_uagg_main":0,
    "name:eng_x_preferred":[
        "Arappuleeswararkovil"
    ],
    "wof:name":"Arappuleeswararkovil",
    "wof:placetype":"neighbourhood",
    "wof:population":34
},
  "geometry": {"coordinates":[78.390052,11.265203],"type":"Point"}
}