{
  "type": "Feature",
  "properties": {
    "gn:admin1_code":"36.0",
    "gn:admin2_code":"192.0",
    "gn:asciiname":"Sheoraj Bhar Kapura",
    "gn:country_code":"IN",
    "gn:dem":76,
    "gn:feature_class":"P",
    "gn:feature_code":"PPL",
    "gn:name":"Sheor\u0101j Bhar Kapura",
    "gn:population":0,
    "gn:timezone":"Asia/Kolkata",
    "iso:country":"IN",
    "wof:name":"Sheoraj Bhar Kapura",
    "wof:placetype":"locality"
},
  "geometry": {"coordinates":[83.50671,26.11189],"type":"Point"}
}