{
  "type": "Feature",
  "properties": {
    "iso:country":"IN",
    "ks:ks_alt_nam":"Dullopur mal",
    "ks:ks_name":"Dullopur Mal",
    "ks:ks_pop":568,
    "ks:ks_type":"HABITATION",
    "name:eng_x_preferred":[
        "Dullopur Mal"
    ],
    "wof:name":"Dullopur Mal",
    "wof:placetype":"locality",
    "wof:population":568
},
  "geometry": {"coordinates":[81.062389,23.002146],"type":"Point"}
}