{
  "type": "Feature",
  "properties": {
    "gn:admin1_code":"39.0",
    "gn:admin2_code":"061",
    "gn:asciiname":"Bandhli",
    "gn:country_code":"IN",
    "gn:dem":981,
    "gn:feature_class":"P",
    "gn:feature_code":"PPL",
    "gn:name":"Bandhli",
    "gn:population":0,
    "gn:timezone":"Asia/Kolkata",
    "iso:country":"IN",
    "wof:name":"Bandhli",
    "wof:placetype":"locality"
},
  "geometry": {"coordinates":[78.62522,29.99187],"type":"Point"}
}