{
  "type": "Feature",
  "properties": {
    "iso:country":"IN",
    "ks:ks_name":"Balgaon",
    "ks:ks_pop":563,
    "ks:ks_type":"VILLAGE",
    "name:eng_x_preferred":[
        "Balgaon"
    ],
    "wof:name":"Balgaon",
    "wof:placetype":"locality",
    "wof:population":563
},
  "geometry": {"coordinates":[85.591661,26.066401],"type":"Point"}
}