{
  "type": "Feature",
  "properties": {
    "iso:country":"IN",
    "ks:ks_name":"Mopahari",
    "ks:ks_pop":10,
    "ks:ks_type":"VILLAGE",
    "name:eng_x_preferred":[
        "Mopahari"
    ],
    "wof:name":"Mopahari",
    "wof:placetype":"locality",
    "wof:population":10
},
  "geometry": {"coordinates":[87.444802,25.179403],"type":"Point"}
}