{
  "type": "Feature",
  "properties": {
    "gn:admin1_code":"34.0",
    "gn:admin2_code":"217.0",
    "gn:asciiname":"Baijalha",
    "gn:country_code":"IN",
    "gn:dem":74,
    "gn:feature_class":"P",
    "gn:feature_code":"PPL",
    "gn:name":"Baijalha",
    "gn:population":0,
    "gn:timezone":"Asia/Kolkata",
    "iso:country":"IN",
    "ks:ks_name":"Baijalha",
    "ks:ks_pop":1182,
    "ks:ks_type":"VILLAGE",
    "ks:ks_uagg_main":0,
    "name:eng_x_preferred":[
        "Baijalha"
    ],
    "wof:name":"Baijalha",
    "wof:placetype":"neighbourhood",
    "wof:population":1182
},
  "geometry": {"coordinates":[84.26483,26.501611],"type":"Point"}
}