{
  "type": "Feature",
  "properties": {
    "gn:admin1_code":"39.0",
    "gn:admin2_code":"66.0",
    "gn:asciiname":"Mohanpur Rautila",
    "gn:country_code":"IN",
    "gn:dem":325,
    "gn:feature_class":"P",
    "gn:feature_code":"PPL",
    "gn:name":"Mohanpur Rautila",
    "gn:population":0,
    "gn:timezone":"Asia/Kolkata",
    "iso:country":"IN",
    "name:und_x_variant":[
        "Bagi\u0101"
    ],
    "wof:name":"Mohanpur Rautila",
    "wof:placetype":"locality"
},
  "geometry": {"coordinates":[79.18300000000001,29.31587],"type":"Point"}
}