{
  "type": "Feature",
  "properties": {
    "iso:country":"IN",
    "ks:ks_alt_nam":"MUNNA SINGH KOTHAR",
    "ks:ks_name":"Munna Singh Kothar",
    "ks:ks_pop":78,
    "ks:ks_type":"HABITATION",
    "name:eng_x_preferred":[
        "Munna Singh Kothar"
    ],
    "wof:name":"Munna Singh Kothar",
    "wof:placetype":"locality",
    "wof:population":78
},
  "geometry": {"coordinates":[81.47141999999999,27.339093],"type":"Point"}
}