{
  "type": "Feature",
  "properties": {
    "iso:country":"IN",
    "ks:ks_name":"Belkanlia",
    "ks:ks_pop":68,
    "ks:ks_type":"VILLAGE",
    "name:eng_x_preferred":[
        "Belkanlia"
    ],
    "wof:name":"Belkanlia",
    "wof:placetype":"locality",
    "wof:population":68
},
  "geometry": {"coordinates":[86.81320700000001,23.031686],"type":"Point"}
}