{
  "type": "Feature",
  "properties": {
    "iso:country":"IN",
    "name:ara_x_preferred":[
        "\u0645\u0633\u062a\u0639\u0645\u0631\u0629 \u0641\u064a\u0631\u0646\u062f\u0631\u0627 \u0646\u0627\u062c\u0627\u0631"
    ],
    "name:ben_bn_x_preferred":[
        "\u09ac\u09c0\u09b0\u09c7\u09a8\u09cd\u09a6\u09cd\u09b0 \u09a8\u0997\u09b0 \u0995\u09b2\u09cb\u09a8\u09c0"
    ],
    "name:ben_in_x_preferred":[
        "\u09ac\u09c0\u09b0\u09c7\u09a8\u09cd\u09a6\u09cd\u09b0 \u09a8\u0997\u09b0 \u0995\u09b2\u09cb\u09a8\u09c0"
    ],
    "name:eng_x_preferred":[
        "Virendra Nagar Colony"
    ],
    "name:guj_x_preferred":[
        "\u0ab5\u0abf\u0ab0\u0ac7\u0aa8\u0acd\u0aa6\u0acd\u0ab0 \u0aa8\u0a97\u0ab0 \u0a95\u0acb\u0ab2\u0acb\u0aa8\u0ac0"
    ],
    "name:hin_x_preferred":[
        "\u0935\u0940\u0930\u0947\u0928\u094d\u0926\u094d\u0930 \u0928\u0917\u0930 \u0915\u0949\u0932\u094b\u0928\u0940"
    ],
    "name:kan_x_preferred":[
        "\u0cb5\u0cc0\u0cb0\u0cc7\u0c82\u0ca6\u0ccd\u0cb0 \u0ca8\u0c97\u0cb0 \u0c95\u0cbe\u0cb2\u0cca\u0ca8\u0cbf"
    ],
    "name:mal_x_preferred":[
        "\u0d35\u0d3f\u0d1c\u0d2f\u0d28\u0d17\u0d30\u0d4d"
    ],
    "name:mar_x_preferred":[
        "\u0935\u0940\u0930\u0947\u0902\u0926\u094d\u0930 \u0928\u0917\u0930 \u0915\u0949\u0932\u0928\u0940"
    ],
    "name:pan_x_preferred":[
        "\u0a35\u0a3f\u0a30\u0a47\u0a02\u0a26\u0a30\u0a3e \u0a28\u0a17\u0a30 \u0a15\u0a32\u0a4c\u0a28\u0a40"
    ],
    "name:tam_x_preferred":[
        "\u0bb5\u0bc0\u0bb0\u0bc7\u0ba8\u0bcd\u0ba4\u0bbf\u0bb0 \u0ba8\u0b95\u0bb0\u0bcd \u0b95\u0bc1\u0b9f\u0bbf\u0baf\u0bbf\u0bb0\u0bc1\u0baa\u0bcd\u0baa\u0bc1"
    ],
    "name:tel_x_preferred":[
        "\u0c35\u0c40\u0c30\u0c47\u0c02\u0c26\u0c4d\u0c30 \u0c28\u0c17\u0c30\u0c4d \u0c15\u0c3e\u0c32\u0c28\u0c40"
    ],
    "name:urd_x_preferred":[
        "\u0648\u06cc\u0631\u06cc\u0646\u062f\u0631 \u0646\u06af\u0631 \u06a9\u0627\u0644\u0648\u0646\u06cc"
    ],
    "qs:gn_adm0_cc":"IN",
    "qs:gn_local":1268865,
    "qs:gn_nam_loc":"Jodhpur, Jodhpur, Rajasthan, IN",
    "qs:gn_namadm1":"24",
    "qs:local_max":5790,
    "qs:local_sum":10087,
    "qs:localhoods":11,
    "qs:name":"Virendra Nagar Colony",
    "qs:name_adm0":"India",
    "qs:name_adm1":"Rajasthan",
    "qs:name_adm2":"Jodhpur",
    "qs:name_local":"Jodhpur",
    "qs:photo_max":385,
    "qs:photo_sum":682,
    "qs:placetype":"Suburb",
    "qs:quad_count":11,
    "qs:woe_adm0":23424848,
    "qs:woe_adm1":2345757,
    "qs:woe_adm2":12586667,
    "qs:woe_lau":0,
    "qs:woe_local":2295392,
    "qs:woe_ver":"7.10.0",
    "wof:lang":[
        "eng"
    ],
    "wof:name":"Virendra Nagar Colony",
    "wof:placetype":"neighbourhood"
},
  "geometry": {"coordinates":[73.035498,26.351749],"type":"Point"}
}