{
  "type": "Feature",
  "properties": {
    "iso:country":"IN",
    "name:eng_x_preferred":[
        "Virendra Nagar Colony"
    ],
    "name:unk_x_variant":[
        "Virendra Nagar Colony"
    ],
    "qs:gn_adm0_cc":"IN",
    "qs:gn_local":1268865,
    "qs:gn_nam_loc":"Jodhpur, Jodhpur, Rajasthan, IN",
    "qs:gn_namadm1":"24",
    "qs:local_max":5790,
    "qs:local_sum":10087,
    "qs:localhoods":11,
    "qs:name":"Virendra Nagar Colony",
    "qs:name_adm0":"India",
    "qs:name_adm1":"Rajasthan",
    "qs:name_adm2":"Jodhpur",
    "qs:name_local":"Jodhpur",
    "qs:photo_max":385,
    "qs:photo_sum":682,
    "qs:placetype":"Suburb",
    "qs:quad_count":11,
    "qs:woe_adm0":23424848,
    "qs:woe_adm1":2345757,
    "qs:woe_adm2":12586667,
    "qs:woe_lau":0,
    "qs:woe_local":2295392,
    "qs:woe_ver":"7.10.0",
    "wof:lang":[
        "eng"
    ],
    "wof:name":"Virendra Nagar Colony",
    "wof:placetype":"neighbourhood"
},
  "geometry": {"coordinates":[73.035498,26.351749],"type":"Point"}
}