{
  "type": "Feature",
  "properties": {
    "iso:country":"IN",
    "ks:ks_name":"Bagua",
    "ks:ks_pop":325,
    "ks:ks_type":"HABITATION",
    "ks:ks_uagg_main":0,
    "name:eng_x_preferred":[
        "Bagua"
    ],
    "wof:name":"Bagua",
    "wof:placetype":"neighbourhood",
    "wof:population":325
},
  "geometry": {"coordinates":[79.868092,26.853268],"type":"Point"}
}