{
  "type": "Feature",
  "properties": {
    "gn:admin1_code":"34.0",
    "gn:admin2_code":"238.0",
    "gn:asciiname":"Bhagrar",
    "gn:country_code":"IN",
    "gn:dem":125,
    "gn:feature_class":"P",
    "gn:feature_code":"PPL",
    "gn:name":"Bhagr\u0101r",
    "gn:population":0,
    "gn:timezone":"Asia/Kolkata",
    "iso:country":"IN",
    "wof:name":"Bhagrar",
    "wof:placetype":"locality"
},
  "geometry": {"coordinates":[86.17939,24.76433],"type":"Point"}
}