{
  "type": "Feature",
  "properties": {
    "iso:country":"IN",
    "ks:ks_name":"Sundar Khed",
    "ks:ks_pop":7841,
    "ks:ks_type":"VILLAGE",
    "ks:ks_uagg_main":0,
    "name:eng_x_preferred":[
        "Sundar Khed"
    ],
    "wof:name":"Sundar Khed",
    "wof:placetype":"neighbourhood",
    "wof:population":7841
},
  "geometry": {"coordinates":[76.19771299999999,20.521333],"type":"Point"}
}