{
  "type": "Feature",
  "properties": {
    "iso:country":"IN",
    "ks:ks_name":"Pannesingh Nagar 176",
    "ks:ks_pop":176,
    "ks:ks_type":"HABITATION",
    "name:eng_x_preferred":[
        "Pannesingh Nagar 176"
    ],
    "wof:name":"Pannesingh Nagar 176",
    "wof:placetype":"locality",
    "wof:population":176
},
  "geometry": {"coordinates":[72.202375,26.337736],"type":"Point"}
}