{
  "type": "Feature",
  "properties": {
    "iso:country":"IN",
    "ks:ks_name":"Bhuiya Tola",
    "ks:ks_pop":87,
    "ks:ks_type":"HABITATION",
    "ks:ks_uagg_main":0,
    "name:eng_x_preferred":[
        "Bhuiya Tola"
    ],
    "wof:name":"Bhuiya Tola",
    "wof:placetype":"neighbourhood",
    "wof:population":87
},
  "geometry": {"coordinates":[83.427509,24.273002],"type":"Point"}
}