{
  "type": "Feature",
  "properties": {
    "iso:country":"IN",
    "ks:ks_name":"Chirodih",
    "ks:ks_pop":246,
    "ks:ks_type":"HABITATION",
    "name:eng_x_preferred":[
        "Chirodih"
    ],
    "wof:name":"Chirodih",
    "wof:placetype":"locality",
    "wof:population":246
},
  "geometry": {"coordinates":[84.703951,22.898352],"type":"Point"}
}