{
  "type": "Feature",
  "properties": {
    "gn:admin1_code":"36.0",
    "gn:admin2_code":"184.0",
    "gn:asciiname":"Sangrampur",
    "gn:country_code":"IN",
    "gn:dem":98,
    "gn:feature_class":"P",
    "gn:feature_code":"PPL",
    "gn:name":"Sangr\u0101mpur",
    "gn:population":0,
    "gn:timezone":"Asia/Kolkata",
    "iso:country":"IN",
    "name:fra_x_preferred":[
        "Sangrampur"
    ],
    "name:new_x_preferred":[
        "\u0938\u0902\u0917\u094d\u0930\u093e\u092e\u092a\u0941\u0930 \u0917\u093e\u0935\u093f\u0938"
    ],
    "name:pol_x_preferred":[
        "Sangrampur"
    ],
    "wof:name":"Sangrampur",
    "wof:placetype":"locality"
},
  "geometry": {"coordinates":[82.71687,27.369],"type":"Point"}
}