{
  "type": "Feature",
  "properties": {
    "gn:admin1_code":"35",
    "gn:admin2_code":"423.0",
    "gn:asciiname":"Erwara",
    "gn:country_code":"IN",
    "gn:dem":448,
    "gn:feature_class":"P",
    "gn:feature_code":"PPL",
    "gn:name":"Erw\u0101ra",
    "gn:population":0,
    "gn:timezone":"Asia/Kolkata",
    "iso:country":"IN",
    "wof:name":"Erwara",
    "wof:placetype":"locality"
},
  "geometry": {"coordinates":[77.69563000000002,25.04946],"type":"Point"}
}