{
  "type": "Feature",
  "properties": {
    "gn:admin1_code":"35.0",
    "gn:admin2_code":"442.0",
    "gn:asciiname":"Semli Kalan",
    "gn:country_code":"IN",
    "gn:dem":412,
    "gn:feature_class":"P",
    "gn:feature_code":"PPL",
    "gn:name":"Semli Kal\u0101n",
    "gn:population":0,
    "gn:timezone":"Asia/Kolkata",
    "iso:country":"IN",
    "ks:ks_alt_nam":"Semli Kal\u0101n",
    "ks:ks_name":"Semli Kalan",
    "ks:ks_type":"VILLAGE",
    "ks:ks_uagg_main":0,
    "name:eng_x_preferred":[
        "Semli Kalan"
    ],
    "name:eng_x_variant":[
        "Semli Kal\u0101n"
    ],
    "wof:name":"Semli Kalan",
    "wof:placetype":"neighbourhood"
},
  "geometry": {"coordinates":[76.48687700000001,24.16202],"type":"Point"}
}