{
  "type": "Feature",
  "properties": {
    "gn:country":"IN",
    "gn:fcode":"PPL",
    "gn:pop":0,
    "iso:country":"IN",
    "name:cat_x_preferred":[
        "Kalasa"
    ],
    "name:eng_x_preferred":[
        "Kalasa"
    ],
    "name:kan_x_preferred":[
        "Kalgundi Sri Marulasidheshwara swami temple"
    ],
    "name:nld_x_preferred":[
        "Kalasa"
    ],
    "name:san_x_preferred":[
        "\u0915\u0933\u0938"
    ],
    "name:unk_x_variant":[
        "Kalsa"
    ],
    "qs:name":"Kalasinda",
    "qs:name_adm0":"India",
    "qs:name_adm1":"Karnataka",
    "qs:photos_9r":0,
    "qs:photos_sr":0,
    "qs:placetype":"Town",
    "qs:pop_sr":"0",
    "wof:name":"Kalasinda",
    "wof:placetype":"locality",
    "wof:population":0
},
  "geometry": {"coordinates":[75.35711999999999,13.23182],"type":"Point"}
}