{
  "type": "Feature",
  "properties": {
    "iso:country":"IN",
    "ks:ks_name":"Sanphatamunda",
    "ks:ks_pop":50,
    "ks:ks_type":"HABITATION",
    "name:eng_x_preferred":[
        "Sanphatamunda"
    ],
    "wof:name":"Sanphatamunda",
    "wof:placetype":"locality",
    "wof:population":50
},
  "geometry": {"coordinates":[83.465121,21.026078],"type":"Point"}
}