{
  "type": "Feature",
  "properties": {
    "gn:admin1_code":"39.0",
    "gn:admin2_code":"061",
    "gn:asciiname":"Silni",
    "gn:country_code":"IN",
    "gn:dem":808,
    "gn:feature_class":"P",
    "gn:feature_code":"PPL",
    "gn:name":"Silni",
    "gn:population":0,
    "gn:timezone":"Asia/Kolkata",
    "iso:country":"IN",
    "ks:ks_name":"Silri",
    "ks:ks_pop":52,
    "ks:ks_type":"VILLAGE",
    "name:eng_x_preferred":[
        "Silri"
    ],
    "name:eng_x_variant":[
        "Silni"
    ],
    "wof:name":"Silri",
    "wof:placetype":"locality",
    "wof:population":52
},
  "geometry": {"coordinates":[78.641571,29.976597],"type":"Point"}
}