{
  "type": "Feature",
  "properties": {
    "iso:country":"IN",
    "ks:ks_name":"Palamkadavu Jn",
    "ks:ks_pop":2933,
    "ks:ks_type":"HABITATION",
    "name:eng_x_preferred":[
        "Palamkadavu Jn"
    ],
    "wof:name":"Palamkadavu Jn",
    "wof:placetype":"locality",
    "wof:population":2933
},
  "geometry": {"coordinates":[76.44612600000001,9.791694],"type":"Point"}
}