{
  "type": "Feature",
  "properties": {
    "gn:admin1_code":"36",
    "gn:admin2_code":"185.0",
    "gn:asciiname":"Suratgarh",
    "gn:country_code":"IN",
    "gn:dem":90,
    "gn:feature_class":"P",
    "gn:feature_code":"PPL",
    "gn:name":"Suratgarh",
    "gn:population":0,
    "gn:timezone":"Asia/Kolkata",
    "iso:country":"IN",
    "name:ben_x_preferred":[
        "\u09b8\u09c1\u09b0\u09a4\u0997\u09a1\u09bc"
    ],
    "name:bpy_x_preferred":[
        "\u09b8\u09c1\u09b0\u09a4\u0997\u09a1\u09bc"
    ],
    "name:ceb_x_preferred":[
        "S\u016bratgarh"
    ],
    "name:deu_x_preferred":[
        "Suratgarh"
    ],
    "name:hif_x_preferred":[
        "Suratgarh"
    ],
    "name:hin_x_preferred":[
        "\u0938\u0942\u0930\u0924\u0917\u0922\u093c"
    ],
    "name:ita_x_preferred":[
        "Suratgarh"
    ],
    "name:mlg_x_preferred":[
        "Suratgarh"
    ],
    "name:msa_x_preferred":[
        "Suratgarh"
    ],
    "name:ori_x_preferred":[
        "\u0b38\u0b41\u0b30\u0b3e\u0b1f\u0b17\u0b21\u0b3c"
    ],
    "name:pam_x_preferred":[
        "Suratgarh"
    ],
    "name:por_x_preferred":[
        "Suratgarh"
    ],
    "name:swe_x_preferred":[
        "S\u016bratgarh"
    ],
    "name:urd_x_preferred":[
        "\u0633\u0648\u0631\u062a \u06af\u0691\u06be"
    ],
    "name:vie_x_preferred":[
        "Suratgarh"
    ],
    "name:zho_x_preferred":[
        "\u82cf\u62c9\u7279\u52a0\u5c14"
    ],
    "wof:name":"Suratgarh",
    "wof:placetype":"locality"
},
  "geometry": {"coordinates":[82.6788,26.93215],"type":"Point"}
}