{
  "type": "Feature",
  "properties": {
    "gn:admin1_code":"34",
    "gn:admin2_code":"219.0",
    "gn:asciiname":"Nagra",
    "gn:country_code":"IN",
    "gn:dem":60,
    "gn:feature_class":"P",
    "gn:feature_code":"PPL",
    "gn:name":"Nagra",
    "gn:population":0,
    "gn:timezone":"Asia/Kolkata",
    "iso:country":"IN",
    "name:cat_x_preferred":[
        "Nagra"
    ],
    "name:fin_x_preferred":[
        "Nagra"
    ],
    "name:fra_x_preferred":[
        "Nagra"
    ],
    "name:ina_x_preferred":[
        "Nagra"
    ],
    "name:ita_x_preferred":[
        "Nagra"
    ],
    "name:pol_x_preferred":[
        "Nagra"
    ],
    "name:rus_x_preferred":[
        "Nagra"
    ],
    "name:spa_x_preferred":[
        "Nagra"
    ],
    "wof:name":"Nagra",
    "wof:placetype":"locality"
},
  "geometry": {"coordinates":[84.75341,25.90145],"type":"Point"}
}