{
  "type": "Feature",
  "properties": {
    "iso:country":"IN",
    "ks:ks_name":"Tangani Nalbari",
    "ks:ks_pop":339,
    "ks:ks_type":"HABITATION",
    "name:eng_x_preferred":[
        "Tangani Nalbari"
    ],
    "wof:name":"Tangani Nalbari",
    "wof:placetype":"locality",
    "wof:population":339
},
  "geometry": {"coordinates":[94.733307,27.484379],"type":"Point"}
}