{
  "type": "Feature",
  "properties": {
    "iso:country":"IN",
    "ks:ks_name":"Turtipur Elha",
    "ks:ks_pop":4729,
    "ks:ks_type":"VILLAGE",
    "ks:ks_uagg_main":0,
    "name:eng_x_preferred":[
        "Turtipur Elha"
    ],
    "wof:name":"Turtipur Elha",
    "wof:placetype":"neighbourhood",
    "wof:population":4729
},
  "geometry": {"coordinates":[78.552882,28.588125],"type":"Point"}
}