{
  "type": "Feature",
  "properties": {
    "iso:country":"IN",
    "ks:ks_name":"Dharsepur",
    "ks:ks_pop":0,
    "ks:ks_type":"VILLAGE",
    "name:eng_x_preferred":[
        "Dharsepur"
    ],
    "wof:name":"Dharsepur",
    "wof:placetype":"locality",
    "wof:population":0
},
  "geometry": {"coordinates":[79.25790499999999,27.363118],"type":"Point"}
}