{
  "type": "Feature",
  "properties": {
    "iso:country":"IN",
    "ks:ks_name":"Nattarasankottai",
    "ks:ks_pop":628,
    "ks:ks_type":"HABITATION",
    "name:eng_x_preferred":[
        "Nattarasankottai"
    ],
    "wof:name":"Nattarasankottai",
    "wof:placetype":"locality",
    "wof:population":628
},
  "geometry": {"coordinates":[79.168886,10.669757],"type":"Point"}
}