{
  "type": "Feature",
  "properties": {
    "iso:country":"IN",
    "ks:ks_name":"Goron Ka Tala",
    "ks:ks_pop":90,
    "ks:ks_type":"VILLAGE",
    "name:eng_x_preferred":[
        "Goron Ka Tala"
    ],
    "wof:name":"Goron Ka Tala",
    "wof:placetype":"locality",
    "wof:population":90
},
  "geometry": {"coordinates":[71.14958900000001,25.272578],"type":"Point"}
}