{
  "type": "Feature",
  "properties": {
    "gn:admin1_code":"38.0",
    "gn:admin2_code":"348.0",
    "gn:asciiname":"Pakartanr",
    "gn:country_code":"IN",
    "gn:dem":402,
    "gn:feature_class":"P",
    "gn:feature_code":"PPL",
    "gn:name":"P\u0101kart\u0101nr",
    "gn:population":0,
    "gn:timezone":"Asia/Kolkata",
    "iso:country":"IN",
    "ks:ks_alt_nam":"P\u0101kart\u0101nr",
    "ks:ks_name":"Pakartanr",
    "ks:ks_pop":285,
    "ks:ks_type":"VILLAGE",
    "ks:ks_uagg_main":0,
    "name:eng_x_preferred":[
        "Pakartanr"
    ],
    "name:eng_x_variant":[
        "P\u0101kart\u0101nr"
    ],
    "wof:name":"Pakartanr",
    "wof:placetype":"neighbourhood",
    "wof:population":285
},
  "geometry": {"coordinates":[85.32966500000001,24.418482],"type":"Point"}
}