{
  "type": "Feature",
  "properties": {
    "gn:admin1_code":"28.0",
    "gn:admin2_code":"329",
    "gn:asciiname":"Baman Hat",
    "gn:country_code":"IN",
    "gn:dem":38,
    "gn:feature_class":"P",
    "gn:feature_code":"PPL",
    "gn:name":"B\u0101man H\u0101t",
    "gn:population":0,
    "gn:timezone":"Asia/Kolkata",
    "iso:country":"IN",
    "name:und_x_variant":[
        "Baman N\u0101t",
        "B\u0101man H\u0101t"
    ],
    "wof:name":"Baman Hat",
    "wof:placetype":"locality"
},
  "geometry": {"coordinates":[89.58471999999998,26.08012],"type":"Point"}
}