{
  "type": "Feature",
  "properties": {
    "iso:country":"IN",
    "ks:ks_name":"Mahadeo Mandir Shiv Mandir",
    "ks:ks_pop":286,
    "ks:ks_type":"HABITATION",
    "name:eng_x_preferred":[
        "Mahadeo Mandir Shiv Mandir"
    ],
    "wof:name":"Mahadeo Mandir Shiv Mandir",
    "wof:placetype":"locality",
    "wof:population":286
},
  "geometry": {"coordinates":[71.668406,25.371086],"type":"Point"}
}