{
  "type": "Feature",
  "properties": {
    "iso:country":"IN",
    "ks:ks_name":"Zadapapada",
    "ks:ks_pop":813,
    "ks:ks_type":"HABITATION",
    "name:eng_x_preferred":[
        "Zadapapada"
    ],
    "wof:name":"Zadapapada",
    "wof:placetype":"locality",
    "wof:population":813
},
  "geometry": {"coordinates":[80.501761,20.072574],"type":"Point"}
}