{
  "type": "Feature",
  "properties": {
    "gn:admin1_code":"36.0",
    "gn:admin2_code":"149",
    "gn:asciiname":"Kundan Nagla",
    "gn:country_code":"IN",
    "gn:dem":167,
    "gn:feature_class":"P",
    "gn:feature_code":"PPL",
    "gn:name":"Kundan Nagla",
    "gn:population":0,
    "gn:timezone":"Asia/Kolkata",
    "iso:country":"IN",
    "wof:name":"Kundan Nagla",
    "wof:placetype":"locality"
},
  "geometry": {"coordinates":[79.18996,27.95298],"type":"Point"}
}