{
  "type": "Feature",
  "properties": {
    "gn:admin1_code":"36",
    "gn:admin2_code":"134.0",
    "gn:asciiname":"Hasanpur Baloch",
    "gn:country_code":"IN",
    "gn:dem":222,
    "gn:feature_class":"P",
    "gn:feature_code":"PPL",
    "gn:name":"Hasanpur Baloch",
    "gn:population":0,
    "gn:timezone":"Asia/Kolkata",
    "iso:country":"IN",
    "ks:ks_name":"Hasanpur Billoch",
    "ks:ks_pop":798,
    "ks:ks_type":"VILLAGE",
    "ks:ks_uagg_main":0,
    "name:eng_x_preferred":[
        "Hasanpur Billoch"
    ],
    "wof:name":"Hasanpur Billoch",
    "wof:placetype":"neighbourhood",
    "wof:population":798
},
  "geometry": {"coordinates":[78.48312199999999,29.086757],"type":"Point"}
}