{
  "type": "Feature",
  "properties": {
    "gn:admin1_code":"7.0",
    "gn:admin2_code":"98.0",
    "gn:asciiname":"Lado Sarai",
    "gn:country_code":"IN",
    "gn:dem":241,
    "gn:feature_class":"P",
    "gn:feature_code":"PPL",
    "gn:name":"L\u0101do Sar\u0101i",
    "gn:population":0,
    "gn:timezone":"Asia/Kolkata",
    "iso:country":"IN",
    "wof:name":"Lado Sarai",
    "wof:placetype":"locality"
},
  "geometry": {"coordinates":[77.19490999999999,28.52545],"type":"Point"}
}