{
  "type": "Feature",
  "properties": {
    "iso:country":"IN",
    "ks:ks_name":"Karbylu",
    "ks:ks_pop":307,
    "ks:ks_type":"HABITATION",
    "name:eng_x_preferred":[
        "Karbylu"
    ],
    "wof:name":"Karbylu",
    "wof:placetype":"locality",
    "wof:population":307
},
  "geometry": {"coordinates":[75.561177,13.181322],"type":"Point"}
}