{
  "type": "Feature",
  "properties": {
    "iso:country":"IN",
    "ks:ks_name":"Papadum",
    "ks:ks_pop":187,
    "ks:ks_type":"HABITATION",
    "name:eng_x_preferred":[
        "Papadum"
    ],
    "wof:name":"Papadum",
    "wof:placetype":"locality",
    "wof:population":187
},
  "geometry": {"coordinates":[83.558905,19.369444],"type":"Point"}
}