{
  "type": "Feature",
  "properties": {
    "iso:country":"IN",
    "ks:ks_name":"Jaitpura",
    "ks:ks_pop":251,
    "ks:ks_type":"HABITATION",
    "name:eng_x_preferred":[
        "Jaitpura"
    ],
    "wof:name":"Jaitpura",
    "wof:placetype":"locality",
    "wof:population":251
},
  "geometry": {"coordinates":[76.66887,24.017078],"type":"Point"}
}