{
  "type": "Feature",
  "properties": {
    "iso:country":"IN",
    "ks:ks_name":"Basti Gadde",
    "ks:ks_pop":140,
    "ks:ks_type":"HABITATION",
    "name:eng_x_preferred":[
        "Basti Gadde"
    ],
    "wof:name":"Basti Gadde",
    "wof:placetype":"locality",
    "wof:population":140
},
  "geometry": {"coordinates":[74.615775,14.116938],"type":"Point"}
}