{
  "type": "Feature",
  "properties": {
    "gn:admin1_code":"16.0",
    "gn:admin2_code":"509.0",
    "gn:asciiname":"Ahiri",
    "gn:country_code":"IN",
    "gn:dem":211,
    "gn:feature_class":"P",
    "gn:feature_code":"PPL",
    "gn:name":"Ahiri",
    "gn:population":0,
    "gn:timezone":"Asia/Kolkata",
    "iso:country":"IN",
    "name:mal_x_preferred":[
        "\u0d06\u0d39\u0d3f\u0d30\u0d3f"
    ],
    "name:new_x_preferred":[
        "\u0930\u093e\u0917 \u0906\u0939\u0940\u0930\u0940"
    ],
    "name:tam_x_preferred":[
        "\u0b86\u0bb9\u0bbf\u0bb0\u0bbf"
    ],
    "wof:name":"Ahiri",
    "wof:placetype":"locality"
},
  "geometry": {"coordinates":[79.29484000000002,19.74016],"type":"Point"}
}