{
  "type": "Feature",
  "properties": {
    "gn:admin1_code":"36",
    "gn:admin2_code":"138.0",
    "gn:asciiname":"Inchi Buzurg",
    "gn:country_code":"IN",
    "gn:dem":229,
    "gn:feature_class":"P",
    "gn:feature_code":"PPL",
    "gn:name":"Inchi Buz\u016brg",
    "gn:population":0,
    "gn:timezone":"Asia/Kolkata",
    "iso:country":"IN",
    "wof:name":"Inchi Buzurg",
    "wof:placetype":"neighbourhood"
},
  "geometry": {"coordinates":[77.97131,29.01928],"type":"Point"}
}