{
  "type": "Feature",
  "properties": {
    "gn:admin1_code":"21",
    "gn:admin2_code":"396.0",
    "gn:asciiname":"Nangalabada",
    "gn:country_code":"IN",
    "gn:dem":467,
    "gn:feature_class":"P",
    "gn:feature_code":"PPL",
    "gn:name":"Nangalabada",
    "gn:population":0,
    "gn:timezone":"Asia/Kolkata",
    "iso:country":"IN",
    "ks:ks_name":"Langalbada",
    "ks:ks_pop":152,
    "ks:ks_type":"HABITATION",
    "name:eng_x_preferred":[
        "Langalbada"
    ],
    "name:eng_x_variant":[
        "Nangalabada"
    ],
    "wof:name":"Langalbada",
    "wof:placetype":"locality",
    "wof:population":152
},
  "geometry": {"coordinates":[83.594793,19.786272],"type":"Point"}
}