{
  "type": "Feature",
  "properties": {
    "iso:country":"IN",
    "ks:ks_name":"Balaghat",
    "ks:ks_pop":1370,
    "ks:ks_type":"VILLAGE",
    "name:eng_x_preferred":[
        "Balaghat"
    ],
    "name:hin_x_preferred":[
        "\u092c\u093e\u0932\u093e\u0918\u093e\u091f"
    ],
    "wof:name":"Balaghat",
    "wof:placetype":"locality",
    "wof:population":1370
},
  "geometry": {"coordinates":[89.63115999999999,26.299639],"type":"Point"}
}