{
  "type": "Feature",
  "properties": {
    "iso:country":"IN",
    "ks:ks_alt_nam":"BHANDARWADI",
    "ks:ks_name":"Bhandarwadi",
    "ks:ks_pop":245,
    "ks:ks_type":"HABITATION",
    "name:eng_x_preferred":[
        "Bhandarwadi"
    ],
    "wof:name":"Bhandarwadi",
    "wof:placetype":"locality",
    "wof:population":245
},
  "geometry": {"coordinates":[73.364537,16.743834],"type":"Point"}
}