{
  "type": "Feature",
  "properties": {
    "iso:country":"IN",
    "ks:ks_name":"Abapur",
    "ks:ks_pop":104,
    "ks:ks_type":"VILLAGE",
    "name:eng_x_preferred":[
        "Abapur"
    ],
    "wof:name":"Abapur",
    "wof:placetype":"locality",
    "wof:population":104
},
  "geometry": {"coordinates":[84.19761,18.903641],"type":"Point"}
}