{
  "type": "Feature",
  "properties": {
    "iso:country":"IN",
    "ks:ks_name":"Nekaraganda",
    "ks:ks_pop":39,
    "ks:ks_type":"VILLAGE",
    "name:eng_x_preferred":[
        "Nekaraganda"
    ],
    "wof:name":"Nekaraganda",
    "wof:placetype":"locality",
    "wof:population":39
},
  "geometry": {"coordinates":[84.76061300000001,20.423051],"type":"Point"}
}