{
  "type": "Feature",
  "properties": {
    "iso:country":"IN",
    "ks:ks_name":"Tukudand",
    "ks:ks_pop":1015,
    "ks:ks_type":"VILLAGE",
    "name:eng_x_preferred":[
        "Tukudand"
    ],
    "wof:name":"Tukudand",
    "wof:placetype":"locality",
    "wof:population":1015
},
  "geometry": {"coordinates":[83.255887,23.461304],"type":"Point"}
}