{
  "type": "Feature",
  "properties": {
    "iso:country":"IN",
    "ks:ks_name":"Assomiya Balijan Gaon",
    "ks:ks_pop":657,
    "ks:ks_type":"VILLAGE",
    "name:eng_x_preferred":[
        "Assomiya Balijan Gaon"
    ],
    "wof:name":"Assomiya Balijan Gaon",
    "wof:placetype":"locality",
    "wof:population":657
},
  "geometry": {"coordinates":[95.493965,27.485784],"type":"Point"}
}