{
  "type": "Feature",
  "properties": {
    "iso:country":"IN",
    "ks:ks_name":"Uttar Basantapur",
    "ks:ks_pop":1222,
    "ks:ks_type":"VILLAGE",
    "ks:ks_uagg_main":0,
    "name:eng_x_preferred":[
        "Uttar Basantapur"
    ],
    "wof:name":"Uttar Basantapur",
    "wof:placetype":"neighbourhood",
    "wof:population":1222
},
  "geometry": {"coordinates":[87.98853800000001,25.4466],"type":"Point"}
}