{
  "type": "Feature",
  "properties": {
    "gn:country":"IN",
    "gn:fcode":"PPL",
    "gn:pop":27901,
    "iso:country":"IN",
    "name:rus_x_preferred":[
        "\u041c\u0430\u043d\u0435\u0440\u0430"
    ],
    "name:unk_x_variant":[
        "Maner Sharif"
    ],
    "qs:name":"Maner",
    "qs:name_adm0":"India",
    "qs:name_adm1":"Bihar",
    "qs:photos_9k":1,
    "qs:photos_9r":1,
    "qs:photos_all":8,
    "qs:photos_sr":0,
    "qs:placetype":"Town",
    "qs:pop_sr":"7",
    "wd:wordcount":345,
    "wof:name":"Maner",
    "wof:placetype":"locality",
    "wof:population":27901
},
  "geometry": {"coordinates":[84.87418,25.64728],"type":"Point"}
}