{
  "type": "Feature",
  "properties": {
    "gn:country":"IN",
    "gn:fcode":"PPL",
    "gn:population":27901,
    "iso:country":"IN",
    "name:ben_x_preferred":[
        "\u09ae\u09be\u09a8\u09c7\u09b0"
    ],
    "name:bho_x_preferred":[
        "\u092e\u0928\u0947\u0930"
    ],
    "name:bpy_x_preferred":[
        "\u09ae\u09be\u09a8\u09c7\u09b0"
    ],
    "name:cat_x_preferred":[
        "Maner"
    ],
    "name:ceb_x_preferred":[
        "Maner"
    ],
    "name:deu_x_preferred":[
        "Maner"
    ],
    "name:eng_x_preferred":[
        "Maner"
    ],
    "name:fra_x_preferred":[
        "Maner"
    ],
    "name:hin_x_preferred":[
        "\u092e\u0928\u0947\u0930"
    ],
    "name:ita_x_preferred":[
        "Maner"
    ],
    "name:msa_x_preferred":[
        "Maner"
    ],
    "name:nan_x_preferred":[
        "Maner"
    ],
    "name:nep_x_preferred":[
        "\u092e\u0928\u0947\u0930"
    ],
    "name:new_x_preferred":[
        "\u092e\u0928\u0947\u0930"
    ],
    "name:nld_x_preferred":[
        "Maner"
    ],
    "name:ori_x_preferred":[
        "\u0b2e\u0b3e\u0b28\u0b47\u0b30\u0b4d"
    ],
    "name:por_x_preferred":[
        "Maner"
    ],
    "name:rus_x_preferred":[
        "\u041c\u0430\u043d\u0435\u0440\u0430"
    ],
    "name:spa_x_preferred":[
        "Maner"
    ],
    "name:swe_x_preferred":[
        "Maner"
    ],
    "name:und_x_variant":[
        "Maner Sharif"
    ],
    "name:urd_x_preferred":[
        "\u0645\u0646\u06d2\u0631"
    ],
    "name:vie_x_preferred":[
        "Maner"
    ],
    "name:zho_x_preferred":[
        "\u9a6c\u5185\u5c14"
    ],
    "qs:name":"Maner",
    "qs:name_adm0":"India",
    "qs:name_adm1":"Bihar",
    "qs:photos_9k":1,
    "qs:photos_9r":1,
    "qs:photos_all":8,
    "qs:photos_sr":0,
    "qs:placetype":"Town",
    "qs:pop_sr":"7",
    "wd:wordcount":345,
    "wof:name":"Maner",
    "wof:placetype":"locality",
    "wof:population":27901
},
  "geometry": {"coordinates":[84.87418,25.64728],"type":"Point"}
}