{
  "type": "Feature",
  "properties": {
    "iso:country":"IN",
    "ks:ks_alt_nam":"HARIJAN TOLA WEST",
    "ks:ks_name":"Harijan Tola West",
    "ks:ks_pop":53,
    "ks:ks_type":"HABITATION",
    "name:eng_x_preferred":[
        "Harijan Tola West"
    ],
    "wof:name":"Harijan Tola West",
    "wof:placetype":"locality",
    "wof:population":53
},
  "geometry": {"coordinates":[84.097143,26.472571],"type":"Point"}
}