{
  "type": "Feature",
  "properties": {
    "gn:admin1_code":"37",
    "gn:admin2_code":"408.0",
    "gn:asciiname":"Arbira",
    "gn:country_code":"IN",
    "gn:dem":317,
    "gn:feature_class":"P",
    "gn:feature_code":"PPL",
    "gn:name":"\u0100rb\u012bra",
    "gn:population":0,
    "gn:timezone":"Asia/Kolkata",
    "iso:country":"IN",
    "ks:ks_alt_nam":"\u0100rb\u012bra",
    "ks:ks_name":"Arbira",
    "ks:ks_pop":638,
    "ks:ks_type":"VILLAGE",
    "name:eng_x_preferred":[
        "Arbira"
    ],
    "name:eng_x_variant":[
        "\u0100rb\u012bra"
    ],
    "wof:name":"Arbira",
    "wof:placetype":"locality",
    "wof:population":638
},
  "geometry": {"coordinates":[80.87473300000001,21.141057],"type":"Point"}
}