{
  "type": "Feature",
  "properties": {
    "iso:country":"IN",
    "ks:ks_name":"Kuravapuram",
    "ks:ks_pop":3696,
    "ks:ks_type":"VILLAGE",
    "ks:ks_uagg_main":0,
    "name:eng_x_preferred":[
        "Kuravapuram"
    ],
    "wof:name":"Kuravapuram",
    "wof:placetype":"neighbourhood",
    "wof:population":3696
},
  "geometry": {"coordinates":[79.78515299999999,10.424953],"type":"Point"}
}