{
  "type": "Feature",
  "properties": {
    "iso:country":"IN",
    "ks:ks_name":"Ladiguda",
    "ks:ks_pop":79,
    "ks:ks_type":"VILLAGE",
    "name:eng_x_preferred":[
        "Ladiguda"
    ],
    "wof:name":"Ladiguda",
    "wof:placetype":"locality",
    "wof:population":79
},
  "geometry": {"coordinates":[82.322777,18.248416],"type":"Point"}
}