{
  "type": "Feature",
  "properties": {
    "iso:country":"IN",
    "ks:ks_name":"Kattadam",
    "ks:ks_pop":105,
    "ks:ks_type":"HABITATION",
    "name:eng_x_preferred":[
        "Kattadam"
    ],
    "wof:name":"Kattadam",
    "wof:placetype":"locality",
    "wof:population":105
},
  "geometry": {"coordinates":[78.794533,9.603358],"type":"Point"}
}