{
  "type": "Feature",
  "properties": {
    "gn:admin1_code":"35.0",
    "gn:admin2_code":"420.0",
    "gn:asciiname":"Dirman",
    "gn:country_code":"IN",
    "gn:dem":184,
    "gn:feature_class":"P",
    "gn:feature_code":"PPL",
    "gn:name":"Dirman",
    "gn:population":0,
    "gn:timezone":"Asia/Kolkata",
    "iso:country":"IN",
    "name:eng_x_preferred":[
        "Dirman"
    ],
    "wof:name":"Dirman",
    "wof:placetype":"locality"
},
  "geometry": {"coordinates":[78.46865,26.27323],"type":"Point"}
}