{
  "type": "Feature",
  "properties": {
    "iso:country":"IN",
    "ks:ks_name":"Tarachutia",
    "ks:ks_pop":808,
    "ks:ks_type":"VILLAGE",
    "name:eng_x_preferred":[
        "Tarachutia"
    ],
    "wof:name":"Tarachutia",
    "wof:placetype":"locality",
    "wof:population":808
},
  "geometry": {"coordinates":[86.97267600000001,23.896893],"type":"Point"}
}