{
  "type": "Feature",
  "properties": {
    "iso:country":"IN",
    "ks:ks_name":"Boyjer Alga Pt.XI",
    "ks:ks_pop":129,
    "ks:ks_type":"VILLAGE",
    "name:eng_x_preferred":[
        "Boyjer Alga Pt.XI"
    ],
    "wof:name":"Boyjer Alga Pt.XI",
    "wof:placetype":"locality",
    "wof:population":129
},
  "geometry": {"coordinates":[90.153395,26.107004],"type":"Point"}
}