{
  "type": "Feature",
  "properties": {
    "gn:admin1_code":"36.0",
    "gn:admin2_code":"135.0",
    "gn:asciiname":"Imritpur Fakhruddin",
    "gn:country_code":"IN",
    "gn:dem":198,
    "gn:feature_class":"P",
    "gn:feature_code":"PPL",
    "gn:name":"Imritpur Fakhrudd\u012bn",
    "gn:population":0,
    "gn:timezone":"Asia/Kolkata",
    "iso:country":"IN",
    "wof:name":"Imritpur Fakhruddin",
    "wof:placetype":"locality"
},
  "geometry": {"coordinates":[78.76437,28.71284],"type":"Point"}
}