{
  "type": "Feature",
  "properties": {
    "iso:country":"IN",
    "ks:ks_name":"Chitbisraon",
    "ks:ks_pop":2503,
    "ks:ks_type":"VILLAGE",
    "name:eng_x_preferred":[
        "Chitbisraon"
    ],
    "wof:name":"Chitbisraon",
    "wof:placetype":"locality",
    "wof:population":2503
},
  "geometry": {"coordinates":[83.49220200000001,24.228057],"type":"Point"}
}