{
  "type": "Feature",
  "properties": {
    "iso:country":"IN",
    "ks:ks_name":"Junoni",
    "ks:ks_pop":0,
    "ks:ks_type":"VILLAGE",
    "name:eng_x_preferred":[
        "Junoni"
    ],
    "wof:name":"Junoni",
    "wof:placetype":"locality",
    "wof:population":0
},
  "geometry": {"coordinates":[78.964929,19.851956],"type":"Point"}
}