{
  "type": "Feature",
  "properties": {
    "iso:country":"IN",
    "ks:ks_name":"Pimpalwadi",
    "ks:ks_pop":308,
    "ks:ks_type":"HABITATION",
    "name:eng_x_preferred":[
        "Pimpalwadi"
    ],
    "wof:name":"Pimpalwadi",
    "wof:placetype":"locality",
    "wof:population":308
},
  "geometry": {"coordinates":[73.637377,16.20728],"type":"Point"}
}