{
  "type": "Feature",
  "properties": {
    "iso:country":"IN",
    "ks:ks_name":"Lakha Beri",
    "ks:ks_pop":627,
    "ks:ks_type":"VILLAGE",
    "name:eng_x_preferred":[
        "Lakha Beri"
    ],
    "wof:name":"Lakha Beri",
    "wof:placetype":"locality",
    "wof:population":627
},
  "geometry": {"coordinates":[71.900606,25.399461],"type":"Point"}
}