{
  "type": "Feature",
  "properties": {
    "iso:country":"IN",
    "ks:ks_name":"Sawarar Pathar",
    "ks:ks_pop":807,
    "ks:ks_type":"VILLAGE",
    "ks:ks_uagg_main":0,
    "name:eng_x_preferred":[
        "Sawarar Pathar"
    ],
    "wof:name":"Sawarar Pathar",
    "wof:placetype":"neighbourhood",
    "wof:population":807
},
  "geometry": {"coordinates":[90.817324,26.223563],"type":"Point"}
}