{
  "type": "Feature",
  "properties": {
    "iso:country":"IN",
    "ks:ks_name":"Kiranagan",
    "ks:ks_pop":24,
    "ks:ks_type":"VILLAGE",
    "name:eng_x_preferred":[
        "Kiranagan"
    ],
    "wof:name":"Kiranagan",
    "wof:placetype":"locality",
    "wof:population":24
},
  "geometry": {"coordinates":[83.748914,20.383511],"type":"Point"}
}