{
  "type": "Feature",
  "properties": {
    "iso:country":"IN",
    "ks:ks_name":"Kholepara",
    "ks:ks_pop":200,
    "ks:ks_type":"HABITATION",
    "name:eng_x_preferred":[
        "Kholepara"
    ],
    "wof:name":"Kholepara",
    "wof:placetype":"locality",
    "wof:population":200
},
  "geometry": {"coordinates":[90.745912,26.040078],"type":"Point"}
}