{
  "type": "Feature",
  "properties": {
    "iso:country":"IN",
    "ks:ks_name":"Nadupatti",
    "ks:ks_pop":429,
    "ks:ks_type":"HABITATION",
    "ks:ks_uagg_main":0,
    "name:eng_x_preferred":[
        "Nadupatti"
    ],
    "wof:name":"Nadupatti",
    "wof:placetype":"neighbourhood",
    "wof:population":429
},
  "geometry": {"coordinates":[78.36635800000001,11.713097],"type":"Point"}
}