{
  "type": "Feature",
  "properties": {
    "gn:admin1_code":"35.0",
    "gn:admin2_code":"455.0",
    "gn:asciiname":"Rehap",
    "gn:country_code":"IN",
    "gn:dem":647,
    "gn:feature_class":"P",
    "gn:feature_code":"PPL",
    "gn:name":"Rehap",
    "gn:population":0,
    "gn:timezone":"Asia/Kolkata",
    "iso:country":"IN",
    "ks:ks_name":"Rahap",
    "ks:ks_pop":629,
    "ks:ks_type":"VILLAGE",
    "name:eng_x_preferred":[
        "Rahap"
    ],
    "name:eng_x_variant":[
        "Rehap"
    ],
    "wof:name":"Rahap",
    "wof:placetype":"locality",
    "wof:population":629
},
  "geometry": {"coordinates":[78.55667800000001,22.017156],"type":"Point"}
}