{
  "type": "Feature",
  "properties": {
    "gn:admin1_code":"10.0",
    "gn:admin2_code":"86.0",
    "gn:asciiname":"Garauli Khurd",
    "gn:country_code":"IN",
    "gn:dem":223,
    "gn:feature_class":"P",
    "gn:feature_code":"PPL",
    "gn:name":"Garauli Khurd",
    "gn:population":0,
    "gn:timezone":"Asia/Kolkata",
    "iso:country":"IN",
    "ks:ks_name":"Garauli Khurd",
    "ks:ks_type":"VILLAGE",
    "ks:ks_uagg_main":0,
    "name:ara_x_preferred":[
        "\u062c\u0627\u0631\u0648\u0644\u064a \u062e\u0648\u0631\u062f"
    ],
    "name:ben_bn_x_preferred":[
        "\u0997\u09be\u09b0\u09cc\u09b2\u09bf \u0996\u09c1\u09b0\u09cd\u09a6"
    ],
    "name:ben_in_x_preferred":[
        "\u0997\u09be\u09b0\u09cc\u09b2\u09bf \u0996\u09c1\u09b0\u09cd\u09a6"
    ],
    "name:guj_x_preferred":[
        "\u0a97\u0abe\u0ab0\u0acc\u0ab2\u0ac0 \u0a96\u0ac1\u0ab0\u0acd\u0aa6"
    ],
    "name:hin_x_preferred":[
        "\u0917\u0930\u094c\u0932\u0940 \u0916\u0941\u0930\u094d\u0926"
    ],
    "name:kan_x_preferred":[
        "\u0c97\u0cb0\u0ccc\u0cb2\u0cbf \u0c96\u0cc1\u0cb0\u0ccd\u0ca6\u0ccd"
    ],
    "name:mal_x_preferred":[
        "\u0d17\u0d30\u0d57\u0d32\u0d3f \u0d16\u0d41\u0d7c\u0d26\u0d4d"
    ],
    "name:mar_x_preferred":[
        "\u0917\u0930\u094c\u0932\u0940 \u0916\u0941\u0930\u094d\u0926"
    ],
    "name:pan_x_preferred":[
        "\u0a17\u0a30\u0a4c\u0a32\u0a40 \u0a16\u0a41\u0a30\u0a26"
    ],
    "name:tam_x_preferred":[
        "\u0b95\u0bb0\u0bcc\u0bb2\u0bbf \u0b95\u0bc1\u0bb0\u0bcd\u0ba4\u0bcd"
    ],
    "name:tel_x_preferred":[
        "\u0c17\u0c30\u0c4c\u0c32\u0c3f \u0c16\u0c41\u0c30\u0c4d\u0c26\u0c4d"
    ],
    "name:urd_x_preferred":[
        "\u06af\u0631\u0648\u0644\u06cc \u062e\u0631\u062f"
    ],
    "wof:name":"Garauli Khurd",
    "wof:placetype":"neighbourhood"
},
  "geometry": {"coordinates":[76.98033,28.44057],"type":"Point"}
}