{
  "type": "Feature",
  "properties": {
    "iso:country":"IN",
    "ks:ks_name":"Ramchandrapur",
    "ks:ks_pop":2147,
    "ks:ks_type":"VILLAGE",
    "name:eng_x_preferred":[
        "Ramchandrapur"
    ],
    "wof:name":"Ramchandrapur",
    "wof:placetype":"locality",
    "wof:population":2147
},
  "geometry": {"coordinates":[87.88047400000001,22.404274],"type":"Point"}
}