{
  "type": "Feature",
  "properties": {
    "iso:country":"IN",
    "ks:ks_name":"Itakhola No 2",
    "ks:ks_pop":2019,
    "ks:ks_type":"VILLAGE",
    "ks:ks_uagg_main":0,
    "name:eng_x_preferred":[
        "Itakhola No 2"
    ],
    "wof:name":"Itakhola No 2",
    "wof:placetype":"neighbourhood",
    "wof:population":2019
},
  "geometry": {"coordinates":[92.985377,26.806395],"type":"Point"}
}