{
  "type": "Feature",
  "properties": {
    "iso:country":"IN",
    "ks:ks_alt_nam":"Mongradih FV",
    "ks:ks_name":"Mongradih Fv",
    "ks:ks_pop":223,
    "ks:ks_type":"HABITATION",
    "name:eng_x_preferred":[
        "Mongradih Fv"
    ],
    "wof:name":"Mongradih Fv",
    "wof:placetype":"locality",
    "wof:population":223
},
  "geometry": {"coordinates":[82.174876,20.099433],"type":"Point"}
}