{
  "type": "Feature",
  "properties": {
    "gn:admin1_code":"36",
    "gn:admin2_code":"200.0",
    "gn:asciiname":"Parsiddhi",
    "gn:country_code":"IN",
    "gn:dem":320,
    "gn:feature_class":"P",
    "gn:feature_code":"PPL",
    "gn:name":"Parsiddhi",
    "gn:population":0,
    "gn:timezone":"Asia/Kolkata",
    "iso:country":"IN",
    "ks:ks_name":"Parsidhi",
    "ks:ks_pop":135,
    "ks:ks_type":"VILLAGE",
    "name:eng_x_preferred":[
        "Parsidhi"
    ],
    "name:eng_x_variant":[
        "Parsiddhi"
    ],
    "wof:name":"Parsidhi",
    "wof:placetype":"locality",
    "wof:population":135
},
  "geometry": {"coordinates":[83.16828700000001,24.66272],"type":"Point"}
}