{
  "type": "Feature",
  "properties": {
    "iso:country":"IN",
    "ks:ks_name":"Thachapuram",
    "ks:ks_pop":400,
    "ks:ks_type":"HABITATION",
    "name:eng_x_preferred":[
        "Thachapuram"
    ],
    "wof:name":"Thachapuram",
    "wof:placetype":"locality",
    "wof:population":400
},
  "geometry": {"coordinates":[77.000765,9.880036],"type":"Point"}
}