{
  "type": "Feature",
  "properties": {
    "gn:admin1_code":"39",
    "gn:admin2_code":"56.0",
    "gn:asciiname":"Piunal",
    "gn:country_code":"IN",
    "gn:dem":1977,
    "gn:feature_class":"P",
    "gn:feature_code":"PPL",
    "gn:name":"Piunal",
    "gn:population":0,
    "gn:timezone":"Asia/Kolkata",
    "iso:country":"IN",
    "wof:name":"Piunal",
    "wof:placetype":"locality"
},
  "geometry": {"coordinates":[77.78004,30.92798],"type":"Point"}
}