{
  "type": "Feature",
  "properties": {
    "gn:admin1_code":"31.0",
    "gn:admin2_code":"283",
    "gn:asciiname":"Chaltlang",
    "gn:country_code":"IN",
    "gn:dem":1048,
    "gn:feature_class":"P",
    "gn:feature_code":"PPL",
    "gn:name":"Chaltl\u0101ng",
    "gn:population":0,
    "gn:timezone":"Asia/Kolkata",
    "iso:country":"IN",
    "wof:name":"Chaltlang",
    "wof:placetype":"neighbourhood"
},
  "geometry": {"coordinates":[92.72548999999999,23.74899],"type":"Point"}
}