{
  "type": "Feature",
  "properties": {
    "gn:admin1_code":"36.0",
    "gn:admin2_code":"182.0",
    "gn:asciiname":"Pura Baghawa",
    "gn:country_code":"IN",
    "gn:dem":104,
    "gn:feature_class":"P",
    "gn:feature_code":"PPL",
    "gn:name":"Pura Bagh\u0101wa",
    "gn:population":0,
    "gn:timezone":"Asia/Kolkata",
    "iso:country":"IN",
    "wof:name":"Pura Baghawa",
    "wof:placetype":"neighbourhood"
},
  "geometry": {"coordinates":[82.30513999999999,27.27742],"type":"Point"}
}