{
  "type": "Feature",
  "properties": {
    "iso:country":"IN",
    "ks:ks_name":"Halladabylu",
    "ks:ks_pop":71,
    "ks:ks_type":"HABITATION",
    "name:eng_x_preferred":[
        "Halladabylu"
    ],
    "wof:name":"Halladabylu",
    "wof:placetype":"locality",
    "wof:population":71
},
  "geometry": {"coordinates":[75.23235699999999,13.603937],"type":"Point"}
}