{
  "type": "Feature",
  "properties": {
    "iso:country":"IN",
    "ks:ks_name":"Pathari Falia",
    "ks:ks_pop":414,
    "ks:ks_type":"HABITATION",
    "name:eng_x_preferred":[
        "Pathari Falia"
    ],
    "wof:name":"Pathari Falia",
    "wof:placetype":"locality",
    "wof:population":414
},
  "geometry": {"coordinates":[73.10941699999999,20.19],"type":"Point"}
}