{
  "type": "Feature",
  "properties": {
    "iso:country":"IN",
    "ks:ks_name":"Chak Rasthi",
    "ks:ks_pop":145,
    "ks:ks_type":"VILLAGE",
    "name:eng_x_preferred":[
        "Chak Rasthi"
    ],
    "wof:name":"Chak Rasthi",
    "wof:placetype":"locality",
    "wof:population":145
},
  "geometry": {"coordinates":[83.28219,25.749081],"type":"Point"}
}