{
  "type": "Feature",
  "properties": {
    "iso:country":"IN",
    "ks:ks_alt_nam":"Buduponi tanda",
    "ks:ks_name":"Buduponi Tanda",
    "ks:ks_pop":100,
    "ks:ks_type":"HABITATION",
    "name:eng_x_preferred":[
        "Buduponi Tanda"
    ],
    "wof:name":"Buduponi Tanda",
    "wof:placetype":"locality",
    "wof:population":100
},
  "geometry": {"coordinates":[78.23407,16.997981],"type":"Point"}
}