{
  "type": "Feature",
  "properties": {
    "iso:country":"IN",
    "ks:ks_name":"Bahamaha",
    "ks:ks_pop":5,
    "ks:ks_type":"HABITATION",
    "name:eng_x_preferred":[
        "Bahamaha"
    ],
    "wof:name":"Bahamaha",
    "wof:placetype":"locality",
    "wof:population":5
},
  "geometry": {"coordinates":[84.005889,19.748388],"type":"Point"}
}