{
  "type": "Feature",
  "properties": {
    "iso:country":"IN",
    "ks:ks_alt_nam":"5 AP",
    "ks:ks_name":"5 Ap",
    "ks:ks_pop":303,
    "ks:ks_type":"HABITATION",
    "name:eng_x_preferred":[
        "5 Ap"
    ],
    "wof:name":"5 Ap",
    "wof:placetype":"locality",
    "wof:population":303
},
  "geometry": {"coordinates":[73.80073400000001,29.177837],"type":"Point"}
}