{
  "type": "Feature",
  "properties": {
    "iso:country":"IN",
    "ks:ks_name":"Ratanapurpatna",
    "ks:ks_pop":754,
    "ks:ks_type":"VILLAGE",
    "ks:ks_uagg_main":0,
    "name:eng_x_preferred":[
        "Ratanapurpatna"
    ],
    "wof:name":"Ratanapurpatna",
    "wof:placetype":"neighbourhood",
    "wof:population":754
},
  "geometry": {"coordinates":[85.401811,19.929906],"type":"Point"}
}