{
  "type": "Feature",
  "properties": {
    "gn:admin1_code":"37",
    "gn:admin2_code":"405.0",
    "gn:asciiname":"Darri",
    "gn:country_code":"IN",
    "gn:dem":255,
    "gn:feature_class":"P",
    "gn:feature_code":"PPL",
    "gn:name":"Darr\u012b",
    "gn:population":0,
    "gn:timezone":"Asia/Kolkata",
    "iso:country":"IN",
    "wof:name":"Darri",
    "wof:placetype":"locality"
},
  "geometry": {"coordinates":[82.77323,22.02521],"type":"Point"}
}