{
  "type": "Feature",
  "properties": {
    "gn:admin1_code":"36",
    "gn:admin2_code":"192.0",
    "gn:asciiname":"Hankaripur",
    "gn:country_code":"IN",
    "gn:dem":76,
    "gn:feature_class":"P",
    "gn:feature_code":"PPL",
    "gn:name":"Hank\u0101r\u012bpur",
    "gn:population":0,
    "gn:timezone":"Asia/Kolkata",
    "iso:country":"IN",
    "ks:ks_name":"Hakaripur",
    "ks:ks_pop":106,
    "ks:ks_type":"VILLAGE",
    "ks:ks_uagg_main":0,
    "name:eng_x_preferred":[
        "Hakaripur"
    ],
    "wof:name":"Hakaripur",
    "wof:placetype":"neighbourhood",
    "wof:population":106
},
  "geometry": {"coordinates":[83.407312,25.903215],"type":"Point"}
}