{
  "type": "Feature",
  "properties": {
    "iso:country":"IN",
    "ks:ks_name":"Lambadi Thanda",
    "ks:ks_pop":250,
    "ks:ks_type":"HABITATION",
    "name:eng_x_preferred":[
        "Lambadi Thanda"
    ],
    "wof:name":"Lambadi Thanda",
    "wof:placetype":"locality",
    "wof:population":250
},
  "geometry": {"coordinates":[78.66462,18.941975],"type":"Point"}
}