{
  "type": "Feature",
  "properties": {
    "iso:country":"IN",
    "ks:ks_name":"Jodhpur",
    "ks:ks_pop":1050,
    "ks:ks_type":"HABITATION",
    "name:eng_x_preferred":[
        "Jodhpur"
    ],
    "wof:name":"Jodhpur",
    "wof:placetype":"locality",
    "wof:population":1050
},
  "geometry": {"coordinates":[73.655417,23.015083],"type":"Point"}
}