{
  "type": "Feature",
  "properties": {
    "iso:country":"IN",
    "ks:ks_name":"Saiyon Ki Basti",
    "ks:ks_pop":215,
    "ks:ks_type":"VILLAGE",
    "name:eng_x_preferred":[
        "Saiyon Ki Basti"
    ],
    "wof:name":"Saiyon Ki Basti",
    "wof:placetype":"locality",
    "wof:population":215
},
  "geometry": {"coordinates":[70.930183,25.558],"type":"Point"}
}