{
  "type": "Feature",
  "properties": {
    "iso:country":"IN",
    "ks:ks_name":"Odderavanipally",
    "ks:ks_pop":46,
    "ks:ks_type":"HABITATION",
    "name:eng_x_preferred":[
        "Odderavanipally"
    ],
    "wof:name":"Odderavanipally",
    "wof:placetype":"locality",
    "wof:population":46
},
  "geometry": {"coordinates":[79.047286,18.319214],"type":"Point"}
}