{
  "type": "Feature",
  "properties": {
    "gn:admin1_code":"21.0",
    "gn:admin2_code":"398.0",
    "gn:asciiname":"Lambatapadu",
    "gn:country_code":"IN",
    "gn:dem":963,
    "gn:feature_class":"P",
    "gn:feature_code":"PPL",
    "gn:name":"Lambatap\u0101du",
    "gn:population":0,
    "gn:timezone":"Asia/Kolkata",
    "iso:country":"IN",
    "wof:name":"Lambatapadu",
    "wof:placetype":"locality"
},
  "geometry": {"coordinates":[83.01141,18.51988],"type":"Point"}
}