{
  "type": "Feature",
  "properties": {
    "gn:admin1_code":"21.0",
    "gn:admin2_code":"398.0",
    "gn:asciiname":"Lambatapadu",
    "gn:country_code":"IN",
    "gn:dem":963,
    "gn:feature_class":"P",
    "gn:feature_code":"PPL",
    "gn:name":"Lambatap\u0101du",
    "gn:population":0,
    "gn:timezone":"Asia/Kolkata",
    "iso:country":"IN",
    "ks:ks_name":"Lamtapadu",
    "ks:ks_pop":88,
    "ks:ks_type":"HABITATION",
    "name:eng_x_preferred":[
        "Lamtapadu"
    ],
    "name:eng_x_variant":[
        "Lambatapadu"
    ],
    "wof:name":"Lamtapadu",
    "wof:placetype":"locality",
    "wof:population":88
},
  "geometry": {"coordinates":[83.01262800000001,18.519221],"type":"Point"}
}