{
  "type": "Feature",
  "properties": {
    "gn:admin1_code":"19.0",
    "gn:admin2_code":"583.0",
    "gn:asciiname":"Oblapur",
    "gn:country_code":"IN",
    "gn:dem":873,
    "gn:feature_class":"P",
    "gn:feature_code":"PPL",
    "gn:name":"Obl\u0101p\u016br",
    "gn:population":0,
    "gn:timezone":"Asia/Kolkata",
    "iso:country":"IN",
    "wof:name":"Oblapur",
    "wof:placetype":"neighbourhood"
},
  "geometry": {"coordinates":[77.82415,12.95999],"type":"Point"}
}