{
  "type": "Feature",
  "properties": {
    "iso:country":"IN",
    "ks:ks_name":"Morang Urf Bazidpur",
    "ks:ks_pop":1476,
    "ks:ks_type":"VILLAGE",
    "ks:ks_uagg_main":0,
    "name:eng_x_preferred":[
        "Morang Urf Bazidpur"
    ],
    "wof:name":"Morang Urf Bazidpur",
    "wof:placetype":"neighbourhood",
    "wof:population":1476
},
  "geometry": {"coordinates":[85.42501,26.302156],"type":"Point"}
}