{
  "type": "Feature",
  "properties": {
    "iso:country":"IN",
    "ks:ks_alt_nam":"BARDAND",
    "ks:ks_name":"Bardand",
    "ks:ks_pop":450,
    "ks:ks_type":"HABITATION",
    "name:eng_x_preferred":[
        "Bardand"
    ],
    "wof:name":"Bardand",
    "wof:placetype":"locality",
    "wof:population":450
},
  "geometry": {"coordinates":[83.892894,22.868323],"type":"Point"}
}