{
  "type": "Feature",
  "properties": {
    "iso:country":"IN",
    "ks:ks_name":"Uthara Settibalijapeta",
    "ks:ks_pop":418,
    "ks:ks_type":"HABITATION",
    "name:eng_x_preferred":[
        "Uthara Settibalijapeta"
    ],
    "wof:name":"Uthara Settibalijapeta",
    "wof:placetype":"locality",
    "wof:population":418
},
  "geometry": {"coordinates":[81.89143300000001,16.596658],"type":"Point"}
}