{
  "type": "Feature",
  "properties": {
    "iso:country":"IN",
    "ks:ks_name":"Dhanoriya",
    "ks:ks_pop":491,
    "ks:ks_type":"VILLAGE",
    "ks:ks_uagg_main":0,
    "name:eng_x_preferred":[
        "Dhanoriya"
    ],
    "wof:name":"Dhanoriya",
    "wof:placetype":"neighbourhood",
    "wof:population":491
},
  "geometry": {"coordinates":[86.808115,24.264404],"type":"Point"}
}