{
  "type": "Feature",
  "properties": {
    "iso:country":"IN",
    "ks:ks_name":"Santoshnagar",
    "ks:ks_pop":715,
    "ks:ks_type":"HABITATION",
    "name:eng_x_preferred":[
        "Santoshnagar"
    ],
    "wof:name":"Santoshnagar",
    "wof:placetype":"locality",
    "wof:population":715
},
  "geometry": {"coordinates":[92.50043700000001,24.673894],"type":"Point"}
}