{
  "type": "Feature",
  "properties": {
    "iso:country":"IN",
    "ks:ks_name":"Dattwadi",
    "ks:ks_pop":281,
    "ks:ks_type":"HABITATION",
    "name:eng_x_preferred":[
        "Dattwadi"
    ],
    "wof:name":"Dattwadi",
    "wof:placetype":"locality",
    "wof:population":281
},
  "geometry": {"coordinates":[73.28209699999999,17.704706],"type":"Point"}
}