{
  "type": "Feature",
  "properties": {
    "iso:country":"IN",
    "ks:ks_name":"Jaspur",
    "ks:ks_pop":1033,
    "ks:ks_type":"VILLAGE",
    "name:eng_x_preferred":[
        "Jaspur"
    ],
    "wof:name":"Jaspur",
    "wof:placetype":"locality",
    "wof:population":1033
},
  "geometry": {"coordinates":[86.98724,23.918246],"type":"Point"}
}