{
  "type": "Feature",
  "properties": {
    "gn:admin1_code":"2",
    "gn:admin2_code":"545.0",
    "gn:asciiname":"Eluru",
    "gn:country_code":"IN",
    "gn:dem":50,
    "gn:feature_class":"P",
    "gn:feature_code":"PPL",
    "gn:name":"El\u016bru",
    "gn:population":0,
    "gn:timezone":"Asia/Kolkata",
    "iso:country":"IN",
    "name:ara_x_preferred":[
        "\u0625\u064a\u0644\u0648\u0631\u0648"
    ],
    "name:bel_x_preferred":[
        "\u042d\u043b\u0443\u0440\u0443"
    ],
    "name:bih_x_preferred":[
        "\u090f\u0932\u0941\u0930\u0941"
    ],
    "name:bpy_x_preferred":[
        "\u098f\u09b2\u09c1\u09b0\u09c1"
    ],
    "name:cat_x_preferred":[
        "Eluru"
    ],
    "name:ceb_x_preferred":[
        "El\u016bru"
    ],
    "name:deu_x_preferred":[
        "Eluru"
    ],
    "name:fas_x_preferred":[
        "\u0627\u06cc\u0644\u0648\u0631\u0648"
    ],
    "name:fin_x_preferred":[
        "Eluru"
    ],
    "name:fra_x_preferred":[
        "Eluru"
    ],
    "name:guj_x_preferred":[
        "\u0a8f\u0ab2\u0ac1\u0ab0"
    ],
    "name:hif_x_preferred":[
        "Eluru"
    ],
    "name:hin_x_preferred":[
        "\u090f\u0932\u0941\u0930\u0941"
    ],
    "name:ita_x_preferred":[
        "Eluru"
    ],
    "name:jpn_x_preferred":[
        "\u30a8\u30fc\u30eb\u30fc\u30eb"
    ],
    "name:mar_x_preferred":[
        "\u090f\u0932\u0941\u0930\u0942"
    ],
    "name:mlg_x_preferred":[
        "Eluru"
    ],
    "name:msa_x_preferred":[
        "Eluru"
    ],
    "name:new_x_preferred":[
        "\u090f\u0932\u0941\u0930\u0941"
    ],
    "name:ori_x_preferred":[
        "\u0b0f\u0b32\u0b41\u0b30\u0b41"
    ],
    "name:pol_x_preferred":[
        "Eluru"
    ],
    "name:por_x_preferred":[
        "Eluru"
    ],
    "name:rus_x_preferred":[
        "\u042d\u043b\u0443\u0440\u0443"
    ],
    "name:san_x_preferred":[
        "\u090f\u0932\u0941\u0930\u0941-\u0928\u0917\u0930\u092e\u094d"
    ],
    "name:spa_x_preferred":[
        "Eluru"
    ],
    "name:srp_x_preferred":[
        "\u0415\u043b\u0443\u0440\u0443"
    ],
    "name:swe_x_preferred":[
        "Eluru"
    ],
    "name:tam_x_preferred":[
        "\u0b8f\u0bb2\u0bc2\u0bb0\u0bc1"
    ],
    "name:tel_x_preferred":[
        "\u0c0f\u0c32\u0c42\u0c30\u0c41"
    ],
    "name:tgl_x_preferred":[
        "Eluru"
    ],
    "name:tur_x_preferred":[
        "Eluru"
    ],
    "name:urd_x_preferred":[
        "\u0627\u06cc\u0644\u0648\u0631\u0648"
    ],
    "name:vie_x_preferred":[
        "Eluru"
    ],
    "name:war_x_preferred":[
        "Eluru"
    ],
    "name:zho_x_preferred":[
        "\u57c3\u76e7\u9b6f"
    ],
    "wof:name":"Eluru",
    "wof:placetype":"locality"
},
  "geometry": {"coordinates":[82.16119999999999,17.2629],"type":"Point"}
}