{
  "type": "Feature",
  "properties": {
    "iso:country":"IN",
    "ks:ks_name":"Jaigawa Bharauti",
    "ks:ks_pop":94,
    "ks:ks_type":"HABITATION",
    "ks:ks_uagg_main":0,
    "name:eng_x_preferred":[
        "Jaigawa Bharauti"
    ],
    "wof:name":"Jaigawa Bharauti",
    "wof:placetype":"neighbourhood",
    "wof:population":94
},
  "geometry": {"coordinates":[83.401594,26.005619],"type":"Point"}
}