{
  "type": "Feature",
  "properties": {
    "iso:country":"IN",
    "ks:ks_name":"Tapadingia",
    "ks:ks_pop":491,
    "ks:ks_type":"VILLAGE",
    "name:eng_x_preferred":[
        "Tapadingia"
    ],
    "wof:name":"Tapadingia",
    "wof:placetype":"locality",
    "wof:population":491
},
  "geometry": {"coordinates":[84.295496,20.311232],"type":"Point"}
}