{
  "type": "Feature",
  "properties": {
    "gn:admin1_code":"31.0",
    "gn:admin2_code":"283",
    "gn:asciiname":"Hualtu",
    "gn:country_code":"IN",
    "gn:dem":1311,
    "gn:feature_class":"P",
    "gn:feature_code":"PPL",
    "gn:name":"Hualtu",
    "gn:population":0,
    "gn:timezone":"Asia/Kolkata",
    "iso:country":"IN",
    "wof:name":"Hualtu",
    "wof:placetype":"locality"
},
  "geometry": {"coordinates":[92.91561,23.52785],"type":"Point"}
}