{
  "type": "Feature",
  "properties": {
    "iso:country":"IN",
    "ks:ks_name":"Mojali Bujurg",
    "ks:ks_pop":726,
    "ks:ks_type":"VILLAGE",
    "name:eng_x_preferred":[
        "Mojali Bujurg"
    ],
    "wof:name":"Mojali Bujurg",
    "wof:placetype":"locality",
    "wof:population":726
},
  "geometry": {"coordinates":[74.993731,21.762906],"type":"Point"}
}