{
  "type": "Feature",
  "properties": {
    "iso:country":"IN",
    "ks:ks_name":"Anterji",
    "ks:ks_pop":135,
    "ks:ks_type":"HABITATION",
    "name:eng_x_preferred":[
        "Anterji"
    ],
    "wof:name":"Anterji",
    "wof:placetype":"locality",
    "wof:population":135
},
  "geometry": {"coordinates":[80.008866,20.497367],"type":"Point"}
}