{
  "type": "Feature",
  "properties": {
    "iso:country":"IN",
    "ks:ks_name":"Parasin",
    "ks:ks_pop":269,
    "ks:ks_type":"HABITATION",
    "ks:ks_uagg_main":0,
    "name:eng_x_preferred":[
        "Parasin"
    ],
    "wof:name":"Parasin",
    "wof:placetype":"neighbourhood",
    "wof:population":269
},
  "geometry": {"coordinates":[82.204745,26.196718],"type":"Point"}
}