{
  "type": "Feature",
  "properties": {
    "gn:admin1_code":"36",
    "gn:admin2_code":"148.0",
    "gn:asciiname":"Kisanon-ka-nagla",
    "gn:country_code":"IN",
    "gn:dem":157,
    "gn:feature_class":"P",
    "gn:feature_code":"PPL",
    "gn:name":"Kis\u0101non-ka-nagla",
    "gn:population":0,
    "gn:timezone":"Asia/Kolkata",
    "iso:country":"IN",
    "wof:name":"Kisanon-ka-nagla",
    "wof:placetype":"neighbourhood"
},
  "geometry": {"coordinates":[79.00086,27.41044],"type":"Point"}
}