{
  "type": "Feature",
  "properties": {
    "iso:country":"IN",
    "ks:ks_name":"Kalathuvalavu",
    "ks:ks_pop":50,
    "ks:ks_type":"HABITATION",
    "name:eng_x_preferred":[
        "Kalathuvalavu"
    ],
    "wof:name":"Kalathuvalavu",
    "wof:placetype":"locality",
    "wof:population":50
},
  "geometry": {"coordinates":[78.337515,11.396185],"type":"Point"}
}