{
  "type": "Feature",
  "properties": {
    "iso:country":"IN",
    "ks:ks_name":"Hanumannager",
    "ks:ks_pop":1691,
    "ks:ks_type":"HABITATION",
    "name:eng_x_preferred":[
        "Hanumannager"
    ],
    "wof:name":"Hanumannager",
    "wof:placetype":"locality",
    "wof:population":1691
},
  "geometry": {"coordinates":[72.777951,19.849536],"type":"Point"}
}