{
  "type": "Feature",
  "properties": {
    "gn:admin1_code":"38",
    "gn:admin2_code":"364.0",
    "gn:asciiname":"Ratu",
    "gn:country_code":"IN",
    "gn:dem":725,
    "gn:feature_class":"P",
    "gn:feature_code":"PPL",
    "gn:name":"R\u0101tu",
    "gn:population":0,
    "gn:timezone":"Asia/Kolkata",
    "iso:country":"IN",
    "wof:name":"Ratu",
    "wof:placetype":"locality"
},
  "geometry": {"coordinates":[85.21459,23.42045],"type":"Point"}
}