{
  "type": "Feature",
  "properties": {
    "iso:country":"IN",
    "ks:ks_name":"Kismat Khawaspur",
    "ks:ks_pop":3172,
    "ks:ks_type":"VILLAGE",
    "ks:ks_uagg_main":0,
    "name:eng_x_preferred":[
        "Kismat Khawaspur"
    ],
    "wof:name":"Kismat Khawaspur",
    "wof:placetype":"neighbourhood",
    "wof:population":3172
},
  "geometry": {"coordinates":[87.454898,26.250418],"type":"Point"}
}