{
  "type": "Feature",
  "properties": {
    "iso:country":"IN",
    "ks:ks_alt_nam":"Ambliya pura",
    "ks:ks_name":"Ambliya Pura",
    "ks:ks_pop":213,
    "ks:ks_type":"HABITATION",
    "name:eng_x_preferred":[
        "Ambliya Pura"
    ],
    "wof:name":"Ambliya Pura",
    "wof:placetype":"locality",
    "wof:population":213
},
  "geometry": {"coordinates":[72.75958300000001,22.374889],"type":"Point"}
}