{
  "type": "Feature",
  "properties": {
    "iso:country":"IN",
    "ks:ks_name":"Timburey",
    "ks:ks_pop":350,
    "ks:ks_type":"HABITATION",
    "name:eng_x_preferred":[
        "Timburey"
    ],
    "wof:name":"Timburey",
    "wof:placetype":"locality",
    "wof:population":350
},
  "geometry": {"coordinates":[88.06365099999999,27.123895],"type":"Point"}
}