{
  "type": "Feature",
  "properties": {
    "iso:country":"IN",
    "ks:ks_name":"Gadariya Kondar",
    "ks:ks_pop":535,
    "ks:ks_type":"VILLAGE",
    "name:eng_x_preferred":[
        "Gadariya Kondar"
    ],
    "wof:name":"Gadariya Kondar",
    "wof:placetype":"locality",
    "wof:population":535
},
  "geometry": {"coordinates":[77.34698899999999,24.942613],"type":"Point"}
}