{
  "type": "Feature",
  "properties": {
    "iso:country":"IN",
    "ks:ks_name":"Dudhbardi",
    "ks:ks_pop":50,
    "ks:ks_type":"VILLAGE",
    "name:eng_x_preferred":[
        "Dudhbardi"
    ],
    "wof:name":"Dudhbardi",
    "wof:placetype":"locality",
    "wof:population":50
},
  "geometry": {"coordinates":[78.473868,20.855092],"type":"Point"}
}