{
  "type": "Feature",
  "properties": {
    "iso:country":"IN",
    "ks:ks_name":"Myderhal Tanda",
    "ks:ks_pop":372,
    "ks:ks_type":"HABITATION",
    "name:eng_x_preferred":[
        "Myderhal Tanda"
    ],
    "wof:name":"Myderhal Tanda",
    "wof:placetype":"locality",
    "wof:population":372
},
  "geometry": {"coordinates":[76.60014,15.950353],"type":"Point"}
}