{
  "type": "Feature",
  "properties": {
    "gn:admin1_code":"19.0",
    "gn:admin2_code":"566.0",
    "gn:asciiname":"Narenahalli",
    "gn:country_code":"IN",
    "gn:dem":664,
    "gn:feature_class":"P",
    "gn:feature_code":"PPL",
    "gn:name":"N\u0101renahalli",
    "gn:population":0,
    "gn:timezone":"Asia/Kolkata",
    "iso:country":"IN",
    "wof:name":"Narenahalli",
    "wof:placetype":"locality"
},
  "geometry": {"coordinates":[76.51572,14.1646],"type":"Point"}
}