{
  "type": "Feature",
  "properties": {
    "iso:country":"IN",
    "ks:ks_name":"Rakhatpur",
    "ks:ks_pop":1456,
    "ks:ks_type":"VILLAGE",
    "ks:ks_uagg_main":0,
    "name:eng_x_preferred":[
        "Rakhatpur"
    ],
    "wof:name":"Rakhatpur",
    "wof:placetype":"neighbourhood",
    "wof:population":1456
},
  "geometry": {"coordinates":[86.517151,23.715234],"type":"Point"}
}