{
  "type": "Feature",
  "properties": {
    "iso:country":"IN",
    "ks:ks_alt_nam":"Puncha west",
    "ks:ks_name":"Puncha West",
    "ks:ks_pop":749,
    "ks:ks_type":"HABITATION",
    "name:eng_x_preferred":[
        "Puncha West"
    ],
    "wof:name":"Puncha West",
    "wof:placetype":"locality",
    "wof:population":749
},
  "geometry": {"coordinates":[76.354142,11.262827],"type":"Point"}
}