{
  "type": "Feature",
  "properties": {
    "iso:country":"IN",
    "ks:ks_alt_nam":"Shiv Sarnon Ki dhani",
    "ks:ks_name":"Shiv Sarnon Ki Dhani",
    "ks:ks_pop":1181,
    "ks:ks_type":"HABITATION",
    "name:eng_x_preferred":[
        "Shiv Sarnon Ki Dhani"
    ],
    "wof:name":"Shiv Sarnon Ki Dhani",
    "wof:placetype":"locality",
    "wof:population":1181
},
  "geometry": {"coordinates":[72.910544,26.379994],"type":"Point"}
}