{
  "type": "Feature",
  "properties": {
    "iso:country":"IN",
    "ks:ks_alt_nam":"Alur New colony",
    "ks:ks_name":"Alur New Colony",
    "ks:ks_pop":360,
    "ks:ks_type":"HABITATION",
    "name:eng_x_preferred":[
        "Alur New Colony"
    ],
    "wof:name":"Alur New Colony",
    "wof:placetype":"locality",
    "wof:population":360
},
  "geometry": {"coordinates":[79.206838,11.870659],"type":"Point"}
}