{
  "type": "Feature",
  "properties": {
    "iso:country":"IN",
    "ks:ks_alt_nam":"Dina prasad para",
    "ks:ks_name":"Dina Prasad Para",
    "ks:ks_pop":140,
    "ks:ks_type":"HABITATION",
    "name:eng_x_preferred":[
        "Dina Prasad Para"
    ],
    "wof:name":"Dina Prasad Para",
    "wof:placetype":"locality",
    "wof:population":140
},
  "geometry": {"coordinates":[91.729097,23.157698],"type":"Point"}
}