{
  "type": "Feature",
  "properties": {
    "gn:admin1_code":"10",
    "gn:admin2_code":"81.0",
    "gn:asciiname":"Khorara",
    "gn:country_code":"IN",
    "gn:dem":253,
    "gn:feature_class":"P",
    "gn:feature_code":"PPL",
    "gn:name":"Khorara",
    "gn:population":0,
    "gn:timezone":"Asia/Kolkata",
    "iso:country":"IN",
    "wof:name":"Khorara",
    "wof:placetype":"locality"
},
  "geometry": {"coordinates":[75.84154000000002,28.52025],"type":"Point"}
}