{
  "type": "Feature",
  "properties": {
    "gn:admin1_code":"38.0",
    "gn:admin2_code":"347.0",
    "gn:asciiname":"Pinja",
    "gn:country_code":"IN",
    "gn:dem":412,
    "gn:feature_class":"P",
    "gn:feature_code":"PPL",
    "gn:name":"Pinj\u0101",
    "gn:population":0,
    "gn:timezone":"Asia/Kolkata",
    "iso:country":"IN",
    "ks:ks_alt_nam":"Pinj\u0101",
    "ks:ks_name":"Pinja",
    "ks:ks_pop":245,
    "ks:ks_type":"VILLAGE",
    "name:eng_x_preferred":[
        "Pinja"
    ],
    "name:eng_x_variant":[
        "Pinj\u0101"
    ],
    "wof:name":"Pinja",
    "wof:placetype":"locality",
    "wof:population":245
},
  "geometry": {"coordinates":[84.70863199999999,24.177904],"type":"Point"}
}