{
  "type": "Feature",
  "properties": {
    "gn:admin1_code":"10",
    "gn:admin2_code":"73.0",
    "gn:asciiname":"Kharkhara",
    "gn:country_code":"IN",
    "gn:dem":242,
    "gn:feature_class":"P",
    "gn:feature_code":"PPL",
    "gn:name":"Kharkhara",
    "gn:population":0,
    "gn:timezone":"Asia/Kolkata",
    "iso:country":"IN",
    "wof:name":"Kharkhara",
    "wof:placetype":"locality"
},
  "geometry": {"coordinates":[76.28681999999998,29.96493],"type":"Point"}
}