{
  "type": "Feature",
  "properties": {
    "iso:country":"IN",
    "ks:ks_name":"Chandrapura",
    "ks:ks_pop":457,
    "ks:ks_type":"VILLAGE",
    "name:eng_x_preferred":[
        "Chandrapura"
    ],
    "wof:name":"Chandrapura",
    "wof:placetype":"locality",
    "wof:population":457
},
  "geometry": {"coordinates":[79.082537,24.061261],"type":"Point"}
}