{
  "type": "Feature",
  "properties": {
    "iso:country":"IN",
    "ks:ks_name":"Paranpur Senduari Chak Hamida",
    "ks:ks_pop":798,
    "ks:ks_type":"VILLAGE",
    "name:eng_x_preferred":[
        "Paranpur Senduari Chak Hamida"
    ],
    "wof:name":"Paranpur Senduari Chak Hamida",
    "wof:placetype":"locality",
    "wof:population":798
},
  "geometry": {"coordinates":[85.27388000000001,25.74625],"type":"Point"}
}