{
  "type": "Feature",
  "properties": {
    "iso:country":"IN",
    "ks:ks_name":"Nehru Nagar",
    "ks:ks_pop":1747,
    "ks:ks_type":"HABITATION",
    "name:eng_x_preferred":[
        "Nehru Nagar"
    ],
    "wof:name":"Nehru Nagar",
    "wof:placetype":"locality",
    "wof:population":1747
},
  "geometry": {"coordinates":[75.046492,27.367511],"type":"Point"}
}