{
  "type": "Feature",
  "properties": {
    "iso:country":"IN",
    "ks:ks_name":"Afzalnagar Garhi",
    "ks:ks_type":"VILLAGE",
    "name:eng_x_preferred":[
        "Afzalnagar Garhi"
    ],
    "wof:name":"Afzalnagar Garhi",
    "wof:placetype":"locality"
},
  "geometry": {"coordinates":[78.682543,29.431474],"type":"Point"}
}