{
  "type": "Feature",
  "properties": {
    "iso:country":"IN",
    "ks:ks_name":"Chemmana Jn",
    "ks:ks_pop":470,
    "ks:ks_type":"HABITATION",
    "name:eng_x_preferred":[
        "Chemmana Jn"
    ],
    "wof:name":"Chemmana Jn",
    "wof:placetype":"locality",
    "wof:population":470
},
  "geometry": {"coordinates":[76.849817,9.038831],"type":"Point"}
}