{
  "type": "Feature",
  "properties": {
    "iso:country":"IN",
    "ks:ks_name":"Hatsimul",
    "ks:ks_pop":1239,
    "ks:ks_type":"VILLAGE",
    "ks:ks_uagg_main":0,
    "name:eng_x_preferred":[
        "Hatsimul"
    ],
    "wof:name":"Hatsimul",
    "wof:placetype":"locality",
    "wof:population":1239
},
  "geometry": {"coordinates":[87.89224,23.211957],"type":"Point"}
}