{
  "type": "Feature",
  "properties": {
    "gn:admin1_code":"36",
    "gn:admin2_code":"193.0",
    "gn:asciiname":"Kamtail",
    "gn:country_code":"IN",
    "gn:dem":72,
    "gn:feature_class":"P",
    "gn:feature_code":"PPL",
    "gn:name":"Kamtail",
    "gn:population":0,
    "gn:timezone":"Asia/Kolkata",
    "iso:country":"IN",
    "ks:ks_name":"Kamtaila",
    "ks:ks_pop":609,
    "ks:ks_type":"VILLAGE",
    "ks:ks_uagg_main":0,
    "name:eng_x_preferred":[
        "Kamtaila"
    ],
    "wof:name":"Kamtaila",
    "wof:placetype":"neighbourhood",
    "wof:population":609
},
  "geometry": {"coordinates":[83.860091,25.881429],"type":"Point"}
}