{
  "type": "Feature",
  "properties": {
    "iso:country":"IN",
    "ks:ks_name":"Jhapursi",
    "ks:ks_pop":1108,
    "ks:ks_type":"VILLAGE",
    "name:eng_x_preferred":[
        "Jhapursi"
    ],
    "wof:name":"Jhapursi",
    "wof:placetype":"locality",
    "wof:population":1108
},
  "geometry": {"coordinates":[88.776482,25.339377],"type":"Point"}
}