{
  "type": "Feature",
  "properties": {
    "iso:country":"IN",
    "ks:ks_name":"Khonda Hajari",
    "ks:ks_pop":334,
    "ks:ks_type":"VILLAGE",
    "ks:ks_uagg_main":0,
    "name:eng_x_preferred":[
        "Khonda Hajari"
    ],
    "wof:name":"Khonda Hajari",
    "wof:placetype":"neighbourhood",
    "wof:population":334
},
  "geometry": {"coordinates":[78.040251,27.587431],"type":"Point"}
}