{
  "type": "Feature",
  "properties": {
    "iso:country":"IN",
    "ks:ks_name":"Pura Madhu",
    "ks:ks_pop":902,
    "ks:ks_type":"VILLAGE",
    "ks:ks_uagg_main":0,
    "name:eng_x_preferred":[
        "Pura Madhu"
    ],
    "wof:name":"Pura Madhu",
    "wof:placetype":"neighbourhood",
    "wof:population":902
},
  "geometry": {"coordinates":[82.14890200000001,25.665495],"type":"Point"}
}