{
  "type": "Feature",
  "properties": {
    "iso:country":"IN",
    "ks:ks_alt_nam":"GhabalaVada Faliya",
    "ks:ks_name":"Ghabalavada Faliya",
    "ks:ks_pop":507,
    "ks:ks_type":"HABITATION",
    "name:eng_x_preferred":[
        "Ghabalavada Faliya"
    ],
    "wof:name":"Ghabalavada Faliya",
    "wof:placetype":"locality",
    "wof:population":507
},
  "geometry": {"coordinates":[73.42358299999999,23.089333],"type":"Point"}
}