{
  "type": "Feature",
  "properties": {
    "iso:country":"IN",
    "ks:ks_name":"Kudiriadka",
    "ks:ks_pop":18,
    "ks:ks_type":"HABITATION",
    "name:eng_x_preferred":[
        "Kudiriadka"
    ],
    "wof:name":"Kudiriadka",
    "wof:placetype":"locality",
    "wof:population":18
},
  "geometry": {"coordinates":[75.19561,12.701559],"type":"Point"}
}