{
  "type": "Feature",
  "properties": {
    "iso:country":"IN",
    "ks:ks_name":"Raka",
    "ks:ks_pop":4,
    "ks:ks_type":"HABITATION",
    "name:eng_x_preferred":[
        "Raka"
    ],
    "wof:name":"Raka",
    "wof:placetype":"locality",
    "wof:population":4
},
  "geometry": {"coordinates":[79.46143499999999,22.989908],"type":"Point"}
}