{
  "type": "Feature",
  "properties": {
    "gn:admin1_code":"02",
    "gn:admin2_code":"552.0",
    "gn:asciiname":"Regadiguduru",
    "gn:country_code":"IN",
    "gn:dem":257,
    "gn:feature_class":"P",
    "gn:feature_code":"PPL",
    "gn:name":"Regadig\u016bd\u016bru",
    "gn:population":0,
    "gn:timezone":"Asia/Kolkata",
    "iso:country":"IN",
    "wof:name":"Regadiguduru",
    "wof:placetype":"locality"
},
  "geometry": {"coordinates":[78.47832,15.71325],"type":"Point"}
}