{
  "type": "Feature",
  "properties": {
    "gn:admin1_code":"19.0",
    "gn:admin2_code":"578.0",
    "gn:asciiname":"Pudunagaram",
    "gn:country_code":"IN",
    "gn:dem":602,
    "gn:feature_class":"P",
    "gn:feature_code":"PPL",
    "gn:name":"Pudunagaram",
    "gn:population":0,
    "gn:timezone":"Asia/Kolkata",
    "iso:country":"IN",
    "wof:name":"Pudunagaram",
    "wof:placetype":"neighbourhood"
},
  "geometry": {"coordinates":[77.44208,12.06697],"type":"Point"}
}