{
  "type": "Feature",
  "properties": {
    "iso:country":"IN",
    "ks:ks_name":"Giringiwada",
    "ks:ks_pop":1,
    "ks:ks_type":"HABITATION",
    "name:eng_x_preferred":[
        "Giringiwada"
    ],
    "wof:name":"Giringiwada",
    "wof:placetype":"locality",
    "wof:population":1
},
  "geometry": {"coordinates":[82.26759,18.395511],"type":"Point"}
}