{
  "type": "Feature",
  "properties": {
    "iso:country":"IN",
    "ks:ks_name":"Patali",
    "ks:ks_pop":152,
    "ks:ks_type":"HABITATION",
    "name:eng_x_preferred":[
        "Patali"
    ],
    "wof:name":"Patali",
    "wof:placetype":"locality",
    "wof:population":152
},
  "geometry": {"coordinates":[79.766547,29.792374],"type":"Point"}
}