{
  "type": "Feature",
  "properties": {
    "iso:country":"IN",
    "ks:ks_name":"Jiginihwa Ur F Jolhabhari",
    "ks:ks_pop":618,
    "ks:ks_type":"HABITATION",
    "name:eng_x_preferred":[
        "Jiginihwa Ur F Jolhabhari"
    ],
    "wof:name":"Jiginihwa Ur F Jolhabhari",
    "wof:placetype":"locality",
    "wof:population":618
},
  "geometry": {"coordinates":[82.867192,27.300198],"type":"Point"}
}