{
  "type": "Feature",
  "properties": {
    "gn:admin1_code":"30.0",
    "gn:admin2_code":"255.0",
    "gn:asciiname":"Gai",
    "gn:country_code":"IN",
    "gn:dem":1136,
    "gn:feature_class":"P",
    "gn:feature_code":"PPL",
    "gn:name":"Gai",
    "gn:population":0,
    "gn:timezone":"Asia/Kolkata",
    "iso:country":"IN",
    "wof:name":"Gai",
    "wof:placetype":"locality"
},
  "geometry": {"coordinates":[93.57959,27.46247],"type":"Point"}
}