{
  "type": "Feature",
  "properties": {
    "gn:admin1_code":"36",
    "gn:admin2_code":"196.0",
    "gn:asciiname":"Pura Bijai",
    "gn:country_code":"IN",
    "gn:dem":77,
    "gn:feature_class":"P",
    "gn:feature_code":"PPL",
    "gn:name":"Pura Bijai",
    "gn:population":0,
    "gn:timezone":"Asia/Kolkata",
    "iso:country":"IN",
    "ks:ks_name":"Pura Bijai",
    "ks:ks_pop":1509,
    "ks:ks_type":"VILLAGE",
    "name:eng_x_preferred":[
        "Pura Bijai"
    ],
    "wof:name":"Pura Bijai",
    "wof:placetype":"locality",
    "wof:population":1509
},
  "geometry": {"coordinates":[83.14021,25.462844],"type":"Point"}
}