{
  "type": "Feature",
  "properties": {
    "iso:country":"IN",
    "ks:ks_name":"Khankalapur",
    "ks:ks_pop":673,
    "ks:ks_type":"VILLAGE",
    "name:eng_x_preferred":[
        "Khankalapur"
    ],
    "wof:name":"Khankalapur",
    "wof:placetype":"locality",
    "wof:population":673
},
  "geometry": {"coordinates":[79.817339,27.51514],"type":"Point"}
}