{
  "type": "Feature",
  "properties": {
    "iso:country":"IN",
    "ks:ks_name":"P Jangal",
    "ks:ks_pop":836,
    "ks:ks_type":"HABITATION",
    "name:eng_x_preferred":[
        "P Jangal"
    ],
    "wof:name":"P Jangal",
    "wof:placetype":"locality",
    "wof:population":836
},
  "geometry": {"coordinates":[81.54170000000001,26.4064],"type":"Point"}
}