{
  "type": "Feature",
  "properties": {
    "gn:admin1_code":"28.0",
    "gn:admin2_code":"333.0",
    "gn:asciiname":"Beniagram Panchayat",
    "gn:country_code":"IN",
    "gn:dem":30,
    "gn:feature_class":"P",
    "gn:feature_code":"PPL",
    "gn:name":"Beniagram Panchayat",
    "gn:population":0,
    "gn:timezone":"Asia/Kolkata",
    "iso:country":"IN",
    "wof:name":"Beniagram Panchayat",
    "wof:placetype":"neighbourhood"
},
  "geometry": {"coordinates":[87.92274,24.76756],"type":"Point"}
}