{
  "type": "Feature",
  "properties": {
    "iso:country":"IN",
    "ks:ks_name":"Madigapalle",
    "ks:ks_pop":68,
    "ks:ks_type":"HABITATION",
    "name:eng_x_preferred":[
        "Madigapalle"
    ],
    "wof:name":"Madigapalle",
    "wof:placetype":"locality",
    "wof:population":68
},
  "geometry": {"coordinates":[78.756406,13.784557],"type":"Point"}
}