{
  "type": "Feature",
  "properties": {
    "iso:country":"IN",
    "ks:ks_name":"Chuvannamanna",
    "ks:ks_pop":1025,
    "ks:ks_type":"HABITATION",
    "ks:ks_uagg_main":0,
    "name:eng_x_preferred":[
        "Chuvannamanna"
    ],
    "wof:name":"Chuvannamanna",
    "wof:placetype":"neighbourhood",
    "wof:population":1025
},
  "geometry": {"coordinates":[76.30518499999999,11.332155],"type":"Point"}
}