{
  "type": "Feature",
  "properties": {
    "iso:country":"IN",
    "ks:ks_name":"Garaganagadde",
    "ks:ks_pop":57,
    "ks:ks_type":"HABITATION",
    "name:eng_x_preferred":[
        "Garaganagadde"
    ],
    "wof:name":"Garaganagadde",
    "wof:placetype":"locality",
    "wof:population":57
},
  "geometry": {"coordinates":[74.48747899999999,14.566066],"type":"Point"}
}