{
  "type": "Feature",
  "properties": {
    "iso:country":"IN",
    "ks:ks_name":"Killahara Pt-I",
    "ks:ks_pop":63,
    "ks:ks_type":"VILLAGE",
    "name:eng_x_preferred":[
        "Killahara Pt-I"
    ],
    "wof:name":"Killahara Pt-I",
    "wof:placetype":"locality",
    "wof:population":63
},
  "geometry": {"coordinates":[90.272668,26.17379],"type":"Point"}
}