{
  "type": "Feature",
  "properties": {
    "iso:country":"IN",
    "ks:ks_alt_nam":"MPV 79",
    "ks:ks_name":"Mpv 79",
    "ks:ks_pop":490,
    "ks:ks_type":"HABITATION",
    "name:eng_x_preferred":[
        "Mpv 79"
    ],
    "wof:name":"Mpv 79",
    "wof:placetype":"locality",
    "wof:population":490
},
  "geometry": {"coordinates":[81.502743,17.95699],"type":"Point"}
}