{
  "type": "Feature",
  "properties": {
    "gn:admin1_code":"12.0",
    "gn:admin2_code":"008",
    "gn:asciiname":"Gadakhod",
    "gn:country_code":"IN",
    "gn:dem":1584,
    "gn:feature_class":"P",
    "gn:feature_code":"PPL",
    "gn:name":"G\u0101dakhod",
    "gn:population":0,
    "gn:timezone":"Asia/Kolkata",
    "iso:country":"IN",
    "wof:name":"Gadakhod",
    "wof:placetype":"locality"
},
  "geometry": {"coordinates":[74.62303,34.18138],"type":"Point"}
}