{
  "type": "Feature",
  "properties": {
    "iso:country":"IN",
    "ks:ks_name":"Dusadh Tola",
    "ks:ks_pop":152,
    "ks:ks_type":"HABITATION",
    "name:eng_x_preferred":[
        "Dusadh Tola"
    ],
    "wof:name":"Dusadh Tola",
    "wof:placetype":"locality",
    "wof:population":152
},
  "geometry": {"coordinates":[84.87405200000001,26.861408],"type":"Point"}
}