{
  "type": "Feature",
  "properties": {
    "iso:country":"IN",
    "ks:ks_name":"Dhadha",
    "ks:ks_pop":76,
    "ks:ks_type":"HABITATION",
    "name:eng_x_preferred":[
        "Dhadha"
    ],
    "wof:name":"Dhadha",
    "wof:placetype":"locality",
    "wof:population":76
},
  "geometry": {"coordinates":[82.01016300000001,24.413042],"type":"Point"}
}