{
  "type": "Feature",
  "properties": {
    "iso:country":"IN",
    "ks:ks_alt_nam":"NIMIYA PUDA TOLA",
    "ks:ks_name":"Nimiya Puda Tola",
    "ks:ks_pop":109,
    "ks:ks_type":"HABITATION",
    "name:eng_x_preferred":[
        "Nimiya Puda Tola"
    ],
    "wof:name":"Nimiya Puda Tola",
    "wof:placetype":"locality",
    "wof:population":109
},
  "geometry": {"coordinates":[85.44752099999999,23.795146],"type":"Point"}
}