{
  "type": "Feature",
  "properties": {
    "iso:country":"IN",
    "ks:ks_name":"Tola Chauki",
    "ks:ks_pop":486,
    "ks:ks_type":"VILLAGE",
    "ks:ks_uagg_main":0,
    "name:eng_x_preferred":[
        "Tola Chauki"
    ],
    "wof:name":"Tola Chauki",
    "wof:placetype":"neighbourhood",
    "wof:population":486
},
  "geometry": {"coordinates":[86.36967199999999,24.740727],"type":"Point"}
}