{
  "type": "Feature",
  "properties": {
    "iso:country":"IN",
    "ks:ks_name":"Jaridih",
    "ks:ks_pop":378,
    "ks:ks_type":"VILLAGE",
    "name:eng_x_preferred":[
        "Jaridih"
    ],
    "wof:name":"Jaridih",
    "wof:placetype":"locality",
    "wof:population":378
},
  "geometry": {"coordinates":[83.545658,22.200512],"type":"Point"}
}