{
  "type": "Feature",
  "properties": {
    "gn:admin1_code":"23",
    "gn:admin2_code":"40.0",
    "gn:asciiname":"Kalaundi",
    "gn:country_code":"IN",
    "gn:dem":271,
    "gn:feature_class":"P",
    "gn:feature_code":"PPL",
    "gn:name":"Kalaundi",
    "gn:population":0,
    "gn:timezone":"Asia/Kolkata",
    "iso:country":"IN",
    "wof:name":"Kalaundi",
    "wof:placetype":"locality"
},
  "geometry": {"coordinates":[76.4363,30.71916],"type":"Point"}
}