{
  "type": "Feature",
  "properties": {
    "iso:country":"IN",
    "ks:ks_name":"Majar Khurd",
    "ks:ks_pop":237,
    "ks:ks_type":"VILLAGE",
    "ks:ks_uagg_main":0,
    "name:eng_x_preferred":[
        "Majar Khurd"
    ],
    "wof:name":"Majar Khurd",
    "wof:placetype":"neighbourhood",
    "wof:population":237
},
  "geometry": {"coordinates":[87.154234,24.996572],"type":"Point"}
}