{
  "type": "Feature",
  "properties": {
    "gn:admin1_code":"35.0",
    "gn:admin2_code":"446.0",
    "gn:asciiname":"Singhar",
    "gn:country_code":"IN",
    "gn:dem":561,
    "gn:feature_class":"P",
    "gn:feature_code":"PPL",
    "gn:name":"Singh\u0101r",
    "gn:population":0,
    "gn:timezone":"Asia/Kolkata",
    "iso:country":"IN",
    "wof:name":"Singhar",
    "wof:placetype":"locality"
},
  "geometry": {"coordinates":[78.42702,23.39235],"type":"Point"}
}