{
  "type": "Feature",
  "properties": {
    "gn:admin1_code":"12",
    "gn:admin2_code":"15.0",
    "gn:asciiname":"Halan",
    "gn:country_code":"IN",
    "gn:dem":2313,
    "gn:feature_class":"P",
    "gn:feature_code":"PPL",
    "gn:name":"H\u0101lan",
    "gn:population":0,
    "gn:timezone":"Asia/Kolkata",
    "iso:country":"IN",
    "wof:name":"Halan",
    "wof:placetype":"locality"
},
  "geometry": {"coordinates":[74.84066,33.6104],"type":"Point"}
}