{
  "type": "Feature",
  "properties": {
    "iso:country":"IN",
    "ks:ks_name":"Jalachiwadi",
    "ks:ks_pop":60,
    "ks:ks_type":"HABITATION",
    "name:eng_x_preferred":[
        "Jalachiwadi"
    ],
    "wof:name":"Jalachiwadi",
    "wof:placetype":"locality",
    "wof:population":60
},
  "geometry": {"coordinates":[73.45120199999999,17.878725],"type":"Point"}
}