{
  "type": "Feature",
  "properties": {
    "iso:country":"IN",
    "ks:ks_name":"Routasankepalli",
    "ks:ks_pop":39,
    "ks:ks_type":"HABITATION",
    "name:eng_x_preferred":[
        "Routasankepalli"
    ],
    "wof:name":"Routasankepalli",
    "wof:placetype":"locality",
    "wof:population":39
},
  "geometry": {"coordinates":[79.34594800000001,19.277427],"type":"Point"}
}