{
  "type": "Feature",
  "properties": {
    "iso:country":"IN",
    "ks:ks_name":"Nabada",
    "ks:ks_pop":501,
    "ks:ks_type":"VILLAGE",
    "ks:ks_uagg_main":0,
    "name:eng_x_preferred":[
        "Nabada"
    ],
    "wof:name":"Nabada",
    "wof:placetype":"neighbourhood",
    "wof:population":501
},
  "geometry": {"coordinates":[87.162558,21.725157],"type":"Point"}
}