{
  "type": "Feature",
  "properties": {
    "iso:country":"IN",
    "ks:ks_alt_nam":"puranabogra",
    "ks:ks_name":"Puranabogra",
    "ks:ks_pop":421,
    "ks:ks_type":"HABITATION",
    "name:eng_x_preferred":[
        "Puranabogra"
    ],
    "wof:name":"Puranabogra",
    "wof:placetype":"locality",
    "wof:population":421
},
  "geometry": {"coordinates":[86.81742300000001,24.461945],"type":"Point"}
}