{
  "type": "Feature",
  "properties": {
    "gn:admin1_code":"11",
    "gn:admin2_code":"23.0",
    "gn:asciiname":"Raila",
    "gn:country_code":"IN",
    "gn:dem":1994,
    "gn:feature_class":"P",
    "gn:feature_code":"PPL",
    "gn:name":"Raila",
    "gn:population":0,
    "gn:timezone":"Asia/Kolkata",
    "iso:country":"IN",
    "name:ara_x_preferred":[
        "\u0631\u0627\u064a\u0644\u0627"
    ],
    "name:ben_bn_x_preferred":[
        "\u09b0\u09be\u0987\u09b2\u09be"
    ],
    "name:ben_in_x_preferred":[
        "\u09b0\u09be\u0987\u09b2\u09be"
    ],
    "name:guj_x_preferred":[
        "\u0ab0\u0ac8\u0ab2\u0abe"
    ],
    "name:hin_x_preferred":[
        "\u0930\u0948\u0932\u093e"
    ],
    "name:kan_x_preferred":[
        "\u0cb0\u0cc8\u0cb2\u0cbe"
    ],
    "name:mal_x_preferred":[
        "\u0d31\u0d48\u0d32"
    ],
    "name:mar_x_preferred":[
        "\u0930\u093e\u092f\u0932\u093e"
    ],
    "name:pan_x_preferred":[
        "\u0a30\u0a48\u0a07\u0a32\u0a3e"
    ],
    "name:tam_x_preferred":[
        "\u0bb0\u0bc8\u0bb2\u0bbe"
    ],
    "name:tel_x_preferred":[
        "\u0c30\u0c3e\u0c2f\u0c4d"
    ],
    "name:urd_x_preferred":[
        "\u0631\u0627\u0626\u06cc\u0644\u06c1"
    ],
    "wof:name":"Raila",
    "wof:placetype":"locality"
},
  "geometry": {"coordinates":[76.49283,32.45336],"type":"Point"}
}