{
  "type": "Feature",
  "properties": {
    "iso:country":"IN",
    "ks:ks_name":"Ramabhadrapuram",
    "ks:ks_pop":82,
    "ks:ks_type":"HABITATION",
    "ks:ks_uagg_main":0,
    "name:eng_x_preferred":[
        "Ramabhadrapuram"
    ],
    "wof:name":"Ramabhadrapuram",
    "wof:placetype":"locality",
    "wof:population":82
},
  "geometry": {"coordinates":[79.060717,13.196994],"type":"Point"}
}