{
  "type": "Feature",
  "properties": {
    "gn:admin1_code":"24.0",
    "gn:admin2_code":"128.0",
    "gn:asciiname":"Udpura",
    "gn:country_code":"IN",
    "gn:dem":242,
    "gn:feature_class":"P",
    "gn:feature_code":"PPL",
    "gn:name":"\u016adpura",
    "gn:population":0,
    "gn:timezone":"Asia/Kolkata",
    "iso:country":"IN",
    "name:ben_x_preferred":[
        "\u0989\u09a6\u09aa\u09c1\u09b0\u09be"
    ],
    "name:bpy_x_preferred":[
        "\u0989\u09a6\u09aa\u09c1\u09b0\u09be"
    ],
    "name:ceb_x_preferred":[
        "Udpura"
    ],
    "name:ita_x_preferred":[
        "Udpura"
    ],
    "name:msa_x_preferred":[
        "Udpura"
    ],
    "name:nld_x_preferred":[
        "Udpura"
    ],
    "name:por_x_preferred":[
        "Udpura"
    ],
    "name:swe_x_preferred":[
        "Udpura"
    ],
    "name:vie_x_preferred":[
        "Udpura"
    ],
    "name:zho_x_preferred":[
        "\u4e4c\u5fb7\u666e\u62c9"
    ],
    "wof:name":"Udpura",
    "wof:placetype":"locality"
},
  "geometry": {"coordinates":[76.32776,25.30477],"type":"Point"}
}