{
  "type": "Feature",
  "properties": {
    "iso:country":"IN",
    "ks:ks_name":"Ammapalle",
    "ks:ks_pop":130,
    "ks:ks_type":"VILLAGE",
    "name:eng_x_preferred":[
        "Ammapalle"
    ],
    "wof:name":"Ammapalle",
    "wof:placetype":"locality",
    "wof:population":130
},
  "geometry": {"coordinates":[78.359522,17.255692],"type":"Point"}
}