{
  "type": "Feature",
  "properties": {
    "gn:admin1_code":"11",
    "gn:admin2_code":"33.0",
    "gn:asciiname":"Kawalag",
    "gn:country_code":"IN",
    "gn:dem":1463,
    "gn:feature_class":"P",
    "gn:feature_code":"PPL",
    "gn:name":"Kaw\u0101lag",
    "gn:population":0,
    "gn:timezone":"Asia/Kolkata",
    "iso:country":"IN",
    "wof:name":"Kawalag",
    "wof:placetype":"locality"
},
  "geometry": {"coordinates":[77.19368,31.04704000000001],"type":"Point"}
}