{
  "type": "Feature",
  "properties": {
    "iso:country":"IN",
    "ks:ks_alt_nam":"Got\u0101g",
    "ks:ks_name":"Gotag",
    "ks:ks_pop":206,
    "ks:ks_type":"VILLAGE",
    "name:eng_x_preferred":[
        "Gotag"
    ],
    "name:eng_x_variant":[
        "Got\u0101g"
    ],
    "wof:name":"Gotag",
    "wof:placetype":"locality",
    "wof:population":206
},
  "geometry": {"coordinates":[84.394397,23.606476],"type":"Point"}
}