{
  "type": "Feature",
  "properties": {
    "gn:admin1_code":"25.0",
    "gn:asciiname":"Olikkudi",
    "gn:country_code":"IN",
    "gn:dem":1501,
    "gn:feature_class":"P",
    "gn:feature_code":"PPL",
    "gn:name":"Olikkudi",
    "gn:population":0,
    "gn:timezone":"Asia/Kolkata",
    "iso:country":"IN",
    "wof:name":"Olikkudi",
    "wof:placetype":"locality"
},
  "geometry": {"coordinates":[77.13741999999998,10.3267],"type":"Point"}
}