{
  "type": "Feature",
  "properties": {
    "iso:country":"IN",
    "ks:ks_name":"Gangahar Hardia",
    "ks:ks_pop":252,
    "ks:ks_type":"VILLAGE",
    "name:eng_x_preferred":[
        "Gangahar Hardia"
    ],
    "wof:name":"Gangahar Hardia",
    "wof:placetype":"locality",
    "wof:population":252
},
  "geometry": {"coordinates":[85.182515,24.607739],"type":"Point"}
}