{
  "type": "Feature",
  "properties": {
    "iso:country":"IN",
    "ks:ks_name":"Shivaguda",
    "ks:ks_pop":39,
    "ks:ks_type":"HABITATION",
    "name:eng_x_preferred":[
        "Shivaguda"
    ],
    "wof:name":"Shivaguda",
    "wof:placetype":"locality",
    "wof:population":39
},
  "geometry": {"coordinates":[78.63702499999999,19.434039],"type":"Point"}
}