{
  "type": "Feature",
  "properties": {
    "iso:country":"IN",
    "ks:ks_name":"Jayapurpatna",
    "ks:ks_pop":725,
    "ks:ks_type":"VILLAGE",
    "ks:ks_uagg_main":0,
    "name:eng_x_preferred":[
        "Jayapurpatna"
    ],
    "wof:name":"Jayapurpatna",
    "wof:placetype":"neighbourhood",
    "wof:population":725
},
  "geometry": {"coordinates":[85.83172500000001,20.205436],"type":"Point"}
}