{
  "type": "Feature",
  "properties": {
    "iso:country":"IN",
    "ks:ks_name":"Kola",
    "ks:ks_pop":44,
    "ks:ks_type":"HABITATION",
    "name:eng_x_preferred":[
        "Kola"
    ],
    "wof:name":"Kola",
    "wof:placetype":"locality",
    "wof:population":44
},
  "geometry": {"coordinates":[78.619135,29.902401],"type":"Point"}
}