{
  "type": "Feature",
  "properties": {
    "iso:country":"IN",
    "ks:ks_name":"Alenga",
    "ks:ks_pop":210,
    "ks:ks_type":"HABITATION",
    "name:eng_x_preferred":[
        "Alenga"
    ],
    "wof:name":"Alenga",
    "wof:placetype":"locality",
    "wof:population":210
},
  "geometry": {"coordinates":[91.996386,26.097133],"type":"Point"}
}