{
  "type": "Feature",
  "properties": {
    "iso:country":"IN",
    "ks:ks_name":"Gudkagal",
    "ks:ks_pop":967,
    "ks:ks_type":"HABITATION",
    "name:eng_x_preferred":[
        "Gudkagal"
    ],
    "wof:name":"Gudkagal",
    "wof:placetype":"locality",
    "wof:population":967
},
  "geometry": {"coordinates":[74.376026,14.507806],"type":"Point"}
}