{
  "type": "Feature",
  "properties": {
    "iso:country":"IN",
    "ks:ks_name":"Lakhanpur",
    "ks:ks_pop":43,
    "ks:ks_type":"VILLAGE",
    "name:eng_x_preferred":[
        "Lakhanpur"
    ],
    "wof:name":"Lakhanpur",
    "wof:placetype":"locality",
    "wof:population":43
},
  "geometry": {"coordinates":[82.456469,25.191559],"type":"Point"}
}