{
  "type": "Feature",
  "properties": {
    "iso:country":"IN",
    "ks:ks_name":"Borghuguloni",
    "ks:ks_pop":523,
    "ks:ks_type":"HABITATION",
    "name:eng_x_preferred":[
        "Borghuguloni"
    ],
    "wof:name":"Borghuguloni",
    "wof:placetype":"locality",
    "wof:population":523
},
  "geometry": {"coordinates":[94.97621599999999,27.277762],"type":"Point"}
}