{
  "type": "Feature",
  "properties": {
    "gn:admin1_code":"19.0",
    "gn:admin2_code":"555.0",
    "gn:asciiname":"Tigadi",
    "gn:country_code":"IN",
    "gn:dem":679,
    "gn:feature_class":"P",
    "gn:feature_code":"PPL",
    "gn:name":"Tigadi",
    "gn:population":0,
    "gn:timezone":"Asia/Kolkata",
    "iso:country":"IN",
    "wof:name":"Tigadi",
    "wof:placetype":"locality"
},
  "geometry": {"coordinates":[74.7183,15.79581],"type":"Point"}
}