{
  "type": "Feature",
  "properties": {
    "iso:country":"IN",
    "ks:ks_name":"Thottipalayam",
    "ks:ks_pop":292,
    "ks:ks_type":"HABITATION",
    "name:eng_x_preferred":[
        "Thottipalayam"
    ],
    "wof:name":"Thottipalayam",
    "wof:placetype":"locality",
    "wof:population":292
},
  "geometry": {"coordinates":[77.37956,11.292881],"type":"Point"}
}