{
  "type": "Feature",
  "properties": {
    "iso:country":"IN",
    "ks:ks_name":"Rathodfali",
    "ks:ks_pop":253,
    "ks:ks_type":"HABITATION",
    "name:eng_x_preferred":[
        "Rathodfali"
    ],
    "wof:name":"Rathodfali",
    "wof:placetype":"locality",
    "wof:population":253
},
  "geometry": {"coordinates":[73.56425400000001,23.444559],"type":"Point"}
}