{
  "type": "Feature",
  "properties": {
    "gn:admin1_code":"19.0",
    "gn:admin2_code":"566.0",
    "gn:asciiname":"Bhatrahalli",
    "gn:country_code":"IN",
    "gn:dem":526,
    "gn:feature_class":"P",
    "gn:feature_code":"PPL",
    "gn:name":"Bhatrahalli",
    "gn:population":0,
    "gn:timezone":"Asia/Kolkata",
    "iso:country":"IN",
    "ks:ks_name":"Bhatrahalli",
    "ks:ks_pop":1213,
    "ks:ks_type":"VILLAGE",
    "ks:ks_uagg_main":0,
    "name:eng_x_preferred":[
        "Bhatrahalli"
    ],
    "wof:name":"Bhatrahalli",
    "wof:placetype":"neighbourhood",
    "wof:population":1213
},
  "geometry": {"coordinates":[76.709754,14.792584],"type":"Point"}
}