{
  "type": "Feature",
  "properties": {
    "gn:admin1_code":"36",
    "gn:admin2_code":"196.0",
    "gn:asciiname":"Semar",
    "gn:country_code":"IN",
    "gn:dem":271,
    "gn:feature_class":"P",
    "gn:feature_code":"PPL",
    "gn:name":"Semar",
    "gn:population":0,
    "gn:timezone":"Asia/Kolkata",
    "iso:country":"IN",
    "name:bjn_x_preferred":[
        "Samar"
    ],
    "name:ces_x_preferred":[
        "Semar"
    ],
    "name:ind_x_preferred":[
        "Semar"
    ],
    "name:jav_x_preferred":[
        "Semar"
    ],
    "name:sun_x_preferred":[
        "Semar"
    ],
    "wof:name":"Semar",
    "wof:placetype":"locality"
},
  "geometry": {"coordinates":[83.35003,24.84971],"type":"Point"}
}