{
  "type": "Feature",
  "properties": {
    "iso:country":"IN",
    "ks:ks_alt_nam":"PURE DAYA MISHRA",
    "ks:ks_name":"Pure Daya Mishra",
    "ks:ks_pop":261,
    "ks:ks_type":"HABITATION",
    "ks:ks_uagg_main":0,
    "name:eng_x_preferred":[
        "Pure Daya Mishra"
    ],
    "wof:name":"Pure Daya Mishra",
    "wof:placetype":"neighbourhood",
    "wof:population":261
},
  "geometry": {"coordinates":[81.792686,26.092558],"type":"Point"}
}