{
  "type": "Feature",
  "properties": {
    "iso:country":"IN",
    "ks:ks_name":"Nani Kyar",
    "ks:ks_pop":808,
    "ks:ks_type":"VILLAGE",
    "name:eng_x_preferred":[
        "Nani Kyar"
    ],
    "wof:name":"Nani Kyar",
    "wof:placetype":"locality",
    "wof:population":808
},
  "geometry": {"coordinates":[73.89838899999999,23.282167],"type":"Point"}
}