{
  "type": "Feature",
  "properties": {
    "iso:country":"IN",
    "ks:ks_name":"Myrolu",
    "ks:ks_pop":533,
    "ks:ks_type":"HABITATION",
    "name:eng_x_preferred":[
        "Myrolu"
    ],
    "wof:name":"Myrolu",
    "wof:placetype":"locality",
    "wof:population":533
},
  "geometry": {"coordinates":[75.213887,12.580914],"type":"Point"}
}