{
  "type": "Feature",
  "properties": {
    "iso:country":"IN",
    "ks:ks_name":"Badyura",
    "ks:ks_pop":237,
    "ks:ks_type":"VILLAGE",
    "name:eng_x_preferred":[
        "Badyura"
    ],
    "wof:name":"Badyura",
    "wof:placetype":"locality",
    "wof:population":237
},
  "geometry": {"coordinates":[79.93399599999999,29.754378],"type":"Point"}
}