{
  "type": "Feature",
  "properties": {
    "iso:country":"IN",
    "ks:ks_name":"Sagwadi",
    "ks:ks_pop":63,
    "ks:ks_type":"HABITATION",
    "name:eng_x_preferred":[
        "Sagwadi"
    ],
    "wof:name":"Sagwadi",
    "wof:placetype":"locality",
    "wof:population":63
},
  "geometry": {"coordinates":[73.312,18.689673],"type":"Point"}
}