{
  "type": "Feature",
  "properties": {
    "iso:country":"IN",
    "ks:ks_name":"Gajatira",
    "ks:ks_pop":908,
    "ks:ks_type":"HABITATION",
    "name:eng_x_preferred":[
        "Gajatira"
    ],
    "wof:name":"Gajatira",
    "wof:placetype":"locality",
    "wof:population":908
},
  "geometry": {"coordinates":[82.86223699999999,27.057735],"type":"Point"}
}