{
  "type": "Feature",
  "properties": {
    "iso:country":"IN",
    "ks:ks_name":"Medipalle",
    "ks:ks_type":"VILLAGE",
    "name:eng_x_preferred":[
        "Medipalle"
    ],
    "wof:name":"Medipalle",
    "wof:placetype":"locality"
},
  "geometry": {"coordinates":[81.550555,16.942779],"type":"Point"}
}