{
  "type": "Feature",
  "properties": {
    "iso:country":"IN",
    "ks:ks_name":"Cristhu Nagar",
    "ks:ks_pop":468,
    "ks:ks_type":"HABITATION",
    "ks:ks_uagg_main":0,
    "name:eng_x_preferred":[
        "Cristhu Nagar"
    ],
    "wof:name":"Cristhu Nagar",
    "wof:placetype":"neighbourhood",
    "wof:population":468
},
  "geometry": {"coordinates":[77.47344,8.215775],"type":"Point"}
}