{
  "type": "Feature",
  "properties": {
    "iso:country":"IN",
    "ks:ks_name":"Chuna Bhati Tea Garden",
    "ks:ks_pop":5348,
    "ks:ks_type":"VILLAGE",
    "ks:ks_uagg_main":0,
    "name:eng_x_preferred":[
        "Chuna Bhati Tea Garden"
    ],
    "wof:name":"Chuna Bhati Tea Garden",
    "wof:placetype":"neighbourhood",
    "wof:population":5348
},
  "geometry": {"coordinates":[89.077485,26.849706],"type":"Point"}
}