{
  "type": "Feature",
  "properties": {
    "iso:country":"IN",
    "ks:ks_name":"Khanapur",
    "ks:ks_pop":942,
    "ks:ks_type":"HABITATION",
    "name:eng_x_preferred":[
        "Khanapur"
    ],
    "wof:name":"Khanapur",
    "wof:placetype":"locality",
    "wof:population":942
},
  "geometry": {"coordinates":[77.390038,18.02716],"type":"Point"}
}