{
  "type": "Feature",
  "properties": {
    "iso:country":"IN",
    "ks:ks_name":"Surtika Purwa",
    "ks:ks_pop":296,
    "ks:ks_type":"HABITATION",
    "ks:ks_uagg_main":0,
    "name:eng_x_preferred":[
        "Surtika Purwa"
    ],
    "wof:name":"Surtika Purwa",
    "wof:placetype":"neighbourhood",
    "wof:population":296
},
  "geometry": {"coordinates":[81.46882100000001,26.605958],"type":"Point"}
}