{
  "type": "Feature",
  "properties": {
    "gn:admin1_code":"40.0",
    "gn:admin2_code":"535.0",
    "gn:asciiname":"Gopalpur",
    "gn:country_code":"IN",
    "gn:dem":569,
    "gn:feature_class":"P",
    "gn:feature_code":"PPL",
    "gn:name":"Gop\u0101lpur",
    "gn:population":0,
    "gn:timezone":"Asia/Kolkata",
    "iso:country":"IN",
    "wof:name":"Gopalpur",
    "wof:placetype":"locality"
},
  "geometry": {"coordinates":[78.81095999999999,17.83633],"type":"Point"}
}