{
  "type": "Feature",
  "properties": {
    "iso:country":"IN",
    "ks:ks_alt_nam":"Rajkhola Sk para",
    "ks:ks_name":"Rajkhola Sk Para",
    "ks:ks_pop":1299,
    "ks:ks_type":"HABITATION",
    "ks:ks_uagg_main":0,
    "name:eng_x_preferred":[
        "Rajkhola Sk Para"
    ],
    "wof:name":"Rajkhola Sk Para",
    "wof:placetype":"locality",
    "wof:population":1299
},
  "geometry": {"coordinates":[88.09137,22.551171],"type":"Point"}
}