{
  "type": "Feature",
  "properties": {
    "iso:country":"IN",
    "ks:ks_name":"Pirijpur",
    "ks:ks_pop":1463,
    "ks:ks_type":"VILLAGE",
    "ks:ks_uagg_main":0,
    "name:eng_x_preferred":[
        "Pirijpur"
    ],
    "wof:name":"Pirijpur",
    "wof:placetype":"neighbourhood",
    "wof:population":1463
},
  "geometry": {"coordinates":[87.874126,22.831744],"type":"Point"}
}