{
  "type": "Feature",
  "properties": {
    "gn:admin1_code":"36",
    "gn:admin2_code":"158.0",
    "gn:asciiname":"Gawa",
    "gn:country_code":"IN",
    "gn:dem":111,
    "gn:feature_class":"P",
    "gn:feature_code":"PPL",
    "gn:name":"Gawa",
    "gn:population":0,
    "gn:timezone":"Asia/Kolkata",
    "iso:country":"IN",
    "name:bar_x_preferred":[
        "Gawa"
    ],
    "name:ceb_x_preferred":[
        "Gawa"
    ],
    "name:swe_x_preferred":[
        "Gawa"
    ],
    "wof:name":"Gawa",
    "wof:placetype":"locality"
},
  "geometry": {"coordinates":[81.34578,26.07781],"type":"Point"}
}