{
  "type": "Feature",
  "properties": {
    "iso:country":"IN",
    "ks:ks_name":"Orkela",
    "ks:ks_pop":504,
    "ks:ks_type":"VILLAGE",
    "name:eng_x_preferred":[
        "Orkela"
    ],
    "wof:name":"Orkela",
    "wof:placetype":"locality",
    "wof:population":504
},
  "geometry": {"coordinates":[83.975685,22.918748],"type":"Point"}
}