{
  "type": "Feature",
  "properties": {
    "gn:admin1_code":"36",
    "gn:admin2_code":"165.0",
    "gn:asciiname":"Chamra Thakurpur",
    "gn:country_code":"IN",
    "gn:dem":161,
    "gn:feature_class":"P",
    "gn:feature_code":"PPL",
    "gn:name":"Chamra Th\u0101kurpur",
    "gn:population":0,
    "gn:timezone":"Asia/Kolkata",
    "iso:country":"IN",
    "wof:name":"Chamra Thakurpur",
    "wof:placetype":"locality"
},
  "geometry": {"coordinates":[79.10077,25.98524],"type":"Point"}
}