{
  "type": "Feature",
  "properties": {
    "iso:country":"IN",
    "ks:ks_name":"Katiwade",
    "ks:ks_pop":100,
    "ks:ks_type":"VILLAGE",
    "name:eng_x_preferred":[
        "Katiwade"
    ],
    "wof:name":"Katiwade",
    "wof:placetype":"locality",
    "wof:population":100
},
  "geometry": {"coordinates":[73.51142400000001,18.087343],"type":"Point"}
}