{
  "type": "Feature",
  "properties": {
    "iso:country":"IN",
    "ks:ks_name":"Chamrauti",
    "ks:ks_pop":350,
    "ks:ks_type":"HABITATION",
    "name:eng_x_preferred":[
        "Chamrauti"
    ],
    "wof:name":"Chamrauti",
    "wof:placetype":"locality",
    "wof:population":350
},
  "geometry": {"coordinates":[82.474994,26.307628],"type":"Point"}
}