{
  "type": "Feature",
  "properties": {
    "gn:admin1_code":"35.0",
    "gn:admin2_code":"446",
    "gn:asciiname":"Bari",
    "gn:country_code":"IN",
    "gn:dem":337,
    "gn:feature_class":"P",
    "gn:feature_code":"PPL",
    "gn:name":"B\u0101ri",
    "gn:population":0,
    "gn:timezone":"Asia/Kolkata",
    "iso:country":"IN",
    "wof:name":"Bari",
    "wof:placetype":"locality"
},
  "geometry": {"coordinates":[78.08079000000002,23.03632],"type":"Point"}
}