{
  "type": "Feature",
  "properties": {
    "gn:country":"IN",
    "gn:fcode":"PPL",
    "gn:pop":19403,
    "iso:country":"IN",
    "name:ast_x_preferred":[
        "Sojitra"
    ],
    "name:ceb_x_preferred":[
        "Soj\u012btra"
    ],
    "name:eng_x_preferred":[
        "Sojitra"
    ],
    "name:guj_x_preferred":[
        "\u0ab8\u0acb\u0a9c\u0abf\u0a82\u0aa4\u0acd\u0ab0\u0abe"
    ],
    "name:guj_x_variant":[
        "\u0ab8\u0acb\u0a9c\u0abf\u0aa4\u0acd\u0ab0\u0abe"
    ],
    "name:nld_x_preferred":[
        "Sojitra"
    ],
    "name:swe_x_preferred":[
        "Soj\u012btra"
    ],
    "name:unk_x_variant":[
        "Soj\u012btra"
    ],
    "qs:name":"Sojitra",
    "qs:name_adm0":"India",
    "qs:name_adm1":"Gujarat",
    "qs:photos_9r":0,
    "qs:photos_sr":0,
    "qs:placetype":"Town",
    "qs:pop_sr":"6",
    "wd:wordcount":667,
    "wof:name":"Sojitra",
    "wof:placetype":"locality",
    "wof:population":19403
},
  "geometry": {"coordinates":[72.71984,22.53884],"type":"Point"}
}