{
  "type": "Feature",
  "properties": {
    "gn:admin1_code":"39",
    "gn:admin2_code":"60.0",
    "gn:asciiname":"Matha Khera",
    "gn:country_code":"IN",
    "gn:dem":1342,
    "gn:feature_class":"P",
    "gn:feature_code":"PPL",
    "gn:name":"Matha Khera",
    "gn:population":0,
    "gn:timezone":"Asia/Kolkata",
    "iso:country":"IN",
    "wof:name":"Matha Khera",
    "wof:placetype":"locality"
},
  "geometry": {"coordinates":[77.84933000000002,30.7947],"type":"Point"}
}