{
  "type": "Feature",
  "properties": {
    "gn:admin1_code":"19",
    "gn:admin2_code":"575.0",
    "gn:asciiname":"Uppinakudru",
    "gn:country_code":"IN",
    "gn:dem":8,
    "gn:feature_class":"P",
    "gn:feature_code":"PPLL",
    "gn:name":"Uppinakudru",
    "gn:population":0,
    "gn:timezone":"Asia/Kolkata",
    "iso:country":"IN",
    "name:spa_x_preferred":[
        "Uppinakudru"
    ],
    "wof:name":"Uppinakudru",
    "wof:placetype":"locality"
},
  "geometry": {"coordinates":[74.68968000000002,13.65996],"type":"Point"}
}