{
  "type": "Feature",
  "properties": {
    "gn:admin1_code":"16",
    "gn:admin2_code":"511.0",
    "gn:asciiname":"Ritha",
    "gn:country_code":"IN",
    "gn:dem":400,
    "gn:feature_class":"P",
    "gn:feature_code":"PPL",
    "gn:name":"R\u012btha",
    "gn:population":0,
    "gn:timezone":"Asia/Kolkata",
    "iso:country":"IN",
    "ks:ks_alt_nam":"R\u012btha Reserved Forest",
    "ks:ks_alt_nam_2":"Ritha Reserved Forest",
    "ks:ks_name":"Ritha",
    "ks:ks_pop":1181,
    "ks:ks_type":"VILLAGE",
    "name:eng_x_preferred":[
        "Ritha"
    ],
    "name:eng_x_variant":[
        "R\u012btha Reserved Forest",
        "Ritha Reserved Forest"
    ],
    "wof:name":"Ritha",
    "wof:placetype":"locality",
    "wof:population":1181
},
  "geometry": {"coordinates":[78.06721400000001,19.422487],"type":"Point"}
}