{
  "type": "Feature",
  "properties": {
    "iso:country":"IN",
    "ks:ks_name":"Bhimpur",
    "ks:ks_pop":132,
    "ks:ks_type":"VILLAGE",
    "name:eng_x_preferred":[
        "Bhimpur"
    ],
    "wof:name":"Bhimpur",
    "wof:placetype":"locality",
    "wof:population":132
},
  "geometry": {"coordinates":[83.54522299999999,19.708947],"type":"Point"}
}