{
  "type": "Feature",
  "properties": {
    "iso:country":"IN",
    "ks:ks_name":"Girui",
    "ks:ks_pop":570,
    "ks:ks_type":"VILLAGE",
    "name:eng_x_preferred":[
        "Girui"
    ],
    "wof:name":"Girui",
    "wof:placetype":"locality",
    "wof:population":570
},
  "geometry": {"coordinates":[81.422571,23.882723],"type":"Point"}
}