{
  "type": "Feature",
  "properties": {
    "iso:country":"IN",
    "ks:ks_alt_nam":"Manyapuram colony road",
    "ks:ks_name":"Manyapuram Colony Road",
    "ks:ks_pop":274,
    "ks:ks_type":"HABITATION",
    "name:eng_x_preferred":[
        "Manyapuram Colony Road"
    ],
    "wof:name":"Manyapuram Colony Road",
    "wof:placetype":"locality",
    "wof:population":274
},
  "geometry": {"coordinates":[76.823927,9.107196],"type":"Point"}
}