{
  "type": "Feature",
  "properties": {
    "gn:admin1_code":"39",
    "gn:admin2_code":"61.0",
    "gn:asciiname":"Sakniana",
    "gn:country_code":"IN",
    "gn:dem":1822,
    "gn:feature_class":"P",
    "gn:feature_code":"PPL",
    "gn:name":"Sakni\u0101na",
    "gn:population":0,
    "gn:timezone":"Asia/Kolkata",
    "iso:country":"IN",
    "wof:name":"Sakniana",
    "wof:placetype":"locality"
},
  "geometry": {"coordinates":[78.98679,30.07016],"type":"Point"}
}