{
  "type": "Feature",
  "properties": {
    "iso:country":"IN",
    "ks:ks_alt_nam":"Thorat faliya",
    "ks:ks_name":"Thorat Faliya",
    "ks:ks_pop":402,
    "ks:ks_type":"HABITATION",
    "name:eng_x_preferred":[
        "Thorat Faliya"
    ],
    "wof:name":"Thorat Faliya",
    "wof:placetype":"locality",
    "wof:population":402
},
  "geometry": {"coordinates":[73.407174,20.586888],"type":"Point"}
}