{
  "type": "Feature",
  "properties": {
    "gn:admin1_code":"22.0",
    "gn:admin2_code":"637",
    "gn:asciiname":"Akkaraivadi",
    "gn:country_code":"IN",
    "gn:dem":10,
    "gn:feature_class":"P",
    "gn:feature_code":"PPL",
    "gn:name":"Akkaraiv\u0101di",
    "gn:population":0,
    "gn:timezone":"Asia/Kolkata",
    "iso:country":"IN",
    "name:und_x_variant":[
        "Accarapatam",
        "Akkaraiv\u0101di"
    ],
    "wof:name":"Akkaraivadi",
    "wof:placetype":"locality"
},
  "geometry": {"coordinates":[79.83851,10.89755],"type":"Point"}
}