{
  "type": "Feature",
  "properties": {
    "iso:country":"IN",
    "ks:ks_name":"Paradpada",
    "ks:ks_pop":131,
    "ks:ks_type":"HABITATION",
    "name:eng_x_preferred":[
        "Paradpada"
    ],
    "wof:name":"Paradpada",
    "wof:placetype":"locality",
    "wof:population":131
},
  "geometry": {"coordinates":[73.07227899999999,19.66887],"type":"Point"}
}