{
  "type": "Feature",
  "properties": {
    "gn:admin1_code":"40.0",
    "gn:admin2_code":"532.0",
    "gn:asciiname":"Kadegaon",
    "gn:country_code":"IN",
    "gn:dem":220,
    "gn:feature_class":"P",
    "gn:feature_code":"PPL",
    "gn:name":"Kadegaon",
    "gn:population":0,
    "gn:timezone":"Asia/Kolkata",
    "iso:country":"IN",
    "name:mar_x_preferred":[
        "\u0915\u0921\u0947\u0917\u093e\u0902\u0935"
    ],
    "wof:name":"Kadegaon",
    "wof:placetype":"locality"
},
  "geometry": {"coordinates":[79.37195,19.43981],"type":"Point"}
}