{
  "type": "Feature",
  "properties": {
    "gn:admin1_code":"40.0",
    "gn:admin2_code":"532.0",
    "gn:asciiname":"Kadegaon",
    "gn:country_code":"IN",
    "gn:dem":220,
    "gn:feature_class":"P",
    "gn:feature_code":"PPL",
    "gn:name":"Kadegaon",
    "gn:population":0,
    "gn:timezone":"Asia/Kolkata",
    "iso:country":"IN",
    "ks:ks_name":"Khedegaon",
    "ks:ks_pop":157,
    "ks:ks_type":"HABITATION",
    "name:eng_x_preferred":[
        "Khedegaon"
    ],
    "name:eng_x_variant":[
        "Kadegaon"
    ],
    "name:mar_x_preferred":[
        "\u0915\u0921\u0947\u0917\u093e\u0902\u0935"
    ],
    "wof:name":"Khedegaon",
    "wof:placetype":"locality",
    "wof:population":157
},
  "geometry": {"coordinates":[79.371933,19.439894],"type":"Point"}
}