{
  "type": "Feature",
  "properties": {
    "iso:country":"IN",
    "ks:ks_name":"Ponnamkayam",
    "ks:ks_pop":626,
    "ks:ks_type":"HABITATION",
    "name:eng_x_preferred":[
        "Ponnamkayam"
    ],
    "wof:name":"Ponnamkayam",
    "wof:placetype":"locality",
    "wof:population":626
},
  "geometry": {"coordinates":[76.045074,11.395968],"type":"Point"}
}