{
  "type": "Feature",
  "properties": {
    "iso:country":"IN",
    "ks:ks_name":"Gunjirpur",
    "ks:ks_pop":1721,
    "ks:ks_type":"VILLAGE",
    "ks:ks_uagg_main":0,
    "name:eng_x_preferred":[
        "Gunjirpur"
    ],
    "wof:name":"Gunjirpur",
    "wof:placetype":"neighbourhood",
    "wof:population":1721
},
  "geometry": {"coordinates":[88.364014,22.13184],"type":"Point"}
}