{
  "type": "Feature",
  "properties": {
    "iso:country":"IN",
    "ks:ks_name":"Pratit Garh",
    "ks:ks_pop":188,
    "ks:ks_type":"HABITATION",
    "ks:ks_uagg_main":0,
    "name:eng_x_preferred":[
        "Pratit Garh"
    ],
    "wof:name":"Pratit Garh",
    "wof:placetype":"neighbourhood",
    "wof:population":188
},
  "geometry": {"coordinates":[81.529045,26.403168],"type":"Point"}
}