{
  "type": "Feature",
  "properties": {
    "gn:admin1_code":"2.0",
    "gn:admin2_code":"554.0",
    "gn:asciiname":"Paipalaiyam",
    "gn:country_code":"IN",
    "gn:dem":693,
    "gn:feature_class":"P",
    "gn:feature_code":"PPL",
    "gn:name":"Paip\u0101laiyam",
    "gn:population":0,
    "gn:timezone":"Asia/Kolkata",
    "iso:country":"IN",
    "wof:name":"Paipalaiyam",
    "wof:placetype":"locality"
},
  "geometry": {"coordinates":[78.35415,12.68362],"type":"Point"}
}