{
  "type": "Feature",
  "properties": {
    "iso:country":"IN",
    "ks:ks_name":"Vijaipur",
    "ks:ks_pop":247,
    "ks:ks_type":"HABITATION",
    "name:eng_x_preferred":[
        "Vijaipur"
    ],
    "wof:name":"Vijaipur",
    "wof:placetype":"locality",
    "wof:population":247
},
  "geometry": {"coordinates":[78.43222299999999,25.716535],"type":"Point"}
}