{
  "type": "Feature",
  "properties": {
    "iso:country":"IN",
    "ks:ks_alt_nam":"Pondi khaspara",
    "ks:ks_name":"Pondi Khaspara",
    "ks:ks_pop":480,
    "ks:ks_type":"HABITATION",
    "name:eng_x_preferred":[
        "Pondi Khaspara"
    ],
    "wof:name":"Pondi Khaspara",
    "wof:placetype":"locality",
    "wof:population":480
},
  "geometry": {"coordinates":[83.349063,23.432199],"type":"Point"}
}