{
  "type": "Feature",
  "properties": {
    "gn:admin1_code":"24.0",
    "gn:admin2_code":"123.0",
    "gn:asciiname":"Butia",
    "gn:country_code":"IN",
    "gn:dem":582,
    "gn:feature_class":"P",
    "gn:feature_code":"PPL",
    "gn:name":"Butia",
    "gn:population":0,
    "gn:timezone":"Asia/Kolkata",
    "iso:country":"IN",
    "name:cat_x_preferred":[
        "Butia"
    ],
    "name:ceb_x_preferred":[
        "Butia"
    ],
    "name:deu_x_preferred":[
        "Geleepalmen"
    ],
    "name:fin_x_preferred":[
        "Butiapalmut"
    ],
    "name:fra_x_preferred":[
        "Butia"
    ],
    "name:grn_x_preferred":[
        "Mbotia"
    ],
    "name:ita_x_preferred":[
        "Butia"
    ],
    "name:lit_x_preferred":[
        "Bucija"
    ],
    "name:nld_x_preferred":[
        "Butia"
    ],
    "name:pol_x_preferred":[
        "Butia"
    ],
    "name:por_x_preferred":[
        "Buti\u00e1"
    ],
    "name:rus_x_preferred":[
        "\u0411\u0443\u0442\u0438\u044f"
    ],
    "name:spa_x_preferred":[
        "Butia"
    ],
    "name:swe_x_preferred":[
        "Butia"
    ],
    "name:war_x_preferred":[
        "Butia"
    ],
    "wof:name":"Butia",
    "wof:placetype":"neighbourhood"
},
  "geometry": {"coordinates":[73.76197999999999,24.79301],"type":"Point"}
}