{
  "type": "Feature",
  "properties": {
    "iso:country":"IN",
    "ks:ks_name":"Herate",
    "ks:ks_pop":56,
    "ks:ks_type":"HABITATION",
    "name:eng_x_preferred":[
        "Herate"
    ],
    "wof:name":"Herate",
    "wof:placetype":"locality",
    "wof:population":56
},
  "geometry": {"coordinates":[75.052791,13.767224],"type":"Point"}
}