{
  "type": "Feature",
  "properties": {
    "iso:country":"IN",
    "ks:ks_name":"Bichhaun",
    "ks:ks_pop":118,
    "ks:ks_type":"VILLAGE",
    "name:eng_x_preferred":[
        "Bichhaun"
    ],
    "wof:name":"Bichhaun",
    "wof:placetype":"locality",
    "wof:population":118
},
  "geometry": {"coordinates":[79.078609,24.26123],"type":"Point"}
}