{
  "type": "Feature",
  "properties": {
    "gn:admin1_code":"9.0",
    "gn:admin2_code":"484.0",
    "gn:asciiname":"Bechar Metana Muwara",
    "gn:country_code":"IN",
    "gn:dem":151,
    "gn:feature_class":"P",
    "gn:feature_code":"PPL",
    "gn:name":"Bechar Met\u0101na Muw\u0101ra",
    "gn:population":0,
    "gn:timezone":"Asia/Kolkata",
    "iso:country":"IN",
    "wof:name":"Bechar Metana Muwara",
    "wof:placetype":"locality"
},
  "geometry": {"coordinates":[73.91248,23.21071],"type":"Point"}
}