{
  "type": "Feature",
  "properties": {
    "iso:country":"IN",
    "ks:ks_alt_nam":"BIHAR",
    "ks:ks_name":"Bihar",
    "ks:ks_pop":438,
    "ks:ks_type":"HABITATION",
    "name:eng_x_preferred":[
        "Bihar"
    ],
    "name:hin_x_preferred":[
        "\u092c\u093f\u0939\u093e\u0930"
    ],
    "wof:name":"Bihar",
    "wof:placetype":"locality",
    "wof:population":438
},
  "geometry": {"coordinates":[85.340918,23.699545],"type":"Point"}
}