{
  "type": "Feature",
  "properties": {
    "iso:country":"IN",
    "ks:ks_name":"Jojobera",
    "ks:ks_pop":2590,
    "ks:ks_type":"VILLAGE",
    "ks:ks_uagg_main":0,
    "name:eng_x_preferred":[
        "Jojobera"
    ],
    "wof:name":"Jojobera",
    "wof:placetype":"neighbourhood",
    "wof:population":2590
},
  "geometry": {"coordinates":[86.25326800000001,22.754267],"type":"Point"}
}