{
  "type": "Feature",
  "properties": {
    "gn:admin1_code":"40",
    "gn:admin2_code":"540.0",
    "gn:asciiname":"Nirmala",
    "gn:country_code":"IN",
    "gn:dem":299,
    "gn:feature_class":"P",
    "gn:feature_code":"PPL",
    "gn:name":"Nirm\u0101la",
    "gn:population":0,
    "gn:timezone":"Asia/Kolkata",
    "iso:country":"IN",
    "name:deu_x_preferred":[
        "Nirmala"
    ],
    "name:fra_x_preferred":[
        "Nirmala"
    ],
    "wof:name":"Nirmala",
    "wof:placetype":"locality"
},
  "geometry": {"coordinates":[79.25259,17.57239],"type":"Point"}
}