{
  "type": "Feature",
  "properties": {
    "iso:country":"IN",
    "ks:ks_name":"Nehru Nagar",
    "ks:ks_pop":392,
    "ks:ks_type":"HABITATION",
    "name:eng_x_preferred":[
        "Nehru Nagar"
    ],
    "wof:name":"Nehru Nagar",
    "wof:placetype":"locality",
    "wof:population":392
},
  "geometry": {"coordinates":[80.894992,16.861891],"type":"Point"}
}