{
  "type": "Feature",
  "properties": {
    "gn:admin1_code":"40",
    "gn:admin2_code":"532.0",
    "gn:asciiname":"Nipani",
    "gn:country_code":"IN",
    "gn:dem":271,
    "gn:feature_class":"P",
    "gn:feature_code":"PPL",
    "gn:name":"Nip\u0101ni",
    "gn:population":0,
    "gn:timezone":"Asia/Kolkata",
    "iso:country":"IN",
    "name:ben_x_preferred":[
        "\u09a8\u09be\u09aa\u09be\u09a8\u09bf"
    ],
    "name:bpy_x_preferred":[
        "\u09a8\u09be\u09aa\u09be\u09a8\u09bf"
    ],
    "name:ceb_x_preferred":[
        "Nip\u0101ni"
    ],
    "name:ita_x_preferred":[
        "Nipani"
    ],
    "name:kan_x_preferred":[
        "\u0ca8\u0cbf\u0caa\u0ccd\u0caa\u0cbe\u0ca3\u0cbf"
    ],
    "name:mar_x_preferred":[
        "\u0928\u093f\u092a\u093e\u0923\u0940"
    ],
    "name:mlg_x_preferred":[
        "Nipani"
    ],
    "name:msa_x_preferred":[
        "Nipani"
    ],
    "name:new_x_preferred":[
        "\u0928\u093f\u092a\u093e\u0928\u0940"
    ],
    "name:nld_x_preferred":[
        "Nipani"
    ],
    "name:por_x_preferred":[
        "Nipani"
    ],
    "name:spa_x_preferred":[
        "Nipani"
    ],
    "name:swe_x_preferred":[
        "Nip\u0101ni"
    ],
    "name:vie_x_preferred":[
        "Nipani"
    ],
    "name:zho_x_preferred":[
        "\u5c3c\u5e15\u5c3c"
    ],
    "wof:name":"Nipani",
    "wof:placetype":"locality"
},
  "geometry": {"coordinates":[78.45675,19.7487],"type":"Point"}
}