{
  "type": "Feature",
  "properties": {
    "iso:country":"IN",
    "ks:ks_name":"Taukala",
    "ks:ks_pop":150,
    "ks:ks_type":"HABITATION",
    "name:eng_x_preferred":[
        "Taukala"
    ],
    "wof:name":"Taukala",
    "wof:placetype":"locality",
    "wof:population":150
},
  "geometry": {"coordinates":[82.342279,26.392867],"type":"Point"}
}