{
  "type": "Feature",
  "properties": {
    "gn:admin1_code":"35",
    "gn:admin2_code":"455.0",
    "gn:asciiname":"Badnur Khurd",
    "gn:country_code":"IN",
    "gn:dem":803,
    "gn:feature_class":"P",
    "gn:feature_code":"PPL",
    "gn:name":"Badn\u016br Khurd",
    "gn:population":0,
    "gn:timezone":"Asia/Kolkata",
    "iso:country":"IN",
    "wof:name":"Badnur Khurd",
    "wof:placetype":"locality"
},
  "geometry": {"coordinates":[78.42522,22.08728],"type":"Point"}
}