{
  "type": "Feature",
  "properties": {
    "iso:country":"IN",
    "ks:ks_name":"Nagla Kesho",
    "ks:ks_pop":76,
    "ks:ks_type":"HABITATION",
    "name:eng_x_preferred":[
        "Nagla Kesho"
    ],
    "wof:name":"Nagla Kesho",
    "wof:placetype":"locality",
    "wof:population":76
},
  "geometry": {"coordinates":[78.511285,27.2415],"type":"Point"}
}