{
  "type": "Feature",
  "properties": {
    "iso:country":"IN",
    "ks:ks_name":"Loharwadi",
    "ks:ks_pop":380,
    "ks:ks_type":"HABITATION",
    "name:eng_x_preferred":[
        "Loharwadi"
    ],
    "wof:name":"Loharwadi",
    "wof:placetype":"locality",
    "wof:population":380
},
  "geometry": {"coordinates":[73.960522,17.163619],"type":"Point"}
}