{
  "type": "Feature",
  "properties": {
    "iso:country":"IN",
    "ks:ks_name":"Junadihi",
    "ks:ks_pop":257,
    "ks:ks_type":"HABITATION",
    "name:eng_x_preferred":[
        "Junadihi"
    ],
    "wof:name":"Junadihi",
    "wof:placetype":"locality",
    "wof:population":257
},
  "geometry": {"coordinates":[82.239057,19.991528],"type":"Point"}
}