{
  "type": "Feature",
  "properties": {
    "iso:country":"IN",
    "ks:ks_name":"Edayoor",
    "ks:ks_pop":30462,
    "ks:ks_type":"VILLAGE",
    "ks:ks_uagg_main":0,
    "name:eng_x_preferred":[
        "Edayoor"
    ],
    "wof:name":"Edayoor",
    "wof:placetype":"neighbourhood",
    "wof:population":30462
},
  "geometry": {"coordinates":[76.09237299999999,10.923252],"type":"Point"}
}