{
  "type": "Feature",
  "properties": {
    "gn:admin1_code":"24",
    "gn:admin2_code":"119.0",
    "gn:asciiname":"Rajpura",
    "gn:country_code":"IN",
    "gn:dem":404,
    "gn:feature_class":"P",
    "gn:feature_code":"PPL",
    "gn:name":"R\u0101jpura",
    "gn:population":0,
    "gn:timezone":"Asia/Kolkata",
    "iso:country":"IN",
    "name:ben_x_preferred":[
        "\u09b0\u09be\u099c\u09aa\u09c1\u09b0\u09be"
    ],
    "name:bpy_x_preferred":[
        "\u09b0\u09be\u099c\u09aa\u09c1\u09b0\u09be"
    ],
    "name:ceb_x_preferred":[
        "R\u0101jpura"
    ],
    "name:hin_x_preferred":[
        "\u0930\u093e\u091c\u092a\u0941\u0930\u093e"
    ],
    "name:ita_x_preferred":[
        "Rajpura"
    ],
    "name:mlg_x_preferred":[
        "Rajpura"
    ],
    "name:msa_x_preferred":[
        "Rajpura"
    ],
    "name:nld_x_preferred":[
        "Rajpura"
    ],
    "name:ori_x_preferred":[
        "\u0b30\u0b3e\u0b1c\u0b2a\u0b41\u0b30\u0b3e"
    ],
    "name:pan_x_preferred":[
        "\u0a30\u0a3e\u0a1c\u0a2a\u0a41\u0a30\u0a3e"
    ],
    "name:por_x_preferred":[
        "Rajpura"
    ],
    "name:spa_x_preferred":[
        "Rajpura"
    ],
    "name:swe_x_preferred":[
        "Rajpura"
    ],
    "name:urd_x_preferred":[
        "\u0631\u0627\u062c\u067e\u0648\u0631\u06c1"
    ],
    "name:vie_x_preferred":[
        "Rajpura"
    ],
    "name:zho_x_preferred":[
        "\u62c9\u6770\u666e\u62c9"
    ],
    "wof:name":"Rajpura",
    "wof:placetype":"neighbourhood"
},
  "geometry": {"coordinates":[74.71343,26.16511],"type":"Point"}
}