{
  "type": "Feature",
  "properties": {
    "iso:country":"IN",
    "ks:ks_name":"Dharnipatti Ramtola",
    "ks:ks_pop":145,
    "ks:ks_type":"HABITATION",
    "name:eng_x_preferred":[
        "Dharnipatti Ramtola"
    ],
    "wof:name":"Dharnipatti Ramtola",
    "wof:placetype":"locality",
    "wof:population":145
},
  "geometry": {"coordinates":[86.646733,26.087737],"type":"Point"}
}