{
  "type": "Feature",
  "properties": {
    "gn:admin1_code":"16",
    "gn:admin2_code":"515.0",
    "gn:asciiname":"Jamkhed",
    "gn:country_code":"IN",
    "gn:dem":530,
    "gn:feature_class":"P",
    "gn:feature_code":"PPL",
    "gn:name":"J\u0101mkhed",
    "gn:population":0,
    "gn:timezone":"Asia/Kolkata",
    "iso:country":"IN",
    "name:ben_x_preferred":[
        "\u099c\u09be\u09ae\u0996\u09c7\u09a6"
    ],
    "name:bpy_x_preferred":[
        "\u099c\u09be\u09ae\u0996\u09c7\u09a6"
    ],
    "name:ceb_x_preferred":[
        "J\u0101mkhed"
    ],
    "name:ita_x_preferred":[
        "Jamkhed"
    ],
    "name:mar_x_preferred":[
        "\u091c\u093e\u092e\u0916\u0947\u0921"
    ],
    "name:mlg_x_preferred":[
        "Jamkhed"
    ],
    "name:msa_x_preferred":[
        "Jamkhed"
    ],
    "name:new_x_preferred":[
        "\u091c\u093e\u092e\u0916\u0947\u0921"
    ],
    "name:nld_x_preferred":[
        "Jamkhed"
    ],
    "name:swe_x_preferred":[
        "J\u0101mkhed"
    ],
    "name:urd_x_preferred":[
        "\u062c\u0627\u0645 \u06a9\u06be\u06cc\u0691"
    ],
    "name:vie_x_preferred":[
        "Jamkhed"
    ],
    "name:zho_x_preferred":[
        "\u8d3e\u59c6\u51ef\u5fb7"
    ],
    "wof:name":"Jamkhed",
    "wof:placetype":"locality"
},
  "geometry": {"coordinates":[74.99479000000002,20.03878],"type":"Point"}
}