{
  "type": "Feature",
  "properties": {
    "iso:country":"IN",
    "ks:ks_alt_nam":"Shimal daha",
    "ks:ks_name":"Shimal Daha",
    "ks:ks_pop":328,
    "ks:ks_type":"HABITATION",
    "name:eng_x_preferred":[
        "Shimal Daha"
    ],
    "wof:name":"Shimal Daha",
    "wof:placetype":"locality",
    "wof:population":328
},
  "geometry": {"coordinates":[87.200073,25.683992],"type":"Point"}
}