{
  "type": "Feature",
  "properties": {
    "gn:admin1_code":"34",
    "gn:admin2_code":"233.0",
    "gn:asciiname":"Parasia",
    "gn:country_code":"IN",
    "gn:dem":71,
    "gn:feature_class":"P",
    "gn:feature_code":"PPL",
    "gn:name":"Par\u0101sia",
    "gn:population":0,
    "gn:timezone":"Asia/Kolkata",
    "iso:country":"IN",
    "name:bpy_x_preferred":[
        "\u09aa\u09b0\u09be\u09b6\u09bf\u09af\u09bc\u09be"
    ],
    "name:ita_x_preferred":[
        "Parasia"
    ],
    "name:mlg_x_preferred":[
        "Parasia"
    ],
    "name:msa_x_preferred":[
        "Parasia"
    ],
    "name:nld_x_preferred":[
        "Parasia"
    ],
    "name:por_x_preferred":[
        "Parasia"
    ],
    "name:vie_x_preferred":[
        "Parasia"
    ],
    "name:zho_x_preferred":[
        "\u5e15\u62c9\u590f"
    ],
    "wof:name":"Parasia",
    "wof:placetype":"locality"
},
  "geometry": {"coordinates":[83.79947,25.28122],"type":"Point"}
}