{
  "type": "Feature",
  "properties": {
    "iso:country":"IN",
    "ks:ks_name":"Bangarpada",
    "ks:ks_pop":220,
    "ks:ks_type":"HABITATION",
    "name:eng_x_preferred":[
        "Bangarpada"
    ],
    "wof:name":"Bangarpada",
    "wof:placetype":"locality",
    "wof:population":220
},
  "geometry": {"coordinates":[73.34098400000001,19.136401],"type":"Point"}
}