{
  "type": "Feature",
  "properties": {
    "gn:admin1_code":"19",
    "gn:admin2_code":"563.0",
    "gn:asciiname":"Mattihalli",
    "gn:country_code":"IN",
    "gn:dem":552,
    "gn:feature_class":"P",
    "gn:feature_code":"PPL",
    "gn:name":"Mattihalli",
    "gn:population":0,
    "gn:timezone":"Asia/Kolkata",
    "iso:country":"IN",
    "ks:ks_name":"Matti Halli",
    "ks:ks_pop":565,
    "ks:ks_type":"VILLAGE",
    "name:eng_x_preferred":[
        "Matti Halli"
    ],
    "name:eng_x_variant":[
        "Mattihalli"
    ],
    "wof:name":"Matti Halli",
    "wof:placetype":"locality",
    "wof:population":565
},
  "geometry": {"coordinates":[74.85897900000001,14.475537],"type":"Point"}
}