{
  "type": "Feature",
  "properties": {
    "iso:country":"IN",
    "ks:ks_alt_nam":"PURE BENI PD",
    "ks:ks_name":"Pure Beni Pd",
    "ks:ks_pop":101,
    "ks:ks_type":"HABITATION",
    "ks:ks_uagg_main":0,
    "name:eng_x_preferred":[
        "Pure Beni Pd"
    ],
    "wof:name":"Pure Beni Pd",
    "wof:placetype":"neighbourhood",
    "wof:population":101
},
  "geometry": {"coordinates":[81.780389,26.30078],"type":"Point"}
}