{
  "type": "Feature",
  "properties": {
    "iso:country":"IN",
    "ks:ks_alt_nam":"Vanse pada",
    "ks:ks_name":"Vanse Pada",
    "ks:ks_pop":289,
    "ks:ks_type":"HABITATION",
    "name:eng_x_preferred":[
        "Vanse Pada"
    ],
    "wof:name":"Vanse Pada",
    "wof:placetype":"locality",
    "wof:population":289
},
  "geometry": {"coordinates":[73.14546900000001,19.831721],"type":"Point"}
}