{
  "type": "Feature",
  "properties": {
    "iso:country":"IN",
    "ks:ks_name":"Parvateshwar",
    "ks:ks_pop":50,
    "ks:ks_type":"HABITATION",
    "name:eng_x_preferred":[
        "Parvateshwar"
    ],
    "wof:name":"Parvateshwar",
    "wof:placetype":"locality",
    "wof:population":50
},
  "geometry": {"coordinates":[74.46496,14.561615],"type":"Point"}
}