{
  "type": "Feature",
  "properties": {
    "iso:country":"IN",
    "ks:ks_name":"Charangpara 1",
    "ks:ks_pop":1056,
    "ks:ks_type":"HABITATION",
    "name:eng_x_preferred":[
        "Charangpara 1"
    ],
    "wof:name":"Charangpara 1",
    "wof:placetype":"locality",
    "wof:population":1056
},
  "geometry": {"coordinates":[91.67256399999999,26.466038],"type":"Point"}
}