{
  "type": "Feature",
  "properties": {
    "gn:admin1_code":"34.0",
    "gn:admin2_code":"227.0",
    "gn:asciiname":"Khawa",
    "gn:country_code":"IN",
    "gn:dem":48,
    "gn:feature_class":"P",
    "gn:feature_code":"PPL",
    "gn:name":"Kh\u0101wa",
    "gn:population":0,
    "gn:timezone":"Asia/Kolkata",
    "iso:country":"IN",
    "ks:ks_alt_nam":"Kh\u0101wa",
    "ks:ks_name":"Khawa",
    "ks:ks_pop":1808,
    "ks:ks_type":"VILLAGE",
    "ks:ks_uagg_main":0,
    "name:bih_x_preferred":[
        "\u0916\u093e\u0935\u093e"
    ],
    "name:ceb_x_preferred":[
        "Khawa"
    ],
    "name:eng_x_preferred":[
        "Khawa"
    ],
    "name:eng_x_variant":[
        "Kh\u0101wa"
    ],
    "name:mai_x_preferred":[
        "\u0916\u093e\u0935\u093e"
    ],
    "name:msa_x_preferred":[
        "Khawa"
    ],
    "name:nep_x_preferred":[
        "\u0916\u093e\u0935\u093e"
    ],
    "name:new_x_preferred":[
        "\u0916\u0935\u093e"
    ],
    "name:pol_x_preferred":[
        "Khawa"
    ],
    "wof:name":"Khawa",
    "wof:placetype":"neighbourhood",
    "wof:population":1808
},
  "geometry": {"coordinates":[86.30709,25.28319],"type":"Point"}
}