{
  "type": "Feature",
  "properties": {
    "iso:country":"IN",
    "ks:ks_name":"Jj Nagar",
    "ks:ks_pop":257,
    "ks:ks_type":"HABITATION",
    "ks:ks_uagg_main":0,
    "name:eng_x_preferred":[
        "Jj Nagar"
    ],
    "wof:name":"Jj Nagar",
    "wof:placetype":"neighbourhood",
    "wof:population":257
},
  "geometry": {"coordinates":[78.62539,12.466187],"type":"Point"}
}