{
  "type": "Feature",
  "properties": {
    "iso:country":"IN",
    "ks:ks_name":"Seranur",
    "ks:ks_pop":762,
    "ks:ks_type":"HABITATION",
    "name:eng_x_preferred":[
        "Seranur"
    ],
    "wof:name":"Seranur",
    "wof:placetype":"locality",
    "wof:population":762
},
  "geometry": {"coordinates":[79.390086,12.200992],"type":"Point"}
}