{
  "type": "Feature",
  "properties": {
    "gn:admin1_code":"24",
    "gn:admin2_code":"111.0",
    "gn:asciiname":"Sihot Bari",
    "gn:country_code":"IN",
    "gn:dem":387,
    "gn:feature_class":"P",
    "gn:feature_code":"PPL",
    "gn:name":"Sihot Bari",
    "gn:population":0,
    "gn:timezone":"Asia/Kolkata",
    "iso:country":"IN",
    "name:und_x_variant":[
        "Sehot"
    ],
    "wof:name":"Sihot Bari",
    "wof:placetype":"locality"
},
  "geometry": {"coordinates":[74.92013,27.55932],"type":"Point"}
}