{
  "type": "Feature",
  "properties": {
    "gn:admin1_code":"12.0",
    "gn:admin2_code":"011",
    "gn:asciiname":"Dhokri",
    "gn:country_code":"IN",
    "gn:dem":2511,
    "gn:feature_class":"P",
    "gn:feature_code":"PPL",
    "gn:name":"Dhokri",
    "gn:population":0,
    "gn:timezone":"Asia/Kolkata",
    "iso:country":"IN",
    "wof:name":"Dhokri",
    "wof:placetype":"locality"
},
  "geometry": {"coordinates":[74.89244000000002,34.32331],"type":"Point"}
}