{
  "type": "Feature",
  "properties": {
    "iso:country":"IN",
    "ks:ks_name":"Charsui",
    "ks:ks_pop":95,
    "ks:ks_type":"HABITATION",
    "name:eng_x_preferred":[
        "Charsui"
    ],
    "wof:name":"Charsui",
    "wof:placetype":"locality",
    "wof:population":95
},
  "geometry": {"coordinates":[85.585249,22.844537],"type":"Point"}
}