{
  "type": "Feature",
  "properties": {
    "gn:admin1_code":"0.0",
    "gn:asciiname":"Bhaisalotan",
    "gn:cc2":"IN",
    "gn:country_code":"IN",
    "gn:dem":115,
    "gn:feature_class":"P",
    "gn:feature_code":"PPL",
    "gn:name":"Bhais\u0101lotan",
    "gn:population":0,
    "gn:timezone":"Asia/Kolkata",
    "iso:country":"IN",
    "name:und_x_variant":[
        "Bhaisolaton",
        "Bhais\u0101lotan"
    ],
    "wof:name":"Bhaisalotan",
    "wof:placetype":"locality"
},
  "geometry": {"coordinates":[83.91667,27.45],"type":"Point"}
}