{
  "type": "Feature",
  "properties": {
    "gn:admin1_code":"36.0",
    "gn:admin2_code":"156.0",
    "gn:asciiname":"Dalanpur",
    "gn:country_code":"IN",
    "gn:dem":116,
    "gn:feature_class":"P",
    "gn:feature_code":"PPL",
    "gn:name":"Dalanpur",
    "gn:population":0,
    "gn:timezone":"Asia/Kolkata",
    "iso:country":"IN",
    "wof:name":"Dalanpur",
    "wof:placetype":"locality"
},
  "geometry": {"coordinates":[80.42017,26.47954],"type":"Point"}
}