{
  "type": "Feature",
  "properties": {
    "gn:admin1_code":"10",
    "gn:admin2_code":"74.0",
    "gn:asciiname":"Samana",
    "gn:country_code":"IN",
    "gn:dem":259,
    "gn:feature_class":"P",
    "gn:feature_code":"PPL",
    "gn:name":"Sam\u0101na",
    "gn:population":0,
    "gn:timezone":"Asia/Kolkata",
    "iso:country":"IN",
    "name:bpy_x_preferred":[
        "\u09b8\u09be\u09ae\u09be\u09a8\u09be"
    ],
    "name:cat_x_preferred":[
        "Samana"
    ],
    "name:ceb_x_preferred":[
        "Samana"
    ],
    "name:deu_x_preferred":[
        "Samana"
    ],
    "name:ell_x_preferred":[
        "\u03a3\u03b1\u03bc\u03b1\u03bd\u03ac"
    ],
    "name:fas_x_preferred":[
        "\u0633\u0627\u0645\u0627\u0646\u0627"
    ],
    "name:fra_x_preferred":[
        "Samana"
    ],
    "name:ita_x_preferred":[
        "Samana"
    ],
    "name:nld_x_preferred":[
        "Samana"
    ],
    "name:rus_x_preferred":[
        "\u0421\u0430\u043c\u0430\u043d\u0430"
    ],
    "name:spa_x_preferred":[
        "Samana"
    ],
    "name:swe_x_preferred":[
        "Samana"
    ],
    "name:ukr_x_preferred":[
        "\u0421\u0430\u043c\u0430\u043d\u0430"
    ],
    "wof:name":"Samana",
    "wof:placetype":"locality"
},
  "geometry": {"coordinates":[76.91105,29.90404],"type":"Point"}
}