{
  "type": "Feature",
  "properties": {
    "gn:admin1_code":"34.0",
    "gn:admin2_code":"223.0",
    "gn:asciiname":"Saharbani",
    "gn:country_code":"IN",
    "gn:dem":42,
    "gn:feature_class":"P",
    "gn:feature_code":"PPL",
    "gn:name":"Saharbani",
    "gn:population":0,
    "gn:timezone":"Asia/Kolkata",
    "iso:country":"IN",
    "ks:ks_name":"Saharbani",
    "ks:ks_pop":7541,
    "ks:ks_type":"VILLAGE",
    "ks:ks_uagg_main":0,
    "name:eng_x_preferred":[
        "Saharbani"
    ],
    "wof:name":"Saharbani",
    "wof:placetype":"neighbourhood",
    "wof:population":7541
},
  "geometry": {"coordinates":[86.409997,25.720068],"type":"Point"}
}