{
  "type": "Feature",
  "properties": {
    "iso:country":"IN",
    "ks:ks_name":"Bhuidharwa",
    "ks:ks_pop":851,
    "ks:ks_type":"VILLAGE",
    "name:eng_x_preferred":[
        "Bhuidharwa"
    ],
    "wof:name":"Bhuidharwa",
    "wof:placetype":"locality",
    "wof:population":851
},
  "geometry": {"coordinates":[82.63076,24.6435],"type":"Point"}
}