{
  "type": "Feature",
  "properties": {
    "gn:admin1_code":"35.0",
    "gn:admin2_code":"422.0",
    "gn:asciiname":"Banoli",
    "gn:country_code":"IN",
    "gn:dem":201,
    "gn:feature_class":"P",
    "gn:feature_code":"PPL",
    "gn:name":"B\u0101noli",
    "gn:population":0,
    "gn:timezone":"Asia/Kolkata",
    "iso:country":"IN",
    "wof:name":"Banoli",
    "wof:placetype":"locality"
},
  "geometry": {"coordinates":[78.44499,25.78629],"type":"Point"}
}