{
  "type": "Feature",
  "properties": {
    "iso:country":"IN",
    "ks:ks_name":"Baniya Gaon",
    "ks:ks_pop":200,
    "ks:ks_type":"VILLAGE",
    "ks:ks_uagg_main":0,
    "name:eng_x_preferred":[
        "Baniya Gaon"
    ],
    "wof:name":"Baniya Gaon",
    "wof:placetype":"neighbourhood",
    "wof:population":200
},
  "geometry": {"coordinates":[78.732663,30.059956],"type":"Point"}
}