{
  "type": "Feature",
  "properties": {
    "gn:admin1_code":"9.0",
    "gn:admin2_code":"488.0",
    "gn:asciiname":"Keswan",
    "gn:country_code":"IN",
    "gn:dem":9,
    "gn:feature_class":"P",
    "gn:feature_code":"PPL",
    "gn:name":"Keswan",
    "gn:population":0,
    "gn:timezone":"Asia/Kolkata",
    "iso:country":"IN",
    "wof:name":"Keswan",
    "wof:placetype":"locality"
},
  "geometry": {"coordinates":[72.71503,21.85485],"type":"Point"}
}