{
  "type": "Feature",
  "properties": {
    "gn:admin1_code":"11.0",
    "gn:admin2_code":"025",
    "gn:asciiname":"Kiato",
    "gn:country_code":"IN",
    "gn:dem":3958,
    "gn:feature_class":"P",
    "gn:feature_code":"PPL",
    "gn:name":"Kiato",
    "gn:population":0,
    "gn:timezone":"Asia/Kolkata",
    "iso:country":"IN",
    "name:ara_x_preferred":[
        "\u0643\u064a\u0627\u062a\u0648"
    ],
    "name:ceb_x_preferred":[
        "Ki\u00e1to"
    ],
    "name:deu_x_preferred":[
        "Kiato"
    ],
    "name:ell_x_preferred":[
        "\u039a\u03b9\u03ac\u03c4\u03bf"
    ],
    "name:fin_x_preferred":[
        "Ki\u00e1to"
    ],
    "name:nno_x_preferred":[
        "Ki\u00e1to"
    ],
    "name:ron_x_preferred":[
        "Kiato"
    ],
    "name:rus_x_preferred":[
        "\u041a\u044c\u044f\u0442\u043e\u043d"
    ],
    "name:sqi_x_preferred":[
        "Qato"
    ],
    "name:srp_x_preferred":[
        "\u041a\u0438\u0458\u0430\u0442\u043e"
    ],
    "name:swe_x_preferred":[
        "Ki\u00e1to"
    ],
    "wof:name":"Kiato",
    "wof:placetype":"locality"
},
  "geometry": {"coordinates":[77.89899,32.44456],"type":"Point"}
}