{
  "type": "Feature",
  "properties": {
    "gn:admin1_code":"11.0",
    "gn:admin2_code":"025",
    "gn:asciiname":"Kiato",
    "gn:country_code":"IN",
    "gn:dem":3958,
    "gn:feature_class":"P",
    "gn:feature_code":"PPL",
    "gn:name":"Kiato",
    "gn:population":0,
    "gn:timezone":"Asia/Kolkata",
    "iso:country":"IN",
    "wof:name":"Kiato",
    "wof:placetype":"locality"
},
  "geometry": {"coordinates":[77.89899,32.44456],"type":"Point"}
}