{
  "type": "Feature",
  "properties": {
    "iso:country":"IN",
    "ks:ks_name":"Shyampur",
    "ks:ks_pop":14,
    "ks:ks_type":"VILLAGE",
    "name:eng_x_preferred":[
        "Shyampur"
    ],
    "wof:name":"Shyampur",
    "wof:placetype":"locality",
    "wof:population":14
},
  "geometry": {"coordinates":[86.42341,23.47538],"type":"Point"}
}