{
  "type": "Feature",
  "properties": {
    "iso:country":"IN",
    "ks:ks_name":"Venugopalapuram",
    "ks:ks_pop":145,
    "ks:ks_type":"HABITATION",
    "name:eng_x_preferred":[
        "Venugopalapuram"
    ],
    "wof:name":"Venugopalapuram",
    "wof:placetype":"locality",
    "wof:population":145
},
  "geometry": {"coordinates":[78.50577699999999,12.951423],"type":"Point"}
}