{
  "type": "Feature",
  "properties": {
    "gn:admin1_code":"23.0",
    "gn:admin2_code":"50.0",
    "gn:asciiname":"Bahojoke",
    "gn:country_code":"IN",
    "gn:dem":195,
    "gn:feature_class":"P",
    "gn:feature_code":"PPL",
    "gn:name":"Bahojoke",
    "gn:population":0,
    "gn:timezone":"Asia/Kolkata",
    "iso:country":"IN",
    "ks:ks_name":"Bhojoke",
    "ks:ks_pop":48,
    "ks:ks_type":"VILLAGE",
    "name:eng_x_preferred":[
        "Bhojoke"
    ],
    "name:eng_x_variant":[
        "Bahojoke"
    ],
    "wof:name":"Bhojoke",
    "wof:placetype":"locality",
    "wof:population":48
},
  "geometry": {"coordinates":[74.766193,31.134496],"type":"Point"}
}