{
  "type": "Feature",
  "properties": {
    "iso:country":"IN",
    "ks:ks_name":"Valu Thanda",
    "ks:ks_pop":147,
    "ks:ks_type":"HABITATION",
    "name:eng_x_preferred":[
        "Valu Thanda"
    ],
    "wof:name":"Valu Thanda",
    "wof:placetype":"locality",
    "wof:population":147
},
  "geometry": {"coordinates":[77.64762899999999,18.141457],"type":"Point"}
}