{
  "type": "Feature",
  "properties": {
    "gn:admin1_code":"36",
    "gn:admin2_code":"159.0",
    "gn:asciiname":"Harharpur",
    "gn:country_code":"IN",
    "gn:dem":150,
    "gn:feature_class":"P",
    "gn:feature_code":"PPL",
    "gn:name":"Harharpur",
    "gn:population":0,
    "gn:timezone":"Asia/Kolkata",
    "iso:country":"IN",
    "ks:ks_name":"Harharpur",
    "ks:ks_type":"VILLAGE",
    "name:eng_x_preferred":[
        "Harharpur"
    ],
    "wof:name":"Harharpur",
    "wof:placetype":"locality"
},
  "geometry": {"coordinates":[79.550803,27.33212],"type":"Point"}
}