{
  "type": "Feature",
  "properties": {
    "gn:admin1_code":"36.0",
    "gn:admin2_code":"134.0",
    "gn:asciiname":"Mian Bhaipur",
    "gn:country_code":"IN",
    "gn:dem":229,
    "gn:feature_class":"P",
    "gn:feature_code":"PPL",
    "gn:name":"Mi\u0101n Bhaipur",
    "gn:population":0,
    "gn:timezone":"Asia/Kolkata",
    "iso:country":"IN",
    "ks:ks_alt_nam":"Mi\u0101n Bhaipur",
    "ks:ks_name":"Mian Bhaipur",
    "ks:ks_type":"VILLAGE",
    "name:eng_x_preferred":[
        "Mian Bhaipur"
    ],
    "name:eng_x_variant":[
        "Mi\u0101n Bhaipur"
    ],
    "wof:name":"Mian Bhaipur",
    "wof:placetype":"locality"
},
  "geometry": {"coordinates":[78.6022,29.430203],"type":"Point"}
}