{
  "type": "Feature",
  "properties": {
    "gn:admin1_code":"34.0",
    "gn:admin2_code":"239.0",
    "gn:asciiname":"Muhammadpur",
    "gn:country_code":"IN",
    "gn:dem":74,
    "gn:feature_class":"P",
    "gn:feature_code":"PPL",
    "gn:name":"Muhammadpur",
    "gn:population":0,
    "gn:timezone":"Asia/Kolkata",
    "iso:country":"IN",
    "ks:ks_name":"Mohammatpur",
    "ks:ks_pop":235,
    "ks:ks_type":"HABITATION",
    "name:eng_x_preferred":[
        "Mohammatpur"
    ],
    "name:eng_x_variant":[
        "Muhammadpur"
    ],
    "wof:name":"Mohammatpur",
    "wof:placetype":"locality",
    "wof:population":235
},
  "geometry": {"coordinates":[85.06215899999999,25.10927],"type":"Point"}
}