{
  "type": "Feature",
  "properties": {
    "iso:country":"IN",
    "ks:ks_name":"Khaspara",
    "ks:ks_pop":340,
    "ks:ks_type":"VILLAGE",
    "ks:ks_uagg_main":0,
    "name:eng_x_preferred":[
        "Khaspara"
    ],
    "wof:name":"Khaspara",
    "wof:placetype":"neighbourhood",
    "wof:population":340
},
  "geometry": {"coordinates":[88.612914,25.36909],"type":"Point"}
}