{
  "type": "Feature",
  "properties": {
    "iso:country":"IN",
    "ks:ks_name":"Udaipur Purbi",
    "ks:ks_pop":623,
    "ks:ks_type":"HABITATION",
    "name:eng_x_preferred":[
        "Udaipur Purbi"
    ],
    "wof:name":"Udaipur Purbi",
    "wof:placetype":"locality",
    "wof:population":623
},
  "geometry": {"coordinates":[80.80669899999999,27.207994],"type":"Point"}
}