{
  "type": "Feature",
  "properties": {
    "iso:country":"IN",
    "ks:ks_name":"Patanabali Patna",
    "ks:ks_pop":455,
    "ks:ks_type":"HABITATION",
    "name:eng_x_preferred":[
        "Patanabali Patna"
    ],
    "wof:name":"Patanabali Patna",
    "wof:placetype":"locality",
    "wof:population":455
},
  "geometry": {"coordinates":[85.501531,20.164928],"type":"Point"}
}