{
  "type": "Feature",
  "properties": {
    "iso:country":"IN",
    "ks:ks_name":"Bahadiha",
    "ks:ks_pop":459,
    "ks:ks_type":"VILLAGE",
    "name:eng_x_preferred":[
        "Bahadiha"
    ],
    "wof:name":"Bahadiha",
    "wof:placetype":"locality",
    "wof:population":459
},
  "geometry": {"coordinates":[86.692936,20.771489],"type":"Point"}
}