{
  "type": "Feature",
  "properties": {
    "iso:country":"IN",
    "ks:ks_name":"Rathava Faliya",
    "ks:ks_pop":418,
    "ks:ks_type":"HABITATION",
    "name:eng_x_preferred":[
        "Rathava Faliya"
    ],
    "wof:name":"Rathava Faliya",
    "wof:placetype":"locality",
    "wof:population":418
},
  "geometry": {"coordinates":[73.61886699999999,22.72155],"type":"Point"}
}