{
  "type": "Feature",
  "properties": {
    "gn:admin1_code":"36",
    "gn:admin2_code":"191.0",
    "gn:asciiname":"Mathia Zabti Mafi",
    "gn:country_code":"IN",
    "gn:dem":88,
    "gn:feature_class":"P",
    "gn:feature_code":"PPL",
    "gn:name":"Mathia Zabti M\u0101fi",
    "gn:population":0,
    "gn:timezone":"Asia/Kolkata",
    "iso:country":"IN",
    "wof:name":"Mathia Zabti Mafi",
    "wof:placetype":"neighbourhood"
},
  "geometry": {"coordinates":[82.9606,26.29445],"type":"Point"}
}