{
  "type": "Feature",
  "properties": {
    "iso:country":"IN",
    "ks:ks_name":"Chitawan Bigha",
    "ks:ks_pop":286,
    "ks:ks_type":"HABITATION",
    "name:eng_x_preferred":[
        "Chitawan Bigha"
    ],
    "wof:name":"Chitawan Bigha",
    "wof:placetype":"locality",
    "wof:population":286
},
  "geometry": {"coordinates":[84.765033,24.949585],"type":"Point"}
}