{
  "type": "Feature",
  "properties": {
    "gn:admin1_code":"11",
    "gn:admin2_code":"23.0",
    "gn:asciiname":"Ghari",
    "gn:country_code":"IN",
    "gn:dem":1295,
    "gn:feature_class":"P",
    "gn:feature_code":"PPL",
    "gn:name":"Gh\u0101ri",
    "gn:population":0,
    "gn:timezone":"Asia/Kolkata",
    "iso:country":"IN",
    "name:ceb_x_preferred":[
        "Ghari"
    ],
    "wof:name":"Ghari",
    "wof:placetype":"locality"
},
  "geometry": {"coordinates":[76.01549,32.70691],"type":"Point"}
}