{
  "type": "Feature",
  "properties": {
    "gn:admin1_code":"36",
    "gn:admin2_code":"142.0",
    "gn:asciiname":"Karanpur Khurd",
    "gn:country_code":"IN",
    "gn:dem":198,
    "gn:feature_class":"P",
    "gn:feature_code":"PPL",
    "gn:name":"Karanp\u016br Khurd",
    "gn:population":0,
    "gn:timezone":"Asia/Kolkata",
    "iso:country":"IN",
    "wof:name":"Karanpur Khurd",
    "wof:placetype":"locality"
},
  "geometry": {"coordinates":[78.15353,28.37011],"type":"Point"}
}