{
  "type": "Feature",
  "properties": {
    "iso:country":"IN",
    "ks:ks_name":"Rampur M.Silaich",
    "ks:ks_pop":0,
    "ks:ks_type":"VILLAGE",
    "name:eng_x_preferred":[
        "Rampur M.Silaich"
    ],
    "wof:name":"Rampur M.Silaich",
    "wof:placetype":"locality",
    "wof:population":0
},
  "geometry": {"coordinates":[83.801964,25.652248],"type":"Point"}
}