{
  "type": "Feature",
  "properties": {
    "iso:country":"IN",
    "ks:ks_alt_nam":"Avalachi wadi",
    "ks:ks_name":"Avalachi Wadi",
    "ks:ks_pop":38,
    "ks:ks_type":"HABITATION",
    "name:eng_x_preferred":[
        "Avalachi Wadi"
    ],
    "wof:name":"Avalachi Wadi",
    "wof:placetype":"locality",
    "wof:population":38
},
  "geometry": {"coordinates":[73.312253,16.731329],"type":"Point"}
}