{
  "type": "Feature",
  "properties": {
    "iso:country":"IN",
    "ks:ks_name":"Pandavwadi",
    "ks:ks_pop":396,
    "ks:ks_type":"HABITATION",
    "name:eng_x_preferred":[
        "Pandavwadi"
    ],
    "wof:name":"Pandavwadi",
    "wof:placetype":"locality",
    "wof:population":396
},
  "geometry": {"coordinates":[73.58727500000001,17.255858],"type":"Point"}
}