{
  "type": "Feature",
  "properties": {
    "gn:admin1_code":"34.0",
    "gn:admin2_code":"203.0",
    "gn:asciiname":"Dharhwa",
    "gn:country_code":"IN",
    "gn:dem":85,
    "gn:feature_class":"P",
    "gn:feature_code":"PPL",
    "gn:name":"Dharhwa",
    "gn:population":0,
    "gn:timezone":"Asia/Kolkata",
    "iso:country":"IN",
    "ks:ks_name":"Dharhwa",
    "ks:ks_pop":3021,
    "ks:ks_type":"VILLAGE",
    "name:eng_x_preferred":[
        "Dharhwa"
    ],
    "wof:name":"Dharhwa",
    "wof:placetype":"locality",
    "wof:population":3021
},
  "geometry": {"coordinates":[84.289232,26.916865],"type":"Point"}
}