{
  "type": "Feature",
  "properties": {
    "iso:country":"IN",
    "ks:ks_name":"Darridih",
    "ks:ks_pop":123,
    "ks:ks_type":"HABITATION",
    "name:eng_x_preferred":[
        "Darridih"
    ],
    "wof:name":"Darridih",
    "wof:placetype":"locality",
    "wof:population":123
},
  "geometry": {"coordinates":[83.04594899999999,22.218],"type":"Point"}
}