{
  "type": "Feature",
  "properties": {
    "gn:admin1_code":"36",
    "gn:admin2_code":"191.0",
    "gn:asciiname":"Bhuapur",
    "gn:country_code":"IN",
    "gn:dem":84,
    "gn:feature_class":"P",
    "gn:feature_code":"PPL",
    "gn:name":"Bh\u016b\u0101pur",
    "gn:population":0,
    "gn:timezone":"Asia/Kolkata",
    "iso:country":"IN",
    "name:ben_x_preferred":[
        "\u09ad\u09c2\u099e\u09be\u09aa\u09c1\u09b0"
    ],
    "name:rus_x_preferred":[
        "\u0411\u0445\u0443\u0430\u043f\u0443\u0440"
    ],
    "wof:name":"Bhuapur",
    "wof:placetype":"locality"
},
  "geometry": {"coordinates":[83.03482,26.30325],"type":"Point"}
}