{
  "type": "Feature",
  "properties": {
    "gn:admin1_code":"25.0",
    "gn:admin2_code":"620.0",
    "gn:asciiname":"Kundur",
    "gn:country_code":"IN",
    "gn:dem":38,
    "gn:feature_class":"P",
    "gn:feature_code":"PPL",
    "gn:name":"Kund\u016br",
    "gn:population":0,
    "gn:timezone":"Asia/Kolkata",
    "iso:country":"IN",
    "name:ceb_x_preferred":[
        "Kundur"
    ],
    "name:nld_x_preferred":[
        "Kundur"
    ],
    "name:swe_x_preferred":[
        "Kundur"
    ],
    "wof:name":"Kundur",
    "wof:placetype":"locality"
},
  "geometry": {"coordinates":[79.19596999999997,10.82787],"type":"Point"}
}