{
  "type": "Feature",
  "properties": {
    "iso:country":"IN",
    "ks:ks_name":"Jadupur",
    "ks:ks_pop":68,
    "ks:ks_type":"VILLAGE",
    "name:eng_x_preferred":[
        "Jadupur"
    ],
    "wof:name":"Jadupur",
    "wof:placetype":"locality",
    "wof:population":68
},
  "geometry": {"coordinates":[85.741893,20.762696],"type":"Point"}
}