{
  "type": "Feature",
  "properties": {
    "iso:country":"IN",
    "ks:ks_name":"Jogimatha",
    "ks:ks_pop":2,
    "ks:ks_type":"VILLAGE",
    "name:eng_x_preferred":[
        "Jogimatha"
    ],
    "wof:name":"Jogimatha",
    "wof:placetype":"locality",
    "wof:population":2
},
  "geometry": {"coordinates":[84.19250700000001,20.574802],"type":"Point"}
}