{
  "type": "Feature",
  "properties": {
    "iso:country":"IN",
    "ks:ks_name":"Pipaliya",
    "ks:ks_pop":195,
    "ks:ks_type":"HABITATION",
    "name:eng_x_preferred":[
        "Pipaliya"
    ],
    "wof:name":"Pipaliya",
    "wof:placetype":"locality",
    "wof:population":195
},
  "geometry": {"coordinates":[78.05087,23.484709],"type":"Point"}
}