{
  "type": "Feature",
  "properties": {
    "iso:country":"IN",
    "ks:ks_name":"Ng.barah N.birsahai",
    "ks:ks_pop":469,
    "ks:ks_type":"HABITATION",
    "name:eng_x_preferred":[
        "Ng.barah N.birsahai"
    ],
    "wof:name":"Ng.barah N.birsahai",
    "wof:placetype":"locality",
    "wof:population":469
},
  "geometry": {"coordinates":[78.71014,27.87968],"type":"Point"}
}