{
  "type": "Feature",
  "properties": {
    "iso:country":"IN",
    "ks:ks_alt_nam":"Damcherra FV",
    "ks:ks_name":"Damcherra Fv",
    "ks:ks_pop":3101,
    "ks:ks_type":"HABITATION",
    "name:eng_x_preferred":[
        "Damcherra Fv"
    ],
    "wof:name":"Damcherra Fv",
    "wof:placetype":"locality",
    "wof:population":3101
},
  "geometry": {"coordinates":[92.47079100000001,24.225098],"type":"Point"}
}