{
  "type": "Feature",
  "properties": {
    "iso:country":"IN",
    "ks:ks_name":"Shivratan Singh",
    "ks:ks_pop":288,
    "ks:ks_type":"HABITATION",
    "name:eng_x_preferred":[
        "Shivratan Singh"
    ],
    "wof:name":"Shivratan Singh",
    "wof:placetype":"locality",
    "wof:population":288
},
  "geometry": {"coordinates":[81.602059,26.582053],"type":"Point"}
}