{
  "type": "Feature",
  "properties": {
    "iso:country":"IN",
    "ks:ks_name":"Bhavanimandir",
    "ks:ks_pop":86,
    "ks:ks_type":"HABITATION",
    "name:eng_x_preferred":[
        "Bhavanimandir"
    ],
    "wof:name":"Bhavanimandir",
    "wof:placetype":"locality",
    "wof:population":86
},
  "geometry": {"coordinates":[73.752008,15.891648],"type":"Point"}
}