{
  "type": "Feature",
  "properties": {
    "iso:country":"IN",
    "ks:ks_name":"Batabari",
    "ks:ks_pop":1223,
    "ks:ks_type":"VILLAGE",
    "name:eng_x_preferred":[
        "Batabari"
    ],
    "wof:name":"Batabari",
    "wof:placetype":"locality",
    "wof:population":1223
},
  "geometry": {"coordinates":[91.805661,23.78332],"type":"Point"}
}