{
  "type": "Feature",
  "properties": {
    "iso:country":"IN",
    "ks:ks_name":"Chakundamunda",
    "ks:ks_pop":365,
    "ks:ks_type":"VILLAGE",
    "ks:ks_uagg_main":0,
    "name:eng_x_preferred":[
        "Chakundamunda"
    ],
    "wof:name":"Chakundamunda",
    "wof:placetype":"neighbourhood",
    "wof:population":365
},
  "geometry": {"coordinates":[84.686469,20.955532],"type":"Point"}
}