{
  "type": "Feature",
  "properties": {
    "gn:admin1_code":"36",
    "gn:admin2_code":"191.0",
    "gn:asciiname":"Bamhanpur",
    "gn:country_code":"IN",
    "gn:dem":82,
    "gn:feature_class":"P",
    "gn:feature_code":"PPL",
    "gn:name":"Bamhanpur",
    "gn:population":0,
    "gn:timezone":"Asia/Kolkata",
    "iso:country":"IN",
    "ks:ks_name":"Babhanpur",
    "ks:ks_pop":60,
    "ks:ks_type":"VILLAGE",
    "name:eng_x_preferred":[
        "Babhanpur"
    ],
    "name:eng_x_variant":[
        "Bamhanpur"
    ],
    "wof:name":"Babhanpur",
    "wof:placetype":"locality",
    "wof:population":60
},
  "geometry": {"coordinates":[83.14263800000001,26.215466],"type":"Point"}
}