{
  "type": "Feature",
  "properties": {
    "iso:country":"IN",
    "ks:ks_name":"Kukkaje",
    "ks:ks_pop":285,
    "ks:ks_type":"HABITATION",
    "name:eng_x_preferred":[
        "Kukkaje"
    ],
    "wof:name":"Kukkaje",
    "wof:placetype":"locality",
    "wof:population":285
},
  "geometry": {"coordinates":[75.40299899999999,12.994906],"type":"Point"}
}