{
  "type": "Feature",
  "properties": {
    "iso:country":"IN",
    "ks:ks_name":"Murat Bigha",
    "ks:ks_pop":166,
    "ks:ks_type":"HABITATION",
    "name:eng_x_preferred":[
        "Murat Bigha"
    ],
    "wof:name":"Murat Bigha",
    "wof:placetype":"locality",
    "wof:population":166
},
  "geometry": {"coordinates":[85.21276899999999,25.296841],"type":"Point"}
}