{
  "type": "Feature",
  "properties": {
    "gn:admin1_code":"36.0",
    "gn:admin2_code":"137.0",
    "gn:asciiname":"Qasimpur Jat",
    "gn:country_code":"IN",
    "gn:dem":205,
    "gn:feature_class":"P",
    "gn:feature_code":"PPL",
    "gn:name":"Q\u0101simpur Jat",
    "gn:population":0,
    "gn:timezone":"Asia/Kolkata",
    "iso:country":"IN",
    "ks:ks_alt_nam":"Q\u0101simpur Jat",
    "ks:ks_name":"Qasimpur Jat",
    "ks:ks_pop":482,
    "ks:ks_type":"VILLAGE",
    "name:eng_x_preferred":[
        "Qasimpur Jat"
    ],
    "name:eng_x_variant":[
        "Q\u0101simpur Jat"
    ],
    "wof:name":"Qasimpur Jat",
    "wof:placetype":"locality",
    "wof:population":482
},
  "geometry": {"coordinates":[78.607524,28.865012],"type":"Point"}
}