{
  "type": "Feature",
  "properties": {
    "iso:country":"IN",
    "ks:ks_name":"Munkinajeddu",
    "ks:ks_pop":140,
    "ks:ks_type":"HABITATION",
    "name:eng_x_preferred":[
        "Munkinajeddu"
    ],
    "wof:name":"Munkinajeddu",
    "wof:placetype":"locality",
    "wof:population":140
},
  "geometry": {"coordinates":[74.810329,13.421423],"type":"Point"}
}