{
  "type": "Feature",
  "properties": {
    "gn:admin1_code":"37",
    "gn:admin2_code":"406.0",
    "gn:asciiname":"Aurapani",
    "gn:country_code":"IN",
    "gn:dem":549,
    "gn:feature_class":"P",
    "gn:feature_code":"PPL",
    "gn:name":"Aur\u0101p\u0101ni",
    "gn:population":0,
    "gn:timezone":"Asia/Kolkata",
    "iso:country":"IN",
    "ks:ks_alt_nam":"Aur\u0101p\u0101ni",
    "ks:ks_name":"Aurapani",
    "ks:ks_type":"VILLAGE",
    "name:eng_x_preferred":[
        "Aurapani"
    ],
    "name:eng_x_variant":[
        "Aur\u0101p\u0101ni"
    ],
    "wof:name":"Aurapani",
    "wof:placetype":"locality"
},
  "geometry": {"coordinates":[81.517349,22.495312],"type":"Point"}
}