{
  "type": "Feature",
  "properties": {
    "iso:country":"IN",
    "ks:ks_name":"Polamguda",
    "ks:ks_pop":31,
    "ks:ks_type":"HABITATION",
    "name:eng_x_preferred":[
        "Polamguda"
    ],
    "wof:name":"Polamguda",
    "wof:placetype":"locality",
    "wof:population":31
},
  "geometry": {"coordinates":[83.662662,18.863796],"type":"Point"}
}