{
  "type": "Feature",
  "properties": {
    "iso:country":"IN",
    "ks:ks_name":"Mughal Pur Khurd",
    "ks:ks_pop":512,
    "ks:ks_type":"HABITATION",
    "name:eng_x_preferred":[
        "Mughal Pur Khurd"
    ],
    "wof:name":"Mughal Pur Khurd",
    "wof:placetype":"locality",
    "wof:population":512
},
  "geometry": {"coordinates":[80.509327,26.482798],"type":"Point"}
}