{
  "type": "Feature",
  "properties": {
    "iso:country":"IN",
    "ks:ks_name":"Kottukkal",
    "ks:ks_pop":73,
    "ks:ks_type":"HABITATION",
    "name:eng_x_preferred":[
        "Kottukkal"
    ],
    "wof:name":"Kottukkal",
    "wof:placetype":"locality",
    "wof:population":73
},
  "geometry": {"coordinates":[76.847883,11.386505],"type":"Point"}
}