{
  "type": "Feature",
  "properties": {
    "iso:country":"IN",
    "ks:ks_name":"Aranthanadka",
    "ks:ks_pop":336,
    "ks:ks_type":"HABITATION",
    "name:eng_x_preferred":[
        "Aranthanadka"
    ],
    "wof:name":"Aranthanadka",
    "wof:placetype":"locality",
    "wof:population":336
},
  "geometry": {"coordinates":[75.214251,12.672141],"type":"Point"}
}