{
  "type": "Feature",
  "properties": {
    "iso:country":"IN",
    "ks:ks_name":"Nau Gaon",
    "ks:ks_pop":76,
    "ks:ks_type":"VILLAGE",
    "name:eng_x_preferred":[
        "Nau Gaon"
    ],
    "wof:name":"Nau Gaon",
    "wof:placetype":"locality",
    "wof:population":76
},
  "geometry": {"coordinates":[78.65951800000001,30.008605],"type":"Point"}
}