{
  "type": "Feature",
  "properties": {
    "iso:country":"IN",
    "ks:ks_name":"Bhehan Beri",
    "ks:ks_pop":611,
    "ks:ks_type":"VILLAGE",
    "name:eng_x_preferred":[
        "Bhehan Beri"
    ],
    "wof:name":"Bhehan Beri",
    "wof:placetype":"locality",
    "wof:population":611
},
  "geometry": {"coordinates":[73.668263,23.750522],"type":"Point"}
}