{
  "type": "Feature",
  "properties": {
    "iso:country":"IN",
    "ks:ks_alt_nam":"NAWATOLI",
    "ks:ks_name":"Nawatoli",
    "ks:ks_pop":161,
    "ks:ks_type":"HABITATION",
    "name:eng_x_preferred":[
        "Nawatoli"
    ],
    "wof:name":"Nawatoli",
    "wof:placetype":"locality",
    "wof:population":161
},
  "geometry": {"coordinates":[83.914642,22.765008],"type":"Point"}
}