{
  "type": "Feature",
  "properties": {
    "gn:admin1_code":"19.0",
    "gn:admin2_code":"563.0",
    "gn:asciiname":"Hastakargadde",
    "gn:country_code":"IN",
    "gn:dem":502,
    "gn:feature_class":"P",
    "gn:feature_code":"PPL",
    "gn:name":"Hastak\u0101rgadde",
    "gn:population":0,
    "gn:timezone":"Asia/Kolkata",
    "iso:country":"IN",
    "ks:ks_name":"Hasrkargadde",
    "ks:ks_pop":44,
    "ks:ks_type":"HABITATION",
    "name:eng_x_preferred":[
        "Hasrkargadde"
    ],
    "name:eng_x_variant":[
        "Hastakargadde"
    ],
    "wof:name":"Hasrkargadde",
    "wof:placetype":"locality",
    "wof:population":44
},
  "geometry": {"coordinates":[74.682243,14.916781],"type":"Point"}
}