{
  "type": "Feature",
  "properties": {
    "gn:admin1_code":"36",
    "gn:admin2_code":"184.0",
    "gn:asciiname":"Harraiya",
    "gn:country_code":"IN",
    "gn:dem":92,
    "gn:feature_class":"P",
    "gn:feature_code":"PPL",
    "gn:name":"Harraiya",
    "gn:population":0,
    "gn:timezone":"Asia/Kolkata",
    "iso:country":"IN",
    "name:bpy_x_preferred":[
        "\u09b9\u09be\u09b0\u09b0\u09be\u0987\u09af\u09bc\u09be"
    ],
    "name:hin_x_preferred":[
        "\u0939\u0930\u094d\u0930\u0948\u092f\u093e"
    ],
    "name:ita_x_preferred":[
        "Harraiya"
    ],
    "name:mlg_x_preferred":[
        "Harraiya"
    ],
    "name:msa_x_preferred":[
        "Harraiya"
    ],
    "name:new_x_preferred":[
        "\u0939\u0930\u094d\u0930\u0948\u092f\u093e"
    ],
    "name:nld_x_preferred":[
        "Harraiya"
    ],
    "name:pol_x_preferred":[
        "Harraiya"
    ],
    "name:por_x_preferred":[
        "Harraiya"
    ],
    "name:urd_x_preferred":[
        "\u06c1\u0631\u06cc\u0627"
    ],
    "name:vie_x_preferred":[
        "Harraiya"
    ],
    "name:zho_x_preferred":[
        "\u54c8\u8d56\u8036"
    ],
    "wof:name":"Harraiya",
    "wof:placetype":"locality"
},
  "geometry": {"coordinates":[83.036,27.23731],"type":"Point"}
}