{
  "type": "Feature",
  "properties": {
    "gn:admin1_code":"34.0",
    "gn:admin2_code":"203.0",
    "gn:asciiname":"Parsotimpur",
    "gn:country_code":"IN",
    "gn:dem":86,
    "gn:feature_class":"P",
    "gn:feature_code":"PPL",
    "gn:name":"Parsotimpur",
    "gn:population":0,
    "gn:timezone":"Asia/Kolkata",
    "iso:country":"IN",
    "ks:ks_name":"Parsotim Pur",
    "ks:ks_pop":519,
    "ks:ks_type":"VILLAGE",
    "ks:ks_uagg_main":0,
    "name:eng_x_preferred":[
        "Parsotim Pur"
    ],
    "wof:name":"Parsotim Pur",
    "wof:placetype":"neighbourhood",
    "wof:population":519
},
  "geometry": {"coordinates":[84.708071,27.012564],"type":"Point"}
}