{
  "type": "Feature",
  "properties": {
    "iso:country":"IN",
    "ks:ks_name":"Rameswarpur",
    "ks:ks_pop":375,
    "ks:ks_type":"VILLAGE",
    "ks:ks_uagg_main":0,
    "name:eng_x_preferred":[
        "Rameswarpur"
    ],
    "wof:name":"Rameswarpur",
    "wof:placetype":"neighbourhood",
    "wof:population":375
},
  "geometry": {"coordinates":[86.719905,20.849003],"type":"Point"}
}