{
  "type": "Feature",
  "properties": {
    "iso:country":"IN",
    "ks:ks_name":"Ashapur",
    "ks:ks_pop":332,
    "ks:ks_type":"HABITATION",
    "name:eng_x_preferred":[
        "Ashapur"
    ],
    "wof:name":"Ashapur",
    "wof:placetype":"locality",
    "wof:population":332
},
  "geometry": {"coordinates":[84.435782,26.350359],"type":"Point"}
}