{
  "type": "Feature",
  "properties": {
    "iso:country":"IN",
    "ks:ks_name":"Bhayyon Ki Dhani",
    "ks:ks_pop":1019,
    "ks:ks_type":"VILLAGE",
    "name:eng_x_preferred":[
        "Bhayyon Ki Dhani"
    ],
    "wof:name":"Bhayyon Ki Dhani",
    "wof:placetype":"locality",
    "wof:population":1019
},
  "geometry": {"coordinates":[72.370839,26.926831],"type":"Point"}
}