{
  "type": "Feature",
  "properties": {
    "iso:country":"IN",
    "ks:ks_name":"Buriuli",
    "ks:ks_pop":150,
    "ks:ks_type":"VILLAGE",
    "name:eng_x_preferred":[
        "Buriuli"
    ],
    "wof:name":"Buriuli",
    "wof:placetype":"locality",
    "wof:population":150
},
  "geometry": {"coordinates":[85.368605,22.685921],"type":"Point"}
}