{
  "type": "Feature",
  "properties": {
    "iso:country":"IN",
    "ks:ks_name":"Pipalia Hasnabad",
    "ks:ks_pop":1273,
    "ks:ks_type":"VILLAGE",
    "name:eng_x_preferred":[
        "Pipalia Hasnabad"
    ],
    "wof:name":"Pipalia Hasnabad",
    "wof:placetype":"locality",
    "wof:population":1273
},
  "geometry": {"coordinates":[77.380195,23.636305],"type":"Point"}
}