{
  "type": "Feature",
  "properties": {
    "gn:admin1_code":"21",
    "gn:admin2_code":"396.0",
    "gn:asciiname":"Jhulkaguda",
    "gn:country_code":"IN",
    "gn:dem":782,
    "gn:feature_class":"P",
    "gn:feature_code":"PPL",
    "gn:name":"Jhulkaguda",
    "gn:population":0,
    "gn:timezone":"Asia/Kolkata",
    "iso:country":"IN",
    "wof:name":"Jhulkaguda",
    "wof:placetype":"locality"
},
  "geometry": {"coordinates":[83.04127,19.52989],"type":"Point"}
}