{
  "type": "Feature",
  "properties": {
    "gn:admin1_code":"21",
    "gn:admin2_code":"396.0",
    "gn:asciiname":"Jhulkaguda",
    "gn:country_code":"IN",
    "gn:dem":782,
    "gn:feature_class":"P",
    "gn:feature_code":"PPL",
    "gn:name":"Jhulkaguda",
    "gn:population":0,
    "gn:timezone":"Asia/Kolkata",
    "iso:country":"IN",
    "ks:ks_name":"Jhulkaguda",
    "ks:ks_pop":373,
    "ks:ks_type":"VILLAGE",
    "name:eng_x_preferred":[
        "Jhulkaguda"
    ],
    "wof:name":"Jhulkaguda",
    "wof:placetype":"locality",
    "wof:population":373
},
  "geometry": {"coordinates":[83.04121600000001,19.529829],"type":"Point"}
}