{
  "type": "Feature",
  "properties": {
    "gn:admin1_code":"39.0",
    "gn:admin2_code":"061",
    "gn:asciiname":"Naugaon",
    "gn:country_code":"IN",
    "gn:dem":1083,
    "gn:feature_class":"P",
    "gn:feature_code":"PPL",
    "gn:name":"Naugaon",
    "gn:population":0,
    "gn:timezone":"Asia/Kolkata",
    "iso:country":"IN",
    "ks:ks_name":"Nau Gaon",
    "ks:ks_pop":150,
    "ks:ks_type":"HABITATION",
    "name:eng_x_preferred":[
        "Nau Gaon"
    ],
    "name:eng_x_variant":[
        "Naugaon"
    ],
    "wof:name":"Nau Gaon",
    "wof:placetype":"locality",
    "wof:population":150
},
  "geometry": {"coordinates":[78.648369,29.844459],"type":"Point"}
}