{
  "type": "Feature",
  "properties": {
    "gn:admin1_code":"39.0",
    "gn:admin2_code":"061",
    "gn:asciiname":"Naugaon",
    "gn:country_code":"IN",
    "gn:dem":1083,
    "gn:feature_class":"P",
    "gn:feature_code":"PPL",
    "gn:name":"Naugaon",
    "gn:population":0,
    "gn:timezone":"Asia/Kolkata",
    "iso:country":"IN",
    "wof:name":"Naugaon",
    "wof:placetype":"locality"
},
  "geometry": {"coordinates":[78.65043,29.84523],"type":"Point"}
}