{
  "type": "Feature",
  "properties": {
    "iso:country":"IN",
    "ks:ks_alt_nam":"Karm\u0101hi",
    "ks:ks_name":"Karmahi",
    "ks:ks_pop":300,
    "ks:ks_type":"VILLAGE",
    "name:eng_x_preferred":[
        "Karmahi"
    ],
    "name:eng_x_variant":[
        "Karm\u0101hi"
    ],
    "wof:name":"Karmahi",
    "wof:placetype":"locality",
    "wof:population":300
},
  "geometry": {"coordinates":[84.80184,24.322206],"type":"Point"}
}