{
  "type": "Feature",
  "properties": {
    "gn:admin1_code":"35",
    "gn:admin2_code":"458.0",
    "gn:asciiname":"Udaipura",
    "gn:country_code":"IN",
    "gn:dem":427,
    "gn:feature_class":"P",
    "gn:feature_code":"PPL",
    "gn:name":"Udaipura",
    "gn:population":0,
    "gn:timezone":"Asia/Kolkata",
    "iso:country":"IN",
    "name:ben_x_preferred":[
        "\u0989\u09a6\u09af\u09bc\u09aa\u09c1\u09b0\u09be"
    ],
    "name:bpy_x_preferred":[
        "\u0989\u09a6\u09af\u09bc\u09aa\u09c1\u09b0\u09be"
    ],
    "name:ceb_x_preferred":[
        "Udaipura"
    ],
    "name:fas_x_preferred":[
        "\u06cc\u0648\u062f\u0627\u06cc\u067e\u0648\u0631\u0627"
    ],
    "name:ita_x_preferred":[
        "Udaipura"
    ],
    "name:mlg_x_preferred":[
        "Udaipura"
    ],
    "name:msa_x_preferred":[
        "Udaipura"
    ],
    "name:nld_x_preferred":[
        "Udaipura"
    ],
    "name:por_x_preferred":[
        "Udaipura"
    ],
    "name:spa_x_preferred":[
        "Udaipura"
    ],
    "name:swe_x_preferred":[
        "Udaipura"
    ],
    "name:urd_x_preferred":[
        "\u0627\u062f\u06d2 \u067e\u0648\u0631\u06c1"
    ],
    "name:vie_x_preferred":[
        "Udaipura"
    ],
    "name:zho_x_preferred":[
        "\u4e4c\u4ee3\u666e\u62c9"
    ],
    "wof:name":"Udaipura",
    "wof:placetype":"locality"
},
  "geometry": {"coordinates":[77.23523,24.09243],"type":"Point"}
}