{
  "type": "Feature",
  "properties": {
    "gn:admin1_code":"35.0",
    "gn:admin2_code":"456.0",
    "gn:asciiname":"Karhaia",
    "gn:country_code":"IN",
    "gn:dem":414,
    "gn:feature_class":"P",
    "gn:feature_code":"PPL",
    "gn:name":"Karhaia",
    "gn:population":0,
    "gn:timezone":"Asia/Kolkata",
    "iso:country":"IN",
    "ks:ks_name":"Karhaiya",
    "ks:ks_pop":299,
    "ks:ks_type":"VILLAGE",
    "name:eng_x_preferred":[
        "Karhaiya"
    ],
    "name:eng_x_variant":[
        "Karhaia"
    ],
    "wof:name":"Karhaiya",
    "wof:placetype":"locality",
    "wof:population":299
},
  "geometry": {"coordinates":[80.031103,22.770449],"type":"Point"}
}