{
  "type": "Feature",
  "properties": {
    "gn:admin1_code":"35.0",
    "gn:admin2_code":"456.0",
    "gn:asciiname":"Karhaia",
    "gn:country_code":"IN",
    "gn:dem":414,
    "gn:feature_class":"P",
    "gn:feature_code":"PPL",
    "gn:name":"Karhaia",
    "gn:population":0,
    "gn:timezone":"Asia/Kolkata",
    "iso:country":"IN",
    "wof:name":"Karhaia",
    "wof:placetype":"locality"
},
  "geometry": {"coordinates":[80.03211999999998,22.77654],"type":"Point"}
}