{
  "type": "Feature",
  "properties": {
    "iso:country":"IN",
    "ks:ks_name":"Palodi",
    "ks:ks_pop":222,
    "ks:ks_type":"HABITATION",
    "name:eng_x_preferred":[
        "Palodi"
    ],
    "wof:name":"Palodi",
    "wof:placetype":"locality",
    "wof:population":222
},
  "geometry": {"coordinates":[81.06029700000001,18.0553],"type":"Point"}
}