{
  "type": "Feature",
  "properties": {
    "gn:admin1_code":"13.0",
    "gn:admin2_code":"593.0",
    "gn:asciiname":"Karakkad",
    "gn:country_code":"IN",
    "gn:dem":35,
    "gn:feature_class":"P",
    "gn:feature_code":"PPL",
    "gn:name":"K\u0101rakk\u0101d",
    "gn:population":0,
    "gn:timezone":"Asia/Kolkata",
    "iso:country":"IN",
    "ks:ks_name":"Karakkad",
    "ks:ks_pop":1866,
    "ks:ks_type":"HABITATION",
    "ks:ks_uagg_main":0,
    "name:eng_x_preferred":[
        "Karakkad"
    ],
    "wof:name":"Karakkad",
    "wof:placetype":"neighbourhood",
    "wof:population":1866
},
  "geometry": {"coordinates":[76.226416,10.784339],"type":"Point"}
}