{
  "type": "Feature",
  "properties": {
    "iso:country":"IN",
    "ks:ks_name":"Ratan Ki Basti",
    "ks:ks_pop":231,
    "ks:ks_type":"VILLAGE",
    "name:eng_x_preferred":[
        "Ratan Ki Basti"
    ],
    "wof:name":"Ratan Ki Basti",
    "wof:placetype":"locality",
    "wof:population":231
},
  "geometry": {"coordinates":[71.541797,26.948361],"type":"Point"}
}