{
  "type": "Feature",
  "properties": {
    "iso:country":"IN",
    "ks:ks_name":"Bavithota",
    "ks:ks_pop":20,
    "ks:ks_type":"HABITATION",
    "name:eng_x_preferred":[
        "Bavithota"
    ],
    "wof:name":"Bavithota",
    "wof:placetype":"locality",
    "wof:population":20
},
  "geometry": {"coordinates":[75.18177,13.422299],"type":"Point"}
}