{
  "type": "Feature",
  "properties": {
    "gn:admin1_code":"40",
    "gn:admin2_code":"535.0",
    "gn:asciiname":"Ramapuram",
    "gn:country_code":"IN",
    "gn:dem":472,
    "gn:feature_class":"P",
    "gn:feature_code":"PPL",
    "gn:name":"R\u0101m\u0101puram",
    "gn:population":0,
    "gn:timezone":"Asia/Kolkata",
    "iso:country":"IN",
    "name:ceb_x_preferred":[
        "Ramapuram"
    ],
    "name:ita_x_preferred":[
        "Ramapuram"
    ],
    "name:mal_x_preferred":[
        "\u0d30\u0d3e\u0d2e\u0d2a\u0d41\u0d30\u0d02"
    ],
    "name:swe_x_preferred":[
        "Ramapuram"
    ],
    "wof:name":"Ramapuram",
    "wof:placetype":"neighbourhood"
},
  "geometry": {"coordinates":[78.57035999999999,18.17642],"type":"Point"}
}