{
  "type": "Feature",
  "properties": {
    "iso:country":"IN",
    "ks:ks_name":"Ambargod",
    "ks:ks_pop":31,
    "ks:ks_type":"HABITATION",
    "name:eng_x_preferred":[
        "Ambargod"
    ],
    "wof:name":"Ambargod",
    "wof:placetype":"locality",
    "wof:population":31
},
  "geometry": {"coordinates":[74.481081,14.225807],"type":"Point"}
}