{
  "type": "Feature",
  "properties": {
    "iso:country":"IN",
    "ks:ks_name":"Nauli",
    "ks:ks_pop":187,
    "ks:ks_type":"VILLAGE",
    "name:eng_x_preferred":[
        "Nauli"
    ],
    "wof:name":"Nauli",
    "wof:placetype":"locality",
    "wof:population":187
},
  "geometry": {"coordinates":[83.658536,19.434461],"type":"Point"}
}