{
  "type": "Feature",
  "properties": {
    "gn:admin1_code":"10.0",
    "gn:admin2_code":"075",
    "gn:asciiname":"Khukrana",
    "gn:country_code":"IN",
    "gn:dem":237,
    "gn:feature_class":"P",
    "gn:feature_code":"PPL",
    "gn:name":"Khukr\u0101na",
    "gn:population":0,
    "gn:timezone":"Asia/Kolkata",
    "iso:country":"IN",
    "wof:name":"Khukrana",
    "wof:placetype":"locality"
},
  "geometry": {"coordinates":[76.89511,29.39545],"type":"Point"}
}