{
  "type": "Feature",
  "properties": {
    "gn:admin1_code":"34.0",
    "gn:admin2_code":"228.0",
    "gn:asciiname":"Matokhar",
    "gn:country_code":"IN",
    "gn:dem":58,
    "gn:feature_class":"P",
    "gn:feature_code":"PPL",
    "gn:name":"Matokh\u0101r",
    "gn:population":0,
    "gn:timezone":"Asia/Kolkata",
    "iso:country":"IN",
    "wof:name":"Matokhar",
    "wof:placetype":"locality"
},
  "geometry": {"coordinates":[85.80235999999999,25.13446],"type":"Point"}
}