{
  "type": "Feature",
  "properties": {
    "gn:admin1_code":"36.0",
    "gn:admin2_code":"167",
    "gn:asciiname":"Muharo",
    "gn:country_code":"IN",
    "gn:dem":341,
    "gn:feature_class":"P",
    "gn:feature_code":"PPL",
    "gn:name":"Muh\u0101ro",
    "gn:population":0,
    "gn:timezone":"Asia/Kolkata",
    "iso:country":"IN",
    "wof:name":"Muharo",
    "wof:placetype":"locality"
},
  "geometry": {"coordinates":[78.43399000000002,24.86395],"type":"Point"}
}