{
  "type": "Feature",
  "properties": {
    "iso:country":"IN",
    "ks:ks_name":"Pahantoli",
    "ks:ks_pop":174,
    "ks:ks_type":"HABITATION",
    "name:eng_x_preferred":[
        "Pahantoli"
    ],
    "wof:name":"Pahantoli",
    "wof:placetype":"locality",
    "wof:population":174
},
  "geometry": {"coordinates":[84.700304,22.463844],"type":"Point"}
}