{
  "type": "Feature",
  "properties": {
    "gn:admin1_code":"34.0",
    "gn:admin2_code":"203.0",
    "gn:asciiname":"Bhitharwa",
    "gn:country_code":"IN",
    "gn:dem":102,
    "gn:feature_class":"P",
    "gn:feature_code":"PPL",
    "gn:name":"Bhitharwa",
    "gn:population":0,
    "gn:timezone":"Asia/Kolkata",
    "iso:country":"IN",
    "ks:ks_name":"Bhitharwa",
    "ks:ks_pop":1018,
    "ks:ks_type":"VILLAGE",
    "ks:ks_uagg_main":0,
    "name:eng_x_preferred":[
        "Bhitharwa"
    ],
    "wof:name":"Bhitharwa",
    "wof:placetype":"neighbourhood",
    "wof:population":1018
},
  "geometry": {"coordinates":[84.489414,27.245299],"type":"Point"}
}