{
  "type": "Feature",
  "properties": {
    "gn:admin1_code":"36.0",
    "gn:admin2_code":"179.0",
    "gn:asciiname":"Manirampur",
    "gn:country_code":"IN",
    "gn:dem":110,
    "gn:feature_class":"P",
    "gn:feature_code":"PPL",
    "gn:name":"Manirampur",
    "gn:population":0,
    "gn:timezone":"Asia/Kolkata",
    "iso:country":"IN",
    "ks:ks_name":"Manirampur",
    "ks:ks_pop":191,
    "ks:ks_type":"HABITATION",
    "ks:ks_uagg_main":0,
    "name:eng_x_preferred":[
        "Manirampur"
    ],
    "wof:name":"Manirampur",
    "wof:placetype":"neighbourhood",
    "wof:population":191
},
  "geometry": {"coordinates":[81.842494,26.203315],"type":"Point"}
}