{
  "type": "Feature",
  "properties": {
    "iso:country":"IN",
    "ks:ks_alt_nam":"Thirumurugan Nagar AC",
    "ks:ks_name":"Thirumurugan Nagar Ac",
    "ks:ks_pop":150,
    "ks:ks_type":"HABITATION",
    "name:eng_x_preferred":[
        "Thirumurugan Nagar Ac"
    ],
    "wof:name":"Thirumurugan Nagar Ac",
    "wof:placetype":"locality",
    "wof:population":150
},
  "geometry": {"coordinates":[79.009343,12.962202],"type":"Point"}
}