{
  "type": "Feature",
  "properties": {
    "iso:country":"IN",
    "ks:ks_name":"Khajurguda",
    "ks:ks_pop":51,
    "ks:ks_type":"VILLAGE",
    "name:eng_x_preferred":[
        "Khajurguda"
    ],
    "wof:name":"Khajurguda",
    "wof:placetype":"locality",
    "wof:population":51
},
  "geometry": {"coordinates":[83.179221,19.579618],"type":"Point"}
}