{
  "type": "Feature",
  "properties": {
    "iso:country":"IN",
    "ks:ks_alt_nam":"Byr\u0101pura",
    "ks:ks_name":"Byrapura",
    "ks:ks_pop":42,
    "ks:ks_type":"VILLAGE",
    "name:eng_x_preferred":[
        "Byrapura"
    ],
    "name:eng_x_variant":[
        "Byr\u0101pura"
    ],
    "wof:name":"Byrapura",
    "wof:placetype":"locality",
    "wof:population":42
},
  "geometry": {"coordinates":[76.306324,13.788858],"type":"Point"}
}