{
  "type": "Feature",
  "properties": {
    "gn:admin1_code":"36",
    "gn:admin2_code":"200.0",
    "gn:asciiname":"Kodai",
    "gn:country_code":"IN",
    "gn:dem":525,
    "gn:feature_class":"P",
    "gn:feature_code":"PPL",
    "gn:name":"Kodai",
    "gn:population":0,
    "gn:timezone":"Asia/Kolkata",
    "iso:country":"IN",
    "ks:ks_name":"Kodai",
    "ks:ks_pop":333,
    "ks:ks_type":"VILLAGE",
    "name:eng_x_preferred":[
        "Kodai"
    ],
    "wof:name":"Kodai",
    "wof:placetype":"locality",
    "wof:population":333
},
  "geometry": {"coordinates":[83.234422,24.549206],"type":"Point"}
}