{
  "type": "Feature",
  "properties": {
    "iso:country":"IN",
    "ks:ks_name":"N G Kandriga",
    "ks:ks_pop":123,
    "ks:ks_type":"HABITATION",
    "name:eng_x_preferred":[
        "N G Kandriga"
    ],
    "wof:name":"N G Kandriga",
    "wof:placetype":"locality",
    "wof:population":123
},
  "geometry": {"coordinates":[79.863276,13.815762],"type":"Point"}
}