{
  "type": "Feature",
  "properties": {
    "iso:country":"IN",
    "ks:ks_name":"Raipur",
    "ks:ks_pop":0,
    "ks:ks_type":"VILLAGE",
    "name:eng_x_preferred":[
        "Raipur"
    ],
    "wof:name":"Raipur",
    "wof:placetype":"locality",
    "wof:population":0
},
  "geometry": {"coordinates":[83.31881799999999,21.616381],"type":"Point"}
}