{
  "type": "Feature",
  "properties": {
    "iso:country":"IN",
    "ks:ks_name":"Bowrapurpenta",
    "ks:ks_pop":67,
    "ks:ks_type":"HABITATION",
    "name:eng_x_preferred":[
        "Bowrapurpenta"
    ],
    "wof:name":"Bowrapurpenta",
    "wof:placetype":"locality",
    "wof:population":67
},
  "geometry": {"coordinates":[78.68173,16.142547],"type":"Point"}
}