{
  "type": "Feature",
  "properties": {
    "gn:admin1_code":"12.0",
    "gn:admin2_code":"010",
    "gn:asciiname":"Zawara",
    "gn:country_code":"IN",
    "gn:dem":1666,
    "gn:feature_class":"P",
    "gn:feature_code":"PPL",
    "gn:name":"Z\u0101wara",
    "gn:population":0,
    "gn:timezone":"Asia/Kolkata",
    "iso:country":"IN",
    "wof:name":"Zawara",
    "wof:placetype":"locality"
},
  "geometry": {"coordinates":[74.9258,34.05343],"type":"Point"}
}