{
  "type": "Feature",
  "properties": {
    "gn:admin1_code":"37",
    "gn:admin2_code":"406.0",
    "gn:asciiname":"Arabandha",
    "gn:country_code":"IN",
    "gn:dem":281,
    "gn:feature_class":"P",
    "gn:feature_code":"PPL",
    "gn:name":"Arabandha",
    "gn:population":0,
    "gn:timezone":"Asia/Kolkata",
    "iso:country":"IN",
    "wof:name":"Arabandha",
    "wof:placetype":"locality"
},
  "geometry": {"coordinates":[81.69887,21.96772],"type":"Point"}
}