{
  "type": "Feature",
  "properties": {
    "iso:country":"IN",
    "ks:ks_name":"Sonarigaon",
    "ks:ks_pop":310,
    "ks:ks_type":"HABITATION",
    "name:eng_x_preferred":[
        "Sonarigaon"
    ],
    "wof:name":"Sonarigaon",
    "wof:placetype":"locality",
    "wof:population":310
},
  "geometry": {"coordinates":[94.014864,26.488734],"type":"Point"}
}