{
  "type": "Feature",
  "properties": {
    "iso:country":"IN",
    "ks:ks_name":"Benda",
    "ks:ks_pop":824,
    "ks:ks_type":"VILLAGE",
    "name:eng_x_preferred":[
        "Benda"
    ],
    "wof:name":"Benda",
    "wof:placetype":"locality",
    "wof:population":824
},
  "geometry": {"coordinates":[78.960769,25.987412],"type":"Point"}
}