{
  "type": "Feature",
  "properties": {
    "iso:country":"IN",
    "ks:ks_name":"Kamarda",
    "ks:ks_pop":532,
    "ks:ks_type":"VILLAGE",
    "name:eng_x_preferred":[
        "Kamarda"
    ],
    "wof:name":"Kamarda",
    "wof:placetype":"locality",
    "wof:population":532
},
  "geometry": {"coordinates":[85.84941999999999,21.053966],"type":"Point"}
}