{
  "type": "Feature",
  "properties": {
    "iso:country":"IN",
    "ks:ks_name":"Majira",
    "ks:ks_pop":205,
    "ks:ks_type":"VILLAGE",
    "name:eng_x_preferred":[
        "Majira"
    ],
    "wof:name":"Majira",
    "wof:placetype":"locality",
    "wof:population":205
},
  "geometry": {"coordinates":[86.20971299999999,24.030985],"type":"Point"}
}