{
  "type": "Feature",
  "properties": {
    "gn:admin1_code":"36",
    "gn:admin2_code":"196.0",
    "gn:asciiname":"Chhuchhar",
    "gn:country_code":"IN",
    "gn:dem":101,
    "gn:feature_class":"P",
    "gn:feature_code":"PPL",
    "gn:name":"Chhuchh\u0101r",
    "gn:population":0,
    "gn:timezone":"Asia/Kolkata",
    "iso:country":"IN",
    "ks:ks_name":"Chuchhar",
    "ks:ks_pop":1082,
    "ks:ks_type":"HABITATION",
    "name:eng_x_preferred":[
        "Chuchhar"
    ],
    "name:eng_x_variant":[
        "Chhuchhar"
    ],
    "wof:name":"Chuchhar",
    "wof:placetype":"locality",
    "wof:population":1082
},
  "geometry": {"coordinates":[83.080647,25.044531],"type":"Point"}
}