{
  "type": "Feature",
  "properties": {
    "iso:country":"IN",
    "ks:ks_name":"Nawae",
    "ks:ks_pop":1448,
    "ks:ks_type":"VILLAGE",
    "ks:ks_uagg_main":0,
    "name:eng_x_preferred":[
        "Nawae"
    ],
    "wof:name":"Nawae",
    "wof:placetype":"neighbourhood",
    "wof:population":1448
},
  "geometry": {"coordinates":[80.651341,26.692185],"type":"Point"}
}