{
  "type": "Feature",
  "properties": {
    "iso:country":"IN",
    "ks:ks_alt_nam":"B.C Colony",
    "ks:ks_name":"B.c Colony",
    "ks:ks_pop":111,
    "ks:ks_type":"HABITATION",
    "name:eng_x_preferred":[
        "B.c Colony"
    ],
    "wof:name":"B.c Colony",
    "wof:placetype":"locality",
    "wof:population":111
},
  "geometry": {"coordinates":[78.97465099999999,14.783144],"type":"Point"}
}