{
  "type": "Feature",
  "properties": {
    "gn:admin1_code":"34.0",
    "gn:admin2_code":"221.0",
    "gn:asciiname":"Koeri",
    "gn:country_code":"IN",
    "gn:dem":54,
    "gn:feature_class":"P",
    "gn:feature_code":"PPL",
    "gn:name":"Koeri",
    "gn:population":0,
    "gn:timezone":"Asia/Kolkata",
    "iso:country":"IN",
    "name:bih_x_preferred":[
        "\u0915\u094b\u0907\u0930\u0940"
    ],
    "name:hin_x_preferred":[
        "\u0915\u094b\u0907\u0930\u0940"
    ],
    "name:nep_x_preferred":[
        "\u0915\u094b\u0907\u0930\u0940"
    ],
    "wof:name":"Koeri",
    "wof:placetype":"locality"
},
  "geometry": {"coordinates":[85.74226999999998,25.92071],"type":"Point"}
}