{
  "type": "Feature",
  "properties": {
    "iso:country":"IN",
    "ks:ks_alt_nam":"NACHANKARWADI 2",
    "ks:ks_name":"Nachankarwadi 2",
    "ks:ks_pop":81,
    "ks:ks_type":"HABITATION",
    "name:eng_x_preferred":[
        "Nachankarwadi 2"
    ],
    "wof:name":"Nachankarwadi 2",
    "wof:placetype":"locality",
    "wof:population":81
},
  "geometry": {"coordinates":[73.58410499999999,16.68324],"type":"Point"}
}