{
  "type": "Feature",
  "properties": {
    "gn:admin1_code":"19.0",
    "gn:admin2_code":"569.0",
    "gn:asciiname":"Kolkebailu",
    "gn:country_code":"IN",
    "gn:dem":22,
    "gn:feature_class":"P",
    "gn:feature_code":"PPL",
    "gn:name":"Kolkebailu",
    "gn:population":0,
    "gn:timezone":"Asia/Kolkata",
    "iso:country":"IN",
    "ks:ks_name":"Kolkebailu",
    "ks:ks_pop":393,
    "ks:ks_type":"HABITATION",
    "name:eng_x_preferred":[
        "Kolkebailu"
    ],
    "wof:name":"Kolkebailu",
    "wof:placetype":"locality",
    "wof:population":393
},
  "geometry": {"coordinates":[74.76544199999999,13.528347],"type":"Point"}
}