{
  "type": "Feature",
  "properties": {
    "gn:admin1_code":"35.0",
    "gn:admin2_code":"453.0",
    "gn:asciiname":"Harratola",
    "gn:country_code":"IN",
    "gn:dem":666,
    "gn:feature_class":"P",
    "gn:feature_code":"PPL",
    "gn:name":"Harr\u0101tol\u0101",
    "gn:population":0,
    "gn:timezone":"Asia/Kolkata",
    "iso:country":"IN",
    "wof:name":"Harratola",
    "wof:placetype":"locality"
},
  "geometry": {"coordinates":[80.79465,22.87144],"type":"Point"}
}