{
  "type": "Feature",
  "properties": {
    "iso:country":"IN",
    "ks:ks_name":"Dhobandih",
    "ks:ks_pop":271,
    "ks:ks_type":"VILLAGE",
    "name:eng_x_preferred":[
        "Dhobandih"
    ],
    "wof:name":"Dhobandih",
    "wof:placetype":"locality",
    "wof:population":271
},
  "geometry": {"coordinates":[82.08127500000001,20.098878],"type":"Point"}
}