{
  "type": "Feature",
  "properties": {
    "iso:country":"IN",
    "ks:ks_name":"Viswanathapuram",
    "ks:ks_pop":425,
    "ks:ks_type":"HABITATION",
    "ks:ks_uagg_main":0,
    "name:eng_x_preferred":[
        "Viswanathapuram"
    ],
    "wof:name":"Viswanathapuram",
    "wof:placetype":"neighbourhood",
    "wof:population":425
},
  "geometry": {"coordinates":[78.786675,10.231078],"type":"Point"}
}