{
  "type": "Feature",
  "properties": {
    "iso:country":"IN",
    "ks:ks_alt_nam":"Daisajan T.E. 13 14 22 15",
    "ks:ks_name":"Daisajan T.e. 13 14 22 15",
    "ks:ks_pop":190,
    "ks:ks_type":"HABITATION",
    "name:eng_x_preferred":[
        "Daisajan T.e. 13 14 22 15"
    ],
    "wof:name":"Daisajan T.e. 13 14 22 15",
    "wof:placetype":"locality",
    "wof:population":190
},
  "geometry": {"coordinates":[95.53967299999999,27.640195],"type":"Point"}
}