{
  "type": "Feature",
  "properties": {
    "iso:country":"IN",
    "ks:ks_name":"Kuwanaritola",
    "ks:ks_pop":154,
    "ks:ks_type":"HABITATION",
    "name:eng_x_preferred":[
        "Kuwanaritola"
    ],
    "wof:name":"Kuwanaritola",
    "wof:placetype":"locality",
    "wof:population":154
},
  "geometry": {"coordinates":[80.51909000000001,21.337094],"type":"Point"}
}