{
  "type": "Feature",
  "properties": {
    "iso:country":"IN",
    "ks:ks_alt_nam":"Jangam wasti",
    "ks:ks_name":"Jangam Wasti",
    "ks:ks_pop":112,
    "ks:ks_type":"HABITATION",
    "name:eng_x_preferred":[
        "Jangam Wasti"
    ],
    "wof:name":"Jangam Wasti",
    "wof:placetype":"locality",
    "wof:population":112
},
  "geometry": {"coordinates":[76.042607,18.538145],"type":"Point"}
}