{
  "type": "Feature",
  "properties": {
    "gn:admin1_code":"19.0",
    "gn:admin2_code":"571.0",
    "gn:asciiname":"Kuradagonahalli",
    "gn:country_code":"IN",
    "gn:dem":741,
    "gn:feature_class":"P",
    "gn:feature_code":"PPL",
    "gn:name":"Kuradagonahalli",
    "gn:population":0,
    "gn:timezone":"Asia/Kolkata",
    "iso:country":"IN",
    "wof:name":"Kuradagonahalli",
    "wof:placetype":"locality"
},
  "geometry": {"coordinates":[77.26335999999998,13.56601],"type":"Point"}
}