{
  "type": "Feature",
  "properties": {
    "gn:admin1_code":"13.0",
    "gn:admin2_code":"590.0",
    "gn:asciiname":"Kolambatt",
    "gn:country_code":"IN",
    "gn:dem":742,
    "gn:feature_class":"P",
    "gn:feature_code":"PPL",
    "gn:name":"Kolambatt",
    "gn:population":0,
    "gn:timezone":"Asia/Kolkata",
    "iso:country":"IN",
    "wof:name":"Kolambatt",
    "wof:placetype":"locality"
},
  "geometry": {"coordinates":[76.13974,11.6618],"type":"Point"}
}