{
  "type": "Feature",
  "properties": {
    "iso:country":"IN",
    "ks:ks_name":"Liyadra",
    "ks:ks_pop":439,
    "ks:ks_type":"VILLAGE",
    "name:eng_x_preferred":[
        "Liyadra"
    ],
    "wof:name":"Liyadra",
    "wof:placetype":"locality",
    "wof:population":439
},
  "geometry": {"coordinates":[71.924863,24.921554],"type":"Point"}
}