{
  "type": "Feature",
  "properties": {
    "gn:country":"IN",
    "gn:fcode":"PPL",
    "gn:pop":16271,
    "iso:country":"IN",
    "name:ara_x_preferred":[
        "\u062c\u0627\u0646\u062f\u0631\u0628\u0627\u0644"
    ],
    "name:bpy_x_preferred":[
        "\u0997\u09a8\u09a6\u09c7\u09b0\u09ac\u09b2"
    ],
    "name:deu_x_preferred":[
        "Ganderbal"
    ],
    "name:eng_x_preferred":[
        "Ganderbal"
    ],
    "name:fra_x_preferred":[
        "Ganderbal"
    ],
    "name:ita_x_preferred":[
        "Ganderbal"
    ],
    "name:kas_x_preferred":[
        "\u06af\u0627\u0646\u065b\u062f\u064e\u0631\u0628\u064e\u0644"
    ],
    "name:mlg_x_preferred":[
        "Ganderbal"
    ],
    "name:msa_x_preferred":[
        "Ganderbal"
    ],
    "name:nan_x_preferred":[
        "Ganderbal"
    ],
    "name:new_x_preferred":[
        "\u0917\u0902\u0926\u0947\u0930\u092c\u0932"
    ],
    "name:nld_x_preferred":[
        "Ganderbal"
    ],
    "name:por_x_preferred":[
        "Ganderbal"
    ],
    "name:san_x_preferred":[
        "\u0917\u0923\u094d\u0921\u0947\u0930\u092c\u093e\u0932"
    ],
    "name:spa_x_preferred":[
        "Ganderbal"
    ],
    "name:swe_x_preferred":[
        "G\u0101ndarbal"
    ],
    "name:unk_x_variant":[
        "Ganderbal"
    ],
    "name:urd_x_preferred":[
        "\u06af\u0627\u0646\u062f\u0631\u0628\u0644"
    ],
    "name:vie_x_preferred":[
        "Ganderbal"
    ],
    "name:zho_x_preferred":[
        "\u52a0\u6069\u5fb7\u5c14\u5df4\u5c14"
    ],
    "qs:name":"G\u0101ndarbal",
    "qs:photos_9r":0,
    "qs:photos_sr":0,
    "qs:pop_sr":"6",
    "wof:name":"G\u0101ndarbal",
    "wof:placetype":"locality",
    "wof:population":16271
},
  "geometry": {"coordinates":[74.7783,34.22992],"type":"Point"}
}