{
  "type": "Feature",
  "properties": {
    "gn:admin1_code":"36",
    "gn:admin2_code":"192.0",
    "gn:asciiname":"Fazil Chak",
    "gn:country_code":"IN",
    "gn:dem":76,
    "gn:feature_class":"P",
    "gn:feature_code":"PPL",
    "gn:name":"F\u0101zil Chak",
    "gn:population":0,
    "gn:timezone":"Asia/Kolkata",
    "iso:country":"IN",
    "ks:ks_alt_nam":"F\u0101zil Chak",
    "ks:ks_name":"Fazil Chak",
    "ks:ks_type":"VILLAGE",
    "ks:ks_uagg_main":0,
    "name:eng_x_preferred":[
        "Fazil Chak"
    ],
    "name:eng_x_variant":[
        "F\u0101zil Chak"
    ],
    "wof:name":"Fazil Chak",
    "wof:placetype":"locality"
},
  "geometry": {"coordinates":[83.603405,25.912296],"type":"Point"}
}