{
  "type": "Feature",
  "properties": {
    "iso:country":"IN",
    "ks:ks_name":"Mogarapani",
    "ks:ks_pop":1066,
    "ks:ks_type":"HABITATION",
    "name:eng_x_preferred":[
        "Mogarapani"
    ],
    "wof:name":"Mogarapani",
    "wof:placetype":"locality",
    "wof:population":1066
},
  "geometry": {"coordinates":[74.52377,21.817928],"type":"Point"}
}