{
  "type": "Feature",
  "properties": {
    "iso:country":"IN",
    "ks:ks_name":"Yetigattuthanda",
    "ks:ks_pop":328,
    "ks:ks_type":"HABITATION",
    "name:eng_x_preferred":[
        "Yetigattuthanda"
    ],
    "wof:name":"Yetigattuthanda",
    "wof:placetype":"locality",
    "wof:population":328
},
  "geometry": {"coordinates":[79.78708899999999,16.780376],"type":"Point"}
}