{
  "type": "Feature",
  "properties": {
    "iso:country":"IN",
    "ks:ks_name":"Balia",
    "ks:ks_pop":422,
    "ks:ks_type":"VILLAGE",
    "ks:ks_uagg_main":0,
    "name:eng_x_preferred":[
        "Balia"
    ],
    "wof:name":"Balia",
    "wof:placetype":"neighbourhood",
    "wof:population":422
},
  "geometry": {"coordinates":[86.418482,25.909687],"type":"Point"}
}