{
  "type": "Feature",
  "properties": {
    "iso:country":"IN",
    "ks:ks_name":"Rongchek",
    "ks:ks_pop":396,
    "ks:ks_type":"HABITATION",
    "name:eng_x_preferred":[
        "Rongchek"
    ],
    "wof:name":"Rongchek",
    "wof:placetype":"locality",
    "wof:population":396
},
  "geometry": {"coordinates":[92.280694,25.897222],"type":"Point"}
}