{
  "type": "Feature",
  "properties": {
    "gn:admin1_code":"37.0",
    "gn:admin2_code":"417.0",
    "gn:asciiname":"Burji",
    "gn:country_code":"IN",
    "gn:dem":350,
    "gn:feature_class":"P",
    "gn:feature_code":"PPL",
    "gn:name":"Burji",
    "gn:population":0,
    "gn:timezone":"Asia/Kolkata",
    "iso:country":"IN",
    "name:ceb_x_preferred":[
        "Burji"
    ],
    "name:deu_x_preferred":[
        "Burji"
    ],
    "name:swe_x_preferred":[
        "Burji"
    ],
    "wof:name":"Burji",
    "wof:placetype":"locality"
},
  "geometry": {"coordinates":[81.07481999999997,18.74003],"type":"Point"}
}