{
  "type": "Feature",
  "properties": {
    "gn:admin1_code":"37.0",
    "gn:admin2_code":"417.0",
    "gn:asciiname":"Burji",
    "gn:country_code":"IN",
    "gn:dem":350,
    "gn:feature_class":"P",
    "gn:feature_code":"PPL",
    "gn:name":"Burji",
    "gn:population":0,
    "gn:timezone":"Asia/Kolkata",
    "iso:country":"IN",
    "ks:ks_name":"Burji",
    "ks:ks_pop":250,
    "ks:ks_type":"VILLAGE",
    "name:ceb_x_preferred":[
        "Burji"
    ],
    "name:deu_x_preferred":[
        "Burji"
    ],
    "name:eng_x_preferred":[
        "Burji"
    ],
    "name:swe_x_preferred":[
        "Burji"
    ],
    "wof:name":"Burji",
    "wof:placetype":"locality",
    "wof:population":250
},
  "geometry": {"coordinates":[81.079761,18.745098],"type":"Point"}
}