{
  "type": "Feature",
  "properties": {
    "gn:admin1_code":"34.0",
    "gn:admin2_code":"212.0",
    "gn:asciiname":"Kalinagar",
    "gn:country_code":"IN",
    "gn:dem":30,
    "gn:feature_class":"P",
    "gn:feature_code":"PPL",
    "gn:name":"K\u0101l\u012bnagar",
    "gn:population":0,
    "gn:timezone":"Asia/Kolkata",
    "iso:country":"IN",
    "name:bpy_x_preferred":[
        "\u0995\u09be\u09b2\u09bf\u09a8\u0997\u09b0"
    ],
    "name:ceb_x_preferred":[
        "K\u0101l\u012bnagar"
    ],
    "name:ita_x_preferred":[
        "Kalinagar"
    ],
    "name:mlg_x_preferred":[
        "Kalinagar"
    ],
    "name:msa_x_preferred":[
        "Kalinagar"
    ],
    "name:new_x_preferred":[
        "\u0915\u093e\u0932\u0940\u0928\u0917\u0930"
    ],
    "name:nld_x_preferred":[
        "Kalinagar"
    ],
    "name:pol_x_preferred":[
        "Kalinagar"
    ],
    "name:por_x_preferred":[
        "Kalinagar"
    ],
    "name:swe_x_preferred":[
        "K\u0101l\u012bnagar"
    ],
    "name:urd_x_preferred":[
        "\u06a9\u0644\u06cc \u0646\u06af\u0631"
    ],
    "name:vie_x_preferred":[
        "Kalinagar"
    ],
    "name:zho_x_preferred":[
        "\u5361\u5229\u7eb3\u52a0\u5c14"
    ],
    "wof:name":"Kalinagar",
    "wof:placetype":"locality"
},
  "geometry": {"coordinates":[87.84805,25.27326],"type":"Point"}
}