{
  "type": "Feature",
  "properties": {
    "gn:admin1_code":"34.0",
    "gn:admin2_code":"210.0",
    "gn:asciiname":"Kurli",
    "gn:country_code":"IN",
    "gn:dem":66,
    "gn:feature_class":"P",
    "gn:feature_code":"PPL",
    "gn:name":"Kurli",
    "gn:population":0,
    "gn:timezone":"Asia/Kolkata",
    "iso:country":"IN",
    "name:tel_x_preferred":[
        "\u0c15\u0c41\u0c30\u0c4d\u0c32\u0c3f"
    ],
    "wof:name":"Kurli",
    "wof:placetype":"locality"
},
  "geometry": {"coordinates":[87.85726,26.34866],"type":"Point"}
}