{
  "type": "Feature",
  "properties": {
    "iso:country":"IN",
    "ks:ks_alt_nam":"Puthikhaity P II",
    "ks:ks_name":"Puthikhaity P Ii",
    "ks:ks_pop":401,
    "ks:ks_type":"HABITATION",
    "ks:ks_uagg_main":0,
    "name:eng_x_preferred":[
        "Puthikhaity P Ii"
    ],
    "wof:name":"Puthikhaity P Ii",
    "wof:placetype":"neighbourhood",
    "wof:population":401
},
  "geometry": {"coordinates":[92.808813,26.475955],"type":"Point"}
}