{
  "type": "Feature",
  "properties": {
    "gn:admin1_code":"11.0",
    "gn:admin2_code":"26.0",
    "gn:asciiname":"Gada Jhakar",
    "gn:country_code":"IN",
    "gn:dem":2353,
    "gn:feature_class":"P",
    "gn:feature_code":"PPL",
    "gn:name":"Gada Jh\u0101kar",
    "gn:population":0,
    "gn:timezone":"Asia/Kolkata",
    "iso:country":"IN",
    "wof:name":"Gada Jhakar",
    "wof:placetype":"locality"
},
  "geometry": {"coordinates":[77.34004,31.48397000000001],"type":"Point"}
}