{
  "type": "Feature",
  "properties": {
    "gn:admin1_code":"24.0",
    "gn:admin2_code":"130.0",
    "gn:asciiname":"Mandwa",
    "gn:country_code":"IN",
    "gn:dem":469,
    "gn:feature_class":"P",
    "gn:feature_code":"PPL",
    "gn:name":"Mandwa",
    "gn:population":0,
    "gn:timezone":"Asia/Kolkata",
    "iso:country":"IN",
    "ks:ks_name":"Mandwa",
    "ks:ks_pop":750,
    "ks:ks_type":"VILLAGE",
    "name:eng_x_preferred":[
        "Mandwa"
    ],
    "wof:name":"Mandwa",
    "wof:placetype":"locality",
    "wof:population":750
},
  "geometry": {"coordinates":[73.275317,24.188468],"type":"Point"}
}