{
  "type": "Feature",
  "properties": {
    "gn:admin1_code":"35",
    "gn:admin2_code":"453.0",
    "gn:asciiname":"Deora",
    "gn:country_code":"IN",
    "gn:dem":693,
    "gn:feature_class":"P",
    "gn:feature_code":"PPL",
    "gn:name":"Deora",
    "gn:population":0,
    "gn:timezone":"Asia/Kolkata",
    "iso:country":"IN",
    "wof:name":"Deora",
    "wof:placetype":"locality"
},
  "geometry": {"coordinates":[81.08498,22.96885],"type":"Point"}
}