{
  "type": "Feature",
  "properties": {
    "iso:country":"IN",
    "ks:ks_name":"Bachai Reserved Forest",
    "ks:ks_type":"VILLAGE",
    "name:eng_x_preferred":[
        "Bachai Reserved Forest"
    ],
    "wof:name":"Bachai Reserved Forest",
    "wof:placetype":"locality"
},
  "geometry": {"coordinates":[79.289541,22.806809],"type":"Point"}
}