{
  "type": "Feature",
  "properties": {
    "iso:country":"IN",
    "ks:ks_name":"Mettuguda",
    "ks:ks_pop":24,
    "ks:ks_type":"HABITATION",
    "name:eng_x_preferred":[
        "Mettuguda"
    ],
    "wof:name":"Mettuguda",
    "wof:placetype":"locality",
    "wof:population":24
},
  "geometry": {"coordinates":[84.016238,18.786686],"type":"Point"}
}