{
  "type": "Feature",
  "properties": {
    "iso:country":"IN",
    "ks:ks_alt_nam":"Kuttiy\u0113ri",
    "ks:ks_name":"Kuttiyeri",
    "ks:ks_pop":10528,
    "ks:ks_type":"VILLAGE",
    "ks:ks_uagg_main":0,
    "name:eng_x_preferred":[
        "Kuttiyeri"
    ],
    "name:eng_x_variant":[
        "Kuttiy\u0113ri"
    ],
    "wof:name":"Kuttiyeri",
    "wof:placetype":"locality",
    "wof:population":10528
},
  "geometry": {"coordinates":[75.380257,12.075983],"type":"Point"}
}