{
  "type": "Feature",
  "properties": {
    "iso:country":"IN",
    "ks:ks_name":"Raynar",
    "ks:ks_pop":333,
    "ks:ks_type":"HABITATION",
    "name:eng_x_preferred":[
        "Raynar"
    ],
    "wof:name":"Raynar",
    "wof:placetype":"locality",
    "wof:population":333
},
  "geometry": {"coordinates":[80.96476199999999,19.728372],"type":"Point"}
}