{
  "type": "Feature",
  "properties": {
    "iso:country":"IN",
    "ks:ks_name":"Khutadi",
    "ks:ks_pop":115,
    "ks:ks_type":"VILLAGE",
    "name:eng_x_preferred":[
        "Khutadi"
    ],
    "wof:name":"Khutadi",
    "wof:placetype":"locality",
    "wof:population":115
},
  "geometry": {"coordinates":[86.376333,22.719082],"type":"Point"}
}