{
  "type": "Feature",
  "properties": {
    "iso:country":"IN",
    "ks:ks_name":"Hasekall",
    "ks:ks_pop":100,
    "ks:ks_type":"HABITATION",
    "name:eng_x_preferred":[
        "Hasekall"
    ],
    "wof:name":"Hasekall",
    "wof:placetype":"locality",
    "wof:population":100
},
  "geometry": {"coordinates":[74.85230799999999,14.865901],"type":"Point"}
}