{
  "type": "Feature",
  "properties": {
    "iso:country":"IN",
    "ks:ks_name":"Tiwarin Purwa",
    "ks:ks_pop":50,
    "ks:ks_type":"HABITATION",
    "name:eng_x_preferred":[
        "Tiwarin Purwa"
    ],
    "wof:name":"Tiwarin Purwa",
    "wof:placetype":"locality",
    "wof:population":50
},
  "geometry": {"coordinates":[80.996403,25.41316],"type":"Point"}
}