{
  "type": "Feature",
  "properties": {
    "gn:admin1_code":"24",
    "gn:asciiname":"Sirauli",
    "gn:country_code":"IN",
    "gn:dem":182,
    "gn:feature_class":"P",
    "gn:feature_code":"PPL",
    "gn:name":"Sirauli",
    "gn:population":0,
    "gn:timezone":"Asia/Kolkata",
    "iso:country":"IN",
    "name:bpy_x_preferred":[
        "\u09b8\u09bf\u09b0\u09be\u0989\u09b2\u09bf"
    ],
    "name:hin_x_preferred":[
        "\u0938\u093f\u0930\u094c\u0932\u0940 \u0917\u093e\u0901\u0935"
    ],
    "name:ita_x_preferred":[
        "Sirauli"
    ],
    "name:msa_x_preferred":[
        "Sirauli"
    ],
    "name:nld_x_preferred":[
        "Sirauli"
    ],
    "name:pol_x_preferred":[
        "Sirauli"
    ],
    "name:por_x_preferred":[
        "Sirauli"
    ],
    "name:urd_x_preferred":[
        "\u0633\u06cc\u0631\u0648\u0644\u06cc"
    ],
    "name:vie_x_preferred":[
        "Sirauli"
    ],
    "name:zho_x_preferred":[
        "\u897f\u52b3\u5229"
    ],
    "wof:name":"Sirauli",
    "wof:placetype":"locality"
},
  "geometry": {"coordinates":[77.57664,27.03751],"type":"Point"}
}