{
  "type": "Feature",
  "properties": {
    "iso:country":"IN",
    "ks:ks_alt_nam":"TELI TOLA",
    "ks:ks_name":"Teli Tola",
    "ks:ks_pop":345,
    "ks:ks_type":"HABITATION",
    "name:eng_x_preferred":[
        "Teli Tola"
    ],
    "wof:name":"Teli Tola",
    "wof:placetype":"locality",
    "wof:population":345
},
  "geometry": {"coordinates":[84.04625799999999,26.428523],"type":"Point"}
}