{
  "type": "Feature",
  "properties": {
    "iso:country":"IN",
    "ks:ks_name":"Chettuvatham",
    "ks:ks_pop":450,
    "ks:ks_type":"HABITATION",
    "name:eng_x_preferred":[
        "Chettuvatham"
    ],
    "wof:name":"Chettuvatham",
    "wof:placetype":"locality",
    "wof:population":450
},
  "geometry": {"coordinates":[76.730352,9.404384],"type":"Point"}
}