{
  "type": "Feature",
  "properties": {
    "iso:country":"IN",
    "ks:ks_alt_nam":"jodumanuguda",
    "ks:ks_name":"Jodumanuguda",
    "ks:ks_pop":118,
    "ks:ks_type":"HABITATION",
    "name:eng_x_preferred":[
        "Jodumanuguda"
    ],
    "wof:name":"Jodumanuguda",
    "wof:placetype":"locality",
    "wof:population":118
},
  "geometry": {"coordinates":[83.67167499999999,18.919843],"type":"Point"}
}