{
  "type": "Feature",
  "properties": {
    "gn:admin1_code":"16",
    "gn:admin2_code":"516.0",
    "gn:asciiname":"Jategaon",
    "gn:country_code":"IN",
    "gn:dem":619,
    "gn:feature_class":"P",
    "gn:feature_code":"PPL",
    "gn:name":"J\u0101tegaon",
    "gn:population":0,
    "gn:timezone":"Asia/Kolkata",
    "iso:country":"IN",
    "wof:name":"Jategaon",
    "wof:placetype":"locality"
},
  "geometry": {"coordinates":[74.87357,20.22912],"type":"Point"}
}