{
  "type": "Feature",
  "properties": {
    "gn:admin1_code":"35.0",
    "gn:admin2_code":"421.0",
    "gn:asciiname":"Birat",
    "gn:country_code":"IN",
    "gn:dem":190,
    "gn:feature_class":"P",
    "gn:feature_code":"PPL",
    "gn:name":"Bir\u0101t",
    "gn:population":0,
    "gn:timezone":"Asia/Kolkata",
    "iso:country":"IN",
    "name:ceb_x_preferred":[
        "Birat"
    ],
    "name:mai_x_preferred":[
        "\u092c\u093f\u0930\u093e\u091f"
    ],
    "name:msa_x_preferred":[
        "Birat"
    ],
    "name:nep_x_preferred":[
        "\u092c\u093f\u0930\u093e\u091f"
    ],
    "name:new_x_preferred":[
        "\u092c\u093f\u0930\u093e\u091f"
    ],
    "name:pol_x_preferred":[
        "Birat"
    ],
    "wof:name":"Birat",
    "wof:placetype":"neighbourhood"
},
  "geometry": {"coordinates":[78.45433,25.92084],"type":"Point"}
}