{
  "type": "Feature",
  "properties": {
    "gn:admin1_code":"39.0",
    "gn:admin2_code":"061",
    "gn:asciiname":"Sila",
    "gn:country_code":"IN",
    "gn:dem":692,
    "gn:feature_class":"P",
    "gn:feature_code":"PPL",
    "gn:name":"S\u012bla",
    "gn:population":0,
    "gn:timezone":"Asia/Kolkata",
    "iso:country":"IN",
    "name:bul_x_preferred":[
        "\u0421\u0438\u043b\u0430"
    ],
    "name:cat_x_preferred":[
        "Sila"
    ],
    "name:ceb_x_preferred":[
        "Sila"
    ],
    "name:dan_x_preferred":[
        "Sila"
    ],
    "name:deu_x_preferred":[
        "Sila"
    ],
    "name:fra_x_preferred":[
        "Sila"
    ],
    "name:hrv_x_preferred":[
        "Sila"
    ],
    "name:ita_x_preferred":[
        "Sila"
    ],
    "name:nld_x_preferred":[
        "Sila"
    ],
    "name:pol_x_preferred":[
        "Sila"
    ],
    "name:por_x_preferred":[
        "Sila"
    ],
    "name:rus_x_preferred":[
        "\u0421\u0438\u043b\u0430"
    ],
    "name:slk_x_preferred":[
        "Sila"
    ],
    "name:slv_x_preferred":[
        "Sila"
    ],
    "name:spa_x_preferred":[
        "Sila"
    ],
    "name:srp_x_preferred":[
        "Sila"
    ],
    "name:swe_x_preferred":[
        "Sila"
    ],
    "name:ukr_x_preferred":[
        "\u0421\u0438\u043b\u0430"
    ],
    "wof:name":"Sila",
    "wof:placetype":"locality"
},
  "geometry": {"coordinates":[78.68496999999998,29.94731],"type":"Point"}
}