{
  "type": "Feature",
  "properties": {
    "gn:admin1_code":"37",
    "gn:admin2_code":"403.0",
    "gn:asciiname":"Bhimsendih",
    "gn:country_code":"IN",
    "gn:dem":216,
    "gn:feature_class":"P",
    "gn:feature_code":"PPL",
    "gn:name":"Bh\u012bmsendih",
    "gn:population":0,
    "gn:timezone":"Asia/Kolkata",
    "iso:country":"IN",
    "wof:name":"Bhimsendih",
    "wof:placetype":"locality"
},
  "geometry": {"coordinates":[83.18701999999998,21.62077],"type":"Point"}
}