{
  "type": "Feature",
  "properties": {
    "gn:admin1_code":"11",
    "gn:admin2_code":"33.0",
    "gn:asciiname":"Loja",
    "gn:country_code":"IN",
    "gn:dem":1656,
    "gn:feature_class":"P",
    "gn:feature_code":"PPL",
    "gn:name":"Loja",
    "gn:population":0,
    "gn:timezone":"Asia/Kolkata",
    "iso:country":"IN",
    "wof:name":"Loja",
    "wof:placetype":"locality"
},
  "geometry": {"coordinates":[77.62971999999998,30.90519],"type":"Point"}
}