{
  "type": "Feature",
  "properties": {
    "gn:admin1_code":"11",
    "gn:admin2_code":"33.0",
    "gn:asciiname":"Loja",
    "gn:country_code":"IN",
    "gn:dem":1656,
    "gn:feature_class":"P",
    "gn:feature_code":"PPL",
    "gn:name":"Loja",
    "gn:population":0,
    "gn:timezone":"Asia/Kolkata",
    "iso:country":"IN",
    "name:cat_x_preferred":[
        "Loja"
    ],
    "name:ceb_x_preferred":[
        "Loja"
    ],
    "name:deu_x_preferred":[
        "Loja"
    ],
    "name:epo_x_preferred":[
        "Loja"
    ],
    "name:est_x_preferred":[
        "Loja"
    ],
    "name:eus_x_preferred":[
        "Loja"
    ],
    "name:fra_x_preferred":[
        "Loja"
    ],
    "name:glg_x_preferred":[
        "Loxa"
    ],
    "name:hrv_x_preferred":[
        "Loja"
    ],
    "name:hye_x_preferred":[
        "\u053c\u0578\u0575\u0561"
    ],
    "name:ita_x_preferred":[
        "Loja"
    ],
    "name:kaz_x_preferred":[
        "\u041b\u043e\u0445\u0430"
    ],
    "name:lav_x_preferred":[
        "Loja"
    ],
    "name:nld_x_preferred":[
        "Loja"
    ],
    "name:nor_x_preferred":[
        "Loja"
    ],
    "name:por_x_preferred":[
        "Loja"
    ],
    "name:rus_x_preferred":[
        "\u041b\u043e\u0445\u0430"
    ],
    "name:slk_x_preferred":[
        "Loja"
    ],
    "name:spa_x_preferred":[
        "Loja"
    ],
    "name:swe_x_preferred":[
        "Loja"
    ],
    "name:ukr_x_preferred":[
        "\u041b\u043e\u0445\u0430"
    ],
    "name:vol_x_preferred":[
        "Loja"
    ],
    "wof:name":"Loja",
    "wof:placetype":"locality"
},
  "geometry": {"coordinates":[77.62971999999998,30.90519],"type":"Point"}
}