{
  "type": "Feature",
  "properties": {
    "iso:country":"IN",
    "ks:ks_name":"Magada",
    "ks:ks_pop":66,
    "ks:ks_type":"VILLAGE",
    "name:eng_x_preferred":[
        "Magada"
    ],
    "wof:name":"Magada",
    "wof:placetype":"locality",
    "wof:population":66
},
  "geometry": {"coordinates":[84.259401,18.819401],"type":"Point"}
}