{
  "type": "Feature",
  "properties": {
    "iso:country":"IN",
    "ks:ks_name":"Digthali",
    "ks:ks_pop":4089,
    "ks:ks_type":"HABITATION",
    "name:eng_x_preferred":[
        "Digthali"
    ],
    "wof:name":"Digthali",
    "wof:placetype":"locality",
    "wof:population":4089
},
  "geometry": {"coordinates":[73.096417,24.340889],"type":"Point"}
}