{
  "type": "Feature",
  "properties": {
    "iso:country":"IN",
    "ks:ks_name":"Chavanwadi",
    "ks:ks_pop":47,
    "ks:ks_type":"HABITATION",
    "name:eng_x_preferred":[
        "Chavanwadi"
    ],
    "wof:name":"Chavanwadi",
    "wof:placetype":"locality",
    "wof:population":47
},
  "geometry": {"coordinates":[73.572579,16.141874],"type":"Point"}
}