{
  "type": "Feature",
  "properties": {
    "gn:admin1_code":"35",
    "gn:admin2_code":"430.0",
    "gn:asciiname":"Gagahana",
    "gn:country_code":"IN",
    "gn:dem":125,
    "gn:feature_class":"P",
    "gn:feature_code":"PPL",
    "gn:name":"Gagahana",
    "gn:population":0,
    "gn:timezone":"Asia/Kolkata",
    "iso:country":"IN",
    "ks:ks_name":"Gagahana",
    "ks:ks_pop":373,
    "ks:ks_type":"HABITATION",
    "name:eng_x_preferred":[
        "Gagahana"
    ],
    "wof:name":"Gagahana",
    "wof:placetype":"locality",
    "wof:population":373
},
  "geometry": {"coordinates":[81.40097299999999,24.986578],"type":"Point"}
}