{
  "type": "Feature",
  "properties": {
    "gn:admin1_code":"16.0",
    "gn:admin2_code":"508.0",
    "gn:asciiname":"Malengatta",
    "gn:country_code":"IN",
    "gn:dem":328,
    "gn:feature_class":"P",
    "gn:feature_code":"PPL",
    "gn:name":"M\u0101lengatta",
    "gn:population":0,
    "gn:timezone":"Asia/Kolkata",
    "iso:country":"IN",
    "ks:ks_name":"Malangatta",
    "ks:ks_pop":91,
    "ks:ks_type":"VILLAGE",
    "name:eng_x_preferred":[
        "Malangatta"
    ],
    "name:eng_x_variant":[
        "Malengatta"
    ],
    "wof:name":"Malangatta",
    "wof:placetype":"locality",
    "wof:population":91
},
  "geometry": {"coordinates":[80.36056600000001,19.981599],"type":"Point"}
}