{
  "type": "Feature",
  "properties": {
    "iso:country":"IN",
    "ks:ks_name":"Dakshin Janardanpur",
    "ks:ks_pop":2456,
    "ks:ks_type":"VILLAGE",
    "ks:ks_uagg_main":0,
    "name:eng_x_preferred":[
        "Dakshin Janardanpur"
    ],
    "wof:name":"Dakshin Janardanpur",
    "wof:placetype":"neighbourhood",
    "wof:population":2456
},
  "geometry": {"coordinates":[88.30243900000001,22.019576],"type":"Point"}
}