{
  "type": "Feature",
  "properties": {
    "iso:country":"IN",
    "ks:ks_alt_nam":"M\u0101rikel",
    "ks:ks_name":"Marikel",
    "ks:ks_pop":185,
    "ks:ks_type":"VILLAGE",
    "name:eng_x_preferred":[
        "Marikel"
    ],
    "name:eng_x_variant":[
        "M\u0101rikel"
    ],
    "wof:name":"Marikel",
    "wof:placetype":"locality",
    "wof:population":185
},
  "geometry": {"coordinates":[85.01820499999999,22.559244],"type":"Point"}
}