{
  "type": "Feature",
  "properties": {
    "gn:admin1_code":"40",
    "gn:admin2_code":"538.0",
    "gn:asciiname":"Venkatagiri",
    "gn:country_code":"IN",
    "gn:dem":515,
    "gn:feature_class":"P",
    "gn:feature_code":"PPL",
    "gn:name":"Venkatagiri",
    "gn:population":0,
    "gn:timezone":"Asia/Kolkata",
    "iso:country":"IN",
    "name:bpy_x_preferred":[
        "\u09ac\u09c7\u09a8\u0995\u09be\u09a4\u09be\u0997\u09bf\u09b0\u09bf"
    ],
    "name:cat_x_preferred":[
        "Venkatagiri"
    ],
    "name:ceb_x_preferred":[
        "Venkatagiri"
    ],
    "name:fas_x_preferred":[
        "\u0648\u0646\u06a9\u062a\u06af\u06cc\u0631\u06cc"
    ],
    "name:fra_x_preferred":[
        "Venkatagiri"
    ],
    "name:hif_x_preferred":[
        "Venkatagiri"
    ],
    "name:ita_x_preferred":[
        "Venkatagiri"
    ],
    "name:jpn_x_preferred":[
        "\u30f4\u30a7\u30f3\u30ab\u30bf\u30ae\u30ea"
    ],
    "name:msa_x_preferred":[
        "Venkatagiri"
    ],
    "name:new_x_preferred":[
        "\u0935\u0947\u0902\u0915\u091f\u0917\u093f\u0930\u093f"
    ],
    "name:nld_x_preferred":[
        "Venkatagiri"
    ],
    "name:por_x_preferred":[
        "Venkatagiri"
    ],
    "name:swe_x_preferred":[
        "Venkatagiri"
    ],
    "name:tel_x_preferred":[
        "\u0c35\u0c46\u0c02\u0c15\u0c1f\u0c17\u0c3f\u0c30\u0c3f"
    ],
    "name:urd_x_preferred":[
        "\u0648\u06cc\u0646\u06a9\u0679\u0627\u06af\u0631\u06cc"
    ],
    "name:vie_x_preferred":[
        "Venkatagiri"
    ],
    "name:zho_x_preferred":[
        "\u6587\u5361\u5854\u5409\u91cc"
    ],
    "wof:name":"Venkatagiri",
    "wof:placetype":"locality"
},
  "geometry": {"coordinates":[78.62942,16.30182000000001],"type":"Point"}
}