{
  "type": "Feature",
  "properties": {
    "gn:country":"IN",
    "gn:fcode":"PPL",
    "gn:pop":15480,
    "iso:country":"IN",
    "name:ben_x_preferred":[
        "\u09b9\u09cb\u09b2\u09be\u09b2\u0995\u09c7\u09b0\u09c7"
    ],
    "name:bpy_x_preferred":[
        "\u09b9\u09cb\u09b2\u09be\u09b2\u0995\u09c7\u09b0\u09c7"
    ],
    "name:bul_x_preferred":[
        "\u0425\u043e\u043b\u0430\u043b\u043a\u0435\u0440\u0435"
    ],
    "name:ceb_x_preferred":[
        "Holalkere"
    ],
    "name:deu_x_preferred":[
        "Holalkere"
    ],
    "name:eng_x_preferred":[
        "Holalkere"
    ],
    "name:fra_x_preferred":[
        "Holalkere"
    ],
    "name:guj_x_preferred":[
        "\u0ab9\u0acb\u0ab2\u0ab2\u0a95\u0ac7\u0ab0"
    ],
    "name:ita_x_preferred":[
        "Holalkere"
    ],
    "name:jpn_x_preferred":[
        "\u30ab\u30ea\u30e0\u30dd\u30f3\u30b0"
    ],
    "name:kan_x_preferred":[
        "\u0cb9\u0cca\u0cb3\u0cb2\u0ccd\u0c95\u0cc6\u0cb0\u0cc6"
    ],
    "name:kor_x_preferred":[
        "\ud640\ub784\ucee4\ub7ec"
    ],
    "name:mlg_x_preferred":[
        "Holalkere"
    ],
    "name:msa_x_preferred":[
        "Holalkere"
    ],
    "name:nan_x_preferred":[
        "Holalkere"
    ],
    "name:new_x_preferred":[
        "\u0939\u094b\u0932\u093e\u0932\u0915\u0947\u0930\u0947"
    ],
    "name:nld_x_preferred":[
        "Holalkere"
    ],
    "name:por_x_preferred":[
        "Holalkere"
    ],
    "name:rus_x_preferred":[
        "\u0425\u043e\u043b\u0430\u043b\u043a\u0435\u0440\u0435"
    ],
    "name:spa_x_preferred":[
        "Holalkere"
    ],
    "name:swe_x_preferred":[
        "Holalkere"
    ],
    "name:tam_x_preferred":[
        "\u0bb9\u0bcb\u0bb2\u0bbe\u0bb2\u0bcd\u0b95\u0bbf\u0bb0\u0bc7"
    ],
    "name:tel_x_preferred":[
        "\u0c39\u0c4b\u0c32\u0c3e\u0c32\u0c4d\u0c15\u0c47\u0c30\u0c47"
    ],
    "name:unk_x_variant":[
        "Holalkere"
    ],
    "name:urd_x_preferred":[
        "\u06c1\u0648\u0644\u0627\u0644\u06a9\u06cc\u0631\u06cc"
    ],
    "name:vie_x_preferred":[
        "Holalkere"
    ],
    "name:zho_x_preferred":[
        "\u970d\u62c9\u5c14\u51ef\u96f7"
    ],
    "qs:name":"Hosakere",
    "qs:name_adm0":"India",
    "qs:name_adm1":"Karnataka",
    "qs:photos_9r":0,
    "qs:photos_sr":0,
    "qs:placetype":"Town",
    "qs:pop_sr":"6",
    "wof:name":"Hosakere",
    "wof:placetype":"locality",
    "wof:population":15480
},
  "geometry": {"coordinates":[76.18424,14.04262],"type":"Point"}
}