{
  "type": "Feature",
  "properties": {
    "gn:country":"IN",
    "gn:fcode":"PPL",
    "gn:population":6468,
    "iso:country":"IN",
    "name:ast_x_preferred":[
        "Kumsi"
    ],
    "name:bul_x_preferred":[
        "\u041a\u0443\u043c\u0441\u0438"
    ],
    "name:ceb_x_preferred":[
        "Kumsi"
    ],
    "name:eng_x_preferred":[
        "Kumsi"
    ],
    "name:nld_x_preferred":[
        "Kumsi"
    ],
    "name:swe_x_preferred":[
        "Kumsi"
    ],
    "qs:name":"Kumsi",
    "qs:name_adm0":"India",
    "qs:name_adm1":"Karnataka",
    "qs:photos_9k":1,
    "qs:photos_9r":1,
    "qs:photos_all":1,
    "qs:photos_sr":0,
    "qs:placetype":"Town",
    "qs:pop_sr":"5",
    "wd:wordcount":93,
    "wof:name":"Kumsi",
    "wof:placetype":"locality",
    "wof:population":6468
},
  "geometry": {"coordinates":[75.39991999999999,14.05455],"type":"Point"}
}