{
  "type": "Feature",
  "properties": {
    "gn:admin1_code":"39.0",
    "gn:admin2_code":"032",
    "gn:asciiname":"Bhuddi",
    "gn:country_code":"IN",
    "gn:dem":453,
    "gn:feature_class":"P",
    "gn:feature_code":"PPL",
    "gn:name":"Bhuddi",
    "gn:population":0,
    "gn:timezone":"Asia/Kolkata",
    "iso:country":"IN",
    "wof:name":"Bhuddi",
    "wof:placetype":"locality"
},
  "geometry": {"coordinates":[77.75064999999999,30.49375],"type":"Point"}
}