{
  "type": "Feature",
  "properties": {
    "gn:admin1_code":"36",
    "gn:admin2_code":"191.0",
    "gn:asciiname":"Surahia",
    "gn:country_code":"IN",
    "gn:dem":81,
    "gn:feature_class":"P",
    "gn:feature_code":"PPL",
    "gn:name":"Sur\u0101hia",
    "gn:population":0,
    "gn:timezone":"Asia/Kolkata",
    "iso:country":"IN",
    "ks:ks_alt_nam":"Sur\u0101hia",
    "ks:ks_name":"Surahia",
    "ks:ks_type":"VILLAGE",
    "ks:ks_uagg_main":0,
    "name:eng_x_preferred":[
        "Surahia"
    ],
    "name:eng_x_variant":[
        "Sur\u0101hia"
    ],
    "wof:name":"Surahia",
    "wof:placetype":"locality"
},
  "geometry": {"coordinates":[83.121545,26.017574],"type":"Point"}
}