{
  "type": "Feature",
  "properties": {
    "iso:country":"IN",
    "ks:ks_name":"Bhatauli Buzurg",
    "ks:ks_pop":4238,
    "ks:ks_type":"VILLAGE",
    "ks:ks_uagg_main":0,
    "name:eng_x_preferred":[
        "Bhatauli Buzurg"
    ],
    "wof:name":"Bhatauli Buzurg",
    "wof:placetype":"neighbourhood",
    "wof:population":4238
},
  "geometry": {"coordinates":[83.63399,26.61154],"type":"Point"}
}