{
  "type": "Feature",
  "properties": {
    "gn:admin1_code":"25.0",
    "gn:admin2_code":"630.0",
    "gn:asciiname":"Gollappatti",
    "gn:country_code":"IN",
    "gn:dem":548,
    "gn:feature_class":"P",
    "gn:feature_code":"PPL",
    "gn:name":"Gollappatti",
    "gn:population":0,
    "gn:timezone":"Asia/Kolkata",
    "iso:country":"IN",
    "wof:name":"Gollappatti",
    "wof:placetype":"locality"
},
  "geometry": {"coordinates":[78.00898000000002,12.22971],"type":"Point"}
}