{
  "type": "Feature",
  "properties": {
    "gn:admin1_code":"25.0",
    "gn:admin2_code":"630.0",
    "gn:asciiname":"Gollappatti",
    "gn:country_code":"IN",
    "gn:dem":548,
    "gn:feature_class":"P",
    "gn:feature_code":"PPL",
    "gn:name":"Gollappatti",
    "gn:population":0,
    "gn:timezone":"Asia/Kolkata",
    "iso:country":"IN",
    "ks:ks_name":"Gollapatti",
    "ks:ks_pop":2500,
    "ks:ks_type":"HABITATION",
    "name:eng_x_preferred":[
        "Gollapatti"
    ],
    "name:eng_x_variant":[
        "Gollappatti"
    ],
    "wof:name":"Gollapatti",
    "wof:placetype":"locality",
    "wof:population":2500
},
  "geometry": {"coordinates":[78.01648,12.247507],"type":"Point"}
}