{
  "type": "Feature",
  "properties": {
    "iso:country":"IN",
    "ks:ks_name":"Uper Tola",
    "ks:ks_pop":136,
    "ks:ks_type":"HABITATION",
    "name:eng_x_preferred":[
        "Uper Tola"
    ],
    "wof:name":"Uper Tola",
    "wof:placetype":"locality",
    "wof:population":136
},
  "geometry": {"coordinates":[85.574482,22.650755],"type":"Point"}
}