{
  "type": "Feature",
  "properties": {
    "iso:country":"IN",
    "ks:ks_name":"No.2 Mainapara Miri",
    "ks:ks_pop":310,
    "ks:ks_type":"VILLAGE",
    "ks:ks_uagg_main":0,
    "name:eng_x_preferred":[
        "No.2 Mainapara Miri"
    ],
    "wof:name":"No.2 Mainapara Miri",
    "wof:placetype":"neighbourhood",
    "wof:population":310
},
  "geometry": {"coordinates":[94.34350499999999,27.437451],"type":"Point"}
}