{
  "type": "Feature",
  "properties": {
    "iso:country":"IN",
    "ks:ks_name":"Karada",
    "ks:ks_pop":662,
    "ks:ks_type":"HABITATION",
    "name:eng_x_preferred":[
        "Karada"
    ],
    "wof:name":"Karada",
    "wof:placetype":"locality",
    "wof:population":662
},
  "geometry": {"coordinates":[86.71509,24.680567],"type":"Point"}
}