{
  "type": "Feature",
  "properties": {
    "iso:country":"IN",
    "ks:ks_name":"Valluvar Colony",
    "ks:ks_pop":160,
    "ks:ks_type":"HABITATION",
    "name:eng_x_preferred":[
        "Valluvar Colony"
    ],
    "wof:name":"Valluvar Colony",
    "wof:placetype":"locality",
    "wof:population":160
},
  "geometry": {"coordinates":[79.68172800000001,12.680822],"type":"Point"}
}