{
  "type": "Feature",
  "properties": {
    "gn:admin1_code":"34",
    "gn:admin2_code":"218.0",
    "gn:asciiname":"Shahganj",
    "gn:country_code":"IN",
    "gn:dem":67,
    "gn:feature_class":"P",
    "gn:feature_code":"PPL",
    "gn:name":"Sh\u0101hganj",
    "gn:population":0,
    "gn:timezone":"Asia/Kolkata",
    "iso:country":"IN",
    "ks:ks_name":"Shahganj",
    "ks:ks_pop":405,
    "ks:ks_type":"VILLAGE",
    "ks:ks_uagg_main":0,
    "name:bpy_x_preferred":[
        "\u09b8\u09be\u09b9\u0997\u099e\u09cd\u099c"
    ],
    "name:eng_x_preferred":[
        "Shahganj"
    ],
    "name:fas_x_preferred":[
        "\u0634\u0627\u0647\u200c\u06af\u0646\u062c"
    ],
    "name:ita_x_preferred":[
        "Shahganj"
    ],
    "name:mlg_x_preferred":[
        "Shahganj"
    ],
    "name:msa_x_preferred":[
        "Shahganj"
    ],
    "name:nld_x_preferred":[
        "Shahganj"
    ],
    "name:ori_x_preferred":[
        "\u0b36\u0b3e\u0b39\u0b17\u0b1e\u0b4d\u0b1c"
    ],
    "name:pnb_x_preferred":[
        "\u0634\u0627\u06c1 \u06af\u0646\u062c"
    ],
    "name:pol_x_preferred":[
        "Shahganj"
    ],
    "name:por_x_preferred":[
        "Shahganj"
    ],
    "name:urd_x_preferred":[
        "\u0634\u0627\u06c1 \u06af\u0646\u062c"
    ],
    "name:vie_x_preferred":[
        "Shahganj"
    ],
    "name:zho_x_preferred":[
        "\u65af\u54c8\u8d6b\u7518\u6770"
    ],
    "wof:name":"Shahganj",
    "wof:placetype":"neighbourhood",
    "wof:population":405
},
  "geometry": {"coordinates":[84.45366,26.162587],"type":"Point"}
}