{
  "type": "Feature",
  "properties": {
    "iso:country":"IN",
    "ks:ks_name":"Hedvali",
    "ks:ks_pop":177,
    "ks:ks_type":"VILLAGE",
    "name:eng_x_preferred":[
        "Hedvali"
    ],
    "wof:name":"Hedvali",
    "wof:placetype":"locality",
    "wof:population":177
},
  "geometry": {"coordinates":[73.29174,18.637461],"type":"Point"}
}