{
  "type": "Feature",
  "properties": {
    "iso:country":"IN",
    "ks:ks_name":"Bhinarwai",
    "ks:ks_pop":100,
    "ks:ks_type":"HABITATION",
    "name:eng_x_preferred":[
        "Bhinarwai"
    ],
    "wof:name":"Bhinarwai",
    "wof:placetype":"locality",
    "wof:population":100
},
  "geometry": {"coordinates":[73.27036699999999,18.330077],"type":"Point"}
}