{
  "type": "Feature",
  "properties": {
    "iso:country":"IN",
    "ks:ks_name":"Balbhadra Chak",
    "ks:ks_pop":1114,
    "ks:ks_type":"VILLAGE",
    "ks:ks_uagg_main":0,
    "name:eng_x_preferred":[
        "Balbhadra Chak"
    ],
    "wof:name":"Balbhadra Chak",
    "wof:placetype":"neighbourhood",
    "wof:population":1114
},
  "geometry": {"coordinates":[87.74984600000001,22.204857],"type":"Point"}
}