{
  "type": "Feature",
  "properties": {
    "gn:admin1_code":"35.0",
    "gn:admin2_code":"455.0",
    "gn:asciiname":"Harshdiwari",
    "gn:country_code":"IN",
    "gn:dem":572,
    "gn:feature_class":"P",
    "gn:feature_code":"PPL",
    "gn:name":"Harshdiw\u0101ri",
    "gn:population":0,
    "gn:timezone":"Asia/Kolkata",
    "iso:country":"IN",
    "ks:ks_alt_nam":"Harshdiw\u0101ri",
    "ks:ks_name":"Harshdiwari",
    "ks:ks_type":"VILLAGE",
    "name:eng_x_preferred":[
        "Harshdiwari"
    ],
    "name:eng_x_variant":[
        "Harshdiw\u0101ri"
    ],
    "wof:name":"Harshdiwari",
    "wof:placetype":"locality"
},
  "geometry": {"coordinates":[78.575592,22.380159],"type":"Point"}
}