{
  "type": "Feature",
  "properties": {
    "iso:country":"IN",
    "ks:ks_name":"Alladigadde",
    "ks:ks_pop":83,
    "ks:ks_type":"HABITATION",
    "name:eng_x_preferred":[
        "Alladigadde"
    ],
    "wof:name":"Alladigadde",
    "wof:placetype":"locality",
    "wof:population":83
},
  "geometry": {"coordinates":[74.70122600000001,14.353572],"type":"Point"}
}