{
  "type": "Feature",
  "properties": {
    "iso:country":"IN",
    "ks:ks_alt_nam":"hemmane",
    "ks:ks_name":"Hemmane",
    "ks:ks_pop":25,
    "ks:ks_type":"HABITATION",
    "name:eng_x_preferred":[
        "Hemmane"
    ],
    "wof:name":"Hemmane",
    "wof:placetype":"locality",
    "wof:population":25
},
  "geometry": {"coordinates":[75.181659,13.537411],"type":"Point"}
}