{
  "type": "Feature",
  "properties": {
    "iso:country":"IN",
    "ks:ks_name":"Piparkhand",
    "ks:ks_pop":764,
    "ks:ks_type":"HABITATION",
    "name:eng_x_preferred":[
        "Piparkhand"
    ],
    "wof:name":"Piparkhand",
    "wof:placetype":"locality",
    "wof:population":764
},
  "geometry": {"coordinates":[82.94009200000001,24.415654],"type":"Point"}
}