{
  "type": "Feature",
  "properties": {
    "gn:admin1_code":"16.0",
    "gn:admin2_code":"514.0",
    "gn:asciiname":"Belur",
    "gn:country_code":"IN",
    "gn:dem":564,
    "gn:feature_class":"P",
    "gn:feature_code":"PPL",
    "gn:name":"Bel\u016br",
    "gn:population":0,
    "gn:timezone":"Asia/Kolkata",
    "iso:country":"IN",
    "name:msa_x_preferred":[
        "Belur"
    ],
    "wof:name":"Belur",
    "wof:placetype":"locality"
},
  "geometry": {"coordinates":[75.77715999999999,20.16842],"type":"Point"}
}