{
  "type": "Feature",
  "properties": {
    "gn:admin1_code":"39.0",
    "gn:admin2_code":"061",
    "gn:asciiname":"Jitugaon",
    "gn:country_code":"IN",
    "gn:dem":1238,
    "gn:feature_class":"P",
    "gn:feature_code":"PPL",
    "gn:name":"J\u012btugaon",
    "gn:population":0,
    "gn:timezone":"Asia/Kolkata",
    "iso:country":"IN",
    "wof:name":"Jitugaon",
    "wof:placetype":"locality"
},
  "geometry": {"coordinates":[78.60531999999998,29.96533],"type":"Point"}
}