{
  "type": "Feature",
  "properties": {
    "iso:country":"IN",
    "ks:ks_name":"Andrapa",
    "ks:ks_pop":775,
    "ks:ks_type":"VILLAGE",
    "name:eng_x_preferred":[
        "Andrapa"
    ],
    "wof:name":"Andrapa",
    "wof:placetype":"locality",
    "wof:population":775
},
  "geometry": {"coordinates":[79.269678,30.023539],"type":"Point"}
}