{
  "type": "Feature",
  "properties": {
    "gn:admin1_code":"19.0",
    "gn:admin2_code":"561.0",
    "gn:asciiname":"Hosur",
    "gn:country_code":"IN",
    "gn:dem":719,
    "gn:feature_class":"P",
    "gn:feature_code":"PPL",
    "gn:name":"Hos\u016br",
    "gn:population":0,
    "gn:timezone":"Asia/Kolkata",
    "iso:country":"IN",
    "name:bih_x_preferred":[
        "\u0939\u094b\u0938\u0941\u0930"
    ],
    "name:bpy_x_preferred":[
        "\u09b9\u09cb\u09b8\u09c1\u09b0"
    ],
    "name:cat_x_preferred":[
        "Hosur"
    ],
    "name:ceb_x_preferred":[
        "Hos\u016br"
    ],
    "name:deu_x_preferred":[
        "Hosur"
    ],
    "name:hin_x_preferred":[
        "\u0939\u094b\u0938\u0942\u0930"
    ],
    "name:ita_x_preferred":[
        "Hosur"
    ],
    "name:kan_x_preferred":[
        "\u0cb9\u0cca\u0cb8\u0cc2\u0cb0\u0cc1"
    ],
    "name:mar_x_preferred":[
        "\u0939\u094b\u0938\u0942\u0930"
    ],
    "name:mlg_x_preferred":[
        "Hosur"
    ],
    "name:msa_x_preferred":[
        "Hosur"
    ],
    "name:new_x_preferred":[
        "\u0939\u094b\u0938\u0941\u0930"
    ],
    "name:spa_x_preferred":[
        "Hosur"
    ],
    "name:swe_x_preferred":[
        "Hosur"
    ],
    "name:tam_x_preferred":[
        "\u0b93\u0b9a\u0bc2\u0bb0\u0bcd"
    ],
    "name:urd_x_preferred":[
        "\u06c1\u0648\u0633\u0648\u0631"
    ],
    "name:vie_x_preferred":[
        "Hosur"
    ],
    "name:zho_x_preferred":[
        "\u970d\u82cf\u5c14"
    ],
    "wof:name":"Hosur",
    "wof:placetype":"locality"
},
  "geometry": {"coordinates":[75.57374,15.30001],"type":"Point"}
}