{
  "type": "Feature",
  "properties": {
    "iso:country":"IN",
    "ks:ks_name":"Shettikoppa",
    "ks:ks_pop":25,
    "ks:ks_type":"HABITATION",
    "name:eng_x_preferred":[
        "Shettikoppa"
    ],
    "wof:name":"Shettikoppa",
    "wof:placetype":"locality",
    "wof:population":25
},
  "geometry": {"coordinates":[74.79705300000001,14.885077],"type":"Point"}
}