{
  "type": "Feature",
  "properties": {
    "iso:country":"IN",
    "ks:ks_alt_nam":"oramtola",
    "ks:ks_name":"Oramtola",
    "ks:ks_pop":301,
    "ks:ks_type":"HABITATION",
    "name:eng_x_preferred":[
        "Oramtola"
    ],
    "wof:name":"Oramtola",
    "wof:placetype":"locality",
    "wof:population":301
},
  "geometry": {"coordinates":[84.977512,22.25555],"type":"Point"}
}