{
  "type": "Feature",
  "properties": {
    "iso:country":"IN",
    "ks:ks_name":"Dakshin Adaberia",
    "ks:ks_pop":559,
    "ks:ks_type":"VILLAGE",
    "ks:ks_uagg_main":0,
    "name:eng_x_preferred":[
        "Dakshin Adaberia"
    ],
    "wof:name":"Dakshin Adaberia",
    "wof:placetype":"locality",
    "wof:population":559
},
  "geometry": {"coordinates":[87.798219,21.778779],"type":"Point"}
}