{
  "type": "Feature",
  "properties": {
    "gn:admin1_code":"19.0",
    "gn:admin2_code":"574.0",
    "gn:asciiname":"Shingatgere",
    "gn:country_code":"IN",
    "gn:dem":920,
    "gn:feature_class":"P",
    "gn:feature_code":"PPL",
    "gn:name":"Shingatg\u0113re",
    "gn:population":0,
    "gn:timezone":"Asia/Kolkata",
    "iso:country":"IN",
    "wof:name":"Shingatgere",
    "wof:placetype":"locality"
},
  "geometry": {"coordinates":[75.96055,12.92272],"type":"Point"}
}