{
  "type": "Feature",
  "properties": {
    "gn:admin1_code":"19.0",
    "gn:admin2_code":"573.0",
    "gn:asciiname":"Hariharapura",
    "gn:country_code":"IN",
    "gn:dem":778,
    "gn:feature_class":"P",
    "gn:feature_code":"PPL",
    "gn:name":"Hariharapura",
    "gn:population":0,
    "gn:timezone":"Asia/Kolkata",
    "iso:country":"IN",
    "name:kan_x_preferred":[
        "\u0cb9\u0cb0\u0cbf\u0cb9\u0cb0\u0caa\u0cc1\u0cb0"
    ],
    "name:vie_x_preferred":[
        "Hariharapura"
    ],
    "wof:name":"Hariharapura",
    "wof:placetype":"locality"
},
  "geometry": {"coordinates":[76.41584,12.60998],"type":"Point"}
}