{
  "type": "Feature",
  "properties": {
    "iso:country":"IN",
    "ks:ks_name":"Kismatnafrai",
    "ks:ks_pop":232,
    "ks:ks_type":"VILLAGE",
    "ks:ks_uagg_main":0,
    "name:eng_x_preferred":[
        "Kismatnafrai"
    ],
    "wof:name":"Kismatnafrai",
    "wof:placetype":"locality",
    "wof:population":232
},
  "geometry": {"coordinates":[87.403025,21.606653],"type":"Point"}
}