{
  "type": "Feature",
  "properties": {
    "iso:country":"IN",
    "ks:ks_alt_nam":"L\u0101jora",
    "ks:ks_name":"Lajora",
    "ks:ks_pop":615,
    "ks:ks_type":"VILLAGE",
    "name:eng_x_preferred":[
        "Lajora"
    ],
    "name:eng_x_variant":[
        "L\u0101jora"
    ],
    "wof:name":"Lajora",
    "wof:placetype":"locality",
    "wof:population":615
},
  "geometry": {"coordinates":[85.399001,22.479495],"type":"Point"}
}