{
  "type": "Feature",
  "properties": {
    "iso:country":"IN",
    "ks:ks_name":"Vinaitheerthapuram",
    "ks:ks_pop":549,
    "ks:ks_type":"HABITATION",
    "ks:ks_uagg_main":0,
    "name:eng_x_preferred":[
        "Vinaitheerthapuram"
    ],
    "wof:name":"Vinaitheerthapuram",
    "wof:placetype":"neighbourhood",
    "wof:population":549
},
  "geometry": {"coordinates":[78.17603200000001,11.321174],"type":"Point"}
}