{
  "type": "Feature",
  "properties": {
    "gn:admin1_code":"39.0",
    "gn:admin2_code":"67.0",
    "gn:asciiname":"Phulpur",
    "gn:country_code":"IN",
    "gn:dem":199,
    "gn:feature_class":"P",
    "gn:feature_code":"PPL",
    "gn:name":"Ph\u016blpur",
    "gn:population":0,
    "gn:timezone":"Asia/Kolkata",
    "iso:country":"IN",
    "name:ara_x_preferred":[
        "\u0628\u0648\u0644\u0628\u0648\u0631"
    ],
    "name:ben_bn_x_preferred":[
        "\u09ab\u09c1\u09b2\u09aa\u09c1\u09b0"
    ],
    "name:ben_in_x_preferred":[
        "\u09ab\u09c1\u09b2\u09aa\u09c1\u09b0"
    ],
    "name:guj_x_preferred":[
        "\u0aab\u0ac1\u0ab2\u0aaa\u0ac1\u0ab0"
    ],
    "name:hin_x_preferred":[
        "\u092b\u0942\u0932\u092a\u0941\u0930"
    ],
    "name:ita_x_preferred":[
        "Phulpur"
    ],
    "name:kan_x_preferred":[
        "\u0cab\u0cc2\u0cb2\u0ccd"
    ],
    "name:mal_x_preferred":[
        "\u0d2b\u0d42\u0d7d\u0d2a\u0d42\u0d7c"
    ],
    "name:mar_x_preferred":[
        "\u092b\u0942\u0932\u092a\u0942\u0930"
    ],
    "name:pan_x_preferred":[
        "\u0a2b\u0a41\u0a32\u0a2a\u0a41\u0a30"
    ],
    "name:pol_x_preferred":[
        "Phulpur"
    ],
    "name:tam_x_preferred":[
        "\u0b83\u0baa\u0bc1\u0bb2\u0bcd\u0baa\u0bc1\u0bb0\u0bcd"
    ],
    "name:tel_x_preferred":[
        "\u0c2b\u0c41\u0c32\u0c4d"
    ],
    "name:urd_x_preferred":[
        "\u067e\u06be\u0648\u0644\u067e\u0648\u0631"
    ],
    "wof:name":"Phulpur",
    "wof:placetype":"locality"
},
  "geometry": {"coordinates":[79.41744,28.9006],"type":"Point"}
}