{
  "type": "Feature",
  "properties": {
    "iso:country":"IN",
    "ks:ks_name":"Rathava Faliya",
    "ks:ks_pop":215,
    "ks:ks_type":"HABITATION",
    "name:eng_x_preferred":[
        "Rathava Faliya"
    ],
    "wof:name":"Rathava Faliya",
    "wof:placetype":"locality",
    "wof:population":215
},
  "geometry": {"coordinates":[73.509467,22.7838],"type":"Point"}
}