{
  "type": "Feature",
  "properties": {
    "iso:country":"IN",
    "ks:ks_name":"Matur Bigha",
    "ks:ks_pop":219,
    "ks:ks_type":"HABITATION",
    "name:eng_x_preferred":[
        "Matur Bigha"
    ],
    "wof:name":"Matur Bigha",
    "wof:placetype":"locality",
    "wof:population":219
},
  "geometry": {"coordinates":[84.50948,25.042683],"type":"Point"}
}