{
  "type": "Feature",
  "properties": {
    "iso:country":"IN",
    "ks:ks_name":"Sujan Bigha",
    "ks:ks_pop":494,
    "ks:ks_type":"HABITATION",
    "name:eng_x_preferred":[
        "Sujan Bigha"
    ],
    "wof:name":"Sujan Bigha",
    "wof:placetype":"locality",
    "wof:population":494
},
  "geometry": {"coordinates":[85.608215,25.220587],"type":"Point"}
}