{
  "type": "Feature",
  "properties": {
    "iso:country":"IN",
    "ks:ks_name":"Talagere",
    "ks:ks_pop":85,
    "ks:ks_type":"HABITATION",
    "name:eng_x_preferred":[
        "Talagere"
    ],
    "wof:name":"Talagere",
    "wof:placetype":"locality",
    "wof:population":85
},
  "geometry": {"coordinates":[74.49244,14.425774],"type":"Point"}
}