{
  "type": "Feature",
  "properties": {
    "iso:country":"IN",
    "ks:ks_alt_nam":"Murabai doddi",
    "ks:ks_name":"Murabai Doddi",
    "ks:ks_pop":411,
    "ks:ks_type":"HABITATION",
    "name:eng_x_preferred":[
        "Murabai Doddi"
    ],
    "wof:name":"Murabai Doddi",
    "wof:placetype":"locality",
    "wof:population":411
},
  "geometry": {"coordinates":[83.142517,17.603589],"type":"Point"}
}