{
  "type": "Feature",
  "properties": {
    "iso:country":"IN",
    "ks:ks_name":"Nalani Pum Konch",
    "ks:ks_pop":1042,
    "ks:ks_type":"VILLAGE",
    "ks:ks_uagg_main":0,
    "name:eng_x_preferred":[
        "Nalani Pum Konch"
    ],
    "wof:name":"Nalani Pum Konch",
    "wof:placetype":"neighbourhood",
    "wof:population":1042
},
  "geometry": {"coordinates":[94.556833,27.467657],"type":"Point"}
}