{
  "type": "Feature",
  "properties": {
    "iso:country":"IN",
    "ks:ks_name":"Kantabad",
    "ks:ks_pop":0,
    "ks:ks_type":"VILLAGE",
    "name:eng_x_preferred":[
        "Kantabad"
    ],
    "wof:name":"Kantabad",
    "wof:placetype":"locality",
    "wof:population":0
},
  "geometry": {"coordinates":[85.7077,20.33424],"type":"Point"}
}