{
  "type": "Feature",
  "properties": {
    "gn:admin1_code":"38.0",
    "gn:admin2_code":"358",
    "gn:asciiname":"Chhatarpur",
    "gn:country_code":"IN",
    "gn:dem":272,
    "gn:feature_class":"P",
    "gn:feature_code":"PPL",
    "gn:name":"Chhatarpur",
    "gn:population":0,
    "gn:timezone":"Asia/Kolkata",
    "iso:country":"IN",
    "wof:name":"Chhatarpur",
    "wof:placetype":"locality"
},
  "geometry": {"coordinates":[84.18675,24.36746],"type":"Point"}
}