{
  "type": "Feature",
  "properties": {
    "gn:admin1_code":"38.0",
    "gn:admin2_code":"358",
    "gn:asciiname":"Chhatarpur",
    "gn:country_code":"IN",
    "gn:dem":272,
    "gn:feature_class":"P",
    "gn:feature_code":"PPL",
    "gn:name":"Chhatarpur",
    "gn:population":0,
    "gn:timezone":"Asia/Kolkata",
    "iso:country":"IN",
    "name:ben_x_preferred":[
        "\u099b\u09a4\u09cd\u09a4\u09b0\u09aa\u09c1\u09b0"
    ],
    "name:bih_x_preferred":[
        "\u091b\u0924\u0930\u092a\u0941\u0930"
    ],
    "name:ceb_x_preferred":[
        "Chhatarpur"
    ],
    "name:deu_x_preferred":[
        "Chhatarpur"
    ],
    "name:fra_x_preferred":[
        "Chhatarpur"
    ],
    "name:hin_x_preferred":[
        "\u091b\u0924\u0930\u092a\u0941\u0930"
    ],
    "name:ita_x_preferred":[
        "Chhatarpur"
    ],
    "name:jpn_x_preferred":[
        "\u30c1\u30e3\u30bf\u30eb\u30d7\u30eb"
    ],
    "name:mlg_x_preferred":[
        "Chhatarpur"
    ],
    "name:msa_x_preferred":[
        "Chhatarpur"
    ],
    "name:new_x_preferred":[
        "\u091b\u0924\u0930\u092a\u0941\u0930"
    ],
    "name:ori_x_preferred":[
        "\u0b1b\u0b24\u0b30\u0b2a\u0b41\u0b30 \u0b30\u0b3e\u0b1c\u0b4d\u0b5f"
    ],
    "name:pam_x_preferred":[
        "Chhatarpur"
    ],
    "name:por_x_preferred":[
        "Chhatarpur"
    ],
    "name:rus_x_preferred":[
        "\u0427\u0445\u0430\u0442\u0430\u0440\u043f\u0443\u0440"
    ],
    "name:san_x_preferred":[
        "\u091b\u0924\u0930\u092a\u0941\u0930\u092e\u094d"
    ],
    "name:spa_x_preferred":[
        "Chhatarpur"
    ],
    "name:swe_x_preferred":[
        "Chhatarpur"
    ],
    "name:tam_x_preferred":[
        "\u0b9a\u0ba4\u0bcd\u0ba4\u0bb0\u0bcd\u0baa\u0bc2\u0bb0\u0bcd"
    ],
    "name:urd_x_preferred":[
        "\u0686\u06be\u062a\u0631\u067e\u0648\u0631"
    ],
    "name:vie_x_preferred":[
        "Chhatarpur"
    ],
    "name:zho_x_preferred":[
        "\u6070\u5854\u5c14\u666e\u5c14"
    ],
    "wof:name":"Chhatarpur",
    "wof:placetype":"locality"
},
  "geometry": {"coordinates":[84.18675,24.36746],"type":"Point"}
}