{
  "type": "Feature",
  "properties": {
    "iso:country":"IN",
    "ks:ks_alt_nam":"BaniaGachhi",
    "ks:ks_name":"Baniagachhi",
    "ks:ks_pop":242,
    "ks:ks_type":"HABITATION",
    "ks:ks_uagg_main":0,
    "name:eng_x_preferred":[
        "Baniagachhi"
    ],
    "wof:name":"Baniagachhi",
    "wof:placetype":"neighbourhood",
    "wof:population":242
},
  "geometry": {"coordinates":[88.188479,26.376596],"type":"Point"}
}