{
  "type": "Feature",
  "properties": {
    "iso:country":"IN",
    "ks:ks_alt_nam":"PURE DARSHAN MISHRA",
    "ks:ks_name":"Pure Darshan Mishra",
    "ks:ks_pop":8,
    "ks:ks_type":"HABITATION",
    "name:eng_x_preferred":[
        "Pure Darshan Mishra"
    ],
    "wof:name":"Pure Darshan Mishra",
    "wof:placetype":"locality",
    "wof:population":8
},
  "geometry": {"coordinates":[81.79752499999999,26.40385],"type":"Point"}
}