{
  "type": "Feature",
  "properties": {
    "gn:admin1_code":"36",
    "gn:admin2_code":"188.0",
    "gn:asciiname":"Bhauapar",
    "gn:country_code":"IN",
    "gn:dem":83,
    "gn:feature_class":"P",
    "gn:feature_code":"PPL",
    "gn:name":"Bhauap\u0101r",
    "gn:population":0,
    "gn:timezone":"Asia/Kolkata",
    "iso:country":"IN",
    "ks:ks_alt_nam":"Bhauap\u0101r",
    "ks:ks_name":"Bhauapar",
    "ks:ks_type":"VILLAGE",
    "ks:ks_uagg_main":0,
    "name:eng_x_preferred":[
        "Bhauapar"
    ],
    "name:eng_x_variant":[
        "Bhauap\u0101r"
    ],
    "wof:name":"Bhauapar",
    "wof:placetype":"neighbourhood"
},
  "geometry": {"coordinates":[83.527147,26.704071],"type":"Point"}
}