{
  "type": "Feature",
  "properties": {
    "gn:admin1_code":"39",
    "gn:admin2_code":"60.0",
    "gn:asciiname":"Sansu Khera",
    "gn:country_code":"IN",
    "gn:dem":1008,
    "gn:feature_class":"P",
    "gn:feature_code":"PPL",
    "gn:name":"Sansu Khera",
    "gn:population":0,
    "gn:timezone":"Asia/Kolkata",
    "iso:country":"IN",
    "wof:name":"Sansu Khera",
    "wof:placetype":"locality"
},
  "geometry": {"coordinates":[77.8292,30.88702],"type":"Point"}
}