{
  "type": "Feature",
  "properties": {
    "gn:admin1_code":"25.0",
    "gn:admin2_code":"610.0",
    "gn:asciiname":"Puvampalaiyam",
    "gn:country_code":"IN",
    "gn:dem":254,
    "gn:feature_class":"P",
    "gn:feature_code":"PPL",
    "gn:name":"P\u016bvamp\u0101laiyam",
    "gn:population":0,
    "gn:timezone":"Asia/Kolkata",
    "iso:country":"IN",
    "wof:name":"Puvampalaiyam",
    "wof:placetype":"locality"
},
  "geometry": {"coordinates":[77.60446999999998,11.30313],"type":"Point"}
}