{
  "type": "Feature",
  "properties": {
    "iso:country":"IN",
    "ks:ks_name":"Makhalpara",
    "ks:ks_pop":531,
    "ks:ks_type":"HABITATION",
    "ks:ks_uagg_main":0,
    "name:eng_x_preferred":[
        "Makhalpara"
    ],
    "wof:name":"Makhalpara",
    "wof:placetype":"locality",
    "wof:population":531
},
  "geometry": {"coordinates":[88.054857,22.471942],"type":"Point"}
}