{
  "type": "Feature",
  "properties": {
    "iso:country":"IN",
    "ks:ks_name":"Chanpa Sol",
    "ks:ks_pop":118,
    "ks:ks_type":"VILLAGE",
    "ks:ks_uagg_main":0,
    "name:eng_x_preferred":[
        "Chanpa Sol"
    ],
    "wof:name":"Chanpa Sol",
    "wof:placetype":"neighbourhood",
    "wof:population":118
},
  "geometry": {"coordinates":[87.128364,22.645476],"type":"Point"}
}