{
  "type": "Feature",
  "properties": {
    "iso:country":"IN",
    "ks:ks_alt_nam":"N\u012bmanpura",
    "ks:ks_name":"Nimanpura",
    "ks:ks_type":"VILLAGE",
    "name:eng_x_preferred":[
        "Nimanpura"
    ],
    "name:eng_x_variant":[
        "N\u012bmanpura"
    ],
    "wof:name":"Nimanpura",
    "wof:placetype":"locality"
},
  "geometry": {"coordinates":[77.762705,22.365952],"type":"Point"}
}