{
  "type": "Feature",
  "properties": {
    "iso:country":"IN",
    "ks:ks_name":"2 MKS-B",
    "ks:ks_pop":113,
    "ks:ks_type":"VILLAGE",
    "name:eng_x_preferred":[
        "2 MKS-B"
    ],
    "wof:name":"2 MKS-B",
    "wof:placetype":"locality",
    "wof:population":113
},
  "geometry": {"coordinates":[74.52022700000001,29.678023],"type":"Point"}
}