{
  "type": "Feature",
  "properties": {
    "iso:country":"IN",
    "ks:ks_alt_nam":"Sadhu ka Purwa",
    "ks:ks_name":"Sadhu Ka Purwa",
    "ks:ks_pop":76,
    "ks:ks_type":"HABITATION",
    "ks:ks_uagg_main":0,
    "name:eng_x_preferred":[
        "Sadhu Ka Purwa"
    ],
    "wof:name":"Sadhu Ka Purwa",
    "wof:placetype":"neighbourhood",
    "wof:population":76
},
  "geometry": {"coordinates":[81.598162,27.007927],"type":"Point"}
}