{
  "type": "Feature",
  "properties": {
    "iso:country":"IN",
    "ks:ks_name":"Arimara",
    "ks:ks_pop":809,
    "ks:ks_type":"VILLAGE",
    "ks:ks_uagg_main":0,
    "name:eng_x_preferred":[
        "Arimara"
    ],
    "wof:name":"Arimara",
    "wof:placetype":"neighbourhood",
    "wof:population":809
},
  "geometry": {"coordinates":[90.6798,26.288742],"type":"Point"}
}