{
  "type": "Feature",
  "properties": {
    "iso:country":"IN",
    "ks:ks_name":"Pebbampalle",
    "ks:ks_pop":116,
    "ks:ks_type":"HABITATION",
    "name:eng_x_preferred":[
        "Pebbampalle"
    ],
    "wof:name":"Pebbampalle",
    "wof:placetype":"locality",
    "wof:population":116
},
  "geometry": {"coordinates":[82.242785,17.924642],"type":"Point"}
}