{
  "type": "Feature",
  "properties": {
    "gn:admin1_code":"24",
    "gn:admin2_code":"123.0",
    "gn:asciiname":"Uriyon ki Bhagal",
    "gn:country_code":"IN",
    "gn:dem":588,
    "gn:feature_class":"P",
    "gn:feature_code":"PPL",
    "gn:name":"Uriyon ki Bh\u0101gal",
    "gn:population":0,
    "gn:timezone":"Asia/Kolkata",
    "iso:country":"IN",
    "wof:name":"Uriyon ki Bhagal",
    "wof:placetype":"locality"
},
  "geometry": {"coordinates":[73.75574,25.00269],"type":"Point"}
}