{
  "type": "Feature",
  "properties": {
    "gn:admin1_code":"35.0",
    "gn:admin2_code":"457.0",
    "gn:asciiname":"Niharwani",
    "gn:country_code":"IN",
    "gn:dem":315,
    "gn:feature_class":"P",
    "gn:feature_code":"PPL",
    "gn:name":"Niharw\u0101n\u012b",
    "gn:population":0,
    "gn:timezone":"Asia/Kolkata",
    "iso:country":"IN",
    "name:mar_x_preferred":[
        "\u0928\u093f\u0939\u093e\u0930\u0935\u093e\u0923\u0940"
    ],
    "wof:name":"Niharwani",
    "wof:placetype":"locality"
},
  "geometry": {"coordinates":[80.30864,21.74554],"type":"Point"}
}