{
  "type": "Feature",
  "properties": {
    "gn:admin1_code":"21",
    "gn:admin2_code":"372.0",
    "gn:asciiname":"Sargidamak",
    "gn:country_code":"IN",
    "gn:dem":228,
    "gn:feature_class":"P",
    "gn:feature_code":"PPL",
    "gn:name":"Sargidamak",
    "gn:population":0,
    "gn:timezone":"Asia/Kolkata",
    "iso:country":"IN",
    "ks:ks_name":"Sargidamak",
    "ks:ks_type":"VILLAGE",
    "name:eng_x_preferred":[
        "Sargidamak"
    ],
    "wof:name":"Sargidamak",
    "wof:placetype":"locality"
},
  "geometry": {"coordinates":[83.972053,21.300427],"type":"Point"}
}