{
  "type": "Feature",
  "properties": {
    "gn:admin1_code":"36",
    "gn:admin2_code":"175.0",
    "gn:asciiname":"Jema",
    "gn:country_code":"IN",
    "gn:dem":94,
    "gn:feature_class":"P",
    "gn:feature_code":"PPL",
    "gn:name":"Jema",
    "gn:population":0,
    "gn:timezone":"Asia/Kolkata",
    "iso:country":"IN",
    "name:deu_x_preferred":[
        "Jema"
    ],
    "name:fra_x_preferred":[
        "Jema"
    ],
    "name:swe_x_preferred":[
        "Jema"
    ],
    "wof:name":"Jema",
    "wof:placetype":"locality"
},
  "geometry": {"coordinates":[82.05759999999999,25.19383],"type":"Point"}
}