{
  "type": "Feature",
  "properties": {
    "iso:country":"IN",
    "ks:ks_name":"Dhaneshpur",
    "ks:ks_pop":0,
    "ks:ks_type":"VILLAGE",
    "name:eng_x_preferred":[
        "Dhaneshpur"
    ],
    "wof:name":"Dhaneshpur",
    "wof:placetype":"locality",
    "wof:population":0
},
  "geometry": {"coordinates":[84.053524,25.291124],"type":"Point"}
}