{
  "type": "Feature",
  "properties": {
    "iso:country":"IN",
    "ks:ks_alt_nam":"gadha",
    "ks:ks_name":"Gadha",
    "ks:ks_pop":157,
    "ks:ks_type":"HABITATION",
    "name:eng_x_preferred":[
        "Gadha"
    ],
    "wof:name":"Gadha",
    "wof:placetype":"locality",
    "wof:population":157
},
  "geometry": {"coordinates":[81.25497300000001,24.394666],"type":"Point"}
}