{
  "type": "Feature",
  "properties": {
    "iso:country":"IN",
    "ks:ks_name":"Kadarmara",
    "ks:ks_pop":88,
    "ks:ks_type":"VILLAGE",
    "name:eng_x_preferred":[
        "Kadarmara"
    ],
    "wof:name":"Kadarmara",
    "wof:placetype":"locality",
    "wof:population":88
},
  "geometry": {"coordinates":[87.402472,24.363184],"type":"Point"}
}