{
  "type": "Feature",
  "properties": {
    "iso:country":"IN",
    "ks:ks_name":"Chalmane",
    "ks:ks_pop":58,
    "ks:ks_type":"HABITATION",
    "name:eng_x_preferred":[
        "Chalmane"
    ],
    "wof:name":"Chalmane",
    "wof:placetype":"locality",
    "wof:population":58
},
  "geometry": {"coordinates":[74.965296,14.136443],"type":"Point"}
}