{
  "type": "Feature",
  "properties": {
    "iso:country":"IN",
    "ks:ks_name":"Margahi",
    "ks:ks_pop":0,
    "ks:ks_type":"VILLAGE",
    "name:eng_x_preferred":[
        "Margahi"
    ],
    "wof:name":"Margahi",
    "wof:placetype":"locality",
    "wof:population":0
},
  "geometry": {"coordinates":[83.747063,27.185605],"type":"Point"}
}