{
  "type": "Feature",
  "properties": {
    "gn:admin1_code":"21",
    "gn:admin2_code":"393.0",
    "gn:asciiname":"Salebhata",
    "gn:cc2":"IN",
    "gn:country_code":"IN",
    "gn:dem":146,
    "gn:feature_class":"P",
    "gn:feature_code":"PPL",
    "gn:name":"Salebhata",
    "gn:population":0,
    "gn:timezone":"Asia/Kolkata",
    "iso:country":"IN",
    "name:und_x_variant":[
        "Salebhatsa",
        "Salebhatta",
        "Salebhata"
    ],
    "wof:name":"Salebhata",
    "wof:placetype":"locality"
},
  "geometry": {"coordinates":[83.53333000000001,20.96667],"type":"Point"}
}