{
  "type": "Feature",
  "properties": {
    "gn:admin1_code":"36.0",
    "gn:admin2_code":"171.0",
    "gn:asciiname":"Hela",
    "gn:country_code":"IN",
    "gn:dem":216,
    "gn:feature_class":"P",
    "gn:feature_code":"PPL",
    "gn:name":"Hela",
    "gn:population":0,
    "gn:timezone":"Asia/Kolkata",
    "iso:country":"IN",
    "name:ceb_x_preferred":[
        "Hela"
    ],
    "name:dan_x_preferred":[
        "Hela"
    ],
    "name:deu_x_preferred":[
        "Hela"
    ],
    "name:epo_x_preferred":[
        "Hela"
    ],
    "name:est_x_preferred":[
        "Hela"
    ],
    "name:eus_x_preferred":[
        "Hela"
    ],
    "name:fas_x_preferred":[
        "\u0647\u0644\u0627"
    ],
    "name:fin_x_preferred":[
        "Hela"
    ],
    "name:fra_x_preferred":[
        "Hela"
    ],
    "name:ita_x_preferred":[
        "Hela"
    ],
    "name:nld_x_preferred":[
        "Hela"
    ],
    "name:nor_x_preferred":[
        "Hela"
    ],
    "name:por_x_preferred":[
        "Hela"
    ],
    "name:rus_x_preferred":[
        "\u0425\u0435\u043b\u0430"
    ],
    "name:srp_x_preferred":[
        "\u0425\u0435\u043b\u0430"
    ],
    "name:swe_x_preferred":[
        "Hela"
    ],
    "name:uzb_x_preferred":[
        "Hela"
    ],
    "wof:name":"Hela",
    "wof:placetype":"locality"
},
  "geometry": {"coordinates":[81.09435999999999,25.02428],"type":"Point"}
}