{
  "type": "Feature",
  "properties": {
    "gn:admin1_code":"21.0",
    "gn:admin2_code":"396.0",
    "gn:asciiname":"Dussapanga",
    "gn:country_code":"IN",
    "gn:dem":257,
    "gn:feature_class":"P",
    "gn:feature_code":"PPL",
    "gn:name":"Dussapanga",
    "gn:population":0,
    "gn:timezone":"Asia/Kolkata",
    "iso:country":"IN",
    "ks:ks_name":"Dusapanga",
    "ks:ks_pop":133,
    "ks:ks_type":"VILLAGE",
    "name:eng_x_preferred":[
        "Dusapanga"
    ],
    "name:eng_x_variant":[
        "Dussapanga"
    ],
    "wof:name":"Dusapanga",
    "wof:placetype":"locality",
    "wof:population":133
},
  "geometry": {"coordinates":[83.863781,19.48152],"type":"Point"}
}