{
  "type": "Feature",
  "properties": {
    "gn:admin1_code":"21.0",
    "gn:admin2_code":"396.0",
    "gn:asciiname":"Dussapanga",
    "gn:country_code":"IN",
    "gn:dem":257,
    "gn:feature_class":"P",
    "gn:feature_code":"PPL",
    "gn:name":"Dussapanga",
    "gn:population":0,
    "gn:timezone":"Asia/Kolkata",
    "iso:country":"IN",
    "wof:name":"Dussapanga",
    "wof:placetype":"locality"
},
  "geometry": {"coordinates":[83.86386,19.48153],"type":"Point"}
}