{
  "type": "Feature",
  "properties": {
    "iso:country":"IN",
    "ks:ks_name":"Pabya",
    "ks:ks_pop":185,
    "ks:ks_type":"HABITATION",
    "name:eng_x_preferred":[
        "Pabya"
    ],
    "wof:name":"Pabya",
    "wof:placetype":"locality",
    "wof:population":185
},
  "geometry": {"coordinates":[80.04135100000001,29.744374],"type":"Point"}
}