{
  "type": "Feature",
  "properties": {
    "gn:admin1_code":"12.0",
    "gn:admin2_code":"18.0",
    "gn:asciiname":"Dharam",
    "gn:country_code":"IN",
    "gn:dem":2277,
    "gn:feature_class":"P",
    "gn:feature_code":"PPL",
    "gn:name":"Dharam",
    "gn:population":0,
    "gn:timezone":"Asia/Kolkata",
    "iso:country":"IN",
    "wof:name":"Dharam",
    "wof:placetype":"locality"
},
  "geometry": {"coordinates":[75.66630000000001,33.46061],"type":"Point"}
}