{
  "type": "Feature",
  "properties": {
    "iso:country":"IN",
    "ks:ks_name":"Tekulaboru",
    "ks:ks_pop":126,
    "ks:ks_type":"HABITATION",
    "ks:ks_uagg_main":0,
    "name:eng_x_preferred":[
        "Tekulaboru"
    ],
    "wof:name":"Tekulaboru",
    "wof:placetype":"neighbourhood",
    "wof:population":126
},
  "geometry": {"coordinates":[80.581874,18.293033],"type":"Point"}
}