{
  "type": "Feature",
  "properties": {
    "iso:country":"IN",
    "ks:ks_name":"Araltoli 1",
    "ks:ks_pop":565,
    "ks:ks_type":"HABITATION",
    "ks:ks_uagg_main":0,
    "name:eng_x_preferred":[
        "Araltoli 1"
    ],
    "wof:name":"Araltoli 1",
    "wof:placetype":"neighbourhood",
    "wof:population":565
},
  "geometry": {"coordinates":[94.730046,27.166644],"type":"Point"}
}