{
  "type": "Feature",
  "properties": {
    "gn:admin1_code":"36",
    "gn:admin2_code":"169.0",
    "gn:asciiname":"Salua",
    "gn:country_code":"IN",
    "gn:dem":146,
    "gn:feature_class":"P",
    "gn:feature_code":"PPL",
    "gn:name":"Salu\u0101",
    "gn:population":0,
    "gn:timezone":"Asia/Kolkata",
    "iso:country":"IN",
    "name:ell_x_preferred":[
        "\u03a3\u03ac\u03bb\u03bf\u03c5\u03b1"
    ],
    "name:slk_x_preferred":[
        "Salua"
    ],
    "wof:name":"Salua",
    "wof:placetype":"locality"
},
  "geometry": {"coordinates":[79.92586999999997,25.46789],"type":"Point"}
}