{
  "type": "Feature",
  "properties": {
    "gn:admin1_code":"23",
    "gn:admin2_code":"38.0",
    "gn:asciiname":"Bariwala",
    "gn:country_code":"IN",
    "gn:dem":527,
    "gn:feature_class":"P",
    "gn:feature_code":"PPL",
    "gn:name":"B\u0101riw\u0101la",
    "gn:population":0,
    "gn:timezone":"Asia/Kolkata",
    "iso:country":"IN",
    "name:ben_x_preferred":[
        "\u09ac\u09be\u09b0\u09bf\u0993\u09af\u09bc\u09be\u09b2\u09be"
    ],
    "name:bpy_x_preferred":[
        "\u09ac\u09be\u09b0\u09bf\u09f1\u09be\u09b2\u09be"
    ],
    "name:hin_x_preferred":[
        "\u092c\u0930\u0940\u0935\u093e\u0932\u093e"
    ],
    "name:ita_x_preferred":[
        "Bariwala"
    ],
    "name:msa_x_preferred":[
        "Bariwala"
    ],
    "name:new_x_preferred":[
        "\u092c\u0930\u093f\u0935\u0932"
    ],
    "name:nld_x_preferred":[
        "Bariwala"
    ],
    "name:pan_x_preferred":[
        "\u0a2c\u0a30\u0a40\u0a35\u0a3e\u0a32\u0a3e"
    ],
    "name:por_x_preferred":[
        "Bariwala"
    ],
    "name:tam_x_preferred":[
        "\u0baa\u0bbe\u0bb0\u0bbf\u0bb5\u0bbe\u0bb2\u0bbe"
    ],
    "name:vie_x_preferred":[
        "Bariwala"
    ],
    "name:zho_x_preferred":[
        "\u5df4\u91cc\u74e6\u62c9"
    ],
    "wof:name":"Bariwala",
    "wof:placetype":"locality"
},
  "geometry": {"coordinates":[75.89131999999999,31.89565],"type":"Point"}
}