{
  "type": "Feature",
  "properties": {
    "gn:admin1_code":"37",
    "gn:admin2_code":"413.0",
    "gn:asciiname":"Saranda",
    "gn:country_code":"IN",
    "gn:dem":420,
    "gn:feature_class":"P",
    "gn:feature_code":"PPL",
    "gn:name":"S\u0101randa",
    "gn:population":0,
    "gn:timezone":"Asia/Kolkata",
    "iso:country":"IN",
    "wof:name":"Saranda",
    "wof:placetype":"locality"
},
  "geometry": {"coordinates":[81.62906,20.25686],"type":"Point"}
}