{
  "type": "Feature",
  "properties": {
    "iso:country":"IN",
    "ks:ks_name":"Khandapara",
    "ks:ks_pop":376,
    "ks:ks_type":"HABITATION",
    "name:eng_x_preferred":[
        "Khandapara"
    ],
    "wof:name":"Khandapara",
    "wof:placetype":"locality",
    "wof:population":376
},
  "geometry": {"coordinates":[84.49895600000001,22.198101],"type":"Point"}
}