{
  "type": "Feature",
  "properties": {
    "iso:country":"IN",
    "ks:ks_name":"Harijot",
    "ks:ks_pop":538,
    "ks:ks_type":"HABITATION",
    "name:eng_x_preferred":[
        "Harijot"
    ],
    "wof:name":"Harijot",
    "wof:placetype":"locality",
    "wof:population":538
},
  "geometry": {"coordinates":[82.65360800000001,27.384386],"type":"Point"}
}