{
  "type": "Feature",
  "properties": {
    "gn:admin1_code":"12.0",
    "gn:admin2_code":"2.0",
    "gn:asciiname":"Sutaharan",
    "gn:country_code":"IN",
    "gn:dem":2252,
    "gn:feature_class":"P",
    "gn:feature_code":"PPL",
    "gn:name":"Sutah\u0101ran",
    "gn:population":0,
    "gn:timezone":"Asia/Kolkata",
    "iso:country":"IN",
    "wof:name":"Sutaharan",
    "wof:placetype":"locality"
},
  "geometry": {"coordinates":[74.55410999999999,33.92846],"type":"Point"}
}