{
  "type": "Feature",
  "properties": {
    "iso:country":"IN",
    "ks:ks_name":"Fatilavadi",
    "ks:ks_pop":225,
    "ks:ks_type":"HABITATION",
    "name:eng_x_preferred":[
        "Fatilavadi"
    ],
    "wof:name":"Fatilavadi",
    "wof:placetype":"locality",
    "wof:population":225
},
  "geometry": {"coordinates":[73.039089,22.322436],"type":"Point"}
}