{
  "type": "Feature",
  "properties": {
    "gn:admin1_code":"40.0",
    "gn:admin2_code":"537.0",
    "gn:asciiname":"Timmaipalli",
    "gn:country_code":"IN",
    "gn:dem":549,
    "gn:feature_class":"P",
    "gn:feature_code":"PPL",
    "gn:name":"Timmaipalli",
    "gn:population":0,
    "gn:timezone":"Asia/Kolkata",
    "iso:country":"IN",
    "wof:name":"Timmaipalli",
    "wof:placetype":"locality"
},
  "geometry": {"coordinates":[78.61579999999999,17.54602],"type":"Point"}
}