{
  "type": "Feature",
  "properties": {
    "iso:country":"IN",
    "ks:ks_name":"Digar",
    "ks:ks_pop":3349,
    "ks:ks_type":"HABITATION",
    "ks:ks_uagg_main":0,
    "name:eng_x_preferred":[
        "Digar"
    ],
    "wof:name":"Digar",
    "wof:placetype":"neighbourhood",
    "wof:population":3349
},
  "geometry": {"coordinates":[75.337676,20.29455],"type":"Point"}
}