{
  "type": "Feature",
  "properties": {
    "iso:country":"IN",
    "ks:ks_name":"Doyasti",
    "ks:ks_pop":481,
    "ks:ks_type":"VILLAGE",
    "name:eng_x_preferred":[
        "Doyasti"
    ],
    "wof:name":"Doyasti",
    "wof:placetype":"locality",
    "wof:population":481
},
  "geometry": {"coordinates":[87.285571,21.98175],"type":"Point"}
}