{
  "type": "Feature",
  "properties": {
    "iso:country":"IN",
    "ks:ks_name":"Pabu Bhakhari",
    "ks:ks_pop":70,
    "ks:ks_type":"HABITATION",
    "name:eng_x_preferred":[
        "Pabu Bhakhari"
    ],
    "wof:name":"Pabu Bhakhari",
    "wof:placetype":"locality",
    "wof:population":70
},
  "geometry": {"coordinates":[72.003128,25.714269],"type":"Point"}
}