{
  "type": "Feature",
  "properties": {
    "iso:country":"IN",
    "ks:ks_name":"Konapara M Punji",
    "ks:ks_pop":244,
    "ks:ks_type":"HABITATION",
    "name:eng_x_preferred":[
        "Konapara M Punji"
    ],
    "wof:name":"Konapara M Punji",
    "wof:placetype":"locality",
    "wof:population":244
},
  "geometry": {"coordinates":[92.539467,24.988414],"type":"Point"}
}