{
  "type": "Feature",
  "properties": {
    "gn:country":"IN",
    "gn:fcode":"PPL",
    "gn:pop":17123,
    "iso:country":"IN",
    "name:ben_x_preferred":[
        "\u0989\u09a4\u09cd\u09a4\u09b0\u0995\u09be\u09b6\u09c0"
    ],
    "name:bpy_x_preferred":[
        "\u0989\u09a4\u09cd\u09a4\u09b0\u0995\u09be\u09b6\u09bf"
    ],
    "name:eng_x_preferred":[
        "Uttarkashi"
    ],
    "name:fra_x_preferred":[
        "Uttarkashi"
    ],
    "name:guj_x_preferred":[
        "\u0a89\u0aa4\u0acd\u0aa4\u0ab0\u0a95\u0abe\u0ab6\u0ac0"
    ],
    "name:hin_x_preferred":[
        "\u0909\u0924\u094d\u0924\u0930\u0915\u093e\u0936\u0940"
    ],
    "name:ita_x_preferred":[
        "Uttarkashi"
    ],
    "name:mar_x_preferred":[
        "\u0909\u0924\u094d\u0924\u0930\u0915\u093e\u0936\u0940"
    ],
    "name:msa_x_preferred":[
        "Uttarkashi"
    ],
    "name:nep_x_preferred":[
        "\u0909\u0924\u094d\u0924\u0930\u0915\u093e\u0936\u0940"
    ],
    "name:nld_x_preferred":[
        "Uttarkashi"
    ],
    "name:pnb_x_preferred":[
        "\u0627\u062a\u0631\u06a9\u0627\u0634\u06cc"
    ],
    "name:pol_x_preferred":[
        "Uttarkashi"
    ],
    "name:rus_x_preferred":[
        "\u0423\u0442\u0442\u0430\u0440\u043a\u0430\u0448\u0438"
    ],
    "name:san_x_preferred":[
        "\u0909\u0924\u094d\u0924\u0930\u0915\u093e\u0936\u0940"
    ],
    "name:swe_x_preferred":[
        "Uttarkashi"
    ],
    "name:tam_x_preferred":[
        "\u0b89\u0ba4\u0bcd\u0ba4\u0bb0\u0b95\u0bbe\u0b9a\u0bbf"
    ],
    "name:tel_x_preferred":[
        "\u0c09\u0c24\u0c4d\u0c24\u0c30\u200c\u0c15\u0c3e\u0c36\u0c3f"
    ],
    "name:ukr_x_preferred":[
        "\u0423\u0442\u0442\u0430\u0440\u043a\u0430\u0448\u0456"
    ],
    "name:unk_x_variant":[
        "B\u0101r\u0101h\u0101t"
    ],
    "name:urd_x_preferred":[
        "\u0627\u062a\u0631 \u06a9\u0627\u0634\u06cc"
    ],
    "name:vie_x_preferred":[
        "Uttarkashi"
    ],
    "name:zho_x_preferred":[
        "\u4e4c\u5854\u5c14\u5361\u65af\u5e0c"
    ],
    "qs:name":"Uttarkashi",
    "qs:name_adm0":"India",
    "qs:name_adm1":"Uttarakhand",
    "qs:photos":75,
    "qs:photos_1k":15,
    "qs:photos_9k":1,
    "qs:photos_9r":4,
    "qs:photos_all":163,
    "qs:photos_sr":2,
    "qs:placetype":"Town",
    "qs:pop_sr":"6",
    "wd:wordcount":1303,
    "wof:name":"Uttarkashi",
    "wof:placetype":"locality",
    "wof:population":17123
},
  "geometry": {"coordinates":[78.44342,30.72986],"type":"Point"}
}