{
  "type": "Feature",
  "properties": {
    "iso:country":"IN",
    "ks:ks_name":"Phool Puri",
    "ks:ks_pop":388,
    "ks:ks_type":"HABITATION",
    "name:eng_x_preferred":[
        "Phool Puri"
    ],
    "wof:name":"Phool Puri",
    "wof:placetype":"locality",
    "wof:population":388
},
  "geometry": {"coordinates":[74.366933,23.097069],"type":"Point"}
}