{
  "type": "Feature",
  "properties": {
    "gn:admin1_code":"16",
    "gn:admin2_code":"524.0",
    "gn:asciiname":"Pimpalgaon",
    "gn:country_code":"IN",
    "gn:dem":635,
    "gn:feature_class":"P",
    "gn:feature_code":"PPL",
    "gn:name":"Pimpalgaon",
    "gn:population":0,
    "gn:timezone":"Asia/Kolkata",
    "iso:country":"IN",
    "wof:name":"Pimpalgaon",
    "wof:placetype":"locality"
},
  "geometry": {"coordinates":[76.28487,18.5171],"type":"Point"}
}