{
  "type": "Feature",
  "properties": {
    "iso:country":"IN",
    "ks:ks_name":"Tambalwadi",
    "ks:ks_pop":255,
    "ks:ks_type":"HABITATION",
    "name:eng_x_preferred":[
        "Tambalwadi"
    ],
    "wof:name":"Tambalwadi",
    "wof:placetype":"locality",
    "wof:population":255
},
  "geometry": {"coordinates":[73.794161,16.275132],"type":"Point"}
}