{
  "type": "Feature",
  "properties": {
    "iso:country":"IN",
    "ks:ks_name":"Doyivarra",
    "ks:ks_pop":492,
    "ks:ks_type":"HABITATION",
    "name:eng_x_preferred":[
        "Doyivarra"
    ],
    "wof:name":"Doyivarra",
    "wof:placetype":"locality",
    "wof:population":492
},
  "geometry": {"coordinates":[83.150717,18.762094],"type":"Point"}
}