{
  "type": "Feature",
  "properties": {
    "gn:country":"IN",
    "gn:fcode":"PPL",
    "gn:pop":86917,
    "iso:country":"IN",
    "name:ben_x_preferred":[
        "\u0985\u0995\u09cb\u099f"
    ],
    "name:bpy_x_preferred":[
        "\u0985\u0995\u09cb\u099f"
    ],
    "name:cat_x_preferred":[
        "Akot"
    ],
    "name:chi_x_preferred":[
        "\u963f\u79d1\u7279"
    ],
    "name:cze_x_preferred":[
        "Akot"
    ],
    "name:dut_x_preferred":[
        "Akot"
    ],
    "name:eng_x_preferred":[
        "Akot"
    ],
    "name:fas_x_preferred":[
        "\u0627\u06a9\u0627\u062a"
    ],
    "name:fre_x_preferred":[
        "Akot"
    ],
    "name:ger_x_preferred":[
        "Akot"
    ],
    "name:guj_x_preferred":[
        "\u0a85\u0a95\u0acb\u0a9f"
    ],
    "name:ita_x_preferred":[
        "Akot"
    ],
    "name:jpn_x_preferred":[
        "\u30a2\u30b3\u30c3\u30c8"
    ],
    "name:kan_x_preferred":[
        "\u0c85\u0c95\u0ccb\u0c9f\u0ccd"
    ],
    "name:kor_x_preferred":[
        "\uc544\ucf54\ud2b8"
    ],
    "name:mar_x_preferred":[
        "\u0905\u0915\u094b\u091f"
    ],
    "name:may_x_preferred":[
        "Akot"
    ],
    "name:min_x_preferred":[
        "Akot"
    ],
    "name:nan_x_preferred":[
        "Akot"
    ],
    "name:new_x_preferred":[
        "\u0905\u0915\u094b\u0924"
    ],
    "name:ori_x_preferred":[
        "\u0b06\u0b15\u0b4b\u0b1f"
    ],
    "name:per_x_preferred":[
        "\u0627\u06a9\u0627\u062a"
    ],
    "name:por_x_preferred":[
        "Akot"
    ],
    "name:rus_x_preferred":[
        "\u0410\u043a\u043e\u0442"
    ],
    "name:spa_x_preferred":[
        "Akot"
    ],
    "name:swe_x_preferred":[
        "Akot"
    ],
    "name:tam_x_preferred":[
        "\u0b85\u0b95\u0bcb\u0b9f\u0bcd"
    ],
    "name:tel_x_preferred":[
        "\u0c05\u0c15\u0c4b\u0c1f\u0c4d"
    ],
    "name:urd_x_preferred":[
        "\u0622\u06a9\u0648\u0679"
    ],
    "name:vie_x_preferred":[
        "Akot"
    ],
    "name:zho_x_preferred":[
        "\u963f\u79d1\u7279"
    ],
    "qs:name":"Akot",
    "qs:name_adm0":"India",
    "qs:name_adm1":"Maharashtra",
    "qs:photos_9k":1,
    "qs:photos_9r":1,
    "qs:photos_all":1,
    "qs:photos_sr":0,
    "qs:placetype":"Town",
    "qs:pop_sr":"8",
    "wd:wordcount":786,
    "wof:name":"Akot",
    "wof:placetype":"locality",
    "wof:population":86917
},
  "geometry": {"coordinates":[77.05861,21.09639],"type":"Point"}
}