{
  "type": "Feature",
  "properties": {
    "gn:admin1_code":"34.0",
    "gn:admin2_code":"236.0",
    "gn:asciiname":"Kharar",
    "gn:country_code":"IN",
    "gn:dem":151,
    "gn:feature_class":"P",
    "gn:feature_code":"PPL",
    "gn:name":"Khar\u0101r",
    "gn:population":0,
    "gn:timezone":"Asia/Kolkata",
    "iso:country":"IN",
    "name:ceb_x_preferred":[
        "Kharar"
    ],
    "name:swe_x_preferred":[
        "Kharar"
    ],
    "wof:name":"Kharar",
    "wof:placetype":"locality"
},
  "geometry": {"coordinates":[84.81709000000002,24.54876],"type":"Point"}
}