{
  "type": "Feature",
  "properties": {
    "gn:admin1_code":"40",
    "gn:admin2_code":"533.0",
    "gn:asciiname":"Sultanpet",
    "gn:country_code":"IN",
    "gn:dem":379,
    "gn:feature_class":"P",
    "gn:feature_code":"PPL",
    "gn:name":"Sult\u0101npet",
    "gn:population":0,
    "gn:timezone":"Asia/Kolkata",
    "iso:country":"IN",
    "wof:name":"Sultanpet",
    "wof:placetype":"locality"
},
  "geometry": {"coordinates":[77.68505,18.46727000000001],"type":"Point"}
}