{
  "type": "Feature",
  "properties": {
    "gn:admin1_code":"34.0",
    "gn:admin2_code":"209.0",
    "gn:asciiname":"Dhangawan",
    "gn:country_code":"IN",
    "gn:dem":49,
    "gn:feature_class":"P",
    "gn:feature_code":"PPL",
    "gn:name":"Dhang\u0101w\u0101n",
    "gn:population":0,
    "gn:timezone":"Asia/Kolkata",
    "iso:country":"IN",
    "ks:ks_alt_nam":"DHANGAMA",
    "ks:ks_name":"Dhangama",
    "ks:ks_pop":369,
    "ks:ks_type":"HABITATION",
    "name:eng_x_preferred":[
        "Dhangama"
    ],
    "name:eng_x_variant":[
        "Dhangawan"
    ],
    "wof:name":"Dhangama",
    "wof:placetype":"locality",
    "wof:population":369
},
  "geometry": {"coordinates":[87.569168,26.077502],"type":"Point"}
}