{
  "type": "Feature",
  "properties": {
    "iso:country":"IN",
    "ks:ks_name":"Jagdishpur",
    "ks:ks_pop":138,
    "ks:ks_type":"VILLAGE",
    "name:eng_x_preferred":[
        "Jagdishpur"
    ],
    "wof:name":"Jagdishpur",
    "wof:placetype":"locality",
    "wof:population":138
},
  "geometry": {"coordinates":[82.60518,23.324634],"type":"Point"}
}