{
  "type": "Feature",
  "properties": {
    "iso:country":"IN",
    "ks:ks_name":"Kolsur Paschim",
    "ks:ks_pop":1376,
    "ks:ks_type":"HABITATION",
    "name:eng_x_preferred":[
        "Kolsur Paschim"
    ],
    "wof:name":"Kolsur Paschim",
    "wof:placetype":"locality",
    "wof:population":1376
},
  "geometry": {"coordinates":[88.72520400000001,22.780229],"type":"Point"}
}