{
  "type": "Feature",
  "properties": {
    "gn:admin1_code":"36",
    "gn:admin2_code":"176.0",
    "gn:asciiname":"Gutauna",
    "gn:country_code":"IN",
    "gn:dem":114,
    "gn:feature_class":"P",
    "gn:feature_code":"PPL",
    "gn:name":"Gutauna",
    "gn:population":0,
    "gn:timezone":"Asia/Kolkata",
    "iso:country":"IN",
    "ks:ks_name":"Gotauna",
    "ks:ks_pop":1011,
    "ks:ks_type":"VILLAGE",
    "ks:ks_uagg_main":0,
    "name:eng_x_preferred":[
        "Gotauna"
    ],
    "wof:name":"Gotauna",
    "wof:placetype":"neighbourhood",
    "wof:population":1011
},
  "geometry": {"coordinates":[81.342111,26.62384],"type":"Point"}
}