{
  "type": "Feature",
  "properties": {
    "iso:country":"IN",
    "ks:ks_name":"Vripadam Jn",
    "ks:ks_pop":934,
    "ks:ks_type":"HABITATION",
    "ks:ks_uagg_main":0,
    "name:eng_x_preferred":[
        "Vripadam Jn"
    ],
    "wof:name":"Vripadam Jn",
    "wof:placetype":"neighbourhood",
    "wof:population":934
},
  "geometry": {"coordinates":[75.92311599999999,11.239227],"type":"Point"}
}