{
  "type": "Feature",
  "properties": {
    "iso:country":"IN",
    "ks:ks_name":"Bogna Alias Ahri",
    "ks:ks_pop":245,
    "ks:ks_type":"VILLAGE",
    "name:eng_x_preferred":[
        "Bogna Alias Ahri"
    ],
    "wof:name":"Bogna Alias Ahri",
    "wof:placetype":"locality",
    "wof:population":245
},
  "geometry": {"coordinates":[84.160901,24.408378],"type":"Point"}
}