{
  "type": "Feature",
  "properties": {
    "iso:country":"IN",
    "ks:ks_alt_nam":"ravattamangalam",
    "ks:ks_name":"Ravattamangalam",
    "ks:ks_pop":772,
    "ks:ks_type":"HABITATION",
    "name:eng_x_preferred":[
        "Ravattamangalam"
    ],
    "wof:name":"Ravattamangalam",
    "wof:placetype":"locality",
    "wof:population":772
},
  "geometry": {"coordinates":[75.724092,11.546385],"type":"Point"}
}