{
  "type": "Feature",
  "properties": {
    "iso:country":"IN",
    "name:eng_x_preferred":[
        "RT Nagar"
    ],
    "name:eng_x_variant":[
        "R. T. Nagar"
    ],
    "name:kan_x_preferred":[
        "\u0c86\u0cb0\u0ccd. \u0c9f\u0cbf. \u0ca8\u0c97\u0cb0"
    ],
    "name:unk_x_variant":[
        "RT Nagar"
    ],
    "qs:gn_adm0_cc":"IN",
    "qs:gn_fcode":"PPL",
    "qs:gn_local":1277333,
    "qs:gn_nam_loc":"Bangalore, Bangalore, Karnataka, IN",
    "qs:gn_namadm1":"19",
    "qs:gn_name":"RT Nagar",
    "qs:local_max":7342,
    "qs:local_sum":38996,
    "qs:localhoods":89,
    "qs:name":"RT Nagar",
    "qs:name_adm0":"India",
    "qs:name_adm1":"Karnataka",
    "qs:name_adm2":"Bangalore",
    "qs:name_local":"Bangalore",
    "qs:photo_max":2,
    "qs:photo_sum":3,
    "qs:placetype":"Suburb",
    "qs:quad_count":2,
    "qs:woe_adm0":23424848,
    "qs:woe_adm1":2345753,
    "qs:woe_adm2":12586572,
    "qs:woe_lau":0,
    "qs:woe_local":2295420,
    "qs:woe_ver":"7.10.0",
    "wd:wordcount":457,
    "wof:lang":[
        "eng"
    ],
    "wof:name":"RT Nagar",
    "wof:placetype":"neighbourhood"
},
  "geometry": {"coordinates":[77.599182,13.025074],"type":"Point"}
}