{
  "type": "Feature",
  "properties": {
    "gn:admin1_code":"25.0",
    "gn:admin2_code":"610.0",
    "gn:asciiname":"Sukkiramaniyakavundanpalaiyam",
    "gn:country_code":"IN",
    "gn:dem":285,
    "gn:feature_class":"P",
    "gn:feature_code":"PPL",
    "gn:name":"Sukkiramaniyakavundanp\u0101laiyam",
    "gn:population":0,
    "gn:timezone":"Asia/Kolkata",
    "iso:country":"IN",
    "wof:name":"Sukkiramaniyakavundanpalaiyam",
    "wof:placetype":"locality"
},
  "geometry": {"coordinates":[77.49585999999999,11.22109],"type":"Point"}
}