{
  "type": "Feature",
  "properties": {
    "gn:admin1_code":"36",
    "gn:admin2_code":"199.0",
    "gn:asciiname":"Chinlikh Gaharwar",
    "gn:country_code":"IN",
    "gn:dem":91,
    "gn:feature_class":"P",
    "gn:feature_code":"PPL",
    "gn:name":"Chinlikh Gaharw\u0101r",
    "gn:population":0,
    "gn:timezone":"Asia/Kolkata",
    "iso:country":"IN",
    "wof:name":"Chinlikh Gaharwar",
    "wof:placetype":"locality"
},
  "geometry": {"coordinates":[82.60196999999999,25.11676],"type":"Point"}
}