{
  "type": "Feature",
  "properties": {
    "iso:country":"IN",
    "ks:ks_name":"Mahatpur",
    "ks:ks_pop":908,
    "ks:ks_type":"VILLAGE",
    "ks:ks_uagg_main":0,
    "name:eng_x_preferred":[
        "Mahatpur"
    ],
    "wof:name":"Mahatpur",
    "wof:placetype":"neighbourhood",
    "wof:population":908
},
  "geometry": {"coordinates":[88.28146599999999,24.335237],"type":"Point"}
}