{
  "type": "Feature",
  "properties": {
    "gn:admin1_code":"12",
    "gn:admin2_code":"14.0",
    "gn:asciiname":"Kulagad",
    "gn:country_code":"IN",
    "gn:dem":1638,
    "gn:feature_class":"P",
    "gn:feature_code":"PPL",
    "gn:name":"Kulagad",
    "gn:population":0,
    "gn:timezone":"Asia/Kolkata",
    "iso:country":"IN",
    "wof:name":"Kulagad",
    "wof:placetype":"locality"
},
  "geometry": {"coordinates":[75.21054000000002,33.6989],"type":"Point"}
}