{
  "type": "Feature",
  "properties": {
    "gn:admin1_code":"36",
    "gn:admin2_code":"198.0",
    "gn:asciiname":"Gonda Jamunajati",
    "gn:country_code":"IN",
    "gn:dem":86,
    "gn:feature_class":"P",
    "gn:feature_code":"PPL",
    "gn:name":"Gonda Jamun\u0101jati",
    "gn:population":0,
    "gn:timezone":"Asia/Kolkata",
    "iso:country":"IN",
    "wof:name":"Gonda Jamunajati",
    "wof:placetype":"locality"
},
  "geometry": {"coordinates":[82.58521999999998,25.42339],"type":"Point"}
}