{
  "type": "Feature",
  "properties": {
    "iso:country":"IN",
    "ks:ks_alt_nam":"14 AS-A",
    "ks:ks_name":"14 As-a",
    "ks:ks_pop":69,
    "ks:ks_type":"HABITATION",
    "name:eng_x_preferred":[
        "14 As-a"
    ],
    "wof:name":"14 As-a",
    "wof:placetype":"locality",
    "wof:population":69
},
  "geometry": {"coordinates":[73.318611,29.095833],"type":"Point"}
}