{
  "type": "Feature",
  "properties": {
    "gn:admin1_code":"37.0",
    "gn:admin2_code":"406",
    "gn:asciiname":"Ghaghra",
    "gn:country_code":"IN",
    "gn:dem":607,
    "gn:feature_class":"P",
    "gn:feature_code":"PPL",
    "gn:name":"Ghaghra",
    "gn:population":0,
    "gn:timezone":"Asia/Kolkata",
    "iso:country":"IN",
    "wof:name":"Ghaghra",
    "wof:placetype":"locality"
},
  "geometry": {"coordinates":[82.07018000000002,22.72535],"type":"Point"}
}