{
  "type": "Feature",
  "properties": {
    "iso:country":"IN",
    "ks:ks_name":"Kothiatoli",
    "ks:ks_pop":992,
    "ks:ks_type":"VILLAGE",
    "ks:ks_uagg_main":0,
    "name:eng_x_preferred":[
        "Kothiatoli"
    ],
    "wof:name":"Kothiatoli",
    "wof:placetype":"neighbourhood",
    "wof:population":992
},
  "geometry": {"coordinates":[94.026635,26.566669],"type":"Point"}
}