{
  "type": "Feature",
  "properties": {
    "gn:admin1_code":"12.0",
    "gn:admin2_code":"018",
    "gn:asciiname":"Inshan",
    "gn:country_code":"IN",
    "gn:dem":2559,
    "gn:feature_class":"P",
    "gn:feature_code":"PPL",
    "gn:name":"Inshan",
    "gn:population":0,
    "gn:timezone":"Asia/Kolkata",
    "iso:country":"IN",
    "wof:name":"Inshan",
    "wof:placetype":"locality"
},
  "geometry": {"coordinates":[75.5668,33.81261],"type":"Point"}
}