{
  "type": "Feature",
  "properties": {
    "iso:country":"IN",
    "ks:ks_name":"Gobardhanpur",
    "ks:ks_pop":514,
    "ks:ks_type":"VILLAGE",
    "name:eng_x_preferred":[
        "Gobardhanpur"
    ],
    "wof:name":"Gobardhanpur",
    "wof:placetype":"locality",
    "wof:population":514
},
  "geometry": {"coordinates":[85.835826,20.197077],"type":"Point"}
}