{
  "type": "Feature",
  "properties": {
    "iso:country":"IN",
    "ks:ks_name":"Gaderla",
    "ks:ks_pop":138,
    "ks:ks_type":"HABITATION",
    "name:eng_x_preferred":[
        "Gaderla"
    ],
    "wof:name":"Gaderla",
    "wof:placetype":"locality",
    "wof:population":138
},
  "geometry": {"coordinates":[78.198086,14.144599],"type":"Point"}
}