{
  "type": "Feature",
  "properties": {
    "iso:country":"IN",
    "ks:ks_name":"Krishna Bahadur Para",
    "ks:ks_pop":35,
    "ks:ks_type":"HABITATION",
    "ks:ks_uagg_main":0,
    "name:eng_x_preferred":[
        "Krishna Bahadur Para"
    ],
    "wof:name":"Krishna Bahadur Para",
    "wof:placetype":"neighbourhood",
    "wof:population":35
},
  "geometry": {"coordinates":[91.896,23.465031],"type":"Point"}
}