{
  "type": "Feature",
  "properties": {
    "iso:country":"IN",
    "ks:ks_name":"Baghmarwa",
    "ks:ks_pop":14,
    "ks:ks_type":"HABITATION",
    "ks:ks_uagg_main":0,
    "name:eng_x_preferred":[
        "Baghmarwa"
    ],
    "wof:name":"Baghmarwa",
    "wof:placetype":"neighbourhood",
    "wof:population":14
},
  "geometry": {"coordinates":[82.42462399999999,26.684702],"type":"Point"}
}