{
  "type": "Feature",
  "properties": {
    "gn:country":"IN",
    "gn:fcode":"PPL",
    "gn:pop":20685,
    "iso:country":"IN",
    "name:bpy_x_preferred":[
        "\u09a1\u09bf\u0997\u09ac\u0987"
    ],
    "name:bul_x_preferred":[
        "\u0414\u0438\u0433\u0431\u043e\u0438"
    ],
    "name:ceb_x_preferred":[
        "Digboi"
    ],
    "name:eng_x_preferred":[
        "Digboi"
    ],
    "name:fra_x_preferred":[
        "Digboi"
    ],
    "name:hin_x_preferred":[
        "\u0921\u093f\u0917\u092c\u094b\u0908"
    ],
    "name:ita_x_preferred":[
        "Digboi"
    ],
    "name:mal_x_preferred":[
        "\u0d21\u0d3f\u0d17\u0d4d\u200c\u0d2c\u0d4b\u0d2f\u0d4d"
    ],
    "name:mlg_x_preferred":[
        "Digboi"
    ],
    "name:msa_x_preferred":[
        "Digboi"
    ],
    "name:nan_x_preferred":[
        "Digboi"
    ],
    "name:new_x_preferred":[
        "\u0921\u093f\u0917\u094d\u092c\u094b\u0907"
    ],
    "name:nld_x_preferred":[
        "Digboi"
    ],
    "name:ori_x_preferred":[
        "\u0b26\u0b3f\u0b17\u0b2c\u0b4b\u0b07"
    ],
    "name:spa_x_preferred":[
        "Digboi"
    ],
    "name:swe_x_preferred":[
        "Digboi"
    ],
    "name:tam_x_preferred":[
        "\u0b9f\u0bbf\u0b95\u0bcd\u0baa\u0bbe\u0baf\u0bcd"
    ],
    "name:unk_x_variant":[
        "Digbor"
    ],
    "name:vie_x_preferred":[
        "Digboi"
    ],
    "qs:name":"Digboi",
    "qs:name_adm0":"India",
    "qs:name_adm1":"Assam",
    "qs:photos_9k":1,
    "qs:photos_9r":3,
    "qs:photos_all":139,
    "qs:photos_sr":0,
    "qs:placetype":"Town",
    "qs:pop_sr":"7",
    "wd:wordcount":1618,
    "wof:name":"Digboi",
    "wof:placetype":"locality",
    "wof:population":20685
},
  "geometry": {"coordinates":[95.61839000000001,27.39321],"type":"Point"}
}