{
  "type": "Feature",
  "properties": {
    "gn:admin1_code":"35",
    "gn:admin2_code":"436.0",
    "gn:asciiname":"Matana",
    "gn:country_code":"IN",
    "gn:dem":449,
    "gn:feature_class":"P",
    "gn:feature_code":"PPL",
    "gn:name":"Mat\u0101na",
    "gn:population":0,
    "gn:timezone":"Asia/Kolkata",
    "iso:country":"IN",
    "wof:name":"Matana",
    "wof:placetype":"locality"
},
  "geometry": {"coordinates":[76.32271,23.57295],"type":"Point"}
}