{
  "type": "Feature",
  "properties": {
    "iso:country":"IN",
    "ks:ks_name":"Bardual Para",
    "ks:ks_pop":389,
    "ks:ks_type":"HABITATION",
    "name:eng_x_preferred":[
        "Bardual Para"
    ],
    "wof:name":"Bardual Para",
    "wof:placetype":"locality",
    "wof:population":389
},
  "geometry": {"coordinates":[91.55075100000001,23.812604],"type":"Point"}
}