{
  "type": "Feature",
  "properties": {
    "gn:admin1_code":"34.0",
    "gn:admin2_code":"204.0",
    "gn:asciiname":"Gorgawan",
    "gn:country_code":"IN",
    "gn:dem":74,
    "gn:feature_class":"P",
    "gn:feature_code":"PPL",
    "gn:name":"Gorg\u0101w\u0101n",
    "gn:population":0,
    "gn:timezone":"Asia/Kolkata",
    "iso:country":"IN",
    "ks:ks_name":"Gorgawan",
    "ks:ks_pop":1472,
    "ks:ks_type":"VILLAGE",
    "name:eng_x_preferred":[
        "Gorgawan"
    ],
    "wof:name":"Gorgawan",
    "wof:placetype":"locality",
    "wof:population":1472
},
  "geometry": {"coordinates":[84.790171,26.771805],"type":"Point"}
}