{
  "type": "Feature",
  "properties": {
    "iso:country":"IN",
    "ks:ks_name":"Bhakhariya",
    "ks:ks_pop":1083,
    "ks:ks_type":"HABITATION",
    "name:eng_x_preferred":[
        "Bhakhariya"
    ],
    "wof:name":"Bhakhariya",
    "wof:placetype":"locality",
    "wof:population":1083
},
  "geometry": {"coordinates":[72.22820299999999,27.250744],"type":"Point"}
}