{
  "type": "Feature",
  "properties": {
    "iso:country":"IN",
    "ks:ks_name":"Hamirpur",
    "ks:ks_pop":195,
    "ks:ks_type":"VILLAGE",
    "name:eng_x_preferred":[
        "Hamirpur"
    ],
    "name:hin_x_preferred":[
        "\u0939\u092e\u0940\u0930\u092a\u0941\u0930"
    ],
    "wof:name":"Hamirpur",
    "wof:placetype":"neighbourhood",
    "wof:population":195
},
  "geometry": {"coordinates":[76.89859800000001,28.435899],"type":"Point"}
}