{
  "type": "Feature",
  "properties": {
    "gn:admin1_code":"24.0",
    "gn:admin2_code":"118.0",
    "gn:asciiname":"Morra",
    "gn:country_code":"IN",
    "gn:dem":309,
    "gn:feature_class":"P",
    "gn:feature_code":"PPL",
    "gn:name":"Morra",
    "gn:population":0,
    "gn:timezone":"Asia/Kolkata",
    "iso:country":"IN",
    "name:ceb_x_preferred":[
        "Morra"
    ],
    "name:deu_x_preferred":[
        "Morra"
    ],
    "name:fra_x_preferred":[
        "Morra"
    ],
    "name:ita_x_preferred":[
        "Morra"
    ],
    "name:nld_x_preferred":[
        "Morra"
    ],
    "name:rus_x_preferred":[
        "\u041c\u043e\u0440\u0440\u0430"
    ],
    "name:spa_x_preferred":[
        "Morra"
    ],
    "name:swe_x_preferred":[
        "Morra"
    ],
    "wof:name":"Morra",
    "wof:placetype":"neighbourhood"
},
  "geometry": {"coordinates":[73.89894,26.05256],"type":"Point"}
}