{
  "type": "Feature",
  "properties": {
    "iso:country":"IN",
    "ks:ks_alt_nam":"P\u0101nch\u0101",
    "ks:ks_name":"Pancha",
    "ks:ks_pop":648,
    "ks:ks_type":"VILLAGE",
    "name:eng_x_preferred":[
        "Pancha"
    ],
    "name:eng_x_variant":[
        "P\u0101nch\u0101"
    ],
    "wof:name":"Pancha",
    "wof:placetype":"locality",
    "wof:population":648
},
  "geometry": {"coordinates":[85.49228599999999,23.213713],"type":"Point"}
}