{
  "type": "Feature",
  "properties": {
    "iso:country":"IN",
    "ks:ks_name":"Kada",
    "ks:ks_pop":1722,
    "ks:ks_type":"VILLAGE",
    "name:eng_x_preferred":[
        "Kada"
    ],
    "wof:name":"Kada",
    "wof:placetype":"locality",
    "wof:population":1722
},
  "geometry": {"coordinates":[73.40034199999999,24.487211],"type":"Point"}
}