{
  "type": "Feature",
  "properties": {
    "iso:country":"IN",
    "ks:ks_name":"Belatanr",
    "ks:ks_pop":0,
    "ks:ks_type":"VILLAGE",
    "name:eng_x_preferred":[
        "Belatanr"
    ],
    "wof:name":"Belatanr",
    "wof:placetype":"locality",
    "wof:population":0
},
  "geometry": {"coordinates":[86.18924800000001,23.935785],"type":"Point"}
}