{
  "type": "Feature",
  "properties": {
    "gn:admin1_code":"35",
    "gn:admin2_code":"423.0",
    "gn:asciiname":"Khurai",
    "gn:country_code":"IN",
    "gn:dem":354,
    "gn:feature_class":"P",
    "gn:feature_code":"PPL",
    "gn:name":"Khurai",
    "gn:population":0,
    "gn:timezone":"Asia/Kolkata",
    "iso:country":"IN",
    "name:ben_x_preferred":[
        "\u0996\u09c1\u09b0\u09be\u0987"
    ],
    "name:bpy_x_preferred":[
        "\u0996\u09c1\u09b0\u09be\u0987"
    ],
    "name:ceb_x_preferred":[
        "Khurai"
    ],
    "name:ita_x_preferred":[
        "Khurai"
    ],
    "name:msa_x_preferred":[
        "Khurai"
    ],
    "name:new_x_preferred":[
        "\u0916\u0941\u0930\u093e\u0908"
    ],
    "name:por_x_preferred":[
        "Khurai"
    ],
    "name:swe_x_preferred":[
        "Khurai"
    ],
    "name:vie_x_preferred":[
        "Khurai"
    ],
    "wof:name":"Khurai",
    "wof:placetype":"locality"
},
  "geometry": {"coordinates":[78.22528,25.21404],"type":"Point"}
}