{
  "type": "Feature",
  "properties": {
    "gn:admin1_code":"34.0",
    "gn:admin2_code":"209.0",
    "gn:asciiname":"Maheshri Dakhinawri",
    "gn:country_code":"IN",
    "gn:dem":67,
    "gn:feature_class":"P",
    "gn:feature_code":"PPL",
    "gn:name":"Maheshri Dakhin\u0101wri",
    "gn:population":0,
    "gn:timezone":"Asia/Kolkata",
    "iso:country":"IN",
    "wof:name":"Maheshri Dakhinawri",
    "wof:placetype":"locality"
},
  "geometry": {"coordinates":[87.2482,26.38057],"type":"Point"}
}