{
  "type": "Feature",
  "properties": {
    "iso:country":"IN",
    "ks:ks_name":"Manavarthi",
    "ks:ks_pop":230,
    "ks:ks_type":"HABITATION",
    "name:eng_x_preferred":[
        "Manavarthi"
    ],
    "wof:name":"Manavarthi",
    "wof:placetype":"locality",
    "wof:population":230
},
  "geometry": {"coordinates":[79.194382,10.838217],"type":"Point"}
}