{
  "type": "Feature",
  "properties": {
    "gn:admin1_code":"11",
    "gn:admin2_code":"27.0",
    "gn:asciiname":"Samkhetar",
    "gn:country_code":"IN",
    "gn:dem":1109,
    "gn:feature_class":"P",
    "gn:feature_code":"PPL",
    "gn:name":"Samkhetar",
    "gn:population":0,
    "gn:timezone":"Asia/Kolkata",
    "iso:country":"IN",
    "wof:name":"Samkhetar",
    "wof:placetype":"locality"
},
  "geometry": {"coordinates":[76.90418000000003,31.87986],"type":"Point"}
}