{
  "type": "Feature",
  "properties": {
    "iso:country":"IN",
    "ks:ks_name":"Mahadevbaran",
    "ks:ks_pop":2877,
    "ks:ks_type":"VILLAGE",
    "ks:ks_uagg_main":0,
    "name:eng_x_preferred":[
        "Mahadevbaran"
    ],
    "wof:name":"Mahadevbaran",
    "wof:placetype":"neighbourhood",
    "wof:population":2877
},
  "geometry": {"coordinates":[87.497518,25.258763],"type":"Point"}
}