{
  "type": "Feature",
  "properties": {
    "iso:country":"IN",
    "ks:ks_name":"Thippasettihalli",
    "ks:ks_pop":654,
    "ks:ks_type":"VILLAGE",
    "ks:ks_uagg_main":0,
    "name:eng_x_preferred":[
        "Thippasettihalli"
    ],
    "wof:name":"Thippasettihalli",
    "wof:placetype":"neighbourhood",
    "wof:population":654
},
  "geometry": {"coordinates":[77.300488,13.223939],"type":"Point"}
}