{
  "type": "Feature",
  "properties": {
    "iso:country":"IN",
    "ks:ks_name":"San-tumkela",
    "ks:ks_pop":8,
    "ks:ks_type":"VILLAGE",
    "name:eng_x_preferred":[
        "San-tumkela"
    ],
    "wof:name":"San-tumkela",
    "wof:placetype":"locality",
    "wof:population":8
},
  "geometry": {"coordinates":[84.922133,21.84525],"type":"Point"}
}