{
  "type": "Feature",
  "properties": {
    "iso:country":"IN",
    "ks:ks_name":"Kasari Khas",
    "ks:ks_pop":222,
    "ks:ks_type":"HABITATION",
    "name:eng_x_preferred":[
        "Kasari Khas"
    ],
    "wof:name":"Kasari Khas",
    "wof:placetype":"locality",
    "wof:population":222
},
  "geometry": {"coordinates":[83.24020299999999,24.669282],"type":"Point"}
}