{
  "type": "Feature",
  "properties": {
    "iso:country":"IN",
    "ks:ks_name":"Rajbandh",
    "ks:ks_pop":1010,
    "ks:ks_type":"VILLAGE",
    "ks:ks_uagg_main":0,
    "name:eng_x_preferred":[
        "Rajbandh"
    ],
    "wof:name":"Rajbandh",
    "wof:placetype":"neighbourhood",
    "wof:population":1010
},
  "geometry": {"coordinates":[87.47986899999999,24.168897],"type":"Point"}
}