{
  "type": "Feature",
  "properties": {
    "iso:country":"IN",
    "ks:ks_name":"Kodagojeddu",
    "ks:ks_pop":230,
    "ks:ks_type":"HABITATION",
    "name:eng_x_preferred":[
        "Kodagojeddu"
    ],
    "wof:name":"Kodagojeddu",
    "wof:placetype":"locality",
    "wof:population":230
},
  "geometry": {"coordinates":[74.815924,13.508686],"type":"Point"}
}