{
  "type": "Feature",
  "properties": {
    "iso:country":"IN",
    "ks:ks_name":"Garatewadi",
    "ks:ks_pop":282,
    "ks:ks_type":"HABITATION",
    "name:eng_x_preferred":[
        "Garatewadi"
    ],
    "wof:name":"Garatewadi",
    "wof:placetype":"locality",
    "wof:population":282
},
  "geometry": {"coordinates":[73.635778,16.991172],"type":"Point"}
}