{
  "type": "Feature",
  "properties": {
    "iso:country":"IN",
    "ks:ks_name":"Mallipadi",
    "ks:ks_pop":150,
    "ks:ks_type":"HABITATION",
    "name:eng_x_preferred":[
        "Mallipadi"
    ],
    "wof:name":"Mallipadi",
    "wof:placetype":"locality",
    "wof:population":150
},
  "geometry": {"coordinates":[75.169107,12.714449],"type":"Point"}
}