{
  "type": "Feature",
  "properties": {
    "gn:admin1_code":"11",
    "gn:admin2_code":"29.0",
    "gn:asciiname":"Ratti Bar",
    "gn:country_code":"IN",
    "gn:dem":519,
    "gn:feature_class":"P",
    "gn:feature_code":"PPL",
    "gn:name":"Ratti B\u0101r",
    "gn:population":0,
    "gn:timezone":"Asia/Kolkata",
    "iso:country":"IN",
    "wof:name":"Ratti Bar",
    "wof:placetype":"locality"
},
  "geometry": {"coordinates":[75.98243000000002,31.83088],"type":"Point"}
}