{
  "type": "Feature",
  "properties": {
    "iso:country":"IN",
    "ks:ks_name":"Sultanpur",
    "ks:ks_pop":59,
    "ks:ks_type":"VILLAGE",
    "name:eng_x_preferred":[
        "Sultanpur"
    ],
    "wof:name":"Sultanpur",
    "wof:placetype":"locality",
    "wof:population":59
},
  "geometry": {"coordinates":[77.720609,24.46746],"type":"Point"}
}