{
  "type": "Feature",
  "properties": {
    "iso:country":"IN",
    "ks:ks_name":"Malla",
    "ks:ks_pop":119,
    "ks:ks_type":"HABITATION",
    "name:eng_x_preferred":[
        "Malla"
    ],
    "wof:name":"Malla",
    "wof:placetype":"locality",
    "wof:population":119
},
  "geometry": {"coordinates":[75.944444,12.523611],"type":"Point"}
}