{
  "type": "Feature",
  "properties": {
    "iso:country":"IN",
    "ks:ks_name":"Jangalia Para",
    "ks:ks_pop":157,
    "ks:ks_type":"HABITATION",
    "ks:ks_uagg_main":0,
    "name:eng_x_preferred":[
        "Jangalia Para"
    ],
    "wof:name":"Jangalia Para",
    "wof:placetype":"neighbourhood",
    "wof:population":157
},
  "geometry": {"coordinates":[91.47728600000001,23.801746],"type":"Point"}
}