{
  "type": "Feature",
  "properties": {
    "iso:country":"IN",
    "ks:ks_name":"Dasota",
    "ks:ks_pop":350,
    "ks:ks_type":"VILLAGE",
    "ks:ks_uagg_main":0,
    "name:eng_x_preferred":[
        "Dasota"
    ],
    "wof:name":"Dasota",
    "wof:placetype":"neighbourhood",
    "wof:population":350
},
  "geometry": {"coordinates":[82.82173,26.825584],"type":"Point"}
}