{
  "type": "Feature",
  "properties": {
    "iso:country":"IN",
    "ks:ks_name":"Turk Walia Dariyao Singh",
    "ks:ks_pop":1073,
    "ks:ks_type":"VILLAGE",
    "ks:ks_uagg_main":0,
    "name:eng_x_preferred":[
        "Turk Walia Dariyao Singh"
    ],
    "wof:name":"Turk Walia Dariyao Singh",
    "wof:placetype":"neighbourhood",
    "wof:population":1073
},
  "geometry": {"coordinates":[83.9076,26.794634],"type":"Point"}
}