{
  "type": "Feature",
  "properties": {
    "iso:country":"IN",
    "ks:ks_name":"Rajalumadurapuram",
    "ks:ks_pop":156,
    "ks:ks_type":"HABITATION",
    "name:eng_x_preferred":[
        "Rajalumadurapuram"
    ],
    "wof:name":"Rajalumadurapuram",
    "wof:placetype":"locality",
    "wof:population":156
},
  "geometry": {"coordinates":[79.468075,13.150212],"type":"Point"}
}