{
  "type": "Feature",
  "properties": {
    "gn:admin1_code":"25.0",
    "gn:admin2_code":"610.0",
    "gn:asciiname":"Toddampattipallarnattam",
    "gn:country_code":"IN",
    "gn:dem":204,
    "gn:feature_class":"P",
    "gn:feature_code":"PPL",
    "gn:name":"Toddampattipallarnattam",
    "gn:population":0,
    "gn:timezone":"Asia/Kolkata",
    "iso:country":"IN",
    "wof:name":"Toddampattipallarnattam",
    "wof:placetype":"locality"
},
  "geometry": {"coordinates":[77.66566999999998,11.35306],"type":"Point"}
}