{
  "type": "Feature",
  "properties": {
    "iso:country":"IN",
    "ks:ks_name":"Jayangondanatharkovil",
    "ks:ks_pop":504,
    "ks:ks_type":"HABITATION",
    "name:eng_x_preferred":[
        "Jayangondanatharkovil"
    ],
    "wof:name":"Jayangondanatharkovil",
    "wof:placetype":"locality",
    "wof:population":504
},
  "geometry": {"coordinates":[79.484807,10.675157],"type":"Point"}
}