{
  "type": "Feature",
  "properties": {
    "gn:admin1_code":"35",
    "gn:admin2_code":"427.0",
    "gn:asciiname":"Bharrai",
    "gn:country_code":"IN",
    "gn:dem":536,
    "gn:feature_class":"P",
    "gn:feature_code":"PPL",
    "gn:name":"Bharrai",
    "gn:population":0,
    "gn:timezone":"Asia/Kolkata",
    "iso:country":"IN",
    "ks:ks_name":"Bharrai",
    "ks:ks_pop":315,
    "ks:ks_type":"VILLAGE",
    "name:eng_x_preferred":[
        "Bharrai"
    ],
    "wof:name":"Bharrai",
    "wof:placetype":"locality",
    "wof:population":315
},
  "geometry": {"coordinates":[79.123248,23.219013],"type":"Point"}
}