{
  "type": "Feature",
  "properties": {
    "gn:admin1_code":"19.0",
    "gn:admin2_code":"563.0",
    "gn:asciiname":"Hodvatti",
    "gn:country_code":"IN",
    "gn:dem":494,
    "gn:feature_class":"P",
    "gn:feature_code":"PPL",
    "gn:name":"Hodvatti",
    "gn:population":0,
    "gn:timezone":"Asia/Kolkata",
    "iso:country":"IN",
    "ks:ks_name":"Hodavatti",
    "ks:ks_pop":116,
    "ks:ks_type":"HABITATION",
    "name:eng_x_preferred":[
        "Hodavatti"
    ],
    "name:eng_x_variant":[
        "Hodvatti"
    ],
    "wof:name":"Hodavatti",
    "wof:placetype":"locality",
    "wof:population":116
},
  "geometry": {"coordinates":[74.726224,14.373358],"type":"Point"}
}