{
  "type": "Feature",
  "properties": {
    "iso:country":"IN",
    "ks:ks_alt_nam":"PURE RIKHPAL",
    "ks:ks_name":"Pure Rikhpal",
    "ks:ks_pop":93,
    "ks:ks_type":"HABITATION",
    "ks:ks_uagg_main":0,
    "name:eng_x_preferred":[
        "Pure Rikhpal"
    ],
    "wof:name":"Pure Rikhpal",
    "wof:placetype":"neighbourhood",
    "wof:population":93
},
  "geometry": {"coordinates":[81.832503,26.467745],"type":"Point"}
}