{
  "type": "Feature",
  "properties": {
    "gn:admin1_code":"36.0",
    "gn:admin2_code":"158.0",
    "gn:asciiname":"Majhgaon",
    "gn:country_code":"IN",
    "gn:dem":117,
    "gn:feature_class":"P",
    "gn:feature_code":"PPL",
    "gn:name":"Majhgaon",
    "gn:population":0,
    "gn:timezone":"Asia/Kolkata",
    "iso:country":"IN",
    "ks:ks_name":"Majhgaon",
    "ks:ks_pop":262,
    "ks:ks_type":"VILLAGE",
    "ks:ks_uagg_main":0,
    "name:eng_x_preferred":[
        "Majhgaon"
    ],
    "wof:name":"Majhgaon",
    "wof:placetype":"neighbourhood",
    "wof:population":262
},
  "geometry": {"coordinates":[81.331136,26.465182],"type":"Point"}
}