{
  "type": "Feature",
  "properties": {
    "iso:country":"IN",
    "ks:ks_name":"Namodih Khas",
    "ks:ks_pop":15,
    "ks:ks_type":"VILLAGE",
    "name:eng_x_preferred":[
        "Namodih Khas"
    ],
    "wof:name":"Namodih Khas",
    "wof:placetype":"locality",
    "wof:population":15
},
  "geometry": {"coordinates":[87.546639,24.366477],"type":"Point"}
}