{
  "type": "Feature",
  "properties": {
    "iso:country":"IN",
    "ks:ks_name":"Sapgandha",
    "ks:ks_pop":136,
    "ks:ks_type":"HABITATION",
    "name:eng_x_preferred":[
        "Sapgandha"
    ],
    "wof:name":"Sapgandha",
    "wof:placetype":"locality",
    "wof:population":136
},
  "geometry": {"coordinates":[82.355064,19.73405],"type":"Point"}
}