{
  "type": "Feature",
  "properties": {
    "iso:country":"IN",
    "ks:ks_name":"Vadapeta",
    "ks:ks_pop":380,
    "ks:ks_type":"HABITATION",
    "name:eng_x_preferred":[
        "Vadapeta"
    ],
    "wof:name":"Vadapeta",
    "wof:placetype":"locality",
    "wof:population":380
},
  "geometry": {"coordinates":[84.346861,18.567779],"type":"Point"}
}