{
  "type": "Feature",
  "properties": {
    "iso:country":"IN",
    "ks:ks_name":"Mohamadpur Manoradh",
    "ks:ks_pop":798,
    "ks:ks_type":"VILLAGE",
    "name:eng_x_preferred":[
        "Mohamadpur Manoradh"
    ],
    "wof:name":"Mohamadpur Manoradh",
    "wof:placetype":"locality",
    "wof:population":798
},
  "geometry": {"coordinates":[85.108377,25.972169],"type":"Point"}
}