{
  "type": "Feature",
  "properties": {
    "iso:country":"IN",
    "ks:ks_name":"Dhepagaon",
    "ks:ks_pop":260,
    "ks:ks_type":"HABITATION",
    "name:eng_x_preferred":[
        "Dhepagaon"
    ],
    "wof:name":"Dhepagaon",
    "wof:placetype":"locality",
    "wof:population":260
},
  "geometry": {"coordinates":[83.89365100000001,19.441792],"type":"Point"}
}