{
  "type": "Feature",
  "properties": {
    "iso:country":"IN",
    "ks:ks_alt_nam":"JAMMUNDA",
    "ks:ks_name":"Jammunda",
    "ks:ks_pop":318,
    "ks:ks_type":"HABITATION",
    "name:eng_x_preferred":[
        "Jammunda"
    ],
    "wof:name":"Jammunda",
    "wof:placetype":"locality",
    "wof:population":318
},
  "geometry": {"coordinates":[83.89157299999999,22.475992],"type":"Point"}
}