{
  "type": "Feature",
  "properties": {
    "iso:country":"IN",
    "ks:ks_name":"Kishunpura",
    "ks:ks_pop":288,
    "ks:ks_type":"VILLAGE",
    "name:eng_x_preferred":[
        "Kishunpura"
    ],
    "wof:name":"Kishunpura",
    "wof:placetype":"locality",
    "wof:population":288
},
  "geometry": {"coordinates":[84.133816,26.539721],"type":"Point"}
}