{
  "type": "Feature",
  "properties": {
    "iso:country":"IN",
    "ks:ks_name":"Kandarsona",
    "ks:ks_pop":3088,
    "ks:ks_type":"VILLAGE",
    "ks:ks_uagg_main":0,
    "name:eng_x_preferred":[
        "Kandarsona"
    ],
    "wof:name":"Kandarsona",
    "wof:placetype":"neighbourhood",
    "wof:population":3088
},
  "geometry": {"coordinates":[87.946228,23.211167],"type":"Point"}
}