{
  "type": "Feature",
  "properties": {
    "iso:country":"IN",
    "ks:ks_name":"Damhalipada",
    "ks:ks_pop":251,
    "ks:ks_type":"HABITATION",
    "name:eng_x_preferred":[
        "Damhalipada"
    ],
    "wof:name":"Damhalipada",
    "wof:placetype":"locality",
    "wof:population":251
},
  "geometry": {"coordinates":[73.05413799999999,19.72164],"type":"Point"}
}