{
  "type": "Feature",
  "properties": {
    "gn:admin1_code":"36",
    "gn:admin2_code":"163.0",
    "gn:asciiname":"Harcharan Purwa",
    "gn:country_code":"IN",
    "gn:dem":135,
    "gn:feature_class":"P",
    "gn:feature_code":"PPL",
    "gn:name":"Harcharan Purwa",
    "gn:population":0,
    "gn:timezone":"Asia/Kolkata",
    "iso:country":"IN",
    "wof:name":"Harcharan Purwa",
    "wof:placetype":"locality"
},
  "geometry": {"coordinates":[79.7791,26.15108],"type":"Point"}
}