{
  "type": "Feature",
  "properties": {
    "iso:country":"IN",
    "ks:ks_name":"Hosakoppa",
    "ks:ks_pop":117,
    "ks:ks_type":"HABITATION",
    "name:eng_x_preferred":[
        "Hosakoppa"
    ],
    "wof:name":"Hosakoppa",
    "wof:placetype":"locality",
    "wof:population":117
},
  "geometry": {"coordinates":[74.684112,14.349571],"type":"Point"}
}