{
  "type": "Feature",
  "properties": {
    "iso:country":"IN",
    "ks:ks_name":"Arasubettu Shirlal",
    "ks:ks_pop":80,
    "ks:ks_type":"HABITATION",
    "name:eng_x_preferred":[
        "Arasubettu Shirlal"
    ],
    "wof:name":"Arasubettu Shirlal",
    "wof:placetype":"locality",
    "wof:population":80
},
  "geometry": {"coordinates":[75.04696800000001,13.305403],"type":"Point"}
}