{
  "type": "Feature",
  "properties": {
    "gn:admin1_code":"28.0",
    "gn:admin2_code":"334.0",
    "gn:asciiname":"Kanaipur",
    "gn:country_code":"IN",
    "gn:dem":37,
    "gn:feature_class":"P",
    "gn:feature_code":"PPL",
    "gn:name":"K\u0101n\u0101ipur",
    "gn:population":0,
    "gn:timezone":"Asia/Kolkata",
    "iso:country":"IN",
    "name:ben_x_preferred":[
        "\u0995\u09be\u09a8\u09be\u0987\u09aa\u09c1\u09b0"
    ],
    "name:bpy_x_preferred":[
        "\u0995\u09be\u09a8\u09be\u0987\u09aa\u09c1\u09b0"
    ],
    "name:hif_x_preferred":[
        "Kanaipur"
    ],
    "name:ind_x_preferred":[
        "Kanaipur"
    ],
    "name:ita_x_preferred":[
        "Kanaipur"
    ],
    "name:msa_x_preferred":[
        "Kanaipur"
    ],
    "name:new_x_preferred":[
        "\u0915\u0928\u0948\u092a\u0941\u0930"
    ],
    "name:nld_x_preferred":[
        "Kanaipur"
    ],
    "name:por_x_preferred":[
        "Kanaipur"
    ],
    "name:tam_x_preferred":[
        "\u0b95\u0bbe\u0ba9\u0bc8\u0baa\u0bc2\u0bb0\u0bcd"
    ],
    "name:vie_x_preferred":[
        "Kanaipur"
    ],
    "name:zho_x_preferred":[
        "\u5361\u5948\u666e\u5c14"
    ],
    "wof:name":"Kanaipur",
    "wof:placetype":"locality"
},
  "geometry": {"coordinates":[87.87809,24.2862],"type":"Point"}
}