{
  "type": "Feature",
  "properties": {
    "gn:admin1_code":"34.0",
    "gn:admin2_code":"226.0",
    "gn:asciiname":"Sijua",
    "gn:country_code":"IN",
    "gn:dem":141,
    "gn:feature_class":"P",
    "gn:feature_code":"PPL",
    "gn:name":"Sijua",
    "gn:population":0,
    "gn:timezone":"Asia/Kolkata",
    "iso:country":"IN",
    "name:bpy_x_preferred":[
        "\u09b8\u09bf\u099c\u09c1\u09f1\u09be"
    ],
    "name:ceb_x_preferred":[
        "Sijua"
    ],
    "name:ita_x_preferred":[
        "Sijua"
    ],
    "name:msa_x_preferred":[
        "Sijua"
    ],
    "name:nld_x_preferred":[
        "Sijua"
    ],
    "name:por_x_preferred":[
        "Sijua"
    ],
    "name:vie_x_preferred":[
        "Sijua"
    ],
    "wof:name":"Sijua",
    "wof:placetype":"locality"
},
  "geometry": {"coordinates":[86.41521999999998,25.04183],"type":"Point"}
}