{
  "type": "Feature",
  "properties": {
    "iso:country":"IN",
    "ks:ks_name":"Rouliguda",
    "ks:ks_pop":78,
    "ks:ks_type":"HABITATION",
    "name:eng_x_preferred":[
        "Rouliguda"
    ],
    "wof:name":"Rouliguda",
    "wof:placetype":"locality",
    "wof:population":78
},
  "geometry": {"coordinates":[82.385864,18.669774],"type":"Point"}
}