{
  "type": "Feature",
  "properties": {
    "iso:country":"IN",
    "qs:name":"Pollayil",
    "qs:name_adm0":"India",
    "qs:name_adm1":"Kerala",
    "qs:photos":104,
    "qs:photos_1k":21,
    "qs:photos_9k":1,
    "qs:photos_9r":3,
    "qs:photos_all":104,
    "qs:photos_sr":3,
    "qs:placetype":"Town",
    "qs:pop_sr":"0",
    "wof:name":"Pollayil",
    "wof:placetype":"locality"
},
  "geometry": {"coordinates":[76.376266,9.487752],"type":"Point"}
}