{
  "type": "Feature",
  "properties": {
    "gn:admin1_code":"35",
    "gn:admin2_code":"448.0",
    "gn:asciiname":"Sirali",
    "gn:country_code":"IN",
    "gn:dem":309,
    "gn:feature_class":"P",
    "gn:feature_code":"PPL",
    "gn:name":"Sir\u0101li",
    "gn:population":0,
    "gn:timezone":"Asia/Kolkata",
    "iso:country":"IN",
    "name:ceb_x_preferred":[
        "S\u012br\u0101li"
    ],
    "name:swe_x_preferred":[
        "S\u012br\u0101li"
    ],
    "name:und_x_variant":[
        "S\u012br\u0101li",
        "Sir\u0101li"
    ],
    "wof:name":"Sirali",
    "wof:placetype":"locality"
},
  "geometry": {"coordinates":[77.06276,22.15246],"type":"Point"}
}