{
  "type": "Feature",
  "properties": {
    "iso:country":"IN",
    "ks:ks_name":"Thirtharampura",
    "ks:ks_pop":57,
    "ks:ks_type":"VILLAGE",
    "name:eng_x_preferred":[
        "Thirtharampura"
    ],
    "wof:name":"Thirtharampura",
    "wof:placetype":"locality",
    "wof:population":57
},
  "geometry": {"coordinates":[75.49254500000001,14.191655],"type":"Point"}
}