{
  "type": "Feature",
  "properties": {
    "iso:country":"IN",
    "ks:ks_alt_nam":"Pokhrab\u0101d",
    "ks:ks_name":"Pokhrabad",
    "ks:ks_type":"VILLAGE",
    "name:eng_x_preferred":[
        "Pokhrabad"
    ],
    "name:eng_x_variant":[
        "Pokhrab\u0101d"
    ],
    "wof:name":"Pokhrabad",
    "wof:placetype":"locality"
},
  "geometry": {"coordinates":[75.89899800000001,21.793444],"type":"Point"}
}