{
  "type": "Feature",
  "properties": {
    "iso:country":"IN",
    "ks:ks_name":"Shanthinagar",
    "ks:ks_pop":149,
    "ks:ks_type":"HABITATION",
    "name:eng_x_preferred":[
        "Shanthinagar"
    ],
    "wof:name":"Shanthinagar",
    "wof:placetype":"locality",
    "wof:population":149
},
  "geometry": {"coordinates":[74.961912,12.833658],"type":"Point"}
}