{
  "type": "Feature",
  "properties": {
    "iso:country":"IN",
    "ks:ks_alt_nam":"TAPASIPUR",
    "ks:ks_name":"Tapasipur",
    "ks:ks_pop":197,
    "ks:ks_type":"HABITATION",
    "name:eng_x_preferred":[
        "Tapasipur"
    ],
    "wof:name":"Tapasipur",
    "wof:placetype":"locality",
    "wof:population":197
},
  "geometry": {"coordinates":[85.78018899999999,24.944544],"type":"Point"}
}