{
  "type": "Feature",
  "properties": {
    "iso:country":"IN",
    "ks:ks_name":"Jakholi Kalan",
    "ks:ks_pop":487,
    "ks:ks_type":"VILLAGE",
    "name:eng_x_preferred":[
        "Jakholi Kalan"
    ],
    "wof:name":"Jakholi Kalan",
    "wof:placetype":"locality",
    "wof:population":487
},
  "geometry": {"coordinates":[75.33126,25.371864],"type":"Point"}
}