{
  "type": "Feature",
  "properties": {
    "gn:admin1_code":"16.0",
    "gn:admin2_code":"500.0",
    "gn:asciiname":"Giroli Budruk",
    "gn:country_code":"IN",
    "gn:dem":578,
    "gn:feature_class":"P",
    "gn:feature_code":"PPL",
    "gn:name":"Giroli Budruk",
    "gn:population":0,
    "gn:timezone":"Asia/Kolkata",
    "iso:country":"IN",
    "wof:name":"Giroli Budruk",
    "wof:placetype":"neighbourhood"
},
  "geometry": {"coordinates":[76.02836000000001,19.97537],"type":"Point"}
}