{
  "type": "Feature",
  "properties": {
    "gn:admin1_code":"16.0",
    "gn:admin2_code":"512.0",
    "gn:asciiname":"Nokha",
    "gn:country_code":"IN",
    "gn:dem":441,
    "gn:feature_class":"P",
    "gn:feature_code":"PPL",
    "gn:name":"Nokha",
    "gn:population":0,
    "gn:timezone":"Asia/Kolkata",
    "iso:country":"IN",
    "wof:name":"Nokha",
    "wof:placetype":"neighbourhood"
},
  "geometry": {"coordinates":[77.15438,19.64205],"type":"Point"}
}