{
  "type": "Feature",
  "properties": {
    "iso:country":"IN",
    "ks:ks_alt_nam":"sigadi",
    "ks:ks_name":"Sigadi",
    "ks:ks_pop":29,
    "ks:ks_type":"HABITATION",
    "name:eng_x_preferred":[
        "Sigadi"
    ],
    "wof:name":"Sigadi",
    "wof:placetype":"locality",
    "wof:population":29
},
  "geometry": {"coordinates":[74.573598,14.208956],"type":"Point"}
}