{
  "type": "Feature",
  "properties": {
    "iso:country":"IN",
    "ks:ks_name":"Navgurewadi",
    "ks:ks_pop":69,
    "ks:ks_type":"HABITATION",
    "name:eng_x_preferred":[
        "Navgurewadi"
    ],
    "wof:name":"Navgurewadi",
    "wof:placetype":"locality",
    "wof:population":69
},
  "geometry": {"coordinates":[73.61658799999999,16.532269],"type":"Point"}
}