{
  "type": "Feature",
  "properties": {
    "iso:country":"IN",
    "ks:ks_name":"Keelapannai",
    "ks:ks_pop":175,
    "ks:ks_type":"HABITATION",
    "name:eng_x_preferred":[
        "Keelapannai"
    ],
    "wof:name":"Keelapannai",
    "wof:placetype":"locality",
    "wof:population":175
},
  "geometry": {"coordinates":[78.63228100000001,10.695246],"type":"Point"}
}