{
  "type": "Feature",
  "properties": {
    "gn:admin1_code":"35",
    "gn:admin2_code":"440.0",
    "gn:asciiname":"Biroti",
    "gn:country_code":"IN",
    "gn:dem":257,
    "gn:feature_class":"P",
    "gn:feature_code":"PPL",
    "gn:name":"Biroti",
    "gn:population":0,
    "gn:timezone":"Asia/Kolkata",
    "iso:country":"IN",
    "wof:name":"Biroti",
    "wof:placetype":"locality"
},
  "geometry": {"coordinates":[75.56265999999999,21.85122],"type":"Point"}
}