{
  "type": "Feature",
  "properties": {
    "iso:country":"IN",
    "ks:ks_name":"Pandari",
    "ks:ks_pop":60,
    "ks:ks_type":"VILLAGE",
    "name:eng_x_preferred":[
        "Pandari"
    ],
    "wof:name":"Pandari",
    "wof:placetype":"locality",
    "wof:population":60
},
  "geometry": {"coordinates":[80.063698,28.432491],"type":"Point"}
}