{
  "type": "Feature",
  "properties": {
    "iso:country":"IN",
    "ks:ks_name":"Kashiram Thanda",
    "ks:ks_pop":50,
    "ks:ks_type":"HABITATION",
    "name:eng_x_preferred":[
        "Kashiram Thanda"
    ],
    "wof:name":"Kashiram Thanda",
    "wof:placetype":"locality",
    "wof:population":50
},
  "geometry": {"coordinates":[77.38673300000001,18.187658],"type":"Point"}
}