{
  "type": "Feature",
  "properties": {
    "iso:country":"IN",
    "ks:ks_alt_nam":"Amr\u0101mau",
    "ks:ks_name":"Amramau",
    "ks:ks_type":"VILLAGE",
    "ks:ks_uagg_main":0,
    "name:eng_x_preferred":[
        "Amramau"
    ],
    "name:eng_x_variant":[
        "Amr\u0101mau"
    ],
    "wof:name":"Amramau",
    "wof:placetype":"neighbourhood"
},
  "geometry": {"coordinates":[80.315468,26.447977],"type":"Point"}
}