{
  "type": "Feature",
  "properties": {
    "iso:country":"IN",
    "ks:ks_name":"Kanhutoli",
    "ks:ks_pop":156,
    "ks:ks_type":"HABITATION",
    "name:eng_x_preferred":[
        "Kanhutoli"
    ],
    "wof:name":"Kanhutoli",
    "wof:placetype":"locality",
    "wof:population":156
},
  "geometry": {"coordinates":[84.402866,22.367502],"type":"Point"}
}