{
  "type": "Feature",
  "properties": {
    "iso:country":"IN",
    "ks:ks_alt_nam":"ECHANGUDI",
    "ks:ks_name":"Echangudi",
    "ks:ks_pop":29,
    "ks:ks_type":"HABITATION",
    "name:eng_x_preferred":[
        "Echangudi"
    ],
    "wof:name":"Echangudi",
    "wof:placetype":"locality",
    "wof:population":29
},
  "geometry": {"coordinates":[79.06088,9.98805],"type":"Point"}
}