{
  "type": "Feature",
  "properties": {
    "iso:country":"IN",
    "ks:ks_name":"Ghilamara 1 2",
    "ks:ks_pop":523,
    "ks:ks_type":"HABITATION",
    "ks:ks_uagg_main":0,
    "name:eng_x_preferred":[
        "Ghilamara 1 2"
    ],
    "wof:name":"Ghilamara 1 2",
    "wof:placetype":"neighbourhood",
    "wof:population":523
},
  "geometry": {"coordinates":[94.41410500000001,27.315274],"type":"Point"}
}