{
  "type": "Feature",
  "properties": {
    "gn:admin1_code":"19",
    "gn:admin2_code":"568.0",
    "gn:asciiname":"Kuntagalale",
    "gn:country_code":"IN",
    "gn:dem":586,
    "gn:feature_class":"P",
    "gn:feature_code":"PPL",
    "gn:name":"Kuntagalale",
    "gn:population":0,
    "gn:timezone":"Asia/Kolkata",
    "iso:country":"IN",
    "wof:name":"Kuntagalale",
    "wof:placetype":"locality"
},
  "geometry": {"coordinates":[74.90375999999998,14.49106],"type":"Point"}
}