{
  "type": "Feature",
  "properties": {
    "gn:admin1_code":"19",
    "gn:admin2_code":"568.0",
    "gn:asciiname":"Kuntagalale",
    "gn:country_code":"IN",
    "gn:dem":586,
    "gn:feature_class":"P",
    "gn:feature_code":"PPL",
    "gn:name":"Kuntagalale",
    "gn:population":0,
    "gn:timezone":"Asia/Kolkata",
    "iso:country":"IN",
    "ks:ks_name":"Kuntagalale",
    "ks:ks_pop":328,
    "ks:ks_type":"VILLAGE",
    "name:eng_x_preferred":[
        "Kuntagalale"
    ],
    "wof:name":"Kuntagalale",
    "wof:placetype":"locality",
    "wof:population":328
},
  "geometry": {"coordinates":[74.904211,14.491755],"type":"Point"}
}