{
  "type": "Feature",
  "properties": {
    "iso:country":"IN",
    "ks:ks_name":"Loombasar",
    "ks:ks_pop":86,
    "ks:ks_type":"VILLAGE",
    "name:eng_x_preferred":[
        "Loombasar"
    ],
    "wof:name":"Loombasar",
    "wof:placetype":"locality",
    "wof:population":86
},
  "geometry": {"coordinates":[72.818917,27.988083],"type":"Point"}
}