{
  "type": "Feature",
  "properties": {
    "iso:country":"IN",
    "ks:ks_name":"Khawda",
    "ks:ks_pop":1179,
    "ks:ks_type":"HABITATION",
    "name:eng_x_preferred":[
        "Khawda"
    ],
    "wof:name":"Khawda",
    "wof:placetype":"locality",
    "wof:population":1179
},
  "geometry": {"coordinates":[76.758627,26.289337],"type":"Point"}
}