{
  "type": "Feature",
  "properties": {
    "iso:country":"IN",
    "ks:ks_name":"Sutarpada",
    "ks:ks_pop":349,
    "ks:ks_type":"HABITATION",
    "ks:ks_uagg_main":0,
    "name:eng_x_preferred":[
        "Sutarpada"
    ],
    "wof:name":"Sutarpada",
    "wof:placetype":"neighbourhood",
    "wof:population":349
},
  "geometry": {"coordinates":[72.754319,20.056547],"type":"Point"}
}