{
  "type": "Feature",
  "properties": {
    "iso:country":"IN",
    "ks:ks_name":"Bhanjabasan",
    "ks:ks_pop":82,
    "ks:ks_type":"VILLAGE",
    "name:eng_x_preferred":[
        "Bhanjabasan"
    ],
    "wof:name":"Bhanjabasan",
    "wof:placetype":"locality",
    "wof:population":82
},
  "geometry": {"coordinates":[87.46433,21.682505],"type":"Point"}
}