{
  "type": "Feature",
  "properties": {
    "gn:admin1_code":"36",
    "gn:admin2_code":"188.0",
    "gn:asciiname":"Ikauna",
    "gn:country_code":"IN",
    "gn:dem":80,
    "gn:feature_class":"P",
    "gn:feature_code":"PPL",
    "gn:name":"Ikauna",
    "gn:population":0,
    "gn:timezone":"Asia/Kolkata",
    "iso:country":"IN",
    "name:bpy_x_preferred":[
        "\u0987\u0995\u09cc\u09a8\u09be"
    ],
    "name:cat_x_preferred":[
        "Ikauna"
    ],
    "name:ceb_x_preferred":[
        "Ikauna"
    ],
    "name:ita_x_preferred":[
        "Ikauna"
    ],
    "name:mlg_x_preferred":[
        "Ikauna"
    ],
    "name:msa_x_preferred":[
        "Ikauna"
    ],
    "name:new_x_preferred":[
        "\u0907\u0915\u094c\u0928\u093e"
    ],
    "name:nld_x_preferred":[
        "Ikauna"
    ],
    "name:pol_x_preferred":[
        "Ikauna"
    ],
    "name:por_x_preferred":[
        "Ikauna"
    ],
    "name:swe_x_preferred":[
        "Ikauna"
    ],
    "name:urd_x_preferred":[
        "\u0627\u06cc\u06a9\u0648\u0646\u0627"
    ],
    "name:vie_x_preferred":[
        "Ikauna"
    ],
    "name:zho_x_preferred":[
        "\u4f0a\u8003\u7eb3"
    ],
    "wof:name":"Ikauna",
    "wof:placetype":"locality"
},
  "geometry": {"coordinates":[83.42055999999999,26.4606],"type":"Point"}
}