{
  "type": "Feature",
  "properties": {
    "iso:country":"IN",
    "ks:ks_name":"Pathavooru",
    "ks:ks_pop":114,
    "ks:ks_type":"HABITATION",
    "name:eng_x_preferred":[
        "Pathavooru"
    ],
    "wof:name":"Pathavooru",
    "wof:placetype":"locality",
    "wof:population":114
},
  "geometry": {"coordinates":[79.725374,13.734401],"type":"Point"}
}