{
  "type": "Feature",
  "properties": {
    "gn:admin1_code":"2.0",
    "gn:admin2_code":"543.0",
    "gn:asciiname":"Komatipalle",
    "gn:country_code":"IN",
    "gn:dem":121,
    "gn:feature_class":"P",
    "gn:feature_code":"PPL",
    "gn:name":"Komatipalle",
    "gn:population":0,
    "gn:timezone":"Asia/Kolkata",
    "iso:country":"IN",
    "name:und_x_variant":[
        "Komatipalli",
        "Komatipalle"
    ],
    "wof:name":"Komatipalle",
    "wof:placetype":"locality"
},
  "geometry": {"coordinates":[83.39515,18.60246],"type":"Point"}
}