{
  "type": "Feature",
  "properties": {
    "iso:country":"IN",
    "ks:ks_name":"Gumukaguda.",
    "ks:ks_pop":1170,
    "ks:ks_type":"HABITATION",
    "name:eng_x_preferred":[
        "Gumukaguda."
    ],
    "wof:name":"Gumukaguda.",
    "wof:placetype":"locality",
    "wof:population":1170
},
  "geometry": {"coordinates":[81.83240600000001,18.155715],"type":"Point"}
}