{
  "type": "Feature",
  "properties": {
    "iso:country":"IN",
    "ks:ks_alt_nam":"khedi Istmurar",
    "ks:ks_name":"Khedi Istmurar",
    "ks:ks_pop":1128,
    "ks:ks_type":"HABITATION",
    "ks:ks_uagg_main":0,
    "name:eng_x_preferred":[
        "Khedi Istmurar"
    ],
    "wof:name":"Khedi Istmurar",
    "wof:placetype":"neighbourhood",
    "wof:population":1128
},
  "geometry": {"coordinates":[75.57337800000001,22.48738],"type":"Point"}
}