{
  "type": "Feature",
  "properties": {
    "gn:admin1_code":"35",
    "gn:admin2_code":"428.0",
    "gn:asciiname":"Shehpura Khurd",
    "gn:country_code":"IN",
    "gn:dem":517,
    "gn:feature_class":"P",
    "gn:feature_code":"PPL",
    "gn:name":"Shehpura Khurd",
    "gn:population":0,
    "gn:timezone":"Asia/Kolkata",
    "iso:country":"IN",
    "ks:ks_name":"Shahpura Khurd",
    "ks:ks_pop":385,
    "ks:ks_type":"HABITATION",
    "name:eng_x_preferred":[
        "Shahpura Khurd"
    ],
    "name:eng_x_variant":[
        "Shehpura Khurd"
    ],
    "wof:name":"Shahpura Khurd",
    "wof:placetype":"locality",
    "wof:population":385
},
  "geometry": {"coordinates":[79.451891,24.286286],"type":"Point"}
}