{
  "type": "Feature",
  "properties": {
    "iso:country":"IN",
    "ks:ks_name":"Manitiri",
    "ks:ks_pop":1132,
    "ks:ks_type":"VILLAGE",
    "name:eng_x_preferred":[
        "Manitiri"
    ],
    "wof:name":"Manitiri",
    "wof:placetype":"locality",
    "wof:population":1132
},
  "geometry": {"coordinates":[85.466578,20.115757],"type":"Point"}
}