{
  "type": "Feature",
  "properties": {
    "iso:country":"IN",
    "ks:ks_name":"Sibchandrpur",
    "ks:ks_pop":1451,
    "ks:ks_type":"VILLAGE",
    "ks:ks_uagg_main":0,
    "name:eng_x_preferred":[
        "Sibchandrpur"
    ],
    "wof:name":"Sibchandrpur",
    "wof:placetype":"neighbourhood",
    "wof:population":1451
},
  "geometry": {"coordinates":[88.67388,23.367303],"type":"Point"}
}