{
  "type": "Feature",
  "properties": {
    "iso:country":"IN",
    "ks:ks_name":"Dabbanagadde",
    "ks:ks_pop":654,
    "ks:ks_type":"VILLAGE",
    "name:eng_x_preferred":[
        "Dabbanagadde"
    ],
    "wof:name":"Dabbanagadde",
    "wof:placetype":"locality",
    "wof:population":654
},
  "geometry": {"coordinates":[75.31845300000001,13.677034],"type":"Point"}
}