{
  "type": "Feature",
  "properties": {
    "gn:admin1_code":"11",
    "gn:admin2_code":"23.0",
    "gn:asciiname":"Banaru Khad",
    "gn:country_code":"IN",
    "gn:dem":1883,
    "gn:feature_class":"P",
    "gn:feature_code":"PPL",
    "gn:name":"Ban\u0101ru Khad",
    "gn:population":0,
    "gn:timezone":"Asia/Kolkata",
    "iso:country":"IN",
    "wof:name":"Banaru Khad",
    "wof:placetype":"locality"
},
  "geometry": {"coordinates":[76.01189000000002,32.49592],"type":"Point"}
}