{
  "type": "Feature",
  "properties": {
    "gn:admin1_code":"39.0",
    "gn:admin2_code":"61.0",
    "gn:asciiname":"Mawanbakhli",
    "gn:country_code":"IN",
    "gn:dem":1709,
    "gn:feature_class":"P",
    "gn:feature_code":"PPL",
    "gn:name":"Maw\u0101nb\u0101khli",
    "gn:population":0,
    "gn:timezone":"Asia/Kolkata",
    "iso:country":"IN",
    "name:und_x_variant":[
        "Maw\u0101nb\u0101khli",
        "Maw\u0101ngaon"
    ],
    "wof:name":"Mawanbakhli",
    "wof:placetype":"locality"
},
  "geometry": {"coordinates":[79.07919,29.85353],"type":"Point"}
}