{
  "type": "Feature",
  "properties": {
    "gn:country":"IN",
    "gn:fcode":"PPL",
    "gn:population":37848,
    "iso:country":"IN",
    "name:ben_x_preferred":[
        "\u09a4\u09be\u09b0\u09bf\u0995\u09c7\u09b0\u09c7"
    ],
    "name:bpy_x_preferred":[
        "\u09a4\u09be\u09b0\u09bf\u0995\u09c7\u09b0\u09c7"
    ],
    "name:bul_x_preferred":[
        "\u0422\u0430\u0440\u0438\u043a\u0435\u0440\u0435"
    ],
    "name:ceb_x_preferred":[
        "Tarikere"
    ],
    "name:deu_x_preferred":[
        "Tarikere"
    ],
    "name:eng_x_preferred":[
        "Tarikere"
    ],
    "name:fra_x_preferred":[
        "Tarikere"
    ],
    "name:guj_x_preferred":[
        "\u0aa4\u0abe\u0ab0\u0ac0\u0a95\u0ac7\u0ab0"
    ],
    "name:ita_x_preferred":[
        "Tarikere"
    ],
    "name:jpn_x_preferred":[
        "\u30bf\u30ea\u30b1\u30ec"
    ],
    "name:kan_x_preferred":[
        "\u0ca4\u0cb0\u0cc0\u0c95\u0cc6\u0cb0\u0cc6"
    ],
    "name:kor_x_preferred":[
        "\ud0c0\ub9ac\ucf00\ub808"
    ],
    "name:mlg_x_preferred":[
        "Tarikere"
    ],
    "name:msa_x_preferred":[
        "Tarikere"
    ],
    "name:nan_x_preferred":[
        "Tarikere"
    ],
    "name:nld_x_preferred":[
        "Tarikere"
    ],
    "name:ori_x_preferred":[
        "\u0b24\u0b3e\u0b30\u0b3f\u0b15\u0b47\u0b30\u0b47"
    ],
    "name:por_x_preferred":[
        "Tarikere"
    ],
    "name:rus_x_preferred":[
        "\u0422\u0430\u0440\u0438\u043a\u0435\u0440\u0435"
    ],
    "name:spa_x_preferred":[
        "Tarikere"
    ],
    "name:swe_x_preferred":[
        "Tarikere"
    ],
    "name:tam_x_preferred":[
        "\u0ba4\u0bb0\u0bbf\u0b95\u0bc6\u0bb0\u0bc6"
    ],
    "name:tel_x_preferred":[
        "\u0c24\u0c30\u0c3f\u0c15\u0c46\u0c30"
    ],
    "name:urd_x_preferred":[
        "\u062a\u0627\u0631\u06cc\u06a9\u06cc\u0631\u06d2"
    ],
    "name:vie_x_preferred":[
        "Tarikere"
    ],
    "name:zho_x_preferred":[
        "\u5854\u91cc\u51ef\u96f7"
    ],
    "qs:name":"Tarikere",
    "qs:name_adm0":"India",
    "qs:name_adm1":"Karnataka",
    "qs:photos_9k":2,
    "qs:photos_9r":5,
    "qs:photos_all":373,
    "qs:photos_sr":0,
    "qs:placetype":"Town",
    "qs:pop_sr":"7",
    "wd:wordcount":629,
    "wof:name":"Tarikere",
    "wof:placetype":"locality",
    "wof:population":37848
},
  "geometry": {"coordinates":[75.81382000000001,13.70954],"type":"Point"}
}