{
  "type": "Feature",
  "properties": {
    "iso:country":"IN",
    "ks:ks_name":"Purunia",
    "ks:ks_pop":6,
    "ks:ks_type":"VILLAGE",
    "name:eng_x_preferred":[
        "Purunia"
    ],
    "wof:name":"Purunia",
    "wof:placetype":"locality",
    "wof:population":6
},
  "geometry": {"coordinates":[85.144429,20.952376],"type":"Point"}
}