{
  "type": "Feature",
  "properties": {
    "iso:country":"IN",
    "ks:ks_name":"Pratappur Raja",
    "ks:ks_pop":426,
    "ks:ks_type":"HABITATION",
    "name:eng_x_preferred":[
        "Pratappur Raja"
    ],
    "wof:name":"Pratappur Raja",
    "wof:placetype":"locality",
    "wof:population":426
},
  "geometry": {"coordinates":[78.53001999999999,27.619005],"type":"Point"}
}