{
  "type": "Feature",
  "properties": {
    "gn:admin1_code":"12.0",
    "gn:admin2_code":"005",
    "gn:asciiname":"Chak Kauro",
    "gn:country_code":"IN",
    "gn:dem":1277,
    "gn:feature_class":"P",
    "gn:feature_code":"PPL",
    "gn:name":"Chak Kauro",
    "gn:population":0,
    "gn:timezone":"Asia/Kolkata",
    "iso:country":"IN",
    "name:und_x_variant":[
        "Chak Katro"
    ],
    "wof:name":"Chak Kauro",
    "wof:placetype":"locality"
},
  "geometry": {"coordinates":[74.18347,33.75521],"type":"Point"}
}