{
  "type": "Feature",
  "properties": {
    "gn:admin1_code":"37",
    "gn:admin2_code":"409.0",
    "gn:asciiname":"Khajri",
    "gn:country_code":"IN",
    "gn:dem":286,
    "gn:feature_class":"P",
    "gn:feature_code":"PPL",
    "gn:name":"Khajri",
    "gn:population":0,
    "gn:timezone":"Asia/Kolkata",
    "iso:country":"IN",
    "ks:ks_name":"Khajri",
    "ks:ks_pop":1231,
    "ks:ks_type":"VILLAGE",
    "name:eng_x_preferred":[
        "Khajri"
    ],
    "wof:name":"Khajri",
    "wof:placetype":"locality",
    "wof:population":1231
},
  "geometry": {"coordinates":[81.41992,21.480249],"type":"Point"}
}