{
  "type": "Feature",
  "properties": {
    "iso:country":"IN",
    "ks:ks_name":"Tigriyaw",
    "ks:ks_pop":102,
    "ks:ks_type":"VILLAGE",
    "name:eng_x_preferred":[
        "Tigriyaw"
    ],
    "wof:name":"Tigriyaw",
    "wof:placetype":"locality",
    "wof:population":102
},
  "geometry": {"coordinates":[75.763592,22.228737],"type":"Point"}
}