{
  "type": "Feature",
  "properties": {
    "iso:country":"IN",
    "ks:ks_name":"Hurraha",
    "ks:ks_pop":646,
    "ks:ks_type":"VILLAGE",
    "ks:ks_uagg_main":0,
    "name:eng_x_preferred":[
        "Hurraha"
    ],
    "wof:name":"Hurraha",
    "wof:placetype":"neighbourhood",
    "wof:population":646
},
  "geometry": {"coordinates":[85.34129,26.408857],"type":"Point"}
}