{
  "type": "Feature",
  "properties": {
    "iso:country":"IN",
    "ks:ks_name":"Bhaliapada",
    "ks:ks_pop":312,
    "ks:ks_type":"VILLAGE",
    "name:eng_x_preferred":[
        "Bhaliapada"
    ],
    "wof:name":"Bhaliapada",
    "wof:placetype":"locality",
    "wof:population":312
},
  "geometry": {"coordinates":[87.054999,21.759807],"type":"Point"}
}