{
  "type": "Feature",
  "properties": {
    "iso:country":"IN",
    "ks:ks_name":"Piperpara",
    "ks:ks_pop":66,
    "ks:ks_type":"HABITATION",
    "name:eng_x_preferred":[
        "Piperpara"
    ],
    "wof:name":"Piperpara",
    "wof:placetype":"locality",
    "wof:population":66
},
  "geometry": {"coordinates":[82.269245,22.853921],"type":"Point"}
}