{
  "type": "Feature",
  "properties": {
    "gn:admin1_code":"10.0",
    "gn:admin2_code":"072",
    "gn:asciiname":"Dadlu",
    "gn:country_code":"IN",
    "gn:dem":271,
    "gn:feature_class":"P",
    "gn:feature_code":"PPL",
    "gn:name":"D\u0101dlu",
    "gn:population":0,
    "gn:timezone":"Asia/Kolkata",
    "iso:country":"IN",
    "name:ceb_x_preferred":[
        "D\u0101dl\u016b"
    ],
    "name:fas_x_preferred":[
        "\u062f\u0627\u062f\u0644\u0648"
    ],
    "name:msa_x_preferred":[
        "Dadlu"
    ],
    "name:swe_x_preferred":[
        "D\u0101dl\u016b"
    ],
    "wof:name":"Dadlu",
    "wof:placetype":"locality"
},
  "geometry": {"coordinates":[76.95215999999998,30.19215],"type":"Point"}
}