{
  "type": "Feature",
  "properties": {
    "iso:country":"IN",
    "ks:ks_name":"Debakua",
    "ks:ks_pop":5,
    "ks:ks_type":"VILLAGE",
    "name:eng_x_preferred":[
        "Debakua"
    ],
    "wof:name":"Debakua",
    "wof:placetype":"locality",
    "wof:population":5
},
  "geometry": {"coordinates":[84.13932,19.395148],"type":"Point"}
}