{
  "type": "Feature",
  "properties": {
    "iso:country":"IN",
    "ks:ks_name":"Kadagedda",
    "ks:ks_pop":123,
    "ks:ks_type":"HABITATION",
    "name:eng_x_preferred":[
        "Kadagedda"
    ],
    "wof:name":"Kadagedda",
    "wof:placetype":"locality",
    "wof:population":123
},
  "geometry": {"coordinates":[82.504177,17.952192],"type":"Point"}
}