{
  "type": "Feature",
  "properties": {
    "iso:country":"IN",
    "ks:ks_name":"Kulapal",
    "ks:ks_pop":159,
    "ks:ks_type":"VILLAGE",
    "name:eng_x_preferred":[
        "Kulapal"
    ],
    "wof:name":"Kulapal",
    "wof:placetype":"locality",
    "wof:population":159
},
  "geometry": {"coordinates":[85.211838,21.135185],"type":"Point"}
}