{
  "type": "Feature",
  "properties": {
    "gn:admin1_code":"25.0",
    "gn:admin2_code":"607.0",
    "gn:asciiname":"Nemali",
    "gn:country_code":"IN",
    "gn:dem":41,
    "gn:feature_class":"P",
    "gn:feature_code":"PPL",
    "gn:name":"Nemali",
    "gn:population":0,
    "gn:timezone":"Asia/Kolkata",
    "iso:country":"IN",
    "name:hin_x_preferred":[
        "\u0928\u0946\u092e\u0932\u093f"
    ],
    "name:new_x_preferred":[
        "\u0928\u0946\u092e\u0932\u093f"
    ],
    "name:tel_x_preferred":[
        "\u0c28\u0c46\u0c2e\u0c32\u0c3f"
    ],
    "wof:name":"Nemali",
    "wof:placetype":"locality"
},
  "geometry": {"coordinates":[79.65611,12.05484],"type":"Point"}
}