{
  "type": "Feature",
  "properties": {
    "iso:country":"IN",
    "ks:ks_name":"Pandharpurpada",
    "ks:ks_pop":185,
    "ks:ks_type":"HABITATION",
    "name:eng_x_preferred":[
        "Pandharpurpada"
    ],
    "wof:name":"Pandharpurpada",
    "wof:placetype":"locality",
    "wof:population":185
},
  "geometry": {"coordinates":[72.982399,19.928167],"type":"Point"}
}