{
  "type": "Feature",
  "properties": {
    "iso:country":"IN",
    "ks:ks_name":"Pure Mulhu",
    "ks:ks_pop":305,
    "ks:ks_type":"HABITATION",
    "name:eng_x_preferred":[
        "Pure Mulhu"
    ],
    "wof:name":"Pure Mulhu",
    "wof:placetype":"locality",
    "wof:population":305
},
  "geometry": {"coordinates":[81.320787,26.017631],"type":"Point"}
}