{
  "type": "Feature",
  "properties": {
    "iso:country":"IN",
    "ks:ks_name":"Madhuvattam Sigarapalli",
    "ks:ks_pop":129,
    "ks:ks_type":"HABITATION",
    "name:eng_x_preferred":[
        "Madhuvattam Sigarapalli"
    ],
    "wof:name":"Madhuvattam Sigarapalli",
    "wof:placetype":"locality",
    "wof:population":129
},
  "geometry": {"coordinates":[78.433663,12.437063],"type":"Point"}
}