{
  "type": "Feature",
  "properties": {
    "iso:country":"IN",
    "ks:ks_name":"Ambherkuchi",
    "ks:ks_pop":1170,
    "ks:ks_type":"HABITATION",
    "name:eng_x_preferred":[
        "Ambherkuchi"
    ],
    "wof:name":"Ambherkuchi",
    "wof:placetype":"locality",
    "wof:population":1170
},
  "geometry": {"coordinates":[91.887839,26.11517],"type":"Point"}
}