{
  "type": "Feature",
  "properties": {
    "iso:country":"IN",
    "ks:ks_name":"Doraguda",
    "ks:ks_pop":30,
    "ks:ks_type":"HABITATION",
    "name:eng_x_preferred":[
        "Doraguda"
    ],
    "wof:name":"Doraguda",
    "wof:placetype":"locality",
    "wof:population":30
},
  "geometry": {"coordinates":[82.74928,18.278357],"type":"Point"}
}