{
  "type": "Feature",
  "properties": {
    "iso:country":"IN",
    "name:ara_x_preferred":[
        "\u0645\u0633\u062a\u0639\u0645\u0631\u0629 \u0628\u0627\u062f\u0648"
    ],
    "name:ben_bn_x_preferred":[
        "\u09aa\u09be\u09a6\u09c1\u09df\u09be \u0995\u09b2\u09cb\u09a8\u09c0"
    ],
    "name:ben_in_x_preferred":[
        "\u09aa\u09be\u09a6\u09c1\u09df\u09be \u0995\u09b2\u09cb\u09a8\u09c0"
    ],
    "name:eng_x_preferred":[
        "Padua Colony"
    ],
    "name:guj_x_preferred":[
        "\u0aaa\u0abe\u0aa6\u0ac1\u0a86 \u0a95\u0acb\u0ab2\u0acb\u0aa8\u0ac0"
    ],
    "name:hin_x_preferred":[
        "\u092a\u0921\u0941\u0906 \u0915\u0949\u0932\u094b\u0928\u0940"
    ],
    "name:kan_x_preferred":[
        "\u0caa\u0ca6\u0cc1\u0cb5\u0cbe \u0c95\u0cbe\u0cb2\u0cca\u0ca8\u0cbf"
    ],
    "name:mal_x_preferred":[
        "\u0d2a\u0d3e\u0d26\u0d41\u0d35 \u0d15\u0d4b\u0d33\u0d28\u0d3f"
    ],
    "name:mar_x_preferred":[
        "\u092a\u0921\u0941\u0906 \u0915\u0949\u0932\u0928\u0940"
    ],
    "name:pan_x_preferred":[
        "\u0a2a\u0a21\u0a41\u0a06 \u0a15\u0a32\u0a4c\u0a28\u0a40"
    ],
    "name:tam_x_preferred":[
        "\u0baa\u0b9f\u0bc1\u0bb5\u0bbe \u0b95\u0bc1\u0b9f\u0bbf\u0baf\u0bbf\u0bb0\u0bc1\u0baa\u0bcd\u0baa\u0bc1"
    ],
    "name:tel_x_preferred":[
        "\u0c2a\u0c21\u0c41\u0c35\u0c3e \u0c15\u0c3e\u0c32\u0c28\u0c40"
    ],
    "name:urd_x_preferred":[
        "\u067e\u0691\u0648\u0648\u0627 \u06a9\u0627\u0644\u0648\u0646\u06cc"
    ],
    "qs:gn_local":0,
    "qs:local_max":3383,
    "qs:local_sum":8346,
    "qs:localhoods":12,
    "qs:name":"Padua Colony",
    "qs:name_adm0":"India",
    "qs:name_adm1":"Kerala",
    "qs:name_adm2":"Ernakulam",
    "qs:name_local":"Kochi",
    "qs:photo_max":84,
    "qs:photo_sum":95,
    "qs:placetype":"Suburb",
    "qs:quad_count":3,
    "qs:woe_adm0":23424848,
    "qs:woe_adm1":2345747,
    "qs:woe_adm2":12586468,
    "qs:woe_lau":0,
    "qs:woe_local":2295423,
    "qs:woe_ver":"7.10.0",
    "wof:lang":[
        "eng"
    ],
    "wof:name":"Padua Colony",
    "wof:placetype":"neighbourhood"
},
  "geometry": {"coordinates":[76.265568,9.984378],"type":"Point"}
}