{
  "type": "Feature",
  "properties": {
    "iso:country":"IN",
    "ks:ks_name":"Palsavade",
    "ks:ks_pop":100,
    "ks:ks_type":"VILLAGE",
    "name:eng_x_preferred":[
        "Palsavade"
    ],
    "wof:name":"Palsavade",
    "wof:placetype":"locality",
    "wof:population":100
},
  "geometry": {"coordinates":[73.873975,17.627009],"type":"Point"}
}