{
  "type": "Feature",
  "properties": {
    "iso:country":"IN",
    "ks:ks_name":"Bidor",
    "ks:ks_pop":66,
    "ks:ks_type":"HABITATION",
    "name:eng_x_preferred":[
        "Bidor"
    ],
    "wof:name":"Bidor",
    "wof:placetype":"locality",
    "wof:population":66
},
  "geometry": {"coordinates":[81.374109,23.891802],"type":"Point"}
}