{
  "type": "Feature",
  "properties": {
    "iso:country":"IN",
    "ks:ks_name":"Padumpur",
    "ks:ks_pop":45,
    "ks:ks_type":"HABITATION",
    "name:eng_x_preferred":[
        "Padumpur"
    ],
    "wof:name":"Padumpur",
    "wof:placetype":"locality",
    "wof:population":45
},
  "geometry": {"coordinates":[82.67054899999999,25.806303],"type":"Point"}
}