{
  "type": "Feature",
  "properties": {
    "gn:admin1_code":"23.0",
    "gn:admin2_code":"42.0",
    "gn:asciiname":"Kishanpura Khurd",
    "gn:country_code":"IN",
    "gn:dem":225,
    "gn:feature_class":"P",
    "gn:feature_code":"PPL",
    "gn:name":"Kishanp\u016bra Khurd",
    "gn:population":0,
    "gn:timezone":"Asia/Kolkata",
    "iso:country":"IN",
    "wof:name":"Kishanpura Khurd",
    "wof:placetype":"locality"
},
  "geometry": {"coordinates":[75.36986,30.92786],"type":"Point"}
}