{
  "type": "Feature",
  "properties": {
    "iso:country":"IN",
    "ks:ks_alt_nam":"GAMHARIKONA",
    "ks:ks_name":"Gamharikona",
    "ks:ks_pop":150,
    "ks:ks_type":"HABITATION",
    "name:eng_x_preferred":[
        "Gamharikona"
    ],
    "wof:name":"Gamharikona",
    "wof:placetype":"locality",
    "wof:population":150
},
  "geometry": {"coordinates":[83.767236,23.137668],"type":"Point"}
}