{
  "type": "Feature",
  "properties": {
    "iso:country":"IN",
    "ks:ks_name":"Banguru",
    "ks:ks_pop":681,
    "ks:ks_type":"VILLAGE",
    "name:eng_x_preferred":[
        "Banguru"
    ],
    "wof:name":"Banguru",
    "wof:placetype":"locality",
    "wof:population":681
},
  "geometry": {"coordinates":[82.131226,18.077597],"type":"Point"}
}