{
  "type": "Feature",
  "properties": {
    "iso:country":"IN",
    "ks:ks_name":"Piura",
    "ks:ks_pop":200,
    "ks:ks_type":"HABITATION",
    "name:eng_x_preferred":[
        "Piura"
    ],
    "wof:name":"Piura",
    "wof:placetype":"locality",
    "wof:population":200
},
  "geometry": {"coordinates":[83.82201000000001,26.474125],"type":"Point"}
}