{
  "type": "Feature",
  "properties": {
    "iso:country":"IN",
    "ks:ks_name":"Badaura",
    "ks:ks_pop":616,
    "ks:ks_type":"VILLAGE",
    "ks:ks_uagg_main":0,
    "name:eng_x_preferred":[
        "Badaura"
    ],
    "wof:name":"Badaura",
    "wof:placetype":"neighbourhood",
    "wof:population":616
},
  "geometry": {"coordinates":[80.675849,26.92145],"type":"Point"}
}