{
  "type": "Feature",
  "properties": {
    "iso:country":"IN",
    "ks:ks_name":"Masaniguda 4",
    "ks:ks_pop":23,
    "ks:ks_type":"HABITATION",
    "name:eng_x_preferred":[
        "Masaniguda 4"
    ],
    "wof:name":"Masaniguda 4",
    "wof:placetype":"locality",
    "wof:population":23
},
  "geometry": {"coordinates":[82.88498800000001,18.445763],"type":"Point"}
}