{
  "type": "Feature",
  "properties": {
    "iso:country":"IN",
    "ks:ks_name":"Deulapalli",
    "ks:ks_pop":70,
    "ks:ks_type":"VILLAGE",
    "name:eng_x_preferred":[
        "Deulapalli"
    ],
    "wof:name":"Deulapalli",
    "wof:placetype":"locality",
    "wof:population":70
},
  "geometry": {"coordinates":[84.87613,19.969458],"type":"Point"}
}