{
  "type": "Feature",
  "properties": {
    "iso:country":"IN",
    "ks:ks_name":"Akkaraipatty",
    "ks:ks_pop":104,
    "ks:ks_type":"HABITATION",
    "name:eng_x_preferred":[
        "Akkaraipatty"
    ],
    "wof:name":"Akkaraipatty",
    "wof:placetype":"locality",
    "wof:population":104
},
  "geometry": {"coordinates":[78.420045,10.852069],"type":"Point"}
}