{
  "type": "Feature",
  "properties": {
    "iso:country":"IN",
    "ks:ks_alt_nam":"Jowku hosur",
    "ks:ks_name":"Jowku Hosur",
    "ks:ks_pop":686,
    "ks:ks_type":"HABITATION",
    "name:eng_x_preferred":[
        "Jowku Hosur"
    ],
    "wof:name":"Jowku Hosur",
    "wof:placetype":"locality",
    "wof:population":686
},
  "geometry": {"coordinates":[76.649869,15.329605],"type":"Point"}
}