{
  "type": "Feature",
  "properties": {
    "iso:country":"IN",
    "ks:ks_name":"Sibnathpur",
    "ks:ks_pop":4416,
    "ks:ks_type":"VILLAGE",
    "name:eng_x_preferred":[
        "Sibnathpur"
    ],
    "wof:name":"Sibnathpur",
    "wof:placetype":"locality",
    "wof:population":4416
},
  "geometry": {"coordinates":[89.257406,26.598239],"type":"Point"}
}