{
  "type": "Feature",
  "properties": {
    "iso:country":"IN",
    "ks:ks_name":"Hardkhale",
    "ks:ks_pop":1608,
    "ks:ks_type":"VILLAGE",
    "name:eng_x_preferred":[
        "Hardkhale"
    ],
    "wof:name":"Hardkhale",
    "wof:placetype":"locality",
    "wof:population":1608
},
  "geometry": {"coordinates":[73.677998,16.813059],"type":"Point"}
}