{
  "type": "Feature",
  "properties": {
    "iso:country":"IN",
    "ks:ks_name":"Krishna Kr. Para",
    "ks:ks_pop":65,
    "ks:ks_type":"HABITATION",
    "name:eng_x_preferred":[
        "Krishna Kr. Para"
    ],
    "wof:name":"Krishna Kr. Para",
    "wof:placetype":"locality",
    "wof:population":65
},
  "geometry": {"coordinates":[91.451094,23.993089],"type":"Point"}
}