{
  "type": "Feature",
  "properties": {
    "iso:country":"IN",
    "ks:ks_alt_nam":"Kulapp\u0101kkam",
    "ks:ks_name":"Kulappakkam",
    "ks:ks_type":"VILLAGE",
    "ks:ks_uagg_main":0,
    "name:eng_x_preferred":[
        "Kulappakkam"
    ],
    "name:eng_x_variant":[
        "Kulapp\u0101kkam"
    ],
    "wof:name":"Kulappakkam",
    "wof:placetype":"neighbourhood"
},
  "geometry": {"coordinates":[79.234554,11.931673],"type":"Point"}
}