{
  "type": "Feature",
  "properties": {
    "iso:country":"IN",
    "ks:ks_name":"Samdaron Ka Tala",
    "ks:ks_pop":664,
    "ks:ks_type":"VILLAGE",
    "name:eng_x_preferred":[
        "Samdaron Ka Tala"
    ],
    "wof:name":"Samdaron Ka Tala",
    "wof:placetype":"locality",
    "wof:population":664
},
  "geometry": {"coordinates":[71.780719,25.585039],"type":"Point"}
}