{
  "type": "Feature",
  "properties": {
    "iso:country":"IN",
    "ks:ks_name":"Kalyanipuram",
    "ks:ks_pop":181,
    "ks:ks_type":"HABITATION",
    "name:eng_x_preferred":[
        "Kalyanipuram"
    ],
    "wof:name":"Kalyanipuram",
    "wof:placetype":"locality",
    "wof:population":181
},
  "geometry": {"coordinates":[77.88348499999999,9.010323],"type":"Point"}
}