{
  "type": "Feature",
  "properties": {
    "iso:country":"IN",
    "ks:ks_name":"Naguguda",
    "ks:ks_pop":44,
    "ks:ks_type":"HABITATION",
    "name:eng_x_preferred":[
        "Naguguda"
    ],
    "wof:name":"Naguguda",
    "wof:placetype":"locality",
    "wof:population":44
},
  "geometry": {"coordinates":[79.312943,19.150847],"type":"Point"}
}