{
  "type": "Feature",
  "properties": {
    "iso:country":"IN",
    "ks:ks_name":"Thoranakuruchi",
    "ks:ks_pop":258,
    "ks:ks_type":"HABITATION",
    "ks:ks_uagg_main":0,
    "name:eng_x_preferred":[
        "Thoranakuruchi"
    ],
    "wof:name":"Thoranakuruchi",
    "wof:placetype":"neighbourhood",
    "wof:population":258
},
  "geometry": {"coordinates":[77.655496,8.454514],"type":"Point"}
}