{
  "type": "Feature",
  "properties": {
    "iso:country":"IN",
    "ks:ks_name":"Jagtopa",
    "ks:ks_pop":144,
    "ks:ks_type":"VILLAGE",
    "name:eng_x_preferred":[
        "Jagtopa"
    ],
    "wof:name":"Jagtopa",
    "wof:placetype":"locality",
    "wof:population":144
},
  "geometry": {"coordinates":[86.67407799999999,24.199143],"type":"Point"}
}