{
  "type": "Feature",
  "properties": {
    "gn:admin1_code":"36.0",
    "gn:admin2_code":"174.0",
    "gn:asciiname":"Pipri Sadiqpur",
    "gn:country_code":"IN",
    "gn:dem":104,
    "gn:feature_class":"P",
    "gn:feature_code":"PPL",
    "gn:name":"Pipri S\u0101diqpur",
    "gn:population":0,
    "gn:timezone":"Asia/Kolkata",
    "iso:country":"IN",
    "name:und_x_variant":[
        "Pipri S\u0101diqpur",
        "Simraha"
    ],
    "wof:name":"Pipri Sadiqpur",
    "wof:placetype":"locality"
},
  "geometry": {"coordinates":[81.44241,25.43688],"type":"Point"}
}