{
  "type": "Feature",
  "properties": {
    "gn:admin1_code":"36",
    "gn:admin2_code":"173.0",
    "gn:asciiname":"Rampur Chauras",
    "gn:country_code":"IN",
    "gn:dem":103,
    "gn:feature_class":"P",
    "gn:feature_code":"PPL",
    "gn:name":"R\u0101mpur Chaur\u0101s",
    "gn:population":0,
    "gn:timezone":"Asia/Kolkata",
    "iso:country":"IN",
    "ks:ks_alt_nam":"R\u0101mpur Chaur\u0101s",
    "ks:ks_name":"Rampur Chauras",
    "ks:ks_type":"VILLAGE",
    "name:eng_x_preferred":[
        "Rampur Chauras"
    ],
    "name:eng_x_variant":[
        "R\u0101mpur Chaur\u0101s"
    ],
    "wof:name":"Rampur Chauras",
    "wof:placetype":"locality"
},
  "geometry": {"coordinates":[81.730216,25.848053],"type":"Point"}
}