{
  "type": "Feature",
  "properties": {
    "gn:admin1_code":"09",
    "gn:admin2_code":"484.0",
    "gn:asciiname":"Rajgarh",
    "gn:country_code":"IN",
    "gn:dem":129,
    "gn:feature_class":"P",
    "gn:feature_code":"PPL",
    "gn:name":"R\u0101jgarh",
    "gn:population":0,
    "gn:timezone":"Asia/Kolkata",
    "iso:country":"IN",
    "name:deu_x_preferred":[
        "Rajgarh"
    ],
    "name:ita_x_preferred":[
        "Rajgarh"
    ],
    "name:nld_x_preferred":[
        "Rajgarh"
    ],
    "name:pol_x_preferred":[
        "Rajgarh"
    ],
    "name:por_x_preferred":[
        "Rajgarh"
    ],
    "name:und_x_variant":[
        "Rajgad",
        "R\u0101jgarh"
    ],
    "name:urd_x_preferred":[
        "\u0631\u0627\u062c\u06af\u0691\u06be"
    ],
    "wof:name":"Rajgarh",
    "wof:placetype":"locality"
},
  "geometry": {"coordinates":[73.66545000000001,22.56631],"type":"Point"}
}