{
  "type": "Feature",
  "properties": {
    "iso:country":"IN",
    "ks:ks_name":"Molla",
    "ks:ks_pop":729,
    "ks:ks_type":"VILLAGE",
    "name:eng_x_preferred":[
        "Molla"
    ],
    "wof:name":"Molla",
    "wof:placetype":"locality",
    "wof:population":729
},
  "geometry": {"coordinates":[88.001102,23.910678],"type":"Point"}
}