{
  "type": "Feature",
  "properties": {
    "gn:admin1_code":"2.0",
    "gn:admin2_code":"548.0",
    "gn:asciiname":"Sankarapuram Siddhehayi",
    "gn:country_code":"IN",
    "gn:dem":114,
    "gn:feature_class":"P",
    "gn:feature_code":"PPL",
    "gn:name":"Sankar\u0101puram Siddheh\u0101yi",
    "gn:population":0,
    "gn:timezone":"Asia/Kolkata",
    "iso:country":"IN",
    "wof:name":"Sankarapuram Siddhehayi",
    "wof:placetype":"locality"
},
  "geometry": {"coordinates":[79.71511,16.52396],"type":"Point"}
}