{
  "type": "Feature",
  "properties": {
    "iso:country":"IN",
    "ks:ks_alt_nam":"BOJEWASTI",
    "ks:ks_name":"Bojewasti",
    "ks:ks_pop":289,
    "ks:ks_type":"HABITATION",
    "name:eng_x_preferred":[
        "Bojewasti"
    ],
    "wof:name":"Bojewasti",
    "wof:placetype":"locality",
    "wof:population":289
},
  "geometry": {"coordinates":[75.501152,16.98737],"type":"Point"}
}