{
  "type": "Feature",
  "properties": {
    "iso:country":"IN",
    "ks:ks_name":"Piplya",
    "ks:ks_pop":954,
    "ks:ks_type":"VILLAGE",
    "name:eng_x_preferred":[
        "Piplya"
    ],
    "wof:name":"Piplya",
    "wof:placetype":"locality",
    "wof:population":954
},
  "geometry": {"coordinates":[75.135932,22.482726],"type":"Point"}
}