{
  "type": "Feature",
  "properties": {
    "iso:country":"IN",
    "ks:ks_name":"Tungi",
    "ks:ks_pop":2328,
    "ks:ks_type":"VILLAGE",
    "ks:ks_uagg_main":0,
    "name:eng_x_preferred":[
        "Tungi"
    ],
    "wof:name":"Tungi",
    "wof:placetype":"neighbourhood",
    "wof:population":2328
},
  "geometry": {"coordinates":[88.42880100000001,23.830841],"type":"Point"}
}