{
  "type": "Feature",
  "properties": {
    "iso:country":"IN",
    "ks:ks_name":"Rajput Tola",
    "ks:ks_pop":1239,
    "ks:ks_type":"HABITATION",
    "name:eng_x_preferred":[
        "Rajput Tola"
    ],
    "wof:name":"Rajput Tola",
    "wof:placetype":"locality",
    "wof:population":1239
},
  "geometry": {"coordinates":[84.628275,26.240286],"type":"Point"}
}