{
  "type": "Feature",
  "properties": {
    "gn:admin1_code":"34.0",
    "gn:admin2_code":"230.0",
    "gn:asciiname":"Chhotka Kharwa",
    "gn:country_code":"IN",
    "gn:dem":65,
    "gn:feature_class":"P",
    "gn:feature_code":"PPL",
    "gn:name":"Chhotka Kharwa",
    "gn:population":0,
    "gn:timezone":"Asia/Kolkata",
    "iso:country":"IN",
    "ks:ks_name":"Chhotka Kharwa",
    "ks:ks_pop":3099,
    "ks:ks_type":"VILLAGE",
    "ks:ks_uagg_main":0,
    "name:eng_x_preferred":[
        "Chhotka Kharwa"
    ],
    "wof:name":"Chhotka Kharwa",
    "wof:placetype":"neighbourhood",
    "wof:population":3099
},
  "geometry": {"coordinates":[84.857986,25.381311],"type":"Point"}
}