{
  "type": "Feature",
  "properties": {
    "gn:admin1_code":"19.0",
    "gn:admin2_code":"568.0",
    "gn:asciiname":"Tavarekoppa",
    "gn:country_code":"IN",
    "gn:dem":621,
    "gn:feature_class":"P",
    "gn:feature_code":"PPL",
    "gn:name":"T\u0101varekoppa",
    "gn:population":0,
    "gn:timezone":"Asia/Kolkata",
    "iso:country":"IN",
    "ks:ks_alt_nam":"T\u0101varekoppa",
    "ks:ks_name":"Tavarekoppa",
    "ks:ks_pop":262,
    "ks:ks_type":"VILLAGE",
    "name:eng_x_preferred":[
        "Tavarekoppa"
    ],
    "name:eng_x_variant":[
        "T\u0101varekoppa"
    ],
    "wof:name":"Tavarekoppa",
    "wof:placetype":"locality",
    "wof:population":262
},
  "geometry": {"coordinates":[75.170812,14.358999],"type":"Point"}
}