{
  "type": "Feature",
  "properties": {
    "gn:admin1_code":"19.0",
    "gn:admin2_code":"568.0",
    "gn:asciiname":"Tavarekoppa",
    "gn:country_code":"IN",
    "gn:dem":621,
    "gn:feature_class":"P",
    "gn:feature_code":"PPL",
    "gn:name":"T\u0101varekoppa",
    "gn:population":0,
    "gn:timezone":"Asia/Kolkata",
    "iso:country":"IN",
    "wof:name":"Tavarekoppa",
    "wof:placetype":"locality"
},
  "geometry": {"coordinates":[75.17126999999998,14.35885],"type":"Point"}
}