{
  "type": "Feature",
  "properties": {
    "gn:admin1_code":"24",
    "gn:admin2_code":"118.0",
    "gn:asciiname":"Dailpura",
    "gn:country_code":"IN",
    "gn:dem":349,
    "gn:feature_class":"P",
    "gn:feature_code":"PPL",
    "gn:name":"Dailpura",
    "gn:population":0,
    "gn:timezone":"Asia/Kolkata",
    "iso:country":"IN",
    "wof:name":"Dailpura",
    "wof:placetype":"locality"
},
  "geometry": {"coordinates":[73.7723,25.51355],"type":"Point"}
}