{
  "type": "Feature",
  "properties": {
    "gn:admin1_code":"19.0",
    "gn:admin2_code":"583.0",
    "gn:asciiname":"Nalkadarenhalli",
    "gn:country_code":"IN",
    "gn:dem":910,
    "gn:feature_class":"P",
    "gn:feature_code":"PPL",
    "gn:name":"Nalkadarenhalli",
    "gn:population":0,
    "gn:timezone":"Asia/Kolkata",
    "iso:country":"IN",
    "wof:name":"Nalkadarenhalli",
    "wof:placetype":"locality"
},
  "geometry": {"coordinates":[77.62151999999998,13.37961],"type":"Point"}
}