{
  "type": "Feature",
  "properties": {
    "iso:country":"IN",
    "ks:ks_name":"Mutlapady Ayere",
    "ks:ks_pop":160,
    "ks:ks_type":"HABITATION",
    "name:eng_x_preferred":[
        "Mutlapady Ayere"
    ],
    "wof:name":"Mutlapady Ayere",
    "wof:placetype":"locality",
    "wof:population":160
},
  "geometry": {"coordinates":[75.05247199999999,13.360914],"type":"Point"}
}