{
  "type": "Feature",
  "properties": {
    "gn:admin1_code":"24.0",
    "gn:admin2_code":"104.0",
    "gn:asciiname":"Surajmukhi",
    "gn:country_code":"IN",
    "gn:dem":302,
    "gn:feature_class":"P",
    "gn:feature_code":"PPL",
    "gn:name":"Surajmukhi",
    "gn:population":0,
    "gn:timezone":"Asia/Kolkata",
    "iso:country":"IN",
    "wof:name":"Surajmukhi",
    "wof:placetype":"locality"
},
  "geometry": {"coordinates":[76.88576999999999,27.92702],"type":"Point"}
}