{
  "type": "Feature",
  "properties": {
    "iso:country":"IN",
    "ks:ks_name":"Bettamukhi",
    "ks:ks_pop":47,
    "ks:ks_type":"HABITATION",
    "name:eng_x_preferred":[
        "Bettamukhi"
    ],
    "wof:name":"Bettamukhi",
    "wof:placetype":"locality",
    "wof:population":47
},
  "geometry": {"coordinates":[75.629552,12.615306],"type":"Point"}
}