{
  "type": "Feature",
  "properties": {
    "iso:country":"IN",
    "ks:ks_name":"Kunthoor",
    "ks:ks_pop":2405,
    "ks:ks_type":"VILLAGE",
    "name:eng_x_preferred":[
        "Kunthoor"
    ],
    "wof:name":"Kunthoor",
    "wof:placetype":"locality",
    "wof:population":2405
},
  "geometry": {"coordinates":[75.39245,12.77054],"type":"Point"}
}