{
  "type": "Feature",
  "properties": {
    "gn:admin1_code":"19.0",
    "gn:admin2_code":"583.0",
    "gn:asciiname":"Bommanhalli",
    "gn:country_code":"IN",
    "gn:dem":890,
    "gn:feature_class":"P",
    "gn:feature_code":"PPL",
    "gn:name":"Bommanhalli",
    "gn:population":0,
    "gn:timezone":"Asia/Kolkata",
    "iso:country":"IN",
    "ks:ks_name":"Bommahalli",
    "ks:ks_pop":227,
    "ks:ks_type":"VILLAGE",
    "name:eng_x_preferred":[
        "Bommahalli"
    ],
    "name:eng_x_variant":[
        "Bommanhalli"
    ],
    "wof:name":"Bommahalli",
    "wof:placetype":"locality",
    "wof:population":227
},
  "geometry": {"coordinates":[77.359213,13.326933],"type":"Point"}
}