{
  "type": "Feature",
  "properties": {
    "gn:admin1_code":"36",
    "gn:admin2_code":"152.0",
    "gn:asciiname":"Farrukhpur Narayanpur",
    "gn:country_code":"IN",
    "gn:dem":155,
    "gn:feature_class":"P",
    "gn:feature_code":"PPL",
    "gn:name":"Farr\u016bkhpur Nar\u0101yanpur",
    "gn:population":0,
    "gn:timezone":"Asia/Kolkata",
    "iso:country":"IN",
    "wof:name":"Farrukhpur Narayanpur",
    "wof:placetype":"locality"
},
  "geometry": {"coordinates":[79.78404999999999,27.84388],"type":"Point"}
}