{
  "type": "Feature",
  "properties": {
    "iso:country":"IN",
    "ks:ks_name":"Mahijipura",
    "ks:ks_pop":268,
    "ks:ks_type":"HABITATION",
    "name:eng_x_preferred":[
        "Mahijipura"
    ],
    "wof:name":"Mahijipura",
    "wof:placetype":"locality",
    "wof:population":268
},
  "geometry": {"coordinates":[72.960222,22.323139],"type":"Point"}
}