{
  "type": "Feature",
  "properties": {
    "gn:admin1_code":"25.0",
    "gn:admin2_code":"633.0",
    "gn:asciiname":"Namasipalaiyam",
    "gn:country_code":"IN",
    "gn:dem":354,
    "gn:feature_class":"P",
    "gn:feature_code":"PPL",
    "gn:name":"Namasip\u0101laiyam",
    "gn:population":0,
    "gn:timezone":"Asia/Kolkata",
    "iso:country":"IN",
    "ks:ks_name":"Namachipalayam",
    "ks:ks_pop":136,
    "ks:ks_type":"HABITATION",
    "ks:ks_uagg_main":0,
    "name:eng_x_preferred":[
        "Namachipalayam"
    ],
    "wof:name":"Namachipalayam",
    "wof:placetype":"neighbourhood",
    "wof:population":136
},
  "geometry": {"coordinates":[77.27026499999999,11.263981],"type":"Point"}
}