{
  "type": "Feature",
  "properties": {
    "iso:country":"IN",
    "ks:ks_name":"Phulajodi",
    "ks:ks_pop":20,
    "ks:ks_type":"HABITATION",
    "name:eng_x_preferred":[
        "Phulajodi"
    ],
    "wof:name":"Phulajodi",
    "wof:placetype":"locality",
    "wof:population":20
},
  "geometry": {"coordinates":[83.030582,18.955313],"type":"Point"}
}