{
  "type": "Feature",
  "properties": {
    "iso:country":"IN",
    "ks:ks_alt_nam":"PURE CHUNNA KA PURA  HARI BASTI",
    "ks:ks_name":"Pure Chunna Ka Pura Hari Basti",
    "ks:ks_pop":54,
    "ks:ks_type":"HABITATION",
    "ks:ks_uagg_main":0,
    "name:eng_x_preferred":[
        "Pure Chunna Ka Pura Hari Basti"
    ],
    "name:eng_x_variant":[
        "PURE CHUNNA KA PURA  HARI BASTI"
    ],
    "wof:name":"Pure Chunna Ka Pura Hari Basti",
    "wof:placetype":"neighbourhood",
    "wof:population":54
},
  "geometry": {"coordinates":[82.245287,26.537843],"type":"Point"}
}