{
  "type": "Feature",
  "properties": {
    "gn:admin1_code":"39.0",
    "gn:admin2_code":"68.0",
    "gn:asciiname":"Sabalgarh",
    "gn:country_code":"IN",
    "gn:dem":274,
    "gn:feature_class":"P",
    "gn:feature_code":"PPL",
    "gn:name":"Sabalgarh",
    "gn:population":0,
    "gn:timezone":"Asia/Kolkata",
    "iso:country":"IN",
    "name:ben_x_preferred":[
        "\u09b8\u09ac\u09b2\u0997\u09a1\u09bc"
    ],
    "name:bpy_x_preferred":[
        "\u09b8\u09ac\u09b2\u0997\u09a1\u09bc"
    ],
    "name:ceb_x_preferred":[
        "Sabalgarh"
    ],
    "name:hif_x_preferred":[
        "Sabalgarh"
    ],
    "name:hin_x_preferred":[
        "\u0938\u092c\u0932\u0917\u0922\u093c"
    ],
    "name:ita_x_preferred":[
        "Sabalgarh"
    ],
    "name:msa_x_preferred":[
        "Sabalgarh"
    ],
    "name:ori_x_preferred":[
        "\u0b38\u0b3e\u0b2c\u0b32\u0b17\u0b21\u0b3c"
    ],
    "name:por_x_preferred":[
        "Sabalgarh"
    ],
    "name:spa_x_preferred":[
        "Sabalgarh"
    ],
    "name:swe_x_preferred":[
        "Sabalgarh"
    ],
    "name:urd_x_preferred":[
        "\u0633\u0628\u0644\u06af\u0627\u0691\u06be"
    ],
    "name:vie_x_preferred":[
        "Sabalgarh"
    ],
    "name:zho_x_preferred":[
        "\u8428\u5df4\u5c14\u52a0\u5c14"
    ],
    "wof:name":"Sabalgarh",
    "wof:placetype":"locality"
},
  "geometry": {"coordinates":[78.22805,29.72429],"type":"Point"}
}