{
  "type": "Feature",
  "properties": {
    "iso:country":"IN",
    "ks:ks_name":"Bandalwasti",
    "ks:ks_pop":130,
    "ks:ks_type":"HABITATION",
    "name:eng_x_preferred":[
        "Bandalwasti"
    ],
    "wof:name":"Bandalwasti",
    "wof:placetype":"locality",
    "wof:population":130
},
  "geometry": {"coordinates":[75.105225,17.761486],"type":"Point"}
}