{
  "type": "Feature",
  "properties": {
    "gn:admin1_code":"34.0",
    "gn:admin2_code":"224.0",
    "gn:asciiname":"Purnawatola",
    "gn:country_code":"IN",
    "gn:dem":37,
    "gn:feature_class":"P",
    "gn:feature_code":"PPL",
    "gn:name":"Purnaw\u0101tola",
    "gn:population":0,
    "gn:timezone":"Asia/Kolkata",
    "iso:country":"IN",
    "wof:name":"Purnawatola",
    "wof:placetype":"locality"
},
  "geometry": {"coordinates":[87.07049000000001,25.44976],"type":"Point"}
}