{
  "type": "Feature",
  "properties": {
    "iso:country":"IN",
    "ks:ks_name":"Henare",
    "ks:ks_pop":43,
    "ks:ks_type":"HABITATION",
    "name:eng_x_preferred":[
        "Henare"
    ],
    "wof:name":"Henare",
    "wof:placetype":"locality",
    "wof:population":43
},
  "geometry": {"coordinates":[75.352238,13.213891],"type":"Point"}
}