{
  "type": "Feature",
  "properties": {
    "iso:country":"IN",
    "ks:ks_name":"Kedwar",
    "ks:ks_pop":358,
    "ks:ks_type":"VILLAGE",
    "name:eng_x_preferred":[
        "Kedwar"
    ],
    "wof:name":"Kedwar",
    "wof:placetype":"locality",
    "wof:population":358
},
  "geometry": {"coordinates":[82.38922100000001,24.866959],"type":"Point"}
}