{
  "type": "Feature",
  "properties": {
    "gn:admin1_code":"19.0",
    "gn:admin2_code":"573.0",
    "gn:asciiname":"Bammenahalli",
    "gn:country_code":"IN",
    "gn:dem":903,
    "gn:feature_class":"P",
    "gn:feature_code":"PPL",
    "gn:name":"Bammenahalli",
    "gn:population":0,
    "gn:timezone":"Asia/Kolkata",
    "iso:country":"IN",
    "wof:name":"Bammenahalli",
    "wof:placetype":"locality"
},
  "geometry": {"coordinates":[76.66729000000002,12.87114],"type":"Point"}
}