{
  "type": "Feature",
  "properties": {
    "gn:admin1_code":"21.0",
    "gn:admin2_code":"399.0",
    "gn:asciiname":"Jigidiguda",
    "gn:country_code":"IN",
    "gn:dem":830,
    "gn:feature_class":"P",
    "gn:feature_code":"PPL",
    "gn:name":"Jigidig\u016bda",
    "gn:population":0,
    "gn:timezone":"Asia/Kolkata",
    "iso:country":"IN",
    "wof:name":"Jigidiguda",
    "wof:placetype":"locality"
},
  "geometry": {"coordinates":[82.36158,18.46904],"type":"Point"}
}