{
  "type": "Feature",
  "properties": {
    "iso:country":"IN",
    "ks:ks_name":"Mugavalli",
    "ks:ks_pop":709,
    "ks:ks_type":"HABITATION",
    "name:eng_x_preferred":[
        "Mugavalli"
    ],
    "wof:name":"Mugavalli",
    "wof:placetype":"locality",
    "wof:population":709
},
  "geometry": {"coordinates":[75.00006500000001,14.491239],"type":"Point"}
}