{
  "type": "Feature",
  "properties": {
    "iso:country":"IN",
    "ks:ks_name":"Maasatiwada",
    "ks:ks_pop":296,
    "ks:ks_type":"HABITATION",
    "name:eng_x_preferred":[
        "Maasatiwada"
    ],
    "wof:name":"Maasatiwada",
    "wof:placetype":"locality",
    "wof:population":296
},
  "geometry": {"coordinates":[74.24148,14.881917],"type":"Point"}
}