{
  "type": "Feature",
  "properties": {
    "iso:country":"IN",
    "ks:ks_name":"Borbil F V",
    "ks:ks_pop":209,
    "ks:ks_type":"HABITATION",
    "name:eng_x_preferred":[
        "Borbil F V"
    ],
    "wof:name":"Borbil F V",
    "wof:placetype":"locality",
    "wof:population":209
},
  "geometry": {"coordinates":[94.980237,27.30116],"type":"Point"}
}