{
  "type": "Feature",
  "properties": {
    "iso:country":"IN",
    "ks:ks_alt_nam":"GUJALEWASTI",
    "ks:ks_name":"Gujalewasti",
    "ks:ks_pop":121,
    "ks:ks_type":"HABITATION",
    "name:eng_x_preferred":[
        "Gujalewasti"
    ],
    "wof:name":"Gujalewasti",
    "wof:placetype":"locality",
    "wof:population":121
},
  "geometry": {"coordinates":[74.66078,17.284091],"type":"Point"}
}