{
  "type": "Feature",
  "properties": {
    "iso:country":"IN",
    "ks:ks_name":"Kakadmal",
    "ks:ks_pop":436,
    "ks:ks_type":"HABITATION",
    "name:eng_x_preferred":[
        "Kakadmal"
    ],
    "wof:name":"Kakadmal",
    "wof:placetype":"locality",
    "wof:population":436
},
  "geometry": {"coordinates":[74.98774899999999,21.588912],"type":"Point"}
}