{
  "type": "Feature",
  "properties": {
    "iso:country":"IN",
    "ks:ks_name":"Uttri Der",
    "ks:ks_pop":322,
    "ks:ks_type":"VILLAGE",
    "name:eng_x_preferred":[
        "Uttri Der"
    ],
    "wof:name":"Uttri Der",
    "wof:placetype":"locality",
    "wof:population":322
},
  "geometry": {"coordinates":[70.97251199999999,25.904277],"type":"Point"}
}