{
  "type": "Feature",
  "properties": {
    "gn:admin1_code":"19.0",
    "gn:admin2_code":"574.0",
    "gn:asciiname":"Kanhalli",
    "gn:country_code":"IN",
    "gn:dem":943,
    "gn:feature_class":"P",
    "gn:feature_code":"PPL",
    "gn:name":"K\u0101nhalli",
    "gn:population":0,
    "gn:timezone":"Asia/Kolkata",
    "iso:country":"IN",
    "name:ceb_x_preferred":[
        "Kanhalli"
    ],
    "name:swe_x_preferred":[
        "Kanhalli"
    ],
    "wof:name":"Kanhalli",
    "wof:placetype":"locality"
},
  "geometry": {"coordinates":[75.75136999999999,13.0492],"type":"Point"}
}