{
  "type": "Feature",
  "properties": {
    "iso:country":"IN",
    "ks:ks_name":"Kajalkura",
    "ks:ks_pop":0,
    "ks:ks_type":"VILLAGE",
    "name:eng_x_preferred":[
        "Kajalkura"
    ],
    "wof:name":"Kajalkura",
    "wof:placetype":"locality",
    "wof:population":0
},
  "geometry": {"coordinates":[86.74083299999999,22.984217],"type":"Point"}
}