{
  "type": "Feature",
  "properties": {
    "iso:country":"IN",
    "ks:ks_name":"Nuapari",
    "ks:ks_pop":530,
    "ks:ks_type":"VILLAGE",
    "ks:ks_uagg_main":0,
    "name:eng_x_preferred":[
        "Nuapari"
    ],
    "wof:name":"Nuapari",
    "wof:placetype":"neighbourhood",
    "wof:population":530
},
  "geometry": {"coordinates":[86.058722,20.334657],"type":"Point"}
}