{
  "type": "Feature",
  "properties": {
    "iso:country":"IN",
    "ks:ks_name":"Shevalalpur",
    "ks:ks_pop":1403,
    "ks:ks_type":"HABITATION",
    "ks:ks_uagg_main":0,
    "name:eng_x_preferred":[
        "Shevalalpur"
    ],
    "wof:name":"Shevalalpur",
    "wof:placetype":"neighbourhood",
    "wof:population":1403
},
  "geometry": {"coordinates":[75.401011,14.987153],"type":"Point"}
}