{
  "type": "Feature",
  "properties": {
    "iso:country":"IN",
    "ks:ks_alt_nam":"Chittilankavari HPeta",
    "ks:ks_name":"Chittilankavari Hpeta",
    "ks:ks_pop":368,
    "ks:ks_type":"HABITATION",
    "name:eng_x_preferred":[
        "Chittilankavari Hpeta"
    ],
    "wof:name":"Chittilankavari Hpeta",
    "wof:placetype":"locality",
    "wof:population":368
},
  "geometry": {"coordinates":[81.89775899999999,16.57316],"type":"Point"}
}