{
  "type": "Feature",
  "properties": {
    "iso:country":"IN",
    "ks:ks_name":"Kalakanta",
    "ks:ks_pop":23,
    "ks:ks_type":"HABITATION",
    "name:eng_x_preferred":[
        "Kalakanta"
    ],
    "wof:name":"Kalakanta",
    "wof:placetype":"locality",
    "wof:population":23
},
  "geometry": {"coordinates":[74.666864,14.552151],"type":"Point"}
}