{
  "type": "Feature",
  "properties": {
    "gn:admin1_code":"19.0",
    "gn:admin2_code":"570.0",
    "gn:asciiname":"Kusal",
    "gn:country_code":"IN",
    "gn:dem":692,
    "gn:feature_class":"P",
    "gn:feature_code":"PPL",
    "gn:name":"Kusal",
    "gn:population":0,
    "gn:timezone":"Asia/Kolkata",
    "iso:country":"IN",
    "name:ceb_x_preferred":[
        "Kusal"
    ],
    "name:swe_x_preferred":[
        "Kusal"
    ],
    "wof:name":"Kusal",
    "wof:placetype":"locality"
},
  "geometry": {"coordinates":[75.53453,13.50449],"type":"Point"}
}