{
  "type": "Feature",
  "properties": {
    "iso:country":"IN",
    "ks:ks_alt_nam":"N\u0101gamalai Reserved Forest",
    "ks:ks_name":"Nagamalai Reserved Forest",
    "ks:ks_type":"VILLAGE",
    "name:eng_x_preferred":[
        "Nagamalai Reserved Forest"
    ],
    "name:eng_x_variant":[
        "N\u0101gamalai Reserved Forest"
    ],
    "wof:name":"Nagamalai Reserved Forest",
    "wof:placetype":"locality"
},
  "geometry": {"coordinates":[77.96367100000001,9.977637],"type":"Point"}
}