{
  "type": "Feature",
  "properties": {
    "gn:admin1_code":"19.0",
    "gn:admin2_code":"573.0",
    "gn:asciiname":"Dudakanahalli",
    "gn:country_code":"IN",
    "gn:dem":808,
    "gn:feature_class":"P",
    "gn:feature_code":"PPL",
    "gn:name":"Dudakanahalli",
    "gn:population":0,
    "gn:timezone":"Asia/Kolkata",
    "iso:country":"IN",
    "wof:name":"Dudakanahalli",
    "wof:placetype":"locality"
},
  "geometry": {"coordinates":[76.37553,12.63417],"type":"Point"}
}