{
  "type": "Feature",
  "properties": {
    "gn:admin1_code":"24",
    "gn:admin2_code":"129.0",
    "gn:asciiname":"Mehidpur",
    "gn:country_code":"IN",
    "gn:dem":433,
    "gn:feature_class":"P",
    "gn:feature_code":"PPL",
    "gn:name":"Mehidpur",
    "gn:population":0,
    "gn:timezone":"Asia/Kolkata",
    "iso:country":"IN",
    "wof:name":"Mehidpur",
    "wof:placetype":"locality"
},
  "geometry": {"coordinates":[75.66667,23.81667],"type":"Point"}
}