{
  "type": "Feature",
  "properties": {
    "iso:country":"IN",
    "ks:ks_name":"Dibri",
    "ks:ks_pop":338,
    "ks:ks_type":"HABITATION",
    "name:eng_x_preferred":[
        "Dibri"
    ],
    "wof:name":"Dibri",
    "wof:placetype":"locality",
    "wof:population":338
},
  "geometry": {"coordinates":[80.060278,26.066944],"type":"Point"}
}