{
  "type": "Feature",
  "properties": {
    "gn:admin1_code":"37",
    "gn:admin2_code":"417.0",
    "gn:asciiname":"Jaitalur",
    "gn:country_code":"IN",
    "gn:dem":327,
    "gn:feature_class":"P",
    "gn:feature_code":"PPL",
    "gn:name":"Jaital\u016br",
    "gn:population":0,
    "gn:timezone":"Asia/Kolkata",
    "iso:country":"IN",
    "wof:name":"Jaitalur",
    "wof:placetype":"locality"
},
  "geometry": {"coordinates":[80.78074000000002,18.80864],"type":"Point"}
}