{
  "type": "Feature",
  "properties": {
    "iso:country":"IN",
    "ks:ks_name":"Kezhankndithazam",
    "ks:ks_pop":1407,
    "ks:ks_type":"HABITATION",
    "name:eng_x_preferred":[
        "Kezhankndithazam"
    ],
    "wof:name":"Kezhankndithazam",
    "wof:placetype":"locality",
    "wof:population":1407
},
  "geometry": {"coordinates":[75.860585,11.329933],"type":"Point"}
}