{
  "type": "Feature",
  "properties": {
    "iso:country":"IN",
    "ks:ks_name":"Subbareddygaripalli",
    "ks:ks_pop":77,
    "ks:ks_type":"HABITATION",
    "name:eng_x_preferred":[
        "Subbareddygaripalli"
    ],
    "wof:name":"Subbareddygaripalli",
    "wof:placetype":"locality",
    "wof:population":77
},
  "geometry": {"coordinates":[78.53859799999999,14.249612],"type":"Point"}
}