{
  "type": "Feature",
  "properties": {
    "iso:country":"IN",
    "ks:ks_name":"Nhavi Teliwadi",
    "ks:ks_pop":41,
    "ks:ks_type":"HABITATION",
    "name:eng_x_preferred":[
        "Nhavi Teliwadi"
    ],
    "wof:name":"Nhavi Teliwadi",
    "wof:placetype":"locality",
    "wof:population":41
},
  "geometry": {"coordinates":[73.647278,16.152861],"type":"Point"}
}