{
  "type": "Feature",
  "properties": {
    "iso:country":"IN",
    "ks:ks_name":"Kande Khalpati",
    "ks:ks_pop":468,
    "ks:ks_type":"VILLAGE",
    "name:eng_x_preferred":[
        "Kande Khalpati"
    ],
    "wof:name":"Kande Khalpati",
    "wof:placetype":"locality",
    "wof:population":468
},
  "geometry": {"coordinates":[79.144257,29.617815],"type":"Point"}
}