{
  "type": "Feature",
  "properties": {
    "iso:country":"IN",
    "ks:ks_name":"Tigalarapalya",
    "ks:ks_pop":207,
    "ks:ks_type":"HABITATION",
    "name:eng_x_preferred":[
        "Tigalarapalya"
    ],
    "wof:name":"Tigalarapalya",
    "wof:placetype":"locality",
    "wof:population":207
},
  "geometry": {"coordinates":[77.302995,13.417693],"type":"Point"}
}