{
  "type": "Feature",
  "properties": {
    "iso:country":"IN",
    "ks:ks_name":"Gadariya Ka Purwa",
    "ks:ks_pop":41,
    "ks:ks_type":"HABITATION",
    "name:eng_x_preferred":[
        "Gadariya Ka Purwa"
    ],
    "wof:name":"Gadariya Ka Purwa",
    "wof:placetype":"locality",
    "wof:population":41
},
  "geometry": {"coordinates":[82.15089399999999,26.598323],"type":"Point"}
}