{
  "type": "Feature",
  "properties": {
    "iso:country":"IN",
    "ks:ks_name":"Bhartoli",
    "ks:ks_pop":312,
    "ks:ks_type":"HABITATION",
    "name:eng_x_preferred":[
        "Bhartoli"
    ],
    "wof:name":"Bhartoli",
    "wof:placetype":"locality",
    "wof:population":312
},
  "geometry": {"coordinates":[83.95739,26.690607],"type":"Point"}
}