{
  "type": "Feature",
  "properties": {
    "iso:country":"IN",
    "ks:ks_name":"Damti Thunara",
    "ks:ks_pop":563,
    "ks:ks_type":"VILLAGE",
    "name:eng_x_preferred":[
        "Damti Thunara"
    ],
    "wof:name":"Damti Thunara",
    "wof:placetype":"locality",
    "wof:population":563
},
  "geometry": {"coordinates":[77.868467,31.013176],"type":"Point"}
}