{
  "type": "Feature",
  "properties": {
    "iso:country":"IN",
    "ks:ks_name":"Balijan Nc",
    "ks:ks_pop":340,
    "ks:ks_type":"VILLAGE",
    "name:eng_x_preferred":[
        "Balijan Nc"
    ],
    "wof:name":"Balijan Nc",
    "wof:placetype":"locality",
    "wof:population":340
},
  "geometry": {"coordinates":[93.553855,26.895865],"type":"Point"}
}