{
  "type": "Feature",
  "properties": {
    "iso:country":"IN",
    "ks:ks_name":"Sasthan Nada",
    "ks:ks_pop":960,
    "ks:ks_type":"HABITATION",
    "name:eng_x_preferred":[
        "Sasthan Nada"
    ],
    "wof:name":"Sasthan Nada",
    "wof:placetype":"locality",
    "wof:population":960
},
  "geometry": {"coordinates":[77.14200599999999,9.70754],"type":"Point"}
}