{
  "type": "Feature",
  "properties": {
    "gn:admin1_code":"37.0",
    "gn:admin2_code":"400.0",
    "gn:asciiname":"Bhaiswar",
    "gn:country_code":"IN",
    "gn:dem":807,
    "gn:feature_class":"P",
    "gn:feature_code":"PPL",
    "gn:name":"Bhaiswar",
    "gn:population":0,
    "gn:timezone":"Asia/Kolkata",
    "iso:country":"IN",
    "wof:name":"Bhaiswar",
    "wof:placetype":"locality"
},
  "geometry": {"coordinates":[82.41974999999999,23.45562],"type":"Point"}
}