{
  "type": "Feature",
  "properties": {
    "iso:country":"IN",
    "ks:ks_name":"Dauligar",
    "ks:ks_pop":7,
    "ks:ks_type":"VILLAGE",
    "name:eng_x_preferred":[
        "Dauligar"
    ],
    "wof:name":"Dauligar",
    "wof:placetype":"locality",
    "wof:population":7
},
  "geometry": {"coordinates":[80.013524,29.784294],"type":"Point"}
}