{
  "type": "Feature",
  "properties": {
    "iso:country":"IN",
    "ks:ks_name":"Khera",
    "ks:ks_type":"VILLAGE",
    "ks:ks_uagg_main":0,
    "name:eng_x_preferred":[
        "Khera"
    ],
    "wof:name":"Khera",
    "wof:placetype":"neighbourhood"
},
  "geometry": {"coordinates":[79.714704,28.225482],"type":"Point"}
}