{
  "type": "Feature",
  "properties": {
    "iso:country":"IN",
    "ks:ks_name":"Mugalpura",
    "ks:ks_pop":539,
    "ks:ks_type":"HABITATION",
    "name:eng_x_preferred":[
        "Mugalpura"
    ],
    "wof:name":"Mugalpura",
    "wof:placetype":"locality",
    "wof:population":539
},
  "geometry": {"coordinates":[77.38132299999999,26.535466],"type":"Point"}
}