{
  "type": "Feature",
  "properties": {
    "gn:admin1_code":"13.0",
    "gn:admin2_code":"589.0",
    "gn:asciiname":"Peralam",
    "gn:country_code":"IN",
    "gn:dem":13,
    "gn:feature_class":"P",
    "gn:feature_code":"PPL",
    "gn:name":"Peralam",
    "gn:population":0,
    "gn:timezone":"Asia/Kolkata",
    "iso:country":"IN",
    "name:bpy_x_preferred":[
        "\u09aa\u09c7\u09b0\u09be\u09b2\u09ae"
    ],
    "name:ita_x_preferred":[
        "Peralam"
    ],
    "name:msa_x_preferred":[
        "Peralam"
    ],
    "name:nld_x_preferred":[
        "Peralam"
    ],
    "name:por_x_preferred":[
        "Peralam"
    ],
    "name:tam_x_preferred":[
        "\u0baa\u0bc7\u0bb0\u0bb3\u0bae\u0bcd"
    ],
    "name:vie_x_preferred":[
        "Peralam"
    ],
    "name:zho_x_preferred":[
        "\u4f69\u62c9\u62c9\u59c6"
    ],
    "wof:name":"Peralam",
    "wof:placetype":"locality"
},
  "geometry": {"coordinates":[75.21423,12.16868],"type":"Point"}
}