{
  "type": "Feature",
  "properties": {
    "gn:admin1_code":"13.0",
    "gn:admin2_code":"589.0",
    "gn:asciiname":"Peralam",
    "gn:country_code":"IN",
    "gn:dem":13,
    "gn:feature_class":"P",
    "gn:feature_code":"PPL",
    "gn:name":"Peralam",
    "gn:population":0,
    "gn:timezone":"Asia/Kolkata",
    "iso:country":"IN",
    "wof:name":"Peralam",
    "wof:placetype":"locality"
},
  "geometry": {"coordinates":[75.21423,12.16868],"type":"Point"}
}