{
  "type": "Feature",
  "properties": {
    "gn:admin1_code":"35.0",
    "gn:admin2_code":"449.0",
    "gn:asciiname":"Gopalpur",
    "gn:country_code":"IN",
    "gn:dem":325,
    "gn:feature_class":"P",
    "gn:feature_code":"PPL",
    "gn:name":"Gop\u0101lpur",
    "gn:population":0,
    "gn:timezone":"Asia/Kolkata",
    "iso:country":"IN",
    "wof:name":"Gopalpur",
    "wof:placetype":"locality"
},
  "geometry": {"coordinates":[78.21947,22.76207],"type":"Point"}
}