{
  "type": "Feature",
  "properties": {
    "iso:country":"IN",
    "ks:ks_name":"Jogeswarpur",
    "ks:ks_pop":921,
    "ks:ks_type":"VILLAGE",
    "ks:ks_uagg_main":0,
    "name:eng_x_preferred":[
        "Jogeswarpur"
    ],
    "wof:name":"Jogeswarpur",
    "wof:placetype":"neighbourhood",
    "wof:population":921
},
  "geometry": {"coordinates":[86.13336200000001,20.032028],"type":"Point"}
}