{
  "type": "Feature",
  "properties": {
    "iso:country":"IN",
    "ks:ks_name":"Tangoli",
    "ks:ks_pop":71,
    "ks:ks_type":"VILLAGE",
    "name:eng_x_preferred":[
        "Tangoli"
    ],
    "wof:name":"Tangoli",
    "wof:placetype":"locality",
    "wof:population":71
},
  "geometry": {"coordinates":[78.72649699999999,30.001819],"type":"Point"}
}