{
  "type": "Feature",
  "properties": {
    "gn:admin1_code":"10",
    "gn:admin2_code":"87.0",
    "gn:asciiname":"Nangal Shahpur",
    "gn:country_code":"IN",
    "gn:dem":192,
    "gn:feature_class":"P",
    "gn:feature_code":"PPL",
    "gn:name":"N\u0101ngal Sh\u0101hpur",
    "gn:population":0,
    "gn:timezone":"Asia/Kolkata",
    "iso:country":"IN",
    "wof:name":"Nangal Shahpur",
    "wof:placetype":"locality"
},
  "geometry": {"coordinates":[77.04734999999999,27.97659],"type":"Point"}
}