{
  "type": "Feature",
  "properties": {
    "gn:admin1_code":"16.0",
    "gn:admin2_code":"499.0",
    "gn:asciiname":"Sabgavhan Budrukh",
    "gn:country_code":"IN",
    "gn:dem":196,
    "gn:feature_class":"P",
    "gn:feature_code":"PPL",
    "gn:name":"Sabgavh\u0101n Budrukh",
    "gn:population":0,
    "gn:timezone":"Asia/Kolkata",
    "iso:country":"IN",
    "wof:name":"Sabgavhan Budrukh",
    "wof:placetype":"locality"
},
  "geometry": {"coordinates":[74.97329000000001,21.10641],"type":"Point"}
}