{
  "type": "Feature",
  "properties": {
    "gn:admin1_code":"10.0",
    "gn:admin2_code":"76.0",
    "gn:asciiname":"Bega",
    "gn:country_code":"IN",
    "gn:dem":221,
    "gn:feature_class":"P",
    "gn:feature_code":"PPL",
    "gn:name":"B\u0113ga",
    "gn:population":0,
    "gn:timezone":"Asia/Kolkata",
    "iso:country":"IN",
    "wof:name":"Bega",
    "wof:placetype":"locality"
},
  "geometry": {"coordinates":[77.11221,29.15436],"type":"Point"}
}