{
  "type": "Feature",
  "properties": {
    "gn:admin1_code":"21.0",
    "gn:admin2_code":"396.0",
    "gn:asciiname":"Gambari",
    "gn:country_code":"IN",
    "gn:dem":550,
    "gn:feature_class":"P",
    "gn:feature_code":"PPL",
    "gn:name":"Gamb\u0101ri",
    "gn:population":0,
    "gn:timezone":"Asia/Kolkata",
    "iso:country":"IN",
    "ks:ks_name":"Gamberi",
    "ks:ks_pop":52,
    "ks:ks_type":"VILLAGE",
    "name:eng_x_preferred":[
        "Gamberi"
    ],
    "name:eng_x_variant":[
        "Gambari"
    ],
    "wof:name":"Gamberi",
    "wof:placetype":"locality",
    "wof:population":52
},
  "geometry": {"coordinates":[83.68503800000001,19.389765],"type":"Point"}
}