{
  "type": "Feature",
  "properties": {
    "gn:admin1_code":"36",
    "gn:admin2_code":"196.0",
    "gn:asciiname":"Bagaya",
    "gn:country_code":"IN",
    "gn:dem":82,
    "gn:feature_class":"P",
    "gn:feature_code":"PPL",
    "gn:name":"Bagaya",
    "gn:population":0,
    "gn:timezone":"Asia/Kolkata",
    "iso:country":"IN",
    "ks:ks_name":"Bagaya",
    "ks:ks_pop":569,
    "ks:ks_type":"VILLAGE",
    "name:ceb_x_preferred":[
        "Bagaya"
    ],
    "name:eng_x_preferred":[
        "Bagaya"
    ],
    "name:fra_x_preferred":[
        "Bagaya"
    ],
    "name:nld_x_preferred":[
        "Bagaya"
    ],
    "wof:name":"Bagaya",
    "wof:placetype":"locality",
    "wof:population":569
},
  "geometry": {"coordinates":[83.092167,25.217956],"type":"Point"}
}