{
  "type": "Feature",
  "properties": {
    "iso:country":"IN",
    "ks:ks_name":"Purbba Durgapur",
    "ks:ks_pop":2054,
    "ks:ks_type":"VILLAGE",
    "ks:ks_uagg_main":0,
    "name:eng_x_preferred":[
        "Purbba Durgapur"
    ],
    "wof:name":"Purbba Durgapur",
    "wof:placetype":"neighbourhood",
    "wof:population":2054
},
  "geometry": {"coordinates":[88.132364,22.753797],"type":"Point"}
}