{
  "type": "Feature",
  "properties": {
    "iso:country":"IN",
    "ks:ks_name":"Kakadpada",
    "ks:ks_pop":211,
    "ks:ks_type":"HABITATION",
    "name:eng_x_preferred":[
        "Kakadpada"
    ],
    "wof:name":"Kakadpada",
    "wof:placetype":"locality",
    "wof:population":211
},
  "geometry": {"coordinates":[72.860101,20.156771],"type":"Point"}
}