{
  "type": "Feature",
  "properties": {
    "gn:admin1_code":"34.0",
    "gn:admin2_code":"227.0",
    "gn:asciiname":"Naukadih",
    "gn:country_code":"IN",
    "gn:dem":49,
    "gn:feature_class":"P",
    "gn:feature_code":"PPL",
    "gn:name":"Nauk\u0101dih",
    "gn:population":0,
    "gn:timezone":"Asia/Kolkata",
    "iso:country":"IN",
    "ks:ks_alt_nam":"Nauk\u0101dih",
    "ks:ks_name":"Naukadih",
    "ks:ks_type":"VILLAGE",
    "ks:ks_uagg_main":0,
    "name:eng_x_preferred":[
        "Naukadih"
    ],
    "name:eng_x_variant":[
        "Nauk\u0101dih"
    ],
    "wof:name":"Naukadih",
    "wof:placetype":"neighbourhood"
},
  "geometry": {"coordinates":[86.21999099999999,25.159537],"type":"Point"}
}