{
  "type": "Feature",
  "properties": {
    "iso:country":"IN",
    "ks:ks_name":"Raghopur Bandh",
    "ks:ks_pop":510,
    "ks:ks_type":"HABITATION",
    "name:eng_x_preferred":[
        "Raghopur Bandh"
    ],
    "wof:name":"Raghopur Bandh",
    "wof:placetype":"locality",
    "wof:population":510
},
  "geometry": {"coordinates":[83.55817999999999,25.471348],"type":"Point"}
}