{
  "type": "Feature",
  "properties": {
    "iso:country":"IN",
    "ks:ks_name":"Lang Makang",
    "ks:ks_pop":25,
    "ks:ks_type":"HABITATION",
    "name:eng_x_preferred":[
        "Lang Makang"
    ],
    "wof:name":"Lang Makang",
    "wof:placetype":"locality",
    "wof:population":25
},
  "geometry": {"coordinates":[92.516757,25.81618],"type":"Point"}
}