{
  "type": "Feature",
  "properties": {
    "iso:country":"IN",
    "ks:ks_name":"Isamaili",
    "ks:ks_pop":404,
    "ks:ks_type":"HABITATION",
    "name:eng_x_preferred":[
        "Isamaili"
    ],
    "wof:name":"Isamaili",
    "wof:placetype":"locality",
    "wof:population":404
},
  "geometry": {"coordinates":[83.052029,27.179671],"type":"Point"}
}