{
  "type": "Feature",
  "properties": {
    "iso:country":"IN",
    "ks:ks_name":"Kottaikarai",
    "ks:ks_pop":195,
    "ks:ks_type":"HABITATION",
    "name:eng_x_preferred":[
        "Kottaikarai"
    ],
    "wof:name":"Kottaikarai",
    "wof:placetype":"locality",
    "wof:population":195
},
  "geometry": {"coordinates":[80.152585,13.45415],"type":"Point"}
}