{
  "type": "Feature",
  "properties": {
    "gn:admin1_code":"36.0",
    "gn:admin2_code":"179.0",
    "gn:asciiname":"Sansarpur",
    "gn:country_code":"IN",
    "gn:dem":110,
    "gn:feature_class":"P",
    "gn:feature_code":"PPL",
    "gn:name":"Sans\u0101rpur",
    "gn:population":0,
    "gn:timezone":"Asia/Kolkata",
    "iso:country":"IN",
    "name:ben_x_preferred":[
        "\u09b8\u0982\u09b8\u09be\u09b0\u09aa\u09c1\u09b0"
    ],
    "name:bpy_x_preferred":[
        "\u09b8\u0982\u09b8\u09be\u09b0\u09aa\u09c1\u09b0"
    ],
    "name:fra_x_preferred":[
        "Sansarpur"
    ],
    "name:ita_x_preferred":[
        "Sansarpur"
    ],
    "name:mlg_x_preferred":[
        "Sansarpur"
    ],
    "name:msa_x_preferred":[
        "Sansarpur"
    ],
    "name:nld_x_preferred":[
        "Sansarpur"
    ],
    "name:pan_x_preferred":[
        "\u0a38\u0a70\u0a38\u0a3e\u0a30\u0a2a\u0a41\u0a30"
    ],
    "name:pol_x_preferred":[
        "Sansarpur"
    ],
    "name:por_x_preferred":[
        "Sansarpur"
    ],
    "name:snd_x_preferred":[
        "\u0633\u0646\u0633\u0627\u0631\u067e\u0648\u0631"
    ],
    "name:tam_x_preferred":[
        "\u0b9a\u0ba9\u0bcd\u0b9a\u0bbe\u0bb0\u0bcd\u0baa\u0bc2\u0bb0\u0bcd"
    ],
    "name:tel_x_preferred":[
        "\u0c38\u0c28\u0c4d\u0c38\u0c3e\u0c30\u0c4d\u200c\u0c2a\u0c42\u0c30\u0c4d"
    ],
    "name:urd_x_preferred":[
        "\u0633\u0646\u0633\u0627\u0631\u067e\u0648\u0631"
    ],
    "name:vie_x_preferred":[
        "Sansarpur"
    ],
    "name:zho_x_preferred":[
        "\u6851\u8428\u5c14\u666e\u5c14"
    ],
    "wof:name":"Sansarpur",
    "wof:placetype":"locality"
},
  "geometry": {"coordinates":[81.59451999999997,26.64624],"type":"Point"}
}