{
  "type": "Feature",
  "properties": {
    "gn:admin1_code":"34.0",
    "gn:admin2_code":"204.0",
    "gn:asciiname":"Miskar",
    "gn:country_code":"IN",
    "gn:dem":69,
    "gn:feature_class":"P",
    "gn:feature_code":"PPL",
    "gn:name":"Miskar",
    "gn:population":0,
    "gn:timezone":"Asia/Kolkata",
    "iso:country":"IN",
    "wof:name":"Miskar",
    "wof:placetype":"locality"
},
  "geometry": {"coordinates":[84.91048000000001,26.54532],"type":"Point"}
}