{
  "type": "Feature",
  "properties": {
    "gn:admin1_code":"36.0",
    "gn:admin2_code":"160.0",
    "gn:asciiname":"Gutera",
    "gn:country_code":"IN",
    "gn:dem":149,
    "gn:feature_class":"P",
    "gn:feature_code":"PPL",
    "gn:name":"Gutera",
    "gn:population":0,
    "gn:timezone":"Asia/Kolkata",
    "iso:country":"IN",
    "wof:name":"Gutera",
    "wof:placetype":"locality"
},
  "geometry": {"coordinates":[79.36858000000002,26.95264],"type":"Point"}
}