{
  "type": "Feature",
  "properties": {
    "iso:country":"IN",
    "ks:ks_alt_nam":"Ramoshi vasti anphale",
    "ks:ks_name":"Ramoshi Vasti Anphale",
    "ks:ks_pop":288,
    "ks:ks_type":"HABITATION",
    "name:eng_x_preferred":[
        "Ramoshi Vasti Anphale"
    ],
    "wof:name":"Ramoshi Vasti Anphale",
    "wof:placetype":"locality",
    "wof:population":288
},
  "geometry": {"coordinates":[74.568263,17.476826],"type":"Point"}
}