{
  "type": "Feature",
  "properties": {
    "gn:admin1_code":"36.0",
    "gn:admin2_code":"161",
    "gn:asciiname":"Sukhdaspur",
    "gn:country_code":"IN",
    "gn:dem":153,
    "gn:feature_class":"P",
    "gn:feature_code":"PPL",
    "gn:name":"Sukhd\u0101spur",
    "gn:population":0,
    "gn:timezone":"Asia/Kolkata",
    "iso:country":"IN",
    "name:und_x_variant":[
        "Sukhd\u0101spur",
        "Sukhdaspur"
    ],
    "wof:name":"Sukhdaspur",
    "wof:placetype":"locality"
},
  "geometry": {"coordinates":[79.11345,26.96883],"type":"Point"}
}