{
  "type": "Feature",
  "properties": {
    "gn:admin1_code":"35",
    "gn:admin2_code":"443.0",
    "gn:asciiname":"Pathari",
    "gn:country_code":"IN",
    "gn:dem":472,
    "gn:feature_class":"P",
    "gn:feature_code":"PPL",
    "gn:name":"Path\u0101ri",
    "gn:population":0,
    "gn:timezone":"Asia/Kolkata",
    "iso:country":"IN",
    "name:und_x_variant":[
        "Path\u0101ri"
    ],
    "wof:name":"Pathari",
    "wof:placetype":"locality"
},
  "geometry": {"coordinates":[78.21958000000002,23.93706],"type":"Point"}
}