{
  "type": "Feature",
  "properties": {
    "iso:country":"IN",
    "ks:ks_name":"Chadakmara",
    "ks:ks_pop":216,
    "ks:ks_type":"HABITATION",
    "name:eng_x_preferred":[
        "Chadakmara"
    ],
    "wof:name":"Chadakmara",
    "wof:placetype":"locality",
    "wof:population":216
},
  "geometry": {"coordinates":[84.723226,21.373035],"type":"Point"}
}