{
  "type": "Feature",
  "properties": {
    "gn:admin1_code":"13.0",
    "gn:admin2_code":"591.0",
    "gn:asciiname":"Aduvad",
    "gn:country_code":"IN",
    "gn:dem":63,
    "gn:feature_class":"P",
    "gn:feature_code":"PPL",
    "gn:name":"Aduvad",
    "gn:population":0,
    "gn:timezone":"Asia/Kolkata",
    "iso:country":"IN",
    "wof:name":"Aduvad",
    "wof:placetype":"locality"
},
  "geometry": {"coordinates":[75.95281999999997,11.2732],"type":"Point"}
}