{
  "type": "Feature",
  "properties": {
    "iso:country":"IN",
    "ks:ks_alt_nam":"KALYANWADI",
    "ks:ks_name":"Kalyanwadi",
    "ks:ks_pop":4116,
    "ks:ks_type":"HABITATION",
    "name:eng_x_preferred":[
        "Kalyanwadi"
    ],
    "wof:name":"Kalyanwadi",
    "wof:placetype":"locality",
    "wof:population":4116
},
  "geometry": {"coordinates":[74.517167,16.777153],"type":"Point"}
}