{
  "type": "Feature",
  "properties": {
    "iso:country":"IN",
    "ks:ks_name":"M Colony",
    "ks:ks_pop":149,
    "ks:ks_type":"HABITATION",
    "name:eng_x_preferred":[
        "M Colony"
    ],
    "wof:name":"M Colony",
    "wof:placetype":"locality",
    "wof:population":149
},
  "geometry": {"coordinates":[76.609117,13.188496],"type":"Point"}
}