{
  "type": "Feature",
  "properties": {
    "iso:country":"IN",
    "ks:ks_name":"Savaskanapalli",
    "ks:ks_pop":137,
    "ks:ks_type":"HABITATION",
    "ks:ks_uagg_main":0,
    "name:eng_x_preferred":[
        "Savaskanapalli"
    ],
    "wof:name":"Savaskanapalli",
    "wof:placetype":"neighbourhood",
    "wof:population":137
},
  "geometry": {"coordinates":[78.665415,14.447526],"type":"Point"}
}