{
  "type": "Feature",
  "properties": {
    "gn:admin1_code":"37",
    "gn:admin2_code":"413.0",
    "gn:asciiname":"Ghotia",
    "gn:country_code":"IN",
    "gn:dem":378,
    "gn:feature_class":"P",
    "gn:feature_code":"PPL",
    "gn:name":"Ghotia",
    "gn:population":0,
    "gn:timezone":"Asia/Kolkata",
    "iso:country":"IN",
    "ks:ks_name":"Ghotia",
    "ks:ks_type":"VILLAGE",
    "name:eng_x_preferred":[
        "Ghotia"
    ],
    "wof:name":"Ghotia",
    "wof:placetype":"locality"
},
  "geometry": {"coordinates":[81.03570999999999,20.22857],"type":"Point"}
}