{
  "type": "Feature",
  "properties": {
    "iso:country":"IN",
    "ks:ks_name":"Shirvanjkhed",
    "ks:ks_type":"VILLAGE",
    "name:eng_x_preferred":[
        "Shirvanjkhed"
    ],
    "wof:name":"Shirvanjkhed",
    "wof:placetype":"locality"
},
  "geometry": {"coordinates":[77.293239,20.643503],"type":"Point"}
}