{
  "type": "Feature",
  "properties": {
    "iso:country":"IN",
    "ks:ks_name":"Kabgal",
    "ks:ks_pop":227,
    "ks:ks_type":"VILLAGE",
    "name:eng_x_preferred":[
        "Kabgal"
    ],
    "wof:name":"Kabgal",
    "wof:placetype":"locality",
    "wof:population":227
},
  "geometry": {"coordinates":[74.480138,14.586668],"type":"Point"}
}