{
  "type": "Feature",
  "properties": {
    "iso:country":"IN",
    "ks:ks_name":"Mandal Tola",
    "ks:ks_pop":285,
    "ks:ks_type":"HABITATION",
    "ks:ks_uagg_main":0,
    "name:eng_x_preferred":[
        "Mandal Tola"
    ],
    "wof:name":"Mandal Tola",
    "wof:placetype":"neighbourhood",
    "wof:population":285
},
  "geometry": {"coordinates":[87.114211,25.631009],"type":"Point"}
}