{
  "type": "Feature",
  "properties": {
    "iso:country":"IN",
    "ks:ks_name":"S Gollarahatti",
    "ks:ks_pop":337,
    "ks:ks_type":"HABITATION",
    "name:eng_x_preferred":[
        "S Gollarahatti"
    ],
    "wof:name":"S Gollarahatti",
    "wof:placetype":"locality",
    "wof:population":337
},
  "geometry": {"coordinates":[76.46517,14.879566],"type":"Point"}
}