{
  "type": "Feature",
  "properties": {
    "iso:country":"IN",
    "ks:ks_name":"Aniguda",
    "ks:ks_pop":198,
    "ks:ks_type":"HABITATION",
    "name:eng_x_preferred":[
        "Aniguda"
    ],
    "wof:name":"Aniguda",
    "wof:placetype":"locality",
    "wof:population":198
},
  "geometry": {"coordinates":[82.44922,19.414707],"type":"Point"}
}