{
  "type": "Feature",
  "properties": {
    "iso:country":"IN",
    "ks:ks_name":"Dhakarkhedi",
    "ks:ks_pop":681,
    "ks:ks_type":"HABITATION",
    "name:eng_x_preferred":[
        "Dhakarkhedi"
    ],
    "wof:name":"Dhakarkhedi",
    "wof:placetype":"locality",
    "wof:population":681
},
  "geometry": {"coordinates":[75.225505,24.626865],"type":"Point"}
}