{
  "type": "Feature",
  "properties": {
    "iso:country":"IN",
    "ks:ks_name":"East Mikirgaon",
    "ks:ks_pop":296,
    "ks:ks_type":"HABITATION",
    "ks:ks_uagg_main":0,
    "name:eng_x_preferred":[
        "East Mikirgaon"
    ],
    "wof:name":"East Mikirgaon",
    "wof:placetype":"neighbourhood",
    "wof:population":296
},
  "geometry": {"coordinates":[92.73532899999999,26.161304],"type":"Point"}
}