{
  "type": "Feature",
  "properties": {
    "iso:country":"IN",
    "ks:ks_name":"Baira",
    "ks:ks_pop":57,
    "ks:ks_type":"HABITATION",
    "name:eng_x_preferred":[
        "Baira"
    ],
    "wof:name":"Baira",
    "wof:placetype":"locality",
    "wof:population":57
},
  "geometry": {"coordinates":[80.05853500000001,29.243849],"type":"Point"}
}