{
  "type": "Feature",
  "properties": {
    "iso:country":"IN",
    "ks:ks_name":"Khash Chak",
    "ks:ks_pop":184,
    "ks:ks_type":"VILLAGE",
    "name:eng_x_preferred":[
        "Khash Chak"
    ],
    "wof:name":"Khash Chak",
    "wof:placetype":"locality",
    "wof:population":184
},
  "geometry": {"coordinates":[87.761143,22.496757],"type":"Point"}
}