{
  "type": "Feature",
  "properties": {
    "gn:admin1_code":"25.0",
    "gn:admin2_code":"625",
    "gn:asciiname":"Kodandaramaswami",
    "gn:country_code":"IN",
    "gn:dem":2,
    "gn:feature_class":"P",
    "gn:feature_code":"PPL",
    "gn:name":"Kodandar\u0101masw\u0101mi",
    "gn:population":0,
    "gn:timezone":"Asia/Kolkata",
    "iso:country":"IN",
    "wof:name":"Kodandaramaswami",
    "wof:placetype":"locality"
},
  "geometry": {"coordinates":[79.34768000000003,9.23269],"type":"Point"}
}