{
  "type": "Feature",
  "properties": {
    "iso:country":"IN",
    "ks:ks_name":"Hetalnar",
    "ks:ks_pop":219,
    "ks:ks_type":"HABITATION",
    "name:eng_x_preferred":[
        "Hetalnar"
    ],
    "wof:name":"Hetalnar",
    "wof:placetype":"locality",
    "wof:population":219
},
  "geometry": {"coordinates":[81.109877,19.656492],"type":"Point"}
}