{
  "type": "Feature",
  "properties": {
    "iso:country":"IN",
    "ks:ks_name":"Palasbani",
    "ks:ks_pop":807,
    "ks:ks_type":"VILLAGE",
    "name:eng_x_preferred":[
        "Palasbani"
    ],
    "wof:name":"Palasbani",
    "wof:placetype":"locality",
    "wof:population":807
},
  "geometry": {"coordinates":[86.71346200000001,22.000621],"type":"Point"}
}