{
  "type": "Feature",
  "properties": {
    "iso:country":"IN",
    "ks:ks_name":"Joygram",
    "ks:ks_pop":1124,
    "ks:ks_type":"HABITATION",
    "name:eng_x_preferred":[
        "Joygram"
    ],
    "wof:name":"Joygram",
    "wof:placetype":"locality",
    "wof:population":1124
},
  "geometry": {"coordinates":[88.738805,22.508377],"type":"Point"}
}