{
  "type": "Feature",
  "properties": {
    "gn:country":"IN",
    "gn:fcode":"PPL",
    "gn:pop":0,
    "iso:country":"IN",
    "name:ben_x_preferred":[
        "\u0995\u09be\u099e\u09cd\u099c\u09bf\u09b0\u09be\u09aa\u09b2\u09cd\u09b2\u09c0"
    ],
    "name:deu_x_preferred":[
        "Kanjirappally"
    ],
    "name:eng_x_preferred":[
        "Kanjirappally"
    ],
    "name:fra_x_preferred":[
        "Kanjirappally"
    ],
    "name:guj_x_preferred":[
        "\u0a95\u0abe\u0aa8\u0acd\u0a9c\u0ac0\u0ab0\u0abe\u0aaa\u0ab2\u0acd\u0ab2\u0ac0"
    ],
    "name:hin_x_preferred":[
        "\u0915\u093e\u0902\u091c\u093f\u0930\u093e\u092a\u0932\u094d\u0932\u0940"
    ],
    "name:jpn_x_preferred":[
        "\u30ab\u30f3\u30b8\u30e9\u30c3\u30d1\u30ea\u30fc"
    ],
    "name:kan_x_preferred":[
        "\u0c95\u0c82\u0c9c\u0cbf\u0cb0\u0caa\u0ccd\u0caa\u0cb3\u0ccd\u0cb3\u0cbf"
    ],
    "name:kor_x_preferred":[
        "\uce78\uc9c0\ub77c\ud314\ub9ac"
    ],
    "name:mal_x_preferred":[
        "\u0d15\u0d3e\u0d1e\u0d4d\u0d1e\u0d3f\u0d30\u0d2a\u0d4d\u0d2a\u0d33\u0d4d\u0d33\u0d3f"
    ],
    "name:nld_x_preferred":[
        "Kanjirappally"
    ],
    "name:pol_x_preferred":[
        "Kanjirappally"
    ],
    "name:por_x_preferred":[
        "Kanjirappally"
    ],
    "name:rus_x_preferred":[
        "\u041a\u0430\u043d\u0434\u0436\u0438\u0440\u0430\u043f\u0430\u043b\u043b\u0438"
    ],
    "name:spa_x_preferred":[
        "Kanjirappally"
    ],
    "name:tam_x_preferred":[
        "\u0b95\u0bbe\u0b9e\u0bcd\u0b9a\u0bbf\u0bb0\u0baa\u0bcd\u0baa\u0bb2\u0bcd\u0bb2\u0bbf"
    ],
    "name:tel_x_preferred":[
        "\u0c15\u0c02\u0c1c\u0c3f\u0c30\u0c2a\u0c32\u0c4d\u0c32\u0c3f"
    ],
    "name:unk_x_variant":[
        "Kanjaripalli"
    ],
    "name:urd_x_preferred":[
        "\u06a9\u0646\u062c\u06cc\u0631\u0627\u067e\u0644\u06cc"
    ],
    "qs:name":"Kanjirappally",
    "qs:name_adm0":"India",
    "qs:name_adm1":"Kerala",
    "qs:photos":33,
    "qs:photos_1k":7,
    "qs:photos_9k":1,
    "qs:photos_9r":2,
    "qs:photos_all":33,
    "qs:photos_sr":2,
    "qs:placetype":"Town",
    "qs:pop_sr":"7",
    "wd:wordcount":2263,
    "wof:name":"Kanjirappally",
    "wof:placetype":"locality",
    "wof:population":0
},
  "geometry": {"coordinates":[76.78975,9.55451],"type":"Point"}
}