{
  "type": "Feature",
  "properties": {
    "gn:admin1_code":"12.0",
    "gn:admin2_code":"18.0",
    "gn:asciiname":"Gooandera",
    "gn:country_code":"IN",
    "gn:dem":3406,
    "gn:feature_class":"P",
    "gn:feature_code":"PPL",
    "gn:name":"G\u014doand\u0113ra",
    "gn:population":0,
    "gn:timezone":"Asia/Kolkata",
    "iso:country":"IN",
    "wof:name":"Gooandera",
    "wof:placetype":"locality"
},
  "geometry": {"coordinates":[75.90196999999998,33.46313],"type":"Point"}
}