{
  "type": "Feature",
  "properties": {
    "gn:admin1_code":"24.0",
    "gn:admin2_code":"099",
    "gn:asciiname":"Singrasar",
    "gn:country_code":"IN",
    "gn:dem":198,
    "gn:feature_class":"P",
    "gn:feature_code":"PPL",
    "gn:name":"Singr\u0101sar",
    "gn:population":0,
    "gn:timezone":"Asia/Kolkata",
    "iso:country":"IN",
    "wof:name":"Singrasar",
    "wof:placetype":"locality"
},
  "geometry": {"coordinates":[73.98487,28.96474000000001],"type":"Point"}
}