{
  "type": "Feature",
  "properties": {
    "iso:country":"IN",
    "ks:ks_alt_nam":"BELSAREWASTI NALEWASTI",
    "ks:ks_name":"Belsarewasti Nalewasti",
    "ks:ks_pop":165,
    "ks:ks_type":"HABITATION",
    "name:eng_x_preferred":[
        "Belsarewasti Nalewasti"
    ],
    "wof:name":"Belsarewasti Nalewasti",
    "wof:placetype":"locality",
    "wof:population":165
},
  "geometry": {"coordinates":[75.06889099999999,18.409473],"type":"Point"}
}