{
  "type": "Feature",
  "properties": {
    "iso:country":"IN",
    "ks:ks_alt_nam":"haruakaman",
    "ks:ks_name":"Haruakaman",
    "ks:ks_pop":950,
    "ks:ks_type":"HABITATION",
    "name:eng_x_preferred":[
        "Haruakaman"
    ],
    "wof:name":"Haruakaman",
    "wof:placetype":"locality",
    "wof:population":950
},
  "geometry": {"coordinates":[85.80158,22.067745],"type":"Point"}
}