{
  "type": "Feature",
  "properties": {
    "iso:country":"IN",
    "ks:ks_name":"Pachim Bhalaguri Gaon",
    "ks:ks_pop":79,
    "ks:ks_type":"HABITATION",
    "ks:ks_uagg_main":0,
    "name:eng_x_preferred":[
        "Pachim Bhalaguri Gaon"
    ],
    "wof:name":"Pachim Bhalaguri Gaon",
    "wof:placetype":"neighbourhood",
    "wof:population":79
},
  "geometry": {"coordinates":[90.937555,26.620574],"type":"Point"}
}