{
  "type": "Feature",
  "properties": {
    "iso:country":"IN",
    "ks:ks_name":"Ramadeipur",
    "ks:ks_pop":0,
    "ks:ks_type":"VILLAGE",
    "name:eng_x_preferred":[
        "Ramadeipur"
    ],
    "wof:name":"Ramadeipur",
    "wof:placetype":"locality",
    "wof:population":0
},
  "geometry": {"coordinates":[87.239248,21.653971],"type":"Point"}
}