{
  "type": "Feature",
  "properties": {
    "gn:admin1_code":"19.0",
    "gn:admin2_code":"581.0",
    "gn:asciiname":"Mudavatti",
    "gn:country_code":"IN",
    "gn:dem":873,
    "gn:feature_class":"P",
    "gn:feature_code":"PPL",
    "gn:name":"Mudavatti",
    "gn:population":0,
    "gn:timezone":"Asia/Kolkata",
    "iso:country":"IN",
    "wof:name":"Mudavatti",
    "wof:placetype":"locality"
},
  "geometry": {"coordinates":[78.08915,13.0693],"type":"Point"}
}