{
  "type": "Feature",
  "properties": {
    "iso:country":"IN",
    "ks:ks_name":"Gouraanga Pally",
    "ks:ks_pop":1038,
    "ks:ks_type":"HABITATION",
    "name:eng_x_preferred":[
        "Gouraanga Pally"
    ],
    "wof:name":"Gouraanga Pally",
    "wof:placetype":"locality",
    "wof:population":1038
},
  "geometry": {"coordinates":[88.412324,21.82122],"type":"Point"}
}