{
  "type": "Feature",
  "properties": {
    "gn:admin1_code":"16.0",
    "gn:admin2_code":"498.0",
    "gn:asciiname":"Jamkhel Pada",
    "gn:country_code":"IN",
    "gn:dem":621,
    "gn:feature_class":"P",
    "gn:feature_code":"PPL",
    "gn:name":"J\u0101mkhel P\u0101da",
    "gn:population":0,
    "gn:timezone":"Asia/Kolkata",
    "iso:country":"IN",
    "wof:name":"Jamkhel Pada",
    "wof:placetype":"neighbourhood"
},
  "geometry": {"coordinates":[74.05867000000001,21.05762],"type":"Point"}
}