{
  "type": "Feature",
  "properties": {
    "iso:country":"IN",
    "ks:ks_name":"Katvalanan",
    "ks:ks_pop":71,
    "ks:ks_type":"HABITATION",
    "ks:ks_uagg_main":0,
    "name:eng_x_preferred":[
        "Katvalanan"
    ],
    "wof:name":"Katvalanan",
    "wof:placetype":"neighbourhood",
    "wof:population":71
},
  "geometry": {"coordinates":[81.49351799999999,27.243758],"type":"Point"}
}