{
  "type": "Feature",
  "properties": {
    "iso:country":"IN",
    "ks:ks_name":"Amtaha",
    "ks:ks_type":"VILLAGE",
    "name:eng_x_preferred":[
        "Amtaha"
    ],
    "wof:name":"Amtaha",
    "wof:placetype":"locality"
},
  "geometry": {"coordinates":[86.132396,24.642143],"type":"Point"}
}