{
  "type": "Feature",
  "properties": {
    "gn:admin1_code":"35",
    "gn:admin2_code":"440.0",
    "gn:asciiname":"Pokhar Buzurg",
    "gn:country_code":"IN",
    "gn:dem":278,
    "gn:feature_class":"P",
    "gn:feature_code":"PPL",
    "gn:name":"Pokhar Buzurg",
    "gn:population":0,
    "gn:timezone":"Asia/Kolkata",
    "iso:country":"IN",
    "ks:ks_name":"Pokhar Buzurg",
    "ks:ks_type":"VILLAGE",
    "name:eng_x_preferred":[
        "Pokhar Buzurg"
    ],
    "wof:name":"Pokhar Buzurg",
    "wof:placetype":"locality"
},
  "geometry": {"coordinates":[75.57353500000001,21.9135],"type":"Point"}
}