{
  "type": "Feature",
  "properties": {
    "iso:country":"IN",
    "ks:ks_name":"Mangaliya Khora",
    "ks:ks_pop":189,
    "ks:ks_type":"VILLAGE",
    "name:eng_x_preferred":[
        "Mangaliya Khora"
    ],
    "wof:name":"Mangaliya Khora",
    "wof:placetype":"locality",
    "wof:population":189
},
  "geometry": {"coordinates":[74.55868100000001,23.428525],"type":"Point"}
}