{
  "type": "Feature",
  "properties": {
    "gn:admin1_code":"11",
    "gn:admin2_code":"24.0",
    "gn:asciiname":"Bhujlang",
    "gn:country_code":"IN",
    "gn:dem":2165,
    "gn:feature_class":"P",
    "gn:feature_code":"PPL",
    "gn:name":"Bhujlang",
    "gn:population":0,
    "gn:timezone":"Asia/Kolkata",
    "iso:country":"IN",
    "wof:name":"Bhujlang",
    "wof:placetype":"locality"
},
  "geometry": {"coordinates":[76.85529,32.10276],"type":"Point"}
}