{
  "type": "Feature",
  "properties": {
    "gn:admin1_code":"39.0",
    "gn:admin2_code":"61.0",
    "gn:asciiname":"Bhainswara",
    "gn:country_code":"IN",
    "gn:dem":1637,
    "gn:feature_class":"P",
    "gn:feature_code":"PPL",
    "gn:name":"Bhainsw\u0101ra",
    "gn:population":0,
    "gn:timezone":"Asia/Kolkata",
    "iso:country":"IN",
    "wof:name":"Bhainswara",
    "wof:placetype":"locality"
},
  "geometry": {"coordinates":[79.06379,29.88741],"type":"Point"}
}