{
  "type": "Feature",
  "properties": {
    "iso:country":"IN",
    "ks:ks_name":"Padebettu",
    "ks:ks_pop":100,
    "ks:ks_type":"HABITATION",
    "name:eng_x_preferred":[
        "Padebettu"
    ],
    "wof:name":"Padebettu",
    "wof:placetype":"locality",
    "wof:population":100
},
  "geometry": {"coordinates":[75.371591,13.120866],"type":"Point"}
}