{
  "type": "Feature",
  "properties": {
    "iso:country":"IN",
    "ks:ks_name":"Pattakalam",
    "ks:ks_pop":1762,
    "ks:ks_type":"HABITATION",
    "name:eng_x_preferred":[
        "Pattakalam"
    ],
    "wof:name":"Pattakalam",
    "wof:placetype":"locality",
    "wof:population":1762
},
  "geometry": {"coordinates":[75.50641899999999,12.172095],"type":"Point"}
}