{
  "type": "Feature",
  "properties": {
    "iso:country":"IN",
    "ks:ks_name":"Pungasur",
    "ks:ks_pop":30,
    "ks:ks_type":"VILLAGE",
    "name:eng_x_preferred":[
        "Pungasur"
    ],
    "wof:name":"Pungasur",
    "wof:placetype":"locality",
    "wof:population":30
},
  "geometry": {"coordinates":[80.844759,19.456806],"type":"Point"}
}