{
  "type": "Feature",
  "properties": {
    "iso:country":"IN",
    "ks:ks_alt_nam":"gondarkeri",
    "ks:ks_name":"Gondarkeri",
    "ks:ks_pop":93,
    "ks:ks_type":"HABITATION",
    "name:eng_x_preferred":[
        "Gondarkeri"
    ],
    "wof:name":"Gondarkeri",
    "wof:placetype":"locality",
    "wof:population":93
},
  "geometry": {"coordinates":[74.61754500000001,13.993692],"type":"Point"}
}