{
  "type": "Feature",
  "properties": {
    "iso:country":"IN",
    "ks:ks_name":"Doodaliya",
    "ks:ks_pop":311,
    "ks:ks_type":"VILLAGE",
    "name:eng_x_preferred":[
        "Doodaliya"
    ],
    "wof:name":"Doodaliya",
    "wof:placetype":"locality",
    "wof:population":311
},
  "geometry": {"coordinates":[73.986637,25.343948],"type":"Point"}
}