{
  "type": "Feature",
  "properties": {
    "iso:country":"IN",
    "ks:ks_name":"Gambhirwadi",
    "ks:ks_pop":269,
    "ks:ks_type":"HABITATION",
    "name:eng_x_preferred":[
        "Gambhirwadi"
    ],
    "wof:name":"Gambhirwadi",
    "wof:placetype":"locality",
    "wof:population":269
},
  "geometry": {"coordinates":[73.910049,19.44185],"type":"Point"}
}