{
  "type": "Feature",
  "properties": {
    "iso:country":"IN",
    "ks:ks_name":"Hiriguda",
    "ks:ks_pop":26,
    "ks:ks_type":"HABITATION",
    "name:eng_x_preferred":[
        "Hiriguda"
    ],
    "wof:name":"Hiriguda",
    "wof:placetype":"locality",
    "wof:population":26
},
  "geometry": {"coordinates":[82.809185,19.282278],"type":"Point"}
}