{
  "type": "Feature",
  "properties": {
    "iso:country":"IN",
    "ks:ks_name":"Pathar Chapri",
    "ks:ks_pop":0,
    "ks:ks_type":"VILLAGE",
    "name:eng_x_preferred":[
        "Pathar Chapri"
    ],
    "wof:name":"Pathar Chapri",
    "wof:placetype":"locality",
    "wof:population":0
},
  "geometry": {"coordinates":[88.310315,25.122423],"type":"Point"}
}