{
  "type": "Feature",
  "properties": {
    "iso:country":"IN",
    "ks:ks_name":"Madhyapara",
    "ks:ks_pop":1505,
    "ks:ks_type":"HABITATION",
    "ks:ks_uagg_main":0,
    "name:eng_x_preferred":[
        "Madhyapara"
    ],
    "wof:name":"Madhyapara",
    "wof:placetype":"neighbourhood",
    "wof:population":1505
},
  "geometry": {"coordinates":[88.61628899999999,22.292261],"type":"Point"}
}