{
  "type": "Feature",
  "properties": {
    "gn:admin1_code":"24.0",
    "gn:admin2_code":"107.0",
    "gn:asciiname":"Bardala",
    "gn:country_code":"IN",
    "gn:dem":251,
    "gn:feature_class":"P",
    "gn:feature_code":"PPL",
    "gn:name":"Bard\u0101la",
    "gn:population":0,
    "gn:timezone":"Asia/Kolkata",
    "iso:country":"IN",
    "name:ara_x_preferred":[
        "\u0628\u0631\u062f\u0644\u0629"
    ],
    "name:cat_x_preferred":[
        "Bardala"
    ],
    "name:ceb_x_preferred":[
        "Bardalah"
    ],
    "name:heb_x_preferred":[
        "\u05d1\u05e8\u05d3\u05dc\u05d4"
    ],
    "name:nno_x_preferred":[
        "Bardala"
    ],
    "name:pol_x_preferred":[
        "Bardala"
    ],
    "name:srp_x_preferred":[
        "\u0411\u0430\u0440\u0434\u0430\u043b\u0430"
    ],
    "wof:name":"Bardala",
    "wof:placetype":"locality"
},
  "geometry": {"coordinates":[76.68947,26.6752],"type":"Point"}
}