{
  "type": "Feature",
  "properties": {
    "iso:country":"IN",
    "ks:ks_name":"Chakeri",
    "ks:ks_type":"VILLAGE",
    "ks:ks_uagg_main":0,
    "name:eng_x_preferred":[
        "Chakeri"
    ],
    "wof:name":"Chakeri",
    "wof:placetype":"neighbourhood"
},
  "geometry": {"coordinates":[80.412547,26.374101],"type":"Point"}
}