{
  "type": "Feature",
  "properties": {
    "iso:country":"IN",
    "ks:ks_name":"Neredupalle",
    "ks:ks_pop":50,
    "ks:ks_type":"VILLAGE",
    "name:eng_x_preferred":[
        "Neredupalle"
    ],
    "wof:name":"Neredupalle",
    "wof:placetype":"locality",
    "wof:population":50
},
  "geometry": {"coordinates":[80.520172,15.965231],"type":"Point"}
}