{
  "type": "Feature",
  "properties": {
    "iso:country":"IN",
    "ks:ks_name":"Kamaraguda",
    "ks:ks_pop":83,
    "ks:ks_type":"VILLAGE",
    "ks:ks_uagg_main":0,
    "name:eng_x_preferred":[
        "Kamaraguda"
    ],
    "wof:name":"Kamaraguda",
    "wof:placetype":"neighbourhood",
    "wof:population":83
},
  "geometry": {"coordinates":[83.42406099999999,19.129305],"type":"Point"}
}