{
  "type": "Feature",
  "properties": {
    "iso:country":"IN",
    "ks:ks_name":"Ganeshipur",
    "ks:ks_pop":50,
    "ks:ks_type":"HABITATION",
    "name:eng_x_preferred":[
        "Ganeshipur"
    ],
    "wof:name":"Ganeshipur",
    "wof:placetype":"locality",
    "wof:population":50
},
  "geometry": {"coordinates":[81.47584000000001,25.180628],"type":"Point"}
}