{
  "type": "Feature",
  "properties": {
    "iso:country":"IN",
    "ks:ks_name":"Tamtichakana",
    "ks:ks_pop":95,
    "ks:ks_type":"HABITATION",
    "name:eng_x_preferred":[
        "Tamtichakana"
    ],
    "wof:name":"Tamtichakana",
    "wof:placetype":"locality",
    "wof:population":95
},
  "geometry": {"coordinates":[73.820008,16.483786],"type":"Point"}
}