{
  "type": "Feature",
  "properties": {
    "iso:country":"IN",
    "ks:ks_name":"Choudharwadi",
    "ks:ks_pop":260,
    "ks:ks_type":"HABITATION",
    "name:eng_x_preferred":[
        "Choudharwadi"
    ],
    "wof:name":"Choudharwadi",
    "wof:placetype":"locality",
    "wof:population":260
},
  "geometry": {"coordinates":[73.894609,18.838131],"type":"Point"}
}