{
  "type": "Feature",
  "properties": {
    "iso:country":"IN",
    "ks:ks_name":"Kanthota",
    "ks:ks_pop":45,
    "ks:ks_type":"HABITATION",
    "name:eng_x_preferred":[
        "Kanthota"
    ],
    "wof:name":"Kanthota",
    "wof:placetype":"locality",
    "wof:population":45
},
  "geometry": {"coordinates":[74.92848600000001,14.158283],"type":"Point"}
}