{
  "type": "Feature",
  "properties": {
    "iso:country":"IN",
    "ks:ks_alt_nam":"Ramcharan purwa",
    "ks:ks_name":"Ramcharan Purwa",
    "ks:ks_pop":89,
    "ks:ks_type":"HABITATION",
    "ks:ks_uagg_main":0,
    "name:eng_x_preferred":[
        "Ramcharan Purwa"
    ],
    "wof:name":"Ramcharan Purwa",
    "wof:placetype":"neighbourhood",
    "wof:population":89
},
  "geometry": {"coordinates":[81.482843,27.265487],"type":"Point"}
}