{
  "type": "Feature",
  "properties": {
    "iso:country":"IN",
    "ks:ks_name":"Kadeshwar Mandir Road",
    "ks:ks_pop":60,
    "ks:ks_type":"HABITATION",
    "name:eng_x_preferred":[
        "Kadeshwar Mandir Road"
    ],
    "wof:name":"Kadeshwar Mandir Road",
    "wof:placetype":"locality",
    "wof:population":60
},
  "geometry": {"coordinates":[74.38556,17.12568],"type":"Point"}
}