{
  "type": "Feature",
  "properties": {
    "iso:country":"IN",
    "ks:ks_name":"Simli Amba",
    "ks:ks_pop":303,
    "ks:ks_type":"HABITATION",
    "name:eng_x_preferred":[
        "Simli Amba"
    ],
    "wof:name":"Simli Amba",
    "wof:placetype":"locality",
    "wof:population":303
},
  "geometry": {"coordinates":[73.27235,21.3132],"type":"Point"}
}