{
  "type": "Feature",
  "properties": {
    "iso:country":"IN",
    "ks:ks_name":"Vallaibeeru",
    "ks:ks_pop":126,
    "ks:ks_type":"HABITATION",
    "name:eng_x_preferred":[
        "Vallaibeeru"
    ],
    "wof:name":"Vallaibeeru",
    "wof:placetype":"locality",
    "wof:population":126
},
  "geometry": {"coordinates":[82.431332,18.275857],"type":"Point"}
}