{
  "type": "Feature",
  "properties": {
    "iso:country":"IN",
    "ks:ks_alt_nam":"Gonid\u0101 Khurd",
    "ks:ks_name":"Gonida Khurd",
    "ks:ks_type":"VILLAGE",
    "ks:ks_uagg_main":0,
    "name:eng_x_preferred":[
        "Gonida Khurd"
    ],
    "name:eng_x_variant":[
        "Gonid\u0101 Khurd"
    ],
    "wof:name":"Gonida Khurd",
    "wof:placetype":"neighbourhood"
},
  "geometry": {"coordinates":[80.213826,21.452502],"type":"Point"}
}