{
  "type": "Feature",
  "properties": {
    "iso:country":"IN",
    "ks:ks_name":"Suragimane",
    "ks:ks_pop":6,
    "ks:ks_type":"HABITATION",
    "name:eng_x_preferred":[
        "Suragimane"
    ],
    "wof:name":"Suragimane",
    "wof:placetype":"locality",
    "wof:population":6
},
  "geometry": {"coordinates":[74.781217,13.953049],"type":"Point"}
}