{
  "type": "Feature",
  "properties": {
    "iso:country":"IN",
    "ks:ks_name":"Kotturuguda",
    "ks:ks_pop":79,
    "ks:ks_type":"HABITATION",
    "name:eng_x_preferred":[
        "Kotturuguda"
    ],
    "wof:name":"Kotturuguda",
    "wof:placetype":"locality",
    "wof:population":79
},
  "geometry": {"coordinates":[83.78727000000001,18.984637],"type":"Point"}
}