{
  "type": "Feature",
  "properties": {
    "iso:country":"IN",
    "ks:ks_name":"Balisamala-1",
    "ks:ks_pop":563,
    "ks:ks_type":"VILLAGE",
    "ks:ks_uagg_main":0,
    "name:eng_x_preferred":[
        "Balisamala-1"
    ],
    "wof:name":"Balisamala-1",
    "wof:placetype":"neighbourhood",
    "wof:population":563
},
  "geometry": {"coordinates":[86.066017,20.510359],"type":"Point"}
}