{
  "type": "Feature",
  "properties": {
    "gn:admin1_code":"34.0",
    "gn:admin2_code":"221.0",
    "gn:asciiname":"Hasanpur Sarsauna",
    "gn:country_code":"IN",
    "gn:dem":53,
    "gn:feature_class":"P",
    "gn:feature_code":"PPL",
    "gn:name":"Hasanpur Sarsauna",
    "gn:population":0,
    "gn:timezone":"Asia/Kolkata",
    "iso:country":"IN",
    "ks:ks_name":"Hasanpur Sarsauna",
    "ks:ks_type":"VILLAGE",
    "name:eng_x_preferred":[
        "Hasanpur Sarsauna"
    ],
    "wof:name":"Hasanpur Sarsauna",
    "wof:placetype":"locality"
},
  "geometry": {"coordinates":[85.63382900000001,25.880009],"type":"Point"}
}