{
  "type": "Feature",
  "properties": {
    "gn:admin1_code":"34.0",
    "gn:admin2_code":"221.0",
    "gn:asciiname":"Hasanpur Sarsauna",
    "gn:country_code":"IN",
    "gn:dem":53,
    "gn:feature_class":"P",
    "gn:feature_code":"PPL",
    "gn:name":"Hasanpur Sarsauna",
    "gn:population":0,
    "gn:timezone":"Asia/Kolkata",
    "iso:country":"IN",
    "wof:name":"Hasanpur Sarsauna",
    "wof:placetype":"locality"
},
  "geometry": {"coordinates":[85.63383,25.88001],"type":"Point"}
}