{
  "type": "Feature",
  "properties": {
    "gn:admin1_code":"23.0",
    "gn:admin2_code":"42.0",
    "gn:asciiname":"Firozwal Mangal Singh",
    "gn:country_code":"IN",
    "gn:dem":222,
    "gn:feature_class":"P",
    "gn:feature_code":"PPL",
    "gn:name":"F\u012brozw\u0101l Mangal Singh",
    "gn:population":0,
    "gn:timezone":"Asia/Kolkata",
    "iso:country":"IN",
    "wof:name":"Firozwal Mangal Singh",
    "wof:placetype":"locality"
},
  "geometry": {"coordinates":[75.27304000000002,30.9803],"type":"Point"}
}