{
  "type": "Feature",
  "properties": {
    "iso:country":"IN",
    "ks:ks_alt_nam":"GULANITARI",
    "ks:ks_name":"Gulanitari",
    "ks:ks_pop":320,
    "ks:ks_type":"HABITATION",
    "name:eng_x_preferred":[
        "Gulanitari"
    ],
    "wof:name":"Gulanitari",
    "wof:placetype":"locality",
    "wof:population":320
},
  "geometry": {"coordinates":[85.945712,24.816761],"type":"Point"}
}