{
  "type": "Feature",
  "properties": {
    "gn:admin1_code":"24",
    "gn:admin2_code":"121.0",
    "gn:asciiname":"Bisanpura",
    "gn:country_code":"IN",
    "gn:dem":333,
    "gn:feature_class":"P",
    "gn:feature_code":"PPL",
    "gn:name":"Bisanpura",
    "gn:population":0,
    "gn:timezone":"Asia/Kolkata",
    "iso:country":"IN",
    "wof:name":"Bisanpura",
    "wof:placetype":"locality"
},
  "geometry": {"coordinates":[75.38361,25.5399],"type":"Point"}
}