{
  "type": "Feature",
  "properties": {
    "gn:admin1_code":"36.0",
    "gn:admin2_code":"161",
    "gn:asciiname":"Kathua",
    "gn:country_code":"IN",
    "gn:dem":155,
    "gn:feature_class":"P",
    "gn:feature_code":"PPL",
    "gn:name":"Kathua",
    "gn:population":0,
    "gn:timezone":"Asia/Kolkata",
    "iso:country":"IN",
    "name:ara_x_preferred":[
        "\u0643\u0627\u062b\u0648\u0627"
    ],
    "name:bpy_x_preferred":[
        "\u0995\u09a5\u09c1\u09f1\u09be"
    ],
    "name:ceb_x_preferred":[
        "Kathua"
    ],
    "name:deu_x_preferred":[
        "Kathua"
    ],
    "name:fas_x_preferred":[
        "\u06a9\u062a\u0648\u0627"
    ],
    "name:fra_x_preferred":[
        "Kathua"
    ],
    "name:guj_x_preferred":[
        "\u0a95\u0aa0\u0ac1\u0a86"
    ],
    "name:hin_x_preferred":[
        "\u0915\u0920\u0941\u0906"
    ],
    "name:ita_x_preferred":[
        "Kathua"
    ],
    "name:mal_x_preferred":[
        "\u0d15\u0d24\u0d4d\u0d35"
    ],
    "name:mar_x_preferred":[
        "\u0915\u0925\u0941\u0906"
    ],
    "name:mlg_x_preferred":[
        "Kathua"
    ],
    "name:msa_x_preferred":[
        "Kathua"
    ],
    "name:new_x_preferred":[
        "\u0915\u0925\u0941\u0930\u093e"
    ],
    "name:nld_x_preferred":[
        "Kathua"
    ],
    "name:ori_x_preferred":[
        "\u0b15\u0b3e\u0b20\u0b41\u0b06"
    ],
    "name:pol_x_preferred":[
        "Kathua"
    ],
    "name:rus_x_preferred":[
        "\u041a\u0430\u0442\u0445\u0443\u0430"
    ],
    "name:san_x_preferred":[
        "\u0915\u0920\u0941\u0935\u093e"
    ],
    "name:spa_x_preferred":[
        "Kathua"
    ],
    "name:swe_x_preferred":[
        "Kathua"
    ],
    "name:urd_x_preferred":[
        "\u06a9\u0679\u06be\u0648\u0639\u06c1"
    ],
    "name:vie_x_preferred":[
        "Kathua"
    ],
    "name:zho_x_preferred":[
        "\u5361\u56fe\u963f"
    ],
    "wof:name":"Kathua",
    "wof:placetype":"locality"
},
  "geometry": {"coordinates":[79.06671999999998,26.97908],"type":"Point"}
}