{
  "type": "Feature",
  "properties": {
    "gn:admin1_code":"40.0",
    "gn:admin2_code":"540.0",
    "gn:asciiname":"Repaka",
    "gn:country_code":"IN",
    "gn:dem":213,
    "gn:feature_class":"P",
    "gn:feature_code":"PPL",
    "gn:name":"Rep\u0101ka",
    "gn:population":0,
    "gn:timezone":"Asia/Kolkata",
    "iso:country":"IN",
    "wof:name":"Repaka",
    "wof:placetype":"locality"
},
  "geometry": {"coordinates":[79.72818000000002,18.27849],"type":"Point"}
}