{
  "type": "Feature",
  "properties": {
    "iso:country":"IN",
    "ks:ks_name":"Katarikoppa",
    "ks:ks_pop":75,
    "ks:ks_type":"HABITATION",
    "name:eng_x_preferred":[
        "Katarikoppa"
    ],
    "wof:name":"Katarikoppa",
    "wof:placetype":"locality",
    "wof:population":75
},
  "geometry": {"coordinates":[75.02827000000001,14.06523],"type":"Point"}
}