{
  "type": "Feature",
  "properties": {
    "gn:admin1_code":"36.0",
    "gn:admin2_code":"182.0",
    "gn:asciiname":"Banki",
    "gn:country_code":"IN",
    "gn:dem":115,
    "gn:feature_class":"P",
    "gn:feature_code":"PPL",
    "gn:name":"B\u0101nki",
    "gn:population":0,
    "gn:timezone":"Asia/Kolkata",
    "iso:country":"IN",
    "name:bpy_x_preferred":[
        "\u09ac\u09be\u0999\u09cd\u0995\u09bf"
    ],
    "name:ceb_x_preferred":[
        "Banki"
    ],
    "name:fra_x_preferred":[
        "Banki"
    ],
    "name:ita_x_preferred":[
        "Banki"
    ],
    "name:nld_x_preferred":[
        "Banki"
    ],
    "name:pol_x_preferred":[
        "Banki"
    ],
    "name:rus_x_preferred":[
        "\u0411\u0430\u043d\u043a\u0438"
    ],
    "name:srp_x_preferred":[
        "\u0411\u0430\u043d\u043a\u0438"
    ],
    "name:swe_x_preferred":[
        "Banki"
    ],
    "wof:name":"Banki",
    "wof:placetype":"locality"
},
  "geometry": {"coordinates":[82.06291,27.51667],"type":"Point"}
}