{
  "type": "Feature",
  "properties": {
    "iso:country":"IN",
    "ks:ks_alt_nam":"yadagoda",
    "ks:ks_name":"Yadagoda",
    "ks:ks_pop":163,
    "ks:ks_type":"HABITATION",
    "name:eng_x_preferred":[
        "Yadagoda"
    ],
    "wof:name":"Yadagoda",
    "wof:placetype":"locality",
    "wof:population":163
},
  "geometry": {"coordinates":[74.600082,14.316615],"type":"Point"}
}