{
  "type": "Feature",
  "properties": {
    "gn:admin1_code":"34",
    "gn:admin2_code":"235.0",
    "gn:asciiname":"Raniganj",
    "gn:country_code":"IN",
    "gn:dem":121,
    "gn:feature_class":"P",
    "gn:feature_code":"PPL",
    "gn:name":"R\u0101n\u012bganj",
    "gn:population":0,
    "gn:timezone":"Asia/Kolkata",
    "iso:country":"IN",
    "wof:name":"Raniganj",
    "wof:placetype":"locality"
},
  "geometry": {"coordinates":[84.51619000000002,24.68366],"type":"Point"}
}