{
  "type": "Feature",
  "properties": {
    "iso:country":"IN",
    "ks:ks_name":"Kadamtanr",
    "ks:ks_pop":302,
    "ks:ks_type":"VILLAGE",
    "name:eng_x_preferred":[
        "Kadamtanr"
    ],
    "wof:name":"Kadamtanr",
    "wof:placetype":"locality",
    "wof:population":302
},
  "geometry": {"coordinates":[84.634044,22.694533],"type":"Point"}
}