{
  "type": "Feature",
  "properties": {
    "gn:admin1_code":"2.0",
    "gn:admin2_code":"552.0",
    "gn:asciiname":"Vemilapadu",
    "gn:country_code":"IN",
    "gn:dem":200,
    "gn:feature_class":"P",
    "gn:feature_code":"PPL",
    "gn:name":"Vemilap\u0101du",
    "gn:population":0,
    "gn:timezone":"Asia/Kolkata",
    "iso:country":"IN",
    "wof:name":"Vemilapadu",
    "wof:placetype":"locality"
},
  "geometry": {"coordinates":[78.19184,15.24051],"type":"Point"}
}