{
  "type": "Feature",
  "properties": {
    "iso:country":"IN",
    "ks:ks_name":"Donifalia",
    "ks:ks_pop":721,
    "ks:ks_type":"HABITATION",
    "name:eng_x_preferred":[
        "Donifalia"
    ],
    "wof:name":"Donifalia",
    "wof:placetype":"locality",
    "wof:population":721
},
  "geometry": {"coordinates":[73.117278,20.520556],"type":"Point"}
}