{
  "type": "Feature",
  "properties": {
    "iso:country":"IN",
    "ks:ks_name":"Purakkileri Colony",
    "ks:ks_pop":168,
    "ks:ks_type":"HABITATION",
    "name:eng_x_preferred":[
        "Purakkileri Colony"
    ],
    "wof:name":"Purakkileri Colony",
    "wof:placetype":"locality",
    "wof:population":168
},
  "geometry": {"coordinates":[75.74811699999999,11.598942],"type":"Point"}
}