{
  "type": "Feature",
  "properties": {
    "iso:country":"IN",
    "ks:ks_alt_nam":"SADOBASA",
    "ks:ks_name":"Sadobasa",
    "ks:ks_pop":224,
    "ks:ks_type":"HABITATION",
    "name:eng_x_preferred":[
        "Sadobasa"
    ],
    "wof:name":"Sadobasa",
    "wof:placetype":"locality",
    "wof:population":224
},
  "geometry": {"coordinates":[85.76559,22.46606],"type":"Point"}
}