{
  "type": "Feature",
  "properties": {
    "gn:admin1_code":"28.0",
    "gn:admin2_code":"335.0",
    "gn:asciiname":"Joykrishnapur",
    "gn:country_code":"IN",
    "gn:dem":10,
    "gn:feature_class":"P",
    "gn:feature_code":"PPL",
    "gn:name":"Joykrishnapur",
    "gn:population":0,
    "gn:timezone":"Asia/Kolkata",
    "iso:country":"IN",
    "wof:name":"Joykrishnapur",
    "wof:placetype":"locality"
},
  "geometry": {"coordinates":[88.21568000000001,23.46597],"type":"Point"}
}