{
  "type": "Feature",
  "properties": {
    "iso:country":"IN",
    "ks:ks_name":"Gerua",
    "ks:ks_pop":1867,
    "ks:ks_type":"VILLAGE",
    "ks:ks_uagg_main":0,
    "name:eng_x_preferred":[
        "Gerua"
    ],
    "wof:name":"Gerua",
    "wof:placetype":"neighbourhood",
    "wof:population":1867
},
  "geometry": {"coordinates":[91.59809,26.58875],"type":"Point"}
}