{
  "type": "Feature",
  "properties": {
    "iso:country":"IN",
    "ks:ks_name":"Chaltaberia Madhyapara",
    "ks:ks_pop":765,
    "ks:ks_type":"HABITATION",
    "ks:ks_uagg_main":0,
    "name:eng_x_preferred":[
        "Chaltaberia Madhyapara"
    ],
    "wof:name":"Chaltaberia Madhyapara",
    "wof:placetype":"locality",
    "wof:population":765
},
  "geometry": {"coordinates":[88.548069,22.760834],"type":"Point"}
}