{
  "type": "Feature",
  "properties": {
    "gn:admin1_code":"37",
    "gn:admin2_code":"408.0",
    "gn:asciiname":"Banspahar",
    "gn:country_code":"IN",
    "gn:dem":419,
    "gn:feature_class":"P",
    "gn:feature_code":"PPL",
    "gn:name":"B\u0101nspah\u0101r",
    "gn:population":0,
    "gn:timezone":"Asia/Kolkata",
    "iso:country":"IN",
    "name:und_x_variant":[
        "B\u0101nspah\u0101r",
        "Sahaspur"
    ],
    "wof:name":"Banspahar",
    "wof:placetype":"locality"
},
  "geometry": {"coordinates":[80.59650000000001,21.17198],"type":"Point"}
}