{
  "type": "Feature",
  "properties": {
    "gn:admin1_code":"39.0",
    "gn:admin2_code":"64.0",
    "gn:asciiname":"Rikholi",
    "gn:country_code":"IN",
    "gn:dem":1090,
    "gn:feature_class":"P",
    "gn:feature_code":"PPL",
    "gn:name":"Rikholi",
    "gn:population":0,
    "gn:timezone":"Asia/Kolkata",
    "iso:country":"IN",
    "wof:name":"Rikholi",
    "wof:placetype":"locality"
},
  "geometry": {"coordinates":[79.40104000000002,29.68653],"type":"Point"}
}