{
  "type": "Feature",
  "properties": {
    "iso:country":"IN",
    "ks:ks_name":"Bagha Gerya",
    "ks:ks_pop":302,
    "ks:ks_type":"VILLAGE",
    "name:eng_x_preferred":[
        "Bagha Gerya"
    ],
    "wof:name":"Bagha Gerya",
    "wof:placetype":"locality",
    "wof:population":302
},
  "geometry": {"coordinates":[87.52404900000001,22.486205],"type":"Point"}
}