{
  "type": "Feature",
  "properties": {
    "gn:admin1_code":"35",
    "gn:admin2_code":"455.0",
    "gn:asciiname":"Temru",
    "gn:country_code":"IN",
    "gn:dem":496,
    "gn:feature_class":"P",
    "gn:feature_code":"PPL",
    "gn:name":"Temru",
    "gn:population":0,
    "gn:timezone":"Asia/Kolkata",
    "iso:country":"IN",
    "ks:ks_name":"Temru",
    "ks:ks_pop":622,
    "ks:ks_type":"HABITATION",
    "name:eng_x_preferred":[
        "Temru"
    ],
    "wof:name":"Temru",
    "wof:placetype":"locality",
    "wof:population":622
},
  "geometry": {"coordinates":[78.271242,22.319585],"type":"Point"}
}