{
  "type": "Feature",
  "properties": {
    "gn:admin1_code":"34.0",
    "gn:admin2_code":"229.0",
    "gn:asciiname":"Kulti",
    "gn:country_code":"IN",
    "gn:dem":58,
    "gn:feature_class":"P",
    "gn:feature_code":"PPL",
    "gn:name":"Kulti",
    "gn:population":0,
    "gn:timezone":"Asia/Kolkata",
    "iso:country":"IN",
    "name:ben_x_preferred":[
        "\u0995\u09c1\u09b2\u099f\u09bf"
    ],
    "name:bih_x_preferred":[
        "\u0915\u0941\u0932\u094d\u091f\u0940"
    ],
    "name:bpy_x_preferred":[
        "\u0995\u09c1\u09b2\u099f\u09bf"
    ],
    "name:ceb_x_preferred":[
        "Kulti"
    ],
    "name:fas_x_preferred":[
        "\u06a9\u0648\u0644\u062a\u06cc"
    ],
    "name:fra_x_preferred":[
        "Kulti"
    ],
    "name:hin_x_preferred":[
        "\u0915\u0941\u0932\u091f\u093f"
    ],
    "name:ita_x_preferred":[
        "Kulti"
    ],
    "name:mlg_x_preferred":[
        "Kulti"
    ],
    "name:msa_x_preferred":[
        "Kulti"
    ],
    "name:new_x_preferred":[
        "\u0915\u0941\u0932\u094d\u0924\u0940"
    ],
    "name:pnb_x_preferred":[
        "\u06a9\u0644\u062a\u06cc"
    ],
    "name:por_x_preferred":[
        "Kulti"
    ],
    "name:spa_x_preferred":[
        "Kulti"
    ],
    "name:srp_x_preferred":[
        "\u041a\u0443\u043b\u0442\u0438"
    ],
    "name:swe_x_preferred":[
        "Kulti"
    ],
    "name:vie_x_preferred":[
        "Kulti"
    ],
    "wof:name":"Kulti",
    "wof:placetype":"locality"
},
  "geometry": {"coordinates":[85.63535,25.18973],"type":"Point"}
}