{
  "type": "Feature",
  "properties": {
    "iso:country":"IN",
    "ks:ks_name":"Mallaha Basti",
    "ks:ks_pop":383,
    "ks:ks_type":"HABITATION",
    "name:eng_x_preferred":[
        "Mallaha Basti"
    ],
    "wof:name":"Mallaha Basti",
    "wof:placetype":"locality",
    "wof:population":383
},
  "geometry": {"coordinates":[82.372726,25.793822],"type":"Point"}
}