{
  "type": "Feature",
  "properties": {
    "iso:country":"IN",
    "ks:ks_name":"Sitepar Mohdura",
    "ks:ks_pop":8,
    "ks:ks_type":"HABITATION",
    "name:eng_x_preferred":[
        "Sitepar Mohdura"
    ],
    "wof:name":"Sitepar Mohdura",
    "wof:placetype":"locality",
    "wof:population":8
},
  "geometry": {"coordinates":[79.569063,21.200485],"type":"Point"}
}