{
  "type": "Feature",
  "properties": {
    "iso:country":"IN",
    "ks:ks_name":"Bharjodi",
    "ks:ks_pop":222,
    "ks:ks_type":"HABITATION",
    "name:eng_x_preferred":[
        "Bharjodi"
    ],
    "wof:name":"Bharjodi",
    "wof:placetype":"locality",
    "wof:population":222
},
  "geometry": {"coordinates":[82.48805,19.779478],"type":"Point"}
}