{
  "type": "Feature",
  "properties": {
    "iso:country":"IN",
    "ks:ks_name":"Vachla",
    "ks:ks_pop":200,
    "ks:ks_type":"HABITATION",
    "name:eng_x_preferred":[
        "Vachla"
    ],
    "wof:name":"Vachla",
    "wof:placetype":"locality",
    "wof:population":200
},
  "geometry": {"coordinates":[73.389306,20.939139],"type":"Point"}
}