{
  "type": "Feature",
  "properties": {
    "gn:country":"IN",
    "gn:fcode":"PPL",
    "gn:population":0,
    "iso:country":"IN",
    "name:ara_x_preferred":[
        "\u0628\u0627\u062b\u0648\u0631\u064a\u0627"
    ],
    "name:ben_bn_x_preferred":[
        "\u09aa\u09be\u09a5\u09be\u0989\u09b0\u09bf\u09df\u09be"
    ],
    "name:ben_in_x_preferred":[
        "\u09aa\u09be\u09a5\u09be\u0989\u09b0\u09bf\u09df\u09be"
    ],
    "name:guj_x_preferred":[
        "\u0aaa\u0aa5\u0acc\u0ab0\u0ac0\u0aaf\u0abe"
    ],
    "name:hin_x_preferred":[
        "\u092a\u0925\u094c\u0930\u093f\u092f\u093e"
    ],
    "name:kan_x_preferred":[
        "\u0caa\u0ca4\u0ccc\u0cb0\u0cbf\u0caf\u0cbe"
    ],
    "name:mal_x_preferred":[
        "\u0d2a\u0d24\u0d4d\u0d24\u0d57\u0d30\u0d3f\u0d2f"
    ],
    "name:mar_x_preferred":[
        "\u092a\u0925\u094c\u0930\u093f\u092f\u093e"
    ],
    "name:pan_x_preferred":[
        "\u0a2a\u0a25\u0a4c\u0a30\u0a40\u0a06"
    ],
    "name:tam_x_preferred":[
        "\u0baa\u0ba4\u0bcc\u0bb0\u0bbf\u0baf\u0bbe"
    ],
    "name:tel_x_preferred":[
        "\u0c2a\u0c3e\u0c25\u0c4c\u0c30\u0c3f\u0c2f\u0c3e"
    ],
    "name:urd_x_preferred":[
        "\u067e\u062a\u06be\u0648\u0631\u06cc\u0627"
    ],
    "qs:name":"Pathauriya",
    "qs:name_adm0":"India",
    "qs:name_adm1":"Uttar Pradesh",
    "qs:photos":2,
    "qs:photos_1k":1,
    "qs:photos_9k":1,
    "qs:photos_9r":1,
    "qs:photos_all":2,
    "qs:photos_sr":1,
    "qs:placetype":"Suburb",
    "qs:pop_sr":"0",
    "wof:name":"Pathauriya",
    "wof:placetype":"neighbourhood",
    "wof:population":0
},
  "geometry": {"coordinates":[78.85626999999999,24.86732],"type":"Point"}
}