{
  "type": "Feature",
  "properties": {
    "gn:admin1_code":"25.0",
    "gn:admin2_code":"611.0",
    "gn:asciiname":"Sundatti",
    "gn:country_code":"IN",
    "gn:dem":2005,
    "gn:feature_class":"P",
    "gn:feature_code":"PPL",
    "gn:name":"Sundatti",
    "gn:population":0,
    "gn:timezone":"Asia/Kolkata",
    "iso:country":"IN",
    "wof:name":"Sundatti",
    "wof:placetype":"locality"
},
  "geometry": {"coordinates":[76.64097,11.29831],"type":"Point"}
}