{
  "type": "Feature",
  "properties": {
    "iso:country":"IN",
    "ks:ks_alt_nam":"BABUL CHOWMUHUNI",
    "ks:ks_name":"Babul Chowmuhuni",
    "ks:ks_pop":210,
    "ks:ks_type":"HABITATION",
    "ks:ks_uagg_main":0,
    "name:eng_x_preferred":[
        "Babul Chowmuhuni"
    ],
    "wof:name":"Babul Chowmuhuni",
    "wof:placetype":"locality",
    "wof:population":210
},
  "geometry": {"coordinates":[91.26663499999999,23.758925],"type":"Point"}
}