{
  "type": "Feature",
  "properties": {
    "iso:country":"IN",
    "ks:ks_name":"Nalapara",
    "ks:ks_pop":249,
    "ks:ks_type":"HABITATION",
    "name:eng_x_preferred":[
        "Nalapara"
    ],
    "wof:name":"Nalapara",
    "wof:placetype":"locality",
    "wof:population":249
},
  "geometry": {"coordinates":[81.557515,19.125878],"type":"Point"}
}