{
  "type": "Feature",
  "properties": {
    "iso:country":"IN",
    "ks:ks_name":"Kolvelwadi",
    "ks:ks_pop":199,
    "ks:ks_type":"HABITATION",
    "name:eng_x_preferred":[
        "Kolvelwadi"
    ],
    "wof:name":"Kolvelwadi",
    "wof:placetype":"locality",
    "wof:population":199
},
  "geometry": {"coordinates":[73.50734300000001,15.947378],"type":"Point"}
}