{
  "type": "Feature",
  "properties": {
    "iso:country":"IN",
    "ks:ks_name":"Jayeepur",
    "ks:ks_pop":500,
    "ks:ks_type":"HABITATION",
    "name:eng_x_preferred":[
        "Jayeepur"
    ],
    "wof:name":"Jayeepur",
    "wof:placetype":"locality",
    "wof:population":500
},
  "geometry": {"coordinates":[82.789362,25.471951],"type":"Point"}
}