{
  "type": "Feature",
  "properties": {
    "gn:admin1_code":"12.0",
    "gn:admin2_code":"8.0",
    "gn:asciiname":"Tsiyu",
    "gn:country_code":"IN",
    "gn:dem":1584,
    "gn:feature_class":"P",
    "gn:feature_code":"PPL",
    "gn:name":"Tsiyu",
    "gn:population":0,
    "gn:timezone":"Asia/Kolkata",
    "iso:country":"IN",
    "name:eng_x_preferred":[
        "Tsiyu"
    ],
    "wof:name":"Tsiyu",
    "wof:placetype":"locality"
},
  "geometry": {"coordinates":[74.66670000000001,34.28008],"type":"Point"}
}