{
  "type": "Feature",
  "properties": {
    "iso:country":"IN",
    "ks:ks_name":"Harekoppa",
    "ks:ks_pop":116,
    "ks:ks_type":"HABITATION",
    "name:eng_x_preferred":[
        "Harekoppa"
    ],
    "wof:name":"Harekoppa",
    "wof:placetype":"locality",
    "wof:population":116
},
  "geometry": {"coordinates":[75.18743000000001,13.927553],"type":"Point"}
}