{
  "type": "Feature",
  "properties": {
    "iso:country":"IN",
    "ks:ks_name":"Maravetti",
    "ks:ks_pop":150,
    "ks:ks_type":"HABITATION",
    "name:eng_x_preferred":[
        "Maravetti"
    ],
    "wof:name":"Maravetti",
    "wof:placetype":"locality",
    "wof:population":150
},
  "geometry": {"coordinates":[78.521308,9.32368],"type":"Point"}
}