{
  "type": "Feature",
  "properties": {
    "iso:country":"IN",
    "ks:ks_name":"Agrlform",
    "ks:ks_pop":813,
    "ks:ks_type":"HABITATION",
    "name:eng_x_preferred":[
        "Agrlform"
    ],
    "wof:name":"Agrlform",
    "wof:placetype":"locality",
    "wof:population":813
},
  "geometry": {"coordinates":[80.43487500000001,16.364323],"type":"Point"}
}