{
  "type": "Feature",
  "properties": {
    "iso:country":"IN",
    "ks:ks_name":"Nuagaon",
    "ks:ks_pop":107,
    "ks:ks_type":"VILLAGE",
    "name:eng_x_preferred":[
        "Nuagaon"
    ],
    "wof:name":"Nuagaon",
    "wof:placetype":"locality",
    "wof:population":107
},
  "geometry": {"coordinates":[85.41356399999999,20.234156],"type":"Point"}
}