{
  "type": "Feature",
  "properties": {
    "iso:country":"IN",
    "name:ben_x_preferred":[
        "\u09b9\u09c7\u09ac\u09cd\u09ac\u09be\u0997\u09c1\u09a6\u09bf"
    ],
    "name:bpy_x_preferred":[
        "\u09b9\u09c7\u09ac\u09cd\u09ac\u09be\u0997\u09c1\u09a6\u09bf"
    ],
    "name:bul_x_preferred":[
        "\u0425\u0435\u0431\u0430\u0433\u043e\u0434\u0438"
    ],
    "name:ceb_x_preferred":[
        "Hebbagodi"
    ],
    "name:eng_x_preferred":[
        "Hebbagodi"
    ],
    "name:fra_x_preferred":[
        "Hebbagodi"
    ],
    "name:ita_x_preferred":[
        "Hebbagodi"
    ],
    "name:mlg_x_preferred":[
        "Hebbagodi"
    ],
    "name:msa_x_preferred":[
        "Hebbagodi"
    ],
    "name:nan_x_preferred":[
        "Hebbagodi"
    ],
    "name:new_x_preferred":[
        "\u0939\u0947\u092c\u094d\u092c\u093e\u0917\u094b\u0921\u0940"
    ],
    "name:nld_x_preferred":[
        "Hebbagodi"
    ],
    "name:por_x_preferred":[
        "Hebbagodi"
    ],
    "name:swe_x_preferred":[
        "Hebbagodi"
    ],
    "name:vie_x_preferred":[
        "Hebbagodi"
    ],
    "name:zho_x_preferred":[
        "\u8d6b\u5e03\u5df4\u6208\u8fea"
    ],
    "qs:name":"Hebbagodi",
    "qs:name_adm0":"India",
    "qs:name_adm1":"Karnataka",
    "qs:photos":1,
    "qs:photos_1k":1,
    "qs:photos_9k":1,
    "qs:photos_9r":1,
    "qs:photos_all":1,
    "qs:photos_sr":1,
    "qs:placetype":"Suburb",
    "qs:pop_sr":"0",
    "wd:wordcount":490,
    "wof:name":"Hebbagodi",
    "wof:placetype":"neighbourhood"
},
  "geometry": {"coordinates":[77.604675,12.971187],"type":"Point"}
}