{
  "type": "Feature",
  "properties": {
    "gn:admin1_code":"34.0",
    "gn:admin2_code":"237.0",
    "gn:asciiname":"Koiri Bigha",
    "gn:country_code":"IN",
    "gn:dem":106,
    "gn:feature_class":"P",
    "gn:feature_code":"PPL",
    "gn:name":"Koiri Bigha",
    "gn:population":0,
    "gn:timezone":"Asia/Kolkata",
    "iso:country":"IN",
    "ks:ks_name":"Koiri Bigha",
    "ks:ks_pop":212,
    "ks:ks_type":"VILLAGE",
    "ks:ks_uagg_main":0,
    "name:eng_x_preferred":[
        "Koiri Bigha"
    ],
    "wof:name":"Koiri Bigha",
    "wof:placetype":"neighbourhood",
    "wof:population":212
},
  "geometry": {"coordinates":[85.487436,24.807634],"type":"Point"}
}