{
  "type": "Feature",
  "properties": {
    "gn:admin1_code":"28.0",
    "gn:admin2_code":"337",
    "gn:asciiname":"Kusdanga",
    "gn:country_code":"IN",
    "gn:dem":11,
    "gn:feature_class":"P",
    "gn:feature_code":"PPL",
    "gn:name":"Kusd\u0101nga",
    "gn:population":0,
    "gn:timezone":"Asia/Kolkata",
    "iso:country":"IN",
    "ks:ks_name":"Kushdanga",
    "ks:ks_pop":1094,
    "ks:ks_type":"VILLAGE",
    "ks:ks_uagg_main":0,
    "name:eng_x_preferred":[
        "Kushdanga"
    ],
    "wof:name":"Kushdanga",
    "wof:placetype":"locality",
    "wof:population":1094
},
  "geometry": {"coordinates":[88.455387,22.814449],"type":"Point"}
}