{
  "type": "Feature",
  "properties": {
    "iso:country":"IN",
    "ks:ks_name":"Upardumuka",
    "ks:ks_pop":1758,
    "ks:ks_type":"VILLAGE",
    "name:eng_x_preferred":[
        "Upardumuka"
    ],
    "wof:name":"Upardumuka",
    "wof:placetype":"locality",
    "wof:population":1758
},
  "geometry": {"coordinates":[86.638383,20.872987],"type":"Point"}
}