{
  "type": "Feature",
  "properties": {
    "iso:country":"IN",
    "ks:ks_name":"Bhavarpada",
    "ks:ks_pop":144,
    "ks:ks_type":"HABITATION",
    "name:eng_x_preferred":[
        "Bhavarpada"
    ],
    "wof:name":"Bhavarpada",
    "wof:placetype":"locality",
    "wof:population":144
},
  "geometry": {"coordinates":[72.795086,19.874449],"type":"Point"}
}