{
  "type": "Feature",
  "properties": {
    "iso:country":"IN",
    "ks:ks_name":"Liloi",
    "ks:ks_pop":124,
    "ks:ks_type":"VILLAGE",
    "name:eng_x_preferred":[
        "Liloi"
    ],
    "wof:name":"Liloi",
    "wof:placetype":"locality",
    "wof:population":124
},
  "geometry": {"coordinates":[69.642611,26.976911],"type":"Point"}
}