{
  "type": "Feature",
  "properties": {
    "gn:admin1_code":"10.0",
    "gn:admin2_code":"85.0",
    "gn:asciiname":"Piragpura",
    "gn:country_code":"IN",
    "gn:dem":261,
    "gn:feature_class":"P",
    "gn:feature_code":"PPL",
    "gn:name":"Piragpura",
    "gn:population":0,
    "gn:timezone":"Asia/Kolkata",
    "iso:country":"IN",
    "wof:name":"Piragpura",
    "wof:placetype":"locality"
},
  "geometry": {"coordinates":[76.52506,28.13499],"type":"Point"}
}