{
  "type": "Feature",
  "properties": {
    "iso:country":"IN",
    "ks:ks_name":"Nalanihola Gaon",
    "ks:ks_pop":900,
    "ks:ks_type":"VILLAGE",
    "ks:ks_uagg_main":0,
    "name:eng_x_preferred":[
        "Nalanihola Gaon"
    ],
    "wof:name":"Nalanihola Gaon",
    "wof:placetype":"neighbourhood",
    "wof:population":900
},
  "geometry": {"coordinates":[95.330883,27.550677],"type":"Point"}
}