{
  "type": "Feature",
  "properties": {
    "gn:country":"IN",
    "gn:fcode":"PPL",
    "gn:population":5723,
    "iso:country":"IN",
    "ks:ks_name":"Colvale",
    "ks:ks_pop":5475,
    "ks:ks_type":"URBAN",
    "ks:ks_uagg_main":0,
    "name:ben_x_preferred":[
        "\u0995\u09cb\u09b2\u09ad\u09be\u09b2\u09c7"
    ],
    "name:bpy_x_preferred":[
        "\u0995\u09cb\u09b2\u09ad\u09be\u09b2\u09c7"
    ],
    "name:ceb_x_preferred":[
        "Colovale"
    ],
    "name:eng_x_preferred":[
        "Colvale"
    ],
    "name:fra_x_preferred":[
        "Colvale"
    ],
    "name:gom_x_preferred":[
        "Kolvale"
    ],
    "name:hin_x_preferred":[
        "\u0915\u094b\u0932\u094d\u0935\u093e\u0932\u0947"
    ],
    "name:ind_x_preferred":[
        "Colvale"
    ],
    "name:ita_x_preferred":[
        "Colvale"
    ],
    "name:msa_x_preferred":[
        "Colvale"
    ],
    "name:nan_x_preferred":[
        "Colvale"
    ],
    "name:new_x_preferred":[
        "\u0915\u094b\u0932\u094d\u092d\u093e\u0932\u0947"
    ],
    "name:nld_x_preferred":[
        "Colvale"
    ],
    "name:por_x_preferred":[
        "Colvale"
    ],
    "name:swe_x_preferred":[
        "Colovale"
    ],
    "name:tam_x_preferred":[
        "\u0b95\u0bcb\u0bb2\u0bcd\u0bb5\u0bbe\u0bb3\u0bc7"
    ],
    "name:vie_x_preferred":[
        "Colvale"
    ],
    "name:zho_x_preferred":[
        "\u4e54\u5c14\u74e6\u83b1"
    ],
    "qs:name":"Colvale",
    "qs:name_adm0":"India",
    "qs:name_adm1":"Goa",
    "qs:photos_9k":1,
    "qs:photos_9r":1,
    "qs:photos_all":1,
    "qs:photos_sr":0,
    "qs:placetype":"Town",
    "qs:pop_sr":"5",
    "wof:name":"Colvale",
    "wof:placetype":"locality",
    "wof:population":5475
},
  "geometry": {"coordinates":[73.83805099999999,15.643252],"type":"Point"}
}