{
  "type": "Feature",
  "properties": {
    "iso:country":"IN",
    "ks:ks_name":"Katoni",
    "ks:ks_pop":189,
    "ks:ks_type":"HABITATION",
    "name:eng_x_preferred":[
        "Katoni"
    ],
    "wof:name":"Katoni",
    "wof:placetype":"locality",
    "wof:population":189
},
  "geometry": {"coordinates":[81.915646,26.427305],"type":"Point"}
}