{
  "type": "Feature",
  "properties": {
    "gn:admin1_code":"11",
    "gn:admin2_code":"33.0",
    "gn:asciiname":"Tikri",
    "gn:country_code":"IN",
    "gn:dem":2042,
    "gn:feature_class":"P",
    "gn:feature_code":"PPL",
    "gn:name":"Tikri",
    "gn:population":0,
    "gn:timezone":"Asia/Kolkata",
    "iso:country":"IN",
    "wof:name":"Tikri",
    "wof:placetype":"locality"
},
  "geometry": {"coordinates":[77.54951,30.95592000000001],"type":"Point"}
}