{
  "type": "Feature",
  "properties": {
    "gn:admin1_code":"2",
    "gn:admin2_code":"546.0",
    "gn:asciiname":"Ramayagudem",
    "gn:country_code":"IN",
    "gn:dem":6,
    "gn:feature_class":"P",
    "gn:feature_code":"PPL",
    "gn:name":"R\u0101m\u0101yag\u016bdem",
    "gn:population":0,
    "gn:timezone":"Asia/Kolkata",
    "iso:country":"IN",
    "wof:name":"Ramayagudem",
    "wof:placetype":"locality"
},
  "geometry": {"coordinates":[81.39304,16.64286],"type":"Point"}
}