{
  "type": "Feature",
  "properties": {
    "iso:country":"IN",
    "ks:ks_name":"Kumaraswamigudem",
    "ks:ks_pop":178,
    "ks:ks_type":"VILLAGE",
    "name:eng_x_preferred":[
        "Kumaraswamigudem"
    ],
    "wof:name":"Kumaraswamigudem",
    "wof:placetype":"locality",
    "wof:population":178
},
  "geometry": {"coordinates":[81.205844,17.574099],"type":"Point"}
}