{
  "type": "Feature",
  "properties": {
    "iso:country":"IN",
    "ks:ks_name":"Shivpura",
    "ks:ks_pop":1802,
    "ks:ks_type":"HABITATION",
    "name:eng_x_preferred":[
        "Shivpura"
    ],
    "wof:name":"Shivpura",
    "wof:placetype":"locality",
    "wof:population":1802
},
  "geometry": {"coordinates":[73.22240600000001,27.044515],"type":"Point"}
}