{
  "type": "Feature",
  "properties": {
    "iso:country":"IN",
    "ks:ks_name":"Badavalagadde",
    "ks:ks_pop":96,
    "ks:ks_type":"HABITATION",
    "name:eng_x_preferred":[
        "Badavalagadde"
    ],
    "wof:name":"Badavalagadde",
    "wof:placetype":"locality",
    "wof:population":96
},
  "geometry": {"coordinates":[74.82367000000001,13.732509],"type":"Point"}
}