{
  "type": "Feature",
  "properties": {
    "iso:country":"IN",
    "ks:ks_name":"Sauon Ka Bas Roopasar",
    "ks:ks_pop":252,
    "ks:ks_type":"HABITATION",
    "name:eng_x_preferred":[
        "Sauon Ka Bas Roopasar"
    ],
    "wof:name":"Sauon Ka Bas Roopasar",
    "wof:placetype":"locality",
    "wof:population":252
},
  "geometry": {"coordinates":[71.963172,26.311561],"type":"Point"}
}