{
  "type": "Feature",
  "properties": {
    "iso:country":"IN",
    "ks:ks_name":"Dostpur",
    "ks:ks_pop":1105,
    "ks:ks_type":"VILLAGE",
    "ks:ks_uagg_main":0,
    "name:eng_x_preferred":[
        "Dostpur"
    ],
    "wof:name":"Dostpur",
    "wof:placetype":"neighbourhood",
    "wof:population":1105
},
  "geometry": {"coordinates":[85.01058999999999,26.3041],"type":"Point"}
}