{
  "type": "Feature",
  "properties": {
    "iso:country":"IN",
    "ks:ks_alt_nam":"Netr\u0101b\u0101h\u0101l",
    "ks:ks_name":"Netrabahal",
    "ks:ks_pop":290,
    "ks:ks_type":"VILLAGE",
    "name:eng_x_preferred":[
        "Netrabahal"
    ],
    "name:eng_x_variant":[
        "Netr\u0101b\u0101h\u0101l"
    ],
    "wof:name":"Netrabahal",
    "wof:placetype":"locality",
    "wof:population":290
},
  "geometry": {"coordinates":[85.100101,21.490039],"type":"Point"}
}