{
  "type": "Feature",
  "properties": {
    "iso:country":"IN",
    "ks:ks_name":"Mushahri Tola",
    "ks:ks_pop":150,
    "ks:ks_type":"HABITATION",
    "name:eng_x_preferred":[
        "Mushahri Tola"
    ],
    "wof:name":"Mushahri Tola",
    "wof:placetype":"locality",
    "wof:population":150
},
  "geometry": {"coordinates":[86.31731499999999,24.665575],"type":"Point"}
}