{
  "type": "Feature",
  "properties": {
    "gn:admin1_code":"40.0",
    "gn:admin2_code":"537",
    "gn:asciiname":"Medalli",
    "gn:country_code":"IN",
    "gn:dem":628,
    "gn:feature_class":"P",
    "gn:feature_code":"PPL",
    "gn:name":"Medalli",
    "gn:population":0,
    "gn:timezone":"Asia/Kolkata",
    "iso:country":"IN",
    "wof:name":"Medalli",
    "wof:placetype":"locality"
},
  "geometry": {"coordinates":[78.00978000000001,17.23237],"type":"Point"}
}