{
  "type": "Feature",
  "properties": {
    "iso:country":"IN",
    "ks:ks_name":"Muslim Para",
    "ks:ks_pop":810,
    "ks:ks_type":"HABITATION",
    "ks:ks_uagg_main":0,
    "name:eng_x_preferred":[
        "Muslim Para"
    ],
    "wof:name":"Muslim Para",
    "wof:placetype":"neighbourhood",
    "wof:population":810
},
  "geometry": {"coordinates":[89.577625,26.315934],"type":"Point"}
}