{
  "type": "Feature",
  "properties": {
    "gn:admin1_code":"25.0",
    "gn:admin2_code":"629.0",
    "gn:asciiname":"Tikkanbankad",
    "gn:country_code":"IN",
    "gn:dem":60,
    "gn:feature_class":"P",
    "gn:feature_code":"PPL",
    "gn:name":"Tikkanbankad",
    "gn:population":0,
    "gn:timezone":"Asia/Kolkata",
    "iso:country":"IN",
    "wof:name":"Tikkanbankad",
    "wof:placetype":"locality"
},
  "geometry": {"coordinates":[77.27334999999999,8.2216],"type":"Point"}
}