{
  "type": "Feature",
  "properties": {
    "iso:country":"IN",
    "ks:ks_name":"Chak Brahman Gram",
    "ks:ks_pop":30,
    "ks:ks_type":"VILLAGE",
    "name:eng_x_preferred":[
        "Chak Brahman Gram"
    ],
    "wof:name":"Chak Brahman Gram",
    "wof:placetype":"locality",
    "wof:population":30
},
  "geometry": {"coordinates":[87.46373800000001,22.661995],"type":"Point"}
}