{
  "type": "Feature",
  "properties": {
    "iso:country":"IN",
    "ks:ks_alt_nam":"Dhot\u012b",
    "ks:ks_name":"Dhoti",
    "ks:ks_pop":1266,
    "ks:ks_type":"VILLAGE",
    "name:eng_x_preferred":[
        "Dhoti"
    ],
    "name:eng_x_variant":[
        "Dhot\u012b"
    ],
    "wof:name":"Dhoti",
    "wof:placetype":"locality",
    "wof:population":1266
},
  "geometry": {"coordinates":[84.87169299999999,23.638959],"type":"Point"}
}