{
  "type": "Feature",
  "properties": {
    "gn:admin1_code":"34.0",
    "gn:admin2_code":"239.0",
    "gn:asciiname":"Sikandra",
    "gn:country_code":"IN",
    "gn:dem":75,
    "gn:feature_class":"P",
    "gn:feature_code":"PPL",
    "gn:name":"Sikandra",
    "gn:population":0,
    "gn:timezone":"Asia/Kolkata",
    "iso:country":"IN",
    "name:bpy_x_preferred":[
        "\u09b8\u09bf\u0995\u09be\u09a8\u09cd\u09a6\u09be\u09b0"
    ],
    "name:ceb_x_preferred":[
        "Sikandra"
    ],
    "name:ita_x_preferred":[
        "Sikandra"
    ],
    "name:mlg_x_preferred":[
        "Sikandra"
    ],
    "name:nld_x_preferred":[
        "Sikandra"
    ],
    "name:pol_x_preferred":[
        "Sikandra"
    ],
    "name:por_x_preferred":[
        "Sikandra"
    ],
    "name:urd_x_preferred":[
        "\u0633\u06a9\u0646\u062f\u0631\u0627"
    ],
    "name:vie_x_preferred":[
        "Sikandra"
    ],
    "name:zho_x_preferred":[
        "\u897f\u574e\u5fb7\u62c9"
    ],
    "wof:name":"Sikandra",
    "wof:placetype":"locality"
},
  "geometry": {"coordinates":[84.86814,25.14262],"type":"Point"}
}