{
  "type": "Feature",
  "properties": {
    "gn:admin1_code":"36",
    "gn:admin2_code":"173.0",
    "gn:asciiname":"Asrahi",
    "gn:country_code":"IN",
    "gn:dem":101,
    "gn:feature_class":"P",
    "gn:feature_code":"PPL",
    "gn:name":"Asr\u0101hi",
    "gn:population":0,
    "gn:timezone":"Asia/Kolkata",
    "iso:country":"IN",
    "ks:ks_alt_nam":"Asr\u0101hi",
    "ks:ks_name":"Asrahi",
    "ks:ks_type":"VILLAGE",
    "name:eng_x_preferred":[
        "Asrahi"
    ],
    "name:eng_x_variant":[
        "Asr\u0101hi"
    ],
    "wof:name":"Asrahi",
    "wof:placetype":"locality"
},
  "geometry": {"coordinates":[81.665009,25.902788],"type":"Point"}
}