{
  "type": "Feature",
  "properties": {
    "iso:country":"IN",
    "ks:ks_name":"Behdala",
    "ks:ks_pop":0,
    "ks:ks_type":"VILLAGE",
    "name:eng_x_preferred":[
        "Behdala"
    ],
    "wof:name":"Behdala",
    "wof:placetype":"locality",
    "wof:population":0
},
  "geometry": {"coordinates":[76.55083500000001,30.845037],"type":"Point"}
}