{
  "type": "Feature",
  "properties": {
    "iso:country":"IN",
    "ks:ks_name":"Maia",
    "ks:ks_pop":12172,
    "ks:ks_type":"VILLAGE",
    "ks:ks_uagg_main":0,
    "name:eng_x_preferred":[
        "Maia"
    ],
    "wof:name":"Maia",
    "wof:placetype":"neighbourhood",
    "wof:population":12172
},
  "geometry": {"coordinates":[88.191022,24.436725],"type":"Point"}
}