{
  "type": "Feature",
  "properties": {
    "iso:country":"IN",
    "ks:ks_name":"Guttu Colony",
    "ks:ks_pop":277,
    "ks:ks_type":"HABITATION",
    "name:eng_x_preferred":[
        "Guttu Colony"
    ],
    "wof:name":"Guttu Colony",
    "wof:placetype":"locality",
    "wof:population":277
},
  "geometry": {"coordinates":[75.235294,12.588558],"type":"Point"}
}