{
  "type": "Feature",
  "properties": {
    "iso:country":"IN",
    "ks:ks_alt_nam":"Ichaganj Pt II",
    "ks:ks_name":"Ichaganj Pt Ii",
    "ks:ks_pop":431,
    "ks:ks_type":"HABITATION",
    "name:eng_x_preferred":[
        "Ichaganj Pt Ii"
    ],
    "wof:name":"Ichaganj Pt Ii",
    "wof:placetype":"locality",
    "wof:population":431
},
  "geometry": {"coordinates":[92.335307,24.718628],"type":"Point"}
}