{
  "type": "Feature",
  "properties": {
    "iso:country":"IN",
    "ks:ks_name":"Uttar Ganak Guri",
    "ks:ks_pop":1286,
    "ks:ks_type":"VILLAGE",
    "ks:ks_uagg_main":0,
    "name:eng_x_preferred":[
        "Uttar Ganak Guri"
    ],
    "wof:name":"Uttar Ganak Guri",
    "wof:placetype":"neighbourhood",
    "wof:population":1286
},
  "geometry": {"coordinates":[90.887666,26.485644],"type":"Point"}
}