{
  "type": "Feature",
  "properties": {
    "iso:country":"IN",
    "ks:ks_name":"6 AS",
    "ks:ks_pop":378,
    "ks:ks_type":"VILLAGE",
    "name:eng_x_preferred":[
        "6 AS"
    ],
    "wof:name":"6 AS",
    "wof:placetype":"locality",
    "wof:population":378
},
  "geometry": {"coordinates":[73.50125199999999,29.161749],"type":"Point"}
}