{
  "type": "Feature",
  "properties": {
    "gn:admin1_code":"23.0",
    "gn:admin2_code":"38.0",
    "gn:asciiname":"Phamian",
    "gn:country_code":"IN",
    "gn:dem":258,
    "gn:feature_class":"P",
    "gn:feature_code":"PPL",
    "gn:name":"Phami\u0101n",
    "gn:population":0,
    "gn:timezone":"Asia/Kolkata",
    "iso:country":"IN",
    "wof:name":"Phamian",
    "wof:placetype":"locality"
},
  "geometry": {"coordinates":[75.75749,31.54011],"type":"Point"}
}