{
  "type": "Feature",
  "properties": {
    "iso:country":"IN",
    "ks:ks_name":"Thondampatti",
    "ks:ks_pop":126,
    "ks:ks_type":"HABITATION",
    "name:eng_x_preferred":[
        "Thondampatti"
    ],
    "wof:name":"Thondampatti",
    "wof:placetype":"locality",
    "wof:population":126
},
  "geometry": {"coordinates":[78.890415,10.815148],"type":"Point"}
}