{
  "type": "Feature",
  "properties": {
    "gn:admin1_code":"38.0",
    "gn:admin2_code":"347.0",
    "gn:asciiname":"Naudiha",
    "gn:country_code":"IN",
    "gn:dem":399,
    "gn:feature_class":"P",
    "gn:feature_code":"PPL",
    "gn:name":"Naudih\u0101",
    "gn:population":0,
    "gn:timezone":"Asia/Kolkata",
    "iso:country":"IN",
    "ks:ks_alt_nam":"Naudih\u0101",
    "ks:ks_name":"Naudiha",
    "ks:ks_pop":362,
    "ks:ks_type":"VILLAGE",
    "ks:ks_uagg_main":0,
    "name:eng_x_preferred":[
        "Naudiha"
    ],
    "name:eng_x_variant":[
        "Naudih\u0101"
    ],
    "wof:name":"Naudiha",
    "wof:placetype":"neighbourhood",
    "wof:population":362
},
  "geometry": {"coordinates":[85.30680599999999,24.279333],"type":"Point"}
}