{
  "type": "Feature",
  "properties": {
    "iso:country":"IN",
    "ks:ks_alt_nam":"G.R.Palle BC Colony",
    "ks:ks_name":"G.r.palle Bc Colony",
    "ks:ks_pop":99,
    "ks:ks_type":"HABITATION",
    "name:eng_x_preferred":[
        "G.r.palle Bc Colony"
    ],
    "wof:name":"G.r.palle Bc Colony",
    "wof:placetype":"locality",
    "wof:population":99
},
  "geometry": {"coordinates":[79.41040700000001,13.542947],"type":"Point"}
}