{
  "type": "Feature",
  "properties": {
    "iso:country":"IN",
    "ks:ks_alt_nam":"Kelagina belalu",
    "ks:ks_name":"Kelagina Belalu",
    "ks:ks_pop":120,
    "ks:ks_type":"HABITATION",
    "name:eng_x_preferred":[
        "Kelagina Belalu"
    ],
    "wof:name":"Kelagina Belalu",
    "wof:placetype":"locality",
    "wof:population":120
},
  "geometry": {"coordinates":[75.319868,12.946147],"type":"Point"}
}