{
  "type": "Feature",
  "properties": {
    "iso:country":"IN",
    "ks:ks_name":"Bajitpur",
    "ks:ks_pop":2383,
    "ks:ks_type":"VILLAGE",
    "ks:ks_uagg_main":0,
    "name:eng_x_preferred":[
        "Bajitpur"
    ],
    "wof:name":"Bajitpur",
    "wof:placetype":"neighbourhood",
    "wof:population":2383
},
  "geometry": {"coordinates":[88.17245800000001,25.586158],"type":"Point"}
}