{
  "type": "Feature",
  "properties": {
    "iso:country":"IN",
    "ks:ks_alt_nam":"kuradpada",
    "ks:ks_name":"Kuradpada",
    "ks:ks_pop":37,
    "ks:ks_type":"HABITATION",
    "name:eng_x_preferred":[
        "Kuradpada"
    ],
    "wof:name":"Kuradpada",
    "wof:placetype":"locality",
    "wof:population":37
},
  "geometry": {"coordinates":[73.03782699999999,19.662432],"type":"Point"}
}