{
  "type": "Feature",
  "properties": {
    "gn:admin1_code":"19.0",
    "gn:admin2_code":"555.0",
    "gn:asciiname":"Karle",
    "gn:country_code":"IN",
    "gn:dem":796,
    "gn:feature_class":"P",
    "gn:feature_code":"PPL",
    "gn:name":"K\u0101rle",
    "gn:population":0,
    "gn:timezone":"Asia/Kolkata",
    "iso:country":"IN",
    "name:deu_x_preferred":[
        "Karle"
    ],
    "name:fra_x_preferred":[
        "Karle"
    ],
    "name:nds_x_preferred":[
        "Karle"
    ],
    "name:spa_x_preferred":[
        "Karle"
    ],
    "wof:name":"Karle",
    "wof:placetype":"locality"
},
  "geometry": {"coordinates":[74.41589999999999,15.77522],"type":"Point"}
}