{
  "type": "Feature",
  "properties": {
    "gn:admin1_code":"21.0",
    "gn:admin2_code":"396.0",
    "gn:asciiname":"Allubadi",
    "gn:country_code":"IN",
    "gn:dem":509,
    "gn:feature_class":"P",
    "gn:feature_code":"PPL",
    "gn:name":"Allub\u0101di",
    "gn:population":0,
    "gn:timezone":"Asia/Kolkata",
    "iso:country":"IN",
    "ks:ks_name":"Alubadi",
    "ks:ks_pop":123,
    "ks:ks_type":"VILLAGE",
    "name:eng_x_preferred":[
        "Alubadi"
    ],
    "name:eng_x_variant":[
        "Allubadi"
    ],
    "wof:name":"Alubadi",
    "wof:placetype":"locality",
    "wof:population":123
},
  "geometry": {"coordinates":[83.635897,19.32913],"type":"Point"}
}