{
  "type": "Feature",
  "properties": {
    "iso:country":"IN",
    "ks:ks_name":"Bogijuli 1",
    "ks:ks_pop":3752,
    "ks:ks_type":"HABITATION",
    "name:eng_x_preferred":[
        "Bogijuli 1"
    ],
    "wof:name":"Bogijuli 1",
    "wof:placetype":"locality",
    "wof:population":3752
},
  "geometry": {"coordinates":[92.718962,26.913988],"type":"Point"}
}