{
  "type": "Feature",
  "properties": {
    "gn:admin1_code":"2.0",
    "gn:admin2_code":"543.0",
    "gn:asciiname":"Gaudaguda",
    "gn:country_code":"IN",
    "gn:dem":331,
    "gn:feature_class":"P",
    "gn:feature_code":"PPL",
    "gn:name":"Gaudaguda",
    "gn:population":0,
    "gn:timezone":"Asia/Kolkata",
    "iso:country":"IN",
    "ks:ks_name":"Gouduguda",
    "ks:ks_pop":85,
    "ks:ks_type":"HABITATION",
    "name:eng_x_preferred":[
        "Gouduguda"
    ],
    "name:eng_x_variant":[
        "Gaudaguda"
    ],
    "wof:name":"Gouduguda",
    "wof:placetype":"locality",
    "wof:population":85
},
  "geometry": {"coordinates":[83.618985,19.030398],"type":"Point"}
}