{
  "type": "Feature",
  "properties": {
    "iso:country":"IN",
    "ks:ks_name":"Kauli Majra",
    "ks:ks_pop":474,
    "ks:ks_type":"VILLAGE",
    "ks:ks_uagg_main":0,
    "name:eng_x_preferred":[
        "Kauli Majra"
    ],
    "wof:name":"Kauli Majra",
    "wof:placetype":"neighbourhood",
    "wof:population":474
},
  "geometry": {"coordinates":[76.80929999999999,30.500203],"type":"Point"}
}