{
  "type": "Feature",
  "properties": {
    "iso:country":"IN",
    "ks:ks_name":"Ganghar",
    "ks:ks_pop":14,
    "ks:ks_type":"VILLAGE",
    "name:eng_x_preferred":[
        "Ganghar"
    ],
    "wof:name":"Ganghar",
    "wof:placetype":"locality",
    "wof:population":14
},
  "geometry": {"coordinates":[80.154391,30.400558],"type":"Point"}
}