{
  "type": "Feature",
  "properties": {
    "iso:country":"IN",
    "ks:ks_name":"Jawariya",
    "ks:ks_pop":118,
    "ks:ks_type":"VILLAGE",
    "name:eng_x_preferred":[
        "Jawariya"
    ],
    "wof:name":"Jawariya",
    "wof:placetype":"locality",
    "wof:population":118
},
  "geometry": {"coordinates":[73.369394,24.447708],"type":"Point"}
}