{
  "type": "Feature",
  "properties": {
    "gn:admin1_code":"35",
    "gn:admin2_code":"459.0",
    "gn:asciiname":"Kachhi Bhonra",
    "gn:country_code":"IN",
    "gn:dem":499,
    "gn:feature_class":"P",
    "gn:feature_code":"PPL",
    "gn:name":"K\u0101chhi Bhonra",
    "gn:population":0,
    "gn:timezone":"Asia/Kolkata",
    "iso:country":"IN",
    "wof:name":"Kachhi Bhonra",
    "wof:placetype":"locality"
},
  "geometry": {"coordinates":[77.69306,24.54543],"type":"Point"}
}