{
  "type": "Feature",
  "properties": {
    "iso:country":"IN",
    "ks:ks_alt_nam":"kattapara",
    "ks:ks_name":"Kattapara",
    "ks:ks_pop":106,
    "ks:ks_type":"HABITATION",
    "name:eng_x_preferred":[
        "Kattapara"
    ],
    "wof:name":"Kattapara",
    "wof:placetype":"locality",
    "wof:population":106
},
  "geometry": {"coordinates":[81.227341,19.685797],"type":"Point"}
}