{
  "type": "Feature",
  "properties": {
    "iso:country":"IN",
    "ks:ks_alt_nam":"NURDICHAK",
    "ks:ks_name":"Nurdichak",
    "ks:ks_pop":532,
    "ks:ks_type":"HABITATION",
    "ks:ks_uagg_main":0,
    "name:eng_x_preferred":[
        "Nurdichak"
    ],
    "wof:name":"Nurdichak",
    "wof:placetype":"neighbourhood",
    "wof:population":532
},
  "geometry": {"coordinates":[85.670402,25.063784],"type":"Point"}
}