{
  "type": "Feature",
  "properties": {
    "iso:country":"IN",
    "ks:ks_name":"Saray Tola",
    "ks:ks_pop":247,
    "ks:ks_type":"HABITATION",
    "name:eng_x_preferred":[
        "Saray Tola"
    ],
    "wof:name":"Saray Tola",
    "wof:placetype":"locality",
    "wof:population":247
},
  "geometry": {"coordinates":[86.170936,24.039612],"type":"Point"}
}