{
  "type": "Feature",
  "properties": {
    "gn:admin1_code":"36",
    "gn:admin2_code":"134.0",
    "gn:asciiname":"Ladawala",
    "gn:country_code":"IN",
    "gn:dem":236,
    "gn:feature_class":"P",
    "gn:feature_code":"PPL",
    "gn:name":"Lad\u0101w\u0101la",
    "gn:population":0,
    "gn:timezone":"Asia/Kolkata",
    "iso:country":"IN",
    "name:und_x_variant":[
        "Lad\u0101w\u0101la",
        "Muhammadpur L\u0101l"
    ],
    "wof:name":"Ladawala",
    "wof:placetype":"locality"
},
  "geometry": {"coordinates":[78.4589,29.30201],"type":"Point"}
}