{
  "type": "Feature",
  "properties": {
    "iso:country":"IN",
    "ks:ks_alt_nam":"Janapar supa",
    "ks:ks_name":"Janapar Supa",
    "ks:ks_pop":245,
    "ks:ks_type":"HABITATION",
    "name:eng_x_preferred":[
        "Janapar Supa"
    ],
    "wof:name":"Janapar Supa",
    "wof:placetype":"locality",
    "wof:population":245
},
  "geometry": {"coordinates":[91.488895,26.56702],"type":"Point"}
}