{
  "type": "Feature",
  "properties": {
    "gn:admin1_code":"21.0",
    "gn:admin2_code":"396.0",
    "gn:asciiname":"Biripanka",
    "gn:country_code":"IN",
    "gn:dem":357,
    "gn:feature_class":"P",
    "gn:feature_code":"PPL",
    "gn:name":"Biripanka",
    "gn:population":0,
    "gn:timezone":"Asia/Kolkata",
    "iso:country":"IN",
    "ks:ks_name":"Biripanga",
    "ks:ks_pop":175,
    "ks:ks_type":"VILLAGE",
    "name:eng_x_preferred":[
        "Biripanga"
    ],
    "name:eng_x_variant":[
        "Biripanka"
    ],
    "wof:name":"Biripanga",
    "wof:placetype":"locality",
    "wof:population":175
},
  "geometry": {"coordinates":[83.71257900000001,19.450637],"type":"Point"}
}