{
  "type": "Feature",
  "properties": {
    "gn:admin1_code":"24.0",
    "gn:admin2_code":"115",
    "gn:asciiname":"Kelnor",
    "gn:country_code":"IN",
    "gn:dem":146,
    "gn:feature_class":"P",
    "gn:feature_code":"PPL",
    "gn:name":"Kelnor",
    "gn:population":0,
    "gn:timezone":"Asia/Kolkata",
    "iso:country":"IN",
    "wof:name":"Kelnor",
    "wof:placetype":"locality"
},
  "geometry": {"coordinates":[70.73134,25.35037],"type":"Point"}
}