{
  "type": "Feature",
  "properties": {
    "gn:admin1_code":"2.0",
    "gn:asciiname":"Nagasandram",
    "gn:country_code":"IN",
    "gn:dem":799,
    "gn:feature_class":"P",
    "gn:feature_code":"PPL",
    "gn:name":"N\u0101gasandram",
    "gn:population":0,
    "gn:timezone":"Asia/Kolkata",
    "iso:country":"IN",
    "wof:name":"Nagasandram",
    "wof:placetype":"locality"
},
  "geometry": {"coordinates":[78.43179000000001,13.30963],"type":"Point"}
}