{
  "type": "Feature",
  "properties": {
    "gn:admin1_code":"23.0",
    "gn:admin2_code":"51.0",
    "gn:asciiname":"Sadabarat",
    "gn:country_code":"IN",
    "gn:dem":272,
    "gn:feature_class":"P",
    "gn:feature_code":"PPL",
    "gn:name":"Sad\u0101barat",
    "gn:population":0,
    "gn:timezone":"Asia/Kolkata",
    "iso:country":"IN",
    "wof:name":"Sadabarat",
    "wof:placetype":"locality"
},
  "geometry": {"coordinates":[76.53675,30.98184],"type":"Point"}
}