{
  "type": "Feature",
  "properties": {
    "iso:country":"IN",
    "ks:ks_name":"Pwarwasti",
    "ks:ks_pop":221,
    "ks:ks_type":"HABITATION",
    "ks:ks_uagg_main":0,
    "name:eng_x_preferred":[
        "Pwarwasti"
    ],
    "wof:name":"Pwarwasti",
    "wof:placetype":"neighbourhood",
    "wof:population":221
},
  "geometry": {"coordinates":[74.004361,18.532988],"type":"Point"}
}