{
  "type": "Feature",
  "properties": {
    "gn:admin1_code":"12.0",
    "gn:admin2_code":"22.0",
    "gn:asciiname":"Nangal",
    "gn:country_code":"IN",
    "gn:dem":393,
    "gn:feature_class":"P",
    "gn:feature_code":"PPL",
    "gn:name":"Nangal",
    "gn:population":0,
    "gn:timezone":"Asia/Kolkata",
    "iso:country":"IN",
    "name:ben_x_preferred":[
        "\u09a8\u09be\u0999\u09cd\u0997\u09be\u09b2"
    ],
    "name:bpy_x_preferred":[
        "\u09a8\u09be\u0999\u09cd\u0997\u09be\u09b2"
    ],
    "name:ceb_x_preferred":[
        "N\u0101ngal Township"
    ],
    "name:hif_x_preferred":[
        "Nangal"
    ],
    "name:hin_x_preferred":[
        "\u0928\u0902\u0917\u0932"
    ],
    "name:ita_x_preferred":[
        "Nangal"
    ],
    "name:msa_x_preferred":[
        "Nangal"
    ],
    "name:new_x_preferred":[
        "\u0928\u0928\u094d\u0917\u0932"
    ],
    "name:ori_x_preferred":[
        "\u0b28\u0b3e\u0b19\u0b4d\u0b17\u0b32\u0b4d"
    ],
    "name:pam_x_preferred":[
        "Nangal"
    ],
    "name:pan_x_preferred":[
        "\u0a28\u0a70\u0a17\u0a32"
    ],
    "name:spa_x_preferred":[
        "Nangal"
    ],
    "name:swe_x_preferred":[
        "N\u0101ngal Township"
    ],
    "name:urd_x_preferred":[
        "\u0646\u0627\u0646\u06af\u0627\u0644"
    ],
    "name:vie_x_preferred":[
        "Nangal"
    ],
    "name:zho_x_preferred":[
        "\u5357\u683c\u963f\u5c14"
    ],
    "wof:name":"Nangal",
    "wof:placetype":"locality"
},
  "geometry": {"coordinates":[75.11003000000002,32.63109],"type":"Point"}
}