{
  "type": "Feature",
  "properties": {
    "iso:country":"IN",
    "ks:ks_name":"Juna Rinchhrota",
    "ks:ks_pop":59,
    "ks:ks_type":"HABITATION",
    "ks:ks_uagg_main":0,
    "name:eng_x_preferred":[
        "Juna Rinchhrota"
    ],
    "wof:name":"Juna Rinchhrota",
    "wof:placetype":"neighbourhood",
    "wof:population":59
},
  "geometry": {"coordinates":[73.55765,22.876567],"type":"Point"}
}