{
  "type": "Feature",
  "properties": {
    "gn:admin1_code":"25.0",
    "gn:admin2_code":"611.0",
    "gn:asciiname":"Manjathala",
    "gn:country_code":"IN",
    "gn:dem":1810,
    "gn:feature_class":"P",
    "gn:feature_code":"PPL",
    "gn:name":"Manjathala",
    "gn:population":0,
    "gn:timezone":"Asia/Kolkata",
    "iso:country":"IN",
    "wof:name":"Manjathala",
    "wof:placetype":"locality"
},
  "geometry": {"coordinates":[76.77894000000001,11.36238],"type":"Point"}
}