{
  "type": "Feature",
  "properties": {
    "gn:admin1_code":"24.0",
    "gn:admin2_code":"112",
    "gn:asciiname":"Bidiyad",
    "gn:country_code":"IN",
    "gn:dem":450,
    "gn:feature_class":"P",
    "gn:feature_code":"PPL",
    "gn:name":"Bidiy\u0101d",
    "gn:population":0,
    "gn:timezone":"Asia/Kolkata",
    "iso:country":"IN",
    "name:und_x_variant":[
        "Bidiy\u0101d",
        "Bidi\u0101d"
    ],
    "wof:name":"Bidiyad",
    "wof:placetype":"locality"
},
  "geometry": {"coordinates":[74.69804000000001,26.96934000000001],"type":"Point"}
}