{
  "type": "Feature",
  "properties": {
    "iso:country":"IN",
    "ks:ks_alt_nam":"16.400 RD-R",
    "ks:ks_name":"16.400 Rd-r",
    "ks:ks_pop":200,
    "ks:ks_type":"HABITATION",
    "name:eng_x_preferred":[
        "16.400 Rd-r"
    ],
    "wof:name":"16.400 Rd-r",
    "wof:placetype":"locality",
    "wof:population":200
},
  "geometry": {"coordinates":[73.88959800000001,29.202036],"type":"Point"}
}