{
  "type": "Feature",
  "properties": {
    "gn:country":"IN",
    "gn:fcode":"PPL",
    "gn:pop":14709,
    "iso:country":"IN",
    "name:deu_x_preferred":[
        "Mohan"
    ],
    "name:eng_x_preferred":[
        "Mohan"
    ],
    "name:fra_x_preferred":[
        "Mohan"
    ],
    "name:hin_x_preferred":[
        "\u092e\u094b\u0939\u093e\u0928"
    ],
    "name:ita_x_preferred":[
        "Mohan"
    ],
    "name:nan_x_preferred":[
        "Mohan"
    ],
    "name:nld_x_preferred":[
        "Mohan"
    ],
    "name:pol_x_preferred":[
        "Mohan"
    ],
    "name:swe_x_preferred":[
        "Moh\u0101n"
    ],
    "name:unk_x_variant":[
        "Moh\u0101n"
    ],
    "name:urd_x_preferred":[
        "\u0645\u0648\u06c1\u0646\u060c \u0627\u062a\u0631\u067e\u0631\u062f\u06cc\u0634"
    ],
    "name:vie_x_preferred":[
        "Mohan"
    ],
    "name:zho_x_preferred":[
        "\u83ab\u6c49"
    ],
    "qs:name":"Mohan",
    "qs:name_adm0":"India",
    "qs:name_adm1":"Uttar Pradesh",
    "qs:photos_9r":0,
    "qs:photos_sr":0,
    "qs:placetype":"Town",
    "qs:pop_sr":"6",
    "wd:wordcount":998,
    "wof:name":"Mohan",
    "wof:placetype":"locality",
    "wof:population":14709
},
  "geometry": {"coordinates":[80.67497,26.78008],"type":"Point"}
}