{
  "type": "Feature",
  "properties": {
    "iso:country":"IN",
    "ks:ks_name":"Mandavkarwadi",
    "ks:ks_pop":516,
    "ks:ks_type":"HABITATION",
    "name:eng_x_preferred":[
        "Mandavkarwadi"
    ],
    "wof:name":"Mandavkarwadi",
    "wof:placetype":"locality",
    "wof:population":516
},
  "geometry": {"coordinates":[73.57669799999999,16.90574],"type":"Point"}
}