{
  "type": "Feature",
  "properties": {
    "iso:country":"IN",
    "ks:ks_name":"Rohidaswadi",
    "ks:ks_pop":53,
    "ks:ks_type":"HABITATION",
    "name:eng_x_preferred":[
        "Rohidaswadi"
    ],
    "wof:name":"Rohidaswadi",
    "wof:placetype":"locality",
    "wof:population":53
},
  "geometry": {"coordinates":[73.386861,17.924389],"type":"Point"}
}