{
  "type": "Feature",
  "properties": {
    "gn:admin1_code":"21",
    "gn:admin2_code":"398.0",
    "gn:asciiname":"Bitra Dabba",
    "gn:country_code":"IN",
    "gn:dem":1197,
    "gn:feature_class":"P",
    "gn:feature_code":"PPL",
    "gn:name":"Bitra Dabba",
    "gn:population":0,
    "gn:timezone":"Asia/Kolkata",
    "iso:country":"IN",
    "wof:name":"Bitra Dabba",
    "wof:placetype":"locality"
},
  "geometry": {"coordinates":[82.76875,18.45996],"type":"Point"}
}