{
  "type": "Feature",
  "properties": {
    "iso:country":"IN",
    "ks:ks_name":"Thana Falia",
    "ks:ks_pop":881,
    "ks:ks_type":"HABITATION",
    "name:eng_x_preferred":[
        "Thana Falia"
    ],
    "wof:name":"Thana Falia",
    "wof:placetype":"locality",
    "wof:population":881
},
  "geometry": {"coordinates":[73.831333,22.644333],"type":"Point"}
}