{
  "type": "Feature",
  "properties": {
    "iso:country":"IN",
    "ks:ks_alt_nam":"G\u0101ro",
    "ks:ks_name":"Garo",
    "ks:ks_pop":0,
    "ks:ks_type":"VILLAGE",
    "name:eng_x_preferred":[
        "Garo"
    ],
    "name:eng_x_variant":[
        "G\u0101ro"
    ],
    "wof:name":"Garo",
    "wof:placetype":"locality",
    "wof:population":0
},
  "geometry": {"coordinates":[83.824974,24.958463],"type":"Point"}
}