{
  "type": "Feature",
  "properties": {
    "gn:admin1_code":"24",
    "gn:admin2_code":"106.0",
    "gn:asciiname":"Gudha",
    "gn:country_code":"IN",
    "gn:dem":244,
    "gn:feature_class":"P",
    "gn:feature_code":"PPL",
    "gn:name":"Gudha",
    "gn:population":0,
    "gn:timezone":"Asia/Kolkata",
    "iso:country":"IN",
    "ks:ks_name":"Gurha",
    "ks:ks_pop":675,
    "ks:ks_type":"VILLAGE",
    "name:eng_x_preferred":[
        "Gurha"
    ],
    "name:eng_x_variant":[
        "Gudha"
    ],
    "wof:name":"Gurha",
    "wof:placetype":"locality",
    "wof:population":675
},
  "geometry": {"coordinates":[77.44151100000001,26.538431],"type":"Point"}
}