{
  "type": "Feature",
  "properties": {
    "gn:admin1_code":"21",
    "gn:admin2_code":"370.0",
    "gn:asciiname":"Telipukhapani",
    "gn:country_code":"IN",
    "gn:dem":182,
    "gn:feature_class":"P",
    "gn:feature_code":"PPL",
    "gn:name":"Telipukh\u0101p\u0101ni",
    "gn:population":0,
    "gn:timezone":"Asia/Kolkata",
    "iso:country":"IN",
    "ks:ks_alt_nam":"Telipukh\u0101p\u0101ni",
    "ks:ks_name":"Telipukhapani",
    "ks:ks_type":"VILLAGE",
    "name:eng_x_preferred":[
        "Telipukhapani"
    ],
    "name:eng_x_variant":[
        "Telipukh\u0101p\u0101ni"
    ],
    "wof:name":"Telipukhapani",
    "wof:placetype":"locality"
},
  "geometry": {"coordinates":[83.252984,20.964706],"type":"Point"}
}