{
  "type": "Feature",
  "properties": {
    "gn:admin1_code":"35.0",
    "gn:admin2_code":"457.0",
    "gn:asciiname":"Garra",
    "gn:country_code":"IN",
    "gn:dem":315,
    "gn:feature_class":"P",
    "gn:feature_code":"PPL",
    "gn:name":"Garr\u0101",
    "gn:population":0,
    "gn:timezone":"Asia/Kolkata",
    "iso:country":"IN",
    "name:ara_x_preferred":[
        "\u0635\u062f"
    ],
    "name:cat_x_preferred":[
        "Garra"
    ],
    "name:ceb_x_preferred":[
        "Garra"
    ],
    "name:deu_x_preferred":[
        "Garra"
    ],
    "name:fas_x_preferred":[
        "\u0633\u0646\u06af\u200c\u0644\u06cc\u0633"
    ],
    "name:fra_x_preferred":[
        "Garra"
    ],
    "name:ita_x_preferred":[
        "Garra"
    ],
    "name:kir_x_preferred":[
        "\u0413\u0430\u0440\u0440\u0430\u043f\u0430\u0440"
    ],
    "name:kor_x_preferred":[
        "\uac00\ub77c\uc18d"
    ],
    "name:lit_x_preferred":[
        "\u016asuotosios prielipos"
    ],
    "name:nld_x_preferred":[
        "Garra"
    ],
    "name:nor_x_preferred":[
        "Garra"
    ],
    "name:pol_x_preferred":[
        "Garra"
    ],
    "name:por_x_preferred":[
        "Garra"
    ],
    "name:spa_x_preferred":[
        "Garra"
    ],
    "name:swe_x_preferred":[
        "Garra"
    ],
    "name:tha_x_preferred":[
        "\u0e1b\u0e25\u0e32\u0e40\u0e25\u0e35\u0e22\u0e2b\u0e34\u0e19"
    ],
    "name:vie_x_preferred":[
        "Garra"
    ],
    "name:war_x_preferred":[
        "Garra"
    ],
    "name:zho_x_preferred":[
        "\u58a8\u5934\u9c7c\u5c5e"
    ],
    "wof:name":"Garra",
    "wof:placetype":"locality"
},
  "geometry": {"coordinates":[80.14108,21.80921],"type":"Point"}
}