{
  "type": "Feature",
  "properties": {
    "gn:admin1_code":"2.0",
    "gn:admin2_code":"553.0",
    "gn:asciiname":"Rekalakunta",
    "gn:country_code":"IN",
    "gn:dem":625,
    "gn:feature_class":"P",
    "gn:feature_code":"PPL",
    "gn:name":"Rekalakunta",
    "gn:population":0,
    "gn:timezone":"Asia/Kolkata",
    "iso:country":"IN",
    "wof:name":"Rekalakunta",
    "wof:placetype":"neighbourhood"
},
  "geometry": {"coordinates":[77.34774,13.94348],"type":"Point"}
}