{
  "type": "Feature",
  "properties": {
    "gn:admin1_code":"19.0",
    "gn:admin2_code":"563.0",
    "gn:asciiname":"Hangar",
    "gn:country_code":"IN",
    "gn:dem":527,
    "gn:feature_class":"P",
    "gn:feature_code":"PPL",
    "gn:name":"Hang\u0101r",
    "gn:population":0,
    "gn:timezone":"Asia/Kolkata",
    "iso:country":"IN",
    "name:ara_x_preferred":[
        "\u062d\u0638\u064a\u0631\u0629 \u0637\u0627\u0626\u0631\u0627\u062a"
    ],
    "name:ast_x_preferred":[
        "Hangar"
    ],
    "name:bul_x_preferred":[
        "\u0425\u0430\u043d\u0433\u0430\u0440"
    ],
    "name:cat_x_preferred":[
        "Hangar"
    ],
    "name:ces_x_preferred":[
        "Hang\u00e1r"
    ],
    "name:dan_x_preferred":[
        "Hangar"
    ],
    "name:deu_x_preferred":[
        "Hangar"
    ],
    "name:epo_x_preferred":[
        "Hangaro"
    ],
    "name:est_x_preferred":[
        "Angaar"
    ],
    "name:fas_x_preferred":[
        "\u0622\u0634\u06cc\u0627\u0646\u0647"
    ],
    "name:fin_x_preferred":[
        "Lentokonehalli"
    ],
    "name:fra_x_preferred":[
        "Hangar"
    ],
    "name:glg_x_preferred":[
        "Hangar"
    ],
    "name:heb_x_preferred":[
        "\u05d4\u05d0\u05e0\u05d2\u05e8"
    ],
    "name:ido_x_preferred":[
        "Hangaro"
    ],
    "name:ind_x_preferred":[
        "Hangar"
    ],
    "name:ita_x_preferred":[
        "Hangar"
    ],
    "name:jpn_x_preferred":[
        "\u683c\u7d0d\u5eab"
    ],
    "name:kat_x_preferred":[
        "\u10d0\u10dc\u10d2\u10d0\u10e0\u10d8"
    ],
    "name:kaz_x_preferred":[
        "\u0410\u043d\u0433\u0430\u0440"
    ],
    "name:kir_x_preferred":[
        "\u0410\u043d\u0433\u0430\u0440"
    ],
    "name:kor_x_preferred":[
        "\uaca9\ub0a9\uace0"
    ],
    "name:lit_x_preferred":[
        "Angaras"
    ],
    "name:nld_x_preferred":[
        "Hangar"
    ],
    "name:nor_x_preferred":[
        "Hangar"
    ],
    "name:pol_x_preferred":[
        "Hangar"
    ],
    "name:por_x_preferred":[
        "Hangar"
    ],
    "name:ron_x_preferred":[
        "Hangar"
    ],
    "name:rus_x_preferred":[
        "\u0410\u043d\u0433\u0430\u0440"
    ],
    "name:slk_x_preferred":[
        "Hang\u00e1r"
    ],
    "name:slv_x_preferred":[
        "Hangar"
    ],
    "name:spa_x_preferred":[
        "Hangar"
    ],
    "name:srp_x_preferred":[
        "\u0425\u0430\u043d\u0433\u0430\u0440"
    ],
    "name:swe_x_preferred":[
        "Hangar"
    ],
    "name:tgk_x_preferred":[
        "\u0410\u043d\u0433\u0430\u0440"
    ],
    "name:tur_x_preferred":[
        "Hangar"
    ],
    "name:ukr_x_preferred":[
        "\u0410\u043d\u0433\u0430\u0440"
    ],
    "name:uzb_x_preferred":[
        "Angar"
    ],
    "name:yid_x_preferred":[
        "\u05d4\u05d0\u05e0\u05d2\u05d0\u05e8"
    ],
    "name:zho_x_preferred":[
        "\u98de\u673a\u5e93"
    ],
    "wof:name":"Hangar",
    "wof:placetype":"locality"
},
  "geometry": {"coordinates":[74.74117,14.53803],"type":"Point"}
}