{
  "type": "Feature",
  "properties": {
    "iso:country":"IN",
    "ks:ks_name":"P. Gokul",
    "ks:ks_pop":255,
    "ks:ks_type":"HABITATION",
    "ks:ks_uagg_main":0,
    "name:eng_x_preferred":[
        "P. Gokul"
    ],
    "wof:name":"P. Gokul",
    "wof:placetype":"neighbourhood",
    "wof:population":255
},
  "geometry": {"coordinates":[81.2341,26.146213],"type":"Point"}
}