{
  "type": "Feature",
  "properties": {
    "gn:admin1_code":"36",
    "gn:admin2_code":"159.0",
    "gn:asciiname":"Chhitapur Kapurapur",
    "gn:country_code":"IN",
    "gn:dem":145,
    "gn:feature_class":"P",
    "gn:feature_code":"PPL",
    "gn:name":"Chhit\u0101pur Kap\u016br\u0101pur",
    "gn:population":0,
    "gn:timezone":"Asia/Kolkata",
    "iso:country":"IN",
    "wof:name":"Chhitapur Kapurapur",
    "wof:placetype":"neighbourhood"
},
  "geometry": {"coordinates":[79.64382000000001,27.25644],"type":"Point"}
}