{
  "type": "Feature",
  "properties": {
    "gn:admin1_code":"25.0",
    "gn:admin2_code":"608.0",
    "gn:asciiname":"Vembadithalam",
    "gn:country_code":"IN",
    "gn:dem":258,
    "gn:feature_class":"P",
    "gn:feature_code":"PPL",
    "gn:name":"Vembadithalam",
    "gn:population":0,
    "gn:timezone":"Asia/Kolkata",
    "iso:country":"IN",
    "name:fas_x_preferred":[
        "\u0648\u0645\u0628\u062f\u06cc\u062a\u0647\u0644\u0645"
    ],
    "wof:name":"Vembadithalam",
    "wof:placetype":"locality"
},
  "geometry": {"coordinates":[78.01094999999999,11.56741],"type":"Point"}
}