{
  "type": "Feature",
  "properties": {
    "gn:admin1_code":"36.0",
    "gn:admin2_code":"177.0",
    "gn:asciiname":"Dhima",
    "gn:country_code":"IN",
    "gn:dem":112,
    "gn:feature_class":"P",
    "gn:feature_code":"PPL",
    "gn:name":"Dhima",
    "gn:population":0,
    "gn:timezone":"Asia/Kolkata",
    "iso:country":"IN",
    "name:guj_x_preferred":[
        "\u0aa2\u0ac0\u0aae\u0abe"
    ],
    "wof:name":"Dhima",
    "wof:placetype":"locality"
},
  "geometry": {"coordinates":[81.74558,26.54981],"type":"Point"}
}