{
  "type": "Feature",
  "properties": {
    "iso:country":"IN",
    "ks:ks_alt_nam":"sinba",
    "ks:ks_name":"Sinba",
    "ks:ks_pop":859,
    "ks:ks_type":"HABITATION",
    "ks:ks_uagg_main":0,
    "name:eng_x_preferred":[
        "Sinba"
    ],
    "wof:name":"Sinba",
    "wof:placetype":"locality",
    "wof:population":859
},
  "geometry": {"coordinates":[88.136081,22.564004],"type":"Point"}
}