{
  "type": "Feature",
  "properties": {
    "iso:country":"IN",
    "ks:ks_name":"Lainguda",
    "ks:ks_pop":81,
    "ks:ks_type":"VILLAGE",
    "name:eng_x_preferred":[
        "Lainguda"
    ],
    "wof:name":"Lainguda",
    "wof:placetype":"locality",
    "wof:population":81
},
  "geometry": {"coordinates":[83.098569,19.658861],"type":"Point"}
}