{
  "type": "Feature",
  "properties": {
    "iso:country":"IN",
    "ks:ks_name":"Jotkalyan",
    "ks:ks_pop":2918,
    "ks:ks_type":"VILLAGE",
    "ks:ks_uagg_main":0,
    "name:eng_x_preferred":[
        "Jotkalyan"
    ],
    "wof:name":"Jotkalyan",
    "wof:placetype":"locality",
    "wof:population":2918
},
  "geometry": {"coordinates":[88.01647199999999,22.586257],"type":"Point"}
}