{
  "type": "Feature",
  "properties": {
    "iso:country":"IN",
    "ks:ks_name":"Ajjet Nagar",
    "ks:ks_pop":636,
    "ks:ks_type":"HABITATION",
    "name:eng_x_preferred":[
        "Ajjet Nagar"
    ],
    "wof:name":"Ajjet Nagar",
    "wof:placetype":"locality",
    "wof:population":636
},
  "geometry": {"coordinates":[72.766289,26.176097],"type":"Point"}
}