{
  "type": "Feature",
  "properties": {
    "iso:country":"IN",
    "ks:ks_name":"Kosamadi",
    "ks:ks_pop":5305,
    "ks:ks_type":"VILLAGE",
    "name:eng_x_preferred":[
        "Kosamadi"
    ],
    "wof:name":"Kosamadi",
    "wof:placetype":"neighbourhood",
    "wof:population":5305
},
  "geometry": {"coordinates":[73.032347,21.582867],"type":"Point"}
}