{
  "type": "Feature",
  "properties": {
    "iso:country":"IN",
    "ks:ks_name":"Petaphula",
    "ks:ks_pop":241,
    "ks:ks_type":"HABITATION",
    "name:eng_x_preferred":[
        "Petaphula"
    ],
    "wof:name":"Petaphula",
    "wof:placetype":"locality",
    "wof:population":241
},
  "geometry": {"coordinates":[82.30134700000001,19.739347],"type":"Point"}
}