{
  "type": "Feature",
  "properties": {
    "iso:country":"IN",
    "ks:ks_name":"Baiga Salhewara",
    "ks:ks_pop":220,
    "ks:ks_type":"HABITATION",
    "name:eng_x_preferred":[
        "Baiga Salhewara"
    ],
    "wof:name":"Baiga Salhewara",
    "wof:placetype":"locality",
    "wof:population":220
},
  "geometry": {"coordinates":[80.83490999999999,21.708256],"type":"Point"}
}