{
  "type": "Feature",
  "properties": {
    "iso:country":"IN",
    "ks:ks_name":"Sabalewadi",
    "ks:ks_pop":358,
    "ks:ks_type":"HABITATION",
    "name:eng_x_preferred":[
        "Sabalewadi"
    ],
    "wof:name":"Sabalewadi",
    "wof:placetype":"locality",
    "wof:population":358
},
  "geometry": {"coordinates":[73.958309,17.249768],"type":"Point"}
}