{
  "type": "Feature",
  "properties": {
    "iso:country":"IN",
    "ks:ks_name":"Karidi Alias Mada",
    "ks:ks_pop":94,
    "ks:ks_type":"VILLAGE",
    "name:eng_x_preferred":[
        "Karidi Alias Mada"
    ],
    "wof:name":"Karidi Alias Mada",
    "wof:placetype":"locality",
    "wof:population":94
},
  "geometry": {"coordinates":[84.87938200000001,24.453739],"type":"Point"}
}