{
  "type": "Feature",
  "properties": {
    "iso:country":"IN",
    "ks:ks_name":"Bind Basti",
    "ks:ks_pop":1120,
    "ks:ks_type":"HABITATION",
    "name:eng_x_preferred":[
        "Bind Basti"
    ],
    "wof:name":"Bind Basti",
    "wof:placetype":"locality",
    "wof:population":1120
},
  "geometry": {"coordinates":[82.426739,25.865025],"type":"Point"}
}