{
  "type": "Feature",
  "properties": {
    "iso:country":"IN",
    "ks:ks_name":"Brahamandara",
    "ks:ks_pop":100,
    "ks:ks_type":"HABITATION",
    "name:eng_x_preferred":[
        "Brahamandara"
    ],
    "wof:name":"Brahamandara",
    "wof:placetype":"locality",
    "wof:population":100
},
  "geometry": {"coordinates":[74.480706,19.085696],"type":"Point"}
}