{
  "type": "Feature",
  "properties": {
    "iso:country":"IN",
    "ks:ks_alt_nam":"NPS Colony",
    "ks:ks_name":"Nps Colony",
    "ks:ks_pop":410,
    "ks:ks_type":"HABITATION",
    "name:eng_x_preferred":[
        "Nps Colony"
    ],
    "wof:name":"Nps Colony",
    "wof:placetype":"locality",
    "wof:population":410
},
  "geometry": {"coordinates":[78.75944,10.715511],"type":"Point"}
}