{
  "type": "Feature",
  "properties": {
    "iso:country":"IN",
    "ks:ks_name":"Sakunde Dhawale Nikam",
    "ks:ks_pop":425,
    "ks:ks_type":"HABITATION",
    "ks:ks_uagg_main":0,
    "name:eng_x_preferred":[
        "Sakunde Dhawale Nikam"
    ],
    "wof:name":"Sakunde Dhawale Nikam",
    "wof:placetype":"neighbourhood",
    "wof:population":425
},
  "geometry": {"coordinates":[74.749,18.278],"type":"Point"}
}