{
  "type": "Feature",
  "properties": {
    "gn:admin1_code":"16.0",
    "gn:admin2_code":"523.0",
    "gn:asciiname":"Kesapuri",
    "gn:country_code":"IN",
    "gn:dem":437,
    "gn:feature_class":"P",
    "gn:feature_code":"PPL",
    "gn:name":"Kes\u0101puri",
    "gn:population":0,
    "gn:timezone":"Asia/Kolkata",
    "iso:country":"IN",
    "wof:name":"Kesapuri",
    "wof:placetype":"locality"
},
  "geometry": {"coordinates":[76.19032,19.1889],"type":"Point"}
}