{
  "type": "Feature",
  "properties": {
    "gn:admin1_code":"36",
    "gn:admin2_code":"178.0",
    "gn:asciiname":"Ausanpur",
    "gn:country_code":"IN",
    "gn:dem":93,
    "gn:feature_class":"P",
    "gn:feature_code":"PPL",
    "gn:name":"Aus\u0101npur",
    "gn:population":0,
    "gn:timezone":"Asia/Kolkata",
    "iso:country":"IN",
    "ks:ks_name":"Absanpur",
    "ks:ks_pop":1927,
    "ks:ks_type":"HABITATION",
    "name:eng_x_preferred":[
        "Absanpur"
    ],
    "name:eng_x_variant":[
        "Ausanpur"
    ],
    "name:urd_x_preferred":[
        "\u0627\u0648\u0633\u0627\u0646 \u067e\u0648\u0631"
    ],
    "wof:name":"Absanpur",
    "wof:placetype":"locality",
    "wof:population":1927
},
  "geometry": {"coordinates":[82.511939,26.633624],"type":"Point"}
}