{
  "type": "Feature",
  "properties": {
    "iso:country":"IN",
    "ks:ks_name":"Jaichandra Badavane",
    "ks:ks_pop":87,
    "ks:ks_type":"HABITATION",
    "name:eng_x_preferred":[
        "Jaichandra Badavane"
    ],
    "wof:name":"Jaichandra Badavane",
    "wof:placetype":"locality",
    "wof:population":87
},
  "geometry": {"coordinates":[76.924457,13.660594],"type":"Point"}
}