{
  "type": "Feature",
  "properties": {
    "iso:country":"IN",
    "ks:ks_name":"Nong Krong 2",
    "ks:ks_pop":70,
    "ks:ks_type":"HABITATION",
    "name:eng_x_preferred":[
        "Nong Krong 2"
    ],
    "wof:name":"Nong Krong 2",
    "wof:placetype":"locality",
    "wof:population":70
},
  "geometry": {"coordinates":[92.5967,25.842358],"type":"Point"}
}