{
  "type": "Feature",
  "properties": {
    "iso:country":"IN",
    "name:ben_x_preferred":[
        "\u09b0\u09be\u09a8\u09cd\u09a8\u09bf"
    ],
    "name:deu_x_preferred":[
        "Ranni"
    ],
    "name:eng_x_preferred":[
        "Ranni"
    ],
    "name:eng_x_variant":[
        "Ranni Taluk"
    ],
    "name:fra_x_preferred":[
        "Ranni"
    ],
    "name:guj_x_preferred":[
        "\u0ab0\u0abe\u0aa8\u0ac0"
    ],
    "name:hin_x_preferred":[
        "\u0930\u093e\u0928\u094d\u0928\u0940"
    ],
    "name:jpn_x_preferred":[
        "\u30e9\u30f3\u30cb"
    ],
    "name:kan_x_preferred":[
        "\u0cb0\u0ca8\u0ccd\u0ca8\u0cbf"
    ],
    "name:kor_x_preferred":[
        "\ub780\ub2c8"
    ],
    "name:mal_x_preferred":[
        "\u0d31\u0d3e\u0d28\u0d4d\u0d28\u0d3f \u0d24\u0d3e\u0d32\u0d42\u0d15\u0d4d\u0d15\u0d4d"
    ],
    "name:mar_x_preferred":[
        "\u0930\u093e\u0928\u094d\u0928\u0940"
    ],
    "name:nld_x_preferred":[
        "Ranni"
    ],
    "name:por_x_preferred":[
        "Ranni"
    ],
    "name:rus_x_preferred":[
        "\u0420\u0430\u043d\u043d\u0438"
    ],
    "name:spa_x_preferred":[
        "Ranni"
    ],
    "name:tam_x_preferred":[
        "\u0bb0\u0ba9\u0bcd\u0ba9\u0bbf"
    ],
    "name:tel_x_preferred":[
        "\u0c30\u0c28\u0c4d\u0c28\u0c3f"
    ],
    "name:urd_x_preferred":[
        "\u0631\u0627\u0646\u0646\u06cc"
    ],
    "qs:name":"Ranni",
    "qs:name_adm0":"India",
    "qs:name_adm1":"Kerala",
    "qs:photos":12,
    "qs:photos_1k":2,
    "qs:photos_9k":1,
    "qs:photos_9r":1,
    "qs:photos_all":12,
    "qs:photos_sr":1,
    "qs:placetype":"Town",
    "qs:pop_sr":"0",
    "wd:wordcount":1542,
    "wof:name":"Ranni",
    "wof:placetype":"locality"
},
  "geometry": {"coordinates":[76.793403,9.369127],"type":"Point"}
}