{
  "type": "Feature",
  "properties": {
    "iso:country":"IN",
    "ks:ks_name":"Chandpur",
    "ks:ks_pop":1782,
    "ks:ks_type":"VILLAGE",
    "name:eng_x_preferred":[
        "Chandpur"
    ],
    "wof:name":"Chandpur",
    "wof:placetype":"locality",
    "wof:population":1782
},
  "geometry": {"coordinates":[73.87374,22.940668],"type":"Point"}
}