{
  "type": "Feature",
  "properties": {
    "iso:country":"IN",
    "ks:ks_name":"Kalkai",
    "ks:ks_pop":190,
    "ks:ks_type":"VILLAGE",
    "name:eng_x_preferred":[
        "Kalkai"
    ],
    "wof:name":"Kalkai",
    "wof:placetype":"locality",
    "wof:population":190
},
  "geometry": {"coordinates":[74.700254,14.367603],"type":"Point"}
}