{
  "type": "Feature",
  "properties": {
    "iso:country":"IN",
    "ks:ks_name":"Chak Ibrahim",
    "ks:ks_pop":739,
    "ks:ks_type":"VILLAGE",
    "name:eng_x_preferred":[
        "Chak Ibrahim"
    ],
    "wof:name":"Chak Ibrahim",
    "wof:placetype":"locality",
    "wof:population":739
},
  "geometry": {"coordinates":[85.338849,25.647054],"type":"Point"}
}