{
  "type": "Feature",
  "properties": {
    "iso:country":"IN",
    "ks:ks_name":"Bellakkana",
    "ks:ks_pop":1523,
    "ks:ks_type":"HABITATION",
    "name:eng_x_preferred":[
        "Bellakkana"
    ],
    "wof:name":"Bellakkana",
    "wof:placetype":"locality",
    "wof:population":1523
},
  "geometry": {"coordinates":[75.256286,12.545743],"type":"Point"}
}