{
  "type": "Feature",
  "properties": {
    "iso:country":"IN",
    "ks:ks_name":"Amrodh",
    "ks:ks_pop":124,
    "ks:ks_type":"VILLAGE",
    "name:eng_x_preferred":[
        "Amrodh"
    ],
    "wof:name":"Amrodh",
    "wof:placetype":"locality",
    "wof:population":124
},
  "geometry": {"coordinates":[79.23009999999999,25.8255],"type":"Point"}
}