{
  "type": "Feature",
  "properties": {
    "gn:admin1_code":"34.0",
    "gn:admin2_code":"236.0",
    "gn:asciiname":"Musi",
    "gn:country_code":"IN",
    "gn:dem":95,
    "gn:feature_class":"P",
    "gn:feature_code":"PPL",
    "gn:name":"Musi",
    "gn:population":0,
    "gn:timezone":"Asia/Kolkata",
    "iso:country":"IN",
    "name:ceb_x_preferred":[
        "Musi"
    ],
    "name:deu_x_preferred":[
        "Musi"
    ],
    "name:fra_x_preferred":[
        "Musi"
    ],
    "name:ind_x_preferred":[
        "Musi"
    ],
    "name:ita_x_preferred":[
        "Musi"
    ],
    "name:nds_x_preferred":[
        "Musi"
    ],
    "name:nld_x_preferred":[
        "Musi"
    ],
    "name:pol_x_preferred":[
        "Musi"
    ],
    "name:rus_x_preferred":[
        "\u041c\u0443\u0441\u0438"
    ],
    "name:swe_x_preferred":[
        "Musi"
    ],
    "wof:name":"Musi",
    "wof:placetype":"locality"
},
  "geometry": {"coordinates":[84.91155999999999,24.9427],"type":"Point"}
}