{
  "type": "Feature",
  "properties": {
    "gn:admin1_code":"23.0",
    "gn:admin2_code":"040",
    "gn:asciiname":"Bhatton",
    "gn:country_code":"IN",
    "gn:dem":259,
    "gn:feature_class":"P",
    "gn:feature_code":"PPL",
    "gn:name":"Bhatton",
    "gn:population":0,
    "gn:timezone":"Asia/Kolkata",
    "iso:country":"IN",
    "wof:name":"Bhatton",
    "wof:placetype":"locality"
},
  "geometry": {"coordinates":[76.20867,30.56433],"type":"Point"}
}