{
  "type": "Feature",
  "properties": {
    "iso:country":"IN",
    "ks:ks_name":"Zurewadi",
    "ks:ks_pop":37,
    "ks:ks_type":"HABITATION",
    "name:eng_x_preferred":[
        "Zurewadi"
    ],
    "wof:name":"Zurewadi",
    "wof:placetype":"locality",
    "wof:population":37
},
  "geometry": {"coordinates":[73.55422299999999,18.066249],"type":"Point"}
}