{
  "type": "Feature",
  "properties": {
    "gn:admin1_code":"36",
    "gn:admin2_code":"148.0",
    "gn:asciiname":"Jaramai",
    "gn:country_code":"IN",
    "gn:dem":161,
    "gn:feature_class":"P",
    "gn:feature_code":"PPL",
    "gn:name":"Jar\u0101ma\u012b",
    "gn:population":0,
    "gn:timezone":"Asia/Kolkata",
    "iso:country":"IN",
    "ks:ks_alt_nam":"Jar\u0101ma\u012b",
    "ks:ks_name":"Jaramai",
    "ks:ks_pop":974,
    "ks:ks_type":"VILLAGE",
    "ks:ks_uagg_main":0,
    "name:eng_x_preferred":[
        "Jaramai"
    ],
    "name:eng_x_variant":[
        "Jar\u0101ma\u012b"
    ],
    "wof:name":"Jaramai",
    "wof:placetype":"neighbourhood",
    "wof:population":974
},
  "geometry": {"coordinates":[79.044479,27.382355],"type":"Point"}
}