{
  "type": "Feature",
  "properties": {
    "gn:admin1_code":"40",
    "gn:admin2_code":"541.0",
    "gn:asciiname":"Munagala",
    "gn:country_code":"IN",
    "gn:dem":63,
    "gn:feature_class":"P",
    "gn:feature_code":"PPL",
    "gn:name":"Munag\u0101la",
    "gn:population":0,
    "gn:timezone":"Asia/Kolkata",
    "iso:country":"IN",
    "name:new_x_preferred":[
        "\u092e\u0941\u0928\u0917\u093e\u0932 \u092e\u0923\u094d\u0921\u0932"
    ],
    "name:tel_x_preferred":[
        "\u0c2e\u0c41\u0c28\u0c17\u0c3e\u0c32"
    ],
    "wof:name":"Munagala",
    "wof:placetype":"neighbourhood"
},
  "geometry": {"coordinates":[80.35455,16.94831],"type":"Point"}
}