{
  "type": "Feature",
  "properties": {
    "iso:country":"IN",
    "ks:ks_name":"Nawagaon",
    "ks:ks_pop":158,
    "ks:ks_type":"VILLAGE",
    "name:eng_x_preferred":[
        "Nawagaon"
    ],
    "wof:name":"Nawagaon",
    "wof:placetype":"locality",
    "wof:population":158
},
  "geometry": {"coordinates":[83.489976,22.39326],"type":"Point"}
}