{
  "type": "Feature",
  "properties": {
    "iso:country":"IN",
    "ks:ks_name":"Arazi Kashi Singhanpura",
    "ks:ks_pop":0,
    "ks:ks_type":"VILLAGE",
    "name:eng_x_preferred":[
        "Arazi Kashi Singhanpura"
    ],
    "wof:name":"Arazi Kashi Singhanpura",
    "wof:placetype":"locality",
    "wof:population":0
},
  "geometry": {"coordinates":[84.181403,25.631343],"type":"Point"}
}