{
  "type": "Feature",
  "properties": {
    "iso:country":"IN",
    "ks:ks_name":"Dhausad",
    "ks:ks_pop":189,
    "ks:ks_type":"HABITATION",
    "name:eng_x_preferred":[
        "Dhausad"
    ],
    "wof:name":"Dhausad",
    "wof:placetype":"locality",
    "wof:population":189
},
  "geometry": {"coordinates":[80.606427,24.292539],"type":"Point"}
}