{
  "type": "Feature",
  "properties": {
    "iso:country":"IN",
    "ks:ks_alt_nam":"Irular colony",
    "ks:ks_name":"Irular Colony",
    "ks:ks_pop":123,
    "ks:ks_type":"HABITATION",
    "ks:ks_uagg_main":0,
    "name:eng_x_preferred":[
        "Irular Colony"
    ],
    "wof:name":"Irular Colony",
    "wof:placetype":"neighbourhood",
    "wof:population":123
},
  "geometry": {"coordinates":[79.778688,13.202188],"type":"Point"}
}