{
  "type": "Feature",
  "properties": {
    "iso:country":"IN",
    "ks:ks_alt_nam":"Mela nattarkualm",
    "ks:ks_name":"Mela Nattarkualm",
    "ks:ks_pop":872,
    "ks:ks_type":"HABITATION",
    "ks:ks_uagg_main":0,
    "name:eng_x_preferred":[
        "Mela Nattarkualm"
    ],
    "wof:name":"Mela Nattarkualm",
    "wof:placetype":"neighbourhood",
    "wof:population":872
},
  "geometry": {"coordinates":[77.826295,8.675252],"type":"Point"}
}