{
  "type": "Feature",
  "properties": {
    "gn:admin1_code":"16",
    "gn:admin2_code":"510.0",
    "gn:asciiname":"Manki",
    "gn:country_code":"IN",
    "gn:dem":210,
    "gn:feature_class":"P",
    "gn:feature_code":"PPL",
    "gn:name":"M\u0101nki",
    "gn:population":0,
    "gn:timezone":"Asia/Kolkata",
    "iso:country":"IN",
    "wof:name":"Manki",
    "wof:placetype":"locality"
},
  "geometry": {"coordinates":[78.93496,20.01395],"type":"Point"}
}