{
  "type": "Feature",
  "properties": {
    "iso:country":"IN",
    "ks:ks_name":"Kurumugai Village",
    "ks:ks_pop":313,
    "ks:ks_type":"HABITATION",
    "name:eng_x_preferred":[
        "Kurumugai Village"
    ],
    "wof:name":"Kurumugai Village",
    "wof:placetype":"locality",
    "wof:population":313
},
  "geometry": {"coordinates":[80.02763299999999,12.564506],"type":"Point"}
}