{
  "type": "Feature",
  "properties": {
    "iso:country":"IN",
    "ks:ks_name":"Harjika Seera",
    "ks:ks_pop":377,
    "ks:ks_type":"HABITATION",
    "name:eng_x_preferred":[
        "Harjika Seera"
    ],
    "wof:name":"Harjika Seera",
    "wof:placetype":"locality",
    "wof:population":377
},
  "geometry": {"coordinates":[73.92186700000001,23.755156],"type":"Point"}
}