{
  "type": "Feature",
  "properties": {
    "gn:admin1_code":"35.0",
    "gn:admin2_code":"420",
    "gn:asciiname":"Phulepura",
    "gn:country_code":"IN",
    "gn:dem":146,
    "gn:feature_class":"P",
    "gn:feature_code":"PPL",
    "gn:name":"Ph\u016blepura",
    "gn:population":0,
    "gn:timezone":"Asia/Kolkata",
    "iso:country":"IN",
    "wof:name":"Phulepura",
    "wof:placetype":"neighbourhood"
},
  "geometry": {"coordinates":[79.04639,26.42312],"type":"Point"}
}