{
  "type": "Feature",
  "properties": {
    "iso:country":"IN",
    "ks:ks_alt_nam":"Loh\u0101ra Reserved Forest",
    "ks:ks_name":"Lohara Reserved Forest",
    "ks:ks_type":"VILLAGE",
    "name:eng_x_preferred":[
        "Lohara Reserved Forest"
    ],
    "name:eng_x_variant":[
        "Loh\u0101ra Reserved Forest"
    ],
    "wof:name":"Lohara Reserved Forest",
    "wof:placetype":"locality"
},
  "geometry": {"coordinates":[83.681369,21.579566],"type":"Point"}
}