{
  "type": "Feature",
  "properties": {
    "iso:country":"IN",
    "ks:ks_name":"Aitnalli",
    "ks:ks_pop":4,
    "ks:ks_type":"HABITATION",
    "name:eng_x_preferred":[
        "Aitnalli"
    ],
    "wof:name":"Aitnalli",
    "wof:placetype":"locality",
    "wof:population":4
},
  "geometry": {"coordinates":[74.69649,14.358023],"type":"Point"}
}