{
  "type": "Feature",
  "properties": {
    "gn:admin1_code":"36",
    "gn:admin2_code":"191.0",
    "gn:asciiname":"Tuhfapur",
    "gn:country_code":"IN",
    "gn:dem":82,
    "gn:feature_class":"P",
    "gn:feature_code":"PPL",
    "gn:name":"Tuhfapur",
    "gn:population":0,
    "gn:timezone":"Asia/Kolkata",
    "iso:country":"IN",
    "ks:ks_name":"Tohfapur",
    "ks:ks_pop":567,
    "ks:ks_type":"VILLAGE",
    "ks:ks_uagg_main":0,
    "name:eng_x_preferred":[
        "Tohfapur"
    ],
    "wof:name":"Tohfapur",
    "wof:placetype":"neighbourhood",
    "wof:population":567
},
  "geometry": {"coordinates":[83.188219,26.164537],"type":"Point"}
}