{
  "type": "Feature",
  "properties": {
    "gn:admin1_code":"40.0",
    "gn:admin2_code":"537",
    "gn:asciiname":"Potaram",
    "gn:country_code":"IN",
    "gn:dem":608,
    "gn:feature_class":"P",
    "gn:feature_code":"PPL",
    "gn:name":"Pot\u0101ram",
    "gn:population":0,
    "gn:timezone":"Asia/Kolkata",
    "iso:country":"IN",
    "wof:name":"Potaram",
    "wof:placetype":"neighbourhood"
},
  "geometry": {"coordinates":[78.37278999999999,17.60321],"type":"Point"}
}