{
  "type": "Feature",
  "properties": {
    "iso:country":"IN",
    "ks:ks_name":"Vadipura",
    "ks:ks_pop":320,
    "ks:ks_type":"HABITATION",
    "name:eng_x_preferred":[
        "Vadipura"
    ],
    "wof:name":"Vadipura",
    "wof:placetype":"locality",
    "wof:population":320
},
  "geometry": {"coordinates":[71.618888,24.242909],"type":"Point"}
}