{
  "type": "Feature",
  "properties": {
    "gn:admin1_code":"38.0",
    "gn:admin2_code":"348.0",
    "gn:asciiname":"Amjhar",
    "gn:country_code":"IN",
    "gn:dem":398,
    "gn:feature_class":"P",
    "gn:feature_code":"PPL",
    "gn:name":"\u0100mjhar",
    "gn:population":0,
    "gn:timezone":"Asia/Kolkata",
    "iso:country":"IN",
    "wof:name":"Amjhar",
    "wof:placetype":"locality"
},
  "geometry": {"coordinates":[85.32980999999999,24.40838],"type":"Point"}
}