{
  "type": "Feature",
  "properties": {
    "iso:country":"IN",
    "ks:ks_name":"Tendudihipara",
    "ks:ks_pop":387,
    "ks:ks_type":"HABITATION",
    "name:eng_x_preferred":[
        "Tendudihipara"
    ],
    "wof:name":"Tendudihipara",
    "wof:placetype":"locality",
    "wof:population":387
},
  "geometry": {"coordinates":[81.87959499999999,19.856404],"type":"Point"}
}