{
  "type": "Feature",
  "properties": {
    "iso:country":"IN",
    "ks:ks_name":"Belouran Purwa",
    "ks:ks_pop":240,
    "ks:ks_type":"HABITATION",
    "name:eng_x_preferred":[
        "Belouran Purwa"
    ],
    "wof:name":"Belouran Purwa",
    "wof:placetype":"locality",
    "wof:population":240
},
  "geometry": {"coordinates":[81.91736,27.089879],"type":"Point"}
}