{
  "type": "Feature",
  "properties": {
    "iso:country":"IN",
    "ks:ks_name":"Gopakeli",
    "ks:ks_pop":75,
    "ks:ks_type":"VILLAGE",
    "name:eng_x_preferred":[
        "Gopakeli"
    ],
    "wof:name":"Gopakeli",
    "wof:placetype":"locality",
    "wof:population":75
},
  "geometry": {"coordinates":[84.528402,18.994563],"type":"Point"}
}