{
  "type": "Feature",
  "properties": {
    "iso:country":"IN",
    "ks:ks_name":"Madhopura",
    "ks:ks_pop":35,
    "ks:ks_type":"VILLAGE",
    "name:eng_x_preferred":[
        "Madhopura"
    ],
    "wof:name":"Madhopura",
    "wof:placetype":"locality",
    "wof:population":35
},
  "geometry": {"coordinates":[74.84279600000001,23.447282],"type":"Point"}
}