{
  "type": "Feature",
  "properties": {
    "iso:country":"IN",
    "ks:ks_name":"Khilawasti",
    "ks:ks_pop":142,
    "ks:ks_type":"HABITATION",
    "name:eng_x_preferred":[
        "Khilawasti"
    ],
    "wof:name":"Khilawasti",
    "wof:placetype":"locality",
    "wof:population":142
},
  "geometry": {"coordinates":[75.28382000000001,19.196177],"type":"Point"}
}