{
  "type": "Feature",
  "properties": {
    "gn:admin1_code":"34.0",
    "gn:admin2_code":"204.0",
    "gn:asciiname":"Chitaha",
    "gn:country_code":"IN",
    "gn:dem":73,
    "gn:feature_class":"P",
    "gn:feature_code":"PPL",
    "gn:name":"Chitaha",
    "gn:population":0,
    "gn:timezone":"Asia/Kolkata",
    "iso:country":"IN",
    "ks:ks_name":"Chitaha",
    "ks:ks_pop":2370,
    "ks:ks_type":"VILLAGE",
    "ks:ks_uagg_main":0,
    "name:eng_x_preferred":[
        "Chitaha"
    ],
    "wof:name":"Chitaha",
    "wof:placetype":"neighbourhood",
    "wof:population":2370
},
  "geometry": {"coordinates":[84.85575799999999,26.79993],"type":"Point"}
}