{
  "type": "Feature",
  "properties": {
    "iso:country":"IN",
    "ks:ks_alt_nam":"12 STB",
    "ks:ks_name":"12 Stb",
    "ks:ks_pop":41,
    "ks:ks_type":"HABITATION",
    "name:eng_x_preferred":[
        "12 Stb"
    ],
    "wof:name":"12 Stb",
    "wof:placetype":"locality",
    "wof:population":41
},
  "geometry": {"coordinates":[73.919816,29.43413],"type":"Point"}
}