{
  "type": "Feature",
  "properties": {
    "iso:country":"IN",
    "ks:ks_alt_nam":"new basti h3",
    "ks:ks_name":"New Basti H3",
    "ks:ks_pop":423,
    "ks:ks_type":"HABITATION",
    "name:eng_x_preferred":[
        "New Basti H3"
    ],
    "wof:name":"New Basti H3",
    "wof:placetype":"locality",
    "wof:population":423
},
  "geometry": {"coordinates":[83.192837,25.253866],"type":"Point"}
}