{
  "type": "Feature",
  "properties": {
    "gn:admin1_code":"24.0",
    "gn:admin2_code":"103",
    "gn:asciiname":"Mila ki Dhani",
    "gn:country_code":"IN",
    "gn:dem":360,
    "gn:feature_class":"P",
    "gn:feature_code":"PPL",
    "gn:name":"Mila ki Dh\u0101ni",
    "gn:population":0,
    "gn:timezone":"Asia/Kolkata",
    "iso:country":"IN",
    "name:und_x_variant":[
        "Mila ki Dh\u0101ni",
        "L\u012blon ki Dh\u0101ni"
    ],
    "wof:name":"Mila ki Dhani",
    "wof:placetype":"locality"
},
  "geometry": {"coordinates":[75.61816999999998,28.07037],"type":"Point"}
}