{
  "type": "Feature",
  "properties": {
    "gn:admin1_code":"12.0",
    "gn:admin2_code":"16.0",
    "gn:asciiname":"Jang",
    "gn:country_code":"IN",
    "gn:dem":1946,
    "gn:feature_class":"P",
    "gn:feature_code":"PPL",
    "gn:name":"Jang",
    "gn:population":0,
    "gn:timezone":"Asia/Kolkata",
    "iso:country":"IN",
    "name:bul_x_preferred":[
        "\u0427\u0430\u043d"
    ],
    "name:ceb_x_preferred":[
        "Jang"
    ],
    "name:ces_x_preferred":[
        "Jang"
    ],
    "name:deu_x_preferred":[
        "Jang"
    ],
    "name:fin_x_preferred":[
        "Jang"
    ],
    "name:rus_x_preferred":[
        "\u0427\u0430\u043d"
    ],
    "name:swe_x_preferred":[
        "Jang"
    ],
    "name:ukr_x_preferred":[
        "\u0427\u0430\u043d"
    ],
    "wof:name":"Jang",
    "wof:placetype":"locality"
},
  "geometry": {"coordinates":[75.94351999999998,33.04625],"type":"Point"}
}