{
  "type": "Feature",
  "properties": {
    "iso:country":"IN",
    "ks:ks_name":"Ragnagiri",
    "ks:ks_pop":1352,
    "ks:ks_type":"HABITATION",
    "name:eng_x_preferred":[
        "Ragnagiri"
    ],
    "wof:name":"Ragnagiri",
    "wof:placetype":"locality",
    "wof:population":1352
},
  "geometry": {"coordinates":[75.571344,12.126041],"type":"Point"}
}