{
  "type": "Feature",
  "properties": {
    "iso:country":"IN",
    "ks:ks_name":"Ahire Bk.",
    "ks:ks_pop":433,
    "ks:ks_type":"VILLAGE",
    "ks:ks_uagg_main":0,
    "name:eng_x_preferred":[
        "Ahire Bk."
    ],
    "wof:name":"Ahire Bk.",
    "wof:placetype":"neighbourhood",
    "wof:population":433
},
  "geometry": {"coordinates":[75.322822,21.095227],"type":"Point"}
}