{
  "type": "Feature",
  "properties": {
    "iso:country":"IN",
    "ks:ks_name":"Hanif Sagar",
    "ks:ks_pop":635,
    "ks:ks_type":"VILLAGE",
    "name:eng_x_preferred":[
        "Hanif Sagar"
    ],
    "wof:name":"Hanif Sagar",
    "wof:placetype":"locality",
    "wof:population":635
},
  "geometry": {"coordinates":[72.263186,26.246922],"type":"Point"}
}