{
  "type": "Feature",
  "properties": {
    "iso:country":"IN",
    "ks:ks_name":"Das Para",
    "ks:ks_pop":1017,
    "ks:ks_type":"HABITATION",
    "name:eng_x_preferred":[
        "Das Para"
    ],
    "wof:name":"Das Para",
    "wof:placetype":"locality",
    "wof:population":1017
},
  "geometry": {"coordinates":[89.055201,26.624432],"type":"Point"}
}