{
  "type": "Feature",
  "properties": {
    "gn:admin1_code":"35.0",
    "gn:admin2_code":"445.0",
    "gn:asciiname":"Raghunathpura",
    "gn:country_code":"IN",
    "gn:dem":538,
    "gn:feature_class":"P",
    "gn:feature_code":"PPL",
    "gn:name":"Raghun\u0101thpura",
    "gn:population":0,
    "gn:timezone":"Asia/Kolkata",
    "iso:country":"IN",
    "name:hin_x_preferred":[
        "\u0930\u0918\u0941\u0928\u093e\u0925\u092a\u0941\u0930\u093e"
    ],
    "name:pan_x_preferred":[
        "\u0a30\u0a18\u0a41\u0a28\u0a3e\u0a25\u0a2a\u0a41\u0a30\u0a3e"
    ],
    "wof:name":"Raghunathpura",
    "wof:placetype":"locality"
},
  "geometry": {"coordinates":[76.93456999999999,22.89277],"type":"Point"}
}