{
  "type": "Feature",
  "properties": {
    "iso:country":"IN",
    "ks:ks_name":"Rajabandh",
    "ks:ks_pop":255,
    "ks:ks_type":"HABITATION",
    "name:eng_x_preferred":[
        "Rajabandh"
    ],
    "wof:name":"Rajabandh",
    "wof:placetype":"locality",
    "wof:population":255
},
  "geometry": {"coordinates":[85.633177,23.428654],"type":"Point"}
}