{
  "type": "Feature",
  "properties": {
    "iso:country":"IN",
    "ks:ks_alt_nam":"M\u0101dhopur",
    "ks:ks_name":"Madhopur",
    "ks:ks_type":"VILLAGE",
    "name:eng_x_preferred":[
        "Madhopur"
    ],
    "name:eng_x_variant":[
        "M\u0101dhopur"
    ],
    "wof:name":"Madhopur",
    "wof:placetype":"locality"
},
  "geometry": {"coordinates":[83.796486,25.894876],"type":"Point"}
}