{
  "type": "Feature",
  "properties": {
    "iso:country":"IN",
    "ks:ks_alt_nam":"Dundu\u0101",
    "ks:ks_name":"Dundua",
    "ks:ks_pop":1686,
    "ks:ks_type":"VILLAGE",
    "name:eng_x_preferred":[
        "Dundua"
    ],
    "name:eng_x_variant":[
        "Dundu\u0101"
    ],
    "wof:name":"Dundua",
    "wof:placetype":"locality",
    "wof:population":1686
},
  "geometry": {"coordinates":[85.3794,23.668103],"type":"Point"}
}