{
  "type": "Feature",
  "properties": {
    "iso:country":"IN",
    "ks:ks_name":"Mishri Chak",
    "ks:ks_pop":192,
    "ks:ks_type":"VILLAGE",
    "name:eng_x_preferred":[
        "Mishri Chak"
    ],
    "wof:name":"Mishri Chak",
    "wof:placetype":"locality",
    "wof:population":192
},
  "geometry": {"coordinates":[87.513426,22.495136],"type":"Point"}
}