{
  "type": "Feature",
  "properties": {
    "gn:admin1_code":"36.0",
    "gn:admin2_code":"141.0",
    "gn:asciiname":"Gopalpur",
    "gn:country_code":"IN",
    "gn:dem":207,
    "gn:feature_class":"P",
    "gn:feature_code":"PPL",
    "gn:name":"Gop\u0101lpur",
    "gn:population":0,
    "gn:timezone":"Asia/Kolkata",
    "iso:country":"IN",
    "name:ben_x_preferred":[
        "\u0997\u09cb\u09aa\u09be\u09b2\u09aa\u09c1\u09b0"
    ],
    "name:ceb_x_preferred":[
        "Gopalpur"
    ],
    "name:deu_x_preferred":[
        "Gopalpur"
    ],
    "name:fra_x_preferred":[
        "Gopalpur"
    ],
    "name:ita_x_preferred":[
        "Gopalpur"
    ],
    "name:nld_x_preferred":[
        "Gopalpur"
    ],
    "name:rus_x_preferred":[
        "\u0413\u043e\u043f\u0430\u043b\u043f\u0443\u0440"
    ],
    "name:swe_x_preferred":[
        "Gopalpur"
    ],
    "name:tel_x_preferred":[
        "\u0c17\u0c4b\u0c2a\u0c3e\u0c32\u0c2a\u0c41\u0c30\u0c02"
    ],
    "wof:name":"Gopalpur",
    "wof:placetype":"locality"
},
  "geometry": {"coordinates":[77.65514,28.49002],"type":"Point"}
}