{
  "type": "Feature",
  "properties": {
    "gn:admin1_code":"39.0",
    "gn:admin2_code":"060",
    "gn:asciiname":"Samet",
    "gn:country_code":"IN",
    "gn:dem":1028,
    "gn:feature_class":"P",
    "gn:feature_code":"PPL",
    "gn:name":"Samet",
    "gn:population":0,
    "gn:timezone":"Asia/Kolkata",
    "iso:country":"IN",
    "name:deu_x_preferred":[
        "Samet"
    ],
    "name:heb_x_preferred":[
        "\u05e1\u05de\u05d8"
    ],
    "wof:name":"Samet",
    "wof:placetype":"locality"
},
  "geometry": {"coordinates":[77.90361,30.49428],"type":"Point"}
}