{
  "type": "Feature",
  "properties": {
    "gn:admin1_code":"19.0",
    "gn:admin2_code":"571.0",
    "gn:asciiname":"Patnaikanhalli",
    "gn:country_code":"IN",
    "gn:dem":654,
    "gn:feature_class":"P",
    "gn:feature_code":"PPL",
    "gn:name":"Patn\u0101ikanhalli",
    "gn:population":0,
    "gn:timezone":"Asia/Kolkata",
    "iso:country":"IN",
    "wof:name":"Patnaikanhalli",
    "wof:placetype":"locality"
},
  "geometry": {"coordinates":[76.92238,13.88669],"type":"Point"}
}