{
  "type": "Feature",
  "properties": {
    "gn:admin1_code":"19.0",
    "gn:admin2_code":"571.0",
    "gn:asciiname":"Marbahalli",
    "gn:country_code":"IN",
    "gn:dem":773,
    "gn:feature_class":"P",
    "gn:feature_code":"PPL",
    "gn:name":"Marbahalli",
    "gn:population":0,
    "gn:timezone":"Asia/Kolkata",
    "iso:country":"IN",
    "wof:name":"Marbahalli",
    "wof:placetype":"locality"
},
  "geometry": {"coordinates":[77.26141,13.62741],"type":"Point"}
}