{
  "type": "Feature",
  "properties": {
    "iso:country":"IN",
    "ks:ks_alt_nam":"MARAN DEBNATH PARA",
    "ks:ks_name":"Maran Debnath Para",
    "ks:ks_pop":227,
    "ks:ks_type":"HABITATION",
    "name:eng_x_preferred":[
        "Maran Debnath Para"
    ],
    "wof:name":"Maran Debnath Para",
    "wof:placetype":"locality",
    "wof:population":227
},
  "geometry": {"coordinates":[91.359095,23.551457],"type":"Point"}
}