{
  "type": "Feature",
  "properties": {
    "iso:country":"IN",
    "ks:ks_name":"Bhapuabasti",
    "ks:ks_pop":636,
    "ks:ks_type":"HABITATION",
    "ks:ks_uagg_main":0,
    "name:eng_x_preferred":[
        "Bhapuabasti"
    ],
    "wof:name":"Bhapuabasti",
    "wof:placetype":"neighbourhood",
    "wof:population":636
},
  "geometry": {"coordinates":[88.069721,26.226634],"type":"Point"}
}