{
  "type": "Feature",
  "properties": {
    "iso:country":"IN",
    "ks:ks_name":"Borjari Gaon",
    "ks:ks_pop":581,
    "ks:ks_type":"VILLAGE",
    "ks:ks_uagg_main":0,
    "name:eng_x_preferred":[
        "Borjari Gaon"
    ],
    "wof:name":"Borjari Gaon",
    "wof:placetype":"neighbourhood",
    "wof:population":581
},
  "geometry": {"coordinates":[92.751919,26.113901],"type":"Point"}
}