{
  "type": "Feature",
  "properties": {
    "gn:admin1_code":"35",
    "gn:admin2_code":"440.0",
    "gn:asciiname":"Ichchhapur",
    "gn:country_code":"IN",
    "gn:dem":321,
    "gn:feature_class":"P",
    "gn:feature_code":"PPL",
    "gn:name":"Ichchh\u0101pur",
    "gn:population":0,
    "gn:timezone":"Asia/Kolkata",
    "iso:country":"IN",
    "wof:name":"Ichchhapur",
    "wof:placetype":"locality"
},
  "geometry": {"coordinates":[76.03914,21.80121],"type":"Point"}
}