{
  "type": "Feature",
  "properties": {
    "gn:country":"IN",
    "gn:fcode":"PPL",
    "gn:population":17696,
    "iso:country":"IN",
    "qs:name":"Moram",
    "qs:photos_9r":0,
    "qs:photos_sr":0,
    "qs:pop_sr":"6",
    "wof:name":"Moram",
    "wof:placetype":"locality",
    "wof:population":17696
},
  "geometry": {"coordinates":[76.4706,17.78744],"type":"Point"}
}