{
  "type": "Feature",
  "properties": {
    "gn:admin1_code":"23.0",
    "gn:admin2_code":"46.0",
    "gn:asciiname":"Mansa Kalan",
    "gn:country_code":"IN",
    "gn:dem":212,
    "gn:feature_class":"P",
    "gn:feature_code":"PPL",
    "gn:name":"M\u0101nsa Kal\u0101n",
    "gn:population":0,
    "gn:timezone":"Asia/Kolkata",
    "iso:country":"IN",
    "wof:name":"Mansa Kalan",
    "wof:placetype":"locality"
},
  "geometry": {"coordinates":[75.17249,30.03859000000001],"type":"Point"}
}