{
  "type": "Feature",
  "properties": {
    "iso:country":"IN",
    "ks:ks_name":"Melatheru",
    "ks:ks_pop":140,
    "ks:ks_type":"HABITATION",
    "ks:ks_uagg_main":0,
    "name:eng_x_preferred":[
        "Melatheru"
    ],
    "wof:name":"Melatheru",
    "wof:placetype":"neighbourhood",
    "wof:population":140
},
  "geometry": {"coordinates":[78.715772,10.325167],"type":"Point"}
}