{
  "type": "Feature",
  "properties": {
    "iso:country":"IN",
    "ks:ks_name":"Chhapra Urf Chaku Chhapra",
    "ks:ks_pop":1118,
    "ks:ks_type":"VILLAGE",
    "name:eng_x_preferred":[
        "Chhapra Urf Chaku Chhapra"
    ],
    "wof:name":"Chhapra Urf Chaku Chhapra",
    "wof:placetype":"locality",
    "wof:population":1118
},
  "geometry": {"coordinates":[85.20515,26.070344],"type":"Point"}
}