{
  "type": "Feature",
  "properties": {
    "iso:country":"IN",
    "ks:ks_alt_nam":"K.Beddaguda",
    "ks:ks_name":"K.beddaguda",
    "ks:ks_pop":93,
    "ks:ks_type":"HABITATION",
    "name:eng_x_preferred":[
        "K.beddaguda"
    ],
    "wof:name":"K.beddaguda",
    "wof:placetype":"locality",
    "wof:population":93
},
  "geometry": {"coordinates":[82.86293999999999,18.211395],"type":"Point"}
}