{
  "type": "Feature",
  "properties": {
    "iso:country":"IN",
    "ks:ks_name":"Korlapal",
    "ks:ks_pop":114,
    "ks:ks_type":"VILLAGE",
    "name:eng_x_preferred":[
        "Korlapal"
    ],
    "wof:name":"Korlapal",
    "wof:placetype":"locality",
    "wof:population":114
},
  "geometry": {"coordinates":[81.331052,19.068864],"type":"Point"}
}