{
  "type": "Feature",
  "properties": {
    "iso:country":"IN",
    "ks:ks_name":"Saithua Khas",
    "ks:ks_pop":486,
    "ks:ks_type":"HABITATION",
    "name:eng_x_preferred":[
        "Saithua Khas"
    ],
    "wof:name":"Saithua Khas",
    "wof:placetype":"locality",
    "wof:population":486
},
  "geometry": {"coordinates":[83.07659700000001,26.356443],"type":"Point"}
}