{
  "type": "Feature",
  "properties": {
    "iso:country":"IN",
    "ks:ks_name":"Sailendranarayanpur",
    "ks:ks_pop":613,
    "ks:ks_type":"VILLAGE",
    "name:eng_x_preferred":[
        "Sailendranarayanpur"
    ],
    "wof:name":"Sailendranarayanpur",
    "wof:placetype":"locality",
    "wof:population":613
},
  "geometry": {"coordinates":[86.87543700000001,20.696574],"type":"Point"}
}