{
  "type": "Feature",
  "properties": {
    "gn:admin1_code":"40.0",
    "gn:admin2_code":"533.0",
    "gn:asciiname":"Talrabalagu",
    "gn:country_code":"IN",
    "gn:dem":496,
    "gn:feature_class":"P",
    "gn:feature_code":"PPL",
    "gn:name":"T\u0101lrabalagu",
    "gn:population":0,
    "gn:timezone":"Asia/Kolkata",
    "iso:country":"IN",
    "wof:name":"Talrabalagu",
    "wof:placetype":"locality"
},
  "geometry": {"coordinates":[78.52353000000002,18.54875],"type":"Point"}
}