{
  "type": "Feature",
  "properties": {
    "gn:admin1_code":"25.0",
    "gn:admin2_code":"611.0",
    "gn:asciiname":"Arakadavu",
    "gn:country_code":"IN",
    "gn:dem":916,
    "gn:feature_class":"P",
    "gn:feature_code":"PPL",
    "gn:name":"Arakadavu",
    "gn:population":0,
    "gn:timezone":"Asia/Kolkata",
    "iso:country":"IN",
    "wof:name":"Arakadavu",
    "wof:placetype":"locality"
},
  "geometry": {"coordinates":[76.49101999999998,11.54066],"type":"Point"}
}