{
  "type": "Feature",
  "properties": {
    "iso:country":"IN",
    "ks:ks_name":"Thiyyamamidi",
    "ks:ks_pop":126,
    "ks:ks_type":"VILLAGE",
    "name:eng_x_preferred":[
        "Thiyyamamidi"
    ],
    "wof:name":"Thiyyamamidi",
    "wof:placetype":"locality",
    "wof:population":126
},
  "geometry": {"coordinates":[82.65121000000001,17.951424],"type":"Point"}
}