{
  "type": "Feature",
  "properties": {
    "iso:country":"IN",
    "ks:ks_alt_nam":"RUPNER WASTI",
    "ks:ks_name":"Rupner Wasti",
    "ks:ks_pop":194,
    "ks:ks_type":"HABITATION",
    "name:eng_x_preferred":[
        "Rupner Wasti"
    ],
    "wof:name":"Rupner Wasti",
    "wof:placetype":"locality",
    "wof:population":194
},
  "geometry": {"coordinates":[75.02237,18.470295],"type":"Point"}
}