{
  "type": "Feature",
  "properties": {
    "iso:country":"IN",
    "ks:ks_name":"Edakuni",
    "ks:ks_pop":379,
    "ks:ks_type":"HABITATION",
    "name:eng_x_preferred":[
        "Edakuni"
    ],
    "wof:name":"Edakuni",
    "wof:placetype":"locality",
    "wof:population":379
},
  "geometry": {"coordinates":[76.051447,11.640278],"type":"Point"}
}