{
  "type": "Feature",
  "properties": {
    "gn:admin1_code":"35",
    "gn:admin2_code":"426.0",
    "gn:asciiname":"Golab ki Purwa",
    "gn:country_code":"IN",
    "gn:dem":176,
    "gn:feature_class":"P",
    "gn:feature_code":"PPL",
    "gn:name":"Golab ki Purwa",
    "gn:population":0,
    "gn:timezone":"Asia/Kolkata",
    "iso:country":"IN",
    "wof:name":"Golab ki Purwa",
    "wof:placetype":"locality"
},
  "geometry": {"coordinates":[80.33972,24.98786],"type":"Point"}
}