{
  "type": "Feature",
  "properties": {
    "iso:country":"IN",
    "ks:ks_name":"Kootelu",
    "ks:ks_pop":259,
    "ks:ks_type":"HABITATION",
    "name:eng_x_preferred":[
        "Kootelu"
    ],
    "wof:name":"Kootelu",
    "wof:placetype":"locality",
    "wof:population":259
},
  "geometry": {"coordinates":[75.21556200000001,12.654705],"type":"Point"}
}