{
  "type": "Feature",
  "properties": {
    "iso:country":"IN",
    "ks:ks_name":"Rampalu",
    "ks:ks_pop":74,
    "ks:ks_type":"HABITATION",
    "name:eng_x_preferred":[
        "Rampalu"
    ],
    "wof:name":"Rampalu",
    "wof:placetype":"locality",
    "wof:population":74
},
  "geometry": {"coordinates":[75.401709,13.415518],"type":"Point"}
}