{
  "type": "Feature",
  "properties": {
    "iso:country":"IN",
    "ks:ks_name":"Nakot Malla",
    "ks:ks_pop":221,
    "ks:ks_type":"VILLAGE",
    "name:eng_x_preferred":[
        "Nakot Malla"
    ],
    "wof:name":"Nakot Malla",
    "wof:placetype":"locality",
    "wof:population":221
},
  "geometry": {"coordinates":[79.246431,30.256356],"type":"Point"}
}