{
  "type": "Feature",
  "properties": {
    "iso:country":"IN",
    "ks:ks_name":"Nuaguda3",
    "ks:ks_pop":249,
    "ks:ks_type":"HABITATION",
    "name:eng_x_preferred":[
        "Nuaguda3"
    ],
    "wof:name":"Nuaguda3",
    "wof:placetype":"locality",
    "wof:population":249
},
  "geometry": {"coordinates":[82.49888,19.256513],"type":"Point"}
}