{
  "type": "Feature",
  "properties": {
    "iso:country":"IN",
    "ks:ks_name":"Masanijhola",
    "ks:ks_pop":29,
    "ks:ks_type":"VILLAGE",
    "name:eng_x_preferred":[
        "Masanijhola"
    ],
    "wof:name":"Masanijhola",
    "wof:placetype":"locality",
    "wof:population":29
},
  "geometry": {"coordinates":[85.13047400000001,19.977361],"type":"Point"}
}