{
  "type": "Feature",
  "properties": {
    "iso:country":"IN",
    "ks:ks_name":"Padiaberena",
    "ks:ks_pop":321,
    "ks:ks_type":"VILLAGE",
    "name:eng_x_preferred":[
        "Padiaberena"
    ],
    "wof:name":"Padiaberena",
    "wof:placetype":"locality",
    "wof:population":321
},
  "geometry": {"coordinates":[84.207123,20.428483],"type":"Point"}
}