{
  "type": "Feature",
  "properties": {
    "gn:admin1_code":"36",
    "gn:admin2_code":"174.0",
    "gn:asciiname":"Jamal Mau",
    "gn:country_code":"IN",
    "gn:dem":107,
    "gn:feature_class":"P",
    "gn:feature_code":"PPL",
    "gn:name":"Jam\u0101l Mau",
    "gn:population":0,
    "gn:timezone":"Asia/Kolkata",
    "iso:country":"IN",
    "ks:ks_alt_nam":"Jam\u0101l Mau",
    "ks:ks_name":"Jamal Mau",
    "ks:ks_pop":1433,
    "ks:ks_type":"VILLAGE",
    "ks:ks_uagg_main":0,
    "name:eng_x_preferred":[
        "Jamal Mau"
    ],
    "name:eng_x_variant":[
        "Jam\u0101l Mau"
    ],
    "wof:name":"Jamal Mau",
    "wof:placetype":"neighbourhood",
    "wof:population":1433
},
  "geometry": {"coordinates":[81.48106199999999,25.586952],"type":"Point"}
}