{
  "type": "Feature",
  "properties": {
    "iso:country":"IN",
    "ks:ks_name":"Pannimoottil",
    "ks:ks_pop":275,
    "ks:ks_type":"HABITATION",
    "name:eng_x_preferred":[
        "Pannimoottil"
    ],
    "wof:name":"Pannimoottil",
    "wof:placetype":"locality",
    "wof:population":275
},
  "geometry": {"coordinates":[76.826064,9.104154],"type":"Point"}
}