{
  "type": "Feature",
  "properties": {
    "gn:admin1_code":"11.0",
    "gn:admin2_code":"26.0",
    "gn:asciiname":"Gundi",
    "gn:country_code":"IN",
    "gn:dem":2005,
    "gn:feature_class":"P",
    "gn:feature_code":"PPL",
    "gn:name":"Gundi",
    "gn:population":0,
    "gn:timezone":"Asia/Kolkata",
    "iso:country":"IN",
    "name:ara_x_preferred":[
        "\u0642\u0646\u062f\u064a\u0629"
    ],
    "name:bre_x_preferred":[
        "Goundi"
    ],
    "name:bul_x_preferred":[
        "\u0413\u0440\u0435\u0431\u0435\u043d\u043e\u043f\u0440\u044a\u0441\u0442\u0438"
    ],
    "name:cat_x_preferred":[
        "Ctenodact\u00edlids"
    ],
    "name:ceb_x_preferred":[
        "Ctenodactylidae"
    ],
    "name:ces_x_preferred":[
        "Gundiovit\u00ed"
    ],
    "name:deu_x_preferred":[
        "Kammfinger"
    ],
    "name:fas_x_preferred":[
        "\u0645\u0648\u0634 \u0634\u0627\u0646\u0647"
    ],
    "name:fra_x_preferred":[
        "Ctenodactylidae"
    ],
    "name:heb_x_preferred":[
        "\u05d2\u05d5\u05e0\u05d3\u05d9\u05d9\u05dd"
    ],
    "name:hun_x_preferred":[
        "Gundif\u00e9l\u00e9k"
    ],
    "name:ita_x_preferred":[
        "Ctenodactylidae"
    ],
    "name:jpn_x_preferred":[
        "\u30b0\u30f3\u30c7\u30a3\u79d1"
    ],
    "name:kab_x_preferred":[
        "Tilut"
    ],
    "name:kir_x_preferred":[
        "\u0422\u0430\u0440\u0430\u043a\u043a\u043e\u043b\u0434\u043e\u0440"
    ],
    "name:kor_x_preferred":[
        "\uad70\ub514\ub958"
    ],
    "name:lit_x_preferred":[
        "Gundiniai"
    ],
    "name:ltz_x_preferred":[
        "Gundien"
    ],
    "name:nav_x_preferred":[
        "K\u00e9zhoozh\u02bcil\u00ed"
    ],
    "name:nld_x_preferred":[
        "Goendi's"
    ],
    "name:nor_x_preferred":[
        "Kamfingerrotter"
    ],
    "name:pol_x_preferred":[
        "Gundiowate"
    ],
    "name:por_x_preferred":[
        "Ctenodactylidae"
    ],
    "name:rus_x_preferred":[
        "\u0413\u0440\u0435\u0431\u043d\u0435\u043f\u0430\u043b\u044b\u0435"
    ],
    "name:spa_x_preferred":[
        "Ctenodactylidae"
    ],
    "name:swa_x_preferred":[
        "Gundi"
    ],
    "name:swe_x_preferred":[
        "Kamfingerr\u00e5ttor"
    ],
    "name:ukr_x_preferred":[
        "\u0413\u0443\u043d\u0434\u0456\u0454\u0432\u0456"
    ],
    "name:vie_x_preferred":[
        "Ctenodactylidae"
    ],
    "name:war_x_preferred":[
        "Ctenodactylidae"
    ],
    "name:zho_x_preferred":[
        "\u68b3\u9f7f\u9f20\u79d1"
    ],
    "wof:name":"Gundi",
    "wof:placetype":"locality"
},
  "geometry": {"coordinates":[77.63221999999998,31.47828],"type":"Point"}
}