{
  "type": "Feature",
  "properties": {
    "iso:country":"IN",
    "ks:ks_name":"Duganga Bajar",
    "ks:ks_pop":377,
    "ks:ks_type":"HABITATION",
    "name:eng_x_preferred":[
        "Duganga Bajar"
    ],
    "wof:name":"Duganga Bajar",
    "wof:placetype":"locality",
    "wof:population":377
},
  "geometry": {"coordinates":[92.20976,24.277888],"type":"Point"}
}