{
  "type": "Feature",
  "properties": {
    "iso:country":"IN",
    "ks:ks_name":"Atkalewasti",
    "ks:ks_pop":995,
    "ks:ks_type":"HABITATION",
    "name:eng_x_preferred":[
        "Atkalewasti"
    ],
    "wof:name":"Atkalewasti",
    "wof:placetype":"locality",
    "wof:population":995
},
  "geometry": {"coordinates":[75.369017,17.678189],"type":"Point"}
}