{
  "type": "Feature",
  "properties": {
    "iso:country":"IN",
    "ks:ks_alt_nam":"S\u0101rugara",
    "ks:ks_name":"Sarugara",
    "ks:ks_pop":905,
    "ks:ks_type":"VILLAGE",
    "name:eng_x_preferred":[
        "Sarugara"
    ],
    "name:eng_x_variant":[
        "S\u0101rugara"
    ],
    "wof:name":"Sarugara",
    "wof:placetype":"locality",
    "wof:population":905
},
  "geometry": {"coordinates":[85.258291,22.58444],"type":"Point"}
}