{
  "type": "Feature",
  "properties": {
    "iso:country":"IN",
    "ks:ks_name":"Kalho",
    "ks:ks_pop":55,
    "ks:ks_type":"HABITATION",
    "name:eng_x_preferred":[
        "Kalho"
    ],
    "wof:name":"Kalho",
    "wof:placetype":"locality",
    "wof:population":55
},
  "geometry": {"coordinates":[86.719685,24.22272],"type":"Point"}
}