{
  "type": "Feature",
  "properties": {
    "gn:admin1_code":"12.0",
    "gn:admin2_code":"5.0",
    "gn:asciiname":"Jhaganwali",
    "gn:country_code":"IN",
    "gn:dem":2322,
    "gn:feature_class":"P",
    "gn:feature_code":"PPL",
    "gn:name":"Jh\u0101g\u0101nw\u0101li",
    "gn:population":0,
    "gn:timezone":"Asia/Kolkata",
    "iso:country":"IN",
    "wof:name":"Jhaganwali",
    "wof:placetype":"locality"
},
  "geometry": {"coordinates":[74.44866,33.64271],"type":"Point"}
}