{
  "type": "Feature",
  "properties": {
    "iso:country":"IN",
    "ks:ks_alt_nam":"V\u0101narkund",
    "ks:ks_name":"Vanarkund",
    "ks:ks_type":"VILLAGE",
    "name:eng_x_preferred":[
        "Vanarkund"
    ],
    "name:eng_x_variant":[
        "V\u0101narkund"
    ],
    "wof:name":"Vanarkund",
    "wof:placetype":"locality"
},
  "geometry": {"coordinates":[78.488281,20.958902],"type":"Point"}
}