{
  "type": "Feature",
  "properties": {
    "iso:country":"IN",
    "ks:ks_name":"Khumtai Gaon",
    "ks:ks_pop":1375,
    "ks:ks_type":"VILLAGE",
    "ks:ks_uagg_main":0,
    "name:eng_x_preferred":[
        "Khumtai Gaon"
    ],
    "wof:name":"Khumtai Gaon",
    "wof:placetype":"locality",
    "wof:population":1375
},
  "geometry": {"coordinates":[94.930982,27.17251],"type":"Point"}
}