{
  "type": "Feature",
  "properties": {
    "gn:country":"IN",
    "gn:fcode":"PPL",
    "gn:population":0,
    "iso:country":"IN",
    "name:ara_x_preferred":[
        "\u0623\u0644\u064a\u0628\u0648\u0631"
    ],
    "name:ben_bn_x_preferred":[
        "\u0986\u09b2\u09bf\u09aa\u09c1\u09b0"
    ],
    "name:ben_in_x_preferred":[
        "\u0986\u09b2\u09bf\u09aa\u09c1\u09b0"
    ],
    "name:cat_x_preferred":[
        "Alipur"
    ],
    "name:ceb_x_preferred":[
        "Alipur"
    ],
    "name:guj_x_preferred":[
        "\u0a85\u0ab2\u0abf\u0aaa\u0ac1\u0ab0"
    ],
    "name:hin_x_preferred":[
        "\u0905\u0932\u0940\u092a\u0941\u0930"
    ],
    "name:kan_x_preferred":[
        "\u0c85\u0cb2\u0cbf\u0caa\u0cc1\u0cb0"
    ],
    "name:mal_x_preferred":[
        "\u0d05\u0d32\u0d3f\u0d2a\u0d42\u0d7c"
    ],
    "name:mar_x_preferred":[
        "\u0905\u0932\u0940\u092a\u0942\u0930"
    ],
    "name:pan_x_preferred":[
        "\u0a05\u0a32\u0a40\u0a2a\u0a41\u0a30"
    ],
    "name:swe_x_preferred":[
        "Alipur"
    ],
    "name:tam_x_preferred":[
        "\u0b85\u0bb2\u0bbf\u0baa\u0bcd\u0baa\u0bc2\u0bb0\u0bcd"
    ],
    "name:tel_x_preferred":[
        "\u0c06\u0c32\u0c3f\u0c2a\u0c42\u0c30\u0c4d"
    ],
    "name:und_x_variant":[
        "Alipore"
    ],
    "name:urd_x_preferred":[
        "\u0639\u0644\u06cc \u067e\u0648\u0631"
    ],
    "qs:name":"Alipur",
    "qs:name_adm0":"India",
    "qs:name_adm1":"West Bengal",
    "qs:photos":310,
    "qs:photos_1k":63,
    "qs:photos_9k":1,
    "qs:photos_9r":5,
    "qs:photos_all":310,
    "qs:photos_sr":5,
    "qs:placetype":"Suburb",
    "qs:pop_sr":"0",
    "wd:wordcount":69,
    "wof:name":"Alipur",
    "wof:placetype":"neighbourhood",
    "wof:population":0
},
  "geometry": {"coordinates":[88.32317999999999,22.53195],"type":"Point"}
}