{
  "type": "Feature",
  "properties": {
    "gn:admin1_code":"11",
    "gn:asciiname":"Maora",
    "gn:country_code":"IN",
    "gn:dem":474,
    "gn:feature_class":"P",
    "gn:feature_code":"PPL",
    "gn:name":"M\u0101ora",
    "gn:population":0,
    "gn:timezone":"Asia/Kolkata",
    "iso:country":"IN",
    "ks:ks_name":"Maura",
    "ks:ks_pop":535,
    "ks:ks_type":"VILLAGE",
    "ks:ks_uagg_main":0,
    "name:eng_x_preferred":[
        "Maura"
    ],
    "wof:name":"Maura",
    "wof:placetype":"neighbourhood",
    "wof:population":535
},
  "geometry": {"coordinates":[76.63831,31.210186],"type":"Point"}
}