{
  "type": "Feature",
  "properties": {
    "iso:country":"IN",
    "ks:ks_name":"Kashi Ka Purwa",
    "ks:ks_pop":250,
    "ks:ks_type":"HABITATION",
    "name:eng_x_preferred":[
        "Kashi Ka Purwa"
    ],
    "wof:name":"Kashi Ka Purwa",
    "wof:placetype":"locality",
    "wof:population":250
},
  "geometry": {"coordinates":[81.518835,26.432035],"type":"Point"}
}