{
  "type": "Feature",
  "properties": {
    "iso:country":"IN",
    "ks:ks_name":"Rambagh",
    "ks:ks_pop":889,
    "ks:ks_type":"VILLAGE",
    "name:eng_x_preferred":[
        "Rambagh"
    ],
    "wof:name":"Rambagh",
    "wof:placetype":"locality",
    "wof:population":889
},
  "geometry": {"coordinates":[77.310681,27.452906],"type":"Point"}
}