{
  "type": "Feature",
  "properties": {
    "iso:country":"IN",
    "ks:ks_name":"Sauraguda",
    "ks:ks_pop":201,
    "ks:ks_type":"VILLAGE",
    "name:eng_x_preferred":[
        "Sauraguda"
    ],
    "wof:name":"Sauraguda",
    "wof:placetype":"locality",
    "wof:population":201
},
  "geometry": {"coordinates":[84.025831,18.815448],"type":"Point"}
}