{
  "type": "Feature",
  "properties": {
    "iso:country":"IN",
    "ks:ks_alt_nam":"CHAORA PARA",
    "ks:ks_name":"Chaora Para",
    "ks:ks_pop":625,
    "ks:ks_type":"HABITATION",
    "name:eng_x_preferred":[
        "Chaora Para"
    ],
    "wof:name":"Chaora Para",
    "wof:placetype":"locality",
    "wof:population":625
},
  "geometry": {"coordinates":[89.825931,26.476762],"type":"Point"}
}