{
  "type": "Feature",
  "properties": {
    "iso:country":"IN",
    "ks:ks_name":"Chak Chandinagar",
    "ks:ks_pop":1226,
    "ks:ks_type":"VILLAGE",
    "name:eng_x_preferred":[
        "Chak Chandinagar"
    ],
    "wof:name":"Chak Chandinagar",
    "wof:placetype":"locality",
    "wof:population":1226
},
  "geometry": {"coordinates":[88.123696,22.817705],"type":"Point"}
}