{
  "type": "Feature",
  "properties": {
    "iso:country":"IN",
    "ks:ks_name":"Kothur",
    "ks:ks_pop":266,
    "ks:ks_type":"VILLAGE",
    "name:eng_x_preferred":[
        "Kothur"
    ],
    "wof:name":"Kothur",
    "wof:placetype":"locality",
    "wof:population":266
},
  "geometry": {"coordinates":[78.35398000000001,13.047358],"type":"Point"}
}