{
  "type": "Feature",
  "properties": {
    "iso:country":"IN",
    "qs:name":"Amaravathi",
    "qs:name_adm0":"India",
    "qs:name_adm1":"Karnataka",
    "qs:photos":32,
    "qs:photos_1k":6,
    "qs:photos_9k":1,
    "qs:photos_9r":2,
    "qs:photos_all":32,
    "qs:photos_sr":2,
    "qs:placetype":"Town",
    "qs:pop_sr":"0",
    "wd:wordcount":217,
    "wof:name":"Amaravathi",
    "wof:placetype":"locality"
},
  "geometry": {"coordinates":[76.345968,15.277395],"type":"Point"}
}