{
  "type": "Feature",
  "properties": {
    "iso:country":"IN",
    "ks:ks_name":"5 STB-A",
    "ks:ks_pop":116,
    "ks:ks_type":"VILLAGE",
    "name:eng_x_preferred":[
        "5 STB-A"
    ],
    "wof:name":"5 STB-A",
    "wof:placetype":"locality",
    "wof:population":116
},
  "geometry": {"coordinates":[73.420125,29.32269],"type":"Point"}
}