{
  "type": "Feature",
  "properties": {
    "iso:country":"IN",
    "ks:ks_name":"Garmal",
    "ks:ks_pop":166,
    "ks:ks_type":"VILLAGE",
    "name:eng_x_preferred":[
        "Garmal"
    ],
    "wof:name":"Garmal",
    "wof:placetype":"locality",
    "wof:population":166
},
  "geometry": {"coordinates":[73.774244,20.721861],"type":"Point"}
}