{
  "type": "Feature",
  "properties": {
    "iso:country":"IN",
    "ks:ks_name":"Sutarwasti",
    "ks:ks_pop":171,
    "ks:ks_type":"HABITATION",
    "name:eng_x_preferred":[
        "Sutarwasti"
    ],
    "wof:name":"Sutarwasti",
    "wof:placetype":"locality",
    "wof:population":171
},
  "geometry": {"coordinates":[74.604652,17.554038],"type":"Point"}
}