{
  "type": "Feature",
  "properties": {
    "iso:country":"IN",
    "ks:ks_name":"Harladka Colony",
    "ks:ks_pop":24,
    "ks:ks_type":"HABITATION",
    "name:eng_x_preferred":[
        "Harladka Colony"
    ],
    "wof:name":"Harladka Colony",
    "wof:placetype":"locality",
    "wof:population":24
},
  "geometry": {"coordinates":[75.462217,12.476032],"type":"Point"}
}