{
  "type": "Feature",
  "properties": {
    "iso:country":"IN",
    "ks:ks_name":"Kalanda",
    "ks:ks_pop":549,
    "ks:ks_type":"VILLAGE",
    "ks:ks_uagg_main":0,
    "name:eng_x_preferred":[
        "Kalanda"
    ],
    "wof:name":"Kalanda",
    "wof:placetype":"neighbourhood",
    "wof:population":549
},
  "geometry": {"coordinates":[87.214465,21.631082],"type":"Point"}
}