{
  "type": "Feature",
  "properties": {
    "iso:country":"IN",
    "ks:ks_name":"Nayapara",
    "ks:ks_pop":418,
    "ks:ks_type":"HABITATION",
    "name:eng_x_preferred":[
        "Nayapara"
    ],
    "wof:name":"Nayapara",
    "wof:placetype":"locality",
    "wof:population":418
},
  "geometry": {"coordinates":[80.845446,18.897071],"type":"Point"}
}