{
  "type": "Feature",
  "properties": {
    "iso:country":"IN",
    "ks:ks_name":"Purey Bhatpurwa",
    "ks:ks_pop":253,
    "ks:ks_type":"HABITATION",
    "ks:ks_uagg_main":0,
    "name:eng_x_preferred":[
        "Purey Bhatpurwa"
    ],
    "wof:name":"Purey Bhatpurwa",
    "wof:placetype":"neighbourhood",
    "wof:population":253
},
  "geometry": {"coordinates":[82.52019900000001,27.07252],"type":"Point"}
}