{
  "type": "Feature",
  "properties": {
    "iso:country":"IN",
    "ks:ks_name":"Gowthampura",
    "ks:ks_pop":1842,
    "ks:ks_type":"VILLAGE",
    "name:eng_x_preferred":[
        "Gowthampura"
    ],
    "wof:name":"Gowthampura",
    "wof:placetype":"locality",
    "wof:population":1842
},
  "geometry": {"coordinates":[75.23302700000001,14.150539],"type":"Point"}
}