{
  "type": "Feature",
  "properties": {
    "gn:admin1_code":"35.0",
    "gn:admin2_code":"458.0",
    "gn:asciiname":"Rampuriya",
    "gn:country_code":"IN",
    "gn:dem":313,
    "gn:feature_class":"P",
    "gn:feature_code":"PPL",
    "gn:name":"R\u0101mpuriya",
    "gn:population":0,
    "gn:timezone":"Asia/Kolkata",
    "iso:country":"IN",
    "ks:ks_alt_nam":"R\u0101mpuriya",
    "ks:ks_name":"Rampuriya",
    "ks:ks_pop":334,
    "ks:ks_type":"VILLAGE",
    "name:eng_x_preferred":[
        "Rampuriya"
    ],
    "name:eng_x_variant":[
        "R\u0101mpuriya"
    ],
    "wof:name":"Rampuriya",
    "wof:placetype":"locality",
    "wof:population":334
},
  "geometry": {"coordinates":[76.81881,24.816778],"type":"Point"}
}