{
  "type": "Feature",
  "properties": {
    "iso:country":"IN",
    "ks:ks_alt_nam":"Jabar khand",
    "ks:ks_name":"Jabar Khand",
    "ks:ks_pop":242,
    "ks:ks_type":"HABITATION",
    "name:eng_x_preferred":[
        "Jabar Khand"
    ],
    "wof:name":"Jabar Khand",
    "wof:placetype":"locality",
    "wof:population":242
},
  "geometry": {"coordinates":[83.591803,23.686399],"type":"Point"}
}