{
  "type": "Feature",
  "properties": {
    "iso:country":"IN",
    "ks:ks_name":"Wagta Ki Beri",
    "ks:ks_pop":702,
    "ks:ks_type":"VILLAGE",
    "name:eng_x_preferred":[
        "Wagta Ki Beri"
    ],
    "wof:name":"Wagta Ki Beri",
    "wof:placetype":"locality",
    "wof:population":702
},
  "geometry": {"coordinates":[71.00176999999999,25.733666],"type":"Point"}
}