{
  "type": "Feature",
  "properties": {
    "iso:country":"IN",
    "ks:ks_name":"Batrupara",
    "ks:ks_pop":82,
    "ks:ks_type":"HABITATION",
    "name:eng_x_preferred":[
        "Batrupara"
    ],
    "wof:name":"Batrupara",
    "wof:placetype":"locality",
    "wof:population":82
},
  "geometry": {"coordinates":[81.380605,19.556155],"type":"Point"}
}