{
  "type": "Feature",
  "properties": {
    "gn:admin1_code":"19.0",
    "gn:admin2_code":"572.0",
    "gn:asciiname":"Kodagihalli",
    "gn:country_code":"IN",
    "gn:dem":846,
    "gn:feature_class":"P",
    "gn:feature_code":"PPL",
    "gn:name":"Kodagihalli",
    "gn:population":0,
    "gn:timezone":"Asia/Kolkata",
    "iso:country":"IN",
    "ks:ks_name":"Kodigehalli",
    "ks:ks_pop":400,
    "ks:ks_type":"VILLAGE",
    "ks:ks_uagg_main":0,
    "name:eng_x_preferred":[
        "Kodigehalli"
    ],
    "wof:name":"Kodigehalli",
    "wof:placetype":"locality",
    "wof:population":400
},
  "geometry": {"coordinates":[77.46484700000001,12.976184],"type":"Point"}
}