{
  "type": "Feature",
  "properties": {
    "gn:admin1_code":"37",
    "gn:admin2_code":"408.0",
    "gn:asciiname":"Nawagaon Barhaitola",
    "gn:country_code":"IN",
    "gn:dem":343,
    "gn:feature_class":"P",
    "gn:feature_code":"PPL",
    "gn:name":"Naw\u0101gaon Barhaitol\u0101",
    "gn:population":0,
    "gn:timezone":"Asia/Kolkata",
    "iso:country":"IN",
    "wof:name":"Nawagaon Barhaitola",
    "wof:placetype":"neighbourhood"
},
  "geometry": {"coordinates":[80.87864999999999,21.37845],"type":"Point"}
}