{
  "type": "Feature",
  "properties": {
    "iso:country":"IN",
    "ks:ks_name":"Kilakulathupatti",
    "ks:ks_pop":112,
    "ks:ks_type":"HABITATION",
    "name:eng_x_preferred":[
        "Kilakulathupatti"
    ],
    "wof:name":"Kilakulathupatti",
    "wof:placetype":"locality",
    "wof:population":112
},
  "geometry": {"coordinates":[78.759006,10.216117],"type":"Point"}
}