{
  "type": "Feature",
  "properties": {
    "iso:country":"IN",
    "ks:ks_name":"Puzhachal",
    "ks:ks_pop":769,
    "ks:ks_type":"HABITATION",
    "name:eng_x_preferred":[
        "Puzhachal"
    ],
    "wof:name":"Puzhachal",
    "wof:placetype":"locality",
    "wof:population":769
},
  "geometry": {"coordinates":[75.98427700000001,11.031493],"type":"Point"}
}