{
  "type": "Feature",
  "properties": {
    "iso:country":"IN",
    "ks:ks_name":"Deu",
    "ks:ks_pop":1448,
    "ks:ks_type":"VILLAGE",
    "name:eng_x_preferred":[
        "Deu"
    ],
    "wof:name":"Deu",
    "wof:placetype":"locality",
    "wof:population":1448
},
  "geometry": {"coordinates":[73.285161,27.131683],"type":"Point"}
}