{
  "type": "Feature",
  "properties": {
    "iso:country":"IN",
    "ks:ks_alt_nam":"Hehegar\u0101",
    "ks:ks_name":"Hehegara",
    "ks:ks_pop":1241,
    "ks:ks_type":"VILLAGE",
    "name:eng_x_preferred":[
        "Hehegara"
    ],
    "name:eng_x_variant":[
        "Hehegar\u0101"
    ],
    "wof:name":"Hehegara",
    "wof:placetype":"locality",
    "wof:population":1241
},
  "geometry": {"coordinates":[84.28299199999999,23.790814],"type":"Point"}
}