{
  "type": "Feature",
  "properties": {
    "gn:admin1_code":"35.0",
    "gn:admin2_code":"456.0",
    "gn:asciiname":"Newargaon",
    "gn:country_code":"IN",
    "gn:dem":379,
    "gn:feature_class":"P",
    "gn:feature_code":"PPL",
    "gn:name":"Newargaon",
    "gn:population":0,
    "gn:timezone":"Asia/Kolkata",
    "iso:country":"IN",
    "wof:name":"Newargaon",
    "wof:placetype":"locality"
},
  "geometry": {"coordinates":[80.0373,22.31161],"type":"Point"}
}