{
  "type": "Feature",
  "properties": {
    "iso:country":"IN",
    "ks:ks_name":"Khempur Shefullapur",
    "ks:ks_pop":1038,
    "ks:ks_type":"HABITATION",
    "ks:ks_uagg_main":0,
    "name:eng_x_preferred":[
        "Khempur Shefullapur"
    ],
    "wof:name":"Khempur Shefullapur",
    "wof:placetype":"neighbourhood",
    "wof:population":1038
},
  "geometry": {"coordinates":[78.661064,29.039171],"type":"Point"}
}