{
  "type": "Feature",
  "properties": {
    "iso:country":"IN",
    "ks:ks_name":"Bhakawa Guda Para",
    "ks:ks_pop":651,
    "ks:ks_type":"HABITATION",
    "name:eng_x_preferred":[
        "Bhakawa Guda Para"
    ],
    "wof:name":"Bhakawa Guda Para",
    "wof:placetype":"locality",
    "wof:population":651
},
  "geometry": {"coordinates":[82.079438,19.301869],"type":"Point"}
}