{
  "type": "Feature",
  "properties": {
    "gn:admin1_code":"23.0",
    "gn:admin2_code":"49.0",
    "gn:asciiname":"Bhoma",
    "gn:country_code":"IN",
    "gn:dem":238,
    "gn:feature_class":"P",
    "gn:feature_code":"PPL",
    "gn:name":"Bhoma",
    "gn:population":0,
    "gn:timezone":"Asia/Kolkata",
    "iso:country":"IN",
    "name:msa_x_preferred":[
        "Boma"
    ],
    "name:tha_x_preferred":[
        "\u0e42\u0e1a\u0e21\u0e32"
    ],
    "wof:name":"Bhoma",
    "wof:placetype":"locality"
},
  "geometry": {"coordinates":[74.97826999999999,31.80614000000001],"type":"Point"}
}