{
  "type": "Feature",
  "properties": {
    "iso:country":"IN",
    "ks:ks_name":"Salrapara",
    "ks:ks_pop":677,
    "ks:ks_type":"VILLAGE",
    "name:eng_x_preferred":[
        "Salrapara"
    ],
    "wof:name":"Salrapara",
    "wof:placetype":"locality",
    "wof:population":677
},
  "geometry": {"coordinates":[74.671469,23.526331],"type":"Point"}
}