{
  "type": "Feature",
  "properties": {
    "iso:country":"IN",
    "ks:ks_name":"Malekarwadi",
    "ks:ks_pop":343,
    "ks:ks_type":"HABITATION",
    "name:eng_x_preferred":[
        "Malekarwadi"
    ],
    "wof:name":"Malekarwadi",
    "wof:placetype":"locality",
    "wof:population":343
},
  "geometry": {"coordinates":[75.4575,18.9089],"type":"Point"}
}