{
  "type": "Feature",
  "properties": {
    "gn:admin1_code":"12.0",
    "gn:asciiname":"Nagni",
    "gn:country_code":"IN",
    "gn:dem":2591,
    "gn:feature_class":"P",
    "gn:feature_code":"PPL",
    "gn:name":"N\u0101gni",
    "gn:population":0,
    "gn:timezone":"Asia/Kolkata",
    "iso:country":"IN",
    "wof:name":"Nagni",
    "wof:placetype":"locality"
},
  "geometry": {"coordinates":[74.29859999999999,34.74723],"type":"Point"}
}