{
  "type": "Feature",
  "properties": {
    "iso:country":"IN",
    "ks:ks_name":"Gali Pathar Singapur",
    "ks:ks_pop":717,
    "ks:ks_type":"HABITATION",
    "name:eng_x_preferred":[
        "Gali Pathar Singapur"
    ],
    "wof:name":"Gali Pathar Singapur",
    "wof:placetype":"locality",
    "wof:population":717
},
  "geometry": {"coordinates":[95.13046300000001,27.810305],"type":"Point"}
}