{
  "type": "Feature",
  "properties": {
    "gn:admin1_code":"34.0",
    "gn:admin2_code":"236.0",
    "gn:asciiname":"Kharagpura",
    "gn:country_code":"IN",
    "gn:dem":95,
    "gn:feature_class":"P",
    "gn:feature_code":"PPL",
    "gn:name":"Kharagpura",
    "gn:population":0,
    "gn:timezone":"Asia/Kolkata",
    "iso:country":"IN",
    "ks:ks_name":"Kharagpura",
    "ks:ks_pop":641,
    "ks:ks_type":"HABITATION",
    "name:eng_x_preferred":[
        "Kharagpura"
    ],
    "wof:name":"Kharagpura",
    "wof:placetype":"locality",
    "wof:population":641
},
  "geometry": {"coordinates":[84.87670199999999,24.977151],"type":"Point"}
}