{
  "type": "Feature",
  "properties": {
    "iso:country":"IN",
    "ks:ks_name":"Ambalapadi",
    "ks:ks_pop":1865,
    "ks:ks_type":"HABITATION",
    "name:eng_x_preferred":[
        "Ambalapadi"
    ],
    "wof:name":"Ambalapadi",
    "wof:placetype":"locality",
    "wof:population":1865
},
  "geometry": {"coordinates":[76.94493,10.019308],"type":"Point"}
}