{
  "type": "Feature",
  "properties": {
    "gn:admin1_code":"39.0",
    "gn:admin2_code":"66.0",
    "gn:asciiname":"Bechabangar",
    "gn:country_code":"IN",
    "gn:dem":314,
    "gn:feature_class":"P",
    "gn:feature_code":"PPL",
    "gn:name":"Bechabangar",
    "gn:population":0,
    "gn:timezone":"Asia/Kolkata",
    "iso:country":"IN",
    "ks:ks_name":"Bechabangar",
    "ks:ks_type":"VILLAGE",
    "name:eng_x_preferred":[
        "Bechabangar"
    ],
    "wof:name":"Bechabangar",
    "wof:placetype":"locality"
},
  "geometry": {"coordinates":[79.253136,29.289268],"type":"Point"}
}