{
  "type": "Feature",
  "properties": {
    "gn:admin1_code":"36",
    "gn:admin2_code":"194.0",
    "gn:asciiname":"Amanwan Khurd",
    "gn:country_code":"IN",
    "gn:dem":92,
    "gn:feature_class":"P",
    "gn:feature_code":"PPL",
    "gn:name":"Am\u0101nw\u0101n Khurd",
    "gn:population":0,
    "gn:timezone":"Asia/Kolkata",
    "iso:country":"IN",
    "ks:ks_alt_nam":"Am\u0101nw\u0101n Khurd",
    "ks:ks_name":"Amanwan Khurd",
    "ks:ks_pop":1181,
    "ks:ks_type":"VILLAGE",
    "ks:ks_uagg_main":0,
    "name:eng_x_preferred":[
        "Amanwan Khurd"
    ],
    "name:eng_x_variant":[
        "Am\u0101nw\u0101n Khurd"
    ],
    "wof:name":"Amanwan Khurd",
    "wof:placetype":"neighbourhood",
    "wof:population":1181
},
  "geometry": {"coordinates":[82.518023,26.05906],"type":"Point"}
}