{
  "type": "Feature",
  "properties": {
    "gn:admin1_code":"19.0",
    "gn:admin2_code":"556.0",
    "gn:asciiname":"Bhadranaikan Jalihal",
    "gn:country_code":"IN",
    "gn:dem":534,
    "gn:feature_class":"P",
    "gn:feature_code":"PPL",
    "gn:name":"Bhadranaikan J\u0101lih\u0101l",
    "gn:population":0,
    "gn:timezone":"Asia/Kolkata",
    "iso:country":"IN",
    "wof:name":"Bhadranaikan Jalihal",
    "wof:placetype":"locality"
},
  "geometry": {"coordinates":[75.78024000000001,15.95414],"type":"Point"}
}