{
  "type": "Feature",
  "properties": {
    "gn:admin1_code":"36.0",
    "gn:admin2_code":"140.0",
    "gn:asciiname":"Mandiya",
    "gn:country_code":"IN",
    "gn:dem":219,
    "gn:feature_class":"P",
    "gn:feature_code":"PPL",
    "gn:name":"Mandiya",
    "gn:population":0,
    "gn:timezone":"Asia/Kolkata",
    "iso:country":"IN",
    "name:ara_x_preferred":[
        "\u0645\u0627\u0646\u062f\u064a\u0627"
    ],
    "name:ben_bn_x_preferred":[
        "\u09ae\u09be\u09a8\u09cd\u09a1\u09bf\u09df\u09be"
    ],
    "name:ben_in_x_preferred":[
        "\u09ae\u09be\u09a8\u09cd\u09a1\u09bf\u09df\u09be"
    ],
    "name:guj_x_preferred":[
        "\u0aae\u0a82\u0aa1\u0ac0\u0aaf\u0abe"
    ],
    "name:hin_x_preferred":[
        "\u092e\u0902\u0921\u093f\u092f\u093e"
    ],
    "name:kan_x_preferred":[
        "\u0cae\u0c82\u0ca1\u0ccd\u0caf"
    ],
    "name:mal_x_preferred":[
        "\u0d2e\u0d3e\u0d23\u0d4d\u0d21\u0d3f\u0d2f"
    ],
    "name:mar_x_preferred":[
        "\u092e\u093e\u0902\u0921\u093f\u092f\u093e"
    ],
    "name:pan_x_preferred":[
        "\u0a2e\u0a70\u0a21\u0a40\u0a06"
    ],
    "name:tam_x_preferred":[
        "\u0bae\u0bbe\u0ba9\u0bcd\u0b9f\u0bcd\u0baf\u0bbe"
    ],
    "name:tel_x_preferred":[
        "\u0c2e\u0c02\u0c21\u0c3f\u0c2f\u0c3e"
    ],
    "name:urd_x_preferred":[
        "\u0645\u0627\u0646\u0688\u06cc\u0627"
    ],
    "wof:name":"Mandiya",
    "wof:placetype":"locality"
},
  "geometry": {"coordinates":[77.91609,28.83978],"type":"Point"}
}