{
  "type": "Feature",
  "properties": {
    "gn:admin1_code":"9.0",
    "gn:admin2_code":"473.0",
    "gn:asciiname":"Rupal",
    "gn:country_code":"IN",
    "gn:dem":86,
    "gn:feature_class":"P",
    "gn:feature_code":"PPL",
    "gn:name":"Rup\u0101l",
    "gn:population":0,
    "gn:timezone":"Asia/Kolkata",
    "iso:country":"IN",
    "name:deu_x_preferred":[
        "Rupal"
    ],
    "name:fra_x_preferred":[
        "Rupal"
    ],
    "wof:name":"Rupal",
    "wof:placetype":"locality"
},
  "geometry": {"coordinates":[72.60110999999998,23.31445],"type":"Point"}
}