{
  "type": "Feature",
  "properties": {
    "gn:admin1_code":"2.0",
    "gn:admin2_code":"543.0",
    "gn:asciiname":"Kilikavalasa",
    "gn:country_code":"IN",
    "gn:dem":133,
    "gn:feature_class":"P",
    "gn:feature_code":"PPL",
    "gn:name":"Kilikavalasa",
    "gn:population":0,
    "gn:timezone":"Asia/Kolkata",
    "iso:country":"IN",
    "ks:ks_name":"Killakavalasa",
    "ks:ks_pop":6,
    "ks:ks_type":"HABITATION",
    "name:eng_x_preferred":[
        "Killakavalasa"
    ],
    "name:eng_x_variant":[
        "Kilikavalasa"
    ],
    "wof:name":"Killakavalasa",
    "wof:placetype":"locality",
    "wof:population":6
},
  "geometry": {"coordinates":[83.473663,18.921812],"type":"Point"}
}