{
  "type": "Feature",
  "properties": {
    "iso:country":"IN",
    "ks:ks_name":"Chainpur Mutaluke Makundpur",
    "ks:ks_pop":47,
    "ks:ks_type":"VILLAGE",
    "name:eng_x_preferred":[
        "Chainpur Mutaluke Makundpur"
    ],
    "wof:name":"Chainpur Mutaluke Makundpur",
    "wof:placetype":"locality",
    "wof:population":47
},
  "geometry": {"coordinates":[85.354275,25.764418],"type":"Point"}
}