{
  "type": "Feature",
  "properties": {
    "iso:country":"IN",
    "ks:ks_name":"Suklan",
    "ks:ks_pop":100,
    "ks:ks_type":"HABITATION",
    "name:eng_x_preferred":[
        "Suklan"
    ],
    "wof:name":"Suklan",
    "wof:placetype":"locality",
    "wof:population":100
},
  "geometry": {"coordinates":[82.127933,25.58535],"type":"Point"}
}