{
  "type": "Feature",
  "properties": {
    "iso:country":"IN",
    "ks:ks_name":"Hasnar",
    "ks:ks_pop":304,
    "ks:ks_type":"HABITATION",
    "name:eng_x_preferred":[
        "Hasnar"
    ],
    "wof:name":"Hasnar",
    "wof:placetype":"locality",
    "wof:population":304
},
  "geometry": {"coordinates":[81.161911,19.405913],"type":"Point"}
}