{
  "type": "Feature",
  "properties": {
    "iso:country":"IN",
    "ks:ks_name":"Sansarsara",
    "ks:ks_pop":43,
    "ks:ks_type":"VILLAGE",
    "name:eng_x_preferred":[
        "Sansarsara"
    ],
    "wof:name":"Sansarsara",
    "wof:placetype":"locality",
    "wof:population":43
},
  "geometry": {"coordinates":[84.819315,21.689084],"type":"Point"}
}