{
  "type": "Feature",
  "properties": {
    "iso:country":"IN",
    "ks:ks_name":"Garchuiya",
    "ks:ks_pop":671,
    "ks:ks_type":"HABITATION",
    "ks:ks_uagg_main":0,
    "name:eng_x_preferred":[
        "Garchuiya"
    ],
    "wof:name":"Garchuiya",
    "wof:placetype":"neighbourhood",
    "wof:population":671
},
  "geometry": {"coordinates":[84.043582,26.690511],"type":"Point"}
}