{
  "type": "Feature",
  "properties": {
    "gn:admin1_code":"34.0",
    "gn:admin2_code":"229.0",
    "gn:asciiname":"Kapatia",
    "gn:country_code":"IN",
    "gn:dem":65,
    "gn:feature_class":"P",
    "gn:feature_code":"PPL",
    "gn:name":"Kapatia",
    "gn:population":0,
    "gn:timezone":"Asia/Kolkata",
    "iso:country":"IN",
    "ks:ks_name":"Kapatiya",
    "ks:ks_pop":653,
    "ks:ks_type":"HABITATION",
    "ks:ks_uagg_main":0,
    "name:eng_x_preferred":[
        "Kapatiya"
    ],
    "wof:name":"Kapatiya",
    "wof:placetype":"neighbourhood",
    "wof:population":653
},
  "geometry": {"coordinates":[85.44658099999999,25.13176],"type":"Point"}
}