{
  "type": "Feature",
  "properties": {
    "gn:admin1_code":"13.0",
    "gn:admin2_code":"590.0",
    "gn:asciiname":"Vallipetta",
    "gn:country_code":"IN",
    "gn:dem":752,
    "gn:feature_class":"P",
    "gn:feature_code":"PPL",
    "gn:name":"Vallipetta",
    "gn:population":0,
    "gn:timezone":"Asia/Kolkata",
    "iso:country":"IN",
    "wof:name":"Vallipetta",
    "wof:placetype":"locality"
},
  "geometry": {"coordinates":[76.11825999999998,11.68868],"type":"Point"}
}