{
  "type": "Feature",
  "properties": {
    "iso:country":"IN",
    "ks:ks_name":"Patharaipur",
    "ks:ks_pop":758,
    "ks:ks_type":"VILLAGE",
    "name:eng_x_preferred":[
        "Patharaipur"
    ],
    "wof:name":"Patharaipur",
    "wof:placetype":"locality",
    "wof:population":758
},
  "geometry": {"coordinates":[86.890919,21.540304],"type":"Point"}
}