{
  "type": "Feature",
  "properties": {
    "gn:admin1_code":"35",
    "gn:admin2_code":"459.0",
    "gn:asciiname":"Marhi Buzurg",
    "gn:country_code":"IN",
    "gn:dem":474,
    "gn:feature_class":"P",
    "gn:feature_code":"PPL",
    "gn:name":"Marhi Buzurg",
    "gn:population":0,
    "gn:timezone":"Asia/Kolkata",
    "iso:country":"IN",
    "ks:ks_name":"Madhi Buzurg",
    "ks:ks_pop":538,
    "ks:ks_type":"VILLAGE",
    "name:eng_x_preferred":[
        "Madhi Buzurg"
    ],
    "name:eng_x_variant":[
        "Marhi Buzurg"
    ],
    "wof:name":"Madhi Buzurg",
    "wof:placetype":"locality",
    "wof:population":538
},
  "geometry": {"coordinates":[77.78151,24.346986],"type":"Point"}
}