{
  "type": "Feature",
  "properties": {
    "iso:country":"IN",
    "ks:ks_name":"Chidanga Khalsa",
    "ks:ks_pop":224,
    "ks:ks_type":"VILLAGE",
    "name:eng_x_preferred":[
        "Chidanga Khalsa"
    ],
    "wof:name":"Chidanga Khalsa",
    "wof:placetype":"locality",
    "wof:population":224
},
  "geometry": {"coordinates":[79.553358,30.034259],"type":"Point"}
}