{
  "type": "Feature",
  "properties": {
    "gn:admin1_code":"21.0",
    "gn:admin2_code":"398.0",
    "gn:asciiname":"Kalliajolla",
    "gn:country_code":"IN",
    "gn:dem":852,
    "gn:feature_class":"P",
    "gn:feature_code":"PPL",
    "gn:name":"Kalliajolla",
    "gn:population":0,
    "gn:timezone":"Asia/Kolkata",
    "iso:country":"IN",
    "wof:name":"Kalliajolla",
    "wof:placetype":"locality"
},
  "geometry": {"coordinates":[82.99925,19.0052],"type":"Point"}
}