{
  "type": "Feature",
  "properties": {
    "gn:admin1_code":"10",
    "gn:admin2_code":"88.0",
    "gn:asciiname":"Rampur Khor",
    "gn:country_code":"IN",
    "gn:dem":196,
    "gn:feature_class":"P",
    "gn:feature_code":"PPL",
    "gn:name":"R\u0101mpur Khor",
    "gn:population":0,
    "gn:timezone":"Asia/Kolkata",
    "iso:country":"IN",
    "wof:name":"Rampur Khor",
    "wof:placetype":"locality"
},
  "geometry": {"coordinates":[77.44173000000001,28.17111],"type":"Point"}
}