{
  "type": "Feature",
  "properties": {
    "iso:country":"IN",
    "ks:ks_name":"Moongthali",
    "ks:ks_pop":1107,
    "ks:ks_type":"VILLAGE",
    "name:eng_x_preferred":[
        "Moongthali"
    ],
    "wof:name":"Moongthali",
    "wof:placetype":"locality",
    "wof:population":1107
},
  "geometry": {"coordinates":[74.30496100000001,23.612094],"type":"Point"}
}