{
  "type": "Feature",
  "properties": {
    "iso:country":"IN",
    "ks:ks_name":"Sonavanewasti",
    "ks:ks_pop":154,
    "ks:ks_type":"HABITATION",
    "name:eng_x_preferred":[
        "Sonavanewasti"
    ],
    "wof:name":"Sonavanewasti",
    "wof:placetype":"locality",
    "wof:population":154
},
  "geometry": {"coordinates":[74.728757,17.634701],"type":"Point"}
}