{
  "type": "Feature",
  "properties": {
    "iso:country":"IN",
    "ks:ks_name":"M Colony",
    "ks:ks_pop":218,
    "ks:ks_type":"HABITATION",
    "name:eng_x_preferred":[
        "M Colony"
    ],
    "wof:name":"M Colony",
    "wof:placetype":"locality",
    "wof:population":218
},
  "geometry": {"coordinates":[76.008307,12.816591],"type":"Point"}
}