{
  "type": "Feature",
  "properties": {
    "gn:admin1_code":"2.0",
    "gn:admin2_code":"543.0",
    "gn:asciiname":"Narangipadu",
    "gn:country_code":"IN",
    "gn:dem":519,
    "gn:feature_class":"P",
    "gn:feature_code":"PPL",
    "gn:name":"N\u0101rangip\u0101du",
    "gn:population":0,
    "gn:timezone":"Asia/Kolkata",
    "iso:country":"IN",
    "wof:name":"Narangipadu",
    "wof:placetype":"locality"
},
  "geometry": {"coordinates":[83.1212,18.58125],"type":"Point"}
}