{
  "type": "Feature",
  "properties": {
    "gn:admin1_code":"36",
    "gn:admin2_code":"167.0",
    "gn:asciiname":"Nekora",
    "gn:country_code":"IN",
    "gn:dem":371,
    "gn:feature_class":"P",
    "gn:feature_code":"PPL",
    "gn:name":"Nekora",
    "gn:population":0,
    "gn:timezone":"Asia/Kolkata",
    "iso:country":"IN",
    "wof:name":"Nekora",
    "wof:placetype":"locality"
},
  "geometry": {"coordinates":[78.90089,24.48275],"type":"Point"}
}