{
  "type": "Feature",
  "properties": {
    "gn:admin1_code":"34.0",
    "gn:admin2_code":"222",
    "gn:asciiname":"Ballia",
    "gn:country_code":"IN",
    "gn:dem":48,
    "gn:feature_class":"P",
    "gn:feature_code":"PPL",
    "gn:name":"Ballia",
    "gn:population":0,
    "gn:timezone":"Asia/Kolkata",
    "iso:country":"IN",
    "name:ara_x_preferred":[
        "\u0628\u0627\u0644\u064a\u0627"
    ],
    "name:ben_bn_x_preferred":[
        "\u09ac\u09be\u09b2\u09bf\u09df\u09be"
    ],
    "name:ben_in_x_preferred":[
        "\u09ac\u09be\u09b2\u09bf\u09df\u09be"
    ],
    "name:guj_x_preferred":[
        "\u0aac\u0ab2\u0abf\u0aaf\u0abe"
    ],
    "name:hin_x_preferred":[
        "\u092c\u0932\u093f\u092f\u093e"
    ],
    "name:kan_x_preferred":[
        "\u0cac\u0cb2\u0ccd\u0cb2\u0cbf\u0caf\u0cbe"
    ],
    "name:mal_x_preferred":[
        "\u0d2c\u0d3e\u0d32\u0d3f\u0d2f"
    ],
    "name:mar_x_preferred":[
        "\u092c\u0932\u093f\u092f\u093e"
    ],
    "name:pan_x_preferred":[
        "\u0a2c\u0a32\u0a40\u0a06"
    ],
    "name:tam_x_preferred":[
        "\u0baa\u0bb2\u0bcd\u0bb2\u0bbf\u0baf\u0bbe"
    ],
    "name:tel_x_preferred":[
        "\u0c2c\u0c32\u0c3f\u0c2f\u0c3e"
    ],
    "name:urd_x_preferred":[
        "\u0628\u0644\u06cc\u0627"
    ],
    "wof:name":"Ballia",
    "wof:placetype":"locality"
},
  "geometry": {"coordinates":[86.31444999999999,25.42139],"type":"Point"}
}