{
  "type": "Feature",
  "properties": {
    "gn:admin1_code":"25.0",
    "gn:admin2_code":"631.0",
    "gn:asciiname":"Noganur",
    "gn:country_code":"IN",
    "gn:dem":934,
    "gn:feature_class":"P",
    "gn:feature_code":"PPL",
    "gn:name":"Nogan\u016br",
    "gn:population":0,
    "gn:timezone":"Asia/Kolkata",
    "iso:country":"IN",
    "wof:name":"Noganur",
    "wof:placetype":"neighbourhood"
},
  "geometry": {"coordinates":[77.77683,12.49506],"type":"Point"}
}