{
  "type": "Feature",
  "properties": {
    "iso:country":"IN",
    "ks:ks_name":"Maniyaran Kudiyiruppu",
    "ks:ks_pop":225,
    "ks:ks_type":"HABITATION",
    "name:eng_x_preferred":[
        "Maniyaran Kudiyiruppu"
    ],
    "wof:name":"Maniyaran Kudiyiruppu",
    "wof:placetype":"locality",
    "wof:population":225
},
  "geometry": {"coordinates":[78.988006,10.277559],"type":"Point"}
}