{
  "type": "Feature",
  "properties": {
    "iso:country":"IN",
    "ks:ks_name":"Checkdamguda",
    "ks:ks_pop":176,
    "ks:ks_type":"HABITATION",
    "name:eng_x_preferred":[
        "Checkdamguda"
    ],
    "wof:name":"Checkdamguda",
    "wof:placetype":"locality",
    "wof:population":176
},
  "geometry": {"coordinates":[78.842623,19.330134],"type":"Point"}
}