{
  "type": "Feature",
  "properties": {
    "iso:country":"IN",
    "ks:ks_alt_nam":"Majhgaw\u0101n",
    "ks:ks_name":"Majhgawan",
    "ks:ks_type":"VILLAGE",
    "name:eng_x_preferred":[
        "Majhgawan"
    ],
    "name:eng_x_variant":[
        "Majhgaw\u0101n"
    ],
    "wof:name":"Majhgawan",
    "wof:placetype":"locality"
},
  "geometry": {"coordinates":[80.820521,26.608962],"type":"Point"}
}