{
  "type": "Feature",
  "properties": {
    "iso:country":"IN",
    "ks:ks_alt_nam":"Tun\u012bkham\u0101r",
    "ks:ks_name":"Tunikhamar",
    "ks:ks_type":"VILLAGE",
    "name:eng_x_preferred":[
        "Tunikhamar"
    ],
    "name:eng_x_variant":[
        "Tun\u012bkham\u0101r"
    ],
    "wof:name":"Tunikhamar",
    "wof:placetype":"locality"
},
  "geometry": {"coordinates":[84.077322,20.709088],"type":"Point"}
}