{
  "type": "Feature",
  "properties": {
    "iso:country":"IN",
    "ks:ks_name":"Aralabaragur",
    "ks:ks_pop":191,
    "ks:ks_type":"HABITATION",
    "name:eng_x_preferred":[
        "Aralabaragur"
    ],
    "wof:name":"Aralabaragur",
    "wof:placetype":"locality",
    "wof:population":191
},
  "geometry": {"coordinates":[76.3505,12.935803],"type":"Point"}
}