{
  "type": "Feature",
  "properties": {
    "iso:country":"IN",
    "ks:ks_name":"Golruan",
    "ks:ks_pop":970,
    "ks:ks_type":"VILLAGE",
    "name:eng_x_preferred":[
        "Golruan"
    ],
    "wof:name":"Golruan",
    "wof:placetype":"locality",
    "wof:population":970
},
  "geometry": {"coordinates":[85.259179,22.519918],"type":"Point"}
}