{
  "type": "Feature",
  "properties": {
    "iso:country":"IN",
    "ks:ks_name":"Hebgigadde",
    "ks:ks_pop":472,
    "ks:ks_type":"HABITATION",
    "name:eng_x_preferred":[
        "Hebgigadde"
    ],
    "wof:name":"Hebgigadde",
    "wof:placetype":"locality",
    "wof:population":472
},
  "geometry": {"coordinates":[74.489754,14.665344],"type":"Point"}
}