{
  "type": "Feature",
  "properties": {
    "iso:country":"IN",
    "ks:ks_name":"Dubhapani",
    "ks:ks_pop":352,
    "ks:ks_type":"VILLAGE",
    "name:eng_x_preferred":[
        "Dubhapani"
    ],
    "wof:name":"Dubhapani",
    "wof:placetype":"locality",
    "wof:population":352
},
  "geometry": {"coordinates":[82.561271,23.167243],"type":"Point"}
}