{
  "type": "Feature",
  "properties": {
    "iso:country":"IN",
    "ks:ks_name":"Odari",
    "ks:ks_pop":1502,
    "ks:ks_type":"VILLAGE",
    "name:eng_x_preferred":[
        "Odari"
    ],
    "wof:name":"Odari",
    "wof:placetype":"locality",
    "wof:population":1502
},
  "geometry": {"coordinates":[83.298762,23.674093],"type":"Point"}
}