{
  "type": "Feature",
  "properties": {
    "iso:country":"IN",
    "ks:ks_name":"Bavanpally",
    "ks:ks_pop":314,
    "ks:ks_type":"HABITATION",
    "name:eng_x_preferred":[
        "Bavanpally"
    ],
    "wof:name":"Bavanpally",
    "wof:placetype":"locality",
    "wof:population":314
},
  "geometry": {"coordinates":[79.782213,18.966492],"type":"Point"}
}