{
  "type": "Feature",
  "properties": {
    "gn:admin1_code":"24",
    "gn:admin2_code":"107.0",
    "gn:asciiname":"Harnagar",
    "gn:country_code":"IN",
    "gn:dem":293,
    "gn:feature_class":"P",
    "gn:feature_code":"PPL",
    "gn:name":"Harnagar",
    "gn:population":0,
    "gn:timezone":"Asia/Kolkata",
    "iso:country":"IN",
    "wof:name":"Harnagar",
    "wof:placetype":"locality"
},
  "geometry": {"coordinates":[77.10288,26.45614],"type":"Point"}
}