{
  "type": "Feature",
  "properties": {
    "iso:country":"IN",
    "ks:ks_alt_nam":"Ghatewadi NV",
    "ks:ks_name":"Ghatewadi Nv",
    "ks:ks_pop":474,
    "ks:ks_type":"HABITATION",
    "name:eng_x_preferred":[
        "Ghatewadi Nv"
    ],
    "wof:name":"Ghatewadi Nv",
    "wof:placetype":"locality",
    "wof:population":474
},
  "geometry": {"coordinates":[73.917485,17.559924],"type":"Point"}
}