{
  "type": "Feature",
  "properties": {
    "iso:country":"IN",
    "ks:ks_name":"Sarthe Terang 1",
    "ks:ks_pop":125,
    "ks:ks_type":"HABITATION",
    "name:eng_x_preferred":[
        "Sarthe Terang 1"
    ],
    "wof:name":"Sarthe Terang 1",
    "wof:placetype":"locality",
    "wof:population":125
},
  "geometry": {"coordinates":[93.75766,26.230888],"type":"Point"}
}