{
  "type": "Feature",
  "properties": {
    "gn:admin1_code":"34.0",
    "gn:admin2_code":"236.0",
    "gn:asciiname":"Geyan Khap",
    "gn:country_code":"IN",
    "gn:dem":172,
    "gn:feature_class":"P",
    "gn:feature_code":"PPL",
    "gn:name":"Gey\u0101n Kh\u0101p",
    "gn:population":0,
    "gn:timezone":"Asia/Kolkata",
    "iso:country":"IN",
    "ks:ks_alt_nam":"Gey\u0101n Kh\u0101p",
    "ks:ks_name":"Geyan Khap",
    "ks:ks_pop":448,
    "ks:ks_type":"VILLAGE",
    "ks:ks_uagg_main":0,
    "name:eng_x_preferred":[
        "Geyan Khap"
    ],
    "name:eng_x_variant":[
        "Gey\u0101n Kh\u0101p"
    ],
    "wof:name":"Geyan Khap",
    "wof:placetype":"neighbourhood",
    "wof:population":448
},
  "geometry": {"coordinates":[84.67366699999999,24.541524],"type":"Point"}
}