{
  "type": "Feature",
  "properties": {
    "iso:country":"IN",
    "ks:ks_name":"Dhabani",
    "ks:ks_pop":728,
    "ks:ks_type":"VILLAGE",
    "name:eng_x_preferred":[
        "Dhabani"
    ],
    "wof:name":"Dhabani",
    "wof:placetype":"locality",
    "wof:population":728
},
  "geometry": {"coordinates":[87.01899899999999,22.027812],"type":"Point"}
}