{
  "type": "Feature",
  "properties": {
    "iso:country":"IN",
    "ks:ks_alt_nam":"Koilamoila II",
    "ks:ks_name":"Koilamoila Ii",
    "ks:ks_pop":263,
    "ks:ks_type":"HABITATION",
    "name:eng_x_preferred":[
        "Koilamoila Ii"
    ],
    "wof:name":"Koilamoila Ii",
    "wof:placetype":"locality",
    "wof:population":263
},
  "geometry": {"coordinates":[90.576291,26.689781],"type":"Point"}
}