{
  "type": "Feature",
  "properties": {
    "iso:country":"IN",
    "ks:ks_alt_nam":"Salchapra TE Sahapur TE",
    "ks:ks_name":"Salchapra Te Sahapur Te",
    "ks:ks_pop":726,
    "ks:ks_type":"HABITATION",
    "name:eng_x_preferred":[
        "Salchapra Te Sahapur Te"
    ],
    "wof:name":"Salchapra Te Sahapur Te",
    "wof:placetype":"locality",
    "wof:population":726
},
  "geometry": {"coordinates":[92.66355900000001,24.675045],"type":"Point"}
}