{
  "type": "Feature",
  "properties": {
    "gn:admin1_code":"37.0",
    "gn:admin2_code":"408.0",
    "gn:asciiname":"Sadak Chichari",
    "gn:country_code":"IN",
    "gn:dem":394,
    "gn:feature_class":"P",
    "gn:feature_code":"PPL",
    "gn:name":"Sadak Chich\u0101r\u012b",
    "gn:population":0,
    "gn:timezone":"Asia/Kolkata",
    "iso:country":"IN",
    "name:und_x_variant":[
        "Sadak Chich\u0101r\u012b",
        "Sadak Chichari"
    ],
    "wof:name":"Sadak Chichari",
    "wof:placetype":"locality"
},
  "geometry": {"coordinates":[80.58569,21.08444],"type":"Point"}
}