{
  "type": "Feature",
  "properties": {
    "gn:admin1_code":"16",
    "gn:admin2_code":"507.0",
    "gn:asciiname":"Kauliwara",
    "gn:country_code":"IN",
    "gn:dem":276,
    "gn:feature_class":"P",
    "gn:feature_code":"PPL",
    "gn:name":"Kaul\u012bw\u0101ra",
    "gn:population":0,
    "gn:timezone":"Asia/Kolkata",
    "iso:country":"IN",
    "wof:name":"Kauliwara",
    "wof:placetype":"neighbourhood"
},
  "geometry": {"coordinates":[79.90057,21.43873],"type":"Point"}
}