{
  "type": "Feature",
  "properties": {
    "iso:country":"IN",
    "ks:ks_name":"Vengavasal",
    "ks:ks_type":"VILLAGE",
    "ks:ks_uagg_main":0,
    "name:eng_x_preferred":[
        "Vengavasal"
    ],
    "wof:name":"Vengavasal",
    "wof:placetype":"locality"
},
  "geometry": {"coordinates":[80.169003,12.899114],"type":"Point"}
}