{
  "type": "Feature",
  "properties": {
    "iso:country":"IN",
    "ks:ks_name":"Manoharpur",
    "ks:ks_pop":1293,
    "ks:ks_type":"HABITATION",
    "name:eng_x_preferred":[
        "Manoharpur"
    ],
    "wof:name":"Manoharpur",
    "wof:placetype":"locality",
    "wof:population":1293
},
  "geometry": {"coordinates":[87.772865,22.06002],"type":"Point"}
}