{
  "type": "Feature",
  "properties": {
    "gn:admin1_code":"35",
    "gn:admin2_code":"455.0",
    "gn:asciiname":"Pindrai",
    "gn:country_code":"IN",
    "gn:dem":703,
    "gn:feature_class":"P",
    "gn:feature_code":"PPL",
    "gn:name":"Pindrai",
    "gn:population":0,
    "gn:timezone":"Asia/Kolkata",
    "iso:country":"IN",
    "wof:name":"Pindrai",
    "wof:placetype":"neighbourhood"
},
  "geometry": {"coordinates":[79.0945,22.22013],"type":"Point"}
}