{
  "type": "Feature",
  "properties": {
    "gn:admin1_code":"34.0",
    "gn:admin2_code":"236.0",
    "gn:asciiname":"Terhi Nadi",
    "gn:country_code":"IN",
    "gn:dem":241,
    "gn:feature_class":"P",
    "gn:feature_code":"PPL",
    "gn:name":"Terh\u012b Nad\u012b",
    "gn:population":0,
    "gn:timezone":"Asia/Kolkata",
    "iso:country":"IN",
    "ks:ks_name":"Tedi Nadi",
    "ks:ks_pop":103,
    "ks:ks_type":"HABITATION",
    "name:eng_x_preferred":[
        "Tedi Nadi"
    ],
    "name:eng_x_variant":[
        "Terhi Nadi"
    ],
    "wof:name":"Tedi Nadi",
    "wof:placetype":"locality",
    "wof:population":103
},
  "geometry": {"coordinates":[84.44544500000001,24.339881],"type":"Point"}
}