{
  "type": "Feature",
  "properties": {
    "iso:country":"IN",
    "ks:ks_name":"Pavoor",
    "ks:ks_pop":5846,
    "ks:ks_type":"VILLAGE",
    "name:eng_x_preferred":[
        "Pavoor"
    ],
    "wof:name":"Pavoor",
    "wof:placetype":"locality",
    "wof:population":5846
},
  "geometry": {"coordinates":[74.94120599999999,12.857346],"type":"Point"}
}