{
  "type": "Feature",
  "properties": {
    "gn:admin1_code":"36.0",
    "gn:admin2_code":"152",
    "gn:asciiname":"Khandar",
    "gn:country_code":"IN",
    "gn:dem":151,
    "gn:feature_class":"P",
    "gn:feature_code":"PPL",
    "gn:name":"Khand\u0101r",
    "gn:population":0,
    "gn:timezone":"Asia/Kolkata",
    "iso:country":"IN",
    "name:hin_x_preferred":[
        "\u0916\u0923\u094d\u0921\u093e\u0930"
    ],
    "wof:name":"Khandar",
    "wof:placetype":"locality"
},
  "geometry": {"coordinates":[79.59475,27.75765],"type":"Point"}
}