{
  "type": "Feature",
  "properties": {
    "gn:admin1_code":"35.0",
    "gn:admin2_code":"446",
    "gn:asciiname":"Bamori",
    "gn:country_code":"IN",
    "gn:dem":319,
    "gn:feature_class":"P",
    "gn:feature_code":"PPL",
    "gn:name":"Bamori",
    "gn:population":0,
    "gn:timezone":"Asia/Kolkata",
    "iso:country":"IN",
    "wof:name":"Bamori",
    "wof:placetype":"locality"
},
  "geometry": {"coordinates":[78.30716,22.95815],"type":"Point"}
}