{
  "type": "Feature",
  "properties": {
    "iso:country":"IN",
    "ks:ks_name":"Ng Chamran",
    "ks:ks_pop":445,
    "ks:ks_type":"HABITATION",
    "name:eng_x_preferred":[
        "Ng Chamran"
    ],
    "wof:name":"Ng Chamran",
    "wof:placetype":"locality",
    "wof:population":445
},
  "geometry": {"coordinates":[78.88333,27.72969],"type":"Point"}
}