{
  "type": "Feature",
  "properties": {
    "gn:admin1_code":"16",
    "gn:admin2_code":"504.0",
    "gn:asciiname":"Dag",
    "gn:country_code":"IN",
    "gn:dem":215,
    "gn:feature_class":"P",
    "gn:feature_code":"PPL",
    "gn:name":"D\u0101g",
    "gn:population":0,
    "gn:timezone":"Asia/Kolkata",
    "iso:country":"IN",
    "name:ceb_x_preferred":[
        "Dag"
    ],
    "name:dan_x_preferred":[
        "Dag"
    ],
    "name:fra_x_preferred":[
        "Dag"
    ],
    "name:hun_x_preferred":[
        "DAG"
    ],
    "name:isl_x_preferred":[
        "Dag"
    ],
    "name:lat_x_preferred":[
        "Dag"
    ],
    "name:nld_x_preferred":[
        "Dag"
    ],
    "name:nor_x_preferred":[
        "Dag"
    ],
    "name:pol_x_preferred":[
        "Dag"
    ],
    "name:rus_x_preferred":[
        "\u0414\u0430\u0433"
    ],
    "name:slk_x_preferred":[
        "Dag"
    ],
    "name:srp_x_preferred":[
        "\u0414\u0430\u0433"
    ],
    "name:swe_x_preferred":[
        "Dag"
    ],
    "wof:name":"Dag",
    "wof:placetype":"locality"
},
  "geometry": {"coordinates":[78.84988,20.58838],"type":"Point"}
}