{
  "type": "Feature",
  "properties": {
    "gn:admin1_code":"9.0",
    "gn:admin2_code":"484.0",
    "gn:asciiname":"Ranakpur",
    "gn:country_code":"IN",
    "gn:dem":124,
    "gn:feature_class":"P",
    "gn:feature_code":"PPL",
    "gn:name":"Ranakpur",
    "gn:population":0,
    "gn:timezone":"Asia/Kolkata",
    "iso:country":"IN",
    "name:cat_x_preferred":[
        "Ranakpur"
    ],
    "name:ces_x_preferred":[
        "Ranakpur"
    ],
    "name:deu_x_preferred":[
        "Ranakpur"
    ],
    "name:fra_x_preferred":[
        "Ranakpur"
    ],
    "name:hin_x_preferred":[
        "\u0930\u0923\u0915\u092a\u0941\u0930"
    ],
    "name:hun_x_preferred":[
        "Ranakpur"
    ],
    "name:ita_x_preferred":[
        "Ranakpur"
    ],
    "name:pol_x_preferred":[
        "Ranakpur"
    ],
    "name:san_x_preferred":[
        "\u0930\u0923\u0915\u092a\u0941\u0930\u092e\u094d"
    ],
    "name:spa_x_preferred":[
        "Ranakpur"
    ],
    "wof:name":"Ranakpur",
    "wof:placetype":"locality"
},
  "geometry": {"coordinates":[73.75474,23.33016],"type":"Point"}
}