{
  "type": "Feature",
  "properties": {
    "iso:country":"IN",
    "ks:ks_alt_nam":"khoparia",
    "ks:ks_name":"Khoparia",
    "ks:ks_pop":684,
    "ks:ks_type":"HABITATION",
    "ks:ks_uagg_main":0,
    "name:eng_x_preferred":[
        "Khoparia"
    ],
    "wof:name":"Khoparia",
    "wof:placetype":"neighbourhood",
    "wof:population":684
},
  "geometry": {"coordinates":[87.039474,25.473023],"type":"Point"}
}