{
  "type": "Feature",
  "properties": {
    "gn:admin1_code":"34.0",
    "gn:admin2_code":"235.0",
    "gn:asciiname":"Bulli Bigha",
    "gn:country_code":"IN",
    "gn:dem":107,
    "gn:feature_class":"P",
    "gn:feature_code":"PPL",
    "gn:name":"Bulli Bigha",
    "gn:population":0,
    "gn:timezone":"Asia/Kolkata",
    "iso:country":"IN",
    "ks:ks_name":"Bulli Bigaha",
    "ks:ks_pop":0,
    "ks:ks_type":"VILLAGE",
    "name:eng_x_preferred":[
        "Bulli Bigaha"
    ],
    "name:eng_x_variant":[
        "Bulli Bigha"
    ],
    "wof:name":"Bulli Bigaha",
    "wof:placetype":"locality",
    "wof:population":0
},
  "geometry": {"coordinates":[84.276563,24.810456],"type":"Point"}
}