{
  "type": "Feature",
  "properties": {
    "gn:admin1_code":"35",
    "gn:admin2_code":"430.0",
    "gn:asciiname":"Goirar",
    "gn:country_code":"IN",
    "gn:dem":388,
    "gn:feature_class":"P",
    "gn:feature_code":"PPL",
    "gn:name":"Goir\u0101r",
    "gn:population":0,
    "gn:timezone":"Asia/Kolkata",
    "iso:country":"IN",
    "ks:ks_name":"Goidar",
    "ks:ks_pop":681,
    "ks:ks_type":"HABITATION",
    "name:eng_x_preferred":[
        "Goidar"
    ],
    "name:eng_x_variant":[
        "Goirar"
    ],
    "wof:name":"Goidar",
    "wof:placetype":"locality",
    "wof:population":681
},
  "geometry": {"coordinates":[82.22131,24.708294],"type":"Point"}
}