{
  "type": "Feature",
  "properties": {
    "iso:country":"IN",
    "ks:ks_alt_nam":"Ekad\u0101l",
    "ks:ks_name":"Ekadal",
    "ks:ks_type":"VILLAGE",
    "ks:ks_uagg_main":0,
    "name:eng_x_preferred":[
        "Ekadal"
    ],
    "name:eng_x_variant":[
        "Ekad\u0101l"
    ],
    "wof:name":"Ekadal",
    "wof:placetype":"neighbourhood"
},
  "geometry": {"coordinates":[85.130106,20.409781],"type":"Point"}
}