{
  "type": "Feature",
  "properties": {
    "gn:admin1_code":"40.0",
    "gn:admin2_code":"534.0",
    "gn:asciiname":"Vitampeta",
    "gn:country_code":"IN",
    "gn:dem":344,
    "gn:feature_class":"P",
    "gn:feature_code":"PPL",
    "gn:name":"Vitampeta",
    "gn:population":0,
    "gn:timezone":"Asia/Kolkata",
    "iso:country":"IN",
    "wof:name":"Vitampeta",
    "wof:placetype":"locality"
},
  "geometry": {"coordinates":[78.58851,18.80207],"type":"Point"}
}