{
  "type": "Feature",
  "properties": {
    "gn:admin1_code":"36",
    "gn:admin2_code":"155.0",
    "gn:asciiname":"Basilia",
    "gn:country_code":"IN",
    "gn:dem":147,
    "gn:feature_class":"P",
    "gn:feature_code":"PPL",
    "gn:name":"Basilia",
    "gn:population":0,
    "gn:timezone":"Asia/Kolkata",
    "iso:country":"IN",
    "name:deu_x_preferred":[
        "Basilia"
    ],
    "name:lat_x_preferred":[
        "Basilia"
    ],
    "name:swe_x_preferred":[
        "Basilia"
    ],
    "wof:name":"Basilia",
    "wof:placetype":"locality"
},
  "geometry": {"coordinates":[79.82642,27.4833],"type":"Point"}
}