{
  "type": "Feature",
  "properties": {
    "gn:admin1_code":"34.0",
    "gn:admin2_code":"234.0",
    "gn:asciiname":"Ahibaran Bigha",
    "gn:country_code":"IN",
    "gn:dem":108,
    "gn:feature_class":"P",
    "gn:feature_code":"PPL",
    "gn:name":"Ahibaran Bigha",
    "gn:population":0,
    "gn:timezone":"Asia/Kolkata",
    "iso:country":"IN",
    "wof:name":"Ahibaran Bigha",
    "wof:placetype":"locality"
},
  "geometry": {"coordinates":[84.1481,24.987],"type":"Point"}
}