{
  "type": "Feature",
  "properties": {
    "iso:country":"IN",
    "ks:ks_name":"Thumakodu",
    "ks:ks_pop":68,
    "ks:ks_type":"HABITATION",
    "name:eng_x_preferred":[
        "Thumakodu"
    ],
    "wof:name":"Thumakodu",
    "wof:placetype":"locality",
    "wof:population":68
},
  "geometry": {"coordinates":[75.007211,13.77964],"type":"Point"}
}