{
  "type": "Feature",
  "properties": {
    "iso:country":"IN",
    "ks:ks_name":"Inkanalli",
    "ks:ks_pop":195,
    "ks:ks_type":"HABITATION",
    "name:eng_x_preferred":[
        "Inkanalli"
    ],
    "wof:name":"Inkanalli",
    "wof:placetype":"locality",
    "wof:population":195
},
  "geometry": {"coordinates":[75.813333,12.6625],"type":"Point"}
}