{
  "type": "Feature",
  "properties": {
    "iso:country":"IN",
    "ks:ks_name":"Hunsekatte",
    "ks:ks_pop":120,
    "ks:ks_type":"HABITATION",
    "name:eng_x_preferred":[
        "Hunsekatte"
    ],
    "wof:name":"Hunsekatte",
    "wof:placetype":"locality",
    "wof:population":120
},
  "geometry": {"coordinates":[74.708761,13.614198],"type":"Point"}
}