{
  "type": "Feature",
  "properties": {
    "iso:country":"IN",
    "ks:ks_name":"Harduwa",
    "ks:ks_pop":0,
    "ks:ks_type":"VILLAGE",
    "name:eng_x_preferred":[
        "Harduwa"
    ],
    "wof:name":"Harduwa",
    "wof:placetype":"locality",
    "wof:population":0
},
  "geometry": {"coordinates":[77.955939,25.156226],"type":"Point"}
}