{
  "type": "Feature",
  "properties": {
    "iso:country":"IN",
    "ks:ks_name":"Dasiadih",
    "ks:ks_pop":346,
    "ks:ks_type":"VILLAGE",
    "name:eng_x_preferred":[
        "Dasiadih"
    ],
    "wof:name":"Dasiadih",
    "wof:placetype":"locality",
    "wof:population":346
},
  "geometry": {"coordinates":[85.90134399999999,22.755275],"type":"Point"}
}