{
  "type": "Feature",
  "properties": {
    "iso:country":"IN",
    "ks:ks_alt_nam":"kairoowala",
    "ks:ks_name":"Kairoowala",
    "ks:ks_pop":267,
    "ks:ks_type":"HABITATION",
    "name:eng_x_preferred":[
        "Kairoowala"
    ],
    "wof:name":"Kairoowala",
    "wof:placetype":"locality",
    "wof:population":267
},
  "geometry": {"coordinates":[72.606306,28.511808],"type":"Point"}
}