{
  "type": "Feature",
  "properties": {
    "iso:country":"IN",
    "ks:ks_name":"Vincholli",
    "ks:ks_pop":22,
    "ks:ks_type":"VILLAGE",
    "name:eng_x_preferred":[
        "Vincholli"
    ],
    "wof:name":"Vincholli",
    "wof:placetype":"locality",
    "wof:population":22
},
  "geometry": {"coordinates":[74.717904,15.131192],"type":"Point"}
}