{
  "type": "Feature",
  "properties": {
    "gn:admin1_code":"30.0",
    "gn:admin2_code":"260",
    "gn:asciiname":"Dong",
    "gn:country_code":"IN",
    "gn:dem":1212,
    "gn:feature_class":"P",
    "gn:feature_code":"PPL",
    "gn:name":"Dong",
    "gn:population":0,
    "gn:timezone":"Asia/Kolkata",
    "iso:country":"IN",
    "name:ara_x_preferred":[
        "\u062f\u0648\u0646\u063a"
    ],
    "name:ben_x_preferred":[
        "\u09a1\u0982"
    ],
    "name:ell_x_preferred":[
        "\u039d\u03c4\u03bf\u03bd\u03b3\u03ba"
    ],
    "name:fas_x_preferred":[
        "\u062f\u0648\u0646\u06af"
    ],
    "name:heb_x_preferred":[
        "\u05d3\u05d5\u05e0\u05d2"
    ],
    "name:hun_x_preferred":[
        "Dong"
    ],
    "name:ind_x_preferred":[
        "Dong"
    ],
    "name:ita_x_preferred":[
        "Dong"
    ],
    "name:nld_x_preferred":[
        "Dong"
    ],
    "name:por_x_preferred":[
        "Dong"
    ],
    "name:tur_x_preferred":[
        "Dong"
    ],
    "name:ukr_x_preferred":[
        "\u0414\u043e\u043d\u0433"
    ],
    "name:urd_x_preferred":[
        "\u0688\u0627\u0646\u06af"
    ],
    "wof:name":"Dong",
    "wof:placetype":"locality"
},
  "geometry": {"coordinates":[97.03780999999999,28.16964],"type":"Point"}
}