{
  "type": "Feature",
  "properties": {
    "gn:admin1_code":"30.0",
    "gn:admin2_code":"260",
    "gn:asciiname":"Dong",
    "gn:country_code":"IN",
    "gn:dem":1212,
    "gn:feature_class":"P",
    "gn:feature_code":"PPL",
    "gn:name":"Dong",
    "gn:population":0,
    "gn:timezone":"Asia/Kolkata",
    "iso:country":"IN",
    "name:ukr_x_preferred":[
        "\u0414\u043e\u043d\u0433"
    ],
    "wof:name":"Dong",
    "wof:placetype":"locality"
},
  "geometry": {"coordinates":[97.03780999999999,28.16964],"type":"Point"}
}