{
  "type": "Feature",
  "properties": {
    "iso:country":"IN",
    "ks:ks_name":"Moramaguda",
    "ks:ks_pop":100,
    "ks:ks_type":"HABITATION",
    "name:eng_x_preferred":[
        "Moramaguda"
    ],
    "wof:name":"Moramaguda",
    "wof:placetype":"locality",
    "wof:population":100
},
  "geometry": {"coordinates":[83.62586899999999,18.984943],"type":"Point"}
}