{
  "type": "Feature",
  "properties": {
    "iso:country":"IN",
    "ks:ks_name":"Bhurasar",
    "ks:ks_pop":304,
    "ks:ks_type":"HABITATION",
    "name:eng_x_preferred":[
        "Bhurasar"
    ],
    "wof:name":"Bhurasar",
    "wof:placetype":"locality",
    "wof:population":304
},
  "geometry": {"coordinates":[71.925102,26.507034],"type":"Point"}
}