{
  "type": "Feature",
  "properties": {
    "iso:country":"IN",
    "ks:ks_alt_nam":"NERWA",
    "ks:ks_name":"Nerwa",
    "ks:ks_pop":42,
    "ks:ks_type":"HABITATION",
    "name:eng_x_preferred":[
        "Nerwa"
    ],
    "wof:name":"Nerwa",
    "wof:placetype":"locality",
    "wof:population":42
},
  "geometry": {"coordinates":[82.19880999999999,26.456639],"type":"Point"}
}