{
  "type": "Feature",
  "properties": {
    "iso:country":"IN",
    "ks:ks_name":"Chacha Basti",
    "ks:ks_pop":285,
    "ks:ks_type":"HABITATION",
    "ks:ks_uagg_main":0,
    "name:eng_x_preferred":[
        "Chacha Basti"
    ],
    "wof:name":"Chacha Basti",
    "wof:placetype":"neighbourhood",
    "wof:population":285
},
  "geometry": {"coordinates":[94.956611,27.009897],"type":"Point"}
}