{
  "type": "Feature",
  "properties": {
    "iso:country":"IN",
    "ks:ks_name":"Manappally",
    "ks:ks_pop":1997,
    "ks:ks_type":"HABITATION",
    "name:eng_x_preferred":[
        "Manappally"
    ],
    "wof:name":"Manappally",
    "wof:placetype":"locality",
    "wof:population":1997
},
  "geometry": {"coordinates":[76.573019,9.106739],"type":"Point"}
}