{
  "type": "Feature",
  "properties": {
    "iso:country":"IN",
    "ks:ks_name":"Fatepur",
    "ks:ks_pop":107,
    "ks:ks_type":"VILLAGE",
    "name:eng_x_preferred":[
        "Fatepur"
    ],
    "wof:name":"Fatepur",
    "wof:placetype":"locality",
    "wof:population":107
},
  "geometry": {"coordinates":[86.897021,23.54058],"type":"Point"}
}