{
  "type": "Feature",
  "properties": {
    "iso:country":"IN",
    "ks:ks_name":"Bendhapada",
    "ks:ks_pop":130,
    "ks:ks_type":"HABITATION",
    "name:eng_x_preferred":[
        "Bendhapada"
    ],
    "wof:name":"Bendhapada",
    "wof:placetype":"locality",
    "wof:population":130
},
  "geometry": {"coordinates":[82.633512,21.073427],"type":"Point"}
}