{
  "type": "Feature",
  "properties": {
    "gn:admin1_code":"25.0",
    "gn:admin2_code":"607.0",
    "gn:asciiname":"Kulirsunai",
    "gn:country_code":"IN",
    "gn:dem":101,
    "gn:feature_class":"P",
    "gn:feature_code":"PPL",
    "gn:name":"Kulirsunai",
    "gn:population":0,
    "gn:timezone":"Asia/Kolkata",
    "iso:country":"IN",
    "ks:ks_name":"Kulirsunai",
    "ks:ks_pop":565,
    "ks:ks_type":"VILLAGE",
    "ks:ks_uagg_main":0,
    "name:eng_x_preferred":[
        "Kulirsunai"
    ],
    "wof:name":"Kulirsunai",
    "wof:placetype":"neighbourhood",
    "wof:population":565
},
  "geometry": {"coordinates":[79.343479,12.042025],"type":"Point"}
}