{
  "type": "Feature",
  "properties": {
    "iso:country":"IN",
    "ks:ks_alt_nam":"Chala Kura Pt.I",
    "ks:ks_name":"Chala Kura Pt.i",
    "ks:ks_pop":564,
    "ks:ks_type":"HABITATION",
    "name:eng_x_preferred":[
        "Chala Kura Pt.i"
    ],
    "wof:name":"Chala Kura Pt.i",
    "wof:placetype":"locality",
    "wof:population":564
},
  "geometry": {"coordinates":[90.020881,26.028696],"type":"Point"}
}