{
  "type": "Feature",
  "properties": {
    "iso:country":"IN",
    "ks:ks_name":"Padanna Bazar",
    "ks:ks_pop":2116,
    "ks:ks_type":"HABITATION",
    "ks:ks_uagg_main":0,
    "name:eng_x_preferred":[
        "Padanna Bazar"
    ],
    "wof:name":"Padanna Bazar",
    "wof:placetype":"locality",
    "wof:population":2116
},
  "geometry": {"coordinates":[75.143416,12.189039],"type":"Point"}
}