{
  "type": "Feature",
  "properties": {
    "gn:admin1_code":"36",
    "gn:admin2_code":"181.0",
    "gn:asciiname":"Tiwari Purwa",
    "gn:country_code":"IN",
    "gn:dem":122,
    "gn:feature_class":"P",
    "gn:feature_code":"PPL",
    "gn:name":"Tiw\u0101ri Purwa",
    "gn:population":0,
    "gn:timezone":"Asia/Kolkata",
    "iso:country":"IN",
    "wof:name":"Tiwari Purwa",
    "wof:placetype":"neighbourhood"
},
  "geometry": {"coordinates":[81.89471,27.73227],"type":"Point"}
}