{
  "type": "Feature",
  "properties": {
    "iso:country":"IN",
    "ks:ks_name":"Hathisola Gaon",
    "ks:ks_pop":506,
    "ks:ks_type":"HABITATION",
    "name:eng_x_preferred":[
        "Hathisola Gaon"
    ],
    "wof:name":"Hathisola Gaon",
    "wof:placetype":"locality",
    "wof:population":506
},
  "geometry": {"coordinates":[91.17111,26.080022],"type":"Point"}
}