{
  "type": "Feature",
  "properties": {
    "iso:country":"IN",
    "ks:ks_alt_nam":"M\u0101npura",
    "ks:ks_name":"Manpura",
    "ks:ks_type":"VILLAGE",
    "name:eng_x_preferred":[
        "Manpura"
    ],
    "name:eng_x_variant":[
        "M\u0101npura"
    ],
    "wof:name":"Manpura",
    "wof:placetype":"locality"
},
  "geometry": {"coordinates":[76.313534,24.418444],"type":"Point"}
}