{
  "type": "Feature",
  "properties": {
    "iso:country":"IN",
    "ks:ks_name":"Bich Tola",
    "ks:ks_pop":425,
    "ks:ks_type":"HABITATION",
    "ks:ks_uagg_main":0,
    "name:eng_x_preferred":[
        "Bich Tola"
    ],
    "wof:name":"Bich Tola",
    "wof:placetype":"neighbourhood",
    "wof:population":425
},
  "geometry": {"coordinates":[84.462029,26.165556],"type":"Point"}
}