{
  "type": "Feature",
  "properties": {
    "iso:country":"IN",
    "ks:ks_name":"Kolur Colony",
    "ks:ks_pop":367,
    "ks:ks_type":"HABITATION",
    "name:eng_x_preferred":[
        "Kolur Colony"
    ],
    "wof:name":"Kolur Colony",
    "wof:placetype":"locality",
    "wof:population":367
},
  "geometry": {"coordinates":[80.16139,13.361615],"type":"Point"}
}