{
  "type": "Feature",
  "properties": {
    "iso:country":"IN",
    "ks:ks_name":"Kudasasansamildurgapur",
    "ks:ks_pop":343,
    "ks:ks_type":"VILLAGE",
    "ks:ks_uagg_main":0,
    "name:eng_x_preferred":[
        "Kudasasansamildurgapur"
    ],
    "wof:name":"Kudasasansamildurgapur",
    "wof:placetype":"neighbourhood",
    "wof:population":343
},
  "geometry": {"coordinates":[86.82957,21.698546],"type":"Point"}
}