{
  "type": "Feature",
  "properties": {
    "gn:admin1_code":"35",
    "gn:admin2_code":"452.0",
    "gn:asciiname":"Tendukheda",
    "gn:country_code":"IN",
    "gn:dem":348,
    "gn:feature_class":"P",
    "gn:feature_code":"PPL",
    "gn:name":"Tend\u016bkheda",
    "gn:population":0,
    "gn:timezone":"Asia/Kolkata",
    "iso:country":"IN",
    "name:und_x_variant":[
        "Tend\u016bkhedn",
        "Tend\u016bkheda"
    ],
    "wof:name":"Tendukheda",
    "wof:placetype":"locality"
},
  "geometry": {"coordinates":[78.87238000000001,23.17085],"type":"Point"}
}