{
  "type": "Feature",
  "properties": {
    "iso:country":"IN",
    "name:ara_x_preferred":[
        "\u062c\u0648\u062c\u0648\u0644\u0627"
    ],
    "name:ast_x_preferred":[
        "Gokula"
    ],
    "name:ben_bn_x_preferred":[
        "\u0997\u09cb\u0995\u09c1\u09b2"
    ],
    "name:ben_in_x_preferred":[
        "\u0997\u09cb\u0995\u09c1\u09b2"
    ],
    "name:eng_x_preferred":[
        "Gokula"
    ],
    "name:guj_x_preferred":[
        "\u0a97\u0acb\u0a95\u0ac1\u0ab2\u0abe"
    ],
    "name:hin_x_preferred":[
        "\u0917\u094b\u0915\u0941\u0932\u093e"
    ],
    "name:hin_x_variant":[
        "\u0917\u094b\u0915\u0941\u0932 \u0938\u093f\u0902\u0939"
    ],
    "name:kan_x_preferred":[
        "\u0c97\u0ccb\u0c95\u0cc1\u0cb2"
    ],
    "name:mal_x_preferred":[
        "\u0d17\u0d4b\u0d15\u0d41\u0d32"
    ],
    "name:mar_x_preferred":[
        "\u0917\u094b\u0915\u0941\u0933\u093e"
    ],
    "name:nld_x_preferred":[
        "Gokula"
    ],
    "name:pan_x_preferred":[
        "\u0a17\u0a4b\u0a15\u0a41\u0a32\u0a3e"
    ],
    "name:spa_x_preferred":[
        "Gokula"
    ],
    "name:tam_x_preferred":[
        "\u0b95\u0bcb\u0b95\u0bc1\u0bb2\u0bbe"
    ],
    "name:tel_x_preferred":[
        "\u0c17\u0c4b\u0c15\u0c41\u0c32"
    ],
    "name:urd_x_preferred":[
        "\u06af\u0648\u06a9\u0648\u0644\u0627"
    ],
    "name:zho_x_preferred":[
        "\u6208\u5eab\u62c9"
    ],
    "qs:gn_adm0_cc":"IN",
    "qs:gn_fcode":"PPL",
    "qs:gn_local":1262321,
    "qs:gn_nam_loc":"Mysore, Karnataka, Mysore, IN",
    "qs:gn_namadm1":"19",
    "qs:gn_name":"Gokula",
    "qs:local_max":3824,
    "qs:local_sum":6741,
    "qs:localhoods":11,
    "qs:name":"Gokula",
    "qs:name_adm0":"India",
    "qs:name_adm1":"Karnataka",
    "qs:name_adm2":"Mysore",
    "qs:name_local":"Mysore",
    "qs:photo_max":30,
    "qs:photo_sum":75,
    "qs:placetype":"Suburb",
    "qs:quad_count":9,
    "qs:woe_adm0":23424848,
    "qs:woe_adm1":2345753,
    "qs:woe_adm2":12586586,
    "qs:woe_lau":0,
    "qs:woe_local":2295421,
    "qs:woe_ver":"7.10.0",
    "wd:wordcount":1407,
    "wof:lang":[
        "eng"
    ],
    "wof:name":"Gokula",
    "wof:placetype":"neighbourhood"
},
  "geometry": {"coordinates":[76.62901100000001,12.332631],"type":"Point"}
}