{
  "type": "Feature",
  "properties": {
    "iso:country":"IN",
    "name:eng_x_preferred":[
        "Gokula"
    ],
    "name:hin_x_preferred":[
        "\u0917\u094b\u0915\u0941\u0932 \u0938\u093f\u0902\u0939"
    ],
    "name:unk_x_variant":[
        "Gokula"
    ],
    "qs:gn_adm0_cc":"IN",
    "qs:gn_fcode":"PPL",
    "qs:gn_local":1262321,
    "qs:gn_nam_loc":"Mysore, Karnataka, Mysore, IN",
    "qs:gn_namadm1":"19",
    "qs:gn_name":"Gokula",
    "qs:local_max":3824,
    "qs:local_sum":6741,
    "qs:localhoods":11,
    "qs:name":"Gokula",
    "qs:name_adm0":"India",
    "qs:name_adm1":"Karnataka",
    "qs:name_adm2":"Mysore",
    "qs:name_local":"Mysore",
    "qs:photo_max":30,
    "qs:photo_sum":75,
    "qs:placetype":"Suburb",
    "qs:quad_count":9,
    "qs:woe_adm0":23424848,
    "qs:woe_adm1":2345753,
    "qs:woe_adm2":12586586,
    "qs:woe_lau":0,
    "qs:woe_local":2295421,
    "qs:woe_ver":"7.10.0",
    "wd:wordcount":1407,
    "wof:lang":[
        "eng"
    ],
    "wof:name":"Gokula",
    "wof:placetype":"neighbourhood"
},
  "geometry": {"coordinates":[76.62901100000001,12.332631],"type":"Point"}
}