{
  "type": "Feature",
  "properties": {
    "iso:country":"IN",
    "ks:ks_name":"Dovari",
    "ks:ks_pop":388,
    "ks:ks_type":"VILLAGE",
    "name:eng_x_preferred":[
        "Dovari"
    ],
    "wof:name":"Dovari",
    "wof:placetype":"locality",
    "wof:population":388
},
  "geometry": {"coordinates":[78.57212800000001,30.082477],"type":"Point"}
}