{
  "type": "Feature",
  "properties": {
    "iso:country":"IN",
    "ks:ks_name":"No 1 Machaki Tongani",
    "ks:ks_pop":687,
    "ks:ks_type":"HABITATION",
    "name:eng_x_preferred":[
        "No 1 Machaki Tongani"
    ],
    "wof:name":"No 1 Machaki Tongani",
    "wof:placetype":"locality",
    "wof:population":687
},
  "geometry": {"coordinates":[94.782325,27.537546],"type":"Point"}
}