{
  "type": "Feature",
  "properties": {
    "iso:country":"IN",
    "ks:ks_name":"Bargadi Magath",
    "ks:ks_pop":3651,
    "ks:ks_type":"VILLAGE",
    "ks:ks_uagg_main":0,
    "name:eng_x_preferred":[
        "Bargadi Magath"
    ],
    "wof:name":"Bargadi Magath",
    "wof:placetype":"neighbourhood",
    "wof:population":3651
},
  "geometry": {"coordinates":[80.927296,26.982519],"type":"Point"}
}