{
  "type": "Feature",
  "properties": {
    "iso:country":"IN",
    "ks:ks_name":"Yadv Tola",
    "ks:ks_pop":157,
    "ks:ks_type":"HABITATION",
    "name:eng_x_preferred":[
        "Yadv Tola"
    ],
    "wof:name":"Yadv Tola",
    "wof:placetype":"locality",
    "wof:population":157
},
  "geometry": {"coordinates":[86.31718100000001,24.744331],"type":"Point"}
}