{
  "type": "Feature",
  "properties": {
    "iso:country":"IN",
    "ks:ks_name":"Charipada1",
    "ks:ks_pop":589,
    "ks:ks_type":"HABITATION",
    "name:eng_x_preferred":[
        "Charipada1"
    ],
    "wof:name":"Charipada1",
    "wof:placetype":"locality",
    "wof:population":589
},
  "geometry": {"coordinates":[85.673936,20.068713],"type":"Point"}
}