{
  "type": "Feature",
  "properties": {
    "iso:country":"IN",
    "ks:ks_name":"Rupabad",
    "ks:ks_pop":232,
    "ks:ks_type":"HABITATION",
    "name:eng_x_preferred":[
        "Rupabad"
    ],
    "wof:name":"Rupabad",
    "wof:placetype":"locality",
    "wof:population":232
},
  "geometry": {"coordinates":[86.728567,24.229352],"type":"Point"}
}