{
  "type": "Feature",
  "properties": {
    "gn:admin1_code":"35",
    "gn:admin2_code":"436.0",
    "gn:asciiname":"Kalmoi",
    "gn:country_code":"IN",
    "gn:dem":423,
    "gn:feature_class":"P",
    "gn:feature_code":"PPL",
    "gn:name":"Kalmoi",
    "gn:population":0,
    "gn:timezone":"Asia/Kolkata",
    "iso:country":"IN",
    "wof:name":"Kalmoi",
    "wof:placetype":"locality"
},
  "geometry": {"coordinates":[76.16951999999998,23.60834],"type":"Point"}
}