{
  "type": "Feature",
  "properties": {
    "iso:country":"IN",
    "ks:ks_name":"Gaud Rumacolonysahi",
    "ks:ks_pop":523,
    "ks:ks_type":"VILLAGE",
    "name:eng_x_preferred":[
        "Gaud Rumacolonysahi"
    ],
    "wof:name":"Gaud Rumacolonysahi",
    "wof:placetype":"locality",
    "wof:population":523
},
  "geometry": {"coordinates":[86.669805,21.978109],"type":"Point"}
}