{
  "type": "Feature",
  "properties": {
    "iso:country":"IN",
    "ks:ks_name":"Santajoy Para",
    "ks:ks_pop":49,
    "ks:ks_type":"HABITATION",
    "ks:ks_uagg_main":0,
    "name:eng_x_preferred":[
        "Santajoy Para"
    ],
    "wof:name":"Santajoy Para",
    "wof:placetype":"neighbourhood",
    "wof:population":49
},
  "geometry": {"coordinates":[91.810109,23.659443],"type":"Point"}
}