{
  "type": "Feature",
  "properties": {
    "iso:country":"IN",
    "ks:ks_name":"Thotlapalem",
    "ks:ks_pop":954,
    "ks:ks_type":"HABITATION",
    "name:eng_x_preferred":[
        "Thotlapalem"
    ],
    "wof:name":"Thotlapalem",
    "wof:placetype":"locality",
    "wof:population":954
},
  "geometry": {"coordinates":[81.960943,16.543717],"type":"Point"}
}