{
  "type": "Feature",
  "properties": {
    "gn:admin1_code":"19.0",
    "gn:admin2_code":"570.0",
    "gn:asciiname":"Kumbardi",
    "gn:country_code":"IN",
    "gn:dem":957,
    "gn:feature_class":"P",
    "gn:feature_code":"PPL",
    "gn:name":"Kumbardi",
    "gn:population":0,
    "gn:timezone":"Asia/Kolkata",
    "iso:country":"IN",
    "ks:ks_name":"Kumbaradi",
    "ks:ks_pop":137,
    "ks:ks_type":"HABITATION",
    "name:eng_x_preferred":[
        "Kumbaradi"
    ],
    "name:eng_x_variant":[
        "Kumbardi"
    ],
    "wof:name":"Kumbaradi",
    "wof:placetype":"locality",
    "wof:population":137
},
  "geometry": {"coordinates":[75.58095299999999,13.025846],"type":"Point"}
}