{
  "type": "Feature",
  "properties": {
    "iso:country":"IN",
    "ks:ks_name":"Chandha Urf Patlapur",
    "ks:ks_pop":314,
    "ks:ks_type":"VILLAGE",
    "ks:ks_uagg_main":0,
    "name:eng_x_preferred":[
        "Chandha Urf Patlapur"
    ],
    "wof:name":"Chandha Urf Patlapur",
    "wof:placetype":"neighbourhood",
    "wof:population":314
},
  "geometry": {"coordinates":[83.87597,26.335919],"type":"Point"}
}