{
  "type": "Feature",
  "properties": {
    "iso:country":"IN",
    "ks:ks_name":"Belekarwadi",
    "ks:ks_pop":500,
    "ks:ks_type":"HABITATION",
    "name:eng_x_preferred":[
        "Belekarwadi"
    ],
    "wof:name":"Belekarwadi",
    "wof:placetype":"locality",
    "wof:population":500
},
  "geometry": {"coordinates":[74.034903,16.733036],"type":"Point"}
}