{
  "type": "Feature",
  "properties": {
    "iso:country":"IN",
    "ks:ks_alt_nam":"balebalpu st calony",
    "ks:ks_name":"Balebalpu St Calony",
    "ks:ks_pop":16,
    "ks:ks_type":"HABITATION",
    "name:eng_x_preferred":[
        "Balebalpu St Calony"
    ],
    "wof:name":"Balebalpu St Calony",
    "wof:placetype":"locality",
    "wof:population":16
},
  "geometry": {"coordinates":[75.363649,12.5125],"type":"Point"}
}