{
  "type": "Feature",
  "properties": {
    "iso:country":"IN",
    "ks:ks_name":"Panaivilai",
    "ks:ks_pop":165,
    "ks:ks_type":"HABITATION",
    "name:eng_x_preferred":[
        "Panaivilai"
    ],
    "wof:name":"Panaivilai",
    "wof:placetype":"locality",
    "wof:population":165
},
  "geometry": {"coordinates":[77.68609499999999,8.211103],"type":"Point"}
}