{
  "type": "Feature",
  "properties": {
    "iso:country":"IN",
    "ks:ks_name":"Chattupara",
    "ks:ks_pop":510,
    "ks:ks_type":"HABITATION",
    "name:eng_x_preferred":[
        "Chattupara"
    ],
    "wof:name":"Chattupara",
    "wof:placetype":"locality",
    "wof:population":510
},
  "geometry": {"coordinates":[76.685219,9.939398],"type":"Point"}
}