{
  "type": "Feature",
  "properties": {
    "gn:admin1_code":"25.0",
    "gn:admin2_code":"602.0",
    "gn:asciiname":"Gunnam",
    "gn:country_code":"IN",
    "gn:dem":64,
    "gn:feature_class":"P",
    "gn:feature_code":"PPL",
    "gn:name":"Gunnam",
    "gn:population":0,
    "gn:timezone":"Asia/Kolkata",
    "iso:country":"IN",
    "wof:name":"Gunnam",
    "wof:placetype":"locality"
},
  "geometry": {"coordinates":[79.70971999999998,13.20967],"type":"Point"}
}