{
  "type": "Feature",
  "properties": {
    "iso:country":"IN",
    "ks:ks_name":"Janumpiri",
    "ks:ks_pop":50,
    "ks:ks_type":"HABITATION",
    "name:eng_x_preferred":[
        "Janumpiri"
    ],
    "wof:name":"Janumpiri",
    "wof:placetype":"locality",
    "wof:population":50
},
  "geometry": {"coordinates":[85.786636,23.072719],"type":"Point"}
}