{
  "type": "Feature",
  "properties": {
    "iso:country":"IN",
    "ks:ks_name":"Kalammanagudda",
    "ks:ks_pop":6,
    "ks:ks_type":"HABITATION",
    "name:eng_x_preferred":[
        "Kalammanagudda"
    ],
    "wof:name":"Kalammanagudda",
    "wof:placetype":"locality",
    "wof:population":6
},
  "geometry": {"coordinates":[76.44219,13.385896],"type":"Point"}
}