{
  "type": "Feature",
  "properties": {
    "iso:country":"IN",
    "ks:ks_name":"Valiyaparambu",
    "ks:ks_pop":470,
    "ks:ks_type":"HABITATION",
    "name:eng_x_preferred":[
        "Valiyaparambu"
    ],
    "wof:name":"Valiyaparambu",
    "wof:placetype":"locality",
    "wof:population":470
},
  "geometry": {"coordinates":[75.78783900000001,11.520317],"type":"Point"}
}