{
  "type": "Feature",
  "properties": {
    "iso:country":"IN",
    "ks:ks_name":"Sateti Patti Sukhat",
    "ks:ks_pop":890,
    "ks:ks_type":"VILLAGE",
    "name:eng_x_preferred":[
        "Sateti Patti Sukhat"
    ],
    "wof:name":"Sateti Patti Sukhat",
    "wof:placetype":"locality",
    "wof:population":890
},
  "geometry": {"coordinates":[78.95571700000001,28.115171],"type":"Point"}
}