{
  "type": "Feature",
  "properties": {
    "iso:country":"IN",
    "ks:ks_name":"Lakhanpurwa",
    "ks:ks_pop":90,
    "ks:ks_type":"HABITATION",
    "name:eng_x_preferred":[
        "Lakhanpurwa"
    ],
    "wof:name":"Lakhanpurwa",
    "wof:placetype":"locality",
    "wof:population":90
},
  "geometry": {"coordinates":[81.59491800000001,27.008739],"type":"Point"}
}