{
  "type": "Feature",
  "properties": {
    "iso:country":"IN",
    "ks:ks_name":"Kavare Wasti",
    "ks:ks_pop":369,
    "ks:ks_type":"HABITATION",
    "ks:ks_uagg_main":0,
    "name:eng_x_preferred":[
        "Kavare Wasti"
    ],
    "wof:name":"Kavare Wasti",
    "wof:placetype":"neighbourhood",
    "wof:population":369
},
  "geometry": {"coordinates":[75.06756300000001,19.438636],"type":"Point"}
}