{
  "type": "Feature",
  "properties": {
    "gn:admin1_code":"34.0",
    "gn:admin2_code":"221.0",
    "gn:asciiname":"Darhia Belar",
    "gn:country_code":"IN",
    "gn:dem":55,
    "gn:feature_class":"P",
    "gn:feature_code":"PPL",
    "gn:name":"Darhia Bel\u0101r",
    "gn:population":0,
    "gn:timezone":"Asia/Kolkata",
    "iso:country":"IN",
    "ks:ks_name":"Darhia Belar",
    "ks:ks_pop":2441,
    "ks:ks_type":"VILLAGE",
    "name:eng_x_preferred":[
        "Darhia Belar"
    ],
    "wof:name":"Darhia Belar",
    "wof:placetype":"locality",
    "wof:population":2441
},
  "geometry": {"coordinates":[85.7265,25.854608],"type":"Point"}
}