{
  "type": "Feature",
  "properties": {
    "iso:country":"IN",
    "ks:ks_name":"Itadi",
    "ks:ks_pop":585,
    "ks:ks_type":"VILLAGE",
    "ks:ks_uagg_main":0,
    "name:eng_x_preferred":[
        "Itadi"
    ],
    "wof:name":"Itadi",
    "wof:placetype":"neighbourhood",
    "wof:population":585
},
  "geometry": {"coordinates":[73.07984999999999,23.762728],"type":"Point"}
}