{
  "type": "Feature",
  "properties": {
    "iso:country":"IN",
    "ks:ks_name":"Kulharitola",
    "ks:ks_pop":13,
    "ks:ks_type":"HABITATION",
    "name:eng_x_preferred":[
        "Kulharitola"
    ],
    "wof:name":"Kulharitola",
    "wof:placetype":"locality",
    "wof:population":13
},
  "geometry": {"coordinates":[80.76488999999999,20.820368],"type":"Point"}
}