{
  "type": "Feature",
  "properties": {
    "iso:country":"IN",
    "ks:ks_name":"Meena Dhani Babulal Wali",
    "ks:ks_pop":160,
    "ks:ks_type":"HABITATION",
    "name:eng_x_preferred":[
        "Meena Dhani Babulal Wali"
    ],
    "wof:name":"Meena Dhani Babulal Wali",
    "wof:placetype":"locality",
    "wof:population":160
},
  "geometry": {"coordinates":[76.314708,26.124092],"type":"Point"}
}