{
  "type": "Feature",
  "properties": {
    "iso:country":"IN",
    "ks:ks_name":"Daregadde",
    "ks:ks_pop":10,
    "ks:ks_type":"HABITATION",
    "name:eng_x_preferred":[
        "Daregadde"
    ],
    "wof:name":"Daregadde",
    "wof:placetype":"locality",
    "wof:population":10
},
  "geometry": {"coordinates":[74.73599299999999,14.045742],"type":"Point"}
}