{
  "type": "Feature",
  "properties": {
    "gn:admin1_code":"12.0",
    "gn:admin2_code":"6.0",
    "gn:asciiname":"Gurdan Bala",
    "gn:country_code":"IN",
    "gn:dem":1055,
    "gn:feature_class":"P",
    "gn:feature_code":"PPL",
    "gn:name":"Gurdan B\u0101la",
    "gn:population":0,
    "gn:timezone":"Asia/Kolkata",
    "iso:country":"IN",
    "wof:name":"Gurdan Bala",
    "wof:placetype":"locality"
},
  "geometry": {"coordinates":[74.29154,33.41017],"type":"Point"}
}