{
  "type": "Feature",
  "properties": {
    "iso:country":"IN",
    "ks:ks_name":"Cheedimetla",
    "ks:ks_pop":28,
    "ks:ks_type":"HABITATION",
    "name:eng_x_preferred":[
        "Cheedimetla"
    ],
    "wof:name":"Cheedimetla",
    "wof:placetype":"locality",
    "wof:population":28
},
  "geometry": {"coordinates":[82.779298,17.967591],"type":"Point"}
}