{
  "type": "Feature",
  "properties": {
    "gn:country":"IN",
    "gn:fcode":"PPL",
    "gn:population":20395,
    "iso:country":"IN",
    "name:bpy_x_preferred":[
        "\u09a5\u09bf\u09b8\u09be\u09af\u09bc\u09be\u09a8\u09ac\u09bf\u09b2\u09cd\u09b2\u09be\u0987"
    ],
    "name:eng_x_preferred":[
        "Thisayanvilai"
    ],
    "name:fra_x_preferred":[
        "Thisayanvilai"
    ],
    "name:ita_x_preferred":[
        "Thisayanvilai"
    ],
    "name:msa_x_preferred":[
        "Thisayanvilai"
    ],
    "name:nan_x_preferred":[
        "Thisayanvilai"
    ],
    "name:nld_x_preferred":[
        "Thisayanvilai"
    ],
    "name:por_x_preferred":[
        "Thisayanvilai"
    ],
    "name:tam_x_preferred":[
        "\u0ba4\u0bbf\u0b9a\u0bc8\u0baf\u0ba9\u0bcd\u0bb5\u0bbf\u0bb3\u0bc8"
    ],
    "name:vie_x_preferred":[
        "Thisayanvilai"
    ],
    "name:zho_x_preferred":[
        "\u8482\u8428\u5ef6\u7ef4\u83b1"
    ],
    "qs:name":"Tisayanvilai",
    "qs:name_adm0":"India",
    "qs:name_adm1":"Tamil Nadu",
    "qs:photos_9r":0,
    "qs:photos_sr":0,
    "qs:placetype":"Town",
    "qs:pop_sr":"7",
    "wof:name":"Tisayanvilai",
    "wof:placetype":"locality",
    "wof:population":20395
},
  "geometry": {"coordinates":[77.86586,8.33248],"type":"Point"}
}