{
  "type": "Feature",
  "properties": {
    "iso:country":"IN",
    "ks:ks_name":"Eachipoil",
    "ks:ks_pop":2131,
    "ks:ks_type":"HABITATION",
    "name:eng_x_preferred":[
        "Eachipoil"
    ],
    "wof:name":"Eachipoil",
    "wof:placetype":"locality",
    "wof:population":2131
},
  "geometry": {"coordinates":[75.31368000000001,12.30774],"type":"Point"}
}