{
  "type": "Feature",
  "properties": {
    "iso:country":"IN",
    "ks:ks_name":"Mulugodu",
    "ks:ks_pop":184,
    "ks:ks_type":"HABITATION",
    "name:eng_x_preferred":[
        "Mulugodu"
    ],
    "wof:name":"Mulugodu",
    "wof:placetype":"locality",
    "wof:population":184
},
  "geometry": {"coordinates":[74.449882,14.461654],"type":"Point"}
}