{
  "type": "Feature",
  "properties": {
    "gn:admin1_code":"23",
    "gn:admin2_code":"38.0",
    "gn:asciiname":"Bah Nangal",
    "gn:country_code":"IN",
    "gn:dem":576,
    "gn:feature_class":"P",
    "gn:feature_code":"PPL",
    "gn:name":"Bah Nangal",
    "gn:population":0,
    "gn:timezone":"Asia/Kolkata",
    "iso:country":"IN",
    "ks:ks_name":"Bah Nangal",
    "ks:ks_pop":918,
    "ks:ks_type":"VILLAGE",
    "name:eng_x_preferred":[
        "Bah Nangal"
    ],
    "wof:name":"Bah Nangal",
    "wof:placetype":"locality",
    "wof:population":918
},
  "geometry": {"coordinates":[75.838279,31.859574],"type":"Point"}
}