{
  "type": "Feature",
  "properties": {
    "gn:admin1_code":"21",
    "gn:admin2_code":"395.0",
    "gn:asciiname":"Semilbhata",
    "gn:country_code":"IN",
    "gn:dem":515,
    "gn:feature_class":"P",
    "gn:feature_code":"PPL",
    "gn:name":"Semilbhata",
    "gn:population":0,
    "gn:timezone":"Asia/Kolkata",
    "iso:country":"IN",
    "ks:ks_name":"Semilivata",
    "ks:ks_pop":168,
    "ks:ks_type":"VILLAGE",
    "name:eng_x_preferred":[
        "Semilivata"
    ],
    "name:eng_x_variant":[
        "Semilbhata"
    ],
    "wof:name":"Semilivata",
    "wof:placetype":"locality",
    "wof:population":168
},
  "geometry": {"coordinates":[83.362488,19.683588],"type":"Point"}
}