{
  "type": "Feature",
  "properties": {
    "gn:admin1_code":"35",
    "gn:admin2_code":"464.0",
    "gn:asciiname":"Tornia",
    "gn:country_code":"IN",
    "gn:dem":292,
    "gn:feature_class":"P",
    "gn:feature_code":"PPL",
    "gn:name":"Tornia",
    "gn:population":0,
    "gn:timezone":"Asia/Kolkata",
    "iso:country":"IN",
    "ks:ks_name":"Torniya",
    "ks:ks_pop":832,
    "ks:ks_type":"VILLAGE",
    "name:eng_x_preferred":[
        "Torniya"
    ],
    "name:eng_x_variant":[
        "Tornia"
    ],
    "wof:name":"Torniya",
    "wof:placetype":"locality",
    "wof:population":832
},
  "geometry": {"coordinates":[74.397198,23.00192],"type":"Point"}
}