{
  "type": "Feature",
  "properties": {
    "iso:country":"IN",
    "ks:ks_name":"Peepal Kheri",
    "ks:ks_pop":357,
    "ks:ks_type":"HABITATION",
    "name:eng_x_preferred":[
        "Peepal Kheri"
    ],
    "wof:name":"Peepal Kheri",
    "wof:placetype":"locality",
    "wof:population":357
},
  "geometry": {"coordinates":[76.99050699999999,24.613215],"type":"Point"}
}