{
  "type": "Feature",
  "properties": {
    "iso:country":"IN",
    "ks:ks_name":"Saranatham",
    "ks:ks_pop":518,
    "ks:ks_type":"HABITATION",
    "name:eng_x_preferred":[
        "Saranatham"
    ],
    "wof:name":"Saranatham",
    "wof:placetype":"locality",
    "wof:population":518
},
  "geometry": {"coordinates":[79.446155,10.829799],"type":"Point"}
}