{
  "type": "Feature",
  "properties": {
    "iso:country":"IN",
    "ks:ks_alt_nam":"MIDDLE. TOLA.",
    "ks:ks_name":"Middle. Tola.",
    "ks:ks_pop":308,
    "ks:ks_type":"HABITATION",
    "name:eng_x_preferred":[
        "Middle. Tola."
    ],
    "wof:name":"Middle. Tola.",
    "wof:placetype":"locality",
    "wof:population":308
},
  "geometry": {"coordinates":[84.983217,24.557026],"type":"Point"}
}