{
  "type": "Feature",
  "properties": {
    "gn:admin1_code":"2.0",
    "gn:admin2_code":"543.0",
    "gn:asciiname":"Gijaba",
    "gn:country_code":"IN",
    "gn:dem":110,
    "gn:feature_class":"P",
    "gn:feature_code":"PPL",
    "gn:name":"Gijaba",
    "gn:population":0,
    "gn:timezone":"Asia/Kolkata",
    "iso:country":"IN",
    "ks:ks_name":"Gijaba",
    "ks:ks_pop":1450,
    "ks:ks_type":"VILLAGE",
    "name:eng_x_preferred":[
        "Gijaba"
    ],
    "wof:name":"Gijaba",
    "wof:placetype":"locality",
    "wof:population":1450
},
  "geometry": {"coordinates":[83.49859499999999,18.804902],"type":"Point"}
}