{
  "type": "Feature",
  "properties": {
    "iso:country":"IN",
    "ks:ks_name":"Khushaltak Usmanpur",
    "ks:ks_pop":347,
    "ks:ks_type":"HABITATION",
    "ks:ks_uagg_main":0,
    "name:eng_x_preferred":[
        "Khushaltak Usmanpur"
    ],
    "wof:name":"Khushaltak Usmanpur",
    "wof:placetype":"neighbourhood",
    "wof:population":347
},
  "geometry": {"coordinates":[84.04007799999999,26.624076],"type":"Point"}
}