{
  "type": "Feature",
  "properties": {
    "iso:country":"IN",
    "ks:ks_name":"Chota Balaha",
    "ks:ks_pop":382,
    "ks:ks_type":"HABITATION",
    "name:eng_x_preferred":[
        "Chota Balaha"
    ],
    "wof:name":"Chota Balaha",
    "wof:placetype":"locality",
    "wof:population":382
},
  "geometry": {"coordinates":[82.342232,27.405643],"type":"Point"}
}