{
  "type": "Feature",
  "properties": {
    "iso:country":"IN",
    "ks:ks_name":"Chokkadu Adivasi Colony Jn",
    "ks:ks_pop":958,
    "ks:ks_type":"HABITATION",
    "name:eng_x_preferred":[
        "Chokkadu Adivasi Colony Jn"
    ],
    "wof:name":"Chokkadu Adivasi Colony Jn",
    "wof:placetype":"locality",
    "wof:population":958
},
  "geometry": {"coordinates":[76.359363,11.231421],"type":"Point"}
}