{
  "type": "Feature",
  "properties": {
    "iso:country":"IN",
    "ks:ks_name":"2 SHPD A",
    "ks:ks_pop":267,
    "ks:ks_type":"VILLAGE",
    "name:eng_x_preferred":[
        "2 SHPD A"
    ],
    "wof:name":"2 SHPD A",
    "wof:placetype":"locality",
    "wof:population":267
},
  "geometry": {"coordinates":[73.815439,29.442381],"type":"Point"}
}