{
  "type": "Feature",
  "properties": {
    "iso:country":"IN",
    "ks:ks_alt_nam":"chandanam vayal SC colony",
    "ks:ks_name":"Chandanam Vayal Sc Colony",
    "ks:ks_pop":298,
    "ks:ks_type":"HABITATION",
    "name:eng_x_preferred":[
        "Chandanam Vayal Sc Colony"
    ],
    "wof:name":"Chandanam Vayal Sc Colony",
    "wof:placetype":"locality",
    "wof:population":298
},
  "geometry": {"coordinates":[75.808924,11.543892],"type":"Point"}
}