{
  "type": "Feature",
  "properties": {
    "iso:country":"IN",
    "ks:ks_name":"Chandanpur",
    "ks:ks_pop":306,
    "ks:ks_type":"VILLAGE",
    "name:eng_x_preferred":[
        "Chandanpur"
    ],
    "wof:name":"Chandanpur",
    "wof:placetype":"locality",
    "wof:population":306
},
  "geometry": {"coordinates":[85.958355,22.699412],"type":"Point"}
}