{
  "type": "Feature",
  "properties": {
    "gn:admin1_code":"39.0",
    "gn:admin2_code":"66.0",
    "gn:asciiname":"Patraini",
    "gn:country_code":"IN",
    "gn:dem":1139,
    "gn:feature_class":"P",
    "gn:feature_code":"PPL",
    "gn:name":"Patraini",
    "gn:population":0,
    "gn:timezone":"Asia/Kolkata",
    "iso:country":"IN",
    "ks:ks_name":"Patrani",
    "ks:ks_pop":653,
    "ks:ks_type":"VILLAGE",
    "name:eng_x_preferred":[
        "Patrani"
    ],
    "name:eng_x_variant":[
        "Patraini"
    ],
    "wof:name":"Patrani",
    "wof:placetype":"locality",
    "wof:population":653
},
  "geometry": {"coordinates":[79.691563,29.218515],"type":"Point"}
}