{
  "type": "Feature",
  "properties": {
    "gn:admin1_code":"39.0",
    "gn:admin2_code":"66.0",
    "gn:asciiname":"Patraini",
    "gn:country_code":"IN",
    "gn:dem":1139,
    "gn:feature_class":"P",
    "gn:feature_code":"PPL",
    "gn:name":"Patraini",
    "gn:population":0,
    "gn:timezone":"Asia/Kolkata",
    "iso:country":"IN",
    "wof:name":"Patraini",
    "wof:placetype":"locality"
},
  "geometry": {"coordinates":[79.68673000000003,29.21978],"type":"Point"}
}