{
  "type": "Feature",
  "properties": {
    "iso:country":"IN",
    "ks:ks_alt_nam":"SHIVNAGAR",
    "ks:ks_name":"Shivnagar",
    "ks:ks_pop":268,
    "ks:ks_type":"HABITATION",
    "name:eng_x_preferred":[
        "Shivnagar"
    ],
    "wof:name":"Shivnagar",
    "wof:placetype":"locality",
    "wof:population":268
},
  "geometry": {"coordinates":[74.18684500000001,17.039773],"type":"Point"}
}