{
  "type": "Feature",
  "properties": {
    "iso:country":"IN",
    "ks:ks_name":"Chirana",
    "ks:ks_pop":1450,
    "ks:ks_type":"HABITATION",
    "name:eng_x_preferred":[
        "Chirana"
    ],
    "wof:name":"Chirana",
    "wof:placetype":"locality",
    "wof:population":1450
},
  "geometry": {"coordinates":[80.084292,26.417256],"type":"Point"}
}