{
  "type": "Feature",
  "properties": {
    "iso:country":"IN",
    "ks:ks_name":"Saibana",
    "ks:ks_pop":516,
    "ks:ks_type":"VILLAGE",
    "ks:ks_uagg_main":0,
    "name:eng_x_preferred":[
        "Saibana"
    ],
    "wof:name":"Saibana",
    "wof:placetype":"locality",
    "wof:population":516
},
  "geometry": {"coordinates":[88.425203,22.744211],"type":"Point"}
}