{
  "type": "Feature",
  "properties": {
    "gn:admin1_code":"36.0",
    "gn:admin2_code":"161.0",
    "gn:asciiname":"Garhia",
    "gn:country_code":"IN",
    "gn:dem":144,
    "gn:feature_class":"P",
    "gn:feature_code":"PPL",
    "gn:name":"Garhia",
    "gn:population":0,
    "gn:timezone":"Asia/Kolkata",
    "iso:country":"IN",
    "ks:ks_name":"Garhia",
    "ks:ks_type":"VILLAGE",
    "name:eng_x_preferred":[
        "Garhia"
    ],
    "wof:name":"Garhia",
    "wof:placetype":"locality"
},
  "geometry": {"coordinates":[79.040791,26.55121],"type":"Point"}
}