{
  "type": "Feature",
  "properties": {
    "iso:country":"IN",
    "ks:ks_name":"Santhal Tola",
    "ks:ks_pop":156,
    "ks:ks_type":"HABITATION",
    "name:eng_x_preferred":[
        "Santhal Tola"
    ],
    "wof:name":"Santhal Tola",
    "wof:placetype":"locality",
    "wof:population":156
},
  "geometry": {"coordinates":[86.381067,24.589253],"type":"Point"}
}