{
  "type": "Feature",
  "properties": {
    "iso:country":"IN",
    "ks:ks_name":"Dehra",
    "ks:ks_pop":0,
    "ks:ks_type":"VILLAGE",
    "name:eng_x_preferred":[
        "Dehra"
    ],
    "wof:name":"Dehra",
    "wof:placetype":"locality",
    "wof:population":0
},
  "geometry": {"coordinates":[83.558385,25.092162],"type":"Point"}
}