{
  "type": "Feature",
  "properties": {
    "iso:country":"IN",
    "ks:ks_name":"Dimirikuti",
    "ks:ks_pop":80,
    "ks:ks_type":"HABITATION",
    "name:eng_x_preferred":[
        "Dimirikuti"
    ],
    "wof:name":"Dimirikuti",
    "wof:placetype":"locality",
    "wof:population":80
},
  "geometry": {"coordinates":[84.793035,20.369497],"type":"Point"}
}