{
  "type": "Feature",
  "properties": {
    "gn:admin1_code":"36.0",
    "gn:admin2_code":"151.0",
    "gn:asciiname":"Gauntia Mata Din",
    "gn:country_code":"IN",
    "gn:dem":189,
    "gn:feature_class":"P",
    "gn:feature_code":"PPL",
    "gn:name":"Gauntia M\u0101ta D\u012bn",
    "gn:population":0,
    "gn:timezone":"Asia/Kolkata",
    "iso:country":"IN",
    "wof:name":"Gauntia Mata Din",
    "wof:placetype":"locality"
},
  "geometry": {"coordinates":[79.84664000000002,28.62582],"type":"Point"}
}