{
  "type": "Feature",
  "properties": {
    "gn:admin1_code":"19.0",
    "gn:admin2_code":"573.0",
    "gn:asciiname":"Sakshibidu",
    "gn:country_code":"IN",
    "gn:dem":800,
    "gn:feature_class":"P",
    "gn:feature_code":"PPL",
    "gn:name":"S\u0101kshib\u012bdu",
    "gn:population":0,
    "gn:timezone":"Asia/Kolkata",
    "iso:country":"IN",
    "wof:name":"Sakshibidu",
    "wof:placetype":"neighbourhood"
},
  "geometry": {"coordinates":[76.38052,12.65175],"type":"Point"}
}