{
  "type": "Feature",
  "properties": {
    "gn:admin1_code":"19",
    "gn:admin2_code":"559.0",
    "gn:asciiname":"Huda",
    "gn:country_code":"IN",
    "gn:dem":486,
    "gn:feature_class":"P",
    "gn:feature_code":"PPL",
    "gn:name":"Huda",
    "gn:population":0,
    "gn:timezone":"Asia/Kolkata",
    "iso:country":"IN",
    "name:deu_x_preferred":[
        "Huda"
    ],
    "name:rus_x_preferred":[
        "\u0425\u0443\u0434\u0430"
    ],
    "wof:name":"Huda",
    "wof:placetype":"locality"
},
  "geometry": {"coordinates":[76.82083,16.21462],"type":"Point"}
}