{
  "type": "Feature",
  "properties": {
    "iso:country":"IN",
    "ks:ks_name":"Vadadari",
    "ks:ks_pop":41,
    "ks:ks_type":"HABITATION",
    "name:eng_x_preferred":[
        "Vadadari"
    ],
    "wof:name":"Vadadari",
    "wof:placetype":"locality",
    "wof:population":41
},
  "geometry": {"coordinates":[74.818642,14.418728],"type":"Point"}
}