{
  "type": "Feature",
  "properties": {
    "gn:admin1_code":"2.0",
    "gn:admin2_code":"544.0",
    "gn:asciiname":"Sundriputtu",
    "gn:country_code":"IN",
    "gn:dem":905,
    "gn:feature_class":"P",
    "gn:feature_code":"PPL",
    "gn:name":"Sundriputtu",
    "gn:population":0,
    "gn:timezone":"Asia/Kolkata",
    "iso:country":"IN",
    "ks:ks_name":"Sundruputtu",
    "ks:ks_pop":198,
    "ks:ks_type":"VILLAGE",
    "name:eng_x_preferred":[
        "Sundruputtu"
    ],
    "name:eng_x_variant":[
        "Sundriputtu"
    ],
    "wof:name":"Sundruputtu",
    "wof:placetype":"locality",
    "wof:population":198
},
  "geometry": {"coordinates":[82.650521,18.171995],"type":"Point"}
}