{
  "type": "Feature",
  "properties": {
    "gn:admin1_code":"2.0",
    "gn:admin2_code":"544.0",
    "gn:asciiname":"Sundriputtu",
    "gn:country_code":"IN",
    "gn:dem":905,
    "gn:feature_class":"P",
    "gn:feature_code":"PPL",
    "gn:name":"Sundriputtu",
    "gn:population":0,
    "gn:timezone":"Asia/Kolkata",
    "iso:country":"IN",
    "wof:name":"Sundriputtu",
    "wof:placetype":"locality"
},
  "geometry": {"coordinates":[82.65059000000002,18.17123],"type":"Point"}
}