{
  "type": "Feature",
  "properties": {
    "iso:country":"IN",
    "ks:ks_name":"Pangiguda",
    "ks:ks_pop":561,
    "ks:ks_type":"VILLAGE",
    "name:eng_x_preferred":[
        "Pangiguda"
    ],
    "wof:name":"Pangiguda",
    "wof:placetype":"locality",
    "wof:population":561
},
  "geometry": {"coordinates":[82.984506,18.485917],"type":"Point"}
}