{
  "type": "Feature",
  "properties": {
    "iso:country":"IN",
    "ks:ks_alt_nam":"Rangamatia sahi",
    "ks:ks_name":"Rangamatia Sahi",
    "ks:ks_pop":30,
    "ks:ks_type":"HABITATION",
    "name:eng_x_preferred":[
        "Rangamatia Sahi"
    ],
    "wof:name":"Rangamatia Sahi",
    "wof:placetype":"locality",
    "wof:population":30
},
  "geometry": {"coordinates":[85.91985699999999,21.318908],"type":"Point"}
}