{
  "type": "Feature",
  "properties": {
    "iso:country":"IN",
    "ks:ks_name":"Periyakuppam",
    "ks:ks_pop":281,
    "ks:ks_type":"HABITATION",
    "ks:ks_uagg_main":0,
    "name:eng_x_preferred":[
        "Periyakuppam"
    ],
    "wof:name":"Periyakuppam",
    "wof:placetype":"neighbourhood",
    "wof:population":281
},
  "geometry": {"coordinates":[80.14093800000001,12.4438],"type":"Point"}
}