{
  "type": "Feature",
  "properties": {
    "iso:country":"IN",
    "ks:ks_name":"Salaiya",
    "ks:ks_pop":76,
    "ks:ks_type":"VILLAGE",
    "name:eng_x_preferred":[
        "Salaiya"
    ],
    "wof:name":"Salaiya",
    "wof:placetype":"locality",
    "wof:population":76
},
  "geometry": {"coordinates":[86.66268599999999,24.28874],"type":"Point"}
}