{
  "type": "Feature",
  "properties": {
    "iso:country":"IN",
    "ks:ks_name":"Phura Gaon",
    "ks:ks_pop":213,
    "ks:ks_type":"HABITATION",
    "ks:ks_uagg_main":0,
    "name:eng_x_preferred":[
        "Phura Gaon"
    ],
    "wof:name":"Phura Gaon",
    "wof:placetype":"neighbourhood",
    "wof:population":213
},
  "geometry": {"coordinates":[92.573671,25.848325],"type":"Point"}
}