{
  "type": "Feature",
  "properties": {
    "iso:country":"IN",
    "ks:ks_name":"Bharauti",
    "ks:ks_pop":83,
    "ks:ks_type":"HABITATION",
    "name:eng_x_preferred":[
        "Bharauti"
    ],
    "wof:name":"Bharauti",
    "wof:placetype":"locality",
    "wof:population":83
},
  "geometry": {"coordinates":[82.74624,26.59541],"type":"Point"}
}