{
  "type": "Feature",
  "properties": {
    "iso:country":"IN",
    "ks:ks_name":"Kheri",
    "ks:ks_pop":1319,
    "ks:ks_type":"VILLAGE",
    "name:eng_x_preferred":[
        "Kheri"
    ],
    "wof:name":"Kheri",
    "wof:placetype":"locality",
    "wof:population":1319
},
  "geometry": {"coordinates":[76.61278,24.608074],"type":"Point"}
}