{
  "type": "Feature",
  "properties": {
    "iso:country":"IN",
    "ks:ks_alt_nam":"Kunjila HC",
    "ks:ks_name":"Kunjila Hc",
    "ks:ks_pop":12,
    "ks:ks_type":"HABITATION",
    "name:eng_x_preferred":[
        "Kunjila Hc"
    ],
    "wof:name":"Kunjila Hc",
    "wof:placetype":"locality",
    "wof:population":12
},
  "geometry": {"coordinates":[75.6575,12.283611],"type":"Point"}
}