{
  "type": "Feature",
  "properties": {
    "iso:country":"IN",
    "ks:ks_name":"Vazhel Linked Road",
    "ks:ks_pop":375,
    "ks:ks_type":"HABITATION",
    "name:eng_x_preferred":[
        "Vazhel Linked Road"
    ],
    "wof:name":"Vazhel Linked Road",
    "wof:placetype":"locality",
    "wof:population":375
},
  "geometry": {"coordinates":[76.379392,10.710074],"type":"Point"}
}