{
  "type": "Feature",
  "properties": {
    "iso:country":"IN",
    "ks:ks_name":"Chandramveedi",
    "ks:ks_pop":59,
    "ks:ks_type":"HABITATION",
    "name:eng_x_preferred":[
        "Chandramveedi"
    ],
    "wof:name":"Chandramveedi",
    "wof:placetype":"locality",
    "wof:population":59
},
  "geometry": {"coordinates":[82.499802,18.228479],"type":"Point"}
}