{
  "type": "Feature",
  "properties": {
    "iso:country":"IN",
    "ks:ks_name":"Chatabar",
    "ks:ks_pop":21,
    "ks:ks_type":"HABITATION",
    "name:eng_x_preferred":[
        "Chatabar"
    ],
    "wof:name":"Chatabar",
    "wof:placetype":"locality",
    "wof:population":21
},
  "geometry": {"coordinates":[84.624205,19.829163],"type":"Point"}
}