{
  "type": "Feature",
  "properties": {
    "iso:country":"IN",
    "ks:ks_name":"Radhamadhabpur",
    "ks:ks_pop":0,
    "ks:ks_type":"VILLAGE",
    "name:eng_x_preferred":[
        "Radhamadhabpur"
    ],
    "wof:name":"Radhamadhabpur",
    "wof:placetype":"locality",
    "wof:population":0
},
  "geometry": {"coordinates":[85.69784799999999,20.494417],"type":"Point"}
}