{
  "type": "Feature",
  "properties": {
    "iso:country":"IN",
    "ks:ks_name":"Dhamnipada",
    "ks:ks_pop":278,
    "ks:ks_type":"HABITATION",
    "name:eng_x_preferred":[
        "Dhamnipada"
    ],
    "wof:name":"Dhamnipada",
    "wof:placetype":"locality",
    "wof:population":278
},
  "geometry": {"coordinates":[72.920154,20.184519],"type":"Point"}
}