{
  "type": "Feature",
  "properties": {
    "iso:country":"IN",
    "ks:ks_name":"Sri Bhagawat Tola",
    "ks:ks_pop":84,
    "ks:ks_type":"HABITATION",
    "ks:ks_uagg_main":0,
    "name:eng_x_preferred":[
        "Sri Bhagawat Tola"
    ],
    "wof:name":"Sri Bhagawat Tola",
    "wof:placetype":"neighbourhood",
    "wof:population":84
},
  "geometry": {"coordinates":[83.502171,27.14887],"type":"Point"}
}