{
  "type": "Feature",
  "properties": {
    "iso:country":"IN",
    "ks:ks_name":"Krishnanagar",
    "ks:ks_pop":97,
    "ks:ks_type":"HABITATION",
    "name:eng_x_preferred":[
        "Krishnanagar"
    ],
    "wof:name":"Krishnanagar",
    "wof:placetype":"locality",
    "wof:population":97
},
  "geometry": {"coordinates":[80.28028399999999,15.726519],"type":"Point"}
}