{
  "type": "Feature",
  "properties": {
    "iso:country":"IN",
    "ks:ks_name":"Chautli",
    "ks:ks_pop":14,
    "ks:ks_type":"VILLAGE",
    "name:eng_x_preferred":[
        "Chautli"
    ],
    "wof:name":"Chautli",
    "wof:placetype":"locality",
    "wof:population":14
},
  "geometry": {"coordinates":[79.59685399999999,29.534701],"type":"Point"}
}