{
  "type": "Feature",
  "properties": {
    "iso:country":"IN",
    "ks:ks_alt_nam":"MIYA TOLLI",
    "ks:ks_name":"Miya Tolli",
    "ks:ks_pop":225,
    "ks:ks_type":"HABITATION",
    "ks:ks_uagg_main":0,
    "name:eng_x_preferred":[
        "Miya Tolli"
    ],
    "wof:name":"Miya Tolli",
    "wof:placetype":"neighbourhood",
    "wof:population":225
},
  "geometry": {"coordinates":[84.94956500000001,25.996362],"type":"Point"}
}