{
  "type": "Feature",
  "properties": {
    "iso:country":"IN",
    "ks:ks_alt_nam":"Tarani F.V pt 2",
    "ks:ks_name":"Tarani F.v Pt 2",
    "ks:ks_pop":280,
    "ks:ks_type":"HABITATION",
    "name:eng_x_preferred":[
        "Tarani F.v Pt 2"
    ],
    "wof:name":"Tarani F.v Pt 2",
    "wof:placetype":"locality",
    "wof:population":280
},
  "geometry": {"coordinates":[94.952158,27.131687],"type":"Point"}
}