{
  "type": "Feature",
  "properties": {
    "iso:country":"IN",
    "ks:ks_name":"Nisalaneer",
    "ks:ks_pop":60,
    "ks:ks_type":"HABITATION",
    "name:eng_x_preferred":[
        "Nisalaneer"
    ],
    "wof:name":"Nisalaneer",
    "wof:placetype":"locality",
    "wof:population":60
},
  "geometry": {"coordinates":[74.535768,14.194604],"type":"Point"}
}