{
  "type": "Feature",
  "properties": {
    "gn:admin1_code":"2.0",
    "gn:admin2_code":"551.0",
    "gn:asciiname":"Basivireddipalle",
    "gn:country_code":"IN",
    "gn:dem":152,
    "gn:feature_class":"P",
    "gn:feature_code":"PPL",
    "gn:name":"Basivireddipalle",
    "gn:population":0,
    "gn:timezone":"Asia/Kolkata",
    "iso:country":"IN",
    "ks:ks_name":"Basireddipalle",
    "ks:ks_pop":224,
    "ks:ks_type":"HABITATION",
    "name:eng_x_preferred":[
        "Basireddipalle"
    ],
    "name:eng_x_variant":[
        "Basivireddipalle"
    ],
    "wof:name":"Basireddipalle",
    "wof:placetype":"locality",
    "wof:population":224
},
  "geometry": {"coordinates":[78.66228099999999,14.757182],"type":"Point"}
}