{
  "type": "Feature",
  "properties": {
    "iso:country":"IN",
    "ks:ks_name":"Ajabnagar",
    "ks:ks_pop":1067,
    "ks:ks_type":"VILLAGE",
    "name:eng_x_preferred":[
        "Ajabnagar"
    ],
    "wof:name":"Ajabnagar",
    "wof:placetype":"locality",
    "wof:population":1067
},
  "geometry": {"coordinates":[83.113955,23.16769],"type":"Point"}
}