{
  "type": "Feature",
  "properties": {
    "iso:country":"IN",
    "ks:ks_name":"Srinivasa Puram Mitta Palem",
    "ks:ks_pop":46,
    "ks:ks_type":"HABITATION",
    "name:eng_x_preferred":[
        "Srinivasa Puram Mitta Palem"
    ],
    "wof:name":"Srinivasa Puram Mitta Palem",
    "wof:placetype":"locality",
    "wof:population":46
},
  "geometry": {"coordinates":[80.14352700000001,13.967723],"type":"Point"}
}