{
  "type": "Feature",
  "properties": {
    "iso:country":"IN",
    "ks:ks_name":"Khonjkhidir",
    "ks:ks_pop":579,
    "ks:ks_type":"VILLAGE",
    "name:eng_x_preferred":[
        "Khonjkhidir"
    ],
    "wof:name":"Khonjkhidir",
    "wof:placetype":"locality",
    "wof:population":579
},
  "geometry": {"coordinates":[88.41823100000001,22.111741],"type":"Point"}
}