{
  "type": "Feature",
  "properties": {
    "iso:country":"IN",
    "ks:ks_name":"Anand Nagar",
    "ks:ks_pop":365,
    "ks:ks_type":"HABITATION",
    "name:eng_x_preferred":[
        "Anand Nagar"
    ],
    "wof:name":"Anand Nagar",
    "wof:placetype":"locality",
    "wof:population":365
},
  "geometry": {"coordinates":[71.83439199999999,25.3396],"type":"Point"}
}