{
  "type": "Feature",
  "properties": {
    "gn:admin1_code":"10.0",
    "gn:admin2_code":"084",
    "gn:asciiname":"Tazipur",
    "gn:country_code":"IN",
    "gn:dem":318,
    "gn:feature_class":"P",
    "gn:feature_code":"PPL",
    "gn:name":"T\u0101zipur",
    "gn:population":0,
    "gn:timezone":"Asia/Kolkata",
    "iso:country":"IN",
    "wof:name":"Tazipur",
    "wof:placetype":"locality"
},
  "geometry": {"coordinates":[76.10304000000002,28.00214],"type":"Point"}
}