{
  "type": "Feature",
  "properties": {
    "gn:admin1_code":"11.0",
    "gn:admin2_code":"033",
    "gn:asciiname":"Bachharag",
    "gn:country_code":"IN",
    "gn:dem":1122,
    "gn:feature_class":"P",
    "gn:feature_code":"PPL",
    "gn:name":"Bachh\u0101rag",
    "gn:population":0,
    "gn:timezone":"Asia/Kolkata",
    "iso:country":"IN",
    "wof:name":"Bachharag",
    "wof:placetype":"locality"
},
  "geometry": {"coordinates":[77.03721999999998,31.19944000000001],"type":"Point"}
}