{
  "type": "Feature",
  "properties": {
    "iso:country":"IN",
    "ks:ks_name":"Awadhiya Tola",
    "ks:ks_pop":306,
    "ks:ks_type":"HABITATION",
    "ks:ks_uagg_main":0,
    "name:eng_x_preferred":[
        "Awadhiya Tola"
    ],
    "wof:name":"Awadhiya Tola",
    "wof:placetype":"neighbourhood",
    "wof:population":306
},
  "geometry": {"coordinates":[84.460115,26.166688],"type":"Point"}
}