{
  "type": "Feature",
  "properties": {
    "iso:country":"IN",
    "ks:ks_name":"Dongripada",
    "ks:ks_pop":422,
    "ks:ks_type":"HABITATION",
    "name:eng_x_preferred":[
        "Dongripada"
    ],
    "wof:name":"Dongripada",
    "wof:placetype":"locality",
    "wof:population":422
},
  "geometry": {"coordinates":[72.84929099999999,20.191613],"type":"Point"}
}