{
  "type": "Feature",
  "properties": {
    "gn:admin1_code":"35.0",
    "gn:admin2_code":"441.0",
    "gn:asciiname":"Ghurchal",
    "gn:country_code":"IN",
    "gn:dem":407,
    "gn:feature_class":"P",
    "gn:feature_code":"PPL",
    "gn:name":"Ghurchal",
    "gn:population":0,
    "gn:timezone":"Asia/Kolkata",
    "iso:country":"IN",
    "ks:ks_name":"Ghudchal",
    "ks:ks_pop":1278,
    "ks:ks_type":"VILLAGE",
    "name:eng_x_preferred":[
        "Ghudchal"
    ],
    "name:eng_x_variant":[
        "Ghurchal"
    ],
    "wof:name":"Ghudchal",
    "wof:placetype":"locality",
    "wof:population":1278
},
  "geometry": {"coordinates":[75.16784800000001,21.675772],"type":"Point"}
}