{
  "type": "Feature",
  "properties": {
    "gn:admin1_code":"19.0",
    "gn:admin2_code":"565.0",
    "gn:asciiname":"Hirehalu",
    "gn:country_code":"IN",
    "gn:dem":376,
    "gn:feature_class":"P",
    "gn:feature_code":"PPL",
    "gn:name":"H\u012breh\u0101lu",
    "gn:population":0,
    "gn:timezone":"Asia/Kolkata",
    "iso:country":"IN",
    "wof:name":"Hirehalu",
    "wof:placetype":"locality"
},
  "geometry": {"coordinates":[76.95244,15.5724],"type":"Point"}
}