{
  "type": "Feature",
  "properties": {
    "iso:country":"IN",
    "ks:ks_name":"Krishnegowdana",
    "ks:ks_pop":257,
    "ks:ks_type":"HABITATION",
    "name:eng_x_preferred":[
        "Krishnegowdana"
    ],
    "wof:name":"Krishnegowdana",
    "wof:placetype":"locality",
    "wof:population":257
},
  "geometry": {"coordinates":[77.23241400000001,12.382143],"type":"Point"}
}