{
  "type": "Feature",
  "properties": {
    "iso:country":"IN",
    "ks:ks_name":"Bawadiya",
    "ks:ks_pop":577,
    "ks:ks_type":"VILLAGE",
    "name:eng_x_preferred":[
        "Bawadiya"
    ],
    "wof:name":"Bawadiya",
    "wof:placetype":"locality",
    "wof:population":577
},
  "geometry": {"coordinates":[74.62620099999999,22.824781],"type":"Point"}
}