{
  "type": "Feature",
  "properties": {
    "iso:country":"IN",
    "ks:ks_name":"Ganrar",
    "ks:ks_pop":46,
    "ks:ks_type":"VILLAGE",
    "name:eng_x_preferred":[
        "Ganrar"
    ],
    "wof:name":"Ganrar",
    "wof:placetype":"locality",
    "wof:population":46
},
  "geometry": {"coordinates":[79.65649500000001,29.256011],"type":"Point"}
}