{
  "type": "Feature",
  "properties": {
    "iso:country":"IN",
    "ks:ks_name":"Tarne Tarf Tale",
    "ks:ks_pop":367,
    "ks:ks_type":"VILLAGE",
    "name:eng_x_preferred":[
        "Tarne Tarf Tale"
    ],
    "wof:name":"Tarne Tarf Tale",
    "wof:placetype":"locality",
    "wof:population":367
},
  "geometry": {"coordinates":[73.12547000000001,18.287703],"type":"Point"}
}