{
  "type": "Feature",
  "properties": {
    "iso:country":"IN",
    "ks:ks_alt_nam":"T. HARIJANAWADA",
    "ks:ks_name":"T. Harijanawada",
    "ks:ks_pop":131,
    "ks:ks_type":"HABITATION",
    "name:eng_x_preferred":[
        "T. Harijanawada"
    ],
    "wof:name":"T. Harijanawada",
    "wof:placetype":"locality",
    "wof:population":131
},
  "geometry": {"coordinates":[79.311226,13.987902],"type":"Point"}
}