{
  "type": "Feature",
  "properties": {
    "gn:admin1_code":"12",
    "gn:admin2_code":"18.0",
    "gn:asciiname":"Dharnist",
    "gn:country_code":"IN",
    "gn:dem":2885,
    "gn:feature_class":"P",
    "gn:feature_code":"PPL",
    "gn:name":"Dh\u0101rnist",
    "gn:population":0,
    "gn:timezone":"Asia/Kolkata",
    "iso:country":"IN",
    "wof:name":"Dharnist",
    "wof:placetype":"locality"
},
  "geometry": {"coordinates":[76.27455,33.17954],"type":"Point"}
}