{
  "type": "Feature",
  "properties": {
    "gn:admin1_code":"36.0",
    "gn:admin2_code":"165.0",
    "gn:asciiname":"Hirapur",
    "gn:country_code":"IN",
    "gn:dem":149,
    "gn:feature_class":"P",
    "gn:feature_code":"PPL",
    "gn:name":"H\u012br\u0101pur",
    "gn:population":0,
    "gn:timezone":"Asia/Kolkata",
    "iso:country":"IN",
    "name:fra_x_preferred":[
        "Hirapur"
    ],
    "wof:name":"Hirapur",
    "wof:placetype":"neighbourhood"
},
  "geometry": {"coordinates":[79.26146,26.24872],"type":"Point"}
}