{
  "type": "Feature",
  "properties": {
    "gn:admin1_code":"35.0",
    "gn:admin2_code":"441",
    "gn:asciiname":"Jamli",
    "gn:country_code":"IN",
    "gn:dem":335,
    "gn:feature_class":"P",
    "gn:feature_code":"PPL",
    "gn:name":"Jamli",
    "gn:population":0,
    "gn:timezone":"Asia/Kolkata",
    "iso:country":"IN",
    "wof:name":"Jamli",
    "wof:placetype":"locality"
},
  "geometry": {"coordinates":[75.15675999999998,21.74487],"type":"Point"}
}