{
  "type": "Feature",
  "properties": {
    "gn:admin1_code":"35.0",
    "gn:admin2_code":"441",
    "gn:asciiname":"Jamli",
    "gn:country_code":"IN",
    "gn:dem":335,
    "gn:feature_class":"P",
    "gn:feature_code":"PPL",
    "gn:name":"Jamli",
    "gn:population":0,
    "gn:timezone":"Asia/Kolkata",
    "iso:country":"IN",
    "ks:ks_name":"Jamli",
    "ks:ks_pop":2270,
    "ks:ks_type":"VILLAGE",
    "name:eng_x_preferred":[
        "Jamli"
    ],
    "wof:name":"Jamli",
    "wof:placetype":"locality",
    "wof:population":2270
},
  "geometry": {"coordinates":[75.153232,21.747555],"type":"Point"}
}