{
  "type": "Feature",
  "properties": {
    "iso:country":"IN",
    "ks:ks_name":"Chiharpari",
    "ks:ks_pop":33,
    "ks:ks_type":"VILLAGE",
    "name:eng_x_preferred":[
        "Chiharpari"
    ],
    "wof:name":"Chiharpari",
    "wof:placetype":"locality",
    "wof:population":33
},
  "geometry": {"coordinates":[87.614836,25.147934],"type":"Point"}
}