{
  "type": "Feature",
  "properties": {
    "gn:admin1_code":"28.0",
    "gn:admin2_code":"343",
    "gn:asciiname":"Madhabpur",
    "gn:country_code":"IN",
    "gn:dem":4,
    "gn:feature_class":"P",
    "gn:feature_code":"PPL",
    "gn:name":"Madhabpur",
    "gn:population":0,
    "gn:timezone":"Asia/Kolkata",
    "iso:country":"IN",
    "ks:ks_name":"Madhabpur",
    "ks:ks_pop":3735,
    "ks:ks_type":"VILLAGE",
    "name:eng_x_preferred":[
        "Madhabpur"
    ],
    "wof:name":"Madhabpur",
    "wof:placetype":"locality",
    "wof:population":3735
},
  "geometry": {"coordinates":[88.5625,22.049722],"type":"Point"}
}