{
  "type": "Feature",
  "properties": {
    "iso:country":"IN",
    "ks:ks_name":"Manchhla",
    "ks:ks_pop":463,
    "ks:ks_type":"VILLAGE",
    "name:eng_x_preferred":[
        "Manchhla"
    ],
    "wof:name":"Manchhla",
    "wof:placetype":"locality",
    "wof:population":463
},
  "geometry": {"coordinates":[72.87598199999999,24.256999],"type":"Point"}
}