{
  "type": "Feature",
  "properties": {
    "iso:country":"IN",
    "ks:ks_name":"Takali Talao",
    "ks:ks_pop":800,
    "ks:ks_type":"HABITATION",
    "name:eng_x_preferred":[
        "Takali Talao"
    ],
    "wof:name":"Takali Talao",
    "wof:placetype":"locality",
    "wof:population":800
},
  "geometry": {"coordinates":[76.386385,20.668778],"type":"Point"}
}