{
  "type": "Feature",
  "properties": {
    "iso:country":"IN",
    "ks:ks_name":"Kashipur",
    "ks:ks_pop":692,
    "ks:ks_type":"VILLAGE",
    "name:eng_x_preferred":[
        "Kashipur"
    ],
    "name:hin_x_preferred":[
        "\u0915\u093e\u0936\u0940\u092a\u0941\u0930"
    ],
    "wof:name":"Kashipur",
    "wof:placetype":"locality",
    "wof:population":692
},
  "geometry": {"coordinates":[87.57757599999999,21.957408],"type":"Point"}
}