{
  "type": "Feature",
  "properties": {
    "gn:admin1_code":"2",
    "gn:admin2_code":"545.0",
    "gn:asciiname":"Ravulapalem",
    "gn:country_code":"IN",
    "gn:dem":156,
    "gn:feature_class":"P",
    "gn:feature_code":"PPL",
    "gn:name":"R\u0101vulap\u0101lem",
    "gn:population":0,
    "gn:timezone":"Asia/Kolkata",
    "iso:country":"IN",
    "name:pam_x_preferred":[
        "Ravulapalem"
    ],
    "name:tgl_x_preferred":[
        "Ravulapalem"
    ],
    "name:urd_x_preferred":[
        "\u0631\u0627\u0648\u0644\u0627\u067e\u0627\u0644\u06cc\u0645"
    ],
    "name:vie_x_preferred":[
        "Ravulapalem"
    ],
    "wof:name":"Ravulapalem",
    "wof:placetype":"locality"
},
  "geometry": {"coordinates":[82.14375,17.48335],"type":"Point"}
}