{
  "type": "Feature",
  "properties": {
    "iso:country":"IN",
    "ks:ks_name":"Khidaki",
    "ks:ks_pop":373,
    "ks:ks_type":"VILLAGE",
    "name:eng_x_preferred":[
        "Khidaki"
    ],
    "wof:name":"Khidaki",
    "wof:placetype":"locality",
    "wof:population":373
},
  "geometry": {"coordinates":[72.960303,18.709109],"type":"Point"}
}