{
  "type": "Feature",
  "properties": {
    "iso:country":"IN",
    "ks:ks_name":"Nadidhipa",
    "ks:ks_pop":75,
    "ks:ks_type":"HABITATION",
    "name:eng_x_preferred":[
        "Nadidhipa"
    ],
    "wof:name":"Nadidhipa",
    "wof:placetype":"locality",
    "wof:population":75
},
  "geometry": {"coordinates":[85.27927200000001,23.244131],"type":"Point"}
}