{
  "type": "Feature",
  "properties": {
    "iso:country":"IN",
    "ks:ks_name":"Harijan Toli",
    "ks:ks_pop":651,
    "ks:ks_type":"HABITATION",
    "ks:ks_uagg_main":0,
    "name:eng_x_preferred":[
        "Harijan Toli"
    ],
    "wof:name":"Harijan Toli",
    "wof:placetype":"neighbourhood",
    "wof:population":651
},
  "geometry": {"coordinates":[84.625636,27.040171],"type":"Point"}
}