{
  "type": "Feature",
  "properties": {
    "gn:admin1_code":"35",
    "gn:admin2_code":"428.0",
    "gn:asciiname":"Agara",
    "gn:country_code":"IN",
    "gn:dem":349,
    "gn:feature_class":"P",
    "gn:feature_code":"PPL",
    "gn:name":"Ag\u0101ra",
    "gn:population":0,
    "gn:timezone":"Asia/Kolkata",
    "iso:country":"IN",
    "name:ceb_x_preferred":[
        "Agara"
    ],
    "name:swe_x_preferred":[
        "Agara"
    ],
    "wof:name":"Agara",
    "wof:placetype":"locality"
},
  "geometry": {"coordinates":[79.4114,24.1022],"type":"Point"}
}