{
  "type": "Feature",
  "properties": {
    "gn:admin1_code":"19.0",
    "gn:admin2_code":"571.0",
    "gn:asciiname":"Salantripalya",
    "gn:country_code":"IN",
    "gn:dem":795,
    "gn:feature_class":"P",
    "gn:feature_code":"PPL",
    "gn:name":"Salantrip\u0101lya",
    "gn:population":0,
    "gn:timezone":"Asia/Kolkata",
    "iso:country":"IN",
    "ks:ks_name":"Salanthripalya",
    "ks:ks_pop":120,
    "ks:ks_type":"HABITATION",
    "name:eng_x_preferred":[
        "Salanthripalya"
    ],
    "name:eng_x_variant":[
        "Salantripalya"
    ],
    "wof:name":"Salanthripalya",
    "wof:placetype":"locality",
    "wof:population":120
},
  "geometry": {"coordinates":[77.016842,12.97346],"type":"Point"}
}