{
  "type": "Feature",
  "properties": {
    "gn:admin1_code":"39.0",
    "gn:admin2_code":"60.0",
    "gn:asciiname":"Defence Colony",
    "gn:country_code":"IN",
    "gn:dem":626,
    "gn:feature_class":"P",
    "gn:feature_code":"PPL",
    "gn:name":"Defence Colony",
    "gn:population":0,
    "gn:timezone":"Asia/Kolkata",
    "iso:country":"IN",
    "name:ara_x_preferred":[
        "\u0645\u0633\u062a\u0639\u0645\u0631\u0629 \u062f\u064a\u0641\u0646\u0633 \u0643\u0648\u0644\u0648\u0646\u064a"
    ],
    "name:ben_bn_x_preferred":[
        "\u09a1\u09bf\u09ab\u09c7\u09a8\u09cd\u09b8 \u0995\u09b2\u09cb\u09a8\u09bf"
    ],
    "name:ben_in_x_preferred":[
        "\u09a1\u09bf\u09ab\u09c7\u09a8\u09cd\u09b8 \u0995\u09b2\u09cb\u09a8\u09bf"
    ],
    "name:guj_x_preferred":[
        "\u0aa1\u0abf\u0aab\u0ac7\u0aa8\u0acd\u0ab8 \u0a95\u0acb\u0ab2\u0acb\u0aa8\u0ac0"
    ],
    "name:hin_x_preferred":[
        "\u0921\u093f\u092b\u0947\u0928\u094d\u0938 \u0915\u0949\u0932\u094b\u0928\u0940"
    ],
    "name:hin_x_variant":[
        "\u0921\u093f\u092b\u0947\u0928\u094d\u0938 \u0915\u093e\u0932\u094b\u0928\u0940"
    ],
    "name:kan_x_preferred":[
        "\u0ca1\u0cbf\u0cab\u0cc6\u0ca8\u0ccd\u0cb8\u0ccd\u200c \u0c95\u0cbe\u0cb2\u0cca\u0ca8\u0cbf"
    ],
    "name:mal_x_preferred":[
        "\u0d21\u0d3f\u0d2b\u0d46\u0d28\u0d4d\u200d\u0d38\u0d4d \u0d15\u0d4b\u0d33\u0d28\u0d3f"
    ],
    "name:mar_x_preferred":[
        "\u0921\u093f\u092b\u0947\u0902\u0938 \u0915\u0949\u0932\u094b\u0928\u0940"
    ],
    "name:pan_x_preferred":[
        "\u0a21\u0a3f\u0a2b\u0a48\u0a02\u0a38 \u0a15\u0a32\u0a4c\u0a28\u0a40"
    ],
    "name:tam_x_preferred":[
        "\u0b87\u0bb0\u0bbe\u0ba3\u0bc1\u0bb5\u0b95\u0bcd \u0b95\u0bc1\u0b9f\u0bbf\u0baf\u0bbf\u0bb0\u0bc1\u0baa\u0bcd\u0baa\u0bc1"
    ],
    "name:tel_x_preferred":[
        "\u0c21\u0c3f\u0c2b\u0c46\u0c28\u0c4d\u0c38\u0c4d \u0c15\u0c3e\u0c32\u0c28\u0c40"
    ],
    "name:urd_x_preferred":[
        "\u0688\u0641\u06cc\u0646\u0633 \u06a9\u0627\u0644\u0648\u0646\u06cc"
    ],
    "name:urd_x_variant":[
        "\u0688\u06cc\u0641\u0646\u0633 \u06a9\u0627\u0644\u0648\u0646\u06cc"
    ],
    "wof:name":"Defence Colony",
    "wof:placetype":"locality"
},
  "geometry": {"coordinates":[78.05445999999998,30.27977000000001],"type":"Point"}
}