{
  "type": "Feature",
  "properties": {
    "gn:admin1_code":"39.0",
    "gn:admin2_code":"60.0",
    "gn:asciiname":"Defence Colony",
    "gn:country_code":"IN",
    "gn:dem":626,
    "gn:feature_class":"P",
    "gn:feature_code":"PPL",
    "gn:name":"Defence Colony",
    "gn:population":0,
    "gn:timezone":"Asia/Kolkata",
    "iso:country":"IN",
    "name:hin_x_preferred":[
        "\u0921\u093f\u092b\u0947\u0928\u094d\u0938 \u0915\u093e\u0932\u094b\u0928\u0940"
    ],
    "name:urd_x_preferred":[
        "\u0688\u06cc\u0641\u0646\u0633 \u06a9\u0627\u0644\u0648\u0646\u06cc"
    ],
    "wof:name":"Defence Colony",
    "wof:placetype":"locality"
},
  "geometry": {"coordinates":[78.05445999999998,30.27977000000001],"type":"Point"}
}