{
  "type": "Feature",
  "properties": {
    "iso:country":"IN",
    "ks:ks_name":"Ajitha Mane",
    "ks:ks_pop":22,
    "ks:ks_type":"HABITATION",
    "name:eng_x_preferred":[
        "Ajitha Mane"
    ],
    "wof:name":"Ajitha Mane",
    "wof:placetype":"locality",
    "wof:population":22
},
  "geometry": {"coordinates":[75.60722199999999,12.357222],"type":"Point"}
}