{
  "type": "Feature",
  "properties": {
    "iso:country":"IN",
    "ks:ks_name":"Kurumbar Kottai",
    "ks:ks_pop":102,
    "ks:ks_type":"HABITATION",
    "name:eng_x_preferred":[
        "Kurumbar Kottai"
    ],
    "wof:name":"Kurumbar Kottai",
    "wof:placetype":"locality",
    "wof:population":102
},
  "geometry": {"coordinates":[78.21086099999999,12.605295],"type":"Point"}
}