{
  "type": "Feature",
  "properties": {
    "iso:country":"IN",
    "ks:ks_name":"Bhetiya Dakshin",
    "ks:ks_pop":312,
    "ks:ks_type":"VILLAGE",
    "name:eng_x_preferred":[
        "Bhetiya Dakshin"
    ],
    "wof:name":"Bhetiya Dakshin",
    "wof:placetype":"locality",
    "wof:population":312
},
  "geometry": {"coordinates":[87.272626,21.821332],"type":"Point"}
}