{
  "type": "Feature",
  "properties": {
    "gn:admin1_code":"36",
    "gn:admin2_code":"172.0",
    "gn:asciiname":"Tendua",
    "gn:country_code":"IN",
    "gn:dem":113,
    "gn:feature_class":"P",
    "gn:feature_code":"PPL",
    "gn:name":"Tendua",
    "gn:population":0,
    "gn:timezone":"Asia/Kolkata",
    "iso:country":"IN",
    "ks:ks_name":"Tendua",
    "ks:ks_pop":2474,
    "ks:ks_type":"VILLAGE",
    "name:eng_x_preferred":[
        "Tendua"
    ],
    "wof:name":"Tendua",
    "wof:placetype":"locality",
    "wof:population":2474
},
  "geometry": {"coordinates":[81.201948,25.655184],"type":"Point"}
}