{
  "type": "Feature",
  "properties": {
    "iso:country":"IN",
    "ks:ks_name":"Madhuban",
    "ks:ks_pop":0,
    "ks:ks_type":"VILLAGE",
    "name:eng_x_preferred":[
        "Madhuban"
    ],
    "wof:name":"Madhuban",
    "wof:placetype":"locality",
    "wof:population":0
},
  "geometry": {"coordinates":[88.133894,25.333598],"type":"Point"}
}