{
  "type": "Feature",
  "properties": {
    "iso:country":"IN",
    "ks:ks_name":"Bazarpurwa",
    "ks:ks_pop":228,
    "ks:ks_type":"HABITATION",
    "ks:ks_uagg_main":0,
    "name:eng_x_preferred":[
        "Bazarpurwa"
    ],
    "wof:name":"Bazarpurwa",
    "wof:placetype":"neighbourhood",
    "wof:population":228
},
  "geometry": {"coordinates":[80.896356,28.064304],"type":"Point"}
}