{
  "type": "Feature",
  "properties": {
    "gn:admin1_code":"23.0",
    "gn:admin2_code":"42.0",
    "gn:asciiname":"Khokri Bhula Singh",
    "gn:country_code":"IN",
    "gn:dem":228,
    "gn:feature_class":"P",
    "gn:feature_code":"PPL",
    "gn:name":"Khokri Bhula Singh",
    "gn:population":0,
    "gn:timezone":"Asia/Kolkata",
    "iso:country":"IN",
    "wof:name":"Khokri Bhula Singh",
    "wof:placetype":"locality"
},
  "geometry": {"coordinates":[75.32080999999999,30.82911],"type":"Point"}
}