{
  "type": "Feature",
  "properties": {
    "iso:country":"IN",
    "ks:ks_alt_nam":"BANAINIA",
    "ks:ks_name":"Banainia",
    "ks:ks_pop":172,
    "ks:ks_type":"HABITATION",
    "ks:ks_uagg_main":0,
    "name:eng_x_preferred":[
        "Banainia"
    ],
    "wof:name":"Banainia",
    "wof:placetype":"neighbourhood",
    "wof:population":172
},
  "geometry": {"coordinates":[86.75076,26.412122],"type":"Point"}
}