{
  "type": "Feature",
  "properties": {
    "gn:admin1_code":"37.0",
    "gn:admin2_code":"412.0",
    "gn:asciiname":"Jarwadih",
    "gn:country_code":"IN",
    "gn:dem":298,
    "gn:feature_class":"P",
    "gn:feature_code":"PPL",
    "gn:name":"Jarw\u0101dih",
    "gn:population":0,
    "gn:timezone":"Asia/Kolkata",
    "iso:country":"IN",
    "wof:name":"Jarwadih",
    "wof:placetype":"locality"
},
  "geometry": {"coordinates":[81.63594999999999,20.96786],"type":"Point"}
}