{
  "type": "Feature",
  "properties": {
    "iso:country":"IN",
    "ks:ks_name":"Ratanpuri Kaular Chal",
    "ks:ks_pop":557,
    "ks:ks_type":"HABITATION",
    "name:eng_x_preferred":[
        "Ratanpuri Kaular Chal"
    ],
    "wof:name":"Ratanpuri Kaular Chal",
    "wof:placetype":"locality",
    "wof:population":557
},
  "geometry": {"coordinates":[74.794,18.05],"type":"Point"}
}