{
  "type": "Feature",
  "properties": {
    "gn:admin1_code":"25.0",
    "gn:admin2_code":"608.0",
    "gn:asciiname":"Adaiyur",
    "gn:country_code":"IN",
    "gn:dem":287,
    "gn:feature_class":"P",
    "gn:feature_code":"PPL",
    "gn:name":"\u0100daiy\u016br",
    "gn:population":0,
    "gn:timezone":"Asia/Kolkata",
    "iso:country":"IN",
    "ks:ks_alt_nam":"\u0100daiy\u016br",
    "ks:ks_name":"Adaiyur",
    "ks:ks_pop":3155,
    "ks:ks_type":"VILLAGE",
    "name:eng_x_preferred":[
        "Adaiyur"
    ],
    "name:eng_x_variant":[
        "\u0100daiy\u016br"
    ],
    "wof:name":"Adaiyur",
    "wof:placetype":"locality",
    "wof:population":3155
},
  "geometry": {"coordinates":[77.839769,11.692337],"type":"Point"}
}