{
  "type": "Feature",
  "properties": {
    "iso:country":"IN",
    "ks:ks_alt_nam":"Jhaua HARIJAN TOLA",
    "ks:ks_name":"Jhaua Harijan Tola",
    "ks:ks_pop":652,
    "ks:ks_type":"HABITATION",
    "ks:ks_uagg_main":0,
    "name:eng_x_preferred":[
        "Jhaua Harijan Tola"
    ],
    "wof:name":"Jhaua Harijan Tola",
    "wof:placetype":"neighbourhood",
    "wof:population":652
},
  "geometry": {"coordinates":[84.92168100000001,25.761657],"type":"Point"}
}