{
  "type": "Feature",
  "properties": {
    "iso:country":"IN",
    "ks:ks_alt_nam":"Ban Barion Ki dhani",
    "ks:ks_name":"Ban Barion Ki Dhani",
    "ks:ks_pop":120,
    "ks:ks_type":"HABITATION",
    "name:eng_x_preferred":[
        "Ban Barion Ki Dhani"
    ],
    "wof:name":"Ban Barion Ki Dhani",
    "wof:placetype":"locality",
    "wof:population":120
},
  "geometry": {"coordinates":[74.283767,29.572061],"type":"Point"}
}