{
  "type": "Feature",
  "properties": {
    "iso:country":"IN",
    "ks:ks_name":"Sadikpur",
    "ks:ks_pop":35,
    "ks:ks_type":"HABITATION",
    "name:eng_x_preferred":[
        "Sadikpur"
    ],
    "wof:name":"Sadikpur",
    "wof:placetype":"locality",
    "wof:population":35
},
  "geometry": {"coordinates":[75.331585,22.185814],"type":"Point"}
}