{
  "type": "Feature",
  "properties": {
    "iso:country":"IN",
    "ks:ks_name":"Domaria",
    "ks:ks_pop":525,
    "ks:ks_type":"HABITATION",
    "ks:ks_uagg_main":0,
    "name:eng_x_preferred":[
        "Domaria"
    ],
    "wof:name":"Domaria",
    "wof:placetype":"neighbourhood",
    "wof:population":525
},
  "geometry": {"coordinates":[87.27557,26.338444],"type":"Point"}
}