{
  "type": "Feature",
  "properties": {
    "iso:country":"IN",
    "ks:ks_name":"Manhat",
    "ks:ks_type":"VILLAGE",
    "ks:ks_uagg_main":0,
    "name:eng_x_preferred":[
        "Manhat"
    ],
    "wof:name":"Manhat",
    "wof:placetype":"neighbourhood"
},
  "geometry": {"coordinates":[83.38990699999999,26.724929],"type":"Point"}
}