{
  "type": "Feature",
  "properties": {
    "iso:country":"IN",
    "ks:ks_name":"Thalamadai",
    "ks:ks_pop":268,
    "ks:ks_type":"HABITATION",
    "ks:ks_uagg_main":0,
    "name:eng_x_preferred":[
        "Thalamadai"
    ],
    "wof:name":"Thalamadai",
    "wof:placetype":"neighbourhood",
    "wof:population":268
},
  "geometry": {"coordinates":[77.761644,11.262151],"type":"Point"}
}