{
  "type": "Feature",
  "properties": {
    "gn:admin1_code":"2.0",
    "gn:admin2_code":"544.0",
    "gn:asciiname":"Putluru",
    "gn:country_code":"IN",
    "gn:dem":969,
    "gn:feature_class":"P",
    "gn:feature_code":"PPL",
    "gn:name":"P\u016btl\u016bru",
    "gn:population":0,
    "gn:timezone":"Asia/Kolkata",
    "iso:country":"IN",
    "ks:ks_name":"Puturu",
    "ks:ks_pop":178,
    "ks:ks_type":"HABITATION",
    "name:eng_x_preferred":[
        "Puturu"
    ],
    "name:eng_x_variant":[
        "Putluru"
    ],
    "wof:name":"Puturu",
    "wof:placetype":"locality",
    "wof:population":178
},
  "geometry": {"coordinates":[82.531408,18.236043],"type":"Point"}
}