{
  "type": "Feature",
  "properties": {
    "iso:country":"IN",
    "ks:ks_name":"Srirampuram",
    "ks:ks_pop":4,
    "ks:ks_type":"HABITATION",
    "name:eng_x_preferred":[
        "Srirampuram"
    ],
    "wof:name":"Srirampuram",
    "wof:placetype":"locality",
    "wof:population":4
},
  "geometry": {"coordinates":[78.836815,13.814623],"type":"Point"}
}