{
  "type": "Feature",
  "properties": {
    "gn:admin1_code":"12.0",
    "gn:admin2_code":"001",
    "gn:asciiname":"Supar Naghom",
    "gn:country_code":"IN",
    "gn:dem":1596,
    "gn:feature_class":"P",
    "gn:feature_code":"PPL",
    "gn:name":"Supar N\u0101ghom",
    "gn:population":0,
    "gn:timezone":"Asia/Kolkata",
    "iso:country":"IN",
    "wof:name":"Supar Naghom",
    "wof:placetype":"locality"
},
  "geometry": {"coordinates":[74.3524,34.35707],"type":"Point"}
}