{
  "type": "Feature",
  "properties": {
    "iso:country":"IN",
    "ks:ks_name":"Kindaru",
    "ks:ks_pop":16,
    "ks:ks_type":"VILLAGE",
    "name:eng_x_preferred":[
        "Kindaru"
    ],
    "wof:name":"Kindaru",
    "wof:placetype":"locality",
    "wof:population":16
},
  "geometry": {"coordinates":[83.979849,19.05989],"type":"Point"}
}