{
  "type": "Feature",
  "properties": {
    "iso:country":"IN",
    "ks:ks_name":"Chakia",
    "ks:ks_pop":348,
    "ks:ks_type":"VILLAGE",
    "name:eng_x_preferred":[
        "Chakia"
    ],
    "wof:name":"Chakia",
    "wof:placetype":"locality",
    "wof:population":348
},
  "geometry": {"coordinates":[85.324243,26.081175],"type":"Point"}
}