{
  "type": "Feature",
  "properties": {
    "iso:country":"IN",
    "ks:ks_name":"Baddana Family",
    "ks:ks_pop":118,
    "ks:ks_type":"HABITATION",
    "name:eng_x_preferred":[
        "Baddana Family"
    ],
    "wof:name":"Baddana Family",
    "wof:placetype":"locality",
    "wof:population":118
},
  "geometry": {"coordinates":[75.765,12.376389],"type":"Point"}
}