{
  "type": "Feature",
  "properties": {
    "iso:country":"IN",
    "ks:ks_name":"Bhaduliya Tola",
    "ks:ks_pop":379,
    "ks:ks_type":"HABITATION",
    "name:eng_x_preferred":[
        "Bhaduliya Tola"
    ],
    "wof:name":"Bhaduliya Tola",
    "wof:placetype":"locality",
    "wof:population":379
},
  "geometry": {"coordinates":[83.73765,24.108562],"type":"Point"}
}