{
  "type": "Feature",
  "properties": {
    "iso:country":"IN",
    "ks:ks_name":"Kotwa Tola",
    "ks:ks_pop":315,
    "ks:ks_type":"HABITATION",
    "ks:ks_uagg_main":0,
    "name:eng_x_preferred":[
        "Kotwa Tola"
    ],
    "wof:name":"Kotwa Tola",
    "wof:placetype":"neighbourhood",
    "wof:population":315
},
  "geometry": {"coordinates":[83.891458,27.210794],"type":"Point"}
}