{
  "type": "Feature",
  "properties": {
    "iso:country":"IN",
    "ks:ks_name":"Borigaon Pub",
    "ks:ks_pop":500,
    "ks:ks_type":"HABITATION",
    "name:eng_x_preferred":[
        "Borigaon Pub"
    ],
    "wof:name":"Borigaon Pub",
    "wof:placetype":"locality",
    "wof:population":500
},
  "geometry": {"coordinates":[91.41986799999999,26.477041],"type":"Point"}
}