{
  "type": "Feature",
  "properties": {
    "iso:country":"IN",
    "ks:ks_name":"Garhi",
    "ks:ks_pop":271,
    "ks:ks_type":"VILLAGE",
    "name:eng_x_preferred":[
        "Garhi"
    ],
    "wof:name":"Garhi",
    "wof:placetype":"locality",
    "wof:population":271
},
  "geometry": {"coordinates":[86.183724,24.579155],"type":"Point"}
}