{
  "type": "Feature",
  "properties": {
    "iso:country":"IN",
    "ks:ks_name":"Bagji Ka Par",
    "ks:ks_pop":200,
    "ks:ks_type":"HABITATION",
    "name:eng_x_preferred":[
        "Bagji Ka Par"
    ],
    "wof:name":"Bagji Ka Par",
    "wof:placetype":"locality",
    "wof:population":200
},
  "geometry": {"coordinates":[72.18572500000001,27.236718],"type":"Point"}
}