{
  "type": "Feature",
  "properties": {
    "gn:admin1_code":"19.0",
    "gn:admin2_code":"578.0",
    "gn:asciiname":"Mukahalli",
    "gn:country_code":"IN",
    "gn:dem":712,
    "gn:feature_class":"P",
    "gn:feature_code":"PPL",
    "gn:name":"M\u016bkahalli",
    "gn:population":0,
    "gn:timezone":"Asia/Kolkata",
    "iso:country":"IN",
    "ks:ks_name":"K Mukahalli",
    "ks:ks_pop":443,
    "ks:ks_type":"VILLAGE",
    "name:eng_x_preferred":[
        "K Mukahalli"
    ],
    "name:eng_x_variant":[
        "Mukahalli"
    ],
    "wof:name":"K Mukahalli",
    "wof:placetype":"locality",
    "wof:population":443
},
  "geometry": {"coordinates":[76.935344,12.006966],"type":"Point"}
}