{
  "type": "Feature",
  "properties": {
    "gn:admin1_code":"19.0",
    "gn:admin2_code":"578.0",
    "gn:asciiname":"Mukahalli",
    "gn:country_code":"IN",
    "gn:dem":712,
    "gn:feature_class":"P",
    "gn:feature_code":"PPL",
    "gn:name":"M\u016bkahalli",
    "gn:population":0,
    "gn:timezone":"Asia/Kolkata",
    "iso:country":"IN",
    "wof:name":"Mukahalli",
    "wof:placetype":"locality"
},
  "geometry": {"coordinates":[76.93448000000002,12.00454],"type":"Point"}
}