{
  "type": "Feature",
  "properties": {
    "iso:country":"IN",
    "ks:ks_name":"No 6 Char",
    "ks:ks_pop":1446,
    "ks:ks_type":"HABITATION",
    "ks:ks_uagg_main":0,
    "name:eng_x_preferred":[
        "No 6 Char"
    ],
    "wof:name":"No 6 Char",
    "wof:placetype":"neighbourhood",
    "wof:population":1446
},
  "geometry": {"coordinates":[90.639662,26.23865],"type":"Point"}
}