{
  "type": "Feature",
  "properties": {
    "iso:country":"IN",
    "ks:ks_alt_nam":"Villiyanall\u016br",
    "ks:ks_name":"Villiyanallur",
    "ks:ks_type":"VILLAGE",
    "ks:ks_uagg_main":0,
    "name:eng_x_preferred":[
        "Villiyanallur"
    ],
    "name:eng_x_variant":[
        "Villiyanall\u016br"
    ],
    "wof:name":"Villiyanallur",
    "wof:placetype":"neighbourhood"
},
  "geometry": {"coordinates":[79.55407200000001,11.088084],"type":"Point"}
}