{
  "type": "Feature",
  "properties": {
    "iso:country":"IN",
    "ks:ks_name":"Amanpura",
    "ks:ks_pop":288,
    "ks:ks_type":"VILLAGE",
    "name:eng_x_preferred":[
        "Amanpura"
    ],
    "wof:name":"Amanpura",
    "wof:placetype":"locality",
    "wof:population":288
},
  "geometry": {"coordinates":[77.25488300000001,26.472408],"type":"Point"}
}