{
  "type": "Feature",
  "properties": {
    "gn:country":"IN",
    "gn:fcode":"PPL",
    "gn:population":0,
    "iso:country":"IN",
    "name:ara_x_preferred":[
        "\u0645\u0627\u062c\u064a\u0631\u0627"
    ],
    "name:ben_bn_x_preferred":[
        "\u09ae\u09be\u099c\u09b0\u09be"
    ],
    "name:ben_in_x_preferred":[
        "\u09ae\u09be\u099c\u09b0\u09be"
    ],
    "name:guj_x_preferred":[
        "\u0aae\u0abe\u0a9c\u0acd\u0ab0\u0abe"
    ],
    "name:hin_x_preferred":[
        "\u092e\u093e\u091c\u0930\u093e"
    ],
    "name:kan_x_preferred":[
        "\u0cae\u0cbe\u0c9c\u0ccd\u0cb0\u0cbe"
    ],
    "name:mal_x_preferred":[
        "\u0d2e\u0d1c\u0d4d"
    ],
    "name:mar_x_preferred":[
        "\u092e\u093e\u091c\u0930\u093e"
    ],
    "name:pan_x_preferred":[
        "\u0a2e\u0a3e\u0a1c\u0a30\u0a3e"
    ],
    "name:tam_x_preferred":[
        "\u0bae\u0b9c\u0bcd\u0bb0\u0bbe"
    ],
    "name:tel_x_preferred":[
        "\u0c2e\u0c1c\u0c4d\u0c30\u0c3e"
    ],
    "name:urd_x_preferred":[
        "\u0645\u0627\u062c\u0631\u0627"
    ],
    "qs_pg:aaroncc":"IN",
    "qs_pg:gn_country":"IN",
    "qs_pg:gn_fcode":"PPL",
    "qs_pg:gn_pop":0,
    "qs_pg:name":"Majra",
    "qs_pg:name_adm0":"India",
    "qs_pg:name_adm1":"Haryana",
    "qs_pg:photos_9r":0,
    "qs_pg:photos_sr":0,
    "qs_pg:pop_sr":0,
    "qs_pg:qs_pg_placetype":"locality",
    "qs_pg:qs_pg_placetype_gp":"Town",
    "qs_pg:woe_adm0":23424848,
    "woe:adm0_id":23424848,
    "woe:name_adm0":"India",
    "woe:name_adm1":"Haryana",
    "woe:placetype":"Town",
    "wof:name":"Majra",
    "wof:placetype":"neighbourhood"
},
  "geometry": {"coordinates":[75.926,30.12919],"type":"Point"}
}