{
  "type": "Feature",
  "properties": {
    "iso:country":"IN",
    "ks:ks_alt_nam":"Devkate wasti",
    "ks:ks_name":"Devkate Wasti",
    "ks:ks_pop":60,
    "ks:ks_type":"HABITATION",
    "name:eng_x_preferred":[
        "Devkate Wasti"
    ],
    "wof:name":"Devkate Wasti",
    "wof:placetype":"locality",
    "wof:population":60
},
  "geometry": {"coordinates":[75.585527,18.449786],"type":"Point"}
}