{
  "type": "Feature",
  "properties": {
    "iso:country":"IN",
    "ks:ks_name":"Gaddemane",
    "ks:ks_pop":354,
    "ks:ks_type":"HABITATION",
    "name:eng_x_preferred":[
        "Gaddemane"
    ],
    "wof:name":"Gaddemane",
    "wof:placetype":"locality",
    "wof:population":354
},
  "geometry": {"coordinates":[75.139886,14.339569],"type":"Point"}
}