{
  "type": "Feature",
  "properties": {
    "gn:admin1_code":"35.0",
    "gn:admin2_code":"455.0",
    "gn:asciiname":"Ghanadhana",
    "gn:country_code":"IN",
    "gn:dem":741,
    "gn:feature_class":"P",
    "gn:feature_code":"PPL",
    "gn:name":"Gh\u0101n\u0101dhana",
    "gn:population":0,
    "gn:timezone":"Asia/Kolkata",
    "iso:country":"IN",
    "wof:name":"Ghanadhana",
    "wof:placetype":"locality"
},
  "geometry": {"coordinates":[78.55790999999998,22.16800000000001],"type":"Point"}
}