{
  "type": "Feature",
  "properties": {
    "gn:admin1_code":"11.0",
    "gn:admin2_code":"27.0",
    "gn:asciiname":"Phandrohal",
    "gn:country_code":"IN",
    "gn:dem":1514,
    "gn:feature_class":"P",
    "gn:feature_code":"PPL",
    "gn:name":"Phandrohal",
    "gn:population":0,
    "gn:timezone":"Asia/Kolkata",
    "iso:country":"IN",
    "wof:name":"Phandrohal",
    "wof:placetype":"locality"
},
  "geometry": {"coordinates":[77.21406,31.27915],"type":"Point"}
}