{
  "type": "Feature",
  "properties": {
    "iso:country":"IN",
    "ks:ks_name":"Buddigaruvu",
    "ks:ks_pop":120,
    "ks:ks_type":"VILLAGE",
    "name:eng_x_preferred":[
        "Buddigaruvu"
    ],
    "wof:name":"Buddigaruvu",
    "wof:placetype":"locality",
    "wof:population":120
},
  "geometry": {"coordinates":[82.908582,18.124264],"type":"Point"}
}