{
  "type": "Feature",
  "properties": {
    "gn:admin1_code":"21.0",
    "gn:admin2_code":"398.0",
    "gn:asciiname":"Pedda Bitra",
    "gn:country_code":"IN",
    "gn:dem":955,
    "gn:feature_class":"P",
    "gn:feature_code":"PPL",
    "gn:name":"Pedda Bitra",
    "gn:population":0,
    "gn:timezone":"Asia/Kolkata",
    "iso:country":"IN",
    "wof:name":"Pedda Bitra",
    "wof:placetype":"locality"
},
  "geometry": {"coordinates":[83.02823000000002,18.56166],"type":"Point"}
}