{
  "type": "Feature",
  "properties": {
    "iso:country":"IN",
    "ks:ks_name":"Pichakhali",
    "ks:ks_pop":1399,
    "ks:ks_type":"HABITATION",
    "name:eng_x_preferred":[
        "Pichakhali"
    ],
    "wof:name":"Pichakhali",
    "wof:placetype":"locality",
    "wof:population":1399
},
  "geometry": {"coordinates":[88.592816,22.171424],"type":"Point"}
}