{
  "type": "Feature",
  "properties": {
    "iso:country":"IN",
    "ks:ks_name":"Gadai Chak",
    "ks:ks_pop":556,
    "ks:ks_type":"VILLAGE",
    "name:eng_x_preferred":[
        "Gadai Chak"
    ],
    "wof:name":"Gadai Chak",
    "wof:placetype":"locality",
    "wof:population":556
},
  "geometry": {"coordinates":[85.35814999999999,26.257418],"type":"Point"}
}