{
  "type": "Feature",
  "properties": {
    "iso:country":"IN",
    "ks:ks_name":"Neharwadi",
    "ks:ks_pop":150,
    "ks:ks_type":"HABITATION",
    "name:eng_x_preferred":[
        "Neharwadi"
    ],
    "wof:name":"Neharwadi",
    "wof:placetype":"locality",
    "wof:population":150
},
  "geometry": {"coordinates":[74.405779,19.405058],"type":"Point"}
}