{
  "type": "Feature",
  "properties": {
    "iso:country":"IN",
    "ks:ks_name":"Bhadav",
    "ks:ks_pop":808,
    "ks:ks_type":"VILLAGE",
    "ks:ks_uagg_main":0,
    "name:eng_x_preferred":[
        "Bhadav"
    ],
    "wof:name":"Bhadav",
    "wof:placetype":"neighbourhood",
    "wof:population":808
},
  "geometry": {"coordinates":[73.28564799999999,18.232049],"type":"Point"}
}