{
  "type": "Feature",
  "properties": {
    "gn:admin1_code":"19.0",
    "gn:admin2_code":"578.0",
    "gn:asciiname":"Kellamballi",
    "gn:country_code":"IN",
    "gn:dem":737,
    "gn:feature_class":"P",
    "gn:feature_code":"PPL",
    "gn:name":"Kellamballi",
    "gn:population":0,
    "gn:timezone":"Asia/Kolkata",
    "iso:country":"IN",
    "wof:name":"Kellamballi",
    "wof:placetype":"locality"
},
  "geometry": {"coordinates":[76.91110999999999,11.97916],"type":"Point"}
}