{
  "type": "Feature",
  "properties": {
    "iso:country":"IN",
    "ks:ks_alt_nam":"White Way jun",
    "ks:ks_name":"White Way Jun",
    "ks:ks_pop":573,
    "ks:ks_type":"HABITATION",
    "ks:ks_uagg_main":0,
    "name:eng_x_preferred":[
        "White Way Jun"
    ],
    "wof:name":"White Way Jun",
    "wof:placetype":"locality",
    "wof:population":573
},
  "geometry": {"coordinates":[76.204455,10.561575],"type":"Point"}
}