{
  "type": "Feature",
  "properties": {
    "gn:admin1_code":"34.0",
    "gn:admin2_code":"225.0",
    "gn:asciiname":"Pirhamu",
    "gn:country_code":"IN",
    "gn:dem":119,
    "gn:feature_class":"P",
    "gn:feature_code":"PPL",
    "gn:name":"Pirh\u0101mu",
    "gn:population":0,
    "gn:timezone":"Asia/Kolkata",
    "iso:country":"IN",
    "ks:ks_alt_nam":"Pirh\u0101mu",
    "ks:ks_name":"Pirhamu",
    "ks:ks_type":"VILLAGE",
    "name:eng_x_preferred":[
        "Pirhamu"
    ],
    "name:eng_x_variant":[
        "Pirh\u0101mu"
    ],
    "wof:name":"Pirhamu",
    "wof:placetype":"locality"
},
  "geometry": {"coordinates":[87.02814600000001,24.755569],"type":"Point"}
}