{
  "type": "Feature",
  "properties": {
    "iso:country":"IN",
    "ks:ks_name":"Chikkayelachagere",
    "ks:ks_pop":217,
    "ks:ks_type":"VILLAGE",
    "name:eng_x_preferred":[
        "Chikkayelachagere"
    ],
    "wof:name":"Chikkayelachagere",
    "wof:placetype":"locality",
    "wof:population":217
},
  "geometry": {"coordinates":[77.22622200000001,12.40676],"type":"Point"}
}