{
  "type": "Feature",
  "properties": {
    "iso:country":"IN",
    "ks:ks_name":"Pallikkadavu",
    "ks:ks_pop":588,
    "ks:ks_type":"HABITATION",
    "name:eng_x_preferred":[
        "Pallikkadavu"
    ],
    "wof:name":"Pallikkadavu",
    "wof:placetype":"locality",
    "wof:population":588
},
  "geometry": {"coordinates":[76.646086,9.017801],"type":"Point"}
}