{
  "type": "Feature",
  "properties": {
    "iso:country":"IN",
    "ks:ks_name":"Kunnumpuram Jn",
    "ks:ks_pop":357,
    "ks:ks_type":"HABITATION",
    "name:eng_x_preferred":[
        "Kunnumpuram Jn"
    ],
    "wof:name":"Kunnumpuram Jn",
    "wof:placetype":"locality",
    "wof:population":357
},
  "geometry": {"coordinates":[76.108339,11.183491],"type":"Point"}
}