{
  "type": "Feature",
  "properties": {
    "iso:country":"IN",
    "ks:ks_name":"Benipurbheta",
    "ks:ks_pop":594,
    "ks:ks_type":"HABITATION",
    "name:eng_x_preferred":[
        "Benipurbheta"
    ],
    "wof:name":"Benipurbheta",
    "wof:placetype":"locality",
    "wof:population":594
},
  "geometry": {"coordinates":[82.03254200000001,27.231689],"type":"Point"}
}