{
  "type": "Feature",
  "properties": {
    "iso:country":"IN",
    "ks:ks_alt_nam":"Sinji Gairi gaon",
    "ks:ks_name":"Sinji Gairi Gaon",
    "ks:ks_pop":580,
    "ks:ks_type":"HABITATION",
    "name:eng_x_preferred":[
        "Sinji Gairi Gaon"
    ],
    "wof:name":"Sinji Gairi Gaon",
    "wof:placetype":"locality",
    "wof:population":580
},
  "geometry": {"coordinates":[88.51510399999999,27.002676],"type":"Point"}
}