{
  "type": "Feature",
  "properties": {
    "gn:admin1_code":"37.0",
    "gn:admin2_code":"404.0",
    "gn:asciiname":"Merai",
    "gn:country_code":"IN",
    "gn:dem":404,
    "gn:feature_class":"P",
    "gn:feature_code":"PPL",
    "gn:name":"Merai",
    "gn:population":0,
    "gn:timezone":"Asia/Kolkata",
    "iso:country":"IN",
    "ks:ks_name":"Merai",
    "ks:ks_pop":592,
    "ks:ks_type":"VILLAGE",
    "name:eng_x_preferred":[
        "Merai"
    ],
    "wof:name":"Merai",
    "wof:placetype":"locality",
    "wof:population":592
},
  "geometry": {"coordinates":[82.264324,22.678971],"type":"Point"}
}