{
  "type": "Feature",
  "properties": {
    "iso:country":"IN",
    "ks:ks_name":"Mahajon Praper",
    "ks:ks_pop":942,
    "ks:ks_type":"HABITATION",
    "name:eng_x_preferred":[
        "Mahajon Praper"
    ],
    "wof:name":"Mahajon Praper",
    "wof:placetype":"locality",
    "wof:population":942
},
  "geometry": {"coordinates":[84.02570900000001,26.753553],"type":"Point"}
}