{
  "type": "Feature",
  "properties": {
    "iso:country":"IN",
    "ks:ks_alt_nam":"PURANI BAZAR",
    "ks:ks_name":"Purani Bazar",
    "ks:ks_pop":292,
    "ks:ks_type":"HABITATION",
    "name:eng_x_preferred":[
        "Purani Bazar"
    ],
    "wof:name":"Purani Bazar",
    "wof:placetype":"locality",
    "wof:population":292
},
  "geometry": {"coordinates":[87.412064,25.939731],"type":"Point"}
}