{
  "type": "Feature",
  "properties": {
    "iso:country":"IN",
    "ks:ks_name":"Mandaliya",
    "ks:ks_pop":309,
    "ks:ks_type":"VILLAGE",
    "name:eng_x_preferred":[
        "Mandaliya"
    ],
    "wof:name":"Mandaliya",
    "wof:placetype":"locality",
    "wof:population":309
},
  "geometry": {"coordinates":[72.566918,24.327341],"type":"Point"}
}