{
  "type": "Feature",
  "properties": {
    "gn:admin1_code":"25.0",
    "gn:admin2_code":"617.0",
    "gn:asciiname":"Perundurai",
    "gn:country_code":"IN",
    "gn:dem":30,
    "gn:feature_class":"P",
    "gn:feature_code":"PPL",
    "gn:name":"Perundurai",
    "gn:population":0,
    "gn:timezone":"Asia/Kolkata",
    "iso:country":"IN",
    "name:bpy_x_preferred":[
        "\u09aa\u09c7\u09b0\u09c1\u09a8\u09a1\u09c1\u09b0\u09be\u0987"
    ],
    "name:ceb_x_preferred":[
        "Perundurai"
    ],
    "name:ind_x_preferred":[
        "Perundurai"
    ],
    "name:ita_x_preferred":[
        "Perundurai"
    ],
    "name:mlg_x_preferred":[
        "Perundurai"
    ],
    "name:msa_x_preferred":[
        "Perundurai"
    ],
    "name:nld_x_preferred":[
        "Perundurai"
    ],
    "name:swe_x_preferred":[
        "Perundurai"
    ],
    "name:tam_x_preferred":[
        "\u0baa\u0bc6\u0bb0\u0bc1\u0ba8\u0bcd\u0ba4\u0bc1\u0bb1\u0bc8"
    ],
    "name:vie_x_preferred":[
        "Perundurai"
    ],
    "name:zho_x_preferred":[
        "\u4f69\u4f26\u675c\u8d56"
    ],
    "wof:name":"Perundurai",
    "wof:placetype":"locality"
},
  "geometry": {"coordinates":[79.45215999999998,11.43276],"type":"Point"}
}