{
  "type": "Feature",
  "properties": {
    "iso:country":"IN",
    "ks:ks_name":"Jaliya",
    "ks:ks_pop":55,
    "ks:ks_type":"HABITATION",
    "name:eng_x_preferred":[
        "Jaliya"
    ],
    "wof:name":"Jaliya",
    "wof:placetype":"locality",
    "wof:population":55
},
  "geometry": {"coordinates":[74.418994,23.228906],"type":"Point"}
}