{
  "type": "Feature",
  "properties": {
    "gn:admin1_code":"11",
    "gn:admin2_code":"23.0",
    "gn:asciiname":"Dhuni Jhikla",
    "gn:country_code":"IN",
    "gn:dem":2073,
    "gn:feature_class":"P",
    "gn:feature_code":"PPL",
    "gn:name":"Dh\u016bni Jhikla",
    "gn:population":0,
    "gn:timezone":"Asia/Kolkata",
    "iso:country":"IN",
    "wof:name":"Dhuni Jhikla",
    "wof:placetype":"locality"
},
  "geometry": {"coordinates":[76.03681,32.48884],"type":"Point"}
}