{
  "type": "Feature",
  "properties": {
    "iso:country":"IN",
    "ks:ks_name":"Kashegudishelu",
    "ks:ks_pop":208,
    "ks:ks_type":"HABITATION",
    "name:eng_x_preferred":[
        "Kashegudishelu"
    ],
    "wof:name":"Kashegudishelu",
    "wof:placetype":"locality",
    "wof:population":208
},
  "geometry": {"coordinates":[79.183181,17.75995],"type":"Point"}
}