{
  "type": "Feature",
  "properties": {
    "iso:country":"IN",
    "ks:ks_name":"Hosagadde",
    "ks:ks_pop":24,
    "ks:ks_type":"HABITATION",
    "name:eng_x_preferred":[
        "Hosagadde"
    ],
    "wof:name":"Hosagadde",
    "wof:placetype":"locality",
    "wof:population":24
},
  "geometry": {"coordinates":[75.333321,13.375708],"type":"Point"}
}