{
  "type": "Feature",
  "properties": {
    "iso:country":"IN",
    "ks:ks_name":"Ahovi",
    "ks:ks_pop":511,
    "ks:ks_type":"HABITATION",
    "name:eng_x_preferred":[
        "Ahovi"
    ],
    "wof:name":"Ahovi",
    "wof:placetype":"locality",
    "wof:population":511
},
  "geometry": {"coordinates":[93.86805699999999,26.080329],"type":"Point"}
}