{
  "type": "Feature",
  "properties": {
    "iso:country":"IN",
    "ks:ks_name":"Bairipur",
    "ks:ks_pop":401,
    "ks:ks_type":"VILLAGE",
    "name:eng_x_preferred":[
        "Bairipur"
    ],
    "wof:name":"Bairipur",
    "wof:placetype":"locality",
    "wof:population":401
},
  "geometry": {"coordinates":[80.266409,26.096324],"type":"Point"}
}