{
  "type": "Feature",
  "properties": {
    "iso:country":"IN",
    "ks:ks_name":"Shivdih - Baljora",
    "ks:ks_pop":43,
    "ks:ks_type":"HABITATION",
    "name:eng_x_preferred":[
        "Shivdih - Baljora"
    ],
    "wof:name":"Shivdih - Baljora",
    "wof:placetype":"locality",
    "wof:population":43
},
  "geometry": {"coordinates":[86.36592400000001,25.02205],"type":"Point"}
}