{
  "type": "Feature",
  "properties": {
    "iso:country":"IN",
    "ks:ks_name":"Gaujajali Bichli",
    "ks:ks_pop":1525,
    "ks:ks_type":"VILLAGE",
    "ks:ks_uagg_main":0,
    "name:eng_x_preferred":[
        "Gaujajali Bichli"
    ],
    "wof:name":"Gaujajali Bichli",
    "wof:placetype":"neighbourhood",
    "wof:population":1525
},
  "geometry": {"coordinates":[79.521962,29.182078],"type":"Point"}
}