{
  "type": "Feature",
  "properties": {
    "iso:country":"IN",
    "ks:ks_name":"Raniyones",
    "ks:ks_pop":150,
    "ks:ks_type":"HABITATION",
    "name:eng_x_preferred":[
        "Raniyones"
    ],
    "wof:name":"Raniyones",
    "wof:placetype":"locality",
    "wof:population":150
},
  "geometry": {"coordinates":[69.958972,21.872083],"type":"Point"}
}