{
  "type": "Feature",
  "properties": {
    "iso:country":"IN",
    "ks:ks_name":"Gaursanda",
    "ks:ks_pop":1339,
    "ks:ks_type":"VILLAGE",
    "name:eng_x_preferred":[
        "Gaursanda"
    ],
    "wof:name":"Gaursanda",
    "wof:placetype":"locality",
    "wof:population":1339
},
  "geometry": {"coordinates":[87.992791,25.318781],"type":"Point"}
}