{
  "type": "Feature",
  "properties": {
    "iso:country":"IN",
    "ks:ks_alt_nam":"Chint\u0101manpur",
    "ks:ks_name":"Chintamanpur",
    "ks:ks_pop":63,
    "ks:ks_type":"VILLAGE",
    "name:eng_x_preferred":[
        "Chintamanpur"
    ],
    "name:eng_x_variant":[
        "Chint\u0101manpur"
    ],
    "wof:name":"Chintamanpur",
    "wof:placetype":"locality",
    "wof:population":63
},
  "geometry": {"coordinates":[83.935076,25.33636],"type":"Point"}
}