{
  "type": "Feature",
  "properties": {
    "gn:admin1_code":"10",
    "gn:admin2_code":"75.0",
    "gn:asciiname":"Sherah",
    "gn:country_code":"IN",
    "gn:dem":238,
    "gn:feature_class":"P",
    "gn:feature_code":"PPL",
    "gn:name":"Sher\u0101h",
    "gn:population":0,
    "gn:timezone":"Asia/Kolkata",
    "iso:country":"IN",
    "name:und_x_variant":[
        "Sher\u0101h",
        "Sherah"
    ],
    "wof:name":"Sherah",
    "wof:placetype":"locality"
},
  "geometry": {"coordinates":[76.82049000000001,29.44111],"type":"Point"}
}