{
  "type": "Feature",
  "properties": {
    "iso:country":"IN",
    "ks:ks_name":"23 PTP",
    "ks:ks_pop":378,
    "ks:ks_type":"VILLAGE",
    "name:eng_x_preferred":[
        "23 PTP"
    ],
    "wof:name":"23 PTP",
    "wof:placetype":"locality",
    "wof:population":378
},
  "geometry": {"coordinates":[74.23847499999999,29.855478],"type":"Point"}
}