{
  "type": "Feature",
  "properties": {
    "iso:country":"IN",
    "ks:ks_alt_nam":"GHOTEMALA",
    "ks:ks_name":"Ghotemala",
    "ks:ks_pop":138,
    "ks:ks_type":"HABITATION",
    "name:eng_x_preferred":[
        "Ghotemala"
    ],
    "wof:name":"Ghotemala",
    "wof:placetype":"locality",
    "wof:population":138
},
  "geometry": {"coordinates":[74.636422,17.340488],"type":"Point"}
}