{
  "type": "Feature",
  "properties": {
    "iso:country":"IN",
    "ks:ks_name":"Pandey Basti",
    "ks:ks_pop":450,
    "ks:ks_type":"HABITATION",
    "name:eng_x_preferred":[
        "Pandey Basti"
    ],
    "wof:name":"Pandey Basti",
    "wof:placetype":"locality",
    "wof:population":450
},
  "geometry": {"coordinates":[82.467883,25.996731],"type":"Point"}
}