{
  "type": "Feature",
  "properties": {
    "iso:country":"IN",
    "ks:ks_name":"Bakhlanj",
    "ks:ks_pop":224,
    "ks:ks_type":"VILLAGE",
    "name:eng_x_preferred":[
        "Bakhlanj"
    ],
    "wof:name":"Bakhlanj",
    "wof:placetype":"locality",
    "wof:population":224
},
  "geometry": {"coordinates":[80.087211,29.491965],"type":"Point"}
}