{
  "type": "Feature",
  "properties": {
    "iso:country":"IN",
    "ks:ks_name":"Begampur",
    "ks:ks_type":"VILLAGE",
    "ks:ks_uagg_main":0,
    "name:eng_x_preferred":[
        "Begampur"
    ],
    "wof:name":"Begampur",
    "wof:placetype":"neighbourhood"
},
  "geometry": {"coordinates":[77.066892,28.726547],"type":"Point"}
}