{
  "type": "Feature",
  "properties": {
    "iso:country":"IN",
    "ks:ks_name":"Lalvaniya",
    "ks:ks_pop":259,
    "ks:ks_type":"HABITATION",
    "name:eng_x_preferred":[
        "Lalvaniya"
    ],
    "wof:name":"Lalvaniya",
    "wof:placetype":"locality",
    "wof:population":259
},
  "geometry": {"coordinates":[74.75802400000001,21.758866],"type":"Point"}
}