{
  "type": "Feature",
  "properties": {
    "iso:country":"IN",
    "ks:ks_name":"Kamarpur Paharpur",
    "ks:ks_pop":2673,
    "ks:ks_type":"VILLAGE",
    "ks:ks_uagg_main":0,
    "name:eng_x_preferred":[
        "Kamarpur Paharpur"
    ],
    "wof:name":"Kamarpur Paharpur",
    "wof:placetype":"neighbourhood",
    "wof:population":2673
},
  "geometry": {"coordinates":[85.518017,25.16818],"type":"Point"}
}