{
  "type": "Feature",
  "properties": {
    "iso:country":"IN",
    "ks:ks_name":"Burusanda",
    "ks:ks_pop":34,
    "ks:ks_type":"VILLAGE",
    "name:eng_x_preferred":[
        "Burusanda"
    ],
    "wof:name":"Burusanda",
    "wof:placetype":"locality",
    "wof:population":34
},
  "geometry": {"coordinates":[84.372331,18.92071],"type":"Point"}
}