{
  "type": "Feature",
  "properties": {
    "iso:country":"IN",
    "ks:ks_name":"Marapipli",
    "ks:ks_pop":290,
    "ks:ks_type":"HABITATION",
    "name:eng_x_preferred":[
        "Marapipli"
    ],
    "wof:name":"Marapipli",
    "wof:placetype":"locality",
    "wof:population":290
},
  "geometry": {"coordinates":[73.04297200000001,24.143889],"type":"Point"}
}