{
  "type": "Feature",
  "properties": {
    "iso:country":"IN",
    "ks:ks_name":"Dakhin Satgaon Chuba",
    "ks:ks_pop":300,
    "ks:ks_type":"HABITATION",
    "ks:ks_uagg_main":0,
    "name:eng_x_preferred":[
        "Dakhin Satgaon Chuba"
    ],
    "wof:name":"Dakhin Satgaon Chuba",
    "wof:placetype":"locality",
    "wof:population":300
},
  "geometry": {"coordinates":[91.87313899999999,26.151375],"type":"Point"}
}