{
  "type": "Feature",
  "properties": {
    "iso:country":"IN",
    "ks:ks_name":"Raghudaspur",
    "ks:ks_pop":210,
    "ks:ks_type":"VILLAGE",
    "name:eng_x_preferred":[
        "Raghudaspur"
    ],
    "wof:name":"Raghudaspur",
    "wof:placetype":"locality",
    "wof:population":210
},
  "geometry": {"coordinates":[85.125029,19.678721],"type":"Point"}
}