{
  "type": "Feature",
  "properties": {
    "iso:country":"IN",
    "ks:ks_name":"Basti",
    "ks:ks_pop":576,
    "ks:ks_type":"HABITATION",
    "name:eng_x_preferred":[
        "Basti"
    ],
    "wof:name":"Basti",
    "wof:placetype":"locality",
    "wof:population":576
},
  "geometry": {"coordinates":[82.900997,19.44015],"type":"Point"}
}