{
  "type": "Feature",
  "properties": {
    "iso:country":"IN",
    "ks:ks_name":"Kelimojara",
    "ks:ks_pop":355,
    "ks:ks_type":"HABITATION",
    "name:eng_x_preferred":[
        "Kelimojara"
    ],
    "wof:name":"Kelimojara",
    "wof:placetype":"locality",
    "wof:population":355
},
  "geometry": {"coordinates":[74.405278,21.727444],"type":"Point"}
}