{
  "type": "Feature",
  "properties": {
    "gn:admin1_code":"24.0",
    "gn:admin2_code":"125.0",
    "gn:asciiname":"Bargota",
    "gn:country_code":"IN",
    "gn:dem":141,
    "gn:feature_class":"P",
    "gn:feature_code":"PPL",
    "gn:name":"Bargota",
    "gn:population":0,
    "gn:timezone":"Asia/Kolkata",
    "iso:country":"IN",
    "name:arg_x_preferred":[
        "Bargota"
    ],
    "name:ast_x_preferred":[
        "Bargota"
    ],
    "name:bre_x_preferred":[
        "Bargota"
    ],
    "name:cat_x_preferred":[
        "Bargota"
    ],
    "name:ceb_x_preferred":[
        "Bargota"
    ],
    "name:eus_x_preferred":[
        "Bargota"
    ],
    "name:fra_x_preferred":[
        "Bargota"
    ],
    "name:hun_x_preferred":[
        "Bargota"
    ],
    "name:ita_x_preferred":[
        "Bargota"
    ],
    "name:msa_x_preferred":[
        "Bargota"
    ],
    "name:nld_x_preferred":[
        "Bargota"
    ],
    "name:oci_x_preferred":[
        "Bargota"
    ],
    "name:pol_x_preferred":[
        "Bargota"
    ],
    "name:por_x_preferred":[
        "Bargota"
    ],
    "name:rus_x_preferred":[
        "\u0411\u0430\u0440\u0433\u043e\u0442\u0430"
    ],
    "name:sco_x_preferred":[
        "Bargota"
    ],
    "name:spa_x_preferred":[
        "Bargota"
    ],
    "name:swe_x_preferred":[
        "Bargota"
    ],
    "name:ukr_x_preferred":[
        "\u0411\u0430\u0440\u0433\u043e\u0442\u0430"
    ],
    "name:vie_x_preferred":[
        "Bargota"
    ],
    "name:war_x_preferred":[
        "Bargota"
    ],
    "name:zho_x_preferred":[
        "\u5df4\u5c14\u6208\u5854"
    ],
    "wof:name":"Bargota",
    "wof:placetype":"locality"
},
  "geometry": {"coordinates":[74.05868000000002,23.41318],"type":"Point"}
}