{
  "type": "Feature",
  "properties": {
    "iso:country":"IN",
    "ks:ks_name":"Kanguveedhi",
    "ks:ks_pop":29,
    "ks:ks_type":"HABITATION",
    "name:eng_x_preferred":[
        "Kanguveedhi"
    ],
    "wof:name":"Kanguveedhi",
    "wof:placetype":"locality",
    "wof:population":29
},
  "geometry": {"coordinates":[82.479491,18.324286],"type":"Point"}
}