{
  "type": "Feature",
  "properties": {
    "iso:country":"IN",
    "ks:ks_name":"Bhadesi",
    "ks:ks_pop":2676,
    "ks:ks_type":"VILLAGE",
    "ks:ks_uagg_main":0,
    "name:eng_x_preferred":[
        "Bhadesi"
    ],
    "wof:name":"Bhadesi",
    "wof:placetype":"neighbourhood",
    "wof:population":2676
},
  "geometry": {"coordinates":[78.09631,27.852167],"type":"Point"}
}