{
  "type": "Feature",
  "properties": {
    "iso:country":"IN",
    "qs:name":"Rasadpura",
    "qs:name_adm0":"India",
    "qs:name_adm1":"Rajasthan",
    "qs:photos":36,
    "qs:photos_1k":7,
    "qs:photos_9k":1,
    "qs:photos_9r":2,
    "qs:photos_all":36,
    "qs:photos_sr":2,
    "qs:placetype":"Town",
    "qs:pop_sr":"0",
    "wof:name":"Rasadpura",
    "wof:placetype":"locality"
},
  "geometry": {"coordinates":[75.21983299999999,25.091166],"type":"Point"}
}