{
  "type": "Feature",
  "properties": {
    "iso:country":"IN",
    "ks:ks_name":"Bhimgaon",
    "ks:ks_pop":151,
    "ks:ks_type":"HABITATION",
    "name:eng_x_preferred":[
        "Bhimgaon"
    ],
    "wof:name":"Bhimgaon",
    "wof:placetype":"locality",
    "wof:population":151
},
  "geometry": {"coordinates":[77.27412200000001,22.745734],"type":"Point"}
}