{
  "type": "Feature",
  "properties": {
    "iso:country":"IN",
    "ks:ks_alt_nam":"Dh\u0101ma",
    "ks:ks_name":"Dhama",
    "ks:ks_type":"VILLAGE",
    "name:eng_x_preferred":[
        "Dhama"
    ],
    "name:eng_x_variant":[
        "Dh\u0101ma"
    ],
    "wof:name":"Dhama",
    "wof:placetype":"locality"
},
  "geometry": {"coordinates":[83.30964,25.255597],"type":"Point"}
}