{
  "type": "Feature",
  "properties": {
    "gn:admin1_code":"11",
    "gn:admin2_code":"24.0",
    "gn:asciiname":"Barnet",
    "gn:country_code":"IN",
    "gn:dem":1468,
    "gn:feature_class":"P",
    "gn:feature_code":"PPL",
    "gn:name":"Barnet",
    "gn:population":0,
    "gn:timezone":"Asia/Kolkata",
    "iso:country":"IN",
    "wof:name":"Barnet",
    "wof:placetype":"locality"
},
  "geometry": {"coordinates":[76.28348000000003,32.25315],"type":"Point"}
}