{
  "type": "Feature",
  "properties": {
    "gn:admin1_code":"37.0",
    "gn:admin2_code":"416.0",
    "gn:asciiname":"Bhandarras",
    "gn:country_code":"IN",
    "gn:dem":290,
    "gn:feature_class":"P",
    "gn:feature_code":"PPL",
    "gn:name":"Bhandarr\u0101s",
    "gn:population":0,
    "gn:timezone":"Asia/Kolkata",
    "iso:country":"IN",
    "ks:ks_name":"Bhandarras",
    "ks:ks_pop":371,
    "ks:ks_type":"HABITATION",
    "name:eng_x_preferred":[
        "Bhandarras"
    ],
    "wof:name":"Bhandarras",
    "wof:placetype":"locality",
    "wof:population":371
},
  "geometry": {"coordinates":[81.605408,18.508003],"type":"Point"}
}