{
  "type": "Feature",
  "properties": {
    "gn:admin1_code":"37.0",
    "gn:admin2_code":"416.0",
    "gn:asciiname":"Bhandarras",
    "gn:country_code":"IN",
    "gn:dem":290,
    "gn:feature_class":"P",
    "gn:feature_code":"PPL",
    "gn:name":"Bhandarr\u0101s",
    "gn:population":0,
    "gn:timezone":"Asia/Kolkata",
    "iso:country":"IN",
    "wof:name":"Bhandarras",
    "wof:placetype":"locality"
},
  "geometry": {"coordinates":[81.6005,18.51254],"type":"Point"}
}