{
  "type": "Feature",
  "properties": {
    "iso:country":"IN",
    "ks:ks_alt_nam":"Aurai basa",
    "ks:ks_name":"Aurai Basa",
    "ks:ks_pop":240,
    "ks:ks_type":"HABITATION",
    "ks:ks_uagg_main":0,
    "name:eng_x_preferred":[
        "Aurai Basa"
    ],
    "wof:name":"Aurai Basa",
    "wof:placetype":"neighbourhood",
    "wof:population":240
},
  "geometry": {"coordinates":[86.967992,25.606458],"type":"Point"}
}