{
  "type": "Feature",
  "properties": {
    "iso:country":"IN",
    "ks:ks_name":"Ranipura",
    "ks:ks_pop":2680,
    "ks:ks_type":"VILLAGE",
    "name:eng_x_preferred":[
        "Ranipura"
    ],
    "wof:name":"Ranipura",
    "wof:placetype":"locality",
    "wof:population":2680
},
  "geometry": {"coordinates":[73.75504599999999,22.726507],"type":"Point"}
}