{
  "type": "Feature",
  "properties": {
    "iso:country":"IN",
    "ks:ks_name":"Sagibhouna",
    "ks:ks_pop":791,
    "ks:ks_type":"VILLAGE",
    "name:eng_x_preferred":[
        "Sagibhouna"
    ],
    "wof:name":"Sagibhouna",
    "wof:placetype":"locality",
    "wof:population":791
},
  "geometry": {"coordinates":[83.7701,22.696407],"type":"Point"}
}