{
  "type": "Feature",
  "properties": {
    "gn:admin1_code":"36.0",
    "gn:admin2_code":"183.0",
    "gn:asciiname":"Pura Tiwari Ram Sahai",
    "gn:country_code":"IN",
    "gn:dem":106,
    "gn:feature_class":"P",
    "gn:feature_code":"PPL",
    "gn:name":"Pura Tiw\u0101ri R\u0101m Sah\u0101i",
    "gn:population":0,
    "gn:timezone":"Asia/Kolkata",
    "iso:country":"IN",
    "wof:name":"Pura Tiwari Ram Sahai",
    "wof:placetype":"locality"
},
  "geometry": {"coordinates":[82.14661,27.30395],"type":"Point"}
}