{
  "type": "Feature",
  "properties": {
    "iso:country":"IN",
    "ks:ks_name":"Navania Khakhariya",
    "ks:ks_pop":97,
    "ks:ks_type":"VILLAGE",
    "name:eng_x_preferred":[
        "Navania Khakhariya"
    ],
    "wof:name":"Navania Khakhariya",
    "wof:placetype":"locality",
    "wof:population":97
},
  "geometry": {"coordinates":[70.453329,22.242579],"type":"Point"}
}