{
  "type": "Feature",
  "properties": {
    "iso:country":"IN",
    "ks:ks_name":"Kurran Tola",
    "ks:ks_pop":199,
    "ks:ks_type":"VILLAGE",
    "name:eng_x_preferred":[
        "Kurran Tola"
    ],
    "wof:name":"Kurran Tola",
    "wof:placetype":"locality",
    "wof:population":199
},
  "geometry": {"coordinates":[81.57956900000001,23.616329],"type":"Point"}
}