{
  "type": "Feature",
  "properties": {
    "gn:admin1_code":"36",
    "gn:admin2_code":"188.0",
    "gn:asciiname":"Tola Birwari",
    "gn:country_code":"IN",
    "gn:dem":84,
    "gn:feature_class":"P",
    "gn:feature_code":"PPL",
    "gn:name":"Tola Birw\u0101ri",
    "gn:population":0,
    "gn:timezone":"Asia/Kolkata",
    "iso:country":"IN",
    "wof:name":"Tola Birwari",
    "wof:placetype":"locality"
},
  "geometry": {"coordinates":[83.4817,26.67921],"type":"Point"}
}