{
  "type": "Feature",
  "properties": {
    "gn:admin1_code":"35",
    "gn:admin2_code":"455.0",
    "gn:asciiname":"Balbuddi",
    "gn:country_code":"IN",
    "gn:dem":520,
    "gn:feature_class":"P",
    "gn:feature_code":"PPL",
    "gn:name":"B\u0101lbuddi",
    "gn:population":0,
    "gn:timezone":"Asia/Kolkata",
    "iso:country":"IN",
    "ks:ks_alt_nam":"B\u0101lbuddi",
    "ks:ks_name":"Balbuddi",
    "ks:ks_pop":76,
    "ks:ks_type":"VILLAGE",
    "name:eng_x_preferred":[
        "Balbuddi"
    ],
    "name:eng_x_variant":[
        "B\u0101lbuddi"
    ],
    "wof:name":"Balbuddi",
    "wof:placetype":"locality",
    "wof:population":76
},
  "geometry": {"coordinates":[79.035667,22.653328],"type":"Point"}
}