{
  "type": "Feature",
  "properties": {
    "iso:country":"IN",
    "ks:ks_name":"Bodduraigudem",
    "ks:ks_pop":315,
    "ks:ks_type":"HABITATION",
    "name:eng_x_preferred":[
        "Bodduraigudem"
    ],
    "wof:name":"Bodduraigudem",
    "wof:placetype":"locality",
    "wof:population":315
},
  "geometry": {"coordinates":[81.413898,17.69388],"type":"Point"}
}