{
  "type": "Feature",
  "properties": {
    "gn:admin1_code":"24",
    "gn:admin2_code":"115.0",
    "gn:asciiname":"Sarwari Purohitan",
    "gn:country_code":"IN",
    "gn:dem":135,
    "gn:feature_class":"P",
    "gn:feature_code":"PPL",
    "gn:name":"Sarwari Purohit\u0101n",
    "gn:population":0,
    "gn:timezone":"Asia/Kolkata",
    "iso:country":"IN",
    "name:und_x_variant":[
        "Sarwari Purohit\u0101n",
        "Sarbari"
    ],
    "wof:name":"Sarwari Purohitan",
    "wof:placetype":"locality"
},
  "geometry": {"coordinates":[72.48061,26.00621],"type":"Point"}
}