{
  "type": "Feature",
  "properties": {
    "iso:country":"IN",
    "ks:ks_name":"33 RWD",
    "ks:ks_pop":180,
    "ks:ks_type":"VILLAGE",
    "name:eng_x_preferred":[
        "33 RWD"
    ],
    "wof:name":"33 RWD",
    "wof:placetype":"locality",
    "wof:population":180
},
  "geometry": {"coordinates":[74.513971,29.177791],"type":"Point"}
}