{
  "type": "Feature",
  "properties": {
    "gn:admin1_code":"40",
    "gn:admin2_code":"538.0",
    "gn:asciiname":"Chandrayanguda",
    "gn:country_code":"IN",
    "gn:dem":610,
    "gn:feature_class":"P",
    "gn:feature_code":"PPL",
    "gn:name":"Chandr\u0101yanguda",
    "gn:population":0,
    "gn:timezone":"Asia/Kolkata",
    "iso:country":"IN",
    "wof:name":"Chandrayanguda",
    "wof:placetype":"locality"
},
  "geometry": {"coordinates":[78.24075999999999,17.11042999999999],"type":"Point"}
}