{
  "type": "Feature",
  "properties": {
    "gn:admin1_code":"36",
    "gn:admin2_code":"180.0",
    "gn:asciiname":"Mirganj",
    "gn:country_code":"IN",
    "gn:dem":115,
    "gn:feature_class":"P",
    "gn:feature_code":"PPL",
    "gn:name":"M\u012brganj",
    "gn:population":0,
    "gn:timezone":"Asia/Kolkata",
    "iso:country":"IN",
    "wof:name":"Mirganj",
    "wof:placetype":"locality"
},
  "geometry": {"coordinates":[81.6018,27.53805],"type":"Point"}
}