{
  "type": "Feature",
  "properties": {
    "gn:admin1_code":"34.0",
    "gn:admin2_code":"217.0",
    "gn:asciiname":"Karanpura",
    "gn:country_code":"IN",
    "gn:dem":75,
    "gn:feature_class":"P",
    "gn:feature_code":"PPL",
    "gn:name":"Karanpura",
    "gn:population":0,
    "gn:timezone":"Asia/Kolkata",
    "iso:country":"IN",
    "ks:ks_name":"Karanpura",
    "ks:ks_pop":575,
    "ks:ks_type":"VILLAGE",
    "name:eng_x_preferred":[
        "Karanpura"
    ],
    "name:msa_x_preferred":[
        "Karanpura"
    ],
    "wof:name":"Karanpura",
    "wof:placetype":"locality",
    "wof:population":575
},
  "geometry": {"coordinates":[84.29342200000001,26.517553],"type":"Point"}
}