{
  "type": "Feature",
  "properties": {
    "iso:country":"IN",
    "ks:ks_name":"Sahu Basti",
    "ks:ks_pop":247,
    "ks:ks_type":"HABITATION",
    "ks:ks_uagg_main":0,
    "name:eng_x_preferred":[
        "Sahu Basti"
    ],
    "wof:name":"Sahu Basti",
    "wof:placetype":"neighbourhood",
    "wof:population":247
},
  "geometry": {"coordinates":[82.925202,25.129588],"type":"Point"}
}