{
  "type": "Feature",
  "properties": {
    "iso:country":"IN",
    "ks:ks_name":"Adibasi Tola",
    "ks:ks_pop":102,
    "ks:ks_type":"HABITATION",
    "name:eng_x_preferred":[
        "Adibasi Tola"
    ],
    "wof:name":"Adibasi Tola",
    "wof:placetype":"locality",
    "wof:population":102
},
  "geometry": {"coordinates":[86.363629,24.71541],"type":"Point"}
}