{
  "type": "Feature",
  "properties": {
    "iso:country":"IN",
    "ks:ks_name":"Sanabaulpur",
    "ks:ks_pop":524,
    "ks:ks_type":"VILLAGE",
    "name:eng_x_preferred":[
        "Sanabaulpur"
    ],
    "wof:name":"Sanabaulpur",
    "wof:placetype":"locality",
    "wof:population":524
},
  "geometry": {"coordinates":[85.52909,20.737585],"type":"Point"}
}