{
  "type": "Feature",
  "properties": {
    "gn:admin1_code":"2",
    "gn:admin2_code":"545.0",
    "gn:asciiname":"Lakshmipuram",
    "gn:country_code":"IN",
    "gn:dem":226,
    "gn:feature_class":"P",
    "gn:feature_code":"PPL",
    "gn:name":"Lakshm\u012bpuram",
    "gn:population":0,
    "gn:timezone":"Asia/Kolkata",
    "iso:country":"IN",
    "wof:name":"Lakshmipuram",
    "wof:placetype":"locality"
},
  "geometry": {"coordinates":[81.94976,17.53058],"type":"Point"}
}