{
  "type": "Feature",
  "properties": {
    "iso:country":"IN",
    "ks:ks_name":"Badgan",
    "ks:ks_pop":1096,
    "ks:ks_type":"VILLAGE",
    "name:eng_x_preferred":[
        "Badgan"
    ],
    "wof:name":"Badgan",
    "wof:placetype":"locality",
    "wof:population":1096
},
  "geometry": {"coordinates":[86.504835,22.010853],"type":"Point"}
}