{
  "type": "Feature",
  "properties": {
    "gn:admin1_code":"12.0",
    "gn:admin2_code":"004",
    "gn:asciiname":"Badgam",
    "gn:country_code":"IN",
    "gn:dem":3140,
    "gn:feature_class":"P",
    "gn:feature_code":"PPL",
    "gn:name":"Badg\u0101m",
    "gn:population":0,
    "gn:timezone":"Asia/Kolkata",
    "iso:country":"IN",
    "name:ara_x_preferred":[
        "\u0628\u0627\u062f\u062c\u0627\u0645"
    ],
    "name:bpy_x_preferred":[
        "\u09ac\u09a6\u0997\u09be\u09ae"
    ],
    "name:ceb_x_preferred":[
        "Badgom"
    ],
    "name:deu_x_preferred":[
        "Badgam"
    ],
    "name:fra_x_preferred":[
        "Badgam"
    ],
    "name:hin_x_preferred":[
        "\u092c\u0921\u0917\u093e\u092e"
    ],
    "name:ita_x_preferred":[
        "Budgam"
    ],
    "name:mar_x_preferred":[
        "\u092c\u0921\u0917\u093e\u092e"
    ],
    "name:msa_x_preferred":[
        "Badgam"
    ],
    "name:new_x_preferred":[
        "\u092c\u093e\u0926\u0917\u093e\u092e"
    ],
    "name:nld_x_preferred":[
        "Badgam"
    ],
    "name:por_x_preferred":[
        "Badgam"
    ],
    "name:san_x_preferred":[
        "\u092c\u0921\u0917\u093e\u0902\u0935"
    ],
    "name:spa_x_preferred":[
        "Badgam"
    ],
    "name:swe_x_preferred":[
        "Badgom"
    ],
    "name:und_x_variant":[
        "Badg\u0101m"
    ],
    "name:urd_x_preferred":[
        "\u0628\u0688\u06af\u0627\u0645"
    ],
    "name:vie_x_preferred":[
        "Badgam"
    ],
    "name:zho_x_preferred":[
        "\u5df4\u5fb7\u52a0\u59c6"
    ],
    "wof:name":"Badgam",
    "wof:placetype":"locality"
},
  "geometry": {"coordinates":[76.04444000000002,34.62917],"type":"Point"}
}