{
  "type": "Feature",
  "properties": {
    "gn:admin1_code":"12.0",
    "gn:admin2_code":"004",
    "gn:asciiname":"Badgam",
    "gn:country_code":"IN",
    "gn:dem":3140,
    "gn:feature_class":"P",
    "gn:feature_code":"PPL",
    "gn:name":"Badg\u0101m",
    "gn:population":0,
    "gn:timezone":"Asia/Kolkata",
    "iso:country":"IN",
    "name:und_x_variant":[
        "Badg\u0101m",
        "Budgam"
    ],
    "wof:name":"Badgam",
    "wof:placetype":"locality"
},
  "geometry": {"coordinates":[76.04444000000002,34.62917],"type":"Point"}
}