{
  "type": "Feature",
  "properties": {
    "gn:admin1_code":"12.0",
    "gn:admin2_code":"004",
    "gn:asciiname":"Badgam",
    "gn:country_code":"IN",
    "gn:dem":3140,
    "gn:feature_class":"P",
    "gn:feature_code":"PPL",
    "gn:name":"Badg\u0101m",
    "gn:population":0,
    "gn:timezone":"Asia/Kolkata",
    "iso:country":"IN",
    "name:ara_x_preferred":[
        "\u0628\u0627\u062f\u062c\u0627\u0645"
    ],
    "name:ben_bn_x_preferred":[
        "\u09ac\u09be\u09a1\u0997\u09be\u09ae"
    ],
    "name:ben_in_x_preferred":[
        "\u09ac\u09be\u09a1\u0997\u09be\u09ae"
    ],
    "name:bpy_x_preferred":[
        "\u09ac\u09a6\u0997\u09be\u09ae"
    ],
    "name:ceb_x_preferred":[
        "Badgom"
    ],
    "name:deu_x_preferred":[
        "Badgam"
    ],
    "name:fra_x_preferred":[
        "Badgam"
    ],
    "name:guj_x_preferred":[
        "\u0aac\u0aa1\u0a97\u0abe\u0aae"
    ],
    "name:hin_x_preferred":[
        "\u092c\u0921\u0917\u093e\u092e"
    ],
    "name:ita_x_preferred":[
        "Budgam"
    ],
    "name:kan_x_preferred":[
        "\u0cac\u0ca1\u0ccd\u0c97\u0cbe\u0c82\u0cb5\u0ccd"
    ],
    "name:mal_x_preferred":[
        "\u0d2c\u0d3e\u0d21\u0d4d"
    ],
    "name:mar_x_preferred":[
        "\u092c\u0921\u0917\u093e\u092e"
    ],
    "name:msa_x_preferred":[
        "Badgam"
    ],
    "name:new_x_preferred":[
        "\u092c\u093e\u0926\u0917\u093e\u092e"
    ],
    "name:nld_x_preferred":[
        "Badgam"
    ],
    "name:pan_x_preferred":[
        "\u0a2c\u0a5c\u0a17\u0a3e\u0a2e"
    ],
    "name:por_x_preferred":[
        "Badgam"
    ],
    "name:san_x_preferred":[
        "\u092c\u0921\u0917\u093e\u0902\u0935"
    ],
    "name:spa_x_preferred":[
        "Badgam"
    ],
    "name:swe_x_preferred":[
        "Badgom"
    ],
    "name:tam_x_preferred":[
        "\u0baa\u0b9f\u0bcd\u0b95\u0bae\u0bcd"
    ],
    "name:tel_x_preferred":[
        "\u0c2c\u0c21\u0c4d"
    ],
    "name:und_x_variant":[
        "Badg\u0101m"
    ],
    "name:urd_x_preferred":[
        "\u0628\u0688\u06af\u0627\u0645"
    ],
    "name:vie_x_preferred":[
        "Badgam"
    ],
    "name:zho_x_preferred":[
        "\u5df4\u5fb7\u52a0\u59c6"
    ],
    "wof:name":"Badgam",
    "wof:placetype":"locality"
},
  "geometry": {"coordinates":[76.04444000000002,34.62917],"type":"Point"}
}