{
  "type": "Feature",
  "properties": {
    "iso:country":"IN",
    "ks:ks_name":"Poolappara",
    "ks:ks_pop":188,
    "ks:ks_type":"HABITATION",
    "name:eng_x_preferred":[
        "Poolappara"
    ],
    "wof:name":"Poolappara",
    "wof:placetype":"locality",
    "wof:population":188
},
  "geometry": {"coordinates":[75.806535,11.705075],"type":"Point"}
}