{
  "type": "Feature",
  "properties": {
    "iso:country":"IN",
    "ks:ks_name":"Pipra",
    "ks:ks_pop":118,
    "ks:ks_type":"HABITATION",
    "name:eng_x_preferred":[
        "Pipra"
    ],
    "wof:name":"Pipra",
    "wof:placetype":"locality",
    "wof:population":118
},
  "geometry": {"coordinates":[86.37717000000001,24.617707],"type":"Point"}
}