{
  "type": "Feature",
  "properties": {
    "gn:admin1_code":"12.0",
    "gn:admin2_code":"20.0",
    "gn:asciiname":"Bhabua",
    "gn:country_code":"IN",
    "gn:dem":1768,
    "gn:feature_class":"P",
    "gn:feature_code":"PPL",
    "gn:name":"Bhabu\u0101",
    "gn:population":0,
    "gn:timezone":"Asia/Kolkata",
    "iso:country":"IN",
    "wof:name":"Bhabua",
    "wof:placetype":"locality"
},
  "geometry": {"coordinates":[75.03990999999998,33.0234],"type":"Point"}
}