{
  "type": "Feature",
  "properties": {
    "gn:admin1_code":"12.0",
    "gn:admin2_code":"20.0",
    "gn:asciiname":"Bhabua",
    "gn:country_code":"IN",
    "gn:dem":1768,
    "gn:feature_class":"P",
    "gn:feature_code":"PPL",
    "gn:name":"Bhabu\u0101",
    "gn:population":0,
    "gn:timezone":"Asia/Kolkata",
    "iso:country":"IN",
    "name:ben_x_preferred":[
        "\u09ad\u09be\u09ac\u09c1\u09af\u09bc\u09be"
    ],
    "name:bih_x_preferred":[
        "\u092d\u092d\u0941\u0906"
    ],
    "name:bpy_x_preferred":[
        "\u09ad\u09be\u09ac\u09c1\u09f1\u09be"
    ],
    "name:ceb_x_preferred":[
        "Bhabua"
    ],
    "name:fra_x_preferred":[
        "Bhabua"
    ],
    "name:guj_x_preferred":[
        "\u0aad\u0aad\u0ac1\u0a86"
    ],
    "name:hin_x_preferred":[
        "\u092d\u092d\u0941\u0906"
    ],
    "name:ita_x_preferred":[
        "Bhabua"
    ],
    "name:mar_x_preferred":[
        "\u092d\u092c\u0941\u0906"
    ],
    "name:mlg_x_preferred":[
        "Bhabua"
    ],
    "name:msa_x_preferred":[
        "Bhabua"
    ],
    "name:nep_x_preferred":[
        "\u092d\u092d\u0941\u0906"
    ],
    "name:new_x_preferred":[
        "\u092d\u092c\u0941\u0935\u093e"
    ],
    "name:ori_x_preferred":[
        "\u0b2d\u0b3e\u0b2c\u0b41\u0b06"
    ],
    "name:por_x_preferred":[
        "Bhabua"
    ],
    "name:san_x_preferred":[
        "\u092d\u092c\u0941\u0935\u093e"
    ],
    "name:spa_x_preferred":[
        "Bhabua"
    ],
    "name:swe_x_preferred":[
        "Bhabua"
    ],
    "name:urd_x_preferred":[
        "\u0628\u06be\u0627\u0628\u0648\u0627"
    ],
    "name:vie_x_preferred":[
        "Bhabua"
    ],
    "wof:name":"Bhabua",
    "wof:placetype":"locality"
},
  "geometry": {"coordinates":[75.03990999999998,33.0234],"type":"Point"}
}