{
  "type": "Feature",
  "properties": {
    "gn:admin1_code":"36",
    "gn:admin2_code":"153.0",
    "gn:asciiname":"Deoria",
    "gn:country_code":"IN",
    "gn:dem":139,
    "gn:feature_class":"P",
    "gn:feature_code":"PPL",
    "gn:name":"Deoria",
    "gn:population":0,
    "gn:timezone":"Asia/Kolkata",
    "iso:country":"IN",
    "name:ara_x_preferred":[
        "\u062f\u0648\u0631\u064a\u0627"
    ],
    "name:ben_bn_x_preferred":[
        "\u09a6\u09c7\u0993\u09b0\u09bf\u09df\u09be"
    ],
    "name:ben_in_x_preferred":[
        "\u09a6\u09c7\u0993\u09b0\u09bf\u09df\u09be"
    ],
    "name:ceb_x_preferred":[
        "Deoria"
    ],
    "name:guj_x_preferred":[
        "\u0aa6\u0ac7\u0ab0\u0acb\u0a87"
    ],
    "name:hin_x_preferred":[
        "\u0926\u0947\u0935\u0930\u093f\u092f\u093e"
    ],
    "name:kan_x_preferred":[
        "\u0ca6\u0cbf\u0caf\u0ccb\u0cb0\u0cbf\u0caf\u0cbe"
    ],
    "name:mal_x_preferred":[
        "\u0d21\u0d3f\u0d2f\u0d4b\u0d31\u0d3f\u0d2f"
    ],
    "name:mar_x_preferred":[
        "\u0926\u0947\u0935\u0930\u093f\u092f\u093e"
    ],
    "name:nld_x_preferred":[
        "Deoria"
    ],
    "name:pan_x_preferred":[
        "\u0a26\u0a3f\u0a13\u0a30\u0a40\u0a06"
    ],
    "name:pol_x_preferred":[
        "Deoria"
    ],
    "name:swe_x_preferred":[
        "Deoria"
    ],
    "name:tam_x_preferred":[
        "\u0b9f\u0bbf\u0baf\u0bcb\u0bb0\u0bbf\u0baf\u0bbe"
    ],
    "name:tel_x_preferred":[
        "\u0c26\u0c47\u0c30\u0c3f\u0c2f\u0c3e"
    ],
    "name:urd_x_preferred":[
        "\u062f\u06cc\u0648\u0631\u06cc\u0627"
    ],
    "wof:name":"Deoria",
    "wof:placetype":"locality"
},
  "geometry": {"coordinates":[80.83981999999997,27.94956],"type":"Point"}
}