{
  "type": "Feature",
  "properties": {
    "gn:admin1_code":"36",
    "gn:admin2_code":"153.0",
    "gn:asciiname":"Deoria",
    "gn:country_code":"IN",
    "gn:dem":139,
    "gn:feature_class":"P",
    "gn:feature_code":"PPL",
    "gn:name":"Deoria",
    "gn:population":0,
    "gn:timezone":"Asia/Kolkata",
    "iso:country":"IN",
    "name:ceb_x_preferred":[
        "Deoria"
    ],
    "name:nld_x_preferred":[
        "Deoria"
    ],
    "name:pol_x_preferred":[
        "Deoria"
    ],
    "name:swe_x_preferred":[
        "Deoria"
    ],
    "wof:name":"Deoria",
    "wof:placetype":"locality"
},
  "geometry": {"coordinates":[80.83981999999997,27.94956],"type":"Point"}
}