{
  "type": "Feature",
  "properties": {
    "iso:country":"IN",
    "ks:ks_name":"Bharchandi",
    "ks:ks_pop":575,
    "ks:ks_type":"VILLAGE",
    "ks:ks_uagg_main":0,
    "name:eng_x_preferred":[
        "Bharchandi"
    ],
    "wof:name":"Bharchandi",
    "wof:placetype":"neighbourhood",
    "wof:population":575
},
  "geometry": {"coordinates":[86.82600600000001,24.012346],"type":"Point"}
}