{
  "type": "Feature",
  "properties": {
    "iso:country":"IN",
    "ks:ks_name":"Chengeliapara",
    "ks:ks_pop":853,
    "ks:ks_type":"VILLAGE",
    "ks:ks_uagg_main":0,
    "name:eng_x_preferred":[
        "Chengeliapara"
    ],
    "wof:name":"Chengeliapara",
    "wof:placetype":"neighbourhood",
    "wof:population":853
},
  "geometry": {"coordinates":[91.97899200000001,26.408396],"type":"Point"}
}