{
  "type": "Feature",
  "properties": {
    "iso:country":"IN",
    "ks:ks_name":"Ratanpur",
    "ks:ks_pop":586,
    "ks:ks_type":"VILLAGE",
    "ks:ks_uagg_main":0,
    "name:eng_x_preferred":[
        "Ratanpur"
    ],
    "wof:name":"Ratanpur",
    "wof:placetype":"neighbourhood",
    "wof:population":586
},
  "geometry": {"coordinates":[87.66077,21.727506],"type":"Point"}
}