{
  "type": "Feature",
  "properties": {
    "iso:country":"IN",
    "ks:ks_name":"Hanman Tanda",
    "ks:ks_pop":12,
    "ks:ks_type":"HABITATION",
    "name:eng_x_preferred":[
        "Hanman Tanda"
    ],
    "wof:name":"Hanman Tanda",
    "wof:placetype":"locality",
    "wof:population":12
},
  "geometry": {"coordinates":[78.029912,18.367559],"type":"Point"}
}