{
  "type": "Feature",
  "properties": {
    "iso:country":"IN",
    "ks:ks_name":"Mirdi",
    "ks:ks_pop":514,
    "ks:ks_type":"VILLAGE",
    "ks:ks_uagg_main":0,
    "name:eng_x_preferred":[
        "Mirdi"
    ],
    "wof:name":"Mirdi",
    "wof:placetype":"neighbourhood",
    "wof:population":514
},
  "geometry": {"coordinates":[86.136809,23.404574],"type":"Point"}
}