{
  "type": "Feature",
  "properties": {
    "iso:country":"IN",
    "ks:ks_name":"Khokharafali",
    "ks:ks_pop":198,
    "ks:ks_type":"HABITATION",
    "name:eng_x_preferred":[
        "Khokharafali"
    ],
    "wof:name":"Khokharafali",
    "wof:placetype":"locality",
    "wof:population":198
},
  "geometry": {"coordinates":[73.532889,23.565972],"type":"Point"}
}