{
  "type": "Feature",
  "properties": {
    "iso:country":"IN",
    "ks:ks_name":"Ghumardora",
    "ks:ks_pop":63,
    "ks:ks_type":"HABITATION",
    "name:eng_x_preferred":[
        "Ghumardora"
    ],
    "wof:name":"Ghumardora",
    "wof:placetype":"locality",
    "wof:population":63
},
  "geometry": {"coordinates":[82.65160400000001,19.412946],"type":"Point"}
}