{
  "type": "Feature",
  "properties": {
    "iso:country":"IN",
    "ks:ks_name":"Chauda",
    "ks:ks_pop":63,
    "ks:ks_type":"VILLAGE",
    "name:eng_x_preferred":[
        "Chauda"
    ],
    "wof:name":"Chauda",
    "wof:placetype":"locality",
    "wof:population":63
},
  "geometry": {"coordinates":[79.44815,29.476092],"type":"Point"}
}