{
  "type": "Feature",
  "properties": {
    "iso:country":"IN",
    "ks:ks_name":"Manmaw Ulup Gaon",
    "ks:ks_pop":303,
    "ks:ks_type":"VILLAGE",
    "ks:ks_uagg_main":0,
    "name:eng_x_preferred":[
        "Manmaw Ulup Gaon"
    ],
    "wof:name":"Manmaw Ulup Gaon",
    "wof:placetype":"neighbourhood",
    "wof:population":303
},
  "geometry": {"coordinates":[95.78057800000001,27.369929],"type":"Point"}
}