{
  "type": "Feature",
  "properties": {
    "iso:country":"IN",
    "ks:ks_name":"Manduvanda",
    "ks:ks_pop":47,
    "ks:ks_type":"HABITATION",
    "name:eng_x_preferred":[
        "Manduvanda"
    ],
    "wof:name":"Manduvanda",
    "wof:placetype":"locality",
    "wof:population":47
},
  "geometry": {"coordinates":[75.736667,12.3725],"type":"Point"}
}