{
  "type": "Feature",
  "properties": {
    "iso:country":"IN",
    "ks:ks_name":"Dhankuawari Kalan",
    "ks:ks_pop":272,
    "ks:ks_type":"VILLAGE",
    "name:eng_x_preferred":[
        "Dhankuawari Kalan"
    ],
    "wof:name":"Dhankuawari Kalan",
    "wof:placetype":"locality",
    "wof:population":272
},
  "geometry": {"coordinates":[83.299874,24.736853],"type":"Point"}
}