{
  "type": "Feature",
  "properties": {
    "gn:admin1_code":"34",
    "gn:admin2_code":"232.0",
    "gn:asciiname":"Kanak Narayanpur",
    "gn:country_code":"IN",
    "gn:dem":70,
    "gn:feature_class":"P",
    "gn:feature_code":"PPL",
    "gn:name":"Kanak N\u0101r\u0101yanpur",
    "gn:population":0,
    "gn:timezone":"Asia/Kolkata",
    "iso:country":"IN",
    "ks:ks_alt_nam":"Kanak N\u0101r\u0101yanpur",
    "ks:ks_name":"Kanak Narayanpur",
    "ks:ks_pop":968,
    "ks:ks_type":"VILLAGE",
    "ks:ks_uagg_main":0,
    "name:eng_x_preferred":[
        "Kanak Narayanpur"
    ],
    "name:eng_x_variant":[
        "Kanak N\u0101r\u0101yanpur"
    ],
    "wof:name":"Kanak Narayanpur",
    "wof:placetype":"neighbourhood",
    "wof:population":968
},
  "geometry": {"coordinates":[83.889151,25.491237],"type":"Point"}
}