{
  "type": "Feature",
  "properties": {
    "gn:admin1_code":"12.0",
    "gn:admin2_code":"005",
    "gn:asciiname":"Suman",
    "gn:country_code":"IN",
    "gn:dem":2211,
    "gn:feature_class":"P",
    "gn:feature_code":"PPL",
    "gn:name":"Sum\u0101n",
    "gn:population":0,
    "gn:timezone":"Asia/Kolkata",
    "iso:country":"IN",
    "name:deu_x_preferred":[
        "Suman"
    ],
    "name:ukr_x_preferred":[
        "\u0421\u0443\u043c\u0430\u043d"
    ],
    "wof:name":"Suman",
    "wof:placetype":"locality"
},
  "geometry": {"coordinates":[74.34768000000003,33.81298],"type":"Point"}
}