{
  "type": "Feature",
  "properties": {
    "iso:country":"IN",
    "ks:ks_name":"Mesoniparupu",
    "ks:ks_pop":48,
    "ks:ks_type":"HABITATION",
    "name:eng_x_preferred":[
        "Mesoniparupu"
    ],
    "wof:name":"Mesoniparupu",
    "wof:placetype":"locality",
    "wof:population":48
},
  "geometry": {"coordinates":[78.639031,19.222137],"type":"Point"}
}