{
  "type": "Feature",
  "properties": {
    "gn:admin1_code":"25.0",
    "gn:admin2_code":"632.0",
    "gn:asciiname":"Solanur",
    "gn:country_code":"IN",
    "gn:dem":299,
    "gn:feature_class":"P",
    "gn:feature_code":"PPL",
    "gn:name":"Solan\u016br",
    "gn:population":0,
    "gn:timezone":"Asia/Kolkata",
    "iso:country":"IN",
    "ks:ks_alt_nam":"Solan\u016br",
    "ks:ks_name":"Solanur",
    "ks:ks_pop":267,
    "ks:ks_type":"VILLAGE",
    "name:eng_x_preferred":[
        "Solanur"
    ],
    "name:eng_x_variant":[
        "Solan\u016br"
    ],
    "wof:name":"Solanur",
    "wof:placetype":"locality",
    "wof:population":267
},
  "geometry": {"coordinates":[77.030477,10.72027],"type":"Point"}
}