{
  "type": "Feature",
  "properties": {
    "iso:country":"IN",
    "ks:ks_name":"Amawa 10",
    "ks:ks_pop":944,
    "ks:ks_type":"HABITATION",
    "name:eng_x_preferred":[
        "Amawa 10"
    ],
    "wof:name":"Amawa 10",
    "wof:placetype":"locality",
    "wof:population":944
},
  "geometry": {"coordinates":[81.633942,24.624714],"type":"Point"}
}