{
  "type": "Feature",
  "properties": {
    "iso:country":"IN",
    "ks:ks_alt_nam":"K Kallahalli Muslim colony",
    "ks:ks_name":"K Kallahalli Muslim Colony",
    "ks:ks_pop":240,
    "ks:ks_type":"HABITATION",
    "name:eng_x_preferred":[
        "K Kallahalli Muslim Colony"
    ],
    "wof:name":"K Kallahalli Muslim Colony",
    "wof:placetype":"locality",
    "wof:population":240
},
  "geometry": {"coordinates":[76.85644600000001,13.155085],"type":"Point"}
}