{
  "type": "Feature",
  "properties": {
    "iso:country":"IN",
    "ks:ks_name":"Badabanahalli",
    "ks:ks_pop":169,
    "ks:ks_type":"HABITATION",
    "name:eng_x_preferred":[
        "Badabanahalli"
    ],
    "wof:name":"Badabanahalli",
    "wof:placetype":"locality",
    "wof:population":169
},
  "geometry": {"coordinates":[75.941667,12.7025],"type":"Point"}
}