{
  "type": "Feature",
  "properties": {
    "gn:admin1_code":"7.0",
    "gn:admin2_code":"90.0",
    "gn:asciiname":"Shahpur Garhi",
    "gn:country_code":"IN",
    "gn:dem":213,
    "gn:feature_class":"P",
    "gn:feature_code":"PPL",
    "gn:name":"Sh\u0101hpur Garhi",
    "gn:population":0,
    "gn:timezone":"Asia/Kolkata",
    "iso:country":"IN",
    "wof:name":"Shahpur Garhi",
    "wof:placetype":"neighbourhood"
},
  "geometry": {"coordinates":[77.10791,28.81851],"type":"Point"}
}