{
  "type": "Feature",
  "properties": {
    "iso:country":"IN",
    "ks:ks_name":"Dal Chandra Nagar",
    "ks:ks_pop":116,
    "ks:ks_type":"HABITATION",
    "ks:ks_uagg_main":0,
    "name:eng_x_preferred":[
        "Dal Chandra Nagar"
    ],
    "wof:name":"Dal Chandra Nagar",
    "wof:placetype":"neighbourhood",
    "wof:population":116
},
  "geometry": {"coordinates":[80.978593,27.208488],"type":"Point"}
}