{
  "type": "Feature",
  "properties": {
    "iso:country":"IN",
    "ks:ks_alt_nam":"Adharkuna pt II",
    "ks:ks_name":"Adharkuna Pt Ii",
    "ks:ks_pop":239,
    "ks:ks_type":"HABITATION",
    "name:eng_x_preferred":[
        "Adharkuna Pt Ii"
    ],
    "wof:name":"Adharkuna Pt Ii",
    "wof:placetype":"locality",
    "wof:population":239
},
  "geometry": {"coordinates":[92.52857299999999,24.757175],"type":"Point"}
}