{
  "type": "Feature",
  "properties": {
    "iso:country":"IN",
    "ks:ks_name":"Kamalpur Bithraul",
    "ks:ks_pop":2154,
    "ks:ks_type":"VILLAGE",
    "ks:ks_uagg_main":0,
    "name:eng_x_preferred":[
        "Kamalpur Bithraul"
    ],
    "wof:name":"Kamalpur Bithraul",
    "wof:placetype":"neighbourhood",
    "wof:population":2154
},
  "geometry": {"coordinates":[85.08583400000001,26.254443],"type":"Point"}
}