{
  "type": "Feature",
  "properties": {
    "gn:admin1_code":"33",
    "gn:admin2_code":"585.0",
    "gn:asciiname":"Marna",
    "gn:country_code":"IN",
    "gn:dem":48,
    "gn:feature_class":"P",
    "gn:feature_code":"PPL",
    "gn:name":"Marna",
    "gn:population":0,
    "gn:timezone":"Asia/Kolkata",
    "iso:country":"IN",
    "name:und_x_variant":[
        "Marn",
        "Marna"
    ],
    "wof:name":"Marna",
    "wof:placetype":"locality"
},
  "geometry": {"coordinates":[73.78331999999997,15.61344],"type":"Point"}
}