{
  "type": "Feature",
  "properties": {
    "iso:country":"IN",
    "ks:ks_name":"Kajikola",
    "ks:ks_pop":0,
    "ks:ks_type":"VILLAGE",
    "name:eng_x_preferred":[
        "Kajikola"
    ],
    "wof:name":"Kajikola",
    "wof:placetype":"locality",
    "wof:population":0
},
  "geometry": {"coordinates":[88.117693,24.497523],"type":"Point"}
}