{
  "type": "Feature",
  "properties": {
    "gn:admin1_code":"10.0",
    "gn:admin2_code":"69.0",
    "gn:asciiname":"Majika",
    "gn:country_code":"IN",
    "gn:dem":901,
    "gn:feature_class":"P",
    "gn:feature_code":"PPL",
    "gn:name":"Maj\u012bka",
    "gn:population":0,
    "gn:timezone":"Asia/Kolkata",
    "iso:country":"IN",
    "name:ind_x_preferred":[
        "Majika"
    ],
    "name:tgl_x_preferred":[
        "Majika"
    ],
    "wof:name":"Majika",
    "wof:placetype":"locality"
},
  "geometry": {"coordinates":[77.12415,30.69082],"type":"Point"}
}