{
  "type": "Feature",
  "properties": {
    "iso:country":"IN",
    "ks:ks_name":"Thirangi",
    "ks:ks_pop":32,
    "ks:ks_type":"HABITATION",
    "name:eng_x_preferred":[
        "Thirangi"
    ],
    "wof:name":"Thirangi",
    "wof:placetype":"locality",
    "wof:population":32
},
  "geometry": {"coordinates":[82.464764,18.262037],"type":"Point"}
}