{
  "type": "Feature",
  "properties": {
    "iso:country":"IN",
    "ks:ks_name":"Palvipada",
    "ks:ks_pop":74,
    "ks:ks_type":"HABITATION",
    "name:eng_x_preferred":[
        "Palvipada"
    ],
    "wof:name":"Palvipada",
    "wof:placetype":"locality",
    "wof:population":74
},
  "geometry": {"coordinates":[72.964119,19.638629],"type":"Point"}
}