{
  "type": "Feature",
  "properties": {
    "iso:country":"IN",
    "ks:ks_name":"Veeripacheri",
    "ks:ks_pop":40,
    "ks:ks_type":"HABITATION",
    "name:eng_x_preferred":[
        "Veeripacheri"
    ],
    "wof:name":"Veeripacheri",
    "wof:placetype":"locality",
    "wof:population":40
},
  "geometry": {"coordinates":[78.84535700000001,9.667425],"type":"Point"}
}