{
  "type": "Feature",
  "properties": {
    "gn:admin1_code":"36",
    "gn:admin2_code":"180.0",
    "gn:asciiname":"Gauria",
    "gn:country_code":"IN",
    "gn:dem":126,
    "gn:feature_class":"P",
    "gn:feature_code":"PPL",
    "gn:name":"Gauria",
    "gn:population":0,
    "gn:timezone":"Asia/Kolkata",
    "iso:country":"IN",
    "ks:ks_name":"Gauriya",
    "ks:ks_pop":325,
    "ks:ks_type":"HABITATION",
    "name:eng_x_preferred":[
        "Gauriya"
    ],
    "name:eng_x_variant":[
        "Gauria"
    ],
    "wof:name":"Gauriya",
    "wof:placetype":"locality",
    "wof:population":325
},
  "geometry": {"coordinates":[81.35005,27.719982],"type":"Point"}
}