{
  "type": "Feature",
  "properties": {
    "iso:country":"IN",
    "ks:ks_name":"Yaduwansh Nagar",
    "ks:ks_pop":110,
    "ks:ks_type":"HABITATION",
    "name:eng_x_preferred":[
        "Yaduwansh Nagar"
    ],
    "wof:name":"Yaduwansh Nagar",
    "wof:placetype":"locality",
    "wof:population":110
},
  "geometry": {"coordinates":[78.37283600000001,27.225054],"type":"Point"}
}