{
  "type": "Feature",
  "properties": {
    "iso:country":"IN",
    "ks:ks_name":"Riniya",
    "ks:ks_pop":1423,
    "ks:ks_type":"VILLAGE",
    "name:eng_x_preferred":[
        "Riniya"
    ],
    "wof:name":"Riniya",
    "wof:placetype":"locality",
    "wof:population":1423
},
  "geometry": {"coordinates":[72.924634,26.618456],"type":"Point"}
}