{
  "type": "Feature",
  "properties": {
    "iso:country":"IN",
    "ks:ks_alt_nam":"PINDRAHI",
    "ks:ks_name":"Pindrahi",
    "ks:ks_pop":165,
    "ks:ks_type":"HABITATION",
    "name:eng_x_preferred":[
        "Pindrahi"
    ],
    "wof:name":"Pindrahi",
    "wof:placetype":"locality",
    "wof:population":165
},
  "geometry": {"coordinates":[85.214536,23.954825],"type":"Point"}
}