{
  "type": "Feature",
  "properties": {
    "iso:country":"IN",
    "ks:ks_name":"Zuj",
    "ks:ks_pop":1022,
    "ks:ks_type":"VILLAGE",
    "name:eng_x_preferred":[
        "Zuj"
    ],
    "wof:name":"Zuj",
    "wof:placetype":"locality",
    "wof:population":1022
},
  "geometry": {"coordinates":[73.388944,20.719022],"type":"Point"}
}