{
  "type": "Feature",
  "properties": {
    "iso:country":"IN",
    "ks:ks_name":"Ravipura Chamariya Vistar",
    "ks:ks_pop":579,
    "ks:ks_type":"HABITATION",
    "name:eng_x_preferred":[
        "Ravipura Chamariya Vistar"
    ],
    "wof:name":"Ravipura Chamariya Vistar",
    "wof:placetype":"locality",
    "wof:population":579
},
  "geometry": {"coordinates":[73.007806,22.410083],"type":"Point"}
}