{
  "type": "Feature",
  "properties": {
    "gn:admin1_code":"40",
    "gn:admin2_code":"538.0",
    "gn:asciiname":"Tankara",
    "gn:country_code":"IN",
    "gn:dem":570,
    "gn:feature_class":"P",
    "gn:feature_code":"PPL",
    "gn:name":"Tankara",
    "gn:population":0,
    "gn:timezone":"Asia/Kolkata",
    "iso:country":"IN",
    "name:ceb_x_preferred":[
        "Tank\u0101ra"
    ],
    "name:guj_x_preferred":[
        "\u0a9f\u0a82\u0a95\u0abe\u0ab0\u0abe"
    ],
    "name:hin_x_preferred":[
        "\u091f\u0902\u0915\u093e\u0930\u093e"
    ],
    "name:swe_x_preferred":[
        "Tank\u0101ra"
    ],
    "wof:name":"Tankara",
    "wof:placetype":"locality"
},
  "geometry": {"coordinates":[77.9496,16.81983],"type":"Point"}
}