{
  "type": "Feature",
  "properties": {
    "gn:admin1_code":"36",
    "gn:admin2_code":"199.0",
    "gn:asciiname":"Belhar",
    "gn:country_code":"IN",
    "gn:dem":90,
    "gn:feature_class":"P",
    "gn:feature_code":"PPL",
    "gn:name":"Belhar",
    "gn:population":0,
    "gn:timezone":"Asia/Kolkata",
    "iso:country":"IN",
    "name:afr_x_preferred":[
        "Belhar"
    ],
    "name:deu_x_preferred":[
        "Belhar"
    ],
    "name:fra_x_preferred":[
        "Belhar"
    ],
    "name:nso_x_preferred":[
        "Belhar"
    ],
    "name:xho_x_preferred":[
        "Belhar"
    ],
    "name:zul_x_preferred":[
        "Belhar"
    ],
    "wof:name":"Belhar",
    "wof:placetype":"locality"
},
  "geometry": {"coordinates":[83.06586999999998,25.08406],"type":"Point"}
}