{
  "type": "Feature",
  "properties": {
    "gn:admin1_code":"35.0",
    "gn:admin2_code":"436",
    "gn:asciiname":"Moman Barodiya",
    "gn:country_code":"IN",
    "gn:dem":448,
    "gn:feature_class":"P",
    "gn:feature_code":"PPL",
    "gn:name":"Moman Barodiya",
    "gn:population":0,
    "gn:timezone":"Asia/Kolkata",
    "iso:country":"IN",
    "name:und_x_variant":[
        "Barodia"
    ],
    "wof:name":"Moman Barodiya",
    "wof:placetype":"locality"
},
  "geometry": {"coordinates":[76.33635,23.60415],"type":"Point"}
}