{
  "type": "Feature",
  "properties": {
    "gn:admin1_code":"16.0",
    "gn:admin2_code":"500.0",
    "gn:asciiname":"Chandol Wadi",
    "gn:country_code":"IN",
    "gn:dem":560,
    "gn:feature_class":"P",
    "gn:feature_code":"PPL",
    "gn:name":"Ch\u0101ndol W\u0101di",
    "gn:population":0,
    "gn:timezone":"Asia/Kolkata",
    "iso:country":"IN",
    "wof:name":"Chandol Wadi",
    "wof:placetype":"locality"
},
  "geometry": {"coordinates":[75.98575,20.3307],"type":"Point"}
}