{
  "type": "Feature",
  "properties": {
    "iso:country":"IN",
    "ks:ks_alt_nam":"Sukanguri T.E. 109 111 nlr  B",
    "ks:ks_name":"Sukanguri T.e. 109 111 Nlr B",
    "ks:ks_pop":2548,
    "ks:ks_type":"HABITATION",
    "name:eng_x_preferred":[
        "Sukanguri T.e. 109 111 Nlr B"
    ],
    "name:eng_x_variant":[
        "Sukanguri T.E. 109 111 nlr  B"
    ],
    "wof:name":"Sukanguri T.e. 109 111 Nlr B",
    "wof:placetype":"locality",
    "wof:population":2548
},
  "geometry": {"coordinates":[95.52926600000001,27.508724],"type":"Point"}
}