{
  "type": "Feature",
  "properties": {
    "gn:admin1_code":"25.0",
    "gn:admin2_code":"605.0",
    "gn:asciiname":"Mottur",
    "gn:country_code":"IN",
    "gn:dem":418,
    "gn:feature_class":"P",
    "gn:feature_code":"PPL",
    "gn:name":"Mott\u016br",
    "gn:population":0,
    "gn:timezone":"Asia/Kolkata",
    "iso:country":"IN",
    "ks:ks_name":"Mottur",
    "ks:ks_pop":212,
    "ks:ks_type":"HABITATION",
    "ks:ks_uagg_main":0,
    "name:eng_x_preferred":[
        "Mottur"
    ],
    "wof:name":"Mottur",
    "wof:placetype":"neighbourhood",
    "wof:population":212
},
  "geometry": {"coordinates":[78.459907,12.460869],"type":"Point"}
}