{
  "type": "Feature",
  "properties": {
    "iso:country":"IN",
    "ks:ks_name":"Chandandhawa",
    "ks:ks_pop":327,
    "ks:ks_type":"HABITATION",
    "name:eng_x_preferred":[
        "Chandandhawa"
    ],
    "wof:name":"Chandandhawa",
    "wof:placetype":"locality",
    "wof:population":327
},
  "geometry": {"coordinates":[82.495507,22.735461],"type":"Point"}
}