{
  "type": "Feature",
  "properties": {
    "iso:country":"IN",
    "ks:ks_alt_nam":"Pars\u0101bera",
    "ks:ks_name":"Parsabera",
    "ks:ks_type":"VILLAGE",
    "name:eng_x_preferred":[
        "Parsabera"
    ],
    "name:eng_x_variant":[
        "Pars\u0101bera"
    ],
    "wof:name":"Parsabera",
    "wof:placetype":"locality"
},
  "geometry": {"coordinates":[85.74924,23.952171],"type":"Point"}
}