{
  "type": "Feature",
  "properties": {
    "gn:admin1_code":"35.0",
    "gn:admin2_code":"424",
    "gn:asciiname":"Astari",
    "gn:country_code":"IN",
    "gn:dem":279,
    "gn:feature_class":"P",
    "gn:feature_code":"PPL",
    "gn:name":"Ast\u0101ri",
    "gn:population":0,
    "gn:timezone":"Asia/Kolkata",
    "iso:country":"IN",
    "name:und_x_variant":[
        "Astahi",
        "Ast\u0101ri"
    ],
    "wof:name":"Astari",
    "wof:placetype":"locality"
},
  "geometry": {"coordinates":[78.8648,25.24215],"type":"Point"}
}