{
  "type": "Feature",
  "properties": {
    "gn:admin1_code":"23",
    "gn:admin2_code":"36.0",
    "gn:asciiname":"Sunran Rajputan",
    "gn:country_code":"IN",
    "gn:dem":239,
    "gn:feature_class":"P",
    "gn:feature_code":"PPL",
    "gn:name":"Sunr\u0101n R\u0101jput\u0101n",
    "gn:population":0,
    "gn:timezone":"Asia/Kolkata",
    "iso:country":"IN",
    "wof:name":"Sunran Rajputan",
    "wof:placetype":"locality"
},
  "geometry": {"coordinates":[75.71810000000001,31.20904],"type":"Point"}
}