{
  "type": "Feature",
  "properties": {
    "iso:country":"IN",
    "ks:ks_name":"Taradkya",
    "ks:ks_pop":826,
    "ks:ks_type":"VILLAGE",
    "name:eng_x_preferred":[
        "Taradkya"
    ],
    "wof:name":"Taradkya",
    "wof:placetype":"locality",
    "wof:population":826
},
  "geometry": {"coordinates":[75.44490500000001,25.588474],"type":"Point"}
}