{
  "type": "Feature",
  "properties": {
    "iso:country":"IN",
    "ks:ks_alt_nam":"santhaltola",
    "ks:ks_name":"Santhaltola",
    "ks:ks_pop":272,
    "ks:ks_type":"HABITATION",
    "name:eng_x_preferred":[
        "Santhaltola"
    ],
    "wof:name":"Santhaltola",
    "wof:placetype":"locality",
    "wof:population":272
},
  "geometry": {"coordinates":[85.408148,22.619351],"type":"Point"}
}