{
  "type": "Feature",
  "properties": {
    "iso:country":"IN",
    "ks:ks_name":"Chhatinbaid",
    "ks:ks_pop":574,
    "ks:ks_type":"VILLAGE",
    "name:eng_x_preferred":[
        "Chhatinbaid"
    ],
    "wof:name":"Chhatinbaid",
    "wof:placetype":"locality",
    "wof:population":574
},
  "geometry": {"coordinates":[86.925021,23.562282],"type":"Point"}
}