{
  "type": "Feature",
  "properties": {
    "iso:country":"IN",
    "ks:ks_name":"Amapara",
    "ks:ks_pop":40,
    "ks:ks_type":"HABITATION",
    "name:eng_x_preferred":[
        "Amapara"
    ],
    "wof:name":"Amapara",
    "wof:placetype":"locality",
    "wof:population":40
},
  "geometry": {"coordinates":[81.92461,19.880098],"type":"Point"}
}