{
  "type": "Feature",
  "properties": {
    "gn:admin1_code":"39.0",
    "gn:admin2_code":"66.0",
    "gn:asciiname":"Palati",
    "gn:country_code":"IN",
    "gn:dem":1063,
    "gn:feature_class":"P",
    "gn:feature_code":"PPL",
    "gn:name":"Pal\u0101ti",
    "gn:population":0,
    "gn:timezone":"Asia/Kolkata",
    "iso:country":"IN",
    "ks:ks_name":"Paladi",
    "ks:ks_pop":46,
    "ks:ks_type":"HABITATION",
    "name:eng_x_preferred":[
        "Paladi"
    ],
    "name:eng_x_variant":[
        "Palati"
    ],
    "wof:name":"Paladi",
    "wof:placetype":"locality",
    "wof:population":46
},
  "geometry": {"coordinates":[79.44144,29.494638],"type":"Point"}
}