{
  "type": "Feature",
  "properties": {
    "iso:country":"IN",
    "ks:ks_alt_nam":"olmokod",
    "ks:ks_name":"Olmokod",
    "ks:ks_pop":267,
    "ks:ks_type":"HABITATION",
    "name:eng_x_preferred":[
        "Olmokod"
    ],
    "wof:name":"Olmokod",
    "wof:placetype":"locality",
    "wof:population":267
},
  "geometry": {"coordinates":[85.21201600000001,22.694817],"type":"Point"}
}