{
  "type": "Feature",
  "properties": {
    "iso:country":"IN",
    "ks:ks_name":"Telugu Colony",
    "ks:ks_pop":320,
    "ks:ks_type":"HABITATION",
    "name:eng_x_preferred":[
        "Telugu Colony"
    ],
    "wof:name":"Telugu Colony",
    "wof:placetype":"locality",
    "wof:population":320
},
  "geometry": {"coordinates":[79.49585399999999,13.226678],"type":"Point"}
}