{
  "type": "Feature",
  "properties": {
    "iso:country":"IN",
    "ks:ks_alt_nam":"BELA GHAT ISTAMRAR",
    "ks:ks_name":"Bela Ghat Istamrar",
    "ks:ks_pop":210,
    "ks:ks_type":"HABITATION",
    "ks:ks_uagg_main":0,
    "name:eng_x_preferred":[
        "Bela Ghat Istamrar"
    ],
    "wof:name":"Bela Ghat Istamrar",
    "wof:placetype":"neighbourhood",
    "wof:population":210
},
  "geometry": {"coordinates":[87.444016,25.822516],"type":"Point"}
}