{
  "type": "Feature",
  "properties": {
    "gn:admin1_code":"16.0",
    "gn:admin2_code":"508.0",
    "gn:asciiname":"Sarkhera",
    "gn:country_code":"IN",
    "gn:dem":299,
    "gn:feature_class":"P",
    "gn:feature_code":"PPL",
    "gn:name":"Sarkhera",
    "gn:population":0,
    "gn:timezone":"Asia/Kolkata",
    "iso:country":"IN",
    "ks:ks_name":"Sarkheda",
    "ks:ks_pop":303,
    "ks:ks_type":"VILLAGE",
    "name:eng_x_preferred":[
        "Sarkheda"
    ],
    "name:eng_x_variant":[
        "Sarkhera"
    ],
    "wof:name":"Sarkheda",
    "wof:placetype":"locality",
    "wof:population":303
},
  "geometry": {"coordinates":[80.450603,19.973305],"type":"Point"}
}