{
  "type": "Feature",
  "properties": {
    "gn:admin1_code":"38.0",
    "gn:admin2_code":"347.0",
    "gn:asciiname":"Kenduatoli",
    "gn:country_code":"IN",
    "gn:dem":577,
    "gn:feature_class":"P",
    "gn:feature_code":"PPL",
    "gn:name":"Kendu\u0101toli",
    "gn:population":0,
    "gn:timezone":"Asia/Kolkata",
    "iso:country":"IN",
    "wof:name":"Kenduatoli",
    "wof:placetype":"locality"
},
  "geometry": {"coordinates":[85.01982,24.03923],"type":"Point"}
}