{
  "type": "Feature",
  "properties": {
    "iso:country":"IN",
    "ks:ks_alt_nam":"LOWER KISHUJORY",
    "ks:ks_name":"Lower Kishujory",
    "ks:ks_pop":100,
    "ks:ks_type":"HABITATION",
    "name:eng_x_preferred":[
        "Lower Kishujory"
    ],
    "wof:name":"Lower Kishujory",
    "wof:placetype":"locality",
    "wof:population":100
},
  "geometry": {"coordinates":[86.535886,24.630417],"type":"Point"}
}