{
  "type": "Feature",
  "properties": {
    "iso:country":"IN",
    "ks:ks_name":"Bishram Nagar",
    "ks:ks_pop":162,
    "ks:ks_type":"VILLAGE",
    "name:eng_x_preferred":[
        "Bishram Nagar"
    ],
    "wof:name":"Bishram Nagar",
    "wof:placetype":"locality",
    "wof:population":162
},
  "geometry": {"coordinates":[80.45208,27.551829],"type":"Point"}
}