{
  "type": "Feature",
  "properties": {
    "gn:admin1_code":"34.0",
    "gn:admin2_code":"236.0",
    "gn:asciiname":"Katari",
    "gn:country_code":"IN",
    "gn:dem":113,
    "gn:feature_class":"P",
    "gn:feature_code":"PPL",
    "gn:name":"Kat\u0101ri",
    "gn:population":0,
    "gn:timezone":"Asia/Kolkata",
    "iso:country":"IN",
    "name:bih_x_preferred":[
        "\u0915\u091f\u093e\u0930\u0940"
    ],
    "name:deu_x_preferred":[
        "Katari"
    ],
    "name:fra_x_preferred":[
        "Katari"
    ],
    "name:hin_x_preferred":[
        "\u0915\u091f\u093e\u0930\u0940"
    ],
    "name:ita_x_preferred":[
        "Katari"
    ],
    "name:msa_x_preferred":[
        "Katari"
    ],
    "name:nep_x_preferred":[
        "\u0915\u091f\u093e\u0930\u0940 \u0928\u0917\u0930\u092a\u093e\u0932\u093f\u0915\u093e"
    ],
    "name:new_x_preferred":[
        "\u0915\u091f\u093e\u0930\u0940"
    ],
    "name:pol_x_preferred":[
        "Katari"
    ],
    "name:urd_x_preferred":[
        "\u06a9\u0679\u0627\u0631\u06cc"
    ],
    "wof:name":"Katari",
    "wof:placetype":"locality"
},
  "geometry": {"coordinates":[84.97301,24.79693],"type":"Point"}
}