{
  "type": "Feature",
  "properties": {
    "gn:admin1_code":"35",
    "gn:admin2_code":"428.0",
    "gn:asciiname":"Mariya",
    "gn:country_code":"IN",
    "gn:dem":348,
    "gn:feature_class":"P",
    "gn:feature_code":"PPL",
    "gn:name":"Mariya",
    "gn:population":0,
    "gn:timezone":"Asia/Kolkata",
    "iso:country":"IN",
    "name:aze_x_preferred":[
        "Mariya"
    ],
    "name:fra_x_preferred":[
        "Mariya"
    ],
    "wof:name":"Mariya",
    "wof:placetype":"neighbourhood"
},
  "geometry": {"coordinates":[79.44589999999999,23.98972],"type":"Point"}
}