{
  "type": "Feature",
  "properties": {
    "iso:country":"IN",
    "ks:ks_alt_nam":"Sarillavari peta",
    "ks:ks_name":"Sarillavari Peta",
    "ks:ks_pop":104,
    "ks:ks_type":"HABITATION",
    "name:eng_x_preferred":[
        "Sarillavari Peta"
    ],
    "wof:name":"Sarillavari Peta",
    "wof:placetype":"locality",
    "wof:population":104
},
  "geometry": {"coordinates":[81.9485,16.669423],"type":"Point"}
}