{
  "type": "Feature",
  "properties": {
    "iso:country":"IN",
    "ks:ks_name":"Rasulwa",
    "ks:ks_pop":380,
    "ks:ks_type":"HABITATION",
    "name:eng_x_preferred":[
        "Rasulwa"
    ],
    "wof:name":"Rasulwa",
    "wof:placetype":"locality",
    "wof:population":380
},
  "geometry": {"coordinates":[80.579363,27.433415],"type":"Point"}
}