{
  "type": "Feature",
  "properties": {
    "iso:country":"IN",
    "ks:ks_name":"Barhaunia",
    "ks:ks_pop":475,
    "ks:ks_type":"VILLAGE",
    "name:eng_x_preferred":[
        "Barhaunia"
    ],
    "wof:name":"Barhaunia",
    "wof:placetype":"locality",
    "wof:population":475
},
  "geometry": {"coordinates":[86.952338,24.933505],"type":"Point"}
}