{
  "type": "Feature",
  "properties": {
    "gn:admin1_code":"34.0",
    "gn:admin2_code":"236.0",
    "gn:asciiname":"Nanhu Bigha",
    "gn:country_code":"IN",
    "gn:dem":161,
    "gn:feature_class":"P",
    "gn:feature_code":"PPL",
    "gn:name":"Nanhu Bigha",
    "gn:population":0,
    "gn:timezone":"Asia/Kolkata",
    "iso:country":"IN",
    "ks:ks_name":"Nanhu Bigha",
    "ks:ks_pop":254,
    "ks:ks_type":"VILLAGE",
    "ks:ks_uagg_main":0,
    "name:eng_x_preferred":[
        "Nanhu Bigha"
    ],
    "wof:name":"Nanhu Bigha",
    "wof:placetype":"neighbourhood",
    "wof:population":254
},
  "geometry": {"coordinates":[84.930481,24.515271],"type":"Point"}
}