{
  "type": "Feature",
  "properties": {
    "iso:country":"IN",
    "ks:ks_name":"Narpi",
    "ks:ks_pop":67,
    "ks:ks_type":"VILLAGE",
    "name:eng_x_preferred":[
        "Narpi"
    ],
    "wof:name":"Narpi",
    "wof:placetype":"locality",
    "wof:population":67
},
  "geometry": {"coordinates":[80.637101,21.691307],"type":"Point"}
}