{
  "type": "Feature",
  "properties": {
    "iso:country":"IN",
    "ks:ks_name":"Bhalyachiwadi",
    "ks:ks_pop":66,
    "ks:ks_type":"HABITATION",
    "name:eng_x_preferred":[
        "Bhalyachiwadi"
    ],
    "wof:name":"Bhalyachiwadi",
    "wof:placetype":"locality",
    "wof:population":66
},
  "geometry": {"coordinates":[73.28620100000001,19.646369],"type":"Point"}
}