{
  "type": "Feature",
  "properties": {
    "iso:country":"IN",
    "ks:ks_name":"Mal Chacha Kheri",
    "ks:ks_pop":24,
    "ks:ks_type":"VILLAGE",
    "ks:ks_uagg_main":0,
    "name:eng_x_preferred":[
        "Mal Chacha Kheri"
    ],
    "wof:name":"Mal Chacha Kheri",
    "wof:placetype":"neighbourhood",
    "wof:population":24
},
  "geometry": {"coordinates":[74.858054,23.71168],"type":"Point"}
}