{
  "type": "Feature",
  "properties": {
    "iso:country":"IN",
    "ks:ks_name":"Jainan",
    "ks:ks_pop":489,
    "ks:ks_type":"VILLAGE",
    "ks:ks_uagg_main":0,
    "name:eng_x_preferred":[
        "Jainan"
    ],
    "wof:name":"Jainan",
    "wof:placetype":"neighbourhood",
    "wof:population":489
},
  "geometry": {"coordinates":[84.28089300000001,26.340421],"type":"Point"}
}