{
  "type": "Feature",
  "properties": {
    "iso:country":"IN",
    "ks:ks_name":"Dhoora Sangroli",
    "ks:ks_pop":710,
    "ks:ks_type":"VILLAGE",
    "name:eng_x_preferred":[
        "Dhoora Sangroli"
    ],
    "wof:name":"Dhoora Sangroli",
    "wof:placetype":"locality",
    "wof:population":710
},
  "geometry": {"coordinates":[79.76814,29.523485],"type":"Point"}
}