{
  "type": "Feature",
  "properties": {
    "iso:country":"IN",
    "ks:ks_name":"Kayem Majer Alga Pt I",
    "ks:ks_pop":377,
    "ks:ks_type":"HABITATION",
    "name:eng_x_preferred":[
        "Kayem Majer Alga Pt I"
    ],
    "wof:name":"Kayem Majer Alga Pt I",
    "wof:placetype":"locality",
    "wof:population":377
},
  "geometry": {"coordinates":[90.47206799999999,26.171464],"type":"Point"}
}