{
  "type": "Feature",
  "properties": {
    "iso:country":"IN",
    "ks:ks_name":"Naik Wasti",
    "ks:ks_pop":152,
    "ks:ks_type":"HABITATION",
    "ks:ks_uagg_main":0,
    "name:eng_x_preferred":[
        "Naik Wasti"
    ],
    "wof:name":"Naik Wasti",
    "wof:placetype":"neighbourhood",
    "wof:population":152
},
  "geometry": {"coordinates":[74.355042,16.04245],"type":"Point"}
}