{
  "type": "Feature",
  "properties": {
    "iso:country":"IN",
    "ks:ks_name":"Vadka",
    "ks:ks_pop":448,
    "ks:ks_type":"VILLAGE",
    "name:eng_x_preferred":[
        "Vadka"
    ],
    "wof:name":"Vadka",
    "wof:placetype":"locality",
    "wof:population":448
},
  "geometry": {"coordinates":[72.948753,25.110656],"type":"Point"}
}