{
  "type": "Feature",
  "properties": {
    "iso:country":"IN",
    "ks:ks_alt_nam":"Muslim tola",
    "ks:ks_name":"Muslim Tola",
    "ks:ks_pop":954,
    "ks:ks_type":"HABITATION",
    "ks:ks_uagg_main":0,
    "name:eng_x_preferred":[
        "Muslim Tola"
    ],
    "wof:name":"Muslim Tola",
    "wof:placetype":"neighbourhood",
    "wof:population":954
},
  "geometry": {"coordinates":[87.052104,25.374508],"type":"Point"}
}