{
  "type": "Feature",
  "properties": {
    "iso:country":"IN",
    "ks:ks_name":"Gobindapur",
    "ks:ks_pop":1047,
    "ks:ks_type":"VILLAGE",
    "name:eng_x_preferred":[
        "Gobindapur"
    ],
    "wof:name":"Gobindapur",
    "wof:placetype":"locality",
    "wof:population":1047
},
  "geometry": {"coordinates":[87.679827,22.191973],"type":"Point"}
}