{
  "type": "Feature",
  "properties": {
    "iso:country":"IN",
    "ks:ks_name":"Chikkakundur",
    "ks:ks_type":"VILLAGE",
    "name:eng_x_preferred":[
        "Chikkakundur"
    ],
    "wof:name":"Chikkakundur",
    "wof:placetype":"locality"
},
  "geometry": {"coordinates":[76.475606,11.851791],"type":"Point"}
}