{
  "type": "Feature",
  "properties": {
    "iso:country":"IN",
    "ks:ks_name":"Pudisara",
    "ks:ks_pop":419,
    "ks:ks_type":"VILLAGE",
    "name:eng_x_preferred":[
        "Pudisara"
    ],
    "wof:name":"Pudisara",
    "wof:placetype":"locality",
    "wof:population":419
},
  "geometry": {"coordinates":[83.022102,20.35293],"type":"Point"}
}