{
  "type": "Feature",
  "properties": {
    "iso:country":"IN",
    "ks:ks_name":"Barapalli",
    "ks:ks_pop":144,
    "ks:ks_type":"VILLAGE",
    "name:eng_x_preferred":[
        "Barapalli"
    ],
    "wof:name":"Barapalli",
    "wof:placetype":"locality",
    "wof:population":144
},
  "geometry": {"coordinates":[84.82742,20.355331],"type":"Point"}
}