{
  "type": "Feature",
  "properties": {
    "iso:country":"IN",
    "ks:ks_name":"Ashnabani",
    "ks:ks_pop":222,
    "ks:ks_type":"HABITATION",
    "name:eng_x_preferred":[
        "Ashnabani"
    ],
    "wof:name":"Ashnabani",
    "wof:placetype":"locality",
    "wof:population":222
},
  "geometry": {"coordinates":[87.178321,22.632825],"type":"Point"}
}