{
  "type": "Feature",
  "properties": {
    "iso:country":"IN",
    "ks:ks_name":"Kammaguttahalli",
    "ks:ks_pop":114,
    "ks:ks_type":"HABITATION",
    "name:eng_x_preferred":[
        "Kammaguttahalli"
    ],
    "wof:name":"Kammaguttahalli",
    "wof:placetype":"locality",
    "wof:population":114
},
  "geometry": {"coordinates":[77.76773300000001,13.633303],"type":"Point"}
}