{
  "type": "Feature",
  "properties": {
    "iso:country":"IN",
    "ks:ks_name":"Purlemane",
    "ks:ks_pop":25,
    "ks:ks_type":"HABITATION",
    "name:eng_x_preferred":[
        "Purlemane"
    ],
    "wof:name":"Purlemane",
    "wof:placetype":"locality",
    "wof:population":25
},
  "geometry": {"coordinates":[74.722961,14.622688],"type":"Point"}
}