{
  "type": "Feature",
  "properties": {
    "gn:admin1_code":"39.0",
    "gn:admin2_code":"61.0",
    "gn:asciiname":"Kakrora",
    "gn:country_code":"IN",
    "gn:dem":1359,
    "gn:feature_class":"P",
    "gn:feature_code":"PPL",
    "gn:name":"Kakrora",
    "gn:population":0,
    "gn:timezone":"Asia/Kolkata",
    "iso:country":"IN",
    "wof:name":"Kakrora",
    "wof:placetype":"locality"
},
  "geometry": {"coordinates":[79.02925999999999,29.87632],"type":"Point"}
}