{
  "type": "Feature",
  "properties": {
    "gn:admin1_code":"39.0",
    "gn:admin2_code":"61.0",
    "gn:asciiname":"Kakrora",
    "gn:country_code":"IN",
    "gn:dem":1359,
    "gn:feature_class":"P",
    "gn:feature_code":"PPL",
    "gn:name":"Kakrora",
    "gn:population":0,
    "gn:timezone":"Asia/Kolkata",
    "iso:country":"IN",
    "ks:ks_name":"Kakroda",
    "ks:ks_pop":245,
    "ks:ks_type":"VILLAGE",
    "name:eng_x_preferred":[
        "Kakroda"
    ],
    "name:eng_x_variant":[
        "Kakrora"
    ],
    "wof:name":"Kakroda",
    "wof:placetype":"locality",
    "wof:population":245
},
  "geometry": {"coordinates":[79.027688,29.875808],"type":"Point"}
}