{
  "type": "Feature",
  "properties": {
    "iso:country":"IN",
    "ks:ks_name":"Laha Biran",
    "ks:ks_pop":78,
    "ks:ks_type":"VILLAGE",
    "name:eng_x_preferred":[
        "Laha Biran"
    ],
    "wof:name":"Laha Biran",
    "wof:placetype":"locality",
    "wof:population":78
},
  "geometry": {"coordinates":[80.188951,28.17789],"type":"Point"}
}