{
  "type": "Feature",
  "properties": {
    "iso:country":"IN",
    "ks:ks_name":"Kuppadi",
    "ks:ks_pop":58,
    "ks:ks_type":"HABITATION",
    "name:eng_x_preferred":[
        "Kuppadi"
    ],
    "wof:name":"Kuppadi",
    "wof:placetype":"locality",
    "wof:population":58
},
  "geometry": {"coordinates":[74.709841,14.015576],"type":"Point"}
}