{
  "type": "Feature",
  "properties": {
    "gn:admin1_code":"11.0",
    "gn:admin2_code":"33.0",
    "gn:asciiname":"Khaloth",
    "gn:country_code":"IN",
    "gn:dem":2014,
    "gn:feature_class":"P",
    "gn:feature_code":"PPL",
    "gn:name":"Khaloth",
    "gn:population":0,
    "gn:timezone":"Asia/Kolkata",
    "iso:country":"IN",
    "wof:name":"Khaloth",
    "wof:placetype":"locality"
},
  "geometry": {"coordinates":[77.42019000000001,31.08218],"type":"Point"}
}