{
  "type": "Feature",
  "properties": {
    "iso:country":"IN",
    "ks:ks_name":"Shiwpur",
    "ks:ks_pop":2021,
    "ks:ks_type":"VILLAGE",
    "name:eng_x_preferred":[
        "Shiwpur"
    ],
    "wof:name":"Shiwpur",
    "wof:placetype":"locality",
    "wof:population":2021
},
  "geometry": {"coordinates":[83.59035900000001,25.147319],"type":"Point"}
}