{
  "type": "Feature",
  "properties": {
    "iso:country":"IN",
    "ks:ks_alt_nam":"gaonmala",
    "ks:ks_name":"Gaonmala",
    "ks:ks_pop":98,
    "ks:ks_type":"HABITATION",
    "name:eng_x_preferred":[
        "Gaonmala"
    ],
    "wof:name":"Gaonmala",
    "wof:placetype":"locality",
    "wof:population":98
},
  "geometry": {"coordinates":[73.58110600000001,16.607119],"type":"Point"}
}