{
  "type": "Feature",
  "properties": {
    "iso:country":"IN",
    "ks:ks_name":"Saij",
    "ks:ks_pop":13882,
    "ks:ks_type":"VILLAGE",
    "ks:ks_uagg_main":0,
    "name:eng_x_preferred":[
        "Saij"
    ],
    "wof:name":"Saij",
    "wof:placetype":"neighbourhood",
    "wof:population":13882
},
  "geometry": {"coordinates":[72.518333,23.22025],"type":"Point"}
}