{
  "type": "Feature",
  "properties": {
    "iso:country":"IN",
    "ks:ks_name":"Patwaria",
    "ks:ks_type":"VILLAGE",
    "name:eng_x_preferred":[
        "Patwaria"
    ],
    "wof:name":"Patwaria",
    "wof:placetype":"locality"
},
  "geometry": {"coordinates":[81.037387,25.33743],"type":"Point"}
}