{
  "type": "Feature",
  "properties": {
    "iso:country":"IN",
    "ks:ks_alt_nam":"NIDHAN PARA",
    "ks:ks_name":"Nidhan Para",
    "ks:ks_pop":266,
    "ks:ks_type":"HABITATION",
    "ks:ks_uagg_main":0,
    "name:eng_x_preferred":[
        "Nidhan Para"
    ],
    "wof:name":"Nidhan Para",
    "wof:placetype":"neighbourhood",
    "wof:population":266
},
  "geometry": {"coordinates":[91.426892,23.621733],"type":"Point"}
}