{
  "type": "Feature",
  "properties": {
    "gn:admin1_code":"9.0",
    "gn:admin2_code":"484.0",
    "gn:asciiname":"Deokanwala Muwara",
    "gn:country_code":"IN",
    "gn:dem":163,
    "gn:feature_class":"P",
    "gn:feature_code":"PPL",
    "gn:name":"Deokanw\u0101la Muw\u0101ra",
    "gn:population":0,
    "gn:timezone":"Asia/Kolkata",
    "iso:country":"IN",
    "wof:name":"Deokanwala Muwara",
    "wof:placetype":"locality"
},
  "geometry": {"coordinates":[73.93874,23.24161],"type":"Point"}
}