{
  "type": "Feature",
  "properties": {
    "iso:country":"IN",
    "ks:ks_name":"Kantipur",
    "ks:ks_pop":519,
    "ks:ks_type":"VILLAGE",
    "ks:ks_uagg_main":0,
    "name:eng_x_preferred":[
        "Kantipur"
    ],
    "wof:name":"Kantipur",
    "wof:placetype":"neighbourhood",
    "wof:population":519
},
  "geometry": {"coordinates":[86.65019599999999,20.668607],"type":"Point"}
}