{
  "type": "Feature",
  "properties": {
    "iso:country":"IN",
    "ks:ks_alt_nam":"SAHAR KUNDI",
    "ks:ks_name":"Sahar Kundi",
    "ks:ks_pop":2428,
    "ks:ks_type":"HABITATION",
    "name:eng_x_preferred":[
        "Sahar Kundi"
    ],
    "wof:name":"Sahar Kundi",
    "wof:placetype":"locality",
    "wof:population":2428
},
  "geometry": {"coordinates":[86.59497399999999,25.516368],"type":"Point"}
}