{
  "type": "Feature",
  "properties": {
    "gn:admin1_code":"19.0",
    "gn:admin2_code":"571.0",
    "gn:asciiname":"Nachakanpalya",
    "gn:country_code":"IN",
    "gn:dem":856,
    "gn:feature_class":"P",
    "gn:feature_code":"PPL",
    "gn:name":"N\u0101chakanp\u0101lya",
    "gn:population":0,
    "gn:timezone":"Asia/Kolkata",
    "iso:country":"IN",
    "wof:name":"Nachakanpalya",
    "wof:placetype":"neighbourhood"
},
  "geometry": {"coordinates":[77.14603,13.23122],"type":"Point"}
}