{
  "type": "Feature",
  "properties": {
    "iso:country":"IN",
    "ks:ks_alt_nam":"Koth\u0101r",
    "ks:ks_name":"Kothar",
    "ks:ks_pop":3234,
    "ks:ks_type":"VILLAGE",
    "ks:ks_uagg_main":0,
    "name:eng_x_preferred":[
        "Kothar"
    ],
    "name:eng_x_variant":[
        "Koth\u0101r"
    ],
    "wof:name":"Kothar",
    "wof:placetype":"locality",
    "wof:population":3234
},
  "geometry": {"coordinates":[85.550085,23.610665],"type":"Point"}
}