{
  "type": "Feature",
  "properties": {
    "iso:country":"IN",
    "ks:ks_name":"Mojal",
    "ks:ks_pop":235,
    "ks:ks_type":"VILLAGE",
    "name:eng_x_preferred":[
        "Mojal"
    ],
    "wof:name":"Mojal",
    "wof:placetype":"locality",
    "wof:population":235
},
  "geometry": {"coordinates":[74.73153600000001,23.811081],"type":"Point"}
}