{
  "type": "Feature",
  "properties": {
    "iso:country":"IN",
    "ne:ADM0CAP":0.0,
    "ne:ADM0NAME":"India",
    "ne:ADM0_A3":"IND",
    "ne:ADM1NAME":"Madhya Pradesh",
    "ne:ADMIN1_COD":0,
    "ne:CAPALT":0,
    "ne:CHANGED":0,
    "ne:CHECKME":1,
    "ne:COMPARE":0,
    "ne:DIFFASCII":0,
    "ne:ELEVATION":0.0,
    "ne:FEATURECLA":"Populated place",
    "ne:GEONAMEID":-1,
    "ne:GEONAMESNO":"No GeoNames match due to small population, not in GeoNames, or poor NEV placement.",
    "ne:GN_POP":0,
    "ne:GTOPO30":0.0,
    "ne:ISO_A2":"IN",
    "ne:LABELRANK":1,
    "ne:LATITUDE":21.300391,
    "ne:LONGITUDE":76.130019,
    "ne:LS_MATCH":1,
    "ne:LS_NAME":"Burhanpur",
    "ne:MAX_AREAKM":95.0,
    "ne:MAX_AREAMI":37.0,
    "ne:MAX_BBXMAX":76.291667,
    "ne:MAX_BBXMIN":76.133333,
    "ne:MAX_BBYMAX":21.366667,
    "ne:MAX_BBYMIN":21.258333,
    "ne:MAX_NATSCA":20.0,
    "ne:MAX_PERKM":77.0,
    "ne:MAX_PERMI":48.0,
    "ne:MAX_POP10":197233,
    "ne:MAX_POP20":197233,
    "ne:MAX_POP300":0,
    "ne:MAX_POP310":0,
    "ne:MAX_POP50":0,
    "ne:MEAN_BBXC":76.221464,
    "ne:MEAN_BBYC":21.31138,
    "ne:MEGACITY":0,
    "ne:MIN_AREAKM":95.0,
    "ne:MIN_AREAMI":37.0,
    "ne:MIN_BBXMAX":76.291667,
    "ne:MIN_BBXMIN":76.133333,
    "ne:MIN_BBYMAX":21.366667,
    "ne:MIN_BBYMIN":21.258333,
    "ne:MIN_PERKM":77.0,
    "ne:MIN_PERMI":48.0,
    "ne:NAME":"Burhanpur",
    "ne:NAMEASCII":"Burhanpur",
    "ne:NAMEDIFF":0,
    "ne:NATSCALE":20,
    "ne:POP1950":0,
    "ne:POP1955":0,
    "ne:POP1960":0,
    "ne:POP1965":0,
    "ne:POP1970":0,
    "ne:POP1975":0,
    "ne:POP1980":0,
    "ne:POP1985":0,
    "ne:POP1990":0,
    "ne:POP1995":0,
    "ne:POP2000":0,
    "ne:POP2005":0,
    "ne:POP2010":0,
    "ne:POP2015":0,
    "ne:POP2020":0,
    "ne:POP2025":0,
    "ne:POP2050":0,
    "ne:POP_MAX":197233,
    "ne:POP_MIN":197233,
    "ne:POP_OTHER":0,
    "ne:RANK_MAX":9,
    "ne:RANK_MIN":9,
    "ne:SCALERANK":7,
    "ne:SOV0NAME":"India",
    "ne:SOV_A3":"IND",
    "ne:UN_FID":0,
    "ne:UN_LAT":0.0,
    "ne:UN_LONG":0.0,
    "ne:WORLDCITY":0,
    "ne:min_zoom":6.7,
    "wof:name":"Burhanpur",
    "wof:placetype":"locality"
},
  "geometry": {"coordinates":[76.13001948944981,21.30039105120852],"type":"Point"}
}