{
  "type": "Feature",
  "properties": {
    "iso:country":"IN",
    "ks:ks_alt_nam":"Dodda M\u0101dag\u0101nahalli",
    "ks:ks_alt_nam_2":"Dodda Madaganahalli",
    "ks:ks_name":"Dodda",
    "ks:ks_type":"VILLAGE",
    "ks:ks_uagg_main":0,
    "name:eng_x_preferred":[
        "Dodda"
    ],
    "name:eng_x_variant":[
        "Dodda M\u0101dag\u0101nahalli",
        "Dodda Madaganahalli"
    ],
    "wof:name":"Dodda",
    "wof:placetype":"locality"
},
  "geometry": {"coordinates":[76.074208,12.991077],"type":"Point"}
}