{
  "type": "Feature",
  "properties": {
    "iso:country":"IN",
    "ks:ks_name":"Pitanali",
    "ks:ks_pop":195,
    "ks:ks_type":"VILLAGE",
    "name:eng_x_preferred":[
        "Pitanali"
    ],
    "wof:name":"Pitanali",
    "wof:placetype":"locality",
    "wof:population":195
},
  "geometry": {"coordinates":[84.38825799999999,21.084675],"type":"Point"}
}