{
  "type": "Feature",
  "properties": {
    "gn:admin1_code":"35.0",
    "gn:admin2_code":"449.0",
    "gn:asciiname":"Ghughari",
    "gn:country_code":"IN",
    "gn:dem":360,
    "gn:feature_class":"P",
    "gn:feature_code":"PPL",
    "gn:name":"Ghughari",
    "gn:population":0,
    "gn:timezone":"Asia/Kolkata",
    "iso:country":"IN",
    "ks:ks_name":"Ghoghari",
    "ks:ks_pop":337,
    "ks:ks_type":"VILLAGE",
    "name:eng_x_preferred":[
        "Ghoghari"
    ],
    "name:eng_x_variant":[
        "Ghughari"
    ],
    "wof:name":"Ghoghari",
    "wof:placetype":"locality",
    "wof:population":337
},
  "geometry": {"coordinates":[78.12495800000001,22.589278],"type":"Point"}
}