{
  "type": "Feature",
  "properties": {
    "iso:country":"IN",
    "ks:ks_name":"Janatha Colony",
    "ks:ks_pop":310,
    "ks:ks_type":"HABITATION",
    "name:eng_x_preferred":[
        "Janatha Colony"
    ],
    "wof:name":"Janatha Colony",
    "wof:placetype":"locality",
    "wof:population":310
},
  "geometry": {"coordinates":[75.438101,12.9975],"type":"Point"}
}