{
  "type": "Feature",
  "properties": {
    "iso:country":"IN",
    "ks:ks_name":"Vadakulatchalapatty",
    "ks:ks_pop":710,
    "ks:ks_type":"HABITATION",
    "name:eng_x_preferred":[
        "Vadakulatchalapatty"
    ],
    "wof:name":"Vadakulatchalapatty",
    "wof:placetype":"locality",
    "wof:population":710
},
  "geometry": {"coordinates":[77.421295,10.504571],"type":"Point"}
}