{
  "type": "Feature",
  "properties": {
    "gn:admin1_code":"36.0",
    "gn:admin2_code":"134.0",
    "gn:asciiname":"Tarikampur Rupchand",
    "gn:country_code":"IN",
    "gn:dem":228,
    "gn:feature_class":"P",
    "gn:feature_code":"PPL",
    "gn:name":"Tar\u012bkampur R\u016bpchand",
    "gn:population":0,
    "gn:timezone":"Asia/Kolkata",
    "iso:country":"IN",
    "name:und_x_variant":[
        "Tar\u012bkampur R\u016bpchand",
        "Tikkupura"
    ],
    "wof:name":"Tarikampur Rupchand",
    "wof:placetype":"locality"
},
  "geometry": {"coordinates":[78.11214,29.40865],"type":"Point"}
}