{
  "type": "Feature",
  "properties": {
    "iso:country":"IN",
    "ks:ks_name":"Sauda",
    "ks:ks_type":"VILLAGE",
    "name:eng_x_preferred":[
        "Sauda"
    ],
    "wof:name":"Sauda",
    "wof:placetype":"neighbourhood"
},
  "geometry": {"coordinates":[76.981804,28.710506],"type":"Point"}
}