{
  "type": "Feature",
  "properties": {
    "gn:admin1_code":"39",
    "gn:admin2_code":"61.0",
    "gn:asciiname":"Lekuli",
    "gn:country_code":"IN",
    "gn:dem":1371,
    "gn:feature_class":"P",
    "gn:feature_code":"PPL",
    "gn:name":"Lekuli",
    "gn:population":0,
    "gn:timezone":"Asia/Kolkata",
    "iso:country":"IN",
    "ks:ks_name":"Lekoli",
    "ks:ks_pop":354,
    "ks:ks_type":"VILLAGE",
    "name:eng_x_preferred":[
        "Lekoli"
    ],
    "name:eng_x_variant":[
        "Lekuli"
    ],
    "wof:name":"Lekoli",
    "wof:placetype":"locality",
    "wof:population":354
},
  "geometry": {"coordinates":[78.92318400000001,29.804927],"type":"Point"}
}