{
  "type": "Feature",
  "properties": {
    "iso:country":"IN",
    "ks:ks_alt_nam":"KERHATOLA",
    "ks:ks_name":"Kerhatola",
    "ks:ks_pop":342,
    "ks:ks_type":"HABITATION",
    "name:eng_x_preferred":[
        "Kerhatola"
    ],
    "wof:name":"Kerhatola",
    "wof:placetype":"locality",
    "wof:population":342
},
  "geometry": {"coordinates":[81.970201,22.940411],"type":"Point"}
}