{
  "type": "Feature",
  "properties": {
    "iso:country":"IN",
    "ks:ks_name":"Payli Ryt",
    "ks:ks_pop":278,
    "ks:ks_type":"VILLAGE",
    "name:eng_x_preferred":[
        "Payli Ryt"
    ],
    "wof:name":"Payli Ryt",
    "wof:placetype":"locality",
    "wof:population":278
},
  "geometry": {"coordinates":[79.92256399999999,22.843581],"type":"Point"}
}