{
  "type": "Feature",
  "properties": {
    "iso:country":"IN",
    "ks:ks_name":"Tharipramunda Jn",
    "ks:ks_pop":758,
    "ks:ks_type":"HABITATION",
    "name:eng_x_preferred":[
        "Tharipramunda Jn"
    ],
    "wof:name":"Tharipramunda Jn",
    "wof:placetype":"locality",
    "wof:population":758
},
  "geometry": {"coordinates":[76.305908,11.12941],"type":"Point"}
}