{
  "type": "Feature",
  "properties": {
    "gn:admin1_code":"10",
    "gn:admin2_code":"87.0",
    "gn:asciiname":"Hathangaon Ka Bas",
    "gn:country_code":"IN",
    "gn:dem":191,
    "gn:feature_class":"P",
    "gn:feature_code":"PPL",
    "gn:name":"Hathangaon Ka B\u0101s",
    "gn:population":0,
    "gn:timezone":"Asia/Kolkata",
    "iso:country":"IN",
    "wof:name":"Hathangaon Ka Bas",
    "wof:placetype":"locality"
},
  "geometry": {"coordinates":[77.24200999999999,27.81061],"type":"Point"}
}