{
  "type": "Feature",
  "properties": {
    "iso:country":"IN",
    "ks:ks_alt_nam":"KHOT VASTI",
    "ks:ks_name":"Khot Vasti",
    "ks:ks_pop":78,
    "ks:ks_type":"HABITATION",
    "name:eng_x_preferred":[
        "Khot Vasti"
    ],
    "wof:name":"Khot Vasti",
    "wof:placetype":"neighbourhood",
    "wof:population":78
},
  "geometry": {"coordinates":[74.664951,16.863133],"type":"Point"}
}