{
  "type": "Feature",
  "properties": {
    "iso:country":"IN",
    "ks:ks_name":"Bhokariya",
    "ks:ks_pop":34,
    "ks:ks_type":"VILLAGE",
    "name:eng_x_preferred":[
        "Bhokariya"
    ],
    "wof:name":"Bhokariya",
    "wof:placetype":"locality",
    "wof:population":34
},
  "geometry": {"coordinates":[75.530012,21.983087],"type":"Point"}
}