{
  "type": "Feature",
  "properties": {
    "iso:country":"IN",
    "ks:ks_name":"Tikarpada",
    "ks:ks_pop":130,
    "ks:ks_type":"VILLAGE",
    "name:eng_x_preferred":[
        "Tikarpada"
    ],
    "wof:name":"Tikarpada",
    "wof:placetype":"locality",
    "wof:population":130
},
  "geometry": {"coordinates":[84.292216,20.575327],"type":"Point"}
}