{
  "type": "Feature",
  "properties": {
    "iso:country":"IN",
    "ks:ks_name":"Tok Jagarnath Urf Dharampur",
    "ks:ks_pop":284,
    "ks:ks_type":"VILLAGE",
    "name:eng_x_preferred":[
        "Tok Jagarnath Urf Dharampur"
    ],
    "wof:name":"Tok Jagarnath Urf Dharampur",
    "wof:placetype":"locality",
    "wof:population":284
},
  "geometry": {"coordinates":[85.22203500000001,25.992644],"type":"Point"}
}