{
  "type": "Feature",
  "properties": {
    "iso:country":"IN",
    "ks:ks_name":"Chibad Khurd",
    "ks:ks_pop":333,
    "ks:ks_type":"VILLAGE",
    "name:eng_x_preferred":[
        "Chibad Khurd"
    ],
    "wof:name":"Chibad Khurd",
    "wof:placetype":"locality",
    "wof:population":333
},
  "geometry": {"coordinates":[76.495969,24.108542],"type":"Point"}
}