{
  "type": "Feature",
  "properties": {
    "iso:country":"IN",
    "ks:ks_name":"Kalingi",
    "ks:ks_pop":150,
    "ks:ks_type":"VILLAGE",
    "name:eng_x_preferred":[
        "Kalingi"
    ],
    "wof:name":"Kalingi",
    "wof:placetype":"locality",
    "wof:population":150
},
  "geometry": {"coordinates":[83.344646,19.145504],"type":"Point"}
}