{
  "type": "Feature",
  "properties": {
    "gn:country":"IN",
    "gn:fcode":"PPL",
    "gn:pop":14077,
    "iso:country":"IN",
    "name:ben_x_preferred":[
        "\u09ae\u09a0"
    ],
    "name:bpy_x_preferred":[
        "\u09ae\u09cb\u09a5"
    ],
    "name:bul_x_preferred":[
        "\u041c\u043e\u0442\u0445"
    ],
    "name:deu_x_preferred":[
        "Moth"
    ],
    "name:eng_x_preferred":[
        "Moth"
    ],
    "name:fra_x_preferred":[
        "Moth"
    ],
    "name:guj_x_preferred":[
        "\u0aae\u0acb\u0aa5"
    ],
    "name:ita_x_preferred":[
        "Moth"
    ],
    "name:jpn_x_preferred":[
        "\u30e2\u30b9"
    ],
    "name:kan_x_preferred":[
        "\u0cae\u0cbe\u0ca4\u0ccd"
    ],
    "name:kor_x_preferred":[
        "\ubaa8\uc2a4"
    ],
    "name:nan_x_preferred":[
        "Moth"
    ],
    "name:nld_x_preferred":[
        "Moth"
    ],
    "name:pol_x_preferred":[
        "Moth"
    ],
    "name:por_x_preferred":[
        "Moth"
    ],
    "name:rus_x_preferred":[
        "\u041c\u043e\u0442\u0445"
    ],
    "name:spa_x_preferred":[
        "Moth"
    ],
    "name:swe_x_preferred":[
        "Moth"
    ],
    "name:tam_x_preferred":[
        "\u0bae\u0bca\u0ba4\u0bcd"
    ],
    "name:tel_x_preferred":[
        "\u0c2e\u0c3e\u0c24\u0c4d"
    ],
    "name:urd_x_preferred":[
        "\u0645\u0648\u0679\u06be\u060c \u0627\u062a\u0631\u067e\u0631\u062f\u06cc\u0634"
    ],
    "name:vie_x_preferred":[
        "Moth"
    ],
    "name:zho_x_preferred":[
        "\u83ab\u7279"
    ],
    "qs:name":"Moth",
    "qs:photos_9r":0,
    "qs:photos_sr":0,
    "qs:pop_sr":"6",
    "wd:wordcount":1789,
    "wof:name":"Moth",
    "wof:placetype":"locality",
    "wof:population":14077
},
  "geometry": {"coordinates":[78.94970000000001,25.72644],"type":"Point"}
}