{
  "type": "Feature",
  "properties": {
    "gn:admin1_code":"35.0",
    "gn:admin2_code":"447.0",
    "gn:asciiname":"Banga",
    "gn:country_code":"IN",
    "gn:dem":706,
    "gn:feature_class":"P",
    "gn:feature_code":"PPL",
    "gn:name":"B\u0101nga",
    "gn:population":0,
    "gn:timezone":"Asia/Kolkata",
    "iso:country":"IN",
    "wof:name":"Banga",
    "wof:placetype":"locality"
},
  "geometry": {"coordinates":[78.37285,21.92981],"type":"Point"}
}