{
  "type": "Feature",
  "properties": {
    "gn:admin1_code":"35.0",
    "gn:admin2_code":"447.0",
    "gn:asciiname":"Banga",
    "gn:country_code":"IN",
    "gn:dem":706,
    "gn:feature_class":"P",
    "gn:feature_code":"PPL",
    "gn:name":"B\u0101nga",
    "gn:population":0,
    "gn:timezone":"Asia/Kolkata",
    "iso:country":"IN",
    "name:ceb_x_preferred":[
        "Banga"
    ],
    "name:deu_x_preferred":[
        "Banga"
    ],
    "name:fra_x_preferred":[
        "Banga"
    ],
    "name:hin_x_preferred":[
        "\u092c\u0902\u0917\u093e"
    ],
    "name:ita_x_preferred":[
        "Banga"
    ],
    "name:lav_x_preferred":[
        "Banga"
    ],
    "name:lit_x_preferred":[
        "Banga"
    ],
    "name:nld_x_preferred":[
        "Banga"
    ],
    "name:por_x_preferred":[
        "Banga"
    ],
    "name:spa_x_preferred":[
        "Banga"
    ],
    "name:swe_x_preferred":[
        "Banga"
    ],
    "name:war_x_preferred":[
        "Banga"
    ],
    "wof:name":"Banga",
    "wof:placetype":"locality"
},
  "geometry": {"coordinates":[78.37285,21.92981],"type":"Point"}
}