{
  "type": "Feature",
  "properties": {
    "gn:admin1_code":"16.0",
    "gn:admin2_code":"497.0",
    "gn:asciiname":"Maloni",
    "gn:country_code":"IN",
    "gn:dem":143,
    "gn:feature_class":"P",
    "gn:feature_code":"PPL",
    "gn:name":"Maloni",
    "gn:population":0,
    "gn:timezone":"Asia/Kolkata",
    "iso:country":"IN",
    "ks:ks_name":"Maloni",
    "ks:ks_pop":904,
    "ks:ks_type":"VILLAGE",
    "ks:ks_uagg_main":0,
    "wof:name":"Maloni",
    "wof:placetype":"neighbourhood"
},
  "geometry": {"coordinates":[74.476,21.56159],"type":"Point"}
}