{
  "type": "Feature",
  "properties": {
    "iso:country":"IN",
    "ks:ks_name":"Pudukarattupatti",
    "ks:ks_pop":308,
    "ks:ks_type":"HABITATION",
    "name:eng_x_preferred":[
        "Pudukarattupatti"
    ],
    "wof:name":"Pudukarattupatti",
    "wof:placetype":"locality",
    "wof:population":308
},
  "geometry": {"coordinates":[78.06318400000001,10.48367],"type":"Point"}
}