{
  "type": "Feature",
  "properties": {
    "gn:admin1_code":"37",
    "gn:admin2_code":"405.0",
    "gn:asciiname":"Amoda",
    "gn:country_code":"IN",
    "gn:dem":217,
    "gn:feature_class":"P",
    "gn:feature_code":"PPL",
    "gn:name":"Amoda",
    "gn:population":0,
    "gn:timezone":"Asia/Kolkata",
    "iso:country":"IN",
    "name:fas_x_preferred":[
        "\u0627\u0645\u0648\u062f\u0627"
    ],
    "wof:name":"Amoda",
    "wof:placetype":"locality"
},
  "geometry": {"coordinates":[82.93709,21.73745],"type":"Point"}
}