{
  "type": "Feature",
  "properties": {
    "gn:admin1_code":"19.0",
    "gn:admin2_code":"570.0",
    "gn:asciiname":"Kanangi",
    "gn:country_code":"IN",
    "gn:dem":652,
    "gn:feature_class":"P",
    "gn:feature_code":"PPL",
    "gn:name":"Kanangi",
    "gn:population":0,
    "gn:timezone":"Asia/Kolkata",
    "iso:country":"IN",
    "wof:name":"Kanangi",
    "wof:placetype":"locality"
},
  "geometry": {"coordinates":[75.20701,13.47143],"type":"Point"}
}