{
  "type": "Feature",
  "properties": {
    "iso:country":"IN",
    "ks:ks_alt_nam":"R\u0101ipurwa",
    "ks:ks_name":"Raipurwa",
    "ks:ks_pop":0,
    "ks:ks_type":"VILLAGE",
    "name:eng_x_preferred":[
        "Raipurwa"
    ],
    "name:eng_x_variant":[
        "R\u0101ipurwa"
    ],
    "wof:name":"Raipurwa",
    "wof:placetype":"locality",
    "wof:population":0
},
  "geometry": {"coordinates":[83.541326,24.676514],"type":"Point"}
}