{
  "type": "Feature",
  "properties": {
    "iso:country":"IN",
    "ks:ks_alt_nam":"Tirl\u0101",
    "ks:ks_name":"Tirla",
    "ks:ks_pop":1152,
    "ks:ks_type":"VILLAGE",
    "ks:ks_uagg_main":0,
    "name:eng_x_preferred":[
        "Tirla"
    ],
    "name:eng_x_variant":[
        "Tirl\u0101"
    ],
    "wof:name":"Tirla",
    "wof:placetype":"locality",
    "wof:population":1152
},
  "geometry": {"coordinates":[85.300633,23.058313],"type":"Point"}
}