{
  "type": "Feature",
  "properties": {
    "gn:admin1_code":"13.0",
    "gn:admin2_code":"592.0",
    "gn:asciiname":"Tiruvali",
    "gn:country_code":"IN",
    "gn:dem":47,
    "gn:feature_class":"P",
    "gn:feature_code":"PPL",
    "gn:name":"Tiruv\u0101li",
    "gn:population":0,
    "gn:timezone":"Asia/Kolkata",
    "iso:country":"IN",
    "wof:name":"Tiruvali",
    "wof:placetype":"locality"
},
  "geometry": {"coordinates":[76.17260999999998,11.20051],"type":"Point"}
}