{
  "type": "Feature",
  "properties": {
    "iso:country":"IN",
    "ks:ks_name":"Gunturpalli",
    "ks:ks_pop":1421,
    "ks:ks_type":"HABITATION",
    "name:eng_x_preferred":[
        "Gunturpalli"
    ],
    "wof:name":"Gunturpalli",
    "wof:placetype":"locality",
    "wof:population":1421
},
  "geometry": {"coordinates":[79.02166,18.306611],"type":"Point"}
}