{
  "type": "Feature",
  "properties": {
    "iso:country":"IN",
    "ks:ks_name":"Galphulli",
    "ks:ks_pop":13,
    "ks:ks_type":"HABITATION",
    "name:eng_x_preferred":[
        "Galphulli"
    ],
    "wof:name":"Galphulli",
    "wof:placetype":"locality",
    "wof:population":13
},
  "geometry": {"coordinates":[87.745704,24.680803],"type":"Point"}
}