{
  "type": "Feature",
  "properties": {
    "gn:admin1_code":"36",
    "gn:admin2_code":"199.0",
    "gn:asciiname":"Dadri Khurd",
    "gn:country_code":"IN",
    "gn:dem":177,
    "gn:feature_class":"P",
    "gn:feature_code":"PPL",
    "gn:name":"Dadri Khurd",
    "gn:population":0,
    "gn:timezone":"Asia/Kolkata",
    "iso:country":"IN",
    "ks:ks_name":"Dadri Khurd",
    "ks:ks_type":"VILLAGE",
    "name:eng_x_preferred":[
        "Dadri Khurd"
    ],
    "wof:name":"Dadri Khurd",
    "wof:placetype":"locality"
},
  "geometry": {"coordinates":[82.671121,24.992697],"type":"Point"}
}