{
  "type": "Feature",
  "properties": {
    "gn:admin1_code":"25.0",
    "gn:admin2_code":"610.0",
    "gn:asciiname":"Mettur",
    "gn:country_code":"IN",
    "gn:dem":202,
    "gn:feature_class":"P",
    "gn:feature_code":"PPL",
    "gn:name":"Mett\u016br",
    "gn:population":0,
    "gn:timezone":"Asia/Kolkata",
    "iso:country":"IN",
    "name:bpy_x_preferred":[
        "\u09ae\u09c7\u09a4\u09cd\u09a4\u09c1\u09b0"
    ],
    "name:ceb_x_preferred":[
        "Mettur"
    ],
    "name:ita_x_preferred":[
        "Mettur"
    ],
    "name:mlg_x_preferred":[
        "Mettur"
    ],
    "name:msa_x_preferred":[
        "Mettur"
    ],
    "name:new_x_preferred":[
        "\u092e\u0947\u0924\u094d\u0924\u0941\u0930"
    ],
    "name:swe_x_preferred":[
        "Mettur"
    ],
    "name:tam_x_preferred":[
        "\u0bae\u0bc7\u0b9f\u0bcd\u0b9f\u0bc2\u0bb0\u0bcd"
    ],
    "name:vie_x_preferred":[
        "Mettur"
    ],
    "name:zho_x_preferred":[
        "\u6885\u56fe\u5c14"
    ],
    "wof:name":"Mettur",
    "wof:placetype":"neighbourhood"
},
  "geometry": {"coordinates":[77.7106,11.58698],"type":"Point"}
}