{
  "type": "Feature",
  "properties": {
    "iso:country":"IN",
    "ks:ks_name":"Gaura",
    "ks:ks_pop":800,
    "ks:ks_type":"VILLAGE",
    "ks:ks_uagg_main":0,
    "name:eng_x_preferred":[
        "Gaura"
    ],
    "wof:name":"Gaura",
    "wof:placetype":"neighbourhood",
    "wof:population":800
},
  "geometry": {"coordinates":[80.549402,27.558711],"type":"Point"}
}