{
  "type": "Feature",
  "properties": {
    "gn:admin1_code":"35.0",
    "gn:admin2_code":"456.0",
    "gn:asciiname":"Bakhari",
    "gn:country_code":"IN",
    "gn:dem":414,
    "gn:feature_class":"P",
    "gn:feature_code":"PPL",
    "gn:name":"Bakh\u0101ri",
    "gn:population":0,
    "gn:timezone":"Asia/Kolkata",
    "iso:country":"IN",
    "name:che_x_preferred":[
        "\u0411\u0430\u0445\u0430\u0440\u0438"
    ],
    "name:rus_x_preferred":[
        "\u0411\u0430\u0445\u0430\u0440\u0438"
    ],
    "wof:name":"Bakhari",
    "wof:placetype":"locality"
},
  "geometry": {"coordinates":[80.14718000000001,22.76148],"type":"Point"}
}