{
  "type": "Feature",
  "properties": {
    "iso:country":"IN",
    "ks:ks_alt_nam":"Dhobi tola",
    "ks:ks_name":"Dhobi Tola",
    "ks:ks_pop":292,
    "ks:ks_type":"HABITATION",
    "name:eng_x_preferred":[
        "Dhobi Tola"
    ],
    "wof:name":"Dhobi Tola",
    "wof:placetype":"locality",
    "wof:population":292
},
  "geometry": {"coordinates":[84.77121,26.511388],"type":"Point"}
}