{
  "type": "Feature",
  "properties": {
    "iso:country":"IN",
    "ks:ks_name":"Ramanagaram",
    "ks:ks_pop":265,
    "ks:ks_type":"HABITATION",
    "name:eng_x_preferred":[
        "Ramanagaram"
    ],
    "name:hin_x_preferred":[
        "\u0930\u093e\u092e\u0928\u0917\u0930\u092e"
    ],
    "name:kan_x_preferred":[
        "\u0cb0\u0cbe\u0cae\u0ca8\u0c97\u0cb0"
    ],
    "wof:name":"Ramanagaram",
    "wof:placetype":"locality",
    "wof:population":265
},
  "geometry": {"coordinates":[83.775761,18.74587],"type":"Point"}
}