{
  "type": "Feature",
  "properties": {
    "gn:admin1_code":"16.0",
    "gn:admin2_code":"497.0",
    "gn:asciiname":"Veri",
    "gn:country_code":"IN",
    "gn:dem":431,
    "gn:feature_class":"P",
    "gn:feature_code":"PPL",
    "gn:name":"Veri",
    "gn:population":0,
    "gn:timezone":"Asia/Kolkata",
    "iso:country":"IN",
    "name:azb_x_preferred":[
        "\u0648\u0626\u0631\u06cc"
    ],
    "name:aze_x_preferred":[
        "Veri"
    ],
    "name:ceb_x_preferred":[
        "Veri"
    ],
    "name:ita_x_preferred":[
        "Veri"
    ],
    "name:msa_x_preferred":[
        "Veri"
    ],
    "name:swe_x_preferred":[
        "Veri"
    ],
    "wof:name":"Veri",
    "wof:placetype":"locality"
},
  "geometry": {"coordinates":[74.06619000000001,21.81853],"type":"Point"}
}