{
  "type": "Feature",
  "properties": {
    "gn:admin1_code":"16.0",
    "gn:admin2_code":"497.0",
    "gn:asciiname":"Veri",
    "gn:country_code":"IN",
    "gn:dem":431,
    "gn:feature_class":"P",
    "gn:feature_code":"PPL",
    "gn:name":"Veri",
    "gn:population":0,
    "gn:timezone":"Asia/Kolkata",
    "iso:country":"IN",
    "ks:ks_name":"Veri",
    "ks:ks_pop":1311,
    "ks:ks_type":"VILLAGE",
    "name:azb_x_preferred":[
        "\u0648\u0626\u0631\u06cc"
    ],
    "name:aze_x_preferred":[
        "Veri"
    ],
    "name:ceb_x_preferred":[
        "Veri"
    ],
    "name:eng_x_preferred":[
        "Veri"
    ],
    "name:ita_x_preferred":[
        "Veri"
    ],
    "name:msa_x_preferred":[
        "Veri"
    ],
    "name:swe_x_preferred":[
        "Veri"
    ],
    "wof:name":"Veri",
    "wof:placetype":"locality",
    "wof:population":1311
},
  "geometry": {"coordinates":[74.064571,21.808812],"type":"Point"}
}