{
  "type": "Feature",
  "properties": {
    "gn:admin1_code":"12",
    "gn:asciiname":"Pringa",
    "gn:country_code":"IN",
    "gn:dem":1548,
    "gn:feature_class":"P",
    "gn:feature_code":"PPL",
    "gn:name":"Pringa",
    "gn:population":0,
    "gn:timezone":"Asia/Kolkata",
    "iso:country":"IN",
    "wof:name":"Pringa",
    "wof:placetype":"locality"
},
  "geometry": {"coordinates":[74.18817,34.15069],"type":"Point"}
}