{
  "type": "Feature",
  "properties": {
    "iso:country":"IN",
    "ks:ks_name":"Bhagavathi Temple",
    "ks:ks_pop":62,
    "ks:ks_type":"HABITATION",
    "name:eng_x_preferred":[
        "Bhagavathi Temple"
    ],
    "wof:name":"Bhagavathi Temple",
    "wof:placetype":"locality",
    "wof:population":62
},
  "geometry": {"coordinates":[75.720556,12.1975],"type":"Point"}
}