{
  "type": "Feature",
  "properties": {
    "gn:country":"IN",
    "gn:fcode":"PPLX",
    "gn:pop":0,
    "iso:country":"IN",
    "qs:name":"Abhiramapuram",
    "qs:name_adm0":"India",
    "qs:name_adm1":"Tamil Nadu",
    "qs:photos":136,
    "qs:photos_1k":28,
    "qs:photos_9k":1,
    "qs:photos_9r":3,
    "qs:photos_all":136,
    "qs:photos_sr":3,
    "qs:placetype":"Suburb",
    "qs:pop_sr":"0",
    "wof:name":"Abhiramapuram",
    "wof:placetype":"neighbourhood",
    "wof:population":0
},
  "geometry": {"coordinates":[80.25749999999999,13.02778],"type":"Point"}
}