{
  "type": "Feature",
  "properties": {
    "iso:country":"IN",
    "ks:ks_name":"Sherpur",
    "ks:ks_pop":0,
    "ks:ks_type":"VILLAGE",
    "name:eng_x_preferred":[
        "Sherpur"
    ],
    "wof:name":"Sherpur",
    "wof:placetype":"locality",
    "wof:population":0
},
  "geometry": {"coordinates":[86.365892,25.395213],"type":"Point"}
}