{
  "type": "Feature",
  "properties": {
    "gn:admin1_code":"25.0",
    "gn:admin2_code":"606.0",
    "gn:asciiname":"Kilpuduppakkam",
    "gn:country_code":"IN",
    "gn:dem":106,
    "gn:feature_class":"P",
    "gn:feature_code":"PPL",
    "gn:name":"K\u012blpudupp\u0101kkam",
    "gn:population":0,
    "gn:timezone":"Asia/Kolkata",
    "iso:country":"IN",
    "ks:ks_name":"Kilpudupakkam",
    "ks:ks_pop":2228,
    "ks:ks_type":"URBAN",
    "ks:ks_uagg_main":0,
    "name:eng_x_preferred":[
        "Kilpudupakkam"
    ],
    "wof:name":"Kilpudupakkam",
    "wof:placetype":"neighbourhood",
    "wof:population":2228
},
  "geometry": {"coordinates":[79.540887,12.678551],"type":"Point"}
}