{
  "type": "Feature",
  "properties": {
    "gn:admin1_code":"11",
    "gn:admin2_code":"31.0",
    "gn:asciiname":"Punaihli",
    "gn:country_code":"IN",
    "gn:dem":670,
    "gn:feature_class":"P",
    "gn:feature_code":"PPL",
    "gn:name":"Punaihli",
    "gn:population":0,
    "gn:timezone":"Asia/Kolkata",
    "iso:country":"IN",
    "wof:name":"Punaihli",
    "wof:placetype":"locality"
},
  "geometry": {"coordinates":[76.68651,31.20789000000001],"type":"Point"}
}