{
  "type": "Feature",
  "properties": {
    "gn:admin1_code":"35",
    "gn:admin2_code":"455.0",
    "gn:asciiname":"Moghar",
    "gn:country_code":"IN",
    "gn:dem":588,
    "gn:feature_class":"P",
    "gn:feature_code":"PPL",
    "gn:name":"Moghar",
    "gn:population":0,
    "gn:timezone":"Asia/Kolkata",
    "iso:country":"IN",
    "name:ara_x_preferred":[
        "\u0645\u063a\u0627\u0631"
    ],
    "name:ceb_x_preferred":[
        "Mogh\u0101r"
    ],
    "name:fas_x_preferred":[
        "\u0645\u063a\u0627\u0631"
    ],
    "name:msa_x_preferred":[
        "Moghar"
    ],
    "name:swe_x_preferred":[
        "Mogh\u0101r"
    ],
    "wof:name":"Moghar",
    "wof:placetype":"locality"
},
  "geometry": {"coordinates":[79.13051999999998,21.91961],"type":"Point"}
}