{
  "type": "Feature",
  "properties": {
    "iso:country":"IN",
    "ks:ks_name":"Palayampatti",
    "ks:ks_pop":14017,
    "ks:ks_type":"URBAN",
    "ks:ks_uagg_main":0,
    "name:eng_x_preferred":[
        "Palayampatti"
    ],
    "wof:name":"Palayampatti",
    "wof:placetype":"locality",
    "wof:population":14017
},
  "geometry": {"coordinates":[78.099475,9.529688],"type":"Point"}
}