{
  "type": "Feature",
  "properties": {
    "iso:country":"IN",
    "ks:ks_name":"Kaurwadi",
    "ks:ks_pop":423,
    "ks:ks_type":"HABITATION",
    "name:eng_x_preferred":[
        "Kaurwadi"
    ],
    "wof:name":"Kaurwadi",
    "wof:placetype":"locality",
    "wof:population":423
},
  "geometry": {"coordinates":[73.955268,16.737875],"type":"Point"}
}