{
  "type": "Feature",
  "properties": {
    "iso:country":"IN",
    "ks:ks_name":"Ranigadia",
    "ks:ks_pop":68,
    "ks:ks_type":"VILLAGE",
    "name:eng_x_preferred":[
        "Ranigadia"
    ],
    "wof:name":"Ranigadia",
    "wof:placetype":"locality",
    "wof:population":68
},
  "geometry": {"coordinates":[84.95046499999999,20.137788],"type":"Point"}
}