{
  "type": "Feature",
  "properties": {
    "iso:country":"IN",
    "ks:ks_name":"Kodambi",
    "ks:ks_pop":1133,
    "ks:ks_type":"VILLAGE",
    "name:eng_x_preferred":[
        "Kodambi"
    ],
    "wof:name":"Kodambi",
    "wof:placetype":"locality",
    "wof:population":1133
},
  "geometry": {"coordinates":[75.005684,14.793508],"type":"Point"}
}