{
  "type": "Feature",
  "properties": {
    "iso:country":"IN",
    "ks:ks_name":"Kadalibari",
    "ks:ks_pop":261,
    "ks:ks_type":"VILLAGE",
    "name:eng_x_preferred":[
        "Kadalibari"
    ],
    "wof:name":"Kadalibari",
    "wof:placetype":"locality",
    "wof:population":261
},
  "geometry": {"coordinates":[85.310344,21.359239],"type":"Point"}
}