{
  "type": "Feature",
  "properties": {
    "iso:country":"IN",
    "ks:ks_name":"Hadiya Gaon",
    "ks:ks_pop":100,
    "ks:ks_type":"VILLAGE",
    "name:eng_x_preferred":[
        "Hadiya Gaon"
    ],
    "wof:name":"Hadiya Gaon",
    "wof:placetype":"locality",
    "wof:population":100
},
  "geometry": {"coordinates":[78.047623,30.588488],"type":"Point"}
}