{
  "type": "Feature",
  "properties": {
    "gn:admin1_code":"36",
    "gn:admin2_code":"140.0",
    "gn:asciiname":"Kothla",
    "gn:country_code":"IN",
    "gn:dem":202,
    "gn:feature_class":"P",
    "gn:feature_code":"PPL",
    "gn:name":"Kothla",
    "gn:population":0,
    "gn:timezone":"Asia/Kolkata",
    "iso:country":"IN",
    "wof:name":"Kothla",
    "wof:placetype":"locality"
},
  "geometry": {"coordinates":[78.09336999999999,28.82502],"type":"Point"}
}