{
  "type": "Feature",
  "properties": {
    "iso:country":"IN",
    "ks:ks_name":"Pobhara",
    "ks:ks_pop":250,
    "ks:ks_type":"HABITATION",
    "name:eng_x_preferred":[
        "Pobhara"
    ],
    "wof:name":"Pobhara",
    "wof:placetype":"locality",
    "wof:population":250
},
  "geometry": {"coordinates":[82.08112199999999,27.218856],"type":"Point"}
}