{
  "type": "Feature",
  "properties": {
    "iso:country":"IN",
    "ks:ks_alt_nam":"DHANIAMARA",
    "ks:ks_name":"Dhaniamara",
    "ks:ks_pop":278,
    "ks:ks_type":"HABITATION",
    "name:eng_x_preferred":[
        "Dhaniamara"
    ],
    "wof:name":"Dhaniamara",
    "wof:placetype":"locality",
    "wof:population":278
},
  "geometry": {"coordinates":[87.717534,24.578586],"type":"Point"}
}