{
  "type": "Feature",
  "properties": {
    "gn:admin1_code":"36",
    "gn:admin2_code":"178.0",
    "gn:asciiname":"Dewapur",
    "gn:country_code":"IN",
    "gn:dem":89,
    "gn:feature_class":"P",
    "gn:feature_code":"PPL",
    "gn:name":"Dew\u0101pur",
    "gn:population":0,
    "gn:timezone":"Asia/Kolkata",
    "iso:country":"IN",
    "ks:ks_name":"Dewa Pur",
    "ks:ks_pop":124,
    "ks:ks_type":"VILLAGE",
    "ks:ks_uagg_main":0,
    "name:ceb_x_preferred":[
        "Dewapur"
    ],
    "name:eng_x_preferred":[
        "Dewa Pur"
    ],
    "name:fra_x_preferred":[
        "Dewapur"
    ],
    "name:mai_x_preferred":[
        "\u0926\u0947\u0935\u093e\u092a\u0941\u0930"
    ],
    "name:msa_x_preferred":[
        "Dewapur"
    ],
    "name:nep_x_preferred":[
        "\u0926\u0947\u0935\u093e\u092a\u0941\u0930"
    ],
    "name:new_x_preferred":[
        "\u0926\u0947\u0935\u093e\u092a\u0941\u0930"
    ],
    "name:pol_x_preferred":[
        "Dewapur"
    ],
    "wof:name":"Dewa Pur",
    "wof:placetype":"neighbourhood",
    "wof:population":124
},
  "geometry": {"coordinates":[82.96154300000001,26.386801],"type":"Point"}
}