{
  "type": "Feature",
  "properties": {
    "gn:admin1_code":"2",
    "gn:admin2_code":"545.0",
    "gn:asciiname":"Sarabhavaram",
    "gn:country_code":"IN",
    "gn:dem":246,
    "gn:feature_class":"P",
    "gn:feature_code":"PPL",
    "gn:name":"Sarabhavaram",
    "gn:population":0,
    "gn:timezone":"Asia/Kolkata",
    "iso:country":"IN",
    "ks:ks_name":"Sarabhavaram",
    "ks:ks_pop":711,
    "ks:ks_type":"VILLAGE",
    "name:eng_x_preferred":[
        "Sarabhavaram"
    ],
    "wof:name":"Sarabhavaram",
    "wof:placetype":"locality",
    "wof:population":711
},
  "geometry": {"coordinates":[82.242684,17.610878],"type":"Point"}
}