{
  "type": "Feature",
  "properties": {
    "gn:admin1_code":"35",
    "gn:admin2_code":"461.0",
    "gn:asciiname":"Sarsatola",
    "gn:country_code":"IN",
    "gn:dem":789,
    "gn:feature_class":"P",
    "gn:feature_code":"PPL",
    "gn:name":"Sars\u0101tola",
    "gn:population":0,
    "gn:timezone":"Asia/Kolkata",
    "iso:country":"IN",
    "wof:name":"Sarsatola",
    "wof:placetype":"locality"
},
  "geometry": {"coordinates":[81.4768,22.80464],"type":"Point"}
}