{
  "type": "Feature",
  "properties": {
    "gn:admin1_code":"36.0",
    "gn:admin2_code":"192.0",
    "gn:asciiname":"Mayari Kalianpur",
    "gn:country_code":"IN",
    "gn:dem":77,
    "gn:feature_class":"P",
    "gn:feature_code":"PPL",
    "gn:name":"May\u0101ri Kali\u0101npur",
    "gn:population":0,
    "gn:timezone":"Asia/Kolkata",
    "iso:country":"IN",
    "ks:ks_name":"Mayari Kalyanpur",
    "ks:ks_pop":499,
    "ks:ks_type":"VILLAGE",
    "ks:ks_uagg_main":0,
    "name:eng_x_preferred":[
        "Mayari Kalyanpur"
    ],
    "wof:name":"Mayari Kalyanpur",
    "wof:placetype":"neighbourhood",
    "wof:population":499
},
  "geometry": {"coordinates":[83.724812,26.121786],"type":"Point"}
}