{
  "type": "Feature",
  "properties": {
    "iso:country":"IN",
    "ks:ks_name":"Bopanda",
    "ks:ks_pop":29,
    "ks:ks_type":"HABITATION",
    "name:eng_x_preferred":[
        "Bopanda"
    ],
    "wof:name":"Bopanda",
    "wof:placetype":"locality",
    "wof:population":29
},
  "geometry": {"coordinates":[75.6575,12.311389],"type":"Point"}
}