{
  "type": "Feature",
  "properties": {
    "gn:admin1_code":"2.0",
    "gn:admin2_code":"554.0",
    "gn:asciiname":"Gollakhandriga",
    "gn:country_code":"IN",
    "gn:dem":202,
    "gn:feature_class":"P",
    "gn:feature_code":"PPL",
    "gn:name":"Gollakhandriga",
    "gn:population":0,
    "gn:timezone":"Asia/Kolkata",
    "iso:country":"IN",
    "ks:ks_name":"Golla Kandriga",
    "ks:ks_pop":326,
    "ks:ks_type":"HABITATION",
    "name:eng_x_preferred":[
        "Golla Kandriga"
    ],
    "name:eng_x_variant":[
        "Gollakhandriga"
    ],
    "wof:name":"Golla Kandriga",
    "wof:placetype":"locality",
    "wof:population":326
},
  "geometry": {"coordinates":[79.49467,13.409884],"type":"Point"}
}