{
  "type": "Feature",
  "properties": {
    "iso:country":"IN",
    "ks:ks_name":"Borpiwad",
    "ks:ks_pop":228,
    "ks:ks_type":"HABITATION",
    "name:eng_x_preferred":[
        "Borpiwad"
    ],
    "wof:name":"Borpiwad",
    "wof:placetype":"locality",
    "wof:population":228
},
  "geometry": {"coordinates":[73.07474999999999,20.422111],"type":"Point"}
}