{
  "type": "Feature",
  "properties": {
    "iso:country":"IN",
    "ks:ks_name":"Masapadar",
    "ks:ks_pop":260,
    "ks:ks_type":"VILLAGE",
    "name:eng_x_preferred":[
        "Masapadar"
    ],
    "wof:name":"Masapadar",
    "wof:placetype":"locality",
    "wof:population":260
},
  "geometry": {"coordinates":[84.23269999999999,20.359962],"type":"Point"}
}