{
  "type": "Feature",
  "properties": {
    "iso:country":"IN",
    "ks:ks_name":"Ghaniamara",
    "ks:ks_pop":6489,
    "ks:ks_type":"VILLAGE",
    "ks:ks_uagg_main":0,
    "name:eng_x_preferred":[
        "Ghaniamara"
    ],
    "wof:name":"Ghaniamara",
    "wof:placetype":"neighbourhood",
    "wof:population":6489
},
  "geometry": {"coordinates":[91.252871,23.682635],"type":"Point"}
}