{
  "type": "Feature",
  "properties": {
    "gn:admin1_code":"16",
    "gn:admin2_code":"524.0",
    "gn:asciiname":"Laman Tanda",
    "gn:country_code":"IN",
    "gn:dem":634,
    "gn:feature_class":"P",
    "gn:feature_code":"PPL",
    "gn:name":"Lam\u0101n T\u0101nda",
    "gn:population":0,
    "gn:timezone":"Asia/Kolkata",
    "iso:country":"IN",
    "wof:name":"Laman Tanda",
    "wof:placetype":"locality"
},
  "geometry": {"coordinates":[76.7803,18.43854],"type":"Point"}
}