{
  "type": "Feature",
  "properties": {
    "gn:admin1_code":"2.0",
    "gn:admin2_code":"550.0",
    "gn:asciiname":"Ragimanidinne",
    "gn:country_code":"IN",
    "gn:dem":258,
    "gn:feature_class":"P",
    "gn:feature_code":"PPL",
    "gn:name":"R\u0101gim\u0101nidinne",
    "gn:population":0,
    "gn:timezone":"Asia/Kolkata",
    "iso:country":"IN",
    "ks:ks_name":"Ravimanudinne",
    "ks:ks_pop":151,
    "ks:ks_type":"HABITATION",
    "name:eng_x_preferred":[
        "Ravimanudinne"
    ],
    "name:eng_x_variant":[
        "Ragimanidinne"
    ],
    "wof:name":"Ravimanudinne",
    "wof:placetype":"locality",
    "wof:population":151
},
  "geometry": {"coordinates":[79.160821,14.939826],"type":"Point"}
}