{
  "type": "Feature",
  "properties": {
    "iso:country":"IN",
    "ks:ks_name":"Bachappu",
    "ks:ks_pop":105,
    "ks:ks_type":"HABITATION",
    "name:eng_x_preferred":[
        "Bachappu"
    ],
    "wof:name":"Bachappu",
    "wof:placetype":"locality",
    "wof:population":105
},
  "geometry": {"coordinates":[75.018759,13.442239],"type":"Point"}
}