{
  "type": "Feature",
  "properties": {
    "iso:country":"IN",
    "ks:ks_alt_nam":"Odaiy\u016br",
    "ks:ks_name":"Odaiyur",
    "ks:ks_pop":732,
    "ks:ks_type":"VILLAGE",
    "ks:ks_uagg_main":0,
    "name:eng_x_preferred":[
        "Odaiyur"
    ],
    "name:eng_x_variant":[
        "Odaiy\u016br"
    ],
    "wof:name":"Odaiyur",
    "wof:placetype":"neighbourhood",
    "wof:population":732
},
  "geometry": {"coordinates":[79.594493,11.250617],"type":"Point"}
}