{
  "type": "Feature",
  "properties": {
    "gn:admin1_code":"25.0",
    "gn:admin2_code":"611.0",
    "gn:asciiname":"Manjoor",
    "gn:country_code":"IN",
    "gn:dem":1845,
    "gn:feature_class":"P",
    "gn:feature_code":"PPL",
    "gn:name":"Manjoor",
    "gn:population":0,
    "gn:timezone":"Asia/Kolkata",
    "iso:country":"IN",
    "wof:name":"Manjoor",
    "wof:placetype":"neighbourhood"
},
  "geometry": {"coordinates":[76.64286,11.27109],"type":"Point"}
}