{
  "type": "Feature",
  "properties": {
    "iso:country":"IN",
    "ks:ks_alt_nam":"GODAM TOL",
    "ks:ks_name":"Godam Tol",
    "ks:ks_pop":341,
    "ks:ks_type":"HABITATION",
    "name:eng_x_preferred":[
        "Godam Tol"
    ],
    "wof:name":"Godam Tol",
    "wof:placetype":"locality",
    "wof:population":341
},
  "geometry": {"coordinates":[86.361226,26.153736],"type":"Point"}
}