{
  "type": "Feature",
  "properties": {
    "gn:admin1_code":"36.0",
    "gn:admin2_code":"151.0",
    "gn:asciiname":"Almanpur",
    "gn:country_code":"IN",
    "gn:dem":199,
    "gn:feature_class":"P",
    "gn:feature_code":"PPL",
    "gn:name":"Alm\u0101npur",
    "gn:population":0,
    "gn:timezone":"Asia/Kolkata",
    "iso:country":"IN",
    "name:und_x_variant":[
        "Alm\u0101npur",
        "\u0100lampur"
    ],
    "wof:name":"Almanpur",
    "wof:placetype":"locality"
},
  "geometry": {"coordinates":[79.86733000000002,28.7766],"type":"Point"}
}