{
  "type": "Feature",
  "properties": {
    "iso:country":"IN",
    "name:ben_x_preferred":[
        "\u09a6\u09b8\u09b0\u09be\u09b9\u09be\u09b2\u09cd\u09b2\u09bf"
    ],
    "name:bpy_x_preferred":[
        "\u09a6\u09b8\u09b0\u09be\u09b9\u09be\u09b2\u09cd\u09b2\u09bf"
    ],
    "name:eng_x_preferred":[
        "T Dasarahalli"
    ],
    "name:fas_x_preferred":[
        "\u062f\u0627\u0633\u0627\u0631\u0627\u0647\u0627\u0644\u06cc"
    ],
    "name:ita_x_preferred":[
        "Dasarahalli"
    ],
    "name:mlg_x_preferred":[
        "Dasarahalli"
    ],
    "name:msa_x_preferred":[
        "Dasarahalli"
    ],
    "name:new_x_preferred":[
        "\u0926\u0938\u0930\u0939\u0932\u094d\u0932\u0940"
    ],
    "name:nld_x_preferred":[
        "Dasarahalli"
    ],
    "name:nor_x_preferred":[
        "Dasarahalli"
    ],
    "name:por_x_preferred":[
        "Dasarahalli"
    ],
    "name:spa_x_preferred":[
        "Dasarahalli"
    ],
    "name:tam_x_preferred":[
        "\u0ba4\u0b9a\u0bb0\u0bbe\u0bb3\u0bbf"
    ],
    "name:unk_x_variant":[
        "T Dasarahalli"
    ],
    "name:vie_x_preferred":[
        "Dasarahalli"
    ],
    "name:zho_min_nan_x_preferred":[
        "Dasarahalli"
    ],
    "name:zho_x_preferred":[
        "\u8fbe\u8428\u62c9\u54c8\u5c14\u5229"
    ],
    "qs:gn_adm0_cc":"IN",
    "qs:gn_local":1277333,
    "qs:gn_nam_loc":"Bangalore, Bangalore, Karnataka, IN",
    "qs:gn_namadm1":"19",
    "qs:local_max":7342,
    "qs:local_sum":38996,
    "qs:localhoods":89,
    "qs:name":"T Dasarahalli",
    "qs:name_adm0":"India",
    "qs:name_adm1":"Karnataka",
    "qs:name_adm2":"Bangalore",
    "qs:name_local":"Bangalore",
    "qs:photo_max":9,
    "qs:photo_sum":16,
    "qs:placetype":"Suburb",
    "qs:quad_count":7,
    "qs:woe_adm0":23424848,
    "qs:woe_adm1":2345753,
    "qs:woe_adm2":12586572,
    "qs:woe_lau":0,
    "qs:woe_local":2295420,
    "qs:woe_ver":"7.10.0",
    "wd:wordcount":209,
    "wof:lang":[
        "eng"
    ],
    "wof:name":"T Dasarahalli",
    "wof:placetype":"neighbourhood"
},
  "geometry": {"coordinates":[77.509232,13.054061],"type":"Point"}
}