{
  "type": "Feature",
  "properties": {
    "iso:country":"IN",
    "ks:ks_alt_nam":"Kiri Rongphar gaon",
    "ks:ks_name":"Kiri Rongphar Gaon",
    "ks:ks_pop":117,
    "ks:ks_type":"HABITATION",
    "ks:ks_uagg_main":0,
    "name:eng_x_preferred":[
        "Kiri Rongphar Gaon"
    ],
    "wof:name":"Kiri Rongphar Gaon",
    "wof:placetype":"neighbourhood",
    "wof:population":117
},
  "geometry": {"coordinates":[92.78855799999999,25.907539],"type":"Point"}
}