{
  "type": "Feature",
  "properties": {
    "gn:admin1_code":"35",
    "gn:admin2_code":"435.0",
    "gn:asciiname":"Piploda",
    "gn:country_code":"IN",
    "gn:dem":504,
    "gn:feature_class":"P",
    "gn:feature_code":"PPL",
    "gn:name":"Piploda",
    "gn:population":0,
    "gn:timezone":"Asia/Kolkata",
    "iso:country":"IN",
    "name:und_x_variant":[
        "Sunder\u0101b\u0101d"
    ],
    "wof:name":"Piploda",
    "wof:placetype":"locality"
},
  "geometry": {"coordinates":[75.31538,23.13696],"type":"Point"}
}