{
  "type": "Feature",
  "properties": {
    "iso:country":"IN",
    "ks:ks_name":"Dharni Hata",
    "ks:ks_pop":1096,
    "ks:ks_type":"VILLAGE",
    "ks:ks_uagg_main":0,
    "name:eng_x_preferred":[
        "Dharni Hata"
    ],
    "wof:name":"Dharni Hata",
    "wof:placetype":"neighbourhood",
    "wof:population":1096
},
  "geometry": {"coordinates":[84.31539100000001,26.393712],"type":"Point"}
}