{
  "type": "Feature",
  "properties": {
    "gn:admin1_code":"40.0",
    "gn:admin2_code":"534.0",
    "gn:asciiname":"Madaram",
    "gn:country_code":"IN",
    "gn:dem":128,
    "gn:feature_class":"P",
    "gn:feature_code":"PPL",
    "gn:name":"Mad\u0101ram",
    "gn:population":0,
    "gn:timezone":"Asia/Kolkata",
    "iso:country":"IN",
    "name:bpy_x_preferred":[
        "\u09ae\u09a6\u09b0\u09ae"
    ],
    "name:ind_x_preferred":[
        "Madaram"
    ],
    "name:ita_x_preferred":[
        "Madaram"
    ],
    "name:msa_x_preferred":[
        "Madaram"
    ],
    "name:new_x_preferred":[
        "\u092e\u0926\u0930\u093e\u092e"
    ],
    "name:nld_x_preferred":[
        "Madaram"
    ],
    "name:por_x_preferred":[
        "Madaram"
    ],
    "name:spa_x_preferred":[
        "Madaram"
    ],
    "name:urd_x_preferred":[
        "\u0645\u06cc\u0688\u0627\u0631\u0627\u0645"
    ],
    "name:vie_x_preferred":[
        "Madaram"
    ],
    "name:zho_x_preferred":[
        "\u9a6c\u8fbe\u62c9\u59c6"
    ],
    "wof:name":"Madaram",
    "wof:placetype":"locality"
},
  "geometry": {"coordinates":[79.84733,18.70661],"type":"Point"}
}