{
  "type": "Feature",
  "properties": {
    "iso:country":"IN",
    "ks:ks_name":"Vilasa Gangavaram",
    "ks:ks_pop":232,
    "ks:ks_type":"HABITATION",
    "name:eng_x_preferred":[
        "Vilasa Gangavaram"
    ],
    "wof:name":"Vilasa Gangavaram",
    "wof:placetype":"locality",
    "wof:population":232
},
  "geometry": {"coordinates":[82.096845,16.783838],"type":"Point"}
}