{
  "type": "Feature",
  "properties": {
    "iso:country":"IN",
    "ks:ks_name":"Gojegaon",
    "ks:ks_pop":100,
    "ks:ks_type":"HABITATION",
    "name:eng_x_preferred":[
        "Gojegaon"
    ],
    "wof:name":"Gojegaon",
    "wof:placetype":"locality",
    "wof:population":100
},
  "geometry": {"coordinates":[73.78290200000001,17.352621],"type":"Point"}
}