{
  "type": "Feature",
  "properties": {
    "iso:country":"IN",
    "name:eng_x_preferred":[
        "Suratkal"
    ],
    "name:eng_x_variant":[
        "Suraikal",
        "Suratakal",
        "Surathkal"
    ],
    "name:gom_x_preferred":[
        "\u0938\u0941\u0930\u0924\u0915\u0932"
    ],
    "name:hin_x_preferred":[
        "\u0938\u0942\u0930\u0924\u0915\u0932"
    ],
    "name:kan_x_preferred":[
        "\u0cb8\u0cc1\u0cb0\u0ca4\u0ccd\u0c95\u0cb2\u0ccd"
    ],
    "name:mar_x_preferred":[
        "\u0938\u0941\u0930\u0924\u0915\u0932"
    ],
    "name:nld_x_preferred":[
        "Surathkal"
    ],
    "name:unk_x_variant":[
        "Suraikal",
        "Suratkal"
    ],
    "qs:gn_adm0_cc":"IN",
    "qs:gn_fcode":"PPL",
    "qs:gn_local":1263780,
    "qs:gn_nam_loc":"mangalore",
    "qs:gn_namadm1":"19",
    "qs:gn_name":"Surathakal",
    "qs:local_max":152,
    "qs:local_sum":477,
    "qs:localhoods":7,
    "qs:name":"Suratkal",
    "qs:name_adm0":"India",
    "qs:name_adm1":"Karnataka",
    "qs:name_adm2":"Dakshina Kannada",
    "qs:name_local":"Mangalore",
    "qs:photo_max":30,
    "qs:photo_sum":152,
    "qs:placetype":"Suburb",
    "qs:quad_count":19,
    "qs:woe_adm0":23424848,
    "qs:woe_adm1":2345753,
    "qs:woe_adm2":12586579,
    "qs:woe_lau":0,
    "qs:woe_local":2295255,
    "qs:woe_ver":"7.10.0",
    "wd:wordcount":606,
    "wof:lang":[
        "eng"
    ],
    "wof:name":"Suratkal",
    "wof:placetype":"neighbourhood"
},
  "geometry": {"coordinates":[74.795491,13.000429],"type":"Point"}
}