{
  "type": "Feature",
  "properties": {
    "iso:country":"IN",
    "name:ara_x_preferred":[
        "\u0633\u0648\u0631\u062a\u0643\u0627\u0644"
    ],
    "name:ben_bn_x_preferred":[
        "\u09b8\u09c1\u09b0\u09be\u09a4\u0995\u09be\u09b2"
    ],
    "name:ben_in_x_preferred":[
        "\u09b8\u09c1\u09b0\u09be\u09a4\u0995\u09be\u09b2"
    ],
    "name:eng_x_preferred":[
        "Suratkal"
    ],
    "name:eng_x_variant":[
        "Suraikal",
        "Suratakal",
        "Surathkal"
    ],
    "name:gom_x_preferred":[
        "\u0938\u0941\u0930\u0924\u0915\u0932"
    ],
    "name:guj_x_preferred":[
        "\u0ab8\u0ac1\u0ab0\u0aa4\u0a95\u0abe\u0ab2"
    ],
    "name:hin_x_preferred":[
        "\u0938\u0941\u0930\u0924\u0915\u0932"
    ],
    "name:hin_x_variant":[
        "\u0938\u0942\u0930\u0924\u0915\u0932"
    ],
    "name:kan_x_preferred":[
        "\u0cb8\u0cc1\u0cb0\u0ca4\u0ccd\u0c95\u0cb2\u0ccd"
    ],
    "name:mal_x_preferred":[
        "\u0d38\u0d42\u0d30\u0d24\u0d4d\u0d15\u0d7d"
    ],
    "name:mar_x_preferred":[
        "\u0938\u0941\u0930\u0924\u0915\u093e\u0932"
    ],
    "name:mar_x_variant":[
        "\u0938\u0941\u0930\u0924\u0915\u0932"
    ],
    "name:nld_x_preferred":[
        "Surathkal"
    ],
    "name:pan_x_preferred":[
        "\u0a38\u0a42\u0a30\u0a24\u0a15\u0a3e\u0a32"
    ],
    "name:tam_x_preferred":[
        "\u0b9a\u0bc2\u0bb0\u0ba4\u0bcd\u0b95\u0bb2\u0bcd"
    ],
    "name:tel_x_preferred":[
        "\u0c38\u0c42\u0c30\u0c24\u0c4d"
    ],
    "name:urd_x_preferred":[
        "\u0633\u0648\u0631\u062a \u06a9\u0627\u0644"
    ],
    "qs:gn_adm0_cc":"IN",
    "qs:gn_fcode":"PPL",
    "qs:gn_local":1263780,
    "qs:gn_nam_loc":"mangalore",
    "qs:gn_namadm1":"19",
    "qs:gn_name":"Surathakal",
    "qs:local_max":152,
    "qs:local_sum":477,
    "qs:localhoods":7,
    "qs:name":"Suratkal",
    "qs:name_adm0":"India",
    "qs:name_adm1":"Karnataka",
    "qs:name_adm2":"Dakshina Kannada",
    "qs:name_local":"Mangalore",
    "qs:photo_max":30,
    "qs:photo_sum":152,
    "qs:placetype":"Suburb",
    "qs:quad_count":19,
    "qs:woe_adm0":23424848,
    "qs:woe_adm1":2345753,
    "qs:woe_adm2":12586579,
    "qs:woe_lau":0,
    "qs:woe_local":2295255,
    "qs:woe_ver":"7.10.0",
    "wd:wordcount":606,
    "wof:lang":[
        "eng"
    ],
    "wof:name":"Suratkal",
    "wof:placetype":"neighbourhood"
},
  "geometry": {"coordinates":[74.795491,13.000429],"type":"Point"}
}