{
  "type": "Feature",
  "properties": {
    "iso:country":"IN",
    "ks:ks_name":"Panibura Gaon No 1",
    "ks:ks_pop":492,
    "ks:ks_type":"VILLAGE",
    "name:eng_x_preferred":[
        "Panibura Gaon No 1"
    ],
    "wof:name":"Panibura Gaon No 1",
    "wof:placetype":"locality",
    "wof:population":492
},
  "geometry": {"coordinates":[95.156481,27.271628],"type":"Point"}
}