{
  "type": "Feature",
  "properties": {
    "iso:country":"IN",
    "ks:ks_name":"Gagan Chow. Para",
    "ks:ks_pop":61,
    "ks:ks_type":"HABITATION",
    "name:eng_x_preferred":[
        "Gagan Chow. Para"
    ],
    "wof:name":"Gagan Chow. Para",
    "wof:placetype":"locality",
    "wof:population":61
},
  "geometry": {"coordinates":[91.890051,23.8279],"type":"Point"}
}