{
  "type": "Feature",
  "properties": {
    "iso:country":"IN",
    "ks:ks_name":"Jalluguda Gondguda",
    "ks:ks_pop":184,
    "ks:ks_type":"HABITATION",
    "name:eng_x_preferred":[
        "Jalluguda Gondguda"
    ],
    "wof:name":"Jalluguda Gondguda",
    "wof:placetype":"locality",
    "wof:population":184
},
  "geometry": {"coordinates":[78.403178,19.463565],"type":"Point"}
}