{
  "type": "Feature",
  "properties": {
    "iso:country":"IN",
    "ks:ks_name":"Khairi Kh.",
    "ks:ks_pop":0,
    "ks:ks_type":"VILLAGE",
    "name:eng_x_preferred":[
        "Khairi Kh."
    ],
    "wof:name":"Khairi Kh.",
    "wof:placetype":"locality",
    "wof:population":0
},
  "geometry": {"coordinates":[79.686953,20.570277],"type":"Point"}
}