{
  "type": "Feature",
  "properties": {
    "iso:country":"IN",
    "ks:ks_name":"Alkusi",
    "ks:ks_pop":36,
    "ks:ks_type":"VILLAGE",
    "name:eng_x_preferred":[
        "Alkusi"
    ],
    "wof:name":"Alkusi",
    "wof:placetype":"locality",
    "wof:population":36
},
  "geometry": {"coordinates":[86.051227,23.241923],"type":"Point"}
}