{
  "type": "Feature",
  "properties": {
    "iso:country":"IN",
    "ks:ks_name":"Paparwa",
    "ks:ks_pop":110,
    "ks:ks_type":"HABITATION",
    "name:eng_x_preferred":[
        "Paparwa"
    ],
    "wof:name":"Paparwa",
    "wof:placetype":"locality",
    "wof:population":110
},
  "geometry": {"coordinates":[86.945866,24.76365],"type":"Point"}
}