{
  "type": "Feature",
  "properties": {
    "gn:admin1_code":"36",
    "gn:admin2_code":"174.0",
    "gn:asciiname":"Muhammadpur Aswan",
    "gn:country_code":"IN",
    "gn:dem":108,
    "gn:feature_class":"P",
    "gn:feature_code":"PPL",
    "gn:name":"Muhammadpur Asw\u0101n",
    "gn:population":0,
    "gn:timezone":"Asia/Kolkata",
    "iso:country":"IN",
    "wof:name":"Muhammadpur Aswan",
    "wof:placetype":"neighbourhood"
},
  "geometry": {"coordinates":[81.49387,25.53941],"type":"Point"}
}