{
  "type": "Feature",
  "properties": {
    "gn:admin1_code":"12.0",
    "gn:admin2_code":"2.0",
    "gn:asciiname":"Awanpur",
    "gn:country_code":"IN",
    "gn:dem":1623,
    "gn:feature_class":"P",
    "gn:feature_code":"PPL",
    "gn:name":"Awanpur",
    "gn:population":0,
    "gn:timezone":"Asia/Kolkata",
    "iso:country":"IN",
    "wof:name":"Awanpur",
    "wof:placetype":"locality"
},
  "geometry": {"coordinates":[74.81926999999997,33.93805],"type":"Point"}
}