{
  "type": "Feature",
  "properties": {
    "gn:admin1_code":"37",
    "gn:admin2_code":"409.0",
    "gn:asciiname":"Kareli",
    "gn:country_code":"IN",
    "gn:dem":287,
    "gn:feature_class":"P",
    "gn:feature_code":"PPL",
    "gn:name":"Kareli",
    "gn:population":0,
    "gn:timezone":"Asia/Kolkata",
    "iso:country":"IN",
    "ks:ks_name":"Kareli",
    "ks:ks_pop":1097,
    "ks:ks_type":"VILLAGE",
    "name:ceb_x_preferred":[
        "Kareli"
    ],
    "name:deu_x_preferred":[
        "Kareli"
    ],
    "name:eng_x_preferred":[
        "Kareli"
    ],
    "name:nld_x_preferred":[
        "Kareli"
    ],
    "name:swe_x_preferred":[
        "Kareli"
    ],
    "wof:name":"Kareli",
    "wof:placetype":"locality",
    "wof:population":1097
},
  "geometry": {"coordinates":[81.3104,21.41586],"type":"Point"}
}