{
  "type": "Feature",
  "properties": {
    "iso:country":"IN",
    "ks:ks_name":"Melakudiyiruppu",
    "ks:ks_pop":101,
    "ks:ks_type":"HABITATION",
    "name:eng_x_preferred":[
        "Melakudiyiruppu"
    ],
    "wof:name":"Melakudiyiruppu",
    "wof:placetype":"locality",
    "wof:population":101
},
  "geometry": {"coordinates":[78.949918,10.181332],"type":"Point"}
}