{
  "type": "Feature",
  "properties": {
    "iso:country":"IN",
    "ks:ks_name":"Sisawan",
    "ks:ks_pop":171,
    "ks:ks_type":"VILLAGE",
    "name:eng_x_preferred":[
        "Sisawan"
    ],
    "wof:name":"Sisawan",
    "wof:placetype":"locality",
    "wof:population":171
},
  "geometry": {"coordinates":[82.35814000000001,25.597288],"type":"Point"}
}