{
  "type": "Feature",
  "properties": {
    "iso:country":"IN",
    "ks:ks_name":"Inchudi",
    "ks:ks_pop":3133,
    "ks:ks_type":"VILLAGE",
    "name:eng_x_preferred":[
        "Inchudi"
    ],
    "wof:name":"Inchudi",
    "wof:placetype":"locality",
    "wof:population":3133
},
  "geometry": {"coordinates":[86.906824,21.328133],"type":"Point"}
}