{
  "type": "Feature",
  "properties": {
    "iso:country":"IN",
    "ks:ks_alt_nam":"Kare ka Pura Kheria Sindh",
    "ks:ks_name":"Kare Ka Pura Kheria Sindh",
    "ks:ks_pop":1149,
    "ks:ks_type":"HABITATION",
    "name:eng_x_preferred":[
        "Kare Ka Pura Kheria Sindh"
    ],
    "wof:name":"Kare Ka Pura Kheria Sindh",
    "wof:placetype":"locality",
    "wof:population":1149
},
  "geometry": {"coordinates":[78.825041,26.341307],"type":"Point"}
}