{
  "type": "Feature",
  "properties": {
    "iso:country":"IN",
    "ks:ks_name":"Gungalvetipatti",
    "ks:ks_pop":108,
    "ks:ks_type":"HABITATION",
    "name:eng_x_preferred":[
        "Gungalvetipatti"
    ],
    "wof:name":"Gungalvetipatti",
    "wof:placetype":"locality",
    "wof:population":108
},
  "geometry": {"coordinates":[78.819681,12.968896],"type":"Point"}
}