{
  "type": "Feature",
  "properties": {
    "gn:admin1_code":"35.0",
    "gn:admin2_code":"457.0",
    "gn:asciiname":"Malamihola",
    "gn:country_code":"IN",
    "gn:dem":610,
    "gn:feature_class":"P",
    "gn:feature_code":"PPL",
    "gn:name":"M\u0101lamihol\u0101",
    "gn:population":0,
    "gn:timezone":"Asia/Kolkata",
    "iso:country":"IN",
    "ks:ks_name":"Malumjhola",
    "ks:ks_pop":553,
    "ks:ks_type":"VILLAGE",
    "name:eng_x_preferred":[
        "Malumjhola"
    ],
    "name:eng_x_variant":[
        "Malamihola"
    ],
    "wof:name":"Malumjhola",
    "wof:placetype":"locality",
    "wof:population":553
},
  "geometry": {"coordinates":[80.888493,22.068486],"type":"Point"}
}