{
  "type": "Feature",
  "properties": {
    "iso:country":"IN",
    "ks:ks_name":"Mulakattammanapalya",
    "ks:ks_pop":124,
    "ks:ks_type":"HABITATION",
    "name:eng_x_preferred":[
        "Mulakattammanapalya"
    ],
    "wof:name":"Mulakattammanapalya",
    "wof:placetype":"locality",
    "wof:population":124
},
  "geometry": {"coordinates":[77.083855,13.085515],"type":"Point"}
}