{
  "type": "Feature",
  "properties": {
    "iso:country":"IN",
    "ks:ks_alt_nam":"B.Srirama hally",
    "ks:ks_name":"B.srirama Hally",
    "ks:ks_pop":471,
    "ks:ks_type":"HABITATION",
    "name:eng_x_preferred":[
        "B.srirama Hally"
    ],
    "wof:name":"B.srirama Hally",
    "wof:placetype":"locality",
    "wof:population":471
},
  "geometry": {"coordinates":[76.650809,12.744311],"type":"Point"}
}