{
  "type": "Feature",
  "properties": {
    "iso:country":"IN",
    "ks:ks_name":"Tikraberpani",
    "ks:ks_pop":295,
    "ks:ks_type":"VILLAGE",
    "name:eng_x_preferred":[
        "Tikraberpani"
    ],
    "wof:name":"Tikraberpani",
    "wof:placetype":"locality",
    "wof:population":295
},
  "geometry": {"coordinates":[80.429438,22.759375],"type":"Point"}
}