{
  "type": "Feature",
  "properties": {
    "gn:admin1_code":"2",
    "gn:admin2_code":"546.0",
    "gn:asciiname":"Matsyapuri",
    "gn:country_code":"IN",
    "gn:dem":14,
    "gn:feature_class":"P",
    "gn:feature_code":"PPL",
    "gn:name":"Matsyapuri",
    "gn:population":0,
    "gn:timezone":"Asia/Kolkata",
    "iso:country":"IN",
    "name:tel_x_preferred":[
        "\u0c2e\u0c24\u0c4d\u0c38\u0c4d\u0c2f\u0c2a\u0c41\u0c30\u0c3f"
    ],
    "wof:name":"Matsyapuri",
    "wof:placetype":"neighbourhood"
},
  "geometry": {"coordinates":[81.62782,16.48069],"type":"Point"}
}