{
  "type": "Feature",
  "properties": {
    "gn:admin1_code":"12.0",
    "gn:admin2_code":"005",
    "gn:asciiname":"Ratanpathri",
    "gn:country_code":"IN",
    "gn:dem":2964,
    "gn:feature_class":"P",
    "gn:feature_code":"PPL",
    "gn:name":"Ratanpathri",
    "gn:population":0,
    "gn:timezone":"Asia/Kolkata",
    "iso:country":"IN",
    "wof:name":"Ratanpathri",
    "wof:placetype":"locality"
},
  "geometry": {"coordinates":[74.31944,33.89722],"type":"Point"}
}