{
  "type": "Feature",
  "properties": {
    "iso:country":"IN",
    "ks:ks_name":"Surauli",
    "ks:ks_pop":2724,
    "ks:ks_type":"VILLAGE",
    "ks:ks_uagg_main":0,
    "name:eng_x_preferred":[
        "Surauli"
    ],
    "wof:name":"Surauli",
    "wof:placetype":"neighbourhood",
    "wof:population":2724
},
  "geometry": {"coordinates":[83.741641,26.459472],"type":"Point"}
}