{
  "type": "Feature",
  "properties": {
    "gn:admin1_code":"21.0",
    "gn:admin2_code":"398.0",
    "gn:asciiname":"Bedhapodoro",
    "gn:country_code":"IN",
    "gn:dem":849,
    "gn:feature_class":"P",
    "gn:feature_code":"PPL",
    "gn:name":"Bedhapodoro",
    "gn:population":0,
    "gn:timezone":"Asia/Kolkata",
    "iso:country":"IN",
    "wof:name":"Bedhapodoro",
    "wof:placetype":"locality"
},
  "geometry": {"coordinates":[82.92298000000002,18.95969],"type":"Point"}
}