{
  "type": "Feature",
  "properties": {
    "gn:admin1_code":"2",
    "gn:admin2_code":"546.0",
    "gn:asciiname":"Komatilanka",
    "gn:country_code":"IN",
    "gn:dem":6,
    "gn:feature_class":"P",
    "gn:feature_code":"PPL",
    "gn:name":"Komatilanka",
    "gn:population":0,
    "gn:timezone":"Asia/Kolkata",
    "iso:country":"IN",
    "name:tel_x_preferred":[
        "\u0c15\u0c4b\u0c2e\u0c1f\u0c3f\u0c32\u0c02\u0c15"
    ],
    "wof:name":"Komatilanka",
    "wof:placetype":"locality"
},
  "geometry": {"coordinates":[81.22781999999999,16.58051],"type":"Point"}
}