{
  "type": "Feature",
  "properties": {
    "gn:country":"IN",
    "gn:fcode":"PPL",
    "gn:pop":19556,
    "iso:country":"IN",
    "name:bpy_x_preferred":[
        "\u09b2\u09be\u09f1\u09be\u09b0 \u098f\u09a8\u09aa\u09bf"
    ],
    "name:ceb_x_preferred":[
        "L\u0101war Kh\u0101s"
    ],
    "name:eng_x_preferred":[
        "Lawar"
    ],
    "name:fra_x_preferred":[
        "Lawar"
    ],
    "name:ita_x_preferred":[
        "Lawar"
    ],
    "name:msa_x_preferred":[
        "Lawar NP"
    ],
    "name:nan_x_preferred":[
        "Lawar"
    ],
    "name:new_x_preferred":[
        "\u0932\u0935\u093e\u0930 \u090f\u0928\u094d \u092a\u0940"
    ],
    "name:nld_x_preferred":[
        "Lawar"
    ],
    "name:pol_x_preferred":[
        "Lawar"
    ],
    "name:por_x_preferred":[
        "Lawar NP"
    ],
    "name:swe_x_preferred":[
        "L\u0101war Kh\u0101s"
    ],
    "name:unk_x_variant":[
        "L\u0101war"
    ],
    "name:urd_x_preferred":[
        "\u0644\u0627\u0648\u0631"
    ],
    "name:vie_x_preferred":[
        "Lawar NP"
    ],
    "name:zho_x_preferred":[
        "\u62c9\u74e6\u5c14\u6069\u666e"
    ],
    "qs:name":"L\u0101war Kh\u0101s",
    "qs:photos_9r":0,
    "qs:photos_sr":0,
    "qs:pop_sr":"6",
    "wof:name":"L\u0101war Kh\u0101s",
    "wof:placetype":"locality",
    "wof:population":19556
},
  "geometry": {"coordinates":[77.77767,29.11091],"type":"Point"}
}