{
  "type": "Feature",
  "properties": {
    "gn:admin1_code":"16.0",
    "gn:admin2_code":"504.0",
    "gn:asciiname":"Kola",
    "gn:country_code":"IN",
    "gn:dem":412,
    "gn:feature_class":"P",
    "gn:feature_code":"PPL",
    "gn:name":"Kola",
    "gn:population":0,
    "gn:timezone":"Asia/Kolkata",
    "iso:country":"IN",
    "name:ara_x_preferred":[
        "\u0643\u0648\u0644\u0627"
    ],
    "name:aze_x_preferred":[
        "Kola"
    ],
    "name:ben_x_preferred":[
        "\u0995\u09cb\u09b2\u09be"
    ],
    "name:bos_x_preferred":[
        "Kola"
    ],
    "name:bul_x_preferred":[
        "\u041a\u043e\u043b\u0430"
    ],
    "name:ceb_x_preferred":[
        "Kola"
    ],
    "name:ces_x_preferred":[
        "Kola"
    ],
    "name:chv_x_preferred":[
        "\u041a\u043e\u043b\u0430"
    ],
    "name:deu_x_preferred":[
        "Kola"
    ],
    "name:ell_x_preferred":[
        "\u039a\u03cc\u03bb\u03b1"
    ],
    "name:epo_x_preferred":[
        "Kola"
    ],
    "name:eus_x_preferred":[
        "Kola"
    ],
    "name:fas_x_preferred":[
        "\u06a9\u0648\u0644\u0627"
    ],
    "name:fin_x_preferred":[
        "Kola"
    ],
    "name:fra_x_preferred":[
        "Kola"
    ],
    "name:hin_x_preferred":[
        "\u0915\u094b\u0932\u093e"
    ],
    "name:hrv_x_preferred":[
        "Kola"
    ],
    "name:hsb_x_preferred":[
        "Kola"
    ],
    "name:hun_x_preferred":[
        "Kola"
    ],
    "name:ind_x_preferred":[
        "Kola"
    ],
    "name:ita_x_preferred":[
        "Kola"
    ],
    "name:jpn_x_preferred":[
        "\u30b3\u30fc\u30e9"
    ],
    "name:kat_x_preferred":[
        "\u10d9\u10dd\u10da\u10d0"
    ],
    "name:kor_x_preferred":[
        "\ucf5c\ub77c"
    ],
    "name:lat_x_preferred":[
        "Kola"
    ],
    "name:lav_x_preferred":[
        "Kola"
    ],
    "name:lit_x_preferred":[
        "Kola"
    ],
    "name:ltz_x_preferred":[
        "Kola"
    ],
    "name:mkd_x_preferred":[
        "\u041a\u043e\u043b\u0430"
    ],
    "name:nld_x_preferred":[
        "Kola"
    ],
    "name:nor_x_preferred":[
        "Kola"
    ],
    "name:pol_x_preferred":[
        "Kola"
    ],
    "name:por_x_preferred":[
        "Kola"
    ],
    "name:rus_x_preferred":[
        "\u041a\u043e\u043b\u0430"
    ],
    "name:slk_x_preferred":[
        "Kola"
    ],
    "name:spa_x_preferred":[
        "Kola"
    ],
    "name:srp_x_preferred":[
        "\u041a\u043e\u043b\u0430"
    ],
    "name:swe_x_preferred":[
        "Kolafloden"
    ],
    "name:swe_x_variant":[
        "Kola"
    ],
    "name:tgl_x_preferred":[
        "Kola"
    ],
    "name:tur_x_preferred":[
        "Kola"
    ],
    "name:ukr_x_preferred":[
        "\u041a\u043e\u043b\u0430"
    ],
    "name:urd_x_preferred":[
        "\u06a9\u0648\u0644\u0627"
    ],
    "name:vie_x_preferred":[
        "S\u00f4ng Kola"
    ],
    "wof:name":"Kola",
    "wof:placetype":"locality"
},
  "geometry": {"coordinates":[78.28146,21.25634],"type":"Point"}
}