{
  "type": "Feature",
  "properties": {
    "iso:country":"IN",
    "ks:ks_name":"Charaipara Gaon",
    "ks:ks_pop":507,
    "ks:ks_type":"HABITATION",
    "name:eng_x_preferred":[
        "Charaipara Gaon"
    ],
    "wof:name":"Charaipara Gaon",
    "wof:placetype":"locality",
    "wof:population":507
},
  "geometry": {"coordinates":[94.524157,27.028456],"type":"Point"}
}