{
  "type": "Feature",
  "properties": {
    "iso:country":"IN",
    "ks:ks_name":"Avalam",
    "ks:ks_pop":441,
    "ks:ks_type":"VILLAGE",
    "name:eng_x_preferred":[
        "Avalam"
    ],
    "wof:name":"Avalam",
    "wof:placetype":"locality",
    "wof:population":441
},
  "geometry": {"coordinates":[79.38226899999999,11.780724],"type":"Point"}
}