{
  "type": "Feature",
  "properties": {
    "iso:country":"IN",
    "ks:ks_name":"Mgr Nagar Irular Colony",
    "ks:ks_pop":315,
    "ks:ks_type":"HABITATION",
    "name:eng_x_preferred":[
        "Mgr Nagar Irular Colony"
    ],
    "wof:name":"Mgr Nagar Irular Colony",
    "wof:placetype":"locality",
    "wof:population":315
},
  "geometry": {"coordinates":[76.923787,11.229007],"type":"Point"}
}