{
  "type": "Feature",
  "properties": {
    "gn:admin1_code":"12.0",
    "gn:admin2_code":"006",
    "gn:asciiname":"Bakhar",
    "gn:country_code":"IN",
    "gn:dem":520,
    "gn:feature_class":"P",
    "gn:feature_code":"PPL",
    "gn:name":"Bakhar",
    "gn:population":0,
    "gn:timezone":"Asia/Kolkata",
    "iso:country":"IN",
    "name:gom_x_preferred":[
        "\u092c\u0916\u0930"
    ],
    "name:mar_x_preferred":[
        "\u092c\u0916\u0930"
    ],
    "name:urd_x_preferred":[
        "\u0628\u06a9\u06be\u0631"
    ],
    "wof:name":"Bakhar",
    "wof:placetype":"locality"
},
  "geometry": {"coordinates":[74.4097,33.08371],"type":"Point"}
}