{
  "type": "Feature",
  "properties": {
    "gn:admin1_code":"37",
    "gn:admin2_code":"404.0",
    "gn:asciiname":"Damia",
    "gn:country_code":"IN",
    "gn:dem":317,
    "gn:feature_class":"P",
    "gn:feature_code":"PPL",
    "gn:name":"Dami\u0101",
    "gn:population":0,
    "gn:timezone":"Asia/Kolkata",
    "iso:country":"IN",
    "ks:ks_name":"Damiya",
    "ks:ks_pop":1052,
    "ks:ks_type":"VILLAGE",
    "name:deu_x_preferred":[
        "Damia"
    ],
    "name:eng_x_preferred":[
        "Damiya"
    ],
    "name:eng_x_variant":[
        "Damia"
    ],
    "name:fra_x_preferred":[
        "Damia"
    ],
    "name:hat_x_preferred":[
        "Damia"
    ],
    "name:nld_x_preferred":[
        "Damia"
    ],
    "wof:name":"Damiya",
    "wof:placetype":"locality",
    "wof:population":1052
},
  "geometry": {"coordinates":[82.323216,22.354159],"type":"Point"}
}