{
  "type": "Feature",
  "properties": {
    "gn:admin1_code":"37",
    "gn:admin2_code":"404.0",
    "gn:asciiname":"Damia",
    "gn:country_code":"IN",
    "gn:dem":317,
    "gn:feature_class":"P",
    "gn:feature_code":"PPL",
    "gn:name":"Dami\u0101",
    "gn:population":0,
    "gn:timezone":"Asia/Kolkata",
    "iso:country":"IN",
    "name:deu_x_preferred":[
        "Damia"
    ],
    "name:fra_x_preferred":[
        "Damia"
    ],
    "name:hat_x_preferred":[
        "Damia"
    ],
    "name:nld_x_preferred":[
        "Damia"
    ],
    "wof:name":"Damia",
    "wof:placetype":"locality"
},
  "geometry": {"coordinates":[82.32365,22.34609],"type":"Point"}
}