{
  "type": "Feature",
  "properties": {
    "gn:admin1_code":"12",
    "gn:admin2_code":"12.0",
    "gn:asciiname":"Hariparigom",
    "gn:country_code":"IN",
    "gn:dem":1602,
    "gn:feature_class":"P",
    "gn:feature_code":"PPL",
    "gn:name":"H\u0101rip\u0101rig\u014dm",
    "gn:population":0,
    "gn:timezone":"Asia/Kolkata",
    "iso:country":"IN",
    "wof:name":"Hariparigom",
    "wof:placetype":"locality"
},
  "geometry": {"coordinates":[75.06839000000002,33.87344],"type":"Point"}
}