{
  "type": "Feature",
  "properties": {
    "iso:country":"IN",
    "ks:ks_alt_nam":"K.Hemmanahally",
    "ks:ks_name":"K.hemmanahally",
    "ks:ks_pop":908,
    "ks:ks_type":"HABITATION",
    "name:eng_x_preferred":[
        "K.hemmanahally"
    ],
    "wof:name":"K.hemmanahally",
    "wof:placetype":"locality",
    "wof:population":908
},
  "geometry": {"coordinates":[76.557396,12.305563],"type":"Point"}
}