{
  "type": "Feature",
  "properties": {
    "iso:country":"IN",
    "ks:ks_name":"Jakarowa Bill",
    "ks:ks_pop":559,
    "ks:ks_type":"VILLAGE",
    "name:eng_x_preferred":[
        "Jakarowa Bill"
    ],
    "wof:name":"Jakarowa Bill",
    "wof:placetype":"locality",
    "wof:population":559
},
  "geometry": {"coordinates":[92.584388,26.242134],"type":"Point"}
}