{
  "type": "Feature",
  "properties": {
    "iso:country":"IN",
    "ks:ks_name":"Batarasahi",
    "ks:ks_pop":55,
    "ks:ks_type":"VILLAGE",
    "name:eng_x_preferred":[
        "Batarasahi"
    ],
    "wof:name":"Batarasahi",
    "wof:placetype":"locality",
    "wof:population":55
},
  "geometry": {"coordinates":[84.41728500000001,18.968955],"type":"Point"}
}