{
  "type": "Feature",
  "properties": {
    "iso:country":"IN",
    "ks:ks_alt_nam":"AHIR TOLA",
    "ks:ks_name":"Ahir Tola",
    "ks:ks_pop":99,
    "ks:ks_type":"HABITATION",
    "name:eng_x_preferred":[
        "Ahir Tola"
    ],
    "wof:name":"Ahir Tola",
    "wof:placetype":"locality",
    "wof:population":99
},
  "geometry": {"coordinates":[84.090394,25.42959],"type":"Point"}
}