{
  "type": "Feature",
  "properties": {
    "gn:admin1_code":"2",
    "gn:admin2_code":"544.0",
    "gn:asciiname":"Totalgondi",
    "gn:country_code":"IN",
    "gn:dem":1191,
    "gn:feature_class":"P",
    "gn:feature_code":"PPL",
    "gn:name":"Totalgondi",
    "gn:population":0,
    "gn:timezone":"Asia/Kolkata",
    "iso:country":"IN",
    "wof:name":"Totalgondi",
    "wof:placetype":"locality"
},
  "geometry": {"coordinates":[82.79668000000002,18.20447],"type":"Point"}
}