{
  "type": "Feature",
  "properties": {
    "gn:admin1_code":"35",
    "gn:admin2_code":"429.0",
    "gn:asciiname":"Barreh",
    "gn:country_code":"IN",
    "gn:dem":357,
    "gn:feature_class":"P",
    "gn:feature_code":"PPL",
    "gn:name":"Barreh",
    "gn:population":0,
    "gn:timezone":"Asia/Kolkata",
    "iso:country":"IN",
    "name:fas_x_preferred":[
        "\u0628\u0631\u0647"
    ],
    "name:msa_x_preferred":[
        "Barreh"
    ],
    "wof:name":"Barreh",
    "wof:placetype":"neighbourhood"
},
  "geometry": {"coordinates":[80.9884,24.34907],"type":"Point"}
}