{
  "type": "Feature",
  "properties": {
    "gn:admin1_code":"36",
    "gn:admin2_code":"154.0",
    "gn:asciiname":"Sukhnandanpur",
    "gn:country_code":"IN",
    "gn:dem":123,
    "gn:feature_class":"P",
    "gn:feature_code":"PPL",
    "gn:name":"Sukhnandanpur",
    "gn:population":0,
    "gn:timezone":"Asia/Kolkata",
    "iso:country":"IN",
    "ks:ks_name":"Sukhnandanpurwa",
    "ks:ks_pop":156,
    "ks:ks_type":"HABITATION",
    "ks:ks_uagg_main":0,
    "name:eng_x_preferred":[
        "Sukhnandanpurwa"
    ],
    "wof:name":"Sukhnandanpurwa",
    "wof:placetype":"neighbourhood",
    "wof:population":156
},
  "geometry": {"coordinates":[81.161874,27.627888],"type":"Point"}
}