{
  "type": "Feature",
  "properties": {
    "iso:country":"IN",
    "ks:ks_name":"Dodlimane",
    "ks:ks_pop":76,
    "ks:ks_type":"HABITATION",
    "name:eng_x_preferred":[
        "Dodlimane"
    ],
    "wof:name":"Dodlimane",
    "wof:placetype":"locality",
    "wof:population":76
},
  "geometry": {"coordinates":[75.12578499999999,13.948695],"type":"Point"}
}