{
  "type": "Feature",
  "properties": {
    "iso:country":"IN",
    "ks:ks_alt_nam":"CHIMTAPANI",
    "ks:ks_name":"Chimtapani",
    "ks:ks_pop":297,
    "ks:ks_type":"HABITATION",
    "name:eng_x_preferred":[
        "Chimtapani"
    ],
    "wof:name":"Chimtapani",
    "wof:placetype":"locality",
    "wof:population":297
},
  "geometry": {"coordinates":[83.585168,22.674897],"type":"Point"}
}