{
  "type": "Feature",
  "properties": {
    "iso:country":"IN",
    "ks:ks_name":"Ambedkar Nagar",
    "ks:ks_pop":543,
    "ks:ks_type":"HABITATION",
    "ks:ks_uagg_main":0,
    "name:eng_x_preferred":[
        "Ambedkar Nagar"
    ],
    "wof:name":"Ambedkar Nagar",
    "wof:placetype":"locality",
    "wof:population":543
},
  "geometry": {"coordinates":[79.960904,12.703],"type":"Point"}
}