{
  "type": "Feature",
  "properties": {
    "gn:admin1_code":"6.0",
    "gn:admin2_code":"496",
    "gn:asciiname":"Amal",
    "gn:country_code":"IN",
    "gn:dem":40,
    "gn:feature_class":"P",
    "gn:feature_code":"PPL",
    "gn:name":"Amal",
    "gn:population":0,
    "gn:timezone":"Asia/Kolkata",
    "iso:country":"IN",
    "name:ceb_x_preferred":[
        "Amal"
    ],
    "name:deu_x_preferred":[
        "Amal"
    ],
    "name:fas_x_preferred":[
        "\u0639\u0645\u0644"
    ],
    "name:fra_x_preferred":[
        "Amal"
    ],
    "name:heb_x_preferred":[
        "\u05d0\u05de\u05dc"
    ],
    "name:ind_x_preferred":[
        "Amal"
    ],
    "name:ita_x_preferred":[
        "Amal"
    ],
    "name:lim_x_preferred":[
        "Amal"
    ],
    "name:nld_x_preferred":[
        "Amal"
    ],
    "name:pol_x_preferred":[
        "Amal"
    ],
    "name:sco_x_preferred":[
        "Amal"
    ],
    "name:spa_x_preferred":[
        "Amal"
    ],
    "name:sun_x_preferred":[
        "Amal"
    ],
    "name:und_x_variant":[
        "Atal",
        "Athal"
    ],
    "wof:name":"Amal",
    "wof:placetype":"locality"
},
  "geometry": {"coordinates":[72.97938000000001,20.26752],"type":"Point"}
}