{
  "type": "Feature",
  "properties": {
    "gn:admin1_code":"6.0",
    "gn:admin2_code":"496",
    "gn:asciiname":"Amal",
    "gn:country_code":"IN",
    "gn:dem":40,
    "gn:feature_class":"P",
    "gn:feature_code":"PPL",
    "gn:name":"Amal",
    "gn:population":0,
    "gn:timezone":"Asia/Kolkata",
    "iso:country":"IN",
    "name:und_x_variant":[
        "Atal",
        "Athal",
        "Amal"
    ],
    "wof:name":"Amal",
    "wof:placetype":"locality"
},
  "geometry": {"coordinates":[72.97938000000001,20.26752],"type":"Point"}
}