{
  "type": "Feature",
  "properties": {
    "gn:admin1_code":"19.0",
    "gn:admin2_code":"570.0",
    "gn:asciiname":"Hire Sigara",
    "gn:country_code":"IN",
    "gn:dem":924,
    "gn:feature_class":"P",
    "gn:feature_code":"PPL",
    "gn:name":"Hire Sigara",
    "gn:population":0,
    "gn:timezone":"Asia/Kolkata",
    "iso:country":"IN",
    "wof:name":"Hire Sigara",
    "wof:placetype":"locality"
},
  "geometry": {"coordinates":[75.73035,13.03154],"type":"Point"}
}