{
  "type": "Feature",
  "properties": {
    "iso:country":"IN",
    "ks:ks_name":"Pipalkheda Isagarh",
    "ks:ks_pop":0,
    "ks:ks_type":"VILLAGE",
    "name:eng_x_preferred":[
        "Pipalkheda Isagarh"
    ],
    "wof:name":"Pipalkheda Isagarh",
    "wof:placetype":"locality",
    "wof:population":0
},
  "geometry": {"coordinates":[77.90774,25.137743],"type":"Point"}
}