{
  "type": "Feature",
  "properties": {
    "iso:country":"IN",
    "ks:ks_name":"Harilai",
    "ks:ks_pop":0,
    "ks:ks_type":"VILLAGE",
    "name:eng_x_preferred":[
        "Harilai"
    ],
    "wof:name":"Harilai",
    "wof:placetype":"locality",
    "wof:population":0
},
  "geometry": {"coordinates":[85.86688599999999,24.366713],"type":"Point"}
}