{
  "type": "Feature",
  "properties": {
    "iso:country":"IN",
    "ks:ks_name":"Padavattamman Nagar",
    "ks:ks_pop":220,
    "ks:ks_type":"HABITATION",
    "ks:ks_uagg_main":0,
    "name:eng_x_preferred":[
        "Padavattamman Nagar"
    ],
    "wof:name":"Padavattamman Nagar",
    "wof:placetype":"locality",
    "wof:population":220
},
  "geometry": {"coordinates":[79.95746699999999,12.712377],"type":"Point"}
}