{
  "type": "Feature",
  "properties": {
    "iso:country":"IN",
    "ks:ks_name":"Manorpur",
    "ks:ks_pop":265,
    "ks:ks_type":"HABITATION",
    "name:eng_x_preferred":[
        "Manorpur"
    ],
    "wof:name":"Manorpur",
    "wof:placetype":"locality",
    "wof:population":265
},
  "geometry": {"coordinates":[73.6456,22.670267],"type":"Point"}
}