{
  "type": "Feature",
  "properties": {
    "gn:admin1_code":"37.0",
    "gn:admin2_code":"416.0",
    "gn:asciiname":"Kumarpara",
    "gn:country_code":"IN",
    "gn:dem":557,
    "gn:feature_class":"P",
    "gn:feature_code":"PPL",
    "gn:name":"Kum\u0101rp\u0101ra",
    "gn:population":0,
    "gn:timezone":"Asia/Kolkata",
    "iso:country":"IN",
    "wof:name":"Kumarpara",
    "wof:placetype":"locality"
},
  "geometry": {"coordinates":[81.40201,18.49747],"type":"Point"}
}