{
  "type": "Feature",
  "properties": {
    "iso:country":"IN",
    "ks:ks_name":"Kota Pura",
    "ks:ks_pop":492,
    "ks:ks_type":"VILLAGE",
    "name:eng_x_preferred":[
        "Kota Pura"
    ],
    "wof:name":"Kota Pura",
    "wof:placetype":"locality",
    "wof:population":492
},
  "geometry": {"coordinates":[77.13055199999999,26.639764],"type":"Point"}
}