{
  "type": "Feature",
  "properties": {
    "iso:country":"IN",
    "ks:ks_name":"Vithalwadi",
    "ks:ks_pop":184,
    "ks:ks_type":"HABITATION",
    "name:eng_x_preferred":[
        "Vithalwadi"
    ],
    "wof:name":"Vithalwadi",
    "wof:placetype":"locality",
    "wof:population":184
},
  "geometry": {"coordinates":[73.283197,17.278486],"type":"Point"}
}