{
  "type": "Feature",
  "properties": {
    "iso:country":"IN",
    "ks:ks_name":"Harsimane",
    "ks:ks_pop":35,
    "ks:ks_type":"HABITATION",
    "name:eng_x_preferred":[
        "Harsimane"
    ],
    "wof:name":"Harsimane",
    "wof:placetype":"locality",
    "wof:population":35
},
  "geometry": {"coordinates":[74.816954,14.430119],"type":"Point"}
}