{
  "type": "Feature",
  "properties": {
    "iso:country":"IN",
    "ks:ks_alt_nam":"Jadayan kombai",
    "ks:ks_name":"Jadayan Kombai",
    "ks:ks_pop":126,
    "ks:ks_type":"HABITATION",
    "name:eng_x_preferred":[
        "Jadayan Kombai"
    ],
    "wof:name":"Jadayan Kombai",
    "wof:placetype":"locality",
    "wof:population":126
},
  "geometry": {"coordinates":[78.611752,11.915812],"type":"Point"}
}