{
  "type": "Feature",
  "properties": {
    "iso:country":"IN",
    "ks:ks_name":"Pattraseri",
    "ks:ks_pop":494,
    "ks:ks_type":"HABITATION",
    "name:eng_x_preferred":[
        "Pattraseri"
    ],
    "wof:name":"Pattraseri",
    "wof:placetype":"locality",
    "wof:population":494
},
  "geometry": {"coordinates":[78.94367800000001,10.267284],"type":"Point"}
}