{
  "type": "Feature",
  "properties": {
    "gn:admin1_code":"16",
    "gn:admin2_code":"521.0",
    "gn:asciiname":"Pimple",
    "gn:country_code":"IN",
    "gn:dem":817,
    "gn:feature_class":"P",
    "gn:feature_code":"PPL",
    "gn:name":"Pimple",
    "gn:population":0,
    "gn:timezone":"Asia/Kolkata",
    "iso:country":"IN",
    "name:deu_x_preferred":[
        "Pustel"
    ],
    "name:eus_x_preferred":[
        "Pustula"
    ],
    "name:fas_x_preferred":[
        "\u0686\u0631\u06a9\u200c\u062f\u0627\u0646\u0647"
    ],
    "name:ita_x_preferred":[
        "Pustola"
    ],
    "name:lat_x_preferred":[
        "Pustula"
    ],
    "name:ltz_x_preferred":[
        "Pautsch"
    ],
    "name:nld_x_preferred":[
        "Pustel"
    ],
    "name:pol_x_preferred":[
        "Krosta"
    ],
    "name:por_x_preferred":[
        "P\u00fastula"
    ],
    "name:rus_x_preferred":[
        "\u041f\u0443\u0441\u0442\u0443\u043b\u0430"
    ],
    "name:slv_x_preferred":[
        "Pustula"
    ],
    "name:spa_x_preferred":[
        "P\u00fastula"
    ],
    "name:ukr_x_preferred":[
        "\u0413\u043d\u043e\u044f\u0447\u043e\u043a"
    ],
    "name:vie_x_preferred":[
        "M\u1ee5n m\u1ee7"
    ],
    "wof:name":"Pimple",
    "wof:placetype":"locality"
},
  "geometry": {"coordinates":[74.03335,18.30557],"type":"Point"}
}