{
  "type": "Feature",
  "properties": {
    "iso:country":"IN",
    "ks:ks_name":"Panchagochhia",
    "ks:ks_pop":119,
    "ks:ks_type":"VILLAGE",
    "ks:ks_uagg_main":0,
    "name:eng_x_preferred":[
        "Panchagochhia"
    ],
    "wof:name":"Panchagochhia",
    "wof:placetype":"neighbourhood",
    "wof:population":119
},
  "geometry": {"coordinates":[86.54648899999999,21.260075],"type":"Point"}
}