{
  "type": "Feature",
  "properties": {
    "iso:country":"IN",
    "ks:ks_name":"Kaliya Kund",
    "ks:ks_pop":195,
    "ks:ks_type":"VILLAGE",
    "name:eng_x_preferred":[
        "Kaliya Kund"
    ],
    "wof:name":"Kaliya Kund",
    "wof:placetype":"locality",
    "wof:population":195
},
  "geometry": {"coordinates":[74.678321,23.822389],"type":"Point"}
}