{
  "type": "Feature",
  "properties": {
    "iso:country":"IN",
    "ks:ks_name":"Gorabanda",
    "ks:ks_pop":80,
    "ks:ks_type":"HABITATION",
    "name:eng_x_preferred":[
        "Gorabanda"
    ],
    "wof:name":"Gorabanda",
    "wof:placetype":"locality",
    "wof:population":80
},
  "geometry": {"coordinates":[81.955382,17.710046],"type":"Point"}
}