{
  "type": "Feature",
  "properties": {
    "iso:country":"IN",
    "ks:ks_name":"Manpur Motaluke Ghatarodih",
    "ks:ks_pop":1067,
    "ks:ks_type":"VILLAGE",
    "name:eng_x_preferred":[
        "Manpur Motaluke Ghatarodih"
    ],
    "wof:name":"Manpur Motaluke Ghatarodih",
    "wof:placetype":"locality",
    "wof:population":1067
},
  "geometry": {"coordinates":[85.181803,25.875738],"type":"Point"}
}