{
  "type": "Feature",
  "properties": {
    "iso:country":"IN",
    "ks:ks_name":"Kasidi",
    "ks:ks_pop":104,
    "ks:ks_type":"VILLAGE",
    "ks:ks_uagg_main":0,
    "name:eng_x_preferred":[
        "Kasidi"
    ],
    "wof:name":"Kasidi",
    "wof:placetype":"neighbourhood",
    "wof:population":104
},
  "geometry": {"coordinates":[86.203602,22.496326],"type":"Point"}
}