{
  "type": "Feature",
  "properties": {
    "iso:country":"IN",
    "ks:ks_alt_nam":"LUMCUM PARA",
    "ks:ks_name":"Lumcum Para",
    "ks:ks_pop":218,
    "ks:ks_type":"HABITATION",
    "name:eng_x_preferred":[
        "Lumcum Para"
    ],
    "wof:name":"Lumcum Para",
    "wof:placetype":"locality",
    "wof:population":218
},
  "geometry": {"coordinates":[91.533976,23.719468],"type":"Point"}
}