{
  "type": "Feature",
  "properties": {
    "gn:admin1_code":"2",
    "gn:admin2_code":"544.0",
    "gn:asciiname":"Kangar Ambuguda",
    "gn:country_code":"IN",
    "gn:dem":969,
    "gn:feature_class":"P",
    "gn:feature_code":"PPL",
    "gn:name":"Kangar Ambug\u016bda",
    "gn:population":0,
    "gn:timezone":"Asia/Kolkata",
    "iso:country":"IN",
    "wof:name":"Kangar Ambuguda",
    "wof:placetype":"locality"
},
  "geometry": {"coordinates":[82.80367,18.25067],"type":"Point"}
}