{
  "type": "Feature",
  "properties": {
    "iso:country":"IN",
    "ks:ks_name":"Gadanga",
    "ks:ks_pop":235,
    "ks:ks_type":"VILLAGE",
    "name:eng_x_preferred":[
        "Gadanga"
    ],
    "wof:name":"Gadanga",
    "wof:placetype":"locality",
    "wof:population":235
},
  "geometry": {"coordinates":[84.38139700000001,19.07118],"type":"Point"}
}