{
  "type": "Feature",
  "properties": {
    "gn:admin1_code":"24.0",
    "gn:admin2_code":"117.0",
    "gn:asciiname":"Warka",
    "gn:country_code":"IN",
    "gn:dem":268,
    "gn:feature_class":"P",
    "gn:feature_code":"PPL",
    "gn:name":"Warka",
    "gn:population":0,
    "gn:timezone":"Asia/Kolkata",
    "iso:country":"IN",
    "name:bel_x_preferred":[
        "\u0412\u0430\u0440\u043a\u0430"
    ],
    "name:ceb_x_preferred":[
        "Warka"
    ],
    "name:deu_x_preferred":[
        "Warka"
    ],
    "name:epo_x_preferred":[
        "Warka"
    ],
    "name:est_x_preferred":[
        "Warka"
    ],
    "name:fra_x_preferred":[
        "Warka"
    ],
    "name:heb_x_preferred":[
        "\u05d5\u05d5\u05e8\u05e7\u05d0"
    ],
    "name:hrv_x_preferred":[
        "Warka"
    ],
    "name:hun_x_preferred":[
        "Warka"
    ],
    "name:ind_x_preferred":[
        "Warka"
    ],
    "name:ita_x_preferred":[
        "Warka"
    ],
    "name:jav_x_preferred":[
        "Warka"
    ],
    "name:lav_x_preferred":[
        "Varka"
    ],
    "name:msa_x_preferred":[
        "Warka"
    ],
    "name:nld_x_preferred":[
        "Warka"
    ],
    "name:pol_x_preferred":[
        "Warka"
    ],
    "name:por_x_preferred":[
        "Warka"
    ],
    "name:ron_x_preferred":[
        "Warka"
    ],
    "name:rus_x_preferred":[
        "\u0412\u0430\u0440\u043a\u0430"
    ],
    "name:slk_x_preferred":[
        "Warka"
    ],
    "name:spa_x_preferred":[
        "Warka"
    ],
    "name:srp_x_preferred":[
        "\u0412\u0430\u0440\u043a\u0430"
    ],
    "name:ukr_x_preferred":[
        "\u0412\u0430\u0440\u043a\u0430"
    ],
    "name:vie_x_preferred":[
        "Warka"
    ],
    "name:yid_x_preferred":[
        "\u05d5\u05d5\u05d0\u05e8\u05e7\u05e2"
    ],
    "name:zho_x_preferred":[
        "\u74e6\u723e\u5361"
    ],
    "wof:name":"Warka",
    "wof:placetype":"locality"
},
  "geometry": {"coordinates":[72.55704,24.64663],"type":"Point"}
}