{
  "type": "Feature",
  "properties": {
    "gn:admin1_code":"36.0",
    "gn:admin2_code":"136.0",
    "gn:asciiname":"Nayagaon Najibabad",
    "gn:country_code":"IN",
    "gn:dem":220,
    "gn:feature_class":"P",
    "gn:feature_code":"PPL",
    "gn:name":"Nay\u0101gaon Naj\u012bb\u0101b\u0101d",
    "gn:population":0,
    "gn:timezone":"Asia/Kolkata",
    "iso:country":"IN",
    "ks:ks_alt_nam":"Nay\u0101gaon Naj\u012bb\u0101b\u0101d",
    "ks:ks_name":"Nayagaon Najibabad",
    "ks:ks_pop":1134,
    "ks:ks_type":"VILLAGE",
    "name:eng_x_preferred":[
        "Nayagaon Najibabad"
    ],
    "name:eng_x_variant":[
        "Nay\u0101gaon Naj\u012bb\u0101b\u0101d"
    ],
    "wof:name":"Nayagaon Najibabad",
    "wof:placetype":"locality",
    "wof:population":1134
},
  "geometry": {"coordinates":[79.129884,29.120814],"type":"Point"}
}