{
  "type": "Feature",
  "properties": {
    "iso:country":"IN",
    "ks:ks_name":"Oravumpuram",
    "ks:ks_pop":1420,
    "ks:ks_type":"HABITATION",
    "name:eng_x_preferred":[
        "Oravumpuram"
    ],
    "wof:name":"Oravumpuram",
    "wof:placetype":"locality",
    "wof:population":1420
},
  "geometry": {"coordinates":[76.235699,11.084055],"type":"Point"}
}