{
  "type": "Feature",
  "properties": {
    "iso:country":"IN",
    "ks:ks_name":"Mittapalli",
    "ks:ks_pop":122,
    "ks:ks_type":"HABITATION",
    "ks:ks_uagg_main":0,
    "name:eng_x_preferred":[
        "Mittapalli"
    ],
    "wof:name":"Mittapalli",
    "wof:placetype":"neighbourhood",
    "wof:population":122
},
  "geometry": {"coordinates":[78.489396,14.521072],"type":"Point"}
}