{
  "type": "Feature",
  "properties": {
    "gn:admin1_code":"24.0",
    "gn:admin2_code":"104.0",
    "gn:asciiname":"Karana",
    "gn:country_code":"IN",
    "gn:dem":382,
    "gn:feature_class":"P",
    "gn:feature_code":"PPL",
    "gn:name":"Kar\u0101na",
    "gn:population":0,
    "gn:timezone":"Asia/Kolkata",
    "iso:country":"IN",
    "name:nld_x_preferred":[
        "Karana"
    ],
    "wof:name":"Karana",
    "wof:placetype":"neighbourhood"
},
  "geometry": {"coordinates":[76.22996000000001,27.565],"type":"Point"}
}