{
  "type": "Feature",
  "properties": {
    "gn:admin1_code":"38.0",
    "gn:admin2_code":"358.0",
    "gn:asciiname":"Salima",
    "gn:country_code":"IN",
    "gn:dem":138,
    "gn:feature_class":"P",
    "gn:feature_code":"PPL",
    "gn:name":"Sal\u012bm\u0101",
    "gn:population":0,
    "gn:timezone":"Asia/Kolkata",
    "iso:country":"IN",
    "name:ara_x_preferred":[
        "\u0633\u0644\u064a\u0645\u0629"
    ],
    "name:ben_x_preferred":[
        "\u09b8\u09be\u09b2\u09bf\u09ae\u09be"
    ],
    "name:ceb_x_preferred":[
        "Salima"
    ],
    "name:deu_x_preferred":[
        "Salima"
    ],
    "name:ell_x_preferred":[
        "\u03a3\u03b1\u03bb\u03af\u03bc\u03b1"
    ],
    "name:heb_x_preferred":[
        "\u05e1\u05dc\u05d9\u05de\u05d4"
    ],
    "name:hin_x_preferred":[
        "\u0938\u093e\u0932\u093f\u092e\u093e"
    ],
    "name:hun_x_preferred":[
        "Salima"
    ],
    "name:kor_x_preferred":[
        "\uc0b4\ub9ac\ub9c8"
    ],
    "name:nld_x_preferred":[
        "Salima"
    ],
    "name:por_x_preferred":[
        "Salima"
    ],
    "name:spa_x_preferred":[
        "Salima"
    ],
    "name:swe_x_preferred":[
        "Salima"
    ],
    "name:ukr_x_preferred":[
        "\u0421\u0430\u043b\u0456\u043c\u0430"
    ],
    "name:urd_x_preferred":[
        "\u0633\u0644\u06cc\u0645\u06c1"
    ],
    "name:vie_x_preferred":[
        "Salima"
    ],
    "wof:name":"Salima",
    "wof:placetype":"locality"
},
  "geometry": {"coordinates":[84.02779,24.6035],"type":"Point"}
}