{
  "type": "Feature",
  "properties": {
    "gn:admin1_code":"38.0",
    "gn:admin2_code":"358.0",
    "gn:asciiname":"Salima",
    "gn:country_code":"IN",
    "gn:dem":138,
    "gn:feature_class":"P",
    "gn:feature_code":"PPL",
    "gn:name":"Sal\u012bm\u0101",
    "gn:population":0,
    "gn:timezone":"Asia/Kolkata",
    "iso:country":"IN",
    "name:ceb_x_preferred":[
        "Salima"
    ],
    "name:deu_x_preferred":[
        "Salima"
    ],
    "name:nld_x_preferred":[
        "Salima"
    ],
    "name:swe_x_preferred":[
        "Salima"
    ],
    "wof:name":"Salima",
    "wof:placetype":"locality"
},
  "geometry": {"coordinates":[84.02779,24.6035],"type":"Point"}
}