{
  "type": "Feature",
  "properties": {
    "iso:country":"IN",
    "ks:ks_name":"Sakri Kuiyan",
    "ks:ks_pop":1092,
    "ks:ks_type":"HABITATION",
    "name:eng_x_preferred":[
        "Sakri Kuiyan"
    ],
    "wof:name":"Sakri Kuiyan",
    "wof:placetype":"locality",
    "wof:population":1092
},
  "geometry": {"coordinates":[82.372058,27.616665],"type":"Point"}
}