{
  "type": "Feature",
  "properties": {
    "iso:country":"IN",
    "ks:ks_name":"Bidasahalli",
    "ks:ks_pop":25,
    "ks:ks_type":"HABITATION",
    "name:eng_x_preferred":[
        "Bidasahalli"
    ],
    "wof:name":"Bidasahalli",
    "wof:placetype":"locality",
    "wof:population":25
},
  "geometry": {"coordinates":[74.717355,14.143098],"type":"Point"}
}