{
  "type": "Feature",
  "properties": {
    "iso:country":"IN",
    "ks:ks_name":"Gotama",
    "ks:ks_pop":72,
    "ks:ks_type":"VILLAGE",
    "name:eng_x_preferred":[
        "Gotama"
    ],
    "wof:name":"Gotama",
    "wof:placetype":"locality",
    "wof:population":72
},
  "geometry": {"coordinates":[84.34519400000001,19.505386],"type":"Point"}
}