{
  "type": "Feature",
  "properties": {
    "iso:country":"IN",
    "ks:ks_name":"Kayam Ki Basti",
    "ks:ks_pop":123,
    "ks:ks_type":"HABITATION",
    "name:eng_x_preferred":[
        "Kayam Ki Basti"
    ],
    "wof:name":"Kayam Ki Basti",
    "wof:placetype":"locality",
    "wof:population":123
},
  "geometry": {"coordinates":[71.397189,26.157625],"type":"Point"}
}