{
  "type": "Feature",
  "properties": {
    "iso:country":"IN",
    "ks:ks_name":"Manoharapur",
    "ks:ks_pop":876,
    "ks:ks_type":"VILLAGE",
    "name:eng_x_preferred":[
        "Manoharapur"
    ],
    "wof:name":"Manoharapur",
    "wof:placetype":"locality",
    "wof:population":876
},
  "geometry": {"coordinates":[85.781436,21.525318],"type":"Point"}
}