{
  "type": "Feature",
  "properties": {
    "iso:country":"IN",
    "ks:ks_name":"Singarapalem",
    "ks:ks_pop":622,
    "ks:ks_type":"HABITATION",
    "name:eng_x_preferred":[
        "Singarapalem"
    ],
    "wof:name":"Singarapalem",
    "wof:placetype":"locality",
    "wof:population":622
},
  "geometry": {"coordinates":[79.721982,15.106476],"type":"Point"}
}