{
  "type": "Feature",
  "properties": {
    "gn:admin1_code":"35.0",
    "gn:admin2_code":"429.0",
    "gn:asciiname":"Piparhat",
    "gn:country_code":"IN",
    "gn:dem":397,
    "gn:feature_class":"P",
    "gn:feature_code":"PPL",
    "gn:name":"Piparhat",
    "gn:population":0,
    "gn:timezone":"Asia/Kolkata",
    "iso:country":"IN",
    "wof:name":"Piparhat",
    "wof:placetype":"locality"
},
  "geometry": {"coordinates":[80.7719,24.12985],"type":"Point"}
}