{
  "type": "Feature",
  "properties": {
    "iso:country":"IN",
    "ks:ks_name":"Pandey Tola South",
    "ks:ks_pop":159,
    "ks:ks_type":"HABITATION",
    "name:eng_x_preferred":[
        "Pandey Tola South"
    ],
    "wof:name":"Pandey Tola South",
    "wof:placetype":"locality",
    "wof:population":159
},
  "geometry": {"coordinates":[84.278091,26.580075],"type":"Point"}
}