{
  "type": "Feature",
  "properties": {
    "gn:admin1_code":"13.0",
    "gn:admin2_code":"593.0",
    "gn:asciiname":"Thekkummangalam",
    "gn:country_code":"IN",
    "gn:dem":65,
    "gn:feature_class":"P",
    "gn:feature_code":"PPL",
    "gn:name":"Thekkummangalam",
    "gn:population":0,
    "gn:timezone":"Asia/Kolkata",
    "iso:country":"IN",
    "ks:ks_alt_nam":"THEKKUMANGALAM",
    "ks:ks_name":"Thekkumangalam",
    "ks:ks_pop":1938,
    "ks:ks_type":"HABITATION",
    "name:eng_x_preferred":[
        "Thekkumangalam"
    ],
    "name:eng_x_variant":[
        "Thekkummangalam"
    ],
    "wof:name":"Thekkumangalam",
    "wof:placetype":"locality",
    "wof:population":1938
},
  "geometry": {"coordinates":[76.429215,10.754595],"type":"Point"}
}