{
  "type": "Feature",
  "properties": {
    "iso:country":"IN",
    "ks:ks_name":"Dungara",
    "ks:ks_pop":171,
    "ks:ks_type":"VILLAGE",
    "name:eng_x_preferred":[
        "Dungara"
    ],
    "wof:name":"Dungara",
    "wof:placetype":"locality",
    "wof:population":171
},
  "geometry": {"coordinates":[79.49745799999999,29.560752],"type":"Point"}
}