{
  "type": "Feature",
  "properties": {
    "gn:admin1_code":"36.0",
    "gn:admin2_code":"193.0",
    "gn:asciiname":"Ghorai Janpah",
    "gn:country_code":"IN",
    "gn:dem":64,
    "gn:feature_class":"P",
    "gn:feature_code":"PPL",
    "gn:name":"Ghorai Janpah",
    "gn:population":0,
    "gn:timezone":"Asia/Kolkata",
    "iso:country":"IN",
    "ks:ks_name":"Ghorai Janpah",
    "ks:ks_type":"VILLAGE",
    "ks:ks_uagg_main":0,
    "name:eng_x_preferred":[
        "Ghorai Janpah"
    ],
    "wof:name":"Ghorai Janpah",
    "wof:placetype":"neighbourhood"
},
  "geometry": {"coordinates":[84.21262299999999,25.912708],"type":"Point"}
}