{
  "type": "Feature",
  "properties": {
    "iso:country":"IN",
    "ks:ks_name":"Simiri",
    "ks:ks_pop":136,
    "ks:ks_type":"VILLAGE",
    "name:eng_x_preferred":[
        "Simiri"
    ],
    "wof:name":"Simiri",
    "wof:placetype":"locality",
    "wof:population":136
},
  "geometry": {"coordinates":[84.112647,19.203131],"type":"Point"}
}