{
  "type": "Feature",
  "properties": {
    "iso:country":"IN",
    "ks:ks_name":"Chamchaka",
    "ks:ks_pop":1075,
    "ks:ks_type":"VILLAGE",
    "name:eng_x_preferred":[
        "Chamchaka"
    ],
    "wof:name":"Chamchaka",
    "wof:placetype":"locality",
    "wof:population":1075
},
  "geometry": {"coordinates":[86.114643,23.473174],"type":"Point"}
}