{
  "type": "Feature",
  "properties": {
    "gn:admin1_code":"36",
    "gn:admin2_code":"200.0",
    "gn:asciiname":"Robertsganj",
    "gn:country_code":"IN",
    "gn:dem":291,
    "gn:feature_class":"P",
    "gn:feature_code":"PPL",
    "gn:name":"Robertsganj",
    "gn:population":0,
    "gn:timezone":"Asia/Kolkata",
    "iso:country":"IN",
    "name:bih_x_preferred":[
        "\u0930\u093e\u092c\u0930\u094d\u091f\u094d\u0938\u0917\u0902\u091c"
    ],
    "name:bpy_x_preferred":[
        "\u09b0\u09ac\u09be\u09b0\u09cd\u099f\u09b8\u0997\u099e\u09cd\u099c"
    ],
    "name:ceb_x_preferred":[
        "Robertsganj"
    ],
    "name:deu_x_preferred":[
        "Robertsganj"
    ],
    "name:fra_x_preferred":[
        "Robertsganj"
    ],
    "name:guj_x_preferred":[
        "\u0ab0\u0acb\u0aac\u0ab0\u0acd\u0a9f\u0ab8\u0a97\u0a82\u0a9c"
    ],
    "name:hin_x_preferred":[
        "\u0930\u093e\u092c\u0930\u094d\u091f\u094d\u0938\u0917\u0902\u091c"
    ],
    "name:ita_x_preferred":[
        "Robertsganj"
    ],
    "name:mar_x_preferred":[
        "\u0930\u0949\u092c\u0930\u094d\u091f\u094d\u200c\u0938\u0917\u0902\u091c"
    ],
    "name:mlg_x_preferred":[
        "Robertsganj"
    ],
    "name:msa_x_preferred":[
        "Robertsganj"
    ],
    "name:nld_x_preferred":[
        "Robertsganj"
    ],
    "name:ori_x_preferred":[
        "\u0b30\u0b2c\u0b30\u0b4d\u0b1f\u0b38\u0b17\u0b1e\u0b4d\u0b1c"
    ],
    "name:pnb_x_preferred":[
        "\u0631\u0648\u0628\u0631\u0679\u0633 \u06af\u0646\u062c"
    ],
    "name:pol_x_preferred":[
        "Robertsganj"
    ],
    "name:rus_x_preferred":[
        "\u0420\u043e\u0431\u0435\u0440\u0442\u0441\u0433\u0430\u043d\u0434\u0436"
    ],
    "name:san_x_preferred":[
        "\u0930\u093e\u092c\u0930\u094d\u091f\u094d\u0938\u094d\u0917\u091e\u094d\u091c"
    ],
    "name:swe_x_preferred":[
        "Sonbhadra"
    ],
    "name:urd_x_preferred":[
        "\u0631\u0648\u0628\u0631\u0679\u0633 \u06af\u0646\u062c"
    ],
    "name:vie_x_preferred":[
        "Robertsganj"
    ],
    "name:zho_x_preferred":[
        "\u7f57\u8d1d\u5c14\u7279\u65af\u7518\u6770"
    ],
    "wof:name":"Robertsganj",
    "wof:placetype":"locality"
},
  "geometry": {"coordinates":[82.99321999999999,24.87607],"type":"Point"}
}