{
  "type": "Feature",
  "properties": {
    "iso:country":"IN",
    "ks:ks_name":"Khodepar",
    "ks:ks_pop":38,
    "ks:ks_type":"HABITATION",
    "name:eng_x_preferred":[
        "Khodepar"
    ],
    "wof:name":"Khodepar",
    "wof:placetype":"locality",
    "wof:population":38
},
  "geometry": {"coordinates":[81.15848,19.370985],"type":"Point"}
}