{
  "type": "Feature",
  "properties": {
    "iso:country":"IN",
    "ks:ks_name":"Purkait Para",
    "ks:ks_pop":501,
    "ks:ks_type":"HABITATION",
    "name:eng_x_preferred":[
        "Purkait Para"
    ],
    "wof:name":"Purkait Para",
    "wof:placetype":"locality",
    "wof:population":501
},
  "geometry": {"coordinates":[88.221357,22.192343],"type":"Point"}
}