{
  "type": "Feature",
  "properties": {
    "iso:country":"IN",
    "ks:ks_name":"Gundahole",
    "ks:ks_pop":67,
    "ks:ks_type":"HABITATION",
    "name:eng_x_preferred":[
        "Gundahole"
    ],
    "wof:name":"Gundahole",
    "wof:placetype":"locality",
    "wof:population":67
},
  "geometry": {"coordinates":[75.31630699999999,13.358531],"type":"Point"}
}