{
  "type": "Feature",
  "properties": {
    "gn:admin1_code":"16",
    "gn:admin2_code":"527.0",
    "gn:asciiname":"Nimb",
    "gn:country_code":"IN",
    "gn:dem":661,
    "gn:feature_class":"P",
    "gn:feature_code":"PPL",
    "gn:name":"Nimb",
    "gn:population":0,
    "gn:timezone":"Asia/Kolkata",
    "iso:country":"IN",
    "wof:name":"Nimb",
    "wof:placetype":"locality"
},
  "geometry": {"coordinates":[74.00801,17.79171000000001],"type":"Point"}
}