{
  "type": "Feature",
  "properties": {
    "gn:admin1_code":"12.0",
    "gn:admin2_code":"018",
    "gn:asciiname":"Dul",
    "gn:country_code":"IN",
    "gn:dem":1886,
    "gn:feature_class":"P",
    "gn:feature_code":"PPL",
    "gn:name":"D\u016bl",
    "gn:population":0,
    "gn:timezone":"Asia/Kolkata",
    "iso:country":"IN",
    "wof:name":"Dul",
    "wof:placetype":"locality"
},
  "geometry": {"coordinates":[75.78833,33.36158],"type":"Point"}
}