{
  "type": "Feature",
  "properties": {
    "iso:country":"IN",
    "ks:ks_name":"Gurgi Purwa",
    "ks:ks_pop":140,
    "ks:ks_type":"HABITATION",
    "name:eng_x_preferred":[
        "Gurgi Purwa"
    ],
    "wof:name":"Gurgi Purwa",
    "wof:placetype":"locality",
    "wof:population":140
},
  "geometry": {"coordinates":[80.93276,28.418912],"type":"Point"}
}