{
  "type": "Feature",
  "properties": {
    "gn:admin1_code":"28.0",
    "gn:admin2_code":"333.0",
    "gn:asciiname":"Singra",
    "gn:country_code":"IN",
    "gn:dem":34,
    "gn:feature_class":"P",
    "gn:feature_code":"PPL",
    "gn:name":"Singra",
    "gn:population":0,
    "gn:timezone":"Asia/Kolkata",
    "iso:country":"IN",
    "name:arg_x_preferred":[
        "Cingla"
    ],
    "name:ast_x_preferred":[
        "Singra"
    ],
    "name:cat_x_preferred":[
        "Singra"
    ],
    "name:ceb_x_preferred":[
        "Singra"
    ],
    "name:eus_x_preferred":[
        "Singra"
    ],
    "name:fra_x_preferred":[
        "Singra"
    ],
    "name:hun_x_preferred":[
        "Singra"
    ],
    "name:ita_x_preferred":[
        "Singra"
    ],
    "name:msa_x_preferred":[
        "Singra"
    ],
    "name:nld_x_preferred":[
        "Singra"
    ],
    "name:oci_x_preferred":[
        "Singra"
    ],
    "name:pol_x_preferred":[
        "Singra"
    ],
    "name:por_x_preferred":[
        "Singra"
    ],
    "name:rus_x_preferred":[
        "\u0421\u0438\u043d\u0433\u0440\u0430"
    ],
    "name:spa_x_preferred":[
        "Singra"
    ],
    "name:ukr_x_preferred":[
        "\u0421\u0456\u043d\u0433\u0440\u0430"
    ],
    "name:vie_x_preferred":[
        "Singra"
    ],
    "name:war_x_preferred":[
        "Singra"
    ],
    "wof:name":"Singra",
    "wof:placetype":"locality"
},
  "geometry": {"coordinates":[87.98455,24.3869],"type":"Point"}
}