{
  "type": "Feature",
  "properties": {
    "gn:admin1_code":"34.0",
    "gn:admin2_code":"217.0",
    "gn:asciiname":"Nari",
    "gn:country_code":"IN",
    "gn:dem":75,
    "gn:feature_class":"P",
    "gn:feature_code":"PPL",
    "gn:name":"Nari",
    "gn:population":0,
    "gn:timezone":"Asia/Kolkata",
    "iso:country":"IN",
    "name:ceb_x_preferred":[
        "Nari"
    ],
    "name:deu_x_preferred":[
        "Nari"
    ],
    "name:swe_x_preferred":[
        "Nari"
    ],
    "name:ukr_x_preferred":[
        "\u041d\u0430\u0440\u0456"
    ],
    "wof:name":"Nari",
    "wof:placetype":"neighbourhood"
},
  "geometry": {"coordinates":[84.19659,26.37192],"type":"Point"}
}