{
  "type": "Feature",
  "properties": {
    "iso:country":"IN",
    "ks:ks_name":"Raepur",
    "ks:ks_pop":935,
    "ks:ks_type":"VILLAGE",
    "ks:ks_uagg_main":0,
    "name:eng_x_preferred":[
        "Raepur"
    ],
    "wof:name":"Raepur",
    "wof:placetype":"locality",
    "wof:population":935
},
  "geometry": {"coordinates":[87.37596499999999,21.688612],"type":"Point"}
}