{
  "type": "Feature",
  "properties": {
    "iso:country":"IN",
    "ks:ks_name":"Kadamwasti",
    "ks:ks_pop":400,
    "ks:ks_type":"HABITATION",
    "ks:ks_uagg_main":0,
    "name:eng_x_preferred":[
        "Kadamwasti"
    ],
    "wof:name":"Kadamwasti",
    "wof:placetype":"neighbourhood",
    "wof:population":400
},
  "geometry": {"coordinates":[74.47092499999999,17.984941],"type":"Point"}
}