{
  "type": "Feature",
  "properties": {
    "iso:country":"IN",
    "ks:ks_name":"Gilapol",
    "ks:ks_pop":364,
    "ks:ks_type":"VILLAGE",
    "ks:ks_uagg_main":0,
    "name:eng_x_preferred":[
        "Gilapol"
    ],
    "wof:name":"Gilapol",
    "wof:placetype":"neighbourhood",
    "wof:population":364
},
  "geometry": {"coordinates":[88.529059,23.134812],"type":"Point"}
}