{
  "type": "Feature",
  "properties": {
    "iso:country":"IN",
    "ks:ks_name":"Kalet",
    "ks:ks_pop":35,
    "ks:ks_type":"VILLAGE",
    "ks:ks_uagg_main":0,
    "name:eng_x_preferred":[
        "Kalet"
    ],
    "wof:name":"Kalet",
    "wof:placetype":"locality",
    "wof:population":35
},
  "geometry": {"coordinates":[79.681388,29.593442],"type":"Point"}
}