{
  "type": "Feature",
  "properties": {
    "gn:admin1_code":"23.0",
    "gn:admin2_code":"041",
    "gn:asciiname":"Kotla Dhak",
    "gn:country_code":"IN",
    "gn:dem":267,
    "gn:feature_class":"P",
    "gn:feature_code":"PPL",
    "gn:name":"Kotla Dh\u0101k",
    "gn:population":0,
    "gn:timezone":"Asia/Kolkata",
    "iso:country":"IN",
    "wof:name":"Kotla Dhak",
    "wof:placetype":"locality"
},
  "geometry": {"coordinates":[76.14064999999999,30.68277],"type":"Point"}
}