{
  "type": "Feature",
  "properties": {
    "gn:admin1_code":"12.0",
    "gn:admin2_code":"005",
    "gn:asciiname":"Dabra",
    "gn:country_code":"IN",
    "gn:dem":856,
    "gn:feature_class":"P",
    "gn:feature_code":"PPL",
    "gn:name":"Dabr\u0101",
    "gn:population":0,
    "gn:timezone":"Asia/Kolkata",
    "iso:country":"IN",
    "wof:name":"Dabra",
    "wof:placetype":"locality"
},
  "geometry": {"coordinates":[74.03413,33.63746],"type":"Point"}
}