{
  "type": "Feature",
  "properties": {
    "gn:admin1_code":"35.0",
    "gn:admin2_code":"436.0",
    "gn:asciiname":"Pura Raipur",
    "gn:country_code":"IN",
    "gn:dem":440,
    "gn:feature_class":"P",
    "gn:feature_code":"PPL",
    "gn:name":"Pura Raipur",
    "gn:population":0,
    "gn:timezone":"Asia/Kolkata",
    "iso:country":"IN",
    "wof:name":"Pura Raipur",
    "wof:placetype":"locality"
},
  "geometry": {"coordinates":[76.68159,23.47838],"type":"Point"}
}