{
  "type": "Feature",
  "properties": {
    "iso:country":"IN",
    "ks:ks_name":"Mahro",
    "ks:ks_pop":740,
    "ks:ks_type":"HABITATION",
    "name:eng_x_preferred":[
        "Mahro"
    ],
    "wof:name":"Mahro",
    "wof:placetype":"locality",
    "wof:population":740
},
  "geometry": {"coordinates":[83.842027,26.161216],"type":"Point"}
}