{
  "type": "Feature",
  "properties": {
    "gn:admin1_code":"39.0",
    "gn:admin2_code":"061",
    "gn:asciiname":"Muni Sakri",
    "gn:country_code":"IN",
    "gn:dem":1253,
    "gn:feature_class":"P",
    "gn:feature_code":"PPL",
    "gn:name":"M\u016bni Sakri",
    "gn:population":0,
    "gn:timezone":"Asia/Kolkata",
    "iso:country":"IN",
    "ks:ks_name":"Muni Sankari",
    "ks:ks_pop":178,
    "ks:ks_type":"VILLAGE",
    "name:eng_x_preferred":[
        "Muni Sankari"
    ],
    "name:eng_x_variant":[
        "Muni Sakri"
    ],
    "wof:name":"Muni Sankari",
    "wof:placetype":"locality",
    "wof:population":178
},
  "geometry": {"coordinates":[78.538685,29.878199],"type":"Point"}
}