{
  "type": "Feature",
  "properties": {
    "iso:country":"IN",
    "ks:ks_name":"Anjar",
    "ks:ks_pop":1734,
    "ks:ks_type":"VILLAGE",
    "name:eng_x_preferred":[
        "Anjar"
    ],
    "wof:name":"Anjar",
    "wof:placetype":"locality",
    "wof:population":1734
},
  "geometry": {"coordinates":[81.642572,19.075249],"type":"Point"}
}