{
  "type": "Feature",
  "properties": {
    "iso:country":"IN",
    "ks:ks_name":"11 KNN",
    "ks:ks_pop":15,
    "ks:ks_type":"VILLAGE",
    "name:eng_x_preferred":[
        "11 KNN"
    ],
    "wof:name":"11 KNN",
    "wof:placetype":"locality",
    "wof:population":15
},
  "geometry": {"coordinates":[74.81784399999999,29.351779],"type":"Point"}
}