{
  "type": "Feature",
  "properties": {
    "gn:admin1_code":"35",
    "gn:admin2_code":"458.0",
    "gn:asciiname":"Baru Panwari",
    "gn:country_code":"IN",
    "gn:dem":518,
    "gn:feature_class":"P",
    "gn:feature_code":"PPL",
    "gn:name":"Baru Panw\u0101ri",
    "gn:population":0,
    "gn:timezone":"Asia/Kolkata",
    "iso:country":"IN",
    "wof:name":"Baru Panwari",
    "wof:placetype":"locality"
},
  "geometry": {"coordinates":[77.61206999999997,24.38483],"type":"Point"}
}