{
  "type": "Feature",
  "properties": {
    "iso:country":"IN",
    "ks:ks_name":"Kondap",
    "ks:ks_pop":75,
    "ks:ks_type":"HABITATION",
    "name:eng_x_preferred":[
        "Kondap"
    ],
    "wof:name":"Kondap",
    "wof:placetype":"locality",
    "wof:population":75
},
  "geometry": {"coordinates":[73.226474,18.658999],"type":"Point"}
}