{
  "type": "Feature",
  "properties": {
    "iso:country":"IN",
    "ks:ks_name":"Ghoshpur",
    "ks:ks_pop":67,
    "ks:ks_type":"VILLAGE",
    "name:eng_x_preferred":[
        "Ghoshpur"
    ],
    "wof:name":"Ghoshpur",
    "wof:placetype":"locality",
    "wof:population":67
},
  "geometry": {"coordinates":[87.780191,22.127204],"type":"Point"}
}