{
  "type": "Feature",
  "properties": {
    "iso:country":"IN",
    "ks:ks_alt_nam":"Gularia Haz\u0101ri L\u0101l",
    "ks:ks_alt_nam_2":"Gularia Hazari Lal",
    "ks:ks_name":"Gularia",
    "ks:ks_type":"VILLAGE",
    "name:eng_x_preferred":[
        "Gularia"
    ],
    "name:eng_x_variant":[
        "Gularia Haz\u0101ri L\u0101l",
        "Gularia Hazari Lal"
    ],
    "wof:name":"Gularia",
    "wof:placetype":"locality"
},
  "geometry": {"coordinates":[79.598043,28.272618],"type":"Point"}
}