{
  "type": "Feature",
  "properties": {
    "iso:country":"IN",
    "ks:ks_name":"Himmatpur",
    "ks:ks_pop":103,
    "ks:ks_type":"VILLAGE",
    "name:eng_x_preferred":[
        "Himmatpur"
    ],
    "wof:name":"Himmatpur",
    "wof:placetype":"locality",
    "wof:population":103
},
  "geometry": {"coordinates":[83.28295900000001,22.388932],"type":"Point"}
}