{
  "type": "Feature",
  "properties": {
    "iso:country":"IN",
    "ks:ks_name":"Hosagollarahatty",
    "ks:ks_pop":249,
    "ks:ks_type":"HABITATION",
    "name:eng_x_preferred":[
        "Hosagollarahatty"
    ],
    "wof:name":"Hosagollarahatty",
    "wof:placetype":"locality",
    "wof:population":249
},
  "geometry": {"coordinates":[76.360422,14.402968],"type":"Point"}
}