{
  "type": "Feature",
  "properties": {
    "iso:country":"IN",
    "ks:ks_name":"Kansalpat",
    "ks:ks_pop":0,
    "ks:ks_type":"VILLAGE",
    "name:eng_x_preferred":[
        "Kansalpat"
    ],
    "wof:name":"Kansalpat",
    "wof:placetype":"locality",
    "wof:population":0
},
  "geometry": {"coordinates":[86.064694,20.834236],"type":"Point"}
}