{
  "type": "Feature",
  "properties": {
    "iso:country":"IN",
    "ks:ks_name":"M.Timmapur",
    "ks:ks_pop":1110,
    "ks:ks_type":"VILLAGE",
    "name:eng_x_preferred":[
        "M.Timmapur"
    ],
    "wof:name":"M.Timmapur",
    "wof:placetype":"locality",
    "wof:population":1110
},
  "geometry": {"coordinates":[75.406858,15.933449],"type":"Point"}
}