{
  "type": "Feature",
  "properties": {
    "gn:admin1_code":"34.0",
    "gn:admin2_code":"232",
    "gn:asciiname":"Chilhar",
    "gn:country_code":"IN",
    "gn:dem":75,
    "gn:feature_class":"P",
    "gn:feature_code":"PPL",
    "gn:name":"Chilhar",
    "gn:population":0,
    "gn:timezone":"Asia/Kolkata",
    "iso:country":"IN",
    "name:und_x_variant":[
        "Chilh\u0101r"
    ],
    "wof:name":"Chilhar",
    "wof:placetype":"locality"
},
  "geometry": {"coordinates":[83.99257,25.41904],"type":"Point"}
}