{
  "type": "Feature",
  "properties": {
    "gn:admin1_code":"19.0",
    "gn:admin2_code":"555.0",
    "gn:asciiname":"Basarkhod",
    "gn:country_code":"IN",
    "gn:dem":723,
    "gn:feature_class":"P",
    "gn:feature_code":"PPL",
    "gn:name":"Basarkhod",
    "gn:population":0,
    "gn:timezone":"Asia/Kolkata",
    "iso:country":"IN",
    "name:vie_x_preferred":[
        "Basarkhod"
    ],
    "wof:name":"Basarkhod",
    "wof:placetype":"locality"
},
  "geometry": {"coordinates":[74.75533,15.58138],"type":"Point"}
}