{
  "type": "Feature",
  "properties": {
    "iso:country":"IN",
    "ks:ks_name":"Navakhola",
    "ks:ks_pop":821,
    "ks:ks_type":"VILLAGE",
    "name:eng_x_preferred":[
        "Navakhola"
    ],
    "wof:name":"Navakhola",
    "wof:placetype":"locality",
    "wof:population":821
},
  "geometry": {"coordinates":[73.195694,24.061389],"type":"Point"}
}