{
  "type": "Feature",
  "properties": {
    "iso:country":"IN",
    "ks:ks_name":"Edulagandi",
    "ks:ks_pop":55,
    "ks:ks_type":"HABITATION",
    "name:eng_x_preferred":[
        "Edulagandi"
    ],
    "wof:name":"Edulagandi",
    "wof:placetype":"locality",
    "wof:population":55
},
  "geometry": {"coordinates":[78.844257,16.907781],"type":"Point"}
}