{
  "type": "Feature",
  "properties": {
    "iso:country":"IN",
    "ks:ks_name":"Bhatoli",
    "ks:ks_pop":95,
    "ks:ks_type":"HABITATION",
    "name:eng_x_preferred":[
        "Bhatoli"
    ],
    "wof:name":"Bhatoli",
    "wof:placetype":"locality",
    "wof:population":95
},
  "geometry": {"coordinates":[79.105457,29.611698],"type":"Point"}
}