{
  "type": "Feature",
  "properties": {
    "gn:admin1_code":"35",
    "gn:admin2_code":"438.0",
    "gn:asciiname":"Baiganda",
    "gn:country_code":"IN",
    "gn:dem":503,
    "gn:feature_class":"P",
    "gn:feature_code":"PPL",
    "gn:name":"Baiganda",
    "gn:population":0,
    "gn:timezone":"Asia/Kolkata",
    "iso:country":"IN",
    "wof:name":"Baiganda",
    "wof:placetype":"locality"
},
  "geometry": {"coordinates":[75.28094,23.08282],"type":"Point"}
}