{
  "type": "Feature",
  "properties": {
    "iso:country":"IN",
    "ks:ks_name":"Chamaran Ka Purwa",
    "ks:ks_pop":84,
    "ks:ks_type":"HABITATION",
    "name:eng_x_preferred":[
        "Chamaran Ka Purwa"
    ],
    "wof:name":"Chamaran Ka Purwa",
    "wof:placetype":"locality",
    "wof:population":84
},
  "geometry": {"coordinates":[82.414546,26.860385],"type":"Point"}
}