{
  "type": "Feature",
  "properties": {
    "iso:country":"IN",
    "ks:ks_name":"Banjara Fali",
    "ks:ks_pop":80,
    "ks:ks_type":"HABITATION",
    "name:eng_x_preferred":[
        "Banjara Fali"
    ],
    "wof:name":"Banjara Fali",
    "wof:placetype":"locality",
    "wof:population":80
},
  "geometry": {"coordinates":[72.928978,24.379981],"type":"Point"}
}