{
  "type": "Feature",
  "properties": {
    "gn:admin1_code":"35.0",
    "gn:admin2_code":"424",
    "gn:asciiname":"Burkikhera",
    "gn:country_code":"IN",
    "gn:dem":343,
    "gn:feature_class":"P",
    "gn:feature_code":"PPL",
    "gn:name":"Burk\u012bkhera",
    "gn:population":0,
    "gn:timezone":"Asia/Kolkata",
    "iso:country":"IN",
    "wof:name":"Burkikhera",
    "wof:placetype":"locality"
},
  "geometry": {"coordinates":[78.95454000000002,24.69611],"type":"Point"}
}