{
  "type": "Feature",
  "properties": {
    "iso:country":"IN",
    "ks:ks_name":"Hotiya",
    "ks:ks_pop":0,
    "ks:ks_type":"VILLAGE",
    "name:eng_x_preferred":[
        "Hotiya"
    ],
    "wof:name":"Hotiya",
    "wof:placetype":"locality",
    "wof:population":0
},
  "geometry": {"coordinates":[69.93563899999999,26.716576],"type":"Point"}
}