{
  "type": "Feature",
  "properties": {
    "iso:country":"IN",
    "ks:ks_name":"Ambar Hol Wasti",
    "ks:ks_pop":140,
    "ks:ks_type":"HABITATION",
    "name:eng_x_preferred":[
        "Ambar Hol Wasti"
    ],
    "wof:name":"Ambar Hol Wasti",
    "wof:placetype":"locality",
    "wof:population":140
},
  "geometry": {"coordinates":[74.687157,18.227375],"type":"Point"}
}