{
  "type": "Feature",
  "properties": {
    "iso:country":"IN",
    "ks:ks_name":"Dunai",
    "ks:ks_pop":11,
    "ks:ks_type":"HABITATION",
    "name:eng_x_preferred":[
        "Dunai"
    ],
    "wof:name":"Dunai",
    "wof:placetype":"locality",
    "wof:population":11
},
  "geometry": {"coordinates":[79.83528200000001,29.750558],"type":"Point"}
}