{
  "type": "Feature",
  "properties": {
    "iso:country":"IN",
    "ks:ks_name":"Olek",
    "ks:ks_type":"VILLAGE",
    "name:eng_x_preferred":[
        "Olek"
    ],
    "wof:name":"Olek",
    "wof:placetype":"locality"
},
  "geometry": {"coordinates":[79.134936,29.657586],"type":"Point"}
}