{
  "type": "Feature",
  "properties": {
    "iso:country":"IN",
    "ks:ks_alt_nam":"DUWGA BASA",
    "ks:ks_name":"Duwga Basa",
    "ks:ks_pop":79,
    "ks:ks_type":"HABITATION",
    "name:eng_x_preferred":[
        "Duwga Basa"
    ],
    "wof:name":"Duwga Basa",
    "wof:placetype":"locality",
    "wof:population":79
},
  "geometry": {"coordinates":[85.400665,22.34736],"type":"Point"}
}