{
  "type": "Feature",
  "properties": {
    "gn:admin1_code":"19.0",
    "gn:admin2_code":"570.0",
    "gn:asciiname":"Karehalli",
    "gn:country_code":"IN",
    "gn:dem":678,
    "gn:feature_class":"P",
    "gn:feature_code":"PPL",
    "gn:name":"K\u0101rehalli",
    "gn:population":0,
    "gn:timezone":"Asia/Kolkata",
    "iso:country":"IN",
    "ks:ks_name":"Karahalli",
    "ks:ks_pop":44,
    "ks:ks_type":"HABITATION",
    "name:eng_x_preferred":[
        "Karahalli"
    ],
    "name:eng_x_variant":[
        "Karehalli"
    ],
    "wof:name":"Karahalli",
    "wof:placetype":"locality",
    "wof:population":44
},
  "geometry": {"coordinates":[75.50958900000001,13.601784],"type":"Point"}
}