{
  "type": "Feature",
  "properties": {
    "iso:country":"IN",
    "ks:ks_name":"Tola Jamhara",
    "ks:ks_pop":284,
    "ks:ks_type":"VILLAGE",
    "name:eng_x_preferred":[
        "Tola Jamhara"
    ],
    "wof:name":"Tola Jamhara",
    "wof:placetype":"locality",
    "wof:population":284
},
  "geometry": {"coordinates":[86.306929,24.504524],"type":"Point"}
}