{
  "type": "Feature",
  "properties": {
    "gn:admin1_code":"36.0",
    "gn:admin2_code":"155.0",
    "gn:asciiname":"Sauli",
    "gn:country_code":"IN",
    "gn:dem":146,
    "gn:feature_class":"P",
    "gn:feature_code":"PPL",
    "gn:name":"Sauli",
    "gn:population":0,
    "gn:timezone":"Asia/Kolkata",
    "iso:country":"IN",
    "name:deu_x_preferred":[
        "Sauli"
    ],
    "name:fin_x_preferred":[
        "Sauli"
    ],
    "name:rus_x_preferred":[
        "\u0421\u0430\u0443\u043b\u0438"
    ],
    "wof:name":"Sauli",
    "wof:placetype":"locality"
},
  "geometry": {"coordinates":[80.10159,27.34082],"type":"Point"}
}