{
  "type": "Feature",
  "properties": {
    "iso:country":"IN",
    "ks:ks_name":"Jandas",
    "ks:ks_pop":3422,
    "ks:ks_type":"HABITATION",
    "name:eng_x_preferred":[
        "Jandas"
    ],
    "wof:name":"Jandas",
    "wof:placetype":"locality",
    "wof:population":3422
},
  "geometry": {"coordinates":[88.822338,26.319383],"type":"Point"}
}