{
  "type": "Feature",
  "properties": {
    "iso:country":"IN",
    "ks:ks_name":"Kanhalgaon",
    "ks:ks_pop":71,
    "ks:ks_type":"HABITATION",
    "name:eng_x_preferred":[
        "Kanhalgaon"
    ],
    "wof:name":"Kanhalgaon",
    "wof:placetype":"locality",
    "wof:population":71
},
  "geometry": {"coordinates":[80.200265,20.05411],"type":"Point"}
}