{
  "type": "Feature",
  "properties": {
    "iso:country":"IN",
    "ks:ks_name":"Bamanjholi",
    "ks:ks_pop":39,
    "ks:ks_type":"HABITATION",
    "name:eng_x_preferred":[
        "Bamanjholi"
    ],
    "wof:name":"Bamanjholi",
    "wof:placetype":"locality",
    "wof:population":39
},
  "geometry": {"coordinates":[83.407713,19.912172],"type":"Point"}
}