{
  "type": "Feature",
  "properties": {
    "iso:country":"IN",
    "ks:ks_name":"Laxmanpur",
    "ks:ks_pop":440,
    "ks:ks_type":"HABITATION",
    "name:eng_x_preferred":[
        "Laxmanpur"
    ],
    "wof:name":"Laxmanpur",
    "wof:placetype":"locality",
    "wof:population":440
},
  "geometry": {"coordinates":[80.97526499999999,25.955741],"type":"Point"}
}