{
  "type": "Feature",
  "properties": {
    "iso:country":"IN",
    "ks:ks_name":"Harokhar",
    "ks:ks_pop":105,
    "ks:ks_type":"HABITATION",
    "name:eng_x_preferred":[
        "Harokhar"
    ],
    "wof:name":"Harokhar",
    "wof:placetype":"locality",
    "wof:population":105
},
  "geometry": {"coordinates":[81.06702900000001,27.237262],"type":"Point"}
}