{
  "type": "Feature",
  "properties": {
    "gn:admin1_code":"36.0",
    "gn:admin2_code":"156.0",
    "gn:asciiname":"Paramsukh Khera",
    "gn:country_code":"IN",
    "gn:dem":117,
    "gn:feature_class":"P",
    "gn:feature_code":"PPL",
    "gn:name":"Paramsukh Khera",
    "gn:population":0,
    "gn:timezone":"Asia/Kolkata",
    "iso:country":"IN",
    "ks:ks_name":"Paramusukh Kheda",
    "ks:ks_pop":1030,
    "ks:ks_type":"HABITATION",
    "ks:ks_uagg_main":0,
    "name:eng_x_preferred":[
        "Paramusukh Kheda"
    ],
    "wof:name":"Paramusukh Kheda",
    "wof:placetype":"locality",
    "wof:population":1030
},
  "geometry": {"coordinates":[80.40032600000001,26.476001],"type":"Point"}
}