{
  "type": "Feature",
  "properties": {
    "gn:admin1_code":"35.0",
    "gn:admin2_code":"424",
    "gn:asciiname":"Karmari",
    "gn:country_code":"IN",
    "gn:dem":355,
    "gn:feature_class":"P",
    "gn:feature_code":"PPL",
    "gn:name":"Karm\u0101ri",
    "gn:population":0,
    "gn:timezone":"Asia/Kolkata",
    "iso:country":"IN",
    "name:und_x_variant":[
        "Karm\u0101rai",
        "Karm\u0101ri"
    ],
    "wof:name":"Karmari",
    "wof:placetype":"locality"
},
  "geometry": {"coordinates":[78.78704999999999,24.64223],"type":"Point"}
}