{
  "type": "Feature",
  "properties": {
    "iso:country":"IN",
    "ks:ks_alt_nam":"ghodevasti",
    "ks:ks_name":"Ghodevasti",
    "ks:ks_pop":172,
    "ks:ks_type":"HABITATION",
    "name:eng_x_preferred":[
        "Ghodevasti"
    ],
    "wof:name":"Ghodevasti",
    "wof:placetype":"locality",
    "wof:population":172
},
  "geometry": {"coordinates":[74.61499999999999,18.1171],"type":"Point"}
}