{
  "type": "Feature",
  "properties": {
    "gn:admin1_code":"37",
    "gn:admin2_code":"406.0",
    "gn:asciiname":"Badgawan",
    "gn:country_code":"IN",
    "gn:dem":375,
    "gn:feature_class":"P",
    "gn:feature_code":"PPL",
    "gn:name":"Badgaw\u0101n",
    "gn:population":0,
    "gn:timezone":"Asia/Kolkata",
    "iso:country":"IN",
    "ks:ks_name":"Bargawan",
    "ks:ks_pop":754,
    "ks:ks_type":"VILLAGE",
    "name:eng_x_preferred":[
        "Bargawan"
    ],
    "name:eng_x_variant":[
        "Badgawan"
    ],
    "wof:name":"Bargawan",
    "wof:placetype":"locality",
    "wof:population":754
},
  "geometry": {"coordinates":[82.118477,22.54905],"type":"Point"}
}