{
  "type": "Feature",
  "properties": {
    "gn:admin1_code":"38",
    "gn:admin2_code":"359.0",
    "gn:asciiname":"Rewad Kalan",
    "gn:country_code":"IN",
    "gn:dem":431,
    "gn:feature_class":"P",
    "gn:feature_code":"PPL",
    "gn:name":"Rewad Kal\u0101n",
    "gn:population":0,
    "gn:timezone":"Asia/Kolkata",
    "iso:country":"IN",
    "name:und_x_variant":[
        "Reward",
        "Rewad",
        "Rewad Kal\u0101n"
    ],
    "wof:name":"Rewad Kalan",
    "wof:placetype":"locality"
},
  "geometry": {"coordinates":[84.50084,23.87341],"type":"Point"}
}