{
  "type": "Feature",
  "properties": {
    "gn:admin1_code":"11",
    "gn:admin2_code":"23.0",
    "gn:asciiname":"Dorar Adwar",
    "gn:country_code":"IN",
    "gn:dem":2881,
    "gn:feature_class":"P",
    "gn:feature_code":"PPL",
    "gn:name":"Dor\u0101r Adw\u0101r",
    "gn:population":0,
    "gn:timezone":"Asia/Kolkata",
    "iso:country":"IN",
    "wof:name":"Dorar Adwar",
    "wof:placetype":"locality"
},
  "geometry": {"coordinates":[76.19744,32.92234000000001],"type":"Point"}
}