{
  "type": "Feature",
  "properties": {
    "iso:country":"IN",
    "ks:ks_name":"Kherjan Forest Village",
    "ks:ks_pop":1095,
    "ks:ks_type":"HABITATION",
    "ks:ks_uagg_main":0,
    "name:eng_x_preferred":[
        "Kherjan Forest Village"
    ],
    "wof:name":"Kherjan Forest Village",
    "wof:placetype":"neighbourhood",
    "wof:population":1095
},
  "geometry": {"coordinates":[95.67939200000001,27.429041],"type":"Point"}
}