{
  "type": "Feature",
  "properties": {
    "iso:country":"IN",
    "ks:ks_alt_nam":"Chalagi vasti",
    "ks:ks_name":"Chalagi Vasti",
    "ks:ks_pop":150,
    "ks:ks_type":"HABITATION",
    "name:eng_x_preferred":[
        "Chalagi Vasti"
    ],
    "wof:name":"Chalagi Vasti",
    "wof:placetype":"locality",
    "wof:population":150
},
  "geometry": {"coordinates":[75.436154,16.9479],"type":"Point"}
}