{
  "type": "Feature",
  "properties": {
    "iso:country":"IN",
    "ks:ks_name":"Velamaguda",
    "ks:ks_pop":33,
    "ks:ks_type":"HABITATION",
    "name:eng_x_preferred":[
        "Velamaguda"
    ],
    "wof:name":"Velamaguda",
    "wof:placetype":"locality",
    "wof:population":33
},
  "geometry": {"coordinates":[83.905002,18.578712],"type":"Point"}
}