{
  "type": "Feature",
  "properties": {
    "gn:admin1_code":"23.0",
    "gn:admin2_code":"50.0",
    "gn:asciiname":"Kalla",
    "gn:country_code":"IN",
    "gn:dem":230,
    "gn:feature_class":"P",
    "gn:feature_code":"PPL",
    "gn:name":"Kalla",
    "gn:population":0,
    "gn:timezone":"Asia/Kolkata",
    "iso:country":"IN",
    "name:new_x_preferred":[
        "\u0915\u093e\u0932\u094d\u0932 \u092e\u0923\u094d\u0921\u0932"
    ],
    "name:tam_x_preferred":[
        "\u0b95\u0bbe\u0bb3\u0bcd\u0bb3\u0bbe"
    ],
    "name:tel_x_preferred":[
        "\u0c15\u0c3e\u0c33\u0c4d\u0c33"
    ],
    "wof:name":"Kalla",
    "wof:placetype":"locality"
},
  "geometry": {"coordinates":[75.04109,31.43763],"type":"Point"}
}