{
  "type": "Feature",
  "properties": {
    "gn:admin1_code":"36",
    "gn:admin2_code":"174.0",
    "gn:asciiname":"Diha Salempur",
    "gn:country_code":"IN",
    "gn:dem":100,
    "gn:feature_class":"P",
    "gn:feature_code":"PPL",
    "gn:name":"D\u012bha Salempur",
    "gn:population":0,
    "gn:timezone":"Asia/Kolkata",
    "iso:country":"IN",
    "ks:ks_name":"Deeha Salempur",
    "ks:ks_pop":0,
    "ks:ks_type":"VILLAGE",
    "name:eng_x_preferred":[
        "Deeha Salempur"
    ],
    "name:eng_x_variant":[
        "Diha Salempur"
    ],
    "wof:name":"Deeha Salempur",
    "wof:placetype":"locality",
    "wof:population":0
},
  "geometry": {"coordinates":[81.36069000000001,25.548886],"type":"Point"}
}