{
  "type": "Feature",
  "properties": {
    "iso:country":"IN",
    "ks:ks_name":"Kotenar",
    "ks:ks_pop":325,
    "ks:ks_type":"HABITATION",
    "name:eng_x_preferred":[
        "Kotenar"
    ],
    "wof:name":"Kotenar",
    "wof:placetype":"locality",
    "wof:population":325
},
  "geometry": {"coordinates":[81.103769,19.409542],"type":"Point"}
}