{
  "type": "Feature",
  "properties": {
    "gn:admin1_code":"25.0",
    "gn:admin2_code":"632.0",
    "gn:asciiname":"Appanayakkanpatti Pudur",
    "gn:country_code":"IN",
    "gn:dem":407,
    "gn:feature_class":"P",
    "gn:feature_code":"PPL",
    "gn:name":"Appan\u0101yakkanpatti Pud\u016br",
    "gn:population":0,
    "gn:timezone":"Asia/Kolkata",
    "iso:country":"IN",
    "wof:name":"Appanayakkanpatti Pudur",
    "wof:placetype":"locality"
},
  "geometry": {"coordinates":[77.13330999999999,10.96949],"type":"Point"}
}