{
  "type": "Feature",
  "properties": {
    "gn:admin1_code":"36.0",
    "gn:admin2_code":"150.0",
    "gn:asciiname":"Taha",
    "gn:country_code":"IN",
    "gn:dem":187,
    "gn:feature_class":"P",
    "gn:feature_code":"PPL",
    "gn:name":"T\u0101ha",
    "gn:population":0,
    "gn:timezone":"Asia/Kolkata",
    "iso:country":"IN",
    "name:ara_x_preferred":[
        "\u0637\u0647"
    ],
    "name:ceb_x_preferred":[
        "Taha"
    ],
    "name:deu_x_preferred":[
        "Taha"
    ],
    "name:fra_x_preferred":[
        "Taha"
    ],
    "name:heb_x_preferred":[
        "\u05d8\u05d0\u05d4\u05d0"
    ],
    "name:swe_x_preferred":[
        "Taha"
    ],
    "wof:name":"Taha",
    "wof:placetype":"locality"
},
  "geometry": {"coordinates":[79.49284,28.64475],"type":"Point"}
}