{
  "type": "Feature",
  "properties": {
    "gn:admin1_code":"36.0",
    "gn:admin2_code":"149",
    "gn:asciiname":"Allahpur",
    "gn:country_code":"IN",
    "gn:dem":164,
    "gn:feature_class":"P",
    "gn:feature_code":"PPL",
    "gn:name":"All\u0101hpur",
    "gn:population":0,
    "gn:timezone":"Asia/Kolkata",
    "iso:country":"IN",
    "name:fas_x_preferred":[
        "\u0627\u0644\u0644\u0647\u200c\u067e\u0648\u0631"
    ],
    "name:urd_x_preferred":[
        "\u0627\u0644\u0644\u06c1 \u067e\u0648\u0631"
    ],
    "wof:name":"Allahpur",
    "wof:placetype":"neighbourhood"
},
  "geometry": {"coordinates":[79.29671999999999,27.90244],"type":"Point"}
}