{
  "type": "Feature",
  "properties": {
    "gn:admin1_code":"11.0",
    "gn:admin2_code":"32.0",
    "gn:asciiname":"Madriya",
    "gn:country_code":"IN",
    "gn:dem":1873,
    "gn:feature_class":"P",
    "gn:feature_code":"PPL",
    "gn:name":"Madriya",
    "gn:population":0,
    "gn:timezone":"Asia/Kolkata",
    "iso:country":"IN",
    "wof:name":"Madriya",
    "wof:placetype":"locality"
},
  "geometry": {"coordinates":[77.33627,30.67987],"type":"Point"}
}