{
  "type": "Feature",
  "properties": {
    "iso:country":"IN",
    "ks:ks_alt_nam":"naniyatanr",
    "ks:ks_name":"Naniyatanr",
    "ks:ks_pop":327,
    "ks:ks_type":"HABITATION",
    "name:eng_x_preferred":[
        "Naniyatanr"
    ],
    "wof:name":"Naniyatanr",
    "wof:placetype":"locality",
    "wof:population":327
},
  "geometry": {"coordinates":[86.78383100000001,24.137296],"type":"Point"}
}