{
  "type": "Feature",
  "properties": {
    "iso:country":"IN",
    "ks:ks_name":"O Karisalkulam",
    "ks:ks_pop":377,
    "ks:ks_type":"HABITATION",
    "name:eng_x_preferred":[
        "O Karisalkulam"
    ],
    "wof:name":"O Karisalkulam",
    "wof:placetype":"locality",
    "wof:population":377
},
  "geometry": {"coordinates":[78.405248,9.325328],"type":"Point"}
}