{
  "type": "Feature",
  "properties": {
    "iso:country":"IN",
    "ks:ks_name":"Balau Jati",
    "ks:ks_pop":1538,
    "ks:ks_type":"VILLAGE",
    "name:eng_x_preferred":[
        "Balau Jati"
    ],
    "wof:name":"Balau Jati",
    "wof:placetype":"locality",
    "wof:population":1538
},
  "geometry": {"coordinates":[72.471136,26.283622],"type":"Point"}
}