{
  "type": "Feature",
  "properties": {
    "iso:country":"IN",
    "ks:ks_name":"Joyhari Para",
    "ks:ks_pop":639,
    "ks:ks_type":"HABITATION",
    "name:eng_x_preferred":[
        "Joyhari Para"
    ],
    "wof:name":"Joyhari Para",
    "wof:placetype":"locality",
    "wof:population":639
},
  "geometry": {"coordinates":[91.494882,23.305866],"type":"Point"}
}