{
  "type": "Feature",
  "properties": {
    "gn:admin1_code":"39.0",
    "gn:admin2_code":"57.0",
    "gn:asciiname":"Gar Kholi",
    "gn:country_code":"IN",
    "gn:dem":2496,
    "gn:feature_class":"P",
    "gn:feature_code":"PPL",
    "gn:name":"Gar Kholi",
    "gn:population":0,
    "gn:timezone":"Asia/Kolkata",
    "iso:country":"IN",
    "wof:name":"Gar Kholi",
    "wof:placetype":"locality"
},
  "geometry": {"coordinates":[79.64394,30.2613],"type":"Point"}
}