{
  "type": "Feature",
  "properties": {
    "gn:admin1_code":"25",
    "gn:admin2_code":"604.0",
    "gn:asciiname":"Pattarrankalani",
    "gn:country_code":"IN",
    "gn:dem":14,
    "gn:feature_class":"P",
    "gn:feature_code":"PPL",
    "gn:name":"Pattarrankalani",
    "gn:population":0,
    "gn:timezone":"Asia/Kolkata",
    "iso:country":"IN",
    "wof:name":"Pattarrankalani",
    "wof:placetype":"locality"
},
  "geometry": {"coordinates":[80.07333,12.52991],"type":"Point"}
}