{
  "type": "Feature",
  "properties": {
    "iso:country":"IN",
    "ks:ks_name":"Guchaguda",
    "ks:ks_pop":291,
    "ks:ks_type":"HABITATION",
    "name:eng_x_preferred":[
        "Guchaguda"
    ],
    "wof:name":"Guchaguda",
    "wof:placetype":"locality",
    "wof:population":291
},
  "geometry": {"coordinates":[82.303962,19.641626],"type":"Point"}
}