{
  "type": "Feature",
  "properties": {
    "iso:country":"IN",
    "ks:ks_name":"Tulai",
    "ks:ks_pop":767,
    "ks:ks_type":"VILLAGE",
    "name:eng_x_preferred":[
        "Tulai"
    ],
    "wof:name":"Tulai",
    "wof:placetype":"locality",
    "wof:population":767
},
  "geometry": {"coordinates":[73.509238,19.216973],"type":"Point"}
}