{
  "type": "Feature",
  "properties": {
    "gn:country":"IN",
    "gn:fcode":"PPL",
    "gn:population":40959,
    "iso:country":"IN",
    "ks:ks_alt_nam":"Jol\u0101rpettai",
    "ks:ks_name":"Jolarpettai",
    "ks:ks_type":"VILLAGE",
    "ks:ks_uagg_main":0,
    "name:eng_x_preferred":[
        "Jolarpettai"
    ],
    "name:eng_x_variant":[
        "Jol\u0101rpettai"
    ],
    "name:und_x_variant":[
        "Jal\u0101rpet"
    ],
    "qs:name":"Jol\u0101rpettai",
    "qs:photos_9r":0,
    "qs:photos_sr":0,
    "qs:pop_sr":"7",
    "wof:name":"Jolarpettai",
    "wof:placetype":"neighbourhood"
},
  "geometry": {"coordinates":[78.573185,12.570252],"type":"Point"}
}