{
  "type": "Feature",
  "properties": {
    "iso:country":"IN",
    "ks:ks_alt_nam":"KADAN PUR",
    "ks:ks_name":"Kadan Pur",
    "ks:ks_pop":150,
    "ks:ks_type":"HABITATION",
    "ks:ks_uagg_main":0,
    "name:eng_x_preferred":[
        "Kadan Pur"
    ],
    "wof:name":"Kadan Pur",
    "wof:placetype":"neighbourhood",
    "wof:population":150
},
  "geometry": {"coordinates":[81.88687899999999,26.527925],"type":"Point"}
}