{
  "type": "Feature",
  "properties": {
    "iso:country":"IN",
    "ks:ks_name":"Narauli",
    "ks:ks_type":"VILLAGE",
    "name:eng_x_preferred":[
        "Narauli"
    ],
    "wof:name":"Narauli",
    "wof:placetype":"locality"
},
  "geometry": {"coordinates":[81.43423799999999,27.263269],"type":"Point"}
}