{
  "type": "Feature",
  "properties": {
    "iso:country":"IN",
    "ks:ks_name":"Ghosko",
    "ks:ks_pop":175,
    "ks:ks_type":"VILLAGE",
    "name:eng_x_preferred":[
        "Ghosko"
    ],
    "wof:name":"Ghosko",
    "wof:placetype":"locality",
    "wof:population":175
},
  "geometry": {"coordinates":[85.959428,23.855744],"type":"Point"}
}