{
  "type": "Feature",
  "properties": {
    "gn:admin1_code":"35.0",
    "gn:admin2_code":"437.0",
    "gn:asciiname":"Panwasa",
    "gn:country_code":"IN",
    "gn:dem":551,
    "gn:feature_class":"P",
    "gn:feature_code":"PPL",
    "gn:name":"Panw\u0101sa",
    "gn:population":0,
    "gn:timezone":"Asia/Kolkata",
    "iso:country":"IN",
    "wof:name":"Panwasa",
    "wof:placetype":"locality"
},
  "geometry": {"coordinates":[76.15103000000001,22.73902],"type":"Point"}
}