{
  "type": "Feature",
  "properties": {
    "iso:country":"IN",
    "ks:ks_name":"Byateranganahalli",
    "ks:ks_pop":12,
    "ks:ks_type":"VILLAGE",
    "name:eng_x_preferred":[
        "Byateranganahalli"
    ],
    "wof:name":"Byateranganahalli",
    "wof:placetype":"locality",
    "wof:population":12
},
  "geometry": {"coordinates":[76.609881,13.361297],"type":"Point"}
}