{
  "type": "Feature",
  "properties": {
    "iso:country":"IN",
    "ks:ks_name":"Tatakawda",
    "ks:ks_pop":105,
    "ks:ks_type":"HABITATION",
    "name:eng_x_preferred":[
        "Tatakawda"
    ],
    "wof:name":"Tatakawda",
    "wof:placetype":"locality",
    "wof:population":105
},
  "geometry": {"coordinates":[78.994534,19.652775],"type":"Point"}
}