{
  "type": "Feature",
  "properties": {
    "iso:country":"IN",
    "ks:ks_name":"Surajpur",
    "ks:ks_pop":690,
    "ks:ks_type":"VILLAGE",
    "name:eng_x_preferred":[
        "Surajpur"
    ],
    "wof:name":"Surajpur",
    "wof:placetype":"locality",
    "wof:population":690
},
  "geometry": {"coordinates":[79.016685,28.644835],"type":"Point"}
}