{
  "type": "Feature",
  "properties": {
    "gn:admin1_code":"16",
    "gn:admin2_code":"506.0",
    "gn:asciiname":"Murmari Hamesha",
    "gn:country_code":"IN",
    "gn:dem":247,
    "gn:feature_class":"P",
    "gn:feature_code":"PPL",
    "gn:name":"Murm\u0101ri Hamesha",
    "gn:population":0,
    "gn:timezone":"Asia/Kolkata",
    "iso:country":"IN",
    "ks:ks_name":"Murmadi Hamesha",
    "ks:ks_pop":37,
    "ks:ks_type":"HABITATION",
    "name:eng_x_preferred":[
        "Murmadi Hamesha"
    ],
    "name:eng_x_variant":[
        "Murmari Hamesha"
    ],
    "wof:name":"Murmadi Hamesha",
    "wof:placetype":"locality",
    "wof:population":37
},
  "geometry": {"coordinates":[79.836781,20.944565],"type":"Point"}
}