{
  "type": "Feature",
  "properties": {
    "iso:country":"IN",
    "ks:ks_name":"Katkarwadi",
    "ks:ks_pop":227,
    "ks:ks_type":"HABITATION",
    "name:eng_x_preferred":[
        "Katkarwadi"
    ],
    "wof:name":"Katkarwadi",
    "wof:placetype":"locality",
    "wof:population":227
},
  "geometry": {"coordinates":[73.204787,18.878554],"type":"Point"}
}