{
  "type": "Feature",
  "properties": {
    "iso:country":"IN",
    "ks:ks_alt_nam":"PATRAPARA",
    "ks:ks_name":"Patrapara",
    "ks:ks_pop":204,
    "ks:ks_type":"HABITATION",
    "name:eng_x_preferred":[
        "Patrapara"
    ],
    "wof:name":"Patrapara",
    "wof:placetype":"locality",
    "wof:population":204
},
  "geometry": {"coordinates":[83.430211,22.657192],"type":"Point"}
}