{
  "type": "Feature",
  "properties": {
    "gn:admin1_code":"11.0",
    "gn:admin2_code":"32.0",
    "gn:asciiname":"Kogal",
    "gn:country_code":"IN",
    "gn:dem":1862,
    "gn:feature_class":"P",
    "gn:feature_code":"PPL",
    "gn:name":"Kogal",
    "gn:population":0,
    "gn:timezone":"Asia/Kolkata",
    "iso:country":"IN",
    "name:deu_x_preferred":[
        "Kogal"
    ],
    "name:fra_x_preferred":[
        "Kogal"
    ],
    "name:hun_x_preferred":[
        "Kogal"
    ],
    "name:ind_x_preferred":[
        "Kogal"
    ],
    "name:ita_x_preferred":[
        "Kogal"
    ],
    "name:jpn_x_preferred":[
        "\u30b3\u30ae\u30e3\u30eb"
    ],
    "name:por_x_preferred":[
        "Kogal"
    ],
    "name:rus_x_preferred":[
        "\u041a\u043e\u0433\u044f\u0440\u0443"
    ],
    "wof:name":"Kogal",
    "wof:placetype":"locality"
},
  "geometry": {"coordinates":[77.48151,30.77221],"type":"Point"}
}