{
  "type": "Feature",
  "properties": {
    "gn:admin1_code":"40",
    "gn:admin2_code":"538.0",
    "gn:asciiname":"Bijjaram",
    "gn:country_code":"IN",
    "gn:dem":500,
    "gn:feature_class":"P",
    "gn:feature_code":"PPL",
    "gn:name":"Bijj\u0101ram",
    "gn:population":0,
    "gn:timezone":"Asia/Kolkata",
    "iso:country":"IN",
    "wof:name":"Bijjaram",
    "wof:placetype":"locality"
},
  "geometry": {"coordinates":[77.68239,16.96497999999999],"type":"Point"}
}