{
  "type": "Feature",
  "properties": {
    "iso:country":"IN",
    "ks:ks_name":"Chalivendra",
    "ks:ks_pop":46,
    "ks:ks_type":"HABITATION",
    "name:eng_x_preferred":[
        "Chalivendra"
    ],
    "wof:name":"Chalivendra",
    "wof:placetype":"locality",
    "wof:population":46
},
  "geometry": {"coordinates":[80.029443,13.76416],"type":"Point"}
}