{
  "type": "Feature",
  "properties": {
    "iso:country":"IN",
    "ks:ks_alt_nam":"pallimukku",
    "ks:ks_name":"Pallimukku",
    "ks:ks_pop":1827,
    "ks:ks_type":"HABITATION",
    "name:eng_x_preferred":[
        "Pallimukku"
    ],
    "wof:name":"Pallimukku",
    "wof:placetype":"locality",
    "wof:population":1827
},
  "geometry": {"coordinates":[75.675404,11.611802],"type":"Point"}
}