{
  "type": "Feature",
  "properties": {
    "gn:admin1_code":"25.0",
    "gn:admin2_code":"630.0",
    "gn:asciiname":"Toppampatti",
    "gn:country_code":"IN",
    "gn:dem":414,
    "gn:feature_class":"P",
    "gn:feature_code":"PPL",
    "gn:name":"Toppampatti",
    "gn:population":0,
    "gn:timezone":"Asia/Kolkata",
    "iso:country":"IN",
    "ks:ks_name":"Thoppampatti",
    "ks:ks_pop":235,
    "ks:ks_type":"VILLAGE",
    "ks:ks_uagg_main":0,
    "name:eng_x_preferred":[
        "Thoppampatti"
    ],
    "wof:name":"Thoppampatti",
    "wof:placetype":"locality",
    "wof:population":235
},
  "geometry": {"coordinates":[78.386368,12.134537],"type":"Point"}
}