{
  "type": "Feature",
  "properties": {
    "iso:country":"IN",
    "ks:ks_name":"Ghutanvad",
    "ks:ks_pop":1778,
    "ks:ks_type":"VILLAGE",
    "name:eng_x_preferred":[
        "Ghutanvad"
    ],
    "wof:name":"Ghutanvad",
    "wof:placetype":"locality",
    "wof:population":1778
},
  "geometry": {"coordinates":[73.86610899999999,22.40901],"type":"Point"}
}