{
  "type": "Feature",
  "properties": {
    "iso:country":"IN",
    "ks:ks_name":"Rajendra Para",
    "ks:ks_pop":77,
    "ks:ks_type":"HABITATION",
    "name:eng_x_preferred":[
        "Rajendra Para"
    ],
    "wof:name":"Rajendra Para",
    "wof:placetype":"locality",
    "wof:population":77
},
  "geometry": {"coordinates":[91.431726,24.079554],"type":"Point"}
}