{
  "type": "Feature",
  "properties": {
    "iso:country":"IN",
    "ks:ks_name":"Kona Forest",
    "ks:ks_pop":15537,
    "ks:ks_type":"VILLAGE",
    "name:eng_x_preferred":[
        "Kona Forest"
    ],
    "wof:name":"Kona Forest",
    "wof:placetype":"locality",
    "wof:population":15537
},
  "geometry": {"coordinates":[82.472925,17.209988],"type":"Point"}
}