{
  "type": "Feature",
  "properties": {
    "iso:country":"IN",
    "ks:ks_name":"Sajai S.c. Basti",
    "ks:ks_pop":289,
    "ks:ks_type":"HABITATION",
    "name:eng_x_preferred":[
        "Sajai S.c. Basti"
    ],
    "wof:name":"Sajai S.c. Basti",
    "wof:placetype":"locality",
    "wof:population":289
},
  "geometry": {"coordinates":[82.74723,26.067641],"type":"Point"}
}