{
  "type": "Feature",
  "properties": {
    "gn:admin1_code":"25.0",
    "gn:admin2_code":"613.0",
    "gn:asciiname":"Kuntanippalaiyam",
    "gn:country_code":"IN",
    "gn:dem":148,
    "gn:feature_class":"P",
    "gn:feature_code":"PPL",
    "gn:name":"Kunt\u0101nipp\u0101laiyam",
    "gn:population":0,
    "gn:timezone":"Asia/Kolkata",
    "iso:country":"IN",
    "wof:name":"Kuntanippalaiyam",
    "wof:placetype":"neighbourhood"
},
  "geometry": {"coordinates":[77.94148,11.02998],"type":"Point"}
}