{
  "type": "Feature",
  "properties": {
    "iso:country":"IN",
    "name:eng_x_preferred":[
        "Amaravathy"
    ],
    "qs:gn_fcode":"PPL",
    "qs:gn_local":0,
    "qs:gn_namadm1":"13",
    "qs:gn_name":"Amaravathy",
    "qs:local_max":3383,
    "qs:local_sum":8346,
    "qs:localhoods":12,
    "qs:name":"Amaravathy",
    "qs:name_adm0":"India",
    "qs:name_adm1":"Kerala",
    "qs:name_adm2":"Ernakulam",
    "qs:name_local":"Kochi",
    "qs:photo_max":100,
    "qs:photo_sum":379,
    "qs:placetype":"Suburb",
    "qs:quad_count":11,
    "qs:woe_adm0":23424848,
    "qs:woe_adm1":2345747,
    "qs:woe_adm2":12586468,
    "qs:woe_lau":0,
    "qs:woe_local":2295423,
    "qs:woe_ver":"7.10.0",
    "wof:lang":[
        "eng"
    ],
    "wof:name":"Amaravathy",
    "wof:placetype":"neighbourhood"
},
  "geometry": {"coordinates":[76.24879300000001,9.959293],"type":"Point"}
}