{
  "type": "Feature",
  "properties": {
    "iso:country":"IN",
    "name:ara_x_preferred":[
        "\u0623\u0645\u0631\u0627\u0641\u0627\u062a\u064a"
    ],
    "name:ben_bn_x_preferred":[
        "\u0985\u09ae\u09b0\u09be\u09ac\u09a4\u09c0"
    ],
    "name:ben_in_x_preferred":[
        "\u0985\u09ae\u09b0\u09be\u09ac\u09a4\u09c0"
    ],
    "name:eng_x_preferred":[
        "Amaravathy"
    ],
    "name:guj_x_preferred":[
        "\u0a85\u0aae\u0acd\u0ab0\u0abe\u0ab5\u0aa4\u0ac0"
    ],
    "name:hin_x_preferred":[
        "\u0905\u092e\u0930\u093e\u0935\u0924\u0940"
    ],
    "name:kan_x_preferred":[
        "\u0c85\u0cae\u0cb0\u0cbe\u0cb5\u0ca4\u0cbf"
    ],
    "name:mal_x_preferred":[
        "\u0d05\u0d2e\u0d30\u0d3e\u0d35\u0d24\u0d3f"
    ],
    "name:mar_x_preferred":[
        "\u0905\u092e\u0930\u093e\u0935\u0924\u0940"
    ],
    "name:pan_x_preferred":[
        "\u0a05\u0a2e\u0a30\u0a3e\u0a35\u0a24\u0a40"
    ],
    "name:tam_x_preferred":[
        "\u0b85\u0bae\u0bb0\u0bbe\u0bb5\u0ba4\u0bbf"
    ],
    "name:tel_x_preferred":[
        "\u0c05\u0c2e\u0c30\u0c3e\u0c35\u0c24\u0c3f"
    ],
    "name:urd_x_preferred":[
        "\u0627\u0645\u0631\u0627\u0624\u062a\u06cc"
    ],
    "qs:gn_fcode":"PPL",
    "qs:gn_local":0,
    "qs:gn_namadm1":"13",
    "qs:gn_name":"Amaravathy",
    "qs:local_max":3383,
    "qs:local_sum":8346,
    "qs:localhoods":12,
    "qs:name":"Amaravathy",
    "qs:name_adm0":"India",
    "qs:name_adm1":"Kerala",
    "qs:name_adm2":"Ernakulam",
    "qs:name_local":"Kochi",
    "qs:photo_max":100,
    "qs:photo_sum":379,
    "qs:placetype":"Suburb",
    "qs:quad_count":11,
    "qs:woe_adm0":23424848,
    "qs:woe_adm1":2345747,
    "qs:woe_adm2":12586468,
    "qs:woe_lau":0,
    "qs:woe_local":2295423,
    "qs:woe_ver":"7.10.0",
    "wof:lang":[
        "eng"
    ],
    "wof:name":"Amaravathy",
    "wof:placetype":"neighbourhood"
},
  "geometry": {"coordinates":[76.24879300000001,9.959293],"type":"Point"}
}