{
  "type": "Feature",
  "properties": {
    "gn:admin1_code":"35",
    "gn:admin2_code":"430.0",
    "gn:asciiname":"Nakti",
    "gn:country_code":"IN",
    "gn:dem":344,
    "gn:feature_class":"P",
    "gn:feature_code":"PPL",
    "gn:name":"Nakti",
    "gn:population":0,
    "gn:timezone":"Asia/Kolkata",
    "iso:country":"IN",
    "ks:ks_name":"Nakati",
    "ks:ks_pop":272,
    "ks:ks_type":"VILLAGE",
    "name:eng_x_preferred":[
        "Nakati"
    ],
    "name:eng_x_variant":[
        "Nakti"
    ],
    "wof:name":"Nakati",
    "wof:placetype":"locality",
    "wof:population":272
},
  "geometry": {"coordinates":[81.890362,24.738797],"type":"Point"}
}