{
  "type": "Feature",
  "properties": {
    "gn:admin1_code":"35",
    "gn:admin2_code":"430.0",
    "gn:asciiname":"Nakti",
    "gn:country_code":"IN",
    "gn:dem":344,
    "gn:feature_class":"P",
    "gn:feature_code":"PPL",
    "gn:name":"Nakti",
    "gn:population":0,
    "gn:timezone":"Asia/Kolkata",
    "iso:country":"IN",
    "wof:name":"Nakti",
    "wof:placetype":"locality"
},
  "geometry": {"coordinates":[81.88951,24.7382],"type":"Point"}
}