{
  "type": "Feature",
  "properties": {
    "iso:country":"IN",
    "ks:ks_name":"Sadhu Mog Para",
    "ks:ks_pop":118,
    "ks:ks_type":"HABITATION",
    "name:eng_x_preferred":[
        "Sadhu Mog Para"
    ],
    "wof:name":"Sadhu Mog Para",
    "wof:placetype":"locality",
    "wof:population":118
},
  "geometry": {"coordinates":[91.783697,23.202253],"type":"Point"}
}