{
  "type": "Feature",
  "properties": {
    "iso:country":"IN",
    "ks:ks_name":"Panasaguda",
    "ks:ks_pop":156,
    "ks:ks_type":"VILLAGE",
    "name:eng_x_preferred":[
        "Panasaguda"
    ],
    "wof:name":"Panasaguda",
    "wof:placetype":"locality",
    "wof:population":156
},
  "geometry": {"coordinates":[83.287136,19.412973],"type":"Point"}
}