{
  "type": "Feature",
  "properties": {
    "iso:country":"IN",
    "ks:ks_name":"Kaliana Kamat",
    "ks:ks_pop":430,
    "ks:ks_type":"HABITATION",
    "ks:ks_uagg_main":0,
    "name:eng_x_preferred":[
        "Kaliana Kamat"
    ],
    "wof:name":"Kaliana Kamat",
    "wof:placetype":"neighbourhood",
    "wof:population":430
},
  "geometry": {"coordinates":[87.047264,25.78974],"type":"Point"}
}