{
  "type": "Feature",
  "properties": {
    "iso:country":"IN",
    "ks:ks_name":"Narsimha Nagar T",
    "ks:ks_pop":240,
    "ks:ks_type":"HABITATION",
    "name:eng_x_preferred":[
        "Narsimha Nagar T"
    ],
    "wof:name":"Narsimha Nagar T",
    "wof:placetype":"locality",
    "wof:population":240
},
  "geometry": {"coordinates":[78.034166,19.02569],"type":"Point"}
}