{
  "type": "Feature",
  "properties": {
    "iso:country":"IN",
    "ks:ks_name":"Chaudhary Purwa",
    "ks:ks_pop":66,
    "ks:ks_type":"HABITATION",
    "name:eng_x_preferred":[
        "Chaudhary Purwa"
    ],
    "wof:name":"Chaudhary Purwa",
    "wof:placetype":"locality",
    "wof:population":66
},
  "geometry": {"coordinates":[82.660174,26.865914],"type":"Point"}
}