{
  "type": "Feature",
  "properties": {
    "iso:country":"IN",
    "ks:ks_name":"Mettupatti",
    "ks:ks_pop":238,
    "ks:ks_type":"HABITATION",
    "name:eng_x_preferred":[
        "Mettupatti"
    ],
    "wof:name":"Mettupatti",
    "wof:placetype":"locality",
    "wof:population":238
},
  "geometry": {"coordinates":[78.520416,10.67611],"type":"Point"}
}