{
  "type": "Feature",
  "properties": {
    "gn:admin1_code":"19.0",
    "gn:admin2_code":"581.0",
    "gn:asciiname":"Picheguthalli",
    "gn:country_code":"IN",
    "gn:dem":846,
    "gn:feature_class":"P",
    "gn:feature_code":"PPL",
    "gn:name":"Picheguthalli",
    "gn:population":0,
    "gn:timezone":"Asia/Kolkata",
    "iso:country":"IN",
    "wof:name":"Picheguthalli",
    "wof:placetype":"neighbourhood"
},
  "geometry": {"coordinates":[78.01291999999999,12.87282],"type":"Point"}
}