{
  "type": "Feature",
  "properties": {
    "gn:admin1_code":"36.0",
    "gn:admin2_code":"192.0",
    "gn:asciiname":"Habibpur Niamatpur",
    "gn:country_code":"IN",
    "gn:dem":74,
    "gn:feature_class":"P",
    "gn:feature_code":"PPL",
    "gn:name":"Hab\u012bbpur Ni\u0101matpur",
    "gn:population":0,
    "gn:timezone":"Asia/Kolkata",
    "iso:country":"IN",
    "wof:name":"Habibpur Niamatpur",
    "wof:placetype":"locality"
},
  "geometry": {"coordinates":[83.76926999999998,26.11722],"type":"Point"}
}