{
  "type": "Feature",
  "properties": {
    "iso:country":"IN",
    "ks:ks_name":"Mahadev Gonish Land",
    "ks:ks_pop":100,
    "ks:ks_type":"HABITATION",
    "name:eng_x_preferred":[
        "Mahadev Gonish Land"
    ],
    "wof:name":"Mahadev Gonish Land",
    "wof:placetype":"locality",
    "wof:population":100
},
  "geometry": {"coordinates":[74.815893,15.268012],"type":"Point"}
}