{
  "type": "Feature",
  "properties": {
    "gn:admin1_code":"23.0",
    "gn:admin2_code":"38.0",
    "gn:asciiname":"Pandori Mindomind",
    "gn:country_code":"IN",
    "gn:dem":276,
    "gn:feature_class":"P",
    "gn:feature_code":"PPL",
    "gn:name":"Pandori Mindomind",
    "gn:population":0,
    "gn:timezone":"Asia/Kolkata",
    "iso:country":"IN",
    "ks:ks_name":"Pandori Mindomind",
    "ks:ks_pop":153,
    "ks:ks_type":"VILLAGE",
    "ks:ks_uagg_main":0,
    "name:eng_x_preferred":[
        "Pandori Mindomind"
    ],
    "wof:name":"Pandori Mindomind",
    "wof:placetype":"neighbourhood",
    "wof:population":153
},
  "geometry": {"coordinates":[75.814627,31.55576],"type":"Point"}
}