{
  "type": "Feature",
  "properties": {
    "iso:country":"IN",
    "ks:ks_name":"Mahrapara\t",
    "ks:ks_pop":75,
    "ks:ks_type":"HABITATION",
    "name:eng_x_preferred":[
        "Mahrapara\t"
    ],
    "wof:name":"Mahrapara\t",
    "wof:placetype":"locality",
    "wof:population":75
},
  "geometry": {"coordinates":[81.73043800000001,18.499292],"type":"Point"}
}