{
  "type": "Feature",
  "properties": {
    "gn:admin1_code":"24.0",
    "gn:admin2_code":"105.0",
    "gn:asciiname":"Nagla Kulwana",
    "gn:country_code":"IN",
    "gn:dem":187,
    "gn:feature_class":"P",
    "gn:feature_code":"PPL",
    "gn:name":"Nagla Kulw\u0101na",
    "gn:population":0,
    "gn:timezone":"Asia/Kolkata",
    "iso:country":"IN",
    "wof:name":"Nagla Kulwana",
    "wof:placetype":"locality"
},
  "geometry": {"coordinates":[77.30750999999999,27.68195],"type":"Point"}
}