{
  "type": "Feature",
  "properties": {
    "iso:country":"IN",
    "ks:ks_name":"Kariyagoundenpudur",
    "ks:ks_pop":250,
    "ks:ks_type":"HABITATION",
    "name:eng_x_preferred":[
        "Kariyagoundenpudur"
    ],
    "wof:name":"Kariyagoundenpudur",
    "wof:placetype":"locality",
    "wof:population":250
},
  "geometry": {"coordinates":[77.129126,11.487908],"type":"Point"}
}