{
  "type": "Feature",
  "properties": {
    "gn:admin1_code":"24",
    "gn:admin2_code":"104.0",
    "gn:asciiname":"Shehzadpur",
    "gn:country_code":"IN",
    "gn:dem":295,
    "gn:feature_class":"P",
    "gn:feature_code":"PPL",
    "gn:name":"Shehz\u0101dp\u016br",
    "gn:population":0,
    "gn:timezone":"Asia/Kolkata",
    "iso:country":"IN",
    "wof:name":"Shehzadpur",
    "wof:placetype":"locality"
},
  "geometry": {"coordinates":[76.48125,27.92985],"type":"Point"}
}