{
  "type": "Feature",
  "properties": {
    "gn:admin1_code":"35",
    "gn:admin2_code":"428.0",
    "gn:asciiname":"Bandarkola",
    "gn:country_code":"IN",
    "gn:dem":374,
    "gn:feature_class":"P",
    "gn:feature_code":"PPL",
    "gn:name":"Bandarkola",
    "gn:population":0,
    "gn:timezone":"Asia/Kolkata",
    "iso:country":"IN",
    "ks:ks_name":"Bandar Kola",
    "ks:ks_pop":190,
    "ks:ks_type":"HABITATION",
    "name:eng_x_preferred":[
        "Bandar Kola"
    ],
    "name:eng_x_variant":[
        "Bandarkola"
    ],
    "wof:name":"Bandar Kola",
    "wof:placetype":"locality",
    "wof:population":190
},
  "geometry": {"coordinates":[79.711737,23.557408],"type":"Point"}
}