{
  "type": "Feature",
  "properties": {
    "iso:country":"IN",
    "ks:ks_alt_nam":"MAHADEVTIKRA",
    "ks:ks_name":"Mahadevtikra",
    "ks:ks_pop":483,
    "ks:ks_type":"HABITATION",
    "name:eng_x_preferred":[
        "Mahadevtikra"
    ],
    "wof:name":"Mahadevtikra",
    "wof:placetype":"locality",
    "wof:population":483
},
  "geometry": {"coordinates":[83.47179300000001,22.586023],"type":"Point"}
}