{
  "type": "Feature",
  "properties": {
    "iso:country":"IN",
    "ks:ks_name":"Duradadi",
    "ks:ks_pop":83,
    "ks:ks_type":"VILLAGE",
    "name:eng_x_preferred":[
        "Duradadi"
    ],
    "wof:name":"Duradadi",
    "wof:placetype":"locality",
    "wof:population":83
},
  "geometry": {"coordinates":[83.987036,20.191481],"type":"Point"}
}