{
  "type": "Feature",
  "properties": {
    "gn:admin1_code":"19.0",
    "gn:admin2_code":"568.0",
    "gn:asciiname":"Koradi",
    "gn:country_code":"IN",
    "gn:dem":639,
    "gn:feature_class":"P",
    "gn:feature_code":"PPL",
    "gn:name":"Koradi",
    "gn:population":0,
    "gn:timezone":"Asia/Kolkata",
    "iso:country":"IN",
    "wof:name":"Koradi",
    "wof:placetype":"locality"
},
  "geometry": {"coordinates":[75.19558000000001,13.71031],"type":"Point"}
}