{
  "type": "Feature",
  "properties": {
    "iso:country":"IN",
    "ks:ks_name":"1 CLD",
    "ks:ks_pop":297,
    "ks:ks_type":"VILLAGE",
    "name:eng_x_preferred":[
        "1 CLD"
    ],
    "wof:name":"1 CLD",
    "wof:placetype":"locality",
    "wof:population":297
},
  "geometry": {"coordinates":[74.245491,29.226613],"type":"Point"}
}