{
  "type": "Feature",
  "properties": {
    "gn:admin1_code":"19.0",
    "gn:admin2_code":"576.0",
    "gn:asciiname":"Ippugalale",
    "gn:country_code":"IN",
    "gn:dem":919,
    "gn:feature_class":"P",
    "gn:feature_code":"PPL",
    "gn:name":"Ippugalale",
    "gn:population":0,
    "gn:timezone":"Asia/Kolkata",
    "iso:country":"IN",
    "wof:name":"Ippugalale",
    "wof:placetype":"locality"
},
  "geometry": {"coordinates":[75.93629,12.79926],"type":"Point"}
}