{
  "type": "Feature",
  "properties": {
    "iso:country":"IN",
    "ks:ks_name":"Lahas",
    "ks:ks_pop":927,
    "ks:ks_type":"HABITATION",
    "name:eng_x_preferred":[
        "Lahas"
    ],
    "wof:name":"Lahas",
    "wof:placetype":"locality",
    "wof:population":927
},
  "geometry": {"coordinates":[82.834879,24.889182],"type":"Point"}
}