{
  "type": "Feature",
  "properties": {
    "iso:country":"IN",
    "ks:ks_name":"Chatra",
    "ks:ks_pop":287,
    "ks:ks_type":"HABITATION",
    "name:eng_x_preferred":[
        "Chatra"
    ],
    "wof:name":"Chatra",
    "wof:placetype":"locality",
    "wof:population":287
},
  "geometry": {"coordinates":[74.997546,12.955585],"type":"Point"}
}