{
  "type": "Feature",
  "properties": {
    "iso:country":"IN",
    "ks:ks_name":"Kesari",
    "ks:ks_pop":484,
    "ks:ks_type":"HABITATION",
    "name:eng_x_preferred":[
        "Kesari"
    ],
    "wof:name":"Kesari",
    "wof:placetype":"locality",
    "wof:population":484
},
  "geometry": {"coordinates":[82.991276,27.358813],"type":"Point"}
}