{
  "type": "Feature",
  "properties": {
    "iso:country":"IN",
    "ks:ks_alt_nam":"Laskar and Molla Para",
    "ks:ks_name":"Laskar And Molla Para",
    "ks:ks_pop":1000,
    "ks:ks_type":"HABITATION",
    "name:eng_x_preferred":[
        "Laskar And Molla Para"
    ],
    "wof:name":"Laskar And Molla Para",
    "wof:placetype":"locality",
    "wof:population":1000
},
  "geometry": {"coordinates":[88.51873000000001,22.134477],"type":"Point"}
}