{
  "type": "Feature",
  "properties": {
    "iso:country":"IN",
    "ks:ks_name":"Bara Karanji",
    "ks:ks_pop":477,
    "ks:ks_type":"VILLAGE",
    "name:eng_x_preferred":[
        "Bara Karanji"
    ],
    "wof:name":"Bara Karanji",
    "wof:placetype":"locality",
    "wof:population":477
},
  "geometry": {"coordinates":[87.507667,22.388865],"type":"Point"}
}