{
  "type": "Feature",
  "properties": {
    "gn:admin1_code":"19.0",
    "gn:admin2_code":"574.0",
    "gn:asciiname":"Bogarahalli",
    "gn:country_code":"IN",
    "gn:dem":1002,
    "gn:feature_class":"P",
    "gn:feature_code":"PPL",
    "gn:name":"Bogarahalli",
    "gn:population":0,
    "gn:timezone":"Asia/Kolkata",
    "iso:country":"IN",
    "wof:name":"Bogarahalli",
    "wof:placetype":"locality"
},
  "geometry": {"coordinates":[76.12889,13.11177],"type":"Point"}
}