{
  "type": "Feature",
  "properties": {
    "gn:admin1_code":"38.0",
    "gn:admin2_code":"352.0",
    "gn:asciiname":"Pokharia",
    "gn:country_code":"IN",
    "gn:dem":153,
    "gn:feature_class":"P",
    "gn:feature_code":"PPL",
    "gn:name":"Pokh\u0101ria",
    "gn:population":0,
    "gn:timezone":"Asia/Kolkata",
    "iso:country":"IN",
    "name:hif_x_preferred":[
        "Pokharia"
    ],
    "wof:name":"Pokharia",
    "wof:placetype":"locality"
},
  "geometry": {"coordinates":[87.63265,25.18593],"type":"Point"}
}