{
  "type": "Feature",
  "properties": {
    "iso:country":"IN",
    "ks:ks_name":"Alupatna",
    "ks:ks_pop":432,
    "ks:ks_type":"VILLAGE",
    "ks:ks_uagg_main":0,
    "name:eng_x_preferred":[
        "Alupatna"
    ],
    "wof:name":"Alupatna",
    "wof:placetype":"neighbourhood",
    "wof:population":432
},
  "geometry": {"coordinates":[85.45153000000001,19.662657],"type":"Point"}
}