{
  "type": "Feature",
  "properties": {
    "iso:country":"IN",
    "ks:ks_name":"Nanakgang Grrnt",
    "ks:ks_pop":5490,
    "ks:ks_type":"VILLAGE",
    "ks:ks_uagg_main":0,
    "name:eng_x_preferred":[
        "Nanakgang Grrnt"
    ],
    "wof:name":"Nanakgang Grrnt",
    "wof:placetype":"locality",
    "wof:population":5490
},
  "geometry": {"coordinates":[80.151837,27.370449],"type":"Point"}
}