{
  "type": "Feature",
  "properties": {
    "gn:admin1_code":"36",
    "gn:admin2_code":"191.0",
    "gn:asciiname":"Chaube Patti",
    "gn:country_code":"IN",
    "gn:dem":87,
    "gn:feature_class":"P",
    "gn:feature_code":"PPL",
    "gn:name":"Chaube Patti",
    "gn:population":0,
    "gn:timezone":"Asia/Kolkata",
    "iso:country":"IN",
    "ks:ks_name":"Chaube Patti",
    "ks:ks_pop":259,
    "ks:ks_type":"VILLAGE",
    "ks:ks_uagg_main":0,
    "name:eng_x_preferred":[
        "Chaube Patti"
    ],
    "wof:name":"Chaube Patti",
    "wof:placetype":"neighbourhood",
    "wof:population":259
},
  "geometry": {"coordinates":[82.94781500000001,26.20502],"type":"Point"}
}