{
  "type": "Feature",
  "properties": {
    "iso:country":"IN",
    "ks:ks_name":"Madhabpur",
    "ks:ks_pop":379,
    "ks:ks_type":"VILLAGE",
    "name:eng_x_preferred":[
        "Madhabpur"
    ],
    "wof:name":"Madhabpur",
    "wof:placetype":"locality",
    "wof:population":379
},
  "geometry": {"coordinates":[87.75047499999999,21.719626],"type":"Point"}
}