{
  "type": "Feature",
  "properties": {
    "iso:country":"IN",
    "ks:ks_name":"Kasarwadi",
    "ks:ks_pop":106,
    "ks:ks_type":"HABITATION",
    "name:eng_x_preferred":[
        "Kasarwadi"
    ],
    "wof:name":"Kasarwadi",
    "wof:placetype":"locality",
    "wof:population":106
},
  "geometry": {"coordinates":[75.046492,18.333056],"type":"Point"}
}