{
  "type": "Feature",
  "properties": {
    "iso:country":"IN",
    "ks:ks_name":"Kamarpur Arazi",
    "ks:ks_pop":916,
    "ks:ks_type":"VILLAGE",
    "ks:ks_uagg_main":0,
    "name:eng_x_preferred":[
        "Kamarpur Arazi"
    ],
    "wof:name":"Kamarpur Arazi",
    "wof:placetype":"neighbourhood",
    "wof:population":916
},
  "geometry": {"coordinates":[86.726626,25.19086],"type":"Point"}
}