{
  "type": "Feature",
  "properties": {
    "iso:country":"IN",
    "ks:ks_name":"Meghadih",
    "ks:ks_pop":173,
    "ks:ks_type":"VILLAGE",
    "name:eng_x_preferred":[
        "Meghadih"
    ],
    "wof:name":"Meghadih",
    "wof:placetype":"locality",
    "wof:population":173
},
  "geometry": {"coordinates":[86.907647,24.408192],"type":"Point"}
}