{
  "type": "Feature",
  "properties": {
    "iso:country":"IN",
    "ks:ks_name":"Padikia",
    "ks:ks_pop":222,
    "ks:ks_type":"VILLAGE",
    "name:eng_x_preferred":[
        "Padikia"
    ],
    "wof:name":"Padikia",
    "wof:placetype":"locality",
    "wof:population":222
},
  "geometry": {"coordinates":[84.172539,19.632574],"type":"Point"}
}