{
  "type": "Feature",
  "properties": {
    "iso:country":"IN",
    "ks:ks_name":"Belkhera",
    "ks:ks_type":"VILLAGE",
    "name:eng_x_preferred":[
        "Belkhera"
    ],
    "wof:name":"Belkhera",
    "wof:placetype":"locality"
},
  "geometry": {"coordinates":[77.95392699999999,21.345806],"type":"Point"}
}