{
  "type": "Feature",
  "properties": {
    "iso:country":"IN",
    "ks:ks_name":"Barai Kote",
    "ks:ks_pop":0,
    "ks:ks_type":"VILLAGE",
    "name:eng_x_preferred":[
        "Barai Kote"
    ],
    "wof:name":"Barai Kote",
    "wof:placetype":"locality",
    "wof:population":0
},
  "geometry": {"coordinates":[77.657633,26.104723],"type":"Point"}
}