{
  "type": "Feature",
  "properties": {
    "iso:country":"IN",
    "ks:ks_name":"Telar",
    "ks:ks_pop":38,
    "ks:ks_type":"VILLAGE",
    "name:eng_x_preferred":[
        "Telar"
    ],
    "wof:name":"Telar",
    "wof:placetype":"locality",
    "wof:population":38
},
  "geometry": {"coordinates":[85.241388,21.269802],"type":"Point"}
}