{
  "type": "Feature",
  "properties": {
    "gn:admin1_code":"11.0",
    "gn:admin2_code":"26.0",
    "gn:asciiname":"Katmori Lanj",
    "gn:country_code":"IN",
    "gn:dem":1382,
    "gn:feature_class":"P",
    "gn:feature_code":"PPL",
    "gn:name":"Katmori L\u0101nj",
    "gn:population":0,
    "gn:timezone":"Asia/Kolkata",
    "iso:country":"IN",
    "wof:name":"Katmori Lanj",
    "wof:placetype":"locality"
},
  "geometry": {"coordinates":[77.54553,31.45668],"type":"Point"}
}