{
  "type": "Feature",
  "properties": {
    "iso:country":"IN",
    "ks:ks_name":"Baromahulo",
    "ks:ks_pop":115,
    "ks:ks_type":"VILLAGE",
    "name:eng_x_preferred":[
        "Baromahulo"
    ],
    "wof:name":"Baromahulo",
    "wof:placetype":"locality",
    "wof:population":115
},
  "geometry": {"coordinates":[83.544847,19.717624],"type":"Point"}
}