{
  "type": "Feature",
  "properties": {
    "iso:country":"IN",
    "ks:ks_name":"Kherpura",
    "ks:ks_pop":11,
    "ks:ks_type":"VILLAGE",
    "name:eng_x_preferred":[
        "Kherpura"
    ],
    "wof:name":"Kherpura",
    "wof:placetype":"locality",
    "wof:population":11
},
  "geometry": {"coordinates":[76.965925,23.108992],"type":"Point"}
}