{
  "type": "Feature",
  "properties": {
    "iso:country":"IN",
    "ks:ks_name":"Kumhia",
    "ks:ks_pop":1736,
    "ks:ks_type":"VILLAGE",
    "ks:ks_uagg_main":0,
    "name:eng_x_preferred":[
        "Kumhia"
    ],
    "wof:name":"Kumhia",
    "wof:placetype":"neighbourhood",
    "wof:population":1736
},
  "geometry": {"coordinates":[84.133391,27.137551],"type":"Point"}
}