{
  "type": "Feature",
  "properties": {
    "iso:country":"IN",
    "ks:ks_name":"Manik Beria",
    "ks:ks_pop":525,
    "ks:ks_type":"HABITATION",
    "name:eng_x_preferred":[
        "Manik Beria"
    ],
    "wof:name":"Manik Beria",
    "wof:placetype":"locality",
    "wof:population":525
},
  "geometry": {"coordinates":[86.803521,22.214111],"type":"Point"}
}