{
  "type": "Feature",
  "properties": {
    "gn:admin1_code":"11.0",
    "gn:admin2_code":"27.0",
    "gn:asciiname":"Leh",
    "gn:country_code":"IN",
    "gn:dem":1694,
    "gn:feature_class":"P",
    "gn:feature_code":"PPL",
    "gn:name":"Leh",
    "gn:population":0,
    "gn:timezone":"Asia/Kolkata",
    "iso:country":"IN",
    "name:afr_x_preferred":[
        "Leh"
    ],
    "name:ara_x_preferred":[
        "\u0644\u064a\u0627\u0647"
    ],
    "name:ben_x_preferred":[
        "\u09b2\u09c7\u09b9"
    ],
    "name:bpy_x_preferred":[
        "\u09b2\u09c7\u09b9"
    ],
    "name:cat_x_preferred":[
        "Leh"
    ],
    "name:ceb_x_preferred":[
        "Leh"
    ],
    "name:ces_x_preferred":[
        "L\u00e9h"
    ],
    "name:deu_x_preferred":[
        "Leh"
    ],
    "name:fas_x_preferred":[
        "\u0644\u0647"
    ],
    "name:fin_x_preferred":[
        "Leh"
    ],
    "name:fra_x_preferred":[
        "Leh"
    ],
    "name:guj_x_preferred":[
        "\u0ab2\u0ac7\u0ab9"
    ],
    "name:heb_x_preferred":[
        "\u05dc\u05d4"
    ],
    "name:hin_x_preferred":[
        "\u0932\u0947\u0939"
    ],
    "name:hun_x_preferred":[
        "Leh"
    ],
    "name:ita_x_preferred":[
        "Leh"
    ],
    "name:jpn_x_preferred":[
        "\u30ec\u30fc"
    ],
    "name:kor_x_preferred":[
        "\ub808"
    ],
    "name:lit_x_preferred":[
        "Lehas"
    ],
    "name:mar_x_preferred":[
        "\u0932\u0947\u0939"
    ],
    "name:msa_x_preferred":[
        "Leh"
    ],
    "name:nep_x_preferred":[
        "\u0932\u0947\u0939"
    ],
    "name:new_x_preferred":[
        "\u0932\u0947\u0939"
    ],
    "name:nld_x_preferred":[
        "Leh"
    ],
    "name:nno_x_preferred":[
        "Leh"
    ],
    "name:nor_x_preferred":[
        "Leh"
    ],
    "name:pam_x_preferred":[
        "Leh"
    ],
    "name:pan_x_preferred":[
        "\u0a32\u0a47\u0a39"
    ],
    "name:pnb_x_preferred":[
        "\u0644\u06cc\u06c1\u06c1"
    ],
    "name:pol_x_preferred":[
        "Leh"
    ],
    "name:por_x_preferred":[
        "Leh"
    ],
    "name:ron_x_preferred":[
        "Leh"
    ],
    "name:rus_x_preferred":[
        "\u041b\u0435\u0445"
    ],
    "name:san_x_preferred":[
        "\u0932\u0947\u0939"
    ],
    "name:spa_x_preferred":[
        "Leh"
    ],
    "name:swe_x_preferred":[
        "Leh"
    ],
    "name:urd_x_preferred":[
        "\u0644\u06cc\u06c1\u06c1"
    ],
    "name:vie_x_preferred":[
        "Leh"
    ],
    "wof:name":"Leh",
    "wof:placetype":"locality"
},
  "geometry": {"coordinates":[77.16916999999999,31.582],"type":"Point"}
}