{
  "type": "Feature",
  "properties": {
    "iso:country":"IN",
    "ks:ks_name":"Beherapada",
    "ks:ks_pop":37,
    "ks:ks_type":"HABITATION",
    "name:eng_x_preferred":[
        "Beherapada"
    ],
    "wof:name":"Beherapada",
    "wof:placetype":"locality",
    "wof:population":37
},
  "geometry": {"coordinates":[83.434286,19.772936],"type":"Point"}
}