{
  "type": "Feature",
  "properties": {
    "iso:country":"IN",
    "ks:ks_name":"Dhurapada",
    "ks:ks_pop":133,
    "ks:ks_type":"HABITATION",
    "name:eng_x_preferred":[
        "Dhurapada"
    ],
    "wof:name":"Dhurapada",
    "wof:placetype":"locality",
    "wof:population":133
},
  "geometry": {"coordinates":[73.404972,20.352972],"type":"Point"}
}