{
  "type": "Feature",
  "properties": {
    "iso:country":"IN",
    "ks:ks_name":"Amargarh Block",
    "ks:ks_pop":681,
    "ks:ks_type":"HABITATION",
    "name:eng_x_preferred":[
        "Amargarh Block"
    ],
    "wof:name":"Amargarh Block",
    "wof:placetype":"locality",
    "wof:population":681
},
  "geometry": {"coordinates":[75.36829400000001,24.486084],"type":"Point"}
}