{
  "type": "Feature",
  "properties": {
    "iso:country":"IN",
    "ks:ks_name":"Jada",
    "ks:ks_pop":51,
    "ks:ks_type":"VILLAGE",
    "name:eng_x_preferred":[
        "Jada"
    ],
    "wof:name":"Jada",
    "wof:placetype":"locality",
    "wof:population":51
},
  "geometry": {"coordinates":[84.37876,19.254089],"type":"Point"}
}