{
  "type": "Feature",
  "properties": {
    "iso:country":"IN",
    "ks:ks_name":"Patagarakeri",
    "ks:ks_pop":163,
    "ks:ks_type":"HABITATION",
    "name:eng_x_preferred":[
        "Patagarakeri"
    ],
    "wof:name":"Patagarakeri",
    "wof:placetype":"locality",
    "wof:population":163
},
  "geometry": {"coordinates":[74.520138,14.52233],"type":"Point"}
}