{
  "type": "Feature",
  "properties": {
    "iso:country":"IN",
    "ks:ks_name":"Bhitakhola",
    "ks:ks_pop":30,
    "ks:ks_type":"VILLAGE",
    "name:eng_x_preferred":[
        "Bhitakhola"
    ],
    "wof:name":"Bhitakhola",
    "wof:placetype":"locality",
    "wof:population":30
},
  "geometry": {"coordinates":[84.89709499999999,19.751656],"type":"Point"}
}