{
  "type": "Feature",
  "properties": {
    "gn:admin1_code":"36",
    "gn:admin2_code":"183.0",
    "gn:asciiname":"Sir Purwa",
    "gn:country_code":"IN",
    "gn:dem":109,
    "gn:feature_class":"P",
    "gn:feature_code":"PPL",
    "gn:name":"Sir Purwa",
    "gn:population":0,
    "gn:timezone":"Asia/Kolkata",
    "iso:country":"IN",
    "ks:ks_name":"Seer Purwa",
    "ks:ks_pop":107,
    "ks:ks_type":"HABITATION",
    "name:eng_x_preferred":[
        "Seer Purwa"
    ],
    "name:eng_x_variant":[
        "Sir Purwa"
    ],
    "wof:name":"Seer Purwa",
    "wof:placetype":"locality",
    "wof:population":107
},
  "geometry": {"coordinates":[81.82260100000001,27.183352],"type":"Point"}
}