{
  "type": "Feature",
  "properties": {
    "iso:country":"IN",
    "ks:ks_name":"Patadhara",
    "ks:ks_pop":96,
    "ks:ks_type":"HABITATION",
    "name:eng_x_preferred":[
        "Patadhara"
    ],
    "wof:name":"Patadhara",
    "wof:placetype":"locality",
    "wof:population":96
},
  "geometry": {"coordinates":[74.2597,19.385773],"type":"Point"}
}