{
  "type": "Feature",
  "properties": {
    "gn:country":"IN",
    "gn:fcode":"PPL",
    "gn:pop":28405,
    "iso:country":"IN",
    "name:ben_x_preferred":[
        "\u099f\u09bf\u09b2\u09be\u0997\u09a1\u09bc"
    ],
    "name:bpy_x_preferred":[
        "\u099f\u09bf\u09b2\u09be\u0997\u09a1\u09bc"
    ],
    "name:chi_x_preferred":[
        "\u8482\u7279\u62c9\u52a0\u5c14"
    ],
    "name:dut_x_preferred":[
        "Titlagarh"
    ],
    "name:eng_x_preferred":[
        "Titlagarh"
    ],
    "name:fre_x_preferred":[
        "Titlagarh"
    ],
    "name:ger_x_preferred":[
        "Titlagarh"
    ],
    "name:guj_x_preferred":[
        "\u0a9f\u0abf\u0a9f\u0ab2\u0abe\u0a97\u0aa2"
    ],
    "name:hin_x_preferred":[
        "\u091f\u093f\u091f\u0932\u093e\u0917\u0922\u093c"
    ],
    "name:ita_x_preferred":[
        "Titlagarh"
    ],
    "name:jpn_x_preferred":[
        "\u30c6\u30a3\u30c8\u30e9\u30ac\u30fc"
    ],
    "name:kan_x_preferred":[
        "\u0c9f\u0cbf\u0c9f\u0ccd\u0cb2\u0cbe\u0c98\u0cb0\u0ccd"
    ],
    "name:kor_x_preferred":[
        "\ud2f0\ud2c0\ub77c\uac00\ub974"
    ],
    "name:may_x_preferred":[
        "Titlagarh"
    ],
    "name:mlg_x_preferred":[
        "Titlagarh"
    ],
    "name:nan_x_preferred":[
        "Titlagarh"
    ],
    "name:ori_x_preferred":[
        "\u0b1f\u0b3f\u0b1f\u0b3f\u0b32\u0b3e\u0b17\u0b21\u0b3c"
    ],
    "name:por_x_preferred":[
        "Titlagarh"
    ],
    "name:rus_x_preferred":[
        "\u0422\u0438\u0442\u043b\u0430\u0433\u0430\u0440\u0445"
    ],
    "name:spa_x_preferred":[
        "Titlagarh"
    ],
    "name:swe_x_preferred":[
        "Titl\u0101garh"
    ],
    "name:tam_x_preferred":[
        "\u0b9f\u0bbf\u0b9f\u0bb2\u0b99\u0bcd\u0b95\u0bbe\u0bb0\u0bcd\u0bb9\u0bcd"
    ],
    "name:tel_x_preferred":[
        "\u0c1f\u0c3f\u0c1f\u0c4d\u0c32\u0c18\u0c30\u0c4d"
    ],
    "name:unk_x_variant":[
        "Titlagar"
    ],
    "name:urd_x_preferred":[
        "\u0679\u0679\u0644\u0627\u06af\u0691\u06be"
    ],
    "name:vie_x_preferred":[
        "Titlagarh"
    ],
    "qs:name":"Titlagarh",
    "qs:name_adm0":"India",
    "qs:name_adm1":"Orissa",
    "qs:photos_9k":1,
    "qs:photos_9r":1,
    "qs:photos_all":6,
    "qs:photos_sr":0,
    "qs:placetype":"Town",
    "qs:pop_sr":"7",
    "wd:wordcount":826,
    "wof:name":"Titlagarh",
    "wof:placetype":"locality",
    "wof:population":28405
},
  "geometry": {"coordinates":[83.15233000000001,20.28961],"type":"Point"}
}