{
  "type": "Feature",
  "properties": {
    "gn:admin1_code":"25.0",
    "gn:admin2_code":"633.0",
    "gn:asciiname":"Lingamanayakkanpalaiyam",
    "gn:country_code":"IN",
    "gn:dem":365,
    "gn:feature_class":"P",
    "gn:feature_code":"PPL",
    "gn:name":"Lingaman\u0101yakkanp\u0101laiyam",
    "gn:population":0,
    "gn:timezone":"Asia/Kolkata",
    "iso:country":"IN",
    "wof:name":"Lingamanayakkanpalaiyam",
    "wof:placetype":"locality"
},
  "geometry": {"coordinates":[77.39301999999998,10.99391],"type":"Point"}
}