{
  "type": "Feature",
  "properties": {
    "iso:country":"IN",
    "ks:ks_alt_nam":"Jetty lane",
    "ks:ks_name":"Jetty Lane",
    "ks:ks_pop":655,
    "ks:ks_type":"HABITATION",
    "ks:ks_uagg_main":0,
    "name:eng_x_preferred":[
        "Jetty Lane"
    ],
    "wof:name":"Jetty Lane",
    "wof:placetype":"neighbourhood",
    "wof:population":655
},
  "geometry": {"coordinates":[75.90871300000001,10.804497],"type":"Point"}
}