{
  "type": "Feature",
  "properties": {
    "iso:country":"IN",
    "ks:ks_alt_nam":"DHAMNE VASTI",
    "ks:ks_name":"Dhamne Vasti",
    "ks:ks_pop":810,
    "ks:ks_type":"HABITATION",
    "name:eng_x_preferred":[
        "Dhamne Vasti"
    ],
    "wof:name":"Dhamne Vasti",
    "wof:placetype":"locality",
    "wof:population":810
},
  "geometry": {"coordinates":[74.703942,16.779447],"type":"Point"}
}