{
  "type": "Feature",
  "properties": {
    "gn:admin1_code":"35",
    "gn:admin2_code":"419.0",
    "gn:asciiname":"Gulab ka Pura",
    "gn:country_code":"IN",
    "gn:dem":166,
    "gn:feature_class":"P",
    "gn:feature_code":"PPL",
    "gn:name":"Gul\u0101b ka Pura",
    "gn:population":0,
    "gn:timezone":"Asia/Kolkata",
    "iso:country":"IN",
    "wof:name":"Gulab ka Pura",
    "wof:placetype":"locality"
},
  "geometry": {"coordinates":[78.23680999999998,26.71202000000001],"type":"Point"}
}