{
  "type": "Feature",
  "properties": {
    "iso:country":"IN",
    "ks:ks_name":"Fardehni",
    "ks:ks_pop":327,
    "ks:ks_type":"HABITATION",
    "name:eng_x_preferred":[
        "Fardehni"
    ],
    "wof:name":"Fardehni",
    "wof:placetype":"locality",
    "wof:population":327
},
  "geometry": {"coordinates":[83.11918799999999,27.312537],"type":"Point"}
}