{
  "type": "Feature",
  "properties": {
    "iso:country":"IN",
    "ks:ks_name":"Parabwadi",
    "ks:ks_pop":135,
    "ks:ks_type":"HABITATION",
    "name:eng_x_preferred":[
        "Parabwadi"
    ],
    "wof:name":"Parabwadi",
    "wof:placetype":"locality",
    "wof:population":135
},
  "geometry": {"coordinates":[73.675517,16.299152],"type":"Point"}
}