{
  "type": "Feature",
  "properties": {
    "gn:admin1_code":"34.0",
    "gn:admin2_code":"209.0",
    "gn:asciiname":"Saidpur",
    "gn:country_code":"IN",
    "gn:dem":46,
    "gn:feature_class":"P",
    "gn:feature_code":"PPL",
    "gn:name":"Saidpur",
    "gn:population":0,
    "gn:timezone":"Asia/Kolkata",
    "iso:country":"IN",
    "name:ara_x_preferred":[
        "\u0633\u064a\u062f\u0628\u0648\u0631"
    ],
    "name:ben_x_preferred":[
        "\u09b8\u09c8\u09af\u09bc\u09a6\u09aa\u09c1\u09b0"
    ],
    "name:bpy_x_preferred":[
        "\u09b8\u09be\u09af\u09bc\u09bf\u09a6\u09aa\u09c1\u09b0"
    ],
    "name:ceb_x_preferred":[
        "Saidpur"
    ],
    "name:ell_x_preferred":[
        "\u03a3\u03ac\u03b9\u03bd\u03c4\u03c0\u03bf\u03c5\u03c1"
    ],
    "name:heb_x_preferred":[
        "\u05e1\u05e2\u05d9\u05d3\u05e4\u05d5\u05e8"
    ],
    "name:hun_x_preferred":[
        "Saidpur"
    ],
    "name:ind_x_preferred":[
        "Saidpur"
    ],
    "name:ita_x_preferred":[
        "Saidpur"
    ],
    "name:kor_x_preferred":[
        "\uc0ac\uc774\ub4dc\ud478\ub974"
    ],
    "name:pol_x_preferred":[
        "Saidpur"
    ],
    "name:por_x_preferred":[
        "Saidpur"
    ],
    "name:spa_x_preferred":[
        "Saidpur"
    ],
    "name:sun_x_preferred":[
        "Saidpur"
    ],
    "name:swe_x_preferred":[
        "Saidpur"
    ],
    "name:tur_x_preferred":[
        "Saidpur"
    ],
    "name:ukr_x_preferred":[
        "\u0421\u0430\u0457\u0434\u043f\u0443\u0440"
    ],
    "name:vie_x_preferred":[
        "Saidpur"
    ],
    "wof:name":"Saidpur",
    "wof:placetype":"locality"
},
  "geometry": {"coordinates":[87.39664,26.00159],"type":"Point"}
}