{
  "type": "Feature",
  "properties": {
    "iso:country":"IN",
    "ks:ks_name":"Badimar",
    "ks:ks_pop":11,
    "ks:ks_type":"HABITATION",
    "name:eng_x_preferred":[
        "Badimar"
    ],
    "wof:name":"Badimar",
    "wof:placetype":"locality",
    "wof:population":11
},
  "geometry": {"coordinates":[82.30886599999999,20.50896],"type":"Point"}
}