{
  "type": "Feature",
  "properties": {
    "gn:admin1_code":"2.0",
    "gn:admin2_code":"542.0",
    "gn:asciiname":"Gandredu",
    "gn:country_code":"IN",
    "gn:dem":25,
    "gn:feature_class":"P",
    "gn:feature_code":"PPL",
    "gn:name":"Gandredu",
    "gn:population":0,
    "gn:timezone":"Asia/Kolkata",
    "iso:country":"IN",
    "wof:name":"Gandredu",
    "wof:placetype":"locality"
},
  "geometry": {"coordinates":[83.84486,18.39096],"type":"Point"}
}