{
  "type": "Feature",
  "properties": {
    "gn:admin1_code":"24.0",
    "gn:admin2_code":"118.0",
    "gn:asciiname":"Patawa",
    "gn:country_code":"IN",
    "gn:dem":332,
    "gn:feature_class":"P",
    "gn:feature_code":"PPL",
    "gn:name":"P\u0101t\u0101wa",
    "gn:population":0,
    "gn:timezone":"Asia/Kolkata",
    "iso:country":"IN",
    "wof:name":"Patawa",
    "wof:placetype":"locality"
},
  "geometry": {"coordinates":[73.29306,25.10945],"type":"Point"}
}