{
  "type": "Feature",
  "properties": {
    "gn:admin1_code":"34.0",
    "gn:admin2_code":"236.0",
    "gn:asciiname":"Gamhariya",
    "gn:country_code":"IN",
    "gn:dem":156,
    "gn:feature_class":"P",
    "gn:feature_code":"PPL",
    "gn:name":"Gamhariya",
    "gn:population":0,
    "gn:timezone":"Asia/Kolkata",
    "iso:country":"IN",
    "ks:ks_name":"Gamharia",
    "ks:ks_pop":1098,
    "ks:ks_type":"VILLAGE",
    "ks:ks_uagg_main":0,
    "name:eng_x_preferred":[
        "Gamharia"
    ],
    "name:fra_x_preferred":[
        "Gamhariya"
    ],
    "name:new_x_preferred":[
        "\u0917\u092e\u094d\u0939\u0930\u093f\u092f\u093e"
    ],
    "name:pol_x_preferred":[
        "Gamhariya"
    ],
    "wof:name":"Gamharia",
    "wof:placetype":"neighbourhood",
    "wof:population":1098
},
  "geometry": {"coordinates":[84.740866,24.591096],"type":"Point"}
}