{
  "type": "Feature",
  "properties": {
    "iso:country":"IN",
    "ks:ks_name":"Harpur Bakhri",
    "ks:ks_pop":631,
    "ks:ks_type":"VILLAGE",
    "name:eng_x_preferred":[
        "Harpur Bakhri"
    ],
    "wof:name":"Harpur Bakhri",
    "wof:placetype":"locality",
    "wof:population":631
},
  "geometry": {"coordinates":[85.419922,26.161983],"type":"Point"}
}