{
  "type": "Feature",
  "properties": {
    "iso:country":"IN",
    "ks:ks_alt_nam":"UMARPUR",
    "ks:ks_name":"Umarpur",
    "ks:ks_pop":766,
    "ks:ks_type":"HABITATION",
    "name:eng_x_preferred":[
        "Umarpur"
    ],
    "wof:name":"Umarpur",
    "wof:placetype":"locality",
    "wof:population":766
},
  "geometry": {"coordinates":[84.055065,25.622765],"type":"Point"}
}