{
  "type": "Feature",
  "properties": {
    "iso:country":"IN",
    "ks:ks_name":"Gadher",
    "ks:ks_pop":505,
    "ks:ks_type":"VILLAGE",
    "name:eng_x_preferred":[
        "Gadher"
    ],
    "wof:name":"Gadher",
    "wof:placetype":"locality",
    "wof:population":505
},
  "geometry": {"coordinates":[73.84780600000001,21.872528],"type":"Point"}
}