{
  "type": "Feature",
  "properties": {
    "gn:admin1_code":"35.0",
    "gn:admin2_code":"465.0",
    "gn:asciiname":"Ambua",
    "gn:country_code":"IN",
    "gn:dem":324,
    "gn:feature_class":"P",
    "gn:feature_code":"PPL",
    "gn:name":"Ambua",
    "gn:population":0,
    "gn:timezone":"Asia/Kolkata",
    "iso:country":"IN",
    "wof:name":"Ambua",
    "wof:placetype":"locality"
},
  "geometry": {"coordinates":[74.41771,22.41585],"type":"Point"}
}