{
  "type": "Feature",
  "properties": {
    "gn:admin1_code":"02",
    "gn:admin2_code":"542.0",
    "gn:asciiname":"Sarvakota",
    "gn:country_code":"IN",
    "gn:dem":61,
    "gn:feature_class":"P",
    "gn:feature_code":"PPL",
    "gn:name":"S\u0101rvakota",
    "gn:population":0,
    "gn:timezone":"Asia/Kolkata",
    "iso:country":"IN",
    "wof:name":"Sarvakota",
    "wof:placetype":"locality"
},
  "geometry": {"coordinates":[84.05306999999998,18.59214],"type":"Point"}
}