{
  "type": "Feature",
  "properties": {
    "iso:country":"IN",
    "ks:ks_name":"Dulhapar Kurd",
    "ks:ks_pop":1,
    "ks:ks_type":"HABITATION",
    "name:eng_x_preferred":[
        "Dulhapar Kurd"
    ],
    "wof:name":"Dulhapar Kurd",
    "wof:placetype":"locality",
    "wof:population":1
},
  "geometry": {"coordinates":[82.936588,26.585524],"type":"Point"}
}