{
  "type": "Feature",
  "properties": {
    "iso:country":"IN",
    "ks:ks_name":"Tholikunne Jn",
    "ks:ks_pop":1100,
    "ks:ks_type":"HABITATION",
    "name:eng_x_preferred":[
        "Tholikunne Jn"
    ],
    "wof:name":"Tholikunne Jn",
    "wof:placetype":"locality",
    "wof:population":1100
},
  "geometry": {"coordinates":[76.92747799999999,8.788917],"type":"Point"}
}