{
  "type": "Feature",
  "properties": {
    "gn:admin1_code":"12.0",
    "gn:admin2_code":"19.0",
    "gn:asciiname":"Sum",
    "gn:country_code":"IN",
    "gn:dem":990,
    "gn:feature_class":"P",
    "gn:feature_code":"PPL",
    "gn:name":"Sum",
    "gn:population":0,
    "gn:timezone":"Asia/Kolkata",
    "iso:country":"IN",
    "name:ceb_x_preferred":[
        "Sum"
    ],
    "name:deu_x_preferred":[
        "Sum"
    ],
    "name:fra_x_preferred":[
        "Sum"
    ],
    "name:kor_x_preferred":[
        "\uc228"
    ],
    "name:nld_x_preferred":[
        "Sum"
    ],
    "name:nor_x_preferred":[
        "Sum"
    ],
    "name:pol_x_preferred":[
        "Sum"
    ],
    "name:rus_x_preferred":[
        "\u0421\u0443\u043c"
    ],
    "name:swe_x_preferred":[
        "Sum"
    ],
    "name:ukr_x_preferred":[
        "\u0421\u0443\u043c"
    ],
    "name:xho_x_preferred":[
        "I-sum"
    ],
    "wof:name":"Sum",
    "wof:placetype":"locality"
},
  "geometry": {"coordinates":[75.16128,33.10667],"type":"Point"}
}