{
  "type": "Feature",
  "properties": {
    "iso:country":"IN",
    "ks:ks_alt_nam":"Katkarwadi no 1",
    "ks:ks_name":"Katkarwadi No 1",
    "ks:ks_pop":25,
    "ks:ks_type":"HABITATION",
    "name:eng_x_preferred":[
        "Katkarwadi No 1"
    ],
    "wof:name":"Katkarwadi No 1",
    "wof:placetype":"locality",
    "wof:population":25
},
  "geometry": {"coordinates":[73.67444399999999,17.605],"type":"Point"}
}