{
  "type": "Feature",
  "properties": {
    "iso:country":"IN",
    "ks:ks_name":"Nichla Khejra",
    "ks:ks_pop":1499,
    "ks:ks_type":"VILLAGE",
    "name:eng_x_preferred":[
        "Nichla Khejra"
    ],
    "wof:name":"Nichla Khejra",
    "wof:placetype":"locality",
    "wof:population":1499
},
  "geometry": {"coordinates":[72.916658,24.466511],"type":"Point"}
}