{
  "type": "Feature",
  "properties": {
    "gn:admin1_code":"39.0",
    "gn:admin2_code":"66.0",
    "gn:asciiname":"Lamjala",
    "gn:country_code":"IN",
    "gn:dem":864,
    "gn:feature_class":"P",
    "gn:feature_code":"PPL",
    "gn:name":"Lamj\u0101la",
    "gn:population":0,
    "gn:timezone":"Asia/Kolkata",
    "iso:country":"IN",
    "wof:name":"Lamjala",
    "wof:placetype":"locality"
},
  "geometry": {"coordinates":[79.61214,29.29737],"type":"Point"}
}