{
  "type": "Feature",
  "properties": {
    "iso:country":"IN",
    "ks:ks_name":"Chipatpada",
    "ks:ks_pop":418,
    "ks:ks_type":"HABITATION",
    "name:eng_x_preferred":[
        "Chipatpada"
    ],
    "wof:name":"Chipatpada",
    "wof:placetype":"locality",
    "wof:population":418
},
  "geometry": {"coordinates":[72.797428,19.808892],"type":"Point"}
}