{
  "type": "Feature",
  "properties": {
    "iso:country":"IN",
    "ks:ks_name":"Ashok Nagar",
    "ks:ks_pop":35,
    "ks:ks_type":"HABITATION",
    "name:eng_x_preferred":[
        "Ashok Nagar"
    ],
    "wof:name":"Ashok Nagar",
    "wof:placetype":"locality",
    "wof:population":35
},
  "geometry": {"coordinates":[79.98274600000001,14.578872],"type":"Point"}
}