{
  "type": "Feature",
  "properties": {
    "gn:admin1_code":"19.0",
    "gn:admin2_code":"573.0",
    "gn:asciiname":"Byalakere",
    "gn:country_code":"IN",
    "gn:dem":707,
    "gn:feature_class":"P",
    "gn:feature_code":"PPL",
    "gn:name":"By\u0101lakere",
    "gn:population":0,
    "gn:timezone":"Asia/Kolkata",
    "iso:country":"IN",
    "wof:name":"Byalakere",
    "wof:placetype":"locality"
},
  "geometry": {"coordinates":[76.88753,12.8365],"type":"Point"}
}