{
  "type": "Feature",
  "properties": {
    "iso:country":"IN",
    "ks:ks_name":"Korantikottai",
    "ks:ks_pop":207,
    "ks:ks_type":"HABITATION",
    "name:eng_x_preferred":[
        "Korantikottai"
    ],
    "wof:name":"Korantikottai",
    "wof:placetype":"locality",
    "wof:population":207
},
  "geometry": {"coordinates":[78.778358,9.719445],"type":"Point"}
}