{
  "type": "Feature",
  "properties": {
    "iso:country":"IN",
    "ks:ks_name":"Khowang T E 17 21 Nlr",
    "ks:ks_pop":2362,
    "ks:ks_type":"HABITATION",
    "name:eng_x_preferred":[
        "Khowang T E 17 21 Nlr"
    ],
    "wof:name":"Khowang T E 17 21 Nlr",
    "wof:placetype":"locality",
    "wof:population":2362
},
  "geometry": {"coordinates":[95.531751,27.668762],"type":"Point"}
}