{
  "type": "Feature",
  "properties": {
    "iso:country":"IN",
    "ks:ks_alt_nam":"Jog\u012by\u0101pokhri",
    "ks:ks_name":"Jogiyapokhri",
    "ks:ks_pop":353,
    "ks:ks_type":"VILLAGE",
    "ks:ks_uagg_main":0,
    "name:eng_x_preferred":[
        "Jogiyapokhri"
    ],
    "name:eng_x_variant":[
        "Jog\u012by\u0101pokhri"
    ],
    "wof:name":"Jogiyapokhri",
    "wof:placetype":"neighbourhood",
    "wof:population":353
},
  "geometry": {"coordinates":[84.25036,23.942679],"type":"Point"}
}