{
  "type": "Feature",
  "properties": {
    "iso:country":"IN",
    "ks:ks_alt_nam":"Lower II",
    "ks:ks_name":"Lower Ii",
    "ks:ks_pop":917,
    "ks:ks_type":"HABITATION",
    "name:eng_x_preferred":[
        "Lower Ii"
    ],
    "wof:name":"Lower Ii",
    "wof:placetype":"locality",
    "wof:population":917
},
  "geometry": {"coordinates":[88.32424899999999,27.064763],"type":"Point"}
}