{
  "type": "Feature",
  "properties": {
    "iso:country":"IN",
    "ks:ks_alt_nam":"BAGARTHALA",
    "ks:ks_name":"Bagarthala",
    "ks:ks_pop":101,
    "ks:ks_type":"HABITATION",
    "name:eng_x_preferred":[
        "Bagarthala"
    ],
    "wof:name":"Bagarthala",
    "wof:placetype":"locality",
    "wof:population":101
},
  "geometry": {"coordinates":[75.270917,25.463139],"type":"Point"}
}