{
  "type": "Feature",
  "properties": {
    "iso:country":"IN",
    "ks:ks_name":"Ghadipadave",
    "ks:ks_pop":510,
    "ks:ks_type":"HABITATION",
    "name:eng_x_preferred":[
        "Ghadipadave"
    ],
    "wof:name":"Ghadipadave",
    "wof:placetype":"locality",
    "wof:population":510
},
  "geometry": {"coordinates":[73.50787800000001,16.346769],"type":"Point"}
}