{
  "type": "Feature",
  "properties": {
    "gn:admin1_code":"16.0",
    "gn:admin2_code":"514.0",
    "gn:asciiname":"Javkhed Buzurg",
    "gn:country_code":"IN",
    "gn:dem":576,
    "gn:feature_class":"P",
    "gn:feature_code":"PPL",
    "gn:name":"Javkhed Buzurg",
    "gn:population":0,
    "gn:timezone":"Asia/Kolkata",
    "iso:country":"IN",
    "wof:name":"Javkhed Buzurg",
    "wof:placetype":"neighbourhood"
},
  "geometry": {"coordinates":[75.73162000000001,20.08897],"type":"Point"}
}