{
  "type": "Feature",
  "properties": {
    "iso:country":"IN",
    "ks:ks_name":"Pulichuvadu",
    "ks:ks_pop":1671,
    "ks:ks_type":"HABITATION",
    "name:eng_x_preferred":[
        "Pulichuvadu"
    ],
    "wof:name":"Pulichuvadu",
    "wof:placetype":"locality",
    "wof:population":1671
},
  "geometry": {"coordinates":[76.347354,9.739148],"type":"Point"}
}