{
  "type": "Feature",
  "properties": {
    "iso:country":"IN",
    "ks:ks_name":"Ajad Nagar",
    "ks:ks_pop":72,
    "ks:ks_type":"VILLAGE",
    "name:eng_x_preferred":[
        "Ajad Nagar"
    ],
    "wof:name":"Ajad Nagar",
    "wof:placetype":"locality",
    "wof:population":72
},
  "geometry": {"coordinates":[71.12221099999999,25.399957],"type":"Point"}
}