{
  "type": "Feature",
  "properties": {
    "iso:country":"IN",
    "ks:ks_name":"Bankira",
    "ks:ks_pop":113,
    "ks:ks_type":"HABITATION",
    "name:eng_x_preferred":[
        "Bankira"
    ],
    "wof:name":"Bankira",
    "wof:placetype":"locality",
    "wof:population":113
},
  "geometry": {"coordinates":[85.510076,22.837513],"type":"Point"}
}