{
  "type": "Feature",
  "properties": {
    "iso:country":"IN",
    "ks:ks_name":"Samnagar",
    "ks:ks_pop":153,
    "ks:ks_type":"HABITATION",
    "name:eng_x_preferred":[
        "Samnagar"
    ],
    "wof:name":"Samnagar",
    "wof:placetype":"locality",
    "wof:population":153
},
  "geometry": {"coordinates":[77.745946,12.509401],"type":"Point"}
}