{
  "type": "Feature",
  "properties": {
    "iso:country":"IN",
    "ks:ks_name":"Tambadshet",
    "ks:ks_pop":1573,
    "ks:ks_type":"VILLAGE",
    "ks:ks_uagg_main":0,
    "name:eng_x_preferred":[
        "Tambadshet"
    ],
    "wof:name":"Tambadshet",
    "wof:placetype":"neighbourhood",
    "wof:population":1573
},
  "geometry": {"coordinates":[73.07485699999999,18.783195],"type":"Point"}
}