{
  "type": "Feature",
  "properties": {
    "iso:country":"IN",
    "ks:ks_name":"Muvad Falia",
    "ks:ks_pop":1055,
    "ks:ks_type":"HABITATION",
    "name:eng_x_preferred":[
        "Muvad Falia"
    ],
    "wof:name":"Muvad Falia",
    "wof:placetype":"locality",
    "wof:population":1055
},
  "geometry": {"coordinates":[74.030861,23.127778],"type":"Point"}
}