{
  "type": "Feature",
  "properties": {
    "gn:admin1_code":"34.0",
    "gn:admin2_code":"207.0",
    "gn:asciiname":"Balat",
    "gn:country_code":"IN",
    "gn:dem":61,
    "gn:feature_class":"P",
    "gn:feature_code":"PPL",
    "gn:name":"Bal\u0101t",
    "gn:population":0,
    "gn:timezone":"Asia/Kolkata",
    "iso:country":"IN",
    "name:cat_x_preferred":[
        "Balat"
    ],
    "name:ceb_x_preferred":[
        "Balat"
    ],
    "name:deu_x_preferred":[
        "Balat"
    ],
    "name:fra_x_preferred":[
        "Balat"
    ],
    "name:pol_x_preferred":[
        "Balat"
    ],
    "name:swe_x_preferred":[
        "Balat"
    ],
    "name:tgl_x_preferred":[
        "Balat"
    ],
    "name:tur_x_preferred":[
        "Balat"
    ],
    "wof:name":"Balat",
    "wof:placetype":"neighbourhood"
},
  "geometry": {"coordinates":[86.14003,26.35407],"type":"Point"}
}