{
  "type": "Feature",
  "properties": {
    "iso:country":"IN",
    "ks:ks_name":"Navapura",
    "ks:ks_pop":580,
    "ks:ks_type":"HABITATION",
    "name:eng_x_preferred":[
        "Navapura"
    ],
    "wof:name":"Navapura",
    "wof:placetype":"locality",
    "wof:population":580
},
  "geometry": {"coordinates":[72.84225000000001,22.561639],"type":"Point"}
}