{
  "type": "Feature",
  "properties": {
    "gn:admin1_code":"16.0",
    "gn:admin2_code":"513.0",
    "gn:asciiname":"Mangrul Palampat",
    "gn:country_code":"IN",
    "gn:dem":404,
    "gn:feature_class":"P",
    "gn:feature_code":"PPL",
    "gn:name":"Mangr\u016bl P\u0101lampat",
    "gn:population":0,
    "gn:timezone":"Asia/Kolkata",
    "iso:country":"IN",
    "wof:name":"Mangrul Palampat",
    "wof:placetype":"locality"
},
  "geometry": {"coordinates":[76.56616,19.40386],"type":"Point"}
}