{
  "type": "Feature",
  "properties": {
    "iso:country":"IN",
    "ks:ks_name":"Karatiasahi",
    "ks:ks_pop":781,
    "ks:ks_type":"VILLAGE",
    "name:eng_x_preferred":[
        "Karatiasahi"
    ],
    "wof:name":"Karatiasahi",
    "wof:placetype":"locality",
    "wof:population":781
},
  "geometry": {"coordinates":[85.43255600000001,19.890851],"type":"Point"}
}