{
  "type": "Feature",
  "properties": {
    "iso:country":"IN",
    "ks:ks_alt_nam":"MUSAHARI TOL",
    "ks:ks_name":"Musahari Tol",
    "ks:ks_pop":1232,
    "ks:ks_type":"HABITATION",
    "ks:ks_uagg_main":0,
    "name:eng_x_preferred":[
        "Musahari Tol"
    ],
    "wof:name":"Musahari Tol",
    "wof:placetype":"neighbourhood",
    "wof:population":1232
},
  "geometry": {"coordinates":[86.049584,26.078718],"type":"Point"}
}