{
  "type": "Feature",
  "properties": {
    "iso:country":"IN",
    "ks:ks_name":"Jalio",
    "ks:ks_pop":572,
    "ks:ks_type":"VILLAGE",
    "name:eng_x_preferred":[
        "Jalio"
    ],
    "wof:name":"Jalio",
    "wof:placetype":"locality",
    "wof:population":572
},
  "geometry": {"coordinates":[84.326655,19.017461],"type":"Point"}
}