{
  "type": "Feature",
  "properties": {
    "gn:admin1_code":"24",
    "gn:admin2_code":"107.0",
    "gn:asciiname":"Chenapura",
    "gn:country_code":"IN",
    "gn:dem":365,
    "gn:feature_class":"P",
    "gn:feature_code":"PPL",
    "gn:name":"Chen\u0101pura",
    "gn:population":0,
    "gn:timezone":"Asia/Kolkata",
    "iso:country":"IN",
    "ks:ks_name":"Chainapura",
    "ks:ks_pop":74,
    "ks:ks_type":"VILLAGE",
    "name:eng_x_preferred":[
        "Chainapura"
    ],
    "name:eng_x_variant":[
        "Chenapura"
    ],
    "wof:name":"Chainapura",
    "wof:placetype":"locality",
    "wof:population":74
},
  "geometry": {"coordinates":[77.188408,26.345976],"type":"Point"}
}