{
  "type": "Feature",
  "properties": {
    "gn:admin1_code":"9.0",
    "gn:admin2_code":"469.0",
    "gn:asciiname":"Vasi",
    "gn:country_code":"IN",
    "gn:dem":292,
    "gn:feature_class":"P",
    "gn:feature_code":"PPL",
    "gn:name":"Vasi",
    "gn:population":0,
    "gn:timezone":"Asia/Kolkata",
    "iso:country":"IN",
    "name:ceb_x_preferred":[
        "Vasi"
    ],
    "name:ita_x_preferred":[
        "Vasi"
    ],
    "name:rus_x_preferred":[
        "\u0412\u0430\u0437\u0438"
    ],
    "name:swe_x_preferred":[
        "Vasi"
    ],
    "name:tur_x_preferred":[
        "Vasi"
    ],
    "wof:name":"Vasi",
    "wof:placetype":"locality"
},
  "geometry": {"coordinates":[72.77298,24.23669],"type":"Point"}
}