{
  "type": "Feature",
  "properties": {
    "iso:country":"IN",
    "ks:ks_name":"Chak Datawali",
    "ks:ks_pop":0,
    "ks:ks_type":"VILLAGE",
    "name:eng_x_preferred":[
        "Chak Datawali"
    ],
    "wof:name":"Chak Datawali",
    "wof:placetype":"locality",
    "wof:population":0
},
  "geometry": {"coordinates":[78.873071,25.814752],"type":"Point"}
}