{
  "type": "Feature",
  "properties": {
    "iso:country":"IN",
    "ks:ks_name":"Borkheda Khurd",
    "ks:ks_pop":2269,
    "ks:ks_type":"VILLAGE",
    "name:eng_x_preferred":[
        "Borkheda Khurd"
    ],
    "wof:name":"Borkheda Khurd",
    "wof:placetype":"locality",
    "wof:population":2269
},
  "geometry": {"coordinates":[76.64013799999999,22.072405],"type":"Point"}
}