{
  "type": "Feature",
  "properties": {
    "iso:country":"IN",
    "ks:ks_name":"Bhojwar",
    "ks:ks_pop":465,
    "ks:ks_type":"VILLAGE",
    "name:eng_x_preferred":[
        "Bhojwar"
    ],
    "wof:name":"Bhojwar",
    "wof:placetype":"locality",
    "wof:population":465
},
  "geometry": {"coordinates":[82.81894200000001,27.352385],"type":"Point"}
}