{
  "type": "Feature",
  "properties": {
    "iso:country":"IN",
    "ks:ks_name":"Bhimnagar",
    "ks:ks_pop":145,
    "ks:ks_type":"HABITATION",
    "name:eng_x_preferred":[
        "Bhimnagar"
    ],
    "wof:name":"Bhimnagar",
    "wof:placetype":"locality",
    "wof:population":145
},
  "geometry": {"coordinates":[73.68271799999999,15.746495],"type":"Point"}
}