{
  "type": "Feature",
  "properties": {
    "iso:country":"IN",
    "ks:ks_name":"Anwla Sultanpur Khadar",
    "ks:ks_pop":0,
    "ks:ks_type":"VILLAGE",
    "name:eng_x_preferred":[
        "Anwla Sultanpur Khadar"
    ],
    "wof:name":"Anwla Sultanpur Khadar",
    "wof:placetype":"locality",
    "wof:population":0
},
  "geometry": {"coordinates":[77.753411,27.394063],"type":"Point"}
}