{
  "type": "Feature",
  "properties": {
    "iso:country":"IN",
    "ks:ks_name":"Adarsh Vishu Nagar",
    "ks:ks_pop":559,
    "ks:ks_type":"HABITATION",
    "name:eng_x_preferred":[
        "Adarsh Vishu Nagar"
    ],
    "wof:name":"Adarsh Vishu Nagar",
    "wof:placetype":"locality",
    "wof:population":559
},
  "geometry": {"coordinates":[71.274033,25.222878],"type":"Point"}
}