{
  "type": "Feature",
  "properties": {
    "iso:country":"IN",
    "ks:ks_name":"Kuplottu",
    "ks:ks_pop":100,
    "ks:ks_type":"HABITATION",
    "name:eng_x_preferred":[
        "Kuplottu"
    ],
    "wof:name":"Kuplottu",
    "wof:placetype":"locality",
    "wof:population":100
},
  "geometry": {"coordinates":[75.307365,13.046824],"type":"Point"}
}