{
  "type": "Feature",
  "properties": {
    "iso:country":"IN",
    "ks:ks_name":"Jayramdih",
    "ks:ks_pop":651,
    "ks:ks_type":"VILLAGE",
    "ks:ks_uagg_main":0,
    "name:eng_x_preferred":[
        "Jayramdih"
    ],
    "wof:name":"Jayramdih",
    "wof:placetype":"neighbourhood",
    "wof:population":651
},
  "geometry": {"coordinates":[86.210261,23.789754],"type":"Point"}
}