{
  "type": "Feature",
  "properties": {
    "iso:country":"IN",
    "ks:ks_name":"No.2 Kowa Donga",
    "ks:ks_pop":1353,
    "ks:ks_type":"VILLAGE",
    "ks:ks_uagg_main":0,
    "name:eng_x_preferred":[
        "No.2 Kowa Donga"
    ],
    "wof:name":"No.2 Kowa Donga",
    "wof:placetype":"neighbourhood",
    "wof:population":1353
},
  "geometry": {"coordinates":[94.012596,27.182819],"type":"Point"}
}