{
  "type": "Feature",
  "properties": {
    "iso:country":"IN",
    "ks:ks_name":"Chamrahipurva",
    "ks:ks_pop":223,
    "ks:ks_type":"HABITATION",
    "name:eng_x_preferred":[
        "Chamrahipurva"
    ],
    "wof:name":"Chamrahipurva",
    "wof:placetype":"locality",
    "wof:population":223
},
  "geometry": {"coordinates":[81.197193,27.055062],"type":"Point"}
}