{
  "type": "Feature",
  "properties": {
    "iso:country":"IN",
    "ks:ks_alt_nam":"Okhar gaon",
    "ks:ks_name":"Okhar Gaon",
    "ks:ks_pop":80,
    "ks:ks_type":"HABITATION",
    "name:eng_x_preferred":[
        "Okhar Gaon"
    ],
    "wof:name":"Okhar Gaon",
    "wof:placetype":"locality",
    "wof:population":80
},
  "geometry": {"coordinates":[80.14915499999999,29.830266],"type":"Point"}
}