{
  "type": "Feature",
  "properties": {
    "iso:country":"IN",
    "ks:ks_name":"Baralakhat",
    "ks:ks_pop":1215,
    "ks:ks_type":"VILLAGE",
    "ks:ks_uagg_main":0,
    "name:eng_x_preferred":[
        "Baralakhat"
    ],
    "wof:name":"Baralakhat",
    "wof:placetype":"neighbourhood",
    "wof:population":1215
},
  "geometry": {"coordinates":[91.844306,26.569453],"type":"Point"}
}