{
  "type": "Feature",
  "properties": {
    "iso:country":"IN",
    "ks:ks_name":"Sonapur Gaon",
    "ks:ks_pop":208,
    "ks:ks_type":"VILLAGE",
    "name:eng_x_preferred":[
        "Sonapur Gaon"
    ],
    "wof:name":"Sonapur Gaon",
    "wof:placetype":"locality",
    "wof:population":208
},
  "geometry": {"coordinates":[94.010344,27.069513],"type":"Point"}
}