{
  "type": "Feature",
  "properties": {
    "iso:country":"IN",
    "ks:ks_name":"Basadi",
    "ks:ks_pop":248,
    "ks:ks_type":"HABITATION",
    "name:eng_x_preferred":[
        "Basadi"
    ],
    "wof:name":"Basadi",
    "wof:placetype":"locality",
    "wof:population":248
},
  "geometry": {"coordinates":[75.01783,13.153944],"type":"Point"}
}