{
  "type": "Feature",
  "properties": {
    "gn:admin1_code":"19.0",
    "gn:admin2_code":"569.0",
    "gn:asciiname":"Mandadi",
    "gn:country_code":"IN",
    "gn:dem":26,
    "gn:feature_class":"P",
    "gn:feature_code":"PPL",
    "gn:name":"Mandadi",
    "gn:population":0,
    "gn:timezone":"Asia/Kolkata",
    "iso:country":"IN",
    "wof:name":"Mandadi",
    "wof:placetype":"locality"
},
  "geometry": {"coordinates":[74.76801,13.59329],"type":"Point"}
}