{
  "type": "Feature",
  "properties": {
    "iso:country":"IN",
    "ks:ks_name":"Haradaguda",
    "ks:ks_pop":44,
    "ks:ks_type":"HABITATION",
    "name:eng_x_preferred":[
        "Haradaguda"
    ],
    "wof:name":"Haradaguda",
    "wof:placetype":"locality",
    "wof:population":44
},
  "geometry": {"coordinates":[82.651126,18.952614],"type":"Point"}
}