{
  "type": "Feature",
  "properties": {
    "gn:admin1_code":"24.0",
    "gn:admin2_code":"122.0",
    "gn:asciiname":"Gadriyakhera",
    "gn:country_code":"IN",
    "gn:dem":464,
    "gn:feature_class":"P",
    "gn:feature_code":"PPL",
    "gn:name":"G\u0101driy\u0101khera",
    "gn:population":0,
    "gn:timezone":"Asia/Kolkata",
    "iso:country":"IN",
    "wof:name":"Gadriyakhera",
    "wof:placetype":"locality"
},
  "geometry": {"coordinates":[74.41083,25.38642],"type":"Point"}
}