{
  "type": "Feature",
  "properties": {
    "iso:country":"IN",
    "ks:ks_alt_nam":"Ceylon colony",
    "ks:ks_name":"Ceylon Colony",
    "ks:ks_pop":130,
    "ks:ks_type":"HABITATION",
    "name:eng_x_preferred":[
        "Ceylon Colony"
    ],
    "wof:name":"Ceylon Colony",
    "wof:placetype":"locality",
    "wof:population":130
},
  "geometry": {"coordinates":[77.776712,9.527893],"type":"Point"}
}