{
  "type": "Feature",
  "properties": {
    "iso:country":"IN",
    "ks:ks_name":"Langariya",
    "ks:ks_pop":307,
    "ks:ks_type":"VILLAGE",
    "name:eng_x_preferred":[
        "Langariya"
    ],
    "wof:name":"Langariya",
    "wof:placetype":"locality",
    "wof:population":307
},
  "geometry": {"coordinates":[74.804749,23.706051],"type":"Point"}
}