{
  "type": "Feature",
  "properties": {
    "iso:country":"IN",
    "ks:ks_alt_nam":"Vadugap\u0101laiyam",
    "ks:ks_alt_nam_2":"Vadugapalaiyam",
    "ks:ks_name":"Vadugapalayam",
    "ks:ks_pop":4082,
    "ks:ks_type":"VILLAGE",
    "ks:ks_uagg_main":0,
    "name:eng_x_preferred":[
        "Vadugapalayam"
    ],
    "name:eng_x_variant":[
        "Vadugap\u0101laiyam",
        "Vadugapalaiyam"
    ],
    "wof:name":"Vadugapalayam",
    "wof:placetype":"neighbourhood",
    "wof:population":4082
},
  "geometry": {"coordinates":[77.27858999999999,10.984718],"type":"Point"}
}