{
  "type": "Feature",
  "properties": {
    "gn:admin1_code":"24.0",
    "gn:admin2_code":"102",
    "gn:asciiname":"Bhajrunsar",
    "gn:country_code":"IN",
    "gn:dem":271,
    "gn:feature_class":"P",
    "gn:feature_code":"PPL",
    "gn:name":"Bhajr\u016bnsar",
    "gn:population":0,
    "gn:timezone":"Asia/Kolkata",
    "iso:country":"IN",
    "name:und_x_variant":[
        "Bhair\u016bnsar",
        "Bharusar",
        "Bhajr\u016bnsar"
    ],
    "wof:name":"Bhajrunsar",
    "wof:placetype":"locality"
},
  "geometry": {"coordinates":[74.68148000000002,28.38825],"type":"Point"}
}