{
  "type": "Feature",
  "properties": {
    "iso:country":"IN",
    "ks:ks_name":"Paterwa",
    "ks:ks_pop":173,
    "ks:ks_type":"HABITATION",
    "name:eng_x_preferred":[
        "Paterwa"
    ],
    "wof:name":"Paterwa",
    "wof:placetype":"locality",
    "wof:population":173
},
  "geometry": {"coordinates":[81.83488199999999,26.254751],"type":"Point"}
}