{
  "type": "Feature",
  "properties": {
    "iso:country":"IN",
    "ks:ks_name":"Masinita",
    "ks:ks_pop":204,
    "ks:ks_type":"VILLAGE",
    "name:eng_x_preferred":[
        "Masinita"
    ],
    "wof:name":"Masinita",
    "wof:placetype":"locality",
    "wof:population":204
},
  "geometry": {"coordinates":[84.72181500000001,21.485922],"type":"Point"}
}