{
  "type": "Feature",
  "properties": {
    "iso:country":"IN",
    "ks:ks_name":"Bhavewadi",
    "ks:ks_pop":246,
    "ks:ks_type":"HABITATION",
    "name:eng_x_preferred":[
        "Bhavewadi"
    ],
    "wof:name":"Bhavewadi",
    "wof:placetype":"locality",
    "wof:population":246
},
  "geometry": {"coordinates":[74.210472,16.040117],"type":"Point"}
}