{
  "type": "Feature",
  "properties": {
    "iso:country":"IN",
    "ks:ks_alt_nam":"SHIL PARA",
    "ks:ks_name":"Shil Para",
    "ks:ks_pop":212,
    "ks:ks_type":"HABITATION",
    "name:eng_x_preferred":[
        "Shil Para"
    ],
    "wof:name":"Shil Para",
    "wof:placetype":"locality",
    "wof:population":212
},
  "geometry": {"coordinates":[91.253879,23.668317],"type":"Point"}
}