{
  "type": "Feature",
  "properties": {
    "iso:country":"IN",
    "ks:ks_name":"Karkudi",
    "ks:ks_pop":90,
    "ks:ks_type":"VILLAGE",
    "name:eng_x_preferred":[
        "Karkudi"
    ],
    "wof:name":"Karkudi",
    "wof:placetype":"locality",
    "wof:population":90
},
  "geometry": {"coordinates":[83.643539,20.048818],"type":"Point"}
}