{
  "type": "Feature",
  "properties": {
    "iso:country":"IN",
    "ks:ks_name":"Bargaon Suba2",
    "ks:ks_pop":510,
    "ks:ks_type":"HABITATION",
    "ks:ks_uagg_main":0,
    "name:eng_x_preferred":[
        "Bargaon Suba2"
    ],
    "wof:name":"Bargaon Suba2",
    "wof:placetype":"neighbourhood",
    "wof:population":510
},
  "geometry": {"coordinates":[91.73675299999999,26.40435],"type":"Point"}
}