{
  "type": "Feature",
  "properties": {
    "gn:admin1_code":"17.0",
    "gn:admin2_code":"273.0",
    "gn:asciiname":"Kandihang",
    "gn:country_code":"IN",
    "gn:dem":550,
    "gn:feature_class":"P",
    "gn:feature_code":"PPL",
    "gn:name":"Kandihang",
    "gn:population":0,
    "gn:timezone":"Asia/Kolkata",
    "iso:country":"IN",
    "wof:name":"Kandihang",
    "wof:placetype":"locality"
},
  "geometry": {"coordinates":[93.32002,25.02985],"type":"Point"}
}