{
  "type": "Feature",
  "properties": {
    "gn:admin1_code":"19.0",
    "gn:admin2_code":"574.0",
    "gn:asciiname":"Belavadi",
    "gn:country_code":"IN",
    "gn:dem":863,
    "gn:feature_class":"P",
    "gn:feature_code":"PPL",
    "gn:name":"Belav\u0101di",
    "gn:population":0,
    "gn:timezone":"Asia/Kolkata",
    "iso:country":"IN",
    "name:bar_x_preferred":[
        "Belavadi"
    ],
    "name:deu_x_preferred":[
        "Belavadi"
    ],
    "name:kan_x_preferred":[
        "\u0cac\u0cc6\u0cb3\u0cb5\u0cbe\u0ca1\u0cbf"
    ],
    "name:tur_x_preferred":[
        "Belavadi"
    ],
    "name:vie_x_preferred":[
        "Belavadi"
    ],
    "wof:name":"Belavadi",
    "wof:placetype":"locality"
},
  "geometry": {"coordinates":[76.14359,12.66662],"type":"Point"}
}