{
  "type": "Feature",
  "properties": {
    "iso:country":"IN",
    "ks:ks_name":"South Samuthiram",
    "ks:ks_pop":362,
    "ks:ks_type":"HABITATION",
    "name:eng_x_preferred":[
        "South Samuthiram"
    ],
    "wof:name":"South Samuthiram",
    "wof:placetype":"locality",
    "wof:population":362
},
  "geometry": {"coordinates":[78.735698,9.615382],"type":"Point"}
}