{
  "type": "Feature",
  "properties": {
    "iso:country":"IN",
    "ks:ks_name":"Mangode",
    "ks:ks_pop":1808,
    "ks:ks_type":"HABITATION",
    "name:eng_x_preferred":[
        "Mangode"
    ],
    "wof:name":"Mangode",
    "wof:placetype":"locality",
    "wof:population":1808
},
  "geometry": {"coordinates":[76.485885,10.965348],"type":"Point"}
}