{
  "type": "Feature",
  "properties": {
    "iso:country":"IN",
    "ks:ks_name":"Amjhar",
    "ks:ks_pop":761,
    "ks:ks_type":"VILLAGE",
    "name:eng_x_preferred":[
        "Amjhar"
    ],
    "wof:name":"Amjhar",
    "wof:placetype":"locality",
    "wof:population":761
},
  "geometry": {"coordinates":[82.224846,22.937112],"type":"Point"}
}