{
  "type": "Feature",
  "properties": {
    "iso:country":"IN",
    "ks:ks_name":"Managobindapur",
    "ks:ks_pop":0,
    "ks:ks_type":"VILLAGE",
    "name:eng_x_preferred":[
        "Managobindapur"
    ],
    "wof:name":"Managobindapur",
    "wof:placetype":"locality",
    "wof:population":0
},
  "geometry": {"coordinates":[85.72762400000001,20.27649],"type":"Point"}
}