{
  "type": "Feature",
  "properties": {
    "iso:country":"IN",
    "ks:ks_name":"Salinaputtuga",
    "ks:ks_pop":625,
    "ks:ks_type":"HABITATION",
    "name:eng_x_preferred":[
        "Salinaputtuga"
    ],
    "wof:name":"Salinaputtuga",
    "wof:placetype":"locality",
    "wof:population":625
},
  "geometry": {"coordinates":[84.617582,18.991678],"type":"Point"}
}