{
  "type": "Feature",
  "properties": {
    "gn:admin1_code":"35",
    "gn:admin2_code":"435.0",
    "gn:asciiname":"Bhagwatpura",
    "gn:country_code":"IN",
    "gn:dem":498,
    "gn:feature_class":"P",
    "gn:feature_code":"PPL",
    "gn:name":"Bhagwatpura",
    "gn:population":0,
    "gn:timezone":"Asia/Kolkata",
    "iso:country":"IN",
    "wof:name":"Bhagwatpura",
    "wof:placetype":"locality"
},
  "geometry": {"coordinates":[76.08635,23.52724],"type":"Point"}
}