{
  "type": "Feature",
  "properties": {
    "gn:admin1_code":"24",
    "gn:admin2_code":"120.0",
    "gn:asciiname":"Titria",
    "gn:country_code":"IN",
    "gn:dem":317,
    "gn:feature_class":"P",
    "gn:feature_code":"PPL",
    "gn:name":"T\u012btria",
    "gn:population":0,
    "gn:timezone":"Asia/Kolkata",
    "iso:country":"IN",
    "wof:name":"Titria",
    "wof:placetype":"locality"
},
  "geometry": {"coordinates":[75.37454,25.98552],"type":"Point"}
}