{
  "type": "Feature",
  "properties": {
    "iso:country":"IN",
    "ks:ks_name":"Dhaneshwari",
    "ks:ks_pop":471,
    "ks:ks_type":"VILLAGE",
    "ks:ks_uagg_main":0,
    "name:eng_x_preferred":[
        "Dhaneshwari"
    ],
    "wof:name":"Dhaneshwari",
    "wof:placetype":"neighbourhood",
    "wof:population":471
},
  "geometry": {"coordinates":[87.66265799999999,21.791155],"type":"Point"}
}