{
  "type": "Feature",
  "properties": {
    "iso:country":"IN",
    "ks:ks_name":"Perunavalur",
    "ks:ks_pop":574,
    "ks:ks_type":"HABITATION",
    "name:eng_x_preferred":[
        "Perunavalur"
    ],
    "wof:name":"Perunavalur",
    "wof:placetype":"locality",
    "wof:population":574
},
  "geometry": {"coordinates":[78.991748,10.09862],"type":"Point"}
}