{
  "type": "Feature",
  "properties": {
    "iso:country":"IN",
    "ks:ks_name":"Khaliapali",
    "ks:ks_pop":234,
    "ks:ks_type":"VILLAGE",
    "name:eng_x_preferred":[
        "Khaliapali"
    ],
    "wof:name":"Khaliapali",
    "wof:placetype":"locality",
    "wof:population":234
},
  "geometry": {"coordinates":[83.53341500000001,20.951508],"type":"Point"}
}