{
  "type": "Feature",
  "properties": {
    "iso:country":"IN",
    "ks:ks_name":"Kendubani Chhota",
    "ks:ks_pop":98,
    "ks:ks_type":"HABITATION",
    "name:eng_x_preferred":[
        "Kendubani Chhota"
    ],
    "wof:name":"Kendubani Chhota",
    "wof:placetype":"locality",
    "wof:population":98
},
  "geometry": {"coordinates":[87.042663,21.988021],"type":"Point"}
}