{
  "type": "Feature",
  "properties": {
    "iso:country":"IN",
    "ks:ks_alt_nam":"MOREWASTI",
    "ks:ks_name":"Morewasti",
    "ks:ks_pop":225,
    "ks:ks_type":"HABITATION",
    "name:eng_x_preferred":[
        "Morewasti"
    ],
    "wof:name":"Morewasti",
    "wof:placetype":"locality",
    "wof:population":225
},
  "geometry": {"coordinates":[74.914213,17.572827],"type":"Point"}
}