{
  "type": "Feature",
  "properties": {
    "iso:country":"IN",
    "ks:ks_alt_nam":"TOTAI GOCHH",
    "ks:ks_name":"Totai Gochh",
    "ks:ks_pop":571,
    "ks:ks_type":"HABITATION",
    "name:eng_x_preferred":[
        "Totai Gochh"
    ],
    "wof:name":"Totai Gochh",
    "wof:placetype":"locality",
    "wof:population":571
},
  "geometry": {"coordinates":[88.518377,26.566643],"type":"Point"}
}