{
  "type": "Feature",
  "properties": {
    "iso:country":"IN",
    "ks:ks_name":"Ojhauli",
    "ks:ks_type":"VILLAGE",
    "name:eng_x_preferred":[
        "Ojhauli"
    ],
    "wof:name":"Ojhauli",
    "wof:placetype":"locality"
},
  "geometry": {"coordinates":[83.399764,26.543378],"type":"Point"}
}