{
  "type": "Feature",
  "properties": {
    "gn:admin1_code":"36",
    "gn:admin2_code":"180.0",
    "gn:asciiname":"Amrit",
    "gn:country_code":"IN",
    "gn:dem":118,
    "gn:feature_class":"P",
    "gn:feature_code":"PPL",
    "gn:name":"Amrit",
    "gn:population":0,
    "gn:timezone":"Asia/Kolkata",
    "iso:country":"IN",
    "name:ara_x_preferred":[
        "\u0639\u0645\u0631\u064a\u062a"
    ],
    "name:bul_x_preferred":[
        "\u0410\u043c\u0440\u0438\u0442"
    ],
    "name:cat_x_preferred":[
        "Maratos"
    ],
    "name:deu_x_preferred":[
        "Amrit"
    ],
    "name:fas_x_preferred":[
        "\u0639\u0645\u0631\u06cc\u062a"
    ],
    "name:fra_x_preferred":[
        "Amrit"
    ],
    "name:hun_x_preferred":[
        "Amr\u00edt"
    ],
    "name:ita_x_preferred":[
        "Amrit"
    ],
    "name:lit_x_preferred":[
        "Amritas"
    ],
    "name:nld_x_preferred":[
        "Amrit"
    ],
    "name:pol_x_preferred":[
        "Amrit"
    ],
    "name:swe_x_preferred":[
        "Amrit"
    ],
    "name:ukr_x_preferred":[
        "\u0410\u043c\u0440\u0456\u0442"
    ],
    "name:vie_x_preferred":[
        "Amrit"
    ],
    "wof:name":"Amrit",
    "wof:placetype":"neighbourhood"
},
  "geometry": {"coordinates":[81.39052,27.5229],"type":"Point"}
}