{
  "type": "Feature",
  "properties": {
    "iso:country":"IN",
    "ks:ks_name":"Salagura",
    "ks:ks_pop":58,
    "ks:ks_type":"VILLAGE",
    "name:eng_x_preferred":[
        "Salagura"
    ],
    "wof:name":"Salagura",
    "wof:placetype":"locality",
    "wof:population":58
},
  "geometry": {"coordinates":[84.13288799999999,20.406325],"type":"Point"}
}