{
  "type": "Feature",
  "properties": {
    "iso:country":"IN",
    "ks:ks_name":"Okhalisirod",
    "ks:ks_type":"VILLAGE",
    "name:eng_x_preferred":[
        "Okhalisirod"
    ],
    "wof:name":"Okhalisirod",
    "wof:placetype":"locality"
},
  "geometry": {"coordinates":[79.76818299999999,29.749817],"type":"Point"}
}