{
  "type": "Feature",
  "properties": {
    "gn:admin1_code":"36.0",
    "gn:admin2_code":"159",
    "gn:asciiname":"Madaiyan Kunwapur",
    "gn:country_code":"IN",
    "gn:dem":146,
    "gn:feature_class":"P",
    "gn:feature_code":"PPL",
    "gn:name":"Madaiy\u0101n Kunw\u0101pur",
    "gn:population":0,
    "gn:timezone":"Asia/Kolkata",
    "iso:country":"IN",
    "wof:name":"Madaiyan Kunwapur",
    "wof:placetype":"locality"
},
  "geometry": {"coordinates":[79.62956,27.53861],"type":"Point"}
}