{
  "type": "Feature",
  "properties": {
    "gn:admin1_code":"2",
    "gn:admin2_code":"544.0",
    "gn:asciiname":"Kannurupalem",
    "gn:country_code":"IN",
    "gn:dem":68,
    "gn:feature_class":"P",
    "gn:feature_code":"PPL",
    "gn:name":"Kann\u016brup\u0101lem",
    "gn:population":0,
    "gn:timezone":"Asia/Kolkata",
    "iso:country":"IN",
    "name:und_x_variant":[
        "Kann\u016brup\u0101lem",
        "Iswarapalletsavuduv\u0101da"
    ],
    "wof:name":"Kannurupalem",
    "wof:placetype":"locality"
},
  "geometry": {"coordinates":[82.8198,17.63385],"type":"Point"}
}