{
  "type": "Feature",
  "properties": {
    "iso:country":"IN",
    "ks:ks_name":"Bhanbhawadi",
    "ks:ks_pop":29,
    "ks:ks_type":"HABITATION",
    "name:eng_x_preferred":[
        "Bhanbhawadi"
    ],
    "wof:name":"Bhanbhawadi",
    "wof:placetype":"locality",
    "wof:population":29
},
  "geometry": {"coordinates":[74.20263300000001,16.18155],"type":"Point"}
}