{
  "type": "Feature",
  "properties": {
    "gn:admin1_code":"36",
    "gn:admin2_code":"155.0",
    "gn:asciiname":"Pawayan",
    "gn:country_code":"IN",
    "gn:dem":135,
    "gn:feature_class":"P",
    "gn:feature_code":"PPL",
    "gn:name":"Paway\u0101n",
    "gn:population":0,
    "gn:timezone":"Asia/Kolkata",
    "iso:country":"IN",
    "name:cat_x_preferred":[
        "Pawayan"
    ],
    "name:ceb_x_preferred":[
        "Paw\u0101yan"
    ],
    "name:swe_x_preferred":[
        "Paw\u0101yan"
    ],
    "wof:name":"Pawayan",
    "wof:placetype":"locality"
},
  "geometry": {"coordinates":[80.68460999999998,27.08823],"type":"Point"}
}