{
  "type": "Feature",
  "properties": {
    "iso:country":"IN",
    "ks:ks_name":"Digor Fulertal Part II",
    "ks:ks_pop":654,
    "ks:ks_type":"VILLAGE",
    "ks:ks_uagg_main":0,
    "name:eng_x_preferred":[
        "Digor Fulertal Part II"
    ],
    "wof:name":"Digor Fulertal Part II",
    "wof:placetype":"neighbourhood",
    "wof:population":654
},
  "geometry": {"coordinates":[93.030473,24.795889],"type":"Point"}
}