{
  "type": "Feature",
  "properties": {
    "iso:country":"IN",
    "ks:ks_name":"Gudai Dulip",
    "ks:ks_pop":0,
    "ks:ks_type":"VILLAGE",
    "name:eng_x_preferred":[
        "Gudai Dulip"
    ],
    "wof:name":"Gudai Dulip",
    "wof:placetype":"locality",
    "wof:population":0
},
  "geometry": {"coordinates":[79.516836,27.785374],"type":"Point"}
}