{
  "type": "Feature",
  "properties": {
    "gn:admin1_code":"12",
    "gn:admin2_code":"3.0",
    "gn:asciiname":"Pongunagu",
    "gn:country_code":"IN",
    "gn:dem":4594,
    "gn:feature_class":"P",
    "gn:feature_code":"PPL",
    "gn:name":"Pongunagu",
    "gn:population":0,
    "gn:timezone":"Asia/Kolkata",
    "iso:country":"IN",
    "name:und_x_variant":[
        "Pongo Nagu",
        "Pongunagu"
    ],
    "wof:name":"Pongunagu",
    "wof:placetype":"locality"
},
  "geometry": {"coordinates":[77.94789,33.37624],"type":"Point"}
}