{
  "type": "Feature",
  "properties": {
    "iso:country":"IN",
    "ks:ks_name":"Jajar Gunth",
    "ks:ks_pop":60,
    "ks:ks_type":"VILLAGE",
    "name:eng_x_preferred":[
        "Jajar Gunth"
    ],
    "wof:name":"Jajar Gunth",
    "wof:placetype":"locality",
    "wof:population":60
},
  "geometry": {"coordinates":[80.024835,29.867984],"type":"Point"}
}