{
  "type": "Feature",
  "properties": {
    "iso:country":"IN",
    "ks:ks_name":"Danison",
    "ks:ks_pop":302,
    "ks:ks_type":"HABITATION",
    "name:eng_x_preferred":[
        "Danison"
    ],
    "wof:name":"Danison",
    "wof:placetype":"locality",
    "wof:population":302
},
  "geometry": {"coordinates":[82.221664,24.632871],"type":"Point"}
}