{
  "type": "Feature",
  "properties": {
    "gn:admin1_code":"36",
    "gn:admin2_code":"148.0",
    "gn:asciiname":"Paras Rampur",
    "gn:country_code":"IN",
    "gn:dem":155,
    "gn:feature_class":"P",
    "gn:feature_code":"PPL",
    "gn:name":"Paras R\u0101mpur",
    "gn:population":0,
    "gn:timezone":"Asia/Kolkata",
    "iso:country":"IN",
    "name:pan_x_preferred":[
        "\u0a2a\u0a30\u0a38\u0a30\u0a3e\u0a2e\u0a2a\u0a41\u0a30"
    ],
    "wof:name":"Paras Rampur",
    "wof:placetype":"locality"
},
  "geometry": {"coordinates":[78.90066,27.03043],"type":"Point"}
}