{
  "type": "Feature",
  "properties": {
    "iso:country":"IN",
    "ks:ks_name":"Negheriting Grant 215",
    "ks:ks_pop":724,
    "ks:ks_type":"HABITATION",
    "ks:ks_uagg_main":0,
    "name:eng_x_preferred":[
        "Negheriting Grant 215"
    ],
    "wof:name":"Negheriting Grant 215",
    "wof:placetype":"neighbourhood",
    "wof:population":724
},
  "geometry": {"coordinates":[94.007622,26.735642],"type":"Point"}
}