{
  "type": "Feature",
  "properties": {
    "gn:admin1_code":"36",
    "gn:admin2_code":"178.0",
    "gn:asciiname":"Reza Shah Ramzan",
    "gn:country_code":"IN",
    "gn:dem":89,
    "gn:feature_class":"P",
    "gn:feature_code":"PPL",
    "gn:name":"Reza Sh\u0101h Ramz\u0101n",
    "gn:population":0,
    "gn:timezone":"Asia/Kolkata",
    "iso:country":"IN",
    "wof:name":"Reza Shah Ramzan",
    "wof:placetype":"locality"
},
  "geometry": {"coordinates":[82.6174,26.34911],"type":"Point"}
}