{
  "type": "Feature",
  "properties": {
    "iso:country":"IN",
    "ks:ks_name":"Maliwasti",
    "ks:ks_pop":172,
    "ks:ks_type":"HABITATION",
    "ks:ks_uagg_main":0,
    "name:eng_x_preferred":[
        "Maliwasti"
    ],
    "wof:name":"Maliwasti",
    "wof:placetype":"neighbourhood",
    "wof:population":172
},
  "geometry": {"coordinates":[74.42964000000001,18.54912],"type":"Point"}
}