{
  "type": "Feature",
  "properties": {
    "iso:country":"IN",
    "ks:ks_name":"Kathalbari Ghat",
    "ks:ks_pop":2550,
    "ks:ks_type":"HABITATION",
    "name:eng_x_preferred":[
        "Kathalbari Ghat"
    ],
    "wof:name":"Kathalbari Ghat",
    "wof:placetype":"locality",
    "wof:population":2550
},
  "geometry": {"coordinates":[89.781435,26.378367],"type":"Point"}
}