{
  "type": "Feature",
  "properties": {
    "iso:country":"IN",
    "ks:ks_name":"Savvalavaripalle",
    "ks:ks_pop":125,
    "ks:ks_type":"HABITATION",
    "ks:ks_uagg_main":0,
    "name:eng_x_preferred":[
        "Savvalavaripalle"
    ],
    "wof:name":"Savvalavaripalle",
    "wof:placetype":"neighbourhood",
    "wof:population":125
},
  "geometry": {"coordinates":[79.024765,13.699508],"type":"Point"}
}