{
  "type": "Feature",
  "properties": {
    "iso:country":"IN",
    "ks:ks_name":"Jain Punjee",
    "ks:ks_pop":580,
    "ks:ks_type":"HABITATION",
    "name:eng_x_preferred":[
        "Jain Punjee"
    ],
    "wof:name":"Jain Punjee",
    "wof:placetype":"locality",
    "wof:population":580
},
  "geometry": {"coordinates":[92.506013,24.377436],"type":"Point"}
}