{
  "type": "Feature",
  "properties": {
    "iso:country":"IN",
    "ks:ks_name":"Gadeli",
    "ks:ks_pop":26,
    "ks:ks_type":"VILLAGE",
    "name:eng_x_preferred":[
        "Gadeli"
    ],
    "wof:name":"Gadeli",
    "wof:placetype":"locality",
    "wof:population":26
},
  "geometry": {"coordinates":[84.247266,20.333532],"type":"Point"}
}