{
  "type": "Feature",
  "properties": {
    "iso:country":"IN",
    "ks:ks_alt_nam":"S.T.COLONY",
    "ks:ks_name":"S.t.colony",
    "ks:ks_pop":186,
    "ks:ks_type":"HABITATION",
    "ks:ks_uagg_main":0,
    "name:eng_x_preferred":[
        "S.t.colony"
    ],
    "wof:name":"S.t.colony",
    "wof:placetype":"neighbourhood",
    "wof:population":186
},
  "geometry": {"coordinates":[79.375438,14.016273],"type":"Point"}
}