{
  "type": "Feature",
  "properties": {
    "gn:admin1_code":"40.0",
    "gn:admin2_code":"537.0",
    "gn:asciiname":"Bonkoniguda",
    "gn:country_code":"IN",
    "gn:dem":469,
    "gn:feature_class":"P",
    "gn:feature_code":"PPL",
    "gn:name":"Bonkonig\u016bda",
    "gn:population":0,
    "gn:timezone":"Asia/Kolkata",
    "iso:country":"IN",
    "wof:name":"Bonkoniguda",
    "wof:placetype":"locality"
},
  "geometry": {"coordinates":[78.69568000000002,17.43826],"type":"Point"}
}