{
  "type": "Feature",
  "properties": {
    "gn:admin1_code":"35.0",
    "gn:admin2_code":"445.0",
    "gn:asciiname":"Khandaurapur",
    "gn:country_code":"IN",
    "gn:dem":510,
    "gn:feature_class":"P",
    "gn:feature_code":"PPL",
    "gn:name":"Kh\u0101ndaur\u0101pur",
    "gn:population":0,
    "gn:timezone":"Asia/Kolkata",
    "iso:country":"IN",
    "name:und_x_variant":[
        "Kh\u0101ndaur\u0101pur",
        "Bhori"
    ],
    "wof:name":"Khandaurapur",
    "wof:placetype":"locality"
},
  "geometry": {"coordinates":[76.81406,22.94706],"type":"Point"}
}