{
  "type": "Feature",
  "properties": {
    "iso:country":"IN",
    "ks:ks_alt_nam":"SAWALON KA KHERA",
    "ks:ks_name":"Sawalon Ka Khera",
    "ks:ks_pop":209,
    "ks:ks_type":"HABITATION",
    "name:eng_x_preferred":[
        "Sawalon Ka Khera"
    ],
    "wof:name":"Sawalon Ka Khera",
    "wof:placetype":"locality",
    "wof:population":209
},
  "geometry": {"coordinates":[74.057526,25.317883],"type":"Point"}
}