{
  "type": "Feature",
  "properties": {
    "gn:admin1_code":"35.0",
    "gn:admin2_code":"431.0",
    "gn:asciiname":"Gura",
    "gn:country_code":"IN",
    "gn:dem":419,
    "gn:feature_class":"P",
    "gn:feature_code":"PPL",
    "gn:name":"Gura",
    "gn:population":0,
    "gn:timezone":"Asia/Kolkata",
    "iso:country":"IN",
    "name:bel_x_preferred":[
        "\u0413\u0443\u0440\u0430"
    ],
    "name:ceb_x_preferred":[
        "Gura"
    ],
    "name:deu_x_preferred":[
        "Gura"
    ],
    "name:ita_x_preferred":[
        "Gura"
    ],
    "name:lit_x_preferred":[
        "Gura"
    ],
    "name:ron_x_preferred":[
        "Gura"
    ],
    "name:rus_x_preferred":[
        "\u0413\u0443\u0440\u0430"
    ],
    "name:swe_x_preferred":[
        "Gura"
    ],
    "name:szl_x_preferred":[
        "G\u016fra"
    ],
    "name:ukr_x_preferred":[
        "\u0413\u0443\u0440\u0430"
    ],
    "wof:name":"Gura",
    "wof:placetype":"neighbourhood"
},
  "geometry": {"coordinates":[80.56175,23.54862],"type":"Point"}
}