{
  "type": "Feature",
  "properties": {
    "iso:country":"IN",
    "ks:ks_name":"Gavatepada",
    "ks:ks_pop":323,
    "ks:ks_type":"HABITATION",
    "name:eng_x_preferred":[
        "Gavatepada"
    ],
    "wof:name":"Gavatepada",
    "wof:placetype":"locality",
    "wof:population":323
},
  "geometry": {"coordinates":[73.20015600000001,20.031039],"type":"Point"}
}