{
  "type": "Feature",
  "properties": {
    "iso:country":"IN",
    "ks:ks_alt_nam":"BANIAR BARI",
    "ks:ks_name":"Baniar Bari",
    "ks:ks_pop":410,
    "ks:ks_type":"HABITATION",
    "ks:ks_uagg_main":0,
    "name:eng_x_preferred":[
        "Baniar Bari"
    ],
    "wof:name":"Baniar Bari",
    "wof:placetype":"neighbourhood",
    "wof:population":410
},
  "geometry": {"coordinates":[88.555797,26.638809],"type":"Point"}
}