{
  "type": "Feature",
  "properties": {
    "gn:admin1_code":"25.0",
    "gn:admin2_code":"605.0",
    "gn:asciiname":"Thangamalai",
    "gn:country_code":"IN",
    "gn:dem":631,
    "gn:feature_class":"P",
    "gn:feature_code":"PPL",
    "gn:name":"Thangamalai",
    "gn:population":0,
    "gn:timezone":"Asia/Kolkata",
    "iso:country":"IN",
    "ks:ks_name":"Thongumalai",
    "ks:ks_pop":110,
    "ks:ks_type":"HABITATION",
    "name:eng_x_preferred":[
        "Thongumalai"
    ],
    "name:eng_x_variant":[
        "Thangamalai"
    ],
    "wof:name":"Thongumalai",
    "wof:placetype":"locality",
    "wof:population":110
},
  "geometry": {"coordinates":[78.974707,12.720607],"type":"Point"}
}