{
  "type": "Feature",
  "properties": {
    "gn:admin1_code":"25.0",
    "gn:admin2_code":"605.0",
    "gn:asciiname":"Thangamalai",
    "gn:country_code":"IN",
    "gn:dem":631,
    "gn:feature_class":"P",
    "gn:feature_code":"PPL",
    "gn:name":"Thangamalai",
    "gn:population":0,
    "gn:timezone":"Asia/Kolkata",
    "iso:country":"IN",
    "wof:name":"Thangamalai",
    "wof:placetype":"locality"
},
  "geometry": {"coordinates":[78.97346999999998,12.72],"type":"Point"}
}