{
  "type": "Feature",
  "properties": {
    "iso:country":"IN",
    "ks:ks_name":"Nambedu Reserved Forest",
    "ks:ks_type":"VILLAGE",
    "name:eng_x_preferred":[
        "Nambedu Reserved Forest"
    ],
    "wof:name":"Nambedu Reserved Forest",
    "wof:placetype":"locality"
},
  "geometry": {"coordinates":[79.462074,12.578737],"type":"Point"}
}