{
  "type": "Feature",
  "properties": {
    "gn:admin1_code":"11",
    "gn:admin2_code":"24.0",
    "gn:asciiname":"Kothi",
    "gn:country_code":"IN",
    "gn:dem":407,
    "gn:feature_class":"P",
    "gn:feature_code":"PPL",
    "gn:name":"Kothi",
    "gn:population":0,
    "gn:timezone":"Asia/Kolkata",
    "iso:country":"IN",
    "name:ceb_x_preferred":[
        "Kothi"
    ],
    "name:swe_x_preferred":[
        "Kothi"
    ],
    "wof:name":"Kothi",
    "wof:placetype":"locality"
},
  "geometry": {"coordinates":[76.03279999999999,31.9461],"type":"Point"}
}