{
  "type": "Feature",
  "properties": {
    "gn:admin1_code":"2.0",
    "gn:admin2_code":"544.0",
    "gn:asciiname":"Kuiba",
    "gn:country_code":"IN",
    "gn:dem":984,
    "gn:feature_class":"P",
    "gn:feature_code":"PPL",
    "gn:name":"Kuiba",
    "gn:population":0,
    "gn:timezone":"Asia/Kolkata",
    "iso:country":"IN",
    "wof:name":"Kuiba",
    "wof:placetype":"locality"
},
  "geometry": {"coordinates":[82.51959000000002,18.23937],"type":"Point"}
}