{
  "type": "Feature",
  "properties": {
    "gn:admin1_code":"34.0",
    "gn:admin2_code":"217.0",
    "gn:asciiname":"Dumar Narind",
    "gn:country_code":"IN",
    "gn:dem":79,
    "gn:feature_class":"P",
    "gn:feature_code":"PPL",
    "gn:name":"Dumar Narind",
    "gn:population":0,
    "gn:timezone":"Asia/Kolkata",
    "iso:country":"IN",
    "ks:ks_name":"Dumar Narind",
    "ks:ks_pop":2084,
    "ks:ks_type":"VILLAGE",
    "name:eng_x_preferred":[
        "Dumar Narind"
    ],
    "wof:name":"Dumar Narind",
    "wof:placetype":"locality",
    "wof:population":2084
},
  "geometry": {"coordinates":[84.122714,26.473275],"type":"Point"}
}