{
  "type": "Feature",
  "properties": {
    "iso:country":"IN",
    "ks:ks_name":"Aali",
    "ks:ks_pop":2682,
    "ks:ks_type":"HABITATION",
    "name:eng_x_preferred":[
        "Aali"
    ],
    "wof:name":"Aali",
    "wof:placetype":"locality",
    "wof:population":2682
},
  "geometry": {"coordinates":[74.678634,22.216116],"type":"Point"}
}