{
  "type": "Feature",
  "properties": {
    "iso:country":"IN",
    "ks:ks_name":"Kaishettymane",
    "ks:ks_pop":12,
    "ks:ks_type":"HABITATION",
    "name:eng_x_preferred":[
        "Kaishettymane"
    ],
    "wof:name":"Kaishettymane",
    "wof:placetype":"locality",
    "wof:population":12
},
  "geometry": {"coordinates":[74.68481199999999,14.988036],"type":"Point"}
}