{
  "type": "Feature",
  "properties": {
    "iso:country":"IN",
    "ks:ks_name":"Baghanala",
    "ks:ks_pop":1557,
    "ks:ks_type":"VILLAGE",
    "name:eng_x_preferred":[
        "Baghanala"
    ],
    "wof:name":"Baghanala",
    "wof:placetype":"locality",
    "wof:population":1557
},
  "geometry": {"coordinates":[87.740568,22.733541],"type":"Point"}
}