{
  "type": "Feature",
  "properties": {
    "iso:country":"IN",
    "ks:ks_name":"Sekhpura",
    "ks:ks_pop":2448,
    "ks:ks_type":"VILLAGE",
    "name:eng_x_preferred":[
        "Sekhpura"
    ],
    "wof:name":"Sekhpura",
    "wof:placetype":"locality",
    "wof:population":2448
},
  "geometry": {"coordinates":[87.901703,25.093219],"type":"Point"}
}