{
  "type": "Feature",
  "properties": {
    "iso:country":"IN",
    "ks:ks_name":"Bardekpar Bodo Suba",
    "ks:ks_pop":284,
    "ks:ks_type":"HABITATION",
    "ks:ks_uagg_main":0,
    "name:eng_x_preferred":[
        "Bardekpar Bodo Suba"
    ],
    "wof:name":"Bardekpar Bodo Suba",
    "wof:placetype":"neighbourhood",
    "wof:population":284
},
  "geometry": {"coordinates":[91.65559500000001,26.321811],"type":"Point"}
}