{
  "type": "Feature",
  "properties": {
    "iso:country":"IN",
    "ks:ks_name":"Mukkadavu West",
    "ks:ks_pop":1159,
    "ks:ks_type":"HABITATION",
    "name:eng_x_preferred":[
        "Mukkadavu West"
    ],
    "wof:name":"Mukkadavu West",
    "wof:placetype":"locality",
    "wof:population":1159
},
  "geometry": {"coordinates":[76.923996,9.039508],"type":"Point"}
}