{
  "type": "Feature",
  "properties": {
    "iso:country":"IN",
    "ks:ks_name":"Kangther Kramsa",
    "ks:ks_pop":42,
    "ks:ks_type":"HABITATION",
    "name:eng_x_preferred":[
        "Kangther Kramsa"
    ],
    "wof:name":"Kangther Kramsa",
    "wof:placetype":"locality",
    "wof:population":42
},
  "geometry": {"coordinates":[93.2979,25.726011],"type":"Point"}
}