{
  "type": "Feature",
  "properties": {
    "gn:admin1_code":"09",
    "gn:admin2_code":"475.0",
    "gn:asciiname":"Thala",
    "gn:country_code":"IN",
    "gn:dem":21,
    "gn:feature_class":"P",
    "gn:feature_code":"PPL",
    "gn:name":"Thala",
    "gn:population":0,
    "gn:timezone":"Asia/Kolkata",
    "iso:country":"IN",
    "wof:name":"Thala",
    "wof:placetype":"locality"
},
  "geometry": {"coordinates":[71.56553000000002,23.10412],"type":"Point"}
}