{
  "type": "Feature",
  "properties": {
    "iso:country":"IN",
    "ks:ks_name":"Kendakod",
    "ks:ks_pop":97,
    "ks:ks_type":"HABITATION",
    "name:eng_x_preferred":[
        "Kendakod"
    ],
    "wof:name":"Kendakod",
    "wof:placetype":"locality",
    "wof:population":97
},
  "geometry": {"coordinates":[74.91066600000001,14.155342],"type":"Point"}
}