{
  "type": "Feature",
  "properties": {
    "iso:country":"IN",
    "ks:ks_name":"Fakali",
    "ks:ks_pop":3021,
    "ks:ks_type":"VILLAGE",
    "name:eng_x_preferred":[
        "Fakali"
    ],
    "wof:name":"Fakali",
    "wof:placetype":"locality",
    "wof:population":3021
},
  "geometry": {"coordinates":[92.624617,26.118574],"type":"Point"}
}