{
  "type": "Feature",
  "properties": {
    "gn:admin1_code":"19",
    "gn:admin2_code":"568.0",
    "gn:asciiname":"Gubigodu",
    "gn:country_code":"IN",
    "gn:dem":645,
    "gn:feature_class":"P",
    "gn:feature_code":"PPL",
    "gn:name":"Gubigodu",
    "gn:population":0,
    "gn:timezone":"Asia/Kolkata",
    "iso:country":"IN",
    "ks:ks_name":"Gubbagodu",
    "ks:ks_pop":53,
    "ks:ks_type":"HABITATION",
    "name:eng_x_preferred":[
        "Gubbagodu"
    ],
    "name:eng_x_variant":[
        "Gubigodu"
    ],
    "wof:name":"Gubbagodu",
    "wof:placetype":"locality",
    "wof:population":53
},
  "geometry": {"coordinates":[74.91838799999999,14.152562],"type":"Point"}
}