{
  "type": "Feature",
  "properties": {
    "iso:country":"IN",
    "ks:ks_alt_nam":"PR Division",
    "ks:ks_name":"Pr Division",
    "ks:ks_pop":1025,
    "ks:ks_type":"HABITATION",
    "name:eng_x_preferred":[
        "Pr Division"
    ],
    "wof:name":"Pr Division",
    "wof:placetype":"locality",
    "wof:population":1025
},
  "geometry": {"coordinates":[77.236412,10.163848],"type":"Point"}
}