{
  "type": "Feature",
  "properties": {
    "gn:admin1_code":"34.0",
    "gn:admin2_code":"234.0",
    "gn:asciiname":"Lohradih",
    "gn:country_code":"IN",
    "gn:dem":122,
    "gn:feature_class":"P",
    "gn:feature_code":"PPL",
    "gn:name":"Lohr\u0101dih",
    "gn:population":0,
    "gn:timezone":"Asia/Kolkata",
    "iso:country":"IN",
    "wof:name":"Lohradih",
    "wof:placetype":"neighbourhood"
},
  "geometry": {"coordinates":[84.05247,24.81002],"type":"Point"}
}