{
  "type": "Feature",
  "properties": {
    "iso:country":"IN",
    "ks:ks_name":"Arazi Chhiruti",
    "ks:ks_pop":0,
    "ks:ks_type":"VILLAGE",
    "name:eng_x_preferred":[
        "Arazi Chhiruti"
    ],
    "wof:name":"Arazi Chhiruti",
    "wof:placetype":"locality",
    "wof:population":0
},
  "geometry": {"coordinates":[88.165316,23.999069],"type":"Point"}
}