{
  "type": "Feature",
  "properties": {
    "gn:admin1_code":"23",
    "gn:admin2_code":"38.0",
    "gn:asciiname":"Shergarh",
    "gn:country_code":"IN",
    "gn:dem":299,
    "gn:feature_class":"P",
    "gn:feature_code":"PPL",
    "gn:name":"Shergarh",
    "gn:population":0,
    "gn:timezone":"Asia/Kolkata",
    "iso:country":"IN",
    "name:ceb_x_preferred":[
        "Shergarh"
    ],
    "name:pol_x_preferred":[
        "Shergarh"
    ],
    "name:swe_x_preferred":[
        "Shergarh"
    ],
    "wof:name":"Shergarh",
    "wof:placetype":"locality"
},
  "geometry": {"coordinates":[75.92950999999999,31.49762],"type":"Point"}
}