{
  "type": "Feature",
  "properties": {
    "iso:country":"IN",
    "ks:ks_name":"Bahadarpur",
    "ks:ks_pop":2230,
    "ks:ks_type":"HABITATION",
    "name:eng_x_preferred":[
        "Bahadarpur"
    ],
    "wof:name":"Bahadarpur",
    "wof:placetype":"locality",
    "wof:population":2230
},
  "geometry": {"coordinates":[76.72296900000001,26.226834],"type":"Point"}
}