{
  "type": "Feature",
  "properties": {
    "iso:country":"IN",
    "ks:ks_alt_nam":"Lat\u012bfpur Naw\u0101da",
    "ks:ks_name":"Latifpur Nawada",
    "ks:ks_type":"VILLAGE",
    "ks:ks_uagg_main":0,
    "name:eng_x_preferred":[
        "Latifpur Nawada"
    ],
    "name:eng_x_variant":[
        "Lat\u012bfpur Naw\u0101da"
    ],
    "wof:name":"Latifpur Nawada",
    "wof:placetype":"neighbourhood"
},
  "geometry": {"coordinates":[77.252059,28.793842],"type":"Point"}
}