{
  "type": "Feature",
  "properties": {
    "iso:country":"IN",
    "ks:ks_name":"Gopalganja",
    "ks:ks_pop":858,
    "ks:ks_type":"VILLAGE",
    "name:eng_x_preferred":[
        "Gopalganja"
    ],
    "wof:name":"Gopalganja",
    "wof:placetype":"locality",
    "wof:population":858
},
  "geometry": {"coordinates":[87.52985700000001,22.950285],"type":"Point"}
}