{
  "type": "Feature",
  "properties": {
    "iso:country":"IN",
    "ks:ks_name":"Chdeigam",
    "ks:ks_pop":70,
    "ks:ks_type":"HABITATION",
    "name:eng_x_preferred":[
        "Chdeigam"
    ],
    "wof:name":"Chdeigam",
    "wof:placetype":"locality",
    "wof:population":70
},
  "geometry": {"coordinates":[84.516869,19.06249],"type":"Point"}
}